{
  "type": "Feature",
  "properties": {
    "iso:country":"US",
    "sg:address":"303 State Rte 42",
    "sg:city":"Byron",
    "sg:classifiers":[
        {
            "category":"Building & Trades",
            "subcategory":"Landscaping Services",
            "type":"Services"
        }
    ],
    "sg:phone":"+1 478 256 3487",
    "sg:postcode":"31008",
    "sg:province":"GA",
    "sg:tags":[
        "landscape",
        "contractor"
    ],
    "wof:name":"Pro Design Irrigation",
    "wof:placetype":"venue"
},
  "geometry": {"coordinates":[-83.762333,32.652581],"type":"Point"}
}