{
  "type": "Feature",
  "properties": {
    "addr:full":"1440 Boulevard SE Atlanta GA 30315",
    "addr:housenumber":"1440",
    "addr:postcode":"30315",
    "addr:street":"Boulevard Se",
    "iso:country":"US",
    "sg:address":"1440 Boulevard SE",
    "sg:city":"Atlanta",
    "sg:classifiers":[
        {
            "category":"Government",
            "subcategory":"Office",
            "type":"Public Place"
        }
    ],
    "sg:phone":"+1 404 624 0750",
    "sg:postcode":"30315",
    "sg:province":"GA",
    "sg:tags":[
        "township",
        "government-city",
        "village"
    ],
    "wof:name":"Atlanta City Government",
    "wof:placetype":"venue"
},
  "geometry": {"coordinates":[-84.368584,33.714642],"type":"Point"}
}