{
  "type": "Feature",
  "properties": {
    "iso:country":"US",
    "sg:address":"2818 Washington Rd",
    "sg:city":"Augusta",
    "sg:classifiers":[
        {
            "category":"Autos & Motor Vehicles",
            "subcategory":"Auto Supplies",
            "type":"Retail Goods"
        }
    ],
    "sg:phone":"+1 706 733 3132",
    "sg:postcode":"30909",
    "sg:province":"GA",
    "sg:tags":[
        "tire"
    ],
    "wof:name":"Tire Kingdom",
    "wof:placetype":"venue"
},
  "geometry": {"coordinates":[-82.033061,33.510572],"type":"Point"}
}