{
  "type": "Feature",
  "properties": {
    "iso:country":"US",
    "sg:address":"3934 Loring Ln",
    "sg:city":"Duluth",
    "sg:classifiers":[
        {
            "category":"Utilities",
            "subcategory":"Telephone",
            "type":"Services"
        }
    ],
    "sg:phone":"+1 770 622 1435",
    "sg:postcode":"30096",
    "sg:province":"GA",
    "sg:tags":[
        "communications"
    ],
    "wof:name":"Diamond Slate",
    "wof:placetype":"venue"
},
  "geometry": {"coordinates":[-84.160453,34.00851],"type":"Point"}
}