{
  "type": "Feature",
  "properties": {
    "addr:full":"67 Kinnimer St Cleveland GA 30528",
    "addr:housenumber":"67",
    "addr:postcode":"30528",
    "addr:street":"Kinnimer St",
    "iso:country":"US",
    "sg:address":"67 Kinnimer St",
    "sg:city":"Cleveland",
    "sg:classifiers":[
        {
            "category":"Professional",
            "subcategory":"Accounting & Tax Preparation",
            "type":"Services"
        }
    ],
    "sg:phone":"+1 706 865 1095",
    "sg:postcode":"30528",
    "sg:province":"GA",
    "sg:tags":[
        "accountant"
    ],
    "wof:name":"Thomas & Owen",
    "wof:placetype":"venue"
},
  "geometry": {"coordinates":[-83.769689,34.605246],"type":"Point"}
}