{
  "type": "Feature",
  "properties": {
    "iso:country":"US",
    "sg:address":"4920 Roswell Rd",
    "sg:city":"Atlanta",
    "sg:classifiers":[
        {
            "category":"Health Services",
            "subcategory":"Optometrist",
            "type":"Services"
        },
        {
            "category":"Shopping",
            "subcategory":"Optician",
            "type":"Retail Goods"
        }
    ],
    "sg:phone":"+1 404 252 1702",
    "sg:postcode":"30342",
    "sg:province":"GA",
    "sg:tags":[
        "eyewear"
    ],
    "sg:website":"www.eye1stvision.com",
    "wof:name":"Eye 1st Vision Center",
    "wof:placetype":"venue"
},
  "geometry": {"coordinates":[-84.38154900000001,33.888651],"type":"Point"}
}