{
  "type": "Feature",
  "properties": {
    "iso:country":"US",
    "sg:address":"4404 Township Dr",
    "sg:city":"Oakwood",
    "sg:classifiers":[
        {
            "category":"Real Estate",
            "subcategory":"Real Estate Operator",
            "type":"Services"
        }
    ],
    "sg:phone":"+1 770 287 1770",
    "sg:postcode":"30566",
    "sg:province":"GA",
    "sg:tags":[
        "apartment"
    ],
    "wof:name":"General Property Management",
    "wof:placetype":"venue"
},
  "geometry": {"coordinates":[-83.89565899999999,34.224494],"type":"Point"}
}