{
  "type": "Feature",
  "properties": {
    "iso:country":"US",
    "sg:address":"4426 Luxembourg Dr",
    "sg:city":"Decatur",
    "sg:classifiers":[
        {
            "category":"Banks & Credit Unions",
            "subcategory":"Investment Brokerage",
            "type":"Services"
        }
    ],
    "sg:phone":"+1 770 987 3080",
    "sg:postcode":"30034",
    "sg:province":"GA",
    "sg:tags":[
        "advisory"
    ],
    "wof:name":"Twin Investment Group",
    "wof:placetype":"venue"
},
  "geometry": {"coordinates":[-84.209219,33.690939],"type":"Point"}
}