{
  "type": "Feature",
  "properties": {
    "addr:full":"5680 Rolling Acres Ln Cumming GA 30028",
    "addr:housenumber":"5680",
    "addr:postcode":"30028",
    "addr:street":"Rolling Acres Ln",
    "iso:country":"US",
    "sg:address":"5680 Rolling Acres Ln",
    "sg:city":"Cumming",
    "sg:classifiers":[
        {
            "category":"Professional",
            "subcategory":"Business Services",
            "type":"Services"
        }
    ],
    "sg:phone":"+1 770 888 2011",
    "sg:postcode":"30028",
    "sg:province":"GA",
    "wof:name":"Alucid Design LLC",
    "wof:placetype":"venue"
},
  "geometry": {"coordinates":[-84.091044,34.308827],"type":"Point"}
}