{
  "type": "Feature",
  "properties": {
    "addr:full":"4155 Arcadia Industrial Cir SW Lilburn GA 30047",
    "addr:housenumber":"4155",
    "addr:postcode":"30047",
    "addr:street":"Arcadia Industrial Cir Sw",
    "iso:country":"US",
    "sg:address":"4155 Arcadia Industrial Cir SW",
    "sg:city":"Lilburn",
    "sg:classifiers":[
        {
            "category":"Building & Trades",
            "subcategory":"Plumbing",
            "type":"Services"
        }
    ],
    "sg:phone":"+1 678 924 1656",
    "sg:postcode":"30047",
    "sg:province":"GA",
    "sg:tags":[
        "conditioning",
        "air",
        "system",
        "contractor"
    ],
    "wof:name":"Maher's Heating & AC",
    "wof:placetype":"venue"
},
  "geometry": {"coordinates":[-84.110591,33.894394],"type":"Point"}
}