{
  "type": "Feature",
  "properties": {
    "addr:full":"1309 Walter St Waycross GA 31501",
    "addr:housenumber":"1309",
    "addr:postcode":"31501",
    "addr:street":"Walter St",
    "iso:country":"US",
    "sg:address":"1309 Walter St",
    "sg:city":"Waycross",
    "sg:classifiers":[
        {
            "category":"Professional",
            "type":"Services"
        }
    ],
    "sg:phone":"+1 912 283 2298",
    "sg:postcode":"31501",
    "sg:province":"GA",
    "wof:name":"Ruth McGahee",
    "wof:placetype":"venue"
},
  "geometry": {"coordinates":[-82.35985599999999,31.231581],"type":"Point"}
}