{
  "type": "Feature",
  "properties": {
    "addr:full":"105 Laurian Way NW Atlanta GA 30328",
    "addr:housenumber":"105",
    "addr:postcode":"30328",
    "addr:street":"Laurian Way Nw",
    "iso:country":"US",
    "sg:address":"105 Laurian Way NW",
    "sg:city":"Atlanta",
    "sg:classifiers":[
        {
            "category":"Professional",
            "type":"Services"
        }
    ],
    "sg:phone":"+1 404 250 0500",
    "sg:postcode":"30328",
    "sg:province":"GA",
    "sg:tags":[
        "establishment"
    ],
    "wof:name":"Innovation Network Inc",
    "wof:placetype":"venue"
},
  "geometry": {"coordinates":[-84.396929,33.938381],"type":"Point"}
}