{
  "type": "Feature",
  "properties": {
    "iso:country":"US",
    "sg:address":"565 Shallowford Rd NW",
    "sg:city":"Gainesville",
    "sg:classifiers":[
        {
            "category":"Home & Garden",
            "subcategory":"Home Furnishings",
            "type":"Retail Goods"
        },
        {
            "category":"Shopping",
            "type":"Retail Goods"
        }
    ],
    "sg:phone":"+1 770 532 3625",
    "sg:postcode":"30504",
    "sg:province":"GA",
    "sg:tags":[
        "picture",
        "repair",
        "frame",
        "merchandise",
        "framing",
        "se"
    ],
    "wof:name":"Frame-Tastic",
    "wof:placetype":"venue"
},
  "geometry": {"coordinates":[-83.84436700000001,34.290129],"type":"Point"}
}