{
  "type": "Feature",
  "properties": {
    "iso:country":"US",
    "sg:address":"2861 E Point St",
    "sg:city":"East Point",
    "sg:classifiers":[
        {
            "category":"Professional",
            "subcategory":"Accounting & Tax Preparation",
            "type":"Services"
        }
    ],
    "sg:phone":"+1 404 766 6552",
    "sg:postcode":"30344",
    "sg:province":"GA",
    "sg:tags":[
        "return",
        "filing"
    ],
    "wof:name":"GNP Accounting",
    "wof:placetype":"venue"
},
  "geometry": {"coordinates":[-84.44147100000001,33.681827],"type":"Point"}
}