{
  "type": "Feature",
  "properties": {
    "iso:country":"US",
    "sg:address":"2456 Golden Camp Rd",
    "sg:city":"Augusta",
    "sg:classifiers":[
        {
            "category":"Social Services",
            "subcategory":"Child Care",
            "type":"Services"
        }
    ],
    "sg:phone":"+1 706 771 1323",
    "sg:postcode":"30906",
    "sg:province":"GA",
    "sg:tags":[
        "day"
    ],
    "wof:name":"Bell Terrance Geogia Pre K",
    "wof:placetype":"venue"
},
  "geometry": {"coordinates":[-82.050363,33.431171],"type":"Point"}
}