{
  "type": "Feature",
  "properties": {
    "iso:country":"US",
    "sg:address":"5500 Abercorn St",
    "sg:city":"Savannah",
    "sg:classifiers":[
        {
            "category":"Restaurant",
            "type":"Food & Drink"
        }
    ],
    "sg:phone":"+1 912 353 9589",
    "sg:postcode":"31405",
    "sg:province":"GA",
    "sg:tags":[
        "eating"
    ],
    "wof:name":"S&S Take Out Shop",
    "wof:placetype":"venue"
},
  "geometry": {"coordinates":[-81.10976599999999,32.023823],"type":"Point"}
}