{
  "type": "Feature",
  "properties": {
    "addr:full":"2000 E Broad Ave Albany GA 31705",
    "addr:housenumber":"2000",
    "addr:postcode":"31705",
    "addr:street":"E Broad Ave",
    "iso:country":"US",
    "sg:address":"2000 E Broad Ave",
    "sg:city":"Albany",
    "sg:classifiers":[
        {
            "category":"Real Estate",
            "subcategory":"Real Estate Operator",
            "type":"Services"
        }
    ],
    "sg:phone":"+1 229 888 5605",
    "sg:postcode":"31705",
    "sg:province":"GA",
    "sg:tags":[
        "mobile",
        "home",
        "site"
    ],
    "wof:name":"Peters Court",
    "wof:placetype":"venue"
},
  "geometry": {"coordinates":[-84.09997199999999,31.575049],"type":"Point"}
}