{
  "type": "Feature",
  "properties": {
    "addr:full":"5365 Crow Rd Cumming GA 30041",
    "addr:housenumber":"5365",
    "addr:postcode":"30041",
    "addr:street":"Crow Rd",
    "iso:country":"US",
    "sg:address":"5365 Crow Rd",
    "sg:city":"Cumming",
    "sg:classifiers":[
        {
            "category":"Home & Garden",
            "subcategory":"Garden Supply",
            "type":"Retail Goods"
        },
        {
            "category":"Building & Trades",
            "subcategory":"Landscaping Services",
            "type":"Services"
        }
    ],
    "sg:phone":"+1 770 886 9700",
    "sg:postcode":"30041",
    "sg:province":"GA",
    "sg:tags":[
        "sprinkler",
        "landscape"
    ],
    "wof:name":"M & J Sprinklers",
    "wof:placetype":"venue"
},
  "geometry": {"coordinates":[-84.03206299999999,34.267696],"type":"Point"}
}