{
  "type": "Feature",
  "properties": {
    "iso:country":"US",
    "sg:address":"4494 Acworth Industrial Dr NW",
    "sg:city":"Acworth",
    "sg:classifiers":[
        {
            "category":"Retail",
            "subcategory":"Auto Repair",
            "type":"Services"
        }
    ],
    "sg:phone":"+1 770 443 7494",
    "sg:postcode":"30101",
    "sg:province":"GA",
    "sg:tags":[
        "general"
    ],
    "wof:name":"Southeastern Turbo",
    "wof:placetype":"venue"
},
  "geometry": {"coordinates":[-84.660905,34.0601],"type":"Point"}
}