{
  "type": "Feature",
  "properties": {
    "iso:country":"US",
    "sg:address":"91 Avery Dr NE",
    "sg:city":"Atlanta",
    "sg:classifiers":[
        {
            "category":"Real Estate",
            "subcategory":"Real Estate Agent",
            "type":"Services"
        }
    ],
    "sg:phone":"+1 404 892 1068",
    "sg:postcode":"30309",
    "sg:province":"GA",
    "wof:name":"Ogunquit Association",
    "wof:placetype":"venue"
},
  "geometry": {"coordinates":[-84.374375,33.796514],"type":"Point"}
}