{
  "type": "Feature",
  "properties": {
    "addr:full":"4562 State Rte 155 N Stockbridge GA 30281",
    "addr:housenumber":"4562",
    "addr:postcode":"30281",
    "addr:street":"State Rte 155 N",
    "iso:country":"US",
    "sg:address":"4562 State Rte 155 N",
    "sg:city":"Stockbridge",
    "sg:classifiers":[
        {
            "category":"Professional",
            "type":"Services"
        }
    ],
    "sg:phone":"+1 770 507 4431",
    "sg:postcode":"30281",
    "sg:province":"GA",
    "wof:name":"R&A Family Ltd Partnershi",
    "wof:placetype":"venue"
},
  "geometry": {"coordinates":[-84.147184,33.573644],"type":"Point"}
}