{
  "type": "Feature",
  "properties": {
    "iso:country":"US",
    "sg:address":"2878 Meadowview Dr SE",
    "sg:city":"Atlanta",
    "sg:classifiers":[
        {
            "category":"Shopping",
            "subcategory":"Discount & Variety Stores",
            "type":"Retail Goods"
        }
    ],
    "sg:phone":"+1 404 241 7940",
    "sg:postcode":"30316",
    "sg:province":"GA",
    "sg:tags":[
        "merchandise",
        "general"
    ],
    "wof:name":"Treasures From The Attic",
    "wof:placetype":"venue"
},
  "geometry": {"coordinates":[-84.304642,33.701857],"type":"Point"}
}