{
  "type": "Feature",
  "properties": {
    "addr:full":"1505 Lexington Rd Athens GA 30605",
    "addr:housenumber":"1505",
    "addr:postcode":"30605",
    "addr:street":"Lexington Rd",
    "iso:country":"US",
    "sg:address":"1505 Lexington Rd",
    "sg:city":"Athens",
    "sg:classifiers":[
        {
            "category":"Autos & Motor Vehicles",
            "subcategory":"Automobile Sales",
            "type":"Retail Goods"
        }
    ],
    "sg:phone":"+1 706 548 8490",
    "sg:postcode":"30605",
    "sg:province":"GA",
    "sg:tags":[
        "car",
        "used",
        "dealer"
    ],
    "wof:name":"Athens Auto Ranch Inc",
    "wof:placetype":"venue"
},
  "geometry": {"coordinates":[-83.350776,33.946692],"type":"Point"}
}