{
  "type": "Feature",
  "properties": {
    "addr:full":"1780 Pechtre Indstrl Blvd Duluth GA 30097",
    "addr:housenumber":"1780",
    "addr:postcode":"30097",
    "addr:street":"Pechtre Indstrl Blvd",
    "iso:country":"US",
    "sg:address":"1780 Pechtre Indstrl Blvd",
    "sg:city":"Duluth",
    "sg:classifiers":[
        {
            "category":"Social Services",
            "subcategory":"Child Care",
            "type":"Services"
        },
        {
            "category":"Education",
            "subcategory":"Preschool",
            "type":"Public Place"
        },
        {
            "category":"Education",
            "subcategory":"School",
            "type":"Public Place"
        }
    ],
    "sg:phone":"+1 770 622 2900",
    "sg:postcode":"30097",
    "sg:province":"GA",
    "sg:tags":[
        "elementary",
        "day"
    ],
    "wof:name":"Kids R Kids International Inc",
    "wof:placetype":"venue"
},
  "geometry": {"coordinates":[-84.10900100000001,34.029301],"type":"Point"}
}