{
  "type": "Feature",
  "properties": {
    "iso:country":"US",
    "sg:address":"5886 Richard B Russell Scenic Hwy",
    "sg:city":"Blairsville",
    "sg:classifiers":[
        {
            "category":"Retail",
            "subcategory":"Repair Shop",
            "type":"Services"
        }
    ],
    "sg:phone":"+1 706 781 2725",
    "sg:postcode":"30512",
    "sg:province":"GA",
    "sg:tags":[
        "repairing",
        "lawn",
        "mower"
    ],
    "wof:name":"Tony's Small Engine Repair",
    "wof:placetype":"venue"
},
  "geometry": {"coordinates":[-83.879238,34.785133],"type":"Point"}
}