{
  "type": "Feature",
  "properties": {
    "addr:full":"4471 Hwy 53 W Jasper GA 30143",
    "addr:housenumber":"4471",
    "addr:postcode":"30143",
    "addr:street":"Hwy 53 W",
    "iso:country":"US",
    "sg:address":"4471 Hwy 53 W",
    "sg:city":"Jasper",
    "sg:classifiers":[
        {
            "category":"Shopping",
            "subcategory":"Discount & Variety Stores",
            "type":"Retail Goods"
        },
        {
            "category":"Shopping",
            "subcategory":"Used Merchandise",
            "type":"Retail Goods"
        }
    ],
    "sg:phone":"+1 706 253 2960",
    "sg:postcode":"30143",
    "sg:province":"GA",
    "sg:tags":[
        "post",
        "trading"
    ],
    "wof:name":"Hill City Trading Post Inc",
    "wof:placetype":"venue"
},
  "geometry": {"coordinates":[-84.483298,34.467001],"type":"Point"}
}