{
  "type": "Feature",
  "properties": {
    "addr:full":"1428 Canton Rd Marietta GA 30066",
    "addr:housenumber":"1428",
    "addr:postcode":"30066",
    "addr:street":"Canton Rd",
    "iso:country":"US",
    "sg:address":"1428 Canton Rd",
    "sg:city":"Marietta",
    "sg:classifiers":[
        {
            "category":"Retail",
            "subcategory":"Auto Repair",
            "type":"Services"
        }
    ],
    "sg:phone":"+1 770 427 8102",
    "sg:postcode":"30066",
    "sg:province":"GA",
    "wof:name":"Patterson's Transmission Service",
    "wof:placetype":"venue"
},
  "geometry": {"coordinates":[-84.53299699999999,33.986401],"type":"Point"}
}