{
  "type": "Feature",
  "properties": {
    "iso:country":"US",
    "sg:address":"5134 Winding Stream Ct",
    "sg:city":"Stone Mountain",
    "sg:classifiers":[
        {
            "category":"Real Estate",
            "subcategory":"Real Estate Operator",
            "type":"Services"
        }
    ],
    "sg:phone":"+1 770 981 2196",
    "sg:postcode":"30088",
    "sg:province":"GA",
    "sg:tags":[
        "building",
        "nonresidential"
    ],
    "wof:name":"All Sports Properties Inc",
    "wof:placetype":"venue"
},
  "geometry": {"coordinates":[-84.178915,33.732289],"type":"Point"}
}