{
  "type": "Feature",
  "properties": {
    "addr:full":"74 Michael Dr Newnan GA 30263",
    "addr:housenumber":"74",
    "addr:postcode":"30263",
    "addr:street":"Michael Dr",
    "iso:country":"US",
    "sg:address":"74 Michael Dr",
    "sg:city":"Newnan",
    "sg:classifiers":[
        {
            "category":"Building & Trades",
            "subcategory":"Plumbing",
            "type":"Services"
        }
    ],
    "sg:phone":"+1 770 252 2011",
    "sg:postcode":"30263",
    "sg:province":"GA",
    "sg:tags":[
        "contractor"
    ],
    "wof:name":"X Stream Heating & Cooling",
    "wof:placetype":"venue"
},
  "geometry": {"coordinates":[-84.772385,33.35963],"type":"Point"}
}