{
  "type": "Feature",
  "properties": {
    "iso:country":"US",
    "sg:address":"1 Lakemont Dr",
    "sg:city":"Augusta",
    "sg:classifiers":[
        {
            "category":"Building & Trades",
            "subcategory":"Electrical",
            "type":"Services"
        }
    ],
    "sg:phone":"+1 706 733 8560",
    "sg:postcode":"30904",
    "sg:province":"GA",
    "sg:tags":[
        "electrical",
        "contractor"
    ],
    "wof:name":"Hatcher Electric Co",
    "wof:placetype":"venue"
},
  "geometry": {"coordinates":[-82.009692,33.492539],"type":"Point"}
}