{
  "type": "Feature",
  "properties": {
    "iso:country":"US",
    "sg:address":"4819 Ridgewood Creek Dr",
    "sg:city":"Acworth",
    "sg:classifiers":[
        {
            "category":"Wholesale",
            "subcategory":"Farm Supplies",
            "type":"Manufacturing & Wholesale Goods"
        }
    ],
    "sg:phone":"+1 770 928 7022",
    "sg:postcode":"30102",
    "sg:province":"GA",
    "wof:name":"Dow Chemicals Inc",
    "wof:placetype":"venue"
},
  "geometry": {"coordinates":[-84.558284,34.069686],"type":"Point"}
}