{
  "type": "Feature",
  "properties": {
    "iso:country":"US",
    "sg:address":"311 Taylor Rowland Rd",
    "sg:city":"Dexter",
    "sg:classifiers":[
        {
            "category":"Food & Beverages",
            "subcategory":"Fruits & Vegetables",
            "type":"Retail Goods"
        }
    ],
    "sg:phone":"+1 478 875 3668",
    "sg:postcode":"31019",
    "sg:province":"GA",
    "wof:name":"Rowlands Produce",
    "wof:placetype":"venue"
},
  "geometry": {"coordinates":[-83.04412000000001,32.431981],"type":"Point"}
}