{
  "type": "Feature",
  "properties": {
    "iso:country":"US",
    "sg:address":"13109 Largo Dr",
    "sg:city":"Savannah",
    "sg:classifiers":[
        {
            "category":"Communications",
            "subcategory":"Radio Station",
            "type":"Services"
        }
    ],
    "sg:phone":"+1 912 920 9394",
    "sg:postcode":"31419",
    "sg:province":"GA",
    "sg:tags":[
        "broadcast"
    ],
    "wof:name":"Shepherd Radio And T V",
    "wof:placetype":"venue"
},
  "geometry": {"coordinates":[-81.150676,31.96191],"type":"Point"}
}