{
  "type": "Feature",
  "properties": {
    "iso:country":"US",
    "sg:address":"899 Croy Ct",
    "sg:city":"Marietta",
    "sg:classifiers":[
        {
            "category":"Professional",
            "subcategory":"Business Services",
            "type":"Services"
        }
    ],
    "sg:phone":"+1 770 928 2892",
    "sg:postcode":"30066",
    "sg:province":"GA",
    "wof:name":"Interior Therapy",
    "wof:placetype":"venue"
},
  "geometry": {"coordinates":[-84.523382,34.046647],"type":"Point"}
}