{
  "type": "Feature",
  "properties": {
    "iso:country":"US",
    "sg:address":"315 W Solomon St Ste C",
    "sg:city":"Griffin",
    "sg:classifiers":[
        {
            "category":"Personal",
            "subcategory":"Beauty Salon",
            "type":"Services"
        }
    ],
    "sg:phone":"+1 770 227 6060",
    "sg:postcode":"30223",
    "sg:province":"GA",
    "wof:name":"Esquire Barber Shop",
    "wof:placetype":"venue"
},
  "geometry": {"coordinates":[-84.26719900000001,33.248677],"type":"Point"}
}