{
  "type": "Feature",
  "properties": {
    "iso:country":"US",
    "sg:address":"4905 Lower Roswell Rd",
    "sg:city":"Marietta",
    "sg:classifiers":[
        {
            "category":"Personal",
            "subcategory":"Beauty Salon",
            "type":"Services"
        }
    ],
    "sg:phone":"+1 770 971 3359",
    "sg:postcode":"30068",
    "sg:province":"GA",
    "sg:tags":[
        "shop"
    ],
    "wof:name":"Gerald's Hair Shop",
    "wof:placetype":"venue"
},
  "geometry": {"coordinates":[-84.40544199999999,33.966458],"type":"Point"}
}