{
  "type": "Feature",
  "properties": {
    "iso:country":"US",
    "sg:address":"173 Oquinns Pond Rd",
    "sg:city":"Milledgeville",
    "sg:classifiers":[
        {
            "category":"Professional",
            "type":"Services"
        },
        {
            "category":"Manufacturing",
            "subcategory":"Food",
            "type":"Manufacturing & Wholesale Goods"
        }
    ],
    "sg:phone":"+1 478 452 1074",
    "sg:postcode":"31061",
    "sg:province":"GA",
    "sg:tags":[
        "product",
        "manufacturer"
    ],
    "wof:name":"J & A Deer and Hog Processing",
    "wof:placetype":"venue"
},
  "geometry": {"coordinates":[-83.10836500000001,33.044283],"type":"Point"}
}