{
  "type": "Feature",
  "properties": {
    "iso:country":"US",
    "sg:address":"8394 Cherokee Blvd",
    "sg:city":"Douglasville",
    "sg:classifiers":[
        {
            "category":"Retail",
            "subcategory":"Car Wash",
            "type":"Services"
        }
    ],
    "sg:phone":"+1 770 947 6655",
    "sg:postcode":"30134",
    "sg:province":"GA",
    "sg:tags":[
        "carwash"
    ],
    "wof:name":"Masters Touch",
    "wof:placetype":"venue"
},
  "geometry": {"coordinates":[-84.720156,33.751194],"type":"Point"}
}