{
  "type": "Feature",
  "properties": {
    "addr:full":"4536 Washington Rd Evans GA 30809",
    "addr:housenumber":"4536",
    "addr:postcode":"30809",
    "addr:street":"Washington Rd",
    "iso:country":"US",
    "sg:address":"4536 Washington Rd",
    "sg:city":"Evans",
    "sg:classifiers":[
        {
            "category":"Education",
            "subcategory":"Special Training",
            "type":"Public Place"
        },
        {
            "category":"Social Services",
            "subcategory":"Child Care",
            "type":"Services"
        }
    ],
    "sg:phone":"+1 706 498 9423",
    "sg:postcode":"30809",
    "sg:province":"GA",
    "sg:tags":[
        "tutoring"
    ],
    "sg:website":"http://oxfordlearning-evansga.com",
    "wof:name":"Oxford Learning Center",
    "wof:placetype":"venue"
},
  "geometry": {"coordinates":[-82.15078,33.548853],"type":"Point"}
}