{
  "type": "Feature",
  "properties": {
    "iso:country":"US",
    "sg:address":"210 Wheatleigh Ln",
    "sg:city":"Peachtree City",
    "sg:classifiers":[
        {
            "category":"Professional",
            "subcategory":"Business Services",
            "type":"Services"
        }
    ],
    "sg:phone":"+1 770 487 9951",
    "sg:postcode":"30269",
    "sg:province":"GA",
    "wof:name":"Waggoner Home Inspectins Inc",
    "wof:placetype":"venue"
},
  "geometry": {"coordinates":[-84.544994,33.383327],"type":"Point"}
}