{
  "type": "Feature",
  "properties": {
    "iso:country":"US",
    "sg:address":"448 Meadowlands Ct",
    "sg:city":"Augusta",
    "sg:classifiers":[
        {
            "category":"Personal",
            "type":"Services"
        }
    ],
    "sg:phone":"+1 706 650 1171",
    "sg:postcode":"30907",
    "sg:province":"GA",
    "sg:tags":[
        "consultant",
        "program",
        "health",
        "fitness"
    ],
    "wof:name":"Fitness Solutions",
    "wof:placetype":"venue"
},
  "geometry": {"coordinates":[-82.065862,33.530398],"type":"Point"}
}