{
  "type": "Feature",
  "properties": {
    "iso:country":"US",
    "sg:address":"1818 Grove Level Rd",
    "sg:city":"Maysville",
    "sg:classifiers":[
        {
            "category":"Farming",
            "subcategory":"Farm",
            "type":"Manufacturing & Wholesale Goods"
        }
    ],
    "sg:phone":"+1 706 652 3473",
    "sg:postcode":"30558",
    "sg:province":"GA",
    "wof:name":"Steve Stumblin Farms",
    "wof:placetype":"venue"
},
  "geometry": {"coordinates":[-83.519716,34.283282],"type":"Point"}
}