{
  "type": "Feature",
  "properties": {
    "iso:country":"US",
    "sg:address":"238 Canton St",
    "sg:city":"Alpharetta",
    "sg:classifiers":[
        {
            "category":"Education",
            "subcategory":"Library",
            "type":"Public Place"
        }
    ],
    "sg:phone":"+1 770 740 2425",
    "sg:postcode":"30004",
    "sg:province":"GA",
    "wof:name":"Alpharetta Library Fulton County",
    "wof:placetype":"venue"
},
  "geometry": {"coordinates":[-84.296997,34.081799],"type":"Point"}
}