{
  "type": "Feature",
  "properties": {
    "iso:country":"US",
    "sg:address":"305 N Main St",
    "sg:city":"Cedartown",
    "sg:classifiers":[
        {
            "category":"Restaurant",
            "type":"Food & Drink"
        }
    ],
    "sg:menulink":"http://www.allmenus.com/ga/cedartown/132326-subway/menu/",
    "sg:phone":"+1 770 748 9624",
    "sg:postcode":"30125",
    "sg:province":"GA",
    "sg:tags":[
        "american",
        "sandwich"
    ],
    "wof:name":"Subway",
    "wof:placetype":"venue"
},
  "geometry": {"coordinates":[-85.25382500000001,34.017511],"type":"Point"}
}