{
  "type": "Feature",
  "properties": {
    "addr:full":"2050 Mountain Industrial Blvd Tucker GA 30084",
    "addr:housenumber":"2050",
    "addr:postcode":"30084",
    "addr:street":"Mountain Industrial Blvd",
    "iso:country":"US",
    "sg:address":"2050 Mountain Industrial Blvd",
    "sg:city":"Tucker",
    "sg:classifiers":[
        {
            "category":"Professional",
            "subcategory":"Computer Services",
            "type":"Services"
        }
    ],
    "sg:phone":"+1 770 496 4494",
    "sg:postcode":"30084",
    "sg:province":"GA",
    "sg:tags":[
        "consultant",
        "designer"
    ],
    "wof:name":"Technodyne Corp",
    "wof:placetype":"venue"
},
  "geometry": {"coordinates":[-84.200945,33.841834],"type":"Point"}
}