{
  "type": "Feature",
  "properties": {
    "iso:country":"US",
    "sg:address":"20 Dogwood Trl",
    "sg:city":"Ringgold",
    "sg:classifiers":[
        {
            "category":"Health Services",
            "subcategory":"Podiatrist",
            "type":"Services"
        }
    ],
    "sg:phone":"+1 706 965 9171",
    "sg:postcode":"30736",
    "sg:province":"GA",
    "wof:name":"Innovtive Footcare Group I LLC",
    "wof:placetype":"venue"
},
  "geometry": {"coordinates":[-85.136556,34.920243],"type":"Point"}
}