{
  "type": "Feature",
  "properties": {
    "iso:country":"US",
    "sg:address":"2220 Riverbrook Rd",
    "sg:city":"Decatur",
    "sg:classifiers":[
        {
            "category":"Building & Trades",
            "subcategory":"Cleaning & Sanitation",
            "type":"Services"
        }
    ],
    "sg:phone":"+1 770 987 4717",
    "sg:postcode":"30035",
    "sg:province":"GA",
    "sg:tags":[
        "janitorial"
    ],
    "wof:name":"Dba.Sims",
    "wof:placetype":"venue"
},
  "geometry": {"coordinates":[-84.211567,33.720221],"type":"Point"}
}