{
  "type": "Feature",
  "properties": {
    "addr:full":"617 N Wall St Calhoun GA 30701",
    "addr:housenumber":"617",
    "addr:postcode":"30701",
    "addr:street":"N Wall St",
    "iso:country":"US",
    "sg:address":"617 N Wall St",
    "sg:city":"Calhoun",
    "sg:classifiers":[
        {
            "category":"Retail",
            "subcategory":"Repair Shop",
            "type":"Services"
        }
    ],
    "sg:phone":"+1 706 625 5384",
    "sg:postcode":"30701",
    "sg:province":"GA",
    "sg:tags":[
        "appliance"
    ],
    "wof:name":"Scott & Son Appliance Repr Svc",
    "wof:placetype":"venue"
},
  "geometry": {"coordinates":[-84.94897,34.510162],"type":"Point"}
}