{
  "type": "Feature",
  "properties": {
    "iso:country":"US",
    "sg:address":"3400 Around Lenox Rd NE",
    "sg:city":"Atlanta",
    "sg:classifiers":[
        {
            "category":"Shopping",
            "subcategory":"Optical Goods",
            "type":"Retail Goods"
        }
    ],
    "sg:phone":"+1 404 262 2020",
    "sg:postcode":"30326",
    "sg:province":"GA",
    "wof:name":"Lens Crafters",
    "wof:placetype":"venue"
},
  "geometry": {"coordinates":[-84.365548,33.847931],"type":"Point"}
}