{
  "type": "Feature",
  "properties": {
    "addr:full":"5 Perriwinkle Ln Savannah GA 31411",
    "addr:housenumber":"5",
    "addr:postcode":"31411",
    "addr:street":"Perriwinkle Ln",
    "iso:country":"US",
    "sg:address":"5 Perriwinkle Ln",
    "sg:city":"Savannah",
    "sg:classifiers":[
        {
            "category":"Professional",
            "subcategory":"Management & Consulting",
            "type":"Services"
        }
    ],
    "sg:phone":"+1 912 598 9389",
    "sg:postcode":"31411",
    "sg:province":"GA",
    "wof:name":"Parrish Enterprises",
    "wof:placetype":"venue"
},
  "geometry": {"coordinates":[-81.033935,31.949045],"type":"Point"}
}