{
  "type": "Feature",
  "properties": {
    "iso:country":"US",
    "sg:address":"160 Cherokee Pl",
    "sg:city":"Fayetteville",
    "sg:classifiers":[
        {
            "category":"Professional",
            "type":"Services"
        }
    ],
    "sg:phone":"+1 770 461 2703",
    "sg:postcode":"30215",
    "sg:province":"GA",
    "wof:name":"Maude Washington",
    "wof:placetype":"venue"
},
  "geometry": {"coordinates":[-84.46536,33.41469],"type":"Point"}
}