{
  "type": "Feature",
  "properties": {
    "iso:country":"US",
    "sg:address":"4310 Lexington Rd",
    "sg:city":"Athens",
    "sg:classifiers":[
        {
            "category":"Home & Garden",
            "subcategory":"Garden Supply",
            "type":"Retail Goods"
        },
        {
            "category":"Home & Garden",
            "subcategory":"Building Materials",
            "type":"Retail Goods"
        },
        {
            "category":"Government",
            "subcategory":"Office",
            "type":"Public Place"
        }
    ],
    "sg:phone":"+1 706 542 9233",
    "sg:postcode":"30605",
    "sg:province":"GA",
    "sg:tags":[
        "government-state",
        "soil",
        "water",
        "conservation",
        "treatment",
        "waste"
    ],
    "sg:website":"http://www.gaswcc.org",
    "wof:name":"Region 2",
    "wof:placetype":"venue"
},
  "geometry": {"coordinates":[-83.31404999999999,33.934198],"type":"Point"}
}