{
  "type": "Feature",
  "properties": {
    "iso:country":"US",
    "sg:address":"12274 Cumming Hwy",
    "sg:city":"Canton",
    "sg:classifiers":[
        {
            "category":"Professional",
            "subcategory":"Advertising",
            "type":"Services"
        }
    ],
    "sg:phone":"+1 770 888 5279",
    "sg:postcode":"30115",
    "sg:province":"GA",
    "sg:tags":[
        "distributing",
        "sample"
    ],
    "wof:name":"P G Distributing",
    "wof:placetype":"venue"
},
  "geometry": {"coordinates":[-84.29413700000001,34.240893],"type":"Point"}
}