{
  "type": "Feature",
  "properties": {
    "addr:full":"9700 Medlock Bridge Rd Ste 168 Johns Creek GA 30097",
    "addr:housenumber":"9700",
    "addr:postcode":"30097",
    "addr:street":"Medlock Bridge Rd Ste 168;Creek",
    "iso:country":"US",
    "sg:address":"9700 Medlock Bridge Rd Ste 168",
    "sg:city":"Johns Creek",
    "sg:classifiers":[
        {
            "category":"Restaurant",
            "type":"Food & Drink"
        }
    ],
    "sg:phone":"+1 678 514 1111",
    "sg:postcode":"30097",
    "sg:province":"GA",
    "sg:tags":[
        "pizza"
    ],
    "sg:website":"www.romeosnypizza.com",
    "wof:name":"Romeo's New York Pizza",
    "wof:placetype":"venue"
},
  "geometry": {"coordinates":[-84.19244999999999,34.01765],"type":"Point"}
}