{
  "type": "Feature",
  "properties": {
    "iso:country":"US",
    "sg:address":"4186 N Arnold Mill Rd",
    "sg:city":"Woodstock",
    "sg:classifiers":[
        {
            "category":"Wholesale",
            "subcategory":"Medical Equipment & Supplies",
            "type":"Manufacturing & Wholesale Goods"
        }
    ],
    "sg:phone":"+1 770 309 1945",
    "sg:postcode":"30188",
    "sg:province":"GA",
    "sg:tags":[
        "product",
        "distribute",
        "safety",
        "retail"
    ],
    "wof:name":"Georgia Safety Supply LLC",
    "wof:placetype":"venue"
},
  "geometry": {"coordinates":[-84.428417,34.124293],"type":"Point"}
}