{
  "type": "Feature",
  "properties": {
    "addr:full":"275 Pavilion Pkwy Fayetteville GA 30214",
    "addr:housenumber":"275",
    "addr:postcode":"30214",
    "addr:street":"Pavilion Pkwy",
    "iso:country":"US",
    "sg:address":"275 Pavilion Pkwy",
    "sg:city":"Fayetteville",
    "sg:classifiers":[
        {
            "category":"Shopping",
            "subcategory":"Shoes",
            "type":"Retail Goods"
        }
    ],
    "sg:phone":"+1 770 460 8028",
    "sg:postcode":"30214",
    "sg:province":"GA",
    "sg:tags":[
        "store"
    ],
    "sg:website":"www.footlocker.com",
    "wof:name":"Foot Locker Store 25334",
    "wof:placetype":"venue"
},
  "geometry": {"coordinates":[-84.44446000000001,33.479783],"type":"Point"}
}