{
  "type": "Feature",
  "properties": {
    "addr:full":"729 Hwy 515 S Jasper GA 30143",
    "addr:housenumber":"729",
    "addr:postcode":"30143",
    "addr:street":"Hwy 515 S",
    "iso:country":"US",
    "sg:address":"729 Hwy 515 S",
    "sg:city":"Jasper",
    "sg:classifiers":[
        {
            "category":"Retail",
            "subcategory":"Auto Repair",
            "type":"Services"
        }
    ],
    "sg:phone":"+1 706 692 2555",
    "sg:postcode":"30143",
    "sg:province":"GA",
    "sg:tags":[
        "glass",
        "replacement"
    ],
    "wof:name":"Jasper Glass & Mirror Inc",
    "wof:placetype":"venue"
},
  "geometry": {"coordinates":[-84.453019,34.45415],"type":"Point"}
}