{
  "type": "Feature",
  "properties": {
    "iso:country":"US",
    "sg:address":"674 Holcomb Bridge Rd",
    "sg:city":"Roswell",
    "sg:classifiers":[
        {
            "category":"Shopping",
            "subcategory":"Jewelry",
            "type":"Retail Goods"
        }
    ],
    "sg:phone":"+1 770 993 1080",
    "sg:postcode":"30076",
    "sg:province":"GA",
    "sg:tags":[
        "watch",
        "jeweler"
    ],
    "sg:website":"www.brownjewelers.com",
    "wof:name":"Brown & Co Jewelers Inc",
    "wof:placetype":"venue"
},
  "geometry": {"coordinates":[-84.34200300000001,34.034199],"type":"Point"}
}