{
  "type": "Feature",
  "properties": {
    "addr:full":"169 Norcross St Roswell GA 30075",
    "addr:housenumber":"169",
    "addr:postcode":"30075",
    "addr:street":"Norcross St",
    "iso:country":"US",
    "sg:address":"169 Norcross St",
    "sg:city":"Roswell",
    "sg:classifiers":[
        {
            "category":"Professional",
            "subcategory":"Lawyer & Legal Services",
            "type":"Services"
        }
    ],
    "sg:phone":"+1 770 587 4963",
    "sg:postcode":"30075",
    "sg:province":"GA",
    "wof:name":"Childress N G Scott",
    "wof:placetype":"venue"
},
  "geometry": {"coordinates":[-84.356246,34.025432],"type":"Point"}
}