{
  "type": "Feature",
  "properties": {
    "iso:country":"US",
    "sg:address":"8270 Southport Ter",
    "sg:city":"Duluth",
    "sg:classifiers":[
        {
            "category":"Manufacturing",
            "subcategory":"Printing",
            "type":"Manufacturing & Wholesale Goods"
        }
    ],
    "sg:phone":"+1 770 623 1502",
    "sg:postcode":"30097",
    "sg:province":"GA",
    "sg:tags":[
        "newspaper"
    ],
    "wof:name":"Free Press Communications",
    "wof:placetype":"venue"
},
  "geometry": {"coordinates":[-84.14124200000001,34.074071],"type":"Point"}
}