{
  "type": "Feature",
  "properties": {
    "iso:country":"US",
    "sg:address":"2945 Glynn Mill Ct",
    "sg:city":"Snellville",
    "sg:classifiers":[
        {
            "category":"Shopping",
            "subcategory":"Optical Goods",
            "type":"Retail Goods"
        }
    ],
    "sg:phone":"+1 770 979 9103",
    "sg:postcode":"30039",
    "sg:province":"GA",
    "wof:name":"Color Comps Inc",
    "wof:placetype":"venue"
},
  "geometry": {"coordinates":[-84.03374599999999,33.827014],"type":"Point"}
}