{
  "type": "Feature",
  "properties": {
    "iso:country":"US",
    "sg:address":"127 Longview Rd",
    "sg:city":"Stockbridge",
    "sg:classifiers":[
        {
            "category":"Building & Trades",
            "subcategory":"Electrical",
            "type":"Services"
        }
    ],
    "sg:phone":"+1 770 474 4807",
    "sg:postcode":"30281",
    "sg:province":"GA",
    "sg:tags":[
        "electrical",
        "contractor"
    ],
    "wof:name":"An-Trac Services",
    "wof:placetype":"venue"
},
  "geometry": {"coordinates":[-84.21498099999999,33.560383],"type":"Point"}
}