{
  "type": "Feature",
  "properties": {
    "addr:full":"6332 Boat Shoal Ln Flowery Branch GA 30542",
    "addr:housenumber":"6332",
    "addr:postcode":"30542",
    "addr:street":"Boat Shoal Ln",
    "iso:country":"US",
    "sg:address":"6332 Boat Shoal Ln",
    "sg:city":"Flowery Branch",
    "sg:classifiers":[
        {
            "category":"Building & Trades",
            "subcategory":"Cleaning & Sanitation",
            "type":"Services"
        }
    ],
    "sg:phone":"+1 770 965 4880",
    "sg:postcode":"30542",
    "sg:province":"GA",
    "sg:tags":[
        "carpet"
    ],
    "wof:name":"North Georgia Rug Busters Llc",
    "wof:placetype":"venue"
},
  "geometry": {"coordinates":[-83.933539,34.182614],"type":"Point"}
}