{
  "type": "Feature",
  "properties": {
    "iso:country":"US",
    "sg:address":"40 Old Tate Rd",
    "sg:city":"Jasper",
    "sg:classifiers":[
        {
            "category":"Retail",
            "subcategory":"Repair Shop",
            "type":"Services"
        }
    ],
    "sg:phone":"+1 706 253 6979",
    "sg:postcode":"30143",
    "sg:province":"GA",
    "wof:name":"North Georgia T V",
    "wof:placetype":"venue"
},
  "geometry": {"coordinates":[-84.41734099999999,34.464165],"type":"Point"}
}