{
  "type": "Feature",
  "properties": {
    "addr:full":"3272 Christian Springs Dr Lithonia GA 30038",
    "addr:housenumber":"3272",
    "addr:postcode":"30038",
    "addr:street":"Christian Springs Dr",
    "iso:country":"US",
    "sg:address":"3272 Christian Springs Dr",
    "sg:city":"Lithonia",
    "sg:classifiers":[
        {
            "category":"Professional",
            "subcategory":"Business Services",
            "type":"Services"
        }
    ],
    "sg:phone":"+1 770 987 0517",
    "sg:postcode":"30038",
    "sg:province":"GA",
    "wof:name":"Katy Brown",
    "wof:placetype":"venue"
},
  "geometry": {"coordinates":[-84.179388,33.68774],"type":"Point"}
}