{
  "type": "Feature",
  "properties": {
    "iso:country":"US",
    "sg:address":"5665 Hwy 9 N",
    "sg:city":"Alpharetta",
    "sg:classifiers":[
        {
            "category":"Professional",
            "subcategory":"Management & Consulting",
            "type":"Services"
        }
    ],
    "sg:phone":"+1 770 932 1156",
    "sg:postcode":"30004",
    "sg:province":"GA",
    "sg:tags":[
        "industry",
        "telecommunication",
        "for"
    ],
    "wof:name":"Uptime Cmmncations Conslt Incs",
    "wof:placetype":"venue"
},
  "geometry": {"coordinates":[-84.251735,34.144357],"type":"Point"}
}