{
  "type": "Feature",
  "properties": {
    "addr:full":"12186 Highway 92 Woodstock GA 30188",
    "addr:housenumber":"12186",
    "addr:postcode":"30188",
    "addr:street":"Highway 92",
    "iso:country":"US",
    "sg:address":"12186 Highway 92",
    "sg:city":"Woodstock",
    "sg:classifiers":[
        {
            "category":"Professional",
            "subcategory":"Accounting & Tax Preparation",
            "type":"Services"
        },
        {
            "category":"Banks & Credit Unions",
            "subcategory":"Financial Services",
            "type":"Services"
        }
    ],
    "sg:phone":"+1 770 926 8898",
    "sg:postcode":"30188",
    "sg:province":"GA",
    "sg:tags":[
        "return",
        "preparation-business",
        "taxes-consultants",
        "loan",
        "reporting",
        "representative",
        "alternative",
        "bookkeeping"
    ],
    "sg:website":"http://www.hrblock.com",
    "wof:name":"H&R Block",
    "wof:placetype":"venue"
},
  "geometry": {"coordinates":[-84.48304,34.087482],"type":"Point"}
}