{
  "type": "Feature",
  "properties": {
    "addr:full":"115 Walden Way Fayetteville GA 30214",
    "addr:housenumber":"115",
    "addr:postcode":"30214",
    "addr:street":"Walden Way",
    "iso:country":"US",
    "sg:address":"115 Walden Way",
    "sg:city":"Fayetteville",
    "sg:classifiers":[
        {
            "category":"Shopping",
            "subcategory":"Used Merchandise",
            "type":"Retail Goods"
        }
    ],
    "sg:phone":"+1 770 460 9820",
    "sg:postcode":"30214",
    "sg:province":"GA",
    "wof:name":"Recollections",
    "wof:placetype":"venue"
},
  "geometry": {"coordinates":[-84.470585,33.500526],"type":"Point"}
}