{
  "type": "Feature",
  "properties": {
    "iso:country":"US",
    "sg:address":"2900 Chamblee Tucker Rd",
    "sg:city":"Atlanta",
    "sg:classifiers":[
        {
            "category":"Professional",
            "subcategory":"Lawyer & Legal Services",
            "type":"Services"
        }
    ],
    "sg:phone":"+1 404 267 1840",
    "sg:postcode":"30341",
    "sg:province":"GA",
    "wof:name":"Corless & Webster PC",
    "wof:placetype":"venue"
},
  "geometry": {"coordinates":[-84.26906700000001,33.877884],"type":"Point"}
}