{
  "type": "Feature",
  "properties": {
    "iso:country":"US",
    "sg:address":"1210 Dalon Rd NE",
    "sg:city":"Atlanta",
    "sg:classifiers":[
        {
            "category":"Autos & Motor Vehicles",
            "subcategory":"Auto Supplies",
            "type":"Retail Goods"
        }
    ],
    "sg:phone":"+1 404 634 9370",
    "sg:postcode":"30306",
    "sg:province":"GA",
    "sg:tags":[
        "automobile",
        "accessory",
        "parts",
        "accessories-wholesale",
        "part",
        "manufacturer"
    ],
    "wof:name":"C & N Autoparts",
    "wof:placetype":"venue"
},
  "geometry": {"coordinates":[-84.340794,33.804589],"type":"Point"}
}