{
  "type": "Feature",
  "properties": {
    "iso:country":"US",
    "sg:address":"5858 N Helton Rd",
    "sg:city":"Villa Rica",
    "sg:classifiers":[
        {
            "category":"Building & Trades",
            "subcategory":"Landscaping Services",
            "type":"Services"
        }
    ],
    "sg:phone":"+1 770 942 6636",
    "sg:postcode":"30180",
    "sg:province":"GA",
    "wof:name":"Wayne L Timmons",
    "wof:placetype":"venue"
},
  "geometry": {"coordinates":[-84.89953,33.645716],"type":"Point"}
}