{
  "type": "Feature",
  "properties": {
    "addr:full":"129 Miller Farm Rd Taylorsville GA 30178",
    "addr:housenumber":"129",
    "addr:postcode":"30178",
    "addr:street":"Miller Farm Rd",
    "iso:country":"US",
    "sg:address":"129 Miller Farm Rd",
    "sg:city":"Taylorsville",
    "sg:classifiers":[
        {
            "category":"Building & Trades",
            "subcategory":"Construction",
            "type":"Services"
        }
    ],
    "sg:phone":"+1 770 684 1060",
    "sg:postcode":"30178",
    "sg:province":"GA",
    "sg:tags":[
        "wallcoverings-installation",
        "wallpaper",
        "painting",
        "contractor"
    ],
    "wof:name":"S&S Painting",
    "wof:placetype":"venue"
},
  "geometry": {"coordinates":[-84.98877299999999,34.126281],"type":"Point"}
}