{
  "type": "Feature",
  "properties": {
    "addr:full":"5040 Pea Ridge Rd Cornelia GA 30531",
    "addr:housenumber":"5040",
    "addr:postcode":"30531",
    "addr:street":"Pea Ridge Rd",
    "iso:country":"US",
    "sg:address":"5040 Pea Ridge Rd",
    "sg:city":"Cornelia",
    "sg:classifiers":[
        {
            "category":"Organizations",
            "subcategory":"Religious Organization",
            "type":"Services"
        }
    ],
    "sg:phone":"+1 706 778 9226",
    "sg:postcode":"30531",
    "sg:province":"GA",
    "sg:tags":[
        "church"
    ],
    "wof:name":"New Hope Baptist Church",
    "wof:placetype":"venue"
},
  "geometry": {"coordinates":[-83.595844,34.535206],"type":"Point"}
}