{
  "type": "Feature",
  "properties": {
    "iso:country":"US",
    "sg:address":"2562 Fontaine Cir",
    "sg:city":"Decatur",
    "sg:classifiers":[
        {
            "category":"Building & Trades",
            "subcategory":"Electrical",
            "type":"Services"
        }
    ],
    "sg:phone":"+1 404 241 6776",
    "sg:postcode":"30032",
    "sg:province":"GA",
    "sg:tags":[
        "electrical",
        "contractor"
    ],
    "wof:name":"S Blackwell Electric Inc",
    "wof:placetype":"venue"
},
  "geometry": {"coordinates":[-84.285009,33.723631],"type":"Point"}
}