{
  "type": "Feature",
  "properties": {
    "iso:country":"US",
    "sg:address":"981 Martin Luther King Jr Dr SW",
    "sg:city":"Atlanta",
    "sg:classifiers":[
        {
            "category":"Personal",
            "subcategory":"Beauty Salon",
            "type":"Services"
        }
    ],
    "sg:phone":"+1 404 522 5342",
    "sg:postcode":"30314",
    "sg:province":"GA",
    "wof:name":"Esther's House Of Styles",
    "wof:placetype":"venue"
},
  "geometry": {"coordinates":[-84.41869,33.754733],"type":"Point"}
}