{
  "type": "Feature",
  "properties": {
    "iso:country":"US",
    "sg:address":"5014 River Rock Way",
    "sg:city":"Woodstock",
    "sg:classifiers":[
        {
            "category":"Organizations",
            "subcategory":"Religious Organization",
            "type":"Services"
        }
    ],
    "sg:phone":"+1 770 516 1458",
    "sg:postcode":"30188",
    "sg:province":"GA",
    "wof:name":"General Assoc Regular Baptist",
    "wof:placetype":"venue"
},
  "geometry": {"coordinates":[-84.451166,34.106818],"type":"Point"}
}