{
  "type": "Feature",
  "properties": {
    "iso:country":"US",
    "sg:address":"2735 Mozley St",
    "sg:city":"Austell",
    "sg:classifiers":[
        {
            "category":"Fast Food",
            "type":"Food & Drink"
        },
        {
            "category":"Food & Beverages",
            "subcategory":"Meat & Fish",
            "type":"Retail Goods"
        }
    ],
    "sg:phone":"+1 770 948 8474",
    "sg:postcode":"30168",
    "sg:province":"GA",
    "sg:tags":[
        "burger",
        "hot",
        "dog"
    ],
    "sg:website":"www.burgerking.com",
    "wof:name":"Burger King",
    "wof:placetype":"venue"
},
  "geometry": {"coordinates":[-84.595901,33.785999],"type":"Point"}
}