{
  "type": "Feature",
  "properties": {
    "addr:full":"2520 E Wesley Chapel Way Decatur GA 30035",
    "addr:housenumber":"2520",
    "addr:postcode":"30035",
    "addr:street":"E Wesley Chapel Way",
    "iso:country":"US",
    "sg:address":"2520 E Wesley Chapel Way",
    "sg:city":"Decatur",
    "sg:classifiers":[
        {
            "category":"Personal",
            "subcategory":"Beauty Salon",
            "type":"Services"
        }
    ],
    "sg:phone":"+1 770 981 8817",
    "sg:postcode":"30035",
    "sg:province":"GA",
    "sg:tags":[
        "shop"
    ],
    "wof:name":"Hair Depot",
    "wof:placetype":"venue"
},
  "geometry": {"coordinates":[-84.215315,33.713992],"type":"Point"}
}