{
  "type": "Feature",
  "properties": {
    "addr:full":"1410 Indian Trail Lilburn Rd Norcross GA 30093",
    "addr:housenumber":"1410",
    "addr:postcode":"30093",
    "addr:street":"Indian Trail Lilburn Rd",
    "iso:country":"US",
    "sg:address":"1410 Indian Trail Lilburn Rd",
    "sg:city":"Norcross",
    "sg:classifiers":[
        {
            "category":"Professional",
            "subcategory":"Engineering",
            "type":"Services"
        }
    ],
    "sg:phone":"+1 770 564 9843",
    "sg:postcode":"30093",
    "sg:province":"GA",
    "sg:tags":[
        "photogrammetric",
        "engineer"
    ],
    "sg:website":"http://www.photoscience.com",
    "wof:name":"G M R Aerial Surveys, Inc.",
    "wof:placetype":"venue"
},
  "geometry": {"coordinates":[-84.16489300000001,33.918176],"type":"Point"}
}