{
  "type": "Feature",
  "properties": {
    "addr:full":"3030 Headland Dr SW Atlanta GA 30311",
    "addr:housenumber":"3030",
    "addr:postcode":"30311",
    "addr:street":"Headland Dr Sw",
    "iso:country":"US",
    "sg:address":"3030 Headland Dr SW",
    "sg:city":"Atlanta",
    "sg:classifiers":[
        {
            "category":"Communications",
            "type":"Services"
        }
    ],
    "sg:phone":"+1 404 494 9436",
    "sg:postcode":"30311",
    "sg:province":"GA",
    "sg:tags":[
        "carrier"
    ],
    "wof:name":"Skytalk Communications",
    "wof:placetype":"venue"
},
  "geometry": {"coordinates":[-84.48762499999999,33.689491],"type":"Point"}
}