{
  "type": "Feature",
  "properties": {
    "iso:country":"US",
    "sg:address":"202 Franklin St",
    "sg:city":"Zebulon",
    "sg:classifiers":[
        {
            "category":"Organizations",
            "subcategory":"Religious Organization",
            "type":"Services"
        }
    ],
    "sg:phone":"+1 770 567 8621",
    "sg:postcode":"30295",
    "sg:province":"GA",
    "sg:tags":[
        "church"
    ],
    "wof:name":"Zebulon United Methodist",
    "wof:placetype":"venue"
},
  "geometry": {"coordinates":[-84.348686,33.100577],"type":"Point"}
}