{
  "type": "Feature",
  "properties": {
    "iso:country":"US",
    "sg:address":"121 Seagraves Dr",
    "sg:city":"Athens",
    "sg:classifiers":[
        {
            "category":"Building & Trades",
            "subcategory":"Landscaping Services",
            "type":"Services"
        }
    ],
    "sg:phone":"+1 770 725 0922",
    "sg:postcode":"30605",
    "sg:province":"GA",
    "sg:tags":[
        "tree"
    ],
    "wof:name":"A Cut Above Tree Svc",
    "wof:placetype":"venue"
},
  "geometry": {"coordinates":[-83.332926,33.941243],"type":"Point"}
}