{
  "type": "Feature",
  "properties": {
    "addr:full":"435 Drayton St Savannah GA 31401",
    "addr:housenumber":"435",
    "addr:postcode":"31401",
    "addr:street":"Drayton St",
    "iso:country":"US",
    "sg:address":"435 Drayton St",
    "sg:city":"Savannah",
    "sg:classifiers":[
        {
            "category":"Recreation",
            "type":"Entertainment"
        }
    ],
    "sg:phone":"+1 912 233 2004",
    "sg:postcode":"31401",
    "sg:province":"GA",
    "wof:name":"East End Gallery",
    "wof:placetype":"venue"
},
  "geometry": {"coordinates":[-81.093954,32.070486],"type":"Point"}
}