{
  "type": "Feature",
  "properties": {
    "addr:full":"1115 Buford Hwy Suwanee GA 30024",
    "addr:housenumber":"1115",
    "addr:postcode":"30024",
    "addr:street":"Buford Hwy",
    "iso:country":"US",
    "sg:address":"1115 Buford Hwy",
    "sg:city":"Suwanee",
    "sg:classifiers":[
        {
            "category":"Retail",
            "subcategory":"Auto Rental",
            "type":"Services"
        }
    ],
    "sg:phone":"+1 770 932 6646",
    "sg:postcode":"30024",
    "sg:province":"GA",
    "sg:tags":[
        "renting",
        "truck",
        "leasing"
    ],
    "wof:name":"Budget Truck Rental",
    "wof:placetype":"venue"
},
  "geometry": {"coordinates":[-84.086382,34.036064],"type":"Point"}
}