{
  "type": "Feature",
  "properties": {
    "addr:full":"4701 State Rte 15 White Plains GA 30678",
    "addr:housenumber":"4701",
    "addr:postcode":"30678",
    "addr:street":"State Rte 15",
    "iso:country":"US",
    "sg:address":"4701 State Rte 15",
    "sg:city":"White Plains",
    "sg:classifiers":[
        {
            "category":"Retail",
            "subcategory":"Auto Rental",
            "type":"Services"
        }
    ],
    "sg:phone":"+1 706 467 0611",
    "sg:postcode":"30678",
    "sg:province":"GA",
    "sg:tags":[
        "renting",
        "truck",
        "leasing"
    ],
    "wof:name":"U-Haul Co",
    "wof:placetype":"venue"
},
  "geometry": {"coordinates":[-83.048945,33.510458],"type":"Point"}
}