{
  "type": "Feature",
  "properties": {
    "iso:country":"US",
    "sg:address":"5217 Augusta Rd",
    "sg:city":"Savannah",
    "sg:classifiers":[
        {
            "category":"Utilities",
            "subcategory":"Refuse",
            "type":"Services"
        }
    ],
    "sg:phone":"+1 912 964 7040",
    "sg:postcode":"31408",
    "sg:province":"GA",
    "sg:tags":[
        "equipment",
        "recycling",
        "system"
    ],
    "wof:name":"Safety-Kleen Corp",
    "wof:placetype":"venue"
},
  "geometry": {"coordinates":[-81.16676,32.118757],"type":"Point"}
}