{
  "type": "Feature",
  "properties": {
    "addr:full":"4335 Norman Hall Rd Valdosta GA 31605",
    "addr:housenumber":"4335",
    "addr:postcode":"31605",
    "addr:street":"Norman Hall Rd",
    "iso:country":"US",
    "sg:address":"4335 Norman Hall Rd",
    "sg:city":"Valdosta",
    "sg:classifiers":[
        {
            "category":"Retail",
            "subcategory":"Repair Shop",
            "type":"Services"
        }
    ],
    "sg:phone":"+1 229 244 3198",
    "sg:postcode":"31605",
    "sg:province":"GA",
    "sg:tags":[
        "welding"
    ],
    "wof:name":"Sam S Welding",
    "wof:placetype":"venue"
},
  "geometry": {"coordinates":[-83.248487,30.955378],"type":"Point"}
}