{
  "type": "Feature",
  "properties": {
    "iso:country":"US",
    "sg:address":"716 16th Ave E",
    "sg:city":"Cordele",
    "sg:classifiers":[
        {
            "category":"Health Services",
            "subcategory":"Chiropractor",
            "type":"Services"
        }
    ],
    "sg:phone":"+1 229 273 5244",
    "sg:postcode":"31015",
    "sg:province":"GA",
    "wof:name":"Rice William M DC PC",
    "wof:placetype":"venue"
},
  "geometry": {"coordinates":[-83.770965,31.96365],"type":"Point"}
}