{
  "type": "Feature",
  "properties": {
    "addr:full":"3780 Youth Monroe Rd Loganville GA 30052",
    "addr:postcode":"30052",
    "addr:street":"Monroe Rd",
    "iso:country":"US",
    "sg:address":"3780 Youth Monroe Rd",
    "sg:city":"Loganville",
    "sg:classifiers":[
        {
            "category":"Building & Trades",
            "subcategory":"Construction",
            "type":"Services"
        }
    ],
    "sg:phone":"+1 678 618 7965",
    "sg:postcode":"30052",
    "sg:province":"GA",
    "sg:tags":[
        "house"
    ],
    "wof:name":"D & D Construction",
    "wof:placetype":"venue"
},
  "geometry": {"coordinates":[-83.843419,33.794125],"type":"Point"}
}