{
  "type": "Feature",
  "properties": {
    "iso:country":"US",
    "sg:address":"130 Claridge Park Dr",
    "sg:city":"Morrow",
    "sg:classifiers":[
        {
            "category":"Real Estate",
            "subcategory":"Real Estate Agent",
            "type":"Services"
        }
    ],
    "sg:phone":"+1 678 618 5671",
    "sg:postcode":"30260",
    "sg:province":"GA",
    "wof:name":"New South Realty Group LLC",
    "wof:placetype":"venue"
},
  "geometry": {"coordinates":[-84.336309,33.562201],"type":"Point"}
}