{
  "type": "Feature",
  "properties": {
    "addr:full":"535 Wheatridge Bluff Roswell GA 30075",
    "addr:housenumber":"535",
    "addr:postcode":"30075",
    "addr:street":"Wheatridge Bluff",
    "iso:country":"US",
    "sg:address":"535 Wheatridge Bluff",
    "sg:city":"Roswell",
    "sg:classifiers":[
        {
            "category":"Wholesale",
            "subcategory":"Seafood",
            "type":"Manufacturing & Wholesale Goods"
        }
    ],
    "sg:phone":"+1 770 518 8004",
    "sg:postcode":"30075",
    "sg:province":"GA",
    "wof:name":"Aunt Bs Oyster House Inc",
    "wof:placetype":"venue"
},
  "geometry": {"coordinates":[-84.388189,34.070158],"type":"Point"}
}