{
  "type": "Feature",
  "properties": {
    "addr:full":"300 S Tibbs Rd Dalton GA 30720",
    "addr:housenumber":"300",
    "addr:postcode":"30720",
    "addr:street":"S Tibbs Rd",
    "iso:country":"US",
    "sg:address":"300 S Tibbs Rd",
    "sg:city":"Dalton",
    "sg:classifiers":[
        {
            "category":"Organizations",
            "subcategory":"Religious Organization",
            "type":"Services"
        }
    ],
    "sg:phone":"+1 706 226 2166",
    "sg:postcode":"30720",
    "sg:province":"GA",
    "sg:tags":[
        "church"
    ],
    "wof:name":"Seventh Day Adventist Church",
    "wof:placetype":"venue"
},
  "geometry": {"coordinates":[-84.99338,34.765217],"type":"Point"}
}