{
  "type": "Feature",
  "properties": {
    "iso:country":"US",
    "sg:address":"101 Marietta St NW",
    "sg:city":"Atlanta",
    "sg:classifiers":[
        {
            "category":"Professional",
            "subcategory":"Lawyer & Legal Services",
            "type":"Services"
        }
    ],
    "sg:phone":"+1 404 688 8810",
    "sg:postcode":"30303",
    "sg:province":"GA",
    "sg:tags":[
        "litigation",
        "tort",
        "attorney"
    ],
    "wof:name":"Kushkin , Lauren M. - Kessler, Schwarz &",
    "wof:placetype":"venue"
},
  "geometry": {"coordinates":[-84.39209700000001,33.756451],"type":"Point"}
}