{
  "type": "Feature",
  "properties": {
    "addr:full":"1249 Springhouse Ln SW Atlanta GA 30311",
    "addr:housenumber":"1249",
    "addr:postcode":"30311",
    "addr:street":"Springhouse Ln Sw",
    "iso:country":"US",
    "sg:address":"1249 Springhouse Ln SW",
    "sg:city":"Atlanta",
    "sg:classifiers":[
        {
            "category":"Banks & Credit Unions",
            "subcategory":"Bank",
            "type":"Services"
        }
    ],
    "sg:phone":"+1 404 847 6677",
    "sg:postcode":"30311",
    "sg:province":"GA",
    "sg:tags":[
        "loan",
        "real estate"
    ],
    "wof:name":"Equity Funding Corp",
    "wof:placetype":"venue"
},
  "geometry": {"coordinates":[-84.473777,33.721466],"type":"Point"}
}