{
  "type": "Feature",
  "properties": {
    "addr:full":"902 Martin Luther King Jr Blvd Savannah GA 31415",
    "addr:housenumber":"902",
    "addr:postcode":"31415",
    "addr:street":"Martin Luther King Jr Blvd",
    "iso:country":"US",
    "sg:address":"902 Martin Luther King Jr Blvd",
    "sg:city":"Savannah",
    "sg:classifiers":[
        {
            "category":"Insurance",
            "subcategory":"Hazard Insurance",
            "type":"Services"
        },
        {
            "category":"Professional",
            "subcategory":"Business Services",
            "type":"Services"
        }
    ],
    "sg:phone":"+1 912 233 2245",
    "sg:postcode":"31415",
    "sg:province":"GA",
    "sg:tags":[
        "bonding",
        "bail",
        "bond"
    ],
    "wof:name":"Alright Bail Bond Inc",
    "wof:placetype":"venue"
},
  "geometry": {"coordinates":[-81.102023,32.067477],"type":"Point"}
}