{
  "type": "Feature",
  "properties": {
    "addr:full":"1068 West Ave SW Conyers GA 30012",
    "addr:housenumber":"1068",
    "addr:postcode":"30012",
    "addr:street":"West Ave Sw",
    "iso:country":"US",
    "sg:address":"1068 West Ave SW",
    "sg:city":"Conyers",
    "sg:classifiers":[
        {
            "category":"Shopping",
            "subcategory":"Computers & Home Electronics",
            "type":"Retail Goods"
        }
    ],
    "sg:phone":"+1 770 922 3520",
    "sg:postcode":"30012",
    "sg:province":"GA",
    "wof:name":"Autosound & Accessories",
    "wof:placetype":"venue"
},
  "geometry": {"coordinates":[-84.02319900000001,33.668726],"type":"Point"}
}