{
  "type": "Feature",
  "properties": {
    "addr:full":"1879 Buford Hwy Ste 8 Buford GA 30518",
    "addr:housenumber":"1879",
    "addr:postcode":"30518",
    "addr:street":"Buford Hwy Ste 8",
    "iso:country":"US",
    "sg:address":"1879 Buford Hwy Ste 8",
    "sg:city":"Buford",
    "sg:classifiers":[
        {
            "category":"Restaurant",
            "type":"Food & Drink"
        }
    ],
    "sg:phone":"+1 770 945 1400",
    "sg:postcode":"30518",
    "sg:province":"GA",
    "sg:tags":[
        "pizza"
    ],
    "sg:website":"dominos.com",
    "wof:name":"Domino's Pizza",
    "wof:placetype":"venue"
},
  "geometry": {"coordinates":[-84.00445999999999,34.104669],"type":"Point"}
}