{
  "type": "Feature",
  "properties": {
    "addr:full":"1716 Inlet Cove Ct Snellville GA 30078",
    "addr:housenumber":"1716",
    "addr:postcode":"30078",
    "addr:street":"Inlet Cove Ct",
    "iso:country":"US",
    "sg:address":"1716 Inlet Cove Ct",
    "sg:city":"Snellville",
    "sg:classifiers":[
        {
            "category":"Building & Trades",
            "subcategory":"Construction",
            "type":"Services"
        }
    ],
    "sg:phone":"+1 770 982 6807",
    "sg:postcode":"30078",
    "sg:province":"GA",
    "sg:tags":[
        "residential"
    ],
    "wof:name":"Teamwork Construction LLC",
    "wof:placetype":"venue"
},
  "geometry": {"coordinates":[-83.98331,33.851564],"type":"Point"}
}