{
  "type": "Feature",
  "properties": {
    "addr:full":"808 Newnan Rd Carrollton GA 30117",
    "addr:housenumber":"808",
    "addr:postcode":"30117",
    "addr:street":"Newnan Rd",
    "iso:country":"US",
    "sg:address":"808 Newnan Rd",
    "sg:city":"Carrollton",
    "sg:classifiers":[
        {
            "category":"Communications",
            "subcategory":"Radio Station",
            "type":"Services"
        }
    ],
    "sg:phone":"+1 678 601 1330",
    "sg:postcode":"30117",
    "sg:province":"GA",
    "sg:tags":[
        "company",
        "broadcasting"
    ],
    "sg:website":"www.newstalk1330.com",
    "wof:name":"WLBB",
    "wof:placetype":"venue"
},
  "geometry": {"coordinates":[-85.051349,33.571732],"type":"Point"}
}