{
  "type": "Feature",
  "properties": {
    "iso:country":"US",
    "sg:address":"4270 Cyndy Jo Cir",
    "sg:city":"Macon",
    "sg:classifiers":[
        {
            "category":"Retail",
            "subcategory":"Repair Shop",
            "type":"Services"
        }
    ],
    "sg:phone":"+1 478 785 9431",
    "sg:postcode":"31216",
    "sg:province":"GA",
    "sg:tags":[
        "equipment",
        "dental",
        "refinishing",
        "instrument"
    ],
    "wof:name":"Hayes Handpiece Repair Co",
    "wof:placetype":"venue"
},
  "geometry": {"coordinates":[-83.70455800000001,32.727702],"type":"Point"}
}