{
  "type": "Feature",
  "properties": {
    "addr:full":"804 Winding Cir Vidalia GA 30474",
    "addr:housenumber":"804",
    "addr:postcode":"30474",
    "addr:street":"Winding Cir",
    "iso:country":"US",
    "sg:address":"804 Winding Cir",
    "sg:city":"Vidalia",
    "sg:classifiers":[
        {
            "category":"Shopping",
            "type":"Retail Goods"
        }
    ],
    "sg:phone":"+1 912 537 7904",
    "sg:postcode":"30474",
    "sg:province":"GA",
    "sg:tags":[
        "merchandise"
    ],
    "wof:name":"Total Packaging Company",
    "wof:placetype":"venue"
},
  "geometry": {"coordinates":[-82.394831,32.228815],"type":"Point"}
}