{
  "type": "Feature",
  "properties": {
    "iso:country":"US",
    "sg:address":"5260 Arrowind Rd NW",
    "sg:city":"Lilburn",
    "sg:classifiers":[
        {
            "category":"Health Services",
            "subcategory":"Nursing And Care Facility",
            "type":"Services"
        }
    ],
    "sg:phone":"+1 770 925 3409",
    "sg:postcode":"30047",
    "sg:province":"GA",
    "sg:tags":[
        "skilled"
    ],
    "wof:name":"Growth Horizons Inc",
    "wof:placetype":"venue"
},
  "geometry": {"coordinates":[-84.15991,33.893969],"type":"Point"}
}