{
  "type": "Feature",
  "properties": {
    "iso:country":"US",
    "sg:address":"2202 N Point Cir",
    "sg:city":"Alpharetta",
    "sg:classifiers":[
        {
            "category":"Deli",
            "type":"Food & Drink"
        },
        {
            "category":"Food & Beverages",
            "subcategory":"Bakery",
            "type":"Retail Goods"
        }
    ],
    "sg:phone":"+1 770 667 4648",
    "sg:postcode":"30022",
    "sg:province":"GA",
    "sg:tags":[
        "sandwich"
    ],
    "wof:name":"Wall Street Deli",
    "wof:placetype":"venue"
},
  "geometry": {"coordinates":[-84.29374,34.051104],"type":"Point"}
}