{
  "type": "Feature",
  "properties": {
    "iso:country":"US",
    "sg:address":"4591 Densmore Dr NE",
    "sg:city":"Dalton",
    "sg:classifiers":[
        {
            "category":"Manufacturing",
            "subcategory":"Tools & Machinery",
            "type":"Manufacturing & Wholesale Goods"
        }
    ],
    "sg:phone":"+1 706 259 9334",
    "sg:postcode":"30721",
    "sg:province":"GA",
    "sg:tags":[
        "machine",
        "shop"
    ],
    "wof:name":"Densmore Machine Co Inc",
    "wof:placetype":"venue"
},
  "geometry": {"coordinates":[-84.87654000000001,34.80928],"type":"Point"}
}