{
  "type": "Feature",
  "properties": {
    "addr:full":"5087 Buford Hwy Doraville GA 30340",
    "addr:housenumber":"5087",
    "addr:postcode":"30340",
    "addr:street":"Buford Hwy",
    "iso:country":"US",
    "sg:address":"5087 Buford Hwy",
    "sg:city":"Doraville",
    "sg:classifiers":[
        {
            "category":"Personal",
            "subcategory":"Beauty Salon",
            "type":"Services"
        }
    ],
    "sg:phone":"+1 770 936 0222",
    "sg:postcode":"30340",
    "sg:province":"GA",
    "sg:tags":[
        "hair"
    ],
    "wof:name":"My Dzung's Hair Salon",
    "wof:placetype":"venue"
},
  "geometry": {"coordinates":[-84.285273,33.89102],"type":"Point"}
}