{
  "type": "Feature",
  "properties": {
    "iso:country":"US",
    "sg:address":"310 Ridge Trl",
    "sg:city":"Riverdale",
    "sg:classifiers":[
        {
            "category":"Autos & Motor Vehicles",
            "subcategory":"Auto Supplies",
            "type":"Retail Goods"
        }
    ],
    "sg:phone":"+1 770 907 5260",
    "sg:postcode":"30274",
    "sg:province":"GA",
    "wof:name":"Kathy James",
    "wof:placetype":"venue"
},
  "geometry": {"coordinates":[-84.40230099999999,33.581913],"type":"Point"}
}