{
  "type": "Feature",
  "properties": {
    "addr:full":"30 Public Sq S Dahlonega GA 30533",
    "addr:housenumber":"30",
    "addr:postcode":"30533",
    "addr:street":"Public Sq S Dahlonega",
    "iso:country":"US",
    "sg:address":"30 Public Sq S",
    "sg:city":"Dahlonega",
    "sg:classifiers":[
        {
            "category":"Food & Beverages",
            "subcategory":"Bakery",
            "type":"Retail Goods"
        }
    ],
    "sg:phone":"+1 706 864 1095",
    "sg:postcode":"30533",
    "sg:province":"GA",
    "sg:tags":[
        "baker",
        "restaurant"
    ],
    "wof:name":"Dahlonega Dessertery",
    "wof:placetype":"venue"
},
  "geometry": {"coordinates":[-83.984544,34.532483],"type":"Point"}
}