{
  "type": "Feature",
  "properties": {
    "addr:full":"207 Culberson Ave La Fayette GA 30728",
    "addr:housenumber":"207",
    "addr:postcode":"30728",
    "addr:street":"Culberson Ave La Fayette",
    "iso:country":"US",
    "sg:address":"207 Culberson Ave",
    "sg:city":"La Fayette",
    "sg:classifiers":[
        {
            "category":"Professional",
            "type":"Services"
        }
    ],
    "sg:phone":"+1 706 638 7748",
    "sg:postcode":"30728",
    "sg:province":"GA",
    "sg:tags":[
        "establishment"
    ],
    "wof:name":"Shahanchristine",
    "wof:placetype":"venue"
},
  "geometry": {"coordinates":[-85.28408,34.707041],"type":"Point"}
}