{
  "type": "Feature",
  "properties": {
    "iso:country":"US",
    "sg:address":"3438 Houston Ave",
    "sg:city":"Macon",
    "sg:classifiers":[
        {
            "category":"Retail",
            "subcategory":"Repair Shop",
            "type":"Services"
        }
    ],
    "sg:phone":"+1 478 781 2525",
    "sg:postcode":"31206",
    "sg:province":"GA",
    "sg:tags":[
        "upholsterer"
    ],
    "wof:name":"Fred Jones Upholstery Shop",
    "wof:placetype":"venue"
},
  "geometry": {"coordinates":[-83.65129399999999,32.800697],"type":"Point"}
}