{
  "type": "Feature",
  "properties": {
    "iso:country":"US",
    "sg:address":"190 Greencastle Rd",
    "sg:city":"Tyrone",
    "sg:phone":"+1 770 631 4480",
    "sg:postcode":"30290",
    "sg:province":"GA",
    "wof:name":"Immediate Care Centers Of Geor",
    "wof:placetype":"venue"
},
  "geometry": {"coordinates":[-84.590683,33.45005],"type":"Point"}
}