{
  "type": "Feature",
  "properties": {
    "iso:country":"US",
    "sg:address":"806 Atkinson Dr",
    "sg:city":"Dalton",
    "sg:classifiers":[
        {
            "category":"Real Estate",
            "subcategory":"Real Estate Agent",
            "type":"Services"
        }
    ],
    "sg:phone":"+1 706 278 8119",
    "sg:postcode":"30720",
    "sg:province":"GA",
    "wof:name":"Medic Realty Inc",
    "wof:placetype":"venue"
},
  "geometry": {"coordinates":[-84.989459,34.764279],"type":"Point"}
}