{
  "type": "Feature",
  "properties": {
    "iso:country":"US",
    "sg:address":"5817 Anson Ave",
    "sg:city":"Eastman",
    "sg:classifiers":[
        {
            "category":"Personal",
            "subcategory":"Barber",
            "type":"Services"
        }
    ],
    "sg:phone":"+1 478 374 9458",
    "sg:postcode":"31023",
    "sg:province":"GA",
    "wof:name":"Flavors Barber Shop",
    "wof:placetype":"venue"
},
  "geometry": {"coordinates":[-83.171352,32.202379],"type":"Point"}
}