{
  "type": "Feature",
  "properties": {
    "addr:full":"3216 Mustang Dr Columbus GA 31909",
    "addr:housenumber":"3216",
    "addr:postcode":"31909",
    "addr:street":"Mustang Dr",
    "iso:country":"US",
    "sg:address":"3216 Mustang Dr",
    "sg:city":"Columbus",
    "sg:classifiers":[
        {
            "category":"Retail",
            "subcategory":"Portrait Studio",
            "type":"Services"
        }
    ],
    "sg:phone":"+1 706 327 3485",
    "sg:postcode":"31909",
    "sg:province":"GA",
    "sg:tags":[
        "photo"
    ],
    "wof:name":"Jk Dallas Photography",
    "wof:placetype":"venue"
},
  "geometry": {"coordinates":[-84.939983,32.521248],"type":"Point"}
}