{
  "type": "Feature",
  "properties": {
    "addr:full":"3051 Co Rd 257 Dublin GA 31021",
    "addr:housenumber":"3051",
    "addr:postcode":"31021",
    "addr:street":"Co Rd 257",
    "iso:country":"US",
    "sg:address":"3051 Co Rd 257",
    "sg:city":"Dublin",
    "sg:classifiers":[
        {
            "category":"Organizations",
            "subcategory":"Religious Organization",
            "type":"Services"
        }
    ],
    "sg:phone":"+1 478 272 5554",
    "sg:postcode":"31021",
    "sg:province":"GA",
    "sg:tags":[
        "church"
    ],
    "wof:name":"New Bethel Baptist Church Inc",
    "wof:placetype":"venue"
},
  "geometry": {"coordinates":[-82.98469900000001,32.4927],"type":"Point"}
}