{
  "type": "Feature",
  "properties": {
    "addr:full":"710 Dorothy St Waycross GA 31501",
    "addr:housenumber":"710",
    "addr:postcode":"31501",
    "addr:street":"Dorothy St",
    "iso:country":"US",
    "sg:address":"710 Dorothy St",
    "sg:city":"Waycross",
    "sg:classifiers":[
        {
            "category":"Organizations",
            "subcategory":"Community Association",
            "type":"Services"
        }
    ],
    "sg:phone":"+1 912 285 9222",
    "sg:postcode":"31501",
    "sg:province":"GA",
    "wof:name":"John Sutton Post 517",
    "wof:placetype":"venue"
},
  "geometry": {"coordinates":[-82.356009,31.225753],"type":"Point"}
}