{
  "type": "Feature",
  "properties": {
    "addr:full":"1018 Pepper Cir Acworth GA 30101",
    "addr:housenumber":"1018",
    "addr:postcode":"30101",
    "addr:street":"Pepper Cir",
    "iso:country":"US",
    "sg:address":"1018 Pepper Cir",
    "sg:city":"Acworth",
    "sg:classifiers":[
        {
            "category":"Professional",
            "type":"Services"
        }
    ],
    "sg:phone":"+1 770 529 2745",
    "sg:postcode":"30101",
    "sg:province":"GA",
    "wof:name":"Christopher R Cudzilo",
    "wof:placetype":"venue"
},
  "geometry": {"coordinates":[-84.671115,34.076377],"type":"Point"}
}