{
  "type": "Feature",
  "properties": {
    "addr:full":"135 Antioch Rd Fayetteville GA 30215",
    "addr:housenumber":"135",
    "addr:postcode":"30215",
    "addr:street":"Antioch Rd",
    "iso:country":"US",
    "sg:address":"135 Antioch Rd",
    "sg:city":"Fayetteville",
    "sg:classifiers":[
        {
            "category":"Organizations",
            "subcategory":"Religious Organization",
            "type":"Services"
        }
    ],
    "sg:phone":"+1 770 461 0492",
    "sg:postcode":"30215",
    "sg:province":"GA",
    "sg:tags":[
        "church"
    ],
    "sg:website":"www.stgabrielga.catholicweb.com",
    "wof:name":"Saint Gabriel Catholic Church",
    "wof:placetype":"venue"
},
  "geometry": {"coordinates":[-84.419798,33.357695],"type":"Point"}
}