{
  "type": "Feature",
  "properties": {
    "addr:full":"1105 N Slappey Blvd Albany GA 31701",
    "addr:housenumber":"1105",
    "addr:postcode":"31701",
    "addr:street":"N Slappey Blvd",
    "iso:country":"US",
    "sg:address":"1105 N Slappey Blvd",
    "sg:city":"Albany",
    "sg:phone":"+1 229 436 5522",
    "sg:postcode":"31701",
    "sg:province":"GA",
    "sg:website":"http://www.mcdonalds.com",
    "wof:name":"McDonald's",
    "wof:placetype":"venue"
},
  "geometry": {"coordinates":[-84.176041,31.591753],"type":"Point"}
}