{
  "type": "Feature",
  "properties": {
    "iso:country":"US",
    "sg:address":"902 Millstream Ct",
    "sg:city":"Savannah",
    "sg:classifiers":[
        {
            "category":"Professional",
            "type":"Services"
        }
    ],
    "sg:phone":"+1 912 920 8707",
    "sg:postcode":"31419",
    "sg:province":"GA",
    "wof:name":"DDS Co",
    "wof:placetype":"venue"
},
  "geometry": {"coordinates":[-81.14437,31.961513],"type":"Point"}
}