{
  "type": "Feature",
  "properties": {
    "iso:country":"US",
    "sg:address":"5895 Arbor Hill Rd",
    "sg:city":"Canton",
    "sg:classifiers":[
        {
            "category":"Autos & Motor Vehicles",
            "subcategory":"Automobile Sales",
            "type":"Retail Goods"
        }
    ],
    "sg:phone":"+1 770 781 9175",
    "sg:postcode":"30115",
    "sg:province":"GA",
    "sg:tags":[
        "used"
    ],
    "wof:name":"Falcon Auto Sales & Leasing",
    "wof:placetype":"venue"
},
  "geometry": {"coordinates":[-84.30581599999999,34.246922],"type":"Point"}
}