{
  "type": "Feature",
  "properties": {
    "addr:full":"1840 Berkeley Mews Atlanta GA 30329",
    "addr:housenumber":"1840",
    "addr:postcode":"30329",
    "addr:street":"Berkeley Mews",
    "iso:country":"US",
    "sg:address":"1840 Berkeley Mews",
    "sg:city":"Atlanta",
    "sg:classifiers":[
        {
            "category":"Professional",
            "subcategory":"Lawyer & Legal Services",
            "type":"Services"
        }
    ],
    "sg:phone":"+1 404 320 1100",
    "sg:postcode":"30329",
    "sg:province":"GA",
    "sg:tags":[
        "attorney"
    ],
    "wof:name":"Ilene H Ferenczy Law Offices",
    "wof:placetype":"venue"
},
  "geometry": {"coordinates":[-84.312656,33.823622],"type":"Point"}
}