{
  "type": "Feature",
  "properties": {
    "iso:country":"US",
    "sg:address":"1081 E Church St",
    "sg:city":"Jasper",
    "sg:classifiers":[
        {
            "category":"Building & Trades",
            "subcategory":"Construction",
            "type":"Services"
        }
    ],
    "sg:phone":"+1 706 253 4736",
    "sg:postcode":"30143",
    "sg:province":"GA",
    "sg:tags":[
        "general",
        "contractor"
    ],
    "wof:name":"Cohutta Contracting",
    "wof:placetype":"venue"
},
  "geometry": {"coordinates":[-84.414216,34.461056],"type":"Point"}
}