{
  "type": "Feature",
  "properties": {
    "iso:country":"US",
    "sg:address":"1780 Century Blvd NE A",
    "sg:city":"Atlanta",
    "sg:classifiers":[
        {
            "category":"Personal",
            "subcategory":"Massage",
            "type":"Services"
        }
    ],
    "sg:phone":"+1 770 337 4520",
    "sg:postcode":"30345",
    "sg:province":"GA",
    "wof:name":"Gina Michael Lmt",
    "wof:placetype":"venue"
},
  "geometry": {"coordinates":[-84.313492,33.846089],"type":"Point"}
}