{
  "type": "Feature",
  "properties": {
    "iso:country":"US",
    "sg:address":"2151 Fountain Sq",
    "sg:city":"Snellville",
    "sg:classifiers":[
        {
            "category":"Health Services",
            "subcategory":"Doctor",
            "type":"Services"
        }
    ],
    "sg:phone":"+1 770 979 9996",
    "sg:postcode":"30078",
    "sg:province":"GA",
    "sg:tags":[
        "physician",
        "surgeon"
    ],
    "wof:name":"New London Anesthesia & Pain",
    "wof:placetype":"venue"
},
  "geometry": {"coordinates":[-84.033421,33.856875],"type":"Point"}
}