{
  "type": "Feature",
  "properties": {
    "iso:country":"US",
    "sg:address":"515 E Ponce De Leon Ave",
    "sg:city":"Decatur",
    "sg:classifiers":[
        {
            "category":"Organizations",
            "subcategory":"Religious Organization",
            "type":"Services"
        }
    ],
    "sg:phone":"+1 404 377 2622",
    "sg:postcode":"30030",
    "sg:province":"GA",
    "sg:website":"www.htparish.com",
    "wof:name":"Holy Trinity Parish-Episcopal",
    "wof:placetype":"venue"
},
  "geometry": {"coordinates":[-84.288945,33.775357],"type":"Point"}
}