{
  "type": "Feature",
  "properties": {
    "addr:full":"560 General Daniels Ave N Danielsville GA 30633",
    "addr:housenumber":"560",
    "addr:postcode":"30633",
    "addr:street":"General Daniels Ave N",
    "iso:country":"US",
    "sg:address":"560 General Daniels Ave N",
    "sg:city":"Danielsville",
    "sg:classifiers":[
        {
            "category":"Government",
            "subcategory":"Office",
            "type":"Public Place"
        }
    ],
    "sg:phone":"+1 706 795 2281",
    "sg:postcode":"30633",
    "sg:province":"GA",
    "wof:name":"Madison County Extension Scv",
    "wof:placetype":"venue"
},
  "geometry": {"coordinates":[-83.215642,34.132275],"type":"Point"}
}