{
  "type": "Feature",
  "properties": {
    "addr:full":"600 Ware St Thomson GA 30824",
    "addr:housenumber":"600",
    "addr:postcode":"30824",
    "addr:street":"Ware St",
    "iso:country":"US",
    "sg:address":"600 Ware St",
    "sg:city":"Thomson",
    "sg:classifiers":[
        {
            "category":"Health Services",
            "subcategory":"Doctor",
            "type":"Services"
        }
    ],
    "sg:phone":"+1 706 595 7000",
    "sg:postcode":"30824",
    "sg:province":"GA",
    "sg:tags":[
        "physician",
        "family",
        "practice",
        "surgeons",
        "medicine"
    ],
    "wof:name":"Julian C Hutchins Md Pc",
    "wof:placetype":"venue"
},
  "geometry": {"coordinates":[-82.509483,33.458641],"type":"Point"}
}