{
  "type": "Feature",
  "properties": {
    "iso:country":"US",
    "sg:address":"4057 Churchill Downs",
    "sg:city":"Gainesville",
    "sg:classifiers":[
        {
            "category":"Manufacturing",
            "subcategory":"Tools & Machinery",
            "type":"Manufacturing & Wholesale Goods"
        }
    ],
    "sg:phone":"+1 770 967 6160",
    "sg:postcode":"30507",
    "sg:province":"GA",
    "sg:tags":[
        "industrial",
        "mfg"
    ],
    "wof:name":"Innovative Machining Solutions",
    "wof:placetype":"venue"
},
  "geometry": {"coordinates":[-83.810699,34.170237],"type":"Point"}
}