{
  "type": "Feature",
  "properties": {
    "addr:full":"149 Burke St Stockbridge GA 30281",
    "addr:housenumber":"149",
    "addr:postcode":"30281",
    "addr:street":"Burke St",
    "iso:country":"US",
    "sg:address":"149 Burke St",
    "sg:city":"Stockbridge",
    "sg:classifiers":[
        {
            "category":"Organizations",
            "subcategory":"Religious Organization",
            "type":"Services"
        }
    ],
    "sg:phone":"+1 678 565 3120",
    "sg:postcode":"30281",
    "sg:province":"GA",
    "sg:tags":[
        "church"
    ],
    "wof:name":"New Faith MSN Non Dnmntnl",
    "wof:placetype":"venue"
},
  "geometry": {"coordinates":[-84.23437199999999,33.546538],"type":"Point"}
}