{
  "type": "Feature",
  "properties": {
    "iso:country":"US",
    "sg:address":"995 Willeo Rd",
    "sg:city":"Roswell",
    "sg:classifiers":[
        {
            "category":"Personal",
            "type":"Services"
        }
    ],
    "sg:phone":"+1 770 992 0575",
    "sg:postcode":"30075",
    "sg:province":"GA",
    "wof:name":"Nannyquest",
    "wof:placetype":"venue"
},
  "geometry": {"coordinates":[-84.39631300000001,34.013007],"type":"Point"}
}