{
  "type": "Feature",
  "properties": {
    "iso:country":"US",
    "sg:address":"4354 Lilburn Industrial Way SW",
    "sg:city":"Lilburn",
    "sg:classifiers":[
        {
            "category":"Professional",
            "subcategory":"Business Services",
            "type":"Services"
        }
    ],
    "sg:phone":"+1 770 925 2441",
    "sg:postcode":"30047",
    "sg:province":"GA",
    "sg:tags":[
        "holding"
    ],
    "wof:name":"Sawa Holdings A Georgia Lt",
    "wof:placetype":"venue"
},
  "geometry": {"coordinates":[-84.11997599999999,33.893312],"type":"Point"}
}