{
  "type": "Feature",
  "properties": {
    "addr:full":"4544 Ridgeview Dr Powder Springs GA 30127",
    "addr:housenumber":"4544",
    "addr:postcode":"30127",
    "addr:street":"Ridgeview Dr",
    "iso:country":"US",
    "sg:address":"4544 Ridgeview Dr",
    "sg:city":"Powder Springs",
    "sg:classifiers":[
        {
            "category":"Building & Trades",
            "subcategory":"Construction",
            "type":"Services"
        }
    ],
    "sg:phone":"+1 770 943 7543",
    "sg:postcode":"30127",
    "sg:province":"GA",
    "sg:tags":[
        "general"
    ],
    "wof:name":"Heath Building Services Inc",
    "wof:placetype":"venue"
},
  "geometry": {"coordinates":[-84.72228800000001,33.844707],"type":"Point"}
}