{
  "type": "Feature",
  "properties": {
    "iso:country":"US",
    "sg:address":"18 Carlyle Ct",
    "sg:city":"Hiram",
    "sg:classifiers":[
        {
            "category":"Home & Garden",
            "subcategory":"Home Furnishings",
            "type":"Retail Goods"
        }
    ],
    "sg:phone":"+1 770 577 7222",
    "sg:postcode":"30141",
    "sg:province":"GA",
    "sg:tags":[
        "mirror"
    ],
    "wof:name":"Mirror Maxx Inc",
    "wof:placetype":"venue"
},
  "geometry": {"coordinates":[-84.779363,33.822376],"type":"Point"}
}