{
  "type": "Feature",
  "properties": {
    "iso:country":"US",
    "sg:address":"529 Stephenson Ave Ste 5",
    "sg:city":"Savannah",
    "sg:classifiers":[
        {
            "category":"Professional",
            "subcategory":"Advertising",
            "type":"Services"
        }
    ],
    "sg:phone":"+1 912 660 7382",
    "sg:postcode":"31405",
    "sg:province":"GA",
    "sg:tags":[
        "agency",
        "specialty"
    ],
    "wof:name":"Moesch Media",
    "wof:placetype":"venue"
},
  "geometry": {"coordinates":[-81.103951,32.0112],"type":"Point"}
}