{
  "type": "Feature",
  "properties": {
    "iso:country":"US",
    "sg:address":"2463 Wise St",
    "sg:city":"Columbus",
    "sg:classifiers":[
        {
            "category":"Building & Trades",
            "subcategory":"Construction",
            "type":"Services"
        }
    ],
    "sg:phone":"+1 706 687 5286",
    "sg:postcode":"31903",
    "sg:province":"GA",
    "sg:tags":[
        "house"
    ],
    "wof:name":"Donnie Phillips Const",
    "wof:placetype":"venue"
},
  "geometry": {"coordinates":[-84.971433,32.409389],"type":"Point"}
}