{
  "type": "Feature",
  "properties": {
    "addr:full":"509 Hurricane Shoals Rd NE Lawrenceville GA 30045",
    "addr:housenumber":"509",
    "addr:postcode":"30045",
    "addr:street":"Hurricane Shoals Rd Ne",
    "iso:country":"US",
    "sg:address":"509 Hurricane Shoals Rd NE",
    "sg:city":"Lawrenceville",
    "sg:classifiers":[
        {
            "category":"Manufacturing",
            "subcategory":"Apparel",
            "type":"Manufacturing & Wholesale Goods"
        }
    ],
    "sg:phone":"+1 770 513 0375",
    "sg:postcode":"30045",
    "sg:province":"GA",
    "wof:name":"Ideas & Images Custom EMB",
    "wof:placetype":"venue"
},
  "geometry": {"coordinates":[-83.976882,33.976389],"type":"Point"}
}