{
  "type": "Feature",
  "properties": {
    "iso:country":"US",
    "sg:address":"2160 Castle Lake Dr",
    "sg:city":"Tyrone",
    "sg:classifiers":[
        {
            "category":"Real Estate",
            "subcategory":"Real Estate Operator",
            "type":"Services"
        }
    ],
    "sg:phone":"+1 770 487 4508",
    "sg:postcode":"30290",
    "sg:province":"GA",
    "sg:tags":[
        "building",
        "nonresidential"
    ],
    "wof:name":"Tilwin Properties Inc",
    "wof:placetype":"venue"
},
  "geometry": {"coordinates":[-84.60864599999999,33.465886],"type":"Point"}
}