{
  "type": "Feature",
  "properties": {
    "iso:country":"US",
    "sg:address":"475 Pleasant Ridge Rd",
    "sg:city":"Carrollton",
    "sg:classifiers":[
        {
            "category":"Building & Trades",
            "subcategory":"Plumbing",
            "type":"Services"
        }
    ],
    "sg:phone":"+1 770 834 5047",
    "sg:postcode":"30117",
    "sg:province":"GA",
    "sg:tags":[
        "heating",
        "contractor"
    ],
    "wof:name":"Ivey Heating & Air Cond",
    "wof:placetype":"venue"
},
  "geometry": {"coordinates":[-85.08399199999999,33.629664],"type":"Point"}
}