{
  "type": "Feature",
  "properties": {
    "iso:country":"US",
    "sg:address":"229 Austell Rd SW",
    "sg:city":"Marietta",
    "sg:classifiers":[
        {
            "category":"Professional",
            "subcategory":"Detective & Security Services",
            "type":"Services"
        },
        {
            "category":"Professional",
            "subcategory":"Lawyer & Legal Services",
            "type":"Services"
        }
    ],
    "sg:phone":"+1 678 905 4486",
    "sg:postcode":"30008",
    "sg:province":"GA",
    "sg:tags":[
        "referral",
        "bail",
        "bond"
    ],
    "sg:website":"http://lighthousebailbonds.reachlocal.com/?scid=1812877",
    "wof:name":"Lighthouse Bail Bonds",
    "wof:placetype":"venue"
},
  "geometry": {"coordinates":[-84.569962,33.901155],"type":"Point"}
}