{
  "type": "Feature",
  "properties": {
    "iso:country":"US",
    "sg:address":"1980 Mount Vernon Rd",
    "sg:city":"Atlanta",
    "sg:classifiers":[
        {
            "category":"Building & Trades",
            "subcategory":"Construction",
            "type":"Services"
        }
    ],
    "sg:phone":"+1 770 396 1029",
    "sg:postcode":"30338",
    "sg:province":"GA",
    "sg:tags":[
        "house"
    ],
    "wof:name":"Ansel Systems Inc",
    "wof:placetype":"venue"
},
  "geometry": {"coordinates":[-84.317564,33.95114],"type":"Point"}
}