{
  "type": "Feature",
  "properties": {
    "iso:country":"US",
    "sg:address":"770 Old Roswell Pl, Ste G 400A",
    "sg:city":"Roswell",
    "sg:classifiers":[
        {
            "category":"Banks & Credit Unions",
            "subcategory":"Investment Brokerage",
            "type":"Services"
        },
        {
            "category":"Banks & Credit Unions",
            "subcategory":"Financial Services",
            "type":"Services"
        }
    ],
    "sg:phone":"+1 678 352 8080",
    "sg:postcode":"30076",
    "sg:province":"GA",
    "sg:tags":[
        "investing",
        "advising"
    ],
    "sg:website":"www.ameripriseadvisors.com",
    "wof:name":"Ameriprise Financial Advisors",
    "wof:placetype":"venue"
},
  "geometry": {"coordinates":[-84.340217,34.035093],"type":"Point"}
}