{
  "type": "Feature",
  "properties": {
    "addr:full":"2401 Greensboro Hwy Watkinsville GA 30677",
    "addr:housenumber":"2401",
    "addr:postcode":"30677",
    "addr:street":"Greensboro Hwy",
    "iso:country":"US",
    "sg:address":"2401 Greensboro Hwy",
    "sg:city":"Watkinsville",
    "sg:classifiers":[
        {
            "category":"Building & Trades",
            "subcategory":"Construction",
            "type":"Services"
        }
    ],
    "sg:phone":"+1 706 769 7404",
    "sg:postcode":"30677",
    "sg:province":"GA",
    "sg:tags":[
        "excavating",
        "contractor"
    ],
    "wof:name":"Dickens Construction Co",
    "wof:placetype":"venue"
},
  "geometry": {"coordinates":[-83.378929,33.831988],"type":"Point"}
}