{
  "type": "Feature",
  "properties": {
    "iso:country":"US",
    "sg:address":"5436 Riverdale Road",
    "sg:city":"Atlanta",
    "sg:classifiers":[
        {
            "category":"Shopping",
            "subcategory":"Pawn Shop",
            "type":"Retail Goods"
        }
    ],
    "sg:phone":"+1 770 907 8229",
    "sg:postcode":"30349",
    "sg:province":"GA",
    "wof:name":"Aero Pawn Shop",
    "wof:placetype":"venue"
},
  "geometry": {"coordinates":[-84.435576,33.606883],"type":"Point"}
}