{
  "type": "Feature",
  "properties": {
    "addr:full":"1109 3rd St Perry GA 31069",
    "addr:housenumber":"1109",
    "addr:postcode":"31069",
    "addr:street":"3Rd St",
    "iso:country":"US",
    "sg:address":"1109 3rd St",
    "sg:city":"Perry",
    "sg:classifiers":[
        {
            "category":"Food & Beverages",
            "subcategory":"Groceries & Convenience Stores",
            "type":"Retail Goods"
        }
    ],
    "sg:phone":"+1 478 218 9396",
    "sg:postcode":"31069",
    "sg:province":"GA",
    "sg:tags":[
        "grocer"
    ],
    "wof:name":"Om Food Mart",
    "wof:placetype":"venue"
},
  "geometry": {"coordinates":[-83.726827,32.462067],"type":"Point"}
}