{
  "type": "Feature",
  "properties": {
    "iso:country":"US",
    "sg:address":"3011 Rainbow Dr",
    "sg:city":"Decatur",
    "sg:classifiers":[
        {
            "category":"Organizations",
            "subcategory":"Non-profit Organization",
            "type":"Services"
        }
    ],
    "sg:phone":"+1 404 243 5576",
    "sg:postcode":"30034",
    "sg:province":"GA",
    "sg:tags":[
        "info",
        "addiction",
        "abuse",
        "treatment",
        "drug"
    ],
    "wof:name":"Circle Of Recovery",
    "wof:placetype":"venue"
},
  "geometry": {"coordinates":[-84.27074399999999,33.709719],"type":"Point"}
}