{
  "type": "Feature",
  "properties": {
    "addr:full":"3685 Dallas Acworth Hwy NW Acworth GA 30101",
    "addr:housenumber":"3685",
    "addr:postcode":"30101",
    "addr:street":"Dallas Acworth Hwy Nw",
    "iso:country":"US",
    "sg:address":"3685 Dallas Acworth Hwy NW",
    "sg:city":"Acworth",
    "sg:classifiers":[
        {
            "category":"Banks & Credit Unions",
            "subcategory":"Bank",
            "type":"Services"
        }
    ],
    "sg:phone":"+1 678 331 1836",
    "sg:postcode":"30101",
    "sg:province":"GA",
    "sg:website":"www.rbccentura.com",
    "wof:name":"Rbc Centura Bank",
    "wof:placetype":"venue"
},
  "geometry": {"coordinates":[-84.728599,34.045203],"type":"Point"}
}