{
  "type": "Feature",
  "properties": {
    "iso:country":"US",
    "sg:address":"23 E de Renne Ave",
    "sg:city":"Savannah",
    "sg:classifiers":[
        {
            "category":"Personal",
            "type":"Services"
        },
        {
            "category":"Personal",
            "subcategory":"Tattoo Parlor",
            "type":"Services"
        }
    ],
    "sg:phone":"+1 912 352 8288",
    "sg:postcode":"31405",
    "sg:province":"GA",
    "sg:tags":[
        "tattooing"
    ],
    "wof:name":"California Tattooing",
    "wof:placetype":"venue"
},
  "geometry": {"coordinates":[-81.109438,32.028471],"type":"Point"}
}