{
  "type": "Feature",
  "properties": {
    "addr:full":"7001 Peachtree Industrial Blvd Norcross GA 30092",
    "addr:housenumber":"7001",
    "addr:postcode":"30092",
    "addr:street":"Peachtree Industrial Blvd",
    "iso:country":"US",
    "sg:address":"7001 Peachtree Industrial Blvd",
    "sg:city":"Norcross",
    "sg:classifiers":[
        {
            "category":"Real Estate",
            "subcategory":"Real Estate Services",
            "type":"Services"
        }
    ],
    "sg:phone":"+1 770 449 3940",
    "sg:postcode":"30092",
    "sg:province":"GA",
    "sg:tags":[
        "management",
        "property"
    ],
    "wof:name":"Intown Management Group",
    "wof:placetype":"venue"
},
  "geometry": {"coordinates":[-84.26065,33.934084],"type":"Point"}
}