{
  "type": "Feature",
  "properties": {
    "addr:full":"123 Bent Tree Dr Athens GA 30606",
    "addr:housenumber":"123",
    "addr:postcode":"30606",
    "addr:street":"Bent Tree Dr",
    "iso:country":"US",
    "sg:address":"123 Bent Tree Dr",
    "sg:city":"Athens",
    "sg:classifiers":[
        {
            "category":"Professional",
            "type":"Services"
        }
    ],
    "sg:phone":"+1 706 549 2550",
    "sg:postcode":"30606",
    "sg:province":"GA",
    "wof:name":"Calathus LLC",
    "wof:placetype":"venue"
},
  "geometry": {"coordinates":[-83.44713,33.955181],"type":"Point"}
}