{
  "type": "Feature",
  "properties": {
    "iso:country":"US",
    "sg:address":"1031 Knotts Point Dr",
    "sg:city":"Woodstock",
    "sg:classifiers":[
        {
            "category":"Wholesale",
            "subcategory":"Electrical",
            "type":"Manufacturing & Wholesale Goods"
        }
    ],
    "sg:phone":"+1 770 516 7770",
    "sg:postcode":"30188",
    "sg:province":"GA",
    "sg:tags":[
        "equipment"
    ],
    "wof:name":"Logia",
    "wof:placetype":"venue"
},
  "geometry": {"coordinates":[-84.43440099999999,34.075869],"type":"Point"}
}