{
  "type": "Feature",
  "properties": {
    "addr:full":"325 E 2nd St Jackson GA 30233",
    "addr:housenumber":"325",
    "addr:postcode":"30233",
    "addr:street":"E 2Nd St",
    "iso:country":"US",
    "sg:address":"325 E 2nd St",
    "sg:city":"Jackson",
    "sg:classifiers":[
        {
            "category":"Home & Garden",
            "subcategory":"Garden Supply",
            "type":"Retail Goods"
        }
    ],
    "sg:phone":"+1 770 775 7826",
    "sg:postcode":"30233",
    "sg:province":"GA",
    "sg:tags":[
        "bulb",
        "seed"
    ],
    "wof:name":"Adams Briscoe Seed Co",
    "wof:placetype":"venue"
},
  "geometry": {"coordinates":[-83.963246,33.295189],"type":"Point"}
}