{
  "type": "Feature",
  "properties": {
    "addr:full":"35 Five Oaks Dr Covington GA 30014",
    "addr:housenumber":"35",
    "addr:postcode":"30014",
    "addr:street":"Five Oaks Dr",
    "iso:country":"US",
    "sg:address":"35 Five Oaks Dr",
    "sg:city":"Covington",
    "sg:classifiers":[
        {
            "category":"Transit Center",
            "subcategory":"Freight",
            "type":"Transportation"
        },
        {
            "category":"Freight",
            "type":"Transportation"
        }
    ],
    "sg:phone":"+1 770 786 9392",
    "sg:postcode":"30014",
    "sg:province":"GA",
    "sg:tags":[
        "local",
        "trucking-motor",
        "trucking"
    ],
    "wof:name":"La Kar Trucking",
    "wof:placetype":"venue"
},
  "geometry": {"coordinates":[-83.812949,33.490822],"type":"Point"}
}