{
  "type": "Feature",
  "properties": {
    "iso:country":"US",
    "sg:address":"130 Cypress Hill Rd",
    "sg:city":"Cordele",
    "sg:classifiers":[
        {
            "category":"Bakery",
            "type":"Food & Drink"
        }
    ],
    "sg:phone":"+1 229 276 1535",
    "sg:postcode":"31015",
    "sg:province":"GA",
    "sg:tags":[
        "cake",
        "pastry",
        "wedding"
    ],
    "wof:name":"Shannas Cakes",
    "wof:placetype":"venue"
},
  "geometry": {"coordinates":[-83.93475599999999,32.013483],"type":"Point"}
}