{
  "type": "Feature",
  "properties": {
    "iso:country":"US",
    "sg:address":"340 Lanier Ave E",
    "sg:city":"Fayetteville",
    "sg:classifiers":[
        {
            "category":"Food & Beverages",
            "subcategory":"Groceries & Convenience Stores",
            "type":"Retail Goods"
        }
    ],
    "sg:phone":"+1 770 461 3499",
    "sg:postcode":"30214",
    "sg:province":"GA",
    "sg:website":"www.flashfoods.com",
    "wof:name":"Kwickie Flash Foods",
    "wof:placetype":"venue"
},
  "geometry": {"coordinates":[-84.449129,33.449131],"type":"Point"}
}