{
  "type": "Feature",
  "properties": {
    "addr:full":"924 Peachtree St Louisville GA 30434",
    "addr:housenumber":"924",
    "addr:postcode":"30434",
    "addr:street":"Peachtree St",
    "iso:country":"US",
    "sg:address":"924 Peachtree St",
    "sg:city":"Louisville",
    "sg:classifiers":[
        {
            "category":"Autos & Motor Vehicles",
            "subcategory":"Auto Supplies",
            "type":"Retail Goods"
        }
    ],
    "sg:phone":"+1 478 625 7258",
    "sg:postcode":"30434",
    "sg:province":"GA",
    "sg:tags":[
        "automobile",
        "part"
    ],
    "sg:website":"http://www.napaonline.com",
    "wof:name":"N APA Auto Parts",
    "wof:placetype":"venue"
},
  "geometry": {"coordinates":[-82.40551000000001,33.00605],"type":"Point"}
}