{
  "type": "Feature",
  "properties": {
    "addr:full":"930 Mulberry Cir Winder GA 30680",
    "addr:housenumber":"930",
    "addr:postcode":"30680",
    "addr:street":"Mulberry Cir",
    "iso:country":"US",
    "sg:address":"930 Mulberry Cir",
    "sg:city":"Winder",
    "sg:classifiers":[
        {
            "category":"Building & Trades",
            "subcategory":"Construction",
            "type":"Services"
        }
    ],
    "sg:phone":"+1 770 867 7440",
    "sg:postcode":"30680",
    "sg:province":"GA",
    "sg:tags":[
        "contractor"
    ],
    "wof:name":"Abbas Drywall",
    "wof:placetype":"venue"
},
  "geometry": {"coordinates":[-83.72776,34.044716],"type":"Point"}
}