{
  "type": "Feature",
  "properties": {
    "iso:country":"US",
    "sg:address":"1673 Old Blueridge Hwy",
    "sg:city":"Blairsville",
    "sg:classifiers":[
        {
            "category":"Autos & Motor Vehicles",
            "subcategory":"Auto Supplies",
            "type":"Retail Goods"
        }
    ],
    "sg:phone":"+1 706 745 6826",
    "sg:postcode":"30512",
    "sg:province":"GA",
    "sg:tags":[
        "tire"
    ],
    "wof:name":"Mack's Tire Shop",
    "wof:placetype":"venue"
},
  "geometry": {"coordinates":[-83.993419,34.850162],"type":"Point"}
}