{
  "type": "Feature",
  "properties": {
    "addr:full":"3165 Roswell Rd NE Atlanta GA 30305",
    "addr:housenumber":"3165;rd",
    "addr:postcode":"30305",
    "addr:street":"Roswell;Ne",
    "iso:country":"US",
    "sg:address":"3165 Roswell Rd NE",
    "sg:city":"Atlanta",
    "sg:classifiers":[
        {
            "category":"Building & Trades",
            "subcategory":"Locksmith",
            "type":"Services"
        }
    ],
    "sg:phone":"+1 678 369 4965",
    "sg:postcode":"30305",
    "sg:province":"GA",
    "sg:tags":[
        "key"
    ],
    "wof:name":"123 Emergency Locksmith",
    "wof:placetype":"venue"
},
  "geometry": {"coordinates":[-84.378737,33.841779],"type":"Point"}
}