{
  "type": "Feature",
  "properties": {
    "iso:country":"US",
    "sg:address":"1250 Iron Gate Blvd",
    "sg:city":"Jonesboro",
    "sg:classifiers":[
        {
            "category":"Professional",
            "subcategory":"Business Services",
            "type":"Services"
        }
    ],
    "sg:phone":"+1 770 477 7237",
    "sg:postcode":"30238",
    "sg:province":"GA",
    "sg:tags":[
        "merchant"
    ],
    "wof:name":"Vcs Enterprises",
    "wof:placetype":"venue"
},
  "geometry": {"coordinates":[-84.351579,33.473441],"type":"Point"}
}