{
  "type": "Feature",
  "properties": {
    "iso:country":"US",
    "sg:address":"1859 Austell Cir SW",
    "sg:city":"Marietta",
    "sg:classifiers":[
        {
            "category":"Shopping",
            "subcategory":"Bicycles & Sporting Goods",
            "type":"Retail Goods"
        }
    ],
    "sg:phone":"+1 770 436 1544",
    "sg:postcode":"30060",
    "sg:province":"GA",
    "wof:name":"Sports Industries Inc",
    "wof:placetype":"venue"
},
  "geometry": {"coordinates":[-84.560109,33.906622],"type":"Point"}
}