{
  "type": "Feature",
  "properties": {
    "addr:full":"1240 Cameron Creek Marietta GA 30062",
    "addr:housenumber":"1240",
    "addr:postcode":"30062",
    "addr:street":"Cameron Creek",
    "iso:country":"US",
    "sg:address":"1240 Cameron Creek",
    "sg:city":"Marietta",
    "sg:classifiers":[
        {
            "category":"Real Estate",
            "subcategory":"Real Estate Agent",
            "type":"Services"
        }
    ],
    "sg:phone":"+1 770 578 6804",
    "sg:postcode":"30062",
    "sg:province":"GA",
    "wof:name":"Investments Encore Real Estate",
    "wof:placetype":"venue"
},
  "geometry": {"coordinates":[-84.515412,33.980606],"type":"Point"}
}