{
  "type": "Feature",
  "properties": {
    "iso:country":"US",
    "sg:address":"3917 Brintons Ml",
    "sg:city":"Marietta",
    "sg:classifiers":[
        {
            "category":"Professional",
            "subcategory":"Business Services",
            "type":"Services"
        }
    ],
    "sg:phone":"+1 770 578 8398",
    "sg:postcode":"30062",
    "sg:province":"GA",
    "wof:name":"Le Designs",
    "wof:placetype":"venue"
},
  "geometry": {"coordinates":[-84.43250500000001,34.003505],"type":"Point"}
}