{
  "type": "Feature",
  "properties": {
    "iso:country":"US",
    "sg:address":"2405 Satellite Blvd",
    "sg:city":"Duluth",
    "sg:classifiers":[
        {
            "category":"Health Services",
            "subcategory":"Doctor",
            "type":"Services"
        }
    ],
    "sg:phone":"+1 770 623 0373",
    "sg:postcode":"30096",
    "sg:province":"GA",
    "sg:tags":[
        "surgeon",
        "oral"
    ],
    "wof:name":"Tissura M Nick DDS",
    "wof:placetype":"venue"
},
  "geometry": {"coordinates":[-84.09410099999999,33.973701],"type":"Point"}
}