{
  "type": "Feature",
  "properties": {
    "addr:full":"2150 E Walnut Ave Dalton GA 30721",
    "addr:housenumber":"2150",
    "addr:postcode":"30721",
    "addr:street":"E Walnut Ave",
    "iso:country":"US",
    "sg:address":"2150 E Walnut Ave",
    "sg:city":"Dalton",
    "sg:classifiers":[
        {
            "category":"Bakery",
            "type":"Food & Drink"
        }
    ],
    "sg:menulink":"http://www.allmenus.com/ga/dalton/230454-great-american-cookies/menu/",
    "sg:phone":"+1 706 226 1107",
    "sg:postcode":"30721",
    "sg:province":"GA",
    "sg:tags":[
        "american",
        "pastry"
    ],
    "wof:name":"Great American Cookies",
    "wof:placetype":"venue"
},
  "geometry": {"coordinates":[-84.933949,34.76129],"type":"Point"}
}