{
  "type": "Feature",
  "properties": {
    "iso:country":"US",
    "sg:address":"582 Twin Oak Ln",
    "sg:city":"Grovetown",
    "sg:classifiers":[
        {
            "category":"Professional",
            "subcategory":"Business Services",
            "type":"Services"
        }
    ],
    "sg:phone":"+1 706 863 6089",
    "sg:postcode":"30813",
    "sg:province":"GA",
    "wof:name":"Btm Solutions Inc",
    "wof:placetype":"venue"
},
  "geometry": {"coordinates":[-82.16663200000001,33.4746],"type":"Point"}
}