{
  "type": "Feature",
  "properties": {
    "addr:full":"4150 Berkeley Creek Dr Duluth GA 30096",
    "addr:housenumber":"4150",
    "addr:postcode":"30096",
    "addr:street":"Berkeley Creek Dr",
    "iso:country":"US",
    "sg:address":"4150 Berkeley Creek Dr",
    "sg:city":"Duluth",
    "sg:classifiers":[
        {
            "category":"Real Estate",
            "subcategory":"Real Estate Services",
            "type":"Services"
        },
        {
            "category":"Building & Trades",
            "subcategory":"Cleaning & Sanitation",
            "type":"Services"
        }
    ],
    "sg:phone":"+1 770 274 9409",
    "sg:postcode":"30096",
    "sg:province":"GA",
    "sg:tags":[
        "maintenance",
        "cleaners-interior"
    ],
    "wof:name":"Mc Mtc Inc",
    "wof:placetype":"venue"
},
  "geometry": {"coordinates":[-84.15560499999999,33.957562],"type":"Point"}
}