{
  "type": "Feature",
  "properties": {
    "iso:country":"US",
    "sg:address":"3000 Hospital Blvd",
    "sg:city":"Roswell",
    "sg:classifiers":[
        {
            "category":"Shopping",
            "subcategory":"Pharmacy",
            "type":"Retail Goods"
        }
    ],
    "sg:phone":"+1 770 751 2540",
    "sg:postcode":"30076",
    "sg:province":"GA",
    "wof:name":"Pharmacy Department",
    "wof:placetype":"venue"
},
  "geometry": {"coordinates":[-84.320691,34.06243],"type":"Point"}
}