{
  "type": "Feature",
  "properties": {
    "iso:country":"US",
    "sg:address":"1500 Jonesboro Rd SE",
    "sg:city":"Atlanta",
    "sg:classifiers":[
        {
            "category":"Manufacturing",
            "subcategory":"Chemicals & Compounds",
            "type":"Manufacturing & Wholesale Goods"
        }
    ],
    "sg:phone":"+1 404 522 8364",
    "sg:postcode":"30315",
    "sg:province":"GA",
    "sg:tags":[
        "inorganic",
        "industrial"
    ],
    "sg:website":"www.soap.com",
    "wof:name":"Hill Manufacturing Co Inc",
    "wof:placetype":"venue"
},
  "geometry": {"coordinates":[-84.382424,33.712751],"type":"Point"}
}