{
  "type": "Feature",
  "properties": {
    "addr:full":"1507 Alice St Waycross GA 31501",
    "addr:housenumber":"1507",
    "addr:postcode":"31501",
    "addr:street":"Alice St",
    "iso:country":"US",
    "sg:address":"1507 Alice St",
    "sg:city":"Waycross",
    "sg:classifiers":[
        {
            "category":"Health Services",
            "subcategory":"Doctor",
            "type":"Services"
        }
    ],
    "sg:phone":"+1 912 283 7220",
    "sg:postcode":"31501",
    "sg:province":"GA",
    "sg:tags":[
        "physician",
        "family",
        "practice",
        "surgeons",
        "medicine",
        "surgeon"
    ],
    "wof:name":"Waycross Family Practice",
    "wof:placetype":"venue"
},
  "geometry": {"coordinates":[-82.34998299999999,31.221856],"type":"Point"}
}