{
  "type": "Feature",
  "properties": {
    "addr:full":"114 New St Decatur GA 30030",
    "addr:housenumber":"114",
    "addr:postcode":"30030",
    "addr:street":"New St",
    "iso:country":"US",
    "sg:address":"114 New St",
    "sg:city":"Decatur",
    "sg:classifiers":[
        {
            "category":"Restaurant",
            "type":"Food & Drink"
        }
    ],
    "sg:menulink":"http://www.allmenus.com/ga/atlanta-decatur/256691-super-suppers/menu/",
    "sg:phone":"+1 404 372 6972",
    "sg:postcode":"30030",
    "sg:province":"GA",
    "sg:tags":[
        "new",
        "american"
    ],
    "wof:name":"Super Suppers",
    "wof:placetype":"venue"
},
  "geometry": {"coordinates":[-84.283973,33.773252],"type":"Point"}
}