{
  "type": "Feature",
  "properties": {
    "addr:full":"2385 Mitchell Rd Lawrenceville GA 30043",
    "addr:housenumber":"2385",
    "addr:postcode":"30043",
    "addr:street":"Mitchell Rd",
    "iso:country":"US",
    "sg:address":"2385 Mitchell Rd",
    "sg:city":"Lawrenceville",
    "sg:classifiers":[
        {
            "category":"Building & Trades",
            "subcategory":"Construction",
            "type":"Services"
        }
    ],
    "sg:phone":"+1 770 513 3100",
    "sg:postcode":"30043",
    "sg:province":"GA",
    "sg:tags":[
        "painter"
    ],
    "wof:name":"McB Construction Inc",
    "wof:placetype":"venue"
},
  "geometry": {"coordinates":[-83.9739,34.043999],"type":"Point"}
}