{
  "type": "Feature",
  "properties": {
    "iso:country":"US",
    "sg:address":"3411 Poplar Springs Rd",
    "sg:city":"Gainesville",
    "sg:classifiers":[
        {
            "category":"Building & Trades",
            "subcategory":"Construction",
            "type":"Services"
        }
    ],
    "sg:phone":"+1 770 287 9667",
    "sg:postcode":"30507",
    "sg:province":"GA",
    "sg:tags":[
        "contractor"
    ],
    "wof:name":"Ceiling Tech",
    "wof:placetype":"venue"
},
  "geometry": {"coordinates":[-83.847779,34.221043],"type":"Point"}
}