{
  "type": "Feature",
  "properties": {
    "iso:country":"US",
    "sg:address":"915 E Inman St",
    "sg:city":"Statesboro",
    "sg:classifiers":[
        {
            "category":"Health Services",
            "subcategory":"Doctor",
            "type":"Services"
        }
    ],
    "sg:phone":"+1 912 764 3724",
    "sg:postcode":"30458",
    "sg:province":"GA",
    "wof:name":"Richard F Marz DDS",
    "wof:placetype":"venue"
},
  "geometry": {"coordinates":[-81.7732,32.441762],"type":"Point"}
}