{
  "type": "Feature",
  "properties": {
    "addr:full":"255 Odell Rd Griffin GA 30224",
    "addr:housenumber":"255",
    "addr:postcode":"30224",
    "addr:street":"Odell Rd",
    "iso:country":"US",
    "sg:address":"255 Odell Rd",
    "sg:city":"Griffin",
    "sg:classifiers":[
        {
            "category":"Freight",
            "type":"Transportation"
        }
    ],
    "sg:phone":"+1 770 227 0270",
    "sg:postcode":"30224",
    "sg:province":"GA",
    "sg:tags":[
        "consultant"
    ],
    "wof:name":"CDO Distribution",
    "wof:placetype":"venue"
},
  "geometry": {"coordinates":[-84.290082,33.217252],"type":"Point"}
}