{
  "type": "Feature",
  "properties": {
    "iso:country":"US",
    "sg:address":"4085 Jonesboro Rd",
    "sg:city":"Union City",
    "sg:classifiers":[
        {
            "category":"Personal",
            "type":"Services"
        }
    ],
    "sg:phone":"+1 770 964 2505",
    "sg:postcode":"30291",
    "sg:province":"GA",
    "sg:tags":[
        "party",
        "planning",
        "event"
    ],
    "wof:name":"Divine Word Community Church",
    "wof:placetype":"venue"
},
  "geometry": {"coordinates":[-84.5205,33.564701],"type":"Point"}
}