{
  "type": "Feature",
  "properties": {
    "addr:full":"3131 S Main St Moultrie GA 31768",
    "addr:housenumber":"3131",
    "addr:postcode":"31768",
    "addr:street":"S Main St",
    "iso:country":"US",
    "sg:address":"3131 S Main St",
    "sg:city":"Moultrie",
    "sg:classifiers":[
        {
            "category":"Health Services",
            "subcategory":"Health Practitioner",
            "type":"Services"
        }
    ],
    "sg:phone":"+1 229 890 3553",
    "sg:postcode":"31768",
    "sg:province":"GA",
    "sg:tags":[
        "pathologist",
        "occupational",
        "therapist",
        "speech"
    ],
    "wof:name":"C R M C Occupational Therapy",
    "wof:placetype":"venue"
},
  "geometry": {"coordinates":[-83.783019,31.126478],"type":"Point"}
}