{
  "type": "Feature",
  "properties": {
    "addr:full":"37 Wagner Ln Danielsville GA 30633",
    "addr:housenumber":"37",
    "addr:postcode":"30633",
    "addr:street":"Wagner Ln",
    "iso:country":"US",
    "sg:address":"37 Wagner Ln",
    "sg:city":"Danielsville",
    "sg:classifiers":[
        {
            "category":"Government",
            "subcategory":"Fire Station",
            "type":"Public Place"
        }
    ],
    "sg:phone":"+1 706 795 0808",
    "sg:postcode":"30633",
    "sg:province":"GA",
    "sg:tags":[
        "department"
    ],
    "sg:website":"www.madisonco.us",
    "wof:name":"Madison County Fire Dept",
    "wof:placetype":"venue"
},
  "geometry": {"coordinates":[-83.223293,34.123546],"type":"Point"}
}