{
  "type": "Feature",
  "properties": {
    "addr:full":"37 Woolsey Rd Hampton GA 30228",
    "addr:housenumber":"37",
    "addr:postcode":"30228",
    "addr:street":"Woolsey Rd",
    "iso:country":"US",
    "sg:address":"37 Woolsey Rd",
    "sg:city":"Hampton",
    "sg:classifiers":[
        {
            "category":"Organizations",
            "subcategory":"Religious Organization",
            "type":"Services"
        }
    ],
    "sg:phone":"+1 770 946 3127",
    "sg:postcode":"30228",
    "sg:province":"GA",
    "sg:tags":[
        "church"
    ],
    "sg:website":"www.bereachristian.org",
    "wof:name":"Berea Christian Church",
    "wof:placetype":"venue"
},
  "geometry": {"coordinates":[-84.288087,33.382144],"type":"Point"}
}