{
  "type": "Feature",
  "properties": {
    "addr:full":"1716 Cleveland Hwy Dalton GA 30721",
    "addr:housenumber":"1716",
    "addr:postcode":"30721",
    "addr:street":"Cleveland Hwy",
    "iso:country":"US",
    "sg:address":"1716 Cleveland Hwy",
    "sg:city":"Dalton",
    "sg:classifiers":[
        {
            "category":"Insurance",
            "subcategory":"Insurance Agent",
            "type":"Services"
        }
    ],
    "sg:phone":"+1 706 259 7466",
    "sg:postcode":"30721",
    "sg:province":"GA",
    "sg:website":"www.statefarm.com",
    "wof:name":"State Farm Insurance",
    "wof:placetype":"venue"
},
  "geometry": {"coordinates":[-84.948987,34.810952],"type":"Point"}
}