{
  "type": "Feature",
  "properties": {
    "addr:full":"1502 Comfort Rd Augusta GA 30909",
    "addr:housenumber":"1502",
    "addr:postcode":"30909",
    "addr:street":"Comfort Rd",
    "iso:country":"US",
    "sg:address":"1502 Comfort Rd",
    "sg:city":"Augusta",
    "sg:classifiers":[
        {
            "category":"Education",
            "subcategory":"School",
            "type":"Public Place"
        }
    ],
    "sg:phone":"+1 706 737 7199",
    "sg:postcode":"30909",
    "sg:province":"GA",
    "sg:tags":[
        "k-",
        "private"
    ],
    "wof:name":"Richmond County Board Of Education",
    "wof:placetype":"venue"
},
  "geometry": {"coordinates":[-82.046679,33.47304],"type":"Point"}
}