{
  "type": "Feature",
  "properties": {
    "iso:country":"US",
    "sg:address":"90 Whipporwill Dr",
    "sg:city":"Warner Robins",
    "sg:classifiers":[
        {
            "category":"Building & Trades",
            "subcategory":"Construction",
            "type":"Services"
        }
    ],
    "sg:phone":"+1 478 953 1691",
    "sg:postcode":"31088",
    "sg:province":"GA",
    "sg:tags":[
        "general",
        "contractor"
    ],
    "wof:name":"Hollywood Homes",
    "wof:placetype":"venue"
},
  "geometry": {"coordinates":[-83.707053,32.589275],"type":"Point"}
}