{
  "type": "Feature",
  "properties": {
    "addr:full":"3585 Northside Dr NW Atlanta GA 30305",
    "addr:housenumber":"3585",
    "addr:postcode":"30305",
    "addr:street":"Northside Dr Nw",
    "iso:country":"US",
    "sg:address":"3585 Northside Dr NW",
    "sg:city":"Atlanta",
    "sg:classifiers":[
        {
            "category":"Professional",
            "subcategory":"Business Services",
            "type":"Services"
        }
    ],
    "sg:phone":"+1 404 239 9926",
    "sg:postcode":"30305",
    "sg:province":"GA",
    "wof:name":"Truck Show Group LLC",
    "wof:placetype":"venue"
},
  "geometry": {"coordinates":[-84.40716,33.849869],"type":"Point"}
}