{
  "type": "Feature",
  "properties": {
    "addr:full":"245 Wimberly Hill Rd Cedartown GA 30125",
    "addr:housenumber":"245",
    "addr:postcode":"30125",
    "addr:street":"Wimberly Hill Rd",
    "iso:country":"US",
    "sg:address":"245 Wimberly Hill Rd",
    "sg:city":"Cedartown",
    "sg:classifiers":[
        {
            "category":"Home & Garden",
            "subcategory":"Furniture",
            "type":"Retail Goods"
        }
    ],
    "sg:phone":"+1 770 748 8073",
    "sg:postcode":"30125",
    "sg:province":"GA",
    "sg:tags":[
        "cabinet",
        "made",
        "door",
        "maker",
        "custom"
    ],
    "wof:name":"Custom Crafted Doors",
    "wof:placetype":"venue"
},
  "geometry": {"coordinates":[-85.17191200000001,34.017968],"type":"Point"}
}