{
  "type": "Feature",
  "properties": {
    "iso:country":"US",
    "sg:address":"1230 Johnson Ferry Rd",
    "sg:city":"Marietta",
    "sg:classifiers":[
        {
            "category":"Manufacturing",
            "subcategory":"Tools & Machinery",
            "type":"Manufacturing & Wholesale Goods"
        }
    ],
    "sg:phone":"+1 770 509 1808",
    "sg:postcode":"30068",
    "sg:province":"GA",
    "sg:tags":[
        "process",
        "control",
        "mfg",
        "instrument"
    ],
    "wof:name":"T D H Company L L C",
    "wof:placetype":"venue"
},
  "geometry": {"coordinates":[-84.420405,33.979078],"type":"Point"}
}