{
  "type": "Feature",
  "properties": {
    "addr:full":"3201 Macon Rd Columbus GA 31906",
    "addr:housenumber":"3201",
    "addr:postcode":"31906",
    "addr:street":"Macon Rd",
    "iso:country":"US",
    "sg:address":"3201 Macon Rd",
    "sg:city":"Columbus",
    "sg:classifiers":[
        {
            "category":"Shopping",
            "subcategory":"Clothing, Apparel, & Fashions",
            "type":"Retail Goods"
        }
    ],
    "sg:phone":"+1 706 569 7490",
    "sg:postcode":"31906",
    "sg:province":"GA",
    "sg:tags":[
        "store"
    ],
    "wof:name":"Fashion Bug",
    "wof:placetype":"venue"
},
  "geometry": {"coordinates":[-84.94359300000001,32.480156],"type":"Point"}
}