{
  "type": "Feature",
  "properties": {
    "addr:full":"295 S Macon St Jesup GA 31545",
    "addr:housenumber":"295",
    "addr:postcode":"31545",
    "addr:street":"S Macon St",
    "iso:country":"US",
    "sg:address":"295 S Macon St",
    "sg:city":"Jesup",
    "sg:classifiers":[
        {
            "category":"Insurance",
            "subcategory":"Insurance Agent",
            "type":"Services"
        }
    ],
    "sg:phone":"+1 912 427 2064",
    "sg:postcode":"31545",
    "sg:province":"GA",
    "wof:name":"Kicklighter Insurance",
    "wof:placetype":"venue"
},
  "geometry": {"coordinates":[-81.886314,31.604322],"type":"Point"}
}