{
  "type": "Feature",
  "properties": {
    "iso:country":"US",
    "sg:address":"121 N Main St",
    "sg:city":"Jonesboro",
    "sg:classifiers":[
        {
            "category":"Real Estate",
            "subcategory":"Surveying",
            "type":"Services"
        },
        {
            "category":"Real Estate",
            "subcategory":"Real Estate Agent",
            "type":"Services"
        }
    ],
    "sg:phone":"+1 770 471 4420",
    "sg:postcode":"30236",
    "sg:province":"GA",
    "wof:name":"Franks & Associates",
    "wof:placetype":"venue"
},
  "geometry": {"coordinates":[-84.35453099999999,33.520863],"type":"Point"}
}