{
  "type": "Feature",
  "properties": {
    "iso:country":"US",
    "sg:address":"3404 Victory Dr",
    "sg:city":"Columbus",
    "sg:classifiers":[
        {
            "category":"Organizations",
            "subcategory":"Religious Organization",
            "type":"Services"
        }
    ],
    "sg:phone":"+1 706 689 8076",
    "sg:postcode":"31903",
    "sg:province":"GA",
    "sg:tags":[
        "church"
    ],
    "wof:name":"New Bethel AME Church",
    "wof:placetype":"venue"
},
  "geometry": {"coordinates":[-84.94999799999999,32.427154],"type":"Point"}
}