{
  "type": "Feature",
  "properties": {
    "iso:country":"US",
    "sg:address":"1293 2nd Ave SW",
    "sg:city":"Cairo",
    "sg:classifiers":[
        {
            "category":"Social Services",
            "subcategory":"Child Care",
            "type":"Services"
        }
    ],
    "sg:phone":"+1 229 377 9776",
    "sg:postcode":"39828",
    "sg:province":"GA",
    "sg:tags":[
        "day"
    ],
    "wof:name":"Paramore Pre-School Academy",
    "wof:placetype":"venue"
},
  "geometry": {"coordinates":[-84.22447099999999,30.875875],"type":"Point"}
}