{
  "type": "Feature",
  "properties": {
    "addr:full":"3650 Jonesboro Rd Fairburn GA 30213",
    "addr:housenumber":"3650",
    "addr:postcode":"30213",
    "addr:street":"Jonesboro Rd",
    "iso:country":"US",
    "sg:address":"3650 Jonesboro Rd",
    "sg:city":"Fairburn",
    "sg:classifiers":[
        {
            "category":"Organizations",
            "subcategory":"Religious Organization",
            "type":"Services"
        }
    ],
    "sg:phone":"+1 770 969 0120",
    "sg:postcode":"30213",
    "sg:province":"GA",
    "sg:tags":[
        "church"
    ],
    "wof:name":"Word Of Love Christian Church",
    "wof:placetype":"venue"
},
  "geometry": {"coordinates":[-84.51372499999999,33.559365],"type":"Point"}
}