{
  "type": "Feature",
  "properties": {
    "iso:country":"US",
    "sg:address":"6423 Williamsburg Dr",
    "sg:city":"Columbus",
    "sg:classifiers":[
        {
            "category":"Professional",
            "type":"Services"
        }
    ],
    "sg:phone":"+1 706 569 0454",
    "sg:postcode":"31909",
    "sg:province":"GA",
    "wof:name":"Eric Parham",
    "wof:placetype":"venue"
},
  "geometry": {"coordinates":[-84.900187,32.537056],"type":"Point"}
}