{
  "type": "Feature",
  "properties": {
    "addr:full":"4050 Palisades Main Kennesaw GA 30144",
    "addr:housenumber":"4050",
    "addr:postcode":"30144",
    "addr:street":"Palisades Main",
    "iso:country":"US",
    "sg:address":"4050 Palisades Main",
    "sg:city":"Kennesaw",
    "sg:classifiers":[
        {
            "category":"Professional",
            "subcategory":"Management & Consulting",
            "type":"Services"
        }
    ],
    "sg:phone":"+1 678 354 2161",
    "sg:postcode":"30144",
    "sg:province":"GA",
    "sg:tags":[
        "modeling",
        "product",
        "technology",
        "business"
    ],
    "wof:name":"Simon Labs Inc",
    "wof:placetype":"venue"
},
  "geometry": {"coordinates":[-84.633037,34.051106],"type":"Point"}
}