{
  "type": "Feature",
  "properties": {
    "iso:country":"US",
    "sg:address":"422 Wilson Rd",
    "sg:city":"Griffin",
    "sg:classifiers":[
        {
            "category":"Building & Trades",
            "subcategory":"Construction",
            "type":"Services"
        }
    ],
    "sg:phone":"+1 770 567 1367",
    "sg:postcode":"30223",
    "sg:province":"GA",
    "sg:tags":[
        "maker",
        "cabinet"
    ],
    "wof:name":"Southern Custom",
    "wof:placetype":"venue"
},
  "geometry": {"coordinates":[-84.232789,33.228269],"type":"Point"}
}