{
  "type": "Feature",
  "properties": {
    "iso:country":"US",
    "sg:address":"14492 Club Cir",
    "sg:city":"Alpharetta",
    "sg:classifiers":[
        {
            "category":"Manufacturing",
            "subcategory":"Apparel",
            "type":"Manufacturing & Wholesale Goods"
        }
    ],
    "sg:phone":"+1 770 752 7636",
    "sg:postcode":"30004",
    "sg:province":"GA",
    "sg:tags":[
        "outerwear",
        "mfg"
    ],
    "wof:name":"Net Designs",
    "wof:placetype":"venue"
},
  "geometry": {"coordinates":[-84.268722,34.139123],"type":"Point"}
}