{
  "type": "Feature",
  "properties": {
    "iso:country":"US",
    "sg:address":"605 Best Friend Ct",
    "sg:city":"Norcross",
    "sg:classifiers":[
        {
            "category":"Shopping",
            "subcategory":"Shoes",
            "type":"Retail Goods"
        }
    ],
    "sg:phone":"+1 770 368 1288",
    "sg:postcode":"30071",
    "sg:province":"GA",
    "sg:tags":[
        "store"
    ],
    "wof:name":"Max Trading Company",
    "wof:placetype":"venue"
},
  "geometry": {"coordinates":[-84.224841,33.921427],"type":"Point"}
}