{
  "type": "Feature",
  "properties": {
    "addr:full":"11810 Wills Road Alpharetta GA 30009",
    "addr:housenumber":"11810",
    "addr:postcode":"30009",
    "addr:street":"Wills Road",
    "iso:country":"US",
    "sg:address":"11810 Wills Road",
    "sg:city":"Alpharetta",
    "sg:classifiers":[
        {
            "category":"Professional",
            "subcategory":"Management & Consulting",
            "type":"Services"
        }
    ],
    "sg:phone":"+1 678 990 7868",
    "sg:postcode":"30009",
    "sg:province":"GA",
    "sg:tags":[
        "supplies-installs-maintains-equipment-systems-commercial-industrial-facilities"
    ],
    "sg:website":"http://iplex.com/",
    "wof:name":"Industriaplex",
    "wof:placetype":"venue"
},
  "geometry": {"coordinates":[-84.309451,34.058412],"type":"Point"}
}