{
  "type": "Feature",
  "properties": {
    "addr:full":"1715 Hemingway Ln Roswell GA 30075",
    "addr:housenumber":"1715",
    "addr:postcode":"30075",
    "addr:street":"Hemingway Ln",
    "iso:country":"US",
    "sg:address":"1715 Hemingway Ln",
    "sg:city":"Roswell",
    "sg:classifiers":[
        {
            "category":"Building & Trades",
            "subcategory":"Landscaping Services",
            "type":"Services"
        }
    ],
    "sg:phone":"+1 678 352 9449",
    "sg:postcode":"30075",
    "sg:province":"GA",
    "sg:tags":[
        "landscape",
        "contractor"
    ],
    "wof:name":"T C's Landscaping",
    "wof:placetype":"venue"
},
  "geometry": {"coordinates":[-84.333915,34.020985],"type":"Point"}
}