{
  "type": "Feature",
  "properties": {
    "iso:country":"US",
    "sg:address":"21 Cedar Run",
    "sg:city":"Atlanta",
    "sg:classifiers":[
        {
            "category":"Retail",
            "subcategory":"Auto Repair",
            "type":"Services"
        }
    ],
    "sg:phone":"+1 404 454 2565",
    "sg:postcode":"30350",
    "sg:province":"GA",
    "sg:tags":[
        "wrecker"
    ],
    "wof:name":"H D Towing",
    "wof:placetype":"venue"
},
  "geometry": {"coordinates":[-84.345344,33.992922],"type":"Point"}
}