{
  "type": "Feature",
  "properties": {
    "iso:country":"US",
    "sg:address":"7214 Douglas Blvd",
    "sg:city":"Douglasville",
    "sg:classifiers":[
        {
            "category":"Personal",
            "subcategory":"Barber",
            "type":"Services"
        }
    ],
    "sg:phone":"+1 770 942 5099",
    "sg:postcode":"30135",
    "sg:province":"GA",
    "wof:name":"Jenkins Barber Shop",
    "wof:placetype":"venue"
},
  "geometry": {"coordinates":[-84.745339,33.73023],"type":"Point"}
}