{
  "type": "Feature",
  "properties": {
    "addr:full":"180 Old Alma Waycross Hwy Nicholls GA 31554",
    "addr:housenumber":"180",
    "addr:postcode":"31554",
    "addr:street":"Old Alma Waycross Hwy",
    "iso:country":"US",
    "sg:address":"180 Old Alma Waycross Hwy",
    "sg:city":"Nicholls",
    "sg:classifiers":[
        {
            "category":"Farming",
            "subcategory":"Poultry Farm",
            "type":"Manufacturing & Wholesale Goods"
        }
    ],
    "sg:phone":"+1 912 632 5799",
    "sg:postcode":"31554",
    "sg:province":"GA",
    "sg:tags":[
        "hatchery"
    ],
    "wof:name":"Steven Lee",
    "wof:placetype":"venue"
},
  "geometry": {"coordinates":[-82.45686000000001,31.45653],"type":"Point"}
}