{
  "type": "Feature",
  "properties": {
    "iso:country":"US",
    "sg:address":"670 Northern Ave",
    "sg:city":"Clarkston",
    "sg:classifiers":[
        {
            "category":"Building & Trades",
            "subcategory":"Equipment Rental",
            "type":"Services"
        }
    ],
    "sg:phone":"+1 404 812 0194",
    "sg:postcode":"30021",
    "sg:province":"GA",
    "sg:tags":[
        "field",
        "oil"
    ],
    "wof:name":"Atlanta Renewable Energy Inc.",
    "wof:placetype":"venue"
},
  "geometry": {"coordinates":[-84.246251,33.794822],"type":"Point"}
}