{
  "type": "Feature",
  "properties": {
    "addr:full":"3751 Longmire Way Atlanta GA 30340",
    "addr:housenumber":"3751",
    "addr:postcode":"30340",
    "addr:street":"Longmire Way",
    "iso:country":"US",
    "sg:address":"3751 Longmire Way",
    "sg:city":"Atlanta",
    "sg:classifiers":[
        {
            "category":"Freight",
            "type":"Transportation"
        }
    ],
    "sg:phone":"+1 770 457 4852",
    "sg:postcode":"30340",
    "sg:province":"GA",
    "sg:tags":[
        "warehouse",
        "self",
        "storage",
        "warehouses-public-commercial"
    ],
    "wof:name":"Colonial Storage Centers",
    "wof:placetype":"venue"
},
  "geometry": {"coordinates":[-84.271934,33.906199],"type":"Point"}
}