{
  "type": "Feature",
  "properties": {
    "addr:full":"10423 Flat Shoals Rd Covington GA 30014",
    "addr:housenumber":"10423",
    "addr:postcode":"30014",
    "addr:street":"Flat Shoals Rd",
    "iso:country":"US",
    "sg:address":"10423 Flat Shoals Rd",
    "sg:city":"Covington",
    "sg:classifiers":[
        {
            "category":"Restaurant",
            "type":"Food & Drink"
        }
    ],
    "sg:phone":"+1 770 787 4118",
    "sg:postcode":"30014",
    "sg:province":"GA",
    "sg:tags":[
        "eating"
    ],
    "wof:name":"Family Fare Restaurant",
    "wof:placetype":"venue"
},
  "geometry": {"coordinates":[-83.872196,33.568422],"type":"Point"}
}