{
  "type": "Feature",
  "properties": {
    "iso:country":"US",
    "sg:address":"1776 Iris Dr SW",
    "sg:city":"Conyers",
    "sg:classifiers":[
        {
            "category":"Autos & Motor Vehicles",
            "subcategory":"Automobile Sales",
            "type":"Retail Goods"
        }
    ],
    "sg:phone":"+1 770 929 8545",
    "sg:postcode":"30094",
    "sg:province":"GA",
    "sg:tags":[
        "used"
    ],
    "wof:name":"Save More Auto Sales",
    "wof:placetype":"venue"
},
  "geometry": {"coordinates":[-84.04366,33.669748],"type":"Point"}
}