{
  "type": "Feature",
  "properties": {
    "addr:full":"1895 Highway 20 SE Conyers GA 30013",
    "addr:housenumber":"1895",
    "addr:postcode":"30013",
    "addr:street":"Highway 20 Se",
    "iso:country":"US",
    "sg:address":"1895 Highway 20 SE",
    "sg:city":"Conyers",
    "sg:classifiers":[
        {
            "category":"Personal",
            "subcategory":"Massage",
            "type":"Services"
        },
        {
            "category":"Sports & Exercise",
            "subcategory":"Gym",
            "type":"Entertainment"
        },
        {
            "category":"Health Services",
            "subcategory":"Chiropractor",
            "type":"Services"
        }
    ],
    "sg:phone":"+1 770 922 8150",
    "sg:postcode":"30013",
    "sg:province":"GA",
    "sg:tags":[
        "yoga"
    ],
    "wof:name":"Byrd Kasie Cmt",
    "wof:placetype":"venue"
},
  "geometry": {"coordinates":[-84.014297,33.633499],"type":"Point"}
}