{
  "type": "Feature",
  "properties": {
    "iso:country":"US",
    "sg:address":"315 Loch Haven Dr SE",
    "sg:city":"Conyers",
    "sg:classifiers":[
        {
            "category":"Professional",
            "subcategory":"Management & Consulting",
            "type":"Services"
        }
    ],
    "sg:phone":"+1 770 761 7790",
    "sg:postcode":"30013",
    "sg:province":"GA",
    "wof:name":"3h Marketing & Public Relation",
    "wof:placetype":"venue"
},
  "geometry": {"coordinates":[-83.980852,33.623411],"type":"Point"}
}