{
  "type": "Feature",
  "properties": {
    "addr:full":"1810 Annwicks Dr Marietta GA 30062",
    "addr:housenumber":"1810",
    "addr:postcode":"30062",
    "addr:street":"Annwicks Dr",
    "iso:country":"US",
    "sg:address":"1810 Annwicks Dr",
    "sg:city":"Marietta",
    "sg:classifiers":[
        {
            "category":"Banks & Credit Unions",
            "subcategory":"Financial Services",
            "type":"Services"
        }
    ],
    "sg:phone":"+1 770 971 8308",
    "sg:postcode":"30062",
    "sg:province":"GA",
    "sg:tags":[
        "investor"
    ],
    "wof:name":"Capital Compliance Inc",
    "wof:placetype":"venue"
},
  "geometry": {"coordinates":[-84.456188,33.995998],"type":"Point"}
}