{
  "type": "Feature",
  "properties": {
    "addr:full":"657 Red Oak Rd Stockbridge GA 30281",
    "addr:housenumber":"657",
    "addr:postcode":"30281",
    "addr:street":"Red Oak Rd",
    "iso:country":"US",
    "sg:address":"657 Red Oak Rd",
    "sg:city":"Stockbridge",
    "sg:classifiers":[
        {
            "category":"Building & Trades",
            "subcategory":"Electrical",
            "type":"Services"
        }
    ],
    "sg:phone":"+1 678 289 9168",
    "sg:postcode":"30281",
    "sg:province":"GA",
    "sg:tags":[
        "electrician"
    ],
    "wof:name":"Grace Electric Inc",
    "wof:placetype":"venue"
},
  "geometry": {"coordinates":[-84.228711,33.527863],"type":"Point"}
}