{
  "type": "Feature",
  "properties": {
    "addr:full":"411 N Jefferson St NE Milledgeville GA 31061",
    "addr:housenumber":"411",
    "addr:postcode":"31061",
    "addr:street":"N Jefferson St Ne",
    "iso:country":"US",
    "sg:address":"411 N Jefferson St NE",
    "sg:city":"Milledgeville",
    "sg:classifiers":[
        {
            "category":"Health Services",
            "subcategory":"Clinic",
            "type":"Services"
        },
        {
            "category":"Health Services",
            "subcategory":"Hospital",
            "type":"Services"
        }
    ],
    "sg:phone":"+1 478 453 0964",
    "sg:postcode":"31061",
    "sg:province":"GA",
    "sg:tags":[
        "medical",
        "dialysis"
    ],
    "wof:name":"Fresenius Medical Care Milledg",
    "wof:placetype":"venue"
},
  "geometry": {"coordinates":[-83.226619,33.085899],"type":"Point"}
}