{
  "type": "Feature",
  "properties": {
    "addr:full":"2054 3rd Ave Augusta GA 30901",
    "addr:housenumber":"2054",
    "addr:postcode":"30901",
    "addr:street":"3Rd Ave",
    "iso:country":"US",
    "sg:address":"2054 3rd Ave",
    "sg:city":"Augusta",
    "sg:classifiers":[
        {
            "category":"Building & Trades",
            "subcategory":"Cleaning & Sanitation",
            "type":"Services"
        }
    ],
    "sg:phone":"+1 706 722 7374",
    "sg:postcode":"30901",
    "sg:province":"GA",
    "sg:tags":[
        "janitor"
    ],
    "wof:name":"Bostic Cleaning Supplies",
    "wof:placetype":"venue"
},
  "geometry": {"coordinates":[-81.99852199999999,33.441789],"type":"Point"}
}