{
  "type": "Feature",
  "properties": {
    "iso:country":"US",
    "sg:address":"4168 Azalea Ct",
    "sg:city":"Snellville",
    "sg:classifiers":[
        {
            "category":"Wholesale",
            "subcategory":"Construction Materials",
            "type":"Manufacturing & Wholesale Goods"
        }
    ],
    "sg:phone":"+1 770 985 1055",
    "sg:postcode":"30039",
    "sg:province":"GA",
    "sg:tags":[
        "tank",
        "system",
        "septic"
    ],
    "wof:name":"Infiltrator Systems",
    "wof:placetype":"venue"
},
  "geometry": {"coordinates":[-84.015393,33.792676],"type":"Point"}
}