{
  "type": "Feature",
  "properties": {
    "iso:country":"US",
    "sg:address":"3001 Wembley Ridge",
    "sg:city":"Atlanta",
    "sg:classifiers":[
        {
            "category":"Professional",
            "subcategory":"Computer Services",
            "type":"Services"
        }
    ],
    "sg:phone":"+1 770 414 4142",
    "sg:postcode":"30340",
    "sg:province":"GA",
    "sg:tags":[
        "prepackaged",
        "software"
    ],
    "wof:name":"RAO Software & Engineering",
    "wof:placetype":"venue"
},
  "geometry": {"coordinates":[-84.225396,33.878698],"type":"Point"}
}