{
  "type": "Feature",
  "properties": {
    "iso:country":"US",
    "sg:address":"1660 N Milford Creek Ln SW",
    "sg:city":"Marietta",
    "sg:classifiers":[
        {
            "category":"Professional",
            "subcategory":"Engineering",
            "type":"Services"
        },
        {
            "category":"Professional",
            "subcategory":"Management & Consulting",
            "type":"Services"
        }
    ],
    "sg:phone":"+1 770 434 2504",
    "sg:postcode":"30008",
    "sg:province":"GA",
    "sg:tags":[
        "business",
        "engineer"
    ],
    "wof:name":"Middleton Consulting",
    "wof:placetype":"venue"
},
  "geometry": {"coordinates":[-84.60344000000001,33.879716],"type":"Point"}
}