{
  "type": "Feature",
  "properties": {
    "iso:country":"US",
    "sg:address":"1587 Olympian Cir SW",
    "sg:city":"Atlanta",
    "sg:classifiers":[
        {
            "category":"Organizations",
            "subcategory":"Professional Association",
            "type":"Services"
        }
    ],
    "sg:phone":"+1 678 334 5779",
    "sg:postcode":"30310",
    "sg:province":"GA",
    "sg:tags":[
        "business",
        "trade"
    ],
    "wof:name":"Uniq Tech",
    "wof:placetype":"venue"
},
  "geometry": {"coordinates":[-84.440173,33.735308],"type":"Point"}
}