{
  "type": "Feature",
  "properties": {
    "addr:full":"4372 Shallowford Rd Indstryh Marietta GA 30062",
    "addr:housenumber":"4372",
    "addr:postcode":"30062",
    "addr:street":"Shallowford Rd Indstryh",
    "iso:country":"US",
    "sg:address":"4372 Shallowford Rd Indstryh",
    "sg:city":"Marietta",
    "sg:classifiers":[
        {
            "category":"Communications",
            "type":"Services"
        },
        {
            "category":"Shopping",
            "subcategory":"Computers & Home Electronics",
            "type":"Retail Goods"
        }
    ],
    "sg:phone":"+1 770 591 1441",
    "sg:postcode":"30062",
    "sg:province":"GA",
    "sg:tags":[
        "sound",
        "television",
        "system",
        "equipment",
        "radio",
        "store"
    ],
    "wof:name":"The Geek Mart Com",
    "wof:placetype":"venue"
},
  "geometry": {"coordinates":[-84.42432700000001,34.027353],"type":"Point"}
}