{
  "type": "Feature",
  "properties": {
    "iso:country":"US",
    "sg:address":"65 Railroad St NW",
    "sg:city":"Lilburn",
    "sg:classifiers":[
        {
            "category":"Building & Trades",
            "subcategory":"Construction",
            "type":"Services"
        }
    ],
    "sg:phone":"+1 770 921 4150",
    "sg:postcode":"30047",
    "sg:province":"GA",
    "sg:tags":[
        "floor",
        "laying",
        "contractor"
    ],
    "wof:name":"A Floor Covering & Design Co",
    "wof:placetype":"venue"
},
  "geometry": {"coordinates":[-84.134677,33.886123],"type":"Point"}
}