{
  "type": "Feature",
  "properties": {
    "addr:full":"409 Blanchard Rd Evans GA 30809",
    "addr:housenumber":"409",
    "addr:postcode":"30809",
    "addr:street":"Blanchard Rd",
    "iso:country":"US",
    "sg:address":"409 Blanchard Rd",
    "sg:city":"Evans",
    "sg:classifiers":[
        {
            "category":"Manufacturing",
            "subcategory":"Apparel",
            "type":"Manufacturing & Wholesale Goods"
        }
    ],
    "sg:phone":"+1 706 860 8917",
    "sg:postcode":"30809",
    "sg:province":"GA",
    "sg:tags":[
        "flag",
        "banner"
    ],
    "wof:name":"Georgia Flag & Pennant Mfg",
    "wof:placetype":"venue"
},
  "geometry": {"coordinates":[-82.167153,33.532922],"type":"Point"}
}