{
  "type": "Feature",
  "properties": {
    "iso:country":"US",
    "sg:address":"2465 N Columbia St",
    "sg:city":"Milledgeville",
    "sg:classifiers":[
        {
            "category":"Restaurant",
            "type":"Food & Drink"
        }
    ],
    "sg:phone":"+1 478 453 0027",
    "sg:postcode":"31061",
    "sg:province":"GA",
    "sg:tags":[
        "mexican"
    ],
    "wof:name":"Amigo Mexican Restaurant",
    "wof:placetype":"venue"
},
  "geometry": {"coordinates":[-83.27066000000001,33.138489],"type":"Point"}
}