{
  "type": "Feature",
  "properties": {
    "addr:full":"217 Morning Mist Way Woodstock GA 30189",
    "addr:housenumber":"217",
    "addr:postcode":"30189",
    "addr:street":"Morning Mist Way",
    "iso:country":"US",
    "sg:address":"217 Morning Mist Way",
    "sg:city":"Woodstock",
    "sg:classifiers":[
        {
            "category":"Professional",
            "subcategory":"Business Services",
            "type":"Services"
        }
    ],
    "sg:phone":"+1 770 926 3621",
    "sg:postcode":"30189",
    "sg:province":"GA",
    "wof:name":"Disaster Resource Management",
    "wof:placetype":"venue"
},
  "geometry": {"coordinates":[-84.56211500000001,34.130545],"type":"Point"}
}