{
  "type": "Feature",
  "properties": {
    "addr:full":"Perimeter Mall Atlanta GA 30346",
    "addr:postcode":"30346",
    "iso:country":"US",
    "sg:address":"Perimeter Mall",
    "sg:city":"Atlanta",
    "sg:classifiers":[
        {
            "category":"Utilities",
            "type":"Services"
        }
    ],
    "sg:phone":"+1 404 592 2740",
    "sg:postcode":"30346",
    "sg:province":"GA",
    "sg:tags":[
        "provider",
        "internet"
    ],
    "sg:website":"www.clear.com/landing/state/GA",
    "wof:name":"Clear Internet",
    "wof:placetype":"venue"
},
  "geometry": {"coordinates":[-84.34171600000001,33.923985],"type":"Point"}
}