{
  "type": "Feature",
  "properties": {
    "addr:full":"3263 Hickory Bluff Dr Marietta GA 30062",
    "addr:housenumber":"3263",
    "addr:postcode":"30062",
    "addr:street":"Hickory Bluff Dr",
    "iso:country":"US",
    "sg:address":"3263 Hickory Bluff Dr",
    "sg:city":"Marietta",
    "sg:classifiers":[
        {
            "category":"Insurance",
            "subcategory":"Insurance Agent",
            "type":"Services"
        }
    ],
    "sg:phone":"+1 770 565 6767",
    "sg:postcode":"30062",
    "sg:province":"GA",
    "sg:tags":[
        "broker"
    ],
    "wof:name":"Randall Cameron & Associates",
    "wof:placetype":"venue"
},
  "geometry": {"coordinates":[-84.449061,34.030283],"type":"Point"}
}