{
  "type": "Feature",
  "properties": {
    "addr:full":"2408 Young Dr Augusta GA 30906",
    "addr:housenumber":"2408",
    "addr:postcode":"30906",
    "addr:street":"Young Dr",
    "iso:country":"US",
    "sg:address":"2408 Young Dr",
    "sg:city":"Augusta",
    "sg:classifiers":[
        {
            "category":"Building & Trades",
            "subcategory":"Construction",
            "type":"Services"
        }
    ],
    "sg:phone":"+1 706 364 9128",
    "sg:postcode":"30906",
    "sg:province":"GA",
    "sg:tags":[
        "concrete",
        "contractor"
    ],
    "wof:name":"Smalls Construction Co",
    "wof:placetype":"venue"
},
  "geometry": {"coordinates":[-82.036833,33.423215],"type":"Point"}
}