{
  "type": "Feature",
  "properties": {
    "iso:country":"US",
    "sg:address":"2280 Reinhardt College Pkwy",
    "sg:city":"Canton",
    "sg:classifiers":[
        {
            "category":"Place Of Worship",
            "subcategory":"Church",
            "type":"Public Place"
        },
        {
            "category":"Place Of Worship",
            "type":"Public Place"
        }
    ],
    "sg:phone":"+1 770 720 3429",
    "sg:postcode":"30114",
    "sg:province":"GA",
    "sg:tags":[
        "churches-baptist-general",
        "churches-baptist"
    ],
    "sg:website":"http://www.olivineband.com",
    "wof:name":"Olivine Baptist Church",
    "wof:placetype":"venue"
},
  "geometry": {"coordinates":[-84.510462,34.281782],"type":"Point"}
}