{
  "type": "Feature",
  "properties": {
    "iso:country":"US",
    "sg:address":"400 Indeco Blvd SW",
    "sg:city":"Atlanta",
    "sg:classifiers":[
        {
            "category":"Retail",
            "subcategory":"Storage",
            "type":"Services"
        }
    ],
    "sg:phone":"+1 404 505 9456",
    "sg:postcode":"30336",
    "sg:province":"GA",
    "sg:tags":[
        "plastics-containers"
    ],
    "wof:name":"Continental Plastic Container",
    "wof:placetype":"venue"
},
  "geometry": {"coordinates":[-84.553009,33.74456],"type":"Point"}
}