{
  "type": "Feature",
  "properties": {
    "iso:country":"US",
    "sg:address":"421 Augusta Rd",
    "sg:city":"North Augusta",
    "sg:classifiers":[
        {
            "category":"Food & Beverages",
            "subcategory":"Groceries & Convenience Stores",
            "type":"Retail Goods"
        }
    ],
    "sg:phone":"+1 803 442 7109",
    "sg:postcode":"29822",
    "sg:province":"SC",
    "wof:name":"Kangaroo Express",
    "wof:placetype":"venue"
},
  "geometry": {"coordinates":[-81.892059,33.496703],"type":"Point"}
}