{
  "type": "Feature",
  "properties": {
    "addr:full":"2301 Bull St Savannah GA 31401",
    "addr:housenumber":"2301",
    "addr:postcode":"31401",
    "addr:street":"Bull St",
    "iso:country":"US",
    "sg:address":"2301 Bull St",
    "sg:city":"Savannah",
    "sg:classifiers":[
        {
            "category":"Government",
            "subcategory":"Office",
            "type":"Public Place"
        }
    ],
    "sg:phone":"+1 912 790 3400",
    "sg:postcode":"31401",
    "sg:province":"GA",
    "sg:website":"www.homelessauthority.org",
    "wof:name":"Homeless Authority",
    "wof:placetype":"venue"
},
  "geometry": {"coordinates":[-81.10113200000001,32.054944],"type":"Point"}
}