{
  "type": "Feature",
  "properties": {
    "addr:full":"202 W Screven St Quitman GA 31643",
    "addr:housenumber":"202",
    "addr:postcode":"31643",
    "addr:street":"W Screven St",
    "iso:country":"US",
    "sg:address":"202 W Screven St",
    "sg:city":"Quitman",
    "sg:classifiers":[
        {
            "category":"Professional",
            "subcategory":"Lawyer & Legal Services",
            "type":"Services"
        }
    ],
    "sg:phone":"+1 229 263 8833",
    "sg:postcode":"31643",
    "sg:province":"GA",
    "sg:tags":[
        "attorney",
        "practice"
    ],
    "wof:name":"Long, Denton Attorneys At Law Llp",
    "wof:placetype":"venue"
},
  "geometry": {"coordinates":[-83.56104499999999,30.784926],"type":"Point"}
}