{
  "type": "Feature",
  "properties": {
    "iso:country":"US",
    "sg:address":"2204 Spear Point Dr",
    "sg:city":"Marietta",
    "sg:classifiers":[
        {
            "category":"Professional",
            "subcategory":"Business Services",
            "type":"Services"
        }
    ],
    "sg:phone":"+1 770 335 6018",
    "sg:postcode":"30062",
    "sg:province":"GA",
    "wof:name":"Knowledge Testing Services Ltd",
    "wof:placetype":"venue"
},
  "geometry": {"coordinates":[-84.474475,34.003],"type":"Point"}
}