{
  "type": "Feature",
  "properties": {
    "iso:country":"US",
    "sg:address":"3175 Frontage Rd",
    "sg:city":"Gainesville",
    "sg:classifiers":[
        {
            "category":"Restaurant",
            "type":"Food & Drink"
        }
    ],
    "sg:menulink":"http://www.allmenus.com/ga/oakwood/242025-wafflehouse/menu/",
    "sg:phone":"+1 770 531 0837",
    "sg:postcode":"30504",
    "sg:province":"GA",
    "sg:tags":[
        "american"
    ],
    "wof:name":"Wafflehouse",
    "wof:placetype":"venue"
},
  "geometry": {"coordinates":[-83.86579399999999,34.227843],"type":"Point"}
}