{
  "type": "Feature",
  "properties": {
    "addr:full":"200 Cedar Ridge Dr Perry GA 31069",
    "addr:housenumber":"200",
    "addr:postcode":"31069",
    "addr:street":"Cedar Ridge Dr",
    "iso:country":"US",
    "sg:address":"200 Cedar Ridge Dr",
    "sg:city":"Perry",
    "sg:classifiers":[
        {
            "category":"Banks & Credit Unions",
            "subcategory":"Financial Services",
            "type":"Services"
        }
    ],
    "sg:phone":"+1 478 987 7982",
    "sg:postcode":"31069",
    "sg:province":"GA",
    "sg:tags":[
        "investment",
        "closed"
    ],
    "wof:name":"Primerica",
    "wof:placetype":"venue"
},
  "geometry": {"coordinates":[-83.723203,32.47922],"type":"Point"}
}