{
  "type": "Feature",
  "properties": {
    "iso:country":"US",
    "sg:address":"4075 Marietta Hwy",
    "sg:city":"Dallas",
    "sg:classifiers":[
        {
            "category":"Shopping",
            "type":"Retail Goods"
        }
    ],
    "sg:phone":"+1 770 505 2884",
    "sg:postcode":"30157",
    "sg:province":"GA",
    "sg:tags":[
        "merchandise"
    ],
    "wof:name":"Highest Praise Trophies & Awar",
    "wof:placetype":"venue"
},
  "geometry": {"coordinates":[-84.72504600000001,33.934138],"type":"Point"}
}