{
  "type": "Feature",
  "properties": {
    "addr:full":"5855 Jimmy Carter Blvd Norcross GA 30071",
    "addr:housenumber":"5855",
    "addr:postcode":"30071",
    "addr:street":"Jimmy Carter Blvd",
    "iso:country":"US",
    "sg:address":"5855 Jimmy Carter Blvd",
    "sg:city":"Norcross",
    "sg:classifiers":[
        {
            "category":"Professional",
            "subcategory":"Lawyer & Legal Services",
            "type":"Services"
        }
    ],
    "sg:phone":"+1 770 448 5767",
    "sg:postcode":"30071",
    "sg:province":"GA",
    "sg:tags":[
        "attorney"
    ],
    "wof:name":"Haley & Kaye",
    "wof:placetype":"venue"
},
  "geometry": {"coordinates":[-84.216111,33.924735],"type":"Point"}
}