{
  "type": "Feature",
  "properties": {
    "addr:full":"275 Carpenter Dr NE Sandy Springs GA 30328",
    "addr:housenumber":"275",
    "addr:postcode":"30328",
    "addr:street":"Carpenter Dr Ne",
    "iso:country":"US",
    "sg:address":"275 Carpenter Dr NE",
    "sg:city":"Sandy Springs",
    "sg:classifiers":[
        {
            "category":"Building & Trades",
            "subcategory":"Locksmith",
            "type":"Services"
        }
    ],
    "sg:phone":"+1 888 277 4514",
    "sg:postcode":"30328",
    "sg:province":"GA",
    "sg:tags":[
        "key"
    ],
    "wof:name":"A 1 Lock & Locksmith",
    "wof:placetype":"venue"
},
  "geometry": {"coordinates":[-84.379031,33.915239],"type":"Point"}
}