{
  "type": "Feature",
  "properties": {
    "iso:country":"US",
    "sg:address":"790 Atlanta South Pkwy",
    "sg:city":"Atlanta",
    "sg:classifiers":[
        {
            "category":"Banks & Credit Unions",
            "subcategory":"Financial Services",
            "type":"Services"
        },
        {
            "category":"Banks & Credit Unions",
            "subcategory":"Investment Brokerage",
            "type":"Services"
        },
        {
            "category":"Professional",
            "subcategory":"Employment Agencies",
            "type":"Services"
        },
        {
            "category":"Professional",
            "subcategory":"Business Services",
            "type":"Services"
        }
    ],
    "sg:phone":"+1 404 761 0866",
    "sg:postcode":"30349",
    "sg:province":"GA",
    "sg:tags":[
        "retirement",
        "consultant",
        "broker",
        "custom",
        "plan",
        "annuity",
        "insurance"
    ],
    "wof:name":"Ragan Lisa Customs Brokerage",
    "wof:placetype":"venue"
},
  "geometry": {"coordinates":[-84.408118,33.611403],"type":"Point"}
}