{
  "type": "Feature",
  "properties": {
    "iso:country":"US",
    "sg:address":"6775 S Goddard Rd",
    "sg:city":"Lithonia",
    "sg:classifiers":[
        {
            "category":"Education",
            "subcategory":"School",
            "type":"Public Place"
        }
    ],
    "sg:phone":"+1 678 676 9100",
    "sg:postcode":"30038",
    "sg:province":"GA",
    "sg:tags":[
        "high",
        "middle",
        "elementary"
    ],
    "wof:name":"Murphey Candler Elementary School",
    "wof:placetype":"venue"
},
  "geometry": {"coordinates":[-84.125434,33.651428],"type":"Point"}
}