{
  "type": "Feature",
  "properties": {
    "addr:full":"476 Scottmill Rd Hartwell GA 30643",
    "addr:housenumber":"476",
    "addr:postcode":"30643",
    "addr:street":"Scottmill Rd",
    "iso:country":"US",
    "sg:address":"476 Scottmill Rd",
    "sg:city":"Hartwell",
    "sg:classifiers":[
        {
            "category":"Organizations",
            "subcategory":"Religious Organization",
            "type":"Services"
        }
    ],
    "sg:phone":"+1 706 376 5424",
    "sg:postcode":"30643",
    "sg:province":"GA",
    "wof:name":"Ministries I Discipleship",
    "wof:placetype":"venue"
},
  "geometry": {"coordinates":[-82.955809,34.344805],"type":"Point"}
}