{
  "type": "Feature",
  "properties": {
    "iso:country":"US",
    "sg:address":"3219 Fort Morris Rd",
    "sg:city":"Midway",
    "sg:classifiers":[
        {
            "category":"Building & Trades",
            "subcategory":"Landscaping Services",
            "type":"Services"
        }
    ],
    "sg:phone":"+1 912 884 4977",
    "sg:postcode":"31320",
    "sg:province":"GA",
    "sg:tags":[
        "lawn",
        "care"
    ],
    "wof:name":"Coastal Turf & Landscape Inc",
    "wof:placetype":"venue"
},
  "geometry": {"coordinates":[-81.280845,31.768594],"type":"Point"}
}