{
  "type": "Feature",
  "properties": {
    "iso:country":"US",
    "sg:address":"587 Collins Rd",
    "sg:city":"Toccoa",
    "sg:classifiers":[
        {
            "category":"Shopping",
            "type":"Retail Goods"
        }
    ],
    "sg:phone":"+1 706 282 1869",
    "sg:postcode":"30577",
    "sg:province":"GA",
    "sg:tags":[
        "pet",
        "food",
        "merchandise",
        "supply"
    ],
    "wof:name":"Sandie Pet & Supplies",
    "wof:placetype":"venue"
},
  "geometry": {"coordinates":[-83.313962,34.571021],"type":"Point"}
}