{
  "type": "Feature",
  "properties": {
    "iso:country":"US",
    "sg:address":"3001 Turner Hill Rd",
    "sg:city":"Lithonia",
    "sg:classifiers":[
        {
            "category":"Shopping",
            "subcategory":"Jewelry",
            "type":"Retail Goods"
        }
    ],
    "sg:phone":"+1 678 526 8398",
    "sg:postcode":"30038",
    "sg:province":"GA",
    "wof:name":"Jared the Galeria of Jewelry",
    "wof:placetype":"venue"
},
  "geometry": {"coordinates":[-84.088402,33.6992],"type":"Point"}
}