{
  "type": "Feature",
  "properties": {
    "addr:full":"2010 Stonehedge Rd Roswell GA 30075",
    "addr:housenumber":"2010",
    "addr:postcode":"30075",
    "addr:street":"Stonehedge Rd",
    "iso:country":"US",
    "sg:address":"2010 Stonehedge Rd",
    "sg:city":"Roswell",
    "sg:classifiers":[
        {
            "category":"Personal",
            "subcategory":"Beauty Salon",
            "type":"Services"
        }
    ],
    "sg:phone":"+1 770 289 5005",
    "sg:postcode":"30075",
    "sg:province":"GA",
    "sg:tags":[
        "shop"
    ],
    "wof:name":"Party All The Time",
    "wof:placetype":"venue"
},
  "geometry": {"coordinates":[-84.398116,34.056998],"type":"Point"}
}