{
  "type": "Feature",
  "properties": {
    "addr:full":"205 Alexander Rd Eatonton GA 31024",
    "addr:housenumber":"205",
    "addr:postcode":"31024",
    "addr:street":"Alexander Rd",
    "iso:country":"US",
    "sg:address":"205 Alexander Rd",
    "sg:city":"Eatonton",
    "sg:classifiers":[
        {
            "category":"Real Estate",
            "subcategory":"Real Estate Agent",
            "type":"Services"
        }
    ],
    "sg:phone":"+1 706 484 1874",
    "sg:postcode":"31024",
    "sg:province":"GA",
    "wof:name":"Coldwell Banker Lake Oconee",
    "wof:placetype":"venue"
},
  "geometry": {"coordinates":[-83.297893,33.416531],"type":"Point"}
}