{
  "type": "Feature",
  "properties": {
    "addr:full":"768 James P Brawley Drive N Atlanta GA 30318",
    "addr:housenumber":"768",
    "addr:postcode":"30318",
    "addr:street":"James P Brawley Drive N",
    "iso:country":"US",
    "sg:address":"768 James P Brawley Drive N",
    "sg:city":"Atlanta",
    "sg:classifiers":[
        {
            "category":"Shopping",
            "subcategory":"Crafts & Fabrics",
            "type":"Retail Goods"
        }
    ],
    "sg:phone":"+1 404 872 1852",
    "sg:postcode":"30318",
    "sg:province":"GA",
    "sg:tags":[
        "art"
    ],
    "wof:name":"Reisman Properties",
    "wof:placetype":"venue"
},
  "geometry": {"coordinates":[-84.412261,33.775808],"type":"Point"}
}