{
  "type": "Feature",
  "properties": {
    "iso:country":"US",
    "sg:address":"1732 Powers Ferry Rd SE",
    "sg:city":"Marietta",
    "sg:classifiers":[
        {
            "category":"Shopping",
            "subcategory":"Computers & Home Electronics",
            "type":"Retail Goods"
        }
    ],
    "sg:phone":"+1 770 980 2050",
    "sg:postcode":"30067",
    "sg:province":"GA",
    "sg:tags":[
        "software"
    ],
    "wof:name":"L & T Information Technology",
    "wof:placetype":"venue"
},
  "geometry": {"coordinates":[-84.465169,33.90897],"type":"Point"}
}