{
  "type": "Feature",
  "properties": {
    "iso:country":"US",
    "sg:address":"655 Lyric Way NW",
    "sg:city":"Atlanta",
    "sg:classifiers":[
        {
            "category":"Social Services",
            "subcategory":"Child Care",
            "type":"Services"
        }
    ],
    "sg:phone":"+1 404 794 4133",
    "sg:postcode":"30318",
    "sg:province":"GA",
    "sg:tags":[
        "day"
    ],
    "wof:name":"2nd Home Day Care",
    "wof:placetype":"venue"
},
  "geometry": {"coordinates":[-84.478392,33.773124],"type":"Point"}
}