{
  "type": "Feature",
  "properties": {
    "iso:country":"US",
    "sg:address":"603 S Marietta Pkwy SE #101",
    "sg:city":"Marietta",
    "sg:classifiers":[
        {
            "category":"Banks & Credit Unions",
            "subcategory":"Financial Services",
            "type":"Services"
        }
    ],
    "sg:phone":"+1 678 594 2295",
    "sg:postcode":"30060",
    "sg:province":"GA",
    "sg:tags":[
        "cashing",
        "loan",
        "payday",
        "alternative",
        "check"
    ],
    "sg:website":"http://www.acecashexpress.com",
    "wof:name":"ACE Cash Express",
    "wof:placetype":"venue"
},
  "geometry": {"coordinates":[-84.53422399999999,33.943332],"type":"Point"}
}