{
  "type": "Feature",
  "properties": {
    "iso:country":"US",
    "sg:address":"1094 Green St",
    "sg:city":"Roswell",
    "sg:classifiers":[
        {
            "category":"Personal",
            "type":"Services"
        }
    ],
    "sg:postcode":"30075",
    "sg:province":"GA",
    "sg:tags":[
        "party",
        "planning",
        "event"
    ],
    "sg:website":"www.farmhouseinthecity.com",
    "wof:name":"Farmhouse in the City",
    "wof:placetype":"venue"
},
  "geometry": {"coordinates":[-84.360197,34.028604],"type":"Point"}
}