{
  "type": "Feature",
  "properties": {
    "iso:country":"US",
    "sg:address":"5741 State Rte 54",
    "sg:city":"Sharpsburg",
    "sg:classifiers":[
        {
            "category":"Professional",
            "subcategory":"Business Services",
            "type":"Services"
        }
    ],
    "sg:phone":"+1 770 599 8069",
    "sg:postcode":"30277",
    "sg:province":"GA",
    "wof:name":"Georgia Assoc of Educator",
    "wof:placetype":"venue"
},
  "geometry": {"coordinates":[-84.64738,33.322067],"type":"Point"}
}