{
  "type": "Feature",
  "properties": {
    "iso:country":"US",
    "sg:address":"618 Green Rd",
    "sg:city":"Chatsworth",
    "sg:classifiers":[
        {
            "category":"Transit Center",
            "subcategory":"Freight",
            "type":"Transportation"
        }
    ],
    "sg:phone":"+1 706 422 8588",
    "sg:postcode":"30705",
    "sg:province":"GA",
    "sg:tags":[
        "container",
        "broker"
    ],
    "wof:name":"Circle M Operations",
    "wof:placetype":"venue"
},
  "geometry": {"coordinates":[-84.777501,34.76953],"type":"Point"}
}