{
  "type": "Feature",
  "properties": {
    "addr:full":"108 Sandy Run Dr Warner Robins GA 31088",
    "addr:housenumber":"108",
    "addr:postcode":"31088",
    "addr:street":"Sandy Run Dr",
    "iso:country":"US",
    "sg:address":"108 Sandy Run Dr",
    "sg:city":"Warner Robins",
    "sg:classifiers":[
        {
            "category":"Building & Trades",
            "subcategory":"Construction",
            "type":"Services"
        }
    ],
    "sg:phone":"+1 478 329 9828",
    "sg:postcode":"31088",
    "sg:province":"GA",
    "sg:tags":[
        "contractor"
    ],
    "wof:name":"E-Z Gutters",
    "wof:placetype":"venue"
},
  "geometry": {"coordinates":[-83.656403,32.573399],"type":"Point"}
}