{
  "type": "Feature",
  "properties": {
    "addr:full":"2430 Cherokee Rd Athens GA 30605",
    "addr:housenumber":"2430",
    "addr:postcode":"30605",
    "addr:street":"Cherokee Rd",
    "iso:country":"US",
    "sg:address":"2430 Cherokee Rd",
    "sg:city":"Athens",
    "sg:classifiers":[
        {
            "category":"Professional",
            "type":"Services"
        },
        {
            "category":"Real Estate",
            "subcategory":"Real Estate Operator",
            "type":"Services"
        }
    ],
    "sg:phone":"+1 706 543 9750",
    "sg:postcode":"30605",
    "sg:province":"GA",
    "sg:tags":[
        "mobile",
        "home",
        "establishment",
        "park"
    ],
    "wof:name":"Beaverdam Estates Mobile Hm Pk",
    "wof:placetype":"venue"
},
  "geometry": {"coordinates":[-83.309882,33.942524],"type":"Point"}
}