{
  "type": "Feature",
  "properties": {
    "iso:country":"US",
    "sg:address":"315 Jonesboro Rd",
    "sg:city":"Mcdonough",
    "sg:classifiers":[
        {
            "category":"Restaurant",
            "type":"Food & Drink"
        }
    ],
    "sg:menulink":"http://www.allmenus.com/ga/mcdonough/239207-mo-jos-wings/menu/",
    "sg:phone":"+1 770 957 7173",
    "sg:postcode":"30253",
    "sg:province":"GA",
    "sg:tags":[
        "american",
        "wing"
    ],
    "wof:name":"Mo-Jo's Wings",
    "wof:placetype":"venue"
},
  "geometry": {"coordinates":[-84.168426,33.454173],"type":"Point"}
}