{
  "type": "Feature",
  "properties": {
    "iso:country":"US",
    "sg:address":"5500 Abercorn St Exn",
    "sg:city":"Savannah",
    "sg:classifiers":[
        {
            "category":"Restaurant",
            "type":"Food & Drink"
        }
    ],
    "sg:phone":"+1 912 355 0683",
    "sg:postcode":"31405",
    "sg:province":"GA",
    "wof:name":"S & S Cafeteria",
    "wof:placetype":"venue"
},
  "geometry": {"coordinates":[-81.10976599999999,32.023823],"type":"Point"}
}