{
  "type": "Feature",
  "properties": {
    "iso:country":"US",
    "sg:address":"244 Cleveland Ave SW D",
    "sg:city":"Atlanta",
    "sg:classifiers":[
        {
            "category":"Banks & Credit Unions",
            "subcategory":"Financial Services",
            "type":"Services"
        }
    ],
    "sg:phone":"+1 404 767 9422",
    "sg:postcode":"30315",
    "sg:province":"GA",
    "sg:tags":[
        "cashing",
        "check"
    ],
    "wof:name":"Atl Check Cashiers Inc",
    "wof:placetype":"venue"
},
  "geometry": {"coordinates":[-84.39643700000001,33.68111],"type":"Point"}
}