{
  "type": "Feature",
  "properties": {
    "addr:full":"4780 Flint Hill Rd Austell GA 30106",
    "addr:housenumber":"4780",
    "addr:postcode":"30106",
    "addr:street":"Flint Hill Rd",
    "iso:country":"US",
    "sg:address":"4780 Flint Hill Rd",
    "sg:city":"Austell",
    "sg:classifiers":[
        {
            "category":"Organizations",
            "subcategory":"Religious Organization",
            "type":"Services"
        }
    ],
    "sg:phone":"+1 770 941 8445",
    "sg:postcode":"30106",
    "sg:province":"GA",
    "wof:name":"Calvary Baptist Church",
    "wof:placetype":"venue"
},
  "geometry": {"coordinates":[-84.624284,33.834891],"type":"Point"}
}