{
  "type": "Feature",
  "properties": {
    "iso:country":"US",
    "sg:address":"3761 Venture Dr",
    "sg:city":"Duluth",
    "sg:phone":"+1 770 497 9997",
    "sg:postcode":"30096",
    "sg:province":"GA",
    "sg:website":"http://atlgec.org/",
    "wof:name":"Atlanta General Educational Center",
    "wof:placetype":"venue"
},
  "geometry": {"coordinates":[-84.13468,33.952775],"type":"Point"}
}