{
  "type": "Feature",
  "properties": {
    "iso:country":"US",
    "sg:address":"111 1st St NE",
    "sg:city":"Moultrie",
    "sg:classifiers":[
        {
            "category":"Government",
            "subcategory":"Police Station",
            "type":"Public Place"
        }
    ],
    "sg:phone":"+1 229 985 3131",
    "sg:postcode":"31768",
    "sg:province":"GA",
    "sg:tags":[
        "department"
    ],
    "wof:name":"Moultrie Police Dept",
    "wof:placetype":"venue"
},
  "geometry": {"coordinates":[-83.787678,31.180215],"type":"Point"}
}