{
  "type": "Feature",
  "properties": {
    "addr:full":"322 Oak St Ste 1 Gainesville GA 30501",
    "addr:housenumber":"322",
    "addr:postcode":"30501",
    "addr:street":"Oak St Ste 1;Ga",
    "iso:country":"US",
    "sg:address":"322 Oak St Ste 1",
    "sg:city":"Gainesville",
    "sg:classifiers":[
        {
            "category":"Professional",
            "subcategory":"Management & Consulting",
            "type":"Services"
        },
        {
            "category":"Education",
            "subcategory":"Special Training",
            "type":"Public Place"
        }
    ],
    "sg:phone":"+1 770 532 7661",
    "sg:postcode":"30501",
    "sg:province":"GA",
    "sg:tags":[
        "consultant",
        "educational",
        "tutoring"
    ],
    "wof:name":"Smart Steps Educational Resources",
    "wof:placetype":"venue"
},
  "geometry": {"coordinates":[-83.830102,34.30069],"type":"Point"}
}