{
  "type": "Feature",
  "properties": {
    "iso:country":"US",
    "sg:address":"8655 Roswell Rd",
    "sg:city":"Atlanta",
    "sg:classifiers":[
        {
            "category":"Retail",
            "subcategory":"Auto Repair",
            "type":"Services"
        }
    ],
    "sg:phone":"+1 770 649 6925",
    "sg:postcode":"30350",
    "sg:province":"GA",
    "wof:name":"World Collison",
    "wof:placetype":"venue"
},
  "geometry": {"coordinates":[-84.351573,33.9911],"type":"Point"}
}