{
  "type": "Feature",
  "properties": {
    "iso:country":"US",
    "sg:address":"334 Old Hamilton Mill Rd",
    "sg:city":"Bremen",
    "sg:classifiers":[
        {
            "category":"Professional",
            "type":"Services"
        }
    ],
    "sg:phone":"+1 770 537 3243",
    "sg:postcode":"30110",
    "sg:province":"GA",
    "wof:name":"Juanita J Parris",
    "wof:placetype":"venue"
},
  "geometry": {"coordinates":[-85.124472,33.750674],"type":"Point"}
}