{
  "type": "Feature",
  "properties": {
    "iso:country":"US",
    "sg:address":"44 Broad St NW",
    "sg:city":"Atlanta",
    "sg:classifiers":[
        {
            "category":"Building & Trades",
            "subcategory":"Cleaning & Sanitation",
            "type":"Services"
        }
    ],
    "sg:phone":"+1 404 525 2001",
    "sg:postcode":"30303",
    "sg:province":"GA",
    "sg:tags":[
        "janitor",
        "maintenance"
    ],
    "wof:name":"Gardner Building Services Inc",
    "wof:placetype":"venue"
},
  "geometry": {"coordinates":[-84.390569,33.754889],"type":"Point"}
}