{
  "type": "Feature",
  "properties": {
    "iso:country":"US",
    "sg:address":"106 E Broad St",
    "sg:city":"Louisville",
    "sg:classifiers":[
        {
            "category":"Professional",
            "type":"Services"
        }
    ],
    "sg:phone":"+1 478 625 8978",
    "sg:postcode":"30434",
    "sg:province":"GA",
    "sg:tags":[
        "establishment"
    ],
    "wof:name":"DSD Enterprises Inc",
    "wof:placetype":"venue"
},
  "geometry": {"coordinates":[-82.409398,32.999738],"type":"Point"}
}