{
  "type": "Feature",
  "properties": {
    "iso:country":"US",
    "sg:address":"2420 Eastgate Pl",
    "sg:city":"Snellville",
    "sg:classifiers":[
        {
            "category":"Building & Trades",
            "subcategory":"Construction",
            "type":"Services"
        }
    ],
    "sg:phone":"+1 770 982 0090",
    "sg:postcode":"30078",
    "sg:province":"GA",
    "sg:tags":[
        "resurfacing",
        "laying",
        "refinishing",
        "floor"
    ],
    "wof:name":"Accent Flooring Co",
    "wof:placetype":"venue"
},
  "geometry": {"coordinates":[-84.007187,33.857906],"type":"Point"}
}