{
  "type": "Feature",
  "properties": {
    "iso:country":"US",
    "sg:address":"1115 E Main St",
    "sg:city":"Hogansville",
    "sg:classifiers":[
        {
            "category":"Retail",
            "subcategory":"Auto Repair",
            "type":"Services"
        }
    ],
    "sg:phone":"+1 706 637 6379",
    "sg:postcode":"30230",
    "sg:province":"GA",
    "sg:tags":[
        "repairing",
        "automobile",
        "parts",
        "automotive",
        "general"
    ],
    "wof:name":"Hubbard & Spinks Parts and Svc",
    "wof:placetype":"venue"
},
  "geometry": {"coordinates":[-84.900176,33.166289],"type":"Point"}
}