{
  "type": "Feature",
  "properties": {
    "addr:full":"3255 Lawrenceville Suwanee Rd Ste N Suwanee GA 30024",
    "addr:housenumber":"3255",
    "addr:postcode":"30024",
    "addr:street":"Lawrenceville Suwanee Rd Ste N",
    "iso:country":"US",
    "sg:address":"3255 Lawrenceville Suwanee Rd Ste N",
    "sg:city":"Suwanee",
    "sg:classifiers":[
        {
            "category":"Cinema",
            "subcategory":"Movie Rental",
            "type":"Entertainment"
        }
    ],
    "sg:phone":"+1 678 546 2270",
    "sg:postcode":"30024",
    "sg:province":"GA",
    "sg:tags":[
        "game",
        "video"
    ],
    "wof:name":"Rhino Video Games",
    "wof:placetype":"venue"
},
  "geometry": {"coordinates":[-84.05259700000001,34.036222],"type":"Point"}
}