{
  "type": "Feature",
  "properties": {
    "iso:country":"US",
    "sg:address":"2365 Satellite Blvd Ste A",
    "sg:city":"Duluth",
    "sg:classifiers":[
        {
            "category":"Sports & Exercise",
            "subcategory":"Gym",
            "type":"Entertainment"
        }
    ],
    "sg:phone":"+1 678 417 0880",
    "sg:postcode":"30096",
    "sg:province":"GA",
    "sg:tags":[
        "trainer"
    ],
    "wof:name":"Bodyrich Fitness Company",
    "wof:placetype":"venue"
},
  "geometry": {"coordinates":[-84.09369700000001,33.975498],"type":"Point"}
}