{
  "type": "Feature",
  "properties": {
    "addr:full":"3560 State Rte 5 Buford GA 30513",
    "addr:housenumber":"3560",
    "addr:postcode":"30513",
    "addr:street":"State Rte 5",
    "iso:country":"US",
    "sg:address":"3560 State Rte 5",
    "sg:city":"Buford",
    "sg:classifiers":[
        {
            "category":"Professional",
            "subcategory":"Management & Consulting",
            "type":"Services"
        }
    ],
    "sg:phone":"+1 678 835 0052",
    "sg:postcode":"30513",
    "sg:province":"GA",
    "sg:tags":[
        "water",
        "marketing",
        "industry",
        "treatment",
        "for"
    ],
    "wof:name":"Adedge Technologies Inc",
    "wof:placetype":"venue"
},
  "geometry": {"coordinates":[-84.336838,34.855761],"type":"Point"}
}