{
  "type": "Feature",
  "properties": {
    "addr:full":"1111 Dawson Rd Albany GA 31707",
    "addr:housenumber":"1111",
    "addr:postcode":"31707",
    "addr:street":"Dawson Rd",
    "iso:country":"US",
    "sg:address":"1111 Dawson Rd",
    "sg:city":"Albany",
    "sg:classifiers":[
        {
            "category":"Bars & Pubs",
            "type":"Food & Drink"
        },
        {
            "category":"Restaurant",
            "type":"Food & Drink"
        }
    ],
    "sg:phone":"+1 229 888 7797",
    "sg:postcode":"31707",
    "sg:province":"GA",
    "sg:tags":[
        "drinking",
        "eating"
    ],
    "wof:name":"Texastar Steakhouse Inc",
    "wof:placetype":"venue"
},
  "geometry": {"coordinates":[-84.180993,31.58464],"type":"Point"}
}