{
  "type": "Feature",
  "properties": {
    "addr:full":"301 McIntosh Pkwy Thomaston GA 30286",
    "addr:housenumber":"301",
    "addr:postcode":"30286",
    "addr:street":"Mcintosh Pkwy",
    "iso:country":"US",
    "sg:address":"301 McIntosh Pkwy",
    "sg:city":"Thomaston",
    "sg:classifiers":[
        {
            "category":"Manufacturing",
            "subcategory":"Metals",
            "type":"Manufacturing & Wholesale Goods"
        }
    ],
    "sg:phone":"+1 706 647 1162",
    "sg:postcode":"30286",
    "sg:province":"GA",
    "sg:tags":[
        "hardware"
    ],
    "wof:name":"Woodbury Box Co",
    "wof:placetype":"venue"
},
  "geometry": {"coordinates":[-84.293111,32.913499],"type":"Point"}
}