{
  "type": "Feature",
  "properties": {
    "addr:full":"303 E Central Ave Valdosta GA 31601",
    "addr:housenumber":"303",
    "addr:postcode":"31601",
    "addr:street":"E Central Ave",
    "iso:country":"US",
    "sg:address":"303 E Central Ave",
    "sg:city":"Valdosta",
    "sg:classifiers":[
        {
            "category":"Retail",
            "subcategory":"Car Wash",
            "type":"Services"
        }
    ],
    "sg:phone":"+1 229 257 0373",
    "sg:postcode":"31601",
    "sg:province":"GA",
    "sg:tags":[
        "carwash",
        "automobile",
        "detail",
        "clean"
    ],
    "wof:name":"Color Finishes Of Valdosta",
    "wof:placetype":"venue"
},
  "geometry": {"coordinates":[-83.275294,30.833488],"type":"Point"}
}