{
  "type": "Feature",
  "properties": {
    "addr:full":"985 N Main St Jasper GA 30143",
    "addr:housenumber":"985",
    "addr:postcode":"30143",
    "addr:street":"N Main St",
    "iso:country":"US",
    "sg:address":"985 N Main St",
    "sg:city":"Jasper",
    "sg:classifiers":[
        {
            "category":"Retail",
            "subcategory":"Auto Repair",
            "type":"Services"
        }
    ],
    "sg:phone":"+1 706 692 6831",
    "sg:postcode":"30143",
    "sg:province":"GA",
    "sg:tags":[
        "wrecker"
    ],
    "wof:name":"R & R Towing",
    "wof:placetype":"venue"
},
  "geometry": {"coordinates":[-84.441101,34.474927],"type":"Point"}
}