{
  "type": "Feature",
  "properties": {
    "addr:full":"3035 Pine Needle Rd Augusta GA 30909",
    "addr:housenumber":"3035",
    "addr:postcode":"30909",
    "addr:street":"Pine Needle Rd",
    "iso:country":"US",
    "sg:address":"3035 Pine Needle Rd",
    "sg:city":"Augusta",
    "sg:classifiers":[
        {
            "category":"Professional",
            "subcategory":"Management & Consulting",
            "type":"Services"
        }
    ],
    "sg:phone":"+1 706 736 5162",
    "sg:postcode":"30909",
    "sg:province":"GA",
    "sg:tags":[
        "business"
    ],
    "wof:name":"Clyde Lester Consultants",
    "wof:placetype":"venue"
},
  "geometry": {"coordinates":[-82.040847,33.47255],"type":"Point"}
}