{
  "type": "Feature",
  "properties": {
    "addr:full":"1184 Lawrenceville Hwy Lawrenceville GA 30045",
    "addr:housenumber":"1184",
    "addr:postcode":"30045",
    "addr:street":"Lawrenceville Hwy",
    "iso:country":"US",
    "sg:address":"1184 Lawrenceville Hwy",
    "sg:city":"Lawrenceville",
    "sg:classifiers":[
        {
            "category":"Food & Beverages",
            "subcategory":"Groceries & Convenience Stores",
            "type":"Retail Goods"
        }
    ],
    "sg:phone":"+1 770 963 4362",
    "sg:postcode":"30045",
    "sg:province":"GA",
    "wof:name":"S & B Food & Beverage",
    "wof:placetype":"venue"
},
  "geometry": {"coordinates":[-84.018396,33.938571],"type":"Point"}
}