{
  "type": "Feature",
  "properties": {
    "addr:full":"700 Hudson Rd Griffin GA 30224",
    "addr:housenumber":"700",
    "addr:postcode":"30224",
    "addr:street":"Hudson Rd",
    "iso:country":"US",
    "sg:address":"700 Hudson Rd",
    "sg:city":"Griffin",
    "sg:classifiers":[
        {
            "category":"Wholesale",
            "subcategory":"Auto Parts",
            "type":"Manufacturing & Wholesale Goods"
        }
    ],
    "sg:phone":"+1 803 905 3904",
    "sg:postcode":"30224",
    "sg:province":"GA",
    "sg:tags":[
        "automotive"
    ],
    "wof:name":"Caterpillar",
    "wof:placetype":"venue"
},
  "geometry": {"coordinates":[-84.226451,33.229446],"type":"Point"}
}