{
  "type": "Feature",
  "properties": {
    "addr:full":"3933 Washington Rd Augusta GA 30907",
    "addr:housenumber":"3933",
    "addr:postcode":"30907",
    "addr:street":"Washington Rd",
    "iso:country":"US",
    "sg:address":"3933 Washington Rd",
    "sg:city":"Augusta",
    "sg:classifiers":[
        {
            "category":"Communications",
            "subcategory":"Film & Video Production",
            "type":"Services"
        }
    ],
    "sg:phone":"+1 706 650 5422",
    "sg:postcode":"30907",
    "sg:province":"GA",
    "sg:tags":[
        "motion"
    ],
    "wof:name":"Studio 54",
    "wof:placetype":"venue"
},
  "geometry": {"coordinates":[-82.099503,33.510143],"type":"Point"}
}