{
  "type": "Feature",
  "properties": {
    "addr:full":"1931 Shorter Ave Rome GA 30165",
    "addr:housenumber":"1931",
    "addr:postcode":"ga 30165",
    "addr:street":"Shorter Ave",
    "iso:country":"US",
    "sg:address":"1931 Shorter Ave",
    "sg:city":"Rome",
    "sg:classifiers":[
        {
            "category":"Professional",
            "type":"Services"
        }
    ],
    "sg:phone":"+1 706 378 0555",
    "sg:postcode":"30165",
    "sg:province":"GA",
    "wof:name":"Romes Faster Refund Service",
    "wof:placetype":"venue"
},
  "geometry": {"coordinates":[-85.220384,34.270434],"type":"Point"}
}