{
  "type": "Feature",
  "properties": {
    "addr:full":"1568 Cooks Pond Dr Powder Springs GA 30127",
    "addr:housenumber":"1568",
    "addr:postcode":"30127",
    "addr:street":"Cooks Pond Dr",
    "iso:country":"US",
    "sg:address":"1568 Cooks Pond Dr",
    "sg:city":"Powder Springs",
    "sg:classifiers":[
        {
            "category":"Professional",
            "subcategory":"Advertising",
            "type":"Services"
        }
    ],
    "sg:phone":"+1 770 919 1211",
    "sg:postcode":"30127",
    "sg:province":"GA",
    "sg:tags":[
        "picture"
    ],
    "wof:name":"National Cine Media",
    "wof:placetype":"venue"
},
  "geometry": {"coordinates":[-84.65300999999999,33.914629],"type":"Point"}
}