{
  "type": "Feature",
  "properties": {
    "iso:country":"US",
    "sg:address":"245 Laurel Pl",
    "sg:city":"Woodstock",
    "sg:classifiers":[
        {
            "category":"Professional",
            "subcategory":"Business Services",
            "type":"Services"
        }
    ],
    "sg:phone":"+1 770 517 3805",
    "sg:postcode":"30188",
    "sg:province":"GA",
    "wof:name":"Sharp Resedential Builders",
    "wof:placetype":"venue"
},
  "geometry": {"coordinates":[-84.514281,34.088538],"type":"Point"}
}