{
  "type": "Feature",
  "properties": {
    "iso:country":"US",
    "sg:address":"4290 Bells Ferry Rd NW",
    "sg:city":"Kennesaw",
    "sg:classifiers":[
        {
            "category":"Banks & Credit Unions",
            "subcategory":"Financial Services",
            "type":"Services"
        }
    ],
    "sg:phone":"+1 770 517 4436",
    "sg:postcode":"30144",
    "sg:province":"GA",
    "wof:name":"Orchard Square Westwood Financial",
    "wof:placetype":"venue"
},
  "geometry": {"coordinates":[-84.556608,34.055717],"type":"Point"}
}