{
  "type": "Feature",
  "properties": {
    "addr:full":"6275 Shadow Rock Dr Lithonia GA 30058",
    "addr:housenumber":"6275",
    "addr:postcode":"30058",
    "addr:street":"Shadow Rock Dr",
    "iso:country":"US",
    "sg:address":"6275 Shadow Rock Dr",
    "sg:city":"Lithonia",
    "sg:classifiers":[
        {
            "category":"Building & Trades",
            "subcategory":"Cleaning & Sanitation",
            "type":"Services"
        }
    ],
    "sg:phone":"+1 770 482 7523",
    "sg:postcode":"30058",
    "sg:province":"GA",
    "sg:tags":[
        "maintenance"
    ],
    "wof:name":"Fretwell Enterprises",
    "wof:placetype":"venue"
},
  "geometry": {"coordinates":[-84.142753,33.754392],"type":"Point"}
}