{
  "type": "Feature",
  "properties": {
    "iso:country":"US",
    "sg:address":"287 Legend Dr",
    "sg:city":"Dallas",
    "sg:classifiers":[
        {
            "category":"Professional",
            "type":"Services"
        }
    ],
    "sg:phone":"+1 770 456 0631",
    "sg:postcode":"30180",
    "sg:province":"GA",
    "wof:name":"Kenneth C Robinson",
    "wof:placetype":"venue"
},
  "geometry": {"coordinates":[-84.857271,33.806616],"type":"Point"}
}