{
  "type": "Feature",
  "properties": {
    "addr:full":"1266 Sylvan Rd SW Atlanta GA 30310",
    "addr:housenumber":"1266",
    "addr:postcode":"30310",
    "addr:street":"Sylvan Rd Sw",
    "iso:country":"US",
    "sg:address":"1266 Sylvan Rd SW",
    "sg:city":"Atlanta",
    "sg:classifiers":[
        {
            "category":"Health Services",
            "subcategory":"Doctor",
            "type":"Services"
        }
    ],
    "sg:phone":"+1 404 752 0484",
    "sg:postcode":"30310",
    "sg:province":"GA",
    "sg:tags":[
        "physician",
        "surgery",
        "oral",
        "surgeons"
    ],
    "wof:name":"Jay Lyrics Productions 2",
    "wof:placetype":"venue"
},
  "geometry": {"coordinates":[-84.418029,33.720302],"type":"Point"}
}