{
  "type": "Feature",
  "properties": {
    "addr:full":"300 Tigner Rd Greenville GA 30222",
    "addr:housenumber":"300",
    "addr:postcode":"30222",
    "addr:street":"Tigner Rd",
    "iso:country":"US",
    "sg:address":"300 Tigner Rd",
    "sg:city":"Greenville",
    "sg:classifiers":[
        {
            "category":"Building & Trades",
            "subcategory":"Construction",
            "type":"Services"
        }
    ],
    "sg:phone":"+1 706 672 0962",
    "sg:postcode":"30222",
    "sg:province":"GA",
    "sg:tags":[
        "heavy"
    ],
    "wof:name":"Bruce McGavic Constructio",
    "wof:placetype":"venue"
},
  "geometry": {"coordinates":[-84.827584,32.998024],"type":"Point"}
}