{
  "type": "Feature",
  "properties": {
    "iso:country":"US",
    "sg:address":"251 N Main St",
    "sg:city":"Jonesboro",
    "sg:classifiers":[
        {
            "category":"Real Estate",
            "subcategory":"Real Estate Agent",
            "type":"Services"
        }
    ],
    "sg:phone":"+1 770 478 8809",
    "sg:postcode":"30236",
    "sg:province":"GA",
    "wof:name":"Bailey Properties",
    "wof:placetype":"venue"
},
  "geometry": {"coordinates":[-84.35485199999999,33.530619],"type":"Point"}
}