{
  "type": "Feature",
  "properties": {
    "iso:country":"US",
    "sg:address":"4170 Old Milton Pkwy",
    "sg:city":"Alpharetta",
    "sg:classifiers":[
        {
            "category":"Restaurant",
            "type":"Food & Drink"
        }
    ],
    "sg:menulink":"http://www.allmenus.com/ga/roswell-alpharetta/121259-la-cazuela/menu/",
    "sg:phone":"+1 770 346 9740",
    "sg:postcode":"30005",
    "sg:province":"GA",
    "sg:tags":[
        "mexican"
    ],
    "wof:name":"La Cazuela",
    "wof:placetype":"venue"
},
  "geometry": {"coordinates":[-84.237799,34.060353],"type":"Point"}
}