{
  "type": "Feature",
  "properties": {
    "addr:full":"1552 Shoup Ct Decatur GA 30033",
    "addr:housenumber":"1552",
    "addr:postcode":"30033",
    "addr:street":"Shoup Ct",
    "iso:country":"US",
    "sg:address":"1552 Shoup Ct",
    "sg:city":"Decatur",
    "sg:classifiers":[
        {
            "category":"Social Services",
            "type":"Services"
        },
        {
            "category":"Social Services",
            "subcategory":"Child Care",
            "type":"Services"
        },
        {
            "category":"Organizations",
            "subcategory":"Non-profit Organization",
            "type":"Services"
        }
    ],
    "sg:phone":"+1 404 327 9200",
    "sg:postcode":"30033",
    "sg:province":"GA",
    "sg:tags":[
        "educational",
        "foundations-educational",
        "philanthropic",
        "cancer",
        "support",
        "research",
        "fund",
        "referral",
        "raising",
        "charity"
    ],
    "sg:website":"http://www.cancer.org",
    "wof:name":"American Cancer Society",
    "wof:placetype":"venue"
},
  "geometry": {"coordinates":[-84.309151,33.799301],"type":"Point"}
}