{
  "type": "Feature",
  "properties": {
    "iso:country":"US",
    "sg:address":"685 Main St",
    "sg:city":"Whitesburg",
    "sg:classifiers":[
        {
            "category":"Manufacturing",
            "subcategory":"Glass & Minerals",
            "type":"Manufacturing & Wholesale Goods"
        }
    ],
    "sg:phone":"+1 770 502 9590",
    "sg:postcode":"30185",
    "sg:province":"GA",
    "sg:tags":[
        "glass-wholesale",
        "shape",
        "circle",
        "special",
        "manufacturer"
    ],
    "wof:name":"H And S Commercial Glass Inc",
    "wof:placetype":"venue"
},
  "geometry": {"coordinates":[-84.91372200000001,33.493695],"type":"Point"}
}