{
  "type": "Feature",
  "properties": {
    "iso:country":"US",
    "sg:address":"600 Houze Way",
    "sg:city":"Roswell",
    "sg:classifiers":[
        {
            "category":"Health Services",
            "subcategory":"Medical Lab",
            "type":"Services"
        }
    ],
    "sg:phone":"+1 770 998 7845",
    "sg:postcode":"30076",
    "sg:province":"GA",
    "sg:tags":[
        "detection",
        "equipment",
        "drug"
    ],
    "sg:website":"www.metscheck.com",
    "wof:name":"METS Medical Evaluation Svc",
    "wof:placetype":"venue"
},
  "geometry": {"coordinates":[-84.339765,34.046437],"type":"Point"}
}