{
  "type": "Feature",
  "properties": {
    "iso:country":"US",
    "sg:address":"1360 Dogwood Dr SE Ste 104",
    "sg:city":"Conyers",
    "sg:classifiers":[
        {
            "category":"Shopping",
            "subcategory":"Mobile Phones",
            "type":"Retail Goods"
        }
    ],
    "sg:phone":"+1 678 210 0500",
    "sg:postcode":"30013",
    "sg:province":"GA",
    "wof:name":"East Metro Cellular Inc",
    "wof:placetype":"venue"
},
  "geometry": {"coordinates":[-83.999163,33.650851],"type":"Point"}
}