{
  "type": "Feature",
  "properties": {
    "iso:country":"US",
    "sg:address":"1708 Peachtree Street NW",
    "sg:city":"Atlanta",
    "sg:classifiers":[
        {
            "category":"Education",
            "subcategory":"School",
            "type":"Public Place"
        }
    ],
    "sg:phone":"+1 404 892 2336",
    "sg:postcode":"30309",
    "sg:province":"GA",
    "wof:name":"The Odyssey Group",
    "wof:placetype":"venue"
},
  "geometry": {"coordinates":[-84.392287,33.799864],"type":"Point"}
}