{
  "type": "Feature",
  "properties": {
    "iso:country":"US",
    "sg:address":"2021 Verbena St NW",
    "sg:city":"Atlanta",
    "sg:classifiers":[
        {
            "category":"Professional",
            "type":"Services"
        }
    ],
    "sg:phone":"+1 404 792 7288",
    "sg:postcode":"30314",
    "sg:province":"GA",
    "wof:name":"Wonder Works Prod",
    "wof:placetype":"venue"
},
  "geometry": {"coordinates":[-84.451767,33.7546],"type":"Point"}
}