{
  "type": "Feature",
  "properties": {
    "addr:full":"102 E Jackson St Dublin GA 31021",
    "addr:housenumber":"102",
    "addr:postcode":"31021",
    "addr:street":"E Jackson St",
    "iso:country":"US",
    "sg:address":"102 E Jackson St",
    "sg:city":"Dublin",
    "sg:classifiers":[
        {
            "category":"Shopping",
            "subcategory":"Shoes",
            "type":"Retail Goods"
        }
    ],
    "sg:phone":"+1 478 272 1203",
    "sg:postcode":"31021",
    "sg:province":"GA",
    "sg:tags":[
        "boots-retail",
        "store"
    ],
    "wof:name":"Stricklands Boots Inc",
    "wof:placetype":"venue"
},
  "geometry": {"coordinates":[-82.90431100000001,32.539607],"type":"Point"}
}