{
  "type": "Feature",
  "properties": {
    "addr:full":"1507 Reynolds St Brunswick GA 31520",
    "addr:housenumber":"1507",
    "addr:postcode":"31520",
    "addr:street":"Reynolds St",
    "iso:country":"US",
    "sg:address":"1507 Reynolds St",
    "sg:city":"Brunswick",
    "sg:classifiers":[
        {
            "category":"Professional",
            "subcategory":"Lawyer & Legal Services",
            "type":"Services"
        }
    ],
    "sg:phone":"+1 912 261 0027",
    "sg:postcode":"31520",
    "sg:province":"GA",
    "wof:name":"Patrick C Kaufman",
    "wof:placetype":"venue"
},
  "geometry": {"coordinates":[-81.494519,31.150717],"type":"Point"}
}