{
  "type": "Feature",
  "properties": {
    "iso:country":"US",
    "sg:address":"134 S Macon St",
    "sg:city":"Jesup",
    "sg:classifiers":[
        {
            "category":"Shopping",
            "subcategory":"Clothing, Apparel, & Fashions",
            "type":"Retail Goods"
        }
    ],
    "sg:phone":"+1 912 427 6119",
    "sg:postcode":"31545",
    "sg:province":"GA",
    "sg:tags":[
        "boutique"
    ],
    "wof:name":"Merle Norman Cosmetics",
    "wof:placetype":"venue"
},
  "geometry": {"coordinates":[-81.88444200000001,31.605836],"type":"Point"}
}