{
  "type": "Feature",
  "properties": {
    "addr:full":"3219 Skidaway Rd Savannah GA 31404",
    "addr:housenumber":"3219",
    "addr:postcode":"31404",
    "addr:street":"Skidaway Rd",
    "iso:country":"US",
    "sg:address":"3219 Skidaway Rd",
    "sg:city":"Savannah",
    "sg:classifiers":[
        {
            "category":"Professional",
            "subcategory":"Detective & Security Services",
            "type":"Services"
        }
    ],
    "sg:phone":"+1 912 354 1743",
    "sg:postcode":"31404",
    "sg:province":"GA",
    "sg:tags":[
        "system"
    ],
    "wof:name":"Cash Transactions",
    "wof:placetype":"venue"
},
  "geometry": {"coordinates":[-81.06786200000001,32.034385],"type":"Point"}
}