{
  "type": "Feature",
  "properties": {
    "addr:full":"560 Fairground St NE Marietta GA 30060",
    "addr:housenumber":"560",
    "addr:postcode":"30060",
    "addr:street":"Fairground St Ne",
    "iso:country":"US",
    "sg:address":"560 Fairground St NE",
    "sg:city":"Marietta",
    "sg:classifiers":[
        {
            "category":"Shopping",
            "subcategory":"Computers & Home Electronics",
            "type":"Retail Goods"
        }
    ],
    "sg:phone":"+1 770 590 0386",
    "sg:postcode":"30060",
    "sg:province":"GA",
    "sg:tags":[
        "comm"
    ],
    "wof:name":"Art Works & Graphics",
    "wof:placetype":"venue"
},
  "geometry": {"coordinates":[-84.53713500000001,33.966392],"type":"Point"}
}