{
  "type": "Feature",
  "properties": {
    "iso:country":"US",
    "sg:address":"926 Jones Mill Rd",
    "sg:city":"Cartersville",
    "sg:classifiers":[
        {
            "category":"Building & Trades",
            "subcategory":"Cleaning & Sanitation",
            "type":"Services"
        }
    ],
    "sg:phone":"+1 770 382 1102",
    "sg:postcode":"30120",
    "sg:province":"GA",
    "sg:tags":[
        "maintenance"
    ],
    "wof:name":"Soot Busters Chimney Services",
    "wof:placetype":"venue"
},
  "geometry": {"coordinates":[-84.80273800000001,34.187719],"type":"Point"}
}