{
  "type": "Feature",
  "properties": {
    "iso:country":"US",
    "sg:address":"5365 Peachtree Industrial Blvd",
    "sg:city":"Norcross",
    "sg:classifiers":[
        {
            "category":"Restaurant",
            "type":"Food & Drink"
        }
    ],
    "sg:phone":"+1 770 449 1916",
    "sg:postcode":"30092",
    "sg:province":"GA",
    "sg:tags":[
        "style",
        "family",
        "lunch",
        "american",
        "brunch",
        "breakfast"
    ],
    "sg:website":"http://www.wafflehouse.com",
    "wof:name":"Waffle House",
    "wof:placetype":"venue"
},
  "geometry": {"coordinates":[-84.20963,33.960613],"type":"Point"}
}