{
  "type": "Feature",
  "properties": {
    "iso:country":"US",
    "sg:address":"1255 Damascus Rd",
    "sg:city":"Epworth",
    "sg:classifiers":[
        {
            "category":"Building & Trades",
            "subcategory":"Construction",
            "type":"Services"
        }
    ],
    "sg:phone":"+1 706 492 3745",
    "sg:postcode":"30547",
    "sg:province":"GA",
    "sg:tags":[
        "maker",
        "cabinet"
    ],
    "wof:name":"Custom Mountain Furniture",
    "wof:placetype":"venue"
},
  "geometry": {"coordinates":[-83.444131,34.400473],"type":"Point"}
}