{
  "type": "Feature",
  "properties": {
    "addr:full":"3 Gresham Lndg Stockbridge GA 30281",
    "addr:housenumber":"3",
    "addr:postcode":"30281",
    "addr:street":"Lndg",
    "iso:country":"US",
    "sg:address":"3 Gresham Lndg",
    "sg:city":"Stockbridge",
    "sg:classifiers":[
        {
            "category":"Insurance",
            "subcategory":"Insurance Agent",
            "type":"Services"
        }
    ],
    "sg:phone":"+1 770 506 0990",
    "sg:postcode":"30281",
    "sg:province":"GA",
    "wof:name":"Econocheck Corp",
    "wof:placetype":"venue"
},
  "geometry": {"coordinates":[-84.21820700000001,33.508042],"type":"Point"}
}