{
  "type": "Feature",
  "properties": {
    "addr:full":"4018 Lindley Rd Powder Springs GA 30127",
    "addr:housenumber":"4018",
    "addr:postcode":"30127",
    "addr:street":"Lindley Rd",
    "iso:country":"US",
    "sg:address":"4018 Lindley Rd",
    "sg:city":"Powder Springs",
    "sg:classifiers":[
        {
            "category":"Retail",
            "subcategory":"Auto Repair",
            "type":"Services"
        }
    ],
    "sg:phone":"+1 770 943 4825",
    "sg:postcode":"30127",
    "sg:province":"GA",
    "wof:name":"James'auto Repair",
    "wof:placetype":"venue"
},
  "geometry": {"coordinates":[-84.67089799999999,33.8601],"type":"Point"}
}