{
  "type": "Feature",
  "properties": {
    "addr:full":"806 N Highland Ave NE Atlanta GA 30306",
    "addr:housenumber":"806",
    "addr:postcode":"30306",
    "addr:street":"N Highland Ave Ne",
    "iso:country":"US",
    "sg:address":"806 N Highland Ave NE",
    "sg:city":"Atlanta",
    "sg:classifiers":[
        {
            "category":"Personal",
            "subcategory":"Beauty Salon",
            "type":"Services"
        }
    ],
    "sg:phone":"+1 404 873 6512",
    "sg:postcode":"30306",
    "sg:province":"GA",
    "sg:tags":[
        "spa",
        "day"
    ],
    "sg:website":"www.keylimepie.net",
    "wof:name":"Key Lime Pie Salon and Wellness Spa",
    "wof:placetype":"venue"
},
  "geometry": {"coordinates":[-84.35230300000001,33.776501],"type":"Point"}
}