{
  "type": "Feature",
  "properties": {
    "iso:country":"US",
    "sg:address":"3870 N Druid Hills Rd",
    "sg:city":"Decatur",
    "sg:classifiers":[
        {
            "category":"Shopping",
            "subcategory":"Pharmacy",
            "type":"Retail Goods"
        }
    ],
    "sg:phone":"+1 404 633 6466",
    "sg:postcode":"30033",
    "sg:province":"GA",
    "sg:tags":[
        "drugstore"
    ],
    "wof:name":"Publix Pharmacy",
    "wof:placetype":"venue"
},
  "geometry": {"coordinates":[-84.275398,33.811001],"type":"Point"}
}