{
  "type": "Feature",
  "properties": {
    "iso:country":"US",
    "sg:address":"4333 Bemiss Rd",
    "sg:city":"Valdosta",
    "sg:classifiers":[
        {
            "category":"Food & Beverages",
            "subcategory":"Groceries & Convenience Stores",
            "type":"Retail Goods"
        }
    ],
    "sg:phone":"+1 229 244 8940",
    "sg:postcode":"31605",
    "sg:province":"GA",
    "sg:tags":[
        "grocer"
    ],
    "wof:name":"Asian Food Mart",
    "wof:placetype":"venue"
},
  "geometry": {"coordinates":[-83.25221999999999,30.921487],"type":"Point"}
}