{
  "type": "Feature",
  "properties": {
    "addr:full":"103 Pony Pl Griffin GA 30224",
    "addr:housenumber":"103",
    "addr:postcode":"30224",
    "addr:street":"Pony Pl",
    "iso:country":"US",
    "sg:address":"103 Pony Pl",
    "sg:city":"Griffin",
    "sg:classifiers":[
        {
            "category":"Building & Trades",
            "subcategory":"Construction",
            "type":"Services"
        }
    ],
    "sg:phone":"+1 404 886 1108",
    "sg:postcode":"30224",
    "sg:province":"GA",
    "sg:tags":[
        "architectural",
        "cabinetry"
    ],
    "wof:name":"Sophisticated Cabinetry Mllwk",
    "wof:placetype":"venue"
},
  "geometry": {"coordinates":[-84.30321600000001,33.235961],"type":"Point"}
}