{
  "type": "Feature",
  "properties": {
    "addr:full":"108 Wynne Rd Mc Donough GA 30252",
    "addr:housenumber":"108",
    "addr:postcode":"30252",
    "addr:street":"Wynne Rd",
    "iso:country":"US",
    "sg:address":"108 Wynne Rd",
    "sg:city":"Mc Donough",
    "sg:classifiers":[
        {
            "category":"Real Estate",
            "subcategory":"Real Estate Agent",
            "type":"Services"
        }
    ],
    "sg:phone":"+1 770 616 9071",
    "sg:postcode":"30252",
    "sg:province":"GA",
    "wof:name":"Hall Homes & Realty Services",
    "wof:placetype":"venue"
},
  "geometry": {"coordinates":[-83.997812,33.452934],"type":"Point"}
}