{
  "type": "Feature",
  "properties": {
    "iso:country":"US",
    "sg:address":"95 Church St NE",
    "sg:city":"Marietta",
    "sg:classifiers":[
        {
            "category":"Shopping",
            "subcategory":"Antiques",
            "type":"Retail Goods"
        }
    ],
    "sg:phone":"+1 678 594 0888",
    "sg:postcode":"30060",
    "sg:province":"GA",
    "wof:name":"Fit For A Queen",
    "wof:placetype":"venue"
},
  "geometry": {"coordinates":[-84.55019799999999,33.953934],"type":"Point"}
}