{
  "type": "Feature",
  "properties": {
    "iso:country":"US",
    "sg:address":"376 Wallis Rd",
    "sg:city":"Villa Rica",
    "sg:classifiers":[
        {
            "category":"Wholesale",
            "subcategory":"Farm Supplies",
            "type":"Manufacturing & Wholesale Goods"
        }
    ],
    "sg:phone":"+1 770 832 2533",
    "sg:postcode":"30180",
    "sg:province":"GA",
    "sg:tags":[
        "buyer",
        "livestock"
    ],
    "wof:name":"Randy Carden Livestock",
    "wof:placetype":"venue"
},
  "geometry": {"coordinates":[-84.94311,33.629749],"type":"Point"}
}