{
  "type": "Feature",
  "properties": {
    "iso:country":"US",
    "sg:address":"724 Pilgrim Mill Rd",
    "sg:city":"Cumming",
    "sg:classifiers":[
        {
            "category":"Organizations",
            "subcategory":"Religious Organization",
            "type":"Services"
        }
    ],
    "sg:phone":"+1 770 887 8190",
    "sg:postcode":"30040",
    "sg:province":"GA",
    "sg:tags":[
        "church"
    ],
    "wof:name":"Episcopal Church-Holy Spirit",
    "wof:placetype":"venue"
},
  "geometry": {"coordinates":[-84.11873900000001,34.222003],"type":"Point"}
}