{
  "type": "Feature",
  "properties": {
    "addr:full":"2480 Briarcliff Rd Atlanta GA 31132",
    "addr:housenumber":"2480",
    "addr:postcode":"31132",
    "addr:street":"Briarcliff Rd",
    "iso:country":"US",
    "sg:address":"2480 Briarcliff Rd",
    "sg:city":"Atlanta",
    "sg:classifiers":[
        {
            "category":"Education",
            "subcategory":"Dance Studio",
            "type":"Public Place"
        }
    ],
    "sg:phone":"+1 404 542 3887",
    "sg:postcode":"31132",
    "sg:province":"GA",
    "sg:website":"dance101.org",
    "wof:name":"Dance 101",
    "wof:placetype":"venue"
},
  "geometry": {"coordinates":[-84.333046,33.825905],"type":"Point"}
}