{
  "type": "Feature",
  "properties": {
    "addr:full":"4525 Glenwood Rd Decatur GA 30032",
    "addr:housenumber":"4525",
    "addr:postcode":"30032",
    "addr:street":"Glenwood Rd",
    "iso:country":"US",
    "sg:address":"4525 Glenwood Rd",
    "sg:city":"Decatur",
    "sg:classifiers":[
        {
            "category":"Autos & Motor Vehicles",
            "subcategory":"Auto Supplies",
            "type":"Retail Goods"
        }
    ],
    "sg:phone":"+1 404 289 0999",
    "sg:postcode":"30032",
    "sg:province":"GA",
    "sg:tags":[
        "automobile",
        "stereo",
        "radio"
    ],
    "wof:name":"E T Car Stereo",
    "wof:placetype":"venue"
},
  "geometry": {"coordinates":[-84.23398299999999,33.737276],"type":"Point"}
}