{
  "type": "Feature",
  "properties": {
    "addr:full":"1500 Wall Bridge Rd Clarkesville GA 30523",
    "addr:housenumber":"1500",
    "addr:postcode":"30523",
    "addr:street":"Wall Bridge Rd",
    "iso:country":"US",
    "sg:address":"1500 Wall Bridge Rd",
    "sg:city":"Clarkesville",
    "sg:classifiers":[
        {
            "category":"Education",
            "subcategory":"Special Training",
            "type":"Public Place"
        },
        {
            "category":"Education",
            "subcategory":"School",
            "type":"Public Place"
        }
    ],
    "sg:phone":"+1 706 754 2915",
    "sg:postcode":"30523",
    "sg:province":"GA",
    "sg:tags":[
        "middle",
        "educational"
    ],
    "sg:website":"http://www.habersham.k12.ga.us",
    "wof:name":"North Habersham Middle School",
    "wof:placetype":"venue"
},
  "geometry": {"coordinates":[-83.51160400000001,34.637875],"type":"Point"}
}