{
  "type": "Feature",
  "properties": {
    "addr:full":"923 Valley Brook Rd Decatur GA 30033",
    "addr:housenumber":"923",
    "addr:postcode":"30033",
    "addr:street":"Valley Brook Rd",
    "iso:country":"US",
    "sg:address":"923 Valley Brook Rd",
    "sg:city":"Decatur",
    "sg:classifiers":[
        {
            "category":"Organizations",
            "subcategory":"Religious Organization",
            "type":"Services"
        }
    ],
    "sg:phone":"+1 404 508 1400",
    "sg:postcode":"30033",
    "sg:province":"GA",
    "sg:tags":[
        "church"
    ],
    "wof:name":"New Beginning Full Gospel",
    "wof:placetype":"venue"
},
  "geometry": {"coordinates":[-84.26818400000001,33.807277],"type":"Point"}
}