{
  "type": "Feature",
  "properties": {
    "iso:country":"US",
    "sg:address":"3957 Cleveland Hwy",
    "sg:city":"Dalton",
    "sg:classifiers":[
        {
            "category":"Restaurant",
            "type":"Food & Drink"
        }
    ],
    "sg:phone":"+1 706 694 8248",
    "sg:postcode":"30721",
    "sg:province":"GA",
    "sg:tags":[
        "italian"
    ],
    "wof:name":"Luigi's Pizza Italian Restauran",
    "wof:placetype":"venue"
},
  "geometry": {"coordinates":[-84.946866,34.897369],"type":"Point"}
}