{
  "type": "Feature",
  "properties": {
    "iso:country":"US",
    "sg:address":"266 Bald Eagle Rd",
    "sg:city":"Richmond Hill",
    "sg:classifiers":[
        {
            "category":"Professional",
            "subcategory":"Business Services",
            "type":"Services"
        }
    ],
    "sg:phone":"+1 912 925 9420",
    "sg:postcode":"31324",
    "sg:province":"GA",
    "sg:tags":[
        "plant",
        "design",
        "maintenance"
    ],
    "wof:name":"Foliage Design Systems",
    "wof:placetype":"venue"
},
  "geometry": {"coordinates":[-81.326314,31.925257],"type":"Point"}
}