{
  "type": "Feature",
  "properties": {
    "iso:country":"US",
    "sg:address":"101 E Main St",
    "sg:city":"Fort Valley",
    "sg:classifiers":[
        {
            "category":"Shopping",
            "subcategory":"Gifts & Souvenirs",
            "type":"Retail Goods"
        }
    ],
    "sg:phone":"+1 478 825 3955",
    "sg:postcode":"31030",
    "sg:province":"GA",
    "sg:tags":[
        "party",
        "supply"
    ],
    "wof:name":"Camellia & Main Store",
    "wof:placetype":"venue"
},
  "geometry": {"coordinates":[-83.886546,32.553622],"type":"Point"}
}