{
  "type": "Feature",
  "properties": {
    "iso:country":"US",
    "sg:address":"318 Cumberland Ct",
    "sg:city":"Peachtree City",
    "sg:classifiers":[
        {
            "category":"Professional",
            "subcategory":"Management & Consulting",
            "type":"Services"
        }
    ],
    "sg:phone":"+1 770 632 7615",
    "sg:postcode":"30269",
    "sg:province":"GA",
    "sg:tags":[
        "financial"
    ],
    "wof:name":"Aurora Management Partners",
    "wof:placetype":"venue"
},
  "geometry": {"coordinates":[-84.52884899999999,33.359512],"type":"Point"}
}