{
  "type": "Feature",
  "properties": {
    "iso:country":"US",
    "sg:address":"6289 Bankhead Hwy",
    "sg:city":"Austell",
    "sg:classifiers":[
        {
            "category":"Building & Trades",
            "subcategory":"Construction",
            "type":"Services"
        }
    ],
    "sg:phone":"+1 770 745 9040",
    "sg:postcode":"30134",
    "sg:province":"GA",
    "sg:tags":[
        "painter"
    ],
    "wof:name":"Statewide Painting Co",
    "wof:placetype":"venue"
},
  "geometry": {"coordinates":[-84.737483,33.756196],"type":"Point"}
}