{
  "type": "Feature",
  "properties": {
    "addr:full":"501 Calibre Woods Dr Atlanta GA 30329",
    "addr:housenumber":"501",
    "addr:postcode":"30329",
    "addr:street":"Calibre Woods Dr",
    "iso:country":"US",
    "sg:address":"501 Calibre Woods Dr",
    "sg:city":"Atlanta",
    "sg:classifiers":[
        {
            "category":"Communications",
            "subcategory":"Radio Station",
            "type":"Services"
        }
    ],
    "sg:phone":"+1 404 248 6468",
    "sg:postcode":"30329",
    "sg:province":"GA",
    "sg:tags":[
        "educational"
    ],
    "wof:name":"Littles  Breverly",
    "wof:placetype":"venue"
},
  "geometry": {"coordinates":[-84.315907,33.815572],"type":"Point"}
}