{
  "type": "Feature",
  "properties": {
    "iso:country":"US",
    "sg:address":"1620 Marietta Blvd NW",
    "sg:city":"Atlanta",
    "sg:classifiers":[
        {
            "category":"Building & Trades",
            "subcategory":"Locksmith",
            "type":"Services"
        }
    ],
    "sg:phone":"+1 404 929 3651",
    "sg:postcode":"30318",
    "sg:province":"GA",
    "sg:tags":[
        "key"
    ],
    "wof:name":"A A A Bomber Locksmith",
    "wof:placetype":"venue"
},
  "geometry": {"coordinates":[-84.434815,33.799181],"type":"Point"}
}