{
  "type": "Feature",
  "properties": {
    "addr:full":"3688 Clearview Ave Atlanta GA 30340",
    "addr:housenumber":"3688",
    "addr:postcode":"30340",
    "addr:street":"Clearview Ave",
    "iso:country":"US",
    "sg:address":"3688 Clearview Ave",
    "sg:city":"Atlanta",
    "sg:classifiers":[
        {
            "category":"Health Services",
            "subcategory":"Doctor",
            "type":"Services"
        }
    ],
    "sg:phone":"+1 770 220 9964",
    "sg:postcode":"30340",
    "sg:province":"GA",
    "sg:tags":[
        "neurologist"
    ],
    "wof:name":"Neural Signals Inc",
    "wof:placetype":"venue"
},
  "geometry": {"coordinates":[-84.274198,33.901367],"type":"Point"}
}