{
  "type": "Feature",
  "properties": {
    "addr:full":"2613 Regal Cir Lawrenceville GA 30044",
    "addr:housenumber":"2613",
    "addr:postcode":"30044",
    "addr:street":"Regal Cir",
    "iso:country":"US",
    "sg:address":"2613 Regal Cir",
    "sg:city":"Lawrenceville",
    "sg:classifiers":[
        {
            "category":"Real Estate",
            "subcategory":"Real Estate Agent",
            "type":"Services"
        }
    ],
    "sg:phone":"+1 770 923 1996",
    "sg:postcode":"30044",
    "sg:province":"GA",
    "sg:tags":[
        "building",
        "maintenance"
    ],
    "wof:name":"Robertson Construction Servi",
    "wof:placetype":"venue"
},
  "geometry": {"coordinates":[-84.06903800000001,33.922276],"type":"Point"}
}