{
  "type": "Feature",
  "properties": {
    "addr:full":"4950 Agate Dr Alpharetta GA 30022",
    "addr:housenumber":"4950",
    "addr:postcode":"30022",
    "addr:street":"Agate Dr",
    "iso:country":"US",
    "sg:address":"4950 Agate Dr",
    "sg:city":"Alpharetta",
    "sg:classifiers":[
        {
            "category":"Building & Trades",
            "subcategory":"Construction",
            "type":"Services"
        }
    ],
    "sg:phone":"+1 770 663 0064",
    "sg:postcode":"30022",
    "sg:province":"GA",
    "sg:tags":[
        "home",
        "improvement"
    ],
    "wof:name":"Terrain & Water Mgmt Inc",
    "wof:placetype":"venue"
},
  "geometry": {"coordinates":[-84.21407600000001,34.052533],"type":"Point"}
}