{
  "type": "Feature",
  "properties": {
    "addr:full":"1467 Lavista Dr Decatur GA 30033",
    "addr:housenumber":"1467",
    "addr:postcode":"30033",
    "addr:street":"Lavista Dr",
    "iso:country":"US",
    "sg:address":"1467 Lavista Dr",
    "sg:city":"Decatur",
    "sg:classifiers":[
        {
            "category":"Manufacturing",
            "subcategory":"Building Materials",
            "type":"Manufacturing & Wholesale Goods"
        }
    ],
    "sg:phone":"+1 404 248 0523",
    "sg:postcode":"30033",
    "sg:province":"GA",
    "sg:tags":[
        "mfg",
        "wood",
        "kitchen",
        "cabinet"
    ],
    "wof:name":"Williams Cabinet Company",
    "wof:placetype":"venue"
},
  "geometry": {"coordinates":[-84.285768,33.824902],"type":"Point"}
}