{
  "type": "Feature",
  "properties": {
    "iso:country":"US",
    "sg:address":"160 Wildcat Trl",
    "sg:city":"Suches",
    "sg:classifiers":[
        {
            "category":"Travel",
            "subcategory":"Travel Agent",
            "type":"Entertainment"
        }
    ],
    "sg:phone":"+1 706 838 4029",
    "sg:postcode":"30572",
    "sg:province":"GA",
    "sg:tags":[
        "agency",
        "services-commercial"
    ],
    "wof:name":"Defoor Vacation Properties",
    "wof:placetype":"venue"
},
  "geometry": {"coordinates":[-84.150408,34.801276],"type":"Point"}
}