{
  "type": "Feature",
  "properties": {
    "addr:full":"1 Joe Frank Harris Blvd Brunswick GA 31523",
    "addr:housenumber":"1",
    "addr:postcode":"31523",
    "addr:street":"Joe Frank Harris Blvd",
    "iso:country":"US",
    "sg:address":"1 Joe Frank Harris Blvd",
    "sg:city":"Brunswick",
    "sg:classifiers":[
        {
            "category":"Railroad",
            "type":"Transportation"
        }
    ],
    "sg:phone":"+1 912 262 9885",
    "sg:postcode":"31523",
    "sg:province":"GA",
    "sg:tags":[
        "agency",
        "railroads-ticket"
    ],
    "wof:name":"Golden Isles Terminal Railroad",
    "wof:placetype":"venue"
},
  "geometry": {"coordinates":[-81.538498,31.12438],"type":"Point"}
}