{
  "type": "Feature",
  "properties": {
    "iso:country":"US",
    "sg:address":"144 Glen Eagle Way",
    "sg:city":"Mcdonough",
    "sg:classifiers":[
        {
            "category":"Professional",
            "subcategory":"Business Services",
            "type":"Services"
        }
    ],
    "sg:phone":"+1 770 507 4562",
    "sg:postcode":"30253",
    "sg:province":"GA",
    "sg:tags":[
        "embroidery"
    ],
    "wof:name":"Lateda Gifts & Embroidery",
    "wof:placetype":"venue"
},
  "geometry": {"coordinates":[-84.21422200000001,33.498548],"type":"Point"}
}