{
  "type": "Feature",
  "properties": {
    "addr:full":"3223 Mcever Woods Trl NW Acworth GA 30101",
    "addr:housenumber":"3223",
    "addr:postcode":"30101",
    "addr:street":"Mcever Woods Trl Nw",
    "iso:country":"US",
    "sg:address":"3223 Mcever Woods Trl NW",
    "sg:city":"Acworth",
    "sg:classifiers":[
        {
            "category":"Place Of Worship",
            "subcategory":"Church",
            "type":"Public Place"
        },
        {
            "category":"Place Of Worship",
            "type":"Public Place"
        }
    ],
    "sg:phone":"+1 770 386 0945",
    "sg:postcode":"30101",
    "sg:province":"GA",
    "sg:tags":[
        "churches-baptist-general",
        "churches-baptist"
    ],
    "wof:name":"Bethel Baptist Church",
    "wof:placetype":"venue"
},
  "geometry": {"coordinates":[-84.64394299999999,34.054511],"type":"Point"}
}