{
  "type": "Feature",
  "properties": {
    "iso:country":"US",
    "sg:address":"5220 Jimmy Lee Smith Pkwy",
    "sg:city":"Hiram",
    "sg:classifiers":[
        {
            "category":"Home & Garden",
            "subcategory":"Furniture",
            "type":"Retail Goods"
        }
    ],
    "sg:phone":"+1 770 439 4944",
    "sg:postcode":"30141",
    "sg:province":"GA",
    "sg:tags":[
        "store"
    ],
    "wof:name":"Ben Haverty's Furniture Xpress",
    "wof:placetype":"venue"
},
  "geometry": {"coordinates":[-84.74246599999999,33.88725],"type":"Point"}
}