{
  "type": "Feature",
  "properties": {
    "iso:country":"US",
    "sg:address":"2035 Towne Lake Pkwy",
    "sg:city":"Woodstock",
    "sg:classifiers":[
        {
            "category":"Restaurant",
            "type":"Food & Drink"
        }
    ],
    "sg:menulink":"http://www.allmenus.com/ga/woodstock/229563-china-bay/menu/",
    "sg:phone":"+1 770 928 1668",
    "sg:postcode":"30189",
    "sg:province":"GA",
    "sg:tags":[
        "asian",
        "chinese"
    ],
    "wof:name":"China Bay",
    "wof:placetype":"venue"
},
  "geometry": {"coordinates":[-84.552329,34.108244],"type":"Point"}
}