{
  "type": "Feature",
  "properties": {
    "iso:country":"US",
    "sg:address":"1894 Kirkland Rd",
    "sg:city":"Covington",
    "sg:classifiers":[
        {
            "category":"Real Estate",
            "subcategory":"Real Estate Operator",
            "type":"Services"
        }
    ],
    "sg:phone":"+1 770 787 4478",
    "sg:postcode":"30016",
    "sg:province":"GA",
    "sg:tags":[
        "apartment"
    ],
    "wof:name":"Plum Orchard Properties",
    "wof:placetype":"venue"
},
  "geometry": {"coordinates":[-83.969459,33.596199],"type":"Point"}
}