{
  "type": "Feature",
  "properties": {
    "addr:full":"1460 Oak Springs Dr Marietta GA 30066",
    "addr:housenumber":"1460",
    "addr:postcode":"30066",
    "addr:street":"Oak Springs Dr",
    "iso:country":"US",
    "sg:address":"1460 Oak Springs Dr",
    "sg:city":"Marietta",
    "sg:classifiers":[
        {
            "category":"Building & Trades",
            "subcategory":"Construction",
            "type":"Services"
        }
    ],
    "sg:phone":"+1 770 565 7818",
    "sg:postcode":"30066",
    "sg:province":"GA",
    "sg:tags":[
        "house"
    ],
    "wof:name":"Arden A Anderson Gen Contrs",
    "wof:placetype":"venue"
},
  "geometry": {"coordinates":[-84.516244,34.028317],"type":"Point"}
}