{
  "type": "Feature",
  "properties": {
    "addr:full":"300 E Main St Statesboro GA 30458",
    "addr:housenumber":"300",
    "addr:postcode":"30458",
    "addr:street":"E Main St",
    "iso:country":"US",
    "sg:address":"300 E Main St",
    "sg:city":"Statesboro",
    "sg:classifiers":[
        {
            "category":"Banks & Credit Unions",
            "subcategory":"Bank",
            "type":"Services"
        }
    ],
    "sg:phone":"+1 912 489 3789",
    "sg:postcode":"30458",
    "sg:province":"GA",
    "sg:tags":[
        "loan"
    ],
    "wof:name":"Statesboro Finance",
    "wof:placetype":"venue"
},
  "geometry": {"coordinates":[-81.773883,32.449096],"type":"Point"}
}