{
  "type": "Feature",
  "properties": {
    "iso:country":"US",
    "sg:address":"5764 Peachtree Industrial Blvd",
    "sg:city":"Atlanta",
    "sg:classifiers":[
        {
            "category":"Health Services",
            "subcategory":"Clinic",
            "type":"Services"
        },
        {
            "category":"Health Services",
            "subcategory":"Nursing And Care Facility",
            "type":"Services"
        },
        {
            "category":"Community Center",
            "type":"Public Place"
        },
        {
            "category":"Health Services",
            "subcategory":"Hospital",
            "type":"Services"
        }
    ],
    "sg:phone":"+1 800 746 7287",
    "sg:postcode":"30341",
    "sg:province":"GA",
    "sg:tags":[
        "urgent",
        "medical",
        "nurse"
    ],
    "sg:website":"http://www.minuteclinic.com",
    "wof:name":"MinuteClinic",
    "wof:placetype":"venue"
},
  "geometry": {"coordinates":[-84.294718,33.905479],"type":"Point"}
}