{
  "type": "Feature",
  "properties": {
    "iso:country":"US",
    "sg:address":"3931 Pechtre Indstrl Blvd Frnt",
    "sg:city":"Duluth",
    "sg:classifiers":[
        {
            "category":"Personal",
            "type":"Services"
        }
    ],
    "sg:phone":"+1 770 623 2050",
    "sg:postcode":"30096",
    "sg:province":"GA",
    "sg:tags":[
        "sewing",
        "alteration"
    ],
    "wof:name":"Jin's Alterations",
    "wof:placetype":"venue"
},
  "geometry": {"coordinates":[-84.170799,33.987202],"type":"Point"}
}