{
  "type": "Feature",
  "properties": {
    "addr:full":"6038 Mableton Pkwy SE Mableton GA 30126",
    "addr:housenumber":"6038",
    "addr:postcode":"30126",
    "addr:street":"Mableton Pkwy Se",
    "iso:country":"US",
    "sg:address":"6038 Mableton Pkwy SE",
    "sg:city":"Mableton",
    "sg:classifiers":[
        {
            "category":"Building & Trades",
            "subcategory":"Construction",
            "type":"Services"
        }
    ],
    "sg:phone":"+1 770 745 6988",
    "sg:postcode":"30126",
    "sg:province":"GA",
    "sg:tags":[
        "house"
    ],
    "wof:name":"John Wieland Homes",
    "wof:placetype":"venue"
},
  "geometry": {"coordinates":[-84.571361,33.807677],"type":"Point"}
}