{
  "type": "Feature",
  "properties": {
    "addr:full":"40 Marchman Dr NE Atlanta GA 30342",
    "addr:housenumber":"40",
    "addr:postcode":"30342",
    "addr:street":"Marchman Dr Ne",
    "iso:country":"US",
    "sg:address":"40 Marchman Dr NE",
    "sg:city":"Atlanta",
    "sg:classifiers":[
        {
            "category":"Professional",
            "subcategory":"Management & Consulting",
            "type":"Services"
        }
    ],
    "sg:phone":"+1 404 252 8471",
    "sg:postcode":"30342",
    "sg:province":"GA",
    "sg:tags":[
        "consultant",
        "training"
    ],
    "sg:website":"www.lifediscoverycenter.com",
    "wof:name":"Life Discovery",
    "wof:placetype":"venue"
},
  "geometry": {"coordinates":[-84.388741,33.908944],"type":"Point"}
}