{
  "type": "Feature",
  "properties": {
    "addr:full":"127 Abercorn St Savannah GA 31401",
    "addr:housenumber":"127",
    "addr:postcode":"31401",
    "addr:street":"Abercorn St",
    "iso:country":"US",
    "sg:address":"127 Abercorn St",
    "sg:city":"Savannah",
    "sg:classifiers":[
        {
            "category":"Community Center",
            "subcategory":"Senior",
            "type":"Public Place"
        },
        {
            "category":"Social Services",
            "type":"Services"
        },
        {
            "category":"Professional",
            "subcategory":"Lawyer & Legal Services",
            "type":"Services"
        }
    ],
    "sg:phone":"+1 912 651 5065",
    "sg:postcode":"31401",
    "sg:province":"GA",
    "sg:tags":[
        "attorney",
        "law",
        "disability",
        "security",
        "citizen"
    ],
    "wof:name":"Larry Sprague Attorney At Law",
    "wof:placetype":"venue"
},
  "geometry": {"coordinates":[-81.090469,32.077511],"type":"Point"}
}