{
  "type": "Feature",
  "properties": {
    "addr:full":"1719 Hamilton Rd Lagrange GA 30241",
    "addr:housenumber":"1719",
    "addr:postcode":"30241",
    "addr:street":"Hamilton Rd",
    "iso:country":"US",
    "sg:address":"1719 Hamilton Rd",
    "sg:city":"Lagrange",
    "sg:classifiers":[
        {
            "category":"Retail",
            "subcategory":"Auto Repair",
            "type":"Services"
        }
    ],
    "sg:phone":"+1 706 884 2999",
    "sg:postcode":"30241",
    "sg:province":"GA",
    "sg:tags":[
        "body",
        "automobile",
        "painting"
    ],
    "wof:name":"Bridwells Collision",
    "wof:placetype":"venue"
},
  "geometry": {"coordinates":[-85.017917,33.0089],"type":"Point"}
}