{
  "type": "Feature",
  "properties": {
    "addr:full":"60 Covey Trl Newnan GA 30265",
    "addr:housenumber":"60",
    "addr:postcode":"30265",
    "addr:street":"Covey Trl",
    "iso:country":"US",
    "sg:address":"60 Covey Trl",
    "sg:city":"Newnan",
    "sg:classifiers":[
        {
            "category":"Building & Trades",
            "subcategory":"Construction",
            "type":"Services"
        }
    ],
    "sg:phone":"+1 770 206 0912",
    "sg:postcode":"30265",
    "sg:province":"GA",
    "sg:tags":[
        "house"
    ],
    "wof:name":"Q Mans Home Improvement",
    "wof:placetype":"venue"
},
  "geometry": {"coordinates":[-84.704078,33.36861],"type":"Point"}
}