{
  "type": "Feature",
  "properties": {
    "addr:full":"3585 Peachtree Industrial Blvd Duluth GA 30096",
    "addr:housenumber":"3585",
    "addr:postcode":"30096",
    "addr:street":"Peachtree Industrial Blvd",
    "iso:country":"US",
    "sg:address":"3585 Peachtree Industrial Blvd",
    "sg:city":"Duluth",
    "sg:classifiers":[
        {
            "category":"Building & Trades",
            "subcategory":"Locksmith",
            "type":"Services"
        }
    ],
    "sg:phone":"+1 678 269 7244",
    "sg:postcode":"30096",
    "sg:province":"GA",
    "sg:tags":[
        "key"
    ],
    "wof:name":"B&h Emergency Locksmith",
    "wof:placetype":"venue"
},
  "geometry": {"coordinates":[-84.16849000000001,34.000192],"type":"Point"}
}