{
  "type": "Feature",
  "properties": {
    "addr:full":"2733 Airport Rd Blairsville GA 30512",
    "addr:housenumber":"2733",
    "addr:postcode":"30512",
    "addr:street":"Airport Rd",
    "iso:country":"US",
    "sg:address":"2733 Airport Rd",
    "sg:city":"Blairsville",
    "sg:classifiers":[
        {
            "category":"Manufacturing",
            "subcategory":"Lumber",
            "type":"Manufacturing & Wholesale Goods"
        }
    ],
    "sg:phone":"+1 706 745 2467",
    "sg:postcode":"30512",
    "sg:province":"GA",
    "sg:tags":[
        "logging"
    ],
    "wof:name":"Sossebee Logging",
    "wof:placetype":"venue"
},
  "geometry": {"coordinates":[-84.007406,34.849937],"type":"Point"}
}