{
  "type": "Feature",
  "properties": {
    "addr:full":"3531 State Rte 42 Stockbridge GA 30281",
    "addr:housenumber":"3531",
    "addr:postcode":"30281",
    "addr:street":"State Rte 42",
    "iso:country":"US",
    "sg:address":"3531 State Rte 42",
    "sg:city":"Stockbridge",
    "sg:classifiers":[
        {
            "category":"Wholesale",
            "subcategory":"Construction Materials",
            "type":"Manufacturing & Wholesale Goods"
        }
    ],
    "sg:phone":"+1 770 389 3377",
    "sg:postcode":"30281",
    "sg:province":"GA",
    "sg:tags":[
        "lumber"
    ],
    "wof:name":"Lumberyard The",
    "wof:placetype":"venue"
},
  "geometry": {"coordinates":[-84.20110699999999,33.537494],"type":"Point"}
}