{
  "type": "Feature",
  "properties": {
    "addr:full":"601 W Hill Ave Valdosta GA 31601",
    "addr:housenumber":"601",
    "addr:postcode":"31601",
    "addr:street":"W Hill Ave",
    "iso:country":"US",
    "sg:address":"601 W Hill Ave",
    "sg:city":"Valdosta",
    "sg:phone":"+1 229 247 8000",
    "sg:postcode":"31601",
    "sg:province":"GA",
    "sg:tags":[
        "oil",
        "gasoline"
    ],
    "wof:name":"Keeman Petroleum Co Inc",
    "wof:placetype":"venue"
},
  "geometry": {"coordinates":[-83.28531099999999,30.828235],"type":"Point"}
}