{
  "type": "Feature",
  "properties": {
    "iso:country":"US",
    "sg:address":"5775 Peachtree Dunwoody Rd",
    "sg:city":"Atlanta",
    "sg:classifiers":[
        {
            "category":"Professional",
            "subcategory":"Credit Reporting & Collection",
            "type":"Services"
        }
    ],
    "sg:phone":"+1 404 845 2701",
    "sg:postcode":"30342",
    "sg:province":"GA",
    "sg:tags":[
        "agency"
    ],
    "wof:name":"Central Financial Control Lrcf",
    "wof:placetype":"venue"
},
  "geometry": {"coordinates":[-84.35211200000001,33.909554],"type":"Point"}
}