{
  "type": "Feature",
  "properties": {
    "iso:country":"US",
    "sg:address":"4487 Park Dr Ste A",
    "sg:city":"Norcross",
    "sg:classifiers":[
        {
            "category":"Professional",
            "subcategory":"Lawyer & Legal Services",
            "type":"Services"
        }
    ],
    "sg:phone":"+1 770 469 4110",
    "sg:postcode":"30093",
    "sg:province":"GA",
    "wof:name":"Buchanan & Associates",
    "wof:placetype":"venue"
},
  "geometry": {"coordinates":[-84.15319,33.933397],"type":"Point"}
}