{
  "type": "Feature",
  "properties": {
    "iso:country":"US",
    "sg:address":"790 Old Mill Rd",
    "sg:city":"Ringgold",
    "sg:classifiers":[
        {
            "category":"Wholesale",
            "subcategory":"Hardware",
            "type":"Manufacturing & Wholesale Goods"
        }
    ],
    "sg:phone":"+1 706 866 1643",
    "sg:postcode":"30736",
    "sg:province":"GA",
    "sg:tags":[
        "nut",
        "bolt"
    ],
    "wof:name":"Catoosa Industrial Supply",
    "wof:placetype":"venue"
},
  "geometry": {"coordinates":[-85.187764,34.944705],"type":"Point"}
}