{
  "type": "Feature",
  "properties": {
    "iso:country":"US",
    "sg:address":"504 Amsterdam Ave NE",
    "sg:city":"Atlanta",
    "sg:classifiers":[
        {
            "category":"Home & Garden",
            "subcategory":"Furniture",
            "type":"Retail Goods"
        }
    ],
    "sg:phone":"+1 404 872 3696",
    "sg:postcode":"30306",
    "sg:province":"GA",
    "sg:tags":[
        "bed"
    ],
    "sg:website":"www.beddown.com",
    "wof:name":"Bed Down",
    "wof:placetype":"venue"
},
  "geometry": {"coordinates":[-84.370223,33.788228],"type":"Point"}
}