{
  "type": "Feature",
  "properties": {
    "iso:country":"US",
    "sg:address":"902 Ponder Place Ct",
    "sg:city":"Evans",
    "sg:classifiers":[
        {
            "category":"Personal",
            "subcategory":"Beauty Salon",
            "type":"Services"
        }
    ],
    "sg:phone":"+1 706 831 0230",
    "sg:postcode":"30809",
    "sg:province":"GA",
    "wof:name":"Jennifer Lott DeLaney",
    "wof:placetype":"venue"
},
  "geometry": {"coordinates":[-82.13589399999999,33.528925],"type":"Point"}
}