{
  "type": "Feature",
  "properties": {
    "addr:full":"2262 Chestnut Log Loop Lithia Springs GA 30122",
    "addr:housenumber":"2262",
    "addr:postcode":"30122",
    "addr:street":"Chestnut Log Loop",
    "iso:country":"US",
    "sg:address":"2262 Chestnut Log Loop",
    "sg:city":"Lithia Springs",
    "sg:classifiers":[
        {
            "category":"Manufacturing",
            "subcategory":"Signs",
            "type":"Manufacturing & Wholesale Goods"
        }
    ],
    "sg:phone":"+1 678 945 0900",
    "sg:postcode":"30122",
    "sg:province":"GA",
    "sg:tags":[
        "advertising",
        "specialty"
    ],
    "wof:name":"Airbrush Plus Signs",
    "wof:placetype":"venue"
},
  "geometry": {"coordinates":[-84.651337,33.748718],"type":"Point"}
}