{
  "type": "Feature",
  "properties": {
    "addr:full":"308 Arlington Dr Vidalia GA 30474",
    "addr:housenumber":"308",
    "addr:postcode":"30474",
    "addr:street":"Arlington Dr Vidalia",
    "iso:country":"US",
    "sg:address":"308 Arlington Dr",
    "sg:city":"Vidalia",
    "sg:classifiers":[
        {
            "category":"Organizations",
            "subcategory":"Religious Organization",
            "type":"Services"
        }
    ],
    "sg:phone":"+1 912 537 7754",
    "sg:postcode":"30474",
    "sg:province":"GA",
    "sg:tags":[
        "church"
    ],
    "wof:name":"Church Of Christ",
    "wof:placetype":"venue"
},
  "geometry": {"coordinates":[-82.388901,32.20656],"type":"Point"}
}