{
  "type": "Feature",
  "properties": {
    "addr:full":"250 Carriage Way Ln Roswell GA 30076",
    "addr:housenumber":"250",
    "addr:postcode":"30076",
    "addr:street":"Carriage Way Ln",
    "iso:country":"US",
    "sg:address":"250 Carriage Way Ln",
    "sg:city":"Roswell",
    "sg:classifiers":[
        {
            "category":"Building & Trades",
            "subcategory":"Construction",
            "type":"Services"
        }
    ],
    "sg:phone":"+1 770 518 4334",
    "sg:postcode":"30076",
    "sg:province":"GA",
    "sg:tags":[
        "floor",
        "laying",
        "contractor"
    ],
    "wof:name":"Mike Ushakov Enterprises",
    "wof:placetype":"venue"
},
  "geometry": {"coordinates":[-84.286636,33.990388],"type":"Point"}
}