{
  "type": "Feature",
  "properties": {
    "iso:country":"US",
    "sg:address":"3700 Mansell Rd",
    "sg:city":"Alpharetta",
    "sg:classifiers":[
        {
            "category":"Manufacturing",
            "subcategory":"Textiles",
            "type":"Manufacturing & Wholesale Goods"
        }
    ],
    "sg:phone":"+1 770 594 2547",
    "sg:postcode":"30076",
    "sg:province":"GA",
    "sg:tags":[
        "mill",
        "narrow",
        "fabric"
    ],
    "wof:name":"Avery Dennison",
    "wof:placetype":"venue"
},
  "geometry": {"coordinates":[-84.29394499999999,34.037333],"type":"Point"}
}