{
  "type": "Feature",
  "properties": {
    "addr:full":"6086 Church St Ochlocknee GA 31773",
    "addr:housenumber":"6086",
    "addr:postcode":"31773",
    "addr:street":"Church St",
    "iso:country":"US",
    "sg:address":"6086 Church St",
    "sg:city":"Ochlocknee",
    "sg:classifiers":[
        {
            "category":"Personal",
            "subcategory":"Beauty Salon",
            "type":"Services"
        }
    ],
    "sg:phone":"+1 229 574 5428",
    "sg:postcode":"31773",
    "sg:province":"GA",
    "sg:tags":[
        "shop"
    ],
    "wof:name":"Glendas Making Memories",
    "wof:placetype":"venue"
},
  "geometry": {"coordinates":[-84.06094299999999,30.973501],"type":"Point"}
}