{
  "type": "Feature",
  "properties": {
    "iso:country":"US",
    "sg:address":"1086 Pea Ridge Rd",
    "sg:city":"Juliette",
    "sg:classifiers":[
        {
            "category":"Wholesale",
            "subcategory":"Auto Parts",
            "type":"Manufacturing & Wholesale Goods"
        }
    ],
    "sg:phone":"+1 478 741 3633",
    "sg:postcode":"31046",
    "sg:province":"GA",
    "sg:tags":[
        "used"
    ],
    "wof:name":"J & W Auto Salvage",
    "wof:placetype":"venue"
},
  "geometry": {"coordinates":[-83.802402,32.975241],"type":"Point"}
}