{
  "type": "Feature",
  "properties": {
    "addr:full":"1951 Sosebee Dr NE Dalton GA 30721",
    "addr:housenumber":"1951",
    "addr:postcode":"30721",
    "addr:street":"Sosebee Dr Ne",
    "iso:country":"US",
    "sg:address":"1951 Sosebee Dr NE",
    "sg:city":"Dalton",
    "sg:classifiers":[
        {
            "category":"Home & Garden",
            "subcategory":"Garden Supply",
            "type":"Retail Goods"
        }
    ],
    "sg:phone":"+1 706 259 8237",
    "sg:postcode":"30721",
    "sg:province":"GA",
    "sg:tags":[
        "repair"
    ],
    "wof:name":"Small Engine Svc Company",
    "wof:placetype":"venue"
},
  "geometry": {"coordinates":[-84.93938300000001,34.836061],"type":"Point"}
}