{
  "type": "Feature",
  "properties": {
    "addr:full":"25 Inland Cir Newnan GA 30263",
    "addr:housenumber":"25",
    "addr:postcode":"30263",
    "addr:street":"Inland Cir",
    "iso:country":"US",
    "sg:address":"25 Inland Cir",
    "sg:city":"Newnan",
    "sg:classifiers":[
        {
            "category":"Building & Trades",
            "subcategory":"Electrical",
            "type":"Services"
        }
    ],
    "sg:phone":"+1 770 251 3073",
    "sg:postcode":"30263",
    "sg:province":"GA",
    "sg:tags":[
        "electrician"
    ],
    "wof:name":"Sutton Electric Company Inc",
    "wof:placetype":"venue"
},
  "geometry": {"coordinates":[-84.763496,33.458401],"type":"Point"}
}