{
  "type": "Feature",
  "properties": {
    "iso:country":"US",
    "sg:address":"2719 Harbins Rd",
    "sg:city":"Bethlehem",
    "sg:classifiers":[
        {
            "category":"Shopping",
            "type":"Retail Goods"
        }
    ],
    "sg:phone":"+1 770 985 9925",
    "sg:postcode":"30620",
    "sg:province":"GA",
    "sg:tags":[
        "merchandise"
    ],
    "wof:name":"Practical Pet Care",
    "wof:placetype":"venue"
},
  "geometry": {"coordinates":[-83.821557,33.952859],"type":"Point"}
}