{
  "type": "Feature",
  "properties": {
    "iso:country":"US",
    "sg:address":"106 Westchester Dr",
    "sg:city":"Barnesville",
    "sg:classifiers":[
        {
            "category":"Organizations",
            "subcategory":"Religious Organization",
            "type":"Services"
        }
    ],
    "sg:phone":"+1 770 358 4674",
    "sg:postcode":"30204",
    "sg:province":"GA",
    "sg:tags":[
        "church"
    ],
    "wof:name":"Barnesville Parish UMC",
    "wof:placetype":"venue"
},
  "geometry": {"coordinates":[-84.16952999999999,33.056044],"type":"Point"}
}