{
  "type": "Feature",
  "properties": {
    "iso:country":"US",
    "sg:address":"763 Sunhill Rd",
    "sg:city":"Sandersville",
    "sg:classifiers":[
        {
            "category":"Social Services",
            "subcategory":"Child Care",
            "type":"Services"
        }
    ],
    "sg:phone":"+1 478 552 9641",
    "sg:postcode":"31082",
    "sg:province":"GA",
    "sg:tags":[
        "day"
    ],
    "wof:name":"Kangaroo Pouch Child Dev Ctr",
    "wof:placetype":"venue"
},
  "geometry": {"coordinates":[-82.79129399999999,32.977889],"type":"Point"}
}