{
  "type": "Feature",
  "properties": {
    "addr:full":"3697 Kings Hwy Douglasville GA 30135",
    "addr:housenumber":"3697",
    "addr:postcode":"30135",
    "addr:street":"Kings Hwy",
    "iso:country":"US",
    "sg:address":"3697 Kings Hwy",
    "sg:city":"Douglasville",
    "sg:classifiers":[
        {
            "category":"Personal",
            "subcategory":"Beauty Salon",
            "type":"Services"
        }
    ],
    "sg:phone":"+1 770 942 6739",
    "sg:postcode":"30135",
    "sg:province":"GA",
    "sg:tags":[
        "hair"
    ],
    "wof:name":"Kings Corner Barber Shop",
    "wof:placetype":"venue"
},
  "geometry": {"coordinates":[-84.771004,33.703499],"type":"Point"}
}