{
  "type": "Feature",
  "properties": {
    "iso:country":"US",
    "sg:address":"2135 Burroughs Ave SE",
    "sg:city":"Atlanta",
    "sg:classifiers":[
        {
            "category":"Building & Trades",
            "subcategory":"Construction",
            "type":"Services"
        }
    ],
    "sg:phone":"+1 404 622 1821",
    "sg:postcode":"30315",
    "sg:province":"GA",
    "sg:tags":[
        "carpenter"
    ],
    "wof:name":"Charles Carpentry",
    "wof:placetype":"venue"
},
  "geometry": {"coordinates":[-84.37128199999999,33.694578],"type":"Point"}
}