{
  "type": "Feature",
  "properties": {
    "addr:full":"2530 Peach Orchard Rd Augusta GA 30906",
    "addr:housenumber":"2530",
    "addr:postcode":"30906",
    "addr:street":"Peach Orchard Rd",
    "iso:country":"US",
    "sg:address":"2530 Peach Orchard Rd",
    "sg:city":"Augusta",
    "sg:classifiers":[
        {
            "category":"Retail",
            "subcategory":"Repair Shop",
            "type":"Services"
        },
        {
            "category":"Building & Trades",
            "subcategory":"Equipment Rental",
            "type":"Services"
        }
    ],
    "sg:phone":"+1 800 508 4761",
    "sg:postcode":"30906",
    "sg:province":"GA",
    "sg:tags":[
        "yard",
        "supply",
        "contractor",
        "tools-renting",
        "store",
        "contractors'"
    ],
    "sg:website":"http://www-sunbeltrentals-com.netsolads.com/?utm_source=yp.com&utm_medium=tilead&utm_term=localsearch&utm_campaign=&_nsag=39093",
    "wof:name":"Sunbelt Rentals",
    "wof:placetype":"venue"
},
  "geometry": {"coordinates":[-82.017096,33.427168],"type":"Point"}
}