{
  "type": "Feature",
  "properties": {
    "addr:full":"899 State Rte 138 W Stockbridge GA 30281",
    "addr:housenumber":"899",
    "addr:postcode":"30281",
    "addr:street":"State Rte 138 W",
    "iso:country":"US",
    "sg:address":"899 State Rte 138 W",
    "sg:city":"Stockbridge",
    "sg:classifiers":[
        {
            "category":"Insurance",
            "subcategory":"Insurance Agent",
            "type":"Services"
        }
    ],
    "sg:phone":"+1 770 389 4554",
    "sg:postcode":"30281",
    "sg:province":"GA",
    "wof:name":"Dependable Insurance",
    "wof:placetype":"venue"
},
  "geometry": {"coordinates":[-84.26313,33.553646],"type":"Point"}
}