{
  "type": "Feature",
  "properties": {
    "addr:full":"6 Boatner Ave Cartersville GA 30120",
    "addr:housenumber":"6",
    "addr:postcode":"30120",
    "addr:street":"Boatner Ave",
    "iso:country":"US",
    "sg:address":"6 Boatner Ave",
    "sg:city":"Cartersville",
    "sg:classifiers":[
        {
            "category":"Building & Trades",
            "subcategory":"Construction",
            "type":"Services"
        }
    ],
    "sg:phone":"+1 770 974 1967",
    "sg:postcode":"30120",
    "sg:province":"GA",
    "sg:tags":[
        "roofing",
        "contractor"
    ],
    "wof:name":"Allatoona Roofing",
    "wof:placetype":"venue"
},
  "geometry": {"coordinates":[-84.79933800000001,34.157655],"type":"Point"}
}