{
  "type": "Feature",
  "properties": {
    "iso:country":"US",
    "sg:address":"280 Ebenezer Church Rd",
    "sg:city":"Fayetteville",
    "sg:classifiers":[
        {
            "category":"Building & Trades",
            "subcategory":"Construction",
            "type":"Services"
        }
    ],
    "sg:phone":"+1 770 487 5266",
    "sg:postcode":"30215",
    "sg:province":"GA",
    "sg:tags":[
        "mason",
        "masonry",
        "industrial",
        "contractors-commercial",
        "contractor"
    ],
    "wof:name":"Webb Masonry Inc",
    "wof:placetype":"venue"
},
  "geometry": {"coordinates":[-84.502357,33.412849],"type":"Point"}
}