{
  "type": "Feature",
  "properties": {
    "iso:country":"US",
    "sg:address":"2240 Macon Hwy",
    "sg:city":"Watkinsville",
    "sg:classifiers":[
        {
            "category":"Wholesale",
            "subcategory":"Plants",
            "type":"Manufacturing & Wholesale Goods"
        }
    ],
    "sg:phone":"+1 706 310 1151",
    "sg:postcode":"30677",
    "sg:province":"GA",
    "sg:tags":[
        "nursery",
        "tree"
    ],
    "sg:website":"www.southeasterngrowers.com",
    "wof:name":"Southeastern Growers",
    "wof:placetype":"venue"
},
  "geometry": {"coordinates":[-83.429312,33.739782],"type":"Point"}
}