{
  "type": "Feature",
  "properties": {
    "addr:full":"926 Ward St Eastman GA 31023",
    "addr:housenumber":"926",
    "addr:postcode":"31023",
    "addr:street":"Ward St",
    "iso:country":"US",
    "sg:address":"926 Ward St",
    "sg:city":"Eastman",
    "sg:classifiers":[
        {
            "category":"Real Estate",
            "subcategory":"Real Estate Operator",
            "type":"Services"
        }
    ],
    "sg:phone":"+1 478 374 7903",
    "sg:postcode":"31023",
    "sg:province":"GA",
    "sg:tags":[
        "apartment"
    ],
    "wof:name":"Dodge Court Apartments",
    "wof:placetype":"venue"
},
  "geometry": {"coordinates":[-83.16746999999999,32.199182],"type":"Point"}
}