{
  "type": "Feature",
  "properties": {
    "iso:country":"US",
    "sg:address":"3777 Peachtree Rd NE Apt 531",
    "sg:city":"Atlanta",
    "sg:classifiers":[
        {
            "category":"Building & Trades",
            "subcategory":"Cleaning & Sanitation",
            "type":"Services"
        }
    ],
    "sg:phone":"+1 678 886 1714",
    "sg:postcode":"30319",
    "sg:province":"GA",
    "sg:tags":[
        "home"
    ],
    "sg:website":"www.maidinusa.com|www.maidinusa.net",
    "wof:name":"Maid In USA",
    "wof:placetype":"venue"
},
  "geometry": {"coordinates":[-84.34841900000001,33.857359],"type":"Point"}
}