{
  "type": "Feature",
  "properties": {
    "addr:full":"4355 Johns Creek Pkwy Suwanee GA 30024",
    "addr:housenumber":"4355",
    "addr:postcode":"30024",
    "addr:street":"Johns Creek Pkwy",
    "iso:country":"US",
    "sg:address":"4355 Johns Creek Pkwy",
    "sg:city":"Suwanee",
    "sg:classifiers":[
        {
            "category":"Health Services",
            "subcategory":"Doctor",
            "type":"Services"
        }
    ],
    "sg:phone":"+1 770 623 0008",
    "sg:postcode":"30024",
    "sg:province":"GA",
    "sg:tags":[
        "medicine",
        "internal"
    ],
    "wof:name":"Paul Internal Medicine Associates",
    "wof:placetype":"venue"
},
  "geometry": {"coordinates":[-84.17259799999999,34.071165],"type":"Point"}
}