{
  "type": "Feature",
  "properties": {
    "addr:full":"313 E Screven St Quitman GA 31643",
    "addr:housenumber":"313",
    "addr:postcode":"31643",
    "addr:street":"E Screven St",
    "iso:country":"US",
    "sg:address":"313 E Screven St",
    "sg:city":"Quitman",
    "sg:classifiers":[
        {
            "category":"Travel",
            "subcategory":"Hotels & Motels",
            "type":"Entertainment"
        },
        {
            "category":"Personal",
            "type":"Services"
        }
    ],
    "sg:phone":"+1 229 242 5139",
    "sg:postcode":"31643",
    "sg:province":"GA",
    "sg:tags":[
        "concierge",
        "assistant"
    ],
    "wof:name":"Knot Just Weddings",
    "wof:placetype":"venue"
},
  "geometry": {"coordinates":[-83.558074,30.784815],"type":"Point"}
}