{
  "type": "Feature",
  "properties": {
    "addr:full":"325 Schub Rd Clarkesville GA 30523",
    "addr:housenumber":"325",
    "addr:postcode":"30523",
    "addr:street":"Schub Rd",
    "iso:country":"US",
    "sg:address":"325 Schub Rd",
    "sg:city":"Clarkesville",
    "sg:classifiers":[
        {
            "category":"Building & Trades",
            "subcategory":"Landscaping Services",
            "type":"Services"
        }
    ],
    "sg:phone":"+1 706 754 5472",
    "sg:postcode":"30523",
    "sg:province":"GA",
    "wof:name":"David Horton Art and Design",
    "wof:placetype":"venue"
},
  "geometry": {"coordinates":[-83.61941,34.655432],"type":"Point"}
}