{
  "type": "Feature",
  "properties": {
    "iso:country":"US",
    "sg:address":"110 Florida Ave",
    "sg:city":"Bremen",
    "sg:classifiers":[
        {
            "category":"Professional",
            "type":"Services"
        }
    ],
    "sg:phone":"+1 770 537 2003",
    "sg:postcode":"30110",
    "sg:province":"GA",
    "wof:name":"Herman Parker Rev",
    "wof:placetype":"venue"
},
  "geometry": {"coordinates":[-85.14079099999999,33.722967],"type":"Point"}
}