{
  "type": "Feature",
  "properties": {
    "addr:full":"904 Akin Dr Savannah GA 31407",
    "addr:housenumber":"904",
    "addr:postcode":"31407",
    "addr:street":"Akin Dr",
    "iso:country":"US",
    "sg:address":"904 Akin Dr",
    "sg:city":"Savannah",
    "sg:classifiers":[
        {
            "category":"Organizations",
            "subcategory":"Religious Organization",
            "type":"Services"
        }
    ],
    "sg:phone":"+1 912 964 5244",
    "sg:postcode":"31407",
    "sg:province":"GA",
    "wof:name":"Mary Magdalene Ministries",
    "wof:placetype":"venue"
},
  "geometry": {"coordinates":[-81.166523,32.147455],"type":"Point"}
}