{
  "type": "Feature",
  "properties": {
    "iso:country":"US",
    "sg:address":"4100 Roswell Rd NE",
    "sg:city":"Atlanta",
    "sg:classifiers":[
        {
            "category":"Organizations",
            "subcategory":"Non-profit Organization",
            "type":"Services"
        }
    ],
    "sg:phone":"+1 404 943 0002",
    "sg:postcode":"30342",
    "sg:province":"GA",
    "sg:tags":[
        "service/non-profit",
        "community"
    ],
    "wof:name":"Buckhead Community Fellowship",
    "wof:placetype":"venue"
},
  "geometry": {"coordinates":[-84.382845,33.867587],"type":"Point"}
}