{
  "type": "Feature",
  "properties": {
    "iso:country":"US",
    "sg:address":"6320 Sugarloaf Pkwy",
    "sg:city":"Duluth",
    "sg:classifiers":[
        {
            "category":"Restaurant",
            "type":"Food & Drink"
        }
    ],
    "sg:menulink":"http://www.allmenus.com/ga/suwanee-duluth/241805-loafing-leprechaun/menu/",
    "sg:phone":"+1 678 218 0800",
    "sg:postcode":"30097",
    "sg:province":"GA",
    "sg:tags":[
        "irish"
    ],
    "wof:name":"Loafing Leprechaun",
    "wof:placetype":"venue"
},
  "geometry": {"coordinates":[-84.088875,33.989986],"type":"Point"}
}