{
  "type": "Feature",
  "properties": {
    "addr:full":"624 Holcomb Bridge Rd Roswell GA 30076",
    "addr:housenumber":"624",
    "addr:postcode":"30076",
    "addr:street":"Holcomb Bridge Rd",
    "iso:country":"US",
    "sg:address":"624 Holcomb Bridge Rd",
    "sg:city":"Roswell",
    "sg:classifiers":[
        {
            "category":"Shopping",
            "subcategory":"Computers & Home Electronics",
            "type":"Retail Goods"
        }
    ],
    "sg:phone":"+1 770 650 6683",
    "sg:postcode":"30076",
    "sg:province":"GA",
    "sg:tags":[
        "software"
    ],
    "sg:website":"www.idi-usa.com",
    "wof:name":"Interactive Designs Inc",
    "wof:placetype":"venue"
},
  "geometry": {"coordinates":[-84.341008,34.033108],"type":"Point"}
}