{
  "type": "Feature",
  "properties": {
    "addr:full":"4100 Spring Cove Dr Duluth GA 30097",
    "addr:housenumber":"4100",
    "addr:postcode":"30097",
    "addr:street":"Spring Cove Dr",
    "iso:country":"US",
    "sg:address":"4100 Spring Cove Dr",
    "sg:city":"Duluth",
    "sg:classifiers":[
        {
            "category":"Professional",
            "type":"Services"
        }
    ],
    "sg:phone":"+1 770 623 0416",
    "sg:postcode":"30097",
    "sg:province":"GA",
    "wof:name":"Massa Ent Inc",
    "wof:placetype":"venue"
},
  "geometry": {"coordinates":[-84.138003,34.024906],"type":"Point"}
}