{
  "type": "Feature",
  "properties": {
    "iso:country":"US",
    "sg:address":"5850 Stoneleigh Dr",
    "sg:city":"Suwanee",
    "sg:classifiers":[
        {
            "category":"Professional",
            "subcategory":"Management & Consulting",
            "type":"Services"
        }
    ],
    "sg:phone":"+1 770 888 4361",
    "sg:postcode":"30024",
    "sg:province":"GA",
    "wof:name":"Bear Marketing Group Inc",
    "wof:placetype":"venue"
},
  "geometry": {"coordinates":[-84.159553,34.095135],"type":"Point"}
}