{
  "type": "Feature",
  "properties": {
    "addr:full":"2520 Cobb Pkwy NW Kennesaw GA 30152",
    "addr:housenumber":"2520",
    "addr:postcode":"30152",
    "addr:street":"Cobb Pkwy Nw",
    "iso:country":"US",
    "sg:address":"2520 Cobb Pkwy NW",
    "sg:city":"Kennesaw",
    "sg:classifiers":[
        {
            "category":"Food & Beverages",
            "subcategory":"Groceries & Convenience Stores",
            "type":"Retail Goods"
        }
    ],
    "sg:phone":"+1 770 794 9998",
    "sg:postcode":"30152",
    "sg:province":"GA",
    "wof:name":"Popal Enterprises Inc",
    "wof:placetype":"venue"
},
  "geometry": {"coordinates":[-84.615442,34.015663],"type":"Point"}
}