{
  "type": "Feature",
  "properties": {
    "iso:country":"US",
    "sg:address":"2110 Austell Rd SW",
    "sg:city":"Marietta",
    "sg:classifiers":[
        {
            "category":"Retail",
            "subcategory":"Repair Shop",
            "type":"Services"
        },
        {
            "category":"Professional",
            "subcategory":"Detective & Security Services",
            "type":"Services"
        }
    ],
    "sg:phone":"+1 770 919 0999",
    "sg:postcode":"30008",
    "sg:province":"GA",
    "sg:tags":[
        "skip",
        "tracing",
        "bail",
        "bond"
    ],
    "sg:website":"http://www.springubailbonds.com",
    "wof:name":"Spring U Bail Bonds",
    "wof:placetype":"venue"
},
  "geometry": {"coordinates":[-84.568753,33.902248],"type":"Point"}
}