{
  "type": "Feature",
  "properties": {
    "iso:country":"US",
    "sg:address":"909 Eagles Landing Pkwy Ste 100",
    "sg:city":"Stockbridge",
    "sg:classifiers":[
        {
            "category":"Retail",
            "subcategory":"Laundry & Dry Cleaning",
            "type":"Services"
        }
    ],
    "sg:phone":"+1 770 474 8886",
    "sg:postcode":"30281",
    "sg:province":"GA",
    "wof:name":"Courtesy Cleaners At Eagles Landing",
    "wof:placetype":"venue"
},
  "geometry": {"coordinates":[-84.220596,33.512001],"type":"Point"}
}