{
  "type": "Feature",
  "properties": {
    "addr:full":"3662 Oak St NW Duluth GA 30096",
    "addr:housenumber":"3662",
    "addr:postcode":"30096",
    "addr:street":"Oak St Nw",
    "iso:country":"US",
    "sg:address":"3662 Oak St NW",
    "sg:city":"Duluth",
    "sg:classifiers":[
        {
            "category":"Manufacturing",
            "subcategory":"Building Materials",
            "type":"Manufacturing & Wholesale Goods"
        }
    ],
    "sg:phone":"+1 770 476 5049",
    "sg:postcode":"30096",
    "sg:province":"GA",
    "sg:tags":[
        "mfg",
        "wood",
        "kitchen",
        "cabinet"
    ],
    "wof:name":"Corlock Custom Cabinets Inc",
    "wof:placetype":"venue"
},
  "geometry": {"coordinates":[-84.14007599999999,34.007539],"type":"Point"}
}