{
  "type": "Feature",
  "properties": {
    "iso:country":"US",
    "sg:address":"603 N Mitchell St",
    "sg:city":"Thomasville",
    "sg:classifiers":[
        {
            "category":"Professional",
            "subcategory":"Business Services",
            "type":"Services"
        }
    ],
    "sg:phone":"+1 229 228 1052",
    "sg:postcode":"31792",
    "sg:province":"GA",
    "sg:tags":[
        "recording",
        "production"
    ],
    "wof:name":"Ladons Studio",
    "wof:placetype":"venue"
},
  "geometry": {"coordinates":[-83.977733,30.850199],"type":"Point"}
}