{
  "type": "Feature",
  "properties": {
    "addr:full":"912 Highland Dr Hinesville GA 31313",
    "addr:housenumber":"912",
    "addr:postcode":"31313",
    "addr:street":"Highland Dr",
    "iso:country":"US",
    "sg:address":"912 Highland Dr",
    "sg:city":"Hinesville",
    "sg:classifiers":[
        {
            "category":"Building & Trades",
            "subcategory":"Construction",
            "type":"Services"
        }
    ],
    "sg:phone":"+1 912 222 9868",
    "sg:postcode":"31313",
    "sg:province":"GA",
    "sg:tags":[
        "residential"
    ],
    "wof:name":"Innovative Construction",
    "wof:placetype":"venue"
},
  "geometry": {"coordinates":[-81.621585,31.844283],"type":"Point"}
}