{
  "type": "Feature",
  "properties": {
    "addr:full":"501 Booth Rd Warner Robins GA 31088",
    "addr:housenumber":"501",
    "addr:postcode":"31088",
    "addr:street":"Booth Rd",
    "iso:country":"US",
    "sg:address":"501 Booth Rd",
    "sg:city":"Warner Robins",
    "sg:classifiers":[
        {
            "category":"Autos & Motor Vehicles",
            "subcategory":"Fuel & Gas Station",
            "type":"Retail Goods"
        }
    ],
    "sg:phone":"+1 478 929 5414",
    "sg:postcode":"31088",
    "sg:province":"GA",
    "sg:website":"www.murphyusa.com",
    "wof:name":"Murphy USA",
    "wof:placetype":"venue"
},
  "geometry": {"coordinates":[-83.614593,32.59269],"type":"Point"}
}