{
  "type": "Feature",
  "properties": {
    "iso:country":"US",
    "sg:address":"1003 Virginia Ave",
    "sg:city":"Atlanta",
    "sg:classifiers":[
        {
            "category":"Health Services",
            "subcategory":"Clinic",
            "type":"Services"
        }
    ],
    "sg:phone":"+1 404 766 9625",
    "sg:postcode":"30354",
    "sg:province":"GA",
    "sg:tags":[
        "information",
        "alcoholism",
        "treatment"
    ],
    "wof:name":"Helen Keller National Center For Deaf-Blind Youths And Adults",
    "wof:placetype":"venue"
},
  "geometry": {"coordinates":[-84.42289700000001,33.658901],"type":"Point"}
}