{
  "type": "Feature",
  "properties": {
    "addr:full":"6250 Peachtree-Dunwoody Rd Atlanta GA 30328",
    "addr:housenumber":"6250",
    "addr:postcode":"30328",
    "addr:street":"Peachtree-Dunwoody Rd",
    "iso:country":"US",
    "sg:address":"6250 Peachtree-Dunwoody Rd",
    "sg:city":"Atlanta",
    "sg:classifiers":[
        {
            "category":"Travel",
            "subcategory":"Hotels & Motels",
            "type":"Entertainment"
        }
    ],
    "sg:phone":"+1 770 393 1000",
    "sg:postcode":"30328",
    "sg:province":"GA",
    "sg:website":"www.marriott.com",
    "wof:name":"Courtyard Atlanta Perimeter Center",
    "wof:placetype":"venue"
},
  "geometry": {"coordinates":[-84.35352399999999,33.925697],"type":"Point"}
}