{
  "type": "Feature",
  "properties": {
    "addr:full":"1601 Ga Highway 40 E Kingsland GA 31548",
    "addr:housenumber":"1601",
    "addr:postcode":"31548",
    "addr:street":"Ga Highway 40 E",
    "iso:country":"US",
    "sg:address":"1601 Ga Highway 40 E",
    "sg:city":"Kingsland",
    "sg:classifiers":[
        {
            "category":"Food & Beverages",
            "subcategory":"Supermarket",
            "type":"Retail Goods"
        }
    ],
    "sg:phone":"+1 912 729 6116",
    "sg:postcode":"31548",
    "sg:province":"GA",
    "sg:tags":[
        "super",
        "store"
    ],
    "sg:website":"http://www.kmart.com",
    "wof:name":"Kmart",
    "wof:placetype":"venue"
},
  "geometry": {"coordinates":[-81.65201,30.788463],"type":"Point"}
}