{
  "type": "Feature",
  "properties": {
    "iso:country":"US",
    "sg:address":"81 Cobb St",
    "sg:city":"Jefferson",
    "sg:classifiers":[
        {
            "category":"Shopping",
            "type":"Retail Goods"
        }
    ],
    "sg:phone":"+1 706 367 7724",
    "sg:postcode":"30549",
    "sg:province":"GA",
    "sg:tags":[
        "plant",
        "flower",
        "tree",
        "artificial"
    ],
    "sg:website":"www.decoraccent.com",
    "wof:name":"Floral Designs Intl",
    "wof:placetype":"venue"
},
  "geometry": {"coordinates":[-83.58211300000001,34.115777],"type":"Point"}
}