{
  "type": "Feature",
  "properties": {
    "addr:full":"6675 State Rte 16 E Senoia GA 30276",
    "addr:housenumber":"6675",
    "addr:postcode":"30276",
    "addr:street":"State Rte 16 E",
    "iso:country":"US",
    "sg:address":"6675 State Rte 16 E",
    "sg:city":"Senoia",
    "sg:classifiers":[
        {
            "category":"Education",
            "subcategory":"School",
            "type":"Public Place"
        }
    ],
    "sg:phone":"+1 770 599 6888",
    "sg:postcode":"30276",
    "sg:province":"GA",
    "wof:name":"Peachtree Baptist Academy",
    "wof:placetype":"venue"
},
  "geometry": {"coordinates":[-84.588286,33.297195],"type":"Point"}
}