{
  "type": "Feature",
  "properties": {
    "addr:full":"2678 Hummingbird Dr Duluth GA 30096",
    "addr:housenumber":"2678",
    "addr:postcode":"30096",
    "addr:street":"Hummingbird Dr",
    "iso:country":"US",
    "sg:address":"2678 Hummingbird Dr",
    "sg:city":"Duluth",
    "sg:classifiers":[
        {
            "category":"Professional",
            "subcategory":"Computer Services",
            "type":"Services"
        }
    ],
    "sg:phone":"+1 770 963 9492",
    "sg:postcode":"30096",
    "sg:province":"GA",
    "sg:tags":[
        "related"
    ],
    "wof:name":"Horizon Controls Inc",
    "wof:placetype":"venue"
},
  "geometry": {"coordinates":[-84.130703,33.97775],"type":"Point"}
}