{
  "type": "Feature",
  "properties": {
    "addr:full":"4801 S Main St Acworth GA 30101",
    "addr:housenumber":"4801",
    "addr:postcode":"30101",
    "addr:street":"S Main St",
    "iso:country":"US",
    "sg:address":"4801 S Main St",
    "sg:city":"Acworth",
    "sg:classifiers":[
        {
            "category":"Banks & Credit Unions",
            "subcategory":"Investment Brokerage",
            "type":"Services"
        },
        {
            "category":"Banks & Credit Unions",
            "subcategory":"Bank",
            "type":"Services"
        },
        {
            "category":"Banks & Credit Unions",
            "subcategory":"Financial Services",
            "type":"Services"
        }
    ],
    "sg:phone":"+1 770 529 9009",
    "sg:postcode":"30101",
    "sg:province":"GA",
    "sg:tags":[
        "mutual",
        "retirement",
        "broker",
        "fund",
        "planning",
        "security",
        "bond",
        "stock"
    ],
    "sg:website":"http://www.edwardjones.com/en_US/fa/index.html&CIRN=388613",
    "wof:name":"Edward Jones - Financial Advisor: JIM NANCE",
    "wof:placetype":"venue"
},
  "geometry": {"coordinates":[-84.676689,34.065701],"type":"Point"}
}