{
  "type": "Feature",
  "properties": {
    "addr:full":"1918 Shields Rd Dalton GA 30720",
    "addr:housenumber":"1918",
    "addr:postcode":"30720",
    "addr:street":"Shields Rd",
    "iso:country":"US",
    "sg:address":"1918 Shields Rd",
    "sg:city":"Dalton",
    "sg:classifiers":[
        {
            "category":"Building & Trades",
            "subcategory":"Construction",
            "type":"Services"
        }
    ],
    "sg:phone":"+1 706 313 6429",
    "sg:postcode":"30720",
    "sg:province":"GA",
    "sg:tags":[
        "wallcoverings-installation",
        "wallpaper",
        "painting",
        "contractor"
    ],
    "wof:name":"Jeff's Quality Painting",
    "wof:placetype":"venue"
},
  "geometry": {"coordinates":[-84.997286,34.755595],"type":"Point"}
}