{
  "type": "Feature",
  "properties": {
    "iso:country":"US",
    "sg:address":"1513 Glencrest Trl NE",
    "sg:city":"Lawrenceville",
    "sg:classifiers":[
        {
            "category":"Building & Trades",
            "subcategory":"Electrical",
            "type":"Services"
        }
    ],
    "sg:phone":"+1 678 377 1810",
    "sg:postcode":"30043",
    "sg:province":"GA",
    "sg:tags":[
        "electrical",
        "contractor"
    ],
    "wof:name":"Electrical Assoc & Labor",
    "wof:placetype":"venue"
},
  "geometry": {"coordinates":[-84.00630099999999,33.998287],"type":"Point"}
}