{
  "type": "Feature",
  "properties": {
    "iso:country":"US",
    "sg:address":"1525 Baytree Rd",
    "sg:city":"Valdosta",
    "sg:classifiers":[
        {
            "category":"Food & Beverages",
            "subcategory":"Specialty",
            "type":"Retail Goods"
        }
    ],
    "sg:phone":"+1 229 241 9573",
    "sg:postcode":"31602",
    "sg:province":"GA",
    "sg:tags":[
        "health",
        "diet"
    ],
    "wof:name":"Metabolic Research Ctr",
    "wof:placetype":"venue"
},
  "geometry": {"coordinates":[-83.31328499999999,30.84687],"type":"Point"}
}