{
  "type": "Feature",
  "properties": {
    "addr:full":"7350 Campbellton Rd SW Atlanta GA 30331",
    "addr:housenumber":"7350",
    "addr:postcode":"30331",
    "addr:street":"Campbellton Rd Sw",
    "iso:country":"US",
    "sg:address":"7350 Campbellton Rd SW",
    "sg:city":"Atlanta",
    "sg:classifiers":[
        {
            "category":"Professional",
            "subcategory":"Computer Services",
            "type":"Services"
        }
    ],
    "sg:phone":"+1 404 844 3674",
    "sg:postcode":"30331",
    "sg:province":"GA",
    "sg:tags":[
        "repair"
    ],
    "sg:website":"www.moultonshottas.com",
    "wof:name":"Moulton Shottas",
    "wof:placetype":"venue"
},
  "geometry": {"coordinates":[-84.62536900000001,33.692803],"type":"Point"}
}