{
  "type": "Feature",
  "properties": {
    "addr:full":"4774 New Jesup Hwy Brunswick GA 31520",
    "addr:housenumber":"4774",
    "addr:postcode":"31520",
    "addr:street":"New Jesup Hwy",
    "iso:country":"US",
    "sg:address":"4774 New Jesup Hwy",
    "sg:city":"Brunswick",
    "sg:classifiers":[
        {
            "category":"Utilities",
            "subcategory":"Water",
            "type":"Services"
        },
        {
            "category":"Retail",
            "subcategory":"Repair Shop",
            "type":"Services"
        }
    ],
    "sg:phone":"+1 912 265 2603",
    "sg:postcode":"31520",
    "sg:province":"GA",
    "sg:tags":[
        "softening",
        "well",
        "contractor",
        "equipment",
        "pump",
        "conditioning",
        "pumps-service",
        "drilling"
    ],
    "sg:website":"http://woodrowsapp.com",
    "wof:name":"Woodrow Sapp Well Drilling",
    "wof:placetype":"venue"
},
  "geometry": {"coordinates":[-81.514855,31.213105],"type":"Point"}
}