{
  "type": "Feature",
  "properties": {
    "iso:country":"US",
    "sg:address":"2945 Main St W",
    "sg:city":"Snellville",
    "sg:classifiers":[
        {
            "category":"Social Services",
            "subcategory":"Child Care",
            "type":"Services"
        },
        {
            "category":"Education",
            "subcategory":"Preschool",
            "type":"Public Place"
        },
        {
            "category":"Education",
            "subcategory":"School",
            "type":"Public Place"
        }
    ],
    "sg:phone":"+1 770 979 3666",
    "sg:postcode":"30078",
    "sg:province":"GA",
    "sg:tags":[
        "elementary",
        "day"
    ],
    "wof:name":"Wolf Creek Day Camp",
    "wof:placetype":"venue"
},
  "geometry": {"coordinates":[-84.03630099999999,33.8531],"type":"Point"}
}