{
  "type": "Feature",
  "properties": {
    "addr:full":"1354 Mercer University Dr Macon GA 31201",
    "addr:housenumber":"1354",
    "addr:postcode":"31201",
    "addr:street":"Mercer University Dr",
    "iso:country":"US",
    "sg:address":"1354 Mercer University Dr",
    "sg:city":"Macon",
    "sg:classifiers":[
        {
            "category":"Personal",
            "subcategory":"Beauty Salon",
            "type":"Services"
        }
    ],
    "sg:phone":"+1 478 405 6107",
    "sg:postcode":"31201",
    "sg:province":"GA",
    "sg:tags":[
        "shop"
    ],
    "wof:name":"University Hair",
    "wof:placetype":"venue"
},
  "geometry": {"coordinates":[-83.652051,32.825586],"type":"Point"}
}