{
  "type": "Feature",
  "properties": {
    "iso:country":"US",
    "sg:address":"535 Cobb Pkwy",
    "sg:city":"Marietta",
    "sg:classifiers":[
        {
            "category":"Home & Garden",
            "subcategory":"Home Furnishings",
            "type":"Retail Goods"
        }
    ],
    "sg:phone":"+1 770 428 2825",
    "sg:postcode":"30062",
    "sg:province":"GA",
    "sg:tags":[
        "fireplace"
    ],
    "wof:name":"Metro House Of Fire Inc",
    "wof:placetype":"venue"
},
  "geometry": {"coordinates":[-84.532999,33.964578],"type":"Point"}
}