{
  "type": "Feature",
  "properties": {
    "addr:full":"641 Sardis Church Rd Moultrie GA 31788",
    "addr:housenumber":"641",
    "addr:postcode":"31788",
    "addr:street":"Sardis Church Rd",
    "iso:country":"US",
    "sg:address":"641 Sardis Church Rd",
    "sg:city":"Moultrie",
    "sg:classifiers":[
        {
            "category":"Utilities",
            "subcategory":"Telephone",
            "type":"Services"
        }
    ],
    "sg:phone":"+1 229 985 2929",
    "sg:postcode":"31788",
    "sg:province":"GA",
    "sg:tags":[
        "communications"
    ],
    "wof:name":"Howard Telephone Service",
    "wof:placetype":"venue"
},
  "geometry": {"coordinates":[-83.716638,31.153087],"type":"Point"}
}