{
  "type": "Feature",
  "properties": {
    "iso:country":"US",
    "sg:address":"2654 Tommy Lee Cook Rd",
    "sg:city":"Newnan",
    "sg:classifiers":[
        {
            "category":"Building & Trades",
            "subcategory":"Construction",
            "type":"Services"
        }
    ],
    "sg:phone":"+1 770 463 1821",
    "sg:postcode":"30263",
    "sg:province":"GA",
    "sg:tags":[
        "house"
    ],
    "wof:name":"Hdw Construction Inc",
    "wof:placetype":"venue"
},
  "geometry": {"coordinates":[-84.740779,33.495632],"type":"Point"}
}