{
  "type": "Feature",
  "properties": {
    "iso:country":"US",
    "sg:address":"1049 Holcombe Rd",
    "sg:city":"Decatur",
    "sg:classifiers":[
        {
            "category":"Shopping",
            "subcategory":"Clothing, Apparel, & Fashions",
            "type":"Retail Goods"
        }
    ],
    "sg:phone":"+1 404 438 7196",
    "sg:postcode":"30032",
    "sg:province":"GA",
    "sg:tags":[
        "dressmaker"
    ],
    "wof:name":"Mahogany Designs",
    "wof:placetype":"venue"
},
  "geometry": {"coordinates":[-84.23379,33.764136],"type":"Point"}
}