{
  "type": "Feature",
  "properties": {
    "iso:country":"US",
    "sg:address":"1548 Mount Vernon Rd",
    "sg:city":"Atlanta",
    "sg:classifiers":[
        {
            "category":"Social Services",
            "type":"Services"
        }
    ],
    "sg:phone":"+1 770 698 0801",
    "sg:postcode":"30338",
    "sg:province":"GA",
    "sg:tags":[
        "counseling",
        "senior",
        "citizen"
    ],
    "sg:website":"www.palsonline.org",
    "wof:name":"Perimeter Adult Learning & Ser",
    "wof:placetype":"venue"
},
  "geometry": {"coordinates":[-84.33615399999999,33.945059],"type":"Point"}
}