{
  "type": "Feature",
  "properties": {
    "addr:full":"102 S Florida St Bainbridge GA 39817",
    "addr:housenumber":"102",
    "addr:postcode":"39817",
    "addr:street":"S Florida St",
    "iso:country":"US",
    "sg:address":"102 S Florida St",
    "sg:city":"Bainbridge",
    "sg:classifiers":[
        {
            "category":"Professional",
            "subcategory":"Lawyer & Legal Services",
            "type":"Services"
        }
    ],
    "sg:phone":"+1 229 246 0971",
    "sg:postcode":"39817",
    "sg:province":"GA",
    "sg:tags":[
        "attorney"
    ],
    "wof:name":"James M Pace Jr",
    "wof:placetype":"venue"
},
  "geometry": {"coordinates":[-84.578171,30.905794],"type":"Point"}
}