{
  "type": "Feature",
  "properties": {
    "addr:full":"2041 Greenland Rd Blythe GA 30805",
    "addr:housenumber":"2041",
    "addr:postcode":"30805",
    "addr:street":"Greenland Rd",
    "iso:country":"US",
    "sg:address":"2041 Greenland Rd",
    "sg:city":"Blythe",
    "sg:classifiers":[
        {
            "category":"Social Services",
            "subcategory":"Child Care",
            "type":"Services"
        }
    ],
    "sg:phone":"+1 706 592 4770",
    "sg:postcode":"30805",
    "sg:province":"GA",
    "wof:name":"Lavonne's Christian Learning",
    "wof:placetype":"venue"
},
  "geometry": {"coordinates":[-82.136528,33.343721],"type":"Point"}
}