{
  "type": "Feature",
  "properties": {
    "addr:full":"229 Graves Rd Spr Acworth GA 30101",
    "addr:housenumber":"229",
    "addr:postcode":"30101",
    "addr:street":"Graves Rd Spr",
    "iso:country":"US",
    "sg:address":"229 Graves Rd Spr",
    "sg:city":"Acworth",
    "sg:classifiers":[
        {
            "category":"Building & Trades",
            "subcategory":"Construction",
            "type":"Services"
        }
    ],
    "sg:phone":"+1 770 529 4969",
    "sg:postcode":"30101",
    "sg:province":"GA",
    "sg:tags":[
        "house"
    ],
    "wof:name":"Haren Construction Co",
    "wof:placetype":"venue"
},
  "geometry": {"coordinates":[-84.76405200000001,34.065981],"type":"Point"}
}