{
  "type": "Feature",
  "properties": {
    "iso:country":"US",
    "sg:address":"638 Fairview Rd NW",
    "sg:city":"Calhoun",
    "sg:classifiers":[
        {
            "category":"Professional",
            "type":"Services"
        }
    ],
    "sg:phone":"+1 706 629 0071",
    "sg:postcode":"30701",
    "sg:province":"GA",
    "wof:name":"Mark King",
    "wof:placetype":"venue"
},
  "geometry": {"coordinates":[-84.987391,34.557423],"type":"Point"}
}