{
  "type": "Feature",
  "properties": {
    "iso:country":"US",
    "sg:address":"137 Johnson Ferry Rd Ste 1100",
    "sg:city":"Marietta",
    "sg:classifiers":[
        {
            "category":"Social Services",
            "subcategory":"Child Care",
            "type":"Services"
        }
    ],
    "sg:phone":"+1 770 956 9718",
    "sg:postcode":"30068",
    "sg:province":"GA",
    "sg:tags":[
        "day"
    ],
    "wof:name":"Cobb Prep School",
    "wof:placetype":"venue"
},
  "geometry": {"coordinates":[-84.41185900000001,33.954086],"type":"Point"}
}