{
  "type": "Feature",
  "properties": {
    "addr:full":"2217 Irvindale Way Atlanta GA 30341",
    "addr:housenumber":"2217",
    "addr:postcode":"30341",
    "addr:street":"Irvindale Way",
    "iso:country":"US",
    "sg:address":"2217 Irvindale Way",
    "sg:city":"Atlanta",
    "sg:classifiers":[
        {
            "category":"Home & Garden",
            "subcategory":"Furniture",
            "type":"Retail Goods"
        }
    ],
    "sg:phone":"+1 678 281 0559",
    "sg:postcode":"30341",
    "sg:province":"GA",
    "sg:tags":[
        "builder",
        "custom"
    ],
    "wof:name":"R L Goins",
    "wof:placetype":"venue"
},
  "geometry": {"coordinates":[-84.296666,33.897534],"type":"Point"}
}