{
  "type": "Feature",
  "properties": {
    "iso:country":"US",
    "sg:address":"207 Kellett Rd NE",
    "sg:city":"Rome",
    "sg:classifiers":[
        {
            "category":"Recreation",
            "type":"Entertainment"
        }
    ],
    "sg:phone":"+1 706 232 6656",
    "sg:postcode":"30165",
    "sg:province":"GA",
    "sg:tags":[
        "stable"
    ],
    "wof:name":"Seven Hills Equestrian Ctr",
    "wof:placetype":"venue"
},
  "geometry": {"coordinates":[-85.146777,34.392236],"type":"Point"}
}