{
  "type": "Feature",
  "properties": {
    "addr:full":"137 New St Decatur GA 30030",
    "addr:housenumber":"137",
    "addr:postcode":"30030",
    "addr:street":"New St",
    "iso:country":"US",
    "sg:address":"137 New St",
    "sg:city":"Decatur",
    "sg:classifiers":[
        {
            "category":"Sports & Exercise",
            "subcategory":"Gym",
            "type":"Entertainment"
        }
    ],
    "sg:phone":"+1 678 687 2983",
    "sg:postcode":"30030",
    "sg:province":"GA",
    "sg:tags":[
        "trainer"
    ],
    "sg:website":"www.decaturboxing.com",
    "wof:name":"Decatur Boxing Club",
    "wof:placetype":"venue"
},
  "geometry": {"coordinates":[-84.285365,33.771849],"type":"Point"}
}