{
  "type": "Feature",
  "properties": {
    "iso:country":"US",
    "sg:address":"1417 Buford Dr",
    "sg:city":"Lawrenceville",
    "sg:classifiers":[
        {
            "category":"Restaurant",
            "type":"Food & Drink"
        }
    ],
    "sg:phone":"+1 678 377 9600",
    "sg:postcode":"30043",
    "sg:province":"GA",
    "sg:tags":[
        "eating"
    ],
    "wof:name":"Gullys Burger Delite Inc",
    "wof:placetype":"venue"
},
  "geometry": {"coordinates":[-83.988719,34.002596],"type":"Point"}
}