{
  "type": "Feature",
  "properties": {
    "iso:country":"US",
    "sg:address":"624 Holly Dr",
    "sg:city":"Albany",
    "sg:classifiers":[
        {
            "category":"Food & Beverages",
            "subcategory":"Groceries & Convenience Stores",
            "type":"Retail Goods"
        }
    ],
    "sg:phone":"+1 229 432 6727",
    "sg:postcode":"31705",
    "sg:province":"GA",
    "wof:name":"Flash Foods",
    "wof:placetype":"venue"
},
  "geometry": {"coordinates":[-84.11726400000001,31.529093],"type":"Point"}
}