{
  "type": "Feature",
  "properties": {
    "iso:country":"US",
    "sg:address":"33 SW Broad St",
    "sg:city":"Fairburn",
    "sg:classifiers":[
        {
            "category":"Personal",
            "subcategory":"Beauty Salon",
            "type":"Services"
        }
    ],
    "sg:phone":"+1 770 964 3488",
    "sg:postcode":"30213",
    "sg:province":"GA",
    "sg:tags":[
        "shop"
    ],
    "wof:name":"Dels Designs",
    "wof:placetype":"venue"
},
  "geometry": {"coordinates":[-84.58195000000001,33.566699],"type":"Point"}
}