{
  "type": "Feature",
  "properties": {
    "addr:full":"5361 Reynolds St Savannah GA 31405",
    "addr:housenumber":"5361",
    "addr:postcode":"31405",
    "addr:street":"Reynolds St",
    "iso:country":"US",
    "sg:address":"5361 Reynolds St",
    "sg:city":"Savannah",
    "sg:classifiers":[
        {
            "category":"Health Services",
            "subcategory":"Doctor",
            "type":"Services"
        }
    ],
    "sg:phone":"+1 912 638 9992",
    "sg:postcode":"31405",
    "sg:province":"GA",
    "sg:tags":[
        "medical"
    ],
    "wof:name":"Luke J Curtsinger MD",
    "wof:placetype":"venue"
},
  "geometry": {"coordinates":[-81.10199799999999,32.026892],"type":"Point"}
}