{
  "type": "Feature",
  "properties": {
    "addr:full":"208 Hedgewood Ln Peachtree City GA 30269",
    "addr:housenumber":"208",
    "addr:postcode":"30269",
    "addr:street":"Hedgewood Ln",
    "iso:country":"US",
    "sg:address":"208 Hedgewood Ln",
    "sg:city":"Peachtree City",
    "sg:classifiers":[
        {
            "category":"Building & Trades",
            "subcategory":"Electrical",
            "type":"Services"
        }
    ],
    "sg:phone":"+1 770 631 1117",
    "sg:postcode":"30269",
    "sg:province":"GA",
    "sg:tags":[
        "electrical",
        "contractor"
    ],
    "wof:name":"Quick Silver Media",
    "wof:placetype":"venue"
},
  "geometry": {"coordinates":[-84.552291,33.394554],"type":"Point"}
}