{
  "type": "Feature",
  "properties": {
    "iso:country":"US",
    "sg:address":"7175 Mount Zion Blvd",
    "sg:city":"Jonesboro",
    "sg:classifiers":[
        {
            "category":"Education",
            "subcategory":"Vocational School",
            "type":"Public Place"
        }
    ],
    "sg:phone":"+1 770 472 7990",
    "sg:postcode":"30236",
    "sg:province":"GA",
    "wof:name":"Hill Academy For Christian",
    "wof:placetype":"venue"
},
  "geometry": {"coordinates":[-84.324349,33.55992],"type":"Point"}
}