{
  "type": "Feature",
  "properties": {
    "addr:full":"401 E Main St Forsyth GA 31029",
    "addr:housenumber":"401",
    "addr:postcode":"31029",
    "addr:street":"E Main St",
    "iso:country":"US",
    "sg:address":"401 E Main St",
    "sg:city":"Forsyth",
    "sg:classifiers":[
        {
            "category":"Social Services",
            "type":"Services"
        }
    ],
    "sg:phone":"+1 478 994 7002",
    "sg:postcode":"31029",
    "sg:province":"GA",
    "sg:tags":[
        "probation"
    ],
    "wof:name":"Monroe County Probation Office",
    "wof:placetype":"venue"
},
  "geometry": {"coordinates":[-83.927289,33.033493],"type":"Point"}
}