{
  "type": "Feature",
  "properties": {
    "iso:country":"US",
    "sg:address":"600 Spring St",
    "sg:city":"Dalton",
    "sg:classifiers":[
        {
            "category":"Shopping",
            "subcategory":"Clothing, Apparel, & Fashions",
            "type":"Retail Goods"
        }
    ],
    "sg:phone":"+1 706 278 3708",
    "sg:postcode":"30720",
    "sg:province":"GA",
    "wof:name":"Raisin Textile Inc",
    "wof:placetype":"venue"
},
  "geometry": {"coordinates":[-84.96858899999999,34.765978],"type":"Point"}
}