{
  "type": "Feature",
  "properties": {
    "addr:full":"4123 MacDuff Dr Douglasville GA 30135",
    "addr:housenumber":"4123",
    "addr:postcode":"30135",
    "addr:street":"Macduff Dr",
    "iso:country":"US",
    "sg:address":"4123 MacDuff Dr",
    "sg:city":"Douglasville",
    "sg:classifiers":[
        {
            "category":"Building & Trades",
            "subcategory":"Plumbing",
            "type":"Services"
        }
    ],
    "sg:phone":"+1 770 489 4155",
    "sg:postcode":"30135",
    "sg:province":"GA",
    "wof:name":"Advance Sewer & Drain",
    "wof:placetype":"venue"
},
  "geometry": {"coordinates":[-84.767197,33.693199],"type":"Point"}
}