{
  "type": "Feature",
  "properties": {
    "addr:full":"1612 Wingate Way Atlanta GA 30350",
    "addr:housenumber":"1612",
    "addr:postcode":"30350",
    "addr:street":"Wingate Way",
    "iso:country":"US",
    "sg:address":"1612 Wingate Way",
    "sg:city":"Atlanta",
    "sg:classifiers":[
        {
            "category":"Professional",
            "subcategory":"Management & Consulting",
            "type":"Services"
        }
    ],
    "sg:phone":"+1 404 249 1773",
    "sg:postcode":"30350",
    "sg:province":"GA",
    "sg:tags":[
        "consultant",
        "business"
    ],
    "wof:name":"Ron Montgomery",
    "wof:placetype":"venue"
},
  "geometry": {"coordinates":[-84.35113200000001,33.966768],"type":"Point"}
}