{
  "type": "Feature",
  "properties": {
    "addr:full":"4981 Flint Hill Rd Austell GA 30106",
    "addr:housenumber":"4981",
    "addr:postcode":"30106",
    "addr:street":"Flint Hill Rd",
    "iso:country":"US",
    "sg:address":"4981 Flint Hill Rd",
    "sg:city":"Austell",
    "sg:classifiers":[
        {
            "category":"Building & Trades",
            "subcategory":"Pest Control",
            "type":"Services"
        }
    ],
    "sg:phone":"+1 770 941 3159",
    "sg:postcode":"30106",
    "sg:province":"GA",
    "sg:tags":[
        "termite",
        "mothproofing"
    ],
    "wof:name":"West Pest Control",
    "wof:placetype":"venue"
},
  "geometry": {"coordinates":[-84.623521,33.832672],"type":"Point"}
}