{
  "type": "Feature",
  "properties": {
    "iso:country":"US",
    "sg:address":"732 Northside Dr E",
    "sg:city":"Statesboro",
    "sg:classifiers":[
        {
            "category":"Restaurant",
            "type":"Food & Drink"
        }
    ],
    "sg:phone":"+1 912 489 3803",
    "sg:postcode":"30458",
    "sg:province":"GA",
    "wof:name":"Krystal Quick",
    "wof:placetype":"venue"
},
  "geometry": {"coordinates":[-81.792384,32.464584],"type":"Point"}
}