{
  "type": "Feature",
  "properties": {
    "iso:country":"US",
    "sg:address":"100 S 6th St",
    "sg:city":"Warner Robins",
    "sg:classifiers":[
        {
            "category":"Professional",
            "subcategory":"Accounting & Tax Preparation",
            "type":"Services"
        }
    ],
    "sg:phone":"+1 478 923 3050",
    "sg:postcode":"31088",
    "sg:province":"GA",
    "wof:name":"K&V Business Services",
    "wof:placetype":"venue"
},
  "geometry": {"coordinates":[-83.60567399999999,32.619118],"type":"Point"}
}