{
  "type": "Feature",
  "properties": {
    "iso:country":"US",
    "sg:address":"248 Gennett Dr",
    "sg:city":"Jasper",
    "sg:classifiers":[
        {
            "category":"Personal",
            "type":"Services"
        }
    ],
    "sg:phone":"+1 706 253 1161",
    "sg:postcode":"30143",
    "sg:province":"GA",
    "wof:name":"Drolet Rudolphe",
    "wof:placetype":"venue"
},
  "geometry": {"coordinates":[-84.440602,34.479844],"type":"Point"}
}