{
  "type": "Feature",
  "properties": {
    "addr:full":"1977 Kimberly Village Ln SE Marietta GA 30067",
    "addr:housenumber":"1977",
    "addr:postcode":"30067",
    "addr:street":"Kimberly Village Ln Se",
    "iso:country":"US",
    "sg:address":"1977 Kimberly Village Ln SE",
    "sg:city":"Marietta",
    "sg:classifiers":[
        {
            "category":"Building & Trades",
            "subcategory":"Equipment Rental",
            "type":"Services"
        }
    ],
    "sg:phone":"+1 770 272 1907",
    "sg:postcode":"30067",
    "sg:province":"GA",
    "sg:tags":[
        "supplies-renting",
        "hospital",
        "wheelchairs-rental"
    ],
    "wof:name":"Covenant Wisdom",
    "wof:placetype":"venue"
},
  "geometry": {"coordinates":[-84.46974,33.907382],"type":"Point"}
}