{
  "type": "Feature",
  "properties": {
    "addr:full":"916 Snapping Shoals Rd Mcdonough GA 30252",
    "addr:housenumber":"916",
    "addr:postcode":"30252",
    "addr:street":"Snapping Shoals Rd",
    "iso:country":"US",
    "sg:address":"916 Snapping Shoals Rd",
    "sg:city":"Mcdonough",
    "sg:classifiers":[
        {
            "category":"Wholesale",
            "subcategory":"Machinery & Supplies",
            "type":"Manufacturing & Wholesale Goods"
        },
        {
            "category":"Manufacturing",
            "subcategory":"Paper Products",
            "type":"Manufacturing & Wholesale Goods"
        }
    ],
    "sg:phone":"+1 770 506 0200",
    "sg:postcode":"30252",
    "sg:province":"GA",
    "sg:tags":[
        "mfg",
        "tape",
        "masking"
    ],
    "wof:name":"Trim Tape Inc",
    "wof:placetype":"venue"
},
  "geometry": {"coordinates":[-84.017415,33.459467],"type":"Point"}
}