{
  "type": "Feature",
  "properties": {
    "addr:full":"66 Greenville St S Newnan GA 30263",
    "addr:housenumber":"66",
    "addr:postcode":"30263",
    "addr:street":"Greenville St S",
    "iso:country":"US",
    "sg:address":"66 Greenville St S",
    "sg:city":"Newnan",
    "sg:classifiers":[
        {
            "category":"Building & Trades",
            "subcategory":"Electrical",
            "type":"Services"
        }
    ],
    "sg:phone":"+1 770 253 0748",
    "sg:postcode":"30263",
    "sg:province":"GA",
    "sg:tags":[
        "installation",
        "telephone",
        "system"
    ],
    "wof:name":"Kight Cmmunications Contg Svcs",
    "wof:placetype":"venue"
},
  "geometry": {"coordinates":[-84.799209,33.37002],"type":"Point"}
}