{
  "type": "Feature",
  "properties": {
    "iso:country":"US",
    "sg:address":"1175 Lewis Ridge Cir",
    "sg:city":"Lawrenceville",
    "sg:classifiers":[
        {
            "category":"Personal",
            "subcategory":"Beauty Salon",
            "type":"Services"
        }
    ],
    "sg:phone":"+1 770 330 5408",
    "sg:postcode":"30045",
    "sg:province":"GA",
    "wof:name":"B S Wheels",
    "wof:placetype":"venue"
},
  "geometry": {"coordinates":[-83.951475,33.936092],"type":"Point"}
}