{
  "type": "Feature",
  "properties": {
    "addr:full":"2850 US Hwy 1 Louisville GA 30434",
    "addr:housenumber":"2850",
    "addr:postcode":"30434",
    "addr:street":"Us Hwy 1",
    "iso:country":"US",
    "sg:address":"2850 US Hwy 1",
    "sg:city":"Louisville",
    "sg:classifiers":[
        {
            "category":"Home & Garden",
            "subcategory":"Garden Supply",
            "type":"Retail Goods"
        }
    ],
    "sg:phone":"+1 478 625 8268",
    "sg:postcode":"30434",
    "sg:province":"GA",
    "sg:tags":[
        "lawn",
        "mower"
    ],
    "wof:name":"Leon Ensz Small Engine Repair",
    "wof:placetype":"venue"
},
  "geometry": {"coordinates":[-82.404528,33.026511],"type":"Point"}
}