{
  "type": "Feature",
  "properties": {
    "addr:full":"950 State Rte 30 Port Wentworth GA 31407",
    "addr:housenumber":"950",
    "addr:postcode":"31407",
    "addr:street":"State Rte 30 Port",
    "iso:country":"US",
    "sg:address":"950 State Rte 30",
    "sg:city":"Port Wentworth",
    "sg:classifiers":[
        {
            "category":"Building & Trades",
            "subcategory":"Construction",
            "type":"Services"
        }
    ],
    "sg:phone":"+1 912 965 1357",
    "sg:postcode":"31407",
    "sg:province":"GA",
    "sg:tags":[
        "plastering",
        "contractor"
    ],
    "wof:name":"MCJ Superior Plastaring Inc",
    "wof:placetype":"venue"
},
  "geometry": {"coordinates":[-81.229958,32.190978],"type":"Point"}
}