{
  "type": "Feature",
  "properties": {
    "addr:full":"3209 Maple Dr NE Atlanta GA 30305",
    "addr:housenumber":"3209",
    "addr:postcode":"30305",
    "addr:street":"Maple Dr Ne",
    "iso:country":"US",
    "sg:address":"3209 Maple Dr NE",
    "sg:city":"Atlanta",
    "sg:classifiers":[
        {
            "category":"Building & Trades",
            "subcategory":"Locksmith",
            "type":"Services"
        }
    ],
    "sg:phone":"+1 678 845 9058",
    "sg:postcode":"30305",
    "sg:province":"GA",
    "sg:tags":[
        "key"
    ],
    "wof:name":"A Always Available Emergency A Locksmith",
    "wof:placetype":"venue"
},
  "geometry": {"coordinates":[-84.372141,33.841268],"type":"Point"}
}