{
  "type": "Feature",
  "properties": {
    "iso:country":"US",
    "sg:address":"5105 Peachtree Industrial Blvd",
    "sg:city":"Chamblee",
    "sg:classifiers":[
        {
            "category":"Health Services",
            "subcategory":"Doctor",
            "type":"Services"
        }
    ],
    "sg:phone":"+1 770 457 2858",
    "sg:postcode":"30341",
    "sg:province":"GA",
    "sg:tags":[
        "dentist"
    ],
    "wof:name":"Richard V Remigailo Jr DDS",
    "wof:placetype":"venue"
},
  "geometry": {"coordinates":[-84.31291400000001,33.888796],"type":"Point"}
}