{
  "type": "Feature",
  "properties": {
    "addr:full":"2499 Marshallville Rd Perry GA 31069",
    "addr:housenumber":"2499",
    "addr:postcode":"31069",
    "addr:street":"Marshallville Rd",
    "iso:country":"US",
    "sg:address":"2499 Marshallville Rd",
    "sg:city":"Perry",
    "sg:classifiers":[
        {
            "category":"Professional",
            "type":"Services"
        }
    ],
    "sg:phone":"+1 478 218 5823",
    "sg:postcode":"31069",
    "sg:province":"GA",
    "wof:name":"Annette M Edwards",
    "wof:placetype":"venue"
},
  "geometry": {"coordinates":[-83.801408,32.440982],"type":"Point"}
}