{
  "type": "Feature",
  "properties": {
    "addr:full":"2801 Deans Bridge Rd Augusta GA 30906",
    "addr:housenumber":"2801",
    "addr:postcode":"30906",
    "addr:street":"Deans Bridge Rd",
    "iso:country":"US",
    "sg:address":"2801 Deans Bridge Rd",
    "sg:city":"Augusta",
    "sg:classifiers":[
        {
            "category":"Shopping",
            "subcategory":"Used Merchandise",
            "type":"Retail Goods"
        },
        {
            "category":"Autos & Motor Vehicles",
            "subcategory":"Automobile Sales",
            "type":"Retail Goods"
        }
    ],
    "sg:phone":"+1 706 771 0641",
    "sg:postcode":"30906",
    "sg:province":"GA",
    "sg:tags":[
        "car",
        "dealer"
    ],
    "wof:name":"Arrington Auto Sales & Rental",
    "wof:placetype":"venue"
},
  "geometry": {"coordinates":[-82.03549700000001,33.433602],"type":"Point"}
}