{
  "type": "Feature",
  "properties": {
    "iso:country":"US",
    "sg:address":"1064 Holly Springs Rd",
    "sg:city":"Rockmart",
    "sg:classifiers":[
        {
            "category":"Building & Trades",
            "subcategory":"Landscaping Services",
            "type":"Services"
        }
    ],
    "sg:phone":"+1 770 505 8606",
    "sg:postcode":"30153",
    "sg:province":"GA",
    "sg:tags":[
        "lawn",
        "maintenance",
        "grounds"
    ],
    "wof:name":"Lawn Doctor-Rockmart Dallas",
    "wof:placetype":"venue"
},
  "geometry": {"coordinates":[-85.02377300000001,33.877327],"type":"Point"}
}