{
  "type": "Feature",
  "properties": {
    "addr:full":"857 Collier Rd NW Atlanta GA 30318",
    "addr:housenumber":"857",
    "addr:postcode":"30318",
    "addr:street":"Collier Rd Nw",
    "iso:country":"US",
    "sg:address":"857 Collier Rd NW",
    "sg:city":"Atlanta",
    "sg:classifiers":[
        {
            "category":"Insurance",
            "subcategory":"Hazard Insurance",
            "type":"Services"
        }
    ],
    "sg:phone":"+1 404 350 9939",
    "sg:postcode":"30318",
    "sg:province":"GA",
    "wof:name":"State Farm Insurance Companies",
    "wof:placetype":"venue"
},
  "geometry": {"coordinates":[-84.41430699999999,33.80946],"type":"Point"}
}