{
  "type": "Feature",
  "properties": {
    "iso:country":"US",
    "sg:address":"4806 Old Louisville Rd",
    "sg:city":"Savannah",
    "sg:classifiers":[
        {
            "category":"Recreation",
            "type":"Entertainment"
        }
    ],
    "sg:phone":"+1 912 964 1101",
    "sg:postcode":"31408",
    "sg:province":"GA",
    "sg:tags":[
        "fishing",
        "lake"
    ],
    "wof:name":"Faith Christian Retreat Thorpe",
    "wof:placetype":"venue"
},
  "geometry": {"coordinates":[-81.190692,32.096469],"type":"Point"}
}