{
  "type": "Feature",
  "properties": {
    "addr:full":"9334 Terri Ln Jonesboro GA 30236",
    "addr:housenumber":"9334",
    "addr:postcode":"30236",
    "addr:street":"Terri Ln",
    "iso:country":"US",
    "sg:address":"9334 Terri Ln",
    "sg:city":"Jonesboro",
    "sg:classifiers":[
        {
            "category":"Professional",
            "subcategory":"Business Services",
            "type":"Services"
        }
    ],
    "sg:phone":"+1 678 479 8680",
    "sg:postcode":"30236",
    "sg:province":"GA",
    "wof:name":"Tfg Enterprises Inc",
    "wof:placetype":"venue"
},
  "geometry": {"coordinates":[-84.287672,33.501274],"type":"Point"}
}