{
  "type": "Feature",
  "properties": {
    "addr:full":"31 Mill St NE Ste 300 Marietta GA 30060",
    "addr:housenumber":"31",
    "addr:postcode":"30060",
    "addr:street":"Mill St Ne Ste 300",
    "iso:country":"US",
    "sg:address":"31 Mill St NE Ste 300",
    "sg:city":"Marietta",
    "sg:classifiers":[
        {
            "category":"Retail",
            "subcategory":"Pet Boarding",
            "type":"Services"
        }
    ],
    "sg:phone":"+1 770 428 8616",
    "sg:postcode":"30060",
    "sg:province":"GA",
    "sg:tags":[
        "boarding/pet",
        "sitting"
    ],
    "wof:name":"Kreature Komfort of Mreta",
    "wof:placetype":"venue"
},
  "geometry": {"coordinates":[-84.550797,33.9533],"type":"Point"}
}