{
  "type": "Feature",
  "properties": {
    "iso:country":"US",
    "sg:address":"1105 Cabin Creek Dr",
    "sg:city":"Nicholson",
    "sg:classifiers":[
        {
            "category":"Restaurant",
            "type":"Food & Drink"
        }
    ],
    "sg:phone":"+1 706 335 9235",
    "sg:postcode":"30565",
    "sg:province":"GA",
    "sg:tags":[
        "eating"
    ],
    "wof:name":"Marks Place",
    "wof:placetype":"venue"
},
  "geometry": {"coordinates":[-83.44886099999999,34.123764],"type":"Point"}
}