{
  "type": "Feature",
  "properties": {
    "addr:full":"203 Old Summerville Rd NW Rome GA 30165",
    "addr:housenumber":"203",
    "addr:postcode":"ga 30165",
    "addr:street":"Old Summerville Rd Nw",
    "iso:country":"US",
    "sg:address":"203 Old Summerville Rd NW",
    "sg:city":"Rome",
    "sg:classifiers":[
        {
            "category":"Professional",
            "subcategory":"Management & Consulting",
            "type":"Services"
        }
    ],
    "sg:phone":"+1 706 232 6640",
    "sg:postcode":"30165",
    "sg:province":"GA",
    "sg:tags":[
        "business"
    ],
    "wof:name":"Mulch & More",
    "wof:placetype":"venue"
},
  "geometry": {"coordinates":[-85.175218,34.305383],"type":"Point"}
}