{
  "type": "Feature",
  "properties": {
    "iso:country":"US",
    "sg:address":"5040 Snapfinger Woods Dr",
    "sg:city":"Decatur",
    "sg:classifiers":[
        {
            "category":"Health Services",
            "subcategory":"Doctor",
            "type":"Services"
        }
    ],
    "sg:phone":"+1 770 322 7333",
    "sg:postcode":"30035",
    "sg:province":"GA",
    "sg:tags":[
        "medicine",
        "sport",
        "orthopedist"
    ],
    "wof:name":"Craven William M MD",
    "wof:placetype":"venue"
},
  "geometry": {"coordinates":[-84.180702,33.711102],"type":"Point"}
}