{
  "type": "Feature",
  "properties": {
    "addr:full":"5883 Camelia Dr Douglasville GA 30135",
    "addr:housenumber":"5883",
    "addr:postcode":"30135",
    "addr:street":"Camelia Dr",
    "iso:country":"US",
    "sg:address":"5883 Camelia Dr",
    "sg:city":"Douglasville",
    "sg:classifiers":[
        {
            "category":"Social Services",
            "type":"Services"
        }
    ],
    "sg:phone":"+1 770 920 9114",
    "sg:postcode":"30135",
    "sg:province":"GA",
    "sg:tags":[
        "counseling"
    ],
    "wof:name":"Children Of Divorce Edu Prgrm",
    "wof:placetype":"venue"
},
  "geometry": {"coordinates":[-84.824799,33.642982],"type":"Point"}
}