{
  "type": "Feature",
  "properties": {
    "iso:country":"US",
    "sg:address":"115 Tilly Farm Rd",
    "sg:city":"Ellijay",
    "sg:classifiers":[
        {
            "category":"Building & Trades",
            "subcategory":"Construction",
            "type":"Services"
        }
    ],
    "sg:phone":"+1 706 635 6713",
    "sg:postcode":"30540",
    "sg:province":"GA",
    "sg:tags":[
        "handyman"
    ],
    "wof:name":"Small Engie Repair",
    "wof:placetype":"venue"
},
  "geometry": {"coordinates":[-84.546283,34.617152],"type":"Point"}
}