{
  "type": "Feature",
  "properties": {
    "addr:full":"5605 State Rte 16 E Senoia GA 30276",
    "addr:housenumber":"5605",
    "addr:postcode":"30276",
    "addr:street":"State Rte 16 E",
    "iso:country":"US",
    "sg:address":"5605 State Rte 16 E",
    "sg:city":"Senoia",
    "sg:classifiers":[
        {
            "category":"Building & Trades",
            "subcategory":"Construction",
            "type":"Services"
        }
    ],
    "sg:phone":"+1 770 599 3447",
    "sg:postcode":"30276",
    "sg:province":"GA",
    "sg:tags":[
        "excavation",
        "contractor"
    ],
    "wof:name":"A & A Excavating",
    "wof:placetype":"venue"
},
  "geometry": {"coordinates":[-84.61593000000001,33.316402],"type":"Point"}
}