{
  "type": "Feature",
  "properties": {
    "addr:full":"80 Whitehouse Dr SW Atlanta GA 30314",
    "addr:housenumber":"80",
    "addr:postcode":"30314",
    "addr:street":"Whitehouse Dr Sw",
    "iso:country":"US",
    "sg:address":"80 Whitehouse Dr SW",
    "sg:city":"Atlanta",
    "sg:classifiers":[
        {
            "category":"Home & Garden",
            "subcategory":"Building Materials",
            "type":"Retail Goods"
        }
    ],
    "sg:phone":"+1 404 756 1699",
    "sg:postcode":"30314",
    "sg:province":"GA",
    "wof:name":"ITC Building Materials",
    "wof:placetype":"venue"
},
  "geometry": {"coordinates":[-84.41979600000001,33.753503],"type":"Point"}
}