{
  "type": "Feature",
  "properties": {
    "addr:full":"2009 Montreal Rd Tucker GA 30084",
    "addr:housenumber":"2009",
    "addr:postcode":"30084",
    "addr:street":"Montreal Rd",
    "iso:country":"US",
    "sg:address":"2009 Montreal Rd",
    "sg:city":"Tucker",
    "sg:classifiers":[
        {
            "category":"Insurance",
            "subcategory":"Insurance Agent",
            "type":"Services"
        }
    ],
    "sg:phone":"+1 770 723 8096",
    "sg:postcode":"30084",
    "sg:province":"GA",
    "wof:name":"Shared Agency Services LLC",
    "wof:placetype":"venue"
},
  "geometry": {"coordinates":[-84.256652,33.844457],"type":"Point"}
}