{
  "type": "Feature",
  "properties": {
    "iso:country":"US",
    "sg:address":"2690 Shaw Rd",
    "sg:city":"Marietta",
    "sg:classifiers":[
        {
            "category":"Shopping",
            "type":"Retail Goods"
        }
    ],
    "sg:phone":"+1 770 977 0142",
    "sg:postcode":"30066",
    "sg:province":"GA",
    "sg:tags":[
        "merchandise"
    ],
    "wof:name":"Robert W Reardon",
    "wof:placetype":"venue"
},
  "geometry": {"coordinates":[-84.510542,34.017514],"type":"Point"}
}