{
  "type": "Feature",
  "properties": {
    "addr:full":"424 Forest Pkwy Forest Park GA 30297",
    "addr:housenumber":"424",
    "addr:postcode":"30297",
    "addr:street":"Forest Pkwy",
    "iso:country":"US",
    "sg:address":"424 Forest Pkwy",
    "sg:city":"Forest Park",
    "sg:classifiers":[
        {
            "category":"Restaurant",
            "type":"Food & Drink"
        }
    ],
    "sg:phone":"+1 404 366 4477",
    "sg:postcode":"30297",
    "sg:province":"GA",
    "wof:name":"Anne & Bill's Restaurant",
    "wof:placetype":"venue"
},
  "geometry": {"coordinates":[-84.394644,33.618179],"type":"Point"}
}