{
  "type": "Feature",
  "properties": {
    "iso:country":"US",
    "sg:address":"150 North St",
    "sg:city":"Canton",
    "sg:classifiers":[
        {
            "category":"Professional",
            "subcategory":"Lawyer & Legal Services",
            "type":"Services"
        }
    ],
    "sg:phone":"+1 678 493 2003",
    "sg:postcode":"30114",
    "sg:province":"GA",
    "wof:name":"Burns J Daran PC",
    "wof:placetype":"venue"
},
  "geometry": {"coordinates":[-84.490493,34.237183],"type":"Point"}
}