{
  "type": "Feature",
  "properties": {
    "addr:full":"2002 Elberta Rd Warner Robins GA 31093",
    "addr:housenumber":"2002",
    "addr:postcode":"31093",
    "addr:street":"Elberta Rd",
    "iso:country":"US",
    "sg:address":"2002 Elberta Rd",
    "sg:city":"Warner Robins",
    "sg:classifiers":[
        {
            "category":"Professional",
            "subcategory":"Engineering",
            "type":"Services"
        },
        {
            "category":"Manufacturing",
            "subcategory":"Tools & Machinery",
            "type":"Manufacturing & Wholesale Goods"
        }
    ],
    "sg:phone":"+1 478 922 8868",
    "sg:postcode":"31093",
    "sg:province":"GA",
    "sg:tags":[
        "control",
        "consulting",
        "electrical",
        "engineer"
    ],
    "wof:name":"New Technology Services Inc",
    "wof:placetype":"venue"
},
  "geometry": {"coordinates":[-83.655711,32.634626],"type":"Point"}
}