{
  "type": "Feature",
  "properties": {
    "iso:country":"US",
    "sg:address":"1400 Church St Exd",
    "sg:city":"Marietta",
    "sg:classifiers":[
        {
            "category":"Retail",
            "subcategory":"Auto Repair",
            "type":"Services"
        }
    ],
    "sg:phone":"+1 770 919 2800",
    "sg:postcode":"30060",
    "sg:province":"GA",
    "sg:tags":[
        "wrecker"
    ],
    "wof:name":"Wright Choice Wrecker Svc",
    "wof:placetype":"venue"
},
  "geometry": {"coordinates":[-84.55291099999999,33.974911],"type":"Point"}
}