{
  "type": "Feature",
  "properties": {
    "addr:full":"5273 Cleveland Hwy Clermont GA 30527",
    "addr:housenumber":"5273",
    "addr:postcode":"30527",
    "addr:street":"Cleveland Hwy",
    "iso:country":"US",
    "sg:address":"5273 Cleveland Hwy",
    "sg:city":"Clermont",
    "sg:classifiers":[
        {
            "category":"Social Services",
            "subcategory":"Child Care",
            "type":"Services"
        }
    ],
    "sg:phone":"+1 770 983 3900",
    "sg:postcode":"30527",
    "sg:province":"GA",
    "sg:tags":[
        "day"
    ],
    "wof:name":"Developing Children Inc",
    "wof:placetype":"venue"
},
  "geometry": {"coordinates":[-83.80489799999999,34.447367],"type":"Point"}
}