{
  "type": "Feature",
  "properties": {
    "addr:full":"107 Billy Blvd Butler GA 31006",
    "addr:housenumber":"107",
    "addr:postcode":"31006",
    "addr:street":"Billy Blvd",
    "iso:country":"US",
    "sg:address":"107 Billy Blvd",
    "sg:city":"Butler",
    "sg:classifiers":[
        {
            "category":"Utilities",
            "subcategory":"Water",
            "type":"Services"
        }
    ],
    "sg:phone":"+1 478 862 3621",
    "sg:postcode":"31006",
    "sg:province":"GA",
    "sg:tags":[
        "pump",
        "well",
        "drilling",
        "contractor"
    ],
    "wof:name":"Bonanza Drilling & Well Company",
    "wof:placetype":"venue"
},
  "geometry": {"coordinates":[-84.25805099999999,32.563805],"type":"Point"}
}