{
  "type": "Feature",
  "properties": {
    "addr:full":"1812 Winston Dr Macon GA 31206",
    "addr:housenumber":"1812",
    "addr:postcode":"31206",
    "addr:street":"Winston Dr",
    "iso:country":"US",
    "sg:address":"1812 Winston Dr",
    "sg:city":"Macon",
    "sg:classifiers":[
        {
            "category":"Professional",
            "type":"Services"
        }
    ],
    "sg:phone":"+1 478 788 7799",
    "sg:postcode":"31206",
    "sg:province":"GA",
    "wof:name":"Debra Kyles",
    "wof:placetype":"venue"
},
  "geometry": {"coordinates":[-83.676061,32.811351],"type":"Point"}
}