{
  "type": "Feature",
  "properties": {
    "iso:country":"US",
    "sg:address":"4 Suncrest Blvd",
    "sg:city":"Savannah",
    "sg:classifiers":[
        {
            "category":"Shopping",
            "subcategory":"Clothing, Apparel, & Fashions",
            "type":"Retail Goods"
        }
    ],
    "sg:phone":"+1 912 897 3560",
    "sg:postcode":"31410",
    "sg:province":"GA",
    "sg:tags":[
        "wear"
    ],
    "wof:name":"Magic Lollipop",
    "wof:placetype":"venue"
},
  "geometry": {"coordinates":[-80.973225,32.030935],"type":"Point"}
}