{
  "type": "Feature",
  "properties": {
    "iso:country":"US",
    "sg:address":"538 S Holly Springs Rd",
    "sg:city":"Woodstock",
    "sg:classifiers":[
        {
            "category":"Building & Trades",
            "subcategory":"Cleaning & Sanitation",
            "type":"Services"
        }
    ],
    "sg:phone":"+1 770 591 9039",
    "sg:postcode":"30188",
    "sg:province":"GA",
    "sg:tags":[
        "maintenance"
    ],
    "wof:name":"Kathys Cleaning Service",
    "wof:placetype":"venue"
},
  "geometry": {"coordinates":[-84.477039,34.139371],"type":"Point"}
}