{
  "type": "Feature",
  "properties": {
    "addr:full":"114 Main St La Grange GA 30240",
    "addr:housenumber":"114",
    "addr:postcode":"30240",
    "addr:street":"Main St",
    "iso:country":"US",
    "sg:address":"114 Main St",
    "sg:city":"La Grange",
    "sg:classifiers":[
        {
            "category":"Organizations",
            "subcategory":"Non-profit Organization",
            "type":"Services"
        }
    ],
    "sg:phone":"+1 706 845 0708",
    "sg:postcode":"30240",
    "sg:province":"GA",
    "sg:tags":[
        "social"
    ],
    "wof:name":"March Dmes Brth Dfcts Fndation",
    "wof:placetype":"venue"
},
  "geometry": {"coordinates":[-85.031031,33.039382],"type":"Point"}
}