{
  "type": "Feature",
  "properties": {
    "addr:full":"4205 N Point Pkwy Ste F Alpharetta GA 30022",
    "addr:housenumber":"4205",
    "addr:postcode":"30022",
    "addr:street":"N Point Pkwy Ste F",
    "iso:country":"US",
    "sg:address":"4205 N Point Pkwy Ste F",
    "sg:city":"Alpharetta",
    "sg:classifiers":[
        {
            "category":"Health Services",
            "subcategory":"Clinic",
            "type":"Services"
        }
    ],
    "sg:phone":"+1 770 664 5353",
    "sg:postcode":"30022",
    "sg:province":"GA",
    "sg:tags":[
        "counseling",
        "mental"
    ],
    "wof:name":"Thomas Daniel A Jr Dr",
    "wof:placetype":"venue"
},
  "geometry": {"coordinates":[-84.264,34.063999],"type":"Point"}
}