{
  "type": "Feature",
  "properties": {
    "iso:country":"US",
    "sg:address":"107 Gordon St",
    "sg:city":"Chickamauga",
    "sg:classifiers":[
        {
            "category":"Health Services",
            "subcategory":"Doctor",
            "type":"Services"
        }
    ],
    "sg:phone":"+1 706 375 3621",
    "sg:postcode":"30707",
    "sg:province":"GA",
    "sg:tags":[
        "dentist"
    ],
    "wof:name":"Douglas M Graydon DDS",
    "wof:placetype":"venue"
},
  "geometry": {"coordinates":[-85.29062500000001,34.871762],"type":"Point"}
}