{
  "type": "Feature",
  "properties": {
    "addr:full":"728 Northside Dr E Statesboro GA 30458",
    "addr:housenumber":"728",
    "addr:postcode":"30458",
    "addr:street":"Northside Dr E",
    "iso:country":"US",
    "sg:address":"728 Northside Dr E",
    "sg:city":"Statesboro",
    "sg:classifiers":[
        {
            "category":"Autos & Motor Vehicles",
            "subcategory":"Fuel & Gas Station",
            "type":"Retail Goods"
        }
    ],
    "sg:phone":"+1 912 489 2161",
    "sg:postcode":"30458",
    "sg:province":"GA",
    "sg:tags":[
        "oil"
    ],
    "wof:name":"Murphy Oil USA Inc",
    "wof:placetype":"venue"
},
  "geometry": {"coordinates":[-81.755869,32.434006],"type":"Point"}
}