{
  "type": "Feature",
  "properties": {
    "iso:country":"US",
    "sg:address":"5074 Valley Ct",
    "sg:city":"Oakwood",
    "sg:classifiers":[
        {
            "category":"Restaurant",
            "type":"Food & Drink"
        }
    ],
    "sg:phone":"+1 770 535 1757",
    "sg:postcode":"30566",
    "sg:province":"GA",
    "sg:tags":[
        "eating"
    ],
    "wof:name":"Paradise Pizza",
    "wof:placetype":"venue"
},
  "geometry": {"coordinates":[-83.9066,34.232561],"type":"Point"}
}