{
  "type": "Feature",
  "properties": {
    "iso:country":"US",
    "sg:address":"2697 Skyland Dr NE",
    "sg:city":"Atlanta",
    "sg:classifiers":[
        {
            "category":"Communications",
            "subcategory":"Film & Video Production",
            "type":"Services"
        }
    ],
    "sg:phone":"+1 404 728 9416",
    "sg:postcode":"30319",
    "sg:province":"GA",
    "sg:tags":[
        "motion",
        "picture"
    ],
    "wof:name":"Helen S Beck",
    "wof:placetype":"venue"
},
  "geometry": {"coordinates":[-84.31517599999999,33.866824],"type":"Point"}
}