{
  "type": "Feature",
  "properties": {
    "addr:full":"134 McGiboney Dr Covington GA 30016",
    "addr:housenumber":"134",
    "addr:postcode":"30016",
    "addr:street":"Mcgiboney Dr",
    "iso:country":"US",
    "sg:address":"134 McGiboney Dr",
    "sg:city":"Covington",
    "sg:classifiers":[
        {
            "category":"Professional",
            "type":"Services"
        }
    ],
    "sg:phone":"+1 770 786 0939",
    "sg:postcode":"30016",
    "sg:province":"GA",
    "wof:name":"Olin W Bennett",
    "wof:placetype":"venue"
},
  "geometry": {"coordinates":[-83.939038,33.581027],"type":"Point"}
}