{
  "type": "Feature",
  "properties": {
    "addr:full":"239 Stafford Rd Spr Chatsworth GA 30705",
    "addr:housenumber":"239",
    "addr:postcode":"30705",
    "addr:street":"Stafford Rd Spr",
    "iso:country":"US",
    "sg:address":"239 Stafford Rd Spr",
    "sg:city":"Chatsworth",
    "sg:classifiers":[
        {
            "category":"Building & Trades",
            "subcategory":"Construction",
            "type":"Services"
        }
    ],
    "sg:phone":"+1 706 695 6459",
    "sg:postcode":"30705",
    "sg:province":"GA",
    "sg:tags":[
        "house"
    ],
    "wof:name":"Hooper Construction",
    "wof:placetype":"venue"
},
  "geometry": {"coordinates":[-84.832247,34.790756],"type":"Point"}
}