{
  "type": "Feature",
  "properties": {
    "iso:country":"US",
    "sg:address":"1827 Powers Ferry Rd SE",
    "sg:city":"Atlanta",
    "sg:classifiers":[
        {
            "category":"Health Services",
            "subcategory":"Doctor",
            "type":"Services"
        }
    ],
    "sg:phone":"+1 770 984 8889",
    "sg:postcode":"30339",
    "sg:province":"GA",
    "sg:tags":[
        "medicine",
        "sport"
    ],
    "wof:name":"Sports Massage & Integrated Therapies",
    "wof:placetype":"venue"
},
  "geometry": {"coordinates":[-84.464996,33.912701],"type":"Point"}
}