{
  "type": "Feature",
  "properties": {
    "iso:country":"US",
    "sg:address":"2111 Highland Ave",
    "sg:city":"Augusta",
    "sg:classifiers":[
        {
            "category":"Manufacturing",
            "subcategory":"Paper Products",
            "type":"Manufacturing & Wholesale Goods"
        }
    ],
    "sg:phone":"+1 706 737 4581",
    "sg:postcode":"30904",
    "sg:province":"GA",
    "sg:tags":[
        "supply"
    ],
    "wof:name":"Sten-C Label",
    "wof:placetype":"venue"
},
  "geometry": {"coordinates":[-82.044831,33.455258],"type":"Point"}
}