{
  "type": "Feature",
  "properties": {
    "addr:full":"110 Walter Way Stockbridge GA 30214",
    "addr:housenumber":"110",
    "addr:postcode":"30214",
    "addr:street":"Walter Way",
    "iso:country":"US",
    "sg:address":"110 Walter Way",
    "sg:city":"Stockbridge",
    "sg:classifiers":[
        {
            "category":"Government",
            "subcategory":"Post Office",
            "type":"Public Place"
        }
    ],
    "sg:phone":"+1 770 507 5483",
    "sg:postcode":"30214",
    "sg:province":"GA",
    "sg:tags":[
        "s",
        "postal",
        "u"
    ],
    "wof:name":"US Post Office",
    "wof:placetype":"venue"
},
  "geometry": {"coordinates":[-84.43112499999999,33.498378],"type":"Point"}
}