{
  "type": "Feature",
  "properties": {
    "addr:full":"758 Lee St Jefferson GA 30549",
    "addr:housenumber":"758",
    "addr:postcode":"30549",
    "addr:street":"Lee St",
    "iso:country":"US",
    "sg:address":"758 Lee St",
    "sg:city":"Jefferson",
    "sg:classifiers":[
        {
            "category":"Professional",
            "subcategory":"Accounting & Tax Preparation",
            "type":"Services"
        }
    ],
    "sg:phone":"+1 706 367 7460",
    "sg:postcode":"30549",
    "sg:province":"GA",
    "sg:tags":[
        "payroll"
    ],
    "wof:name":"Chapman Payroll Solutions",
    "wof:placetype":"venue"
},
  "geometry": {"coordinates":[-83.58458400000001,34.113113],"type":"Point"}
}