{
  "type": "Feature",
  "properties": {
    "addr:full":"1438 Beaverdale Rd NE Dalton GA 30721",
    "addr:housenumber":"1438",
    "addr:postcode":"30721",
    "addr:street":"Beaverdale Rd Ne",
    "iso:country":"US",
    "sg:address":"1438 Beaverdale Rd NE",
    "sg:city":"Dalton",
    "sg:classifiers":[
        {
            "category":"Professional",
            "subcategory":"Engineering",
            "type":"Services"
        }
    ],
    "sg:phone":"+1 706 278 8944",
    "sg:postcode":"30721",
    "sg:province":"GA",
    "wof:name":"Samuel Headrick Cnstr Inc",
    "wof:placetype":"venue"
},
  "geometry": {"coordinates":[-84.88070500000001,34.875908],"type":"Point"}
}