{
  "type": "Feature",
  "properties": {
    "addr:full":"5871 Gateway Blvd Stone Mountain GA 30087",
    "addr:housenumber":"5871",
    "addr:postcode":"30087",
    "addr:street":"Gateway Blvd",
    "iso:country":"US",
    "sg:address":"5871 Gateway Blvd",
    "sg:city":"Stone Mountain",
    "sg:classifiers":[
        {
            "category":"Professional",
            "subcategory":"Computer Services",
            "type":"Services"
        }
    ],
    "sg:phone":"+1 770 498 4222",
    "sg:postcode":"30087",
    "sg:province":"GA",
    "sg:tags":[
        "information",
        "consulting",
        "technology"
    ],
    "wof:name":"Bethea and Associates Inc",
    "wof:placetype":"venue"
},
  "geometry": {"coordinates":[-84.15074199999999,33.776597],"type":"Point"}
}