{
  "type": "Feature",
  "properties": {
    "iso:country":"US",
    "sg:address":"792 Houston Mill Rd NE",
    "sg:city":"Atlanta",
    "sg:classifiers":[
        {
            "category":"Social Services",
            "type":"Services"
        }
    ],
    "sg:phone":"+1 404 315 1133",
    "sg:postcode":"30329",
    "sg:province":"GA",
    "sg:tags":[
        "organization",
        "welfare"
    ],
    "sg:website":"www.armh.com",
    "wof:name":"Ronald Mc Donald House",
    "wof:placetype":"venue"
},
  "geometry": {"coordinates":[-84.323724,33.798656],"type":"Point"}
}