{
  "type": "Feature",
  "properties": {
    "addr:full":"11180 State Bridge Rd Alpharetta GA 30097",
    "addr:housenumber":"11180",
    "addr:postcode":"30097",
    "addr:street":"State Bridge Rd",
    "iso:country":"US",
    "sg:address":"11180 State Bridge Rd",
    "sg:city":"Alpharetta",
    "sg:classifiers":[
        {
            "category":"Professional",
            "subcategory":"Management & Consulting",
            "type":"Services"
        }
    ],
    "sg:phone":"+1 770 667 9565",
    "sg:postcode":"30097",
    "sg:province":"GA",
    "sg:tags":[
        "insurance"
    ],
    "wof:name":"Primerica Finacial Services",
    "wof:placetype":"venue"
},
  "geometry": {"coordinates":[-84.180527,34.008381],"type":"Point"}
}