{
  "type": "Feature",
  "properties": {
    "iso:country":"US",
    "sg:address":"235 W Roosevelt Ave",
    "sg:city":"Albany",
    "sg:classifiers":[
        {
            "category":"Social Services",
            "type":"Services"
        }
    ],
    "sg:phone":"+1 229 889 1530",
    "sg:postcode":"31701",
    "sg:province":"GA",
    "sg:tags":[
        "info",
        "program",
        "referral"
    ],
    "wof:name":"MST-Community Solutions",
    "wof:placetype":"venue"
},
  "geometry": {"coordinates":[-84.152248,31.581611],"type":"Point"}
}