{
  "type": "Feature",
  "properties": {
    "addr:full":"6163 Clyattville-Nankin Rd Valdosta GA 31601",
    "addr:housenumber":"6163",
    "addr:postcode":"31601",
    "addr:street":"Clyattville-Nankin Rd",
    "iso:country":"US",
    "sg:address":"6163 Clyattville-Nankin Rd",
    "sg:city":"Valdosta",
    "sg:classifiers":[
        {
            "category":"Organizations",
            "subcategory":"Religious Organization",
            "type":"Services"
        }
    ],
    "sg:phone":"+1 229 559 7748",
    "sg:postcode":"31601",
    "sg:province":"GA",
    "wof:name":"Harvest Church of God",
    "wof:placetype":"venue"
},
  "geometry": {"coordinates":[-83.355896,30.691682],"type":"Point"}
}