{
  "type": "Feature",
  "properties": {
    "iso:country":"US",
    "sg:address":"988 Mountain Brook Rd",
    "sg:city":"Fortson",
    "sg:classifiers":[
        {
            "category":"Professional",
            "subcategory":"Business Services",
            "type":"Services"
        }
    ],
    "sg:phone":"+1 706 682 1616",
    "sg:postcode":"31808",
    "sg:province":"GA",
    "wof:name":"Diamond Exchange",
    "wof:placetype":"venue"
},
  "geometry": {"coordinates":[-84.98466999999999,32.606635],"type":"Point"}
}