{
  "type": "Feature",
  "properties": {
    "addr:full":"1870 Christophers Trce Macon GA 31220",
    "addr:housenumber":"1870",
    "addr:postcode":"31220",
    "addr:street":"Christophers Trce",
    "iso:country":"US",
    "sg:address":"1870 Christophers Trce",
    "sg:city":"Macon",
    "sg:classifiers":[
        {
            "category":"Autos & Motor Vehicles",
            "subcategory":"Auto Supplies",
            "type":"Retail Goods"
        }
    ],
    "sg:phone":"+1 478 477 5115",
    "sg:postcode":"31220",
    "sg:province":"GA",
    "wof:name":"Bobbys Buggies LLC",
    "wof:placetype":"venue"
},
  "geometry": {"coordinates":[-83.777334,32.833348],"type":"Point"}
}