{
  "type": "Feature",
  "properties": {
    "iso:country":"US",
    "sg:address":"153 E College St",
    "sg:city":"Colquitt",
    "sg:classifiers":[
        {
            "category":"Shopping",
            "subcategory":"Florist",
            "type":"Retail Goods"
        }
    ],
    "sg:phone":"+1 229 758 3560",
    "sg:postcode":"31709",
    "sg:province":"GA",
    "wof:name":"Posie Patch",
    "wof:placetype":"venue"
},
  "geometry": {"coordinates":[-84.228353,32.065572],"type":"Point"}
}