{
  "type": "Feature",
  "properties": {
    "iso:country":"US",
    "sg:address":"21 Court Sq",
    "sg:city":"Warrenton",
    "sg:classifiers":[
        {
            "category":"Professional",
            "subcategory":"Lawyer & Legal Services",
            "type":"Services"
        }
    ],
    "sg:phone":"+1 706 465 3238",
    "sg:postcode":"30828",
    "sg:province":"GA",
    "sg:tags":[
        "plan"
    ],
    "wof:name":"Harold A Hinesley",
    "wof:placetype":"venue"
},
  "geometry": {"coordinates":[-82.661889,33.406588],"type":"Point"}
}