{
  "type": "Feature",
  "properties": {
    "iso:country":"US",
    "sg:address":"570 Old Cabaniss Rd",
    "sg:city":"Forsyth",
    "sg:classifiers":[
        {
            "category":"Retail",
            "subcategory":"Repair Shop",
            "type":"Services"
        }
    ],
    "sg:phone":"+1 478 994 3333",
    "sg:postcode":"31029",
    "sg:province":"GA",
    "sg:tags":[
        "automotive"
    ],
    "wof:name":"Forsyth Lock and Key",
    "wof:placetype":"venue"
},
  "geometry": {"coordinates":[-83.875269,33.143088],"type":"Point"}
}