{
  "type": "Feature",
  "properties": {
    "addr:full":"214 Wedgefield Xing Savannah GA 31405",
    "addr:housenumber":"214",
    "addr:postcode":"31405",
    "addr:street":"Wedgefield Xing",
    "iso:country":"US",
    "sg:address":"214 Wedgefield Xing",
    "sg:city":"Savannah",
    "sg:classifiers":[
        {
            "category":"Real Estate",
            "subcategory":"Architect",
            "type":"Services"
        }
    ],
    "sg:phone":"+1 912 238 3633",
    "sg:postcode":"31405",
    "sg:province":"GA",
    "sg:tags":[
        "architectural"
    ],
    "wof:name":"Parazzel",
    "wof:placetype":"venue"
},
  "geometry": {"coordinates":[-81.213525,32.065525],"type":"Point"}
}