{
  "type": "Feature",
  "properties": {
    "addr:full":"4774 Kitty Hawk Dr NE Atlanta GA 30342",
    "addr:housenumber":"4774",
    "addr:postcode":"30342",
    "addr:street":"Kitty Hawk Dr Ne",
    "iso:country":"US",
    "sg:address":"4774 Kitty Hawk Dr NE",
    "sg:city":"Atlanta",
    "sg:classifiers":[
        {
            "category":"Insurance",
            "subcategory":"Hazard Insurance",
            "type":"Services"
        }
    ],
    "sg:phone":"+1 770 396 4499",
    "sg:postcode":"30342",
    "sg:province":"GA",
    "wof:name":"State Farm Insurance",
    "wof:placetype":"venue"
},
  "geometry": {"coordinates":[-84.384719,33.885014],"type":"Point"}
}