{
  "type": "Feature",
  "properties": {
    "addr:full":"200 Barber Rd Rockmart GA 30153",
    "addr:housenumber":"200",
    "addr:postcode":"30153",
    "addr:street":"Barber Rd",
    "iso:country":"US",
    "sg:address":"200 Barber Rd",
    "sg:city":"Rockmart",
    "sg:classifiers":[
        {
            "category":"Building & Trades",
            "subcategory":"Construction",
            "type":"Services"
        }
    ],
    "sg:phone":"+1 770 684 2931",
    "sg:postcode":"30153",
    "sg:province":"GA",
    "sg:tags":[
        "hanging",
        "contractor"
    ],
    "wof:name":"Quality Painting Inc",
    "wof:placetype":"venue"
},
  "geometry": {"coordinates":[-85.13861900000001,34.01114],"type":"Point"}
}