{
  "type": "Feature",
  "properties": {
    "iso:country":"US",
    "sg:address":"438 Canton Rd",
    "sg:city":"Cumming",
    "sg:classifiers":[
        {
            "category":"Shopping",
            "subcategory":"Pharmacy",
            "type":"Retail Goods"
        }
    ],
    "sg:phone":"+1 770 889 2141",
    "sg:postcode":"30040",
    "sg:province":"GA",
    "sg:tags":[
        "drug",
        "store"
    ],
    "wof:name":"Eckerd",
    "wof:placetype":"venue"
},
  "geometry": {"coordinates":[-84.145608,34.2139],"type":"Point"}
}