{
  "type": "Feature",
  "properties": {
    "addr:full":"2200 Northlake Pkwy Tucker GA 30084",
    "addr:housenumber":"2200",
    "addr:postcode":"30084",
    "addr:street":"Northlake Pkwy",
    "iso:country":"US",
    "sg:address":"2200 Northlake Pkwy",
    "sg:city":"Tucker",
    "sg:classifiers":[
        {
            "category":"Travel",
            "subcategory":"Hotels & Motels",
            "type":"Entertainment"
        }
    ],
    "sg:phone":"+1 770 939 1801",
    "sg:postcode":"30084",
    "sg:province":"GA",
    "wof:name":"Best Western",
    "wof:placetype":"venue"
},
  "geometry": {"coordinates":[-84.244614,33.849319],"type":"Point"}
}