{
  "type": "Feature",
  "properties": {
    "iso:country":"US",
    "sg:address":"423 Pine Ave",
    "sg:city":"Albany",
    "sg:classifiers":[
        {
            "category":"Professional",
            "subcategory":"Lawyer & Legal Services",
            "type":"Services"
        }
    ],
    "sg:phone":"+1 229 878 6222",
    "sg:postcode":"31701",
    "sg:province":"GA",
    "sg:tags":[
        "attorney"
    ],
    "wof:name":"Brown-Williams & Assoc",
    "wof:placetype":"venue"
},
  "geometry": {"coordinates":[-84.15836400000001,31.578573],"type":"Point"}
}