{
  "type": "Feature",
  "properties": {
    "addr:full":"1074 Eagles Landing Pkwy Stockbridge GA 30281",
    "addr:housenumber":"1074",
    "addr:postcode":"30281",
    "addr:street":"Eagles Landing Pkwy",
    "iso:country":"US",
    "sg:address":"1074 Eagles Landing Pkwy",
    "sg:city":"Stockbridge",
    "sg:classifiers":[
        {
            "category":"Wholesale",
            "subcategory":"Medical Equipment & Supplies",
            "type":"Manufacturing & Wholesale Goods"
        }
    ],
    "sg:phone":"+1 770 506 2788",
    "sg:postcode":"30281",
    "sg:province":"GA",
    "wof:name":"Med-Mart Diabetic Supply",
    "wof:placetype":"venue"
},
  "geometry": {"coordinates":[-84.217189,33.512711],"type":"Point"}
}