{
  "type": "Feature",
  "properties": {
    "iso:country":"US",
    "sg:address":"806 Parland Rd",
    "sg:city":"Brunswick",
    "sg:classifiers":[
        {
            "category":"Building & Trades",
            "subcategory":"Plumbing",
            "type":"Services"
        }
    ],
    "sg:phone":"+1 912 262 5982",
    "sg:postcode":"31523",
    "sg:province":"GA",
    "sg:tags":[
        "contractor"
    ],
    "wof:name":"Dependable Plumbing Service",
    "wof:placetype":"venue"
},
  "geometry": {"coordinates":[-81.555458,31.18814],"type":"Point"}
}