{
  "type": "Feature",
  "properties": {
    "iso:country":"US",
    "sg:address":"4817 Ga Hwy",
    "sg:city":"Tate",
    "sg:classifiers":[
        {
            "category":"Shopping",
            "subcategory":"Used Merchandise",
            "type":"Retail Goods"
        }
    ],
    "sg:phone":"+1 678 454 2021",
    "sg:postcode":"30176",
    "sg:province":"GA",
    "sg:tags":[
        "shop",
        "consignment"
    ],
    "wof:name":"Mommy's Place",
    "wof:placetype":"venue"
},
  "geometry": {"coordinates":[-85.296499,33.778739],"type":"Point"}
}