{
  "type": "Feature",
  "properties": {
    "iso:country":"US",
    "sg:address":"5698 Highway 20 SE Ste D",
    "sg:city":"Cartersville",
    "sg:classifiers":[
        {
            "category":"Fast Food",
            "type":"Food & Drink"
        },
        {
            "category":"Restaurant",
            "type":"Food & Drink"
        },
        {
            "category":"Food & Beverages",
            "subcategory":"Groceries & Convenience Stores",
            "type":"Retail Goods"
        }
    ],
    "sg:phone":"+1 678 721 0001",
    "sg:postcode":"30121",
    "sg:province":"GA",
    "sg:tags":[
        "shop",
        "american",
        "sandwich",
        "take"
    ],
    "sg:website":"http://www.subway.com",
    "wof:name":"Subway",
    "wof:placetype":"venue"
},
  "geometry": {"coordinates":[-84.751085,34.216956],"type":"Point"}
}