{
  "type": "Feature",
  "properties": {
    "iso:country":"US",
    "sg:address":"3676 Neals Mill Rd",
    "sg:city":"Dearing",
    "sg:classifiers":[
        {
            "category":"Organizations",
            "subcategory":"Religious Organization",
            "type":"Services"
        }
    ],
    "sg:phone":"+1 706 556 3176",
    "sg:postcode":"30808",
    "sg:province":"GA",
    "wof:name":"Dearing Church Of God",
    "wof:placetype":"venue"
},
  "geometry": {"coordinates":[-82.380614,33.402362],"type":"Point"}
}