{
  "type": "Feature",
  "properties": {
    "iso:country":"US",
    "sg:address":"4223 Covington Hwy",
    "sg:city":"Decatur",
    "sg:classifiers":[
        {
            "category":"Restaurant",
            "type":"Food & Drink"
        }
    ],
    "sg:phone":"+1 404 286 9595",
    "sg:postcode":"30035",
    "sg:province":"GA",
    "sg:website":"www.subway.com",
    "wof:name":"Subway",
    "wof:placetype":"venue"
},
  "geometry": {"coordinates":[-84.229797,33.751598],"type":"Point"}
}