{
  "type": "Feature",
  "properties": {
    "addr:full":"3391 Windsong Ct Roswell GA 30075",
    "addr:housenumber":"3391",
    "addr:postcode":"30075",
    "addr:street":"Windsong Ct",
    "iso:country":"US",
    "sg:address":"3391 Windsong Ct",
    "sg:city":"Roswell",
    "sg:classifiers":[
        {
            "category":"Banks & Credit Unions",
            "subcategory":"Investment Brokerage",
            "type":"Services"
        }
    ],
    "sg:phone":"+1 770 587 1394",
    "sg:postcode":"30075",
    "sg:province":"GA",
    "sg:tags":[
        "advisory",
        "financial"
    ],
    "wof:name":"Outsource Financial Svc",
    "wof:placetype":"venue"
},
  "geometry": {"coordinates":[-84.420086,34.032072],"type":"Point"}
}