{
  "type": "Feature",
  "properties": {
    "iso:country":"US",
    "sg:address":"503 W 54th St",
    "sg:city":"Savannah",
    "sg:classifiers":[
        {
            "category":"Retail",
            "subcategory":"Auto Repair",
            "type":"Services"
        }
    ],
    "sg:phone":"+1 912 233 2211",
    "sg:postcode":"31405",
    "sg:province":"GA",
    "sg:tags":[
        "wrecker"
    ],
    "wof:name":"Well Towing Recovery",
    "wof:placetype":"venue"
},
  "geometry": {"coordinates":[-81.112354,32.046232],"type":"Point"}
}