{
  "type": "Feature",
  "properties": {
    "iso:country":"US",
    "sg:address":"16 Atlanta St",
    "sg:city":"Mcdonough",
    "sg:classifiers":[
        {
            "category":"Organizations",
            "subcategory":"Religious Organization",
            "type":"Services"
        }
    ],
    "sg:phone":"+1 678 432 5273",
    "sg:postcode":"30253",
    "sg:province":"GA",
    "sg:tags":[
        "church"
    ],
    "wof:name":"Total Grace Christian Ctr Sth",
    "wof:placetype":"venue"
},
  "geometry": {"coordinates":[-84.147299,33.448153],"type":"Point"}
}