{
  "type": "Feature",
  "properties": {
    "iso:country":"US",
    "sg:address":"1734 Rainbow Cir NE",
    "sg:city":"Dalton",
    "sg:classifiers":[
        {
            "category":"Building & Trades",
            "subcategory":"Construction",
            "type":"Services"
        }
    ],
    "sg:phone":"+1 706 226 2254",
    "sg:postcode":"30721",
    "sg:province":"GA",
    "sg:tags":[
        "wallcoverings-installation",
        "wallpaper",
        "painting",
        "contractor"
    ],
    "wof:name":"Roger Painter",
    "wof:placetype":"venue"
},
  "geometry": {"coordinates":[-84.870178,34.834672],"type":"Point"}
}