{
  "type": "Feature",
  "properties": {
    "addr:full":"10141 Commerce Rd Athens GA 30607",
    "addr:housenumber":"10141",
    "addr:postcode":"30607",
    "addr:street":"Commerce Rd",
    "iso:country":"US",
    "sg:address":"10141 Commerce Rd",
    "sg:city":"Athens",
    "sg:classifiers":[
        {
            "category":"Food & Beverages",
            "subcategory":"Groceries & Convenience Stores",
            "type":"Retail Goods"
        }
    ],
    "sg:phone":"+1 706 369 7010",
    "sg:postcode":"30607",
    "sg:province":"GA",
    "wof:name":"D's Food Store",
    "wof:placetype":"venue"
},
  "geometry": {"coordinates":[-83.402221,34.038293],"type":"Point"}
}