{
  "type": "Feature",
  "properties": {
    "addr:full":"2866 Johnson Ferry Rd Marietta GA 30062",
    "addr:housenumber":"2866",
    "addr:postcode":"30062",
    "addr:street":"Johnson Ferry Rd",
    "iso:country":"US",
    "sg:address":"2866 Johnson Ferry Rd",
    "sg:city":"Marietta",
    "sg:classifiers":[
        {
            "category":"Professional",
            "subcategory":"Management & Consulting",
            "type":"Services"
        }
    ],
    "sg:phone":"+1 770 518 4406",
    "sg:postcode":"30062",
    "sg:province":"GA",
    "wof:name":"Impact Medical Consulting",
    "wof:placetype":"venue"
},
  "geometry": {"coordinates":[-84.428551,34.018501],"type":"Point"}
}