{
  "type": "Feature",
  "properties": {
    "iso:country":"US",
    "sg:address":"321 Chandler Rdg",
    "sg:city":"Mcdonough",
    "sg:classifiers":[
        {
            "category":"Professional",
            "type":"Services"
        }
    ],
    "sg:phone":"+1 770 318 4575",
    "sg:postcode":"30253",
    "sg:province":"GA",
    "sg:tags":[
        "transportation"
    ],
    "wof:name":"C & V Transport",
    "wof:placetype":"venue"
},
  "geometry": {"coordinates":[-84.16892199999999,33.466011],"type":"Point"}
}