{
  "type": "Feature",
  "properties": {
    "iso:country":"US",
    "sg:address":"3203 University Ave",
    "sg:city":"Columbus",
    "sg:classifiers":[
        {
            "category":"Personal",
            "subcategory":"Beauty Salon",
            "type":"Services"
        }
    ],
    "sg:phone":"+1 706 653 1583",
    "sg:postcode":"31907",
    "sg:province":"GA",
    "sg:tags":[
        "shop"
    ],
    "wof:name":"Shontee Virtuous Touch",
    "wof:placetype":"venue"
},
  "geometry": {"coordinates":[-84.932306,32.49543],"type":"Point"}
}