{
  "type": "Feature",
  "properties": {
    "iso:country":"US",
    "sg:address":"330 S Wall St",
    "sg:city":"Calhoun",
    "sg:classifiers":[
        {
            "category":"Real Estate",
            "subcategory":"Developer",
            "type":"Services"
        },
        {
            "category":"Real Estate",
            "subcategory":"Real Estate Agent",
            "type":"Services"
        }
    ],
    "sg:phone":"+1 706 629 2877",
    "sg:postcode":"30701",
    "sg:province":"GA",
    "sg:tags":[
        "business"
    ],
    "wof:name":"Erwin Realty",
    "wof:placetype":"venue"
},
  "geometry": {"coordinates":[-84.951883,34.498909],"type":"Point"}
}