{
  "type": "Feature",
  "properties": {
    "iso:country":"US",
    "sg:address":"427 Moreland Avenue NE Suite 400",
    "sg:city":"Atlanta",
    "sg:classifiers":[
        {
            "category":"Health Services",
            "subcategory":"Doctor",
            "type":"Services"
        }
    ],
    "sg:phone":"+1 404 521 2445",
    "sg:postcode":"30307",
    "sg:province":"GA",
    "wof:name":"Polizos Victor G MD",
    "wof:placetype":"venue"
},
  "geometry": {"coordinates":[-84.349034,33.765976],"type":"Point"}
}