{
  "type": "Feature",
  "properties": {
    "iso:country":"US",
    "sg:address":"130 Conway Dr",
    "sg:city":"Bogart",
    "sg:classifiers":[
        {
            "category":"Shopping",
            "type":"Retail Goods"
        }
    ],
    "sg:phone":"+1 770 353 0229",
    "sg:postcode":"30622",
    "sg:province":"GA",
    "sg:tags":[
        "merchandise"
    ],
    "wof:name":"IKON Office Solutions",
    "wof:placetype":"venue"
},
  "geometry": {"coordinates":[-83.48094500000001,33.942034],"type":"Point"}
}