{
  "type": "Feature",
  "properties": {
    "iso:country":"US",
    "sg:address":"216 Devonwood Dr NE",
    "sg:city":"Atlanta",
    "sg:classifiers":[
        {
            "category":"Professional",
            "type":"Services"
        }
    ],
    "sg:phone":"+1 770 394 8798",
    "sg:postcode":"30328",
    "sg:province":"GA",
    "wof:name":"Tams Services",
    "wof:placetype":"venue"
},
  "geometry": {"coordinates":[-84.382014,33.948163],"type":"Point"}
}