{
  "type": "Feature",
  "properties": {
    "addr:full":"3991 Snapfinger Rd Lithonia GA 30038",
    "addr:housenumber":"3991",
    "addr:postcode":"30038",
    "addr:street":"Snapfinger Rd",
    "iso:country":"US",
    "sg:address":"3991 Snapfinger Rd",
    "sg:city":"Lithonia",
    "sg:classifiers":[
        {
            "category":"Education",
            "subcategory":"School",
            "type":"Public Place"
        }
    ],
    "sg:phone":"+1 678 874 5402",
    "sg:postcode":"30038",
    "sg:province":"GA",
    "wof:name":"Martin Luther King Jr High Sch",
    "wof:placetype":"venue"
},
  "geometry": {"coordinates":[-84.19525,33.664319],"type":"Point"}
}