{
  "type": "Feature",
  "properties": {
    "iso:country":"US",
    "sg:address":"145 Tuttle Ln",
    "sg:city":"Brunswick",
    "sg:classifiers":[
        {
            "category":"Professional",
            "type":"Services"
        }
    ],
    "sg:phone":"+1 912 554 0888",
    "sg:postcode":"31520",
    "sg:province":"GA",
    "sg:tags":[
        "establishment"
    ],
    "wof:name":"Time Slicer",
    "wof:placetype":"venue"
},
  "geometry": {"coordinates":[-81.506305,31.217705],"type":"Point"}
}