{
  "type": "Feature",
  "properties": {
    "iso:country":"US",
    "sg:address":"553 Riverstone Pkwy",
    "sg:city":"Canton",
    "sg:classifiers":[
        {
            "category":"Sports & Exercise",
            "subcategory":"Gym",
            "type":"Entertainment"
        }
    ],
    "sg:phone":"+1 770 720 4653",
    "sg:postcode":"30114",
    "sg:province":"GA",
    "sg:tags":[
        "facility",
        "club",
        "gymnasium",
        "health",
        "fitness",
        "studio",
        "physical"
    ],
    "wof:name":"Gold's Gym",
    "wof:placetype":"venue"
},
  "geometry": {"coordinates":[-84.483424,34.245265],"type":"Point"}
}