{
  "type": "Feature",
  "properties": {
    "iso:country":"US",
    "sg:address":"2156 Sylvan Rd",
    "sg:city":"East Point",
    "sg:classifiers":[
        {
            "category":"Shopping",
            "type":"Retail Goods"
        }
    ],
    "sg:phone":"+1 404 530 0872",
    "sg:postcode":"30344",
    "sg:province":"GA",
    "sg:tags":[
        "monument"
    ],
    "wof:name":"Arlington Memorial Co",
    "wof:placetype":"venue"
},
  "geometry": {"coordinates":[-84.41831500000001,33.696606],"type":"Point"}
}