{
  "type": "Feature",
  "properties": {
    "iso:country":"US",
    "sg:address":"2921 Lenox Road NE",
    "sg:city":"Atlanta",
    "sg:classifiers":[
        {
            "category":"Real Estate",
            "subcategory":"Real Estate Operator",
            "type":"Services"
        }
    ],
    "sg:phone":"+1 404 233 5540",
    "sg:postcode":"30324",
    "sg:province":"GA",
    "sg:tags":[
        "apartment"
    ],
    "wof:name":"The Richmond",
    "wof:placetype":"venue"
},
  "geometry": {"coordinates":[-84.35753699999999,33.834335],"type":"Point"}
}