{
  "type": "Feature",
  "properties": {
    "iso:country":"US",
    "sg:address":"2782 Riverside Dr",
    "sg:city":"Macon",
    "sg:classifiers":[
        {
            "category":"Shopping",
            "type":"Retail Goods"
        }
    ],
    "sg:phone":"+1 478 750 9770",
    "sg:postcode":"31204",
    "sg:province":"GA",
    "sg:tags":[
        "merchandise"
    ],
    "wof:name":"Riverside Trophies",
    "wof:placetype":"venue"
},
  "geometry": {"coordinates":[-83.666737,32.878105],"type":"Point"}
}