{
  "type": "Feature",
  "properties": {
    "addr:full":"1033 Franklin Rd SE Marietta GA 30067",
    "addr:housenumber":"1033",
    "addr:postcode":"30067",
    "addr:street":"Franklin Rd Se",
    "iso:country":"US",
    "sg:address":"1033 Franklin Rd SE",
    "sg:city":"Marietta",
    "sg:classifiers":[
        {
            "category":"Restaurant",
            "type":"Food & Drink"
        }
    ],
    "sg:phone":"+1 770 690 9988",
    "sg:postcode":"30067",
    "sg:province":"GA",
    "wof:name":"Red Train",
    "wof:placetype":"venue"
},
  "geometry": {"coordinates":[-84.49430099999999,33.9286],"type":"Point"}
}