{
  "type": "Feature",
  "properties": {
    "iso:country":"US",
    "sg:address":"5959 Mark Trl",
    "sg:city":"Norcross",
    "sg:classifiers":[
        {
            "category":"Manufacturing",
            "subcategory":"Leather Goods",
            "type":"Manufacturing & Wholesale Goods"
        }
    ],
    "sg:phone":"+1 770 925 0390",
    "sg:postcode":"30093",
    "sg:province":"GA",
    "sg:tags":[
        "manufacturer"
    ],
    "wof:name":"Mabry Custom Leather",
    "wof:placetype":"venue"
},
  "geometry": {"coordinates":[-84.186875,33.893098],"type":"Point"}
}