{
  "type": "Feature",
  "properties": {
    "addr:full":"208 Sandy Springs Place NE Atlanta GA 30328",
    "addr:housenumber":"208",
    "addr:postcode":"30328",
    "addr:street":"Sandy Springs Place Ne",
    "iso:country":"US",
    "sg:address":"208 Sandy Springs Place NE",
    "sg:city":"Atlanta",
    "sg:classifiers":[
        {
            "category":"Retail",
            "subcategory":"Veterinary Services",
            "type":"Services"
        }
    ],
    "sg:phone":"+1 404 255 9345",
    "sg:postcode":"30328",
    "sg:province":"GA",
    "sg:tags":[
        "veterinarian"
    ],
    "wof:name":"North Atlanta Animal Medical",
    "wof:placetype":"venue"
},
  "geometry": {"coordinates":[-84.381314,33.921438],"type":"Point"}
}