{
  "type": "Feature",
  "properties": {
    "iso:country":"US",
    "sg:address":"1383 Wyntercreek Ln",
    "sg:city":"Atlanta",
    "sg:classifiers":[
        {
            "category":"Professional",
            "type":"Services"
        }
    ],
    "sg:phone":"+1 770 393 3522",
    "sg:postcode":"30338",
    "sg:province":"GA",
    "sg:tags":[
        "establishment"
    ],
    "wof:name":"Bosworth's Designs",
    "wof:placetype":"venue"
},
  "geometry": {"coordinates":[-84.334958,33.954706],"type":"Point"}
}