{
  "type": "Feature",
  "properties": {
    "addr:full":"3155 Franklinton Rd Dry Branch GA 31020",
    "addr:housenumber":"3155",
    "addr:postcode":"31020",
    "addr:street":"Franklinton Rd Dry Branch",
    "iso:country":"US",
    "sg:address":"3155 Franklinton Rd",
    "sg:city":"Dry Branch",
    "sg:classifiers":[
        {
            "category":"Manufacturing",
            "subcategory":"Building Materials",
            "type":"Manufacturing & Wholesale Goods"
        }
    ],
    "sg:phone":"+1 478 742 4594",
    "sg:postcode":"31020",
    "sg:province":"GA",
    "sg:website":"www.huttig.com",
    "wof:name":"Huttig Building Products",
    "wof:placetype":"venue"
},
  "geometry": {"coordinates":[-83.533385,32.804139],"type":"Point"}
}