{
  "type": "Feature",
  "properties": {
    "addr:full":"1265 N Cherokee Rd Social Circle GA 30025",
    "addr:housenumber":"1265",
    "addr:postcode":"30025",
    "addr:street":"N Cherokee Rd;Circle",
    "iso:country":"US",
    "sg:address":"1265 N Cherokee Rd",
    "sg:city":"Social Circle",
    "sg:classifiers":[
        {
            "category":"Restaurant",
            "type":"Food & Drink"
        }
    ],
    "sg:menulink":"http://www.allmenus.com/ga/social-circle/160526-burger-king/menu/",
    "sg:phone":"+1 770 464 0269",
    "sg:postcode":"30025",
    "sg:province":"GA",
    "sg:tags":[
        "burger",
        "american"
    ],
    "wof:name":"Burger King",
    "wof:placetype":"venue"
},
  "geometry": {"coordinates":[-83.708066,33.676195],"type":"Point"}
}