{
  "type": "Feature",
  "properties": {
    "addr:full":"3915 Cascade Road SW Atlanta GA 30331",
    "addr:housenumber":"3915",
    "addr:postcode":"30331",
    "addr:street":"Cascade Road Sw",
    "iso:country":"US",
    "sg:address":"3915 Cascade Road SW",
    "sg:city":"Atlanta",
    "sg:classifiers":[
        {
            "category":"Shopping",
            "subcategory":"Hobbies, Toys, & Games",
            "type":"Retail Goods"
        },
        {
            "category":"Professional",
            "subcategory":"Lawyer & Legal Services",
            "type":"Services"
        }
    ],
    "sg:phone":"+1 404 446 3400",
    "sg:postcode":"30331",
    "sg:province":"GA",
    "sg:tags":[
        "supply"
    ],
    "sg:website":"www.millerandgaines.com",
    "wof:name":"Miller & Gaines PC",
    "wof:placetype":"venue"
},
  "geometry": {"coordinates":[-84.516289,33.726037],"type":"Point"}
}