{
  "type": "Feature",
  "properties": {
    "addr:full":"1559 Lilburn Stone Mtn Rd Stone Mountain GA 30087",
    "addr:housenumber":"1559",
    "addr:postcode":"30087",
    "addr:street":"Lilburn Stone Mtn Rd",
    "iso:country":"US",
    "sg:address":"1559 Lilburn Stone Mtn Rd",
    "sg:city":"Stone Mountain",
    "sg:classifiers":[
        {
            "category":"Food & Beverages",
            "subcategory":"Liquor & Beverages",
            "type":"Retail Goods"
        }
    ],
    "sg:phone":"+1 770 469 1483",
    "sg:postcode":"30087",
    "sg:province":"GA",
    "sg:tags":[
        "beer",
        "spirit",
        "wine"
    ],
    "wof:name":"Atkinson Richard",
    "wof:placetype":"venue"
},
  "geometry": {"coordinates":[-84.153198,33.828899],"type":"Point"}
}