{
  "type": "Feature",
  "properties": {
    "addr:full":"1857 Gordon Hwy Augusta GA 30904",
    "addr:housenumber":"1857",
    "addr:postcode":"30904",
    "addr:street":"Gordon Hwy",
    "iso:country":"US",
    "sg:address":"1857 Gordon Hwy",
    "sg:city":"Augusta",
    "sg:classifiers":[
        {
            "category":"Food & Beverages",
            "subcategory":"Liquor & Beverages",
            "type":"Retail Goods"
        }
    ],
    "sg:phone":"+1 706 738 5526",
    "sg:postcode":"30904",
    "sg:province":"GA",
    "wof:name":"Daniels Package Store",
    "wof:placetype":"venue"
},
  "geometry": {"coordinates":[-82.037503,33.45145],"type":"Point"}
}