{
  "type": "Feature",
  "properties": {
    "addr:full":"101 W Jefferson St Americus GA 31709",
    "addr:housenumber":"101",
    "addr:postcode":"31709",
    "addr:street":"W Jefferson St",
    "iso:country":"US",
    "sg:address":"101 W Jefferson St",
    "sg:city":"Americus",
    "sg:classifiers":[
        {
            "category":"Deli",
            "type":"Food & Drink"
        },
        {
            "category":"Restaurant",
            "type":"Food & Drink"
        }
    ],
    "sg:phone":"+1 229 924 2222",
    "sg:postcode":"31709",
    "sg:province":"GA",
    "sg:tags":[
        "delicatessen"
    ],
    "wof:name":"King's Deli",
    "wof:placetype":"venue"
},
  "geometry": {"coordinates":[-84.23252100000001,32.074348],"type":"Point"}
}