{
  "type": "Feature",
  "properties": {
    "addr:full":"3611 New High Shoals Rd Bishop GA 30621",
    "addr:housenumber":"3611",
    "addr:postcode":"30621",
    "addr:street":"New High Shoals Rd",
    "iso:country":"US",
    "sg:address":"3611 New High Shoals Rd",
    "sg:city":"Bishop",
    "sg:classifiers":[
        {
            "category":"Building & Trades",
            "subcategory":"Construction",
            "type":"Services"
        }
    ],
    "sg:phone":"+1 706 769 3770",
    "sg:postcode":"30621",
    "sg:province":"GA",
    "sg:tags":[
        "contractor",
        "fence-sales"
    ],
    "wof:name":"Brown's Fence Contracting",
    "wof:placetype":"venue"
},
  "geometry": {"coordinates":[-83.491407,33.830263],"type":"Point"}
}