{
  "type": "Feature",
  "properties": {
    "iso:country":"US",
    "sg:address":"3295 Old Highway 5 S",
    "sg:city":"Ellijay",
    "sg:classifiers":[
        {
            "category":"Place Of Worship",
            "subcategory":"Church",
            "type":"Public Place"
        },
        {
            "category":"Place Of Worship",
            "type":"Public Place"
        }
    ],
    "sg:phone":"+1 706 636 4673",
    "sg:postcode":"30540",
    "sg:province":"GA",
    "sg:tags":[
        "lutheran",
        "america",
        "churches-lutheran",
        "churches-lutheran-evangelical"
    ],
    "wof:name":"Elca",
    "wof:placetype":"venue"
},
  "geometry": {"coordinates":[-84.517363,34.62384],"type":"Point"}
}