{
  "type": "Feature",
  "properties": {
    "addr:full":"2049 Old Savannah Rd Augusta GA 30901",
    "addr:housenumber":"2049",
    "addr:postcode":"30901",
    "addr:street":"Old Savannah Rd",
    "iso:country":"US",
    "sg:address":"2049 Old Savannah Rd",
    "sg:city":"Augusta",
    "sg:classifiers":[
        {
            "category":"Personal",
            "subcategory":"Barber",
            "type":"Services"
        }
    ],
    "sg:phone":"+1 706 826 4844",
    "sg:postcode":"30901",
    "sg:province":"GA",
    "sg:tags":[
        "shop"
    ],
    "wof:name":"Chris Barber",
    "wof:placetype":"venue"
},
  "geometry": {"coordinates":[-81.99570300000001,33.441923],"type":"Point"}
}