{
  "type": "Feature",
  "properties": {
    "addr:full":"2132 Hopkins Mill Rd Duluth GA 30096",
    "addr:housenumber":"2132",
    "addr:postcode":"30096",
    "addr:street":"Hopkins Mill Rd",
    "iso:country":"US",
    "sg:address":"2132 Hopkins Mill Rd",
    "sg:city":"Duluth",
    "sg:classifiers":[
        {
            "category":"Wholesale",
            "subcategory":"Non-durable Goods",
            "type":"Manufacturing & Wholesale Goods"
        }
    ],
    "sg:phone":"+1 770 449 6742",
    "sg:postcode":"30096",
    "sg:province":"GA",
    "sg:tags":[
        "merchandise-wholesale"
    ],
    "wof:name":"Pps Distributors Inc",
    "wof:placetype":"venue"
},
  "geometry": {"coordinates":[-84.162577,33.946048],"type":"Point"}
}