{
  "type": "Feature",
  "properties": {
    "addr:full":"1613 Bryn Mawr Cir Marietta GA 30068",
    "addr:housenumber":"1613",
    "addr:postcode":"30068",
    "addr:street":"Bryn Mawr Cir",
    "iso:country":"US",
    "sg:address":"1613 Bryn Mawr Cir",
    "sg:city":"Marietta",
    "sg:classifiers":[
        {
            "category":"Insurance",
            "subcategory":"Insurance Agent",
            "type":"Services"
        }
    ],
    "sg:phone":"+1 770 579 1646",
    "sg:postcode":"30068",
    "sg:province":"GA",
    "wof:name":"Radian Guaranty Inc",
    "wof:placetype":"venue"
},
  "geometry": {"coordinates":[-84.412138,33.987326],"type":"Point"}
}