{
  "type": "Feature",
  "properties": {
    "addr:full":"223 S Sims St Bainbridge GA 39817",
    "addr:housenumber":"223",
    "addr:postcode":"39817",
    "addr:street":"S Sims St",
    "iso:country":"US",
    "sg:address":"223 S Sims St",
    "sg:city":"Bainbridge",
    "sg:classifiers":[
        {
            "category":"Shopping",
            "subcategory":"Department Store",
            "type":"Retail Goods"
        }
    ],
    "sg:phone":"+1 229 243 9919",
    "sg:postcode":"39817",
    "sg:province":"GA",
    "wof:name":"His & Hers Elite",
    "wof:placetype":"venue"
},
  "geometry": {"coordinates":[-84.56153500000001,30.904596],"type":"Point"}
}