{
  "type": "Feature",
  "properties": {
    "addr:full":"2835 Mornington Dr NW Atlanta GA 30327",
    "addr:housenumber":"2835",
    "addr:postcode":"30327",
    "addr:street":"Mornington Dr Nw",
    "iso:country":"US",
    "sg:address":"2835 Mornington Dr NW",
    "sg:city":"Atlanta",
    "sg:classifiers":[
        {
            "category":"Professional",
            "type":"Services"
        },
        {
            "category":"Professional",
            "subcategory":"Management & Consulting",
            "type":"Services"
        }
    ],
    "sg:phone":"+1 404 352 0393",
    "sg:postcode":"30327",
    "sg:province":"GA",
    "sg:tags":[
        "consultant"
    ],
    "wof:name":"Stanley Fiveash Consulting",
    "wof:placetype":"venue"
},
  "geometry": {"coordinates":[-84.411641,33.834706],"type":"Point"}
}