{
  "type": "Feature",
  "properties": {
    "addr:full":"87 Gawin Dr Warner Robins GA 31093",
    "addr:housenumber":"87",
    "addr:postcode":"31093",
    "addr:street":"Gawin Dr",
    "iso:country":"US",
    "sg:address":"87 Gawin Dr",
    "sg:city":"Warner Robins",
    "sg:classifiers":[
        {
            "category":"Food & Beverages",
            "subcategory":"Liquor & Beverages",
            "type":"Retail Goods"
        },
        {
            "category":"Food & Beverages",
            "subcategory":"Groceries & Convenience Stores",
            "type":"Retail Goods"
        }
    ],
    "sg:phone":"+1 478 929 4790",
    "sg:postcode":"31093",
    "sg:province":"GA",
    "sg:tags":[
        "beer",
        "spirit",
        "wine"
    ],
    "wof:name":"Stop and Go Bp",
    "wof:placetype":"venue"
},
  "geometry": {"coordinates":[-83.658798,32.639999],"type":"Point"}
}