{
  "type": "Feature",
  "properties": {
    "addr:full":"1658 S Chestatee Dahlonega GA 30533",
    "addr:housenumber":"1658",
    "addr:postcode":"30533",
    "addr:street":"S Chestatee",
    "iso:country":"US",
    "sg:address":"1658 S Chestatee",
    "sg:city":"Dahlonega",
    "sg:classifiers":[
        {
            "category":"Home & Garden",
            "subcategory":"Building Materials",
            "type":"Retail Goods"
        }
    ],
    "sg:phone":"+1 770 534 3465",
    "sg:postcode":"30533",
    "sg:province":"GA",
    "wof:name":"Lummus Supply Co",
    "wof:placetype":"venue"
},
  "geometry": {"coordinates":[-83.975613,34.515045],"type":"Point"}
}