{
  "type": "Feature",
  "properties": {
    "iso:country":"US",
    "sg:address":"307 Jackson Woods Blvd",
    "sg:city":"Savannah",
    "sg:classifiers":[
        {
            "category":"Insurance",
            "subcategory":"Insurance Agent",
            "type":"Services"
        }
    ],
    "sg:phone":"+1 912 352 3501",
    "sg:postcode":"31405",
    "sg:province":"GA",
    "wof:name":"Arnold H Karp Insurance Agcy",
    "wof:placetype":"venue"
},
  "geometry": {"coordinates":[-81.110068,32.016467],"type":"Point"}
}