{
  "type": "Feature",
  "properties": {
    "iso:country":"US",
    "sg:address":"2410 Bethelview Rd",
    "sg:city":"Cumming",
    "sg:classifiers":[
        {
            "category":"Insurance",
            "subcategory":"Insurance Agent",
            "type":"Services"
        }
    ],
    "sg:phone":"+1 770 887 9256",
    "sg:postcode":"30040",
    "sg:province":"GA",
    "wof:name":"Integrity Insurance & Finance",
    "wof:placetype":"venue"
},
  "geometry": {"coordinates":[-84.194737,34.237019],"type":"Point"}
}