{
  "type": "Feature",
  "properties": {
    "addr:full":"1206 N Slappey Blvd Albany GA 31701",
    "addr:housenumber":"1206",
    "addr:postcode":"31701",
    "addr:street":"N Slappey Blvd",
    "iso:country":"US",
    "sg:address":"1206 N Slappey Blvd",
    "sg:city":"Albany",
    "sg:classifiers":[
        {
            "category":"Wholesale",
            "subcategory":"Machinery & Supplies",
            "type":"Manufacturing & Wholesale Goods"
        }
    ],
    "sg:phone":"+1 229 878 0300",
    "sg:postcode":"31701",
    "sg:province":"GA",
    "sg:tags":[
        "equipment",
        "safety",
        "clothing"
    ],
    "wof:name":"Safety Max",
    "wof:placetype":"venue"
},
  "geometry": {"coordinates":[-84.175923,31.59433],"type":"Point"}
}