{
  "type": "Feature",
  "properties": {
    "addr:full":"4799 Helton Rd Gainesville GA 30506",
    "addr:housenumber":"4799",
    "addr:postcode":"30506",
    "addr:street":"Helton Rd",
    "iso:country":"US",
    "sg:address":"4799 Helton Rd",
    "sg:city":"Gainesville",
    "sg:classifiers":[
        {
            "category":"Professional",
            "subcategory":"Printing & Photocopies",
            "type":"Services"
        }
    ],
    "sg:phone":"+1 770 983 9550",
    "sg:postcode":"30506",
    "sg:province":"GA",
    "sg:tags":[
        "duplicating",
        "copying"
    ],
    "sg:website":"www.copymedicalrecords.com",
    "wof:name":"Correspondence Copy Svc",
    "wof:placetype":"venue"
},
  "geometry": {"coordinates":[-83.821845,34.415493],"type":"Point"}
}