{
  "type": "Feature",
  "properties": {
    "iso:country":"US",
    "sg:address":"4881 Arcado Rd SW",
    "sg:city":"Lilburn",
    "sg:classifiers":[
        {
            "category":"Home & Garden",
            "subcategory":"Hardware",
            "type":"Retail Goods"
        }
    ],
    "sg:phone":"+1 770 638 0040",
    "sg:postcode":"30047",
    "sg:province":"GA",
    "wof:name":"Best Value Inn",
    "wof:placetype":"venue"
},
  "geometry": {"coordinates":[-84.12802600000001,33.87425],"type":"Point"}
}