{
  "type": "Feature",
  "properties": {
    "iso:country":"US",
    "sg:address":"588 Washington Ave NE",
    "sg:city":"Marietta",
    "sg:classifiers":[
        {
            "category":"Personal",
            "subcategory":"Beauty Salon",
            "type":"Services"
        }
    ],
    "sg:phone":"+1 770 827 8298",
    "sg:postcode":"30060",
    "sg:province":"GA",
    "sg:tags":[
        "shop"
    ],
    "wof:name":"Tony 4 Cuts",
    "wof:placetype":"venue"
},
  "geometry": {"coordinates":[-84.53471399999999,33.952081],"type":"Point"}
}