{
  "type": "Feature",
  "properties": {
    "iso:country":"US",
    "sg:address":"2830 Sagamore Hill Dr SE",
    "sg:city":"Marietta",
    "sg:classifiers":[
        {
            "category":"Professional",
            "subcategory":"Management & Consulting",
            "type":"Services"
        },
        {
            "category":"Professional",
            "subcategory":"Engineering",
            "type":"Services"
        }
    ],
    "sg:phone":"+1 770 951 8748",
    "sg:postcode":"30067",
    "sg:province":"GA",
    "sg:tags":[
        "consultant",
        "ecological",
        "engineer",
        "environmental"
    ],
    "wof:name":"G & S Enterprises Inc",
    "wof:placetype":"venue"
},
  "geometry": {"coordinates":[-84.470575,33.933913],"type":"Point"}
}