{
  "type": "Feature",
  "properties": {
    "iso:country":"US",
    "sg:address":"231 W Memorial Dr",
    "sg:city":"Dallas",
    "sg:classifiers":[
        {
            "category":"Retail",
            "subcategory":"Auto Repair",
            "type":"Services"
        }
    ],
    "sg:phone":"+1 770 505 5622",
    "sg:postcode":"30132",
    "sg:province":"GA",
    "sg:tags":[
        "automobile",
        "customizing"
    ],
    "wof:name":"Street Sweeper Customs",
    "wof:placetype":"venue"
},
  "geometry": {"coordinates":[-84.84331400000001,33.923956],"type":"Point"}
}