{
  "type": "Feature",
  "properties": {
    "iso:country":"US",
    "sg:address":"85 Mcdonough St",
    "sg:city":"Hampton",
    "sg:classifiers":[
        {
            "category":"Place Of Worship",
            "subcategory":"Church",
            "type":"Public Place"
        }
    ],
    "sg:phone":"+1 770 946 4804",
    "sg:postcode":"30228",
    "sg:province":"GA",
    "sg:tags":[
        "churches-baptist"
    ],
    "wof:name":"First Baptist Church Of Hampton",
    "wof:placetype":"venue"
},
  "geometry": {"coordinates":[-84.27030600000001,33.383235],"type":"Point"}
}