{
  "type": "Feature",
  "properties": {
    "iso:country":"US",
    "sg:address":"3127 Flamingo Dr",
    "sg:city":"Atlanta",
    "sg:classifiers":[
        {
            "category":"Professional",
            "subcategory":"Management & Consulting",
            "type":"Services"
        }
    ],
    "sg:phone":"+1 404 494 3186",
    "sg:postcode":"30344",
    "sg:province":"GA",
    "wof:name":"Paige Davis Management Systems",
    "wof:placetype":"venue"
},
  "geometry": {"coordinates":[-84.479011,33.669225],"type":"Point"}
}