{
  "type": "Feature",
  "properties": {
    "addr:full":"3589 Fryer Rd Jakin GA 39861",
    "addr:housenumber":"3589",
    "addr:postcode":"39861",
    "addr:street":"Fryer Rd",
    "iso:country":"US",
    "sg:address":"3589 Fryer Rd",
    "sg:city":"Jakin",
    "sg:classifiers":[
        {
            "category":"Farming",
            "subcategory":"Farm",
            "type":"Manufacturing & Wholesale Goods"
        }
    ],
    "sg:phone":"+1 229 372 4781",
    "sg:postcode":"39861",
    "sg:province":"GA",
    "wof:name":"Phillip Buckhalter Farms",
    "wof:placetype":"venue"
},
  "geometry": {"coordinates":[-84.954159,31.297769],"type":"Point"}
}