{
  "type": "Feature",
  "properties": {
    "addr:full":"1631 Phoenix Blvd Atlanta GA 30349",
    "addr:housenumber":"1631",
    "addr:postcode":"30349",
    "addr:street":"Phoenix Blvd",
    "iso:country":"US",
    "sg:address":"1631 Phoenix Blvd",
    "sg:city":"Atlanta",
    "sg:classifiers":[
        {
            "category":"Insurance",
            "subcategory":"Insurance Agent",
            "type":"Services"
        }
    ],
    "sg:phone":"+1 770 996 4724",
    "sg:postcode":"30349",
    "sg:province":"GA",
    "sg:tags":[
        "information"
    ],
    "wof:name":"Portamedic 624",
    "wof:placetype":"venue"
},
  "geometry": {"coordinates":[-84.442992,33.61477],"type":"Point"}
}