{
  "type": "Feature",
  "properties": {
    "iso:country":"US",
    "sg:address":"2399 Lawrenceville Hwy",
    "sg:city":"Lawrenceville",
    "sg:classifiers":[
        {
            "category":"Restaurant",
            "type":"Food & Drink"
        }
    ],
    "sg:phone":"+1 770 338 9688",
    "sg:postcode":"30044",
    "sg:province":"GA",
    "sg:tags":[
        "caterer"
    ],
    "wof:name":"Dedi-Caters",
    "wof:placetype":"venue"
},
  "geometry": {"coordinates":[-84.060748,33.926522],"type":"Point"}
}