{
  "type": "Feature",
  "properties": {
    "addr:full":"423 Commercial Dr Thomasville GA 31792",
    "addr:housenumber":"423",
    "addr:postcode":"31792",
    "addr:street":"Commercial Dr",
    "iso:country":"US",
    "sg:address":"423 Commercial Dr",
    "sg:city":"Thomasville",
    "sg:classifiers":[
        {
            "category":"Home & Garden",
            "subcategory":"Garden Supply",
            "type":"Retail Goods"
        }
    ],
    "sg:phone":"+1 229 225 9595",
    "sg:postcode":"31792",
    "sg:province":"GA",
    "sg:tags":[
        "sprinkler"
    ],
    "wof:name":"Rain Pro",
    "wof:placetype":"venue"
},
  "geometry": {"coordinates":[-83.940286,30.852642],"type":"Point"}
}