{
  "type": "Feature",
  "properties": {
    "iso:country":"US",
    "sg:address":"401 N Duval St",
    "sg:city":"Claxton",
    "sg:classifiers":[
        {
            "category":"Shopping",
            "subcategory":"Department Store",
            "type":"Retail Goods"
        }
    ],
    "sg:phone":"+1 912 739 2482",
    "sg:postcode":"30417",
    "sg:province":"GA",
    "sg:website":"http://www.familydollar.com",
    "wof:name":"Family Dollar Stores",
    "wof:placetype":"venue"
},
  "geometry": {"coordinates":[-81.903373,32.16705],"type":"Point"}
}