{
  "type": "Feature",
  "properties": {
    "addr:full":"885 Woodstock Rd Roswell GA 30075",
    "addr:housenumber":"885",
    "addr:postcode":"30075",
    "addr:street":"Woodstock Rd",
    "iso:country":"US",
    "sg:address":"885 Woodstock Rd",
    "sg:city":"Roswell",
    "sg:classifiers":[
        {
            "category":"Utilities",
            "subcategory":"Mobile Phone",
            "type":"Services"
        }
    ],
    "sg:phone":"+1 770 552 4141",
    "sg:postcode":"30075",
    "sg:province":"GA",
    "sg:tags":[
        "communication",
        "radiotelephone"
    ],
    "wof:name":"Wireless Innovations",
    "wof:placetype":"venue"
},
  "geometry": {"coordinates":[-84.391503,34.062613],"type":"Point"}
}