{
  "type": "Feature",
  "properties": {
    "addr:full":"628 Myrick St Waynesboro GA 30830",
    "addr:housenumber":"628",
    "addr:postcode":"30830",
    "addr:street":"Myrick St",
    "iso:country":"US",
    "sg:address":"628 Myrick St",
    "sg:city":"Waynesboro",
    "sg:classifiers":[
        {
            "category":"Government",
            "subcategory":"Police Station",
            "type":"Public Place"
        }
    ],
    "sg:phone":"+1 706 554 4444",
    "sg:postcode":"30830",
    "sg:province":"GA",
    "sg:tags":[
        "department"
    ],
    "wof:name":"Police Department",
    "wof:placetype":"venue"
},
  "geometry": {"coordinates":[-82.014904,33.090664],"type":"Point"}
}