{
  "type": "Feature",
  "properties": {
    "addr:full":"2990 Hogan Rd SW Atlanta GA 30331",
    "addr:housenumber":"2990",
    "addr:postcode":"30331",
    "addr:street":"Hogan Rd Sw",
    "iso:country":"US",
    "sg:address":"2990 Hogan Rd SW",
    "sg:city":"Atlanta",
    "sg:classifiers":[
        {
            "category":"Wholesale",
            "subcategory":"Non-durable Goods",
            "type":"Manufacturing & Wholesale Goods"
        }
    ],
    "sg:phone":"+1 404 349 3063",
    "sg:postcode":"30331",
    "sg:province":"GA",
    "wof:name":"Abundant Scent Sations",
    "wof:placetype":"venue"
},
  "geometry": {"coordinates":[-84.486617,33.67792],"type":"Point"}
}