{
  "type": "Feature",
  "properties": {
    "addr:full":"3718 Dallas Hwy Marietta GA 30064",
    "addr:housenumber":"3718",
    "addr:postcode":"30064",
    "addr:street":"Dallas Hwy",
    "iso:country":"US",
    "sg:address":"3718 Dallas Hwy",
    "sg:city":"Marietta",
    "sg:classifiers":[
        {
            "category":"Shopping",
            "subcategory":"Clothing, Apparel, & Fashions",
            "type":"Retail Goods"
        }
    ],
    "sg:phone":"+1 770 499 0023",
    "sg:postcode":"30064",
    "sg:province":"GA",
    "sg:tags":[
        "wear"
    ],
    "wof:name":"Gymboree",
    "wof:placetype":"venue"
},
  "geometry": {"coordinates":[-84.66015400000001,33.953196],"type":"Point"}
}