{
  "type": "Feature",
  "properties": {
    "iso:country":"US",
    "sg:address":"4260 Happy Valley Cir",
    "sg:city":"Newnan",
    "sg:classifiers":[
        {
            "category":"Professional",
            "subcategory":"Advertising",
            "type":"Services"
        }
    ],
    "sg:phone":"+1 770 251 1553",
    "sg:postcode":"30263",
    "sg:province":"GA",
    "sg:tags":[
        "specialty"
    ],
    "wof:name":"Sky Georgia Sign Inc",
    "wof:placetype":"venue"
},
  "geometry": {"coordinates":[-84.762855,33.452126],"type":"Point"}
}