{
  "type": "Feature",
  "properties": {
    "iso:country":"US",
    "sg:address":"202 Church St",
    "sg:city":"Marietta",
    "sg:classifiers":[
        {
            "category":"Insurance",
            "subcategory":"Hazard Insurance",
            "type":"Services"
        }
    ],
    "sg:phone":"+1 770 428 3308",
    "sg:postcode":"30060",
    "sg:province":"GA",
    "sg:website":"littleandsmith.com/",
    "wof:name":"Little & Smith",
    "wof:placetype":"venue"
},
  "geometry": {"coordinates":[-84.54976600000001,33.956582],"type":"Point"}
}