{
  "type": "Feature",
  "properties": {
    "addr:full":"6459 Zebulon Rd Macon GA 31220",
    "addr:housenumber":"6459",
    "addr:postcode":"31220",
    "addr:street":"Zebulon Rd",
    "iso:country":"US",
    "sg:address":"6459 Zebulon Rd",
    "sg:city":"Macon",
    "sg:phone":"+1 478 405 2983",
    "sg:postcode":"31220",
    "sg:province":"GA",
    "sg:website":"http://www.advanceautoparts.com",
    "wof:name":"Advance Auto Parts",
    "wof:placetype":"venue"
},
  "geometry": {"coordinates":[-83.77520699999999,32.880449],"type":"Point"}
}