{
  "type": "Feature",
  "properties": {
    "iso:country":"US",
    "sg:address":"735 Holcomb Woods Ct",
    "sg:city":"Auburn",
    "sg:classifiers":[
        {
            "category":"Building & Trades",
            "subcategory":"Electrical",
            "type":"Services"
        }
    ],
    "sg:phone":"+1 770 995 7157",
    "sg:postcode":"30011",
    "sg:province":"GA",
    "sg:tags":[
        "electric",
        "contractor"
    ],
    "wof:name":"Watts Needed",
    "wof:placetype":"venue"
},
  "geometry": {"coordinates":[-83.87716500000001,34.036741],"type":"Point"}
}