{
  "type": "Feature",
  "properties": {
    "iso:country":"US",
    "sg:address":"143 Houston St",
    "sg:city":"Savannah",
    "sg:classifiers":[
        {
            "category":"Government",
            "subcategory":"Office",
            "type":"Public Place"
        }
    ],
    "sg:phone":"+1 912 651 2070",
    "sg:postcode":"31401",
    "sg:province":"GA",
    "sg:tags":[
        "state",
        "resource"
    ],
    "wof:name":"Human Resources Dept",
    "wof:placetype":"venue"
},
  "geometry": {"coordinates":[-81.08649200000001,32.075266],"type":"Point"}
}