{
  "type": "Feature",
  "properties": {
    "addr:full":"3524 Broad St Atlanta GA 30341",
    "addr:housenumber":"3524",
    "addr:postcode":"30341",
    "addr:street":"Broad St",
    "iso:country":"US",
    "sg:address":"3524 Broad St",
    "sg:city":"Atlanta",
    "sg:classifiers":[
        {
            "category":"Shopping",
            "subcategory":"Florist",
            "type":"Retail Goods"
        }
    ],
    "sg:phone":"+1 770 451 6852",
    "sg:postcode":"30341",
    "sg:province":"GA",
    "wof:name":"Chamblee Flower Shop",
    "wof:placetype":"venue"
},
  "geometry": {"coordinates":[-84.298383,33.89446],"type":"Point"}
}