{
  "type": "Feature",
  "properties": {
    "addr:full":"2820 Holly Springs Pkwy Canton GA 30115",
    "addr:housenumber":"2820",
    "addr:postcode":"30115",
    "addr:street":"Holly Springs Pkwy",
    "iso:country":"US",
    "sg:address":"2820 Holly Springs Pkwy",
    "sg:city":"Canton",
    "sg:classifiers":[
        {
            "category":"Retail",
            "subcategory":"Storage",
            "type":"Services"
        }
    ],
    "sg:phone":"+1 770 345 6464",
    "sg:postcode":"30115",
    "sg:province":"GA",
    "sg:tags":[
        "self"
    ],
    "wof:name":"Stuff'n Storage",
    "wof:placetype":"venue"
},
  "geometry": {"coordinates":[-84.501198,34.173599],"type":"Point"}
}