{
  "type": "Feature",
  "properties": {
    "iso:country":"US",
    "sg:address":"1628 Horseshoe Bend Rd",
    "sg:city":"Dahlonega",
    "sg:classifiers":[
        {
            "category":"Professional",
            "subcategory":"Lawyer & Legal Services",
            "type":"Services"
        }
    ],
    "sg:phone":"+1 706 219 2133",
    "sg:postcode":"30533",
    "sg:province":"GA",
    "wof:name":"Alfred K Barr PC",
    "wof:placetype":"venue"
},
  "geometry": {"coordinates":[-83.90821800000001,34.591613],"type":"Point"}
}