{
  "type": "Feature",
  "properties": {
    "addr:full":"1306 W Broad Ave Albany GA 31707",
    "addr:housenumber":"1306",
    "addr:postcode":"31707",
    "addr:street":"W Broad Ave",
    "iso:country":"US",
    "sg:address":"1306 W Broad Ave",
    "sg:city":"Albany",
    "sg:classifiers":[
        {
            "category":"Manufacturing",
            "subcategory":"Printing",
            "type":"Manufacturing & Wholesale Goods"
        }
    ],
    "sg:phone":"+1 229 889 1740",
    "sg:postcode":"31707",
    "sg:province":"GA",
    "sg:tags":[
        "lithographic",
        "screen",
        "commercial"
    ],
    "sg:website":"www.farrisscreenprinting.com",
    "wof:name":"Farris Screen Printing Inc",
    "wof:placetype":"venue"
},
  "geometry": {"coordinates":[-84.183403,31.576759],"type":"Point"}
}