{
  "type": "Feature",
  "properties": {
    "iso:country":"US",
    "sg:address":"191 Satterfield Rd",
    "sg:city":"Canton",
    "sg:classifiers":[
        {
            "category":"Professional",
            "type":"Services"
        }
    ],
    "sg:phone":"+1 678 493 9069",
    "sg:postcode":"30114",
    "sg:province":"GA",
    "wof:name":"Angela K Johnson",
    "wof:placetype":"venue"
},
  "geometry": {"coordinates":[-84.51236,34.221482],"type":"Point"}
}