{
  "type": "Feature",
  "properties": {
    "addr:full":"1130 Euclid Ave NE Atlanta GA 30307",
    "addr:housenumber":"1130",
    "addr:postcode":"30307",
    "addr:street":"Euclid Ave Ne",
    "iso:country":"US",
    "sg:address":"1130 Euclid Ave NE",
    "sg:city":"Atlanta",
    "sg:classifiers":[
        {
            "category":"Building & Trades",
            "subcategory":"Construction",
            "type":"Services"
        }
    ],
    "sg:phone":"+1 678 659 9600",
    "sg:postcode":"30307",
    "sg:province":"GA",
    "sg:tags":[
        "repair",
        "installation",
        "ceilings-supplies"
    ],
    "wof:name":"Just Repairs",
    "wof:placetype":"venue"
},
  "geometry": {"coordinates":[-84.35028800000001,33.764561],"type":"Point"}
}