{
  "type": "Feature",
  "properties": {
    "addr:full":"4151 Memorial Dr Decatur GA 30032",
    "addr:housenumber":"4151",
    "addr:postcode":"30032",
    "addr:street":"Memorial Dr",
    "iso:country":"US",
    "sg:address":"4151 Memorial Dr",
    "sg:city":"Decatur",
    "sg:classifiers":[
        {
            "category":"Shopping",
            "type":"Retail Goods"
        }
    ],
    "sg:phone":"+1 404 297 9461",
    "sg:postcode":"30032",
    "sg:province":"GA",
    "sg:tags":[
        "merchandise"
    ],
    "wof:name":"Georgia T E D P Program",
    "wof:placetype":"venue"
},
  "geometry": {"coordinates":[-84.24968200000001,33.771262],"type":"Point"}
}