{
  "type": "Feature",
  "properties": {
    "iso:country":"US",
    "sg:address":"995 Buddy Moore Rd",
    "sg:city":"Colbert",
    "sg:classifiers":[
        {
            "category":"Building & Trades",
            "subcategory":"Construction",
            "type":"Services"
        }
    ],
    "sg:phone":"+1 706 788 2938",
    "sg:postcode":"30628",
    "sg:province":"GA",
    "sg:tags":[
        "house"
    ],
    "wof:name":"All American Home Improvements",
    "wof:placetype":"venue"
},
  "geometry": {"coordinates":[-83.27923699999999,34.074025],"type":"Point"}
}