{
  "type": "Feature",
  "properties": {
    "iso:country":"US",
    "sg:address":"7 E Parrish St",
    "sg:city":"Statesboro",
    "sg:classifiers":[
        {
            "category":"Building & Trades",
            "subcategory":"Construction",
            "type":"Services"
        }
    ],
    "sg:phone":"+1 912 764 4624",
    "sg:postcode":"30458",
    "sg:province":"GA",
    "sg:tags":[
        "home",
        "improvement"
    ],
    "wof:name":"Honey-Do Maintenance",
    "wof:placetype":"venue"
},
  "geometry": {"coordinates":[-81.781227,32.458208],"type":"Point"}
}