{
  "type": "Feature",
  "properties": {
    "iso:country":"US",
    "sg:address":"614 Holloway Ave",
    "sg:city":"Albany",
    "sg:classifiers":[
        {
            "category":"Social Services",
            "subcategory":"Child Care",
            "type":"Services"
        }
    ],
    "sg:phone":"+1 229 439 2516",
    "sg:postcode":"31701",
    "sg:province":"GA",
    "sg:tags":[
        "center",
        "day"
    ],
    "wof:name":"Marys Kiddie Kottage",
    "wof:placetype":"venue"
},
  "geometry": {"coordinates":[-84.164703,31.563548],"type":"Point"}
}