{
  "type": "Feature",
  "properties": {
    "addr:full":"2041 Shallowford Rd Marietta GA 30066",
    "addr:housenumber":"2041",
    "addr:postcode":"30066",
    "addr:street":"Shallowford Rd",
    "iso:country":"US",
    "sg:address":"2041 Shallowford Rd",
    "sg:city":"Marietta",
    "sg:classifiers":[
        {
            "category":"Professional",
            "subcategory":"Management & Consulting",
            "type":"Services"
        }
    ],
    "sg:phone":"+1 770 591 1191",
    "sg:postcode":"30066",
    "sg:province":"GA",
    "sg:tags":[
        "organization",
        "religious"
    ],
    "wof:name":"Harmony Marketing & Sales",
    "wof:placetype":"venue"
},
  "geometry": {"coordinates":[-84.49346799999999,34.046923],"type":"Point"}
}