{
  "type": "Feature",
  "properties": {
    "addr:full":"1470 N Crossing Cir Atlanta GA 30329",
    "addr:housenumber":"1470",
    "addr:postcode":"30329",
    "addr:street":"N Crossing Cir",
    "iso:country":"US",
    "sg:address":"1470 N Crossing Cir",
    "sg:city":"Atlanta",
    "sg:classifiers":[
        {
            "category":"Shopping",
            "subcategory":"Computers & Home Electronics",
            "type":"Retail Goods"
        }
    ],
    "sg:phone":"+1 404 327 5677",
    "sg:postcode":"30329",
    "sg:province":"GA",
    "sg:tags":[
        "software"
    ],
    "sg:website":"www.saratogasystems.com",
    "wof:name":"Saratoga Systems",
    "wof:placetype":"venue"
},
  "geometry": {"coordinates":[-84.319936,33.823014],"type":"Point"}
}