{
  "type": "Feature",
  "properties": {
    "iso:country":"US",
    "sg:address":"4580 Big Sky Rd",
    "sg:city":"Blairsville",
    "sg:classifiers":[
        {
            "category":"Building & Trades",
            "subcategory":"Construction",
            "type":"Services"
        }
    ],
    "sg:phone":"+1 706 745 8133",
    "sg:postcode":"30512",
    "sg:province":"GA",
    "sg:tags":[
        "house"
    ],
    "wof:name":"Midcountry Construction Inc",
    "wof:placetype":"venue"
},
  "geometry": {"coordinates":[-83.873029,34.801421],"type":"Point"}
}