{
  "type": "Feature",
  "properties": {
    "addr:full":"442 Woodwind Ct Jonesboro GA 30236",
    "addr:housenumber":"442",
    "addr:postcode":"30236",
    "addr:street":"Woodwind Ct",
    "iso:country":"US",
    "sg:address":"442 Woodwind Ct",
    "sg:city":"Jonesboro",
    "sg:classifiers":[
        {
            "category":"Building & Trades",
            "subcategory":"Construction",
            "type":"Services"
        }
    ],
    "sg:phone":"+1 404 391 2064",
    "sg:postcode":"30236",
    "sg:province":"GA",
    "sg:tags":[
        "residential"
    ],
    "wof:name":"Rk Construction Co",
    "wof:placetype":"venue"
},
  "geometry": {"coordinates":[-84.283365,33.537804],"type":"Point"}
}