{
  "type": "Feature",
  "properties": {
    "addr:full":"283 Burtom Rd SW Eatonton GA 31024",
    "addr:housenumber":"283",
    "addr:postcode":"31024",
    "addr:street":"Burtom Rd Sw",
    "iso:country":"US",
    "sg:address":"283 Burtom Rd SW",
    "sg:city":"Eatonton",
    "sg:classifiers":[
        {
            "category":"Wholesale",
            "subcategory":"Non-durable Goods",
            "type":"Manufacturing & Wholesale Goods"
        }
    ],
    "sg:phone":"+1 706 485 9962",
    "sg:postcode":"31024",
    "sg:province":"GA",
    "wof:name":"Hull Woodwork",
    "wof:placetype":"venue"
},
  "geometry": {"coordinates":[-83.41423500000001,33.22388],"type":"Point"}
}