{
  "type": "Feature",
  "properties": {
    "addr:full":"119 Holiday Rd Buford GA 30518",
    "addr:housenumber":"119",
    "addr:postcode":"30518",
    "addr:street":"Holiday Rd",
    "iso:country":"US",
    "sg:address":"119 Holiday Rd",
    "sg:city":"Buford",
    "sg:classifiers":[
        {
            "category":"Real Estate",
            "subcategory":"Real Estate Operator",
            "type":"Services"
        }
    ],
    "sg:phone":"+1 770 945 2907",
    "sg:postcode":"30518",
    "sg:province":"GA",
    "sg:tags":[
        "condominium"
    ],
    "wof:name":"Friendship Corners LLC",
    "wof:placetype":"venue"
},
  "geometry": {"coordinates":[-83.96996,34.144574],"type":"Point"}
}