{
  "type": "Feature",
  "properties": {
    "addr:full":"400 Brantley Rd Atlanta GA 30350",
    "addr:housenumber":"400",
    "addr:postcode":"30350",
    "addr:street":"Brantley Rd",
    "iso:country":"US",
    "sg:address":"400 Brantley Rd",
    "sg:city":"Atlanta",
    "sg:classifiers":[
        {
            "category":"Food & Beverages",
            "subcategory":"Specialty",
            "type":"Retail Goods"
        }
    ],
    "sg:phone":"+1 770 730 0256",
    "sg:postcode":"30350",
    "sg:province":"GA",
    "wof:name":"Good Life Health Food Inc",
    "wof:placetype":"venue"
},
  "geometry": {"coordinates":[-84.356658,33.975425],"type":"Point"}
}