{
  "type": "Feature",
  "properties": {
    "addr:full":"810 Whitehead Rd Sugar Hill GA 30518",
    "addr:housenumber":"810",
    "addr:postcode":"30518",
    "addr:street":"Whitehead Rd",
    "iso:country":"US",
    "sg:address":"810 Whitehead Rd",
    "sg:city":"Sugar Hill",
    "sg:classifiers":[
        {
            "category":"Building & Trades",
            "subcategory":"Locksmith",
            "type":"Services"
        }
    ],
    "sg:phone":"+1 404 968 8314",
    "sg:postcode":"30518",
    "sg:province":"GA",
    "sg:tags":[
        "key"
    ],
    "wof:name":"North Locksmith",
    "wof:placetype":"venue"
},
  "geometry": {"coordinates":[-84.05082299999999,34.104022],"type":"Point"}
}