{
  "type": "Feature",
  "properties": {
    "addr:full":"2005 Augusta Ave Savannah GA 31415",
    "addr:housenumber":"2005",
    "addr:postcode":"31415",
    "addr:street":"Augusta Ave",
    "iso:country":"US",
    "sg:address":"2005 Augusta Ave",
    "sg:city":"Savannah",
    "sg:classifiers":[
        {
            "category":"Organizations",
            "subcategory":"Religious Organization",
            "type":"Services"
        }
    ],
    "sg:phone":"+1 912 236 8892",
    "sg:postcode":"31415",
    "sg:province":"GA",
    "sg:tags":[
        "church"
    ],
    "wof:name":"Solomon Temple Church Of God",
    "wof:placetype":"venue"
},
  "geometry": {"coordinates":[-81.122995,32.085949],"type":"Point"}
}