{
  "type": "Feature",
  "properties": {
    "iso:country":"US",
    "sg:address":"2415 Montview Dr NW",
    "sg:city":"Atlanta",
    "sg:classifiers":[
        {
            "category":"Professional",
            "type":"Services"
        }
    ],
    "sg:phone":"+1 404 355 4872",
    "sg:postcode":"30305",
    "sg:province":"GA",
    "wof:name":"Susan Welsh Inc",
    "wof:placetype":"venue"
},
  "geometry": {"coordinates":[-84.401307,33.819823],"type":"Point"}
}