{
  "type": "Feature",
  "properties": {
    "iso:country":"US",
    "sg:address":"2520 Woodland Way",
    "sg:city":"Brunswick",
    "sg:classifiers":[
        {
            "category":"Social Services",
            "subcategory":"Child Care",
            "type":"Services"
        }
    ],
    "sg:phone":"+1 912 267 6813",
    "sg:postcode":"31520",
    "sg:province":"GA",
    "sg:tags":[
        "day"
    ],
    "wof:name":"Bright Eyes Creative Learning",
    "wof:placetype":"venue"
},
  "geometry": {"coordinates":[-81.48868299999999,31.193153],"type":"Point"}
}