{
  "type": "Feature",
  "properties": {
    "iso:country":"US",
    "sg:address":"545 Lorene Dr",
    "sg:city":"Marietta",
    "sg:classifiers":[
        {
            "category":"Organizations",
            "subcategory":"Religious Organization",
            "type":"Services"
        }
    ],
    "sg:phone":"+1 770 431 0866",
    "sg:postcode":"30060",
    "sg:province":"GA",
    "sg:tags":[
        "church"
    ],
    "wof:name":"Praise International Mnstrs",
    "wof:placetype":"venue"
},
  "geometry": {"coordinates":[-84.566322,33.901895],"type":"Point"}
}