{
  "type": "Feature",
  "properties": {
    "iso:country":"US",
    "sg:address":"29 Poteet Dr",
    "sg:city":"Chickamauga",
    "sg:classifiers":[
        {
            "category":"Wholesale",
            "subcategory":"Auto Parts",
            "type":"Manufacturing & Wholesale Goods"
        }
    ],
    "sg:phone":"+1 706 375 8202",
    "sg:postcode":"30707",
    "sg:province":"GA",
    "sg:tags":[
        "automobile"
    ],
    "wof:name":"North Georgia Collision Ctr",
    "wof:placetype":"venue"
},
  "geometry": {"coordinates":[-85.277631,34.840197],"type":"Point"}
}