{
  "type": "Feature",
  "properties": {
    "addr:full":"3932 Pinehurst Valley Dr Decatur GA 30034",
    "addr:housenumber":"3932",
    "addr:postcode":"30034",
    "addr:street":"Pinehurst Valley Dr",
    "iso:country":"US",
    "sg:address":"3932 Pinehurst Valley Dr",
    "sg:city":"Decatur",
    "sg:classifiers":[
        {
            "category":"Professional",
            "subcategory":"Management & Consulting",
            "type":"Services"
        }
    ],
    "sg:phone":"+1 770 987 4777",
    "sg:postcode":"30034",
    "sg:province":"GA",
    "wof:name":"Johnson Financial Management",
    "wof:placetype":"venue"
},
  "geometry": {"coordinates":[-84.22516299999999,33.68635],"type":"Point"}
}