{
  "type": "Feature",
  "properties": {
    "addr:full":"102 E Clinton St Ste 5 Gray GA 31032",
    "addr:housenumber":"102",
    "addr:postcode":"31032",
    "addr:street":"E Clinton St Ste 5",
    "iso:country":"US",
    "sg:address":"102 E Clinton St Ste 5",
    "sg:city":"Gray",
    "sg:classifiers":[
        {
            "category":"Insurance",
            "subcategory":"Hazard Insurance",
            "type":"Services"
        },
        {
            "category":"Insurance",
            "subcategory":"Life Insurance",
            "type":"Services"
        }
    ],
    "sg:phone":"+1 478 986 1042",
    "sg:postcode":"31032",
    "sg:province":"GA",
    "wof:name":"Woodmen Of World Life",
    "wof:placetype":"venue"
},
  "geometry": {"coordinates":[-83.533928,33.009609],"type":"Point"}
}