{
  "type": "Feature",
  "properties": {
    "iso:country":"US",
    "sg:address":"1231 Green St SE",
    "sg:city":"Conyers",
    "sg:classifiers":[
        {
            "category":"Autos & Motor Vehicles",
            "subcategory":"Auto Supplies",
            "type":"Retail Goods"
        }
    ],
    "sg:phone":"+1 678 413 3569",
    "sg:postcode":"30012",
    "sg:province":"GA",
    "sg:tags":[
        "automobile",
        "parts"
    ],
    "wof:name":"White Brothers Auto Supply",
    "wof:placetype":"venue"
},
  "geometry": {"coordinates":[-84.011718,33.657329],"type":"Point"}
}