{
  "type": "Feature",
  "properties": {
    "iso:country":"US",
    "sg:address":"1568 Baytree Rd",
    "sg:city":"Valdosta",
    "sg:classifiers":[
        {
            "category":"Shopping",
            "subcategory":"Pharmacy",
            "type":"Retail Goods"
        }
    ],
    "sg:phone":"+1 229 249 0830",
    "sg:postcode":"31602",
    "sg:province":"GA",
    "wof:name":"Barnes Healthcare Svc",
    "wof:placetype":"venue"
},
  "geometry": {"coordinates":[-83.31496,30.84702],"type":"Point"}
}