{
  "type": "Feature",
  "properties": {
    "addr:full":"235 Ga Highway 49 S Byron GA 31008",
    "addr:housenumber":"235",
    "addr:postcode":"31008",
    "addr:street":"Ga Highway 49 S Byron",
    "iso:country":"US",
    "sg:address":"235 Ga Highway 49 S",
    "sg:city":"Byron",
    "sg:classifiers":[
        {
            "category":"Farming",
            "subcategory":"Farm",
            "type":"Manufacturing & Wholesale Goods"
        },
        {
            "category":"Wholesale",
            "subcategory":"Fruits & Vegetables",
            "type":"Manufacturing & Wholesale Goods"
        }
    ],
    "sg:phone":"+1 478 956 1822",
    "sg:postcode":"31008",
    "sg:province":"GA",
    "sg:tags":[
        "veggie"
    ],
    "wof:name":"Barbour Farms Fresh Peaches & Produce Llc",
    "wof:placetype":"venue"
},
  "geometry": {"coordinates":[-83.76109599999999,32.647274],"type":"Point"}
}