{
  "type": "Feature",
  "properties": {
    "iso:country":"US",
    "sg:address":"403 N Decatur St",
    "sg:city":"Dublin",
    "sg:classifiers":[
        {
            "category":"Insurance",
            "subcategory":"Insurance Agent",
            "type":"Services"
        }
    ],
    "sg:phone":"+1 478 272 0173",
    "sg:postcode":"31021",
    "sg:province":"GA",
    "wof:name":"Robert L Williams Jr Insurance",
    "wof:placetype":"venue"
},
  "geometry": {"coordinates":[-82.90215499999999,32.545302],"type":"Point"}
}