{
  "type": "Feature",
  "properties": {
    "addr:full":"4124 Carroll St SW Covington GA 30014",
    "addr:housenumber":"4124",
    "addr:postcode":"30014",
    "addr:street":"Carroll St Sw",
    "iso:country":"US",
    "sg:address":"4124 Carroll St SW",
    "sg:city":"Covington",
    "sg:classifiers":[
        {
            "category":"Government",
            "subcategory":"Office",
            "type":"Public Place"
        }
    ],
    "sg:phone":"+1 770 784 2482",
    "sg:postcode":"30014",
    "sg:province":"GA",
    "sg:tags":[
        "state",
        "security"
    ],
    "wof:name":"National Guard",
    "wof:placetype":"venue"
},
  "geometry": {"coordinates":[-83.870138,33.596094],"type":"Point"}
}