{
  "type": "Feature",
  "properties": {
    "iso:country":"US",
    "sg:address":"1820 Garraux Rd NW",
    "sg:city":"Atlanta",
    "sg:classifiers":[
        {
            "category":"Professional",
            "subcategory":"Management & Consulting",
            "type":"Services"
        }
    ],
    "sg:phone":"+1 404 233 6017",
    "sg:postcode":"30327",
    "sg:province":"GA",
    "wof:name":"Margaret Logan Carspecken",
    "wof:placetype":"venue"
},
  "geometry": {"coordinates":[-84.44529199999999,33.853791],"type":"Point"}
}