{
  "type": "Feature",
  "properties": {
    "iso:country":"US",
    "sg:address":"350 Limousin Ln",
    "sg:city":"Thomasville",
    "sg:classifiers":[
        {
            "category":"Utilities",
            "subcategory":"Water",
            "type":"Services"
        }
    ],
    "sg:phone":"+1 229 226 3807",
    "sg:postcode":"31792",
    "sg:province":"GA",
    "sg:tags":[
        "supply"
    ],
    "wof:name":"Thomas County Water System",
    "wof:placetype":"venue"
},
  "geometry": {"coordinates":[-83.978809,30.908109],"type":"Point"}
}