{
  "type": "Feature",
  "properties": {
    "iso:country":"US",
    "sg:address":"362 Auburn Ave NE",
    "sg:city":"Atlanta",
    "sg:classifiers":[
        {
            "category":"Restaurant",
            "type":"Food & Drink"
        }
    ],
    "sg:phone":"+1 404 522 5333",
    "sg:postcode":"30312",
    "sg:province":"GA",
    "wof:name":"Supreme Fish Delight",
    "wof:placetype":"venue"
},
  "geometry": {"coordinates":[-84.37599899999999,33.755402],"type":"Point"}
}