{
  "type": "Feature",
  "properties": {
    "addr:full":"421 S Westover Blvd Albany GA 31707",
    "addr:housenumber":"421",
    "addr:postcode":"31707",
    "addr:street":"S Westover Blvd",
    "iso:country":"US",
    "sg:address":"421 S Westover Blvd",
    "sg:city":"Albany",
    "sg:classifiers":[
        {
            "category":"Real Estate",
            "subcategory":"Real Estate Operator",
            "type":"Services"
        }
    ],
    "sg:phone":"+1 229 420 4074",
    "sg:postcode":"31707",
    "sg:province":"GA",
    "sg:tags":[
        "building",
        "apartment"
    ],
    "wof:name":"Woodpine Way Apartments",
    "wof:placetype":"venue"
},
  "geometry": {"coordinates":[-84.22148199999999,31.571489],"type":"Point"}
}