{
  "type": "Feature",
  "properties": {
    "addr:full":"354A Memorial Dr Hinesville GA 31313",
    "addr:housenumber":"354a",
    "addr:postcode":"31313",
    "addr:street":"Memorial Dr",
    "iso:country":"US",
    "sg:address":"354A Memorial Dr",
    "sg:city":"Hinesville",
    "sg:classifiers":[
        {
            "category":"Personal",
            "subcategory":"Barber",
            "type":"Services"
        }
    ],
    "sg:phone":"+1 912 877 3773",
    "sg:postcode":"31313",
    "sg:province":"GA",
    "wof:name":"Willie's Ebony & Ivory Barber Shop",
    "wof:placetype":"venue"
},
  "geometry": {"coordinates":[-81.600486,31.85204],"type":"Point"}
}