{
  "type": "Feature",
  "properties": {
    "iso:country":"US",
    "sg:address":"1103 Los Angeles Ave NE",
    "sg:city":"Atlanta",
    "sg:classifiers":[
        {
            "category":"Professional",
            "subcategory":"Computer Services",
            "type":"Services"
        }
    ],
    "sg:phone":"+1 404 724 0078",
    "sg:postcode":"30306",
    "sg:province":"GA",
    "sg:tags":[
        "consultant",
        "designer"
    ],
    "wof:name":"Websighted",
    "wof:placetype":"venue"
},
  "geometry": {"coordinates":[-84.35263500000001,33.783207],"type":"Point"}
}