{
  "type": "Feature",
  "properties": {
    "iso:country":"US",
    "sg:address":"4317 Castlewood Ct",
    "sg:city":"Columbus",
    "sg:classifiers":[
        {
            "category":"Professional",
            "subcategory":"Management & Consulting",
            "type":"Services"
        }
    ],
    "sg:phone":"+1 706 569 7731",
    "sg:postcode":"31907",
    "sg:province":"GA",
    "sg:tags":[
        "control",
        "loss",
        "risk",
        "safety",
        "total",
        "quality",
        "man"
    ],
    "wof:name":"Rema",
    "wof:placetype":"venue"
},
  "geometry": {"coordinates":[-84.92063400000001,32.505368],"type":"Point"}
}