{
  "type": "Feature",
  "properties": {
    "iso:country":"US",
    "sg:address":"6099 Brook Hollow Ln",
    "sg:city":"Lithonia",
    "sg:classifiers":[
        {
            "category":"Travel",
            "subcategory":"Travel Agent",
            "type":"Entertainment"
        }
    ],
    "sg:phone":"+1 770 323 1130",
    "sg:postcode":"30058",
    "sg:province":"GA",
    "sg:tags":[
        "agency",
        "bureau"
    ],
    "sg:website":"www.bookfriendlytravel.com",
    "wof:name":"Friendly Travel",
    "wof:placetype":"venue"
},
  "geometry": {"coordinates":[-84.14012099999999,33.713519],"type":"Point"}
}