{
  "type": "Feature",
  "properties": {
    "iso:country":"US",
    "sg:address":"1414 Woody Trl NE",
    "sg:city":"Atlanta",
    "sg:classifiers":[
        {
            "category":"Home & Garden",
            "subcategory":"Garden Supply",
            "type":"Retail Goods"
        }
    ],
    "sg:phone":"+1 404 664 5321",
    "sg:postcode":"30319",
    "sg:province":"GA",
    "sg:tags":[
        "landscaping",
        "equipment"
    ],
    "wof:name":"Stuart Bracey",
    "wof:placetype":"venue"
},
  "geometry": {"coordinates":[-84.331793,33.865856],"type":"Point"}
}