{
  "type": "Feature",
  "properties": {
    "addr:full":"2105 Roswell Rd Marietta GA 30062",
    "addr:housenumber":"2105",
    "addr:postcode":"30062",
    "addr:street":"Roswell Rd",
    "iso:country":"US",
    "sg:address":"2105 Roswell Rd",
    "sg:city":"Marietta",
    "sg:classifiers":[
        {
            "category":"Restaurant",
            "type":"Food & Drink"
        }
    ],
    "sg:menulink":"http://www.allmenus.com/ga/marietta/179917-chick-fil-a/menu/",
    "sg:phone":"+1 770 977 3355",
    "sg:postcode":"30062",
    "sg:province":"GA",
    "sg:tags":[
        "wrap",
        "soup",
        "american",
        "sandwich",
        "salad"
    ],
    "wof:name":"Chick-fil-A",
    "wof:placetype":"venue"
},
  "geometry": {"coordinates":[-84.491454,33.966138],"type":"Point"}
}