{
  "type": "Feature",
  "properties": {
    "iso:country":"US",
    "sg:address":"495 Lake Mirror Rd",
    "sg:city":"Atlanta",
    "sg:classifiers":[
        {
            "category":"Manufacturing",
            "subcategory":"Aerospace",
            "type":"Manufacturing & Wholesale Goods"
        }
    ],
    "sg:phone":"+1 404 767 3384",
    "sg:postcode":"30349",
    "sg:province":"GA",
    "sg:tags":[
        "avionics",
        "supply",
        "equipment",
        "aircraft",
        "part",
        "instrument"
    ],
    "wof:name":"Precision Heliparts",
    "wof:placetype":"venue"
},
  "geometry": {"coordinates":[-84.407898,33.628312],"type":"Point"}
}