{
  "type": "Feature",
  "properties": {
    "iso:country":"US",
    "sg:address":"795 Fulton St",
    "sg:city":"Macon",
    "sg:classifiers":[
        {
            "category":"Food & Beverages",
            "subcategory":"Candy",
            "type":"Retail Goods"
        }
    ],
    "sg:phone":"+1 478 788 9440",
    "sg:postcode":"31206",
    "sg:province":"GA",
    "sg:tags":[
        "popcorn",
        "supply"
    ],
    "sg:website":"www.colemanconcessions.com",
    "wof:name":"Coleman Concessions",
    "wof:placetype":"venue"
},
  "geometry": {"coordinates":[-83.649592,32.791658],"type":"Point"}
}