{
  "type": "Feature",
  "properties": {
    "iso:country":"US",
    "sg:address":"765 Rosehill Ln SW",
    "sg:city":"Lawrenceville",
    "sg:classifiers":[
        {
            "category":"Shopping",
            "subcategory":"Clothing, Apparel, & Fashions",
            "type":"Retail Goods"
        }
    ],
    "sg:phone":"+1 770 979 3549",
    "sg:postcode":"30044",
    "sg:province":"GA",
    "sg:tags":[
        "item",
        "boutique"
    ],
    "wof:name":"Sew Boutique",
    "wof:placetype":"venue"
},
  "geometry": {"coordinates":[-84.04576,33.899396],"type":"Point"}
}