{
  "type": "Feature",
  "properties": {
    "iso:country":"US",
    "sg:address":"219 S Perry St",
    "sg:city":"Lawrenceville",
    "sg:classifiers":[
        {
            "category":"Building & Trades",
            "subcategory":"Construction",
            "type":"Services"
        }
    ],
    "sg:phone":"+1 678 508 3539",
    "sg:postcode":"30045",
    "sg:province":"GA",
    "sg:tags":[
        "contractor"
    ],
    "wof:name":"Stuards Tile",
    "wof:placetype":"venue"
},
  "geometry": {"coordinates":[-83.989163,33.953459],"type":"Point"}
}