{
  "type": "Feature",
  "properties": {
    "addr:full":"4005 Ogeechee Rd Savannah GA 31405",
    "addr:housenumber":"4005",
    "addr:postcode":"31405",
    "addr:street":"Ogeechee Rd",
    "iso:country":"US",
    "sg:address":"4005 Ogeechee Rd",
    "sg:city":"Savannah",
    "sg:classifiers":[
        {
            "category":"Travel",
            "subcategory":"Hotels & Motels",
            "type":"Entertainment"
        }
    ],
    "sg:phone":"+1 912 234 6733",
    "sg:postcode":"31405",
    "sg:province":"GA",
    "wof:name":"Patek, Sanmukh",
    "wof:placetype":"venue"
},
  "geometry": {"coordinates":[-81.153486,32.050969],"type":"Point"}
}