{
  "type": "Feature",
  "properties": {
    "addr:full":"1900 Abbey Ct Alpharetta GA 30004",
    "addr:housenumber":"1900",
    "addr:postcode":"30004",
    "addr:street":"Abbey Ct",
    "iso:country":"US",
    "sg:address":"1900 Abbey Ct",
    "sg:city":"Alpharetta",
    "sg:classifiers":[
        {
            "category":"Professional",
            "subcategory":"Management & Consulting",
            "type":"Services"
        }
    ],
    "sg:phone":"+1 678 393 0200",
    "sg:postcode":"30004",
    "sg:province":"GA",
    "sg:tags":[
        "public",
        "relations"
    ],
    "wof:name":"Driver Promotions Inc",
    "wof:placetype":"venue"
},
  "geometry": {"coordinates":[-84.35512799999999,34.086903],"type":"Point"}
}