{
  "type": "Feature",
  "properties": {
    "iso:country":"US",
    "sg:address":"113 Jamestown Ct SW",
    "sg:city":"Lilburn",
    "sg:classifiers":[
        {
            "category":"Banks & Credit Unions",
            "subcategory":"Bank",
            "type":"Services"
        }
    ],
    "sg:phone":"+1 770 806 9945",
    "sg:postcode":"30047",
    "sg:province":"GA",
    "sg:tags":[
        "financing"
    ],
    "wof:name":"Everest Financial Inc",
    "wof:placetype":"venue"
},
  "geometry": {"coordinates":[-84.11679100000001,33.885986],"type":"Point"}
}