{
  "type": "Feature",
  "properties": {
    "addr:full":"630 Bridgewater Dr NW Atlanta GA 30328",
    "addr:housenumber":"630",
    "addr:postcode":"30328",
    "addr:street":"Bridgewater Dr Nw",
    "iso:country":"US",
    "sg:address":"630 Bridgewater Dr NW",
    "sg:city":"Atlanta",
    "sg:classifiers":[
        {
            "category":"Professional",
            "type":"Services"
        }
    ],
    "sg:phone":"+1 404 252 2521",
    "sg:postcode":"30328",
    "sg:province":"GA",
    "wof:name":"White Oak Creek - Ashley",
    "wof:placetype":"venue"
},
  "geometry": {"coordinates":[-84.407179,33.92945],"type":"Point"}
}