{
  "type": "Feature",
  "properties": {
    "iso:country":"US",
    "sg:address":"3239 Lynwood Dr NE",
    "sg:city":"Atlanta",
    "sg:classifiers":[
        {
            "category":"Professional",
            "type":"Services"
        }
    ],
    "sg:phone":"+1 404 256 5885",
    "sg:postcode":"30319",
    "sg:province":"GA",
    "wof:name":"Commamerica",
    "wof:placetype":"venue"
},
  "geometry": {"coordinates":[-84.343395,33.885765],"type":"Point"}
}