{
  "type": "Feature",
  "properties": {
    "iso:country":"US",
    "sg:address":"3299 Peach Orchard Rd",
    "sg:city":"Augusta",
    "sg:classifiers":[
        {
            "category":"Shopping",
            "subcategory":"Gifts & Souvenirs",
            "type":"Retail Goods"
        }
    ],
    "sg:phone":"+1 706 796 8794",
    "sg:postcode":"30906",
    "sg:province":"GA",
    "wof:name":"Creative Gifts",
    "wof:placetype":"venue"
},
  "geometry": {"coordinates":[-82.026293,33.404314],"type":"Point"}
}