{
  "type": "Feature",
  "properties": {
    "addr:full":"680 Engineering Dr Norcross GA 30092",
    "addr:postcode":"30092",
    "addr:street":"Dr",
    "iso:country":"US",
    "sg:address":"680 Engineering Dr",
    "sg:city":"Norcross",
    "sg:classifiers":[
        {
            "category":"Professional",
            "type":"Services"
        }
    ],
    "sg:phone":"+1 678 421 9694",
    "sg:postcode":"30092",
    "sg:province":"GA",
    "sg:tags":[
        "establishment"
    ],
    "wof:name":"Nano Lumens Inc",
    "wof:placetype":"venue"
},
  "geometry": {"coordinates":[-84.227345,33.969921],"type":"Point"}
}