{
  "type": "Feature",
  "properties": {
    "iso:country":"US",
    "sg:address":"920 S West St",
    "sg:city":"Bainbridge",
    "sg:classifiers":[
        {
            "category":"Government",
            "subcategory":"Office",
            "type":"Public Place"
        }
    ],
    "sg:phone":"+1 229 243 6400",
    "sg:postcode":"39819",
    "sg:province":"GA",
    "sg:tags":[
        "government-state"
    ],
    "wof:name":"Georgia State Government Georgia Pines Mh Mr S",
    "wof:placetype":"venue"
},
  "geometry": {"coordinates":[-84.576407,30.896932],"type":"Point"}
}