{
  "type": "Feature",
  "properties": {
    "iso:country":"US",
    "sg:address":"465 Redding Trce",
    "sg:city":"Marietta",
    "sg:classifiers":[
        {
            "category":"Real Estate",
            "subcategory":"Real Estate Agent",
            "type":"Services"
        }
    ],
    "sg:phone":"+1 770 973 5793",
    "sg:postcode":"30068",
    "sg:province":"GA",
    "wof:name":"Freeman Property MGT LLC",
    "wof:placetype":"venue"
},
  "geometry": {"coordinates":[-84.44792200000001,33.961459],"type":"Point"}
}