{
  "type": "Feature",
  "properties": {
    "iso:country":"US",
    "sg:address":"3490 Emperor Way",
    "sg:city":"Tucker",
    "sg:classifiers":[
        {
            "category":"Travel",
            "subcategory":"Travel Agent",
            "type":"Entertainment"
        }
    ],
    "sg:phone":"+1 770 493 8777",
    "sg:postcode":"30084",
    "sg:province":"GA",
    "sg:tags":[
        "operator",
        "tour"
    ],
    "wof:name":"Deluxe Tours Inc",
    "wof:placetype":"venue"
},
  "geometry": {"coordinates":[-84.244466,33.86345],"type":"Point"}
}