{
  "type": "Feature",
  "properties": {
    "addr:full":"3556 Trinity Dr Columbus GA 31907",
    "addr:housenumber":"3556",
    "addr:postcode":"31907",
    "addr:street":"Trinity Dr",
    "iso:country":"US",
    "sg:address":"3556 Trinity Dr",
    "sg:city":"Columbus",
    "sg:classifiers":[
        {
            "category":"Place Of Worship",
            "type":"Public Place"
        },
        {
            "category":"Education",
            "subcategory":"School",
            "type":"Public Place"
        }
    ],
    "sg:phone":"+1 706 561 8243",
    "sg:postcode":"31907",
    "sg:province":"GA",
    "sg:tags":[
        "private",
        "k-",
        "church"
    ],
    "sg:website":"http://www.st-teresa.com",
    "wof:name":"St Anne Pacelli Catholic School",
    "wof:placetype":"venue"
},
  "geometry": {"coordinates":[-84.934637,32.483871],"type":"Point"}
}