{
  "type": "Feature",
  "properties": {
    "iso:country":"US",
    "sg:address":"3804 Martingale Dr SE",
    "sg:city":"Conyers",
    "sg:classifiers":[
        {
            "category":"Building & Trades",
            "subcategory":"Landscaping Services",
            "type":"Services"
        }
    ],
    "sg:phone":"+1 770 922 1585",
    "sg:postcode":"30094",
    "sg:province":"GA",
    "sg:tags":[
        "lawn",
        "maintenance",
        "grounds"
    ],
    "wof:name":"Proscapes Lawn Maintenance",
    "wof:placetype":"venue"
},
  "geometry": {"coordinates":[-84.02796600000001,33.580971],"type":"Point"}
}