{
  "type": "Feature",
  "properties": {
    "iso:country":"US",
    "sg:address":"302 N Westberry St",
    "sg:city":"Sylvester",
    "sg:classifiers":[
        {
            "category":"Building & Trades",
            "subcategory":"Construction",
            "type":"Services"
        }
    ],
    "sg:phone":"+1 229 776 0601",
    "sg:postcode":"31791",
    "sg:province":"GA",
    "sg:tags":[
        "contractor"
    ],
    "wof:name":"Howell Construction Contractors Inc",
    "wof:placetype":"venue"
},
  "geometry": {"coordinates":[-83.833769,31.528981],"type":"Point"}
}