{
  "type": "Feature",
  "properties": {
    "iso:country":"US",
    "sg:address":"6850 Peachtree Dunwoody Rd NE",
    "sg:city":"Atlanta",
    "sg:classifiers":[
        {
            "category":"Real Estate",
            "subcategory":"Real Estate Services",
            "type":"Services"
        },
        {
            "category":"Real Estate",
            "subcategory":"Real Estate Agent",
            "type":"Services"
        }
    ],
    "sg:phone":"+1 352 870 7440",
    "sg:postcode":"30328",
    "sg:province":"GA",
    "sg:tags":[
        "management"
    ],
    "wof:name":"Gemps Financial Group",
    "wof:placetype":"venue"
},
  "geometry": {"coordinates":[-84.352546,33.942136],"type":"Point"}
}