{
  "type": "Feature",
  "properties": {
    "iso:country":"US",
    "sg:address":"2926 Professional Pkwy",
    "sg:city":"Augusta",
    "sg:classifiers":[
        {
            "category":"Health Services",
            "subcategory":"Doctor",
            "type":"Services"
        }
    ],
    "sg:phone":"+1 706 860 0575",
    "sg:postcode":"30907",
    "sg:province":"GA",
    "sg:tags":[
        "business"
    ],
    "wof:name":"Callan Richard S DMD",
    "wof:placetype":"venue"
},
  "geometry": {"coordinates":[-82.080586,33.498948],"type":"Point"}
}