{
  "type": "Feature",
  "properties": {
    "iso:country":"US",
    "sg:address":"2452 Brookhurst Dr",
    "sg:city":"Atlanta",
    "sg:classifiers":[
        {
            "category":"Organizations",
            "subcategory":"Religious Organization",
            "type":"Services"
        }
    ],
    "sg:phone":"+1 770 457 3696",
    "sg:postcode":"30338",
    "sg:province":"GA",
    "wof:name":"Faith Developments Inc",
    "wof:placetype":"venue"
},
  "geometry": {"coordinates":[-84.286203,33.927435],"type":"Point"}
}