{
  "type": "Feature",
  "properties": {
    "iso:country":"US",
    "sg:address":"4643 Buford Dr",
    "sg:city":"Atlanta",
    "sg:classifiers":[
        {
            "category":"Professional",
            "subcategory":"Lawyer & Legal Services",
            "type":"Services"
        }
    ],
    "sg:phone":"+1 770 455 4155",
    "sg:postcode":"30341",
    "sg:province":"GA",
    "sg:tags":[
        "attorney",
        "criminal",
        "law"
    ],
    "wof:name":"Jones Law Associates",
    "wof:placetype":"venue"
},
  "geometry": {"coordinates":[-84.29330899999999,33.876096],"type":"Point"}
}