{
  "type": "Feature",
  "properties": {
    "addr:full":"3079 Campbellton Rd SW Atlanta GA 30311",
    "addr:housenumber":"3079",
    "addr:postcode":"30311",
    "addr:street":"Campbellton Rd Sw",
    "iso:country":"US",
    "sg:address":"3079 Campbellton Rd SW",
    "sg:city":"Atlanta",
    "sg:classifiers":[
        {
            "category":"Health Services",
            "subcategory":"Chiropractor",
            "type":"Services"
        }
    ],
    "sg:phone":"+1 404 344 0838",
    "sg:postcode":"30311",
    "sg:province":"GA",
    "wof:name":"Chiropractic Atlanta",
    "wof:placetype":"venue"
},
  "geometry": {"coordinates":[-84.489098,33.693901],"type":"Point"}
}