{
  "type": "Feature",
  "properties": {
    "iso:country":"US",
    "sg:address":"4180 Buford Dr",
    "sg:city":"Buford",
    "sg:classifiers":[
        {
            "category":"Professional",
            "type":"Services"
        }
    ],
    "sg:phone":"+1 678 546 8566",
    "sg:postcode":"30518",
    "sg:province":"GA",
    "sg:tags":[
        "establishment"
    ],
    "wof:name":"S E Auto Group",
    "wof:placetype":"venue"
},
  "geometry": {"coordinates":[-84.012899,34.095782],"type":"Point"}
}