{
  "type": "Feature",
  "properties": {
    "addr:full":"2507 Shorter Ave Rome GA 30165",
    "addr:housenumber":"2507",
    "addr:postcode":"ga 30165",
    "addr:street":"Shorter Ave",
    "iso:country":"US",
    "sg:address":"2507 Shorter Ave",
    "sg:city":"Rome",
    "sg:classifiers":[
        {
            "category":"Retail",
            "subcategory":"Repair Shop",
            "type":"Services"
        },
        {
            "category":"Retail",
            "subcategory":"Auto Repair",
            "type":"Services"
        }
    ],
    "sg:phone":"+1 706 232 9864",
    "sg:postcode":"30165",
    "sg:province":"GA",
    "sg:tags":[
        "body",
        "automobile",
        "painting"
    ],
    "wof:name":"Nick's Auto Repair & Detailing",
    "wof:placetype":"venue"
},
  "geometry": {"coordinates":[-85.24053000000001,34.272107],"type":"Point"}
}