{
  "type": "Feature",
  "properties": {
    "addr:full":"925 Kim Ct Dublin GA 31021",
    "addr:housenumber":"925",
    "addr:postcode":"31021",
    "addr:street":"Kim Ct",
    "iso:country":"US",
    "sg:address":"925 Kim Ct",
    "sg:city":"Dublin",
    "sg:classifiers":[
        {
            "category":"Professional",
            "type":"Services"
        }
    ],
    "sg:phone":"+1 478 274 9192",
    "sg:postcode":"31021",
    "sg:province":"GA",
    "wof:name":"David Plunkett",
    "wof:placetype":"venue"
},
  "geometry": {"coordinates":[-82.906364,32.441406],"type":"Point"}
}