{
  "type": "Feature",
  "properties": {
    "iso:country":"US",
    "sg:address":"1476 State Rte 301",
    "sg:city":"Trenton",
    "sg:classifiers":[
        {
            "category":"Home & Garden",
            "subcategory":"Furniture",
            "type":"Retail Goods"
        }
    ],
    "sg:phone":"+1 706 657 6022",
    "sg:postcode":"30752",
    "sg:province":"GA",
    "sg:tags":[
        "builder",
        "custom"
    ],
    "wof:name":"Ridley Foster Rustic Furn",
    "wof:placetype":"venue"
},
  "geometry": {"coordinates":[-85.56221600000001,34.840009],"type":"Point"}
}