{
  "type": "Feature",
  "properties": {
    "iso:country":"US",
    "sg:address":"6211 Redan Rd",
    "sg:city":"Lithonia",
    "sg:classifiers":[
        {
            "category":"Utilities",
            "subcategory":"Water",
            "type":"Services"
        },
        {
            "category":"Retail",
            "subcategory":"Laundry & Dry Cleaning",
            "type":"Services"
        },
        {
            "category":"Building & Trades",
            "subcategory":"Cleaning & Sanitation",
            "type":"Services"
        }
    ],
    "sg:phone":"+1 770 482 8636",
    "sg:postcode":"30058",
    "sg:province":"GA",
    "sg:tags":[
        "cleaner",
        "pressure",
        "cleaning-exterior",
        "house"
    ],
    "wof:name":"AAA Pressure Washers",
    "wof:placetype":"venue"
},
  "geometry": {"coordinates":[-84.144859,33.747082],"type":"Point"}
}