{
  "type": "Feature",
  "properties": {
    "iso:country":"US",
    "sg:address":"101 Greenville St S",
    "sg:city":"Newnan",
    "sg:classifiers":[
        {
            "category":"Professional",
            "subcategory":"Business Services",
            "type":"Services"
        }
    ],
    "sg:phone":"+1 770 304 0909",
    "sg:postcode":"30263",
    "sg:province":"GA",
    "sg:tags":[
        "interior",
        "consultant",
        "design",
        "decorator"
    ],
    "wof:name":"C C S Interior Design",
    "wof:placetype":"venue"
},
  "geometry": {"coordinates":[-84.79866800000001,33.367568],"type":"Point"}
}