{
  "type": "Feature",
  "properties": {
    "addr:full":"632 McDonald St SE Atlanta GA 30312",
    "addr:housenumber":"632",
    "addr:postcode":"30312",
    "addr:street":"Mcdonald St Se",
    "iso:country":"US",
    "sg:address":"632 McDonald St SE",
    "sg:city":"Atlanta",
    "sg:classifiers":[
        {
            "category":"Restaurant",
            "type":"Food & Drink"
        }
    ],
    "sg:phone":"+1 404 230 8900",
    "sg:postcode":"30312",
    "sg:province":"GA",
    "sg:tags":[
        "chinese"
    ],
    "wof:name":"Dawa",
    "wof:placetype":"venue"
},
  "geometry": {"coordinates":[-84.366962,33.746226],"type":"Point"}
}