{
  "type": "Feature",
  "properties": {
    "addr:full":"4545 Granite Dr Tucker GA 30084",
    "addr:housenumber":"4545",
    "addr:postcode":"30084",
    "addr:street":"Granite Dr",
    "iso:country":"US",
    "sg:address":"4545 Granite Dr",
    "sg:city":"Tucker",
    "sg:classifiers":[
        {
            "category":"Manufacturing",
            "subcategory":"Glass & Minerals",
            "type":"Manufacturing & Wholesale Goods"
        }
    ],
    "sg:phone":"+1 770 939 4370",
    "sg:postcode":"30084",
    "sg:province":"GA",
    "sg:tags":[
        "tile"
    ],
    "wof:name":"Tile House Inc",
    "wof:placetype":"venue"
},
  "geometry": {"coordinates":[-84.19547300000001,33.845258],"type":"Point"}
}