{
  "type": "Feature",
  "properties": {
    "iso:country":"US",
    "sg:address":"7823 State Rte 120",
    "sg:city":"Buchanan",
    "sg:classifiers":[
        {
            "category":"Retail",
            "subcategory":"Auto Repair",
            "type":"Services"
        }
    ],
    "sg:phone":"+1 770 646 8672",
    "sg:postcode":"30113",
    "sg:province":"GA",
    "sg:tags":[
        "repairing",
        "automobile"
    ],
    "wof:name":"Westmoreland Automotive",
    "wof:placetype":"venue"
},
  "geometry": {"coordinates":[-85.070153,33.824677],"type":"Point"}
}