{
  "type": "Feature",
  "properties": {
    "iso:country":"US",
    "sg:address":"2111 Madison Hwy",
    "sg:city":"Valdosta",
    "sg:classifiers":[
        {
            "category":"Home & Garden",
            "subcategory":"Hardware",
            "type":"Retail Goods"
        },
        {
            "category":"Home & Garden",
            "subcategory":"Garden Supply",
            "type":"Retail Goods"
        }
    ],
    "sg:phone":"+1 229 242 8247",
    "sg:postcode":"31601",
    "sg:province":"GA",
    "sg:tags":[
        "repair",
        "saw"
    ],
    "wof:name":"Saw Goble Shop Inc",
    "wof:placetype":"venue"
},
  "geometry": {"coordinates":[-83.27160600000001,30.791136],"type":"Point"}
}