{
  "type": "Feature",
  "properties": {
    "iso:country":"US",
    "sg:address":"2009 Torch Hill Rd",
    "sg:city":"Columbus",
    "sg:classifiers":[
        {
            "category":"Organizations",
            "subcategory":"Religious Organization",
            "type":"Services"
        }
    ],
    "sg:phone":"+1 706 687 9908",
    "sg:postcode":"31903",
    "sg:province":"GA",
    "sg:tags":[
        "church"
    ],
    "wof:name":"Church Of Christ-Torch Hill Rd",
    "wof:placetype":"venue"
},
  "geometry": {"coordinates":[-84.94784799999999,32.41605],"type":"Point"}
}