{
  "type": "Feature",
  "properties": {
    "addr:full":"7960 Highway 98 W Commerce GA 30530",
    "addr:housenumber":"7960",
    "addr:postcode":"30530",
    "addr:street":"Highway 98 W",
    "iso:country":"US",
    "sg:address":"7960 Highway 98 W",
    "sg:city":"Commerce",
    "sg:classifiers":[
        {
            "category":"Structure",
            "subcategory":"Office Building",
            "type":"Public Place"
        }
    ],
    "sg:phone":"+1 706 789 3292",
    "sg:postcode":"30530",
    "sg:province":"GA",
    "sg:tags":[
        "park"
    ],
    "wof:name":"Busy Bee Properties",
    "wof:placetype":"venue"
},
  "geometry": {"coordinates":[-83.33672,34.182444],"type":"Point"}
}