{
  "type": "Feature",
  "properties": {
    "addr:full":"427 W Dame Ave Homerville GA 31634",
    "addr:housenumber":"427",
    "addr:postcode":"31634",
    "addr:street":"W Dame Ave",
    "iso:country":"US",
    "sg:address":"427 W Dame Ave",
    "sg:city":"Homerville",
    "sg:classifiers":[
        {
            "category":"Education",
            "subcategory":"School",
            "type":"Public Place"
        }
    ],
    "sg:phone":"+1 912 487 5959",
    "sg:postcode":"31634",
    "sg:province":"GA",
    "sg:website":"http://www.clinchcounty.com",
    "wof:name":"Homerville Head Start",
    "wof:placetype":"venue"
},
  "geometry": {"coordinates":[-82.751452,31.03573],"type":"Point"}
}