{
  "type": "Feature",
  "properties": {
    "addr:full":"1902 Mountain Brook Dr Dalton GA 30720",
    "addr:housenumber":"1902",
    "addr:postcode":"30720",
    "addr:street":"Mountain Brook Dr",
    "iso:country":"US",
    "sg:address":"1902 Mountain Brook Dr",
    "sg:city":"Dalton",
    "sg:classifiers":[
        {
            "category":"Utilities",
            "subcategory":"Mobile Phone",
            "type":"Services"
        },
        {
            "category":"Utilities",
            "subcategory":"Telephone",
            "type":"Services"
        },
        {
            "category":"Shopping",
            "subcategory":"Mobile Phones",
            "type":"Retail Goods"
        },
        {
            "category":"Manufacturing",
            "subcategory":"Electronics",
            "type":"Manufacturing & Wholesale Goods"
        },
        {
            "category":"Communications",
            "type":"Services"
        }
    ],
    "sg:phone":"+1 706 226 1015",
    "sg:postcode":"30720",
    "sg:province":"GA",
    "sg:tags":[
        "equipment",
        "telecommunications-equipment",
        "system",
        "cellular",
        "supply"
    ],
    "sg:website":"http://www.alltel.com",
    "wof:name":"Alltel Wireless",
    "wof:placetype":"venue"
},
  "geometry": {"coordinates":[-84.991753,34.73824],"type":"Point"}
}