{
  "type": "Feature",
  "properties": {
    "iso:country":"US",
    "sg:address":"4250 Industrial Center Ln",
    "sg:city":"Acworth",
    "sg:classifiers":[
        {
            "category":"Manufacturing",
            "subcategory":"Petroleum Products",
            "type":"Manufacturing & Wholesale Goods"
        }
    ],
    "sg:phone":"+1 770 874 4444",
    "sg:postcode":"30101",
    "sg:province":"GA",
    "wof:name":"Cherokee Petroleum",
    "wof:placetype":"venue"
},
  "geometry": {"coordinates":[-84.647797,34.058848],"type":"Point"}
}