{
  "type": "Feature",
  "properties": {
    "addr:full":"450 Capitol Ave SW Atlanta GA 30315",
    "addr:housenumber":"450",
    "addr:postcode":"30315",
    "addr:street":"Capitol Ave Sw",
    "iso:country":"US",
    "sg:address":"450 Capitol Ave SW",
    "sg:city":"Atlanta",
    "sg:classifiers":[
        {
            "category":"Restaurant",
            "type":"Food & Drink"
        }
    ],
    "sg:phone":"+1 404 591 2000",
    "sg:postcode":"30315",
    "sg:province":"GA",
    "sg:tags":[
        "new",
        "american"
    ],
    "wof:name":"Rockfish Grille",
    "wof:placetype":"venue"
},
  "geometry": {"coordinates":[-84.388047,33.724479],"type":"Point"}
}