{
  "type": "Feature",
  "properties": {
    "iso:country":"US",
    "sg:address":"1545 Peacthree St Ste 225",
    "sg:city":"Atlanta",
    "sg:classifiers":[
        {
            "category":"Arts & Performance",
            "subcategory":"Art Gallery",
            "type":"Entertainment"
        }
    ],
    "sg:postcode":"30309",
    "sg:province":"GA",
    "sg:website":"www.scad.edu/exhibitions/galleries/",
    "wof:name":"Dewberry Gallery",
    "wof:placetype":"venue"
},
  "geometry": {"coordinates":[-84.388711,33.797178],"type":"Point"}
}