{
  "type": "Feature",
  "properties": {
    "addr:full":"5455 Meridian Marks Rd NE Atlanta GA 30342",
    "addr:housenumber":"5455",
    "addr:postcode":"30342",
    "addr:street":"Meridian Marks Rd Ne",
    "iso:country":"US",
    "sg:address":"5455 Meridian Marks Rd NE",
    "sg:city":"Atlanta",
    "sg:classifiers":[
        {
            "category":"Health Services",
            "subcategory":"Dentist",
            "type":"Services"
        }
    ],
    "sg:phone":"+1 404 785 2072",
    "sg:postcode":"30342",
    "sg:province":"GA",
    "sg:tags":[
        "pediatric"
    ],
    "wof:name":"Childrens Healthcare of Atlanta",
    "wof:placetype":"venue"
},
  "geometry": {"coordinates":[-84.35481900000001,33.907599],"type":"Point"}
}