{
  "type": "Feature",
  "properties": {
    "iso:country":"US",
    "sg:address":"4985 Lakebrooke Run",
    "sg:city":"Stone Mountain",
    "sg:classifiers":[
        {
            "category":"Professional",
            "subcategory":"Lawyer & Legal Services",
            "type":"Services"
        }
    ],
    "sg:phone":"+1 770 413 9089",
    "sg:postcode":"30087",
    "sg:province":"GA",
    "wof:name":"Imm Assistance",
    "wof:placetype":"venue"
},
  "geometry": {"coordinates":[-84.114985,33.828744],"type":"Point"}
}