{
  "type": "Feature",
  "properties": {
    "iso:country":"US",
    "sg:address":"8022 Cone St",
    "sg:city":"Douglasville",
    "sg:classifiers":[
        {
            "category":"Building & Trades",
            "subcategory":"Construction",
            "type":"Services"
        }
    ],
    "sg:phone":"+1 770 942 3978",
    "sg:postcode":"30134",
    "sg:province":"GA",
    "sg:tags":[
        "concrete",
        "contractor"
    ],
    "wof:name":"Saffo Concrete Business",
    "wof:placetype":"venue"
},
  "geometry": {"coordinates":[-84.745688,33.762365],"type":"Point"}
}