{
  "type": "Feature",
  "properties": {
    "addr:full":"306 Cagle Dr SE Fairmount GA 30139",
    "addr:housenumber":"306",
    "addr:postcode":"30139",
    "addr:street":"Cagle Dr Se",
    "iso:country":"US",
    "sg:address":"306 Cagle Dr SE",
    "sg:city":"Fairmount",
    "sg:classifiers":[
        {
            "category":"Organizations",
            "subcategory":"Religious Organization",
            "type":"Services"
        }
    ],
    "sg:phone":"+1 706 337 4627",
    "sg:postcode":"30139",
    "sg:province":"GA",
    "wof:name":"Sword Truth Ministries Intl",
    "wof:placetype":"venue"
},
  "geometry": {"coordinates":[-84.694093,34.460724],"type":"Point"}
}