{
  "type": "Feature",
  "properties": {
    "addr:full":"952 Mayson Turner Rd NW Atlanta GA 30314",
    "addr:housenumber":"952",
    "addr:postcode":"30314",
    "addr:street":"Mayson Turner Rd Nw",
    "iso:country":"US",
    "sg:address":"952 Mayson Turner Rd NW",
    "sg:city":"Atlanta",
    "sg:classifiers":[
        {
            "category":"Personal",
            "subcategory":"Beauty Salon",
            "type":"Services"
        }
    ],
    "sg:phone":"+1 404 688 0827",
    "sg:postcode":"30314",
    "sg:province":"GA",
    "sg:tags":[
        "shop"
    ],
    "wof:name":"Shirleys Beauty Salon",
    "wof:placetype":"venue"
},
  "geometry": {"coordinates":[-84.418611,33.759594],"type":"Point"}
}