{
  "type": "Feature",
  "properties": {
    "iso:country":"US",
    "sg:address":"5207 Anson Ave",
    "sg:city":"Eastman",
    "sg:classifiers":[
        {
            "category":"Autos & Motor Vehicles",
            "subcategory":"Auto Supplies",
            "type":"Retail Goods"
        }
    ],
    "sg:phone":"+1 478 374 3408",
    "sg:postcode":"31023",
    "sg:province":"GA",
    "sg:tags":[
        "tire"
    ],
    "wof:name":"Bubbas Tire Ctr",
    "wof:placetype":"venue"
},
  "geometry": {"coordinates":[-83.17630699999999,32.199625],"type":"Point"}
}