{
  "type": "Feature",
  "properties": {
    "addr:full":"3122 Corral Trl Gainesville GA 30506",
    "addr:housenumber":"3122",
    "addr:postcode":"30506",
    "addr:street":"Corral Trl",
    "iso:country":"US",
    "sg:address":"3122 Corral Trl",
    "sg:city":"Gainesville",
    "sg:classifiers":[
        {
            "category":"Retail",
            "subcategory":"Repair Shop",
            "type":"Services"
        }
    ],
    "sg:phone":"+1 770 536 6879",
    "sg:postcode":"30506",
    "sg:province":"GA",
    "sg:tags":[
        "electrical"
    ],
    "wof:name":"All Day Appliance",
    "wof:placetype":"venue"
},
  "geometry": {"coordinates":[-83.910444,34.33484],"type":"Point"}
}