{
  "type": "Feature",
  "properties": {
    "addr:full":"805 Marathon Pkwy Lawrenceville GA 30044",
    "addr:housenumber":"805",
    "addr:postcode":"30044",
    "addr:street":"Marathon Pkwy",
    "iso:country":"US",
    "sg:address":"805 Marathon Pkwy",
    "sg:city":"Lawrenceville",
    "sg:classifiers":[
        {
            "category":"Utilities",
            "subcategory":"Telephone",
            "type":"Services"
        }
    ],
    "sg:phone":"+1 678 377 4747",
    "sg:postcode":"30044",
    "sg:province":"GA",
    "sg:tags":[
        "company"
    ],
    "wof:name":"Electronic Directory Assist",
    "wof:placetype":"venue"
},
  "geometry": {"coordinates":[-84.053057,33.956578],"type":"Point"}
}