{
  "type": "Feature",
  "properties": {
    "addr:full":"119 N 2nd St Cochran GA 31014",
    "addr:housenumber":"119",
    "addr:postcode":"31014",
    "addr:street":"N 2Nd St",
    "iso:country":"US",
    "sg:address":"119 N 2nd St",
    "sg:city":"Cochran",
    "sg:classifiers":[
        {
            "category":"Internet Cafe",
            "subcategory":"None",
            "type":"Food & Drink"
        },
        {
            "category":"Communications",
            "subcategory":"Television Station",
            "type":"Services"
        },
        {
            "category":"Utilities",
            "subcategory":"Telephone",
            "type":"Services"
        },
        {
            "category":"Professional",
            "subcategory":"Computer Services",
            "type":"Services"
        }
    ],
    "sg:phone":"+1 478 271 4001",
    "sg:postcode":"31014",
    "sg:province":"GA",
    "sg:tags":[
        "repair",
        "product",
        "cable",
        "satellite",
        "system",
        "equipment",
        "equipment-service"
    ],
    "sg:website":"http://www.comsouth.net",
    "wof:name":"Comsouth Telecommunications",
    "wof:placetype":"venue"
},
  "geometry": {"coordinates":[-83.35613499999999,32.387735],"type":"Point"}
}