{
  "type": "Feature",
  "properties": {
    "addr:full":"8 Brookhaven Dr NE Atlanta GA 30319",
    "addr:housenumber":"8",
    "addr:postcode":"30319",
    "addr:street":"Brookhaven Dr Ne",
    "iso:country":"US",
    "sg:address":"8 Brookhaven Dr NE",
    "sg:city":"Atlanta",
    "sg:classifiers":[
        {
            "category":"Professional",
            "type":"Services"
        }
    ],
    "sg:phone":"+1 404 231 4477",
    "sg:postcode":"30319",
    "sg:province":"GA",
    "wof:name":"Linda B Diedrich",
    "wof:placetype":"venue"
},
  "geometry": {"coordinates":[-84.34526700000001,33.858125],"type":"Point"}
}