{
  "type": "Feature",
  "properties": {
    "addr:full":"2372 S Stone Mtn Lithonia Rd Lithonia GA 30058",
    "addr:housenumber":"2372",
    "addr:postcode":"30058",
    "addr:street":"S Stone Mtn Lithonia Rd",
    "iso:country":"US",
    "sg:address":"2372 S Stone Mtn Lithonia Rd",
    "sg:city":"Lithonia",
    "sg:classifiers":[
        {
            "category":"Manufacturing",
            "subcategory":"Printing",
            "type":"Manufacturing & Wholesale Goods"
        }
    ],
    "sg:phone":"+1 678 526 8045",
    "sg:postcode":"30058",
    "sg:province":"GA",
    "sg:tags":[
        "printer"
    ],
    "wof:name":"Classic Images",
    "wof:placetype":"venue"
},
  "geometry": {"coordinates":[-84.1157,33.735555],"type":"Point"}
}