{
  "type": "Feature",
  "properties": {
    "addr:full":"3358 Wrightsboro Rd Augusta GA 30909",
    "addr:housenumber":"3358",
    "addr:postcode":"30909",
    "addr:street":"Wrightsboro Rd",
    "iso:country":"US",
    "sg:address":"3358 Wrightsboro Rd",
    "sg:city":"Augusta",
    "sg:classifiers":[
        {
            "category":"Home & Garden",
            "subcategory":"Furniture",
            "type":"Retail Goods"
        }
    ],
    "sg:phone":"+1 706 729 9424",
    "sg:postcode":"30909",
    "sg:province":"GA",
    "wof:name":"Furniture Warehouse",
    "wof:placetype":"venue"
},
  "geometry": {"coordinates":[-82.07478399999999,33.468259],"type":"Point"}
}