{
  "type": "Feature",
  "properties": {
    "addr:full":"4372 Oglethorpe Hwy Hinesville GA 31313",
    "addr:housenumber":"4372",
    "addr:postcode":"31313",
    "addr:street":"Oglethorpe Hwy",
    "iso:country":"US",
    "sg:address":"4372 Oglethorpe Hwy",
    "sg:city":"Hinesville",
    "sg:classifiers":[
        {
            "category":"Organizations",
            "subcategory":"Religious Organization",
            "type":"Services"
        }
    ],
    "sg:phone":"+1 912 877 6080",
    "sg:postcode":"31313",
    "sg:province":"GA",
    "sg:tags":[
        "church"
    ],
    "wof:name":"Fellowship Of Love Outreach",
    "wof:placetype":"venue"
},
  "geometry": {"coordinates":[-81.562044,31.858393],"type":"Point"}
}