{
  "type": "Feature",
  "properties": {
    "addr:full":"447 N Clarendon Ave # A Scottdale GA 30079",
    "addr:housenumber":"447",
    "addr:postcode":"30079",
    "addr:street":"N Clarendon Ave # A",
    "iso:country":"US",
    "sg:address":"447 N Clarendon Ave # A",
    "sg:city":"Scottdale",
    "sg:classifiers":[
        {
            "category":"Retail",
            "subcategory":"Auto Repair",
            "type":"Services"
        }
    ],
    "sg:phone":"+1 404 299 0841",
    "sg:postcode":"30079",
    "sg:province":"GA",
    "sg:tags":[
        "body",
        "shop"
    ],
    "wof:name":"Spivey's Body Shop",
    "wof:placetype":"venue"
},
  "geometry": {"coordinates":[-84.264099,33.7883],"type":"Point"}
}