{
  "type": "Feature",
  "properties": {
    "addr:full":"110 E Andrews Dr NW Atlanta GA 30305",
    "addr:housenumber":"110",
    "addr:postcode":"30305",
    "addr:street":"E Andrews Dr Nw",
    "iso:country":"US",
    "sg:address":"110 E Andrews Dr NW",
    "sg:city":"Atlanta",
    "sg:classifiers":[
        {
            "category":"Shopping",
            "subcategory":"Jewelry",
            "type":"Retail Goods"
        }
    ],
    "sg:phone":"+1 404 233 6991",
    "sg:postcode":"30305",
    "sg:province":"GA",
    "sg:tags":[
        "precious",
        "semi-precious",
        "stone",
        "jeweler"
    ],
    "wof:name":"Litchfield & Company",
    "wof:placetype":"venue"
},
  "geometry": {"coordinates":[-84.382715,33.843431],"type":"Point"}
}