{
  "type": "Feature",
  "properties": {
    "addr:full":"835 Oglethorpe Ave SW Atlanta GA 30310",
    "addr:housenumber":"835",
    "addr:postcode":"30310",
    "addr:street":"Oglethorpe Ave Sw",
    "iso:country":"US",
    "sg:address":"835 Oglethorpe Ave SW",
    "sg:city":"Atlanta",
    "sg:classifiers":[
        {
            "category":"Personal",
            "type":"Services"
        }
    ],
    "sg:phone":"+1 404 758 6523",
    "sg:postcode":"30310",
    "sg:province":"GA",
    "sg:tags":[
        "miscellaneous"
    ],
    "wof:name":"Taalebus Institute For Lrng",
    "wof:placetype":"venue"
},
  "geometry": {"coordinates":[-84.41561900000001,33.735907],"type":"Point"}
}