{
  "type": "Feature",
  "properties": {
    "addr:full":"5012 Amis Ln Powder Springs GA 30127",
    "addr:postcode":"5012;30127",
    "addr:street":"Amis Ln",
    "iso:country":"US",
    "sg:address":"5012 Amis Ln",
    "sg:city":"Powder Springs",
    "sg:classifiers":[
        {
            "category":"Retail",
            "subcategory":"Repair Shop",
            "type":"Services"
        }
    ],
    "sg:phone":"+1 770 943 2630",
    "sg:postcode":"30127",
    "sg:province":"GA",
    "wof:name":"Allred Maintenance Service",
    "wof:placetype":"venue"
},
  "geometry": {"coordinates":[-84.69990199999999,33.851372],"type":"Point"}
}