{
  "type": "Feature",
  "properties": {
    "iso:country":"US",
    "sg:address":"3335 Endicott Ln",
    "sg:city":"Lithonia",
    "sg:classifiers":[
        {
            "category":"Freight",
            "type":"Transportation"
        }
    ],
    "sg:phone":"+1 770 593 1944",
    "sg:postcode":"30038",
    "sg:province":"GA",
    "sg:tags":[
        "driver",
        "leasing",
        "truck",
        "trucking"
    ],
    "wof:name":"D & D Transportation",
    "wof:placetype":"venue"
},
  "geometry": {"coordinates":[-84.187167,33.685049],"type":"Point"}
}