{
  "type": "Feature",
  "properties": {
    "addr:full":"23 Lick Skillet Rd Hamilton GA 31808",
    "addr:housenumber":"23",
    "addr:postcode":"31808",
    "addr:street":"Skillet Rd",
    "iso:country":"US",
    "sg:address":"23 Lick Skillet Rd",
    "sg:city":"Hamilton",
    "sg:classifiers":[
        {
            "category":"Building & Trades",
            "subcategory":"Construction",
            "type":"Services"
        }
    ],
    "sg:phone":"+1 706 327 6711",
    "sg:postcode":"31808",
    "sg:province":"GA",
    "sg:tags":[
        "maker",
        "cabinet"
    ],
    "wof:name":"Berndt Co",
    "wof:placetype":"venue"
},
  "geometry": {"coordinates":[-85.058013,32.677749],"type":"Point"}
}