{
  "type": "Feature",
  "properties": {
    "addr:full":"5696 Peachtree Pkwy Ste A Norcross GA 30092",
    "addr:housenumber":"5696",
    "addr:postcode":"30092",
    "addr:street":"Peachtree Pkwy Ste A",
    "iso:country":"US",
    "sg:address":"5696 Peachtree Pkwy Ste A",
    "sg:city":"Norcross",
    "sg:classifiers":[
        {
            "category":"Professional",
            "subcategory":"Printing & Photocopies",
            "type":"Services"
        }
    ],
    "sg:phone":"+1 678 992 2630",
    "sg:postcode":"30092",
    "sg:province":"GA",
    "sg:tags":[
        "lithographer"
    ],
    "wof:name":"Print Logics",
    "wof:placetype":"venue"
},
  "geometry": {"coordinates":[-84.225644,33.962691],"type":"Point"}
}