{
  "type": "Feature",
  "properties": {
    "addr:full":"384 Kersey Rd Elko GA 31025",
    "addr:housenumber":"384",
    "addr:postcode":"31025",
    "addr:street":"Kersey Rd",
    "iso:country":"US",
    "sg:address":"384 Kersey Rd",
    "sg:city":"Elko",
    "sg:classifiers":[
        {
            "category":"Professional",
            "type":"Services"
        }
    ],
    "sg:phone":"+1 478 988 8294",
    "sg:postcode":"31025",
    "sg:province":"GA",
    "wof:name":"Pete M Miller",
    "wof:placetype":"venue"
},
  "geometry": {"coordinates":[-83.837295,32.337715],"type":"Point"}
}