{
  "type": "Feature",
  "properties": {
    "addr:full":"3981 Piedmont Mountain Rd Clarkesville GA 30523",
    "addr:housenumber":"3981",
    "addr:postcode":"30523",
    "addr:street":"Piedmont Mountain Rd",
    "iso:country":"US",
    "sg:address":"3981 Piedmont Mountain Rd",
    "sg:city":"Clarkesville",
    "sg:classifiers":[
        {
            "category":"Manufacturing",
            "subcategory":"Buildings",
            "type":"Manufacturing & Wholesale Goods"
        },
        {
            "category":"Building & Trades",
            "subcategory":"Construction",
            "type":"Services"
        }
    ],
    "sg:phone":"+1 706 947 3077",
    "sg:postcode":"30523",
    "sg:province":"GA",
    "sg:tags":[
        "home",
        "builder",
        "contractor"
    ],
    "wof:name":"Reed Realty & Construction",
    "wof:placetype":"venue"
},
  "geometry": {"coordinates":[-83.604142,34.718013],"type":"Point"}
}