{
  "type": "Feature",
  "properties": {
    "addr:full":"6045 N Henry Blvd Stockbridge GA 30281",
    "addr:housenumber":"6045",
    "addr:postcode":"30281",
    "addr:street":"N Henry Blvd",
    "iso:country":"US",
    "sg:address":"6045 N Henry Blvd",
    "sg:city":"Stockbridge",
    "sg:classifiers":[
        {
            "category":"Building & Trades",
            "subcategory":"Plumbing",
            "type":"Services"
        }
    ],
    "sg:phone":"+1 770 507 1500",
    "sg:postcode":"30281",
    "sg:province":"GA",
    "sg:tags":[
        "conditioning",
        "air",
        "system",
        "contractor"
    ],
    "wof:name":"Bob Maddox Heating & Air",
    "wof:placetype":"venue"
},
  "geometry": {"coordinates":[-84.25997700000001,33.557241],"type":"Point"}
}