{
  "type": "Feature",
  "properties": {
    "addr:full":"11685 Alpharetta Hwy Ste 300 Roswell GA 30076",
    "addr:housenumber":"11685",
    "addr:postcode":"30076",
    "addr:street":"Alpharetta Hwy Ste 300",
    "iso:country":"US",
    "sg:address":"11685 Alpharetta Hwy Ste 300",
    "sg:city":"Roswell",
    "sg:classifiers":[
        {
            "category":"Health Services",
            "subcategory":"Doctor",
            "type":"Services"
        }
    ],
    "sg:phone":"+1 770 475 3361",
    "sg:postcode":"30076",
    "sg:province":"GA",
    "sg:tags":[
        "throat",
        "ear",
        "nose"
    ],
    "wof:name":"Northside Ent",
    "wof:placetype":"venue"
},
  "geometry": {"coordinates":[-84.321602,34.064301],"type":"Point"}
}