{
  "type": "Feature",
  "properties": {
    "addr:full":"5065 Standifer Rd Cohutta GA 30710",
    "addr:housenumber":"5065",
    "addr:postcode":"30710",
    "addr:street":"Standifer Rd",
    "iso:country":"US",
    "sg:address":"5065 Standifer Rd",
    "sg:city":"Cohutta",
    "sg:classifiers":[
        {
            "category":"Professional",
            "type":"Services"
        }
    ],
    "sg:phone":"+1 706 694 3474",
    "sg:postcode":"30710",
    "sg:province":"GA",
    "wof:name":"Rhonda J Howell",
    "wof:placetype":"venue"
},
  "geometry": {"coordinates":[-84.97476899999999,34.950887],"type":"Point"}
}