{
  "type": "Feature",
  "properties": {
    "iso:country":"US",
    "sg:address":"1500 12th St",
    "sg:city":"Columbus",
    "sg:classifiers":[
        {
            "category":"Real Estate",
            "subcategory":"Real Estate Operator",
            "type":"Services"
        }
    ],
    "sg:phone":"+1 706 323 5699",
    "sg:postcode":"31906",
    "sg:province":"GA",
    "sg:tags":[
        "apartment"
    ],
    "wof:name":"Dinglewood Court",
    "wof:placetype":"venue"
},
  "geometry": {"coordinates":[-84.968993,32.468696],"type":"Point"}
}