{
  "type": "Feature",
  "properties": {
    "iso:country":"US",
    "sg:address":"734 Calhoun Rd",
    "sg:city":"Dahlonega",
    "sg:classifiers":[
        {
            "category":"Professional",
            "type":"Services"
        }
    ],
    "sg:phone":"+1 706 864 6422",
    "sg:postcode":"30533",
    "sg:province":"GA",
    "sg:tags":[
        "art",
        "fine",
        "artist"
    ],
    "wof:name":"Crannell Studio",
    "wof:placetype":"venue"
},
  "geometry": {"coordinates":[-83.99116600000001,34.51257],"type":"Point"}
}