{
  "type": "Feature",
  "properties": {
    "iso:country":"US",
    "sg:address":"434 S Belair Rd",
    "sg:city":"Martinez",
    "sg:classifiers":[
        {
            "category":"Travel",
            "subcategory":"Hotels & Motels",
            "type":"Entertainment"
        }
    ],
    "sg:phone":"+1 706 860 8173",
    "sg:postcode":"30907",
    "sg:province":"GA",
    "wof:name":"Georgia Inn Hotel",
    "wof:placetype":"venue"
},
  "geometry": {"coordinates":[-82.133077,33.485527],"type":"Point"}
}