{
  "type": "Feature",
  "properties": {
    "iso:country":"US",
    "sg:address":"1328 13th St",
    "sg:city":"Columbus",
    "sg:classifiers":[
        {
            "category":"Shopping",
            "subcategory":"Crafts & Fabrics",
            "type":"Retail Goods"
        }
    ],
    "sg:phone":"+1 706 321 1898",
    "sg:postcode":"31906",
    "sg:province":"GA",
    "sg:tags":[
        "material",
        "needlework"
    ],
    "wof:name":"Threaded Needle",
    "wof:placetype":"venue"
},
  "geometry": {"coordinates":[-84.973311,32.470518],"type":"Point"}
}