{
  "type": "Feature",
  "properties": {
    "iso:country":"US",
    "sg:address":"6520 Yacht Club Rd",
    "sg:city":"Flowery Branch",
    "sg:classifiers":[
        {
            "category":"Professional",
            "type":"Services"
        }
    ],
    "sg:phone":"+1 770 965 2131",
    "sg:postcode":"30542",
    "sg:province":"GA",
    "wof:name":"Auntee Bellums",
    "wof:placetype":"venue"
},
  "geometry": {"coordinates":[-83.973845,34.171103],"type":"Point"}
}