{
  "type": "Feature",
  "properties": {
    "iso:country":"US",
    "sg:address":"139 Etowah Industrial Ct",
    "sg:city":"Canton",
    "sg:classifiers":[
        {
            "category":"Manufacturing",
            "subcategory":"Metals",
            "type":"Manufacturing & Wholesale Goods"
        }
    ],
    "sg:phone":"+1 770 479 2227",
    "sg:postcode":"30114",
    "sg:province":"GA",
    "sg:tags":[
        "spring"
    ],
    "sg:website":"www.piolaxusa.com",
    "wof:name":"Piolax Corp",
    "wof:placetype":"venue"
},
  "geometry": {"coordinates":[-84.47329999999999,34.244454],"type":"Point"}
}