{
  "type": "Feature",
  "properties": {
    "addr:full":"504 5th Ave Albany GA 31701",
    "addr:housenumber":"504",
    "addr:postcode":"31701",
    "addr:street":"5Th Ave",
    "iso:country":"US",
    "sg:address":"504 5th Ave",
    "sg:city":"Albany",
    "sg:classifiers":[
        {
            "category":"Professional",
            "type":"Services"
        }
    ],
    "sg:phone":"+1 229 435 4743",
    "sg:postcode":"31701",
    "sg:province":"GA",
    "wof:name":"Anna Crimmins",
    "wof:placetype":"venue"
},
  "geometry": {"coordinates":[-84.159942,31.592874],"type":"Point"}
}