{
  "type": "Feature",
  "properties": {
    "addr:full":"2475 Jefferson Rd Ste 500 Athens GA 30607",
    "addr:housenumber":"2475",
    "addr:postcode":"30607",
    "addr:street":"Jefferson Rd Ste 500",
    "iso:country":"US",
    "sg:address":"2475 Jefferson Rd Ste 500",
    "sg:city":"Athens",
    "sg:classifiers":[
        {
            "category":"Restaurant",
            "type":"Food & Drink"
        }
    ],
    "sg:phone":"+1 706 353 3399",
    "sg:postcode":"30607",
    "sg:province":"GA",
    "sg:tags":[
        "asian",
        "chinese",
        "pan"
    ],
    "sg:website":"http://www.chinawokky.com",
    "wof:name":"China Wok",
    "wof:placetype":"venue"
},
  "geometry": {"coordinates":[-83.412903,33.972667],"type":"Point"}
}