{
  "type": "Feature",
  "properties": {
    "iso:country":"US",
    "sg:address":"6048 Ga Highway 21 S",
    "sg:city":"Rincon",
    "sg:classifiers":[
        {
            "category":"Personal",
            "subcategory":"Beauty Salon",
            "type":"Services"
        }
    ],
    "sg:phone":"+1 912 826 1606",
    "sg:postcode":"31326",
    "sg:province":"GA",
    "wof:name":"Ladies & Shears",
    "wof:placetype":"venue"
},
  "geometry": {"coordinates":[-81.215057,32.253274],"type":"Point"}
}