{
  "type": "Feature",
  "properties": {
    "iso:country":"US",
    "sg:address":"2040 E 10th St",
    "sg:city":"Woodbine",
    "sg:classifiers":[
        {
            "category":"Restaurant",
            "type":"Food & Drink"
        }
    ],
    "sg:phone":"+1 912 674 4205",
    "sg:postcode":"31569",
    "sg:province":"GA",
    "sg:tags":[
        "grill",
        "bar"
    ],
    "wof:name":"Sunshine Travel Plaza",
    "wof:placetype":"venue"
},
  "geometry": {"coordinates":[-81.71502700000001,30.96055],"type":"Point"}
}