{
  "type": "Feature",
  "properties": {
    "addr:full":"3999 Austell Rd Austell GA 30106",
    "addr:housenumber":"3999",
    "addr:postcode":"30106",
    "addr:street":"Austell Rd",
    "iso:country":"US",
    "sg:address":"3999 Austell Rd",
    "sg:city":"Austell",
    "sg:classifiers":[
        {
            "category":"Shopping",
            "subcategory":"Books",
            "type":"Retail Goods"
        }
    ],
    "sg:phone":"+1 770 948 6130",
    "sg:postcode":"30106",
    "sg:province":"GA",
    "sg:tags":[
        "bookstore"
    ],
    "wof:name":"Family Christian Stores",
    "wof:placetype":"venue"
},
  "geometry": {"coordinates":[-84.601501,33.8564],"type":"Point"}
}