{
  "type": "Feature",
  "properties": {
    "addr:full":"895 Glynn St N Fayetteville GA 30214",
    "addr:housenumber":"895",
    "addr:postcode":"30214",
    "addr:street":"Glynn St N",
    "iso:country":"US",
    "sg:address":"895 Glynn St N",
    "sg:city":"Fayetteville",
    "sg:classifiers":[
        {
            "category":"Personal",
            "subcategory":"Beauty Salon",
            "type":"Services"
        }
    ],
    "sg:phone":"+1 770 716 3300",
    "sg:postcode":"30214",
    "sg:province":"GA",
    "wof:name":"Raspberry",
    "wof:placetype":"venue"
},
  "geometry": {"coordinates":[-84.448053,33.466231],"type":"Point"}
}