{
  "type": "Feature",
  "properties": {
    "addr:full":"213 Newnan St Carrollton GA 30117",
    "addr:housenumber":"213",
    "addr:postcode":"30117",
    "addr:street":"Newnan St",
    "iso:country":"US",
    "sg:address":"213 Newnan St",
    "sg:city":"Carrollton",
    "sg:classifiers":[
        {
            "category":"Government",
            "subcategory":"Office",
            "type":"Public Place"
        }
    ],
    "sg:phone":"+1 770 838 9520",
    "sg:postcode":"30117",
    "sg:province":"GA",
    "sg:tags":[
        "state",
        "program",
        "health"
    ],
    "wof:name":"Nations Health Care Inc",
    "wof:placetype":"venue"
},
  "geometry": {"coordinates":[-85.073774,33.579878],"type":"Point"}
}