{
  "type": "Feature",
  "properties": {
    "iso:country":"US",
    "sg:address":"5247 Brasswood Dr",
    "sg:city":"Stone Mountain",
    "sg:classifiers":[
        {
            "category":"Professional",
            "subcategory":"Management & Consulting",
            "type":"Services"
        }
    ],
    "sg:phone":"+1 770 987 5492",
    "sg:postcode":"30088",
    "sg:province":"GA",
    "sg:tags":[
        "business"
    ],
    "wof:name":"Asparete Inc",
    "wof:placetype":"venue"
},
  "geometry": {"coordinates":[-84.17665,33.7384],"type":"Point"}
}