{
  "type": "Feature",
  "properties": {
    "addr:full":"701 Martin Luther King Jr Blvd Savannah GA 31401",
    "addr:housenumber":"701",
    "addr:postcode":"31401",
    "addr:street":"Martin Luther King Jr Blvd",
    "iso:country":"US",
    "sg:address":"701 Martin Luther King Jr Blvd",
    "sg:city":"Savannah",
    "sg:classifiers":[
        {
            "category":"Banks & Credit Unions",
            "subcategory":"Bank",
            "type":"Services"
        }
    ],
    "sg:phone":"+1 912 233 9971",
    "sg:postcode":"31401",
    "sg:province":"GA",
    "sg:website":"www.carverstatebank.com",
    "wof:name":"Carver State Bank",
    "wof:placetype":"venue"
},
  "geometry": {"coordinates":[-81.101663,32.06861],"type":"Point"}
}