{
  "type": "Feature",
  "properties": {
    "iso:country":"US",
    "sg:address":"122 Windsor Cir",
    "sg:city":"Brunswick",
    "sg:classifiers":[
        {
            "category":"Building & Trades",
            "subcategory":"Construction",
            "type":"Services"
        }
    ],
    "sg:phone":"+1 912 262 0171",
    "sg:postcode":"31525",
    "sg:province":"GA",
    "sg:tags":[
        "roofer"
    ],
    "wof:name":"David M Rollins",
    "wof:placetype":"venue"
},
  "geometry": {"coordinates":[-81.470894,31.202653],"type":"Point"}
}