{
  "type": "Feature",
  "properties": {
    "addr:full":"1100 Northmeadow Pkwy Ste 150 Roswell GA 30076",
    "addr:housenumber":"1100",
    "addr:postcode":"30076",
    "addr:street":"Northmeadow Pkwy Ste 150",
    "iso:country":"US",
    "sg:address":"1100 Northmeadow Pkwy Ste 150",
    "sg:city":"Roswell",
    "sg:classifiers":[
        {
            "category":"Professional",
            "subcategory":"Computer Services",
            "type":"Services"
        }
    ],
    "sg:phone":"+1 770 475 2725",
    "sg:postcode":"30076",
    "sg:province":"GA",
    "sg:tags":[
        "repair"
    ],
    "wof:name":"Computone Products Inc",
    "wof:placetype":"venue"
},
  "geometry": {"coordinates":[-84.314499,34.062401],"type":"Point"}
}