{
  "type": "Feature",
  "properties": {
    "iso:country":"US",
    "sg:address":"7651 Houston Rd",
    "sg:city":"Byron",
    "sg:classifiers":[
        {
            "category":"Retail",
            "subcategory":"Auto Repair",
            "type":"Services"
        }
    ],
    "sg:phone":"+1 478 785 9090",
    "sg:postcode":"31008",
    "sg:province":"GA",
    "sg:tags":[
        "body",
        "scooter",
        "motorcycle",
        "motor"
    ],
    "wof:name":"2 Wheel Body Shop",
    "wof:placetype":"venue"
},
  "geometry": {"coordinates":[-83.703062,32.679963],"type":"Point"}
}