{
  "type": "Feature",
  "properties": {
    "addr:full":"5996 Bradford Rd Lake Park GA 31636",
    "addr:housenumber":"5996",
    "addr:postcode":"31636",
    "addr:street":"Bradford Rd",
    "iso:country":"US",
    "sg:address":"5996 Bradford Rd",
    "sg:city":"Lake Park",
    "sg:phone":"+1 229 559 7406",
    "sg:postcode":"31636",
    "sg:province":"GA",
    "sg:tags":[
        "farm"
    ],
    "wof:name":"Danny Herring",
    "wof:placetype":"venue"
},
  "geometry": {"coordinates":[-83.169873,30.714064],"type":"Point"}
}