{
  "type": "Feature",
  "properties": {
    "addr:full":"4832 Beverly Dr SW Lilburn GA 30047",
    "addr:housenumber":"4832",
    "addr:postcode":"30047",
    "addr:street":"Beverly Dr Sw",
    "iso:country":"US",
    "sg:address":"4832 Beverly Dr SW",
    "sg:city":"Lilburn",
    "sg:classifiers":[
        {
            "category":"Professional",
            "subcategory":"Management & Consulting",
            "type":"Services"
        }
    ],
    "sg:phone":"+1 678 770 5568",
    "sg:postcode":"30047",
    "sg:province":"GA",
    "wof:name":"Pattillo Consulting LLC",
    "wof:placetype":"venue"
},
  "geometry": {"coordinates":[-84.094959,33.82321],"type":"Point"}
}