{
  "type": "Feature",
  "properties": {
    "iso:country":"US",
    "sg:address":"516 Chester Hwy",
    "sg:city":"Eastman",
    "sg:classifiers":[
        {
            "category":"Retail",
            "subcategory":"Auto Repair",
            "type":"Services"
        }
    ],
    "sg:phone":"+1 478 374 6202",
    "sg:postcode":"31023",
    "sg:province":"GA",
    "sg:tags":[
        "repairing",
        "automobile"
    ],
    "wof:name":"Swinson Car Care",
    "wof:placetype":"venue"
},
  "geometry": {"coordinates":[-83.177515,32.214827],"type":"Point"}
}