{
  "type": "Feature",
  "properties": {
    "iso:country":"US",
    "sg:address":"6272 Welton Dr",
    "sg:city":"Riverdale",
    "sg:classifiers":[
        {
            "category":"Professional",
            "subcategory":"Management & Consulting",
            "type":"Services"
        }
    ],
    "sg:phone":"+1 770 996 6755",
    "sg:postcode":"30296",
    "sg:province":"GA",
    "sg:tags":[
        "consultant",
        "business"
    ],
    "wof:name":"Glymph & Assoc",
    "wof:placetype":"venue"
},
  "geometry": {"coordinates":[-84.43583599999999,33.583884],"type":"Point"}
}