{
  "type": "Feature",
  "properties": {
    "addr:full":"1237 Clermont Ave Atlanta GA 30344",
    "addr:housenumber":"1237",
    "addr:postcode":"30344",
    "addr:street":"Clermont Ave",
    "iso:country":"US",
    "sg:address":"1237 Clermont Ave",
    "sg:city":"Atlanta",
    "sg:classifiers":[
        {
            "category":"Banks & Credit Unions",
            "subcategory":"Bank",
            "type":"Services"
        }
    ],
    "sg:phone":"+1 404 329 6415",
    "sg:postcode":"30344",
    "sg:province":"GA",
    "wof:name":"Emory Federal Credit Union",
    "wof:placetype":"venue"
},
  "geometry": {"coordinates":[-84.43180099999999,33.694901],"type":"Point"}
}