{
  "type": "Feature",
  "properties": {
    "addr:full":"180 Cobb Pkwy S Marietta GA 30060",
    "addr:housenumber":"180",
    "addr:postcode":"30060",
    "addr:street":"Cobb Pkwy S",
    "iso:country":"US",
    "sg:address":"180 Cobb Pkwy S",
    "sg:city":"Marietta",
    "sg:classifiers":[
        {
            "category":"Cinema",
            "subcategory":"Movie Rental",
            "type":"Entertainment"
        }
    ],
    "sg:phone":"+1 770 421 1178",
    "sg:postcode":"30060",
    "sg:province":"GA",
    "sg:tags":[
        "game",
        "video"
    ],
    "sg:website":"www.gamestop.com",
    "wof:name":"Gamestop",
    "wof:placetype":"venue"
},
  "geometry": {"coordinates":[-84.51893200000001,33.947433],"type":"Point"}
}