{
  "type": "Feature",
  "properties": {
    "addr:full":"4568 Lawrenceville Hwy Lilburn GA 30047",
    "addr:housenumber":"4568",
    "addr:postcode":"30047",
    "addr:street":"Lawrenceville Hwy",
    "iso:country":"US",
    "sg:address":"4568 Lawrenceville Hwy",
    "sg:city":"Lilburn",
    "sg:classifiers":[
        {
            "category":"Professional",
            "subcategory":"Management & Consulting",
            "type":"Services"
        }
    ],
    "sg:phone":"+1 770 925 9898",
    "sg:postcode":"30047",
    "sg:province":"GA",
    "sg:tags":[
        "consultant",
        "energy",
        "conservation"
    ],
    "sg:website":"www.karallc.com",
    "wof:name":"Clinical Alternative Resource",
    "wof:placetype":"venue"
},
  "geometry": {"coordinates":[-84.137697,33.898117],"type":"Point"}
}