{
  "type": "Feature",
  "properties": {
    "addr:full":"6270 N Point Pkwy Ste 330 Alpharetta GA 30022",
    "addr:housenumber":"6270",
    "addr:postcode":"30022",
    "addr:street":"N Point Pkwy Ste 330",
    "iso:country":"US",
    "sg:address":"6270 N Point Pkwy Ste 330",
    "sg:city":"Alpharetta",
    "sg:classifiers":[
        {
            "category":"Health Services",
            "subcategory":"Optometrist",
            "type":"Services"
        },
        {
            "category":"Shopping",
            "subcategory":"Optician",
            "type":"Retail Goods"
        }
    ],
    "sg:phone":"+1 770 410 1540",
    "sg:postcode":"30022",
    "sg:province":"GA",
    "sg:tags":[
        "eyewear"
    ],
    "wof:name":"North Point Eyecare Inc",
    "wof:placetype":"venue"
},
  "geometry": {"coordinates":[-84.290001,34.046902],"type":"Point"}
}