{
  "type": "Feature",
  "properties": {
    "iso:country":"US",
    "sg:address":"4145 Lawrenceville Hwy NW",
    "sg:city":"Lilburn",
    "sg:classifiers":[
        {
            "category":"Personal",
            "type":"Services"
        }
    ],
    "sg:phone":"+1 770 717 0410",
    "sg:postcode":"30047",
    "sg:province":"GA",
    "sg:tags":[
        "sewing",
        "alteration"
    ],
    "wof:name":"Pearl Alterations",
    "wof:placetype":"venue"
},
  "geometry": {"coordinates":[-84.119202,33.9035],"type":"Point"}
}