{
  "type": "Feature",
  "properties": {
    "addr:full":"500 Austell Powder Sprin Austell GA 30168",
    "addr:housenumber":"500",
    "addr:postcode":"30168",
    "addr:street":"Austell Powder Sprin",
    "iso:country":"US",
    "sg:address":"500 Austell Powder Sprin",
    "sg:city":"Austell",
    "sg:classifiers":[
        {
            "category":"Professional",
            "subcategory":"Lawyer & Legal Services",
            "type":"Services"
        }
    ],
    "sg:phone":"+1 770 941 3322",
    "sg:postcode":"30168",
    "sg:province":"GA",
    "sg:tags":[
        "divorce",
        "law",
        "family"
    ],
    "wof:name":"Rhonda Breaux Attorney At Law",
    "wof:placetype":"venue"
},
  "geometry": {"coordinates":[-84.595901,33.785999],"type":"Point"}
}