{
  "type": "Feature",
  "properties": {
    "iso:country":"US",
    "sg:address":"6015 Mableton Pkwy SW",
    "sg:city":"Mableton",
    "sg:classifiers":[
        {
            "category":"Retail",
            "subcategory":"Auto Repair",
            "type":"Services"
        }
    ],
    "sg:phone":"+1 770 693 0223",
    "sg:postcode":"30126",
    "sg:province":"GA",
    "wof:name":"Crest Auto & Truck Repair",
    "wof:placetype":"venue"
},
  "geometry": {"coordinates":[-84.570948,33.807524],"type":"Point"}
}