{
  "type": "Feature",
  "properties": {
    "iso:country":"US",
    "sg:address":"4815 Campbellton Rd SW",
    "sg:city":"Atlanta",
    "sg:classifiers":[
        {
            "category":"Professional",
            "subcategory":"Secretarial Services",
            "type":"Services"
        },
        {
            "category":"Professional",
            "subcategory":"Employment Agencies",
            "type":"Services"
        }
    ],
    "sg:phone":"+1 404 344 1764",
    "sg:postcode":"30331",
    "sg:province":"GA",
    "sg:tags":[
        "typing"
    ],
    "wof:name":"Ab Secretary Service Inc",
    "wof:placetype":"venue"
},
  "geometry": {"coordinates":[-84.54495799999999,33.698229],"type":"Point"}
}