{
  "type": "Feature",
  "properties": {
    "iso:country":"US",
    "sg:address":"737 Lora Smith Rd",
    "sg:city":"Newnan",
    "sg:classifiers":[
        {
            "category":"Home & Garden",
            "subcategory":"Building Materials",
            "type":"Retail Goods"
        },
        {
            "category":"Manufacturing",
            "subcategory":"Building Materials",
            "type":"Manufacturing & Wholesale Goods"
        }
    ],
    "sg:phone":"+1 770 254 1998",
    "sg:postcode":"30265",
    "sg:province":"GA",
    "sg:tags":[
        "solid",
        "top",
        "counter",
        "surface"
    ],
    "wof:name":"Shelby Industries",
    "wof:placetype":"venue"
},
  "geometry": {"coordinates":[-84.700829,33.392469],"type":"Point"}
}