{
  "type": "Feature",
  "properties": {
    "addr:full":"2121 Harding Rd Augusta GA 30906",
    "addr:housenumber":"2121",
    "addr:postcode":"30906",
    "addr:street":"Harding Rd",
    "iso:country":"US",
    "sg:address":"2121 Harding Rd",
    "sg:city":"Augusta",
    "sg:classifiers":[
        {
            "category":"Mining & Drilling",
            "type":"Manufacturing & Wholesale Goods"
        }
    ],
    "sg:phone":"+1 706 793 1781",
    "sg:postcode":"30906",
    "sg:province":"GA",
    "sg:tags":[
        "field",
        "repair"
    ],
    "wof:name":"Owens Well and Pump Service",
    "wof:placetype":"venue"
},
  "geometry": {"coordinates":[-82.026826,33.416812],"type":"Point"}
}