{
  "type": "Feature",
  "properties": {
    "addr:full":"2830 Peachtree Industrial Blvd Suite Aa Duluth GA 30097",
    "addr:housenumber":"2830",
    "addr:postcode":"30097",
    "addr:street":"Peachtree Industrial Blvd Suite Aa",
    "iso:country":"US",
    "sg:address":"2830 Peachtree Industrial Blvd Suite Aa",
    "sg:city":"Duluth",
    "sg:classifiers":[
        {
            "category":"Education",
            "subcategory":"Special Training",
            "type":"Public Place"
        },
        {
            "category":"Sports & Exercise",
            "subcategory":"Gym",
            "type":"Entertainment"
        },
        {
            "category":"Arena",
            "subcategory":"Sports Club",
            "type":"Entertainment"
        }
    ],
    "sg:phone":"+1 770 403 1363",
    "sg:postcode":"30097",
    "sg:province":"GA",
    "sg:tags":[
        "trainer",
        "personal",
        "instruction",
        "gymnasium",
        "equipment",
        "self defense",
        "fitness",
        "martial art"
    ],
    "sg:website":"http://www.extreme-fitness.org",
    "wof:name":"Extreme Fitness & Conditioning",
    "wof:placetype":"venue"
},
  "geometry": {"coordinates":[-84.148127,34.02282],"type":"Point"}
}