{
  "type": "Feature",
  "properties": {
    "iso:country":"US",
    "sg:address":"1250 Sunset Dr",
    "sg:city":"Thomasville",
    "sg:classifiers":[
        {
            "category":"Freight",
            "type":"Transportation"
        }
    ],
    "sg:phone":"+1 229 386 5040",
    "sg:postcode":"31792",
    "sg:province":"GA",
    "sg:tags":[
        "operator",
        "trucking"
    ],
    "sg:website":"www.watkins.com",
    "wof:name":"Watkins Motor Lines Inc",
    "wof:placetype":"venue"
},
  "geometry": {"coordinates":[-83.99779100000001,30.822038],"type":"Point"}
}