{
  "type": "Feature",
  "properties": {
    "addr:full":"1201 Broadway Columbus GA 31901",
    "addr:housenumber":"1201",
    "addr:postcode":"31901",
    "addr:street":"Broadway",
    "iso:country":"US",
    "sg:address":"1201 Broadway",
    "sg:city":"Columbus",
    "sg:classifiers":[
        {
            "category":"Banks & Credit Unions",
            "subcategory":"Bank",
            "type":"Services"
        },
        {
            "category":"Banks & Credit Unions",
            "subcategory":"Financial Services",
            "type":"Services"
        }
    ],
    "sg:phone":"+1 706 494 5170",
    "sg:postcode":"31901",
    "sg:province":"GA",
    "sg:tags":[
        "commercial",
        "financing",
        "saving",
        "loan"
    ],
    "sg:website":"http://www.bbt.com",
    "wof:name":"BB & T",
    "wof:placetype":"venue"
},
  "geometry": {"coordinates":[-84.993309,32.468601],"type":"Point"}
}