{
  "type": "Feature",
  "properties": {
    "addr:full":"2852 Napier Ave Macon GA 31204",
    "addr:housenumber":"2852",
    "addr:postcode":"31204",
    "addr:street":"Napier Ave",
    "iso:country":"US",
    "sg:address":"2852 Napier Ave",
    "sg:city":"Macon",
    "sg:classifiers":[
        {
            "category":"Banks & Credit Unions",
            "subcategory":"Investment Brokerage",
            "type":"Services"
        }
    ],
    "sg:phone":"+1 478 750 8077",
    "sg:postcode":"31204",
    "sg:province":"GA",
    "sg:tags":[
        "advisory",
        "financial"
    ],
    "wof:name":"Old World Financial Svc",
    "wof:placetype":"venue"
},
  "geometry": {"coordinates":[-83.668639,32.83649],"type":"Point"}
}