{
  "type": "Feature",
  "properties": {
    "addr:full":"3755 River Dr SW Lilburn GA 30047",
    "addr:housenumber":"3755",
    "addr:postcode":"30047",
    "addr:street":"River Dr Sw",
    "iso:country":"US",
    "sg:address":"3755 River Dr SW",
    "sg:city":"Lilburn",
    "sg:classifiers":[
        {
            "category":"Building & Trades",
            "subcategory":"Locksmith",
            "type":"Services"
        }
    ],
    "sg:phone":"+1 770 325 2496",
    "sg:postcode":"30047",
    "sg:province":"GA",
    "sg:tags":[
        "key"
    ],
    "wof:name":"0 1 Emergency A Locksmith",
    "wof:placetype":"venue"
},
  "geometry": {"coordinates":[-84.091121,33.888159],"type":"Point"}
}