{
  "type": "Feature",
  "properties": {
    "iso:country":"US",
    "sg:address":"1248 Washington St",
    "sg:city":"Jefferson",
    "sg:phone":"+1 706 367 4960",
    "sg:postcode":"30549",
    "sg:province":"GA",
    "wof:name":"Ali-V's Resturant & Gift Shop",
    "wof:placetype":"venue"
},
  "geometry": {"coordinates":[-83.58847900000001,34.130625],"type":"Point"}
}