{
  "type": "Feature",
  "properties": {
    "iso:country":"US",
    "sg:address":"1987 Candler Rd",
    "sg:city":"Decatur",
    "sg:classifiers":[
        {
            "category":"Health Services",
            "subcategory":"Doctor",
            "type":"Services"
        }
    ],
    "sg:phone":"+1 404 286 1700",
    "sg:postcode":"30032",
    "sg:province":"GA",
    "sg:tags":[
        "clinic"
    ],
    "sg:website":"www.davita.com",
    "wof:name":"Da Vita-Decatur Dialysis Ctr",
    "wof:placetype":"venue"
},
  "geometry": {"coordinates":[-84.283738,33.732441],"type":"Point"}
}