{
  "type": "Feature",
  "properties": {
    "iso:country":"US",
    "sg:address":"7334 Cardigan Cir NE",
    "sg:city":"Atlanta",
    "sg:classifiers":[
        {
            "category":"Professional",
            "subcategory":"Business Services",
            "type":"Services"
        }
    ],
    "sg:phone":"+1 770 901 9790",
    "sg:postcode":"30328",
    "sg:province":"GA",
    "wof:name":"Leslie Anns Interiors Inc",
    "wof:placetype":"venue"
},
  "geometry": {"coordinates":[-84.37165,33.947601],"type":"Point"}
}