{
  "type": "Feature",
  "properties": {
    "iso:country":"US",
    "sg:address":"1436 Holly Ln NE",
    "sg:city":"Atlanta",
    "sg:classifiers":[
        {
            "category":"Professional",
            "subcategory":"Management & Consulting",
            "type":"Services"
        },
        {
            "category":"Professional",
            "subcategory":"Engineering",
            "type":"Services"
        }
    ],
    "sg:phone":"+1 404 634 4656",
    "sg:postcode":"30329",
    "sg:province":"GA",
    "sg:tags":[
        "consultant",
        "ecological",
        "engineer",
        "environmental"
    ],
    "wof:name":"Jeremy Sarnat",
    "wof:placetype":"venue"
},
  "geometry": {"coordinates":[-84.323052,33.821232],"type":"Point"}
}