{
  "type": "Feature",
  "properties": {
    "iso:country":"US",
    "sg:address":"3219 Faceville Hwy",
    "sg:city":"Bainbridge",
    "sg:classifiers":[
        {
            "category":"Wholesale",
            "subcategory":"Machinery & Supplies",
            "type":"Manufacturing & Wholesale Goods"
        }
    ],
    "sg:phone":"+1 229 246 1227",
    "sg:postcode":"39819",
    "sg:province":"GA",
    "sg:tags":[
        "equipment",
        "irrigation",
        "system"
    ],
    "wof:name":"Willis Irrigation & Farm Sup",
    "wof:placetype":"venue"
},
  "geometry": {"coordinates":[-84.63119399999999,30.757837],"type":"Point"}
}