{
  "type": "Feature",
  "properties": {
    "iso:country":"US",
    "sg:address":"108 Glenloch Pkwy",
    "sg:city":"Stockbridge",
    "sg:classifiers":[
        {
            "category":"Building & Trades",
            "subcategory":"Construction",
            "type":"Services"
        }
    ],
    "sg:phone":"+1 770 474 3748",
    "sg:postcode":"30281",
    "sg:province":"GA",
    "sg:tags":[
        "contractor"
    ],
    "wof:name":"Integrated Surfaces",
    "wof:placetype":"venue"
},
  "geometry": {"coordinates":[-84.22960999999999,33.591408],"type":"Point"}
}