{
  "type": "Feature",
  "properties": {
    "addr:full":"155 Reserve Dr Covington GA 30014",
    "addr:housenumber":"155",
    "addr:postcode":"30014",
    "addr:street":"Reserve Dr",
    "iso:country":"US",
    "sg:address":"155 Reserve Dr",
    "sg:city":"Covington",
    "sg:classifiers":[
        {
            "category":"Real Estate",
            "subcategory":"Real Estate Operator",
            "type":"Services"
        }
    ],
    "sg:phone":"+1 770 787 8504",
    "sg:postcode":"30014",
    "sg:province":"GA",
    "sg:tags":[
        "building",
        "nonresidential"
    ],
    "wof:name":"Mira Properties Inc",
    "wof:placetype":"venue"
},
  "geometry": {"coordinates":[-83.80148699999999,33.520995],"type":"Point"}
}