{
  "type": "Feature",
  "properties": {
    "iso:country":"US",
    "sg:address":"6110 Northbelt Pkwy",
    "sg:city":"Norcross",
    "sg:classifiers":[
        {
            "category":"Professional",
            "subcategory":"Engineering",
            "type":"Services"
        },
        {
            "category":"Building & Trades",
            "subcategory":"Construction",
            "type":"Services"
        }
    ],
    "sg:phone":"+1 770 447 8677",
    "sg:postcode":"30071",
    "sg:province":"GA",
    "sg:tags":[
        "repair",
        "system",
        "equipment",
        "air conditioning"
    ],
    "wof:name":"Topp Portable Air",
    "wof:placetype":"venue"
},
  "geometry": {"coordinates":[-84.215187,33.925617],"type":"Point"}
}