{
  "type": "Feature",
  "properties": {
    "iso:country":"US",
    "sg:address":"478 Strickland Cir",
    "sg:city":"Colbert",
    "sg:classifiers":[
        {
            "category":"Building & Trades",
            "subcategory":"Construction",
            "type":"Services"
        }
    ],
    "sg:phone":"+1 706 788 2935",
    "sg:postcode":"30628",
    "sg:province":"GA",
    "sg:tags":[
        "painting",
        "contractor"
    ],
    "wof:name":"D & S Contractors",
    "wof:placetype":"venue"
},
  "geometry": {"coordinates":[-83.271269,34.070614],"type":"Point"}
}