{
  "type": "Feature",
  "properties": {
    "iso:country":"US",
    "sg:address":"505 Water Works Rd",
    "sg:city":"Palmetto",
    "sg:classifiers":[
        {
            "category":"Social Services",
            "type":"Services"
        }
    ],
    "sg:phone":"+1 770 463 3800",
    "sg:postcode":"30268",
    "sg:province":"GA",
    "sg:tags":[
        "organization",
        "welfare"
    ],
    "sg:website":"www.gbchfm.org",
    "wof:name":"Georgia Baptist Childrens Home",
    "wof:placetype":"venue"
},
  "geometry": {"coordinates":[-84.67830600000001,33.51995],"type":"Point"}
}