{
  "type": "Feature",
  "properties": {
    "iso:country":"US",
    "sg:address":"185 Laurel Mill Ct",
    "sg:city":"Roswell",
    "sg:classifiers":[
        {
            "category":"Professional",
            "type":"Services"
        }
    ],
    "sg:phone":"+1 770 643 9876",
    "sg:postcode":"30076",
    "sg:province":"GA",
    "wof:name":"Craig Roth",
    "wof:placetype":"venue"
},
  "geometry": {"coordinates":[-84.294759,34.030337],"type":"Point"}
}