{
  "type": "Feature",
  "properties": {
    "addr:full":"5000 Snapfinger Woods Dr Decatur GA 30035",
    "addr:housenumber":"5000",
    "addr:postcode":"30035",
    "addr:street":"Snapfinger Woods Dr",
    "iso:country":"US",
    "sg:address":"5000 Snapfinger Woods Dr",
    "sg:city":"Decatur",
    "sg:classifiers":[
        {
            "category":"Professional",
            "subcategory":"Accounting & Tax Preparation",
            "type":"Services"
        }
    ],
    "sg:phone":"+1 770 322 0096",
    "sg:postcode":"30035",
    "sg:province":"GA",
    "sg:tags":[
        "accountant"
    ],
    "wof:name":"Conklin Eugene J CPA",
    "wof:placetype":"venue"
},
  "geometry": {"coordinates":[-84.184196,33.711201],"type":"Point"}
}