{
  "type": "Feature",
  "properties": {
    "iso:country":"US",
    "sg:address":"4380 Roswell Rd NE",
    "sg:city":"Atlanta",
    "sg:classifiers":[
        {
            "category":"Retail",
            "subcategory":"Car Wash",
            "type":"Services"
        }
    ],
    "sg:phone":"+1 404 256 5457",
    "sg:postcode":"30342",
    "sg:province":"GA",
    "wof:name":"Rays Car Wash & Emission Inspection",
    "wof:placetype":"venue"
},
  "geometry": {"coordinates":[-84.380798,33.874199],"type":"Point"}
}