{
  "type": "Feature",
  "properties": {
    "iso:country":"US",
    "sg:address":"1 National Data Plz NE",
    "sg:city":"Atlanta",
    "sg:classifiers":[
        {
            "category":"Building & Trades",
            "subcategory":"Locksmith",
            "type":"Services"
        }
    ],
    "sg:phone":"+1 800 364 3194",
    "sg:postcode":"30329",
    "sg:province":"GA",
    "sg:tags":[
        "key"
    ],
    "wof:name":"1 24 Hour Emergency Locksmith",
    "wof:placetype":"venue"
},
  "geometry": {"coordinates":[-84.32965299999999,33.835096],"type":"Point"}
}