{
  "type": "Feature",
  "properties": {
    "iso:country":"US",
    "sg:address":"2336 Wisteria Dr Ste 110",
    "sg:city":"Snellville",
    "sg:classifiers":[
        {
            "category":"Professional",
            "subcategory":"Employment Agencies",
            "type":"Services"
        }
    ],
    "sg:phone":"+1 770 979 8977",
    "sg:postcode":"30078",
    "sg:province":"GA",
    "wof:name":"Retail",
    "wof:placetype":"venue"
},
  "geometry": {"coordinates":[-84.01356699999999,33.858709],"type":"Point"}
}