{
  "type": "Feature",
  "properties": {
    "addr:full":"7 Lake Coweta Trl Newnan GA 30263",
    "addr:housenumber":"7",
    "addr:postcode":"30263",
    "addr:street":"Lake Coweta Trl",
    "iso:country":"US",
    "sg:address":"7 Lake Coweta Trl",
    "sg:city":"Newnan",
    "sg:classifiers":[
        {
            "category":"Professional",
            "subcategory":"Business Services",
            "type":"Services"
        }
    ],
    "sg:phone":"+1 770 252 3238",
    "sg:postcode":"30263",
    "sg:province":"GA",
    "sg:tags":[
        "consultant",
        "coach"
    ],
    "wof:name":"C H Solutions Inc",
    "wof:placetype":"venue"
},
  "geometry": {"coordinates":[-84.779427,33.450249],"type":"Point"}
}