{
  "type": "Feature",
  "properties": {
    "addr:full":"1214 Wildwood Ave Columbus GA 31906",
    "addr:housenumber":"1214",
    "addr:postcode":"31906",
    "addr:street":"Wildwood Ave",
    "iso:country":"US",
    "sg:address":"1214 Wildwood Ave",
    "sg:city":"Columbus",
    "sg:classifiers":[
        {
            "category":"Health Services",
            "subcategory":"Doctor",
            "type":"Services"
        }
    ],
    "sg:phone":"+1 706 320 0230",
    "sg:postcode":"31906",
    "sg:province":"GA",
    "sg:tags":[
        "clinic"
    ],
    "wof:name":"KLA Medical",
    "wof:placetype":"venue"
},
  "geometry": {"coordinates":[-84.957802,32.472475],"type":"Point"}
}