{
  "type": "Feature",
  "properties": {
    "addr:full":"415 4th Ave E Cordele GA 31015",
    "addr:housenumber":"415",
    "addr:postcode":"31015",
    "addr:street":"4Th Ave E",
    "iso:country":"US",
    "sg:address":"415 4th Ave E",
    "sg:city":"Cordele",
    "sg:classifiers":[
        {
            "category":"Health Services",
            "subcategory":"Nursing And Care Facility",
            "type":"Services"
        }
    ],
    "sg:phone":"+1 229 271 0300",
    "sg:postcode":"31015",
    "sg:province":"GA",
    "sg:tags":[
        "skilled"
    ],
    "wof:name":"United Hospice",
    "wof:placetype":"venue"
},
  "geometry": {"coordinates":[-83.77676700000001,31.976364],"type":"Point"}
}