{
  "type": "Feature",
  "properties": {
    "addr:full":"483 Washington Ave NE Marietta GA 30060",
    "addr:housenumber":"483",
    "addr:postcode":"30060",
    "addr:street":"Washington Ave Ne",
    "iso:country":"US",
    "sg:address":"483 Washington Ave NE",
    "sg:city":"Marietta",
    "sg:classifiers":[
        {
            "category":"Banks & Credit Unions",
            "subcategory":"Financial Services",
            "type":"Services"
        }
    ],
    "sg:phone":"+1 770 428 6138",
    "sg:postcode":"30060",
    "sg:province":"GA",
    "sg:tags":[
        "investor"
    ],
    "wof:name":"Sanders Realty Investments",
    "wof:placetype":"venue"
},
  "geometry": {"coordinates":[-84.53963899999999,33.952163],"type":"Point"}
}