{
  "type": "Feature",
  "properties": {
    "iso:country":"US",
    "sg:address":"3029 Pine Needle Rd",
    "sg:city":"Augusta",
    "sg:classifiers":[
        {
            "category":"Professional",
            "type":"Services"
        }
    ],
    "sg:phone":"+1 706 736 6792",
    "sg:postcode":"30909",
    "sg:province":"GA",
    "wof:name":"National Society of Daugh",
    "wof:placetype":"venue"
},
  "geometry": {"coordinates":[-82.04207100000001,33.472672],"type":"Point"}
}