{
  "type": "Feature",
  "properties": {
    "addr:full":"112 Patterson Ln Adairsville GA 30103",
    "addr:housenumber":"112",
    "addr:postcode":"30103",
    "addr:street":"Patterson Ln",
    "iso:country":"US",
    "sg:address":"112 Patterson Ln",
    "sg:city":"Adairsville",
    "sg:classifiers":[
        {
            "category":"Freight",
            "type":"Transportation"
        }
    ],
    "sg:phone":"+1 770 877 3370",
    "sg:postcode":"30103",
    "sg:province":"GA",
    "sg:tags":[
        "operator",
        "local",
        "trucking"
    ],
    "wof:name":"B Transport",
    "wof:placetype":"venue"
},
  "geometry": {"coordinates":[-84.91010199999999,34.366998],"type":"Point"}
}