{
  "type": "Feature",
  "properties": {
    "iso:country":"US",
    "sg:address":"3209 Paces Ferry Pl NW",
    "sg:city":"Atlanta",
    "sg:classifiers":[
        {
            "category":"Shopping",
            "subcategory":"Clothing, Apparel, & Fashions",
            "type":"Retail Goods"
        }
    ],
    "sg:phone":"+1 404 239 0411",
    "sg:postcode":"30305",
    "sg:province":"GA",
    "sg:tags":[
        "accessory",
        "clothing",
        "women's"
    ],
    "wof:name":"P B J C Inc",
    "wof:placetype":"venue"
},
  "geometry": {"coordinates":[-84.382103,33.841599],"type":"Point"}
}