{
  "type": "Feature",
  "properties": {
    "iso:country":"US",
    "sg:address":"138 May Ave",
    "sg:city":"Lincolnton",
    "sg:classifiers":[
        {
            "category":"Personal",
            "type":"Services"
        },
        {
            "category":"Retail",
            "subcategory":"Auto Repair",
            "type":"Services"
        }
    ],
    "sg:phone":"+1 706 359 4181",
    "sg:postcode":"30817",
    "sg:province":"GA",
    "sg:tags":[
        "body",
        "repairing",
        "towing",
        "painting",
        "automobile"
    ],
    "wof:name":"Cooper's Paint & Body Shop",
    "wof:placetype":"venue"
},
  "geometry": {"coordinates":[-82.476077,33.78831],"type":"Point"}
}