{
  "type": "Feature",
  "properties": {
    "addr:full":"2755 Canton Rd Marietta GA 30066",
    "addr:housenumber":"2755",
    "addr:postcode":"30066",
    "addr:street":"Canton Rd",
    "iso:country":"US",
    "sg:address":"2755 Canton Rd",
    "sg:city":"Marietta",
    "sg:classifiers":[
        {
            "category":"Restaurant",
            "type":"Food & Drink"
        }
    ],
    "sg:phone":"+1 770 514 7555",
    "sg:postcode":"30066",
    "sg:province":"GA",
    "sg:tags":[
        "vietnamese"
    ],
    "wof:name":"Saigon Pearl",
    "wof:placetype":"venue"
},
  "geometry": {"coordinates":[-84.527559,34.017706],"type":"Point"}
}