{
  "type": "Feature",
  "properties": {
    "iso:country":"US",
    "sg:address":"7585 Ponce de Leon Cir NW",
    "sg:city":"Atlanta",
    "sg:classifiers":[
        {
            "category":"Banks & Credit Unions",
            "subcategory":"Bank",
            "type":"Services"
        }
    ],
    "sg:phone":"+1 770 446 1229",
    "sg:postcode":"30340",
    "sg:province":"GA",
    "sg:tags":[
        "federal"
    ],
    "wof:name":"Credit Union Car Exchange",
    "wof:placetype":"venue"
},
  "geometry": {"coordinates":[-84.23584,33.911089],"type":"Point"}
}