{
  "type": "Feature",
  "properties": {
    "addr:full":"102 Head Ave Tallapoosa GA 30176",
    "addr:housenumber":"102",
    "addr:postcode":"30176",
    "addr:street":"Head Ave",
    "iso:country":"US",
    "sg:address":"102 Head Ave",
    "sg:city":"Tallapoosa",
    "sg:classifiers":[
        {
            "category":"Manufacturing",
            "subcategory":"Apparel",
            "type":"Manufacturing & Wholesale Goods"
        }
    ],
    "sg:phone":"+1 770 574 9929",
    "sg:postcode":"30176",
    "sg:province":"GA",
    "wof:name":"Sew Simple Embroidery",
    "wof:placetype":"venue"
},
  "geometry": {"coordinates":[-85.28812600000001,33.746404],"type":"Point"}
}