{
  "type": "Feature",
  "properties": {
    "addr:full":"1115 N Patterson St Valdosta GA 31601",
    "addr:housenumber":"1115",
    "addr:postcode":"31601",
    "addr:street":"N Patterson St",
    "iso:country":"US",
    "sg:address":"1115 N Patterson St",
    "sg:city":"Valdosta",
    "sg:classifiers":[
        {
            "category":"Retail",
            "subcategory":"Auto Repair",
            "type":"Services"
        }
    ],
    "sg:phone":"+1 229 244 1567",
    "sg:postcode":"31601",
    "sg:province":"GA",
    "sg:tags":[
        "repairing",
        "automobile"
    ],
    "wof:name":"Mike & Son Svc Ctr",
    "wof:placetype":"venue"
},
  "geometry": {"coordinates":[-83.285116,30.842976],"type":"Point"}
}