{
  "type": "Feature",
  "properties": {
    "iso:country":"US",
    "sg:address":"3781 Presidential Pkwy",
    "sg:city":"Atlanta",
    "sg:classifiers":[
        {
            "category":"Professional",
            "subcategory":"Business Services",
            "type":"Services"
        }
    ],
    "sg:phone":"+1 404 327 4771",
    "sg:postcode":"30340",
    "sg:province":"GA",
    "sg:tags":[
        "tv",
        "designer",
        "cable"
    ],
    "wof:name":"Globe Broadband Design",
    "wof:placetype":"venue"
},
  "geometry": {"coordinates":[-84.26546500000001,33.887017],"type":"Point"}
}