{
  "type": "Feature",
  "properties": {
    "iso:country":"US",
    "sg:address":"2380 Buford Dr",
    "sg:city":"Lawrenceville",
    "sg:classifiers":[
        {
            "category":"Professional",
            "subcategory":"Advertising",
            "type":"Services"
        }
    ],
    "sg:phone":"+1 770 962 7299",
    "sg:postcode":"30043",
    "sg:province":"GA",
    "sg:tags":[
        "mailing",
        "shipping"
    ],
    "wof:name":"UPS Store",
    "wof:placetype":"venue"
},
  "geometry": {"coordinates":[-83.988315,34.036327],"type":"Point"}
}