{
  "type": "Feature",
  "properties": {
    "iso:country":"US",
    "sg:address":"902 Marden Ct",
    "sg:city":"Smyrna",
    "sg:classifiers":[
        {
            "category":"Professional",
            "subcategory":"Computer Services",
            "type":"Services"
        }
    ],
    "sg:phone":"+1 770 384 0202",
    "sg:postcode":"30082",
    "sg:province":"GA",
    "sg:tags":[
        "related"
    ],
    "wof:name":"Advancenetworkssolutions",
    "wof:placetype":"venue"
},
  "geometry": {"coordinates":[-84.51228999999999,33.853113],"type":"Point"}
}