{
  "type": "Feature",
  "properties": {
    "addr:full":"200 Olympia Dr Warner Robins GA 31093",
    "addr:housenumber":"200",
    "addr:postcode":"31093",
    "addr:street":"Olympia Dr",
    "iso:country":"US",
    "sg:address":"200 Olympia Dr",
    "sg:city":"Warner Robins",
    "sg:classifiers":[
        {
            "category":"Real Estate",
            "subcategory":"Real Estate Operator",
            "type":"Services"
        },
        {
            "category":"Real Estate",
            "subcategory":"Real Estate Agent",
            "type":"Services"
        }
    ],
    "sg:phone":"+1 478 922 1815",
    "sg:postcode":"31093",
    "sg:province":"GA",
    "sg:tags":[
        "apartment",
        "complex",
        "operates"
    ],
    "wof:name":"Wellston Ridge Apts",
    "wof:placetype":"venue"
},
  "geometry": {"coordinates":[-83.652199,32.620098],"type":"Point"}
}