{
  "type": "Feature",
  "properties": {
    "addr:full":"720 State Rte 293 Emerson GA 30137",
    "addr:housenumber":"720",
    "addr:postcode":"30137",
    "addr:street":"State Rte 293",
    "iso:country":"US",
    "sg:address":"720 State Rte 293",
    "sg:city":"Emerson",
    "sg:classifiers":[
        {
            "category":"Professional",
            "subcategory":"Accounting & Tax Preparation",
            "type":"Services"
        }
    ],
    "sg:phone":"+1 770 382 0447",
    "sg:postcode":"30137",
    "sg:province":"GA",
    "sg:tags":[
        "return",
        "filing"
    ],
    "wof:name":"Mc Kay's Income Tax Svc",
    "wof:placetype":"venue"
},
  "geometry": {"coordinates":[-84.755792,34.125298],"type":"Point"}
}