{
  "type": "Feature",
  "properties": {
    "addr:full":"5 Northlake Cir Peachtree City GA 30269",
    "addr:housenumber":"5",
    "addr:postcode":"30269",
    "addr:street":"Northlake Cir",
    "iso:country":"US",
    "sg:address":"5 Northlake Cir",
    "sg:city":"Peachtree City",
    "sg:classifiers":[
        {
            "category":"Wholesale",
            "subcategory":"Construction Materials",
            "type":"Manufacturing & Wholesale Goods"
        }
    ],
    "sg:phone":"+1 770 631 6407",
    "sg:postcode":"30269",
    "sg:province":"GA",
    "sg:tags":[
        "lumber",
        "plywood"
    ],
    "wof:name":"Forest Products",
    "wof:placetype":"venue"
},
  "geometry": {"coordinates":[-84.580473,33.405295],"type":"Point"}
}