{
  "type": "Feature",
  "properties": {
    "addr:full":"900 Dill Ave SW Atlanta GA 30310",
    "addr:housenumber":"900",
    "addr:postcode":"30310",
    "addr:street":"Dill Ave Sw",
    "iso:country":"US",
    "sg:address":"900 Dill Ave SW",
    "sg:city":"Atlanta",
    "sg:classifiers":[
        {
            "category":"Wholesale",
            "subcategory":"Painting Supplies",
            "type":"Manufacturing & Wholesale Goods"
        }
    ],
    "sg:phone":"+1 404 254 5326",
    "sg:postcode":"30310",
    "sg:province":"GA",
    "sg:tags":[
        "paint-wholesale",
        "manufacturer"
    ],
    "wof:name":"All In One Paint And Body",
    "wof:placetype":"venue"
},
  "geometry": {"coordinates":[-84.417621,33.718295],"type":"Point"}
}