{
  "type": "Feature",
  "properties": {
    "addr:full":"1645 Manchester Expy Columbus GA 31904",
    "addr:housenumber":"1645",
    "addr:postcode":"31904",
    "addr:street":"Manchester Expy",
    "iso:country":"US",
    "sg:address":"1645 Manchester Expy",
    "sg:city":"Columbus",
    "sg:classifiers":[
        {
            "category":"Food & Beverages",
            "subcategory":"Groceries & Convenience Stores",
            "type":"Retail Goods"
        }
    ],
    "sg:phone":"+1 706 576 5146",
    "sg:postcode":"31904",
    "sg:province":"GA",
    "sg:website":"http://www.circlek.com",
    "wof:name":"Circle K",
    "wof:placetype":"venue"
},
  "geometry": {"coordinates":[-84.96766700000001,32.50708],"type":"Point"}
}