{
  "type": "Feature",
  "properties": {
    "iso:country":"US",
    "sg:address":"722 Redland Dr",
    "sg:city":"Jonesboro",
    "sg:classifiers":[
        {
            "category":"Building & Trades",
            "subcategory":"Construction",
            "type":"Services"
        }
    ],
    "sg:phone":"+1 770 994 3612",
    "sg:postcode":"30238",
    "sg:province":"GA",
    "sg:tags":[
        "house"
    ],
    "wof:name":"Rasheed Contractors",
    "wof:placetype":"venue"
},
  "geometry": {"coordinates":[-84.414024,33.519267],"type":"Point"}
}