{
  "type": "Feature",
  "properties": {
    "iso:country":"US",
    "sg:address":"411 King Arnold St",
    "sg:city":"Hapeville",
    "sg:classifiers":[
        {
            "category":"Social Services",
            "type":"Services"
        }
    ],
    "sg:phone":"+1 404 763 4357",
    "sg:postcode":"30354",
    "sg:province":"GA",
    "sg:tags":[
        "pregnancy",
        "counseling",
        "information"
    ],
    "wof:name":"Pregnancy Problem Ctr",
    "wof:placetype":"venue"
},
  "geometry": {"coordinates":[-84.399253,33.6555],"type":"Point"}
}