{
  "type": "Feature",
  "properties": {
    "iso:country":"US",
    "sg:address":"1826 Rue de Montreal",
    "sg:city":"Tucker",
    "sg:classifiers":[
        {
            "category":"Professional",
            "type":"Services"
        }
    ],
    "sg:phone":"+1 678 596 3342",
    "sg:postcode":"30084",
    "sg:province":"GA",
    "wof:name":"Popular Systems",
    "wof:placetype":"venue"
},
  "geometry": {"coordinates":[-84.258392,33.832856],"type":"Point"}
}