{
  "type": "Feature",
  "properties": {
    "addr:full":"938 Center St SW Villa Rica GA 30126",
    "addr:housenumber":"938",
    "addr:postcode":"30126",
    "addr:street":"Center St Sw",
    "iso:country":"US",
    "sg:address":"938 Center St SW",
    "sg:city":"Villa Rica",
    "sg:classifiers":[
        {
            "category":"Real Estate",
            "subcategory":"Real Estate Agent",
            "type":"Services"
        }
    ],
    "sg:phone":"+1 770 459 1992",
    "sg:postcode":"30126",
    "sg:province":"GA",
    "wof:name":"Prudential Georgia Realty",
    "wof:placetype":"venue"
},
  "geometry": {"coordinates":[-84.58116,33.82211],"type":"Point"}
}