{
  "type": "Feature",
  "properties": {
    "iso:country":"US",
    "sg:address":"465 S Jeff Davis Dr",
    "sg:city":"Fayetteville",
    "sg:classifiers":[
        {
            "category":"Real Estate",
            "subcategory":"Real Estate Agent",
            "type":"Services"
        }
    ],
    "sg:phone":"+1 770 461 5435",
    "sg:postcode":"30215",
    "sg:province":"GA",
    "wof:name":"Home Power Realty Inc",
    "wof:placetype":"venue"
},
  "geometry": {"coordinates":[-84.442173,33.440332],"type":"Point"}
}