{
  "type": "Feature",
  "properties": {
    "addr:full":"2060 Watson Blvd Warner Robins GA 31093",
    "addr:housenumber":"2060",
    "addr:postcode":"31093",
    "addr:street":"Watson Blvd",
    "iso:country":"US",
    "sg:address":"2060 Watson Blvd",
    "sg:city":"Warner Robins",
    "sg:classifiers":[
        {
            "category":"Professional",
            "subcategory":"Advertising",
            "type":"Services"
        }
    ],
    "sg:phone":"+1 478 329 9900",
    "sg:postcode":"31093",
    "sg:province":"GA",
    "sg:website":"www.houstonhomejournal.com",
    "wof:name":"Houston Home Journal",
    "wof:placetype":"venue"
},
  "geometry": {"coordinates":[-83.65185099999999,32.61842],"type":"Point"}
}