{
  "type": "Feature",
  "properties": {
    "iso:country":"US",
    "sg:address":"12 Silverleaf Ct",
    "sg:city":"Savannah",
    "sg:classifiers":[
        {
            "category":"Building & Trades",
            "subcategory":"Plumbing",
            "type":"Services"
        }
    ],
    "sg:phone":"+1 912 353 7702",
    "sg:postcode":"31406",
    "sg:province":"GA",
    "sg:tags":[
        "contractor"
    ],
    "wof:name":"Anthony Plumbing",
    "wof:placetype":"venue"
},
  "geometry": {"coordinates":[-81.06464800000001,31.997323],"type":"Point"}
}