{
  "type": "Feature",
  "properties": {
    "iso:country":"US",
    "sg:address":"105 Mountain Brook Dr",
    "sg:city":"Canton",
    "sg:classifiers":[
        {
            "category":"Health Services",
            "subcategory":"Dentist",
            "type":"Services"
        }
    ],
    "sg:phone":"+1 770 345 6864",
    "sg:postcode":"30115",
    "sg:province":"GA",
    "wof:name":"Smile Solutions of Ga",
    "wof:placetype":"venue"
},
  "geometry": {"coordinates":[-84.503985,34.178541],"type":"Point"}
}