{
  "type": "Feature",
  "properties": {
    "iso:country":"US",
    "sg:address":"2893 N Main St NW",
    "sg:city":"Kennesaw",
    "sg:classifiers":[
        {
            "category":"Personal",
            "subcategory":"Beauty Salon",
            "type":"Services"
        }
    ],
    "sg:phone":"+1 678 907 7775",
    "sg:postcode":"30144",
    "sg:province":"GA",
    "sg:tags":[
        "hair"
    ],
    "wof:name":"Nell Cook - Phase II Hair Salon",
    "wof:placetype":"venue"
},
  "geometry": {"coordinates":[-84.615319,34.02407],"type":"Point"}
}