{
  "type": "Feature",
  "properties": {
    "iso:country":"US",
    "sg:address":"6461 Corley Rd NW",
    "sg:city":"Norcross",
    "sg:classifiers":[
        {
            "category":"Building & Trades",
            "subcategory":"Equipment Rental",
            "type":"Services"
        }
    ],
    "sg:phone":"+1 770 662 8881",
    "sg:postcode":"30071",
    "sg:province":"GA",
    "sg:tags":[
        "leasing"
    ],
    "wof:name":"Salem Leasing",
    "wof:placetype":"venue"
},
  "geometry": {"coordinates":[-84.232228,33.934155],"type":"Point"}
}