{
  "type": "Feature",
  "properties": {
    "addr:full":"408 Wall Rd Statham GA 30666",
    "addr:housenumber":"408",
    "addr:postcode":"30666",
    "addr:street":"Wall Rd",
    "iso:country":"US",
    "sg:address":"408 Wall Rd",
    "sg:city":"Statham",
    "sg:classifiers":[
        {
            "category":"Professional",
            "type":"Services"
        }
    ],
    "sg:phone":"+1 770 725 1212",
    "sg:postcode":"30666",
    "sg:province":"GA",
    "wof:name":"Pro Works Services Inc",
    "wof:placetype":"venue"
},
  "geometry": {"coordinates":[-83.617119,33.971649],"type":"Point"}
}