{
  "type": "Feature",
  "properties": {
    "iso:country":"US",
    "sg:address":"8975 Roswell Rd",
    "sg:city":"Atlanta",
    "sg:classifiers":[
        {
            "category":"Shopping",
            "subcategory":"Computers & Home Electronics",
            "type":"Retail Goods"
        }
    ],
    "sg:phone":"+1 770 998 0564",
    "sg:postcode":"30350",
    "sg:province":"GA",
    "wof:name":"Mitsubishi Electronics",
    "wof:placetype":"venue"
},
  "geometry": {"coordinates":[-84.35035499999999,34.001856],"type":"Point"}
}