{
  "type": "Feature",
  "properties": {
    "addr:full":"6631H Roswell Rd NE Atlanta GA 30328",
    "addr:housenumber":"6631h;rd",
    "addr:postcode":"30328",
    "addr:street":"Roswell;Ne",
    "iso:country":"US",
    "sg:address":"6631H Roswell Rd NE",
    "sg:city":"Atlanta",
    "sg:classifiers":[
        {
            "category":"Professional",
            "subcategory":"Accounting & Tax Preparation",
            "type":"Services"
        },
        {
            "category":"Wholesale",
            "subcategory":"Office Equipment",
            "type":"Manufacturing & Wholesale Goods"
        },
        {
            "category":"Professional",
            "subcategory":"Lawyer & Legal Services",
            "type":"Services"
        }
    ],
    "sg:phone":"+1 404 252 2615",
    "sg:postcode":"30328",
    "sg:province":"GA",
    "sg:tags":[
        "attorney",
        "return",
        "taxes-consultants",
        "supply",
        "machine",
        "representative",
        "bookkeeping"
    ],
    "wof:name":"H&R Block Inside Abernathy Square Shopping Center",
    "wof:placetype":"venue"
},
  "geometry": {"coordinates":[-84.378801,33.936291],"type":"Point"}
}