{
  "type": "Feature",
  "properties": {
    "iso:country":"US",
    "sg:address":"3502 Birchwood Trl",
    "sg:city":"Snellville",
    "sg:classifiers":[
        {
            "category":"Building & Trades",
            "subcategory":"Landscaping Services",
            "type":"Services"
        }
    ],
    "sg:phone":"+1 770 560 4288",
    "sg:postcode":"30078",
    "sg:province":"GA",
    "sg:tags":[
        "landscape",
        "contractor"
    ],
    "wof:name":"A Special Edition",
    "wof:placetype":"venue"
},
  "geometry": {"coordinates":[-84.055977,33.847445],"type":"Point"}
}