{
  "type": "Feature",
  "properties": {
    "iso:country":"US",
    "sg:address":"211 J D Walton Rd",
    "sg:city":"Newnan",
    "sg:classifiers":[
        {
            "category":"Professional",
            "type":"Services"
        }
    ],
    "sg:phone":"+1 770 304 0885",
    "sg:postcode":"30263",
    "sg:province":"GA",
    "sg:tags":[
        "establishment"
    ],
    "wof:name":"Everest Imaging LTD",
    "wof:placetype":"venue"
},
  "geometry": {"coordinates":[-84.922166,33.320418],"type":"Point"}
}