{
  "type": "Feature",
  "properties": {
    "addr:full":"4580 Cargo Dr Columbus GA 31907",
    "addr:housenumber":"4580",
    "addr:postcode":"31907",
    "addr:street":"Cargo Dr",
    "iso:country":"US",
    "sg:address":"4580 Cargo Dr",
    "sg:city":"Columbus",
    "sg:classifiers":[
        {
            "category":"Manufacturing",
            "subcategory":"Printing",
            "type":"Manufacturing & Wholesale Goods"
        }
    ],
    "sg:phone":"+1 706 644 1585",
    "sg:postcode":"31907",
    "sg:province":"GA",
    "sg:tags":[
        "lithographic",
        "b",
        "commercial",
        "typesetting"
    ],
    "sg:website":"www.columbusproductionsinc.com",
    "wof:name":"Columbus Productions Inc",
    "wof:placetype":"venue"
},
  "geometry": {"coordinates":[-84.871189,32.506635],"type":"Point"}
}