{
  "type": "Feature",
  "properties": {
    "iso:country":"US",
    "sg:address":"6010 Whitehall Run",
    "sg:city":"Suwanee",
    "sg:classifiers":[
        {
            "category":"Professional",
            "subcategory":"Business Services",
            "type":"Services"
        }
    ],
    "sg:phone":"+1 770 497 8168",
    "sg:postcode":"30024",
    "sg:province":"GA",
    "wof:name":"Lscc Enterprises LLC",
    "wof:placetype":"venue"
},
  "geometry": {"coordinates":[-84.119439,34.079314],"type":"Point"}
}