{
  "type": "Feature",
  "properties": {
    "iso:country":"US",
    "sg:address":"4285 Banks Creek Church Rd",
    "sg:city":"Portal",
    "sg:classifiers":[
        {
            "category":"Real Estate",
            "subcategory":"Real Estate Operator",
            "type":"Services"
        }
    ],
    "sg:phone":"+1 912 865 2513",
    "sg:postcode":"30450",
    "sg:province":"GA",
    "sg:tags":[
        "property",
        "lessor"
    ],
    "wof:name":"Kellys Pntg & Pressure Wash",
    "wof:placetype":"venue"
},
  "geometry": {"coordinates":[-81.906733,32.586723],"type":"Point"}
}