{
  "type": "Feature",
  "properties": {
    "addr:full":"105 Dogwood Rd Savannah GA 31410",
    "addr:housenumber":"105",
    "addr:postcode":"31410",
    "addr:street":"Dogwood Rd",
    "iso:country":"US",
    "sg:address":"105 Dogwood Rd",
    "sg:city":"Savannah",
    "sg:classifiers":[
        {
            "category":"Building & Trades",
            "subcategory":"Construction",
            "type":"Services"
        }
    ],
    "sg:phone":"+1 912 657 8542",
    "sg:postcode":"31410",
    "sg:province":"GA",
    "sg:tags":[
        "heavy"
    ],
    "wof:name":"T N Hampton Landclearing",
    "wof:placetype":"venue"
},
  "geometry": {"coordinates":[-80.988387,32.0112],"type":"Point"}
}