{
  "type": "Feature",
  "properties": {
    "iso:country":"US",
    "sg:address":"755 Raco Dr",
    "sg:city":"Lawrenceville",
    "sg:classifiers":[
        {
            "category":"Home & Garden",
            "subcategory":"Furniture",
            "type":"Retail Goods"
        }
    ],
    "sg:phone":"+1 770 682 1148",
    "sg:postcode":"30045",
    "sg:province":"GA",
    "sg:tags":[
        "cabinet"
    ],
    "wof:name":"Commercial Cabinets",
    "wof:placetype":"venue"
},
  "geometry": {"coordinates":[-84.02636200000001,33.957777],"type":"Point"}
}