{
  "type": "Feature",
  "properties": {
    "iso:country":"US",
    "sg:address":"790 Wire Rd",
    "sg:city":"Thomson",
    "sg:classifiers":[
        {
            "category":"Professional",
            "subcategory":"Detective & Security Services",
            "type":"Services"
        }
    ],
    "sg:phone":"+1 706 595 9043",
    "sg:postcode":"30824",
    "sg:province":"GA",
    "sg:tags":[
        "system"
    ],
    "wof:name":"Superior Alarm and Fire Eqp",
    "wof:placetype":"venue"
},
  "geometry": {"coordinates":[-82.51563299999999,33.441336],"type":"Point"}
}