{
  "type": "Feature",
  "properties": {
    "iso:country":"US",
    "sg:address":"11375 Southbridge Pkwy",
    "sg:city":"Alpharetta",
    "sg:classifiers":[
        {
            "category":"Shopping",
            "subcategory":"Computers & Home Electronics",
            "type":"Retail Goods"
        },
        {
            "category":"Professional",
            "subcategory":"Computer Services",
            "type":"Services"
        }
    ],
    "sg:phone":"+1 770 475 1950",
    "sg:postcode":"30022",
    "sg:province":"GA",
    "sg:tags":[
        "consulting",
        "software"
    ],
    "sg:website":"www.crestonetech.com",
    "wof:name":"Paaridian Technologies Inc",
    "wof:placetype":"venue"
},
  "geometry": {"coordinates":[-84.23742799999999,34.057537],"type":"Point"}
}