{
  "type": "Feature",
  "properties": {
    "iso:country":"US",
    "sg:address":"2022 Capitol St",
    "sg:city":"Savannah",
    "sg:classifiers":[
        {
            "category":"Restaurant",
            "type":"Food & Drink"
        }
    ],
    "sg:phone":"+1 912 238 8318",
    "sg:postcode":"31404",
    "sg:province":"GA",
    "sg:tags":[
        "eating"
    ],
    "wof:name":"Happy China II",
    "wof:placetype":"venue"
},
  "geometry": {"coordinates":[-81.05670499999999,32.06443],"type":"Point"}
}