{
  "type": "Feature",
  "properties": {
    "iso:country":"US",
    "sg:address":"225 Tidwell Dr",
    "sg:city":"Alpharetta",
    "sg:classifiers":[
        {
            "category":"Building & Trades",
            "subcategory":"Construction",
            "type":"Services"
        }
    ],
    "sg:phone":"+1 770 475 0070",
    "sg:postcode":"30004",
    "sg:province":"GA",
    "sg:tags":[
        "control",
        "erosion"
    ],
    "wof:name":"Reeves & Wagner Waterproofing",
    "wof:placetype":"venue"
},
  "geometry": {"coordinates":[-84.23948900000001,34.11058],"type":"Point"}
}