{
  "type": "Feature",
  "properties": {
    "iso:country":"US",
    "sg:address":"1698 Laurel Creek Cir",
    "sg:city":"Lithonia",
    "sg:classifiers":[
        {
            "category":"Professional",
            "subcategory":"Business Services",
            "type":"Services"
        }
    ],
    "sg:phone":"+1 678 517 1126",
    "sg:postcode":"30058",
    "sg:province":"GA",
    "sg:tags":[
        "building",
        "maintenance"
    ],
    "wof:name":"Archer Inspection & Maint",
    "wof:placetype":"venue"
},
  "geometry": {"coordinates":[-84.16204500000001,33.741505],"type":"Point"}
}