{
  "type": "Feature",
  "properties": {
    "addr:city":"Atlanta",
    "addr:full":"1404 Spring Street Nw Atlanta, Ga 30309-2820",
    "addr:house_number":"1404",
    "addr:housenumber":"1404",
    "addr:phone":"+1 404-873-3391",
    "addr:postcode":"30309-2820",
    "addr:road":"Spring Street Nw",
    "addr:state":"GA",
    "addr:street":"Spring St Nw",
    "iso:country":"US",
    "sg:address":"1404 Spring St NW",
    "sg:city":"Atlanta",
    "sg:classifiers":[
        {
            "category":"Arts & Performance",
            "subcategory":"Arts Center",
            "type":"Entertainment"
        },
        {
            "category":"Museum",
            "type":"Entertainment"
        }
    ],
    "sg:phone":"+1 404 873 3391",
    "sg:postcode":"30309",
    "sg:province":"GA",
    "sg:tags":[
        "performing"
    ],
    "sg:website":"www.puppet.org",
    "wof:airports":[
        102525899,
        102526927
    ],
    "wof:name":"Center For Puppetry Arts",
    "wof:placetype":"venue"
},
  "geometry": {"coordinates":[-84.38982,33.79277],"type":"Point"}
}