{
  "type": "Feature",
  "properties": {
    "addr:full":"1404 Spring St NW Atlanta GA 30309",
    "addr:housenumber":"1404",
    "addr:postcode":"30309",
    "addr:street":"Spring St Nw",
    "iso:country":"US",
    "sg:address":"1404 Spring St NW",
    "sg:city":"Atlanta",
    "sg:classifiers":[
        {
            "category":"Arts & Performance",
            "subcategory":"Arts Center",
            "type":"Entertainment"
        },
        {
            "category":"Museum",
            "type":"Entertainment"
        }
    ],
    "sg:phone":"+1 404 873 3391",
    "sg:postcode":"30309",
    "sg:province":"GA",
    "sg:tags":[
        "performing"
    ],
    "sg:website":"www.puppet.org",
    "wof:name":"Center For Puppetry Arts",
    "wof:placetype":"venue"
},
  "geometry": {"coordinates":[-84.38911899999999,33.792772],"type":"Point"}
}