{
  "type": "Feature",
  "properties": {
    "iso:country":"US",
    "sg:address":"676 Pepperwood Ln",
    "sg:city":"Stone Mountain",
    "sg:classifiers":[
        {
            "category":"Banks & Credit Unions",
            "subcategory":"Investment Brokerage",
            "type":"Services"
        }
    ],
    "sg:phone":"+1 770 647 2365",
    "sg:postcode":"30087",
    "sg:province":"GA",
    "sg:tags":[
        "security"
    ],
    "wof:name":"Edward Jones 19664",
    "wof:placetype":"venue"
},
  "geometry": {"coordinates":[-84.164327,33.797093],"type":"Point"}
}