{
  "type": "Feature",
  "properties": {
    "iso:country":"US",
    "sg:address":"3901 Darien Hwy",
    "sg:city":"Brunswick",
    "sg:classifiers":[
        {
            "category":"Professional",
            "subcategory":"Business Services",
            "type":"Services"
        }
    ],
    "sg:phone":"+1 912 261 9332",
    "sg:postcode":"31525",
    "sg:province":"GA",
    "wof:name":"Richard R Fields & Associates",
    "wof:placetype":"venue"
},
  "geometry": {"coordinates":[-81.464902,31.215774],"type":"Point"}
}