{
  "type": "Feature",
  "properties": {
    "addr:full":"709 Roosevelt St Vidalia GA 30474",
    "addr:housenumber":"709",
    "addr:postcode":"30474",
    "addr:street":"Roosevelt St",
    "iso:country":"US",
    "sg:address":"709 Roosevelt St",
    "sg:city":"Vidalia",
    "sg:classifiers":[
        {
            "category":"Professional",
            "subcategory":"Art Services",
            "type":"Services"
        }
    ],
    "sg:phone":"+1 912 537 9121",
    "sg:postcode":"30474",
    "sg:province":"GA",
    "sg:tags":[
        "commercial",
        "design"
    ],
    "wof:name":"Creation Barbara",
    "wof:placetype":"venue"
},
  "geometry": {"coordinates":[-82.404325,32.226588],"type":"Point"}
}