{
  "type": "Feature",
  "properties": {
    "iso:country":"US",
    "sg:address":"2217 Irvindale Dr",
    "sg:city":"Atlanta",
    "sg:classifiers":[
        {
            "category":"Building & Trades",
            "subcategory":"Locksmith",
            "type":"Services"
        }
    ],
    "sg:phone":"+1 800 890 4662",
    "sg:postcode":"30341",
    "sg:province":"GA",
    "sg:tags":[
        "key"
    ],
    "wof:name":"24 Hour 7 Day Emergency Locksmith",
    "wof:placetype":"venue"
},
  "geometry": {"coordinates":[-84.29664200000001,33.896785],"type":"Point"}
}