{
  "type": "Feature",
  "properties": {
    "addr:full":"800 Veterans Memorial Pkwy SW Mableton GA 30126",
    "addr:housenumber":"800",
    "addr:postcode":"30126",
    "addr:street":"Veterans Memorial Pkwy Sw",
    "iso:country":"US",
    "sg:address":"800 Veterans Memorial Pkwy SW",
    "sg:city":"Mableton",
    "sg:classifiers":[
        {
            "category":"Manufacturing",
            "subcategory":"Tools & Machinery",
            "type":"Manufacturing & Wholesale Goods"
        }
    ],
    "sg:phone":"+1 770 948 8394",
    "sg:postcode":"30126",
    "sg:province":"GA",
    "sg:tags":[
        "measuring",
        "instrument",
        "electrical",
        "mfg"
    ],
    "wof:name":"Streamline Multimedia",
    "wof:placetype":"venue"
},
  "geometry": {"coordinates":[-84.580033,33.818866],"type":"Point"}
}