{
  "type": "Feature",
  "properties": {
    "addr:full":"10904 Crabapple Rd Roswell GA 30075",
    "addr:housenumber":"10904",
    "addr:postcode":"30075",
    "addr:street":"Crabapple Rd",
    "iso:country":"US",
    "sg:address":"10904 Crabapple Rd",
    "sg:city":"Roswell",
    "sg:classifiers":[
        {
            "category":"Organizations",
            "subcategory":"Community Association",
            "type":"Services"
        }
    ],
    "sg:phone":"+1 770 998 3333",
    "sg:postcode":"30075",
    "sg:province":"GA",
    "wof:name":"Canterbury Woods Comm Assn",
    "wof:placetype":"venue"
},
  "geometry": {"coordinates":[-84.36116699999999,34.046254],"type":"Point"}
}