{
  "type": "Feature",
  "properties": {
    "iso:country":"US",
    "sg:address":"528 Saltlick Trce",
    "sg:city":"Peachtree City",
    "sg:classifiers":[
        {
            "category":"Manufacturing",
            "subcategory":"Lumber",
            "type":"Manufacturing & Wholesale Goods"
        }
    ],
    "sg:phone":"+1 770 487 6518",
    "sg:postcode":"30269",
    "sg:province":"GA",
    "sg:tags":[
        "hardwood",
        "mill"
    ],
    "wof:name":"Parks Upholstery",
    "wof:placetype":"venue"
},
  "geometry": {"coordinates":[-84.557508,33.402758],"type":"Point"}
}