{
  "type": "Feature",
  "properties": {
    "addr:full":"163 N Jackson St Athens GA 30601",
    "addr:housenumber":"163",
    "addr:postcode":"30601",
    "addr:street":"N Jackson St",
    "iso:country":"US",
    "sg:address":"163 N Jackson St",
    "sg:city":"Athens",
    "sg:classifiers":[
        {
            "category":"Professional",
            "type":"Services"
        }
    ],
    "sg:phone":"+1 706 559 7500",
    "sg:postcode":"30601",
    "sg:province":"GA",
    "wof:name":"Gasworks Inc",
    "wof:placetype":"venue"
},
  "geometry": {"coordinates":[-83.374431,33.958215],"type":"Point"}
}