{
  "type": "Feature",
  "properties": {
    "iso:country":"US",
    "sg:address":"768 Grant St",
    "sg:city":"Savannah",
    "sg:classifiers":[
        {
            "category":"Education",
            "subcategory":"School",
            "type":"Public Place"
        }
    ],
    "sg:phone":"+1 912 201 5235",
    "sg:postcode":"31401",
    "sg:province":"GA",
    "sg:tags":[
        "middle"
    ],
    "sg:website":"http://www.savannah.chatham.k12.ga.us",
    "wof:name":"Hubert Middle School",
    "wof:placetype":"venue"
},
  "geometry": {"coordinates":[-81.084975,32.064946],"type":"Point"}
}