{
  "type": "Feature",
  "properties": {
    "iso:country":"US",
    "sg:address":"1702 Will Lewis Rd",
    "sg:city":"Pearson",
    "sg:classifiers":[
        {
            "category":"Place Of Worship",
            "subcategory":"Church",
            "type":"Public Place"
        },
        {
            "category":"Place Of Worship",
            "type":"Public Place"
        }
    ],
    "sg:phone":"+1 912 422 3286",
    "sg:postcode":"31642",
    "sg:province":"GA",
    "sg:tags":[
        "churches-baptist-general",
        "churches-baptist"
    ],
    "wof:name":"Ozias Freewill Baptist Ch",
    "wof:placetype":"venue"
},
  "geometry": {"coordinates":[-82.93035,31.34549],"type":"Point"}
}