{
  "type": "Feature",
  "properties": {
    "iso:country":"US",
    "sg:address":"2066 Old Savannah Rd",
    "sg:city":"Augusta",
    "sg:classifiers":[
        {
            "category":"Wholesale",
            "subcategory":"Farm Supplies",
            "type":"Manufacturing & Wholesale Goods"
        }
    ],
    "sg:phone":"+1 706 724 4704",
    "sg:postcode":"30901",
    "sg:province":"GA",
    "wof:name":"Daniel Feed & Seed Co Inc",
    "wof:placetype":"venue"
},
  "geometry": {"coordinates":[-81.996302,33.4412],"type":"Point"}
}