{
  "type": "Feature",
  "properties": {
    "addr:full":"3717 Washington Rd Augusta GA 30809",
    "addr:housenumber":"3717",
    "addr:postcode":"30809",
    "addr:street":"Washington Rd",
    "iso:country":"US",
    "sg:address":"3717 Washington Rd",
    "sg:city":"Augusta",
    "sg:classifiers":[
        {
            "category":"Home & Garden",
            "subcategory":"Building Materials",
            "type":"Retail Goods"
        }
    ],
    "sg:phone":"+1 706 863 6191",
    "sg:postcode":"30809",
    "sg:province":"GA",
    "sg:website":"www.maner.com",
    "wof:name":"Maner Builders Supply Co",
    "wof:placetype":"venue"
},
  "geometry": {"coordinates":[-82.086124,33.513159],"type":"Point"}
}