{
  "type": "Feature",
  "properties": {
    "iso:country":"US",
    "sg:address":"3424 Belmont Heights Dr",
    "sg:city":"Gainesville",
    "sg:classifiers":[
        {
            "category":"Restaurant",
            "type":"Food & Drink"
        }
    ],
    "sg:phone":"+1 678 450 0136",
    "sg:postcode":"30507",
    "sg:province":"GA",
    "wof:name":"Flama",
    "wof:placetype":"venue"
},
  "geometry": {"coordinates":[-83.764933,34.18533],"type":"Point"}
}