{
  "type": "Feature",
  "properties": {
    "addr:full":"163 Baker St NE Atlanta GA 30308",
    "addr:housenumber":"163",
    "addr:postcode":"30308",
    "addr:street":"Baker St Ne",
    "iso:country":"US",
    "sg:address":"163 Baker St NE",
    "sg:city":"Atlanta",
    "sg:classifiers":[
        {
            "category":"Building & Trades",
            "subcategory":"Locksmith",
            "type":"Services"
        }
    ],
    "sg:phone":"+1 404 682 9705",
    "sg:postcode":"30308",
    "sg:province":"GA",
    "sg:tags":[
        "key"
    ],
    "wof:name":"0 Alwayes 1 24 A Locksmith",
    "wof:placetype":"venue"
},
  "geometry": {"coordinates":[-84.38302,33.762059],"type":"Point"}
}