{
  "type": "Feature",
  "properties": {
    "iso:country":"US",
    "sg:address":"1405 Hillside Pl SE",
    "sg:city":"Conyers",
    "sg:classifiers":[
        {
            "category":"Manufacturing",
            "subcategory":"Retail Goods",
            "type":"Manufacturing & Wholesale Goods"
        }
    ],
    "sg:phone":"+1 770 761 9525",
    "sg:postcode":"30094",
    "sg:province":"GA",
    "sg:tags":[
        "product",
        "mfg"
    ],
    "wof:name":"Mc Crossing Industries Inc",
    "wof:placetype":"venue"
},
  "geometry": {"coordinates":[-84.03174199999999,33.619138],"type":"Point"}
}