{
  "type": "Feature",
  "properties": {
    "addr:full":"4241 Loch Highland Pkwy Roswell GA 30075",
    "addr:housenumber":"4241",
    "addr:postcode":"30075",
    "addr:street":"Loch Highland Pkwy",
    "iso:country":"US",
    "sg:address":"4241 Loch Highland Pkwy",
    "sg:city":"Roswell",
    "sg:classifiers":[
        {
            "category":"Shopping",
            "subcategory":"Books",
            "type":"Retail Goods"
        }
    ],
    "sg:phone":"+1 770 587 1264",
    "sg:postcode":"30075",
    "sg:province":"GA",
    "wof:name":"Grampas Create A Book",
    "wof:placetype":"venue"
},
  "geometry": {"coordinates":[-84.428718,34.051041],"type":"Point"}
}