{
  "type": "Feature",
  "properties": {
    "iso:country":"US",
    "sg:address":"5920 Roswell Rd",
    "sg:city":"Atlanta",
    "sg:classifiers":[
        {
            "category":"Retail",
            "subcategory":"Repair Shop",
            "type":"Services"
        }
    ],
    "sg:phone":"+1 678 806 0471",
    "sg:postcode":"30328",
    "sg:province":"GA",
    "wof:name":"Emergency Locksmith",
    "wof:placetype":"venue"
},
  "geometry": {"coordinates":[-84.379009,33.918016],"type":"Point"}
}