{
  "type": "Feature",
  "properties": {
    "addr:full":"111 S Jackson St Americus GA 31709",
    "addr:housenumber":"111",
    "addr:postcode":"31709",
    "addr:street":"S Jackson St",
    "iso:country":"US",
    "sg:address":"111 S Jackson St",
    "sg:city":"Americus",
    "sg:classifiers":[
        {
            "category":"Restaurant",
            "type":"Food & Drink"
        }
    ],
    "sg:phone":"+1 229 924 6846",
    "sg:postcode":"31709",
    "sg:province":"GA",
    "sg:tags":[
        "eating",
        "caterer"
    ],
    "wof:name":"Cousins Catering Inc",
    "wof:placetype":"venue"
},
  "geometry": {"coordinates":[-84.23389299999999,32.072038],"type":"Point"}
}