{
  "type": "Feature",
  "properties": {
    "iso:country":"US",
    "sg:address":"2 Lee St",
    "sg:city":"Newnan",
    "sg:classifiers":[
        {
            "category":"Professional",
            "subcategory":"Advertising",
            "type":"Services"
        }
    ],
    "sg:phone":"+1 770 304 1881",
    "sg:postcode":"30263",
    "sg:province":"GA",
    "sg:tags":[
        "guide"
    ],
    "wof:name":"Yellow Book USA",
    "wof:placetype":"venue"
},
  "geometry": {"coordinates":[-84.79923100000001,33.37746],"type":"Point"}
}