{
  "type": "Feature",
  "properties": {
    "iso:country":"US",
    "sg:address":"1205 W Walnut Ave",
    "sg:city":"Dalton",
    "sg:classifiers":[
        {
            "category":"Restaurant",
            "type":"Food & Drink"
        }
    ],
    "sg:menulink":"http://www.allmenus.com/ga/dalton/246446-garcias/menu/",
    "sg:phone":"+1 706 529 6855",
    "sg:postcode":"30720",
    "sg:province":"GA",
    "sg:tags":[
        "mexican"
    ],
    "wof:name":"Garcia's",
    "wof:placetype":"venue"
},
  "geometry": {"coordinates":[-84.986949,34.758746],"type":"Point"}
}