{
  "type": "Feature",
  "properties": {
    "iso:country":"US",
    "sg:address":"1085 Katie Kerr Dr",
    "sg:city":"Decatur",
    "sg:classifiers":[
        {
            "category":"Professional",
            "type":"Services"
        }
    ],
    "sg:phone":"+1 404 405 5900",
    "sg:postcode":"30030",
    "sg:province":"GA",
    "sg:tags":[
        "establishment"
    ],
    "wof:name":"Careertalk",
    "wof:placetype":"venue"
},
  "geometry": {"coordinates":[-84.2778,33.763073],"type":"Point"}
}