{
  "type": "Feature",
  "properties": {
    "addr:full":"5871 Fairburn Rd Douglasville GA 30134",
    "addr:housenumber":"5871",
    "addr:postcode":"30134",
    "addr:street":"Fairburn Rd",
    "iso:country":"US",
    "sg:address":"5871 Fairburn Rd",
    "sg:city":"Douglasville",
    "sg:classifiers":[
        {
            "category":"Banks & Credit Unions",
            "subcategory":"Bank",
            "type":"Services"
        }
    ],
    "sg:phone":"+1 770 942 2505",
    "sg:postcode":"30134",
    "sg:province":"GA",
    "sg:tags":[
        "commercial"
    ],
    "wof:name":"Regions Bank",
    "wof:placetype":"venue"
},
  "geometry": {"coordinates":[-84.737742,33.750731],"type":"Point"}
}