{
  "type": "Feature",
  "properties": {
    "addr:full":"2611 Moody Rd Warner Robins GA 31088",
    "addr:housenumber":"2611",
    "addr:postcode":"31088",
    "addr:street":"Moody Rd",
    "iso:country":"US",
    "sg:address":"2611 Moody Rd",
    "sg:city":"Warner Robins",
    "sg:classifiers":[
        {
            "category":"Health Services",
            "subcategory":"Doctor",
            "type":"Services"
        }
    ],
    "sg:phone":"+1 478 975 9648",
    "sg:postcode":"31088",
    "sg:province":"GA",
    "sg:tags":[
        "clinic"
    ],
    "wof:name":"Vizzini Chiropractic Clinic",
    "wof:placetype":"venue"
},
  "geometry": {"coordinates":[-83.62378,32.573842],"type":"Point"}
}