{
  "type": "Feature",
  "properties": {
    "addr:full":"2900 George Busbee Pkwy NW Kennesaw GA 30144",
    "addr:housenumber":"2900",
    "addr:postcode":"30144",
    "addr:street":"George Busbee Pkwy Nw",
    "iso:country":"US",
    "sg:address":"2900 George Busbee Pkwy NW",
    "sg:city":"Kennesaw",
    "sg:classifiers":[
        {
            "category":"Travel",
            "subcategory":"Hotels & Motels",
            "type":"Entertainment"
        }
    ],
    "sg:phone":"+1 800 424 6423",
    "sg:postcode":"30144",
    "sg:province":"GA",
    "sg:website":"http://www.suburbanhotels.com/hotel-kennesaw-georgia-GA556?promo=yplocal",
    "wof:name":"Suburban Extended Stay Kennesaw",
    "wof:placetype":"venue"
},
  "geometry": {"coordinates":[-84.567627,34.026509],"type":"Point"}
}