{
  "type": "Feature",
  "properties": {
    "iso:country":"US",
    "sg:address":"2403 US Hwy 19 NE",
    "sg:city":"Pelham",
    "sg:classifiers":[
        {
            "category":"Freight",
            "type":"Transportation"
        }
    ],
    "sg:phone":"+1 229 294 2199",
    "sg:postcode":"31779",
    "sg:province":"GA",
    "sg:tags":[
        "warehouse",
        "self",
        "storage"
    ],
    "wof:name":"Pine Cliff Planters Wrhse 2",
    "wof:placetype":"venue"
},
  "geometry": {"coordinates":[-84.140749,31.135297],"type":"Point"}
}