{
  "type": "Feature",
  "properties": {
    "addr:full":"36 Terry Ct Athens GA 30607",
    "addr:housenumber":"36",
    "addr:postcode":"30607",
    "addr:street":"Terry Ct",
    "iso:country":"US",
    "sg:address":"36 Terry Ct",
    "sg:city":"Athens",
    "sg:classifiers":[
        {
            "category":"Retail",
            "subcategory":"Auto Repair",
            "type":"Services"
        }
    ],
    "sg:phone":"+1 706 227 2005",
    "sg:postcode":"30607",
    "sg:province":"GA",
    "sg:tags":[
        "general"
    ],
    "wof:name":"Smokeys",
    "wof:placetype":"venue"
},
  "geometry": {"coordinates":[-83.479793,34.003217],"type":"Point"}
}