{
  "type": "Feature",
  "properties": {
    "iso:country":"US",
    "sg:address":"3956 Due West Rd NW",
    "sg:city":"Marietta",
    "sg:classifiers":[
        {
            "category":"Organizations",
            "subcategory":"Religious Organization",
            "type":"Services"
        }
    ],
    "sg:phone":"+1 770 427 3835",
    "sg:postcode":"30064",
    "sg:province":"GA",
    "sg:tags":[
        "church"
    ],
    "sg:website":"www.duewest.org",
    "wof:name":"Due West United Methodist Chr",
    "wof:placetype":"venue"
},
  "geometry": {"coordinates":[-84.669071,33.967271],"type":"Point"}
}