{
  "type": "Feature",
  "properties": {
    "addr:full":"525 Lawshe Rd Senoia GA 30276",
    "addr:housenumber":"525",
    "addr:postcode":"30276",
    "addr:street":"Lawshe Rd",
    "iso:country":"US",
    "sg:address":"525 Lawshe Rd",
    "sg:city":"Senoia",
    "sg:classifiers":[
        {
            "category":"Building & Trades",
            "subcategory":"Pest Control",
            "type":"Services"
        }
    ],
    "sg:phone":"+1 770 599 3999",
    "sg:postcode":"30276",
    "sg:province":"GA",
    "wof:name":"Abel Tru-Kil Pest Control",
    "wof:placetype":"venue"
},
  "geometry": {"coordinates":[-84.60803900000001,33.292808],"type":"Point"}
}