{
  "type": "Feature",
  "properties": {
    "addr:full":"1245 Washington Rd Thomson GA 30824",
    "addr:housenumber":"1245",
    "addr:postcode":"30824",
    "addr:street":"Washington Rd",
    "iso:country":"US",
    "sg:address":"1245 Washington Rd",
    "sg:city":"Thomson",
    "sg:classifiers":[
        {
            "category":"Food & Beverages",
            "subcategory":"Groceries & Convenience Stores",
            "type":"Retail Goods"
        }
    ],
    "sg:phone":"+1 706 595 6196",
    "sg:postcode":"30824",
    "sg:province":"GA",
    "sg:tags":[
        "supermarket",
        "chain"
    ],
    "wof:name":"Food Lion Store 496",
    "wof:placetype":"venue"
},
  "geometry": {"coordinates":[-82.504653,33.49004],"type":"Point"}
}