{
  "type": "Feature",
  "properties": {
    "iso:country":"US",
    "sg:address":"503 Grady St",
    "sg:city":"Blackshear",
    "sg:classifiers":[
        {
            "category":"Health Services",
            "subcategory":"Doctor",
            "type":"Services"
        }
    ],
    "sg:phone":"+1 912 287 0252",
    "sg:postcode":"31516",
    "sg:province":"GA",
    "sg:tags":[
        "physician",
        "surgeon"
    ],
    "wof:name":"Harold E Snyder MD",
    "wof:placetype":"venue"
},
  "geometry": {"coordinates":[-82.245925,31.309493],"type":"Point"}
}