{
  "type": "Feature",
  "properties": {
    "iso:country":"US",
    "sg:address":"2121 Fairburn Rd",
    "sg:city":"Douglasville",
    "sg:classifiers":[
        {
            "category":"Professional",
            "subcategory":"Accounting & Tax Preparation",
            "type":"Services"
        }
    ],
    "sg:phone":"+1 770 947 9252",
    "sg:postcode":"30135",
    "sg:province":"GA",
    "sg:tags":[
        "accountant"
    ],
    "wof:name":"All Accounting and Tax Services",
    "wof:placetype":"venue"
},
  "geometry": {"coordinates":[-84.701634,33.747643],"type":"Point"}
}