{
  "type": "Feature",
  "properties": {
    "addr:full":"859 Sandy Cross Rd Lexington GA 30648",
    "addr:housenumber":"859",
    "addr:postcode":"30648",
    "addr:street":"Sandy Cross Rd",
    "iso:country":"US",
    "sg:address":"859 Sandy Cross Rd",
    "sg:city":"Lexington",
    "sg:classifiers":[
        {
            "category":"Food & Beverages",
            "subcategory":"Groceries & Convenience Stores",
            "type":"Retail Goods"
        }
    ],
    "sg:phone":"+1 706 743 7767",
    "sg:postcode":"30648",
    "sg:province":"GA",
    "wof:name":"Jiffy Mart",
    "wof:placetype":"venue"
},
  "geometry": {"coordinates":[-83.061336,33.942942],"type":"Point"}
}