{
  "type": "Feature",
  "properties": {
    "addr:full":"2688 Rivers Edge Dr NE Atlanta GA 30324",
    "addr:housenumber":"2688",
    "addr:postcode":"30324",
    "addr:street":"Rivers Edge Dr Ne",
    "iso:country":"US",
    "sg:address":"2688 Rivers Edge Dr NE",
    "sg:city":"Atlanta",
    "sg:classifiers":[
        {
            "category":"Professional",
            "subcategory":"Management & Consulting",
            "type":"Services"
        }
    ],
    "sg:phone":"+1 404 633 9988",
    "sg:postcode":"30324",
    "sg:province":"GA",
    "sg:tags":[
        "consultant",
        "planning",
        "space",
        "facility"
    ],
    "wof:name":"Altered Spaces",
    "wof:placetype":"venue"
},
  "geometry": {"coordinates":[-84.348721,33.828028],"type":"Point"}
}