{
  "type": "Feature",
  "properties": {
    "iso:country":"US",
    "sg:address":"456 Page Ave NE",
    "sg:city":"Atlanta",
    "sg:classifiers":[
        {
            "category":"Education",
            "subcategory":"Vocational School",
            "type":"Public Place"
        }
    ],
    "sg:phone":"+1 404 373 1002",
    "sg:postcode":"30307",
    "sg:province":"GA",
    "sg:tags":[
        "training",
        "computer"
    ],
    "wof:name":"Envision It Inc",
    "wof:placetype":"venue"
},
  "geometry": {"coordinates":[-84.334231,33.765756],"type":"Point"}
}