{
  "type": "Feature",
  "properties": {
    "addr:full":"1240 Johnson Ferry Rd Marietta GA 30068",
    "addr:housenumber":"1240",
    "addr:postcode":"30068",
    "addr:street":"Johnson Ferry Rd",
    "iso:country":"US",
    "sg:address":"1240 Johnson Ferry Rd",
    "sg:city":"Marietta",
    "sg:classifiers":[
        {
            "category":"Health Services",
            "subcategory":"Clinic",
            "type":"Services"
        }
    ],
    "sg:phone":"+1 770 321 5657",
    "sg:postcode":"30068",
    "sg:province":"GA",
    "sg:tags":[
        "home"
    ],
    "wof:name":"American Pediatric Consultants",
    "wof:placetype":"venue"
},
  "geometry": {"coordinates":[-84.421761,33.979549],"type":"Point"}
}