{
  "type": "Feature",
  "properties": {
    "iso:country":"US",
    "sg:address":"5080 Hampton Farms Dr",
    "sg:city":"Marietta",
    "sg:classifiers":[
        {
            "category":"Real Estate",
            "subcategory":"Real Estate Agent",
            "type":"Services"
        }
    ],
    "sg:phone":"+1 770 578 6959",
    "sg:postcode":"30068",
    "sg:province":"GA",
    "wof:name":"Samuel Brown Jr",
    "wof:placetype":"venue"
},
  "geometry": {"coordinates":[-84.402669,33.955074],"type":"Point"}
}