{
  "type": "Feature",
  "properties": {
    "iso:country":"US",
    "sg:address":"4702 Cromwell Ct",
    "sg:city":"Acworth",
    "sg:classifiers":[
        {
            "category":"Shopping",
            "subcategory":"Clothing, Apparel, & Fashions",
            "type":"Retail Goods"
        }
    ],
    "sg:phone":"+1 770 590 7995",
    "sg:postcode":"30102",
    "sg:province":"GA",
    "wof:name":"Chess Holding Company Inc",
    "wof:placetype":"venue"
},
  "geometry": {"coordinates":[-84.578304,34.064775],"type":"Point"}
}