{
  "type": "Feature",
  "properties": {
    "iso:country":"US",
    "sg:address":"1115 Mount Zion Rd",
    "sg:city":"Morrow",
    "sg:classifiers":[
        {
            "category":"Health Services",
            "subcategory":"Hospital",
            "type":"Services"
        }
    ],
    "sg:phone":"+1 770 968 1911",
    "sg:postcode":"30260",
    "sg:province":"GA",
    "sg:tags":[
        "ambulance"
    ],
    "wof:name":"Metro South EMS",
    "wof:placetype":"venue"
},
  "geometry": {"coordinates":[-84.354688,33.571928],"type":"Point"}
}