{
  "type": "Feature",
  "properties": {
    "iso:country":"US",
    "sg:address":"979 Rockbridge Way NW",
    "sg:city":"Norcross",
    "sg:classifiers":[
        {
            "category":"Professional",
            "subcategory":"Business Services",
            "type":"Services"
        }
    ],
    "sg:phone":"+1 770 925 8231",
    "sg:postcode":"30093",
    "sg:province":"GA",
    "wof:name":"Radiant Business Technology",
    "wof:placetype":"venue"
},
  "geometry": {"coordinates":[-84.184951,33.89329],"type":"Point"}
}