{
  "type": "Feature",
  "properties": {
    "addr:full":"4125 US Hwy 78 Lilburn GA 30047",
    "addr:housenumber":"4125",
    "addr:postcode":"30047",
    "addr:street":"Us Hwy 78",
    "iso:country":"US",
    "sg:address":"4125 US Hwy 78",
    "sg:city":"Lilburn",
    "sg:classifiers":[
        {
            "category":"Retail",
            "subcategory":"Auto Repair",
            "type":"Services"
        }
    ],
    "sg:phone":"+1 770 979 0308",
    "sg:postcode":"30047",
    "sg:province":"GA",
    "sg:tags":[
        "tire",
        "performs",
        "general"
    ],
    "wof:name":"Big 10 Tires 61",
    "wof:placetype":"venue"
},
  "geometry": {"coordinates":[-84.071513,33.836623],"type":"Point"}
}