{
  "type": "Feature",
  "properties": {
    "iso:country":"US",
    "sg:address":"7160 Delta Cir",
    "sg:city":"Austell",
    "sg:classifiers":[
        {
            "category":"Manufacturing",
            "subcategory":"Glass & Minerals",
            "type":"Manufacturing & Wholesale Goods"
        }
    ],
    "sg:phone":"+1 770 941 4700",
    "sg:postcode":"30168",
    "sg:province":"GA",
    "sg:tags":[
        "flat",
        "product",
        "mfg"
    ],
    "wof:name":"Tempered Glass Inc",
    "wof:placetype":"venue"
},
  "geometry": {"coordinates":[-84.542569,33.775138],"type":"Point"}
}