{
  "type": "Feature",
  "properties": {
    "addr:full":"4693 N Marble Top Rd Chickamauga GA 30707",
    "addr:housenumber":"4693",
    "addr:postcode":"30707",
    "addr:street":"N Marble Top Rd",
    "iso:country":"US",
    "sg:address":"4693 N Marble Top Rd",
    "sg:city":"Chickamauga",
    "sg:classifiers":[
        {
            "category":"Food & Beverages",
            "subcategory":"Groceries & Convenience Stores",
            "type":"Retail Goods"
        }
    ],
    "sg:phone":"+1 706 375 6913",
    "sg:postcode":"30707",
    "sg:province":"GA",
    "wof:name":"EZ Stop",
    "wof:placetype":"venue"
},
  "geometry": {"coordinates":[-85.358656,34.844481],"type":"Point"}
}