{
  "type": "Feature",
  "properties": {
    "addr:full":"55 Whitcher St NE Marietta GA 30060",
    "addr:housenumber":"55",
    "addr:postcode":"30060",
    "addr:street":"Whitcher St Ne",
    "iso:country":"US",
    "sg:address":"55 Whitcher St NE",
    "sg:city":"Marietta",
    "sg:classifiers":[
        {
            "category":"Health Services",
            "subcategory":"Doctor",
            "type":"Services"
        }
    ],
    "sg:phone":"+1 770 429 0083",
    "sg:postcode":"30060",
    "sg:province":"GA",
    "wof:name":"Sheftel Thomas G MD",
    "wof:placetype":"venue"
},
  "geometry": {"coordinates":[-84.551438,33.96748],"type":"Point"}
}