{
  "type": "Feature",
  "properties": {
    "addr:full":"124 W Solomon St Griffin GA 30223",
    "addr:housenumber":"124",
    "addr:postcode":"30223",
    "addr:street":"W Solomon St",
    "iso:country":"US",
    "sg:address":"124 W Solomon St",
    "sg:city":"Griffin",
    "sg:classifiers":[
        {
            "category":"Shopping",
            "subcategory":"Jewelry",
            "type":"Retail Goods"
        }
    ],
    "sg:phone":"+1 770 227 2595",
    "sg:postcode":"30223",
    "sg:province":"GA",
    "sg:tags":[
        "repair",
        "watch"
    ],
    "wof:name":"Sharps Jewelers",
    "wof:placetype":"venue"
},
  "geometry": {"coordinates":[-84.264216,33.248601],"type":"Point"}
}