{
  "type": "Feature",
  "properties": {
    "iso:country":"US",
    "sg:address":"2207 Ga Highway 313 Sylv",
    "sg:city":"Sylvester",
    "sg:classifiers":[
        {
            "category":"Professional",
            "subcategory":"Accounting & Tax Preparation",
            "type":"Services"
        }
    ],
    "sg:phone":"+1 229 776 7628",
    "sg:postcode":"31791",
    "sg:province":"GA",
    "sg:tags":[
        "payroll",
        "bookkeeping",
        "return",
        "billing",
        "preparation-business"
    ],
    "wof:name":"Davis Tax Service",
    "wof:placetype":"venue"
},
  "geometry": {"coordinates":[-83.84799,31.5586],"type":"Point"}
}