{
  "type": "Feature",
  "properties": {
    "addr:full":"160 Riverbend Dr Mcdonough GA 30252",
    "addr:housenumber":"160",
    "addr:postcode":"30252",
    "addr:street":"Riverbend Dr",
    "iso:country":"US",
    "sg:address":"160 Riverbend Dr",
    "sg:city":"Mcdonough",
    "sg:classifiers":[
        {
            "category":"Manufacturing",
            "subcategory":"Tools & Machinery",
            "type":"Manufacturing & Wholesale Goods"
        },
        {
            "category":"Industrial Area",
            "type":"Public Place"
        }
    ],
    "sg:phone":"+1 770 957 5236",
    "sg:postcode":"30252",
    "sg:province":"GA",
    "sg:tags":[
        "repair",
        "equipment-repairing",
        "machinery-rebuild"
    ],
    "wof:name":"Snack Attack Snack Machines",
    "wof:placetype":"venue"
},
  "geometry": {"coordinates":[-84.06174,33.532148],"type":"Point"}
}