{
  "type": "Feature",
  "properties": {
    "iso:country":"US",
    "sg:address":"1101 Cherokee Dr",
    "sg:city":"Waycross",
    "sg:classifiers":[
        {
            "category":"Professional",
            "subcategory":"Engineering",
            "type":"Services"
        }
    ],
    "sg:phone":"+1 912 285 4452",
    "sg:postcode":"31501",
    "sg:province":"GA",
    "sg:tags":[
        "engineer"
    ],
    "wof:name":"Mayes Sudderth & Etheredge Inc",
    "wof:placetype":"venue"
},
  "geometry": {"coordinates":[-82.34098899999999,31.218199],"type":"Point"}
}