{
  "type": "Feature",
  "properties": {
    "iso:country":"US",
    "sg:address":"958 Redfield Way",
    "sg:city":"Jasper",
    "sg:classifiers":[
        {
            "category":"Professional",
            "type":"Services"
        }
    ],
    "sg:phone":"+1 706 692 9145",
    "sg:postcode":"30143",
    "sg:province":"GA",
    "wof:name":"Dka Services",
    "wof:placetype":"venue"
},
  "geometry": {"coordinates":[-84.442893,34.495108],"type":"Point"}
}