{
  "type": "Feature",
  "properties": {
    "iso:country":"US",
    "sg:address":"811 US Hwy 441",
    "sg:city":"Clayton",
    "sg:classifiers":[
        {
            "category":"Manufacturing",
            "subcategory":"Apparel",
            "type":"Manufacturing & Wholesale Goods"
        }
    ],
    "sg:phone":"+1 706 782 4241",
    "sg:postcode":"30525",
    "sg:province":"GA",
    "sg:tags":[
        "clothing",
        "outerwear",
        "mfg"
    ],
    "wof:name":"Don L Inc",
    "wof:placetype":"venue"
},
  "geometry": {"coordinates":[-83.40331399999999,34.86581],"type":"Point"}
}