{
  "type": "Feature",
  "properties": {
    "iso:country":"US",
    "sg:address":"428 Winn Ct",
    "sg:city":"Decatur",
    "sg:classifiers":[
        {
            "category":"Health Services",
            "subcategory":"Doctor",
            "type":"Services"
        }
    ],
    "sg:phone":"+1 404 292 3727",
    "sg:postcode":"30030",
    "sg:province":"GA",
    "sg:tags":[
        "physician",
        "surgeon"
    ],
    "wof:name":"Georgia Urology-De Kalb",
    "wof:placetype":"venue"
},
  "geometry": {"coordinates":[-84.277755,33.788263],"type":"Point"}
}