{
  "type": "Feature",
  "properties": {
    "addr:full":"240 Stone Mill Trl NE Atlanta GA 30328",
    "addr:housenumber":"240",
    "addr:postcode":"30328",
    "addr:street":"Stone Mill Trl Ne",
    "iso:country":"US",
    "sg:address":"240 Stone Mill Trl NE",
    "sg:city":"Atlanta",
    "sg:classifiers":[
        {
            "category":"Building & Trades",
            "subcategory":"Construction",
            "type":"Services"
        }
    ],
    "sg:phone":"+1 404 298 1656",
    "sg:postcode":"30328",
    "sg:province":"GA",
    "sg:tags":[
        "painter"
    ],
    "wof:name":"Ceiltech Acoustical Ceiling Coatings",
    "wof:placetype":"venue"
},
  "geometry": {"coordinates":[-84.38069900000001,33.940601],"type":"Point"}
}