{
  "type": "Feature",
  "properties": {
    "iso:country":"US",
    "sg:address":"1353 Cleveland Avenue",
    "sg:city":"Atlanta",
    "sg:classifiers":[
        {
            "category":"Professional",
            "subcategory":"Lawyer & Legal Services",
            "type":"Services"
        }
    ],
    "sg:phone":"+1 404 768 3963",
    "sg:postcode":"30344",
    "sg:province":"GA",
    "wof:name":"Washington Law Firm",
    "wof:placetype":"venue"
},
  "geometry": {"coordinates":[-84.432849,33.679325],"type":"Point"}
}