{
  "type": "Feature",
  "properties": {
    "addr:full":"803 Ridgeview Dr SW Lilburn GA 30047",
    "addr:housenumber":"803",
    "addr:postcode":"30047",
    "addr:street":"Ridgeview Dr Sw",
    "iso:country":"US",
    "sg:address":"803 Ridgeview Dr SW",
    "sg:city":"Lilburn",
    "sg:classifiers":[
        {
            "category":"Wholesale",
            "subcategory":"Medical Equipment & Supplies",
            "type":"Manufacturing & Wholesale Goods"
        }
    ],
    "sg:phone":"+1 770 381 1327",
    "sg:postcode":"30047",
    "sg:province":"GA",
    "wof:name":"Thomas V McAbee",
    "wof:placetype":"venue"
},
  "geometry": {"coordinates":[-84.095195,33.875825],"type":"Point"}
}