{
  "type": "Feature",
  "properties": {
    "iso:country":"US",
    "sg:address":"140 Vann St NE Ste 420",
    "sg:city":"Marietta",
    "sg:classifiers":[
        {
            "category":"Professional",
            "subcategory":"Lawyer & Legal Services",
            "type":"Services"
        }
    ],
    "sg:phone":"+1 770 218 0104",
    "sg:postcode":"30060",
    "sg:province":"GA",
    "wof:name":"McKee & Samuels Llc",
    "wof:placetype":"venue"
},
  "geometry": {"coordinates":[-84.549797,33.972099],"type":"Point"}
}