{
  "type": "Feature",
  "properties": {
    "addr:full":"1161 Pleasant Hill Rd Ellijay GA 30540",
    "addr:housenumber":"1161",
    "addr:postcode":"30540",
    "addr:street":"Pleasant Hill Rd",
    "iso:country":"US",
    "sg:address":"1161 Pleasant Hill Rd",
    "sg:city":"Ellijay",
    "sg:classifiers":[
        {
            "category":"Organizations",
            "subcategory":"Religious Organization",
            "type":"Services"
        }
    ],
    "sg:phone":"+1 706 635 3003",
    "sg:postcode":"30540",
    "sg:province":"GA",
    "wof:name":"Pleasant Hill Baptist Church",
    "wof:placetype":"venue"
},
  "geometry": {"coordinates":[-84.602152,34.753399],"type":"Point"}
}