{
  "type": "Feature",
  "properties": {
    "iso:country":"US",
    "sg:address":"3051 US Hwy 82 E",
    "sg:city":"Sumner",
    "sg:classifiers":[
        {
            "category":"Home & Garden",
            "subcategory":"Mobile Homes",
            "type":"Retail Goods"
        }
    ],
    "sg:phone":"+1 229 776 5700",
    "sg:postcode":"31789",
    "sg:province":"GA",
    "wof:name":"Southern Recovery LLC",
    "wof:placetype":"venue"
},
  "geometry": {"coordinates":[-83.722981,31.503851],"type":"Point"}
}