{
  "type": "Feature",
  "properties": {
    "iso:country":"US",
    "sg:address":"6526 Pleasant Valley Dr",
    "sg:city":"Morrow",
    "sg:classifiers":[
        {
            "category":"Retail",
            "subcategory":"Animal Services",
            "type":"Services"
        }
    ],
    "sg:phone":"+1 770 968 6611",
    "sg:postcode":"30260",
    "sg:province":"GA",
    "sg:tags":[
        "pet",
        "exercising",
        "sitting"
    ],
    "sg:website":"http://www.thepetshepherd.com",
    "wof:name":"Pet Shepherd Pet Sitting",
    "wof:placetype":"venue"
},
  "geometry": {"coordinates":[-84.327455,33.576934],"type":"Point"}
}