{
  "type": "Feature",
  "properties": {
    "iso:country":"US",
    "sg:address":"1927 US Hwy 441",
    "sg:city":"Dublin",
    "sg:classifiers":[
        {
            "category":"Home & Garden",
            "subcategory":"Furniture",
            "type":"Retail Goods"
        }
    ],
    "sg:phone":"+1 478 275 3144",
    "sg:postcode":"31021",
    "sg:province":"GA",
    "sg:website":"www.badcock.com",
    "wof:name":"Badcock Home Furniture & More",
    "wof:placetype":"venue"
},
  "geometry": {"coordinates":[-82.92326799999999,32.514069],"type":"Point"}
}