{
  "type": "Feature",
  "properties": {
    "addr:full":"720 Orchard Ct Atlanta GA 30328",
    "addr:housenumber":"720",
    "addr:postcode":"30328",
    "addr:street":"Orchard Ct",
    "iso:country":"US",
    "sg:address":"720 Orchard Ct",
    "sg:city":"Atlanta",
    "sg:classifiers":[
        {
            "category":"Utilities",
            "subcategory":"Telephone",
            "type":"Services"
        }
    ],
    "sg:phone":"+1 404 223 0060",
    "sg:postcode":"30328",
    "sg:province":"GA",
    "sg:tags":[
        "communications"
    ],
    "wof:name":"Atyourservercom Inc",
    "wof:placetype":"venue"
},
  "geometry": {"coordinates":[-84.353556,33.940267],"type":"Point"}
}