{
  "type": "Feature",
  "properties": {
    "addr:full":"6030 Bethelview Rd Cumming GA 30040",
    "addr:housenumber":"6030",
    "addr:postcode":"30040",
    "addr:street":"Bethelview Rd",
    "iso:country":"US",
    "sg:address":"6030 Bethelview Rd",
    "sg:city":"Cumming",
    "sg:classifiers":[
        {
            "category":"Wholesale",
            "subcategory":"Groceries",
            "type":"Manufacturing & Wholesale Goods"
        }
    ],
    "sg:phone":"+1 770 887 0807",
    "sg:postcode":"30040",
    "sg:province":"GA",
    "sg:tags":[
        "general"
    ],
    "wof:name":"International Gourmet Products",
    "wof:placetype":"venue"
},
  "geometry": {"coordinates":[-84.174559,34.161651],"type":"Point"}
}