{
  "type": "Feature",
  "properties": {
    "addr:full":"1101 Clark Ave Albany GA 31705",
    "addr:housenumber":"1101",
    "addr:postcode":"31705",
    "addr:street":"Clark Ave",
    "iso:country":"US",
    "sg:address":"1101 Clark Ave",
    "sg:city":"Albany",
    "sg:classifiers":[
        {
            "category":"Personal",
            "subcategory":"Beauty Salon",
            "type":"Services"
        }
    ],
    "sg:phone":"+1 229 483 9939",
    "sg:postcode":"31705",
    "sg:province":"GA",
    "wof:name":"Barbara Brooks Salon",
    "wof:placetype":"venue"
},
  "geometry": {"coordinates":[-84.126789,31.579946],"type":"Point"}
}