{
  "type": "Feature",
  "properties": {
    "addr:full":"1645 Williams Dr Marietta GA 30066",
    "addr:housenumber":"1645",
    "addr:postcode":"30066",
    "addr:street":"Williams Dr",
    "iso:country":"US",
    "sg:address":"1645 Williams Dr",
    "sg:city":"Marietta",
    "sg:classifiers":[
        {
            "category":"Building & Trades",
            "subcategory":"Landscaping Services",
            "type":"Services"
        }
    ],
    "sg:phone":"+1 770 590 0630",
    "sg:postcode":"30066",
    "sg:province":"GA",
    "sg:tags":[
        "landscape",
        "maintenance",
        "contractor"
    ],
    "wof:name":"Brickman Group Ltd",
    "wof:placetype":"venue"
},
  "geometry": {"coordinates":[-84.53219199999999,33.997546],"type":"Point"}
}