{
  "type": "Feature",
  "properties": {
    "iso:country":"US",
    "sg:address":"150 Henry Burson Ave",
    "sg:city":"Carrollton",
    "sg:classifiers":[
        {
            "category":"Health Services",
            "subcategory":"Medical Lab",
            "type":"Services"
        }
    ],
    "sg:phone":"+1 770 836 1913",
    "sg:postcode":"30117",
    "sg:province":"GA",
    "sg:tags":[
        "laboratory"
    ],
    "wof:name":"Speech & Language Pathology",
    "wof:placetype":"venue"
},
  "geometry": {"coordinates":[-85.07172,33.569556],"type":"Point"}
}