{
  "type": "Feature",
  "properties": {
    "iso:country":"US",
    "sg:address":"579 Fernstone Trl",
    "sg:city":"Lawrenceville",
    "sg:classifiers":[
        {
            "category":"Professional",
            "type":"Services"
        }
    ],
    "sg:phone":"+1 770 237 8697",
    "sg:postcode":"30045",
    "sg:province":"GA",
    "wof:name":"Student Opportunity Netwrk Inc",
    "wof:placetype":"venue"
},
  "geometry": {"coordinates":[-83.992029,33.926697],"type":"Point"}
}