{
  "type": "Feature",
  "properties": {
    "iso:country":"US",
    "sg:address":"1034 Dixie St",
    "sg:city":"Carrollton",
    "sg:classifiers":[
        {
            "category":"Banks & Credit Unions",
            "subcategory":"Bank",
            "type":"Services"
        }
    ],
    "sg:phone":"+1 770 830 6355",
    "sg:postcode":"30117",
    "sg:province":"GA",
    "wof:name":"Associated Credit Union",
    "wof:placetype":"venue"
},
  "geometry": {"coordinates":[-85.07266,33.564381],"type":"Point"}
}