{
  "type": "Feature",
  "properties": {
    "iso:country":"US",
    "sg:address":"5148 Augusta Rd",
    "sg:city":"Garden City",
    "sg:classifiers":[
        {
            "category":"Shopping",
            "subcategory":"Used Merchandise",
            "type":"Retail Goods"
        },
        {
            "category":"Shopping",
            "subcategory":"Jewelry",
            "type":"Retail Goods"
        }
    ],
    "sg:phone":"+1 912 964 1744",
    "sg:postcode":"31408",
    "sg:province":"GA",
    "sg:tags":[
        "pawnshop",
        "jeweler"
    ],
    "wof:name":"Cash America Pawn 481",
    "wof:placetype":"venue"
},
  "geometry": {"coordinates":[-81.164382,32.114343],"type":"Point"}
}