{
  "type": "Feature",
  "properties": {
    "iso:country":"US",
    "sg:address":"111 S Ralph St",
    "sg:city":"Claxton",
    "sg:classifiers":[
        {
            "category":"Professional",
            "type":"Services"
        }
    ],
    "sg:phone":"+1 912 739 8788",
    "sg:postcode":"30417",
    "sg:province":"GA",
    "sg:tags":[
        "establishment"
    ],
    "wof:name":"Nei Nei",
    "wof:placetype":"venue"
},
  "geometry": {"coordinates":[-81.914108,32.15854],"type":"Point"}
}