{
  "type": "Feature",
  "properties": {
    "addr:full":"53 Johnston Cir Palmetto GA 30268",
    "addr:housenumber":"53",
    "addr:postcode":"30268",
    "addr:street":"Johnston Cir",
    "iso:country":"US",
    "sg:address":"53 Johnston Cir",
    "sg:city":"Palmetto",
    "sg:classifiers":[
        {
            "category":"Home & Garden",
            "subcategory":"Building Materials",
            "type":"Retail Goods"
        },
        {
            "category":"Building & Trades",
            "subcategory":"Construction",
            "type":"Services"
        }
    ],
    "sg:phone":"+1 770 463 1448",
    "sg:postcode":"30268",
    "sg:province":"GA",
    "sg:tags":[
        "concrete",
        "staining",
        "contractor"
    ],
    "sg:website":"http://www.apecformwork.com",
    "wof:name":"Apec",
    "wof:placetype":"venue"
},
  "geometry": {"coordinates":[-84.669482,33.499771],"type":"Point"}
}