{
  "type": "Feature",
  "properties": {
    "iso:country":"US",
    "sg:address":"106 N College St",
    "sg:city":"Cedartown",
    "sg:classifiers":[
        {
            "category":"Retail",
            "subcategory":"Funeral Services",
            "type":"Services"
        }
    ],
    "sg:phone":"+1 770 748 1431",
    "sg:postcode":"30125",
    "sg:province":"GA",
    "sg:tags":[
        "director"
    ],
    "wof:name":"Gammage Funeral Home",
    "wof:placetype":"venue"
},
  "geometry": {"coordinates":[-85.256506,34.016818],"type":"Point"}
}