{
  "type": "Feature",
  "properties": {
    "addr:full":"1955 Bear Creek Rd Canon GA 30520",
    "addr:housenumber":"1955",
    "addr:postcode":"30520",
    "addr:street":"Bear Creek Rd",
    "iso:country":"US",
    "sg:address":"1955 Bear Creek Rd",
    "sg:city":"Canon",
    "sg:classifiers":[
        {
            "category":"Professional",
            "type":"Services"
        }
    ],
    "sg:phone":"+1 706 356 1101",
    "sg:postcode":"30520",
    "sg:province":"GA",
    "wof:name":"Joe W Addison",
    "wof:placetype":"venue"
},
  "geometry": {"coordinates":[-83.124426,34.406742],"type":"Point"}
}