{
  "type": "Feature",
  "properties": {
    "addr:full":"112 Krog St NE Atlanta GA 30307",
    "addr:housenumber":"112",
    "addr:postcode":"30307",
    "addr:street":"Krog St Ne",
    "iso:country":"US",
    "sg:address":"112 Krog St NE",
    "sg:city":"Atlanta",
    "sg:classifiers":[
        {
            "category":"Real Estate",
            "subcategory":"Architect",
            "type":"Services"
        }
    ],
    "sg:phone":"+1 404 223 1313",
    "sg:postcode":"30307",
    "sg:province":"GA",
    "sg:tags":[
        "architects'",
        "specification",
        "builders'",
        "construction",
        "architectural",
        "engineer"
    ],
    "sg:website":"http://www.taylor-architecture.com",
    "wof:name":"Taylor Architecture",
    "wof:placetype":"venue"
},
  "geometry": {"coordinates":[-84.364299,33.756665],"type":"Point"}
}