{
  "type": "Feature",
  "properties": {
    "addr:full":"5725 Buford Hwy NE Atlanta GA 30340",
    "addr:housenumber":"5725",
    "addr:postcode":"30340",
    "addr:street":"Buford Hwy Ne",
    "iso:country":"US",
    "sg:address":"5725 Buford Hwy NE",
    "sg:city":"Atlanta",
    "sg:classifiers":[
        {
            "category":"Communications",
            "subcategory":"Newspaper",
            "type":"Services"
        }
    ],
    "sg:phone":"+1 770 455 0880",
    "sg:postcode":"30340",
    "sg:province":"GA",
    "sg:tags":[
        "print",
        "medium"
    ],
    "sg:website":"www.atlantachinesenews.com",
    "wof:name":"Atlanta Chinese News",
    "wof:placetype":"venue"
},
  "geometry": {"coordinates":[-84.269116,33.906999],"type":"Point"}
}