{
  "type": "Feature",
  "properties": {
    "iso:country":"US",
    "sg:address":"9870 Tara Blvd",
    "sg:city":"Jonesboro",
    "sg:classifiers":[
        {
            "category":"Home & Garden",
            "subcategory":"Mobile Homes",
            "type":"Retail Goods"
        }
    ],
    "sg:phone":"+1 770 471 1674",
    "sg:postcode":"30236",
    "sg:province":"GA",
    "wof:name":"Galaxy Mobile Homes",
    "wof:placetype":"venue"
},
  "geometry": {"coordinates":[-84.354749,33.507576],"type":"Point"}
}