{
  "type": "Feature",
  "properties": {
    "iso:country":"US",
    "sg:address":"3042 Medina Dr",
    "sg:city":"Jonesboro",
    "sg:classifiers":[
        {
            "category":"Building & Trades",
            "subcategory":"Cleaning & Sanitation",
            "type":"Services"
        }
    ],
    "sg:phone":"+1 678 480 8591",
    "sg:postcode":"30236",
    "sg:province":"GA",
    "sg:tags":[
        "maintenance"
    ],
    "wof:name":"Corbins Clean Up Service",
    "wof:placetype":"venue"
},
  "geometry": {"coordinates":[-84.294059,33.559478],"type":"Point"}
}