{
  "type": "Feature",
  "properties": {
    "addr:full":"2174 Azalea Cir Decatur GA 30033",
    "addr:housenumber":"2174",
    "addr:postcode":"30033",
    "addr:street":"Azalea Cir",
    "iso:country":"US",
    "sg:address":"2174 Azalea Cir",
    "sg:city":"Decatur",
    "sg:classifiers":[
        {
            "category":"Communications",
            "subcategory":"Film & Video Production",
            "type":"Services"
        },
        {
            "category":"Communications",
            "subcategory":"Television Station",
            "type":"Services"
        }
    ],
    "sg:phone":"+1 404 633 7090",
    "sg:postcode":"30033",
    "sg:province":"GA",
    "sg:tags":[
        "companies-film",
        "producer",
        "tv",
        "program",
        "radio",
        "distributor"
    ],
    "wof:name":"Yang Communications",
    "wof:placetype":"venue"
},
  "geometry": {"coordinates":[-84.300713,33.814652],"type":"Point"}
}