{
  "type": "Feature",
  "properties": {
    "iso:country":"US",
    "sg:address":"1045 Franklin Rd SE",
    "sg:city":"Marietta",
    "sg:classifiers":[
        {
            "category":"Food & Beverages",
            "subcategory":"Groceries & Convenience Stores",
            "type":"Retail Goods"
        }
    ],
    "sg:phone":"+1 770 818 0870",
    "sg:postcode":"30067",
    "sg:province":"GA",
    "wof:name":"Fast Trip Convenience Store",
    "wof:placetype":"venue"
},
  "geometry": {"coordinates":[-84.492655,33.927183],"type":"Point"}
}