{
  "type": "Feature",
  "properties": {
    "iso:country":"US",
    "sg:address":"4235 S Lee St",
    "sg:city":"Buford",
    "sg:classifiers":[
        {
            "category":"Real Estate",
            "subcategory":"Real Estate Agent",
            "type":"Services"
        }
    ],
    "sg:phone":"+1 770 945 3241",
    "sg:postcode":"30518",
    "sg:province":"GA",
    "wof:name":"Prime Interest Inc",
    "wof:placetype":"venue"
},
  "geometry": {"coordinates":[-83.999635,34.094812],"type":"Point"}
}