{
  "type": "Feature",
  "properties": {
    "addr:full":"8622 Ellard Dr Alpharetta GA 30022",
    "addr:housenumber":"8622",
    "addr:postcode":"30022",
    "addr:street":"Ellard Dr",
    "iso:country":"US",
    "sg:address":"8622 Ellard Dr",
    "sg:city":"Alpharetta",
    "sg:classifiers":[
        {
            "category":"Organizations",
            "subcategory":"Professional Association",
            "type":"Services"
        }
    ],
    "sg:phone":"+1 770 552 1983",
    "sg:postcode":"30022",
    "sg:province":"GA",
    "wof:name":"Ellard Community Assn Inc",
    "wof:placetype":"venue"
},
  "geometry": {"coordinates":[-84.271683,33.981753],"type":"Point"}
}