{
  "type": "Feature",
  "properties": {
    "iso:country":"US",
    "sg:address":"2000 Shakerag Hl",
    "sg:city":"Peachtree City",
    "sg:classifiers":[
        {
            "category":"Building & Trades",
            "subcategory":"Locksmith",
            "type":"Services"
        }
    ],
    "sg:phone":"+1 678 269 7153",
    "sg:postcode":"30269",
    "sg:province":"GA",
    "sg:tags":[
        "key"
    ],
    "wof:name":"7 Days Emergency Locksmith",
    "wof:placetype":"venue"
},
  "geometry": {"coordinates":[-84.560502,33.414661],"type":"Point"}
}