{
  "type": "Feature",
  "properties": {
    "addr:full":"2704 Shannon Rd Albany GA 31721",
    "addr:housenumber":"2704",
    "addr:postcode":"31721",
    "addr:street":"Shannon Rd",
    "iso:country":"US",
    "sg:address":"2704 Shannon Rd",
    "sg:city":"Albany",
    "sg:classifiers":[
        {
            "category":"Freight",
            "type":"Transportation"
        }
    ],
    "sg:phone":"+1 229 436 2283",
    "sg:postcode":"31721",
    "sg:province":"GA",
    "wof:name":"Field Warehousing Corp",
    "wof:placetype":"venue"
},
  "geometry": {"coordinates":[-84.243217,31.621541],"type":"Point"}
}