{
  "type": "Feature",
  "properties": {
    "addr:full":"2300 Dellwood Dr NW Atlanta GA 30305",
    "addr:housenumber":"2300",
    "addr:postcode":"30305",
    "addr:street":"Dellwood Dr Nw",
    "iso:country":"US",
    "sg:address":"2300 Dellwood Dr NW",
    "sg:city":"Atlanta",
    "sg:classifiers":[
        {
            "category":"Professional",
            "type":"Services"
        }
    ],
    "sg:phone":"+1 404 355 8126",
    "sg:postcode":"30305",
    "sg:province":"GA",
    "sg:tags":[
        "establishment"
    ],
    "wof:name":"Patrick James Inc",
    "wof:placetype":"venue"
},
  "geometry": {"coordinates":[-84.398341,33.818465],"type":"Point"}
}