{
  "type": "Feature",
  "properties": {
    "iso:country":"US",
    "sg:address":"1640 Co Rd 19",
    "sg:city":"Dublin",
    "sg:phone":"+1 478 272 1803",
    "sg:postcode":"31021",
    "sg:province":"GA",
    "sg:tags":[
        "beef",
        "farm",
        "crop",
        "field",
        "cattle",
        "feedlot"
    ],
    "wof:name":"Cook",
    "wof:placetype":"venue"
},
  "geometry": {"coordinates":[-82.932596,32.53653],"type":"Point"}
}