{
  "type": "Feature",
  "properties": {
    "addr:full":"744 Spring Street NW Atlanta GA 30308",
    "addr:housenumber":"744",
    "addr:postcode":"30308",
    "addr:street":"Spring Street Nw",
    "iso:country":"US",
    "sg:address":"744 Spring Street NW",
    "sg:city":"Atlanta",
    "sg:classifiers":[
        {
            "category":"Building & Trades",
            "subcategory":"Locksmith",
            "type":"Services"
        }
    ],
    "sg:phone":"+1 678 806 0527",
    "sg:postcode":"30308",
    "sg:province":"GA",
    "sg:tags":[
        "key"
    ],
    "wof:name":"E Mergency A Locksmith",
    "wof:placetype":"venue"
},
  "geometry": {"coordinates":[-84.388688,33.774993],"type":"Point"}
}