{
  "type": "Feature",
  "properties": {
    "addr:full":"100 Cracker Barrel Dr Calhoun GA 30701",
    "addr:housenumber":"100",
    "addr:postcode":"30701",
    "addr:street":"Cracker Barrel Dr",
    "iso:country":"US",
    "sg:address":"100 Cracker Barrel Dr",
    "sg:city":"Calhoun",
    "sg:classifiers":[
        {
            "category":"Bars & Pubs",
            "type":"Food & Drink"
        }
    ],
    "sg:menulink":"http://www.allmenus.com/ga/calhoun/35064-cracker-barrel-old-country-store/menu/",
    "sg:phone":"+1 706 624 1661",
    "sg:postcode":"30701",
    "sg:province":"GA",
    "sg:tags":[
        "american",
        "southern"
    ],
    "wof:name":"Cracker Barrel Old Country Store",
    "wof:placetype":"venue"
},
  "geometry": {"coordinates":[-84.914931,34.47036],"type":"Point"}
}