{
  "type": "Feature",
  "properties": {
    "addr:full":"2749 Delk Rd SE Marietta GA 30067",
    "addr:housenumber":"2749",
    "addr:postcode":"30067",
    "addr:street":"Delk Rd Se",
    "iso:country":"US",
    "sg:address":"2749 Delk Rd SE",
    "sg:city":"Marietta",
    "sg:classifiers":[
        {
            "category":"Shopping",
            "subcategory":"Bicycles & Sporting Goods",
            "type":"Retail Goods"
        }
    ],
    "sg:phone":"+1 770 303 0064",
    "sg:postcode":"30067",
    "sg:province":"GA",
    "sg:tags":[
        "apparel",
        "equipment",
        "bowling",
        "accessory",
        "supply"
    ],
    "wof:name":"Bowlers Aid Pro Shops Inc",
    "wof:placetype":"venue"
},
  "geometry": {"coordinates":[-84.473624,33.922968],"type":"Point"}
}