{
  "type": "Feature",
  "properties": {
    "iso:country":"US",
    "sg:address":"110 Don Rich Dr",
    "sg:city":"Carrollton",
    "sg:classifiers":[
        {
            "category":"Professional",
            "subcategory":"Business Services",
            "type":"Services"
        }
    ],
    "sg:phone":"+1 770 832 3990",
    "sg:postcode":"30117",
    "sg:province":"GA",
    "wof:name":"La McKenzie & Assoc Inc",
    "wof:placetype":"venue"
},
  "geometry": {"coordinates":[-85.079981,33.535014],"type":"Point"}
}