{
  "type": "Feature",
  "properties": {
    "iso:country":"US",
    "sg:address":"275 Village Pkwy NE",
    "sg:city":"Marietta",
    "sg:classifiers":[
        {
            "category":"Professional",
            "subcategory":"Engineering",
            "type":"Services"
        },
        {
            "category":"Building & Trades",
            "subcategory":"Landscaping Services",
            "type":"Services"
        }
    ],
    "sg:phone":"+1 770 955 2421",
    "sg:postcode":"30067",
    "sg:province":"GA",
    "sg:tags":[
        "land",
        "civil",
        "planner",
        "architect",
        "landscape",
        "engineer"
    ],
    "wof:name":"J Lancaster Associates Inc",
    "wof:placetype":"venue"
},
  "geometry": {"coordinates":[-84.415125,33.949445],"type":"Point"}
}