{
  "type": "Feature",
  "properties": {
    "addr:full":"1500 Riggs Store Rd Hartsfield GA 31756",
    "addr:housenumber":"1500",
    "addr:postcode":"31756",
    "addr:street":"Riggs Store Rd",
    "iso:country":"US",
    "sg:address":"1500 Riggs Store Rd",
    "sg:city":"Hartsfield",
    "sg:classifiers":[
        {
            "category":"Transit Center",
            "subcategory":"Freight",
            "type":"Transportation"
        },
        {
            "category":"Freight",
            "type":"Transportation"
        }
    ],
    "sg:phone":"+1 229 941 2057",
    "sg:postcode":"31756",
    "sg:province":"GA",
    "sg:tags":[
        "trucking-heavy",
        "local",
        "hauling",
        "trucking"
    ],
    "wof:name":"William T Daniels",
    "wof:placetype":"venue"
},
  "geometry": {"coordinates":[-83.994601,31.152597],"type":"Point"}
}