{
  "type": "Feature",
  "properties": {
    "iso:country":"US",
    "sg:address":"2695 New Macland Rd",
    "sg:city":"Powder Springs",
    "sg:classifiers":[
        {
            "category":"Building & Trades",
            "subcategory":"Landscaping Services",
            "type":"Services"
        }
    ],
    "sg:phone":"+1 770 943 4786",
    "sg:postcode":"30127",
    "sg:province":"GA",
    "wof:name":"Lawn Service Inc",
    "wof:placetype":"venue"
},
  "geometry": {"coordinates":[-84.67635799999999,33.886409],"type":"Point"}
}