{
  "type": "Feature",
  "properties": {
    "addr:full":"3600 Regency Park Dr Duluth GA 30096",
    "addr:housenumber":"3600",
    "addr:postcode":"30096",
    "addr:street":"Regency Park Dr",
    "iso:country":"US",
    "sg:address":"3600 Regency Park Dr",
    "sg:city":"Duluth",
    "sg:classifiers":[
        {
            "category":"Shopping",
            "subcategory":"Gifts & Souvenirs",
            "type":"Retail Goods"
        }
    ],
    "sg:phone":"+1 678 584 9313",
    "sg:postcode":"30096",
    "sg:province":"GA",
    "wof:name":"Decomarj",
    "wof:placetype":"venue"
},
  "geometry": {"coordinates":[-84.152213,33.981052],"type":"Point"}
}