{
  "type": "Feature",
  "properties": {
    "addr:full":"2179 Lawrenceville Hwy Lawrenceville GA 30044",
    "addr:housenumber":"2179",
    "addr:postcode":"30044",
    "addr:street":"Lawrenceville Hwy",
    "iso:country":"US",
    "sg:address":"2179 Lawrenceville Hwy",
    "sg:city":"Lawrenceville",
    "sg:classifiers":[
        {
            "category":"Banks & Credit Unions",
            "subcategory":"Bank",
            "type":"Services"
        }
    ],
    "sg:phone":"+1 770 339 3785",
    "sg:postcode":"30044",
    "sg:province":"GA",
    "sg:tags":[
        "loan",
        "real estate"
    ],
    "wof:name":"Keyes Penn Mortgage Co",
    "wof:placetype":"venue"
},
  "geometry": {"coordinates":[-84.053555,33.927012],"type":"Point"}
}