{
  "type": "Feature",
  "properties": {
    "iso:country":"US",
    "sg:address":"951 Harmony Rd",
    "sg:city":"Eatonton",
    "sg:classifiers":[
        {
            "category":"Professional",
            "subcategory":"Employment Agencies",
            "type":"Services"
        }
    ],
    "sg:phone":"+1 706 484 2000",
    "sg:postcode":"31024",
    "sg:province":"GA",
    "sg:tags":[
        "consultant",
        "search",
        "executive"
    ],
    "wof:name":"Recruiting Group",
    "wof:placetype":"venue"
},
  "geometry": {"coordinates":[-83.27430200000001,33.428378],"type":"Point"}
}