{
  "type": "Feature",
  "properties": {
    "addr:full":"1640 Sharpton Trl Lawrenceville GA 30045",
    "addr:housenumber":"1640",
    "addr:postcode":"30045",
    "addr:street":"Sharpton Trl",
    "iso:country":"US",
    "sg:address":"1640 Sharpton Trl",
    "sg:city":"Lawrenceville",
    "sg:classifiers":[
        {
            "category":"Building & Trades",
            "subcategory":"Construction",
            "type":"Services"
        }
    ],
    "sg:phone":"+1 770 963 6942",
    "sg:postcode":"30045",
    "sg:province":"GA",
    "wof:name":"Jmg Management Inc",
    "wof:placetype":"venue"
},
  "geometry": {"coordinates":[-83.939059,33.913052],"type":"Point"}
}