{
  "type": "Feature",
  "properties": {
    "iso:country":"US",
    "sg:address":"1227 Dickens Rd NW",
    "sg:city":"Lilburn",
    "sg:classifiers":[
        {
            "category":"Professional",
            "type":"Services"
        }
    ],
    "sg:phone":"+1 770 923 0703",
    "sg:postcode":"30047",
    "sg:province":"GA",
    "wof:name":"Cisneros Jovel Inc",
    "wof:placetype":"venue"
},
  "geometry": {"coordinates":[-84.14989,33.908639],"type":"Point"}
}