{
  "type": "Feature",
  "properties": {
    "addr:full":"1843 Sandy Cross Rd Royston GA 30662",
    "addr:housenumber":"1843",
    "addr:postcode":"30662",
    "addr:street":"Sandy Cross Rd",
    "iso:country":"US",
    "sg:address":"1843 Sandy Cross Rd",
    "sg:city":"Royston",
    "sg:classifiers":[
        {
            "category":"Farming",
            "subcategory":"Farm",
            "type":"Manufacturing & Wholesale Goods"
        }
    ],
    "sg:phone":"+1 706 245 4830",
    "sg:postcode":"30662",
    "sg:province":"GA",
    "wof:name":"Cary Farms",
    "wof:placetype":"venue"
},
  "geometry": {"coordinates":[-83.213494,34.291599],"type":"Point"}
}