{
  "type": "Feature",
  "properties": {
    "addr:full":"265 Chief Vann Dr Alpharetta GA 30004",
    "addr:housenumber":"265",
    "addr:postcode":"30004",
    "addr:street":"Chief Vann Dr",
    "iso:country":"US",
    "sg:address":"265 Chief Vann Dr",
    "sg:city":"Alpharetta",
    "sg:classifiers":[
        {
            "category":"Building & Trades",
            "subcategory":"Construction",
            "type":"Services"
        }
    ],
    "sg:phone":"+1 770 889 2828",
    "sg:postcode":"30004",
    "sg:province":"GA",
    "sg:tags":[
        "hanging",
        "contractor"
    ],
    "wof:name":"Jeff & Kristy Paint Contrs",
    "wof:placetype":"venue"
},
  "geometry": {"coordinates":[-84.266329,34.198375],"type":"Point"}
}