{
  "type": "Feature",
  "properties": {
    "addr:full":"1055 Old Peachtree Rd NE Lawrenceville GA 30043",
    "addr:housenumber":"1055",
    "addr:postcode":"30043",
    "addr:street":"Old Peachtree Rd Ne",
    "iso:country":"US",
    "sg:address":"1055 Old Peachtree Rd NE",
    "sg:city":"Lawrenceville",
    "sg:classifiers":[
        {
            "category":"Food & Beverages",
            "subcategory":"Groceries & Convenience Stores",
            "type":"Retail Goods"
        }
    ],
    "sg:phone":"+1 770 277 1266",
    "sg:postcode":"30043",
    "sg:province":"GA",
    "wof:name":"Quik Trip",
    "wof:placetype":"venue"
},
  "geometry": {"coordinates":[-83.98816600000001,34.036048],"type":"Point"}
}