{
  "type": "Feature",
  "properties": {
    "addr:full":"2235 N Ashley St Valdosta GA 31602",
    "addr:housenumber":"2235",
    "addr:postcode":"31602",
    "addr:street":"N Ashley St",
    "iso:country":"US",
    "sg:address":"2235 N Ashley St",
    "sg:city":"Valdosta",
    "sg:classifiers":[
        {
            "category":"Autos & Motor Vehicles",
            "subcategory":"Automobile Sales",
            "type":"Retail Goods"
        }
    ],
    "sg:phone":"+1 229 242 5929",
    "sg:postcode":"31602",
    "sg:province":"GA",
    "sg:tags":[
        "used"
    ],
    "wof:name":"Rite-Deal Inc",
    "wof:placetype":"venue"
},
  "geometry": {"coordinates":[-83.283033,30.861071],"type":"Point"}
}