{
  "type": "Feature",
  "properties": {
    "iso:country":"US",
    "sg:address":"230 Blounts Xing",
    "sg:city":"Darien",
    "sg:classifiers":[
        {
            "category":"Organizations",
            "subcategory":"Community Association",
            "type":"Services"
        }
    ],
    "sg:phone":"+1 912 437 2476",
    "sg:postcode":"31305",
    "sg:province":"GA",
    "wof:name":"Sams Ced",
    "wof:placetype":"venue"
},
  "geometry": {"coordinates":[-81.428355,31.393472],"type":"Point"}
}