{
  "type": "Feature",
  "properties": {
    "addr:full":"148 Silver Mine Trl Austell GA 30168",
    "addr:housenumber":"148",
    "addr:postcode":"30168",
    "addr:street":"Silver Mine Trl",
    "iso:country":"US",
    "sg:address":"148 Silver Mine Trl",
    "sg:city":"Austell",
    "sg:classifiers":[
        {
            "category":"Manufacturing",
            "subcategory":"Chemicals & Compounds",
            "type":"Manufacturing & Wholesale Goods"
        },
        {
            "category":"Wholesale",
            "subcategory":"Medical Equipment & Supplies",
            "type":"Manufacturing & Wholesale Goods"
        },
        {
            "category":"Shopping",
            "subcategory":"Pharmacy",
            "type":"Retail Goods"
        }
    ],
    "sg:phone":"+1 770 465 3956",
    "sg:postcode":"30168",
    "sg:province":"GA",
    "sg:tags":[
        "pharmaceutical",
        "product",
        "proprietary",
        "products-wholesale",
        "medicines-patent",
        "manufacturer"
    ],
    "sg:website":"http://www.venturepharm.com",
    "wof:name":"Venturepharm",
    "wof:placetype":"venue"
},
  "geometry": {"coordinates":[-84.549519,33.776898],"type":"Point"}
}