{
  "type": "Feature",
  "properties": {
    "iso:country":"US",
    "sg:address":"28036 Gardner Dr",
    "sg:city":"Alpharetta",
    "sg:classifiers":[
        {
            "category":"Professional",
            "type":"Services"
        }
    ],
    "sg:phone":"+1 678 566 1336",
    "sg:postcode":"30004",
    "sg:province":"GA",
    "wof:name":"Voice Projects",
    "wof:placetype":"venue"
},
  "geometry": {"coordinates":[-84.288377,34.067813],"type":"Point"}
}