{
  "type": "Feature",
  "properties": {
    "iso:country":"US",
    "sg:address":"465 Dix-Lee-on Dr",
    "sg:city":"Fairburn",
    "sg:classifiers":[
        {
            "category":"Communications",
            "type":"Services"
        }
    ],
    "sg:phone":"+1 770 716 6738",
    "sg:postcode":"30213",
    "sg:province":"GA",
    "sg:tags":[
        "communication"
    ],
    "wof:name":"Hobbs Communication Inc",
    "wof:placetype":"venue"
},
  "geometry": {"coordinates":[-84.46293300000001,33.54518],"type":"Point"}
}