{
  "type": "Feature",
  "properties": {
    "addr:full":"102 Malone St Sandersville GA 31082",
    "addr:housenumber":"102",
    "addr:postcode":"31082",
    "addr:street":"Malone St",
    "iso:country":"US",
    "sg:address":"102 Malone St",
    "sg:city":"Sandersville",
    "sg:classifiers":[
        {
            "category":"Shopping",
            "subcategory":"Florist",
            "type":"Retail Goods"
        }
    ],
    "sg:phone":"+1 478 552 0557",
    "sg:postcode":"31082",
    "sg:province":"GA",
    "wof:name":"Enchanted Florist",
    "wof:placetype":"venue"
},
  "geometry": {"coordinates":[-82.812127,32.983863],"type":"Point"}
}