{
  "type": "Feature",
  "properties": {
    "addr:full":"5719 Glade Rd SE Acworth GA 30102",
    "addr:housenumber":"5719",
    "addr:postcode":"30102",
    "addr:street":"Glade Rd Se",
    "iso:country":"US",
    "sg:address":"5719 Glade Rd SE",
    "sg:city":"Acworth",
    "sg:classifiers":[
        {
            "category":"Professional",
            "type":"Services"
        }
    ],
    "sg:phone":"+1 770 917 1783",
    "sg:postcode":"30102",
    "sg:province":"GA",
    "wof:name":"Daniels Tree Service",
    "wof:placetype":"venue"
},
  "geometry": {"coordinates":[-84.682219,34.090984],"type":"Point"}
}