{
  "type": "Feature",
  "properties": {
    "addr:full":"1270 Fields Chapel Rd Canton GA 30114",
    "addr:housenumber":"1270",
    "addr:postcode":"30114",
    "addr:street":"Fields Chapel Rd",
    "iso:country":"US",
    "sg:address":"1270 Fields Chapel Rd",
    "sg:city":"Canton",
    "sg:classifiers":[
        {
            "category":"Building & Trades",
            "subcategory":"Plumbing",
            "type":"Services"
        }
    ],
    "sg:phone":"+1 770 422 5226",
    "sg:postcode":"30114",
    "sg:province":"GA",
    "sg:tags":[
        "contractor"
    ],
    "wof:name":"Atlanta Plumbing Plus",
    "wof:placetype":"venue"
},
  "geometry": {"coordinates":[-84.582149,34.202687],"type":"Point"}
}