{
  "type": "Feature",
  "properties": {
    "addr:full":"835 Franklin Rd SE Marietta GA 30067",
    "addr:housenumber":"835",
    "addr:postcode":"30067",
    "addr:street":"Franklin Rd Se",
    "iso:country":"US",
    "sg:address":"835 Franklin Rd SE",
    "sg:city":"Marietta",
    "sg:classifiers":[
        {
            "category":"Freight",
            "type":"Transportation"
        }
    ],
    "sg:phone":"+1 770 795 3773",
    "sg:postcode":"30067",
    "sg:province":"GA",
    "sg:tags":[
        "arrangement"
    ],
    "wof:name":"Rf International Ltd",
    "wof:placetype":"venue"
},
  "geometry": {"coordinates":[-84.500426,33.932849],"type":"Point"}
}