{
  "type": "Feature",
  "properties": {
    "addr:full":"24 Sloan St Roswell GA 30075",
    "addr:housenumber":"24",
    "addr:postcode":"30075",
    "addr:street":"Sloan St",
    "iso:country":"US",
    "sg:address":"24 Sloan St",
    "sg:city":"Roswell",
    "sg:classifiers":[
        {
            "category":"Professional",
            "subcategory":"Advertising",
            "type":"Services"
        }
    ],
    "sg:phone":"+1 770 992 1995",
    "sg:postcode":"30075",
    "sg:province":"GA",
    "sg:tags":[
        "publisher",
        "representative"
    ],
    "sg:website":"www.gcarbonara.com",
    "wof:name":"G Carbonara & Co",
    "wof:placetype":"venue"
},
  "geometry": {"coordinates":[-84.36175299999999,34.015494],"type":"Point"}
}