{
  "type": "Feature",
  "properties": {
    "iso:country":"US",
    "sg:address":"1921 4th St",
    "sg:city":"Brunswick",
    "sg:classifiers":[
        {
            "category":"Building & Trades",
            "subcategory":"Plumbing",
            "type":"Services"
        }
    ],
    "sg:phone":"+1 912 265 2486",
    "sg:postcode":"31520",
    "sg:province":"GA",
    "sg:tags":[
        "heater",
        "plumber",
        "industrial",
        "repair",
        "water",
        "sewer",
        "cleaning",
        "plumbing-drain",
        "contractors-commercial"
    ],
    "wof:name":"Snyder Plumbing Co Inc",
    "wof:placetype":"venue"
},
  "geometry": {"coordinates":[-81.493616,31.177222],"type":"Point"}
}