{
  "type": "Feature",
  "properties": {
    "addr:full":"1185 Garnett Ward Rd Hull GA 30646",
    "addr:housenumber":"1185",
    "addr:postcode":"30646",
    "addr:street":"Garnett Ward Rd",
    "iso:country":"US",
    "sg:address":"1185 Garnett Ward Rd",
    "sg:city":"Hull",
    "sg:classifiers":[
        {
            "category":"Building & Trades",
            "subcategory":"Landscaping Services",
            "type":"Services"
        }
    ],
    "sg:phone":"+1 706 549 2455",
    "sg:postcode":"30646",
    "sg:province":"GA",
    "sg:tags":[
        "tree"
    ],
    "wof:name":"Betts Tree Svc",
    "wof:placetype":"venue"
},
  "geometry": {"coordinates":[-83.309258,34.060514],"type":"Point"}
}