{
  "type": "Feature",
  "properties": {
    "iso:country":"US",
    "sg:address":"230 S Jackson St",
    "sg:city":"Albany",
    "sg:classifiers":[
        {
            "category":"Government",
            "subcategory":"Office",
            "type":"Public Place"
        }
    ],
    "sg:phone":"+1 229 430 5283",
    "sg:postcode":"31701",
    "sg:province":"GA",
    "sg:tags":[
        "city",
        "planning",
        "dev"
    ],
    "wof:name":"Albany Community Development",
    "wof:placetype":"venue"
},
  "geometry": {"coordinates":[-84.153589,31.574273],"type":"Point"}
}