{
  "type": "Feature",
  "properties": {
    "addr:full":"11277 Highway 27 Summerville GA 30747",
    "addr:housenumber":"11277",
    "addr:postcode":"30747",
    "addr:street":"Highway 27",
    "iso:country":"US",
    "sg:address":"11277 Highway 27",
    "sg:city":"Summerville",
    "sg:classifiers":[
        {
            "category":"Fast Food",
            "type":"Food & Drink"
        },
        {
            "category":"Restaurant",
            "type":"Food & Drink"
        }
    ],
    "sg:phone":"+1 706 857 1966",
    "sg:postcode":"30747",
    "sg:province":"GA",
    "sg:tags":[
        "mexican"
    ],
    "sg:website":"http://www.tacobell.com",
    "wof:name":"Taco Bell",
    "wof:placetype":"venue"
},
  "geometry": {"coordinates":[-85.322869,34.510492],"type":"Point"}
}