{
  "type": "Feature",
  "properties": {
    "iso:country":"US",
    "sg:address":"22 Marty Ln",
    "sg:city":"Dallas",
    "sg:classifiers":[
        {
            "category":"Professional",
            "type":"Services"
        }
    ],
    "sg:phone":"+1 770 445 4479",
    "sg:postcode":"30132",
    "sg:province":"GA",
    "wof:name":"James M Langford",
    "wof:placetype":"venue"
},
  "geometry": {"coordinates":[-84.796757,33.962052],"type":"Point"}
}