{
  "type": "Feature",
  "properties": {
    "addr:full":"6473 Dearborn Dr Acworth GA 30102",
    "addr:housenumber":"6473",
    "addr:postcode":"30102",
    "addr:street":"Dearborn Dr",
    "iso:country":"US",
    "sg:address":"6473 Dearborn Dr",
    "sg:city":"Acworth",
    "sg:classifiers":[
        {
            "category":"Professional",
            "subcategory":"Detective & Security Services",
            "type":"Services"
        }
    ],
    "sg:phone":"+1 770 231 5246",
    "sg:postcode":"30102",
    "sg:province":"GA",
    "sg:tags":[
        "investigator"
    ],
    "wof:name":"Fugitive Apprehensions Specs",
    "wof:placetype":"venue"
},
  "geometry": {"coordinates":[-84.60647,34.113636],"type":"Point"}
}