{
  "type": "Feature",
  "properties": {
    "iso:country":"US",
    "sg:address":"109 Jordan Rd",
    "sg:city":"Tifton",
    "sg:classifiers":[
        {
            "category":"Manufacturing",
            "subcategory":"Apparel",
            "type":"Manufacturing & Wholesale Goods"
        }
    ],
    "sg:phone":"+1 229 388 8008",
    "sg:postcode":"31793",
    "sg:province":"GA",
    "sg:tags":[
        "cottonseed",
        "product"
    ],
    "sg:website":"http://www.chickashaofgeorgia.com",
    "wof:name":"Chickasha Of Georgia",
    "wof:placetype":"venue"
},
  "geometry": {"coordinates":[-83.525621,31.423132],"type":"Point"}
}