{
  "type": "Feature",
  "properties": {
    "addr:full":"302 E Washington St Monroe GA 30655",
    "addr:housenumber":"302",
    "addr:postcode":"30655",
    "addr:street":"E Washington St",
    "iso:country":"US",
    "sg:address":"302 E Washington St",
    "sg:city":"Monroe",
    "sg:classifiers":[
        {
            "category":"Professional",
            "subcategory":"Business Services",
            "type":"Services"
        },
        {
            "category":"Government",
            "subcategory":"Post Office",
            "type":"Public Place"
        }
    ],
    "sg:phone":"+1 770 267 5254",
    "sg:postcode":"30655",
    "sg:province":"GA",
    "sg:tags":[
        "mail",
        "shipping"
    ],
    "sg:website":"http://www.usps.com",
    "wof:name":"USPS - United States Post Office - Monroe",
    "wof:placetype":"venue"
},
  "geometry": {"coordinates":[-83.71048999999999,33.793863],"type":"Point"}
}