{
  "type": "Feature",
  "properties": {
    "iso:country":"US",
    "sg:address":"986 State Rte 36",
    "sg:city":"Barnesville",
    "sg:classifiers":[
        {
            "category":"Freight",
            "type":"Transportation"
        }
    ],
    "sg:phone":"+1 770 358 4925",
    "sg:postcode":"30204",
    "sg:province":"GA",
    "sg:tags":[
        "operator",
        "local",
        "trucking"
    ],
    "wof:name":"Harpers Trucking",
    "wof:placetype":"venue"
},
  "geometry": {"coordinates":[-84.19069399999999,33.006707],"type":"Point"}
}