{
  "type": "Feature",
  "properties": {
    "addr:full":"233 Sivell Rd Lagrange GA 30241",
    "addr:housenumber":"233",
    "addr:postcode":"30241",
    "addr:street":"Sivell Rd",
    "iso:country":"US",
    "sg:address":"233 Sivell Rd",
    "sg:city":"Lagrange",
    "sg:classifiers":[
        {
            "category":"Wholesale",
            "subcategory":"Construction Materials",
            "type":"Manufacturing & Wholesale Goods"
        },
        {
            "category":"Building & Trades",
            "subcategory":"Construction",
            "type":"Services"
        }
    ],
    "sg:phone":"+1 706 884 6298",
    "sg:postcode":"30241",
    "sg:province":"GA",
    "sg:tags":[
        "contractor",
        "concrete",
        "lumber",
        "common",
        "brick",
        "face"
    ],
    "wof:name":"Fowler Masonry Inc",
    "wof:placetype":"venue"
},
  "geometry": {"coordinates":[-84.979845,33.065091],"type":"Point"}
}