{
  "type": "Feature",
  "properties": {
    "iso:country":"US",
    "sg:address":"2750 Holcomb Bridge Rd Ste 220",
    "sg:city":"Alpharetta",
    "sg:classifiers":[
        {
            "category":"Real Estate",
            "subcategory":"Real Estate Services",
            "type":"Services"
        }
    ],
    "sg:phone":"+1 770 518 1800",
    "sg:postcode":"30022",
    "sg:province":"GA",
    "sg:tags":[
        "management",
        "property"
    ],
    "wof:name":"Epco Real Estate",
    "wof:placetype":"venue"
},
  "geometry": {"coordinates":[-84.27480300000001,34.003899],"type":"Point"}
}