{
  "type": "Feature",
  "properties": {
    "addr:full":"51 Temple Ave W Newnan GA 30263",
    "addr:housenumber":"51",
    "addr:postcode":"30263",
    "addr:street":"Temple Ave W",
    "iso:country":"US",
    "sg:address":"51 Temple Ave W",
    "sg:city":"Newnan",
    "sg:classifiers":[
        {
            "category":"Shopping",
            "subcategory":"Gifts & Souvenirs",
            "type":"Retail Goods"
        }
    ],
    "sg:phone":"+1 770 304 9003",
    "sg:postcode":"30263",
    "sg:province":"GA",
    "wof:name":"Paper Moon Productions Inc",
    "wof:placetype":"venue"
},
  "geometry": {"coordinates":[-84.80359300000001,33.378797],"type":"Point"}
}