{
  "type": "Feature",
  "properties": {
    "iso:country":"US",
    "sg:address":"340 Hunt Rd",
    "sg:city":"Kathleen",
    "sg:classifiers":[
        {
            "category":"Building & Trades",
            "subcategory":"Plumbing",
            "type":"Services"
        }
    ],
    "sg:phone":"+1 478 988 0026",
    "sg:postcode":"31047",
    "sg:province":"GA",
    "sg:tags":[
        "plumbing",
        "contractor"
    ],
    "wof:name":"Ron's Plumbing & Electric",
    "wof:placetype":"venue"
},
  "geometry": {"coordinates":[-83.690771,32.539124],"type":"Point"}
}