{
  "type": "Feature",
  "properties": {
    "addr:full":"7855 Roswell Rd Atlanta GA 30350",
    "addr:housenumber":"7855",
    "addr:postcode":"30350",
    "addr:street":"Roswell Rd",
    "iso:country":"US",
    "sg:address":"7855 Roswell Rd",
    "sg:city":"Atlanta",
    "sg:classifiers":[
        {
            "category":"Shopping",
            "subcategory":"Gifts & Souvenirs",
            "type":"Retail Goods"
        }
    ],
    "sg:phone":"+1 770 677 9650",
    "sg:postcode":"30350",
    "sg:province":"GA",
    "sg:tags":[
        "novelty",
        "adult"
    ],
    "wof:name":"Inserection",
    "wof:placetype":"venue"
},
  "geometry": {"coordinates":[-84.360311,33.969505],"type":"Point"}
}