{
  "type": "Feature",
  "properties": {
    "iso:country":"US",
    "sg:address":"339 Cotton Ave",
    "sg:city":"Macon",
    "sg:classifiers":[
        {
            "category":"Professional",
            "type":"Services"
        }
    ],
    "sg:phone":"+1 478 742 5737",
    "sg:postcode":"31201",
    "sg:province":"GA",
    "wof:name":"Dreams",
    "wof:placetype":"venue"
},
  "geometry": {"coordinates":[-83.628364,32.837687],"type":"Point"}
}