{
  "type": "Feature",
  "properties": {
    "addr:full":"3937 Holcomb Bridge Rd Norcross GA 30092",
    "addr:housenumber":"3937",
    "addr:postcode":"30092",
    "addr:street":"Holcomb Bridge Rd",
    "iso:country":"US",
    "sg:address":"3937 Holcomb Bridge Rd",
    "sg:city":"Norcross",
    "sg:classifiers":[
        {
            "category":"Professional",
            "type":"Services"
        }
    ],
    "sg:phone":"+1 770 242 3543",
    "sg:postcode":"30092",
    "sg:province":"GA",
    "sg:tags":[
        "establishment"
    ],
    "wof:name":"Acuity Cfo",
    "wof:placetype":"venue"
},
  "geometry": {"coordinates":[-84.258089,33.968184],"type":"Point"}
}