{
  "type": "Feature",
  "properties": {
    "addr:full":"4785 Hammermill Rd Tucker GA 30084",
    "addr:housenumber":"4785",
    "addr:postcode":"30084",
    "addr:street":"Hammermill Rd",
    "iso:country":"US",
    "sg:address":"4785 Hammermill Rd",
    "sg:city":"Tucker",
    "sg:classifiers":[
        {
            "category":"Government",
            "subcategory":"Post Office",
            "type":"Public Place"
        }
    ],
    "sg:phone":"+1 404 892 9775",
    "sg:postcode":"30084",
    "sg:province":"GA",
    "sg:tags":[
        "support",
        "architectural"
    ],
    "wof:name":"Georgia Architectual Products",
    "wof:placetype":"venue"
},
  "geometry": {"coordinates":[-84.19652600000001,33.836941],"type":"Point"}
}