{
  "type": "Feature",
  "properties": {
    "addr:full":"132 E Broughton St Savannah GA 31401",
    "addr:housenumber":"132",
    "addr:postcode":"31401",
    "addr:street":"E Broughton St",
    "iso:country":"US",
    "sg:address":"132 E Broughton St",
    "sg:city":"Savannah",
    "sg:classifiers":[
        {
            "category":"Organizations",
            "subcategory":"Non-profit Organization",
            "type":"Services"
        }
    ],
    "sg:phone":"+1 912 234 2020",
    "sg:postcode":"31401",
    "sg:province":"GA",
    "sg:tags":[
        "program",
        "prevention",
        "crime"
    ],
    "wof:name":"Crime Stoppers",
    "wof:placetype":"venue"
},
  "geometry": {"coordinates":[-81.08999300000001,32.078553],"type":"Point"}
}