{
  "type": "Feature",
  "properties": {
    "addr:full":"5357 Hwy 20 NE Cartersville GA 30121",
    "addr:housenumber":"5357",
    "addr:postcode":"30121",
    "addr:street":"Hwy 20 Ne",
    "iso:country":"US",
    "sg:address":"5357 Hwy 20 NE",
    "sg:city":"Cartersville",
    "sg:classifiers":[
        {
            "category":"Health Services",
            "subcategory":"Doctor",
            "type":"Services"
        }
    ],
    "sg:phone":"+1 770 606 8900",
    "sg:postcode":"30121",
    "sg:province":"GA",
    "sg:tags":[
        "medical"
    ],
    "wof:name":"Allatoona Ent Fcl Plstc Srgy",
    "wof:placetype":"venue"
},
  "geometry": {"coordinates":[-84.780974,34.206157],"type":"Point"}
}