{
  "type": "Feature",
  "properties": {
    "addr:full":"1400 Burch Branch Rd Hiawassee GA 30546",
    "addr:housenumber":"1400",
    "addr:postcode":"30546",
    "addr:street":"Burch Branch Rd",
    "iso:country":"US",
    "sg:address":"1400 Burch Branch Rd",
    "sg:city":"Hiawassee",
    "sg:classifiers":[
        {
            "category":"Arts & Performance",
            "subcategory":"Music",
            "type":"Entertainment"
        },
        {
            "category":"Sports & Exercise",
            "subcategory":"Sports Center",
            "type":"Entertainment"
        },
        {
            "category":"Recreation",
            "type":"Entertainment"
        }
    ],
    "sg:phone":"+1 706 507 1258",
    "sg:postcode":"30546",
    "sg:province":"GA",
    "sg:tags":[
        "musician",
        "entertainers-family",
        "business"
    ],
    "sg:website":"http://www.longridgecampground.com",
    "wof:name":"Long Ridge Campground",
    "wof:placetype":"venue"
},
  "geometry": {"coordinates":[-83.767815,34.929411],"type":"Point"}
}