{
  "type": "Feature",
  "properties": {
    "iso:country":"US",
    "sg:address":"201 N Burwell Ave",
    "sg:city":"Adel",
    "sg:classifiers":[
        {
            "category":"Ice Cream",
            "type":"Food & Drink"
        }
    ],
    "sg:phone":"+1 229 896 3988",
    "sg:postcode":"31620",
    "sg:province":"GA",
    "sg:website":"http://www.adel-ice.com",
    "wof:name":"Adel Ice Co",
    "wof:placetype":"venue"
},
  "geometry": {"coordinates":[-83.424683,31.138041],"type":"Point"}
}