{
  "type": "Feature",
  "properties": {
    "addr:full":"411 Edmond St Calhoun GA 30701",
    "addr:housenumber":"411",
    "addr:postcode":"30701",
    "addr:street":"Edmond St",
    "iso:country":"US",
    "sg:address":"411 Edmond St",
    "sg:city":"Calhoun",
    "sg:classifiers":[
        {
            "category":"Social Services",
            "type":"Services"
        }
    ],
    "sg:phone":"+1 706 625 3311",
    "sg:postcode":"30701",
    "sg:province":"GA",
    "sg:tags":[
        "profit",
        "family"
    ],
    "wof:name":"Commission On Children & Youth",
    "wof:placetype":"venue"
},
  "geometry": {"coordinates":[-84.962086,34.496731],"type":"Point"}
}