{
  "type": "Feature",
  "properties": {
    "iso:country":"US",
    "sg:address":"3051 Whiteside Rd",
    "sg:city":"Macon",
    "sg:classifiers":[
        {
            "category":"Health Services",
            "subcategory":"Nursing And Care Facility",
            "type":"Services"
        }
    ],
    "sg:phone":"+1 478 788 1421",
    "sg:postcode":"31216",
    "sg:province":"GA",
    "sg:tags":[
        "home",
        "convalescent"
    ],
    "wof:name":"Hartley Woods Health & Rehab",
    "wof:placetype":"venue"
},
  "geometry": {"coordinates":[-83.675679,32.740103],"type":"Point"}
}