{
  "type": "Feature",
  "properties": {
    "addr:full":"1807 5th Ave Macon GA 31201",
    "addr:housenumber":"1807",
    "addr:postcode":"31201",
    "addr:street":"5Th Ave",
    "iso:country":"US",
    "sg:address":"1807 5th Ave",
    "sg:city":"Macon",
    "sg:classifiers":[
        {
            "category":"Professional",
            "subcategory":"Business Services",
            "type":"Services"
        }
    ],
    "sg:phone":"+1 478 750 9746",
    "sg:postcode":"31201",
    "sg:province":"GA",
    "wof:name":"Harold McColumn Music Pro",
    "wof:placetype":"venue"
},
  "geometry": {"coordinates":[-83.64474199999999,32.847582],"type":"Point"}
}