{
  "type": "Feature",
  "properties": {
    "addr:full":"2806 Lavista Rd Decatur GA 30033",
    "addr:housenumber":"2806",
    "addr:postcode":"30033",
    "addr:street":"Lavista Rd",
    "iso:country":"US",
    "sg:address":"2806 Lavista Rd",
    "sg:city":"Decatur",
    "sg:classifiers":[
        {
            "category":"Retail",
            "subcategory":"Laundry & Dry Cleaning",
            "type":"Services"
        }
    ],
    "sg:phone":"+1 404 633 8096",
    "sg:postcode":"30033",
    "sg:province":"GA",
    "sg:tags":[
        "cleaner"
    ],
    "wof:name":"Joe May Valet Cleaners & Laundry",
    "wof:placetype":"venue"
},
  "geometry": {"coordinates":[-84.29239699999999,33.824699],"type":"Point"}
}