{
  "type": "Feature",
  "properties": {
    "addr:full":"3150 Buford Dam Rd Cumming GA 30041",
    "addr:housenumber":"3150",
    "addr:postcode":"30041",
    "addr:street":"Buford Dam Rd",
    "iso:country":"US",
    "sg:address":"3150 Buford Dam Rd",
    "sg:city":"Cumming",
    "sg:classifiers":[
        {
            "category":"Personal",
            "type":"Services"
        }
    ],
    "sg:phone":"+1 770 889 9100",
    "sg:postcode":"30041",
    "sg:province":"GA",
    "sg:tags":[
        "towing"
    ],
    "wof:name":"Advantage Towing",
    "wof:placetype":"venue"
},
  "geometry": {"coordinates":[-84.080399,34.176201],"type":"Point"}
}