{
  "type": "Feature",
  "properties": {
    "addr:full":"3113 Roswell Rd Marietta GA 30062",
    "addr:housenumber":"3113",
    "addr:postcode":"30062",
    "addr:street":"Roswell Rd",
    "iso:country":"US",
    "sg:address":"3113 Roswell Rd",
    "sg:city":"Marietta",
    "sg:classifiers":[
        {
            "category":"Shopping",
            "type":"Retail Goods"
        }
    ],
    "sg:phone":"+1 770 578 9188",
    "sg:postcode":"30062",
    "sg:province":"GA",
    "sg:tags":[
        "repair",
        "merchandise"
    ],
    "wof:name":"First Service",
    "wof:placetype":"venue"
},
  "geometry": {"coordinates":[-84.46134499999999,33.979509],"type":"Point"}
}