{
  "type": "Feature",
  "properties": {
    "iso:country":"US",
    "sg:address":"1515 Newcastle St",
    "sg:city":"Brunswick",
    "sg:classifiers":[
        {
            "category":"Professional",
            "subcategory":"Lawyer & Legal Services",
            "type":"Services"
        }
    ],
    "sg:phone":"+1 912 261 2241",
    "sg:postcode":"31520",
    "sg:province":"GA",
    "sg:tags":[
        "attorney"
    ],
    "wof:name":"Ellen M Mayoue",
    "wof:placetype":"venue"
},
  "geometry": {"coordinates":[-81.496043,31.151254],"type":"Point"}
}