{
  "type": "Feature",
  "properties": {
    "iso:country":"US",
    "sg:address":"517 Country Club Dr",
    "sg:city":"Stockbridge",
    "sg:classifiers":[
        {
            "category":"Building & Trades",
            "subcategory":"Cleaning & Sanitation",
            "type":"Services"
        }
    ],
    "sg:phone":"+1 770 507 4900",
    "sg:postcode":"30281",
    "sg:province":"GA",
    "wof:name":"Molly Maid",
    "wof:placetype":"venue"
},
  "geometry": {"coordinates":[-84.218536,33.514836],"type":"Point"}
}