{
  "type": "Feature",
  "properties": {
    "addr:full":"2200 Centre Park Ct Stone Mountain GA 30087",
    "addr:housenumber":"2200",
    "addr:postcode":"30087",
    "addr:street":"Centre Park Ct",
    "iso:country":"US",
    "sg:address":"2200 Centre Park Ct",
    "sg:city":"Stone Mountain",
    "sg:classifiers":[
        {
            "category":"Wholesale",
            "subcategory":"Machinery & Supplies",
            "type":"Manufacturing & Wholesale Goods"
        }
    ],
    "sg:phone":"+1 770 469 2720",
    "sg:postcode":"30087",
    "sg:province":"GA",
    "sg:tags":[
        "boring",
        "drilling"
    ],
    "wof:name":"Boart Longyear Co",
    "wof:placetype":"venue"
},
  "geometry": {"coordinates":[-84.1135,33.816061],"type":"Point"}
}