{
  "type": "Feature",
  "properties": {
    "iso:country":"US",
    "sg:address":"3378 Hazelwood Dr SW",
    "sg:city":"Atlanta",
    "sg:classifiers":[
        {
            "category":"Social Services",
            "subcategory":"Child Care",
            "type":"Services"
        }
    ],
    "sg:phone":"+1 404 691 7021",
    "sg:postcode":"30311",
    "sg:province":"GA",
    "sg:tags":[
        "day"
    ],
    "wof:name":"New Day Consultants Inc",
    "wof:placetype":"venue"
},
  "geometry": {"coordinates":[-84.49847699999999,33.72758],"type":"Point"}
}