{
  "type": "Feature",
  "properties": {
    "addr:full":"300 W 4th St Waynesboro GA 30830",
    "addr:housenumber":"300",
    "addr:postcode":"30830",
    "addr:street":"W 4Th St",
    "iso:country":"US",
    "sg:address":"300 W 4th St",
    "sg:city":"Waynesboro",
    "sg:classifiers":[
        {
            "category":"Health Services",
            "subcategory":"Optometrist",
            "type":"Services"
        }
    ],
    "sg:phone":"+1 706 554 2020",
    "sg:postcode":"30830",
    "sg:province":"GA",
    "wof:name":"Durant Eye Clinic",
    "wof:placetype":"venue"
},
  "geometry": {"coordinates":[-82.013728,33.083467],"type":"Point"}
}