{
  "type": "Feature",
  "properties": {
    "addr:full":"3777 Peachtree Rd NE Atlanta GA 30319",
    "addr:housenumber":"3777",
    "addr:postcode":"30319",
    "addr:street":"Peachtree Rd Ne",
    "iso:country":"US",
    "sg:address":"3777 Peachtree Rd NE",
    "sg:city":"Atlanta",
    "sg:classifiers":[
        {
            "category":"Professional",
            "type":"Services"
        }
    ],
    "sg:phone":"+1 404 841 9006",
    "sg:postcode":"30319",
    "sg:province":"GA",
    "sg:tags":[
        "establishment"
    ],
    "wof:name":"Suzanne & Stokes",
    "wof:placetype":"venue"
},
  "geometry": {"coordinates":[-84.34739500000001,33.857634],"type":"Point"}
}