{
  "type": "Feature",
  "properties": {
    "addr:full":"8325 Meridian Dr Riverdale GA 30274",
    "addr:housenumber":"8325",
    "addr:postcode":"30274",
    "addr:street":"Meridian Dr",
    "iso:country":"US",
    "sg:address":"8325 Meridian Dr",
    "sg:city":"Riverdale",
    "sg:classifiers":[
        {
            "category":"Organizations",
            "subcategory":"Membership Organization",
            "type":"Services"
        }
    ],
    "sg:phone":"+1 770 472 4191",
    "sg:postcode":"30274",
    "sg:province":"GA",
    "wof:name":"Allen Family Connection",
    "wof:placetype":"venue"
},
  "geometry": {"coordinates":[-84.409605,33.528195],"type":"Point"}
}