{
  "type": "Feature",
  "properties": {
    "addr:full":"3386 Windsong Ct Roswell GA 30075",
    "addr:housenumber":"3386",
    "addr:postcode":"30075",
    "addr:street":"Windsong Ct",
    "iso:country":"US",
    "sg:address":"3386 Windsong Ct",
    "sg:city":"Roswell",
    "sg:classifiers":[
        {
            "category":"Insurance",
            "subcategory":"Insurance Agent",
            "type":"Services"
        }
    ],
    "sg:phone":"+1 770 993 0545",
    "sg:postcode":"30075",
    "sg:province":"GA",
    "wof:name":"Claimspro",
    "wof:placetype":"venue"
},
  "geometry": {"coordinates":[-84.419899,34.031981],"type":"Point"}
}