{
  "type": "Feature",
  "properties": {
    "iso:country":"US",
    "sg:address":"3450 Venture Pkwy NW",
    "sg:city":"Duluth",
    "sg:classifiers":[
        {
            "category":"Travel",
            "subcategory":"Hotels & Motels",
            "type":"Entertainment"
        }
    ],
    "sg:phone":"+1 770 622 7277",
    "sg:postcode":"30096",
    "sg:province":"GA",
    "sg:website":"www.wingateinns.com",
    "wof:name":"Wingate Inn",
    "wof:placetype":"venue"
},
  "geometry": {"coordinates":[-84.126818,33.955932],"type":"Point"}
}