{
  "type": "Feature",
  "properties": {
    "iso:country":"US",
    "sg:address":"900 Holcomb Bridge Rd",
    "sg:city":"Roswell",
    "sg:classifiers":[
        {
            "category":"Health Services",
            "subcategory":"Clinic",
            "type":"Services"
        },
        {
            "category":"Health Services",
            "subcategory":"Medical Lab",
            "type":"Services"
        },
        {
            "category":"Personal",
            "type":"Services"
        }
    ],
    "sg:phone":"+1 866 867 0393",
    "sg:postcode":"30076",
    "sg:province":"GA",
    "sg:tags":[
        "laboratory",
        "testing",
        "paternity",
        "drug"
    ],
    "sg:website":"http://www.rapidstdtesting.com",
    "wof:name":"Rapid STD DNA Drug Testing ROSWELL",
    "wof:placetype":"venue"
},
  "geometry": {"coordinates":[-84.335159,34.028252],"type":"Point"}
}