{
  "type": "Feature",
  "properties": {
    "addr:full":"6063 Boat Rock Blvd SW Atlanta GA 30336",
    "addr:housenumber":"6063",
    "addr:postcode":"30336",
    "addr:street":"Boat Rock Blvd Sw",
    "iso:country":"US",
    "sg:address":"6063 Boat Rock Blvd SW",
    "sg:city":"Atlanta",
    "sg:classifiers":[
        {
            "category":"Freight",
            "type":"Transportation"
        }
    ],
    "sg:phone":"+1 404 349 4450",
    "sg:postcode":"30336",
    "sg:province":"GA",
    "sg:tags":[
        "logistics",
        "party",
        "general",
        "warehousing"
    ],
    "sg:website":"www.totalwarehousinginc.com",
    "wof:name":"Total Warehousing Inc",
    "wof:placetype":"venue"
},
  "geometry": {"coordinates":[-84.585548,33.726383],"type":"Point"}
}