{
  "type": "Feature",
  "properties": {
    "addr:full":"870 Westfield Row Acworth GA 30102",
    "addr:housenumber":"870",
    "addr:postcode":"30102",
    "addr:street":"Westfield Row",
    "iso:country":"US",
    "sg:address":"870 Westfield Row",
    "sg:city":"Acworth",
    "sg:classifiers":[
        {
            "category":"Banks & Credit Unions",
            "subcategory":"Financial Services",
            "type":"Services"
        }
    ],
    "sg:phone":"+1 770 419 7936",
    "sg:postcode":"30102",
    "sg:province":"GA",
    "sg:tags":[
        "investor"
    ],
    "wof:name":"Simco Investments",
    "wof:placetype":"venue"
},
  "geometry": {"coordinates":[-84.579397,34.06168],"type":"Point"}
}