{
  "type": "Feature",
  "properties": {
    "addr:full":"6130 Thomas Ln Cumming GA 30028",
    "addr:housenumber":"6130",
    "addr:postcode":"30028",
    "addr:street":"Thomas Ln",
    "iso:country":"US",
    "sg:address":"6130 Thomas Ln",
    "sg:city":"Cumming",
    "sg:classifiers":[
        {
            "category":"Building & Trades",
            "subcategory":"Landscaping Services",
            "type":"Services"
        }
    ],
    "sg:phone":"+1 770 887 6044",
    "sg:postcode":"30028",
    "sg:province":"GA",
    "wof:name":"Loggers Lawn Service",
    "wof:placetype":"venue"
},
  "geometry": {"coordinates":[-84.105552,34.324187],"type":"Point"}
}