{
  "type": "Feature",
  "properties": {
    "addr:full":"3104 E Shadowlawn Ave NE Atlanta GA 30305",
    "addr:housenumber":"3104",
    "addr:postcode":"30305",
    "addr:street":"E Shadowlawn Ave Ne",
    "iso:country":"US",
    "sg:address":"3104 E Shadowlawn Ave NE",
    "sg:city":"Atlanta",
    "sg:classifiers":[
        {
            "category":"Professional",
            "subcategory":"Management & Consulting",
            "type":"Services"
        }
    ],
    "sg:phone":"+1 404 262 3311",
    "sg:postcode":"30305",
    "sg:province":"GA",
    "sg:tags":[
        "marketing",
        "consultant"
    ],
    "wof:name":"Z Group",
    "wof:placetype":"venue"
},
  "geometry": {"coordinates":[-84.374179,33.840097],"type":"Point"}
}