{
  "type": "Feature",
  "properties": {
    "addr:full":"6057 New Peachtree Rd Atlanta GA 30340",
    "addr:housenumber":"6057",
    "addr:postcode":"30340",
    "addr:street":"New Peachtree Rd",
    "iso:country":"US",
    "sg:address":"6057 New Peachtree Rd",
    "sg:city":"Atlanta",
    "sg:classifiers":[
        {
            "category":"Manufacturing",
            "subcategory":"Printing",
            "type":"Manufacturing & Wholesale Goods"
        }
    ],
    "sg:phone":"+1 770 458 7454",
    "sg:postcode":"30340",
    "sg:province":"GA",
    "sg:tags":[
        "scanning",
        "printer",
        "supply",
        "equipment",
        "offset",
        "plotting"
    ],
    "sg:website":"http://www.fastprinting.net",
    "wof:name":"Fast Printing",
    "wof:placetype":"venue"
},
  "geometry": {"coordinates":[-84.278412,33.903301],"type":"Point"}
}