{
  "type": "Feature",
  "properties": {
    "iso:country":"US",
    "sg:address":"3274 Medlock Bridge Rd",
    "sg:city":"Norcross",
    "sg:classifiers":[
        {
            "category":"Professional",
            "subcategory":"Engineering",
            "type":"Services"
        },
        {
            "category":"Banks & Credit Unions",
            "subcategory":"Bank",
            "type":"Services"
        }
    ],
    "sg:phone":"+1 770 453 9771",
    "sg:postcode":"30092",
    "sg:province":"GA",
    "sg:tags":[
        "consulting",
        "actuary",
        "engineer"
    ],
    "sg:website":"www.merlinosinc.com",
    "wof:name":"Merlinos & Associates Inc",
    "wof:placetype":"venue"
},
  "geometry": {"coordinates":[-84.208355,33.961659],"type":"Point"}
}