{
  "type": "Feature",
  "properties": {
    "addr:full":"1563 N Decatur Road NE Atlanta GA 30307",
    "addr:housenumber":"1563",
    "addr:postcode":"30307",
    "addr:street":"N Decatur Road Ne",
    "iso:country":"US",
    "sg:address":"1563 N Decatur Road NE",
    "sg:city":"Atlanta",
    "sg:classifiers":[
        {
            "category":"Restaurant",
            "type":"Food & Drink"
        }
    ],
    "sg:phone":"+1 404 377 1999",
    "sg:postcode":"30307",
    "sg:province":"GA",
    "sg:website":"www.blimpie.com",
    "wof:name":"Blimpie Emory Village",
    "wof:placetype":"venue"
},
  "geometry": {"coordinates":[-84.326874,33.788051],"type":"Point"}
}