{
  "type": "Feature",
  "properties": {
    "addr:full":"1414 N Amanda Cir NE Atlanta GA 30329",
    "addr:housenumber":"1414",
    "addr:postcode":"30329",
    "addr:street":"N Amanda Cir Ne",
    "iso:country":"US",
    "sg:address":"1414 N Amanda Cir NE",
    "sg:city":"Atlanta",
    "sg:classifiers":[
        {
            "category":"Professional",
            "subcategory":"Employment Agencies",
            "type":"Services"
        }
    ],
    "sg:phone":"+1 404 634 9720",
    "sg:postcode":"30329",
    "sg:province":"GA",
    "wof:name":"Technical Chemical Recruiters",
    "wof:placetype":"venue"
},
  "geometry": {"coordinates":[-84.308857,33.821684],"type":"Point"}
}