{
  "type": "Feature",
  "properties": {
    "iso:country":"US",
    "sg:address":"4205 Canterbury Walk Dr",
    "sg:city":"Duluth",
    "sg:classifiers":[
        {
            "category":"Manufacturing",
            "subcategory":"Chemicals & Compounds",
            "type":"Manufacturing & Wholesale Goods"
        }
    ],
    "sg:phone":"+1 770 232 7582",
    "sg:postcode":"30097",
    "sg:province":"GA",
    "sg:tags":[
        "performance",
        "industrial",
        "mfg"
    ],
    "wof:name":"FMC Corporation",
    "wof:placetype":"venue"
},
  "geometry": {"coordinates":[-84.12124,34.026739],"type":"Point"}
}