{
  "type": "Feature",
  "properties": {
    "addr:full":"3000 Windy Hill Rd SE Marietta GA 30067",
    "addr:housenumber":"3000",
    "addr:postcode":"30067",
    "addr:street":"Windy Hill Rd Se",
    "iso:country":"US",
    "sg:address":"3000 Windy Hill Rd SE",
    "sg:city":"Marietta",
    "sg:classifiers":[
        {
            "category":"Insurance",
            "subcategory":"Hazard Insurance",
            "type":"Services"
        }
    ],
    "sg:phone":"+1 770 988 0253",
    "sg:postcode":"30067",
    "sg:province":"GA",
    "sg:website":"http://www.allstate.com",
    "wof:name":"Allstate Insurance Companies",
    "wof:placetype":"venue"
},
  "geometry": {"coordinates":[-84.467758,33.90451],"type":"Point"}
}