{
  "type": "Feature",
  "properties": {
    "addr:full":"7057 Wind Run Way Stone Mountain GA 30087",
    "addr:housenumber":"7057",
    "addr:postcode":"30087",
    "addr:street":"Wind Run Way",
    "iso:country":"US",
    "sg:address":"7057 Wind Run Way",
    "sg:city":"Stone Mountain",
    "sg:classifiers":[
        {
            "category":"Professional",
            "subcategory":"Credit Reporting & Collection",
            "type":"Services"
        }
    ],
    "sg:phone":"+1 770 498 6160",
    "sg:postcode":"30087",
    "sg:province":"GA",
    "sg:tags":[
        "agency"
    ],
    "wof:name":"Asset Recovery Management",
    "wof:placetype":"venue"
},
  "geometry": {"coordinates":[-84.10077200000001,33.79254],"type":"Point"}
}