{
  "type": "Feature",
  "properties": {
    "iso:country":"US",
    "sg:address":"9603 Leatherwood Ln",
    "sg:city":"Douglasville",
    "sg:classifiers":[
        {
            "category":"Professional",
            "type":"Services"
        }
    ],
    "sg:phone":"+1 770 942 6894",
    "sg:postcode":"30135",
    "sg:province":"GA",
    "wof:name":"Randall Knotts",
    "wof:placetype":"venue"
},
  "geometry": {"coordinates":[-84.718132,33.72352],"type":"Point"}
}