{
  "type": "Feature",
  "properties": {
    "iso:country":"US",
    "sg:address":"3041 Landrum Dr SW",
    "sg:city":"Atlanta",
    "sg:classifiers":[
        {
            "category":"Professional",
            "subcategory":"Secretarial Services",
            "type":"Services"
        }
    ],
    "sg:phone":"+1 404 349 6027",
    "sg:postcode":"30311",
    "sg:province":"GA",
    "sg:tags":[
        "reporting"
    ],
    "wof:name":"In A Hurry Secretary",
    "wof:placetype":"venue"
},
  "geometry": {"coordinates":[-84.486954,33.706458],"type":"Point"}
}