{
  "type": "Feature",
  "properties": {
    "addr:full":"2266 Ingleside Ave Macon GA 31204",
    "addr:housenumber":"2266",
    "addr:postcode":"31204",
    "addr:street":"Ingleside Ave",
    "iso:country":"US",
    "sg:address":"2266 Ingleside Ave",
    "sg:city":"Macon",
    "sg:classifiers":[
        {
            "category":"Health Services",
            "subcategory":"Doctor",
            "type":"Services"
        }
    ],
    "sg:phone":"+1 478 745 6050",
    "sg:postcode":"31204",
    "sg:province":"GA",
    "sg:tags":[
        "medical"
    ],
    "wof:name":"Ridley Charles III M D",
    "wof:placetype":"venue"
},
  "geometry": {"coordinates":[-83.652586,32.853671],"type":"Point"}
}