{
  "type": "Feature",
  "properties": {
    "addr:full":"515 John Wesley Dobbs Ave NE Atlanta GA 30312",
    "addr:housenumber":"515",
    "addr:postcode":"30312",
    "addr:street":"John Wesley Dobbs Ave Ne",
    "iso:country":"US",
    "sg:address":"515 John Wesley Dobbs Ave NE",
    "sg:city":"Atlanta",
    "sg:classifiers":[
        {
            "category":"Social Services",
            "type":"Services"
        }
    ],
    "sg:phone":"+1 404 523 2866",
    "sg:postcode":"30312",
    "sg:province":"GA",
    "sg:tags":[
        "senior",
        "citizen"
    ],
    "wof:name":"Helene Mills Sr Ctr Fulton Co",
    "wof:placetype":"venue"
},
  "geometry": {"coordinates":[-84.371337,33.759267],"type":"Point"}
}