{
  "type": "Feature",
  "properties": {
    "iso:country":"US",
    "sg:address":"79 Bennett Xing",
    "sg:city":"Odum",
    "sg:classifiers":[
        {
            "category":"Manufacturing",
            "subcategory":"Apparel",
            "type":"Manufacturing & Wholesale Goods"
        }
    ],
    "sg:phone":"+1 912 586 2227",
    "sg:postcode":"31555",
    "sg:province":"GA",
    "sg:tags":[
        "furnishing",
        "mfg"
    ],
    "wof:name":"Grandmas Sewing House",
    "wof:placetype":"venue"
},
  "geometry": {"coordinates":[-81.987207,31.632121],"type":"Point"}
}