{
  "type": "Feature",
  "properties": {
    "addr:full":"3048 Clairmont Rd NE Atlanta GA 30329",
    "addr:housenumber":"3048",
    "addr:postcode":"30329",
    "addr:street":"Clairmont Rd Ne",
    "iso:country":"US",
    "sg:address":"3048 Clairmont Rd NE",
    "sg:city":"Atlanta",
    "sg:classifiers":[
        {
            "category":"Professional",
            "type":"Services"
        }
    ],
    "sg:phone":"+1 404 376 5821",
    "sg:postcode":"30329",
    "sg:province":"GA",
    "wof:name":"Office Images",
    "wof:placetype":"venue"
},
  "geometry": {"coordinates":[-84.31532,33.845666],"type":"Point"}
}