{
  "type": "Feature",
  "properties": {
    "addr:full":"104 Acacia Dr Kingsland GA 31548",
    "addr:housenumber":"104",
    "addr:postcode":"31548",
    "addr:street":"Acacia Dr",
    "iso:country":"US",
    "sg:address":"104 Acacia Dr",
    "sg:city":"Kingsland",
    "sg:classifiers":[
        {
            "category":"Professional",
            "subcategory":"Management & Consulting",
            "type":"Services"
        }
    ],
    "sg:phone":"+1 912 576 1356",
    "sg:postcode":"31548",
    "sg:province":"GA",
    "sg:tags":[
        "consultant"
    ],
    "wof:name":"William Terrell Consulting",
    "wof:placetype":"venue"
},
  "geometry": {"coordinates":[-81.645465,30.800796],"type":"Point"}
}