{
  "type": "Feature",
  "properties": {
    "addr:full":"13015 Brown Bridge Rd Covington GA 30016",
    "addr:housenumber":"13015",
    "addr:postcode":"30016",
    "addr:street":"Brown Bridge Rd",
    "iso:country":"US",
    "sg:address":"13015 Brown Bridge Rd",
    "sg:city":"Covington",
    "sg:classifiers":[
        {
            "category":"Restaurant",
            "type":"Food & Drink"
        }
    ],
    "sg:phone":"+1 770 787 0740",
    "sg:postcode":"30016",
    "sg:province":"GA",
    "sg:tags":[
        "eating"
    ],
    "wof:name":"Wing Cafe",
    "wof:placetype":"venue"
},
  "geometry": {"coordinates":[-83.964493,33.578585],"type":"Point"}
}