{
  "type": "Feature",
  "properties": {
    "addr:full":"53 E Jarman St Hazlehurst GA 31539",
    "addr:housenumber":"53",
    "addr:postcode":"31539",
    "addr:street":"E Jarman St",
    "iso:country":"US",
    "sg:address":"53 E Jarman St",
    "sg:city":"Hazlehurst",
    "sg:classifiers":[
        {
            "category":"Travel",
            "subcategory":"Travel Agent",
            "type":"Entertainment"
        }
    ],
    "sg:phone":"+1 912 375 3777",
    "sg:postcode":"31539",
    "sg:province":"GA",
    "sg:tags":[
        "agency",
        "bureau"
    ],
    "wof:name":"Cruise One",
    "wof:placetype":"venue"
},
  "geometry": {"coordinates":[-82.592641,31.86816],"type":"Point"}
}