{
  "type": "Feature",
  "properties": {
    "iso:country":"US",
    "sg:address":"6617 Gunstock Ln",
    "sg:city":"Tucker",
    "sg:classifiers":[
        {
            "category":"Professional",
            "subcategory":"Business Services",
            "type":"Services"
        }
    ],
    "sg:phone":"+1 770 938 6699",
    "sg:postcode":"30084",
    "sg:province":"GA",
    "sg:tags":[
        "consultant",
        "coach"
    ],
    "wof:name":"K2 Horizon",
    "wof:placetype":"venue"
},
  "geometry": {"coordinates":[-84.210256,33.885866],"type":"Point"}
}