{
  "type": "Feature",
  "properties": {
    "addr:full":"2587 Sherbrooke Dr NE Atlanta GA 30345",
    "addr:housenumber":"2587",
    "addr:postcode":"30345",
    "addr:street":"Sherbrooke Dr Ne",
    "iso:country":"US",
    "sg:address":"2587 Sherbrooke Dr NE",
    "sg:city":"Atlanta",
    "sg:classifiers":[
        {
            "category":"Retail",
            "subcategory":"Auto Repair",
            "type":"Services"
        }
    ],
    "sg:phone":"+1 404 321 7619",
    "sg:postcode":"30345",
    "sg:province":"GA",
    "sg:tags":[
        "automotive"
    ],
    "wof:name":"Wagner Wheels",
    "wof:placetype":"venue"
},
  "geometry": {"coordinates":[-84.284154,33.857253],"type":"Point"}
}