{
  "type": "Feature",
  "properties": {
    "addr:full":"5895 Garber Dr NE Atlanta GA 30328",
    "addr:housenumber":"5895",
    "addr:postcode":"30328",
    "addr:street":"Garber Dr Ne",
    "iso:country":"US",
    "sg:address":"5895 Garber Dr NE",
    "sg:city":"Atlanta",
    "sg:classifiers":[
        {
            "category":"Restaurant",
            "type":"Food & Drink"
        }
    ],
    "sg:phone":"+1 404 303 7827",
    "sg:postcode":"30328",
    "sg:province":"GA",
    "sg:tags":[
        "barbeque"
    ],
    "wof:name":"Five Star Barbecue",
    "wof:placetype":"venue"
},
  "geometry": {"coordinates":[-84.369086,33.915893],"type":"Point"}
}