{
  "type": "Feature",
  "properties": {
    "addr:full":"323 Possum Trl Guyton GA 31312",
    "addr:housenumber":"323",
    "addr:postcode":"31312",
    "addr:street":"Possum Trl",
    "iso:country":"US",
    "sg:address":"323 Possum Trl",
    "sg:city":"Guyton",
    "sg:classifiers":[
        {
            "category":"Professional",
            "type":"Services"
        }
    ],
    "sg:phone":"+1 912 728 6901",
    "sg:postcode":"31312",
    "sg:province":"GA",
    "wof:name":"Savannah Power",
    "wof:placetype":"venue"
},
  "geometry": {"coordinates":[-81.404129,32.220044],"type":"Point"}
}