{
  "type": "Feature",
  "properties": {
    "addr:full":"1120 E Church St Monroe GA 30655",
    "addr:housenumber":"1120",
    "addr:postcode":"30655",
    "addr:street":"E Church St",
    "iso:country":"US",
    "sg:address":"1120 E Church St",
    "sg:city":"Monroe",
    "sg:classifiers":[
        {
            "category":"Place Of Worship",
            "subcategory":"Church",
            "type":"Public Place"
        },
        {
            "category":"Place Of Worship",
            "type":"Public Place"
        }
    ],
    "sg:phone":"+1 770 266 0340",
    "sg:postcode":"30655",
    "sg:province":"GA",
    "sg:tags":[
        "churches-interdenominational",
        "churches-various",
        "denomination"
    ],
    "wof:name":"East Church Street Center",
    "wof:placetype":"venue"
},
  "geometry": {"coordinates":[-83.694757,33.79306],"type":"Point"}
}