{
  "type": "Feature",
  "properties": {
    "addr:full":"1706 N Expy Griffin GA 30223",
    "addr:housenumber":"1706",
    "addr:postcode":"30223",
    "addr:street":"N Expy",
    "iso:country":"US",
    "sg:address":"1706 N Expy",
    "sg:city":"Griffin",
    "sg:classifiers":[
        {
            "category":"Insurance",
            "subcategory":"Insurance Agent",
            "type":"Services"
        }
    ],
    "sg:phone":"+1 770 228 6164",
    "sg:postcode":"30223",
    "sg:province":"GA",
    "wof:name":"State Farm Insurance",
    "wof:placetype":"venue"
},
  "geometry": {"coordinates":[-84.287898,33.254975],"type":"Point"}
}