{
  "type": "Feature",
  "properties": {
    "iso:country":"US",
    "sg:address":"111 Blankets Creek Way",
    "sg:city":"Canton",
    "sg:classifiers":[
        {
            "category":"Personal",
            "type":"Services"
        }
    ],
    "sg:phone":"+1 770 704 4502",
    "sg:postcode":"30114",
    "sg:province":"GA",
    "wof:name":"Cherish Weddings",
    "wof:placetype":"venue"
},
  "geometry": {"coordinates":[-84.54615200000001,34.166907],"type":"Point"}
}