{
  "type": "Feature",
  "properties": {
    "addr:full":"760 S Main St Hinesville GA 31313",
    "addr:housenumber":"760",
    "addr:postcode":"31313",
    "addr:street":"S Main St",
    "iso:country":"US",
    "sg:address":"760 S Main St",
    "sg:city":"Hinesville",
    "sg:classifiers":[
        {
            "category":"Social Services",
            "subcategory":"Adult Care",
            "type":"Services"
        }
    ],
    "sg:phone":"+1 912 368 7472",
    "sg:postcode":"31313",
    "sg:province":"GA",
    "sg:tags":[
        "residential",
        "provider"
    ],
    "wof:name":"Liberty Group Homes Inc",
    "wof:placetype":"venue"
},
  "geometry": {"coordinates":[-81.603937,31.827085],"type":"Point"}
}