{
  "type": "Feature",
  "properties": {
    "iso:country":"US",
    "sg:address":"4675 River Green Pkwy",
    "sg:city":"Duluth",
    "sg:classifiers":[
        {
            "category":"Professional",
            "type":"Services"
        }
    ],
    "sg:phone":"+1 770 623 4064",
    "sg:postcode":"30096",
    "sg:province":"GA",
    "wof:name":"Battey Machinery",
    "wof:placetype":"venue"
},
  "geometry": {"coordinates":[-84.173509,34.0164],"type":"Point"}
}