{
  "type": "Feature",
  "properties": {
    "iso:country":"US",
    "sg:address":"3233 Highpoint Ct",
    "sg:city":"Snellville",
    "sg:classifiers":[
        {
            "category":"Food & Beverages",
            "subcategory":"Liquor & Beverages",
            "type":"Retail Goods"
        },
        {
            "category":"Food & Beverages",
            "subcategory":"Groceries & Convenience Stores",
            "type":"Retail Goods"
        }
    ],
    "sg:phone":"+1 770 905 2133",
    "sg:postcode":"30078",
    "sg:province":"GA",
    "sg:tags":[
        "juice",
        "bottler",
        "beverages-distributors"
    ],
    "wof:name":"Dlja Juices",
    "wof:placetype":"venue"
},
  "geometry": {"coordinates":[-84.042733,33.848872],"type":"Point"}
}