{
  "type": "Feature",
  "properties": {
    "addr:full":"3480 Ansley Park Dr Suwanee GA 30024",
    "addr:housenumber":"3480",
    "addr:postcode":"30024",
    "addr:street":"Ansley Park Dr",
    "iso:country":"US",
    "sg:address":"3480 Ansley Park Dr",
    "sg:city":"Suwanee",
    "sg:classifiers":[
        {
            "category":"Social Services",
            "subcategory":"Child Care",
            "type":"Services"
        }
    ],
    "sg:phone":"+1 770 831 7802",
    "sg:postcode":"30024",
    "sg:province":"GA",
    "sg:tags":[
        "day"
    ],
    "wof:name":"Heavenly Treasures",
    "wof:placetype":"venue"
},
  "geometry": {"coordinates":[-84.047579,34.04749],"type":"Point"}
}