{
  "type": "Feature",
  "properties": {
    "iso:country":"US",
    "sg:address":"101 Elberta Rd",
    "sg:city":"Warner Robins",
    "sg:classifiers":[
        {
            "category":"Professional",
            "subcategory":"Business Services",
            "type":"Services"
        }
    ],
    "sg:phone":"+1 478 918 0440",
    "sg:postcode":"31093",
    "sg:province":"GA",
    "wof:name":"King Melody",
    "wof:placetype":"venue"
},
  "geometry": {"coordinates":[-83.618888,32.659227],"type":"Point"}
}