{
  "type": "Feature",
  "properties": {
    "addr:full":"103 Eagle Rd Brunswick GA 31523",
    "addr:housenumber":"103",
    "addr:postcode":"31523",
    "addr:street":"Eagle Rd",
    "iso:country":"US",
    "sg:address":"103 Eagle Rd",
    "sg:city":"Brunswick",
    "sg:classifiers":[
        {
            "category":"Building & Trades",
            "subcategory":"Landscaping Services",
            "type":"Services"
        }
    ],
    "sg:phone":"+1 912 262 9257",
    "sg:postcode":"31523",
    "sg:province":"GA",
    "sg:tags":[
        "lawn"
    ],
    "wof:name":"N Neat Natural Inc",
    "wof:placetype":"venue"
},
  "geometry": {"coordinates":[-81.543789,31.236735],"type":"Point"}
}