{
  "type": "Feature",
  "properties": {
    "addr:full":"2325 US Hwy 41 Perry GA 31069",
    "addr:housenumber":"2325",
    "addr:postcode":"31069",
    "addr:street":"Us Hwy 41",
    "iso:country":"US",
    "sg:address":"2325 US Hwy 41",
    "sg:city":"Perry",
    "sg:phone":"+1 478 987 4176",
    "sg:postcode":"31069",
    "sg:province":"GA",
    "sg:tags":[
        "farm",
        "field",
        "crop"
    ],
    "wof:name":"Highlands Ranch",
    "wof:placetype":"venue"
},
  "geometry": {"coordinates":[-83.777494,32.411905],"type":"Point"}
}