{
  "type": "Feature",
  "properties": {
    "iso:country":"US",
    "sg:address":"3161 Warren Rd",
    "sg:city":"Decatur",
    "sg:classifiers":[
        {
            "category":"Government",
            "subcategory":"Fire Station",
            "type":"Public Place"
        }
    ],
    "sg:phone":"+1 404 244 4910",
    "sg:postcode":"30034",
    "sg:province":"GA",
    "sg:tags":[
        "protection"
    ],
    "wof:name":"Fire Dept- Academy",
    "wof:placetype":"venue"
},
  "geometry": {"coordinates":[-84.26892599999999,33.704478],"type":"Point"}
}