{
  "type": "Feature",
  "properties": {
    "addr:full":"465 Maltbie St Lawrenceville GA 30045",
    "addr:housenumber":"465",
    "addr:postcode":"30045",
    "addr:street":"Maltbie St",
    "iso:country":"US",
    "sg:address":"465 Maltbie St",
    "sg:city":"Lawrenceville",
    "sg:classifiers":[
        {
            "category":"Professional",
            "subcategory":"Business Services",
            "type":"Services"
        },
        {
            "category":"Professional",
            "subcategory":"Management & Consulting",
            "type":"Services"
        }
    ],
    "sg:phone":"+1 770 237 9665",
    "sg:postcode":"30045",
    "sg:province":"GA",
    "sg:tags":[
        "consultant",
        "electrical",
        "safety",
        "contractor"
    ],
    "wof:name":"Columbus Fire & Safety",
    "wof:placetype":"venue"
},
  "geometry": {"coordinates":[-83.999167,33.963723],"type":"Point"}
}