{
  "type": "Feature",
  "properties": {
    "iso:country":"US",
    "sg:address":"555 Spindlewick Dr",
    "sg:city":"Atlanta",
    "sg:classifiers":[
        {
            "category":"Professional",
            "subcategory":"Business Services",
            "type":"Services"
        }
    ],
    "sg:phone":"+1 770 522 0403",
    "sg:postcode":"30350",
    "sg:province":"GA",
    "wof:name":"Revealing Knowledge Group",
    "wof:placetype":"venue"
},
  "geometry": {"coordinates":[-84.344976,33.972896],"type":"Point"}
}