{
  "type": "Feature",
  "properties": {
    "addr:full":"5613 Bland Dairy Dr Valdosta GA 31601",
    "addr:housenumber":"5613",
    "addr:postcode":"31601",
    "addr:street":"Bland Dairy Dr",
    "iso:country":"US",
    "sg:address":"5613 Bland Dairy Dr",
    "sg:city":"Valdosta",
    "sg:classifiers":[
        {
            "category":"Real Estate",
            "subcategory":"Real Estate Services",
            "type":"Services"
        },
        {
            "category":"Real Estate",
            "subcategory":"Real Estate Agent",
            "type":"Services"
        }
    ],
    "sg:phone":"+1 229 559 4300",
    "sg:postcode":"31601",
    "sg:province":"GA",
    "sg:tags":[
        "management"
    ],
    "wof:name":"Hku Enterprises",
    "wof:placetype":"venue"
},
  "geometry": {"coordinates":[-83.335668,30.69013],"type":"Point"}
}