{
  "type": "Feature",
  "properties": {
    "iso:country":"US",
    "sg:address":"6761 Highway 85",
    "sg:city":"Riverdale",
    "sg:classifiers":[
        {
            "category":"Building & Trades",
            "subcategory":"Locksmith",
            "type":"Services"
        }
    ],
    "sg:phone":"+1 770 872 0132",
    "sg:postcode":"30274",
    "sg:province":"GA",
    "sg:tags":[
        "key"
    ],
    "wof:name":"All Day Emergency Locksmith",
    "wof:placetype":"venue"
},
  "geometry": {"coordinates":[-84.412914,33.570192],"type":"Point"}
}