{
  "type": "Feature",
  "properties": {
    "addr:full":"2211 Chattanooga Rd Dalton GA 30720",
    "addr:housenumber":"2211",
    "addr:postcode":"30720",
    "addr:street":"Chattanooga Rd",
    "iso:country":"US",
    "sg:address":"2211 Chattanooga Rd",
    "sg:city":"Dalton",
    "sg:classifiers":[
        {
            "category":"Recreation",
            "subcategory":"Arcade",
            "type":"Entertainment"
        }
    ],
    "sg:phone":"+1 706 370 5883",
    "sg:postcode":"30720",
    "sg:province":"GA",
    "sg:tags":[
        "video"
    ],
    "wof:name":"Sports Lotto",
    "wof:placetype":"venue"
},
  "geometry": {"coordinates":[-84.987081,34.798689],"type":"Point"}
}