{
  "type": "Feature",
  "properties": {
    "iso:country":"US",
    "sg:address":"2764 Cumberland Blvd SE",
    "sg:city":"Smyrna",
    "sg:classifiers":[
        {
            "category":"Social Services",
            "subcategory":"Child Care",
            "type":"Services"
        }
    ],
    "sg:phone":"+1 770 434 4774",
    "sg:postcode":"30080",
    "sg:province":"GA",
    "sg:tags":[
        "day"
    ],
    "sg:website":"www.daycare-ratedk.com",
    "wof:name":"Rated K For Kids Only",
    "wof:placetype":"venue"
},
  "geometry": {"coordinates":[-84.476738,33.886112],"type":"Point"}
}