{
  "type": "Feature",
  "properties": {
    "addr:full":"189 W Athens St Winder GA 30680",
    "addr:housenumber":"189",
    "addr:postcode":"30680",
    "addr:street":"W Athens St",
    "iso:country":"US",
    "sg:address":"189 W Athens St",
    "sg:city":"Winder",
    "sg:classifiers":[
        {
            "category":"Shopping",
            "subcategory":"Used Merchandise",
            "type":"Retail Goods"
        }
    ],
    "sg:phone":"+1 770 867 1009",
    "sg:postcode":"30680",
    "sg:province":"GA",
    "sg:tags":[
        "resale",
        "shop"
    ],
    "wof:name":"Tutti Frutti's",
    "wof:placetype":"venue"
},
  "geometry": {"coordinates":[-83.717516,33.989841],"type":"Point"}
}