{
  "type": "Feature",
  "properties": {
    "addr:full":"3658 Walton Way Exd Augusta GA 30909",
    "addr:housenumber":"3658",
    "addr:postcode":"30909",
    "addr:street":"Walton Way Exd",
    "iso:country":"US",
    "sg:address":"3658 Walton Way Exd",
    "sg:city":"Augusta",
    "sg:classifiers":[
        {
            "category":"Shopping",
            "subcategory":"Computers & Home Electronics",
            "type":"Retail Goods"
        }
    ],
    "sg:phone":"+1 706 733 4835",
    "sg:postcode":"30909",
    "sg:province":"GA",
    "sg:tags":[
        "equipment",
        "electronic",
        "supply"
    ],
    "wof:name":"Circuit City",
    "wof:placetype":"venue"
},
  "geometry": {"coordinates":[-82.07583099999999,33.491278],"type":"Point"}
}