{
  "type": "Feature",
  "properties": {
    "iso:country":"US",
    "sg:address":"90 W Coffee St",
    "sg:city":"Hazlehurst",
    "sg:phone":"+1 912 375 2396",
    "sg:postcode":"31539",
    "sg:province":"GA",
    "wof:name":"Sisters' Kountry Kitchen",
    "wof:placetype":"venue"
},
  "geometry": {"coordinates":[-82.597257,31.877892],"type":"Point"}
}