{
  "type": "Feature",
  "properties": {
    "iso:country":"US",
    "sg:address":"2673 Moss Ln SE",
    "sg:city":"Marietta",
    "sg:classifiers":[
        {
            "category":"Professional",
            "type":"Services"
        }
    ],
    "sg:phone":"+1 770 405 8116",
    "sg:postcode":"30067",
    "sg:province":"GA",
    "sg:tags":[
        "transportation"
    ],
    "wof:name":"Wellcare Transportation Incorporated",
    "wof:placetype":"venue"
},
  "geometry": {"coordinates":[-84.476248,33.917586],"type":"Point"}
}