{
  "type": "Feature",
  "properties": {
    "iso:country":"US",
    "sg:address":"202 East Ave",
    "sg:city":"Cedartown",
    "sg:classifiers":[
        {
            "category":"Restaurant",
            "type":"Food & Drink"
        }
    ],
    "sg:menulink":"http://www.allmenus.com/ga/cedartown/76162-dominos-pizza/menu/",
    "sg:phone":"+1 770 748 0909",
    "sg:postcode":"30125",
    "sg:province":"GA",
    "sg:tags":[
        "american",
        "wing",
        "pizza"
    ],
    "wof:name":"Domino's Pizza",
    "wof:placetype":"venue"
},
  "geometry": {"coordinates":[-85.253598,34.014381],"type":"Point"}
}