{
  "type": "Feature",
  "properties": {
    "iso:country":"US",
    "sg:address":"44 Academy St",
    "sg:city":"Alpharetta",
    "sg:classifiers":[
        {
            "category":"Education",
            "subcategory":"School",
            "type":"Public Place"
        }
    ],
    "sg:phone":"+1 770 475 5762",
    "sg:postcode":"30004",
    "sg:province":"GA",
    "sg:website":"www.alpharettachristianacademy.com",
    "wof:name":"Alpharetta Christain Academy",
    "wof:placetype":"venue"
},
  "geometry": {"coordinates":[-84.293503,34.0755],"type":"Point"}
}