{
  "type": "Feature",
  "properties": {
    "addr:full":"1270 Castle Pointe Ln Grayson GA 30017",
    "addr:housenumber":"1270",
    "addr:postcode":"30017",
    "addr:street":"Castle Pointe Ln",
    "iso:country":"US",
    "sg:address":"1270 Castle Pointe Ln",
    "sg:city":"Grayson",
    "sg:classifiers":[
        {
            "category":"Real Estate",
            "subcategory":"Real Estate Agent",
            "type":"Services"
        }
    ],
    "sg:phone":"+1 770 978 6818",
    "sg:postcode":"30017",
    "sg:province":"GA",
    "sg:tags":[
        "appraiser"
    ],
    "wof:name":"Integrity Appraisals Inc",
    "wof:placetype":"venue"
},
  "geometry": {"coordinates":[-83.990781,33.892636],"type":"Point"}
}