{
  "type": "Feature",
  "properties": {
    "addr:full":"26 Welcome Rd Hartwell GA 30643",
    "addr:housenumber":"26",
    "addr:postcode":"30643",
    "addr:street":"Welcome Rd",
    "iso:country":"US",
    "sg:address":"26 Welcome Rd",
    "sg:city":"Hartwell",
    "sg:classifiers":[
        {
            "category":"Organizations",
            "subcategory":"Religious Organization",
            "type":"Services"
        }
    ],
    "sg:phone":"+1 706 376 2644",
    "sg:postcode":"30643",
    "sg:province":"GA",
    "wof:name":"New Prospect Baptist Church",
    "wof:placetype":"venue"
},
  "geometry": {"coordinates":[-82.904858,34.418474],"type":"Point"}
}