{
  "type": "Feature",
  "properties": {
    "iso:country":"US",
    "sg:address":"117 Caren Way",
    "sg:city":"Stockbridge",
    "sg:classifiers":[
        {
            "category":"Wholesale",
            "subcategory":"Home Furnishings",
            "type":"Manufacturing & Wholesale Goods"
        }
    ],
    "sg:phone":"+1 770 474 6081",
    "sg:postcode":"30281",
    "sg:province":"GA",
    "wof:name":"Southern Floor Matting Inc",
    "wof:placetype":"venue"
},
  "geometry": {"coordinates":[-84.21348999999999,33.572806],"type":"Point"}
}