{
  "type": "Feature",
  "properties": {
    "addr:full":"10 Moreland Ave NE Atlanta GA 30307",
    "addr:housenumber":"10",
    "addr:postcode":"30307",
    "addr:street":"Moreland Ave Ne",
    "iso:country":"US",
    "sg:address":"10 Moreland Ave NE",
    "sg:city":"Atlanta",
    "sg:classifiers":[
        {
            "category":"Retail",
            "subcategory":"Emissions Testing",
            "type":"Services"
        }
    ],
    "sg:phone":"+1 404 963 2566",
    "sg:postcode":"30307",
    "sg:province":"GA",
    "sg:tags":[
        "inspection"
    ],
    "wof:name":"Mid City Emission And Detail",
    "wof:placetype":"venue"
},
  "geometry": {"coordinates":[-84.349186,33.75376],"type":"Point"}
}