{
  "type": "Feature",
  "properties": {
    "iso:country":"US",
    "sg:address":"52 Shady Valley Dr SW",
    "sg:city":"Cartersville",
    "sg:classifiers":[
        {
            "category":"Professional",
            "subcategory":"Business Services",
            "type":"Services"
        }
    ],
    "sg:phone":"+1 770 377 3161",
    "sg:postcode":"30120",
    "sg:province":"GA",
    "wof:name":"Cardinal Interior Construction",
    "wof:placetype":"venue"
},
  "geometry": {"coordinates":[-84.863651,34.179079],"type":"Point"}
}