{
  "type": "Feature",
  "properties": {
    "addr:full":"4687 Georgia Highway 120 Buchanan GA 30113",
    "addr:housenumber":"4687",
    "addr:postcode":"30113",
    "addr:street":"Georgia Highway 120",
    "iso:country":"US",
    "sg:address":"4687 Georgia Highway 120",
    "sg:city":"Buchanan",
    "sg:classifiers":[
        {
            "category":"Restaurant",
            "type":"Food & Drink"
        }
    ],
    "sg:menulink":"http://www.allmenus.com/ga/buchanan/132293-subway/menu/",
    "sg:phone":"+1 770 646 5335",
    "sg:postcode":"30113",
    "sg:province":"GA",
    "sg:tags":[
        "american",
        "sandwich"
    ],
    "wof:name":"Subway",
    "wof:placetype":"venue"
},
  "geometry": {"coordinates":[-85.177334,33.80355],"type":"Point"}
}