{
  "type": "Feature",
  "properties": {
    "addr:full":"3867 Spring Meadow Dr Acworth GA 30101",
    "addr:housenumber":"3867",
    "addr:postcode":"30101",
    "addr:street":"Spring Meadow Dr",
    "iso:country":"US",
    "sg:address":"3867 Spring Meadow Dr",
    "sg:city":"Acworth",
    "sg:classifiers":[
        {
            "category":"Building & Trades",
            "subcategory":"Construction",
            "type":"Services"
        }
    ],
    "sg:phone":"+1 404 895 9059",
    "sg:postcode":"30101",
    "sg:province":"GA",
    "sg:tags":[
        "maintenance",
        "contractor"
    ],
    "wof:name":"Daves Cleaning",
    "wof:placetype":"venue"
},
  "geometry": {"coordinates":[-84.66740299999999,34.072415],"type":"Point"}
}