{
  "type": "Feature",
  "properties": {
    "iso:country":"US",
    "sg:address":"1000 Johnson Ferry Rd",
    "sg:city":"Atlanta",
    "sg:classifiers":[
        {
            "category":"Health Services",
            "subcategory":"Clinic",
            "type":"Services"
        }
    ],
    "sg:phone":"+1 404 851 8850",
    "sg:postcode":"30342",
    "sg:province":"GA",
    "sg:tags":[
        "treatment",
        "cancer",
        "center"
    ],
    "wof:name":"Institute For Cancer Control",
    "wof:placetype":"venue"
},
  "geometry": {"coordinates":[-84.352891,33.907404],"type":"Point"}
}