{
  "type": "Feature",
  "properties": {
    "iso:country":"US",
    "sg:address":"3585 Pechtre Indstrl Blvd",
    "sg:city":"Duluth",
    "sg:classifiers":[
        {
            "category":"Health Services",
            "subcategory":"Dentist",
            "type":"Services"
        }
    ],
    "sg:phone":"+1 770 623 6714",
    "sg:postcode":"30096",
    "sg:province":"GA",
    "wof:name":"Dr B Patrick Dongieux",
    "wof:placetype":"venue"
},
  "geometry": {"coordinates":[-84.144402,33.968102],"type":"Point"}
}