{
  "type": "Feature",
  "properties": {
    "iso:country":"US",
    "sg:address":"123 Luckie St NW",
    "sg:city":"Atlanta",
    "sg:classifiers":[
        {
            "category":"Banks & Credit Unions",
            "subcategory":"Bank",
            "type":"Services"
        }
    ],
    "sg:phone":"+1 404 522 1625",
    "sg:postcode":"30303",
    "sg:province":"GA",
    "sg:tags":[
        "loan",
        "real estate"
    ],
    "wof:name":"First Georgia Mortgage",
    "wof:placetype":"venue"
},
  "geometry": {"coordinates":[-84.39039200000001,33.758171],"type":"Point"}
}