{
  "type": "Feature",
  "properties": {
    "iso:country":"US",
    "sg:address":"877 Mulberry St",
    "sg:city":"Macon",
    "sg:classifiers":[
        {
            "category":"Professional",
            "subcategory":"Lawyer & Legal Services",
            "type":"Services"
        }
    ],
    "sg:phone":"+1 478 746 3583",
    "sg:postcode":"31201",
    "sg:province":"GA",
    "wof:name":"Lane Walter J Jr",
    "wof:placetype":"venue"
},
  "geometry": {"coordinates":[-83.63208299999999,32.840363],"type":"Point"}
}