{
  "type": "Feature",
  "properties": {
    "addr:full":"2187 Tilson Cir Decatur GA 30032",
    "addr:housenumber":"2187",
    "addr:postcode":"30032",
    "addr:street":"Tilson Cir",
    "iso:country":"US",
    "sg:address":"2187 Tilson Cir",
    "sg:city":"Decatur",
    "sg:classifiers":[
        {
            "category":"Building & Trades",
            "subcategory":"Cleaning & Sanitation",
            "type":"Services"
        }
    ],
    "sg:phone":"+1 404 475 8869",
    "sg:postcode":"30032",
    "sg:province":"GA",
    "sg:tags":[
        "janitor"
    ],
    "wof:name":"Second Look Cleaning Svc",
    "wof:placetype":"venue"
},
  "geometry": {"coordinates":[-84.293907,33.723918],"type":"Point"}
}