{
  "type": "Feature",
  "properties": {
    "addr:full":"1180 Franklin Rd SE Marietta GA 30067",
    "addr:housenumber":"1180",
    "addr:postcode":"30067",
    "addr:street":"Franklin Rd Se",
    "iso:country":"US",
    "sg:address":"1180 Franklin Rd SE",
    "sg:city":"Marietta",
    "sg:classifiers":[
        {
            "category":"Professional",
            "subcategory":"Lawyer & Legal Services",
            "type":"Services"
        }
    ],
    "sg:phone":"+1 770 612 2626",
    "sg:postcode":"30067",
    "sg:province":"GA",
    "sg:tags":[
        "attorney"
    ],
    "wof:name":"Gordon & Boykin",
    "wof:placetype":"venue"
},
  "geometry": {"coordinates":[-84.492093,33.923644],"type":"Point"}
}