{
  "type": "Feature",
  "properties": {
    "addr:full":"5465 New Forsyth Rd Macon GA 31210",
    "addr:housenumber":"5465",
    "addr:postcode":"31210",
    "addr:street":"New Forsyth Rd",
    "iso:country":"US",
    "sg:address":"5465 New Forsyth Rd",
    "sg:city":"Macon",
    "sg:classifiers":[
        {
            "category":"Building & Trades",
            "subcategory":"Construction",
            "type":"Services"
        }
    ],
    "sg:phone":"+1 478 471 7871",
    "sg:postcode":"31210",
    "sg:province":"GA",
    "sg:tags":[
        "general",
        "contractor"
    ],
    "wof:name":"Windham & Windham Inc",
    "wof:placetype":"venue"
},
  "geometry": {"coordinates":[-83.72730300000001,32.936115],"type":"Point"}
}