{
  "type": "Feature",
  "properties": {
    "addr:full":"4400 May Apple Dr Alpharetta GA 30005",
    "addr:housenumber":"4400",
    "addr:postcode":"30005",
    "addr:street":"May Apple Dr",
    "iso:country":"US",
    "sg:address":"4400 May Apple Dr",
    "sg:city":"Alpharetta",
    "sg:classifiers":[
        {
            "category":"Professional",
            "subcategory":"Management & Consulting",
            "type":"Services"
        }
    ],
    "sg:phone":"+1 770 619 9395",
    "sg:postcode":"30005",
    "sg:province":"GA",
    "wof:name":"Accenture Inc",
    "wof:placetype":"venue"
},
  "geometry": {"coordinates":[-84.233243,34.066834],"type":"Point"}
}