{
  "type": "Feature",
  "properties": {
    "iso:country":"US",
    "sg:address":"5 Chelmsford Ln",
    "sg:city":"Savannah",
    "sg:classifiers":[
        {
            "category":"Professional",
            "subcategory":"Business Services",
            "type":"Services"
        }
    ],
    "sg:phone":"+1 912 598 9007",
    "sg:postcode":"31411",
    "sg:province":"GA",
    "wof:name":"Ips",
    "wof:placetype":"venue"
},
  "geometry": {"coordinates":[-81.062642,31.932568],"type":"Point"}
}