{
  "type": "Feature",
  "properties": {
    "iso:country":"US",
    "sg:address":"2790 Riverside Dr",
    "sg:city":"Macon",
    "sg:classifiers":[
        {
            "category":"Personal",
            "type":"Services"
        }
    ],
    "sg:phone":"+1 478 741 0001",
    "sg:postcode":"31204",
    "sg:province":"GA",
    "wof:name":"Tokyo Health Spa",
    "wof:placetype":"venue"
},
  "geometry": {"coordinates":[-83.666551,32.87784],"type":"Point"}
}