{
  "type": "Feature",
  "properties": {
    "addr:full":"1030 Tripple Hill Dr Macon GA 31206",
    "addr:housenumber":"1030",
    "addr:postcode":"31206",
    "addr:street":"Tripple Hill Dr",
    "iso:country":"US",
    "sg:address":"1030 Tripple Hill Dr",
    "sg:city":"Macon",
    "sg:classifiers":[
        {
            "category":"Real Estate",
            "subcategory":"Real Estate Agent",
            "type":"Services"
        }
    ],
    "sg:phone":"+1 478 785 9102",
    "sg:postcode":"31206",
    "sg:province":"GA",
    "wof:name":"Haynes & Thomas Properties",
    "wof:placetype":"venue"
},
  "geometry": {"coordinates":[-83.655968,32.793034],"type":"Point"}
}