{
  "type": "Feature",
  "properties": {
    "addr:full":"46 Singleton Rd Temple GA 30179",
    "addr:housenumber":"46",
    "addr:postcode":"30179",
    "addr:street":"Singleton Rd",
    "iso:country":"US",
    "sg:address":"46 Singleton Rd",
    "sg:city":"Temple",
    "sg:classifiers":[
        {
            "category":"Professional",
            "type":"Services"
        }
    ],
    "sg:phone":"+1 770 562 0230",
    "sg:postcode":"30179",
    "sg:province":"GA",
    "sg:tags":[
        "establishment"
    ],
    "wof:name":"Fishermark",
    "wof:placetype":"venue"
},
  "geometry": {"coordinates":[-85.037908,33.818442],"type":"Point"}
}