{
  "type": "Feature",
  "properties": {
    "addr:full":"5833 Hillside Dr SW Doraville GA 30340",
    "addr:housenumber":"5833",
    "addr:postcode":"30340",
    "addr:street":"Hillside Dr Sw",
    "iso:country":"US",
    "sg:address":"5833 Hillside Dr SW",
    "sg:city":"Doraville",
    "sg:classifiers":[
        {
            "category":"Building & Trades",
            "subcategory":"Construction",
            "type":"Services"
        }
    ],
    "sg:phone":"+1 404 609 9444",
    "sg:postcode":"30340",
    "sg:province":"GA",
    "sg:tags":[
        "roofing",
        "contractor"
    ],
    "wof:name":"Peachtree Roofing & Repairs",
    "wof:placetype":"venue"
},
  "geometry": {"coordinates":[-84.233513,33.922187],"type":"Point"}
}