{
  "type": "Feature",
  "properties": {
    "addr:full":"230 N Macon St Jesup GA 31545",
    "addr:housenumber":"230",
    "addr:postcode":"31545",
    "addr:street":"N Macon St",
    "iso:country":"US",
    "sg:address":"230 N Macon St",
    "sg:city":"Jesup",
    "sg:classifiers":[
        {
            "category":"Wholesale",
            "subcategory":"Machinery & Supplies",
            "type":"Manufacturing & Wholesale Goods"
        },
        {
            "category":"Retail",
            "subcategory":"Laundry & Dry Cleaning",
            "type":"Services"
        }
    ],
    "sg:phone":"+1 912 427 4274",
    "sg:postcode":"31545",
    "sg:province":"GA",
    "sg:tags":[
        "washing",
        "power",
        "mach"
    ],
    "wof:name":"Ms Pat's Laundromat",
    "wof:placetype":"venue"
},
  "geometry": {"coordinates":[-81.88318200000001,31.60702],"type":"Point"}
}