{
  "type": "Feature",
  "properties": {
    "addr:full":"4113 Austell Powder Springs Rd Powder Springs GA 30127",
    "addr:housenumber":"4113",
    "addr:postcode":"30127",
    "addr:street":"Austell Powder Springs Rd",
    "iso:country":"US",
    "sg:address":"4113 Austell Powder Springs Rd",
    "sg:city":"Powder Springs",
    "sg:classifiers":[
        {
            "category":"Wholesale",
            "subcategory":"Auto Parts",
            "type":"Manufacturing & Wholesale Goods"
        }
    ],
    "sg:phone":"+1 770 943 9889",
    "sg:postcode":"30127",
    "sg:province":"GA",
    "sg:tags":[
        "automobile",
        "rebuilt",
        "used"
    ],
    "wof:name":"American Auto Salvage",
    "wof:placetype":"venue"
},
  "geometry": {"coordinates":[-84.66944599999999,33.854091],"type":"Point"}
}