{
  "type": "Feature",
  "properties": {
    "addr:full":"902 N Glenwood Ave Dalton GA 30721",
    "addr:housenumber":"902",
    "addr:postcode":"30721",
    "addr:street":"N Glenwood Ave",
    "iso:country":"US",
    "sg:address":"902 N Glenwood Ave",
    "sg:city":"Dalton",
    "sg:classifiers":[
        {
            "category":"Shopping",
            "subcategory":"Used Merchandise",
            "type":"Retail Goods"
        }
    ],
    "sg:phone":"+1 706 226 4165",
    "sg:postcode":"30721",
    "sg:province":"GA",
    "wof:name":"King & Sons Pawnbrokers",
    "wof:placetype":"venue"
},
  "geometry": {"coordinates":[-84.962811,34.78603],"type":"Point"}
}