{
  "type": "Feature",
  "properties": {
    "iso:country":"US",
    "sg:address":"1219 Williams St NW",
    "sg:city":"Atlanta",
    "sg:classifiers":[
        {
            "category":"Manufacturing",
            "subcategory":"Food",
            "type":"Manufacturing & Wholesale Goods"
        }
    ],
    "sg:phone":"+1 404 892 4436",
    "sg:postcode":"30309",
    "sg:province":"GA",
    "sg:tags":[
        "malt",
        "beverage",
        "mfg"
    ],
    "wof:name":"Atlanta Brewing Company",
    "wof:placetype":"venue"
},
  "geometry": {"coordinates":[-84.390501,33.788654],"type":"Point"}
}