{
  "type": "Feature",
  "properties": {
    "iso:country":"US",
    "sg:address":"519 Forest Pkwy",
    "sg:city":"Forest Park",
    "sg:classifiers":[
        {
            "category":"Building & Trades",
            "subcategory":"Pest Control",
            "type":"Services"
        }
    ],
    "sg:phone":"+1 404 524 7368",
    "sg:postcode":"30297",
    "sg:province":"GA",
    "wof:name":"Mosquito Clarke",
    "wof:placetype":"venue"
},
  "geometry": {"coordinates":[-84.373299,33.6213],"type":"Point"}
}