{
  "type": "Feature",
  "properties": {
    "addr:full":"1459 Experiment St Griffin GA 30223",
    "addr:housenumber":"1459",
    "addr:postcode":"30223",
    "addr:street":"Experiment St",
    "iso:country":"US",
    "sg:address":"1459 Experiment St",
    "sg:city":"Griffin",
    "sg:classifiers":[
        {
            "category":"Taxi",
            "type":"Transportation"
        }
    ],
    "sg:phone":"+1 770 412 8511",
    "sg:postcode":"30223",
    "sg:province":"GA",
    "sg:tags":[
        "taxicab"
    ],
    "wof:name":"Freemans Taxi Svc",
    "wof:placetype":"venue"
},
  "geometry": {"coordinates":[-84.285005,33.270089],"type":"Point"}
}