{
  "type": "Feature",
  "properties": {
    "iso:country":"US",
    "sg:address":"3274 Turtle Lake Club Dr",
    "sg:city":"Marietta",
    "sg:classifiers":[
        {
            "category":"Professional",
            "type":"Services"
        }
    ],
    "sg:phone":"+1 770 850 8219",
    "sg:postcode":"30067",
    "sg:province":"GA",
    "wof:name":"Evelyn Sacks Communicatio",
    "wof:placetype":"venue"
},
  "geometry": {"coordinates":[-84.454683,33.942242],"type":"Point"}
}