{
  "type": "Feature",
  "properties": {
    "addr:full":"6662 Buford Hwy NE Atlanta GA 30340",
    "addr:housenumber":"6662",
    "addr:postcode":"30340",
    "addr:street":"Buford Hwy Ne",
    "iso:country":"US",
    "sg:address":"6662 Buford Hwy NE",
    "sg:city":"Atlanta",
    "sg:classifiers":[
        {
            "category":"Autos & Motor Vehicles",
            "subcategory":"Auto Supplies",
            "type":"Retail Goods"
        },
        {
            "category":"Retail",
            "subcategory":"Auto Repair",
            "type":"Services"
        }
    ],
    "sg:phone":"+1 770 368 8976",
    "sg:postcode":"30340",
    "sg:province":"GA",
    "sg:tags":[
        "tire"
    ],
    "wof:name":"Tire Omni",
    "wof:placetype":"venue"
},
  "geometry": {"coordinates":[-84.241294,33.927827],"type":"Point"}
}