{
  "type": "Feature",
  "properties": {
    "addr:full":"2030 W Broad Ave Albany GA 31707",
    "addr:housenumber":"2030",
    "addr:postcode":"31707",
    "addr:street":"W Broad Ave",
    "iso:country":"US",
    "sg:address":"2030 W Broad Ave",
    "sg:city":"Albany",
    "sg:classifiers":[
        {
            "category":"Real Estate",
            "subcategory":"Real Estate Operator",
            "type":"Services"
        }
    ],
    "sg:phone":"+1 229 434 9765",
    "sg:postcode":"31707",
    "sg:province":"GA",
    "sg:tags":[
        "apartment"
    ],
    "wof:name":"Windsor Apartments",
    "wof:placetype":"venue"
},
  "geometry": {"coordinates":[-84.200706,31.5791],"type":"Point"}
}