{
  "type": "Feature",
  "properties": {
    "addr:full":"1 7th St Augusta GA 30901",
    "addr:housenumber":"1",
    "addr:postcode":"30901",
    "addr:street":"7Th St",
    "iso:country":"US",
    "sg:address":"1 7th St",
    "sg:city":"Augusta",
    "sg:classifiers":[
        {
            "category":"Museum",
            "type":"Entertainment"
        }
    ],
    "sg:phone":"+1 706 821 0600",
    "sg:postcode":"30901",
    "sg:province":"GA",
    "sg:tags":[
        "gallery"
    ],
    "wof:name":"Fort Discovery",
    "wof:placetype":"venue"
},
  "geometry": {"coordinates":[-81.96265699999999,33.475888],"type":"Point"}
}