{
  "type": "Feature",
  "properties": {
    "iso:country":"US",
    "sg:address":"3072 Duren St",
    "sg:city":"Meigs",
    "sg:classifiers":[
        {
            "category":"Building & Trades",
            "subcategory":"Construction",
            "type":"Services"
        }
    ],
    "sg:phone":"+1 229 683 3211",
    "sg:postcode":"31765",
    "sg:province":"GA",
    "sg:tags":[
        "concrete",
        "contractor"
    ],
    "wof:name":"Conney Backhoe Svc",
    "wof:placetype":"venue"
},
  "geometry": {"coordinates":[-84.093317,31.068056],"type":"Point"}
}