{
  "type": "Feature",
  "properties": {
    "iso:country":"US",
    "sg:address":"2180 Pleasant Hill Rd Ste A5-152",
    "sg:city":"Duluth",
    "sg:classifiers":[
        {
            "category":"Taxi",
            "type":"Transportation"
        }
    ],
    "sg:phone":"+1 770 623 0504",
    "sg:postcode":"30096",
    "sg:province":"GA",
    "wof:name":"Duluth Coach & Taxi Systems",
    "wof:placetype":"venue"
},
  "geometry": {"coordinates":[-84.134823,33.959306],"type":"Point"}
}