{
  "type": "Feature",
  "properties": {
    "iso:country":"US",
    "sg:address":"301 N Peterson Ave",
    "sg:city":"Douglas",
    "sg:classifiers":[
        {
            "category":"Real Estate",
            "subcategory":"Surveying",
            "type":"Services"
        }
    ],
    "sg:phone":"+1 912 384 1144",
    "sg:postcode":"31533",
    "sg:province":"GA",
    "sg:tags":[
        "surveyor"
    ],
    "wof:name":"Southern Surveying Associates",
    "wof:placetype":"venue"
},
  "geometry": {"coordinates":[-82.850385,31.510551],"type":"Point"}
}