{
  "type": "Feature",
  "properties": {
    "iso:country":"US",
    "sg:address":"118 Dewey St",
    "sg:city":"Warner Robins",
    "sg:classifiers":[
        {
            "category":"Farming",
            "subcategory":"Farm",
            "type":"Manufacturing & Wholesale Goods"
        }
    ],
    "sg:phone":"+1 478 922 3489",
    "sg:postcode":"31093",
    "sg:province":"GA",
    "sg:tags":[
        "crop",
        "general"
    ],
    "wof:name":"Jones Malon",
    "wof:placetype":"venue"
},
  "geometry": {"coordinates":[-83.62386600000001,32.627534],"type":"Point"}
}