{
  "type": "Feature",
  "properties": {
    "addr:full":"1234 Noland Dr Columbus GA 31907",
    "addr:housenumber":"1234",
    "addr:postcode":"31907",
    "addr:street":"Noland Dr",
    "iso:country":"US",
    "sg:address":"1234 Noland Dr",
    "sg:city":"Columbus",
    "sg:classifiers":[
        {
            "category":"Building & Trades",
            "subcategory":"Construction",
            "type":"Services"
        }
    ],
    "sg:phone":"+1 706 568 4095",
    "sg:postcode":"31907",
    "sg:province":"GA",
    "sg:tags":[
        "striping"
    ],
    "wof:name":"Smith Painting Contractor Inc",
    "wof:placetype":"venue"
},
  "geometry": {"coordinates":[-84.92386500000001,32.472277],"type":"Point"}
}