{
  "type": "Feature",
  "properties": {
    "addr:full":"547 Ponce De Leon Ave NE Atlanta GA 30308",
    "addr:housenumber":"547",
    "addr:postcode":"30308",
    "addr:street":"Ponce De Leon Ave Ne",
    "iso:country":"US",
    "sg:address":"547 Ponce De Leon Ave NE",
    "sg:city":"Atlanta",
    "sg:classifiers":[
        {
            "category":"Health Services",
            "subcategory":"Doctor",
            "type":"Services"
        }
    ],
    "sg:phone":"+1 404 685 3113",
    "sg:postcode":"30308",
    "sg:province":"GA",
    "sg:tags":[
        "psychiatrist"
    ],
    "wof:name":"Prudent Michael MD Dr",
    "wof:placetype":"venue"
},
  "geometry": {"coordinates":[-84.36889600000001,33.773701],"type":"Point"}
}