{
  "type": "Feature",
  "properties": {
    "iso:country":"US",
    "sg:address":"2184 Henderson Mill Rd NE",
    "sg:city":"Atlanta",
    "sg:classifiers":[
        {
            "category":"Health Services",
            "subcategory":"Optometrist",
            "type":"Services"
        },
        {
            "category":"Shopping",
            "subcategory":"Optical Goods",
            "type":"Retail Goods"
        }
    ],
    "sg:phone":"+1 770 938 2923",
    "sg:postcode":"30345",
    "sg:province":"GA",
    "sg:tags":[
        "lens",
        "contact"
    ],
    "sg:website":"http://www.northlakeeyecare.com",
    "wof:name":"Eye First Vision Center",
    "wof:placetype":"venue"
},
  "geometry": {"coordinates":[-84.25569900000001,33.847801],"type":"Point"}
}