{
  "type": "Feature",
  "properties": {
    "addr:full":"110 W Jackson St Dublin GA 31021",
    "addr:housenumber":"110",
    "addr:postcode":"31021",
    "addr:street":"W Jackson St",
    "iso:country":"US",
    "sg:address":"110 W Jackson St",
    "sg:city":"Dublin",
    "sg:classifiers":[
        {
            "category":"Food & Beverages",
            "subcategory":"Groceries & Convenience Stores",
            "type":"Retail Goods"
        }
    ],
    "sg:phone":"+1 478 272 3881",
    "sg:postcode":"31021",
    "sg:province":"GA",
    "sg:tags":[
        "eating"
    ],
    "wof:name":"Peppercorn Company",
    "wof:placetype":"venue"
},
  "geometry": {"coordinates":[-82.904623,32.539829],"type":"Point"}
}