{
  "type": "Feature",
  "properties": {
    "addr:full":"2738 N Decatur Rd Decatur GA 30033",
    "addr:housenumber":"2738",
    "addr:postcode":"30033",
    "addr:street":"N Decatur Rd",
    "iso:country":"US",
    "sg:address":"2738 N Decatur Rd",
    "sg:city":"Decatur",
    "sg:classifiers":[
        {
            "category":"Health Services",
            "subcategory":"Hospital",
            "type":"Services"
        },
        {
            "category":"Health Services",
            "subcategory":"Nursing And Care Facility",
            "type":"Services"
        },
        {
            "category":"Community Center",
            "type":"Public Place"
        },
        {
            "category":"Health Services",
            "subcategory":"Clinic",
            "type":"Services"
        }
    ],
    "sg:phone":"+1 800 746 7287",
    "sg:postcode":"30033",
    "sg:province":"GA",
    "sg:tags":[
        "urgent",
        "medical",
        "nurse"
    ],
    "sg:website":"http://www.minuteclinic.com",
    "wof:name":"MinuteClinic",
    "wof:placetype":"venue"
},
  "geometry": {"coordinates":[-84.281254,33.792626],"type":"Point"}
}