{
  "type": "Feature",
  "properties": {
    "addr:full":"10305 Medlock Bridge Rd Duluth GA 30097",
    "addr:housenumber":"10305",
    "addr:postcode":"30097",
    "addr:street":"Medlock Bridge Rd",
    "iso:country":"US",
    "sg:address":"10305 Medlock Bridge Rd",
    "sg:city":"Duluth",
    "sg:classifiers":[
        {
            "category":"Bars & Pubs",
            "type":"Food & Drink"
        }
    ],
    "sg:menulink":"http://www.allmenus.com/ga/roswell-alpharetta/244531-harp-irish-pub/menu/",
    "sg:phone":"+1 770 495 9484",
    "sg:postcode":"30097",
    "sg:province":"GA",
    "sg:tags":[
        "irish"
    ],
    "wof:name":"Harp Irish Pub",
    "wof:placetype":"venue"
},
  "geometry": {"coordinates":[-84.18518400000001,34.032214],"type":"Point"}
}