{
  "type": "Feature",
  "properties": {
    "iso:country":"US",
    "sg:address":"355 S Wall St",
    "sg:city":"Calhoun",
    "sg:classifiers":[
        {
            "category":"Building & Trades",
            "subcategory":"Equipment Rental",
            "type":"Services"
        }
    ],
    "sg:phone":"+1 706 625 1560",
    "sg:postcode":"30701",
    "sg:province":"GA",
    "sg:tags":[
        "television",
        "own",
        "household",
        "appliance",
        "to",
        "electrical",
        "rent"
    ],
    "wof:name":"Century Rentals & Sales",
    "wof:placetype":"venue"
},
  "geometry": {"coordinates":[-84.951877,34.496721],"type":"Point"}
}