{
  "type": "Feature",
  "properties": {
    "addr:full":"1207 S Harris St Sandersville GA 31082",
    "addr:housenumber":"1207",
    "addr:postcode":"31082",
    "addr:street":"S Harris St",
    "iso:country":"US",
    "sg:address":"1207 S Harris St",
    "sg:city":"Sandersville",
    "sg:classifiers":[
        {
            "category":"Autos & Motor Vehicles",
            "subcategory":"Automobile Sales",
            "type":"Retail Goods"
        }
    ],
    "sg:phone":"+1 478 552 8200",
    "sg:postcode":"31082",
    "sg:province":"GA",
    "sg:tags":[
        "car",
        "dealer"
    ],
    "sg:website":"www.childrefordmercury.com",
    "wof:name":"Childre Ford-Mercury Inc",
    "wof:placetype":"venue"
},
  "geometry": {"coordinates":[-82.809011,32.957323],"type":"Point"}
}