{
  "type": "Feature",
  "properties": {
    "addr:full":"13015 Abercorn St Exn Savannah GA 31419",
    "addr:housenumber":"13015",
    "addr:postcode":"31419",
    "addr:street":"Abercorn St Exn",
    "iso:country":"US",
    "sg:address":"13015 Abercorn St Exn",
    "sg:city":"Savannah",
    "sg:classifiers":[
        {
            "category":"Shopping",
            "subcategory":"Shoes",
            "type":"Retail Goods"
        }
    ],
    "sg:phone":"+1 912 920 0065",
    "sg:postcode":"31419",
    "sg:province":"GA",
    "wof:name":"Good Feet 176",
    "wof:placetype":"venue"
},
  "geometry": {"coordinates":[-81.16562,31.981429],"type":"Point"}
}