{
  "type": "Feature",
  "properties": {
    "addr:full":"690 N Varnell Rd Tunnel Hill GA 30755",
    "addr:housenumber":"690",
    "addr:postcode":"30755",
    "addr:street":"N Varnell Rd",
    "iso:country":"US",
    "sg:address":"690 N Varnell Rd",
    "sg:city":"Tunnel Hill",
    "sg:classifiers":[
        {
            "category":"Home & Garden",
            "subcategory":"Carpets & Floor Coverings",
            "type":"Retail Goods"
        }
    ],
    "sg:phone":"+1 706 673 2334",
    "sg:postcode":"30755",
    "sg:province":"GA",
    "wof:name":"Carpet Wholesale Outlet",
    "wof:placetype":"venue"
},
  "geometry": {"coordinates":[-85.041731,34.859488],"type":"Point"}
}