{
  "type": "Feature",
  "properties": {
    "iso:country":"US",
    "sg:address":"790 Monticello Ln",
    "sg:city":"Mc Donough",
    "sg:classifiers":[
        {
            "category":"Professional",
            "subcategory":"Engineering",
            "type":"Services"
        }
    ],
    "sg:phone":"+1 770 898 4861",
    "sg:postcode":"30253",
    "sg:province":"GA",
    "sg:tags":[
        "consulting"
    ],
    "wof:name":"Ancher Enterprises",
    "wof:placetype":"venue"
},
  "geometry": {"coordinates":[-84.17905399999999,33.467765],"type":"Point"}
}