{
  "type": "Feature",
  "properties": {
    "addr:full":"2229 Harrison Rd NE Thomson GA 30824",
    "addr:housenumber":"2229",
    "addr:postcode":"30824",
    "addr:street":"Harrison Rd Ne",
    "iso:country":"US",
    "sg:address":"2229 Harrison Rd NE",
    "sg:city":"Thomson",
    "sg:classifiers":[
        {
            "category":"Shopping",
            "subcategory":"Shoes",
            "type":"Retail Goods"
        }
    ],
    "sg:phone":"+1 706 595 5881",
    "sg:postcode":"30824",
    "sg:province":"GA",
    "wof:name":"Shoe Show 728",
    "wof:placetype":"venue"
},
  "geometry": {"coordinates":[-82.50100399999999,33.482659],"type":"Point"}
}