{
  "type": "Feature",
  "properties": {
    "iso:country":"US",
    "sg:address":"587 Dickens Rd NW",
    "sg:city":"Lilburn",
    "sg:classifiers":[
        {
            "category":"Building & Trades",
            "subcategory":"Construction",
            "type":"Services"
        }
    ],
    "sg:phone":"+1 404 314 2638",
    "sg:postcode":"30047",
    "sg:province":"GA",
    "sg:tags":[
        "contractor"
    ],
    "wof:name":"Carrillo Roofing",
    "wof:placetype":"venue"
},
  "geometry": {"coordinates":[-84.165571,33.886552],"type":"Point"}
}