{
  "type": "Feature",
  "properties": {
    "addr:full":"111 Tibet Ave Savannah GA 31406",
    "addr:housenumber":"111",
    "addr:postcode":"31406",
    "addr:street":"Tibet Ave",
    "iso:country":"US",
    "sg:address":"111 Tibet Ave",
    "sg:city":"Savannah",
    "sg:classifiers":[
        {
            "category":"Freight",
            "type":"Transportation"
        }
    ],
    "sg:phone":"+1 912 927 1648",
    "sg:postcode":"31406",
    "sg:province":"GA",
    "sg:tags":[
        "general"
    ],
    "wof:name":"Storage Systems",
    "wof:placetype":"venue"
},
  "geometry": {"coordinates":[-81.132795,31.989572],"type":"Point"}
}