{
  "type": "Feature",
  "properties": {
    "addr:full":"430 Gilley Rd Sycamore GA 31790",
    "addr:housenumber":"430",
    "addr:postcode":"31790",
    "addr:street":"Gilley Rd",
    "iso:country":"US",
    "sg:address":"430 Gilley Rd",
    "sg:city":"Sycamore",
    "sg:classifiers":[
        {
            "category":"Manufacturing",
            "subcategory":"Textiles",
            "type":"Manufacturing & Wholesale Goods"
        }
    ],
    "sg:phone":"+1 229 567 2669",
    "sg:postcode":"31790",
    "sg:province":"GA",
    "sg:tags":[
        "broker",
        "cotton"
    ],
    "wof:name":"Phil Gilley",
    "wof:placetype":"venue"
},
  "geometry": {"coordinates":[-83.589044,31.656875],"type":"Point"}
}