{
  "type": "Feature",
  "properties": {
    "addr:full":"5190 Ridge Tarn Acworth GA 30102",
    "addr:housenumber":"5190",
    "addr:postcode":"30102",
    "addr:street":"Ridge Tarn",
    "iso:country":"US",
    "sg:address":"5190 Ridge Tarn",
    "sg:city":"Acworth",
    "sg:classifiers":[
        {
            "category":"Professional",
            "type":"Services"
        }
    ],
    "sg:phone":"+1 770 789 4365",
    "sg:postcode":"30102",
    "sg:province":"GA",
    "wof:name":"Aum International",
    "wof:placetype":"venue"
},
  "geometry": {"coordinates":[-84.564708,34.078923],"type":"Point"}
}