{
  "type": "Feature",
  "properties": {
    "addr:full":"243 E Midland Ave Winder GA 30680",
    "addr:housenumber":"243",
    "addr:postcode":"30680",
    "addr:street":"E Midland Ave",
    "iso:country":"US",
    "sg:address":"243 E Midland Ave",
    "sg:city":"Winder",
    "sg:classifiers":[
        {
            "category":"Manufacturing",
            "subcategory":"Pet Food",
            "type":"Manufacturing & Wholesale Goods"
        }
    ],
    "sg:phone":"+1 770 867 7568",
    "sg:postcode":"30680",
    "sg:province":"GA",
    "sg:tags":[
        "feed"
    ],
    "wof:name":"Harrison Milling",
    "wof:placetype":"venue"
},
  "geometry": {"coordinates":[-83.715316,33.988028],"type":"Point"}
}