{
  "type": "Feature",
  "properties": {
    "iso:country":"US",
    "sg:address":"4453 Pineridge Cir",
    "sg:city":"Atlanta",
    "sg:classifiers":[
        {
            "category":"Professional",
            "type":"Services"
        }
    ],
    "sg:phone":"+1 770 986 9135",
    "sg:postcode":"30338",
    "sg:province":"GA",
    "wof:name":"Sun Life International Inc",
    "wof:placetype":"venue"
},
  "geometry": {"coordinates":[-84.29900000000001,33.924852],"type":"Point"}
}