{
  "type": "Feature",
  "properties": {
    "iso:country":"US",
    "sg:address":"508 Industrial Park Dr",
    "sg:city":"Evans",
    "sg:classifiers":[
        {
            "category":"Restaurant",
            "type":"Food & Drink"
        }
    ],
    "sg:phone":"+1 706 860 6990",
    "sg:postcode":"30809",
    "sg:province":"GA",
    "sg:tags":[
        "eating"
    ],
    "wof:name":"Huddle House",
    "wof:placetype":"venue"
},
  "geometry": {"coordinates":[-82.127684,33.537676],"type":"Point"}
}