{
  "type": "Feature",
  "properties": {
    "addr:full":"1196 Ernest W Barrett Pkwy NW Kennesaw GA 30144",
    "addr:housenumber":"1196",
    "addr:postcode":"30144",
    "addr:street":"Ernest W Barrett Pkwy Nw",
    "iso:country":"US",
    "sg:address":"1196 Ernest W Barrett Pkwy NW",
    "sg:city":"Kennesaw",
    "sg:classifiers":[
        {
            "category":"Autos & Motor Vehicles",
            "subcategory":"Auto Supplies",
            "type":"Retail Goods"
        },
        {
            "category":"Retail",
            "subcategory":"Auto Repair",
            "type":"Services"
        }
    ],
    "sg:phone":"+1 770 421 8811",
    "sg:postcode":"30144",
    "sg:province":"GA",
    "sg:tags":[
        "brake",
        "tire"
    ],
    "sg:website":"www.goodyear.com",
    "wof:name":"Goodyear Tire Center",
    "wof:placetype":"venue"
},
  "geometry": {"coordinates":[-84.58532200000001,33.999828],"type":"Point"}
}