{
  "type": "Feature",
  "properties": {
    "iso:country":"US",
    "sg:address":"1204 Williams St",
    "sg:city":"Valdosta",
    "sg:classifiers":[
        {
            "category":"Education",
            "subcategory":"School",
            "type":"Public Place"
        }
    ],
    "sg:phone":"+1 229 333 8580",
    "sg:postcode":"31601",
    "sg:province":"GA",
    "wof:name":"Title I/Esol",
    "wof:placetype":"venue"
},
  "geometry": {"coordinates":[-83.282625,30.845517],"type":"Point"}
}