{
  "type": "Feature",
  "properties": {
    "iso:country":"US",
    "sg:address":"155 Gilbert Rd",
    "sg:city":"Fayetteville",
    "sg:classifiers":[
        {
            "category":"Communications",
            "type":"Services"
        }
    ],
    "sg:phone":"+1 770 946 8374",
    "sg:postcode":"30214",
    "sg:province":"GA",
    "wof:name":"Imagesmith Communications",
    "wof:placetype":"venue"
},
  "geometry": {"coordinates":[-84.44307499999999,33.46284],"type":"Point"}
}