{
  "type": "Feature",
  "properties": {
    "addr:full":"116 Mill Creek Ct Woodstock GA 30188",
    "addr:housenumber":"116",
    "addr:postcode":"30188",
    "addr:street":"Mill Creek Ct",
    "iso:country":"US",
    "sg:address":"116 Mill Creek Ct",
    "sg:city":"Woodstock",
    "sg:classifiers":[
        {
            "category":"Social Services",
            "subcategory":"Adult Care",
            "type":"Services"
        }
    ],
    "sg:phone":"+1 770 924 9620",
    "sg:postcode":"30188",
    "sg:province":"GA",
    "sg:tags":[
        "home",
        "residential"
    ],
    "wof:name":"Langston's Personal Care Home",
    "wof:placetype":"venue"
},
  "geometry": {"coordinates":[-84.494614,34.128204],"type":"Point"}
}