{
  "type": "Feature",
  "properties": {
    "iso:country":"US",
    "sg:address":"3365 W Hospital Ave",
    "sg:city":"Atlanta",
    "sg:classifiers":[
        {
            "category":"Building & Trades",
            "subcategory":"Construction",
            "type":"Services"
        }
    ],
    "sg:phone":"+1 770 216 9733",
    "sg:postcode":"30341",
    "sg:province":"GA",
    "sg:tags":[
        "plastering",
        "business",
        "coping",
        "contractor",
        "concrete",
        "tiling",
        "pool",
        "swimming"
    ],
    "wof:name":"Envirodek Concrete Resurfacing",
    "wof:placetype":"venue"
},
  "geometry": {"coordinates":[-84.294572,33.889689],"type":"Point"}
}