{
  "type": "Feature",
  "properties": {
    "iso:country":"US",
    "sg:address":"1308 Hogansville Rd",
    "sg:city":"Lagrange",
    "sg:classifiers":[
        {
            "category":"Personal",
            "type":"Services"
        }
    ],
    "sg:phone":"+1 706 812 8103",
    "sg:postcode":"30241",
    "sg:province":"GA",
    "sg:tags":[
        "therapist",
        "massage"
    ],
    "wof:name":"A Balanced Body",
    "wof:placetype":"venue"
},
  "geometry": {"coordinates":[-84.99881000000001,33.05475],"type":"Point"}
}