{
  "type": "Feature",
  "properties": {
    "iso:country":"US",
    "sg:address":"6342 Grand Hickory Dr",
    "sg:city":"Braselton",
    "sg:classifiers":[
        {
            "category":"Insurance",
            "subcategory":"Hazard Insurance",
            "type":"Services"
        },
        {
            "category":"Insurance",
            "subcategory":"Insurance Agent",
            "type":"Services"
        },
        {
            "category":"Insurance",
            "subcategory":"Life Insurance",
            "type":"Services"
        },
        {
            "category":"Insurance",
            "subcategory":"Title Insurance",
            "type":"Services"
        }
    ],
    "sg:phone":"+1 256 891 0379",
    "sg:postcode":"30517",
    "sg:province":"GA",
    "sg:tags":[
        "property",
        "casualty",
        "homeowner"
    ],
    "sg:website":"http://atlanta.citysearch.com/profile/external/43838828/braselton_ga/cotton_states_joe_campbell.html?publisher=yellowpages&reference_id=1&placement=ypwebsitemip",
    "wof:name":"Cotton States - Joe Campbell",
    "wof:placetype":"venue"
},
  "geometry": {"coordinates":[-83.82396799999999,34.119892],"type":"Point"}
}