{
  "type": "Feature",
  "properties": {
    "iso:country":"US",
    "sg:address":"12290 Augusta Rd",
    "sg:city":"Lavonia",
    "sg:classifiers":[
        {
            "category":"Real Estate",
            "subcategory":"Real Estate Agent",
            "type":"Services"
        }
    ],
    "sg:phone":"+1 706 356 2068",
    "sg:postcode":"30553",
    "sg:province":"GA",
    "wof:name":"Ronnie Singleton Realty",
    "wof:placetype":"venue"
},
  "geometry": {"coordinates":[-83.107197,34.430213],"type":"Point"}
}