{
  "type": "Feature",
  "properties": {
    "iso:country":"US",
    "sg:address":"750 Ponce de Leon Pl Ste 1",
    "sg:city":"Atlanta",
    "sg:classifiers":[
        {
            "category":"Animal Shelter",
            "type":"Public Place"
        },
        {
            "category":"Shopping",
            "subcategory":"Pets & Pet Supplies",
            "type":"Retail Goods"
        },
        {
            "category":"Retail",
            "subcategory":"Pet Boarding",
            "type":"Services"
        },
        {
            "category":"Retail",
            "subcategory":"Animal Services",
            "type":"Services"
        }
    ],
    "sg:phone":"+1 404 745 4243",
    "sg:postcode":"30306",
    "sg:province":"GA",
    "sg:tags":[
        "sitting",
        "exercising",
        "dog",
        "boarding/pet",
        "walker",
        "grooming",
        "cat",
        "kennel"
    ],
    "sg:website":"www.spotfordogs.com",
    "wof:name":"SPOT For Dogs",
    "wof:placetype":"venue"
},
  "geometry": {"coordinates":[-84.363721,33.774357],"type":"Point"}
}