{
  "type": "Feature",
  "properties": {
    "addr:full":"420 E 6th St Tifton GA 31794",
    "addr:housenumber":"420",
    "addr:postcode":"31794",
    "addr:street":"E 6Th St",
    "iso:country":"US",
    "sg:address":"420 E 6th St",
    "sg:city":"Tifton",
    "sg:classifiers":[
        {
            "category":"Wholesale",
            "subcategory":"Toys & Hobbies",
            "type":"Manufacturing & Wholesale Goods"
        }
    ],
    "sg:phone":"+1 229 382 5600",
    "sg:postcode":"31794",
    "sg:province":"GA",
    "sg:tags":[
        "arts",
        "craft"
    ],
    "wof:name":"Country Praise",
    "wof:placetype":"venue"
},
  "geometry": {"coordinates":[-83.503996,31.4566],"type":"Point"}
}