{
  "type": "Feature",
  "properties": {
    "iso:country":"US",
    "sg:address":"4143 Legion Dr SE",
    "sg:city":"Covington",
    "sg:classifiers":[
        {
            "category":"Wholesale",
            "subcategory":"Machinery & Supplies",
            "type":"Manufacturing & Wholesale Goods"
        }
    ],
    "sg:phone":"+1 770 787 5360",
    "sg:postcode":"30014",
    "sg:province":"GA",
    "sg:tags":[
        "equipment",
        "conveyor",
        "conveying"
    ],
    "wof:name":"Amtec Engineering",
    "wof:placetype":"venue"
},
  "geometry": {"coordinates":[-83.85476199999999,33.588496],"type":"Point"}
}