{
  "type": "Feature",
  "properties": {
    "addr:full":"1444 Ashwoody Ct Atlanta GA 30319",
    "addr:housenumber":"1444",
    "addr:postcode":"30319",
    "addr:street":"Ashwoody Ct",
    "iso:country":"US",
    "sg:address":"1444 Ashwoody Ct",
    "sg:city":"Atlanta",
    "sg:classifiers":[
        {
            "category":"Building & Trades",
            "subcategory":"Landscaping Services",
            "type":"Services"
        }
    ],
    "sg:phone":"+1 770 256 1479",
    "sg:postcode":"30319",
    "sg:province":"GA",
    "wof:name":"Greenblades Turf Care, Inc",
    "wof:placetype":"venue"
},
  "geometry": {"coordinates":[-84.32986699999999,33.917053],"type":"Point"}
}