{
  "type": "Feature",
  "properties": {
    "iso:country":"US",
    "sg:address":"2345 Cheshire Bridge Rd Ste4",
    "sg:city":"Atlanta",
    "sg:classifiers":[
        {
            "category":"Personal",
            "subcategory":"Day Spa",
            "type":"Services"
        }
    ],
    "sg:phone":"+1 404 704 5314",
    "sg:postcode":"30324",
    "sg:province":"GA",
    "sg:website":"http://CarliClinicalSkincare.com",
    "wof:name":"Carli Clinical Skincare",
    "wof:placetype":"venue"
},
  "geometry": {"coordinates":[-84.35145,33.818889],"type":"Point"}
}