{
  "type": "Feature",
  "properties": {
    "addr:full":"402 North Avenue NE Atlanta GA 30308",
    "addr:housenumber":"402",
    "addr:postcode":"30308",
    "addr:street":"North Avenue Ne",
    "iso:country":"US",
    "sg:address":"402 North Avenue NE",
    "sg:city":"Atlanta",
    "sg:classifiers":[
        {
            "category":"Health Services",
            "subcategory":"Doctor",
            "type":"Services"
        }
    ],
    "sg:phone":"+1 404 873 1894",
    "sg:postcode":"30308",
    "sg:province":"GA",
    "wof:name":"Chaudhari Rajani",
    "wof:placetype":"venue"
},
  "geometry": {"coordinates":[-84.37390000000001,33.77108],"type":"Point"}
}