{
  "type": "Feature",
  "properties": {
    "addr:full":"223 W Lamar St Americus GA 31709",
    "addr:housenumber":"223",
    "addr:postcode":"31709",
    "addr:street":"W Lamar St",
    "iso:country":"US",
    "sg:address":"223 W Lamar St",
    "sg:city":"Americus",
    "sg:classifiers":[
        {
            "category":"Shopping",
            "subcategory":"Gifts & Souvenirs",
            "type":"Retail Goods"
        }
    ],
    "sg:phone":"+1 229 924 2605",
    "sg:postcode":"31709",
    "sg:province":"GA",
    "sg:tags":[
        "shop"
    ],
    "wof:name":"Downtown Gifts",
    "wof:placetype":"venue"
},
  "geometry": {"coordinates":[-84.23316800000001,32.072212],"type":"Point"}
}