{
  "type": "Feature",
  "properties": {
    "addr:full":"828 Oak St SW Atlanta GA 30310",
    "addr:housenumber":"828",
    "addr:postcode":"30310",
    "addr:street":"Oak St Sw",
    "iso:country":"US",
    "sg:address":"828 Oak St SW",
    "sg:city":"Atlanta",
    "sg:classifiers":[
        {
            "category":"Shopping",
            "subcategory":"Clothing, Apparel, & Fashions",
            "type":"Retail Goods"
        }
    ],
    "sg:phone":"+1 404 758 8956",
    "sg:postcode":"30310",
    "sg:province":"GA",
    "wof:name":"Happenings",
    "wof:placetype":"venue"
},
  "geometry": {"coordinates":[-84.41585499999999,33.740575],"type":"Point"}
}