{
  "type": "Feature",
  "properties": {
    "iso:country":"US",
    "sg:address":"1159 Greenway Rd",
    "sg:city":"Dawsonville",
    "sg:classifiers":[
        {
            "category":"Manufacturing",
            "subcategory":"Lumber",
            "type":"Manufacturing & Wholesale Goods"
        }
    ],
    "sg:phone":"+1 706 265 3103",
    "sg:postcode":"30534",
    "sg:province":"GA",
    "sg:tags":[
        "tree",
        "logging"
    ],
    "wof:name":"Clonts Logging Inc",
    "wof:placetype":"venue"
},
  "geometry": {"coordinates":[-84.130475,34.489861],"type":"Point"}
}