{
  "type": "Feature",
  "properties": {
    "addr:full":"4690 S Lee St Buford GA 30518",
    "addr:housenumber":"4690",
    "addr:postcode":"30518",
    "addr:street":"S Lee St",
    "iso:country":"US",
    "sg:address":"4690 S Lee St",
    "sg:city":"Buford",
    "sg:classifiers":[
        {
            "category":"Building & Trades",
            "subcategory":"Construction",
            "type":"Services"
        }
    ],
    "sg:phone":"+1 770 945 1665",
    "sg:postcode":"30518",
    "sg:province":"GA",
    "sg:tags":[
        "house"
    ],
    "wof:name":"Kts Renovations",
    "wof:placetype":"venue"
},
  "geometry": {"coordinates":[-83.99876399999999,34.092449],"type":"Point"}
}