{
  "type": "Feature",
  "properties": {
    "iso:country":"US",
    "sg:address":"2483 Lake Harbin Rd",
    "sg:city":"Morrow",
    "sg:classifiers":[
        {
            "category":"Professional",
            "type":"Services"
        }
    ],
    "sg:phone":"+1 770 961 2025",
    "sg:postcode":"30260",
    "sg:province":"GA",
    "wof:name":"Diamond Real Estate",
    "wof:placetype":"venue"
},
  "geometry": {"coordinates":[-84.309443,33.582878],"type":"Point"}
}