{
  "type": "Feature",
  "properties": {
    "addr:full":"4815 Buford Hwy Atlanta GA 30341",
    "addr:housenumber":"4815",
    "addr:postcode":"30341",
    "addr:street":"Buford Hwy",
    "iso:country":"US",
    "sg:address":"4815 Buford Hwy",
    "sg:city":"Atlanta",
    "sg:classifiers":[
        {
            "category":"Travel",
            "subcategory":"Hotels & Motels",
            "type":"Entertainment"
        }
    ],
    "sg:phone":"+1 770 458 8011",
    "sg:postcode":"30341",
    "sg:province":"GA",
    "wof:name":"Lodge On Buford",
    "wof:placetype":"venue"
},
  "geometry": {"coordinates":[-84.288217,33.882538],"type":"Point"}
}