{
  "type": "Feature",
  "properties": {
    "iso:country":"US",
    "sg:address":"1004 Cobb Pkwy",
    "sg:city":"Marietta",
    "sg:classifiers":[
        {
            "category":"Autos & Motor Vehicles",
            "subcategory":"Auto Supplies",
            "type":"Retail Goods"
        }
    ],
    "sg:phone":"+1 770 426 5755",
    "sg:postcode":"30062",
    "sg:province":"GA",
    "sg:tags":[
        "automobile",
        "parts"
    ],
    "wof:name":"Best Japanese Engine",
    "wof:placetype":"venue"
},
  "geometry": {"coordinates":[-84.54732199999999,33.97642],"type":"Point"}
}