{
  "type": "Feature",
  "properties": {
    "addr:full":"3131 Atlanta Hwy Athens GA 30606",
    "addr:housenumber":"3131",
    "addr:postcode":"30606",
    "addr:street":"Atlanta Hwy",
    "iso:country":"US",
    "sg:address":"3131 Atlanta Hwy",
    "sg:city":"Athens",
    "sg:classifiers":[
        {
            "category":"Health Services",
            "subcategory":"Doctor",
            "type":"Services"
        }
    ],
    "sg:phone":"+1 706 354 8383",
    "sg:postcode":"30606",
    "sg:province":"GA",
    "sg:tags":[
        "dentist"
    ],
    "wof:name":"Pickron Orthodontics",
    "wof:placetype":"venue"
},
  "geometry": {"coordinates":[-83.4525,33.939637],"type":"Point"}
}