{
  "type": "Feature",
  "properties": {
    "iso:country":"US",
    "sg:address":"2690 Cumberland Pkwy SE",
    "sg:city":"Atlanta",
    "sg:classifiers":[
        {
            "category":"Wholesale",
            "subcategory":"Computers",
            "type":"Manufacturing & Wholesale Goods"
        },
        {
            "category":"Professional",
            "subcategory":"Computer Services",
            "type":"Services"
        }
    ],
    "sg:phone":"+1 770 874 7802",
    "sg:postcode":"30339",
    "sg:province":"GA",
    "sg:tags":[
        "equipment",
        "cd-rom"
    ],
    "wof:name":"The Syllogist Group",
    "wof:placetype":"venue"
},
  "geometry": {"coordinates":[-84.474177,33.874975],"type":"Point"}
}