{
  "type": "Feature",
  "properties": {
    "iso:country":"US",
    "sg:address":"545 E Monroe Ave",
    "sg:city":"Ashburn",
    "sg:classifiers":[
        {
            "category":"Insurance",
            "subcategory":"Hazard Insurance",
            "type":"Services"
        }
    ],
    "sg:phone":"+1 229 567 3184",
    "sg:postcode":"31714",
    "sg:province":"GA",
    "wof:name":"Lloyd Scott Ewing",
    "wof:placetype":"venue"
},
  "geometry": {"coordinates":[-83.64495700000001,31.707537],"type":"Point"}
}