{
  "type": "Feature",
  "properties": {
    "addr:full":"1553 Virginia Avenue Suite 104 Atlanta GA 30337",
    "addr:housenumber":"1553",
    "addr:postcode":"30337",
    "addr:street":"Virginia Avenue Suite 104",
    "iso:country":"US",
    "sg:address":"1553 Virginia Avenue Suite 104",
    "sg:city":"Atlanta",
    "sg:classifiers":[
        {
            "category":"Professional",
            "subcategory":"Employment Agencies",
            "type":"Services"
        }
    ],
    "sg:phone":"+1 404 684 8867",
    "sg:postcode":"30337",
    "sg:province":"GA",
    "wof:name":"Gdi Staffing Services",
    "wof:placetype":"venue"
},
  "geometry": {"coordinates":[-84.440499,33.659286],"type":"Point"}
}