{
  "type": "Feature",
  "properties": {
    "iso:country":"US",
    "sg:address":"201 W Athens St",
    "sg:city":"Winder",
    "sg:classifiers":[
        {
            "category":"Food & Beverages",
            "subcategory":"Specialty",
            "type":"Retail Goods"
        }
    ],
    "sg:phone":"+1 770 868 5687",
    "sg:postcode":"30680",
    "sg:province":"GA",
    "wof:name":"Winder Oriental Market",
    "wof:placetype":"venue"
},
  "geometry": {"coordinates":[-83.72307600000001,33.993666],"type":"Point"}
}