{
  "type": "Feature",
  "properties": {
    "addr:full":"1581 Cobb Pkwy Marietta GA 30062",
    "addr:housenumber":"1581",
    "addr:postcode":"30062",
    "addr:street":"Cobb Pkwy",
    "iso:country":"US",
    "sg:address":"1581 Cobb Pkwy",
    "sg:city":"Marietta",
    "sg:classifiers":[
        {
            "category":"Shopping",
            "subcategory":"Bicycles & Sporting Goods",
            "type":"Retail Goods"
        }
    ],
    "sg:phone":"+1 770 955 9500",
    "sg:postcode":"30062",
    "sg:province":"GA",
    "sg:tags":[
        "equipment",
        "golf",
        "supply"
    ],
    "sg:website":"www.mapquest.com",
    "wof:name":"Edwin Watts Golf",
    "wof:placetype":"venue"
},
  "geometry": {"coordinates":[-84.57535,33.988809],"type":"Point"}
}