{
  "type": "Feature",
  "properties": {
    "iso:country":"US",
    "sg:address":"1035 Merchants Dr",
    "sg:city":"Dallas",
    "sg:classifiers":[
        {
            "category":"Personal",
            "type":"Services"
        }
    ],
    "sg:phone":"+1 678 491 0260",
    "sg:postcode":"30132",
    "sg:province":"GA",
    "wof:name":"Badmunkey Inc",
    "wof:placetype":"venue"
},
  "geometry": {"coordinates":[-84.82204299999999,33.912547],"type":"Point"}
}