{
  "type": "Feature",
  "properties": {
    "addr:full":"3320 Buford Dr Buford GA 30519",
    "addr:housenumber":"3320",
    "addr:postcode":"30519",
    "addr:street":"Buford Dr",
    "iso:country":"US",
    "sg:address":"3320 Buford Dr",
    "sg:city":"Buford",
    "sg:classifiers":[
        {
            "category":"Shopping",
            "type":"Retail Goods"
        }
    ],
    "sg:phone":"+1 678 714 0732",
    "sg:postcode":"30519",
    "sg:province":"GA",
    "sg:tags":[
        "plant",
        "flower",
        "tree",
        "artificial"
    ],
    "wof:name":"Evergreen Silk Plants",
    "wof:placetype":"venue"
},
  "geometry": {"coordinates":[-83.985488,34.079614],"type":"Point"}
}