{
  "type": "Feature",
  "properties": {
    "addr:full":"5120 Post Road Pass Stone Mountain GA 30088",
    "addr:housenumber":"5120",
    "addr:postcode":"30088",
    "addr:street":"Post Road Pass",
    "iso:country":"US",
    "sg:address":"5120 Post Road Pass",
    "sg:city":"Stone Mountain",
    "sg:classifiers":[
        {
            "category":"Shopping",
            "subcategory":"Gifts & Souvenirs",
            "type":"Retail Goods"
        }
    ],
    "sg:phone":"+1 770 413 0386",
    "sg:postcode":"30088",
    "sg:province":"GA",
    "wof:name":"Specialty Gift Store",
    "wof:placetype":"venue"
},
  "geometry": {"coordinates":[-84.178586,33.772668],"type":"Point"}
}