{
  "type": "Feature",
  "properties": {
    "addr:full":"5295 Indian Trl Thomaston GA 30286",
    "addr:housenumber":"5295",
    "addr:postcode":"30286",
    "addr:street":"Indian Trl",
    "iso:country":"US",
    "sg:address":"5295 Indian Trl",
    "sg:city":"Thomaston",
    "sg:classifiers":[
        {
            "category":"Travel",
            "subcategory":"Hotels & Motels",
            "type":"Entertainment"
        }
    ],
    "sg:phone":"+1 706 647 9146",
    "sg:postcode":"30286",
    "sg:province":"GA",
    "sg:tags":[
        "operation"
    ],
    "wof:name":"Holiday Motel",
    "wof:placetype":"venue"
},
  "geometry": {"coordinates":[-84.317311,32.855951],"type":"Point"}
}