{
  "type": "Feature",
  "properties": {
    "addr:full":"1415 Centerboard Ct Cumming GA 30041",
    "addr:housenumber":"1415",
    "addr:postcode":"30041",
    "addr:street":"Centerboard Ct",
    "iso:country":"US",
    "sg:address":"1415 Centerboard Ct",
    "sg:city":"Cumming",
    "sg:classifiers":[
        {
            "category":"Professional",
            "type":"Services"
        }
    ],
    "sg:phone":"+1 770 205 7336",
    "sg:postcode":"30041",
    "sg:province":"GA",
    "wof:name":"Michael A Searles",
    "wof:placetype":"venue"
},
  "geometry": {"coordinates":[-84.11856899999999,34.197173],"type":"Point"}
}