{
  "type": "Feature",
  "properties": {
    "iso:country":"US",
    "sg:address":"6428 Narramore Way",
    "sg:city":"Lula",
    "sg:classifiers":[
        {
            "category":"Shopping",
            "subcategory":"Clothing, Apparel, & Fashions",
            "type":"Retail Goods"
        }
    ],
    "sg:phone":"+1 770 869 1017",
    "sg:postcode":"30554",
    "sg:province":"GA",
    "wof:name":"Just Two Dollars More or Less",
    "wof:placetype":"venue"
},
  "geometry": {"coordinates":[-83.660439,34.400934],"type":"Point"}
}