{
  "type": "Feature",
  "properties": {
    "iso:country":"US",
    "sg:address":"6465 Tara Blvd",
    "sg:city":"Jonesboro",
    "sg:classifiers":[
        {
            "category":"Shopping",
            "subcategory":"Beauty & Cosmetics",
            "type":"Retail Goods"
        }
    ],
    "sg:phone":"+1 770 477 6766",
    "sg:postcode":"30236",
    "sg:province":"GA",
    "sg:tags":[
        "supply"
    ],
    "wof:name":"Beauty City",
    "wof:placetype":"venue"
},
  "geometry": {"coordinates":[-84.373001,33.577499],"type":"Point"}
}