{
  "type": "Feature",
  "properties": {
    "iso:country":"US",
    "sg:address":"2570 Spires Dr",
    "sg:city":"Macon",
    "sg:classifiers":[
        {
            "category":"Professional",
            "subcategory":"Advertising",
            "type":"Services"
        }
    ],
    "sg:phone":"+1 478 803 1274",
    "sg:postcode":"31216",
    "sg:province":"GA",
    "wof:name":"Phoenix Diversified",
    "wof:placetype":"venue"
},
  "geometry": {"coordinates":[-83.655749,32.73348],"type":"Point"}
}