{
  "type": "Feature",
  "properties": {
    "iso:country":"US",
    "sg:address":"5621 Old Jefferson Hwy",
    "sg:city":"Woodbine",
    "sg:classifiers":[
        {
            "category":"Building & Trades",
            "subcategory":"Cleaning & Sanitation",
            "type":"Services"
        }
    ],
    "sg:phone":"+1 912 576 3322",
    "sg:postcode":"31569",
    "sg:province":"GA",
    "sg:tags":[
        "maintenance"
    ],
    "wof:name":"Minnies Maid",
    "wof:placetype":"venue"
},
  "geometry": {"coordinates":[-81.75138200000001,30.923847],"type":"Point"}
}