{
  "type": "Feature",
  "properties": {
    "addr:full":"2950 George Busbee Pkwy NW Kennesaw GA 30144",
    "addr:housenumber":"2950",
    "addr:postcode":"30144",
    "addr:street":"George Busbee Pkwy Nw",
    "iso:country":"US",
    "sg:address":"2950 George Busbee Pkwy NW",
    "sg:city":"Kennesaw",
    "sg:classifiers":[
        {
            "category":"Deli",
            "type":"Food & Drink"
        }
    ],
    "sg:menulink":"http://www.allmenus.com/ga/acworth-kennesaw/92997-mcalisters-deli/menu/",
    "sg:phone":"+1 770 499 1581",
    "sg:postcode":"30144",
    "sg:province":"GA",
    "sg:tags":[
        "wrap",
        "american",
        "sandwich"
    ],
    "wof:name":"Mcalister's Deli",
    "wof:placetype":"venue"
},
  "geometry": {"coordinates":[-84.56710699999999,34.025178],"type":"Point"}
}