{
  "type": "Feature",
  "properties": {
    "addr:full":"3388 Hyland Dr Decatur GA 30032",
    "addr:housenumber":"3388",
    "addr:postcode":"30032",
    "addr:street":"Hyland Dr",
    "iso:country":"US",
    "sg:address":"3388 Hyland Dr",
    "sg:city":"Decatur",
    "sg:classifiers":[
        {
            "category":"Manufacturing",
            "subcategory":"Signs",
            "type":"Manufacturing & Wholesale Goods"
        }
    ],
    "sg:phone":"+1 404 289 9170",
    "sg:postcode":"30032",
    "sg:province":"GA",
    "wof:name":"Sign Guy's",
    "wof:placetype":"venue"
},
  "geometry": {"coordinates":[-84.250145,33.730067],"type":"Point"}
}