{
  "type": "Feature",
  "properties": {
    "iso:country":"US",
    "sg:address":"1301 Hightower Trl",
    "sg:city":"Atlanta",
    "sg:classifiers":[
        {
            "category":"Professional",
            "subcategory":"Computer Services",
            "type":"Services"
        }
    ],
    "sg:phone":"+1 404 685 9505",
    "sg:postcode":"30350",
    "sg:province":"GA",
    "sg:tags":[
        "scanning"
    ],
    "sg:website":"www.dartfish.com",
    "wof:name":"Dartfish USA",
    "wof:placetype":"venue"
},
  "geometry": {"coordinates":[-84.345437,33.986836],"type":"Point"}
}