{
  "type": "Feature",
  "properties": {
    "iso:country":"US",
    "sg:address":"136 Jackson Dr",
    "sg:city":"Leesburg",
    "sg:classifiers":[
        {
            "category":"Professional",
            "type":"Services"
        }
    ],
    "sg:phone":"+1 229 431 1152",
    "sg:postcode":"31763",
    "sg:province":"GA",
    "wof:name":"Richard Milburn",
    "wof:placetype":"venue"
},
  "geometry": {"coordinates":[-84.17858200000001,31.640331],"type":"Point"}
}