{
  "type": "Feature",
  "properties": {
    "iso:country":"US",
    "sg:address":"92 Old Center Point Rd",
    "sg:city":"Carrollton",
    "sg:classifiers":[
        {
            "category":"Autos & Motor Vehicles",
            "subcategory":"Automobile Sales",
            "type":"Retail Goods"
        }
    ],
    "sg:phone":"+1 770 830 8053",
    "sg:postcode":"30117",
    "sg:province":"GA",
    "sg:tags":[
        "used"
    ],
    "wof:name":"Morris Auto Sales Inc",
    "wof:placetype":"venue"
},
  "geometry": {"coordinates":[-85.05053599999999,33.664196],"type":"Point"}
}