{
  "type": "Feature",
  "properties": {
    "iso:country":"US",
    "sg:address":"209 N Broad St",
    "sg:city":"Bainbridge",
    "sg:classifiers":[
        {
            "category":"Real Estate",
            "subcategory":"Surveying",
            "type":"Services"
        }
    ],
    "sg:phone":"+1 229 248 4000",
    "sg:postcode":"39817",
    "sg:province":"GA",
    "sg:tags":[
        "surveyor"
    ],
    "wof:name":"Richard Matthews & Assoc",
    "wof:placetype":"venue"
},
  "geometry": {"coordinates":[-84.57554,30.907187],"type":"Point"}
}