{
  "type": "Feature",
  "properties": {
    "iso:country":"US",
    "sg:address":"326 W 2nd St",
    "sg:city":"Jackson",
    "sg:classifiers":[
        {
            "category":"Shopping",
            "subcategory":"Gifts & Souvenirs",
            "type":"Retail Goods"
        }
    ],
    "sg:phone":"+1 770 775 9258",
    "sg:postcode":"30233",
    "sg:province":"GA",
    "sg:tags":[
        "used",
        "merchandise"
    ],
    "wof:name":"Artitic Touch",
    "wof:placetype":"venue"
},
  "geometry": {"coordinates":[-83.969545,33.295228],"type":"Point"}
}