{
  "type": "Feature",
  "properties": {
    "addr:full":"506 Sanders Rd Dalton GA 30720",
    "addr:housenumber":"506",
    "addr:postcode":"30720",
    "addr:street":"Sanders Rd",
    "iso:country":"US",
    "sg:address":"506 Sanders Rd",
    "sg:city":"Dalton",
    "sg:classifiers":[
        {
            "category":"Home & Garden",
            "subcategory":"Carpets & Floor Coverings",
            "type":"Retail Goods"
        }
    ],
    "sg:phone":"+1 706 226 5580",
    "sg:postcode":"30720",
    "sg:province":"GA",
    "wof:name":"Reliable Carpets",
    "wof:placetype":"venue"
},
  "geometry": {"coordinates":[-84.979083,34.742779],"type":"Point"}
}