{
  "type": "Feature",
  "properties": {
    "addr:full":"101 Regency Park Dr Mc Donough GA 30253",
    "addr:housenumber":"101",
    "addr:postcode":"30253",
    "addr:street":"Regency Park Dr",
    "iso:country":"US",
    "sg:address":"101 Regency Park Dr",
    "sg:city":"Mc Donough",
    "sg:classifiers":[
        {
            "category":"Health Services",
            "subcategory":"Medical Lab",
            "type":"Services"
        }
    ],
    "sg:phone":"+1 770 898 4080",
    "sg:postcode":"30253",
    "sg:province":"GA",
    "sg:tags":[
        "laboratory"
    ],
    "wof:name":"My Obgyn",
    "wof:placetype":"venue"
},
  "geometry": {"coordinates":[-84.17273900000001,33.430279],"type":"Point"}
}