{
  "type": "Feature",
  "properties": {
    "iso:country":"US",
    "sg:address":"310 Spaulding Rd",
    "sg:city":"Montezuma",
    "sg:classifiers":[
        {
            "category":"Home & Garden",
            "subcategory":"Furniture",
            "type":"Retail Goods"
        }
    ],
    "sg:phone":"+1 478 472 7368",
    "sg:postcode":"31063",
    "sg:province":"GA",
    "wof:name":"A Touch Above",
    "wof:placetype":"venue"
},
  "geometry": {"coordinates":[-84.02727899999999,32.298012],"type":"Point"}
}