{
  "type": "Feature",
  "properties": {
    "addr:full":"5015 Old Ellis Pt Roswell GA 30076",
    "addr:housenumber":"5015",
    "addr:postcode":"30076",
    "addr:street":"Old Ellis Pt",
    "iso:country":"US",
    "sg:address":"5015 Old Ellis Pt",
    "sg:city":"Roswell",
    "sg:classifiers":[
        {
            "category":"Retail",
            "subcategory":"Auto Repair",
            "type":"Services"
        }
    ],
    "sg:phone":"+1 770 569 4646",
    "sg:postcode":"30076",
    "sg:province":"GA",
    "sg:website":"www.sovereign-automotive.com",
    "wof:name":"Sovereign Automotive Import Specialists",
    "wof:placetype":"venue"
},
  "geometry": {"coordinates":[-84.324303,34.050499],"type":"Point"}
}