{
  "type": "Feature",
  "properties": {
    "iso:country":"US",
    "sg:address":"1792 Dyson Dr",
    "sg:city":"Decatur",
    "sg:classifiers":[
        {
            "category":"Sports & Exercise",
            "subcategory":"Tennis Court",
            "type":"Entertainment"
        }
    ],
    "sg:phone":"+1 404 370 0852",
    "sg:postcode":"30030",
    "sg:province":"GA",
    "sg:tags":[
        "courts-private"
    ],
    "sg:website":"http://www.atlantatennisacademy.com",
    "wof:name":"Atlanta Tennis Academy Inc",
    "wof:placetype":"venue"
},
  "geometry": {"coordinates":[-84.314849,33.77966],"type":"Point"}
}