{
  "type": "Feature",
  "properties": {
    "iso:country":"US",
    "sg:address":"4132 Steve Reynolds Blvd",
    "sg:city":"Norcross",
    "sg:classifiers":[
        {
            "category":"Professional",
            "subcategory":"Accounting & Tax Preparation",
            "type":"Services"
        }
    ],
    "sg:phone":"+1 770 216 9777",
    "sg:postcode":"30093",
    "sg:province":"GA",
    "sg:tags":[
        "accountant"
    ],
    "wof:name":"Professional Accounting & Tax",
    "wof:placetype":"venue"
},
  "geometry": {"coordinates":[-84.147308,33.928597],"type":"Point"}
}