{
  "type": "Feature",
  "properties": {
    "addr:full":"524 Willow Creek Rd Fairburn GA 30213",
    "addr:housenumber":"524",
    "addr:postcode":"30213",
    "addr:street":"Willow Creek Rd",
    "iso:country":"US",
    "sg:address":"524 Willow Creek Rd",
    "sg:city":"Fairburn",
    "sg:classifiers":[
        {
            "category":"Building & Trades",
            "subcategory":"Construction",
            "type":"Services"
        }
    ],
    "sg:phone":"+1 770 964 6847",
    "sg:postcode":"30213",
    "sg:province":"GA",
    "sg:tags":[
        "hanging",
        "contractor"
    ],
    "wof:name":"Preferred Painter",
    "wof:placetype":"venue"
},
  "geometry": {"coordinates":[-84.572613,33.559233],"type":"Point"}
}