{
  "type": "Feature",
  "properties": {
    "iso:country":"US",
    "sg:address":"3586 Jackson St",
    "sg:city":"Atlanta",
    "sg:classifiers":[
        {
            "category":"Taxi",
            "type":"Transportation"
        }
    ],
    "sg:phone":"+1 404 766 7033",
    "sg:postcode":"30337",
    "sg:province":"GA",
    "wof:name":"Taxi Taxi",
    "wof:placetype":"venue"
},
  "geometry": {"coordinates":[-84.443365,33.657386],"type":"Point"}
}