{
  "type": "Feature",
  "properties": {
    "addr:full":"2741 Mayo Rd Augusta GA 30907",
    "addr:housenumber":"2741",
    "addr:postcode":"30907",
    "addr:street":"Mayo Rd",
    "iso:country":"US",
    "sg:address":"2741 Mayo Rd",
    "sg:city":"Augusta",
    "sg:classifiers":[
        {
            "category":"Travel",
            "subcategory":"Travel Agent",
            "type":"Entertainment"
        }
    ],
    "sg:phone":"+1 706 829 3085",
    "sg:postcode":"30907",
    "sg:province":"GA",
    "sg:tags":[
        "agency",
        "services-commercial"
    ],
    "wof:name":"Ultra Experience Travel",
    "wof:placetype":"venue"
},
  "geometry": {"coordinates":[-82.055074,33.521231],"type":"Point"}
}