{
  "type": "Feature",
  "properties": {
    "addr:full":"420 Tanner Hall Rd Dawsonville GA 30534",
    "addr:housenumber":"420",
    "addr:postcode":"30534",
    "addr:street":"Tanner Hall Rd",
    "iso:country":"US",
    "sg:address":"420 Tanner Hall Rd",
    "sg:city":"Dawsonville",
    "sg:classifiers":[
        {
            "category":"Building & Trades",
            "subcategory":"Construction",
            "type":"Services"
        }
    ],
    "sg:phone":"+1 706 216 0384",
    "sg:postcode":"30534",
    "sg:province":"GA",
    "sg:tags":[
        "excavation",
        "contractor"
    ],
    "wof:name":"Dirt Diggers Grading Inc",
    "wof:placetype":"venue"
},
  "geometry": {"coordinates":[-84.143147,34.48164],"type":"Point"}
}