{
  "type": "Feature",
  "properties": {
    "addr:full":"1021 Bryant St SW Conyers GA 30012",
    "addr:housenumber":"1021",
    "addr:postcode":"30012",
    "addr:street":"Bryant St Sw",
    "iso:country":"US",
    "sg:address":"1021 Bryant St SW",
    "sg:city":"Conyers",
    "sg:classifiers":[
        {
            "category":"Organizations",
            "subcategory":"Religious Organization",
            "type":"Services"
        }
    ],
    "sg:phone":"+1 770 922 5707",
    "sg:postcode":"30012",
    "sg:province":"GA",
    "wof:name":"Rock Temple AME Church",
    "wof:placetype":"venue"
},
  "geometry": {"coordinates":[-84.022381,33.664532],"type":"Point"}
}