{
  "type": "Feature",
  "properties": {
    "iso:country":"US",
    "sg:address":"23 Bullsboro Dr",
    "sg:city":"Newnan",
    "sg:classifiers":[
        {
            "category":"Professional",
            "subcategory":"Business Services",
            "type":"Services"
        }
    ],
    "sg:phone":"+1 770 254 3070",
    "sg:postcode":"30263",
    "sg:province":"GA",
    "sg:tags":[
        "agent",
        "real estate"
    ],
    "wof:name":"21st Century Coweta",
    "wof:placetype":"venue"
},
  "geometry": {"coordinates":[-84.79073699999999,33.382696],"type":"Point"}
}