{
  "type": "Feature",
  "properties": {
    "addr:full":"1121 Johnson Ferry Rd Marietta GA 30068",
    "addr:housenumber":"1121",
    "addr:postcode":"30068",
    "addr:street":"Johnson Ferry Rd",
    "iso:country":"US",
    "sg:address":"1121 Johnson Ferry Rd",
    "sg:city":"Marietta",
    "sg:classifiers":[
        {
            "category":"Health Services",
            "subcategory":"Clinic",
            "type":"Services"
        }
    ],
    "sg:phone":"+1 770 973 3044",
    "sg:postcode":"30068",
    "sg:province":"GA",
    "sg:tags":[
        "counseling",
        "mental"
    ],
    "wof:name":"Hartley-Selvey Bonnie Lcsw Lmft",
    "wof:placetype":"venue"
},
  "geometry": {"coordinates":[-84.418503,33.978401],"type":"Point"}
}