{
  "type": "Feature",
  "properties": {
    "addr:full":"4616 Hugh Howell Rd Tucker GA 30084",
    "addr:housenumber":"4616",
    "addr:postcode":"30084",
    "addr:street":"Hugh Howell Rd",
    "iso:country":"US",
    "sg:address":"4616 Hugh Howell Rd",
    "sg:city":"Tucker",
    "sg:classifiers":[
        {
            "category":"Manufacturing",
            "subcategory":"Rubber & Plastics",
            "type":"Manufacturing & Wholesale Goods"
        },
        {
            "category":"Autos & Motor Vehicles",
            "subcategory":"Auto Supplies",
            "type":"Retail Goods"
        },
        {
            "category":"Retail",
            "subcategory":"Auto Repair",
            "type":"Services"
        }
    ],
    "sg:phone":"+1 770 493 6077",
    "sg:postcode":"30084",
    "sg:province":"GA",
    "sg:tags":[
        "wheel",
        "tires-wholesale",
        "tire",
        "retread",
        "balancing",
        "wheels-aligning",
        "recap",
        "brake",
        "manufacturer"
    ],
    "sg:website":"www.ntb.com",
    "wof:name":"Ntb-National Tire & Battery",
    "wof:placetype":"venue"
},
  "geometry": {"coordinates":[-84.19969,33.849078],"type":"Point"}
}