{
  "type": "Feature",
  "properties": {
    "addr:full":"2550 Milledgeville Rd Augusta GA 30904",
    "addr:housenumber":"2550",
    "addr:postcode":"30904",
    "addr:street":"Milledgeville Rd",
    "iso:country":"US",
    "sg:address":"2550 Milledgeville Rd",
    "sg:city":"Augusta",
    "sg:classifiers":[
        {
            "category":"Personal",
            "subcategory":"Beauty Salon",
            "type":"Services"
        }
    ],
    "sg:phone":"+1 706 738 1004",
    "sg:postcode":"30904",
    "sg:province":"GA",
    "sg:tags":[
        "hair",
        "stylist"
    ],
    "wof:name":"Charmante",
    "wof:placetype":"venue"
},
  "geometry": {"coordinates":[-82.017983,33.446667],"type":"Point"}
}