{
  "type": "Feature",
  "properties": {
    "iso:country":"US",
    "sg:address":"1422 Southworth Dr",
    "sg:city":"Griffin",
    "sg:classifiers":[
        {
            "category":"Professional",
            "type":"Services"
        }
    ],
    "sg:phone":"+1 770 227 8082",
    "sg:postcode":"30224",
    "sg:province":"GA",
    "wof:name":"J Moyer Inc",
    "wof:placetype":"venue"
},
  "geometry": {"coordinates":[-84.253061,33.209149],"type":"Point"}
}