{
  "type": "Feature",
  "properties": {
    "iso:country":"US",
    "sg:address":"22 Perimeter Center E",
    "sg:city":"Atlanta",
    "sg:classifiers":[
        {
            "category":"Banks & Credit Unions",
            "subcategory":"Bank",
            "type":"Services"
        }
    ],
    "sg:phone":"+1 770 673 0029",
    "sg:postcode":"30346",
    "sg:province":"GA",
    "sg:tags":[
        "mortgage"
    ],
    "wof:name":"Pulaski Mortgage Company",
    "wof:placetype":"venue"
},
  "geometry": {"coordinates":[-84.32996,33.923444],"type":"Point"}
}