{
  "type": "Feature",
  "properties": {
    "iso:country":"US",
    "sg:address":"230 Roxbury Cir",
    "sg:city":"Alpharetta",
    "sg:classifiers":[
        {
            "category":"Food & Beverages",
            "subcategory":"Bakery",
            "type":"Retail Goods"
        }
    ],
    "sg:phone":"+1 678 455 7674",
    "sg:postcode":"30004",
    "sg:province":"GA",
    "sg:tags":[
        "baker"
    ],
    "wof:name":"Posh Cakes",
    "wof:placetype":"venue"
},
  "geometry": {"coordinates":[-84.270803,34.18876],"type":"Point"}
}