{
  "type": "Feature",
  "properties": {
    "iso:country":"US",
    "sg:address":"2377 Lumpkin Rd",
    "sg:city":"Augusta",
    "sg:classifiers":[
        {
            "category":"Personal",
            "subcategory":"Beauty Salon",
            "type":"Services"
        }
    ],
    "sg:phone":"+1 706 796 2998",
    "sg:postcode":"30906",
    "sg:province":"GA",
    "sg:tags":[
        "shop"
    ],
    "wof:name":"Everns Salon",
    "wof:placetype":"venue"
},
  "geometry": {"coordinates":[-82.038794,33.420651],"type":"Point"}
}