{
  "type": "Feature",
  "properties": {
    "addr:full":"6710 Douglas Blvd Douglasville GA 30135",
    "addr:housenumber":"6710",
    "addr:postcode":"30135",
    "addr:street":"Douglas Blvd",
    "iso:country":"US",
    "sg:address":"6710 Douglas Blvd",
    "sg:city":"Douglasville",
    "sg:classifiers":[
        {
            "category":"Restaurant",
            "type":"Food & Drink"
        }
    ],
    "sg:menulink":"http://www.allmenus.com/ga/bill-arp/13859-olive-garden-italian-restaurant/menu/",
    "sg:phone":"+1 770 577 5858",
    "sg:postcode":"30135",
    "sg:province":"GA",
    "sg:tags":[
        "italian"
    ],
    "wof:name":"Olive Garden Italian Restaurant",
    "wof:placetype":"venue"
},
  "geometry": {"coordinates":[-84.749853,33.728997],"type":"Point"}
}