{
  "type": "Feature",
  "properties": {
    "iso:country":"US",
    "sg:address":"206 Nelson St",
    "sg:city":"Cartersville",
    "sg:classifiers":[
        {
            "category":"Shopping",
            "subcategory":"Gifts & Souvenirs",
            "type":"Retail Goods"
        }
    ],
    "sg:phone":"+1 678 721 6952",
    "sg:postcode":"30120",
    "sg:province":"GA",
    "sg:tags":[
        "shop"
    ],
    "wof:name":"Tuesday Morning",
    "wof:placetype":"venue"
},
  "geometry": {"coordinates":[-84.790184,34.172327],"type":"Point"}
}