{
  "type": "Feature",
  "properties": {
    "iso:country":"US",
    "sg:address":"104 Augusta",
    "sg:city":"Saint Simons Island",
    "sg:classifiers":[
        {
            "category":"Real Estate",
            "subcategory":"Real Estate Agent",
            "type":"Services"
        }
    ],
    "sg:phone":"+1 912 634 1989",
    "sg:postcode":"31522",
    "sg:province":"GA",
    "wof:name":"Hoshall Co Inc",
    "wof:placetype":"venue"
},
  "geometry": {"coordinates":[-81.402857,31.153021],"type":"Point"}
}