{
  "type": "Feature",
  "properties": {
    "iso:country":"US",
    "sg:address":"4350 Highborne Dr NE",
    "sg:city":"Marietta",
    "sg:classifiers":[
        {
            "category":"Health Services",
            "subcategory":"Doctor",
            "type":"Services"
        }
    ],
    "sg:phone":"+1 770 971 7293",
    "sg:postcode":"30066",
    "sg:province":"GA",
    "sg:tags":[
        "surgeon",
        "oral"
    ],
    "wof:name":"Coe Stuart E DDS",
    "wof:placetype":"venue"
},
  "geometry": {"coordinates":[-84.453796,34.059601],"type":"Point"}
}