{
  "type": "Feature",
  "properties": {
    "iso:country":"US",
    "sg:address":"900 Sun Valley Dr",
    "sg:city":"Roswell",
    "sg:classifiers":[
        {
            "category":"Professional",
            "subcategory":"Business Services",
            "type":"Services"
        }
    ],
    "sg:phone":"+1 770 998 0885",
    "sg:postcode":"30076",
    "sg:province":"GA",
    "wof:name":"Las Americas Automotive Servic",
    "wof:placetype":"venue"
},
  "geometry": {"coordinates":[-84.3348,34.049319],"type":"Point"}
}