{
  "type": "Feature",
  "properties": {
    "addr:full":"108 E Railroad St NE Parrott GA 31779",
    "addr:housenumber":"108",
    "addr:postcode":"31779",
    "addr:street":"E Railroad St Ne",
    "iso:country":"US",
    "sg:address":"108 E Railroad St NE",
    "sg:city":"Parrott",
    "sg:classifiers":[
        {
            "category":"Shopping",
            "subcategory":"Musical Instruments",
            "type":"Retail Goods"
        }
    ],
    "sg:phone":"+1 229 623 5545",
    "sg:postcode":"31779",
    "sg:province":"GA",
    "wof:name":"Sound Play",
    "wof:placetype":"venue"
},
  "geometry": {"coordinates":[-84.151853,31.127889],"type":"Point"}
}