{
  "type": "Feature",
  "properties": {
    "addr:full":"1103 N Davis Dr Warner Robins GA 31093",
    "addr:housenumber":"1103",
    "addr:postcode":"31093",
    "addr:street":"N Davis Dr",
    "iso:country":"US",
    "sg:address":"1103 N Davis Dr",
    "sg:city":"Warner Robins",
    "sg:classifiers":[
        {
            "category":"Retail",
            "subcategory":"Auto Repair",
            "type":"Services"
        }
    ],
    "sg:phone":"+1 478 929 4252",
    "sg:postcode":"31093",
    "sg:province":"GA",
    "sg:tags":[
        "general"
    ],
    "wof:name":"Killian S Porting Srvice",
    "wof:placetype":"venue"
},
  "geometry": {"coordinates":[-83.6127,32.650872],"type":"Point"}
}