{
  "type": "Feature",
  "properties": {
    "addr:full":"420 Center Point Dr SE Dalton GA 30721",
    "addr:housenumber":"420",
    "addr:postcode":"30721",
    "addr:street":"Center Point Dr Se",
    "iso:country":"US",
    "sg:address":"420 Center Point Dr SE",
    "sg:city":"Dalton",
    "sg:classifiers":[
        {
            "category":"Organizations",
            "subcategory":"Religious Organization",
            "type":"Services"
        }
    ],
    "sg:phone":"+1 706 277 2100",
    "sg:postcode":"30721",
    "sg:province":"GA",
    "sg:tags":[
        "church"
    ],
    "wof:name":"Center Point Baptist Chr",
    "wof:placetype":"venue"
},
  "geometry": {"coordinates":[-84.987742,34.688433],"type":"Point"}
}