{
  "type": "Feature",
  "properties": {
    "addr:full":"2009 US Hwy 80 Dublin GA 31027",
    "addr:housenumber":"2009",
    "addr:postcode":"31027",
    "addr:street":"Us Hwy 80",
    "iso:country":"US",
    "sg:address":"2009 US Hwy 80",
    "sg:city":"Dublin",
    "sg:classifiers":[
        {
            "category":"Food & Beverages",
            "subcategory":"Groceries & Convenience Stores",
            "type":"Retail Goods"
        }
    ],
    "sg:phone":"+1 478 275 2844",
    "sg:postcode":"31027",
    "sg:province":"GA",
    "wof:name":"Friendly Gus Food Store 7",
    "wof:placetype":"venue"
},
  "geometry": {"coordinates":[-82.745029,32.555916],"type":"Point"}
}