{
  "type": "Feature",
  "properties": {
    "addr:full":"6289 Jimmy Carter Blvd Norcross GA 30071",
    "addr:housenumber":"6289",
    "addr:postcode":"30071",
    "addr:street":"Jimmy Carter Blvd",
    "iso:country":"US",
    "sg:address":"6289 Jimmy Carter Blvd",
    "sg:city":"Norcross",
    "sg:classifiers":[
        {
            "category":"Freight",
            "type":"Transportation"
        }
    ],
    "sg:phone":"+1 770 368 9515",
    "sg:postcode":"30071",
    "sg:province":"GA",
    "sg:tags":[
        "commercial",
        "storage"
    ],
    "wof:name":"Public Storage Inc",
    "wof:placetype":"venue"
},
  "geometry": {"coordinates":[-84.220977,33.930062],"type":"Point"}
}