{
  "type": "Feature",
  "properties": {
    "addr:full":"514 Scotts Way Augusta GA 30909",
    "addr:housenumber":"514",
    "addr:postcode":"30909",
    "addr:street":"Scotts Way",
    "iso:country":"US",
    "sg:address":"514 Scotts Way",
    "sg:city":"Augusta",
    "sg:classifiers":[
        {
            "category":"Banks & Credit Unions",
            "subcategory":"Financial Services",
            "type":"Services"
        }
    ],
    "sg:phone":"+1 706 733 6157",
    "sg:postcode":"30909",
    "sg:province":"GA",
    "sg:tags":[
        "investor"
    ],
    "wof:name":"Perkins Enterprises LP",
    "wof:placetype":"venue"
},
  "geometry": {"coordinates":[-82.06135399999999,33.495189],"type":"Point"}
}