{
  "type": "Feature",
  "properties": {
    "iso:country":"US",
    "sg:address":"3270 Timber Moon Ct",
    "sg:city":"Lawrenceville",
    "sg:classifiers":[
        {
            "category":"Shopping",
            "subcategory":"Computers & Home Electronics",
            "type":"Retail Goods"
        }
    ],
    "sg:phone":"+1 770 381 1721",
    "sg:postcode":"30044",
    "sg:province":"GA",
    "sg:tags":[
        "equipment",
        "dealer"
    ],
    "wof:name":"Computer Ingenuity Assoc",
    "wof:placetype":"venue"
},
  "geometry": {"coordinates":[-84.078834,33.897097],"type":"Point"}
}