{
  "type": "Feature",
  "properties": {
    "addr:full":"1909 Watson Blvd Warner Robins GA 31093",
    "addr:housenumber":"1909",
    "addr:postcode":"31093",
    "addr:street":"Watson Blvd",
    "iso:country":"US",
    "sg:address":"1909 Watson Blvd",
    "sg:city":"Warner Robins",
    "sg:classifiers":[
        {
            "category":"Autos & Motor Vehicles",
            "subcategory":"Automobile Sales",
            "type":"Retail Goods"
        }
    ],
    "sg:phone":"+1 478 929 0053",
    "sg:postcode":"31093",
    "sg:province":"GA",
    "sg:tags":[
        "used"
    ],
    "wof:name":"Martins Autos",
    "wof:placetype":"venue"
},
  "geometry": {"coordinates":[-83.641768,32.618295],"type":"Point"}
}