{
  "type": "Feature",
  "properties": {
    "addr:full":"604 Hillcrest Pkwy Dublin GA 31021",
    "addr:housenumber":"604",
    "addr:postcode":"31021",
    "addr:street":"Hillcrest Pkwy",
    "iso:country":"US",
    "sg:address":"604 Hillcrest Pkwy",
    "sg:city":"Dublin",
    "sg:classifiers":[
        {
            "category":"Real Estate",
            "subcategory":"Real Estate Services",
            "type":"Services"
        },
        {
            "category":"Real Estate",
            "subcategory":"Real Estate Operator",
            "type":"Services"
        }
    ],
    "sg:phone":"+1 478 275 3208",
    "sg:postcode":"31021",
    "sg:province":"GA",
    "sg:tags":[
        "vacancy",
        "apartment",
        "rental",
        "finder",
        "listing"
    ],
    "sg:website":"http://www.trailsapts.com",
    "wof:name":"Carriage Hill Apartments",
    "wof:placetype":"venue"
},
  "geometry": {"coordinates":[-82.922225,32.550525],"type":"Point"}
}