{
  "type": "Feature",
  "properties": {
    "addr:full":"2 Macon St Mcdonough GA 30253",
    "addr:housenumber":"2",
    "addr:postcode":"30253",
    "addr:street":"Macon St",
    "iso:country":"US",
    "sg:address":"2 Macon St",
    "sg:city":"Mcdonough",
    "sg:classifiers":[
        {
            "category":"Real Estate",
            "subcategory":"Architect",
            "type":"Services"
        }
    ],
    "sg:phone":"+1 678 583 1020",
    "sg:postcode":"30253",
    "sg:province":"GA",
    "wof:name":"Colvin & Colvin",
    "wof:placetype":"venue"
},
  "geometry": {"coordinates":[-84.146373,33.447007],"type":"Point"}
}