{
  "type": "Feature",
  "properties": {
    "iso:country":"US",
    "sg:address":"3655 Kennesaw 75 Pkwy",
    "sg:city":"Kennesaw",
    "sg:classifiers":[
        {
            "category":"Freight",
            "type":"Transportation"
        }
    ],
    "sg:phone":"+1 678 290 2024",
    "sg:postcode":"30144",
    "sg:province":"GA",
    "sg:tags":[
        "operator",
        "local",
        "storage",
        "trucking"
    ],
    "wof:name":"Budd Van Lines",
    "wof:placetype":"venue"
},
  "geometry": {"coordinates":[-84.609831,34.046937],"type":"Point"}
}