{
  "type": "Feature",
  "properties": {
    "iso:country":"US",
    "sg:address":"1164 Pair Rd SW",
    "sg:city":"Marietta",
    "sg:classifiers":[
        {
            "category":"Home & Garden",
            "subcategory":"Building Materials",
            "type":"Retail Goods"
        }
    ],
    "sg:phone":"+1 770 485 1011",
    "sg:postcode":"30060",
    "sg:province":"GA",
    "sg:tags":[
        "awning",
        "canopy"
    ],
    "wof:name":"Awnings By Design",
    "wof:placetype":"venue"
},
  "geometry": {"coordinates":[-84.587962,33.876543],"type":"Point"}
}