{
  "type": "Feature",
  "properties": {
    "iso:country":"US",
    "sg:address":"925 Peachtree St NE",
    "sg:city":"Atlanta",
    "sg:classifiers":[
        {
            "category":"Building & Trades",
            "subcategory":"Construction",
            "type":"Services"
        }
    ],
    "sg:phone":"+1 678 973 4253",
    "sg:postcode":"30309",
    "sg:province":"GA",
    "sg:tags":[
        "contractor"
    ],
    "sg:website":"concreteinatlanta.info",
    "wof:name":"All American Decorative Concrete",
    "wof:placetype":"venue"
},
  "geometry": {"coordinates":[-84.384061,33.780003],"type":"Point"}
}