{
  "type": "Feature",
  "properties": {
    "addr:full":"4882 Ardsley Dr Lithonia GA 30038",
    "addr:housenumber":"4882",
    "addr:postcode":"30038",
    "addr:street":"Ardsley Dr",
    "iso:country":"US",
    "sg:address":"4882 Ardsley Dr",
    "sg:city":"Lithonia",
    "sg:classifiers":[
        {
            "category":"Shopping",
            "subcategory":"Gifts & Souvenirs",
            "type":"Retail Goods"
        }
    ],
    "sg:phone":"+1 770 981 5226",
    "sg:postcode":"30038",
    "sg:province":"GA",
    "wof:name":"Abide Florals & Gifts",
    "wof:placetype":"venue"
},
  "geometry": {"coordinates":[-84.187984,33.681818],"type":"Point"}
}