{
  "type": "Feature",
  "properties": {
    "iso:country":"US",
    "sg:address":"757 Grimes Bridge Rd",
    "sg:city":"Roswell",
    "sg:classifiers":[
        {
            "category":"Building & Trades",
            "subcategory":"Electrical",
            "type":"Services"
        }
    ],
    "sg:phone":"+1 678 461 8886",
    "sg:postcode":"30075",
    "sg:province":"GA",
    "sg:tags":[
        "energy",
        "company"
    ],
    "wof:name":"International Energy Solutions",
    "wof:placetype":"venue"
},
  "geometry": {"coordinates":[-84.340701,34.016072],"type":"Point"}
}