{
  "type": "Feature",
  "properties": {
    "iso:country":"US",
    "sg:address":"308 N Main St",
    "sg:city":"Jonesboro",
    "sg:classifiers":[
        {
            "category":"Home & Garden",
            "subcategory":"Building Materials",
            "type":"Retail Goods"
        }
    ],
    "sg:phone":"+1 770 478 4390",
    "sg:postcode":"30236",
    "sg:province":"GA",
    "sg:tags":[
        "front",
        "glass",
        "window",
        "store",
        "plate"
    ],
    "sg:website":"http://www.realpagessites.com/betterbuyglass",
    "wof:name":"Better Buy Glass Mirror & Screen Co",
    "wof:placetype":"venue"
},
  "geometry": {"coordinates":[-84.358304,33.53405],"type":"Point"}
}