{
  "type": "Feature",
  "properties": {
    "iso:country":"US",
    "sg:address":"50 Standing Rock Rd",
    "sg:city":"Senoia",
    "sg:classifiers":[
        {
            "category":"Building & Trades",
            "subcategory":"Construction",
            "type":"Services"
        }
    ],
    "sg:phone":"+1 770 599 9769",
    "sg:postcode":"30276",
    "sg:province":"GA",
    "sg:tags":[
        "contractor"
    ],
    "wof:name":"On Site Gutters",
    "wof:placetype":"venue"
},
  "geometry": {"coordinates":[-84.561701,33.309673],"type":"Point"}
}