{
  "type": "Feature",
  "properties": {
    "iso:country":"US",
    "sg:address":"1500 Eastview Rd NE",
    "sg:city":"Conyers",
    "sg:classifiers":[
        {
            "category":"Real Estate",
            "subcategory":"Real Estate Operator",
            "type":"Services"
        }
    ],
    "sg:phone":"+1 877 254 1089",
    "sg:postcode":"30012",
    "sg:province":"GA",
    "sg:tags":[
        "apartment"
    ],
    "sg:website":"http://local.ingenio.com/Listings/Details.aspx?NUM=a%3a10249063%3a13%3a4859924%3a14%3a0%3a7",
    "wof:name":"Brandon Glen",
    "wof:placetype":"venue"
},
  "geometry": {"coordinates":[-83.991241,33.672974],"type":"Point"}
}