{
  "type": "Feature",
  "properties": {
    "iso:country":"US",
    "sg:address":"3010 Fairplay Rd",
    "sg:city":"Rutledge",
    "sg:classifiers":[
        {
            "category":"Autos & Motor Vehicles",
            "subcategory":"Automobile Sales",
            "type":"Retail Goods"
        }
    ],
    "sg:phone":"+1 706 342 4852",
    "sg:postcode":"30663",
    "sg:province":"GA",
    "sg:tags":[
        "car",
        "used",
        "dealer"
    ],
    "wof:name":"Knights Used Cars Inc",
    "wof:placetype":"venue"
},
  "geometry": {"coordinates":[-83.573168,33.692902],"type":"Point"}
}