{
  "type": "Feature",
  "properties": {
    "addr:full":"2141 Shady Ln Tucker GA 30084",
    "addr:housenumber":"2141",
    "addr:postcode":"30084",
    "addr:street":"Shady Ln",
    "iso:country":"US",
    "sg:address":"2141 Shady Ln",
    "sg:city":"Tucker",
    "sg:classifiers":[
        {
            "category":"Retail",
            "subcategory":"Auto Repair",
            "type":"Services"
        }
    ],
    "sg:phone":"+1 770 491 3150",
    "sg:postcode":"30084",
    "sg:province":"GA",
    "sg:tags":[
        "body",
        "shop"
    ],
    "wof:name":"Auto Motion Body Shop",
    "wof:placetype":"venue"
},
  "geometry": {"coordinates":[-84.22666599999999,33.846852],"type":"Point"}
}