{
  "type": "Feature",
  "properties": {
    "addr:full":"8632 Main St Woodstock GA 30188",
    "addr:housenumber":"8632",
    "addr:postcode":"30188",
    "addr:street":"Main St",
    "iso:country":"US",
    "sg:address":"8632 Main St",
    "sg:city":"Woodstock",
    "sg:classifiers":[
        {
            "category":"Building & Trades",
            "subcategory":"Construction",
            "type":"Services"
        }
    ],
    "sg:phone":"+1 678 494 1991",
    "sg:postcode":"30188",
    "sg:province":"GA",
    "sg:tags":[
        "marble",
        "terrazzo"
    ],
    "wof:name":"ARC Restoration",
    "wof:placetype":"venue"
},
  "geometry": {"coordinates":[-84.519549,34.100903],"type":"Point"}
}