{
  "type": "Feature",
  "properties": {
    "addr:full":"3370 Calhoun Rd NE Rome GA 30161",
    "addr:housenumber":"3370",
    "addr:postcode":"ga 30161",
    "addr:street":"Calhoun Rd Ne",
    "iso:country":"US",
    "sg:address":"3370 Calhoun Rd NE",
    "sg:city":"Rome",
    "sg:classifiers":[
        {
            "category":"Building & Trades",
            "subcategory":"Electrical",
            "type":"Services"
        }
    ],
    "sg:phone":"+1 706 235 3858",
    "sg:postcode":"30161",
    "sg:province":"GA",
    "sg:tags":[
        "electric",
        "contractor"
    ],
    "wof:name":"Central Electrical Systems",
    "wof:placetype":"venue"
},
  "geometry": {"coordinates":[-85.09762600000001,34.312045],"type":"Point"}
}