{
  "type": "Feature",
  "properties": {
    "addr:full":"718 Sowell Rd Mc Donough GA 30252",
    "addr:housenumber":"718",
    "addr:postcode":"30252",
    "addr:street":"Sowell Rd",
    "iso:country":"US",
    "sg:address":"718 Sowell Rd",
    "sg:city":"Mc Donough",
    "sg:classifiers":[
        {
            "category":"Wholesale",
            "subcategory":"Construction Materials",
            "type":"Manufacturing & Wholesale Goods"
        }
    ],
    "sg:phone":"+1 770 957 2034",
    "sg:postcode":"30252",
    "sg:province":"GA",
    "wof:name":"Lacewood Corp",
    "wof:placetype":"venue"
},
  "geometry": {"coordinates":[-84.102037,33.415784],"type":"Point"}
}