{
  "type": "Feature",
  "properties": {
    "addr:full":"4020 Jonesboro Rd Forest Park GA 30297",
    "addr:housenumber":"4020",
    "addr:postcode":"30297",
    "addr:street":"Jonesboro Rd",
    "iso:country":"US",
    "sg:address":"4020 Jonesboro Rd",
    "sg:city":"Forest Park",
    "sg:classifiers":[
        {
            "category":"Wholesale",
            "subcategory":"Auto Parts",
            "type":"Manufacturing & Wholesale Goods"
        }
    ],
    "sg:phone":"+1 404 366 2441",
    "sg:postcode":"30297",
    "sg:province":"GA",
    "sg:tags":[
        "supply"
    ],
    "wof:name":"U S Auto Parts & Salvage",
    "wof:placetype":"venue"
},
  "geometry": {"coordinates":[-84.36145,33.640275],"type":"Point"}
}