{
  "type": "Feature",
  "properties": {
    "addr:full":"402 Musket Ridge Hull GA 30646",
    "addr:housenumber":"402",
    "addr:postcode":"30646",
    "addr:street":"Musket Ridge",
    "iso:country":"US",
    "sg:address":"402 Musket Ridge",
    "sg:city":"Hull",
    "sg:classifiers":[
        {
            "category":"Shopping",
            "subcategory":"Gifts & Souvenirs",
            "type":"Retail Goods"
        }
    ],
    "sg:phone":"+1 706 353 0585",
    "sg:postcode":"30646",
    "sg:province":"GA",
    "wof:name":"Georgia Bikeboy Gourmet",
    "wof:placetype":"venue"
},
  "geometry": {"coordinates":[-83.268989,34.016908],"type":"Point"}
}