{
  "type": "Feature",
  "properties": {
    "iso:country":"US",
    "sg:address":"290 E Main St",
    "sg:city":"Rutledge",
    "sg:classifiers":[
        {
            "category":"Farming",
            "subcategory":"Farm",
            "type":"Manufacturing & Wholesale Goods"
        }
    ],
    "sg:phone":"+1 706 557 2755",
    "sg:postcode":"30663",
    "sg:province":"GA",
    "wof:name":"Pine Valley Farms Inc",
    "wof:placetype":"venue"
},
  "geometry": {"coordinates":[-83.597756,33.623632],"type":"Point"}
}