{
  "type": "Feature",
  "properties": {
    "addr:full":"153 Liberty St Waynesboro GA 30830",
    "addr:housenumber":"153",
    "addr:postcode":"30830",
    "addr:street":"Liberty St",
    "iso:country":"US",
    "sg:address":"153 Liberty St",
    "sg:city":"Waynesboro",
    "sg:classifiers":[
        {
            "category":"Sports & Exercise",
            "subcategory":"Gym",
            "type":"Entertainment"
        }
    ],
    "sg:phone":"+1 706 554 9191",
    "sg:postcode":"30830",
    "sg:province":"GA",
    "sg:tags":[
        "gymnasium"
    ],
    "wof:name":"Body Right Fitness Ctr",
    "wof:placetype":"venue"
},
  "geometry": {"coordinates":[-82.008515,33.079649],"type":"Point"}
}