{
  "type": "Feature",
  "properties": {
    "addr:full":"1105 Saint Marks Walk Suwanee GA 30024",
    "addr:housenumber":"1105",
    "addr:postcode":"30024",
    "addr:street":"Saint Marks Walk",
    "iso:country":"US",
    "sg:address":"1105 Saint Marks Walk",
    "sg:city":"Suwanee",
    "sg:classifiers":[
        {
            "category":"Professional",
            "subcategory":"Management & Consulting",
            "type":"Services"
        }
    ],
    "sg:phone":"+1 770 495 1600",
    "sg:postcode":"30024",
    "sg:province":"GA",
    "sg:tags":[
        "business"
    ],
    "wof:name":"Leadership Consulting Group",
    "wof:placetype":"venue"
},
  "geometry": {"coordinates":[-84.139538,34.059142],"type":"Point"}
}