{
  "type": "Feature",
  "properties": {
    "iso:country":"US",
    "sg:address":"1165 Pace St",
    "sg:city":"Covington",
    "sg:classifiers":[
        {
            "category":"Social Services",
            "type":"Services"
        }
    ],
    "sg:phone":"+1 770 784 2110",
    "sg:postcode":"30014",
    "sg:province":"GA",
    "sg:tags":[
        "probation"
    ],
    "wof:name":"Newton County State Probation",
    "wof:placetype":"venue"
},
  "geometry": {"coordinates":[-83.859482,33.597647],"type":"Point"}
}