{
  "type": "Feature",
  "properties": {
    "addr:full":"1155 Mount Vernon Hwy Ste 700 Atlanta GA 30338",
    "addr:housenumber":"1155",
    "addr:postcode":"30338",
    "addr:street":"Mount Vernon Hwy Ste 700",
    "iso:country":"US",
    "sg:address":"1155 Mount Vernon Hwy Ste 700",
    "sg:city":"Atlanta",
    "sg:classifiers":[
        {
            "category":"Shopping",
            "subcategory":"Stationery & Office Supplies",
            "type":"Retail Goods"
        },
        {
            "category":"Wholesale",
            "subcategory":"Computers",
            "type":"Manufacturing & Wholesale Goods"
        }
    ],
    "sg:phone":"+1 770 396 8898",
    "sg:postcode":"30338",
    "sg:province":"GA",
    "sg:tags":[
        "equipment"
    ],
    "sg:website":"www.officedepot.com",
    "wof:name":"Office Depot",
    "wof:placetype":"venue"
},
  "geometry": {"coordinates":[-84.42620700000001,33.898405],"type":"Point"}
}