{
  "type": "Feature",
  "properties": {
    "iso:country":"US",
    "sg:address":"151 Cormorant Ct",
    "sg:city":"Savannah",
    "sg:classifiers":[
        {
            "category":"Professional",
            "type":"Services"
        }
    ],
    "sg:phone":"+1 912 920 3900",
    "sg:postcode":"31419",
    "sg:province":"GA",
    "wof:name":"Greatness For Ageless",
    "wof:placetype":"venue"
},
  "geometry": {"coordinates":[-81.244871,31.973922],"type":"Point"}
}