{
  "type": "Feature",
  "properties": {
    "iso:country":"US",
    "sg:address":"500 E Grady St",
    "sg:city":"Statesboro",
    "sg:classifiers":[
        {
            "category":"Building & Trades",
            "subcategory":"Plumbing",
            "type":"Services"
        }
    ],
    "sg:phone":"+1 912 764 4421",
    "sg:postcode":"30458",
    "sg:province":"GA",
    "sg:tags":[
        "plumber",
        "industrial",
        "contractors-commercial"
    ],
    "wof:name":"Jerry L Brown Plumbing And Electrical",
    "wof:placetype":"venue"
},
  "geometry": {"coordinates":[-81.77149199999999,32.441921],"type":"Point"}
}