{
  "type": "Feature",
  "properties": {
    "addr:full":"129 N Main St Cleveland GA 30528",
    "addr:housenumber":"129",
    "addr:postcode":"30528",
    "addr:street":"N Main St",
    "iso:country":"US",
    "sg:address":"129 N Main St",
    "sg:city":"Cleveland",
    "sg:classifiers":[
        {
            "category":"Restaurant",
            "type":"Food & Drink"
        }
    ],
    "sg:menulink":"http://www.allmenus.com/ga/cleveland/101656-huddle-house/menu/",
    "sg:phone":"+1 706 865 5922",
    "sg:postcode":"30528",
    "sg:province":"GA",
    "sg:tags":[
        "american",
        "diner"
    ],
    "wof:name":"Huddle House",
    "wof:placetype":"venue"
},
  "geometry": {"coordinates":[-83.763493,34.597076],"type":"Point"}
}