{
  "type": "Feature",
  "properties": {
    "addr:full":"126 Grove Rd Locust Grove GA 30248",
    "addr:housenumber":"126",
    "addr:postcode":"30248",
    "addr:street":"Grove Rd",
    "iso:country":"US",
    "sg:address":"126 Grove Rd",
    "sg:city":"Locust Grove",
    "sg:classifiers":[
        {
            "category":"Building & Trades",
            "subcategory":"Construction",
            "type":"Services"
        }
    ],
    "sg:phone":"+1 678 432 2244",
    "sg:postcode":"30248",
    "sg:province":"GA",
    "sg:tags":[
        "general"
    ],
    "wof:name":"J & J General Contrators",
    "wof:placetype":"venue"
},
  "geometry": {"coordinates":[-84.099358,33.344333],"type":"Point"}
}