{
  "type": "Feature",
  "properties": {
    "addr:full":"2049 Kinderton Manor Dr Duluth GA 30097",
    "addr:housenumber":"2049",
    "addr:postcode":"30097",
    "addr:street":"Kinderton Manor Dr",
    "iso:country":"US",
    "sg:address":"2049 Kinderton Manor Dr",
    "sg:city":"Duluth",
    "sg:classifiers":[
        {
            "category":"Building & Trades",
            "subcategory":"Construction",
            "type":"Services"
        }
    ],
    "sg:phone":"+1 770 814 9590",
    "sg:postcode":"30097",
    "sg:province":"GA",
    "sg:tags":[
        "house"
    ],
    "wof:name":"Restoration Experts Inc",
    "wof:placetype":"venue"
},
  "geometry": {"coordinates":[-84.18099599999999,34.033197],"type":"Point"}
}