{
  "type": "Feature",
  "properties": {
    "addr:full":"2124 Boar Tusk Rd NE Conyers GA 30012",
    "addr:housenumber":"2124",
    "addr:postcode":"30012",
    "addr:street":"Boar Tusk Rd Ne",
    "iso:country":"US",
    "sg:address":"2124 Boar Tusk Rd NE",
    "sg:city":"Conyers",
    "sg:classifiers":[
        {
            "category":"Education",
            "subcategory":"Preschool",
            "type":"Public Place"
        }
    ],
    "sg:phone":"+1 770 761 9289",
    "sg:postcode":"30012",
    "sg:province":"GA",
    "sg:tags":[
        "kindergarten"
    ],
    "wof:name":"New Generation Pre School",
    "wof:placetype":"venue"
},
  "geometry": {"coordinates":[-83.975954,33.680106],"type":"Point"}
}