{
  "type": "Feature",
  "properties": {
    "iso:country":"US",
    "sg:address":"3855 Pleasant Hill Rd Ste 420",
    "sg:city":"Duluth",
    "sg:classifiers":[
        {
            "category":"Health Services",
            "subcategory":"Doctor",
            "type":"Services"
        }
    ],
    "sg:phone":"+1 770 495 1955",
    "sg:postcode":"30096",
    "sg:province":"GA",
    "wof:name":"Gadlage Robert A MD",
    "wof:placetype":"venue"
},
  "geometry": {"coordinates":[-84.16149900000001,34.000099],"type":"Point"}
}