{
  "type": "Feature",
  "properties": {
    "addr:full":"722 Pebble Creek Trl Norcross GA 30093",
    "addr:housenumber":"722",
    "addr:postcode":"30093",
    "addr:street":"Pebble Creek Trl",
    "iso:country":"US",
    "sg:address":"722 Pebble Creek Trl",
    "sg:city":"Norcross",
    "sg:classifiers":[
        {
            "category":"Personal",
            "subcategory":"Beauty Salon",
            "type":"Services"
        }
    ],
    "sg:phone":"+1 770 935 9733",
    "sg:postcode":"30093",
    "sg:province":"GA",
    "sg:tags":[
        "hair"
    ],
    "sg:website":"www.callahairdresser.com",
    "wof:name":"Call A Hairdresser",
    "wof:placetype":"venue"
},
  "geometry": {"coordinates":[-84.182525,33.88569],"type":"Point"}
}