{
  "type": "Feature",
  "properties": {
    "iso:country":"US",
    "sg:address":"815 Saint Marks Walk",
    "sg:city":"Suwanee",
    "sg:classifiers":[
        {
            "category":"Travel",
            "subcategory":"Hotels & Motels",
            "type":"Entertainment"
        },
        {
            "category":"Travel",
            "subcategory":"Bed & Breakfast",
            "type":"Entertainment"
        }
    ],
    "sg:phone":"+1 678 475 1478",
    "sg:postcode":"30024",
    "sg:province":"GA",
    "sg:tags":[
        "inn",
        "lodging"
    ],
    "wof:name":"Guest House",
    "wof:placetype":"venue"
},
  "geometry": {"coordinates":[-84.136036,34.058644],"type":"Point"}
}