{
  "type": "Feature",
  "properties": {
    "iso:country":"US",
    "sg:address":"4735 Roswell Rd",
    "sg:city":"Atlanta",
    "sg:classifiers":[
        {
            "category":"Real Estate",
            "subcategory":"Real Estate Operator",
            "type":"Services"
        }
    ],
    "sg:phone":"+1 404 252 4822",
    "sg:postcode":"30342",
    "sg:province":"GA",
    "sg:tags":[
        "apartment"
    ],
    "sg:website":"www.equityapartments.com",
    "wof:name":"Arboretum Apartments",
    "wof:placetype":"venue"
},
  "geometry": {"coordinates":[-84.380132,33.883307],"type":"Point"}
}