{
  "type": "Feature",
  "properties": {
    "iso:country":"US",
    "sg:address":"2266 Nottely Dam Rd",
    "sg:city":"Blairsville",
    "sg:classifiers":[
        {
            "category":"Autos & Motor Vehicles",
            "subcategory":"Automobile Sales",
            "type":"Retail Goods"
        }
    ],
    "sg:phone":"+1 706 745 7939",
    "sg:postcode":"30512",
    "sg:province":"GA",
    "sg:tags":[
        "used"
    ],
    "wof:name":"C JS Unlimited",
    "wof:placetype":"venue"
},
  "geometry": {"coordinates":[-84.092902,34.908349],"type":"Point"}
}