{
  "type": "Feature",
  "properties": {
    "addr:full":"2236 Riverbrook Ct Decatur GA 30035",
    "addr:housenumber":"2236",
    "addr:postcode":"30035",
    "addr:street":"Riverbrook Ct",
    "iso:country":"US",
    "sg:address":"2236 Riverbrook Ct",
    "sg:city":"Decatur",
    "sg:classifiers":[
        {
            "category":"Building & Trades",
            "subcategory":"Landscaping Services",
            "type":"Services"
        }
    ],
    "sg:phone":"+1 770 981 2670",
    "sg:postcode":"30035",
    "sg:province":"GA",
    "wof:name":"Dorothys Lawn Care Inc",
    "wof:placetype":"venue"
},
  "geometry": {"coordinates":[-84.212867,33.720025],"type":"Point"}
}