{
  "type": "Feature",
  "properties": {
    "addr:full":"990 Whitlock Ave NW Marietta GA 30064",
    "addr:housenumber":"990",
    "addr:postcode":"30064",
    "addr:street":"Whitlock Ave Nw",
    "iso:country":"US",
    "sg:address":"990 Whitlock Ave NW",
    "sg:city":"Marietta",
    "sg:classifiers":[
        {
            "category":"Health Services",
            "subcategory":"Dentist",
            "type":"Services"
        }
    ],
    "sg:phone":"+1 770 919 0800",
    "sg:postcode":"30064",
    "sg:province":"GA",
    "sg:tags":[
        "orthodontist"
    ],
    "wof:name":"Sylvester Carlo III DMD",
    "wof:placetype":"venue"
},
  "geometry": {"coordinates":[-84.57933300000001,33.952257],"type":"Point"}
}