{
  "type": "Feature",
  "properties": {
    "addr:full":"377 Chalfont Dr Athens GA 30606",
    "addr:housenumber":"377",
    "addr:postcode":"30606",
    "addr:street":"Chalfont Dr",
    "iso:country":"US",
    "sg:address":"377 Chalfont Dr",
    "sg:city":"Athens",
    "sg:classifiers":[
        {
            "category":"Professional",
            "subcategory":"Business Services",
            "type":"Services"
        }
    ],
    "sg:phone":"+1 706 316 3931",
    "sg:postcode":"30606",
    "sg:province":"GA",
    "wof:name":"Ajees Enterprises",
    "wof:placetype":"venue"
},
  "geometry": {"coordinates":[-83.438407,33.963526],"type":"Point"}
}