{
  "type": "Feature",
  "properties": {
    "iso:country":"US",
    "sg:address":"130 The Prado NE",
    "sg:city":"Atlanta",
    "sg:classifiers":[
        {
            "category":"Banks & Credit Unions",
            "subcategory":"Bank",
            "type":"Services"
        }
    ],
    "sg:phone":"+1 404 376 0334",
    "sg:postcode":"30309",
    "sg:province":"GA",
    "sg:tags":[
        "broker",
        "mortgage"
    ],
    "wof:name":"Choice Mortgage Group Inc",
    "wof:placetype":"venue"
},
  "geometry": {"coordinates":[-84.37858,33.792676],"type":"Point"}
}