{
  "type": "Feature",
  "properties": {
    "iso:country":"US",
    "sg:address":"5324 Highway 85",
    "sg:city":"Atlanta",
    "sg:classifiers":[
        {
            "category":"Manufacturing",
            "subcategory":"Tools & Machinery",
            "type":"Manufacturing & Wholesale Goods"
        }
    ],
    "sg:phone":"+1 404 762 8404",
    "sg:postcode":"30349",
    "sg:province":"GA",
    "sg:tags":[
        "fasteners-industrial"
    ],
    "wof:name":"Iwata Bolt USA Inc",
    "wof:placetype":"venue"
},
  "geometry": {"coordinates":[-84.40316900000001,33.60975],"type":"Point"}
}