{
  "type": "Feature",
  "properties": {
    "iso:country":"US",
    "sg:address":"3124 Tig Knight Rd",
    "sg:city":"Loganville",
    "sg:classifiers":[
        {
            "category":"Building & Trades",
            "subcategory":"Cleaning & Sanitation",
            "type":"Services"
        }
    ],
    "sg:phone":"+1 770 554 1777",
    "sg:postcode":"30052",
    "sg:province":"GA",
    "sg:tags":[
        "maintenance"
    ],
    "wof:name":"A & R Quality Cleaning Svcs",
    "wof:placetype":"venue"
},
  "geometry": {"coordinates":[-83.872585,33.813164],"type":"Point"}
}