{
  "type": "Feature",
  "properties": {
    "addr:full":"873 Mitchell St SW Atlanta GA 30314",
    "addr:housenumber":"873",
    "addr:postcode":"30314",
    "addr:street":"Mitchell St Sw",
    "iso:country":"US",
    "sg:address":"873 Mitchell St SW",
    "sg:city":"Atlanta",
    "sg:classifiers":[
        {
            "category":"Building & Trades",
            "subcategory":"Locksmith",
            "type":"Services"
        }
    ],
    "sg:phone":"+1 404 682 5291",
    "sg:postcode":"30314",
    "sg:province":"GA",
    "sg:tags":[
        "key"
    ],
    "wof:name":"A 1 2 3 24 Hour A Locksmith",
    "wof:placetype":"venue"
},
  "geometry": {"coordinates":[-84.41491000000001,33.753574],"type":"Point"}
}