{
  "type": "Feature",
  "properties": {
    "addr:full":"487 Hub Tatum Rd Clarkesville GA 30571",
    "addr:housenumber":"487",
    "addr:postcode":"30571",
    "addr:street":"Hub Tatum Rd",
    "iso:country":"US",
    "sg:address":"487 Hub Tatum Rd",
    "sg:city":"Clarkesville",
    "sg:classifiers":[
        {
            "category":"Organizations",
            "subcategory":"Religious Organization",
            "type":"Services"
        }
    ],
    "sg:phone":"+1 706 754 6621",
    "sg:postcode":"30571",
    "sg:province":"GA",
    "sg:tags":[
        "church"
    ],
    "wof:name":"Old Nacoochee Missionary Bapt",
    "wof:placetype":"venue"
},
  "geometry": {"coordinates":[-83.63215700000001,34.697174],"type":"Point"}
}