{
  "type": "Feature",
  "properties": {
    "addr:full":"113 Park 42 Dr Locust Grove GA 30248",
    "addr:housenumber":"113;42",
    "addr:postcode":"30248",
    "addr:street":"Park;Dr",
    "iso:country":"US",
    "sg:address":"113 Park 42 Dr",
    "sg:city":"Locust Grove",
    "sg:classifiers":[
        {
            "category":"Building & Trades",
            "subcategory":"Construction",
            "type":"Services"
        }
    ],
    "sg:phone":"+1 678 583 2180",
    "sg:postcode":"30248",
    "sg:province":"GA",
    "sg:tags":[
        "home",
        "improvement"
    ],
    "wof:name":"Peach State Siding Inc",
    "wof:placetype":"venue"
},
  "geometry": {"coordinates":[-84.12576300000001,33.375954],"type":"Point"}
}