{
  "type": "Feature",
  "properties": {
    "iso:country":"US",
    "sg:address":"115 3rd St W",
    "sg:city":"Tifton",
    "sg:classifiers":[
        {
            "category":"Shopping",
            "subcategory":"Books",
            "type":"Retail Goods"
        }
    ],
    "sg:phone":"+1 229 382 9105",
    "sg:postcode":"31794",
    "sg:province":"GA",
    "wof:name":"Book Haven",
    "wof:placetype":"venue"
},
  "geometry": {"coordinates":[-83.513018,31.451879],"type":"Point"}
}