{
  "type": "Feature",
  "properties": {
    "addr:full":"2996 Grandview Ave NE # 107 Atlanta GA 30305",
    "addr:housenumber":"2996",
    "addr:postcode":"30305",
    "addr:street":"Grandview Ave Ne # 107",
    "iso:country":"US",
    "sg:address":"2996 Grandview Ave NE # 107",
    "sg:city":"Atlanta",
    "sg:classifiers":[
        {
            "category":"Wholesale",
            "subcategory":"Medical Equipment & Supplies",
            "type":"Manufacturing & Wholesale Goods"
        },
        {
            "category":"Shopping",
            "subcategory":"Pets & Pet Supplies",
            "type":"Retail Goods"
        },
        {
            "category":"Retail",
            "subcategory":"Veterinary Services",
            "type":"Services"
        }
    ],
    "sg:phone":"+1 404 237 5200",
    "sg:postcode":"30305",
    "sg:province":"GA",
    "sg:tags":[
        "product",
        "supply-wholesale",
        "veterinarian",
        "animal",
        "health"
    ],
    "sg:website":"http://www.athcentral.com",
    "wof:name":"Bonaseptic Co",
    "wof:placetype":"venue"
},
  "geometry": {"coordinates":[-84.376328,33.836995],"type":"Point"}
}