{
  "type": "Feature",
  "properties": {
    "iso:country":"US",
    "sg:address":"605 Hunnicut Rd",
    "sg:city":"Mableton",
    "sg:classifiers":[
        {
            "category":"Professional",
            "subcategory":"Business Services",
            "type":"Services"
        }
    ],
    "sg:phone":"+1 404 644 6794",
    "sg:postcode":"30126",
    "sg:province":"GA",
    "wof:name":"A Little of This & That Inc",
    "wof:placetype":"venue"
},
  "geometry": {"coordinates":[-84.53772499999999,33.787006],"type":"Point"}
}