{
  "type": "Feature",
  "properties": {
    "addr:full":"2929 Turner Hill Rd Ste 2510 Lithonia GA 30038",
    "addr:housenumber":"2929",
    "addr:postcode":"30038",
    "addr:street":"Turner Hill Rd Ste 2510",
    "iso:country":"US",
    "sg:address":"2929 Turner Hill Rd Ste 2510",
    "sg:city":"Lithonia",
    "sg:classifiers":[
        {
            "category":"Restaurant",
            "type":"Food & Drink"
        },
        {
            "category":"Ice Cream",
            "type":"Food & Drink"
        }
    ],
    "sg:phone":"+1 770 484 5866",
    "sg:postcode":"30038",
    "sg:province":"GA",
    "sg:tags":[
        "frozen",
        "dessert"
    ],
    "wof:name":"Tcby",
    "wof:placetype":"venue"
},
  "geometry": {"coordinates":[-84.088809,33.698082],"type":"Point"}
}