{
  "type": "Feature",
  "properties": {
    "addr:full":"314 N Glenwood Ave Dalton GA 30721",
    "addr:housenumber":"314",
    "addr:postcode":"30721",
    "addr:street":"N Glenwood Ave",
    "iso:country":"US",
    "sg:address":"314 N Glenwood Ave",
    "sg:city":"Dalton",
    "sg:classifiers":[
        {
            "category":"Shopping",
            "subcategory":"Used Merchandise",
            "type":"Retail Goods"
        }
    ],
    "sg:phone":"+1 706 272 3255",
    "sg:postcode":"30721",
    "sg:province":"GA",
    "wof:name":"Discount Title Pawn Of Dalton",
    "wof:placetype":"venue"
},
  "geometry": {"coordinates":[-84.965456,34.775946],"type":"Point"}
}