{
  "type": "Feature",
  "properties": {
    "addr:full":"4771 Britt Rd Norcross GA 30093",
    "addr:housenumber":"4771",
    "addr:postcode":"30093",
    "addr:street":"Britt Rd",
    "iso:country":"US",
    "sg:address":"4771 Britt Rd",
    "sg:city":"Norcross",
    "sg:classifiers":[
        {
            "category":"Shopping",
            "subcategory":"Bicycles & Sporting Goods",
            "type":"Retail Goods"
        }
    ],
    "sg:phone":"+1 770 771 7148",
    "sg:postcode":"30093",
    "sg:province":"GA",
    "wof:name":"Stop Sport One",
    "wof:placetype":"venue"
},
  "geometry": {"coordinates":[-84.194171,33.88362],"type":"Point"}
}