{
  "type": "Feature",
  "properties": {
    "addr:full":"3508 Park Lake Ln Norcross GA 30092",
    "addr:housenumber":"3508",
    "addr:postcode":"30092",
    "addr:street":"Park Lake Ln",
    "iso:country":"US",
    "sg:address":"3508 Park Lake Ln",
    "sg:city":"Norcross",
    "sg:classifiers":[
        {
            "category":"Wholesale",
            "subcategory":"Books, Periodicals, & Newspapers",
            "type":"Manufacturing & Wholesale Goods"
        }
    ],
    "sg:phone":"+1 770 676 0626",
    "sg:postcode":"30092",
    "sg:province":"GA",
    "sg:tags":[
        "publisher",
        "book"
    ],
    "wof:name":"3g Publishing Incorporated",
    "wof:placetype":"venue"
},
  "geometry": {"coordinates":[-84.25060499999999,33.961984],"type":"Point"}
}