{
  "type": "Feature",
  "properties": {
    "addr:full":"1850 Whispering Willow Way SW Lilburn GA 30047",
    "addr:housenumber":"1850",
    "addr:postcode":"30047",
    "addr:street":"Whispering Willow Way Sw",
    "iso:country":"US",
    "sg:address":"1850 Whispering Willow Way SW",
    "sg:city":"Lilburn",
    "sg:classifiers":[
        {
            "category":"Professional",
            "subcategory":"Management & Consulting",
            "type":"Services"
        }
    ],
    "sg:phone":"+1 770 736 1807",
    "sg:postcode":"30047",
    "sg:province":"GA",
    "sg:tags":[
        "business"
    ],
    "wof:name":"Engineering Department",
    "wof:placetype":"venue"
},
  "geometry": {"coordinates":[-84.070712,33.84904],"type":"Point"}
}