{
  "type": "Feature",
  "properties": {
    "addr:full":"2818 Middleham Ct Tucker GA 30084",
    "addr:housenumber":"2818",
    "addr:postcode":"30084",
    "addr:street":"Middleham Ct",
    "iso:country":"US",
    "sg:address":"2818 Middleham Ct",
    "sg:city":"Tucker",
    "sg:classifiers":[
        {
            "category":"Building & Trades",
            "subcategory":"Construction",
            "type":"Services"
        }
    ],
    "sg:phone":"+1 770 939 4888",
    "sg:postcode":"30084",
    "sg:province":"GA",
    "sg:tags":[
        "contractor"
    ],
    "wof:name":"Summit Developement & Construc",
    "wof:placetype":"venue"
},
  "geometry": {"coordinates":[-84.20933599999999,33.869784],"type":"Point"}
}