{
  "type": "Feature",
  "properties": {
    "addr:full":"3910 Lawrenceville Hwy Tucker GA 30084",
    "addr:housenumber":"3910",
    "addr:postcode":"30084",
    "addr:street":"Lawrenceville Hwy",
    "iso:country":"US",
    "sg:address":"3910 Lawrenceville Hwy",
    "sg:city":"Tucker",
    "sg:classifiers":[
        {
            "category":"Autos & Motor Vehicles",
            "subcategory":"Automobile Sales",
            "type":"Retail Goods"
        },
        {
            "category":"Wholesale",
            "subcategory":"Motor Vehicles",
            "type":"Manufacturing & Wholesale Goods"
        }
    ],
    "sg:phone":"+1 770 414 1158",
    "sg:postcode":"30084",
    "sg:province":"GA",
    "sg:tags":[
        "car",
        "dealer"
    ],
    "wof:name":"Salek Motors USA",
    "wof:placetype":"venue"
},
  "geometry": {"coordinates":[-84.222476,33.849776],"type":"Point"}
}