{
  "type": "Feature",
  "properties": {
    "addr:full":"1 Windwalk Ln Savannah GA 31411",
    "addr:housenumber":"1",
    "addr:postcode":"31411",
    "addr:street":"Windwalk Ln",
    "iso:country":"US",
    "sg:address":"1 Windwalk Ln",
    "sg:city":"Savannah",
    "sg:classifiers":[
        {
            "category":"Professional",
            "subcategory":"Computer Services",
            "type":"Services"
        }
    ],
    "sg:phone":"+1 912 598 1768",
    "sg:postcode":"31411",
    "sg:province":"GA",
    "sg:tags":[
        "related"
    ],
    "wof:name":"Skidaway Consulting Inc",
    "wof:placetype":"venue"
},
  "geometry": {"coordinates":[-81.038054,31.919324],"type":"Point"}
}