{
  "type": "Feature",
  "properties": {
    "addr:full":"7953 Villa Rica Hwy Dallas GA 30157",
    "addr:housenumber":"7953",
    "addr:postcode":"30157",
    "addr:street":"Villa Rica Hwy",
    "iso:country":"US",
    "sg:address":"7953 Villa Rica Hwy",
    "sg:city":"Dallas",
    "sg:classifiers":[
        {
            "category":"Deli",
            "type":"Food & Drink"
        },
        {
            "category":"Food & Beverages",
            "subcategory":"Supermarket",
            "type":"Retail Goods"
        },
        {
            "category":"Shopping",
            "subcategory":"Pharmacy",
            "type":"Retail Goods"
        },
        {
            "category":"Food & Beverages",
            "subcategory":"Groceries & Convenience Stores",
            "type":"Retail Goods"
        }
    ],
    "sg:phone":"+1 678 840 4676",
    "sg:postcode":"30157",
    "sg:province":"GA",
    "sg:tags":[
        "delicatessen",
        "super"
    ],
    "sg:website":"http://storedetail.publix.com/USA/GA/7953-Villa-Rica-Hwy.html",
    "wof:name":"Publix Super Market",
    "wof:placetype":"venue"
},
  "geometry": {"coordinates":[-84.88852199999999,33.810205],"type":"Point"}
}