{
  "type": "Feature",
  "properties": {
    "addr:full":"1454 Chattahoochee Ave NW Atlanta GA 30318",
    "addr:housenumber":"1454",
    "addr:postcode":"30318",
    "addr:street":"Chattahoochee Ave Nw",
    "iso:country":"US",
    "sg:address":"1454 Chattahoochee Ave NW",
    "sg:city":"Atlanta",
    "sg:classifiers":[
        {
            "category":"Home & Garden",
            "subcategory":"Furniture",
            "type":"Retail Goods"
        }
    ],
    "sg:phone":"+1 404 352 0546",
    "sg:postcode":"30318",
    "sg:province":"GA",
    "sg:tags":[
        "store"
    ],
    "wof:name":"P V I",
    "wof:placetype":"venue"
},
  "geometry": {"coordinates":[-84.434387,33.8064],"type":"Point"}
}