{
  "type": "Feature",
  "properties": {
    "addr:full":"2285 Browns Bridge Rd Gainesville GA 30501",
    "addr:housenumber":"2285",
    "addr:postcode":"30501",
    "addr:street":"Browns Bridge Rd",
    "iso:country":"US",
    "sg:address":"2285 Browns Bridge Rd",
    "sg:city":"Gainesville",
    "sg:classifiers":[
        {
            "category":"Shopping",
            "subcategory":"Books",
            "type":"Retail Goods"
        }
    ],
    "sg:phone":"+1 770 532 9164",
    "sg:postcode":"30501",
    "sg:province":"GA",
    "sg:tags":[
        "cards",
        "music",
        "gift"
    ],
    "wof:name":"Family Christian Stores 250",
    "wof:placetype":"venue"
},
  "geometry": {"coordinates":[-83.85302900000001,34.280083],"type":"Point"}
}