{
  "type": "Feature",
  "properties": {
    "iso:country":"US",
    "sg:address":"2110 Austell Rd SW",
    "sg:city":"Marietta",
    "sg:classifiers":[
        {
            "category":"Building & Trades",
            "subcategory":"Construction",
            "type":"Services"
        }
    ],
    "sg:phone":"+1 770 384 0196",
    "sg:postcode":"30008",
    "sg:province":"GA",
    "sg:tags":[
        "general",
        "contractor"
    ],
    "wof:name":"Frs Contracting",
    "wof:placetype":"venue"
},
  "geometry": {"coordinates":[-84.56674,33.903578],"type":"Point"}
}