{
  "type": "Feature",
  "properties": {
    "iso:country":"US",
    "sg:address":"300 Smith Dr",
    "sg:city":"Perry",
    "sg:classifiers":[
        {
            "category":"Retail",
            "subcategory":"Auto Repair",
            "type":"Services"
        }
    ],
    "sg:phone":"+1 478 988 8686",
    "sg:postcode":"31069",
    "sg:province":"GA",
    "sg:tags":[
        "repairing",
        "automobile"
    ],
    "wof:name":"Professional Automotive Svc",
    "wof:placetype":"venue"
},
  "geometry": {"coordinates":[-83.741726,32.465869],"type":"Point"}
}