{
  "type": "Feature",
  "properties": {
    "addr:full":"8160 S Main St Helen GA 30545",
    "addr:housenumber":"8160",
    "addr:postcode":"30545",
    "addr:street":"S Main St",
    "iso:country":"US",
    "sg:address":"8160 S Main St",
    "sg:city":"Helen",
    "sg:classifiers":[
        {
            "category":"Personal",
            "subcategory":"Beauty Salon",
            "type":"Services"
        }
    ],
    "sg:phone":"+1 706 878 5585",
    "sg:postcode":"30545",
    "sg:province":"GA",
    "sg:tags":[
        "manicuring"
    ],
    "wof:name":"Best Nails Image",
    "wof:placetype":"venue"
},
  "geometry": {"coordinates":[-83.721183,34.698521],"type":"Point"}
}