{
  "type": "Feature",
  "properties": {
    "iso:country":"US",
    "sg:address":"303 Henry St",
    "sg:city":"Marietta",
    "sg:classifiers":[
        {
            "category":"Banks & Credit Unions",
            "subcategory":"Investment Brokerage",
            "type":"Services"
        }
    ],
    "sg:phone":"+1 770 420 6942",
    "sg:postcode":"30060",
    "sg:province":"GA",
    "sg:tags":[
        "advisory"
    ],
    "wof:name":"Investment Solututions",
    "wof:placetype":"venue"
},
  "geometry": {"coordinates":[-84.54297099999999,33.931782],"type":"Point"}
}