{
  "type": "Feature",
  "properties": {
    "addr:full":"506 New Franklin Rd La Grange GA 30240",
    "addr:housenumber":"506",
    "addr:postcode":"30240",
    "addr:street":"New Franklin Rd",
    "iso:country":"US",
    "sg:address":"506 New Franklin Rd",
    "sg:city":"La Grange",
    "sg:classifiers":[
        {
            "category":"Retail",
            "subcategory":"Auto Rental",
            "type":"Services"
        }
    ],
    "sg:phone":"+1 706 884 0200",
    "sg:postcode":"30240",
    "sg:province":"GA",
    "sg:tags":[
        "car"
    ],
    "wof:name":"Thrifty Car Rental",
    "wof:placetype":"venue"
},
  "geometry": {"coordinates":[-85.028477,33.063334],"type":"Point"}
}