{
  "type": "Feature",
  "properties": {
    "addr:full":"5964 Covington Hwy Decatur GA 30035",
    "addr:housenumber":"5964",
    "addr:postcode":"30035",
    "addr:street":"Covington Hwy",
    "iso:country":"US",
    "sg:address":"5964 Covington Hwy",
    "sg:city":"Decatur",
    "sg:classifiers":[
        {
            "category":"Organizations",
            "subcategory":"Religious Organization",
            "type":"Services"
        }
    ],
    "sg:phone":"+1 770 593 2205",
    "sg:postcode":"30035",
    "sg:province":"GA",
    "wof:name":"Liberty Hall House Of God",
    "wof:placetype":"venue"
},
  "geometry": {"coordinates":[-84.17460800000001,33.724224],"type":"Point"}
}