{
  "type": "Feature",
  "properties": {
    "iso:country":"US",
    "sg:address":"2338 Lawrenceville Hwy",
    "sg:city":"Decatur",
    "sg:classifiers":[
        {
            "category":"Social Services",
            "subcategory":"Child Care",
            "type":"Services"
        }
    ],
    "sg:phone":"+1 404 315 4877",
    "sg:postcode":"30033",
    "sg:province":"GA",
    "sg:tags":[
        "day"
    ],
    "wof:name":"Kaylor Fam Daycare",
    "wof:placetype":"venue"
},
  "geometry": {"coordinates":[-84.26808699999999,33.816791],"type":"Point"}
}