{
  "type": "Feature",
  "properties": {
    "iso:country":"US",
    "sg:address":"229 E Dykes St",
    "sg:city":"Cochran",
    "sg:classifiers":[
        {
            "category":"Autos & Motor Vehicles",
            "subcategory":"Auto Supplies",
            "type":"Retail Goods"
        },
        {
            "category":"Retail",
            "subcategory":"Car Wash",
            "type":"Services"
        }
    ],
    "sg:phone":"+1 478 934 7999",
    "sg:postcode":"31014",
    "sg:province":"GA",
    "sg:tags":[
        "lube",
        "oil"
    ],
    "wof:name":"Quick & Easy Lube & Wash",
    "wof:placetype":"venue"
},
  "geometry": {"coordinates":[-83.34657,32.393529],"type":"Point"}
}