{
  "type": "Feature",
  "properties": {
    "addr:full":"4954 Highpoint Way Marietta GA 30066",
    "addr:housenumber":"4954",
    "addr:postcode":"30066",
    "addr:street":"Highpoint Way",
    "iso:country":"US",
    "sg:address":"4954 Highpoint Way",
    "sg:city":"Marietta",
    "sg:classifiers":[
        {
            "category":"Retail",
            "subcategory":"Repair Shop",
            "type":"Services"
        }
    ],
    "sg:phone":"+1 770 926 9179",
    "sg:postcode":"30066",
    "sg:province":"GA",
    "sg:tags":[
        "refrigerator",
        "freezer"
    ],
    "sg:website":"www.apaylessappliancerepair.com",
    "wof:name":"A Payless Svc Today",
    "wof:placetype":"venue"
},
  "geometry": {"coordinates":[-84.489193,34.070934],"type":"Point"}
}