{
  "type": "Feature",
  "properties": {
    "iso:country":"US",
    "sg:address":"1914 Central Ave",
    "sg:city":"Augusta",
    "sg:classifiers":[
        {
            "category":"Health Services",
            "subcategory":"Doctor",
            "type":"Services"
        }
    ],
    "sg:phone":"+1 706 733 2201",
    "sg:postcode":"30904",
    "sg:province":"GA",
    "sg:tags":[
        "medical"
    ],
    "wof:name":"Central Ave Chrprctic Clnic PC",
    "wof:placetype":"venue"
},
  "geometry": {"coordinates":[-82.00715599999999,33.468549],"type":"Point"}
}