{
  "type": "Feature",
  "properties": {
    "iso:country":"US",
    "sg:address":"990 Hammond Dr NE",
    "sg:city":"Atlanta",
    "sg:classifiers":[
        {
            "category":"Professional",
            "subcategory":"Business Services",
            "type":"Services"
        },
        {
            "category":"Banks & Credit Unions",
            "subcategory":"Bank",
            "type":"Services"
        }
    ],
    "sg:phone":"+1 770 395 7559",
    "sg:postcode":"30328",
    "sg:province":"GA",
    "sg:tags":[
        "financing"
    ],
    "wof:name":"Revanta Financial Group LLC",
    "wof:placetype":"venue"
},
  "geometry": {"coordinates":[-84.357131,33.919002],"type":"Point"}
}