{
  "type": "Feature",
  "properties": {
    "addr:full":"2487 Rocky Creek Rd Macon GA 31206",
    "addr:housenumber":"2487",
    "addr:postcode":"31206",
    "addr:street":"Rocky Creek Rd",
    "iso:country":"US",
    "sg:address":"2487 Rocky Creek Rd",
    "sg:city":"Macon",
    "sg:classifiers":[
        {
            "category":"Food & Beverages",
            "subcategory":"Groceries & Convenience Stores",
            "type":"Retail Goods"
        }
    ],
    "sg:phone":"+1 478 788 2717",
    "sg:postcode":"31206",
    "sg:province":"GA",
    "sg:tags":[
        "discount"
    ],
    "wof:name":"Melody's Magic Mart",
    "wof:placetype":"venue"
},
  "geometry": {"coordinates":[-83.702347,32.786579],"type":"Point"}
}