{
  "type": "Feature",
  "properties": {
    "addr:full":"77 Collier Rd NW Ste 2080 Atlanta GA 30309",
    "addr:housenumber":"77",
    "addr:postcode":"30309",
    "addr:street":"Collier Rd Nw Ste 2080",
    "iso:country":"US",
    "sg:address":"77 Collier Rd NW Ste 2080",
    "sg:city":"Atlanta",
    "sg:classifiers":[
        {
            "category":"Health Services",
            "subcategory":"Doctor",
            "type":"Services"
        }
    ],
    "sg:phone":"+1 404 355 4393",
    "sg:postcode":"30309",
    "sg:province":"GA",
    "wof:name":"Robertson David G MD",
    "wof:placetype":"venue"
},
  "geometry": {"coordinates":[-84.396103,33.8078],"type":"Point"}
}