{
  "type": "Feature",
  "properties": {
    "addr:full":"630 Mountain Rd Woodstock GA 30188",
    "addr:housenumber":"630",
    "addr:postcode":"30188",
    "addr:street":"Mountain Rd",
    "iso:country":"US",
    "sg:address":"630 Mountain Rd",
    "sg:city":"Woodstock",
    "sg:classifiers":[
        {
            "category":"Home & Garden",
            "subcategory":"Furniture",
            "type":"Retail Goods"
        }
    ],
    "sg:phone":"+1 770 442 3199",
    "sg:postcode":"30188",
    "sg:province":"GA",
    "wof:name":"Keheley & Son Cabinets Inc",
    "wof:placetype":"venue"
},
  "geometry": {"coordinates":[-84.40606,34.137234],"type":"Point"}
}