{
  "type": "Feature",
  "properties": {
    "addr:full":"1366 Gray Hwy Macon GA 31211",
    "addr:housenumber":"1366",
    "addr:postcode":"31211",
    "addr:street":"Gray Hwy",
    "iso:country":"US",
    "sg:address":"1366 Gray Hwy",
    "sg:city":"Macon",
    "sg:classifiers":[
        {
            "category":"Autos & Motor Vehicles",
            "subcategory":"Auto Supplies",
            "type":"Retail Goods"
        }
    ],
    "sg:phone":"+1 478 788 4551",
    "sg:postcode":"31211",
    "sg:province":"GA",
    "sg:tags":[
        "tire"
    ],
    "wof:name":"Pro Tire & Fleet Svc",
    "wof:placetype":"venue"
},
  "geometry": {"coordinates":[-83.61372900000001,32.861629],"type":"Point"}
}