{
  "type": "Feature",
  "properties": {
    "iso:country":"US",
    "sg:address":"630 Hillcrest Rd NW",
    "sg:city":"Lilburn",
    "sg:classifiers":[
        {
            "category":"Personal",
            "subcategory":"Beauty Salon",
            "type":"Services"
        }
    ],
    "sg:phone":"+1 770 923 2249",
    "sg:postcode":"30047",
    "sg:province":"GA",
    "wof:name":"Da Rie's Hair Gallery",
    "wof:placetype":"venue"
},
  "geometry": {"coordinates":[-84.14787200000001,33.898689],"type":"Point"}
}