{
  "type": "Feature",
  "properties": {
    "iso:country":"US",
    "sg:address":"3108 Wisteria Ct",
    "sg:city":"Albany",
    "sg:classifiers":[
        {
            "category":"Professional",
            "type":"Services"
        }
    ],
    "sg:phone":"+1 229 436 5291",
    "sg:postcode":"31721",
    "sg:province":"GA",
    "wof:name":"Georgia Society For Hospi",
    "wof:placetype":"venue"
},
  "geometry": {"coordinates":[-84.225774,31.597792],"type":"Point"}
}