{
  "type": "Feature",
  "properties": {
    "iso:country":"US",
    "sg:address":"1155 Hammond Dr NE",
    "sg:city":"Atlanta",
    "sg:classifiers":[
        {
            "category":"Organizations",
            "subcategory":"Membership Organization",
            "type":"Services"
        }
    ],
    "sg:phone":"+1 678 441 9600",
    "sg:postcode":"30328",
    "sg:province":"GA",
    "sg:website":"www.visitingphysicians.com",
    "wof:name":"Visiting Physicians Assn",
    "wof:placetype":"venue"
},
  "geometry": {"coordinates":[-84.350503,33.918891],"type":"Point"}
}