{
  "type": "Feature",
  "properties": {
    "iso:country":"US",
    "sg:address":"3600 Dallas Hwy",
    "sg:city":"Marietta",
    "sg:classifiers":[
        {
            "category":"Building & Trades",
            "subcategory":"Construction",
            "type":"Services"
        }
    ],
    "sg:phone":"+1 770 652 5552",
    "sg:postcode":"30064",
    "sg:province":"GA",
    "sg:tags":[
        "housing",
        "apartment",
        "family"
    ],
    "wof:name":"Taylors Ridge LLC",
    "wof:placetype":"venue"
},
  "geometry": {"coordinates":[-84.657061,33.953798],"type":"Point"}
}