{
  "type": "Feature",
  "properties": {
    "addr:full":"2295 Hamptons Xing Alpharetta GA 30005",
    "addr:housenumber":"2295",
    "addr:postcode":"30005",
    "addr:street":"Hamptons Xing",
    "iso:country":"US",
    "sg:address":"2295 Hamptons Xing",
    "sg:city":"Alpharetta",
    "sg:classifiers":[
        {
            "category":"Professional",
            "type":"Services"
        }
    ],
    "sg:phone":"+1 770 569 1440",
    "sg:postcode":"30005",
    "sg:province":"GA",
    "wof:name":"Future Tech Designs",
    "wof:placetype":"venue"
},
  "geometry": {"coordinates":[-84.20868,34.089338],"type":"Point"}
}