{
  "type": "Feature",
  "properties": {
    "iso:country":"US",
    "sg:address":"2380 Mitchell Rd",
    "sg:city":"Marietta",
    "sg:classifiers":[
        {
            "category":"Travel",
            "subcategory":"Travel Agent",
            "type":"Entertainment"
        }
    ],
    "sg:phone":"+1 770 973 2333",
    "sg:postcode":"30062",
    "sg:province":"GA",
    "sg:tags":[
        "tours",
        "promoter"
    ],
    "wof:name":"Burfield & Goolsby LTD",
    "wof:placetype":"venue"
},
  "geometry": {"coordinates":[-84.452074,34.007876],"type":"Point"}
}