{
  "type": "Feature",
  "properties": {
    "iso:country":"US",
    "sg:address":"3519 Maryvale Dr",
    "sg:city":"Decatur",
    "sg:classifiers":[
        {
            "category":"Building & Trades",
            "subcategory":"Landscaping Services",
            "type":"Services"
        }
    ],
    "sg:phone":"+1 404 288 6841",
    "sg:postcode":"30032",
    "sg:province":"GA",
    "sg:tags":[
        "lawn",
        "maintenance",
        "grounds"
    ],
    "wof:name":"E & G Lawn Svc & Cleaning",
    "wof:placetype":"venue"
},
  "geometry": {"coordinates":[-84.245873,33.752117],"type":"Point"}
}