{
  "type": "Feature",
  "properties": {
    "addr:full":"4052 Dunwoody Park N Atlanta GA 30338",
    "addr:housenumber":"4052",
    "addr:postcode":"30338",
    "addr:street":"Dunwoody Park N",
    "iso:country":"US",
    "sg:address":"4052 Dunwoody Park N",
    "sg:city":"Atlanta",
    "sg:classifiers":[
        {
            "category":"Manufacturing",
            "subcategory":"Tools & Machinery",
            "type":"Manufacturing & Wholesale Goods"
        }
    ],
    "sg:phone":"+1 770 390 9950",
    "sg:postcode":"30338",
    "sg:province":"GA",
    "sg:tags":[
        "manufacture",
        "water",
        "monitor",
        "ground"
    ],
    "wof:name":"Dmls",
    "wof:placetype":"venue"
},
  "geometry": {"coordinates":[-84.31399999999999,33.925537],"type":"Point"}
}