{
  "type": "Feature",
  "properties": {
    "addr:full":"2910 N Ashley St Valdosta GA 31602",
    "addr:housenumber":"2910",
    "addr:postcode":"31602",
    "addr:street":"N Ashley St",
    "iso:country":"US",
    "sg:address":"2910 N Ashley St",
    "sg:city":"Valdosta",
    "sg:classifiers":[
        {
            "category":"Restaurant",
            "type":"Food & Drink"
        }
    ],
    "sg:phone":"+1 229 247 7800",
    "sg:postcode":"31602",
    "sg:province":"GA",
    "sg:tags":[
        "eating"
    ],
    "wof:name":"Little Caesars",
    "wof:placetype":"venue"
},
  "geometry": {"coordinates":[-83.289737,30.87216],"type":"Point"}
}