{
  "type": "Feature",
  "properties": {
    "iso:country":"US",
    "sg:address":"3455 N Desert Drive",
    "sg:city":"Atlanta",
    "sg:classifiers":[
        {
            "category":"Shopping",
            "subcategory":"Stationery & Office Supplies",
            "type":"Retail Goods"
        }
    ],
    "sg:phone":"+1 404 684 0800",
    "sg:postcode":"30344",
    "sg:province":"GA",
    "sg:tags":[
        "equipment"
    ],
    "wof:name":"Contract Business Interiors",
    "wof:placetype":"venue"
},
  "geometry": {"coordinates":[-84.495296,33.662106],"type":"Point"}
}