{
  "type": "Feature",
  "properties": {
    "iso:country":"US",
    "sg:address":"3242 Connemara Trce",
    "sg:city":"Lawrenceville",
    "sg:classifiers":[
        {
            "category":"Professional",
            "subcategory":"Business Services",
            "type":"Services"
        }
    ],
    "sg:phone":"+1 678 380 0280",
    "sg:postcode":"30044",
    "sg:province":"GA",
    "sg:tags":[
        "embroidery"
    ],
    "wof:name":"Initial Offerings Embroidery",
    "wof:placetype":"venue"
},
  "geometry": {"coordinates":[-84.079836,33.897994],"type":"Point"}
}