{
  "type": "Feature",
  "properties": {
    "addr:full":"900 S Thornton Ave Dalton GA 30720",
    "addr:housenumber":"900",
    "addr:postcode":"30720",
    "addr:street":"S Thornton Ave",
    "iso:country":"US",
    "sg:address":"900 S Thornton Ave",
    "sg:city":"Dalton",
    "sg:classifiers":[
        {
            "category":"Restaurant",
            "type":"Food & Drink"
        }
    ],
    "sg:menulink":"http://www.allmenus.com/ga/dalton/154413-hardees/menu/",
    "sg:phone":"+1 706 226 4914",
    "sg:postcode":"30720",
    "sg:province":"GA",
    "sg:tags":[
        "burger",
        "american"
    ],
    "wof:name":"Hardee's",
    "wof:placetype":"venue"
},
  "geometry": {"coordinates":[-84.97034600000001,34.759683],"type":"Point"}
}