{
  "type": "Feature",
  "properties": {
    "iso:country":"US",
    "sg:address":"1101 Mount Zion Rd NE",
    "sg:city":"Dalton",
    "sg:classifiers":[
        {
            "category":"Retail",
            "subcategory":"Auto Repair",
            "type":"Services"
        }
    ],
    "sg:phone":"+1 706 278 7382",
    "sg:postcode":"30721",
    "sg:province":"GA",
    "sg:tags":[
        "body",
        "automobile",
        "painting"
    ],
    "wof:name":"Janow's Custom Rods",
    "wof:placetype":"venue"
},
  "geometry": {"coordinates":[-84.893745,34.824419],"type":"Point"}
}