{
  "type": "Feature",
  "properties": {
    "iso:country":"US",
    "sg:address":"419 E Crossville Rd Ste 204",
    "sg:city":"Roswell",
    "sg:classifiers":[
        {
            "category":"Real Estate",
            "subcategory":"Real Estate Services",
            "type":"Services"
        },
        {
            "category":"Real Estate",
            "subcategory":"Developer",
            "type":"Services"
        },
        {
            "category":"Industrial Area",
            "type":"Public Place"
        }
    ],
    "sg:phone":"+1 770 649 7000",
    "sg:postcode":"30075",
    "sg:province":"GA",
    "sg:tags":[
        "investing",
        "development",
        "commercial"
    ],
    "wof:name":"Resource Capital Group",
    "wof:placetype":"venue"
},
  "geometry": {"coordinates":[-84.349553,34.039226],"type":"Point"}
}