{
  "type": "Feature",
  "properties": {
    "iso:country":"US",
    "sg:address":"167 Shadowood Dr",
    "sg:city":"Cleveland",
    "sg:classifiers":[
        {
            "category":"Professional",
            "subcategory":"Employment Agencies",
            "type":"Services"
        }
    ],
    "sg:phone":"+1 706 219 2911",
    "sg:postcode":"30528",
    "sg:province":"GA",
    "sg:tags":[
        "help",
        "supply"
    ],
    "wof:name":"Promed Transcribers Inc",
    "wof:placetype":"venue"
},
  "geometry": {"coordinates":[-83.789531,34.597518],"type":"Point"}
}