{
  "type": "Feature",
  "properties": {
    "iso:country":"US",
    "sg:address":"793 Lake Laurie Dr",
    "sg:city":"Valdosta",
    "sg:classifiers":[
        {
            "category":"Freight",
            "type":"Transportation"
        }
    ],
    "sg:phone":"+1 229 333 0553",
    "sg:postcode":"31605",
    "sg:province":"GA",
    "sg:tags":[
        "warehouse",
        "self",
        "storage"
    ],
    "wof:name":"Advanced Lifts & Wrhse Design",
    "wof:placetype":"venue"
},
  "geometry": {"coordinates":[-83.30526999999999,30.895775],"type":"Point"}
}