{
  "type": "Feature",
  "properties": {
    "iso:country":"US",
    "sg:address":"328 Mell Ave NE Ste A",
    "sg:city":"Atlanta",
    "sg:classifiers":[
        {
            "category":"Building & Trades",
            "subcategory":"Electrical",
            "type":"Services"
        }
    ],
    "sg:phone":"+1 404 577 4191",
    "sg:postcode":"30307",
    "sg:province":"GA",
    "sg:tags":[
        "electrician"
    ],
    "sg:website":"www.patmurphyelectric.com",
    "wof:name":"Murphy Pat Electric",
    "wof:placetype":"venue"
},
  "geometry": {"coordinates":[-84.337475,33.763153],"type":"Point"}
}