{
  "type": "Feature",
  "properties": {
    "addr:full":"135 Habersham Dr Fayetteville GA 30214",
    "addr:housenumber":"135",
    "addr:postcode":"30214",
    "addr:street":"Habersham Dr",
    "iso:country":"US",
    "sg:address":"135 Habersham Dr",
    "sg:city":"Fayetteville",
    "sg:classifiers":[
        {
            "category":"Real Estate",
            "subcategory":"Real Estate Services",
            "type":"Services"
        }
    ],
    "sg:phone":"+1 770 461 4315",
    "sg:postcode":"30214",
    "sg:province":"GA",
    "wof:name":"Harbin Maurice Jr Rl Est",
    "wof:placetype":"venue"
},
  "geometry": {"coordinates":[-84.45410200000001,33.4585],"type":"Point"}
}