{
  "type": "Feature",
  "properties": {
    "iso:country":"US",
    "sg:address":"6630 McGinnis Ferry Rd",
    "sg:city":"Duluth",
    "sg:classifiers":[
        {
            "category":"Health Services",
            "subcategory":"Doctor",
            "type":"Services"
        }
    ],
    "sg:phone":"+1 404 297 6130",
    "sg:postcode":"30097",
    "sg:province":"GA",
    "wof:name":"Malaika M Witter Hewitt MD",
    "wof:placetype":"venue"
},
  "geometry": {"coordinates":[-84.18342800000001,34.078122],"type":"Point"}
}