{
  "type": "Feature",
  "properties": {
    "addr:full":"1057 Vijay Dr Atlanta GA 30341",
    "addr:housenumber":"1057",
    "addr:postcode":"30341",
    "addr:street":"Vijay Dr",
    "iso:country":"US",
    "sg:address":"1057 Vijay Dr",
    "sg:city":"Atlanta",
    "sg:classifiers":[
        {
            "category":"Wholesale",
            "subcategory":"Machinery & Supplies",
            "type":"Manufacturing & Wholesale Goods"
        }
    ],
    "sg:phone":"+1 770 458 4882",
    "sg:postcode":"30341",
    "sg:province":"GA",
    "sg:tags":[
        "equipment",
        "industrial"
    ],
    "wof:name":"Cangen Holdings LLC",
    "wof:placetype":"venue"
},
  "geometry": {"coordinates":[-84.313441,33.882478],"type":"Point"}
}