{
  "type": "Feature",
  "properties": {
    "iso:country":"US",
    "sg:address":"41 Maple St",
    "sg:city":"Hartwell",
    "sg:classifiers":[
        {
            "category":"Personal",
            "subcategory":"Beauty Salon",
            "type":"Services"
        },
        {
            "category":"Personal",
            "subcategory":"Barber",
            "type":"Services"
        }
    ],
    "sg:phone":"+1 706 376 3852",
    "sg:postcode":"30643",
    "sg:province":"GA",
    "wof:name":"Cut Curl & Dye Ltd",
    "wof:placetype":"venue"
},
  "geometry": {"coordinates":[-82.92433200000001,34.353243],"type":"Point"}
}