{
  "type": "Feature",
  "properties": {
    "iso:country":"US",
    "sg:address":"6949 S Sweetwater Rd",
    "sg:city":"Lithia Springs",
    "sg:classifiers":[
        {
            "category":"Building & Trades",
            "subcategory":"Construction",
            "type":"Services"
        },
        {
            "category":"Building & Trades",
            "subcategory":"Plumbing",
            "type":"Services"
        }
    ],
    "sg:phone":"+1 770 944 7455",
    "sg:postcode":"30122",
    "sg:province":"GA",
    "sg:tags":[
        "plumbing",
        "contractor"
    ],
    "wof:name":"Underground Plumbing Service",
    "wof:placetype":"venue"
},
  "geometry": {"coordinates":[-84.656255,33.785862],"type":"Point"}
}