{
  "type": "Feature",
  "properties": {
    "addr:full":"3225 Town Manor Cir Dacula GA 30019",
    "addr:housenumber":"3225",
    "addr:postcode":"ga 30019",
    "addr:street":"Town Manor Cir",
    "iso:country":"US",
    "sg:address":"3225 Town Manor Cir",
    "sg:city":"Dacula",
    "sg:classifiers":[
        {
            "category":"Real Estate",
            "subcategory":"Real Estate Services",
            "type":"Services"
        }
    ],
    "sg:phone":"+1 770 831 0040",
    "sg:postcode":"30019",
    "sg:province":"GA",
    "wof:name":"Perdue Bill Rl Est",
    "wof:placetype":"venue"
},
  "geometry": {"coordinates":[-83.91570299999999,34.058601],"type":"Point"}
}