{
  "type": "Feature",
  "properties": {
    "iso:country":"US",
    "sg:address":"4971 Sheraton Dr",
    "sg:city":"Macon",
    "sg:classifiers":[
        {
            "category":"Social Services",
            "subcategory":"Child Care",
            "type":"Services"
        }
    ],
    "sg:phone":"+1 478 474 8829",
    "sg:postcode":"31210",
    "sg:province":"GA",
    "sg:tags":[
        "day"
    ],
    "wof:name":"Childrens Friend Lrng Ctr 25",
    "wof:placetype":"venue"
},
  "geometry": {"coordinates":[-83.708843,32.924413],"type":"Point"}
}