{
  "type": "Feature",
  "properties": {
    "addr:full":"2800 Chelsey Trl Jonesboro GA 30236",
    "addr:housenumber":"2800",
    "addr:postcode":"30236",
    "addr:street":"Chelsey Trl",
    "iso:country":"US",
    "sg:address":"2800 Chelsey Trl",
    "sg:city":"Jonesboro",
    "sg:classifiers":[
        {
            "category":"Education",
            "subcategory":"Vocational School",
            "type":"Public Place"
        }
    ],
    "sg:phone":"+1 770 968 7656",
    "sg:postcode":"30236",
    "sg:province":"GA",
    "wof:name":"Georgia International Air Inc",
    "wof:placetype":"venue"
},
  "geometry": {"coordinates":[-84.295717,33.561133],"type":"Point"}
}