{
  "type": "Feature",
  "properties": {
    "addr:full":"2205 US Hwy 19 Dahlonega GA 30533",
    "addr:housenumber":"2205",
    "addr:postcode":"30533",
    "addr:street":"Us Hwy 19",
    "iso:country":"US",
    "sg:address":"2205 US Hwy 19",
    "sg:city":"Dahlonega",
    "sg:classifiers":[
        {
            "category":"Retail",
            "subcategory":"Car Wash",
            "type":"Services"
        },
        {
            "category":"Professional",
            "type":"Services"
        }
    ],
    "sg:phone":"+1 706 867 1726",
    "sg:postcode":"30533",
    "sg:province":"GA",
    "sg:tags":[
        "carwash",
        "establishment"
    ],
    "wof:name":"Frank's Clean Up",
    "wof:placetype":"venue"
},
  "geometry": {"coordinates":[-83.9683,34.555097],"type":"Point"}
}