{
  "type": "Feature",
  "properties": {
    "iso:country":"US",
    "sg:address":"100 Piedmont Ct NW",
    "sg:city":"Atlanta",
    "sg:classifiers":[
        {
            "category":"Wholesale",
            "subcategory":"Furniture",
            "type":"Manufacturing & Wholesale Goods"
        }
    ],
    "sg:phone":"+1 770 248 0388",
    "sg:postcode":"30340",
    "sg:province":"GA",
    "sg:tags":[
        "baby"
    ],
    "wof:name":"Million Dollar Baby",
    "wof:placetype":"venue"
},
  "geometry": {"coordinates":[-84.236375,33.908683],"type":"Point"}
}