{
  "type": "Feature",
  "properties": {
    "iso:country":"US",
    "sg:address":"4099 Houston Ave",
    "sg:city":"Macon",
    "sg:classifiers":[
        {
            "category":"Autos & Motor Vehicles",
            "subcategory":"Auto Supplies",
            "type":"Retail Goods"
        }
    ],
    "sg:phone":"+1 478 788 9974",
    "sg:postcode":"31206",
    "sg:province":"GA",
    "sg:tags":[
        "tire"
    ],
    "wof:name":"Darryl Wash New & Used Tires",
    "wof:placetype":"venue"
},
  "geometry": {"coordinates":[-83.655739,32.791809],"type":"Point"}
}