{
  "type": "Feature",
  "properties": {
    "iso:country":"US",
    "sg:address":"528 S Main St",
    "sg:city":"Swainsboro",
    "sg:classifiers":[
        {
            "category":"Shopping",
            "subcategory":"Computers & Home Electronics",
            "type":"Retail Goods"
        }
    ],
    "sg:phone":"+1 478 237 2853",
    "sg:postcode":"30401",
    "sg:province":"GA",
    "sg:tags":[
        "equipment",
        "satellite",
        "system"
    ],
    "wof:name":"Reynolds Cable TV Inc",
    "wof:placetype":"venue"
},
  "geometry": {"coordinates":[-82.31895799999999,32.582232],"type":"Point"}
}