{
  "type": "Feature",
  "properties": {
    "addr:full":"121 Nanette Dr Newnan GA 30265",
    "addr:housenumber":"121",
    "addr:postcode":"30265",
    "addr:street":"Nanette Dr",
    "iso:country":"US",
    "sg:address":"121 Nanette Dr",
    "sg:city":"Newnan",
    "sg:classifiers":[
        {
            "category":"Building & Trades",
            "subcategory":"Construction",
            "type":"Services"
        }
    ],
    "sg:phone":"+1 770 252 1646",
    "sg:postcode":"30265",
    "sg:province":"GA",
    "sg:tags":[
        "contractor"
    ],
    "wof:name":"Lasting Exteriors",
    "wof:placetype":"venue"
},
  "geometry": {"coordinates":[-84.687901,33.413343],"type":"Point"}
}