{
  "type": "Feature",
  "properties": {
    "addr:full":"931 Monroe Dr Ste A-101 Atlanta GA 30308",
    "addr:housenumber":"931",
    "addr:postcode":"30308",
    "addr:street":"Monroe Dr Ste A-101",
    "iso:country":"US",
    "sg:address":"931 Monroe Dr Ste A-101",
    "sg:city":"Atlanta",
    "sg:classifiers":[
        {
            "category":"Restaurant",
            "type":"Food & Drink"
        }
    ],
    "sg:phone":"+1 404 541 9997",
    "sg:postcode":"30308",
    "sg:province":"GA",
    "sg:tags":[
        "fusion",
        "asian",
        "vietnamese"
    ],
    "sg:website":"www.namrestaurant.com",
    "wof:name":"Nam Restaurant",
    "wof:placetype":"venue"
},
  "geometry": {"coordinates":[-84.369339,33.779509],"type":"Point"}
}