{
  "type": "Feature",
  "properties": {
    "addr:full":"231 Riverbend Ln Hampton GA 30228",
    "addr:housenumber":"231",
    "addr:postcode":"30228",
    "addr:street":"Riverbend Ln",
    "iso:country":"US",
    "sg:address":"231 Riverbend Ln",
    "sg:city":"Hampton",
    "sg:classifiers":[
        {
            "category":"Local Transit",
            "type":"Transportation"
        }
    ],
    "sg:phone":"+1 770 897 0039",
    "sg:postcode":"30228",
    "sg:province":"GA",
    "sg:tags":[
        "limousine"
    ],
    "wof:name":"Atlanta Fun Bus & Limousines",
    "wof:placetype":"venue"
},
  "geometry": {"coordinates":[-84.38538,33.373683],"type":"Point"}
}