{
  "type": "Feature",
  "properties": {
    "iso:country":"US",
    "sg:address":"6125 Roswell Rd",
    "sg:city":"Atlanta",
    "sg:classifiers":[
        {
            "category":"Retail",
            "subcategory":"Laundry & Dry Cleaning",
            "type":"Services"
        },
        {
            "category":"Professional",
            "subcategory":"Business Services",
            "type":"Services"
        }
    ],
    "sg:phone":"+1 404 250 9252",
    "sg:postcode":"30328",
    "sg:province":"GA",
    "sg:tags":[
        "cleaners"
    ],
    "wof:name":"Pavilion Dry Cleaners & Lndry",
    "wof:placetype":"venue"
},
  "geometry": {"coordinates":[-84.378981,33.920718],"type":"Point"}
}