{
  "type": "Feature",
  "properties": {
    "addr:full":"1 University Dr Savannah GA 31419",
    "addr:housenumber":"1",
    "addr:postcode":"31419",
    "addr:street":"University Dr",
    "iso:country":"US",
    "sg:address":"1 University Dr",
    "sg:city":"Savannah",
    "sg:classifiers":[
        {
            "category":"Education",
            "subcategory":"University",
            "type":"Public Place"
        }
    ],
    "sg:phone":"+1 912 961 8303",
    "sg:postcode":"31419",
    "sg:province":"GA",
    "sg:tags":[
        "college"
    ],
    "wof:name":"Armstong Atlantic State University",
    "wof:placetype":"venue"
},
  "geometry": {"coordinates":[-81.164413,31.981001],"type":"Point"}
}