{
  "type": "Feature",
  "properties": {
    "addr:full":"1343 Jackson St Griffin GA 30223",
    "addr:housenumber":"1343",
    "addr:postcode":"30223",
    "addr:street":"Jackson St",
    "iso:country":"US",
    "sg:address":"1343 Jackson St",
    "sg:city":"Griffin",
    "sg:classifiers":[
        {
            "category":"Personal",
            "subcategory":"Beauty Salon",
            "type":"Services"
        }
    ],
    "sg:phone":"+1 770 412 9027",
    "sg:postcode":"30223",
    "sg:province":"GA",
    "wof:name":"Hair Care By Atrecia",
    "wof:placetype":"venue"
},
  "geometry": {"coordinates":[-84.27420499999999,33.274687],"type":"Point"}
}