{
  "type": "Feature",
  "properties": {
    "iso:country":"US",
    "sg:address":"2316 Bona Bella Ave",
    "sg:city":"Savannah",
    "sg:classifiers":[
        {
            "category":"Building & Trades",
            "subcategory":"Construction",
            "type":"Services"
        }
    ],
    "sg:phone":"+1 912 659 3775",
    "sg:postcode":"31406",
    "sg:province":"GA",
    "sg:tags":[
        "sewer",
        "contractor"
    ],
    "wof:name":"Rich's Sewer & Drain Plumbing",
    "wof:placetype":"venue"
},
  "geometry": {"coordinates":[-81.06906499999999,32.011606],"type":"Point"}
}