{
  "type": "Feature",
  "properties": {
    "addr:full":"2331 Browns Bridge Rd Gainesville GA 30504",
    "addr:housenumber":"2331",
    "addr:postcode":"30504",
    "addr:street":"Browns Bridge Rd",
    "iso:country":"US",
    "sg:address":"2331 Browns Bridge Rd",
    "sg:city":"Gainesville",
    "sg:classifiers":[
        {
            "category":"Home & Garden",
            "subcategory":"Building Materials",
            "type":"Retail Goods"
        }
    ],
    "sg:phone":"+1 770 535 7204",
    "sg:postcode":"30504",
    "sg:province":"GA",
    "wof:name":"Handi-House Truck Accessories",
    "wof:placetype":"venue"
},
  "geometry": {"coordinates":[-83.856874,34.276624],"type":"Point"}
}