{
  "type": "Feature",
  "properties": {
    "addr:full":"632 W Barnard St Glennville GA 30427",
    "addr:housenumber":"632",
    "addr:postcode":"30427",
    "addr:street":"W Barnard St",
    "iso:country":"US",
    "sg:address":"632 W Barnard St",
    "sg:city":"Glennville",
    "sg:classifiers":[
        {
            "category":"Health Services",
            "subcategory":"Doctor",
            "type":"Services"
        }
    ],
    "sg:phone":"+1 912 654 3100",
    "sg:postcode":"30427",
    "sg:province":"GA",
    "sg:tags":[
        "physician",
        "surgeon"
    ],
    "wof:name":"Family Practice Specialists",
    "wof:placetype":"venue"
},
  "geometry": {"coordinates":[-81.937552,31.939777],"type":"Point"}
}