{
  "type": "Feature",
  "properties": {
    "iso:country":"US",
    "sg:address":"3443 Middle Ground Rd",
    "sg:city":"Statesboro",
    "sg:classifiers":[
        {
            "category":"Restaurant",
            "type":"Food & Drink"
        }
    ],
    "sg:phone":"+1 912 587 2353",
    "sg:postcode":"30461",
    "sg:province":"GA",
    "sg:tags":[
        "eating"
    ],
    "wof:name":"Middleground Cafe",
    "wof:placetype":"venue"
},
  "geometry": {"coordinates":[-81.832866,32.535396],"type":"Point"}
}