{
  "type": "Feature",
  "properties": {
    "iso:country":"US",
    "sg:address":"11675 Great Oaks Way",
    "sg:city":"Alpharetta",
    "sg:classifiers":[
        {
            "category":"Retail",
            "subcategory":"Repair Shop",
            "type":"Services"
        }
    ],
    "sg:phone":"+1 770 360 0045",
    "sg:postcode":"30022",
    "sg:province":"GA",
    "sg:tags":[
        "elevator"
    ],
    "wof:name":"Mac",
    "wof:placetype":"venue"
},
  "geometry": {"coordinates":[-84.266553,34.062315],"type":"Point"}
}