{
  "type": "Feature",
  "properties": {
    "iso:country":"US",
    "sg:address":"208 W Gordon St",
    "sg:city":"Dalton",
    "sg:classifiers":[
        {
            "category":"Professional",
            "subcategory":"Lawyer & Legal Services",
            "type":"Services"
        }
    ],
    "sg:phone":"+1 706 277 9052",
    "sg:postcode":"30720",
    "sg:province":"GA",
    "wof:name":"Brown Rick Attorney At Law",
    "wof:placetype":"venue"
},
  "geometry": {"coordinates":[-84.969311,34.770786],"type":"Point"}
}