{
  "type": "Feature",
  "properties": {
    "addr:full":"11251 Alpharetta Hwy Roswell GA 30076",
    "addr:housenumber":"11251",
    "addr:postcode":"30076",
    "addr:street":"Alpharetta Hwy",
    "iso:country":"US",
    "sg:address":"11251 Alpharetta Hwy",
    "sg:city":"Roswell",
    "sg:classifiers":[
        {
            "category":"Real Estate",
            "subcategory":"Real Estate Operator",
            "type":"Services"
        }
    ],
    "sg:phone":"+1 770 442 1773",
    "sg:postcode":"30076",
    "sg:province":"GA",
    "sg:tags":[
        "apartment"
    ],
    "sg:website":"www.equityapartments.com/Atlanta...",
    "wof:name":"Greenhouse",
    "wof:placetype":"venue"
},
  "geometry": {"coordinates":[-84.325226,34.054202],"type":"Point"}
}