{
  "type": "Feature",
  "properties": {
    "addr:full":"570 Twin Oak Ln Grovetown GA 30813",
    "addr:housenumber":"570",
    "addr:postcode":"30813",
    "addr:street":"Twin Oak Ln",
    "iso:country":"US",
    "sg:address":"570 Twin Oak Ln",
    "sg:city":"Grovetown",
    "sg:classifiers":[
        {
            "category":"Building & Trades",
            "subcategory":"Landscaping Services",
            "type":"Services"
        }
    ],
    "sg:phone":"+1 706 863 5097",
    "sg:postcode":"30813",
    "sg:province":"GA",
    "sg:tags":[
        "landscape",
        "maintenance"
    ],
    "wof:name":"Davids Landscape Management",
    "wof:placetype":"venue"
},
  "geometry": {"coordinates":[-82.1683,33.474302],"type":"Point"}
}