{
  "type": "Feature",
  "properties": {
    "addr:full":"27 Wildwood Dr Savannah GA 31405",
    "addr:housenumber":"27",
    "addr:postcode":"31405",
    "addr:street":"Wildwood Dr",
    "iso:country":"US",
    "sg:address":"27 Wildwood Dr",
    "sg:city":"Savannah",
    "sg:classifiers":[
        {
            "category":"Professional",
            "subcategory":"Business Services",
            "type":"Services"
        }
    ],
    "sg:phone":"+1 912 232 3534",
    "sg:postcode":"31405",
    "sg:province":"GA",
    "wof:name":"Mr Sidney Peay",
    "wof:placetype":"venue"
},
  "geometry": {"coordinates":[-81.15028599999999,32.047702],"type":"Point"}
}