{
  "type": "Feature",
  "properties": {
    "addr:full":"2520 Watson Blvd Warner Robins GA 31093",
    "addr:housenumber":"2520",
    "addr:postcode":"31093",
    "addr:street":"Watson Blvd",
    "iso:country":"US",
    "sg:address":"2520 Watson Blvd",
    "sg:city":"Warner Robins",
    "sg:classifiers":[
        {
            "category":"Building & Trades",
            "subcategory":"Construction",
            "type":"Services"
        }
    ],
    "sg:phone":"+1 478 923 6778",
    "sg:postcode":"31093",
    "sg:province":"GA",
    "sg:tags":[
        "contractor"
    ],
    "sg:website":"www.fairchildroofs.com",
    "wof:name":"Fairchild Neal Home Improvements & Painting",
    "wof:placetype":"venue"
},
  "geometry": {"coordinates":[-83.66470200000001,32.618271],"type":"Point"}
}