{
  "type": "Feature",
  "properties": {
    "addr:full":"366 Quail Run Sautee Nacoochee GA 30571",
    "addr:housenumber":"366",
    "addr:postcode":"30571",
    "addr:street":"Quail Run",
    "iso:country":"US",
    "sg:address":"366 Quail Run",
    "sg:city":"Sautee Nacoochee",
    "sg:classifiers":[
        {
            "category":"Professional",
            "subcategory":"Management & Consulting",
            "type":"Services"
        }
    ],
    "sg:phone":"+1 706 892 1225",
    "sg:postcode":"30571",
    "sg:province":"GA",
    "sg:tags":[
        "business"
    ],
    "wof:name":"National Envmtl Solutions",
    "wof:placetype":"venue"
},
  "geometry": {"coordinates":[-83.674663,34.727851],"type":"Point"}
}