{
  "type": "Feature",
  "properties": {
    "addr:full":"6624 Catawba Dr Acworth GA 30102",
    "addr:housenumber":"6624",
    "addr:postcode":"30102",
    "addr:street":"Catawba Dr",
    "iso:country":"US",
    "sg:address":"6624 Catawba Dr",
    "sg:city":"Acworth",
    "sg:classifiers":[
        {
            "category":"Autos & Motor Vehicles",
            "subcategory":"Recreational Vehicle Sales",
            "type":"Retail Goods"
        },
        {
            "category":"Autos & Motor Vehicles",
            "subcategory":"Motorcycle Sales",
            "type":"Retail Goods"
        }
    ],
    "sg:phone":"+1 678 445 2229",
    "sg:postcode":"30102",
    "sg:province":"GA",
    "wof:name":"Ramp Connection LLC",
    "wof:placetype":"venue"
},
  "geometry": {"coordinates":[-84.633179,34.11848],"type":"Point"}
}