{
  "type": "Feature",
  "properties": {
    "iso:country":"US",
    "sg:address":"2990 Pio Nono Ave",
    "sg:city":"Macon",
    "sg:classifiers":[
        {
            "category":"Freight",
            "type":"Transportation"
        }
    ],
    "sg:phone":"+1 478 788 5949",
    "sg:postcode":"31206",
    "sg:province":"GA",
    "sg:tags":[
        "general"
    ],
    "wof:name":"Colonial Storage Center 164",
    "wof:placetype":"venue"
},
  "geometry": {"coordinates":[-83.66286700000001,32.811163],"type":"Point"}
}