{
  "type": "Feature",
  "properties": {
    "addr:full":"4756 Hammermill Rd Ste 404 Tucker GA 30084",
    "addr:housenumber":"4756",
    "addr:postcode":"30084",
    "addr:street":"Hammermill Rd Ste 404",
    "iso:country":"US",
    "sg:address":"4756 Hammermill Rd Ste 404",
    "sg:city":"Tucker",
    "sg:classifiers":[
        {
            "category":"Food & Beverages",
            "subcategory":"Candy",
            "type":"Retail Goods"
        }
    ],
    "sg:phone":"+1 770 938 4227",
    "sg:postcode":"30084",
    "sg:province":"GA",
    "sg:tags":[
        "store"
    ],
    "wof:name":"Choice Specialty Foods & Confections",
    "wof:placetype":"venue"
},
  "geometry": {"coordinates":[-84.195503,33.837002],"type":"Point"}
}