{
  "type": "Feature",
  "properties": {
    "addr:full":"128 SW Main St Vidalia GA 30474",
    "addr:housenumber":"128",
    "addr:postcode":"30474",
    "addr:street":"Sw Main St",
    "iso:country":"US",
    "sg:address":"128 SW Main St",
    "sg:city":"Vidalia",
    "sg:classifiers":[
        {
            "category":"Shopping",
            "subcategory":"Clothing, Apparel, & Fashions",
            "type":"Retail Goods"
        }
    ],
    "sg:phone":"+1 912 537 3212",
    "sg:postcode":"30474",
    "sg:province":"GA",
    "sg:tags":[
        "alteration"
    ],
    "wof:name":"Shuman-Ideal Cleaners",
    "wof:placetype":"venue"
},
  "geometry": {"coordinates":[-82.413436,32.219051],"type":"Point"}
}