{
  "type": "Feature",
  "properties": {
    "addr:full":"49 Boulevard SE Apt 368 Atlanta GA 30312",
    "addr:housenumber":"49;368",
    "addr:postcode":"30312",
    "addr:street":"Boulevard Se Apt",
    "iso:country":"US",
    "sg:address":"49 Boulevard SE Apt 368",
    "sg:city":"Atlanta",
    "sg:classifiers":[
        {
            "category":"Professional",
            "subcategory":"Management & Consulting",
            "type":"Services"
        }
    ],
    "sg:phone":"+1 404 748 1474",
    "sg:postcode":"30312",
    "sg:province":"GA",
    "sg:tags":[
        "consultant"
    ],
    "wof:name":"Shamrock Management Services",
    "wof:placetype":"venue"
},
  "geometry": {"coordinates":[-84.37194100000001,33.75349],"type":"Point"}
}