{
  "type": "Feature",
  "properties": {
    "iso:country":"US",
    "sg:address":"8130 Grogans Ferry Rd",
    "sg:city":"Atlanta",
    "sg:classifiers":[
        {
            "category":"Real Estate",
            "subcategory":"Real Estate Agent",
            "type":"Services"
        }
    ],
    "sg:phone":"+1 770 396 1468",
    "sg:postcode":"30350",
    "sg:province":"GA",
    "sg:tags":[
        "property",
        "management"
    ],
    "wof:name":"Grogans Bluff Subdivision",
    "wof:placetype":"venue"
},
  "geometry": {"coordinates":[-84.357609,33.976016],"type":"Point"}
}