{
  "type": "Feature",
  "properties": {
    "iso:country":"US",
    "sg:address":"2660 Godby Road",
    "sg:city":"Atlanta",
    "sg:classifiers":[
        {
            "category":"Home & Garden",
            "subcategory":"Furniture",
            "type":"Retail Goods"
        }
    ],
    "sg:phone":"+1 404 761 1075",
    "sg:postcode":"30349",
    "sg:province":"GA",
    "sg:tags":[
        "store"
    ],
    "wof:name":"Walther Discount Furniture",
    "wof:placetype":"venue"
},
  "geometry": {"coordinates":[-84.474672,33.616499],"type":"Point"}
}