{
  "type": "Feature",
  "properties": {
    "iso:country":"US",
    "sg:address":"2790 Sandy Plains Rd",
    "sg:city":"Marietta",
    "sg:classifiers":[
        {
            "category":"Professional",
            "type":"Services"
        }
    ],
    "sg:phone":"+1 770 565 2195",
    "sg:postcode":"30066",
    "sg:province":"GA",
    "sg:tags":[
        "establishment"
    ],
    "wof:name":"Hume Group",
    "wof:placetype":"venue"
},
  "geometry": {"coordinates":[-84.490923,34.018517],"type":"Point"}
}