{
  "type": "Feature",
  "properties": {
    "iso:country":"US",
    "sg:address":"905 Senoia Rd",
    "sg:city":"Tyrone",
    "sg:classifiers":[
        {
            "category":"Insurance",
            "subcategory":"Insurance Agent",
            "type":"Services"
        }
    ],
    "sg:phone":"+1 770 487 8000",
    "sg:postcode":"30290",
    "sg:province":"GA",
    "wof:name":"State Farm Insurance",
    "wof:placetype":"venue"
},
  "geometry": {"coordinates":[-84.596487,33.47716],"type":"Point"}
}