{
  "type": "Feature",
  "properties": {
    "addr:full":"6518 Highway 85 Riverdale GA 30274",
    "addr:housenumber":"6518",
    "addr:postcode":"30274",
    "addr:street":"Highway 85",
    "iso:country":"US",
    "sg:address":"6518 Highway 85",
    "sg:city":"Riverdale",
    "sg:classifiers":[
        {
            "category":"Restaurant",
            "type":"Food & Drink"
        }
    ],
    "sg:phone":"+1 770 997 6040",
    "sg:postcode":"30274",
    "sg:province":"GA",
    "sg:tags":[
        "pizza"
    ],
    "wof:name":"Anthony's Pizza & Pasta",
    "wof:placetype":"venue"
},
  "geometry": {"coordinates":[-84.412003,33.577],"type":"Point"}
}