{
  "type": "Feature",
  "properties": {
    "addr:full":"5290 Roswell Rd Atlanta GA 30342",
    "addr:housenumber":"5290",
    "addr:postcode":"30342",
    "addr:street":"Roswell Rd",
    "iso:country":"US",
    "sg:address":"5290 Roswell Rd",
    "sg:city":"Atlanta",
    "sg:classifiers":[
        {
            "category":"Home & Garden",
            "subcategory":"Building Materials",
            "type":"Retail Goods"
        }
    ],
    "sg:phone":"+1 404 846 5844",
    "sg:postcode":"30342",
    "sg:province":"GA",
    "sg:tags":[
        "glass",
        "window",
        "plate"
    ],
    "wof:name":"ACI Glass Co",
    "wof:placetype":"venue"
},
  "geometry": {"coordinates":[-84.380414,33.900068],"type":"Point"}
}