{
  "type": "Feature",
  "properties": {
    "iso:country":"US",
    "sg:address":"1031 Cloudland Ct",
    "sg:city":"Greensboro",
    "sg:classifiers":[
        {
            "category":"Retail",
            "subcategory":"Auto Repair",
            "type":"Services"
        }
    ],
    "sg:phone":"+1 706 453 4400",
    "sg:postcode":"30642",
    "sg:province":"GA",
    "sg:tags":[
        "glass",
        "replacement"
    ],
    "wof:name":"Aardvark Windshield Repair",
    "wof:placetype":"venue"
},
  "geometry": {"coordinates":[-83.210538,33.463547],"type":"Point"}
}