{
  "type": "Feature",
  "properties": {
    "addr:full":"8655 Colony Club Dr Alpharetta GA 30022",
    "addr:housenumber":"8655",
    "addr:postcode":"30022",
    "addr:street":"Colony Club Dr",
    "iso:country":"US",
    "sg:address":"8655 Colony Club Dr",
    "sg:city":"Alpharetta",
    "sg:classifiers":[
        {
            "category":"Building & Trades",
            "subcategory":"Construction",
            "type":"Services"
        }
    ],
    "sg:phone":"+1 770 587 4096",
    "sg:postcode":"30022",
    "sg:province":"GA",
    "sg:tags":[
        "house"
    ],
    "wof:name":"Vitalizer Network",
    "wof:placetype":"venue"
},
  "geometry": {"coordinates":[-84.271941,33.991184],"type":"Point"}
}