{
  "type": "Feature",
  "properties": {
    "iso:country":"US",
    "sg:address":"33 Ridgemere Trce",
    "sg:city":"Atlanta",
    "sg:classifiers":[
        {
            "category":"Real Estate",
            "subcategory":"Developer",
            "type":"Services"
        }
    ],
    "sg:phone":"+1 404 943 0550",
    "sg:postcode":"30328",
    "sg:province":"GA",
    "wof:name":"Stevenson Asset Management Inc",
    "wof:placetype":"venue"
},
  "geometry": {"coordinates":[-84.388437,33.917301],"type":"Point"}
}