{
  "type": "Feature",
  "properties": {
    "iso:country":"US",
    "sg:address":"1672 Northridge Rd",
    "sg:city":"Atlanta",
    "sg:classifiers":[
        {
            "category":"Shopping",
            "type":"Retail Goods"
        }
    ],
    "sg:phone":"+1 770 393 8503",
    "sg:postcode":"30350",
    "sg:province":"GA",
    "sg:tags":[
        "merchandise"
    ],
    "wof:name":"Aquarius Aquarium & Pond",
    "wof:placetype":"venue"
},
  "geometry": {"coordinates":[-84.33244999999999,33.98515],"type":"Point"}
}