{
  "type": "Feature",
  "properties": {
    "addr:full":"417 Center Cir SW Conyers GA 30094",
    "addr:housenumber":"417",
    "addr:postcode":"30094",
    "addr:street":"Center Cir Sw",
    "iso:country":"US",
    "sg:address":"417 Center Cir SW",
    "sg:city":"Conyers",
    "sg:classifiers":[
        {
            "category":"Arts & Performance",
            "subcategory":"Theater",
            "type":"Entertainment"
        }
    ],
    "sg:phone":"+1 678 698 4469",
    "sg:postcode":"30094",
    "sg:province":"GA",
    "sg:tags":[
        "group"
    ],
    "wof:name":"Toni GS Karaoke",
    "wof:placetype":"venue"
},
  "geometry": {"coordinates":[-84.073759,33.679052],"type":"Point"}
}