{
  "type": "Feature",
  "properties": {
    "addr:full":"2055 Pleasant Hill Rd Duluth GA 30096",
    "addr:housenumber":"2055",
    "addr:postcode":"30096",
    "addr:street":"Pleasant Hill Rd",
    "iso:country":"US",
    "sg:address":"2055 Pleasant Hill Rd",
    "sg:city":"Duluth",
    "sg:classifiers":[
        {
            "category":"Restaurant",
            "type":"Food & Drink"
        }
    ],
    "sg:phone":"+1 770 476 8376",
    "sg:postcode":"30096",
    "sg:province":"GA",
    "wof:name":"Red Lobster Restaurants",
    "wof:placetype":"venue"
},
  "geometry": {"coordinates":[-84.132797,33.9561],"type":"Point"}
}