{
  "type": "Feature",
  "properties": {
    "addr:full":"1050 Wisteria Drive Mableton GA 30126",
    "addr:housenumber":"1050",
    "addr:postcode":"30126",
    "addr:street":"Wisteria Drive",
    "iso:country":"US",
    "sg:address":"1050 Wisteria Drive",
    "sg:city":"Mableton",
    "sg:classifiers":[
        {
            "category":"Retail",
            "subcategory":"Car Wash",
            "type":"Services"
        },
        {
            "category":"Retail",
            "subcategory":"Auto Repair",
            "type":"Services"
        }
    ],
    "sg:phone":"+1 678 402 8651",
    "sg:postcode":"30126",
    "sg:province":"GA",
    "sg:tags":[
        "detailing"
    ],
    "wof:name":"T & S Detailing",
    "wof:placetype":"venue"
},
  "geometry": {"coordinates":[-84.584534,33.845214],"type":"Point"}
}