{
  "type": "Feature",
  "properties": {
    "iso:country":"US",
    "sg:address":"5957 Downington Ridge NW",
    "sg:city":"Acworth",
    "sg:classifiers":[
        {
            "category":"Shopping",
            "subcategory":"Clothing, Apparel, & Fashions",
            "type":"Retail Goods"
        }
    ],
    "sg:phone":"+1 678 443 9323",
    "sg:postcode":"30101",
    "sg:province":"GA",
    "sg:tags":[
        "designer"
    ],
    "wof:name":"Yo Yos Designs",
    "wof:placetype":"venue"
},
  "geometry": {"coordinates":[-84.726067,33.992727],"type":"Point"}
}