{
  "type": "Feature",
  "properties": {
    "iso:country":"US",
    "sg:address":"485 E Clayton St",
    "sg:city":"Athens",
    "sg:classifiers":[
        {
            "category":"Shopping",
            "subcategory":"Musical Instruments",
            "type":"Retail Goods"
        }
    ],
    "sg:phone":"+1 706 548 9599",
    "sg:postcode":"30601",
    "sg:province":"GA",
    "wof:name":"Drums Center",
    "wof:placetype":"venue"
},
  "geometry": {"coordinates":[-83.37364599999999,33.958996],"type":"Point"}
}