{
  "type": "Feature",
  "properties": {
    "iso:country":"US",
    "sg:address":"149 Elam St",
    "sg:city":"Gordon",
    "sg:classifiers":[
        {
            "category":"Building & Trades",
            "subcategory":"Construction",
            "type":"Services"
        }
    ],
    "sg:phone":"+1 478 628 2238",
    "sg:postcode":"31031",
    "sg:province":"GA",
    "sg:tags":[
        "painter"
    ],
    "wof:name":"Barrett's Painting",
    "wof:placetype":"venue"
},
  "geometry": {"coordinates":[-83.336423,32.886056],"type":"Point"}
}