{
  "type": "Feature",
  "properties": {
    "addr:full":"6059 Riverdale Rd Atlanta GA 30349",
    "addr:housenumber":"6059",
    "addr:postcode":"30349",
    "addr:street":"Riverdale Rd",
    "iso:country":"US",
    "sg:address":"6059 Riverdale Rd",
    "sg:city":"Atlanta",
    "sg:classifiers":[
        {
            "category":"Utilities",
            "subcategory":"Telephone",
            "type":"Services"
        }
    ],
    "sg:phone":"+1 770 991 2096",
    "sg:postcode":"30349",
    "sg:province":"GA",
    "sg:website":"http://www.att.com",
    "wof:name":"AT&T",
    "wof:placetype":"venue"
},
  "geometry": {"coordinates":[-84.426793,33.59019],"type":"Point"}
}