{
  "type": "Feature",
  "properties": {
    "addr:full":"23277 US Hwy 19 Ochlocknee GA 31773",
    "addr:postcode":"23277;31773",
    "addr:street":"Us Hwy 19 Ochlocknee",
    "iso:country":"US",
    "sg:address":"23277 US Hwy 19",
    "sg:city":"Ochlocknee",
    "sg:classifiers":[
        {
            "category":"Home & Garden",
            "subcategory":"Furniture",
            "type":"Retail Goods"
        }
    ],
    "sg:phone":"+1 229 226 0480",
    "sg:postcode":"31773",
    "sg:province":"GA",
    "sg:tags":[
        "cabinet"
    ],
    "wof:name":"Woodmasters Limited",
    "wof:placetype":"venue"
},
  "geometry": {"coordinates":[-84.00259200000001,30.932366],"type":"Point"}
}