{
  "type": "Feature",
  "properties": {
    "iso:country":"US",
    "sg:address":"6115 Green Gables Ct",
    "sg:city":"Suwanee",
    "sg:classifiers":[
        {
            "category":"Professional",
            "type":"Services"
        }
    ],
    "sg:phone":"+1 770 476 8558",
    "sg:postcode":"30024",
    "sg:province":"GA",
    "wof:name":"M & M Surety Services Inc",
    "wof:placetype":"venue"
},
  "geometry": {"coordinates":[-84.11679599999999,34.083468],"type":"Point"}
}