{
  "type": "Feature",
  "properties": {
    "iso:country":"US",
    "sg:address":"4200 Northside Pkwy NW",
    "sg:city":"Atlanta",
    "sg:classifiers":[
        {
            "category":"Banks & Credit Unions",
            "subcategory":"Financial Services",
            "type":"Services"
        }
    ],
    "sg:phone":"+1 404 949 9489",
    "sg:postcode":"30327",
    "sg:province":"GA",
    "sg:tags":[
        "investment",
        "real estate"
    ],
    "wof:name":"Galen Kilburn",
    "wof:placetype":"venue"
},
  "geometry": {"coordinates":[-84.443501,33.863753],"type":"Point"}
}