{
  "type": "Feature",
  "properties": {
    "iso:country":"US",
    "sg:address":"203 Forrest Rd",
    "sg:city":"Fort Oglethorpe",
    "sg:classifiers":[
        {
            "category":"Government",
            "subcategory":"Office",
            "type":"Public Place"
        }
    ],
    "sg:phone":"+1 706 866 4744",
    "sg:postcode":"30742",
    "sg:province":"GA",
    "sg:tags":[
        "village"
    ],
    "wof:name":"Fort Oglethorpe Constitution",
    "wof:placetype":"venue"
},
  "geometry": {"coordinates":[-85.253484,34.948667],"type":"Point"}
}