{
  "type": "Feature",
  "properties": {
    "iso:country":"US",
    "sg:address":"2299 Summertown Dr",
    "sg:city":"Norcross",
    "sg:classifiers":[
        {
            "category":"Manufacturing",
            "subcategory":"Musical Instruments",
            "type":"Manufacturing & Wholesale Goods"
        }
    ],
    "sg:phone":"+1 770 409 7476",
    "sg:postcode":"30071",
    "sg:province":"GA",
    "wof:name":"Kim's Piano Lesson Shop",
    "wof:placetype":"venue"
},
  "geometry": {"coordinates":[-84.195301,33.932917],"type":"Point"}
}