{
  "type": "Feature",
  "properties": {
    "iso:country":"US",
    "sg:address":"901 Burnt Hickory Rd NW",
    "sg:city":"Marietta",
    "sg:classifiers":[
        {
            "category":"Shopping",
            "type":"Retail Goods"
        }
    ],
    "sg:phone":"+1 770 422 8013",
    "sg:postcode":"30064",
    "sg:province":"GA",
    "sg:tags":[
        "merchandise"
    ],
    "wof:name":"Car Washh Depot II",
    "wof:placetype":"venue"
},
  "geometry": {"coordinates":[-84.57988400000001,33.954651],"type":"Point"}
}