{
  "type": "Feature",
  "properties": {
    "addr:full":"111 W College St Bowdon GA 30108",
    "addr:housenumber":"111",
    "addr:postcode":"30108",
    "addr:street":"W College St",
    "iso:country":"US",
    "sg:address":"111 W College St",
    "sg:city":"Bowdon",
    "sg:classifiers":[
        {
            "category":"Shopping",
            "subcategory":"Used Merchandise",
            "type":"Retail Goods"
        }
    ],
    "sg:phone":"+1 770 258 2978",
    "sg:postcode":"30108",
    "sg:province":"GA",
    "sg:tags":[
        "antique"
    ],
    "wof:name":"Kelli's Antiques",
    "wof:placetype":"venue"
},
  "geometry": {"coordinates":[-85.253518,33.538142],"type":"Point"}
}