{
  "type": "Feature",
  "properties": {
    "addr:full":"7669 Dallas Hwy Douglasville GA 30134",
    "addr:housenumber":"7669",
    "addr:postcode":"30134",
    "addr:street":"Dallas Hwy",
    "iso:country":"US",
    "sg:address":"7669 Dallas Hwy",
    "sg:city":"Douglasville",
    "sg:classifiers":[
        {
            "category":"Manufacturing",
            "subcategory":"Apparel",
            "type":"Manufacturing & Wholesale Goods"
        }
    ],
    "sg:phone":"+1 770 920 3263",
    "sg:postcode":"30134",
    "sg:province":"GA",
    "wof:name":"Heavenly Stitches",
    "wof:placetype":"venue"
},
  "geometry": {"coordinates":[-84.747794,33.772011],"type":"Point"}
}