{
  "type": "Feature",
  "properties": {
    "addr:full":"2170 Greene St Augusta GA 30904",
    "addr:housenumber":"2170",
    "addr:postcode":"30904",
    "addr:street":"Greene St",
    "iso:country":"US",
    "sg:address":"2170 Greene St",
    "sg:city":"Augusta",
    "sg:classifiers":[
        {
            "category":"Organizations",
            "subcategory":"Religious Organization",
            "type":"Services"
        }
    ],
    "sg:phone":"+1 706 736 6032",
    "sg:postcode":"30904",
    "sg:province":"GA",
    "wof:name":"First Dayspring Baptist Church",
    "wof:placetype":"venue"
},
  "geometry": {"coordinates":[-82.004862,33.485793],"type":"Point"}
}