{
  "type": "Feature",
  "properties": {
    "iso:country":"US",
    "sg:address":"4600 N Royal Atlanta Dr",
    "sg:city":"Tucker",
    "sg:classifiers":[
        {
            "category":"Manufacturing",
            "subcategory":"Chemicals & Compounds",
            "type":"Manufacturing & Wholesale Goods"
        },
        {
            "category":"Home & Garden",
            "subcategory":"Home Furnishings",
            "type":"Retail Goods"
        }
    ],
    "sg:phone":"+1 678 464 0893",
    "sg:postcode":"30084",
    "sg:province":"GA",
    "sg:tags":[
        "wicker",
        "product",
        "house"
    ],
    "wof:name":"Wicker Depot, Ltd",
    "wof:placetype":"venue"
},
  "geometry": {"coordinates":[-84.20056200000001,33.860619],"type":"Point"}
}