{
  "type": "Feature",
  "properties": {
    "addr:full":"222 Johnson Ferry Rd NW Atlanta GA 30328",
    "addr:housenumber":"222",
    "addr:postcode":"30328",
    "addr:street":"Johnson Ferry Rd Nw",
    "iso:country":"US",
    "sg:address":"222 Johnson Ferry Rd NW",
    "sg:city":"Atlanta",
    "sg:classifiers":[
        {
            "category":"Shopping",
            "type":"Retail Goods"
        }
    ],
    "sg:phone":"+1 404 851 1761",
    "sg:postcode":"30328",
    "sg:province":"GA",
    "sg:tags":[
        "picture",
        "frame",
        "merchandise"
    ],
    "wof:name":"Frame Source",
    "wof:placetype":"venue"
},
  "geometry": {"coordinates":[-84.38950699999999,33.934083],"type":"Point"}
}