{
  "type": "Feature",
  "properties": {
    "addr:full":"305 West Wieuca Road NE Atlanta GA 30342",
    "addr:housenumber":"305",
    "addr:postcode":"30342",
    "addr:street":"West Wieuca Road Ne",
    "iso:country":"US",
    "sg:address":"305 West Wieuca Road NE",
    "sg:city":"Atlanta",
    "sg:classifiers":[
        {
            "category":"Professional",
            "subcategory":"Lawyer & Legal Services",
            "type":"Services"
        }
    ],
    "sg:phone":"+1 404 842 7700",
    "sg:postcode":"30342",
    "sg:province":"GA",
    "sg:tags":[
        "personal",
        "injury"
    ],
    "sg:website":"www.atlantatriallawyers.com",
    "wof:name":"Allen L. Broughton, P.C.",
    "wof:placetype":"venue"
},
  "geometry": {"coordinates":[-84.377684,33.875151],"type":"Point"}
}