{
  "type": "Feature",
  "properties": {
    "addr:full":"300 E Main St Statesboro GA 30458",
    "addr:housenumber":"300",
    "addr:postcode":"30458",
    "addr:street":"E Main St",
    "iso:country":"US",
    "sg:address":"300 E Main St",
    "sg:city":"Statesboro",
    "sg:classifiers":[
        {
            "category":"Home & Garden",
            "subcategory":"Carpets & Floor Coverings",
            "type":"Retail Goods"
        }
    ],
    "sg:phone":"+1 912 489 8142",
    "sg:postcode":"30458",
    "sg:province":"GA",
    "sg:tags":[
        "dealer",
        "rug"
    ],
    "wof:name":"Tripps Area Rugs",
    "wof:placetype":"venue"
},
  "geometry": {"coordinates":[-81.773883,32.449096],"type":"Point"}
}