{
  "type": "Feature",
  "properties": {
    "addr:full":"2614 Peach Orchard Rd Augusta GA 30906",
    "addr:housenumber":"2614",
    "addr:postcode":"30906",
    "addr:street":"Peach Orchard Rd",
    "iso:country":"US",
    "sg:address":"2614 Peach Orchard Rd",
    "sg:city":"Augusta",
    "sg:classifiers":[
        {
            "category":"Banks & Credit Unions",
            "subcategory":"Bank",
            "type":"Services"
        }
    ],
    "sg:phone":"+1 706 792 1020",
    "sg:postcode":"30906",
    "sg:province":"GA",
    "sg:tags":[
        "cashing",
        "check"
    ],
    "wof:name":"ACE Cash Express",
    "wof:placetype":"venue"
},
  "geometry": {"coordinates":[-82.01937599999999,33.423586],"type":"Point"}
}