{
  "type": "Feature",
  "properties": {
    "iso:country":"US",
    "sg:address":"3232 Cobb Pkwy S",
    "sg:city":"Atlanta",
    "sg:classifiers":[
        {
            "category":"Professional",
            "subcategory":"Testing Lab",
            "type":"Services"
        }
    ],
    "sg:phone":"+1 770 640 2770",
    "sg:postcode":"30339",
    "sg:province":"GA",
    "sg:tags":[
        "repair",
        "pipette",
        "calibration"
    ],
    "sg:website":"www.precisionpipette.com",
    "wof:name":"Precision Pipette Inc",
    "wof:placetype":"venue"
},
  "geometry": {"coordinates":[-84.45619600000001,33.874756],"type":"Point"}
}