{
  "type": "Feature",
  "properties": {
    "iso:country":"US",
    "sg:address":"3060 Royal Blvd S",
    "sg:city":"Alpharetta",
    "sg:classifiers":[
        {
            "category":"Insurance",
            "subcategory":"Health Insurance",
            "type":"Services"
        }
    ],
    "sg:phone":"+1 770 864 1125",
    "sg:postcode":"30022",
    "sg:province":"GA",
    "wof:name":"Cambridge Health",
    "wof:placetype":"venue"
},
  "geometry": {"coordinates":[-84.273166,34.054234],"type":"Point"}
}