{
  "type": "Feature",
  "properties": {
    "addr:full":"221 Barry Whatley Way Griffin GA 30224",
    "addr:housenumber":"221",
    "addr:postcode":"30224",
    "addr:street":"Barry Whatley Way",
    "iso:country":"US",
    "sg:address":"221 Barry Whatley Way",
    "sg:city":"Griffin",
    "sg:classifiers":[
        {
            "category":"Building & Trades",
            "subcategory":"Construction",
            "type":"Services"
        }
    ],
    "sg:phone":"+1 770 233 5169",
    "sg:postcode":"30224",
    "sg:province":"GA",
    "sg:tags":[
        "contractor"
    ],
    "wof:name":"South Atlanta Aircraft Interio",
    "wof:placetype":"venue"
},
  "geometry": {"coordinates":[-84.261855,33.230223],"type":"Point"}
}