{
  "type": "Feature",
  "properties": {
    "iso:country":"US",
    "sg:address":"1731 Homestead Ave NE",
    "sg:city":"Atlanta",
    "sg:classifiers":[
        {
            "category":"Professional",
            "subcategory":"Art Services",
            "type":"Services"
        }
    ],
    "sg:phone":"+1 404 875 8209",
    "sg:postcode":"30306",
    "sg:province":"GA",
    "sg:tags":[
        "commercial",
        "design"
    ],
    "wof:name":"Carol Hatcher",
    "wof:placetype":"venue"
},
  "geometry": {"coordinates":[-84.34785100000001,33.801685],"type":"Point"}
}