{
  "type": "Feature",
  "properties": {
    "iso:country":"US",
    "sg:address":"4475 Roswell Rd",
    "sg:city":"Marietta",
    "sg:classifiers":[
        {
            "category":"Personal",
            "subcategory":"Beauty Salon",
            "type":"Services"
        }
    ],
    "sg:phone":"+1 770 578 1151",
    "sg:postcode":"30062",
    "sg:province":"GA",
    "sg:tags":[
        "treatment",
        "skin"
    ],
    "wof:name":"Origins",
    "wof:placetype":"venue"
},
  "geometry": {"coordinates":[-84.421871,33.986435],"type":"Point"}
}