{
  "type": "Feature",
  "properties": {
    "addr:full":"4701 Log Cabin Dr Macon GA 31204",
    "addr:housenumber":"4701",
    "addr:postcode":"31204",
    "addr:street":"Log Cabin Dr",
    "iso:country":"US",
    "sg:address":"4701 Log Cabin Dr",
    "sg:city":"Macon",
    "sg:classifiers":[
        {
            "category":"Utilities",
            "subcategory":"Mobile Phone",
            "type":"Services"
        },
        {
            "category":"Shopping",
            "subcategory":"Mobile Phones",
            "type":"Retail Goods"
        },
        {
            "category":"Utilities",
            "subcategory":"Telephone",
            "type":"Services"
        },
        {
            "category":"Professional",
            "subcategory":"Computer Services",
            "type":"Services"
        }
    ],
    "sg:phone":"+1 478 781 5871",
    "sg:postcode":"31204",
    "sg:province":"GA",
    "sg:tags":[
        "telecommunication",
        "supply",
        "communication",
        "system",
        "wireless",
        "equipment",
        "cellular"
    ],
    "sg:website":"http://clickserve.dartsearch.net/link/click?lid=43000000308049899",
    "wof:name":"T-Mobile",
    "wof:placetype":"venue"
},
  "geometry": {"coordinates":[-83.708252,32.816029],"type":"Point"}
}