{
  "type": "Feature",
  "properties": {
    "addr:full":"1331 Fields Chapel Rd Canton GA 30114",
    "addr:housenumber":"1331",
    "addr:postcode":"30114",
    "addr:street":"Fields Chapel Rd",
    "iso:country":"US",
    "sg:address":"1331 Fields Chapel Rd",
    "sg:city":"Canton",
    "sg:classifiers":[
        {
            "category":"Place Of Worship",
            "subcategory":"Church",
            "type":"Public Place"
        },
        {
            "category":"Place Of Worship",
            "type":"Public Place"
        }
    ],
    "sg:phone":"+1 770 479 6030",
    "sg:postcode":"30114",
    "sg:province":"GA",
    "sg:tags":[
        "churches-methodist"
    ],
    "wof:name":"Fields Chapel Umc",
    "wof:placetype":"venue"
},
  "geometry": {"coordinates":[-84.57672599999999,34.200231],"type":"Point"}
}