{
  "type": "Feature",
  "properties": {
    "addr:full":"735 Pierce Chapel Rd Newnan GA 30263",
    "addr:housenumber":"735",
    "addr:postcode":"30263",
    "addr:street":"Pierce Chapel Rd",
    "iso:country":"US",
    "sg:address":"735 Pierce Chapel Rd",
    "sg:city":"Newnan",
    "sg:classifiers":[
        {
            "category":"Wholesale",
            "subcategory":"Non-durable Goods",
            "type":"Manufacturing & Wholesale Goods"
        }
    ],
    "sg:phone":"+1 770 251 0608",
    "sg:postcode":"30263",
    "sg:province":"GA",
    "wof:name":"Nan V Johnston",
    "wof:placetype":"venue"
},
  "geometry": {"coordinates":[-84.91803299999999,33.36454],"type":"Point"}
}