{
  "type": "Feature",
  "properties": {
    "addr:full":"3357 Deans Bridge Rd Augusta GA 30906",
    "addr:housenumber":"3357",
    "addr:postcode":"30906",
    "addr:street":"Deans Bridge Rd",
    "iso:country":"US",
    "sg:address":"3357 Deans Bridge Rd",
    "sg:city":"Augusta",
    "sg:classifiers":[
        {
            "category":"Professional",
            "type":"Services"
        }
    ],
    "sg:phone":"+1 706 560 6438",
    "sg:postcode":"30906",
    "sg:province":"GA",
    "sg:tags":[
        "establishment"
    ],
    "wof:name":"Perseco",
    "wof:placetype":"venue"
},
  "geometry": {"coordinates":[-82.068774,33.420531],"type":"Point"}
}