{
  "type": "Feature",
  "properties": {
    "iso:country":"US",
    "sg:address":"336 2nd St",
    "sg:city":"Macon",
    "sg:classifiers":[
        {
            "category":"Restaurant",
            "type":"Food & Drink"
        }
    ],
    "sg:phone":"+1 478 746 1772",
    "sg:postcode":"31201",
    "sg:province":"GA",
    "sg:tags":[
        "eating"
    ],
    "wof:name":"Sid's Sandwich Shop",
    "wof:placetype":"venue"
},
  "geometry": {"coordinates":[-83.627973,32.837715],"type":"Point"}
}