{
  "type": "Feature",
  "properties": {
    "addr:full":"1596 Cloverdale Dr SE Marietta GA 30067",
    "addr:housenumber":"1596",
    "addr:postcode":"30067",
    "addr:street":"Cloverdale Dr Se",
    "iso:country":"US",
    "sg:address":"1596 Cloverdale Dr SE",
    "sg:city":"Marietta",
    "sg:classifiers":[
        {
            "category":"Home & Garden",
            "subcategory":"Carpets & Floor Coverings",
            "type":"Retail Goods"
        }
    ],
    "sg:phone":"+1 770 509 3476",
    "sg:postcode":"30067",
    "sg:province":"GA",
    "sg:tags":[
        "distributor",
        "material",
        "rug",
        "manufacturer"
    ],
    "sg:website":"http://www.americarpet.net",
    "wof:name":"Americarpets",
    "wof:placetype":"venue"
},
  "geometry": {"coordinates":[-84.504935,33.948967],"type":"Point"}
}