{
  "type": "Feature",
  "properties": {
    "addr:full":"140 River Park Cir Mc Donough GA 30252",
    "addr:housenumber":"140",
    "addr:postcode":"30252",
    "addr:street":"River Park Cir",
    "iso:country":"US",
    "sg:address":"140 River Park Cir",
    "sg:city":"Mc Donough",
    "sg:classifiers":[
        {
            "category":"Organizations",
            "subcategory":"Community Association",
            "type":"Services"
        }
    ],
    "sg:phone":"+1 770 914 8488",
    "sg:postcode":"30252",
    "sg:province":"GA",
    "wof:name":"River Pk Phase One Two Hmwners",
    "wof:placetype":"venue"
},
  "geometry": {"coordinates":[-84.07786,33.419535],"type":"Point"}
}