{
  "type": "Feature",
  "properties": {
    "addr:full":"592 Old Mill Ct NW Norcross GA 30093",
    "addr:housenumber":"592",
    "addr:postcode":"30093",
    "addr:street":"Old Mill Ct Nw",
    "iso:country":"US",
    "sg:address":"592 Old Mill Ct NW",
    "sg:city":"Norcross",
    "sg:classifiers":[
        {
            "category":"Professional",
            "subcategory":"Business Services",
            "type":"Services"
        },
        {
            "category":"Professional",
            "subcategory":"Research",
            "type":"Services"
        }
    ],
    "sg:phone":"+1 770 934 9003",
    "sg:postcode":"30093",
    "sg:province":"GA",
    "sg:tags":[
        "development",
        "marketing",
        "product"
    ],
    "wof:name":"Phillips Innovation Team LLC",
    "wof:placetype":"venue"
},
  "geometry": {"coordinates":[-84.185963,33.877038],"type":"Point"}
}