{
  "type": "Feature",
  "properties": {
    "iso:country":"US",
    "sg:address":"75 Spring St SW Ste 1721",
    "sg:city":"Atlanta",
    "sg:classifiers":[
        {
            "category":"Professional",
            "subcategory":"Lawyer & Legal Services",
            "type":"Services"
        }
    ],
    "sg:phone":"+1 404 215 1486",
    "sg:postcode":"30303",
    "sg:province":"GA",
    "sg:tags":[
        "convention",
        "reporters-court"
    ],
    "wof:name":"Registered Merit Reporter",
    "wof:placetype":"venue"
},
  "geometry": {"coordinates":[-84.39522599999999,33.75293],"type":"Point"}
}