{
  "type": "Feature",
  "properties": {
    "iso:country":"US",
    "sg:address":"1200 State Rte 247",
    "sg:city":"Kathleen",
    "sg:classifiers":[
        {
            "category":"Health Services",
            "subcategory":"Medical Lab",
            "type":"Services"
        }
    ],
    "sg:phone":"+1 478 987 6169",
    "sg:postcode":"31047",
    "sg:province":"GA",
    "sg:tags":[
        "laboratory"
    ],
    "wof:name":"IMC Health Care",
    "wof:placetype":"venue"
},
  "geometry": {"coordinates":[-83.598595,32.451526],"type":"Point"}
}