{
  "type": "Feature",
  "properties": {
    "iso:country":"US",
    "sg:address":"2500 Louisville Rd",
    "sg:city":"Savannah",
    "sg:classifiers":[
        {
            "category":"Freight",
            "type":"Transportation"
        }
    ],
    "sg:phone":"+1 912 232 2105",
    "sg:postcode":"31415",
    "sg:province":"GA",
    "sg:tags":[
        "trucking"
    ],
    "wof:name":"Lumber Transport Inc",
    "wof:placetype":"venue"
},
  "geometry": {"coordinates":[-81.138896,32.08609],"type":"Point"}
}