{
  "type": "Feature",
  "properties": {
    "iso:country":"US",
    "sg:address":"64 Saylors Rd",
    "sg:city":"Ellijay",
    "sg:classifiers":[
        {
            "category":"Retail",
            "subcategory":"Photofinishing",
            "type":"Services"
        }
    ],
    "sg:phone":"+1 706 698 7587",
    "sg:postcode":"30516",
    "sg:province":"GA",
    "sg:tags":[
        "photo"
    ],
    "wof:name":"Photos Plus",
    "wof:placetype":"venue"
},
  "geometry": {"coordinates":[-83.092705,34.364959],"type":"Point"}
}