{
  "type": "Feature",
  "properties": {
    "addr:full":"90 Christie Ct Stockbridge GA 30281",
    "addr:housenumber":"90",
    "addr:postcode":"30281",
    "addr:street":"Christie Ct",
    "iso:country":"US",
    "sg:address":"90 Christie Ct",
    "sg:city":"Stockbridge",
    "sg:classifiers":[
        {
            "category":"Professional",
            "subcategory":"Business Services",
            "type":"Services"
        }
    ],
    "sg:phone":"+1 770 914 1456",
    "sg:postcode":"30281",
    "sg:province":"GA",
    "sg:tags":[
        "trust",
        "investment",
        "real estate"
    ],
    "wof:name":"Elite Financial Services",
    "wof:placetype":"venue"
},
  "geometry": {"coordinates":[-84.242583,33.474468],"type":"Point"}
}