{
  "type": "Feature",
  "properties": {
    "iso:country":"US",
    "sg:address":"2568 Old Alabama Rd",
    "sg:city":"Austell",
    "sg:classifiers":[
        {
            "category":"Wholesale",
            "subcategory":"Motor Vehicles",
            "type":"Manufacturing & Wholesale Goods"
        }
    ],
    "sg:phone":"+1 770 941 9775",
    "sg:postcode":"30168",
    "sg:province":"GA",
    "sg:tags":[
        "auto"
    ],
    "sg:website":"www.copart.com",
    "wof:name":"Copart Inc",
    "wof:placetype":"venue"
},
  "geometry": {"coordinates":[-84.625325,33.800216],"type":"Point"}
}