{
  "type": "Feature",
  "properties": {
    "iso:country":"US",
    "sg:address":"526 N Main St",
    "sg:city":"Alpharetta",
    "sg:classifiers":[
        {
            "category":"Building & Trades",
            "subcategory":"Construction",
            "type":"Services"
        }
    ],
    "sg:phone":"+1 770 667 3104",
    "sg:postcode":"30004",
    "sg:province":"GA",
    "sg:tags":[
        "general",
        "contractor"
    ],
    "wof:name":"Timeless Architectural Homes",
    "wof:placetype":"venue"
},
  "geometry": {"coordinates":[-84.2932,34.090654],"type":"Point"}
}