{
  "type": "Feature",
  "properties": {
    "addr:full":"3094 Mercer University Dr Chamblee GA 30341",
    "addr:housenumber":"3094",
    "addr:postcode":"30341",
    "addr:street":"Mercer University Dr",
    "iso:country":"US",
    "sg:address":"3094 Mercer University Dr",
    "sg:city":"Chamblee",
    "sg:classifiers":[
        {
            "category":"Education",
            "subcategory":"Vocational School",
            "type":"Public Place"
        }
    ],
    "sg:phone":"+1 770 455 7725",
    "sg:postcode":"30341",
    "sg:province":"GA",
    "wof:name":"International Education System",
    "wof:placetype":"venue"
},
  "geometry": {"coordinates":[-84.257459,33.876803],"type":"Point"}
}