{
  "type": "Feature",
  "properties": {
    "iso:country":"US",
    "sg:address":"755 N Mount Vernon Hwy",
    "sg:city":"Atlanta",
    "sg:classifiers":[
        {
            "category":"Health Services",
            "subcategory":"Doctor",
            "type":"Services"
        }
    ],
    "sg:phone":"+1 404 256 2688",
    "sg:postcode":"30327",
    "sg:province":"GA",
    "sg:tags":[
        "pediatrician"
    ],
    "wof:name":"Hill Allison B MD",
    "wof:placetype":"venue"
},
  "geometry": {"coordinates":[-84.41147599999999,33.909378],"type":"Point"}
}