{
  "type": "Feature",
  "properties": {
    "addr:full":"578 BRASELTON HWY LAWRENCEVILLE GA 30043",
    "addr:housenumber":"578",
    "addr:postcode":"30043",
    "addr:street":"Braselton Hwy",
    "iso:country":"US",
    "sg:address":"578 BRASELTON HWY",
    "sg:city":"LAWRENCEVILLE",
    "sg:classifiers":[
        {
            "category":"Personal",
            "type":"Services"
        },
        {
            "category":"Shopping",
            "subcategory":"Florist",
            "type":"Retail Goods"
        }
    ],
    "sg:phone":"+1 770 277 0607",
    "sg:postcode":"30043",
    "sg:province":"GA",
    "sg:tags":[
        "consultant",
        "planning",
        "wedding"
    ],
    "sg:website":"http://www.designhouseofflowers.com",
    "wof:name":"Design House of Flowers. Inc.",
    "wof:placetype":"venue"
},
  "geometry": {"coordinates":[-83.981911,33.991533],"type":"Point"}
}