{
  "type": "Feature",
  "properties": {
    "addr:full":"1001 S Dogwood Dr Nashville GA 31639",
    "addr:housenumber":"1001",
    "addr:postcode":"31639",
    "addr:street":"S Dogwood Dr",
    "iso:country":"US",
    "sg:address":"1001 S Dogwood Dr",
    "sg:city":"Nashville",
    "sg:classifiers":[
        {
            "category":"Food & Beverages",
            "subcategory":"Groceries & Convenience Stores",
            "type":"Retail Goods"
        }
    ],
    "sg:phone":"+1 229 686 7687",
    "sg:postcode":"31639",
    "sg:province":"GA",
    "wof:name":"Exprezit Cnvnience Stores LLC",
    "wof:placetype":"venue"
},
  "geometry": {"coordinates":[-83.260004,31.196538],"type":"Point"}
}