{
  "type": "Feature",
  "properties": {
    "iso:country":"US",
    "sg:address":"1442 Richland Rd SW",
    "sg:city":"Atlanta",
    "sg:classifiers":[
        {
            "category":"Sports & Exercise",
            "subcategory":"Sports Center",
            "type":"Entertainment"
        }
    ],
    "sg:phone":"+1 404 752 5385",
    "sg:postcode":"30310",
    "sg:province":"GA",
    "sg:tags":[
        "amateur",
        "team"
    ],
    "sg:website":"www.atlantaga.gov",
    "wof:name":"Atlanta City Government",
    "wof:placetype":"venue"
},
  "geometry": {"coordinates":[-84.434646,33.728908],"type":"Point"}
}