{
  "type": "Feature",
  "properties": {
    "addr:full":"1924 Flintwood Dr SE Atlanta GA 30316",
    "addr:housenumber":"1924",
    "addr:postcode":"30316",
    "addr:street":"Flintwood Dr Se",
    "iso:country":"US",
    "sg:address":"1924 Flintwood Dr SE",
    "sg:city":"Atlanta",
    "sg:classifiers":[
        {
            "category":"Personal",
            "type":"Services"
        },
        {
            "category":"Organizations",
            "subcategory":"Professional Association",
            "type":"Services"
        }
    ],
    "sg:phone":"+1 404 914 8092",
    "sg:postcode":"30316",
    "sg:province":"GA",
    "sg:tags":[
        "singles-organizations",
        "dating"
    ],
    "wof:name":"Candy Coated Dating Services",
    "wof:placetype":"venue"
},
  "geometry": {"coordinates":[-84.31119200000001,33.710153],"type":"Point"}
}