{
  "type": "Feature",
  "properties": {
    "addr:full":"159 Dunlap Landing Rd Gainesville GA 30506",
    "addr:housenumber":"159",
    "addr:postcode":"30506",
    "addr:street":"Dunlap Landing Rd",
    "iso:country":"US",
    "sg:address":"159 Dunlap Landing Rd",
    "sg:city":"Gainesville",
    "sg:classifiers":[
        {
            "category":"Professional",
            "subcategory":"Management & Consulting",
            "type":"Services"
        }
    ],
    "sg:phone":"+1 770 503 0484",
    "sg:postcode":"30506",
    "sg:province":"GA",
    "sg:tags":[
        "business"
    ],
    "wof:name":"Loveland Robert A Consultant 1",
    "wof:placetype":"venue"
},
  "geometry": {"coordinates":[-83.849316,34.348788],"type":"Point"}
}