{
  "type": "Feature",
  "properties": {
    "addr:full":"888 Woodland Ct Stone Mountain GA 30087",
    "addr:housenumber":"888",
    "addr:postcode":"30087",
    "addr:street":"Woodland Ct",
    "iso:country":"US",
    "sg:address":"888 Woodland Ct",
    "sg:city":"Stone Mountain",
    "sg:classifiers":[
        {
            "category":"Building & Trades",
            "subcategory":"Landscaping Services",
            "type":"Services"
        }
    ],
    "sg:phone":"+1 770 923 1605",
    "sg:postcode":"30087",
    "sg:province":"GA",
    "wof:name":"J Z Lawn Care",
    "wof:placetype":"venue"
},
  "geometry": {"coordinates":[-84.143592,33.848345],"type":"Point"}
}