{
  "type": "Feature",
  "properties": {
    "addr:full":"4331 Pio Nono Ave Macon GA 31206",
    "addr:housenumber":"4331",
    "addr:postcode":"31206",
    "addr:street":"Pio Nono Ave",
    "iso:country":"US",
    "sg:address":"4331 Pio Nono Ave",
    "sg:city":"Macon",
    "sg:classifiers":[
        {
            "category":"Autos & Motor Vehicles",
            "subcategory":"Fuel & Gas Station",
            "type":"Retail Goods"
        }
    ],
    "sg:phone":"+1 478 788 5687",
    "sg:postcode":"31206",
    "sg:province":"GA",
    "sg:tags":[
        "convenience",
        "station",
        "gasoline",
        "store"
    ],
    "wof:name":"Racetrac",
    "wof:placetype":"venue"
},
  "geometry": {"coordinates":[-83.665237,32.782385],"type":"Point"}
}