{
  "type": "Feature",
  "properties": {
    "iso:country":"US",
    "sg:address":"740 Conisburgh Ct",
    "sg:city":"Stone Mountain",
    "sg:classifiers":[
        {
            "category":"Professional",
            "subcategory":"Management & Consulting",
            "type":"Services"
        }
    ],
    "sg:phone":"+1 770 413 4132",
    "sg:postcode":"30087",
    "sg:province":"GA",
    "wof:name":"Case Your Choice Mgmt",
    "wof:placetype":"venue"
},
  "geometry": {"coordinates":[-84.13113300000001,33.779469],"type":"Point"}
}