{
  "type": "Feature",
  "properties": {
    "iso:country":"US",
    "sg:address":"2096 Mozelle Dr",
    "sg:city":"Marietta",
    "sg:classifiers":[
        {
            "category":"Professional",
            "subcategory":"Testing Lab",
            "type":"Services"
        }
    ],
    "sg:phone":"+1 770 973 7514",
    "sg:postcode":"30062",
    "sg:province":"GA",
    "sg:tags":[
        "laboratory"
    ],
    "wof:name":"Rigaku/Msc Inc",
    "wof:placetype":"venue"
},
  "geometry": {"coordinates":[-84.49084499999999,34.007699],"type":"Point"}
}