{
  "type": "Feature",
  "properties": {
    "iso:country":"US",
    "sg:address":"9228 River Chase Way",
    "sg:city":"Jonesboro",
    "sg:classifiers":[
        {
            "category":"Banks & Credit Unions",
            "subcategory":"Bank",
            "type":"Services"
        }
    ],
    "sg:phone":"+1 678 610 1383",
    "sg:postcode":"30238",
    "sg:province":"GA",
    "sg:tags":[
        "loan",
        "real estate"
    ],
    "wof:name":"Georgia Commercial Mortgage",
    "wof:placetype":"venue"
},
  "geometry": {"coordinates":[-84.40317400000001,33.504436],"type":"Point"}
}