{
  "type": "Feature",
  "properties": {
    "iso:country":"US",
    "sg:address":"312 Southwood Dr",
    "sg:city":"Albany",
    "sg:classifiers":[
        {
            "category":"Banks & Credit Unions",
            "subcategory":"Investment Brokerage",
            "type":"Services"
        }
    ],
    "sg:phone":"+1 229 639 2204",
    "sg:postcode":"31701",
    "sg:province":"GA",
    "sg:tags":[
        "advisory",
        "financial"
    ],
    "wof:name":"Diversified Ventures Assn",
    "wof:placetype":"venue"
},
  "geometry": {"coordinates":[-84.154996,31.542932],"type":"Point"}
}