{
  "type": "Feature",
  "properties": {
    "addr:full":"3695 Claude Brewer Rd Loganville GA 30052",
    "addr:housenumber":"3695",
    "addr:postcode":"30052",
    "addr:street":"Claude Brewer Rd",
    "iso:country":"US",
    "sg:address":"3695 Claude Brewer Rd",
    "sg:city":"Loganville",
    "sg:classifiers":[
        {
            "category":"Retail",
            "subcategory":"Repair Shop",
            "type":"Services"
        }
    ],
    "sg:phone":"+1 678 957 6090",
    "sg:postcode":"30052",
    "sg:province":"GA",
    "sg:tags":[
        "appliance"
    ],
    "wof:name":"Jose's Technology 2000",
    "wof:placetype":"venue"
},
  "geometry": {"coordinates":[-83.878359,33.804169],"type":"Point"}
}