{
  "type": "Feature",
  "properties": {
    "addr:full":"450 Hwy 29 N Athens GA 30601",
    "addr:housenumber":"450",
    "addr:postcode":"30601",
    "addr:street":"Hwy 29 N",
    "iso:country":"US",
    "sg:address":"450 Hwy 29 N",
    "sg:city":"Athens",
    "sg:classifiers":[
        {
            "category":"Freight",
            "type":"Transportation"
        }
    ],
    "sg:phone":"+1 706 353 2590",
    "sg:postcode":"30601",
    "sg:province":"GA",
    "sg:tags":[
        "trucking"
    ],
    "sg:website":"www.yellowfreight.com",
    "wof:name":"Yellow Transportation Inc",
    "wof:placetype":"venue"
},
  "geometry": {"coordinates":[-83.33668299999999,33.996093],"type":"Point"}
}