{
  "type": "Feature",
  "properties": {
    "iso:country":"US",
    "sg:address":"9375 Barnwell Rd",
    "sg:city":"Alpharetta",
    "sg:classifiers":[
        {
            "category":"Organizations",
            "subcategory":"Community Association",
            "type":"Services"
        }
    ],
    "sg:phone":"+1 770 998 0131",
    "sg:postcode":"30022",
    "sg:province":"GA",
    "sg:tags":[
        "homeowner"
    ],
    "wof:name":"Country Club of The South Home",
    "wof:placetype":"venue"
},
  "geometry": {"coordinates":[-84.25724599999999,34.000268],"type":"Point"}
}