{
  "type": "Feature",
  "properties": {
    "iso:country":"US",
    "sg:address":"229 Rio Cir",
    "sg:city":"Decatur",
    "sg:classifiers":[
        {
            "category":"Building & Trades",
            "subcategory":"Cleaning & Sanitation",
            "type":"Services"
        }
    ],
    "sg:phone":"+1 404 373 3128",
    "sg:postcode":"30030",
    "sg:province":"GA",
    "sg:tags":[
        "janitor",
        "janitorial"
    ],
    "wof:name":"Repco Building Services Inc",
    "wof:placetype":"venue"
},
  "geometry": {"coordinates":[-84.270807,33.781485],"type":"Point"}
}