{
  "type": "Feature",
  "properties": {
    "iso:country":"US",
    "sg:address":"1380 Boulevard SE",
    "sg:city":"Atlanta",
    "sg:classifiers":[
        {
            "category":"Organizations",
            "subcategory":"Religious Organization",
            "type":"Services"
        }
    ],
    "sg:phone":"+1 404 627 4601",
    "sg:postcode":"30315",
    "sg:province":"GA",
    "wof:name":"Church of Atlanta Lighthouse",
    "wof:placetype":"venue"
},
  "geometry": {"coordinates":[-84.368656,33.716591],"type":"Point"}
}