{
  "type": "Feature",
  "properties": {
    "addr:full":"94 Commercial Dr Thomasville GA 31792",
    "addr:housenumber":"94",
    "addr:postcode":"31792",
    "addr:street":"Commercial Dr",
    "iso:country":"US",
    "sg:address":"94 Commercial Dr",
    "sg:city":"Thomasville",
    "sg:classifiers":[
        {
            "category":"Wholesale",
            "subcategory":"Electrical",
            "type":"Manufacturing & Wholesale Goods"
        },
        {
            "category":"Wholesale",
            "subcategory":"Auto Parts",
            "type":"Manufacturing & Wholesale Goods"
        }
    ],
    "sg:phone":"+1 229 226 1601",
    "sg:postcode":"31792",
    "sg:province":"GA",
    "sg:tags":[
        "battery",
        "buy",
        "component"
    ],
    "wof:name":"Battery Buyers Of America",
    "wof:placetype":"venue"
},
  "geometry": {"coordinates":[-83.94217500000001,30.850827],"type":"Point"}
}