{
  "type": "Feature",
  "properties": {
    "iso:country":"US",
    "sg:address":"1211 Hall Memorial Rd NW",
    "sg:city":"Resaca",
    "sg:classifiers":[
        {
            "category":"Building & Trades",
            "subcategory":"Construction",
            "type":"Services"
        }
    ],
    "sg:phone":"+1 706 602 9697",
    "sg:postcode":"30735",
    "sg:province":"GA",
    "sg:tags":[
        "house"
    ],
    "wof:name":"JC Haney Paul Haney",
    "wof:placetype":"venue"
},
  "geometry": {"coordinates":[-84.972623,34.544121],"type":"Point"}
}