{
  "type": "Feature",
  "properties": {
    "iso:country":"US",
    "sg:address":"2166 Mountain Industrial Blvd",
    "sg:city":"Tucker",
    "sg:classifiers":[
        {
            "category":"Wholesale",
            "subcategory":"Medical Equipment & Supplies",
            "type":"Manufacturing & Wholesale Goods"
        }
    ],
    "sg:phone":"+1 770 407 4989",
    "sg:postcode":"30084",
    "sg:province":"GA",
    "sg:tags":[
        "soundproofing"
    ],
    "wof:name":"Elma Electronics",
    "wof:placetype":"venue"
},
  "geometry": {"coordinates":[-84.200892,33.847856],"type":"Point"}
}