{
  "type": "Feature",
  "properties": {
    "addr:full":"697 Davis Rd Stockbridge GA 30281",
    "addr:housenumber":"697",
    "addr:postcode":"30281",
    "addr:street":"Davis Rd",
    "iso:country":"US",
    "sg:address":"697 Davis Rd",
    "sg:city":"Stockbridge",
    "sg:classifiers":[
        {
            "category":"Restaurant",
            "type":"Food & Drink"
        }
    ],
    "sg:phone":"+1 678 565 8881",
    "sg:postcode":"30281",
    "sg:province":"GA",
    "sg:tags":[
        "japanese",
        "chinese"
    ],
    "wof:name":"Kazu Chinese & Japanese Restaurant",
    "wof:placetype":"venue"
},
  "geometry": {"coordinates":[-84.25508000000001,33.555887],"type":"Point"}
}