{
  "type": "Feature",
  "properties": {
    "iso:country":"US",
    "sg:address":"6349 Godfrey Dr",
    "sg:city":"Mableton",
    "sg:classifiers":[
        {
            "category":"Building & Trades",
            "subcategory":"Construction",
            "type":"Services"
        }
    ],
    "sg:phone":"+1 770 941 1936",
    "sg:postcode":"30126",
    "sg:province":"GA",
    "sg:tags":[
        "contractor"
    ],
    "wof:name":"Rain Control of Atlanta",
    "wof:placetype":"venue"
},
  "geometry": {"coordinates":[-84.56111900000001,33.799782],"type":"Point"}
}