{
  "type": "Feature",
  "properties": {
    "addr:full":"6090 Riley Rd Cumming GA 30028",
    "addr:housenumber":"6090",
    "addr:postcode":"30028",
    "addr:street":"Riley Rd",
    "iso:country":"US",
    "sg:address":"6090 Riley Rd",
    "sg:city":"Cumming",
    "sg:classifiers":[
        {
            "category":"Building & Trades",
            "subcategory":"Landscaping Services",
            "type":"Services"
        }
    ],
    "sg:phone":"+1 678 965 5669",
    "sg:postcode":"30028",
    "sg:province":"GA",
    "sg:tags":[
        "landscape",
        "contractor"
    ],
    "wof:name":"Reed Landscaping Inc",
    "wof:placetype":"venue"
},
  "geometry": {"coordinates":[-84.12780600000001,34.318926],"type":"Point"}
}