{
  "type": "Feature",
  "properties": {
    "addr:full":"709 5th Ave Dalton GA 30721",
    "addr:housenumber":"709",
    "addr:postcode":"30721",
    "addr:street":"5Th Ave",
    "iso:country":"US",
    "sg:address":"709 5th Ave",
    "sg:city":"Dalton",
    "sg:classifiers":[
        {
            "category":"Professional",
            "subcategory":"Accounting & Tax Preparation",
            "type":"Services"
        }
    ],
    "sg:phone":"+1 706 463 1686",
    "sg:postcode":"30721",
    "sg:province":"GA",
    "sg:tags":[
        "return"
    ],
    "wof:name":"Morales Income Tax",
    "wof:placetype":"venue"
},
  "geometry": {"coordinates":[-84.953791,34.762628],"type":"Point"}
}