{
  "type": "Feature",
  "properties": {
    "addr:full":"109 Gettys St Dublin GA 31027",
    "addr:housenumber":"109",
    "addr:postcode":"31027",
    "addr:street":"Gettys St",
    "iso:country":"US",
    "sg:address":"109 Gettys St",
    "sg:city":"Dublin",
    "sg:classifiers":[
        {
            "category":"Social Services",
            "subcategory":"Child Care",
            "type":"Services"
        }
    ],
    "sg:phone":"+1 478 275 8078",
    "sg:postcode":"31027",
    "sg:province":"GA",
    "sg:tags":[
        "day"
    ],
    "wof:name":"Childrens Ark",
    "wof:placetype":"venue"
},
  "geometry": {"coordinates":[-82.868582,32.538628],"type":"Point"}
}