{
  "type": "Feature",
  "properties": {
    "iso:country":"US",
    "sg:address":"600 Ponderosa Ct",
    "sg:city":"Fayetteville",
    "sg:classifiers":[
        {
            "category":"Wholesale",
            "subcategory":"Durable Goods & Equipment",
            "type":"Manufacturing & Wholesale Goods"
        }
    ],
    "sg:phone":"+1 770 461 8684",
    "sg:postcode":"30214",
    "sg:province":"GA",
    "wof:name":"In Thiem Diversified",
    "wof:placetype":"venue"
},
  "geometry": {"coordinates":[-84.422026,33.471016],"type":"Point"}
}