{
  "type": "Feature",
  "properties": {
    "iso:country":"US",
    "sg:address":"3912 Springleaf Pt",
    "sg:city":"Stone Mountain",
    "sg:classifiers":[
        {
            "category":"Building & Trades",
            "subcategory":"Construction",
            "type":"Services"
        }
    ],
    "sg:phone":"+1 404 254 3948",
    "sg:postcode":"30083",
    "sg:province":"GA",
    "sg:tags":[
        "contractor"
    ],
    "wof:name":"Cleaning Services Yes",
    "wof:placetype":"venue"
},
  "geometry": {"coordinates":[-84.229535,33.776027],"type":"Point"}
}