{
  "type": "Feature",
  "properties": {
    "addr:full":"107 W Courthouse Sq Cumming GA 30040",
    "addr:housenumber":"107",
    "addr:postcode":"30040",
    "addr:street":"W Courthouse Sq",
    "iso:country":"US",
    "sg:address":"107 W Courthouse Sq",
    "sg:city":"Cumming",
    "sg:classifiers":[
        {
            "category":"Professional",
            "subcategory":"Accounting & Tax Preparation",
            "type":"Services"
        }
    ],
    "sg:phone":"+1 770 887 2094",
    "sg:postcode":"30040",
    "sg:province":"GA",
    "sg:tags":[
        "accountant"
    ],
    "wof:name":"James Owens & Assoc",
    "wof:placetype":"venue"
},
  "geometry": {"coordinates":[-84.140393,34.207021],"type":"Point"}
}