{
  "type": "Feature",
  "properties": {
    "addr:full":"677 Jonesboro Rd Mc Donough GA 30253",
    "addr:housenumber":"677",
    "addr:postcode":"30253",
    "addr:street":"Jonesboro Rd",
    "iso:country":"US",
    "sg:address":"677 Jonesboro Rd",
    "sg:city":"Mc Donough",
    "sg:classifiers":[
        {
            "category":"Professional",
            "subcategory":"Business Services",
            "type":"Services"
        }
    ],
    "sg:phone":"+1 770 957 6950",
    "sg:postcode":"30253",
    "sg:province":"GA",
    "wof:name":"Eddie Bee Enterprises Inc",
    "wof:placetype":"venue"
},
  "geometry": {"coordinates":[-84.180477,33.458997],"type":"Point"}
}