{
  "type": "Feature",
  "properties": {
    "addr:full":"4294 Atlanta St Powder Springs GA 30127",
    "addr:housenumber":"4294",
    "addr:postcode":"30127",
    "addr:street":"Atlanta St",
    "iso:country":"US",
    "sg:address":"4294 Atlanta St",
    "sg:city":"Powder Springs",
    "sg:classifiers":[
        {
            "category":"Organizations",
            "subcategory":"Religious Organization",
            "type":"Services"
        }
    ],
    "sg:phone":"+1 770 439 6145",
    "sg:postcode":"30127",
    "sg:province":"GA",
    "sg:tags":[
        "church"
    ],
    "wof:name":"Powder Springs First Mthdst",
    "wof:placetype":"venue"
},
  "geometry": {"coordinates":[-84.67781600000001,33.857611],"type":"Point"}
}