{
  "type": "Feature",
  "properties": {
    "iso:country":"US",
    "sg:address":"3709 Gentian Blvd",
    "sg:city":"Columbus",
    "sg:classifiers":[
        {
            "category":"Restaurant",
            "type":"Food & Drink"
        }
    ],
    "sg:menulink":"http://www.allmenus.com/ga/columbus/94246-red-kaoliang/menu/",
    "sg:phone":"+1 706 563 2487",
    "sg:postcode":"31907",
    "sg:province":"GA",
    "sg:tags":[
        "asian",
        "chinese"
    ],
    "wof:name":"Red Kaoliang",
    "wof:placetype":"venue"
},
  "geometry": {"coordinates":[-84.932573,32.507611],"type":"Point"}
}