{
  "type": "Feature",
  "properties": {
    "iso:country":"US",
    "sg:address":"4550 Browns Bridge Rd",
    "sg:city":"Gainesville",
    "sg:classifiers":[
        {
            "category":"Retail",
            "subcategory":"Auto Repair",
            "type":"Services"
        }
    ],
    "sg:phone":"+1 770 536 3700",
    "sg:postcode":"30504",
    "sg:province":"GA",
    "sg:tags":[
        "repairing",
        "automobile",
        "general"
    ],
    "wof:name":"Martins Auto Repair",
    "wof:placetype":"venue"
},
  "geometry": {"coordinates":[-83.921504,34.26878],"type":"Point"}
}