{
  "type": "Feature",
  "properties": {
    "iso:country":"US",
    "sg:address":"3626 Chamblee Tucker Rd",
    "sg:city":"Atlanta",
    "sg:classifiers":[
        {
            "category":"Building & Trades",
            "subcategory":"Equipment Rental",
            "type":"Services"
        }
    ],
    "sg:phone":"+1 770 270 2889",
    "sg:postcode":"30341",
    "sg:province":"GA",
    "sg:tags":[
        "leasing"
    ],
    "wof:name":"Best Cash Leasing",
    "wof:placetype":"venue"
},
  "geometry": {"coordinates":[-84.24618100000001,33.884214],"type":"Point"}
}