{
  "type": "Feature",
  "properties": {
    "iso:country":"US",
    "sg:address":"1130 Grace St SW",
    "sg:city":"Mableton",
    "sg:classifiers":[
        {
            "category":"Organizations",
            "subcategory":"Community Association",
            "type":"Services"
        }
    ],
    "sg:phone":"+1 770 745 4247",
    "sg:postcode":"30126",
    "sg:province":"GA",
    "sg:website":"http://www.payneandglory.com",
    "wof:name":"Motivtion Empwerment Image Dev",
    "wof:placetype":"venue"
},
  "geometry": {"coordinates":[-84.58733100000001,33.824391],"type":"Point"}
}