{
  "type": "Feature",
  "properties": {
    "iso:country":"US",
    "sg:address":"1935 McDonough Rd",
    "sg:city":"Hampton",
    "sg:classifiers":[
        {
            "category":"Government",
            "subcategory":"Office",
            "type":"Public Place"
        }
    ],
    "sg:phone":"+1 770 473 5730",
    "sg:postcode":"30228",
    "sg:province":"GA",
    "wof:name":"Lovejoy Soccer Complex",
    "wof:placetype":"venue"
},
  "geometry": {"coordinates":[-84.330952,33.448117],"type":"Point"}
}