{
  "type": "Feature",
  "properties": {
    "addr:full":"786 Elma G Miles Pkwy Hinesville GA 31313",
    "addr:housenumber":"786;g",
    "addr:postcode":"31313",
    "addr:street":"Elma;Miles Pkwy",
    "iso:country":"US",
    "sg:address":"786 Elma G Miles Pkwy",
    "sg:city":"Hinesville",
    "sg:classifiers":[
        {
            "category":"Autos & Motor Vehicles",
            "subcategory":"Automobile Sales",
            "type":"Retail Goods"
        }
    ],
    "sg:phone":"+1 912 369 0288",
    "sg:postcode":"31313",
    "sg:province":"GA",
    "sg:tags":[
        "car",
        "dealer"
    ],
    "wof:name":"Ken's Auto Sales",
    "wof:placetype":"venue"
},
  "geometry": {"coordinates":[-81.61481499999999,31.830848],"type":"Point"}
}