{
  "type": "Feature",
  "properties": {
    "addr:full":"5075 Roswell Rd Atlanta GA 30342",
    "addr:housenumber":"5075",
    "addr:postcode":"30342",
    "addr:street":"Roswell Rd",
    "iso:country":"US",
    "sg:address":"5075 Roswell Rd",
    "sg:city":"Atlanta",
    "sg:classifiers":[
        {
            "category":"Social Services",
            "subcategory":"Job Training",
            "type":"Services"
        }
    ],
    "sg:phone":"+1 404 843 8333",
    "sg:postcode":"30342",
    "sg:province":"GA",
    "sg:tags":[
        "control",
        "pollution",
        "air"
    ],
    "wof:name":"Warren Environment Inc",
    "wof:placetype":"venue"
},
  "geometry": {"coordinates":[-84.381221,33.893698],"type":"Point"}
}