{
  "type": "Feature",
  "properties": {
    "addr:full":"5009 State Rte 5 Douglasville GA 30135",
    "addr:housenumber":"5009",
    "addr:postcode":"30135",
    "addr:street":"State Rte 5",
    "iso:country":"US",
    "sg:address":"5009 State Rte 5",
    "sg:city":"Douglasville",
    "sg:classifiers":[
        {
            "category":"Building & Trades",
            "subcategory":"Construction",
            "type":"Services"
        }
    ],
    "sg:phone":"+1 770 577 8866",
    "sg:postcode":"30135",
    "sg:province":"GA",
    "sg:tags":[
        "roofing",
        "contractor"
    ],
    "wof:name":"Interstate Consoidated Roofing",
    "wof:placetype":"venue"
},
  "geometry": {"coordinates":[-84.806325,33.666314],"type":"Point"}
}