{
  "type": "Feature",
  "properties": {
    "addr:full":"5890 Ogeechee Rd Savannah GA 31419",
    "addr:housenumber":"5890",
    "addr:postcode":"31419",
    "addr:street":"Ogeechee Rd",
    "iso:country":"US",
    "sg:address":"5890 Ogeechee Rd",
    "sg:city":"Savannah",
    "sg:classifiers":[
        {
            "category":"Home & Garden",
            "subcategory":"Mobile Homes",
            "type":"Retail Goods"
        }
    ],
    "sg:phone":"+1 912 920 3692",
    "sg:postcode":"31419",
    "sg:province":"GA",
    "sg:tags":[
        "manufactured"
    ],
    "wof:name":"Ray Sollie Homes",
    "wof:placetype":"venue"
},
  "geometry": {"coordinates":[-81.246998,32.001542],"type":"Point"}
}