{
  "type": "Feature",
  "properties": {
    "iso:country":"US",
    "sg:address":"1710 Defoor Ave NW",
    "sg:city":"Atlanta",
    "sg:classifiers":[
        {
            "category":"Manufacturing",
            "subcategory":"Printing",
            "type":"Manufacturing & Wholesale Goods"
        }
    ],
    "sg:phone":"+1 404 591 3706",
    "sg:postcode":"30318",
    "sg:province":"GA",
    "sg:tags":[
        "publisher"
    ],
    "wof:name":"Cherokee Publishing",
    "wof:placetype":"venue"
},
  "geometry": {"coordinates":[-84.41950199999999,33.801474],"type":"Point"}
}