{
  "type": "Feature",
  "properties": {
    "addr:full":"4128 Clay Dr Valdosta GA 31605",
    "addr:housenumber":"4128",
    "addr:postcode":"31605",
    "addr:street":"Clay Dr",
    "iso:country":"US",
    "sg:address":"4128 Clay Dr",
    "sg:city":"Valdosta",
    "sg:classifiers":[
        {
            "category":"Building & Trades",
            "subcategory":"Landscaping Services",
            "type":"Services"
        }
    ],
    "sg:phone":"+1 229 242 1871",
    "sg:postcode":"31605",
    "sg:province":"GA",
    "wof:name":"Lancaster Lawn Care",
    "wof:placetype":"venue"
},
  "geometry": {"coordinates":[-83.252422,30.944013],"type":"Point"}
}