{
  "type": "Feature",
  "properties": {
    "iso:country":"US",
    "sg:address":"5980 Collins Rd",
    "sg:city":"Acworth",
    "sg:classifiers":[
        {
            "category":"Real Estate",
            "subcategory":"Real Estate Agent",
            "type":"Services"
        }
    ],
    "sg:phone":"+1 770 427 5832",
    "sg:postcode":"30101",
    "sg:province":"GA",
    "sg:tags":[
        "inspection"
    ],
    "wof:name":"Royal Home Inspections",
    "wof:placetype":"venue"
},
  "geometry": {"coordinates":[-84.724092,34.006644],"type":"Point"}
}