{
  "type": "Feature",
  "properties": {
    "iso:country":"US",
    "sg:address":"102 Linda Dr",
    "sg:city":"Byron",
    "sg:classifiers":[
        {
            "category":"Retail",
            "subcategory":"Auto Repair",
            "type":"Services"
        }
    ],
    "sg:phone":"+1 478 956 5662",
    "sg:postcode":"31093",
    "sg:province":"GA",
    "sg:tags":[
        "body",
        "automobile",
        "painting"
    ],
    "wof:name":"Clyde's Body Shop",
    "wof:placetype":"venue"
},
  "geometry": {"coordinates":[-83.637573,32.630617],"type":"Point"}
}