{
  "type": "Feature",
  "properties": {
    "addr:full":"1419 Hogansville Rd Lagrange GA 30241",
    "addr:housenumber":"1419",
    "addr:postcode":"30241",
    "addr:street":"Hogansville Rd",
    "iso:country":"US",
    "sg:address":"1419 Hogansville Rd",
    "sg:city":"Lagrange",
    "sg:classifiers":[
        {
            "category":"Retail",
            "subcategory":"Auto Repair",
            "type":"Services"
        }
    ],
    "sg:phone":"+1 706 882 9117",
    "sg:postcode":"30241",
    "sg:province":"GA",
    "sg:tags":[
        "body",
        "automobile",
        "painting",
        "repairing"
    ],
    "wof:name":"Reed's Auto Body Shop",
    "wof:placetype":"venue"
},
  "geometry": {"coordinates":[-85.001271,33.053475],"type":"Point"}
}