{
  "type": "Feature",
  "properties": {
    "addr:full":"9110 US Hwy 78 Bremen GA 30110",
    "addr:housenumber":"9110",
    "addr:postcode":"30110",
    "addr:street":"Us Hwy 78",
    "iso:country":"US",
    "sg:address":"9110 US Hwy 78",
    "sg:city":"Bremen",
    "sg:classifiers":[
        {
            "category":"Autos & Motor Vehicles",
            "subcategory":"Automobile Sales",
            "type":"Retail Goods"
        }
    ],
    "sg:phone":"+1 770 214 0202",
    "sg:postcode":"30110",
    "sg:province":"GA",
    "sg:tags":[
        "car",
        "dealer"
    ],
    "wof:name":"Healthy Auto Sales & Svc",
    "wof:placetype":"venue"
},
  "geometry": {"coordinates":[-85.08299,33.724271],"type":"Point"}
}