{
  "type": "Feature",
  "properties": {
    "iso:country":"US",
    "sg:address":"13975 Highway 9 N",
    "sg:city":"Alpharetta",
    "sg:classifiers":[
        {
            "category":"Home & Garden",
            "subcategory":"Garden Supply",
            "type":"Retail Goods"
        }
    ],
    "sg:phone":"+1 770 664 8200",
    "sg:postcode":"30004",
    "sg:province":"GA",
    "sg:tags":[
        "sodding",
        "sod"
    ],
    "sg:website":"http://www.glmsod.com/index.html",
    "wof:name":"GLM Sod & Landscape Materials",
    "wof:placetype":"venue"
},
  "geometry": {"coordinates":[-84.270493,34.121674],"type":"Point"}
}