{
  "type": "Feature",
  "properties": {
    "addr:full":"6705 Emerald Pointe Cir Atlanta GA 30349",
    "addr:housenumber":"6705",
    "addr:postcode":"30349",
    "addr:street":"Emerald Pointe Cir",
    "iso:country":"US",
    "sg:address":"6705 Emerald Pointe Cir",
    "sg:city":"Atlanta",
    "sg:classifiers":[
        {
            "category":"Professional",
            "type":"Services"
        }
    ],
    "sg:phone":"+1 770 907 8009",
    "sg:postcode":"30349",
    "sg:province":"GA",
    "wof:name":"Dust Be Gone",
    "wof:placetype":"venue"
},
  "geometry": {"coordinates":[-84.475662,33.585305],"type":"Point"}
}