{
  "type": "Feature",
  "properties": {
    "iso:country":"US",
    "sg:address":"2214 Whispering Pines Rd",
    "sg:city":"Albany",
    "sg:classifiers":[
        {
            "category":"Organizations",
            "subcategory":"Non-profit Organization",
            "type":"Services"
        }
    ],
    "sg:phone":"+1 229 431 2343",
    "sg:postcode":"31707",
    "sg:province":"GA",
    "sg:tags":[
        "alternative",
        "abortion"
    ],
    "wof:name":"Alpha Crisis Pregnancy Ctr",
    "wof:placetype":"venue"
},
  "geometry": {"coordinates":[-84.200183,31.605774],"type":"Point"}
}