{
  "type": "Feature",
  "properties": {
    "iso:country":"US",
    "sg:address":"331 Rockbridge Rd NW Ste 1300",
    "sg:city":"Lilburn",
    "sg:classifiers":[
        {
            "category":"Wholesale",
            "subcategory":"Computers",
            "type":"Manufacturing & Wholesale Goods"
        }
    ],
    "sg:phone":"+1 770 717 1017",
    "sg:postcode":"30047",
    "sg:province":"GA",
    "wof:name":"Discount Computers",
    "wof:placetype":"venue"
},
  "geometry": {"coordinates":[-84.16128399999999,33.882153],"type":"Point"}
}