{
  "type": "Feature",
  "properties": {
    "addr:full":"811 US Highway 27 Cataula GA 31804",
    "addr:housenumber":"811",
    "addr:postcode":"31804",
    "addr:street":"Us Highway 27 Cataula",
    "iso:country":"US",
    "sg:address":"811 US Highway 27",
    "sg:city":"Cataula",
    "sg:classifiers":[
        {
            "category":"Organizations",
            "subcategory":"Religious Organization",
            "type":"Services"
        }
    ],
    "sg:phone":"+1 706 324 7595",
    "sg:postcode":"31804",
    "sg:province":"GA",
    "wof:name":"Georgia Baptist Convention",
    "wof:placetype":"venue"
},
  "geometry": {"coordinates":[-84.905953,32.617924],"type":"Point"}
}