{
  "type": "Feature",
  "properties": {
    "iso:country":"US",
    "sg:address":"540 Normandy Trl",
    "sg:city":"Lavonia",
    "sg:classifiers":[
        {
            "category":"Real Estate",
            "subcategory":"Real Estate Agent",
            "type":"Services"
        }
    ],
    "sg:phone":"+1 706 356 0561",
    "sg:postcode":"30553",
    "sg:province":"GA",
    "sg:website":"www.thomasandassoc-rep.com",
    "wof:name":"Thomas & Assoc",
    "wof:placetype":"venue"
},
  "geometry": {"coordinates":[-83.09760300000001,34.491969],"type":"Point"}
}