{
  "type": "Feature",
  "properties": {
    "addr:full":"1110 College St Tifton GA 31794",
    "addr:housenumber":"1110",
    "addr:postcode":"31794",
    "addr:street":"College St",
    "iso:country":"US",
    "sg:address":"1110 College St",
    "sg:city":"Tifton",
    "sg:classifiers":[
        {
            "category":"Professional",
            "type":"Services"
        }
    ],
    "sg:phone":"+1 229 388 0614",
    "sg:postcode":"31794",
    "sg:province":"GA",
    "wof:name":"Daviss Med Claim Co",
    "wof:placetype":"venue"
},
  "geometry": {"coordinates":[-83.511377,31.436241],"type":"Point"}
}