{
  "type": "Feature",
  "properties": {
    "addr:full":"396 Sutton Rd Ellijay GA 30540",
    "addr:housenumber":"396",
    "addr:postcode":"30540",
    "addr:street":"Sutton Rd",
    "iso:country":"US",
    "sg:address":"396 Sutton Rd",
    "sg:city":"Ellijay",
    "sg:classifiers":[
        {
            "category":"Building & Trades",
            "subcategory":"Construction",
            "type":"Services"
        }
    ],
    "sg:phone":"+1 706 276 1001",
    "sg:postcode":"30540",
    "sg:province":"GA",
    "sg:tags":[
        "house"
    ],
    "wof:name":"Buckner Const",
    "wof:placetype":"venue"
},
  "geometry": {"coordinates":[-84.52134599999999,34.622418],"type":"Point"}
}