{
  "type": "Feature",
  "properties": {
    "addr:full":"109 Silverthorne Pl Douglasville GA 30134",
    "addr:housenumber":"109",
    "addr:postcode":"30134",
    "addr:street":"Silverthorne Pl",
    "iso:country":"US",
    "sg:address":"109 Silverthorne Pl",
    "sg:city":"Douglasville",
    "sg:classifiers":[
        {
            "category":"Building & Trades",
            "subcategory":"Electrical",
            "type":"Services"
        }
    ],
    "sg:phone":"+1 770 947 3201",
    "sg:postcode":"30134",
    "sg:province":"GA",
    "sg:tags":[
        "electrician"
    ],
    "wof:name":"H&R Electric",
    "wof:placetype":"venue"
},
  "geometry": {"coordinates":[-84.823125,33.803104],"type":"Point"}
}