{
  "type": "Feature",
  "properties": {
    "addr:full":"1287 Cameron Creek Marietta GA 30062",
    "addr:housenumber":"1287",
    "addr:postcode":"30062",
    "addr:street":"Cameron Creek",
    "iso:country":"US",
    "sg:address":"1287 Cameron Creek",
    "sg:city":"Marietta",
    "sg:classifiers":[
        {
            "category":"Shopping",
            "subcategory":"Florist",
            "type":"Retail Goods"
        }
    ],
    "sg:phone":"+1 770 565 7915",
    "sg:postcode":"30062",
    "sg:province":"GA",
    "wof:name":"Unique Floral Decor",
    "wof:placetype":"venue"
},
  "geometry": {"coordinates":[-84.514443,33.981303],"type":"Point"}
}