{
  "type": "Feature",
  "properties": {
    "addr:full":"2474 Arcadia Dr. N.W. Acworth GA 30101",
    "addr:housenumber":"2474",
    "addr:postcode":"30101",
    "addr:street":"Arcadia Dr. N.W.",
    "iso:country":"US",
    "sg:address":"2474 Arcadia Dr. N.W.",
    "sg:city":"Acworth",
    "sg:classifiers":[
        {
            "category":"Retail",
            "subcategory":"Animal Services",
            "type":"Services"
        }
    ],
    "sg:phone":"+1 678 986 9366",
    "sg:postcode":"30101",
    "sg:province":"GA",
    "sg:tags":[
        "pet",
        "exercising",
        "sitting"
    ],
    "wof:name":"A Loving Touch Pet Sitting",
    "wof:placetype":"venue"
},
  "geometry": {"coordinates":[-84.620216,34.068432],"type":"Point"}
}