{
  "type": "Feature",
  "properties": {
    "addr:full":"2422 Smith Ave SW Marietta GA 30064",
    "addr:housenumber":"2422",
    "addr:postcode":"30064",
    "addr:street":"Smith Ave Sw",
    "iso:country":"US",
    "sg:address":"2422 Smith Ave SW",
    "sg:city":"Marietta",
    "sg:classifiers":[
        {
            "category":"Sports & Exercise",
            "subcategory":"Stables",
            "type":"Entertainment"
        }
    ],
    "sg:phone":"+1 770 792 9090",
    "sg:postcode":"30064",
    "sg:province":"GA",
    "sg:tags":[
        "riding",
        "academy"
    ],
    "wof:name":"Works Xenophon & Torey",
    "wof:placetype":"venue"
},
  "geometry": {"coordinates":[-84.62968100000001,33.895352],"type":"Point"}
}