{
  "type": "Feature",
  "properties": {
    "iso:country":"US",
    "sg:address":"4351 Washington Rd",
    "sg:city":"Evans",
    "sg:classifiers":[
        {
            "category":"Personal",
            "subcategory":"Beauty Salon",
            "type":"Services"
        }
    ],
    "sg:phone":"+1 706 860 9135",
    "sg:postcode":"30809",
    "sg:province":"GA",
    "sg:tags":[
        "hair"
    ],
    "wof:name":"Creative Hairdressers",
    "wof:placetype":"venue"
},
  "geometry": {"coordinates":[-82.13535,33.541931],"type":"Point"}
}