{
  "type": "Feature",
  "properties": {
    "addr:full":"4512 Martha Berry Hwy NE Rome GA 30165",
    "addr:housenumber":"4512",
    "addr:postcode":"ga 30165",
    "addr:street":"Martha Berry Hwy Ne",
    "iso:country":"US",
    "sg:address":"4512 Martha Berry Hwy NE",
    "sg:city":"Rome",
    "sg:classifiers":[
        {
            "category":"Personal",
            "subcategory":"Beauty Salon",
            "type":"Services"
        }
    ],
    "sg:phone":"+1 706 622 2223",
    "sg:postcode":"30165",
    "sg:province":"GA",
    "wof:name":"Boondocks",
    "wof:placetype":"venue"
},
  "geometry": {"coordinates":[-85.172438,34.349545],"type":"Point"}
}