{
  "type": "Feature",
  "properties": {
    "iso:country":"US",
    "sg:address":"3512 Moultrie Rd",
    "sg:city":"Albany",
    "sg:classifiers":[
        {
            "category":"Organizations",
            "subcategory":"Religious Organization",
            "type":"Services"
        }
    ],
    "sg:phone":"+1 229 439 7262",
    "sg:postcode":"31705",
    "sg:province":"GA",
    "wof:name":"Antioch Baptist Church",
    "wof:placetype":"venue"
},
  "geometry": {"coordinates":[-84.014928,31.478232],"type":"Point"}
}