{
  "type": "Feature",
  "properties": {
    "iso:country":"US",
    "sg:address":"454 Cyrene Rd",
    "sg:city":"Bainbridge",
    "sg:classifiers":[
        {
            "category":"Insurance",
            "subcategory":"Hazard Insurance",
            "type":"Services"
        }
    ],
    "sg:phone":"+1 229 246 5506",
    "sg:postcode":"39817",
    "sg:province":"GA",
    "wof:name":"Charlie Livingston",
    "wof:placetype":"venue"
},
  "geometry": {"coordinates":[-84.69376800000001,30.963768],"type":"Point"}
}