{
  "type": "Feature",
  "properties": {
    "iso:country":"US",
    "sg:address":"3370 Sugarloaf Pkwy",
    "sg:city":"Lawrenceville",
    "sg:classifiers":[
        {
            "category":"Utilities",
            "subcategory":"Mobile Phone",
            "type":"Services"
        }
    ],
    "sg:phone":"+1 770 513 4299",
    "sg:postcode":"30044",
    "sg:province":"GA",
    "sg:tags":[
        "telephone",
        "cellular"
    ],
    "wof:name":"Rio Wireless",
    "wof:placetype":"venue"
},
  "geometry": {"coordinates":[-84.01706299999999,33.922792],"type":"Point"}
}