{
  "type": "Feature",
  "properties": {
    "iso:country":"US",
    "sg:address":"113 N 16th St",
    "sg:city":"Griffin",
    "sg:classifiers":[
        {
            "category":"Insurance",
            "subcategory":"Insurance Agent",
            "type":"Services"
        }
    ],
    "sg:phone":"+1 770 228 2341",
    "sg:postcode":"30223",
    "sg:province":"GA",
    "wof:name":"Farm Bureau Insurance",
    "wof:placetype":"venue"
},
  "geometry": {"coordinates":[-84.278085,33.250207],"type":"Point"}
}