{
  "type": "Feature",
  "properties": {
    "iso:country":"US",
    "sg:address":"2405 Beverly Hills Drive",
    "sg:city":"Atlanta",
    "sg:classifiers":[
        {
            "category":"Real Estate",
            "subcategory":"Real Estate Operator",
            "type":"Services"
        }
    ],
    "sg:phone":"+1 770 451 6566",
    "sg:postcode":"30341",
    "sg:province":"GA",
    "sg:tags":[
        "apartment"
    ],
    "wof:name":"Beverly Hills Apartments",
    "wof:placetype":"venue"
},
  "geometry": {"coordinates":[-84.289422,33.881433],"type":"Point"}
}