{
  "type": "Feature",
  "properties": {
    "iso:country":"US",
    "sg:address":"2957 Highway 85",
    "sg:city":"Senoia",
    "sg:classifiers":[
        {
            "category":"Restaurant",
            "type":"Food & Drink"
        }
    ],
    "sg:phone":"+1 770 599 0618",
    "sg:postcode":"30276",
    "sg:province":"GA",
    "wof:name":"Big Jim's Highway 85 Shack",
    "wof:placetype":"venue"
},
  "geometry": {"coordinates":[-84.54139000000001,33.296912],"type":"Point"}
}