{
  "type": "Feature",
  "properties": {
    "addr:full":"5750 Buford Hwy NE Atlanta GA 30340",
    "addr:housenumber":"5750",
    "addr:postcode":"30340",
    "addr:street":"Buford Hwy Ne",
    "iso:country":"US",
    "sg:address":"5750 Buford Hwy NE",
    "sg:city":"Atlanta",
    "sg:classifiers":[
        {
            "category":"Shopping",
            "subcategory":"Music",
            "type":"Retail Goods"
        }
    ],
    "sg:phone":"+1 770 455 1804",
    "sg:postcode":"30340",
    "sg:province":"GA",
    "sg:tags":[
        "cashing",
        "disc",
        "video",
        "tape",
        "check",
        "cassette"
    ],
    "wof:name":"Video Azteca",
    "wof:placetype":"venue"
},
  "geometry": {"coordinates":[-84.26807599999999,33.907884],"type":"Point"}
}