{
  "type": "Feature",
  "properties": {
    "iso:country":"US",
    "sg:address":"3384 Holcomb Bridge Rd",
    "sg:city":"Norcross",
    "sg:classifiers":[
        {
            "category":"Food & Beverages",
            "subcategory":"Bakery",
            "type":"Retail Goods"
        }
    ],
    "sg:phone":"+1 770 209 6642",
    "sg:postcode":"30092",
    "sg:province":"GA",
    "sg:tags":[
        "sandwich"
    ],
    "wof:name":"Firehouse Subs",
    "wof:placetype":"venue"
},
  "geometry": {"coordinates":[-84.24056400000001,33.951316],"type":"Point"}
}