{
  "type": "Feature",
  "properties": {
    "addr:full":"624 E Lee St Thomaston GA 30286",
    "addr:housenumber":"624",
    "addr:postcode":"30286",
    "addr:street":"E Lee St",
    "iso:country":"US",
    "sg:address":"624 E Lee St",
    "sg:city":"Thomaston",
    "sg:classifiers":[
        {
            "category":"Building & Trades",
            "subcategory":"Construction",
            "type":"Services"
        }
    ],
    "sg:phone":"+1 706 647 0606",
    "sg:postcode":"30286",
    "sg:province":"GA",
    "sg:tags":[
        "general",
        "contractor"
    ],
    "wof:name":"Mike English Contractors",
    "wof:placetype":"venue"
},
  "geometry": {"coordinates":[-84.319434,32.880009],"type":"Point"}
}