{
  "type": "Feature",
  "properties": {
    "addr:full":"937 Reed Ave Atlanta GA 30344",
    "addr:housenumber":"937",
    "addr:postcode":"30344",
    "addr:street":"Reed Ave",
    "iso:country":"US",
    "sg:address":"937 Reed Ave",
    "sg:city":"Atlanta",
    "sg:classifiers":[
        {
            "category":"Building & Trades",
            "subcategory":"Construction",
            "type":"Services"
        }
    ],
    "sg:phone":"+1 404 767 2928",
    "sg:postcode":"30344",
    "sg:province":"GA",
    "sg:tags":[
        "industrial",
        "contractor",
        "contractors-commercial",
        "masonry",
        "mason"
    ],
    "wof:name":"Joses Masonry Inc",
    "wof:placetype":"venue"
},
  "geometry": {"coordinates":[-84.419788,33.680221],"type":"Point"}
}