{
  "type": "Feature",
  "properties": {
    "iso:country":"US",
    "sg:address":"3229 Old Louisville Rd",
    "sg:city":"Augusta",
    "sg:classifiers":[
        {
            "category":"Social Services",
            "subcategory":"Adult Care",
            "type":"Services"
        }
    ],
    "sg:phone":"+1 706 796 8444",
    "sg:postcode":"30906",
    "sg:province":"GA",
    "sg:tags":[
        "home",
        "residential"
    ],
    "wof:name":"Ellen's Personal Care Home",
    "wof:placetype":"venue"
},
  "geometry": {"coordinates":[-82.01193499999999,33.40657],"type":"Point"}
}