{
  "type": "Feature",
  "properties": {
    "addr:full":"7955 North Point Pkwy Alpharetta GA 30022",
    "addr:housenumber":"7955",
    "addr:postcode":"30022",
    "addr:street":"North Point Pkwy",
    "iso:country":"US",
    "sg:address":"7955 North Point Pkwy",
    "sg:city":"Alpharetta",
    "sg:classifiers":[
        {
            "category":"Restaurant",
            "type":"Food & Drink"
        }
    ],
    "sg:phone":"+1 770 642 1933",
    "sg:postcode":"30022",
    "sg:province":"GA",
    "sg:tags":[
        "traditional",
        "american"
    ],
    "sg:website":"www.champps.com",
    "wof:name":"Champps",
    "wof:placetype":"venue"
},
  "geometry": {"coordinates":[-84.306257,34.038734],"type":"Point"}
}