{
  "type": "Feature",
  "properties": {
    "addr:full":"2314 N Slappey Blvd Albany GA 31701",
    "addr:housenumber":"2314",
    "addr:postcode":"31701",
    "addr:street":"N Slappey Blvd",
    "iso:country":"US",
    "sg:address":"2314 N Slappey Blvd",
    "sg:city":"Albany",
    "sg:classifiers":[
        {
            "category":"Retail",
            "subcategory":"Laundry & Dry Cleaning",
            "type":"Services"
        }
    ],
    "sg:phone":"+1 229 878 6023",
    "sg:postcode":"31701",
    "sg:province":"GA",
    "sg:tags":[
        "drycleaning",
        "plant"
    ],
    "wof:name":"Eagle Cleaners",
    "wof:placetype":"venue"
},
  "geometry": {"coordinates":[-84.175693,31.608726],"type":"Point"}
}