{
  "type": "Feature",
  "properties": {
    "addr:full":"1000 Parkwood Cir SE Atlanta GA 30339",
    "addr:housenumber":"1000",
    "addr:postcode":"30339",
    "addr:street":"Parkwood Cir Se",
    "iso:country":"US",
    "sg:address":"1000 Parkwood Cir SE",
    "sg:city":"Atlanta",
    "sg:classifiers":[
        {
            "category":"Professional",
            "subcategory":"Accounting & Tax Preparation",
            "type":"Services"
        }
    ],
    "sg:phone":"+1 770 850 0370",
    "sg:postcode":"30339",
    "sg:province":"GA",
    "sg:tags":[
        "consultant"
    ],
    "wof:name":"Du Charme Mc Millen & Assoc",
    "wof:placetype":"venue"
},
  "geometry": {"coordinates":[-84.45939199999999,33.903271],"type":"Point"}
}