{
  "type": "Feature",
  "properties": {
    "addr:full":"2804 Elton St Albany GA 31707",
    "addr:housenumber":"2804",
    "addr:postcode":"31707",
    "addr:street":"Elton St",
    "iso:country":"US",
    "sg:address":"2804 Elton St",
    "sg:city":"Albany",
    "sg:classifiers":[
        {
            "category":"Building & Trades",
            "subcategory":"Construction",
            "type":"Services"
        }
    ],
    "sg:phone":"+1 229 432 1002",
    "sg:postcode":"31707",
    "sg:province":"GA",
    "sg:tags":[
        "house"
    ],
    "wof:name":"Stringer Construction",
    "wof:placetype":"venue"
},
  "geometry": {"coordinates":[-84.195626,31.619827],"type":"Point"}
}