{
  "type": "Feature",
  "properties": {
    "addr:full":"2460 Moreland Ave SE Atlanta GA 30315",
    "addr:housenumber":"2460",
    "addr:postcode":"30315",
    "addr:street":"Moreland Ave Se",
    "iso:country":"US",
    "sg:address":"2460 Moreland Ave SE",
    "sg:city":"Atlanta",
    "sg:classifiers":[
        {
            "category":"Building & Trades",
            "subcategory":"Plumbing",
            "type":"Services"
        }
    ],
    "sg:phone":"+1 404 627 5783",
    "sg:postcode":"30315",
    "sg:province":"GA",
    "sg:tags":[
        "pluming",
        "contractor"
    ],
    "wof:name":"Kimble Plumbing Co Inc",
    "wof:placetype":"venue"
},
  "geometry": {"coordinates":[-84.348271,33.685204],"type":"Point"}
}