{
  "type": "Feature",
  "properties": {
    "iso:country":"US",
    "sg:address":"5720 Rockbridge Rd",
    "sg:city":"Stone Mountain",
    "sg:classifiers":[
        {
            "category":"Autos & Motor Vehicles",
            "subcategory":"Auto Supplies",
            "type":"Retail Goods"
        }
    ],
    "sg:phone":"+1 770 465 8811",
    "sg:postcode":"30087",
    "sg:province":"GA",
    "sg:tags":[
        "tire"
    ],
    "wof:name":"Kauffman Tire",
    "wof:placetype":"venue"
},
  "geometry": {"coordinates":[-84.15900600000001,33.78656],"type":"Point"}
}