{
  "type": "Feature",
  "properties": {
    "addr:full":"1000 Abernathy Rd NE Atlanta GA 30328",
    "addr:housenumber":"1000",
    "addr:postcode":"30328",
    "addr:street":"Abernathy Rd Ne",
    "iso:country":"US",
    "sg:address":"1000 Abernathy Rd NE",
    "sg:city":"Atlanta",
    "sg:classifiers":[
        {
            "category":"Professional",
            "subcategory":"Business Services",
            "type":"Services"
        }
    ],
    "sg:phone":"+1 770 392 1844",
    "sg:postcode":"30328",
    "sg:province":"GA",
    "sg:tags":[
        "recording",
        "studio"
    ],
    "wof:name":"BMG Distribution",
    "wof:placetype":"venue"
},
  "geometry": {"coordinates":[-84.352436,33.932905],"type":"Point"}
}