{
  "type": "Feature",
  "properties": {
    "addr:full":"500 S Columbia Dr Decatur GA 30030",
    "addr:housenumber":"500",
    "addr:postcode":"30030",
    "addr:street":"S Columbia Dr",
    "iso:country":"US",
    "sg:address":"500 S Columbia Dr",
    "sg:city":"Decatur",
    "sg:classifiers":[
        {
            "category":"Shopping",
            "subcategory":"Gifts & Souvenirs",
            "type":"Retail Goods"
        }
    ],
    "sg:phone":"+1 404 370 1565",
    "sg:postcode":"30030",
    "sg:province":"GA",
    "wof:name":"Umch Aux",
    "wof:placetype":"venue"
},
  "geometry": {"coordinates":[-84.280461,33.765401],"type":"Point"}
}