{
  "type": "Feature",
  "properties": {
    "addr:full":"537 Northridge Rd Atlanta GA 30350",
    "addr:housenumber":"537",
    "addr:postcode":"30350",
    "addr:street":"Northridge Rd",
    "iso:country":"US",
    "sg:address":"537 Northridge Rd",
    "sg:city":"Atlanta",
    "sg:classifiers":[
        {
            "category":"Organizations",
            "subcategory":"Non-profit Organization",
            "type":"Services"
        }
    ],
    "sg:phone":"+1 770 557 1250",
    "sg:postcode":"30350",
    "sg:province":"GA",
    "sg:tags":[
        "charity"
    ],
    "wof:name":"U Hope Cdc Inc",
    "wof:placetype":"venue"
},
  "geometry": {"coordinates":[-84.346159,33.981863],"type":"Point"}
}