{
  "type": "Feature",
  "properties": {
    "iso:country":"US",
    "sg:address":"142 Tiana Cir",
    "sg:city":"Savannah",
    "sg:classifiers":[
        {
            "category":"Building & Trades",
            "subcategory":"Construction",
            "type":"Services"
        }
    ],
    "sg:phone":"+1 912 351 9236",
    "sg:postcode":"31406",
    "sg:province":"GA",
    "sg:tags":[
        "house"
    ],
    "wof:name":"Sitework Construction LLC",
    "wof:placetype":"venue"
},
  "geometry": {"coordinates":[-81.081378,31.978724],"type":"Point"}
}