{
  "type": "Feature",
  "properties": {
    "addr:full":"746 Wheaton St Savannah GA 31401",
    "addr:housenumber":"746",
    "addr:postcode":"31401",
    "addr:street":"Wheaton St",
    "iso:country":"US",
    "sg:address":"746 Wheaton St",
    "sg:city":"Savannah",
    "sg:classifiers":[
        {
            "category":"Retail",
            "subcategory":"Auto Rental",
            "type":"Services"
        }
    ],
    "sg:phone":"+1 912 232 3798",
    "sg:postcode":"31401",
    "sg:province":"GA",
    "sg:tags":[
        "renting",
        "truck",
        "leasing"
    ],
    "wof:name":"Tico Manufacturing",
    "wof:placetype":"venue"
},
  "geometry": {"coordinates":[-81.08400899999999,32.07237],"type":"Point"}
}