{
  "type": "Feature",
  "properties": {
    "addr:full":"9014 Gardner Dr Alpharetta GA 30004",
    "addr:housenumber":"9014",
    "addr:postcode":"30004",
    "addr:street":"Gardner Dr",
    "iso:country":"US",
    "sg:address":"9014 Gardner Dr",
    "sg:city":"Alpharetta",
    "sg:classifiers":[
        {
            "category":"Professional",
            "type":"Services"
        }
    ],
    "sg:phone":"+1 770 475 8909",
    "sg:postcode":"30004",
    "sg:province":"GA",
    "wof:name":"CC Designs Inc",
    "wof:placetype":"venue"
},
  "geometry": {"coordinates":[-84.288106,34.06756],"type":"Point"}
}