{
  "type": "Feature",
  "properties": {
    "iso:country":"US",
    "sg:address":"104 E Point Dr",
    "sg:city":"Savannah",
    "sg:classifiers":[
        {
            "category":"Wholesale",
            "subcategory":"Apparel",
            "type":"Manufacturing & Wholesale Goods"
        }
    ],
    "sg:phone":"+1 912 898 0142",
    "sg:postcode":"31410",
    "sg:province":"GA",
    "sg:tags":[
        "footwear"
    ],
    "wof:name":"Woodies Sandles",
    "wof:placetype":"venue"
},
  "geometry": {"coordinates":[-80.96254500000001,32.035167],"type":"Point"}
}