{
  "type": "Feature",
  "properties": {
    "iso:country":"US",
    "sg:address":"8516 Main St",
    "sg:city":"Woodstock",
    "sg:classifiers":[
        {
            "category":"Personal",
            "subcategory":"Beauty Salon",
            "type":"Services"
        }
    ],
    "sg:phone":"+1 770 591 2079",
    "sg:postcode":"30188",
    "sg:province":"GA",
    "wof:name":"Salon Venessa",
    "wof:placetype":"venue"
},
  "geometry": {"coordinates":[-84.519177,34.102073],"type":"Point"}
}