{
  "type": "Feature",
  "properties": {
    "iso:country":"US",
    "sg:address":"3135 Gus Robinson Rd",
    "sg:city":"Powder Springs",
    "sg:classifiers":[
        {
            "category":"Building & Trades",
            "subcategory":"Construction",
            "type":"Services"
        }
    ],
    "sg:phone":"+1 678 908 4298",
    "sg:postcode":"30127",
    "sg:province":"GA",
    "sg:tags":[
        "hanging",
        "contractor"
    ],
    "wof:name":"A Womans Touch Decorating",
    "wof:placetype":"venue"
},
  "geometry": {"coordinates":[-84.64422500000001,33.906845],"type":"Point"}
}