{
  "type": "Feature",
  "properties": {
    "addr:full":"105 Emerald Way S Sparta GA 31087",
    "addr:housenumber":"105",
    "addr:postcode":"31087",
    "addr:street":"Emerald Way S",
    "iso:country":"US",
    "sg:address":"105 Emerald Way S",
    "sg:city":"Sparta",
    "sg:classifiers":[
        {
            "category":"Professional",
            "subcategory":"Management & Consulting",
            "type":"Services"
        },
        {
            "category":"Banks & Credit Unions",
            "subcategory":"Financial Services",
            "type":"Services"
        }
    ],
    "sg:phone":"+1 706 444 9543",
    "sg:postcode":"31087",
    "sg:province":"GA",
    "sg:tags":[
        "consultant",
        "financing",
        "planning"
    ],
    "wof:name":"James Tromza",
    "wof:placetype":"venue"
},
  "geometry": {"coordinates":[-83.236481,33.173585],"type":"Point"}
}