{
  "type": "Feature",
  "properties": {
    "addr:full":"1390 Bus Center Dr SW Conyers GA 30094",
    "addr:housenumber":"1390",
    "addr:postcode":"30094",
    "addr:street":"Bus Center Dr Sw",
    "iso:country":"US",
    "sg:address":"1390 Bus Center Dr SW",
    "sg:city":"Conyers",
    "sg:classifiers":[
        {
            "category":"Wholesale",
            "subcategory":"Groceries",
            "type":"Manufacturing & Wholesale Goods"
        }
    ],
    "sg:phone":"+1 770 761 4062",
    "sg:postcode":"30094",
    "sg:province":"GA",
    "sg:tags":[
        "confectionery",
        "candy"
    ],
    "wof:name":"Ruth Crisp Associates",
    "wof:placetype":"venue"
},
  "geometry": {"coordinates":[-84.022863,33.65475],"type":"Point"}
}