{
  "type": "Feature",
  "properties": {
    "iso:country":"US",
    "sg:address":"2615 Deep Springs Rd NE",
    "sg:city":"Dalton",
    "sg:classifiers":[
        {
            "category":"Wholesale",
            "subcategory":"Vending Machines",
            "type":"Manufacturing & Wholesale Goods"
        }
    ],
    "sg:phone":"+1 706 259 3487",
    "sg:postcode":"30721",
    "sg:province":"GA",
    "sg:tags":[
        "operator"
    ],
    "wof:name":"Select Vending Service",
    "wof:placetype":"venue"
},
  "geometry": {"coordinates":[-84.87611099999999,34.885391],"type":"Point"}
}