{
  "type": "Feature",
  "properties": {
    "iso:country":"US",
    "sg:address":"216 Bullsboro Dr",
    "sg:city":"Newnan",
    "sg:classifiers":[
        {
            "category":"Shopping",
            "subcategory":"Stationery & Office Supplies",
            "type":"Retail Goods"
        }
    ],
    "sg:phone":"+1 770 251 6280",
    "sg:postcode":"30263",
    "sg:province":"GA",
    "sg:tags":[
        "equipment",
        "microfilming"
    ],
    "wof:name":"Lason Systems",
    "wof:placetype":"venue"
},
  "geometry": {"coordinates":[-84.770667,33.391173],"type":"Point"}
}