{
  "type": "Feature",
  "properties": {
    "addr:full":"4225 Jonathan Ln Cumming GA 30040",
    "addr:housenumber":"4225",
    "addr:postcode":"30040",
    "addr:street":"Jonathan Ln",
    "iso:country":"US",
    "sg:address":"4225 Jonathan Ln",
    "sg:city":"Cumming",
    "sg:classifiers":[
        {
            "category":"Professional",
            "subcategory":"Art Services",
            "type":"Services"
        }
    ],
    "sg:phone":"+1 770 887 9930",
    "sg:postcode":"30040",
    "sg:province":"GA",
    "sg:tags":[
        "commercial",
        "design"
    ],
    "wof:name":"Modak Illustrations",
    "wof:placetype":"venue"
},
  "geometry": {"coordinates":[-84.121082,34.275713],"type":"Point"}
}