{
  "type": "Feature",
  "properties": {
    "addr:full":"2318 N Monroe St Albany GA 31701",
    "addr:housenumber":"2318",
    "addr:postcode":"31701",
    "addr:street":"N Monroe St",
    "iso:country":"US",
    "sg:address":"2318 N Monroe St",
    "sg:city":"Albany",
    "sg:classifiers":[
        {
            "category":"Retail",
            "subcategory":"Auto Repair",
            "type":"Services"
        }
    ],
    "sg:phone":"+1 229 435 6003",
    "sg:postcode":"31701",
    "sg:province":"GA",
    "sg:tags":[
        "automotive",
        "general"
    ],
    "wof:name":"Charleys Towing & Recovery",
    "wof:placetype":"venue"
},
  "geometry": {"coordinates":[-84.159964,31.606049],"type":"Point"}
}