{
  "type": "Feature",
  "properties": {
    "iso:country":"US",
    "sg:address":"2379 Adams Town Rd",
    "sg:city":"Bowersville",
    "sg:classifiers":[
        {
            "category":"Building & Trades",
            "subcategory":"Plumbing",
            "type":"Services"
        }
    ],
    "sg:phone":"+1 706 245 7429",
    "sg:postcode":"30516",
    "sg:province":"GA",
    "sg:tags":[
        "conditioning",
        "air",
        "system",
        "contractor"
    ],
    "wof:name":"J N Air Cond Htg Electrical",
    "wof:placetype":"venue"
},
  "geometry": {"coordinates":[-83.067295,34.384086],"type":"Point"}
}