{
  "type": "Feature",
  "properties": {
    "iso:country":"US",
    "sg:address":"1453 Straylott Rd",
    "sg:city":"Franklin",
    "sg:classifiers":[
        {
            "category":"Transit Center",
            "subcategory":"Freight",
            "type":"Transportation"
        },
        {
            "category":"Freight",
            "type":"Transportation"
        }
    ],
    "sg:phone":"+1 706 957 7054",
    "sg:postcode":"30217",
    "sg:province":"GA",
    "sg:tags":[
        "trucking-motor",
        "trucking"
    ],
    "wof:name":"Sweet Trucking",
    "wof:placetype":"venue"
},
  "geometry": {"coordinates":[-85.179936,33.2242],"type":"Point"}
}