{
  "type": "Feature",
  "properties": {
    "addr:full":"1189 Dorby Park Dr NE Atlanta GA 30319",
    "addr:housenumber":"1189",
    "addr:postcode":"30319",
    "addr:street":"Dorby Park Dr Ne",
    "iso:country":"US",
    "sg:address":"1189 Dorby Park Dr NE",
    "sg:city":"Atlanta",
    "sg:classifiers":[
        {
            "category":"Professional",
            "subcategory":"Lawyer & Legal Services",
            "type":"Services"
        }
    ],
    "sg:phone":"+1 404 266 9970",
    "sg:postcode":"30319",
    "sg:province":"GA",
    "wof:name":"S Scott Critzer PC",
    "wof:placetype":"venue"
},
  "geometry": {"coordinates":[-84.340288,33.871117],"type":"Point"}
}