{
  "type": "Feature",
  "properties": {
    "iso:country":"US",
    "sg:address":"708 W Broad Ave",
    "sg:city":"Albany",
    "sg:classifiers":[
        {
            "category":"Retail",
            "subcategory":"Auto Repair",
            "type":"Services"
        }
    ],
    "sg:phone":"+1 229 439 7083",
    "sg:postcode":"31701",
    "sg:province":"GA",
    "sg:tags":[
        "transmission",
        "automotive"
    ],
    "wof:name":"Aatco Transmission",
    "wof:placetype":"venue"
},
  "geometry": {"coordinates":[-84.16542800000001,31.576762],"type":"Point"}
}