{
  "type": "Feature",
  "properties": {
    "addr:full":"2247 Northlake Pkwy Tucker GA 30084",
    "addr:housenumber":"2247",
    "addr:postcode":"30084",
    "addr:street":"Northlake Pkwy",
    "iso:country":"US",
    "sg:address":"2247 Northlake Pkwy",
    "sg:city":"Tucker",
    "sg:classifiers":[
        {
            "category":"Professional",
            "subcategory":"Computer Services",
            "type":"Services"
        }
    ],
    "sg:phone":"+1 678 406 2272",
    "sg:postcode":"30084",
    "sg:province":"GA",
    "sg:tags":[
        "design",
        "system"
    ],
    "wof:name":"Amdocs Inc",
    "wof:placetype":"venue"
},
  "geometry": {"coordinates":[-84.244535,33.849402],"type":"Point"}
}