{
  "type": "Feature",
  "properties": {
    "iso:country":"US",
    "sg:address":"4086 Sweetwater Pkwy",
    "sg:city":"Ellenwood",
    "sg:classifiers":[
        {
            "category":"Real Estate",
            "subcategory":"Real Estate Agent",
            "type":"Services"
        }
    ],
    "sg:phone":"+1 404 244 0080",
    "sg:postcode":"30294",
    "sg:province":"GA",
    "sg:tags":[
        "investment"
    ],
    "wof:name":"Fortune 101 Inc",
    "wof:placetype":"venue"
},
  "geometry": {"coordinates":[-84.204909,33.656387],"type":"Point"}
}