{
  "type": "Feature",
  "properties": {
    "iso:country":"US",
    "sg:address":"543 N Davis Dr",
    "sg:city":"Warner Robins",
    "sg:classifiers":[
        {
            "category":"Retail",
            "subcategory":"Auto Repair",
            "type":"Services"
        }
    ],
    "sg:phone":"+1 478 225 2468",
    "sg:postcode":"31093",
    "sg:province":"GA",
    "sg:tags":[
        "body",
        "shop"
    ],
    "wof:name":"Houston Collision Center",
    "wof:placetype":"venue"
},
  "geometry": {"coordinates":[-83.61309799999999,32.633801],"type":"Point"}
}