{
  "type": "Feature",
  "properties": {
    "addr:full":"608 N Ashley St Valdosta GA 31601",
    "addr:housenumber":"608",
    "addr:postcode":"31601",
    "addr:street":"N Ashley St",
    "iso:country":"US",
    "sg:address":"608 N Ashley St",
    "sg:city":"Valdosta",
    "sg:classifiers":[
        {
            "category":"Personal",
            "subcategory":"Beauty Salon",
            "type":"Services"
        }
    ],
    "sg:phone":"+1 229 247 2800",
    "sg:postcode":"31601",
    "sg:province":"GA",
    "wof:name":"All Nationalities",
    "wof:placetype":"venue"
},
  "geometry": {"coordinates":[-83.279731,30.838449],"type":"Point"}
}