{
  "type": "Feature",
  "properties": {
    "addr:full":"26 Little Texas Valley Rd NE Rome GA 30165",
    "addr:housenumber":"26",
    "addr:postcode":"ga 30165",
    "addr:street":"Little Texas Valley Rd Ne",
    "iso:country":"US",
    "sg:address":"26 Little Texas Valley Rd NE",
    "sg:city":"Rome",
    "sg:classifiers":[
        {
            "category":"Organizations",
            "subcategory":"Religious Organization",
            "type":"Services"
        }
    ],
    "sg:phone":"+1 706 234 7363",
    "sg:postcode":"30165",
    "sg:province":"GA",
    "sg:tags":[
        "church"
    ],
    "wof:name":"Living Water Ministries",
    "wof:placetype":"venue"
},
  "geometry": {"coordinates":[-85.171967,34.371565],"type":"Point"}
}