{
  "type": "Feature",
  "properties": {
    "addr:full":"1285 Parker Rd SE Conyers GA 30094",
    "addr:housenumber":"1285",
    "addr:postcode":"30094",
    "addr:street":"Parker Rd Se",
    "iso:country":"US",
    "sg:address":"1285 Parker Rd SE",
    "sg:city":"Conyers",
    "sg:classifiers":[
        {
            "category":"Sports & Exercise",
            "subcategory":"Sports Center",
            "type":"Entertainment"
        }
    ],
    "sg:phone":"+1 770 670 1403",
    "sg:postcode":"30094",
    "sg:province":"GA",
    "sg:tags":[
        "amateur",
        "team"
    ],
    "wof:name":"Georgia Recreation & Park Assoc",
    "wof:placetype":"venue"
},
  "geometry": {"coordinates":[-84.020302,33.6562],"type":"Point"}
}