{
  "type": "Feature",
  "properties": {
    "addr:full":"660 Fair St SW Atlanta GA 30314",
    "addr:housenumber":"660",
    "addr:postcode":"30314",
    "addr:street":"Fair St Sw",
    "iso:country":"US",
    "sg:address":"660 Fair St SW",
    "sg:city":"Atlanta",
    "sg:classifiers":[
        {
            "category":"Government",
            "subcategory":"Office",
            "type":"Public Place"
        }
    ],
    "sg:phone":"+1 404 332 1529",
    "sg:postcode":"30314",
    "sg:province":"GA",
    "sg:tags":[
        "state",
        "program"
    ],
    "wof:name":"University Homes",
    "wof:placetype":"venue"
},
  "geometry": {"coordinates":[-84.409706,33.749256],"type":"Point"}
}