{
  "type": "Feature",
  "properties": {
    "addr:full":"536 Tatum Dr Alpharetta GA 30022",
    "addr:housenumber":"536",
    "addr:postcode":"30022",
    "addr:street":"Tatum Dr",
    "iso:country":"US",
    "sg:address":"536 Tatum Dr",
    "sg:city":"Alpharetta",
    "sg:classifiers":[
        {
            "category":"Building & Trades",
            "subcategory":"Locksmith",
            "type":"Services"
        }
    ],
    "sg:phone":"+1 678 259 1052",
    "sg:postcode":"30022",
    "sg:province":"GA",
    "sg:tags":[
        "key"
    ],
    "wof:name":"Locks A A A Locksmith",
    "wof:placetype":"venue"
},
  "geometry": {"coordinates":[-84.27247699999999,34.04603],"type":"Point"}
}