{
  "type": "Feature",
  "properties": {
    "iso:country":"US",
    "sg:address":"3852 McElroy Road",
    "sg:city":"Atlanta",
    "sg:classifiers":[
        {
            "category":"Real Estate",
            "subcategory":"Real Estate Operator",
            "type":"Services"
        }
    ],
    "sg:phone":"+1 770 457 6545",
    "sg:postcode":"30340",
    "sg:province":"GA",
    "sg:tags":[
        "apartment"
    ],
    "wof:name":"Foxwood Apartments",
    "wof:placetype":"venue"
},
  "geometry": {"coordinates":[-84.26612,33.905747],"type":"Point"}
}