{
  "type": "Feature",
  "properties": {
    "addr:full":"19 Griffin St Mcdonough GA 30253",
    "addr:housenumber":"19",
    "addr:postcode":"30253",
    "addr:street":"Griffin St",
    "iso:country":"US",
    "sg:address":"19 Griffin St",
    "sg:city":"Mcdonough",
    "sg:classifiers":[
        {
            "category":"Organizations",
            "subcategory":"Religious Organization",
            "type":"Services"
        }
    ],
    "sg:phone":"+1 770 914 7909",
    "sg:postcode":"30253",
    "sg:province":"GA",
    "sg:tags":[
        "church"
    ],
    "wof:name":"Agape International Ministries",
    "wof:placetype":"venue"
},
  "geometry": {"coordinates":[-84.147318,33.446569],"type":"Point"}
}