{
  "type": "Feature",
  "properties": {
    "iso:country":"US",
    "sg:address":"485 Womack Rd",
    "sg:city":"Covington",
    "sg:classifiers":[
        {
            "category":"Freight",
            "type":"Transportation"
        }
    ],
    "sg:phone":"+1 678 625 2913",
    "sg:postcode":"30016",
    "sg:province":"GA",
    "sg:tags":[
        "consultant"
    ],
    "wof:name":"Fulmer Brothers Inc",
    "wof:placetype":"venue"
},
  "geometry": {"coordinates":[-83.951199,33.598703],"type":"Point"}
}