{
  "type": "Feature",
  "properties": {
    "addr:full":"3144 Milford Chase SW Marietta GA 30008",
    "addr:housenumber":"3144",
    "addr:postcode":"30008",
    "addr:street":"Milford Chase Sw",
    "iso:country":"US",
    "sg:address":"3144 Milford Chase SW",
    "sg:city":"Marietta",
    "sg:classifiers":[
        {
            "category":"Building & Trades",
            "subcategory":"Construction",
            "type":"Services"
        }
    ],
    "sg:phone":"+1 770 714 7053",
    "sg:postcode":"30008",
    "sg:province":"GA",
    "sg:tags":[
        "house"
    ],
    "wof:name":"Contract & Analysis Svc Group",
    "wof:placetype":"venue"
},
  "geometry": {"coordinates":[-84.598023,33.877414],"type":"Point"}
}