{
  "type": "Feature",
  "properties": {
    "addr:full":"737 East Ave Cedartown GA 30125",
    "addr:housenumber":"737",
    "addr:postcode":"30125",
    "addr:street":"East Ave",
    "iso:country":"US",
    "sg:address":"737 East Ave",
    "sg:city":"Cedartown",
    "sg:classifiers":[
        {
            "category":"Insurance",
            "subcategory":"Insurance Agent",
            "type":"Services"
        }
    ],
    "sg:phone":"+1 770 749 0059",
    "sg:postcode":"30125",
    "sg:province":"GA",
    "wof:name":"Polk County Risk Reduction",
    "wof:placetype":"venue"
},
  "geometry": {"coordinates":[-85.24459299999999,34.014418],"type":"Point"}
}