{
  "type": "Feature",
  "properties": {
    "addr:full":"7 State Rte 157 Lookout Mountain GA 30750",
    "addr:housenumber":"7",
    "addr:postcode":"30750",
    "addr:street":"State Rte 157",
    "iso:country":"US",
    "sg:address":"7 State Rte 157",
    "sg:city":"Lookout Mountain",
    "sg:classifiers":[
        {
            "category":"Building & Trades",
            "subcategory":"Construction",
            "type":"Services"
        }
    ],
    "sg:phone":"+1 706 398 0616",
    "sg:postcode":"30750",
    "sg:province":"GA",
    "sg:tags":[
        "general",
        "contractor"
    ],
    "wof:name":"Vannoy Graham Construction Co",
    "wof:placetype":"venue"
},
  "geometry": {"coordinates":[-85.393542,34.927286],"type":"Point"}
}