{
  "type": "Feature",
  "properties": {
    "iso:country":"US",
    "sg:address":"2331 Sunnyview Ln",
    "sg:city":"Dacula",
    "sg:classifiers":[
        {
            "category":"Building & Trades",
            "subcategory":"Construction",
            "type":"Services"
        }
    ],
    "sg:phone":"+1 770 271 8645",
    "sg:postcode":"30019",
    "sg:province":"GA",
    "sg:tags":[
        "builder",
        "patio",
        "deck"
    ],
    "wof:name":"Decks By Dave",
    "wof:placetype":"venue"
},
  "geometry": {"coordinates":[-83.926663,34.065475],"type":"Point"}
}