{
  "type": "Feature",
  "properties": {
    "addr:full":"456 Neverland Trl Cleveland GA 30528",
    "addr:housenumber":"456",
    "addr:postcode":"30528",
    "addr:street":"Neverland Trl",
    "iso:country":"US",
    "sg:address":"456 Neverland Trl",
    "sg:city":"Cleveland",
    "sg:classifiers":[
        {
            "category":"Professional",
            "subcategory":"Management & Consulting",
            "type":"Services"
        }
    ],
    "sg:phone":"+1 706 865 7549",
    "sg:postcode":"30528",
    "sg:province":"GA",
    "wof:name":"Moon Mountain Studio",
    "wof:placetype":"venue"
},
  "geometry": {"coordinates":[-83.88811099999999,34.650384],"type":"Point"}
}