{
  "type": "Feature",
  "properties": {
    "iso:country":"US",
    "sg:address":"73 W Fairmont Ave",
    "sg:city":"Savannah",
    "sg:classifiers":[
        {
            "category":"Professional",
            "type":"Services"
        }
    ],
    "sg:phone":"+1 912 925 1902",
    "sg:postcode":"31406",
    "sg:province":"GA",
    "wof:name":"Imrg LLC",
    "wof:placetype":"venue"
},
  "geometry": {"coordinates":[-81.123265,32.000578],"type":"Point"}
}