{
  "type": "Feature",
  "properties": {
    "iso:country":"US",
    "sg:address":"220 Briarvista Way NE",
    "sg:city":"Atlanta",
    "sg:classifiers":[
        {
            "category":"Building & Trades",
            "subcategory":"Electrical",
            "type":"Services"
        }
    ],
    "sg:phone":"+1 404 929 7288",
    "sg:postcode":"30329",
    "sg:province":"GA",
    "sg:tags":[
        "electrician"
    ],
    "wof:name":"Atlanta Electrical & Controls Inc",
    "wof:placetype":"venue"
},
  "geometry": {"coordinates":[-84.331841,33.814309],"type":"Point"}
}