{
  "type": "Feature",
  "properties": {
    "addr:full":"242 Treadwell Rd Chatsworth GA 30705",
    "addr:housenumber":"242",
    "addr:postcode":"30705",
    "addr:street":"Treadwell Rd",
    "iso:country":"US",
    "sg:address":"242 Treadwell Rd",
    "sg:city":"Chatsworth",
    "sg:classifiers":[
        {
            "category":"Wholesale",
            "subcategory":"Home Furnishings",
            "type":"Manufacturing & Wholesale Goods"
        }
    ],
    "sg:phone":"+1 706 695 3414",
    "sg:postcode":"30705",
    "sg:province":"GA",
    "sg:tags":[
        "rug",
        "carpet"
    ],
    "wof:name":"Omega Pattern Works",
    "wof:placetype":"venue"
},
  "geometry": {"coordinates":[-84.80027800000001,34.780477],"type":"Point"}
}