{
  "type": "Feature",
  "properties": {
    "addr:full":"200 Lafayette Pkwy Lagrange GA 30241",
    "addr:housenumber":"200",
    "addr:postcode":"30241",
    "addr:street":"Lafayette Pkwy",
    "iso:country":"US",
    "sg:address":"200 Lafayette Pkwy",
    "sg:city":"Lagrange",
    "sg:classifiers":[
        {
            "category":"Organizations",
            "subcategory":"Religious Organization",
            "type":"Services"
        }
    ],
    "sg:phone":"+1 706 884 4224",
    "sg:postcode":"30241",
    "sg:province":"GA",
    "sg:tags":[
        "church"
    ],
    "wof:name":"St Peter's Catholic Church",
    "wof:placetype":"venue"
},
  "geometry": {"coordinates":[-85.026465,33.038781],"type":"Point"}
}