{
  "type": "Feature",
  "properties": {
    "addr:full":"4820 Clark Howell Hwy Atlanta GA 30349",
    "addr:housenumber":"4820",
    "addr:postcode":"30349",
    "addr:street":"Clark Howell Hwy",
    "iso:country":"US",
    "sg:address":"4820 Clark Howell Hwy",
    "sg:city":"Atlanta",
    "sg:classifiers":[
        {
            "category":"Food & Beverages",
            "subcategory":"Supermarket",
            "type":"Retail Goods"
        }
    ],
    "sg:phone":"+1 404 305 8887",
    "sg:postcode":"30349",
    "sg:province":"GA",
    "sg:tags":[
        "super",
        "store"
    ],
    "wof:name":"Dhl - Atl",
    "wof:placetype":"venue"
},
  "geometry": {"coordinates":[-84.408726,33.623789],"type":"Point"}
}