{
  "type": "Feature",
  "properties": {
    "addr:full":"115 E Hendry St Hinesville GA 31313",
    "addr:housenumber":"115",
    "addr:postcode":"31313",
    "addr:street":"E Hendry St",
    "iso:country":"US",
    "sg:address":"115 E Hendry St",
    "sg:city":"Hinesville",
    "sg:classifiers":[
        {
            "category":"Professional",
            "subcategory":"Employment Agencies",
            "type":"Services"
        }
    ],
    "sg:phone":"+1 912 368 5627",
    "sg:postcode":"31313",
    "sg:province":"GA",
    "sg:tags":[
        "help",
        "supply"
    ],
    "wof:name":"Hinesvlle Job Sarch Assist Ctr",
    "wof:placetype":"venue"
},
  "geometry": {"coordinates":[-81.593812,31.84342],"type":"Point"}
}