{
  "type": "Feature",
  "properties": {
    "addr:full":"815 Houston Mill Rd NE Atlanta GA 30329",
    "addr:housenumber":"815",
    "addr:postcode":"30329",
    "addr:street":"Houston Mill Rd Ne",
    "iso:country":"US",
    "sg:address":"815 Houston Mill Rd NE",
    "sg:city":"Atlanta",
    "sg:classifiers":[
        {
            "category":"Education",
            "subcategory":"College",
            "type":"Public Place"
        },
        {
            "category":"Organizations",
            "subcategory":"Community Association",
            "type":"Services"
        }
    ],
    "sg:phone":"+1 404 727 6400",
    "sg:postcode":"30329",
    "sg:province":"GA",
    "sg:tags":[
        "academic",
        "school"
    ],
    "sg:website":"www.alumni.emory.edu",
    "wof:name":"Association of Emory Alumni",
    "wof:placetype":"venue"
},
  "geometry": {"coordinates":[-84.32277000000001,33.801533],"type":"Point"}
}