{
  "type": "Feature",
  "properties": {
    "iso:country":"US",
    "sg:address":"1324 Athens Rd",
    "sg:city":"Crawford",
    "sg:classifiers":[
        {
            "category":"Retail",
            "subcategory":"Auto Repair",
            "type":"Services"
        }
    ],
    "sg:phone":"+1 706 743 5500",
    "sg:postcode":"30630",
    "sg:province":"GA",
    "sg:tags":[
        "body"
    ],
    "wof:name":"Mixon Used Cars & Body Shop",
    "wof:placetype":"venue"
},
  "geometry": {"coordinates":[-83.194261,33.891435],"type":"Point"}
}