{
  "type": "Feature",
  "properties": {
    "iso:country":"US",
    "sg:address":"671 Lumpkin Campground Rd S",
    "sg:city":"Dawsonville",
    "sg:classifiers":[
        {
            "category":"Restaurant",
            "type":"Food & Drink"
        }
    ],
    "sg:phone":"+1 706 216 7370",
    "sg:postcode":"30534",
    "sg:province":"GA",
    "wof:name":"Tuscany Restaurant",
    "wof:placetype":"venue"
},
  "geometry": {"coordinates":[-84.04931000000001,34.360784],"type":"Point"}
}