{
  "type": "Feature",
  "properties": {
    "iso:country":"US",
    "sg:address":"79 5th St NW",
    "sg:city":"Atlanta",
    "sg:classifiers":[
        {
            "category":"Landmark",
            "subcategory":"Historic",
            "type":"Public Place"
        }
    ],
    "sg:postcode":"30308",
    "sg:province":"GA",
    "sg:tags":[
        "building",
        "historical"
    ],
    "sg:website":"www.gatech.edu/technology-square",
    "wof:name":"Tech Square",
    "wof:placetype":"venue"
},
  "geometry": {"coordinates":[-84.389715,33.776836],"type":"Point"}
}