{
  "type": "Feature",
  "properties": {
    "iso:country":"US",
    "sg:address":"2589 Oak Cir",
    "sg:city":"Ellenwood",
    "sg:classifiers":[
        {
            "category":"Home & Garden",
            "subcategory":"Building Materials",
            "type":"Retail Goods"
        }
    ],
    "sg:phone":"+1 404 366 8607",
    "sg:postcode":"30294",
    "sg:province":"GA",
    "sg:tags":[
        "glass",
        "window",
        "plate"
    ],
    "wof:name":"B H Glass",
    "wof:placetype":"venue"
},
  "geometry": {"coordinates":[-84.30526,33.622472],"type":"Point"}
}