{
  "type": "Feature",
  "properties": {
    "iso:country":"US",
    "sg:address":"3259 Somerset Trce",
    "sg:city":"Marietta",
    "sg:classifiers":[
        {
            "category":"Professional",
            "subcategory":"Management & Consulting",
            "type":"Services"
        }
    ],
    "sg:phone":"+1 770 937 9996",
    "sg:postcode":"30067",
    "sg:province":"GA",
    "sg:tags":[
        "business"
    ],
    "wof:name":"Bing Eng Consulting",
    "wof:placetype":"venue"
},
  "geometry": {"coordinates":[-84.457902,33.941579],"type":"Point"}
}