{
  "type": "Feature",
  "properties": {
    "addr:full":"11720 Medlock Bridge Rd Ste 155 Duluth GA 30097",
    "addr:housenumber":"11720",
    "addr:postcode":"30097",
    "addr:street":"Medlock Bridge Rd Ste 155",
    "iso:country":"US",
    "sg:address":"11720 Medlock Bridge Rd Ste 155",
    "sg:city":"Duluth",
    "sg:classifiers":[
        {
            "category":"Building & Trades",
            "subcategory":"Construction",
            "type":"Services"
        }
    ],
    "sg:phone":"+1 770 622 5120",
    "sg:postcode":"30097",
    "sg:province":"GA",
    "sg:tags":[
        "interior",
        "design"
    ],
    "sg:website":"www.dotitemecula.com",
    "wof:name":"Designs of the Interior",
    "wof:placetype":"venue"
},
  "geometry": {"coordinates":[-84.169827,34.065508],"type":"Point"}
}