{
  "type": "Feature",
  "properties": {
    "iso:country":"US",
    "sg:address":"210 Stovall St SE",
    "sg:city":"Atlanta",
    "sg:classifiers":[
        {
            "category":"Retail",
            "subcategory":"Auto Repair",
            "type":"Services"
        }
    ],
    "sg:phone":"+1 404 880 9362",
    "sg:postcode":"30316",
    "sg:province":"GA",
    "sg:tags":[
        "automotive"
    ],
    "wof:name":"Mr Mobile Emergency Road Serv",
    "wof:placetype":"venue"
},
  "geometry": {"coordinates":[-84.35426699999999,33.747674],"type":"Point"}
}