{
  "type": "Feature",
  "properties": {
    "addr:full":"4092 Mill Creek Gate Kennesaw GA 30144",
    "addr:housenumber":"4092",
    "addr:postcode":"30144",
    "addr:street":"Mill Creek Gate",
    "iso:country":"US",
    "sg:address":"4092 Mill Creek Gate",
    "sg:city":"Kennesaw",
    "sg:classifiers":[
        {
            "category":"Shopping",
            "subcategory":"Catalog Store",
            "type":"Retail Goods"
        }
    ],
    "sg:phone":"+1 770 419 8587",
    "sg:postcode":"30144",
    "sg:province":"GA",
    "sg:tags":[
        "marketing",
        "general",
        "mail",
        "order",
        "merchandise",
        "con"
    ],
    "wof:name":"Increasalescom",
    "wof:placetype":"venue"
},
  "geometry": {"coordinates":[-84.632065,34.051794],"type":"Point"}
}