{
  "type": "Feature",
  "properties": {
    "iso:country":"US",
    "sg:address":"1417 Chattahoochee Ave NW",
    "sg:city":"Atlanta",
    "sg:classifiers":[
        {
            "category":"Shopping",
            "subcategory":"Used Merchandise",
            "type":"Retail Goods"
        }
    ],
    "sg:phone":"+1 404 355 7576",
    "sg:postcode":"30318",
    "sg:province":"GA",
    "wof:name":"Debris Antiques",
    "wof:placetype":"venue"
},
  "geometry": {"coordinates":[-84.434365,33.806051],"type":"Point"}
}