{
  "type": "Feature",
  "properties": {
    "addr:full":"6851 Shannon Pkwy Union City GA 30291",
    "addr:housenumber":"6851",
    "addr:postcode":"30291",
    "addr:street":"Shannon Pkwy",
    "iso:country":"US",
    "sg:address":"6851 Shannon Pkwy",
    "sg:city":"Union City",
    "sg:classifiers":[
        {
            "category":"Banks & Credit Unions",
            "subcategory":"Bank",
            "type":"Services"
        }
    ],
    "sg:phone":"+1 770 306 1884",
    "sg:postcode":"30291",
    "sg:province":"GA",
    "sg:tags":[
        "personal",
        "institution"
    ],
    "wof:name":"Advance America",
    "wof:placetype":"venue"
},
  "geometry": {"coordinates":[-84.539387,33.56928],"type":"Point"}
}