{
  "type": "Feature",
  "properties": {
    "addr:full":"2679 Peachtree Sq Atlanta GA 30360",
    "addr:housenumber":"2679",
    "addr:postcode":"30360",
    "addr:street":"Peachtree Sq",
    "iso:country":"US",
    "sg:address":"2679 Peachtree Sq",
    "sg:city":"Atlanta",
    "sg:classifiers":[
        {
            "category":"Local Transit",
            "type":"Transportation"
        }
    ],
    "sg:phone":"+1 770 458 3292",
    "sg:postcode":"30360",
    "sg:province":"GA",
    "sg:tags":[
        "limousine"
    ],
    "wof:name":"Atlanta Chauffeur",
    "wof:placetype":"venue"
},
  "geometry": {"coordinates":[-84.276532,33.923504],"type":"Point"}
}