{
  "type": "Feature",
  "properties": {
    "iso:country":"US",
    "sg:address":"100 Vicarage Ct",
    "sg:city":"Alpharetta",
    "sg:classifiers":[
        {
            "category":"Building & Trades",
            "subcategory":"Locksmith",
            "type":"Services"
        }
    ],
    "sg:phone":"+1 678 259 9781",
    "sg:postcode":"30005",
    "sg:province":"GA",
    "sg:tags":[
        "key"
    ],
    "wof:name":"1 1 24 A Emergency A Locksmith",
    "wof:placetype":"venue"
},
  "geometry": {"coordinates":[-84.19725699999999,34.086254],"type":"Point"}
}