{
  "type": "Feature",
  "properties": {
    "iso:country":"US",
    "sg:address":"751 Country Ln",
    "sg:city":"Lake Park",
    "sg:classifiers":[
        {
            "category":"Government",
            "subcategory":"Office",
            "type":"Public Place"
        }
    ],
    "sg:phone":"+1 229 559 6470",
    "sg:postcode":"31636",
    "sg:province":"GA",
    "wof:name":"Lake Park Clinic",
    "wof:placetype":"venue"
},
  "geometry": {"coordinates":[-83.212547,30.684752],"type":"Point"}
}