{
  "type": "Feature",
  "properties": {
    "iso:country":"US",
    "sg:address":"2024 Luther Bailey Rd",
    "sg:city":"Senoia",
    "sg:classifiers":[
        {
            "category":"Personal",
            "subcategory":"Beauty Salon",
            "type":"Services"
        }
    ],
    "sg:phone":"+1 770 599 0491",
    "sg:postcode":"30276",
    "sg:province":"GA",
    "sg:tags":[
        "shop"
    ],
    "wof:name":"Hair Illusions Inc",
    "wof:placetype":"venue"
},
  "geometry": {"coordinates":[-84.600055,33.260324],"type":"Point"}
}