{
  "type": "Feature",
  "properties": {
    "addr:full":"1610 Gibbs Dr Gainesville GA 30507",
    "addr:housenumber":"1610",
    "addr:postcode":"30507",
    "addr:street":"Gibbs Dr",
    "iso:country":"US",
    "sg:address":"1610 Gibbs Dr",
    "sg:city":"Gainesville",
    "sg:classifiers":[
        {
            "category":"Retail",
            "subcategory":"Laundry & Dry Cleaning",
            "type":"Services"
        },
        {
            "category":"Building & Trades",
            "subcategory":"Construction",
            "type":"Services"
        }
    ],
    "sg:phone":"+1 770 536 9258",
    "sg:postcode":"30507",
    "sg:province":"GA",
    "sg:tags":[
        "fire",
        "damage",
        "restoration",
        "carpet",
        "coin",
        "furniture"
    ],
    "wof:name":"Clean Way Inc",
    "wof:placetype":"venue"
},
  "geometry": {"coordinates":[-83.812416,34.241089],"type":"Point"}
}