{
  "type": "Feature",
  "properties": {
    "addr:full":"150 Avalon Rd Covington GA 30014",
    "addr:housenumber":"150",
    "addr:postcode":"30014",
    "addr:street":"Avalon Rd",
    "iso:country":"US",
    "sg:address":"150 Avalon Rd",
    "sg:city":"Covington",
    "sg:classifiers":[
        {
            "category":"Building & Trades",
            "subcategory":"Plumbing",
            "type":"Services"
        }
    ],
    "sg:phone":"+1 770 788 1199",
    "sg:postcode":"30014",
    "sg:province":"GA",
    "sg:tags":[
        "contractor"
    ],
    "wof:name":"Lance White Heating & A/C Inc",
    "wof:placetype":"venue"
},
  "geometry": {"coordinates":[-83.807799,33.491991],"type":"Point"}
}