{
  "type": "Feature",
  "properties": {
    "addr:full":"4071 Brockett Creek Ct Tucker GA 30084",
    "addr:housenumber":"4071",
    "addr:postcode":"30084",
    "addr:street":"Brockett Creek Ct",
    "iso:country":"US",
    "sg:address":"4071 Brockett Creek Ct",
    "sg:city":"Tucker",
    "sg:classifiers":[
        {
            "category":"Building & Trades",
            "subcategory":"Construction",
            "type":"Services"
        }
    ],
    "sg:phone":"+1 770 939 8016",
    "sg:postcode":"30084",
    "sg:province":"GA",
    "sg:tags":[
        "house"
    ],
    "wof:name":"L R Construction Services Inc",
    "wof:placetype":"venue"
},
  "geometry": {"coordinates":[-84.221136,33.838361],"type":"Point"}
}