{
  "type": "Feature",
  "properties": {
    "addr:full":"604 N Monroe St Albany GA 31701",
    "addr:housenumber":"604",
    "addr:postcode":"31701",
    "addr:street":"N Monroe St",
    "iso:country":"US",
    "sg:address":"604 N Monroe St",
    "sg:city":"Albany",
    "sg:classifiers":[
        {
            "category":"Shopping",
            "subcategory":"Used Merchandise",
            "type":"Retail Goods"
        }
    ],
    "sg:phone":"+1 229 431 1125",
    "sg:postcode":"31701",
    "sg:province":"GA",
    "wof:name":"Thrift Store",
    "wof:placetype":"venue"
},
  "geometry": {"coordinates":[-84.158947,31.586038],"type":"Point"}
}