{
  "type": "Feature",
  "properties": {
    "addr:full":"1973 Highway 34 E Newnan GA 30265",
    "addr:housenumber":"1973",
    "addr:postcode":"30265",
    "addr:street":"Highway 34 E",
    "iso:country":"US",
    "sg:address":"1973 Highway 34 E",
    "sg:city":"Newnan",
    "sg:phone":"+1 770 253 8636",
    "sg:postcode":"30265",
    "sg:province":"GA",
    "sg:website":"http://www.lisarobertslaw.com",
    "wof:name":"Roberts, Lisa R",
    "wof:placetype":"venue"
},
  "geometry": {"coordinates":[-84.702702,33.405234],"type":"Point"}
}