{
  "type": "Feature",
  "properties": {
    "iso:country":"US",
    "sg:address":"16942 State Rte 67",
    "sg:city":"Statesboro",
    "sg:classifiers":[
        {
            "category":"Organizations",
            "subcategory":"Community Association",
            "type":"Services"
        }
    ],
    "sg:phone":"+1 912 681 7342",
    "sg:postcode":"30458",
    "sg:province":"GA",
    "sg:tags":[
        "club"
    ],
    "wof:name":"Kiwanis Club Community Bldg",
    "wof:placetype":"venue"
},
  "geometry": {"coordinates":[-81.80304,32.478896],"type":"Point"}
}