{
  "type": "Feature",
  "properties": {
    "iso:country":"US",
    "sg:address":"9180 Brookshire Rd",
    "sg:city":"Gainesville",
    "sg:classifiers":[
        {
            "category":"Building & Trades",
            "subcategory":"Construction",
            "type":"Services"
        }
    ],
    "sg:phone":"+1 770 844 8889",
    "sg:postcode":"30506",
    "sg:province":"GA",
    "sg:tags":[
        "general",
        "contractor"
    ],
    "wof:name":"KAN Development",
    "wof:placetype":"venue"
},
  "geometry": {"coordinates":[-83.945046,34.286177],"type":"Point"}
}