{
  "type": "Feature",
  "properties": {
    "iso:country":"US",
    "sg:address":"777 Clarktown Rd",
    "sg:city":"Richmond Hill",
    "sg:classifiers":[
        {
            "category":"Retail",
            "subcategory":"Repair Shop",
            "type":"Services"
        }
    ],
    "sg:phone":"+1 912 355 4404",
    "sg:postcode":"31324",
    "sg:province":"GA",
    "sg:tags":[
        "upholsterer"
    ],
    "wof:name":"Kinard Upholstery Co",
    "wof:placetype":"venue"
},
  "geometry": {"coordinates":[-81.384681,31.910477],"type":"Point"}
}