{
  "type": "Feature",
  "properties": {
    "iso:country":"US",
    "sg:address":"3159 Mill St SE",
    "sg:city":"Covington",
    "sg:classifiers":[
        {
            "category":"Personal",
            "subcategory":"Beauty Salon",
            "type":"Services"
        }
    ],
    "sg:phone":"+1 770 786 6440",
    "sg:postcode":"30014",
    "sg:province":"GA",
    "wof:name":"Mason's Cuts & Styles",
    "wof:placetype":"venue"
},
  "geometry": {"coordinates":[-83.85066,33.594161],"type":"Point"}
}