{
  "type": "Feature",
  "properties": {
    "iso:country":"US",
    "sg:address":"3319 Sylvester Hwy",
    "sg:city":"Albany",
    "sg:classifiers":[
        {
            "category":"Retail",
            "subcategory":"Auto Repair",
            "type":"Services"
        }
    ],
    "sg:phone":"+1 229 878 0550",
    "sg:postcode":"31705",
    "sg:province":"GA",
    "sg:tags":[
        "transmission",
        "tractor",
        "general"
    ],
    "wof:name":"Ced's Auto & Truck Repair",
    "wof:placetype":"venue"
},
  "geometry": {"coordinates":[-84.052209,31.572595],"type":"Point"}
}