{
  "type": "Feature",
  "properties": {
    "addr:full":"200 Rolling Meadows Trl Fayetteville GA 30215",
    "addr:housenumber":"200",
    "addr:postcode":"30215",
    "addr:street":"Rolling Meadows Trl",
    "iso:country":"US",
    "sg:address":"200 Rolling Meadows Trl",
    "sg:city":"Fayetteville",
    "sg:classifiers":[
        {
            "category":"Wholesale",
            "subcategory":"Machinery & Supplies",
            "type":"Manufacturing & Wholesale Goods"
        }
    ],
    "sg:phone":"+1 770 461 0900",
    "sg:postcode":"30215",
    "sg:province":"GA",
    "sg:tags":[
        "police",
        "mfg",
        "fire",
        "rep",
        "equipment",
        "safety",
        "department"
    ],
    "wof:name":"Dixie Marketing Associates",
    "wof:placetype":"venue"
},
  "geometry": {"coordinates":[-84.477735,33.407381],"type":"Point"}
}