{
  "type": "Feature",
  "properties": {
    "addr:full":"100 Colony Park Dr Cumming GA 30040",
    "addr:housenumber":"100",
    "addr:postcode":"30040",
    "addr:street":"Colony Park Dr",
    "iso:country":"US",
    "sg:address":"100 Colony Park Dr",
    "sg:city":"Cumming",
    "sg:classifiers":[
        {
            "category":"Real Estate",
            "subcategory":"Real Estate Agent",
            "type":"Services"
        }
    ],
    "sg:phone":"+1 770 889 4080",
    "sg:postcode":"30040",
    "sg:province":"GA",
    "sg:website":"www.coldwellbanker.com",
    "wof:name":"French Properties",
    "wof:placetype":"venue"
},
  "geometry": {"coordinates":[-84.134216,34.193916],"type":"Point"}
}