{
  "type": "Feature",
  "properties": {
    "addr:full":"6854 Main St Lithonia GA 30058",
    "addr:housenumber":"6854",
    "addr:postcode":"30058",
    "addr:street":"Main St",
    "iso:country":"US",
    "sg:address":"6854 Main St",
    "sg:city":"Lithonia",
    "sg:classifiers":[
        {
            "category":"Education",
            "subcategory":"School",
            "type":"Public Place"
        }
    ],
    "sg:phone":"+1 770 484 3439",
    "sg:postcode":"30058",
    "sg:province":"GA",
    "wof:name":"Christian Pebbles Academy",
    "wof:placetype":"venue"
},
  "geometry": {"coordinates":[-84.109582,33.709708],"type":"Point"}
}