{
  "type": "Feature",
  "properties": {
    "iso:country":"US",
    "sg:address":"21 Waverly Ln",
    "sg:city":"Winder",
    "sg:classifiers":[
        {
            "category":"Professional",
            "type":"Services"
        }
    ],
    "sg:phone":"+1 770 725 9811",
    "sg:postcode":"30680",
    "sg:province":"GA",
    "sg:tags":[
        "establishment"
    ],
    "wof:name":"Agreturns Corp",
    "wof:placetype":"venue"
},
  "geometry": {"coordinates":[-83.693872,34.002204],"type":"Point"}
}