{
  "type": "Feature",
  "properties": {
    "addr:full":"1271 Gray Hwy Macon GA 31211",
    "addr:housenumber":"1271",
    "addr:postcode":"31211",
    "addr:street":"Gray Hwy",
    "iso:country":"US",
    "sg:address":"1271 Gray Hwy",
    "sg:city":"Macon",
    "sg:classifiers":[
        {
            "category":"Shopping",
            "subcategory":"Pharmacy",
            "type":"Retail Goods"
        }
    ],
    "sg:phone":"+1 478 746 3219",
    "sg:postcode":"31211",
    "sg:province":"GA",
    "wof:name":"CVS",
    "wof:placetype":"venue"
},
  "geometry": {"coordinates":[-83.61500100000001,32.859396],"type":"Point"}
}