{
  "type": "Feature",
  "properties": {
    "iso:country":"US",
    "sg:address":"114 Lake Ave",
    "sg:city":"East Dublin",
    "sg:classifiers":[
        {
            "category":"Building & Trades",
            "subcategory":"Construction",
            "type":"Services"
        }
    ],
    "sg:phone":"+1 478 272 1452",
    "sg:postcode":"31027",
    "sg:province":"GA",
    "sg:tags":[
        "downspouts",
        "gutter"
    ],
    "wof:name":"Home Exterior Of Georgia Inc",
    "wof:placetype":"venue"
},
  "geometry": {"coordinates":[-82.869591,32.546259],"type":"Point"}
}