{
  "type": "Feature",
  "properties": {
    "addr:full":"4327 E Conway Dr NW Atlanta GA 30327",
    "addr:housenumber":"4327",
    "addr:postcode":"30327",
    "addr:street":"E Conway Dr Nw",
    "iso:country":"US",
    "sg:address":"4327 E Conway Dr NW",
    "sg:city":"Atlanta",
    "sg:classifiers":[
        {
            "category":"Building & Trades",
            "subcategory":"Construction",
            "type":"Services"
        }
    ],
    "sg:phone":"+1 404 705 9091",
    "sg:postcode":"30327",
    "sg:province":"GA",
    "sg:tags":[
        "contractor"
    ],
    "wof:name":"Piedmont Builders",
    "wof:placetype":"venue"
},
  "geometry": {"coordinates":[-84.40635399999999,33.873512],"type":"Point"}
}