{
  "type": "Feature",
  "properties": {
    "iso:country":"US",
    "sg:address":"830 Rose Brooke Dr",
    "sg:city":"Lawrenceville",
    "sg:classifiers":[
        {
            "category":"Personal",
            "subcategory":"Nail Salon",
            "type":"Services"
        }
    ],
    "sg:phone":"+1 770 985 4375",
    "sg:postcode":"30045",
    "sg:province":"GA",
    "wof:name":"J & P Diamond Nail",
    "wof:placetype":"venue"
},
  "geometry": {"coordinates":[-83.98410800000001,33.910223],"type":"Point"}
}