{
  "type": "Feature",
  "properties": {
    "addr:full":"1384 Greene St Augusta GA 30901",
    "addr:housenumber":"1384",
    "addr:postcode":"30901",
    "addr:street":"Greene St",
    "iso:country":"US",
    "sg:address":"1384 Greene St",
    "sg:city":"Augusta",
    "sg:classifiers":[
        {
            "category":"Health Services",
            "subcategory":"Doctor",
            "type":"Services"
        }
    ],
    "sg:phone":"+1 706 828 3444",
    "sg:postcode":"30901",
    "sg:province":"GA",
    "sg:tags":[
        "medical"
    ],
    "wof:name":"Saint Vincent Depaul Health CL",
    "wof:placetype":"venue"
},
  "geometry": {"coordinates":[-81.979536,33.477656],"type":"Point"}
}