{
  "type": "Feature",
  "properties": {
    "addr:full":"367 Abbott St SW Atlanta GA 30310",
    "addr:housenumber":"367",
    "addr:postcode":"30310",
    "addr:street":"Abbott St Sw",
    "iso:country":"US",
    "sg:address":"367 Abbott St SW",
    "sg:city":"Atlanta",
    "sg:classifiers":[
        {
            "category":"Building & Trades",
            "subcategory":"Locksmith",
            "type":"Services"
        }
    ],
    "sg:phone":"+1 404 965 0377",
    "sg:postcode":"30310",
    "sg:province":"GA",
    "sg:tags":[
        "key"
    ],
    "wof:name":"1 2 3 24 Hour A Locksmith",
    "wof:placetype":"venue"
},
  "geometry": {"coordinates":[-84.419735,33.745881],"type":"Point"}
}