{
  "type": "Feature",
  "properties": {
    "iso:country":"US",
    "sg:address":"1991 Pierce Dairy Rd",
    "sg:city":"Madison",
    "sg:classifiers":[
        {
            "category":"Farming",
            "subcategory":"Farm",
            "type":"Manufacturing & Wholesale Goods"
        }
    ],
    "sg:phone":"+1 706 342 9071",
    "sg:postcode":"30650",
    "sg:province":"GA",
    "sg:tags":[
        "crop",
        "general"
    ],
    "wof:name":"Banks Farms LLC",
    "wof:placetype":"venue"
},
  "geometry": {"coordinates":[-83.477363,33.523151],"type":"Point"}
}