{
  "type": "Feature",
  "properties": {
    "iso:country":"US",
    "sg:address":"327 Awendaw Cir",
    "sg:city":"Ellenwood",
    "sg:classifiers":[
        {
            "category":"Shopping",
            "type":"Retail Goods"
        }
    ],
    "sg:phone":"+1 770 323 0528",
    "sg:postcode":"30294",
    "sg:province":"GA",
    "sg:tags":[
        "merchandise"
    ],
    "wof:name":"Sahara Shop",
    "wof:placetype":"venue"
},
  "geometry": {"coordinates":[-84.208811,33.635471],"type":"Point"}
}