{
  "type": "Feature",
  "properties": {
    "addr:full":"201 Central Ave S Tifton GA 31794",
    "addr:housenumber":"201",
    "addr:postcode":"31794",
    "addr:street":"Central Ave S",
    "iso:country":"US",
    "sg:address":"201 Central Ave S",
    "sg:city":"Tifton",
    "sg:classifiers":[
        {
            "category":"Government",
            "subcategory":"Office",
            "type":"Public Place"
        }
    ],
    "sg:phone":"+1 229 391 6847",
    "sg:postcode":"31794",
    "sg:province":"GA",
    "wof:name":"Assertive Community Treatment",
    "wof:placetype":"venue"
},
  "geometry": {"coordinates":[-83.51214899999999,31.451164],"type":"Point"}
}