{
  "type": "Feature",
  "properties": {
    "addr:full":"29 Dogwood Rd Franklin GA 30217",
    "addr:housenumber":"29",
    "addr:postcode":"30217",
    "addr:street":"Dogwood Rd",
    "iso:country":"US",
    "sg:address":"29 Dogwood Rd",
    "sg:city":"Franklin",
    "sg:classifiers":[
        {
            "category":"Restaurant",
            "type":"Food & Drink"
        }
    ],
    "sg:phone":"+1 770 253 8919",
    "sg:postcode":"30217",
    "sg:province":"GA",
    "wof:name":"Lynda's Sandwich Shop",
    "wof:placetype":"venue"
},
  "geometry": {"coordinates":[-84.99868600000001,33.335239],"type":"Point"}
}