{
  "type": "Feature",
  "properties": {
    "addr:full":"2176 Oak Rd Ste B Snellville GA 30078",
    "addr:housenumber":"2176",
    "addr:postcode":"30078",
    "addr:street":"Oak Rd Ste B",
    "iso:country":"US",
    "sg:address":"2176 Oak Rd Ste B",
    "sg:city":"Snellville",
    "sg:classifiers":[
        {
            "category":"Health Services",
            "subcategory":"Doctor",
            "type":"Services"
        }
    ],
    "sg:phone":"+1 770 985 2900",
    "sg:postcode":"30078",
    "sg:province":"GA",
    "sg:tags":[
        "medicine",
        "internal"
    ],
    "wof:name":"Lassiter Nolan M MD PC",
    "wof:placetype":"venue"
},
  "geometry": {"coordinates":[-84.019402,33.860901],"type":"Point"}
}