{
  "type": "Feature",
  "properties": {
    "addr:full":"827 Kurtz Rd Marietta GA 30066",
    "addr:housenumber":"827",
    "addr:postcode":"30066",
    "addr:street":"Kurtz Rd",
    "iso:country":"US",
    "sg:address":"827 Kurtz Rd",
    "sg:city":"Marietta",
    "sg:classifiers":[
        {
            "category":"Building & Trades",
            "subcategory":"Construction",
            "type":"Services"
        }
    ],
    "sg:phone":"+1 770 426 1832",
    "sg:postcode":"30066",
    "sg:province":"GA",
    "sg:tags":[
        "residential",
        "remodeling"
    ],
    "wof:name":"Robert E Andrews",
    "wof:placetype":"venue"
},
  "geometry": {"coordinates":[-84.525674,34.002347],"type":"Point"}
}