{
  "type": "Feature",
  "properties": {
    "iso:country":"US",
    "sg:address":"7370 Brookstead Xing",
    "sg:city":"Duluth",
    "sg:classifiers":[
        {
            "category":"Building & Trades",
            "subcategory":"Construction",
            "type":"Services"
        }
    ],
    "sg:phone":"+1 770 623 5585",
    "sg:postcode":"30097",
    "sg:province":"GA",
    "sg:tags":[
        "handyman"
    ],
    "wof:name":"Handyman Matters",
    "wof:placetype":"venue"
},
  "geometry": {"coordinates":[-84.142692,34.053086],"type":"Point"}
}