{
  "type": "Feature",
  "properties": {
    "iso:country":"US",
    "sg:address":"207 E Main St",
    "sg:city":"Hahira",
    "sg:classifiers":[
        {
            "category":"Health Services",
            "subcategory":"Doctor",
            "type":"Services"
        }
    ],
    "sg:phone":"+1 229 794 1794",
    "sg:postcode":"31632",
    "sg:province":"GA",
    "sg:tags":[
        "physician",
        "family",
        "practice",
        "surgeons",
        "medicine"
    ],
    "wof:name":"G G Family Medical",
    "wof:placetype":"venue"
},
  "geometry": {"coordinates":[-83.370227,30.991511],"type":"Point"}
}