{
  "type": "Feature",
  "properties": {
    "iso:country":"US",
    "sg:address":"5469 Memorial Dr",
    "sg:city":"Stone Mountain",
    "sg:classifiers":[
        {
            "category":"Bars & Pubs",
            "subcategory":"Nightclub",
            "type":"Food & Drink"
        }
    ],
    "sg:phone":"+1 404 297 9910",
    "sg:postcode":"30083",
    "sg:province":"GA",
    "sg:tags":[
        "nightlife"
    ],
    "wof:name":"Club 426 Restaurant & Lounge",
    "wof:placetype":"venue"
},
  "geometry": {"coordinates":[-84.214598,33.800298],"type":"Point"}
}