{
  "type": "Feature",
  "properties": {
    "iso:country":"US",
    "sg:address":"18 Capitol Sq SW Ste 108",
    "sg:city":"Atlanta",
    "sg:classifiers":[
        {
            "category":"Government",
            "subcategory":"Court House",
            "type":"Public Place"
        }
    ],
    "sg:phone":"+1 404 657 0406",
    "sg:postcode":"30334",
    "sg:province":"GA",
    "sg:tags":[
        "legislator"
    ],
    "wof:name":"Committee On State And Local",
    "wof:placetype":"venue"
},
  "geometry": {"coordinates":[-84.38803900000001,33.748203],"type":"Point"}
}