{
  "type": "Feature",
  "properties": {
    "addr:full":"2301 Hamilton Rd Columbus GA 31904",
    "addr:housenumber":"2301",
    "addr:postcode":"31904",
    "addr:street":"Hamilton Rd",
    "iso:country":"US",
    "sg:address":"2301 Hamilton Rd",
    "sg:city":"Columbus",
    "sg:classifiers":[
        {
            "category":"Home & Garden",
            "subcategory":"Furniture",
            "type":"Retail Goods"
        }
    ],
    "sg:phone":"+1 706 596 1212",
    "sg:postcode":"31904",
    "sg:province":"GA",
    "sg:tags":[
        "cabinet"
    ],
    "wof:name":"Southern Kitchen & Baths",
    "wof:placetype":"venue"
},
  "geometry": {"coordinates":[-84.98347699999999,32.486024],"type":"Point"}
}