{
  "type": "Feature",
  "properties": {
    "iso:country":"US",
    "sg:address":"105 Ivanhoe Dr",
    "sg:city":"Thomasville",
    "sg:classifiers":[
        {
            "category":"Professional",
            "type":"Services"
        }
    ],
    "sg:phone":"+1 229 228 9263",
    "sg:postcode":"31792",
    "sg:province":"GA",
    "wof:name":"Writers Ink LLC",
    "wof:placetype":"venue"
},
  "geometry": {"coordinates":[-83.99435,30.799923],"type":"Point"}
}