{
  "type": "Feature",
  "properties": {
    "iso:country":"US",
    "sg:address":"127 E Calhoun St",
    "sg:city":"Bainbridge",
    "sg:classifiers":[
        {
            "category":"Real Estate",
            "subcategory":"Real Estate Agent",
            "type":"Services"
        }
    ],
    "sg:phone":"+1 229 246 3311",
    "sg:postcode":"39817",
    "sg:province":"GA",
    "wof:name":"Flint River Realty",
    "wof:placetype":"venue"
},
  "geometry": {"coordinates":[-84.57635500000001,30.909313],"type":"Point"}
}