{
  "type": "Feature",
  "properties": {
    "iso:country":"US",
    "sg:address":"694 Mount Pleasant Rd",
    "sg:city":"Carrollton",
    "sg:classifiers":[
        {
            "category":"Organizations",
            "subcategory":"Religious Organization",
            "type":"Services"
        }
    ],
    "sg:phone":"+1 770 834 0048",
    "sg:postcode":"30116",
    "sg:province":"GA",
    "sg:tags":[
        "church"
    ],
    "wof:name":"Mt Pleasant Baptist Church",
    "wof:placetype":"venue"
},
  "geometry": {"coordinates":[-85.029825,33.527007],"type":"Point"}
}