{
  "type": "Feature",
  "properties": {
    "iso:country":"US",
    "sg:address":"721 Story Rd",
    "sg:city":"Sylvester",
    "sg:phone":"+1 229 776 2283",
    "sg:postcode":"31772",
    "sg:province":"GA",
    "sg:tags":[
        "farm",
        "cotton"
    ],
    "wof:name":"Dan J Story",
    "wof:placetype":"venue"
},
  "geometry": {"coordinates":[-83.964032,31.650346],"type":"Point"}
}