{
  "type": "Feature",
  "properties": {
    "iso:country":"US",
    "sg:address":"1298 Reinhardt College Pkwy",
    "sg:city":"Canton",
    "sg:classifiers":[
        {
            "category":"Professional",
            "subcategory":"Business Services",
            "type":"Services"
        },
        {
            "category":"Professional",
            "subcategory":"Secretarial Services",
            "type":"Services"
        }
    ],
    "sg:phone":"+1 770 479 3763",
    "sg:postcode":"30114",
    "sg:province":"GA",
    "sg:tags":[
        "transcription",
        "medical"
    ],
    "wof:name":"Medical Transportation Assoc",
    "wof:placetype":"venue"
},
  "geometry": {"coordinates":[-84.493995,34.258419],"type":"Point"}
}