{
  "type": "Feature",
  "properties": {
    "iso:country":"US",
    "sg:address":"3001 Westpoint Rd",
    "sg:city":"Lagrange",
    "sg:classifiers":[
        {
            "category":"Retail",
            "subcategory":"Auto Repair",
            "type":"Services"
        }
    ],
    "sg:phone":"+1 706 884 4655",
    "sg:postcode":"30240",
    "sg:province":"GA",
    "sg:tags":[
        "body",
        "automobile",
        "painting"
    ],
    "wof:name":"Hall's Body Shop",
    "wof:placetype":"venue"
},
  "geometry": {"coordinates":[-85.102054,33.015206],"type":"Point"}
}