{
  "type": "Feature",
  "properties": {
    "iso:country":"US",
    "sg:address":"4140 Jonesboro Rd",
    "sg:city":"Forest Park",
    "sg:classifiers":[
        {
            "category":"Shopping",
            "subcategory":"Books",
            "type":"Retail Goods"
        }
    ],
    "sg:phone":"+1 404 608 9977",
    "sg:postcode":"30297",
    "sg:province":"GA",
    "wof:name":"Le Phan By Le Inc",
    "wof:placetype":"venue"
},
  "geometry": {"coordinates":[-84.36252500000001,33.642304],"type":"Point"}
}