{
  "type": "Feature",
  "properties": {
    "addr:full":"3585 Forest Edge Dr SW Conyers GA 30094",
    "addr:housenumber":"3585",
    "addr:postcode":"30094",
    "addr:street":"Forest Edge Dr Sw",
    "iso:country":"US",
    "sg:address":"3585 Forest Edge Dr SW",
    "sg:city":"Conyers",
    "sg:classifiers":[
        {
            "category":"Building & Trades",
            "subcategory":"Electrical",
            "type":"Services"
        }
    ],
    "sg:phone":"+1 770 922 1497",
    "sg:postcode":"30094",
    "sg:province":"GA",
    "sg:tags":[
        "installation",
        "telephone"
    ],
    "wof:name":"Quality Communication Services",
    "wof:placetype":"venue"
},
  "geometry": {"coordinates":[-84.05202199999999,33.594164],"type":"Point"}
}