{
  "type": "Feature",
  "properties": {
    "iso:country":"US",
    "sg:address":"3395 Cypress Mill Rd",
    "sg:city":"Brunswick",
    "sg:classifiers":[
        {
            "category":"Manufacturing",
            "subcategory":"Printing",
            "type":"Manufacturing & Wholesale Goods"
        }
    ],
    "sg:phone":"+1 912 267 7878",
    "sg:postcode":"31520",
    "sg:province":"GA",
    "sg:tags":[
        "newspaper",
        "publisher"
    ],
    "wof:name":"Jekyll's Golden Islander",
    "wof:placetype":"venue"
},
  "geometry": {"coordinates":[-81.48550400000001,31.19511],"type":"Point"}
}