{
  "type": "Feature",
  "properties": {
    "addr:full":"591 Jones Ave NW Atlanta GA 30314",
    "addr:housenumber":"591",
    "addr:postcode":"30314",
    "addr:street":"Jones Ave Nw",
    "iso:country":"US",
    "sg:address":"591 Jones Ave NW",
    "sg:city":"Atlanta",
    "sg:classifiers":[
        {
            "category":"Organizations",
            "subcategory":"Religious Organization",
            "type":"Services"
        }
    ],
    "sg:phone":"+1 404 524 0976",
    "sg:postcode":"30314",
    "sg:province":"GA",
    "wof:name":"Body of Chrst Tmple Aoh Hlness",
    "wof:placetype":"venue"
},
  "geometry": {"coordinates":[-84.407337,33.764335],"type":"Point"}
}