{
  "type": "Feature",
  "properties": {
    "iso:country":"US",
    "sg:address":"3783 Eagle Woods Cir",
    "sg:city":"Lithonia",
    "sg:classifiers":[
        {
            "category":"Shopping",
            "subcategory":"Crafts & Fabrics",
            "type":"Retail Goods"
        }
    ],
    "sg:phone":"+1 770 322 9493",
    "sg:postcode":"30038",
    "sg:province":"GA",
    "sg:tags":[
        "sewing",
        "machines-household"
    ],
    "wof:name":"Sarah Howard",
    "wof:placetype":"venue"
},
  "geometry": {"coordinates":[-84.173271,33.669802],"type":"Point"}
}