{
  "type": "Feature",
  "properties": {
    "addr:full":"285 Price Rd Carrollton GA 30116",
    "addr:housenumber":"285",
    "addr:postcode":"30116",
    "addr:street":"Price Rd",
    "iso:country":"US",
    "sg:address":"285 Price Rd",
    "sg:city":"Carrollton",
    "sg:classifiers":[
        {
            "category":"Building & Trades",
            "subcategory":"Plumbing",
            "type":"Services"
        }
    ],
    "sg:phone":"+1 770 214 0529",
    "sg:postcode":"30116",
    "sg:province":"GA",
    "sg:tags":[
        "contractor"
    ],
    "wof:name":"Crum Brothers Heating & Air",
    "wof:placetype":"venue"
},
  "geometry": {"coordinates":[-84.988103,33.645379],"type":"Point"}
}