{
  "type": "Feature",
  "properties": {
    "iso:country":"US",
    "sg:address":"710 N Fork Dr SW",
    "sg:city":"Marietta",
    "sg:classifiers":[
        {
            "category":"Building & Trades",
            "subcategory":"Construction",
            "type":"Services"
        }
    ],
    "sg:phone":"+1 770 333 0825",
    "sg:postcode":"30008",
    "sg:province":"GA",
    "sg:tags":[
        "siding",
        "contractor"
    ],
    "wof:name":"Gonzalez Siding",
    "wof:placetype":"venue"
},
  "geometry": {"coordinates":[-84.573329,33.900493],"type":"Point"}
}