{
  "type": "Feature",
  "properties": {
    "addr:full":"1111 Commerce St Madison GA 30650",
    "addr:housenumber":"1111",
    "addr:postcode":"30650",
    "addr:street":"Commerce St",
    "iso:country":"US",
    "sg:address":"1111 Commerce St",
    "sg:city":"Madison",
    "sg:classifiers":[
        {
            "category":"Manufacturing",
            "subcategory":"Tools & Machinery",
            "type":"Manufacturing & Wholesale Goods"
        }
    ],
    "sg:phone":"+1 706 342 2442",
    "sg:postcode":"30650",
    "sg:province":"GA",
    "sg:tags":[
        "machine",
        "shop"
    ],
    "wof:name":"Madison Tractor & Equipment",
    "wof:placetype":"venue"
},
  "geometry": {"coordinates":[-83.479924,33.577549],"type":"Point"}
}