{
  "type": "Feature",
  "properties": {
    "iso:country":"US",
    "sg:address":"341 S Dugger Ave",
    "sg:city":"Roberta",
    "sg:classifiers":[
        {
            "category":"Food & Beverages",
            "subcategory":"Groceries & Convenience Stores",
            "type":"Retail Goods"
        }
    ],
    "sg:phone":"+1 478 836 4416",
    "sg:postcode":"31078",
    "sg:province":"GA",
    "wof:name":"Bob's Magic Mart",
    "wof:placetype":"venue"
},
  "geometry": {"coordinates":[-84.010757,32.716873],"type":"Point"}
}