{
  "type": "Feature",
  "properties": {
    "iso:country":"US",
    "sg:address":"1608 S Slappey Blvd",
    "sg:city":"Albany",
    "sg:classifiers":[
        {
            "category":"Government",
            "subcategory":"Office",
            "type":"Public Place"
        }
    ],
    "sg:phone":"+1 229 430 2979",
    "sg:postcode":"31701",
    "sg:province":"GA",
    "sg:tags":[
        "state",
        "resource"
    ],
    "sg:website":"www.dol.state.ga.us",
    "wof:name":"Unemployment Insurance Claims",
    "wof:placetype":"venue"
},
  "geometry": {"coordinates":[-84.17650500000001,31.554433],"type":"Point"}
}