{
  "type": "Feature",
  "properties": {
    "addr:full":"1176 Booker Ave SW Atlanta GA 30310",
    "addr:housenumber":"1176",
    "addr:postcode":"30310",
    "addr:street":"Booker Ave Sw",
    "iso:country":"US",
    "sg:address":"1176 Booker Ave SW",
    "sg:city":"Atlanta",
    "sg:classifiers":[
        {
            "category":"Organizations",
            "subcategory":"Religious Organization",
            "type":"Services"
        }
    ],
    "sg:phone":"+1 404 584 6722",
    "sg:postcode":"30310",
    "sg:province":"GA",
    "wof:name":"New Hope Bapt Ch/Pitt Area",
    "wof:placetype":"venue"
},
  "geometry": {"coordinates":[-84.397527,33.723718],"type":"Point"}
}