{
  "type": "Feature",
  "properties": {
    "iso:country":"US",
    "sg:address":"12 Reece St",
    "sg:city":"Rossville",
    "sg:classifiers":[
        {
            "category":"Restaurant",
            "type":"Food & Drink"
        }
    ],
    "sg:phone":"+1 706 866 3932",
    "sg:postcode":"30741",
    "sg:province":"GA",
    "wof:name":"Aunt Effies Restaurant",
    "wof:placetype":"venue"
},
  "geometry": {"coordinates":[-85.28842899999999,34.94689],"type":"Point"}
}