{
  "type": "Feature",
  "properties": {
    "iso:country":"US",
    "sg:address":"1717 Russell Pkwy",
    "sg:city":"Warner Robins",
    "sg:classifiers":[
        {
            "category":"Insurance",
            "subcategory":"Hazard Insurance",
            "type":"Services"
        }
    ],
    "sg:phone":"+1 478 929 4141",
    "sg:postcode":"31088",
    "sg:province":"GA",
    "sg:website":"www.mcnealagency.com",
    "wof:name":"Mcneal Agency, Inc",
    "wof:placetype":"venue"
},
  "geometry": {"coordinates":[-83.661438,32.593094],"type":"Point"}
}