{
  "type": "Feature",
  "properties": {
    "addr:full":"4450 Calibre Xing NW Acworth GA 30101",
    "addr:housenumber":"4450",
    "addr:postcode":"30101",
    "addr:street":"Calibre Xing Nw",
    "iso:country":"US",
    "sg:address":"4450 Calibre Xing NW",
    "sg:city":"Acworth",
    "sg:classifiers":[
        {
            "category":"Health Services",
            "subcategory":"Doctor",
            "type":"Services"
        }
    ],
    "sg:phone":"+1 678 631 4600",
    "sg:postcode":"30101",
    "sg:province":"GA",
    "wof:name":"Duphare Harsh V MD",
    "wof:placetype":"venue"
},
  "geometry": {"coordinates":[-84.72265299999999,34.064366],"type":"Point"}
}