{
  "type": "Feature",
  "properties": {
    "iso:country":"US",
    "sg:address":"97 Washington St",
    "sg:city":"Mc Donough",
    "sg:classifiers":[
        {
            "category":"Retail",
            "subcategory":"Auto Repair",
            "type":"Services"
        }
    ],
    "sg:phone":"+1 678 595 2913",
    "sg:postcode":"30253",
    "sg:province":"GA",
    "sg:tags":[
        "automotive"
    ],
    "wof:name":"After Six Tire & Towing Mobile",
    "wof:placetype":"venue"
},
  "geometry": {"coordinates":[-84.153881,33.438414],"type":"Point"}
}