{
  "type": "Feature",
  "properties": {
    "addr:full":"506 S Harris St Sandersville GA 31082",
    "addr:housenumber":"506",
    "addr:postcode":"31082",
    "addr:street":"S Harris St",
    "iso:country":"US",
    "sg:address":"506 S Harris St",
    "sg:city":"Sandersville",
    "sg:classifiers":[
        {
            "category":"Real Estate",
            "subcategory":"Real Estate Agent",
            "type":"Services"
        }
    ],
    "sg:phone":"+1 478 552 1405",
    "sg:postcode":"31082",
    "sg:province":"GA",
    "wof:name":"Century 21 Twin City Realty",
    "wof:placetype":"venue"
},
  "geometry": {"coordinates":[-82.809506,32.975293],"type":"Point"}
}