{
  "type": "Feature",
  "properties": {
    "iso:country":"US",
    "sg:address":"4215 Wheeler Rd",
    "sg:city":"Martinez",
    "sg:classifiers":[
        {
            "category":"Building & Trades",
            "subcategory":"Construction",
            "type":"Services"
        }
    ],
    "sg:phone":"+1 706 855 5140",
    "sg:postcode":"30907",
    "sg:province":"GA",
    "sg:tags":[
        "company"
    ],
    "wof:name":"Heath Construction",
    "wof:placetype":"venue"
},
  "geometry": {"coordinates":[-82.119911,33.488022],"type":"Point"}
}