{
  "type": "Feature",
  "properties": {
    "addr:full":"1991 Westwood Ave SW Atlanta GA 30310",
    "addr:housenumber":"1991",
    "addr:postcode":"30310",
    "addr:street":"Westwood Ave Sw",
    "iso:country":"US",
    "sg:address":"1991 Westwood Ave SW",
    "sg:city":"Atlanta",
    "sg:classifiers":[
        {
            "category":"Organizations",
            "subcategory":"Religious Organization",
            "type":"Services"
        }
    ],
    "sg:phone":"+1 404 755 8351",
    "sg:postcode":"30310",
    "sg:province":"GA",
    "wof:name":"Lift Into Life Ministry Inc",
    "wof:placetype":"venue"
},
  "geometry": {"coordinates":[-84.453839,33.738916],"type":"Point"}
}