{
  "type": "Feature",
  "properties": {
    "iso:country":"US",
    "sg:address":"370 Highway 155 S",
    "sg:city":"McDonough",
    "sg:classifiers":[
        {
            "category":"Sports & Exercise",
            "subcategory":"Bowling",
            "type":"Entertainment"
        }
    ],
    "sg:phone":"+1 770 898 4272",
    "sg:postcode":"30253",
    "sg:province":"GA",
    "sg:website":"myfunbowl.com",
    "wof:name":"Fun Bowl of Henry County",
    "wof:placetype":"venue"
},
  "geometry": {"coordinates":[-84.15270200000001,33.4188],"type":"Point"}
}