{
  "type": "Feature",
  "properties": {
    "iso:country":"US",
    "sg:address":"255 N Clarendon Ave",
    "sg:city":"Scottdale",
    "sg:classifiers":[
        {
            "category":"Retail",
            "subcategory":"Repair Shop",
            "type":"Services"
        }
    ],
    "sg:phone":"+1 404 294 9006",
    "sg:postcode":"30079",
    "sg:province":"GA",
    "sg:tags":[
        "lock",
        "locksmith"
    ],
    "sg:website":"www.adriansecurity.com",
    "wof:name":"Adrian Security Inc",
    "wof:placetype":"venue"
},
  "geometry": {"coordinates":[-84.26317,33.782799],"type":"Point"}
}