{
  "type": "Feature",
  "properties": {
    "addr:full":"202 S 2nd Ave Chatsworth GA 30705",
    "addr:housenumber":"202",
    "addr:postcode":"30705",
    "addr:street":"S 2Nd Ave",
    "iso:country":"US",
    "sg:address":"202 S 2nd Ave",
    "sg:city":"Chatsworth",
    "sg:classifiers":[
        {
            "category":"Retail",
            "subcategory":"Auto Repair",
            "type":"Services"
        }
    ],
    "sg:phone":"+1 706 517 8223",
    "sg:postcode":"30705",
    "sg:province":"GA",
    "sg:tags":[
        "general"
    ],
    "wof:name":"J T Auto",
    "wof:placetype":"venue"
},
  "geometry": {"coordinates":[-84.768423,34.763529],"type":"Point"}
}