{
  "type": "Feature",
  "properties": {
    "iso:country":"US",
    "sg:address":"717 Industrial Park Dr",
    "sg:city":"Evans",
    "sg:classifiers":[
        {
            "category":"Education",
            "subcategory":"School",
            "type":"Public Place"
        }
    ],
    "sg:phone":"+1 706 364 3169",
    "sg:postcode":"30809",
    "sg:province":"GA",
    "wof:name":"Academics Plus",
    "wof:placetype":"venue"
},
  "geometry": {"coordinates":[-82.119198,33.555589],"type":"Point"}
}