{
  "type": "Feature",
  "properties": {
    "iso:country":"US",
    "sg:address":"111 Sweet Gum Rd S",
    "sg:city":"Savannah",
    "sg:classifiers":[
        {
            "category":"Professional",
            "subcategory":"Detective & Security Services",
            "type":"Services"
        }
    ],
    "sg:phone":"+1 912 897 9709",
    "sg:postcode":"31410",
    "sg:province":"GA",
    "sg:tags":[
        "investigator"
    ],
    "wof:name":"Robert C Braver",
    "wof:placetype":"venue"
},
  "geometry": {"coordinates":[-80.963166,32.007637],"type":"Point"}
}