{
  "type": "Feature",
  "properties": {
    "iso:country":"US",
    "sg:address":"4210 Longview Dr",
    "sg:city":"Atlanta",
    "sg:classifiers":[
        {
            "category":"Building & Trades",
            "subcategory":"Construction",
            "type":"Services"
        }
    ],
    "sg:phone":"+1 404 822 4970",
    "sg:postcode":"30341",
    "sg:province":"GA",
    "sg:tags":[
        "roofing",
        "contractor"
    ],
    "wof:name":"Mitchell, Steven - Ace Roofing",
    "wof:placetype":"venue"
},
  "geometry": {"coordinates":[-84.303416,33.916293],"type":"Point"}
}