{
  "type": "Feature",
  "properties": {
    "addr:full":"5395 Buford Hwy Norcross GA 30071",
    "addr:housenumber":"5395",
    "addr:postcode":"30071",
    "addr:street":"Buford Hwy",
    "iso:country":"US",
    "sg:address":"5395 Buford Hwy",
    "sg:city":"Norcross",
    "sg:classifiers":[
        {
            "category":"Building & Trades",
            "subcategory":"Construction",
            "type":"Services"
        }
    ],
    "sg:phone":"+1 678 205 2359",
    "sg:postcode":"30071",
    "sg:province":"GA",
    "sg:tags":[
        "home",
        "builder"
    ],
    "wof:name":"Home Supplies",
    "wof:placetype":"venue"
},
  "geometry": {"coordinates":[-84.202404,33.946108],"type":"Point"}
}