{
  "type": "Feature",
  "properties": {
    "addr:full":"11115 Tara Blvd Hampton GA 30228",
    "addr:housenumber":"11115",
    "addr:postcode":"30228",
    "addr:street":"Tara Blvd",
    "iso:country":"US",
    "sg:address":"11115 Tara Blvd",
    "sg:city":"Hampton",
    "sg:classifiers":[
        {
            "category":"Banks & Credit Unions",
            "subcategory":"Bank",
            "type":"Services"
        }
    ],
    "sg:phone":"+1 770 980 2255",
    "sg:postcode":"30228",
    "sg:province":"GA",
    "wof:name":"Sun Trust Bank",
    "wof:placetype":"venue"
},
  "geometry": {"coordinates":[-84.32940000000001,33.45962],"type":"Point"}
}