{
  "type": "Feature",
  "properties": {
    "iso:country":"US",
    "sg:address":"1602 Homestead Trl",
    "sg:city":"Alpharetta",
    "sg:classifiers":[
        {
            "category":"Retail",
            "subcategory":"Auto Repair",
            "type":"Services"
        }
    ],
    "sg:phone":"+1 770 754 5885",
    "sg:postcode":"30004",
    "sg:province":"GA",
    "sg:tags":[
        "automobile",
        "testing",
        "emission"
    ],
    "wof:name":"Horiba International Inc",
    "wof:placetype":"venue"
},
  "geometry": {"coordinates":[-84.27855700000001,34.083785],"type":"Point"}
}