{
  "type": "Feature",
  "properties": {
    "addr:full":"4850 Sugarloaf Pkwy Ste 401 Lawrenceville GA 30044",
    "addr:housenumber":"4850",
    "addr:postcode":"30044",
    "addr:street":"Sugarloaf Pkwy Ste 401",
    "iso:country":"US",
    "sg:address":"4850 Sugarloaf Pkwy Ste 401",
    "sg:city":"Lawrenceville",
    "sg:classifiers":[
        {
            "category":"Restaurant",
            "type":"Food & Drink"
        }
    ],
    "sg:phone":"+1 770 822 1488",
    "sg:postcode":"30044",
    "sg:province":"GA",
    "sg:tags":[
        "chinese"
    ],
    "wof:name":"New China Restaurant",
    "wof:placetype":"venue"
},
  "geometry": {"coordinates":[-84.07869700000001,33.9258],"type":"Point"}
}