{
  "type": "Feature",
  "properties": {
    "addr:full":"3773 S Cobb Dr SE Smyrna GA 30080",
    "addr:housenumber":"3773",
    "addr:postcode":"30080",
    "addr:street":"S Cobb Dr Se",
    "iso:country":"US",
    "sg:address":"3773 S Cobb Dr SE",
    "sg:city":"Smyrna",
    "sg:classifiers":[
        {
            "category":"Retail",
            "subcategory":"Pet Boarding",
            "type":"Services"
        }
    ],
    "sg:phone":"+1 770 436 1818",
    "sg:postcode":"30080",
    "sg:province":"GA",
    "sg:tags":[
        "boarding/pet",
        "sitting"
    ],
    "sg:website":"www.furryfriendsacademy.com",
    "wof:name":"Furry Friends Academy",
    "wof:placetype":"venue"
},
  "geometry": {"coordinates":[-84.516403,33.858898],"type":"Point"}
}