{
  "type": "Feature",
  "properties": {
    "addr:full":"755 Commerce Dr Decatur GA 30030",
    "addr:housenumber":"755",
    "addr:postcode":"30030",
    "addr:street":"Commerce Dr",
    "iso:country":"US",
    "sg:address":"755 Commerce Dr",
    "sg:city":"Decatur",
    "sg:classifiers":[
        {
            "category":"Real Estate",
            "subcategory":"Developer",
            "type":"Services"
        }
    ],
    "sg:phone":"+1 404 373 9411",
    "sg:postcode":"30030",
    "sg:province":"GA",
    "sg:tags":[
        "development",
        "management"
    ],
    "wof:name":"R E L Properties Inc",
    "wof:placetype":"venue"
},
  "geometry": {"coordinates":[-84.29308,33.777814],"type":"Point"}
}