{
  "type": "Feature",
  "properties": {
    "iso:country":"US",
    "sg:address":"8356 Roswell Rd",
    "sg:city":"Atlanta",
    "sg:classifiers":[
        {
            "category":"Freight",
            "type":"Transportation"
        }
    ],
    "sg:phone":"+1 770 642 9604",
    "sg:postcode":"30350",
    "sg:province":"GA",
    "wof:name":"Nation Movers Inc",
    "wof:placetype":"venue"
},
  "geometry": {"coordinates":[-84.35035499999999,33.980781],"type":"Point"}
}