{
  "type": "Feature",
  "properties": {
    "addr:full":"618 E Main St Blue Ridge GA 30513",
    "addr:housenumber":"618",
    "addr:postcode":"30513",
    "addr:street":"E Main St",
    "iso:country":"US",
    "sg:address":"618 E Main St",
    "sg:city":"Blue Ridge",
    "sg:classifiers":[
        {
            "category":"Real Estate",
            "subcategory":"Real Estate Operator",
            "type":"Services"
        }
    ],
    "sg:phone":"+1 706 632 1063",
    "sg:postcode":"30513",
    "sg:province":"GA",
    "sg:tags":[
        "mall",
        "shopping",
        "center"
    ],
    "wof:name":"Blue Ridge Mountain Mall",
    "wof:placetype":"venue"
},
  "geometry": {"coordinates":[-84.323363,34.866594],"type":"Point"}
}