{
  "type": "Feature",
  "properties": {
    "addr:full":"3105-J Gateway Dr Norcross GA 30071",
    "addr:housenumber":"3105-j",
    "addr:postcode":"30071",
    "addr:street":"Gateway Dr",
    "iso:country":"US",
    "sg:address":"3105-J Gateway Dr",
    "sg:city":"Norcross",
    "sg:classifiers":[
        {
            "category":"Shopping",
            "subcategory":"Stationery & Office Supplies",
            "type":"Retail Goods"
        },
        {
            "category":"Home & Garden",
            "subcategory":"Furniture",
            "type":"Retail Goods"
        }
    ],
    "sg:phone":"+1 770 734 9483",
    "sg:postcode":"30071",
    "sg:province":"GA",
    "sg:tags":[
        "equipment",
        "store"
    ],
    "sg:website":"corporate.onlygreen4me.com",
    "wof:name":"OnlyGreen4Me - Green Products",
    "wof:placetype":"venue"
},
  "geometry": {"coordinates":[-84.257259,33.932083],"type":"Point"}
}