{
  "type": "Feature",
  "properties": {
    "addr:full":"759 Old Hwy 5 N Ellijay GA 30540",
    "addr:housenumber":"759",
    "addr:postcode":"30540",
    "addr:street":"Old Hwy 5 N",
    "iso:country":"US",
    "sg:address":"759 Old Hwy 5 N",
    "sg:city":"Ellijay",
    "sg:classifiers":[
        {
            "category":"Shopping",
            "subcategory":"Bicycles & Sporting Goods",
            "type":"Retail Goods"
        }
    ],
    "sg:phone":"+1 706 276 7145",
    "sg:postcode":"30540",
    "sg:province":"GA",
    "sg:tags":[
        "bait",
        "fishing"
    ],
    "wof:name":"K & M Fishing & Camping Supl",
    "wof:placetype":"venue"
},
  "geometry": {"coordinates":[-84.45659999999999,34.716216],"type":"Point"}
}