{
  "type": "Feature",
  "properties": {
    "iso:country":"US",
    "sg:address":"3980 Bayside Cir",
    "sg:city":"Atlanta",
    "sg:classifiers":[
        {
            "category":"Personal",
            "type":"Services"
        }
    ],
    "sg:phone":"+1 770 493 4471",
    "sg:postcode":"30340",
    "sg:province":"GA",
    "wof:name":"Loop Home Services",
    "wof:placetype":"venue"
},
  "geometry": {"coordinates":[-84.225241,33.890811],"type":"Point"}
}