{
  "type": "Feature",
  "properties": {
    "addr:full":"406 S Main St Boston GA 31626",
    "addr:housenumber":"406",
    "addr:postcode":"31626",
    "addr:street":"S Main St",
    "iso:country":"US",
    "sg:address":"406 S Main St",
    "sg:city":"Boston",
    "sg:classifiers":[
        {
            "category":"Place Of Worship",
            "subcategory":"Church",
            "type":"Public Place"
        },
        {
            "category":"Place Of Worship",
            "type":"Public Place"
        }
    ],
    "sg:phone":"+1 229 498 1155",
    "sg:postcode":"31626",
    "sg:province":"GA",
    "sg:tags":[
        "churches-interdenominational",
        "churches-various",
        "denomination"
    ],
    "wof:name":"St John Ame Church",
    "wof:placetype":"venue"
},
  "geometry": {"coordinates":[-83.79041599999999,30.78905],"type":"Point"}
}