{
  "type": "Feature",
  "properties": {
    "addr:full":"18 Greenville St S Newnan GA 30263",
    "addr:housenumber":"18",
    "addr:postcode":"30263",
    "addr:street":"Greenville St S",
    "iso:country":"US",
    "sg:address":"18 Greenville St S",
    "sg:city":"Newnan",
    "sg:classifiers":[
        {
            "category":"Building & Trades",
            "subcategory":"Cleaning & Sanitation",
            "type":"Services"
        }
    ],
    "sg:phone":"+1 770 254 1827",
    "sg:postcode":"30263",
    "sg:province":"GA",
    "sg:tags":[
        "maintenance"
    ],
    "wof:name":"CMC & Maintenance Inc",
    "wof:placetype":"venue"
},
  "geometry": {"coordinates":[-84.79960699999999,33.371644],"type":"Point"}
}