{
  "type": "Feature",
  "properties": {
    "addr:full":"11706 Alpharetta Hwy Roswell GA 30076",
    "addr:housenumber":"11706",
    "addr:postcode":"30076",
    "addr:street":"Alpharetta Hwy",
    "iso:country":"US",
    "sg:address":"11706 Alpharetta Hwy",
    "sg:city":"Roswell",
    "sg:classifiers":[
        {
            "category":"Restaurant",
            "type":"Food & Drink"
        }
    ],
    "sg:phone":"+1 770 751 6022",
    "sg:postcode":"30076",
    "sg:province":"GA",
    "sg:tags":[
        "eating"
    ],
    "wof:name":"Subrageous",
    "wof:placetype":"venue"
},
  "geometry": {"coordinates":[-84.32118199999999,34.064808],"type":"Point"}
}