{
  "type": "Feature",
  "properties": {
    "addr:full":"3429 White Sands Way Suwanee GA 30024",
    "addr:housenumber":"3429",
    "addr:postcode":"30024",
    "addr:street":"White Sands Way",
    "iso:country":"US",
    "sg:address":"3429 White Sands Way",
    "sg:city":"Suwanee",
    "sg:classifiers":[
        {
            "category":"Shopping",
            "subcategory":"Clothing, Apparel, & Fashions",
            "type":"Retail Goods"
        }
    ],
    "sg:phone":"+1 770 614 0431",
    "sg:postcode":"30024",
    "sg:province":"GA",
    "sg:tags":[
        "hair",
        "supply"
    ],
    "wof:name":"Bowtique",
    "wof:placetype":"venue"
},
  "geometry": {"coordinates":[-84.04625900000001,34.043976],"type":"Point"}
}