{
  "type": "Feature",
  "properties": {
    "addr:full":"652 Gordon St Jefferson GA 30549",
    "addr:housenumber":"652",
    "addr:postcode":"30549",
    "addr:street":"Gordon St",
    "iso:country":"US",
    "sg:address":"652 Gordon St",
    "sg:city":"Jefferson",
    "sg:classifiers":[
        {
            "category":"Place Of Worship",
            "subcategory":"Church",
            "type":"Public Place"
        },
        {
            "category":"Place Of Worship",
            "type":"Public Place"
        }
    ],
    "sg:phone":"+1 706 367 8974",
    "sg:postcode":"30549",
    "sg:province":"GA",
    "sg:tags":[
        "churches-presbyterian-arp",
        "churches-presbyterian"
    ],
    "wof:name":"Sardis Presbyterian Church",
    "wof:placetype":"venue"
},
  "geometry": {"coordinates":[-83.570204,34.109848],"type":"Point"}
}