{
  "type": "Feature",
  "properties": {
    "addr:full":"243 Pinehurst Dr Augusta GA 30907",
    "addr:housenumber":"243",
    "addr:postcode":"30907",
    "addr:street":"Pinehurst Dr",
    "iso:country":"US",
    "sg:address":"243 Pinehurst Dr",
    "sg:city":"Augusta",
    "sg:classifiers":[
        {
            "category":"Professional",
            "subcategory":"Detective & Security Services",
            "type":"Services"
        }
    ],
    "sg:phone":"+1 706 825 5607",
    "sg:postcode":"30907",
    "sg:province":"GA",
    "sg:tags":[
        "guard",
        "patrol"
    ],
    "wof:name":"Bess Pelkey",
    "wof:placetype":"venue"
},
  "geometry": {"coordinates":[-82.10576,33.502195],"type":"Point"}
}