{
  "type": "Feature",
  "properties": {
    "iso:country":"US",
    "sg:address":"5154 Jimmy Carter Blvd",
    "sg:city":"Norcross",
    "sg:classifiers":[
        {
            "category":"Recreation",
            "type":"Entertainment"
        }
    ],
    "sg:phone":"+1 770 729 9890",
    "sg:postcode":"30093",
    "sg:province":"GA",
    "sg:tags":[
        "psychic",
        "medium"
    ],
    "wof:name":"Katherine Psychic Reader",
    "wof:placetype":"venue"
},
  "geometry": {"coordinates":[-84.201731,33.89839],"type":"Point"}
}