{
  "type": "Feature",
  "properties": {
    "iso:country":"US",
    "sg:address":"1588 Veterans Memoril Hwy",
    "sg:city":"Austell",
    "sg:classifiers":[
        {
            "category":"Retail",
            "subcategory":"Auto Repair",
            "type":"Services"
        }
    ],
    "sg:phone":"+1 678 945 1111",
    "sg:postcode":"30168",
    "sg:province":"GA",
    "sg:tags":[
        "body",
        "shop"
    ],
    "wof:name":"Reid's Paint Body & Towing Inc",
    "wof:placetype":"venue"
},
  "geometry": {"coordinates":[-84.5998,33.815399],"type":"Point"}
}