{
  "type": "Feature",
  "properties": {
    "iso:country":"US",
    "sg:address":"1830 Atlanta Rd",
    "sg:city":"Gainesville",
    "sg:classifiers":[
        {
            "category":"Restaurant",
            "type":"Food & Drink"
        }
    ],
    "sg:phone":"+1 770 534 8644",
    "sg:postcode":"30504",
    "sg:province":"GA",
    "sg:tags":[
        "eating"
    ],
    "wof:name":"El Ranchero",
    "wof:placetype":"venue"
},
  "geometry": {"coordinates":[-83.84487300000001,34.260998],"type":"Point"}
}