{
  "type": "Feature",
  "properties": {
    "addr:full":"316 McFarland Ave Rossville GA 30741",
    "addr:housenumber":"316",
    "addr:postcode":"30741",
    "addr:street":"Mcfarland Ave",
    "iso:country":"US",
    "sg:address":"316 McFarland Ave",
    "sg:city":"Rossville",
    "sg:classifiers":[
        {
            "category":"Retail",
            "subcategory":"Auto Repair",
            "type":"Services"
        }
    ],
    "sg:phone":"+1 706 866 2094",
    "sg:postcode":"30741",
    "sg:province":"GA",
    "sg:tags":[
        "repairing",
        "automobile"
    ],
    "wof:name":"American Tire & Auto Repair",
    "wof:placetype":"venue"
},
  "geometry": {"coordinates":[-85.287836,34.98197],"type":"Point"}
}