{
  "type": "Feature",
  "properties": {
    "addr:full":"1264 Beaver Ruin Rd Norcross GA 30093",
    "addr:housenumber":"1264",
    "addr:postcode":"30093",
    "addr:street":"Beaver Ruin Rd",
    "iso:country":"US",
    "sg:address":"1264 Beaver Ruin Rd",
    "sg:city":"Norcross",
    "sg:classifiers":[
        {
            "category":"Insurance",
            "subcategory":"Insurance Agent",
            "type":"Services"
        }
    ],
    "sg:phone":"+1 770 381 0884",
    "sg:postcode":"30093",
    "sg:province":"GA",
    "wof:name":"Wichalonis Gerard",
    "wof:placetype":"venue"
},
  "geometry": {"coordinates":[-84.137945,33.926793],"type":"Point"}
}