{
  "type": "Feature",
  "properties": {
    "iso:country":"US",
    "sg:address":"155 Farm Hill Cir",
    "sg:city":"Roswell",
    "sg:classifiers":[
        {
            "category":"Manufacturing",
            "subcategory":"Apparel",
            "type":"Manufacturing & Wholesale Goods"
        }
    ],
    "sg:phone":"+1 770 645 6459",
    "sg:postcode":"30075",
    "sg:province":"GA",
    "sg:tags":[
        "outerwear",
        "mfg"
    ],
    "wof:name":"Kimberlys Accessories",
    "wof:placetype":"venue"
},
  "geometry": {"coordinates":[-84.378114,34.01886],"type":"Point"}
}