{
  "type": "Feature",
  "properties": {
    "addr:full":"3630 Doroco Dr Atlanta GA 30340",
    "addr:housenumber":"3630",
    "addr:postcode":"30340",
    "addr:street":"Doroco Dr",
    "iso:country":"US",
    "sg:address":"3630 Doroco Dr",
    "sg:city":"Atlanta",
    "sg:classifiers":[
        {
            "category":"Professional",
            "subcategory":"Business Services",
            "type":"Services"
        },
        {
            "category":"Wholesale",
            "subcategory":"Non-durable Goods",
            "type":"Manufacturing & Wholesale Goods"
        }
    ],
    "sg:phone":"+1 770 939 4365",
    "sg:postcode":"30340",
    "sg:province":"GA",
    "sg:tags":[
        "packaging"
    ],
    "wof:name":"Spicer Packaging Company",
    "wof:placetype":"venue"
},
  "geometry": {"coordinates":[-84.237702,33.877334],"type":"Point"}
}