{
  "type": "Feature",
  "properties": {
    "addr:full":"702 2nd Ave Eastman GA 31023",
    "addr:housenumber":"702",
    "addr:postcode":"31023",
    "addr:street":"2Nd Ave",
    "iso:country":"US",
    "sg:address":"702 2nd Ave",
    "sg:city":"Eastman",
    "sg:classifiers":[
        {
            "category":"Health Services",
            "subcategory":"Health Practitioner",
            "type":"Services"
        },
        {
            "category":"Health Services",
            "subcategory":"Doctor",
            "type":"Services"
        }
    ],
    "sg:phone":"+1 478 374 5511",
    "sg:postcode":"31023",
    "sg:province":"GA",
    "sg:tags":[
        "acupuncture",
        "physician",
        "surgeon"
    ],
    "wof:name":"Eastman Acupuncture Clinic",
    "wof:placetype":"venue"
},
  "geometry": {"coordinates":[-83.181605,32.191345],"type":"Point"}
}