{
  "type": "Feature",
  "properties": {
    "iso:country":"US",
    "sg:address":"10006 Lake Union Hill Way",
    "sg:city":"Alpharetta",
    "sg:classifiers":[
        {
            "category":"Utilities",
            "subcategory":"Telephone",
            "type":"Services"
        }
    ],
    "sg:phone":"+1 678 393 0287",
    "sg:postcode":"30004",
    "sg:province":"GA",
    "sg:tags":[
        "communications",
        "radiotelephone",
        "communication"
    ],
    "wof:name":"AT&T",
    "wof:placetype":"venue"
},
  "geometry": {"coordinates":[-84.27848299999999,34.0806],"type":"Point"}
}