{
  "type": "Feature",
  "properties": {
    "addr:full":"1874 Piedmont Rd NE Atlanta GA 30324",
    "addr:housenumber":"1874",
    "addr:postcode":"30324",
    "addr:street":"Piedmont Rd Ne",
    "iso:country":"US",
    "sg:address":"1874 Piedmont Rd NE",
    "sg:city":"Atlanta",
    "sg:classifiers":[
        {
            "category":"Personal",
            "subcategory":"Beauty Salon",
            "type":"Services"
        },
        {
            "category":"Personal",
            "subcategory":"Barber",
            "type":"Services"
        }
    ],
    "sg:phone":"+1 404 815 0404",
    "sg:postcode":"30324",
    "sg:province":"GA",
    "sg:tags":[
        "hair"
    ],
    "sg:website":"www.axiomsfm.com",
    "wof:name":"Axiom Salon For Men",
    "wof:placetype":"venue"
},
  "geometry": {"coordinates":[-84.366304,33.807233],"type":"Point"}
}