{
  "type": "Feature",
  "properties": {
    "addr:full":"2228 Tara Ln Brunswick GA 31520",
    "addr:housenumber":"2228",
    "addr:postcode":"31520",
    "addr:street":"Tara Ln",
    "iso:country":"US",
    "sg:address":"2228 Tara Ln",
    "sg:city":"Brunswick",
    "sg:classifiers":[
        {
            "category":"Insurance",
            "subcategory":"Hazard Insurance",
            "type":"Services"
        }
    ],
    "sg:phone":"+1 912 265 3481",
    "sg:postcode":"31520",
    "sg:province":"GA",
    "sg:tags":[
        "commercial",
        "business"
    ],
    "wof:name":"Anderson, Mcnear Jr Insurance Agency",
    "wof:placetype":"venue"
},
  "geometry": {"coordinates":[-81.494624,31.190423],"type":"Point"}
}