{
  "type": "Feature",
  "properties": {
    "iso:country":"US",
    "sg:address":"1200 Fort Benning Rd",
    "sg:city":"Columbus",
    "sg:classifiers":[
        {
            "category":"Retail",
            "subcategory":"Auto Repair",
            "type":"Services"
        }
    ],
    "sg:phone":"+1 706 689 1511",
    "sg:postcode":"31903",
    "sg:province":"GA",
    "sg:tags":[
        "repairing",
        "automobile"
    ],
    "wof:name":"T J's Auto Repair",
    "wof:placetype":"venue"
},
  "geometry": {"coordinates":[-84.940175,32.429815],"type":"Point"}
}