{
  "type": "Feature",
  "properties": {
    "addr:full":"2216 Breton Hunt Ln Suwanee GA 30024",
    "addr:housenumber":"2216",
    "addr:postcode":"30024",
    "addr:street":"Breton Hunt Ln",
    "iso:country":"US",
    "sg:address":"2216 Breton Hunt Ln",
    "sg:city":"Suwanee",
    "sg:classifiers":[
        {
            "category":"Home & Garden",
            "subcategory":"Building Materials",
            "type":"Retail Goods"
        }
    ],
    "sg:phone":"+1 770 831 7450",
    "sg:postcode":"30024",
    "sg:province":"GA",
    "sg:tags":[
        "door"
    ],
    "wof:name":"All About Garage Doors",
    "wof:placetype":"venue"
},
  "geometry": {"coordinates":[-84.09186699999999,34.048648],"type":"Point"}
}