{
  "type": "Feature",
  "properties": {
    "iso:country":"US",
    "sg:address":"2281 Midway Rd",
    "sg:city":"Douglasville",
    "sg:classifiers":[
        {
            "category":"Wholesale",
            "subcategory":"Construction Materials",
            "type":"Manufacturing & Wholesale Goods"
        }
    ],
    "sg:phone":"+1 770 942 0738",
    "sg:postcode":"30135",
    "sg:province":"GA",
    "sg:tags":[
        "fence"
    ],
    "wof:name":"Atlantic Fence Builders",
    "wof:placetype":"venue"
},
  "geometry": {"coordinates":[-84.698995,33.744234],"type":"Point"}
}