{
  "type": "Feature",
  "properties": {
    "addr:full":"1291 Green Oak Cir NW Lawrenceville GA 30043",
    "addr:housenumber":"1291",
    "addr:postcode":"30043",
    "addr:street":"Green Oak Cir Nw",
    "iso:country":"US",
    "sg:address":"1291 Green Oak Cir NW",
    "sg:city":"Lawrenceville",
    "sg:classifiers":[
        {
            "category":"Food & Beverages",
            "subcategory":"Groceries & Convenience Stores",
            "type":"Retail Goods"
        }
    ],
    "sg:phone":"+1 678 376 3788",
    "sg:postcode":"30043",
    "sg:province":"GA",
    "wof:name":"Escobar Corporation",
    "wof:placetype":"venue"
},
  "geometry": {"coordinates":[-84.019695,33.986587],"type":"Point"}
}