{
  "type": "Feature",
  "properties": {
    "addr:full":"5030 Buford Hwy NE Atlanta GA 30341",
    "addr:housenumber":"5030",
    "addr:postcode":"30341",
    "addr:street":"Buford Hwy Ne",
    "iso:country":"US",
    "sg:address":"5030 Buford Hwy NE",
    "sg:city":"Atlanta",
    "sg:classifiers":[
        {
            "category":"Local Transit",
            "type":"Transportation"
        }
    ],
    "sg:phone":"+1 770 986 8067",
    "sg:postcode":"30341",
    "sg:province":"GA",
    "wof:name":"Autobuses Adame Inc",
    "wof:placetype":"venue"
},
  "geometry": {"coordinates":[-84.286008,33.889798],"type":"Point"}
}