{
  "type": "Feature",
  "properties": {
    "addr:full":"108 Old Villanow Rd La Fayette GA 30728",
    "addr:housenumber":"108",
    "addr:postcode":"30728",
    "addr:street":"Old Villanow Rd",
    "iso:country":"US",
    "sg:address":"108 Old Villanow Rd",
    "sg:city":"La Fayette",
    "sg:classifiers":[
        {
            "category":"Professional",
            "subcategory":"Lawyer & Legal Services",
            "type":"Services"
        }
    ],
    "sg:phone":"+1 706 638 5609",
    "sg:postcode":"30728",
    "sg:province":"GA",
    "sg:tags":[
        "attorney"
    ],
    "wof:name":"Drug Prosecution",
    "wof:placetype":"venue"
},
  "geometry": {"coordinates":[-85.197335,34.695687],"type":"Point"}
}