{
  "type": "Feature",
  "properties": {
    "iso:country":"US",
    "sg:address":"954 Nicholson St",
    "sg:city":"Richland",
    "sg:classifiers":[
        {
            "category":"Retail",
            "subcategory":"Laundry & Dry Cleaning",
            "type":"Services"
        }
    ],
    "sg:phone":"+1 229 887 9007",
    "sg:postcode":"31825",
    "sg:province":"GA",
    "wof:name":"Olivers Alteration & Laundry",
    "wof:placetype":"venue"
},
  "geometry": {"coordinates":[-84.65301599999999,32.088918],"type":"Point"}
}