{
  "type": "Feature",
  "properties": {
    "addr:full":"1210 Howell Mill Rd Atlanta GA 30318",
    "addr:housenumber":"1210",
    "addr:postcode":"30318",
    "addr:street":"Howell Mill Rd",
    "iso:country":"US",
    "sg:address":"1210 Howell Mill Rd",
    "sg:city":"Atlanta",
    "sg:classifiers":[
        {
            "category":"Fast Food",
            "type":"Food & Drink"
        },
        {
            "category":"Restaurant",
            "type":"Food & Drink"
        },
        {
            "category":"Professional",
            "type":"Services"
        }
    ],
    "sg:phone":"+1 404 351 3700",
    "sg:postcode":"30318",
    "sg:province":"GA",
    "sg:tags":[
        "lunch",
        "take",
        "caterer",
        "brunch",
        "breakfast",
        "italian"
    ],
    "sg:website":"www.figopasta.com/",
    "wof:name":"Osteria del Figo",
    "wof:placetype":"venue"
},
  "geometry": {"coordinates":[-84.41171900000001,33.786678],"type":"Point"}
}