{
  "type": "Feature",
  "properties": {
    "iso:country":"US",
    "sg:address":"815 Old Alabama Rd SW",
    "sg:city":"Mableton",
    "sg:classifiers":[
        {
            "category":"Home & Garden",
            "subcategory":"Building Materials",
            "type":"Retail Goods"
        },
        {
            "category":"Professional",
            "subcategory":"Business Services",
            "type":"Services"
        }
    ],
    "sg:phone":"+1 678 945 1694",
    "sg:postcode":"30126",
    "sg:province":"GA",
    "sg:tags":[
        "marble-natural",
        "top",
        "counter",
        "marble-natural-wholesale",
        "granite",
        "manufacturer"
    ],
    "sg:website":"http://www.marbleandgranitedesigns.com",
    "wof:name":"Marble & Granite Design Corporation",
    "wof:placetype":"venue"
},
  "geometry": {"coordinates":[-84.577789,33.809021],"type":"Point"}
}