{
  "type": "Feature",
  "properties": {
    "addr:full":"1135 Woodstock Rd Roswell GA 30075",
    "addr:housenumber":"1135",
    "addr:postcode":"30075",
    "addr:street":"Woodstock Rd",
    "iso:country":"US",
    "sg:address":"1135 Woodstock Rd",
    "sg:city":"Roswell",
    "sg:classifiers":[
        {
            "category":"Banks & Credit Unions",
            "subcategory":"Investment Brokerage",
            "type":"Services"
        }
    ],
    "sg:phone":"+1 678 461 0158",
    "sg:postcode":"30075",
    "sg:province":"GA",
    "sg:tags":[
        "security"
    ],
    "wof:name":"E Trade Financial Zone",
    "wof:placetype":"venue"
},
  "geometry": {"coordinates":[-84.397902,34.062105],"type":"Point"}
}