{
  "type": "Feature",
  "properties": {
    "iso:country":"US",
    "sg:address":"2035 Amber Creek Dr",
    "sg:city":"Buford",
    "sg:classifiers":[
        {
            "category":"Building & Trades",
            "subcategory":"Construction",
            "type":"Services"
        }
    ],
    "sg:phone":"+1 770 682 7262",
    "sg:postcode":"30519",
    "sg:province":"GA",
    "sg:tags":[
        "contractor"
    ],
    "wof:name":"C P C Services",
    "wof:placetype":"venue"
},
  "geometry": {"coordinates":[-83.93915800000001,34.049144],"type":"Point"}
}