{
  "type": "Feature",
  "properties": {
    "iso:country":"US",
    "sg:address":"375 Ernest W Barrett Pkwy NW",
    "sg:city":"Kennesaw",
    "sg:classifiers":[
        {
            "category":"Autos & Motor Vehicles",
            "subcategory":"Auto Supplies",
            "type":"Retail Goods"
        }
    ],
    "sg:phone":"+1 770 919 8473",
    "sg:postcode":"30144",
    "sg:province":"GA",
    "sg:tags":[
        "wheel",
        "tire"
    ],
    "sg:website":"http://www.big10tires.com",
    "wof:name":"Big 10 Tires",
    "wof:placetype":"venue"
},
  "geometry": {"coordinates":[-84.56118499999999,34.013876],"type":"Point"}
}