{
  "type": "Feature",
  "properties": {
    "addr:full":"5180 Roswell Road NE Atlanta GA 30342",
    "addr:housenumber":"5180",
    "addr:postcode":"30342",
    "addr:street":"Roswell Road Ne",
    "iso:country":"US",
    "sg:address":"5180 Roswell Road NE",
    "sg:city":"Atlanta",
    "sg:classifiers":[
        {
            "category":"Professional",
            "subcategory":"Lawyer & Legal Services",
            "type":"Services"
        }
    ],
    "sg:phone":"+1 404 843 2002",
    "sg:postcode":"30342",
    "sg:province":"GA",
    "wof:name":"Gort Cliffe Lane Atty",
    "wof:placetype":"venue"
},
  "geometry": {"coordinates":[-84.381421,33.896158],"type":"Point"}
}