{
  "type": "Feature",
  "properties": {
    "iso:country":"US",
    "sg:address":"301 S Zetterower Ave",
    "sg:city":"Statesboro",
    "sg:classifiers":[
        {
            "category":"Retail",
            "subcategory":"Laundry & Dry Cleaning",
            "type":"Services"
        },
        {
            "category":"Shopping",
            "subcategory":"Clothing, Apparel, & Fashions",
            "type":"Retail Goods"
        }
    ],
    "sg:phone":"+1 912 764 9931",
    "sg:postcode":"30458",
    "sg:province":"GA",
    "sg:tags":[
        "alteration"
    ],
    "wof:name":"Teresa's Alteration Shop",
    "wof:placetype":"venue"
},
  "geometry": {"coordinates":[-81.779656,32.441601],"type":"Point"}
}