{
  "type": "Feature",
  "properties": {
    "addr:full":"1468 Southland Cir NW Atlanta GA 30318",
    "addr:housenumber":"1468",
    "addr:postcode":"30318",
    "addr:street":"Southland Cir Nw",
    "iso:country":"US",
    "sg:address":"1468 Southland Cir NW",
    "sg:city":"Atlanta",
    "sg:classifiers":[
        {
            "category":"Manufacturing",
            "subcategory":"Rubber & Plastics",
            "type":"Manufacturing & Wholesale Goods"
        },
        {
            "category":"Professional",
            "subcategory":"Computer Services",
            "type":"Services"
        }
    ],
    "sg:phone":"+1 404 350 0540",
    "sg:postcode":"30318",
    "sg:province":"GA",
    "sg:tags":[
        "product",
        "datum",
        "mfg"
    ],
    "wof:name":"Mars Associates Inc",
    "wof:placetype":"venue"
},
  "geometry": {"coordinates":[-84.431166,33.798404],"type":"Point"}
}