{
  "type": "Feature",
  "properties": {
    "iso:country":"US",
    "sg:address":"2027 Blackwell Rd",
    "sg:city":"Marietta",
    "sg:classifiers":[
        {
            "category":"Recreation",
            "type":"Entertainment"
        }
    ],
    "sg:phone":"+1 770 517 6919",
    "sg:postcode":"30066",
    "sg:province":"GA",
    "sg:tags":[
        "club",
        "baseball"
    ],
    "wof:name":"Doyle Baseball Circle-Chapions",
    "wof:placetype":"venue"
},
  "geometry": {"coordinates":[-84.491089,34.043603],"type":"Point"}
}