{
  "type": "Feature",
  "properties": {
    "addr:full":"101 W Currahee St Toccoa GA 30577",
    "addr:housenumber":"101",
    "addr:postcode":"30577",
    "addr:street":"W Currahee St",
    "iso:country":"US",
    "sg:address":"101 W Currahee St",
    "sg:city":"Toccoa",
    "sg:classifiers":[
        {
            "category":"Shopping",
            "subcategory":"Computers & Home Electronics",
            "type":"Retail Goods"
        }
    ],
    "sg:phone":"+1 706 886 3430",
    "sg:postcode":"30577",
    "sg:province":"GA",
    "sg:tags":[
        "repair",
        "television",
        "video",
        "stereo",
        "system"
    ],
    "wof:name":"Advanced Electronics & Video",
    "wof:placetype":"venue"
},
  "geometry": {"coordinates":[-83.33303600000001,34.577338],"type":"Point"}
}