{
  "type": "Feature",
  "properties": {
    "addr:full":"1785 Saddleridge Dr Cumming GA 30041",
    "addr:housenumber":"1785",
    "addr:postcode":"30041",
    "addr:street":"Saddleridge Dr",
    "iso:country":"US",
    "sg:address":"1785 Saddleridge Dr",
    "sg:city":"Cumming",
    "sg:classifiers":[
        {
            "category":"Building & Trades",
            "subcategory":"Construction",
            "type":"Services"
        }
    ],
    "sg:phone":"+1 770 889 3849",
    "sg:postcode":"30041",
    "sg:province":"GA",
    "sg:tags":[
        "house"
    ],
    "wof:name":"R Teem Construction Inc",
    "wof:placetype":"venue"
},
  "geometry": {"coordinates":[-84.18131200000001,34.130788],"type":"Point"}
}