{
  "type": "Feature",
  "properties": {
    "addr:full":"3844 Laurel Crest Dr Snellville GA 30039",
    "addr:housenumber":"3844",
    "addr:postcode":"30039",
    "addr:street":"Laurel Crest Dr",
    "iso:country":"US",
    "sg:address":"3844 Laurel Crest Dr",
    "sg:city":"Snellville",
    "sg:classifiers":[
        {
            "category":"Manufacturing",
            "subcategory":"Tools & Machinery",
            "type":"Manufacturing & Wholesale Goods"
        }
    ],
    "sg:phone":"+1 770 708 8584",
    "sg:postcode":"30039",
    "sg:province":"GA",
    "sg:tags":[
        "measuring",
        "instrument",
        "electrical",
        "mfg"
    ],
    "wof:name":"Wendal Roane",
    "wof:placetype":"venue"
},
  "geometry": {"coordinates":[-84.036935,33.795671],"type":"Point"}
}