{
  "type": "Feature",
  "properties": {
    "addr:full":"17 Johnson St Hazlehurst GA 31539",
    "addr:housenumber":"17",
    "addr:postcode":"31539",
    "addr:street":"Johnson St",
    "iso:country":"US",
    "sg:address":"17 Johnson St",
    "sg:city":"Hazlehurst",
    "sg:classifiers":[
        {
            "category":"Health Services",
            "subcategory":"Doctor",
            "type":"Services"
        }
    ],
    "sg:phone":"+1 912 375 0390",
    "sg:postcode":"31539",
    "sg:province":"GA",
    "sg:tags":[
        "physician",
        "surgeon"
    ],
    "wof:name":"H Clark Deriso PC",
    "wof:placetype":"venue"
},
  "geometry": {"coordinates":[-82.602861,31.861897],"type":"Point"}
}