{
  "type": "Feature",
  "properties": {
    "iso:country":"US",
    "sg:address":"1401 W Paces Ferry Rd NW",
    "sg:city":"Atlanta",
    "sg:classifiers":[
        {
            "category":"Manufacturing",
            "subcategory":"Chemicals & Compounds",
            "type":"Manufacturing & Wholesale Goods"
        }
    ],
    "sg:phone":"+1 770 869 8780",
    "sg:postcode":"30327",
    "sg:province":"GA",
    "sg:tags":[
        "manufacture",
        "body",
        "product",
        "bath"
    ],
    "wof:name":"Rinse Soap",
    "wof:placetype":"venue"
},
  "geometry": {"coordinates":[-84.432334,33.848397],"type":"Point"}
}