{
  "type": "Feature",
  "properties": {
    "iso:country":"US",
    "sg:address":"124 Hinton Dr",
    "sg:city":"Mcdonough",
    "sg:classifiers":[
        {
            "category":"Cinema",
            "subcategory":"Movie Rental",
            "type":"Entertainment"
        }
    ],
    "sg:phone":"+1 678 583 2117",
    "sg:postcode":"30253",
    "sg:province":"GA",
    "sg:tags":[
        "leasing",
        "video",
        "disc",
        "tape"
    ],
    "wof:name":"Movie Gallery",
    "wof:placetype":"venue"
},
  "geometry": {"coordinates":[-84.151982,33.428965],"type":"Point"}
}