{
  "type": "Feature",
  "properties": {
    "iso:country":"US",
    "sg:address":"6354 Jimmy Carter Blvd",
    "sg:city":"Norcross",
    "sg:classifiers":[
        {
            "category":"Restaurant",
            "type":"Food & Drink"
        }
    ],
    "sg:phone":"+1 770 246 0222",
    "sg:postcode":"30093",
    "sg:province":"GA",
    "sg:tags":[
        "eating"
    ],
    "wof:name":"El Adobe",
    "wof:placetype":"venue"
},
  "geometry": {"coordinates":[-84.22191100000001,33.931208],"type":"Point"}
}