{
  "type": "Feature",
  "properties": {
    "addr:full":"7804 Abercorn St Savannah GA 31406",
    "addr:housenumber":"7804",
    "addr:postcode":"31406",
    "addr:street":"Abercorn St",
    "iso:country":"US",
    "sg:address":"7804 Abercorn St",
    "sg:city":"Savannah",
    "sg:classifiers":[
        {
            "category":"Personal",
            "subcategory":"Nail Salon",
            "type":"Services"
        }
    ],
    "sg:phone":"+1 912 355 3510",
    "sg:postcode":"31406",
    "sg:province":"GA",
    "wof:name":"Tip Top Nails",
    "wof:placetype":"venue"
},
  "geometry": {"coordinates":[-81.117265,32.005062],"type":"Point"}
}