{
  "type": "Feature",
  "properties": {
    "iso:country":"US",
    "sg:address":"2121 Lawrenceville Suwanee Rd",
    "sg:city":"Suwanee",
    "sg:classifiers":[
        {
            "category":"Banks & Credit Unions",
            "subcategory":"Bank",
            "type":"Services"
        }
    ],
    "sg:phone":"+1 770 822 0176",
    "sg:postcode":"30024",
    "sg:province":"GA",
    "sg:tags":[
        "state",
        "commercial"
    ],
    "sg:website":"www.ironstonebank.com",
    "wof:name":"Ironstone Bank",
    "wof:placetype":"venue"
},
  "geometry": {"coordinates":[-84.040228,34.003174],"type":"Point"}
}