{
  "type": "Feature",
  "properties": {
    "addr:full":"2675 N Decatur Rd Ste 404 Decatur GA 30033",
    "addr:housenumber":"2675",
    "addr:postcode":"30033",
    "addr:street":"N Decatur Rd Ste 404",
    "iso:country":"US",
    "sg:address":"2675 N Decatur Rd Ste 404",
    "sg:city":"Decatur",
    "sg:classifiers":[
        {
            "category":"Health Services",
            "subcategory":"Doctor",
            "type":"Services"
        }
    ],
    "sg:phone":"+1 404 294 4761",
    "sg:postcode":"30033",
    "sg:province":"GA",
    "wof:name":"Gottlieb George R MD PC",
    "wof:placetype":"venue"
},
  "geometry": {"coordinates":[-84.284401,33.792099],"type":"Point"}
}