{
  "type": "Feature",
  "properties": {
    "iso:country":"US",
    "sg:address":"105 Dogwood Ln",
    "sg:city":"Toccoa",
    "sg:classifiers":[
        {
            "category":"Professional",
            "subcategory":"Business Services",
            "type":"Services"
        }
    ],
    "sg:phone":"+1 706 886 7954",
    "sg:postcode":"30577",
    "sg:province":"GA",
    "wof:name":"H&K Enterprises",
    "wof:placetype":"venue"
},
  "geometry": {"coordinates":[-83.31234000000001,34.563017],"type":"Point"}
}