{
  "type": "Feature",
  "properties": {
    "iso:country":"US",
    "sg:address":"5945 State Bridge Rd",
    "sg:city":"Duluth",
    "sg:classifiers":[
        {
            "category":"Food & Beverages",
            "subcategory":"Groceries & Convenience Stores",
            "type":"Retail Goods"
        }
    ],
    "sg:phone":"+1 678 514 2400",
    "sg:postcode":"30097",
    "sg:province":"GA",
    "sg:website":"www.wholefoodsmarket.com",
    "wof:name":"Whole Foods Market",
    "wof:placetype":"venue"
},
  "geometry": {"coordinates":[-84.18437,34.014517],"type":"Point"}
}