{
  "type": "Feature",
  "properties": {
    "addr:full":"301 Petrol Pt Peachtree City GA 30269",
    "addr:housenumber":"301",
    "addr:postcode":"30269",
    "addr:street":"Petrol Pt",
    "iso:country":"US",
    "sg:address":"301 Petrol Pt",
    "sg:city":"Peachtree City",
    "sg:classifiers":[
        {
            "category":"Restaurant",
            "type":"Food & Drink"
        }
    ],
    "sg:menulink":"http://www.allmenus.com/ga/tyrone/101715-huddle-house/menu/",
    "sg:phone":"+1 770 487 2421",
    "sg:postcode":"30269",
    "sg:province":"GA",
    "sg:tags":[
        "american",
        "diner"
    ],
    "wof:name":"Huddle House",
    "wof:placetype":"venue"
},
  "geometry": {"coordinates":[-84.562872,33.413779],"type":"Point"}
}