{
  "type": "Feature",
  "properties": {
    "iso:country":"US",
    "sg:address":"2420 Vivian Dr",
    "sg:city":"Macon",
    "sg:classifiers":[
        {
            "category":"Building & Trades",
            "subcategory":"Cleaning & Sanitation",
            "type":"Services"
        }
    ],
    "sg:phone":"+1 478 781 0621",
    "sg:postcode":"31206",
    "sg:province":"GA",
    "sg:tags":[
        "maintenance"
    ],
    "wof:name":"Dolls Cleaning Service",
    "wof:placetype":"venue"
},
  "geometry": {"coordinates":[-83.701733,32.785633],"type":"Point"}
}