{
  "type": "Feature",
  "properties": {
    "addr:full":"487 Tim Brown Rd Manchester GA 31816",
    "addr:housenumber":"487",
    "addr:postcode":"31816",
    "addr:street":"Tim Brown Rd",
    "iso:country":"US",
    "sg:address":"487 Tim Brown Rd",
    "sg:city":"Manchester",
    "sg:classifiers":[
        {
            "category":"Organizations",
            "subcategory":"Religious Organization",
            "type":"Services"
        }
    ],
    "sg:phone":"+1 706 846 8059",
    "sg:postcode":"31816",
    "sg:province":"GA",
    "wof:name":"Mt Sinai Methodist Church",
    "wof:placetype":"venue"
},
  "geometry": {"coordinates":[-84.62551499999999,32.860536],"type":"Point"}
}