{
  "type": "Feature",
  "properties": {
    "iso:country":"US",
    "sg:address":"71 Mc Ferrin Cir",
    "sg:city":"Riverdale",
    "sg:classifiers":[
        {
            "category":"Building & Trades",
            "subcategory":"Construction",
            "type":"Services"
        }
    ],
    "sg:phone":"+1 770 478 1686",
    "sg:postcode":"30274",
    "sg:province":"GA",
    "sg:tags":[
        "general",
        "contractor"
    ],
    "wof:name":"James Edward Keeno",
    "wof:placetype":"venue"
},
  "geometry": {"coordinates":[-84.39122,33.575904],"type":"Point"}
}