{
  "type": "Feature",
  "properties": {
    "iso:country":"US",
    "sg:address":"540 Marietta Hwy",
    "sg:city":"Roswell",
    "sg:classifiers":[
        {
            "category":"Social Services",
            "subcategory":"Adult Care",
            "type":"Services"
        }
    ],
    "sg:phone":"+1 770 641 1500",
    "sg:postcode":"30075",
    "sg:province":"GA",
    "sg:tags":[
        "home",
        "residential"
    ],
    "wof:name":"Just People Village",
    "wof:placetype":"venue"
},
  "geometry": {"coordinates":[-84.378839,34.010381],"type":"Point"}
}