{
  "type": "Feature",
  "properties": {
    "iso:country":"US",
    "sg:address":"556 Hambrick Sq",
    "sg:city":"Stone Mountain",
    "sg:classifiers":[
        {
            "category":"Shopping",
            "subcategory":"Clothing, Apparel, & Fashions",
            "type":"Retail Goods"
        }
    ],
    "sg:phone":"+1 404 298 5009",
    "sg:postcode":"30083",
    "sg:province":"GA",
    "wof:name":"Accessory Express Showcas",
    "wof:placetype":"venue"
},
  "geometry": {"coordinates":[-84.212853,33.791672],"type":"Point"}
}