{
  "type": "Feature",
  "properties": {
    "addr:full":"5715 Oakbrook Pkwy Norcross GA 30093",
    "addr:housenumber":"5715",
    "addr:postcode":"30093",
    "addr:street":"Oakbrook Pkwy",
    "iso:country":"US",
    "sg:address":"5715 Oakbrook Pkwy",
    "sg:city":"Norcross",
    "sg:classifiers":[
        {
            "category":"Home & Garden",
            "subcategory":"Carpets & Floor Coverings",
            "type":"Retail Goods"
        }
    ],
    "sg:phone":"+1 770 263 0579",
    "sg:postcode":"30093",
    "sg:province":"GA",
    "sg:tags":[
        "flooring"
    ],
    "wof:name":"Flooring Services Llc",
    "wof:placetype":"venue"
},
  "geometry": {"coordinates":[-84.193729,33.917416],"type":"Point"}
}