{
  "type": "Feature",
  "properties": {
    "iso:country":"US",
    "sg:address":"315 W Ponce de Leon Ave",
    "sg:city":"Decatur",
    "sg:classifiers":[
        {
            "category":"Shopping",
            "type":"Retail Goods"
        },
        {
            "category":"Organizations",
            "subcategory":"Non-profit Organization",
            "type":"Services"
        }
    ],
    "sg:phone":"+1 404 371 8404",
    "sg:postcode":"30030",
    "sg:province":"GA",
    "sg:tags":[
        "supply",
        "fund",
        "games",
        "merchandise",
        "raising"
    ],
    "wof:name":"Fund For Southern Communities Inc",
    "wof:placetype":"venue"
},
  "geometry": {"coordinates":[-84.300082,33.775613],"type":"Point"}
}