{
  "type": "Feature",
  "properties": {
    "iso:country":"US",
    "sg:address":"1316 Augusta Ave",
    "sg:city":"Savannah",
    "sg:classifiers":[
        {
            "category":"Social Services",
            "subcategory":"Child Care",
            "type":"Services"
        }
    ],
    "sg:phone":"+1 912 233 7373",
    "sg:postcode":"31415",
    "sg:province":"GA",
    "sg:tags":[
        "day"
    ],
    "wof:name":"Mrs J Preschool",
    "wof:placetype":"venue"
},
  "geometry": {"coordinates":[-81.115718,32.080841],"type":"Point"}
}