{
  "type": "Feature",
  "properties": {
    "iso:country":"US",
    "sg:address":"710 Main St",
    "sg:city":"Willacoochee",
    "sg:classifiers":[
        {
            "category":"Manufacturing",
            "subcategory":"Food",
            "type":"Manufacturing & Wholesale Goods"
        }
    ],
    "sg:phone":"+1 912 534 6200",
    "sg:postcode":"31650",
    "sg:province":"GA",
    "sg:tags":[
        "mfg"
    ],
    "wof:name":"Roscoe Allen Co",
    "wof:placetype":"venue"
},
  "geometry": {"coordinates":[-83.035763,31.337479],"type":"Point"}
}