{
  "type": "Feature",
  "properties": {
    "iso:country":"US",
    "sg:address":"6458 Dawson Blvd",
    "sg:city":"Norcross",
    "sg:classifiers":[
        {
            "category":"Arts & Performance",
            "subcategory":"Art Gallery",
            "type":"Entertainment"
        }
    ],
    "sg:phone":"+1 770 840 7701",
    "sg:postcode":"30093",
    "sg:province":"GA",
    "sg:website":"www.regencyfineart.com",
    "wof:name":"Regency Fine Art",
    "wof:placetype":"venue"
},
  "geometry": {"coordinates":[-84.220001,33.910198],"type":"Point"}
}