{
  "type": "Feature",
  "properties": {
    "addr:full":"623 Scott St Hinesville GA 31313",
    "addr:housenumber":"623",
    "addr:postcode":"31313",
    "addr:street":"Scott St",
    "iso:country":"US",
    "sg:address":"623 Scott St",
    "sg:city":"Hinesville",
    "sg:classifiers":[
        {
            "category":"Building & Trades",
            "subcategory":"Construction",
            "type":"Services"
        }
    ],
    "sg:phone":"+1 912 369 4965",
    "sg:postcode":"31313",
    "sg:province":"GA",
    "sg:tags":[
        "home",
        "remodeling"
    ],
    "wof:name":"Done Right",
    "wof:placetype":"venue"
},
  "geometry": {"coordinates":[-81.612638,31.843112],"type":"Point"}
}