{
  "type": "Feature",
  "properties": {
    "iso:country":"US",
    "sg:address":"6323 Laurel Wood Trl",
    "sg:city":"Flowery Branch",
    "sg:classifiers":[
        {
            "category":"Professional",
            "type":"Services"
        }
    ],
    "sg:phone":"+1 678 523 7836",
    "sg:postcode":"30542",
    "sg:province":"GA",
    "wof:name":"Moons Sushi Service",
    "wof:placetype":"venue"
},
  "geometry": {"coordinates":[-83.945396,34.168134],"type":"Point"}
}