{
  "type": "Feature",
  "properties": {
    "addr:full":"1736 Cooper Lake Dr SE Smyrna GA 30080",
    "addr:housenumber":"1736",
    "addr:postcode":"30080",
    "addr:street":"Cooper Lake Dr Se",
    "iso:country":"US",
    "sg:address":"1736 Cooper Lake Dr SE",
    "sg:city":"Smyrna",
    "sg:classifiers":[
        {
            "category":"Health Services",
            "subcategory":"Chiropractor",
            "type":"Services"
        }
    ],
    "sg:phone":"+1 770 437 1767",
    "sg:postcode":"30080",
    "sg:province":"GA",
    "sg:tags":[
        "chiropractic"
    ],
    "wof:name":"Access To Healing Inc",
    "wof:placetype":"venue"
},
  "geometry": {"coordinates":[-84.50427500000001,33.849542],"type":"Point"}
}