{
  "type": "Feature",
  "properties": {
    "iso:country":"US",
    "sg:address":"2720 Holcomb Bridge Rd",
    "sg:city":"Alpharetta",
    "sg:classifiers":[
        {
            "category":"Social Services",
            "subcategory":"Adult Care",
            "type":"Services"
        }
    ],
    "sg:phone":"+1 770 998 3292",
    "sg:postcode":"30022",
    "sg:province":"GA",
    "sg:tags":[
        "a",
        "home",
        "for",
        "retarded"
    ],
    "wof:name":"Holcombe Bridge Group Home",
    "wof:placetype":"venue"
},
  "geometry": {"coordinates":[-84.28106099999999,33.994239],"type":"Point"}
}