{
  "type": "Feature",
  "properties": {
    "iso:country":"US",
    "sg:address":"437 Moreland Ave NE",
    "sg:city":"Atlanta",
    "sg:classifiers":[
        {
            "category":"Bars & Pubs",
            "type":"Food & Drink"
        },
        {
            "category":"Arts & Performance",
            "subcategory":"Music",
            "type":"Entertainment"
        }
    ],
    "sg:phone":"+1 404 681 9018",
    "sg:postcode":"30307",
    "sg:province":"GA",
    "sg:tags":[
        "venue"
    ],
    "sg:website":"www.starbar.net",
    "wof:name":"Star Community Bar",
    "wof:placetype":"venue"
},
  "geometry": {"coordinates":[-84.34904,33.766249],"type":"Point"}
}