{
  "type": "Feature",
  "properties": {
    "iso:country":"US",
    "sg:address":"425 E. Crossville Rd Suite 213",
    "sg:city":"Roswell",
    "sg:classifiers":[
        {
            "category":"Professional",
            "subcategory":"Advertising",
            "type":"Services"
        },
        {
            "category":"Communications",
            "subcategory":"Newspaper",
            "type":"Services"
        },
        {
            "category":"Communications",
            "type":"Services"
        }
    ],
    "sg:phone":"+1 404 641 9134",
    "sg:postcode":"30075",
    "sg:province":"GA",
    "sg:tags":[
        "marketing",
        "design",
        "web"
    ],
    "sg:website":"www.NewThoughtMarketing.com",
    "wof:name":"New Thought Marketing",
    "wof:placetype":"venue"
},
  "geometry": {"coordinates":[-84.348581,34.039727],"type":"Point"}
}