{
  "type": "Feature",
  "properties": {
    "addr:full":"323 Summer Xing Atlanta GA 30350",
    "addr:housenumber":"323",
    "addr:postcode":"30350",
    "addr:street":"Summer Xing",
    "iso:country":"US",
    "sg:address":"323 Summer Xing",
    "sg:city":"Atlanta",
    "sg:classifiers":[
        {
            "category":"Building & Trades",
            "subcategory":"Cleaning & Sanitation",
            "type":"Services"
        }
    ],
    "sg:phone":"+1 770 642 7366",
    "sg:postcode":"30350",
    "sg:province":"GA",
    "sg:tags":[
        "janitor"
    ],
    "wof:name":"Aspen Cleaning",
    "wof:placetype":"venue"
},
  "geometry": {"coordinates":[-84.334496,34.000189],"type":"Point"}
}