{
  "type": "Feature",
  "properties": {
    "iso:country":"US",
    "sg:address":"10450 Medlock Bridge Rd",
    "sg:city":"Duluth",
    "sg:classifiers":[
        {
            "category":"Personal",
            "subcategory":"Psychics & Astrologers",
            "type":"Services"
        }
    ],
    "sg:phone":"+1 770 622 2000",
    "sg:postcode":"30097",
    "sg:province":"GA",
    "sg:tags":[
        "medium"
    ],
    "wof:name":"Psychic Studio",
    "wof:placetype":"venue"
},
  "geometry": {"coordinates":[-84.185683,34.034964],"type":"Point"}
}