{
  "type": "Feature",
  "properties": {
    "addr:full":"303 Hwy 138 Riverdale GA 30274",
    "addr:housenumber":"303",
    "addr:postcode":"30274",
    "addr:street":"Hwy 138",
    "iso:country":"US",
    "sg:address":"303 Hwy 138",
    "sg:city":"Riverdale",
    "sg:classifiers":[
        {
            "category":"Retail",
            "subcategory":"Storage",
            "type":"Services"
        }
    ],
    "sg:phone":"+1 866 838 2192",
    "sg:postcode":"30274",
    "sg:province":"GA",
    "sg:tags":[
        "self"
    ],
    "sg:website":"www.unclebobs.com",
    "wof:name":"Uncle Bob's Self Storage",
    "wof:placetype":"venue"
},
  "geometry": {"coordinates":[-84.444878,33.550253],"type":"Point"}
}