{
  "type": "Feature",
  "properties": {
    "iso:country":"US",
    "sg:address":"215 Mossy Hollow",
    "sg:city":"Newnan",
    "sg:classifiers":[
        {
            "category":"Building & Trades",
            "subcategory":"Landscaping Services",
            "type":"Services"
        }
    ],
    "sg:phone":"+1 770 252 5225",
    "sg:postcode":"30265",
    "sg:province":"GA",
    "wof:name":"Tree Tech Tree Service",
    "wof:placetype":"venue"
},
  "geometry": {"coordinates":[-84.677767,33.418487],"type":"Point"}
}