{
  "type": "Feature",
  "properties": {
    "iso:country":"US",
    "sg:address":"1944 Maddox Rd",
    "sg:city":"Hoschton",
    "sg:classifiers":[
        {
            "category":"Autos & Motor Vehicles",
            "subcategory":"Motorcycle Sales",
            "type":"Retail Goods"
        }
    ],
    "sg:phone":"+1 404 668 1025",
    "sg:postcode":"30548",
    "sg:province":"GA",
    "sg:tags":[
        "scooter"
    ],
    "wof:name":"D & D Cycle & Auto Brokers",
    "wof:placetype":"venue"
},
  "geometry": {"coordinates":[-83.737776,34.114113],"type":"Point"}
}