{
  "type": "Feature",
  "properties": {
    "addr:full":"1106 Cobb Xing SE Marietta GA 30080",
    "addr:housenumber":"1106",
    "addr:postcode":"30080",
    "addr:street":"Cobb Xing Se",
    "iso:country":"US",
    "sg:address":"1106 Cobb Xing SE",
    "sg:city":"Marietta",
    "sg:classifiers":[
        {
            "category":"Home & Garden",
            "subcategory":"Household Appliances",
            "type":"Retail Goods"
        }
    ],
    "sg:phone":"+1 770 424 1605",
    "sg:postcode":"30080",
    "sg:province":"GA",
    "wof:name":"Abbey Appliances Co",
    "wof:placetype":"venue"
},
  "geometry": {"coordinates":[-84.506118,33.923903],"type":"Point"}
}