{
  "type": "Feature",
  "properties": {
    "addr:full":"930 Newton Bridge Rd Athens GA 30607",
    "addr:housenumber":"930",
    "addr:postcode":"30607",
    "addr:street":"Newton Bridge Rd",
    "iso:country":"US",
    "sg:address":"930 Newton Bridge Rd",
    "sg:city":"Athens",
    "sg:classifiers":[
        {
            "category":"Shopping",
            "type":"Retail Goods"
        }
    ],
    "sg:phone":"+1 706 549 6277",
    "sg:postcode":"30607",
    "sg:province":"GA",
    "sg:tags":[
        "pet",
        "shop"
    ],
    "wof:name":"Gold KIST Inc",
    "wof:placetype":"venue"
},
  "geometry": {"coordinates":[-83.401213,34.004086],"type":"Point"}
}