{
  "type": "Feature",
  "properties": {
    "addr:full":"3475 Oak Valley Rd NE Atlanta GA 30326",
    "addr:housenumber":"3475",
    "addr:postcode":"30326",
    "addr:street":"Oak Valley Rd Ne",
    "iso:country":"US",
    "sg:address":"3475 Oak Valley Rd NE",
    "sg:city":"Atlanta",
    "sg:classifiers":[
        {
            "category":"Professional",
            "subcategory":"Management & Consulting",
            "type":"Services"
        }
    ],
    "sg:phone":"+1 404 467 4405",
    "sg:postcode":"30326",
    "sg:province":"GA",
    "wof:name":"Demiurge Consulting",
    "wof:placetype":"venue"
},
  "geometry": {"coordinates":[-84.35973300000001,33.850062],"type":"Point"}
}