{
  "type": "Feature",
  "properties": {
    "iso:country":"US",
    "sg:address":"20 Jonesboro St",
    "sg:city":"Mcdonough",
    "sg:classifiers":[
        {
            "category":"Professional",
            "subcategory":"Lawyer & Legal Services",
            "type":"Services"
        }
    ],
    "sg:phone":"+1 770 938 1061",
    "sg:postcode":"30253",
    "sg:province":"GA",
    "sg:tags":[
        "attorney"
    ],
    "wof:name":"Mechem & Scott LLC",
    "wof:placetype":"venue"
},
  "geometry": {"coordinates":[-84.147667,33.447694],"type":"Point"}
}