{
  "type": "Feature",
  "properties": {
    "addr:full":"30 Ridge Rd Covington GA 30016",
    "addr:housenumber":"30",
    "addr:postcode":"30016",
    "addr:street":"Ridge Rd",
    "iso:country":"US",
    "sg:address":"30 Ridge Rd",
    "sg:city":"Covington",
    "sg:classifiers":[
        {
            "category":"Building & Trades",
            "subcategory":"Plumbing",
            "type":"Services"
        }
    ],
    "sg:phone":"+1 770 784 7631",
    "sg:postcode":"30016",
    "sg:province":"GA",
    "sg:tags":[
        "mechanical",
        "contractor"
    ],
    "wof:name":"Prestige Mech Contractors",
    "wof:placetype":"venue"
},
  "geometry": {"coordinates":[-83.93710799999999,33.54421],"type":"Point"}
}