{
  "type": "Feature",
  "properties": {
    "iso:country":"US",
    "sg:address":"4295 Thurmond Rd",
    "sg:city":"Forest Park",
    "sg:classifiers":[
        {
            "category":"Education",
            "subcategory":"Special Training",
            "type":"Public Place"
        }
    ],
    "sg:phone":"+1 404 608 8608",
    "sg:postcode":"30297",
    "sg:province":"GA",
    "sg:tags":[
        "instruction",
        "driving"
    ],
    "sg:website":"www.americasdrivingforce.com",
    "wof:name":"America's Driving Force Inc",
    "wof:placetype":"venue"
},
  "geometry": {"coordinates":[-84.357798,33.636841],"type":"Point"}
}