{
  "type": "Feature",
  "properties": {
    "iso:country":"US",
    "sg:address":"879 Hemphill Ave NW",
    "sg:city":"Atlanta",
    "sg:classifiers":[
        {
            "category":"Government",
            "subcategory":"Police Station",
            "type":"Public Place"
        }
    ],
    "sg:phone":"+1 404 894 2500",
    "sg:postcode":"30318",
    "sg:province":"GA",
    "sg:tags":[
        "protection"
    ],
    "wof:name":"Georgia Tech Cmpus Police Dept",
    "wof:placetype":"venue"
},
  "geometry": {"coordinates":[-84.401366,33.778546],"type":"Point"}
}