{
  "type": "Feature",
  "properties": {
    "iso:country":"US",
    "sg:address":"145 N Marietta Pkwy NE Ste D",
    "sg:city":"Marietta",
    "sg:classifiers":[
        {
            "category":"Health Services",
            "subcategory":"Chiropractor",
            "type":"Services"
        }
    ],
    "sg:phone":"+1 770 426 9707",
    "sg:postcode":"30060",
    "sg:province":"GA",
    "wof:name":"Pizza Bradford J DC Dr",
    "wof:placetype":"venue"
},
  "geometry": {"coordinates":[-84.5485,33.959],"type":"Point"}
}