{
  "type": "Feature",
  "properties": {
    "addr:full":"306 Willow Bend Rd Peachtree City GA 30269",
    "addr:housenumber":"306",
    "addr:postcode":"30269",
    "addr:street":"Willow Bend Rd",
    "iso:country":"US",
    "sg:address":"306 Willow Bend Rd",
    "sg:city":"Peachtree City",
    "sg:classifiers":[
        {
            "category":"Communications",
            "type":"Services"
        },
        {
            "category":"Real Estate",
            "subcategory":"Real Estate Operator",
            "type":"Services"
        }
    ],
    "sg:phone":"+1 770 631 4112",
    "sg:postcode":"30269",
    "sg:province":"GA",
    "sg:tags":[
        "building",
        "apartment"
    ],
    "wof:name":"Twin Towers Communication LLC",
    "wof:placetype":"venue"
},
  "geometry": {"coordinates":[-84.58526999999999,33.398685],"type":"Point"}
}