{
  "type": "Feature",
  "properties": {
    "iso:country":"US",
    "sg:address":"4720 Powers Ferry Rd NW",
    "sg:city":"Atlanta",
    "sg:classifiers":[
        {
            "category":"Professional",
            "type":"Services"
        }
    ],
    "sg:phone":"+1 770 491 6662",
    "sg:postcode":"30327",
    "sg:province":"GA",
    "wof:name":"Barbara Malone Inc",
    "wof:placetype":"venue"
},
  "geometry": {"coordinates":[-84.397256,33.884074],"type":"Point"}
}