{
  "type": "Feature",
  "properties": {
    "addr:full":"1050 Richard D Sailors Pkwy Powder Springs GA 30127",
    "addr:housenumber":"1050;d",
    "addr:postcode":"30127",
    "addr:street":"Richard;Sailors Pkwy",
    "iso:country":"US",
    "sg:address":"1050 Richard D Sailors Pkwy",
    "sg:city":"Powder Springs",
    "sg:classifiers":[
        {
            "category":"Restaurant",
            "type":"Food & Drink"
        }
    ],
    "sg:phone":"+1 678 567 2626",
    "sg:postcode":"30127",
    "sg:province":"GA",
    "sg:tags":[
        "italian"
    ],
    "sg:website":"www.cangelosipizza.com",
    "wof:name":"Cangelosi's Pizzeria",
    "wof:placetype":"venue"
},
  "geometry": {"coordinates":[-84.679374,33.864145],"type":"Point"}
}