{
  "type": "Feature",
  "properties": {
    "iso:country":"US",
    "sg:address":"541 Buford Dr",
    "sg:city":"Lawrenceville",
    "sg:classifiers":[
        {
            "category":"Retail",
            "subcategory":"Auto Repair",
            "type":"Services"
        }
    ],
    "sg:phone":"+1 770 962 7694",
    "sg:postcode":"30046",
    "sg:province":"GA",
    "wof:name":"Kars Auto Paint & Body Shop",
    "wof:placetype":"venue"
},
  "geometry": {"coordinates":[-83.986266,33.972586],"type":"Point"}
}