{
  "type": "Feature",
  "properties": {
    "iso:country":"US",
    "sg:address":"535 Coliseum Dr",
    "sg:city":"Macon",
    "sg:classifiers":[
        {
            "category":"Building & Trades",
            "subcategory":"Construction",
            "type":"Services"
        }
    ],
    "sg:phone":"+1 478 746 1481",
    "sg:postcode":"31217",
    "sg:province":"GA",
    "sg:tags":[
        "contractor"
    ],
    "sg:website":"www.williamsandassociates.com",
    "wof:name":"Williams & Assoc Inc",
    "wof:placetype":"venue"
},
  "geometry": {"coordinates":[-83.616551,32.847654],"type":"Point"}
}