{
  "type": "Feature",
  "properties": {
    "addr:full":"3623 J Dewey Gray Cir Augusta GA 30909",
    "addr:housenumber":"3623 j",
    "addr:postcode":"30909",
    "addr:street":"Dewey Gray Cir",
    "iso:country":"US",
    "sg:address":"3623 J Dewey Gray Cir",
    "sg:city":"Augusta",
    "sg:classifiers":[
        {
            "category":"Health Services",
            "subcategory":"Doctor",
            "type":"Services"
        }
    ],
    "sg:phone":"+1 706 650 0006",
    "sg:postcode":"30909",
    "sg:province":"GA",
    "sg:tags":[
        "medical"
    ],
    "wof:name":"Corazon Tan",
    "wof:placetype":"venue"
},
  "geometry": {"coordinates":[-82.09619000000001,33.487541],"type":"Point"}
}