{
  "type": "Feature",
  "properties": {
    "addr:full":"3179 Peachtree Rd NE Atlanta GA 30305",
    "addr:housenumber":"3179",
    "addr:postcode":"30305",
    "addr:street":"Peachtree Rd Ne",
    "iso:country":"US",
    "sg:address":"3179 Peachtree Rd NE",
    "sg:city":"Atlanta",
    "sg:classifiers":[
        {
            "category":"Bars & Pubs",
            "type":"Food & Drink"
        },
        {
            "category":"Arts & Performance",
            "subcategory":"Music",
            "type":"Entertainment"
        }
    ],
    "sg:phone":"+1 404 231 4223",
    "sg:postcode":"30305",
    "sg:province":"GA",
    "sg:tags":[
        "venue"
    ],
    "sg:website":"http://atlanta.citysearch.com/profile/2994826/atlanta_ga/moondogs.html?publisher=yellowpages&reference_id=1&placement=ypwebsitemip",
    "wof:name":"Moondogs",
    "wof:placetype":"venue"
},
  "geometry": {"coordinates":[-84.374802,33.8414],"type":"Point"}
}