{
  "type": "Feature",
  "properties": {
    "addr:full":"2375 Stratford Ln Snellville GA 30078",
    "addr:housenumber":"2375",
    "addr:postcode":"30078",
    "addr:street":"Stratford Ln",
    "iso:country":"US",
    "sg:address":"2375 Stratford Ln",
    "sg:city":"Snellville",
    "sg:classifiers":[
        {
            "category":"Real Estate",
            "subcategory":"Real Estate Operator",
            "type":"Services"
        }
    ],
    "sg:phone":"+1 770 985 2104",
    "sg:postcode":"30078",
    "sg:province":"GA",
    "sg:tags":[
        "building",
        "nonresidential"
    ],
    "wof:name":"Maitland Properties LLC",
    "wof:placetype":"venue"
},
  "geometry": {"coordinates":[-83.999444,33.837138],"type":"Point"}
}