{
  "type": "Feature",
  "properties": {
    "addr:full":"105 1st St W Darien GA 31305",
    "addr:housenumber":"105",
    "addr:postcode":"31305",
    "addr:street":"1St St W Darien",
    "iso:country":"US",
    "sg:address":"105 1st St W",
    "sg:city":"Darien",
    "sg:classifiers":[
        {
            "category":"Shopping",
            "subcategory":"Used Merchandise",
            "type":"Retail Goods"
        }
    ],
    "sg:phone":"+1 912 437 6882",
    "sg:postcode":"31305",
    "sg:province":"GA",
    "sg:tags":[
        "antique"
    ],
    "wof:name":"This Old House",
    "wof:placetype":"venue"
},
  "geometry": {"coordinates":[-81.435917,31.369682],"type":"Point"}
}