{
  "type": "Feature",
  "properties": {
    "iso:country":"US",
    "sg:address":"2703 Old Norcross Rd",
    "sg:city":"Tucker",
    "sg:classifiers":[
        {
            "category":"Building & Trades",
            "subcategory":"Construction",
            "type":"Services"
        }
    ],
    "sg:phone":"+1 770 939 8808",
    "sg:postcode":"30084",
    "sg:province":"GA",
    "sg:tags":[
        "plumbing",
        "handyman"
    ],
    "wof:name":"Epies Handyman",
    "wof:placetype":"venue"
},
  "geometry": {"coordinates":[-84.207525,33.865514],"type":"Point"}
}