{
  "type": "Feature",
  "properties": {
    "addr:full":"2010 W Broad Ave Albany GA 31707",
    "addr:housenumber":"2010",
    "addr:postcode":"31707",
    "addr:street":"W Broad Ave",
    "iso:country":"US",
    "sg:address":"2010 W Broad Ave",
    "sg:city":"Albany",
    "sg:classifiers":[
        {
            "category":"Building & Trades",
            "subcategory":"Construction",
            "type":"Services"
        }
    ],
    "sg:phone":"+1 229 888 2150",
    "sg:postcode":"31707",
    "sg:province":"GA",
    "sg:tags":[
        "wallcoverings-installation",
        "wallpaper",
        "painting",
        "contractor"
    ],
    "wof:name":"Don Reddock Painting",
    "wof:placetype":"venue"
},
  "geometry": {"coordinates":[-84.20079,31.57856],"type":"Point"}
}