{
  "type": "Feature",
  "properties": {
    "iso:country":"US",
    "sg:address":"4278 N Puckett Rd",
    "sg:city":"Buford",
    "sg:classifiers":[
        {
            "category":"Building & Trades",
            "subcategory":"Construction",
            "type":"Services"
        }
    ],
    "sg:phone":"+1 770 617 0961",
    "sg:postcode":"30519",
    "sg:province":"GA",
    "sg:tags":[
        "contractor"
    ],
    "wof:name":"Sawyer Tile Repair",
    "wof:placetype":"venue"
},
  "geometry": {"coordinates":[-83.91484199999999,34.114012],"type":"Point"}
}