{
  "type": "Feature",
  "properties": {
    "iso:country":"US",
    "sg:address":"689 State Rte 293",
    "sg:city":"Emerson",
    "sg:classifiers":[
        {
            "category":"Personal",
            "subcategory":"Beauty Salon",
            "type":"Services"
        }
    ],
    "sg:phone":"+1 770 382 0828",
    "sg:postcode":"30137",
    "sg:province":"GA",
    "sg:tags":[
        "shop"
    ],
    "wof:name":"Studio",
    "wof:placetype":"venue"
},
  "geometry": {"coordinates":[-84.757014,34.127815],"type":"Point"}
}