{
  "type": "Feature",
  "properties": {
    "iso:country":"US",
    "sg:address":"311 Warren Rd",
    "sg:city":"Augusta",
    "sg:classifiers":[
        {
            "category":"Education",
            "subcategory":"School",
            "type":"Public Place"
        }
    ],
    "sg:phone":"+1 706 868 4022",
    "sg:postcode":"30907",
    "sg:province":"GA",
    "sg:tags":[
        "elementary"
    ],
    "wof:name":"Warren Road School",
    "wof:placetype":"venue"
},
  "geometry": {"coordinates":[-82.057877,33.507328],"type":"Point"}
}