{
  "type": "Feature",
  "properties": {
    "addr:full":"11 Melanie Rose Ln Lawrenceville GA 30044",
    "addr:housenumber":"11",
    "addr:postcode":"30044",
    "addr:street":"Melanie Rose Ln",
    "iso:country":"US",
    "sg:address":"11 Melanie Rose Ln",
    "sg:city":"Lawrenceville",
    "sg:classifiers":[
        {
            "category":"Building & Trades",
            "subcategory":"Landscaping Services",
            "type":"Services"
        }
    ],
    "sg:phone":"+1 678 377 4744",
    "sg:postcode":"30044",
    "sg:province":"GA",
    "wof:name":"Sen Suprette",
    "wof:placetype":"venue"
},
  "geometry": {"coordinates":[-84.032748,33.929716],"type":"Point"}
}