{
  "type": "Feature",
  "properties": {
    "iso:country":"US",
    "sg:address":"3980 N Henry Blvd",
    "sg:city":"Stockbridge",
    "sg:classifiers":[
        {
            "category":"Organizations",
            "subcategory":"Religious Organization",
            "type":"Services"
        }
    ],
    "sg:phone":"+1 678 565 7500",
    "sg:postcode":"30281",
    "sg:province":"GA",
    "wof:name":"Church Faith and Deliveranc",
    "wof:placetype":"venue"
},
  "geometry": {"coordinates":[-84.214011,33.542103],"type":"Point"}
}