{
  "type": "Feature",
  "properties": {
    "addr:full":"25 Nelson St Cartersville GA 30120",
    "addr:housenumber":"25",
    "addr:postcode":"30120",
    "addr:street":"Nelson St",
    "iso:country":"US",
    "sg:address":"25 Nelson St",
    "sg:city":"Cartersville",
    "sg:classifiers":[
        {
            "category":"Insurance",
            "subcategory":"Insurance Agent",
            "type":"Services"
        }
    ],
    "sg:phone":"+1 770 382 2951",
    "sg:postcode":"30120",
    "sg:province":"GA",
    "wof:name":"Bartow County Farm Bureau Ins",
    "wof:placetype":"venue"
},
  "geometry": {"coordinates":[-84.792985,34.172271],"type":"Point"}
}