{
  "type": "Feature",
  "properties": {
    "iso:country":"US",
    "sg:address":"322 Pharr Rd NE",
    "sg:city":"Atlanta",
    "sg:phone":"+1 404 240 0260",
    "sg:postcode":"30305",
    "sg:province":"GA",
    "wof:name":"New Yorker MarketPlace & Delicatessan",
    "wof:placetype":"venue"
},
  "geometry": {"coordinates":[-84.376994,33.837045],"type":"Point"}
}