{
  "type": "Feature",
  "properties": {
    "addr:full":"11560 Northgate Trl Roswell GA 30075",
    "addr:housenumber":"11560",
    "addr:postcode":"30075",
    "addr:street":"Northgate Trl",
    "iso:country":"US",
    "sg:address":"11560 Northgate Trl",
    "sg:city":"Roswell",
    "sg:classifiers":[
        {
            "category":"Professional",
            "subcategory":"Business Services",
            "type":"Services"
        }
    ],
    "sg:phone":"+1 770 493 6222",
    "sg:postcode":"30075",
    "sg:province":"GA",
    "wof:name":"Harrison Elle Designs",
    "wof:placetype":"venue"
},
  "geometry": {"coordinates":[-84.366789,34.063101],"type":"Point"}
}