{
  "type": "Feature",
  "properties": {
    "iso:country":"US",
    "sg:address":"107 Ladd Cir",
    "sg:city":"Statesboro",
    "sg:classifiers":[
        {
            "category":"Professional",
            "subcategory":"Computer Services",
            "type":"Services"
        }
    ],
    "sg:phone":"+1 912 489 9333",
    "sg:postcode":"30458",
    "sg:province":"GA",
    "sg:tags":[
        "web",
        "design",
        "hosting",
        "site"
    ],
    "wof:name":"Internet Eye Magazine",
    "wof:placetype":"venue"
},
  "geometry": {"coordinates":[-81.7777,32.473609],"type":"Point"}
}