{
  "type": "Feature",
  "properties": {
    "addr:full":"1131 N Indian Creek Dr Clarkston GA 30021",
    "addr:housenumber":"1131",
    "addr:postcode":"30021",
    "addr:street":"N Indian Creek Dr",
    "iso:country":"US",
    "sg:address":"1131 N Indian Creek Dr",
    "sg:city":"Clarkston",
    "sg:classifiers":[
        {
            "category":"Retail",
            "subcategory":"Auto Repair",
            "type":"Services"
        }
    ],
    "sg:phone":"+1 404 299 5678",
    "sg:postcode":"30021",
    "sg:province":"GA",
    "sg:tags":[
        "repairing",
        "automobile"
    ],
    "wof:name":"NASAR Auto Electric Engine",
    "wof:placetype":"venue"
},
  "geometry": {"coordinates":[-84.242108,33.80889],"type":"Point"}
}