{
  "type": "Feature",
  "properties": {
    "addr:full":"4058 Whitlock St Brunswick GA 31520",
    "addr:housenumber":"4058",
    "addr:postcode":"31520",
    "addr:street":"Whitlock St",
    "iso:country":"US",
    "sg:address":"4058 Whitlock St",
    "sg:city":"Brunswick",
    "sg:classifiers":[
        {
            "category":"Building & Trades",
            "subcategory":"Electrical",
            "type":"Services"
        }
    ],
    "sg:phone":"+1 912 265 6690",
    "sg:postcode":"31520",
    "sg:province":"GA",
    "sg:tags":[
        "electrician"
    ],
    "sg:website":"http://www.mcinniselectriccompany-bwk.com",
    "wof:name":"McInnis Electric Company",
    "wof:placetype":"venue"
},
  "geometry": {"coordinates":[-81.50587299999999,31.201443],"type":"Point"}
}