{
  "type": "Feature",
  "properties": {
    "iso:country":"US",
    "sg:address":"123 N Main St",
    "sg:city":"Jonesboro",
    "sg:classifiers":[
        {
            "category":"Health Services",
            "subcategory":"Hospital",
            "type":"Services"
        }
    ],
    "sg:phone":"+1 770 478 6581",
    "sg:postcode":"30236",
    "sg:province":"GA",
    "sg:tags":[
        "mental"
    ],
    "wof:name":"Clayton Mental Health",
    "wof:placetype":"venue"
},
  "geometry": {"coordinates":[-84.354533,33.520928],"type":"Point"}
}