{
  "type": "Feature",
  "properties": {
    "addr:full":"East Lake Shopping Centre 2145 Roswell Rd Marietta GA 30062",
    "addr:housenumber":"2145",
    "addr:postcode":"30062",
    "addr:street":"Roswell Rd",
    "iso:country":"US",
    "sg:address":"East Lake Shopping Centre 2145 Roswell Rd",
    "sg:city":"Marietta",
    "sg:classifiers":[
        {
            "category":"Shopping",
            "subcategory":"Hobbies, Toys, & Games",
            "type":"Retail Goods"
        },
        {
            "category":"Coffee & Tea",
            "type":"Food & Drink"
        },
        {
            "category":"Food & Beverages",
            "subcategory":"Bakery",
            "type":"Retail Goods"
        }
    ],
    "sg:phone":"+1 770 578 1497",
    "sg:postcode":"30062",
    "sg:province":"GA",
    "sg:tags":[
        "shop",
        "hobby",
        "sandwich"
    ],
    "sg:website":"www.giga-bitescafe.com",
    "wof:name":"Giga-Bites Cafe",
    "wof:placetype":"venue"
},
  "geometry": {"coordinates":[-84.491725,33.965917],"type":"Point"}
}