{
  "type": "Feature",
  "properties": {
    "addr:full":"231 E Spring St Mount Vernon GA 30445",
    "addr:housenumber":"231",
    "addr:postcode":"30445",
    "addr:street":"E Spring St",
    "iso:country":"US",
    "sg:address":"231 E Spring St",
    "sg:city":"Mount Vernon",
    "sg:classifiers":[
        {
            "category":"Restaurant",
            "type":"Food & Drink"
        }
    ],
    "sg:phone":"+1 912 583 2828",
    "sg:postcode":"30445",
    "sg:province":"GA",
    "sg:tags":[
        "eating"
    ],
    "wof:name":"Hong Kong Chinese Restaurant",
    "wof:placetype":"venue"
},
  "geometry": {"coordinates":[-82.592883,32.178334],"type":"Point"}
}