{
  "type": "Feature",
  "properties": {
    "iso:country":"US",
    "sg:address":"3007 E Walnut Ave",
    "sg:city":"Dalton",
    "sg:classifiers":[
        {
            "category":"Shopping",
            "type":"Retail Goods"
        }
    ],
    "sg:phone":"+1 706 278 1655",
    "sg:postcode":"30721",
    "sg:province":"GA",
    "sg:tags":[
        "merchandise"
    ],
    "wof:name":"Candles N Scents",
    "wof:placetype":"venue"
},
  "geometry": {"coordinates":[-84.91688600000001,34.777215],"type":"Point"}
}