{
  "type": "Feature",
  "properties": {
    "addr:full":"257 Matthews School Rd Winder GA 30680",
    "addr:housenumber":"257",
    "addr:postcode":"30680",
    "addr:street":"Matthews School Rd",
    "iso:country":"US",
    "sg:address":"257 Matthews School Rd",
    "sg:city":"Winder",
    "sg:classifiers":[
        {
            "category":"Professional",
            "subcategory":"Computer Services",
            "type":"Services"
        }
    ],
    "sg:phone":"+1 770 586 0127",
    "sg:postcode":"30680",
    "sg:province":"GA",
    "sg:tags":[
        "prepackaged",
        "software"
    ],
    "wof:name":"Integrity Software Design",
    "wof:placetype":"venue"
},
  "geometry": {"coordinates":[-83.75654299999999,33.976189],"type":"Point"}
}