{
  "type": "Feature",
  "properties": {
    "iso:country":"US",
    "sg:address":"120 Kates Brg",
    "sg:city":"Newnan",
    "sg:classifiers":[
        {
            "category":"Professional",
            "subcategory":"Business Services",
            "type":"Services"
        }
    ],
    "sg:phone":"+1 770 252 8270",
    "sg:postcode":"30263",
    "sg:province":"GA",
    "wof:name":"Omni Tech Solutions",
    "wof:placetype":"venue"
},
  "geometry": {"coordinates":[-84.782814,33.4444],"type":"Point"}
}