{
  "type": "Feature",
  "properties": {
    "iso:country":"US",
    "sg:address":"4005 Buford Hwy NE Ste A",
    "sg:city":"Atlanta",
    "sg:classifiers":[
        {
            "category":"Retail",
            "subcategory":"Laundry & Dry Cleaning",
            "type":"Services"
        }
    ],
    "sg:phone":"+1 404 321 9908",
    "sg:postcode":"30345",
    "sg:province":"GA",
    "sg:tags":[
        "operated",
        "dryer",
        "laundries-self",
        "washer",
        "coin"
    ],
    "wof:name":"Song Laundry Matt",
    "wof:placetype":"venue"
},
  "geometry": {"coordinates":[-84.309999,33.859745],"type":"Point"}
}