{
  "type": "Feature",
  "properties": {
    "iso:country":"US",
    "sg:address":"100 Firethorne Dr",
    "sg:city":"Newnan",
    "sg:classifiers":[
        {
            "category":"Building & Trades",
            "subcategory":"Construction",
            "type":"Services"
        }
    ],
    "sg:phone":"+1 770 252 3800",
    "sg:postcode":"30265",
    "sg:province":"GA",
    "wof:name":"Southern Network Services Inc",
    "wof:placetype":"venue"
},
  "geometry": {"coordinates":[-84.678259,33.411463],"type":"Point"}
}