{
  "type": "Feature",
  "properties": {
    "iso:country":"US",
    "sg:address":"446 Pleasant Home Rd",
    "sg:city":"Augusta",
    "sg:classifiers":[
        {
            "category":"Real Estate",
            "subcategory":"Real Estate Agent",
            "type":"Services"
        }
    ],
    "sg:phone":"+1 706 394 2196",
    "sg:postcode":"30907",
    "sg:province":"GA",
    "sg:tags":[
        "inspection"
    ],
    "wof:name":"American Home Inspection",
    "wof:placetype":"venue"
},
  "geometry": {"coordinates":[-82.07464299999999,33.504406],"type":"Point"}
}