{
  "type": "Feature",
  "properties": {
    "addr:full":"2361 N Elm St Commerce GA 30529",
    "addr:housenumber":"2361",
    "addr:postcode":"30529",
    "addr:street":"N Elm St",
    "iso:country":"US",
    "sg:address":"2361 N Elm St",
    "sg:city":"Commerce",
    "sg:classifiers":[
        {
            "category":"Professional",
            "subcategory":"Business Services",
            "type":"Services"
        }
    ],
    "sg:phone":"+1 706 335 3051",
    "sg:postcode":"30529",
    "sg:province":"GA",
    "sg:tags":[
        "auctioneer"
    ],
    "wof:name":"Carriage House Auction Co",
    "wof:placetype":"venue"
},
  "geometry": {"coordinates":[-83.467358,34.206833],"type":"Point"}
}