{
  "type": "Feature",
  "properties": {
    "iso:country":"US",
    "sg:address":"55 Horseshoe Dr",
    "sg:city":"Covington",
    "sg:classifiers":[
        {
            "category":"Recreation",
            "type":"Entertainment"
        }
    ],
    "sg:phone":"+1 770 385 0402",
    "sg:postcode":"30014",
    "sg:province":"GA",
    "sg:tags":[
        "stable"
    ],
    "wof:name":"Fourwood Farm",
    "wof:placetype":"venue"
},
  "geometry": {"coordinates":[-83.932199,33.634268],"type":"Point"}
}