{
  "type": "Feature",
  "properties": {
    "addr:full":"2497 Cedar Wood Ct Marietta GA 30068",
    "addr:housenumber":"2497",
    "addr:postcode":"30068",
    "addr:street":"Cedar Wood Ct",
    "iso:country":"US",
    "sg:address":"2497 Cedar Wood Ct",
    "sg:city":"Marietta",
    "sg:classifiers":[
        {
            "category":"Wholesale",
            "subcategory":"Machinery & Supplies",
            "type":"Manufacturing & Wholesale Goods"
        }
    ],
    "sg:phone":"+1 770 579 1929",
    "sg:postcode":"30068",
    "sg:province":"GA",
    "sg:tags":[
        "equipment",
        "establishment"
    ],
    "wof:name":"Wharton & Assoc Inc",
    "wof:placetype":"venue"
},
  "geometry": {"coordinates":[-84.478132,33.94914],"type":"Point"}
}