{
  "type": "Feature",
  "properties": {
    "iso:country":"US",
    "sg:address":"1152 Cumberland Mall SE",
    "sg:city":"Atlanta",
    "sg:classifiers":[
        {
            "category":"Coffee & Tea",
            "type":"Food & Drink"
        }
    ],
    "sg:menulink":"http://www.allmenus.com/ga/vinings/108011-starbucks-coffee/menu/",
    "sg:phone":"+1 770 433 0354",
    "sg:postcode":"30339",
    "sg:province":"GA",
    "sg:tags":[
        "american"
    ],
    "wof:name":"Starbucks Coffee",
    "wof:placetype":"venue"
},
  "geometry": {"coordinates":[-84.47190399999999,33.881193],"type":"Point"}
}