{
  "type": "Feature",
  "properties": {
    "addr:full":"882 Buford Hwy Cumming GA 30041",
    "addr:housenumber":"882",
    "addr:postcode":"30041",
    "addr:street":"Buford Hwy",
    "iso:country":"US",
    "sg:address":"882 Buford Hwy",
    "sg:city":"Cumming",
    "sg:classifiers":[
        {
            "category":"Shopping",
            "subcategory":"Photographic Equipment",
            "type":"Retail Goods"
        }
    ],
    "sg:phone":"+1 678 947 8995",
    "sg:postcode":"30041",
    "sg:province":"GA",
    "sg:tags":[
        "supply"
    ],
    "wof:name":"Wolf Camera & Video",
    "wof:placetype":"venue"
},
  "geometry": {"coordinates":[-84.13306900000001,34.179371],"type":"Point"}
}