{
  "type": "Feature",
  "properties": {
    "addr:full":"1924 Leguin Mill Rd Locust Grove GA 30248",
    "addr:housenumber":"1924",
    "addr:postcode":"30248",
    "addr:street":"Leguin Mill Rd",
    "iso:country":"US",
    "sg:address":"1924 Leguin Mill Rd",
    "sg:city":"Locust Grove",
    "sg:classifiers":[
        {
            "category":"Utilities",
            "subcategory":"Refuse",
            "type":"Services"
        }
    ],
    "sg:phone":"+1 770 898 4933",
    "sg:postcode":"30248",
    "sg:province":"GA",
    "sg:tags":[
        "system"
    ],
    "wof:name":"Giant Recovery Resources",
    "wof:placetype":"venue"
},
  "geometry": {"coordinates":[-84.055097,33.384687],"type":"Point"}
}