{
  "type": "Feature",
  "properties": {
    "addr:full":"201 Fisk Dr SW Atlanta GA 30336",
    "addr:housenumber":"201",
    "addr:postcode":"30336",
    "addr:street":"Fisk Dr Sw",
    "iso:country":"US",
    "sg:address":"201 Fisk Dr SW",
    "sg:city":"Atlanta",
    "sg:classifiers":[
        {
            "category":"Freight",
            "type":"Transportation"
        }
    ],
    "sg:phone":"+1 404 344 1121",
    "sg:postcode":"30336",
    "sg:province":"GA",
    "sg:tags":[
        "warehouse",
        "merchandise"
    ],
    "wof:name":"Best Distribution & Warehouse",
    "wof:placetype":"venue"
},
  "geometry": {"coordinates":[-84.586895,33.724751],"type":"Point"}
}