{
  "type": "Feature",
  "properties": {
    "addr:full":"337 Eagle Pointe Dr Dallas GA 30132",
    "addr:housenumber":"337",
    "addr:postcode":"30132",
    "addr:street":"Eagle Pointe Dr",
    "iso:country":"US",
    "sg:address":"337 Eagle Pointe Dr",
    "sg:city":"Dallas",
    "sg:classifiers":[
        {
            "category":"Professional",
            "subcategory":"Management & Consulting",
            "type":"Services"
        },
        {
            "category":"Wholesale",
            "subcategory":"Electrical",
            "type":"Manufacturing & Wholesale Goods"
        }
    ],
    "sg:phone":"+1 770 505 2444",
    "sg:postcode":"30132",
    "sg:province":"GA",
    "sg:tags":[
        "alarm",
        "burglar",
        "system",
        "business"
    ],
    "wof:name":"Das Security Systems Inc",
    "wof:placetype":"venue"
},
  "geometry": {"coordinates":[-84.80837099999999,33.972846],"type":"Point"}
}