{
  "type": "Feature",
  "properties": {
    "addr:full":"8860 Tara Blvd Jonesboro GA 30236",
    "addr:housenumber":"8860",
    "addr:postcode":"30236",
    "addr:street":"Tara Blvd",
    "iso:country":"US",
    "sg:address":"8860 Tara Blvd",
    "sg:city":"Jonesboro",
    "sg:classifiers":[
        {
            "category":"Home & Garden",
            "subcategory":"Mobile Homes",
            "type":"Retail Goods"
        }
    ],
    "sg:phone":"+1 770 210 1090",
    "sg:postcode":"30236",
    "sg:province":"GA",
    "wof:name":"Masterpiece Homes",
    "wof:placetype":"venue"
},
  "geometry": {"coordinates":[-84.362989,33.51654],"type":"Point"}
}