{
  "type": "Feature",
  "properties": {
    "addr:full":"7166 Gumlog Rd Young Harris GA 30582",
    "addr:housenumber":"7166",
    "addr:postcode":"30582",
    "addr:street":"Gumlog Rd;Harris",
    "iso:country":"US",
    "sg:address":"7166 Gumlog Rd",
    "sg:city":"Young Harris",
    "sg:classifiers":[
        {
            "category":"Retail",
            "subcategory":"Auto Repair",
            "type":"Services"
        }
    ],
    "sg:phone":"+1 706 379 2703",
    "sg:postcode":"30582",
    "sg:province":"GA",
    "sg:tags":[
        "general"
    ],
    "wof:name":"T & S Auto Repair",
    "wof:placetype":"venue"
},
  "geometry": {"coordinates":[-83.882389,34.973252],"type":"Point"}
}