{
  "type": "Feature",
  "properties": {
    "addr:full":"3915 Emerald North Dr Decatur GA 30035",
    "addr:housenumber":"3915",
    "addr:postcode":"30035",
    "addr:street":"Emerald North Dr",
    "iso:country":"US",
    "sg:address":"3915 Emerald North Dr",
    "sg:city":"Decatur",
    "sg:classifiers":[
        {
            "category":"Building & Trades",
            "subcategory":"Construction",
            "type":"Services"
        }
    ],
    "sg:phone":"+1 404 966 1376",
    "sg:postcode":"30035",
    "sg:province":"GA",
    "sg:tags":[
        "house"
    ],
    "wof:name":"Big Boy Home Improvement",
    "wof:placetype":"venue"
},
  "geometry": {"coordinates":[-84.23183299999999,33.723915],"type":"Point"}
}