{
  "type": "Feature",
  "properties": {
    "addr:full":"4002 Woods Point Rd Rocky Face GA 30740",
    "addr:housenumber":"4002",
    "addr:postcode":"30740",
    "addr:street":"Woods Point Rd",
    "iso:country":"US",
    "sg:address":"4002 Woods Point Rd",
    "sg:city":"Rocky Face",
    "sg:classifiers":[
        {
            "category":"Travel",
            "subcategory":"Hotels & Motels",
            "type":"Entertainment"
        }
    ],
    "sg:phone":"+1 706 673 2126",
    "sg:postcode":"30740",
    "sg:province":"GA",
    "sg:tags":[
        "operation"
    ],
    "wof:name":"Farm Guest House",
    "wof:placetype":"venue"
},
  "geometry": {"coordinates":[-85.01739999999999,34.771563],"type":"Point"}
}