{
  "type": "Feature",
  "properties": {
    "iso:country":"US",
    "sg:address":"241 Pine St NE",
    "sg:city":"Atlanta",
    "sg:classifiers":[
        {
            "category":"Organizations",
            "subcategory":"Non-profit Organization",
            "type":"Services"
        }
    ],
    "sg:phone":"+1 404 872 3549",
    "sg:postcode":"30308",
    "sg:province":"GA",
    "sg:tags":[
        "profit",
        "on",
        "educational",
        "energy",
        "solar"
    ],
    "sg:website":"www.southface.org",
    "wof:name":"Southface Energy Institute",
    "wof:placetype":"venue"
},
  "geometry": {"coordinates":[-84.387457,33.76734],"type":"Point"}
}