{
  "type": "Feature",
  "properties": {
    "iso:country":"US",
    "sg:address":"4371 Shallowford Industrial Pkwy",
    "sg:city":"Marietta",
    "sg:classifiers":[
        {
            "category":"Wholesale",
            "subcategory":"Medical Equipment & Supplies",
            "type":"Manufacturing & Wholesale Goods"
        }
    ],
    "sg:phone":"+1 770 926 7336",
    "sg:postcode":"30066",
    "sg:province":"GA",
    "sg:tags":[
        "therapy",
        "physical"
    ],
    "wof:name":"Electro-Medical Equipment",
    "wof:placetype":"venue"
},
  "geometry": {"coordinates":[-84.515508,34.057628],"type":"Point"}
}