{
  "type": "Feature",
  "properties": {
    "addr:full":"3881 Bemiss Rd Valdosta GA 31605",
    "addr:housenumber":"3881",
    "addr:postcode":"31605",
    "addr:street":"Bemiss Rd",
    "iso:country":"US",
    "sg:address":"3881 Bemiss Rd",
    "sg:city":"Valdosta",
    "sg:classifiers":[
        {
            "category":"Building & Trades",
            "subcategory":"Pest Control",
            "type":"Services"
        }
    ],
    "sg:phone":"+1 229 245 8282",
    "sg:postcode":"31605",
    "sg:province":"GA",
    "wof:name":"Fairway Pest Control Co Inc",
    "wof:placetype":"venue"
},
  "geometry": {"coordinates":[-83.265135,30.905035],"type":"Point"}
}