{
  "type": "Feature",
  "properties": {
    "iso:country":"US",
    "sg:address":"4007 Moultrie Rd",
    "sg:city":"Albany",
    "sg:classifiers":[
        {
            "category":"Organizations",
            "subcategory":"Religious Organization",
            "type":"Services"
        }
    ],
    "sg:phone":"+1 229 888 0740",
    "sg:postcode":"31705",
    "sg:province":"GA",
    "wof:name":"Cornerstone Baptist Church",
    "wof:placetype":"venue"
},
  "geometry": {"coordinates":[-83.998706,31.462324],"type":"Point"}
}