{
  "type": "Feature",
  "properties": {
    "addr:full":"19 John Wesley Dr Dallas GA 30132",
    "addr:housenumber":"19",
    "addr:postcode":"30132",
    "addr:street":"John Wesley Dr",
    "iso:country":"US",
    "sg:address":"19 John Wesley Dr",
    "sg:city":"Dallas",
    "sg:classifiers":[
        {
            "category":"Manufacturing",
            "subcategory":"Furniture",
            "type":"Manufacturing & Wholesale Goods"
        }
    ],
    "sg:phone":"+1 678 363 7499",
    "sg:postcode":"30132",
    "sg:province":"GA",
    "sg:tags":[
        "household",
        "wood",
        "mfg"
    ],
    "wof:name":"Colonial Cabinet Shop",
    "wof:placetype":"venue"
},
  "geometry": {"coordinates":[-84.828092,34.042501],"type":"Point"}
}