{
  "type": "Feature",
  "properties": {
    "addr:full":"570 Rockbridge Rd SW Lilburn GA 30047",
    "addr:housenumber":"570",
    "addr:postcode":"30047",
    "addr:street":"Rockbridge Rd Sw",
    "iso:country":"US",
    "sg:address":"570 Rockbridge Rd SW",
    "sg:city":"Lilburn",
    "sg:classifiers":[
        {
            "category":"Communications",
            "subcategory":"Film & Video Production",
            "type":"Services"
        }
    ],
    "sg:phone":"+1 770 638 8795",
    "sg:postcode":"30047",
    "sg:province":"GA",
    "sg:tags":[
        "motion"
    ],
    "wof:name":"Scarey Productions Inc",
    "wof:placetype":"venue"
},
  "geometry": {"coordinates":[-84.141662,33.858181],"type":"Point"}
}