{
  "type": "Feature",
  "properties": {
    "addr:full":"185 Kevin Way Hull GA 30646",
    "addr:housenumber":"185",
    "addr:postcode":"30646",
    "addr:street":"Kevin Way",
    "iso:country":"US",
    "sg:address":"185 Kevin Way",
    "sg:city":"Hull",
    "sg:classifiers":[
        {
            "category":"Building & Trades",
            "subcategory":"Construction",
            "type":"Services"
        }
    ],
    "sg:phone":"+1 706 357 4999",
    "sg:postcode":"30646",
    "sg:province":"GA",
    "sg:tags":[
        "home",
        "contractor",
        "roofing",
        "improvement"
    ],
    "wof:name":"Home Fix Inc",
    "wof:placetype":"venue"
},
  "geometry": {"coordinates":[-83.31080900000001,34.026852],"type":"Point"}
}