{
  "type": "Feature",
  "properties": {
    "addr:full":"2420 Atlanta Rd SE Smyrna GA 30080",
    "addr:housenumber":"2420",
    "addr:postcode":"30080",
    "addr:street":"Atlanta Rd Se",
    "iso:country":"US",
    "sg:address":"2420 Atlanta Rd SE",
    "sg:city":"Smyrna",
    "sg:classifiers":[
        {
            "category":"Shopping",
            "subcategory":"Discount & Variety Stores",
            "type":"Retail Goods"
        }
    ],
    "sg:phone":"+1 404 329 1908",
    "sg:postcode":"30080",
    "sg:province":"GA",
    "wof:name":"Wonder Dollar",
    "wof:placetype":"venue"
},
  "geometry": {"coordinates":[-84.518157,33.891202],"type":"Point"}
}