{
  "type": "Feature",
  "properties": {
    "iso:country":"US",
    "sg:address":"101 Pilgrim Village Dr",
    "sg:city":"Cumming",
    "sg:classifiers":[
        {
            "category":"Building & Trades",
            "subcategory":"Plumbing",
            "type":"Services"
        }
    ],
    "sg:phone":"+1 678 947 3473",
    "sg:postcode":"30040",
    "sg:province":"GA",
    "sg:tags":[
        "plumber",
        "industrial",
        "contractors-commercial"
    ],
    "wof:name":"Plumbing & Mechanical Association Of Georgia",
    "wof:placetype":"venue"
},
  "geometry": {"coordinates":[-84.135223,34.209536],"type":"Point"}
}