{
  "type": "Feature",
  "properties": {
    "iso:country":"US",
    "sg:address":"114 Gordon St",
    "sg:city":"Blackshear",
    "sg:classifiers":[
        {
            "category":"Restaurant",
            "type":"Food & Drink"
        }
    ],
    "sg:menulink":"http://www.allmenus.com/ga/blackshear/203183-mcdonalds/menu/",
    "sg:postcode":"31516",
    "sg:province":"GA",
    "sg:tags":[
        "burger",
        "american"
    ],
    "wof:name":"McDonald's",
    "wof:placetype":"venue"
},
  "geometry": {"coordinates":[-82.24213899999999,31.306256],"type":"Point"}
}