{
  "type": "Feature",
  "properties": {
    "iso:country":"US",
    "sg:address":"495 Wickerberry Ln",
    "sg:city":"Roswell",
    "sg:classifiers":[
        {
            "category":"Professional",
            "subcategory":"Employment Agencies",
            "type":"Services"
        }
    ],
    "sg:phone":"+1 770 552 9898",
    "sg:postcode":"30075",
    "sg:province":"GA",
    "sg:tags":[
        "employee",
        "benefit",
        "consulting"
    ],
    "wof:name":"New Benefit Directions",
    "wof:placetype":"venue"
},
  "geometry": {"coordinates":[-84.377358,34.0224],"type":"Point"}
}