{
  "type": "Feature",
  "properties": {
    "addr:full":"1110 Red Bud Rd NE Calhoun GA 30701",
    "addr:housenumber":"1110",
    "addr:postcode":"30701",
    "addr:street":"Red Bud Rd Ne",
    "iso:country":"US",
    "sg:address":"1110 Red Bud Rd NE",
    "sg:city":"Calhoun",
    "sg:classifiers":[
        {
            "category":"Shopping",
            "type":"Retail Goods"
        }
    ],
    "sg:phone":"+1 706 383 6173",
    "sg:postcode":"30701",
    "sg:province":"GA",
    "sg:tags":[
        "collectible"
    ],
    "wof:name":"Georgia Collectorcom",
    "wof:placetype":"venue"
},
  "geometry": {"coordinates":[-84.92191800000001,34.511832],"type":"Point"}
}