{
  "type": "Feature",
  "properties": {
    "iso:country":"US",
    "sg:address":"222A Johnson Ferry Road NE",
    "sg:city":"Atlanta",
    "sg:classifiers":[
        {
            "category":"Personal",
            "type":"Services"
        }
    ],
    "sg:phone":"+1 404 252 4363",
    "sg:postcode":"30328",
    "sg:province":"GA",
    "sg:tags":[
        "sewing",
        "alteration"
    ],
    "wof:name":"Shanghai Alterations",
    "wof:placetype":"venue"
},
  "geometry": {"coordinates":[-84.380404,33.925293],"type":"Point"}
}