{
  "type": "Feature",
  "properties": {
    "iso:country":"US",
    "sg:address":"4701 Jefferson Davis Hwy",
    "sg:city":"Beech Island",
    "sg:classifiers":[
        {
            "category":"Banks & Credit Unions",
            "subcategory":"Bank",
            "type":"Services"
        }
    ],
    "sg:phone":"+1 803 594 9444",
    "sg:postcode":"29842",
    "sg:province":"SC",
    "sg:tags":[
        "cashing",
        "check"
    ],
    "wof:name":"Quick Cash",
    "wof:placetype":"venue"
},
  "geometry": {"coordinates":[-81.910775,33.497881],"type":"Point"}
}