{
  "type": "Feature",
  "properties": {
    "addr:full":"2575 Pinetree Rd Cumming GA 30041",
    "addr:housenumber":"2575",
    "addr:postcode":"30041",
    "addr:street":"Pinetree Rd",
    "iso:country":"US",
    "sg:address":"2575 Pinetree Rd",
    "sg:city":"Cumming",
    "sg:classifiers":[
        {
            "category":"Building & Trades",
            "subcategory":"Construction",
            "type":"Services"
        }
    ],
    "sg:phone":"+1 770 205 7433",
    "sg:postcode":"30041",
    "sg:province":"GA",
    "sg:tags":[
        "contractor"
    ],
    "wof:name":"Georgia Gutter Inc",
    "wof:placetype":"venue"
},
  "geometry": {"coordinates":[-84.09191199999999,34.182216],"type":"Point"}
}