{
  "type": "Feature",
  "properties": {
    "addr:full":"1467 High Shoals Rd Dallas GA 30132",
    "addr:housenumber":"1467",
    "addr:postcode":"30132",
    "addr:street":"High Shoals Rd",
    "iso:country":"US",
    "sg:address":"1467 High Shoals Rd",
    "sg:city":"Dallas",
    "sg:classifiers":[
        {
            "category":"Personal",
            "type":"Services"
        }
    ],
    "sg:phone":"+1 770 443 3822",
    "sg:postcode":"30132",
    "sg:province":"GA",
    "wof:name":"American Moonwalks",
    "wof:placetype":"venue"
},
  "geometry": {"coordinates":[-84.87812700000001,33.978889],"type":"Point"}
}