{
  "type": "Feature",
  "properties": {
    "iso:country":"US",
    "sg:address":"4012 Lawrenceville Hwy",
    "sg:city":"Tucker",
    "sg:classifiers":[
        {
            "category":"Food & Beverages",
            "subcategory":"Liquor & Beverages",
            "type":"Retail Goods"
        }
    ],
    "sg:phone":"+1 770 939 8597",
    "sg:postcode":"30084",
    "sg:province":"GA",
    "sg:tags":[
        "beer",
        "spirit",
        "wine"
    ],
    "wof:name":"Shan Hung Yu",
    "wof:placetype":"venue"
},
  "geometry": {"coordinates":[-84.21740800000001,33.850147],"type":"Point"}
}