{
  "type": "Feature",
  "properties": {
    "iso:country":"US",
    "sg:address":"1410 Shorter Ave",
    "sg:city":"Rome",
    "sg:classifiers":[
        {
            "category":"Organizations",
            "subcategory":"Religious Organization",
            "type":"Services"
        }
    ],
    "sg:phone":"+1 706 234 8266",
    "sg:postcode":"30165",
    "sg:province":"GA",
    "wof:name":"Shorter Avenue Baptist Church",
    "wof:placetype":"venue"
},
  "geometry": {"coordinates":[-85.211883,34.2684],"type":"Point"}
}