{
  "type": "Feature",
  "properties": {
    "addr:full":"1860 Sandy Plains Rd Marietta GA 30066",
    "addr:housenumber":"1860",
    "addr:postcode":"30066",
    "addr:street":"Sandy Plains Rd",
    "iso:country":"US",
    "sg:address":"1860 Sandy Plains Rd",
    "sg:city":"Marietta",
    "sg:classifiers":[
        {
            "category":"Professional",
            "subcategory":"Business Services",
            "type":"Services"
        }
    ],
    "sg:phone":"+1 770 238 1100",
    "sg:postcode":"30066",
    "sg:province":"GA",
    "wof:name":"Contours Express",
    "wof:placetype":"venue"
},
  "geometry": {"coordinates":[-84.506001,33.997167],"type":"Point"}
}