{
  "type": "Feature",
  "properties": {
    "addr:full":"285 Morrow Rd Forest Park GA 30297",
    "addr:housenumber":"285",
    "addr:postcode":"30297",
    "addr:street":"Morrow Rd",
    "iso:country":"US",
    "sg:address":"285 Morrow Rd",
    "sg:city":"Forest Park",
    "sg:classifiers":[
        {
            "category":"Organizations",
            "subcategory":"Religious Organization",
            "type":"Services"
        }
    ],
    "sg:phone":"+1 404 363 2571",
    "sg:postcode":"30297",
    "sg:province":"GA",
    "wof:name":"Central Spanish Seventh Day",
    "wof:placetype":"venue"
},
  "geometry": {"coordinates":[-84.381733,33.591945],"type":"Point"}
}