{
  "type": "Feature",
  "properties": {
    "addr:full":"337 S Milledge Ave Athens GA 30605",
    "addr:housenumber":"337",
    "addr:postcode":"30605",
    "addr:street":"S Milledge Ave",
    "iso:country":"US",
    "sg:address":"337 S Milledge Ave",
    "sg:city":"Athens",
    "sg:classifiers":[
        {
            "category":"Social Services",
            "type":"Services"
        }
    ],
    "sg:phone":"+1 706 546 7267",
    "sg:postcode":"30605",
    "sg:province":"GA",
    "sg:tags":[
        "agency",
        "adoption"
    ],
    "wof:name":"Covenant Care Svc",
    "wof:placetype":"venue"
},
  "geometry": {"coordinates":[-83.387389,33.952492],"type":"Point"}
}