{
  "type": "Feature",
  "properties": {
    "addr:full":"1650 Rising Mist Ln Cumming GA 30041",
    "addr:housenumber":"1650",
    "addr:postcode":"30041",
    "addr:street":"Rising Mist Ln",
    "iso:country":"US",
    "sg:address":"1650 Rising Mist Ln",
    "sg:city":"Cumming",
    "sg:classifiers":[
        {
            "category":"Professional",
            "subcategory":"Business Services",
            "type":"Services"
        }
    ],
    "sg:phone":"+1 770 844 0700",
    "sg:postcode":"30041",
    "sg:province":"GA",
    "wof:name":"Collaborative Design",
    "wof:placetype":"venue"
},
  "geometry": {"coordinates":[-84.115058,34.199029],"type":"Point"}
}