{
  "type": "Feature",
  "properties": {
    "addr:full":"111 Mountain Brook Dr Canton GA 30115",
    "addr:housenumber":"111",
    "addr:postcode":"30115",
    "addr:street":"Mountain Brook Dr",
    "iso:country":"US",
    "sg:address":"111 Mountain Brook Dr",
    "sg:city":"Canton",
    "sg:classifiers":[
        {
            "category":"Real Estate",
            "subcategory":"Real Estate Agent",
            "type":"Services"
        }
    ],
    "sg:phone":"+1 770 479 0312",
    "sg:postcode":"30115",
    "sg:province":"GA",
    "wof:name":"Sandra Saxon Realty",
    "wof:placetype":"venue"
},
  "geometry": {"coordinates":[-84.505492,34.178722],"type":"Point"}
}