{
  "type": "Feature",
  "properties": {
    "iso:country":"US",
    "sg:address":"1727 Highway 42 N",
    "sg:city":"McDonough",
    "sg:classifiers":[
        {
            "category":"Health Services",
            "subcategory":"Chiropractor",
            "type":"Services"
        }
    ],
    "sg:phone":"+1 770 898 3670",
    "sg:postcode":"30253",
    "sg:province":"GA",
    "wof:name":"Morrow Chiropractic",
    "wof:placetype":"venue"
},
  "geometry": {"coordinates":[-84.17558200000001,33.489968],"type":"Point"}
}