{
  "type": "Feature",
  "properties": {
    "iso:country":"US",
    "sg:address":"1189 Avon Ave SW",
    "sg:city":"Atlanta",
    "sg:classifiers":[
        {
            "category":"Manufacturing",
            "subcategory":"Paper Products",
            "type":"Manufacturing & Wholesale Goods"
        }
    ],
    "sg:phone":"+1 404 758 1814",
    "sg:postcode":"30310",
    "sg:province":"GA",
    "sg:tags":[
        "machine",
        "cutting",
        "drilling"
    ],
    "wof:name":"Absolute Integrity Group",
    "wof:placetype":"venue"
},
  "geometry": {"coordinates":[-84.42678100000001,33.72226],"type":"Point"}
}