{
  "type": "Feature",
  "properties": {
    "iso:country":"US",
    "sg:address":"2042 Whitfield Ln",
    "sg:city":"Lawrenceville",
    "sg:classifiers":[
        {
            "category":"Manufacturing",
            "subcategory":"Apparel",
            "type":"Manufacturing & Wholesale Goods"
        }
    ],
    "sg:phone":"+1 678 377 1891",
    "sg:postcode":"30043",
    "sg:province":"GA",
    "sg:tags":[
        "mfg"
    ],
    "wof:name":"Virtual Expression",
    "wof:placetype":"venue"
},
  "geometry": {"coordinates":[-84.048903,33.993932],"type":"Point"}
}