{
  "type": "Feature",
  "properties": {
    "addr:full":"1004 Hillcrest Pkwy Dublin GA 31021",
    "addr:housenumber":"1004",
    "addr:postcode":"31021",
    "addr:street":"Hillcrest Pkwy",
    "iso:country":"US",
    "sg:address":"1004 Hillcrest Pkwy",
    "sg:city":"Dublin",
    "sg:classifiers":[
        {
            "category":"Professional",
            "subcategory":"Accounting & Tax Preparation",
            "type":"Services"
        }
    ],
    "sg:phone":"+1 478 272 2030",
    "sg:postcode":"31021",
    "sg:province":"GA",
    "sg:tags":[
        "accountant"
    ],
    "sg:website":"www.tjscpa.com",
    "wof:name":"Thigpen Jones Seaton & Co PC",
    "wof:placetype":"venue"
},
  "geometry": {"coordinates":[-82.927677,32.548162],"type":"Point"}
}