{
  "type": "Feature",
  "properties": {
    "addr:full":"2585 Old Rockbridge Rd Norcross GA 30071",
    "addr:housenumber":"2585",
    "addr:postcode":"30071",
    "addr:street":"Old Rockbridge Rd",
    "iso:country":"US",
    "sg:address":"2585 Old Rockbridge Rd",
    "sg:city":"Norcross",
    "sg:classifiers":[
        {
            "category":"Retail",
            "subcategory":"Auto Repair",
            "type":"Services"
        }
    ],
    "sg:phone":"+1 770 447 8822",
    "sg:postcode":"30071",
    "sg:province":"GA",
    "sg:tags":[
        "repairing",
        "automobile",
        "automotive"
    ],
    "wof:name":"Alliance Service Center Inc",
    "wof:placetype":"venue"
},
  "geometry": {"coordinates":[-84.2257,33.927601],"type":"Point"}
}