{
  "type": "Feature",
  "properties": {
    "addr:full":"4299 Hugh Howell Rd Tucker GA 30084",
    "addr:housenumber":"4299",
    "addr:postcode":"30084",
    "addr:street":"Hugh Howell Rd",
    "iso:country":"US",
    "sg:address":"4299 Hugh Howell Rd",
    "sg:city":"Tucker",
    "sg:classifiers":[
        {
            "category":"Retail",
            "subcategory":"Repair Shop",
            "type":"Services"
        }
    ],
    "sg:phone":"+1 770 491 1432",
    "sg:postcode":"30084",
    "sg:province":"GA",
    "wof:name":"Crabb L B & Associates",
    "wof:placetype":"venue"
},
  "geometry": {"coordinates":[-84.20862099999999,33.851784],"type":"Point"}
}