{
  "type": "Feature",
  "properties": {
    "addr:full":"4500 S Main St Acworth GA 30101",
    "addr:housenumber":"4500",
    "addr:postcode":"30101",
    "addr:street":"S Main St",
    "iso:country":"US",
    "sg:address":"4500 S Main St",
    "sg:city":"Acworth",
    "sg:classifiers":[
        {
            "category":"Real Estate",
            "subcategory":"Developer",
            "type":"Services"
        }
    ],
    "sg:phone":"+1 770 974 3777",
    "sg:postcode":"30101",
    "sg:province":"GA",
    "wof:name":"Clark's Construction & Dvlpmnt",
    "wof:placetype":"venue"
},
  "geometry": {"coordinates":[-84.667683,34.064042],"type":"Point"}
}