{
  "type": "Feature",
  "properties": {
    "addr:full":"323 College Dr Barnesville GA 30204",
    "addr:housenumber":"323",
    "addr:postcode":"30204",
    "addr:street":"College Dr",
    "iso:country":"US",
    "sg:address":"323 College Dr",
    "sg:city":"Barnesville",
    "sg:classifiers":[
        {
            "category":"Restaurant",
            "type":"Food & Drink"
        }
    ],
    "sg:menulink":"http://www.allmenus.com/ga/barnesville/154396-hardees/menu/",
    "sg:phone":"+1 770 358 6122",
    "sg:postcode":"30204",
    "sg:province":"GA",
    "sg:tags":[
        "burger",
        "american"
    ],
    "wof:name":"Hardee's",
    "wof:placetype":"venue"
},
  "geometry": {"coordinates":[-84.15059599999999,33.058182],"type":"Point"}
}