{
  "type": "Feature",
  "properties": {
    "addr:full":"314 Progress Ave Hawkinsville GA 31036",
    "addr:housenumber":"314",
    "addr:postcode":"31036",
    "addr:street":"Progress Ave",
    "iso:country":"US",
    "sg:address":"314 Progress Ave",
    "sg:city":"Hawkinsville",
    "sg:classifiers":[
        {
            "category":"Government",
            "subcategory":"Office",
            "type":"Public Place"
        }
    ],
    "sg:phone":"+1 478 892 9830",
    "sg:postcode":"31036",
    "sg:province":"GA",
    "sg:tags":[
        "village"
    ],
    "wof:name":"Henry Way Apartments",
    "wof:placetype":"venue"
},
  "geometry": {"coordinates":[-83.474542,32.286392],"type":"Point"}
}