{
  "type": "Feature",
  "properties": {
    "addr:full":"661 Dyer Rd Newnan GA 30263",
    "addr:housenumber":"661",
    "addr:postcode":"30263",
    "addr:street":"Dyer Rd",
    "iso:country":"US",
    "sg:address":"661 Dyer Rd",
    "sg:city":"Newnan",
    "sg:classifiers":[
        {
            "category":"Manufacturing",
            "subcategory":"Chemicals & Compounds",
            "type":"Manufacturing & Wholesale Goods"
        }
    ],
    "sg:phone":"+1 770 251 3122",
    "sg:postcode":"30263",
    "sg:province":"GA",
    "sg:tags":[
        "concrete",
        "additive"
    ],
    "wof:name":"Boral Material Technologies",
    "wof:placetype":"venue"
},
  "geometry": {"coordinates":[-84.89527,33.467348],"type":"Point"}
}