{
  "type": "Feature",
  "properties": {
    "iso:country":"US",
    "sg:address":"304 Martin Luther King Jr Ave",
    "sg:city":"Vidalia",
    "sg:classifiers":[
        {
            "category":"Organizations",
            "subcategory":"Religious Organization",
            "type":"Services"
        }
    ],
    "sg:phone":"+1 912 537 4872",
    "sg:postcode":"30474",
    "sg:province":"GA",
    "sg:tags":[
        "church"
    ],
    "wof:name":"St Paul's AME Church",
    "wof:placetype":"venue"
},
  "geometry": {"coordinates":[-82.40576,32.22035],"type":"Point"}
}