{
  "type": "Feature",
  "properties": {
    "iso:country":"US",
    "sg:address":"3101 Mccall Dr",
    "sg:city":"Atlanta",
    "sg:classifiers":[
        {
            "category":"Shopping",
            "subcategory":"Crafts & Fabrics",
            "type":"Retail Goods"
        },
        {
            "category":"Professional",
            "subcategory":"Printing & Photocopies",
            "type":"Services"
        }
    ],
    "sg:phone":"+1 678 547 0828",
    "sg:postcode":"30340",
    "sg:province":"GA",
    "sg:tags":[
        "lithographer",
        "material",
        "manufacturer",
        "ink"
    ],
    "wof:name":"Flint Ink",
    "wof:placetype":"venue"
},
  "geometry": {"coordinates":[-84.260293,33.89856],"type":"Point"}
}