{
  "type": "Feature",
  "properties": {
    "iso:country":"US",
    "sg:address":"2778 W Fontainebleau Dr",
    "sg:city":"Atlanta",
    "sg:classifiers":[
        {
            "category":"Communications",
            "type":"Services"
        }
    ],
    "sg:phone":"+1 770 396 9924",
    "sg:postcode":"30360",
    "sg:province":"GA",
    "sg:tags":[
        "communication"
    ],
    "wof:name":"Right Brain Communications",
    "wof:placetype":"venue"
},
  "geometry": {"coordinates":[-84.281367,33.955203],"type":"Point"}
}