{
  "type": "Feature",
  "properties": {
    "addr:full":"101 River Pointe Pkwy Canton GA 30114",
    "addr:housenumber":"101",
    "addr:postcode":"30114",
    "addr:street":"River Pointe Pkwy",
    "iso:country":"US",
    "sg:address":"101 River Pointe Pkwy",
    "sg:city":"Canton",
    "sg:classifiers":[
        {
            "category":"Fast Food",
            "type":"Food & Drink"
        },
        {
            "category":"Food & Beverages",
            "subcategory":"Meat & Fish",
            "type":"Retail Goods"
        }
    ],
    "sg:phone":"+1 770 345 4981",
    "sg:postcode":"30114",
    "sg:province":"GA",
    "sg:tags":[
        "burger",
        "hot",
        "dog"
    ],
    "wof:name":"Wendy's Old Fashioned Hamburgers",
    "wof:placetype":"venue"
},
  "geometry": {"coordinates":[-84.46292800000001,34.259417],"type":"Point"}
}