{
  "type": "Feature",
  "properties": {
    "iso:country":"US",
    "sg:address":"3618 Sandy Plains Rd.",
    "sg:city":"Marietta",
    "sg:classifiers":[
        {
            "category":"Health Services",
            "subcategory":"Doctor",
            "type":"Services"
        }
    ],
    "sg:phone":"+1 770 977 3513",
    "sg:postcode":"30066",
    "sg:province":"GA",
    "sg:tags":[
        "obstetrician",
        "gynecologist"
    ],
    "wof:name":"North Atlanta OBGYN",
    "wof:placetype":"venue"
},
  "geometry": {"coordinates":[-84.460714,34.038159],"type":"Point"}
}