{
  "type": "Feature",
  "properties": {
    "iso:country":"US",
    "sg:address":"109 Eastwick Ct",
    "sg:city":"Macon",
    "sg:classifiers":[
        {
            "category":"Building & Trades",
            "subcategory":"Construction",
            "type":"Services"
        }
    ],
    "sg:phone":"+1 478 476 8105",
    "sg:postcode":"31210",
    "sg:province":"GA",
    "sg:tags":[
        "house"
    ],
    "wof:name":"Tucker Tile & Remodeling",
    "wof:placetype":"venue"
},
  "geometry": {"coordinates":[-83.721165,32.922177],"type":"Point"}
}