{
  "type": "Feature",
  "properties": {
    "iso:country":"US",
    "sg:address":"1680 Mall of Georgia Blvd Ste 1720",
    "sg:city":"Buford",
    "sg:classifiers":[
        {
            "category":"Wholesale",
            "subcategory":"Fruits & Vegetables",
            "type":"Manufacturing & Wholesale Goods"
        }
    ],
    "sg:phone":"+1 770 945 8867",
    "sg:postcode":"30519",
    "sg:province":"GA",
    "sg:tags":[
        "veggie"
    ],
    "sg:website":"www.ediblearrangements.com",
    "wof:name":"Edible Arrangements- Mall of Georgia",
    "wof:placetype":"venue"
},
  "geometry": {"coordinates":[-83.99521,34.061627],"type":"Point"}
}