{
  "type": "Feature",
  "properties": {
    "addr:full":"1581 Satellite Blvd Duluth GA 30097",
    "addr:housenumber":"1581",
    "addr:postcode":"30097",
    "addr:street":"Satellite Blvd",
    "iso:country":"US",
    "sg:address":"1581 Satellite Blvd",
    "sg:city":"Duluth",
    "sg:classifiers":[
        {
            "category":"Banks & Credit Unions",
            "subcategory":"Bank",
            "type":"Services"
        }
    ],
    "sg:phone":"+1 770 442 7770",
    "sg:postcode":"30097",
    "sg:province":"GA",
    "wof:name":"Integrity Bank",
    "wof:placetype":"venue"
},
  "geometry": {"coordinates":[-84.08288400000001,34.000489],"type":"Point"}
}