{
  "type": "Feature",
  "properties": {
    "addr:full":"3625 Moon Rd Loganville GA 30052",
    "addr:housenumber":"3625",
    "addr:postcode":"30052",
    "addr:street":"Moon Rd",
    "iso:country":"US",
    "sg:address":"3625 Moon Rd",
    "sg:city":"Loganville",
    "sg:classifiers":[
        {
            "category":"Autos & Motor Vehicles",
            "subcategory":"Automobile Sales",
            "type":"Retail Goods"
        }
    ],
    "sg:phone":"+1 770 466 7893",
    "sg:postcode":"30052",
    "sg:province":"GA",
    "sg:tags":[
        "used"
    ],
    "wof:name":"My Auto Sales",
    "wof:placetype":"venue"
},
  "geometry": {"coordinates":[-83.954643,33.79051],"type":"Point"}
}