{
  "type": "Feature",
  "properties": {
    "addr:full":"7218 State Rte 85 Riverdale GA 30274",
    "addr:housenumber":"7218",
    "addr:postcode":"30274",
    "addr:street":"State Rte 85",
    "iso:country":"US",
    "sg:address":"7218 State Rte 85",
    "sg:city":"Riverdale",
    "sg:classifiers":[
        {
            "category":"Manufacturing",
            "subcategory":"Printing",
            "type":"Manufacturing & Wholesale Goods"
        },
        {
            "category":"Wholesale",
            "subcategory":"Jewelry",
            "type":"Manufacturing & Wholesale Goods"
        }
    ],
    "sg:phone":"+1 770 991 5636",
    "sg:postcode":"30274",
    "sg:province":"GA",
    "sg:tags":[
        "trophy",
        "screen"
    ],
    "wof:name":"Tag Team Sports Inc",
    "wof:placetype":"venue"
},
  "geometry": {"coordinates":[-84.413832,33.561188],"type":"Point"}
}