{
  "type": "Feature",
  "properties": {
    "iso:country":"US",
    "sg:address":"700 S Harney St",
    "sg:city":"Camilla",
    "sg:classifiers":[
        {
            "category":"Organizations",
            "subcategory":"Religious Organization",
            "type":"Services"
        }
    ],
    "sg:phone":"+1 229 336 7574",
    "sg:postcode":"31730",
    "sg:province":"GA",
    "wof:name":"Tucker Baptist Association",
    "wof:placetype":"venue"
},
  "geometry": {"coordinates":[-84.200462,31.213449],"type":"Point"}
}