{
  "type": "Feature",
  "properties": {
    "addr:full":"842 Sunset Rd Canon GA 30520",
    "addr:housenumber":"842",
    "addr:postcode":"30520",
    "addr:street":"Sunset Rd",
    "iso:country":"US",
    "sg:address":"842 Sunset Rd",
    "sg:city":"Canon",
    "sg:classifiers":[
        {
            "category":"Food & Beverages",
            "subcategory":"Liquor & Beverages",
            "type":"Retail Goods"
        }
    ],
    "sg:phone":"+1 706 376 9555",
    "sg:postcode":"30520",
    "sg:province":"GA",
    "sg:tags":[
        "alcoholic"
    ],
    "wof:name":"Ellas Pac A Sac",
    "wof:placetype":"venue"
},
  "geometry": {"coordinates":[-82.973797,34.334488],"type":"Point"}
}