{
  "type": "Feature",
  "properties": {
    "addr:full":"5830 Ettington Dr Suwanee GA 30024",
    "addr:housenumber":"5830",
    "addr:postcode":"30024",
    "addr:street":"Ettington Dr",
    "iso:country":"US",
    "sg:address":"5830 Ettington Dr",
    "sg:city":"Suwanee",
    "sg:classifiers":[
        {
            "category":"Insurance",
            "subcategory":"Insurance Agent",
            "type":"Services"
        }
    ],
    "sg:phone":"+1 770 888 4399",
    "sg:postcode":"30024",
    "sg:province":"GA",
    "wof:name":"Great American",
    "wof:placetype":"venue"
},
  "geometry": {"coordinates":[-84.15718099999999,34.089731],"type":"Point"}
}