{
  "type": "Feature",
  "properties": {
    "addr:full":"2551 Roswell Rd Bldg. 400, ste. 420 Marietta GA 30062",
    "addr:housenumber":"2551;400 ste. 420",
    "addr:postcode":"30062",
    "addr:street":"Roswell Rd Bldg.",
    "iso:country":"US",
    "sg:address":"2551 Roswell Rd Bldg. 400, ste. 420",
    "sg:city":"Marietta",
    "sg:classifiers":[
        {
            "category":"Professional",
            "subcategory":"Computer Services",
            "type":"Services"
        }
    ],
    "sg:phone":"+1 678 560 3033",
    "sg:postcode":"30062",
    "sg:province":"GA",
    "sg:tags":[
        "repair"
    ],
    "sg:website":"www.pcrepair.net",
    "wof:name":"Cci-Chapman Computers Inc",
    "wof:placetype":"venue"
},
  "geometry": {"coordinates":[-84.477816,33.97461],"type":"Point"}
}