{
  "type": "Feature",
  "properties": {
    "addr:full":"10922 Alpharetta Hwy Roswell GA 30076",
    "addr:housenumber":"10922",
    "addr:postcode":"30076",
    "addr:street":"Alpharetta Hwy",
    "iso:country":"US",
    "sg:address":"10922 Alpharetta Hwy",
    "sg:city":"Roswell",
    "sg:classifiers":[
        {
            "category":"Shopping",
            "subcategory":"Used Merchandise",
            "type":"Retail Goods"
        }
    ],
    "sg:phone":"+1 770 518 6900",
    "sg:postcode":"30076",
    "sg:province":"GA",
    "sg:tags":[
        "pawnbroker"
    ],
    "wof:name":"Cash King",
    "wof:placetype":"venue"
},
  "geometry": {"coordinates":[-84.33456,34.051852],"type":"Point"}
}