{
  "type": "Feature",
  "properties": {
    "addr:full":"6534 Beaver Trl Midland GA 31820",
    "addr:housenumber":"6534",
    "addr:postcode":"31820",
    "addr:street":"Beaver Trl",
    "iso:country":"US",
    "sg:address":"6534 Beaver Trl",
    "sg:city":"Midland",
    "sg:classifiers":[
        {
            "category":"Building & Trades",
            "subcategory":"Landscaping Services",
            "type":"Services"
        }
    ],
    "sg:phone":"+1 706 565 6191",
    "sg:postcode":"31820",
    "sg:province":"GA",
    "sg:tags":[
        "landscape"
    ],
    "wof:name":"Gill Cargill Landscapes",
    "wof:placetype":"venue"
},
  "geometry": {"coordinates":[-84.860895,32.538422],"type":"Point"}
}