{
  "type": "Feature",
  "properties": {
    "iso:country":"US",
    "sg:address":"13 Cypress St",
    "sg:city":"Bloomingdale",
    "sg:classifiers":[
        {
            "category":"Restaurant",
            "type":"Food & Drink"
        }
    ],
    "sg:phone":"+1 912 545 2751",
    "sg:postcode":"31302",
    "sg:province":"GA",
    "wof:name":"Sharon's Southern Fried Chckn",
    "wof:placetype":"venue"
},
  "geometry": {"coordinates":[-81.290133,32.129224],"type":"Point"}
}