{
  "type": "Feature",
  "properties": {
    "addr:full":"930 Lake Park Rd Valdosta GA 31601",
    "addr:housenumber":"930",
    "addr:postcode":"31601",
    "addr:street":"Lake Park Rd",
    "iso:country":"US",
    "sg:address":"930 Lake Park Rd",
    "sg:city":"Valdosta",
    "sg:classifiers":[
        {
            "category":"Education",
            "subcategory":"School",
            "type":"Public Place"
        }
    ],
    "sg:phone":"+1 229 333 8520",
    "sg:postcode":"31601",
    "sg:province":"GA",
    "wof:name":"Lomax-Pinevale Elementary",
    "wof:placetype":"venue"
},
  "geometry": {"coordinates":[-83.26781099999999,30.826027],"type":"Point"}
}