{
  "type": "Feature",
  "properties": {
    "addr:full":"709 Middlebrook Dr Jonesboro GA 30236",
    "addr:housenumber":"709",
    "addr:postcode":"30236",
    "addr:street":"Middlebrook Dr",
    "iso:country":"US",
    "sg:address":"709 Middlebrook Dr",
    "sg:city":"Jonesboro",
    "sg:classifiers":[
        {
            "category":"Organizations",
            "subcategory":"Religious Organization",
            "type":"Services"
        }
    ],
    "sg:phone":"+1 770 478 5647",
    "sg:postcode":"30236",
    "sg:province":"GA",
    "wof:name":"Apostolic Christian Church",
    "wof:placetype":"venue"
},
  "geometry": {"coordinates":[-84.36692499999999,33.549054],"type":"Point"}
}