{
  "type": "Feature",
  "properties": {
    "addr:full":"2009 Commerce Dr Peachtree City GA 30269",
    "addr:housenumber":"2009",
    "addr:postcode":"30269",
    "addr:street":"Commerce Dr",
    "iso:country":"US",
    "sg:address":"2009 Commerce Dr",
    "sg:city":"Peachtree City",
    "sg:classifiers":[
        {
            "category":"Recreation",
            "type":"Entertainment"
        }
    ],
    "sg:phone":"+1 770 631 0930",
    "sg:postcode":"30269",
    "sg:province":"GA",
    "sg:tags":[
        "equipment",
        "tennis",
        "center"
    ],
    "wof:name":"Goodsports",
    "wof:placetype":"venue"
},
  "geometry": {"coordinates":[-84.592944,33.399726],"type":"Point"}
}