{
  "type": "Feature",
  "properties": {
    "iso:country":"US",
    "sg:address":"1000 Soshama Ln",
    "sg:city":"Young Harris",
    "sg:classifiers":[
        {
            "category":"Retail",
            "subcategory":"Animal Services",
            "type":"Services"
        }
    ],
    "sg:phone":"+1 706 379 2050",
    "sg:postcode":"30582",
    "sg:province":"GA",
    "sg:tags":[
        "specialty"
    ],
    "wof:name":"Soshayma K-9s",
    "wof:placetype":"venue"
},
  "geometry": {"coordinates":[-83.87690499999999,34.962596],"type":"Point"}
}