{
  "type": "Feature",
  "properties": {
    "addr:full":"1865 Savoy Dr Atlanta GA 30341",
    "addr:housenumber":"1865",
    "addr:postcode":"30341",
    "addr:street":"Savoy Dr",
    "iso:country":"US",
    "sg:address":"1865 Savoy Dr",
    "sg:city":"Atlanta",
    "sg:classifiers":[
        {
            "category":"Freight",
            "type":"Transportation"
        }
    ],
    "sg:phone":"+1 770 458 6405",
    "sg:postcode":"30341",
    "sg:province":"GA",
    "sg:tags":[
        "paper",
        "general"
    ],
    "wof:name":"Shurgard Storage Centers",
    "wof:placetype":"venue"
},
  "geometry": {"coordinates":[-84.307536,33.919759],"type":"Point"}
}