{
  "type": "Feature",
  "properties": {
    "iso:country":"US",
    "sg:address":"5082 Verbena Dr",
    "sg:city":"Acworth",
    "sg:classifiers":[
        {
            "category":"Professional",
            "type":"Services"
        }
    ],
    "sg:phone":"+1 770 516 1707",
    "sg:postcode":"30102",
    "sg:province":"GA",
    "sg:tags":[
        "establishment"
    ],
    "wof:name":"Strategic Commerce Intern",
    "wof:placetype":"venue"
},
  "geometry": {"coordinates":[-84.568381,34.068992],"type":"Point"}
}