{
  "type": "Feature",
  "properties": {
    "iso:country":"US",
    "sg:address":"2725 Mtn Industrial Blvd",
    "sg:city":"Tucker",
    "sg:classifiers":[
        {
            "category":"Professional",
            "subcategory":"Computer Services",
            "type":"Services"
        }
    ],
    "sg:phone":"+1 770 414 0010",
    "sg:postcode":"30084",
    "sg:province":"GA",
    "sg:tags":[
        "stereo",
        "installation"
    ],
    "wof:name":"Car Stereo Plus Inc",
    "wof:placetype":"venue"
},
  "geometry": {"coordinates":[-84.18910200000001,33.857899],"type":"Point"}
}