{
  "type": "Feature",
  "properties": {
    "addr:full":"991 Peachtree Industrial Blvd. Suwanee GA 30024",
    "addr:housenumber":"991",
    "addr:postcode":"30024",
    "addr:street":"Peachtree Industrial Blvd.",
    "iso:country":"US",
    "sg:address":"991 Peachtree Industrial Blvd.",
    "sg:city":"Suwanee",
    "sg:classifiers":[
        {
            "category":"Restaurant",
            "type":"Food & Drink"
        }
    ],
    "sg:phone":"+1 770 271 9992",
    "sg:postcode":"30024",
    "sg:province":"GA",
    "sg:tags":[
        "pizza"
    ],
    "sg:website":"www.riversidepizza.net",
    "wof:name":"Riverside Pizza",
    "wof:placetype":"venue"
},
  "geometry": {"coordinates":[-84.091993,34.049255],"type":"Point"}
}