{
  "type": "Feature",
  "properties": {
    "addr:full":"4522 Villa Rica Hwy Dallas GA 30157",
    "addr:housenumber":"4522",
    "addr:postcode":"30157",
    "addr:street":"Villa Rica Hwy",
    "iso:country":"US",
    "sg:address":"4522 Villa Rica Hwy",
    "sg:city":"Dallas",
    "sg:classifiers":[
        {
            "category":"Building & Trades",
            "subcategory":"Construction",
            "type":"Services"
        }
    ],
    "sg:phone":"+1 770 445 2988",
    "sg:postcode":"30157",
    "sg:province":"GA",
    "sg:tags":[
        "manufactured",
        "housing-communities"
    ],
    "wof:name":"Lawrence Junction Mobile Home Park",
    "wof:placetype":"venue"
},
  "geometry": {"coordinates":[-84.85505000000001,33.85134],"type":"Point"}
}