{
  "type": "Feature",
  "properties": {
    "addr:full":"205 Banks Rd Ochlocknee GA 31773",
    "addr:housenumber":"205",
    "addr:postcode":"31773",
    "addr:street":"Banks Rd",
    "iso:country":"US",
    "sg:address":"205 Banks Rd",
    "sg:city":"Ochlocknee",
    "sg:classifiers":[
        {
            "category":"Professional",
            "type":"Services"
        }
    ],
    "sg:phone":"+1 229 377 5864",
    "sg:postcode":"31773",
    "sg:province":"GA",
    "wof:name":"Robert Raker",
    "wof:placetype":"venue"
},
  "geometry": {"coordinates":[-84.142061,30.985082],"type":"Point"}
}