{
  "type": "Feature",
  "properties": {
    "iso:country":"US",
    "sg:address":"2000 ClearView Avenue Suite 111",
    "sg:city":"Doraville",
    "sg:classifiers":[
        {
            "category":"Health Services",
            "subcategory":"Doctor",
            "type":"Services"
        },
        {
            "category":"Community Center",
            "type":"Public Place"
        }
    ],
    "sg:phone":"+1 770 451 3100",
    "sg:postcode":"30340",
    "sg:province":"GA",
    "sg:tags":[
        "medical",
        "obstetrician",
        "gynecologist"
    ],
    "sg:website":"www.cimasalud.net",
    "wof:name":"CIMA",
    "wof:placetype":"venue"
},
  "geometry": {"coordinates":[-84.27374500000001,33.900361],"type":"Point"}
}