{
  "type": "Feature",
  "properties": {
    "iso:country":"US",
    "sg:address":"155 Birch Hollow Trl",
    "sg:city":"Marietta",
    "sg:classifiers":[
        {
            "category":"Professional",
            "subcategory":"Employment Agencies",
            "type":"Services"
        }
    ],
    "sg:phone":"+1 770 422 2280",
    "sg:postcode":"30064",
    "sg:province":"GA",
    "sg:tags":[
        "trainer",
        "c",
        "providing",
        "for",
        "broker",
        "education"
    ],
    "wof:name":"Training Connections Inc",
    "wof:placetype":"venue"
},
  "geometry": {"coordinates":[-84.591058,33.954092],"type":"Point"}
}