{
  "type": "Feature",
  "properties": {
    "addr:full":"1966 Morning Ln Acworth GA 30102",
    "addr:housenumber":"1966",
    "addr:postcode":"30102",
    "addr:street":"Morning Ln",
    "iso:country":"US",
    "sg:address":"1966 Morning Ln",
    "sg:city":"Acworth",
    "sg:classifiers":[
        {
            "category":"Professional",
            "subcategory":"Business Services",
            "type":"Services"
        }
    ],
    "sg:phone":"+1 770 975 9710",
    "sg:postcode":"30102",
    "sg:province":"GA",
    "wof:name":"Optimus Enterprises Inc",
    "wof:placetype":"venue"
},
  "geometry": {"coordinates":[-84.609376,34.073932],"type":"Point"}
}