{
  "type": "Feature",
  "properties": {
    "addr:full":"27 Lakes Edge Dr Smyrna GA 30080",
    "addr:housenumber":"27",
    "addr:postcode":"30080",
    "addr:street":"Lakes Edge Dr",
    "iso:country":"US",
    "sg:address":"27 Lakes Edge Dr",
    "sg:city":"Smyrna",
    "sg:classifiers":[
        {
            "category":"Professional",
            "subcategory":"Business Services",
            "type":"Services"
        }
    ],
    "sg:phone":"+1 770 329 6575",
    "sg:postcode":"30080",
    "sg:province":"GA",
    "wof:name":"Safety Enterprise",
    "wof:placetype":"venue"
},
  "geometry": {"coordinates":[-84.495682,33.895086],"type":"Point"}
}