{
  "type": "Feature",
  "properties": {
    "iso:country":"US",
    "sg:address":"27 Lenox Pointe NE",
    "sg:city":"Atlanta",
    "sg:classifiers":[
        {
            "category":"Health Services",
            "subcategory":"Doctor",
            "type":"Services"
        }
    ],
    "sg:phone":"+1 404 237 3210",
    "sg:postcode":"30324",
    "sg:province":"GA",
    "wof:name":"Brown Samuel B MD",
    "wof:placetype":"venue"
},
  "geometry": {"coordinates":[-84.355322,33.825774],"type":"Point"}
}