{
  "type": "Feature",
  "properties": {
    "addr:full":"33 Northwood Ave NE Atlanta GA 30309",
    "addr:housenumber":"33",
    "addr:postcode":"30309",
    "addr:street":"Northwood Ave Ne",
    "iso:country":"US",
    "sg:address":"33 Northwood Ave NE",
    "sg:city":"Atlanta",
    "sg:classifiers":[
        {
            "category":"Professional",
            "subcategory":"Business Services",
            "type":"Services"
        }
    ],
    "sg:phone":"+1 404 607 8080",
    "sg:postcode":"30309",
    "sg:province":"GA",
    "wof:name":"Chaumont Inc",
    "wof:placetype":"venue"
},
  "geometry": {"coordinates":[-84.390991,33.804524],"type":"Point"}
}