{
  "type": "Feature",
  "properties": {
    "addr:full":"5855 Sunset Maple Dr Alpharetta GA 30005",
    "addr:housenumber":"5855",
    "addr:postcode":"30005",
    "addr:street":"Sunset Maple Dr",
    "iso:country":"US",
    "sg:address":"5855 Sunset Maple Dr",
    "sg:city":"Alpharetta",
    "sg:classifiers":[
        {
            "category":"Shopping",
            "subcategory":"Bicycles & Sporting Goods",
            "type":"Retail Goods"
        }
    ],
    "sg:phone":"+1 770 569 2265",
    "sg:postcode":"30005",
    "sg:province":"GA",
    "wof:name":"Gameday",
    "wof:placetype":"venue"
},
  "geometry": {"coordinates":[-84.191169,34.082475],"type":"Point"}
}