{
  "type": "Feature",
  "properties": {
    "addr:full":"3372 Cobb Pkwy NW Acworth GA 30101",
    "addr:housenumber":"3372",
    "addr:postcode":"30101",
    "addr:street":"Cobb Pkwy Nw",
    "iso:country":"US",
    "sg:address":"3372 Cobb Pkwy NW",
    "sg:city":"Acworth",
    "sg:classifiers":[
        {
            "category":"Shopping",
            "subcategory":"Stationery & Office Supplies",
            "type":"Retail Goods"
        }
    ],
    "sg:phone":"+1 770 529 3021",
    "sg:postcode":"30101",
    "sg:province":"GA",
    "sg:tags":[
        "equipment"
    ],
    "wof:name":"Officemax",
    "wof:placetype":"venue"
},
  "geometry": {"coordinates":[-84.681899,34.035766],"type":"Point"}
}