{
  "type": "Feature",
  "properties": {
    "iso:country":"US",
    "sg:address":"2487 Shenley Park Ct",
    "sg:city":"Duluth",
    "sg:classifiers":[
        {
            "category":"Restaurant",
            "type":"Food & Drink"
        }
    ],
    "sg:phone":"+1 770 716 5959",
    "sg:postcode":"30097",
    "sg:province":"GA",
    "sg:tags":[
        "style",
        "family"
    ],
    "wof:name":"Dong Son",
    "wof:placetype":"venue"
},
  "geometry": {"coordinates":[-84.10387799999999,33.987443],"type":"Point"}
}