{
  "type": "Feature",
  "properties": {
    "iso:country":"US",
    "sg:address":"3240 S Cobb Dr SE",
    "sg:city":"Smyrna",
    "sg:classifiers":[
        {
            "category":"Insurance",
            "subcategory":"Health Insurance",
            "type":"Services"
        }
    ],
    "sg:phone":"+1 770 435 8567",
    "sg:postcode":"30080",
    "sg:province":"GA",
    "sg:tags":[
        "market"
    ],
    "wof:name":"The Herb Shop",
    "wof:placetype":"venue"
},
  "geometry": {"coordinates":[-84.528198,33.870998],"type":"Point"}
}