{
  "type": "Feature",
  "properties": {
    "iso:country":"US",
    "sg:address":"701 Whitlock Ave SW",
    "sg:city":"Marietta",
    "sg:classifiers":[
        {
            "category":"Professional",
            "subcategory":"Lawyer & Legal Services",
            "type":"Services"
        }
    ],
    "sg:phone":"+1 770 424 5125",
    "sg:postcode":"30064",
    "sg:province":"GA",
    "wof:name":"Persons Firm the",
    "wof:placetype":"venue"
},
  "geometry": {"coordinates":[-84.573339,33.951763],"type":"Point"}
}