{
  "type": "Feature",
  "properties": {
    "iso:country":"US",
    "sg:address":"1 Riverside Pkwy NE",
    "sg:city":"Rome",
    "sg:classifiers":[
        {
            "category":"Organizations",
            "subcategory":"Professional Association",
            "type":"Services"
        }
    ],
    "sg:phone":"+1 706 291 7663",
    "sg:postcode":"30161",
    "sg:province":"GA",
    "sg:tags":[
        "chambers",
        "commerce",
        "chamber"
    ],
    "sg:website":"www.romega.com",
    "wof:name":"Greater Rome Chamber Commerce",
    "wof:placetype":"venue"
},
  "geometry": {"coordinates":[-85.167908,34.257526],"type":"Point"}
}