{
  "type": "Feature",
  "properties": {
    "addr:full":"898 Emerson Ave Atlanta GA 30316",
    "addr:housenumber":"898",
    "addr:postcode":"30316",
    "addr:street":"Emerson Ave",
    "iso:country":"US",
    "sg:address":"898 Emerson Ave",
    "sg:city":"Atlanta",
    "sg:classifiers":[
        {
            "category":"Professional",
            "subcategory":"Art Services",
            "type":"Services"
        }
    ],
    "sg:phone":"+1 404 931 3189",
    "sg:postcode":"30316",
    "sg:province":"GA",
    "sg:tags":[
        "photographer"
    ],
    "sg:website":"www.weddingsbyjason.com/",
    "wof:name":"Weddings by Jason",
    "wof:placetype":"venue"
},
  "geometry": {"coordinates":[-84.358133,33.733075],"type":"Point"}
}