{
  "type": "Feature",
  "properties": {
    "iso:country":"US",
    "sg:address":"10 E Park Sq",
    "sg:city":"Marietta",
    "sg:classifiers":[
        {
            "category":"Communications",
            "type":"Services"
        }
    ],
    "sg:phone":"+1 770 514 0001",
    "sg:postcode":"30090",
    "sg:province":"GA",
    "sg:tags":[
        "consultant"
    ],
    "wof:name":"Clec Solutions",
    "wof:placetype":"venue"
},
  "geometry": {"coordinates":[-84.54904500000001,33.952334],"type":"Point"}
}