{
  "type": "Feature",
  "properties": {
    "iso:country":"US",
    "sg:address":"412 Bradford Creek Trl",
    "sg:city":"Duluth",
    "sg:classifiers":[
        {
            "category":"Retail",
            "subcategory":"Car Wash",
            "type":"Services"
        }
    ],
    "sg:phone":"+1 678 698 2232",
    "sg:postcode":"30096",
    "sg:province":"GA",
    "sg:tags":[
        "carwash"
    ],
    "wof:name":"Platinum Cleaning Concepts",
    "wof:placetype":"venue"
},
  "geometry": {"coordinates":[-84.16329,33.993773],"type":"Point"}
}