{
  "type": "Feature",
  "properties": {
    "addr:full":"24 State Hwy 20 Spur SE Cartersville GA 30121",
    "addr:housenumber":"24",
    "addr:postcode":"30121",
    "addr:street":"State Hwy 20 Spur Se",
    "iso:country":"US",
    "sg:address":"24 State Hwy 20 Spur SE",
    "sg:city":"Cartersville",
    "sg:classifiers":[
        {
            "category":"Wholesale",
            "subcategory":"Auto Parts",
            "type":"Manufacturing & Wholesale Goods"
        }
    ],
    "sg:phone":"+1 770 607 3616",
    "sg:postcode":"30121",
    "sg:province":"GA",
    "sg:tags":[
        "group",
        "for",
        "automotive",
        "an",
        "program",
        "warehouse",
        "distribution"
    ],
    "wof:name":"I A P A",
    "wof:placetype":"venue"
},
  "geometry": {"coordinates":[-84.759207,34.207973],"type":"Point"}
}