{
  "type": "Feature",
  "properties": {
    "iso:country":"US",
    "sg:address":"39 Pine Grove Rd",
    "sg:city":"Locust Grove",
    "sg:classifiers":[
        {
            "category":"Building & Trades",
            "subcategory":"Construction",
            "type":"Services"
        }
    ],
    "sg:phone":"+1 770 898 8445",
    "sg:postcode":"30248",
    "sg:province":"GA",
    "sg:tags":[
        "institutional",
        "general",
        "commercial",
        "contractor"
    ],
    "wof:name":"Task Force Construction Inc",
    "wof:placetype":"venue"
},
  "geometry": {"coordinates":[-84.124985,33.373663],"type":"Point"}
}