{
  "type": "Feature",
  "properties": {
    "addr:full":"228 Porter St Alto GA 30510",
    "addr:housenumber":"228",
    "addr:postcode":"30510",
    "addr:street":"Porter St",
    "iso:country":"US",
    "sg:address":"228 Porter St",
    "sg:city":"Alto",
    "sg:classifiers":[
        {
            "category":"Autos & Motor Vehicles",
            "subcategory":"Automobile Sales",
            "type":"Retail Goods"
        },
        {
            "category":"Retail",
            "subcategory":"Auto Repair",
            "type":"Services"
        }
    ],
    "sg:phone":"+1 706 778 3048",
    "sg:postcode":"30510",
    "sg:province":"GA",
    "sg:tags":[
        "used",
        "truck",
        "general"
    ],
    "wof:name":"Rick's Truck & Tire Repair",
    "wof:placetype":"venue"
},
  "geometry": {"coordinates":[-83.573731,34.464934],"type":"Point"}
}