{
  "type": "Feature",
  "properties": {
    "addr:full":"12182 Hwy 92 Woodstock GA 30188",
    "addr:housenumber":"12182",
    "addr:postcode":"30188",
    "addr:street":"Hwy 92",
    "iso:country":"US",
    "sg:address":"12182 Hwy 92",
    "sg:city":"Woodstock",
    "sg:classifiers":[
        {
            "category":"Shopping",
            "subcategory":"Department Store",
            "type":"Retail Goods"
        },
        {
            "category":"Shopping",
            "subcategory":"Mobile Phones",
            "type":"Retail Goods"
        },
        {
            "category":"Food & Beverages",
            "subcategory":"Groceries & Convenience Stores",
            "type":"Retail Goods"
        }
    ],
    "sg:phone":"+1 770 516 4719",
    "sg:postcode":"30188",
    "sg:province":"GA",
    "sg:website":"www.walmart.com",
    "wof:name":"Walmart",
    "wof:placetype":"venue"
},
  "geometry": {"coordinates":[-84.481234,34.084529],"type":"Point"}
}