{
  "type": "Feature",
  "properties": {
    "iso:country":"US",
    "sg:address":"1279 Windburn Dr",
    "sg:city":"Marietta",
    "sg:classifiers":[
        {
            "category":"Shopping",
            "subcategory":"Jewelry",
            "type":"Retail Goods"
        }
    ],
    "sg:phone":"+1 770 971 8134",
    "sg:postcode":"30066",
    "sg:province":"GA",
    "sg:tags":[
        "jeweler"
    ],
    "wof:name":"Metropolitan Jewelry Appraisal Svc",
    "wof:placetype":"venue"
},
  "geometry": {"coordinates":[-84.51329800000001,34.0326],"type":"Point"}
}