{
  "type": "Feature",
  "properties": {
    "iso:country":"US",
    "sg:address":"7246 Wheeler Ct",
    "sg:city":"Lithonia",
    "sg:classifiers":[
        {
            "category":"Building & Trades",
            "subcategory":"Electrical",
            "type":"Services"
        }
    ],
    "sg:phone":"+1 770 484 6402",
    "sg:postcode":"30058",
    "sg:province":"GA",
    "sg:tags":[
        "electrical",
        "contractor"
    ],
    "wof:name":"McCall Enterprises  Inc",
    "wof:placetype":"venue"
},
  "geometry": {"coordinates":[-84.093215,33.762918],"type":"Point"}
}