{
  "type": "Feature",
  "properties": {
    "iso:country":"US",
    "sg:address":"56 Overlook Rd",
    "sg:city":"Ellijay",
    "sg:classifiers":[
        {
            "category":"Utilities",
            "subcategory":"Refuse",
            "type":"Services"
        },
        {
            "category":"Utilities",
            "subcategory":"Recycling",
            "type":"Services"
        }
    ],
    "sg:phone":"+1 706 698 7964",
    "sg:postcode":"30540",
    "sg:province":"GA",
    "sg:tags":[
        "container",
        "garbage",
        "rubbish",
        "removal"
    ],
    "wof:name":"Backdoor Sanitation",
    "wof:placetype":"venue"
},
  "geometry": {"coordinates":[-84.567757,34.748288],"type":"Point"}
}