{
  "type": "Feature",
  "properties": {
    "iso:country":"US",
    "sg:address":"6540 Grindle Rd",
    "sg:city":"Gainesville",
    "sg:classifiers":[
        {
            "category":"Building & Trades",
            "subcategory":"Construction",
            "type":"Services"
        }
    ],
    "sg:phone":"+1 770 844 4422",
    "sg:postcode":"30506",
    "sg:province":"GA",
    "sg:tags":[
        "drywall"
    ],
    "wof:name":"Central Drywall Inc",
    "wof:placetype":"venue"
},
  "geometry": {"coordinates":[-84.016471,34.291069],"type":"Point"}
}