{
  "type": "Feature",
  "properties": {
    "iso:country":"US",
    "sg:address":"3893 Chamblee Dunwoody Rd",
    "sg:city":"Atlanta",
    "sg:classifiers":[
        {
            "category":"Professional",
            "type":"Services"
        }
    ],
    "sg:phone":"+1 770 458 8520",
    "sg:postcode":"30341",
    "sg:province":"GA",
    "wof:name":"First Love Inc",
    "wof:placetype":"venue"
},
  "geometry": {"coordinates":[-84.309484,33.903082],"type":"Point"}
}