{
  "type": "Feature",
  "properties": {
    "iso:country":"US",
    "sg:address":"384 Dogwood Rd",
    "sg:city":"Ellijay",
    "sg:classifiers":[
        {
            "category":"Farming",
            "subcategory":"Poultry Farm",
            "type":"Manufacturing & Wholesale Goods"
        }
    ],
    "sg:phone":"+1 706 276 7932",
    "sg:postcode":"30536",
    "sg:province":"GA",
    "sg:tags":[
        "chicken"
    ],
    "wof:name":"Dd Poultry",
    "wof:placetype":"venue"
},
  "geometry": {"coordinates":[-84.47108799999999,34.614695],"type":"Point"}
}