{
  "type": "Feature",
  "properties": {
    "iso:country":"US",
    "sg:address":"203 Main St",
    "sg:city":"Thomson",
    "sg:classifiers":[
        {
            "category":"Shopping",
            "subcategory":"Clothing, Apparel, & Fashions",
            "type":"Retail Goods"
        }
    ],
    "sg:phone":"+1 706 595 9779",
    "sg:postcode":"30824",
    "sg:province":"GA",
    "sg:tags":[
        "patent"
    ],
    "wof:name":"Pickles & Ice Cream Catalog Co",
    "wof:placetype":"venue"
},
  "geometry": {"coordinates":[-82.503389,33.467813],"type":"Point"}
}