{
  "type": "Feature",
  "properties": {
    "addr:full":"1529 Piedmont Ave Suite D Atlanta GA 30324",
    "addr:housenumber":"1529",
    "addr:postcode":"30324",
    "addr:street":"Piedmont Ave Suite D",
    "iso:country":"US",
    "sg:address":"1529 Piedmont Ave Suite D",
    "sg:city":"Atlanta",
    "sg:classifiers":[
        {
            "category":"Restaurant",
            "type":"Food & Drink"
        }
    ],
    "sg:phone":"+1 404 874 7373",
    "sg:postcode":"30324",
    "sg:province":"GA",
    "sg:tags":[
        "vegetarian",
        "chinese"
    ],
    "sg:website":"www.greensproutga.com",
    "wof:name":"Green Sprout",
    "wof:placetype":"venue"
},
  "geometry": {"coordinates":[-84.369536,33.796522],"type":"Point"}
}