{
  "type": "Feature",
  "properties": {
    "addr:full":"3820 Leisure Ln Atlanta GA 30349",
    "addr:housenumber":"3820",
    "addr:postcode":"30349",
    "addr:street":"Leisure Ln",
    "iso:country":"US",
    "sg:address":"3820 Leisure Ln",
    "sg:city":"Atlanta",
    "sg:classifiers":[
        {
            "category":"Professional",
            "subcategory":"Business Services",
            "type":"Services"
        }
    ],
    "sg:phone":"+1 678 642 0041",
    "sg:postcode":"30349",
    "sg:province":"GA",
    "wof:name":"Marketing Plus Network Systems",
    "wof:placetype":"venue"
},
  "geometry": {"coordinates":[-84.501947,33.571383],"type":"Point"}
}