{
  "type": "Feature",
  "properties": {
    "addr:full":"2064 Cherrybrook Dr Decatur GA 30032",
    "addr:housenumber":"2064",
    "addr:postcode":"30032",
    "addr:street":"Cherrybrook Dr",
    "iso:country":"US",
    "sg:address":"2064 Cherrybrook Dr",
    "sg:city":"Decatur",
    "sg:classifiers":[
        {
            "category":"Professional",
            "subcategory":"Computer Services",
            "type":"Services"
        }
    ],
    "sg:phone":"+1 404 284 6095",
    "sg:postcode":"30032",
    "sg:province":"GA",
    "sg:tags":[
        "repair",
        "processing",
        "datum",
        "maintenance"
    ],
    "wof:name":"Terminaltech Inc",
    "wof:placetype":"venue"
},
  "geometry": {"coordinates":[-84.23667,33.73028],"type":"Point"}
}