{
  "type": "Feature",
  "properties": {
    "iso:country":"US",
    "sg:address":"3855 Shallowford Rd",
    "sg:city":"Marietta",
    "sg:classifiers":[
        {
            "category":"Home & Garden",
            "subcategory":"Garden Supply",
            "type":"Retail Goods"
        }
    ],
    "sg:phone":"+1 770 993 5790",
    "sg:postcode":"30062",
    "sg:province":"GA",
    "sg:tags":[
        "landscaping",
        "equipment"
    ],
    "wof:name":"Straw Country",
    "wof:placetype":"venue"
},
  "geometry": {"coordinates":[-84.43923700000001,34.032619],"type":"Point"}
}