{
  "type": "Feature",
  "properties": {
    "iso:country":"US",
    "sg:address":"1010 Huntcliff NE",
    "sg:city":"Atlanta",
    "sg:classifiers":[
        {
            "category":"Retail",
            "subcategory":"Auto Repair",
            "type":"Services"
        }
    ],
    "sg:phone":"+1 770 587 1500",
    "sg:postcode":"30350",
    "sg:province":"GA",
    "sg:tags":[
        "automotive",
        "consultant"
    ],
    "sg:website":"www.mpg20.com",
    "wof:name":"Management Performance Groups",
    "wof:placetype":"venue"
},
  "geometry": {"coordinates":[-84.355925,33.99312],"type":"Point"}
}