{
  "type": "Feature",
  "properties": {
    "addr:full":"107 Applewood St Cairo GA 39828",
    "addr:housenumber":"107",
    "addr:postcode":"39828",
    "addr:street":"Applewood St",
    "iso:country":"US",
    "sg:address":"107 Applewood St",
    "sg:city":"Cairo",
    "sg:classifiers":[
        {
            "category":"Restaurant",
            "type":"Food & Drink"
        }
    ],
    "sg:phone":"+1 229 377 7857",
    "sg:postcode":"39828",
    "sg:province":"GA",
    "sg:tags":[
        "eating"
    ],
    "wof:name":"Blimpie",
    "wof:placetype":"venue"
},
  "geometry": {"coordinates":[-84.149119,30.867857],"type":"Point"}
}