{
  "type": "Feature",
  "properties": {
    "iso:country":"US",
    "sg:address":"1919 Tubman Home Rd",
    "sg:city":"Augusta",
    "sg:classifiers":[
        {
            "category":"Building & Trades",
            "subcategory":"Plumbing",
            "type":"Services"
        }
    ],
    "sg:phone":"+1 706 733 9772",
    "sg:postcode":"30906",
    "sg:province":"GA",
    "sg:tags":[
        "plumbing",
        "contractor"
    ],
    "wof:name":"Scotty's Plumbing & Electric",
    "wof:placetype":"venue"
},
  "geometry": {"coordinates":[-82.010741,33.44308],"type":"Point"}
}