{
  "type": "Feature",
  "properties": {
    "addr:full":"801 S Elbert St Milledgeville GA 31061",
    "addr:housenumber":"801",
    "addr:postcode":"31061",
    "addr:street":"S Elbert St",
    "iso:country":"US",
    "sg:address":"801 S Elbert St",
    "sg:city":"Milledgeville",
    "sg:classifiers":[
        {
            "category":"Retail",
            "subcategory":"Auto Repair",
            "type":"Services"
        }
    ],
    "sg:phone":"+1 478 452 5286",
    "sg:postcode":"31061",
    "sg:province":"GA",
    "sg:tags":[
        "repairing",
        "automobile",
        "general"
    ],
    "wof:name":"Dean's Garage",
    "wof:placetype":"venue"
},
  "geometry": {"coordinates":[-83.220395,33.070139],"type":"Point"}
}