{
  "type": "Feature",
  "properties": {
    "addr:full":"2060 Fisher Trl NE Atlanta GA 30345",
    "addr:housenumber":"2060",
    "addr:postcode":"30345",
    "addr:street":"Fisher Trl Ne",
    "iso:country":"US",
    "sg:address":"2060 Fisher Trl NE",
    "sg:city":"Atlanta",
    "sg:classifiers":[
        {
            "category":"Real Estate",
            "subcategory":"Real Estate Agent",
            "type":"Services"
        }
    ],
    "sg:phone":"+1 404 315 6444",
    "sg:postcode":"30345",
    "sg:province":"GA",
    "wof:name":"Stephen B Bevill",
    "wof:placetype":"venue"
},
  "geometry": {"coordinates":[-84.30561,33.842867],"type":"Point"}
}