{
  "type": "Feature",
  "properties": {
    "iso:country":"US",
    "sg:address":"3466 Cobb Pkwy NW",
    "sg:city":"Acworth",
    "sg:classifiers":[
        {
            "category":"Restaurant",
            "type":"Food & Drink"
        }
    ],
    "sg:phone":"+1 770 917 8436",
    "sg:postcode":"30101",
    "sg:province":"GA",
    "sg:tags":[
        "barbeque"
    ],
    "sg:website":"www.bar-b-cutie.com",
    "wof:name":"Bar-B-Cutie",
    "wof:placetype":"venue"
},
  "geometry": {"coordinates":[-84.689988,34.038299],"type":"Point"}
}