{
  "type": "Feature",
  "properties": {
    "addr:full":"1435 Thompson Bridge Rd Gainesville GA 30501",
    "addr:housenumber":"1435",
    "addr:postcode":"30501",
    "addr:street":"Thompson Bridge Rd",
    "iso:country":"US",
    "sg:address":"1435 Thompson Bridge Rd",
    "sg:city":"Gainesville",
    "sg:classifiers":[
        {
            "category":"Retail",
            "subcategory":"Laundry & Dry Cleaning",
            "type":"Services"
        }
    ],
    "sg:phone":"+1 770 535 2539",
    "sg:postcode":"30501",
    "sg:province":"GA",
    "wof:name":"Euroclean Cleaners",
    "wof:placetype":"venue"
},
  "geometry": {"coordinates":[-83.832932,34.321169],"type":"Point"}
}