{
  "type": "Feature",
  "properties": {
    "addr:full":"1009 US Hwy 80 Savannah GA 31408",
    "addr:housenumber":"1009",
    "addr:postcode":"31408",
    "addr:street":"Us Hwy 80",
    "iso:country":"US",
    "sg:address":"1009 US Hwy 80",
    "sg:city":"Savannah",
    "sg:classifiers":[
        {
            "category":"Restaurant",
            "type":"Food & Drink"
        }
    ],
    "sg:phone":"+1 912 748 8347",
    "sg:postcode":"31408",
    "sg:province":"GA",
    "wof:name":"Huddle House",
    "wof:placetype":"venue"
},
  "geometry": {"coordinates":[-81.15755900000001,32.088019],"type":"Point"}
}