{
  "type": "Feature",
  "properties": {
    "iso:country":"US",
    "sg:address":"1002 Big A Rd S",
    "sg:city":"Toccoa",
    "sg:classifiers":[
        {
            "category":"Shopping",
            "subcategory":"Clothing, Apparel, & Fashions",
            "type":"Retail Goods"
        }
    ],
    "sg:phone":"+1 706 886 8127",
    "sg:postcode":"30577",
    "sg:province":"GA",
    "wof:name":"Scott Jewelers",
    "wof:placetype":"venue"
},
  "geometry": {"coordinates":[-83.30238300000001,34.567469],"type":"Point"}
}