{
  "type": "Feature",
  "properties": {
    "iso:country":"US",
    "sg:address":"2126 W Point Ave",
    "sg:city":"Atlanta",
    "sg:classifiers":[
        {
            "category":"Bus Station",
            "type":"Transportation"
        }
    ],
    "sg:phone":"+1 404 848 3180",
    "sg:postcode":"30337",
    "sg:province":"GA",
    "sg:tags":[
        "facility"
    ],
    "wof:name":"Metro Atlanta Trnsp Auth",
    "wof:placetype":"venue"
},
  "geometry": {"coordinates":[-84.458682,33.638751],"type":"Point"}
}