{
  "type": "Feature",
  "properties": {
    "addr:full":"900 Legacy Park Dr Lawrenceville GA 30043",
    "addr:housenumber":"900",
    "addr:postcode":"30043",
    "addr:street":"Legacy Park Dr",
    "iso:country":"US",
    "sg:address":"900 Legacy Park Dr",
    "sg:city":"Lawrenceville",
    "sg:classifiers":[
        {
            "category":"Insurance",
            "subcategory":"Hazard Insurance",
            "type":"Services"
        },
        {
            "category":"Insurance",
            "subcategory":"Health Insurance",
            "type":"Services"
        }
    ],
    "sg:phone":"+1 404 314 0507",
    "sg:postcode":"30043",
    "sg:province":"GA",
    "wof:name":"Health Markets",
    "wof:placetype":"venue"
},
  "geometry": {"coordinates":[-84.02547199999999,33.965187],"type":"Point"}
}