{
  "type": "Feature",
  "properties": {
    "iso:country":"US",
    "sg:address":"612 Vernon Ferry Rd",
    "sg:city":"La Grange",
    "sg:classifiers":[
        {
            "category":"Organizations",
            "subcategory":"Religious Organization",
            "type":"Services"
        }
    ],
    "sg:phone":"+1 706 845 1671",
    "sg:postcode":"30240",
    "sg:province":"GA",
    "wof:name":"Roger Yearwood",
    "wof:placetype":"venue"
},
  "geometry": {"coordinates":[-85.126746,33.039979],"type":"Point"}
}