{
  "type": "Feature",
  "properties": {
    "addr:full":"2900 Chamblee Tucker Rd Atlanta GA 30341",
    "addr:housenumber":"2900",
    "addr:postcode":"30341",
    "addr:street":"Chamblee Tucker Rd",
    "iso:country":"US",
    "sg:address":"2900 Chamblee Tucker Rd",
    "sg:city":"Atlanta",
    "sg:classifiers":[
        {
            "category":"Professional",
            "subcategory":"Accounting & Tax Preparation",
            "type":"Services"
        }
    ],
    "sg:phone":"+1 770 451 0870",
    "sg:postcode":"30341",
    "sg:province":"GA",
    "sg:tags":[
        "accountant"
    ],
    "wof:name":"Linda Nay CPA",
    "wof:placetype":"venue"
},
  "geometry": {"coordinates":[-84.26906700000001,33.877884],"type":"Point"}
}