{
  "type": "Feature",
  "properties": {
    "iso:country":"US",
    "sg:address":"1975 Hillspring Ln",
    "sg:city":"Lithonia",
    "sg:classifiers":[
        {
            "category":"Health Services",
            "subcategory":"Doctor",
            "type":"Services"
        }
    ],
    "sg:phone":"+1 770 482 7202",
    "sg:postcode":"30058",
    "sg:province":"GA",
    "sg:tags":[
        "physician",
        "surgeon"
    ],
    "wof:name":"Mahboob Enterprise Inc",
    "wof:placetype":"venue"
},
  "geometry": {"coordinates":[-84.08236100000001,33.732001],"type":"Point"}
}