{
  "type": "Feature",
  "properties": {
    "iso:country":"US",
    "sg:address":"1200 Foster St NW",
    "sg:city":"Atlanta",
    "sg:classifiers":[
        {
            "category":"Manufacturing",
            "subcategory":"Metals",
            "type":"Manufacturing & Wholesale Goods"
        }
    ],
    "sg:phone":"+1 404 351 6686",
    "sg:postcode":"30318",
    "sg:province":"GA",
    "sg:tags":[
        "fabricator",
        "sheet"
    ],
    "wof:name":"Southeastern Metal Products",
    "wof:placetype":"venue"
},
  "geometry": {"coordinates":[-84.414995,33.785589],"type":"Point"}
}