{
  "type": "Feature",
  "properties": {
    "iso:country":"US",
    "sg:address":"165 Wesley Pl",
    "sg:city":"Fayetteville",
    "sg:classifiers":[
        {
            "category":"Home & Garden",
            "subcategory":"Carpets & Floor Coverings",
            "type":"Retail Goods"
        }
    ],
    "sg:phone":"+1 770 719 5243",
    "sg:postcode":"30214",
    "sg:province":"GA",
    "sg:tags":[
        "material"
    ],
    "wof:name":"Thanh & Son",
    "wof:placetype":"venue"
},
  "geometry": {"coordinates":[-84.482049,33.464854],"type":"Point"}
}