{
  "type": "Feature",
  "properties": {
    "iso:country":"US",
    "sg:address":"1593 N Expy",
    "sg:city":"Griffin",
    "sg:classifiers":[
        {
            "category":"Shopping",
            "subcategory":"Clothing, Apparel, & Fashions",
            "type":"Retail Goods"
        }
    ],
    "sg:phone":"+1 770 227 9094",
    "sg:postcode":"30223",
    "sg:province":"GA",
    "wof:name":"Hiks Fashions Of New York",
    "wof:placetype":"venue"
},
  "geometry": {"coordinates":[-84.28813700000001,33.255618],"type":"Point"}
}