{
  "type": "Feature",
  "properties": {
    "iso:country":"US",
    "sg:address":"2792 US Hwy 80",
    "sg:city":"Savannah",
    "sg:classifiers":[
        {
            "category":"Freight",
            "type":"Transportation"
        }
    ],
    "sg:phone":"+1 912 964 7166",
    "sg:postcode":"31408",
    "sg:province":"GA",
    "sg:tags":[
        "operator",
        "local",
        "trucking"
    ],
    "wof:name":"Perkins Trucking",
    "wof:placetype":"venue"
},
  "geometry": {"coordinates":[-81.192695,32.091728],"type":"Point"}
}