{
  "type": "Feature",
  "properties": {
    "addr:full":"2222 Bull St Ste 204 Savannah GA 31401",
    "addr:housenumber":"2222",
    "addr:postcode":"31401",
    "addr:street":"Bull St Ste 204",
    "iso:country":"US",
    "sg:address":"2222 Bull St Ste 204",
    "sg:city":"Savannah",
    "sg:classifiers":[
        {
            "category":"Organizations",
            "subcategory":"Labor Organization",
            "type":"Services"
        }
    ],
    "sg:phone":"+1 912 233 2707",
    "sg:postcode":"31401",
    "sg:province":"GA",
    "sg:website":"http://www.nalc.org",
    "wof:name":"National Association of Letter Carriers",
    "wof:placetype":"venue"
},
  "geometry": {"coordinates":[-81.100703,32.056038],"type":"Point"}
}