{
  "type": "Feature",
  "properties": {
    "addr:full":"5250 Blue Yarrow Run Norcross GA 30092",
    "addr:housenumber":"5250",
    "addr:postcode":"30092",
    "addr:street":"Blue Yarrow Run",
    "iso:country":"US",
    "sg:address":"5250 Blue Yarrow Run",
    "sg:city":"Norcross",
    "sg:classifiers":[
        {
            "category":"Communications",
            "type":"Services"
        }
    ],
    "sg:phone":"+1 770 582 9204",
    "sg:postcode":"30092",
    "sg:province":"GA",
    "wof:name":"Transcentury Communication",
    "wof:placetype":"venue"
},
  "geometry": {"coordinates":[-84.22042,33.981196],"type":"Point"}
}