{
  "type": "Feature",
  "properties": {
    "iso:country":"US",
    "sg:address":"10262 Main St",
    "sg:city":"Woodstock",
    "sg:classifiers":[
        {
            "category":"Autos & Motor Vehicles",
            "subcategory":"Motorcycle Sales",
            "type":"Retail Goods"
        }
    ],
    "sg:phone":"+1 770 517 4540",
    "sg:postcode":"30188",
    "sg:province":"GA",
    "wof:name":"Moto Britalia",
    "wof:placetype":"venue"
},
  "geometry": {"coordinates":[-84.52195500000001,34.077012],"type":"Point"}
}