{
  "type": "Feature",
  "properties": {
    "addr:full":"320 Bill Morris Rd Baxley GA 31513",
    "addr:housenumber":"320",
    "addr:postcode":"31513",
    "addr:street":"Bill Morris Rd",
    "iso:country":"US",
    "sg:address":"320 Bill Morris Rd",
    "sg:city":"Baxley",
    "sg:classifiers":[
        {
            "category":"Professional",
            "type":"Services"
        }
    ],
    "sg:phone":"+1 912 367 4242",
    "sg:postcode":"31513",
    "sg:province":"GA",
    "wof:name":"Alvin H Crosby",
    "wof:placetype":"venue"
},
  "geometry": {"coordinates":[-82.336144,31.689867],"type":"Point"}
}