{
  "type": "Feature",
  "properties": {
    "iso:country":"US",
    "sg:address":"5035 N Henry Blvd",
    "sg:city":"Stockbridge",
    "sg:classifiers":[
        {
            "category":"Professional",
            "type":"Services"
        }
    ],
    "sg:phone":"+1 678 289 1112",
    "sg:postcode":"30281",
    "sg:province":"GA",
    "wof:name":"Grand Lake Scooters",
    "wof:placetype":"venue"
},
  "geometry": {"coordinates":[-84.24450299999999,33.544827],"type":"Point"}
}