{
  "type": "Feature",
  "properties": {
    "iso:country":"US",
    "sg:address":"2100 Malcom Bridge Rd",
    "sg:city":"Bogart",
    "sg:classifiers":[
        {
            "category":"Building & Trades",
            "subcategory":"Construction",
            "type":"Services"
        }
    ],
    "sg:phone":"+1 770 725 7334",
    "sg:postcode":"30622",
    "sg:province":"GA",
    "sg:tags":[
        "steel",
        "contractor",
        "erection",
        "structural"
    ],
    "wof:name":"Farmers Prtble Wldg Stl Erecti",
    "wof:placetype":"venue"
},
  "geometry": {"coordinates":[-83.50406700000001,33.901161],"type":"Point"}
}