{
  "type": "Feature",
  "properties": {
    "iso:country":"US",
    "sg:address":"2256 Northwest Pkwy SE",
    "sg:city":"Marietta",
    "sg:classifiers":[
        {
            "category":"Wholesale",
            "subcategory":"Electrical",
            "type":"Manufacturing & Wholesale Goods"
        }
    ],
    "sg:phone":"+1 770 951 0921",
    "sg:postcode":"30067",
    "sg:province":"GA",
    "sg:tags":[
        "switches-electric"
    ],
    "sg:website":"http://www.amsol-us.com",
    "wof:name":"American Solenoid Co",
    "wof:placetype":"venue"
},
  "geometry": {"coordinates":[-84.487942,33.918227],"type":"Point"}
}