{
  "type": "Feature",
  "properties": {
    "iso:country":"US",
    "sg:address":"835 McMillan St NW",
    "sg:city":"Atlanta",
    "sg:classifiers":[
        {
            "category":"Education",
            "subcategory":"College",
            "type":"Public Place"
        }
    ],
    "sg:phone":"+1 404 894 6718",
    "sg:postcode":"30332",
    "sg:province":"GA",
    "wof:name":"Georgia Tech Tool Room",
    "wof:placetype":"venue"
},
  "geometry": {"coordinates":[-84.40416999999999,33.779655],"type":"Point"}
}