{
  "type": "Feature",
  "properties": {
    "addr:full":"318 E River St Savannah GA 31401",
    "addr:housenumber":"318",
    "addr:postcode":"31401",
    "addr:street":"E River St",
    "iso:country":"US",
    "sg:address":"318 E River St",
    "sg:city":"Savannah",
    "sg:classifiers":[
        {
            "category":"Parking",
            "type":"Transportation"
        }
    ],
    "sg:phone":"+1 912 232 0600",
    "sg:postcode":"31401",
    "sg:province":"GA",
    "sg:tags":[
        "garage"
    ],
    "wof:name":"Professional Parking Systems",
    "wof:placetype":"venue"
},
  "geometry": {"coordinates":[-81.086135,32.080523],"type":"Point"}
}