{
  "type": "Feature",
  "properties": {
    "addr:full":"5120 Thompson Bridge Rd Murrayville GA 30564",
    "addr:housenumber":"5120",
    "addr:postcode":"30564",
    "addr:street":"Thompson Bridge Rd",
    "iso:country":"US",
    "sg:address":"5120 Thompson Bridge Rd",
    "sg:city":"Murrayville",
    "sg:classifiers":[
        {
            "category":"Food & Beverages",
            "subcategory":"Groceries & Convenience Stores",
            "type":"Retail Goods"
        }
    ],
    "sg:phone":"+1 770 287 9911",
    "sg:postcode":"30564",
    "sg:province":"GA",
    "wof:name":"Petrofast Food Store",
    "wof:placetype":"venue"
},
  "geometry": {"coordinates":[-83.90007,34.412714],"type":"Point"}
}