{
  "type": "Feature",
  "properties": {
    "addr:full":"4040 Orchard Rd SE Atlanta GA 30303",
    "addr:housenumber":"4040",
    "addr:postcode":"30303",
    "addr:street":"Orchard Rd Se",
    "iso:country":"US",
    "sg:address":"4040 Orchard Rd SE",
    "sg:city":"Atlanta",
    "sg:classifiers":[
        {
            "category":"Real Estate",
            "subcategory":"Real Estate Services",
            "type":"Services"
        }
    ],
    "sg:phone":"+1 770 955 2000",
    "sg:postcode":"30303",
    "sg:province":"GA",
    "sg:tags":[
        "management",
        "property"
    ],
    "wof:name":"McWhirter Realty Corp",
    "wof:placetype":"venue"
},
  "geometry": {"coordinates":[-84.39070100000001,33.756302],"type":"Point"}
}