{
  "type": "Feature",
  "properties": {
    "addr:full":"764 Miami Cir NE Ste 136 Atlanta GA 30324",
    "addr:housenumber":"764",
    "addr:postcode":"30324",
    "addr:street":"Miami Cir Ne Ste 136",
    "iso:country":"US",
    "sg:address":"764 Miami Cir NE Ste 136",
    "sg:city":"Atlanta",
    "sg:classifiers":[
        {
            "category":"Shopping",
            "subcategory":"Antiques",
            "type":"Retail Goods"
        }
    ],
    "sg:phone":"+1 404 848 9553",
    "sg:postcode":"30324",
    "sg:province":"GA",
    "sg:website":"www.faygoldgallery.com",
    "wof:name":"Nicholson Gallery the",
    "wof:placetype":"venue"
},
  "geometry": {"coordinates":[-84.36337399999999,33.830289],"type":"Point"}
}