{
  "type": "Feature",
  "properties": {
    "iso:country":"US",
    "sg:address":"239 Wellington Cir",
    "sg:city":"Statesboro",
    "sg:classifiers":[
        {
            "category":"Retail",
            "subcategory":"Portrait Studio",
            "type":"Services"
        }
    ],
    "sg:phone":"+1 912 764 6553",
    "sg:postcode":"30458",
    "sg:province":"GA",
    "sg:tags":[
        "photo"
    ],
    "wof:name":"Fortune Frank Phtgrphy Grphics",
    "wof:placetype":"venue"
},
  "geometry": {"coordinates":[-81.83526000000001,32.413142],"type":"Point"}
}