{
  "type": "Feature",
  "properties": {
    "addr:full":"2140 Peachtree Rd NW Atlanta GA 30309",
    "addr:housenumber":"2140",
    "addr:postcode":"30309",
    "addr:street":"Peachtree Rd Nw",
    "iso:country":"US",
    "sg:address":"2140 Peachtree Rd NW",
    "sg:city":"Atlanta",
    "sg:classifiers":[
        {
            "category":"Restaurant",
            "type":"Food & Drink"
        }
    ],
    "sg:phone":"+1 404 352 8859",
    "sg:postcode":"30309",
    "sg:province":"GA",
    "sg:tags":[
        "vegetarian"
    ],
    "sg:website":"www.cafesunflower.com",
    "wof:name":"Cafe Sunflower Buckhead",
    "wof:placetype":"venue"
},
  "geometry": {"coordinates":[-84.392403,33.8125],"type":"Point"}
}