{
  "type": "Feature",
  "properties": {
    "addr:full":"1009 Maria Dr Mc Donough GA 30253",
    "addr:housenumber":"1009",
    "addr:postcode":"30253",
    "addr:street":"Maria Dr",
    "iso:country":"US",
    "sg:address":"1009 Maria Dr",
    "sg:city":"Mc Donough",
    "sg:classifiers":[
        {
            "category":"Building & Trades",
            "subcategory":"Pest Control",
            "type":"Services"
        }
    ],
    "sg:phone":"+1 678 432 7717",
    "sg:postcode":"30253",
    "sg:province":"GA",
    "wof:name":"Bugsy Pest Control Inc",
    "wof:placetype":"venue"
},
  "geometry": {"coordinates":[-84.210669,33.403203],"type":"Point"}
}