{
  "type": "Feature",
  "properties": {
    "addr:full":"2202 Lakeshore Dr Valdosta GA 31602",
    "addr:housenumber":"2202",
    "addr:postcode":"31602",
    "addr:street":"Lakeshore Dr",
    "iso:country":"US",
    "sg:address":"2202 Lakeshore Dr",
    "sg:city":"Valdosta",
    "sg:classifiers":[
        {
            "category":"Building & Trades",
            "subcategory":"Construction",
            "type":"Services"
        }
    ],
    "sg:phone":"+1 229 241 0370",
    "sg:postcode":"31602",
    "sg:province":"GA",
    "sg:tags":[
        "house"
    ],
    "wof:name":"Tlg Inc",
    "wof:placetype":"venue"
},
  "geometry": {"coordinates":[-83.32817300000001,30.852703],"type":"Point"}
}