{
  "type": "Feature",
  "properties": {
    "addr:full":"112 Main St SW Gainesville GA 30501",
    "addr:housenumber":"112",
    "addr:postcode":"30501",
    "addr:street":"Main St Sw",
    "iso:country":"US",
    "sg:address":"112 Main St SW",
    "sg:city":"Gainesville",
    "sg:classifiers":[
        {
            "category":"Shopping",
            "subcategory":"Bicycles & Sporting Goods",
            "type":"Retail Goods"
        }
    ],
    "sg:phone":"+1 770 287 9245",
    "sg:postcode":"30501",
    "sg:province":"GA",
    "sg:website":"www.horseandhound.org",
    "wof:name":"Horse & Hound Tack Shop",
    "wof:placetype":"venue"
},
  "geometry": {"coordinates":[-83.827513,34.299347],"type":"Point"}
}