{
  "type": "Feature",
  "properties": {
    "addr:full":"3424 Peachtree Rd Atlanta GA 30326",
    "addr:housenumber":"3424",
    "addr:postcode":"30326",
    "addr:street":"Peachtree Rd",
    "iso:country":"US",
    "sg:address":"3424 Peachtree Rd",
    "sg:city":"Atlanta",
    "sg:classifiers":[
        {
            "category":"Travel",
            "subcategory":"Hotels & Motels",
            "type":"Entertainment"
        }
    ],
    "sg:phone":"+1 404 262 9660",
    "sg:postcode":"30326",
    "sg:province":"GA",
    "sg:tags":[
        "operation",
        "management"
    ],
    "wof:name":"Hampton Inn",
    "wof:placetype":"venue"
},
  "geometry": {"coordinates":[-84.366387,33.848682],"type":"Point"}
}