{
  "type": "Feature",
  "properties": {
    "addr:full":"191 11th St NE Atlanta GA 30309",
    "addr:housenumber":"191",
    "addr:postcode":"30309",
    "addr:street":"11Th St Ne",
    "iso:country":"US",
    "sg:address":"191 11th St NE",
    "sg:city":"Atlanta",
    "sg:classifiers":[
        {
            "category":"Social Services",
            "subcategory":"Child Care",
            "type":"Services"
        }
    ],
    "sg:phone":"+1 404 840 6444",
    "sg:postcode":"30309",
    "sg:province":"GA",
    "sg:tags":[
        "nursery",
        "day"
    ],
    "wof:name":"Jump Start Events",
    "wof:placetype":"venue"
},
  "geometry": {"coordinates":[-84.38009599999999,33.783058],"type":"Point"}
}