{
  "type": "Feature",
  "properties": {
    "iso:country":"US",
    "sg:address":"100 N Valhalla Ln",
    "sg:city":"Cordele",
    "sg:classifiers":[
        {
            "category":"Professional",
            "type":"Services"
        }
    ],
    "sg:phone":"+1 229 273 6998",
    "sg:postcode":"31015",
    "sg:province":"GA",
    "wof:name":"Charles Hurt",
    "wof:placetype":"venue"
},
  "geometry": {"coordinates":[-83.92753500000001,31.974635],"type":"Point"}
}