{
  "type": "Feature",
  "properties": {
    "addr:full":"113 Fontaine Dr Thomasville GA 31792",
    "addr:housenumber":"113",
    "addr:postcode":"31792",
    "addr:street":"Fontaine Dr",
    "iso:country":"US",
    "sg:address":"113 Fontaine Dr",
    "sg:city":"Thomasville",
    "sg:classifiers":[
        {
            "category":"Manufacturing",
            "subcategory":"Signs",
            "type":"Manufacturing & Wholesale Goods"
        }
    ],
    "sg:phone":"+1 229 228 1845",
    "sg:postcode":"31792",
    "sg:province":"GA",
    "wof:name":"Operation House Id",
    "wof:placetype":"venue"
},
  "geometry": {"coordinates":[-83.97455100000001,30.854243],"type":"Point"}
}