{
  "type": "Feature",
  "properties": {
    "addr:full":"988 Lanier Blvd NE Atlanta GA 30306",
    "addr:housenumber":"988",
    "addr:postcode":"30306",
    "addr:street":"Lanier Blvd Ne",
    "iso:country":"US",
    "sg:address":"988 Lanier Blvd NE",
    "sg:city":"Atlanta",
    "sg:classifiers":[
        {
            "category":"Wholesale",
            "subcategory":"Machinery & Supplies",
            "type":"Manufacturing & Wholesale Goods"
        }
    ],
    "sg:phone":"+1 404 872 5665",
    "sg:postcode":"30306",
    "sg:province":"GA",
    "sg:tags":[
        "equipment",
        "industrial"
    ],
    "wof:name":"Throckmorton",
    "wof:placetype":"venue"
},
  "geometry": {"coordinates":[-84.35285399999999,33.781242],"type":"Point"}
}