{
  "type": "Feature",
  "properties": {
    "iso:country":"US",
    "sg:address":"409 W Congress St",
    "sg:city":"Savannah",
    "sg:classifiers":[
        {
            "category":"Restaurant",
            "type":"Food & Drink"
        }
    ],
    "sg:menulink":"http://www.allmenus.com/ga/savannah/33919-murphys-law/menu/",
    "sg:phone":"+1 912 443 0855",
    "sg:postcode":"31401",
    "sg:province":"GA",
    "sg:tags":[
        "american",
        "pub"
    ],
    "wof:name":"Murphy's Law",
    "wof:placetype":"venue"
},
  "geometry": {"coordinates":[-81.08721799999999,32.078422],"type":"Point"}
}