{
  "type": "Feature",
  "properties": {
    "addr:full":"90 Glenda Dr Newnan GA 30241",
    "addr:housenumber":"90",
    "addr:postcode":"30241",
    "addr:street":"Glenda Dr",
    "iso:country":"US",
    "sg:address":"90 Glenda Dr",
    "sg:city":"Newnan",
    "sg:classifiers":[
        {
            "category":"Manufacturing",
            "subcategory":"Rubber & Plastics",
            "type":"Manufacturing & Wholesale Goods"
        },
        {
            "category":"Professional",
            "subcategory":"Advertising",
            "type":"Services"
        }
    ],
    "sg:phone":"+1 678 423 6161",
    "sg:postcode":"30241",
    "sg:province":"GA",
    "sg:tags":[
        "product",
        "foam",
        "mailing",
        "shipping",
        "mfg"
    ],
    "wof:name":"UPS Store",
    "wof:placetype":"venue"
},
  "geometry": {"coordinates":[-85.019392,33.070412],"type":"Point"}
}