{
  "type": "Feature",
  "properties": {
    "iso:country":"US",
    "sg:address":"2191 Northlake Pkwy",
    "sg:city":"Tucker",
    "sg:classifiers":[
        {
            "category":"Professional",
            "subcategory":"Lawyer & Legal Services",
            "type":"Services"
        }
    ],
    "sg:phone":"+1 770 270 3800",
    "sg:postcode":"30084",
    "sg:province":"GA",
    "sg:tags":[
        "attorney",
        "wills",
        "planning",
        "real estate",
        "trust"
    ],
    "sg:website":"http://www.ztspc.com",
    "wof:name":"Zion Tarleton & Siskin PC",
    "wof:placetype":"venue"
},
  "geometry": {"coordinates":[-84.244601,33.848273],"type":"Point"}
}