{
  "type": "Feature",
  "properties": {
    "addr:full":"200 Landing Ln Covington GA 30016",
    "addr:housenumber":"200",
    "addr:postcode":"30016",
    "addr:street":"Landing Ln",
    "iso:country":"US",
    "sg:address":"200 Landing Ln",
    "sg:city":"Covington",
    "sg:classifiers":[
        {
            "category":"Communications",
            "type":"Services"
        }
    ],
    "sg:phone":"+1 770 385 7030",
    "sg:postcode":"30016",
    "sg:province":"GA",
    "wof:name":"Print Media",
    "wof:placetype":"venue"
},
  "geometry": {"coordinates":[-83.94404400000001,33.607593],"type":"Point"}
}