{
  "type": "Feature",
  "properties": {
    "addr:full":"126 Carnation Ct Kingsland GA 31548",
    "addr:housenumber":"126",
    "addr:postcode":"31548",
    "addr:street":"Carnation Ct",
    "iso:country":"US",
    "sg:address":"126 Carnation Ct",
    "sg:city":"Kingsland",
    "sg:classifiers":[
        {
            "category":"Professional",
            "subcategory":"Lawyer & Legal Services",
            "type":"Services"
        }
    ],
    "sg:phone":"+1 912 882 7322",
    "sg:postcode":"31548",
    "sg:province":"GA",
    "wof:name":"Gary Bacon",
    "wof:placetype":"venue"
},
  "geometry": {"coordinates":[-81.652119,30.793332],"type":"Point"}
}