{
  "type": "Feature",
  "properties": {
    "addr:full":"370 Galesburg Dr Lawrenceville GA 30044",
    "addr:housenumber":"370",
    "addr:postcode":"30044",
    "addr:street":"Galesburg Dr",
    "iso:country":"US",
    "sg:address":"370 Galesburg Dr",
    "sg:city":"Lawrenceville",
    "sg:classifiers":[
        {
            "category":"Professional",
            "subcategory":"Management & Consulting",
            "type":"Services"
        }
    ],
    "sg:phone":"+1 678 522 7664",
    "sg:postcode":"30044",
    "sg:province":"GA",
    "wof:name":"Blue Ridge Consulting",
    "wof:placetype":"venue"
},
  "geometry": {"coordinates":[-84.081191,33.896371],"type":"Point"}
}