{
  "type": "Feature",
  "properties": {
    "addr:full":"340 S Broad St Ellaville GA 31806",
    "addr:housenumber":"340",
    "addr:postcode":"31806",
    "addr:street":"S Broad St",
    "iso:country":"US",
    "sg:address":"340 S Broad St",
    "sg:city":"Ellaville",
    "sg:classifiers":[
        {
            "category":"Organizations",
            "subcategory":"Religious Organization",
            "type":"Services"
        }
    ],
    "sg:phone":"+1 229 937 2100",
    "sg:postcode":"31806",
    "sg:province":"GA",
    "sg:tags":[
        "church"
    ],
    "wof:name":"Ellaville Baptist Church",
    "wof:placetype":"venue"
},
  "geometry": {"coordinates":[-84.308896,32.242206],"type":"Point"}
}