{
  "type": "Feature",
  "properties": {
    "iso:country":"US",
    "sg:address":"4205 N Point Pkwy Ste F",
    "sg:city":"Alpharetta",
    "sg:classifiers":[
        {
            "category":"Health Services",
            "subcategory":"Doctor",
            "type":"Services"
        }
    ],
    "sg:phone":"+1 770 664 5550",
    "sg:postcode":"30022",
    "sg:province":"GA",
    "sg:tags":[
        "surgeon",
        "oral"
    ],
    "sg:website":"www.jawimplant.com/",
    "wof:name":"Atlanta Oral & Maxillofacial Surgery",
    "wof:placetype":"venue"
},
  "geometry": {"coordinates":[-84.26486199999999,34.06379],"type":"Point"}
}