{
  "type": "Feature",
  "properties": {
    "addr:full":"7611 Berea Rd Winston GA 30187",
    "addr:housenumber":"7611",
    "addr:postcode":"30187",
    "addr:street":"Berea Rd",
    "iso:country":"US",
    "sg:address":"7611 Berea Rd",
    "sg:city":"Winston",
    "sg:classifiers":[
        {
            "category":"Building & Trades",
            "subcategory":"Construction",
            "type":"Services"
        }
    ],
    "sg:phone":"+1 678 687 9746",
    "sg:postcode":"30187",
    "sg:province":"GA",
    "sg:tags":[
        "house"
    ],
    "wof:name":"Final Touch",
    "wof:placetype":"venue"
},
  "geometry": {"coordinates":[-84.826235,33.680983],"type":"Point"}
}