{
  "type": "Feature",
  "properties": {
    "addr:full":"7750 Roswell Rd Apt 10-G Atlanta GA 30350",
    "addr:housenumber":"7750",
    "addr:postcode":"30350",
    "addr:street":"Roswell Rd Apt 10-G",
    "iso:country":"US",
    "sg:address":"7750 Roswell Rd Apt 10-G",
    "sg:city":"Atlanta",
    "sg:classifiers":[
        {
            "category":"Retail",
            "subcategory":"Repair Shop",
            "type":"Services"
        },
        {
            "category":"Wholesale",
            "subcategory":"Construction Materials",
            "type":"Manufacturing & Wholesale Goods"
        },
        {
            "category":"Shopping",
            "subcategory":"Antiques",
            "type":"Retail Goods"
        }
    ],
    "sg:phone":"+1 770 396 0473",
    "sg:postcode":"30350",
    "sg:province":"GA",
    "sg:tags":[
        "refinish",
        "furniture",
        "caning",
        "supply"
    ],
    "wof:name":"Michael Pressimone Furniture Frame Restoration",
    "wof:placetype":"venue"
},
  "geometry": {"coordinates":[-84.36260299999999,33.966669],"type":"Point"}
}