{
  "type": "Feature",
  "properties": {
    "iso:country":"US",
    "sg:address":"467 Inland Way NW",
    "sg:city":"Lilburn",
    "sg:classifiers":[
        {
            "category":"Building & Trades",
            "subcategory":"Landscaping Services",
            "type":"Services"
        }
    ],
    "sg:phone":"+1 770 564 2186",
    "sg:postcode":"30047",
    "sg:province":"GA",
    "sg:tags":[
        "landscape",
        "contractor"
    ],
    "wof:name":"Skb Industries Inc",
    "wof:placetype":"venue"
},
  "geometry": {"coordinates":[-84.159115,33.887795],"type":"Point"}
}