{
  "type": "Feature",
  "properties": {
    "addr:full":"1145 Rottenwood Dr Marietta GA 30067",
    "addr:housenumber":"1145",
    "addr:postcode":"30067",
    "addr:street":"Rottenwood Dr",
    "iso:country":"US",
    "sg:address":"1145 Rottenwood Dr",
    "sg:city":"Marietta",
    "sg:classifiers":[
        {
            "category":"Professional",
            "subcategory":"Computer Services",
            "type":"Services"
        }
    ],
    "sg:phone":"+1 678 318 1488",
    "sg:postcode":"30067",
    "sg:province":"GA",
    "sg:tags":[
        "manages",
        "it",
        "for"
    ],
    "wof:name":"Baseline",
    "wof:placetype":"venue"
},
  "geometry": {"coordinates":[-84.504085,33.923125],"type":"Point"}
}