{
  "type": "Feature",
  "properties": {
    "addr:full":"170 Thurman Dr Gray GA 31032",
    "addr:housenumber":"170",
    "addr:postcode":"31032",
    "addr:street":"Thurman Dr",
    "iso:country":"US",
    "sg:address":"170 Thurman Dr",
    "sg:city":"Gray",
    "sg:classifiers":[
        {
            "category":"Place Of Worship",
            "subcategory":"Church",
            "type":"Public Place"
        },
        {
            "category":"Place Of Worship",
            "type":"Public Place"
        }
    ],
    "sg:phone":"+1 478 986 9154",
    "sg:postcode":"31032",
    "sg:province":"GA",
    "sg:tags":[
        "churches-interdenominational",
        "churches-various",
        "denomination"
    ],
    "wof:name":"Calvary Deliverance Holiness Temple",
    "wof:placetype":"venue"
},
  "geometry": {"coordinates":[-83.553202,33.003134],"type":"Point"}
}