{
  "type": "Feature",
  "properties": {
    "iso:country":"US",
    "sg:address":"1455 English St NW",
    "sg:city":"Atlanta",
    "sg:classifiers":[
        {
            "category":"Building & Trades",
            "subcategory":"Construction",
            "type":"Services"
        }
    ],
    "sg:phone":"+1 404 355 8383",
    "sg:postcode":"30318",
    "sg:province":"GA",
    "sg:tags":[
        "fabricator",
        "metal"
    ],
    "wof:name":"Wilbanks/Mc Worth",
    "wof:placetype":"venue"
},
  "geometry": {"coordinates":[-84.419847,33.794488],"type":"Point"}
}