{
  "type": "Feature",
  "properties": {
    "addr:full":"157 W May St Winder GA 30680",
    "addr:housenumber":"157",
    "addr:postcode":"30680",
    "addr:street":"W May St",
    "iso:country":"US",
    "sg:address":"157 W May St",
    "sg:city":"Winder",
    "sg:classifiers":[
        {
            "category":"Autos & Motor Vehicles",
            "subcategory":"Automobile Sales",
            "type":"Retail Goods"
        },
        {
            "category":"Retail",
            "subcategory":"Auto Rental",
            "type":"Services"
        }
    ],
    "sg:phone":"+1 770 586 5001",
    "sg:postcode":"30680",
    "sg:province":"GA",
    "sg:tags":[
        "car",
        "leasing",
        "truck"
    ],
    "sg:website":"http://www.enterprise.com/car_rental/deeplinkmap.do?gpbr=03J1&bid=004&cnty=US&arc=YPTRL01&cm_mmc=Yellowpages.com-_-IYP-_-Tradelisting-_-branch",
    "wof:name":"Enterprise Rent-A-Car",
    "wof:placetype":"venue"
},
  "geometry": {"coordinates":[-83.732265,33.994342],"type":"Point"}
}