{
  "type": "Feature",
  "properties": {
    "iso:country":"US",
    "sg:address":"2650 Lawrenceville Suwanee Rd",
    "sg:city":"Suwanee",
    "sg:classifiers":[
        {
            "category":"Health Services",
            "subcategory":"Doctor",
            "type":"Services"
        }
    ],
    "sg:phone":"+1 770 277 4028",
    "sg:postcode":"30024",
    "sg:province":"GA",
    "sg:tags":[
        "medicine",
        "practice",
        "internal",
        "family"
    ],
    "sg:website":"www.gwinnettclinic.com",
    "wof:name":"Gwinnett Clinic",
    "wof:placetype":"venue"
},
  "geometry": {"coordinates":[-84.042036,34.020629],"type":"Point"}
}