{
  "type": "Feature",
  "properties": {
    "iso:country":"US",
    "sg:address":"2880 Holcomb Bridge Rd",
    "sg:city":"Alpharetta",
    "sg:classifiers":[
        {
            "category":"Shopping",
            "subcategory":"Computers & Home Electronics",
            "type":"Retail Goods"
        }
    ],
    "sg:phone":"+1 770 993 6359",
    "sg:postcode":"30022",
    "sg:province":"GA",
    "sg:tags":[
        "equipment",
        "dealer"
    ],
    "wof:name":"First Mobile Computers",
    "wof:placetype":"venue"
},
  "geometry": {"coordinates":[-84.275141,33.989631],"type":"Point"}
}