{
  "type": "Feature",
  "properties": {
    "addr:full":"4400 2nd Ave Columbus GA 31904",
    "addr:housenumber":"4400",
    "addr:postcode":"31904",
    "addr:street":"2Nd Ave",
    "iso:country":"US",
    "sg:address":"4400 2nd Ave",
    "sg:city":"Columbus",
    "sg:classifiers":[
        {
            "category":"Personal",
            "subcategory":"Beauty Salon",
            "type":"Services"
        }
    ],
    "sg:phone":"+1 706 324 7986",
    "sg:postcode":"31904",
    "sg:province":"GA",
    "sg:tags":[
        "shop"
    ],
    "wof:name":"Betty's Hair Fashions",
    "wof:placetype":"venue"
},
  "geometry": {"coordinates":[-84.98984799999999,32.507142],"type":"Point"}
}