{
  "type": "Feature",
  "properties": {
    "iso:country":"US",
    "sg:address":"387 Old Commerce Rd",
    "sg:city":"Athens",
    "sg:classifiers":[
        {
            "category":"Autos & Motor Vehicles",
            "subcategory":"Auto Supplies",
            "type":"Retail Goods"
        },
        {
            "category":"Wholesale",
            "subcategory":"Auto Parts",
            "type":"Manufacturing & Wholesale Goods"
        }
    ],
    "sg:phone":"+1 706 546 8640",
    "sg:postcode":"30607",
    "sg:province":"GA",
    "sg:tags":[
        "bearing",
        "bearings-wholesale"
    ],
    "wof:name":"Bearings & Drives Inc",
    "wof:placetype":"venue"
},
  "geometry": {"coordinates":[-83.380697,33.994378],"type":"Point"}
}