{
  "type": "Feature",
  "properties": {
    "iso:country":"US",
    "sg:address":"1847 Memorial Dr SE",
    "sg:city":"Atlanta",
    "sg:classifiers":[
        {
            "category":"Personal",
            "subcategory":"Beauty Salon",
            "type":"Services"
        }
    ],
    "sg:phone":"+1 404 373 8500",
    "sg:postcode":"30317",
    "sg:province":"GA",
    "sg:tags":[
        "shop"
    ],
    "wof:name":"Georgia Nails 2",
    "wof:placetype":"venue"
},
  "geometry": {"coordinates":[-84.32637699999999,33.747319],"type":"Point"}
}