{
  "type": "Feature",
  "properties": {
    "addr:full":"350 Modoc Dr Cornelia GA 30531",
    "addr:housenumber":"350",
    "addr:postcode":"30531",
    "addr:street":"Modoc Dr Cornelia",
    "iso:country":"US",
    "sg:address":"350 Modoc Dr",
    "sg:city":"Cornelia",
    "sg:classifiers":[
        {
            "category":"Manufacturing",
            "subcategory":"Printing",
            "type":"Manufacturing & Wholesale Goods"
        }
    ],
    "sg:phone":"+1 706 778 8732",
    "sg:postcode":"30531",
    "sg:province":"GA",
    "sg:tags":[
        "photocopying",
        "commercial"
    ],
    "wof:name":"Appalachian Printing Company",
    "wof:placetype":"venue"
},
  "geometry": {"coordinates":[-83.539266,34.521422],"type":"Point"}
}