{
  "type": "Feature",
  "properties": {
    "iso:country":"US",
    "sg:address":"100 Shelia Dr",
    "sg:city":"Warner Robins",
    "sg:classifiers":[
        {
            "category":"Professional",
            "subcategory":"Management & Consulting",
            "type":"Services"
        }
    ],
    "sg:phone":"+1 478 922 2455",
    "sg:postcode":"31088",
    "sg:province":"GA",
    "wof:name":"James Boswell",
    "wof:placetype":"venue"
},
  "geometry": {"coordinates":[-83.639974,32.604642],"type":"Point"}
}