{
  "type": "Feature",
  "properties": {
    "iso:country":"US",
    "sg:address":"1562 Doug Barnard Pkwy",
    "sg:city":"Augusta",
    "sg:classifiers":[
        {
            "category":"Shopping",
            "subcategory":"Used Merchandise",
            "type":"Retail Goods"
        }
    ],
    "sg:phone":"+1 803 279 9111",
    "sg:postcode":"30906",
    "sg:province":"GA",
    "wof:name":"Aurora Borealis",
    "wof:placetype":"venue"
},
  "geometry": {"coordinates":[-81.989215,33.428081],"type":"Point"}
}