{
  "type": "Feature",
  "properties": {
    "addr:full":"4217 Gateswalk Way Smyrna GA 30080",
    "addr:housenumber":"4217",
    "addr:postcode":"30080",
    "addr:street":"Gateswalk Way",
    "iso:country":"US",
    "sg:address":"4217 Gateswalk Way",
    "sg:city":"Smyrna",
    "sg:classifiers":[
        {
            "category":"Professional",
            "subcategory":"Management & Consulting",
            "type":"Services"
        }
    ],
    "sg:phone":"+1 770 333 1283",
    "sg:postcode":"30080",
    "sg:province":"GA",
    "sg:tags":[
        "business"
    ],
    "wof:name":"Programmer Plus Consulting",
    "wof:placetype":"venue"
},
  "geometry": {"coordinates":[-84.485375,33.852748],"type":"Point"}
}