{
  "type": "Feature",
  "properties": {
    "iso:country":"US",
    "sg:address":"5441 Peachtree Rd",
    "sg:city":"Atlanta",
    "sg:classifiers":[
        {
            "category":"Building & Trades",
            "subcategory":"Construction",
            "type":"Services"
        },
        {
            "category":"Manufacturing",
            "subcategory":"Building Materials",
            "type":"Manufacturing & Wholesale Goods"
        }
    ],
    "sg:phone":"+1 770 451 8779",
    "sg:postcode":"30341",
    "sg:province":"GA",
    "sg:tags":[
        "cabinetmakers-commercial",
        "industrial",
        "maker",
        "cabinet"
    ],
    "wof:name":"The Ice House Cabinets And Consignments",
    "wof:placetype":"venue"
},
  "geometry": {"coordinates":[-84.299369,33.893849],"type":"Point"}
}