{
  "type": "Feature",
  "properties": {
    "iso:country":"US",
    "sg:address":"5715 Cumming Hwy",
    "sg:city":"Sugar Hill",
    "sg:classifiers":[
        {
            "category":"Health Services",
            "subcategory":"Chiropractor",
            "type":"Services"
        }
    ],
    "sg:phone":"+1 678 482 4400",
    "sg:postcode":"30518",
    "sg:province":"GA",
    "wof:name":"Sugar Hill Family Chiropractic",
    "wof:placetype":"venue"
},
  "geometry": {"coordinates":[-84.078796,34.115002],"type":"Point"}
}