{
  "type": "Feature",
  "properties": {
    "iso:country":"US",
    "sg:address":"2214 Gillionville Rd",
    "sg:city":"Albany",
    "sg:classifiers":[
        {
            "category":"Building & Trades",
            "subcategory":"Construction",
            "type":"Services"
        }
    ],
    "sg:phone":"+1 229 446 8464",
    "sg:postcode":"31707",
    "sg:province":"GA",
    "sg:tags":[
        "home",
        "builder"
    ],
    "wof:name":"Stephen Bacon Realty & Constr",
    "wof:placetype":"venue"
},
  "geometry": {"coordinates":[-84.204633,31.584109],"type":"Point"}
}