{
  "type": "Feature",
  "properties": {
    "addr:full":"162 Buena Vista St Winder GA 30680",
    "addr:housenumber":"162",
    "addr:postcode":"30680",
    "addr:street":"Buena Vista St",
    "iso:country":"US",
    "sg:address":"162 Buena Vista St",
    "sg:city":"Winder",
    "sg:classifiers":[
        {
            "category":"Professional",
            "subcategory":"Computer Services",
            "type":"Services"
        }
    ],
    "sg:phone":"+1 770 947 1817",
    "sg:postcode":"30680",
    "sg:province":"GA",
    "sg:tags":[
        "related"
    ],
    "wof:name":"Computer Integrated Services",
    "wof:placetype":"venue"
},
  "geometry": {"coordinates":[-83.71368699999999,34.006164],"type":"Point"}
}