{
  "type": "Feature",
  "properties": {
    "iso:country":"US",
    "sg:address":"875 Lawrenceville Hwy",
    "sg:city":"Lawrenceville",
    "sg:classifiers":[
        {
            "category":"Health Services",
            "subcategory":"Optometrist",
            "type":"Services"
        }
    ],
    "sg:phone":"+1 770 963 0370",
    "sg:postcode":"30045",
    "sg:province":"GA",
    "wof:name":"Paula Gorlin Od",
    "wof:placetype":"venue"
},
  "geometry": {"coordinates":[-84.0094,33.944983],"type":"Point"}
}