{
  "type": "Feature",
  "properties": {
    "addr:full":"420 Wesley Plantation Dr Duluth GA 30096",
    "addr:housenumber":"420",
    "addr:postcode":"30096",
    "addr:street":"Wesley Plantation Dr",
    "iso:country":"US",
    "sg:address":"420 Wesley Plantation Dr",
    "sg:city":"Duluth",
    "sg:classifiers":[
        {
            "category":"Professional",
            "type":"Services"
        }
    ],
    "sg:phone":"+1 770 232 9427",
    "sg:postcode":"30096",
    "sg:province":"GA",
    "wof:name":"Elite Referral Svc",
    "wof:placetype":"venue"
},
  "geometry": {"coordinates":[-84.169656,34.00102],"type":"Point"}
}