{
  "type": "Feature",
  "properties": {
    "addr:full":"1105 Peachtree Industrial Blvd Suwanee GA 30024",
    "addr:housenumber":"1105",
    "addr:postcode":"30024",
    "addr:street":"Peachtree Industrial Blvd",
    "iso:country":"US",
    "sg:address":"1105 Peachtree Industrial Blvd",
    "sg:city":"Suwanee",
    "sg:classifiers":[
        {
            "category":"Home & Garden",
            "subcategory":"Garden Supply",
            "type":"Retail Goods"
        }
    ],
    "sg:phone":"+1 770 271 5433",
    "sg:postcode":"30024",
    "sg:province":"GA",
    "sg:tags":[
        "bulb",
        "nurseryman",
        "nursery",
        "seed",
        "stock"
    ],
    "wof:name":"Pike Family Nurseries",
    "wof:placetype":"venue"
},
  "geometry": {"coordinates":[-84.096349,34.044274],"type":"Point"}
}