{
  "type": "Feature",
  "properties": {
    "addr:full":"104 Tibet Ave Savannah GA 31406",
    "addr:housenumber":"104",
    "addr:postcode":"31406",
    "addr:street":"Tibet Ave",
    "iso:country":"US",
    "sg:address":"104 Tibet Ave",
    "sg:city":"Savannah",
    "sg:classifiers":[
        {
            "category":"Food & Beverages",
            "subcategory":"Groceries & Convenience Stores",
            "type":"Retail Goods"
        }
    ],
    "sg:phone":"+1 912 925 2315",
    "sg:postcode":"31406",
    "sg:province":"GA",
    "sg:tags":[
        "station",
        "gasoline"
    ],
    "wof:name":"Circle K",
    "wof:placetype":"venue"
},
  "geometry": {"coordinates":[-81.13137999999999,31.98923],"type":"Point"}
}