{
  "type": "Feature",
  "properties": {
    "iso:country":"US",
    "sg:address":"1115 Clay Rd SW",
    "sg:city":"Mableton",
    "sg:classifiers":[
        {
            "category":"Retail",
            "subcategory":"Funeral Services",
            "type":"Services"
        }
    ],
    "sg:phone":"+1 770 948 0113",
    "sg:postcode":"30126",
    "sg:province":"GA",
    "sg:tags":[
        "cemetery"
    ],
    "wof:name":"White Columns Funeral Chapels Inc",
    "wof:placetype":"venue"
},
  "geometry": {"coordinates":[-84.586601,33.827801],"type":"Point"}
}