{
  "type": "Feature",
  "properties": {
    "addr:full":"1090 Northchase Pkwy SE Marietta GA 30067",
    "addr:housenumber":"1090",
    "addr:postcode":"30067",
    "addr:street":"Northchase Pkwy Se",
    "iso:country":"US",
    "sg:address":"1090 Northchase Pkwy SE",
    "sg:city":"Marietta",
    "sg:classifiers":[
        {
            "category":"Banks & Credit Unions",
            "subcategory":"Bank",
            "type":"Services"
        }
    ],
    "sg:phone":"+1 770 984 3265",
    "sg:postcode":"30067",
    "sg:province":"GA",
    "sg:tags":[
        "loan",
        "real estate"
    ],
    "wof:name":"Upland Mortgage",
    "wof:placetype":"venue"
},
  "geometry": {"coordinates":[-84.47974000000001,33.926506],"type":"Point"}
}