{
  "type": "Feature",
  "properties": {
    "addr:full":"6023 Caribou Dr Columbus GA 31907",
    "addr:housenumber":"6023",
    "addr:postcode":"31907",
    "addr:street":"Caribou Dr",
    "iso:country":"US",
    "sg:address":"6023 Caribou Dr",
    "sg:city":"Columbus",
    "sg:classifiers":[
        {
            "category":"Professional",
            "subcategory":"Computer Services",
            "type":"Services"
        }
    ],
    "sg:phone":"+1 706 507 4845",
    "sg:postcode":"31907",
    "sg:province":"GA",
    "sg:tags":[
        "repair"
    ],
    "wof:name":"Carlo Williams Computer Repair",
    "wof:placetype":"venue"
},
  "geometry": {"coordinates":[-84.887912,32.489176],"type":"Point"}
}