{
  "type": "Feature",
  "properties": {
    "iso:country":"US",
    "sg:address":"4140 Waldrop Hills Ter",
    "sg:city":"Decatur",
    "sg:classifiers":[
        {
            "category":"Building & Trades",
            "subcategory":"Construction",
            "type":"Services"
        }
    ],
    "sg:phone":"+1 404 384 8660",
    "sg:postcode":"30034",
    "sg:province":"GA",
    "sg:tags":[
        "residential"
    ],
    "wof:name":"Franklins Fine Finishes",
    "wof:placetype":"venue"
},
  "geometry": {"coordinates":[-84.245452,33.678553],"type":"Point"}
}