{
  "type": "Feature",
  "properties": {
    "addr:full":"4906 Timber Dr Lake Park GA 31636",
    "addr:housenumber":"4906",
    "addr:postcode":"31636",
    "addr:street":"Timber Dr",
    "iso:country":"US",
    "sg:address":"4906 Timber Dr",
    "sg:city":"Lake Park",
    "sg:classifiers":[
        {
            "category":"Travel",
            "subcategory":"Hotels & Motels",
            "type":"Entertainment"
        }
    ],
    "sg:phone":"+1 229 559 5565",
    "sg:postcode":"31636",
    "sg:province":"GA",
    "sg:tags":[
        "operation"
    ],
    "wof:name":"Hampton Inn",
    "wof:placetype":"venue"
},
  "geometry": {"coordinates":[-83.227896,30.682029],"type":"Point"}
}