{
  "type": "Feature",
  "properties": {
    "iso:country":"US",
    "sg:address":"107 Shelby Ct",
    "sg:city":"Augusta",
    "sg:classifiers":[
        {
            "category":"Building & Trades",
            "subcategory":"Pest Control",
            "type":"Services"
        }
    ],
    "sg:phone":"+1 706 790 0318",
    "sg:postcode":"30906",
    "sg:province":"GA",
    "wof:name":"Riggin's Pest & Moisture Cntrl",
    "wof:placetype":"venue"
},
  "geometry": {"coordinates":[-82.040879,33.416876],"type":"Point"}
}