{
  "type": "Feature",
  "properties": {
    "iso:country":"US",
    "sg:address":"2385 Clower St SW",
    "sg:city":"Snellville",
    "sg:classifiers":[
        {
            "category":"Personal",
            "subcategory":"Beauty Salon",
            "type":"Services"
        }
    ],
    "sg:phone":"+1 770 978 7787",
    "sg:postcode":"30078",
    "sg:province":"GA",
    "sg:website":"www.salon124.com",
    "wof:name":"Salon 124 Group",
    "wof:placetype":"venue"
},
  "geometry": {"coordinates":[-84.01518,33.859127],"type":"Point"}
}