{
  "type": "Feature",
  "properties": {
    "iso:country":"US",
    "sg:address":"1120 Thomas Rd",
    "sg:city":"Cleveland",
    "sg:classifiers":[
        {
            "category":"Farming",
            "subcategory":"Farm",
            "type":"Manufacturing & Wholesale Goods"
        }
    ],
    "sg:phone":"+1 706 865 4076",
    "sg:postcode":"30528",
    "sg:province":"GA",
    "sg:tags":[
        "crop",
        "general"
    ],
    "wof:name":"Chigger Ridge Farm",
    "wof:placetype":"venue"
},
  "geometry": {"coordinates":[-83.821066,34.555895],"type":"Point"}
}