{
  "type": "Feature",
  "properties": {
    "addr:full":"505 Heyward Cir Marietta GA 30064",
    "addr:housenumber":"505",
    "addr:postcode":"30064",
    "addr:street":"Heyward Cir",
    "iso:country":"US",
    "sg:address":"505 Heyward Cir",
    "sg:city":"Marietta",
    "sg:classifiers":[
        {
            "category":"Building & Trades",
            "subcategory":"Construction",
            "type":"Services"
        }
    ],
    "sg:phone":"+1 770 729 0427",
    "sg:postcode":"30064",
    "sg:province":"GA",
    "sg:tags":[
        "house"
    ],
    "wof:name":"Dr Shamblin Construction",
    "wof:placetype":"venue"
},
  "geometry": {"coordinates":[-84.574078,33.96783],"type":"Point"}
}