{
  "type": "Feature",
  "properties": {
    "addr:full":"914 Pacific Ave Bremen GA 30110",
    "addr:housenumber":"914",
    "addr:postcode":"30110",
    "addr:street":"Pacific Ave",
    "iso:country":"US",
    "sg:address":"914 Pacific Ave",
    "sg:city":"Bremen",
    "sg:classifiers":[
        {
            "category":"Real Estate",
            "subcategory":"Real Estate Operator",
            "type":"Services"
        }
    ],
    "sg:phone":"+1 770 537 5100",
    "sg:postcode":"30110",
    "sg:province":"GA",
    "sg:tags":[
        "building",
        "apartment"
    ],
    "wof:name":"Gateway Inn",
    "wof:placetype":"venue"
},
  "geometry": {"coordinates":[-85.12907800000001,33.723585],"type":"Point"}
}