{
  "type": "Feature",
  "properties": {
    "addr:full":"2020 Honey Creek Pkwy SE Conyers GA 30013",
    "addr:housenumber":"2020",
    "addr:postcode":"30013",
    "addr:street":"Honey Creek Pkwy Se",
    "iso:country":"US",
    "sg:address":"2020 Honey Creek Pkwy SE",
    "sg:city":"Conyers",
    "sg:classifiers":[
        {
            "category":"Health Services",
            "subcategory":"Doctor",
            "type":"Services"
        }
    ],
    "sg:phone":"+1 770 929 0813",
    "sg:postcode":"30013",
    "sg:province":"GA",
    "sg:tags":[
        "practice",
        "family"
    ],
    "wof:name":"Gulati Anu MD",
    "wof:placetype":"venue"
},
  "geometry": {"coordinates":[-84.014144,33.598109],"type":"Point"}
}