{
  "type": "Feature",
  "properties": {
    "iso:country":"US",
    "sg:address":"492 Shiloh Rd",
    "sg:city":"Jenkinsburg",
    "sg:classifiers":[
        {
            "category":"Organizations",
            "subcategory":"Religious Organization",
            "type":"Services"
        }
    ],
    "sg:phone":"+1 770 775 1261",
    "sg:postcode":"30233",
    "sg:province":"GA",
    "wof:name":"Shiloh Baptist Church",
    "wof:placetype":"venue"
},
  "geometry": {"coordinates":[-84.025958,33.294384],"type":"Point"}
}