{
  "type": "Feature",
  "properties": {
    "addr:full":"140 Alps Rd Athens GA 30606",
    "addr:housenumber":"140",
    "addr:postcode":"30606",
    "addr:street":"Alps Rd",
    "iso:country":"US",
    "sg:address":"140 Alps Rd",
    "sg:city":"Athens",
    "sg:classifiers":[
        {
            "category":"Restaurant",
            "type":"Food & Drink"
        }
    ],
    "sg:phone":"+1 706 543 5960",
    "sg:postcode":"30606",
    "sg:province":"GA",
    "sg:tags":[
        "drinking",
        "eating"
    ],
    "wof:name":"Bennigans",
    "wof:placetype":"venue"
},
  "geometry": {"coordinates":[-83.40927000000001,33.947247],"type":"Point"}
}