{
  "type": "Feature",
  "properties": {
    "addr:full":"2990 Olympic Industrial Dr SE Smyrna GA 30080",
    "addr:housenumber":"2990",
    "addr:postcode":"30080",
    "addr:street":"Olympic Industrial Dr Se",
    "iso:country":"US",
    "sg:address":"2990 Olympic Industrial Dr SE",
    "sg:city":"Smyrna",
    "sg:classifiers":[
        {
            "category":"Home & Garden",
            "subcategory":"Building Materials",
            "type":"Retail Goods"
        }
    ],
    "sg:phone":"+1 404 603 5240",
    "sg:postcode":"30080",
    "sg:province":"GA",
    "sg:tags":[
        "supply"
    ],
    "wof:name":"Residential Wholesale Supply",
    "wof:placetype":"venue"
},
  "geometry": {"coordinates":[-84.467933,33.831755],"type":"Point"}
}