{
  "type": "Feature",
  "properties": {
    "iso:country":"US",
    "sg:address":"3803 Macon Rd",
    "sg:city":"Columbus",
    "sg:classifiers":[
        {
            "category":"Health Services",
            "subcategory":"Chiropractor",
            "type":"Services"
        }
    ],
    "sg:phone":"+1 706 682 5575",
    "sg:postcode":"31907",
    "sg:province":"GA",
    "wof:name":"Access Medical",
    "wof:placetype":"venue"
},
  "geometry": {"coordinates":[-84.930723,32.490115],"type":"Point"}
}