{
  "type": "Feature",
  "properties": {
    "addr:full":"1461 Hudson Bridge Rd Stockbridge GA 30281",
    "addr:housenumber":"1461",
    "addr:postcode":"30281",
    "addr:street":"Hudson Bridge Rd",
    "iso:country":"US",
    "sg:address":"1461 Hudson Bridge Rd",
    "sg:city":"Stockbridge",
    "sg:classifiers":[
        {
            "category":"Freight",
            "type":"Transportation"
        }
    ],
    "sg:phone":"+1 770 801 1888",
    "sg:postcode":"30281",
    "sg:province":"GA",
    "sg:tags":[
        "self",
        "storage",
        "facility"
    ],
    "wof:name":"Hudson Storage",
    "wof:placetype":"venue"
},
  "geometry": {"coordinates":[-84.238308,33.50359],"type":"Point"}
}