{
  "type": "Feature",
  "properties": {
    "iso:country":"US",
    "sg:address":"232 Atlantic Ave",
    "sg:city":"Bremen",
    "sg:classifiers":[
        {
            "category":"Retail",
            "subcategory":"Auto Repair",
            "type":"Services"
        }
    ],
    "sg:phone":"+1 770 537 4800",
    "sg:postcode":"30110",
    "sg:province":"GA",
    "sg:tags":[
        "automotive"
    ],
    "wof:name":"Bremen Wrecker Services",
    "wof:placetype":"venue"
},
  "geometry": {"coordinates":[-85.150699,33.71849],"type":"Point"}
}