{
  "type": "Feature",
  "properties": {
    "addr:full":"5898 Val del Rd Hahira GA 31632",
    "addr:housenumber":"5898",
    "addr:postcode":"31632",
    "addr:street":"Val Del Rd",
    "iso:country":"US",
    "sg:address":"5898 Val del Rd",
    "sg:city":"Hahira",
    "sg:classifiers":[
        {
            "category":"Real Estate",
            "subcategory":"Real Estate Services",
            "type":"Services"
        },
        {
            "category":"Real Estate",
            "subcategory":"Real Estate Agent",
            "type":"Services"
        }
    ],
    "sg:phone":"+1 229 794 1029",
    "sg:postcode":"31632",
    "sg:province":"GA",
    "sg:tags":[
        "buyer",
        "broker"
    ],
    "wof:name":"Kelty Real Estate",
    "wof:placetype":"venue"
},
  "geometry": {"coordinates":[-83.32401400000001,30.996262],"type":"Point"}
}