{
  "type": "Feature",
  "properties": {
    "addr:full":"1808 Powers Ferry Rd SE Atlanta GA 30339",
    "addr:housenumber":"1808",
    "addr:postcode":"30339",
    "addr:street":"Powers Ferry Rd Se",
    "iso:country":"US",
    "sg:address":"1808 Powers Ferry Rd SE",
    "sg:city":"Atlanta",
    "sg:classifiers":[
        {
            "category":"Restaurant",
            "type":"Food & Drink"
        }
    ],
    "sg:phone":"+1 770 953 0121",
    "sg:postcode":"30339",
    "sg:province":"GA",
    "wof:name":"Frontera Mex-Mex Grill",
    "wof:placetype":"venue"
},
  "geometry": {"coordinates":[-84.46551700000001,33.908578],"type":"Point"}
}