{
  "type": "Feature",
  "properties": {
    "addr:full":"2625 Deans Bridge Rd Augusta GA 30906",
    "addr:housenumber":"2625",
    "addr:postcode":"30906",
    "addr:street":"Deans Bridge Rd",
    "iso:country":"US",
    "sg:address":"2625 Deans Bridge Rd",
    "sg:city":"Augusta",
    "sg:classifiers":[
        {
            "category":"Shopping",
            "subcategory":"Used Merchandise",
            "type":"Retail Goods"
        }
    ],
    "sg:phone":"+1 706 796 0493",
    "sg:postcode":"30906",
    "sg:province":"GA",
    "wof:name":"Advance Long Distance",
    "wof:placetype":"venue"
},
  "geometry": {"coordinates":[-82.016946,33.443957],"type":"Point"}
}