{
  "type": "Feature",
  "properties": {
    "addr:full":"3185 Kellogg Creek Rd Acworth GA 30102",
    "addr:housenumber":"3185",
    "addr:postcode":"30102",
    "addr:street":"Kellogg Creek Rd",
    "iso:country":"US",
    "sg:address":"3185 Kellogg Creek Rd",
    "sg:city":"Acworth",
    "sg:classifiers":[
        {
            "category":"Farming",
            "subcategory":"Farm",
            "type":"Manufacturing & Wholesale Goods"
        }
    ],
    "sg:phone":"+1 770 974 5575",
    "sg:postcode":"30102",
    "sg:province":"GA",
    "wof:name":"Family Thompson Farm",
    "wof:placetype":"venue"
},
  "geometry": {"coordinates":[-84.641795,34.114571],"type":"Point"}
}