{
  "type": "Feature",
  "properties": {
    "iso:country":"US",
    "sg:address":"1814 North Rd SW",
    "sg:city":"Snellville",
    "sg:classifiers":[
        {
            "category":"Retail",
            "subcategory":"Auto Repair",
            "type":"Services"
        }
    ],
    "sg:phone":"+1 770 972 7289",
    "sg:postcode":"30078",
    "sg:province":"GA",
    "sg:tags":[
        "automotive"
    ],
    "wof:name":"J & B Towing",
    "wof:placetype":"venue"
},
  "geometry": {"coordinates":[-84.008262,33.876992],"type":"Point"}
}