{
  "type": "Feature",
  "properties": {
    "iso:country":"US",
    "sg:address":"1717 N Decatur Rd",
    "sg:city":"Atlanta",
    "sg:classifiers":[
        {
            "category":"Real Estate",
            "subcategory":"Real Estate Agent",
            "type":"Services"
        }
    ],
    "sg:phone":"+1 404 377 7778",
    "sg:postcode":"30307",
    "sg:province":"GA",
    "wof:name":"Clifton Condominiums",
    "wof:placetype":"venue"
},
  "geometry": {"coordinates":[-84.319143,33.789383],"type":"Point"}
}