{
  "type": "Feature",
  "properties": {
    "iso:country":"US",
    "sg:address":"3030 US Hwy 41",
    "sg:city":"Valdosta",
    "sg:classifiers":[
        {
            "category":"Organizations",
            "subcategory":"Religious Organization",
            "type":"Services"
        }
    ],
    "sg:phone":"+1 229 242 7580",
    "sg:postcode":"31601",
    "sg:province":"GA",
    "wof:name":"United Kindom Hall Jehovas WI",
    "wof:placetype":"venue"
},
  "geometry": {"coordinates":[-83.23108999999999,30.774642],"type":"Point"}
}