{
  "type": "Feature",
  "properties": {
    "addr:full":"626 E Franklin St Sylvester GA 31791",
    "addr:housenumber":"626",
    "addr:postcode":"31791",
    "addr:street":"E Franklin St",
    "iso:country":"US",
    "sg:address":"626 E Franklin St",
    "sg:city":"Sylvester",
    "sg:classifiers":[
        {
            "category":"Retail",
            "subcategory":"Laundry & Dry Cleaning",
            "type":"Services"
        }
    ],
    "sg:phone":"+1 229 776 9733",
    "sg:postcode":"31791",
    "sg:province":"GA",
    "sg:tags":[
        "cleaners"
    ],
    "wof:name":"Hometown Cleaners",
    "wof:placetype":"venue"
},
  "geometry": {"coordinates":[-83.82834200000001,31.530111],"type":"Point"}
}