{
  "type": "Feature",
  "properties": {
    "addr:full":"3285 New Macland Rd Powder Springs GA 30127",
    "addr:housenumber":"3285",
    "addr:postcode":"30127",
    "addr:street":"New Macland Rd",
    "iso:country":"US",
    "sg:address":"3285 New Macland Rd",
    "sg:city":"Powder Springs",
    "sg:classifiers":[
        {
            "category":"Shopping",
            "subcategory":"Pharmacy",
            "type":"Retail Goods"
        }
    ],
    "sg:phone":"+1 770 943 4136",
    "sg:postcode":"30127",
    "sg:province":"GA",
    "wof:name":"CVS",
    "wof:placetype":"venue"
},
  "geometry": {"coordinates":[-84.67626199999999,33.873916],"type":"Point"}
}