{
  "type": "Feature",
  "properties": {
    "addr:full":"3531 Habersham At Nrthlke Tucker GA 30084",
    "addr:housenumber":"3531",
    "addr:postcode":"30084",
    "addr:street":"At",
    "iso:country":"US",
    "sg:address":"3531 Habersham At Nrthlke",
    "sg:city":"Tucker",
    "sg:classifiers":[
        {
            "category":"Education",
            "subcategory":"School",
            "type":"Public Place"
        }
    ],
    "sg:phone":"+1 770 493 5094",
    "sg:postcode":"30084",
    "sg:province":"GA",
    "wof:name":"Performance Management Magazine",
    "wof:placetype":"venue"
},
  "geometry": {"coordinates":[-84.244102,33.851799],"type":"Point"}
}