{
  "type": "Feature",
  "properties": {
    "iso:country":"US",
    "sg:address":"302 N Greenwood St",
    "sg:city":"La Grange",
    "sg:classifiers":[
        {
            "category":"Personal",
            "type":"Services"
        }
    ],
    "sg:phone":"+1 706 883 7339",
    "sg:postcode":"30240",
    "sg:province":"GA",
    "wof:name":"Body Tree",
    "wof:placetype":"venue"
},
  "geometry": {"coordinates":[-85.034898,33.043339],"type":"Point"}
}