{
  "type": "Feature",
  "properties": {
    "addr:full":"212 W Jackson St Dublin GA 31021",
    "addr:housenumber":"212",
    "addr:postcode":"31021",
    "addr:street":"W Jackson St",
    "iso:country":"US",
    "sg:address":"212 W Jackson St",
    "sg:city":"Dublin",
    "sg:classifiers":[
        {
            "category":"Professional",
            "subcategory":"Lawyer & Legal Services",
            "type":"Services"
        }
    ],
    "sg:phone":"+1 478 275 7672",
    "sg:postcode":"31021",
    "sg:province":"GA",
    "sg:tags":[
        "attorney"
    ],
    "wof:name":"Kathleen Kaye",
    "wof:placetype":"venue"
},
  "geometry": {"coordinates":[-82.906041,32.539306],"type":"Point"}
}