{
  "type": "Feature",
  "properties": {
    "iso:country":"US",
    "sg:address":"6303 Brighton Way",
    "sg:city":"Flowery Branch",
    "sg:classifiers":[
        {
            "category":"Building & Trades",
            "subcategory":"Construction",
            "type":"Services"
        }
    ],
    "sg:phone":"+1 770 967 9103",
    "sg:postcode":"30542",
    "sg:province":"GA",
    "sg:tags":[
        "fence",
        "contractor"
    ],
    "wof:name":"Action Sales & Planning",
    "wof:placetype":"venue"
},
  "geometry": {"coordinates":[-83.958198,34.172973],"type":"Point"}
}