{
  "type": "Feature",
  "properties": {
    "iso:country":"US",
    "sg:address":"2211 Toledo Dr",
    "sg:city":"Albany",
    "sg:classifiers":[
        {
            "category":"Wholesale",
            "subcategory":"Machinery & Supplies",
            "type":"Manufacturing & Wholesale Goods"
        }
    ],
    "sg:phone":"+1 229 436 8486",
    "sg:postcode":"31705",
    "sg:province":"GA",
    "sg:tags":[
        "industrial"
    ],
    "wof:name":"Jim Horne/Young & Vann",
    "wof:placetype":"venue"
},
  "geometry": {"coordinates":[-84.09837899999999,31.558393],"type":"Point"}
}