{
  "type": "Feature",
  "properties": {
    "iso:country":"US",
    "sg:address":"1500 Veterans Memorial Pkwy SW",
    "sg:city":"Mableton",
    "sg:classifiers":[
        {
            "category":"Utilities",
            "subcategory":"Mobile Phone",
            "type":"Services"
        }
    ],
    "sg:phone":"+1 770 739 9300",
    "sg:postcode":"30126",
    "sg:province":"GA",
    "sg:tags":[
        "telephone",
        "cellular"
    ],
    "wof:name":"Amigos Wireless",
    "wof:placetype":"venue"
},
  "geometry": {"coordinates":[-84.59696099999999,33.815317],"type":"Point"}
}