{
  "type": "Feature",
  "properties": {
    "iso:country":"US",
    "sg:address":"540 Amboy Rd",
    "sg:city":"Arabi",
    "sg:phone":"+1 229 273 5920",
    "sg:postcode":"31712",
    "sg:province":"GA",
    "sg:tags":[
        "farm",
        "cotton"
    ],
    "wof:name":"Eddie Luke",
    "wof:placetype":"venue"
},
  "geometry": {"coordinates":[-83.686004,31.820596],"type":"Point"}
}