{
  "type": "Feature",
  "properties": {
    "iso:country":"US",
    "sg:address":"6850 Buford Hwy NE Drvl",
    "sg:city":"Atlanta",
    "sg:classifiers":[
        {
            "category":"Autos & Motor Vehicles",
            "subcategory":"Auto Supplies",
            "type":"Retail Goods"
        }
    ],
    "sg:phone":"+1 770 441 0611",
    "sg:postcode":"30340",
    "sg:province":"GA",
    "sg:tags":[
        "transmission"
    ],
    "wof:name":"Specialized Transmission Repair",
    "wof:placetype":"venue"
},
  "geometry": {"coordinates":[-84.24768400000001,33.925811],"type":"Point"}
}