{
  "type": "Feature",
  "properties": {
    "addr:full":"577 Mulberry St Macon GA 31201",
    "addr:housenumber":"577",
    "addr:postcode":"31201",
    "addr:street":"Mulberry St",
    "iso:country":"US",
    "sg:address":"577 Mulberry St",
    "sg:city":"Macon",
    "sg:phone":"+1 478 755 0010",
    "sg:postcode":"31201",
    "sg:province":"GA",
    "sg:website":"http://www.realpagessites.com/randallpc",
    "wof:name":"Randall & Nestor",
    "wof:placetype":"venue"
},
  "geometry": {"coordinates":[-83.627568,32.837836],"type":"Point"}
}