{
  "type": "Feature",
  "properties": {
    "addr:full":"1470 Beaver Ruin Rd Norcross GA 30093",
    "addr:housenumber":"1470",
    "addr:postcode":"30093",
    "addr:street":"Beaver Ruin Rd",
    "iso:country":"US",
    "sg:address":"1470 Beaver Ruin Rd",
    "sg:city":"Norcross",
    "sg:classifiers":[
        {
            "category":"Banks & Credit Unions",
            "subcategory":"Bank",
            "type":"Services"
        }
    ],
    "sg:phone":"+1 770 925 9261",
    "sg:postcode":"30093",
    "sg:province":"GA",
    "wof:name":"Associated & Federal Employees Credit Union",
    "wof:placetype":"venue"
},
  "geometry": {"coordinates":[-84.144402,33.930599],"type":"Point"}
}