{
  "type": "Feature",
  "properties": {
    "addr:full":"7590 Spalding Ln Atlanta GA 30350",
    "addr:housenumber":"7590",
    "addr:postcode":"30350",
    "addr:street":"Spalding Ln",
    "iso:country":"US",
    "sg:address":"7590 Spalding Ln",
    "sg:city":"Atlanta",
    "sg:classifiers":[
        {
            "category":"Professional",
            "subcategory":"Computer Services",
            "type":"Services"
        }
    ],
    "sg:phone":"+1 404 543 0200",
    "sg:postcode":"30350",
    "sg:province":"GA",
    "sg:tags":[
        "related"
    ],
    "wof:name":"Network Pathways LLC",
    "wof:placetype":"venue"
},
  "geometry": {"coordinates":[-84.274202,33.958504],"type":"Point"}
}