{
  "type": "Feature",
  "properties": {
    "addr:full":"1111 W Baker Hwy Douglas GA 31533",
    "addr:housenumber":"1111",
    "addr:postcode":"31533",
    "addr:street":"W Baker Hwy",
    "iso:country":"US",
    "sg:address":"1111 W Baker Hwy",
    "sg:city":"Douglas",
    "sg:classifiers":[
        {
            "category":"Government",
            "subcategory":"Office",
            "type":"Public Place"
        }
    ],
    "sg:phone":"+1 912 389 4450",
    "sg:postcode":"31533",
    "sg:province":"GA",
    "sg:tags":[
        "state",
        "program",
        "health"
    ],
    "wof:name":"Health Dept",
    "wof:placetype":"venue"
},
  "geometry": {"coordinates":[-82.86183,31.500985],"type":"Point"}
}