{
  "type": "Feature",
  "properties": {
    "iso:country":"US",
    "sg:address":"602 Waldroup Ave",
    "sg:city":"Douglas",
    "sg:classifiers":[
        {
            "category":"Manufacturing",
            "subcategory":"Apparel",
            "type":"Manufacturing & Wholesale Goods"
        }
    ],
    "sg:phone":"+1 912 384 7902",
    "sg:postcode":"31535",
    "sg:province":"GA",
    "sg:tags":[
        "shop",
        "rag",
        "mfg"
    ],
    "wof:name":"Brittany-Meryl Wiping Cloth",
    "wof:placetype":"venue"
},
  "geometry": {"coordinates":[-82.82566,31.498494],"type":"Point"}
}