{
  "type": "Feature",
  "properties": {
    "iso:country":"US",
    "sg:address":"1067 Redstone Ln",
    "sg:city":"Atlanta",
    "sg:classifiers":[
        {
            "category":"Autos & Motor Vehicles",
            "subcategory":"Automobile Sales",
            "type":"Retail Goods"
        }
    ],
    "sg:phone":"+1 770 394 6474",
    "sg:postcode":"30338",
    "sg:province":"GA",
    "sg:tags":[
        "car",
        "used",
        "dealer"
    ],
    "wof:name":"Dekalb Auto Sales Inc",
    "wof:placetype":"venue"
},
  "geometry": {"coordinates":[-84.345247,33.961586],"type":"Point"}
}