{
  "type": "Feature",
  "properties": {
    "addr:full":"12112 Brown Bridge Rd Covington GA 30016",
    "addr:housenumber":"12112",
    "addr:postcode":"30016",
    "addr:street":"Brown Bridge Rd",
    "iso:country":"US",
    "sg:address":"12112 Brown Bridge Rd",
    "sg:city":"Covington",
    "sg:classifiers":[
        {
            "category":"Retail",
            "subcategory":"Auto Repair",
            "type":"Services"
        }
    ],
    "sg:phone":"+1 770 483 5808",
    "sg:postcode":"30016",
    "sg:province":"GA",
    "sg:tags":[
        "repairing",
        "tire"
    ],
    "wof:name":"East Metro Tire Svc",
    "wof:placetype":"venue"
},
  "geometry": {"coordinates":[-83.93351800000001,33.579712],"type":"Point"}
}