{
  "type": "Feature",
  "properties": {
    "addr:full":"900 Old Statenville Rd Valdosta GA 31601",
    "addr:housenumber":"900",
    "addr:postcode":"31601",
    "addr:street":"Old Statenville Rd",
    "iso:country":"US",
    "sg:address":"900 Old Statenville Rd",
    "sg:city":"Valdosta",
    "sg:classifiers":[
        {
            "category":"Recreation",
            "type":"Entertainment"
        }
    ],
    "sg:phone":"+1 229 333 1843",
    "sg:postcode":"31601",
    "sg:province":"GA",
    "sg:tags":[
        "parks"
    ],
    "wof:name":"Scott Park",
    "wof:placetype":"venue"
},
  "geometry": {"coordinates":[-83.258636,30.821582],"type":"Point"}
}