{
  "type": "Feature",
  "properties": {
    "addr:full":"1232 S Highway 74 Atlanta GA 30303",
    "addr:housenumber":"1232",
    "addr:postcode":"30303",
    "addr:street":"S Highway 74",
    "iso:country":"US",
    "sg:address":"1232 S Highway 74",
    "sg:city":"Atlanta",
    "sg:classifiers":[
        {
            "category":"Shopping",
            "subcategory":"Pharmacy",
            "type":"Retail Goods"
        }
    ],
    "sg:phone":"+1 770 631 3766",
    "sg:postcode":"30303",
    "sg:province":"GA",
    "sg:tags":[
        "drugstore"
    ],
    "sg:website":"www.riteaid.com",
    "wof:name":"Rite Aid Pharmacies",
    "wof:placetype":"venue"
},
  "geometry": {"coordinates":[-84.584728,33.490125],"type":"Point"}
}