{
  "type": "Feature",
  "properties": {
    "iso:country":"US",
    "sg:address":"6377 Riverview Rd SE",
    "sg:city":"Mableton",
    "sg:classifiers":[
        {
            "category":"Utilities",
            "subcategory":"Refuse",
            "type":"Services"
        }
    ],
    "sg:phone":"+1 404 691 7710",
    "sg:postcode":"30082",
    "sg:province":"GA",
    "sg:tags":[
        "system"
    ],
    "wof:name":"Atlanta Waste Services Inc",
    "wof:placetype":"venue"
},
  "geometry": {"coordinates":[-84.505031,33.79945],"type":"Point"}
}