{
  "type": "Feature",
  "properties": {
    "iso:country":"US",
    "sg:address":"235 Jefferson St",
    "sg:city":"Newnan",
    "sg:classifiers":[
        {
            "category":"Retail",
            "subcategory":"Repair Shop",
            "type":"Services"
        },
        {
            "category":"Home & Garden",
            "subcategory":"Building Materials",
            "type":"Retail Goods"
        },
        {
            "category":"Building & Trades",
            "subcategory":"Construction",
            "type":"Services"
        }
    ],
    "sg:phone":"+1 678 854 8443",
    "sg:postcode":"30263",
    "sg:province":"GA",
    "sg:tags":[
        "planning",
        "bathroom",
        "altering",
        "handyman",
        "contractor",
        "fix-it",
        "maintenance",
        "basement",
        "improvement",
        "remodeling",
        "kitchen"
    ],
    "sg:website":"http://gahandymanllc.iarbiz.com/Q5VAWqBsC2s=",
    "wof:name":"GA Handyman, LLC",
    "wof:placetype":"venue"
},
  "geometry": {"coordinates":[-84.78862599999999,33.387514],"type":"Point"}
}