{
  "type": "Feature",
  "properties": {
    "addr:full":"3525 Pebble Creek Dr Hephzibah GA 30815",
    "addr:housenumber":"3525",
    "addr:postcode":"30815",
    "addr:street":"Pebble Creek Dr",
    "iso:country":"US",
    "sg:address":"3525 Pebble Creek Dr",
    "sg:city":"Hephzibah",
    "sg:classifiers":[
        {
            "category":"Health Services",
            "subcategory":"Nursing And Care Facility",
            "type":"Services"
        }
    ],
    "sg:phone":"+1 706 790 6290",
    "sg:postcode":"30815",
    "sg:province":"GA",
    "sg:tags":[
        "intermediate"
    ],
    "wof:name":"L & J Assisted Living Home",
    "wof:placetype":"venue"
},
  "geometry": {"coordinates":[-82.098964,33.397104],"type":"Point"}
}