{
  "type": "Feature",
  "properties": {
    "iso:country":"US",
    "sg:address":"1210 Shurling Dr",
    "sg:city":"Macon",
    "sg:classifiers":[
        {
            "category":"Education",
            "subcategory":"School",
            "type":"Public Place"
        }
    ],
    "sg:phone":"+1 478 751 6758",
    "sg:postcode":"31211",
    "sg:province":"GA",
    "sg:tags":[
        "middle"
    ],
    "sg:website":"www.bibb.k12.ga.us",
    "wof:name":"Appling Middle School",
    "wof:placetype":"venue"
},
  "geometry": {"coordinates":[-83.601539,32.859657],"type":"Point"}
}