{
  "type": "Feature",
  "properties": {
    "iso:country":"US",
    "sg:address":"1308 Hogansville Rd",
    "sg:city":"Lagrange",
    "sg:classifiers":[
        {
            "category":"Personal",
            "subcategory":"Beauty Salon",
            "type":"Services"
        }
    ],
    "sg:phone":"+1 706 882 0990",
    "sg:postcode":"30241",
    "sg:province":"GA",
    "sg:tags":[
        "manicuring"
    ],
    "wof:name":"Anthony's Nail",
    "wof:placetype":"venue"
},
  "geometry": {"coordinates":[-84.99881000000001,33.05475],"type":"Point"}
}