{
  "type": "Feature",
  "properties": {
    "iso:country":"US",
    "sg:address":"1807 Connally Dr",
    "sg:city":"Atlanta",
    "sg:classifiers":[
        {
            "category":"Taxi",
            "type":"Transportation"
        }
    ],
    "sg:phone":"+1 912 964 9494",
    "sg:postcode":"30344",
    "sg:province":"GA",
    "wof:name":"Sunshine Taxi 24-7",
    "wof:placetype":"venue"
},
  "geometry": {"coordinates":[-84.447413,33.690361],"type":"Point"}
}