{
  "type": "Feature",
  "properties": {
    "addr:full":"1226 Ponce de Leon Ave NE Atlanta GA 30306",
    "addr:housenumber":"1226",
    "addr:postcode":"30306",
    "addr:street":"Ponce De Leon Ave Ne",
    "iso:country":"US",
    "sg:address":"1226 Ponce de Leon Ave NE",
    "sg:city":"Atlanta",
    "sg:classifiers":[
        {
            "category":"Home & Garden",
            "subcategory":"Hardware",
            "type":"Retail Goods"
        }
    ],
    "sg:phone":"+1 404 607 0080",
    "sg:postcode":"30306",
    "sg:province":"GA",
    "wof:name":"Home Improvement Super Store",
    "wof:placetype":"venue"
},
  "geometry": {"coordinates":[-84.346892,33.774408],"type":"Point"}
}