{
  "type": "Feature",
  "properties": {
    "iso:country":"US",
    "sg:address":"500 Wedowee St",
    "sg:city":"Bowdon",
    "sg:classifiers":[
        {
            "category":"Wholesale",
            "subcategory":"Auto Parts",
            "type":"Manufacturing & Wholesale Goods"
        }
    ],
    "sg:phone":"+1 770 258 5551",
    "sg:postcode":"30108",
    "sg:province":"GA",
    "sg:tags":[
        "tire"
    ],
    "sg:website":"www.trintex.com",
    "wof:name":"Carlisle Tire & Wheel Co",
    "wof:placetype":"venue"
},
  "geometry": {"coordinates":[-85.25314400000001,33.532669],"type":"Point"}
}