{
  "type": "Feature",
  "properties": {
    "addr:full":"510 Veterans Memorial Pkwy SW Mableton GA 30126",
    "addr:housenumber":"510",
    "addr:postcode":"30126",
    "addr:street":"Veterans Memorial Pkwy Sw",
    "iso:country":"US",
    "sg:address":"510 Veterans Memorial Pkwy SW",
    "sg:city":"Mableton",
    "sg:classifiers":[
        {
            "category":"Autos & Motor Vehicles",
            "subcategory":"Automobile Sales",
            "type":"Retail Goods"
        }
    ],
    "sg:phone":"+1 770 948 9696",
    "sg:postcode":"30126",
    "sg:province":"GA",
    "sg:tags":[
        "used",
        "car",
        "pickup",
        "parts",
        "truck",
        "new",
        "dealer"
    ],
    "wof:name":"Lee Lewis Motor Co Inc",
    "wof:placetype":"venue"
},
  "geometry": {"coordinates":[-84.56930199999999,33.817353],"type":"Point"}
}