{
  "type": "Feature",
  "properties": {
    "addr:full":"51 S Jackson St Winder GA 30680",
    "addr:housenumber":"51",
    "addr:postcode":"30680",
    "addr:street":"S Jackson St",
    "iso:country":"US",
    "sg:address":"51 S Jackson St",
    "sg:city":"Winder",
    "sg:classifiers":[
        {
            "category":"Shopping",
            "subcategory":"Discount & Variety Stores",
            "type":"Retail Goods"
        },
        {
            "category":"Personal",
            "type":"Services"
        }
    ],
    "sg:phone":"+1 678 425 9938",
    "sg:postcode":"30680",
    "sg:province":"GA",
    "sg:tags":[
        "wrapping",
        "gift"
    ],
    "wof:name":"Sara's Place",
    "wof:placetype":"venue"
},
  "geometry": {"coordinates":[-83.724419,33.987007],"type":"Point"}
}