{
  "type": "Feature",
  "properties": {
    "iso:country":"US",
    "sg:address":"1430 Mineral Springs Rd",
    "sg:city":"Hoschton",
    "sg:classifiers":[
        {
            "category":"Shopping",
            "subcategory":"Gifts & Souvenirs",
            "type":"Retail Goods"
        }
    ],
    "sg:phone":"+1 678 546 8679",
    "sg:postcode":"30548",
    "sg:province":"GA",
    "wof:name":"Josettes Gifts & Things",
    "wof:placetype":"venue"
},
  "geometry": {"coordinates":[-83.877927,34.057874],"type":"Point"}
}