{
  "type": "Feature",
  "properties": {
    "iso:country":"US",
    "sg:address":"6435 Water Oak Ct",
    "sg:city":"Cumming",
    "sg:classifiers":[
        {
            "category":"Professional",
            "type":"Services"
        }
    ],
    "sg:phone":"+1 770 772 6363",
    "sg:postcode":"30040",
    "sg:province":"GA",
    "wof:name":"J William Gunby Inc",
    "wof:placetype":"venue"
},
  "geometry": {"coordinates":[-84.247062,34.176965],"type":"Point"}
}