{
  "type": "Feature",
  "properties": {
    "addr:full":"13 Saint Claire Ln NE Atlanta GA 30324",
    "addr:housenumber":"13",
    "addr:postcode":"30324",
    "addr:street":"Saint Claire Ln Ne",
    "iso:country":"US",
    "sg:address":"13 Saint Claire Ln NE",
    "sg:city":"Atlanta",
    "sg:classifiers":[
        {
            "category":"Shopping",
            "subcategory":"Florist",
            "type":"Retail Goods"
        }
    ],
    "sg:phone":"+1 404 233 9469",
    "sg:postcode":"30324",
    "sg:province":"GA",
    "wof:name":"Cullowhee Flowers & Gifts",
    "wof:placetype":"venue"
},
  "geometry": {"coordinates":[-84.355121,33.83071],"type":"Point"}
}