{
  "type": "Feature",
  "properties": {
    "addr:full":"3574 Oakvale Falls Ct Decatur GA 30034",
    "addr:housenumber":"3574",
    "addr:postcode":"30034",
    "addr:street":"Oakvale Falls Ct",
    "iso:country":"US",
    "sg:address":"3574 Oakvale Falls Ct",
    "sg:city":"Decatur",
    "sg:classifiers":[
        {
            "category":"Real Estate",
            "subcategory":"Real Estate Agent",
            "type":"Services"
        }
    ],
    "sg:phone":"+1 404 223 9891",
    "sg:postcode":"30034",
    "sg:province":"GA",
    "wof:name":"Wagner Enterprises",
    "wof:placetype":"venue"
},
  "geometry": {"coordinates":[-84.27439200000001,33.678066],"type":"Point"}
}