{
  "type": "Feature",
  "properties": {
    "addr:full":"3335 Steve Reynolds Blvd Duluth GA 30096",
    "addr:housenumber":"3335",
    "addr:postcode":"30096",
    "addr:street":"Steve Reynolds Blvd",
    "iso:country":"US",
    "sg:address":"3335 Steve Reynolds Blvd",
    "sg:city":"Duluth",
    "sg:classifiers":[
        {
            "category":"Restaurant",
            "type":"Food & Drink"
        }
    ],
    "sg:menulink":"http://www.allmenus.com/ga/suwanee-duluth/55054-waffle-house/menu/",
    "sg:phone":"+1 770 623 0892",
    "sg:postcode":"30096",
    "sg:province":"GA",
    "sg:tags":[
        "american"
    ],
    "wof:name":"Waffle House",
    "wof:placetype":"venue"
},
  "geometry": {"coordinates":[-84.141339,33.955051],"type":"Point"}
}