{
  "type": "Feature",
  "properties": {
    "iso:country":"US",
    "sg:address":"5837 Stewart Pkwy",
    "sg:city":"Douglasville",
    "sg:classifiers":[
        {
            "category":"Building & Trades",
            "subcategory":"Construction",
            "type":"Services"
        }
    ],
    "sg:phone":"+1 770 489 3234",
    "sg:postcode":"30135",
    "sg:province":"GA",
    "sg:tags":[
        "resurfacing",
        "laying",
        "refinishing",
        "floor"
    ],
    "wof:name":"Hardwood Flooring Depot",
    "wof:placetype":"venue"
},
  "geometry": {"coordinates":[-84.76488999999999,33.718451],"type":"Point"}
}