{
  "type": "Feature",
  "properties": {
    "iso:country":"US",
    "sg:address":"4690 S Old Peachtree Rd NW",
    "sg:city":"Norcross",
    "sg:classifiers":[
        {
            "category":"Wholesale",
            "subcategory":"Hardware",
            "type":"Manufacturing & Wholesale Goods"
        }
    ],
    "sg:phone":"+1 678 969 9147",
    "sg:postcode":"30071",
    "sg:province":"GA",
    "sg:tags":[
        "product",
        "retail",
        "cutlery"
    ],
    "wof:name":"Thunderforge",
    "wof:placetype":"venue"
},
  "geometry": {"coordinates":[-84.18745800000001,33.966775],"type":"Point"}
}