{
  "type": "Feature",
  "properties": {
    "iso:country":"US",
    "sg:address":"5430 Truman Mountain Rd",
    "sg:city":"Gainesville",
    "sg:classifiers":[
        {
            "category":"Banks & Credit Unions",
            "subcategory":"Bank",
            "type":"Services"
        }
    ],
    "sg:phone":"+1 770 886 0281",
    "sg:postcode":"30506",
    "sg:province":"GA",
    "sg:tags":[
        "mortgage"
    ],
    "wof:name":"Action Processing",
    "wof:placetype":"venue"
},
  "geometry": {"coordinates":[-83.957509,34.314645],"type":"Point"}
}