{
  "type": "Feature",
  "properties": {
    "iso:country":"US",
    "sg:address":"6620 Bay Cir",
    "sg:city":"Norcross",
    "sg:classifiers":[
        {
            "category":"Professional",
            "subcategory":"Computer Services",
            "type":"Services"
        }
    ],
    "sg:phone":"+1 770 448 8900",
    "sg:postcode":"30071",
    "sg:province":"GA",
    "sg:tags":[
        "processing",
        "datum"
    ],
    "wof:name":"Federated Systems Group",
    "wof:placetype":"venue"
},
  "geometry": {"coordinates":[-84.246683,33.935309],"type":"Point"}
}