{
  "type": "Feature",
  "properties": {
    "iso:country":"US",
    "sg:address":"2501 Cobb Pkwy NW",
    "sg:city":"Kennesaw",
    "sg:classifiers":[
        {
            "category":"Restaurant",
            "type":"Food & Drink"
        }
    ],
    "sg:menulink":"http://www.allmenus.com/ga/acworth-kennesaw/94782-joes-crab-shack/menu/",
    "sg:phone":"+1 770 429 7703",
    "sg:postcode":"30152",
    "sg:province":"GA",
    "sg:tags":[
        "seafood",
        "american"
    ],
    "wof:name":"Joe's Crab Shack",
    "wof:placetype":"venue"
},
  "geometry": {"coordinates":[-84.615103,34.015158],"type":"Point"}
}