{
  "type": "Feature",
  "properties": {
    "iso:country":"US",
    "sg:address":"1250 N Hill St",
    "sg:city":"Griffin",
    "sg:classifiers":[
        {
            "category":"Restaurant",
            "type":"Food & Drink"
        }
    ],
    "sg:phone":"+1 678 688 5551",
    "sg:postcode":"30223",
    "sg:province":"GA",
    "wof:name":"Rita's Grill",
    "wof:placetype":"venue"
},
  "geometry": {"coordinates":[-84.26141800000001,33.268352],"type":"Point"}
}