{
  "type": "Feature",
  "properties": {
    "addr:full":"679 Powder Springs St SE Smyrna GA 30080",
    "addr:housenumber":"679",
    "addr:postcode":"30080",
    "addr:street":"Powder Springs St Se",
    "iso:country":"US",
    "sg:address":"679 Powder Springs St SE",
    "sg:city":"Smyrna",
    "sg:classifiers":[
        {
            "category":"Retail",
            "subcategory":"Auto Repair",
            "type":"Services"
        }
    ],
    "sg:phone":"+1 770 428 3876",
    "sg:postcode":"30080",
    "sg:province":"GA",
    "sg:tags":[
        "repairing",
        "automobile"
    ],
    "wof:name":"Import Service",
    "wof:placetype":"venue"
},
  "geometry": {"coordinates":[-84.533503,33.887469],"type":"Point"}
}