{
  "type": "Feature",
  "properties": {
    "iso:country":"US",
    "sg:address":"5751 Little Mill Rd",
    "sg:city":"Buford",
    "sg:classifiers":[
        {
            "category":"Restaurant",
            "type":"Food & Drink"
        }
    ],
    "sg:phone":"+1 770 614 0441",
    "sg:postcode":"30518",
    "sg:province":"GA",
    "sg:tags":[
        "pizza"
    ],
    "wof:name":"Pizza Di Folco",
    "wof:placetype":"venue"
},
  "geometry": {"coordinates":[-84.019096,34.139301],"type":"Point"}
}