{
  "type": "Feature",
  "properties": {
    "addr:full":"114 Washington St SE Gainesville GA 30501",
    "addr:housenumber":"114",
    "addr:postcode":"30501",
    "addr:street":"Washington St Se;Ga",
    "iso:country":"US",
    "sg:address":"114 Washington St SE",
    "sg:city":"Gainesville",
    "sg:classifiers":[
        {
            "category":"Personal",
            "subcategory":"Beauty Salon",
            "type":"Services"
        }
    ],
    "sg:phone":"+1 770 536 1822",
    "sg:postcode":"30501",
    "sg:province":"GA",
    "sg:tags":[
        "manicuring"
    ],
    "wof:name":"Natural Nails",
    "wof:placetype":"venue"
},
  "geometry": {"coordinates":[-83.82588800000001,34.300215],"type":"Point"}
}