{
  "type": "Feature",
  "properties": {
    "iso:country":"US",
    "sg:address":"228 Riverview Trl",
    "sg:city":"Roswell",
    "sg:classifiers":[
        {
            "category":"Communications",
            "subcategory":"Film & Video Production",
            "type":"Services"
        }
    ],
    "sg:phone":"+1 770 518 4744",
    "sg:postcode":"30075",
    "sg:province":"GA",
    "sg:tags":[
        "motion"
    ],
    "wof:name":"Encore Encore Productions Inc",
    "wof:placetype":"venue"
},
  "geometry": {"coordinates":[-84.35849899999999,34.005808],"type":"Point"}
}