{
  "type": "Feature",
  "properties": {
    "addr:full":"5801 Goshen Springs Rd Norcross GA 30071",
    "addr:housenumber":"5801",
    "addr:postcode":"30071",
    "addr:street":"Goshen Springs Rd",
    "iso:country":"US",
    "sg:address":"5801 Goshen Springs Rd",
    "sg:city":"Norcross",
    "sg:classifiers":[
        {
            "category":"Manufacturing",
            "subcategory":"Printing",
            "type":"Manufacturing & Wholesale Goods"
        }
    ],
    "sg:phone":"+1 770 417 1727",
    "sg:postcode":"30071",
    "sg:province":"GA",
    "sg:tags":[
        "printer",
        "commercial",
        "offset"
    ],
    "sg:website":"www.olympicprinting.net",
    "wof:name":"Olympic Printing",
    "wof:placetype":"venue"
},
  "geometry": {"coordinates":[-84.202878,33.91705],"type":"Point"}
}