{
  "type": "Feature",
  "properties": {
    "iso:country":"US",
    "sg:address":"6158 Mill Branch Rd",
    "sg:city":"Columbus",
    "sg:classifiers":[
        {
            "category":"Professional",
            "subcategory":"Management & Consulting",
            "type":"Services"
        }
    ],
    "sg:phone":"+1 706 565 0023",
    "sg:postcode":"31907",
    "sg:province":"GA",
    "sg:tags":[
        "employment",
        "screening"
    ],
    "wof:name":"H & H Svc Inc",
    "wof:placetype":"venue"
},
  "geometry": {"coordinates":[-84.884641,32.471304],"type":"Point"}
}