{
  "type": "Feature",
  "properties": {
    "addr:full":"233 Peachtree St NE Ste 2 Atlanta GA 30303",
    "addr:housenumber":"233",
    "addr:postcode":"30303",
    "addr:street":"Peachtree St Ne Ste 2",
    "iso:country":"US",
    "sg:address":"233 Peachtree St NE Ste 2",
    "sg:city":"Atlanta",
    "sg:classifiers":[
        {
            "category":"Organizations",
            "subcategory":"Community Association",
            "type":"Services"
        }
    ],
    "sg:phone":"+1 404 622 2467",
    "sg:postcode":"30303",
    "sg:province":"GA",
    "wof:name":"Park Place South Community Association, Inc.",
    "wof:placetype":"venue"
},
  "geometry": {"coordinates":[-84.395263,33.748091],"type":"Point"}
}