{
  "type": "Feature",
  "properties": {
    "addr:full":"1756 Stillwood Forest Drive Atlanta GA 30047",
    "addr:housenumber":"1756",
    "addr:postcode":"30047",
    "addr:street":"Stillwood Forest Drive",
    "iso:country":"US",
    "sg:address":"1756 Stillwood Forest Drive",
    "sg:city":"Atlanta",
    "sg:classifiers":[
        {
            "category":"Professional",
            "subcategory":"Lawyer & Legal Services",
            "type":"Services"
        }
    ],
    "sg:phone":"+1 404 963 8742",
    "sg:postcode":"30047",
    "sg:province":"GA",
    "sg:tags":[
        "paralegal",
        "paralegals",
        "law",
        "legal-assistants",
        "legal"
    ],
    "sg:website":"http://www.ParalegalGateway.com",
    "wof:name":"ParalegalGateway",
    "wof:placetype":"venue"
},
  "geometry": {"coordinates":[-84.110243,33.837337],"type":"Point"}
}