{
  "type": "Feature",
  "properties": {
    "addr:full":"1695 Luke Edwards Rd Dacula GA 30019",
    "addr:housenumber":"1695",
    "addr:postcode":"ga 30019",
    "addr:street":"Luke Edwards Rd",
    "iso:country":"US",
    "sg:address":"1695 Luke Edwards Rd",
    "sg:city":"Dacula",
    "sg:classifiers":[
        {
            "category":"Building & Trades",
            "subcategory":"Electrical",
            "type":"Services"
        }
    ],
    "sg:phone":"+1 770 616 8492",
    "sg:postcode":"30019",
    "sg:province":"GA",
    "sg:tags":[
        "electrical",
        "contractor"
    ],
    "wof:name":"Electrical Contract Service",
    "wof:placetype":"venue"
},
  "geometry": {"coordinates":[-83.877307,33.948963],"type":"Point"}
}