{
  "type": "Feature",
  "properties": {
    "iso:country":"US",
    "sg:address":"2638 Woodwin Rd",
    "sg:city":"Atlanta",
    "sg:classifiers":[
        {
            "category":"Building & Trades",
            "subcategory":"Landscaping Services",
            "type":"Services"
        }
    ],
    "sg:phone":"+1 404 845 0076",
    "sg:postcode":"30360",
    "sg:province":"GA",
    "sg:tags":[
        "consulting",
        "business"
    ],
    "wof:name":"Land Wizard",
    "wof:placetype":"venue"
},
  "geometry": {"coordinates":[-84.27953599999999,33.918912],"type":"Point"}
}