{
  "type": "Feature",
  "properties": {
    "addr:full":"1246 Old Henry Grady Rd Dawsonville GA 30534",
    "addr:housenumber":"1246",
    "addr:postcode":"30534",
    "addr:street":"Old Henry Grady Rd",
    "iso:country":"US",
    "sg:address":"1246 Old Henry Grady Rd",
    "sg:city":"Dawsonville",
    "sg:classifiers":[
        {
            "category":"Retail",
            "subcategory":"Auto Repair",
            "type":"Services"
        }
    ],
    "sg:phone":"+1 706 265 7180",
    "sg:postcode":"30534",
    "sg:province":"GA",
    "sg:tags":[
        "body",
        "automobile",
        "painting"
    ],
    "wof:name":"Stevie Sheriff Auto Works",
    "wof:placetype":"venue"
},
  "geometry": {"coordinates":[-84.1606,34.46633],"type":"Point"}
}