{
  "type": "Feature",
  "properties": {
    "iso:country":"US",
    "sg:address":"1683 Defoor Cir NW",
    "sg:city":"Atlanta",
    "sg:classifiers":[
        {
            "category":"Food & Beverages",
            "subcategory":"Specialty",
            "type":"Retail Goods"
        }
    ],
    "sg:phone":"+1 404 355 0029",
    "sg:postcode":"30318",
    "sg:province":"GA",
    "sg:tags":[
        "vitamin"
    ],
    "wof:name":"Saturn Supplements",
    "wof:placetype":"venue"
},
  "geometry": {"coordinates":[-84.420193,33.800473],"type":"Point"}
}