{
  "type": "Feature",
  "properties": {
    "iso:country":"US",
    "sg:address":"4640 Warm Springs Rd",
    "sg:city":"Columbus",
    "sg:classifiers":[
        {
            "category":"Building & Trades",
            "subcategory":"Electrical",
            "type":"Services"
        }
    ],
    "sg:phone":"+1 706 562 1748",
    "sg:postcode":"31909",
    "sg:province":"GA",
    "sg:tags":[
        "electrical",
        "contractor"
    ],
    "wof:name":"Grantham Electric Co",
    "wof:placetype":"venue"
},
  "geometry": {"coordinates":[-84.915335,32.524132],"type":"Point"}
}