{
  "type": "Feature",
  "properties": {
    "iso:country":"US",
    "sg:address":"5894 Love St",
    "sg:city":"Austell",
    "sg:classifiers":[
        {
            "category":"Professional",
            "subcategory":"Lawyer & Legal Services",
            "type":"Services"
        },
        {
            "category":"Banks & Credit Unions",
            "subcategory":"Atm",
            "type":"Services"
        }
    ],
    "sg:phone":"+1 770 732 1621",
    "sg:postcode":"30168",
    "sg:province":"GA",
    "sg:tags":[
        "personal",
        "injury",
        "bankruptcy"
    ],
    "wof:name":"Clark & Washington PC Attorneys At Law",
    "wof:placetype":"venue"
},
  "geometry": {"coordinates":[-84.634102,33.811199],"type":"Point"}
}