{
  "type": "Feature",
  "properties": {
    "addr:full":"2012 Gainsborough Dr # 101 Atlanta GA 30341",
    "addr:housenumber":"2012",
    "addr:postcode":"30341",
    "addr:street":"Gainsborough Dr # 101",
    "iso:country":"US",
    "sg:address":"2012 Gainsborough Dr # 101",
    "sg:city":"Atlanta",
    "sg:classifiers":[
        {
            "category":"Building & Trades",
            "subcategory":"Construction",
            "type":"Services"
        }
    ],
    "sg:phone":"+1 770 986 7838",
    "sg:postcode":"30341",
    "sg:province":"GA",
    "sg:tags":[
        "contractor",
        "mechanical"
    ],
    "wof:name":"James Corwell Mechanical Contracting Inc",
    "wof:placetype":"venue"
},
  "geometry": {"coordinates":[-84.308891,33.91623],"type":"Point"}
}