{
  "type": "Feature",
  "properties": {
    "iso:country":"US",
    "sg:address":"5058 Verbena Dr",
    "sg:city":"Acworth",
    "sg:classifiers":[
        {
            "category":"Professional",
            "subcategory":"Management & Consulting",
            "type":"Services"
        }
    ],
    "sg:phone":"+1 770 329 1630",
    "sg:postcode":"30102",
    "sg:province":"GA",
    "sg:tags":[
        "business"
    ],
    "wof:name":"Free Your Mind Consulting",
    "wof:placetype":"venue"
},
  "geometry": {"coordinates":[-84.568968,34.066253],"type":"Point"}
}