{
  "type": "Feature",
  "properties": {
    "addr:full":"4282 Fairfax Dr Macon GA 31206",
    "addr:housenumber":"4282",
    "addr:postcode":"31206",
    "addr:street":"Fairfax Dr",
    "iso:country":"US",
    "sg:address":"4282 Fairfax Dr",
    "sg:city":"Macon",
    "sg:classifiers":[
        {
            "category":"Building & Trades",
            "subcategory":"Cleaning & Sanitation",
            "type":"Services"
        }
    ],
    "sg:phone":"+1 478 785 0912",
    "sg:postcode":"31206",
    "sg:province":"GA",
    "sg:tags":[
        "janitor"
    ],
    "wof:name":"Alco Cleaning Systems",
    "wof:placetype":"venue"
},
  "geometry": {"coordinates":[-83.69747700000001,32.782983],"type":"Point"}
}