{
  "type": "Feature",
  "properties": {
    "addr:full":"2993 Wren Cir NW Kennesaw GA 30144",
    "addr:housenumber":"2993",
    "addr:postcode":"30144",
    "addr:street":"Wren Cir Nw",
    "iso:country":"US",
    "sg:address":"2993 Wren Cir NW",
    "sg:city":"Kennesaw",
    "sg:classifiers":[
        {
            "category":"Communications",
            "type":"Services"
        }
    ],
    "sg:phone":"+1 770 427 2025",
    "sg:postcode":"30144",
    "sg:province":"GA",
    "sg:tags":[
        "communication"
    ],
    "wof:name":"DOT Communications Inc",
    "wof:placetype":"venue"
},
  "geometry": {"coordinates":[-84.638372,34.029804],"type":"Point"}
}