{
  "type": "Feature",
  "properties": {
    "iso:country":"US",
    "sg:address":"2890 Laguna Dr",
    "sg:city":"Decatur",
    "sg:classifiers":[
        {
            "category":"Building & Trades",
            "subcategory":"Construction",
            "type":"Services"
        }
    ],
    "sg:phone":"+1 404 286 0484",
    "sg:postcode":"30032",
    "sg:province":"GA",
    "sg:tags":[
        "contractor"
    ],
    "wof:name":"Lee & Sons Masonry Inc",
    "wof:placetype":"venue"
},
  "geometry": {"coordinates":[-84.272034,33.749409],"type":"Point"}
}