{
  "type": "Feature",
  "properties": {
    "addr:full":"2 Yellow Warbler Ct Savannah GA 31419",
    "addr:housenumber":"2",
    "addr:postcode":"31419",
    "addr:street":"Yellow Warbler Ct",
    "iso:country":"US",
    "sg:address":"2 Yellow Warbler Ct",
    "sg:city":"Savannah",
    "sg:classifiers":[
        {
            "category":"Real Estate",
            "subcategory":"Real Estate Agent",
            "type":"Services"
        }
    ],
    "sg:phone":"+1 912 925 5466",
    "sg:postcode":"31419",
    "sg:province":"GA",
    "wof:name":"Tnc Properties",
    "wof:placetype":"venue"
},
  "geometry": {"coordinates":[-81.25953199999999,32.007889],"type":"Point"}
}