{
  "type": "Feature",
  "properties": {
    "iso:country":"US",
    "sg:address":"625 E Broad Ave",
    "sg:city":"Albany",
    "sg:classifiers":[
        {
            "category":"Retail",
            "subcategory":"Auto Repair",
            "type":"Services"
        }
    ],
    "sg:phone":"+1 229 435 4266",
    "sg:postcode":"31705",
    "sg:province":"GA",
    "sg:tags":[
        "body"
    ],
    "wof:name":"Singleton Paint & Body Shop",
    "wof:placetype":"venue"
},
  "geometry": {"coordinates":[-84.13727900000001,31.576295],"type":"Point"}
}