{
  "type": "Feature",
  "properties": {
    "iso:country":"US",
    "sg:address":"1070 Stewart Rd",
    "sg:city":"Ringgold",
    "sg:classifiers":[
        {
            "category":"Home & Garden",
            "subcategory":"Carpets & Floor Coverings",
            "type":"Retail Goods"
        }
    ],
    "sg:phone":"+1 706 937 4483",
    "sg:postcode":"30736",
    "sg:province":"GA",
    "wof:name":"Eastside Carpets Inc",
    "wof:placetype":"venue"
},
  "geometry": {"coordinates":[-85.002568,34.962752],"type":"Point"}
}