{
  "type": "Feature",
  "properties": {
    "addr:full":"22 Planters Dr SW Lilburn GA 30047",
    "addr:housenumber":"22",
    "addr:postcode":"30047",
    "addr:street":"Planters Dr Sw",
    "iso:country":"US",
    "sg:address":"22 Planters Dr SW",
    "sg:city":"Lilburn",
    "sg:classifiers":[
        {
            "category":"Real Estate",
            "subcategory":"Real Estate Services",
            "type":"Services"
        },
        {
            "category":"Real Estate",
            "subcategory":"Real Estate Agent",
            "type":"Services"
        },
        {
            "category":"Professional",
            "type":"Services"
        }
    ],
    "sg:phone":"+1 770 381 2489",
    "sg:postcode":"30047",
    "sg:province":"GA",
    "sg:tags":[
        "buyer",
        "commercial",
        "management",
        "relocation",
        "broker"
    ],
    "sg:website":"http://www.lilburnrealty.com",
    "wof:name":"Lilburn Realty, LLC",
    "wof:placetype":"venue"
},
  "geometry": {"coordinates":[-84.148842,33.878719],"type":"Point"}
}