{
  "type": "Feature",
  "properties": {
    "addr:full":"2170 Satellite Blvd Ste 200 Duluth GA 30097",
    "addr:housenumber":"2170",
    "addr:postcode":"30097",
    "addr:street":"Satellite Blvd Ste 200",
    "iso:country":"US",
    "sg:address":"2170 Satellite Blvd Ste 200",
    "sg:city":"Duluth",
    "sg:classifiers":[
        {
            "category":"Banks & Credit Unions",
            "subcategory":"Financial Services",
            "type":"Services"
        }
    ],
    "sg:phone":"+1 678 475 6700",
    "sg:postcode":"30097",
    "sg:province":"GA",
    "sg:tags":[
        "broker",
        "mortgage"
    ],
    "wof:name":"Homebanc Mortgage Corporation",
    "wof:placetype":"venue"
},
  "geometry": {"coordinates":[-84.092697,33.983398],"type":"Point"}
}