{
  "type": "Feature",
  "properties": {
    "addr:full":"1080 Big A Rd S Toccoa GA 30577",
    "addr:housenumber":"1080",
    "addr:postcode":"30577",
    "addr:street":"Big A Rd",
    "iso:country":"US",
    "sg:address":"1080 Big A Rd S",
    "sg:city":"Toccoa",
    "sg:classifiers":[
        {
            "category":"Shopping",
            "subcategory":"Department Store",
            "type":"Retail Goods"
        }
    ],
    "sg:phone":"+1 706 886 1422",
    "sg:postcode":"30577",
    "sg:province":"GA",
    "wof:name":"Goody's",
    "wof:placetype":"venue"
},
  "geometry": {"coordinates":[-83.299408,34.565647],"type":"Point"}
}