{
  "type": "Feature",
  "properties": {
    "iso:country":"US",
    "sg:address":"32 Pier Rd",
    "sg:city":"Jekyll Island",
    "sg:classifiers":[
        {
            "category":"Shopping",
            "subcategory":"Gifts & Souvenirs",
            "type":"Retail Goods"
        }
    ],
    "sg:phone":"+1 912 635 2643",
    "sg:postcode":"31527",
    "sg:province":"GA",
    "sg:tags":[
        "shop"
    ],
    "wof:name":"Cottage On Jekyll",
    "wof:placetype":"venue"
},
  "geometry": {"coordinates":[-81.420907,31.059016],"type":"Point"}
}