{
  "type": "Feature",
  "properties": {
    "iso:country":"US",
    "sg:address":"4154 Silver Peak Pkwy",
    "sg:city":"Suwanee",
    "sg:classifiers":[
        {
            "category":"Building & Trades",
            "subcategory":"Construction",
            "type":"Services"
        }
    ],
    "sg:phone":"+1 770 831 6261",
    "sg:postcode":"30024",
    "sg:province":"GA",
    "sg:tags":[
        "interior",
        "design"
    ],
    "wof:name":"Harcrest Homes Design Center",
    "wof:placetype":"venue"
},
  "geometry": {"coordinates":[-84.081997,34.055761],"type":"Point"}
}