{
  "type": "Feature",
  "properties": {
    "addr:full":"3021 Heritage Rd Milledgeville GA 31061",
    "addr:housenumber":"3021",
    "addr:postcode":"31061",
    "addr:street":"Heritage Rd",
    "iso:country":"US",
    "sg:address":"3021 Heritage Rd",
    "sg:city":"Milledgeville",
    "sg:classifiers":[
        {
            "category":"Recreation",
            "type":"Entertainment"
        }
    ],
    "sg:phone":"+1 478 452 6853",
    "sg:postcode":"31061",
    "sg:province":"GA",
    "wof:name":"Rocket Roller Rink",
    "wof:placetype":"venue"
},
  "geometry": {"coordinates":[-83.26111299999999,33.119148],"type":"Point"}
}