{
  "type": "Feature",
  "properties": {
    "addr:full":"3060 Royal Blvd S Alpharetta GA 30022",
    "addr:housenumber":"3060",
    "addr:postcode":"30022",
    "addr:street":"Royal Blvd S",
    "iso:country":"US",
    "sg:address":"3060 Royal Blvd S",
    "sg:city":"Alpharetta",
    "sg:classifiers":[
        {
            "category":"Banks & Credit Unions",
            "subcategory":"Bank",
            "type":"Services"
        }
    ],
    "sg:phone":"+1 770 343 8177",
    "sg:postcode":"30022",
    "sg:province":"GA",
    "wof:name":"First National Bank",
    "wof:placetype":"venue"
},
  "geometry": {"coordinates":[-84.272487,34.053495],"type":"Point"}
}