{
  "type": "Feature",
  "properties": {
    "addr:full":"3250 Peachtree Corners Cir Norcross GA 30092",
    "addr:housenumber":"3250",
    "addr:postcode":"30092",
    "addr:street":"Peachtree Corners Cir",
    "iso:country":"US",
    "sg:address":"3250 Peachtree Corners Cir",
    "sg:city":"Norcross",
    "sg:classifiers":[
        {
            "category":"Retail",
            "subcategory":"Repair Shop",
            "type":"Services"
        }
    ],
    "sg:phone":"+1 770 441 9088",
    "sg:postcode":"30092",
    "sg:province":"GA",
    "sg:tags":[
        "watch"
    ],
    "wof:name":"It's About Time",
    "wof:placetype":"venue"
},
  "geometry": {"coordinates":[-84.25058300000001,33.944244],"type":"Point"}
}