{
  "type": "Feature",
  "properties": {
    "addr:full":"4319 Covington Hwy Ste 217 Decatur GA 30035",
    "addr:housenumber":"4319",
    "addr:postcode":"30035",
    "addr:street":"Covington Hwy Ste 217",
    "iso:country":"US",
    "sg:address":"4319 Covington Hwy Ste 217",
    "sg:city":"Decatur",
    "sg:classifiers":[
        {
            "category":"Banks & Credit Unions",
            "subcategory":"Financial Services",
            "type":"Services"
        }
    ],
    "sg:phone":"+1 404 289 5574",
    "sg:postcode":"30035",
    "sg:province":"GA",
    "sg:tags":[
        "broker",
        "mortgage"
    ],
    "wof:name":"Consumers Financial Options Inc",
    "wof:placetype":"venue"
},
  "geometry": {"coordinates":[-84.226997,33.749802],"type":"Point"}
}