{
  "type": "Feature",
  "properties": {
    "iso:country":"US",
    "sg:address":"3468 Bailey Rd",
    "sg:city":"Dacula",
    "sg:classifiers":[
        {
            "category":"Shopping",
            "subcategory":"Gifts & Souvenirs",
            "type":"Retail Goods"
        }
    ],
    "sg:phone":"+1 770 963 9709",
    "sg:postcode":"30019",
    "sg:province":"GA",
    "sg:tags":[
        "shop"
    ],
    "wof:name":"Especially For You",
    "wof:placetype":"venue"
},
  "geometry": {"coordinates":[-83.874049,34.014743],"type":"Point"}
}