{
  "type": "Feature",
  "properties": {
    "addr:full":"127 Pioneer Trl Arlington GA 31768",
    "addr:housenumber":"127",
    "addr:postcode":"31768",
    "addr:street":"Pioneer Trl",
    "iso:country":"US",
    "sg:address":"127 Pioneer Trl",
    "sg:city":"Arlington",
    "sg:classifiers":[
        {
            "category":"Personal",
            "subcategory":"Beauty Salon",
            "type":"Services"
        }
    ],
    "sg:phone":"+1 229 725 4731",
    "sg:postcode":"31768",
    "sg:province":"GA",
    "wof:name":"B & B Beauty Shop",
    "wof:placetype":"venue"
},
  "geometry": {"coordinates":[-83.756242,31.136774],"type":"Point"}
}