{
  "type": "Feature",
  "properties": {
    "iso:country":"US",
    "sg:address":"927 Quaker Rd",
    "sg:city":"Waynesboro",
    "sg:classifiers":[
        {
            "category":"Professional",
            "type":"Services"
        }
    ],
    "sg:phone":"+1 706 554 2445",
    "sg:postcode":"30830",
    "sg:province":"GA",
    "wof:name":"Michelles",
    "wof:placetype":"venue"
},
  "geometry": {"coordinates":[-82.022571,33.094935],"type":"Point"}
}