{
  "type": "Feature",
  "properties": {
    "addr:full":"3435 Breckinridge Blvd Duluth GA 30096",
    "addr:housenumber":"3435",
    "addr:postcode":"30096",
    "addr:street":"Breckinridge Blvd",
    "iso:country":"US",
    "sg:address":"3435 Breckinridge Blvd",
    "sg:city":"Duluth",
    "sg:classifiers":[
        {
            "category":"Wholesale",
            "subcategory":"Computers",
            "type":"Manufacturing & Wholesale Goods"
        },
        {
            "category":"Manufacturing",
            "subcategory":"Tools & Machinery",
            "type":"Manufacturing & Wholesale Goods"
        }
    ],
    "sg:phone":"+1 770 923 9533",
    "sg:postcode":"30096",
    "sg:province":"GA",
    "sg:tags":[
        "equipment",
        "peripheral",
        "mfg"
    ],
    "wof:name":"Tekvisions Inc",
    "wof:placetype":"venue"
},
  "geometry": {"coordinates":[-84.122094,33.953595],"type":"Point"}
}