{
  "type": "Feature",
  "properties": {
    "iso:country":"US",
    "sg:address":"4129 Magnolia Glen Walk",
    "sg:city":"Norcross",
    "sg:classifiers":[
        {
            "category":"Manufacturing",
            "subcategory":"Textiles",
            "type":"Manufacturing & Wholesale Goods"
        }
    ],
    "sg:phone":"+1 404 433 3521",
    "sg:postcode":"30093",
    "sg:province":"GA",
    "sg:tags":[
        "textiles-manufacturers"
    ],
    "sg:website":"http://www.uniquesashes.com",
    "wof:name":"Unique Sashes",
    "wof:placetype":"venue"
},
  "geometry": {"coordinates":[-84.14022900000001,33.92612],"type":"Point"}
}