{
  "type": "Feature",
  "properties": {
    "iso:country":"US",
    "sg:address":"2621 Graham Rd",
    "sg:city":"Gray",
    "sg:classifiers":[
        {
            "category":"Farming",
            "subcategory":"Dairy Farm",
            "type":"Manufacturing & Wholesale Goods"
        }
    ],
    "sg:phone":"+1 478 742 8915",
    "sg:postcode":"31032",
    "sg:province":"GA",
    "wof:name":"Robert Roberts",
    "wof:placetype":"venue"
},
  "geometry": {"coordinates":[-83.605282,32.933972],"type":"Point"}
}