{
  "type": "Feature",
  "properties": {
    "iso:country":"US",
    "sg:address":"259 Woods Edge Ct",
    "sg:city":"Marietta",
    "sg:classifiers":[
        {
            "category":"Manufacturing",
            "subcategory":"Pottery",
            "type":"Manufacturing & Wholesale Goods"
        }
    ],
    "sg:phone":"+1 770 977 2831",
    "sg:postcode":"30068",
    "sg:province":"GA",
    "wof:name":"Buckleys of Atlanta Inc",
    "wof:placetype":"venue"
},
  "geometry": {"coordinates":[-84.403758,33.954014],"type":"Point"}
}