{
  "type": "Feature",
  "properties": {
    "addr:full":"1320 Baxter St Athens GA 30606",
    "addr:housenumber":"1320",
    "addr:postcode":"30606",
    "addr:street":"Baxter St",
    "iso:country":"US",
    "sg:address":"1320 Baxter St",
    "sg:city":"Athens",
    "sg:classifiers":[
        {
            "category":"Restaurant",
            "type":"Food & Drink"
        }
    ],
    "sg:menulink":"http://www.allmenus.com/ga/athens/89509-moes-southwest-grill/menu/",
    "sg:phone":"+1 706 369 7776",
    "sg:postcode":"30606",
    "sg:province":"GA",
    "sg:tags":[
        "mexican"
    ],
    "wof:name":"Moe's Southwest Grill",
    "wof:placetype":"venue"
},
  "geometry": {"coordinates":[-83.401236,33.94651],"type":"Point"}
}