{
  "type": "Feature",
  "properties": {
    "addr:full":"1749 Bass Rd Macon GA 31210",
    "addr:housenumber":"1749",
    "addr:postcode":"31210",
    "addr:street":"Bass Rd",
    "iso:country":"US",
    "sg:address":"1749 Bass Rd",
    "sg:city":"Macon",
    "sg:classifiers":[
        {
            "category":"Health Services",
            "subcategory":"Medical Lab",
            "type":"Services"
        }
    ],
    "sg:phone":"+1 478 474 8011",
    "sg:postcode":"31210",
    "sg:province":"GA",
    "sg:tags":[
        "laboratory",
        "dental"
    ],
    "wof:name":"Restorative Dental Studio",
    "wof:placetype":"venue"
},
  "geometry": {"coordinates":[-83.72037899999999,32.936642],"type":"Point"}
}