{
  "type": "Feature",
  "properties": {
    "iso:country":"US",
    "sg:address":"2086 Glenellen Dr NW",
    "sg:city":"Kennesaw",
    "sg:classifiers":[
        {
            "category":"Manufacturing",
            "subcategory":"Building Materials",
            "type":"Manufacturing & Wholesale Goods"
        },
        {
            "category":"Building & Trades",
            "subcategory":"Construction",
            "type":"Services"
        }
    ],
    "sg:phone":"+1 770 514 7243",
    "sg:postcode":"30152",
    "sg:province":"GA",
    "sg:tags":[
        "mfg",
        "woodworker"
    ],
    "wof:name":"Doug's Outdoor Woodworking",
    "wof:placetype":"venue"
},
  "geometry": {"coordinates":[-84.66560800000001,34.002663],"type":"Point"}
}