{
  "type": "Feature",
  "properties": {
    "addr:full":"230 W College St Griffin GA 30224",
    "addr:housenumber":"230",
    "addr:postcode":"30224",
    "addr:street":"W College St",
    "iso:country":"US",
    "sg:address":"230 W College St",
    "sg:city":"Griffin",
    "sg:classifiers":[
        {
            "category":"Health Services",
            "subcategory":"Doctor",
            "type":"Services"
        }
    ],
    "sg:phone":"+1 770 229 2171",
    "sg:postcode":"30224",
    "sg:province":"GA",
    "sg:tags":[
        "physician",
        "surgeon"
    ],
    "wof:name":"Atlanta's Urology & Gynecolgy",
    "wof:placetype":"venue"
},
  "geometry": {"coordinates":[-84.264689,33.244376],"type":"Point"}
}