{
  "type": "Feature",
  "properties": {
    "addr:full":"41 Round Pond Rd La Fayette GA 30728",
    "addr:housenumber":"41",
    "addr:postcode":"30728",
    "addr:street":"Round Pond Rd",
    "iso:country":"US",
    "sg:address":"41 Round Pond Rd",
    "sg:city":"La Fayette",
    "sg:classifiers":[
        {
            "category":"Utilities",
            "subcategory":"Water",
            "type":"Services"
        }
    ],
    "sg:phone":"+1 706 764 2950",
    "sg:postcode":"30728",
    "sg:province":"GA",
    "sg:tags":[
        "company",
        "sewage"
    ],
    "wof:name":"Walker County Rural Water",
    "wof:placetype":"venue"
},
  "geometry": {"coordinates":[-85.19309199999999,34.749347],"type":"Point"}
}