{
  "type": "Feature",
  "properties": {
    "iso:country":"US",
    "sg:address":"4380 Bus Park Ct",
    "sg:city":"Lilburn",
    "sg:classifiers":[
        {
            "category":"Retail",
            "subcategory":"Auto Repair",
            "type":"Services"
        }
    ],
    "sg:phone":"+1 770 381 1411",
    "sg:postcode":"30047",
    "sg:province":"GA",
    "sg:tags":[
        "body",
        "automobile",
        "painting"
    ],
    "wof:name":"Osborne Body Works Inc",
    "wof:placetype":"venue"
},
  "geometry": {"coordinates":[-84.118173,33.892145],"type":"Point"}
}