{
  "type": "Feature",
  "properties": {
    "addr:full":"2044 S Cove Trl Marietta GA 30066",
    "addr:housenumber":"2044",
    "addr:postcode":"30066",
    "addr:street":"S Cove Trl",
    "iso:country":"US",
    "sg:address":"2044 S Cove Trl",
    "sg:city":"Marietta",
    "sg:classifiers":[
        {
            "category":"Professional",
            "type":"Services"
        }
    ],
    "sg:phone":"+1 770 592 8008",
    "sg:postcode":"30066",
    "sg:province":"GA",
    "wof:name":"Rob Carver Tennis Inc",
    "wof:placetype":"venue"
},
  "geometry": {"coordinates":[-84.490765,34.058822],"type":"Point"}
}