{
  "type": "Feature",
  "properties": {
    "addr:full":"660 Broad St Augusta GA 30901",
    "addr:housenumber":"660",
    "addr:postcode":"30901",
    "addr:street":"Broad St",
    "iso:country":"US",
    "sg:address":"660 Broad St",
    "sg:city":"Augusta",
    "sg:classifiers":[
        {
            "category":"Bars & Pubs",
            "type":"Food & Drink"
        }
    ],
    "sg:phone":"+1 706 823 5712",
    "sg:postcode":"30901",
    "sg:province":"GA",
    "sg:tags":[
        "club",
        "night"
    ],
    "wof:name":"Hale Tiki",
    "wof:placetype":"venue"
},
  "geometry": {"coordinates":[-81.96238700000001,33.474221],"type":"Point"}
}