{
  "type": "Feature",
  "properties": {
    "iso:country":"US",
    "sg:address":"6291 Rogers Rd",
    "sg:city":"Lizella",
    "sg:classifiers":[
        {
            "category":"Organizations",
            "subcategory":"Religious Organization",
            "type":"Services"
        }
    ],
    "sg:phone":"+1 478 784 1919",
    "sg:postcode":"31052",
    "sg:province":"GA",
    "sg:tags":[
        "church"
    ],
    "wof:name":"Rose Of Sharon Church",
    "wof:placetype":"venue"
},
  "geometry": {"coordinates":[-83.77833,32.741566],"type":"Point"}
}