{
  "type": "Feature",
  "properties": {
    "iso:country":"US",
    "sg:address":"240 State Rte 206 Con",
    "sg:city":"Douglas",
    "sg:classifiers":[
        {
            "category":"Retail",
            "subcategory":"Auto Repair",
            "type":"Services"
        }
    ],
    "sg:phone":"+1 912 384 6766",
    "sg:postcode":"31533",
    "sg:province":"GA",
    "sg:tags":[
        "repairing",
        "automobile"
    ],
    "wof:name":"Spivey Alignment Svc",
    "wof:placetype":"venue"
},
  "geometry": {"coordinates":[-82.825108,31.538692],"type":"Point"}
}