{
  "type": "Feature",
  "properties": {
    "addr:full":"1005 S Broad St Monroe GA 30655",
    "addr:housenumber":"1005",
    "addr:postcode":"30655",
    "addr:street":"S Broad St",
    "iso:country":"US",
    "sg:address":"1005 S Broad St",
    "sg:city":"Monroe",
    "sg:classifiers":[
        {
            "category":"Personal",
            "subcategory":"Beauty Salon",
            "type":"Services"
        }
    ],
    "sg:phone":"+1 770 207 4353",
    "sg:postcode":"30655",
    "sg:province":"GA",
    "sg:tags":[
        "shop",
        "tanning"
    ],
    "wof:name":"Sun-Set Tanning Salon",
    "wof:placetype":"venue"
},
  "geometry": {"coordinates":[-83.70863,33.782442],"type":"Point"}
}