{
  "type": "Feature",
  "properties": {
    "addr:full":"104 Kingstree Ln Warner Robins GA 31093",
    "addr:housenumber":"104",
    "addr:postcode":"31093",
    "addr:street":"Kingstree Ln",
    "iso:country":"US",
    "sg:address":"104 Kingstree Ln",
    "sg:city":"Warner Robins",
    "sg:classifiers":[
        {
            "category":"Building & Trades",
            "subcategory":"Plumbing",
            "type":"Services"
        }
    ],
    "sg:phone":"+1 478 953 1934",
    "sg:postcode":"31093",
    "sg:province":"GA",
    "sg:tags":[
        "plumbing",
        "heating",
        "air"
    ],
    "wof:name":"Harbin Heating & Air",
    "wof:placetype":"venue"
},
  "geometry": {"coordinates":[-83.69462,32.646241],"type":"Point"}
}