{
  "type": "Feature",
  "properties": {
    "iso:country":"US",
    "sg:address":"6612 Coventry Pt",
    "sg:city":"Austell",
    "sg:classifiers":[
        {
            "category":"Professional",
            "subcategory":"Management & Consulting",
            "type":"Services"
        }
    ],
    "sg:phone":"+1 770 819 1584",
    "sg:postcode":"30168",
    "sg:province":"GA",
    "sg:tags":[
        "business"
    ],
    "wof:name":"Unity In Spirit",
    "wof:placetype":"venue"
},
  "geometry": {"coordinates":[-84.613917,33.792931],"type":"Point"}
}