{
  "type": "Feature",
  "properties": {
    "addr:full":"1918 Ledo Rd Albany GA 31707",
    "addr:housenumber":"1918",
    "addr:postcode":"31707",
    "addr:street":"Ledo Rd",
    "iso:country":"US",
    "sg:address":"1918 Ledo Rd",
    "sg:city":"Albany",
    "sg:classifiers":[
        {
            "category":"Wholesale",
            "subcategory":"Chemicals & Plastics",
            "type":"Manufacturing & Wholesale Goods"
        }
    ],
    "sg:phone":"+1 229 430 2040",
    "sg:postcode":"31707",
    "sg:province":"GA",
    "sg:tags":[
        "glass",
        "material",
        "coating",
        "tinting"
    ],
    "wof:name":"Superior Film Distributing",
    "wof:placetype":"venue"
},
  "geometry": {"coordinates":[-84.18843699999999,31.622601],"type":"Point"}
}