{
  "type": "Feature",
  "properties": {
    "iso:country":"US",
    "sg:address":"5445 Mallard Pt",
    "sg:city":"Gainesville",
    "sg:classifiers":[
        {
            "category":"Health Services",
            "subcategory":"Health Practitioner",
            "type":"Services"
        }
    ],
    "sg:phone":"+1 770 534 1156",
    "sg:postcode":"30504",
    "sg:province":"GA",
    "sg:tags":[
        "psychologist"
    ],
    "wof:name":"Wierson & Assoc Inc",
    "wof:placetype":"venue"
},
  "geometry": {"coordinates":[-83.920126,34.240988],"type":"Point"}
}