{
  "type": "Feature",
  "properties": {
    "addr:full":"1102 S Madison Ave Monroe GA 30655",
    "addr:housenumber":"1102",
    "addr:postcode":"30655",
    "addr:street":"S Madison Ave",
    "iso:country":"US",
    "sg:address":"1102 S Madison Ave",
    "sg:city":"Monroe",
    "sg:classifiers":[
        {
            "category":"Retail",
            "subcategory":"Repair Shop",
            "type":"Services"
        }
    ],
    "sg:phone":"+1 770 972 6450",
    "sg:postcode":"30655",
    "sg:province":"GA",
    "wof:name":"Septic Systems Inc",
    "wof:placetype":"venue"
},
  "geometry": {"coordinates":[-83.70349400000001,33.781856],"type":"Point"}
}