{
  "type": "Feature",
  "properties": {
    "addr:full":"215 Colton Crest Dr Alpharetta GA 30005",
    "addr:housenumber":"215",
    "addr:postcode":"30005",
    "addr:street":"Colton Crest Dr",
    "iso:country":"US",
    "sg:address":"215 Colton Crest Dr",
    "sg:city":"Alpharetta",
    "sg:classifiers":[
        {
            "category":"Organizations",
            "subcategory":"Religious Organization",
            "type":"Services"
        }
    ],
    "sg:phone":"+1 770 622 1992",
    "sg:postcode":"30005",
    "sg:province":"GA",
    "wof:name":"Trinity Info Svc Inc",
    "wof:placetype":"venue"
},
  "geometry": {"coordinates":[-84.18104200000001,34.073317],"type":"Point"}
}