{
  "type": "Feature",
  "properties": {
    "addr:full":"35 Forsyth St SW Atlanta GA 30303",
    "addr:housenumber":"35",
    "addr:postcode":"30303",
    "addr:street":"Forsyth St Sw",
    "iso:country":"US",
    "sg:address":"35 Forsyth St SW",
    "sg:city":"Atlanta",
    "sg:classifiers":[
        {
            "category":"Restaurant",
            "type":"Food & Drink"
        }
    ],
    "sg:phone":"+1 404 524 8457",
    "sg:postcode":"30303",
    "sg:province":"GA",
    "sg:tags":[
        "fast"
    ],
    "wof:name":"McDonalds",
    "wof:placetype":"venue"
},
  "geometry": {"coordinates":[-84.392861,33.753815],"type":"Point"}
}