{
  "type": "Feature",
  "properties": {
    "addr:full":"8271 Tara Blvd Jonesboro GA 30236",
    "addr:housenumber":"8271",
    "addr:postcode":"30236",
    "addr:street":"Tara Blvd",
    "iso:country":"US",
    "sg:address":"8271 Tara Blvd",
    "sg:city":"Jonesboro",
    "sg:classifiers":[
        {
            "category":"Home & Garden",
            "subcategory":"Mobile Homes",
            "type":"Retail Goods"
        }
    ],
    "sg:phone":"+1 770 477 8756",
    "sg:postcode":"30236",
    "sg:province":"GA",
    "wof:name":"Global Homes Inc",
    "wof:placetype":"venue"
},
  "geometry": {"coordinates":[-84.363696,33.520811],"type":"Point"}
}