{
  "type": "Feature",
  "properties": {
    "iso:country":"US",
    "sg:address":"243 N Broad St",
    "sg:city":"Winder",
    "sg:classifiers":[
        {
            "category":"Manufacturing",
            "subcategory":"Tobacco Products",
            "type":"Manufacturing & Wholesale Goods"
        },
        {
            "category":"Shopping",
            "subcategory":"Tobacco",
            "type":"Retail Goods"
        }
    ],
    "sg:phone":"+1 770 586 0280",
    "sg:postcode":"30680",
    "sg:province":"GA",
    "sg:tags":[
        "cigarette",
        "cigar",
        "manufacturer",
        "tobacco-wholesale"
    ],
    "wof:name":"Tobacco House",
    "wof:placetype":"venue"
},
  "geometry": {"coordinates":[-83.71579,33.995144],"type":"Point"}
}