{
  "type": "Feature",
  "properties": {
    "iso:country":"US",
    "sg:address":"2517 Abercorn St",
    "sg:city":"Savannah",
    "sg:classifiers":[
        {
            "category":"Home & Garden",
            "subcategory":"Carpets & Floor Coverings",
            "type":"Retail Goods"
        }
    ],
    "sg:phone":"+1 912 232 7191",
    "sg:postcode":"31401",
    "sg:province":"GA",
    "sg:tags":[
        "oriental",
        "rug"
    ],
    "wof:name":"Pars Oriental Rugs Inc",
    "wof:placetype":"venue"
},
  "geometry": {"coordinates":[-81.099524,32.052428],"type":"Point"}
}