{
  "type": "Feature",
  "properties": {
    "addr:full":"225 Deep Step Rd Covington GA 30014",
    "addr:housenumber":"225",
    "addr:postcode":"30014",
    "addr:street":"Deep Step Rd",
    "iso:country":"US",
    "sg:address":"225 Deep Step Rd",
    "sg:city":"Covington",
    "sg:classifiers":[
        {
            "category":"Professional",
            "subcategory":"Business Services",
            "type":"Services"
        }
    ],
    "sg:phone":"+1 770 385 5829",
    "sg:postcode":"30014",
    "sg:province":"GA",
    "wof:name":"Rbs Enterprise",
    "wof:placetype":"venue"
},
  "geometry": {"coordinates":[-83.79060699999999,33.604849],"type":"Point"}
}