{
  "type": "Feature",
  "properties": {
    "iso:country":"US",
    "sg:address":"1675 Cumberland Pkwy SE Ste 202",
    "sg:city":"Smyrna",
    "sg:classifiers":[
        {
            "category":"Arts & Performance",
            "subcategory":"Arts Center",
            "type":"Entertainment"
        }
    ],
    "sg:phone":"+1 678 556 0444",
    "sg:postcode":"30080",
    "sg:province":"GA",
    "sg:tags":[
        "performing"
    ],
    "sg:website":"www.thestudioatlantadance.org",
    "wof:name":"The Studio-Atlanta Dance",
    "wof:placetype":"venue"
},
  "geometry": {"coordinates":[-84.498155,33.847287],"type":"Point"}
}