{
  "type": "Feature",
  "properties": {
    "addr:full":"60 Technology Dr Alpharetta GA 30005",
    "addr:housenumber":"60",
    "addr:postcode":"30005",
    "addr:street":"Technology Dr",
    "iso:country":"US",
    "sg:address":"60 Technology Dr",
    "sg:city":"Alpharetta",
    "sg:classifiers":[
        {
            "category":"Professional",
            "type":"Services"
        }
    ],
    "sg:phone":"+1 770 772 7270",
    "sg:postcode":"30005",
    "sg:province":"GA",
    "sg:tags":[
        "establishment"
    ],
    "wof:name":"Linster Mahx F Inc",
    "wof:placetype":"venue"
},
  "geometry": {"coordinates":[-84.220474,34.115207],"type":"Point"}
}