{
  "type": "Feature",
  "properties": {
    "iso:country":"US",
    "sg:address":"674 Carman Pl",
    "sg:city":"Macon",
    "sg:classifiers":[
        {
            "category":"Organizations",
            "subcategory":"Religious Organization",
            "type":"Services"
        }
    ],
    "sg:phone":"+1 478 784 7220",
    "sg:postcode":"31206",
    "sg:province":"GA",
    "sg:tags":[
        "church"
    ],
    "wof:name":"United Tabernacle Of Praise",
    "wof:placetype":"venue"
},
  "geometry": {"coordinates":[-83.648188,32.784516],"type":"Point"}
}