{
  "type": "Feature",
  "properties": {
    "iso:country":"US",
    "sg:address":"1425 2nd St",
    "sg:city":"Dudley",
    "sg:classifiers":[
        {
            "category":"Place Of Worship",
            "subcategory":"Church",
            "type":"Public Place"
        },
        {
            "category":"Place Of Worship",
            "type":"Public Place"
        }
    ],
    "sg:phone":"+1 478 676 3186",
    "sg:postcode":"31022",
    "sg:province":"GA",
    "sg:tags":[
        "churches-baptist-general",
        "churches-baptist"
    ],
    "wof:name":"Dudley Baptist Church",
    "wof:placetype":"venue"
},
  "geometry": {"coordinates":[-83.070483,32.542987],"type":"Point"}
}