{
  "type": "Feature",
  "properties": {
    "addr:full":"1439 McLendon Dr Decatur GA 30033",
    "addr:housenumber":"1439",
    "addr:postcode":"30033",
    "addr:street":"Mclendon Dr",
    "iso:country":"US",
    "sg:address":"1439 McLendon Dr",
    "sg:city":"Decatur",
    "sg:classifiers":[
        {
            "category":"Real Estate",
            "subcategory":"Real Estate Agent",
            "type":"Services"
        }
    ],
    "sg:phone":"+1 770 938 0002",
    "sg:postcode":"30033",
    "sg:province":"GA",
    "sg:tags":[
        "appraiser"
    ],
    "wof:name":"Appraisal Pro Svc",
    "wof:placetype":"venue"
},
  "geometry": {"coordinates":[-84.26204199999999,33.822508],"type":"Point"}
}