{
  "type": "Feature",
  "properties": {
    "addr:full":"3401 Norman Berry Dr Atlanta GA 30344",
    "addr:housenumber":"3401",
    "addr:postcode":"30344",
    "addr:street":"Norman Berry Dr",
    "iso:country":"US",
    "sg:address":"3401 Norman Berry Dr",
    "sg:city":"Atlanta",
    "sg:classifiers":[
        {
            "category":"Wholesale",
            "subcategory":"Metals & Minerals",
            "type":"Manufacturing & Wholesale Goods"
        }
    ],
    "sg:phone":"+1 404 766 3441",
    "sg:postcode":"30344",
    "sg:province":"GA",
    "sg:tags":[
        "center"
    ],
    "wof:name":"Isg Group",
    "wof:placetype":"venue"
},
  "geometry": {"coordinates":[-84.428354,33.658971],"type":"Point"}
}