{
  "type": "Feature",
  "properties": {
    "addr:full":"3414 Endicott Ln Lithonia GA 30038",
    "addr:housenumber":"3414",
    "addr:postcode":"30038",
    "addr:street":"Endicott Ln",
    "iso:country":"US",
    "sg:address":"3414 Endicott Ln",
    "sg:city":"Lithonia",
    "sg:classifiers":[
        {
            "category":"Professional",
            "type":"Services"
        }
    ],
    "sg:phone":"+1 678 518 9774",
    "sg:postcode":"30038",
    "sg:province":"GA",
    "sg:tags":[
        "establishment"
    ],
    "wof:name":"S & N Enterprises Inc",
    "wof:placetype":"venue"
},
  "geometry": {"coordinates":[-84.18790300000001,33.683901],"type":"Point"}
}