{
  "type": "Feature",
  "properties": {
    "addr:full":"349 Hamilton Dr Jefferson GA 30528",
    "addr:housenumber":"349",
    "addr:postcode":"30528",
    "addr:street":"Hamilton Dr",
    "iso:country":"US",
    "sg:address":"349 Hamilton Dr",
    "sg:city":"Jefferson",
    "sg:classifiers":[
        {
            "category":"Professional",
            "type":"Services"
        }
    ],
    "sg:phone":"+1 706 367 8136",
    "sg:postcode":"30528",
    "sg:province":"GA",
    "wof:name":"Michelles Sitters",
    "wof:placetype":"venue"
},
  "geometry": {"coordinates":[-83.746495,34.567092],"type":"Point"}
}