{
  "type": "Feature",
  "properties": {
    "iso:country":"US",
    "sg:address":"300 Cash Memorial Blvd",
    "sg:city":"Forest Park",
    "sg:phone":"+1 404 366 3965",
    "sg:postcode":"30297",
    "sg:province":"GA",
    "sg:tags":[
        "equipment",
        "petroleum",
        "sales",
        "dispensing"
    ],
    "wof:name":"A L Thompson Enterprises Inc",
    "wof:placetype":"venue"
},
  "geometry": {"coordinates":[-84.380179,33.607433],"type":"Point"}
}