{
  "type": "Feature",
  "properties": {
    "iso:country":"US",
    "sg:address":"1402 Desert Storm Dr",
    "sg:city":"Hinesville",
    "sg:classifiers":[
        {
            "category":"Professional",
            "subcategory":"Computer Services",
            "type":"Services"
        }
    ],
    "sg:phone":"+1 912 572 4957",
    "sg:postcode":"31313",
    "sg:province":"GA",
    "sg:tags":[
        "website",
        "design"
    ],
    "wof:name":"Arcane Designs",
    "wof:placetype":"venue"
},
  "geometry": {"coordinates":[-81.613331,31.809551],"type":"Point"}
}