{
  "type": "Feature",
  "properties": {
    "iso:country":"US",
    "sg:address":"6675 Peachtree Industrial Blvd",
    "sg:city":"Norcross",
    "sg:classifiers":[
        {
            "category":"Shopping",
            "subcategory":"Computers & Home Electronics",
            "type":"Retail Goods"
        }
    ],
    "sg:phone":"+1 770 447 6660",
    "sg:postcode":"30092",
    "sg:province":"GA",
    "wof:name":"Applied Intl Cmpt Concepts",
    "wof:placetype":"venue"
},
  "geometry": {"coordinates":[-84.249836,33.938628],"type":"Point"}
}