{
  "type": "Feature",
  "properties": {
    "iso:country":"US",
    "sg:address":"1206 Greene St",
    "sg:city":"Augusta",
    "sg:classifiers":[
        {
            "category":"Professional",
            "subcategory":"Employment Agencies",
            "type":"Services"
        }
    ],
    "sg:phone":"+1 706 993 2795",
    "sg:postcode":"30901",
    "sg:province":"GA",
    "sg:tags":[
        "temporary"
    ],
    "sg:website":"http://augusta.citysearch.com/profile/external/3100270/augusta_ga/manpower.html?publisher=yellowpages&reference_id=1&placement=ypwebsitemip",
    "wof:name":"Manpower",
    "wof:placetype":"venue"
},
  "geometry": {"coordinates":[-81.973994,33.475842],"type":"Point"}
}