{
  "type": "Feature",
  "properties": {
    "addr:full":"1741 Patriots Way Kennesaw GA 30152",
    "addr:housenumber":"1741",
    "addr:postcode":"30152",
    "addr:street":"Patriots Way",
    "iso:country":"US",
    "sg:address":"1741 Patriots Way",
    "sg:city":"Kennesaw",
    "sg:classifiers":[
        {
            "category":"Building & Trades",
            "subcategory":"Cleaning & Sanitation",
            "type":"Services"
        }
    ],
    "sg:phone":"+1 404 766 7078",
    "sg:postcode":"30152",
    "sg:province":"GA",
    "sg:tags":[
        "maintenance"
    ],
    "wof:name":"Ayers Maintenance",
    "wof:placetype":"venue"
},
  "geometry": {"coordinates":[-84.60077099999999,33.984167],"type":"Point"}
}