{
  "type": "Feature",
  "properties": {
    "iso:country":"US",
    "sg:address":"708 Old Greenville Rd",
    "sg:city":"Fayetteville",
    "sg:classifiers":[
        {
            "category":"Building & Trades",
            "subcategory":"Construction",
            "type":"Services"
        }
    ],
    "sg:phone":"+1 770 461 2370",
    "sg:postcode":"30215",
    "sg:province":"GA",
    "sg:tags":[
        "general",
        "contractor"
    ],
    "wof:name":"Parrish Custom Homes",
    "wof:placetype":"venue"
},
  "geometry": {"coordinates":[-84.46100199999999,33.357831],"type":"Point"}
}