{
  "type": "Feature",
  "properties": {
    "iso:country":"US",
    "sg:address":"518 N Broad St",
    "sg:city":"Thomasville",
    "sg:classifiers":[
        {
            "category":"Insurance",
            "subcategory":"Insurance Agent",
            "type":"Services"
        }
    ],
    "sg:phone":"+1 229 226 3244",
    "sg:postcode":"31792",
    "sg:province":"GA",
    "sg:tags":[
        "contractor"
    ],
    "wof:name":"Insursouth Inc",
    "wof:placetype":"venue"
},
  "geometry": {"coordinates":[-83.98486800000001,30.842553],"type":"Point"}
}