{
  "type": "Feature",
  "properties": {
    "iso:country":"US",
    "sg:address":"6016 W Rosie Ln SE",
    "sg:city":"Mableton",
    "sg:classifiers":[
        {
            "category":"Real Estate",
            "subcategory":"Real Estate Agent",
            "type":"Services"
        }
    ],
    "sg:phone":"+1 770 745 4500",
    "sg:postcode":"30126",
    "sg:province":"GA",
    "sg:tags":[
        "investment"
    ],
    "wof:name":"American Mortgage Investors",
    "wof:placetype":"venue"
},
  "geometry": {"coordinates":[-84.519324,33.809065],"type":"Point"}
}