{
  "type": "Feature",
  "properties": {
    "iso:country":"US",
    "sg:address":"1130 Topaz Way",
    "sg:city":"Marietta",
    "sg:classifiers":[
        {
            "category":"Professional",
            "subcategory":"Business Services",
            "type":"Services"
        }
    ],
    "sg:phone":"+1 770 998 9443",
    "sg:postcode":"30068",
    "sg:province":"GA",
    "sg:tags":[
        "interior",
        "designer"
    ],
    "wof:name":"Bright Ideas Interior Design",
    "wof:placetype":"venue"
},
  "geometry": {"coordinates":[-84.392455,33.976992],"type":"Point"}
}