{
  "type": "Feature",
  "properties": {
    "addr:full":"1634 Crestline Dr NE Atlanta GA 30345",
    "addr:housenumber":"1634",
    "addr:postcode":"30345",
    "addr:street":"Crestline Dr Ne",
    "iso:country":"US",
    "sg:address":"1634 Crestline Dr NE",
    "sg:city":"Atlanta",
    "sg:classifiers":[
        {
            "category":"Building & Trades",
            "subcategory":"Equipment Rental",
            "type":"Services"
        }
    ],
    "sg:phone":"+1 404 728 9482",
    "sg:postcode":"30345",
    "sg:province":"GA",
    "sg:tags":[
        "yard",
        "leasing",
        "store"
    ],
    "wof:name":"Louis D Olin Rental",
    "wof:placetype":"venue"
},
  "geometry": {"coordinates":[-84.29324800000001,33.83629],"type":"Point"}
}