{
  "type": "Feature",
  "properties": {
    "iso:country":"US",
    "sg:address":"3125 Vineville Ave",
    "sg:city":"Macon",
    "sg:classifiers":[
        {
            "category":"Autos & Motor Vehicles",
            "subcategory":"Auto Supplies",
            "type":"Retail Goods"
        },
        {
            "category":"Wholesale",
            "subcategory":"Electrical",
            "type":"Manufacturing & Wholesale Goods"
        },
        {
            "category":"Wholesale",
            "subcategory":"Auto Parts",
            "type":"Manufacturing & Wholesale Goods"
        }
    ],
    "sg:phone":"+1 478 742 5786",
    "sg:postcode":"31204",
    "sg:province":"GA",
    "sg:tags":[
        "body",
        "battery",
        "automobile",
        "accessory",
        "equipment",
        "truck"
    ],
    "sg:website":"http://www.oreillyauto.com?utm_source=yellowpages&utm_medium=iyp&utm_campaign=1412",
    "wof:name":"O'Reilly Auto Parts",
    "wof:placetype":"venue"
},
  "geometry": {"coordinates":[-83.675209,32.851086],"type":"Point"}
}