{
  "type": "Feature",
  "properties": {
    "addr:full":"118 Buren Way Temple GA 30179",
    "addr:housenumber":"118",
    "addr:postcode":"30179",
    "addr:street":"Buren Way",
    "iso:country":"US",
    "sg:address":"118 Buren Way",
    "sg:city":"Temple",
    "sg:classifiers":[
        {
            "category":"Wholesale",
            "subcategory":"Office Equipment",
            "type":"Manufacturing & Wholesale Goods"
        }
    ],
    "sg:phone":"+1 770 319 9382",
    "sg:postcode":"30179",
    "sg:province":"GA",
    "sg:tags":[
        "machine",
        "duplicating",
        "copying"
    ],
    "wof:name":"Byrd Business Systems",
    "wof:placetype":"venue"
},
  "geometry": {"coordinates":[-85.00363,33.781348],"type":"Point"}
}