{
  "type": "Feature",
  "properties": {
    "iso:country":"US",
    "sg:address":"2224 River Bend Rd",
    "sg:city":"Demorest",
    "sg:classifiers":[
        {
            "category":"Building & Trades",
            "subcategory":"Landscaping Services",
            "type":"Services"
        }
    ],
    "sg:phone":"+1 706 754 2659",
    "sg:postcode":"30535",
    "sg:province":"GA",
    "sg:tags":[
        "tree"
    ],
    "wof:name":"Taylor Tree Svc",
    "wof:placetype":"venue"
},
  "geometry": {"coordinates":[-83.61476500000001,34.60296],"type":"Point"}
}