{
  "type": "Feature",
  "properties": {
    "iso:country":"US",
    "sg:address":"3870 Lawrenceville Hwy",
    "sg:city":"Lawrenceville",
    "sg:classifiers":[
        {
            "category":"Professional",
            "type":"Services"
        }
    ],
    "sg:phone":"+1 770 931 4052",
    "sg:postcode":"30044",
    "sg:province":"GA",
    "sg:tags":[
        "establishment"
    ],
    "wof:name":"Euro-Scope",
    "wof:placetype":"venue"
},
  "geometry": {"coordinates":[-84.10857300000001,33.907756],"type":"Point"}
}