{
  "type": "Feature",
  "properties": {
    "iso:country":"US",
    "sg:address":"634 Reading Ct NE",
    "sg:city":"Lawrenceville",
    "sg:classifiers":[
        {
            "category":"Building & Trades",
            "subcategory":"Electrical",
            "type":"Services"
        }
    ],
    "sg:phone":"+1 770 277 3638",
    "sg:postcode":"30043",
    "sg:province":"GA",
    "wof:name":"Powell Cable Svc",
    "wof:placetype":"venue"
},
  "geometry": {"coordinates":[-83.990076,33.989158],"type":"Point"}
}