{
  "type": "Feature",
  "properties": {
    "iso:country":"US",
    "sg:address":"20 Lookout Pointe",
    "sg:city":"Stockbridge",
    "sg:classifiers":[
        {
            "category":"Building & Trades",
            "subcategory":"Construction",
            "type":"Services"
        }
    ],
    "sg:phone":"+1 770 389 0414",
    "sg:postcode":"30281",
    "sg:province":"GA",
    "sg:tags":[
        "house"
    ],
    "wof:name":"Home Renewal",
    "wof:placetype":"venue"
},
  "geometry": {"coordinates":[-84.232056,33.574511],"type":"Point"}
}