{
  "type": "Feature",
  "properties": {
    "iso:country":"US",
    "sg:address":"300 Rose St",
    "sg:city":"Augusta",
    "sg:classifiers":[
        {
            "category":"Professional",
            "subcategory":"Engineering",
            "type":"Services"
        },
        {
            "category":"Retail",
            "subcategory":"Repair Shop",
            "type":"Services"
        },
        {
            "category":"Home & Garden",
            "subcategory":"Building Materials",
            "type":"Retail Goods"
        },
        {
            "category":"Building & Trades",
            "subcategory":"Construction",
            "type":"Services"
        }
    ],
    "sg:phone":"+1 706 860 7400",
    "sg:postcode":"30907",
    "sg:province":"GA",
    "sg:tags":[
        "systems-repairing",
        "major",
        "refinishing",
        "appliance",
        "specialty",
        "system",
        "equipment",
        "heating",
        "contractor",
        "air conditioning"
    ],
    "sg:website":"http://www.ruud.com",
    "wof:name":"A Connells Appliance Heating And Air",
    "wof:placetype":"venue"
},
  "geometry": {"coordinates":[-82.08750499999999,33.506421],"type":"Point"}
}