{
  "type": "Feature",
  "properties": {
    "iso:country":"US",
    "sg:address":"1896 Forge St",
    "sg:city":"Tucker",
    "sg:classifiers":[
        {
            "category":"Wholesale",
            "subcategory":"Vending Machines",
            "type":"Manufacturing & Wholesale Goods"
        },
        {
            "category":"Home & Garden",
            "subcategory":"Kitchen Supply",
            "type":"Retail Goods"
        }
    ],
    "sg:phone":"+1 770 939 6740",
    "sg:postcode":"30084",
    "sg:province":"GA",
    "sg:tags":[
        "machines-parts",
        "food",
        "processing",
        "machines-wholesale",
        "equipment",
        "manufacturer"
    ],
    "sg:website":"http://www.southernequipmentsales.com",
    "wof:name":"Southern Equipment Sales",
    "wof:placetype":"venue"
},
  "geometry": {"coordinates":[-84.198662,33.838976],"type":"Point"}
}