{
  "type": "Feature",
  "properties": {
    "addr:full":"110 Zetterower Rd Statesboro GA 30458",
    "addr:housenumber":"110",
    "addr:postcode":"30458",
    "addr:street":"Zetterower Rd",
    "iso:country":"US",
    "sg:address":"110 Zetterower Rd",
    "sg:city":"Statesboro",
    "sg:classifiers":[
        {
            "category":"Professional",
            "subcategory":"Lawyer & Legal Services",
            "type":"Services"
        }
    ],
    "sg:phone":"+1 912 764 2865",
    "sg:postcode":"30458",
    "sg:province":"GA",
    "wof:name":"Kidd James Kelly Atty At Law",
    "wof:placetype":"venue"
},
  "geometry": {"coordinates":[-81.78974599999999,32.469178],"type":"Point"}
}