{
  "type": "Feature",
  "properties": {
    "addr:full":"113 E Montgomery Xrd Savannah GA 31406",
    "addr:housenumber":"113",
    "addr:postcode":"31406",
    "addr:street":"E Montgomery Xrd",
    "iso:country":"US",
    "sg:address":"113 E Montgomery Xrd",
    "sg:city":"Savannah",
    "sg:classifiers":[
        {
            "category":"Recreation",
            "type":"Entertainment"
        },
        {
            "category":"Sports & Exercise",
            "subcategory":"Gym",
            "type":"Entertainment"
        }
    ],
    "sg:phone":"+1 912 927 0479",
    "sg:postcode":"31406",
    "sg:province":"GA",
    "sg:tags":[
        "arts",
        "facility",
        "instruction",
        "martial",
        "fitness",
        "physical"
    ],
    "wof:name":"Lee's Tae KWON Do Fitness Ctr",
    "wof:placetype":"venue"
},
  "geometry": {"coordinates":[-81.11926,31.997477],"type":"Point"}
}