{
  "type": "Feature",
  "properties": {
    "iso:country":"US",
    "sg:address":"1034 Live Oak Dr",
    "sg:city":"Hinesville",
    "sg:classifiers":[
        {
            "category":"Organizations",
            "subcategory":"Community Association",
            "type":"Services"
        }
    ],
    "sg:phone":"+1 912 369 6285",
    "sg:postcode":"31313",
    "sg:province":"GA",
    "wof:name":"Knights of Columbus",
    "wof:placetype":"venue"
},
  "geometry": {"coordinates":[-81.62633099999999,31.81555],"type":"Point"}
}