{
  "type": "Feature",
  "properties": {
    "addr:full":"1600 Forest Ln Albany GA 31707",
    "addr:housenumber":"1600",
    "addr:postcode":"31707",
    "addr:street":"Forest Ln",
    "iso:country":"US",
    "sg:address":"1600 Forest Ln",
    "sg:city":"Albany",
    "sg:classifiers":[
        {
            "category":"Real Estate",
            "subcategory":"Real Estate Services",
            "type":"Services"
        },
        {
            "category":"Professional",
            "subcategory":"Research",
            "type":"Services"
        }
    ],
    "sg:phone":"+1 229 888 9035",
    "sg:postcode":"31707",
    "sg:province":"GA",
    "sg:tags":[
        "abstracter",
        "title"
    ],
    "wof:name":"Dougherty Abstract & Title Svc",
    "wof:placetype":"venue"
},
  "geometry": {"coordinates":[-84.186958,31.593941],"type":"Point"}
}