{
  "type": "Feature",
  "properties": {
    "iso:country":"US",
    "sg:address":"309 Veterans Dr",
    "sg:city":"Thomaston",
    "sg:classifiers":[
        {
            "category":"Building & Trades",
            "subcategory":"Construction",
            "type":"Services"
        }
    ],
    "sg:phone":"+1 706 647 7144",
    "sg:postcode":"30286",
    "sg:province":"GA",
    "sg:tags":[
        "marking",
        "maintenance",
        "parking"
    ],
    "wof:name":"Thomaston Public Works",
    "wof:placetype":"venue"
},
  "geometry": {"coordinates":[-84.330898,32.875314],"type":"Point"}
}