{
  "type": "Feature",
  "properties": {
    "iso:country":"US",
    "sg:address":"1148 Camp John Hope Rd",
    "sg:city":"Fort Valley",
    "sg:classifiers":[
        {
            "category":"Professional",
            "type":"Services"
        }
    ],
    "sg:phone":"+1 478 825 7372",
    "sg:postcode":"31030",
    "sg:province":"GA",
    "wof:name":"H & M Technical Services",
    "wof:placetype":"venue"
},
  "geometry": {"coordinates":[-83.864799,32.503475],"type":"Point"}
}