{
  "type": "Feature",
  "properties": {
    "addr:full":"602 Brannen St Statesboro GA 30458",
    "addr:housenumber":"602",
    "addr:postcode":"30458",
    "addr:street":"Brannen St",
    "iso:country":"US",
    "sg:address":"602 Brannen St",
    "sg:city":"Statesboro",
    "sg:classifiers":[
        {
            "category":"Food & Beverages",
            "subcategory":"Groceries & Convenience Stores",
            "type":"Retail Goods"
        }
    ],
    "sg:phone":"+1 912 764 9238",
    "sg:postcode":"30458",
    "sg:province":"GA",
    "sg:website":"www.winndixie.com",
    "wof:name":"Winn-Dixie",
    "wof:placetype":"venue"
},
  "geometry": {"coordinates":[-81.767714,32.434888],"type":"Point"}
}