{
  "type": "Feature",
  "properties": {
    "addr:full":"963 N Burnt Hickory Rd Ste A Douglasville GA 30134",
    "addr:housenumber":"963",
    "addr:postcode":"30134",
    "addr:street":"N Burnt Hickory Rd Ste A",
    "iso:country":"US",
    "sg:address":"963 N Burnt Hickory Rd Ste A",
    "sg:city":"Douglasville",
    "sg:classifiers":[
        {
            "category":"Building & Trades",
            "subcategory":"Electrical",
            "type":"Services"
        }
    ],
    "sg:phone":"+1 770 949 7800",
    "sg:postcode":"30134",
    "sg:province":"GA",
    "sg:tags":[
        "electrician"
    ],
    "wof:name":"West Star Electrical Contractors Inc",
    "wof:placetype":"venue"
},
  "geometry": {"coordinates":[-84.70880099999999,33.780701],"type":"Point"}
}