{
  "type": "Feature",
  "properties": {
    "addr:full":"4990 Bryant Dr Snellville GA 30039",
    "addr:housenumber":"4990",
    "addr:postcode":"30039",
    "addr:street":"Bryant Dr",
    "iso:country":"US",
    "sg:address":"4990 Bryant Dr",
    "sg:city":"Snellville",
    "sg:classifiers":[
        {
            "category":"Building & Trades",
            "subcategory":"Construction",
            "type":"Services"
        }
    ],
    "sg:phone":"+1 770 602 4355",
    "sg:postcode":"30039",
    "sg:province":"GA",
    "sg:tags":[
        "painter"
    ],
    "wof:name":"Schultz Group-Painting the",
    "wof:placetype":"venue"
},
  "geometry": {"coordinates":[-84.00460099999999,33.771801],"type":"Point"}
}