{
  "type": "Feature",
  "properties": {
    "iso:country":"US",
    "sg:address":"3714 Salem Kirk Dr",
    "sg:city":"Lithonia",
    "sg:classifiers":[
        {
            "category":"Shopping",
            "subcategory":"Clothing, Apparel, & Fashions",
            "type":"Retail Goods"
        }
    ],
    "sg:phone":"+1 770 757 9037",
    "sg:postcode":"30038",
    "sg:province":"GA",
    "sg:tags":[
        "item",
        "boutique"
    ],
    "wof:name":"Kenya's Boutique",
    "wof:placetype":"venue"
},
  "geometry": {"coordinates":[-84.17277199999999,33.672557],"type":"Point"}
}