{
  "type": "Feature",
  "properties": {
    "addr:full":"1934 N Druid Hills Rd NE Ste A Atlanta GA 30319",
    "addr:housenumber":"1934",
    "addr:postcode":"30319",
    "addr:street":"N Druid Hills Rd Ne Ste A",
    "iso:country":"US",
    "sg:address":"1934 N Druid Hills Rd NE Ste A",
    "sg:city":"Atlanta",
    "sg:classifiers":[
        {
            "category":"Professional",
            "subcategory":"Lawyer & Legal Services",
            "type":"Services"
        }
    ],
    "sg:phone":"+1 770 993 1010",
    "sg:postcode":"30319",
    "sg:province":"GA",
    "wof:name":"Greene Delia",
    "wof:placetype":"venue"
},
  "geometry": {"coordinates":[-84.341427,33.834836],"type":"Point"}
}