{
  "type": "Feature",
  "properties": {
    "iso:country":"US",
    "sg:address":"221 W Poplar St",
    "sg:city":"Griffin",
    "sg:classifiers":[
        {
            "category":"Professional",
            "subcategory":"Testing Lab",
            "type":"Services"
        },
        {
            "category":"Health Services",
            "subcategory":"Medical Lab",
            "type":"Services"
        }
    ],
    "sg:phone":"+1 770 467 6700",
    "sg:postcode":"30224",
    "sg:province":"GA",
    "sg:tags":[
        "analytical",
        "laboratory"
    ],
    "wof:name":"Choice Lab Services",
    "wof:placetype":"venue"
},
  "geometry": {"coordinates":[-84.265856,33.245791],"type":"Point"}
}