{
  "type": "Feature",
  "properties": {
    "iso:country":"US",
    "sg:address":"405 Lee St",
    "sg:city":"Jefferson",
    "sg:classifiers":[
        {
            "category":"Professional",
            "subcategory":"Credit Reporting & Collection",
            "type":"Services"
        }
    ],
    "sg:phone":"+1 706 367 1231",
    "sg:postcode":"30549",
    "sg:province":"GA",
    "sg:tags":[
        "agency"
    ],
    "wof:name":"North Georgia Collections",
    "wof:placetype":"venue"
},
  "geometry": {"coordinates":[-83.579746,34.115316],"type":"Point"}
}