{
  "type": "Feature",
  "properties": {
    "addr:full":"1502 Ridgeway Dr Vidalia GA 30474",
    "addr:housenumber":"1502",
    "addr:postcode":"30474",
    "addr:street":"Ridgeway Dr Vidalia",
    "iso:country":"US",
    "sg:address":"1502 Ridgeway Dr",
    "sg:city":"Vidalia",
    "sg:classifiers":[
        {
            "category":"Personal",
            "type":"Services"
        }
    ],
    "sg:phone":"+1 912 537 0408",
    "sg:postcode":"30474",
    "sg:province":"GA",
    "sg:tags":[
        "bureau",
        "babysitting"
    ],
    "wof:name":"Heavens Children",
    "wof:placetype":"venue"
},
  "geometry": {"coordinates":[-82.398251,32.203114],"type":"Point"}
}