{
  "type": "Feature",
  "properties": {
    "iso:country":"US",
    "sg:address":"338 Main St",
    "sg:city":"Thomson",
    "sg:classifiers":[
        {
            "category":"Education",
            "subcategory":"Library",
            "type":"Public Place"
        }
    ],
    "sg:phone":"+1 706 595 1341",
    "sg:postcode":"30824",
    "sg:province":"GA",
    "wof:name":"Thomson Mc Duffie Library",
    "wof:placetype":"venue"
},
  "geometry": {"coordinates":[-82.504593,33.470327],"type":"Point"}
}