{
  "type": "Feature",
  "properties": {
    "addr:full":"1720 Mount Vernon Rd Atlanta GA 30338",
    "addr:housenumber":"1720",
    "addr:postcode":"30338",
    "addr:street":"Mount Vernon Rd",
    "iso:country":"US",
    "sg:address":"1720 Mount Vernon Rd",
    "sg:city":"Atlanta",
    "sg:classifiers":[
        {
            "category":"Manufacturing",
            "subcategory":"Printing",
            "type":"Manufacturing & Wholesale Goods"
        }
    ],
    "sg:phone":"+1 770 913 0603",
    "sg:postcode":"30338",
    "sg:province":"GA",
    "sg:tags":[
        "printer",
        "commercial",
        "offset"
    ],
    "wof:name":"Dunwoody Atlanta Printing Inc",
    "wof:placetype":"venue"
},
  "geometry": {"coordinates":[-84.329464,33.947191],"type":"Point"}
}