{
  "type": "Feature",
  "properties": {
    "addr:full":"312 Grey St Dublin GA 31021",
    "addr:housenumber":"312",
    "addr:postcode":"31021",
    "addr:street":"Grey St",
    "iso:country":"US",
    "sg:address":"312 Grey St",
    "sg:city":"Dublin",
    "sg:classifiers":[
        {
            "category":"Personal",
            "subcategory":"Barber",
            "type":"Services"
        }
    ],
    "sg:phone":"+1 478 296 9303",
    "sg:postcode":"31021",
    "sg:province":"GA",
    "wof:name":"Roy's Barber Shop",
    "wof:placetype":"venue"
},
  "geometry": {"coordinates":[-82.899252,32.53108],"type":"Point"}
}