{
  "type": "Feature",
  "properties": {
    "addr:full":"100 Cottage Ln Macon GA 31210",
    "addr:housenumber":"100",
    "addr:postcode":"31210",
    "addr:street":"Cottage Ln",
    "iso:country":"US",
    "sg:address":"100 Cottage Ln",
    "sg:city":"Macon",
    "sg:classifiers":[
        {
            "category":"Real Estate",
            "subcategory":"Real Estate Services",
            "type":"Services"
        },
        {
            "category":"Real Estate",
            "subcategory":"Real Estate Agent",
            "type":"Services"
        }
    ],
    "sg:phone":"+1 478 405 0066",
    "sg:postcode":"31210",
    "sg:province":"GA",
    "sg:tags":[
        "buyer",
        "broker"
    ],
    "wof:name":"Waterford Cottages At Providence",
    "wof:placetype":"venue"
},
  "geometry": {"coordinates":[-83.749527,32.93309],"type":"Point"}
}