{
  "type": "Feature",
  "properties": {
    "addr:full":"3150 Austell Rd Marietta GA 30008",
    "addr:housenumber":"3150",
    "addr:postcode":"30008",
    "addr:street":"Austell Rd",
    "iso:country":"US",
    "sg:address":"3150 Austell Rd",
    "sg:city":"Marietta",
    "sg:classifiers":[
        {
            "category":"Retail",
            "subcategory":"Storage",
            "type":"Services"
        }
    ],
    "sg:phone":"+1 866 838 2192",
    "sg:postcode":"30008",
    "sg:province":"GA",
    "sg:tags":[
        "self"
    ],
    "sg:website":"www.unclebobs.com/",
    "wof:name":"Uncle Bob's Self Storage",
    "wof:placetype":"venue"
},
  "geometry": {"coordinates":[-84.589062,33.879038],"type":"Point"}
}