{
  "type": "Feature",
  "properties": {
    "addr:full":"644 Main St Thomson GA 30824",
    "addr:housenumber":"644",
    "addr:postcode":"30824",
    "addr:street":"Main St",
    "iso:country":"US",
    "sg:address":"644 Main St",
    "sg:city":"Thomson",
    "sg:classifiers":[
        {
            "category":"Shopping",
            "subcategory":"Discount & Variety Stores",
            "type":"Retail Goods"
        }
    ],
    "sg:phone":"+1 706 595 9626",
    "sg:postcode":"30824",
    "sg:province":"GA",
    "wof:name":"Dollar General",
    "wof:placetype":"venue"
},
  "geometry": {"coordinates":[-82.50553499999999,33.480223],"type":"Point"}
}