{
  "type": "Feature",
  "properties": {
    "iso:country":"US",
    "sg:address":"2702 Michael Rd",
    "sg:city":"Albany",
    "sg:classifiers":[
        {
            "category":"Freight",
            "type":"Transportation"
        }
    ],
    "sg:phone":"+1 229 446 9966",
    "sg:postcode":"31721",
    "sg:province":"GA",
    "sg:tags":[
        "operator",
        "trucking"
    ],
    "wof:name":"Millard Transport Corp",
    "wof:placetype":"venue"
},
  "geometry": {"coordinates":[-84.247343,31.620997],"type":"Point"}
}