{
  "type": "Feature",
  "properties": {
    "iso:country":"US",
    "sg:address":"4030 Pleasantdale Rd",
    "sg:city":"Atlanta",
    "sg:classifiers":[
        {
            "category":"Professional",
            "subcategory":"Business Services",
            "type":"Services"
        }
    ],
    "sg:phone":"+1 770 409 3988",
    "sg:postcode":"30340",
    "sg:province":"GA",
    "sg:tags":[
        "exporter",
        "export",
        "representative"
    ],
    "wof:name":"J Z Trading Corp",
    "wof:placetype":"venue"
},
  "geometry": {"coordinates":[-84.243531,33.899513],"type":"Point"}
}