{
  "type": "Feature",
  "properties": {
    "addr:full":"930 Memorial Dr Waycross GA 31501",
    "addr:housenumber":"930",
    "addr:postcode":"31501",
    "addr:street":"Memorial Dr",
    "iso:country":"US",
    "sg:address":"930 Memorial Dr",
    "sg:city":"Waycross",
    "sg:classifiers":[
        {
            "category":"Personal",
            "type":"Services"
        }
    ],
    "sg:phone":"+1 912 283 4770",
    "sg:postcode":"31501",
    "sg:province":"GA",
    "wof:name":"Xtremes Tattoo & Piercing",
    "wof:placetype":"venue"
},
  "geometry": {"coordinates":[-82.345643,31.210138],"type":"Point"}
}