{
  "type": "Feature",
  "properties": {
    "addr:full":"3180 Young Harris Hwy Blairsville GA 30512",
    "addr:housenumber":"3180",
    "addr:postcode":"30512",
    "addr:street":"Young Harris Hwy",
    "iso:country":"US",
    "sg:address":"3180 Young Harris Hwy",
    "sg:city":"Blairsville",
    "sg:classifiers":[
        {
            "category":"Autos & Motor Vehicles",
            "subcategory":"Automobile Sales",
            "type":"Retail Goods"
        }
    ],
    "sg:phone":"+1 706 745 3075",
    "sg:postcode":"30512",
    "sg:province":"GA",
    "sg:tags":[
        "car",
        "dealer"
    ],
    "wof:name":"Murray's Car & Truck Sales",
    "wof:placetype":"venue"
},
  "geometry": {"coordinates":[-83.883353,34.907157],"type":"Point"}
}