{
  "type": "Feature",
  "properties": {
    "iso:country":"US",
    "sg:address":"2543 Habersham Rd NW",
    "sg:city":"Atlanta",
    "sg:classifiers":[
        {
            "category":"Professional",
            "subcategory":"Management & Consulting",
            "type":"Services"
        }
    ],
    "sg:phone":"+1 404 841 1939",
    "sg:postcode":"30305",
    "sg:province":"GA",
    "sg:tags":[
        "business"
    ],
    "wof:name":"Seitz Consulting",
    "wof:placetype":"venue"
},
  "geometry": {"coordinates":[-84.392454,33.823201],"type":"Point"}
}