{
  "type": "Feature",
  "properties": {
    "iso:country":"US",
    "sg:address":"9083 Jenni Cir",
    "sg:city":"Jonesboro",
    "sg:classifiers":[
        {
            "category":"Professional",
            "type":"Services"
        }
    ],
    "sg:phone":"+1 404 593 1032",
    "sg:postcode":"30238",
    "sg:province":"GA",
    "sg:tags":[
        "transportation"
    ],
    "wof:name":"Trell & Trell Enterprises",
    "wof:placetype":"venue"
},
  "geometry": {"coordinates":[-84.366679,33.509219],"type":"Point"}
}