{
  "type": "Feature",
  "properties": {
    "iso:country":"US",
    "sg:address":"226 Robert C Daniel Jr Pkwy",
    "sg:city":"Augusta",
    "sg:classifiers":[
        {
            "category":"Shopping",
            "subcategory":"Clothing, Apparel, & Fashions",
            "type":"Retail Goods"
        }
    ],
    "sg:phone":"+1 706 736 1585",
    "sg:postcode":"30909",
    "sg:province":"GA",
    "sg:tags":[
        "fur",
        "business"
    ],
    "wof:name":"Henig Furs & Leathers",
    "wof:placetype":"venue"
},
  "geometry": {"coordinates":[-82.070882,33.47612],"type":"Point"}
}