{
  "type": "Feature",
  "properties": {
    "addr:full":"1649 Pine St Bainbridge FL 39819",
    "addr:housenumber":"1649",
    "addr:postcode":"39819",
    "addr:street":"Pine St",
    "iso:country":"US",
    "sg:address":"1649 Pine St",
    "sg:city":"Bainbridge",
    "sg:classifiers":[
        {
            "category":"Organizations",
            "subcategory":"Religious Organization",
            "type":"Services"
        }
    ],
    "sg:phone":"+1 229 243 7652",
    "sg:postcode":"39819",
    "sg:province":"FL",
    "sg:tags":[
        "church"
    ],
    "wof:name":"Church Of Jesus Christ Of Lds",
    "wof:placetype":"venue"
},
  "geometry": {"coordinates":[-84.547962,30.898976],"type":"Point"}
}