{
  "type": "Feature",
  "properties": {
    "addr:full":"2493 Fraser Rd Marietta GA 30066",
    "addr:housenumber":"2493",
    "addr:postcode":"30066",
    "addr:street":"Fraser Rd",
    "iso:country":"US",
    "sg:address":"2493 Fraser Rd",
    "sg:city":"Marietta",
    "sg:classifiers":[
        {
            "category":"Building & Trades",
            "subcategory":"Construction",
            "type":"Services"
        }
    ],
    "sg:phone":"+1 770 426 4978",
    "sg:postcode":"30066",
    "sg:province":"GA",
    "sg:tags":[
        "hanging",
        "contractor"
    ],
    "wof:name":"Sartain Enterprises",
    "wof:placetype":"venue"
},
  "geometry": {"coordinates":[-84.530035,34.012125],"type":"Point"}
}