{
  "type": "Feature",
  "properties": {
    "iso:country":"US",
    "sg:address":"2111 New York Ave",
    "sg:city":"Waycross",
    "sg:classifiers":[
        {
            "category":"Personal",
            "subcategory":"Beauty Salon",
            "type":"Services"
        }
    ],
    "sg:phone":"+1 912 285 4971",
    "sg:postcode":"31503",
    "sg:province":"GA",
    "wof:name":"Wanda's Beauty Shop",
    "wof:placetype":"venue"
},
  "geometry": {"coordinates":[-82.393642,31.194283],"type":"Point"}
}