{
  "type": "Feature",
  "properties": {
    "addr:full":"183 1st St Trenton GA 30752",
    "addr:housenumber":"183",
    "addr:postcode":"30752",
    "addr:street":"1St St",
    "iso:country":"US",
    "sg:address":"183 1st St",
    "sg:city":"Trenton",
    "sg:classifiers":[
        {
            "category":"Utilities",
            "subcategory":"Telephone",
            "type":"Services"
        }
    ],
    "sg:phone":"+1 706 657 4367",
    "sg:postcode":"30752",
    "sg:province":"GA",
    "sg:tags":[
        "company"
    ],
    "sg:website":"www.trenton-telco.com",
    "wof:name":"Trenton Telephone Co",
    "wof:placetype":"venue"
},
  "geometry": {"coordinates":[-85.513154,34.874826],"type":"Point"}
}