{
  "type": "Feature",
  "properties": {
    "addr:full":"3595 Canton Rd Marietta GA 30066",
    "addr:housenumber":"3595",
    "addr:postcode":"30066",
    "addr:street":"Canton Rd",
    "iso:country":"US",
    "sg:address":"3595 Canton Rd",
    "sg:city":"Marietta",
    "sg:classifiers":[
        {
            "category":"Personal",
            "subcategory":"Beauty Salon",
            "type":"Services"
        }
    ],
    "sg:phone":"+1 770 516 9485",
    "sg:postcode":"30066",
    "sg:province":"GA",
    "wof:name":"Creative Hairdressers",
    "wof:placetype":"venue"
},
  "geometry": {"coordinates":[-84.528408,34.038543],"type":"Point"}
}