{
  "type": "Feature",
  "properties": {
    "iso:country":"US",
    "sg:address":"323 Ashton Pl",
    "sg:city":"Mc Donough",
    "sg:classifiers":[
        {
            "category":"Manufacturing",
            "subcategory":"Lumber",
            "type":"Manufacturing & Wholesale Goods"
        }
    ],
    "sg:phone":"+1 770 898 9506",
    "sg:postcode":"30253",
    "sg:province":"GA",
    "sg:tags":[
        "hardwood",
        "mill"
    ],
    "wof:name":"Joseph Godby",
    "wof:placetype":"venue"
},
  "geometry": {"coordinates":[-84.18691,33.436396],"type":"Point"}
}