{
  "type": "Feature",
  "properties": {
    "iso:country":"US",
    "sg:address":"525 Laney Walker Blvd",
    "sg:city":"Augusta",
    "sg:classifiers":[
        {
            "category":"Wholesale",
            "subcategory":"Machinery & Supplies",
            "type":"Manufacturing & Wholesale Goods"
        }
    ],
    "sg:phone":"+1 706 826 1714",
    "sg:postcode":"30901",
    "sg:province":"GA",
    "sg:tags":[
        "truck"
    ],
    "wof:name":"Toyota Forklift Of Augusta",
    "wof:placetype":"venue"
},
  "geometry": {"coordinates":[-81.967477,33.461427],"type":"Point"}
}