{
  "type": "Feature",
  "properties": {
    "addr:full":"11720 Medlock Bridge Rd Duluth GA 30097",
    "addr:housenumber":"11720",
    "addr:postcode":"30097",
    "addr:street":"Medlock Bridge Rd",
    "iso:country":"US",
    "sg:address":"11720 Medlock Bridge Rd",
    "sg:city":"Duluth",
    "sg:classifiers":[
        {
            "category":"Building & Trades",
            "subcategory":"Locksmith",
            "type":"Services"
        }
    ],
    "sg:phone":"+1 678 269 7260",
    "sg:postcode":"30097",
    "sg:province":"GA",
    "sg:tags":[
        "key"
    ],
    "wof:name":"123 Emergency Locksmith",
    "wof:placetype":"venue"
},
  "geometry": {"coordinates":[-84.169827,34.065508],"type":"Point"}
}