{
  "type": "Feature",
  "properties": {
    "addr:full":"6920 Main St Lithonia GA 30058",
    "addr:housenumber":"6920",
    "addr:postcode":"30058",
    "addr:street":"Main St",
    "iso:country":"US",
    "sg:address":"6920 Main St",
    "sg:city":"Lithonia",
    "sg:classifiers":[
        {
            "category":"Professional",
            "subcategory":"Lawyer & Legal Services",
            "type":"Services"
        }
    ],
    "sg:phone":"+1 770 484 0927",
    "sg:postcode":"30058",
    "sg:province":"GA",
    "sg:tags":[
        "attorney"
    ],
    "wof:name":"John T Davis",
    "wof:placetype":"venue"
},
  "geometry": {"coordinates":[-84.10823000000001,33.710675],"type":"Point"}
}