{
  "type": "Feature",
  "properties": {
    "iso:country":"US",
    "sg:address":"859 Broad St",
    "sg:city":"Augusta",
    "sg:classifiers":[
        {
            "category":"Personal",
            "subcategory":"Beauty Salon",
            "type":"Services"
        }
    ],
    "sg:phone":"+1 706 774 0072",
    "sg:postcode":"30901",
    "sg:province":"GA",
    "sg:tags":[
        "shop"
    ],
    "wof:name":"Thee Salon Beautiful Braids",
    "wof:placetype":"venue"
},
  "geometry": {"coordinates":[-81.967099,33.476046],"type":"Point"}
}