{
  "type": "Feature",
  "properties": {
    "iso:country":"US",
    "sg:address":"1430 Chattahoochee Ave NW",
    "sg:city":"Atlanta",
    "sg:classifiers":[
        {
            "category":"Building & Trades",
            "subcategory":"Construction",
            "type":"Services"
        }
    ],
    "sg:phone":"+1 404 350 2181",
    "sg:postcode":"30318",
    "sg:province":"GA",
    "sg:tags":[
        "interior",
        "design"
    ],
    "wof:name":"Focus Design & Merchandising Inc",
    "wof:placetype":"venue"
},
  "geometry": {"coordinates":[-84.43380000000001,33.805401],"type":"Point"}
}