{
  "type": "Feature",
  "properties": {
    "iso:country":"US",
    "sg:address":"490 Windy Hill Rd SE",
    "sg:city":"Marietta",
    "sg:classifiers":[
        {
            "category":"Professional",
            "subcategory":"Lawyer & Legal Services",
            "type":"Services"
        }
    ],
    "sg:phone":"+1 678 213 0500",
    "sg:postcode":"30060",
    "sg:province":"GA",
    "sg:tags":[
        "attorney",
        "law",
        "consultant",
        "immigration",
        "naturalization"
    ],
    "wof:name":"Latin American Association",
    "wof:placetype":"venue"
},
  "geometry": {"coordinates":[-84.540138,33.894539],"type":"Point"}
}