{
  "type": "Feature",
  "properties": {
    "iso:country":"US",
    "sg:address":"2301 Gordon Hwy",
    "sg:city":"Augusta",
    "sg:classifiers":[
        {
            "category":"Bars & Pubs",
            "type":"Food & Drink"
        }
    ],
    "sg:phone":"+1 706 738 3273",
    "sg:postcode":"30909",
    "sg:province":"GA",
    "sg:tags":[
        "brew",
        "tavern"
    ],
    "wof:name":"Ralph's Five Pines Saloon",
    "wof:placetype":"venue"
},
  "geometry": {"coordinates":[-82.09204800000001,33.445629],"type":"Point"}
}