{
  "type": "Feature",
  "properties": {
    "iso:country":"US",
    "sg:address":"6595 Roswell Rd NE Ste G",
    "sg:city":"Atlanta",
    "sg:classifiers":[
        {
            "category":"Professional",
            "subcategory":"Business Services",
            "type":"Services"
        },
        {
            "category":"Government",
            "subcategory":"Post Office",
            "type":"Public Place"
        }
    ],
    "sg:phone":"+1 404 843 0425",
    "sg:postcode":"30328",
    "sg:province":"GA",
    "sg:tags":[
        "delivery",
        "mail",
        "shipping",
        "courier"
    ],
    "wof:name":"America's Mail Center",
    "wof:placetype":"venue"
},
  "geometry": {"coordinates":[-84.37933099999999,33.935471],"type":"Point"}
}