{
  "type": "Feature",
  "properties": {
    "addr:full":"111 E Richardson St Oxford GA 30054",
    "addr:housenumber":"111",
    "addr:postcode":"30054",
    "addr:street":"E Richardson St",
    "iso:country":"US",
    "sg:address":"111 E Richardson St",
    "sg:city":"Oxford",
    "sg:classifiers":[
        {
            "category":"Professional",
            "type":"Services"
        }
    ],
    "sg:phone":"+1 770 786 1505",
    "sg:postcode":"30054",
    "sg:province":"GA",
    "wof:name":"Bobby Terrell",
    "wof:placetype":"venue"
},
  "geometry": {"coordinates":[-83.86729200000001,33.633853],"type":"Point"}
}