{
  "type": "Feature",
  "properties": {
    "addr:full":"3343 Pucketts Mill Rd Buford GA 30519",
    "addr:housenumber":"3343",
    "addr:postcode":"30519",
    "addr:street":"Pucketts Mill Rd",
    "iso:country":"US",
    "sg:address":"3343 Pucketts Mill Rd",
    "sg:city":"Buford",
    "sg:classifiers":[
        {
            "category":"Recreation",
            "type":"Entertainment"
        }
    ],
    "sg:phone":"+1 770 932 6003",
    "sg:postcode":"30519",
    "sg:province":"GA",
    "sg:tags":[
        "martial",
        "arts",
        "instruction"
    ],
    "wof:name":"Global Karate",
    "wof:placetype":"venue"
},
  "geometry": {"coordinates":[-83.926687,34.081262],"type":"Point"}
}