{
  "type": "Feature",
  "properties": {
    "iso:country":"US",
    "sg:address":"1010 Old Pretoria Rd",
    "sg:city":"Albany",
    "sg:classifiers":[
        {
            "category":"Place Of Worship",
            "subcategory":"Church",
            "type":"Public Place"
        },
        {
            "category":"Place Of Worship",
            "type":"Public Place"
        }
    ],
    "sg:phone":"+1 229 439 0494",
    "sg:postcode":"31721",
    "sg:province":"GA",
    "sg:tags":[
        "churches-baptist-general",
        "churches-baptist"
    ],
    "wof:name":"Zion Outreach Ministries Inc",
    "wof:placetype":"venue"
},
  "geometry": {"coordinates":[-84.227091,31.523538],"type":"Point"}
}