{
  "type": "Feature",
  "properties": {
    "addr:full":"1497 Watsons Pl Lawrenceville GA 30043",
    "addr:housenumber":"1497",
    "addr:postcode":"30043",
    "addr:street":"Watsons Pl",
    "iso:country":"US",
    "sg:address":"1497 Watsons Pl",
    "sg:city":"Lawrenceville",
    "sg:classifiers":[
        {
            "category":"Home & Garden",
            "subcategory":"Home Furnishings",
            "type":"Retail Goods"
        }
    ],
    "sg:phone":"+1 770 963 3764",
    "sg:postcode":"30043",
    "sg:province":"GA",
    "wof:name":"Fabulous Fabrications",
    "wof:placetype":"venue"
},
  "geometry": {"coordinates":[-84.065758,33.989278],"type":"Point"}
}