{
  "type": "Feature",
  "properties": {
    "addr:full":"110 Gladwyne Ct Alpharetta GA 30004",
    "addr:housenumber":"110",
    "addr:postcode":"30004",
    "addr:street":"Gladwyne Ct",
    "iso:country":"US",
    "sg:address":"110 Gladwyne Ct",
    "sg:city":"Alpharetta",
    "sg:classifiers":[
        {
            "category":"Shopping",
            "subcategory":"Books",
            "type":"Retail Goods"
        }
    ],
    "sg:phone":"+1 770 569 0530",
    "sg:postcode":"30004",
    "sg:province":"GA",
    "wof:name":"Mmi Campus Bookstore",
    "wof:placetype":"venue"
},
  "geometry": {"coordinates":[-84.360209,34.11539],"type":"Point"}
}