{
  "type": "Feature",
  "properties": {
    "addr:full":"3704 12th Ave Columbus GA 31904",
    "addr:housenumber":"3704",
    "addr:postcode":"31904",
    "addr:street":"12Th Ave",
    "iso:country":"US",
    "sg:address":"3704 12th Ave",
    "sg:city":"Columbus",
    "sg:classifiers":[
        {
            "category":"Building & Trades",
            "subcategory":"Plumbing",
            "type":"Services"
        }
    ],
    "sg:phone":"+1 706 327 8583",
    "sg:postcode":"31904",
    "sg:province":"GA",
    "sg:tags":[
        "conditioning",
        "air",
        "system",
        "contractor"
    ],
    "sg:website":"www.holbrookserviceinc.com",
    "wof:name":"Holbrook Service Co",
    "wof:placetype":"venue"
},
  "geometry": {"coordinates":[-84.97566,32.499494],"type":"Point"}
}