{
  "type": "Feature",
  "properties": {
    "addr:full":"20 State Rte 193 Flintstone GA 30725",
    "addr:housenumber":"20",
    "addr:postcode":"30725",
    "addr:street":"State Rte 193 Flintstone",
    "iso:country":"US",
    "sg:address":"20 State Rte 193",
    "sg:city":"Flintstone",
    "sg:classifiers":[
        {
            "category":"Autos & Motor Vehicles",
            "subcategory":"Fuel & Gas Station",
            "type":"Retail Goods"
        }
    ],
    "sg:phone":"+1 706 820 8179",
    "sg:postcode":"30725",
    "sg:province":"GA",
    "sg:tags":[
        "station",
        "gasoline"
    ],
    "wof:name":"Conocophillips Holding Company",
    "wof:placetype":"venue"
},
  "geometry": {"coordinates":[-85.33441000000001,34.981729],"type":"Point"}
}