{
  "type": "Feature",
  "properties": {
    "iso:country":"US",
    "sg:address":"264 Eagle Landing Dr",
    "sg:city":"Flintstone",
    "sg:classifiers":[
        {
            "category":"Food & Beverages",
            "subcategory":"Groceries & Convenience Stores",
            "type":"Retail Goods"
        }
    ],
    "sg:phone":"+1 706 861 2994",
    "sg:postcode":"30725",
    "sg:province":"GA",
    "sg:tags":[
        "grocer"
    ],
    "wof:name":"Mr Jack's",
    "wof:placetype":"venue"
},
  "geometry": {"coordinates":[-85.35045700000001,34.920432],"type":"Point"}
}