{
  "type": "Feature",
  "properties": {
    "addr:full":"2006 Oakdale Dr Valdosta GA 31602",
    "addr:housenumber":"2006",
    "addr:postcode":"31602",
    "addr:street":"Oakdale Dr",
    "iso:country":"US",
    "sg:address":"2006 Oakdale Dr",
    "sg:city":"Valdosta",
    "sg:classifiers":[
        {
            "category":"Real Estate",
            "subcategory":"Real Estate Agent",
            "type":"Services"
        }
    ],
    "sg:phone":"+1 229 219 0899",
    "sg:postcode":"31602",
    "sg:province":"GA",
    "sg:tags":[
        "appraiser"
    ],
    "wof:name":"Advanced Real State Svc",
    "wof:placetype":"venue"
},
  "geometry": {"coordinates":[-83.32011300000001,30.850129],"type":"Point"}
}