{
  "type": "Feature",
  "properties": {
    "addr:full":"111 Hurricane Shoals Rd NE Lawrenceville GA 30045",
    "addr:housenumber":"111",
    "addr:postcode":"30045",
    "addr:street":"Hurricane Shoals Rd Ne",
    "iso:country":"US",
    "sg:address":"111 Hurricane Shoals Rd NE",
    "sg:city":"Lawrenceville",
    "sg:classifiers":[
        {
            "category":"Utilities",
            "subcategory":"Refuse",
            "type":"Services"
        }
    ],
    "sg:phone":"+1 770 682 0035",
    "sg:postcode":"30045",
    "sg:province":"GA",
    "sg:tags":[
        "system"
    ],
    "wof:name":"BFI",
    "wof:placetype":"venue"
},
  "geometry": {"coordinates":[-83.987668,33.974106],"type":"Point"}
}