{
  "type": "Feature",
  "properties": {
    "addr:full":"329 E Ridgeway Rd Commerce GA 30529",
    "addr:housenumber":"329",
    "addr:postcode":"30529",
    "addr:street":"E Ridgeway Rd",
    "iso:country":"US",
    "sg:address":"329 E Ridgeway Rd",
    "sg:city":"Commerce",
    "sg:classifiers":[
        {
            "category":"Wholesale",
            "subcategory":"Plants",
            "type":"Manufacturing & Wholesale Goods"
        }
    ],
    "sg:phone":"+1 706 335 2455",
    "sg:postcode":"30529",
    "sg:province":"GA",
    "sg:tags":[
        "florist"
    ],
    "wof:name":"Piedmont Floral Supply",
    "wof:placetype":"venue"
},
  "geometry": {"coordinates":[-83.46848799999999,34.257216],"type":"Point"}
}