{
  "type": "Feature",
  "properties": {
    "iso:country":"US",
    "sg:address":"5482 Chamblee Dunwoody Rd",
    "sg:city":"Atlanta",
    "sg:classifiers":[
        {
            "category":"Restaurant",
            "type":"Food & Drink"
        }
    ],
    "sg:menulink":"http://www.allmenus.com/ga/chamblee-doraville/185695-j-christophers/menu/",
    "sg:phone":"+1 770 395 1642",
    "sg:postcode":"30338",
    "sg:province":"GA",
    "sg:tags":[
        "american"
    ],
    "wof:name":"J. Christopher's",
    "wof:placetype":"venue"
},
  "geometry": {"coordinates":[-84.335658,33.948045],"type":"Point"}
}