{
  "type": "Feature",
  "properties": {
    "addr:full":"1409 Browns Bridge Rd Gainesville GA 30501",
    "addr:housenumber":"1409",
    "addr:postcode":"30501",
    "addr:street":"Browns Bridge Rd",
    "iso:country":"US",
    "sg:address":"1409 Browns Bridge Rd",
    "sg:city":"Gainesville",
    "sg:classifiers":[
        {
            "category":"Restaurant",
            "type":"Food & Drink"
        }
    ],
    "sg:menulink":"http://www.allmenus.com/ga/gainesville/196016-taco-bell/menu/",
    "sg:postcode":"30501",
    "sg:province":"GA",
    "sg:tags":[
        "mexican"
    ],
    "wof:name":"Taco Bell",
    "wof:placetype":"venue"
},
  "geometry": {"coordinates":[-83.841898,34.286094],"type":"Point"}
}