{
  "type": "Feature",
  "properties": {
    "iso:country":"US",
    "sg:address":"4414 Dunriver Dr SW",
    "sg:city":"Lilburn",
    "sg:classifiers":[
        {
            "category":"Manufacturing",
            "subcategory":"Printing",
            "type":"Manufacturing & Wholesale Goods"
        }
    ],
    "sg:phone":"+1 770 717 1724",
    "sg:postcode":"30047",
    "sg:province":"GA",
    "sg:tags":[
        "typesetting"
    ],
    "wof:name":"Woodard Typesetting & Graphics",
    "wof:placetype":"venue"
},
  "geometry": {"coordinates":[-84.10647,33.866818],"type":"Point"}
}