{
  "type": "Feature",
  "properties": {
    "iso:country":"US",
    "sg:address":"780 Johnson Ferry Rd NE Fifth Floor",
    "sg:city":"Atlanta",
    "sg:classifiers":[
        {
            "category":"Communications",
            "subcategory":"Radio Station",
            "type":"Services"
        }
    ],
    "sg:phone":"+1 404 741 4999",
    "sg:postcode":"30342",
    "sg:province":"GA",
    "sg:website":"www.99x.com",
    "wof:name":"99X at 97.9",
    "wof:placetype":"venue"
},
  "geometry": {"coordinates":[-84.36337399999999,33.907385],"type":"Point"}
}