{
  "type": "Feature",
  "properties": {
    "iso:country":"US",
    "sg:address":"3000 Moreland Ave",
    "sg:city":"Conley",
    "sg:classifiers":[
        {
            "category":"Building & Trades",
            "subcategory":"Locksmith",
            "type":"Services"
        }
    ],
    "sg:phone":"+1 404 720 5053",
    "sg:postcode":"30288",
    "sg:province":"GA",
    "sg:tags":[
        "key"
    ],
    "wof:name":"L O C K Smith 1 A1",
    "wof:placetype":"venue"
},
  "geometry": {"coordinates":[-84.340166,33.669002],"type":"Point"}
}