{
  "type": "Feature",
  "properties": {
    "iso:country":"US",
    "sg:address":"1470 Dorchester Dr",
    "sg:city":"Lawrenceville",
    "sg:classifiers":[
        {
            "category":"Health Services",
            "subcategory":"Medical Lab",
            "type":"Services"
        }
    ],
    "sg:phone":"+1 770 339 4046",
    "sg:postcode":"30043",
    "sg:province":"GA",
    "sg:tags":[
        "dental"
    ],
    "wof:name":"Metro Crown & Bridge Lab",
    "wof:placetype":"venue"
},
  "geometry": {"coordinates":[-84.013839,33.992991],"type":"Point"}
}