{
  "type": "Feature",
  "properties": {
    "iso:country":"US",
    "sg:address":"1921 Ledo Rd",
    "sg:city":"Albany",
    "sg:classifiers":[
        {
            "category":"Shopping",
            "subcategory":"Used Merchandise",
            "type":"Retail Goods"
        }
    ],
    "sg:phone":"+1 229 435 1515",
    "sg:postcode":"31707",
    "sg:province":"GA",
    "wof:name":"Southern Heritage Antiques",
    "wof:placetype":"venue"
},
  "geometry": {"coordinates":[-84.18847700000001,31.6226],"type":"Point"}
}