{
  "type": "Feature",
  "properties": {
    "addr:full":"6752 Songwood Dr Austell GA 30168",
    "addr:housenumber":"6752",
    "addr:postcode":"30168",
    "addr:street":"Songwood Dr",
    "iso:country":"US",
    "sg:address":"6752 Songwood Dr",
    "sg:city":"Austell",
    "sg:classifiers":[
        {
            "category":"Freight",
            "type":"Transportation"
        }
    ],
    "sg:phone":"+1 770 944 1737",
    "sg:postcode":"30168",
    "sg:province":"GA",
    "sg:tags":[
        "local",
        "storage",
        "trucking"
    ],
    "wof:name":"James Eichelberger",
    "wof:placetype":"venue"
},
  "geometry": {"coordinates":[-84.596801,33.790185],"type":"Point"}
}