{
  "type": "Feature",
  "properties": {
    "addr:full":"4 N Gill St Hazlehurst GA 31539",
    "addr:housenumber":"4",
    "addr:postcode":"31539",
    "addr:street":"N Gill St",
    "iso:country":"US",
    "sg:address":"4 N Gill St",
    "sg:city":"Hazlehurst",
    "sg:classifiers":[
        {
            "category":"Home & Garden",
            "subcategory":"Building Materials",
            "type":"Retail Goods"
        }
    ],
    "sg:phone":"+1 912 375 4415",
    "sg:postcode":"31539",
    "sg:province":"GA",
    "sg:tags":[
        "siding"
    ],
    "wof:name":"Corbitt Siding Supply",
    "wof:placetype":"venue"
},
  "geometry": {"coordinates":[-82.59353299999999,31.863875],"type":"Point"}
}