{
  "type": "Feature",
  "properties": {
    "iso:country":"US",
    "sg:address":"312 E Lake Ave",
    "sg:city":"Rossville",
    "sg:classifiers":[
        {
            "category":"Professional",
            "subcategory":"Lawyer & Legal Services",
            "type":"Services"
        }
    ],
    "sg:phone":"+1 706 858 9990",
    "sg:postcode":"30741",
    "sg:province":"GA",
    "sg:tags":[
        "attorney"
    ],
    "wof:name":"Setters Law Office",
    "wof:placetype":"venue"
},
  "geometry": {"coordinates":[-85.28439899999999,34.98171],"type":"Point"}
}