{
  "type": "Feature",
  "properties": {
    "iso:country":"US",
    "sg:address":"1214 N Columbia Ave",
    "sg:city":"Rincon",
    "sg:classifiers":[
        {
            "category":"Personal",
            "subcategory":"Beauty Salon",
            "type":"Services"
        }
    ],
    "sg:phone":"+1 912 826 1124",
    "sg:postcode":"31326",
    "sg:province":"GA",
    "wof:name":"Von'sauna Salon",
    "wof:placetype":"venue"
},
  "geometry": {"coordinates":[-81.243889,32.302795],"type":"Point"}
}