{
  "type": "Feature",
  "properties": {
    "iso:country":"US",
    "sg:address":"1326 Broad St",
    "sg:city":"Augusta",
    "sg:classifiers":[
        {
            "category":"Organizations",
            "subcategory":"Religious Organization",
            "type":"Services"
        }
    ],
    "sg:phone":"+1 706 722 7348",
    "sg:postcode":"30901",
    "sg:province":"GA",
    "sg:tags":[
        "church"
    ],
    "sg:website":"www.curtisbaptist.org",
    "wof:name":"Curtis Baptist Church",
    "wof:placetype":"venue"
},
  "geometry": {"coordinates":[-81.977647,33.479397],"type":"Point"}
}