{
  "type": "Feature",
  "properties": {
    "addr:full":"101 Brian Dr Warner Robins GA 31088",
    "addr:housenumber":"101",
    "addr:postcode":"31088",
    "addr:street":"Brian Dr",
    "iso:country":"US",
    "sg:address":"101 Brian Dr",
    "sg:city":"Warner Robins",
    "sg:classifiers":[
        {
            "category":"Professional",
            "subcategory":"Management & Consulting",
            "type":"Services"
        }
    ],
    "sg:phone":"+1 478 953 0274",
    "sg:postcode":"31088",
    "sg:province":"GA",
    "sg:tags":[
        "logistics"
    ],
    "wof:name":"Lesley A Bledsoe",
    "wof:placetype":"venue"
},
  "geometry": {"coordinates":[-83.695458,32.606992],"type":"Point"}
}