{
  "type": "Feature",
  "properties": {
    "addr:full":"2595 Baker Rd Acworth GA 30101",
    "addr:housenumber":"2595",
    "addr:postcode":"30101",
    "addr:street":"Baker Rd",
    "iso:country":"US",
    "sg:address":"2595 Baker Rd",
    "sg:city":"Acworth",
    "sg:classifiers":[
        {
            "category":"Home & Garden",
            "subcategory":"Furniture",
            "type":"Retail Goods"
        }
    ],
    "sg:phone":"+1 678 574 3444",
    "sg:postcode":"30101",
    "sg:province":"GA",
    "wof:name":"Peach State Kitchens",
    "wof:placetype":"venue"
},
  "geometry": {"coordinates":[-84.625212,34.065332],"type":"Point"}
}