{
  "type": "Feature",
  "properties": {
    "addr:full":"2746 Riverside Dr Macon GA 31204",
    "addr:housenumber":"2746",
    "addr:postcode":"31204",
    "addr:street":"Riverside Dr",
    "iso:country":"US",
    "sg:address":"2746 Riverside Dr",
    "sg:city":"Macon",
    "sg:classifiers":[
        {
            "category":"Food & Beverages",
            "subcategory":"Groceries & Convenience Stores",
            "type":"Retail Goods"
        }
    ],
    "sg:phone":"+1 478 746 9817",
    "sg:postcode":"31204",
    "sg:province":"GA",
    "wof:name":"Minifoods",
    "wof:placetype":"venue"
},
  "geometry": {"coordinates":[-83.66436,32.874905],"type":"Point"}
}