{
  "type": "Feature",
  "properties": {
    "iso:country":"US",
    "sg:address":"204 Waterwood Bend",
    "sg:city":"Peachtree City",
    "sg:classifiers":[
        {
            "category":"Wholesale",
            "subcategory":"Metals & Minerals",
            "type":"Manufacturing & Wholesale Goods"
        }
    ],
    "sg:phone":"+1 770 487 0585",
    "sg:postcode":"30269",
    "sg:province":"GA",
    "sg:tags":[
        "center"
    ],
    "wof:name":"Structural Detailing Service",
    "wof:placetype":"venue"
},
  "geometry": {"coordinates":[-84.57192499999999,33.40462],"type":"Point"}
}