{
  "type": "Feature",
  "properties": {
    "iso:country":"US",
    "sg:address":"5575 Hunters Forest Ln",
    "sg:city":"Atlanta",
    "sg:classifiers":[
        {
            "category":"Communications",
            "subcategory":"Film & Video Production",
            "type":"Services"
        }
    ],
    "sg:phone":"+1 404 766 9749",
    "sg:postcode":"30349",
    "sg:province":"GA",
    "sg:tags":[
        "motion"
    ],
    "wof:name":"Pan Jam Production Inc",
    "wof:placetype":"venue"
},
  "geometry": {"coordinates":[-84.462585,33.601719],"type":"Point"}
}