{
  "type": "Feature",
  "properties": {
    "iso:country":"US",
    "sg:address":"2208 Goode Rd",
    "sg:city":"Conyers",
    "sg:classifiers":[
        {
            "category":"Real Estate",
            "subcategory":"Real Estate Services",
            "type":"Services"
        },
        {
            "category":"Real Estate",
            "subcategory":"Real Estate Agent",
            "type":"Services"
        }
    ],
    "sg:phone":"+1 770 922 2108",
    "sg:postcode":"30094",
    "sg:province":"GA",
    "sg:tags":[
        "buyer",
        "broker"
    ],
    "sg:website":"http://www.atlrealestategroup.com",
    "wof:name":"Atl Real Estate Group",
    "wof:placetype":"venue"
},
  "geometry": {"coordinates":[-84.05910900000001,33.605126],"type":"Point"}
}