{
  "type": "Feature",
  "properties": {
    "iso:country":"US",
    "sg:address":"3280 Peachtree Corners Cir",
    "sg:city":"Norcross",
    "sg:classifiers":[
        {
            "category":"Professional",
            "type":"Services"
        }
    ],
    "sg:phone":"+1 770 729 0880",
    "sg:postcode":"30092",
    "sg:province":"GA",
    "sg:tags":[
        "establishment"
    ],
    "wof:name":"Ecofreeze Co",
    "wof:placetype":"venue"
},
  "geometry": {"coordinates":[-84.250885,33.945306],"type":"Point"}
}