{
  "type": "Feature",
  "properties": {
    "addr:full":"3167 Peachtree Dr NE Atlanta GA 30305",
    "addr:housenumber":"3167",
    "addr:postcode":"30305",
    "addr:street":"Peachtree Dr Ne",
    "iso:country":"US",
    "sg:address":"3167 Peachtree Dr NE",
    "sg:city":"Atlanta",
    "sg:classifiers":[
        {
            "category":"Sports & Exercise",
            "subcategory":"Gym",
            "type":"Entertainment"
        }
    ],
    "sg:phone":"+1 404 233 2588",
    "sg:postcode":"30305",
    "sg:province":"GA",
    "sg:tags":[
        "shop",
        "fitness",
        "physical",
        "beauty",
        "facility"
    ],
    "sg:website":"www.milaeuropeanspa.com",
    "wof:name":"Mila European Spa",
    "wof:placetype":"venue"
},
  "geometry": {"coordinates":[-84.362863,33.842433],"type":"Point"}
}