{
  "type": "Feature",
  "properties": {
    "iso:country":"US",
    "sg:address":"618 N Church St",
    "sg:city":"Thomaston",
    "sg:classifiers":[
        {
            "category":"Health Services",
            "subcategory":"Doctor",
            "type":"Services"
        }
    ],
    "sg:phone":"+1 706 647 4633",
    "sg:postcode":"30286",
    "sg:province":"GA",
    "sg:tags":[
        "dentist"
    ],
    "wof:name":"Dobbs M Drennan Jr DDS",
    "wof:placetype":"venue"
},
  "geometry": {"coordinates":[-84.327917,32.896843],"type":"Point"}
}