{
  "type": "Feature",
  "properties": {
    "iso:country":"US",
    "sg:address":"2817 Sardis St NW",
    "sg:city":"Kennesaw",
    "sg:classifiers":[
        {
            "category":"Professional",
            "subcategory":"Computer Services",
            "type":"Services"
        }
    ],
    "sg:phone":"+1 770 427 7583",
    "sg:postcode":"30144",
    "sg:province":"GA",
    "sg:tags":[
        "technical",
        "assistance",
        "support",
        "data",
        "recovery"
    ],
    "wof:name":"Ferris One Internet Solutions",
    "wof:placetype":"venue"
},
  "geometry": {"coordinates":[-84.611752,34.02125],"type":"Point"}
}