{
  "type": "Feature",
  "properties": {
    "addr:full":"951 Auburn Rd Dacula GA 30019",
    "addr:housenumber":"951",
    "addr:postcode":"ga 30019",
    "addr:street":"Auburn Rd",
    "iso:country":"US",
    "sg:address":"951 Auburn Rd",
    "sg:city":"Dacula",
    "sg:classifiers":[
        {
            "category":"Building & Trades",
            "subcategory":"Construction",
            "type":"Services"
        }
    ],
    "sg:phone":"+1 404 216 3147",
    "sg:postcode":"30019",
    "sg:province":"GA",
    "sg:tags":[
        "residential"
    ],
    "wof:name":"P C I Inc",
    "wof:placetype":"venue"
},
  "geometry": {"coordinates":[-83.88436799999999,34.031456],"type":"Point"}
}