{
  "type": "Feature",
  "properties": {
    "addr:full":"4805 Kitty Hawk Dr NE Atlanta GA 30342",
    "addr:housenumber":"4805",
    "addr:postcode":"30342",
    "addr:street":"Kitty Hawk Dr Ne",
    "iso:country":"US",
    "sg:address":"4805 Kitty Hawk Dr NE",
    "sg:city":"Atlanta",
    "sg:classifiers":[
        {
            "category":"Professional",
            "subcategory":"Business Services",
            "type":"Services"
        }
    ],
    "sg:phone":"+1 404 705 9791",
    "sg:postcode":"30342",
    "sg:province":"GA",
    "wof:name":"DME Enterprises Inc",
    "wof:placetype":"venue"
},
  "geometry": {"coordinates":[-84.383154,33.88799],"type":"Point"}
}