{
  "type": "Feature",
  "properties": {
    "iso:country":"US",
    "sg:address":"4010 Wisteria Ln SW",
    "sg:city":"Atlanta",
    "sg:classifiers":[
        {
            "category":"Shopping",
            "subcategory":"Gifts & Souvenirs",
            "type":"Retail Goods"
        }
    ],
    "sg:phone":"+1 404 865 8098",
    "sg:postcode":"30331",
    "sg:province":"GA",
    "sg:tags":[
        "shop"
    ],
    "wof:name":"Bap's Cap & Partners",
    "wof:placetype":"venue"
},
  "geometry": {"coordinates":[-84.509787,33.758345],"type":"Point"}
}