{
  "type": "Feature",
  "properties": {
    "iso:country":"US",
    "sg:address":"310 Jep Wheeler Ln",
    "sg:city":"Woodstock",
    "sg:classifiers":[
        {
            "category":"Professional",
            "subcategory":"Business Services",
            "type":"Services"
        }
    ],
    "sg:phone":"+1 770 928 8580",
    "sg:postcode":"30188",
    "sg:province":"GA",
    "wof:name":"Frank Welch",
    "wof:placetype":"venue"
},
  "geometry": {"coordinates":[-84.41785299999999,34.135668],"type":"Point"}
}