{
  "type": "Feature",
  "properties": {
    "addr:full":"3002 Kingston Ct Marietta GA 30067",
    "addr:housenumber":"3002",
    "addr:postcode":"30067",
    "addr:street":"Kingston Ct",
    "iso:country":"US",
    "sg:address":"3002 Kingston Ct",
    "sg:city":"Marietta",
    "sg:classifiers":[
        {
            "category":"Building & Trades",
            "subcategory":"Cleaning & Sanitation",
            "type":"Services"
        }
    ],
    "sg:phone":"+1 770 955 6711",
    "sg:postcode":"30067",
    "sg:province":"GA",
    "sg:tags":[
        "maintenance"
    ],
    "wof:name":"Redlee/Scs Inc",
    "wof:placetype":"venue"
},
  "geometry": {"coordinates":[-84.492001,33.923978],"type":"Point"}
}