{
  "type": "Feature",
  "properties": {
    "iso:country":"US",
    "sg:address":"6049 Roswell Rd NE",
    "sg:city":"Atlanta",
    "sg:classifiers":[
        {
            "category":"Restaurant",
            "type":"Food & Drink"
        }
    ],
    "sg:menulink":"http://www.allmenus.com/ga/atlanta/202560-mcdonalds/menu/",
    "sg:postcode":"30328",
    "sg:province":"GA",
    "sg:tags":[
        "burger",
        "american"
    ],
    "wof:name":"McDonald's",
    "wof:placetype":"venue"
},
  "geometry": {"coordinates":[-84.37855500000001,33.919803],"type":"Point"}
}