{
  "type": "Feature",
  "properties": {
    "iso:country":"US",
    "sg:address":"248 Bobby Jones Expy",
    "sg:city":"Augusta",
    "sg:classifiers":[
        {
            "category":"Shopping",
            "type":"Retail Goods"
        },
        {
            "category":"Food & Beverages",
            "subcategory":"Bakery",
            "type":"Retail Goods"
        }
    ],
    "sg:phone":"+1 706 855 7840",
    "sg:postcode":"30907",
    "sg:province":"GA",
    "sg:tags":[
        "cake",
        "equipment",
        "decorating",
        "supply"
    ],
    "wof:name":"Arnold's Party Pantry",
    "wof:placetype":"venue"
},
  "geometry": {"coordinates":[-82.09444999999999,33.50979],"type":"Point"}
}