{
  "type": "Feature",
  "properties": {
    "iso:country":"US",
    "sg:address":"107 Jefferson St",
    "sg:city":"Newnan",
    "sg:classifiers":[
        {
            "category":"Manufacturing",
            "subcategory":"Signs",
            "type":"Manufacturing & Wholesale Goods"
        }
    ],
    "sg:phone":"+1 770 253 6444",
    "sg:postcode":"30263",
    "sg:province":"GA",
    "sg:tags":[
        "stencil",
        "supply"
    ],
    "sg:website":"www.deesigns.com",
    "wof:name":"Dee-Signs LTD",
    "wof:placetype":"venue"
},
  "geometry": {"coordinates":[-84.795132,33.382089],"type":"Point"}
}