{
  "type": "Feature",
  "properties": {
    "iso:country":"US",
    "sg:address":"360 Skyview Dr",
    "sg:city":"Cleveland",
    "sg:classifiers":[
        {
            "category":"Building & Trades",
            "subcategory":"Construction",
            "type":"Services"
        }
    ],
    "sg:phone":"+1 706 865 5201",
    "sg:postcode":"30528",
    "sg:province":"GA",
    "sg:tags":[
        "contractor"
    ],
    "wof:name":"Ricky Pardue Construction",
    "wof:placetype":"venue"
},
  "geometry": {"coordinates":[-83.731989,34.517196],"type":"Point"}
}