{
  "type": "Feature",
  "properties": {
    "addr:full":"2881 3rd Ave SW Atlanta GA 30315",
    "addr:housenumber":"2881",
    "addr:postcode":"30315",
    "addr:street":"3Rd Ave Sw",
    "iso:country":"US",
    "sg:address":"2881 3rd Ave SW",
    "sg:city":"Atlanta",
    "sg:classifiers":[
        {
            "category":"Building & Trades",
            "subcategory":"Construction",
            "type":"Services"
        }
    ],
    "sg:phone":"+1 404 684 0160",
    "sg:postcode":"30315",
    "sg:province":"GA",
    "sg:tags":[
        "house"
    ],
    "wof:name":"Georgia Peach Construction",
    "wof:placetype":"venue"
},
  "geometry": {"coordinates":[-84.404338,33.676234],"type":"Point"}
}