{
  "type": "Feature",
  "properties": {
    "addr:full":"1520 Atlanta Hwy Auburn GA 30011",
    "addr:housenumber":"1520",
    "addr:postcode":"30011",
    "addr:street":"Atlanta Hwy",
    "iso:country":"US",
    "sg:address":"1520 Atlanta Hwy",
    "sg:city":"Auburn",
    "sg:classifiers":[
        {
            "category":"Restaurant",
            "type":"Food & Drink"
        }
    ],
    "sg:menulink":"http://www.allmenus.com/ga/auburn/88879-papas-pizza-to-go/menu/",
    "sg:phone":"+1 770 682 9796",
    "sg:postcode":"30011",
    "sg:province":"GA",
    "sg:tags":[
        "american",
        "pizza"
    ],
    "wof:name":"Papas Pizza To Go",
    "wof:placetype":"venue"
},
  "geometry": {"coordinates":[-83.839444,34.011583],"type":"Point"}
}