{
  "type": "Feature",
  "properties": {
    "iso:country":"US",
    "sg:address":"3391 Peachtree Rd NE Ste 105",
    "sg:city":"Atlanta",
    "sg:classifiers":[
        {
            "category":"Shopping",
            "subcategory":"Clothing, Apparel, & Fashions",
            "type":"Retail Goods"
        }
    ],
    "sg:phone":"+1 404 321 1608",
    "sg:postcode":"30326",
    "sg:province":"GA",
    "sg:tags":[
        "clothing",
        "women's"
    ],
    "sg:website":"www.spanx.com",
    "wof:name":"Spanx",
    "wof:placetype":"venue"
},
  "geometry": {"coordinates":[-84.36552399999999,33.848753],"type":"Point"}
}