{
  "type": "Feature",
  "properties": {
    "addr:full":"2212 US Hwy 41 South SE Calhoun GA 30701",
    "addr:housenumber":"2212",
    "addr:postcode":"30701",
    "addr:street":"Us Hwy 41 South Se",
    "iso:country":"US",
    "sg:address":"2212 US Hwy 41 South SE",
    "sg:city":"Calhoun",
    "sg:classifiers":[
        {
            "category":"Wholesale",
            "subcategory":"Machinery & Supplies",
            "type":"Manufacturing & Wholesale Goods"
        }
    ],
    "sg:phone":"+1 706 629 0664",
    "sg:postcode":"30701",
    "sg:province":"GA",
    "wof:name":"Russell Farm Equipment",
    "wof:placetype":"venue"
},
  "geometry": {"coordinates":[-84.93553300000001,34.44825],"type":"Point"}
}