{
  "type": "Feature",
  "properties": {
    "iso:country":"US",
    "sg:address":"753 Broad St",
    "sg:city":"Augusta",
    "sg:classifiers":[
        {
            "category":"Organizations",
            "subcategory":"Membership Organization",
            "type":"Services"
        }
    ],
    "sg:phone":"+1 706 312 5263",
    "sg:postcode":"30901",
    "sg:province":"GA",
    "wof:name":"Central Savannah River Land Tr",
    "wof:placetype":"venue"
},
  "geometry": {"coordinates":[-81.965091,33.47535],"type":"Point"}
}