{
  "type": "Feature",
  "properties": {
    "addr:full":"1804 Over Lake Dr SE Ste A Conyers GA 30013",
    "addr:housenumber":"1804",
    "addr:postcode":"30013",
    "addr:street":"Over Lake Dr Se Ste A",
    "iso:country":"US",
    "sg:address":"1804 Over Lake Dr SE Ste A",
    "sg:city":"Conyers",
    "sg:classifiers":[
        {
            "category":"Banks & Credit Unions",
            "subcategory":"Investment Brokerage",
            "type":"Services"
        }
    ],
    "sg:phone":"+1 770 760 8933",
    "sg:postcode":"30013",
    "sg:province":"GA",
    "sg:tags":[
        "investing"
    ],
    "wof:name":"Sanders Preston F",
    "wof:placetype":"venue"
},
  "geometry": {"coordinates":[-83.992699,33.624199],"type":"Point"}
}