{
  "type": "Feature",
  "properties": {
    "addr:full":"50 W Main St Blue Ridge GA 30513",
    "addr:housenumber":"50",
    "addr:postcode":"30513",
    "addr:street":"W Main St",
    "iso:country":"US",
    "sg:address":"50 W Main St",
    "sg:city":"Blue Ridge",
    "sg:classifiers":[
        {
            "category":"Organizations",
            "subcategory":"Religious Organization",
            "type":"Services"
        }
    ],
    "sg:phone":"+1 706 632 5857",
    "sg:postcode":"30513",
    "sg:province":"GA",
    "sg:tags":[
        "church"
    ],
    "wof:name":"Temple Baptist Church",
    "wof:placetype":"venue"
},
  "geometry": {"coordinates":[-84.323127,34.868144],"type":"Point"}
}