{
  "type": "Feature",
  "properties": {
    "iso:country":"US",
    "sg:address":"8490 Tara Blvd",
    "sg:city":"Jonesboro",
    "sg:classifiers":[
        {
            "category":"Restaurant",
            "type":"Food & Drink"
        }
    ],
    "sg:phone":"+1 770 473 9030",
    "sg:postcode":"30236",
    "sg:province":"GA",
    "sg:tags":[
        "eating"
    ],
    "wof:name":"Arbys",
    "wof:placetype":"venue"
},
  "geometry": {"coordinates":[-84.363382,33.519044],"type":"Point"}
}