{
  "type": "Feature",
  "properties": {
    "addr:full":"4788 Washington Rd Evans GA 30809",
    "addr:housenumber":"4788",
    "addr:postcode":"30809",
    "addr:street":"Washington Rd",
    "iso:country":"US",
    "sg:address":"4788 Washington Rd",
    "sg:city":"Evans",
    "sg:classifiers":[
        {
            "category":"Retail",
            "subcategory":"Auto Repair",
            "type":"Services"
        }
    ],
    "sg:phone":"+1 706 868 7213",
    "sg:postcode":"30809",
    "sg:province":"GA",
    "sg:tags":[
        "body",
        "automotive"
    ],
    "wof:name":"Cushmans Pnt & Bdy & Wrckr Svc",
    "wof:placetype":"venue"
},
  "geometry": {"coordinates":[-82.171615,33.562394],"type":"Point"}
}