{
  "type": "Feature",
  "properties": {
    "addr:full":"182 Longview Rd Fayetteville GA 30214",
    "addr:housenumber":"182",
    "addr:postcode":"30214",
    "addr:street":"Longview Rd",
    "iso:country":"US",
    "sg:address":"182 Longview Rd",
    "sg:city":"Fayetteville",
    "sg:classifiers":[
        {
            "category":"Utilities",
            "subcategory":"Refuse",
            "type":"Services"
        }
    ],
    "sg:phone":"+1 770 716 2526",
    "sg:postcode":"30214",
    "sg:province":"GA",
    "sg:tags":[
        "garbage",
        "collection"
    ],
    "wof:name":"Rainbow Trash Removal",
    "wof:placetype":"venue"
},
  "geometry": {"coordinates":[-84.452737,33.491621],"type":"Point"}
}