{
  "type": "Feature",
  "properties": {
    "iso:country":"US",
    "sg:address":"425 Chappell Road NW",
    "sg:city":"Atlanta",
    "sg:classifiers":[
        {
            "category":"Real Estate",
            "subcategory":"Real Estate Operator",
            "type":"Services"
        }
    ],
    "sg:phone":"+1 404 874 8232",
    "sg:postcode":"30318",
    "sg:province":"GA",
    "sg:tags":[
        "apartment"
    ],
    "wof:name":"Vintage Investment Properties",
    "wof:placetype":"venue"
},
  "geometry": {"coordinates":[-84.432475,33.76672],"type":"Point"}
}