{
  "type": "Feature",
  "properties": {
    "iso:country":"US",
    "sg:address":"984 Georgian Pt",
    "sg:city":"Lawrenceville",
    "sg:classifiers":[
        {
            "category":"Professional",
            "subcategory":"Business Services",
            "type":"Services"
        }
    ],
    "sg:phone":"+1 770 456 5586",
    "sg:postcode":"30045",
    "sg:province":"GA",
    "sg:tags":[
        "integration"
    ],
    "wof:name":"Denson Technology Co",
    "wof:placetype":"venue"
},
  "geometry": {"coordinates":[-83.937725,33.954068],"type":"Point"}
}