{
  "type": "Feature",
  "properties": {
    "iso:country":"US",
    "sg:address":"185 Veterans Memorial Hwy Ste 109",
    "sg:city":"Mableton",
    "sg:classifiers":[
        {
            "category":"Fast Food",
            "type":"Food & Drink"
        },
        {
            "category":"Restaurant",
            "type":"Food & Drink"
        },
        {
            "category":"Food & Beverages",
            "subcategory":"Ethnic Foods",
            "type":"Retail Goods"
        }
    ],
    "sg:phone":"+1 770 745 0070",
    "sg:postcode":"30126",
    "sg:province":"GA",
    "sg:tags":[
        "chicken",
        "southern",
        "wing",
        "soul"
    ],
    "sg:website":"flavorsgrillseafood.yolasite.com/",
    "wof:name":"Flavors Grill & Seafood",
    "wof:placetype":"venue"
},
  "geometry": {"coordinates":[-84.56088200000001,33.812658],"type":"Point"}
}