{
  "type": "Feature",
  "properties": {
    "addr:full":"1204 Moody Rd Warner Robins GA 31088",
    "addr:housenumber":"1204",
    "addr:postcode":"31088",
    "addr:street":"Moody Rd",
    "iso:country":"US",
    "sg:address":"1204 Moody Rd",
    "sg:city":"Warner Robins",
    "sg:classifiers":[
        {
            "category":"Professional",
            "type":"Services"
        }
    ],
    "sg:phone":"+1 478 922 2886",
    "sg:postcode":"31088",
    "sg:province":"GA",
    "wof:name":"Bessie Campbell",
    "wof:placetype":"venue"
},
  "geometry": {"coordinates":[-83.61434800000001,32.599854],"type":"Point"}
}