{
  "type": "Feature",
  "properties": {
    "iso:country":"US",
    "sg:address":"3752 Kingswood Dr",
    "sg:city":"Decatur",
    "sg:classifiers":[
        {
            "category":"Building & Trades",
            "subcategory":"Construction",
            "type":"Services"
        }
    ],
    "sg:phone":"+1 404 296 4974",
    "sg:postcode":"30032",
    "sg:province":"GA",
    "sg:tags":[
        "house"
    ],
    "wof:name":"B Mitchells Inc",
    "wof:placetype":"venue"
},
  "geometry": {"coordinates":[-84.236557,33.778935],"type":"Point"}
}