{
  "type": "Feature",
  "properties": {
    "addr:full":"1001 Duluth Hwy Lawrenceville GA 30043",
    "addr:housenumber":"1001",
    "addr:postcode":"30043",
    "addr:street":"Duluth Hwy",
    "iso:country":"US",
    "sg:address":"1001 Duluth Hwy",
    "sg:city":"Lawrenceville",
    "sg:classifiers":[
        {
            "category":"Organizations",
            "subcategory":"Religious Organization",
            "type":"Services"
        }
    ],
    "sg:phone":"+1 770 963 4499",
    "sg:postcode":"30043",
    "sg:province":"GA",
    "sg:website":"www.christthelordlutheran.org",
    "wof:name":"Christ the Lord Lutheran Church",
    "wof:placetype":"venue"
},
  "geometry": {"coordinates":[-84.030998,33.9687],"type":"Point"}
}