{
  "type": "Feature",
  "properties": {
    "addr:full":"4359 Dixon Rd Blackshear GA 31516",
    "addr:housenumber":"4359",
    "addr:postcode":"31516",
    "addr:street":"Dixon Rd",
    "iso:country":"US",
    "sg:address":"4359 Dixon Rd",
    "sg:city":"Blackshear",
    "sg:classifiers":[
        {
            "category":"Personal",
            "subcategory":"Beauty Salon",
            "type":"Services"
        }
    ],
    "sg:phone":"+1 912 449 3881",
    "sg:postcode":"31516",
    "sg:province":"GA",
    "wof:name":"Kathy's Country Cuts",
    "wof:placetype":"venue"
},
  "geometry": {"coordinates":[-82.201055,31.24043],"type":"Point"}
}