{
  "type": "Feature",
  "properties": {
    "addr:full":"7495 Petersburg Rd Fairburn GA 30213",
    "addr:housenumber":"7495",
    "addr:postcode":"30213",
    "addr:street":"Petersburg Rd",
    "iso:country":"US",
    "sg:address":"7495 Petersburg Rd",
    "sg:city":"Fairburn",
    "sg:classifiers":[
        {
            "category":"Professional",
            "type":"Services"
        }
    ],
    "sg:phone":"+1 770 463 5245",
    "sg:postcode":"30213",
    "sg:province":"GA",
    "wof:name":"Cunningham Care Inc",
    "wof:placetype":"venue"
},
  "geometry": {"coordinates":[-84.66715499999999,33.553456],"type":"Point"}
}