{
  "type": "Feature",
  "properties": {
    "addr:full":"4511 Jones Bridge Cir Norcross GA 30092",
    "addr:housenumber":"4511",
    "addr:postcode":"30092",
    "addr:street":"Jones Bridge Cir",
    "iso:country":"US",
    "sg:address":"4511 Jones Bridge Cir",
    "sg:city":"Norcross",
    "sg:classifiers":[
        {
            "category":"Travel",
            "subcategory":"Campground",
            "type":"Entertainment"
        }
    ],
    "sg:phone":"+1 770 441 1111",
    "sg:postcode":"30092",
    "sg:province":"GA",
    "sg:tags":[
        "conference",
        "center",
        "retreat"
    ],
    "wof:name":"Simpsnwood Cnfrnce Retreat Ctr",
    "wof:placetype":"venue"
},
  "geometry": {"coordinates":[-84.232979,33.985961],"type":"Point"}
}