{
  "type": "Feature",
  "properties": {
    "addr:full":"5065 Smith Dr Cumming GA 30041",
    "addr:housenumber":"5065",
    "addr:postcode":"30041",
    "addr:street":"Smith Dr",
    "iso:country":"US",
    "sg:address":"5065 Smith Dr",
    "sg:city":"Cumming",
    "sg:classifiers":[
        {
            "category":"Professional",
            "type":"Services"
        }
    ],
    "sg:phone":"+1 770 889 1865",
    "sg:postcode":"30041",
    "sg:province":"GA",
    "wof:name":"Sorrells Loy",
    "wof:placetype":"venue"
},
  "geometry": {"coordinates":[-84.057936,34.298518],"type":"Point"}
}