{
  "type": "Feature",
  "properties": {
    "addr:full":"3534 Greenshire Ct Douglasville GA 30135",
    "addr:postcode":"3534;30135",
    "addr:street":"Greenshire Ct",
    "iso:country":"US",
    "sg:address":"3534 Greenshire Ct",
    "sg:city":"Douglasville",
    "sg:classifiers":[
        {
            "category":"Personal",
            "type":"Services"
        },
        {
            "category":"Sports & Exercise",
            "subcategory":"Gym",
            "type":"Entertainment"
        }
    ],
    "sg:phone":"+1 770 949 5799",
    "sg:postcode":"30135",
    "sg:province":"GA",
    "sg:tags":[
        "trainer",
        "consultant",
        "program",
        "physical",
        "fitness"
    ],
    "wof:name":"Millennium Pt Inc",
    "wof:placetype":"venue"
},
  "geometry": {"coordinates":[-84.726489,33.708828],"type":"Point"}
}