{
  "type": "Feature",
  "properties": {
    "addr:full":"3637 Pleasantdale Rd NW Atlanta GA 30340",
    "addr:housenumber":"3637",
    "addr:postcode":"30340",
    "addr:street":"Pleasantdale Rd Nw",
    "iso:country":"US",
    "sg:address":"3637 Pleasantdale Rd NW",
    "sg:city":"Atlanta",
    "sg:classifiers":[
        {
            "category":"Building & Trades",
            "subcategory":"Cleaning & Sanitation",
            "type":"Services"
        }
    ],
    "sg:phone":"+1 678 937 0021",
    "sg:postcode":"30340",
    "sg:province":"GA",
    "sg:tags":[
        "maintenance"
    ],
    "wof:name":"Twin Cleaning Service Inc",
    "wof:placetype":"venue"
},
  "geometry": {"coordinates":[-84.246439,33.9129],"type":"Point"}
}