{
  "type": "Feature",
  "properties": {
    "addr:full":"104 Philema Rd Albany GA 31701",
    "addr:housenumber":"104",
    "addr:postcode":"31701",
    "addr:street":"Philema Rd",
    "iso:country":"US",
    "sg:address":"104 Philema Rd",
    "sg:city":"Albany",
    "sg:classifiers":[
        {
            "category":"Food & Beverages",
            "subcategory":"Groceries & Convenience Stores",
            "type":"Retail Goods"
        }
    ],
    "sg:phone":"+1 229 883 6114",
    "sg:postcode":"31701",
    "sg:province":"GA",
    "sg:tags":[
        "filling",
        "station",
        "liquor"
    ],
    "wof:name":"Stocks Market & Package Store",
    "wof:placetype":"venue"
},
  "geometry": {"coordinates":[-84.15389399999999,31.609388],"type":"Point"}
}