{
  "type": "Feature",
  "properties": {
    "addr:full":"5335 Triangle Pkwy Norcross GA 30092",
    "addr:housenumber":"5335",
    "addr:postcode":"30092",
    "addr:street":"Triangle Pkwy",
    "iso:country":"US",
    "sg:address":"5335 Triangle Pkwy",
    "sg:city":"Norcross",
    "sg:classifiers":[
        {
            "category":"Banks & Credit Unions",
            "subcategory":"Bank",
            "type":"Services"
        }
    ],
    "sg:phone":"+1 770 729 8844",
    "sg:postcode":"30092",
    "sg:province":"GA",
    "wof:name":"Fiserve",
    "wof:placetype":"venue"
},
  "geometry": {"coordinates":[-84.22559200000001,33.975988],"type":"Point"}
}