{
  "type": "Feature",
  "properties": {
    "iso:country":"US",
    "sg:address":"2516 Dawson Rd",
    "sg:city":"Albany",
    "sg:classifiers":[
        {
            "category":"Professional",
            "subcategory":"Business Services",
            "type":"Services"
        }
    ],
    "sg:phone":"+1 229 888 5885",
    "sg:postcode":"31707",
    "sg:province":"GA",
    "wof:name":"Onsite Wireless Communications",
    "wof:placetype":"venue"
},
  "geometry": {"coordinates":[-84.215007,31.612732],"type":"Point"}
}