{
  "type": "Feature",
  "properties": {
    "iso:country":"US",
    "sg:address":"15 Dr Turfler Rd",
    "sg:city":"Hazlehurst",
    "sg:classifiers":[
        {
            "category":"Manufacturing",
            "subcategory":"Tools & Machinery",
            "type":"Manufacturing & Wholesale Goods"
        }
    ],
    "sg:phone":"+1 912 379 1332",
    "sg:postcode":"31539",
    "sg:province":"GA",
    "sg:tags":[
        "machine",
        "shop"
    ],
    "wof:name":"Hazelhurst Custom Products",
    "wof:placetype":"venue"
},
  "geometry": {"coordinates":[-82.560579,31.859001],"type":"Point"}
}