{
  "type": "Feature",
  "properties": {
    "addr:full":"21 N Zetterower Ave Statesboro GA 30458",
    "addr:housenumber":"21",
    "addr:postcode":"30458",
    "addr:street":"N Zetterower Ave",
    "iso:country":"US",
    "sg:address":"21 N Zetterower Ave",
    "sg:city":"Statesboro",
    "sg:classifiers":[
        {
            "category":"Wholesale",
            "subcategory":"Hardware",
            "type":"Manufacturing & Wholesale Goods"
        }
    ],
    "sg:phone":"+1 912 764 7010",
    "sg:postcode":"30458",
    "sg:province":"GA",
    "wof:name":"Statesboro Eyewear",
    "wof:placetype":"venue"
},
  "geometry": {"coordinates":[-81.77744199999999,32.452531],"type":"Point"}
}