{
  "type": "Feature",
  "properties": {
    "iso:country":"US",
    "sg:address":"2239 Lakeside Dr",
    "sg:city":"Monroe",
    "sg:classifiers":[
        {
            "category":"Wholesale",
            "subcategory":"Vending Machines",
            "type":"Manufacturing & Wholesale Goods"
        }
    ],
    "sg:phone":"+1 770 900 6192",
    "sg:postcode":"30655",
    "sg:province":"GA",
    "wof:name":"Value Vending Inc",
    "wof:placetype":"venue"
},
  "geometry": {"coordinates":[-83.81662900000001,33.761786],"type":"Point"}
}