{
  "type": "Feature",
  "properties": {
    "addr:full":"104 Snead Ave NW Carrollton GA 30165",
    "addr:housenumber":"104",
    "addr:postcode":"30165",
    "addr:street":"Snead Ave Nw",
    "iso:country":"US",
    "sg:address":"104 Snead Ave NW",
    "sg:city":"Carrollton",
    "sg:classifiers":[
        {
            "category":"Building & Trades",
            "subcategory":"Construction",
            "type":"Services"
        }
    ],
    "sg:phone":"+1 770 834 0592",
    "sg:postcode":"30165",
    "sg:province":"GA",
    "sg:tags":[
        "restoration",
        "cleaning"
    ],
    "wof:name":"R & R Cleaning",
    "wof:placetype":"venue"
},
  "geometry": {"coordinates":[-85.198466,34.347085],"type":"Point"}
}