{
  "type": "Feature",
  "properties": {
    "iso:country":"US",
    "sg:address":"925 Cripple Creek Dr",
    "sg:city":"Lawrenceville",
    "sg:classifiers":[
        {
            "category":"Professional",
            "subcategory":"Art Services",
            "type":"Services"
        }
    ],
    "sg:phone":"+1 770 339 7280",
    "sg:postcode":"30043",
    "sg:province":"GA",
    "sg:tags":[
        "a",
        "purchase",
        "arts",
        "graphic",
        "for",
        "point",
        "related",
        "design"
    ],
    "wof:name":"Slow-Fade Window ADS",
    "wof:placetype":"venue"
},
  "geometry": {"coordinates":[-83.985972,33.985575],"type":"Point"}
}