{
  "type": "Feature",
  "properties": {
    "addr:full":"576 Litchfield Ct Evans GA 30809",
    "addr:housenumber":"576",
    "addr:postcode":"30809",
    "addr:street":"Litchfield Ct",
    "iso:country":"US",
    "sg:address":"576 Litchfield Ct",
    "sg:city":"Evans",
    "sg:classifiers":[
        {
            "category":"Utilities",
            "subcategory":"Mobile Phone",
            "type":"Services"
        }
    ],
    "sg:phone":"+1 706 922 4559",
    "sg:postcode":"30809",
    "sg:province":"GA",
    "sg:tags":[
        "telephone",
        "cellular"
    ],
    "wof:name":"Alltel",
    "wof:placetype":"venue"
},
  "geometry": {"coordinates":[-82.108687,33.540851],"type":"Point"}
}