{
  "type": "Feature",
  "properties": {
    "iso:country":"US",
    "sg:address":"3948 Deans Bridge Rd",
    "sg:city":"Hephzibah",
    "sg:classifiers":[
        {
            "category":"Organizations",
            "subcategory":"Religious Organization",
            "type":"Services"
        }
    ],
    "sg:phone":"+1 706 772 4240",
    "sg:postcode":"30815",
    "sg:province":"GA",
    "sg:tags":[
        "church"
    ],
    "wof:name":"First Baptist of Keysville",
    "wof:placetype":"venue"
},
  "geometry": {"coordinates":[-82.121673,33.388123],"type":"Point"}
}