{
  "type": "Feature",
  "properties": {
    "iso:country":"US",
    "sg:address":"1150 Pine Park Rd",
    "sg:city":"Cairo",
    "sg:classifiers":[
        {
            "category":"Shopping",
            "subcategory":"Clothing, Apparel, & Fashions",
            "type":"Retail Goods"
        }
    ],
    "sg:phone":"+1 229 377 4958",
    "sg:postcode":"39828",
    "sg:province":"GA",
    "sg:tags":[
        "furniture"
    ],
    "wof:name":"Mommy and ME",
    "wof:placetype":"venue"
},
  "geometry": {"coordinates":[-84.19928899999999,30.841112],"type":"Point"}
}