{
  "type": "Feature",
  "properties": {
    "iso:country":"US",
    "sg:address":"1745 Martin Luther King J",
    "sg:city":"Atlanta",
    "sg:classifiers":[
        {
            "category":"Professional",
            "subcategory":"Lawyer & Legal Services",
            "type":"Services"
        }
    ],
    "sg:phone":"+1 404 758 9111",
    "sg:postcode":"30314",
    "sg:province":"GA",
    "sg:tags":[
        "personal",
        "injury"
    ],
    "wof:name":"Toliver Antonio L",
    "wof:placetype":"venue"
},
  "geometry": {"coordinates":[-84.44058800000001,33.751908],"type":"Point"}
}