{
  "type": "Feature",
  "properties": {
    "iso:country":"US",
    "sg:address":"215 Cherokee St",
    "sg:city":"Canton",
    "sg:classifiers":[
        {
            "category":"Building & Trades",
            "subcategory":"Landscaping Services",
            "type":"Services"
        }
    ],
    "sg:phone":"+1 404 569 9545",
    "sg:postcode":"30114",
    "sg:province":"GA",
    "sg:tags":[
        "landscape",
        "contractor"
    ],
    "wof:name":"ALS Services",
    "wof:placetype":"venue"
},
  "geometry": {"coordinates":[-84.48547499999999,34.23182],"type":"Point"}
}