{
  "type": "Feature",
  "properties": {
    "iso:country":"US",
    "sg:address":"2310 Deer Ridge Dr",
    "sg:city":"Stone Mountain",
    "sg:classifiers":[
        {
            "category":"Building & Trades",
            "subcategory":"Construction",
            "type":"Services"
        }
    ],
    "sg:phone":"+1 770 934 4495",
    "sg:postcode":"30087",
    "sg:province":"GA",
    "sg:tags":[
        "floor",
        "laying",
        "contractor"
    ],
    "wof:name":"Earthtone Flooring Inc",
    "wof:placetype":"venue"
},
  "geometry": {"coordinates":[-84.177835,33.85124],"type":"Point"}
}