{
  "type": "Feature",
  "properties": {
    "addr:full":"2749 Tell Place Way SW Atlanta GA 30331",
    "addr:housenumber":"2749",
    "addr:postcode":"30331",
    "addr:street":"Tell Place Way Sw",
    "iso:country":"US",
    "sg:address":"2749 Tell Place Way SW",
    "sg:city":"Atlanta",
    "sg:classifiers":[
        {
            "category":"Home & Garden",
            "subcategory":"Building Materials",
            "type":"Retail Goods"
        },
        {
            "category":"Manufacturing",
            "subcategory":"Building Materials",
            "type":"Manufacturing & Wholesale Goods"
        }
    ],
    "sg:phone":"+1 404 629 5955",
    "sg:postcode":"30331",
    "sg:province":"GA",
    "sg:tags":[
        "materials-wholesale",
        "manufacturer"
    ],
    "wof:name":"Windows By U, Inc.",
    "wof:placetype":"venue"
},
  "geometry": {"coordinates":[-84.527604,33.68113],"type":"Point"}
}