{
  "type": "Feature",
  "properties": {
    "iso:country":"US",
    "sg:address":"634 Pine St",
    "sg:city":"Warrenton",
    "sg:classifiers":[
        {
            "category":"Personal",
            "subcategory":"Barber",
            "type":"Services"
        }
    ],
    "sg:phone":"+1 706 595 6757",
    "sg:postcode":"30828",
    "sg:province":"GA",
    "wof:name":"Griffin's Barber Shop",
    "wof:placetype":"venue"
},
  "geometry": {"coordinates":[-82.676344,33.406593],"type":"Point"}
}