{
  "type": "Feature",
  "properties": {
    "addr:full":"1245 Cumberland Mall Atlanta GA 30339",
    "addr:housenumber":"1245",
    "addr:postcode":"30339",
    "addr:street":"Cumberland Mall",
    "iso:country":"US",
    "sg:address":"1245 Cumberland Mall",
    "sg:city":"Atlanta",
    "sg:classifiers":[
        {
            "category":"Shopping",
            "subcategory":"Music",
            "type":"Retail Goods"
        }
    ],
    "sg:phone":"+1 770 438 1693",
    "sg:postcode":"30339",
    "sg:province":"GA",
    "sg:tags":[
        "product",
        "prerecorded",
        "tape",
        "blank",
        "small",
        "video",
        "audio"
    ],
    "wof:name":"Sam Goody 605",
    "wof:placetype":"venue"
},
  "geometry": {"coordinates":[-84.471265,33.879559],"type":"Point"}
}