{
  "type": "Feature",
  "properties": {
    "addr:full":"503 W Parker St Baxley GA 31513",
    "addr:housenumber":"503",
    "addr:postcode":"31513",
    "addr:street":"W Parker St",
    "iso:country":"US",
    "sg:address":"503 W Parker St",
    "sg:city":"Baxley",
    "sg:classifiers":[
        {
            "category":"Restaurant",
            "type":"Food & Drink"
        }
    ],
    "sg:menulink":"http://www.allmenus.com/ga/baxley/124510-quiznos-sub/menu/",
    "sg:phone":"+1 912 366 1156",
    "sg:postcode":"31513",
    "sg:province":"GA",
    "sg:tags":[
        "wrap",
        "american",
        "sandwich"
    ],
    "wof:name":"Quiznos Sub",
    "wof:placetype":"venue"
},
  "geometry": {"coordinates":[-82.353357,31.779887],"type":"Point"}
}