{
  "type": "Feature",
  "properties": {
    "addr:full":"1700 Gronto Rd Valdosta GA 31601",
    "addr:housenumber":"1700",
    "addr:postcode":"31601",
    "addr:street":"Gronto Rd",
    "iso:country":"US",
    "sg:address":"1700 Gronto Rd",
    "sg:city":"Valdosta",
    "sg:classifiers":[
        {
            "category":"Shopping",
            "subcategory":"Department Store",
            "type":"Retail Goods"
        }
    ],
    "sg:phone":"+1 229 244 6000",
    "sg:postcode":"31601",
    "sg:province":"GA",
    "wof:name":"JC Penney",
    "wof:placetype":"venue"
},
  "geometry": {"coordinates":[-83.32431,30.846245],"type":"Point"}
}