{
  "type": "Feature",
  "properties": {
    "iso:country":"US",
    "sg:address":"224 Bullsboro Dr",
    "sg:city":"Newnan",
    "sg:classifiers":[
        {
            "category":"Bars & Pubs",
            "type":"Food & Drink"
        }
    ],
    "sg:phone":"+1 770 251 0028",
    "sg:postcode":"30263",
    "sg:province":"GA",
    "sg:tags":[
        "drinking"
    ],
    "wof:name":"Banzai",
    "wof:placetype":"venue"
},
  "geometry": {"coordinates":[-84.768998,33.391782],"type":"Point"}
}