{
  "type": "Feature",
  "properties": {
    "iso:country":"US",
    "sg:address":"653 Night Dr",
    "sg:city":"Dawsonville",
    "sg:classifiers":[
        {
            "category":"Sports & Exercise",
            "subcategory":"Golf",
            "type":"Entertainment"
        }
    ],
    "sg:phone":"+1 706 216 4066",
    "sg:postcode":"30540",
    "sg:province":"GA",
    "sg:tags":[
        "course",
        "public"
    ],
    "wof:name":"Chestatee Development Corp",
    "wof:placetype":"venue"
},
  "geometry": {"coordinates":[-84.56755699999999,34.688306],"type":"Point"}
}