{
  "type": "Feature",
  "properties": {
    "addr:full":"189 Hurricane Shoals Rd NE Lawrenceville GA 30045",
    "addr:housenumber":"189",
    "addr:postcode":"30045",
    "addr:street":"Hurricane Shoals Rd Ne",
    "iso:country":"US",
    "sg:address":"189 Hurricane Shoals Rd NE",
    "sg:city":"Lawrenceville",
    "sg:classifiers":[
        {
            "category":"Retail",
            "subcategory":"Auto Repair",
            "type":"Services"
        }
    ],
    "sg:phone":"+1 770 963 9762",
    "sg:postcode":"30045",
    "sg:province":"GA",
    "sg:tags":[
        "alternator",
        "repairing",
        "generator",
        "automotive",
        "automobile",
        "starter"
    ],
    "wof:name":"Lawrenceville Auto Electric",
    "wof:placetype":"venue"
},
  "geometry": {"coordinates":[-83.983442,33.97524],"type":"Point"}
}