{
  "type": "Feature",
  "properties": {
    "addr:full":"123 Bankhead Hwy Carrollton GA 30117",
    "addr:housenumber":"123",
    "addr:postcode":"30117",
    "addr:street":"Bankhead Hwy",
    "iso:country":"US",
    "sg:address":"123 Bankhead Hwy",
    "sg:city":"Carrollton",
    "sg:classifiers":[
        {
            "category":"Banks & Credit Unions",
            "subcategory":"Investment Brokerage",
            "type":"Services"
        }
    ],
    "sg:phone":"+1 678 796 0553",
    "sg:postcode":"30117",
    "sg:province":"GA",
    "sg:tags":[
        "consultant",
        "financing"
    ],
    "wof:name":"F N Finance",
    "wof:placetype":"venue"
},
  "geometry": {"coordinates":[-85.064559,33.580745],"type":"Point"}
}