{
  "type": "Feature",
  "properties": {
    "addr:full":"6749 Rioca Cir Mableton GA 30126",
    "addr:housenumber":"6749",
    "addr:postcode":"30126",
    "addr:street":"Rioca Cir",
    "iso:country":"US",
    "sg:address":"6749 Rioca Cir",
    "sg:city":"Mableton",
    "sg:classifiers":[
        {
            "category":"Manufacturing",
            "subcategory":"Printing",
            "type":"Manufacturing & Wholesale Goods"
        }
    ],
    "sg:phone":"+1 770 948 3109",
    "sg:postcode":"30126",
    "sg:province":"GA",
    "sg:tags":[
        "commercial"
    ],
    "wof:name":"Commercial Press",
    "wof:placetype":"venue"
},
  "geometry": {"coordinates":[-84.54857699999999,33.79062],"type":"Point"}
}