{
  "type": "Feature",
  "properties": {
    "addr:full":"1424 Shadowbrook Dr Marietta GA 30062",
    "addr:housenumber":"1424",
    "addr:postcode":"30062",
    "addr:street":"Shadowbrook Dr",
    "iso:country":"US",
    "sg:address":"1424 Shadowbrook Dr",
    "sg:city":"Marietta",
    "sg:classifiers":[
        {
            "category":"Health Services",
            "subcategory":"Clinic",
            "type":"Services"
        }
    ],
    "sg:phone":"+1 770 509 3743",
    "sg:postcode":"30062",
    "sg:province":"GA",
    "sg:tags":[
        "home",
        "care"
    ],
    "wof:name":"East Natural Health Care",
    "wof:placetype":"venue"
},
  "geometry": {"coordinates":[-84.509429,33.95846],"type":"Point"}
}