{
  "type": "Feature",
  "properties": {
    "addr:full":"1 Regency Rd Alpharetta GA 30022",
    "addr:housenumber":"1",
    "addr:postcode":"30022",
    "addr:street":"Regency Rd",
    "iso:country":"US",
    "sg:address":"1 Regency Rd",
    "sg:city":"Alpharetta",
    "sg:phone":"+1 678 933 6767",
    "sg:postcode":"30022",
    "sg:province":"GA",
    "wof:name":"White Glove Enterprise",
    "wof:placetype":"venue"
},
  "geometry": {"coordinates":[-84.278267,34.000359],"type":"Point"}
}