{
  "type": "Feature",
  "properties": {
    "addr:full":"122 Produce Ln Athens GA 30605",
    "addr:housenumber":"122",
    "addr:postcode":"30605",
    "addr:street":"Produce Ln",
    "iso:country":"US",
    "sg:address":"122 Produce Ln",
    "sg:city":"Athens",
    "sg:classifiers":[
        {
            "category":"Building & Trades",
            "subcategory":"Construction",
            "type":"Services"
        }
    ],
    "sg:phone":"+1 706 613 6550",
    "sg:postcode":"30605",
    "sg:province":"GA",
    "sg:tags":[
        "home",
        "builder"
    ],
    "wof:name":"Hardeman Enterprises Inc",
    "wof:placetype":"venue"
},
  "geometry": {"coordinates":[-83.342612,33.957415],"type":"Point"}
}