{
  "type": "Feature",
  "properties": {
    "addr:full":"48 Pearl Pentecost Rd Winder GA 30680",
    "addr:housenumber":"48",
    "addr:postcode":"30680",
    "addr:street":"Pearl Pentecost Rd",
    "iso:country":"US",
    "sg:address":"48 Pearl Pentecost Rd",
    "sg:city":"Winder",
    "sg:classifiers":[
        {
            "category":"Building & Trades",
            "subcategory":"Construction",
            "type":"Services"
        }
    ],
    "sg:phone":"+1 770 307 1561",
    "sg:postcode":"30680",
    "sg:province":"GA",
    "sg:tags":[
        "painting",
        "contractor"
    ],
    "sg:website":"http://www.masttank.com",
    "wof:name":"Mast Tank Cleaning Of Ga",
    "wof:placetype":"venue"
},
  "geometry": {"coordinates":[-83.76360200000001,33.995122],"type":"Point"}
}