{
  "type": "Feature",
  "properties": {
    "iso:country":"US",
    "sg:address":"884 Splitrock Ln",
    "sg:city":"Douglasville",
    "sg:classifiers":[
        {
            "category":"Freight",
            "type":"Transportation"
        }
    ],
    "sg:phone":"+1 770 489 4673",
    "sg:postcode":"30134",
    "sg:province":"GA",
    "wof:name":"W T Transportation",
    "wof:placetype":"venue"
},
  "geometry": {"coordinates":[-84.700907,33.782701],"type":"Point"}
}