{
  "type": "Feature",
  "properties": {
    "iso:country":"US",
    "sg:address":"3134 Washington Rd",
    "sg:city":"Atlanta",
    "sg:classifiers":[
        {
            "category":"Utilities",
            "subcategory":"Mobile Phone",
            "type":"Services"
        }
    ],
    "sg:phone":"+1 404 768 0990",
    "sg:postcode":"30344",
    "sg:province":"GA",
    "sg:tags":[
        "pager",
        "cellular"
    ],
    "wof:name":"Delta Communications 3",
    "wof:placetype":"venue"
},
  "geometry": {"coordinates":[-84.46326500000001,33.669962],"type":"Point"}
}