{
  "type": "Feature",
  "properties": {
    "iso:country":"US",
    "sg:address":"307 Pilgrim Mill Rd",
    "sg:city":"Cumming",
    "sg:classifiers":[
        {
            "category":"Animal Shelter",
            "type":"Public Place"
        },
        {
            "category":"Retail",
            "subcategory":"Veterinary Services",
            "type":"Services"
        }
    ],
    "sg:phone":"+1 770 889 2521",
    "sg:postcode":"30040",
    "sg:province":"GA",
    "sg:tags":[
        "emergency",
        "hospital",
        "clinic",
        "veterinarian",
        "kennel"
    ],
    "sg:website":"http://www.crestviewah.com/",
    "wof:name":"Crestview Animal Hospital",
    "wof:placetype":"venue"
},
  "geometry": {"coordinates":[-84.135882,34.208378],"type":"Point"}
}