{
  "type": "Feature",
  "properties": {
    "addr:full":"2094 Corsica Way SW Marietta GA 30008",
    "addr:housenumber":"2094",
    "addr:postcode":"30008",
    "addr:street":"Corsica Way Sw",
    "iso:country":"US",
    "sg:address":"2094 Corsica Way SW",
    "sg:city":"Marietta",
    "sg:classifiers":[
        {
            "category":"Professional",
            "subcategory":"Computer Services",
            "type":"Services"
        }
    ],
    "sg:phone":"+1 770 427 8597",
    "sg:postcode":"30008",
    "sg:province":"GA",
    "sg:tags":[
        "related"
    ],
    "wof:name":"T L A Specialist Inc",
    "wof:placetype":"venue"
},
  "geometry": {"coordinates":[-84.596704,33.901506],"type":"Point"}
}