{
  "type": "Feature",
  "properties": {
    "iso:country":"US",
    "sg:address":"4440 Floyd Rd SW",
    "sg:city":"Mableton",
    "sg:classifiers":[
        {
            "category":"Autos & Motor Vehicles",
            "subcategory":"Motorcycle Sales",
            "type":"Retail Goods"
        }
    ],
    "sg:phone":"+1 770 732 0089",
    "sg:postcode":"30126",
    "sg:province":"GA",
    "sg:tags":[
        "shop",
        "bicycle"
    ],
    "wof:name":"Silver Comet Depot",
    "wof:placetype":"venue"
},
  "geometry": {"coordinates":[-84.58537,33.847181],"type":"Point"}
}