{
  "type": "Feature",
  "properties": {
    "iso:country":"US",
    "sg:address":"4679 Hugh Howell Rd",
    "sg:city":"Tucker",
    "sg:classifiers":[
        {
            "category":"Building & Trades",
            "subcategory":"Equipment Rental",
            "type":"Services"
        }
    ],
    "sg:phone":"+1 770 934 1172",
    "sg:postcode":"30084",
    "sg:province":"GA",
    "sg:tags":[
        "medical",
        "leasing",
        "supply"
    ],
    "wof:name":"McGehees Medical Supplies",
    "wof:placetype":"venue"
},
  "geometry": {"coordinates":[-84.197509,33.848972],"type":"Point"}
}