{
  "type": "Feature",
  "properties": {
    "iso:country":"US",
    "sg:address":"3945 Piper Glen Dr NE",
    "sg:city":"Buford",
    "sg:classifiers":[
        {
            "category":"Professional",
            "subcategory":"Management & Consulting",
            "type":"Services"
        }
    ],
    "sg:phone":"+1 770 597 3212",
    "sg:postcode":"30519",
    "sg:province":"GA",
    "sg:tags":[
        "business"
    ],
    "wof:name":"Jose Miiqueli Consulting",
    "wof:placetype":"venue"
},
  "geometry": {"coordinates":[-83.960256,34.108044],"type":"Point"}
}