{
  "type": "Feature",
  "properties": {
    "iso:country":"US",
    "sg:address":"50 Ernest Barrett Pkwy",
    "sg:city":"Marietta",
    "sg:classifiers":[
        {
            "category":"Shopping",
            "subcategory":"Shoes",
            "type":"Retail Goods"
        }
    ],
    "sg:phone":"+1 678 354 7154",
    "sg:postcode":"30060",
    "sg:province":"GA",
    "sg:tags":[
        "store"
    ],
    "sg:website":"www.famousfootwear.com",
    "wof:name":"Famous Footwear",
    "wof:placetype":"venue"
},
  "geometry": {"coordinates":[-84.54989500000001,34.014022],"type":"Point"}
}