{
  "type": "Feature",
  "properties": {
    "iso:country":"US",
    "sg:address":"2820 Hillcreek Dr",
    "sg:city":"Augusta",
    "sg:classifiers":[
        {
            "category":"Professional",
            "subcategory":"Lawyer & Legal Services",
            "type":"Services"
        }
    ],
    "sg:phone":"+1 706 650 2100",
    "sg:postcode":"30909",
    "sg:province":"GA",
    "sg:tags":[
        "attorney",
        "law",
        "family",
        "personal",
        "divorce",
        "injury"
    ],
    "sg:website":"http://www.jennifermckinzie.com",
    "wof:name":"McKinzie Jennifer S",
    "wof:placetype":"venue"
},
  "geometry": {"coordinates":[-82.09192299999999,33.479987],"type":"Point"}
}