{
  "type": "Feature",
  "properties": {
    "iso:country":"US",
    "sg:address":"1184 Winder Hwy",
    "sg:city":"Lawrenceville",
    "sg:classifiers":[
        {
            "category":"Food & Beverages",
            "subcategory":"Groceries & Convenience Stores",
            "type":"Retail Goods"
        }
    ],
    "sg:phone":"+1 770 339 9990",
    "sg:postcode":"30045",
    "sg:province":"GA",
    "wof:name":"Noman Foodmart",
    "wof:placetype":"venue"
},
  "geometry": {"coordinates":[-83.94544999999999,33.975831],"type":"Point"}
}