{
  "type": "Feature",
  "properties": {
    "iso:country":"US",
    "sg:address":"5962 Rosie Ln SE",
    "sg:city":"Mableton",
    "sg:classifiers":[
        {
            "category":"Building & Trades",
            "subcategory":"Landscaping Services",
            "type":"Services"
        }
    ],
    "sg:phone":"+1 770 739 7671",
    "sg:postcode":"30126",
    "sg:province":"GA",
    "sg:tags":[
        "landscape",
        "contractor"
    ],
    "wof:name":"Dogwood Daddy Landscaping Svc",
    "wof:placetype":"venue"
},
  "geometry": {"coordinates":[-84.51750800000001,33.807703],"type":"Point"}
}