{
  "type": "Feature",
  "properties": {
    "iso:country":"US",
    "sg:address":"2002 Lakewood Ave SE",
    "sg:city":"Atlanta",
    "sg:classifiers":[
        {
            "category":"Communications",
            "subcategory":"Radio Station",
            "type":"Services"
        }
    ],
    "sg:phone":"+1 404 635 0980",
    "sg:postcode":"30315",
    "sg:province":"GA",
    "sg:tags":[
        "company",
        "broadcasting"
    ],
    "wof:name":"Radio One",
    "wof:placetype":"venue"
},
  "geometry": {"coordinates":[-84.386169,33.701406],"type":"Point"}
}