{
  "type": "Feature",
  "properties": {
    "iso:country":"US",
    "sg:address":"7736 Melanie Dr",
    "sg:city":"Douglasville",
    "sg:classifiers":[
        {
            "category":"Building & Trades",
            "subcategory":"Construction",
            "type":"Services"
        }
    ],
    "sg:phone":"+1 678 838 7808",
    "sg:postcode":"30134",
    "sg:province":"GA",
    "sg:tags":[
        "contractor"
    ],
    "wof:name":"Ricky S Kent Roof",
    "wof:placetype":"venue"
},
  "geometry": {"coordinates":[-84.76233499999999,33.766959],"type":"Point"}
}