{
  "type": "Feature",
  "properties": {
    "addr:full":"2381 John Glenn Drive Atlanta GA 30341",
    "addr:housenumber":"2381",
    "addr:postcode":"30341",
    "addr:street":"John Glenn Drive",
    "iso:country":"US",
    "sg:address":"2381 John Glenn Drive",
    "sg:city":"Atlanta",
    "sg:classifiers":[
        {
            "category":"Restaurant",
            "type":"Food & Drink"
        }
    ],
    "sg:phone":"+1 770 457 3474",
    "sg:postcode":"30341",
    "sg:province":"GA",
    "sg:tags":[
        "seafood"
    ],
    "wof:name":"Atlanta Fish Company",
    "wof:placetype":"venue"
},
  "geometry": {"coordinates":[-84.291493,33.905162],"type":"Point"}
}