{
  "type": "Feature",
  "properties": {
    "addr:full":"339 Pat Mell Rd SE Marietta GA 30060",
    "addr:housenumber":"339",
    "addr:postcode":"30060",
    "addr:street":"Pat Mell Rd Se",
    "iso:country":"US",
    "sg:address":"339 Pat Mell Rd SE",
    "sg:city":"Marietta",
    "sg:classifiers":[
        {
            "category":"Personal",
            "subcategory":"Barber",
            "type":"Services"
        }
    ],
    "sg:phone":"+1 770 435 7706",
    "sg:postcode":"30060",
    "sg:province":"GA",
    "wof:name":"Pat Mell Barber & Style Shop",
    "wof:placetype":"venue"
},
  "geometry": {"coordinates":[-84.540802,33.9021],"type":"Point"}
}