{
  "type": "Feature",
  "properties": {
    "iso:country":"US",
    "sg:address":"2189 Flintstone Dr",
    "sg:city":"Tucker",
    "sg:classifiers":[
        {
            "category":"Professional",
            "subcategory":"Business Services",
            "type":"Services"
        }
    ],
    "sg:phone":"+1 678 376 5720",
    "sg:postcode":"30084",
    "sg:province":"GA",
    "sg:tags":[
        "trade",
        "fair",
        "show"
    ],
    "wof:name":"Geo Creative",
    "wof:placetype":"venue"
},
  "geometry": {"coordinates":[-84.194354,33.847519],"type":"Point"}
}