{
  "type": "Feature",
  "properties": {
    "addr:full":"5344 Budding Ct Marietta GA 30068",
    "addr:housenumber":"5344",
    "addr:postcode":"30068",
    "addr:street":"Budding Ct",
    "iso:country":"US",
    "sg:address":"5344 Budding Ct",
    "sg:city":"Marietta",
    "sg:classifiers":[
        {
            "category":"Shopping",
            "subcategory":"Jewelry",
            "type":"Retail Goods"
        }
    ],
    "sg:phone":"+1 770 993 2734",
    "sg:postcode":"30068",
    "sg:province":"GA",
    "sg:tags":[
        "jeweler"
    ],
    "wof:name":"Marbak",
    "wof:placetype":"venue"
},
  "geometry": {"coordinates":[-84.396147,33.964089],"type":"Point"}
}