{
  "type": "Feature",
  "properties": {
    "iso:country":"US",
    "sg:address":"502 Gi Maddox Pkwy",
    "sg:city":"Chatsworth",
    "sg:classifiers":[
        {
            "category":"Shopping",
            "subcategory":"Department Store",
            "type":"Retail Goods"
        }
    ],
    "sg:phone":"+1 706 517 4495",
    "sg:postcode":"30705",
    "sg:province":"GA",
    "sg:tags":[
        "shop"
    ],
    "wof:name":"Family Dollar Store",
    "wof:placetype":"venue"
},
  "geometry": {"coordinates":[-84.782551,34.782416],"type":"Point"}
}