{
  "type": "Feature",
  "properties": {
    "iso:country":"US",
    "sg:address":"5939 Hwy 20 NE",
    "sg:city":"Cartersville",
    "sg:classifiers":[
        {
            "category":"Professional",
            "subcategory":"Art Services",
            "type":"Services"
        }
    ],
    "sg:phone":"+1 770 386 3607",
    "sg:postcode":"30121",
    "sg:province":"GA",
    "sg:tags":[
        "commercial",
        "design"
    ],
    "wof:name":"Graphic Machine & Design Inc",
    "wof:placetype":"venue"
},
  "geometry": {"coordinates":[-84.72111,34.220248],"type":"Point"}
}