{
  "type": "Feature",
  "properties": {
    "iso:country":"US",
    "sg:address":"1440 Hillcrest Hts",
    "sg:city":"Alpharetta",
    "sg:classifiers":[
        {
            "category":"Professional",
            "type":"Services"
        }
    ],
    "sg:phone":"+1 770 664 1196",
    "sg:postcode":"30005",
    "sg:province":"GA",
    "wof:name":"Chambers & Wilson Inc",
    "wof:placetype":"venue"
},
  "geometry": {"coordinates":[-84.224058,34.096024],"type":"Point"}
}