{
  "type": "Feature",
  "properties": {
    "addr:full":"999 Peachtree St Atlanta GA 30309",
    "addr:housenumber":"999",
    "addr:postcode":"30309",
    "addr:street":"Peachtree St",
    "iso:country":"US",
    "sg:address":"999 Peachtree St",
    "sg:city":"Atlanta",
    "sg:classifiers":[
        {
            "category":"Restaurant",
            "type":"Food & Drink"
        }
    ],
    "sg:phone":"+1 404 541 1105",
    "sg:postcode":"30309",
    "sg:province":"GA",
    "sg:tags":[
        "southern"
    ],
    "sg:website":"www.empirestatesouth.com",
    "wof:name":"Empire State South",
    "wof:placetype":"venue"
},
  "geometry": {"coordinates":[-84.383312,33.781097],"type":"Point"}
}