{
  "type": "Feature",
  "properties": {
    "iso:country":"US",
    "sg:address":"4574 Walker Rd",
    "sg:city":"Toccoa",
    "sg:classifiers":[
        {
            "category":"Professional",
            "subcategory":"Lawyer & Legal Services",
            "type":"Services"
        }
    ],
    "sg:phone":"+1 706 886 0549",
    "sg:postcode":"30577",
    "sg:province":"GA",
    "sg:tags":[
        "attorney"
    ],
    "wof:name":"Smith & Tabor",
    "wof:placetype":"venue"
},
  "geometry": {"coordinates":[-83.365611,34.524668],"type":"Point"}
}