{
  "type": "Feature",
  "properties": {
    "iso:country":"US",
    "sg:address":"5891 New Peachtree Rd",
    "sg:city":"Doraville",
    "sg:classifiers":[
        {
            "category":"Building & Trades",
            "subcategory":"Locksmith",
            "type":"Services"
        }
    ],
    "sg:phone":"+1 877 563 3174",
    "sg:postcode":"30340",
    "sg:province":"GA",
    "sg:tags":[
        "key"
    ],
    "wof:name":"1 & A Emergency Locksmith",
    "wof:placetype":"venue"
},
  "geometry": {"coordinates":[-84.282375,33.899266],"type":"Point"}
}