{
  "type": "Feature",
  "properties": {
    "addr:full":"102 E Clinton St Gray GA 31032",
    "addr:housenumber":"102",
    "addr:postcode":"31032",
    "addr:street":"E Clinton St",
    "iso:country":"US",
    "sg:address":"102 E Clinton St",
    "sg:city":"Gray",
    "sg:classifiers":[
        {
            "category":"Shopping",
            "subcategory":"Gifts & Souvenirs",
            "type":"Retail Goods"
        }
    ],
    "sg:phone":"+1 478 986 6258",
    "sg:postcode":"31032",
    "sg:province":"GA",
    "wof:name":"Stock Exchange Gifts & Jewelry",
    "wof:placetype":"venue"
},
  "geometry": {"coordinates":[-83.53238899999999,33.010246],"type":"Point"}
}