{
  "type": "Feature",
  "properties": {
    "addr:full":"125 Bedgood Rd Bogart GA 30622",
    "addr:housenumber":"125",
    "addr:postcode":"30622",
    "addr:street":"Bedgood Rd",
    "iso:country":"US",
    "sg:address":"125 Bedgood Rd",
    "sg:city":"Bogart",
    "sg:classifiers":[
        {
            "category":"Building & Trades",
            "subcategory":"Construction",
            "type":"Services"
        }
    ],
    "sg:phone":"+1 706 548 8456",
    "sg:postcode":"30622",
    "sg:province":"GA",
    "sg:tags":[
        "contractor"
    ],
    "wof:name":"Bart Woodell Acoustical",
    "wof:placetype":"venue"
},
  "geometry": {"coordinates":[-83.491027,33.943003],"type":"Point"}
}