{
  "type": "Feature",
  "properties": {
    "addr:full":"115 Martin St Lincolnton GA 30817",
    "addr:housenumber":"115",
    "addr:postcode":"30817",
    "addr:street":"Martin St",
    "iso:country":"US",
    "sg:address":"115 Martin St",
    "sg:city":"Lincolnton",
    "sg:classifiers":[
        {
            "category":"Government",
            "subcategory":"Office",
            "type":"Public Place"
        }
    ],
    "sg:phone":"+1 706 359 5769",
    "sg:postcode":"30817",
    "sg:province":"GA",
    "wof:name":"Lincoln County Family Cnnctn",
    "wof:placetype":"venue"
},
  "geometry": {"coordinates":[-82.481662,33.788534],"type":"Point"}
}