{
  "type": "Feature",
  "properties": {
    "addr:full":"41 Pine Cone Rd Moultrie GA 31768",
    "addr:housenumber":"41",
    "addr:postcode":"31768",
    "addr:street":"Pine Cone Rd",
    "iso:country":"US",
    "sg:address":"41 Pine Cone Rd",
    "sg:city":"Moultrie",
    "sg:classifiers":[
        {
            "category":"Fast Food",
            "type":"Food & Drink"
        },
        {
            "category":"Restaurant",
            "type":"Food & Drink"
        },
        {
            "category":"Food & Beverages",
            "subcategory":"Groceries & Convenience Stores",
            "type":"Retail Goods"
        }
    ],
    "sg:phone":"+1 229 886 7000",
    "sg:postcode":"31768",
    "sg:province":"GA",
    "sg:tags":[
        "shop",
        "american",
        "sandwich",
        "take"
    ],
    "wof:name":"Subway",
    "wof:placetype":"venue"
},
  "geometry": {"coordinates":[-83.796009,31.131482],"type":"Point"}
}