{
  "type": "Feature",
  "properties": {
    "addr:full":"4897 Buford Hwy Ste 202 Atlanta GA 30341",
    "addr:housenumber":"4897",
    "addr:postcode":"30341",
    "addr:street":"Buford Hwy Ste 202",
    "iso:country":"US",
    "sg:address":"4897 Buford Hwy Ste 202",
    "sg:city":"Atlanta",
    "sg:classifiers":[
        {
            "category":"Banks & Credit Unions",
            "subcategory":"Bank",
            "type":"Services"
        }
    ],
    "sg:phone":"+1 770 457 7888",
    "sg:postcode":"30341",
    "sg:province":"GA",
    "sg:tags":[
        "telegraph"
    ],
    "wof:name":"Abc Money Transactions, Inc.",
    "wof:placetype":"venue"
},
  "geometry": {"coordinates":[-84.288628,33.88501],"type":"Point"}
}