{
  "type": "Feature",
  "properties": {
    "iso:country":"US",
    "sg:address":"305 Commerce Blvd",
    "sg:city":"Bogart",
    "sg:classifiers":[
        {
            "category":"Autos & Motor Vehicles",
            "subcategory":"Auto Supplies",
            "type":"Retail Goods"
        }
    ],
    "sg:phone":"+1 706 227 6100",
    "sg:postcode":"30622",
    "sg:province":"GA",
    "wof:name":"Terminal Supply Co",
    "wof:placetype":"venue"
},
  "geometry": {"coordinates":[-83.477233,33.931076],"type":"Point"}
}