{
  "type": "Feature",
  "properties": {
    "iso:country":"US",
    "sg:address":"225 W Hall St",
    "sg:city":"Thomson",
    "sg:classifiers":[
        {
            "category":"Manufacturing",
            "subcategory":"Signs",
            "type":"Manufacturing & Wholesale Goods"
        }
    ],
    "sg:phone":"+1 706 595 2924",
    "sg:postcode":"30824",
    "sg:province":"GA",
    "wof:name":"H & H Sign Co",
    "wof:placetype":"venue"
},
  "geometry": {"coordinates":[-82.505567,33.468094],"type":"Point"}
}