{
  "type": "Feature",
  "properties": {
    "addr:full":"233 Mitchell St SW Atlanta GA 30303",
    "addr:housenumber":"233",
    "addr:postcode":"30303",
    "addr:street":"Mitchell St Sw",
    "iso:country":"US",
    "sg:address":"233 Mitchell St SW",
    "sg:city":"Atlanta",
    "sg:classifiers":[
        {
            "category":"Social Services",
            "type":"Services"
        }
    ],
    "sg:phone":"+1 404 521 2410",
    "sg:postcode":"30303",
    "sg:province":"GA",
    "wof:name":"Aniz Inc",
    "wof:placetype":"venue"
},
  "geometry": {"coordinates":[-84.394882,33.751965],"type":"Point"}
}