{
  "type": "Feature",
  "properties": {
    "addr:full":"1328 N Saint Augustine Rd Valdosta GA 31601",
    "addr:housenumber":"1328",
    "addr:postcode":"31601",
    "addr:street":"N Saint Augustine Rd",
    "iso:country":"US",
    "sg:address":"1328 N Saint Augustine Rd",
    "sg:city":"Valdosta",
    "sg:classifiers":[
        {
            "category":"Restaurant",
            "type":"Food & Drink"
        }
    ],
    "sg:menulink":"http://www.allmenus.com/ga/valdosta/11679-dennys/menu/",
    "sg:phone":"+1 912 253 9388",
    "sg:postcode":"31601",
    "sg:province":"GA",
    "sg:tags":[
        "american",
        "diner"
    ],
    "wof:name":"Denny's",
    "wof:placetype":"venue"
},
  "geometry": {"coordinates":[-83.331862,30.84557],"type":"Point"}
}