{
  "type": "Feature",
  "properties": {
    "iso:country":"US",
    "sg:address":"145 N Marietta Pkwy",
    "sg:city":"Marietta",
    "sg:classifiers":[
        {
            "category":"Shopping",
            "subcategory":"Used Merchandise",
            "type":"Retail Goods"
        },
        {
            "category":"Shopping",
            "subcategory":"Clothing, Apparel, & Fashions",
            "type":"Retail Goods"
        }
    ],
    "sg:phone":"+1 770 423 1344",
    "sg:postcode":"30060",
    "sg:province":"GA",
    "sg:tags":[
        "shop",
        "consignment"
    ],
    "wof:name":"Once Upon A Closet",
    "wof:placetype":"venue"
},
  "geometry": {"coordinates":[-84.545528,33.958996],"type":"Point"}
}