{
  "type": "Feature",
  "properties": {
    "iso:country":"US",
    "sg:address":"4622 E Ponce de Leon Ave",
    "sg:city":"Clarkston",
    "sg:classifiers":[
        {
            "category":"Professional",
            "type":"Services"
        }
    ],
    "sg:phone":"+1 770 939 2644",
    "sg:postcode":"30021",
    "sg:province":"GA",
    "sg:tags":[
        "establishment"
    ],
    "wof:name":"Continent II",
    "wof:placetype":"venue"
},
  "geometry": {"coordinates":[-84.228233,33.819135],"type":"Point"}
}