{
  "type": "Feature",
  "properties": {
    "iso:country":"US",
    "sg:address":"170 Lukes Path",
    "sg:city":"Jasper",
    "sg:classifiers":[
        {
            "category":"Building & Trades",
            "subcategory":"Cleaning & Sanitation",
            "type":"Services"
        },
        {
            "category":"Utilities",
            "subcategory":"Electric",
            "type":"Services"
        }
    ],
    "sg:phone":"+1 770 735 1082",
    "sg:postcode":"30143",
    "sg:province":"GA",
    "sg:tags":[
        "maintenance"
    ],
    "wof:name":"Lighting Maintenance Systems",
    "wof:placetype":"venue"
},
  "geometry": {"coordinates":[-84.392838,34.398976],"type":"Point"}
}