{
  "type": "Feature",
  "properties": {
    "addr:full":"715 Arborside Ct Alpharetta GA 30022",
    "addr:housenumber":"715",
    "addr:postcode":"30022",
    "addr:street":"Arborside Ct",
    "iso:country":"US",
    "sg:address":"715 Arborside Ct",
    "sg:city":"Alpharetta",
    "sg:classifiers":[
        {
            "category":"Shopping",
            "type":"Retail Goods"
        }
    ],
    "sg:phone":"+1 770 642 9393",
    "sg:postcode":"30022",
    "sg:province":"GA",
    "sg:tags":[
        "merchandise"
    ],
    "wof:name":"Gibbs Enterprises",
    "wof:placetype":"venue"
},
  "geometry": {"coordinates":[-84.268601,34.009399],"type":"Point"}
}