{
  "type": "Feature",
  "properties": {
    "iso:country":"US",
    "sg:address":"565 Lowell Rd",
    "sg:city":"Carrollton",
    "sg:classifiers":[
        {
            "category":"Building & Trades",
            "subcategory":"Construction",
            "type":"Services"
        }
    ],
    "sg:phone":"+1 770 854 4257",
    "sg:postcode":"30116",
    "sg:province":"GA",
    "sg:tags":[
        "grading",
        "contractor"
    ],
    "wof:name":"Carl Harris & Son Constr Co",
    "wof:placetype":"venue"
},
  "geometry": {"coordinates":[-85.066974,33.496164],"type":"Point"}
}