{
  "type": "Feature",
  "properties": {
    "iso:country":"US",
    "sg:address":"35 Fred Kelly Rd NE",
    "sg:city":"Rome",
    "sg:classifiers":[
        {
            "category":"Autos & Motor Vehicles",
            "subcategory":"Automobile Sales",
            "type":"Retail Goods"
        }
    ],
    "sg:phone":"+1 706 235 2299",
    "sg:postcode":"30161",
    "sg:province":"GA",
    "sg:tags":[
        "car",
        "dealer"
    ],
    "wof:name":"Matt's Auto Sales",
    "wof:placetype":"venue"
},
  "geometry": {"coordinates":[-85.081132,34.255853],"type":"Point"}
}