{
  "type": "Feature",
  "properties": {
    "iso:country":"US",
    "sg:address":"210 Main St",
    "sg:city":"Toomsboro",
    "sg:classifiers":[
        {
            "category":"Health Services",
            "subcategory":"Clinic",
            "type":"Services"
        }
    ],
    "sg:phone":"+1 478 933 9930",
    "sg:postcode":"31090",
    "sg:province":"GA",
    "sg:tags":[
        "specialty",
        "outpatient"
    ],
    "wof:name":"Select Med Rehabilitation Svc",
    "wof:placetype":"venue"
},
  "geometry": {"coordinates":[-83.07859000000001,32.819175],"type":"Point"}
}