{
  "type": "Feature",
  "properties": {
    "iso:country":"US",
    "sg:address":"4016 Cochran Rd",
    "sg:city":"Gainesville",
    "sg:classifiers":[
        {
            "category":"Building & Trades",
            "subcategory":"Construction",
            "type":"Services"
        }
    ],
    "sg:phone":"+1 770 534 4359",
    "sg:postcode":"30506",
    "sg:province":"GA",
    "sg:tags":[
        "house"
    ],
    "wof:name":"First Construction of Georgia",
    "wof:placetype":"venue"
},
  "geometry": {"coordinates":[-83.84633599999999,34.370094],"type":"Point"}
}