{
  "type": "Feature",
  "properties": {
    "addr:full":"7504 Highway 92 Woodstock GA 30189",
    "addr:housenumber":"7504",
    "addr:postcode":"30189",
    "addr:street":"Highway 92",
    "iso:country":"US",
    "sg:address":"7504 Highway 92",
    "sg:city":"Woodstock",
    "sg:classifiers":[
        {
            "category":"Organizations",
            "subcategory":"Religious Organization",
            "type":"Services"
        }
    ],
    "sg:phone":"+1 770 926 0422",
    "sg:postcode":"30189",
    "sg:province":"GA",
    "wof:name":"South Cherokee Baptist Church",
    "wof:placetype":"venue"
},
  "geometry": {"coordinates":[-84.56349899999999,34.083698],"type":"Point"}
}