{
  "type": "Feature",
  "properties": {
    "addr:full":"100 Stuart St Savannah GA 31405",
    "addr:housenumber":"100",
    "addr:postcode":"31405",
    "addr:street":"Stuart St",
    "iso:country":"US",
    "sg:address":"100 Stuart St",
    "sg:city":"Savannah",
    "sg:classifiers":[
        {
            "category":"Health Services",
            "subcategory":"Doctor",
            "type":"Services"
        }
    ],
    "sg:phone":"+1 912 354 4045",
    "sg:postcode":"31405",
    "sg:province":"GA",
    "sg:tags":[
        "medical"
    ],
    "wof:name":"Baruch Kalman Dr",
    "wof:placetype":"venue"
},
  "geometry": {"coordinates":[-81.10950699999999,32.018205],"type":"Point"}
}