{
  "type": "Feature",
  "properties": {
    "addr:full":"297 W Hancock Ave Athens GA 30601",
    "addr:housenumber":"297",
    "addr:postcode":"30601",
    "addr:street":"W Hancock Ave",
    "iso:country":"US",
    "sg:address":"297 W Hancock Ave",
    "sg:city":"Athens",
    "sg:classifiers":[
        {
            "category":"Autos & Motor Vehicles",
            "subcategory":"Auto Supplies",
            "type":"Retail Goods"
        }
    ],
    "sg:phone":"+1 706 543 4371",
    "sg:postcode":"30601",
    "sg:province":"GA",
    "sg:tags":[
        "tire"
    ],
    "sg:website":"www.snowtireco.com",
    "wof:name":"Snow Tire Co",
    "wof:placetype":"venue"
},
  "geometry": {"coordinates":[-83.379341,33.95944],"type":"Point"}
}