{
  "type": "Feature",
  "properties": {
    "iso:country":"US",
    "sg:address":"44 12th St NE",
    "sg:city":"Atlanta",
    "sg:classifiers":[
        {
            "category":"Bars & Pubs",
            "type":"Food & Drink"
        }
    ],
    "sg:phone":"+1 404 745 9551",
    "sg:postcode":"30309",
    "sg:province":"GA",
    "sg:tags":[
        "club",
        "night"
    ],
    "wof:name":"Whiskey Peach",
    "wof:placetype":"venue"
},
  "geometry": {"coordinates":[-84.38449,33.784624],"type":"Point"}
}