{
  "type": "Feature",
  "properties": {
    "addr:full":"1004 Northside Dr Perry GA 31069",
    "addr:housenumber":"1004",
    "addr:postcode":"31069",
    "addr:street":"Northside Dr",
    "iso:country":"US",
    "sg:address":"1004 Northside Dr",
    "sg:city":"Perry",
    "sg:classifiers":[
        {
            "category":"Retail",
            "subcategory":"Repair Shop",
            "type":"Services"
        }
    ],
    "sg:phone":"+1 478 987 2206",
    "sg:postcode":"31069",
    "sg:province":"GA",
    "wof:name":"Nelsons Sharpening Service",
    "wof:placetype":"venue"
},
  "geometry": {"coordinates":[-83.732249,32.461037],"type":"Point"}
}