{
  "type": "Feature",
  "properties": {
    "addr:full":"6280 Fairburn Rd Douglasville GA 30134",
    "addr:housenumber":"6280",
    "addr:postcode":"30134",
    "addr:street":"Fairburn Rd",
    "iso:country":"US",
    "sg:address":"6280 Fairburn Rd",
    "sg:city":"Douglasville",
    "sg:classifiers":[
        {
            "category":"Retail",
            "subcategory":"Auto Repair",
            "type":"Services"
        }
    ],
    "sg:phone":"+1 770 942 4225",
    "sg:postcode":"30134",
    "sg:province":"GA",
    "sg:tags":[
        "automobile",
        "lubrication"
    ],
    "wof:name":"Texaco Xpress Lube",
    "wof:placetype":"venue"
},
  "geometry": {"coordinates":[-84.740602,33.751682],"type":"Point"}
}