{
  "type": "Feature",
  "properties": {
    "addr:full":"644 E Main St Blue Ridge GA 30513",
    "addr:housenumber":"644",
    "addr:postcode":"30513",
    "addr:street":"E Main St",
    "iso:country":"US",
    "sg:address":"644 E Main St",
    "sg:city":"Blue Ridge",
    "sg:classifiers":[
        {
            "category":"Professional",
            "subcategory":"Management & Consulting",
            "type":"Services"
        }
    ],
    "sg:phone":"+1 770 445 8138",
    "sg:postcode":"30513",
    "sg:province":"GA",
    "sg:tags":[
        "business"
    ],
    "wof:name":"Andrews Group Inc",
    "wof:placetype":"venue"
},
  "geometry": {"coordinates":[-84.323363,34.866594],"type":"Point"}
}