{
  "type": "Feature",
  "properties": {
    "addr:full":"515 Katherines Cove Mc Donough GA 30253",
    "addr:housenumber":"515",
    "addr:postcode":"30253",
    "addr:street":"Katherines Cove Mc Donough",
    "iso:country":"US",
    "sg:address":"515 Katherines Cove",
    "sg:city":"Mc Donough",
    "sg:classifiers":[
        {
            "category":"Professional",
            "subcategory":"Business Services",
            "type":"Services"
        }
    ],
    "sg:phone":"+1 770 914 7228",
    "sg:postcode":"30253",
    "sg:province":"GA",
    "wof:name":"James Morgan Enterprises",
    "wof:placetype":"venue"
},
  "geometry": {"coordinates":[-84.17095999999999,33.46052],"type":"Point"}
}