{
  "type": "Feature",
  "properties": {
    "addr:full":"4602 Holly Avenue Columbus GA 31904",
    "addr:housenumber":"4602",
    "addr:postcode":"31904",
    "addr:street":"Holly Avenue",
    "iso:country":"US",
    "sg:address":"4602 Holly Avenue",
    "sg:city":"Columbus",
    "sg:classifiers":[
        {
            "category":"Building & Trades",
            "subcategory":"Plumbing",
            "type":"Services"
        },
        {
            "category":"Wholesale",
            "subcategory":"Construction Materials",
            "type":"Manufacturing & Wholesale Goods"
        }
    ],
    "sg:phone":"+1 706 403 5194",
    "sg:postcode":"31904",
    "sg:province":"GA",
    "sg:tags":[
        "supply",
        "part",
        "cleaning",
        "fixtures",
        "plumbing-drain",
        "sewer"
    ],
    "wof:name":"The Plumbing and Rooter Co",
    "wof:placetype":"venue"
},
  "geometry": {"coordinates":[-84.97362200000001,32.507843],"type":"Point"}
}