{
  "type": "Feature",
  "properties": {
    "iso:country":"US",
    "sg:address":"312 W Liberty St",
    "sg:city":"Savannah",
    "sg:classifiers":[
        {
            "category":"Shopping",
            "subcategory":"Optical Goods",
            "type":"Retail Goods"
        }
    ],
    "sg:phone":"+1 912 233 5445",
    "sg:postcode":"31401",
    "sg:province":"GA",
    "wof:name":"Binocular Glasses",
    "wof:placetype":"venue"
},
  "geometry": {"coordinates":[-81.097832,32.075729],"type":"Point"}
}