{
  "type": "Feature",
  "properties": {
    "addr:full":"5506 Chamblee Dunwoody Rd Atlanta GA 30338",
    "addr:housenumber":"5506",
    "addr:postcode":"30338",
    "addr:street":"Chamblee Dunwoody Rd",
    "iso:country":"US",
    "sg:address":"5506 Chamblee Dunwoody Rd",
    "sg:city":"Atlanta",
    "sg:classifiers":[
        {
            "category":"Restaurant",
            "type":"Food & Drink"
        }
    ],
    "sg:phone":"+1 770 673 0048",
    "sg:postcode":"30338",
    "sg:province":"GA",
    "wof:name":"Boston Market",
    "wof:placetype":"venue"
},
  "geometry": {"coordinates":[-84.336197,33.950001],"type":"Point"}
}