{
  "type": "Feature",
  "properties": {
    "addr:full":"4321 Toccoa Dr Acworth GA 30101",
    "addr:housenumber":"4321",
    "addr:postcode":"30101",
    "addr:street":"Toccoa Dr",
    "iso:country":"US",
    "sg:address":"4321 Toccoa Dr",
    "sg:city":"Acworth",
    "sg:classifiers":[
        {
            "category":"Organizations",
            "subcategory":"Professional Association",
            "type":"Services"
        }
    ],
    "sg:phone":"+1 770 974 6616",
    "sg:postcode":"30101",
    "sg:province":"GA",
    "wof:name":"Acworth Baseball Assn",
    "wof:placetype":"venue"
},
  "geometry": {"coordinates":[-84.66189,34.063387],"type":"Point"}
}