{
  "type": "Feature",
  "properties": {
    "addr:full":"3120 Buford Hwy NE Atlanta GA 30329",
    "addr:housenumber":"3120",
    "addr:postcode":"30329",
    "addr:street":"Buford Hwy Ne",
    "iso:country":"US",
    "sg:address":"3120 Buford Hwy NE",
    "sg:city":"Atlanta",
    "sg:classifiers":[
        {
            "category":"Real Estate",
            "subcategory":"Real Estate Operator",
            "type":"Services"
        }
    ],
    "sg:phone":"+1 404 486 8717",
    "sg:postcode":"30329",
    "sg:province":"GA",
    "sg:tags":[
        "apartment"
    ],
    "wof:name":"Cross Keys Huntington",
    "wof:placetype":"venue"
},
  "geometry": {"coordinates":[-84.33429099999999,33.838128],"type":"Point"}
}