{
  "type": "Feature",
  "properties": {
    "addr:full":"6238 Townsend Way Riverdale GA 30296",
    "addr:housenumber":"6238",
    "addr:postcode":"30296",
    "addr:street":"Townsend Way",
    "iso:country":"US",
    "sg:address":"6238 Townsend Way",
    "sg:city":"Riverdale",
    "sg:classifiers":[
        {
            "category":"Shopping",
            "subcategory":"Gifts & Souvenirs",
            "type":"Retail Goods"
        }
    ],
    "sg:phone":"+1 770 997 1533",
    "sg:postcode":"30296",
    "sg:province":"GA",
    "wof:name":"Brendas Gifts & Accessories",
    "wof:placetype":"venue"
},
  "geometry": {"coordinates":[-84.434403,33.584974],"type":"Point"}
}