{
  "type": "Feature",
  "properties": {
    "addr:full":"275 Beebe Rd Springfield GA 31329",
    "addr:housenumber":"275",
    "addr:postcode":"31329",
    "addr:street":"Beebe Rd",
    "iso:country":"US",
    "sg:address":"275 Beebe Rd",
    "sg:city":"Springfield",
    "sg:classifiers":[
        {
            "category":"Freight",
            "type":"Transportation"
        }
    ],
    "sg:phone":"+1 912 754 9205",
    "sg:postcode":"31329",
    "sg:province":"GA",
    "sg:tags":[
        "operator",
        "local",
        "trucking"
    ],
    "wof:name":"Faith & Hope Trucking Inc",
    "wof:placetype":"venue"
},
  "geometry": {"coordinates":[-81.292005,32.350605],"type":"Point"}
}