{
  "type": "Feature",
  "properties": {
    "iso:country":"US",
    "sg:address":"2200 Clark Ave",
    "sg:city":"Albany",
    "sg:classifiers":[
        {
            "category":"Social Services",
            "subcategory":"Child Care",
            "type":"Services"
        }
    ],
    "sg:phone":"+1 229 430 9964",
    "sg:postcode":"31705",
    "sg:province":"GA",
    "wof:name":"Aisha Laster",
    "wof:placetype":"venue"
},
  "geometry": {"coordinates":[-84.095609,31.579897],"type":"Point"}
}