{
  "type": "Feature",
  "properties": {
    "addr:full":"3646 Ledan Rd Gainesville GA 30506",
    "addr:housenumber":"3646",
    "addr:postcode":"30506",
    "addr:street":"Ledan Rd",
    "iso:country":"US",
    "sg:address":"3646 Ledan Rd",
    "sg:city":"Gainesville",
    "sg:classifiers":[
        {
            "category":"Real Estate",
            "subcategory":"Real Estate Services",
            "type":"Services"
        }
    ],
    "sg:phone":"+1 770 718 0045",
    "sg:postcode":"30506",
    "sg:province":"GA",
    "sg:tags":[
        "management"
    ],
    "wof:name":"Proper D Management & Rental Service",
    "wof:placetype":"venue"
},
  "geometry": {"coordinates":[-83.874559,34.363614],"type":"Point"}
}