{
  "type": "Feature",
  "properties": {
    "iso:country":"US",
    "sg:address":"205 Grand Ave",
    "sg:city":"Eatonton",
    "sg:classifiers":[
        {
            "category":"Restaurant",
            "type":"Food & Drink"
        }
    ],
    "sg:phone":"+1 706 485 6465",
    "sg:postcode":"31024",
    "sg:province":"GA",
    "sg:tags":[
        "eating"
    ],
    "wof:name":"We Believe In You Inc",
    "wof:placetype":"venue"
},
  "geometry": {"coordinates":[-83.382959,33.326726],"type":"Point"}
}