{
  "type": "Feature",
  "properties": {
    "iso:country":"US",
    "sg:address":"1759 Possum Trot Rd",
    "sg:city":"Blairsville",
    "sg:classifiers":[
        {
            "category":"Shopping",
            "subcategory":"Computers & Home Electronics",
            "type":"Retail Goods"
        }
    ],
    "sg:phone":"+1 706 781 2987",
    "sg:postcode":"30512",
    "sg:province":"GA",
    "sg:tags":[
        "equipment",
        "dealer"
    ],
    "wof:name":"Computers Limited",
    "wof:placetype":"venue"
},
  "geometry": {"coordinates":[-83.905252,34.853606],"type":"Point"}
}