{
  "type": "Feature",
  "properties": {
    "iso:country":"US",
    "sg:address":"132 Laurel Wood Ln",
    "sg:city":"Newnan",
    "sg:classifiers":[
        {
            "category":"Professional",
            "type":"Services"
        }
    ],
    "sg:phone":"+1 770 251 0513",
    "sg:postcode":"30263",
    "sg:province":"GA",
    "wof:name":"Michael Bettencourt",
    "wof:placetype":"venue"
},
  "geometry": {"coordinates":[-84.819592,33.464253],"type":"Point"}
}