{
  "type": "Feature",
  "properties": {
    "addr:full":"195 Parkwood Cir Carrollton GA 30117",
    "addr:housenumber":"195",
    "addr:postcode":"30117",
    "addr:street":"Parkwood Cir",
    "iso:country":"US",
    "sg:address":"195 Parkwood Cir",
    "sg:city":"Carrollton",
    "sg:classifiers":[
        {
            "category":"Health Services",
            "subcategory":"Doctor",
            "type":"Services"
        }
    ],
    "sg:phone":"+1 770 832 1322",
    "sg:postcode":"30117",
    "sg:province":"GA",
    "sg:tags":[
        "physician"
    ],
    "wof:name":"BMA of Carrollton",
    "wof:placetype":"venue"
},
  "geometry": {"coordinates":[-85.086966,33.616859],"type":"Point"}
}