{
  "type": "Feature",
  "properties": {
    "iso:country":"US",
    "sg:address":"509 W Main St",
    "sg:city":"Folkston",
    "sg:classifiers":[
        {
            "category":"Travel",
            "subcategory":"Hotels & Motels",
            "type":"Entertainment"
        },
        {
            "category":"Travel",
            "subcategory":"Bed & Breakfast",
            "type":"Entertainment"
        }
    ],
    "sg:phone":"+1 888 509 6246",
    "sg:postcode":"31537",
    "sg:province":"GA",
    "sg:tags":[
        "inn",
        "lodging"
    ],
    "wof:name":"Inn at Folkston",
    "wof:placetype":"venue"
},
  "geometry": {"coordinates":[-82.01029,30.830681],"type":"Point"}
}