{
  "type": "Feature",
  "properties": {
    "addr:full":"7215 Seawright Dr Savannah GA 31406",
    "addr:housenumber":"7215",
    "addr:postcode":"31406",
    "addr:street":"Seawright Dr",
    "iso:country":"US",
    "sg:address":"7215 Seawright Dr",
    "sg:city":"Savannah",
    "sg:classifiers":[
        {
            "category":"Education",
            "subcategory":"Dance Studio",
            "type":"Public Place"
        }
    ],
    "sg:phone":"+1 912 356 3623",
    "sg:postcode":"31406",
    "sg:province":"GA",
    "sg:tags":[
        "instruction",
        "dancing"
    ],
    "wof:name":"A & I Butterfly Ballroom",
    "wof:placetype":"venue"
},
  "geometry": {"coordinates":[-81.09496900000001,32.009273],"type":"Point"}
}