{
  "type": "Feature",
  "properties": {
    "addr:full":"4618 Cabinwood Turn Douglasville GA 30135",
    "addr:housenumber":"4618",
    "addr:postcode":"30135",
    "addr:street":"Cabinwood Turn",
    "iso:country":"US",
    "sg:address":"4618 Cabinwood Turn",
    "sg:city":"Douglasville",
    "sg:classifiers":[
        {
            "category":"Organizations",
            "subcategory":"Labor Organization",
            "type":"Services"
        }
    ],
    "sg:phone":"+1 770 577 9107",
    "sg:postcode":"30135",
    "sg:province":"GA",
    "wof:name":"Local Web Biz",
    "wof:placetype":"venue"
},
  "geometry": {"coordinates":[-84.72132999999999,33.707271],"type":"Point"}
}