{
  "type": "Feature",
  "properties": {
    "iso:country":"US",
    "sg:address":"1300 Church St",
    "sg:city":"Vidalia",
    "sg:classifiers":[
        {
            "category":"Building & Trades",
            "subcategory":"Construction",
            "type":"Services"
        }
    ],
    "sg:phone":"+1 912 538 9393",
    "sg:postcode":"30474",
    "sg:province":"GA",
    "sg:tags":[
        "company"
    ],
    "wof:name":"Beasley Construction",
    "wof:placetype":"venue"
},
  "geometry": {"coordinates":[-82.41914199999999,32.206438],"type":"Point"}
}