{
  "type": "Feature",
  "properties": {
    "iso:country":"US",
    "sg:address":"195 Grosvenor Pl NW",
    "sg:city":"Atlanta",
    "sg:classifiers":[
        {
            "category":"Professional",
            "subcategory":"Business Services",
            "type":"Services"
        }
    ],
    "sg:phone":"+1 404 252 2111",
    "sg:postcode":"30328",
    "sg:province":"GA",
    "wof:name":"Tech Ventures Inc",
    "wof:placetype":"venue"
},
  "geometry": {"coordinates":[-84.389633,33.91507],"type":"Point"}
}