{
  "type": "Feature",
  "properties": {
    "addr:full":"223 James P Brawley Dr SW Atlanta GA 30314",
    "addr:housenumber":"223",
    "addr:postcode":"30314",
    "addr:street":"James P Brawley Dr Sw",
    "iso:country":"US",
    "sg:address":"223 James P Brawley Dr SW",
    "sg:city":"Atlanta",
    "sg:classifiers":[
        {
            "category":"Professional",
            "type":"Services"
        }
    ],
    "sg:phone":"+1 404 727 2545",
    "sg:postcode":"30314",
    "sg:province":"GA",
    "wof:name":"Graduate Bus Studnt Foundation",
    "wof:placetype":"venue"
},
  "geometry": {"coordinates":[-84.412886,33.747459],"type":"Point"}
}