{
  "type": "Feature",
  "properties": {
    "iso:country":"US",
    "sg:address":"2995 Summit View Ct",
    "sg:city":"Snellville",
    "sg:classifiers":[
        {
            "category":"Home & Garden",
            "subcategory":"Building Materials",
            "type":"Retail Goods"
        }
    ],
    "sg:phone":"+1 678 344 0022",
    "sg:postcode":"30078",
    "sg:province":"GA",
    "wof:name":"Tiptop Glass Co",
    "wof:placetype":"venue"
},
  "geometry": {"coordinates":[-83.97998800000001,33.855512],"type":"Point"}
}