{
  "type": "Feature",
  "properties": {
    "iso:country":"US",
    "sg:address":"1412 E Park Ave",
    "sg:city":"Valdosta",
    "sg:classifiers":[
        {
            "category":"Retail",
            "subcategory":"Driving School",
            "type":"Services"
        }
    ],
    "sg:phone":"+1 229 244 2428",
    "sg:postcode":"31602",
    "sg:province":"GA",
    "sg:tags":[
        "instruction",
        "traffic"
    ],
    "sg:website":"http://www.duidefensivedriving.com",
    "wof:name":"Lowndes County DUI School",
    "wof:placetype":"venue"
},
  "geometry": {"coordinates":[-83.26850899999999,30.857343],"type":"Point"}
}