{
  "type": "Feature",
  "properties": {
    "iso:country":"US",
    "sg:address":"4183 Mike Padgett Hwy",
    "sg:city":"Augusta",
    "sg:classifiers":[
        {
            "category":"Retail",
            "subcategory":"Repair Shop",
            "type":"Services"
        }
    ],
    "sg:phone":"+1 706 793 9710",
    "sg:postcode":"30906",
    "sg:province":"GA",
    "sg:tags":[
        "welding"
    ],
    "wof:name":"Advance IMF Inc",
    "wof:placetype":"venue"
},
  "geometry": {"coordinates":[-81.96413699999999,33.333935],"type":"Point"}
}