{
  "type": "Feature",
  "properties": {
    "iso:country":"US",
    "sg:address":"1754 Laurel Ridge Dr SW",
    "sg:city":"Conyers",
    "sg:classifiers":[
        {
            "category":"Professional",
            "subcategory":"Detective & Security Services",
            "type":"Services"
        }
    ],
    "sg:phone":"+1 770 761 1086",
    "sg:postcode":"30094",
    "sg:province":"GA",
    "sg:tags":[
        "car"
    ],
    "wof:name":"Mobley Security Lls",
    "wof:placetype":"venue"
},
  "geometry": {"coordinates":[-84.07044399999999,33.643363],"type":"Point"}
}