{
  "type": "Feature",
  "properties": {
    "addr:full":"512 W Main St Claxton GA 30417",
    "addr:housenumber":"512",
    "addr:postcode":"30417",
    "addr:street":"W Main St",
    "iso:country":"US",
    "sg:address":"512 W Main St",
    "sg:city":"Claxton",
    "sg:classifiers":[
        {
            "category":"Retail",
            "subcategory":"Car Wash",
            "type":"Services"
        }
    ],
    "sg:phone":"+1 912 739 2524",
    "sg:postcode":"30417",
    "sg:province":"GA",
    "sg:tags":[
        "carwash"
    ],
    "wof:name":"McCords Car Care",
    "wof:placetype":"venue"
},
  "geometry": {"coordinates":[-81.91367,32.161161],"type":"Point"}
}