{
  "type": "Feature",
  "properties": {
    "iso:country":"US",
    "sg:address":"3751 Venture Dr NW",
    "sg:city":"Duluth",
    "sg:classifiers":[
        {
            "category":"Building & Trades",
            "subcategory":"Construction",
            "type":"Services"
        }
    ],
    "sg:phone":"+1 770 232 4539",
    "sg:postcode":"30096",
    "sg:province":"GA",
    "sg:tags":[
        "equipment",
        "welding"
    ],
    "wof:name":"Sonotronic Inc",
    "wof:placetype":"venue"
},
  "geometry": {"coordinates":[-84.131823,33.954254],"type":"Point"}
}