{
  "type": "Feature",
  "properties": {
    "addr:full":"5826 Marcelle Ln NW Norcross GA 30093",
    "addr:housenumber":"5826",
    "addr:postcode":"30093",
    "addr:street":"Marcelle Ln Nw",
    "iso:country":"US",
    "sg:address":"5826 Marcelle Ln NW",
    "sg:city":"Norcross",
    "sg:classifiers":[
        {
            "category":"Manufacturing",
            "subcategory":"Glass & Minerals",
            "type":"Manufacturing & Wholesale Goods"
        }
    ],
    "sg:phone":"+1 678 887 8175",
    "sg:postcode":"30093",
    "sg:province":"GA",
    "sg:tags":[
        "ready",
        "concrete",
        "mfg"
    ],
    "wof:name":"Ready On Time Cleaning",
    "wof:placetype":"venue"
},
  "geometry": {"coordinates":[-84.18865599999999,33.9042],"type":"Point"}
}