{
  "type": "Feature",
  "properties": {
    "addr:full":"922 Forest Path Stone Mountain GA 30088",
    "addr:housenumber":"922",
    "addr:postcode":"30088",
    "addr:street":"Forest Path",
    "iso:country":"US",
    "sg:address":"922 Forest Path",
    "sg:city":"Stone Mountain",
    "sg:classifiers":[
        {
            "category":"Retail",
            "subcategory":"Laundry & Dry Cleaning",
            "type":"Services"
        }
    ],
    "sg:phone":"+1 770 413 6172",
    "sg:postcode":"30088",
    "sg:province":"GA",
    "sg:tags":[
        "cleaners",
        "rug",
        "carpet"
    ],
    "wof:name":"Excellent Cleaning Service",
    "wof:placetype":"venue"
},
  "geometry": {"coordinates":[-84.16861900000001,33.767927],"type":"Point"}
}