{
  "type": "Feature",
  "properties": {
    "iso:country":"US",
    "sg:address":"5450 McGinnis Ferry Rd",
    "sg:city":"Alpharetta",
    "sg:classifiers":[
        {
            "category":"Real Estate",
            "subcategory":"Real Estate Agent",
            "type":"Services"
        }
    ],
    "sg:phone":"+1 678 893 0238",
    "sg:postcode":"30005",
    "sg:province":"GA",
    "wof:name":"Atlanta Real Estate",
    "wof:placetype":"venue"
},
  "geometry": {"coordinates":[-84.19650300000001,34.088503],"type":"Point"}
}