{
  "type": "Feature",
  "properties": {
    "iso:country":"US",
    "sg:address":"4360 San Carlos Dr",
    "sg:city":"Macon",
    "sg:classifiers":[
        {
            "category":"Manufacturing",
            "subcategory":"Printing",
            "type":"Manufacturing & Wholesale Goods"
        }
    ],
    "sg:phone":"+1 478 314 2290",
    "sg:postcode":"31206",
    "sg:province":"GA",
    "sg:tags":[
        "periodical"
    ],
    "wof:name":"I Media",
    "wof:placetype":"venue"
},
  "geometry": {"coordinates":[-83.643086,32.78026],"type":"Point"}
}