{
  "type": "Feature",
  "properties": {
    "addr:full":"2365 Buford Dr Lawrenceville GA 30043",
    "addr:housenumber":"2365",
    "addr:postcode":"30043",
    "addr:street":"Buford Dr",
    "iso:country":"US",
    "sg:address":"2365 Buford Dr",
    "sg:city":"Lawrenceville",
    "sg:classifiers":[
        {
            "category":"Shopping",
            "subcategory":"Pharmacy",
            "type":"Retail Goods"
        }
    ],
    "sg:phone":"+1 770 339 4749",
    "sg:postcode":"30043",
    "sg:province":"GA",
    "sg:tags":[
        "drugstore"
    ],
    "wof:name":"Walgreens",
    "wof:placetype":"venue"
},
  "geometry": {"coordinates":[-83.987413,34.035023],"type":"Point"}
}