{
  "type": "Feature",
  "properties": {
    "addr:full":"1230 Johnson Ferry Pl Marietta GA 30068",
    "addr:housenumber":"1230",
    "addr:postcode":"30068",
    "addr:street":"Johnson Ferry Pl",
    "iso:country":"US",
    "sg:address":"1230 Johnson Ferry Pl",
    "sg:city":"Marietta",
    "sg:classifiers":[
        {
            "category":"Health Services",
            "subcategory":"Doctor",
            "type":"Services"
        }
    ],
    "sg:phone":"+1 770 977 9067",
    "sg:postcode":"30068",
    "sg:province":"GA",
    "wof:name":"Obadina Abiodun MD",
    "wof:placetype":"venue"
},
  "geometry": {"coordinates":[-84.4216,33.98],"type":"Point"}
}