{
  "type": "Feature",
  "properties": {
    "iso:country":"US",
    "sg:address":"35 Saddle Ln NW",
    "sg:city":"Cartersville",
    "sg:classifiers":[
        {
            "category":"Professional",
            "type":"Services"
        }
    ],
    "sg:phone":"+1 770 386 9716",
    "sg:postcode":"30121",
    "sg:province":"GA",
    "sg:tags":[
        "establishment"
    ],
    "wof:name":"North Georgia Exteriors",
    "wof:placetype":"venue"
},
  "geometry": {"coordinates":[-84.822171,34.258665],"type":"Point"}
}