{
  "type": "Feature",
  "properties": {
    "addr:full":"6075 Carlisle Ln Alpharetta GA 30022",
    "addr:housenumber":"6075",
    "addr:postcode":"30022",
    "addr:street":"Carlisle Ln",
    "iso:country":"US",
    "sg:address":"6075 Carlisle Ln",
    "sg:city":"Alpharetta",
    "sg:classifiers":[
        {
            "category":"Real Estate",
            "subcategory":"Architect",
            "type":"Services"
        }
    ],
    "sg:phone":"+1 770 772 6001",
    "sg:postcode":"30022",
    "sg:province":"GA",
    "sg:tags":[
        "building",
        "construction"
    ],
    "wof:name":"Hughes Consulting Assoc",
    "wof:placetype":"venue"
},
  "geometry": {"coordinates":[-84.244829,34.006407],"type":"Point"}
}