{
  "type": "Feature",
  "properties": {
    "iso:country":"US",
    "sg:address":"1354 Milledge St",
    "sg:city":"Atlanta",
    "sg:classifiers":[
        {
            "category":"Wholesale",
            "subcategory":"Painting Supplies",
            "type":"Manufacturing & Wholesale Goods"
        },
        {
            "category":"Manufacturing",
            "subcategory":"Chemicals & Compounds",
            "type":"Manufacturing & Wholesale Goods"
        },
        {
            "category":"Autos & Motor Vehicles",
            "subcategory":"Fuel & Gas Station",
            "type":"Retail Goods"
        }
    ],
    "sg:phone":"+1 404 761 7961",
    "sg:postcode":"30344",
    "sg:province":"GA",
    "sg:tags":[
        "equipment",
        "color",
        "pigment",
        "paint-wholesale",
        "paint",
        "manufacturer"
    ],
    "wof:name":"Ed Simal & Associates Inc",
    "wof:placetype":"venue"
},
  "geometry": {"coordinates":[-84.429922,33.692844],"type":"Point"}
}