{
  "type": "Feature",
  "properties": {
    "iso:country":"US",
    "sg:address":"1044 Arnold Spence Rd",
    "sg:city":"Ball Ground",
    "sg:classifiers":[
        {
            "category":"Farming",
            "subcategory":"Poultry Farm",
            "type":"Manufacturing & Wholesale Goods"
        }
    ],
    "sg:phone":"+1 770 735 3491",
    "sg:postcode":"30107",
    "sg:province":"GA",
    "sg:tags":[
        "chicken"
    ],
    "wof:name":"Dilbeck Farm",
    "wof:placetype":"venue"
},
  "geometry": {"coordinates":[-84.42681899999999,34.345249],"type":"Point"}
}