{
  "type": "Feature",
  "properties": {
    "addr:full":"4700 Brightwood Ln SW Atlanta GA 30331",
    "addr:housenumber":"4700",
    "addr:postcode":"30331",
    "addr:street":"Brightwood Ln Sw",
    "iso:country":"US",
    "sg:address":"4700 Brightwood Ln SW",
    "sg:city":"Atlanta",
    "sg:classifiers":[
        {
            "category":"Professional",
            "subcategory":"Business Services",
            "type":"Services"
        }
    ],
    "sg:phone":"+1 404 505 9879",
    "sg:postcode":"30331",
    "sg:province":"GA",
    "sg:tags":[
        "consultant",
        "fashion"
    ],
    "wof:name":"Simplestyle",
    "wof:placetype":"venue"
},
  "geometry": {"coordinates":[-84.536827,33.72311],"type":"Point"}
}