{
  "type": "Feature",
  "properties": {
    "iso:country":"US",
    "sg:address":"2436 Southlake Mall",
    "sg:city":"Morrow",
    "sg:classifiers":[
        {
            "category":"Shopping",
            "subcategory":"Luggage & Leather Goods",
            "type":"Retail Goods"
        },
        {
            "category":"Shopping",
            "subcategory":"Clothing, Apparel, & Fashions",
            "type":"Retail Goods"
        }
    ],
    "sg:phone":"+1 770 961 0051",
    "sg:postcode":"30260",
    "sg:province":"GA",
    "wof:name":"Royal Leather Inc",
    "wof:placetype":"venue"
},
  "geometry": {"coordinates":[-84.35362000000001,33.577262],"type":"Point"}
}