{
  "type": "Feature",
  "properties": {
    "iso:country":"US",
    "sg:address":"2833 Dublin Eastman Rd",
    "sg:city":"Dexter",
    "sg:classifiers":[
        {
            "category":"Professional",
            "subcategory":"Engineering",
            "type":"Services"
        }
    ],
    "sg:phone":"+1 478 875 3327",
    "sg:postcode":"31019",
    "sg:province":"GA",
    "sg:tags":[
        "industrial",
        "engineer"
    ],
    "wof:name":"Williams Jams Calvin",
    "wof:placetype":"venue"
},
  "geometry": {"coordinates":[-83.09237400000001,32.380167],"type":"Point"}
}