{
  "type": "Feature",
  "properties": {
    "iso:country":"US",
    "sg:address":"455 State Hwy 138 Spr",
    "sg:city":"Jonesboro",
    "sg:classifiers":[
        {
            "category":"Wholesale",
            "subcategory":"Groceries",
            "type":"Manufacturing & Wholesale Goods"
        }
    ],
    "sg:phone":"+1 770 477 7223",
    "sg:postcode":"30238",
    "sg:province":"GA",
    "sg:tags":[
        "food",
        "product"
    ],
    "wof:name":"Kelco Food Svc Co",
    "wof:placetype":"venue"
},
  "geometry": {"coordinates":[-84.36527100000001,33.532321],"type":"Point"}
}