{
  "type": "Feature",
  "properties": {
    "addr:full":"5295 Buffington Rd Atlanta GA 30349",
    "addr:housenumber":"5295",
    "addr:postcode":"30349",
    "addr:street":"Buffington Rd",
    "iso:country":"US",
    "sg:address":"5295 Buffington Rd",
    "sg:city":"Atlanta",
    "sg:classifiers":[
        {
            "category":"Freight",
            "type":"Transportation"
        },
        {
            "category":"Airline",
            "type":"Transportation"
        }
    ],
    "sg:phone":"+1 404 363 6633",
    "sg:postcode":"30349",
    "sg:province":"GA",
    "sg:tags":[
        "courier",
        "air"
    ],
    "sg:website":"www.pilotair.com",
    "wof:name":"Pilot Air Freight Corp",
    "wof:placetype":"venue"
},
  "geometry": {"coordinates":[-84.49970999999999,33.61011],"type":"Point"}
}