{
  "type": "Feature",
  "properties": {
    "addr:full":"1287 State Rte 138 Jonesboro GA 30236",
    "addr:housenumber":"1287",
    "addr:postcode":"30236",
    "addr:street":"State Rte 138",
    "iso:country":"US",
    "sg:address":"1287 State Rte 138",
    "sg:city":"Jonesboro",
    "sg:classifiers":[
        {
            "category":"Professional",
            "type":"Services"
        }
    ],
    "sg:phone":"+1 770 472 3541",
    "sg:postcode":"30236",
    "sg:province":"GA",
    "wof:name":"Knowledgepoints",
    "wof:placetype":"venue"
},
  "geometry": {"coordinates":[-84.336737,33.531387],"type":"Point"}
}