{
  "type": "Feature",
  "properties": {
    "addr:full":"2820 Martha Berry Hwy Rome GA 30165",
    "addr:housenumber":"2820",
    "addr:postcode":"ga 30165",
    "addr:street":"Martha Berry Hwy",
    "iso:country":"US",
    "sg:address":"2820 Martha Berry Hwy",
    "sg:city":"Rome",
    "sg:classifiers":[
        {
            "category":"Cinema",
            "subcategory":"Movie Theater",
            "type":"Entertainment"
        }
    ],
    "sg:phone":"+1 706 235 9335",
    "sg:postcode":"30165",
    "sg:province":"GA",
    "sg:tags":[
        "motion",
        "picture",
        "except",
        "drive"
    ],
    "wof:name":"Movies At Berry Square",
    "wof:placetype":"venue"
},
  "geometry": {"coordinates":[-85.175134,34.303568],"type":"Point"}
}