{
  "type": "Feature",
  "properties": {
    "iso:country":"US",
    "sg:address":"1813 Addison Rd NE",
    "sg:city":"Marietta",
    "sg:classifiers":[
        {
            "category":"Retail",
            "subcategory":"Car Wash",
            "type":"Services"
        }
    ],
    "sg:phone":"+1 678 355 0707",
    "sg:postcode":"30066",
    "sg:province":"GA",
    "wof:name":"On the Corner Car Wash",
    "wof:placetype":"venue"
},
  "geometry": {"coordinates":[-84.520933,33.995056],"type":"Point"}
}