{
  "type": "Feature",
  "properties": {
    "addr:full":"414 W Broughton St Savannah GA 31401",
    "addr:housenumber":"414",
    "addr:postcode":"31401",
    "addr:street":"W Broughton St",
    "iso:country":"US",
    "sg:address":"414 W Broughton St",
    "sg:city":"Savannah",
    "sg:classifiers":[
        {
            "category":"Shopping",
            "subcategory":"Jewelry",
            "type":"Retail Goods"
        }
    ],
    "sg:phone":"+1 912 447 5150",
    "sg:postcode":"31401",
    "sg:province":"GA",
    "sg:tags":[
        "jeweler"
    ],
    "wof:name":"Jacob's",
    "wof:placetype":"venue"
},
  "geometry": {"coordinates":[-81.09711,32.080397],"type":"Point"}
}