{
  "type": "Feature",
  "properties": {
    "iso:country":"US",
    "sg:address":"8440 Merion Dr",
    "sg:city":"Duluth",
    "sg:classifiers":[
        {
            "category":"Travel",
            "subcategory":"Travel Agent",
            "type":"Entertainment"
        }
    ],
    "sg:phone":"+1 678 417 0781",
    "sg:postcode":"30097",
    "sg:province":"GA",
    "sg:tags":[
        "agency",
        "services-commercial"
    ],
    "wof:name":"Carribean Villa Rentals",
    "wof:placetype":"venue"
},
  "geometry": {"coordinates":[-84.133369,34.068947],"type":"Point"}
}