{
  "type": "Feature",
  "properties": {
    "addr:full":"79 Maloy Rd Griffin GA 30224",
    "addr:housenumber":"79",
    "addr:postcode":"30224",
    "addr:street":"Maloy Rd",
    "iso:country":"US",
    "sg:address":"79 Maloy Rd",
    "sg:city":"Griffin",
    "sg:classifiers":[
        {
            "category":"Place Of Worship",
            "subcategory":"Church",
            "type":"Public Place"
        },
        {
            "category":"Place Of Worship",
            "type":"Public Place"
        }
    ],
    "sg:phone":"+1 770 467 8832",
    "sg:postcode":"30224",
    "sg:province":"GA",
    "sg:tags":[
        "churches-holiness"
    ],
    "wof:name":"Saint Luke Overcoming Church Of God",
    "wof:placetype":"venue"
},
  "geometry": {"coordinates":[-84.33668900000001,33.208842],"type":"Point"}
}