{
  "type": "Feature",
  "properties": {
    "iso:country":"US",
    "sg:address":"2108 Norwich St",
    "sg:city":"Brunswick",
    "sg:classifiers":[
        {
            "category":"Building & Trades",
            "subcategory":"Plumbing",
            "type":"Services"
        }
    ],
    "sg:phone":"+1 912 264 6306",
    "sg:postcode":"31520",
    "sg:province":"GA",
    "sg:tags":[
        "plumbing",
        "contractor"
    ],
    "wof:name":"Outlaw's Plumbing Co",
    "wof:placetype":"venue"
},
  "geometry": {"coordinates":[-81.494726,31.159334],"type":"Point"}
}