{
  "type": "Feature",
  "properties": {
    "iso:country":"US",
    "sg:address":"334 Chapel Hill Rd",
    "sg:city":"Williamson",
    "sg:classifiers":[
        {
            "category":"Manufacturing",
            "subcategory":"Signs",
            "type":"Manufacturing & Wholesale Goods"
        }
    ],
    "sg:phone":"+1 770 228 9578",
    "sg:postcode":"30292",
    "sg:province":"GA",
    "sg:tags":[
        "specialty",
        "mfg"
    ],
    "wof:name":"Graphics Solutions",
    "wof:placetype":"venue"
},
  "geometry": {"coordinates":[-84.334187,33.172817],"type":"Point"}
}