{
  "type": "Feature",
  "properties": {
    "addr:full":"334 Joe Collins Rd Lyons GA 30436",
    "addr:housenumber":"334",
    "addr:postcode":"30436",
    "addr:street":"Joe Collins Rd",
    "iso:country":"US",
    "sg:address":"334 Joe Collins Rd",
    "sg:city":"Lyons",
    "sg:classifiers":[
        {
            "category":"Farming",
            "subcategory":"Farm",
            "type":"Manufacturing & Wholesale Goods"
        }
    ],
    "sg:phone":"+1 912 526 6316",
    "sg:postcode":"30436",
    "sg:province":"GA",
    "sg:tags":[
        "crop",
        "general"
    ],
    "wof:name":"Milligan Farms",
    "wof:placetype":"venue"
},
  "geometry": {"coordinates":[-82.251051,32.237721],"type":"Point"}
}