{
  "type": "Feature",
  "properties": {
    "iso:country":"US",
    "sg:address":"133 Pavilion Pkwy",
    "sg:city":"Fayetteville",
    "sg:classifiers":[
        {
            "category":"Restaurant",
            "type":"Food & Drink"
        }
    ],
    "sg:phone":"+1 678 923 1971",
    "sg:postcode":"30214",
    "sg:province":"GA",
    "sg:tags":[
        "eating"
    ],
    "wof:name":"Tea Dragon",
    "wof:placetype":"venue"
},
  "geometry": {"coordinates":[-84.438067,33.480226],"type":"Point"}
}