{
  "type": "Feature",
  "properties": {
    "iso:country":"US",
    "sg:address":"1720 Cumberland Point Dr SE Ste 14",
    "sg:city":"Marietta",
    "sg:classifiers":[
        {
            "category":"Personal",
            "type":"Services"
        }
    ],
    "sg:phone":"+1 770 850 0447",
    "sg:postcode":"30067",
    "sg:province":"GA",
    "sg:tags":[
        "mover"
    ],
    "wof:name":"Brasil Box Courier Corp",
    "wof:placetype":"venue"
},
  "geometry": {"coordinates":[-84.493151,33.91061],"type":"Point"}
}