{
  "type": "Feature",
  "properties": {
    "addr:full":"149 Allison Cir Carrollton GA 30117",
    "addr:housenumber":"149",
    "addr:postcode":"30117",
    "addr:street":"Allison Cir",
    "iso:country":"US",
    "sg:address":"149 Allison Cir",
    "sg:city":"Carrollton",
    "sg:classifiers":[
        {
            "category":"Banks & Credit Unions",
            "subcategory":"Bank",
            "type":"Services"
        }
    ],
    "sg:phone":"+1 770 838 0327",
    "sg:postcode":"30117",
    "sg:province":"GA",
    "sg:tags":[
        "mortgage"
    ],
    "wof:name":"Marathon Mortgage Inc",
    "wof:placetype":"venue"
},
  "geometry": {"coordinates":[-85.078288,33.562175],"type":"Point"}
}