{
  "type": "Feature",
  "properties": {
    "iso:country":"US",
    "sg:address":"3038 Lavista Rd",
    "sg:city":"Decatur",
    "sg:classifiers":[
        {
            "category":"Organizations",
            "subcategory":"Community Association",
            "type":"Services"
        }
    ],
    "sg:phone":"+1 404 634 6070",
    "sg:postcode":"30033",
    "sg:province":"GA",
    "sg:tags":[
        "fraternal"
    ],
    "wof:name":"Masonic Lodge",
    "wof:placetype":"venue"
},
  "geometry": {"coordinates":[-84.283175,33.825948],"type":"Point"}
}