{
  "type": "Feature",
  "properties": {
    "iso:country":"US",
    "sg:address":"1133 Oakcliff Rd",
    "sg:city":"Macon",
    "sg:classifiers":[
        {
            "category":"Structure",
            "subcategory":"Office Building",
            "type":"Public Place"
        }
    ],
    "sg:phone":"+1 478 755 9549",
    "sg:postcode":"31211",
    "sg:province":"GA",
    "sg:tags":[
        "park"
    ],
    "wof:name":"Mealor Properties",
    "wof:placetype":"venue"
},
  "geometry": {"coordinates":[-83.63127,32.86001],"type":"Point"}
}