{
  "type": "Feature",
  "properties": {
    "addr:full":"3640 Val Tech Rd Valdosta GA 31602",
    "addr:housenumber":"3640",
    "addr:postcode":"31602",
    "addr:street":"Val Tech Rd",
    "iso:country":"US",
    "sg:address":"3640 Val Tech Rd",
    "sg:city":"Valdosta",
    "sg:classifiers":[
        {
            "category":"Autos & Motor Vehicles",
            "subcategory":"Boat Sales",
            "type":"Retail Goods"
        }
    ],
    "sg:phone":"+1 229 253 0528",
    "sg:postcode":"31602",
    "sg:province":"GA",
    "wof:name":"A Boat Store",
    "wof:placetype":"venue"
},
  "geometry": {"coordinates":[-83.34420900000001,30.8767],"type":"Point"}
}