{
  "type": "Feature",
  "properties": {
    "iso:country":"US",
    "sg:address":"285 Boulevard NE",
    "sg:city":"Atlanta",
    "sg:classifiers":[
        {
            "category":"Health Services",
            "subcategory":"Doctor",
            "type":"Services"
        }
    ],
    "sg:phone":"+1 404 586 9985",
    "sg:postcode":"30312",
    "sg:province":"GA",
    "sg:tags":[
        "physician",
        "surgeons",
        "medicine",
        "surgeon",
        "rehabilitation",
        "physical"
    ],
    "wof:name":"Paramount Family Medicine",
    "wof:placetype":"venue"
},
  "geometry": {"coordinates":[-84.371971,33.762691],"type":"Point"}
}