{
  "type": "Feature",
  "properties": {
    "iso:country":"US",
    "sg:address":"6356 Corley Rd NW",
    "sg:city":"Norcross",
    "sg:classifiers":[
        {
            "category":"Professional",
            "subcategory":"Lawyer & Legal Services",
            "type":"Services"
        }
    ],
    "sg:phone":"+1 770 446 9996",
    "sg:postcode":"30071",
    "sg:province":"GA",
    "sg:tags":[
        "attorney",
        "probate",
        "network",
        "collection",
        "bankruptcy"
    ],
    "wof:name":"Tsys Total Debt Management",
    "wof:placetype":"venue"
},
  "geometry": {"coordinates":[-84.23667399999999,33.931718],"type":"Point"}
}