{
  "type": "Feature",
  "properties": {
    "iso:country":"US",
    "sg:address":"2670 Tucker Mill Rd SW",
    "sg:city":"Conyers",
    "sg:classifiers":[
        {
            "category":"Building & Trades",
            "subcategory":"Construction",
            "type":"Services"
        }
    ],
    "sg:phone":"+1 770 929 0353",
    "sg:postcode":"30094",
    "sg:province":"GA",
    "sg:tags":[
        "general",
        "contractor"
    ],
    "wof:name":"L R C Construciton",
    "wof:placetype":"venue"
},
  "geometry": {"coordinates":[-84.072543,33.602131],"type":"Point"}
}