{
  "type": "Feature",
  "properties": {
    "addr:full":"5810 Pierce Chapel Rd Midland GA 31820",
    "addr:housenumber":"5810",
    "addr:postcode":"31820",
    "addr:street":"Pierce Chapel Rd",
    "iso:country":"US",
    "sg:address":"5810 Pierce Chapel Rd",
    "sg:city":"Midland",
    "sg:classifiers":[
        {
            "category":"Real Estate",
            "subcategory":"Developer",
            "type":"Services"
        }
    ],
    "sg:phone":"+1 706 563 9697",
    "sg:postcode":"31820",
    "sg:province":"GA",
    "wof:name":"Hart Real Estates Services",
    "wof:placetype":"venue"
},
  "geometry": {"coordinates":[-84.890697,32.580155],"type":"Point"}
}