{
  "type": "Feature",
  "properties": {
    "iso:country":"US",
    "sg:address":"5095 Cartersville Hwy",
    "sg:city":"Dallas",
    "sg:classifiers":[
        {
            "category":"Building & Trades",
            "subcategory":"Construction",
            "type":"Services"
        }
    ],
    "sg:phone":"+1 770 445 5533",
    "sg:postcode":"30132",
    "sg:province":"GA",
    "sg:tags":[
        "grading",
        "contractor"
    ],
    "wof:name":"Ferguson Grading",
    "wof:placetype":"venue"
},
  "geometry": {"coordinates":[-84.862303,34.013814],"type":"Point"}
}