{
  "type": "Feature",
  "properties": {
    "iso:country":"US",
    "sg:address":"151 Cardinal Ln",
    "sg:city":"Sautee Nacoochee",
    "sg:classifiers":[
        {
            "category":"Building & Trades",
            "subcategory":"Construction",
            "type":"Services"
        }
    ],
    "sg:phone":"+1 706 865 0412",
    "sg:postcode":"30571",
    "sg:province":"GA",
    "sg:tags":[
        "hanging",
        "contractor"
    ],
    "wof:name":"Burris Painting",
    "wof:placetype":"venue"
},
  "geometry": {"coordinates":[-83.686939,34.640608],"type":"Point"}
}