{
  "type": "Feature",
  "properties": {
    "iso:country":"US",
    "sg:address":"107 Spring Valley Ct",
    "sg:city":"Macon",
    "sg:classifiers":[
        {
            "category":"Real Estate",
            "subcategory":"Real Estate Agent",
            "type":"Services"
        }
    ],
    "sg:phone":"+1 478 474 9095",
    "sg:postcode":"31210",
    "sg:province":"GA",
    "wof:name":"Causey H Chris Appraiser/",
    "wof:placetype":"venue"
},
  "geometry": {"coordinates":[-83.73522800000001,32.892913],"type":"Point"}
}