{
  "type": "Feature",
  "properties": {
    "addr:full":"702 7th St Augusta GA 30901",
    "addr:housenumber":"702",
    "addr:postcode":"30901",
    "addr:street":"7Th St",
    "iso:country":"US",
    "sg:address":"702 7th St",
    "sg:city":"Augusta",
    "sg:classifiers":[
        {
            "category":"Wholesale",
            "subcategory":"Furniture",
            "type":"Manufacturing & Wholesale Goods"
        }
    ],
    "sg:phone":"+1 706 722 7266",
    "sg:postcode":"30901",
    "sg:province":"GA",
    "wof:name":"COF Of Augusta",
    "wof:placetype":"venue"
},
  "geometry": {"coordinates":[-81.96684500000001,33.467521],"type":"Point"}
}