{
  "type": "Feature",
  "properties": {
    "iso:country":"US",
    "sg:address":"614 Park Ave SE",
    "sg:city":"Atlanta",
    "sg:classifiers":[
        {
            "category":"Professional",
            "subcategory":"Accounting & Tax Preparation",
            "type":"Services"
        }
    ],
    "sg:phone":"+1 404 635 9598",
    "sg:postcode":"30312",
    "sg:province":"GA",
    "sg:tags":[
        "accountant"
    ],
    "wof:name":"Accounting Advisors Inc",
    "wof:placetype":"venue"
},
  "geometry": {"coordinates":[-84.36976199999999,33.738097],"type":"Point"}
}