{
  "type": "Feature",
  "properties": {
    "iso:country":"US",
    "sg:address":"20 Lenox Pointe NE",
    "sg:city":"Atlanta",
    "sg:classifiers":[
        {
            "category":"Real Estate",
            "subcategory":"Real Estate Services",
            "type":"Services"
        },
        {
            "category":"Real Estate",
            "subcategory":"Real Estate Agent",
            "type":"Services"
        },
        {
            "category":"Banks & Credit Unions",
            "subcategory":"Financial Services",
            "type":"Services"
        },
        {
            "category":"Real Estate",
            "subcategory":"Developer",
            "type":"Services"
        },
        {
            "category":"Real Estate",
            "subcategory":"Real Estate Operator",
            "type":"Services"
        }
    ],
    "sg:phone":"+1 888 471 7659",
    "sg:postcode":"30324",
    "sg:province":"GA",
    "sg:tags":[
        "apartment",
        "mortgage",
        "investing",
        "consultant",
        "loan",
        "processing",
        "commercial",
        "broker",
        "management",
        "buyer"
    ],
    "sg:website":"http://www.atlantafirstclasshomes.com",
    "wof:name":"HouseSold Group LLC",
    "wof:placetype":"venue"
},
  "geometry": {"coordinates":[-84.35457,33.825402],"type":"Point"}
}