{
  "type": "Feature",
  "properties": {
    "iso:country":"US",
    "sg:address":"4790 Highway 136",
    "sg:city":"Trenton",
    "sg:classifiers":[
        {
            "category":"Restaurant",
            "type":"Food & Drink"
        }
    ],
    "sg:phone":"+1 706 657 8644",
    "sg:postcode":"30752",
    "sg:province":"GA",
    "sg:tags":[
        "lunch",
        "brunch",
        "cafeteria",
        "breakfast"
    ],
    "wof:name":"Teen Time Cafe",
    "wof:placetype":"venue"
},
  "geometry": {"coordinates":[-85.52177399999999,34.869659],"type":"Point"}
}