{
  "type": "Feature",
  "properties": {
    "addr:full":"380 Market Pl Roswell GA 30075",
    "addr:housenumber":"380",
    "addr:postcode":"30075",
    "addr:street":"Market Pl",
    "iso:country":"US",
    "sg:address":"380 Market Pl",
    "sg:city":"Roswell",
    "sg:classifiers":[
        {
            "category":"Professional",
            "subcategory":"Lawyer & Legal Services",
            "type":"Services"
        }
    ],
    "sg:phone":"+1 678 893 9008",
    "sg:postcode":"30075",
    "sg:province":"GA",
    "wof:name":"Law Offices of Chris Lazarou",
    "wof:placetype":"venue"
},
  "geometry": {"coordinates":[-84.34097300000001,34.030497],"type":"Point"}
}