{
  "type": "Feature",
  "properties": {
    "iso:country":"US",
    "sg:address":"322 Stephenson Ave",
    "sg:city":"Savannah",
    "sg:classifiers":[
        {
            "category":"Health Services",
            "subcategory":"Doctor",
            "type":"Services"
        }
    ],
    "sg:phone":"+1 912 354 3130",
    "sg:postcode":"31405",
    "sg:province":"GA",
    "sg:tags":[
        "physician",
        "surgeon",
        "pediatrics",
        "surgeons"
    ],
    "wof:name":"Cossio, Roberto M, Md - Ga Pediatrics",
    "wof:placetype":"venue"
},
  "geometry": {"coordinates":[-81.108047,32.012371],"type":"Point"}
}