{
  "type": "Feature",
  "properties": {
    "addr:full":"3540 Evans Mill Rd Lithonia GA 30038",
    "addr:housenumber":"3540",
    "addr:postcode":"30038",
    "addr:street":"Evans Mill Rd",
    "iso:country":"US",
    "sg:address":"3540 Evans Mill Rd",
    "sg:city":"Lithonia",
    "sg:classifiers":[
        {
            "category":"Building & Trades",
            "subcategory":"Construction",
            "type":"Services"
        }
    ],
    "sg:phone":"+1 770 656 7702",
    "sg:postcode":"30038",
    "sg:province":"GA",
    "sg:tags":[
        "general",
        "contractor"
    ],
    "wof:name":"TDNK",
    "wof:placetype":"venue"
},
  "geometry": {"coordinates":[-84.134551,33.684091],"type":"Point"}
}