{
  "type": "Feature",
  "properties": {
    "addr:full":"3712 New Franklin Rd Hogansville GA 30230",
    "addr:housenumber":"3712",
    "addr:postcode":"30230",
    "addr:street":"New Franklin Rd",
    "iso:country":"US",
    "sg:address":"3712 New Franklin Rd",
    "sg:city":"Hogansville",
    "sg:classifiers":[
        {
            "category":"Recreation",
            "type":"Entertainment"
        }
    ],
    "sg:phone":"+1 706 884 1400",
    "sg:postcode":"30230",
    "sg:province":"GA",
    "wof:name":"Bruce Albea Contracting Inc",
    "wof:placetype":"venue"
},
  "geometry": {"coordinates":[-85.04007900000001,33.134157],"type":"Point"}
}