{
  "type": "Feature",
  "properties": {
    "addr:full":"991 Cascade Xing SW Atlanta GA 30331",
    "addr:housenumber":"991",
    "addr:postcode":"30331",
    "addr:street":"Cascade Xing Sw",
    "iso:country":"US",
    "sg:address":"991 Cascade Xing SW",
    "sg:city":"Atlanta",
    "sg:classifiers":[
        {
            "category":"Insurance",
            "subcategory":"Hazard Insurance",
            "type":"Services"
        }
    ],
    "sg:phone":"+1 404 758 3511",
    "sg:postcode":"30331",
    "sg:province":"GA",
    "wof:name":"Gibb Insurance Agency",
    "wof:placetype":"venue"
},
  "geometry": {"coordinates":[-84.56363,33.728688],"type":"Point"}
}