{
  "type": "Feature",
  "properties": {
    "addr:full":"3571 Lawrenceville Hwy NW Lawrenceville GA 30044",
    "addr:housenumber":"3571",
    "addr:postcode":"30044",
    "addr:street":"Lawrenceville Hwy Nw",
    "iso:country":"US",
    "sg:address":"3571 Lawrenceville Hwy NW",
    "sg:city":"Lawrenceville",
    "sg:classifiers":[
        {
            "category":"Restaurant",
            "type":"Food & Drink"
        },
        {
            "category":"Retail",
            "subcategory":"Event Space",
            "type":"Services"
        }
    ],
    "sg:phone":"+1 770 923 3434",
    "sg:postcode":"30044",
    "sg:province":"GA",
    "sg:tags":[
        "venue"
    ],
    "sg:website":"www.littlegardens.com",
    "wof:name":"Little Gardens Restaurant & Lounge",
    "wof:placetype":"venue"
},
  "geometry": {"coordinates":[-84.101372,33.91117],"type":"Point"}
}