{
  "type": "Feature",
  "properties": {
    "addr:full":"2100 Post Oak Tritt Road NE Atlanta GA 30303",
    "addr:housenumber":"2100",
    "addr:postcode":"30303",
    "addr:street":"Post Oak Tritt Road Ne",
    "iso:country":"US",
    "sg:address":"2100 Post Oak Tritt Road NE",
    "sg:city":"Atlanta",
    "sg:classifiers":[
        {
            "category":"Social Services",
            "subcategory":"Child Care",
            "type":"Services"
        }
    ],
    "sg:phone":"+1 770 971 7200",
    "sg:postcode":"30303",
    "sg:province":"GA",
    "sg:tags":[
        "day"
    ],
    "wof:name":"Kids R Kids International",
    "wof:placetype":"venue"
},
  "geometry": {"coordinates":[-84.38897,33.755418],"type":"Point"}
}