{
  "type": "Feature",
  "properties": {
    "iso:country":"US",
    "sg:address":"3412 Sewell Mill Rd",
    "sg:city":"Marietta",
    "sg:classifiers":[
        {
            "category":"Professional",
            "subcategory":"Business Services",
            "type":"Services"
        }
    ],
    "sg:phone":"+1 770 578 8511",
    "sg:postcode":"30062",
    "sg:province":"GA",
    "wof:name":"Serendib Enterprises Inc",
    "wof:placetype":"venue"
},
  "geometry": {"coordinates":[-84.45360599999999,33.988119],"type":"Point"}
}