{
  "type": "Feature",
  "properties": {
    "addr:full":"1219 Ocean Blvd Saint Simons Island GA 31522",
    "addr:housenumber":"1219",
    "addr:postcode":"31522",
    "addr:street":"Ocean Blvd",
    "iso:country":"US",
    "sg:address":"1219 Ocean Blvd",
    "sg:city":"Saint Simons Island",
    "sg:classifiers":[
        {
            "category":"Restaurant",
            "type":"Food & Drink"
        }
    ],
    "sg:phone":"+1 912 638 7339",
    "sg:postcode":"31522",
    "sg:province":"GA",
    "sg:tags":[
        "eating"
    ],
    "wof:name":"Crabdaddys Restaurant",
    "wof:placetype":"venue"
},
  "geometry": {"coordinates":[-81.381693,31.140477],"type":"Point"}
}