{
  "type": "Feature",
  "properties": {
    "addr:full":"3300 Marjan Dr Atlanta GA 30340",
    "addr:postcode":"3300;30340",
    "addr:street":"Marjan Dr",
    "iso:country":"US",
    "sg:address":"3300 Marjan Dr",
    "sg:city":"Atlanta",
    "sg:classifiers":[
        {
            "category":"Building & Trades",
            "subcategory":"Construction",
            "type":"Services"
        }
    ],
    "sg:phone":"+1 770 458 8165",
    "sg:postcode":"30340",
    "sg:province":"GA",
    "sg:tags":[
        "roofing",
        "contractor"
    ],
    "wof:name":"Standard Of Atlanta",
    "wof:placetype":"venue"
},
  "geometry": {"coordinates":[-84.264791,33.883332],"type":"Point"}
}