{
  "type": "Feature",
  "properties": {
    "addr:full":"1413 E 51st St Savannah GA 31404",
    "addr:housenumber":"1413",
    "addr:postcode":"31404",
    "addr:street":"E 51St St",
    "iso:country":"US",
    "sg:address":"1413 E 51st St",
    "sg:city":"Savannah",
    "sg:classifiers":[
        {
            "category":"Professional",
            "type":"Services"
        },
        {
            "category":"Professional",
            "subcategory":"Lawyer & Legal Services",
            "type":"Services"
        }
    ],
    "sg:phone":"+1 912 692 1111",
    "sg:postcode":"31404",
    "sg:province":"GA",
    "sg:tags":[
        "attorney",
        "family",
        "divorce",
        "mediation",
        "adoption",
        "law"
    ],
    "wof:name":"Powell Janice Atty At Law",
    "wof:placetype":"venue"
},
  "geometry": {"coordinates":[-81.081869,32.04052],"type":"Point"}
}