{
  "type": "Feature",
  "properties": {
    "iso:country":"US",
    "sg:address":"5310 Covington Hwy",
    "sg:city":"Decatur",
    "sg:classifiers":[
        {
            "category":"Professional",
            "type":"Services"
        }
    ],
    "sg:phone":"+1 770 593 9991",
    "sg:postcode":"30035",
    "sg:province":"GA",
    "sg:tags":[
        "establishment"
    ],
    "wof:name":"B & E Development",
    "wof:placetype":"venue"
},
  "geometry": {"coordinates":[-84.195092,33.731642],"type":"Point"}
}