{
  "type": "Feature",
  "properties": {
    "iso:country":"US",
    "sg:address":"2901 Wesley Chapel Rd",
    "sg:city":"Decatur",
    "sg:classifiers":[
        {
            "category":"Social Services",
            "subcategory":"Child Care",
            "type":"Services"
        }
    ],
    "sg:phone":"+1 404 288 2494",
    "sg:postcode":"30034",
    "sg:province":"GA",
    "sg:tags":[
        "day"
    ],
    "sg:website":"www.beulahlearningcenter.com",
    "wof:name":"Beulah Learning Center",
    "wof:placetype":"venue"
},
  "geometry": {"coordinates":[-84.22175799999999,33.70251],"type":"Point"}
}