{
  "type": "Feature",
  "properties": {
    "addr:full":"1354 Plaza Dr Gainesville GA 30501",
    "addr:housenumber":"1354",
    "addr:postcode":"30501",
    "addr:street":"Plaza Dr",
    "iso:country":"US",
    "sg:address":"1354 Plaza Dr",
    "sg:city":"Gainesville",
    "sg:classifiers":[
        {
            "category":"Personal",
            "subcategory":"Massage",
            "type":"Services"
        },
        {
            "category":"Personal",
            "subcategory":"Beauty Salon",
            "type":"Services"
        },
        {
            "category":"Personal",
            "subcategory":"Barber",
            "type":"Services"
        },
        {
            "category":"Personal",
            "subcategory":"Day Spa",
            "type":"Services"
        }
    ],
    "sg:phone":"+1 770 536 4247",
    "sg:postcode":"30501",
    "sg:province":"GA",
    "sg:tags":[
        "hair",
        "accessory",
        "therapist",
        "stylist",
        "supply"
    ],
    "wof:name":"American Salon and Spa",
    "wof:placetype":"venue"
},
  "geometry": {"coordinates":[-83.84717999999999,34.293122],"type":"Point"}
}