{
  "type": "Feature",
  "properties": {
    "iso:country":"US",
    "sg:address":"900 Legacy Park Dr 33",
    "sg:city":"Lawrenceville",
    "sg:classifiers":[
        {
            "category":"Wholesale",
            "subcategory":"Non-durable Goods",
            "type":"Manufacturing & Wholesale Goods"
        }
    ],
    "sg:phone":"+1 678 773 2198",
    "sg:postcode":"30043",
    "sg:province":"GA",
    "sg:tags":[
        "merchandise-wholesale"
    ],
    "wof:name":"Mac Import & Export Corp",
    "wof:placetype":"venue"
},
  "geometry": {"coordinates":[-84.02547199999999,33.965187],"type":"Point"}
}