{
  "type": "Feature",
  "properties": {
    "addr:full":"4875 Floyd Rd SW Mableton GA 30126",
    "addr:housenumber":"4875",
    "addr:postcode":"30126",
    "addr:street":"Floyd Rd Sw",
    "iso:country":"US",
    "sg:address":"4875 Floyd Rd SW",
    "sg:city":"Mableton",
    "sg:classifiers":[
        {
            "category":"Utilities",
            "subcategory":"Mobile Phone",
            "type":"Services"
        }
    ],
    "sg:phone":"+1 770 948 2284",
    "sg:postcode":"30126",
    "sg:province":"GA",
    "sg:tags":[
        "telephone"
    ],
    "wof:name":"DKJ Communications",
    "wof:placetype":"venue"
},
  "geometry": {"coordinates":[-84.577359,33.83957],"type":"Point"}
}