{
  "type": "Feature",
  "properties": {
    "iso:country":"US",
    "sg:address":"515 N McDonough St",
    "sg:city":"Decatur",
    "sg:classifiers":[
        {
            "category":"Professional",
            "subcategory":"Management & Consulting",
            "type":"Services"
        }
    ],
    "sg:phone":"+1 404 370 1415",
    "sg:postcode":"30030",
    "sg:province":"GA",
    "sg:tags":[
        "forwarding",
        "sales",
        "freight",
        "for"
    ],
    "wof:name":"Trans-World Shipping APS",
    "wof:placetype":"venue"
},
  "geometry": {"coordinates":[-84.296448,33.774414],"type":"Point"}
}