{
  "type": "Feature",
  "properties": {
    "iso:country":"US",
    "sg:address":"4141 Fairoaks Rd",
    "sg:city":"Augusta",
    "sg:classifiers":[
        {
            "category":"Retail",
            "subcategory":"Repair Shop",
            "type":"Services"
        }
    ],
    "sg:phone":"+1 706 855 0979",
    "sg:postcode":"30907",
    "sg:province":"GA",
    "wof:name":"Pro Tee Golf",
    "wof:placetype":"venue"
},
  "geometry": {"coordinates":[-82.11405600000001,33.497216],"type":"Point"}
}