{
  "type": "Feature",
  "properties": {
    "iso:country":"US",
    "sg:address":"4010 Canton Hwy",
    "sg:city":"Cumming",
    "sg:classifiers":[
        {
            "category":"Shopping",
            "subcategory":"Used Merchandise",
            "type":"Retail Goods"
        },
        {
            "category":"Home & Garden",
            "subcategory":"Household Appliances",
            "type":"Retail Goods"
        }
    ],
    "sg:phone":"+1 770 887 8524",
    "sg:postcode":"30040",
    "sg:province":"GA",
    "sg:tags":[
        "antique"
    ],
    "wof:name":"Runt's Place",
    "wof:placetype":"venue"
},
  "geometry": {"coordinates":[-84.23774400000001,34.238252],"type":"Point"}
}