{
  "type": "Feature",
  "properties": {
    "addr:full":"8648 Blue Ridge Hwy Blairsville GA 30512",
    "addr:housenumber":"8648",
    "addr:postcode":"30512",
    "addr:street":"Blue Ridge Hwy",
    "iso:country":"US",
    "sg:address":"8648 Blue Ridge Hwy",
    "sg:city":"Blairsville",
    "sg:classifiers":[
        {
            "category":"Shopping",
            "type":"Retail Goods"
        }
    ],
    "sg:phone":"+1 706 745 6788",
    "sg:postcode":"30512",
    "sg:province":"GA",
    "sg:tags":[
        "merchandise"
    ],
    "sg:website":"www.framefarm.com",
    "wof:name":"Frame Farm",
    "wof:placetype":"venue"
},
  "geometry": {"coordinates":[-84.110375,34.872753],"type":"Point"}
}