{
  "type": "Feature",
  "properties": {
    "iso:country":"US",
    "sg:address":"182 N Columbia St",
    "sg:city":"Milledgeville",
    "sg:classifiers":[
        {
            "category":"Building & Trades",
            "subcategory":"Construction",
            "type":"Services"
        }
    ],
    "sg:phone":"+1 478 452 1976",
    "sg:postcode":"31061",
    "sg:province":"GA",
    "sg:tags":[
        "contractor"
    ],
    "wof:name":"Mid State Pools & Spas Inc",
    "wof:placetype":"venue"
},
  "geometry": {"coordinates":[-83.233906,33.080108],"type":"Point"}
}