{
  "type": "Feature",
  "properties": {
    "addr:full":"361 Pearl St SE Atlanta GA 30316",
    "addr:housenumber":"361",
    "addr:postcode":"30316",
    "addr:street":"Pearl St Se",
    "iso:country":"US",
    "sg:address":"361 Pearl St SE",
    "sg:city":"Atlanta",
    "sg:classifiers":[
        {
            "category":"Building & Trades",
            "subcategory":"Construction",
            "type":"Services"
        }
    ],
    "sg:phone":"+1 404 653 0028",
    "sg:postcode":"30316",
    "sg:province":"GA",
    "sg:tags":[
        "utility",
        "contractor"
    ],
    "wof:name":"Ansco & Assoc Inc",
    "wof:placetype":"venue"
},
  "geometry": {"coordinates":[-84.362403,33.74566],"type":"Point"}
}