{
  "type": "Feature",
  "properties": {
    "iso:country":"US",
    "sg:address":"2101 Faulkner Rd NE",
    "sg:city":"Atlanta",
    "sg:classifiers":[
        {
            "category":"Professional",
            "type":"Services"
        }
    ],
    "sg:phone":"+1 404 634 5591",
    "sg:postcode":"30324",
    "sg:province":"GA",
    "wof:name":"Location Finders",
    "wof:placetype":"venue"
},
  "geometry": {"coordinates":[-84.35758800000001,33.811962],"type":"Point"}
}