{
  "type": "Feature",
  "properties": {
    "iso:country":"US",
    "sg:address":"669 Fort Argyle Rd",
    "sg:city":"Savannah",
    "sg:classifiers":[
        {
            "category":"Retail",
            "subcategory":"Auto Repair",
            "type":"Services"
        }
    ],
    "sg:phone":"+1 912 663 7913",
    "sg:postcode":"31419",
    "sg:province":"GA",
    "sg:tags":[
        "repairing",
        "automobile"
    ],
    "wof:name":"Import South",
    "wof:placetype":"venue"
},
  "geometry": {"coordinates":[-81.30670000000001,32.016582],"type":"Point"}
}