{
  "type": "Feature",
  "properties": {
    "iso:country":"US",
    "sg:address":"3166 Cherokee St NW",
    "sg:city":"Kennesaw",
    "sg:classifiers":[
        {
            "category":"Professional",
            "subcategory":"Credit Reporting & Collection",
            "type":"Services"
        }
    ],
    "sg:phone":"+1 770 425 4044",
    "sg:postcode":"30144",
    "sg:province":"GA",
    "sg:tags":[
        "agency"
    ],
    "wof:name":"Nca Receivable Management",
    "wof:placetype":"venue"
},
  "geometry": {"coordinates":[-84.60857799999999,34.030264],"type":"Point"}
}