{
  "type": "Feature",
  "properties": {
    "addr:full":"11 Upper Riverdale Rd Riverdale GA 30274",
    "addr:housenumber":"11",
    "addr:postcode":"30274",
    "addr:street":"Upper Riverdale Rd",
    "iso:country":"US",
    "sg:address":"11 Upper Riverdale Rd",
    "sg:city":"Riverdale",
    "sg:classifiers":[
        {
            "category":"Banks & Credit Unions",
            "subcategory":"Financial Services",
            "type":"Services"
        }
    ],
    "sg:phone":"+1 770 991 8000",
    "sg:postcode":"30274",
    "sg:province":"GA",
    "sg:tags":[
        "company",
        "holding"
    ],
    "wof:name":"Georgia Medcorp Development",
    "wof:placetype":"venue"
},
  "geometry": {"coordinates":[-84.391226,33.577439],"type":"Point"}
}