{
  "type": "Feature",
  "properties": {
    "iso:country":"US",
    "sg:address":"103 Springfield Center Dr",
    "sg:city":"Woodstock",
    "sg:classifiers":[
        {
            "category":"Real Estate",
            "subcategory":"Real Estate Agent",
            "type":"Services"
        },
        {
            "category":"Professional",
            "subcategory":"Management & Consulting",
            "type":"Services"
        }
    ],
    "sg:phone":"+1 770 517 2666",
    "sg:postcode":"30188",
    "sg:province":"GA",
    "sg:tags":[
        "consultant"
    ],
    "wof:name":"Real Property Research Group",
    "wof:placetype":"venue"
},
  "geometry": {"coordinates":[-84.510203,34.087166],"type":"Point"}
}