{
  "type": "Feature",
  "properties": {
    "iso:country":"US",
    "sg:address":"1544 Piedmont Ave NE",
    "sg:city":"Atlanta",
    "sg:classifiers":[
        {
            "category":"Health Services",
            "subcategory":"Chiropractor",
            "type":"Services"
        }
    ],
    "sg:phone":"+1 404 875 0146",
    "sg:postcode":"30324",
    "sg:province":"GA",
    "wof:name":"Hall Chiropractic Clinic",
    "wof:placetype":"venue"
},
  "geometry": {"coordinates":[-84.369698,33.796398],"type":"Point"}
}