{
  "type": "Feature",
  "properties": {
    "addr:full":"670 Deering Rd SE Conyers GA 30094",
    "addr:housenumber":"670",
    "addr:postcode":"30094",
    "addr:street":"Deering Rd Se",
    "iso:country":"US",
    "sg:address":"670 Deering Rd SE",
    "sg:city":"Conyers",
    "sg:classifiers":[
        {
            "category":"Social Services",
            "subcategory":"Adult Care",
            "type":"Services"
        }
    ],
    "sg:phone":"+1 770 761 4997",
    "sg:postcode":"30094",
    "sg:province":"GA",
    "sg:tags":[
        "home",
        "residential"
    ],
    "wof:name":"Our Lady Of Hope Assisted Lvng",
    "wof:placetype":"venue"
},
  "geometry": {"coordinates":[-84.023752,33.613959],"type":"Point"}
}