{
  "type": "Feature",
  "properties": {
    "addr:full":"4317 Evans To Locks Rd Evans GA 30809",
    "addr:housenumber":"4317;to",
    "addr:postcode":"30809",
    "addr:street":"Evans;Locks Rd",
    "iso:country":"US",
    "sg:address":"4317 Evans To Locks Rd",
    "sg:city":"Evans",
    "sg:classifiers":[
        {
            "category":"Retail",
            "subcategory":"Veterinary Services",
            "type":"Services"
        }
    ],
    "sg:phone":"+1 706 868 0479",
    "sg:postcode":"30809",
    "sg:province":"GA",
    "sg:tags":[
        "veterinarian"
    ],
    "wof:name":"Evans Animal Hospital",
    "wof:placetype":"venue"
},
  "geometry": {"coordinates":[-82.118233,33.539823],"type":"Point"}
}