{
  "type": "Feature",
  "properties": {
    "iso:country":"US",
    "sg:address":"1485 Barrier Rd",
    "sg:city":"Marietta",
    "sg:classifiers":[
        {
            "category":"Building & Trades",
            "subcategory":"Construction",
            "type":"Services"
        }
    ],
    "sg:phone":"+1 770 591 8387",
    "sg:postcode":"30066",
    "sg:province":"GA",
    "sg:tags":[
        "carpentry",
        "contractor"
    ],
    "wof:name":"Carpentry By Design",
    "wof:placetype":"venue"
},
  "geometry": {"coordinates":[-84.505135,34.060138],"type":"Point"}
}