{
  "type": "Feature",
  "properties": {
    "iso:country":"US",
    "sg:address":"4860 Crystal Lake Ct",
    "sg:city":"Kennesaw",
    "sg:classifiers":[
        {
            "category":"Building & Trades",
            "subcategory":"Construction",
            "type":"Services"
        }
    ],
    "sg:phone":"+1 770 928 4019",
    "sg:postcode":"30144",
    "sg:province":"GA",
    "sg:tags":[
        "acoustical",
        "drywall",
        "contractor"
    ],
    "wof:name":"Chandler Interiors Inc",
    "wof:placetype":"venue"
},
  "geometry": {"coordinates":[-84.54916,34.067461],"type":"Point"}
}