{
  "type": "Feature",
  "properties": {
    "addr:full":"2208 N Point Cir Alpharetta GA 30022",
    "addr:housenumber":"2208",
    "addr:postcode":"30022",
    "addr:street":"N Point Cir",
    "iso:country":"US",
    "sg:address":"2208 N Point Cir",
    "sg:city":"Alpharetta",
    "sg:classifiers":[
        {
            "category":"Shopping",
            "subcategory":"Music",
            "type":"Retail Goods"
        }
    ],
    "sg:phone":"+1 770 664 5751",
    "sg:postcode":"30022",
    "sg:province":"GA",
    "sg:tags":[
        "compact",
        "record",
        "disc",
        "tape",
        "dvd's"
    ],
    "wof:name":"Fye",
    "wof:placetype":"venue"
},
  "geometry": {"coordinates":[-84.294701,34.050999],"type":"Point"}
}