{
  "type": "Feature",
  "properties": {
    "iso:country":"US",
    "sg:address":"11238 US Hwy 129",
    "sg:city":"Talmo",
    "sg:classifiers":[
        {
            "category":"Organizations",
            "subcategory":"Religious Organization",
            "type":"Services"
        }
    ],
    "sg:phone":"+1 706 693 2644",
    "sg:postcode":"30575",
    "sg:province":"GA",
    "sg:tags":[
        "church"
    ],
    "wof:name":"Mercy's Call Ministries Inc",
    "wof:placetype":"venue"
},
  "geometry": {"coordinates":[-83.720006,34.201336],"type":"Point"}
}