{
  "type": "Feature",
  "properties": {
    "addr:full":"214 Main St Eastman GA 31023",
    "addr:housenumber":"214",
    "addr:postcode":"31023",
    "addr:street":"Main St",
    "iso:country":"US",
    "sg:address":"214 Main St",
    "sg:city":"Eastman",
    "sg:classifiers":[
        {
            "category":"Manufacturing",
            "subcategory":"Jewelry",
            "type":"Manufacturing & Wholesale Goods"
        }
    ],
    "sg:phone":"+1 478 374 3613",
    "sg:postcode":"31023",
    "sg:province":"GA",
    "sg:tags":[
        "mfg"
    ],
    "wof:name":"Rosie Designs",
    "wof:placetype":"venue"
},
  "geometry": {"coordinates":[-83.175785,32.197935],"type":"Point"}
}