{
  "type": "Feature",
  "properties": {
    "iso:country":"US",
    "sg:address":"561 E Olliff St",
    "sg:city":"Statesboro",
    "sg:classifiers":[
        {
            "category":"Communications",
            "subcategory":"Radio Station",
            "type":"Services"
        }
    ],
    "sg:phone":"+1 912 764 6000",
    "sg:postcode":"30458",
    "sg:province":"GA",
    "sg:tags":[
        "company",
        "broadcasting"
    ],
    "wof:name":"WMCD",
    "wof:placetype":"venue"
},
  "geometry": {"coordinates":[-81.77379000000001,32.454843],"type":"Point"}
}