{
  "type": "Feature",
  "properties": {
    "addr:full":"3815 Sandy Cross Rd Royston GA 30662",
    "addr:housenumber":"3815",
    "addr:postcode":"30662",
    "addr:street":"Sandy Cross Rd",
    "iso:country":"US",
    "sg:address":"3815 Sandy Cross Rd",
    "sg:city":"Royston",
    "sg:classifiers":[
        {
            "category":"Professional",
            "type":"Services"
        }
    ],
    "sg:phone":"+1 706 245 7249",
    "sg:postcode":"30662",
    "sg:province":"GA",
    "wof:name":"Garmonaubury",
    "wof:placetype":"venue"
},
  "geometry": {"coordinates":[-83.237709,34.291013],"type":"Point"}
}