{
  "type": "Feature",
  "properties": {
    "addr:full":"4512 Beacon Hill Dr Lilburn GA 30047",
    "addr:housenumber":"4512",
    "addr:postcode":"30047",
    "addr:street":"Beacon Hill Dr",
    "iso:country":"US",
    "sg:address":"4512 Beacon Hill Dr",
    "sg:city":"Lilburn",
    "sg:classifiers":[
        {
            "category":"Professional",
            "type":"Services"
        }
    ],
    "sg:phone":"+1 770 923 5193",
    "sg:postcode":"30047",
    "sg:province":"GA",
    "sg:tags":[
        "establishment"
    ],
    "wof:name":"Exodus Lifestyles",
    "wof:placetype":"venue"
},
  "geometry": {"coordinates":[-84.10321500000001,33.856553],"type":"Point"}
}