{
  "type": "Feature",
  "properties": {
    "addr:full":"565 Mize Rd Toccoa GA 30577",
    "addr:housenumber":"565",
    "addr:postcode":"30577",
    "addr:street":"Mize Rd",
    "iso:country":"US",
    "sg:address":"565 Mize Rd",
    "sg:city":"Toccoa",
    "sg:classifiers":[
        {
            "category":"Food & Beverages",
            "subcategory":"Groceries & Convenience Stores",
            "type":"Retail Goods"
        }
    ],
    "sg:phone":"+1 706 282 7269",
    "sg:postcode":"30577",
    "sg:province":"GA",
    "wof:name":"Quick Mart",
    "wof:placetype":"venue"
},
  "geometry": {"coordinates":[-83.32167800000001,34.552716],"type":"Point"}
}