{
  "type": "Feature",
  "properties": {
    "iso:country":"US",
    "sg:address":"6120 Northbelt Pkwy",
    "sg:city":"Norcross",
    "sg:classifiers":[
        {
            "category":"Manufacturing",
            "subcategory":"Chemicals & Compounds",
            "type":"Manufacturing & Wholesale Goods"
        },
        {
            "category":"Building & Trades",
            "subcategory":"Landscaping Services",
            "type":"Services"
        },
        {
            "category":"Building & Trades",
            "subcategory":"Pest Control",
            "type":"Services"
        },
        {
            "category":"Professional",
            "subcategory":"Testing Lab",
            "type":"Services"
        }
    ],
    "sg:phone":"+1 770 409 8882",
    "sg:postcode":"30071",
    "sg:province":"GA",
    "sg:tags":[
        "lawn",
        "industrial",
        "supply",
        "services-commercial",
        "termite",
        "radon",
        "equipment",
        "mitigation",
        "maintenance"
    ],
    "sg:website":"http://www.bacoexterminating.com",
    "wof:name":"BACO Exterminating Services LLC",
    "wof:placetype":"venue"
},
  "geometry": {"coordinates":[-84.214643,33.925242],"type":"Point"}
}