{
  "type": "Feature",
  "properties": {
    "addr:full":"5615 Houston Rd Macon GA 31216",
    "addr:housenumber":"5615",
    "addr:postcode":"31216",
    "addr:street":"Houston Rd",
    "iso:country":"US",
    "sg:address":"5615 Houston Rd",
    "sg:city":"Macon",
    "sg:classifiers":[
        {
            "category":"Food & Beverages",
            "subcategory":"Groceries & Convenience Stores",
            "type":"Retail Goods"
        }
    ],
    "sg:phone":"+1 478 785 0655",
    "sg:postcode":"31216",
    "sg:province":"GA",
    "sg:tags":[
        "supermarket",
        "chain"
    ],
    "wof:name":"Food Lion Store 1245",
    "wof:placetype":"venue"
},
  "geometry": {"coordinates":[-83.672,32.746784],"type":"Point"}
}