{
  "type": "Feature",
  "properties": {
    "iso:country":"US",
    "sg:address":"104 Spring Lake Cir",
    "sg:city":"Morrow",
    "sg:classifiers":[
        {
            "category":"Real Estate",
            "subcategory":"Real Estate Agent",
            "type":"Services"
        }
    ],
    "sg:phone":"+1 404 569 0215",
    "sg:postcode":"30260",
    "sg:province":"GA",
    "wof:name":"Perfect Appraisal",
    "wof:placetype":"venue"
},
  "geometry": {"coordinates":[-84.335973,33.564095],"type":"Point"}
}