{
  "type": "Feature",
  "properties": {
    "iso:country":"US",
    "sg:address":"1089 Riverdale Dr",
    "sg:city":"Waycross",
    "sg:classifiers":[
        {
            "category":"Building & Trades",
            "subcategory":"Construction",
            "type":"Services"
        }
    ],
    "sg:phone":"+1 912 283 1259",
    "sg:postcode":"31503",
    "sg:province":"GA",
    "sg:tags":[
        "house"
    ],
    "wof:name":"L & P Homebuilders Inc",
    "wof:placetype":"venue"
},
  "geometry": {"coordinates":[-82.315687,31.216547],"type":"Point"}
}