{
  "type": "Feature",
  "properties": {
    "addr:full":"3408 Botany Woods Dr Gainesville GA 30506",
    "addr:housenumber":"3408",
    "addr:postcode":"30506",
    "addr:street":"Botany Woods Dr",
    "iso:country":"US",
    "sg:address":"3408 Botany Woods Dr",
    "sg:city":"Gainesville",
    "sg:classifiers":[
        {
            "category":"Shopping",
            "subcategory":"Gifts & Souvenirs",
            "type":"Retail Goods"
        }
    ],
    "sg:phone":"+1 770 536 3823",
    "sg:postcode":"30506",
    "sg:province":"GA",
    "wof:name":"Gifts Unique Inc",
    "wof:placetype":"venue"
},
  "geometry": {"coordinates":[-83.788094,34.3622],"type":"Point"}
}