{
  "type": "Feature",
  "properties": {
    "iso:country":"US",
    "sg:address":"332 Washington St SW",
    "sg:city":"Gainesville",
    "sg:classifiers":[
        {
            "category":"Home & Garden",
            "subcategory":"Hardware",
            "type":"Retail Goods"
        }
    ],
    "sg:phone":"+1 770 538 0114",
    "sg:postcode":"30501",
    "sg:province":"GA",
    "wof:name":"Streetscape Hardware",
    "wof:placetype":"venue"
},
  "geometry": {"coordinates":[-83.82957399999999,34.298823],"type":"Point"}
}