{
  "type": "Feature",
  "properties": {
    "addr:full":"3131 Cobb Pkwy #100 Atlanta GA 30339",
    "addr:housenumber":"3131",
    "addr:postcode":"30339",
    "addr:street":"Cobb Pkwy # 100",
    "iso:country":"US",
    "sg:address":"3131 Cobb Pkwy #100",
    "sg:city":"Atlanta",
    "sg:classifiers":[
        {
            "category":"Fast Food",
            "type":"Food & Drink"
        },
        {
            "category":"Restaurant",
            "type":"Food & Drink"
        }
    ],
    "sg:phone":"+1 770 955 5929",
    "sg:postcode":"30339",
    "sg:province":"GA",
    "sg:tags":[
        "style",
        "mexican",
        "family",
        "lunch",
        "take",
        "brunch",
        "breakfast"
    ],
    "sg:website":"http://www.donpablos.com/",
    "wof:name":"Don Pablo's",
    "wof:placetype":"venue"
},
  "geometry": {"coordinates":[-84.456492,33.877365],"type":"Point"}
}