{
  "type": "Feature",
  "properties": {
    "addr:full":"2206 Hanfred Ln Tucker GA 30084",
    "addr:housenumber":"2206",
    "addr:postcode":"30084",
    "addr:street":"Hanfred Ln",
    "iso:country":"US",
    "sg:address":"2206 Hanfred Ln",
    "sg:city":"Tucker",
    "sg:classifiers":[
        {
            "category":"Autos & Motor Vehicles",
            "subcategory":"Automobile Sales",
            "type":"Retail Goods"
        },
        {
            "category":"Autos & Motor Vehicles",
            "subcategory":"Auto Supplies",
            "type":"Retail Goods"
        }
    ],
    "sg:phone":"+1 770 270 5979",
    "sg:postcode":"30084",
    "sg:province":"GA",
    "sg:tags":[
        "car",
        "dealer"
    ],
    "wof:name":"Car Pro Auto Sales LLC",
    "wof:placetype":"venue"
},
  "geometry": {"coordinates":[-84.210042,33.847851],"type":"Point"}
}