{
  "type": "Feature",
  "properties": {
    "addr:full":"2092 Red Rose Ln Loganville GA 30052",
    "addr:housenumber":"2092",
    "addr:postcode":"30052",
    "addr:street":"Red Rose Ln",
    "iso:country":"US",
    "sg:address":"2092 Red Rose Ln",
    "sg:city":"Loganville",
    "sg:classifiers":[
        {
            "category":"Manufacturing",
            "subcategory":"Printing",
            "type":"Manufacturing & Wholesale Goods"
        }
    ],
    "sg:phone":"+1 770 978 7158",
    "sg:postcode":"30052",
    "sg:province":"GA",
    "sg:tags":[
        "printer"
    ],
    "wof:name":"TNT Print Finishing",
    "wof:placetype":"venue"
},
  "geometry": {"coordinates":[-83.969477,33.834071],"type":"Point"}
}