{
  "type": "Feature",
  "properties": {
    "iso:country":"US",
    "sg:address":"39 Winter Pl",
    "sg:city":"Chula",
    "sg:classifiers":[
        {
            "category":"Professional",
            "type":"Services"
        }
    ],
    "sg:phone":"+1 229 382 8517",
    "sg:postcode":"31733",
    "sg:province":"GA",
    "wof:name":"John H Dekle",
    "wof:placetype":"venue"
},
  "geometry": {"coordinates":[-83.496281,31.551548],"type":"Point"}
}