{
  "type": "Feature",
  "properties": {
    "iso:country":"US",
    "sg:address":"1841 Piedmont Rd",
    "sg:city":"Marietta",
    "sg:classifiers":[
        {
            "category":"Professional",
            "subcategory":"Employment Agencies",
            "type":"Services"
        }
    ],
    "sg:phone":"+1 770 578 6677",
    "sg:postcode":"30066",
    "sg:province":"GA",
    "sg:tags":[
        "opportunity"
    ],
    "sg:website":"www.computerstaffing.net",
    "wof:name":"Computer Staffing Solutions",
    "wof:placetype":"venue"
},
  "geometry": {"coordinates":[-84.499584,34.014276],"type":"Point"}
}