{
  "type": "Feature",
  "properties": {
    "addr:full":"112 Crestwood Cir Centerville GA 31028",
    "addr:housenumber":"112",
    "addr:postcode":"31028",
    "addr:street":"Crestwood Cir",
    "iso:country":"US",
    "sg:address":"112 Crestwood Cir",
    "sg:city":"Centerville",
    "sg:classifiers":[
        {
            "category":"Professional",
            "subcategory":"Management & Consulting",
            "type":"Services"
        }
    ],
    "sg:phone":"+1 478 321 2050",
    "sg:postcode":"31028",
    "sg:province":"GA",
    "sg:tags":[
        "consultant"
    ],
    "wof:name":"Austin Moore Group",
    "wof:placetype":"venue"
},
  "geometry": {"coordinates":[-83.675156,32.635715],"type":"Point"}
}