{
  "type": "Feature",
  "properties": {
    "iso:country":"US",
    "sg:address":"4036 E Ponce de Leon Ave",
    "sg:city":"Clarkston",
    "sg:classifiers":[
        {
            "category":"Social Services",
            "subcategory":"Adult Care",
            "type":"Services"
        }
    ],
    "sg:phone":"+1 404 292 6420",
    "sg:postcode":"30021",
    "sg:province":"GA",
    "sg:tags":[
        "residential",
        "child"
    ],
    "sg:website":"www.positivegrowth.org",
    "wof:name":"Positive Growth Inc",
    "wof:placetype":"venue"
},
  "geometry": {"coordinates":[-84.242107,33.806368],"type":"Point"}
}