{
  "type": "Feature",
  "properties": {
    "addr:full":"3405 Dallas Hwy SW Marietta GA 30064",
    "addr:housenumber":"3405",
    "addr:postcode":"30064",
    "addr:street":"Dallas Hwy Sw",
    "iso:country":"US",
    "sg:address":"3405 Dallas Hwy SW",
    "sg:city":"Marietta",
    "sg:classifiers":[
        {
            "category":"Professional",
            "type":"Services"
        },
        {
            "category":"Food & Beverages",
            "subcategory":"Bakery",
            "type":"Retail Goods"
        }
    ],
    "sg:phone":"+1 770 795 0196",
    "sg:postcode":"30064",
    "sg:province":"GA",
    "sg:tags":[
        "sandwich",
        "caterer"
    ],
    "wof:name":"Honeybaked Ham Company",
    "wof:placetype":"venue"
},
  "geometry": {"coordinates":[-84.65207700000001,33.953458],"type":"Point"}
}