{
  "type": "Feature",
  "properties": {
    "addr:full":"1186 E Broad Ave Albany GA 31705",
    "addr:housenumber":"1186",
    "addr:postcode":"31705",
    "addr:street":"E Broad Ave",
    "iso:country":"US",
    "sg:address":"1186 E Broad Ave",
    "sg:city":"Albany",
    "sg:classifiers":[
        {
            "category":"Building & Trades",
            "subcategory":"Cleaning & Sanitation",
            "type":"Services"
        }
    ],
    "sg:phone":"+1 229 436 3004",
    "sg:postcode":"31705",
    "sg:province":"GA",
    "sg:tags":[
        "livestock",
        "maintenance"
    ],
    "wof:name":"Poultry Housekeeping Service",
    "wof:placetype":"venue"
},
  "geometry": {"coordinates":[-84.124351,31.576401],"type":"Point"}
}