{
  "type": "Feature",
  "properties": {
    "iso:country":"US",
    "sg:address":"Peachtree St NE",
    "sg:city":"Atlanta",
    "sg:classifiers":[
        {
            "category":"Retail",
            "subcategory":"Animal Services",
            "type":"Services"
        }
    ],
    "sg:phone":"+1 404 874 5224",
    "sg:postcode":"30309",
    "sg:province":"GA",
    "sg:tags":[
        "pet"
    ],
    "wof:name":"Alpha Academy Of Dog Training By Bob Moorefield",
    "wof:placetype":"venue"
},
  "geometry": {"coordinates":[-84.38385,33.788481],"type":"Point"}
}