{
  "type": "Feature",
  "properties": {
    "addr:full":"702 Woodgate Rd Ringgold GA 30736",
    "addr:housenumber":"702",
    "addr:postcode":"30736",
    "addr:street":"Woodgate Rd",
    "iso:country":"US",
    "sg:address":"702 Woodgate Rd",
    "sg:city":"Ringgold",
    "sg:classifiers":[
        {
            "category":"Real Estate",
            "subcategory":"Real Estate Agent",
            "type":"Services"
        }
    ],
    "sg:phone":"+1 706 937 7379",
    "sg:postcode":"30736",
    "sg:province":"GA",
    "wof:name":"Hale Burk Realtors Inc",
    "wof:placetype":"venue"
},
  "geometry": {"coordinates":[-85.16048600000001,34.931534],"type":"Point"}
}