{
  "type": "Feature",
  "properties": {
    "iso:country":"US",
    "sg:address":"17 Heartwood Dr SW",
    "sg:city":"Cartersville",
    "sg:classifiers":[
        {
            "category":"Recreation",
            "type":"Entertainment"
        }
    ],
    "sg:phone":"+1 770 607 5272",
    "sg:postcode":"30120",
    "sg:province":"GA",
    "sg:tags":[
        "pool",
        "swimming"
    ],
    "wof:name":"Mission Estates Pool",
    "wof:placetype":"venue"
},
  "geometry": {"coordinates":[-84.85860099999999,34.175464],"type":"Point"}
}