{
  "type": "Feature",
  "properties": {
    "iso:country":"US",
    "sg:address":"2580 Riverwood Spring",
    "sg:city":"Ellenwood",
    "sg:classifiers":[
        {
            "category":"Social Services",
            "subcategory":"Child Care",
            "type":"Services"
        }
    ],
    "sg:phone":"+1 404 243 1355",
    "sg:postcode":"30294",
    "sg:province":"GA",
    "sg:tags":[
        "day"
    ],
    "wof:name":"Babysteps To Success",
    "wof:placetype":"venue"
},
  "geometry": {"coordinates":[-84.283506,33.671264],"type":"Point"}
}