{
  "type": "Feature",
  "properties": {
    "addr:full":"2641 Colony Way Snellville GA 30078",
    "addr:housenumber":"2641",
    "addr:postcode":"30078",
    "addr:street":"Colony Way",
    "iso:country":"US",
    "sg:address":"2641 Colony Way",
    "sg:city":"Snellville",
    "sg:classifiers":[
        {
            "category":"Professional",
            "subcategory":"Computer Services",
            "type":"Services"
        }
    ],
    "sg:phone":"+1 770 985 8108",
    "sg:postcode":"30078",
    "sg:province":"GA",
    "sg:tags":[
        "repair"
    ],
    "wof:name":"Your On Call Tech",
    "wof:placetype":"venue"
},
  "geometry": {"coordinates":[-84.031733,33.86694],"type":"Point"}
}