{
  "type": "Feature",
  "properties": {
    "addr:full":"2638 W Regency Dr Tucker GA 30084",
    "addr:housenumber":"2638",
    "addr:postcode":"30084",
    "addr:street":"W Regency Dr",
    "iso:country":"US",
    "sg:address":"2638 W Regency Dr",
    "sg:city":"Tucker",
    "sg:classifiers":[
        {
            "category":"Shopping",
            "subcategory":"Computers & Home Electronics",
            "type":"Retail Goods"
        }
    ],
    "sg:phone":"+1 770 414 5654",
    "sg:postcode":"30084",
    "sg:province":"GA",
    "wof:name":"Katiess Cds",
    "wof:placetype":"venue"
},
  "geometry": {"coordinates":[-84.24486400000001,33.864653],"type":"Point"}
}