{
  "type": "Feature",
  "properties": {
    "iso:country":"US",
    "sg:address":"2523 Madison Cmns",
    "sg:city":"Atlanta",
    "sg:classifiers":[
        {
            "category":"Professional",
            "type":"Services"
        }
    ],
    "sg:phone":"+1 404 840 1154",
    "sg:postcode":"30360",
    "sg:province":"GA",
    "wof:name":"Ecareworks Inc",
    "wof:placetype":"venue"
},
  "geometry": {"coordinates":[-84.28494499999999,33.929489],"type":"Point"}
}