{
  "type": "Feature",
  "properties": {
    "addr:full":"3969 Athens Hwy Loganville GA 30052",
    "addr:housenumber":"3969",
    "addr:postcode":"30052",
    "addr:street":"Athens Hwy",
    "iso:country":"US",
    "sg:address":"3969 Athens Hwy",
    "sg:city":"Loganville",
    "sg:classifiers":[
        {
            "category":"Building & Trades",
            "subcategory":"Construction",
            "type":"Services"
        }
    ],
    "sg:phone":"+1 770 466 1976",
    "sg:postcode":"30052",
    "sg:province":"GA",
    "sg:tags":[
        "general",
        "contractor"
    ],
    "wof:name":"L Carter Construction Inc",
    "wof:placetype":"venue"
},
  "geometry": {"coordinates":[-83.91383500000001,33.847727],"type":"Point"}
}