{
  "type": "Feature",
  "properties": {
    "addr:full":"4682 Monticello Cir Marietta GA 30066",
    "addr:housenumber":"4682",
    "addr:postcode":"30066",
    "addr:street":"Monticello Cir",
    "iso:country":"US",
    "sg:address":"4682 Monticello Cir",
    "sg:city":"Marietta",
    "sg:classifiers":[
        {
            "category":"Professional",
            "subcategory":"Computer Services",
            "type":"Services"
        }
    ],
    "sg:phone":"+1 770 552 1813",
    "sg:postcode":"30066",
    "sg:province":"GA",
    "sg:tags":[
        "related"
    ],
    "wof:name":"Lester R Reed",
    "wof:placetype":"venue"
},
  "geometry": {"coordinates":[-84.427747,34.063806],"type":"Point"}
}