{
  "type": "Feature",
  "properties": {
    "iso:country":"US",
    "sg:address":"596 Maynard St",
    "sg:city":"Macon",
    "sg:classifiers":[
        {
            "category":"Personal",
            "subcategory":"Beauty Salon",
            "type":"Services"
        }
    ],
    "sg:phone":"+1 478 722 6377",
    "sg:postcode":"31217",
    "sg:province":"GA",
    "wof:name":"Myer's Hair Care",
    "wof:placetype":"venue"
},
  "geometry": {"coordinates":[-83.610917,32.847685],"type":"Point"}
}