{
  "type": "Feature",
  "properties": {
    "iso:country":"US",
    "sg:address":"124 Cedar Ln",
    "sg:city":"Augusta",
    "sg:classifiers":[
        {
            "category":"Recreation",
            "type":"Entertainment"
        }
    ],
    "sg:phone":"+1 706 650 2111",
    "sg:postcode":"30907",
    "sg:province":"GA",
    "sg:tags":[
        "gymnastics",
        "instructions"
    ],
    "wof:name":"Mr Mooses Mighty Mytes",
    "wof:placetype":"venue"
},
  "geometry": {"coordinates":[-82.07680999999999,33.519898],"type":"Point"}
}