{
  "type": "Feature",
  "properties": {
    "iso:country":"US",
    "sg:address":"2880 Lawrenceville Suwanee Rd",
    "sg:city":"Suwanee",
    "sg:classifiers":[
        {
            "category":"Restaurant",
            "type":"Food & Drink"
        }
    ],
    "sg:menulink":"http://www.allmenus.com/ga/lawrenceville/93742-the-orient-garden---chinese,-japanese--thai/menu/",
    "sg:phone":"+1 770 932 6688",
    "sg:postcode":"30024",
    "sg:province":"GA",
    "sg:tags":[
        "asian",
        "chinese"
    ],
    "wof:name":"The Orient Garden - Chinese, Japanese & Thai",
    "wof:placetype":"venue"
},
  "geometry": {"coordinates":[-84.047116,34.028801],"type":"Point"}
}