{
  "type": "Feature",
  "properties": {
    "iso:country":"US",
    "sg:address":"6825 Dressage Xing",
    "sg:city":"Cumming",
    "sg:classifiers":[
        {
            "category":"Manufacturing",
            "subcategory":"Tools & Machinery",
            "type":"Manufacturing & Wholesale Goods"
        }
    ],
    "sg:phone":"+1 404 317 0042",
    "sg:postcode":"30040",
    "sg:province":"GA",
    "sg:tags":[
        "equipment",
        "peripheral",
        "computer"
    ],
    "wof:name":"Digital Color Group Inc",
    "wof:placetype":"venue"
},
  "geometry": {"coordinates":[-84.22088599999999,34.170274],"type":"Point"}
}