{
  "type": "Feature",
  "properties": {
    "addr:full":"3231 Cains Hill Pl NW Ste A Atlanta GA 30305",
    "addr:housenumber":"3231",
    "addr:postcode":"30305",
    "addr:street":"Cains Hill Pl Nw Ste A",
    "iso:country":"US",
    "sg:address":"3231 Cains Hill Pl NW Ste A",
    "sg:city":"Atlanta",
    "sg:phone":"+1 404 816 8230",
    "sg:postcode":"30305",
    "sg:province":"GA",
    "sg:website":"http://www.brinabeads.com",
    "wof:name":"Brina Beads Inc",
    "wof:placetype":"venue"
},
  "geometry": {"coordinates":[-84.38054700000001,33.842807],"type":"Point"}
}