{
  "type": "Feature",
  "properties": {
    "iso:country":"US",
    "sg:address":"7107 Skidaway Rd",
    "sg:city":"Savannah",
    "sg:classifiers":[
        {
            "category":"Banks & Credit Unions",
            "subcategory":"Bank",
            "type":"Services"
        }
    ],
    "sg:phone":"+1 912 354 0660",
    "sg:postcode":"31406",
    "sg:province":"GA",
    "sg:tags":[
        "cashing",
        "check"
    ],
    "wof:name":"Skidaway Check Cashing",
    "wof:placetype":"venue"
},
  "geometry": {"coordinates":[-81.077905,31.998569],"type":"Point"}
}