{
  "type": "Feature",
  "properties": {
    "iso:country":"US",
    "sg:address":"1010 Huntcliff NE",
    "sg:city":"Atlanta",
    "sg:classifiers":[
        {
            "category":"Real Estate",
            "subcategory":"Real Estate Agent",
            "type":"Services"
        }
    ],
    "sg:phone":"+1 770 518 2450",
    "sg:postcode":"30350",
    "sg:province":"GA",
    "wof:name":"MTS Realty",
    "wof:placetype":"venue"
},
  "geometry": {"coordinates":[-84.355925,33.99312],"type":"Point"}
}