{
  "type": "Feature",
  "properties": {
    "iso:country":"US",
    "sg:address":"10865 Glenbarr Dr",
    "sg:city":"Duluth",
    "sg:classifiers":[
        {
            "category":"Wholesale",
            "subcategory":"Non-durable Goods",
            "type":"Manufacturing & Wholesale Goods"
        }
    ],
    "sg:phone":"+1 770 671 0380",
    "sg:postcode":"30097",
    "sg:province":"GA",
    "sg:tags":[
        "advertising",
        "specialty"
    ],
    "wof:name":"Kay-Cee Enterprises of Atlanta",
    "wof:placetype":"venue"
},
  "geometry": {"coordinates":[-84.171648,34.040943],"type":"Point"}
}