{
  "type": "Feature",
  "properties": {
    "iso:country":"US",
    "sg:address":"Pine Log Rd NE Apt 1043",
    "sg:city":"Conyers",
    "sg:classifiers":[
        {
            "category":"Real Estate",
            "subcategory":"Real Estate Operator",
            "type":"Services"
        }
    ],
    "sg:phone":"+1 770 483 1517",
    "sg:postcode":"30013",
    "sg:province":"GA",
    "sg:tags":[
        "apartment"
    ],
    "wof:name":"Towne Pointe",
    "wof:placetype":"venue"
},
  "geometry": {"coordinates":[-83.992699,33.624199],"type":"Point"}
}