{
  "type": "Feature",
  "properties": {
    "addr:full":"3049 Carrollton Villa Rica Hwy Carrollton GA 30116",
    "addr:housenumber":"3049",
    "addr:postcode":"30116",
    "addr:street":"Carrollton Villa Rica Hwy",
    "iso:country":"US",
    "sg:address":"3049 Carrollton Villa Rica Hwy",
    "sg:city":"Carrollton",
    "sg:classifiers":[
        {
            "category":"Professional",
            "subcategory":"Business Services",
            "type":"Services"
        }
    ],
    "sg:phone":"+1 770 214 2979",
    "sg:postcode":"30116",
    "sg:province":"GA",
    "sg:tags":[
        "auctioneer"
    ],
    "wof:name":"Braswell's Mini Storage",
    "wof:placetype":"venue"
},
  "geometry": {"coordinates":[-84.98874600000001,33.630012],"type":"Point"}
}