{
  "type": "Feature",
  "properties": {
    "addr:full":"5164 Mill Branch Rd Grovetown GA 30813",
    "addr:housenumber":"5164",
    "addr:postcode":"30813",
    "addr:street":"Mill Branch Rd",
    "iso:country":"US",
    "sg:address":"5164 Mill Branch Rd",
    "sg:city":"Grovetown",
    "sg:classifiers":[
        {
            "category":"Autos & Motor Vehicles",
            "subcategory":"Automobile Sales",
            "type":"Retail Goods"
        }
    ],
    "sg:phone":"+1 706 855 6178",
    "sg:postcode":"30813",
    "sg:province":"GA",
    "sg:tags":[
        "used"
    ],
    "wof:name":"Columbia County Auto Sales",
    "wof:placetype":"venue"
},
  "geometry": {"coordinates":[-82.202961,33.50188],"type":"Point"}
}