{
  "type": "Feature",
  "properties": {
    "addr:full":"598 S Park St Carrollton GA 30117",
    "addr:housenumber":"598",
    "addr:postcode":"30117",
    "addr:street":"S Park St",
    "iso:country":"US",
    "sg:address":"598 S Park St",
    "sg:city":"Carrollton",
    "sg:classifiers":[
        {
            "category":"Real Estate",
            "subcategory":"Real Estate Operator",
            "type":"Services"
        }
    ],
    "sg:phone":"+1 770 832 8432",
    "sg:postcode":"30117",
    "sg:province":"GA",
    "sg:tags":[
        "apartment"
    ],
    "wof:name":"South Park Apartments",
    "wof:placetype":"venue"
},
  "geometry": {"coordinates":[-85.07878100000001,33.572462],"type":"Point"}
}