{
  "type": "Feature",
  "properties": {
    "iso:country":"US",
    "sg:address":"4077 Glenwood Rd",
    "sg:city":"Decatur",
    "sg:classifiers":[
        {
            "category":"Professional",
            "subcategory":"Employment Agencies",
            "type":"Services"
        }
    ],
    "sg:phone":"+1 404 286 8484",
    "sg:postcode":"30032",
    "sg:province":"GA",
    "sg:tags":[
        "opportunity",
        "help",
        "supply"
    ],
    "wof:name":"Worker's Temporary Staffing",
    "wof:placetype":"venue"
},
  "geometry": {"coordinates":[-84.249742,33.737887],"type":"Point"}
}