{
  "type": "Feature",
  "properties": {
    "addr:full":"540 River Rd Mc Donough GA 30252",
    "addr:housenumber":"540",
    "addr:postcode":"30252",
    "addr:street":"River Rd",
    "iso:country":"US",
    "sg:address":"540 River Rd",
    "sg:city":"Mc Donough",
    "sg:classifiers":[
        {
            "category":"Building & Trades",
            "subcategory":"Plumbing",
            "type":"Services"
        }
    ],
    "sg:phone":"+1 770 957 7560",
    "sg:postcode":"30252",
    "sg:province":"GA",
    "sg:tags":[
        "contractor"
    ],
    "wof:name":"Barham Mechanical Services",
    "wof:placetype":"venue"
},
  "geometry": {"coordinates":[-83.997272,33.475682],"type":"Point"}
}