{
  "type": "Feature",
  "properties": {
    "iso:country":"US",
    "sg:address":"117 E Main St",
    "sg:city":"Statesboro",
    "sg:classifiers":[
        {
            "category":"Building & Trades",
            "subcategory":"Construction",
            "type":"Services"
        }
    ],
    "sg:phone":"+1 912 531 0077",
    "sg:postcode":"30458",
    "sg:province":"GA",
    "sg:tags":[
        "home",
        "builder"
    ],
    "wof:name":"Pugliano Construction Co",
    "wof:placetype":"venue"
},
  "geometry": {"coordinates":[-81.77927200000001,32.448804],"type":"Point"}
}