{
  "type": "Feature",
  "properties": {
    "iso:country":"US",
    "sg:address":"5380 Peachtree Blvd",
    "sg:city":"Atlanta",
    "sg:classifiers":[
        {
            "category":"Health Services",
            "subcategory":"Medical Lab",
            "type":"Services"
        }
    ],
    "sg:phone":"+1 770 559 8739",
    "sg:postcode":"30341",
    "sg:province":"GA",
    "sg:tags":[
        "examination",
        "insurance"
    ],
    "wof:name":"Medical Exams Direct Inc",
    "wof:placetype":"venue"
},
  "geometry": {"coordinates":[-84.3013,33.891579],"type":"Point"}
}