{
  "type": "Feature",
  "properties": {
    "addr:full":"5812 Thompson Bridge Rd Murrayville GA 30564",
    "addr:housenumber":"5812",
    "addr:postcode":"30564",
    "addr:street":"Thompson Bridge Rd",
    "iso:country":"US",
    "sg:address":"5812 Thompson Bridge Rd",
    "sg:city":"Murrayville",
    "sg:classifiers":[
        {
            "category":"Shopping",
            "subcategory":"Florist",
            "type":"Retail Goods"
        }
    ],
    "sg:phone":"+1 770 532 8820",
    "sg:postcode":"30564",
    "sg:province":"GA",
    "wof:name":"Max Flower Shop",
    "wof:placetype":"venue"
},
  "geometry": {"coordinates":[-83.916326,34.429051],"type":"Point"}
}