{
  "type": "Feature",
  "properties": {
    "addr:full":"2699 Beaver Creek Xing Powder Springs GA 30127",
    "addr:housenumber":"2699",
    "addr:postcode":"30127",
    "addr:street":"Beaver Creek Xing",
    "iso:country":"US",
    "sg:address":"2699 Beaver Creek Xing",
    "sg:city":"Powder Springs",
    "sg:classifiers":[
        {
            "category":"Sports & Exercise",
            "subcategory":"Gym",
            "type":"Entertainment"
        }
    ],
    "sg:phone":"+1 770 222 1260",
    "sg:postcode":"30127",
    "sg:province":"GA",
    "sg:tags":[
        "fitness",
        "physical",
        "facility"
    ],
    "wof:name":"New Dawn Fitness Management",
    "wof:placetype":"venue"
},
  "geometry": {"coordinates":[-84.64667900000001,33.8869],"type":"Point"}
}