{
  "type": "Feature",
  "properties": {
    "iso:country":"US",
    "sg:address":"410 Millard St",
    "sg:city":"Athens",
    "sg:classifiers":[
        {
            "category":"Professional",
            "subcategory":"Business Services",
            "type":"Services"
        }
    ],
    "sg:phone":"+1 706 255 9384",
    "sg:postcode":"30606",
    "sg:province":"GA",
    "wof:name":"Pagliacci Bros Design & Bldg",
    "wof:placetype":"venue"
},
  "geometry": {"coordinates":[-83.409913,33.9564],"type":"Point"}
}