{
  "type": "Feature",
  "properties": {
    "addr:full":"6100 Lake Forrest Dr NW Atlanta GA 30328",
    "addr:housenumber":"6100",
    "addr:postcode":"30328",
    "addr:street":"Lake Forrest Dr Nw",
    "iso:country":"US",
    "sg:address":"6100 Lake Forrest Dr NW",
    "sg:city":"Atlanta",
    "sg:classifiers":[
        {
            "category":"Real Estate",
            "subcategory":"Real Estate Agent",
            "type":"Services"
        }
    ],
    "sg:phone":"+1 404 252 9500",
    "sg:postcode":"30328",
    "sg:province":"GA",
    "sg:tags":[
        "brokerage"
    ],
    "sg:website":"www.johnhallmanrealtors.com",
    "wof:name":"John Hallman Realtors Inc",
    "wof:placetype":"venue"
},
  "geometry": {"coordinates":[-84.387108,33.921004],"type":"Point"}
}