{
  "type": "Feature",
  "properties": {
    "addr:full":"609 E Gaines St Dublin GA 31021",
    "addr:housenumber":"609",
    "addr:postcode":"31021",
    "addr:street":"E Gaines St",
    "iso:country":"US",
    "sg:address":"609 E Gaines St",
    "sg:city":"Dublin",
    "sg:classifiers":[
        {
            "category":"Retail",
            "subcategory":"Auto Repair",
            "type":"Services"
        }
    ],
    "sg:phone":"+1 478 272 0929",
    "sg:postcode":"31021",
    "sg:province":"GA",
    "sg:tags":[
        "repairing",
        "automobile"
    ],
    "wof:name":"C & S Automotive Repair",
    "wof:placetype":"venue"
},
  "geometry": {"coordinates":[-82.897492,32.543797],"type":"Point"}
}