{
  "type": "Feature",
  "properties": {
    "iso:country":"US",
    "sg:address":"456 Cobb Pkwy S",
    "sg:city":"Marietta",
    "sg:classifiers":[
        {
            "category":"Retail",
            "subcategory":"Auto Repair",
            "type":"Services"
        }
    ],
    "sg:phone":"+1 770 499 6581",
    "sg:postcode":"30060",
    "sg:province":"GA",
    "sg:tags":[
        "repairing",
        "cylinder"
    ],
    "wof:name":"Automobile Machine Shops",
    "wof:placetype":"venue"
},
  "geometry": {"coordinates":[-84.515631,33.941291],"type":"Point"}
}