{
  "type": "Feature",
  "properties": {
    "addr:full":"720 Powder Springs St Marietta GA 30064",
    "addr:housenumber":"720",
    "addr:postcode":"30064",
    "addr:street":"Powder Springs St",
    "iso:country":"US",
    "sg:address":"720 Powder Springs St",
    "sg:city":"Marietta",
    "sg:classifiers":[
        {
            "category":"Organizations",
            "subcategory":"Religious Organization",
            "type":"Services"
        }
    ],
    "sg:phone":"+1 770 426 7005",
    "sg:postcode":"30064",
    "sg:province":"GA",
    "wof:name":"In the Meantime Ministries",
    "wof:placetype":"venue"
},
  "geometry": {"coordinates":[-84.55734200000001,33.935325],"type":"Point"}
}