{
  "type": "Feature",
  "properties": {
    "iso:country":"US",
    "sg:address":"659 Auburn Ave NE Apt 237",
    "sg:city":"Atlanta",
    "sg:classifiers":[
        {
            "category":"Professional",
            "subcategory":"Art Services",
            "type":"Services"
        }
    ],
    "sg:phone":"+1 770 905 0597",
    "sg:postcode":"30312",
    "sg:province":"GA",
    "sg:tags":[
        "designer",
        "display",
        "producer"
    ],
    "wof:name":"Mo'fresh Designs",
    "wof:placetype":"venue"
},
  "geometry": {"coordinates":[-84.36653099999999,33.75681],"type":"Point"}
}