{
  "type": "Feature",
  "properties": {
    "addr:full":"1911 Memorial Dr Waycross GA 31501",
    "addr:housenumber":"1911",
    "addr:postcode":"31501",
    "addr:street":"Memorial Dr",
    "iso:country":"US",
    "sg:address":"1911 Memorial Dr",
    "sg:city":"Waycross",
    "sg:classifiers":[
        {
            "category":"Retail",
            "subcategory":"Auto Rental",
            "type":"Services"
        }
    ],
    "sg:phone":"+1 912 338 9797",
    "sg:postcode":"31501",
    "sg:province":"GA",
    "sg:tags":[
        "renting",
        "truck",
        "leasing"
    ],
    "wof:name":"Budget Truck Rental",
    "wof:placetype":"venue"
},
  "geometry": {"coordinates":[-82.334367,31.20408],"type":"Point"}
}