{
  "type": "Feature",
  "properties": {
    "addr:full":"490 Wall St Marietta GA 30068",
    "addr:housenumber":"490",
    "addr:postcode":"30068",
    "addr:street":"Wall St",
    "iso:country":"US",
    "sg:address":"490 Wall St",
    "sg:city":"Marietta",
    "sg:classifiers":[
        {
            "category":"Home & Garden",
            "subcategory":"Home Furnishings",
            "type":"Retail Goods"
        }
    ],
    "sg:phone":"+1 770 509 1214",
    "sg:postcode":"30068",
    "sg:province":"GA",
    "sg:tags":[
        "curtain",
        "made",
        "drapery"
    ],
    "wof:name":"Designs In Draperies",
    "wof:placetype":"venue"
},
  "geometry": {"coordinates":[-84.46664,33.962885],"type":"Point"}
}