{
  "type": "Feature",
  "properties": {
    "addr:full":"4414 US Hwy 441 N Alto GA 30510",
    "addr:housenumber":"4414",
    "addr:postcode":"30510",
    "addr:street":"Us Hwy 441 N Alto",
    "iso:country":"US",
    "sg:address":"4414 US Hwy 441 N",
    "sg:city":"Alto",
    "sg:classifiers":[
        {
            "category":"Freight",
            "type":"Transportation"
        }
    ],
    "sg:phone":"+1 706 499 6019",
    "sg:postcode":"30510",
    "sg:province":"GA",
    "sg:tags":[
        "waste"
    ],
    "wof:name":"Ducks Roll Off Inc",
    "wof:placetype":"venue"
},
  "geometry": {"coordinates":[-83.511696,34.421099],"type":"Point"}
}