{
  "type": "Feature",
  "properties": {
    "iso:country":"US",
    "sg:address":"1590 Macedonia Rd",
    "sg:city":"Newnan",
    "sg:classifiers":[
        {
            "category":"Social Services",
            "subcategory":"Child Care",
            "type":"Services"
        }
    ],
    "sg:phone":"+1 770 683 4811",
    "sg:postcode":"30263",
    "sg:province":"GA",
    "wof:name":"Heavenly Laughter Daycare Ctr",
    "wof:placetype":"venue"
},
  "geometry": {"coordinates":[-84.818,33.443884],"type":"Point"}
}