{
  "type": "Feature",
  "properties": {
    "iso:country":"US",
    "sg:address":"620 Frances Ln",
    "sg:city":"Brooklet",
    "sg:classifiers":[
        {
            "category":"Health Services",
            "subcategory":"Nursing And Care Facility",
            "type":"Services"
        },
        {
            "category":"Health Services",
            "subcategory":"Health Practitioner",
            "type":"Services"
        }
    ],
    "sg:phone":"+1 912 552 3341",
    "sg:postcode":"30415",
    "sg:province":"GA",
    "sg:tags":[
        "home",
        "eldercare-home"
    ],
    "wof:name":"Statesboro Home Care",
    "wof:placetype":"venue"
},
  "geometry": {"coordinates":[-81.741124,32.373059],"type":"Point"}
}