{
  "type": "Feature",
  "properties": {
    "addr:full":"12 Oak Walk Villa Rica GA 30180",
    "addr:housenumber":"12",
    "addr:postcode":"30180",
    "addr:street":"Oak Walk",
    "iso:country":"US",
    "sg:address":"12 Oak Walk",
    "sg:city":"Villa Rica",
    "sg:classifiers":[
        {
            "category":"Communications",
            "subcategory":"Film & Video Production",
            "type":"Services"
        }
    ],
    "sg:phone":"+1 770 459 0512",
    "sg:postcode":"30180",
    "sg:province":"GA",
    "sg:tags":[
        "motion"
    ],
    "wof:name":"In Focus Productions",
    "wof:placetype":"venue"
},
  "geometry": {"coordinates":[-84.957688,33.715394],"type":"Point"}
}