{
  "type": "Feature",
  "properties": {
    "iso:country":"US",
    "sg:address":"101 N Franklin St",
    "sg:city":"Dublin",
    "sg:classifiers":[
        {
            "category":"Real Estate",
            "subcategory":"Real Estate Agent",
            "type":"Services"
        }
    ],
    "sg:phone":"+1 478 275 8719",
    "sg:postcode":"31021",
    "sg:province":"GA",
    "wof:name":"Fickling & Company Real Estate",
    "wof:placetype":"venue"
},
  "geometry": {"coordinates":[-82.903279,32.540878],"type":"Point"}
}