{
  "type": "Feature",
  "properties": {
    "addr:full":"659 Auburn Ave NE Atlanta GA 30312",
    "addr:housenumber":"659",
    "addr:postcode":"30312",
    "addr:street":"Auburn Ave Ne",
    "iso:country":"US",
    "sg:address":"659 Auburn Ave NE",
    "sg:city":"Atlanta",
    "sg:classifiers":[
        {
            "category":"Arts & Performance",
            "subcategory":"Art Gallery",
            "type":"Entertainment"
        },
        {
            "category":"Shopping",
            "subcategory":"Crafts & Fabrics",
            "type":"Retail Goods"
        }
    ],
    "sg:phone":"+1 404 584 0305",
    "sg:postcode":"30312",
    "sg:province":"GA",
    "sg:website":"www.jankestudios.com",
    "wof:name":"Janke Studios",
    "wof:placetype":"venue"
},
  "geometry": {"coordinates":[-84.366061,33.756048],"type":"Point"}
}