{
  "type": "Feature",
  "properties": {
    "iso:country":"US",
    "sg:address":"120 N Lee St",
    "sg:city":"Americus",
    "sg:classifiers":[
        {
            "category":"Restaurant",
            "type":"Food & Drink"
        }
    ],
    "sg:phone":"+1 229 924 2999",
    "sg:postcode":"31709",
    "sg:province":"GA",
    "wof:name":"Gavino's",
    "wof:placetype":"venue"
},
  "geometry": {"coordinates":[-84.232564,32.072851],"type":"Point"}
}