{
  "type": "Feature",
  "properties": {
    "addr:full":"9120 Whitfield Ave Savannah GA 31406",
    "addr:housenumber":"9120",
    "addr:postcode":"31406",
    "addr:street":"Whitfield Ave",
    "iso:country":"US",
    "sg:address":"9120 Whitfield Ave",
    "sg:city":"Savannah",
    "sg:classifiers":[
        {
            "category":"Organizations",
            "subcategory":"Religious Organization",
            "type":"Services"
        }
    ],
    "sg:phone":"+1 912 355 1505",
    "sg:postcode":"31406",
    "sg:province":"GA",
    "sg:tags":[
        "child",
        "day",
        "care"
    ],
    "wof:name":"Cresthill Bptst Pr-Kndergarten",
    "wof:placetype":"venue"
},
  "geometry": {"coordinates":[-81.105701,31.976375],"type":"Point"}
}