{
  "type": "Feature",
  "properties": {
    "iso:country":"US",
    "sg:address":"93 Stephens Dr",
    "sg:city":"Jesup",
    "sg:classifiers":[
        {
            "category":"Freight",
            "type":"Transportation"
        }
    ],
    "sg:phone":"+1 912 530 9803",
    "sg:postcode":"31545",
    "sg:province":"GA",
    "sg:tags":[
        "operator",
        "local",
        "trucking"
    ],
    "wof:name":"Stephens Trucking",
    "wof:placetype":"venue"
},
  "geometry": {"coordinates":[-81.849188,31.638788],"type":"Point"}
}