{
  "type": "Feature",
  "properties": {
    "iso:country":"US",
    "sg:address":"110 Peachtree Way NE",
    "sg:city":"Atlanta",
    "sg:classifiers":[
        {
            "category":"Professional",
            "subcategory":"Lawyer & Legal Services",
            "type":"Services"
        }
    ],
    "sg:phone":"+1 404 815 6360",
    "sg:postcode":"30305",
    "sg:province":"GA",
    "wof:name":"Lurey Al Atty",
    "wof:placetype":"venue"
},
  "geometry": {"coordinates":[-84.38400300000001,33.827301],"type":"Point"}
}