{
  "type": "Feature",
  "properties": {
    "addr:full":"1204 Wellspring Way SE Conyers GA 30094",
    "addr:housenumber":"1204",
    "addr:postcode":"30094",
    "addr:street":"Wellspring Way Se",
    "iso:country":"US",
    "sg:address":"1204 Wellspring Way SE",
    "sg:city":"Conyers",
    "sg:classifiers":[
        {
            "category":"Building & Trades",
            "subcategory":"Construction",
            "type":"Services"
        }
    ],
    "sg:phone":"+1 678 413 1808",
    "sg:postcode":"30094",
    "sg:province":"GA",
    "sg:tags":[
        "house"
    ],
    "wof:name":"M & S Construction",
    "wof:placetype":"venue"
},
  "geometry": {"coordinates":[-84.039841,33.569185],"type":"Point"}
}