{
  "type": "Feature",
  "properties": {
    "addr:full":"313 Boulevard SE Atlanta GA 30312",
    "addr:housenumber":"313",
    "addr:postcode":"30312",
    "addr:street":"Boulevard Se",
    "iso:country":"US",
    "sg:address":"313 Boulevard SE",
    "sg:city":"Atlanta",
    "sg:classifiers":[
        {
            "category":"Restaurant",
            "type":"Food & Drink"
        }
    ],
    "sg:menulink":"http://www.allmenus.com/ga/atlanta/42071-just-loafn/menu/",
    "sg:phone":"+1 404 525 4001",
    "sg:postcode":"30312",
    "sg:province":"GA",
    "sg:tags":[
        "seafood",
        "american"
    ],
    "wof:name":"Just Loaf'N",
    "wof:placetype":"venue"
},
  "geometry": {"coordinates":[-84.368083,33.745853],"type":"Point"}
}