{
  "type": "Feature",
  "properties": {
    "addr:full":"175 Inverness Approach Roswell GA 30075",
    "addr:housenumber":"175",
    "addr:postcode":"30075",
    "addr:street":"Inverness Approach",
    "iso:country":"US",
    "sg:address":"175 Inverness Approach",
    "sg:city":"Roswell",
    "sg:classifiers":[
        {
            "category":"Professional",
            "subcategory":"Employment Agencies",
            "type":"Services"
        }
    ],
    "sg:phone":"+1 770 552 1559",
    "sg:postcode":"30075",
    "sg:province":"GA",
    "sg:tags":[
        "opportunity"
    ],
    "wof:name":"Career Spa",
    "wof:placetype":"venue"
},
  "geometry": {"coordinates":[-84.38027200000001,34.00734],"type":"Point"}
}