{
  "type": "Feature",
  "properties": {
    "iso:country":"US",
    "sg:address":"102 Spring Ln",
    "sg:city":"Mt Vernon",
    "sg:classifiers":[
        {
            "category":"Food & Beverages",
            "subcategory":"Groceries & Convenience Stores",
            "type":"Retail Goods"
        }
    ],
    "sg:phone":"+1 912 583 2011",
    "sg:postcode":"30445",
    "sg:province":"GA",
    "wof:name":"T Byrd's Foods Inc",
    "wof:placetype":"venue"
},
  "geometry": {"coordinates":[-82.587864,32.181547],"type":"Point"}
}