{
  "type": "Feature",
  "properties": {
    "iso:country":"US",
    "sg:address":"1815 High Ridge Dr SW",
    "sg:city":"Conyers",
    "sg:classifiers":[
        {
            "category":"Manufacturing",
            "subcategory":"Building Materials",
            "type":"Manufacturing & Wholesale Goods"
        }
    ],
    "sg:phone":"+1 770 929 8442",
    "sg:postcode":"30094",
    "sg:province":"GA",
    "sg:tags":[
        "mfg"
    ],
    "wof:name":"Simplicity Woodworking",
    "wof:placetype":"venue"
},
  "geometry": {"coordinates":[-84.047534,33.591042],"type":"Point"}
}