{
  "type": "Feature",
  "properties": {
    "iso:country":"US",
    "sg:address":"3 Logwood Ln",
    "sg:city":"Newnan",
    "sg:classifiers":[
        {
            "category":"Building & Trades",
            "subcategory":"Construction",
            "type":"Services"
        }
    ],
    "sg:phone":"+1 770 253 0058",
    "sg:postcode":"30265",
    "sg:province":"GA",
    "sg:tags":[
        "house"
    ],
    "wof:name":"Zackerys Homes",
    "wof:placetype":"venue"
},
  "geometry": {"coordinates":[-84.730805,33.388612],"type":"Point"}
}