{
  "type": "Feature",
  "properties": {
    "iso:country":"US",
    "sg:address":"3910 Mountain Way Cove",
    "sg:city":"Snellville",
    "sg:classifiers":[
        {
            "category":"Professional",
            "type":"Services"
        }
    ],
    "sg:phone":"+1 404 218 0948",
    "sg:postcode":"30039",
    "sg:province":"GA",
    "sg:tags":[
        "consulting"
    ],
    "wof:name":"McM Consulting Svc LLC",
    "wof:placetype":"venue"
},
  "geometry": {"coordinates":[-84.057407,33.785543],"type":"Point"}
}