{
  "type": "Feature",
  "properties": {
    "addr:full":"474 Bennett Xing Odum GA 31545",
    "addr:housenumber":"474",
    "addr:postcode":"31545",
    "addr:street":"Bennett Xing",
    "iso:country":"US",
    "sg:address":"474 Bennett Xing",
    "sg:city":"Odum",
    "sg:classifiers":[
        {
            "category":"Retail",
            "subcategory":"Auto Repair",
            "type":"Services"
        }
    ],
    "sg:phone":"+1 912 586 2278",
    "sg:postcode":"31545",
    "sg:province":"GA",
    "sg:tags":[
        "general"
    ],
    "wof:name":"Jesup Auto Works",
    "wof:placetype":"venue"
},
  "geometry": {"coordinates":[-81.98673700000001,31.628496],"type":"Point"}
}