{
  "type": "Feature",
  "properties": {
    "addr:full":"612 Pickard Rd Thomaston GA 30286",
    "addr:housenumber":"612",
    "addr:postcode":"30286",
    "addr:street":"Pickard Rd",
    "iso:country":"US",
    "sg:address":"612 Pickard Rd",
    "sg:city":"Thomaston",
    "sg:classifiers":[
        {
            "category":"Recreation",
            "type":"Entertainment"
        }
    ],
    "sg:phone":"+1 706 647 3618",
    "sg:postcode":"30286",
    "sg:province":"GA",
    "sg:tags":[
        "club",
        "membership"
    ],
    "wof:name":"Khirah Club Inc",
    "wof:placetype":"venue"
},
  "geometry": {"coordinates":[-84.40313500000001,32.90851],"type":"Point"}
}