{
  "type": "Feature",
  "properties": {
    "iso:country":"US",
    "sg:address":"5467 Bells Ferry Rd",
    "sg:city":"Acworth",
    "sg:classifiers":[
        {
            "category":"Building & Trades",
            "subcategory":"Construction",
            "type":"Services"
        }
    ],
    "sg:phone":"+1 678 494 8728",
    "sg:postcode":"30102",
    "sg:province":"GA",
    "sg:tags":[
        "contractor"
    ],
    "sg:website":"www.mccluredesign.net",
    "wof:name":"McClure Design & Build Contractors Llc",
    "wof:placetype":"venue"
},
  "geometry": {"coordinates":[-84.57440200000001,34.0769],"type":"Point"}
}