{
  "type": "Feature",
  "properties": {
    "iso:country":"US",
    "sg:address":"4545 Stone Mountain Hwy",
    "sg:city":"Lilburn",
    "sg:classifiers":[
        {
            "category":"Building & Trades",
            "subcategory":"Construction",
            "type":"Services"
        }
    ],
    "sg:phone":"+1 770 972 6671",
    "sg:postcode":"30047",
    "sg:province":"GA",
    "sg:tags":[
        "contractor"
    ],
    "sg:website":"www.arentalteam.com",
    "wof:name":"Gwinnett Rental Center",
    "wof:placetype":"venue"
},
  "geometry": {"coordinates":[-84.088413,33.832603],"type":"Point"}
}