{
  "type": "Feature",
  "properties": {
    "iso:country":"US",
    "sg:address":"1000 Mallory St",
    "sg:city":"Saint Simons Island",
    "sg:classifiers":[
        {
            "category":"Professional",
            "type":"Services"
        }
    ],
    "sg:phone":"+1 912 638 2032",
    "sg:postcode":"31522",
    "sg:province":"GA",
    "wof:name":"Erika Gamble",
    "wof:placetype":"venue"
},
  "geometry": {"coordinates":[-81.39154499999999,31.144601],"type":"Point"}
}