{
  "type": "Feature",
  "properties": {
    "addr:full":"10385 Hwy 278 E Covington GA 30014",
    "addr:housenumber":"10385",
    "addr:postcode":"30014",
    "addr:street":"Hwy 278 E",
    "iso:country":"US",
    "sg:address":"10385 Hwy 278 E",
    "sg:city":"Covington",
    "sg:classifiers":[
        {
            "category":"Health Services",
            "subcategory":"Clinic",
            "type":"Services"
        }
    ],
    "sg:phone":"+1 770 784 9777",
    "sg:postcode":"30014",
    "sg:province":"GA",
    "sg:tags":[
        "specialty",
        "animal",
        "outpatient"
    ],
    "wof:name":"Falconwood Vaulters",
    "wof:placetype":"venue"
},
  "geometry": {"coordinates":[-83.822868,33.596037],"type":"Point"}
}