{
  "type": "Feature",
  "properties": {
    "iso:country":"US",
    "sg:address":"5095 Buford Hwy NE",
    "sg:city":"Atlanta",
    "sg:classifiers":[
        {
            "category":"Restaurant",
            "type":"Food & Drink"
        },
        {
            "category":"Retail",
            "subcategory":"Auto Rental",
            "type":"Services"
        },
        {
            "category":"Shopping",
            "subcategory":"Pawn Shop",
            "type":"Retail Goods"
        }
    ],
    "sg:phone":"+1 770 455 4200",
    "sg:postcode":"30340",
    "sg:province":"GA",
    "sg:tags":[
        "car"
    ],
    "wof:name":"Cafe Thuy Nga",
    "wof:placetype":"venue"
},
  "geometry": {"coordinates":[-84.28508600000001,33.891268],"type":"Point"}
}