{
  "type": "Feature",
  "properties": {
    "addr:full":"2911 Pendleton Ln SW Marietta GA 30064",
    "addr:housenumber":"2911",
    "addr:postcode":"30064",
    "addr:street":"Pendleton Ln Sw",
    "iso:country":"US",
    "sg:address":"2911 Pendleton Ln SW",
    "sg:city":"Marietta",
    "sg:classifiers":[
        {
            "category":"Home & Garden",
            "subcategory":"Furniture",
            "type":"Retail Goods"
        }
    ],
    "sg:phone":"+1 770 795 8160",
    "sg:postcode":"30064",
    "sg:province":"GA",
    "wof:name":"John Haverty III",
    "wof:placetype":"venue"
},
  "geometry": {"coordinates":[-84.639956,33.907931],"type":"Point"}
}