{
  "type": "Feature",
  "properties": {
    "iso:country":"US",
    "sg:address":"3750 Shallowford Rd NE",
    "sg:city":"Atlanta",
    "sg:classifiers":[
        {
            "category":"Health Services",
            "subcategory":"Chiropractor",
            "type":"Services"
        },
        {
            "category":"Professional",
            "type":"Services"
        }
    ],
    "sg:phone":"+1 678 205 0211",
    "sg:postcode":"30340",
    "sg:province":"GA",
    "wof:name":"Chamblee Spine Center",
    "wof:placetype":"venue"
},
  "geometry": {"coordinates":[-84.284013,33.89745],"type":"Point"}
}