{
  "type": "Feature",
  "properties": {
    "addr:full":"1641 E Washington Rd East Point GA 30344",
    "addr:housenumber":"1641",
    "addr:postcode":"30344",
    "addr:street":"E Washington Rd",
    "iso:country":"US",
    "sg:address":"1641 E Washington Rd",
    "sg:city":"East Point",
    "sg:classifiers":[
        {
            "category":"Organizations",
            "subcategory":"Community Association",
            "type":"Services"
        }
    ],
    "sg:phone":"+1 404 767 1541",
    "sg:postcode":"30344",
    "sg:province":"GA",
    "sg:tags":[
        "military"
    ],
    "wof:name":"American Legion",
    "wof:placetype":"venue"
},
  "geometry": {"coordinates":[-84.442871,33.675606],"type":"Point"}
}