{
  "type": "Feature",
  "properties": {
    "addr:full":"9738 Main St Woodstock GA 30188",
    "addr:housenumber":"9738",
    "addr:postcode":"30188",
    "addr:street":"Main St",
    "iso:country":"US",
    "sg:address":"9738 Main St",
    "sg:city":"Woodstock",
    "sg:classifiers":[
        {
            "category":"Retail",
            "subcategory":"Laundry & Dry Cleaning",
            "type":"Services"
        }
    ],
    "sg:phone":"+1 770 928 4630",
    "sg:postcode":"30188",
    "sg:province":"GA",
    "wof:name":"Star Alterations",
    "wof:placetype":"venue"
},
  "geometry": {"coordinates":[-84.519329,34.084439],"type":"Point"}
}