{
  "type": "Feature",
  "properties": {
    "addr:full":"3393 Springside Ridge Decatur GA 30034",
    "addr:housenumber":"3393",
    "addr:postcode":"30034",
    "addr:street":"Springside Ridge",
    "iso:country":"US",
    "sg:address":"3393 Springside Ridge",
    "sg:city":"Decatur",
    "sg:classifiers":[
        {
            "category":"Government",
            "subcategory":"Office",
            "type":"Public Place"
        }
    ],
    "sg:phone":"+1 404 286 4940",
    "sg:postcode":"30034",
    "sg:province":"GA",
    "sg:tags":[
        "security",
        "hearing",
        "officer",
        "for",
        "social"
    ],
    "wof:name":"Hearing Officer",
    "wof:placetype":"venue"
},
  "geometry": {"coordinates":[-84.251088,33.697266],"type":"Point"}
}