{
  "type": "Feature",
  "properties": {
    "iso:country":"US",
    "sg:address":"100 Squire Ln",
    "sg:city":"Fayetteville",
    "sg:classifiers":[
        {
            "category":"Manufacturing",
            "subcategory":"Glass & Minerals",
            "type":"Manufacturing & Wholesale Goods"
        }
    ],
    "sg:phone":"+1 770 460 9089",
    "sg:postcode":"30214",
    "sg:province":"GA",
    "sg:tags":[
        "container"
    ],
    "wof:name":"Owens Illionis",
    "wof:placetype":"venue"
},
  "geometry": {"coordinates":[-84.453622,33.480956],"type":"Point"}
}