{
  "type": "Feature",
  "properties": {
    "addr:full":"7131 Discovery Blvd Mableton GA 30126",
    "addr:housenumber":"7131",
    "addr:postcode":"30126",
    "addr:street":"Discovery Blvd",
    "iso:country":"US",
    "sg:address":"7131 Discovery Blvd",
    "sg:city":"Mableton",
    "sg:classifiers":[
        {
            "category":"Manufacturing",
            "subcategory":"Furniture",
            "type":"Manufacturing & Wholesale Goods"
        }
    ],
    "sg:phone":"+1 770 732 1202",
    "sg:postcode":"30126",
    "sg:province":"GA",
    "sg:tags":[
        "bedding"
    ],
    "wof:name":"Simmons Co",
    "wof:placetype":"venue"
},
  "geometry": {"coordinates":[-84.524894,33.7882],"type":"Point"}
}