{
  "type": "Feature",
  "properties": {
    "addr:full":"7415 Davidson Cir W Stockbridge GA 30281",
    "addr:housenumber":"7415",
    "addr:postcode":"30281",
    "addr:street":"Davidson Cir W",
    "iso:country":"US",
    "sg:address":"7415 Davidson Cir W",
    "sg:city":"Stockbridge",
    "sg:classifiers":[
        {
            "category":"Restaurant",
            "type":"Food & Drink"
        }
    ],
    "sg:menulink":"http://www.allmenus.com/ga/jonesboro/102749-waffle-house/menu/",
    "sg:phone":"+1 770 389 5765",
    "sg:postcode":"30281",
    "sg:province":"GA",
    "sg:tags":[
        "american"
    ],
    "wof:name":"Waffle House",
    "wof:placetype":"venue"
},
  "geometry": {"coordinates":[-84.26667999999999,33.552182],"type":"Point"}
}