{
  "type": "Feature",
  "properties": {
    "iso:country":"US",
    "sg:address":"9 N Gordon St",
    "sg:city":"Statesboro",
    "sg:classifiers":[
        {
            "category":"Retail",
            "subcategory":"Car Wash",
            "type":"Services"
        }
    ],
    "sg:phone":"+1 912 489 3734",
    "sg:postcode":"30458",
    "sg:province":"GA",
    "sg:tags":[
        "automobile",
        "detail",
        "clean"
    ],
    "wof:name":"K & B Auto Detailing",
    "wof:placetype":"venue"
},
  "geometry": {"coordinates":[-81.77437500000001,32.449988],"type":"Point"}
}