{
  "type": "Feature",
  "properties": {
    "iso:country":"US",
    "sg:address":"3029 Lexington Ave",
    "sg:city":"Woodstock",
    "sg:classifiers":[
        {
            "category":"Home & Garden",
            "subcategory":"Building Materials",
            "type":"Retail Goods"
        }
    ],
    "sg:phone":"+1 770 579 4930",
    "sg:postcode":"30189",
    "sg:province":"GA",
    "sg:tags":[
        "glass",
        "window",
        "plate"
    ],
    "wof:name":"Miracle Glass Windshield",
    "wof:placetype":"venue"
},
  "geometry": {"coordinates":[-84.555396,34.100697],"type":"Point"}
}