{
  "type": "Feature",
  "properties": {
    "addr:full":"3121 Villa Rica Hwy Dallas GA 30157",
    "addr:housenumber":"3121",
    "addr:postcode":"30157",
    "addr:street":"Villa Rica Hwy",
    "iso:country":"US",
    "sg:address":"3121 Villa Rica Hwy",
    "sg:city":"Dallas",
    "sg:classifiers":[
        {
            "category":"Food & Beverages",
            "subcategory":"Groceries & Convenience Stores",
            "type":"Retail Goods"
        }
    ],
    "sg:phone":"+1 770 445 1312",
    "sg:postcode":"30157",
    "sg:province":"GA",
    "wof:name":"Buddys",
    "wof:placetype":"venue"
},
  "geometry": {"coordinates":[-84.841674,33.866391],"type":"Point"}
}