{
  "type": "Feature",
  "properties": {
    "addr:full":"245 Duvall Rd Chatsworth GA 30705",
    "addr:housenumber":"245",
    "addr:postcode":"30705",
    "addr:street":"Duvall Rd",
    "iso:country":"US",
    "sg:address":"245 Duvall Rd",
    "sg:city":"Chatsworth",
    "sg:classifiers":[
        {
            "category":"Wholesale",
            "subcategory":"Stationery",
            "type":"Manufacturing & Wholesale Goods"
        }
    ],
    "sg:phone":"+1 706 517 4033",
    "sg:postcode":"30705",
    "sg:province":"GA",
    "sg:tags":[
        "core",
        "tube",
        "paper"
    ],
    "wof:name":"D & W Paper Tube",
    "wof:placetype":"venue"
},
  "geometry": {"coordinates":[-84.793719,34.785858],"type":"Point"}
}