{
  "type": "Feature",
  "properties": {
    "iso:country":"US",
    "sg:address":"120 N Industrial Blvd NE",
    "sg:city":"Calhoun",
    "sg:classifiers":[
        {
            "category":"Freight",
            "type":"Transportation"
        }
    ],
    "sg:phone":"+1 706 629 1592",
    "sg:postcode":"30701",
    "sg:province":"GA",
    "sg:tags":[
        "warehouse",
        "merchandise"
    ],
    "wof:name":"Distribution Services",
    "wof:placetype":"venue"
},
  "geometry": {"coordinates":[-84.930919,34.547216],"type":"Point"}
}