{
  "type": "Feature",
  "properties": {
    "addr:full":"1326 Little Neck Rd Savannah GA 31419",
    "addr:housenumber":"1326",
    "addr:postcode":"31419",
    "addr:street":"Little Neck Rd",
    "iso:country":"US",
    "sg:address":"1326 Little Neck Rd",
    "sg:city":"Savannah",
    "sg:classifiers":[
        {
            "category":"Building & Trades",
            "subcategory":"Landscaping Services",
            "type":"Services"
        }
    ],
    "sg:phone":"+1 912 898 3677",
    "sg:postcode":"31419",
    "sg:province":"GA",
    "sg:tags":[
        "landscape",
        "contractor"
    ],
    "wof:name":"Huttons Landscapes Inc",
    "wof:placetype":"venue"
},
  "geometry": {"coordinates":[-81.278199,32.041264],"type":"Point"}
}