{
  "type": "Feature",
  "properties": {
    "addr:full":"1886 Wellbourne Dr NE Atlanta GA 30324",
    "addr:housenumber":"1886",
    "addr:postcode":"30324",
    "addr:street":"Wellbourne Dr Ne",
    "iso:country":"US",
    "sg:address":"1886 Wellbourne Dr NE",
    "sg:city":"Atlanta",
    "sg:classifiers":[
        {
            "category":"Professional",
            "subcategory":"Management & Consulting",
            "type":"Services"
        }
    ],
    "sg:phone":"+1 404 875 7657",
    "sg:postcode":"30324",
    "sg:province":"GA",
    "wof:name":"M Bruce Davidson",
    "wof:placetype":"venue"
},
  "geometry": {"coordinates":[-84.360162,33.803804],"type":"Point"}
}