{
  "type": "Feature",
  "properties": {
    "addr:full":"2900 N Oak St Valdosta GA 31602",
    "addr:housenumber":"2900",
    "addr:postcode":"31602",
    "addr:street":"N Oak St",
    "iso:country":"US",
    "sg:address":"2900 N Oak St",
    "sg:city":"Valdosta",
    "sg:classifiers":[
        {
            "category":"Health Services",
            "subcategory":"Doctor",
            "type":"Services"
        }
    ],
    "sg:phone":"+1 229 245 0447",
    "sg:postcode":"31602",
    "sg:province":"GA",
    "sg:tags":[
        "physician",
        "surgeon"
    ],
    "wof:name":"Pathology Associates-Valdosta",
    "wof:placetype":"venue"
},
  "geometry": {"coordinates":[-83.292073,30.872459],"type":"Point"}
}