{
  "type": "Feature",
  "properties": {
    "addr:full":"2825 Buford Hwy Duluth GA 30096",
    "addr:housenumber":"2825",
    "addr:postcode":"30096",
    "addr:street":"Buford Hwy",
    "iso:country":"US",
    "sg:address":"2825 Buford Hwy",
    "sg:city":"Duluth",
    "sg:classifiers":[
        {
            "category":"Sports & Exercise",
            "subcategory":"Race Track",
            "type":"Entertainment"
        },
        {
            "category":"Manufacturing",
            "subcategory":"Motor Vehicles & Parts",
            "type":"Manufacturing & Wholesale Goods"
        }
    ],
    "sg:phone":"+1 770 558 6998",
    "sg:postcode":"30096",
    "sg:province":"GA",
    "sg:tags":[
        "body",
        "equipment",
        "supply",
        "mfg"
    ],
    "wof:name":"Formula World Racing Inc",
    "wof:placetype":"venue"
},
  "geometry": {"coordinates":[-84.135273,34.006462],"type":"Point"}
}