{
  "type": "Feature",
  "properties": {
    "addr:full":"228 Main St Cedartown GA 30125",
    "addr:housenumber":"228",
    "addr:postcode":"30125",
    "addr:street":"Main St",
    "iso:country":"US",
    "sg:address":"228 Main St",
    "sg:city":"Cedartown",
    "sg:classifiers":[
        {
            "category":"Retail",
            "subcategory":"Driving School",
            "type":"Services"
        }
    ],
    "sg:phone":"+1 770 748 4434",
    "sg:postcode":"30125",
    "sg:province":"GA",
    "sg:tags":[
        "instruction"
    ],
    "sg:website":"http://www.northgeorgiadrivingschools.com",
    "wof:name":"A Plus Driving School",
    "wof:placetype":"venue"
},
  "geometry": {"coordinates":[-85.253292,33.989521],"type":"Point"}
}