{
  "type": "Feature",
  "properties": {
    "iso:country":"US",
    "sg:address":"805 Briars Bend",
    "sg:city":"Alpharetta",
    "sg:classifiers":[
        {
            "category":"Health Services",
            "subcategory":"Doctor",
            "type":"Services"
        }
    ],
    "sg:phone":"+1 770 664 4923",
    "sg:postcode":"30004",
    "sg:province":"GA",
    "sg:tags":[
        "osteopathic"
    ],
    "wof:name":"Zen Do Inc",
    "wof:placetype":"venue"
},
  "geometry": {"coordinates":[-84.318382,34.088106],"type":"Point"}
}