{
  "type": "Feature",
  "properties": {
    "addr:full":"116 Lisa Dr Warner Robins GA 31093",
    "addr:housenumber":"116",
    "addr:postcode":"31093",
    "addr:street":"Lisa Dr",
    "iso:country":"US",
    "sg:address":"116 Lisa Dr",
    "sg:city":"Warner Robins",
    "sg:classifiers":[
        {
            "category":"Real Estate",
            "subcategory":"Real Estate Operator",
            "type":"Services"
        }
    ],
    "sg:phone":"+1 478 922 9998",
    "sg:postcode":"31093",
    "sg:province":"GA",
    "sg:tags":[
        "building",
        "apartment"
    ],
    "wof:name":"Heritage Apartments",
    "wof:placetype":"venue"
},
  "geometry": {"coordinates":[-83.643162,32.628256],"type":"Point"}
}