{
  "type": "Feature",
  "properties": {
    "addr:full":"223 Courtland St NE Ste 300 Atlanta GA 30303",
    "addr:housenumber":"223",
    "addr:postcode":"30303",
    "addr:street":"Courtland St Ne Ste 300",
    "iso:country":"US",
    "sg:address":"223 Courtland St NE Ste 300",
    "sg:city":"Atlanta",
    "sg:classifiers":[
        {
            "category":"Government",
            "subcategory":"Office",
            "type":"Public Place"
        }
    ],
    "sg:phone":"+1 404 232 3875",
    "sg:postcode":"30303",
    "sg:province":"GA",
    "sg:tags":[
        "government-state"
    ],
    "wof:name":"Labor Market Information",
    "wof:placetype":"venue"
},
  "geometry": {"coordinates":[-84.384193,33.760492],"type":"Point"}
}