{
  "type": "Feature",
  "properties": {
    "iso:country":"US",
    "sg:address":"4048 Wintercress Pl NE",
    "sg:city":"Marietta",
    "sg:classifiers":[
        {
            "category":"Retail",
            "subcategory":"Portrait Studio",
            "type":"Services"
        }
    ],
    "sg:phone":"+1 770 777 2327",
    "sg:postcode":"30066",
    "sg:province":"GA",
    "sg:tags":[
        "photographer"
    ],
    "wof:name":"Carol Cole Photography",
    "wof:placetype":"venue"
},
  "geometry": {"coordinates":[-84.51092199999999,34.049643],"type":"Point"}
}