{
  "type": "Feature",
  "properties": {
    "addr:full":"1942 Red Rose Lane Loganville GA 30052",
    "addr:housenumber":"1942",
    "addr:postcode":"30052",
    "addr:street":"Red Rose Lane",
    "iso:country":"US",
    "sg:address":"1942 Red Rose Lane",
    "sg:city":"Loganville",
    "sg:classifiers":[
        {
            "category":"Communications",
            "subcategory":"Television Station",
            "type":"Services"
        }
    ],
    "sg:phone":"+1 678 712 4701",
    "sg:postcode":"30052",
    "sg:province":"GA",
    "sg:tags":[
        "satellite",
        "cable"
    ],
    "wof:name":"Dish Loganville- Satellite TV",
    "wof:placetype":"venue"
},
  "geometry": {"coordinates":[-83.970792,33.831622],"type":"Point"}
}