{
  "type": "Feature",
  "properties": {
    "addr:full":"3901 Johnson Ferry Rd Marietta GA 30062",
    "addr:housenumber":"3901",
    "addr:postcode":"30062",
    "addr:street":"Johnson Ferry Rd",
    "iso:country":"US",
    "sg:address":"3901 Johnson Ferry Rd",
    "sg:city":"Marietta",
    "sg:classifiers":[
        {
            "category":"Shopping",
            "subcategory":"Jewelry",
            "type":"Retail Goods"
        }
    ],
    "sg:phone":"+1 770 973 2797",
    "sg:postcode":"30062",
    "sg:province":"GA",
    "wof:name":"Goldmasters Jewelers",
    "wof:placetype":"venue"
},
  "geometry": {"coordinates":[-84.436476,34.009601],"type":"Point"}
}