{
  "type": "Feature",
  "properties": {
    "addr:full":"603 Grant St SE Atlanta GA 30312",
    "addr:housenumber":"603",
    "addr:postcode":"30312",
    "addr:street":"Grant St Se",
    "iso:country":"US",
    "sg:address":"603 Grant St SE",
    "sg:city":"Atlanta",
    "sg:classifiers":[
        {
            "category":"Communications",
            "subcategory":"Radio Station",
            "type":"Services"
        },
        {
            "category":"Professional",
            "subcategory":"Business Services",
            "type":"Services"
        }
    ],
    "sg:phone":"+1 404 627 7001",
    "sg:postcode":"30312",
    "sg:province":"GA",
    "sg:tags":[
        "medium",
        "publicity",
        "broker"
    ],
    "wof:name":"Neil Media Resources Inc",
    "wof:placetype":"venue"
},
  "geometry": {"coordinates":[-84.37637599999999,33.738182],"type":"Point"}
}