{
  "type": "Feature",
  "properties": {
    "iso:country":"US",
    "sg:address":"2745 Marietta Hwy",
    "sg:city":"Canton",
    "sg:classifiers":[
        {
            "category":"Personal",
            "subcategory":"Beauty Salon",
            "type":"Services"
        }
    ],
    "sg:phone":"+1 770 720 7077",
    "sg:postcode":"30114",
    "sg:province":"GA",
    "sg:tags":[
        "hair",
        "stylist"
    ],
    "wof:name":"Hometown Hair",
    "wof:placetype":"venue"
},
  "geometry": {"coordinates":[-84.504662,34.21019],"type":"Point"}
}