{
  "type": "Feature",
  "properties": {
    "addr:full":"3215 Stoney Acres Dr Kennesaw GA 30152",
    "addr:housenumber":"3215",
    "addr:postcode":"30152",
    "addr:street":"Stoney Acres Dr",
    "iso:country":"US",
    "sg:address":"3215 Stoney Acres Dr",
    "sg:city":"Kennesaw",
    "sg:classifiers":[
        {
            "category":"Professional",
            "subcategory":"Management & Consulting",
            "type":"Services"
        }
    ],
    "sg:phone":"+1 770 514 1993",
    "sg:postcode":"30152",
    "sg:province":"GA",
    "sg:tags":[
        "fuel"
    ],
    "wof:name":"Croker Rhyne Capital Mgmt Inc",
    "wof:placetype":"venue"
},
  "geometry": {"coordinates":[-84.64275600000001,33.970746],"type":"Point"}
}