{
  "type": "Feature",
  "properties": {
    "addr:full":"1107 Sycamore Ave Brunswick GA 31520",
    "addr:housenumber":"1107",
    "addr:postcode":"31520",
    "addr:street":"Sycamore Ave",
    "iso:country":"US",
    "sg:address":"1107 Sycamore Ave",
    "sg:city":"Brunswick",
    "sg:classifiers":[
        {
            "category":"Wholesale",
            "subcategory":"Machinery & Supplies",
            "type":"Manufacturing & Wholesale Goods"
        }
    ],
    "sg:phone":"+1 912 262 1181",
    "sg:postcode":"31520",
    "sg:province":"GA",
    "sg:tags":[
        "sell",
        "machine",
        "c"
    ],
    "wof:name":"V-Max Products",
    "wof:placetype":"venue"
},
  "geometry": {"coordinates":[-81.482422,31.148185],"type":"Point"}
}