{
  "type": "Feature",
  "properties": {
    "iso:country":"US",
    "sg:address":"609 Sycamore St",
    "sg:city":"Decatur",
    "sg:classifiers":[
        {
            "category":"Professional",
            "subcategory":"Business Services",
            "type":"Services"
        }
    ],
    "sg:phone":"+1 404 378 9032",
    "sg:postcode":"30030",
    "sg:province":"GA",
    "wof:name":"Becky Lamb Associates Inc",
    "wof:placetype":"venue"
},
  "geometry": {"coordinates":[-84.289401,33.774463],"type":"Point"}
}