{
  "type": "Feature",
  "properties": {
    "addr:full":"15 Lester Rd Odum GA 31555",
    "addr:housenumber":"15",
    "addr:postcode":"31555",
    "addr:street":"Lester Rd",
    "iso:country":"US",
    "sg:address":"15 Lester Rd",
    "sg:city":"Odum",
    "sg:classifiers":[
        {
            "category":"Home & Garden",
            "subcategory":"Furniture",
            "type":"Retail Goods"
        }
    ],
    "sg:phone":"+1 912 586 6114",
    "sg:postcode":"31555",
    "sg:province":"GA",
    "sg:tags":[
        "cabinet"
    ],
    "wof:name":"Dents Cabinet Doors",
    "wof:placetype":"venue"
},
  "geometry": {"coordinates":[-81.999938,31.722378],"type":"Point"}
}