{
  "type": "Feature",
  "properties": {
    "iso:country":"US",
    "sg:address":"1351 Bowens Mill Rd SE",
    "sg:city":"Douglas",
    "sg:classifiers":[
        {
            "category":"Utilities",
            "subcategory":"Telephone",
            "type":"Services"
        }
    ],
    "sg:phone":"+1 912 632 3102",
    "sg:postcode":"31533",
    "sg:province":"GA",
    "sg:tags":[
        "communications"
    ],
    "wof:name":"Access A T C",
    "wof:placetype":"venue"
},
  "geometry": {"coordinates":[-82.83678500000001,31.489069],"type":"Point"}
}