{
  "type": "Feature",
  "properties": {
    "addr:full":"113 W Laurel Trce Jasper GA 30143",
    "addr:housenumber":"113",
    "addr:postcode":"30143",
    "addr:street":"W Laurel Trce",
    "iso:country":"US",
    "sg:address":"113 W Laurel Trce",
    "sg:city":"Jasper",
    "sg:classifiers":[
        {
            "category":"Personal",
            "subcategory":"Hair Removal",
            "type":"Services"
        }
    ],
    "sg:phone":"+1 706 692 0280",
    "sg:postcode":"30143",
    "sg:province":"GA",
    "wof:name":"Gateway Financial Distributors",
    "wof:placetype":"venue"
},
  "geometry": {"coordinates":[-84.408351,34.464932],"type":"Point"}
}