{
  "type": "Feature",
  "properties": {
    "addr:full":"418 Blackland Rd NW Atlanta GA 30342",
    "addr:housenumber":"418",
    "addr:postcode":"30342",
    "addr:street":"Blackland Rd Nw",
    "iso:country":"US",
    "sg:address":"418 Blackland Rd NW",
    "sg:city":"Atlanta",
    "sg:classifiers":[
        {
            "category":"Professional",
            "subcategory":"Business Services",
            "type":"Services"
        }
    ],
    "sg:phone":"+1 404 239 6010",
    "sg:postcode":"30342",
    "sg:province":"GA",
    "wof:name":"Ashcraft Enterprises Inc",
    "wof:placetype":"venue"
},
  "geometry": {"coordinates":[-84.397711,33.859365],"type":"Point"}
}