{
  "type": "Feature",
  "properties": {
    "addr:full":"402 W 6th St Waynesboro GA 30830",
    "addr:housenumber":"402",
    "addr:postcode":"30830",
    "addr:street":"W 6Th St",
    "iso:country":"US",
    "sg:address":"402 W 6th St",
    "sg:city":"Waynesboro",
    "sg:classifiers":[
        {
            "category":"Shopping",
            "subcategory":"Catalog Store",
            "type":"Retail Goods"
        }
    ],
    "sg:phone":"+1 706 554 6166",
    "sg:postcode":"30830",
    "sg:province":"GA",
    "sg:tags":[
        "mail",
        "order"
    ],
    "wof:name":"J C Penney Catalog",
    "wof:placetype":"venue"
},
  "geometry": {"coordinates":[-82.018691,33.088486],"type":"Point"}
}