{
  "type": "Feature",
  "properties": {
    "addr:full":"4989 Peachtree Pkwy Norcross GA 30092",
    "addr:housenumber":"4989",
    "addr:postcode":"30092",
    "addr:street":"Peachtree Pkwy",
    "iso:country":"US",
    "sg:address":"4989 Peachtree Pkwy",
    "sg:city":"Norcross",
    "sg:classifiers":[
        {
            "category":"Professional",
            "subcategory":"Computer Services",
            "type":"Services"
        }
    ],
    "sg:phone":"+1 678 417 9885",
    "sg:postcode":"30092",
    "sg:province":"GA",
    "sg:tags":[
        "repair"
    ],
    "sg:website":"www.gnatwork.com",
    "wof:name":"Gnatwork Networks Inc",
    "wof:placetype":"venue"
},
  "geometry": {"coordinates":[-84.211901,33.986521],"type":"Point"}
}