{
  "type": "Feature",
  "properties": {
    "iso:country":"US",
    "sg:address":"3615 McKown Rd",
    "sg:city":"Douglasville",
    "sg:classifiers":[
        {
            "category":"Freight",
            "type":"Transportation"
        }
    ],
    "sg:phone":"+1 770 949 6845",
    "sg:postcode":"30134",
    "sg:province":"GA",
    "sg:tags":[
        "mover"
    ],
    "wof:name":"A-Absolute Amazing Movers",
    "wof:placetype":"venue"
},
  "geometry": {"coordinates":[-84.692682,33.76543],"type":"Point"}
}