{
  "type": "Feature",
  "properties": {
    "addr:full":"866 Nathan Roberts Rd Gray GA 31032",
    "addr:housenumber":"866",
    "addr:postcode":"31032",
    "addr:street":"Nathan Roberts Rd",
    "iso:country":"US",
    "sg:address":"866 Nathan Roberts Rd",
    "sg:city":"Gray",
    "sg:classifiers":[
        {
            "category":"Building & Trades",
            "subcategory":"Plumbing",
            "type":"Services"
        }
    ],
    "sg:phone":"+1 478 986 4451",
    "sg:postcode":"31032",
    "sg:province":"GA",
    "sg:tags":[
        "contractor"
    ],
    "wof:name":"Parrish Heating & Cooling Co",
    "wof:placetype":"venue"
},
  "geometry": {"coordinates":[-83.458004,32.994198],"type":"Point"}
}