{
  "type": "Feature",
  "properties": {
    "addr:full":"311 Cork Pond Rd Sylvania GA 30467",
    "addr:housenumber":"311",
    "addr:postcode":"30467",
    "addr:street":"Cork Pond Rd",
    "iso:country":"US",
    "sg:address":"311 Cork Pond Rd",
    "sg:city":"Sylvania",
    "sg:classifiers":[
        {
            "category":"Utilities",
            "subcategory":"Electric",
            "type":"Services"
        }
    ],
    "sg:phone":"+1 912 564 5743",
    "sg:postcode":"30467",
    "sg:province":"GA",
    "wof:name":"Southeastern Power Servic",
    "wof:placetype":"venue"
},
  "geometry": {"coordinates":[-81.631643,32.766413],"type":"Point"}
}