{
  "type": "Feature",
  "properties": {
    "addr:full":"4960 Niagara Dr NW Acworth GA 30102",
    "addr:housenumber":"4960",
    "addr:postcode":"30102",
    "addr:street":"Niagara Dr Nw",
    "iso:country":"US",
    "sg:address":"4960 Niagara Dr NW",
    "sg:city":"Acworth",
    "sg:classifiers":[
        {
            "category":"Professional",
            "type":"Services"
        }
    ],
    "sg:phone":"+1 770 975 1950",
    "sg:postcode":"30102",
    "sg:province":"GA",
    "sg:tags":[
        "establishment"
    ],
    "wof:name":"Garrett Venture",
    "wof:placetype":"venue"
},
  "geometry": {"coordinates":[-84.600335,34.07256],"type":"Point"}
}