{
  "type": "Feature",
  "properties": {
    "addr:full":"1588 Lovejoy Rd Hampton GA 30228",
    "addr:housenumber":"1588",
    "addr:postcode":"30228",
    "addr:street":"Lovejoy Rd",
    "iso:country":"US",
    "sg:address":"1588 Lovejoy Rd",
    "sg:city":"Hampton",
    "sg:classifiers":[
        {
            "category":"Education",
            "subcategory":"School",
            "type":"Public Place"
        }
    ],
    "sg:phone":"+1 770 473 2933",
    "sg:postcode":"30228",
    "sg:province":"GA",
    "sg:tags":[
        "middle"
    ],
    "wof:name":"Lovejoy Middle School",
    "wof:placetype":"venue"
},
  "geometry": {"coordinates":[-84.33974600000001,33.441562],"type":"Point"}
}