{
  "type": "Feature",
  "properties": {
    "addr:full":"710 Keller Rd Mount Airy GA 30563",
    "addr:housenumber":"710",
    "addr:postcode":"30563",
    "addr:street":"Keller Rd",
    "iso:country":"US",
    "sg:address":"710 Keller Rd",
    "sg:city":"Mount Airy",
    "sg:classifiers":[
        {
            "category":"Shopping",
            "subcategory":"Clothing, Apparel, & Fashions",
            "type":"Retail Goods"
        }
    ],
    "sg:phone":"+1 706 776 6846",
    "sg:postcode":"30563",
    "sg:province":"GA",
    "wof:name":"Lingerie 4a Deal",
    "wof:placetype":"venue"
},
  "geometry": {"coordinates":[-83.50452799999999,34.525334],"type":"Point"}
}