{
  "type": "Feature",
  "properties": {
    "addr:full":"950 Eastside Dr Marietta GA 30060",
    "addr:housenumber":"950",
    "addr:postcode":"30060",
    "addr:street":"Eastside Dr",
    "iso:country":"US",
    "sg:address":"950 Eastside Dr",
    "sg:city":"Marietta",
    "sg:classifiers":[
        {
            "category":"Retail",
            "subcategory":"Auto Repair",
            "type":"Services"
        }
    ],
    "sg:phone":"+1 770 422 3405",
    "sg:postcode":"30060",
    "sg:province":"GA",
    "sg:tags":[
        "body"
    ],
    "wof:name":"Reno Mobile Home Svc",
    "wof:placetype":"venue"
},
  "geometry": {"coordinates":[-84.548772,33.929155],"type":"Point"}
}