{
  "type": "Feature",
  "properties": {
    "iso:country":"US",
    "sg:address":"580 Indian Springs St",
    "sg:city":"Jackson",
    "sg:classifiers":[
        {
            "category":"Building & Trades",
            "subcategory":"Electrical",
            "type":"Services"
        }
    ],
    "sg:phone":"+1 770 775 2235",
    "sg:postcode":"30233",
    "sg:province":"GA",
    "sg:tags":[
        "electrical",
        "contractor"
    ],
    "wof:name":"Peters Electric",
    "wof:placetype":"venue"
},
  "geometry": {"coordinates":[-83.953391,33.292784],"type":"Point"}
}