{
  "type": "Feature",
  "properties": {
    "iso:country":"US",
    "sg:address":"205 Lakeside Trl",
    "sg:city":"Covington",
    "sg:classifiers":[
        {
            "category":"Shopping",
            "subcategory":"Gifts & Souvenirs",
            "type":"Retail Goods"
        }
    ],
    "sg:phone":"+1 770 787 4148",
    "sg:postcode":"30016",
    "sg:province":"GA",
    "sg:tags":[
        "basket",
        "parcel"
    ],
    "wof:name":"Pumpkin Patch Creations",
    "wof:placetype":"venue"
},
  "geometry": {"coordinates":[-83.962439,33.559932],"type":"Point"}
}