{
  "type": "Feature",
  "properties": {
    "addr:full":"1198 Howell Mill Rd Atlanta GA 30318",
    "addr:housenumber":"1198",
    "addr:postcode":"30318",
    "addr:street":"Howell Mill Rd",
    "iso:country":"US",
    "sg:address":"1198 Howell Mill Rd",
    "sg:city":"Atlanta",
    "sg:classifiers":[
        {
            "category":"Home & Garden",
            "subcategory":"Furniture",
            "type":"Retail Goods"
        }
    ],
    "sg:phone":"+1 404 605 0196",
    "sg:postcode":"30318",
    "sg:province":"GA",
    "sg:tags":[
        "equipment",
        "kitchen",
        "cabinet"
    ],
    "wof:name":"Poliform Atlanta",
    "wof:placetype":"venue"
},
  "geometry": {"coordinates":[-84.411822,33.787008],"type":"Point"}
}