{
  "type": "Feature",
  "properties": {
    "iso:country":"US",
    "sg:address":"223 del Rio Rd",
    "sg:city":"Hephzibah",
    "sg:classifiers":[
        {
            "category":"Building & Trades",
            "subcategory":"Construction",
            "type":"Services"
        }
    ],
    "sg:phone":"+1 706 554 3458",
    "sg:postcode":"30815",
    "sg:province":"GA",
    "sg:tags":[
        "house"
    ],
    "wof:name":"Frenchies Home Repair",
    "wof:placetype":"venue"
},
  "geometry": {"coordinates":[-82.063164,33.220604],"type":"Point"}
}