{
  "type": "Feature",
  "properties": {
    "addr:full":"4322 Granby Way Marietta GA 30062",
    "addr:housenumber":"4322",
    "addr:postcode":"30062",
    "addr:street":"Granby Way",
    "iso:country":"US",
    "sg:address":"4322 Granby Way",
    "sg:city":"Marietta",
    "sg:classifiers":[
        {
            "category":"Professional",
            "subcategory":"Management & Consulting",
            "type":"Services"
        }
    ],
    "sg:phone":"+1 770 552 1054",
    "sg:postcode":"30062",
    "sg:province":"GA",
    "sg:tags":[
        "business"
    ],
    "wof:name":"Public Affairs Consulting Svc",
    "wof:placetype":"venue"
},
  "geometry": {"coordinates":[-84.423614,33.991332],"type":"Point"}
}