{
  "type": "Feature",
  "properties": {
    "addr:full":"1202 Mobley Pond Rd Girard GA 30426",
    "addr:housenumber":"1202",
    "addr:postcode":"30426",
    "addr:street":"Mobley Pond Rd",
    "iso:country":"US",
    "sg:address":"1202 Mobley Pond Rd",
    "sg:city":"Girard",
    "sg:phone":"+1 912 829 4378",
    "sg:postcode":"30426",
    "sg:province":"GA",
    "sg:tags":[
        "farm",
        "field",
        "crop"
    ],
    "wof:name":"Brian E Cain Farm",
    "wof:placetype":"venue"
},
  "geometry": {"coordinates":[-81.545604,32.996816],"type":"Point"}
}