{
  "type": "Feature",
  "properties": {
    "addr:full":"1081 Katherine Ln Greensboro GA 30642",
    "addr:housenumber":"1081",
    "addr:postcode":"30642",
    "addr:street":"Katherine Ln",
    "iso:country":"US",
    "sg:address":"1081 Katherine Ln",
    "sg:city":"Greensboro",
    "sg:classifiers":[
        {
            "category":"Professional",
            "type":"Services"
        }
    ],
    "sg:phone":"+1 706 467 3092",
    "sg:postcode":"30642",
    "sg:province":"GA",
    "wof:name":"Noel David Ltd",
    "wof:placetype":"venue"
},
  "geometry": {"coordinates":[-83.246691,33.439949],"type":"Point"}
}