{
  "type": "Feature",
  "properties": {
    "addr:full":"6414 State Rte 40 Kingsland GA 31548",
    "addr:housenumber":"6414",
    "addr:postcode":"31548",
    "addr:street":"State Rte 40",
    "iso:country":"US",
    "sg:address":"6414 State Rte 40",
    "sg:city":"Kingsland",
    "sg:classifiers":[
        {
            "category":"Autos & Motor Vehicles",
            "subcategory":"Auto Supplies",
            "type":"Retail Goods"
        }
    ],
    "sg:phone":"+1 912 729 5663",
    "sg:postcode":"31548",
    "sg:province":"GA",
    "sg:tags":[
        "automobile",
        "parts"
    ],
    "wof:name":"NAPA Auto Parts",
    "wof:placetype":"venue"
},
  "geometry": {"coordinates":[-81.738508,30.808487],"type":"Point"}
}