{
  "type": "Feature",
  "properties": {
    "iso:country":"US",
    "sg:address":"1013 6th Ave",
    "sg:city":"Albany",
    "sg:classifiers":[
        {
            "category":"Health Services",
            "subcategory":"Chiropractor",
            "type":"Services"
        }
    ],
    "sg:phone":"+1 229 435 7500",
    "sg:postcode":"31701",
    "sg:province":"GA",
    "wof:name":"Joe Greenway DC",
    "wof:placetype":"venue"
},
  "geometry": {"coordinates":[-84.175754,31.594492],"type":"Point"}
}