{
  "type": "Feature",
  "properties": {
    "addr:full":"25 Meadow Way Covington GA 30014",
    "addr:housenumber":"25",
    "addr:postcode":"30014",
    "addr:street":"Meadow Way",
    "iso:country":"US",
    "sg:address":"25 Meadow Way",
    "sg:city":"Covington",
    "sg:classifiers":[
        {
            "category":"Professional",
            "subcategory":"Engineering",
            "type":"Services"
        }
    ],
    "sg:phone":"+1 770 787 1441",
    "sg:postcode":"30014",
    "sg:province":"GA",
    "sg:tags":[
        "engineer"
    ],
    "wof:name":"Industrial Machine Works",
    "wof:placetype":"venue"
},
  "geometry": {"coordinates":[-83.795556,33.595497],"type":"Point"}
}