{
  "type": "Feature",
  "properties": {
    "addr:full":"2974 Grandview Ave NE Atlanta GA 30305",
    "addr:housenumber":"2974",
    "addr:postcode":"30305",
    "addr:street":"Grandview Ave Ne",
    "iso:country":"US",
    "sg:address":"2974 Grandview Ave NE",
    "sg:city":"Atlanta",
    "sg:phone":"+1 404 233 9889",
    "sg:postcode":"30305",
    "sg:province":"GA",
    "sg:website":"http://www.anisbistro.com",
    "wof:name":"Anis Cafe & Bistro",
    "wof:placetype":"venue"
},
  "geometry": {"coordinates":[-84.37633099999999,33.836499],"type":"Point"}
}