{
  "type": "Feature",
  "properties": {
    "addr:full":"357 Commerce Ave Lagrange GA 30241",
    "addr:housenumber":"357",
    "addr:postcode":"30241",
    "addr:street":"Commerce Ave",
    "iso:country":"US",
    "sg:address":"357 Commerce Ave",
    "sg:city":"Lagrange",
    "sg:classifiers":[
        {
            "category":"Personal",
            "subcategory":"Beauty Salon",
            "type":"Services"
        }
    ],
    "sg:phone":"+1 706 882 7827",
    "sg:postcode":"30241",
    "sg:province":"GA",
    "wof:name":"Hair & Co",
    "wof:placetype":"venue"
},
  "geometry": {"coordinates":[-85.015799,33.048132],"type":"Point"}
}