{
  "type": "Feature",
  "properties": {
    "addr:full":"1218 W Spring St Monroe GA 30655",
    "addr:housenumber":"1218",
    "addr:postcode":"30655",
    "addr:street":"W Spring St",
    "iso:country":"US",
    "sg:address":"1218 W Spring St",
    "sg:city":"Monroe",
    "sg:classifiers":[
        {
            "category":"Autos & Motor Vehicles",
            "subcategory":"Auto Supplies",
            "type":"Retail Goods"
        },
        {
            "category":"Wholesale",
            "subcategory":"Electrical",
            "type":"Manufacturing & Wholesale Goods"
        },
        {
            "category":"Wholesale",
            "subcategory":"Auto Parts",
            "type":"Manufacturing & Wholesale Goods"
        }
    ],
    "sg:phone":"+1 770 266 0483",
    "sg:postcode":"30655",
    "sg:province":"GA",
    "sg:tags":[
        "body",
        "battery",
        "automobile",
        "accessory",
        "equipment",
        "truck"
    ],
    "sg:website":"http://www.oreillyauto.com?utm_source=yellowpages&utm_medium=iyp&utm_campaign=2056",
    "wof:name":"O'Reilly Auto Parts",
    "wof:placetype":"venue"
},
  "geometry": {"coordinates":[-83.733351,33.792471],"type":"Point"}
}