{
  "type": "Feature",
  "properties": {
    "addr:full":"150 Starcadia Cir Macon GA 31210",
    "addr:housenumber":"150",
    "addr:postcode":"31210",
    "addr:street":"Starcadia Cir",
    "iso:country":"US",
    "sg:address":"150 Starcadia Cir",
    "sg:city":"Macon",
    "sg:classifiers":[
        {
            "category":"Recreation",
            "type":"Entertainment"
        }
    ],
    "sg:phone":"+1 478 475 9880",
    "sg:postcode":"31210",
    "sg:province":"GA",
    "sg:tags":[
        "course",
        "golf"
    ],
    "sg:website":"www.starcadia.net",
    "wof:name":"Starcadia Entertainment Park",
    "wof:placetype":"venue"
},
  "geometry": {"coordinates":[-83.72504000000001,32.928293],"type":"Point"}
}