{
  "type": "Feature",
  "properties": {
    "iso:country":"US",
    "sg:address":"200 Shoreline Dr",
    "sg:city":"Fayetteville",
    "sg:classifiers":[
        {
            "category":"Building & Trades",
            "subcategory":"Pest Control",
            "type":"Services"
        }
    ],
    "sg:phone":"+1 770 716 1827",
    "sg:postcode":"30215",
    "sg:province":"GA",
    "wof:name":"Bug Enterprises, Inc.",
    "wof:placetype":"venue"
},
  "geometry": {"coordinates":[-84.405674,33.429483],"type":"Point"}
}