{
  "type": "Feature",
  "properties": {
    "iso:country":"US",
    "sg:address":"132 S Main St",
    "sg:city":"Moultrie",
    "sg:classifiers":[
        {
            "category":"Recreation",
            "type":"Entertainment"
        }
    ],
    "sg:phone":"+1 229 985 1949",
    "sg:postcode":"31768",
    "sg:province":"GA",
    "sg:tags":[
        "parlor",
        "billiard"
    ],
    "wof:name":"Moultrie Sports Bar Inc",
    "wof:placetype":"venue"
},
  "geometry": {"coordinates":[-83.788939,31.178647],"type":"Point"}
}