{
  "type": "Feature",
  "properties": {
    "iso:country":"US",
    "sg:address":"6060 Lake Acworth Dr",
    "sg:city":"Acworth",
    "sg:classifiers":[
        {
            "category":"Airline",
            "type":"Transportation"
        }
    ],
    "sg:phone":"+1 770 529 8382",
    "sg:postcode":"30101",
    "sg:province":"GA",
    "sg:tags":[
        "courier",
        "air"
    ],
    "wof:name":"International Bonded Couriers",
    "wof:placetype":"venue"
},
  "geometry": {"coordinates":[-84.659891,34.076914],"type":"Point"}
}