{
  "type": "Feature",
  "properties": {
    "iso:country":"US",
    "sg:address":"1134 Main St",
    "sg:city":"Forest Park",
    "sg:classifiers":[
        {
            "category":"Restaurant",
            "type":"Food & Drink"
        }
    ],
    "sg:phone":"+1 404 361 3644",
    "sg:postcode":"30297",
    "sg:province":"GA",
    "sg:tags":[
        "barbecue"
    ],
    "wof:name":"Frank's Barbecue",
    "wof:placetype":"venue"
},
  "geometry": {"coordinates":[-84.351822,33.618768],"type":"Point"}
}