{
  "type": "Feature",
  "properties": {
    "iso:country":"US",
    "sg:address":"16 Forest Pkwy Bldg F26",
    "sg:city":"Forest Park",
    "sg:classifiers":[
        {
            "category":"Wholesale",
            "subcategory":"Fruits & Vegetables",
            "type":"Manufacturing & Wholesale Goods"
        }
    ],
    "sg:phone":"+1 404 366 5062",
    "sg:postcode":"30297",
    "sg:province":"GA",
    "sg:tags":[
        "veggie"
    ],
    "wof:name":"Georgia Tomato Company Inc",
    "wof:placetype":"venue"
},
  "geometry": {"coordinates":[-84.396117,33.618235],"type":"Point"}
}