{
  "type": "Feature",
  "properties": {
    "iso:country":"US",
    "sg:address":"2250 Parkway Ct",
    "sg:city":"Smyrna",
    "sg:classifiers":[
        {
            "category":"Wholesale",
            "subcategory":"Stationery",
            "type":"Manufacturing & Wholesale Goods"
        }
    ],
    "sg:phone":"+1 770 984 1922",
    "sg:postcode":"30080",
    "sg:province":"GA",
    "sg:tags":[
        "business",
        "form",
        "system"
    ],
    "wof:name":"Micros Business Systems",
    "wof:placetype":"venue"
},
  "geometry": {"coordinates":[-84.52774700000001,33.897324],"type":"Point"}
}