{
  "type": "Feature",
  "properties": {
    "addr:full":"1847 S Cobb Industrial Blvd SE Smyrna GA 30082",
    "addr:housenumber":"1847",
    "addr:postcode":"30082",
    "addr:street":"S Cobb Industrial Blvd Se",
    "iso:country":"US",
    "sg:address":"1847 S Cobb Industrial Blvd SE",
    "sg:city":"Smyrna",
    "sg:classifiers":[
        {
            "category":"Building & Trades",
            "subcategory":"Plumbing",
            "type":"Services"
        }
    ],
    "sg:phone":"+1 770 433 3232",
    "sg:postcode":"30082",
    "sg:province":"GA",
    "sg:tags":[
        "plumber"
    ],
    "wof:name":"Art Plumbing Co",
    "wof:placetype":"venue"
},
  "geometry": {"coordinates":[-84.501498,33.837695],"type":"Point"}
}