{
  "type": "Feature",
  "properties": {
    "addr:full":"600 Chastain Rd NW # 600 Kennesaw GA 30144",
    "addr:housenumber":"600",
    "addr:postcode":"30144",
    "addr:street":"Chastain Rd Nw # 600",
    "iso:country":"US",
    "sg:address":"600 Chastain Rd NW # 600",
    "sg:city":"Kennesaw",
    "sg:classifiers":[
        {
            "category":"Restaurant",
            "type":"Food & Drink"
        }
    ],
    "sg:phone":"+1 770 874 7781",
    "sg:postcode":"30144",
    "sg:province":"GA",
    "sg:tags":[
        "tex-mex"
    ],
    "sg:website":"www.taco-mac.com",
    "wof:name":"Taco Mac",
    "wof:placetype":"venue"
},
  "geometry": {"coordinates":[-84.570346,34.036075],"type":"Point"}
}