{
  "type": "Feature",
  "properties": {
    "iso:country":"US",
    "sg:address":"1327 23rd St",
    "sg:city":"Columbus",
    "sg:classifiers":[
        {
            "category":"Restaurant",
            "type":"Food & Drink"
        }
    ],
    "sg:phone":"+1 706 649 7991",
    "sg:postcode":"31901",
    "sg:province":"GA",
    "sg:tags":[
        "eating"
    ],
    "wof:name":"Twenty Third St Grill",
    "wof:placetype":"venue"
},
  "geometry": {"coordinates":[-84.97353099999999,32.484753],"type":"Point"}
}