{
  "type": "Feature",
  "properties": {
    "iso:country":"US",
    "sg:address":"242 Milledgeville Hwy",
    "sg:city":"Gordon",
    "sg:classifiers":[
        {
            "category":"Health Services",
            "subcategory":"Clinic",
            "type":"Services"
        }
    ],
    "sg:phone":"+1 478 628 6033",
    "sg:postcode":"31031",
    "sg:province":"GA",
    "sg:tags":[
        "welfare"
    ],
    "wof:name":"Classic Wellness",
    "wof:placetype":"venue"
},
  "geometry": {"coordinates":[-83.33329000000001,32.882288],"type":"Point"}
}