{
  "type": "Feature",
  "properties": {
    "iso:country":"US",
    "sg:address":"2280 Salem Rd SE",
    "sg:city":"Conyers",
    "sg:classifiers":[
        {
            "category":"Health Services",
            "subcategory":"Clinic",
            "type":"Services"
        }
    ],
    "sg:phone":"+1 770 860 8860",
    "sg:postcode":"30013",
    "sg:province":"GA",
    "sg:tags":[
        "specialty",
        "outpatient"
    ],
    "wof:name":"Medical Wght Loss Inst Conyers",
    "wof:placetype":"venue"
},
  "geometry": {"coordinates":[-83.97852899999999,33.629992],"type":"Point"}
}