{
  "type": "Feature",
  "properties": {
    "iso:country":"US",
    "sg:address":"2943 Vada Rd",
    "sg:city":"Bainbridge",
    "sg:classifiers":[
        {
            "category":"Food & Beverages",
            "subcategory":"Groceries & Convenience Stores",
            "type":"Retail Goods"
        }
    ],
    "sg:phone":"+1 229 246 6320",
    "sg:postcode":"39817",
    "sg:province":"GA",
    "wof:name":"Scotts Grocery",
    "wof:placetype":"venue"
},
  "geometry": {"coordinates":[-84.51209799999999,30.950813],"type":"Point"}
}