{
  "type": "Feature",
  "properties": {
    "addr:full":"126 Davis Mill Ct Lawrenceville GA 30044",
    "addr:housenumber":"126",
    "addr:postcode":"30044",
    "addr:street":"Davis Mill Ct",
    "iso:country":"US",
    "sg:address":"126 Davis Mill Ct",
    "sg:city":"Lawrenceville",
    "sg:classifiers":[
        {
            "category":"Professional",
            "subcategory":"Business Services",
            "type":"Services"
        }
    ],
    "sg:phone":"+1 770 963 7945",
    "sg:postcode":"30044",
    "sg:province":"GA",
    "wof:name":"Design Group",
    "wof:placetype":"venue"
},
  "geometry": {"coordinates":[-84.03763600000001,33.934677],"type":"Point"}
}