{
  "type": "Feature",
  "properties": {
    "iso:country":"US",
    "sg:address":"160 Bastille Way",
    "sg:city":"Fayetteville",
    "sg:classifiers":[
        {
            "category":"Banks & Credit Unions",
            "subcategory":"Bank",
            "type":"Services"
        }
    ],
    "sg:phone":"+1 770 460 4800",
    "sg:postcode":"30214",
    "sg:province":"GA",
    "sg:tags":[
        "personal",
        "mortgage"
    ],
    "wof:name":"Griffin Financial Services",
    "wof:placetype":"venue"
},
  "geometry": {"coordinates":[-84.483447,33.451304],"type":"Point"}
}