{
  "type": "Feature",
  "properties": {
    "iso:country":"US",
    "sg:address":"1023 McLynn Ave NE",
    "sg:city":"Atlanta",
    "sg:classifiers":[
        {
            "category":"Travel",
            "subcategory":"Travel Agent",
            "type":"Entertainment"
        }
    ],
    "sg:phone":"+1 404 875 1813",
    "sg:postcode":"30306",
    "sg:province":"GA",
    "sg:tags":[
        "agency"
    ],
    "wof:name":"ODowd Travel Inc",
    "wof:placetype":"venue"
},
  "geometry": {"coordinates":[-84.352825,33.788624],"type":"Point"}
}