{
  "type": "Feature",
  "properties": {
    "addr:full":"28 Hamby Rd SE Marietta GA 30067",
    "addr:housenumber":"28",
    "addr:postcode":"30067",
    "addr:street":"Hamby Rd Se",
    "iso:country":"US",
    "sg:address":"28 Hamby Rd SE",
    "sg:city":"Marietta",
    "sg:classifiers":[
        {
            "category":"Building & Trades",
            "subcategory":"Construction",
            "type":"Services"
        }
    ],
    "sg:phone":"+1 678 560 7703",
    "sg:postcode":"30067",
    "sg:province":"GA",
    "sg:tags":[
        "contractor"
    ],
    "wof:name":"Atkinson Interior Contractor's Inc",
    "wof:placetype":"venue"
},
  "geometry": {"coordinates":[-84.50009900000001,33.951199],"type":"Point"}
}