{
  "type": "Feature",
  "properties": {
    "iso:country":"US",
    "sg:address":"3249 Duluth Hwy 120",
    "sg:city":"Duluth",
    "sg:classifiers":[
        {
            "category":"Organizations",
            "subcategory":"Religious Organization",
            "type":"Services"
        }
    ],
    "sg:phone":"+1 770 476 2159",
    "sg:postcode":"30096",
    "sg:province":"GA",
    "sg:tags":[
        "church"
    ],
    "sg:website":"www.duluthcofc.org",
    "wof:name":"Church of Christ At Duluth",
    "wof:placetype":"venue"
},
  "geometry": {"coordinates":[-84.13772899999999,33.996992],"type":"Point"}
}