{
  "type": "Feature",
  "properties": {
    "iso:country":"US",
    "sg:address":"129 Roy Huie Rd",
    "sg:city":"Riverdale",
    "sg:classifiers":[
        {
            "category":"Personal",
            "subcategory":"Beauty Salon",
            "type":"Services"
        }
    ],
    "sg:phone":"+1 770 994 9883",
    "sg:postcode":"30274",
    "sg:province":"GA",
    "sg:tags":[
        "shop"
    ],
    "wof:name":"Hair Solutions",
    "wof:placetype":"venue"
},
  "geometry": {"coordinates":[-84.394289,33.579881],"type":"Point"}
}