{
  "type": "Feature",
  "properties": {
    "addr:full":"21 W Park Sq Marietta GA 30060",
    "addr:housenumber":"21",
    "addr:postcode":"30060",
    "addr:street":"W Park Sq",
    "iso:country":"US",
    "sg:address":"21 W Park Sq",
    "sg:city":"Marietta",
    "sg:classifiers":[
        {
            "category":"Shopping",
            "subcategory":"Clothing, Apparel, & Fashions",
            "type":"Retail Goods"
        }
    ],
    "sg:phone":"+1 678 354 9700",
    "sg:postcode":"30060",
    "sg:province":"GA",
    "sg:tags":[
        "hat"
    ],
    "wof:name":"Noble Antiques & More",
    "wof:placetype":"venue"
},
  "geometry": {"coordinates":[-84.550237,33.952454],"type":"Point"}
}