{
  "type": "Feature",
  "properties": {
    "addr:full":"5444 White Cedar Ter Buford GA 30518",
    "addr:housenumber":"5444",
    "addr:postcode":"30518",
    "addr:street":"White Cedar Ter",
    "iso:country":"US",
    "sg:address":"5444 White Cedar Ter",
    "sg:city":"Buford",
    "sg:classifiers":[
        {
            "category":"Travel",
            "subcategory":"Hotels & Motels",
            "type":"Entertainment"
        }
    ],
    "sg:phone":"+1 770 614 7528",
    "sg:postcode":"30518",
    "sg:province":"GA",
    "sg:tags":[
        "operation"
    ],
    "wof:name":"Marriott",
    "wof:placetype":"venue"
},
  "geometry": {"coordinates":[-84.080906,34.101777],"type":"Point"}
}