{
  "type": "Feature",
  "properties": {
    "addr:full":"40 Technology Pkwy NW Norcross GA 30092",
    "addr:housenumber":"40",
    "addr:postcode":"30092",
    "addr:street":"Technology Pkwy Nw",
    "iso:country":"US",
    "sg:address":"40 Technology Pkwy NW",
    "sg:city":"Norcross",
    "sg:classifiers":[
        {
            "category":"Insurance",
            "subcategory":"Insurance Agent",
            "type":"Services"
        }
    ],
    "sg:phone":"+1 770 662 8753",
    "sg:postcode":"30092",
    "sg:province":"GA",
    "wof:name":"Cincinnati Insurance Co",
    "wof:placetype":"venue"
},
  "geometry": {"coordinates":[-84.217426,33.967848],"type":"Point"}
}