{
  "type": "Feature",
  "properties": {
    "addr:full":"110 Woodberry Pl Fayetteville GA 30215",
    "addr:housenumber":"110",
    "addr:postcode":"30215",
    "addr:street":"Woodberry Pl",
    "iso:country":"US",
    "sg:address":"110 Woodberry Pl",
    "sg:city":"Fayetteville",
    "sg:classifiers":[
        {
            "category":"Professional",
            "subcategory":"Management & Consulting",
            "type":"Services"
        },
        {
            "category":"Banks & Credit Unions",
            "subcategory":"Financial Services",
            "type":"Services"
        }
    ],
    "sg:phone":"+1 678 489 6064",
    "sg:postcode":"30215",
    "sg:province":"GA",
    "sg:tags":[
        "consultant",
        "financing",
        "planning"
    ],
    "wof:name":"Financial Inc",
    "wof:placetype":"venue"
},
  "geometry": {"coordinates":[-84.52816799999999,33.379112],"type":"Point"}
}