{
  "type": "Feature",
  "properties": {
    "addr:full":"600 Holly Dr Albany GA 31705",
    "addr:housenumber":"600",
    "addr:postcode":"31705",
    "addr:street":"Holly Dr",
    "iso:country":"US",
    "sg:address":"600 Holly Dr",
    "sg:city":"Albany",
    "sg:classifiers":[
        {
            "category":"Professional",
            "subcategory":"Printing & Photocopies",
            "type":"Services"
        }
    ],
    "sg:phone":"+1 229 436 5588",
    "sg:postcode":"31705",
    "sg:province":"GA",
    "sg:tags":[
        "photocopying"
    ],
    "wof:name":"Bee Express Delivery Service",
    "wof:placetype":"venue"
},
  "geometry": {"coordinates":[-84.11680200000001,31.529168],"type":"Point"}
}