{
  "type": "Feature",
  "properties": {
    "addr:full":"995 Oakland Cemetery Rd Byromville GA 31007",
    "addr:housenumber":"995",
    "addr:postcode":"31007",
    "addr:street":"Oakland Cemetery Rd",
    "iso:country":"US",
    "sg:address":"995 Oakland Cemetery Rd",
    "sg:city":"Byromville",
    "sg:classifiers":[
        {
            "category":"Building & Trades",
            "subcategory":"Construction",
            "type":"Services"
        }
    ],
    "sg:phone":"+1 478 953 8906",
    "sg:postcode":"31007",
    "sg:province":"GA",
    "sg:tags":[
        "roofing",
        "industrial",
        "contractors-commercial",
        "contractor"
    ],
    "wof:name":"T N T Roofing",
    "wof:placetype":"venue"
},
  "geometry": {"coordinates":[-83.83577099999999,32.274335],"type":"Point"}
}