{
  "type": "Feature",
  "properties": {
    "iso:country":"US",
    "sg:address":"416 Pegg Rd SW",
    "sg:city":"Atlanta",
    "sg:classifiers":[
        {
            "category":"Education",
            "subcategory":"Dance Studio",
            "type":"Public Place"
        }
    ],
    "sg:phone":"+1 404 766 4001",
    "sg:postcode":"30315",
    "sg:province":"GA",
    "wof:name":"Giwayen Mata",
    "wof:placetype":"venue"
},
  "geometry": {"coordinates":[-84.40365300000001,33.689019],"type":"Point"}
}