{
  "type": "Feature",
  "properties": {
    "iso:country":"US",
    "sg:address":"49 Artley Rd",
    "sg:city":"Savannah",
    "sg:classifiers":[
        {
            "category":"Manufacturing",
            "subcategory":"Metals",
            "type":"Manufacturing & Wholesale Goods"
        }
    ],
    "sg:phone":"+1 912 748 7175",
    "sg:postcode":"31408",
    "sg:province":"GA",
    "sg:tags":[
        "steel"
    ],
    "wof:name":"Douglas Brothers Of Georgia",
    "wof:placetype":"venue"
},
  "geometry": {"coordinates":[-81.21682699999999,32.110574],"type":"Point"}
}