{
  "type": "Feature",
  "properties": {
    "iso:country":"US",
    "sg:address":"4437 Columbus Rd",
    "sg:city":"Macon",
    "sg:classifiers":[
        {
            "category":"Food & Beverages",
            "subcategory":"Groceries & Convenience Stores",
            "type":"Retail Goods"
        }
    ],
    "sg:phone":"+1 478 757 1710",
    "sg:postcode":"31206",
    "sg:province":"GA",
    "wof:name":"Food Max 844",
    "wof:placetype":"venue"
},
  "geometry": {"coordinates":[-83.714163,32.825125],"type":"Point"}
}