{
  "type": "Feature",
  "properties": {
    "iso:country":"US",
    "sg:address":"8879 Dallas Acworth Hwy",
    "sg:city":"Dallas",
    "sg:classifiers":[
        {
            "category":"Fast Food",
            "type":"Food & Drink"
        },
        {
            "category":"Restaurant",
            "type":"Food & Drink"
        }
    ],
    "sg:phone":"+1 770 917 9992",
    "sg:postcode":"30101",
    "sg:province":"GA",
    "sg:tags":[
        "burger",
        "american",
        "new"
    ],
    "wof:name":"Denny's Burgers and Grill",
    "wof:placetype":"venue"
},
  "geometry": {"coordinates":[-84.754548,34.012752],"type":"Point"}
}