{
  "type": "Feature",
  "properties": {
    "iso:country":"US",
    "sg:address":"5465 Chamblee Dunwoody Road",
    "sg:city":"Atlanta",
    "sg:classifiers":[
        {
            "category":"Autos & Motor Vehicles",
            "subcategory":"Fuel & Gas Station",
            "type":"Retail Goods"
        }
    ],
    "sg:phone":"+1 770 396 0614",
    "sg:postcode":"30338",
    "sg:province":"GA",
    "sg:website":"www.chevron.com",
    "wof:name":"Dunwoody Chevron",
    "wof:placetype":"venue"
},
  "geometry": {"coordinates":[-84.335401,33.947279],"type":"Point"}
}