{
  "type": "Feature",
  "properties": {
    "iso:country":"US",
    "sg:address":"101 W Broughton St",
    "sg:city":"Savannah",
    "sg:classifiers":[
        {
            "category":"Professional",
            "subcategory":"Business Services",
            "type":"Services"
        }
    ],
    "sg:phone":"+1 912 239 9720",
    "sg:postcode":"31401",
    "sg:province":"GA",
    "wof:name":"M L Mabry Inc",
    "wof:placetype":"venue"
},
  "geometry": {"coordinates":[-81.09417500000001,32.079577],"type":"Point"}
}