{
  "type": "Feature",
  "properties": {
    "addr:full":"18 Thorncrest Dr Ringgold GA 30736",
    "addr:housenumber":"18",
    "addr:postcode":"30736",
    "addr:street":"Thorncrest Dr",
    "iso:country":"US",
    "sg:address":"18 Thorncrest Dr",
    "sg:city":"Ringgold",
    "sg:classifiers":[
        {
            "category":"Fast Food",
            "type":"Food & Drink"
        },
        {
            "category":"Restaurant",
            "type":"Food & Drink"
        }
    ],
    "sg:phone":"+1 706 965 8535",
    "sg:postcode":"30736",
    "sg:province":"GA",
    "sg:tags":[
        "take",
        "buffet",
        "pizza"
    ],
    "sg:website":"http://www.cicispizza.com",
    "wof:name":"CiCi's Pizza",
    "wof:placetype":"venue"
},
  "geometry": {"coordinates":[-85.12374199999999,34.932923],"type":"Point"}
}