{
  "type": "Feature",
  "properties": {
    "addr:full":"1897 Lake Rabun Rd Lakemont GA 30552",
    "addr:housenumber":"1897",
    "addr:postcode":"30552",
    "addr:street":"Lake Rabun Rd",
    "iso:country":"US",
    "sg:address":"1897 Lake Rabun Rd",
    "sg:city":"Lakemont",
    "sg:classifiers":[
        {
            "category":"Retail",
            "subcategory":"Repair Shop",
            "type":"Services"
        }
    ],
    "sg:phone":"+1 706 782 4981",
    "sg:postcode":"30552",
    "sg:province":"GA",
    "sg:tags":[
        "boat"
    ],
    "wof:name":"Lakemont Marine Inc",
    "wof:placetype":"venue"
},
  "geometry": {"coordinates":[-83.440546,34.767728],"type":"Point"}
}