{
  "type": "Feature",
  "properties": {
    "addr:full":"1550 Wrightsboro Rd Augusta GA 30904",
    "addr:housenumber":"1550",
    "addr:postcode":"30904",
    "addr:street":"Wrightsboro Rd",
    "iso:country":"US",
    "sg:address":"1550 Wrightsboro Rd",
    "sg:city":"Augusta",
    "sg:classifiers":[
        {
            "category":"Wholesale",
            "subcategory":"Stationery",
            "type":"Manufacturing & Wholesale Goods"
        }
    ],
    "sg:phone":"+1 706 737 7000",
    "sg:postcode":"30904",
    "sg:province":"GA",
    "sg:tags":[
        "product",
        "paper"
    ],
    "wof:name":"Sweetheart Cup Co",
    "wof:placetype":"venue"
},
  "geometry": {"coordinates":[-81.997828,33.465543],"type":"Point"}
}