{
  "type": "Feature",
  "properties": {
    "iso:country":"US",
    "sg:address":"1020 Woodstock Rd Ste 2110",
    "sg:city":"Roswell",
    "sg:classifiers":[
        {
            "category":"Health Services",
            "subcategory":"Chiropractor",
            "type":"Services"
        }
    ],
    "sg:phone":"+1 770 817 0544",
    "sg:postcode":"30075",
    "sg:province":"GA",
    "sg:website":"www.vitalitawellness.org/",
    "wof:name":"Vitalita Chiropractic & Wellness Center",
    "wof:placetype":"venue"
},
  "geometry": {"coordinates":[-84.39174199999999,34.062343],"type":"Point"}
}