{
  "type": "Feature",
  "properties": {
    "addr:full":"5412 Lake Mayers Rd Baxley GA 31513",
    "addr:housenumber":"5412",
    "addr:postcode":"31513",
    "addr:street":"Lake Mayers Rd",
    "iso:country":"US",
    "sg:address":"5412 Lake Mayers Rd",
    "sg:city":"Baxley",
    "sg:classifiers":[
        {
            "category":"Professional",
            "type":"Services"
        }
    ],
    "sg:phone":"+1 912 367 2874",
    "sg:postcode":"31513",
    "sg:province":"GA",
    "wof:name":"George E Griffin",
    "wof:placetype":"venue"
},
  "geometry": {"coordinates":[-82.474586,31.752193],"type":"Point"}
}