{
  "type": "Feature",
  "properties": {
    "addr:full":"1450 54th St Columbus GA 31904",
    "addr:housenumber":"1450",
    "addr:postcode":"31904",
    "addr:street":"54Th St",
    "iso:country":"US",
    "sg:address":"1450 54th St",
    "sg:city":"Columbus",
    "sg:classifiers":[
        {
            "category":"Manufacturing",
            "subcategory":"Printing",
            "type":"Manufacturing & Wholesale Goods"
        },
        {
            "category":"Professional",
            "subcategory":"Advertising",
            "type":"Services"
        },
        {
            "category":"Professional",
            "subcategory":"Printing & Photocopies",
            "type":"Services"
        },
        {
            "category":"Wholesale",
            "subcategory":"Books, Periodicals, & Newspapers",
            "type":"Manufacturing & Wholesale Goods"
        }
    ],
    "sg:phone":"+1 706 321 3390",
    "sg:postcode":"31904",
    "sg:province":"GA",
    "sg:tags":[
        "directory",
        "publishers-directory",
        "consultant",
        "guide",
        "publisher"
    ],
    "wof:name":"Yellow Book",
    "wof:placetype":"venue"
},
  "geometry": {"coordinates":[-84.967072,32.520679],"type":"Point"}
}