{
  "type": "Feature",
  "properties": {
    "addr:full":"4601 Derby Ln SE Smyrna GA 30082",
    "addr:housenumber":"4601",
    "addr:postcode":"30082",
    "addr:street":"Derby Ln Se",
    "iso:country":"US",
    "sg:address":"4601 Derby Ln SE",
    "sg:city":"Smyrna",
    "sg:classifiers":[
        {
            "category":"Professional",
            "subcategory":"Computer Services",
            "type":"Services"
        }
    ],
    "sg:phone":"+1 678 293 5845",
    "sg:postcode":"30082",
    "sg:province":"GA",
    "sg:tags":[
        "repair"
    ],
    "wof:name":"Tardis Technical Solutions Llc",
    "wof:placetype":"venue"
},
  "geometry": {"coordinates":[-84.53405600000001,33.847702],"type":"Point"}
}