{
  "type": "Feature",
  "properties": {
    "iso:country":"US",
    "sg:address":"8 W Johnston St",
    "sg:city":"Forsyth",
    "sg:classifiers":[
        {
            "category":"Professional",
            "subcategory":"Lawyer & Legal Services",
            "type":"Services"
        }
    ],
    "sg:phone":"+1 478 994 4257",
    "sg:postcode":"31029",
    "sg:province":"GA",
    "wof:name":"Ham and Jenkins Law Office of",
    "wof:placetype":"venue"
},
  "geometry": {"coordinates":[-83.93935399999999,33.035005],"type":"Point"}
}