{
  "type": "Feature",
  "properties": {
    "addr:full":"621 E Main St Thomaston GA 30286",
    "addr:housenumber":"621",
    "addr:postcode":"30286",
    "addr:street":"E Main St",
    "iso:country":"US",
    "sg:address":"621 E Main St",
    "sg:city":"Thomaston",
    "sg:classifiers":[
        {
            "category":"Manufacturing",
            "subcategory":"Printing",
            "type":"Manufacturing & Wholesale Goods"
        }
    ],
    "sg:phone":"+1 706 647 5414",
    "sg:postcode":"30286",
    "sg:province":"GA",
    "sg:tags":[
        "newspaper"
    ],
    "sg:website":"www.thomastontimes.com",
    "wof:name":"Thomaston Times",
    "wof:placetype":"venue"
},
  "geometry": {"coordinates":[-84.31748899999999,32.887994],"type":"Point"}
}