{
  "type": "Feature",
  "properties": {
    "iso:country":"US",
    "sg:address":"437 Creekside Dr",
    "sg:city":"Leesburg",
    "sg:classifiers":[
        {
            "category":"Building & Trades",
            "subcategory":"Electrical",
            "type":"Services"
        }
    ],
    "sg:phone":"+1 229 432 1915",
    "sg:postcode":"31763",
    "sg:province":"GA",
    "sg:tags":[
        "electrical",
        "contractor"
    ],
    "wof:name":"Beamon Electric Co Allen",
    "wof:placetype":"venue"
},
  "geometry": {"coordinates":[-84.18657399999999,31.652086],"type":"Point"}
}