{
  "type": "Feature",
  "properties": {
    "iso:country":"US",
    "sg:address":"742 E Chappel St",
    "sg:city":"Griffin",
    "sg:classifiers":[
        {
            "category":"Professional",
            "type":"Services"
        }
    ],
    "sg:phone":"+1 770 229 2272",
    "sg:postcode":"30223",
    "sg:province":"GA",
    "wof:name":"Raymond Evans",
    "wof:placetype":"venue"
},
  "geometry": {"coordinates":[-84.252893,33.251828],"type":"Point"}
}