{
  "type": "Feature",
  "properties": {
    "iso:country":"US",
    "sg:address":"2757 Wesley Chapel Rd",
    "sg:city":"Decatur",
    "sg:classifiers":[
        {
            "category":"Autos & Motor Vehicles",
            "subcategory":"Automobile Sales",
            "type":"Retail Goods"
        }
    ],
    "sg:phone":"+1 404 421 2465",
    "sg:postcode":"30034",
    "sg:province":"GA",
    "sg:tags":[
        "car",
        "dealer"
    ],
    "wof:name":"Affordable Used Cars",
    "wof:placetype":"venue"
},
  "geometry": {"coordinates":[-84.21860100000001,33.706896],"type":"Point"}
}