{
  "type": "Feature",
  "properties": {
    "iso:country":"US",
    "sg:address":"1100 Baptist Medical Center Dr",
    "sg:city":"Cumming",
    "sg:classifiers":[
        {
            "category":"Shopping",
            "subcategory":"Pharmacy",
            "type":"Retail Goods"
        }
    ],
    "sg:phone":"+1 770 205 0290",
    "sg:postcode":"30041",
    "sg:province":"GA",
    "wof:name":"Lakeside Pharmacy LLC",
    "wof:placetype":"venue"
},
  "geometry": {"coordinates":[-84.136028,34.179154],"type":"Point"}
}