{
  "type": "Feature",
  "properties": {
    "addr:full":"2516 Wrightsboro Rd Augusta GA 30904",
    "addr:housenumber":"2516",
    "addr:postcode":"30904",
    "addr:street":"Wrightsboro Rd",
    "iso:country":"US",
    "sg:address":"2516 Wrightsboro Rd",
    "sg:city":"Augusta",
    "sg:classifiers":[
        {
            "category":"Real Estate",
            "subcategory":"Real Estate Agent",
            "type":"Services"
        }
    ],
    "sg:phone":"+1 706 294 7844",
    "sg:postcode":"30904",
    "sg:province":"GA",
    "wof:name":"Good Sense Realty",
    "wof:placetype":"venue"
},
  "geometry": {"coordinates":[-82.029704,33.468786],"type":"Point"}
}