{
  "type": "Feature",
  "properties": {
    "iso:country":"US",
    "sg:address":"4816 Old Dixie Hwy",
    "sg:city":"Forest Park",
    "sg:classifiers":[
        {
            "category":"Autos & Motor Vehicles",
            "subcategory":"Automobile Sales",
            "type":"Retail Goods"
        }
    ],
    "sg:phone":"+1 404 361 6330",
    "sg:postcode":"30297",
    "sg:province":"GA",
    "sg:tags":[
        "car"
    ],
    "wof:name":"Emmax Auto Sales",
    "wof:placetype":"venue"
},
  "geometry": {"coordinates":[-84.384201,33.623402],"type":"Point"}
}