{
  "type": "Feature",
  "properties": {
    "iso:country":"US",
    "sg:address":"3727 Summitridge Dr",
    "sg:city":"Atlanta",
    "sg:classifiers":[
        {
            "category":"Professional",
            "subcategory":"Management & Consulting",
            "type":"Services"
        }
    ],
    "sg:phone":"+1 770 723 1785",
    "sg:postcode":"30340",
    "sg:province":"GA",
    "sg:tags":[
        "consultant",
        "business"
    ],
    "wof:name":"Lawrence A Wilson & Associates",
    "wof:placetype":"venue"
},
  "geometry": {"coordinates":[-84.23733900000001,33.890856],"type":"Point"}
}