{
  "type": "Feature",
  "properties": {
    "addr:full":"3646 Harry Rd Bristol GA 31518",
    "addr:housenumber":"3646",
    "addr:postcode":"31518",
    "addr:street":"Harry Rd",
    "iso:country":"US",
    "sg:address":"3646 Harry Rd",
    "sg:city":"Bristol",
    "sg:classifiers":[
        {
            "category":"Military Area",
            "subcategory":"Restricted Area",
            "type":"Public Place"
        }
    ],
    "sg:phone":"+1 912 647 1924",
    "sg:postcode":"31518",
    "sg:province":"GA",
    "sg:tags":[
        "navy",
        "good",
        "army"
    ],
    "wof:name":"Charles G Murphy Jr",
    "wof:placetype":"venue"
},
  "geometry": {"coordinates":[-82.237292,31.512862],"type":"Point"}
}