{
  "type": "Feature",
  "properties": {
    "iso:country":"US",
    "sg:address":"102 Augusta Ave",
    "sg:city":"Thomasville",
    "sg:classifiers":[
        {
            "category":"Shopping",
            "type":"Retail Goods"
        }
    ],
    "sg:phone":"+1 229 226 9820",
    "sg:postcode":"31792",
    "sg:province":"GA",
    "sg:tags":[
        "cosmetic",
        "perfume"
    ],
    "wof:name":"Southside Beauty Supply",
    "wof:placetype":"venue"
},
  "geometry": {"coordinates":[-83.986251,30.818575],"type":"Point"}
}