{
  "type": "Feature",
  "properties": {
    "iso:country":"US",
    "sg:address":"10 Dartmouth Ave",
    "sg:city":"Avondale Estates",
    "sg:classifiers":[
        {
            "category":"Professional",
            "subcategory":"Art Services",
            "type":"Services"
        }
    ],
    "sg:phone":"+1 404 296 0672",
    "sg:postcode":"30002",
    "sg:province":"GA",
    "sg:tags":[
        "calligrapher"
    ],
    "wof:name":"Don Connelly & Assoc",
    "wof:placetype":"venue"
},
  "geometry": {"coordinates":[-84.269548,33.772482],"type":"Point"}
}