{
  "type": "Feature",
  "properties": {
    "addr:full":"3709 Lawrenceville Hwy Tucker GA 30084",
    "addr:housenumber":"3709",
    "addr:postcode":"30084",
    "addr:street":"Lawrenceville Hwy",
    "iso:country":"US",
    "sg:address":"3709 Lawrenceville Hwy",
    "sg:city":"Tucker",
    "sg:classifiers":[
        {
            "category":"Retail",
            "subcategory":"Auto Repair",
            "type":"Services"
        }
    ],
    "sg:phone":"+1 770 491 3150",
    "sg:postcode":"30084",
    "sg:province":"GA",
    "sg:tags":[
        "body",
        "repairing",
        "painting",
        "automobile"
    ],
    "wof:name":"Automotion Body Shop",
    "wof:placetype":"venue"
},
  "geometry": {"coordinates":[-84.229033,33.846325],"type":"Point"}
}