{
  "type": "Feature",
  "properties": {
    "addr:full":"729 Smithstone Ct SE Marietta GA 30067",
    "addr:housenumber":"729",
    "addr:postcode":"30067",
    "addr:street":"Smithstone Ct Se",
    "iso:country":"US",
    "sg:address":"729 Smithstone Ct SE",
    "sg:city":"Marietta",
    "sg:classifiers":[
        {
            "category":"Utilities",
            "subcategory":"Cable",
            "type":"Services"
        }
    ],
    "sg:phone":"+1 770 973 1181",
    "sg:postcode":"30067",
    "sg:province":"GA",
    "sg:tags":[
        "cable-non-electric",
        "wire"
    ],
    "wof:name":"Werling Contracting Co",
    "wof:placetype":"venue"
},
  "geometry": {"coordinates":[-84.476578,33.934367],"type":"Point"}
}