{
  "type": "Feature",
  "properties": {
    "iso:country":"US",
    "sg:address":"980 Concord Rd SE",
    "sg:city":"Smyrna",
    "sg:classifiers":[
        {
            "category":"Banks & Credit Unions",
            "subcategory":"Financial Services",
            "type":"Services"
        }
    ],
    "sg:phone":"+1 678 766 8889",
    "sg:postcode":"30080",
    "sg:province":"GA",
    "sg:tags":[
        "broker",
        "mortgage"
    ],
    "wof:name":"Platinum Capital Group",
    "wof:placetype":"venue"
},
  "geometry": {"coordinates":[-84.5252,33.875999],"type":"Point"}
}