{
  "type": "Feature",
  "properties": {
    "addr:full":"350 Lenox Way NE Atlanta GA 30324",
    "addr:housenumber":"350",
    "addr:postcode":"30324",
    "addr:street":"Lenox Way Ne",
    "iso:country":"US",
    "sg:address":"350 Lenox Way NE",
    "sg:city":"Atlanta",
    "sg:classifiers":[
        {
            "category":"Professional",
            "subcategory":"Lawyer & Legal Services",
            "type":"Services"
        }
    ],
    "sg:phone":"+1 404 926 4500",
    "sg:postcode":"30324",
    "sg:province":"GA",
    "wof:name":"Weissman Nowack Curry & Wilco PC",
    "wof:placetype":"venue"
},
  "geometry": {"coordinates":[-84.356697,33.834999],"type":"Point"}
}