{
  "type": "Feature",
  "properties": {
    "addr:full":"966 Eisenhower Rd SE Atlanta GA 30354",
    "addr:housenumber":"966",
    "addr:postcode":"30354",
    "addr:street":"Eisenhower Rd Se",
    "iso:country":"US",
    "sg:address":"966 Eisenhower Rd SE",
    "sg:city":"Atlanta",
    "sg:classifiers":[
        {
            "category":"Professional",
            "type":"Services"
        }
    ],
    "sg:phone":"+1 404 361 4032",
    "sg:postcode":"30354",
    "sg:province":"GA",
    "wof:name":"Total Impact Professional Serv",
    "wof:placetype":"venue"
},
  "geometry": {"coordinates":[-84.357642,33.656727],"type":"Point"}
}