{
  "type": "Feature",
  "properties": {
    "addr:full":"220 Livingston Rd SW Livingston GA 30161",
    "addr:housenumber":"220",
    "addr:postcode":"30161",
    "addr:street":"Livingston Rd Sw",
    "iso:country":"US",
    "sg:address":"220 Livingston Rd SW",
    "sg:city":"Livingston",
    "sg:classifiers":[
        {
            "category":"Insurance",
            "subcategory":"Insurance Agent",
            "type":"Services"
        }
    ],
    "sg:phone":"+1 973 597 1885",
    "sg:postcode":"30161",
    "sg:province":"GA",
    "wof:name":"New York Life Insurance Co",
    "wof:placetype":"venue"
},
  "geometry": {"coordinates":[-85.29706299999999,34.196331],"type":"Point"}
}