{
  "type": "Feature",
  "properties": {
    "addr:full":"309 Bell Park Dr Woodstock GA 30188",
    "addr:housenumber":"309",
    "addr:postcode":"30188",
    "addr:street":"Bell Park Dr",
    "iso:country":"US",
    "sg:address":"309 Bell Park Dr",
    "sg:city":"Woodstock",
    "sg:classifiers":[
        {
            "category":"Organizations",
            "subcategory":"Religious Organization",
            "type":"Services"
        }
    ],
    "sg:phone":"+1 770 928 6053",
    "sg:postcode":"30188",
    "sg:province":"GA",
    "wof:name":"Jubilee Conferences",
    "wof:placetype":"venue"
},
  "geometry": {"coordinates":[-84.510458,34.121688],"type":"Point"}
}