{
  "type": "Feature",
  "properties": {
    "addr:full":"1294 W Ridge Rd Gainesville GA 30501",
    "addr:housenumber":"1294",
    "addr:postcode":"30501",
    "addr:street":"W Ridge Rd",
    "iso:country":"US",
    "sg:address":"1294 W Ridge Rd",
    "sg:city":"Gainesville",
    "sg:classifiers":[
        {
            "category":"Professional",
            "subcategory":"Lawyer & Legal Services",
            "type":"Services"
        }
    ],
    "sg:phone":"+1 770 535 0222",
    "sg:postcode":"30501",
    "sg:province":"GA",
    "sg:tags":[
        "attorney"
    ],
    "wof:name":"James E Palmour III",
    "wof:placetype":"venue"
},
  "geometry": {"coordinates":[-83.82280900000001,34.275373],"type":"Point"}
}