{
  "type": "Feature",
  "properties": {
    "addr:full":"710 Ponce De Leon Ave Atlanta GA 30308",
    "addr:housenumber":"710",
    "addr:postcode":"30308",
    "addr:street":"Ponce De Leon Ave",
    "iso:country":"US",
    "sg:address":"710 Ponce De Leon Ave",
    "sg:city":"Atlanta",
    "sg:classifiers":[
        {
            "category":"Retail",
            "subcategory":"Auto Repair",
            "type":"Services"
        }
    ],
    "sg:phone":"+1 404 688 4949",
    "sg:postcode":"30308",
    "sg:province":"GA",
    "sg:tags":[
        "motorcycle"
    ],
    "wof:name":"Atlanta Motorcycles & Repair",
    "wof:placetype":"venue"
},
  "geometry": {"coordinates":[-84.364053,33.773693],"type":"Point"}
}