{
  "type": "Feature",
  "properties": {
    "addr:full":"106 Pencross Ct Kathleen GA 31047",
    "addr:housenumber":"106",
    "addr:postcode":"31047",
    "addr:street":"Pencross Ct",
    "iso:country":"US",
    "sg:address":"106 Pencross Ct",
    "sg:city":"Kathleen",
    "sg:classifiers":[
        {
            "category":"Government",
            "subcategory":"Office",
            "type":"Public Place"
        }
    ],
    "sg:phone":"+1 478 988 0618",
    "sg:postcode":"31047",
    "sg:province":"GA",
    "sg:tags":[
        "sourcing"
    ],
    "wof:name":"Loyd Inc",
    "wof:placetype":"venue"
},
  "geometry": {"coordinates":[-83.685259,32.54474],"type":"Point"}
}