{
  "type": "Feature",
  "properties": {
    "addr:full":"26 S Jackson St Hartwell GA 30643",
    "addr:housenumber":"26",
    "addr:postcode":"30643",
    "addr:street":"S Jackson St",
    "iso:country":"US",
    "sg:address":"26 S Jackson St",
    "sg:city":"Hartwell",
    "sg:classifiers":[
        {
            "category":"Wholesale",
            "subcategory":"Apparel",
            "type":"Manufacturing & Wholesale Goods"
        }
    ],
    "sg:phone":"+1 706 376 7272",
    "sg:postcode":"30643",
    "sg:province":"GA",
    "sg:tags":[
        "clothing"
    ],
    "wof:name":"Hartwell Co",
    "wof:placetype":"venue"
},
  "geometry": {"coordinates":[-82.93424,34.3529],"type":"Point"}
}