{
  "type": "Feature",
  "properties": {
    "addr:full":"1945 Alderbrook Rd NE Atlanta GA 30345",
    "addr:housenumber":"1945",
    "addr:postcode":"30345",
    "addr:street":"Alderbrook Rd Ne",
    "iso:country":"US",
    "sg:address":"1945 Alderbrook Rd NE",
    "sg:city":"Atlanta",
    "sg:classifiers":[
        {
            "category":"Professional",
            "type":"Services"
        }
    ],
    "sg:phone":"+1 404 634 2660",
    "sg:postcode":"30345",
    "sg:province":"GA",
    "wof:name":"Gob Temp Services Inc",
    "wof:placetype":"venue"
},
  "geometry": {"coordinates":[-84.308137,33.833013],"type":"Point"}
}