{
  "type": "Feature",
  "properties": {
    "iso:country":"US",
    "sg:address":"1150 Crooked Creek Rd",
    "sg:city":"Watkinsville",
    "sg:classifiers":[
        {
            "category":"Building & Trades",
            "subcategory":"Cleaning & Sanitation",
            "type":"Services"
        }
    ],
    "sg:phone":"+1 706 769 6066",
    "sg:postcode":"30677",
    "sg:province":"GA",
    "sg:tags":[
        "repair",
        "maintenance"
    ],
    "wof:name":"Daytime Cinderellas Clg Svc",
    "wof:placetype":"venue"
},
  "geometry": {"coordinates":[-83.465959,33.895543],"type":"Point"}
}