{
  "type": "Feature",
  "properties": {
    "addr:full":"123 S Broad St Cairo GA 39828",
    "addr:housenumber":"123",
    "addr:postcode":"39828",
    "addr:street":"S Broad St",
    "iso:country":"US",
    "sg:address":"123 S Broad St",
    "sg:city":"Cairo",
    "sg:classifiers":[
        {
            "category":"Personal",
            "subcategory":"Beauty Salon",
            "type":"Services"
        }
    ],
    "sg:phone":"+1 229 377 8472",
    "sg:postcode":"39828",
    "sg:province":"GA",
    "sg:tags":[
        "manicuring"
    ],
    "wof:name":"L A Nails",
    "wof:placetype":"venue"
},
  "geometry": {"coordinates":[-84.208001,30.876459],"type":"Point"}
}