{
  "type": "Feature",
  "properties": {
    "iso:country":"US",
    "sg:address":"2002 Mitchell St",
    "sg:city":"Savannah",
    "sg:classifiers":[
        {
            "category":"Organizations",
            "subcategory":"Religious Organization",
            "type":"Services"
        }
    ],
    "sg:phone":"+1 912 233 4930",
    "sg:postcode":"31405",
    "sg:province":"GA",
    "wof:name":"Spirit & In Truth Inc",
    "wof:placetype":"venue"
},
  "geometry": {"coordinates":[-81.139951,32.050479],"type":"Point"}
}