{
  "type": "Feature",
  "properties": {
    "iso:country":"US",
    "sg:address":"1659 Damon Ct",
    "sg:city":"Atlanta",
    "sg:classifiers":[
        {
            "category":"Building & Trades",
            "subcategory":"Electrical",
            "type":"Services"
        }
    ],
    "sg:phone":"+1 770 393 8899",
    "sg:postcode":"30338",
    "sg:province":"GA",
    "sg:tags":[
        "electrical",
        "contractor"
    ],
    "wof:name":"Electromech Services Inc",
    "wof:placetype":"venue"
},
  "geometry": {"coordinates":[-84.32067000000001,33.945013],"type":"Point"}
}