{
  "type": "Feature",
  "properties": {
    "iso:country":"US",
    "sg:address":"217 Taylor St",
    "sg:city":"Americus",
    "sg:classifiers":[
        {
            "category":"Professional",
            "type":"Services"
        }
    ],
    "sg:phone":"+1 229 928 3237",
    "sg:postcode":"31709",
    "sg:province":"GA",
    "wof:name":"Martin K Johnson Inc",
    "wof:placetype":"venue"
},
  "geometry": {"coordinates":[-84.227351,32.068142],"type":"Point"}
}