{
  "type": "Feature",
  "properties": {
    "addr:full":"3243 Lindas Cir SE Conyers GA 30013",
    "addr:postcode":"3243;30013",
    "addr:street":"Lindas Cir Se",
    "iso:country":"US",
    "sg:address":"3243 Lindas Cir SE",
    "sg:city":"Conyers",
    "sg:classifiers":[
        {
            "category":"Building & Trades",
            "subcategory":"Landscaping Services",
            "type":"Services"
        }
    ],
    "sg:phone":"+1 770 785 7951",
    "sg:postcode":"30013",
    "sg:province":"GA",
    "sg:tags":[
        "landscape"
    ],
    "wof:name":"Le Lawn Care",
    "wof:placetype":"venue"
},
  "geometry": {"coordinates":[-83.98651099999999,33.605306],"type":"Point"}
}