{
  "type": "Feature",
  "properties": {
    "addr:full":"1336 Emerald Ave SE Atlanta GA 30316",
    "addr:housenumber":"1336",
    "addr:postcode":"30316",
    "addr:street":"Emerald Ave Se",
    "iso:country":"US",
    "sg:address":"1336 Emerald Ave SE",
    "sg:city":"Atlanta",
    "sg:classifiers":[
        {
            "category":"Personal",
            "type":"Services"
        }
    ],
    "sg:phone":"+1 404 254 0876",
    "sg:postcode":"30316",
    "sg:province":"GA",
    "sg:tags":[
        "mover"
    ],
    "sg:website":"www.metropromoves.com",
    "wof:name":"Metro Pro Moves Inc",
    "wof:placetype":"venue"
},
  "geometry": {"coordinates":[-84.33588399999999,33.716444],"type":"Point"}
}