{
  "type": "Feature",
  "properties": {
    "addr:full":"2158 Mc Daniels Bridge Rd SW Lilburn GA 30047",
    "addr:housenumber":"2158",
    "addr:postcode":"30047",
    "addr:street":"Mc Daniels Bridge Rd Sw",
    "iso:country":"US",
    "sg:address":"2158 Mc Daniels Bridge Rd SW",
    "sg:city":"Lilburn",
    "sg:classifiers":[
        {
            "category":"Wholesale",
            "subcategory":"Home Furnishings",
            "type":"Manufacturing & Wholesale Goods"
        },
        {
            "category":"Home & Garden",
            "subcategory":"Carpets & Floor Coverings",
            "type":"Retail Goods"
        }
    ],
    "sg:phone":"+1 770 921 0711",
    "sg:postcode":"30047",
    "sg:province":"GA",
    "sg:tags":[
        "dealer",
        "rug"
    ],
    "wof:name":"Ace Carpets",
    "wof:placetype":"venue"
},
  "geometry": {"coordinates":[-84.06198500000001,33.842274],"type":"Point"}
}