{
  "type": "Feature",
  "properties": {
    "iso:country":"US",
    "sg:address":"4445 Nassau Way NE",
    "sg:city":"Marietta",
    "sg:classifiers":[
        {
            "category":"Professional",
            "subcategory":"Lawyer & Legal Services",
            "type":"Services"
        }
    ],
    "sg:phone":"+1 770 971 3270",
    "sg:postcode":"30068",
    "sg:province":"GA",
    "wof:name":"Hilley D Byron Atty",
    "wof:placetype":"venue"
},
  "geometry": {"coordinates":[-84.4235,33.977402],"type":"Point"}
}