{
  "type": "Feature",
  "properties": {
    "addr:full":"4588 Kinsdale Dr Mableton GA 30126",
    "addr:postcode":"4588;30126",
    "addr:street":"Kinsdale Dr",
    "iso:country":"US",
    "sg:address":"4588 Kinsdale Dr",
    "sg:city":"Mableton",
    "sg:classifiers":[
        {
            "category":"Recreation",
            "type":"Entertainment"
        }
    ],
    "sg:phone":"+1 770 732 8445",
    "sg:postcode":"30126",
    "sg:province":"GA",
    "wof:name":"Total Defense Systems",
    "wof:placetype":"venue"
},
  "geometry": {"coordinates":[-84.585252,33.841573],"type":"Point"}
}