{
  "type": "Feature",
  "properties": {
    "iso:country":"US",
    "sg:address":"3965 Stone Village Ct NW",
    "sg:city":"Duluth",
    "sg:classifiers":[
        {
            "category":"Professional",
            "subcategory":"Business Services",
            "type":"Services"
        }
    ],
    "sg:phone":"+1 770 623 3456",
    "sg:postcode":"30097",
    "sg:province":"GA",
    "wof:name":"White Technologies Inc",
    "wof:placetype":"venue"
},
  "geometry": {"coordinates":[-84.140973,34.019478],"type":"Point"}
}