{
  "type": "Feature",
  "properties": {
    "addr:full":"2525 Pio Nono Ave Macon GA 31206",
    "addr:housenumber":"2525",
    "addr:postcode":"31206",
    "addr:street":"Pio Nono Ave",
    "iso:country":"US",
    "sg:address":"2525 Pio Nono Ave",
    "sg:city":"Macon",
    "sg:classifiers":[
        {
            "category":"Shopping",
            "subcategory":"Clothing, Apparel, & Fashions",
            "type":"Retail Goods"
        }
    ],
    "sg:phone":"+1 478 788 4900",
    "sg:postcode":"31206",
    "sg:province":"GA",
    "sg:tags":[
        "family"
    ],
    "sg:website":"www.coat.com",
    "wof:name":"Burlington Coat Factory",
    "wof:placetype":"venue"
},
  "geometry": {"coordinates":[-83.663009,32.81152],"type":"Point"}
}