{
  "type": "Feature",
  "properties": {
    "addr:full":"1852 Enterprise Dr Norcross GA 30093",
    "addr:housenumber":"1852",
    "addr:postcode":"30093",
    "addr:street":"Enterprise Dr",
    "iso:country":"US",
    "sg:address":"1852 Enterprise Dr",
    "sg:city":"Norcross",
    "sg:classifiers":[
        {
            "category":"Shopping",
            "subcategory":"Stationery & Office Supplies",
            "type":"Retail Goods"
        },
        {
            "category":"Personal",
            "type":"Services"
        }
    ],
    "sg:phone":"+1 770 368 0101",
    "sg:postcode":"30093",
    "sg:province":"GA",
    "sg:tags":[
        "equipment",
        "mover"
    ],
    "wof:name":"Wegman Inc",
    "wof:placetype":"venue"
},
  "geometry": {"coordinates":[-84.220398,33.9072],"type":"Point"}
}