{
  "type": "Feature",
  "properties": {
    "iso:country":"US",
    "sg:address":"4215 Jimmy Lee Smith Pkwy",
    "sg:city":"Hiram",
    "sg:classifiers":[
        {
            "category":"Home & Garden",
            "subcategory":"Carpets & Floor Coverings",
            "type":"Retail Goods"
        }
    ],
    "sg:phone":"+1 770 439 7151",
    "sg:postcode":"30141",
    "sg:province":"GA",
    "sg:tags":[
        "mattress"
    ],
    "wof:name":"Mattress Direct",
    "wof:placetype":"venue"
},
  "geometry": {"coordinates":[-84.753998,33.891102],"type":"Point"}
}