{
  "type": "Feature",
  "properties": {
    "addr:full":"1601 Krug St Albany GA 31705",
    "addr:housenumber":"1601",
    "addr:postcode":"31705",
    "addr:street":"Krug St",
    "iso:country":"US",
    "sg:address":"1601 Krug St",
    "sg:city":"Albany",
    "sg:classifiers":[
        {
            "category":"Retail",
            "subcategory":"Auto Repair",
            "type":"Services"
        }
    ],
    "sg:phone":"+1 229 438 1193",
    "sg:postcode":"31705",
    "sg:province":"GA",
    "sg:tags":[
        "shop",
        "automotive",
        "machine",
        "automobile",
        "general"
    ],
    "wof:name":"A & D Engine Rebuilders/Machin",
    "wof:placetype":"venue"
},
  "geometry": {"coordinates":[-84.103803,31.590346],"type":"Point"}
}