{
  "type": "Feature",
  "properties": {
    "iso:country":"US",
    "sg:address":"1802 Old Dean Forest Rd",
    "sg:city":"Pooler",
    "sg:classifiers":[
        {
            "category":"Wholesale",
            "subcategory":"Machinery & Supplies",
            "type":"Manufacturing & Wholesale Goods"
        }
    ],
    "sg:phone":"+1 912 964 5539",
    "sg:postcode":"31322",
    "sg:province":"GA",
    "sg:tags":[
        "engine"
    ],
    "wof:name":"A-1 Trailer & Truck Repair",
    "wof:placetype":"venue"
},
  "geometry": {"coordinates":[-81.20151,32.094899],"type":"Point"}
}