{
  "type": "Feature",
  "properties": {
    "iso:country":"US",
    "sg:address":"2676 Kimmeridge Dr",
    "sg:city":"Atlanta",
    "sg:classifiers":[
        {
            "category":"Professional",
            "subcategory":"Management & Consulting",
            "type":"Services"
        }
    ],
    "sg:phone":"+1 404 593 8943",
    "sg:postcode":"30344",
    "sg:province":"GA",
    "sg:tags":[
        "provide"
    ],
    "wof:name":"Blue Collar Inc",
    "wof:placetype":"venue"
},
  "geometry": {"coordinates":[-84.453356,33.682712],"type":"Point"}
}