{
  "type": "Feature",
  "properties": {
    "addr:full":"3035 Walnut Creek Dr Alpharetta GA 30005",
    "addr:housenumber":"3035",
    "addr:postcode":"30005",
    "addr:street":"Walnut Creek Dr",
    "iso:country":"US",
    "sg:address":"3035 Walnut Creek Dr",
    "sg:city":"Alpharetta",
    "sg:classifiers":[
        {
            "category":"Local Transit",
            "type":"Transportation"
        }
    ],
    "sg:phone":"+1 678 867 7685",
    "sg:postcode":"30005",
    "sg:province":"GA",
    "sg:tags":[
        "bus",
        "line"
    ],
    "wof:name":"TWC South LLC",
    "wof:placetype":"venue"
},
  "geometry": {"coordinates":[-84.217052,34.092854],"type":"Point"}
}