{
  "type": "Feature",
  "properties": {
    "addr:full":"1145 Oxford Rd NE Atlanta GA 30306",
    "addr:housenumber":"1145",
    "addr:postcode":"30306",
    "addr:street":"Oxford Rd Ne",
    "iso:country":"US",
    "sg:address":"1145 Oxford Rd NE",
    "sg:city":"Atlanta",
    "sg:classifiers":[
        {
            "category":"Food & Beverages",
            "subcategory":"Groceries & Convenience Stores",
            "type":"Retail Goods"
        }
    ],
    "sg:phone":"+1 404 610 5765",
    "sg:postcode":"30306",
    "sg:province":"GA",
    "sg:tags":[
        "juice"
    ],
    "wof:name":"Hot Squeeze",
    "wof:placetype":"venue"
},
  "geometry": {"coordinates":[-84.33508,33.786293],"type":"Point"}
}