{
  "type": "Feature",
  "properties": {
    "addr:full":"3876 Saddlecreek Rd Douglasville GA 30135",
    "addr:housenumber":"3876",
    "addr:postcode":"30135",
    "addr:street":"Saddlecreek Rd",
    "iso:country":"US",
    "sg:address":"3876 Saddlecreek Rd",
    "sg:city":"Douglasville",
    "sg:classifiers":[
        {
            "category":"Wholesale",
            "subcategory":"Machinery & Supplies",
            "type":"Manufacturing & Wholesale Goods"
        }
    ],
    "sg:phone":"+1 770 942 0238",
    "sg:postcode":"30135",
    "sg:province":"GA",
    "sg:tags":[
        "equipment",
        "establishment"
    ],
    "wof:name":"Willis Quick Snax",
    "wof:placetype":"venue"
},
  "geometry": {"coordinates":[-84.71100199999999,33.702142],"type":"Point"}
}