{
  "type": "Feature",
  "properties": {
    "addr:full":"1089 Columbia Dr Decatur GA 30030",
    "addr:housenumber":"1089",
    "addr:postcode":"30030",
    "addr:street":"Columbia Dr",
    "iso:country":"US",
    "sg:address":"1089 Columbia Dr",
    "sg:city":"Decatur",
    "sg:classifiers":[
        {
            "category":"Personal",
            "subcategory":"Beauty Salon",
            "type":"Services"
        }
    ],
    "sg:phone":"+1 404 288 5786",
    "sg:postcode":"30030",
    "sg:province":"GA",
    "sg:tags":[
        "shop"
    ],
    "wof:name":"J J's Barber & Beauty Salon",
    "wof:placetype":"venue"
},
  "geometry": {"coordinates":[-84.269357,33.755758],"type":"Point"}
}