{
  "type": "Feature",
  "properties": {
    "iso:country":"US",
    "sg:address":"6658 Hillandale Dr",
    "sg:city":"Lithonia",
    "sg:classifiers":[
        {
            "category":"Professional",
            "type":"Services"
        }
    ],
    "sg:phone":"+1 770 484 8797",
    "sg:postcode":"30058",
    "sg:province":"GA",
    "wof:name":"Dwenda Everson",
    "wof:placetype":"venue"
},
  "geometry": {"coordinates":[-84.128196,33.703845],"type":"Point"}
}