{
  "type": "Feature",
  "properties": {
    "addr:full":"15 Anastasia Dr Mableton GA 30126",
    "addr:housenumber":"15",
    "addr:postcode":"30126",
    "addr:street":"Anastasia Dr",
    "iso:country":"US",
    "sg:address":"15 Anastasia Dr",
    "sg:city":"Mableton",
    "sg:classifiers":[
        {
            "category":"Manufacturing",
            "subcategory":"Jewelry",
            "type":"Manufacturing & Wholesale Goods"
        }
    ],
    "sg:phone":"+1 770 948 4462",
    "sg:postcode":"30126",
    "sg:province":"GA",
    "sg:tags":[
        "costume",
        "mfg"
    ],
    "sg:website":"www.shaleana.com",
    "wof:name":"Shaleanas Designs",
    "wof:placetype":"venue"
},
  "geometry": {"coordinates":[-84.553051,33.843226],"type":"Point"}
}