{
  "type": "Feature",
  "properties": {
    "addr:full":"1370 Center Dr Ste 201 Atlanta GA 30338",
    "addr:housenumber":"1370",
    "addr:postcode":"30338",
    "addr:street":"Center Dr Ste 201",
    "iso:country":"US",
    "sg:address":"1370 Center Dr Ste 201",
    "sg:city":"Atlanta",
    "sg:classifiers":[
        {
            "category":"Banks & Credit Unions",
            "subcategory":"Financial Services",
            "type":"Services"
        }
    ],
    "sg:phone":"+1 770 399 7775",
    "sg:postcode":"30338",
    "sg:province":"GA",
    "sg:tags":[
        "broker",
        "mortgage"
    ],
    "wof:name":"Innovative Mortgage Solutions Inc Llc",
    "wof:placetype":"venue"
},
  "geometry": {"coordinates":[-84.33520300000001,33.951216],"type":"Point"}
}