{
  "type": "Feature",
  "properties": {
    "addr:full":"1621 Christopher Dr Jonesboro GA 30236",
    "addr:housenumber":"1621",
    "addr:postcode":"30236",
    "addr:street":"Christopher Dr",
    "iso:country":"US",
    "sg:address":"1621 Christopher Dr",
    "sg:city":"Jonesboro",
    "sg:classifiers":[
        {
            "category":"Restaurant",
            "type":"Food & Drink"
        }
    ],
    "sg:phone":"+1 770 477 8275",
    "sg:postcode":"30236",
    "sg:province":"GA",
    "sg:tags":[
        "eating"
    ],
    "wof:name":"Piggy Backs Barbeque Inc",
    "wof:placetype":"venue"
},
  "geometry": {"coordinates":[-84.33702,33.534118],"type":"Point"}
}