{
  "type": "Feature",
  "properties": {
    "addr:full":"1731 Powder Springs St S Marietta GA 30064",
    "addr:housenumber":"1731",
    "addr:postcode":"30064",
    "addr:street":"Powder Springs St S",
    "iso:country":"US",
    "sg:address":"1731 Powder Springs St S",
    "sg:city":"Marietta",
    "sg:classifiers":[
        {
            "category":"Restaurant",
            "type":"Food & Drink"
        }
    ],
    "sg:phone":"+1 770 499 1239",
    "sg:postcode":"30064",
    "sg:province":"GA",
    "sg:tags":[
        "eating"
    ],
    "wof:name":"Starbucks Corporation",
    "wof:placetype":"venue"
},
  "geometry": {"coordinates":[-84.604332,33.904482],"type":"Point"}
}