{
  "type": "Feature",
  "properties": {
    "addr:full":"109 W Broadway St Griffin GA 30223",
    "addr:housenumber":"109",
    "addr:postcode":"30223",
    "addr:street":"W Broadway St",
    "iso:country":"US",
    "sg:address":"109 W Broadway St",
    "sg:city":"Griffin",
    "sg:classifiers":[
        {
            "category":"Shopping",
            "subcategory":"Used Merchandise",
            "type":"Retail Goods"
        }
    ],
    "sg:phone":"+1 770 467 9949",
    "sg:postcode":"30223",
    "sg:province":"GA",
    "sg:tags":[
        "shop",
        "consignment"
    ],
    "wof:name":"Christian Missionary",
    "wof:placetype":"venue"
},
  "geometry": {"coordinates":[-84.268405,33.251412],"type":"Point"}
}