{
  "type": "Feature",
  "properties": {
    "iso:country":"US",
    "sg:address":"829 Donald Lee Hollowell",
    "sg:city":"Atlanta",
    "sg:classifiers":[
        {
            "category":"Organizations",
            "subcategory":"Religious Organization",
            "type":"Services"
        }
    ],
    "sg:phone":"+1 404 872 6067",
    "sg:postcode":"30318",
    "sg:province":"GA",
    "wof:name":"Pure Church of Jesus Christ",
    "wof:placetype":"venue"
},
  "geometry": {"coordinates":[-84.414692,33.772933],"type":"Point"}
}