{
  "type": "Feature",
  "properties": {
    "addr:full":"2000 Manchester Street Atlanta GA 30324",
    "addr:housenumber":"2000",
    "addr:postcode":"30324",
    "addr:street":"Manchester Street",
    "iso:country":"US",
    "sg:address":"2000 Manchester Street",
    "sg:city":"Atlanta",
    "sg:classifiers":[
        {
            "category":"Taxi",
            "type":"Transportation"
        }
    ],
    "sg:phone":"+1 404 872 5232",
    "sg:postcode":"30324",
    "sg:province":"GA",
    "sg:website":"www.usatoplights.com",
    "wof:name":"USA Top Lights",
    "wof:placetype":"venue"
},
  "geometry": {"coordinates":[-84.36374499999999,33.809426],"type":"Point"}
}