{
  "type": "Feature",
  "properties": {
    "iso:country":"US",
    "sg:address":"2539 Sandy Creek Rd",
    "sg:city":"Commerce",
    "sg:classifiers":[
        {
            "category":"Professional",
            "type":"Services"
        }
    ],
    "sg:phone":"+1 706 336 0018",
    "sg:postcode":"30530",
    "sg:province":"GA",
    "sg:tags":[
        "transportation"
    ],
    "wof:name":"J Morgan & Taylor Inc",
    "wof:placetype":"venue"
},
  "geometry": {"coordinates":[-83.39277800000001,34.161907],"type":"Point"}
}