{
  "type": "Feature",
  "properties": {
    "iso:country":"US",
    "sg:address":"1500 Mount Zion Rd",
    "sg:city":"Morrow",
    "sg:classifiers":[
        {
            "category":"Food & Beverages",
            "subcategory":"Specialty",
            "type":"Retail Goods"
        }
    ],
    "sg:phone":"+1 770 961 0077",
    "sg:postcode":"30260",
    "sg:province":"GA",
    "sg:tags":[
        "vitamin"
    ],
    "wof:name":"Discount Nutrition Southlake",
    "wof:placetype":"venue"
},
  "geometry": {"coordinates":[-84.338106,33.571521],"type":"Point"}
}