{
  "type": "Feature",
  "properties": {
    "iso:country":"US",
    "sg:address":"1115 Telfair St",
    "sg:city":"Dublin",
    "sg:classifiers":[
        {
            "category":"Restaurant",
            "type":"Food & Drink"
        }
    ],
    "sg:phone":"+1 478 272 6709",
    "sg:postcode":"31021",
    "sg:province":"GA",
    "sg:tags":[
        "eating"
    ],
    "wof:name":"Roberson Barbecue",
    "wof:placetype":"venue"
},
  "geometry": {"coordinates":[-82.91419500000001,32.527406],"type":"Point"}
}