{
  "type": "Feature",
  "properties": {
    "iso:country":"US",
    "sg:address":"1811 Rice Ave",
    "sg:city":"Dublin",
    "sg:classifiers":[
        {
            "category":"Travel",
            "subcategory":"Travel Agent",
            "type":"Entertainment"
        }
    ],
    "sg:phone":"+1 478 274 1999",
    "sg:postcode":"31021",
    "sg:province":"GA",
    "sg:tags":[
        "agency"
    ],
    "sg:website":"http://www.quicktaninc.com",
    "wof:name":"Quick Tan",
    "wof:placetype":"venue"
},
  "geometry": {"coordinates":[-82.93477,32.537273],"type":"Point"}
}