{
  "type": "Feature",
  "properties": {
    "addr:full":"208 Harwell Pl NW Apt F Atlanta GA 30318",
    "addr:housenumber":"208",
    "addr:postcode":"30318",
    "addr:street":"Harwell Pl Nw Apt F",
    "iso:country":"US",
    "sg:address":"208 Harwell Pl NW Apt F",
    "sg:city":"Atlanta",
    "sg:classifiers":[
        {
            "category":"Retail",
            "subcategory":"Laundry & Dry Cleaning",
            "type":"Services"
        },
        {
            "category":"Building & Trades",
            "subcategory":"Cleaning & Sanitation",
            "type":"Services"
        }
    ],
    "sg:phone":"+1 404 423 6918",
    "sg:postcode":"30318",
    "sg:province":"GA",
    "sg:tags":[
        "cleaner",
        "house"
    ],
    "wof:name":"Right Touch Cleaning Service",
    "wof:placetype":"venue"
},
  "geometry": {"coordinates":[-84.491955,33.780752],"type":"Point"}
}