{
  "type": "Feature",
  "properties": {
    "iso:country":"US",
    "sg:address":"2375 Castle Ln NE",
    "sg:city":"Marietta",
    "sg:classifiers":[
        {
            "category":"Wholesale",
            "subcategory":"Medical Equipment & Supplies",
            "type":"Manufacturing & Wholesale Goods"
        }
    ],
    "sg:phone":"+1 770 971 6895",
    "sg:postcode":"30062",
    "sg:province":"GA",
    "sg:tags":[
        "rep",
        "dental",
        "mfg"
    ],
    "wof:name":"Lichter Marketing Group Inc",
    "wof:placetype":"venue"
},
  "geometry": {"coordinates":[-84.44540499999999,34.007749],"type":"Point"}
}