{
  "type": "Feature",
  "properties": {
    "iso:country":"US",
    "sg:address":"1207 Royal Dr SW",
    "sg:city":"Conyers",
    "sg:classifiers":[
        {
            "category":"Organizations",
            "subcategory":"Religious Organization",
            "type":"Services"
        }
    ],
    "sg:phone":"+1 770 483 9945",
    "sg:postcode":"30094",
    "sg:province":"GA",
    "wof:name":"Praise Temple of Conyers",
    "wof:placetype":"venue"
},
  "geometry": {"coordinates":[-84.024101,33.657398],"type":"Point"}
}