{
  "type": "Feature",
  "properties": {
    "addr:full":"5229 Slygo Rd Trenton GA 30752",
    "addr:housenumber":"5229",
    "addr:postcode":"30752",
    "addr:street":"Slygo Rd",
    "iso:country":"US",
    "sg:address":"5229 Slygo Rd",
    "sg:city":"Trenton",
    "sg:classifiers":[
        {
            "category":"Real Estate",
            "subcategory":"Real Estate Operator",
            "type":"Services"
        }
    ],
    "sg:phone":"+1 423 314 5211",
    "sg:postcode":"30752",
    "sg:province":"GA",
    "sg:tags":[
        "boarding",
        "house"
    ],
    "wof:name":"Heatherfield Horse Park",
    "wof:placetype":"venue"
},
  "geometry": {"coordinates":[-85.448982,34.96538],"type":"Point"}
}