{
  "type": "Feature",
  "properties": {
    "addr:full":"502 Jackson St Vidalia GA 30474",
    "addr:housenumber":"502",
    "addr:postcode":"30474",
    "addr:street":"Jackson St",
    "iso:country":"US",
    "sg:address":"502 Jackson St",
    "sg:city":"Vidalia",
    "sg:classifiers":[
        {
            "category":"Professional",
            "subcategory":"Lawyer & Legal Services",
            "type":"Services"
        }
    ],
    "sg:phone":"+1 912 537 9021",
    "sg:postcode":"30474",
    "sg:province":"GA",
    "sg:tags":[
        "attorney"
    ],
    "wof:name":"Malcolm F Bryant Jr Law Office",
    "wof:placetype":"venue"
},
  "geometry": {"coordinates":[-82.41376700000001,32.213389],"type":"Point"}
}