{
  "type": "Feature",
  "properties": {
    "iso:country":"US",
    "sg:address":"3345 Cobb Pkwy",
    "sg:city":"Acworth",
    "sg:classifiers":[
        {
            "category":"Personal",
            "subcategory":"Beauty Salon",
            "type":"Services"
        }
    ],
    "sg:phone":"+1 770 974 8474",
    "sg:postcode":"30101",
    "sg:province":"GA",
    "sg:tags":[
        "shop"
    ],
    "wof:name":"Salon Serein",
    "wof:placetype":"venue"
},
  "geometry": {"coordinates":[-84.680982,34.035289],"type":"Point"}
}