{
  "type": "Feature",
  "properties": {
    "addr:full":"283 Sentry Ridge Dallas GA 30157",
    "addr:housenumber":"283",
    "addr:postcode":"30157",
    "addr:street":"Sentry Ridge",
    "iso:country":"US",
    "sg:address":"283 Sentry Ridge",
    "sg:city":"Dallas",
    "sg:classifiers":[
        {
            "category":"Health Services",
            "subcategory":"Doctor",
            "type":"Services"
        }
    ],
    "sg:phone":"+1 678 363 8568",
    "sg:postcode":"30157",
    "sg:province":"GA",
    "sg:tags":[
        "medical"
    ],
    "wof:name":"Tammy Beatty",
    "wof:placetype":"venue"
},
  "geometry": {"coordinates":[-84.770263,33.973309],"type":"Point"}
}