{
  "type": "Feature",
  "properties": {
    "addr:full":"731 Ridge Ln Lula GA 30554",
    "addr:housenumber":"731",
    "addr:postcode":"30554",
    "addr:street":"Ridge Ln",
    "iso:country":"US",
    "sg:address":"731 Ridge Ln",
    "sg:city":"Lula",
    "sg:classifiers":[
        {
            "category":"Building & Trades",
            "subcategory":"Electrical",
            "type":"Services"
        }
    ],
    "sg:phone":"+1 678 410 8503",
    "sg:postcode":"30554",
    "sg:province":"GA",
    "sg:tags":[
        "electrician"
    ],
    "wof:name":"D&L Electric",
    "wof:placetype":"venue"
},
  "geometry": {"coordinates":[-83.60985599999999,34.393415],"type":"Point"}
}