{
  "type": "Feature",
  "properties": {
    "iso:country":"US",
    "sg:address":"267 Rose St",
    "sg:city":"Martinez",
    "sg:classifiers":[
        {
            "category":"Building & Trades",
            "subcategory":"Plumbing",
            "type":"Services"
        }
    ],
    "sg:phone":"+1 706 863 4800",
    "sg:postcode":"30907",
    "sg:province":"GA",
    "sg:tags":[
        "conditioning",
        "air",
        "system",
        "contractor"
    ],
    "wof:name":"Komfort Heating & Air Cond Inc",
    "wof:placetype":"venue"
},
  "geometry": {"coordinates":[-82.089054,33.507429],"type":"Point"}
}