{
  "type": "Feature",
  "properties": {
    "addr:full":"105 N Elm St Jesup GA 31546",
    "addr:housenumber":"105",
    "addr:postcode":"31546",
    "addr:street":"N Elm St",
    "iso:country":"US",
    "sg:address":"105 N Elm St",
    "sg:city":"Jesup",
    "sg:classifiers":[
        {
            "category":"Banks & Credit Unions",
            "subcategory":"Bank",
            "type":"Services"
        }
    ],
    "sg:phone":"+1 912 427 7076",
    "sg:postcode":"31546",
    "sg:province":"GA",
    "wof:name":"Patterson Bank",
    "wof:placetype":"venue"
},
  "geometry": {"coordinates":[-81.87779999999999,31.602882],"type":"Point"}
}