{
  "type": "Feature",
  "properties": {
    "iso:country":"US",
    "sg:address":"1612 Mars Hill Rd",
    "sg:city":"Watkinsville",
    "sg:classifiers":[
        {
            "category":"Health Services",
            "subcategory":"Clinic",
            "type":"Services"
        }
    ],
    "sg:phone":"+1 706 769 3200",
    "sg:postcode":"30677",
    "sg:province":"GA",
    "sg:tags":[
        "home"
    ],
    "wof:name":"Protocol Home Care Svc Inc",
    "wof:placetype":"venue"
},
  "geometry": {"coordinates":[-83.454144,33.881137],"type":"Point"}
}