{
  "type": "Feature",
  "properties": {
    "addr:full":"366 Brooks Cove Dr Valdosta GA 31602",
    "addr:housenumber":"366",
    "addr:postcode":"31602",
    "addr:street":"Brooks Cove Dr",
    "iso:country":"US",
    "sg:address":"366 Brooks Cove Dr",
    "sg:city":"Valdosta",
    "sg:classifiers":[
        {
            "category":"Building & Trades",
            "subcategory":"Construction",
            "type":"Services"
        }
    ],
    "sg:phone":"+1 229 219 1040",
    "sg:postcode":"31602",
    "sg:province":"GA",
    "sg:tags":[
        "contractor"
    ],
    "wof:name":"Fender & Sons Fencing",
    "wof:placetype":"venue"
},
  "geometry": {"coordinates":[-83.384834,30.875812],"type":"Point"}
}