{
  "type": "Feature",
  "properties": {
    "addr:full":"4126 Pleasantdale Rd Atlanta GA 30340",
    "addr:housenumber":"4126",
    "addr:postcode":"30340",
    "addr:street":"Pleasantdale Rd",
    "iso:country":"US",
    "sg:address":"4126 Pleasantdale Rd",
    "sg:city":"Atlanta",
    "sg:classifiers":[
        {
            "category":"Real Estate",
            "subcategory":"Real Estate Agent",
            "type":"Services"
        }
    ],
    "sg:phone":"+1 770 491 7662",
    "sg:postcode":"30340",
    "sg:province":"GA",
    "wof:name":"Final Links Realty Group LLC",
    "wof:placetype":"venue"
},
  "geometry": {"coordinates":[-84.245249,33.903377],"type":"Point"}
}