{
  "type": "Feature",
  "properties": {
    "iso:country":"US",
    "sg:address":"496 White Pines Dr",
    "sg:city":"Dallas",
    "sg:classifiers":[
        {
            "category":"Shopping",
            "subcategory":"Clothing, Apparel, & Fashions",
            "type":"Retail Goods"
        }
    ],
    "sg:phone":"+1 770 443 3385",
    "sg:postcode":"30157",
    "sg:province":"GA",
    "wof:name":"Mister Shop",
    "wof:placetype":"venue"
},
  "geometry": {"coordinates":[-84.826455,33.870132],"type":"Point"}
}