{
  "type": "Feature",
  "properties": {
    "addr:full":"561 S Main St Swainsboro GA 30401",
    "addr:housenumber":"561",
    "addr:postcode":"30401",
    "addr:street":"S Main St",
    "iso:country":"US",
    "sg:address":"561 S Main St",
    "sg:city":"Swainsboro",
    "sg:classifiers":[
        {
            "category":"Travel",
            "subcategory":"Hotels & Motels",
            "type":"Entertainment"
        }
    ],
    "sg:phone":"+1 478 237 7542",
    "sg:postcode":"30401",
    "sg:province":"GA",
    "wof:name":"Sunset Inn",
    "wof:placetype":"venue"
},
  "geometry": {"coordinates":[-82.31829999999999,32.581638],"type":"Point"}
}