{
  "type": "Feature",
  "properties": {
    "addr:full":"3901 Peachtree Rd NE Atlanta GA 30319",
    "addr:housenumber":"3901",
    "addr:postcode":"30319",
    "addr:street":"Peachtree Rd Ne",
    "iso:country":"US",
    "sg:address":"3901 Peachtree Rd NE",
    "sg:city":"Atlanta",
    "sg:classifiers":[
        {
            "category":"Coffee & Tea",
            "type":"Food & Drink"
        }
    ],
    "sg:menulink":"http://www.allmenus.com/ga/chamblee-doraville/107923-starbucks-coffee/menu/",
    "sg:phone":"+1 404 504 9277",
    "sg:postcode":"30319",
    "sg:province":"GA",
    "sg:tags":[
        "american"
    ],
    "wof:name":"Starbucks Coffee",
    "wof:placetype":"venue"
},
  "geometry": {"coordinates":[-84.343654,33.857204],"type":"Point"}
}