{
  "type": "Feature",
  "properties": {
    "iso:country":"US",
    "sg:address":"2602 Young Rd",
    "sg:city":"Stone Mountain",
    "sg:classifiers":[
        {
            "category":"Organizations",
            "subcategory":"Religious Organization",
            "type":"Services"
        }
    ],
    "sg:phone":"+1 770 808 8887",
    "sg:postcode":"30088",
    "sg:province":"GA",
    "sg:tags":[
        "church"
    ],
    "wof:name":"Mountainside Seventh Day Adven",
    "wof:placetype":"venue"
},
  "geometry": {"coordinates":[-84.182543,33.732288],"type":"Point"}
}