{
  "type": "Feature",
  "properties": {
    "iso:country":"US",
    "sg:address":"955 Wenham Ln",
    "sg:city":"Lawrenceville",
    "sg:classifiers":[
        {
            "category":"Building & Trades",
            "subcategory":"Construction",
            "type":"Services"
        }
    ],
    "sg:phone":"+1 770 338 2643",
    "sg:postcode":"30044",
    "sg:province":"GA",
    "sg:tags":[
        "house"
    ],
    "wof:name":"Ftrb Construction Inc",
    "wof:placetype":"venue"
},
  "geometry": {"coordinates":[-84.079847,33.944624],"type":"Point"}
}