{
  "type": "Feature",
  "properties": {
    "iso:country":"US",
    "sg:address":"247 Moreland Ave NE",
    "sg:city":"Atlanta",
    "sg:classifiers":[
        {
            "category":"Autos & Motor Vehicles",
            "subcategory":"Fuel & Gas Station",
            "type":"Retail Goods"
        }
    ],
    "sg:phone":"+1 404 525 6786",
    "sg:postcode":"30307",
    "sg:province":"GA",
    "wof:name":"All Star Convenience Stores",
    "wof:placetype":"venue"
},
  "geometry": {"coordinates":[-84.348975,33.760006],"type":"Point"}
}