{
  "type": "Feature",
  "properties": {
    "iso:country":"US",
    "sg:address":"311 Marble Mill Rd NW",
    "sg:city":"Marietta",
    "sg:classifiers":[
        {
            "category":"Utilities",
            "subcategory":"Recycling",
            "type":"Services"
        },
        {
            "category":"Wholesale",
            "subcategory":"Scrap",
            "type":"Manufacturing & Wholesale Goods"
        }
    ],
    "sg:phone":"+1 770 425 6600",
    "sg:postcode":"30060",
    "sg:province":"GA",
    "sg:tags":[
        "metal"
    ],
    "sg:website":"http://www.mariettarecyclingcenter.com",
    "wof:name":"Marietta Recycling Center",
    "wof:placetype":"venue"
},
  "geometry": {"coordinates":[-84.558835,33.97695],"type":"Point"}
}