{
  "type": "Feature",
  "properties": {
    "addr:full":"1420 N Cliff Valley Way NE Atlanta GA 30319",
    "addr:housenumber":"1420",
    "addr:postcode":"30319",
    "addr:street":"N Cliff Valley Way Ne",
    "iso:country":"US",
    "sg:address":"1420 N Cliff Valley Way NE",
    "sg:city":"Atlanta",
    "sg:classifiers":[
        {
            "category":"Building & Trades",
            "subcategory":"Landscaping Services",
            "type":"Services"
        }
    ],
    "sg:phone":"+1 770 652 7780",
    "sg:postcode":"30319",
    "sg:province":"GA",
    "sg:tags":[
        "aged",
        "homes-institutional"
    ],
    "wof:name":"Zamudio Helping Hand",
    "wof:placetype":"venue"
},
  "geometry": {"coordinates":[-84.33144799999999,33.843024],"type":"Point"}
}