{
  "type": "Feature",
  "properties": {
    "addr:full":"3529 Wrightsboro Rd Augusta GA 30909",
    "addr:housenumber":"3529",
    "addr:postcode":"30909",
    "addr:street":"Wrightsboro Rd",
    "iso:country":"US",
    "sg:address":"3529 Wrightsboro Rd",
    "sg:city":"Augusta",
    "sg:classifiers":[
        {
            "category":"Personal",
            "subcategory":"Barber",
            "type":"Services"
        }
    ],
    "sg:phone":"+1 706 736 1125",
    "sg:postcode":"30909",
    "sg:province":"GA",
    "sg:tags":[
        "shop"
    ],
    "wof:name":"Urban Cutz",
    "wof:placetype":"venue"
},
  "geometry": {"coordinates":[-82.086883,33.465706],"type":"Point"}
}