{
  "type": "Feature",
  "properties": {
    "addr:full":"332 Fletcher Rd Bowdon GA 30108",
    "addr:housenumber":"332",
    "addr:postcode":"30108",
    "addr:street":"Fletcher Rd",
    "iso:country":"US",
    "sg:address":"332 Fletcher Rd",
    "sg:city":"Bowdon",
    "sg:classifiers":[
        {
            "category":"Building & Trades",
            "subcategory":"Landscaping Services",
            "type":"Services"
        }
    ],
    "sg:phone":"+1 770 258 4634",
    "sg:postcode":"30108",
    "sg:province":"GA",
    "sg:tags":[
        "tree"
    ],
    "wof:name":"Wardlaw Lawn & Tree Svc",
    "wof:placetype":"venue"
},
  "geometry": {"coordinates":[-85.308246,33.544272],"type":"Point"}
}