{
  "type": "Feature",
  "properties": {
    "addr:full":"1595 Battlecreek Rd Jonesboro GA 30236",
    "addr:housenumber":"1595",
    "addr:postcode":"30236",
    "addr:street":"Battlecreek Rd",
    "iso:country":"US",
    "sg:address":"1595 Battlecreek Rd",
    "sg:city":"Jonesboro",
    "sg:classifiers":[
        {
            "category":"Organizations",
            "subcategory":"Community Association",
            "type":"Services"
        }
    ],
    "sg:phone":"+1 678 479 7390",
    "sg:postcode":"30236",
    "sg:province":"GA",
    "sg:tags":[
        "fraternal"
    ],
    "wof:name":"Loyal Order Of Moose",
    "wof:placetype":"venue"
},
  "geometry": {"coordinates":[-84.33387999999999,33.552758],"type":"Point"}
}