{
  "type": "Feature",
  "properties": {
    "iso:country":"US",
    "sg:address":"1929 Scenic Hwy N",
    "sg:city":"Snellville",
    "sg:classifiers":[
        {
            "category":"Shopping",
            "subcategory":"Books",
            "type":"Retail Goods"
        }
    ],
    "sg:phone":"+1 770 982 0454",
    "sg:postcode":"30078",
    "sg:province":"GA",
    "sg:tags":[
        "bookstore"
    ],
    "sg:website":"www.borders.com",
    "wof:name":"Borders Books Music Movies & Cafe",
    "wof:placetype":"venue"
},
  "geometry": {"coordinates":[-84.01424,33.873475],"type":"Point"}
}