{
  "type": "Feature",
  "properties": {
    "iso:country":"US",
    "sg:address":"3874 Riverview Spring Ct",
    "sg:city":"Ellenwood",
    "sg:classifiers":[
        {
            "category":"Building & Trades",
            "subcategory":"Landscaping Services",
            "type":"Services"
        }
    ],
    "sg:phone":"+1 404 218 6583",
    "sg:postcode":"30294",
    "sg:province":"GA",
    "sg:tags":[
        "lawn",
        "maintenance",
        "grounds"
    ],
    "wof:name":"Lawn Boyz",
    "wof:placetype":"venue"
},
  "geometry": {"coordinates":[-84.24784099999999,33.66806],"type":"Point"}
}