{
  "type": "Feature",
  "properties": {
    "iso:country":"US",
    "sg:address":"730 Franklin Rd SE Apt E3",
    "sg:city":"Marietta",
    "sg:classifiers":[
        {
            "category":"Real Estate",
            "subcategory":"Real Estate Operator",
            "type":"Services"
        }
    ],
    "sg:phone":"+1 770 429 0157",
    "sg:postcode":"30067",
    "sg:province":"GA",
    "sg:tags":[
        "apartment"
    ],
    "wof:name":"Cinnamon Ridge Apartments",
    "wof:placetype":"venue"
},
  "geometry": {"coordinates":[-84.501999,33.933498],"type":"Point"}
}