{
  "type": "Feature",
  "properties": {
    "iso:country":"US",
    "sg:address":"1175 Grimes Bridge Rd",
    "sg:city":"Roswell",
    "sg:classifiers":[
        {
            "category":"Professional",
            "subcategory":"Lawyer & Legal Services",
            "type":"Services"
        }
    ],
    "sg:phone":"+1 770 992 3480",
    "sg:postcode":"30075",
    "sg:province":"GA",
    "wof:name":"Sullivan Michael E Atty",
    "wof:placetype":"venue"
},
  "geometry": {"coordinates":[-84.342102,34.030899],"type":"Point"}
}