{
  "type": "Feature",
  "properties": {
    "addr:full":"5854 Goshen Springs Rd Norcross GA 30071",
    "addr:housenumber":"5854",
    "addr:postcode":"30071",
    "addr:street":"Goshen Springs Rd",
    "iso:country":"US",
    "sg:address":"5854 Goshen Springs Rd",
    "sg:city":"Norcross",
    "sg:classifiers":[
        {
            "category":"Home & Garden",
            "subcategory":"Carpets & Floor Coverings",
            "type":"Retail Goods"
        }
    ],
    "sg:phone":"+1 404 552 0503",
    "sg:postcode":"30071",
    "sg:province":"GA",
    "sg:tags":[
        "carpeting"
    ],
    "sg:website":"www.carpetsurplusliquidators.com",
    "wof:name":"Carpet Surplus Liquidators",
    "wof:placetype":"venue"
},
  "geometry": {"coordinates":[-84.19939599999999,33.917716],"type":"Point"}
}