{
  "type": "Feature",
  "properties": {
    "addr:full":"11 Franklin Loop SE Cartersville GA 30121",
    "addr:housenumber":"11",
    "addr:postcode":"30121",
    "addr:street":"Franklin Loop Se",
    "iso:country":"US",
    "sg:address":"11 Franklin Loop SE",
    "sg:city":"Cartersville",
    "sg:classifiers":[
        {
            "category":"Organizations",
            "subcategory":"Religious Organization",
            "type":"Services"
        }
    ],
    "sg:phone":"+1 770 382 5874",
    "sg:postcode":"30121",
    "sg:province":"GA",
    "sg:tags":[
        "church"
    ],
    "sg:website":"www.emersonbaptist.com",
    "wof:name":"Emerson Baptist Church",
    "wof:placetype":"venue"
},
  "geometry": {"coordinates":[-84.74675499999999,34.105113],"type":"Point"}
}