{
  "type": "Feature",
  "properties": {
    "addr:full":"672 Beckwith St SW Atlanta GA 30314",
    "addr:housenumber":"672",
    "addr:postcode":"30314",
    "addr:street":"Beckwith St Sw",
    "iso:country":"US",
    "sg:address":"672 Beckwith St SW",
    "sg:city":"Atlanta",
    "sg:classifiers":[
        {
            "category":"Professional",
            "subcategory":"Computer Services",
            "type":"Services"
        }
    ],
    "sg:phone":"+1 404 524 5569",
    "sg:postcode":"30314",
    "sg:province":"GA",
    "sg:tags":[
        "programming",
        "custom"
    ],
    "wof:name":"Pds Software",
    "wof:placetype":"venue"
},
  "geometry": {"coordinates":[-84.40997900000001,33.752026],"type":"Point"}
}