{
  "type": "Feature",
  "properties": {
    "iso:country":"US",
    "sg:address":"97 Thunder Ridge Dr",
    "sg:city":"Acworth",
    "sg:classifiers":[
        {
            "category":"Professional",
            "subcategory":"Business Services",
            "type":"Services"
        }
    ],
    "sg:phone":"+1 770 548 9293",
    "sg:postcode":"30101",
    "sg:province":"GA",
    "sg:tags":[
        "inspection"
    ],
    "wof:name":"Crescent Inspection Svc",
    "wof:placetype":"venue"
},
  "geometry": {"coordinates":[-84.77806699999999,34.05249],"type":"Point"}
}