{
  "type": "Feature",
  "properties": {
    "iso:country":"US",
    "sg:address":"1102 N Maple St",
    "sg:city":"Springfield",
    "sg:classifiers":[
        {
            "category":"Organizations",
            "subcategory":"Religious Organization",
            "type":"Services"
        }
    ],
    "sg:phone":"+1 912 754 7530",
    "sg:postcode":"31329",
    "sg:province":"GA",
    "wof:name":"Gethsemane Baptist Church",
    "wof:placetype":"venue"
},
  "geometry": {"coordinates":[-81.31507000000001,32.376935],"type":"Point"}
}