{
  "type": "Feature",
  "properties": {
    "addr:full":"1314 Concord Rd SE Smyrna GA 30080",
    "addr:housenumber":"1314",
    "addr:postcode":"30080",
    "addr:street":"Concord Rd Se",
    "iso:country":"US",
    "sg:address":"1314 Concord Rd SE",
    "sg:city":"Smyrna",
    "sg:classifiers":[
        {
            "category":"Health Services",
            "subcategory":"Doctor",
            "type":"Services"
        }
    ],
    "sg:phone":"+1 770 333 8889",
    "sg:postcode":"30080",
    "sg:province":"GA",
    "sg:tags":[
        "practice",
        "family"
    ],
    "wof:name":"Harvey James S MD",
    "wof:placetype":"venue"
},
  "geometry": {"coordinates":[-84.5158,33.880199],"type":"Point"}
}