{
  "type": "Feature",
  "properties": {
    "iso:country":"US",
    "sg:address":"1721 Wildflower Ln",
    "sg:city":"Albany",
    "sg:classifiers":[
        {
            "category":"Shopping",
            "subcategory":"Florist",
            "type":"Retail Goods"
        }
    ],
    "sg:phone":"+1 229 883 6489",
    "sg:postcode":"31705",
    "sg:province":"GA",
    "wof:name":"Perfect Present Flowers",
    "wof:placetype":"venue"
},
  "geometry": {"coordinates":[-84.091247,31.533595],"type":"Point"}
}