{
  "type": "Feature",
  "properties": {
    "addr:full":"1406 Hog Mountain Rd Winder GA 30680",
    "addr:housenumber":"1406",
    "addr:postcode":"30680",
    "addr:street":"Hog Mountain Rd",
    "iso:country":"US",
    "sg:address":"1406 Hog Mountain Rd",
    "sg:city":"Winder",
    "sg:classifiers":[
        {
            "category":"Organizations",
            "subcategory":"Religious Organization",
            "type":"Services"
        }
    ],
    "sg:phone":"+1 770 725 7639",
    "sg:postcode":"30680",
    "sg:province":"GA",
    "sg:tags":[
        "church"
    ],
    "wof:name":"Midway Christian Church Inc",
    "wof:placetype":"venue"
},
  "geometry": {"coordinates":[-83.63212799999999,33.937604],"type":"Point"}
}