{
  "type": "Feature",
  "properties": {
    "iso:country":"US",
    "sg:address":"2110 Campbellton Rd SW",
    "sg:city":"Atlanta",
    "sg:classifiers":[
        {
            "category":"Food & Beverages",
            "subcategory":"Liquor & Beverages",
            "type":"Retail Goods"
        }
    ],
    "sg:phone":"+1 404 758 7494",
    "sg:postcode":"30311",
    "sg:province":"GA",
    "wof:name":"New Image Package Store",
    "wof:placetype":"venue"
},
  "geometry": {"coordinates":[-84.46232999999999,33.704823],"type":"Point"}
}