{
  "type": "Feature",
  "properties": {
    "addr:full":"251 Smokerise Trce Peachtree City GA 30269",
    "addr:housenumber":"251",
    "addr:postcode":"30269",
    "addr:street":"Smokerise Trce",
    "iso:country":"US",
    "sg:address":"251 Smokerise Trce",
    "sg:city":"Peachtree City",
    "sg:classifiers":[
        {
            "category":"Professional",
            "type":"Services"
        }
    ],
    "sg:phone":"+1 770 486 1358",
    "sg:postcode":"30269",
    "sg:province":"GA",
    "sg:tags":[
        "establishment"
    ],
    "wof:name":"Bradshaw Co",
    "wof:placetype":"venue"
},
  "geometry": {"coordinates":[-84.571393,33.439301],"type":"Point"}
}