{
  "type": "Feature",
  "properties": {
    "iso:country":"US",
    "sg:address":"146 E Howell St",
    "sg:city":"Hartwell",
    "sg:classifiers":[
        {
            "category":"Real Estate",
            "subcategory":"Real Estate Agent",
            "type":"Services"
        }
    ],
    "sg:phone":"+1 706 376 9777",
    "sg:postcode":"30643",
    "sg:province":"GA",
    "wof:name":"Charles Sanford Realty",
    "wof:placetype":"venue"
},
  "geometry": {"coordinates":[-82.937004,34.353374],"type":"Point"}
}