{
  "type": "Feature",
  "properties": {
    "addr:full":"411 Oak Tree Rd Ringgold GA 30736",
    "addr:housenumber":"411",
    "addr:postcode":"30736",
    "addr:street":"Oak Tree Rd",
    "iso:country":"US",
    "sg:address":"411 Oak Tree Rd",
    "sg:city":"Ringgold",
    "sg:classifiers":[
        {
            "category":"Building & Trades",
            "subcategory":"Landscaping Services",
            "type":"Services"
        }
    ],
    "sg:phone":"+1 423 309 0594",
    "sg:postcode":"30736",
    "sg:province":"GA",
    "sg:tags":[
        "landscape",
        "contractor"
    ],
    "sg:website":"http://www.hallslawncarelandscape.com",
    "wof:name":"Hall's Lawn Care & Landscapes",
    "wof:placetype":"venue"
},
  "geometry": {"coordinates":[-85.165999,34.891289],"type":"Point"}
}