{
  "type": "Feature",
  "properties": {
    "iso:country":"US",
    "sg:address":"1202 Lafayette Rd",
    "sg:city":"Rossville",
    "sg:classifiers":[
        {
            "category":"Communications",
            "type":"Services"
        }
    ],
    "sg:phone":"+1 706 866 4202",
    "sg:postcode":"30741",
    "sg:province":"GA",
    "sg:tags":[
        "communication"
    ],
    "wof:name":"Communications L Georgia North",
    "wof:placetype":"venue"
},
  "geometry": {"coordinates":[-85.267954,34.88612],"type":"Point"}
}