{
  "type": "Feature",
  "properties": {
    "iso:country":"US",
    "sg:address":"2330 Waters Ferry Dr",
    "sg:city":"Lawrenceville",
    "sg:classifiers":[
        {
            "category":"Banks & Credit Unions",
            "subcategory":"Financial Services",
            "type":"Services"
        }
    ],
    "sg:phone":"+1 678 376 7505",
    "sg:postcode":"30043",
    "sg:province":"GA",
    "sg:tags":[
        "patent",
        "furniture"
    ],
    "wof:name":"Phr & Associates",
    "wof:placetype":"venue"
},
  "geometry": {"coordinates":[-83.998451,34.010006],"type":"Point"}
}