{
  "type": "Feature",
  "properties": {
    "iso:country":"US",
    "sg:address":"338 Veterans Memorial Pkwy SW",
    "sg:city":"Mableton",
    "sg:classifiers":[
        {
            "category":"Autos & Motor Vehicles",
            "subcategory":"Automobile Sales",
            "type":"Retail Goods"
        }
    ],
    "sg:phone":"+1 770 949 8802",
    "sg:postcode":"30126",
    "sg:province":"GA",
    "wof:name":"Auto Outlet Express",
    "wof:placetype":"venue"
},
  "geometry": {"coordinates":[-84.564024,33.815658],"type":"Point"}
}