{
  "type": "Feature",
  "properties": {
    "iso:country":"US",
    "sg:address":"5904 E Heights Dr",
    "sg:city":"Columbus",
    "sg:classifiers":[
        {
            "category":"Building & Trades",
            "subcategory":"Construction",
            "type":"Services"
        }
    ],
    "sg:phone":"+1 706 563 8218",
    "sg:postcode":"31909",
    "sg:province":"GA",
    "sg:tags":[
        "designer",
        "dealer",
        "pool",
        "swimming"
    ],
    "wof:name":"Crystal Pools",
    "wof:placetype":"venue"
},
  "geometry": {"coordinates":[-84.908118,32.530783],"type":"Point"}
}