{
  "type": "Feature",
  "properties": {
    "iso:country":"US",
    "sg:address":"5399 New Peachtree Rd",
    "sg:city":"Chamblee",
    "sg:classifiers":[
        {
            "category":"Retail",
            "subcategory":"Repair Shop",
            "type":"Services"
        }
    ],
    "sg:phone":"+1 678 806 0424",
    "sg:postcode":"30341",
    "sg:province":"GA",
    "sg:tags":[
        "key",
        "locksmith"
    ],
    "wof:name":"0 Emergency 24 Hour A Locksmith",
    "wof:placetype":"venue"
},
  "geometry": {"coordinates":[-84.30038999999999,33.890549],"type":"Point"}
}