{
  "type": "Feature",
  "properties": {
    "iso:country":"US",
    "sg:address":"3700 Campbellton Rd SW",
    "sg:city":"Atlanta",
    "sg:classifiers":[
        {
            "category":"Personal",
            "subcategory":"Beauty Salon",
            "type":"Services"
        }
    ],
    "sg:phone":"+1 404 629 9091",
    "sg:postcode":"30331",
    "sg:province":"GA",
    "sg:tags":[
        "hair",
        "stylist"
    ],
    "wof:name":"Bamba Hair Braiding",
    "wof:placetype":"venue"
},
  "geometry": {"coordinates":[-84.50852399999999,33.690083],"type":"Point"}
}