{
  "type": "Feature",
  "properties": {
    "iso:country":"US",
    "sg:address":"220 Industrial Blvd Ste D",
    "sg:city":"Dublin",
    "sg:classifiers":[
        {
            "category":"Shopping",
            "subcategory":"Clothing, Apparel, & Fashions",
            "type":"Retail Goods"
        },
        {
            "category":"Wholesale",
            "subcategory":"Medical Equipment & Supplies",
            "type":"Manufacturing & Wholesale Goods"
        },
        {
            "category":"Autos & Motor Vehicles",
            "subcategory":"Fuel & Gas Station",
            "type":"Retail Goods"
        }
    ],
    "sg:phone":"+1 478 275 9444",
    "sg:postcode":"31021",
    "sg:province":"GA",
    "sg:tags":[
        "made",
        "form",
        "appliance",
        "prosthetic",
        "alterations-clothing",
        "accessory",
        "shirts-custom",
        "apparel",
        "surgical",
        "orthopedic",
        "device",
        "women's",
        "mastectomy"
    ],
    "sg:website":"http://www.chmartinco.com",
    "wof:name":"C H Martin Co O & P",
    "wof:placetype":"venue"
},
  "geometry": {"coordinates":[-82.948128,32.53231],"type":"Point"}
}