{
  "type": "Feature",
  "properties": {
    "iso:country":"US",
    "sg:address":"4166 Buford Hwy NE",
    "sg:city":"Atlanta",
    "sg:classifiers":[
        {
            "category":"Personal",
            "subcategory":"Shoe Repair & Shine",
            "type":"Services"
        }
    ],
    "sg:phone":"+1 404 634 5550",
    "sg:postcode":"30345",
    "sg:province":"GA",
    "wof:name":"V & J Instant Shoe Repair",
    "wof:placetype":"venue"
},
  "geometry": {"coordinates":[-84.304199,33.864899],"type":"Point"}
}