{
  "type": "Feature",
  "properties": {
    "addr:full":"151 N Main St Cedartown GA 30125",
    "addr:housenumber":"151",
    "addr:postcode":"30125",
    "addr:street":"N Main St",
    "iso:country":"US",
    "sg:address":"151 N Main St",
    "sg:city":"Cedartown",
    "sg:classifiers":[
        {
            "category":"Shopping",
            "subcategory":"Bicycles & Sporting Goods",
            "type":"Retail Goods"
        }
    ],
    "sg:phone":"+1 770 748 7711",
    "sg:postcode":"30125",
    "sg:province":"GA",
    "sg:tags":[
        "equipment",
        "saddlery",
        "equestrian"
    ],
    "wof:name":"Halls Saddle",
    "wof:placetype":"venue"
},
  "geometry": {"coordinates":[-85.25411200000001,34.017104],"type":"Point"}
}