{
  "type": "Feature",
  "properties": {
    "addr:full":"3425 Cherokee Ave Columbus GA 31906",
    "addr:housenumber":"3425",
    "addr:postcode":"31906",
    "addr:street":"Cherokee Ave",
    "iso:country":"US",
    "sg:address":"3425 Cherokee Ave",
    "sg:city":"Columbus",
    "sg:classifiers":[
        {
            "category":"Wholesale",
            "subcategory":"Electrical",
            "type":"Manufacturing & Wholesale Goods"
        }
    ],
    "sg:phone":"+1 706 324 1661",
    "sg:postcode":"31906",
    "sg:province":"GA",
    "sg:tags":[
        "fire",
        "alarm",
        "system"
    ],
    "wof:name":"G & G Electronics Inc",
    "wof:placetype":"venue"
},
  "geometry": {"coordinates":[-84.95827,32.495918],"type":"Point"}
}