{
  "type": "Feature",
  "properties": {
    "addr:full":"552 Laney Walker Blvd Exd Augusta GA 30901",
    "addr:housenumber":"552",
    "addr:postcode":"30901",
    "addr:street":"Laney Walker Blvd Exd",
    "iso:country":"US",
    "sg:address":"552 Laney Walker Blvd Exd",
    "sg:city":"Augusta",
    "sg:classifiers":[
        {
            "category":"Communications",
            "subcategory":"Radio Station",
            "type":"Services"
        }
    ],
    "sg:phone":"+1 706 722 6077",
    "sg:postcode":"30901",
    "sg:province":"GA",
    "sg:tags":[
        "company",
        "broadcasting"
    ],
    "wof:name":"WFAM Radio",
    "wof:placetype":"venue"
},
  "geometry": {"coordinates":[-81.944339,33.456108],"type":"Point"}
}