{
  "type": "Feature",
  "properties": {
    "addr:full":"1642 Dekalb Ave NE Atlanta GA 30307",
    "addr:housenumber":"1642",
    "addr:postcode":"30307",
    "addr:street":"Dekalb Ave Ne",
    "iso:country":"US",
    "sg:address":"1642 Dekalb Ave NE",
    "sg:city":"Atlanta",
    "sg:classifiers":[
        {
            "category":"Real Estate",
            "subcategory":"Real Estate Agent",
            "type":"Services"
        }
    ],
    "sg:phone":"+1 404 371 4419",
    "sg:postcode":"30307",
    "sg:province":"GA",
    "sg:website":"www.realestateofatlanta.com",
    "wof:name":"Re/Max Metro Atlanta Cityside",
    "wof:placetype":"venue"
},
  "geometry": {"coordinates":[-84.333147,33.762271],"type":"Point"}
}