{
  "type": "Feature",
  "properties": {
    "addr:full":"720 Old Johnson Rd Lawrenceville GA 30045",
    "addr:housenumber":"720",
    "addr:postcode":"30045",
    "addr:street":"Old Johnson Rd",
    "iso:country":"US",
    "sg:address":"720 Old Johnson Rd",
    "sg:city":"Lawrenceville",
    "sg:classifiers":[
        {
            "category":"Professional",
            "type":"Services"
        }
    ],
    "sg:phone":"+1 678 377 2207",
    "sg:postcode":"30045",
    "sg:province":"GA",
    "wof:name":"Kimberly Kase",
    "wof:placetype":"venue"
},
  "geometry": {"coordinates":[-83.976383,33.919956],"type":"Point"}
}