{
  "type": "Feature",
  "properties": {
    "addr:full":"2500 Victory Dr Columbus GA 31901",
    "addr:housenumber":"2500",
    "addr:postcode":"31901",
    "addr:street":"Victory Dr",
    "iso:country":"US",
    "sg:address":"2500 Victory Dr",
    "sg:city":"Columbus",
    "sg:classifiers":[
        {
            "category":"Autos & Motor Vehicles",
            "subcategory":"Automobile Sales",
            "type":"Retail Goods"
        }
    ],
    "sg:phone":"+1 706 221 9536",
    "sg:postcode":"31901",
    "sg:province":"GA",
    "sg:tags":[
        "car",
        "dealer"
    ],
    "wof:name":"Eagle Motors",
    "wof:placetype":"venue"
},
  "geometry": {"coordinates":[-84.965783,32.440553],"type":"Point"}
}