{
  "type": "Feature",
  "properties": {
    "addr:full":"789 Skymeadow Dr Pine Mountain GA 31822",
    "addr:housenumber":"789",
    "addr:postcode":"31822",
    "addr:street":"Skymeadow Dr",
    "iso:country":"US",
    "sg:address":"789 Skymeadow Dr",
    "sg:city":"Pine Mountain",
    "sg:classifiers":[
        {
            "category":"Airport",
            "type":"Transportation"
        }
    ],
    "sg:phone":"+1 706 663 5055",
    "sg:postcode":"31822",
    "sg:province":"GA",
    "wof:name":"Callaway-Harris County Airport",
    "wof:placetype":"venue"
},
  "geometry": {"coordinates":[-84.871771,32.84526],"type":"Point"}
}