{
  "type": "Feature",
  "properties": {
    "addr:full":"5775 Jimmy Carter Blvd Norcross GA 30071",
    "addr:housenumber":"5775",
    "addr:postcode":"30071",
    "addr:street":"Jimmy Carter Blvd",
    "iso:country":"US",
    "sg:address":"5775 Jimmy Carter Blvd",
    "sg:city":"Norcross",
    "sg:classifiers":[
        {
            "category":"Personal",
            "subcategory":"Beauty Salon",
            "type":"Services"
        }
    ],
    "sg:phone":"+1 770 242 1252",
    "sg:postcode":"30071",
    "sg:province":"GA",
    "sg:tags":[
        "hair"
    ],
    "wof:name":"Shyama Beauty Salon",
    "wof:placetype":"venue"
},
  "geometry": {"coordinates":[-84.209396,33.917198],"type":"Point"}
}