{
  "type": "Feature",
  "properties": {
    "iso:country":"US",
    "sg:address":"2515 Fort Daniels Dr NE",
    "sg:city":"Dacula",
    "sg:classifiers":[
        {
            "category":"Professional",
            "type":"Services"
        }
    ],
    "sg:phone":"+1 678 482 8100",
    "sg:postcode":"30519",
    "sg:province":"GA",
    "wof:name":"Custom Wood Products",
    "wof:placetype":"venue"
},
  "geometry": {"coordinates":[-83.93080399999999,34.040753],"type":"Point"}
}