{
  "type": "Feature",
  "properties": {
    "addr:full":"258 Beulah Church Rd Carrollton GA 30117",
    "addr:housenumber":"258",
    "addr:postcode":"30117",
    "addr:street":"Beulah Church Rd",
    "iso:country":"US",
    "sg:address":"258 Beulah Church Rd",
    "sg:city":"Carrollton",
    "sg:classifiers":[
        {
            "category":"Wholesale",
            "subcategory":"Groceries",
            "type":"Manufacturing & Wholesale Goods"
        }
    ],
    "sg:phone":"+1 770 832 1688",
    "sg:postcode":"30117",
    "sg:province":"GA",
    "sg:tags":[
        "food",
        "snack"
    ],
    "wof:name":"Frito-Lay",
    "wof:placetype":"venue"
},
  "geometry": {"coordinates":[-85.098966,33.600485],"type":"Point"}
}