{
  "type": "Feature",
  "properties": {
    "addr:full":"4435 State Bridge Way Alpharetta GA 30022",
    "addr:housenumber":"4435",
    "addr:postcode":"30022",
    "addr:street":"State Bridge Way",
    "iso:country":"US",
    "sg:address":"4435 State Bridge Way",
    "sg:city":"Alpharetta",
    "sg:classifiers":[
        {
            "category":"Retail",
            "subcategory":"Auto Repair",
            "type":"Services"
        }
    ],
    "sg:phone":"+1 770 569 9008",
    "sg:postcode":"30022",
    "sg:province":"GA",
    "sg:tags":[
        "automobile",
        "lubrication"
    ],
    "wof:name":"Texaco Xpress Lube",
    "wof:placetype":"venue"
},
  "geometry": {"coordinates":[-84.23282399999999,34.058009],"type":"Point"}
}