{
  "type": "Feature",
  "properties": {
    "iso:country":"US",
    "sg:address":"9 Medical Arts Center",
    "sg:city":"Savannah",
    "sg:classifiers":[
        {
            "category":"Health Services",
            "subcategory":"Doctor",
            "type":"Services"
        }
    ],
    "sg:phone":"+1 912 355 7790",
    "sg:postcode":"31405",
    "sg:province":"GA",
    "wof:name":"Derek V Miles D M D",
    "wof:placetype":"venue"
},
  "geometry": {"coordinates":[-81.09472,32.030954],"type":"Point"}
}