{
  "type": "Feature",
  "properties": {
    "addr:full":"3900 Brunswick Hwy Waycross GA 31503",
    "addr:housenumber":"3900",
    "addr:postcode":"31503",
    "addr:street":"Brunswick Hwy",
    "iso:country":"US",
    "sg:address":"3900 Brunswick Hwy",
    "sg:city":"Waycross",
    "sg:classifiers":[
        {
            "category":"Food & Beverages",
            "subcategory":"Groceries & Convenience Stores",
            "type":"Retail Goods"
        },
        {
            "category":"Freight",
            "type":"Transportation"
        }
    ],
    "sg:phone":"+1 912 283 8414",
    "sg:postcode":"31503",
    "sg:province":"GA",
    "sg:tags":[
        "be",
        "alcoholic",
        "commercial",
        "storage",
        "station",
        "gasoline"
    ],
    "wof:name":"Griffin's Mini Storage",
    "wof:placetype":"venue"
},
  "geometry": {"coordinates":[-82.28758000000001,31.192774],"type":"Point"}
}