{
  "type": "Feature",
  "properties": {
    "iso:country":"US",
    "sg:address":"446 Connemara Trl",
    "sg:city":"Evans",
    "sg:classifiers":[
        {
            "category":"Professional",
            "subcategory":"Business Services",
            "type":"Services"
        }
    ],
    "sg:phone":"+1 706 869 0814",
    "sg:postcode":"30809",
    "sg:province":"GA",
    "wof:name":"Emannuel Chrstn Counciling Ctr",
    "wof:placetype":"venue"
},
  "geometry": {"coordinates":[-82.142166,33.53014],"type":"Point"}
}