{
  "type": "Feature",
  "properties": {
    "addr:full":"560 Meadowbrook Dr Mc Donough GA 30253",
    "addr:housenumber":"560",
    "addr:postcode":"30253",
    "addr:street":"Meadowbrook Dr",
    "iso:country":"US",
    "sg:address":"560 Meadowbrook Dr",
    "sg:city":"Mc Donough",
    "sg:classifiers":[
        {
            "category":"Professional",
            "subcategory":"Business Services",
            "type":"Services"
        }
    ],
    "sg:phone":"+1 678 432 1173",
    "sg:postcode":"30253",
    "sg:province":"GA",
    "wof:name":"Randy Waczowski LLC",
    "wof:placetype":"venue"
},
  "geometry": {"coordinates":[-84.20609899999999,33.477055],"type":"Point"}
}