{
  "type": "Feature",
  "properties": {
    "addr:full":"3000 Corporate Center Dr Morrow GA 30260",
    "addr:housenumber":"3000",
    "addr:postcode":"30260",
    "addr:street":"Corporate Center Dr",
    "iso:country":"US",
    "sg:address":"3000 Corporate Center Dr",
    "sg:city":"Morrow",
    "sg:classifiers":[
        {
            "category":"Real Estate",
            "subcategory":"Developer",
            "type":"Services"
        }
    ],
    "sg:phone":"+1 770 968 0857",
    "sg:postcode":"30260",
    "sg:province":"GA",
    "wof:name":"Piedmont Development",
    "wof:placetype":"venue"
},
  "geometry": {"coordinates":[-84.332329,33.57045],"type":"Point"}
}