{
  "type": "Feature",
  "properties": {
    "iso:country":"US",
    "sg:address":"520 McKinne's Park",
    "sg:city":"Evans",
    "sg:classifiers":[
        {
            "category":"Manufacturing",
            "subcategory":"Food",
            "type":"Manufacturing & Wholesale Goods"
        }
    ],
    "sg:phone":"+1 706 228 3522",
    "sg:postcode":"30809",
    "sg:province":"GA",
    "sg:tags":[
        "canned",
        "specialty",
        "mfg"
    ],
    "wof:name":"Brule Gourmet",
    "wof:placetype":"venue"
},
  "geometry": {"coordinates":[-82.10736,33.545443],"type":"Point"}
}