{
  "type": "Feature",
  "properties": {
    "iso:country":"US",
    "sg:address":"1215 Hightower Trl",
    "sg:city":"Atlanta",
    "sg:classifiers":[
        {
            "category":"Professional",
            "subcategory":"Advertising",
            "type":"Services"
        }
    ],
    "sg:phone":"+1 770 993 7204",
    "sg:postcode":"30350",
    "sg:province":"GA",
    "sg:tags":[
        "print"
    ],
    "wof:name":"Whelan Group",
    "wof:placetype":"venue"
},
  "geometry": {"coordinates":[-84.346255,33.987028],"type":"Point"}
}