{
  "type": "Feature",
  "properties": {
    "addr:full":"2058 Walton Way Augusta GA 30904",
    "addr:housenumber":"2058",
    "addr:postcode":"30904",
    "addr:street":"Walton Way",
    "iso:country":"US",
    "sg:address":"2058 Walton Way",
    "sg:city":"Augusta",
    "sg:classifiers":[
        {
            "category":"Restaurant",
            "type":"Food & Drink"
        }
    ],
    "sg:phone":"+1 706 733 5931",
    "sg:postcode":"30904",
    "sg:province":"GA",
    "sg:tags":[
        "barbecue"
    ],
    "wof:name":"Smoaks Deli Bakery & Catering Service",
    "wof:placetype":"venue"
},
  "geometry": {"coordinates":[-82.007469,33.475861],"type":"Point"}
}