{
  "type": "Feature",
  "properties": {
    "iso:country":"US",
    "sg:address":"1385 Harmony Grove Church Rd",
    "sg:city":"Auburn",
    "sg:classifiers":[
        {
            "category":"Real Estate",
            "subcategory":"Real Estate Agent",
            "type":"Services"
        }
    ],
    "sg:phone":"+1 770 277 7997",
    "sg:postcode":"30011",
    "sg:province":"GA",
    "sg:tags":[
        "authorities",
        "housing"
    ],
    "wof:name":"Barrow County Habitat-Humanity",
    "wof:placetype":"venue"
},
  "geometry": {"coordinates":[-83.826684,34.038464],"type":"Point"}
}