{
  "type": "Feature",
  "properties": {
    "iso:country":"US",
    "sg:address":"3025 Washington Rd",
    "sg:city":"Augusta",
    "sg:classifiers":[
        {
            "category":"Restaurant",
            "type":"Food & Drink"
        }
    ],
    "sg:phone":"+1 706 868 5585",
    "sg:postcode":"30907",
    "sg:province":"GA",
    "sg:tags":[
        "eating"
    ],
    "wof:name":"Sapparo Japanese Steakhouse",
    "wof:placetype":"venue"
},
  "geometry": {"coordinates":[-82.05024,33.513087],"type":"Point"}
}