{
  "type": "Feature",
  "properties": {
    "iso:country":"US",
    "sg:address":"1201 Williams St",
    "sg:city":"Valdosta",
    "sg:classifiers":[
        {
            "category":"Insurance",
            "subcategory":"Insurance Agent",
            "type":"Services"
        }
    ],
    "sg:phone":"+1 229 242 4282",
    "sg:postcode":"31601",
    "sg:province":"GA",
    "wof:name":"Life Of The South Insurance Co",
    "wof:placetype":"venue"
},
  "geometry": {"coordinates":[-83.282709,30.84552],"type":"Point"}
}