{
  "type": "Feature",
  "properties": {
    "addr:full":"701 2nd St W Tifton GA 31794",
    "addr:housenumber":"701",
    "addr:postcode":"31794",
    "addr:street":"2Nd St W",
    "iso:country":"US",
    "sg:address":"701 2nd St W",
    "sg:city":"Tifton",
    "sg:classifiers":[
        {
            "category":"Food & Beverages",
            "subcategory":"Groceries & Convenience Stores",
            "type":"Retail Goods"
        }
    ],
    "sg:phone":"+1 229 382 0437",
    "sg:postcode":"31794",
    "sg:province":"GA",
    "sg:tags":[
        "grocer"
    ],
    "wof:name":"Purvis' Grocery",
    "wof:placetype":"venue"
},
  "geometry": {"coordinates":[-83.52246,31.457766],"type":"Point"}
}