{
  "type": "Feature",
  "properties": {
    "addr:full":"1134 GA-20/81 Mcdonough GA 30253",
    "addr:housenumber":"1134;/ 81",
    "addr:postcode":"30253",
    "addr:street":"Ga-20",
    "iso:country":"US",
    "sg:address":"1134 GA-20/81",
    "sg:city":"Mcdonough",
    "sg:classifiers":[
        {
            "category":"Restaurant",
            "type":"Food & Drink"
        }
    ],
    "sg:menulink":"http://www.allmenus.com/ga/mcdonough/124029-quiznos-sub/menu/",
    "sg:phone":"+1 770 305 9050",
    "sg:postcode":"30253",
    "sg:province":"GA",
    "sg:tags":[
        "wrap",
        "american",
        "sandwich"
    ],
    "wof:name":"Quiznos Sub",
    "wof:placetype":"venue"
},
  "geometry": {"coordinates":[-84.180226,33.429114],"type":"Point"}
}