{
  "type": "Feature",
  "properties": {
    "iso:country":"US",
    "sg:address":"601 Woodlawn Dr NE",
    "sg:city":"Marietta",
    "sg:classifiers":[
        {
            "category":"Professional",
            "type":"Services"
        }
    ],
    "sg:phone":"+1 770 509 3390",
    "sg:postcode":"30067",
    "sg:province":"GA",
    "sg:tags":[
        "establishment"
    ],
    "wof:name":"Palladian Inc",
    "wof:placetype":"venue"
},
  "geometry": {"coordinates":[-84.41618699999999,33.964358],"type":"Point"}
}