{
  "type": "Feature",
  "properties": {
    "addr:full":"6420 Bennett Dr Rex GA 30273",
    "addr:housenumber":"6420",
    "addr:postcode":"30273",
    "addr:street":"Bennett Dr",
    "iso:country":"US",
    "sg:address":"6420 Bennett Dr",
    "sg:city":"Rex",
    "sg:classifiers":[
        {
            "category":"Health Services",
            "subcategory":"Nursing And Care Facility",
            "type":"Services"
        }
    ],
    "sg:phone":"+1 678 565 9940",
    "sg:postcode":"30273",
    "sg:province":"GA",
    "sg:tags":[
        "personal",
        "home"
    ],
    "wof:name":"Sunset Personal Care Home",
    "wof:placetype":"venue"
},
  "geometry": {"coordinates":[-84.284171,33.57769],"type":"Point"}
}