{
  "type": "Feature",
  "properties": {
    "addr:full":"1121 Rome St Carrollton GA 30117",
    "addr:housenumber":"1121",
    "addr:postcode":"30117",
    "addr:street":"Rome St",
    "iso:country":"US",
    "sg:address":"1121 Rome St",
    "sg:city":"Carrollton",
    "sg:classifiers":[
        {
            "category":"Professional",
            "type":"Services"
        }
    ],
    "sg:phone":"+1 770 214 8089",
    "sg:postcode":"30117",
    "sg:province":"GA",
    "sg:tags":[
        "establishment"
    ],
    "wof:name":"Nationwide",
    "wof:placetype":"venue"
},
  "geometry": {"coordinates":[-85.07934400000001,33.595352],"type":"Point"}
}