{
  "type": "Feature",
  "properties": {
    "iso:country":"US",
    "sg:address":"615 Macon St",
    "sg:city":"Mcdonough",
    "sg:classifiers":[
        {
            "category":"Manufacturing",
            "subcategory":"Apparel",
            "type":"Manufacturing & Wholesale Goods"
        }
    ],
    "sg:phone":"+1 770 957 3981",
    "sg:postcode":"30253",
    "sg:province":"GA",
    "sg:tags":[
        "uniform"
    ],
    "sg:website":"www.encompassgroup.net",
    "wof:name":"Encompass Group",
    "wof:placetype":"venue"
},
  "geometry": {"coordinates":[-84.144988,33.429699],"type":"Point"}
}