{
  "type": "Feature",
  "properties": {
    "addr:full":"1611 Queensbury St Savannah GA 31406",
    "addr:housenumber":"1611",
    "addr:postcode":"31406",
    "addr:street":"Queensbury St",
    "iso:country":"US",
    "sg:address":"1611 Queensbury St",
    "sg:city":"Savannah",
    "sg:classifiers":[
        {
            "category":"Professional",
            "subcategory":"Secretarial Services",
            "type":"Services"
        }
    ],
    "sg:phone":"+1 912 354 9503",
    "sg:postcode":"31406",
    "sg:province":"GA",
    "sg:tags":[
        "report",
        "hearing"
    ],
    "wof:name":"Lavine B Cobia",
    "wof:placetype":"venue"
},
  "geometry": {"coordinates":[-81.09177699999999,31.991751],"type":"Point"}
}