{
  "type": "Feature",
  "properties": {
    "iso:country":"US",
    "sg:address":"117 Lonnie Johnson Rd",
    "sg:city":"Hazlehurst",
    "sg:classifiers":[
        {
            "category":"Professional",
            "subcategory":"Computer Services",
            "type":"Services"
        }
    ],
    "sg:phone":"+1 912 375 5850",
    "sg:postcode":"31539",
    "sg:province":"GA",
    "sg:tags":[
        "internet"
    ],
    "wof:name":"Golden Isles Wireless Internet",
    "wof:placetype":"venue"
},
  "geometry": {"coordinates":[-82.47967800000001,31.91843],"type":"Point"}
}