{
  "type": "Feature",
  "properties": {
    "iso:country":"US",
    "sg:address":"2140 Kilgore Rd",
    "sg:city":"Buford",
    "sg:classifiers":[
        {
            "category":"Personal",
            "subcategory":"Beauty Salon",
            "type":"Services"
        }
    ],
    "sg:phone":"+1 770 945 4869",
    "sg:postcode":"30519",
    "sg:province":"GA",
    "wof:name":"Headstart Beauty Salon",
    "wof:placetype":"venue"
},
  "geometry": {"coordinates":[-83.978452,34.083435],"type":"Point"}
}