{
  "type": "Feature",
  "properties": {
    "addr:full":"211 Hill Rd Lagrange GA 30240",
    "addr:housenumber":"211",
    "addr:postcode":"30240",
    "addr:street":"Hill Rd",
    "iso:country":"US",
    "sg:address":"211 Hill Rd",
    "sg:city":"Lagrange",
    "sg:classifiers":[
        {
            "category":"Government",
            "subcategory":"Office",
            "type":"Public Place"
        }
    ],
    "sg:phone":"+1 706 883 2110",
    "sg:postcode":"30240",
    "sg:province":"GA",
    "sg:tags":[
        "village"
    ],
    "wof:name":"LA Grange City Garage",
    "wof:placetype":"venue"
},
  "geometry": {"coordinates":[-85.11304699999999,33.019493],"type":"Point"}
}