{
  "type": "Feature",
  "properties": {
    "addr:full":"9218 Reed Creek Hwy Hartwell GA 30643",
    "addr:housenumber":"9218",
    "addr:postcode":"30643",
    "addr:street":"Reed Creek Hwy",
    "iso:country":"US",
    "sg:address":"9218 Reed Creek Hwy",
    "sg:city":"Hartwell",
    "sg:classifiers":[
        {
            "category":"Building & Trades",
            "subcategory":"Electrical",
            "type":"Services"
        }
    ],
    "sg:phone":"+1 706 376 3713",
    "sg:postcode":"30643",
    "sg:province":"GA",
    "sg:tags":[
        "electric",
        "contractor"
    ],
    "wof:name":"Holland Electrical Plumbing",
    "wof:placetype":"venue"
},
  "geometry": {"coordinates":[-82.89842400000001,34.4669],"type":"Point"}
}