{
  "type": "Feature",
  "properties": {
    "iso:country":"US",
    "sg:address":"551 Stoneywood Trce",
    "sg:city":"Mableton",
    "sg:classifiers":[
        {
            "category":"Organizations",
            "subcategory":"Community Association",
            "type":"Services"
        }
    ],
    "sg:phone":"+1 770 944 8561",
    "sg:postcode":"30126",
    "sg:province":"GA",
    "wof:name":"Stoneybrook Owners Association",
    "wof:placetype":"venue"
},
  "geometry": {"coordinates":[-84.541467,33.826629],"type":"Point"}
}