{
  "type": "Feature",
  "properties": {
    "addr:full":"167 Joyce Dr Ringgold GA 30736",
    "addr:housenumber":"167",
    "addr:postcode":"30736",
    "addr:street":"Joyce Dr",
    "iso:country":"US",
    "sg:address":"167 Joyce Dr",
    "sg:city":"Ringgold",
    "sg:classifiers":[
        {
            "category":"Building & Trades",
            "subcategory":"Construction",
            "type":"Services"
        }
    ],
    "sg:phone":"+1 706 965 6585",
    "sg:postcode":"30736",
    "sg:province":"GA",
    "sg:tags":[
        "steel",
        "ventilated",
        "shelving",
        "installation"
    ],
    "wof:name":"Custom Closets By Tom",
    "wof:placetype":"venue"
},
  "geometry": {"coordinates":[-85.143871,34.924073],"type":"Point"}
}