{
  "type": "Feature",
  "properties": {
    "addr:full":"901 S Park St Carrollton GA 30117",
    "addr:housenumber":"901",
    "addr:postcode":"30117",
    "addr:street":"S Park St",
    "iso:country":"US",
    "sg:address":"901 S Park St",
    "sg:city":"Carrollton",
    "sg:classifiers":[
        {
            "category":"Travel",
            "subcategory":"Hotels & Motels",
            "type":"Entertainment"
        }
    ],
    "sg:phone":"+1 770 834 2001",
    "sg:postcode":"30117",
    "sg:province":"GA",
    "wof:name":"S B S",
    "wof:placetype":"venue"
},
  "geometry": {"coordinates":[-85.074851,33.563328],"type":"Point"}
}