{
  "type": "Feature",
  "properties": {
    "iso:country":"US",
    "sg:address":"1081 Iris Dr SE",
    "sg:city":"Conyers",
    "sg:classifiers":[
        {
            "category":"Restaurant",
            "type":"Food & Drink"
        }
    ],
    "sg:menulink":"http://www.allmenus.com/ga/conyers/216955-folks-southern-kitchen-/menu/",
    "sg:phone":"+1 770 922 2830",
    "sg:postcode":"30094",
    "sg:province":"GA",
    "sg:tags":[
        "american"
    ],
    "wof:name":"Folks Southern Kitchen ",
    "wof:placetype":"venue"
},
  "geometry": {"coordinates":[-84.01180600000001,33.65469],"type":"Point"}
}