{
  "type": "Feature",
  "properties": {
    "iso:country":"US",
    "sg:address":"119 W Central Ave",
    "sg:city":"Moultrie",
    "sg:classifiers":[
        {
            "category":"Professional",
            "subcategory":"Management & Consulting",
            "type":"Services"
        },
        {
            "category":"Professional",
            "subcategory":"Advertising",
            "type":"Services"
        }
    ],
    "sg:phone":"+1 229 985 9466",
    "sg:postcode":"31768",
    "sg:province":"GA",
    "sg:tags":[
        "marketing",
        "program",
        "consultant"
    ],
    "wof:name":"Prospex Inc",
    "wof:placetype":"venue"
},
  "geometry": {"coordinates":[-83.79015,31.179965],"type":"Point"}
}