{
  "type": "Feature",
  "properties": {
    "addr:full":"1020 Deer Chase Ct Stone Mountain GA 30088",
    "addr:housenumber":"1020",
    "addr:postcode":"30088",
    "addr:street":"Deer Chase Ct",
    "iso:country":"US",
    "sg:address":"1020 Deer Chase Ct",
    "sg:city":"Stone Mountain",
    "sg:classifiers":[
        {
            "category":"Wholesale",
            "subcategory":"Groceries",
            "type":"Manufacturing & Wholesale Goods"
        }
    ],
    "sg:phone":"+1 770 498 4673",
    "sg:postcode":"30088",
    "sg:province":"GA",
    "wof:name":"Duprees Bbq Service",
    "wof:placetype":"venue"
},
  "geometry": {"coordinates":[-84.183904,33.764773],"type":"Point"}
}