{
  "type": "Feature",
  "properties": {
    "addr:full":"1099 Johnson Ferry Rd Marietta GA 30068",
    "addr:housenumber":"1099",
    "addr:postcode":"30068",
    "addr:street":"Johnson Ferry Rd",
    "iso:country":"US",
    "sg:address":"1099 Johnson Ferry Rd",
    "sg:city":"Marietta",
    "sg:classifiers":[
        {
            "category":"Shopping",
            "subcategory":"Pharmacy",
            "type":"Retail Goods"
        }
    ],
    "sg:phone":"+1 770 971 6395",
    "sg:postcode":"30068",
    "sg:province":"GA",
    "wof:name":"CVS Pharmacy",
    "wof:placetype":"venue"
},
  "geometry": {"coordinates":[-84.414438,33.974606],"type":"Point"}
}