{
  "type": "Feature",
  "properties": {
    "iso:country":"US",
    "sg:address":"1215 Hightower Trl",
    "sg:city":"Atlanta",
    "sg:classifiers":[
        {
            "category":"Professional",
            "subcategory":"Advertising",
            "type":"Services"
        }
    ],
    "sg:phone":"+1 770 518 1000",
    "sg:postcode":"30350",
    "sg:province":"GA",
    "sg:tags":[
        "counselor"
    ],
    "sg:website":"www.kleberadvertising.com",
    "wof:name":"Kleber & Assoc Advertising",
    "wof:placetype":"venue"
},
  "geometry": {"coordinates":[-84.350739,33.987914],"type":"Point"}
}