{
  "type": "Feature",
  "properties": {
    "addr:full":"2906 Morehall Dr Augusta GA 30906",
    "addr:housenumber":"2906",
    "addr:postcode":"30906",
    "addr:street":"Morehall Dr",
    "iso:country":"US",
    "sg:address":"2906 Morehall Dr",
    "sg:city":"Augusta",
    "sg:classifiers":[
        {
            "category":"Social Services",
            "subcategory":"Child Care",
            "type":"Services"
        }
    ],
    "sg:phone":"+1 706 793 5116",
    "sg:postcode":"30906",
    "sg:province":"GA",
    "sg:tags":[
        "day"
    ],
    "wof:name":"Julias Day Care Ctr",
    "wof:placetype":"venue"
},
  "geometry": {"coordinates":[-82.074861,33.413471],"type":"Point"}
}