{
  "type": "Feature",
  "properties": {
    "addr:full":"3808 Oakcliff Industrial Ct Atlanta GA 30340",
    "addr:housenumber":"3808",
    "addr:postcode":"30340",
    "addr:street":"Oakcliff Industrial Ct",
    "iso:country":"US",
    "sg:address":"3808 Oakcliff Industrial Ct",
    "sg:city":"Atlanta",
    "sg:classifiers":[
        {
            "category":"Food & Beverages",
            "subcategory":"Groceries & Convenience Stores",
            "type":"Retail Goods"
        }
    ],
    "sg:phone":"+1 770 447 1220",
    "sg:postcode":"30340",
    "sg:province":"GA",
    "wof:name":"Bmb Southeast",
    "wof:placetype":"venue"
},
  "geometry": {"coordinates":[-84.250045,33.903803],"type":"Point"}
}