{
  "type": "Feature",
  "properties": {
    "iso:country":"US",
    "sg:address":"1015 Alpharetta Hwy",
    "sg:city":"Roswell",
    "sg:classifiers":[
        {
            "category":"Insurance",
            "subcategory":"Insurance Agent",
            "type":"Services"
        }
    ],
    "sg:phone":"+1 678 461 8399",
    "sg:postcode":"30075",
    "sg:province":"GA",
    "wof:name":"Charrua",
    "wof:placetype":"venue"
},
  "geometry": {"coordinates":[-84.35831899999999,34.027589],"type":"Point"}
}