{
  "type": "Feature",
  "properties": {
    "addr:full":"275 Pharr Rd NE Atlanta GA 30305",
    "addr:housenumber":"275",
    "addr:postcode":"30305",
    "addr:street":"Pharr Rd Ne",
    "iso:country":"US",
    "sg:address":"275 Pharr Rd NE",
    "sg:city":"Atlanta",
    "sg:classifiers":[
        {
            "category":"Building & Trades",
            "subcategory":"Electrical",
            "type":"Services"
        }
    ],
    "sg:phone":"+1 404 233 0482",
    "sg:postcode":"30305",
    "sg:province":"GA",
    "sg:tags":[
        "contractors-commercial",
        "industrial",
        "electrician",
        "electric",
        "contractor"
    ],
    "wof:name":"Eidson Bros Electric Co",
    "wof:placetype":"venue"
},
  "geometry": {"coordinates":[-84.378998,33.8372],"type":"Point"}
}