{
  "type": "Feature",
  "properties": {
    "iso:country":"US",
    "sg:address":"604 Cordell Dr",
    "sg:city":"Atlanta",
    "sg:classifiers":[
        {
            "category":"Professional",
            "type":"Services"
        }
    ],
    "sg:phone":"+1 404 762 0092",
    "sg:postcode":"30349",
    "sg:province":"GA",
    "sg:tags":[
        "establishment"
    ],
    "wof:name":"Brooks Berry Haynie & Assoc",
    "wof:placetype":"venue"
},
  "geometry": {"coordinates":[-84.409302,33.625675],"type":"Point"}
}