{
  "type": "Feature",
  "properties": {
    "addr:full":"738 Bovine Rd Sylvania GA 30467",
    "addr:housenumber":"738",
    "addr:postcode":"30467",
    "addr:street":"Bovine Rd",
    "iso:country":"US",
    "sg:address":"738 Bovine Rd",
    "sg:city":"Sylvania",
    "sg:classifiers":[
        {
            "category":"Building & Trades",
            "subcategory":"Construction",
            "type":"Services"
        }
    ],
    "sg:phone":"+1 912 863 4088",
    "sg:postcode":"30467",
    "sg:province":"GA",
    "sg:tags":[
        "general",
        "contractor"
    ],
    "wof:name":"Crews & Crews",
    "wof:placetype":"venue"
},
  "geometry": {"coordinates":[-81.56434299999999,32.71868],"type":"Point"}
}