{
  "type": "Feature",
  "properties": {
    "iso:country":"US",
    "sg:address":"2037 Whitesville St",
    "sg:city":"Lagrange",
    "sg:classifiers":[
        {
            "category":"Manufacturing",
            "subcategory":"Buildings",
            "type":"Manufacturing & Wholesale Goods"
        }
    ],
    "sg:phone":"+1 706 837 0021",
    "sg:postcode":"30240",
    "sg:province":"GA",
    "sg:tags":[
        "prefab"
    ],
    "wof:name":"Horton Homes Of Lagrange",
    "wof:placetype":"venue"
},
  "geometry": {"coordinates":[-85.029257,32.999279],"type":"Point"}
}