{
  "type": "Feature",
  "properties": {
    "iso:country":"US",
    "sg:address":"1600 Pinefield Cir",
    "sg:city":"Marietta",
    "sg:classifiers":[
        {
            "category":"Manufacturing",
            "subcategory":"Printing",
            "type":"Manufacturing & Wholesale Goods"
        }
    ],
    "sg:phone":"+1 770 517 3665",
    "sg:postcode":"30066",
    "sg:province":"GA",
    "sg:tags":[
        "lithographic",
        "printer",
        "commercial"
    ],
    "wof:name":"Business Cards Direct Inc",
    "wof:placetype":"venue"
},
  "geometry": {"coordinates":[-84.504037,34.074162],"type":"Point"}
}