{
  "type": "Feature",
  "properties": {
    "iso:country":"US",
    "sg:address":"73 N Main St",
    "sg:city":"Luthersville",
    "sg:classifiers":[
        {
            "category":"Home & Garden",
            "subcategory":"Furniture",
            "type":"Retail Goods"
        }
    ],
    "sg:phone":"+1 770 927 9300",
    "sg:postcode":"30251",
    "sg:province":"GA",
    "wof:name":"Shannon Country Store",
    "wof:placetype":"venue"
},
  "geometry": {"coordinates":[-84.747257,33.220857],"type":"Point"}
}