{
  "type": "Feature",
  "properties": {
    "addr:full":"368 Godley Rd Savannah GA 31407",
    "addr:housenumber":"368",
    "addr:postcode":"31407",
    "addr:street":"Godley Rd",
    "iso:country":"US",
    "sg:address":"368 Godley Rd",
    "sg:city":"Savannah",
    "sg:classifiers":[
        {
            "category":"Home & Garden",
            "subcategory":"Building Materials",
            "type":"Retail Goods"
        }
    ],
    "sg:phone":"+1 912 964 2681",
    "sg:postcode":"31407",
    "sg:province":"GA",
    "wof:name":"Lafarge Building Materials",
    "wof:placetype":"venue"
},
  "geometry": {"coordinates":[-81.19931800000001,32.166442],"type":"Point"}
}