{
  "type": "Feature",
  "properties": {
    "iso:country":"US",
    "sg:address":"1040 Martin Luther King Jr Dr",
    "sg:city":"Bainbridge",
    "sg:classifiers":[
        {
            "category":"Social Services",
            "subcategory":"Child Care",
            "type":"Services"
        }
    ],
    "sg:phone":"+1 229 243 1442",
    "sg:postcode":"39817",
    "sg:province":"GA",
    "sg:tags":[
        "day"
    ],
    "wof:name":"Bright Day and Evening CA",
    "wof:placetype":"venue"
},
  "geometry": {"coordinates":[-84.56218699999999,30.908141],"type":"Point"}
}