{
  "type": "Feature",
  "properties": {
    "addr:full":"2552 US Hwy 41 Valdosta GA 31601",
    "addr:housenumber":"2552",
    "addr:postcode":"31601",
    "addr:street":"Us Hwy 41",
    "iso:country":"US",
    "sg:address":"2552 US Hwy 41",
    "sg:city":"Valdosta",
    "sg:classifiers":[
        {
            "category":"Wholesale",
            "subcategory":"Auto Parts",
            "type":"Manufacturing & Wholesale Goods"
        }
    ],
    "sg:phone":"+1 229 242 2107",
    "sg:postcode":"31601",
    "sg:province":"GA",
    "sg:tags":[
        "material",
        "used"
    ],
    "wof:name":"Coffmans U Auto Parts & Towing",
    "wof:placetype":"venue"
},
  "geometry": {"coordinates":[-83.240106,30.793824],"type":"Point"}
}