{
  "type": "Feature",
  "properties": {
    "iso:country":"US",
    "sg:address":"1900 Spring Ave",
    "sg:city":"Atlanta",
    "sg:classifiers":[
        {
            "category":"Building & Trades",
            "subcategory":"Locksmith",
            "type":"Services"
        }
    ],
    "sg:phone":"+1 678 269 7282",
    "sg:postcode":"30344",
    "sg:province":"GA",
    "sg:tags":[
        "key"
    ],
    "wof:name":"7 Days Emergency Locksmith",
    "wof:placetype":"venue"
},
  "geometry": {"coordinates":[-84.45004900000001,33.687231],"type":"Point"}
}