{
  "type": "Feature",
  "properties": {
    "iso:country":"US",
    "sg:address":"5872 Buford Hwy NE",
    "sg:city":"Doraville",
    "sg:classifiers":[
        {
            "category":"Restaurant",
            "type":"Food & Drink"
        }
    ],
    "sg:phone":"+1 770 220 3013",
    "sg:postcode":"30340",
    "sg:province":"GA",
    "wof:name":"Harue",
    "wof:placetype":"venue"
},
  "geometry": {"coordinates":[-84.266007,33.909537],"type":"Point"}
}