{
  "type": "Feature",
  "properties": {
    "iso:country":"US",
    "sg:address":"948 Victoria Landing Dr",
    "sg:city":"Woodstock",
    "sg:classifiers":[
        {
            "category":"Professional",
            "subcategory":"Business Services",
            "type":"Services"
        }
    ],
    "sg:phone":"+1 770 928 0089",
    "sg:postcode":"30189",
    "sg:province":"GA",
    "wof:name":"Tfy & Associates Inc",
    "wof:placetype":"venue"
},
  "geometry": {"coordinates":[-84.60981099999999,34.148755],"type":"Point"}
}