{
  "type": "Feature",
  "properties": {
    "addr:full":"1105 5th Ave Albany GA 31707",
    "addr:housenumber":"1105",
    "addr:postcode":"31707",
    "addr:street":"5Th Ave",
    "iso:country":"US",
    "sg:address":"1105 5th Ave",
    "sg:city":"Albany",
    "sg:classifiers":[
        {
            "category":"Professional",
            "subcategory":"Advertising",
            "type":"Services"
        },
        {
            "category":"Shopping",
            "subcategory":"Crafts & Fabrics",
            "type":"Retail Goods"
        },
        {
            "category":"Professional",
            "subcategory":"Printing & Photocopies",
            "type":"Services"
        }
    ],
    "sg:phone":"+1 229 883 6677",
    "sg:postcode":"31707",
    "sg:province":"GA",
    "sg:tags":[
        "screen",
        "specialty",
        "trophies",
        "embroidery",
        "medal",
        "plaque"
    ],
    "sg:website":"http://www.advertisingwithlisa.com",
    "wof:name":"Advertising With Lisa",
    "wof:placetype":"venue"
},
  "geometry": {"coordinates":[-84.176107,31.59308],"type":"Point"}
}