{
  "type": "Feature",
  "properties": {
    "addr:full":"146 Acadian Dr Stockbridge GA 30281",
    "addr:housenumber":"146",
    "addr:postcode":"30281",
    "addr:street":"Acadian Dr",
    "iso:country":"US",
    "sg:address":"146 Acadian Dr",
    "sg:city":"Stockbridge",
    "sg:classifiers":[
        {
            "category":"Freight",
            "type":"Transportation"
        }
    ],
    "sg:phone":"+1 770 957 7194",
    "sg:postcode":"30281",
    "sg:province":"GA",
    "wof:name":"Boone Transport Inc",
    "wof:placetype":"venue"
},
  "geometry": {"coordinates":[-84.238519,33.493463],"type":"Point"}
}