{
  "type": "Feature",
  "properties": {
    "addr:full":"2785 Cruse Rd Lawrenceville GA 30044",
    "addr:housenumber":"2785",
    "addr:postcode":"30044",
    "addr:street":"Cruse Rd",
    "iso:country":"US",
    "sg:address":"2785 Cruse Rd",
    "sg:city":"Lawrenceville",
    "sg:classifiers":[
        {
            "category":"Restaurant",
            "type":"Food & Drink"
        }
    ],
    "sg:phone":"+1 770 923 7777",
    "sg:postcode":"30044",
    "sg:province":"GA",
    "sg:tags":[
        "mexican"
    ],
    "wof:name":"Restaurant Mexico Salvadoreno Genesis",
    "wof:placetype":"venue"
},
  "geometry": {"coordinates":[-84.087017,33.937608],"type":"Point"}
}