{
  "type": "Feature",
  "properties": {
    "addr:full":"149 Ralph Wommack Rd Hazlehurst GA 31539",
    "addr:housenumber":"149",
    "addr:postcode":"31539",
    "addr:street":"Ralph Wommack Rd",
    "iso:country":"US",
    "sg:address":"149 Ralph Wommack Rd",
    "sg:city":"Hazlehurst",
    "sg:phone":"+1 912 375 2621",
    "sg:postcode":"31539",
    "sg:province":"GA",
    "sg:tags":[
        "farm",
        "wheat",
        "tobacco",
        "soybean"
    ],
    "wof:name":"Pprooduce Place",
    "wof:placetype":"venue"
},
  "geometry": {"coordinates":[-82.552926,31.898846],"type":"Point"}
}