{
  "type": "Feature",
  "properties": {
    "addr:full":"165 Courtland St SE Atlanta GA 30303",
    "addr:housenumber":"165",
    "addr:postcode":"30303",
    "addr:street":"Courtland St Se",
    "iso:country":"US",
    "sg:address":"165 Courtland St SE",
    "sg:city":"Atlanta",
    "sg:classifiers":[
        {
            "category":"Travel",
            "subcategory":"Hotels & Motels",
            "type":"Entertainment"
        }
    ],
    "sg:phone":"+1 404 659 6500",
    "sg:postcode":"30303",
    "sg:province":"GA",
    "wof:name":"Radisson Inn",
    "wof:placetype":"venue"
},
  "geometry": {"coordinates":[-84.387,33.752006],"type":"Point"}
}