{
  "type": "Feature",
  "properties": {
    "iso:country":"US",
    "sg:address":"8975 Two Chop Rd",
    "sg:city":"Statesboro",
    "sg:classifiers":[
        {
            "category":"Farming",
            "subcategory":"Farm",
            "type":"Manufacturing & Wholesale Goods"
        }
    ],
    "sg:phone":"+1 912 865 2718",
    "sg:postcode":"30461",
    "sg:province":"GA",
    "wof:name":"Prince Farm Shop",
    "wof:placetype":"venue"
},
  "geometry": {"coordinates":[-81.81225499999999,32.57879],"type":"Point"}
}