{
  "type": "Feature",
  "properties": {
    "addr:full":"305 Monroe Rd Fitzgerald GA 31750",
    "addr:housenumber":"305",
    "addr:postcode":"31750",
    "addr:street":"Monroe Rd",
    "iso:country":"US",
    "sg:address":"305 Monroe Rd",
    "sg:city":"Fitzgerald",
    "sg:classifiers":[
        {
            "category":"Farming",
            "subcategory":"Farm",
            "type":"Manufacturing & Wholesale Goods"
        }
    ],
    "sg:phone":"+1 229 831 4102",
    "sg:postcode":"31750",
    "sg:province":"GA",
    "sg:tags":[
        "crop",
        "general"
    ],
    "wof:name":"Bart Bradley",
    "wof:placetype":"venue"
},
  "geometry": {"coordinates":[-83.368854,31.66897],"type":"Point"}
}