{
  "type": "Feature",
  "properties": {
    "addr:full":"1805 Normandie Ln Albany GA 31721",
    "addr:housenumber":"1805",
    "addr:postcode":"31721",
    "addr:street":"Normandie Ln",
    "iso:country":"US",
    "sg:address":"1805 Normandie Ln",
    "sg:city":"Albany",
    "sg:classifiers":[
        {
            "category":"Professional",
            "type":"Services"
        }
    ],
    "sg:phone":"+1 229 878 1806",
    "sg:postcode":"31721",
    "sg:province":"GA",
    "wof:name":"Dan J Perron",
    "wof:placetype":"venue"
},
  "geometry": {"coordinates":[-84.22213499999999,31.546438],"type":"Point"}
}