{
  "type": "Feature",
  "properties": {
    "iso:country":"US",
    "sg:address":"39 Lily Ln",
    "sg:city":"Ellijay",
    "sg:classifiers":[
        {
            "category":"Professional",
            "subcategory":"Management & Consulting",
            "type":"Services"
        }
    ],
    "sg:phone":"+1 706 636 3945",
    "sg:postcode":"30540",
    "sg:province":"GA",
    "sg:tags":[
        "training",
        "sales"
    ],
    "wof:name":"Learning Innovations",
    "wof:placetype":"venue"
},
  "geometry": {"coordinates":[-84.558159,34.657012],"type":"Point"}
}