{
  "type": "Feature",
  "properties": {
    "addr:full":"4545 Chappell Dr Valdosta GA 31605",
    "addr:housenumber":"4545",
    "addr:postcode":"31605",
    "addr:street":"Chappell Dr",
    "iso:country":"US",
    "sg:address":"4545 Chappell Dr",
    "sg:city":"Valdosta",
    "sg:classifiers":[
        {
            "category":"Personal",
            "type":"Services"
        }
    ],
    "sg:phone":"+1 229 247 4644",
    "sg:postcode":"31605",
    "sg:province":"GA",
    "sg:tags":[
        "costume"
    ],
    "wof:name":"Bouncin' Balloons & Costumes",
    "wof:placetype":"venue"
},
  "geometry": {"coordinates":[-83.24253299999999,30.965985],"type":"Point"}
}