{
  "type": "Feature",
  "properties": {
    "iso:country":"US",
    "sg:address":"790 Willard Adams Rd",
    "sg:city":"Douglas",
    "sg:classifiers":[
        {
            "category":"Professional",
            "type":"Services"
        }
    ],
    "sg:phone":"+1 912 384 7980",
    "sg:postcode":"31535",
    "sg:province":"GA",
    "wof:name":"David W Werntz",
    "wof:placetype":"venue"
},
  "geometry": {"coordinates":[-82.828929,31.46151],"type":"Point"}
}