{
  "type": "Feature",
  "properties": {
    "iso:country":"US",
    "sg:address":"3091 Liberty Church Rd",
    "sg:city":"White Plains",
    "sg:classifiers":[
        {
            "category":"Organizations",
            "subcategory":"Religious Organization",
            "type":"Services"
        }
    ],
    "sg:phone":"+1 706 467 3089",
    "sg:postcode":"30678",
    "sg:province":"GA",
    "sg:tags":[
        "church"
    ],
    "wof:name":"Liberty United Methodist Chr",
    "wof:placetype":"venue"
},
  "geometry": {"coordinates":[-83.140265,33.435057],"type":"Point"}
}