{
  "type": "Feature",
  "properties": {
    "iso:country":"US",
    "sg:address":"2117 Old Cornelia Hwy",
    "sg:city":"Gainesville",
    "sg:classifiers":[
        {
            "category":"Shopping",
            "subcategory":"Crafts & Fabrics",
            "type":"Retail Goods"
        }
    ],
    "sg:phone":"+1 770 532 1979",
    "sg:postcode":"30507",
    "sg:province":"GA",
    "wof:name":"Kinsey Enterprise",
    "wof:placetype":"venue"
},
  "geometry": {"coordinates":[-83.786428,34.31151],"type":"Point"}
}