{
  "type": "Feature",
  "properties": {
    "addr:full":"1711 Old Dean Forest Rd Savannah GA 31408",
    "addr:housenumber":"1711",
    "addr:postcode":"31408",
    "addr:street":"Old Dean Forest Rd",
    "iso:country":"US",
    "sg:address":"1711 Old Dean Forest Rd",
    "sg:city":"Savannah",
    "sg:classifiers":[
        {
            "category":"Building & Trades",
            "subcategory":"Equipment Rental",
            "type":"Services"
        }
    ],
    "sg:phone":"+1 912 966 0010",
    "sg:postcode":"31408",
    "sg:province":"GA",
    "wof:name":"Have Ice Will Travel",
    "wof:placetype":"venue"
},
  "geometry": {"coordinates":[-81.200084,32.071218],"type":"Point"}
}