{
  "type": "Feature",
  "properties": {
    "iso:country":"US",
    "sg:address":"135 Newton Ridge Dr",
    "sg:city":"Covington",
    "sg:classifiers":[
        {
            "category":"Personal",
            "type":"Services"
        },
        {
            "category":"Building & Trades",
            "subcategory":"Cleaning & Sanitation",
            "type":"Services"
        }
    ],
    "sg:phone":"+1 770 787 8606",
    "sg:postcode":"30014",
    "sg:province":"GA",
    "sg:tags":[
        "house",
        "washing",
        "cleaning-exterior"
    ],
    "wof:name":"Superior Paint Pressure W",
    "wof:placetype":"venue"
},
  "geometry": {"coordinates":[-83.777458,33.58717],"type":"Point"}
}