{
  "type": "Feature",
  "properties": {
    "addr:full":"488 Crawford St N E Dawson GA 39842",
    "addr:housenumber":"488",
    "addr:postcode":"39842",
    "addr:street":"Crawford St N E Dawson",
    "iso:country":"US",
    "sg:address":"488 Crawford St N E",
    "sg:city":"Dawson",
    "sg:classifiers":[
        {
            "category":"Education",
            "subcategory":"School",
            "type":"Public Place"
        }
    ],
    "sg:phone":"+1 229 995 2544",
    "sg:postcode":"39842",
    "sg:province":"GA",
    "sg:tags":[
        "middle"
    ],
    "wof:name":"Terrell Middle High School",
    "wof:placetype":"venue"
},
  "geometry": {"coordinates":[-84.43667600000001,31.777039],"type":"Point"}
}