{
  "type": "Feature",
  "properties": {
    "addr:full":"165 Cherokee Cir Cedartown GA 30125",
    "addr:housenumber":"165",
    "addr:postcode":"30125",
    "addr:street":"Cherokee Cir",
    "iso:country":"US",
    "sg:address":"165 Cherokee Cir",
    "sg:city":"Cedartown",
    "sg:classifiers":[
        {
            "category":"Manufacturing",
            "subcategory":"Printing",
            "type":"Manufacturing & Wholesale Goods"
        }
    ],
    "sg:phone":"+1 770 748 7025",
    "sg:postcode":"30125",
    "sg:province":"GA",
    "sg:tags":[
        "commercial"
    ],
    "wof:name":"Parker Printing & Graphic Arts",
    "wof:placetype":"venue"
},
  "geometry": {"coordinates":[-85.258804,34.043635],"type":"Point"}
}