{
  "type": "Feature",
  "properties": {
    "iso:country":"US",
    "sg:address":"1322 Choyce Johnson Rd",
    "sg:city":"Statham",
    "sg:classifiers":[
        {
            "category":"Farming",
            "subcategory":"Farm",
            "type":"Manufacturing & Wholesale Goods"
        }
    ],
    "sg:phone":"+1 770 725 5470",
    "sg:postcode":"30666",
    "sg:province":"GA",
    "sg:tags":[
        "crop",
        "general"
    ],
    "wof:name":"Twin Sycamore Farms Inc",
    "wof:placetype":"venue"
},
  "geometry": {"coordinates":[-83.600471,33.898496],"type":"Point"}
}