{
  "type": "Feature",
  "properties": {
    "addr:full":"2041 Kinderton Manor Dr Duluth GA 30097",
    "addr:housenumber":"2041",
    "addr:postcode":"30097",
    "addr:street":"Kinderton Manor Dr",
    "iso:country":"US",
    "sg:address":"2041 Kinderton Manor Dr",
    "sg:city":"Duluth",
    "sg:classifiers":[
        {
            "category":"Travel",
            "subcategory":"Hotels & Motels",
            "type":"Entertainment"
        }
    ],
    "sg:phone":"+1 770 623 9050",
    "sg:postcode":"30097",
    "sg:province":"GA",
    "sg:tags":[
        "operation"
    ],
    "wof:name":"Board Inn Inc",
    "wof:placetype":"venue"
},
  "geometry": {"coordinates":[-84.181054,34.032833],"type":"Point"}
}