{
  "type": "Feature",
  "properties": {
    "addr:full":"353 Timber Ridge Rd Senoia GA 30276",
    "addr:housenumber":"353",
    "addr:postcode":"30276",
    "addr:street":"Timber Ridge Rd",
    "iso:country":"US",
    "sg:address":"353 Timber Ridge Rd",
    "sg:city":"Senoia",
    "sg:classifiers":[
        {
            "category":"Airline",
            "type":"Transportation"
        }
    ],
    "sg:phone":"+1 706 538 6039",
    "sg:postcode":"30276",
    "sg:province":"GA",
    "sg:tags":[
        "courier",
        "air"
    ],
    "wof:name":"Heritage World Enterprise",
    "wof:placetype":"venue"
},
  "geometry": {"coordinates":[-84.5853,33.193267],"type":"Point"}
}