{
  "type": "Feature",
  "properties": {
    "iso:country":"US",
    "sg:address":"4300 Paces Ferry Rd SE",
    "sg:city":"Atlanta",
    "sg:classifiers":[
        {
            "category":"Shopping",
            "subcategory":"Clothing, Apparel, & Fashions",
            "type":"Retail Goods"
        }
    ],
    "sg:phone":"+1 770 333 6350",
    "sg:postcode":"30339",
    "sg:province":"GA",
    "sg:tags":[
        "furnishing"
    ],
    "wof:name":"WEBB Limited-Vinings",
    "wof:placetype":"venue"
},
  "geometry": {"coordinates":[-84.46590999999999,33.866155],"type":"Point"}
}