{
  "type": "Feature",
  "properties": {
    "addr:full":"2725 Hamilton Mill Rd Buford GA 30519",
    "addr:housenumber":"2725",
    "addr:postcode":"30519",
    "addr:street":"Hamilton Mill Rd",
    "iso:country":"US",
    "sg:address":"2725 Hamilton Mill Rd",
    "sg:city":"Buford",
    "sg:classifiers":[
        {
            "category":"Bars & Pubs",
            "type":"Food & Drink"
        }
    ],
    "sg:menulink":"http://www.allmenus.com/ga/dacula-rocky-creek/237075-barberitos/menu/",
    "sg:phone":"+1 770 945 1877",
    "sg:postcode":"30519",
    "sg:province":"GA",
    "sg:tags":[
        "mexican"
    ],
    "wof:name":"Barberitos",
    "wof:placetype":"venue"
},
  "geometry": {"coordinates":[-83.92167000000001,34.080788],"type":"Point"}
}