{
  "type": "Feature",
  "properties": {
    "iso:country":"US",
    "sg:address":"701 W Society Ave",
    "sg:city":"Albany",
    "sg:classifiers":[
        {
            "category":"Food & Beverages",
            "subcategory":"Groceries & Convenience Stores",
            "type":"Retail Goods"
        }
    ],
    "sg:phone":"+1 229 446 2396",
    "sg:postcode":"31701",
    "sg:province":"GA",
    "sg:tags":[
        "grocer"
    ],
    "wof:name":"Proxy Plus",
    "wof:placetype":"venue"
},
  "geometry": {"coordinates":[-84.166686,31.586073],"type":"Point"}
}