{
  "type": "Feature",
  "properties": {
    "addr:full":"104 Magnolia Rd Americus GA 31719",
    "addr:housenumber":"104",
    "addr:postcode":"31719",
    "addr:street":"Magnolia Rd",
    "iso:country":"US",
    "sg:address":"104 Magnolia Rd",
    "sg:city":"Americus",
    "sg:classifiers":[
        {
            "category":"Real Estate",
            "subcategory":"Real Estate Operator",
            "type":"Services"
        }
    ],
    "sg:phone":"+1 229 924 8466",
    "sg:postcode":"31719",
    "sg:province":"GA",
    "sg:tags":[
        "apartment"
    ],
    "wof:name":"Magnolia Village Apartments",
    "wof:placetype":"venue"
},
  "geometry": {"coordinates":[-84.29407999999999,32.127961],"type":"Point"}
}