{
  "type": "Feature",
  "properties": {
    "iso:country":"US",
    "sg:address":"1003 Windy Hill Rd SE",
    "sg:city":"Smyrna",
    "sg:classifiers":[
        {
            "category":"Professional",
            "subcategory":"Computer Services",
            "type":"Services"
        }
    ],
    "sg:phone":"+1 770 432 2194",
    "sg:postcode":"30080",
    "sg:province":"GA",
    "sg:tags":[
        "repair"
    ],
    "wof:name":"Tv-Analysts",
    "wof:placetype":"venue"
},
  "geometry": {"coordinates":[-84.52407100000001,33.89446],"type":"Point"}
}