{
  "type": "Feature",
  "properties": {
    "addr:full":"2467 Arkose Dr Marietta GA 30060",
    "addr:housenumber":"2467",
    "addr:postcode":"30060",
    "addr:street":"Arkose Dr",
    "iso:country":"US",
    "sg:address":"2467 Arkose Dr",
    "sg:city":"Marietta",
    "sg:classifiers":[
        {
            "category":"Manufacturing",
            "subcategory":"Lumber",
            "type":"Manufacturing & Wholesale Goods"
        }
    ],
    "sg:phone":"+1 770 432 5094",
    "sg:postcode":"30060",
    "sg:province":"GA",
    "sg:tags":[
        "attendant",
        "park"
    ],
    "wof:name":"John T Crist",
    "wof:placetype":"venue"
},
  "geometry": {"coordinates":[-84.57367499999999,33.892098],"type":"Point"}
}