{
  "type": "Feature",
  "properties": {
    "addr:full":"140 Hampton Woods Dr Fayetteville GA 30215",
    "addr:housenumber":"140",
    "addr:postcode":"30215",
    "addr:street":"Hampton Woods Dr",
    "iso:country":"US",
    "sg:address":"140 Hampton Woods Dr",
    "sg:city":"Fayetteville",
    "sg:classifiers":[
        {
            "category":"Building & Trades",
            "subcategory":"Construction",
            "type":"Services"
        }
    ],
    "sg:phone":"+1 770 460 8842",
    "sg:postcode":"30215",
    "sg:province":"GA",
    "sg:tags":[
        "house",
        "family"
    ],
    "wof:name":"Anco Construction & Dev",
    "wof:placetype":"venue"
},
  "geometry": {"coordinates":[-84.42774199999999,33.415387],"type":"Point"}
}