{
  "type": "Feature",
  "properties": {
    "addr:full":"25 Kirkland Ct Covington GA 30016",
    "addr:housenumber":"25",
    "addr:postcode":"30016",
    "addr:street":"Kirkland Ct",
    "iso:country":"US",
    "sg:address":"25 Kirkland Ct",
    "sg:city":"Covington",
    "sg:classifiers":[
        {
            "category":"Building & Trades",
            "subcategory":"Construction",
            "type":"Services"
        }
    ],
    "sg:phone":"+1 770 787 7971",
    "sg:postcode":"30016",
    "sg:province":"GA",
    "sg:tags":[
        "house",
        "contractor"
    ],
    "wof:name":"Reynolds Construction",
    "wof:placetype":"venue"
},
  "geometry": {"coordinates":[-83.93892700000001,33.590081],"type":"Point"}
}