{
  "type": "Feature",
  "properties": {
    "iso:country":"US",
    "sg:address":"3453 Peach Orchard Rd",
    "sg:city":"Augusta",
    "sg:classifiers":[
        {
            "category":"Personal",
            "subcategory":"Beauty Salon",
            "type":"Services"
        }
    ],
    "sg:phone":"+1 706 796 2777",
    "sg:postcode":"30906",
    "sg:province":"GA",
    "sg:tags":[
        "manicuring"
    ],
    "wof:name":"Falcon Nails",
    "wof:placetype":"venue"
},
  "geometry": {"coordinates":[-82.027079,33.389566],"type":"Point"}
}