{
  "type": "Feature",
  "properties": {
    "addr:full":"1550 Mulkey Rd SW Austell GA 30106",
    "addr:housenumber":"1550",
    "addr:postcode":"30106",
    "addr:street":"Mulkey Rd Sw",
    "iso:country":"US",
    "sg:address":"1550 Mulkey Rd SW",
    "sg:city":"Austell",
    "sg:classifiers":[
        {
            "category":"Health Services",
            "subcategory":"Doctor",
            "type":"Services"
        }
    ],
    "sg:phone":"+1 770 732 1137",
    "sg:postcode":"30106",
    "sg:province":"GA",
    "sg:tags":[
        "physician",
        "surgeon"
    ],
    "wof:name":"Atlanta West Dermatology",
    "wof:placetype":"venue"
},
  "geometry": {"coordinates":[-84.60118199999999,33.858435],"type":"Point"}
}