{
  "type": "Feature",
  "properties": {
    "addr:full":"680 Indian Trail Lilburn Rd NW Lilburn GA 30047",
    "addr:housenumber":"680",
    "addr:postcode":"30047",
    "addr:street":"Indian Trail Lilburn Rd Nw",
    "iso:country":"US",
    "sg:address":"680 Indian Trail Lilburn Rd NW",
    "sg:city":"Lilburn",
    "sg:classifiers":[
        {
            "category":"Building & Trades",
            "subcategory":"Cleaning & Sanitation",
            "type":"Services"
        }
    ],
    "sg:phone":"+1 678 280 0584",
    "sg:postcode":"30047",
    "sg:province":"GA",
    "sg:tags":[
        "janitor"
    ],
    "wof:name":"Martboyd Facility Management",
    "wof:placetype":"venue"
},
  "geometry": {"coordinates":[-84.14922799999999,33.901028],"type":"Point"}
}