{
  "type": "Feature",
  "properties": {
    "iso:country":"US",
    "sg:address":"3619 Braselton Hwy",
    "sg:city":"Dacula",
    "sg:classifiers":[
        {
            "category":"Health Services",
            "subcategory":"Doctor",
            "type":"Services"
        }
    ],
    "sg:phone":"+1 770 831 6602",
    "sg:postcode":"30019",
    "sg:province":"GA",
    "sg:tags":[
        "dentist"
    ],
    "wof:name":"Hamilton Mill Ctr For Oral",
    "wof:placetype":"venue"
},
  "geometry": {"coordinates":[-83.90214,34.06951],"type":"Point"}
}