{
  "type": "Feature",
  "properties": {
    "addr:full":"236 Oquinn Rd Surrency GA 31563",
    "addr:housenumber":"236",
    "addr:postcode":"31563",
    "addr:street":"Oquinn Rd",
    "iso:country":"US",
    "sg:address":"236 Oquinn Rd",
    "sg:city":"Surrency",
    "sg:classifiers":[
        {
            "category":"Farming",
            "subcategory":"Farm",
            "type":"Manufacturing & Wholesale Goods"
        }
    ],
    "sg:phone":"+1 912 367 3981",
    "sg:postcode":"31563",
    "sg:province":"GA",
    "sg:tags":[
        "crop",
        "general"
    ],
    "wof:name":"Harold A Turner",
    "wof:placetype":"venue"
},
  "geometry": {"coordinates":[-82.166466,31.580456],"type":"Point"}
}