{
  "type": "Feature",
  "properties": {
    "addr:full":"2010 Cobb Pkwy Kennesaw GA 30152",
    "addr:housenumber":"2010",
    "addr:postcode":"30152",
    "addr:street":"Cobb Pkwy",
    "iso:country":"US",
    "sg:address":"2010 Cobb Pkwy",
    "sg:city":"Kennesaw",
    "sg:classifiers":[
        {
            "category":"Wholesale",
            "subcategory":"Machinery & Supplies",
            "type":"Manufacturing & Wholesale Goods"
        }
    ],
    "sg:phone":"+1 770 794 1876",
    "sg:postcode":"30152",
    "sg:province":"GA",
    "sg:tags":[
        "equipment",
        "layer",
        "carpet"
    ],
    "wof:name":"Georgia Foam Recycling",
    "wof:placetype":"venue"
},
  "geometry": {"coordinates":[-84.601563,34.003619],"type":"Point"}
}