{
  "type": "Feature",
  "properties": {
    "addr:full":"2022 Hastings St Marietta GA 30062",
    "addr:housenumber":"2022",
    "addr:postcode":"30062",
    "addr:street":"Hastings St",
    "iso:country":"US",
    "sg:address":"2022 Hastings St",
    "sg:city":"Marietta",
    "sg:classifiers":[
        {
            "category":"Building & Trades",
            "subcategory":"Construction",
            "type":"Services"
        }
    ],
    "sg:phone":"+1 770 565 0245",
    "sg:postcode":"30062",
    "sg:province":"GA",
    "sg:tags":[
        "heavy"
    ],
    "wof:name":"Mobile Dredging & Pumping Co",
    "wof:placetype":"venue"
},
  "geometry": {"coordinates":[-84.44116200000001,33.997165],"type":"Point"}
}