{
  "type": "Feature",
  "properties": {
    "addr:full":"1568 Southlake Pkwy Morrow GA 30260",
    "addr:housenumber":"1568",
    "addr:postcode":"30260",
    "addr:street":"Southlake Pkwy",
    "iso:country":"US",
    "sg:address":"1568 Southlake Pkwy",
    "sg:city":"Morrow",
    "sg:classifiers":[
        {
            "category":"Shopping",
            "subcategory":"Department Store",
            "type":"Retail Goods"
        }
    ],
    "sg:phone":"+1 678 422 7420",
    "sg:postcode":"30260",
    "sg:province":"GA",
    "sg:website":"www.tuesdaymorning.com",
    "wof:name":"Tuesday Morning",
    "wof:placetype":"venue"
},
  "geometry": {"coordinates":[-84.33765099999999,33.572749],"type":"Point"}
}