{
  "type": "Feature",
  "properties": {
    "addr:full":"2025 Washington Rd Rayle GA 30660",
    "addr:housenumber":"2025",
    "addr:postcode":"30660",
    "addr:street":"Washington Rd",
    "iso:country":"US",
    "sg:address":"2025 Washington Rd",
    "sg:city":"Rayle",
    "sg:classifiers":[
        {
            "category":"Farming",
            "subcategory":"Farm",
            "type":"Manufacturing & Wholesale Goods"
        }
    ],
    "sg:phone":"+1 706 743 7023",
    "sg:postcode":"30660",
    "sg:province":"GA",
    "sg:tags":[
        "crop",
        "general"
    ],
    "wof:name":"Anderson Farms",
    "wof:placetype":"venue"
},
  "geometry": {"coordinates":[-83.01972600000001,33.814911],"type":"Point"}
}