{
  "type": "Feature",
  "properties": {
    "addr:full":"10835 Centennial Dr Alpharetta GA 30022",
    "addr:housenumber":"10835",
    "addr:postcode":"30022",
    "addr:street":"Centennial Dr",
    "iso:country":"US",
    "sg:address":"10835 Centennial Dr",
    "sg:city":"Alpharetta",
    "sg:classifiers":[
        {
            "category":"Professional",
            "subcategory":"Business Services",
            "type":"Services"
        }
    ],
    "sg:phone":"+1 678 339 9861",
    "sg:postcode":"30022",
    "sg:province":"GA",
    "wof:name":"Telcomp Consulting Group Inc",
    "wof:placetype":"venue"
},
  "geometry": {"coordinates":[-84.248707,34.035531],"type":"Point"}
}