{
  "type": "Feature",
  "properties": {
    "addr:full":"521 E Main St Canton GA 30114",
    "addr:housenumber":"521",
    "addr:postcode":"30114",
    "addr:street":"E Main St",
    "iso:country":"US",
    "sg:address":"521 E Main St",
    "sg:city":"Canton",
    "sg:classifiers":[
        {
            "category":"Professional",
            "subcategory":"Lawyer & Legal Services",
            "type":"Services"
        }
    ],
    "sg:phone":"+1 404 588 9568",
    "sg:postcode":"30114",
    "sg:province":"GA",
    "wof:name":"Thomas George Atty",
    "wof:placetype":"venue"
},
  "geometry": {"coordinates":[-84.48173800000001,34.236531],"type":"Point"}
}