{
  "type": "Feature",
  "properties": {
    "iso:country":"US",
    "sg:address":"1723 Canton Rd",
    "sg:city":"Marietta",
    "sg:classifiers":[
        {
            "category":"Retail",
            "subcategory":"Auto Repair",
            "type":"Services"
        }
    ],
    "sg:phone":"+1 770 425 0001",
    "sg:postcode":"30066",
    "sg:province":"GA",
    "sg:tags":[
        "repairing",
        "automobile"
    ],
    "wof:name":"Canton Road Car Care",
    "wof:placetype":"venue"
},
  "geometry": {"coordinates":[-84.52770200000001,33.992901],"type":"Point"}
}