{
  "type": "Feature",
  "properties": {
    "addr:full":"2267 Chimney Swift Cir Marietta GA 30062",
    "addr:housenumber":"2267",
    "addr:postcode":"30062",
    "addr:street":"Chimney Swift Cir",
    "iso:country":"US",
    "sg:address":"2267 Chimney Swift Cir",
    "sg:city":"Marietta",
    "sg:classifiers":[
        {
            "category":"Shopping",
            "subcategory":"Shoes",
            "type":"Retail Goods"
        }
    ],
    "sg:phone":"+1 770 578 0454",
    "sg:postcode":"30062",
    "sg:province":"GA",
    "wof:name":"Bill Roussarie",
    "wof:placetype":"venue"
},
  "geometry": {"coordinates":[-84.484948,33.993301],"type":"Point"}
}