{
  "type": "Feature",
  "properties": {
    "iso:country":"US",
    "sg:address":"1996 Dekalb Ave NE",
    "sg:city":"Atlanta",
    "sg:classifiers":[
        {
            "category":"Building & Trades",
            "subcategory":"Landscaping Services",
            "type":"Services"
        }
    ],
    "sg:phone":"+1 404 270 9909",
    "sg:postcode":"30307",
    "sg:province":"GA",
    "sg:tags":[
        "lawn",
        "maintenance",
        "grounds"
    ],
    "wof:name":"Strawcage",
    "wof:placetype":"venue"
},
  "geometry": {"coordinates":[-84.322311,33.76147],"type":"Point"}
}