{
  "type": "Feature",
  "properties": {
    "iso:country":"US",
    "sg:address":"1212 W Medical Park Rd",
    "sg:city":"Augusta",
    "sg:classifiers":[
        {
            "category":"Insurance",
            "subcategory":"Insurance Agent",
            "type":"Services"
        }
    ],
    "sg:phone":"+1 706 798 3244",
    "sg:postcode":"30909",
    "sg:province":"GA",
    "wof:name":"Delta Life Insurance Co",
    "wof:placetype":"venue"
},
  "geometry": {"coordinates":[-82.089415,33.482094],"type":"Point"}
}