{
  "type": "Feature",
  "properties": {
    "iso:country":"US",
    "sg:address":"250 Spring St NW",
    "sg:city":"Atlanta",
    "sg:classifiers":[
        {
            "category":"Wholesale",
            "subcategory":"Jewelry",
            "type":"Manufacturing & Wholesale Goods"
        },
        {
            "category":"Shopping",
            "subcategory":"Jewelry",
            "type":"Retail Goods"
        }
    ],
    "sg:phone":"+1 404 688 0788",
    "sg:postcode":"30303",
    "sg:province":"GA",
    "sg:tags":[
        "stone",
        "jeweler"
    ],
    "wof:name":"Universal Silver & Supplies",
    "wof:placetype":"venue"
},
  "geometry": {"coordinates":[-84.389,33.761299],"type":"Point"}
}