{
  "type": "Feature",
  "properties": {
    "addr:full":"735 Cobbham Rd Thomson GA 30824",
    "addr:housenumber":"735",
    "addr:postcode":"30824",
    "addr:street":"Cobbham Rd",
    "iso:country":"US",
    "sg:address":"735 Cobbham Rd",
    "sg:city":"Thomson",
    "sg:classifiers":[
        {
            "category":"Shopping",
            "subcategory":"Bicycles & Sporting Goods",
            "type":"Retail Goods"
        }
    ],
    "sg:phone":"+1 706 597 0430",
    "sg:postcode":"30824",
    "sg:province":"GA",
    "sg:tags":[
        "equipment",
        "saddlery",
        "equestrian"
    ],
    "wof:name":"Southern Stirrups Inc",
    "wof:placetype":"venue"
},
  "geometry": {"coordinates":[-82.494716,33.481191],"type":"Point"}
}