{
  "type": "Feature",
  "properties": {
    "addr:full":"4500 West Village Pl Ste 1011 Smyrna GA 30080",
    "addr:housenumber":"4500",
    "addr:postcode":"30080",
    "addr:street":"West Village Pl Ste 1011",
    "iso:country":"US",
    "sg:address":"4500 West Village Pl Ste 1011",
    "sg:city":"Smyrna",
    "sg:classifiers":[
        {
            "category":"Manufacturing",
            "subcategory":"Leather Goods",
            "type":"Manufacturing & Wholesale Goods"
        },
        {
            "category":"Shopping",
            "subcategory":"Shoes",
            "type":"Retail Goods"
        }
    ],
    "sg:phone":"+1 770 438 0173",
    "sg:postcode":"30080",
    "sg:province":"GA",
    "sg:tags":[
        "store"
    ],
    "sg:website":"www.paloshoes.com",
    "wof:name":"Palo's Shoe Gallery",
    "wof:placetype":"venue"
},
  "geometry": {"coordinates":[-84.49123899999999,33.844668],"type":"Point"}
}