{
  "type": "Feature",
  "properties": {
    "iso:country":"US",
    "sg:address":"89 McKenzie Dr",
    "sg:city":"Swainsboro",
    "sg:classifiers":[
        {
            "category":"Wholesale",
            "subcategory":"Machinery & Supplies",
            "type":"Manufacturing & Wholesale Goods"
        },
        {
            "category":"Manufacturing",
            "subcategory":"Tools & Machinery",
            "type":"Manufacturing & Wholesale Goods"
        }
    ],
    "sg:phone":"+1 478 237 2823",
    "sg:postcode":"30401",
    "sg:province":"GA",
    "sg:tags":[
        "equipment",
        "industrial",
        "grinder",
        "meat",
        "chopper"
    ],
    "wof:name":"Tim's Deer Processing",
    "wof:placetype":"venue"
},
  "geometry": {"coordinates":[-82.363173,32.630273],"type":"Point"}
}