{
  "type": "Feature",
  "properties": {
    "iso:country":"US",
    "sg:address":"3060 Bouldercrest Rd",
    "sg:city":"Ellenwood",
    "sg:classifiers":[
        {
            "category":"Place Of Worship",
            "subcategory":"Church",
            "type":"Public Place"
        }
    ],
    "sg:phone":"+1 404 241 2000",
    "sg:postcode":"30294",
    "sg:province":"GA",
    "sg:tags":[
        "churches-unity"
    ],
    "wof:name":"Atlanta Family Church",
    "wof:placetype":"venue"
},
  "geometry": {"coordinates":[-84.308151,33.670736],"type":"Point"}
}