{
  "type": "Feature",
  "properties": {
    "iso:country":"US",
    "sg:address":"1455 Ridgefield Dr",
    "sg:city":"Roswell",
    "sg:classifiers":[
        {
            "category":"Professional",
            "type":"Services"
        }
    ],
    "sg:phone":"+1 770 998 3430",
    "sg:postcode":"30075",
    "sg:province":"GA",
    "wof:name":"Ramsden & Ramsden Inc",
    "wof:placetype":"venue"
},
  "geometry": {"coordinates":[-84.390137,34.021104],"type":"Point"}
}