{
  "type": "Feature",
  "properties": {
    "iso:country":"US",
    "sg:address":"3888 Ashford Trl NE",
    "sg:city":"Atlanta",
    "sg:classifiers":[
        {
            "category":"Wholesale",
            "subcategory":"Non-durable Goods",
            "type":"Manufacturing & Wholesale Goods"
        },
        {
            "category":"Manufacturing",
            "subcategory":"Printing",
            "type":"Manufacturing & Wholesale Goods"
        }
    ],
    "sg:phone":"+1 770 455 6977",
    "sg:postcode":"30319",
    "sg:province":"GA",
    "sg:tags":[
        "plate",
        "name",
        "rep",
        "label",
        "decal",
        "advertising",
        "promotion"
    ],
    "wof:name":"Macco Label Company",
    "wof:placetype":"venue"
},
  "geometry": {"coordinates":[-84.32248800000001,33.906332],"type":"Point"}
}