{
  "type": "Feature",
  "properties": {
    "addr:full":"1890 Old Savannah Rd Augusta GA 30901",
    "addr:housenumber":"1890",
    "addr:postcode":"30901",
    "addr:street":"Old Savannah Rd",
    "iso:country":"US",
    "sg:address":"1890 Old Savannah Rd",
    "sg:city":"Augusta",
    "sg:classifiers":[
        {
            "category":"Wholesale",
            "subcategory":"Scrap",
            "type":"Manufacturing & Wholesale Goods"
        }
    ],
    "sg:phone":"+1 706 722 3154",
    "sg:postcode":"30901",
    "sg:province":"GA",
    "sg:tags":[
        "recycling",
        "center"
    ],
    "wof:name":"Temega Industrial Recycling",
    "wof:placetype":"venue"
},
  "geometry": {"coordinates":[-81.988136,33.449576],"type":"Point"}
}