{
  "type": "Feature",
  "properties": {
    "addr:full":"2734 Vernon Rd NW Atlanta GA 30305",
    "addr:housenumber":"2734",
    "addr:postcode":"30305",
    "addr:street":"Vernon Rd Nw",
    "iso:country":"US",
    "sg:address":"2734 Vernon Rd NW",
    "sg:city":"Atlanta",
    "sg:classifiers":[
        {
            "category":"Real Estate",
            "subcategory":"Real Estate Agent",
            "type":"Services"
        }
    ],
    "sg:phone":"+1 404 233 4727",
    "sg:postcode":"30305",
    "sg:province":"GA",
    "wof:name":"College Park Realestate LLC",
    "wof:placetype":"venue"
},
  "geometry": {"coordinates":[-84.391188,33.831827],"type":"Point"}
}