{
  "type": "Feature",
  "properties": {
    "addr:full":"104 Spaulding Ct Brunswick GA 31525",
    "addr:housenumber":"104",
    "addr:postcode":"31525",
    "addr:street":"Spaulding Ct",
    "iso:country":"US",
    "sg:address":"104 Spaulding Ct",
    "sg:city":"Brunswick",
    "sg:classifiers":[
        {
            "category":"Building & Trades",
            "subcategory":"Construction",
            "type":"Services"
        }
    ],
    "sg:phone":"+1 912 267 9880",
    "sg:postcode":"31525",
    "sg:province":"GA",
    "sg:tags":[
        "enclosure",
        "pool",
        "swimming"
    ],
    "wof:name":"Coastal Siding",
    "wof:placetype":"venue"
},
  "geometry": {"coordinates":[-81.45942599999999,31.242825],"type":"Point"}
}