{
  "type": "Feature",
  "properties": {
    "addr:full":"3655 Roswell Rd Atlanta GA 30342",
    "addr:housenumber":"3655",
    "addr:postcode":"30342",
    "addr:street":"Roswell Rd",
    "iso:country":"US",
    "sg:address":"3655 Roswell Rd",
    "sg:city":"Atlanta",
    "sg:classifiers":[
        {
            "category":"Food & Beverages",
            "subcategory":"Specialty",
            "type":"Retail Goods"
        }
    ],
    "sg:phone":"+1 404 261 8663",
    "sg:postcode":"30342",
    "sg:province":"GA",
    "sg:tags":[
        "herb"
    ],
    "wof:name":"Herb Shop",
    "wof:placetype":"venue"
},
  "geometry": {"coordinates":[-84.382649,33.855806],"type":"Point"}
}