{
  "type": "Feature",
  "properties": {
    "addr:full":"610 Ridge Ave S Tifton GA 31794",
    "addr:housenumber":"610",
    "addr:postcode":"31794",
    "addr:street":"Ridge Ave S",
    "iso:country":"US",
    "sg:address":"610 Ridge Ave S",
    "sg:city":"Tifton",
    "sg:classifiers":[
        {
            "category":"Building & Trades",
            "subcategory":"Construction",
            "type":"Services"
        }
    ],
    "sg:phone":"+1 229 387 9836",
    "sg:postcode":"31794",
    "sg:province":"GA",
    "sg:tags":[
        "house",
        "family"
    ],
    "wof:name":"Walkers Home Improv & Vin Sid",
    "wof:placetype":"venue"
},
  "geometry": {"coordinates":[-83.51630299999999,31.451135],"type":"Point"}
}