{
  "type": "Feature",
  "properties": {
    "addr:full":"440 Charter Blvd Macon GA 31210",
    "addr:housenumber":"440",
    "addr:postcode":"31210",
    "addr:street":"Charter Blvd",
    "iso:country":"US",
    "sg:address":"440 Charter Blvd",
    "sg:city":"Macon",
    "sg:classifiers":[
        {
            "category":"Shopping",
            "subcategory":"Pharmacy",
            "type":"Retail Goods"
        }
    ],
    "sg:phone":"+1 478 474 6767",
    "sg:postcode":"31210",
    "sg:province":"GA",
    "sg:tags":[
        "drug",
        "store"
    ],
    "wof:name":"Powell's Northside Pharmacy",
    "wof:placetype":"venue"
},
  "geometry": {"coordinates":[-83.693406,32.867242],"type":"Point"}
}