{
  "type": "Feature",
  "properties": {
    "iso:country":"US",
    "sg:address":"504 Finch Ct",
    "sg:city":"Woodstock",
    "sg:classifiers":[
        {
            "category":"Professional",
            "subcategory":"Business Services",
            "type":"Services"
        }
    ],
    "sg:phone":"+1 770 517 6593",
    "sg:postcode":"30188",
    "sg:province":"GA",
    "wof:name":"Communction Slutions Unlimited",
    "wof:placetype":"venue"
},
  "geometry": {"coordinates":[-84.529329,34.110153],"type":"Point"}
}