{
  "type": "Feature",
  "properties": {
    "addr:full":"3607 Parkway Ln NW Norcross GA 30092",
    "addr:housenumber":"3607",
    "addr:postcode":"30092",
    "addr:street":"Parkway Ln Nw",
    "iso:country":"US",
    "sg:address":"3607 Parkway Ln NW",
    "sg:city":"Norcross",
    "sg:classifiers":[
        {
            "category":"Retail",
            "subcategory":"Auto Rental",
            "type":"Services"
        }
    ],
    "sg:phone":"+1 770 447 8122",
    "sg:postcode":"30092",
    "sg:province":"GA",
    "sg:tags":[
        "equipment",
        "truck"
    ],
    "wof:name":"Ryder",
    "wof:placetype":"venue"
},
  "geometry": {"coordinates":[-84.23676399999999,33.959637],"type":"Point"}
}