{
  "type": "Feature",
  "properties": {
    "addr:full":"948 Broad St Augusta GA 30901",
    "addr:housenumber":"948",
    "addr:postcode":"30901",
    "addr:street":"Broad St",
    "iso:country":"US",
    "sg:address":"948 Broad St",
    "sg:city":"Augusta",
    "sg:classifiers":[
        {
            "category":"Building & Trades",
            "subcategory":"Construction",
            "type":"Services"
        }
    ],
    "sg:phone":"+1 706 724 1440",
    "sg:postcode":"30901",
    "sg:province":"GA",
    "sg:tags":[
        "home",
        "builder"
    ],
    "wof:name":"David's Custom Homes",
    "wof:placetype":"venue"
},
  "geometry": {"coordinates":[-81.96962499999999,33.476839],"type":"Point"}
}