{
  "type": "Feature",
  "properties": {
    "addr:full":"287 Chastain Rd NW Kennesaw GA 30144",
    "addr:housenumber":"287",
    "addr:postcode":"30144",
    "addr:street":"Chastain Rd Nw",
    "iso:country":"US",
    "sg:address":"287 Chastain Rd NW",
    "sg:city":"Kennesaw",
    "sg:classifiers":[
        {
            "category":"Building & Trades",
            "subcategory":"Pest Control",
            "type":"Services"
        }
    ],
    "sg:phone":"+1 770 698 6474",
    "sg:postcode":"30144",
    "sg:province":"GA",
    "wof:name":"Any Pest Inc",
    "wof:placetype":"venue"
},
  "geometry": {"coordinates":[-84.551498,34.034],"type":"Point"}
}