{
  "type": "Feature",
  "properties": {
    "addr:full":"611 W Oglethorpe Ave Savannah GA 31401",
    "addr:housenumber":"611",
    "addr:postcode":"31401",
    "addr:street":"W Oglethorpe Ave",
    "iso:country":"US",
    "sg:address":"611 W Oglethorpe Ave",
    "sg:city":"Savannah",
    "sg:classifiers":[
        {
            "category":"Travel",
            "subcategory":"Hotels & Motels",
            "type":"Entertainment"
        },
        {
            "category":"Travel",
            "subcategory":"Bed & Breakfast",
            "type":"Entertainment"
        }
    ],
    "sg:phone":"+1 912 232 2661",
    "sg:postcode":"31401",
    "sg:province":"GA",
    "sg:tags":[
        "inn",
        "lodging"
    ],
    "wof:name":"Thunderbird Inn",
    "wof:placetype":"venue"
},
  "geometry": {"coordinates":[-81.084864,32.074767],"type":"Point"}
}