{
  "type": "Feature",
  "properties": {
    "addr:full":"745 Hill St SE Atlanta GA 30315",
    "addr:housenumber":"745",
    "addr:postcode":"30315",
    "addr:street":"Hill St Se",
    "iso:country":"US",
    "sg:address":"745 Hill St SE",
    "sg:city":"Atlanta",
    "sg:classifiers":[
        {
            "category":"Health Services",
            "subcategory":"Nursing And Care Facility",
            "type":"Services"
        },
        {
            "category":"Health Services",
            "subcategory":"Health Practitioner",
            "type":"Services"
        }
    ],
    "sg:phone":"+1 404 213 3903",
    "sg:postcode":"30315",
    "sg:province":"GA",
    "sg:tags":[
        "home",
        "eldercare-home"
    ],
    "wof:name":"Total Solutions Group",
    "wof:placetype":"venue"
},
  "geometry": {"coordinates":[-84.378441,33.734123],"type":"Point"}
}