{
  "type": "Feature",
  "properties": {
    "iso:country":"US",
    "sg:address":"229 Peachtree St NE",
    "sg:city":"Atlanta",
    "sg:classifiers":[
        {
            "category":"Professional",
            "subcategory":"Management & Consulting",
            "type":"Services"
        }
    ],
    "sg:phone":"+1 404 525 6663",
    "sg:postcode":"30303",
    "sg:province":"GA",
    "sg:tags":[
        "consultant",
        "business"
    ],
    "wof:name":"Weidenbach & Associates Inc",
    "wof:placetype":"venue"
},
  "geometry": {"coordinates":[-84.387479,33.761282],"type":"Point"}
}