{
  "type": "Feature",
  "properties": {
    "iso:country":"US",
    "sg:address":"440 Flat Shoals Avenue SE",
    "sg:city":"Atlanta",
    "sg:classifiers":[
        {
            "category":"Health Services",
            "subcategory":"Dentist",
            "type":"Services"
        }
    ],
    "sg:phone":"+1 404 688 2223",
    "sg:postcode":"30316",
    "sg:province":"GA",
    "sg:website":"www.eastatlantadentalcare.com",
    "wof:name":"East Atlanta Dental Care Center",
    "wof:placetype":"venue"
},
  "geometry": {"coordinates":[-84.347551,33.742099],"type":"Point"}
}