{
  "type": "Feature",
  "properties": {
    "addr:full":"2113 Condor Dr Lawrenceville GA 30044",
    "addr:housenumber":"2113",
    "addr:postcode":"30044",
    "addr:street":"Condor Dr",
    "iso:country":"US",
    "sg:address":"2113 Condor Dr",
    "sg:city":"Lawrenceville",
    "sg:classifiers":[
        {
            "category":"Wholesale",
            "subcategory":"Non-durable Goods",
            "type":"Manufacturing & Wholesale Goods"
        }
    ],
    "sg:phone":"+1 770 962 8336",
    "sg:postcode":"30044",
    "sg:province":"GA",
    "sg:tags":[
        "merchandise-wholesale"
    ],
    "wof:name":"Handbags Import",
    "wof:placetype":"venue"
},
  "geometry": {"coordinates":[-84.06000299999999,33.940577],"type":"Point"}
}