{
  "type": "Feature",
  "properties": {
    "iso:country":"US",
    "sg:address":"4968 Snook Thompson Rd SE",
    "sg:city":"Oxford",
    "sg:classifiers":[
        {
            "category":"Retail",
            "subcategory":"Repair Shop",
            "type":"Services"
        }
    ],
    "sg:phone":"+1 678 313 2595",
    "sg:postcode":"30054",
    "sg:province":"GA",
    "sg:tags":[
        "refrigeration"
    ],
    "wof:name":"Maintenance Air",
    "wof:placetype":"venue"
},
  "geometry": {"coordinates":[-83.848681,33.71439],"type":"Point"}
}