{
  "type": "Feature",
  "properties": {
    "iso:country":"US",
    "sg:address":"2395 Wall St SE",
    "sg:city":"Conyers",
    "sg:classifiers":[
        {
            "category":"Professional",
            "type":"Services"
        }
    ],
    "sg:phone":"+1 770 922 6675",
    "sg:postcode":"30013",
    "sg:province":"GA",
    "sg:tags":[
        "establishment"
    ],
    "wof:name":"Gibraltar Square",
    "wof:placetype":"venue"
},
  "geometry": {"coordinates":[-83.978275,33.626113],"type":"Point"}
}