{
  "type": "Feature",
  "properties": {
    "addr:full":"310 N Selvidge St Dalton GA 30720",
    "addr:housenumber":"310",
    "addr:postcode":"30720",
    "addr:street":"N Selvidge St",
    "iso:country":"US",
    "sg:address":"310 N Selvidge St",
    "sg:city":"Dalton",
    "sg:classifiers":[
        {
            "category":"Social Services",
            "type":"Services"
        }
    ],
    "sg:phone":"+1 706 270 3091",
    "sg:postcode":"30720",
    "sg:province":"GA",
    "sg:tags":[
        "counseling"
    ],
    "wof:name":"Crossroads Counseling",
    "wof:placetype":"venue"
},
  "geometry": {"coordinates":[-84.969684,34.775901],"type":"Point"}
}