{
  "type": "Feature",
  "properties": {
    "iso:country":"US",
    "sg:address":"3333 W Hospital Avenue",
    "sg:city":"Atlanta",
    "sg:classifiers":[
        {
            "category":"Communications",
            "subcategory":"Newspaper",
            "type":"Services"
        }
    ],
    "sg:phone":"+1 770 458 9590",
    "sg:postcode":"30341",
    "sg:province":"GA",
    "sg:tags":[
        "print",
        "medium"
    ],
    "sg:website":"www.roxpublishing.com",
    "wof:name":"Rox Publishing",
    "wof:placetype":"venue"
},
  "geometry": {"coordinates":[-84.29477799999999,33.887332],"type":"Point"}
}