{
  "type": "Feature",
  "properties": {
    "iso:country":"US",
    "sg:address":"7037 State Rte 85",
    "sg:city":"Riverdale",
    "sg:classifiers":[
        {
            "category":"Shopping",
            "subcategory":"Computers & Home Electronics",
            "type":"Retail Goods"
        }
    ],
    "sg:phone":"+1 770 994 7300",
    "sg:postcode":"30274",
    "sg:province":"GA",
    "wof:name":"Sound Sensations",
    "wof:placetype":"venue"
},
  "geometry": {"coordinates":[-84.411812,33.581142],"type":"Point"}
}