{
  "type": "Feature",
  "properties": {
    "iso:country":"US",
    "sg:address":"5536 Jackson Trail Rd",
    "sg:city":"Hoschton",
    "sg:classifiers":[
        {
            "category":"Building & Trades",
            "subcategory":"Construction",
            "type":"Services"
        }
    ],
    "sg:phone":"+1 706 654 1136",
    "sg:postcode":"30548",
    "sg:province":"GA",
    "sg:tags":[
        "carpentry",
        "contractor"
    ],
    "wof:name":"Majors Cabinet Shop Inc",
    "wof:placetype":"venue"
},
  "geometry": {"coordinates":[-83.68781,34.065096],"type":"Point"}
}