{
  "type": "Feature",
  "properties": {
    "addr:full":"3225 Shallowford Rd NE Marietta GA 30062",
    "addr:housenumber":"3225",
    "addr:postcode":"30062",
    "addr:street":"Shallowford Rd Ne",
    "iso:country":"US",
    "sg:address":"3225 Shallowford Rd NE",
    "sg:city":"Marietta",
    "sg:classifiers":[
        {
            "category":"Banks & Credit Unions",
            "subcategory":"Investment Brokerage",
            "type":"Services"
        }
    ],
    "sg:phone":"+1 770 971 7117",
    "sg:postcode":"30062",
    "sg:province":"GA",
    "sg:tags":[
        "consultant",
        "planning",
        "financial"
    ],
    "wof:name":"Anovest Investment Advisers",
    "wof:placetype":"venue"
},
  "geometry": {"coordinates":[-84.452022,34.037372],"type":"Point"}
}