{
  "type": "Feature",
  "properties": {
    "iso:country":"US",
    "sg:address":"5393 Greenhedge Ct",
    "sg:city":"Stone Mountain",
    "sg:classifiers":[
        {
            "category":"Professional",
            "subcategory":"Management & Consulting",
            "type":"Services"
        }
    ],
    "sg:phone":"+1 770 498 3481",
    "sg:postcode":"30088",
    "sg:province":"GA",
    "sg:tags":[
        "small",
        "consultant",
        "business"
    ],
    "wof:name":"Sankofa Business Enterprises",
    "wof:placetype":"venue"
},
  "geometry": {"coordinates":[-84.16927800000001,33.769389],"type":"Point"}
}