{
  "type": "Feature",
  "properties": {
    "iso:country":"US",
    "sg:address":"118 South Ave",
    "sg:city":"Jonesboro",
    "sg:classifiers":[
        {
            "category":"Freight",
            "type":"Transportation"
        }
    ],
    "sg:phone":"+1 770 472 9786",
    "sg:postcode":"30236",
    "sg:province":"GA",
    "sg:tags":[
        "operator",
        "local",
        "trucking"
    ],
    "wof:name":"AGA Trucking Inc",
    "wof:placetype":"venue"
},
  "geometry": {"coordinates":[-84.35485,33.513904],"type":"Point"}
}