{
  "type": "Feature",
  "properties": {
    "addr:full":"217 Chickamauga Ave Rossville GA 30741",
    "addr:housenumber":"217",
    "addr:postcode":"30741",
    "addr:street":"Chickamauga Ave",
    "iso:country":"US",
    "sg:address":"217 Chickamauga Ave",
    "sg:city":"Rossville",
    "sg:classifiers":[
        {
            "category":"Shopping",
            "subcategory":"Used Merchandise",
            "type":"Retail Goods"
        }
    ],
    "sg:phone":"+1 706 861 2068",
    "sg:postcode":"30741",
    "sg:province":"GA",
    "sg:tags":[
        "pawnbroker"
    ],
    "wof:name":"Kat's Pawn Shop",
    "wof:placetype":"venue"
},
  "geometry": {"coordinates":[-85.28642600000001,34.98362],"type":"Point"}
}