{
  "type": "Feature",
  "properties": {
    "iso:country":"US",
    "sg:address":"83 Depot St",
    "sg:city":"Hartwell",
    "sg:classifiers":[
        {
            "category":"Arts & Performance",
            "subcategory":"Theater",
            "type":"Entertainment"
        }
    ],
    "sg:phone":"+1 706 376 5599",
    "sg:postcode":"30643",
    "sg:province":"GA",
    "wof:name":"Hart County Community Theatre",
    "wof:placetype":"venue"
},
  "geometry": {"coordinates":[-82.934031,34.352013],"type":"Point"}
}