{
  "type": "Feature",
  "properties": {
    "addr:full":"3105 Milledgeville Rd Augusta GA 30904",
    "addr:housenumber":"3105",
    "addr:postcode":"30904",
    "addr:street":"Milledgeville Rd",
    "iso:country":"US",
    "sg:address":"3105 Milledgeville Rd",
    "sg:city":"Augusta",
    "sg:classifiers":[
        {
            "category":"Organizations",
            "subcategory":"Religious Organization",
            "type":"Services"
        }
    ],
    "sg:phone":"+1 706 738 7245",
    "sg:postcode":"30904",
    "sg:province":"GA",
    "sg:tags":[
        "church"
    ],
    "wof:name":"Fairview Missionary Baptist",
    "wof:placetype":"venue"
},
  "geometry": {"coordinates":[-82.04442899999999,33.448189],"type":"Point"}
}