{
  "type": "Feature",
  "properties": {
    "iso:country":"US",
    "sg:address":"25 Dogwood Trl",
    "sg:city":"Senoia",
    "sg:classifiers":[
        {
            "category":"Professional",
            "subcategory":"Printing & Photocopies",
            "type":"Services"
        }
    ],
    "sg:phone":"+1 770 599 3267",
    "sg:postcode":"30276",
    "sg:province":"GA",
    "sg:tags":[
        "lithographer"
    ],
    "wof:name":"Peachtree Publishing & Printing",
    "wof:placetype":"venue"
},
  "geometry": {"coordinates":[-84.576369,33.320685],"type":"Point"}
}