{
  "type": "Feature",
  "properties": {
    "addr:full":"250 Great Southwest Pkwy SW Atlanta GA 30336",
    "addr:housenumber":"250",
    "addr:postcode":"30336",
    "addr:street":"Great Southwest Pkwy Sw",
    "iso:country":"US",
    "sg:address":"250 Great Southwest Pkwy SW",
    "sg:city":"Atlanta",
    "sg:classifiers":[
        {
            "category":"Retail",
            "subcategory":"Storage",
            "type":"Services"
        }
    ],
    "sg:phone":"+1 404 696 2254",
    "sg:postcode":"30336",
    "sg:province":"GA",
    "sg:tags":[
        "self"
    ],
    "sg:website":"http://www.poly-fil.com",
    "wof:name":"The Fairfield Processing Corporation",
    "wof:placetype":"venue"
},
  "geometry": {"coordinates":[-84.56245199999999,33.748152],"type":"Point"}
}