{
  "type": "Feature",
  "properties": {
    "addr:full":"2673 Richard Bennett Rd Crandall GA 30711",
    "addr:housenumber":"2673",
    "addr:postcode":"30711",
    "addr:street":"Richard Bennett Rd",
    "iso:country":"US",
    "sg:address":"2673 Richard Bennett Rd",
    "sg:city":"Crandall",
    "sg:classifiers":[
        {
            "category":"Building & Trades",
            "subcategory":"Landscaping Services",
            "type":"Services"
        }
    ],
    "sg:phone":"+1 706 264 4661",
    "sg:postcode":"30711",
    "sg:province":"GA",
    "sg:tags":[
        "excavation",
        "tree"
    ],
    "wof:name":"Top Notch Tree Service Experts",
    "wof:placetype":"venue"
},
  "geometry": {"coordinates":[-84.774705,34.945897],"type":"Point"}
}