{
  "type": "Feature",
  "properties": {
    "iso:country":"US",
    "sg:address":"1640 Powers Ferry Rd SE",
    "sg:city":"Marietta",
    "sg:classifiers":[
        {
            "category":"Professional",
            "subcategory":"Accounting & Tax Preparation",
            "type":"Services"
        }
    ],
    "sg:phone":"+1 770 953 0040",
    "sg:postcode":"30067",
    "sg:province":"GA",
    "sg:tags":[
        "accountant"
    ],
    "wof:name":"Gallagher Mark CPA",
    "wof:placetype":"venue"
},
  "geometry": {"coordinates":[-84.46550000000001,33.909901],"type":"Point"}
}