{
  "type": "Feature",
  "properties": {
    "iso:country":"US",
    "sg:address":"708 Ralston Creek Trl",
    "sg:city":"Ellijay",
    "sg:classifiers":[
        {
            "category":"Real Estate",
            "subcategory":"Real Estate Services",
            "type":"Services"
        }
    ],
    "sg:phone":"+1 706 636 3331",
    "sg:postcode":"30536",
    "sg:province":"GA",
    "sg:tags":[
        "inspection"
    ],
    "wof:name":"A-1 Home Inspection & Home",
    "wof:placetype":"venue"
},
  "geometry": {"coordinates":[-84.330709,34.701652],"type":"Point"}
}