{
  "type": "Feature",
  "properties": {
    "addr:full":"1135 Sandy Springs Ln Marietta GA 30062",
    "addr:housenumber":"1135",
    "addr:postcode":"30062",
    "addr:street":"Sandy Springs Ln",
    "iso:country":"US",
    "sg:address":"1135 Sandy Springs Ln",
    "sg:city":"Marietta",
    "sg:classifiers":[
        {
            "category":"Building & Trades",
            "subcategory":"Construction",
            "type":"Services"
        }
    ],
    "sg:phone":"+1 770 565 2649",
    "sg:postcode":"30062",
    "sg:province":"GA",
    "sg:tags":[
        "residential"
    ],
    "wof:name":"Rs Moore & Assoc",
    "wof:placetype":"venue"
},
  "geometry": {"coordinates":[-84.477493,33.978381],"type":"Point"}
}