{
  "type": "Feature",
  "properties": {
    "iso:country":"US",
    "sg:address":"395 Edna Dr",
    "sg:city":"Stockbridge",
    "sg:classifiers":[
        {
            "category":"Utilities",
            "subcategory":"Electric",
            "type":"Services"
        }
    ],
    "sg:phone":"+1 678 565 6190",
    "sg:postcode":"30281",
    "sg:province":"GA",
    "sg:tags":[
        "transformer"
    ],
    "wof:name":"Alpha-Solar Alternative Energy Solutions Inc.",
    "wof:placetype":"venue"
},
  "geometry": {"coordinates":[-84.238248,33.592477],"type":"Point"}
}