{
  "type": "Feature",
  "properties": {
    "iso:country":"US",
    "sg:address":"24 E Dawson St",
    "sg:city":"Cuthbert",
    "sg:classifiers":[
        {
            "category":"Banks & Credit Unions",
            "subcategory":"Financial Services",
            "type":"Services"
        }
    ],
    "sg:phone":"+1 229 732 6322",
    "sg:postcode":"39840",
    "sg:province":"GA",
    "sg:tags":[
        "loan",
        "financing"
    ],
    "wof:name":"Greene Finance Co Inc",
    "wof:placetype":"venue"
},
  "geometry": {"coordinates":[-84.783722,31.77014],"type":"Point"}
}