{
  "type": "Feature",
  "properties": {
    "iso:country":"US",
    "sg:address":"510 Flint Ave",
    "sg:city":"Albany",
    "sg:classifiers":[
        {
            "category":"Professional",
            "subcategory":"Management & Consulting",
            "type":"Services"
        }
    ],
    "sg:phone":"+1 229 432 2180",
    "sg:postcode":"31701",
    "sg:province":"GA",
    "sg:tags":[
        "security"
    ],
    "wof:name":"American Express",
    "wof:placetype":"venue"
},
  "geometry": {"coordinates":[-84.16166699999999,31.579902],"type":"Point"}
}