{
  "type": "Feature",
  "properties": {
    "addr:full":"3687 Chavers Pl Stone Mountain GA 30083",
    "addr:housenumber":"3687",
    "addr:postcode":"30083",
    "addr:street":"Chavers Pl",
    "iso:country":"US",
    "sg:address":"3687 Chavers Pl",
    "sg:city":"Stone Mountain",
    "sg:classifiers":[
        {
            "category":"Shopping",
            "type":"Retail Goods"
        }
    ],
    "sg:phone":"+1 404 292 4837",
    "sg:postcode":"30083",
    "sg:province":"GA",
    "sg:tags":[
        "sauna"
    ],
    "wof:name":"Wall Steam Sauna & Whirlpool",
    "wof:placetype":"venue"
},
  "geometry": {"coordinates":[-84.238361,33.789553],"type":"Point"}
}