{
  "type": "Feature",
  "properties": {
    "addr:full":"815 Osborne St St Marys GA 31558",
    "addr:housenumber":"815",
    "addr:postcode":"31558",
    "addr:street":"Osborne St",
    "iso:country":"US",
    "sg:address":"815 Osborne St",
    "sg:city":"St Marys",
    "sg:classifiers":[
        {
            "category":"Retail",
            "subcategory":"Auto Repair",
            "type":"Services"
        }
    ],
    "sg:phone":"+1 912 729 2210",
    "sg:postcode":"31558",
    "sg:province":"GA",
    "sg:tags":[
        "repairing",
        "automobile",
        "general"
    ],
    "wof:name":"Old Town Automotive",
    "wof:placetype":"venue"
},
  "geometry": {"coordinates":[-81.54605100000001,30.731721],"type":"Point"}
}