{
  "type": "Feature",
  "properties": {
    "iso:country":"US",
    "sg:address":"4429 S Main St",
    "sg:city":"Acworth",
    "sg:classifiers":[
        {
            "category":"Shopping",
            "subcategory":"Hobbies, Toys, & Games",
            "type":"Retail Goods"
        },
        {
            "category":"Personal",
            "subcategory":"Beauty Salon",
            "type":"Services"
        }
    ],
    "sg:phone":"+1 770 974 5611",
    "sg:postcode":"30101",
    "sg:province":"GA",
    "sg:tags":[
        "shop"
    ],
    "wof:name":"Alice's Wonderland",
    "wof:placetype":"venue"
},
  "geometry": {"coordinates":[-84.665537,34.060707],"type":"Point"}
}