{
  "type": "Feature",
  "properties": {
    "iso:country":"US",
    "sg:address":"609 Newnan St",
    "sg:city":"Carrollton",
    "sg:classifiers":[
        {
            "category":"Professional",
            "subcategory":"Lawyer & Legal Services",
            "type":"Services"
        }
    ],
    "sg:phone":"+1 770 838 1709",
    "sg:postcode":"30117",
    "sg:province":"GA",
    "sg:tags":[
        "attorney"
    ],
    "wof:name":"Kurt M Thomas PC",
    "wof:placetype":"venue"
},
  "geometry": {"coordinates":[-85.06871,33.58023],"type":"Point"}
}