{
  "type": "Feature",
  "properties": {
    "iso:country":"US",
    "sg:address":"183 Old College St",
    "sg:city":"Hamilton",
    "sg:classifiers":[
        {
            "category":"Autos & Motor Vehicles",
            "subcategory":"Auto Supplies",
            "type":"Retail Goods"
        }
    ],
    "sg:phone":"+1 706 628 4606",
    "sg:postcode":"31811",
    "sg:province":"GA",
    "wof:name":"J & A Tires & Service Center",
    "wof:placetype":"venue"
},
  "geometry": {"coordinates":[-84.86744899999999,32.740369],"type":"Point"}
}