{
  "type": "Feature",
  "properties": {
    "iso:country":"US",
    "sg:address":"226 Iris Glen",
    "sg:city":"Dallas",
    "sg:classifiers":[
        {
            "category":"Building & Trades",
            "subcategory":"Construction",
            "type":"Services"
        }
    ],
    "sg:phone":"+1 404 925 1101",
    "sg:postcode":"30157",
    "sg:province":"GA",
    "sg:tags":[
        "contractor"
    ],
    "wof:name":"A Plus Vinyl Siding",
    "wof:placetype":"venue"
},
  "geometry": {"coordinates":[-84.84354500000001,33.878606],"type":"Point"}
}