{
  "type": "Feature",
  "properties": {
    "addr:full":"1162 Moreland Avenue SE Atlanta GA 30316",
    "addr:housenumber":"1162",
    "addr:postcode":"30316",
    "addr:street":"Moreland Avenue Se",
    "iso:country":"US",
    "sg:address":"1162 Moreland Avenue SE",
    "sg:city":"Atlanta",
    "sg:classifiers":[
        {
            "category":"Utilities",
            "subcategory":"Mobile Phone",
            "type":"Services"
        },
        {
            "category":"Shopping",
            "subcategory":"Mobile Phones",
            "type":"Retail Goods"
        },
        {
            "category":"Communications",
            "type":"Services"
        }
    ],
    "sg:phone":"+1 404 627 0064",
    "sg:postcode":"30316",
    "sg:province":"GA",
    "sg:tags":[
        "systems-repair",
        "telephone",
        "equipment",
        "paging",
        "signaling",
        "cellular"
    ],
    "wof:name":"Southeast Wireless",
    "wof:placetype":"venue"
},
  "geometry": {"coordinates":[-84.34941499999999,33.722564],"type":"Point"}
}