{
  "type": "Feature",
  "properties": {
    "addr:full":"2204 Old Poor Robin Rd Sylvania GA 30467",
    "addr:housenumber":"2204",
    "addr:postcode":"30467",
    "addr:street":"Old Poor Robin Rd",
    "iso:country":"US",
    "sg:address":"2204 Old Poor Robin Rd",
    "sg:city":"Sylvania",
    "sg:classifiers":[
        {
            "category":"Transit Center",
            "subcategory":"Freight",
            "type":"Transportation"
        },
        {
            "category":"Freight",
            "type":"Transportation"
        }
    ],
    "sg:phone":"+1 912 531 8248",
    "sg:postcode":"30467",
    "sg:province":"GA",
    "sg:tags":[
        "trucking-motor",
        "trucking"
    ],
    "wof:name":"Buffalo Express",
    "wof:placetype":"venue"
},
  "geometry": {"coordinates":[-81.49869099999999,32.709097],"type":"Point"}
}