{
  "type": "Feature",
  "properties": {
    "addr:full":"501 Deer Run Way Woodstock GA 30189",
    "addr:housenumber":"501",
    "addr:postcode":"30189",
    "addr:street":"Deer Run Way",
    "iso:country":"US",
    "sg:address":"501 Deer Run Way",
    "sg:city":"Woodstock",
    "sg:classifiers":[
        {
            "category":"Shopping",
            "subcategory":"Bicycles & Sporting Goods",
            "type":"Retail Goods"
        }
    ],
    "sg:phone":"+1 770 928 4339",
    "sg:postcode":"30189",
    "sg:province":"GA",
    "wof:name":"Giglio Group",
    "wof:placetype":"venue"
},
  "geometry": {"coordinates":[-84.55184,34.136825],"type":"Point"}
}