{
  "type": "Feature",
  "properties": {
    "addr:full":"250 W Clinton St Gray GA 31032",
    "addr:housenumber":"250",
    "addr:postcode":"31032",
    "addr:street":"W Clinton St",
    "iso:country":"US",
    "sg:address":"250 W Clinton St",
    "sg:city":"Gray",
    "sg:classifiers":[
        {
            "category":"Building & Trades",
            "subcategory":"Plumbing",
            "type":"Services"
        }
    ],
    "sg:phone":"+1 478 986 2588",
    "sg:postcode":"31032",
    "sg:province":"GA",
    "sg:tags":[
        "conditioning",
        "air",
        "system",
        "contractor"
    ],
    "wof:name":"A D Select Svc",
    "wof:placetype":"venue"
},
  "geometry": {"coordinates":[-83.545117,33.005542],"type":"Point"}
}