{
  "type": "Feature",
  "properties": {
    "addr:full":"3776 Clairmont Rd Atlanta GA 30341",
    "addr:housenumber":"3776",
    "addr:postcode":"30341",
    "addr:street":"Clairmont Rd",
    "iso:country":"US",
    "sg:address":"3776 Clairmont Rd",
    "sg:city":"Atlanta",
    "sg:classifiers":[
        {
            "category":"Professional",
            "subcategory":"Lawyer & Legal Services",
            "type":"Services"
        }
    ],
    "sg:phone":"+1 770 274 2700",
    "sg:postcode":"30341",
    "sg:province":"GA",
    "sg:tags":[
        "clinic",
        "attorney"
    ],
    "wof:name":"Atlanta Injury Group",
    "wof:placetype":"venue"
},
  "geometry": {"coordinates":[-84.30948600000001,33.870544],"type":"Point"}
}