{
  "type": "Feature",
  "properties": {
    "iso:country":"US",
    "sg:address":"7238 Brittany Way",
    "sg:city":"Douglasville",
    "sg:classifiers":[
        {
            "category":"Retail",
            "subcategory":"Laundry & Dry Cleaning",
            "type":"Services"
        },
        {
            "category":"Building & Trades",
            "subcategory":"Cleaning & Sanitation",
            "type":"Services"
        }
    ],
    "sg:phone":"+1 404 242 7459",
    "sg:postcode":"30134",
    "sg:province":"GA",
    "sg:tags":[
        "carpet",
        "cleaner",
        "upholstery",
        "rug",
        "house"
    ],
    "wof:name":"Nat and Son Carpet Cleaning",
    "wof:placetype":"venue"
},
  "geometry": {"coordinates":[-84.73394999999999,33.777473],"type":"Point"}
}