{
  "type": "Feature",
  "properties": {
    "addr:full":"3121 Woodlawn Ave Columbus GA 31904",
    "addr:housenumber":"3121",
    "addr:postcode":"31904",
    "addr:street":"Woodlawn Ave",
    "iso:country":"US",
    "sg:address":"3121 Woodlawn Ave",
    "sg:city":"Columbus",
    "sg:classifiers":[
        {
            "category":"Building & Trades",
            "subcategory":"Cleaning & Sanitation",
            "type":"Services"
        }
    ],
    "sg:phone":"+1 706 653 1199",
    "sg:postcode":"31904",
    "sg:province":"GA",
    "sg:tags":[
        "maintenance"
    ],
    "wof:name":"Harris & Sons",
    "wof:placetype":"venue"
},
  "geometry": {"coordinates":[-84.966724,32.492471],"type":"Point"}
}