{
  "type": "Feature",
  "properties": {
    "addr:full":"713 Lookout Pointe NW Lawrenceville GA 30043",
    "addr:housenumber":"713",
    "addr:postcode":"30043",
    "addr:street":"Lookout Pointe Nw",
    "iso:country":"US",
    "sg:address":"713 Lookout Pointe NW",
    "sg:city":"Lawrenceville",
    "sg:classifiers":[
        {
            "category":"Local Transit",
            "type":"Transportation"
        }
    ],
    "sg:phone":"+1 770 513 8650",
    "sg:postcode":"30043",
    "sg:province":"GA",
    "sg:tags":[
        "automobile",
        "rental"
    ],
    "wof:name":"Brittingham Enterprises",
    "wof:placetype":"venue"
},
  "geometry": {"coordinates":[-84.03049300000001,33.983819],"type":"Point"}
}