{
  "type": "Feature",
  "properties": {
    "iso:country":"US",
    "sg:address":"2446 Sterling Manor Dr",
    "sg:city":"Buford",
    "sg:classifiers":[
        {
            "category":"Professional",
            "subcategory":"Management & Consulting",
            "type":"Services"
        },
        {
            "category":"Professional",
            "subcategory":"Advertising",
            "type":"Services"
        }
    ],
    "sg:phone":"+1 770 614 4892",
    "sg:postcode":"30518",
    "sg:province":"GA",
    "sg:tags":[
        "marketing",
        "program",
        "consultant"
    ],
    "wof:name":"R & D Marketing",
    "wof:placetype":"venue"
},
  "geometry": {"coordinates":[-84.01384,34.147552],"type":"Point"}
}