{
  "type": "Feature",
  "properties": {
    "addr:full":"306 Rome St Carrollton GA 30117",
    "addr:housenumber":"306",
    "addr:postcode":"30117",
    "addr:street":"Rome St",
    "iso:country":"US",
    "sg:address":"306 Rome St",
    "sg:city":"Carrollton",
    "sg:classifiers":[
        {
            "category":"Autos & Motor Vehicles",
            "subcategory":"Auto Supplies",
            "type":"Retail Goods"
        }
    ],
    "sg:phone":"+1 770 214 8264",
    "sg:postcode":"30117",
    "sg:province":"GA",
    "sg:tags":[
        "lube",
        "oil"
    ],
    "wof:name":"Automotive Machine Shop",
    "wof:placetype":"venue"
},
  "geometry": {"coordinates":[-85.074882,33.581474],"type":"Point"}
}