{
  "type": "Feature",
  "properties": {
    "iso:country":"US",
    "sg:address":"3087 Victory Dr",
    "sg:city":"Columbus",
    "sg:classifiers":[
        {
            "category":"Shopping",
            "subcategory":"Shoes",
            "type":"Retail Goods"
        }
    ],
    "sg:phone":"+1 706 687 7362",
    "sg:postcode":"31903",
    "sg:province":"GA",
    "wof:name":"Payless Shoe Source",
    "wof:placetype":"venue"
},
  "geometry": {"coordinates":[-84.960188,32.437778],"type":"Point"}
}