{
  "type": "Feature",
  "properties": {
    "iso:country":"US",
    "sg:address":"2122 Spring Creek Rd",
    "sg:city":"Decatur",
    "sg:classifiers":[
        {
            "category":"Wholesale",
            "subcategory":"Durable Goods & Equipment",
            "type":"Manufacturing & Wholesale Goods"
        }
    ],
    "sg:phone":"+1 404 929 6697",
    "sg:postcode":"30033",
    "sg:province":"GA",
    "sg:tags":[
        "exporter"
    ],
    "wof:name":"About Design Of The Home",
    "wof:placetype":"venue"
},
  "geometry": {"coordinates":[-84.302744,33.817328],"type":"Point"}
}