{
  "type": "Feature",
  "properties": {
    "addr:full":"1987 Scenic Hwy Ste 207 Snellville GA 30078",
    "addr:housenumber":"1987",
    "addr:postcode":"30078",
    "addr:street":"Scenic Hwy Ste 207",
    "iso:country":"US",
    "sg:address":"1987 Scenic Hwy Ste 207",
    "sg:city":"Snellville",
    "sg:classifiers":[
        {
            "category":"Arena",
            "subcategory":"Sports Club",
            "type":"Entertainment"
        }
    ],
    "sg:phone":"+1 770 985 0050",
    "sg:postcode":"30078",
    "sg:province":"GA",
    "sg:tags":[
        "martial art"
    ],
    "sg:website":"www.minterkarate.com",
    "wof:name":"Charles Minter Tae Kwon Do Karate",
    "wof:placetype":"venue"
},
  "geometry": {"coordinates":[-84.015353,33.869508],"type":"Point"}
}