{
  "type": "Feature",
  "properties": {
    "addr:full":"3092 Pio Nono Ave Macon GA 31206",
    "addr:housenumber":"3092",
    "addr:postcode":"31206",
    "addr:street":"Pio Nono Ave",
    "iso:country":"US",
    "sg:address":"3092 Pio Nono Ave",
    "sg:city":"Macon",
    "sg:classifiers":[
        {
            "category":"Banks & Credit Unions",
            "subcategory":"Bank",
            "type":"Services"
        }
    ],
    "sg:phone":"+1 478 781 7676",
    "sg:postcode":"31206",
    "sg:province":"GA",
    "sg:tags":[
        "mortgage",
        "loan",
        "broker",
        "real estate"
    ],
    "wof:name":"Land & Land Mortgage Corp",
    "wof:placetype":"venue"
},
  "geometry": {"coordinates":[-83.66298399999999,32.807166],"type":"Point"}
}