{
  "type": "Feature",
  "properties": {
    "addr:full":"965 E Piedmont Rd Marietta GA 30062",
    "addr:housenumber":"965",
    "addr:postcode":"30062",
    "addr:street":"E Piedmont Rd",
    "iso:country":"US",
    "sg:address":"965 E Piedmont Rd",
    "sg:city":"Marietta",
    "sg:classifiers":[
        {
            "category":"Banks & Credit Unions",
            "subcategory":"Bank",
            "type":"Services"
        }
    ],
    "sg:phone":"+1 770 382 4622",
    "sg:postcode":"30062",
    "sg:province":"GA",
    "sg:tags":[
        "mortgage"
    ],
    "wof:name":"GMAC",
    "wof:placetype":"venue"
},
  "geometry": {"coordinates":[-84.479842,33.975993],"type":"Point"}
}