{
  "type": "Feature",
  "properties": {
    "iso:country":"US",
    "sg:address":"811 Church St SE",
    "sg:city":"Smyrna",
    "sg:classifiers":[
        {
            "category":"Education",
            "subcategory":"Preschool",
            "type":"Public Place"
        },
        {
            "category":"Education",
            "subcategory":"School",
            "type":"Public Place"
        }
    ],
    "sg:phone":"+1 770 435 8858",
    "sg:postcode":"30080",
    "sg:province":"GA",
    "sg:tags":[
        "elementary"
    ],
    "wof:name":"Oxford Babies",
    "wof:placetype":"venue"
},
  "geometry": {"coordinates":[-84.530281,33.880688],"type":"Point"}
}