{
  "type": "Feature",
  "properties": {
    "iso:country":"US",
    "sg:address":"757 Craigtown Rd",
    "sg:city":"Ellijay",
    "sg:classifiers":[
        {
            "category":"Professional",
            "type":"Services"
        }
    ],
    "sg:phone":"+1 706 276 7842",
    "sg:postcode":"30540",
    "sg:province":"GA",
    "wof:name":"Barry C Kingsley",
    "wof:placetype":"venue"
},
  "geometry": {"coordinates":[-84.52101999999999,34.729761],"type":"Point"}
}