{
  "type": "Feature",
  "properties": {
    "iso:country":"US",
    "sg:address":"1708 Peachtree St NW",
    "sg:city":"Atlanta",
    "sg:classifiers":[
        {
            "category":"Health Services",
            "subcategory":"Clinic",
            "type":"Services"
        }
    ],
    "sg:phone":"+1 404 872 8065",
    "sg:postcode":"30309",
    "sg:province":"GA",
    "sg:tags":[
        "counseling",
        "mental"
    ],
    "wof:name":"Chafin Michael L",
    "wof:placetype":"venue"
},
  "geometry": {"coordinates":[-84.392601,33.8004],"type":"Point"}
}