{
  "type": "Feature",
  "properties": {
    "addr:full":"10950 Flat Shoals Rd Covington GA 30016",
    "addr:housenumber":"10950",
    "addr:postcode":"30016",
    "addr:street":"Flat Shoals Rd",
    "iso:country":"US",
    "sg:address":"10950 Flat Shoals Rd",
    "sg:city":"Covington",
    "sg:classifiers":[
        {
            "category":"Manufacturing",
            "subcategory":"Tools & Machinery",
            "type":"Manufacturing & Wholesale Goods"
        }
    ],
    "sg:phone":"+1 770 385 3478",
    "sg:postcode":"30016",
    "sg:province":"GA",
    "sg:tags":[
        "computer",
        "mfg"
    ],
    "wof:name":"Spheregear",
    "wof:placetype":"venue"
},
  "geometry": {"coordinates":[-83.870875,33.553493],"type":"Point"}
}