{
  "type": "Feature",
  "properties": {
    "iso:country":"US",
    "sg:address":"5192 McGinnis Ferry Rd",
    "sg:city":"Alpharetta",
    "sg:classifiers":[
        {
            "category":"Restaurant",
            "type":"Food & Drink"
        }
    ],
    "sg:phone":"+1 678 893 9000",
    "sg:postcode":"30005",
    "sg:province":"GA",
    "wof:name":"Oughtabee's",
    "wof:placetype":"venue"
},
  "geometry": {"coordinates":[-84.212018,34.098011],"type":"Point"}
}