{
  "type": "Feature",
  "properties": {
    "addr:full":"341 Fletcher St Thomasville GA 31792",
    "addr:housenumber":"341",
    "addr:postcode":"31792",
    "addr:street":"Fletcher St",
    "iso:country":"US",
    "sg:address":"341 Fletcher St",
    "sg:city":"Thomasville",
    "sg:classifiers":[
        {
            "category":"Government",
            "subcategory":"Office",
            "type":"Public Place"
        }
    ],
    "sg:phone":"+1 229 225 1057",
    "sg:postcode":"31792",
    "sg:province":"GA",
    "sg:tags":[
        "village"
    ],
    "sg:website":"www.rose.net",
    "wof:name":"City Of Thomasville",
    "wof:placetype":"venue"
},
  "geometry": {"coordinates":[-83.981345,30.833443],"type":"Point"}
}