{
  "type": "Feature",
  "properties": {
    "iso:country":"US",
    "sg:address":"10955 Jones Bridge Rd",
    "sg:city":"Alpharetta",
    "sg:classifiers":[
        {
            "category":"Recreation",
            "type":"Entertainment"
        }
    ],
    "sg:phone":"+1 770 667 1064",
    "sg:postcode":"30022",
    "sg:province":"GA",
    "sg:tags":[
        "martial",
        "arts",
        "instruction"
    ],
    "sg:website":"www.joecorley.com",
    "wof:name":"Joe Corley Karate",
    "wof:placetype":"venue"
},
  "geometry": {"coordinates":[-84.222887,34.046547],"type":"Point"}
}