{
  "type": "Feature",
  "properties": {
    "addr:full":"406 Jersey Rd Oxford GA 30054",
    "addr:housenumber":"406",
    "addr:postcode":"30054",
    "addr:street":"Jersey Rd",
    "iso:country":"US",
    "sg:address":"406 Jersey Rd",
    "sg:city":"Oxford",
    "sg:classifiers":[
        {
            "category":"Building & Trades",
            "subcategory":"Electrical",
            "type":"Services"
        }
    ],
    "sg:phone":"+1 770 784 0608",
    "sg:postcode":"30054",
    "sg:province":"GA",
    "sg:tags":[
        "electrical",
        "contractor"
    ],
    "wof:name":"Stewarts Electrical Services",
    "wof:placetype":"venue"
},
  "geometry": {"coordinates":[-83.848833,33.695004],"type":"Point"}
}