{
  "type": "Feature",
  "properties": {
    "addr:full":"5622 Central Church Rd Douglasville GA 30135",
    "addr:housenumber":"5622",
    "addr:postcode":"30135",
    "addr:street":"Church Rd",
    "iso:country":"US",
    "sg:address":"5622 Central Church Rd",
    "sg:city":"Douglasville",
    "sg:classifiers":[
        {
            "category":"Professional",
            "subcategory":"Accounting & Tax Preparation",
            "type":"Services"
        }
    ],
    "sg:phone":"+1 770 920 0811",
    "sg:postcode":"30135",
    "sg:province":"GA",
    "sg:tags":[
        "auditing",
        "bookkeeping"
    ],
    "wof:name":"S Marsha Bowen",
    "wof:placetype":"venue"
},
  "geometry": {"coordinates":[-84.75935200000001,33.70023],"type":"Point"}
}