{
  "type": "Feature",
  "properties": {
    "addr:full":"8008 Albany Hwy Millwood GA 31552",
    "addr:housenumber":"8008",
    "addr:postcode":"31552",
    "addr:street":"Albany Hwy",
    "iso:country":"US",
    "sg:address":"8008 Albany Hwy",
    "sg:city":"Millwood",
    "sg:classifiers":[
        {
            "category":"Organizations",
            "subcategory":"Religious Organization",
            "type":"Services"
        }
    ],
    "sg:phone":"+1 912 285 0175",
    "sg:postcode":"31552",
    "sg:province":"GA",
    "wof:name":"Millwood Baptist Church",
    "wof:placetype":"venue"
},
  "geometry": {"coordinates":[-82.659814,31.26764],"type":"Point"}
}