{
  "type": "Feature",
  "properties": {
    "iso:country":"US",
    "sg:address":"1740 Century Cir",
    "sg:city":"Atlanta",
    "sg:classifiers":[
        {
            "category":"Real Estate",
            "subcategory":"Real Estate Operator",
            "type":"Services"
        }
    ],
    "sg:phone":"+1 866 575 8110",
    "sg:postcode":"30345",
    "sg:province":"GA",
    "sg:tags":[
        "apartment"
    ],
    "sg:website":"www.gables.com",
    "wof:name":"Gables Century Center",
    "wof:placetype":"venue"
},
  "geometry": {"coordinates":[-84.310712,33.84795],"type":"Point"}
}