{
  "type": "Feature",
  "properties": {
    "iso:country":"US",
    "sg:address":"227 4th St NW",
    "sg:city":"Atlanta",
    "sg:classifiers":[
        {
            "category":"Organizations",
            "subcategory":"Membership Organization",
            "type":"Services"
        }
    ],
    "sg:phone":"+1 404 892 8007",
    "sg:postcode":"30313",
    "sg:province":"GA",
    "sg:tags":[
        "fraternal"
    ],
    "wof:name":"The Delta Tau Delta Fraternity",
    "wof:placetype":"venue"
},
  "geometry": {"coordinates":[-84.39443900000001,33.775845],"type":"Point"}
}