{
  "type": "Feature",
  "properties": {
    "iso:country":"US",
    "sg:address":"6052 Ga Highway 85",
    "sg:city":"Ellerslie",
    "sg:classifiers":[
        {
            "category":"Restaurant",
            "type":"Food & Drink"
        }
    ],
    "sg:phone":"+1 706 582 2629",
    "sg:postcode":"31807",
    "sg:province":"GA",
    "wof:name":"Ossahatchee Oyster Bar",
    "wof:placetype":"venue"
},
  "geometry": {"coordinates":[-84.77359800000001,32.655899],"type":"Point"}
}