{
  "type": "Feature",
  "properties": {
    "iso:country":"US",
    "sg:address":"102 Maplewood Ln",
    "sg:city":"Sylvester",
    "sg:classifiers":[
        {
            "category":"Building & Trades",
            "subcategory":"Landscaping Services",
            "type":"Services"
        }
    ],
    "sg:phone":"+1 229 777 0460",
    "sg:postcode":"31791",
    "sg:province":"GA",
    "sg:tags":[
        "landscape"
    ],
    "wof:name":"Brooks Landscaping Co",
    "wof:placetype":"venue"
},
  "geometry": {"coordinates":[-83.821905,31.539632],"type":"Point"}
}