{
  "type": "Feature",
  "properties": {
    "addr:full":"108 Gross St Glennville GA 30427",
    "addr:housenumber":"108",
    "addr:postcode":"30427",
    "addr:street":"Gross St",
    "iso:country":"US",
    "sg:address":"108 Gross St",
    "sg:city":"Glennville",
    "sg:classifiers":[
        {
            "category":"Professional",
            "type":"Services"
        }
    ],
    "sg:phone":"+1 912 654 9238",
    "sg:postcode":"30427",
    "sg:province":"GA",
    "sg:tags":[
        "establishment"
    ],
    "wof:name":"Deb's Attic Treasures",
    "wof:placetype":"venue"
},
  "geometry": {"coordinates":[-81.92735399999999,31.93847],"type":"Point"}
}