{
  "type": "Feature",
  "properties": {
    "addr:full":"401 Club Rd Buchanan GA 30113",
    "addr:housenumber":"401",
    "addr:postcode":"30113",
    "addr:street":"Club Rd",
    "iso:country":"US",
    "sg:address":"401 Club Rd",
    "sg:city":"Buchanan",
    "sg:classifiers":[
        {
            "category":"Real Estate",
            "subcategory":"Real Estate Operator",
            "type":"Services"
        }
    ],
    "sg:phone":"+1 770 646 7111",
    "sg:postcode":"30113",
    "sg:province":"GA",
    "sg:tags":[
        "apartment"
    ],
    "wof:name":"Kelly Foundation For Senior Living, Inc.",
    "wof:placetype":"venue"
},
  "geometry": {"coordinates":[-85.16884,33.836413],"type":"Point"}
}