{
  "type": "Feature",
  "properties": {
    "addr:full":"3557 Memorial Dr Decatur GA 30032",
    "addr:housenumber":"3557",
    "addr:postcode":"30032",
    "addr:street":"Memorial Dr",
    "iso:country":"US",
    "sg:address":"3557 Memorial Dr",
    "sg:city":"Decatur",
    "sg:classifiers":[
        {
            "category":"Food & Beverages",
            "subcategory":"Groceries & Convenience Stores",
            "type":"Retail Goods"
        }
    ],
    "sg:phone":"+1 404 288 0344",
    "sg:postcode":"30032",
    "sg:province":"GA",
    "wof:name":"Kashmir Inc",
    "wof:placetype":"venue"
},
  "geometry": {"coordinates":[-84.267899,33.754902],"type":"Point"}
}