{
  "type": "Feature",
  "properties": {
    "addr:full":"52 Nannie Ln Ringgold GA 30736",
    "addr:housenumber":"52",
    "addr:postcode":"30736",
    "addr:street":"Nannie Ln",
    "iso:country":"US",
    "sg:address":"52 Nannie Ln",
    "sg:city":"Ringgold",
    "sg:classifiers":[
        {
            "category":"Personal",
            "subcategory":"Beauty Salon",
            "type":"Services"
        }
    ],
    "sg:phone":"+1 706 965 3495",
    "sg:postcode":"30736",
    "sg:province":"GA",
    "sg:tags":[
        "shop"
    ],
    "wof:name":"Talk Of The Town Beauty Salon",
    "wof:placetype":"venue"
},
  "geometry": {"coordinates":[-85.182604,34.798613],"type":"Point"}
}