{
  "type": "Feature",
  "properties": {
    "iso:country":"US",
    "sg:address":"2635 Skidaway Rd",
    "sg:city":"Savannah",
    "sg:classifiers":[
        {
            "category":"Restaurant",
            "type":"Food & Drink"
        }
    ],
    "sg:menulink":"http://www.allmenus.com/ga/savannah/158413-arbys/menu/",
    "sg:phone":"+1 912 238 4601",
    "sg:postcode":"31404",
    "sg:province":"GA",
    "sg:tags":[
        "burger",
        "american"
    ],
    "wof:name":"Arby's",
    "wof:placetype":"venue"
},
  "geometry": {"coordinates":[-81.06424199999999,32.041646],"type":"Point"}
}