{
  "type": "Feature",
  "properties": {
    "addr:full":"798 Lafayette St Ringgold GA 30736",
    "addr:housenumber":"798",
    "addr:postcode":"30736",
    "addr:street":"Lafayette St",
    "iso:country":"US",
    "sg:address":"798 Lafayette St",
    "sg:city":"Ringgold",
    "sg:classifiers":[
        {
            "category":"Government",
            "subcategory":"Court House",
            "type":"Public Place"
        }
    ],
    "sg:phone":"+1 706 935 3114",
    "sg:postcode":"30736",
    "sg:province":"GA",
    "sg:tags":[
        "city"
    ],
    "wof:name":"Fort Oglethorpe Magistrate",
    "wof:placetype":"venue"
},
  "geometry": {"coordinates":[-85.111492,34.915183],"type":"Point"}
}