{
  "type": "Feature",
  "properties": {
    "addr:full":"4289 Memorial Dr Decatur GA 30032",
    "addr:housenumber":"4289",
    "addr:postcode":"30032",
    "addr:street":"Memorial Dr",
    "iso:country":"US",
    "sg:address":"4289 Memorial Dr",
    "sg:city":"Decatur",
    "sg:classifiers":[
        {
            "category":"Organizations",
            "subcategory":"Religious Organization",
            "type":"Services"
        }
    ],
    "sg:phone":"+1 404 508 1646",
    "sg:postcode":"30032",
    "sg:province":"GA",
    "wof:name":"Word Reconciliation Ministr",
    "wof:placetype":"venue"
},
  "geometry": {"coordinates":[-84.24869700000001,33.772927],"type":"Point"}
}