{
  "type": "Feature",
  "properties": {
    "addr:full":"1600 Maple St Carrollton GA 30118",
    "addr:housenumber":"1600",
    "addr:postcode":"30118",
    "addr:street":"Maple St",
    "iso:country":"US",
    "sg:address":"1600 Maple St",
    "sg:city":"Carrollton",
    "sg:classifiers":[
        {
            "category":"Professional",
            "type":"Services"
        }
    ],
    "sg:phone":"+1 770 832 0497",
    "sg:postcode":"30118",
    "sg:province":"GA",
    "wof:name":"Archer Western Contract",
    "wof:placetype":"venue"
},
  "geometry": {"coordinates":[-85.09665699999999,33.571106],"type":"Point"}
}