{
  "type": "Feature",
  "properties": {
    "addr:full":"105 S Jeff Davis Dr Fayetteville GA 30214",
    "addr:housenumber":"105",
    "addr:postcode":"30214",
    "addr:street":"S Jeff Davis Dr",
    "iso:country":"US",
    "sg:address":"105 S Jeff Davis Dr",
    "sg:city":"Fayetteville",
    "sg:classifiers":[
        {
            "category":"Retail",
            "subcategory":"Auto Repair",
            "type":"Services"
        }
    ],
    "sg:phone":"+1 770 461 6479",
    "sg:postcode":"30214",
    "sg:province":"GA",
    "sg:tags":[
        "wheel",
        "servicing-automotive",
        "balancing",
        "axle",
        "wheels-aligning",
        "alignment-frame",
        "brake"
    ],
    "wof:name":"Holt Alignment",
    "wof:placetype":"venue"
},
  "geometry": {"coordinates":[-84.44985800000001,33.446899],"type":"Point"}
}