{
  "type": "Feature",
  "properties": {
    "addr:full":"3940 Jonesboro Rd Union City GA 30291",
    "addr:housenumber":"3940",
    "addr:postcode":"30291",
    "addr:street":"Jonesboro Rd",
    "iso:country":"US",
    "sg:address":"3940 Jonesboro Rd",
    "sg:city":"Union City",
    "sg:classifiers":[
        {
            "category":"Shopping",
            "subcategory":"Pharmacy",
            "type":"Retail Goods"
        }
    ],
    "sg:phone":"+1 770 774 1161",
    "sg:postcode":"30291",
    "sg:province":"GA",
    "sg:tags":[
        "drugstore"
    ],
    "sg:website":"www.cvs.com",
    "wof:name":"Cvs Pharmacy",
    "wof:placetype":"venue"
},
  "geometry": {"coordinates":[-84.51763,33.562827],"type":"Point"}
}