{
  "type": "Feature",
  "properties": {
    "addr:full":"2567 Washington Rd Augusta GA 30904",
    "addr:housenumber":"2567",
    "addr:postcode":"30904",
    "addr:street":"Washington Rd",
    "iso:country":"US",
    "sg:address":"2567 Washington Rd",
    "sg:city":"Augusta",
    "sg:classifiers":[
        {
            "category":"Personal",
            "type":"Services"
        }
    ],
    "sg:phone":"+1 706 729 0070",
    "sg:postcode":"30904",
    "sg:province":"GA",
    "sg:tags":[
        "specializing",
        "banquet",
        "provides",
        "hall"
    ],
    "wof:name":"Events More By Trry Wick Assoc",
    "wof:placetype":"venue"
},
  "geometry": {"coordinates":[-82.019059,33.50643],"type":"Point"}
}