{
  "type": "Feature",
  "properties": {
    "iso:country":"US",
    "sg:address":"104 Kings Crest Blvd",
    "sg:city":"Perry",
    "sg:classifiers":[
        {
            "category":"Building & Trades",
            "subcategory":"Landscaping Services",
            "type":"Services"
        }
    ],
    "sg:phone":"+1 478 987 2981",
    "sg:postcode":"31069",
    "sg:province":"GA",
    "wof:name":"Lampleys Lawn Maintenance",
    "wof:placetype":"venue"
},
  "geometry": {"coordinates":[-83.788016,32.485864],"type":"Point"}
}