{
  "type": "Feature",
  "properties": {
    "iso:country":"US",
    "sg:address":"122 Forrester St NW",
    "sg:city":"Pelham",
    "sg:classifiers":[
        {
            "category":"Health Services",
            "subcategory":"Medical Lab",
            "type":"Services"
        }
    ],
    "sg:phone":"+1 229 294 3057",
    "sg:postcode":"31779",
    "sg:province":"GA",
    "sg:tags":[
        "laboratory",
        "dental"
    ],
    "wof:name":"Drake Dental Design",
    "wof:placetype":"venue"
},
  "geometry": {"coordinates":[-84.157984,31.128623],"type":"Point"}
}