{
  "type": "Feature",
  "properties": {
    "addr:full":"5160 Austell Rd Austell GA 30106",
    "addr:housenumber":"5160",
    "addr:postcode":"30106",
    "addr:street":"Austell Rd",
    "iso:country":"US",
    "sg:address":"5160 Austell Rd",
    "sg:city":"Austell",
    "sg:classifiers":[
        {
            "category":"Autos & Motor Vehicles",
            "subcategory":"Fuel & Gas Station",
            "type":"Retail Goods"
        }
    ],
    "sg:phone":"+1 770 941 7115",
    "sg:postcode":"30106",
    "sg:province":"GA",
    "sg:tags":[
        "convenience",
        "oil",
        "store"
    ],
    "sg:website":"www.shell.com",
    "wof:name":"Shell Food Mart",
    "wof:placetype":"venue"
},
  "geometry": {"coordinates":[-84.614304,33.828602],"type":"Point"}
}