{
  "type": "Feature",
  "properties": {
    "addr:full":"3205 Woodward Crossing Blvd Ste 200 Buford GA 30519",
    "addr:housenumber":"3205",
    "addr:postcode":"30519",
    "addr:street":"Woodward Crossing Blvd Ste 200",
    "iso:country":"US",
    "sg:address":"3205 Woodward Crossing Blvd Ste 200",
    "sg:city":"Buford",
    "sg:classifiers":[
        {
            "category":"Shopping",
            "subcategory":"Shoes",
            "type":"Retail Goods"
        }
    ],
    "sg:phone":"+1 678 482 5114",
    "sg:postcode":"30519",
    "sg:province":"GA",
    "sg:tags":[
        "store"
    ],
    "sg:website":"www.famousfootwear.com",
    "wof:name":"Famous Footwear",
    "wof:placetype":"venue"
},
  "geometry": {"coordinates":[-83.98114,34.069232],"type":"Point"}
}