{
  "type": "Feature",
  "properties": {
    "iso:country":"US",
    "sg:address":"2100 Parklake Dr NE",
    "sg:city":"Atlanta",
    "sg:classifiers":[
        {
            "category":"Banks & Credit Unions",
            "subcategory":"Investment Brokerage",
            "type":"Services"
        }
    ],
    "sg:phone":"+1 770 492 0642",
    "sg:postcode":"30345",
    "sg:province":"GA",
    "sg:tags":[
        "advisory",
        "financial"
    ],
    "wof:name":"Southern Atlantic Financial",
    "wof:placetype":"venue"
},
  "geometry": {"coordinates":[-84.249155,33.850806],"type":"Point"}
}