{
  "type": "Feature",
  "properties": {
    "iso:country":"US",
    "sg:address":"10994 Millarden Rd",
    "sg:city":"Woodbury",
    "sg:classifiers":[
        {
            "category":"Coffee & Tea",
            "type":"Food & Drink"
        },
        {
            "category":"Restaurant",
            "type":"Food & Drink"
        }
    ],
    "sg:phone":"+1 706 553 3601",
    "sg:postcode":"30293",
    "sg:province":"GA",
    "sg:tags":[
        "espresso"
    ],
    "wof:name":"Butcher Block-Takeout",
    "wof:placetype":"venue"
},
  "geometry": {"coordinates":[-84.57394499999999,32.985735],"type":"Point"}
}