{
  "type": "Feature",
  "properties": {
    "iso:country":"US",
    "sg:address":"4590 Buford Hwy",
    "sg:city":"Norcross",
    "sg:classifiers":[
        {
            "category":"Home & Garden",
            "subcategory":"Furniture",
            "type":"Retail Goods"
        }
    ],
    "sg:phone":"+1 770 416 6062",
    "sg:postcode":"30071",
    "sg:province":"GA",
    "sg:tags":[
        "mattress"
    ],
    "wof:name":"Atlanta Mattress Factory Sale",
    "wof:placetype":"venue"
},
  "geometry": {"coordinates":[-84.181934,33.963157],"type":"Point"}
}