{
  "type": "Feature",
  "properties": {
    "iso:country":"US",
    "sg:address":"1445 Cherokee Rd",
    "sg:city":"Winterville",
    "sg:classifiers":[
        {
            "category":"Professional",
            "type":"Services"
        }
    ],
    "sg:phone":"+1 706 742 8938",
    "sg:postcode":"30683",
    "sg:province":"GA",
    "wof:name":"William R Harris",
    "wof:placetype":"venue"
},
  "geometry": {"coordinates":[-83.298047,33.953934],"type":"Point"}
}