{
  "type": "Feature",
  "properties": {
    "addr:full":"2100 Roswell Rd Marietta GA 30062",
    "addr:housenumber":"2100",
    "addr:postcode":"30062",
    "addr:street":"Roswell Rd",
    "iso:country":"US",
    "sg:address":"2100 Roswell Rd",
    "sg:city":"Marietta",
    "sg:classifiers":[
        {
            "category":"Professional",
            "type":"Services"
        }
    ],
    "sg:phone":"+1 770 321 1624",
    "sg:postcode":"30062",
    "sg:province":"GA",
    "wof:name":"Atlanta Gormet Popcorn",
    "wof:placetype":"venue"
},
  "geometry": {"coordinates":[-84.48954500000001,33.968309],"type":"Point"}
}