{
  "type": "Feature",
  "properties": {
    "iso:country":"US",
    "sg:address":"1001 S Thornton Ave",
    "sg:city":"Dalton",
    "sg:classifiers":[
        {
            "category":"Real Estate",
            "subcategory":"Real Estate Operator",
            "type":"Services"
        }
    ],
    "sg:phone":"+1 706 277 3695",
    "sg:postcode":"30720",
    "sg:province":"GA",
    "sg:tags":[
        "building",
        "nonresidential"
    ],
    "wof:name":"Miami Club",
    "wof:placetype":"venue"
},
  "geometry": {"coordinates":[-84.971536,34.7637],"type":"Point"}
}