{
  "type": "Feature",
  "properties": {
    "addr:full":"3260 Railroad St Ellenwood GA 30294",
    "addr:housenumber":"3260",
    "addr:postcode":"30294",
    "addr:street":"Railroad St",
    "iso:country":"US",
    "sg:address":"3260 Railroad St",
    "sg:city":"Ellenwood",
    "sg:classifiers":[
        {
            "category":"Building & Trades",
            "subcategory":"Construction",
            "type":"Services"
        }
    ],
    "sg:phone":"+1 770 961 2740",
    "sg:postcode":"30294",
    "sg:province":"GA",
    "sg:tags":[
        "paving",
        "contractor"
    ],
    "sg:website":"www.gbtop.com",
    "wof:name":"Georgia Black Top Paving Inc",
    "wof:placetype":"venue"
},
  "geometry": {"coordinates":[-84.284605,33.608579],"type":"Point"}
}