{
  "type": "Feature",
  "properties": {
    "addr:full":"4505 Ashford Dunwoody Rd NE Atlanta GA 30346",
    "addr:housenumber":"4505",
    "addr:postcode":"30346",
    "addr:street":"Ashford Dunwoody Rd Ne",
    "iso:country":"US",
    "sg:address":"4505 Ashford Dunwoody Rd NE",
    "sg:city":"Atlanta",
    "sg:classifiers":[
        {
            "category":"Personal",
            "subcategory":"Day Spa",
            "type":"Services"
        }
    ],
    "sg:phone":"+1 404 255 7727",
    "sg:postcode":"30346",
    "sg:province":"GA",
    "sg:website":"www.spasydell.com",
    "wof:name":"Spa Sydell",
    "wof:placetype":"venue"
},
  "geometry": {"coordinates":[-84.33783699999999,33.923912],"type":"Point"}
}