{
  "type": "Feature",
  "properties": {
    "addr:full":"5926 Seville Dr Lake Park GA 31636",
    "addr:housenumber":"5926",
    "addr:postcode":"31636",
    "addr:street":"Seville Dr",
    "iso:country":"US",
    "sg:address":"5926 Seville Dr",
    "sg:city":"Lake Park",
    "sg:classifiers":[
        {
            "category":"Professional",
            "subcategory":"Lawyer & Legal Services",
            "type":"Services"
        }
    ],
    "sg:phone":"+1 229 559 5188",
    "sg:postcode":"31636",
    "sg:province":"GA",
    "sg:tags":[
        "attorney"
    ],
    "wof:name":"Joseph E Vallotton",
    "wof:placetype":"venue"
},
  "geometry": {"coordinates":[-83.18889299999999,30.69502],"type":"Point"}
}