{
  "type": "Feature",
  "properties": {
    "iso:country":"US",
    "sg:address":"4000 Dekalb Technology Pk",
    "sg:city":"Atlanta",
    "sg:classifiers":[
        {
            "category":"Shopping",
            "subcategory":"Computers & Home Electronics",
            "type":"Retail Goods"
        }
    ],
    "sg:phone":"+1 770 776 7670",
    "sg:postcode":"30340",
    "sg:province":"GA",
    "wof:name":"Video Central South",
    "wof:placetype":"venue"
},
  "geometry": {"coordinates":[-84.263226,33.892586],"type":"Point"}
}