{
  "type": "Feature",
  "properties": {
    "addr:full":"3760 Sixes Rd Ste 134 Canton GA 30114",
    "addr:housenumber":"3760",
    "addr:postcode":"30114",
    "addr:street":"Sixes Rd Ste 134",
    "iso:country":"US",
    "sg:address":"3760 Sixes Rd Ste 134",
    "sg:city":"Canton",
    "sg:phone":"+1 770 720 8268",
    "sg:postcode":"30114",
    "sg:province":"GA",
    "sg:website":"http://www.chinawokky.com",
    "wof:name":"China Wok",
    "wof:placetype":"venue"
},
  "geometry": {"coordinates":[-84.549843,34.177971],"type":"Point"}
}