{
  "type": "Feature",
  "properties": {
    "addr:full":"5505 Interstate North Pkwy Sandy Springs GA 30328",
    "addr:housenumber":"5505",
    "addr:postcode":"30328",
    "addr:street":"Interstate North Pkwy",
    "iso:country":"US",
    "sg:address":"5505 Interstate North Pkwy",
    "sg:city":"Sandy Springs",
    "sg:classifiers":[
        {
            "category":"Real Estate",
            "subcategory":"Developer",
            "type":"Services"
        }
    ],
    "sg:phone":"+1 770 952 2233",
    "sg:postcode":"30328",
    "sg:province":"GA",
    "wof:name":"JTH Realty Co",
    "wof:placetype":"venue"
},
  "geometry": {"coordinates":[-84.43804799999999,33.904144],"type":"Point"}
}