{
  "type": "Feature",
  "properties": {
    "addr:full":"1710 Macby Dr Marietta GA 30066",
    "addr:housenumber":"1710",
    "addr:postcode":"30066",
    "addr:street":"Macby Dr",
    "iso:country":"US",
    "sg:address":"1710 Macby Dr",
    "sg:city":"Marietta",
    "sg:classifiers":[
        {
            "category":"Building & Trades",
            "subcategory":"Construction",
            "type":"Services"
        }
    ],
    "sg:phone":"+1 770 321 5528",
    "sg:postcode":"30066",
    "sg:province":"GA",
    "sg:tags":[
        "house"
    ],
    "wof:name":"Serenity Remodeling LLC",
    "wof:placetype":"venue"
},
  "geometry": {"coordinates":[-84.499554,34.020417],"type":"Point"}
}