{
  "type": "Feature",
  "properties": {
    "addr:full":"1 Saint Andrews Ct Brunswick GA 31520",
    "addr:housenumber":"1",
    "addr:postcode":"31520",
    "addr:street":"Saint Andrews Ct",
    "iso:country":"US",
    "sg:address":"1 Saint Andrews Ct",
    "sg:city":"Brunswick",
    "sg:classifiers":[
        {
            "category":"Insurance",
            "subcategory":"Hazard Insurance",
            "type":"Services"
        }
    ],
    "sg:phone":"+1 912 265 2840",
    "sg:postcode":"31520",
    "sg:province":"GA",
    "sg:tags":[
        "commercial",
        "business"
    ],
    "wof:name":"Turner & Associates Insurance Inc",
    "wof:placetype":"venue"
},
  "geometry": {"coordinates":[-81.49839799999999,31.149765],"type":"Point"}
}