{
  "type": "Feature",
  "properties": {
    "iso:country":"US",
    "sg:address":"260 Hickory Ridge Rd",
    "sg:city":"Jackson",
    "sg:classifiers":[
        {
            "category":"Autos & Motor Vehicles",
            "subcategory":"Automobile Sales",
            "type":"Retail Goods"
        }
    ],
    "sg:phone":"+1 770 775 5901",
    "sg:postcode":"30233",
    "sg:province":"GA",
    "sg:tags":[
        "used"
    ],
    "wof:name":"Waldrop Auto Sales",
    "wof:placetype":"venue"
},
  "geometry": {"coordinates":[-83.95485600000001,33.280161],"type":"Point"}
}