{
  "type": "Feature",
  "properties": {
    "iso:country":"US",
    "sg:address":"2611 Keys Pointe SE",
    "sg:city":"Conyers",
    "sg:classifiers":[
        {
            "category":"Building & Trades",
            "subcategory":"Construction",
            "type":"Services"
        }
    ],
    "sg:phone":"+1 770 929 3436",
    "sg:postcode":"30013",
    "sg:province":"GA",
    "sg:tags":[
        "glass",
        "work"
    ],
    "wof:name":"Southeastern Glass & Metal",
    "wof:placetype":"venue"
},
  "geometry": {"coordinates":[-83.95618,33.632806],"type":"Point"}
}