{
  "type": "Feature",
  "properties": {
    "addr:full":"1250 Logan Cir NW Atlanta GA 30318",
    "addr:housenumber":"1250",
    "addr:postcode":"30318",
    "addr:street":"Logan Cir Nw",
    "iso:country":"US",
    "sg:address":"1250 Logan Cir NW",
    "sg:city":"Atlanta",
    "sg:classifiers":[
        {
            "category":"Shopping",
            "subcategory":"Stationery & Office Supplies",
            "type":"Retail Goods"
        },
        {
            "category":"Personal",
            "type":"Services"
        }
    ],
    "sg:phone":"+1 404 352 1401",
    "sg:postcode":"30318",
    "sg:province":"GA",
    "sg:tags":[
        "equipment",
        "mover"
    ],
    "wof:name":"Commercial Renlocation Specialist of Georgia",
    "wof:placetype":"venue"
},
  "geometry": {"coordinates":[-84.42925700000001,33.805454],"type":"Point"}
}