{
  "type": "Feature",
  "properties": {
    "iso:country":"US",
    "sg:address":"5000 Snapfinger Woods Dr",
    "sg:city":"Decatur",
    "sg:classifiers":[
        {
            "category":"Personal",
            "subcategory":"Beauty Salon",
            "type":"Services"
        }
    ],
    "sg:phone":"+1 770 817 0600",
    "sg:postcode":"30035",
    "sg:province":"GA",
    "wof:name":"Duckas Salon",
    "wof:placetype":"venue"
},
  "geometry": {"coordinates":[-84.18509,33.711206],"type":"Point"}
}