{
  "type": "Feature",
  "properties": {
    "iso:country":"US",
    "sg:address":"1141 Veterans Mmrl Hwy SW",
    "sg:city":"Mableton",
    "sg:classifiers":[
        {
            "category":"Deli",
            "type":"Food & Drink"
        }
    ],
    "sg:phone":"+1 770 944 3541",
    "sg:postcode":"30126",
    "sg:province":"GA",
    "wof:name":"Reid's Deli",
    "wof:placetype":"venue"
},
  "geometry": {"coordinates":[-84.587402,33.817501],"type":"Point"}
}