{
  "type": "Feature",
  "properties": {
    "iso:country":"US",
    "sg:address":"1410 State Rte 40",
    "sg:city":"Kingsland",
    "sg:classifiers":[
        {
            "category":"Education",
            "subcategory":"Library",
            "type":"Public Place"
        }
    ],
    "sg:phone":"+1 912 729 2040",
    "sg:postcode":"31548",
    "sg:province":"GA",
    "wof:name":"Camden Public Library",
    "wof:placetype":"venue"
},
  "geometry": {"coordinates":[-81.734747,30.807689],"type":"Point"}
}