{
  "type": "Feature",
  "properties": {
    "iso:country":"US",
    "sg:address":"4037 Flint Hill Rd",
    "sg:city":"Powder Springs",
    "sg:classifiers":[
        {
            "category":"Retail",
            "subcategory":"Auto Repair",
            "type":"Services"
        }
    ],
    "sg:phone":"+1 770 222 0848",
    "sg:postcode":"30127",
    "sg:province":"GA",
    "sg:tags":[
        "general"
    ],
    "wof:name":"Little Garage",
    "wof:placetype":"venue"
},
  "geometry": {"coordinates":[-84.639275,33.855972],"type":"Point"}
}