{
  "type": "Feature",
  "properties": {
    "addr:full":"1187 Riverside Dr Macon GA 31201",
    "addr:housenumber":"1187",
    "addr:postcode":"31201",
    "addr:street":"Riverside Dr",
    "iso:country":"US",
    "sg:address":"1187 Riverside Dr",
    "sg:city":"Macon",
    "sg:classifiers":[
        {
            "category":"Autos & Motor Vehicles",
            "subcategory":"Automobile Sales",
            "type":"Retail Goods"
        }
    ],
    "sg:phone":"+1 478 742 9971",
    "sg:postcode":"31201",
    "sg:province":"GA",
    "sg:tags":[
        "car",
        "used",
        "dealer"
    ],
    "wof:name":"Riverside Auto Sales LLC",
    "wof:placetype":"venue"
},
  "geometry": {"coordinates":[-83.63473999999999,32.846176],"type":"Point"}
}