{
  "type": "Feature",
  "properties": {
    "iso:country":"US",
    "sg:address":"947 Pine Roc Dr",
    "sg:city":"Stone Mountain",
    "sg:classifiers":[
        {
            "category":"Wholesale",
            "subcategory":"Electrical",
            "type":"Manufacturing & Wholesale Goods"
        }
    ],
    "sg:phone":"+1 770 413 6016",
    "sg:postcode":"30083",
    "sg:province":"GA",
    "sg:tags":[
        "alarm",
        "burglar",
        "system"
    ],
    "wof:name":"Front Line Security",
    "wof:placetype":"venue"
},
  "geometry": {"coordinates":[-84.179197,33.803752],"type":"Point"}
}