{
  "type": "Feature",
  "properties": {
    "iso:country":"US",
    "sg:address":"3274 Stone Mountain Hwy",
    "sg:city":"Snellville",
    "sg:classifiers":[
        {
            "category":"Retail",
            "subcategory":"Funeral Services",
            "type":"Services"
        }
    ],
    "sg:phone":"+1 770 972 3155",
    "sg:postcode":"30078",
    "sg:province":"GA",
    "sg:tags":[
        "cemetery"
    ],
    "wof:name":"Eternal Hills Funeral Home",
    "wof:placetype":"venue"
},
  "geometry": {"coordinates":[-84.0466,33.8494],"type":"Point"}
}