{
  "type": "Feature",
  "properties": {
    "iso:country":"US",
    "sg:address":"1711 River St",
    "sg:city":"Valdosta",
    "sg:classifiers":[
        {
            "category":"Shopping",
            "subcategory":"Pharmacy",
            "type":"Retail Goods"
        }
    ],
    "sg:phone":"+1 229 244 8868",
    "sg:postcode":"31601",
    "sg:province":"GA",
    "wof:name":"United Pharmacy Svc",
    "wof:placetype":"venue"
},
  "geometry": {"coordinates":[-83.318196,30.828495],"type":"Point"}
}