{
  "type": "Feature",
  "properties": {
    "addr:full":"544 Crosstown Rd Peachtree City GA 30269",
    "addr:housenumber":"544",
    "addr:postcode":"30269",
    "addr:street":"Crosstown Rd",
    "iso:country":"US",
    "sg:address":"544 Crosstown Rd",
    "sg:city":"Peachtree City",
    "sg:classifiers":[
        {
            "category":"Utilities",
            "subcategory":"Mobile Phone",
            "type":"Services"
        }
    ],
    "sg:phone":"+1 770 631 7966",
    "sg:postcode":"30269",
    "sg:province":"GA",
    "sg:tags":[
        "communication",
        "radiotelephone",
        "merchandise"
    ],
    "wof:name":"Cingular Wireless",
    "wof:placetype":"venue"
},
  "geometry": {"coordinates":[-84.557573,33.377398],"type":"Point"}
}