{
  "type": "Feature",
  "properties": {
    "iso:country":"US",
    "sg:address":"120 Mountain Brook Dr",
    "sg:city":"Canton",
    "sg:classifiers":[
        {
            "category":"Building & Trades",
            "subcategory":"Construction",
            "type":"Services"
        }
    ],
    "sg:phone":"+1 770 345 3500",
    "sg:postcode":"30115",
    "sg:province":"GA",
    "sg:tags":[
        "fire",
        "restoration",
        "damage",
        "contractor"
    ],
    "sg:website":"www.southeastrestoration.com",
    "wof:name":"Southeast Restoration",
    "wof:placetype":"venue"
},
  "geometry": {"coordinates":[-84.50562499999999,34.178868],"type":"Point"}
}