{
  "type": "Feature",
  "properties": {
    "addr:full":"6220 Oakdale Rd SE Mableton GA 30126",
    "addr:housenumber":"6220",
    "addr:postcode":"30126",
    "addr:street":"Oakdale Rd Se",
    "iso:country":"US",
    "sg:address":"6220 Oakdale Rd SE",
    "sg:city":"Mableton",
    "sg:classifiers":[
        {
            "category":"Building & Trades",
            "subcategory":"Landscaping Services",
            "type":"Services"
        }
    ],
    "sg:phone":"+1 404 447 5934",
    "sg:postcode":"30126",
    "sg:province":"GA",
    "sg:tags":[
        "lawn",
        "maintenance"
    ],
    "wof:name":"Quality Landscaping & Pressure Washing Services",
    "wof:placetype":"venue"
},
  "geometry": {"coordinates":[-84.51361199999999,33.800977],"type":"Point"}
}