{
  "type": "Feature",
  "properties": {
    "addr:full":"103 N Camellia Blvd Fort Valley GA 31030",
    "addr:housenumber":"103",
    "addr:postcode":"31030",
    "addr:street":"N Camellia Blvd Fort Valley",
    "iso:country":"US",
    "sg:address":"103 N Camellia Blvd",
    "sg:city":"Fort Valley",
    "sg:classifiers":[
        {
            "category":"Restaurant",
            "type":"Food & Drink"
        }
    ],
    "sg:menulink":"http://www.allmenus.com/ga/fort-valley/241874-china-house/menu/",
    "sg:phone":"+1 478 825 1473",
    "sg:postcode":"31030",
    "sg:province":"GA",
    "sg:tags":[
        "asian",
        "chinese"
    ],
    "wof:name":"China House",
    "wof:placetype":"venue"
},
  "geometry": {"coordinates":[-83.885182,32.556003],"type":"Point"}
}