{
  "type": "Feature",
  "properties": {
    "addr:full":"3706 Beardsley Ml NW Kennesaw GA 30144",
    "addr:housenumber":"3706",
    "addr:postcode":"30144",
    "addr:street":"Beardsley Ml Nw",
    "iso:country":"US",
    "sg:address":"3706 Beardsley Ml NW",
    "sg:city":"Kennesaw",
    "sg:classifiers":[
        {
            "category":"Organizations",
            "subcategory":"Non-profit Organization",
            "type":"Services"
        }
    ],
    "sg:phone":"+1 770 420 9120",
    "sg:postcode":"30144",
    "sg:province":"GA",
    "sg:tags":[
        "social"
    ],
    "wof:name":"Medseek Inc",
    "wof:placetype":"venue"
},
  "geometry": {"coordinates":[-84.63030999999999,34.046523],"type":"Point"}
}