{
  "type": "Feature",
  "properties": {
    "iso:country":"US",
    "sg:address":"14 N Court Sq",
    "sg:city":"Newnan",
    "sg:classifiers":[
        {
            "category":"Shopping",
            "subcategory":"Jewelry",
            "type":"Retail Goods"
        }
    ],
    "sg:phone":"+1 770 253 2720",
    "sg:postcode":"30263",
    "sg:province":"GA",
    "sg:tags":[
        "jeweler"
    ],
    "wof:name":"Morgan Jewelers Inc",
    "wof:placetype":"venue"
},
  "geometry": {"coordinates":[-84.800313,33.375279],"type":"Point"}
}