{
  "type": "Feature",
  "properties": {
    "addr:full":"1909 US Hwy 341 Jesup GA 31546",
    "addr:housenumber":"1909",
    "addr:postcode":"31546",
    "addr:street":"Us Hwy 341",
    "iso:country":"US",
    "sg:address":"1909 US Hwy 341",
    "sg:city":"Jesup",
    "sg:classifiers":[
        {
            "category":"Manufacturing",
            "subcategory":"Furniture",
            "type":"Manufacturing & Wholesale Goods"
        }
    ],
    "sg:phone":"+1 912 530 7530",
    "sg:postcode":"31546",
    "sg:province":"GA",
    "sg:tags":[
        "mfg",
        "cabinet"
    ],
    "wof:name":"Altamaha Cabinet",
    "wof:placetype":"venue"
},
  "geometry": {"coordinates":[-81.85390599999999,31.581266],"type":"Point"}
}