{
  "type": "Feature",
  "properties": {
    "addr:full":"300 Cline Ave Milledgeville GA 31061",
    "addr:housenumber":"300",
    "addr:postcode":"31061",
    "addr:street":"Cline Ave",
    "iso:country":"US",
    "sg:address":"300 Cline Ave",
    "sg:city":"Milledgeville",
    "sg:classifiers":[
        {
            "category":"Health Services",
            "subcategory":"Doctor",
            "type":"Services"
        }
    ],
    "sg:phone":"+1 478 452 5164",
    "sg:postcode":"31061",
    "sg:province":"GA",
    "sg:tags":[
        "dentist"
    ],
    "wof:name":"J T Curry DDS",
    "wof:placetype":"venue"
},
  "geometry": {"coordinates":[-83.21804899999999,33.067076],"type":"Point"}
}