{
  "type": "Feature",
  "properties": {
    "iso:country":"US",
    "sg:address":"220 Constitution Blvd",
    "sg:city":"Lawrenceville",
    "sg:classifiers":[
        {
            "category":"Retail",
            "subcategory":"Auto Repair",
            "type":"Services"
        }
    ],
    "sg:phone":"+1 770 963 3182",
    "sg:postcode":"30045",
    "sg:province":"GA",
    "sg:tags":[
        "body",
        "shop"
    ],
    "wof:name":"Masters Paint & Body Shop",
    "wof:placetype":"venue"
},
  "geometry": {"coordinates":[-83.99009700000001,33.944302],"type":"Point"}
}