{
  "type": "Feature",
  "properties": {
    "addr:full":"3745 Lakeshore Dr NE Marietta GA 30067",
    "addr:housenumber":"3745",
    "addr:postcode":"30067",
    "addr:street":"Lakeshore Dr Ne",
    "iso:country":"US",
    "sg:address":"3745 Lakeshore Dr NE",
    "sg:city":"Marietta",
    "sg:classifiers":[
        {
            "category":"Professional",
            "subcategory":"Lawyer & Legal Services",
            "type":"Services"
        }
    ],
    "sg:phone":"+1 770 952 9274",
    "sg:postcode":"30067",
    "sg:province":"GA",
    "wof:name":"McGuire James E Atty",
    "wof:placetype":"venue"
},
  "geometry": {"coordinates":[-84.433296,33.9496],"type":"Point"}
}