{
  "type": "Feature",
  "properties": {
    "iso:country":"US",
    "sg:address":"25 Greenville St",
    "sg:city":"Newnan",
    "sg:classifiers":[
        {
            "category":"Insurance",
            "subcategory":"Hazard Insurance",
            "type":"Services"
        },
        {
            "category":"Insurance",
            "subcategory":"Life Insurance",
            "type":"Services"
        }
    ],
    "sg:phone":"+1 770 253 0033",
    "sg:postcode":"30263",
    "sg:province":"GA",
    "sg:tags":[
        "commercial",
        "business"
    ],
    "sg:website":"http://www.matrixins.com",
    "wof:name":"Matrix Insurance Agency",
    "wof:placetype":"venue"
},
  "geometry": {"coordinates":[-84.799826,33.372433],"type":"Point"}
}