{
  "type": "Feature",
  "properties": {
    "addr:full":"4124 Jimmy Carter Blvd Norcross GA 30093",
    "addr:housenumber":"4124",
    "addr:postcode":"30093",
    "addr:street":"Jimmy Carter Blvd",
    "iso:country":"US",
    "sg:address":"4124 Jimmy Carter Blvd",
    "sg:city":"Norcross",
    "sg:classifiers":[
        {
            "category":"Autos & Motor Vehicles",
            "subcategory":"Auto Supplies",
            "type":"Retail Goods"
        }
    ],
    "sg:phone":"+1 770 414 9400",
    "sg:postcode":"30093",
    "sg:province":"GA",
    "sg:tags":[
        "automobile",
        "stereo",
        "radio"
    ],
    "wof:name":"Audio Expo",
    "wof:placetype":"venue"
},
  "geometry": {"coordinates":[-84.18827,33.868045],"type":"Point"}
}