{
  "type": "Feature",
  "properties": {
    "addr:full":"3530 State Rte 42 Stockbridge GA 30281",
    "addr:housenumber":"3530",
    "addr:postcode":"30281",
    "addr:street":"State Rte 42",
    "iso:country":"US",
    "sg:address":"3530 State Rte 42",
    "sg:city":"Stockbridge",
    "sg:classifiers":[
        {
            "category":"Professional",
            "subcategory":"Business Services",
            "type":"Services"
        }
    ],
    "sg:phone":"+1 678 779 2169",
    "sg:postcode":"30281",
    "sg:province":"GA",
    "wof:name":"P & P Enterprises Inc",
    "wof:placetype":"venue"
},
  "geometry": {"coordinates":[-84.20096700000001,33.537547],"type":"Point"}
}