{
  "type": "Feature",
  "properties": {
    "iso:country":"US",
    "sg:address":"165 Woodgate Cir",
    "sg:city":"Fayetteville",
    "sg:classifiers":[
        {
            "category":"Home & Garden",
            "subcategory":"Furniture",
            "type":"Retail Goods"
        }
    ],
    "sg:phone":"+1 770 719 0178",
    "sg:postcode":"30214",
    "sg:province":"GA",
    "wof:name":"United Arts and Furniture Co",
    "wof:placetype":"venue"
},
  "geometry": {"coordinates":[-84.45072399999999,33.436321],"type":"Point"}
}