{
  "type": "Feature",
  "properties": {
    "iso:country":"US",
    "sg:address":"3205 Heritage Cir",
    "sg:city":"Augusta",
    "sg:classifiers":[
        {
            "category":"Real Estate",
            "subcategory":"Real Estate Operator",
            "type":"Services"
        }
    ],
    "sg:phone":"+1 706 738 2925",
    "sg:postcode":"30909",
    "sg:province":"GA",
    "sg:tags":[
        "house",
        "apartment"
    ],
    "wof:name":"Heritage Apartments",
    "wof:placetype":"venue"
},
  "geometry": {"coordinates":[-82.067863,33.470914],"type":"Point"}
}