{
  "type": "Feature",
  "properties": {
    "addr:full":"2873 Audubon Cir Macon GA 31204",
    "addr:housenumber":"2873",
    "addr:postcode":"31204",
    "addr:street":"Audubon Cir",
    "iso:country":"US",
    "sg:address":"2873 Audubon Cir",
    "sg:city":"Macon",
    "sg:classifiers":[
        {
            "category":"Social Services",
            "type":"Services"
        }
    ],
    "sg:phone":"+1 478 474 1003",
    "sg:postcode":"31204",
    "sg:province":"GA",
    "wof:name":"Alcy Acres Enterprises Inc",
    "wof:placetype":"venue"
},
  "geometry": {"coordinates":[-83.66574,32.8819],"type":"Point"}
}