{
  "type": "Feature",
  "properties": {
    "addr:full":"1054 Mission Rd SW Cartersville GA 30120",
    "addr:housenumber":"1054",
    "addr:postcode":"30120",
    "addr:street":"Mission Rd Sw",
    "iso:country":"US",
    "sg:address":"1054 Mission Rd SW",
    "sg:city":"Cartersville",
    "sg:classifiers":[
        {
            "category":"Professional",
            "subcategory":"Advertising",
            "type":"Services"
        }
    ],
    "sg:phone":"+1 770 606 4576",
    "sg:postcode":"30120",
    "sg:province":"GA",
    "sg:tags":[
        "mail"
    ],
    "wof:name":"Building Solutions",
    "wof:placetype":"venue"
},
  "geometry": {"coordinates":[-84.871748,34.160824],"type":"Point"}
}