{
  "type": "Feature",
  "properties": {
    "addr:full":"2755 Antioch Rd Ste 9 Cumming GA 30040",
    "addr:housenumber":"2755",
    "addr:postcode":"30040",
    "addr:street":"Antioch Rd Ste 9",
    "iso:country":"US",
    "sg:address":"2755 Antioch Rd Ste 9",
    "sg:city":"Cumming",
    "sg:classifiers":[
        {
            "category":"Home & Garden",
            "subcategory":"Carpets & Floor Coverings",
            "type":"Retail Goods"
        }
    ],
    "sg:phone":"+1 770 888 2111",
    "sg:postcode":"30040",
    "sg:province":"GA",
    "sg:tags":[
        "mattress"
    ],
    "wof:name":"Mattress Smart Outlet",
    "wof:placetype":"venue"
},
  "geometry": {"coordinates":[-84.104417,34.229778],"type":"Point"}
}