{
  "type": "Feature",
  "properties": {
    "iso:country":"US",
    "sg:address":"219 Skyland Dr",
    "sg:city":"Roswell",
    "sg:classifiers":[
        {
            "category":"Travel",
            "subcategory":"Travel Agent",
            "type":"Entertainment"
        }
    ],
    "sg:phone":"+1 770 998 6935",
    "sg:postcode":"30075",
    "sg:province":"GA",
    "sg:tags":[
        "agency"
    ],
    "wof:name":"Skyland Travel",
    "wof:placetype":"venue"
},
  "geometry": {"coordinates":[-84.371478,34.006784],"type":"Point"}
}