{
  "type": "Feature",
  "properties": {
    "iso:country":"US",
    "sg:address":"211 Main St",
    "sg:city":"Dallas",
    "sg:classifiers":[
        {
            "category":"Personal",
            "subcategory":"Tattoo Parlor",
            "type":"Services"
        }
    ],
    "sg:phone":"+1 770 445 8000",
    "sg:postcode":"30132",
    "sg:province":"GA",
    "sg:tags":[
        "tattooing"
    ],
    "sg:website":"www.debiillustratortattoo.com",
    "wof:name":"Illustrator",
    "wof:placetype":"venue"
},
  "geometry": {"coordinates":[-84.84104600000001,33.923489],"type":"Point"}
}