{
  "type": "Feature",
  "properties": {
    "addr:full":"357 N 1st St Jesup GA 31545",
    "addr:housenumber":"357",
    "addr:postcode":"31545",
    "addr:street":"N 1St St",
    "iso:country":"US",
    "sg:address":"357 N 1st St",
    "sg:city":"Jesup",
    "sg:classifiers":[
        {
            "category":"Communications",
            "type":"Services"
        }
    ],
    "sg:phone":"+1 912 427 0297",
    "sg:postcode":"31545",
    "sg:province":"GA",
    "wof:name":"Duncan Communications",
    "wof:placetype":"venue"
},
  "geometry": {"coordinates":[-81.882746,31.609486],"type":"Point"}
}