{
  "type": "Feature",
  "properties": {
    "addr:full":"3697 Highway 5 Ste 14 Douglasville GA 30135",
    "addr:housenumber":"3697",
    "addr:postcode":"30135",
    "addr:street":"Highway 5 Ste 14",
    "iso:country":"US",
    "sg:address":"3697 Highway 5 Ste 14",
    "sg:city":"Douglasville",
    "sg:classifiers":[
        {
            "category":"Shopping",
            "subcategory":"Department Store",
            "type":"Retail Goods"
        },
        {
            "category":"Shopping",
            "subcategory":"Discount & Variety Stores",
            "type":"Retail Goods"
        },
        {
            "category":"Shopping",
            "type":"Retail Goods"
        },
        {
            "category":"Food & Beverages",
            "subcategory":"Groceries & Convenience Stores",
            "type":"Retail Goods"
        }
    ],
    "sg:phone":"+1 678 501 5165",
    "sg:postcode":"30135",
    "sg:province":"GA",
    "sg:tags":[
        "merchandise"
    ],
    "sg:website":"http://www.dollargeneral.com",
    "wof:name":"Dollar General",
    "wof:placetype":"venue"
},
  "geometry": {"coordinates":[-84.77775099999999,33.705827],"type":"Point"}
}