{
  "type": "Feature",
  "properties": {
    "iso:country":"US",
    "sg:address":"562 Moreland Ave SE",
    "sg:city":"Atlanta",
    "sg:classifiers":[
        {
            "category":"Organizations",
            "subcategory":"Religious Organization",
            "type":"Services"
        }
    ],
    "sg:phone":"+1 404 622 5105",
    "sg:postcode":"30316",
    "sg:province":"GA",
    "sg:tags":[
        "church"
    ],
    "wof:name":"Powerful Truth Sanctuary",
    "wof:placetype":"venue"
},
  "geometry": {"coordinates":[-84.349177,33.73856],"type":"Point"}
}