{
  "type": "Feature",
  "properties": {
    "addr:full":"102 E Robert Toombs Ave Washington GA 30673",
    "addr:housenumber":"102",
    "addr:postcode":"30673",
    "addr:street":"E Robert Toombs Ave",
    "iso:country":"US",
    "sg:address":"102 E Robert Toombs Ave",
    "sg:city":"Washington",
    "sg:classifiers":[
        {
            "category":"Food & Beverages",
            "subcategory":"Groceries & Convenience Stores",
            "type":"Retail Goods"
        }
    ],
    "sg:phone":"+1 706 678 1601",
    "sg:postcode":"30673",
    "sg:province":"GA",
    "wof:name":"Destiny Corp",
    "wof:placetype":"venue"
},
  "geometry": {"coordinates":[-82.73898800000001,33.736821],"type":"Point"}
}