{
  "type": "Feature",
  "properties": {
    "addr:full":"306 Fallview Dr Mcdonough GA 30253",
    "addr:housenumber":"306",
    "addr:postcode":"30253",
    "addr:street":"Fallview Dr",
    "iso:country":"US",
    "sg:address":"306 Fallview Dr",
    "sg:city":"Mcdonough",
    "sg:classifiers":[
        {
            "category":"Professional",
            "subcategory":"Accounting & Tax Preparation",
            "type":"Services"
        }
    ],
    "sg:phone":"+1 678 432 5708",
    "sg:postcode":"30253",
    "sg:province":"GA",
    "sg:tags":[
        "bookkeeping"
    ],
    "wof:name":"Jeree Billing & More",
    "wof:placetype":"venue"
},
  "geometry": {"coordinates":[-84.16143099999999,33.447838],"type":"Point"}
}