{
  "type": "Feature",
  "properties": {
    "addr:full":"215 Burnie Rd Woodstock GA 30188",
    "addr:housenumber":"215",
    "addr:postcode":"30188",
    "addr:street":"Burnie Rd",
    "iso:country":"US",
    "sg:address":"215 Burnie Rd",
    "sg:city":"Woodstock",
    "sg:classifiers":[
        {
            "category":"Professional",
            "subcategory":"Business Services",
            "type":"Services"
        }
    ],
    "sg:phone":"+1 770 778 0579",
    "sg:postcode":"30188",
    "sg:province":"GA",
    "wof:name":"Ben Riley Productions",
    "wof:placetype":"venue"
},
  "geometry": {"coordinates":[-84.390242,34.130929],"type":"Point"}
}