{
  "type": "Feature",
  "properties": {
    "addr:full":"3315 Maple Ridge Ct Suwanee GA 30024",
    "addr:housenumber":"3315",
    "addr:postcode":"30024",
    "addr:street":"Maple Ridge Ct",
    "iso:country":"US",
    "sg:address":"3315 Maple Ridge Ct",
    "sg:city":"Suwanee",
    "sg:classifiers":[
        {
            "category":"Professional",
            "subcategory":"Business Services",
            "type":"Services"
        }
    ],
    "sg:phone":"+1 770 813 1003",
    "sg:postcode":"30024",
    "sg:province":"GA",
    "wof:name":"Hometown Inspection Svcs LLC",
    "wof:placetype":"venue"
},
  "geometry": {"coordinates":[-84.095225,34.018921],"type":"Point"}
}