{
  "type": "Feature",
  "properties": {
    "iso:country":"US",
    "sg:address":"1250 Custer Avenue SE",
    "sg:city":"Atlanta",
    "sg:classifiers":[
        {
            "category":"Shopping",
            "subcategory":"Pawn Shop",
            "type":"Retail Goods"
        }
    ],
    "sg:phone":"+1 404 622 9896",
    "sg:postcode":"30316",
    "sg:province":"GA",
    "wof:name":"Moreland Pawn Shop",
    "wof:placetype":"venue"
},
  "geometry": {"coordinates":[-84.347123,33.715605],"type":"Point"}
}