{
  "type": "Feature",
  "properties": {
    "iso:country":"US",
    "sg:address":"971 N Hairston Rd Ste A-9 #113",
    "sg:city":"Stone Mountain",
    "sg:classifiers":[
        {
            "category":"Arts & Performance",
            "subcategory":"Music",
            "type":"Entertainment"
        }
    ],
    "sg:phone":"+1 678 317 4578",
    "sg:postcode":"30083",
    "sg:province":"GA",
    "sg:tags":[
        "venue"
    ],
    "wof:name":"Donzgalore Inc",
    "wof:placetype":"venue"
},
  "geometry": {"coordinates":[-84.192179,33.805324],"type":"Point"}
}