{
  "type": "Feature",
  "properties": {
    "iso:country":"US",
    "sg:address":"824 Tinsley St",
    "sg:city":"Dalton",
    "sg:classifiers":[
        {
            "category":"Manufacturing",
            "subcategory":"Textiles",
            "type":"Manufacturing & Wholesale Goods"
        }
    ],
    "sg:phone":"+1 706 226 0742",
    "sg:postcode":"30720",
    "sg:province":"GA",
    "sg:tags":[
        "rug",
        "carpet"
    ],
    "wof:name":"Dave's Carpet",
    "wof:placetype":"venue"
},
  "geometry": {"coordinates":[-84.965158,34.7845],"type":"Point"}
}