{
  "type": "Feature",
  "properties": {
    "addr:full":"16 Wolf St Hampton GA 30228",
    "addr:housenumber":"16",
    "addr:postcode":"30228",
    "addr:street":"Wolf St",
    "iso:country":"US",
    "sg:address":"16 Wolf St",
    "sg:city":"Hampton",
    "sg:classifiers":[
        {
            "category":"Government",
            "subcategory":"Office",
            "type":"Public Place"
        }
    ],
    "sg:phone":"+1 770 946 3234",
    "sg:postcode":"30228",
    "sg:province":"GA",
    "sg:tags":[
        "village"
    ],
    "wof:name":"Hampton Maintenance Shop",
    "wof:placetype":"venue"
},
  "geometry": {"coordinates":[-84.281952,33.386613],"type":"Point"}
}