{
  "type": "Feature",
  "properties": {
    "addr:full":"11490 Boxford Pl Alpharetta GA 30022",
    "addr:housenumber":"11490",
    "addr:postcode":"30022",
    "addr:street":"Boxford Pl",
    "iso:country":"US",
    "sg:address":"11490 Boxford Pl",
    "sg:city":"Alpharetta",
    "sg:classifiers":[
        {
            "category":"Organizations",
            "subcategory":"Religious Organization",
            "type":"Services"
        }
    ],
    "sg:phone":"+1 770 993 1691",
    "sg:postcode":"30022",
    "sg:province":"GA",
    "sg:tags":[
        "church"
    ],
    "wof:name":"New Haven Baptist Church",
    "wof:placetype":"venue"
},
  "geometry": {"coordinates":[-84.20794100000001,34.059292],"type":"Point"}
}