{
  "type": "Feature",
  "properties": {
    "iso:country":"US",
    "sg:address":"4118 7th St",
    "sg:city":"Savannah",
    "sg:classifiers":[
        {
            "category":"Professional",
            "type":"Services"
        }
    ],
    "sg:phone":"+1 912 964 0172",
    "sg:postcode":"31408",
    "sg:province":"GA",
    "wof:name":"Macks",
    "wof:placetype":"venue"
},
  "geometry": {"coordinates":[-81.151394,32.096365],"type":"Point"}
}