{
  "type": "Feature",
  "properties": {
    "iso:country":"US",
    "sg:address":"300 E Main St",
    "sg:city":"Statesboro",
    "sg:classifiers":[
        {
            "category":"Personal",
            "subcategory":"Beauty Salon",
            "type":"Services"
        }
    ],
    "sg:phone":"+1 912 489 6972",
    "sg:postcode":"30458",
    "sg:province":"GA",
    "sg:tags":[
        "shop",
        "barber"
    ],
    "wof:name":"Shantoria's Salon",
    "wof:placetype":"venue"
},
  "geometry": {"coordinates":[-81.773883,32.449096],"type":"Point"}
}