{
  "type": "Feature",
  "properties": {
    "addr:full":"1101 Pendleton St Waycross GA 31501",
    "addr:housenumber":"1101",
    "addr:postcode":"31501",
    "addr:street":"Pendleton St",
    "iso:country":"US",
    "sg:address":"1101 Pendleton St",
    "sg:city":"Waycross",
    "sg:classifiers":[
        {
            "category":"Organizations",
            "subcategory":"Religious Organization",
            "type":"Services"
        }
    ],
    "sg:phone":"+1 912 284 0976",
    "sg:postcode":"31501",
    "sg:province":"GA",
    "wof:name":"Wings Of Deliverance",
    "wof:placetype":"venue"
},
  "geometry": {"coordinates":[-82.355902,31.218923],"type":"Point"}
}