{
  "type": "Feature",
  "properties": {
    "addr:full":"855 Sunset Dr Athens GA 30606",
    "addr:housenumber":"855",
    "addr:postcode":"30606",
    "addr:street":"Sunset Dr",
    "iso:country":"US",
    "sg:address":"855 Sunset Dr",
    "sg:city":"Athens",
    "sg:classifiers":[
        {
            "category":"Health Services",
            "subcategory":"Nursing And Care Facility",
            "type":"Services"
        },
        {
            "category":"Health Services",
            "subcategory":"Health Practitioner",
            "type":"Services"
        }
    ],
    "sg:phone":"+1 706 316 1516",
    "sg:postcode":"30606",
    "sg:province":"GA",
    "sg:tags":[
        "home",
        "eldercare-home"
    ],
    "wof:name":"Family Care Inc",
    "wof:placetype":"venue"
},
  "geometry": {"coordinates":[-83.410201,33.967198],"type":"Point"}
}