{
  "type": "Feature",
  "properties": {
    "addr:full":"3212 Old Mill Trce Marietta GA 30067",
    "addr:housenumber":"3212",
    "addr:postcode":"30067",
    "addr:street":"Old Mill Trce",
    "iso:country":"US",
    "sg:address":"3212 Old Mill Trce",
    "sg:city":"Marietta",
    "sg:classifiers":[
        {
            "category":"Professional",
            "subcategory":"Art Services",
            "type":"Services"
        }
    ],
    "sg:phone":"+1 770 690 8660",
    "sg:postcode":"30067",
    "sg:province":"GA",
    "sg:tags":[
        "commercial",
        "design"
    ],
    "wof:name":"Durst Design",
    "wof:placetype":"venue"
},
  "geometry": {"coordinates":[-84.460314,33.926874],"type":"Point"}
}