{
  "type": "Feature",
  "properties": {
    "iso:country":"US",
    "sg:address":"1697 N Main St",
    "sg:city":"La Fayette",
    "sg:classifiers":[
        {
            "category":"Autos & Motor Vehicles",
            "subcategory":"Automobile Sales",
            "type":"Retail Goods"
        }
    ],
    "sg:phone":"+1 706 638 5898",
    "sg:postcode":"30728",
    "sg:province":"GA",
    "sg:tags":[
        "used"
    ],
    "wof:name":"Valley Auto Sales",
    "wof:placetype":"venue"
},
  "geometry": {"coordinates":[-85.27564099999999,34.734408],"type":"Point"}
}