{
  "type": "Feature",
  "properties": {
    "addr:full":"4953 Canton Rd Marietta GA 30066",
    "addr:housenumber":"4953",
    "addr:postcode":"30066",
    "addr:street":"Canton Rd",
    "iso:country":"US",
    "sg:address":"4953 Canton Rd",
    "sg:city":"Marietta",
    "sg:classifiers":[
        {
            "category":"Retail",
            "subcategory":"Veterinary Services",
            "type":"Services"
        },
        {
            "category":"Retail",
            "subcategory":"Pet Boarding",
            "type":"Services"
        }
    ],
    "sg:phone":"+1 770 926 8888",
    "sg:postcode":"30066",
    "sg:province":"GA",
    "sg:tags":[
        "sitting",
        "hospital",
        "specialty",
        "clinic",
        "veterinarian",
        "boarding/pet"
    ],
    "wof:name":"Etowah Veterinary Hospital",
    "wof:placetype":"venue"
},
  "geometry": {"coordinates":[-84.522102,34.071899],"type":"Point"}
}