{
  "type": "Feature",
  "properties": {
    "iso:country":"US",
    "sg:address":"181 Scenic Hwy",
    "sg:city":"Lawrenceville",
    "sg:classifiers":[
        {
            "category":"Personal",
            "subcategory":"Beauty Salon",
            "type":"Services"
        }
    ],
    "sg:phone":"+1 770 963 0073",
    "sg:postcode":"30045",
    "sg:province":"GA",
    "sg:tags":[
        "shop"
    ],
    "wof:name":"Cuttin Caboose",
    "wof:placetype":"venue"
},
  "geometry": {"coordinates":[-83.98471000000001,33.948622],"type":"Point"}
}