{
  "type": "Feature",
  "properties": {
    "iso:country":"US",
    "sg:address":"3760 Crestwood Pl",
    "sg:city":"Cumming",
    "sg:classifiers":[
        {
            "category":"Building & Trades",
            "subcategory":"Plumbing",
            "type":"Services"
        }
    ],
    "sg:phone":"+1 770 781 4132",
    "sg:postcode":"30041",
    "sg:province":"GA",
    "sg:tags":[
        "repair",
        "air",
        "conditioning",
        "heating"
    ],
    "wof:name":"Service First Hcv",
    "wof:placetype":"venue"
},
  "geometry": {"coordinates":[-84.08131299999999,34.166175],"type":"Point"}
}