{
  "type": "Feature",
  "properties": {
    "iso:country":"US",
    "sg:address":"510 Aumond Rd",
    "sg:city":"Augusta",
    "sg:classifiers":[
        {
            "category":"Building & Trades",
            "subcategory":"Construction",
            "type":"Services"
        }
    ],
    "sg:phone":"+1 706 364 2434",
    "sg:postcode":"30909",
    "sg:province":"GA",
    "sg:tags":[
        "home",
        "improvement"
    ],
    "wof:name":"Augusta Renovations & Rstrtns",
    "wof:placetype":"venue"
},
  "geometry": {"coordinates":[-82.04941100000001,33.49268],"type":"Point"}
}