{
  "type": "Feature",
  "properties": {
    "iso:country":"US",
    "sg:address":"721 Washington Ave",
    "sg:city":"Savannah",
    "sg:classifiers":[
        {
            "category":"Organizations",
            "subcategory":"Religious Organization",
            "type":"Services"
        }
    ],
    "sg:phone":"+1 912 354 7290",
    "sg:postcode":"31405",
    "sg:province":"GA",
    "sg:tags":[
        "church"
    ],
    "wof:name":"St Michaels Episcople Church",
    "wof:placetype":"venue"
},
  "geometry": {"coordinates":[-81.086461,32.045004],"type":"Point"}
}