{
  "type": "Feature",
  "properties": {
    "addr:full":"48 Hwy 213 Covington GA 30014",
    "addr:postcode":"30014",
    "addr:street":"48 Hwy 213",
    "iso:country":"US",
    "sg:address":"48 Hwy 213",
    "sg:city":"Covington",
    "sg:classifiers":[
        {
            "category":"Shopping",
            "subcategory":"Used Merchandise",
            "type":"Retail Goods"
        }
    ],
    "sg:phone":"+1 770 784 8136",
    "sg:postcode":"30014",
    "sg:province":"GA",
    "sg:tags":[
        "antique",
        "gift",
        "accessory"
    ],
    "wof:name":"Rose Vintage",
    "wof:placetype":"venue"
},
  "geometry": {"coordinates":[-83.843715,33.544607],"type":"Point"}
}