{
  "type": "Feature",
  "properties": {
    "iso:country":"US",
    "sg:address":"7 S Mulberry St",
    "sg:city":"Statesboro",
    "sg:classifiers":[
        {
            "category":"Personal",
            "subcategory":"Beauty Salon",
            "type":"Services"
        }
    ],
    "sg:phone":"+1 912 489 4528",
    "sg:postcode":"30458",
    "sg:province":"GA",
    "sg:tags":[
        "shop"
    ],
    "wof:name":"Karens Kuts",
    "wof:placetype":"venue"
},
  "geometry": {"coordinates":[-81.77968,32.447938],"type":"Point"}
}