{
  "type": "Feature",
  "properties": {
    "iso:country":"US",
    "sg:address":"4200 Perimeter Park S",
    "sg:city":"Atlanta",
    "sg:classifiers":[
        {
            "category":"Professional",
            "subcategory":"Engineering",
            "type":"Services"
        }
    ],
    "sg:phone":"+1 770 458 3005",
    "sg:postcode":"30341",
    "sg:province":"GA",
    "wof:name":"Womack & Associates Inc",
    "wof:placetype":"venue"
},
  "geometry": {"coordinates":[-84.296994,33.917233],"type":"Point"}
}