{
  "type": "Feature",
  "properties": {
    "iso:country":"US",
    "sg:address":"2926 Peach Orchard Rd",
    "sg:city":"Augusta",
    "sg:classifiers":[
        {
            "category":"Travel",
            "subcategory":"Hotels & Motels",
            "type":"Entertainment"
        }
    ],
    "sg:phone":"+1 706 793 3306",
    "sg:postcode":"30906",
    "sg:province":"GA",
    "sg:tags":[
        "lodging"
    ],
    "wof:name":"Quality Inn South",
    "wof:placetype":"venue"
},
  "geometry": {"coordinates":[-82.023045,33.417436],"type":"Point"}
}