{
  "type": "Feature",
  "properties": {
    "addr:full":"978 Davis St Gainesville GA 30501",
    "addr:housenumber":"978",
    "addr:postcode":"30501",
    "addr:street":"Davis St",
    "iso:country":"US",
    "sg:address":"978 Davis St",
    "sg:city":"Gainesville",
    "sg:classifiers":[
        {
            "category":"Manufacturing",
            "subcategory":"Glass & Minerals",
            "type":"Manufacturing & Wholesale Goods"
        }
    ],
    "sg:phone":"+1 770 532 7014",
    "sg:postcode":"30501",
    "sg:province":"GA",
    "sg:tags":[
        "fitting",
        "mfg"
    ],
    "wof:name":"Hydro Conduit Corporation",
    "wof:placetype":"venue"
},
  "geometry": {"coordinates":[-83.829818,34.28345],"type":"Point"}
}