{
  "type": "Feature",
  "properties": {
    "addr:full":"908 Corder Rd Warner Robins GA 31088",
    "addr:housenumber":"908",
    "addr:postcode":"31088",
    "addr:street":"Corder Rd",
    "iso:country":"US",
    "sg:address":"908 Corder Rd",
    "sg:city":"Warner Robins",
    "sg:classifiers":[
        {
            "category":"Professional",
            "subcategory":"Art Services",
            "type":"Services"
        }
    ],
    "sg:phone":"+1 478 929 2407",
    "sg:postcode":"31088",
    "sg:province":"GA",
    "sg:tags":[
        "photography",
        "commercial"
    ],
    "wof:name":"Curtis Photography",
    "wof:placetype":"venue"
},
  "geometry": {"coordinates":[-83.66109299999999,32.605938],"type":"Point"}
}