{
  "type": "Feature",
  "properties": {
    "iso:country":"US",
    "sg:address":"5502 Export Cir",
    "sg:city":"Savannah",
    "sg:classifiers":[
        {
            "category":"Retail",
            "subcategory":"Auto Repair",
            "type":"Services"
        }
    ],
    "sg:phone":"+1 912 963 0609",
    "sg:postcode":"31408",
    "sg:province":"GA",
    "sg:tags":[
        "tire"
    ],
    "wof:name":"Collins Advantage Alignment",
    "wof:placetype":"venue"
},
  "geometry": {"coordinates":[-81.174863,32.124303],"type":"Point"}
}