{
  "type": "Feature",
  "properties": {
    "iso:country":"US",
    "sg:address":"3575 Koger Blvd Ste 220",
    "sg:city":"Duluth",
    "sg:classifiers":[
        {
            "category":"Professional",
            "subcategory":"Lawyer & Legal Services",
            "type":"Services"
        }
    ],
    "sg:phone":"+1 770 923 4626",
    "sg:postcode":"30096",
    "sg:province":"GA",
    "wof:name":"Weldon Michael S Atty",
    "wof:placetype":"venue"
},
  "geometry": {"coordinates":[-84.12550400000001,33.947899],"type":"Point"}
}