{
  "type": "Feature",
  "properties": {
    "addr:full":"1150 Cobb International Pl NW A Kennesaw GA 30152",
    "addr:housenumber":"1150",
    "addr:postcode":"30152",
    "addr:street":"Cobb International Pl Nw A",
    "iso:country":"US",
    "sg:address":"1150 Cobb International Pl NW A",
    "sg:city":"Kennesaw",
    "sg:classifiers":[
        {
            "category":"Wholesale",
            "subcategory":"Chemicals & Plastics",
            "type":"Manufacturing & Wholesale Goods"
        },
        {
            "category":"Manufacturing",
            "subcategory":"Paper Products",
            "type":"Manufacturing & Wholesale Goods"
        }
    ],
    "sg:phone":"+1 770 435 2611",
    "sg:postcode":"30152",
    "sg:province":"GA",
    "sg:tags":[
        "bag",
        "bags-paper"
    ],
    "sg:website":"http://www.metrobagllc.com",
    "wof:name":"Metro Bag",
    "wof:placetype":"venue"
},
  "geometry": {"coordinates":[-84.611743,34.006055],"type":"Point"}
}