{
  "type": "Feature",
  "properties": {
    "iso:country":"US",
    "sg:address":"1040 Southern Rd",
    "sg:city":"Morrow",
    "sg:classifiers":[
        {
            "category":"Professional",
            "subcategory":"Advertising",
            "type":"Services"
        }
    ],
    "sg:phone":"+1 678 422 7822",
    "sg:postcode":"30260",
    "sg:province":"GA",
    "sg:tags":[
        "distribution"
    ],
    "sg:website":"www.wagnerindustries.com",
    "wof:name":"Wagner Industries",
    "wof:placetype":"venue"
},
  "geometry": {"coordinates":[-84.356461,33.564137],"type":"Point"}
}