{
  "type": "Feature",
  "properties": {
    "iso:country":"US",
    "sg:address":"1141 Leslie Pl",
    "sg:city":"Lithonia",
    "sg:classifiers":[
        {
            "category":"Real Estate",
            "subcategory":"Surveying",
            "type":"Services"
        }
    ],
    "sg:phone":"+1 770 482 1988",
    "sg:postcode":"30058",
    "sg:province":"GA",
    "wof:name":"Taz Services",
    "wof:placetype":"venue"
},
  "geometry": {"coordinates":[-84.102835,33.762936],"type":"Point"}
}