{
  "type": "Feature",
  "properties": {
    "iso:country":"US",
    "sg:address":"33 Roosevelt St",
    "sg:city":"Camilla",
    "sg:phone":"+1 229 336 0580",
    "sg:postcode":"31730",
    "sg:province":"GA",
    "sg:tags":[
        "farm",
        "field",
        "crop",
        "soybean"
    ],
    "wof:name":"Eugene Williams",
    "wof:placetype":"venue"
},
  "geometry": {"coordinates":[-84.209225,31.221988],"type":"Point"}
}