{
  "type": "Feature",
  "properties": {
    "addr:full":"7031 Setters Way Lithonia GA 30038",
    "addr:housenumber":"7031",
    "addr:postcode":"30038",
    "addr:street":"Setters Way",
    "iso:country":"US",
    "sg:address":"7031 Setters Way",
    "sg:city":"Lithonia",
    "sg:classifiers":[
        {
            "category":"Professional",
            "subcategory":"Accounting & Tax Preparation",
            "type":"Services"
        }
    ],
    "sg:phone":"+1 770 987 3516",
    "sg:postcode":"30038",
    "sg:province":"GA",
    "sg:tags":[
        "billing"
    ],
    "wof:name":"CJG Medical Coding & Billing",
    "wof:placetype":"venue"
},
  "geometry": {"coordinates":[-84.113659,33.634926],"type":"Point"}
}