{
  "type": "Feature",
  "properties": {
    "addr:full":"118 Chicago Ave Hoboken GA 31542",
    "addr:housenumber":"118",
    "addr:postcode":"31542",
    "addr:street":"Chicago Ave",
    "iso:country":"US",
    "sg:address":"118 Chicago Ave",
    "sg:city":"Hoboken",
    "sg:classifiers":[
        {
            "category":"Restaurant",
            "type":"Food & Drink"
        }
    ],
    "sg:phone":"+1 912 458 2129",
    "sg:postcode":"31542",
    "sg:province":"GA",
    "wof:name":"Country Boy Restaurant",
    "wof:placetype":"venue"
},
  "geometry": {"coordinates":[-82.126536,31.186402],"type":"Point"}
}