{
  "type": "Feature",
  "properties": {
    "iso:country":"US",
    "sg:address":"1438 Bouldercrest Rd SE",
    "sg:city":"Atlanta",
    "sg:classifiers":[
        {
            "category":"Real Estate",
            "subcategory":"Real Estate Operator",
            "type":"Services"
        }
    ],
    "sg:phone":"+1 404 241 6600",
    "sg:postcode":"30316",
    "sg:province":"GA",
    "sg:tags":[
        "building",
        "townhouses",
        "apartment"
    ],
    "wof:name":"Sun Valley Apartments",
    "wof:placetype":"venue"
},
  "geometry": {"coordinates":[-84.329223,33.712902],"type":"Point"}
}