{
  "type": "Feature",
  "properties": {
    "addr:full":"111 Menendez Ave St Simons Island GA 31522",
    "addr:housenumber":"111",
    "addr:postcode":"31522",
    "addr:street":"Menendez Ave St Simons Island",
    "iso:country":"US",
    "sg:address":"111 Menendez Ave",
    "sg:city":"St Simons Island",
    "sg:classifiers":[
        {
            "category":"Social Services",
            "subcategory":"Child Care",
            "type":"Services"
        }
    ],
    "sg:phone":"+1 912 638 1692",
    "sg:postcode":"31522",
    "sg:province":"GA",
    "sg:tags":[
        "kindergarten",
        "academic",
        "school"
    ],
    "wof:name":"Lord Of Life Christian School",
    "wof:placetype":"venue"
},
  "geometry": {"coordinates":[-81.37883100000001,31.180274],"type":"Point"}
}