{
  "type": "Feature",
  "properties": {
    "addr:full":"10 Hampton Ln Cartersville GA 30120",
    "addr:housenumber":"10",
    "addr:postcode":"30120",
    "addr:street":"Hampton Ln",
    "iso:country":"US",
    "sg:address":"10 Hampton Ln",
    "sg:city":"Cartersville",
    "sg:classifiers":[
        {
            "category":"Shopping",
            "subcategory":"Computers & Home Electronics",
            "type":"Retail Goods"
        }
    ],
    "sg:phone":"+1 770 607 0974",
    "sg:postcode":"30120",
    "sg:province":"GA",
    "sg:tags":[
        "software"
    ],
    "wof:name":"E Project Tools",
    "wof:placetype":"venue"
},
  "geometry": {"coordinates":[-84.800797,34.131915],"type":"Point"}
}