{
  "type": "Feature",
  "properties": {
    "addr:full":"443 Kelly Rd Mc Donough GA 30253",
    "addr:housenumber":"443",
    "addr:postcode":"30253",
    "addr:street":"Kelly Rd",
    "iso:country":"US",
    "sg:address":"443 Kelly Rd",
    "sg:city":"Mc Donough",
    "sg:classifiers":[
        {
            "category":"Professional",
            "subcategory":"Management & Consulting",
            "type":"Services"
        }
    ],
    "sg:phone":"+1 678 479 6014",
    "sg:postcode":"30253",
    "sg:province":"GA",
    "sg:tags":[
        "business"
    ],
    "wof:name":"Easy Life",
    "wof:placetype":"venue"
},
  "geometry": {"coordinates":[-84.178831,33.456137],"type":"Point"}
}