{
  "type": "Feature",
  "properties": {
    "addr:full":"190 W Oak St Lawrenceville GA 30045",
    "addr:housenumber":"190",
    "addr:postcode":"30045",
    "addr:street":"W Oak St",
    "iso:country":"US",
    "sg:address":"190 W Oak St",
    "sg:city":"Lawrenceville",
    "sg:classifiers":[
        {
            "category":"Health Services",
            "subcategory":"Nursing And Care Facility",
            "type":"Services"
        }
    ],
    "sg:phone":"+1 770 339 6576",
    "sg:postcode":"30045",
    "sg:province":"GA",
    "sg:tags":[
        "mental",
        "center",
        "outpatient"
    ],
    "wof:name":"Gwinnett Mental Health",
    "wof:placetype":"venue"
},
  "geometry": {"coordinates":[-83.989817,33.958625],"type":"Point"}
}