{
  "type": "Feature",
  "properties": {
    "iso:country":"US",
    "sg:address":"8290 Roswell Rd Ste 100",
    "sg:city":"Atlanta",
    "sg:classifiers":[
        {
            "category":"Retail",
            "subcategory":"Laundry & Dry Cleaning",
            "type":"Services"
        }
    ],
    "sg:phone":"+1 770 641 8311",
    "sg:postcode":"30350",
    "sg:province":"GA",
    "wof:name":"World of Dry Cleaning",
    "wof:placetype":"venue"
},
  "geometry": {"coordinates":[-84.35019699999999,33.981098],"type":"Point"}
}