{
  "type": "Feature",
  "properties": {
    "addr:full":"2524 Falcon Chase Ct Suwanee GA 30024",
    "addr:housenumber":"2524",
    "addr:postcode":"30024",
    "addr:street":"Falcon Chase Ct",
    "iso:country":"US",
    "sg:address":"2524 Falcon Chase Ct",
    "sg:city":"Suwanee",
    "sg:classifiers":[
        {
            "category":"Shopping",
            "subcategory":"Florist",
            "type":"Retail Goods"
        }
    ],
    "sg:phone":"+1 404 934 9558",
    "sg:postcode":"30024",
    "sg:province":"GA",
    "wof:name":"Rhee's Floral Arrangements",
    "wof:placetype":"venue"
},
  "geometry": {"coordinates":[-84.041994,34.016375],"type":"Point"}
}