{
  "type": "Feature",
  "properties": {
    "addr:full":"1170 Madelyn Ln Madison GA 30650",
    "addr:housenumber":"1170",
    "addr:postcode":"30650",
    "addr:street":"Madelyn Ln",
    "iso:country":"US",
    "sg:address":"1170 Madelyn Ln",
    "sg:city":"Madison",
    "sg:classifiers":[
        {
            "category":"Wholesale",
            "subcategory":"Machinery & Supplies",
            "type":"Manufacturing & Wholesale Goods"
        }
    ],
    "sg:phone":"+1 706 342 4945",
    "sg:postcode":"30650",
    "sg:province":"GA",
    "sg:tags":[
        "specializing",
        "industrial",
        "valve"
    ],
    "wof:name":"Richter-Cochran Inc",
    "wof:placetype":"venue"
},
  "geometry": {"coordinates":[-83.53179799999999,33.597978],"type":"Point"}
}