{
  "type": "Feature",
  "properties": {
    "addr:full":"2401 Windy Hill Rd SE Marietta GA 30067",
    "addr:housenumber":"2401",
    "addr:postcode":"30067",
    "addr:street":"Windy Hill Rd Se",
    "iso:country":"US",
    "sg:address":"2401 Windy Hill Rd SE",
    "sg:city":"Marietta",
    "sg:classifiers":[
        {
            "category":"Professional",
            "type":"Services"
        }
    ],
    "sg:phone":"+1 770 485 2147",
    "sg:postcode":"30067",
    "sg:province":"GA",
    "sg:tags":[
        "processing",
        "data"
    ],
    "wof:name":"Atlanta Demo Services",
    "wof:placetype":"venue"
},
  "geometry": {"coordinates":[-84.48226200000001,33.903488],"type":"Point"}
}