{
  "type": "Feature",
  "properties": {
    "iso:country":"US",
    "sg:address":"140 Cedar Ridge Rd",
    "sg:city":"Locust Grove",
    "sg:classifiers":[
        {
            "category":"Professional",
            "subcategory":"Management & Consulting",
            "type":"Services"
        }
    ],
    "sg:phone":"+1 678 610 6768",
    "sg:postcode":"30248",
    "sg:province":"GA",
    "sg:tags":[
        "consultant"
    ],
    "wof:name":"Southside Consulting Group Inc",
    "wof:placetype":"venue"
},
  "geometry": {"coordinates":[-84.055492,33.40237],"type":"Point"}
}