{
  "type": "Feature",
  "properties": {
    "addr:full":"5054 Beverly Glen Village Ln Norcross GA 30092",
    "addr:housenumber":"5054",
    "addr:postcode":"30092",
    "addr:street":"Beverly Glen Village Ln",
    "iso:country":"US",
    "sg:address":"5054 Beverly Glen Village Ln",
    "sg:city":"Norcross",
    "sg:classifiers":[
        {
            "category":"Retail",
            "subcategory":"Repair Shop",
            "type":"Services"
        }
    ],
    "sg:phone":"+1 770 453 9030",
    "sg:postcode":"30092",
    "sg:province":"GA",
    "sg:tags":[
        "paint",
        "clean"
    ],
    "wof:name":"A Call Away Cleaning Svcs LLC",
    "wof:placetype":"venue"
},
  "geometry": {"coordinates":[-84.207345,33.967474],"type":"Point"}
}