{
  "type": "Feature",
  "properties": {
    "iso:country":"US",
    "sg:address":"1235 Southlake Mall",
    "sg:city":"Morrow",
    "sg:classifiers":[
        {
            "category":"Banks & Credit Unions",
            "subcategory":"Bank",
            "type":"Services"
        },
        {
            "category":"Banks & Credit Unions",
            "subcategory":"Financial Services",
            "type":"Services"
        }
    ],
    "sg:phone":"+1 770 960 3250",
    "sg:postcode":"30260",
    "sg:province":"GA",
    "sg:tags":[
        "loan",
        "financing"
    ],
    "sg:website":"http://www.SunTrust.com",
    "wof:name":"SunTrust Bank - Southlake",
    "wof:placetype":"venue"
},
  "geometry": {"coordinates":[-84.349949,33.573532],"type":"Point"}
}