{
  "type": "Feature",
  "properties": {
    "iso:country":"US",
    "sg:address":"159 N Strathmore Dr",
    "sg:city":"Sharpsburg",
    "sg:classifiers":[
        {
            "category":"Wholesale",
            "subcategory":"Non-durable Goods",
            "type":"Manufacturing & Wholesale Goods"
        }
    ],
    "sg:phone":"+1 770 463 9424",
    "sg:postcode":"30277",
    "sg:province":"GA",
    "sg:tags":[
        "product",
        "dist",
        "promotional"
    ],
    "wof:name":"Lech Promotions Inc",
    "wof:placetype":"venue"
},
  "geometry": {"coordinates":[-84.652711,33.461612],"type":"Point"}
}