{
  "type": "Feature",
  "properties": {
    "addr:full":"5701 Mableton Pkwy SE Mableton GA 30126",
    "addr:housenumber":"5701",
    "addr:postcode":"30126",
    "addr:street":"Mableton Pkwy Se",
    "iso:country":"US",
    "sg:address":"5701 Mableton Pkwy SE",
    "sg:city":"Mableton",
    "sg:classifiers":[
        {
            "category":"Manufacturing",
            "subcategory":"Printing",
            "type":"Manufacturing & Wholesale Goods"
        }
    ],
    "sg:phone":"+1 770 948 5672",
    "sg:postcode":"30126",
    "sg:province":"GA",
    "sg:tags":[
        "merchant",
        "for",
        "mfg",
        "cards",
        "check",
        "bank"
    ],
    "wof:name":"Advance Payment Systems Inc",
    "wof:placetype":"venue"
},
  "geometry": {"coordinates":[-84.57190799999999,33.81095],"type":"Point"}
}