{
  "type": "Feature",
  "properties": {
    "addr:full":"403 Knight Dr Statesboro GA 30458",
    "addr:housenumber":"403",
    "addr:postcode":"30458",
    "addr:street":"Knight Dr",
    "iso:country":"US",
    "sg:address":"403 Knight Dr",
    "sg:city":"Statesboro",
    "sg:classifiers":[
        {
            "category":"Real Estate",
            "subcategory":"Real Estate Operator",
            "type":"Services"
        }
    ],
    "sg:phone":"+1 912 681 1927",
    "sg:postcode":"30458",
    "sg:province":"GA",
    "sg:tags":[
        "building",
        "apartment",
        "nonresidential"
    ],
    "wof:name":"Campus Rentals",
    "wof:placetype":"venue"
},
  "geometry": {"coordinates":[-81.78231100000001,32.417724],"type":"Point"}
}