{
  "type": "Feature",
  "properties": {
    "addr:full":"2100 Northwest Pkwy SE I-75 Marietta GA 30067",
    "addr:housenumber":"2100",
    "addr:postcode":"30067",
    "addr:street":"Northwest Pkwy Se",
    "iso:country":"US",
    "sg:address":"2100 Northwest Pkwy SE I-75",
    "sg:city":"Marietta",
    "sg:classifiers":[
        {
            "category":"Travel",
            "subcategory":"Hotels & Motels",
            "type":"Entertainment"
        }
    ],
    "sg:phone":"+1 770 952 3000",
    "sg:postcode":"30067",
    "sg:province":"GA",
    "sg:tags":[
        "lodging"
    ],
    "sg:website":"http://www.comfortinn.com/hotel-marietta-georgia-GA231",
    "wof:name":"Comfort Inn Marietta",
    "wof:placetype":"venue"
},
  "geometry": {"coordinates":[-84.492081,33.920238],"type":"Point"}
}