{
  "type": "Feature",
  "properties": {
    "iso:country":"US",
    "sg:address":"4002 Stonemont Dr SW",
    "sg:city":"Lilburn",
    "sg:classifiers":[
        {
            "category":"Government",
            "subcategory":"Police Station",
            "type":"Public Place"
        }
    ],
    "sg:phone":"+1 770 736 9404",
    "sg:postcode":"30047",
    "sg:province":"GA",
    "sg:tags":[
        "protection"
    ],
    "wof:name":"Georgia State Patrol",
    "wof:placetype":"venue"
},
  "geometry": {"coordinates":[-84.079767,33.850004],"type":"Point"}
}