{
  "type": "Feature",
  "properties": {
    "addr:full":"560 Huntwick Pl Roswell GA 30075",
    "addr:housenumber":"560",
    "addr:postcode":"30075",
    "addr:street":"Huntwick Pl",
    "iso:country":"US",
    "sg:address":"560 Huntwick Pl",
    "sg:city":"Roswell",
    "sg:classifiers":[
        {
            "category":"Banks & Credit Unions",
            "subcategory":"Bank",
            "type":"Services"
        }
    ],
    "sg:phone":"+1 678 352 0365",
    "sg:postcode":"30075",
    "sg:province":"GA",
    "sg:tags":[
        "broker",
        "mortgage"
    ],
    "sg:website":"www.lenoxmortgage.com",
    "wof:name":"Lenox Mortgage Inc",
    "wof:placetype":"venue"
},
  "geometry": {"coordinates":[-84.377663,34.01428],"type":"Point"}
}