{
  "type": "Feature",
  "properties": {
    "addr:full":"4565 Ridgeview Dr Powder Springs GA 30127",
    "addr:housenumber":"4565",
    "addr:postcode":"30127",
    "addr:street":"Ridgeview Dr",
    "iso:country":"US",
    "sg:address":"4565 Ridgeview Dr",
    "sg:city":"Powder Springs",
    "sg:classifiers":[
        {
            "category":"Building & Trades",
            "subcategory":"Electrical",
            "type":"Services"
        }
    ],
    "sg:phone":"+1 770 943 7707",
    "sg:postcode":"30127",
    "sg:province":"GA",
    "sg:tags":[
        "electric",
        "contractor"
    ],
    "wof:name":"Rutherford Electrical Svc",
    "wof:placetype":"venue"
},
  "geometry": {"coordinates":[-84.72213600000001,33.844747],"type":"Point"}
}