{
  "type": "Feature",
  "properties": {
    "addr:full":"323 Summer Pl Peachtree City GA 30269",
    "addr:housenumber":"323",
    "addr:postcode":"30269",
    "addr:street":"Summer Pl",
    "iso:country":"US",
    "sg:address":"323 Summer Pl",
    "sg:city":"Peachtree City",
    "sg:classifiers":[
        {
            "category":"Professional",
            "type":"Services"
        }
    ],
    "sg:phone":"+1 770 487 2303",
    "sg:postcode":"30269",
    "sg:province":"GA",
    "wof:name":"Galloping Around",
    "wof:placetype":"venue"
},
  "geometry": {"coordinates":[-84.531752,33.349678],"type":"Point"}
}