{
  "type": "Feature",
  "properties": {
    "iso:country":"US",
    "sg:address":"2227 Oak Grove Rd",
    "sg:city":"Dahlonega",
    "sg:classifiers":[
        {
            "category":"Retail",
            "subcategory":"Auto Repair",
            "type":"Services"
        }
    ],
    "sg:phone":"+1 706 864 5151",
    "sg:postcode":"30533",
    "sg:province":"GA",
    "sg:tags":[
        "general"
    ],
    "wof:name":"Jeffs Automotive",
    "wof:placetype":"venue"
},
  "geometry": {"coordinates":[-84.029962,34.553663],"type":"Point"}
}