{
  "type": "Feature",
  "properties": {
    "addr:full":"400 S Thornton Ave Dalton GA 30720",
    "addr:housenumber":"400",
    "addr:postcode":"30720",
    "addr:street":"S Thornton Ave",
    "iso:country":"US",
    "sg:address":"400 S Thornton Ave",
    "sg:city":"Dalton",
    "sg:classifiers":[
        {
            "category":"Health Services",
            "subcategory":"Doctor",
            "type":"Services"
        }
    ],
    "sg:phone":"+1 706 270 5775",
    "sg:postcode":"30720",
    "sg:province":"GA",
    "wof:name":"DDS Robert LLC Purday",
    "wof:placetype":"venue"
},
  "geometry": {"coordinates":[-84.97183099999999,34.769294],"type":"Point"}
}