{
  "type": "Feature",
  "properties": {
    "addr:full":"4642 Bentley Pl Duluth GA 30096",
    "addr:housenumber":"4642",
    "addr:postcode":"30096",
    "addr:street":"Bentley Pl",
    "iso:country":"US",
    "sg:address":"4642 Bentley Pl",
    "sg:city":"Duluth",
    "sg:classifiers":[
        {
            "category":"Professional",
            "subcategory":"Computer Services",
            "type":"Services"
        }
    ],
    "sg:phone":"+1 770 662 8321",
    "sg:postcode":"30096",
    "sg:province":"GA",
    "sg:tags":[
        "related"
    ],
    "wof:name":"Fly-By-Day Consulting Inc",
    "wof:placetype":"venue"
},
  "geometry": {"coordinates":[-84.192931,33.978428],"type":"Point"}
}