{
  "type": "Feature",
  "properties": {
    "iso:country":"US",
    "sg:address":"997 Senoia Rd",
    "sg:city":"Tyrone",
    "sg:classifiers":[
        {
            "category":"Manufacturing",
            "subcategory":"Printing",
            "type":"Manufacturing & Wholesale Goods"
        }
    ],
    "sg:phone":"+1 770 487 7376",
    "sg:postcode":"30290",
    "sg:province":"GA",
    "sg:tags":[
        "commercial",
        "b",
        "printer",
        "lithographic",
        "typesetting"
    ],
    "wof:name":"Gunnin Graphics Inc",
    "wof:placetype":"venue"
},
  "geometry": {"coordinates":[-84.58895099999999,33.479884],"type":"Point"}
}