{
  "type": "Feature",
  "properties": {
    "iso:country":"US",
    "sg:address":"1941 S Cobb Dr",
    "sg:city":"Marietta",
    "sg:classifiers":[
        {
            "category":"Autos & Motor Vehicles",
            "subcategory":"Automobile Sales",
            "type":"Retail Goods"
        }
    ],
    "sg:phone":"+1 770 436 1760",
    "sg:postcode":"30060",
    "sg:province":"GA",
    "sg:tags":[
        "car",
        "used",
        "dealer"
    ],
    "wof:name":"Amigo Auto Sales Inc",
    "wof:placetype":"venue"
},
  "geometry": {"coordinates":[-84.542643,33.905779],"type":"Point"}
}