{
  "type": "Feature",
  "properties": {
    "iso:country":"US",
    "sg:address":"2233 Ballard Dr",
    "sg:city":"Macon",
    "sg:classifiers":[
        {
            "category":"Building & Trades",
            "subcategory":"Construction",
            "type":"Services"
        }
    ],
    "sg:phone":"+1 478 746 0804",
    "sg:postcode":"31206",
    "sg:province":"GA",
    "sg:tags":[
        "hanging",
        "contractor"
    ],
    "wof:name":"Hampton Painting",
    "wof:placetype":"venue"
},
  "geometry": {"coordinates":[-83.655078,32.820014],"type":"Point"}
}