{
  "type": "Feature",
  "properties": {
    "iso:country":"US",
    "sg:address":"7259 Laurel Creek Dr",
    "sg:city":"Stockbridge",
    "sg:classifiers":[
        {
            "category":"Building & Trades",
            "subcategory":"Equipment Rental",
            "type":"Services"
        }
    ],
    "sg:phone":"+1 770 961 9624",
    "sg:postcode":"30281",
    "sg:province":"GA",
    "sg:tags":[
        "equipment-repair",
        "restaurant"
    ],
    "wof:name":"Metro Restaurant Equipment Repair",
    "wof:placetype":"venue"
},
  "geometry": {"coordinates":[-84.29148600000001,33.555508],"type":"Point"}
}