{
  "type": "Feature",
  "properties": {
    "addr:full":"6401 Linecrest Dr Douglasville GA 30134",
    "addr:housenumber":"6401",
    "addr:postcode":"30134",
    "addr:street":"Linecrest Dr",
    "iso:country":"US",
    "sg:address":"6401 Linecrest Dr",
    "sg:city":"Douglasville",
    "sg:classifiers":[
        {
            "category":"Wholesale",
            "subcategory":"Durable Goods & Equipment",
            "type":"Manufacturing & Wholesale Goods"
        },
        {
            "category":"Farming",
            "subcategory":"Farm & Veterinary Services",
            "type":"Manufacturing & Wholesale Goods"
        }
    ],
    "sg:phone":"+1 770 947 6176",
    "sg:postcode":"30134",
    "sg:province":"GA",
    "sg:tags":[
        "exporter",
        "cotton",
        "ginning"
    ],
    "wof:name":"Mar Gins Mobile Maintenance",
    "wof:placetype":"venue"
},
  "geometry": {"coordinates":[-84.74035000000001,33.770575],"type":"Point"}
}