{
  "type": "Feature",
  "properties": {
    "addr:full":"1372 Fama Dr NE Atlanta GA 30329",
    "addr:housenumber":"1372",
    "addr:postcode":"30329",
    "addr:street":"Fama Dr Ne",
    "iso:country":"US",
    "sg:address":"1372 Fama Dr NE",
    "sg:city":"Atlanta",
    "sg:classifiers":[
        {
            "category":"Building & Trades",
            "subcategory":"Construction",
            "type":"Services"
        }
    ],
    "sg:phone":"+1 678 585 9191",
    "sg:postcode":"30329",
    "sg:province":"GA",
    "sg:tags":[
        "house"
    ],
    "wof:name":"Encore Construction",
    "wof:placetype":"venue"
},
  "geometry": {"coordinates":[-84.311497,33.82106],"type":"Point"}
}