{
  "type": "Feature",
  "properties": {
    "iso:country":"US",
    "sg:address":"1665 Washington Rd",
    "sg:city":"Thomson",
    "sg:classifiers":[
        {
            "category":"Real Estate",
            "subcategory":"Real Estate Agent",
            "type":"Services"
        }
    ],
    "sg:phone":"+1 706 595 8421",
    "sg:postcode":"30824",
    "sg:province":"GA",
    "wof:name":"Century 21 Larry Miller",
    "wof:placetype":"venue"
},
  "geometry": {"coordinates":[-82.5035,33.501009],"type":"Point"}
}