{
  "type": "Feature",
  "properties": {
    "addr:full":"5032 Augusta Rd Savannah GA 31408",
    "addr:housenumber":"5032",
    "addr:postcode":"31408",
    "addr:street":"Augusta Rd",
    "iso:country":"US",
    "sg:address":"5032 Augusta Rd",
    "sg:city":"Savannah",
    "sg:classifiers":[
        {
            "category":"Insurance",
            "subcategory":"Insurance Agent",
            "type":"Services"
        }
    ],
    "sg:phone":"+1 912 964 2781",
    "sg:postcode":"31408",
    "sg:province":"GA",
    "sg:website":"http://www.realpages.com/sites/fountaininsurance",
    "wof:name":"Fountain Insurance Agency",
    "wof:placetype":"venue"
},
  "geometry": {"coordinates":[-81.162116,32.112124],"type":"Point"}
}