{
  "type": "Feature",
  "properties": {
    "iso:country":"US",
    "sg:address":"3292 Allen Cir",
    "sg:city":"Loganville",
    "sg:classifiers":[
        {
            "category":"Train Station",
            "subcategory":"Light Rail",
            "type":"Transportation"
        }
    ],
    "sg:phone":"+1 770 554 0486",
    "sg:postcode":"30052",
    "sg:province":"GA",
    "sg:tags":[
        "lighting",
        "contractor"
    ],
    "sg:website":"http://www.niteliteinspirations.com",
    "wof:name":"Nite Lite Designs",
    "wof:placetype":"venue"
},
  "geometry": {"coordinates":[-83.864197,33.819794],"type":"Point"}
}