{
  "type": "Feature",
  "properties": {
    "addr:full":"629 Dawsonville Hwy Gainesville GA 30501",
    "addr:housenumber":"629",
    "addr:postcode":"30501",
    "addr:street":"Dawsonville Hwy",
    "iso:country":"US",
    "sg:address":"629 Dawsonville Hwy",
    "sg:city":"Gainesville",
    "sg:classifiers":[
        {
            "category":"Professional",
            "subcategory":"Management & Consulting",
            "type":"Services"
        }
    ],
    "sg:phone":"+1 770 534 1399",
    "sg:postcode":"30501",
    "sg:province":"GA",
    "wof:name":"AFLAC",
    "wof:placetype":"venue"
},
  "geometry": {"coordinates":[-83.84828,34.295743],"type":"Point"}
}