{
  "type": "Feature",
  "properties": {
    "addr:full":"5015 Floyd Rd SW Mableton GA 30126",
    "addr:housenumber":"5015",
    "addr:postcode":"30126",
    "addr:street":"Floyd Rd Sw",
    "iso:country":"US",
    "sg:address":"5015 Floyd Rd SW",
    "sg:city":"Mableton",
    "sg:classifiers":[
        {
            "category":"Banks & Credit Unions",
            "subcategory":"Bank",
            "type":"Services"
        }
    ],
    "sg:phone":"+1 770 739 5442",
    "sg:postcode":"30126",
    "sg:province":"GA",
    "sg:tags":[
        "broker",
        "factoring"
    ],
    "wof:name":"Diversified Funding Specialist",
    "wof:placetype":"venue"
},
  "geometry": {"coordinates":[-84.575608,33.829328],"type":"Point"}
}