{
  "type": "Feature",
  "properties": {
    "iso:country":"US",
    "sg:address":"6344 US Hwy 29",
    "sg:city":"Palmetto",
    "sg:classifiers":[
        {
            "category":"Freight",
            "type":"Transportation"
        }
    ],
    "sg:phone":"+1 770 463 8697",
    "sg:postcode":"30268",
    "sg:province":"GA",
    "sg:tags":[
        "mobile",
        "home"
    ],
    "wof:name":"Triple A Home Mobile I & S",
    "wof:placetype":"venue"
},
  "geometry": {"coordinates":[-84.672406,33.501091],"type":"Point"}
}