{
  "type": "Feature",
  "properties": {
    "addr:full":"1317 Athens Hwy Elberton GA 30635",
    "addr:housenumber":"1317",
    "addr:postcode":"30635",
    "addr:street":"Athens Hwy",
    "iso:country":"US",
    "sg:address":"1317 Athens Hwy",
    "sg:city":"Elberton",
    "sg:classifiers":[
        {
            "category":"Social Services",
            "type":"Services"
        }
    ],
    "sg:phone":"+1 706 283 8838",
    "sg:postcode":"30635",
    "sg:province":"GA",
    "wof:name":"Elbert Cnty Cncil For Effctive",
    "wof:placetype":"venue"
},
  "geometry": {"coordinates":[-82.90418099999999,34.109922],"type":"Point"}
}