{
  "type": "Feature",
  "properties": {
    "iso:country":"US",
    "sg:address":"2383 Akers Mill Rd SE",
    "sg:city":"Atlanta",
    "sg:classifiers":[
        {
            "category":"Travel",
            "subcategory":"Hotels & Motels",
            "type":"Entertainment"
        }
    ],
    "sg:phone":"+1 404 559 7413",
    "sg:postcode":"30339",
    "sg:province":"GA",
    "wof:name":"Atlanta Westin",
    "wof:placetype":"venue"
},
  "geometry": {"coordinates":[-84.45156900000001,33.895249],"type":"Point"}
}