{
  "type": "Feature",
  "properties": {
    "addr:full":"313 Dividend Dr Peachtree City GA 30269",
    "addr:housenumber":"313",
    "addr:postcode":"30269",
    "addr:street":"Dividend Dr",
    "iso:country":"US",
    "sg:address":"313 Dividend Dr",
    "sg:city":"Peachtree City",
    "sg:classifiers":[
        {
            "category":"Recreation",
            "subcategory":"Arcade",
            "type":"Entertainment"
        }
    ],
    "sg:phone":"+1 770 631 4003",
    "sg:postcode":"30269",
    "sg:province":"GA",
    "sg:tags":[
        "casino"
    ],
    "wof:name":"Xplayground Console Gaming Ctr",
    "wof:placetype":"venue"
},
  "geometry": {"coordinates":[-84.581945,33.382521],"type":"Point"}
}