{
  "type": "Feature",
  "properties": {
    "iso:country":"US",
    "sg:address":"1042 Rockcrest Dr",
    "sg:city":"Marietta",
    "sg:classifiers":[
        {
            "category":"Professional",
            "subcategory":"Management & Consulting",
            "type":"Services"
        }
    ],
    "sg:phone":"+1 770 973 8537",
    "sg:postcode":"30062",
    "sg:province":"GA",
    "wof:name":"Claudia Crim Inc",
    "wof:placetype":"venue"
},
  "geometry": {"coordinates":[-84.50492300000001,33.976958],"type":"Point"}
}