{
  "type": "Feature",
  "properties": {
    "addr:full":"1010 Live Oak Rd Tybee Island GA 31328",
    "addr:housenumber":"1010",
    "addr:postcode":"31328",
    "addr:street":"Live Oak Rd",
    "iso:country":"US",
    "sg:address":"1010 Live Oak Rd",
    "sg:city":"Tybee Island",
    "sg:classifiers":[
        {
            "category":"Travel",
            "subcategory":"Hotels & Motels",
            "type":"Entertainment"
        }
    ],
    "sg:phone":"+1 912 786 6478",
    "sg:postcode":"31328",
    "sg:province":"GA",
    "sg:tags":[
        "resort"
    ],
    "sg:website":"www.tybeeplace.com",
    "wof:name":"TYBEEPLACE.COM",
    "wof:placetype":"venue"
},
  "geometry": {"coordinates":[-80.853177,32.020819],"type":"Point"}
}