{
  "type": "Feature",
  "properties": {
    "iso:country":"US",
    "sg:address":"2380 Northside Parkway NW",
    "sg:city":"Atlanta",
    "sg:classifiers":[
        {
            "category":"Real Estate",
            "subcategory":"Architect",
            "type":"Services"
        }
    ],
    "sg:phone":"+1 404 231 0712",
    "sg:postcode":"30327",
    "sg:province":"GA",
    "wof:name":"Thompson Romulus H Archt",
    "wof:placetype":"venue"
},
  "geometry": {"coordinates":[-84.41200499999999,33.840236],"type":"Point"}
}