{
  "type": "Feature",
  "properties": {
    "iso:country":"US",
    "sg:address":"1085 Waterbury Close",
    "sg:city":"Powder Springs",
    "sg:classifiers":[
        {
            "category":"Professional",
            "type":"Services"
        }
    ],
    "sg:phone":"+1 770 426 7050",
    "sg:postcode":"30127",
    "sg:province":"GA",
    "wof:name":"Unique Products Co",
    "wof:placetype":"venue"
},
  "geometry": {"coordinates":[-84.69100899999999,33.926094],"type":"Point"}
}