{
  "type": "Feature",
  "properties": {
    "addr:full":"303 Harper Valley Dr Tunnel Hill GA 30755",
    "addr:housenumber":"303",
    "addr:postcode":"30755",
    "addr:street":"Harper Valley Dr Tunnel Hill",
    "iso:country":"US",
    "sg:address":"303 Harper Valley Dr",
    "sg:city":"Tunnel Hill",
    "sg:classifiers":[
        {
            "category":"Insurance",
            "subcategory":"Insurance Agent",
            "type":"Services"
        }
    ],
    "sg:phone":"+1 706 516 9963",
    "sg:postcode":"30755",
    "sg:province":"GA",
    "wof:name":"Excalibur Claims Svc",
    "wof:placetype":"venue"
},
  "geometry": {"coordinates":[-85.043024,34.855615],"type":"Point"}
}