{
  "type": "Feature",
  "properties": {
    "addr:full":"255 Promenade Way SW Atlanta GA 30331",
    "addr:housenumber":"255",
    "addr:postcode":"30331",
    "addr:street":"Promenade Way Sw",
    "iso:country":"US",
    "sg:address":"255 Promenade Way SW",
    "sg:city":"Atlanta",
    "sg:classifiers":[
        {
            "category":"Real Estate",
            "subcategory":"Real Estate Agent",
            "type":"Services"
        }
    ],
    "sg:phone":"+1 404 346 7603",
    "sg:postcode":"30331",
    "sg:province":"GA",
    "sg:tags":[
        "investment"
    ],
    "wof:name":"Harris Realty Investments Inc",
    "wof:placetype":"venue"
},
  "geometry": {"coordinates":[-84.552757,33.707869],"type":"Point"}
}