{
  "type": "Feature",
  "properties": {
    "addr:full":"11109 Commerce St Summerville GA 30747",
    "addr:housenumber":"11109",
    "addr:postcode":"30747",
    "addr:street":"Commerce St",
    "iso:country":"US",
    "sg:address":"11109 Commerce St",
    "sg:city":"Summerville",
    "sg:classifiers":[
        {
            "category":"Restaurant",
            "type":"Food & Drink"
        }
    ],
    "sg:phone":"+1 706 857 5551",
    "sg:postcode":"30747",
    "sg:province":"GA",
    "sg:tags":[
        "eating"
    ],
    "wof:name":"Digi Byte",
    "wof:placetype":"venue"
},
  "geometry": {"coordinates":[-85.338037,34.492528],"type":"Point"}
}