{
  "type": "Feature",
  "properties": {
    "addr:full":"3365 Buford Hwy NE Atlanta GA 30329",
    "addr:housenumber":"3365",
    "addr:postcode":"30329",
    "addr:street":"Buford Hwy Ne",
    "iso:country":"US",
    "sg:address":"3365 Buford Hwy NE",
    "sg:city":"Atlanta",
    "sg:classifiers":[
        {
            "category":"Fast Food",
            "type":"Food & Drink"
        },
        {
            "category":"Restaurant",
            "type":"Food & Drink"
        }
    ],
    "sg:phone":"+1 404 321 6050",
    "sg:postcode":"30329",
    "sg:province":"GA",
    "sg:tags":[
        "take",
        "pizza"
    ],
    "sg:website":"www.mygoodfellows.com",
    "wof:name":"Goodfellows Pizza",
    "wof:placetype":"venue"
},
  "geometry": {"coordinates":[-84.327741,33.843815],"type":"Point"}
}