{
  "type": "Feature",
  "properties": {
    "iso:country":"US",
    "sg:address":"593 S Atlanta St",
    "sg:city":"Roswell",
    "sg:classifiers":[
        {
            "category":"Professional",
            "type":"Services"
        }
    ],
    "sg:phone":"+1 770 650 7086",
    "sg:postcode":"30075",
    "sg:province":"GA",
    "wof:name":"Cambridge Warsaw LLC",
    "wof:placetype":"venue"
},
  "geometry": {"coordinates":[-84.362751,34.012182],"type":"Point"}
}