{
  "type": "Feature",
  "properties": {
    "iso:country":"US",
    "sg:address":"2459 N. Decatur Road",
    "sg:city":"Decatur",
    "sg:classifiers":[
        {
            "category":"Personal",
            "subcategory":"Beauty Salon",
            "type":"Services"
        }
    ],
    "sg:phone":"+1 404 929 8801",
    "sg:postcode":"30033",
    "sg:province":"GA",
    "sg:tags":[
        "hair"
    ],
    "sg:website":"www.segosalon.com",
    "wof:name":"Sego Salon",
    "wof:placetype":"venue"
},
  "geometry": {"coordinates":[-84.29241500000001,33.793579],"type":"Point"}
}