{
  "type": "Feature",
  "properties": {
    "addr:full":"441 Summer Dr Atlanta GA 30328",
    "addr:housenumber":"441",
    "addr:postcode":"30328",
    "addr:street":"Summer Dr",
    "iso:country":"US",
    "sg:address":"441 Summer Dr",
    "sg:city":"Atlanta",
    "sg:classifiers":[
        {
            "category":"Professional",
            "type":"Services"
        }
    ],
    "sg:phone":"+1 678 320 0847",
    "sg:postcode":"30328",
    "sg:province":"GA",
    "wof:name":"Otcx LLC",
    "wof:placetype":"venue"
},
  "geometry": {"coordinates":[-84.35215700000001,33.925506],"type":"Point"}
}