{
  "type": "Feature",
  "properties": {
    "addr:full":"195 Center Hill School Rd Crawfordville GA 30631",
    "addr:housenumber":"195",
    "addr:postcode":"30631",
    "addr:street":"Center;School Rd",
    "iso:country":"US",
    "sg:address":"195 Center Hill School Rd",
    "sg:city":"Crawfordville",
    "sg:classifiers":[
        {
            "category":"Food & Beverages",
            "subcategory":"Groceries & Convenience Stores",
            "type":"Retail Goods"
        }
    ],
    "sg:phone":"+1 706 456 2306",
    "sg:postcode":"30631",
    "sg:province":"GA",
    "wof:name":"Bills Grocery & Building Sup",
    "wof:placetype":"venue"
},
  "geometry": {"coordinates":[-82.972303,33.575393],"type":"Point"}
}