{
  "type": "Feature",
  "properties": {
    "iso:country":"US",
    "sg:address":"300 Jackson St",
    "sg:city":"Douglas",
    "sg:classifiers":[
        {
            "category":"Manufacturing",
            "subcategory":"Rubber & Plastics",
            "type":"Manufacturing & Wholesale Goods"
        },
        {
            "category":"Manufacturing",
            "subcategory":"Motor Vehicles & Parts",
            "type":"Manufacturing & Wholesale Goods"
        }
    ],
    "sg:phone":"+1 912 383 6228",
    "sg:postcode":"31533",
    "sg:province":"GA",
    "sg:tags":[
        "product",
        "mfg",
        "fiberglass",
        "foam",
        "trailer",
        "manufacturer"
    ],
    "wof:name":"Lott Manufacturing Inc",
    "wof:placetype":"venue"
},
  "geometry": {"coordinates":[-82.852769,31.511203],"type":"Point"}
}