{
  "type": "Feature",
  "properties": {
    "addr:full":"2375 Wesley Chapel Rd Decatur GA 30035",
    "addr:housenumber":"2375",
    "addr:postcode":"30035",
    "addr:street":"Wesley Chapel Rd",
    "iso:country":"US",
    "sg:address":"2375 Wesley Chapel Rd",
    "sg:city":"Decatur",
    "sg:classifiers":[
        {
            "category":"Professional",
            "subcategory":"Management & Consulting",
            "type":"Services"
        }
    ],
    "sg:phone":"+1 404 822 3894",
    "sg:postcode":"30035",
    "sg:province":"GA",
    "sg:tags":[
        "development",
        "business"
    ],
    "wof:name":"A Wilson Ventures Corporation",
    "wof:placetype":"venue"
},
  "geometry": {"coordinates":[-84.215464,33.719487],"type":"Point"}
}