{
  "type": "Feature",
  "properties": {
    "iso:country":"US",
    "sg:address":"223 Brookcliff Trce",
    "sg:city":"Marietta",
    "sg:classifiers":[
        {
            "category":"Professional",
            "subcategory":"Lawyer & Legal Services",
            "type":"Services"
        }
    ],
    "sg:phone":"+1 770 977 2237",
    "sg:postcode":"30068",
    "sg:province":"GA",
    "wof:name":"Gordon Richard A Atty",
    "wof:placetype":"venue"
},
  "geometry": {"coordinates":[-84.441597,33.9552],"type":"Point"}
}