{
  "type": "Feature",
  "properties": {
    "addr:full":"5232 E Wolf Creek Rd Tiger GA 30525",
    "addr:housenumber":"5232",
    "addr:postcode":"30525",
    "addr:street":"E Wolf Creek Rd",
    "iso:country":"US",
    "sg:address":"5232 E Wolf Creek Rd",
    "sg:city":"Tiger",
    "sg:classifiers":[
        {
            "category":"Building & Trades",
            "subcategory":"Construction",
            "type":"Services"
        }
    ],
    "sg:phone":"+1 706 782 4652",
    "sg:postcode":"30525",
    "sg:province":"GA",
    "sg:tags":[
        "concrete",
        "contractor"
    ],
    "wof:name":"Taylor Concrete Foundations",
    "wof:placetype":"venue"
},
  "geometry": {"coordinates":[-83.36554700000001,34.814455],"type":"Point"}
}