{
  "type": "Feature",
  "properties": {
    "iso:country":"US",
    "sg:address":"162 Cade St",
    "sg:city":"Hartwell",
    "sg:classifiers":[
        {
            "category":"Health Services",
            "subcategory":"Doctor",
            "type":"Services"
        }
    ],
    "sg:phone":"+1 706 376 6570",
    "sg:postcode":"30643",
    "sg:province":"GA",
    "sg:tags":[
        "physician",
        "surgeon"
    ],
    "wof:name":"M Samer Hamwy MD",
    "wof:placetype":"venue"
},
  "geometry": {"coordinates":[-82.94020500000001,34.346843],"type":"Point"}
}