{
  "type": "Feature",
  "properties": {
    "iso:country":"US",
    "sg:address":"33 Mansell Ct",
    "sg:city":"Roswell",
    "sg:classifiers":[
        {
            "category":"Professional",
            "subcategory":"Advertising",
            "type":"Services"
        }
    ],
    "sg:phone":"+1 770 998 5701",
    "sg:postcode":"30076",
    "sg:province":"GA",
    "sg:tags":[
        "designer",
        "display",
        "producer"
    ],
    "wof:name":"Spectrum 4 Exhibitronics",
    "wof:placetype":"venue"
},
  "geometry": {"coordinates":[-84.33165700000001,34.040379],"type":"Point"}
}