{
  "type": "Feature",
  "properties": {
    "iso:country":"US",
    "sg:address":"132 Threatt Rd",
    "sg:city":"Jefferson",
    "sg:classifiers":[
        {
            "category":"Home & Garden",
            "subcategory":"Carpets & Floor Coverings",
            "type":"Retail Goods"
        }
    ],
    "sg:phone":"+1 706 335 0730",
    "sg:postcode":"30549",
    "sg:province":"GA",
    "wof:name":"Quality Carpet",
    "wof:placetype":"venue"
},
  "geometry": {"coordinates":[-83.466982,34.129921],"type":"Point"}
}