{
  "type": "Feature",
  "properties": {
    "iso:country":"US",
    "sg:address":"3299 Alabama Hwy",
    "sg:city":"Rome",
    "sg:classifiers":[
        {
            "category":"Retail",
            "subcategory":"Veterinary Services",
            "type":"Services"
        }
    ],
    "sg:phone":"+1 706 232 0168",
    "sg:postcode":"30165",
    "sg:province":"GA",
    "sg:tags":[
        "veterinarian"
    ],
    "wof:name":"Lake View Animal Clinic",
    "wof:placetype":"venue"
},
  "geometry": {"coordinates":[-85.269007,34.272415],"type":"Point"}
}