{
  "type": "Feature",
  "properties": {
    "addr:full":"1725 Roswell Rd Marietta GA 30062",
    "addr:housenumber":"1725",
    "addr:postcode":"30062",
    "addr:street":"Roswell Rd",
    "iso:country":"US",
    "sg:address":"1725 Roswell Rd",
    "sg:city":"Marietta",
    "sg:classifiers":[
        {
            "category":"Building & Trades",
            "subcategory":"Cleaning & Sanitation",
            "type":"Services"
        }
    ],
    "sg:phone":"+1 770 509 0684",
    "sg:postcode":"30062",
    "sg:province":"GA",
    "sg:tags":[
        "house"
    ],
    "wof:name":"Ju-Housekeeper",
    "wof:placetype":"venue"
},
  "geometry": {"coordinates":[-84.502449,33.955962],"type":"Point"}
}