{
  "type": "Feature",
  "properties": {
    "iso:country":"US",
    "sg:address":"906 Atlantic Ave",
    "sg:city":"Waycross",
    "sg:classifiers":[
        {
            "category":"Building & Trades",
            "subcategory":"Construction",
            "type":"Services"
        }
    ],
    "sg:phone":"+1 912 284 1527",
    "sg:postcode":"31501",
    "sg:province":"GA",
    "sg:tags":[
        "company"
    ],
    "wof:name":"Dowling Construction",
    "wof:placetype":"venue"
},
  "geometry": {"coordinates":[-82.33611500000001,31.216128],"type":"Point"}
}