{
  "type": "Feature",
  "properties": {
    "iso:country":"US",
    "sg:address":"218 2nd St",
    "sg:city":"Manchester",
    "sg:classifiers":[
        {
            "category":"Shopping",
            "subcategory":"Florist",
            "type":"Retail Goods"
        }
    ],
    "sg:phone":"+1 706 846 3957",
    "sg:postcode":"31816",
    "sg:province":"GA",
    "wof:name":"Dee Dee's Flower & Gifts Inc",
    "wof:placetype":"venue"
},
  "geometry": {"coordinates":[-84.617099,32.852444],"type":"Point"}
}