{
  "type": "Feature",
  "properties": {
    "addr:full":"5944 State Hwy 92 Acworth GA 30102",
    "addr:housenumber":"5944",
    "addr:postcode":"30102",
    "addr:street":"State Hwy 92",
    "iso:country":"US",
    "sg:address":"5944 State Hwy 92",
    "sg:city":"Acworth",
    "sg:classifiers":[
        {
            "category":"Autos & Motor Vehicles",
            "subcategory":"Automobile Sales",
            "type":"Retail Goods"
        }
    ],
    "sg:phone":"+1 770 517 9454",
    "sg:postcode":"30102",
    "sg:province":"GA",
    "sg:tags":[
        "car",
        "dealer"
    ],
    "wof:name":"Extreme Auto Sales",
    "wof:placetype":"venue"
},
  "geometry": {"coordinates":[-84.590164,34.087716],"type":"Point"}
}