{
  "type": "Feature",
  "properties": {
    "addr:full":"124 S Hulin Ave Tignall GA 30668",
    "addr:housenumber":"124",
    "addr:postcode":"30668",
    "addr:street":"S Hulin Ave",
    "iso:country":"US",
    "sg:address":"124 S Hulin Ave",
    "sg:city":"Tignall",
    "sg:classifiers":[
        {
            "category":"Government",
            "subcategory":"City Hall",
            "type":"Public Place"
        }
    ],
    "sg:phone":"+1 706 285 2959",
    "sg:postcode":"30668",
    "sg:province":"GA",
    "wof:name":"City Hall Tignall Fax Line",
    "wof:placetype":"venue"
},
  "geometry": {"coordinates":[-82.74131300000001,33.867196],"type":"Point"}
}