{
  "type": "Feature",
  "properties": {
    "addr:full":"2351 Wadley Rd Waycross GA 31503",
    "addr:housenumber":"2351",
    "addr:postcode":"31503",
    "addr:street":"Wadley Rd",
    "iso:country":"US",
    "sg:address":"2351 Wadley Rd",
    "sg:city":"Waycross",
    "sg:classifiers":[
        {
            "category":"Place Of Worship",
            "subcategory":"Church",
            "type":"Public Place"
        },
        {
            "category":"Place Of Worship",
            "type":"Public Place"
        }
    ],
    "sg:phone":"+1 912 287 0490",
    "sg:postcode":"31503",
    "sg:province":"GA",
    "sg:tags":[
        "churches-baptist-general",
        "churches-baptist"
    ],
    "wof:name":"Ware Baptist Church",
    "wof:placetype":"venue"
},
  "geometry": {"coordinates":[-82.397777,31.194863],"type":"Point"}
}