{
  "type": "Feature",
  "properties": {
    "iso:country":"US",
    "sg:address":"1202 Primrose View Cir",
    "sg:city":"Lawrenceville",
    "sg:classifiers":[
        {
            "category":"Shopping",
            "subcategory":"Gifts & Souvenirs",
            "type":"Retail Goods"
        },
        {
            "category":"Manufacturing",
            "subcategory":"Retail Goods",
            "type":"Manufacturing & Wholesale Goods"
        }
    ],
    "sg:phone":"+1 770 722 3036",
    "sg:postcode":"30044",
    "sg:province":"GA",
    "sg:tags":[
        "shop",
        "giftware's-wholesale",
        "manufacturer"
    ],
    "wof:name":"Rl Enterprises",
    "wof:placetype":"venue"
},
  "geometry": {"coordinates":[-84.087749,33.939557],"type":"Point"}
}