{
  "type": "Feature",
  "properties": {
    "iso:country":"US",
    "sg:address":"1662 W Ware Ave",
    "sg:city":"Atlanta",
    "sg:classifiers":[
        {
            "category":"Organizations",
            "subcategory":"Religious Organization",
            "type":"Services"
        }
    ],
    "sg:phone":"+1 404 761 7027",
    "sg:postcode":"30344",
    "sg:province":"GA",
    "sg:tags":[
        "church"
    ],
    "wof:name":"New Hope Youth Svc Inc",
    "wof:placetype":"venue"
},
  "geometry": {"coordinates":[-84.442905,33.682273],"type":"Point"}
}