{
  "type": "Feature",
  "properties": {
    "addr:full":"2395 Mills Wood Run Canton GA 30114",
    "addr:housenumber":"2395",
    "addr:postcode":"30114",
    "addr:street":"Mills Wood Run",
    "iso:country":"US",
    "sg:address":"2395 Mills Wood Run",
    "sg:city":"Canton",
    "sg:classifiers":[
        {
            "category":"Wholesale",
            "subcategory":"Electrical",
            "type":"Manufacturing & Wholesale Goods"
        }
    ],
    "sg:phone":"+1 770 345 1435",
    "sg:postcode":"30114",
    "sg:province":"GA",
    "sg:tags":[
        "equipment"
    ],
    "wof:name":"United Protective Services",
    "wof:placetype":"venue"
},
  "geometry": {"coordinates":[-84.51915700000001,34.188081],"type":"Point"}
}