{
  "type": "Feature",
  "properties": {
    "addr:full":"210 Sandy Springs Pl NE Atlanta GA 30328",
    "addr:housenumber":"210",
    "addr:postcode":"30328",
    "addr:street":"Sandy;Pl Ne",
    "iso:country":"US",
    "sg:address":"210 Sandy Springs Pl NE",
    "sg:city":"Atlanta",
    "sg:classifiers":[
        {
            "category":"Banks & Credit Unions",
            "subcategory":"Investment Brokerage",
            "type":"Services"
        }
    ],
    "sg:phone":"+1 404 705 8565",
    "sg:postcode":"30328",
    "sg:province":"GA",
    "sg:tags":[
        "security"
    ],
    "wof:name":"Sessions & Co",
    "wof:placetype":"venue"
},
  "geometry": {"coordinates":[-84.381236,33.921646],"type":"Point"}
}