{
  "type": "Feature",
  "properties": {
    "iso:country":"US",
    "sg:address":"110 S Broad St",
    "sg:city":"Thomasville",
    "sg:classifiers":[
        {
            "category":"Home & Garden",
            "subcategory":"Furniture",
            "type":"Retail Goods"
        }
    ],
    "sg:phone":"+1 229 225 1771",
    "sg:postcode":"31792",
    "sg:province":"GA",
    "wof:name":"Hollybrook Inc",
    "wof:placetype":"venue"
},
  "geometry": {"coordinates":[-83.98021199999999,30.837328],"type":"Point"}
}