{
  "type": "Feature",
  "properties": {
    "addr:full":"811 Putney Ave Albany GA 31705",
    "addr:housenumber":"811",
    "addr:postcode":"31705",
    "addr:street":"Putney Ave",
    "iso:country":"US",
    "sg:address":"811 Putney Ave",
    "sg:city":"Albany",
    "sg:classifiers":[
        {
            "category":"Professional",
            "type":"Services"
        }
    ],
    "sg:phone":"+1 229 883 6401",
    "sg:postcode":"31705",
    "sg:province":"GA",
    "wof:name":"Figgware",
    "wof:placetype":"venue"
},
  "geometry": {"coordinates":[-84.132892,31.480992],"type":"Point"}
}