{
  "type": "Feature",
  "properties": {
    "addr:full":"5101 Old Dawson Rd Albany GA 31721",
    "addr:housenumber":"5101",
    "addr:postcode":"31721",
    "addr:street":"Old Dawson Rd",
    "iso:country":"US",
    "sg:address":"5101 Old Dawson Rd",
    "sg:city":"Albany",
    "sg:classifiers":[
        {
            "category":"Recreation",
            "type":"Entertainment"
        }
    ],
    "sg:phone":"+1 229 888 2992",
    "sg:postcode":"31721",
    "sg:province":"GA",
    "sg:tags":[
        "club",
        "membership"
    ],
    "wof:name":"United States Pony Clubs Inc",
    "wof:placetype":"venue"
},
  "geometry": {"coordinates":[-84.28952099999999,31.610954],"type":"Point"}
}