{
  "type": "Feature",
  "properties": {
    "iso:country":"US",
    "sg:address":"4925 S Royal Atlanta Dr",
    "sg:city":"Tucker",
    "sg:classifiers":[
        {
            "category":"Manufacturing",
            "subcategory":"Metals",
            "type":"Manufacturing & Wholesale Goods"
        }
    ],
    "sg:phone":"+1 770 934 7100",
    "sg:postcode":"30084",
    "sg:province":"GA",
    "sg:tags":[
        "plating"
    ],
    "sg:website":"www.dixie-industrial.com",
    "wof:name":"Dixie Industrial Finishing Co",
    "wof:placetype":"venue"
},
  "geometry": {"coordinates":[-84.177505,33.856282],"type":"Point"}
}