{
  "type": "Feature",
  "properties": {
    "addr:full":"1420 Kellogg Creek Rd Acworth GA 30102",
    "addr:housenumber":"1420",
    "addr:postcode":"30102",
    "addr:street":"Kellogg Creek Rd",
    "iso:country":"US",
    "sg:address":"1420 Kellogg Creek Rd",
    "sg:city":"Acworth",
    "sg:classifiers":[
        {
            "category":"Food & Beverages",
            "subcategory":"Groceries & Convenience Stores",
            "type":"Retail Goods"
        }
    ],
    "sg:phone":"+1 770 928 7208",
    "sg:postcode":"30102",
    "sg:province":"GA",
    "sg:tags":[
        "station",
        "gasoline"
    ],
    "wof:name":"Three Way Grocery",
    "wof:placetype":"venue"
},
  "geometry": {"coordinates":[-84.585578,34.119864],"type":"Point"}
}