{
  "type": "Feature",
  "properties": {
    "iso:country":"US",
    "sg:address":"814 New Hope Rd",
    "sg:city":"Fayetteville",
    "sg:classifiers":[
        {
            "category":"Organizations",
            "subcategory":"Religious Organization",
            "type":"Services"
        }
    ],
    "sg:phone":"+1 770 460 5904",
    "sg:postcode":"30214",
    "sg:province":"GA",
    "sg:tags":[
        "church"
    ],
    "wof:name":"Fayette Seventh Day Adventist",
    "wof:placetype":"venue"
},
  "geometry": {"coordinates":[-84.483132,33.504976],"type":"Point"}
}