{
  "type": "Feature",
  "properties": {
    "addr:full":"1313 Rogers St Savannah GA 31415",
    "addr:housenumber":"1313",
    "addr:postcode":"31415",
    "addr:street":"Rogers St",
    "iso:country":"US",
    "sg:address":"1313 Rogers St",
    "sg:city":"Savannah",
    "sg:classifiers":[
        {
            "category":"Wholesale",
            "subcategory":"Construction Materials",
            "type":"Manufacturing & Wholesale Goods"
        }
    ],
    "sg:phone":"+1 912 236 7923",
    "sg:postcode":"31415",
    "sg:province":"GA",
    "sg:tags":[
        "building",
        "roofing",
        "siding"
    ],
    "wof:name":"ABC Supply",
    "wof:placetype":"venue"
},
  "geometry": {"coordinates":[-81.11567700000001,32.088633],"type":"Point"}
}