{
  "type": "Feature",
  "properties": {
    "addr:full":"1123 Manning Farms Ct Atlanta GA 30338",
    "addr:housenumber":"1123",
    "addr:postcode":"30338",
    "addr:street":"Manning Farms Ct",
    "iso:country":"US",
    "sg:address":"1123 Manning Farms Ct",
    "sg:city":"Atlanta",
    "sg:classifiers":[
        {
            "category":"Wholesale",
            "subcategory":"Chemicals & Plastics",
            "type":"Manufacturing & Wholesale Goods"
        }
    ],
    "sg:phone":"+1 770 395 0387",
    "sg:postcode":"30338",
    "sg:province":"GA",
    "sg:tags":[
        "intermediate"
    ],
    "wof:name":"Kensington Industries Inc",
    "wof:placetype":"venue"
},
  "geometry": {"coordinates":[-84.340198,33.966627],"type":"Point"}
}