{
  "type": "Feature",
  "properties": {
    "addr:full":"6725 Highway 92 Woodstock GA 30189",
    "addr:housenumber":"6725",
    "addr:postcode":"30189",
    "addr:street":"Highway 92",
    "iso:country":"US",
    "sg:address":"6725 Highway 92",
    "sg:city":"Woodstock",
    "sg:classifiers":[
        {
            "category":"Banks & Credit Unions",
            "subcategory":"Bank",
            "type":"Services"
        },
        {
            "category":"Banks & Credit Unions",
            "subcategory":"Financial Services",
            "type":"Services"
        }
    ],
    "sg:phone":"+1 770 926 6166",
    "sg:postcode":"30189",
    "sg:province":"GA",
    "sg:tags":[
        "commercial",
        "loan",
        "saving",
        "mortgage"
    ],
    "sg:website":"https://www.wellsfargo.com/wfonline/",
    "wof:name":"Wachovia Bank",
    "wof:placetype":"venue"
},
  "geometry": {"coordinates":[-84.576847,34.087972],"type":"Point"}
}