{
  "type": "Feature",
  "properties": {
    "addr:full":"2100 Sunset Blvd Jesup GA 31545",
    "addr:housenumber":"2100",
    "addr:postcode":"31545",
    "addr:street":"Sunset Blvd",
    "iso:country":"US",
    "sg:address":"2100 Sunset Blvd",
    "sg:city":"Jesup",
    "sg:classifiers":[
        {
            "category":"Wholesale",
            "subcategory":"Durable Goods & Equipment",
            "type":"Manufacturing & Wholesale Goods"
        }
    ],
    "sg:phone":"+1 912 427 8734",
    "sg:postcode":"31545",
    "sg:province":"GA",
    "sg:tags":[
        "importer"
    ],
    "wof:name":"Ashley Manufacturing Corp",
    "wof:placetype":"venue"
},
  "geometry": {"coordinates":[-81.907456,31.603752],"type":"Point"}
}