{
  "type": "Feature",
  "properties": {
    "addr:full":"202 Ga Highway 49 N Byron GA 31008",
    "addr:housenumber":"202",
    "addr:postcode":"31008",
    "addr:street":"Ga Highway 49 N",
    "iso:country":"US",
    "sg:address":"202 Ga Highway 49 N",
    "sg:city":"Byron",
    "sg:classifiers":[
        {
            "category":"Shopping",
            "subcategory":"Mobile Phones",
            "type":"Retail Goods"
        }
    ],
    "sg:phone":"+1 478 956 6052",
    "sg:postcode":"31008",
    "sg:province":"GA",
    "wof:name":"Dixie Trails",
    "wof:placetype":"venue"
},
  "geometry": {"coordinates":[-83.752296,32.654701],"type":"Point"}
}