{
  "type": "Feature",
  "properties": {
    "addr:full":"1016 Debbie St Savannah GA 31410",
    "addr:housenumber":"1016",
    "addr:postcode":"31410",
    "addr:street":"Debbie St",
    "iso:country":"US",
    "sg:address":"1016 Debbie St",
    "sg:city":"Savannah",
    "sg:classifiers":[
        {
            "category":"Professional",
            "subcategory":"Computer Services",
            "type":"Services"
        }
    ],
    "sg:phone":"+1 912 897 5652",
    "sg:postcode":"31410",
    "sg:province":"GA",
    "wof:name":"New ERA Computer Svces",
    "wof:placetype":"venue"
},
  "geometry": {"coordinates":[-81.010464,32.047167],"type":"Point"}
}