{
  "type": "Feature",
  "properties": {
    "addr:full":"2121 Favor Rd SW Marietta GA 30060",
    "addr:housenumber":"2121",
    "addr:postcode":"30060",
    "addr:street":"Favor Rd Sw",
    "iso:country":"US",
    "sg:address":"2121 Favor Rd SW",
    "sg:city":"Marietta",
    "sg:classifiers":[
        {
            "category":"Professional",
            "type":"Services"
        }
    ],
    "sg:phone":"+1 678 305 0908",
    "sg:postcode":"30060",
    "sg:province":"GA",
    "wof:name":"My Hope Paper Products",
    "wof:placetype":"venue"
},
  "geometry": {"coordinates":[-84.56424199999999,33.901794],"type":"Point"}
}