{
  "type": "Feature",
  "properties": {
    "iso:country":"US",
    "sg:address":"2030 Norwich St",
    "sg:city":"Brunswick",
    "sg:classifiers":[
        {
            "category":"Retail",
            "subcategory":"Auto Repair",
            "type":"Services"
        }
    ],
    "sg:phone":"+1 912 265 6213",
    "sg:postcode":"31520",
    "sg:province":"GA",
    "sg:tags":[
        "automobile",
        "electric",
        "automotive"
    ],
    "wof:name":"Pitts Electric Service Co",
    "wof:placetype":"venue"
},
  "geometry": {"coordinates":[-81.494165,31.157731],"type":"Point"}
}