{
  "type": "Feature",
  "properties": {
    "iso:country":"US",
    "sg:address":"206 Peeble Creek Dr",
    "sg:city":"Toccoa",
    "sg:classifiers":[
        {
            "category":"Professional",
            "type":"Services"
        }
    ],
    "sg:phone":"+1 706 282 0018",
    "sg:postcode":"30577",
    "sg:province":"GA",
    "wof:name":"Joshua M Likins",
    "wof:placetype":"venue"
},
  "geometry": {"coordinates":[-83.307042,34.558688],"type":"Point"}
}