{
  "type": "Feature",
  "properties": {
    "addr:full":"2650 Dixie Rd Fort Benning GA 31905",
    "addr:housenumber":"2650",
    "addr:postcode":"31905",
    "addr:street":"Dixie Rd",
    "iso:country":"US",
    "sg:address":"2650 Dixie Rd",
    "sg:city":"Fort Benning",
    "sg:classifiers":[
        {
            "category":"Building & Trades",
            "subcategory":"Construction",
            "type":"Services"
        }
    ],
    "sg:phone":"+1 706 689 1630",
    "sg:postcode":"31905",
    "sg:province":"GA",
    "sg:tags":[
        "general",
        "contractor"
    ],
    "wof:name":"George Hicks Construction",
    "wof:placetype":"venue"
},
  "geometry": {"coordinates":[-84.95205799999999,32.352616],"type":"Point"}
}