{
  "type": "Feature",
  "properties": {
    "iso:country":"US",
    "sg:address":"100 E Montgomery St",
    "sg:city":"Villa Rica",
    "sg:classifiers":[
        {
            "category":"Personal",
            "subcategory":"Beauty Salon",
            "type":"Services"
        }
    ],
    "sg:phone":"+1 770 459 4745",
    "sg:postcode":"30180",
    "sg:province":"GA",
    "wof:name":"Upper Cut",
    "wof:placetype":"venue"
},
  "geometry": {"coordinates":[-84.917749,33.729959],"type":"Point"}
}