{
  "type": "Feature",
  "properties": {
    "iso:country":"US",
    "sg:address":"310 Brannon Rd",
    "sg:city":"Cumming",
    "sg:classifiers":[
        {
            "category":"Restaurant",
            "type":"Food & Drink"
        }
    ],
    "sg:menulink":"http://www.allmenus.com/ga/big-creek/105505-waffle-house/menu/",
    "sg:phone":"+1 770 844 1665",
    "sg:postcode":"30041",
    "sg:province":"GA",
    "sg:tags":[
        "american"
    ],
    "wof:name":"Waffle House",
    "wof:placetype":"venue"
},
  "geometry": {"coordinates":[-84.17317,34.155232],"type":"Point"}
}