{
  "type": "Feature",
  "properties": {
    "iso:country":"US",
    "sg:address":"4850 Sugarloaf Pkwy",
    "sg:city":"Lawrenceville",
    "sg:classifiers":[
        {
            "category":"Health Services",
            "subcategory":"Chiropractor",
            "type":"Services"
        }
    ],
    "sg:phone":"+1 770 817 4445",
    "sg:postcode":"30044",
    "sg:province":"GA",
    "sg:website":"www.chiropractorlawrencevillega.com",
    "wof:name":"Lawrenceville Chiropractic Aetna BCBS Cigna United",
    "wof:placetype":"venue"
},
  "geometry": {"coordinates":[-84.055226,33.954147],"type":"Point"}
}