{
  "type": "Feature",
  "properties": {
    "iso:country":"US",
    "sg:address":"54 Warehouse Rd",
    "sg:city":"Ringgold",
    "sg:classifiers":[
        {
            "category":"Home & Garden",
            "subcategory":"Home Furnishings",
            "type":"Retail Goods"
        }
    ],
    "sg:phone":"+1 706 937 3643",
    "sg:postcode":"30736",
    "sg:province":"GA",
    "sg:tags":[
        "fireplace"
    ],
    "wof:name":"Firesides",
    "wof:placetype":"venue"
},
  "geometry": {"coordinates":[-85.175383,34.96209],"type":"Point"}
}