{
  "type": "Feature",
  "properties": {
    "iso:country":"US",
    "sg:address":"220 College Ave",
    "sg:city":"Athens",
    "sg:classifiers":[
        {
            "category":"Professional",
            "subcategory":"Management & Consulting",
            "type":"Services"
        }
    ],
    "sg:phone":"+1 706 546 4045",
    "sg:postcode":"30601",
    "sg:province":"GA",
    "sg:tags":[
        "consultant",
        "business",
        "engineer"
    ],
    "sg:website":"http://www.changepartners.com",
    "wof:name":"Change Partners",
    "wof:placetype":"venue"
},
  "geometry": {"coordinates":[-83.375559,33.958673],"type":"Point"}
}