{
  "type": "Feature",
  "properties": {
    "iso:country":"US",
    "sg:address":"212 Lumpkin Rd",
    "sg:city":"Leesburg",
    "sg:classifiers":[
        {
            "category":"Manufacturing",
            "subcategory":"Chemicals & Compounds",
            "type":"Manufacturing & Wholesale Goods"
        }
    ],
    "sg:phone":"+1 229 928 6331",
    "sg:postcode":"31763",
    "sg:province":"GA",
    "sg:tags":[
        "preparation",
        "mfg"
    ],
    "wof:name":"Americus Chem Jantr & Pool Sup",
    "wof:placetype":"venue"
},
  "geometry": {"coordinates":[-84.14524,31.771262],"type":"Point"}
}