{
  "type": "Feature",
  "properties": {
    "addr:full":"8163 Old Atlanta Hwy Covington GA 30014",
    "addr:housenumber":"8163",
    "addr:postcode":"30014",
    "addr:street":"Old Atlanta Hwy",
    "iso:country":"US",
    "sg:address":"8163 Old Atlanta Hwy",
    "sg:city":"Covington",
    "sg:classifiers":[
        {
            "category":"Freight",
            "type":"Transportation"
        }
    ],
    "sg:phone":"+1 770 786 5369",
    "sg:postcode":"30014",
    "sg:province":"GA",
    "sg:tags":[
        "operator",
        "local",
        "trucking"
    ],
    "wof:name":"Dale Miller Trucking Co Inc",
    "wof:placetype":"venue"
},
  "geometry": {"coordinates":[-83.875142,33.607938],"type":"Point"}
}