{
  "type": "Feature",
  "properties": {
    "iso:country":"US",
    "sg:address":"6186 Central Church Rd",
    "sg:city":"Douglasville",
    "sg:classifiers":[
        {
            "category":"Retail",
            "subcategory":"Auto Repair",
            "type":"Services"
        }
    ],
    "sg:phone":"+1 770 949 4322",
    "sg:postcode":"30135",
    "sg:province":"GA",
    "sg:tags":[
        "automobile",
        "customizing"
    ],
    "wof:name":"UFO Imports",
    "wof:placetype":"venue"
},
  "geometry": {"coordinates":[-84.778271,33.709624],"type":"Point"}
}