{
  "type": "Feature",
  "properties": {
    "addr:full":"218 Church St NE Marietta GA 30060",
    "addr:housenumber":"218",
    "addr:postcode":"30060",
    "addr:street":"Church St Ne",
    "iso:country":"US",
    "sg:address":"218 Church St NE",
    "sg:city":"Marietta",
    "sg:classifiers":[
        {
            "category":"Real Estate",
            "subcategory":"Real Estate Agent",
            "type":"Services"
        }
    ],
    "sg:phone":"+1 770 428 4856",
    "sg:postcode":"30060",
    "sg:province":"GA",
    "wof:name":"Pressley Properties Lllp",
    "wof:placetype":"venue"
},
  "geometry": {"coordinates":[-84.550066,33.957074],"type":"Point"}
}