{
  "type": "Feature",
  "properties": {
    "iso:country":"US",
    "sg:address":"23 Ivory Ct",
    "sg:city":"Hiram",
    "sg:classifiers":[
        {
            "category":"Professional",
            "type":"Services"
        }
    ],
    "sg:phone":"+1 770 222 1424",
    "sg:postcode":"30141",
    "sg:province":"GA",
    "wof:name":"Southern Services",
    "wof:placetype":"venue"
},
  "geometry": {"coordinates":[-84.779338,33.874033],"type":"Point"}
}