{
  "type": "Feature",
  "properties": {
    "iso:country":"US",
    "sg:address":"2505 Johnson Dr Ste D",
    "sg:city":"Cumming",
    "sg:classifiers":[
        {
            "category":"Real Estate",
            "subcategory":"Real Estate Services",
            "type":"Services"
        },
        {
            "category":"Real Estate",
            "subcategory":"Real Estate Agent",
            "type":"Services"
        }
    ],
    "sg:phone":"+1 770 888 9142",
    "sg:postcode":"30040",
    "sg:province":"GA",
    "sg:tags":[
        "management"
    ],
    "wof:name":"Landmark Realty Assoc. Inc",
    "wof:placetype":"venue"
},
  "geometry": {"coordinates":[-84.105054,34.257642],"type":"Point"}
}