{
  "type": "Feature",
  "properties": {
    "iso:country":"US",
    "sg:address":"3587 US Hwy 17",
    "sg:city":"Brunswick",
    "sg:classifiers":[
        {
            "category":"Retail",
            "subcategory":"Auto Repair",
            "type":"Services"
        }
    ],
    "sg:phone":"+1 912 262 6546",
    "sg:postcode":"31523",
    "sg:province":"GA",
    "sg:tags":[
        "wrecker"
    ],
    "wof:name":"Expressway Towing",
    "wof:placetype":"venue"
},
  "geometry": {"coordinates":[-81.46895499999999,31.192037],"type":"Point"}
}