{
  "type": "Feature",
  "properties": {
    "addr:full":"2547 Lakebrook Ct Atlanta GA 30360",
    "addr:housenumber":"2547",
    "addr:postcode":"30360",
    "addr:street":"Lakebrook Ct",
    "iso:country":"US",
    "sg:address":"2547 Lakebrook Ct",
    "sg:city":"Atlanta",
    "sg:classifiers":[
        {
            "category":"Travel",
            "subcategory":"Travel Agent",
            "type":"Entertainment"
        }
    ],
    "sg:phone":"+1 770 457 1083",
    "sg:postcode":"30360",
    "sg:province":"GA",
    "sg:tags":[
        "operator",
        "tour"
    ],
    "wof:name":"Group Travel Management",
    "wof:placetype":"venue"
},
  "geometry": {"coordinates":[-84.280191,33.944271],"type":"Point"}
}