{
  "type": "Feature",
  "properties": {
    "addr:full":"3567 Buford Dr Buford GA 30519",
    "addr:housenumber":"3567",
    "addr:postcode":"30519",
    "addr:street":"Buford Dr",
    "iso:country":"US",
    "sg:address":"3567 Buford Dr",
    "sg:city":"Buford",
    "sg:classifiers":[
        {
            "category":"Autos & Motor Vehicles",
            "subcategory":"Auto Supplies",
            "type":"Retail Goods"
        }
    ],
    "sg:phone":"+1 678 546 7298",
    "sg:postcode":"30519",
    "sg:province":"GA",
    "sg:tags":[
        "tire"
    ],
    "sg:website":"www.discounttire.com",
    "wof:name":"Discount Tire",
    "wof:placetype":"venue"
},
  "geometry": {"coordinates":[-83.987419,34.081895],"type":"Point"}
}