{
  "type": "Feature",
  "properties": {
    "addr:full":"1369 Clairmont Rd Decatur GA 30033",
    "addr:housenumber":"1369",
    "addr:postcode":"30033",
    "addr:street":"Clairmont Rd",
    "iso:country":"US",
    "sg:address":"1369 Clairmont Rd",
    "sg:city":"Decatur",
    "sg:classifiers":[
        {
            "category":"Building & Trades",
            "subcategory":"Locksmith",
            "type":"Services"
        }
    ],
    "sg:phone":"+1 404 418 6500",
    "sg:postcode":"30033",
    "sg:province":"GA",
    "sg:tags":[
        "key"
    ],
    "wof:name":"24 7 Emergency Locksmith",
    "wof:placetype":"venue"
},
  "geometry": {"coordinates":[-84.305385,33.793593],"type":"Point"}
}