{
  "type": "Feature",
  "properties": {
    "iso:country":"US",
    "sg:address":"737 Pansy Ave",
    "sg:city":"Macon",
    "sg:classifiers":[
        {
            "category":"Place Of Worship",
            "subcategory":"Church",
            "type":"Public Place"
        },
        {
            "category":"Place Of Worship",
            "type":"Public Place"
        }
    ],
    "sg:phone":"+1 478 745 4010",
    "sg:postcode":"31204",
    "sg:province":"GA",
    "sg:tags":[
        "churches-baptist-general",
        "churches-baptist"
    ],
    "sg:website":"http://www.mvbcfocus.org",
    "wof:name":"Mt Vernon Baptist Church",
    "wof:placetype":"venue"
},
  "geometry": {"coordinates":[-83.668381,32.822775],"type":"Point"}
}