{
  "type": "Feature",
  "properties": {
    "iso:country":"US",
    "sg:address":"1427 Flatwoods Rd",
    "sg:city":"Elberton",
    "sg:classifiers":[
        {
            "category":"Farming",
            "subcategory":"Farm",
            "type":"Manufacturing & Wholesale Goods"
        }
    ],
    "sg:phone":"+1 706 283 6782",
    "sg:postcode":"30635",
    "sg:province":"GA",
    "sg:tags":[
        "crop",
        "general"
    ],
    "wof:name":"Cluck N Moo Farms Inc",
    "wof:placetype":"venue"
},
  "geometry": {"coordinates":[-82.73950600000001,34.041368],"type":"Point"}
}