{
  "type": "Feature",
  "properties": {
    "addr:full":"4500 Frederick Dr SW Atlanta GA 30336",
    "addr:housenumber":"4500",
    "addr:postcode":"30336",
    "addr:street":"Frederick Dr Sw",
    "iso:country":"US",
    "sg:address":"4500 Frederick Dr SW",
    "sg:city":"Atlanta",
    "sg:classifiers":[
        {
            "category":"Banks & Credit Unions",
            "subcategory":"Financial Services",
            "type":"Services"
        }
    ],
    "sg:phone":"+1 404 699 2988",
    "sg:postcode":"30336",
    "sg:province":"GA",
    "sg:tags":[
        "international",
        "trade"
    ],
    "wof:name":"Rainbow Trading",
    "wof:placetype":"venue"
},
  "geometry": {"coordinates":[-84.53572200000001,33.766368],"type":"Point"}
}