{
  "type": "Feature",
  "properties": {
    "iso:country":"US",
    "sg:address":"2239 Wayside Dr",
    "sg:city":"Atlanta",
    "sg:classifiers":[
        {
            "category":"Professional",
            "subcategory":"Employment Agencies",
            "type":"Services"
        }
    ],
    "sg:phone":"+1 404 262 2952",
    "sg:postcode":"30319",
    "sg:province":"GA",
    "sg:tags":[
        "consultant",
        "search",
        "executive"
    ],
    "wof:name":"Exi Inc",
    "wof:placetype":"venue"
},
  "geometry": {"coordinates":[-84.331704,33.850539],"type":"Point"}
}