{
  "type": "Feature",
  "properties": {
    "addr:full":"1813 Bo Jo Ella Dr Douglas GA 31533",
    "addr:housenumber":"1813",
    "addr:postcode":"31533",
    "addr:street":"Bo Jo Ella Dr",
    "iso:country":"US",
    "sg:address":"1813 Bo Jo Ella Dr",
    "sg:city":"Douglas",
    "sg:classifiers":[
        {
            "category":"Building & Trades",
            "subcategory":"Pest Control",
            "type":"Services"
        }
    ],
    "sg:phone":"+1 912 384 4181",
    "sg:postcode":"31533",
    "sg:province":"GA",
    "wof:name":"Moores Pest Control",
    "wof:placetype":"venue"
},
  "geometry": {"coordinates":[-82.82076499999999,31.506679],"type":"Point"}
}