{
  "type": "Feature",
  "properties": {
    "iso:country":"US",
    "sg:address":"4451 Lawrenceville Hwy",
    "sg:city":"Tucker",
    "sg:classifiers":[
        {
            "category":"Government",
            "subcategory":"Office",
            "type":"Public Place"
        }
    ],
    "sg:phone":"+1 678 937 5340",
    "sg:postcode":"30084",
    "sg:province":"GA",
    "sg:tags":[
        "parish",
        "government-county"
    ],
    "wof:name":"DeKalb County Government",
    "wof:placetype":"venue"
},
  "geometry": {"coordinates":[-84.203981,33.858219],"type":"Point"}
}