{
  "type": "Feature",
  "properties": {
    "addr:full":"895 Satilla Church Rd Baxley GA 31513",
    "addr:housenumber":"895",
    "addr:postcode":"31513",
    "addr:street":"Church Rd",
    "iso:country":"US",
    "sg:address":"895 Satilla Church Rd",
    "sg:city":"Baxley",
    "sg:classifiers":[
        {
            "category":"Personal",
            "subcategory":"Beauty Salon",
            "type":"Services"
        }
    ],
    "sg:phone":"+1 912 705 2427",
    "sg:postcode":"31513",
    "sg:province":"GA",
    "sg:tags":[
        "hair",
        "stylist"
    ],
    "sg:website":"http://www.hairitissalonandspa.com",
    "wof:name":"Hair It Is",
    "wof:placetype":"venue"
},
  "geometry": {"coordinates":[-82.353335,31.732821],"type":"Point"}
}