{
  "type": "Feature",
  "properties": {
    "addr:full":"2380 Buford Dr Lawrenceville GA 30043",
    "addr:housenumber":"2380",
    "addr:postcode":"30043",
    "addr:street":"Buford Dr",
    "iso:country":"US",
    "sg:address":"2380 Buford Dr",
    "sg:city":"Lawrenceville",
    "sg:classifiers":[
        {
            "category":"Restaurant",
            "type":"Food & Drink"
        }
    ],
    "sg:phone":"+1 770 339 3000",
    "sg:postcode":"30043",
    "sg:province":"GA",
    "sg:tags":[
        "mexican"
    ],
    "wof:name":"La Fiesta Grande",
    "wof:placetype":"venue"
},
  "geometry": {"coordinates":[-83.988315,34.036327],"type":"Point"}
}