{
  "type": "Feature",
  "properties": {
    "addr:full":"110 Habersham Dr Fayetteville GA 30214",
    "addr:housenumber":"110",
    "addr:postcode":"30214",
    "addr:street":"Habersham Dr",
    "iso:country":"US",
    "sg:address":"110 Habersham Dr",
    "sg:city":"Fayetteville",
    "sg:classifiers":[
        {
            "category":"Home & Garden",
            "subcategory":"Building Materials",
            "type":"Retail Goods"
        }
    ],
    "sg:phone":"+1 770 371 5023",
    "sg:postcode":"30214",
    "sg:province":"GA",
    "wof:name":"World Home Building Materials",
    "wof:placetype":"venue"
},
  "geometry": {"coordinates":[-84.454407,33.458649],"type":"Point"}
}