{
  "type": "Feature",
  "properties": {
    "addr:full":"2030 Watson Blvd Warner Robins GA 31093",
    "addr:housenumber":"2030",
    "addr:postcode":"31093",
    "addr:street":"Watson Blvd",
    "iso:country":"US",
    "sg:address":"2030 Watson Blvd",
    "sg:city":"Warner Robins",
    "sg:classifiers":[
        {
            "category":"Restaurant",
            "type":"Food & Drink"
        }
    ],
    "sg:phone":"+1 478 923 7123",
    "sg:postcode":"31093",
    "sg:province":"GA",
    "wof:name":"Po Folks Restaurant",
    "wof:placetype":"venue"
},
  "geometry": {"coordinates":[-83.64991499999999,32.618376],"type":"Point"}
}