{
  "type": "Feature",
  "properties": {
    "addr:full":"325 Art Ave Columbus GA 31907",
    "addr:housenumber":"325",
    "addr:postcode":"31907",
    "addr:street":"Art Ave",
    "iso:country":"US",
    "sg:address":"325 Art Ave",
    "sg:city":"Columbus",
    "sg:classifiers":[
        {
            "category":"Organizations",
            "subcategory":"Religious Organization",
            "type":"Services"
        }
    ],
    "sg:phone":"+1 706 687 6249",
    "sg:postcode":"31907",
    "sg:province":"GA",
    "wof:name":"Beatric Roffe Rev",
    "wof:placetype":"venue"
},
  "geometry": {"coordinates":[-84.91117300000001,32.447498],"type":"Point"}
}