{
  "type": "Feature",
  "properties": {
    "iso:country":"US",
    "sg:address":"3428 Browns Mill Rd",
    "sg:city":"Atlanta",
    "sg:classifiers":[
        {
            "category":"Wholesale",
            "subcategory":"Construction Materials",
            "type":"Manufacturing & Wholesale Goods"
        }
    ],
    "sg:phone":"+1 404 684 5850",
    "sg:postcode":"30354",
    "sg:province":"GA",
    "wof:name":"Epic Siding & Windows",
    "wof:placetype":"venue"
},
  "geometry": {"coordinates":[-84.384652,33.660639],"type":"Point"}
}