{
  "type": "Feature",
  "properties": {
    "iso:country":"US",
    "sg:address":"10 Britt Ave NW",
    "sg:city":"Norcross",
    "sg:classifiers":[
        {
            "category":"Organizations",
            "subcategory":"Religious Organization",
            "type":"Services"
        }
    ],
    "sg:phone":"+1 770 441 9248",
    "sg:postcode":"30071",
    "sg:province":"GA",
    "wof:name":"Norcross Praise Fellowship",
    "wof:placetype":"venue"
},
  "geometry": {"coordinates":[-84.209841,33.941119],"type":"Point"}
}