{
  "type": "Feature",
  "properties": {
    "addr:full":"5990 Deerwoods Trl Alpharetta GA 30005",
    "addr:housenumber":"5990",
    "addr:postcode":"30005",
    "addr:street":"Deerwoods Trl",
    "iso:country":"US",
    "sg:address":"5990 Deerwoods Trl",
    "sg:city":"Alpharetta",
    "sg:classifiers":[
        {
            "category":"Home & Garden",
            "subcategory":"Building Materials",
            "type":"Retail Goods"
        }
    ],
    "sg:phone":"+1 770 844 0330",
    "sg:postcode":"30005",
    "sg:province":"GA",
    "sg:tags":[
        "window",
        "wallpaper",
        "furnishing",
        "furniture"
    ],
    "wof:name":"Interior Solutions",
    "wof:placetype":"venue"
},
  "geometry": {"coordinates":[-84.17339699999999,34.077202],"type":"Point"}
}