{
  "type": "Feature",
  "properties": {
    "addr:full":"1207 Beech Valley Rd NE Atlanta GA 30306",
    "addr:housenumber":"1207",
    "addr:postcode":"30306",
    "addr:street":"Beech Valley Rd Ne",
    "iso:country":"US",
    "sg:address":"1207 Beech Valley Rd NE",
    "sg:city":"Atlanta",
    "sg:classifiers":[
        {
            "category":"Professional",
            "subcategory":"Research",
            "type":"Services"
        }
    ],
    "sg:phone":"+1 404 875 2740",
    "sg:postcode":"30306",
    "sg:province":"GA",
    "sg:tags":[
        "nonphysical",
        "commercial"
    ],
    "wof:name":"Nasser Research LLC",
    "wof:placetype":"venue"
},
  "geometry": {"coordinates":[-84.347296,33.796956],"type":"Point"}
}