{
  "type": "Feature",
  "properties": {
    "iso:country":"US",
    "sg:address":"489 Sherwood Cir",
    "sg:city":"Stone Mountain",
    "sg:classifiers":[
        {
            "category":"Freight",
            "type":"Transportation"
        }
    ],
    "sg:phone":"+1 770 465 9507",
    "sg:postcode":"30087",
    "sg:province":"GA",
    "sg:tags":[
        "operator",
        "trucking"
    ],
    "wof:name":"Cay Court Carriers",
    "wof:placetype":"venue"
},
  "geometry": {"coordinates":[-84.154938,33.783068],"type":"Point"}
}