{
  "type": "Feature",
  "properties": {
    "iso:country":"US",
    "sg:address":"1425 Ellsworth Industrial Blvd Suite 33",
    "sg:city":"Atlanta",
    "sg:classifiers":[
        {
            "category":"Professional",
            "subcategory":"Computer Services",
            "type":"Services"
        }
    ],
    "sg:phone":"+1 866 926 3374",
    "sg:postcode":"30318",
    "sg:province":"GA",
    "sg:tags":[
        "wifi",
        "wifi-hotspot",
        "hotspot",
        "wifi-provider"
    ],
    "sg:website":"http://www.wanderingwifi.com/",
    "wof:name":"Wandering WiFi",
    "wof:placetype":"venue"
},
  "geometry": {"coordinates":[-84.427089,33.800448],"type":"Point"}
}