{
  "type": "Feature",
  "properties": {
    "addr:full":"2985 Gray Rd Smyrna GA 30082",
    "addr:housenumber":"2985",
    "addr:postcode":"30082",
    "addr:street":"Gray Rd",
    "iso:country":"US",
    "sg:address":"2985 Gray Rd",
    "sg:city":"Smyrna",
    "sg:classifiers":[
        {
            "category":"Personal",
            "subcategory":"Beauty Salon",
            "type":"Services"
        }
    ],
    "sg:phone":"+1 770 432 9125",
    "sg:postcode":"30082",
    "sg:province":"GA",
    "sg:tags":[
        "shop"
    ],
    "wof:name":"Violets Hair Styling",
    "wof:placetype":"venue"
},
  "geometry": {"coordinates":[-84.551289,33.881964],"type":"Point"}
}