{
  "type": "Feature",
  "properties": {
    "iso:country":"US",
    "sg:address":"4549 Briarwood Dr",
    "sg:city":"Oakwood",
    "sg:classifiers":[
        {
            "category":"Building & Trades",
            "subcategory":"Construction",
            "type":"Services"
        }
    ],
    "sg:phone":"+1 770 297 0872",
    "sg:postcode":"30566",
    "sg:province":"GA",
    "sg:tags":[
        "hanging",
        "contractor"
    ],
    "wof:name":"Bree Ransoms Designs",
    "wof:placetype":"venue"
},
  "geometry": {"coordinates":[-83.871686,34.223587],"type":"Point"}
}