{
  "type": "Feature",
  "properties": {
    "iso:country":"US",
    "sg:address":"6685 Marbut Rd",
    "sg:city":"Lithonia",
    "sg:classifiers":[
        {
            "category":"Professional",
            "type":"Services"
        }
    ],
    "sg:phone":"+1 770 484 4145",
    "sg:postcode":"30058",
    "sg:province":"GA",
    "wof:name":"Reliable Tape Products",
    "wof:placetype":"venue"
},
  "geometry": {"coordinates":[-84.111468,33.726786],"type":"Point"}
}