{
  "type": "Feature",
  "properties": {
    "addr:full":"2343 Echocliff Ct Atlanta GA 30345",
    "addr:housenumber":"2343",
    "addr:postcode":"30345",
    "addr:street":"Echocliff Ct",
    "iso:country":"US",
    "sg:address":"2343 Echocliff Ct",
    "sg:city":"Atlanta",
    "sg:classifiers":[
        {
            "category":"Real Estate",
            "subcategory":"Real Estate Services",
            "type":"Services"
        }
    ],
    "sg:phone":"+1 404 313 1960",
    "sg:postcode":"30345",
    "sg:province":"GA",
    "sg:tags":[
        "home",
        "inspector"
    ],
    "sg:website":"mike-monahan.com",
    "wof:name":"Michael Monahan Home Inspections, Inc.",
    "wof:placetype":"venue"
},
  "geometry": {"coordinates":[-84.291866,33.853077],"type":"Point"}
}