{
  "type": "Feature",
  "properties": {
    "addr:full":"34 Peachtree St NW Atlanta GA 30303",
    "addr:housenumber":"34",
    "addr:postcode":"30303",
    "addr:street":"Peachtree St Nw",
    "iso:country":"US",
    "sg:address":"34 Peachtree St NW",
    "sg:city":"Atlanta",
    "sg:classifiers":[
        {
            "category":"Professional",
            "subcategory":"Computer Services",
            "type":"Services"
        }
    ],
    "sg:phone":"+1 404 221 1916",
    "sg:postcode":"30303",
    "sg:province":"GA",
    "sg:tags":[
        "isp",
        "provider",
        "internet"
    ],
    "wof:name":"Digex",
    "wof:placetype":"venue"
},
  "geometry": {"coordinates":[-84.389426,33.754768],"type":"Point"}
}