{
  "type": "Feature",
  "properties": {
    "addr:full":"6085 Lake Forrest Dr NW Atlanta GA 30328",
    "addr:housenumber":"6085",
    "addr:postcode":"30328",
    "addr:street":"Lake Forrest Dr Nw",
    "iso:country":"US",
    "sg:address":"6085 Lake Forrest Dr NW",
    "sg:city":"Atlanta",
    "sg:classifiers":[
        {
            "category":"Banks & Credit Unions",
            "subcategory":"Bank",
            "type":"Services"
        }
    ],
    "sg:phone":"+1 404 845 0071",
    "sg:postcode":"30328",
    "sg:province":"GA",
    "sg:tags":[
        "loan",
        "real estate"
    ],
    "wof:name":"Allied Home Mortgage Capital",
    "wof:placetype":"venue"
},
  "geometry": {"coordinates":[-84.386957,33.921058],"type":"Point"}
}