{
  "type": "Feature",
  "properties": {
    "iso:country":"US",
    "sg:address":"5707 Veterans Pkwy",
    "sg:city":"Columbus",
    "sg:classifiers":[
        {
            "category":"Shopping",
            "subcategory":"Pharmacy",
            "type":"Retail Goods"
        }
    ],
    "sg:phone":"+1 706 322 3633",
    "sg:postcode":"31904",
    "sg:province":"GA",
    "sg:tags":[
        "photofinishing",
        "laboratory"
    ],
    "wof:name":"Walgreens",
    "wof:placetype":"venue"
},
  "geometry": {"coordinates":[-84.96104099999999,32.52683],"type":"Point"}
}