{
  "type": "Feature",
  "properties": {
    "iso:country":"US",
    "sg:address":"4447 New Jesup Hwy",
    "sg:city":"Brunswick",
    "sg:classifiers":[
        {
            "category":"Retail",
            "subcategory":"Animal Services",
            "type":"Services"
        }
    ],
    "sg:phone":"+1 912 265 9300",
    "sg:postcode":"31520",
    "sg:province":"GA",
    "sg:tags":[
        "pet",
        "grooming",
        "washing"
    ],
    "wof:name":"Golden Isles All Breed Pet Grm",
    "wof:placetype":"venue"
},
  "geometry": {"coordinates":[-81.51288099999999,31.210603],"type":"Point"}
}