{
  "type": "Feature",
  "properties": {
    "addr:full":"463 Campground Rd Mc Donough GA 30253",
    "addr:housenumber":"463",
    "addr:postcode":"30253",
    "addr:street":"Campground Rd",
    "iso:country":"US",
    "sg:address":"463 Campground Rd",
    "sg:city":"Mc Donough",
    "sg:classifiers":[
        {
            "category":"Building & Trades",
            "subcategory":"Construction",
            "type":"Services"
        }
    ],
    "sg:phone":"+1 770 914 6436",
    "sg:postcode":"30253",
    "sg:province":"GA",
    "sg:tags":[
        "house"
    ],
    "wof:name":"Kebco Construction Services",
    "wof:placetype":"venue"
},
  "geometry": {"coordinates":[-84.163703,33.491538],"type":"Point"}
}