{
  "type": "Feature",
  "properties": {
    "iso:country":"US",
    "sg:address":"6349 Spring Lake Dr",
    "sg:city":"Flowery Branch",
    "sg:classifiers":[
        {
            "category":"Professional",
            "subcategory":"Business Services",
            "type":"Services"
        }
    ],
    "sg:phone":"+1 770 967 2442",
    "sg:postcode":"30542",
    "sg:province":"GA",
    "wof:name":"TLC Business Svcs",
    "wof:placetype":"venue"
},
  "geometry": {"coordinates":[-83.952094,34.176947],"type":"Point"}
}