{
  "type": "Feature",
  "properties": {
    "iso:country":"US",
    "sg:address":"1495 Powers Ferry Rd SE",
    "sg:city":"Marietta",
    "sg:classifiers":[
        {
            "category":"Professional",
            "subcategory":"Lawyer & Legal Services",
            "type":"Services"
        }
    ],
    "sg:phone":"+1 770 953 3100",
    "sg:postcode":"30067",
    "sg:province":"GA",
    "wof:name":"Kennedy Reid G Atty",
    "wof:placetype":"venue"
},
  "geometry": {"coordinates":[-84.466003,33.9161],"type":"Point"}
}