{
  "type": "Feature",
  "properties": {
    "addr:full":"2810 Creekwood Ln NW Lawrenceville GA 30044",
    "addr:housenumber":"2810",
    "addr:postcode":"30044",
    "addr:street":"Creekwood Ln Nw",
    "iso:country":"US",
    "sg:address":"2810 Creekwood Ln NW",
    "sg:city":"Lawrenceville",
    "sg:classifiers":[
        {
            "category":"Real Estate",
            "subcategory":"Real Estate Agent",
            "type":"Services"
        }
    ],
    "sg:phone":"+1 770 564 1608",
    "sg:postcode":"30044",
    "sg:province":"GA",
    "wof:name":"Lawrence & Lawrence Corp",
    "wof:placetype":"venue"
},
  "geometry": {"coordinates":[-84.0783,33.921207],"type":"Point"}
}