{
  "type": "Feature",
  "properties": {
    "iso:country":"US",
    "sg:address":"1617 Blanchard Blvd",
    "sg:city":"Columbus",
    "sg:classifiers":[
        {
            "category":"Wholesale",
            "subcategory":"Construction Materials",
            "type":"Manufacturing & Wholesale Goods"
        }
    ],
    "sg:phone":"+1 706 327 1278",
    "sg:postcode":"31901",
    "sg:province":"GA",
    "sg:tags":[
        "fence"
    ],
    "wof:name":"Georgia Fence Wholesale Inc",
    "wof:placetype":"venue"
},
  "geometry": {"coordinates":[-84.97107099999999,32.448307],"type":"Point"}
}