{
  "type": "Feature",
  "properties": {
    "addr:full":"121 S Broad St Monroe GA 30655",
    "addr:housenumber":"121",
    "addr:postcode":"30655",
    "addr:street":"S Broad St",
    "iso:country":"US",
    "sg:address":"121 S Broad St",
    "sg:city":"Monroe",
    "sg:classifiers":[
        {
            "category":"Professional",
            "subcategory":"Art Services",
            "type":"Services"
        }
    ],
    "sg:phone":"+1 770 207 5660",
    "sg:postcode":"30655",
    "sg:province":"GA",
    "sg:tags":[
        "photographer"
    ],
    "wof:name":"One Moment In Time A Photo Std",
    "wof:placetype":"venue"
},
  "geometry": {"coordinates":[-83.713036,33.794163],"type":"Point"}
}