{
  "type": "Feature",
  "properties": {
    "iso:country":"US",
    "sg:address":"416 5th St NE # 80",
    "sg:city":"Atlanta",
    "sg:classifiers":[
        {
            "category":"Retail",
            "subcategory":"Auto Repair",
            "type":"Services"
        }
    ],
    "sg:phone":"+1 404 762 7646",
    "sg:postcode":"30308",
    "sg:province":"GA",
    "wof:name":"Truco Clutch",
    "wof:placetype":"venue"
},
  "geometry": {"coordinates":[-84.37433900000001,33.775327],"type":"Point"}
}