{
  "type": "Feature",
  "properties": {
    "addr:full":"1170 Highway 155 S McDonough GA 30253",
    "addr:housenumber":"1170",
    "addr:postcode":"30253",
    "addr:street":"Highway 155 S",
    "iso:country":"US",
    "sg:address":"1170 Highway 155 S",
    "sg:city":"McDonough",
    "sg:classifiers":[
        {
            "category":"Restaurant",
            "type":"Food & Drink"
        }
    ],
    "sg:phone":"+1 678 432 3088",
    "sg:postcode":"30253",
    "sg:province":"GA",
    "sg:tags":[
        "pizza"
    ],
    "wof:name":"Vendetta Pizza Cafe",
    "wof:placetype":"venue"
},
  "geometry": {"coordinates":[-84.169225,33.406746],"type":"Point"}
}