{
  "type": "Feature",
  "properties": {
    "iso:country":"US",
    "sg:address":"203 E 6th St",
    "sg:city":"Donalsonville",
    "sg:classifiers":[
        {
            "category":"Education",
            "subcategory":"School",
            "type":"Public Place"
        }
    ],
    "sg:phone":"+1 229 524 6156",
    "sg:postcode":"31794",
    "sg:province":"GA",
    "sg:tags":[
        "academic",
        "special"
    ],
    "wof:name":"Pathways Educational Program",
    "wof:placetype":"venue"
},
  "geometry": {"coordinates":[-83.50765800000001,31.457913],"type":"Point"}
}