{
  "type": "Feature",
  "properties": {
    "addr:full":"114 W Cherry St Jesup GA 31545",
    "addr:housenumber":"114",
    "addr:postcode":"31545",
    "addr:street":"W Cherry St",
    "iso:country":"US",
    "sg:address":"114 W Cherry St",
    "sg:city":"Jesup",
    "sg:classifiers":[
        {
            "category":"Shopping",
            "subcategory":"Florist",
            "type":"Retail Goods"
        }
    ],
    "sg:phone":"+1 912 427 9361",
    "sg:postcode":"31545",
    "sg:province":"GA",
    "wof:name":"Christine's Wedding Flowers",
    "wof:placetype":"venue"
},
  "geometry": {"coordinates":[-81.884017,31.606231],"type":"Point"}
}