{
  "type": "Feature",
  "properties": {
    "iso:country":"US",
    "sg:address":"3384 Peachtree Rd NE",
    "sg:city":"Atlanta",
    "sg:classifiers":[
        {
            "category":"Real Estate",
            "subcategory":"Real Estate Services",
            "type":"Services"
        }
    ],
    "sg:phone":"+1 404 816 1098",
    "sg:postcode":"30326",
    "sg:province":"GA",
    "sg:tags":[
        "management",
        "property"
    ],
    "wof:name":"Lenox Plaza",
    "wof:placetype":"venue"
},
  "geometry": {"coordinates":[-84.365196,33.848999],"type":"Point"}
}