{
  "type": "Feature",
  "properties": {
    "iso:country":"US",
    "sg:address":"318 Cottage Way",
    "sg:city":"Lawrenceville",
    "sg:classifiers":[
        {
            "category":"Professional",
            "subcategory":"Management & Consulting",
            "type":"Services"
        }
    ],
    "sg:phone":"+1 770 682 7909",
    "sg:postcode":"30044",
    "sg:province":"GA",
    "wof:name":"Wellsys Corporation",
    "wof:placetype":"venue"
},
  "geometry": {"coordinates":[-84.035056,33.918824],"type":"Point"}
}