{
  "type": "Feature",
  "properties": {
    "iso:country":"US",
    "sg:address":"5126 Thorn Oak Cir",
    "sg:city":"Buford",
    "sg:classifiers":[
        {
            "category":"Professional",
            "subcategory":"Detective & Security Services",
            "type":"Services"
        }
    ],
    "sg:phone":"+1 770 945 1625",
    "sg:postcode":"30518",
    "sg:province":"GA",
    "sg:tags":[
        "high",
        "claim",
        "investigation",
        "insurance",
        "exposure"
    ],
    "wof:name":"Cutting Edge Clims Invstgation",
    "wof:placetype":"venue"
},
  "geometry": {"coordinates":[-84.04668700000001,34.106213],"type":"Point"}
}