{
  "type": "Feature",
  "properties": {
    "iso:country":"US",
    "sg:address":"3232 Roswell Rd",
    "sg:city":"Atlanta",
    "sg:classifiers":[
        {
            "category":"Building & Trades",
            "subcategory":"Plumbing",
            "type":"Services"
        }
    ],
    "sg:phone":"+1 404 231 1514",
    "sg:postcode":"30305",
    "sg:province":"GA",
    "sg:tags":[
        "plumbing",
        "contractor"
    ],
    "wof:name":"J K Williams Plumbing Co",
    "wof:placetype":"venue"
},
  "geometry": {"coordinates":[-84.37897,33.842285],"type":"Point"}
}