{
  "type": "Feature",
  "properties": {
    "iso:country":"US",
    "sg:address":"556 Sevilla Springs Cir",
    "sg:city":"Lake Park",
    "sg:classifiers":[
        {
            "category":"Building & Trades",
            "subcategory":"Plumbing",
            "type":"Services"
        }
    ],
    "sg:phone":"+1 229 559 1077",
    "sg:postcode":"31636",
    "sg:province":"GA",
    "sg:tags":[
        "contractor"
    ],
    "wof:name":"MCI Sewer Service",
    "wof:placetype":"venue"
},
  "geometry": {"coordinates":[-83.194759,30.688888],"type":"Point"}
}