{
  "type": "Feature",
  "properties": {
    "iso:country":"US",
    "sg:address":"3209 Bath Patterson Rd",
    "sg:city":"Hephzibah",
    "sg:classifiers":[
        {
            "category":"Home & Garden",
            "subcategory":"Carpets & Floor Coverings",
            "type":"Retail Goods"
        }
    ],
    "sg:phone":"+1 706 592 4031",
    "sg:postcode":"30815",
    "sg:province":"GA",
    "sg:tags":[
        "installation"
    ],
    "wof:name":"Arthurs Carpet Installation",
    "wof:placetype":"venue"
},
  "geometry": {"coordinates":[-82.15595,33.326778],"type":"Point"}
}