{
  "type": "Feature",
  "properties": {
    "iso:country":"US",
    "sg:address":"217 W Cuyler St",
    "sg:city":"Dalton",
    "sg:classifiers":[
        {
            "category":"Travel",
            "subcategory":"Hotels & Motels",
            "type":"Entertainment"
        }
    ],
    "sg:phone":"+1 706 278 6620",
    "sg:postcode":"30720",
    "sg:province":"GA",
    "sg:tags":[
        "operation"
    ],
    "wof:name":"Holly Tree House",
    "wof:placetype":"venue"
},
  "geometry": {"coordinates":[-84.971113,34.769783],"type":"Point"}
}