{
  "type": "Feature",
  "properties": {
    "addr:full":"23 S Elm St Commerce GA 30529",
    "addr:housenumber":"23",
    "addr:postcode":"30529",
    "addr:street":"S Elm St",
    "iso:country":"US",
    "sg:address":"23 S Elm St",
    "sg:city":"Commerce",
    "sg:classifiers":[
        {
            "category":"Restaurant",
            "type":"Food & Drink"
        }
    ],
    "sg:menulink":"http://www.allmenus.com/ga/commerce/101658-huddle-house/menu/",
    "sg:phone":"+1 706 336 8187",
    "sg:postcode":"30529",
    "sg:province":"GA",
    "sg:tags":[
        "american",
        "diner"
    ],
    "wof:name":"Huddle House",
    "wof:placetype":"venue"
},
  "geometry": {"coordinates":[-83.457255,34.203152],"type":"Point"}
}