{
  "type": "Feature",
  "properties": {
    "iso:country":"US",
    "sg:address":"1180 Steeple Run",
    "sg:city":"Lawrenceville",
    "sg:classifiers":[
        {
            "category":"Real Estate",
            "subcategory":"Real Estate Agent",
            "type":"Services"
        }
    ],
    "sg:phone":"+1 770 682 8787",
    "sg:postcode":"30043",
    "sg:province":"GA",
    "sg:website":"www.realestatebroker.com",
    "wof:name":"Rieser & Rieser Inc",
    "wof:placetype":"venue"
},
  "geometry": {"coordinates":[-84.05784800000001,33.992374],"type":"Point"}
}