{
  "type": "Feature",
  "properties": {
    "addr:full":"4817 11th Ave Columbus GA 31904",
    "addr:housenumber":"4817",
    "addr:postcode":"31904",
    "addr:street":"11Th Ave",
    "iso:country":"US",
    "sg:address":"4817 11th Ave",
    "sg:city":"Columbus",
    "sg:classifiers":[
        {
            "category":"Real Estate",
            "subcategory":"Real Estate Agent",
            "type":"Services"
        }
    ],
    "sg:phone":"+1 706 221 9700",
    "sg:postcode":"31904",
    "sg:province":"GA",
    "wof:name":"Spires Properties",
    "wof:placetype":"venue"
},
  "geometry": {"coordinates":[-84.97437499999999,32.512357],"type":"Point"}
}