{
  "type": "Feature",
  "properties": {
    "iso:country":"US",
    "sg:address":"725 Northcrest Dr",
    "sg:city":"Winder",
    "sg:classifiers":[
        {
            "category":"Building & Trades",
            "subcategory":"Construction",
            "type":"Services"
        }
    ],
    "sg:phone":"+1 770 867 1075",
    "sg:postcode":"30680",
    "sg:province":"GA",
    "sg:tags":[
        "residential"
    ],
    "wof:name":"Jjs Construction",
    "wof:placetype":"venue"
},
  "geometry": {"coordinates":[-83.729145,34.013492],"type":"Point"}
}