{
  "type": "Feature",
  "properties": {
    "addr:full":"7571 Bethel Church Rd Lizella GA 31052",
    "addr:housenumber":"7571",
    "addr:postcode":"31052",
    "addr:street":"Bethel Church Rd",
    "iso:country":"US",
    "sg:address":"7571 Bethel Church Rd",
    "sg:city":"Lizella",
    "sg:classifiers":[
        {
            "category":"Wholesale",
            "subcategory":"Petroleum",
            "type":"Manufacturing & Wholesale Goods"
        }
    ],
    "sg:phone":"+1 478 935 2232",
    "sg:postcode":"31052",
    "sg:province":"GA",
    "sg:tags":[
        "pipe",
        "crude",
        "pipeline",
        "line",
        "company"
    ],
    "wof:name":"Colonial Pipeline Company",
    "wof:placetype":"venue"
},
  "geometry": {"coordinates":[-83.79006800000001,32.785573],"type":"Point"}
}