{
  "type": "Feature",
  "properties": {
    "addr:full":"3307 Abercorn Ave Atlanta GA 30346",
    "addr:housenumber":"3307",
    "addr:postcode":"30346",
    "addr:street":"Abercorn Ave",
    "iso:country":"US",
    "sg:address":"3307 Abercorn Ave",
    "sg:city":"Atlanta",
    "sg:classifiers":[
        {
            "category":"Wholesale",
            "subcategory":"Non-durable Goods",
            "type":"Manufacturing & Wholesale Goods"
        }
    ],
    "sg:phone":"+1 770 710 0967",
    "sg:postcode":"30346",
    "sg:province":"GA",
    "sg:tags":[
        "merchandise-wholesale"
    ],
    "wof:name":"Asa Importing & Exporting Group",
    "wof:placetype":"venue"
},
  "geometry": {"coordinates":[-84.332823,33.924931],"type":"Point"}
}