{
  "type": "Feature",
  "properties": {
    "iso:country":"US",
    "sg:address":"15 Villamar St NW",
    "sg:city":"Rome",
    "sg:classifiers":[
        {
            "category":"Building & Trades",
            "subcategory":"Pest Control",
            "type":"Services"
        }
    ],
    "sg:phone":"+1 706 234 0410",
    "sg:postcode":"30165",
    "sg:province":"GA",
    "sg:tags":[
        "mothproofing"
    ],
    "wof:name":"APC Pest Control",
    "wof:placetype":"venue"
},
  "geometry": {"coordinates":[-85.27398700000001,34.274281],"type":"Point"}
}