{
  "type": "Feature",
  "properties": {
    "addr:full":"1811 Piedmont Ave NE Atlanta GA 30324",
    "addr:housenumber":"1811",
    "addr:postcode":"30324",
    "addr:street":"Piedmont Ave Ne",
    "iso:country":"US",
    "sg:address":"1811 Piedmont Ave NE",
    "sg:city":"Atlanta",
    "sg:classifiers":[
        {
            "category":"Restaurant",
            "type":"Food & Drink"
        }
    ],
    "sg:phone":"+1 404 607 1622",
    "sg:postcode":"30324",
    "sg:province":"GA",
    "sg:tags":[
        "soul",
        "lunch",
        "barbecue",
        "brunch",
        "breakfast",
        "barbeque"
    ],
    "sg:website":"www.fatmattsribshack.com",
    "wof:name":"Fat Matt's Rib Shack",
    "wof:placetype":"venue"
},
  "geometry": {"coordinates":[-84.367599,33.804699],"type":"Point"}
}