{
  "type": "Feature",
  "properties": {
    "iso:country":"US",
    "sg:address":"273 Willow Ln Unit 3D",
    "sg:city":"Mcdonough",
    "sg:classifiers":[
        {
            "category":"Real Estate",
            "subcategory":"Real Estate Operator",
            "type":"Services"
        },
        {
            "category":"Real Estate",
            "subcategory":"Real Estate Services",
            "type":"Services"
        }
    ],
    "sg:phone":"+1 770 957 8905",
    "sg:postcode":"30253",
    "sg:province":"GA",
    "sg:tags":[
        "management",
        "apartment",
        "condominium"
    ],
    "wof:name":"Willow Springs Apts",
    "wof:placetype":"venue"
},
  "geometry": {"coordinates":[-84.185585,33.436457],"type":"Point"}
}