{
  "type": "Feature",
  "properties": {
    "addr:full":"2607 Moody Rd Warner Robins GA 31088",
    "addr:housenumber":"2607",
    "addr:postcode":"31088",
    "addr:street":"Moody Rd",
    "iso:country":"US",
    "sg:address":"2607 Moody Rd",
    "sg:city":"Warner Robins",
    "sg:classifiers":[
        {
            "category":"Professional",
            "subcategory":"Printing & Photocopies",
            "type":"Services"
        },
        {
            "category":"Professional",
            "subcategory":"Advertising",
            "type":"Services"
        }
    ],
    "sg:phone":"+1 478 929 4007",
    "sg:postcode":"31088",
    "sg:province":"GA",
    "sg:tags":[
        "photocopying",
        "mailing",
        "shipping"
    ],
    "wof:name":"Speedy Mail",
    "wof:placetype":"venue"
},
  "geometry": {"coordinates":[-83.623739,32.574311],"type":"Point"}
}