{
  "type": "Feature",
  "properties": {
    "addr:full":"340 Cannady Ct Atlanta GA 30350",
    "addr:housenumber":"340",
    "addr:postcode":"30350",
    "addr:street":"Cannady Ct",
    "iso:country":"US",
    "sg:address":"340 Cannady Ct",
    "sg:city":"Atlanta",
    "sg:classifiers":[
        {
            "category":"Professional",
            "subcategory":"Business Services",
            "type":"Services"
        }
    ],
    "sg:phone":"+1 770 392 1928",
    "sg:postcode":"30350",
    "sg:province":"GA",
    "wof:name":"Peter C Herbert Corp",
    "wof:placetype":"venue"
},
  "geometry": {"coordinates":[-84.290481,33.96207],"type":"Point"}
}