{
  "type": "Feature",
  "properties": {
    "iso:country":"US",
    "sg:address":"2654 Whitehurst Dr",
    "sg:city":"Marietta",
    "sg:classifiers":[
        {
            "category":"Professional",
            "subcategory":"Management & Consulting",
            "type":"Services"
        }
    ],
    "sg:phone":"+1 770 578 0222",
    "sg:postcode":"30062",
    "sg:province":"GA",
    "sg:tags":[
        "business"
    ],
    "wof:name":"Letter Perfect Engraving",
    "wof:placetype":"venue"
},
  "geometry": {"coordinates":[-84.47547400000001,33.995717],"type":"Point"}
}