{
  "type": "Feature",
  "properties": {
    "addr:full":"4929 N Henry Blvd Stockbridge GA 30281",
    "addr:housenumber":"4929",
    "addr:postcode":"30281",
    "addr:street":"N Henry Blvd",
    "iso:country":"US",
    "sg:address":"4929 N Henry Blvd",
    "sg:city":"Stockbridge",
    "sg:classifiers":[
        {
            "category":"Utilities",
            "subcategory":"Mobile Phone",
            "type":"Services"
        },
        {
            "category":"Shopping",
            "subcategory":"Computers & Home Electronics",
            "type":"Retail Goods"
        }
    ],
    "sg:phone":"+1 770 507 8980",
    "sg:postcode":"30281",
    "sg:province":"GA",
    "sg:tags":[
        "dish",
        "satellite",
        "telephone",
        "cellular"
    ],
    "wof:name":"R & L Communications",
    "wof:placetype":"venue"
},
  "geometry": {"coordinates":[-84.23775999999999,33.544317],"type":"Point"}
}