{
  "type": "Feature",
  "properties": {
    "iso:country":"US",
    "sg:address":"1044 Greenwood Ave NE",
    "sg:city":"Atlanta",
    "sg:classifiers":[
        {
            "category":"Restaurant",
            "type":"Food & Drink"
        }
    ],
    "sg:phone":"+1 404 892 0552",
    "sg:postcode":"30306",
    "sg:province":"GA",
    "wof:name":"Surin of Thailand",
    "wof:placetype":"venue"
},
  "geometry": {"coordinates":[-84.353104,33.7766],"type":"Point"}
}