{
  "type": "Feature",
  "properties": {
    "iso:country":"US",
    "sg:address":"2400 Riverside Dr",
    "sg:city":"Macon",
    "sg:classifiers":[
        {
            "category":"Restaurant",
            "type":"Food & Drink"
        }
    ],
    "sg:phone":"+1 478 750 8800",
    "sg:postcode":"31204",
    "sg:province":"GA",
    "wof:name":"Red Potato Country Buffet",
    "wof:placetype":"venue"
},
  "geometry": {"coordinates":[-83.657033,32.867981],"type":"Point"}
}