{
  "type": "Feature",
  "properties": {
    "addr:full":"100 New Ave Athens GA 30601",
    "addr:housenumber":"100",
    "addr:postcode":"30601",
    "addr:street":"New Ave",
    "iso:country":"US",
    "sg:address":"100 New Ave",
    "sg:city":"Athens",
    "sg:classifiers":[
        {
            "category":"Personal",
            "subcategory":"Beauty Salon",
            "type":"Services"
        }
    ],
    "sg:phone":"+1 706 369 0676",
    "sg:postcode":"30601",
    "sg:province":"GA",
    "sg:tags":[
        "shop"
    ],
    "wof:name":"Keepin It Real Hair Studio",
    "wof:placetype":"venue"
},
  "geometry": {"coordinates":[-83.396523,33.96843],"type":"Point"}
}