{
  "type": "Feature",
  "properties": {
    "iso:country":"US",
    "sg:address":"67 E Coffee St",
    "sg:city":"Hazlehurst",
    "sg:classifiers":[
        {
            "category":"Education",
            "subcategory":"School",
            "type":"Public Place"
        }
    ],
    "sg:phone":"+1 912 375 6730",
    "sg:postcode":"31539",
    "sg:province":"GA",
    "wof:name":"Jeff Davis Elementary",
    "wof:placetype":"venue"
},
  "geometry": {"coordinates":[-82.596081,31.868512],"type":"Point"}
}