{
  "type": "Feature",
  "properties": {
    "addr:full":"1588 Doc McLocklin Rd Statham GA 30666",
    "addr:housenumber":"1588",
    "addr:postcode":"30666",
    "addr:street":"Doc Mclocklin Rd",
    "iso:country":"US",
    "sg:address":"1588 Doc McLocklin Rd",
    "sg:city":"Statham",
    "sg:classifiers":[
        {
            "category":"Building & Trades",
            "subcategory":"Landscaping Services",
            "type":"Services"
        }
    ],
    "sg:phone":"+1 770 982 8258",
    "sg:postcode":"30666",
    "sg:province":"GA",
    "sg:tags":[
        "landscape"
    ],
    "wof:name":"All Purpose Landscapes Inc",
    "wof:placetype":"venue"
},
  "geometry": {"coordinates":[-83.60303,33.949],"type":"Point"}
}