{
  "type": "Feature",
  "properties": {
    "iso:country":"US",
    "sg:address":"1815 Atlanta Rd",
    "sg:city":"Gainesville",
    "sg:classifiers":[
        {
            "category":"Communications",
            "type":"Services"
        }
    ],
    "sg:phone":"+1 770 533 4230",
    "sg:postcode":"30504",
    "sg:province":"GA",
    "wof:name":"Bell Express Communication",
    "wof:placetype":"venue"
},
  "geometry": {"coordinates":[-83.844938,34.260734],"type":"Point"}
}