{
  "type": "Feature",
  "properties": {
    "iso:country":"US",
    "sg:address":"1221 Thomas St",
    "sg:city":"Waycross",
    "sg:classifiers":[
        {
            "category":"Place Of Worship",
            "type":"Public Place"
        }
    ],
    "sg:phone":"+1 912 283 7916",
    "sg:postcode":"31501",
    "sg:province":"GA",
    "sg:tags":[
        "church"
    ],
    "wof:name":"Big Bethel Freewill Baptist Church",
    "wof:placetype":"venue"
},
  "geometry": {"coordinates":[-82.364777,31.226391],"type":"Point"}
}