{
  "type": "Feature",
  "properties": {
    "addr:full":"960 Sundew Dr SE Conyers GA 30013",
    "addr:housenumber":"960",
    "addr:postcode":"30013",
    "addr:street":"Sundew Dr Se",
    "iso:country":"US",
    "sg:address":"960 Sundew Dr SE",
    "sg:city":"Conyers",
    "sg:classifiers":[
        {
            "category":"Manufacturing",
            "subcategory":"Chemicals & Compounds",
            "type":"Manufacturing & Wholesale Goods"
        }
    ],
    "sg:phone":"+1 678 413 0834",
    "sg:postcode":"30013",
    "sg:province":"GA",
    "sg:tags":[
        "preparation",
        "mfg"
    ],
    "wof:name":"Octagon Process Inc",
    "wof:placetype":"venue"
},
  "geometry": {"coordinates":[-84.011274,33.630937],"type":"Point"}
}