{
  "type": "Feature",
  "properties": {
    "iso:country":"US",
    "sg:address":"914 6th Ave",
    "sg:city":"Albany",
    "sg:classifiers":[
        {
            "category":"Health Services",
            "subcategory":"Doctor",
            "type":"Services"
        }
    ],
    "sg:phone":"+1 229 439 4601",
    "sg:postcode":"31701",
    "sg:province":"GA",
    "wof:name":"Lj Myers DDS Inc",
    "wof:placetype":"venue"
},
  "geometry": {"coordinates":[-84.173388,31.594344],"type":"Point"}
}