{
  "type": "Feature",
  "properties": {
    "iso:country":"US",
    "sg:address":"1602 E 16th Ave",
    "sg:city":"Cordele",
    "sg:classifiers":[
        {
            "category":"Travel",
            "subcategory":"Hotels & Motels",
            "type":"Entertainment"
        }
    ],
    "sg:phone":"+1 229 559 0110",
    "sg:postcode":"31015",
    "sg:province":"GA",
    "sg:tags":[
        "lodging"
    ],
    "sg:website":"http://www.travelodge.com",
    "wof:name":"Travelodge",
    "wof:placetype":"venue"
},
  "geometry": {"coordinates":[-83.760474,31.961575],"type":"Point"}
}