{
  "type": "Feature",
  "properties": {
    "iso:country":"US",
    "sg:address":"3073 Dunn St SE",
    "sg:city":"Smyrna",
    "sg:classifiers":[
        {
            "category":"Manufacturing",
            "subcategory":"Buildings",
            "type":"Manufacturing & Wholesale Goods"
        },
        {
            "category":"Building & Trades",
            "subcategory":"Construction",
            "type":"Services"
        }
    ],
    "sg:phone":"+1 770 436 6868",
    "sg:postcode":"30080",
    "sg:province":"GA",
    "sg:tags":[
        "home",
        "builder",
        "contractor"
    ],
    "wof:name":"Magnolia Homes",
    "wof:placetype":"venue"
},
  "geometry": {"coordinates":[-84.51568399999999,33.878434],"type":"Point"}
}