{
  "type": "Feature",
  "properties": {
    "iso:country":"US",
    "sg:address":"270 Shannon Way",
    "sg:city":"Lawrenceville",
    "sg:classifiers":[
        {
            "category":"Retail",
            "subcategory":"Auto Repair",
            "type":"Services"
        }
    ],
    "sg:phone":"+1 770 963 1500",
    "sg:postcode":"30044",
    "sg:province":"GA",
    "sg:tags":[
        "transmission"
    ],
    "wof:name":"Top Gear Transmission & Auto",
    "wof:placetype":"venue"
},
  "geometry": {"coordinates":[-84.063123,33.926992],"type":"Point"}
}