{
  "type": "Feature",
  "properties": {
    "iso:country":"US",
    "sg:address":"2604 Crosscreek Rd",
    "sg:city":"Hephzibah",
    "sg:classifiers":[
        {
            "category":"Wholesale",
            "subcategory":"Vending Machines",
            "type":"Manufacturing & Wholesale Goods"
        }
    ],
    "sg:phone":"+1 706 651 9027",
    "sg:postcode":"30815",
    "sg:province":"GA",
    "wof:name":"TKS Enterprises",
    "wof:placetype":"venue"
},
  "geometry": {"coordinates":[-82.073898,33.392356],"type":"Point"}
}