{
  "type": "Feature",
  "properties": {
    "addr:full":"5580 Oglesby Rd Atlanta GA 30349",
    "addr:housenumber":"5580",
    "addr:postcode":"30349",
    "addr:street":"Oglesby Rd",
    "iso:country":"US",
    "sg:address":"5580 Oglesby Rd",
    "sg:city":"Atlanta",
    "sg:classifiers":[
        {
            "category":"Building & Trades",
            "subcategory":"Construction",
            "type":"Services"
        }
    ],
    "sg:phone":"+1 404 209 1182",
    "sg:postcode":"30349",
    "sg:province":"GA",
    "sg:tags":[
        "equipment",
        "supply",
        "drywall",
        "contractor"
    ],
    "wof:name":"S Hill Drywall",
    "wof:placetype":"venue"
},
  "geometry": {"coordinates":[-84.51965,33.603861],"type":"Point"}
}