{
  "type": "Feature",
  "properties": {
    "addr:full":"4354 Double Branches Rd Lincolnton GA 30817",
    "addr:housenumber":"4354",
    "addr:postcode":"30817",
    "addr:street":"Double Branches Rd",
    "iso:country":"US",
    "sg:address":"4354 Double Branches Rd",
    "sg:city":"Lincolnton",
    "sg:classifiers":[
        {
            "category":"Social Services",
            "subcategory":"Child Care",
            "type":"Services"
        }
    ],
    "sg:phone":"+1 706 359 4102",
    "sg:postcode":"30817",
    "sg:province":"GA",
    "sg:tags":[
        "day"
    ],
    "wof:name":"Barbara's Family Day Care",
    "wof:placetype":"venue"
},
  "geometry": {"coordinates":[-82.357636,33.76347],"type":"Point"}
}