{
  "type": "Feature",
  "properties": {
    "iso:country":"US",
    "sg:address":"1809 Dallas Dr",
    "sg:city":"Tifton",
    "sg:classifiers":[
        {
            "category":"Professional",
            "subcategory":"Detective & Security Services",
            "type":"Services"
        }
    ],
    "sg:phone":"+1 229 382 4953",
    "sg:postcode":"31794",
    "sg:province":"GA",
    "sg:tags":[
        "information",
        "bureau"
    ],
    "wof:name":"Triple J Well Pump",
    "wof:placetype":"venue"
},
  "geometry": {"coordinates":[-83.47889600000001,31.454222],"type":"Point"}
}