{
  "type": "Feature",
  "properties": {
    "iso:country":"US",
    "sg:address":"1503 Hinton Wilson Rd",
    "sg:city":"Harlem",
    "sg:classifiers":[
        {
            "category":"Building & Trades",
            "subcategory":"Construction",
            "type":"Services"
        }
    ],
    "sg:phone":"+1 706 556 6699",
    "sg:postcode":"30814",
    "sg:province":"GA",
    "sg:tags":[
        "house",
        "contractor"
    ],
    "wof:name":"Steve A Melcher Builder",
    "wof:placetype":"venue"
},
  "geometry": {"coordinates":[-82.380083,33.484752],"type":"Point"}
}