{
  "type": "Feature",
  "properties": {
    "addr:full":"202 Lukken Industrial Dr E Lagrange GA 30241",
    "addr:housenumber":"202",
    "addr:postcode":"30241",
    "addr:street":"Lukken Industrial Dr E",
    "iso:country":"US",
    "sg:address":"202 Lukken Industrial Dr E",
    "sg:city":"Lagrange",
    "sg:classifiers":[
        {
            "category":"Wholesale",
            "subcategory":"Auto Parts",
            "type":"Manufacturing & Wholesale Goods"
        }
    ],
    "sg:phone":"+1 706 884 4504",
    "sg:postcode":"30241",
    "sg:province":"GA",
    "sg:tags":[
        "equipment",
        "truck"
    ],
    "wof:name":"Cherry Sales Assoc Inc",
    "wof:placetype":"venue"
},
  "geometry": {"coordinates":[-85.020588,33.013759],"type":"Point"}
}