{
  "type": "Feature",
  "properties": {
    "addr:full":"5153 Hwy 278 NE Covington GA 30014",
    "addr:housenumber":"5153",
    "addr:postcode":"30014",
    "addr:street":"Hwy 278 Ne",
    "iso:country":"US",
    "sg:address":"5153 Hwy 278 NE",
    "sg:city":"Covington",
    "sg:classifiers":[
        {
            "category":"Home & Garden",
            "subcategory":"Household Appliances",
            "type":"Retail Goods"
        }
    ],
    "sg:phone":"+1 770 786 3434",
    "sg:postcode":"30014",
    "sg:province":"GA",
    "sg:tags":[
        "store"
    ],
    "wof:name":"Sears Roebuck and Co Inc",
    "wof:placetype":"venue"
},
  "geometry": {"coordinates":[-83.848315,33.602845],"type":"Point"}
}