{
  "type": "Feature",
  "properties": {
    "iso:country":"US",
    "sg:address":"3977 Lawrenceville Hwy",
    "sg:city":"Tucker",
    "sg:classifiers":[
        {
            "category":"Professional",
            "subcategory":"Advertising",
            "type":"Services"
        }
    ],
    "sg:phone":"+1 770 723 1470",
    "sg:postcode":"30084",
    "sg:province":"GA",
    "wof:name":"Perimeter",
    "wof:placetype":"venue"
},
  "geometry": {"coordinates":[-84.220096,33.849971],"type":"Point"}
}