{
  "type": "Feature",
  "properties": {
    "iso:country":"US",
    "sg:address":"700 Morosgo Dr NE",
    "sg:city":"Atlanta",
    "sg:classifiers":[
        {
            "category":"Health Services",
            "subcategory":"Doctor",
            "type":"Services"
        }
    ],
    "sg:phone":"+1 404 816 3933",
    "sg:postcode":"30324",
    "sg:province":"GA",
    "sg:website":"www.skinmedicalaesthetics.com",
    "wof:name":"Abbott Cynthia MD",
    "wof:placetype":"venue"
},
  "geometry": {"coordinates":[-84.36407199999999,33.823377],"type":"Point"}
}