{
  "type": "Feature",
  "properties": {
    "iso:country":"US",
    "sg:address":"2604 Frederica Rd",
    "sg:city":"Saint Simons Island",
    "sg:classifiers":[
        {
            "category":"Professional",
            "subcategory":"Lawyer & Legal Services",
            "type":"Services"
        }
    ],
    "sg:phone":"+1 912 638 9307",
    "sg:postcode":"31522",
    "sg:province":"GA",
    "wof:name":"Edward S Armstrong Jr Inc",
    "wof:placetype":"venue"
},
  "geometry": {"coordinates":[-81.377617,31.177349],"type":"Point"}
}