{
  "type": "Feature",
  "properties": {
    "addr:full":"4450 Friendship Rd Buford GA 30518",
    "addr:housenumber":"4450",
    "addr:postcode":"30518",
    "addr:street":"Friendship Rd",
    "iso:country":"US",
    "sg:address":"4450 Friendship Rd",
    "sg:city":"Buford",
    "sg:classifiers":[
        {
            "category":"Education",
            "subcategory":"School",
            "type":"Public Place"
        }
    ],
    "sg:phone":"+1 770 932 1223",
    "sg:postcode":"30518",
    "sg:province":"GA",
    "sg:tags":[
        "elementary"
    ],
    "wof:name":"Friendship Elementary School",
    "wof:placetype":"venue"
},
  "geometry": {"coordinates":[-83.935233,34.134129],"type":"Point"}
}