{
  "type": "Feature",
  "properties": {
    "addr:full":"3590 Cherokee St NW Kennesaw GA 30144",
    "addr:housenumber":"3590",
    "addr:postcode":"30144",
    "addr:street":"Cherokee St Nw",
    "iso:country":"US",
    "sg:address":"3590 Cherokee St NW",
    "sg:city":"Kennesaw",
    "sg:classifiers":[
        {
            "category":"Professional",
            "subcategory":"Business Services",
            "type":"Services"
        }
    ],
    "sg:phone":"+1 770 419 9613",
    "sg:postcode":"30144",
    "sg:province":"GA",
    "wof:name":"Southrn Inspection Service",
    "wof:placetype":"venue"
},
  "geometry": {"coordinates":[-84.604123,34.040422],"type":"Point"}
}