{
  "type": "Feature",
  "properties": {
    "iso:country":"US",
    "sg:address":"6223 Hwy 278 NE",
    "sg:city":"Covington",
    "sg:classifiers":[
        {
            "category":"Insurance",
            "subcategory":"Insurance Agent",
            "type":"Services"
        }
    ],
    "sg:phone":"+1 770 385 4055",
    "sg:postcode":"30014",
    "sg:province":"GA",
    "wof:name":"Mark Lavelle",
    "wof:placetype":"venue"
},
  "geometry": {"coordinates":[-83.842556,33.602215],"type":"Point"}
}