{
  "type": "Feature",
  "properties": {
    "iso:country":"US",
    "sg:address":"173 Addy Ln",
    "sg:city":"Stockbridge",
    "sg:classifiers":[
        {
            "category":"Real Estate",
            "subcategory":"Real Estate Services",
            "type":"Services"
        }
    ],
    "sg:phone":"+1 800 355 9002",
    "sg:postcode":"30281",
    "sg:province":"GA",
    "sg:tags":[
        "management",
        "property"
    ],
    "sg:website":"www.gtrpropertymanagement.com",
    "wof:name":"Greentree Realty, Inc",
    "wof:placetype":"venue"
},
  "geometry": {"coordinates":[-84.25963,33.5462],"type":"Point"}
}