{
  "type": "Feature",
  "properties": {
    "iso:country":"US",
    "sg:address":"1101 Big A Rd S",
    "sg:city":"Toccoa",
    "sg:classifiers":[
        {
            "category":"Travel",
            "subcategory":"Hotels & Motels",
            "type":"Entertainment"
        }
    ],
    "sg:phone":"+1 706 886 9461",
    "sg:postcode":"30577",
    "sg:province":"GA",
    "sg:tags":[
        "lodging"
    ],
    "sg:website":"http://www.daysinn.com",
    "wof:name":"Days Inn",
    "wof:placetype":"venue"
},
  "geometry": {"coordinates":[-83.306099,34.570228],"type":"Point"}
}