{
  "type": "Feature",
  "properties": {
    "addr:full":"25 Heritage Trce Newnan GA 30263",
    "addr:housenumber":"25",
    "addr:postcode":"30263",
    "addr:street":"Heritage Trce",
    "iso:country":"US",
    "sg:address":"25 Heritage Trce",
    "sg:city":"Newnan",
    "sg:classifiers":[
        {
            "category":"Wholesale",
            "subcategory":"Electrical",
            "type":"Manufacturing & Wholesale Goods"
        }
    ],
    "sg:phone":"+1 770 253 0065",
    "sg:postcode":"30263",
    "sg:province":"GA",
    "sg:tags":[
        "control",
        "security",
        "system"
    ],
    "wof:name":"Pro Tech Fire Svc Inc",
    "wof:placetype":"venue"
},
  "geometry": {"coordinates":[-84.771614,33.418239],"type":"Point"}
}