{
  "type": "Feature",
  "properties": {
    "iso:country":"US",
    "sg:address":"119 Cedar St",
    "sg:city":"Lagrange",
    "sg:classifiers":[
        {
            "category":"Organizations",
            "subcategory":"Religious Organization",
            "type":"Services"
        }
    ],
    "sg:phone":"+1 706 883 6849",
    "sg:postcode":"30241",
    "sg:province":"GA",
    "sg:tags":[
        "churches-baptist",
        "church"
    ],
    "wof:name":"Mt Gillard Baptist Church",
    "wof:placetype":"venue"
},
  "geometry": {"coordinates":[-85.027181,33.023849],"type":"Point"}
}