{
  "type": "Feature",
  "properties": {
    "iso:country":"US",
    "sg:address":"104 Stable Aly E",
    "sg:city":"Saint Marys",
    "sg:classifiers":[
        {
            "category":"Building & Trades",
            "subcategory":"Construction",
            "type":"Services"
        }
    ],
    "sg:phone":"+1 912 673 1333",
    "sg:postcode":"31558",
    "sg:province":"GA",
    "sg:tags":[
        "house"
    ],
    "wof:name":"Lange Construction",
    "wof:placetype":"venue"
},
  "geometry": {"coordinates":[-81.549925,30.721332],"type":"Point"}
}