{
  "type": "Feature",
  "properties": {
    "addr:full":"227 Foothill Dr Woodstock GA 30188",
    "addr:housenumber":"227",
    "addr:postcode":"30188",
    "addr:street":"Foothill Dr",
    "iso:country":"US",
    "sg:address":"227 Foothill Dr",
    "sg:city":"Woodstock",
    "sg:classifiers":[
        {
            "category":"Building & Trades",
            "subcategory":"Construction",
            "type":"Services"
        }
    ],
    "sg:phone":"+1 678 409 6922",
    "sg:postcode":"30188",
    "sg:province":"GA",
    "sg:tags":[
        "house"
    ],
    "wof:name":"Dillard Construction Company",
    "wof:placetype":"venue"
},
  "geometry": {"coordinates":[-84.49063200000001,34.108949],"type":"Point"}
}