{
  "type": "Feature",
  "properties": {
    "iso:country":"US",
    "sg:address":"120 Florence St",
    "sg:city":"Rossville",
    "sg:classifiers":[
        {
            "category":"Building & Trades",
            "subcategory":"Construction",
            "type":"Services"
        }
    ],
    "sg:phone":"+1 706 861 5619",
    "sg:postcode":"30741",
    "sg:province":"GA",
    "sg:tags":[
        "contractor"
    ],
    "wof:name":"Tri County Roofing Co",
    "wof:placetype":"venue"
},
  "geometry": {"coordinates":[-85.299494,34.982703],"type":"Point"}
}