{
  "type": "Feature",
  "properties": {
    "iso:country":"US",
    "sg:address":"818 J And J Dr",
    "sg:city":"Dalton",
    "sg:classifiers":[
        {
            "category":"Home & Garden",
            "subcategory":"Carpets & Floor Coverings",
            "type":"Retail Goods"
        }
    ],
    "sg:phone":"+1 706 529 2100",
    "sg:postcode":"30721",
    "sg:province":"GA",
    "sg:tags":[
        "distributor",
        "rug",
        "manufacturer"
    ],
    "sg:website":"http://www.jj-invision.com",
    "wof:name":"J&J/Invision",
    "wof:placetype":"venue"
},
  "geometry": {"coordinates":[-84.947141,34.783487],"type":"Point"}
}