{
  "type": "Feature",
  "properties": {
    "iso:country":"US",
    "sg:address":"600 Chickamauga Ave",
    "sg:city":"Rossville",
    "sg:classifiers":[
        {
            "category":"Food & Beverages",
            "subcategory":"Groceries & Convenience Stores",
            "type":"Retail Goods"
        }
    ],
    "sg:phone":"+1 706 866 6786",
    "sg:postcode":"30741",
    "sg:province":"GA",
    "wof:name":"Sunset Market 3",
    "wof:placetype":"venue"
},
  "geometry": {"coordinates":[-85.279934,34.983761],"type":"Point"}
}