{
  "type": "Feature",
  "properties": {
    "iso:country":"US",
    "sg:address":"3400 McClure Bridge Rd",
    "sg:city":"Duluth",
    "sg:classifiers":[
        {
            "category":"Shopping",
            "subcategory":"Computers & Home Electronics",
            "type":"Retail Goods"
        }
    ],
    "sg:phone":"+1 770 495 1659",
    "sg:postcode":"30096",
    "sg:province":"GA",
    "sg:tags":[
        "software"
    ],
    "wof:name":"Primus Software Corp",
    "wof:placetype":"venue"
},
  "geometry": {"coordinates":[-84.15923100000001,34.003702],"type":"Point"}
}