{
  "type": "Feature",
  "properties": {
    "iso:country":"US",
    "sg:address":"7977 Rockbridge Rd",
    "sg:city":"Lithonia",
    "sg:classifiers":[
        {
            "category":"Restaurant",
            "type":"Food & Drink"
        }
    ],
    "sg:phone":"+1 770 482 4582",
    "sg:postcode":"30058",
    "sg:province":"GA",
    "sg:tags":[
        "out"
    ],
    "wof:name":"124 Wings & Fish",
    "wof:placetype":"venue"
},
  "geometry": {"coordinates":[-84.077181,33.774252],"type":"Point"}
}