{
  "type": "Feature",
  "properties": {
    "addr:full":"312 Clarinbridge Pkwy NW Kennesaw GA 30144",
    "addr:housenumber":"312",
    "addr:postcode":"30144",
    "addr:street":"Clarinbridge Pkwy Nw",
    "iso:country":"US",
    "sg:address":"312 Clarinbridge Pkwy NW",
    "sg:city":"Kennesaw",
    "sg:classifiers":[
        {
            "category":"Travel",
            "subcategory":"Hotels & Motels",
            "type":"Entertainment"
        }
    ],
    "sg:phone":"+1 770 423 0716",
    "sg:postcode":"30144",
    "sg:province":"GA",
    "wof:name":"T P Corp Lodging",
    "wof:placetype":"venue"
},
  "geometry": {"coordinates":[-84.57287100000001,34.044289],"type":"Point"}
}