{
  "type": "Feature",
  "properties": {
    "addr:full":"3522 Acworth Due West Rd Acworth GA 30144",
    "addr:housenumber":"3522",
    "addr:postcode":"30144",
    "addr:street":"Acworth Due West Rd",
    "iso:country":"US",
    "sg:address":"3522 Acworth Due West Rd",
    "sg:city":"Acworth",
    "sg:classifiers":[
        {
            "category":"Organizations",
            "subcategory":"Religious Organization",
            "type":"Services"
        }
    ],
    "sg:phone":"+1 770 974 1720",
    "sg:postcode":"30144",
    "sg:province":"GA",
    "wof:name":"Nehemiah Ministries",
    "wof:placetype":"venue"
},
  "geometry": {"coordinates":[-84.674722,34.039237],"type":"Point"}
}