{
  "type": "Feature",
  "properties": {
    "addr:full":"174 Lakat Ln Bainbridge GA 39819",
    "addr:housenumber":"174",
    "addr:postcode":"39819",
    "addr:street":"Lakat Ln",
    "iso:country":"US",
    "sg:address":"174 Lakat Ln",
    "sg:city":"Bainbridge",
    "sg:phone":"+1 229 246 7344",
    "sg:postcode":"39819",
    "sg:province":"GA",
    "sg:tags":[
        "farm",
        "field",
        "crop"
    ],
    "wof:name":"Van Smith",
    "wof:placetype":"venue"
},
  "geometry": {"coordinates":[-84.553848,30.809694],"type":"Point"}
}