{
  "type": "Feature",
  "properties": {
    "addr:full":"1110 Atlanta Rd Gainesville GA 30501",
    "addr:housenumber":"1110",
    "addr:postcode":"30501",
    "addr:street":"Atlanta Rd",
    "iso:country":"US",
    "sg:address":"1110 Atlanta Rd",
    "sg:city":"Gainesville",
    "sg:classifiers":[
        {
            "category":"Autos & Motor Vehicles",
            "subcategory":"Auto Supplies",
            "type":"Retail Goods"
        }
    ],
    "sg:phone":"+1 678 549 6499",
    "sg:postcode":"30501",
    "sg:province":"GA",
    "sg:tags":[
        "tire"
    ],
    "wof:name":"ABC Express Tire Shop",
    "wof:placetype":"venue"
},
  "geometry": {"coordinates":[-83.841129,34.275017],"type":"Point"}
}