{
  "type": "Feature",
  "properties": {
    "iso:country":"US",
    "sg:address":"6200 Watson Blvd",
    "sg:city":"Byron",
    "sg:classifiers":[
        {
            "category":"Wholesale",
            "subcategory":"Auto Parts",
            "type":"Manufacturing & Wholesale Goods"
        },
        {
            "category":"Autos & Motor Vehicles",
            "subcategory":"Auto Supplies",
            "type":"Retail Goods"
        },
        {
            "category":"Professional",
            "subcategory":"Advertising",
            "type":"Services"
        },
        {
            "category":"Local Transit",
            "type":"Transportation"
        }
    ],
    "sg:phone":"+1 478 225 0779",
    "sg:postcode":"31008",
    "sg:province":"GA",
    "sg:tags":[
        "shell",
        "liner",
        "caps",
        "equipment",
        "truck",
        "accessory",
        "winch",
        "hitch",
        "trailer"
    ],
    "wof:name":"H & H Truck Accessories",
    "wof:placetype":"venue"
},
  "geometry": {"coordinates":[-83.710824,32.61459],"type":"Point"}
}