{
  "type": "Feature",
  "properties": {
    "addr:full":"207 Derby Run Dallas GA 30132",
    "addr:housenumber":"207",
    "addr:postcode":"30132",
    "addr:street":"Derby Run",
    "iso:country":"US",
    "sg:address":"207 Derby Run",
    "sg:city":"Dallas",
    "sg:classifiers":[
        {
            "category":"Professional",
            "subcategory":"Art Services",
            "type":"Services"
        }
    ],
    "sg:phone":"+1 770 443 9233",
    "sg:postcode":"30132",
    "sg:province":"GA",
    "sg:tags":[
        "commercial",
        "design"
    ],
    "wof:name":"Prosigns & Graphics LLC",
    "wof:placetype":"venue"
},
  "geometry": {"coordinates":[-84.830578,33.952446],"type":"Point"}
}