{
  "type": "Feature",
  "properties": {
    "iso:country":"US",
    "sg:address":"226 N Peterson Ave",
    "sg:city":"Douglas",
    "sg:classifiers":[
        {
            "category":"Shopping",
            "subcategory":"Used Merchandise",
            "type":"Retail Goods"
        }
    ],
    "sg:phone":"+1 912 384 1735",
    "sg:postcode":"31533",
    "sg:province":"GA",
    "sg:tags":[
        "shop",
        "consignment"
    ],
    "wof:name":"Kon Sign-A-Kid",
    "wof:placetype":"venue"
},
  "geometry": {"coordinates":[-82.850212,31.510949],"type":"Point"}
}