{
  "type": "Feature",
  "properties": {
    "iso:country":"US",
    "sg:address":"152 N Crest Blvd",
    "sg:city":"Macon",
    "sg:classifiers":[
        {
            "category":"Real Estate",
            "subcategory":"Real Estate Agent",
            "type":"Services"
        }
    ],
    "sg:phone":"+1 478 477 9172",
    "sg:postcode":"31210",
    "sg:province":"GA",
    "wof:name":"Ben G Porter",
    "wof:placetype":"venue"
},
  "geometry": {"coordinates":[-83.693213,32.903367],"type":"Point"}
}