{
  "type": "Feature",
  "properties": {
    "iso:country":"US",
    "sg:address":"221 Peachtree Cir NE",
    "sg:city":"Atlanta",
    "sg:classifiers":[
        {
            "category":"Insurance",
            "subcategory":"Hazard Insurance",
            "type":"Services"
        },
        {
            "category":"Insurance",
            "subcategory":"Life Insurance",
            "type":"Services"
        }
    ],
    "sg:phone":"+1 404 233 2824",
    "sg:postcode":"30309",
    "sg:province":"GA",
    "sg:website":"http://www.equitable.com",
    "wof:name":"Equitable Life Assurance",
    "wof:placetype":"venue"
},
  "geometry": {"coordinates":[-84.385293,33.795338],"type":"Point"}
}