{
  "type": "Feature",
  "properties": {
    "addr:full":"101 Bear Branch Rd Kathleen GA 31047",
    "addr:housenumber":"101",
    "addr:postcode":"31047",
    "addr:street":"Bear Branch Rd",
    "iso:country":"US",
    "sg:address":"101 Bear Branch Rd",
    "sg:city":"Kathleen",
    "sg:classifiers":[
        {
            "category":"Organizations",
            "subcategory":"Religious Organization",
            "type":"Services"
        }
    ],
    "sg:phone":"+1 478 987 3330",
    "sg:postcode":"31047",
    "sg:province":"GA",
    "sg:tags":[
        "church"
    ],
    "wof:name":"First Baptist Church Kathleen",
    "wof:placetype":"venue"
},
  "geometry": {"coordinates":[-83.613006,32.485554],"type":"Point"}
}