{
  "type": "Feature",
  "properties": {
    "iso:country":"US",
    "sg:address":"3435 Breckinridge Blvd",
    "sg:city":"Duluth",
    "sg:classifiers":[
        {
            "category":"Shopping",
            "subcategory":"Mobile Phones",
            "type":"Retail Goods"
        }
    ],
    "sg:phone":"+1 770 277 2760",
    "sg:postcode":"30096",
    "sg:province":"GA",
    "sg:website":"www.cynergyhitech.com",
    "wof:name":"Ktm Wireless",
    "wof:placetype":"venue"
},
  "geometry": {"coordinates":[-84.12321300000001,33.952552],"type":"Point"}
}