{
  "type": "Feature",
  "properties": {
    "iso:country":"US",
    "sg:address":"2201 Henderson Mill Rd NE",
    "sg:city":"Atlanta",
    "sg:classifiers":[
        {
            "category":"Shopping",
            "subcategory":"Gifts & Souvenirs",
            "type":"Retail Goods"
        }
    ],
    "sg:phone":"+1 770 723 0067",
    "sg:postcode":"30345",
    "sg:province":"GA",
    "sg:tags":[
        "shop"
    ],
    "wof:name":"Gift Center At Sears",
    "wof:placetype":"venue"
},
  "geometry": {"coordinates":[-84.25839499999999,33.85078],"type":"Point"}
}