{
  "type": "Feature",
  "properties": {
    "iso:country":"US",
    "sg:address":"5770 Peachtree Rd Ste 109",
    "sg:city":"Atlanta",
    "sg:classifiers":[
        {
            "category":"Retail",
            "subcategory":"Auto Rental",
            "type":"Services"
        }
    ],
    "sg:phone":"+1 770 300 9726",
    "sg:postcode":"30341",
    "sg:province":"GA",
    "sg:tags":[
        "car"
    ],
    "sg:website":"www.avis.com",
    "wof:name":"Avis Rent A Car",
    "wof:placetype":"venue"
},
  "geometry": {"coordinates":[-84.290361,33.897254],"type":"Point"}
}