{
  "type": "Feature",
  "properties": {
    "addr:full":"408 Railroad St Warrenton GA 30828",
    "addr:housenumber":"408",
    "addr:postcode":"30828",
    "addr:street":"Railroad St",
    "iso:country":"US",
    "sg:address":"408 Railroad St",
    "sg:city":"Warrenton",
    "sg:classifiers":[
        {
            "category":"Building & Trades",
            "subcategory":"Plumbing",
            "type":"Services"
        }
    ],
    "sg:phone":"+1 706 465 0906",
    "sg:postcode":"30828",
    "sg:province":"GA",
    "sg:tags":[
        "contractor"
    ],
    "wof:name":"Hap S Heating Cooling",
    "wof:placetype":"venue"
},
  "geometry": {"coordinates":[-82.65562799999999,33.413356],"type":"Point"}
}