{
  "type": "Feature",
  "properties": {
    "iso:country":"US",
    "sg:address":"1293 Wellbrook Cir NE",
    "sg:city":"Conyers",
    "sg:classifiers":[
        {
            "category":"Health Services",
            "subcategory":"Doctor",
            "type":"Services"
        }
    ],
    "sg:phone":"+1 678 413 1336",
    "sg:postcode":"30012",
    "sg:province":"GA",
    "wof:name":"Southeastern Gyn Oncology",
    "wof:placetype":"venue"
},
  "geometry": {"coordinates":[-84.002899,33.678699],"type":"Point"}
}