{
  "type": "Feature",
  "properties": {
    "iso:country":"US",
    "sg:address":"5 Seaboard St",
    "sg:city":"Elberton",
    "sg:classifiers":[
        {
            "category":"Government",
            "subcategory":"Office",
            "type":"Public Place"
        }
    ],
    "sg:phone":"+1 706 213 2028",
    "sg:postcode":"30635",
    "sg:province":"GA",
    "wof:name":"Elberton Career Center",
    "wof:placetype":"venue"
},
  "geometry": {"coordinates":[-82.85087300000001,34.102382],"type":"Point"}
}