{
  "type": "Feature",
  "properties": {
    "iso:country":"US",
    "sg:address":"87 Edna Cir",
    "sg:city":"Thomaston",
    "sg:classifiers":[
        {
            "category":"Building & Trades",
            "subcategory":"Construction",
            "type":"Services"
        }
    ],
    "sg:phone":"+1 706 647 9906",
    "sg:postcode":"30286",
    "sg:province":"GA",
    "sg:tags":[
        "contractor"
    ],
    "wof:name":"Fagan Masonry Tony Fagan",
    "wof:placetype":"venue"
},
  "geometry": {"coordinates":[-84.28172600000001,32.872977],"type":"Point"}
}