{
  "type": "Feature",
  "properties": {
    "addr:full":"500 N McDonald Ave Douglas GA 31533",
    "addr:housenumber":"500",
    "addr:postcode":"31533",
    "addr:street":"N Mcdonald Ave",
    "iso:country":"US",
    "sg:address":"500 N McDonald Ave",
    "sg:city":"Douglas",
    "sg:classifiers":[
        {
            "category":"Organizations",
            "subcategory":"Religious Organization",
            "type":"Services"
        }
    ],
    "sg:phone":"+1 912 384 0014",
    "sg:postcode":"31533",
    "sg:province":"GA",
    "wof:name":"Missionaries LDS",
    "wof:placetype":"venue"
},
  "geometry": {"coordinates":[-82.838995,31.513827],"type":"Point"}
}