{
  "type": "Feature",
  "properties": {
    "iso:country":"US",
    "sg:address":"455 Grayson Hwy",
    "sg:city":"Lawrenceville",
    "sg:classifiers":[
        {
            "category":"Restaurant",
            "type":"Food & Drink"
        }
    ],
    "sg:phone":"+1 770 237 0096",
    "sg:postcode":"30045",
    "sg:province":"GA",
    "sg:tags":[
        "eating"
    ],
    "wof:name":"Blimpie",
    "wof:placetype":"venue"
},
  "geometry": {"coordinates":[-83.980816,33.937956],"type":"Point"}
}