{
  "type": "Feature",
  "properties": {
    "addr:full":"3668 Sterling Ridge Way Decatur GA 30032",
    "addr:housenumber":"3668",
    "addr:postcode":"30032",
    "addr:street":"Sterling Ridge Way",
    "iso:country":"US",
    "sg:address":"3668 Sterling Ridge Way",
    "sg:city":"Decatur",
    "sg:classifiers":[
        {
            "category":"Building & Trades",
            "subcategory":"Construction",
            "type":"Services"
        }
    ],
    "sg:phone":"+1 770 842 4465",
    "sg:postcode":"30032",
    "sg:province":"GA",
    "sg:tags":[
        "industrial",
        "contractors-commercial"
    ],
    "wof:name":"Spartan Waste Systems Incorporated",
    "wof:placetype":"venue"
},
  "geometry": {"coordinates":[-84.239203,33.721551],"type":"Point"}
}