{
  "type": "Feature",
  "properties": {
    "addr:full":"5700 State Rte 354 Pine Mountain GA 31822",
    "addr:housenumber":"5700",
    "addr:postcode":"31822",
    "addr:street":"State Rte 354",
    "iso:country":"US",
    "sg:address":"5700 State Rte 354",
    "sg:city":"Pine Mountain",
    "sg:classifiers":[
        {
            "category":"Wholesale",
            "subcategory":"Machinery & Supplies",
            "type":"Manufacturing & Wholesale Goods"
        },
        {
            "category":"Banks & Credit Unions",
            "subcategory":"Investment Brokerage",
            "type":"Services"
        }
    ],
    "sg:phone":"+1 706 663 9890",
    "sg:postcode":"31822",
    "sg:province":"GA",
    "sg:tags":[
        "forestry",
        "advisory",
        "timber"
    ],
    "wof:name":"Forest Technology Group",
    "wof:placetype":"venue"
},
  "geometry": {"coordinates":[-84.844492,32.852215],"type":"Point"}
}