{
  "type": "Feature",
  "properties": {
    "addr:full":"1011 S Green St Thomaston GA 30286",
    "addr:housenumber":"1011",
    "addr:postcode":"30286",
    "addr:street":"S Green St",
    "iso:country":"US",
    "sg:address":"1011 S Green St",
    "sg:city":"Thomaston",
    "sg:classifiers":[
        {
            "category":"Social Services",
            "subcategory":"Job Training",
            "type":"Services"
        }
    ],
    "sg:phone":"+1 706 647 3538",
    "sg:postcode":"30286",
    "sg:province":"GA",
    "sg:tags":[
        "rehabilitation"
    ],
    "wof:name":"Integra Rehabilitation",
    "wof:placetype":"venue"
},
  "geometry": {"coordinates":[-84.344598,32.876252],"type":"Point"}
}