{
  "type": "Feature",
  "properties": {
    "addr:full":"321 Aster Trce Canton GA 30115",
    "addr:housenumber":"321",
    "addr:postcode":"30115",
    "addr:street":"Aster Trce",
    "iso:country":"US",
    "sg:address":"321 Aster Trce",
    "sg:city":"Canton",
    "sg:classifiers":[
        {
            "category":"Wholesale",
            "subcategory":"Non-durable Goods",
            "type":"Manufacturing & Wholesale Goods"
        }
    ],
    "sg:phone":"+1 770 366 6458",
    "sg:postcode":"30115",
    "sg:province":"GA",
    "wof:name":"Mossy Creek Trading Co",
    "wof:placetype":"venue"
},
  "geometry": {"coordinates":[-84.39598599999999,34.186285],"type":"Point"}
}