{
  "type": "Feature",
  "properties": {
    "addr:full":"101 Washington St SE Gainesville GA 30501",
    "addr:housenumber":"101",
    "addr:postcode":"30501",
    "addr:street":"Washington St Se;Ga",
    "iso:country":"US",
    "sg:address":"101 Washington St SE",
    "sg:city":"Gainesville",
    "sg:classifiers":[
        {
            "category":"Shopping",
            "subcategory":"Clothing, Apparel, & Fashions",
            "type":"Retail Goods"
        }
    ],
    "sg:phone":"+1 770 534 1904",
    "sg:postcode":"30501",
    "sg:province":"GA",
    "sg:tags":[
        "evening",
        "tuxedo",
        "boutique",
        "item",
        "wear",
        "bridal",
        "rent"
    ],
    "wof:name":"Christopher's Tuxedo & Bridal",
    "wof:placetype":"venue"
},
  "geometry": {"coordinates":[-83.82580799999999,34.300354],"type":"Point"}
}