{
  "type": "Feature",
  "properties": {
    "iso:country":"US",
    "sg:address":"2130 Pleasant Hill Road",
    "sg:city":"Atlanta",
    "sg:classifiers":[
        {
            "category":"Shopping",
            "subcategory":"Mobile Phones",
            "type":"Retail Goods"
        }
    ],
    "sg:phone":"+1 678 475 9812",
    "sg:postcode":"30349",
    "sg:province":"GA",
    "wof:name":"T-Mobile",
    "wof:placetype":"venue"
},
  "geometry": {"coordinates":[-84.45949299999999,33.60004],"type":"Point"}
}