{
  "type": "Feature",
  "properties": {
    "addr:full":"250 Bull St Savannah GA 31401",
    "addr:housenumber":"250",
    "addr:postcode":"31401",
    "addr:street":"Bull St",
    "iso:country":"US",
    "sg:address":"250 Bull St",
    "sg:city":"Savannah",
    "sg:classifiers":[
        {
            "category":"Shopping",
            "subcategory":"Clothing, Apparel, & Fashions",
            "type":"Retail Goods"
        }
    ],
    "sg:phone":"+1 912 232 7414",
    "sg:postcode":"31401",
    "sg:province":"GA",
    "sg:tags":[
        "item",
        "boutique"
    ],
    "wof:name":"Gaucho",
    "wof:placetype":"venue"
},
  "geometry": {"coordinates":[-81.093462,32.074765],"type":"Point"}
}