{
  "type": "Feature",
  "properties": {
    "iso:country":"US",
    "sg:address":"2228 Rosier Rd Ste F",
    "sg:city":"Augusta",
    "sg:classifiers":[
        {
            "category":"Food & Beverages",
            "subcategory":"Meat & Fish",
            "type":"Retail Goods"
        }
    ],
    "sg:phone":"+1 706 796 7877",
    "sg:postcode":"30906",
    "sg:province":"GA",
    "sg:tags":[
        "seafood",
        "market"
    ],
    "wof:name":"Manna Mart",
    "wof:placetype":"venue"
},
  "geometry": {"coordinates":[-82.04541399999999,33.398033],"type":"Point"}
}