{
  "type": "Feature",
  "properties": {
    "iso:country":"US",
    "sg:address":"2813A Regency Blvd",
    "sg:city":"Augusta",
    "sg:classifiers":[
        {
            "category":"Insurance",
            "subcategory":"Insurance Agent",
            "type":"Services"
        },
        {
            "category":"Insurance",
            "subcategory":"Hazard Insurance",
            "type":"Services"
        },
        {
            "category":"Insurance",
            "subcategory":"Title Insurance",
            "type":"Services"
        },
        {
            "category":"Insurance",
            "subcategory":"Life Insurance",
            "type":"Services"
        }
    ],
    "sg:phone":"+1 706 738 6283",
    "sg:postcode":"30904",
    "sg:province":"GA",
    "sg:tags":[
        "business",
        "auto",
        "commercial",
        "homeowner",
        "motorcycle",
        "renter"
    ],
    "wof:name":"Allstate Insurance Company - Cozette Watkins",
    "wof:placetype":"venue"
},
  "geometry": {"coordinates":[-82.034436,33.442194],"type":"Point"}
}