{
  "type": "Feature",
  "properties": {
    "addr:full":"2880 Village Dr Marietta GA 30062",
    "addr:housenumber":"2880",
    "addr:postcode":"30062",
    "addr:street":"Village Dr",
    "iso:country":"US",
    "sg:address":"2880 Village Dr",
    "sg:city":"Marietta",
    "sg:classifiers":[
        {
            "category":"Home & Garden",
            "subcategory":"Carpets & Floor Coverings",
            "type":"Retail Goods"
        }
    ],
    "sg:phone":"+1 770 973 2067",
    "sg:postcode":"30062",
    "sg:province":"GA",
    "sg:tags":[
        "broker"
    ],
    "wof:name":"Quality Trade Show Carpet",
    "wof:placetype":"venue"
},
  "geometry": {"coordinates":[-84.46611900000001,34.005676],"type":"Point"}
}