{
  "type": "Feature",
  "properties": {
    "iso:country":"US",
    "sg:address":"313 Byrds Mill Rd",
    "sg:city":"Cordele",
    "sg:classifiers":[
        {
            "category":"Building & Trades",
            "subcategory":"Construction",
            "type":"Services"
        }
    ],
    "sg:phone":"+1 229 273 9363",
    "sg:postcode":"31015",
    "sg:province":"GA",
    "wof:name":"Ricky Jones Construction",
    "wof:placetype":"venue"
},
  "geometry": {"coordinates":[-83.82132,31.9234],"type":"Point"}
}