{
  "type": "Feature",
  "properties": {
    "addr:full":"7805 Abercorn St Savannah GA 31406",
    "addr:housenumber":"7805",
    "addr:postcode":"31406",
    "addr:street":"Abercorn St",
    "iso:country":"US",
    "sg:address":"7805 Abercorn St",
    "sg:city":"Savannah",
    "sg:classifiers":[
        {
            "category":"Shopping",
            "subcategory":"Gifts & Souvenirs",
            "type":"Retail Goods"
        }
    ],
    "sg:phone":"+1 912 352 7793",
    "sg:postcode":"31406",
    "sg:province":"GA",
    "sg:tags":[
        "shop"
    ],
    "wof:name":"Grand Harbour",
    "wof:placetype":"venue"
},
  "geometry": {"coordinates":[-81.11967,32.004034],"type":"Point"}
}