{
  "type": "Feature",
  "properties": {
    "iso:country":"US",
    "sg:address":"1690 Chantilly Dr",
    "sg:city":"Atlanta",
    "sg:classifiers":[
        {
            "category":"Building & Trades",
            "subcategory":"Construction",
            "type":"Services"
        }
    ],
    "sg:phone":"+1 678 916 7663",
    "sg:postcode":"30324",
    "sg:province":"GA",
    "sg:tags":[
        "roofing"
    ],
    "sg:website":"www.atlantaroofingcont.com",
    "wof:name":"Atlanta Roofing Contractors Inc.",
    "wof:placetype":"venue"
},
  "geometry": {"coordinates":[-84.347325,33.824641],"type":"Point"}
}