{
  "type": "Feature",
  "properties": {
    "iso:country":"US",
    "sg:address":"3823 Sentry Xing",
    "sg:city":"Marietta",
    "sg:classifiers":[
        {
            "category":"Professional",
            "subcategory":"Advertising",
            "type":"Services"
        }
    ],
    "sg:phone":"+1 770 565 1252",
    "sg:postcode":"30068",
    "sg:province":"GA",
    "wof:name":"A G Industries Inc",
    "wof:placetype":"venue"
},
  "geometry": {"coordinates":[-84.438692,33.967833],"type":"Point"}
}