{
  "type": "Feature",
  "properties": {
    "iso:country":"US",
    "sg:address":"3956 Murphy Hwy",
    "sg:city":"Mineral Bluff",
    "sg:classifiers":[
        {
            "category":"Autos & Motor Vehicles",
            "subcategory":"Auto Supplies",
            "type":"Retail Goods"
        }
    ],
    "sg:phone":"+1 706 374 5801",
    "sg:postcode":"30559",
    "sg:province":"GA",
    "wof:name":"Nicholsons Tires",
    "wof:placetype":"venue"
},
  "geometry": {"coordinates":[-84.25115700000001,34.938877],"type":"Point"}
}