{
  "type": "Feature",
  "properties": {
    "iso:country":"US",
    "sg:address":"6127 Oakbrook Pkwy",
    "sg:city":"Norcross",
    "sg:classifiers":[
        {
            "category":"Banks & Credit Unions",
            "subcategory":"Financial Services",
            "type":"Services"
        }
    ],
    "sg:phone":"+1 678 990 7338",
    "sg:postcode":"30093",
    "sg:province":"GA",
    "sg:tags":[
        "broker",
        "mortgage"
    ],
    "wof:name":"Georgia Funding Network Inc",
    "wof:placetype":"venue"
},
  "geometry": {"coordinates":[-84.206802,33.910198],"type":"Point"}
}