{
  "type": "Feature",
  "properties": {
    "addr:full":"104 Autumn Leaf Peachtree City GA 30269",
    "addr:housenumber":"104",
    "addr:postcode":"30269",
    "addr:street":"Autumn Leaf",
    "iso:country":"US",
    "sg:address":"104 Autumn Leaf",
    "sg:city":"Peachtree City",
    "sg:classifiers":[
        {
            "category":"Retail",
            "subcategory":"Repair Shop",
            "type":"Services"
        }
    ],
    "sg:phone":"+1 770 487 9452",
    "sg:postcode":"30269",
    "sg:province":"GA",
    "wof:name":"Fab Golf",
    "wof:placetype":"venue"
},
  "geometry": {"coordinates":[-84.56425900000001,33.385269],"type":"Point"}
}