{
  "type": "Feature",
  "properties": {
    "addr:full":"2854 Old Thompson Mill Rd Buford GA 30519",
    "addr:housenumber":"2854",
    "addr:postcode":"30519",
    "addr:street":"Old Thompson Mill Rd",
    "iso:country":"US",
    "sg:address":"2854 Old Thompson Mill Rd",
    "sg:city":"Buford",
    "sg:classifiers":[
        {
            "category":"Building & Trades",
            "subcategory":"Construction",
            "type":"Services"
        }
    ],
    "sg:phone":"+1 770 945 6960",
    "sg:postcode":"30519",
    "sg:province":"GA",
    "sg:tags":[
        "paving",
        "contractor"
    ],
    "wof:name":"Cooper Paving Inc",
    "wof:placetype":"venue"
},
  "geometry": {"coordinates":[-83.89783799999999,34.103117],"type":"Point"}
}