{
  "type": "Feature",
  "properties": {
    "iso:country":"US",
    "sg:address":"2880 Old Norcross Rd",
    "sg:city":"Tucker",
    "sg:classifiers":[
        {
            "category":"Building & Trades",
            "subcategory":"Construction",
            "type":"Services"
        }
    ],
    "sg:phone":"+1 770 414 0917",
    "sg:postcode":"30084",
    "sg:province":"GA",
    "sg:tags":[
        "concrete",
        "contractor"
    ],
    "wof:name":"Ortega's Concrete",
    "wof:placetype":"venue"
},
  "geometry": {"coordinates":[-84.203096,33.869983],"type":"Point"}
}