{
  "type": "Feature",
  "properties": {
    "iso:country":"US",
    "sg:address":"3349 Peachtree Road",
    "sg:city":"Atlanta",
    "sg:classifiers":[
        {
            "category":"Communications",
            "subcategory":"Film & Video Production",
            "type":"Services"
        },
        {
            "category":"Professional",
            "subcategory":"Art Services",
            "type":"Services"
        },
        {
            "category":"Professional",
            "subcategory":"Advertising",
            "type":"Services"
        }
    ],
    "sg:phone":"+1 404 680 6126",
    "sg:postcode":"30309",
    "sg:province":"GA",
    "sg:tags":[
        "agency",
        "services-commercial",
        "creative",
        "tape",
        "editing",
        "audio-visual"
    ],
    "sg:website":"http://www.mcicom.com",
    "wof:name":"Millennium Communications",
    "wof:placetype":"venue"
},
  "geometry": {"coordinates":[-84.367012,33.84801],"type":"Point"}
}