{
  "type": "Feature",
  "properties": {
    "addr:full":"4086 Robin Cir Atlanta GA 30349",
    "addr:housenumber":"4086",
    "addr:postcode":"30349",
    "addr:street":"Robin Cir",
    "iso:country":"US",
    "sg:address":"4086 Robin Cir",
    "sg:city":"Atlanta",
    "sg:classifiers":[
        {
            "category":"Retail",
            "subcategory":"Event Space",
            "type":"Services"
        }
    ],
    "sg:phone":"+1 770 306 2541",
    "sg:postcode":"30349",
    "sg:province":"GA",
    "sg:tags":[
        "ticket",
        "sale"
    ],
    "wof:name":"Splendid Soirees",
    "wof:placetype":"venue"
},
  "geometry": {"coordinates":[-84.578025,33.605354],"type":"Point"}
}