{
  "type": "Feature",
  "properties": {
    "iso:country":"US",
    "sg:address":"11545 Park Woods Cir",
    "sg:city":"Alpharetta",
    "sg:classifiers":[
        {
            "category":"Professional",
            "subcategory":"Lawyer & Legal Services",
            "type":"Services"
        }
    ],
    "sg:phone":"+1 678 867 9390",
    "sg:postcode":"30005",
    "sg:province":"GA",
    "wof:name":"Gokare Manjunath PC Atty",
    "wof:placetype":"venue"
},
  "geometry": {"coordinates":[-84.24299600000001,34.060799],"type":"Point"}
}