{
  "type": "Feature",
  "properties": {
    "iso:country":"US",
    "sg:address":"2690 Still Farms Ct NE",
    "sg:city":"Lawrenceville",
    "sg:classifiers":[
        {
            "category":"Professional",
            "type":"Services"
        }
    ],
    "sg:phone":"+1 678 742 8255",
    "sg:postcode":"30043",
    "sg:province":"GA",
    "wof:name":"Candy Walls",
    "wof:placetype":"venue"
},
  "geometry": {"coordinates":[-84.02149799999999,34.030463],"type":"Point"}
}