{
  "type": "Feature",
  "properties": {
    "addr:full":"4953 W Price Rd Suwanee GA 30024",
    "addr:housenumber":"4953",
    "addr:postcode":"30024",
    "addr:street":"W Price Rd",
    "iso:country":"US",
    "sg:address":"4953 W Price Rd",
    "sg:city":"Suwanee",
    "sg:classifiers":[
        {
            "category":"Wholesale",
            "subcategory":"Plants",
            "type":"Manufacturing & Wholesale Goods"
        }
    ],
    "sg:phone":"+1 770 932 5546",
    "sg:postcode":"30024",
    "sg:province":"GA",
    "sg:tags":[
        "supply"
    ],
    "wof:name":"Paz Wholesale Nursery",
    "wof:placetype":"venue"
},
  "geometry": {"coordinates":[-84.073549,34.089518],"type":"Point"}
}