{
  "type": "Feature",
  "properties": {
    "addr:full":"396 Stockwood Dr Woodstock GA 30188",
    "addr:housenumber":"396",
    "addr:postcode":"30188",
    "addr:street":"Stockwood Dr",
    "iso:country":"US",
    "sg:address":"396 Stockwood Dr",
    "sg:city":"Woodstock",
    "sg:classifiers":[
        {
            "category":"Building & Trades",
            "subcategory":"Landscaping Services",
            "type":"Services"
        }
    ],
    "sg:phone":"+1 770 620 8789",
    "sg:postcode":"30188",
    "sg:province":"GA",
    "wof:name":"Cooke Cutter Lawn Serv",
    "wof:placetype":"venue"
},
  "geometry": {"coordinates":[-84.52812900000001,34.078951],"type":"Point"}
}