{
  "type": "Feature",
  "properties": {
    "addr:full":"3404 Oakcliff Rd C-9 Atlanta GA 30340",
    "addr:housenumber":"3404",
    "addr:postcode":"30340",
    "addr:street":"Oakcliff Rd",
    "iso:country":"US",
    "sg:address":"3404 Oakcliff Rd C-9",
    "sg:city":"Atlanta",
    "sg:classifiers":[
        {
            "category":"Retail",
            "subcategory":"Laundry & Dry Cleaning",
            "type":"Services"
        }
    ],
    "sg:phone":"+1 678 328 1611",
    "sg:postcode":"30340",
    "sg:province":"GA",
    "sg:tags":[
        "cleaner",
        "rug",
        "carpet"
    ],
    "wof:name":"Sears Carpet Air Duct Cleaning",
    "wof:placetype":"venue"
},
  "geometry": {"coordinates":[-84.254496,33.905428],"type":"Point"}
}