{
  "type": "Feature",
  "properties": {
    "addr:full":"1175 Fleming St SE Smyrna GA 30080",
    "addr:housenumber":"1175",
    "addr:postcode":"30080",
    "addr:street":"Fleming St Se",
    "iso:country":"US",
    "sg:address":"1175 Fleming St SE",
    "sg:city":"Smyrna",
    "sg:classifiers":[
        {
            "category":"Retail",
            "subcategory":"Repair Shop",
            "type":"Services"
        },
        {
            "category":"Building & Trades",
            "subcategory":"Construction",
            "type":"Services"
        }
    ],
    "sg:phone":"+1 770 444 9142",
    "sg:postcode":"30080",
    "sg:province":"GA",
    "sg:tags":[
        "major",
        "refinishing",
        "appliance",
        "system",
        "contractor",
        "air conditioning"
    ],
    "wof:name":"Perfection Air Hvac",
    "wof:placetype":"venue"
},
  "geometry": {"coordinates":[-84.520308,33.88965],"type":"Point"}
}