{
  "type": "Feature",
  "properties": {
    "iso:country":"US",
    "sg:address":"1702 Brumby Cir",
    "sg:city":"Lithia Springs",
    "sg:classifiers":[
        {
            "category":"Shopping",
            "subcategory":"Discount & Variety Stores",
            "type":"Retail Goods"
        }
    ],
    "sg:phone":"+1 770 378 5295",
    "sg:postcode":"30122",
    "sg:province":"GA",
    "sg:tags":[
        "consultant"
    ],
    "wof:name":"Plan B Consultant Group  Inc",
    "wof:placetype":"venue"
},
  "geometry": {"coordinates":[-84.63030000000001,33.781202],"type":"Point"}
}