{
  "type": "Feature",
  "properties": {
    "iso:country":"US",
    "sg:address":"201 Talmadge Dr",
    "sg:city":"Moultrie",
    "sg:classifiers":[
        {
            "category":"Building & Trades",
            "subcategory":"Electrical",
            "type":"Services"
        }
    ],
    "sg:phone":"+1 229 985 4587",
    "sg:postcode":"31768",
    "sg:province":"GA",
    "sg:tags":[
        "electric",
        "industrial",
        "contractors-commercial",
        "contractor"
    ],
    "wof:name":"Ronny Knghts Colquitt Cnty Elc",
    "wof:placetype":"venue"
},
  "geometry": {"coordinates":[-83.771156,31.176001],"type":"Point"}
}