{
  "type": "Feature",
  "properties": {
    "addr:full":"186 New Hope Rd Lawrenceville GA 30045",
    "addr:housenumber":"186",
    "addr:postcode":"30045",
    "addr:street":"New Hope Rd",
    "iso:country":"US",
    "sg:address":"186 New Hope Rd",
    "sg:city":"Lawrenceville",
    "sg:classifiers":[
        {
            "category":"Organizations",
            "subcategory":"Religious Organization",
            "type":"Services"
        }
    ],
    "sg:phone":"+1 770 963 8802",
    "sg:postcode":"30045",
    "sg:province":"GA",
    "sg:tags":[
        "membership"
    ],
    "wof:name":"Southern Territorial Salvation",
    "wof:placetype":"venue"
},
  "geometry": {"coordinates":[-83.980058,33.951396],"type":"Point"}
}