{
  "type": "Feature",
  "properties": {
    "iso:country":"US",
    "sg:address":"4606 Ellisbury Dr",
    "sg:city":"Atlanta",
    "sg:classifiers":[
        {
            "category":"Professional",
            "subcategory":"Engineering",
            "type":"Services"
        }
    ],
    "sg:phone":"+1 770 458 5132",
    "sg:postcode":"30338",
    "sg:province":"GA",
    "sg:tags":[
        "trust",
        "investment",
        "real estate"
    ],
    "wof:name":"Chyn John",
    "wof:placetype":"venue"
},
  "geometry": {"coordinates":[-84.293599,33.93113],"type":"Point"}
}