{
  "type": "Feature",
  "properties": {
    "addr:full":"201 Tower Heights Rd Gainesville GA 30501",
    "addr:housenumber":"201",
    "addr:postcode":"30501",
    "addr:street":"Tower Heights Rd",
    "iso:country":"US",
    "sg:address":"201 Tower Heights Rd",
    "sg:city":"Gainesville",
    "sg:classifiers":[
        {
            "category":"Professional",
            "type":"Services"
        }
    ],
    "sg:phone":"+1 770 536 3036",
    "sg:postcode":"30501",
    "sg:province":"GA",
    "wof:name":"John E Hulsey Family LP",
    "wof:placetype":"venue"
},
  "geometry": {"coordinates":[-83.84138900000001,34.293012],"type":"Point"}
}