{
  "type": "Feature",
  "properties": {
    "addr:full":"22 Lambeth Dr Hiram GA 30141",
    "addr:housenumber":"22",
    "addr:postcode":"30141",
    "addr:street":"Lambeth Dr",
    "iso:country":"US",
    "sg:address":"22 Lambeth Dr",
    "sg:city":"Hiram",
    "sg:classifiers":[
        {
            "category":"Professional",
            "subcategory":"Advertising",
            "type":"Services"
        }
    ],
    "sg:phone":"+1 770 949 3267",
    "sg:postcode":"30141",
    "sg:province":"GA",
    "wof:name":"Source",
    "wof:placetype":"venue"
},
  "geometry": {"coordinates":[-84.796302,33.817436],"type":"Point"}
}