{
  "type": "Feature",
  "properties": {
    "addr:full":"304 E Washington St Athens GA 30601",
    "addr:housenumber":"304",
    "addr:postcode":"30601",
    "addr:street":"E Washington St",
    "iso:country":"US",
    "sg:address":"304 E Washington St",
    "sg:city":"Athens",
    "sg:classifiers":[
        {
            "category":"Professional",
            "subcategory":"Lawyer & Legal Services",
            "type":"Services"
        }
    ],
    "sg:phone":"+1 404 602 5948",
    "sg:postcode":"30601",
    "sg:province":"GA",
    "sg:tags":[
        "attorney",
        "law",
        "personal",
        "medical",
        "malpractice",
        "real estate",
        "injury",
        "criminal"
    ],
    "sg:website":"http://www.cntblaw.com",
    "wof:name":"Cook Noell Tolley & Bates LLP",
    "wof:placetype":"venue"
},
  "geometry": {"coordinates":[-83.374746,33.959623],"type":"Point"}
}