{
  "type": "Feature",
  "properties": {
    "addr:full":"584 Line Church Rd Alto GA 30510",
    "addr:housenumber":"584",
    "addr:postcode":"30510",
    "addr:street":"Line Church Rd Alto",
    "iso:country":"US",
    "sg:address":"584 Line Church Rd",
    "sg:city":"Alto",
    "sg:classifiers":[
        {
            "category":"Professional",
            "type":"Services"
        }
    ],
    "sg:phone":"+1 706 677 3905",
    "sg:postcode":"30510",
    "sg:province":"GA",
    "wof:name":"J Stephen Shi",
    "wof:placetype":"venue"
},
  "geometry": {"coordinates":[-83.519831,34.404185],"type":"Point"}
}