{
  "type": "Feature",
  "properties": {
    "iso:country":"US",
    "sg:address":"479 E Main St",
    "sg:city":"Cartersville",
    "sg:classifiers":[
        {
            "category":"Personal",
            "subcategory":"Beauty Salon",
            "type":"Services"
        },
        {
            "category":"Personal",
            "subcategory":"Barber",
            "type":"Services"
        },
        {
            "category":"Personal",
            "subcategory":"Nail Salon",
            "type":"Services"
        }
    ],
    "sg:phone":"+1 770 386 0026",
    "sg:postcode":"30121",
    "sg:province":"GA",
    "sg:tags":[
        "hair",
        "stylist"
    ],
    "wof:name":"Hair Techniques",
    "wof:placetype":"venue"
},
  "geometry": {"coordinates":[-84.786115,34.16837],"type":"Point"}
}