{
  "type": "Feature",
  "properties": {
    "addr:full":"1462 Montreal Rd Tucker GA 30084",
    "addr:housenumber":"1462",
    "addr:postcode":"30084",
    "addr:street":"Montreal Rd",
    "iso:country":"US",
    "sg:address":"1462 Montreal Rd",
    "sg:city":"Tucker",
    "sg:classifiers":[
        {
            "category":"Health Services",
            "subcategory":"Doctor",
            "type":"Services"
        }
    ],
    "sg:phone":"+1 770 938 2929",
    "sg:postcode":"30084",
    "sg:province":"GA",
    "sg:tags":[
        "physician",
        "surgeon"
    ],
    "wof:name":"Georgia Women's Specialist",
    "wof:placetype":"venue"
},
  "geometry": {"coordinates":[-84.254665,33.825792],"type":"Point"}
}