{
  "type": "Feature",
  "properties": {
    "iso:country":"US",
    "sg:address":"3260 Covington Hwy",
    "sg:city":"Decatur",
    "sg:classifiers":[
        {
            "category":"Organizations",
            "subcategory":"Religious Organization",
            "type":"Services"
        }
    ],
    "sg:phone":"+1 404 294 4063",
    "sg:postcode":"30032",
    "sg:province":"GA",
    "sg:tags":[
        "church"
    ],
    "wof:name":"Avondale Pittillo Umc",
    "wof:placetype":"venue"
},
  "geometry": {"coordinates":[-84.257085,33.773501],"type":"Point"}
}