{
  "type": "Feature",
  "properties": {
    "addr:full":"150 Governor's Sq Ste D Fayetteville GA 30215",
    "addr:housenumber":"150",
    "addr:postcode":"30215",
    "addr:street":"Governor'S Sq Ste D",
    "iso:country":"US",
    "sg:address":"150 Governor's Sq Ste D",
    "sg:city":"Fayetteville",
    "sg:classifiers":[
        {
            "category":"Personal",
            "subcategory":"Beauty Salon",
            "type":"Services"
        }
    ],
    "sg:phone":"+1 770 487 1434",
    "sg:postcode":"30215",
    "sg:province":"GA",
    "sg:tags":[
        "hair"
    ],
    "sg:website":"www.cgloveshair.com",
    "wof:name":"C.G. Salon",
    "wof:placetype":"venue"
},
  "geometry": {"coordinates":[-84.555126,33.427678],"type":"Point"}
}