{
  "type": "Feature",
  "properties": {
    "addr:full":"1102 Park Blvd Cairo GA 39828",
    "addr:housenumber":"1102",
    "addr:postcode":"39828",
    "addr:street":"Park Blvd",
    "iso:country":"US",
    "sg:address":"1102 Park Blvd",
    "sg:city":"Cairo",
    "sg:classifiers":[
        {
            "category":"Organizations",
            "subcategory":"Religious Organization",
            "type":"Services"
        }
    ],
    "sg:phone":"+1 229 377 2090",
    "sg:postcode":"39828",
    "sg:province":"GA",
    "wof:name":"Memorial Baptist Church",
    "wof:placetype":"venue"
},
  "geometry": {"coordinates":[-84.194479,30.881805],"type":"Point"}
}