{
  "type": "Feature",
  "properties": {
    "iso:country":"US",
    "sg:address":"120 Interstate North Pkwy SE Ste 308",
    "sg:city":"Atlanta",
    "sg:classifiers":[
        {
            "category":"Home & Garden",
            "subcategory":"Home Furnishings",
            "type":"Retail Goods"
        }
    ],
    "sg:phone":"+1 770 612 1500",
    "sg:postcode":"30339",
    "sg:province":"GA",
    "sg:tags":[
        "decor"
    ],
    "wof:name":"Ben Tally & Associates",
    "wof:placetype":"venue"
},
  "geometry": {"coordinates":[-84.465369,33.903298],"type":"Point"}
}