{
  "type": "Feature",
  "properties": {
    "addr:full":"1611 McNutt Creek Rd Bogart GA 30622",
    "addr:housenumber":"1611",
    "addr:postcode":"30622",
    "addr:street":"Mcnutt Creek Rd",
    "iso:country":"US",
    "sg:address":"1611 McNutt Creek Rd",
    "sg:city":"Bogart",
    "sg:classifiers":[
        {
            "category":"Building & Trades",
            "subcategory":"Construction",
            "type":"Services"
        }
    ],
    "sg:phone":"+1 770 725 5089",
    "sg:postcode":"30622",
    "sg:province":"GA",
    "sg:tags":[
        "contractor"
    ],
    "wof:name":"Eddy Gunter Masonry Contr",
    "wof:placetype":"venue"
},
  "geometry": {"coordinates":[-83.547332,33.934001],"type":"Point"}
}