{
  "type": "Feature",
  "properties": {
    "iso:country":"US",
    "sg:address":"110 Gaye St",
    "sg:city":"Brunswick",
    "sg:classifiers":[
        {
            "category":"Shopping",
            "subcategory":"Used Merchandise",
            "type":"Retail Goods"
        }
    ],
    "sg:phone":"+1 912 265 3633",
    "sg:postcode":"31520",
    "sg:province":"GA",
    "wof:name":"Jacks Antiques & Collectibles",
    "wof:placetype":"venue"
},
  "geometry": {"coordinates":[-81.508528,31.215532],"type":"Point"}
}