{
  "type": "Feature",
  "properties": {
    "iso:country":"US",
    "sg:address":"851 Main St SW",
    "sg:city":"Gainesville",
    "sg:classifiers":[
        {
            "category":"Wholesale",
            "subcategory":"Electrical",
            "type":"Manufacturing & Wholesale Goods"
        }
    ],
    "sg:phone":"+1 706 776 9576",
    "sg:postcode":"30501",
    "sg:province":"GA",
    "sg:tags":[
        "fire",
        "alarm",
        "installs",
        "system",
        "equipment",
        "electronic"
    ],
    "sg:website":"http://www.electronicsalesco.com",
    "wof:name":"Electronic Sales Co.",
    "wof:placetype":"venue"
},
  "geometry": {"coordinates":[-83.820992,34.29044],"type":"Point"}
}