{
  "type": "Feature",
  "properties": {
    "addr:full":"8070 Campbellton Redwine Rd Palmetto GA 30268",
    "addr:housenumber":"8070",
    "addr:postcode":"30268",
    "addr:street":"Campbellton Redwine Rd",
    "iso:country":"US",
    "sg:address":"8070 Campbellton Redwine Rd",
    "sg:city":"Palmetto",
    "sg:classifiers":[
        {
            "category":"Farming",
            "subcategory":"Farm",
            "type":"Manufacturing & Wholesale Goods"
        }
    ],
    "sg:phone":"+1 770 463 3818",
    "sg:postcode":"30268",
    "sg:province":"GA",
    "sg:tags":[
        "crop",
        "general"
    ],
    "wof:name":"Spirit of Christmas Tree",
    "wof:placetype":"venue"
},
  "geometry": {"coordinates":[-84.802346,33.535573],"type":"Point"}
}