{
  "type": "Feature",
  "properties": {
    "iso:country":"US",
    "sg:address":"6100 Lake Forrest Drive NW Suite 340",
    "sg:city":"Atlanta",
    "sg:classifiers":[
        {
            "category":"Professional",
            "subcategory":"Lawyer & Legal Services",
            "type":"Services"
        }
    ],
    "sg:phone":"+1 404 705 9299",
    "sg:postcode":"30328",
    "sg:province":"GA",
    "wof:name":"Rodgers Walter A Patnt Atty",
    "wof:placetype":"venue"
},
  "geometry": {"coordinates":[-84.387061,33.920803],"type":"Point"}
}