{
  "type": "Feature",
  "properties": {
    "iso:country":"US",
    "sg:address":"3629 Montreal Creek Cir",
    "sg:city":"Clarkston",
    "sg:classifiers":[
        {
            "category":"Communications",
            "type":"Services"
        }
    ],
    "sg:phone":"+1 404 508 2234",
    "sg:postcode":"30021",
    "sg:province":"GA",
    "sg:tags":[
        "consultant"
    ],
    "wof:name":"Inc Group",
    "wof:placetype":"venue"
},
  "geometry": {"coordinates":[-84.242538,33.815263],"type":"Point"}
}