{
  "type": "Feature",
  "properties": {
    "iso:country":"US",
    "sg:address":"2954 Bankhead Hwy",
    "sg:city":"Austell",
    "sg:classifiers":[
        {
            "category":"Retail",
            "subcategory":"Repair Shop",
            "type":"Services"
        }
    ],
    "sg:phone":"+1 770 819 0092",
    "sg:postcode":"30116",
    "sg:province":"GA",
    "sg:tags":[
        "appliance",
        "electrical"
    ],
    "wof:name":"Rudy's Appliances",
    "wof:placetype":"venue"
},
  "geometry": {"coordinates":[-84.985271,33.614491],"type":"Point"}
}