{
  "type": "Feature",
  "properties": {
    "iso:country":"US",
    "sg:address":"110 Kristin Dr",
    "sg:city":"Ringgold",
    "sg:classifiers":[
        {
            "category":"Restaurant",
            "type":"Food & Drink"
        }
    ],
    "sg:phone":"+1 706 937 5400",
    "sg:postcode":"30736",
    "sg:province":"GA",
    "sg:tags":[
        "mexican"
    ],
    "wof:name":"Los Reyes",
    "wof:placetype":"venue"
},
  "geometry": {"coordinates":[-85.12969699999999,34.91283],"type":"Point"}
}