{
  "type": "Feature",
  "properties": {
    "addr:full":"215 Clayton Wallace Rd Dawsonville GA 30534",
    "addr:housenumber":"215",
    "addr:postcode":"30534",
    "addr:street":"Clayton Wallace Rd",
    "iso:country":"US",
    "sg:address":"215 Clayton Wallace Rd",
    "sg:city":"Dawsonville",
    "sg:classifiers":[
        {
            "category":"Government",
            "subcategory":"Office",
            "type":"Public Place"
        }
    ],
    "sg:phone":"+1 706 216 2079",
    "sg:postcode":"30534",
    "sg:province":"GA",
    "wof:name":"Kenneth Lee Little",
    "wof:placetype":"venue"
},
  "geometry": {"coordinates":[-84.014094,34.363142],"type":"Point"}
}