{
  "type": "Feature",
  "properties": {
    "iso:country":"US",
    "sg:address":"6513 Sunset Ct",
    "sg:city":"Flowery Branch",
    "sg:classifiers":[
        {
            "category":"Shopping",
            "subcategory":"Gifts & Souvenirs",
            "type":"Retail Goods"
        }
    ],
    "sg:phone":"+1 770 965 3008",
    "sg:postcode":"30542",
    "sg:province":"GA",
    "wof:name":"Creative Wagon",
    "wof:placetype":"venue"
},
  "geometry": {"coordinates":[-83.972143,34.173847],"type":"Point"}
}