{
  "type": "Feature",
  "properties": {
    "addr:full":"1630 Peachtree Industrial Blvd Suwanee GA 30024",
    "addr:housenumber":"1630",
    "addr:postcode":"30024",
    "addr:street":"Peachtree Industrial Blvd",
    "iso:country":"US",
    "sg:address":"1630 Peachtree Industrial Blvd",
    "sg:city":"Suwanee",
    "sg:classifiers":[
        {
            "category":"Real Estate",
            "subcategory":"Developer",
            "type":"Services"
        }
    ],
    "sg:phone":"+1 770 945 5059",
    "sg:postcode":"30024",
    "sg:province":"GA",
    "sg:tags":[
        "development"
    ],
    "wof:name":"Perimeter Group Corporation",
    "wof:placetype":"venue"
},
  "geometry": {"coordinates":[-84.103791,34.035361],"type":"Point"}
}