{
  "type": "Feature",
  "properties": {
    "iso:country":"US",
    "sg:address":"6251 Vernon Woods Dr NE",
    "sg:city":"Atlanta",
    "sg:classifiers":[
        {
            "category":"Professional",
            "subcategory":"Management & Consulting",
            "type":"Services"
        }
    ],
    "sg:phone":"+1 404 943 1761",
    "sg:postcode":"30328",
    "sg:province":"GA",
    "sg:tags":[
        "business"
    ],
    "wof:name":"Multi Tier Solutions Inc",
    "wof:placetype":"venue"
},
  "geometry": {"coordinates":[-84.370952,33.925969],"type":"Point"}
}