{
  "type": "Feature",
  "properties": {
    "addr:full":"434 Elbert St Elberton GA 30635",
    "addr:housenumber":"434",
    "addr:postcode":"30635",
    "addr:street":"Elbert St",
    "iso:country":"US",
    "sg:address":"434 Elbert St",
    "sg:city":"Elberton",
    "sg:classifiers":[
        {
            "category":"Food & Beverages",
            "subcategory":"Groceries & Convenience Stores",
            "type":"Retail Goods"
        }
    ],
    "sg:phone":"+1 706 213 1889",
    "sg:postcode":"30635",
    "sg:province":"GA",
    "wof:name":"Golden Pantry Food Store",
    "wof:placetype":"venue"
},
  "geometry": {"coordinates":[-82.856458,34.107075],"type":"Point"}
}