{
  "type": "Feature",
  "properties": {
    "iso:country":"US",
    "sg:address":"107 Randolph St NE",
    "sg:city":"Atlanta",
    "sg:classifiers":[
        {
            "category":"Professional",
            "subcategory":"Business Services",
            "type":"Services"
        }
    ],
    "sg:phone":"+1 404 525 1797",
    "sg:postcode":"30312",
    "sg:province":"GA",
    "sg:tags":[
        "consultant",
        "coach"
    ],
    "wof:name":"Michael D Syphoe Consultant",
    "wof:placetype":"venue"
},
  "geometry": {"coordinates":[-84.367921,33.756833],"type":"Point"}
}