{
  "type": "Feature",
  "properties": {
    "iso:country":"US",
    "sg:address":"3527 Norwich St",
    "sg:city":"Brunswick",
    "sg:classifiers":[
        {
            "category":"Building & Trades",
            "subcategory":"Construction",
            "type":"Services"
        }
    ],
    "sg:phone":"+1 912 265 0030",
    "sg:postcode":"31520",
    "sg:province":"GA",
    "sg:tags":[
        "general",
        "contractor"
    ],
    "wof:name":"John Mc Eachern Co",
    "wof:placetype":"venue"
},
  "geometry": {"coordinates":[-81.501544,31.177592],"type":"Point"}
}