{
  "type": "Feature",
  "properties": {
    "iso:country":"US",
    "sg:address":"6842 Creekwood Dr",
    "sg:city":"Douglasville",
    "sg:classifiers":[
        {
            "category":"Banks & Credit Unions",
            "subcategory":"Investment Brokerage",
            "type":"Services"
        }
    ],
    "sg:phone":"+1 678 391 0041",
    "sg:postcode":"30135",
    "sg:province":"GA",
    "sg:tags":[
        "advisory",
        "financial"
    ],
    "wof:name":"D & K Brown Financial Spec",
    "wof:placetype":"venue"
},
  "geometry": {"coordinates":[-84.746449,33.723073],"type":"Point"}
}