{
  "type": "Feature",
  "properties": {
    "iso:country":"US",
    "sg:address":"355 Cliett Rd",
    "sg:city":"Byron",
    "sg:classifiers":[
        {
            "category":"Utilities",
            "subcategory":"Refuse",
            "type":"Services"
        }
    ],
    "sg:phone":"+1 478 956 2300",
    "sg:postcode":"31008",
    "sg:province":"GA",
    "sg:tags":[
        "wood",
        "construction",
        "recycling",
        "commercial"
    ],
    "wof:name":"J D Rogers Inc",
    "wof:placetype":"venue"
},
  "geometry": {"coordinates":[-83.78443,32.598227],"type":"Point"}
}