{
  "type": "Feature",
  "properties": {
    "iso:country":"US",
    "sg:address":"2860 Emerald Springs Dr",
    "sg:city":"Lawrenceville",
    "sg:classifiers":[
        {
            "category":"Professional",
            "type":"Services"
        }
    ],
    "sg:phone":"+1 770 466 6935",
    "sg:postcode":"30045",
    "sg:province":"GA",
    "wof:name":"David Roberts Inc",
    "wof:placetype":"venue"
},
  "geometry": {"coordinates":[-83.88489300000001,33.901972],"type":"Point"}
}