{
  "type": "Feature",
  "properties": {
    "iso:country":"US",
    "sg:address":"1229 Graham Rd",
    "sg:city":"Dublin",
    "sg:classifiers":[
        {
            "category":"Professional",
            "type":"Services"
        }
    ],
    "sg:phone":"+1 478 272 5817",
    "sg:postcode":"31027",
    "sg:province":"GA",
    "wof:name":"Jason Mimbs",
    "wof:placetype":"venue"
},
  "geometry": {"coordinates":[-82.79634,32.618648],"type":"Point"}
}