{
  "type": "Feature",
  "properties": {
    "addr:full":"101 Baldwin Dr Albany GA 31707",
    "addr:housenumber":"101",
    "addr:postcode":"31707",
    "addr:street":"Baldwin Dr",
    "iso:country":"US",
    "sg:address":"101 Baldwin Dr",
    "sg:city":"Albany",
    "sg:classifiers":[
        {
            "category":"Home & Garden",
            "subcategory":"Building Materials",
            "type":"Retail Goods"
        }
    ],
    "sg:phone":"+1 229 883 7450",
    "sg:postcode":"31707",
    "sg:province":"GA",
    "sg:tags":[
        "plumbing",
        "fixture",
        "supply"
    ],
    "wof:name":"Hughes Supply Inc",
    "wof:placetype":"venue"
},
  "geometry": {"coordinates":[-84.187067,31.576919],"type":"Point"}
}