{
  "type": "Feature",
  "properties": {
    "addr:full":"124 Butler Lake Dr Saint Simons Island GA 31522",
    "addr:housenumber":"124",
    "addr:postcode":"31522",
    "addr:street":"Butler Lake Dr",
    "iso:country":"US",
    "sg:address":"124 Butler Lake Dr",
    "sg:city":"Saint Simons Island",
    "sg:classifiers":[
        {
            "category":"Real Estate",
            "subcategory":"Real Estate Agent",
            "type":"Services"
        }
    ],
    "sg:phone":"+1 912 638 2701",
    "sg:postcode":"31522",
    "sg:province":"GA",
    "wof:name":"McKenzie Appraisal Services",
    "wof:placetype":"venue"
},
  "geometry": {"coordinates":[-81.346318,31.280791],"type":"Point"}
}