{
  "type": "Feature",
  "properties": {
    "iso:country":"US",
    "sg:address":"3263 Highway 52 E",
    "sg:city":"Ellijay",
    "sg:classifiers":[
        {
            "category":"Retail",
            "subcategory":"Auto Repair",
            "type":"Services"
        }
    ],
    "sg:phone":"+1 706 276 4552",
    "sg:postcode":"30536",
    "sg:province":"GA",
    "sg:tags":[
        "body",
        "painting",
        "repairing",
        "automobile"
    ],
    "wof:name":"Eastside Auto Body",
    "wof:placetype":"venue"
},
  "geometry": {"coordinates":[-84.445047,34.659499],"type":"Point"}
}