{
  "type": "Feature",
  "properties": {
    "iso:country":"US",
    "sg:address":"715 N Main St",
    "sg:city":"Hiawassee",
    "sg:classifiers":[
        {
            "category":"Shopping",
            "subcategory":"Gifts & Souvenirs",
            "type":"Retail Goods"
        }
    ],
    "sg:phone":"+1 706 896 3559",
    "sg:postcode":"30545",
    "sg:province":"GA",
    "sg:tags":[
        "shop"
    ],
    "wof:name":"Always Christmas",
    "wof:placetype":"venue"
},
  "geometry": {"coordinates":[-83.725696,34.699976],"type":"Point"}
}