{
  "type": "Feature",
  "properties": {
    "iso:country":"US",
    "sg:address":"315 E Solomon St",
    "sg:city":"Griffin",
    "sg:classifiers":[
        {
            "category":"Place Of Worship",
            "type":"Public Place"
        }
    ],
    "sg:phone":"+1 678 603 2012",
    "sg:postcode":"30223",
    "sg:province":"GA",
    "sg:tags":[
        "church"
    ],
    "wof:name":"Journey Church Dove Down",
    "wof:placetype":"venue"
},
  "geometry": {"coordinates":[-84.26027999999999,33.248559],"type":"Point"}
}