{
  "type": "Feature",
  "properties": {
    "addr:full":"10 W Huntington Rd Athens GA 30606",
    "addr:housenumber":"10",
    "addr:postcode":"30606",
    "addr:street":"W Huntington Rd",
    "iso:country":"US",
    "sg:address":"10 W Huntington Rd",
    "sg:city":"Athens",
    "sg:classifiers":[
        {
            "category":"Personal",
            "subcategory":"Beauty Salon",
            "type":"Services"
        }
    ],
    "sg:phone":"+1 706 425 2847",
    "sg:postcode":"30606",
    "sg:province":"GA",
    "sg:tags":[
        "shop"
    ],
    "wof:name":"VIP Salon",
    "wof:placetype":"venue"
},
  "geometry": {"coordinates":[-83.464578,33.942077],"type":"Point"}
}