{
  "type": "Feature",
  "properties": {
    "iso:country":"US",
    "sg:address":"3805 Community Rd",
    "sg:city":"Brunswick",
    "sg:classifiers":[
        {
            "category":"Real Estate",
            "subcategory":"Real Estate Services",
            "type":"Services"
        },
        {
            "category":"Real Estate",
            "subcategory":"Real Estate Agent",
            "type":"Services"
        }
    ],
    "sg:phone":"+1 912 265 6767",
    "sg:postcode":"31520",
    "sg:province":"GA",
    "sg:tags":[
        "buyer",
        "broker"
    ],
    "sg:website":"http://driggersrealty.com",
    "wof:name":"Driggers Realty Inc",
    "wof:placetype":"venue"
},
  "geometry": {"coordinates":[-81.49399200000001,31.201214],"type":"Point"}
}