{
  "type": "Feature",
  "properties": {
    "addr:full":"3041 Oakcliff Rd Atlanta GA 30340",
    "addr:housenumber":"3041",
    "addr:postcode":"30340",
    "addr:street":"Oakcliff Rd",
    "iso:country":"US",
    "sg:address":"3041 Oakcliff Rd",
    "sg:city":"Atlanta",
    "sg:classifiers":[
        {
            "category":"Building & Trades",
            "subcategory":"Locksmith",
            "type":"Services"
        }
    ],
    "sg:phone":"+1 866 713 9402",
    "sg:postcode":"30340",
    "sg:province":"GA",
    "sg:tags":[
        "key"
    ],
    "wof:name":"24 Hour 1 Emergency Locksmith",
    "wof:placetype":"venue"
},
  "geometry": {"coordinates":[-84.26308,33.910965],"type":"Point"}
}