{
  "type": "Feature",
  "properties": {
    "iso:country":"US",
    "sg:address":"1122 Old Doctortown Rd",
    "sg:city":"Jesup",
    "sg:classifiers":[
        {
            "category":"Building & Trades",
            "subcategory":"Construction",
            "type":"Services"
        }
    ],
    "sg:phone":"+1 912 588 0222",
    "sg:postcode":"31545",
    "sg:province":"GA",
    "sg:tags":[
        "house"
    ],
    "wof:name":"George E Moxley",
    "wof:placetype":"venue"
},
  "geometry": {"coordinates":[-81.84584700000001,31.642924],"type":"Point"}
}