{
  "type": "Feature",
  "properties": {
    "addr:full":"108 Woolsey Rd Hampton GA 30228",
    "addr:housenumber":"108",
    "addr:postcode":"30228",
    "addr:street":"Woolsey Rd",
    "iso:country":"US",
    "sg:address":"108 Woolsey Rd",
    "sg:city":"Hampton",
    "sg:classifiers":[
        {
            "category":"Deli",
            "type":"Food & Drink"
        }
    ],
    "sg:menulink":"http://www.allmenus.com/ga/hampton/126990-blimpie-subs--sandwiches/menu/",
    "sg:phone":"+1 770 707 2200",
    "sg:postcode":"30228",
    "sg:province":"GA",
    "sg:tags":[
        "wrap",
        "american",
        "sandwich"
    ],
    "wof:name":"Blimpie Subs & Sandwiches",
    "wof:placetype":"venue"
},
  "geometry": {"coordinates":[-84.298777,33.381077],"type":"Point"}
}