{
  "type": "Feature",
  "properties": {
    "addr:full":"2068 Wellborn Rd Lithonia GA 30058",
    "addr:housenumber":"2068",
    "addr:postcode":"30058",
    "addr:street":"Wellborn Rd",
    "iso:country":"US",
    "sg:address":"2068 Wellborn Rd",
    "sg:city":"Lithonia",
    "sg:classifiers":[
        {
            "category":"Place Of Worship",
            "type":"Public Place"
        }
    ],
    "sg:phone":"+1 770 593 0315",
    "sg:postcode":"30058",
    "sg:province":"GA",
    "sg:tags":[
        "church"
    ],
    "wof:name":"Tabernacle Of Testimonies",
    "wof:placetype":"venue"
},
  "geometry": {"coordinates":[-84.146773,33.72805],"type":"Point"}
}