{
  "type": "Feature",
  "properties": {
    "iso:country":"US",
    "sg:address":"1506 Wood Thrush Way",
    "sg:city":"Marietta",
    "sg:classifiers":[
        {
            "category":"Real Estate",
            "subcategory":"Real Estate Agent",
            "type":"Services"
        }
    ],
    "sg:phone":"+1 770 951 2476",
    "sg:postcode":"30062",
    "sg:province":"GA",
    "sg:tags":[
        "inspection"
    ],
    "wof:name":"Keystone Home Inspections",
    "wof:placetype":"venue"
},
  "geometry": {"coordinates":[-84.480684,33.988661],"type":"Point"}
}