{
  "type": "Feature",
  "properties": {
    "iso:country":"US",
    "sg:address":"820 James Jackson Pkwy NW",
    "sg:city":"Atlanta",
    "sg:classifiers":[
        {
            "category":"Food & Beverages",
            "subcategory":"Groceries & Convenience Stores",
            "type":"Retail Goods"
        }
    ],
    "sg:phone":"+1 404 794 1019",
    "sg:postcode":"30318",
    "sg:province":"GA",
    "sg:tags":[
        "grocer"
    ],
    "wof:name":"Buy Low Super Market",
    "wof:placetype":"venue"
},
  "geometry": {"coordinates":[-84.473834,33.776415],"type":"Point"}
}