{
  "type": "Feature",
  "properties": {
    "iso:country":"US",
    "sg:address":"1329 N Jefferson St",
    "sg:city":"Dublin",
    "sg:classifiers":[
        {
            "category":"Food & Beverages",
            "subcategory":"Groceries & Convenience Stores",
            "type":"Retail Goods"
        }
    ],
    "sg:phone":"+1 478 275 2446",
    "sg:postcode":"31021",
    "sg:province":"GA",
    "wof:name":"Friendly Gus Food Store 10",
    "wof:placetype":"venue"
},
  "geometry": {"coordinates":[-82.916785,32.562899],"type":"Point"}
}