{
  "type": "Feature",
  "properties": {
    "addr:full":"120 Rommel Ave Savannah GA 31408",
    "addr:housenumber":"120",
    "addr:postcode":"31408",
    "addr:street":"Rommel Ave",
    "iso:country":"US",
    "sg:address":"120 Rommel Ave",
    "sg:city":"Savannah",
    "sg:classifiers":[
        {
            "category":"Building & Trades",
            "subcategory":"Plumbing",
            "type":"Services"
        }
    ],
    "sg:phone":"+1 912 964 5305",
    "sg:postcode":"31408",
    "sg:province":"GA",
    "sg:tags":[
        "contractor"
    ],
    "wof:name":"Jerry Bazemore Plumbing",
    "wof:placetype":"venue"
},
  "geometry": {"coordinates":[-81.156634,32.114001],"type":"Point"}
}