{
  "type": "Feature",
  "properties": {
    "addr:full":"1709 E Oglethorpe Blvd Albany GA 31705",
    "addr:housenumber":"1709",
    "addr:postcode":"31705",
    "addr:street":"E Oglethorpe Blvd",
    "iso:country":"US",
    "sg:address":"1709 E Oglethorpe Blvd",
    "sg:city":"Albany",
    "sg:classifiers":[
        {
            "category":"Banks & Credit Unions",
            "subcategory":"Financial Services",
            "type":"Services"
        }
    ],
    "sg:phone":"+1 229 439 0123",
    "sg:postcode":"31705",
    "sg:province":"GA",
    "sg:tags":[
        "loan"
    ],
    "wof:name":"Dougherty Finance",
    "wof:placetype":"venue"
},
  "geometry": {"coordinates":[-84.10667599999999,31.570921],"type":"Point"}
}