{
  "type": "Feature",
  "properties": {
    "iso:country":"US",
    "sg:address":"4893 Autumn Cir",
    "sg:city":"Stone Mountain",
    "sg:classifiers":[
        {
            "category":"Communications",
            "subcategory":"Film & Video Production",
            "type":"Services"
        }
    ],
    "sg:phone":"+1 404 550 1241",
    "sg:postcode":"30088",
    "sg:province":"GA",
    "sg:tags":[
        "motion"
    ],
    "wof:name":"Seeing Beyond Images",
    "wof:placetype":"venue"
},
  "geometry": {"coordinates":[-84.19085800000001,33.771928],"type":"Point"}
}