{
  "type": "Feature",
  "properties": {
    "addr:full":"310 E Brewton St Mc Rae GA 31055",
    "addr:housenumber":"310",
    "addr:postcode":"31055",
    "addr:street":"E Brewton St Mc Rae",
    "iso:country":"US",
    "sg:address":"310 E Brewton St",
    "sg:city":"Mc Rae",
    "sg:classifiers":[
        {
            "category":"Government",
            "subcategory":"Office",
            "type":"Public Place"
        }
    ],
    "sg:phone":"+1 229 868 3030",
    "sg:postcode":"31055",
    "sg:province":"GA",
    "sg:tags":[
        "state",
        "resource"
    ],
    "wof:name":"Human Resources Dept",
    "wof:placetype":"venue"
},
  "geometry": {"coordinates":[-82.897206,32.060152],"type":"Point"}
}