{
  "type": "Feature",
  "properties": {
    "addr:full":"306 Christian Ct Hampton GA 30228",
    "addr:housenumber":"306",
    "addr:postcode":"30228",
    "addr:street":"Christian Ct",
    "iso:country":"US",
    "sg:address":"306 Christian Ct",
    "sg:city":"Hampton",
    "sg:classifiers":[
        {
            "category":"Wholesale",
            "subcategory":"Machinery & Supplies",
            "type":"Manufacturing & Wholesale Goods"
        }
    ],
    "sg:phone":"+1 770 707 1047",
    "sg:postcode":"30228",
    "sg:province":"GA",
    "sg:tags":[
        "equipment",
        "industrial"
    ],
    "wof:name":"Systeng Automation Systems",
    "wof:placetype":"venue"
},
  "geometry": {"coordinates":[-84.273713,33.389165],"type":"Point"}
}