{
  "type": "Feature",
  "properties": {
    "iso:country":"US",
    "sg:address":"3901 Roswell Rd",
    "sg:city":"Marietta",
    "sg:classifiers":[
        {
            "category":"Professional",
            "type":"Services"
        }
    ],
    "sg:phone":"+1 770 499 9316",
    "sg:postcode":"30062",
    "sg:province":"GA",
    "sg:tags":[
        "establishment"
    ],
    "wof:name":"CCI Europe",
    "wof:placetype":"venue"
},
  "geometry": {"coordinates":[-84.437867,33.978017],"type":"Point"}
}