{
  "type": "Feature",
  "properties": {
    "addr:full":"2975 Angellette Dr Austell GA 30106",
    "addr:postcode":"2975;30106",
    "addr:street":"Angellette Dr",
    "iso:country":"US",
    "sg:address":"2975 Angellette Dr",
    "sg:city":"Austell",
    "sg:classifiers":[
        {
            "category":"Building & Trades",
            "subcategory":"Landscaping Services",
            "type":"Services"
        }
    ],
    "sg:phone":"+1 770 944 9090",
    "sg:postcode":"30106",
    "sg:province":"GA",
    "sg:tags":[
        "landscape"
    ],
    "wof:name":"Brown Nursery Landscaping Inc",
    "wof:placetype":"venue"
},
  "geometry": {"coordinates":[-84.637236,33.852062],"type":"Point"}
}