{
  "type": "Feature",
  "properties": {
    "addr:full":"6150 Xavier Drive SW Atlanta GA 30336",
    "addr:housenumber":"6150",
    "addr:postcode":"30336",
    "addr:street":"Xavier Drive Sw",
    "iso:country":"US",
    "sg:address":"6150 Xavier Drive SW",
    "sg:city":"Atlanta",
    "sg:classifiers":[
        {
            "category":"Building & Trades",
            "subcategory":"Construction",
            "type":"Services"
        }
    ],
    "sg:phone":"+1 404 344 8720",
    "sg:postcode":"30336",
    "sg:province":"GA",
    "sg:tags":[
        "contractor"
    ],
    "wof:name":"United Refrigeration Services",
    "wof:placetype":"venue"
},
  "geometry": {"coordinates":[-84.592787,33.724618],"type":"Point"}
}