{
  "type": "Feature",
  "properties": {
    "iso:country":"US",
    "sg:address":"1117 Jennings Dr",
    "sg:city":"Woodstock",
    "sg:classifiers":[
        {
            "category":"Building & Trades",
            "subcategory":"Construction",
            "type":"Services"
        }
    ],
    "sg:phone":"+1 678 319 0077",
    "sg:postcode":"30188",
    "sg:province":"GA",
    "sg:tags":[
        "home",
        "improvement"
    ],
    "wof:name":"Martin Home Improvements",
    "wof:placetype":"venue"
},
  "geometry": {"coordinates":[-84.384401,34.140305],"type":"Point"}
}