{
  "type": "Feature",
  "properties": {
    "iso:country":"US",
    "sg:address":"59 Lakeview Dr NE",
    "sg:city":"Atlanta",
    "sg:classifiers":[
        {
            "category":"Professional",
            "subcategory":"Business Services",
            "type":"Services"
        }
    ],
    "sg:phone":"+1 404 872 1900",
    "sg:postcode":"30317",
    "sg:province":"GA",
    "sg:tags":[
        "management",
        "organizing",
        "services-household"
    ],
    "wof:name":"Harrington Management",
    "wof:placetype":"venue"
},
  "geometry": {"coordinates":[-84.31321199999999,33.753014],"type":"Point"}
}