{
  "type": "Feature",
  "properties": {
    "addr:full":"351 State Rte 96 Bonaire GA 31005",
    "addr:housenumber":"351",
    "addr:postcode":"31005",
    "addr:street":"State Rte 96",
    "iso:country":"US",
    "sg:address":"351 State Rte 96",
    "sg:city":"Bonaire",
    "sg:classifiers":[
        {
            "category":"Organizations",
            "subcategory":"Religious Organization",
            "type":"Services"
        }
    ],
    "sg:phone":"+1 478 929 1823",
    "sg:postcode":"31005",
    "sg:province":"GA",
    "wof:name":"Calvary Baptist Church",
    "wof:placetype":"venue"
},
  "geometry": {"coordinates":[-83.641345,32.554555],"type":"Point"}
}