{
  "type": "Feature",
  "properties": {
    "iso:country":"US",
    "sg:address":"130 Ethridge Rd",
    "sg:city":"Haddock",
    "sg:classifiers":[
        {
            "category":"Professional",
            "type":"Services"
        }
    ],
    "sg:phone":"+1 478 932 5654",
    "sg:postcode":"31033",
    "sg:province":"GA",
    "wof:name":"Bubbas Bar-B-Que",
    "wof:placetype":"venue"
},
  "geometry": {"coordinates":[-83.42906600000001,33.032638],"type":"Point"}
}