{
  "type": "Feature",
  "properties": {
    "addr:full":"203 E Church St Americus GA 31709",
    "addr:housenumber":"203",
    "addr:postcode":"31709",
    "addr:street":"E Church St",
    "iso:country":"US",
    "sg:address":"203 E Church St",
    "sg:city":"Americus",
    "sg:classifiers":[
        {
            "category":"Building & Trades",
            "subcategory":"Construction",
            "type":"Services"
        }
    ],
    "sg:phone":"+1 229 928 7879",
    "sg:postcode":"31709",
    "sg:province":"GA",
    "sg:tags":[
        "house"
    ],
    "wof:name":"Bowden Upkeep",
    "wof:placetype":"venue"
},
  "geometry": {"coordinates":[-84.23065200000001,32.070312],"type":"Point"}
}