{
  "type": "Feature",
  "properties": {
    "addr:full":"120 Prospect St Alpharetta GA 30075",
    "addr:housenumber":"120",
    "addr:postcode":"30075",
    "addr:street":"Prospect St",
    "iso:country":"US",
    "sg:address":"120 Prospect St",
    "sg:city":"Alpharetta",
    "sg:classifiers":[
        {
            "category":"Health Services",
            "subcategory":"Clinic",
            "type":"Services"
        }
    ],
    "sg:phone":"+1 770 442 8664",
    "sg:postcode":"30075",
    "sg:province":"GA",
    "sg:tags":[
        "home",
        "care"
    ],
    "wof:name":"Easy Living Services Inc",
    "wof:placetype":"venue"
},
  "geometry": {"coordinates":[-84.35327700000001,34.031756],"type":"Point"}
}