{
  "type": "Feature",
  "properties": {
    "addr:full":"1701 Williams Rd Columbus GA 31904",
    "addr:housenumber":"1701",
    "addr:postcode":"31904",
    "addr:street":"Williams Rd",
    "iso:country":"US",
    "sg:address":"1701 Williams Rd",
    "sg:city":"Columbus",
    "sg:classifiers":[
        {
            "category":"Real Estate",
            "subcategory":"Real Estate Operator",
            "type":"Services"
        }
    ],
    "sg:phone":"+1 706 507 1701",
    "sg:postcode":"31904",
    "sg:province":"GA",
    "sg:tags":[
        "apartment"
    ],
    "sg:website":"http://www.greystoneproperties.net/greystone-falls-apartments.htm",
    "wof:name":"Greystone Falls Apartments",
    "wof:placetype":"venue"
},
  "geometry": {"coordinates":[-84.964775,32.569864],"type":"Point"}
}