{
  "type": "Feature",
  "properties": {
    "iso:country":"US",
    "sg:address":"1224 Moore Hwy",
    "sg:city":"Tifton",
    "sg:classifiers":[
        {
            "category":"Organizations",
            "subcategory":"Community Association",
            "type":"Services"
        }
    ],
    "sg:phone":"+1 229 382 6929",
    "sg:postcode":"31794",
    "sg:province":"GA",
    "sg:tags":[
        "military"
    ],
    "wof:name":"American Legion",
    "wof:placetype":"venue"
},
  "geometry": {"coordinates":[-83.51983300000001,31.469545],"type":"Point"}
}