{
  "type": "Feature",
  "properties": {
    "iso:country":"US",
    "sg:address":"5566 Bells Ferry Rd",
    "sg:city":"Acworth",
    "sg:classifiers":[
        {
            "category":"Personal",
            "subcategory":"Nail Salon",
            "type":"Services"
        }
    ],
    "sg:phone":"+1 770 592 9192",
    "sg:postcode":"30102",
    "sg:province":"GA",
    "wof:name":"Nail Care",
    "wof:placetype":"venue"
},
  "geometry": {"coordinates":[-84.5749,34.083445],"type":"Point"}
}