{
  "type": "Feature",
  "properties": {
    "iso:country":"US",
    "sg:address":"248 Richardson Rd",
    "sg:city":"Calhoun",
    "sg:classifiers":[
        {
            "category":"Retail",
            "subcategory":"Auto Repair",
            "type":"Services"
        }
    ],
    "sg:phone":"+1 706 629 3551",
    "sg:postcode":"30701",
    "sg:province":"GA",
    "sg:tags":[
        "general"
    ],
    "wof:name":"Best Auto Repair",
    "wof:placetype":"venue"
},
  "geometry": {"coordinates":[-84.92553599999999,34.474722],"type":"Point"}
}