{
  "type": "Feature",
  "properties": {
    "iso:country":"US",
    "sg:address":"42 State Rte 56",
    "sg:city":"Swainsboro",
    "sg:classifiers":[
        {
            "category":"Social Services",
            "type":"Services"
        }
    ],
    "sg:phone":"+1 478 237 5434",
    "sg:postcode":"30401",
    "sg:province":"GA",
    "wof:name":"Emanuel County Senior",
    "wof:placetype":"venue"
},
  "geometry": {"coordinates":[-82.33734,32.593702],"type":"Point"}
}