{
  "type": "Feature",
  "properties": {
    "iso:country":"US",
    "sg:address":"725 Gable Rd",
    "sg:city":"Albany",
    "sg:classifiers":[
        {
            "category":"Real Estate",
            "subcategory":"Real Estate Agent",
            "type":"Services"
        }
    ],
    "sg:phone":"+1 229 439 0006",
    "sg:postcode":"31763",
    "sg:province":"GA",
    "sg:tags":[
        "appraiser"
    ],
    "wof:name":"Robert F Mc Kinney",
    "wof:placetype":"venue"
},
  "geometry": {"coordinates":[-84.09644900000001,31.621632],"type":"Point"}
}