{
  "type": "Feature",
  "properties": {
    "addr:full":"750 Baconsfield Dr Macon GA 31211",
    "addr:housenumber":"750",
    "addr:postcode":"31211",
    "addr:street":"Baconsfield Dr",
    "iso:country":"US",
    "sg:address":"750 Baconsfield Dr",
    "sg:city":"Macon",
    "sg:classifiers":[
        {
            "category":"Shopping",
            "type":"Retail Goods"
        }
    ],
    "sg:phone":"+1 478 746 2777",
    "sg:postcode":"31211",
    "sg:province":"GA",
    "sg:tags":[
        "machine",
        "business"
    ],
    "wof:name":"Wilson Business Products",
    "wof:placetype":"venue"
},
  "geometry": {"coordinates":[-83.627341,32.851443],"type":"Point"}
}