{
  "type": "Feature",
  "properties": {
    "iso:country":"US",
    "sg:address":"209 Park Pl",
    "sg:city":"Woodstock",
    "sg:classifiers":[
        {
            "category":"Real Estate",
            "subcategory":"Real Estate Agent",
            "type":"Services"
        }
    ],
    "sg:phone":"+1 770 231 5224",
    "sg:postcode":"30189",
    "sg:province":"GA",
    "wof:name":"Carla Delgadoharmon Inc",
    "wof:placetype":"venue"
},
  "geometry": {"coordinates":[-84.574275,34.126849],"type":"Point"}
}