{
  "type": "Feature",
  "properties": {
    "iso:country":"US",
    "sg:address":"3801 Washington Rd",
    "sg:city":"Augusta",
    "sg:classifiers":[
        {
            "category":"Wholesale",
            "subcategory":"Medical Equipment & Supplies",
            "type":"Manufacturing & Wholesale Goods"
        },
        {
            "category":"Health Services",
            "subcategory":"Clinic",
            "type":"Services"
        }
    ],
    "sg:phone":"+1 706 210 4747",
    "sg:postcode":"30907",
    "sg:province":"GA",
    "sg:tags":[
        "physician",
        "surgeon"
    ],
    "wof:name":"Bonro Medical Inc",
    "wof:placetype":"venue"
},
  "geometry": {"coordinates":[-82.087688,33.512645],"type":"Point"}
}