{
  "type": "Feature",
  "properties": {
    "iso:country":"US",
    "sg:address":"41 River Ct SW",
    "sg:city":"Cartersville",
    "sg:classifiers":[
        {
            "category":"Retail",
            "subcategory":"Repair Shop",
            "type":"Services"
        }
    ],
    "sg:phone":"+1 770 387 0673",
    "sg:postcode":"30120",
    "sg:province":"GA",
    "sg:tags":[
        "compactors"
    ],
    "wof:name":"HEM Svc Co",
    "wof:placetype":"venue"
},
  "geometry": {"coordinates":[-84.84110800000001,34.140478],"type":"Point"}
}