{
  "type": "Feature",
  "properties": {
    "addr:full":"4719 Ashford Dunwoody Rd NE Atlanta GA 30338",
    "addr:housenumber":"4719",
    "addr:postcode":"30338",
    "addr:street":"Ashford Dunwoody Rd Ne",
    "iso:country":"US",
    "sg:address":"4719 Ashford Dunwoody Rd NE",
    "sg:city":"Atlanta",
    "sg:classifiers":[
        {
            "category":"Real Estate",
            "subcategory":"Real Estate Agent",
            "type":"Services"
        }
    ],
    "sg:phone":"+1 678 441 0024",
    "sg:postcode":"30338",
    "sg:province":"GA",
    "wof:name":"Prizm Partners",
    "wof:placetype":"venue"
},
  "geometry": {"coordinates":[-84.337535,33.932969],"type":"Point"}
}