{
  "type": "Feature",
  "properties": {
    "addr:full":"1122 Walton Way Augusta GA 30901",
    "addr:housenumber":"1122",
    "addr:postcode":"30901",
    "addr:street":"Walton Way",
    "iso:country":"US",
    "sg:address":"1122 Walton Way",
    "sg:city":"Augusta",
    "sg:classifiers":[
        {
            "category":"Autos & Motor Vehicles",
            "subcategory":"Automobile Sales",
            "type":"Retail Goods"
        }
    ],
    "sg:phone":"+1 706 724 0111",
    "sg:postcode":"30901",
    "sg:province":"GA",
    "sg:tags":[
        "car",
        "dealer"
    ],
    "sg:website":"www.johnsonmotorco.com",
    "wof:name":"Johnson Motor Co Of Ga",
    "wof:placetype":"venue"
},
  "geometry": {"coordinates":[-81.975857,33.470542],"type":"Point"}
}