{
  "type": "Feature",
  "properties": {
    "iso:country":"US",
    "sg:address":"2401 Gillionville Rd",
    "sg:city":"Albany",
    "sg:classifiers":[
        {
            "category":"Retail",
            "subcategory":"Car Wash",
            "type":"Services"
        }
    ],
    "sg:phone":"+1 229 436 7552",
    "sg:postcode":"31707",
    "sg:province":"GA",
    "sg:tags":[
        "automobile",
        "detail",
        "clean"
    ],
    "wof:name":"Clean As A Whistle",
    "wof:placetype":"venue"
},
  "geometry": {"coordinates":[-84.21029799999999,31.585821],"type":"Point"}
}