{
  "type": "Feature",
  "properties": {
    "iso:country":"US",
    "sg:address":"72 Wakefield Dr",
    "sg:city":"Newnan",
    "sg:classifiers":[
        {
            "category":"Wholesale",
            "subcategory":"Groceries",
            "type":"Manufacturing & Wholesale Goods"
        }
    ],
    "sg:phone":"+1 770 304 3838",
    "sg:postcode":"30265",
    "sg:province":"GA",
    "sg:tags":[
        "confectionery"
    ],
    "wof:name":"Sherriffs of Kingsbridge USA",
    "wof:placetype":"venue"
},
  "geometry": {"coordinates":[-84.694233,33.424319],"type":"Point"}
}