{
  "type": "Feature",
  "properties": {
    "iso:country":"US",
    "sg:address":"2200 Ranchwood Dr NE",
    "sg:city":"Atlanta",
    "sg:classifiers":[
        {
            "category":"Real Estate",
            "subcategory":"Real Estate Operator",
            "type":"Services"
        }
    ],
    "sg:phone":"+1 770 493 4434",
    "sg:postcode":"30345",
    "sg:province":"GA",
    "sg:tags":[
        "apartment",
        "complex"
    ],
    "wof:name":"Camelot At Northlake",
    "wof:placetype":"venue"
},
  "geometry": {"coordinates":[-84.251532,33.84827],"type":"Point"}
}