{
  "type": "Feature",
  "properties": {
    "addr:full":"1006 Creekmont Ct Marietta GA 30064",
    "addr:housenumber":"1006",
    "addr:postcode":"30064",
    "addr:street":"Creekmont Ct",
    "iso:country":"US",
    "sg:address":"1006 Creekmont Ct",
    "sg:city":"Marietta",
    "sg:classifiers":[
        {
            "category":"Real Estate",
            "subcategory":"Real Estate Agent",
            "type":"Services"
        }
    ],
    "sg:phone":"+1 770 861 3289",
    "sg:postcode":"30064",
    "sg:province":"GA",
    "wof:name":"Berry Appraisal Services",
    "wof:placetype":"venue"
},
  "geometry": {"coordinates":[-84.617705,33.92963],"type":"Point"}
}