{
  "type": "Feature",
  "properties": {
    "iso:country":"US",
    "sg:address":"3770 Cherie Glen Rd SW",
    "sg:city":"Snellville",
    "sg:classifiers":[
        {
            "category":"Building & Trades",
            "subcategory":"Construction",
            "type":"Services"
        }
    ],
    "sg:phone":"+1 770 978 1937",
    "sg:postcode":"30039",
    "sg:province":"GA",
    "sg:tags":[
        "house"
    ],
    "wof:name":"Affordable Advantage Home Repr",
    "wof:placetype":"venue"
},
  "geometry": {"coordinates":[-84.05708,33.83514],"type":"Point"}
}