{
  "type": "Feature",
  "properties": {
    "addr:full":"3050 Martin Luther King Jr Dr SW Atlanta GA 30311",
    "addr:housenumber":"3050",
    "addr:postcode":"30311",
    "addr:street":"Martin Luther King Jr Dr Sw",
    "iso:country":"US",
    "sg:address":"3050 Martin Luther King Jr Dr SW",
    "sg:city":"Atlanta",
    "sg:classifiers":[
        {
            "category":"Retail",
            "subcategory":"Self-service Laundry",
            "type":"Services"
        }
    ],
    "sg:phone":"+1 404 699 5606",
    "sg:postcode":"30311",
    "sg:province":"GA",
    "sg:tags":[
        "coin"
    ],
    "wof:name":"Ben & Trang Laundromat",
    "wof:placetype":"venue"
},
  "geometry": {"coordinates":[-84.48341499999999,33.754199],"type":"Point"}
}