{
  "type": "Feature",
  "properties": {
    "addr:full":"2970 Peachtree Park Dr NE Atlanta GA 30309",
    "addr:housenumber":"2970",
    "addr:postcode":"30309",
    "addr:street":"Peachtree Park Dr Ne",
    "iso:country":"US",
    "sg:address":"2970 Peachtree Park Dr NE",
    "sg:city":"Atlanta",
    "sg:classifiers":[
        {
            "category":"Banks & Credit Unions",
            "subcategory":"Investment Brokerage",
            "type":"Services"
        }
    ],
    "sg:phone":"+1 404 467 9592",
    "sg:postcode":"30309",
    "sg:province":"GA",
    "sg:tags":[
        "advisory"
    ],
    "wof:name":"Huntington Investments",
    "wof:placetype":"venue"
},
  "geometry": {"coordinates":[-84.390252,33.812282],"type":"Point"}
}