{
  "type": "Feature",
  "properties": {
    "addr:full":"1425 Turner McCall Blvd Rome GA 30161",
    "addr:housenumber":"1425",
    "addr:postcode":"ga 30161",
    "addr:street":"Turner Mccall Blvd",
    "iso:country":"US",
    "sg:address":"1425 Turner McCall Blvd",
    "sg:city":"Rome",
    "sg:phone":"+1 706 291 8700",
    "sg:postcode":"30161",
    "sg:province":"GA",
    "sg:tags":[
        "oil"
    ],
    "wof:name":"D & D Oil Inc",
    "wof:placetype":"venue"
},
  "geometry": {"coordinates":[-85.16170200000001,34.247257],"type":"Point"}
}