{
  "type": "Feature",
  "properties": {
    "addr:full":"1915 Old Dixie Hwy White Oak GA 31568",
    "addr:housenumber":"1915",
    "addr:postcode":"31568",
    "addr:street":"Old Dixie Hwy",
    "iso:country":"US",
    "sg:address":"1915 Old Dixie Hwy",
    "sg:city":"White Oak",
    "sg:classifiers":[
        {
            "category":"Government",
            "subcategory":"Post Office",
            "type":"Public Place"
        }
    ],
    "sg:phone":"+1 912 000 1111",
    "sg:postcode":"31568",
    "sg:province":"GA",
    "wof:name":"US Post Office",
    "wof:placetype":"venue"
},
  "geometry": {"coordinates":[-81.736273,31.053195],"type":"Point"}
}