{
  "type": "Feature",
  "properties": {
    "iso:country":"US",
    "sg:address":"1483 High Meadow Dr",
    "sg:city":"Stone Mountain",
    "sg:classifiers":[
        {
            "category":"Building & Trades",
            "subcategory":"Plumbing",
            "type":"Services"
        }
    ],
    "sg:phone":"+1 404 286 8874",
    "sg:postcode":"30083",
    "sg:province":"GA",
    "sg:tags":[
        "contractor"
    ],
    "wof:name":"Leonards Hvac Service",
    "wof:placetype":"venue"
},
  "geometry": {"coordinates":[-84.21041700000001,33.751362],"type":"Point"}
}