{
  "type": "Feature",
  "properties": {
    "addr:full":"5530 Old National Hwy Atlanta GA 30349",
    "addr:housenumber":"5530",
    "addr:postcode":"30349",
    "addr:street":"Old National Hwy",
    "iso:country":"US",
    "sg:address":"5530 Old National Hwy",
    "sg:city":"Atlanta",
    "sg:classifiers":[
        {
            "category":"Autos & Motor Vehicles",
            "subcategory":"Automobile Sales",
            "type":"Retail Goods"
        }
    ],
    "sg:phone":"+1 404 761 2702",
    "sg:postcode":"30349",
    "sg:province":"GA",
    "sg:tags":[
        "car",
        "used",
        "dealer"
    ],
    "wof:name":"Valu Auto Inc",
    "wof:placetype":"venue"
},
  "geometry": {"coordinates":[-84.47165800000001,33.605207],"type":"Point"}
}