{
  "type": "Feature",
  "properties": {
    "iso:country":"US",
    "sg:address":"909 W Roosevelt Ave",
    "sg:city":"Albany",
    "sg:classifiers":[
        {
            "category":"Wholesale",
            "subcategory":"Home Furnishings",
            "type":"Manufacturing & Wholesale Goods"
        }
    ],
    "sg:phone":"+1 229 435 0887",
    "sg:postcode":"31701",
    "sg:province":"GA",
    "wof:name":"Southern Wholesale Flooring Co",
    "wof:placetype":"venue"
},
  "geometry": {"coordinates":[-84.168644,31.581531],"type":"Point"}
}