{
  "type": "Feature",
  "properties": {
    "addr:full":"530 Hampton Rd Mcdonough GA 30253",
    "addr:housenumber":"530",
    "addr:postcode":"30253",
    "addr:street":"Hampton Rd",
    "iso:country":"US",
    "sg:address":"530 Hampton Rd",
    "sg:city":"Mcdonough",
    "sg:classifiers":[
        {
            "category":"Banks & Credit Unions",
            "subcategory":"Bank",
            "type":"Services"
        }
    ],
    "sg:phone":"+1 770 957 0408",
    "sg:postcode":"30253",
    "sg:province":"GA",
    "wof:name":"Peachtree National Bank",
    "wof:placetype":"venue"
},
  "geometry": {"coordinates":[-84.170214,33.433622],"type":"Point"}
}