{
  "type": "Feature",
  "properties": {
    "iso:country":"US",
    "sg:address":"1357 Elders Mill Rd",
    "sg:city":"Senoia",
    "sg:classifiers":[
        {
            "category":"Professional",
            "type":"Services"
        }
    ],
    "sg:phone":"+1 770 599 1853",
    "sg:postcode":"30276",
    "sg:province":"GA",
    "wof:name":"Denene M Carpenter Inc",
    "wof:placetype":"venue"
},
  "geometry": {"coordinates":[-84.623249,33.288577],"type":"Point"}
}