{
  "type": "Feature",
  "properties": {
    "iso:country":"US",
    "sg:address":"1959 Mallard Ave",
    "sg:city":"Macon",
    "sg:classifiers":[
        {
            "category":"Building & Trades",
            "subcategory":"Construction",
            "type":"Services"
        }
    ],
    "sg:phone":"+1 478 784 8215",
    "sg:postcode":"31204",
    "sg:province":"GA",
    "sg:tags":[
        "concrete",
        "finishing"
    ],
    "wof:name":"Dailey Construction",
    "wof:placetype":"venue"
},
  "geometry": {"coordinates":[-83.681071,32.817681],"type":"Point"}
}