{
  "type": "Feature",
  "properties": {
    "iso:country":"US",
    "sg:address":"132 Paul Ln",
    "sg:city":"Crawford",
    "sg:classifiers":[
        {
            "category":"Home & Garden",
            "subcategory":"Home Furnishings",
            "type":"Retail Goods"
        }
    ],
    "sg:phone":"+1 706 743 5801",
    "sg:postcode":"30630",
    "sg:province":"GA",
    "sg:tags":[
        "cover",
        "slip"
    ],
    "wof:name":"Jeans Custom Slip Covers",
    "wof:placetype":"venue"
},
  "geometry": {"coordinates":[-83.118737,33.949335],"type":"Point"}
}