{
  "type": "Feature",
  "properties": {
    "addr:full":"4250 Perimeter Park S # 105 Atlanta GA 30341",
    "addr:housenumber":"4250",
    "addr:postcode":"30341",
    "addr:street":"Perimeter Park S # 105",
    "iso:country":"US",
    "sg:address":"4250 Perimeter Park S # 105",
    "sg:city":"Atlanta",
    "sg:classifiers":[
        {
            "category":"Real Estate",
            "subcategory":"Real Estate Services",
            "type":"Services"
        },
        {
            "category":"Industrial Area",
            "type":"Public Place"
        }
    ],
    "sg:phone":"+1 770 451 3280",
    "sg:postcode":"30341",
    "sg:province":"GA",
    "sg:tags":[
        "development",
        "commercial"
    ],
    "wof:name":"Kge",
    "wof:placetype":"venue"
},
  "geometry": {"coordinates":[-84.296965,33.915895],"type":"Point"}
}