{
  "type": "Feature",
  "properties": {
    "addr:full":"92 Nancy Ln Flintstone GA 30725",
    "addr:housenumber":"92",
    "addr:postcode":"30725",
    "addr:street":"Nancy Ln",
    "iso:country":"US",
    "sg:address":"92 Nancy Ln",
    "sg:city":"Flintstone",
    "sg:classifiers":[
        {
            "category":"Professional",
            "subcategory":"Accounting & Tax Preparation",
            "type":"Services"
        }
    ],
    "sg:phone":"+1 706 820 0777",
    "sg:postcode":"30725",
    "sg:province":"GA",
    "wof:name":"Stephens Bookkeeping Service",
    "wof:placetype":"venue"
},
  "geometry": {"coordinates":[-85.35144,34.924968],"type":"Point"}
}