{
  "type": "Feature",
  "properties": {
    "addr:full":"4001 Pio Nono Ave Macon GA 31206",
    "addr:housenumber":"4001",
    "addr:postcode":"31206",
    "addr:street":"Pio Nono Ave",
    "iso:country":"US",
    "sg:address":"4001 Pio Nono Ave",
    "sg:city":"Macon",
    "sg:classifiers":[
        {
            "category":"Restaurant",
            "type":"Food & Drink"
        }
    ],
    "sg:phone":"+1 478 781 2685",
    "sg:postcode":"31206",
    "sg:province":"GA",
    "sg:tags":[
        "eating"
    ],
    "wof:name":"Janets Home Cooked Meals",
    "wof:placetype":"venue"
},
  "geometry": {"coordinates":[-83.668643,32.791421],"type":"Point"}
}