{
  "type": "Feature",
  "properties": {
    "addr:full":"3118 Sandhurst Dr Woodstock GA 30189",
    "addr:housenumber":"3118",
    "addr:postcode":"30189",
    "addr:street":"Sandhurst Dr",
    "iso:country":"US",
    "sg:address":"3118 Sandhurst Dr",
    "sg:city":"Woodstock",
    "sg:classifiers":[
        {
            "category":"Wholesale",
            "subcategory":"Apparel",
            "type":"Manufacturing & Wholesale Goods"
        }
    ],
    "sg:phone":"+1 770 926 8188",
    "sg:postcode":"30189",
    "sg:province":"GA",
    "sg:tags":[
        "piece",
        "notion",
        "gift",
        "or"
    ],
    "wof:name":"Christina Collection",
    "wof:placetype":"venue"
},
  "geometry": {"coordinates":[-84.554284,34.141614],"type":"Point"}
}