{
  "type": "Feature",
  "properties": {
    "addr:full":"3037 White Oak Mews Decatur GA 30034",
    "addr:housenumber":"3037",
    "addr:postcode":"30034",
    "addr:street":"White Oak Mews",
    "iso:country":"US",
    "sg:address":"3037 White Oak Mews",
    "sg:city":"Decatur",
    "sg:classifiers":[
        {
            "category":"Professional",
            "subcategory":"Business Services",
            "type":"Services"
        }
    ],
    "sg:phone":"+1 404 244 9939",
    "sg:postcode":"30034",
    "sg:province":"GA",
    "wof:name":"Darrisaw Enterprises Inc",
    "wof:placetype":"venue"
},
  "geometry": {"coordinates":[-84.265182,33.680979],"type":"Point"}
}