{
  "type": "Feature",
  "properties": {
    "iso:country":"US",
    "sg:address":"1421 Gateview Way",
    "sg:city":"Marietta",
    "sg:classifiers":[
        {
            "category":"Professional",
            "subcategory":"Business Services",
            "type":"Services"
        }
    ],
    "sg:phone":"+1 770 565 7980",
    "sg:postcode":"30062",
    "sg:province":"GA",
    "wof:name":"Tunis Enterprises Inc",
    "wof:placetype":"venue"
},
  "geometry": {"coordinates":[-84.512063,33.987027],"type":"Point"}
}