{
  "type": "Feature",
  "properties": {
    "addr:full":"2451 Cumberland Pkwy Atlanta GA 30339",
    "addr:housenumber":"2451",
    "addr:postcode":"30339",
    "addr:street":"Cumberland Pkwy",
    "iso:country":"US",
    "sg:address":"2451 Cumberland Pkwy",
    "sg:city":"Atlanta",
    "sg:classifiers":[
        {
            "category":"Professional",
            "subcategory":"Advertising",
            "type":"Services"
        },
        {
            "category":"Communications",
            "type":"Services"
        }
    ],
    "sg:phone":"+1 404 418 6434",
    "sg:postcode":"30339",
    "sg:province":"GA",
    "sg:tags":[
        "marketing",
        "design",
        "web"
    ],
    "sg:website":"www.triumphwebsolutions.com",
    "wof:name":"Triumph Web Solutions",
    "wof:placetype":"venue"
},
  "geometry": {"coordinates":[-84.477503,33.862505],"type":"Point"}
}