{
  "type": "Feature",
  "properties": {
    "addr:full":"3114 Oakey Mountain Rd Clarkesville GA 30523",
    "addr:housenumber":"3114",
    "addr:postcode":"30523",
    "addr:street":"Oakey Mountain Rd",
    "iso:country":"US",
    "sg:address":"3114 Oakey Mountain Rd",
    "sg:city":"Clarkesville",
    "sg:classifiers":[
        {
            "category":"Professional",
            "type":"Services"
        }
    ],
    "sg:phone":"+1 706 947 3119",
    "sg:postcode":"30523",
    "sg:province":"GA",
    "wof:name":"Ezra Barron",
    "wof:placetype":"venue"
},
  "geometry": {"coordinates":[-83.530247,34.713837],"type":"Point"}
}