{
  "type": "Feature",
  "properties": {
    "iso:country":"US",
    "sg:address":"2304 Smyrna Church Rd",
    "sg:city":"Chatsworth",
    "sg:classifiers":[
        {
            "category":"Professional",
            "subcategory":"Management & Consulting",
            "type":"Services"
        }
    ],
    "sg:phone":"+1 706 422 8553",
    "sg:postcode":"30705",
    "sg:province":"GA",
    "sg:tags":[
        "business"
    ],
    "wof:name":"American Tower Corp",
    "wof:placetype":"venue"
},
  "geometry": {"coordinates":[-84.7891,34.729455],"type":"Point"}
}