{
  "type": "Feature",
  "properties": {
    "iso:country":"US",
    "sg:address":"1849 Cheshire Bridge Rd",
    "sg:city":"Atlanta",
    "sg:classifiers":[
        {
            "category":"Professional",
            "type":"Services"
        }
    ],
    "sg:phone":"+1 404 876 4511",
    "sg:postcode":"30324",
    "sg:province":"GA",
    "sg:tags":[
        "establishment"
    ],
    "wof:name":"DUI Car Interlock",
    "wof:placetype":"venue"
},
  "geometry": {"coordinates":[-84.361643,33.8093],"type":"Point"}
}