{
  "type": "Feature",
  "properties": {
    "addr:full":"1810 E Walnut Ave Dalton GA 30721",
    "addr:housenumber":"1810",
    "addr:postcode":"30721",
    "addr:street":"E Walnut Ave",
    "iso:country":"US",
    "sg:address":"1810 E Walnut Ave",
    "sg:city":"Dalton",
    "sg:classifiers":[
        {
            "category":"Shopping",
            "type":"Retail Goods"
        }
    ],
    "sg:phone":"+1 706 275 8085",
    "sg:postcode":"30721",
    "sg:province":"GA",
    "sg:tags":[
        "pet",
        "shop"
    ],
    "wof:name":"H2o Pets",
    "wof:placetype":"venue"
},
  "geometry": {"coordinates":[-84.937579,34.761014],"type":"Point"}
}