{
  "type": "Feature",
  "properties": {
    "iso:country":"US",
    "sg:address":"987 Gaines School Rd",
    "sg:city":"Athens",
    "sg:classifiers":[
        {
            "category":"Personal",
            "type":"Services"
        },
        {
            "category":"Personal",
            "subcategory":"Beauty Salon",
            "type":"Services"
        }
    ],
    "sg:phone":"+1 706 543 5862",
    "sg:postcode":"30605",
    "sg:province":"GA",
    "sg:tags":[
        "shop",
        "electrolysis"
    ],
    "wof:name":"Buchanan's Electrolysis",
    "wof:placetype":"venue"
},
  "geometry": {"coordinates":[-83.337159,33.927828],"type":"Point"}
}