{
  "type": "Feature",
  "properties": {
    "addr:full":"2490 Waterford Park Dr Lawrenceville GA 30044",
    "addr:housenumber":"2490",
    "addr:postcode":"30044",
    "addr:street":"Waterford Park Dr",
    "iso:country":"US",
    "sg:address":"2490 Waterford Park Dr",
    "sg:city":"Lawrenceville",
    "sg:classifiers":[
        {
            "category":"Building & Trades",
            "subcategory":"Cleaning & Sanitation",
            "type":"Services"
        }
    ],
    "sg:phone":"+1 770 367 2534",
    "sg:postcode":"30044",
    "sg:province":"GA",
    "sg:tags":[
        "maintenance"
    ],
    "wof:name":"Barraza Home Cleaning",
    "wof:placetype":"venue"
},
  "geometry": {"coordinates":[-84.07639399999999,33.946787],"type":"Point"}
}