{
  "type": "Feature",
  "properties": {
    "iso:country":"US",
    "sg:address":"129 Salt Creek Rd",
    "sg:city":"Savannah",
    "sg:classifiers":[
        {
            "category":"Building & Trades",
            "subcategory":"Electrical",
            "type":"Services"
        }
    ],
    "sg:phone":"+1 912 443 0119",
    "sg:postcode":"31405",
    "sg:province":"GA",
    "sg:tags":[
        "electric",
        "contractor"
    ],
    "wof:name":"James Dyal Electric Co",
    "wof:placetype":"venue"
},
  "geometry": {"coordinates":[-81.197895,32.045764],"type":"Point"}
}