{
  "type": "Feature",
  "properties": {
    "addr:full":"3300 Buckeye Rd Ste 840 Atlanta GA 30341",
    "addr:housenumber":"3300",
    "addr:postcode":"30341",
    "addr:street":"Buckeye Rd Ste 840",
    "iso:country":"US",
    "sg:address":"3300 Buckeye Rd Ste 840",
    "sg:city":"Atlanta",
    "sg:classifiers":[
        {
            "category":"Professional",
            "subcategory":"Management & Consulting",
            "type":"Services"
        }
    ],
    "sg:phone":"+1 404 932 2111",
    "sg:postcode":"30341",
    "sg:province":"GA",
    "sg:tags":[
        "consultant"
    ],
    "wof:name":"Doctor Incorporation Inc",
    "wof:placetype":"venue"
},
  "geometry": {"coordinates":[-84.25765199999999,33.884449],"type":"Point"}
}