{
  "type": "Feature",
  "properties": {
    "addr:full":"306 3rd St N Cordele GA 31015",
    "addr:housenumber":"306",
    "addr:postcode":"31015",
    "addr:street":"3Rd St N",
    "iso:country":"US",
    "sg:address":"306 3rd St N",
    "sg:city":"Cordele",
    "sg:classifiers":[
        {
            "category":"Professional",
            "type":"Services"
        }
    ],
    "sg:phone":"+1 229 273 7140",
    "sg:postcode":"31015",
    "sg:province":"GA",
    "wof:name":"Sammie McGill",
    "wof:placetype":"venue"
},
  "geometry": {"coordinates":[-83.776414,31.971591],"type":"Point"}
}