{
  "type": "Feature",
  "properties": {
    "iso:country":"US",
    "sg:address":"101 Andrew Dr # 200",
    "sg:city":"Stockbridge",
    "sg:classifiers":[
        {
            "category":"Shopping",
            "subcategory":"Computers & Home Electronics",
            "type":"Retail Goods"
        }
    ],
    "sg:phone":"+1 770 507 2821",
    "sg:postcode":"30281",
    "sg:province":"GA",
    "wof:name":"P A C Audio Inc",
    "wof:placetype":"venue"
},
  "geometry": {"coordinates":[-84.24050099999999,33.499901],"type":"Point"}
}