{
  "type": "Feature",
  "properties": {
    "iso:country":"US",
    "sg:address":"1510 Clifton Rd NE",
    "sg:city":"Atlanta",
    "sg:classifiers":[
        {
            "category":"Health Services",
            "subcategory":"Doctor",
            "type":"Services"
        },
        {
            "category":"Education",
            "subcategory":"School",
            "type":"Public Place"
        },
        {
            "category":"Education",
            "subcategory":"University",
            "type":"Public Place"
        }
    ],
    "sg:phone":"+1 404 616 4459",
    "sg:postcode":"30322",
    "sg:province":"GA",
    "sg:tags":[
        "physician",
        "gynecology",
        "surgeons",
        "college",
        "obstetrics"
    ],
    "wof:name":"Emory University Medicine School of Gyneclgy & Obstetrics Neurology",
    "wof:placetype":"venue"
},
  "geometry": {"coordinates":[-84.322243,33.797029],"type":"Point"}
}