{
  "type": "Feature",
  "properties": {
    "addr:full":"4803 S Main St Acworth GA 30101",
    "addr:housenumber":"4803",
    "addr:postcode":"30101",
    "addr:street":"S Main St",
    "iso:country":"US",
    "sg:address":"4803 S Main St",
    "sg:city":"Acworth",
    "sg:classifiers":[
        {
            "category":"Health Services",
            "subcategory":"Doctor",
            "type":"Services"
        }
    ],
    "sg:phone":"+1 770 529 7585",
    "sg:postcode":"30101",
    "sg:province":"GA",
    "sg:tags":[
        "medical"
    ],
    "wof:name":"Nickell Family Chiropractic",
    "wof:placetype":"venue"
},
  "geometry": {"coordinates":[-84.675003,34.0649],"type":"Point"}
}