{
  "type": "Feature",
  "properties": {
    "iso:country":"US",
    "sg:address":"9700 Medlock Bridge Rd",
    "sg:city":"Duluth",
    "sg:classifiers":[
        {
            "category":"Personal",
            "type":"Services"
        }
    ],
    "sg:phone":"+1 678 473 7766",
    "sg:postcode":"30097",
    "sg:province":"GA",
    "sg:tags":[
        "a",
        "specializing",
        "salon",
        "operates",
        "as",
        "facial",
        "an",
        "massage"
    ],
    "wof:name":"Spa Degas Inc",
    "wof:placetype":"venue"
},
  "geometry": {"coordinates":[-84.188996,34.024052],"type":"Point"}
}