{
  "type": "Feature",
  "properties": {
    "iso:country":"US",
    "sg:address":"2390 Murphy Blvd",
    "sg:city":"Gainesville",
    "sg:classifiers":[
        {
            "category":"Manufacturing",
            "subcategory":"Rubber & Plastics",
            "type":"Manufacturing & Wholesale Goods"
        },
        {
            "category":"Manufacturing",
            "subcategory":"Printing",
            "type":"Manufacturing & Wholesale Goods"
        }
    ],
    "sg:phone":"+1 770 534 2200",
    "sg:postcode":"30504",
    "sg:province":"GA",
    "sg:tags":[
        "product",
        "commercial"
    ],
    "sg:website":"www.psi-ga.com",
    "wof:name":"Packaging Specialties of GA",
    "wof:placetype":"venue"
},
  "geometry": {"coordinates":[-83.85499,34.273392],"type":"Point"}
}