{
  "type": "Feature",
  "properties": {
    "addr:full":"4900 Martha Berry Hwy Rome GA 30165",
    "addr:housenumber":"4900",
    "addr:postcode":"ga 30165",
    "addr:street":"Martha Berry Hwy",
    "iso:country":"US",
    "sg:address":"4900 Martha Berry Hwy",
    "sg:city":"Rome",
    "sg:classifiers":[
        {
            "category":"Organizations",
            "subcategory":"Religious Organization",
            "type":"Services"
        }
    ],
    "sg:phone":"+1 706 292 9712",
    "sg:postcode":"30165",
    "sg:province":"GA",
    "sg:tags":[
        "church"
    ],
    "wof:name":"Mt Berry United Methodist",
    "wof:placetype":"venue"
},
  "geometry": {"coordinates":[-85.17244700000001,34.361392],"type":"Point"}
}