{
  "type": "Feature",
  "properties": {
    "iso:country":"US",
    "sg:address":"460 Rock Creek Dr",
    "sg:city":"Chatsworth",
    "sg:classifiers":[
        {
            "category":"Autos & Motor Vehicles",
            "subcategory":"Auto Supplies",
            "type":"Retail Goods"
        }
    ],
    "sg:phone":"+1 706 517 3356",
    "sg:postcode":"30705",
    "sg:province":"GA",
    "wof:name":"High Country Tires",
    "wof:placetype":"venue"
},
  "geometry": {"coordinates":[-84.73441099999999,34.689745],"type":"Point"}
}