{
  "type": "Feature",
  "properties": {
    "iso:country":"US",
    "sg:address":"501 Roberts Court",
    "sg:city":"Kennesaw",
    "sg:classifiers":[
        {
            "category":"Restaurant",
            "type":"Food & Drink"
        }
    ],
    "sg:phone":"+1 678 921 2493",
    "sg:postcode":"30144",
    "sg:province":"GA",
    "sg:website":"www.goldencrustbakery.com",
    "wof:name":"Golden Krust Caribbean Bakery",
    "wof:placetype":"venue"
},
  "geometry": {"coordinates":[-84.564688,34.010445],"type":"Point"}
}