{
  "type": "Feature",
  "properties": {
    "iso:country":"US",
    "sg:address":"202 Canton Rd",
    "sg:city":"Cumming",
    "sg:classifiers":[
        {
            "category":"Real Estate",
            "subcategory":"Real Estate Agent",
            "type":"Services"
        },
        {
            "category":"Professional",
            "subcategory":"Computer Services",
            "type":"Services"
        }
    ],
    "sg:phone":"+1 770 888 3311",
    "sg:postcode":"30040",
    "sg:province":"GA",
    "sg:tags":[
        "desk",
        "design",
        "system",
        "space"
    ],
    "wof:name":"Signet Key Technologies",
    "wof:placetype":"venue"
},
  "geometry": {"coordinates":[-84.143653,34.210011],"type":"Point"}
}