{
  "type": "Feature",
  "properties": {
    "iso:country":"US",
    "sg:address":"3518 Clarkston Industrial Blvd",
    "sg:city":"Clarkston",
    "sg:classifiers":[
        {
            "category":"Building & Trades",
            "subcategory":"Locksmith",
            "type":"Services"
        }
    ],
    "sg:phone":"+1 678 965 3672",
    "sg:postcode":"30021",
    "sg:province":"GA",
    "sg:tags":[
        "key"
    ],
    "wof:name":"1 Chance 1 Locksmith",
    "wof:placetype":"venue"
},
  "geometry": {"coordinates":[-84.244955,33.817707],"type":"Point"}
}