{
  "type": "Feature",
  "properties": {
    "iso:country":"US",
    "sg:address":"1640 Roper Hill Rd",
    "sg:city":"Gainesville",
    "sg:classifiers":[
        {
            "category":"Real Estate",
            "subcategory":"Real Estate Agent",
            "type":"Services"
        }
    ],
    "sg:phone":"+1 770 536 7749",
    "sg:postcode":"30501",
    "sg:province":"GA",
    "sg:tags":[
        "apartment",
        "management"
    ],
    "wof:name":"Ridgecrest Apartments",
    "wof:placetype":"venue"
},
  "geometry": {"coordinates":[-83.815541,34.327168],"type":"Point"}
}