{
  "type": "Feature",
  "properties": {
    "addr:full":"54 Centerport Dr White GA 30184",
    "addr:housenumber":"54",
    "addr:postcode":"30184",
    "addr:street":"Centerport Dr",
    "iso:country":"US",
    "sg:address":"54 Centerport Dr",
    "sg:city":"White",
    "sg:classifiers":[
        {
            "category":"Building & Trades",
            "subcategory":"Construction",
            "type":"Services"
        }
    ],
    "sg:phone":"+1 404 925 3775",
    "sg:postcode":"30184",
    "sg:province":"GA",
    "sg:tags":[
        "commercial",
        "painting"
    ],
    "wof:name":"Shellhorse Commercial Finishes",
    "wof:placetype":"venue"
},
  "geometry": {"coordinates":[-84.741083,34.273248],"type":"Point"}
}