{
  "type": "Feature",
  "properties": {
    "addr:full":"1321 Sylvester Dr Moultrie GA 31768",
    "addr:housenumber":"1321",
    "addr:postcode":"31768",
    "addr:street":"Sylvester Dr",
    "iso:country":"US",
    "sg:address":"1321 Sylvester Dr",
    "sg:city":"Moultrie",
    "sg:classifiers":[
        {
            "category":"Wholesale",
            "subcategory":"Machinery & Supplies",
            "type":"Manufacturing & Wholesale Goods"
        }
    ],
    "sg:phone":"+1 229 985 7792",
    "sg:postcode":"31768",
    "sg:province":"GA",
    "sg:tags":[
        "janitor"
    ],
    "wof:name":"Moultrie Distributors",
    "wof:placetype":"venue"
},
  "geometry": {"coordinates":[-83.793661,31.20226],"type":"Point"}
}