{
  "type": "Feature",
  "properties": {
    "iso:country":"US",
    "sg:address":"3085 Deans Bridge Rd",
    "sg:city":"Augusta",
    "sg:classifiers":[
        {
            "category":"Restaurant",
            "type":"Food & Drink"
        }
    ],
    "sg:menulink":"http://www.allmenus.com/ga/augusta/189972-kfc---kentucky-fried-chicken/menu/",
    "sg:phone":"+1 404 793 1943",
    "sg:postcode":"30906",
    "sg:province":"GA",
    "sg:tags":[
        "american",
        "chicken"
    ],
    "wof:name":"KFC - Kentucky Fried Chicken",
    "wof:placetype":"venue"
},
  "geometry": {"coordinates":[-82.0513,33.426888],"type":"Point"}
}