{
  "type": "Feature",
  "properties": {
    "addr:full":"2215 Gillionville Rd Albany GA 31707",
    "addr:housenumber":"2215",
    "addr:postcode":"31707",
    "addr:street":"Gillionville Rd",
    "iso:country":"US",
    "sg:address":"2215 Gillionville Rd",
    "sg:city":"Albany",
    "sg:classifiers":[
        {
            "category":"Home & Garden",
            "subcategory":"Carpets & Floor Coverings",
            "type":"Retail Goods"
        }
    ],
    "sg:phone":"+1 229 432 6767",
    "sg:postcode":"31707",
    "sg:province":"GA",
    "sg:tags":[
        "tile",
        "carpeting"
    ],
    "wof:name":"Turnipseed Carpet Service",
    "wof:placetype":"venue"
},
  "geometry": {"coordinates":[-84.20453999999999,31.584226],"type":"Point"}
}