{
  "type": "Feature",
  "properties": {
    "addr:full":"2148 Rockhaven Cir Decatur GA 30032",
    "addr:housenumber":"2148",
    "addr:postcode":"30032",
    "addr:street":"Rockhaven Cir",
    "iso:country":"US",
    "sg:address":"2148 Rockhaven Cir",
    "sg:city":"Decatur",
    "sg:classifiers":[
        {
            "category":"Building & Trades",
            "subcategory":"Construction",
            "type":"Services"
        }
    ],
    "sg:phone":"+1 404 277 0775",
    "sg:postcode":"30032",
    "sg:province":"GA",
    "sg:tags":[
        "repairing",
        "remodeling",
        "contractor"
    ],
    "wof:name":"Repairs & Remodeling",
    "wof:placetype":"venue"
},
  "geometry": {"coordinates":[-84.302092,33.7308],"type":"Point"}
}