{
  "type": "Feature",
  "properties": {
    "addr:full":"75 5th St Atlanta GA 30344",
    "addr:housenumber":"75",
    "addr:postcode":"30344",
    "addr:street":"5Th St",
    "iso:country":"US",
    "sg:address":"75 5th St",
    "sg:city":"Atlanta",
    "sg:classifiers":[
        {
            "category":"Banks & Credit Unions",
            "subcategory":"Bank",
            "type":"Services"
        }
    ],
    "sg:phone":"+1 404 495 6645",
    "sg:postcode":"30344",
    "sg:province":"GA",
    "sg:tags":[
        "loan",
        "real estate"
    ],
    "wof:name":"RBC Mortgage Co",
    "wof:placetype":"venue"
},
  "geometry": {"coordinates":[-84.428814,33.677038],"type":"Point"}
}