{
  "type": "Feature",
  "properties": {
    "iso:country":"US",
    "sg:address":"289 Salem Glen Way",
    "sg:city":"Conyers",
    "sg:classifiers":[
        {
            "category":"Banks & Credit Unions",
            "subcategory":"Financial Services",
            "type":"Services"
        }
    ],
    "sg:phone":"+1 404 454 0510",
    "sg:postcode":"30013",
    "sg:province":"GA",
    "sg:tags":[
        "trust",
        "investment",
        "real estate"
    ],
    "wof:name":"Entheo Enterprises Inc",
    "wof:placetype":"venue"
},
  "geometry": {"coordinates":[-83.966776,33.599341],"type":"Point"}
}