{
  "type": "Feature",
  "properties": {
    "iso:country":"US",
    "sg:address":"115 W Jackson St",
    "sg:city":"Dublin",
    "sg:classifiers":[
        {
            "category":"Shopping",
            "subcategory":"Clothing, Apparel, & Fashions",
            "type":"Retail Goods"
        }
    ],
    "sg:phone":"+1 478 272 8247",
    "sg:postcode":"31021",
    "sg:province":"GA",
    "sg:tags":[
        "wig",
        "jewelry"
    ],
    "wof:name":"Esquire Wig Fashions",
    "wof:placetype":"venue"
},
  "geometry": {"coordinates":[-82.904735,32.539944],"type":"Point"}
}