{
  "type": "Feature",
  "properties": {
    "iso:country":"US",
    "sg:address":"8330 Fields Ford Rd",
    "sg:city":"Gainesville",
    "sg:classifiers":[
        {
            "category":"Professional",
            "subcategory":"Business Services",
            "type":"Services"
        }
    ],
    "sg:phone":"+1 678 947 5546",
    "sg:postcode":"30506",
    "sg:province":"GA",
    "sg:tags":[
        "interior",
        "decorating",
        "design",
        "consulting"
    ],
    "wof:name":"Ideas In Decorating",
    "wof:placetype":"venue"
},
  "geometry": {"coordinates":[-83.95339199999999,34.297785],"type":"Point"}
}