{
  "type": "Feature",
  "properties": {
    "iso:country":"US",
    "sg:address":"37 Ridgeview Dr",
    "sg:city":"Lagrange",
    "sg:classifiers":[
        {
            "category":"Building & Trades",
            "subcategory":"Construction",
            "type":"Services"
        }
    ],
    "sg:phone":"+1 706 884 2724",
    "sg:postcode":"30241",
    "sg:province":"GA",
    "sg:tags":[
        "general",
        "contractor"
    ],
    "wof:name":"H & H Builders General Contr",
    "wof:placetype":"venue"
},
  "geometry": {"coordinates":[-84.98369,33.081687],"type":"Point"}
}