{
  "type": "Feature",
  "properties": {
    "iso:country":"US",
    "sg:address":"1601 Berkeley Ln NE",
    "sg:city":"Atlanta",
    "sg:classifiers":[
        {
            "category":"Professional",
            "subcategory":"Lawyer & Legal Services",
            "type":"Services"
        }
    ],
    "sg:phone":"+1 404 634 4993",
    "sg:postcode":"30329",
    "sg:province":"GA",
    "sg:website":"www.worldboundaries.com",
    "wof:name":"Robillard Walter G Atty",
    "wof:placetype":"venue"
},
  "geometry": {"coordinates":[-84.31157899999999,33.828173],"type":"Point"}
}