{
  "type": "Feature",
  "properties": {
    "addr:full":"3306 Perrington Pointe Marietta GA 30066",
    "addr:housenumber":"3306",
    "addr:postcode":"30066",
    "addr:street":"Perrington Pointe",
    "iso:country":"US",
    "sg:address":"3306 Perrington Pointe",
    "sg:city":"Marietta",
    "sg:classifiers":[
        {
            "category":"Utilities",
            "subcategory":"Cable",
            "type":"Services"
        }
    ],
    "sg:phone":"+1 770 321 0133",
    "sg:postcode":"30066",
    "sg:province":"GA",
    "sg:tags":[
        "tv",
        "design",
        "mapping",
        "optic"
    ],
    "wof:name":"Lee Communications Inc",
    "wof:placetype":"venue"
},
  "geometry": {"coordinates":[-84.472937,34.036074],"type":"Point"}
}