{
  "type": "Feature",
  "properties": {
    "iso:country":"US",
    "sg:address":"238B W Magnolia Ave",
    "sg:city":"Savannah",
    "sg:classifiers":[
        {
            "category":"Building & Trades",
            "subcategory":"Construction",
            "type":"Services"
        }
    ],
    "sg:phone":"+1 912 412 9850",
    "sg:postcode":"31419",
    "sg:province":"GA",
    "sg:tags":[
        "roofing",
        "industrial",
        "contractors-commercial",
        "contractor"
    ],
    "wof:name":"Glover Roofing",
    "wof:placetype":"venue"
},
  "geometry": {"coordinates":[-81.13317499999999,31.986625],"type":"Point"}
}