{
  "type": "Feature",
  "properties": {
    "iso:country":"US",
    "sg:address":"3400 Around Lenox Rd NE",
    "sg:city":"Atlanta",
    "sg:classifiers":[
        {
            "category":"Banks & Credit Unions",
            "subcategory":"Investment Brokerage",
            "type":"Services"
        }
    ],
    "sg:phone":"+1 404 364 1715",
    "sg:postcode":"30326",
    "sg:province":"GA",
    "sg:tags":[
        "security"
    ],
    "wof:name":"Scottrade 10batb",
    "wof:placetype":"venue"
},
  "geometry": {"coordinates":[-84.365548,33.847931],"type":"Point"}
}