{
  "type": "Feature",
  "properties": {
    "iso:country":"US",
    "sg:address":"1496 Church St",
    "sg:city":"Decatur",
    "sg:classifiers":[
        {
            "category":"Personal",
            "subcategory":"Nail Salon",
            "type":"Services"
        }
    ],
    "sg:phone":"+1 404 377 9489",
    "sg:postcode":"30030",
    "sg:province":"GA",
    "wof:name":"Nails 4 U",
    "wof:placetype":"venue"
},
  "geometry": {"coordinates":[-84.285698,33.7915],"type":"Point"}
}