{
  "type": "Feature",
  "properties": {
    "addr:full":"3193 Howell Mill Rd NW Atlanta GA 30327",
    "addr:housenumber":"3193",
    "addr:postcode":"30327",
    "addr:street":"Howell Mill Rd Nw",
    "iso:country":"US",
    "sg:address":"3193 Howell Mill Rd NW",
    "sg:city":"Atlanta",
    "sg:classifiers":[
        {
            "category":"Building & Trades",
            "subcategory":"Locksmith",
            "type":"Services"
        }
    ],
    "sg:phone":"+1 866 242 4834",
    "sg:postcode":"30327",
    "sg:province":"GA",
    "sg:tags":[
        "key"
    ],
    "wof:name":"A 1 Lock & Locksmith",
    "wof:placetype":"venue"
},
  "geometry": {"coordinates":[-84.42693800000001,33.840475],"type":"Point"}
}