{
  "type": "Feature",
  "properties": {
    "iso:country":"US",
    "sg:address":"144 Glen Arvin Dr",
    "sg:city":"Leesburg",
    "sg:classifiers":[
        {
            "category":"Freight",
            "type":"Transportation"
        }
    ],
    "sg:phone":"+1 229 439 2914",
    "sg:postcode":"31763",
    "sg:province":"GA",
    "sg:tags":[
        "courier"
    ],
    "wof:name":"R A Courier Service",
    "wof:placetype":"venue"
},
  "geometry": {"coordinates":[-84.261808,31.643808],"type":"Point"}
}