{
  "type": "Feature",
  "properties": {
    "addr:full":"1245 Cahaba Dr SW Atlanta GA 30311",
    "addr:housenumber":"1245",
    "addr:postcode":"30311",
    "addr:street":"Cahaba Dr Sw",
    "iso:country":"US",
    "sg:address":"1245 Cahaba Dr SW",
    "sg:city":"Atlanta",
    "sg:classifiers":[
        {
            "category":"Professional",
            "subcategory":"Research",
            "type":"Services"
        }
    ],
    "sg:phone":"+1 404 755 3201",
    "sg:postcode":"30311",
    "sg:province":"GA",
    "sg:tags":[
        "nonphysical",
        "commercial"
    ],
    "wof:name":"Barry Marketing Research",
    "wof:placetype":"venue"
},
  "geometry": {"coordinates":[-84.448413,33.719871],"type":"Point"}
}