{
  "type": "Feature",
  "properties": {
    "iso:country":"US",
    "sg:address":"324 N Clarendon Ave",
    "sg:city":"Scottdale",
    "sg:classifiers":[
        {
            "category":"Retail",
            "subcategory":"Auto Repair",
            "type":"Services"
        }
    ],
    "sg:phone":"+1 404 292 0504",
    "sg:postcode":"30079",
    "sg:province":"GA",
    "sg:tags":[
        "towing"
    ],
    "wof:name":"Avondale Roadside Service",
    "wof:placetype":"venue"
},
  "geometry": {"coordinates":[-84.26325,33.783046],"type":"Point"}
}