{
  "type": "Feature",
  "properties": {
    "addr:full":"144 Lagrange St Newnan GA 30263",
    "addr:housenumber":"144",
    "addr:postcode":"30263",
    "addr:street":"Lagrange St",
    "iso:country":"US",
    "sg:address":"144 Lagrange St",
    "sg:city":"Newnan",
    "sg:classifiers":[
        {
            "category":"Professional",
            "type":"Services"
        }
    ],
    "sg:phone":"+1 770 253 1517",
    "sg:postcode":"30263",
    "sg:province":"GA",
    "wof:name":"Charles B Goodell Dr",
    "wof:placetype":"venue"
},
  "geometry": {"coordinates":[-84.810852,33.36504],"type":"Point"}
}