{
  "type": "Feature",
  "properties": {
    "iso:country":"US",
    "sg:address":"1575 Satilla Rd",
    "sg:city":"Arlington",
    "sg:classifiers":[
        {
            "category":"Farming",
            "subcategory":"Vineyard",
            "type":"Manufacturing & Wholesale Goods"
        }
    ],
    "sg:phone":"+1 229 792 6382",
    "sg:postcode":"31798",
    "sg:province":"GA",
    "wof:name":"Still Pond Vineyard Inc",
    "wof:placetype":"venue"
},
  "geometry": {"coordinates":[-83.100229,31.553229],"type":"Point"}
}