{
  "type": "Feature",
  "properties": {
    "addr:full":"294 State Rte 101 Dallas GA 30157",
    "addr:housenumber":"294",
    "addr:postcode":"30157",
    "addr:street":"State Rte 101",
    "iso:country":"US",
    "sg:address":"294 State Rte 101",
    "sg:city":"Dallas",
    "sg:classifiers":[
        {
            "category":"Building & Trades",
            "subcategory":"Construction",
            "type":"Services"
        }
    ],
    "sg:phone":"+1 770 459 9222",
    "sg:postcode":"30157",
    "sg:province":"GA",
    "sg:tags":[
        "house",
        "builder",
        "ma",
        "home"
    ],
    "wof:name":"Heartland Home Developers",
    "wof:placetype":"venue"
},
  "geometry": {"coordinates":[-84.98352199999999,33.845835],"type":"Point"}
}