{
  "type": "Feature",
  "properties": {
    "addr:full":"1712 Storey Ln Jefferson GA 30549",
    "addr:housenumber":"1712",
    "addr:postcode":"30549",
    "addr:street":"Storey Ln",
    "iso:country":"US",
    "sg:address":"1712 Storey Ln",
    "sg:city":"Jefferson",
    "sg:classifiers":[
        {
            "category":"Real Estate",
            "subcategory":"Developer",
            "type":"Services"
        }
    ],
    "sg:phone":"+1 706 367 8570",
    "sg:postcode":"30549",
    "sg:province":"GA",
    "wof:name":"Beatty Farm",
    "wof:placetype":"venue"
},
  "geometry": {"coordinates":[-83.611238,34.164569],"type":"Point"}
}