{
  "type": "Feature",
  "properties": {
    "addr:full":"1380 GA-85 Fayetteville GA 30214",
    "addr:housenumber":"1380",
    "addr:postcode":"30214",
    "addr:street":"Ga-85",
    "iso:country":"US",
    "sg:address":"1380 GA-85",
    "sg:city":"Fayetteville",
    "sg:classifiers":[
        {
            "category":"Restaurant",
            "type":"Food & Drink"
        }
    ],
    "sg:menulink":"http://www.allmenus.com/ga/fayetteville/105704-bugaboo-creek-steakhouse/menu/",
    "sg:phone":"+1 770 461 2240",
    "sg:postcode":"30214",
    "sg:province":"GA",
    "sg:tags":[
        "american",
        "steakhouse"
    ],
    "wof:name":"Bugaboo Creek Steakhouse",
    "wof:placetype":"venue"
},
  "geometry": {"coordinates":[-84.440713,33.475006],"type":"Point"}
}