{
  "type": "Feature",
  "properties": {
    "iso:country":"US",
    "sg:address":"3225 Shallowford Rd Ste 1100",
    "sg:city":"Marietta",
    "sg:classifiers":[
        {
            "category":"Banks & Credit Unions",
            "subcategory":"Bank",
            "type":"Services"
        }
    ],
    "sg:phone":"+1 770 509 5000",
    "sg:postcode":"30062",
    "sg:province":"GA",
    "wof:name":"Craig Crump State Farm Insurance",
    "wof:placetype":"venue"
},
  "geometry": {"coordinates":[-84.451103,34.0373],"type":"Point"}
}