{
  "type": "Feature",
  "properties": {
    "addr:full":"45 High St Sharpsburg GA 30277",
    "addr:housenumber":"45",
    "addr:postcode":"30277",
    "addr:street":"High St",
    "iso:country":"US",
    "sg:address":"45 High St",
    "sg:city":"Sharpsburg",
    "sg:classifiers":[
        {
            "category":"Professional",
            "subcategory":"Management & Consulting",
            "type":"Services"
        }
    ],
    "sg:phone":"+1 770 463 1387",
    "sg:postcode":"30277",
    "sg:province":"GA",
    "wof:name":"Rmb Consulting Group Inc",
    "wof:placetype":"venue"
},
  "geometry": {"coordinates":[-84.646052,33.479884],"type":"Point"}
}