{
  "type": "Feature",
  "properties": {
    "addr:full":"1030 W Girard Ave Cedartown GA 30125",
    "addr:housenumber":"1030",
    "addr:postcode":"30125",
    "addr:street":"W Girard Ave",
    "iso:country":"US",
    "sg:address":"1030 W Girard Ave",
    "sg:city":"Cedartown",
    "sg:classifiers":[
        {
            "category":"Social Services",
            "type":"Services"
        }
    ],
    "sg:phone":"+1 770 749 2300",
    "sg:postcode":"30125",
    "sg:province":"GA",
    "sg:tags":[
        "probation"
    ],
    "wof:name":"Nw Probation Detention Ctr",
    "wof:placetype":"venue"
},
  "geometry": {"coordinates":[-85.281789,34.017288],"type":"Point"}
}