{
  "type": "Feature",
  "properties": {
    "addr:full":"1796 Mack Smith Rd Rossville GA 30741",
    "addr:housenumber":"1796",
    "addr:postcode":"30741",
    "addr:street":"Mack Smith Rd",
    "iso:country":"US",
    "sg:address":"1796 Mack Smith Rd",
    "sg:city":"Rossville",
    "sg:classifiers":[
        {
            "category":"Building & Trades",
            "subcategory":"Construction",
            "type":"Services"
        }
    ],
    "sg:phone":"+1 706 891 5200",
    "sg:postcode":"30741",
    "sg:province":"GA",
    "sg:tags":[
        "general",
        "contractor"
    ],
    "wof:name":"Whitmire Construction",
    "wof:placetype":"venue"
},
  "geometry": {"coordinates":[-85.21135099999999,34.985675],"type":"Point"}
}