{
  "type": "Feature",
  "properties": {
    "addr:full":"63 Bradford Pl Lavonia GA 30553",
    "addr:housenumber":"63",
    "addr:postcode":"30553",
    "addr:street":"Bradford Pl",
    "iso:country":"US",
    "sg:address":"63 Bradford Pl",
    "sg:city":"Lavonia",
    "sg:classifiers":[
        {
            "category":"Retail",
            "subcategory":"Portrait Studio",
            "type":"Services"
        },
        {
            "category":"Professional",
            "subcategory":"Art Services",
            "type":"Services"
        }
    ],
    "sg:phone":"+1 706 356 5991",
    "sg:postcode":"30553",
    "sg:province":"GA",
    "sg:tags":[
        "photographer",
        "photography",
        "commercial"
    ],
    "wof:name":"Rich Beginning's Photography",
    "wof:placetype":"venue"
},
  "geometry": {"coordinates":[-83.08964400000001,34.456804],"type":"Point"}
}