{
  "type": "Feature",
  "properties": {
    "iso:country":"US",
    "sg:address":"805 Jett Ferry Manor",
    "sg:city":"Atlanta",
    "sg:classifiers":[
        {
            "category":"Real Estate",
            "subcategory":"Real Estate Agent",
            "type":"Services"
        }
    ],
    "sg:phone":"+1 770 804 9160",
    "sg:postcode":"30350",
    "sg:province":"GA",
    "wof:name":"Tkw Properties Inc",
    "wof:placetype":"venue"
},
  "geometry": {"coordinates":[-84.289928,33.970406],"type":"Point"}
}