{
  "type": "Feature",
  "properties": {
    "addr:full":"6 Chieftain Dr NW Rome GA 30165",
    "addr:housenumber":"6",
    "addr:postcode":"ga 30165",
    "addr:street":"Chieftain Dr Nw",
    "iso:country":"US",
    "sg:address":"6 Chieftain Dr NW",
    "sg:city":"Rome",
    "sg:classifiers":[
        {
            "category":"Retail",
            "subcategory":"Storage",
            "type":"Services"
        }
    ],
    "sg:phone":"+1 706 294 5106",
    "sg:postcode":"30165",
    "sg:province":"GA",
    "sg:tags":[
        "self"
    ],
    "wof:name":"Other Attic West",
    "wof:placetype":"venue"
},
  "geometry": {"coordinates":[-85.226242,34.282372],"type":"Point"}
}