{
  "type": "Feature",
  "properties": {
    "iso:country":"US",
    "sg:address":"295 Carlisle Rd",
    "sg:city":"Jasper",
    "sg:classifiers":[
        {
            "category":"Building & Trades",
            "subcategory":"Plumbing",
            "type":"Services"
        }
    ],
    "sg:phone":"+1 770 735 3484",
    "sg:postcode":"30143",
    "sg:province":"GA",
    "sg:tags":[
        "tank",
        "septic"
    ],
    "wof:name":"Blue Septic Tank Svc",
    "wof:placetype":"venue"
},
  "geometry": {"coordinates":[-84.454612,34.38066],"type":"Point"}
}