{
  "type": "Feature",
  "properties": {
    "addr:full":"131 Ginger Cake Rd Fayetteville GA 30214",
    "addr:housenumber":"131",
    "addr:postcode":"30214",
    "addr:street":"Ginger Cake Rd",
    "iso:country":"US",
    "sg:address":"131 Ginger Cake Rd",
    "sg:city":"Fayetteville",
    "sg:classifiers":[
        {
            "category":"Banks & Credit Unions",
            "subcategory":"Bank",
            "type":"Services"
        }
    ],
    "sg:phone":"+1 770 719 1200",
    "sg:postcode":"30214",
    "sg:province":"GA",
    "wof:name":"State Bank of Georgia",
    "wof:placetype":"venue"
},
  "geometry": {"coordinates":[-84.484819,33.449939],"type":"Point"}
}