{
  "type": "Feature",
  "properties": {
    "iso:country":"US",
    "sg:address":"1797 Roswell Rd",
    "sg:city":"Marietta",
    "sg:classifiers":[
        {
            "category":"Retail",
            "subcategory":"Animal Services",
            "type":"Services"
        }
    ],
    "sg:phone":"+1 770 973 2465",
    "sg:postcode":"30062",
    "sg:province":"GA",
    "sg:tags":[
        "pet",
        "grooming",
        "washing"
    ],
    "wof:name":"Marietta Pet Grooming",
    "wof:placetype":"venue"
},
  "geometry": {"coordinates":[-84.50080699999999,33.957419],"type":"Point"}
}