{
  "type": "Feature",
  "properties": {
    "iso:country":"US",
    "sg:address":"132 Maxwell Ave SW",
    "sg:city":"Marietta",
    "sg:classifiers":[
        {
            "category":"Building & Trades",
            "subcategory":"Construction",
            "type":"Services"
        }
    ],
    "sg:phone":"+1 770 428 8293",
    "sg:postcode":"30064",
    "sg:province":"GA",
    "sg:tags":[
        "house"
    ],
    "wof:name":"Glenn Brothers LLC",
    "wof:placetype":"venue"
},
  "geometry": {"coordinates":[-84.55713900000001,33.949177],"type":"Point"}
}