{
  "type": "Feature",
  "properties": {
    "iso:country":"US",
    "sg:address":"1670 Victory Church Rd",
    "sg:city":"Bowdon",
    "sg:classifiers":[
        {
            "category":"Building & Trades",
            "subcategory":"Construction",
            "type":"Services"
        }
    ],
    "sg:phone":"+1 770 834 7771",
    "sg:postcode":"30108",
    "sg:province":"GA",
    "sg:tags":[
        "downspouts",
        "gutter"
    ],
    "wof:name":"Bell Gutters",
    "wof:placetype":"venue"
},
  "geometry": {"coordinates":[-85.199894,33.523181],"type":"Point"}
}