{
  "type": "Feature",
  "properties": {
    "addr:full":"500 Hillcrest Industrial Blvd Macon GA 31204",
    "addr:housenumber":"500",
    "addr:postcode":"31204",
    "addr:street":"Hillcrest Industrial Blvd",
    "iso:country":"US",
    "sg:address":"500 Hillcrest Industrial Blvd",
    "sg:city":"Macon",
    "sg:classifiers":[
        {
            "category":"Manufacturing",
            "subcategory":"Buildings",
            "type":"Manufacturing & Wholesale Goods"
        },
        {
            "category":"Building & Trades",
            "subcategory":"Construction",
            "type":"Services"
        }
    ],
    "sg:phone":"+1 478 257 6727",
    "sg:postcode":"31204",
    "sg:province":"GA",
    "sg:tags":[
        "industrial",
        "system",
        "specialty",
        "builder",
        "heating",
        "contractor",
        "contractors-commercial",
        "home",
        "air conditioning"
    ],
    "wof:name":"Moye and Associates",
    "wof:placetype":"venue"
},
  "geometry": {"coordinates":[-83.672859,32.845959],"type":"Point"}
}