{
  "type": "Feature",
  "properties": {
    "addr:full":"3730 Glenevon Ct Cumming GA 30041",
    "addr:housenumber":"3730",
    "addr:postcode":"30041",
    "addr:street":"Glenevon Ct",
    "iso:country":"US",
    "sg:address":"3730 Glenevon Ct",
    "sg:city":"Cumming",
    "sg:classifiers":[
        {
            "category":"Building & Trades",
            "subcategory":"Construction",
            "type":"Services"
        }
    ],
    "sg:phone":"+1 770 480 2388",
    "sg:postcode":"30041",
    "sg:province":"GA",
    "sg:tags":[
        "home",
        "improvement"
    ],
    "wof:name":"Creating Space",
    "wof:placetype":"venue"
},
  "geometry": {"coordinates":[-84.184505,34.089415],"type":"Point"}
}