{
  "type": "Feature",
  "properties": {
    "addr:full":"3236 Millwood Trl SE Smyrna GA 30080",
    "addr:housenumber":"3236",
    "addr:postcode":"30080",
    "addr:street":"Millwood Trl Se",
    "iso:country":"US",
    "sg:address":"3236 Millwood Trl SE",
    "sg:city":"Smyrna",
    "sg:classifiers":[
        {
            "category":"Real Estate",
            "subcategory":"Real Estate Agent",
            "type":"Services"
        }
    ],
    "sg:phone":"+1 770 384 0258",
    "sg:postcode":"30080",
    "sg:province":"GA",
    "wof:name":"Rodney Miller Realty",
    "wof:placetype":"venue"
},
  "geometry": {"coordinates":[-84.504926,33.875602],"type":"Point"}
}