{
  "type": "Feature",
  "properties": {
    "addr:full":"1133 Euclid Avenue NE Atlanta GA 30307",
    "addr:housenumber":"1133",
    "addr:postcode":"30307",
    "addr:street":"Euclid Avenue Ne",
    "iso:country":"US",
    "sg:address":"1133 Euclid Avenue NE",
    "sg:city":"Atlanta",
    "sg:classifiers":[
        {
            "category":"Shopping",
            "subcategory":"Clothing, Apparel, & Fashions",
            "type":"Retail Goods"
        }
    ],
    "sg:phone":"+1 404 880 8611",
    "sg:postcode":"30307",
    "sg:province":"GA",
    "sg:tags":[
        "men's",
        "clothing",
        "accessory",
        "women's"
    ],
    "sg:website":"www.americanapparel.net",
    "wof:name":"American Apparel",
    "wof:placetype":"venue"
},
  "geometry": {"coordinates":[-84.35002299999999,33.764531],"type":"Point"}
}