{
  "type": "Feature",
  "properties": {
    "iso:country":"US",
    "sg:address":"125 Jamey Ct",
    "sg:city":"Carrollton",
    "sg:classifiers":[
        {
            "category":"Government",
            "subcategory":"Office",
            "type":"Public Place"
        }
    ],
    "sg:phone":"+1 770 838 1018",
    "sg:postcode":"30117",
    "sg:province":"GA",
    "wof:name":"Lee Spidey Inc",
    "wof:placetype":"venue"
},
  "geometry": {"coordinates":[-85.111729,33.601751],"type":"Point"}
}