{
  "type": "Feature",
  "properties": {
    "addr:full":"3738 Old Penia Rd Cordele GA 31015",
    "addr:housenumber":"3738",
    "addr:postcode":"31015",
    "addr:street":"Old Penia Rd",
    "iso:country":"US",
    "sg:address":"3738 Old Penia Rd",
    "sg:city":"Cordele",
    "sg:classifiers":[
        {
            "category":"Organizations",
            "subcategory":"Religious Organization",
            "type":"Services"
        }
    ],
    "sg:phone":"+1 229 273 5146",
    "sg:postcode":"31015",
    "sg:province":"GA",
    "wof:name":"Penia Baptist Church",
    "wof:placetype":"venue"
},
  "geometry": {"coordinates":[-83.70018,31.967627],"type":"Point"}
}