{
  "type": "Feature",
  "properties": {
    "addr:full":"1767 Ike Stone Rd Monroe GA 30656",
    "addr:housenumber":"1767",
    "addr:postcode":"30656",
    "addr:street":"Ike Stone Rd",
    "iso:country":"US",
    "sg:address":"1767 Ike Stone Rd",
    "sg:city":"Monroe",
    "sg:classifiers":[
        {
            "category":"Farming",
            "subcategory":"Farm",
            "type":"Manufacturing & Wholesale Goods"
        }
    ],
    "sg:phone":"+1 770 207 5836",
    "sg:postcode":"30656",
    "sg:province":"GA",
    "sg:tags":[
        "crop",
        "general"
    ],
    "wof:name":"Walker Farms Stables Inc",
    "wof:placetype":"venue"
},
  "geometry": {"coordinates":[-83.667753,33.856644],"type":"Point"}
}