{
  "type": "Feature",
  "properties": {
    "iso:country":"US",
    "sg:address":"950 Lundy Ter",
    "sg:city":"Macon",
    "sg:classifiers":[
        {
            "category":"Home & Garden",
            "subcategory":"Home Furnishings",
            "type":"Retail Goods"
        }
    ],
    "sg:phone":"+1 478 474 5145",
    "sg:postcode":"31210",
    "sg:province":"GA",
    "wof:name":"Todays Window Fashions",
    "wof:placetype":"venue"
},
  "geometry": {"coordinates":[-83.69349,32.885139],"type":"Point"}
}