{
  "type": "Feature",
  "properties": {
    "iso:country":"US",
    "sg:address":"2801 Wylds Rd",
    "sg:city":"Augusta",
    "sg:classifiers":[
        {
            "category":"Social Services",
            "subcategory":"Child Care",
            "type":"Services"
        }
    ],
    "sg:phone":"+1 706 736 2136",
    "sg:postcode":"30909",
    "sg:province":"GA",
    "sg:website":"www.childtime.com",
    "wof:name":"Childtime Learning Ctr",
    "wof:placetype":"venue"
},
  "geometry": {"coordinates":[-82.075975,33.459497],"type":"Point"}
}