{
  "type": "Feature",
  "properties": {
    "iso:country":"US",
    "sg:address":"1947 Broad St",
    "sg:city":"Augusta",
    "sg:classifiers":[
        {
            "category":"Personal",
            "subcategory":"Beauty Salon",
            "type":"Services"
        }
    ],
    "sg:phone":"+1 706 738 4002",
    "sg:postcode":"30904",
    "sg:province":"GA",
    "wof:name":"Tara's Salon",
    "wof:placetype":"venue"
},
  "geometry": {"coordinates":[-81.99704199999999,33.485747],"type":"Point"}
}