{
  "type": "Feature",
  "properties": {
    "addr:full":"38 Peachtree Center Ave NE Atlanta GA 30303",
    "addr:housenumber":"38",
    "addr:postcode":"30303",
    "addr:street":"Peachtree Center Ave Ne",
    "iso:country":"US",
    "sg:address":"38 Peachtree Center Ave NE",
    "sg:city":"Atlanta",
    "sg:classifiers":[
        {
            "category":"Education",
            "subcategory":"Special Training",
            "type":"Public Place"
        }
    ],
    "sg:phone":"+1 404 651 2693",
    "sg:postcode":"30303",
    "sg:province":"GA",
    "sg:tags":[
        "business"
    ],
    "wof:name":"Samla",
    "wof:placetype":"venue"
},
  "geometry": {"coordinates":[-84.386273,33.754794],"type":"Point"}
}