{
  "type": "Feature",
  "properties": {
    "addr:full":"453 Gaines Ave Albany GA 31701",
    "addr:housenumber":"453",
    "addr:postcode":"31701",
    "addr:street":"Gaines Ave",
    "iso:country":"US",
    "sg:address":"453 Gaines Ave",
    "sg:city":"Albany",
    "sg:classifiers":[
        {
            "category":"Personal",
            "subcategory":"Beauty Salon",
            "type":"Services"
        }
    ],
    "sg:phone":"+1 229 883 6656",
    "sg:postcode":"31701",
    "sg:province":"GA",
    "sg:tags":[
        "shop"
    ],
    "wof:name":"Styles In Minutes",
    "wof:placetype":"venue"
},
  "geometry": {"coordinates":[-84.160139,31.549567],"type":"Point"}
}