{
  "type": "Feature",
  "properties": {
    "iso:country":"US",
    "sg:address":"300 Martin Luther King Jr Dr SE #343",
    "sg:city":"Atlanta",
    "sg:classifiers":[
        {
            "category":"Professional",
            "subcategory":"Art Services",
            "type":"Services"
        }
    ],
    "sg:phone":"+1 404 791 5503",
    "sg:postcode":"30312",
    "sg:province":"GA",
    "sg:tags":[
        "photographer"
    ],
    "sg:website":"www.bellettiphotography.com",
    "wof:name":"Belletti Photography",
    "wof:placetype":"venue"
},
  "geometry": {"coordinates":[-84.376639,33.747411],"type":"Point"}
}