{
  "type": "Feature",
  "properties": {
    "iso:country":"US",
    "sg:address":"5880 Sandy Creek Rd",
    "sg:city":"Loganville",
    "sg:classifiers":[
        {
            "category":"Building & Trades",
            "subcategory":"Construction",
            "type":"Services"
        }
    ],
    "sg:phone":"+1 770 466 6396",
    "sg:postcode":"30052",
    "sg:province":"GA",
    "sg:tags":[
        "floor",
        "laying",
        "contractor"
    ],
    "wof:name":"Keith Myers",
    "wof:placetype":"venue"
},
  "geometry": {"coordinates":[-83.932444,33.781735],"type":"Point"}
}