{
  "type": "Feature",
  "properties": {
    "iso:country":"US",
    "sg:address":"1904 Rockbridge Rd NW",
    "sg:city":"Conyers",
    "sg:classifiers":[
        {
            "category":"Shopping",
            "subcategory":"Bicycles & Sporting Goods",
            "type":"Retail Goods"
        }
    ],
    "sg:phone":"+1 770 761 3163",
    "sg:postcode":"30012",
    "sg:province":"GA",
    "wof:name":"Southeast Bait Distributors",
    "wof:placetype":"venue"
},
  "geometry": {"coordinates":[-84.039609,33.693807],"type":"Point"}
}