{
  "type": "Feature",
  "properties": {
    "iso:country":"US",
    "sg:address":"2480 Bell Scene Rd",
    "sg:city":"Hiawassee",
    "sg:classifiers":[
        {
            "category":"Real Estate",
            "subcategory":"Real Estate Agent",
            "type":"Services"
        }
    ],
    "sg:phone":"+1 706 896 2300",
    "sg:postcode":"30546",
    "sg:province":"GA",
    "wof:name":"Town Center Land Co",
    "wof:placetype":"venue"
},
  "geometry": {"coordinates":[-83.724951,34.986162],"type":"Point"}
}