{
  "type": "Feature",
  "properties": {
    "addr:full":"825 Church St NE Marietta GA 30060",
    "addr:housenumber":"825",
    "addr:postcode":"30060",
    "addr:street":"Church St Ne",
    "iso:country":"US",
    "sg:address":"825 Church St NE",
    "sg:city":"Marietta",
    "sg:classifiers":[
        {
            "category":"Fast Food",
            "type":"Food & Drink"
        },
        {
            "category":"Restaurant",
            "type":"Food & Drink"
        },
        {
            "category":"Food & Beverages",
            "subcategory":"Groceries & Convenience Stores",
            "type":"Retail Goods"
        }
    ],
    "sg:phone":"+1 678 581 4550",
    "sg:postcode":"30060",
    "sg:province":"GA",
    "sg:tags":[
        "shop",
        "sandwich",
        "take"
    ],
    "sg:website":"http://www.jimmyjohns.com",
    "wof:name":"Jimmy John's",
    "wof:placetype":"venue"
},
  "geometry": {"coordinates":[-84.550788,33.97191],"type":"Point"}
}