{
  "type": "Feature",
  "properties": {
    "addr:full":"1046 Justice Ln Acworth GA 30102",
    "addr:housenumber":"1046",
    "addr:postcode":"30102",
    "addr:street":"Justice Ln",
    "iso:country":"US",
    "sg:address":"1046 Justice Ln",
    "sg:city":"Acworth",
    "sg:classifiers":[
        {
            "category":"Professional",
            "type":"Services"
        }
    ],
    "sg:phone":"+1 770 591 1724",
    "sg:postcode":"30102",
    "sg:province":"GA",
    "wof:name":"Han Co",
    "wof:placetype":"venue"
},
  "geometry": {"coordinates":[-84.579975,34.073266],"type":"Point"}
}