{
  "type": "Feature",
  "properties": {
    "iso:country":"US",
    "sg:address":"6689 Peachtree Industrial Blvd",
    "sg:city":"Norcross",
    "sg:classifiers":[
        {
            "category":"Organizations",
            "subcategory":"Professional Association",
            "type":"Services"
        }
    ],
    "sg:phone":"+1 770 446 8600",
    "sg:postcode":"30092",
    "sg:province":"GA",
    "sg:tags":[
        "business"
    ],
    "wof:name":"National Business Oprtnty Bur",
    "wof:placetype":"venue"
},
  "geometry": {"coordinates":[-84.25012599999999,33.938424],"type":"Point"}
}