{
  "type": "Feature",
  "properties": {
    "iso:country":"US",
    "sg:address":"559 Highland Ave NE",
    "sg:city":"Atlanta",
    "sg:classifiers":[
        {
            "category":"Building & Trades",
            "subcategory":"Construction",
            "type":"Services"
        }
    ],
    "sg:phone":"+1 404 582 0051",
    "sg:postcode":"30312",
    "sg:province":"GA",
    "sg:tags":[
        "contractor"
    ],
    "wof:name":"South Eastern Building Svc",
    "wof:placetype":"venue"
},
  "geometry": {"coordinates":[-84.369773,33.761262],"type":"Point"}
}