{
  "type": "Feature",
  "properties": {
    "addr:full":"915 Gunter Ct Alpharetta GA 30022",
    "addr:housenumber":"915",
    "addr:postcode":"30022",
    "addr:street":"Gunter Ct",
    "iso:country":"US",
    "sg:address":"915 Gunter Ct",
    "sg:city":"Alpharetta",
    "sg:classifiers":[
        {
            "category":"Manufacturing",
            "subcategory":"Tools & Machinery",
            "type":"Manufacturing & Wholesale Goods"
        }
    ],
    "sg:phone":"+1 770 772 0846",
    "sg:postcode":"30022",
    "sg:province":"GA",
    "sg:tags":[
        "woodworking",
        "mfg"
    ],
    "wof:name":"Casa Machine & Tool Inc",
    "wof:placetype":"venue"
},
  "geometry": {"coordinates":[-84.274677,34.049577],"type":"Point"}
}