{
  "type": "Feature",
  "properties": {
    "iso:country":"US",
    "sg:address":"4020 Cranwood Dr",
    "sg:city":"Atlanta",
    "sg:classifiers":[
        {
            "category":"Building & Trades",
            "subcategory":"Plumbing",
            "type":"Services"
        }
    ],
    "sg:phone":"+1 404 561 3790",
    "sg:postcode":"30349",
    "sg:province":"GA",
    "sg:tags":[
        "conditioning",
        "air",
        "system",
        "contractor"
    ],
    "wof:name":"Smith Heating & Air Cond",
    "wof:placetype":"venue"
},
  "geometry": {"coordinates":[-84.594487,33.646451],"type":"Point"}
}