{
  "type": "Feature",
  "properties": {
    "iso:country":"US",
    "sg:address":"2033 Mount Zion Rd",
    "sg:city":"Morrow",
    "sg:classifiers":[
        {
            "category":"Health Services",
            "subcategory":"Doctor",
            "type":"Services"
        }
    ],
    "sg:phone":"+1 770 961 6002",
    "sg:postcode":"30260",
    "sg:province":"GA",
    "sg:tags":[
        "dentist"
    ],
    "wof:name":"North Georgia Orthodontics",
    "wof:placetype":"venue"
},
  "geometry": {"coordinates":[-84.323189,33.56197],"type":"Point"}
}