{
  "type": "Feature",
  "properties": {
    "iso:country":"US",
    "sg:address":"861 Holcomb Bridge Rd Ste 201",
    "sg:city":"Roswell",
    "sg:classifiers":[
        {
            "category":"Health Services",
            "subcategory":"Chiropractor",
            "type":"Services"
        }
    ],
    "sg:phone":"+1 770 645 8669",
    "sg:postcode":"30076",
    "sg:province":"GA",
    "wof:name":"Prendes Family Chiropractic Spanish",
    "wof:placetype":"venue"
},
  "geometry": {"coordinates":[-84.337231,34.029511],"type":"Point"}
}