{
  "type": "Feature",
  "properties": {
    "addr:full":"42 E Main St Forsyth GA 31029",
    "addr:housenumber":"42",
    "addr:postcode":"31029",
    "addr:street":"E Main St",
    "iso:country":"US",
    "sg:address":"42 E Main St",
    "sg:city":"Forsyth",
    "sg:classifiers":[
        {
            "category":"Personal",
            "subcategory":"Beauty Salon",
            "type":"Services"
        }
    ],
    "sg:phone":"+1 478 994 0360",
    "sg:postcode":"31029",
    "sg:province":"GA",
    "wof:name":"Creations Salon",
    "wof:placetype":"venue"
},
  "geometry": {"coordinates":[-83.936804,33.03421],"type":"Point"}
}