{
  "type": "Feature",
  "properties": {
    "iso:country":"US",
    "sg:address":"79 Planters Dr",
    "sg:city":"Cartersville",
    "sg:classifiers":[
        {
            "category":"Autos & Motor Vehicles",
            "subcategory":"Auto Supplies",
            "type":"Retail Goods"
        }
    ],
    "sg:phone":"+1 770 606 9948",
    "sg:postcode":"30120",
    "sg:province":"GA",
    "sg:tags":[
        "filter",
        "gas"
    ],
    "wof:name":"Southern Industrial Filtration",
    "wof:placetype":"venue"
},
  "geometry": {"coordinates":[-84.879149,34.229989],"type":"Point"}
}