{
  "type": "Feature",
  "properties": {
    "addr:full":"243 Church St Bainbridge GA 39817",
    "addr:housenumber":"243",
    "addr:postcode":"39817",
    "addr:street":"Church St",
    "iso:country":"US",
    "sg:address":"243 Church St",
    "sg:city":"Bainbridge",
    "sg:classifiers":[
        {
            "category":"Organizations",
            "subcategory":"Religious Organization",
            "type":"Services"
        }
    ],
    "sg:phone":"+1 229 246 8570",
    "sg:postcode":"39817",
    "sg:province":"GA",
    "sg:tags":[
        "church"
    ],
    "wof:name":"Mount Zion Baptist Church",
    "wof:placetype":"venue"
},
  "geometry": {"coordinates":[-84.591284,30.913854],"type":"Point"}
}