{
  "type": "Feature",
  "properties": {
    "iso:country":"US",
    "sg:address":"3921 Johns Creek Ct",
    "sg:city":"Suwanee",
    "sg:classifiers":[
        {
            "category":"Health Services",
            "subcategory":"Doctor",
            "type":"Services"
        }
    ],
    "sg:phone":"+1 678 475 1606",
    "sg:postcode":"30024",
    "sg:province":"GA",
    "wof:name":"Advanced Gastroenterology Assoc",
    "wof:placetype":"venue"
},
  "geometry": {"coordinates":[-84.160599,34.069302],"type":"Point"}
}