{
  "type": "Feature",
  "properties": {
    "iso:country":"US",
    "sg:address":"2632 Blueberry Cir",
    "sg:city":"Augusta",
    "sg:classifiers":[
        {
            "category":"Food & Beverages",
            "subcategory":"Bakery",
            "type":"Retail Goods"
        }
    ],
    "sg:phone":"+1 706 560 0115",
    "sg:postcode":"30906",
    "sg:province":"GA",
    "wof:name":"Syms Distributors Inc",
    "wof:placetype":"venue"
},
  "geometry": {"coordinates":[-82.01964099999999,33.414619],"type":"Point"}
}