{
  "type": "Feature",
  "properties": {
    "iso:country":"US",
    "sg:address":"3737 Kings Hwy",
    "sg:city":"Douglasville",
    "sg:classifiers":[
        {
            "category":"Restaurant",
            "type":"Food & Drink"
        }
    ],
    "sg:phone":"+1 678 715 7355",
    "sg:postcode":"30135",
    "sg:province":"GA",
    "sg:tags":[
        "eating"
    ],
    "wof:name":"Sammys Restaurant",
    "wof:placetype":"venue"
},
  "geometry": {"coordinates":[-84.770927,33.705611],"type":"Point"}
}