{
  "type": "Feature",
  "properties": {
    "iso:country":"US",
    "sg:address":"1923 Pulliam Mill Rd",
    "sg:city":"Dewy Rose",
    "sg:classifiers":[
        {
            "category":"Organizations",
            "subcategory":"Religious Organization",
            "type":"Services"
        }
    ],
    "sg:phone":"+1 706 213 0712",
    "sg:postcode":"30634",
    "sg:province":"GA",
    "sg:tags":[
        "church"
    ],
    "wof:name":"Dewy Rose Baptist Church",
    "wof:placetype":"venue"
},
  "geometry": {"coordinates":[-82.943387,34.179351],"type":"Point"}
}