{
  "type": "Feature",
  "properties": {
    "addr:full":"3470 N Valdosta Rd Valdosta GA 31602",
    "addr:housenumber":"3470",
    "addr:postcode":"31602",
    "addr:street":"N Valdosta Rd",
    "iso:country":"US",
    "sg:address":"3470 N Valdosta Rd",
    "sg:city":"Valdosta",
    "sg:classifiers":[
        {
            "category":"Professional",
            "subcategory":"Lawyer & Legal Services",
            "type":"Services"
        }
    ],
    "sg:phone":"+1 229 245 7823",
    "sg:postcode":"31602",
    "sg:province":"GA",
    "sg:tags":[
        "attorney"
    ],
    "wof:name":"Moore Clarke Duvall & Rodgers",
    "wof:placetype":"venue"
},
  "geometry": {"coordinates":[-83.30414399999999,30.879956],"type":"Point"}
}