{
  "type": "Feature",
  "properties": {
    "iso:country":"US",
    "sg:address":"59 E Main St",
    "sg:city":"Dahlonega",
    "sg:classifiers":[
        {
            "category":"Shopping",
            "subcategory":"Pharmacy",
            "type":"Retail Goods"
        }
    ],
    "sg:phone":"+1 706 864 3308",
    "sg:postcode":"30533",
    "sg:province":"GA",
    "sg:tags":[
        "drug",
        "store"
    ],
    "wof:name":"Sisk Drug Store",
    "wof:placetype":"venue"
},
  "geometry": {"coordinates":[-83.983723,34.533471],"type":"Point"}
}