{
  "type": "Feature",
  "properties": {
    "iso:country":"US",
    "sg:address":"327 Osburn Rd",
    "sg:city":"Chickamauga",
    "sg:classifiers":[
        {
            "category":"Professional",
            "subcategory":"Engineering",
            "type":"Services"
        }
    ],
    "sg:phone":"+1 706 375 3642",
    "sg:postcode":"30707",
    "sg:province":"GA",
    "wof:name":"Charles L Cofer Pe",
    "wof:placetype":"venue"
},
  "geometry": {"coordinates":[-85.276098,34.902636],"type":"Point"}
}