{
  "type": "Feature",
  "properties": {
    "addr:full":"6683 Bells Ferry Rd Woodstock GA 30189",
    "addr:housenumber":"6683",
    "addr:postcode":"30189",
    "addr:street":"Bells Ferry Rd",
    "iso:country":"US",
    "sg:address":"6683 Bells Ferry Rd",
    "sg:city":"Woodstock",
    "sg:classifiers":[
        {
            "category":"Building & Trades",
            "subcategory":"Plumbing",
            "type":"Services"
        }
    ],
    "sg:phone":"+1 770 592 5620",
    "sg:postcode":"30189",
    "sg:province":"GA",
    "sg:tags":[
        "plumbing",
        "contractor"
    ],
    "wof:name":"Plumb Crazy Plumbing",
    "wof:placetype":"venue"
},
  "geometry": {"coordinates":[-84.586229,34.131755],"type":"Point"}
}