{
  "type": "Feature",
  "properties": {
    "addr:full":"7670 Airport Dr Macon GA 31297",
    "addr:housenumber":"7670",
    "addr:postcode":"31297",
    "addr:street":"Airport Dr",
    "iso:country":"US",
    "sg:address":"7670 Airport Dr",
    "sg:city":"Macon",
    "sg:classifiers":[
        {
            "category":"Manufacturing",
            "subcategory":"Paper Products",
            "type":"Manufacturing & Wholesale Goods"
        }
    ],
    "sg:phone":"+1 478 781 1474",
    "sg:postcode":"31297",
    "sg:province":"GA",
    "sg:tags":[
        "die",
        "paperboard"
    ],
    "wof:name":"Pactiv Corp",
    "wof:placetype":"venue"
},
  "geometry": {"coordinates":[-83.64988099999999,32.705047],"type":"Point"}
}