{
  "type": "Feature",
  "properties": {
    "iso:country":"US",
    "sg:address":"2265 Cassina Pointe",
    "sg:city":"Marietta",
    "sg:classifiers":[
        {
            "category":"Professional",
            "type":"Services"
        }
    ],
    "sg:phone":"+1 770 590 5092",
    "sg:postcode":"30064",
    "sg:province":"GA",
    "sg:tags":[
        "establishment"
    ],
    "wof:name":"V 2 Performance",
    "wof:placetype":"venue"
},
  "geometry": {"coordinates":[-84.621104,33.914417],"type":"Point"}
}