{
  "type": "Feature",
  "properties": {
    "addr:full":"35 Leader Rd SW Marietta GA 30008",
    "addr:housenumber":"35",
    "addr:postcode":"30008",
    "addr:street":"Leader Rd Sw",
    "iso:country":"US",
    "sg:address":"35 Leader Rd SW",
    "sg:city":"Marietta",
    "sg:classifiers":[
        {
            "category":"Organizations",
            "subcategory":"Religious Organization",
            "type":"Services"
        }
    ],
    "sg:phone":"+1 770 919 7667",
    "sg:postcode":"30008",
    "sg:province":"GA",
    "sg:tags":[
        "church"
    ],
    "wof:name":"Miracle Faith Ministries Intl",
    "wof:placetype":"venue"
},
  "geometry": {"coordinates":[-84.553804,33.926484],"type":"Point"}
}