{
  "type": "Feature",
  "properties": {
    "addr:full":"2550 Tobacco Rd Hephzibah GA 30815",
    "addr:housenumber":"2550",
    "addr:postcode":"30815",
    "addr:street":"Tobacco Rd",
    "iso:country":"US",
    "sg:address":"2550 Tobacco Rd",
    "sg:city":"Hephzibah",
    "sg:classifiers":[
        {
            "category":"Banks & Credit Unions",
            "subcategory":"Bank",
            "type":"Services"
        }
    ],
    "sg:phone":"+1 706 798 2424",
    "sg:postcode":"30815",
    "sg:province":"GA",
    "wof:name":"First National Bank & Trust Co",
    "wof:placetype":"venue"
},
  "geometry": {"coordinates":[-82.079995,33.378134],"type":"Point"}
}