{
  "type": "Feature",
  "properties": {
    "iso:country":"US",
    "sg:address":"2000 10th Ave Ste 180",
    "sg:city":"Columbus",
    "sg:classifiers":[
        {
            "category":"Health Services",
            "subcategory":"Doctor",
            "type":"Services"
        }
    ],
    "sg:phone":"+1 706 653 8556",
    "sg:postcode":"31901",
    "sg:province":"GA",
    "sg:tags":[
        "medicine",
        "physician",
        "practice",
        "surgeons",
        "family"
    ],
    "wof:name":"Thomas R Stewart Md Pc",
    "wof:placetype":"venue"
},
  "geometry": {"coordinates":[-84.979569,32.481144],"type":"Point"}
}