{
  "type": "Feature",
  "properties": {
    "addr:full":"6039 Gateway Rd Columbus GA 31909",
    "addr:housenumber":"6039",
    "addr:postcode":"31909",
    "addr:street":"Gateway Rd",
    "iso:country":"US",
    "sg:address":"6039 Gateway Rd",
    "sg:city":"Columbus",
    "sg:classifiers":[
        {
            "category":"Restaurant",
            "type":"Food & Drink"
        }
    ],
    "sg:phone":"+1 706 327 4222",
    "sg:postcode":"31909",
    "sg:province":"GA",
    "wof:name":"Subway Sandwiches & Salads",
    "wof:placetype":"venue"
},
  "geometry": {"coordinates":[-84.88697500000001,32.527555],"type":"Point"}
}