{
  "type": "Feature",
  "properties": {
    "iso:country":"US",
    "sg:address":"2905 Cobb Pkwy S",
    "sg:city":"Atlanta",
    "sg:classifiers":[
        {
            "category":"Professional",
            "type":"Services"
        },
        {
            "category":"Health Services",
            "subcategory":"Optometrist",
            "type":"Services"
        }
    ],
    "sg:phone":"+1 404 298 1823",
    "sg:postcode":"30339",
    "sg:province":"GA",
    "wof:name":"Laser Vision Institute LLC",
    "wof:placetype":"venue"
},
  "geometry": {"coordinates":[-84.46830199999999,33.883099],"type":"Point"}
}