{
  "type": "Feature",
  "properties": {
    "addr:full":"7816 Barkers Bend Dr Murrayville GA 30564",
    "addr:housenumber":"7816",
    "addr:postcode":"30564",
    "addr:street":"Barkers Bend Dr",
    "iso:country":"US",
    "sg:address":"7816 Barkers Bend Dr",
    "sg:city":"Murrayville",
    "sg:classifiers":[
        {
            "category":"Communications",
            "type":"Services"
        }
    ],
    "sg:phone":"+1 678 450 0328",
    "sg:postcode":"30564",
    "sg:province":"GA",
    "sg:tags":[
        "communication"
    ],
    "wof:name":"Shurn Communications Denn",
    "wof:placetype":"venue"
},
  "geometry": {"coordinates":[-83.9726,34.410622],"type":"Point"}
}