{
  "type": "Feature",
  "properties": {
    "iso:country":"US",
    "sg:address":"141 Hanner Ln",
    "sg:city":"Ashburn",
    "sg:classifiers":[
        {
            "category":"Freight",
            "type":"Transportation"
        }
    ],
    "sg:phone":"+1 229 567 2758",
    "sg:postcode":"31714",
    "sg:province":"GA",
    "sg:tags":[
        "trucking"
    ],
    "wof:name":"Hanner Transport Inc",
    "wof:placetype":"venue"
},
  "geometry": {"coordinates":[-83.604488,31.720656],"type":"Point"}
}