{
  "type": "Feature",
  "properties": {
    "addr:full":"196 Farmers Bridge Cir Hephzibah GA 30815",
    "addr:housenumber":"196",
    "addr:postcode":"30815",
    "addr:street":"Farmers Bridge Cir",
    "iso:country":"US",
    "sg:address":"196 Farmers Bridge Cir",
    "sg:city":"Hephzibah",
    "sg:classifiers":[
        {
            "category":"Farming",
            "subcategory":"Farm",
            "type":"Manufacturing & Wholesale Goods"
        }
    ],
    "sg:phone":"+1 706 592 4509",
    "sg:postcode":"30815",
    "sg:province":"GA",
    "wof:name":"James M Boyd",
    "wof:placetype":"venue"
},
  "geometry": {"coordinates":[-82.161058,33.23259],"type":"Point"}
}