{
  "type": "Feature",
  "properties": {
    "iso:country":"US",
    "sg:address":"112 Golden Ln",
    "sg:city":"Douglas",
    "sg:classifiers":[
        {
            "category":"Retail",
            "subcategory":"Repair Shop",
            "type":"Services"
        }
    ],
    "sg:phone":"+1 912 384 6749",
    "sg:postcode":"31535",
    "sg:province":"GA",
    "wof:name":"James Earl Strickland",
    "wof:placetype":"venue"
},
  "geometry": {"coordinates":[-82.902495,31.459734],"type":"Point"}
}