{
  "type": "Feature",
  "properties": {
    "addr:full":"7865 Jot Em Down Rd Gainesville GA 30506",
    "addr:housenumber":"7865",
    "addr:postcode":"30506",
    "addr:street":"Jot Em Down Rd",
    "iso:country":"US",
    "sg:address":"7865 Jot Em Down Rd",
    "sg:city":"Gainesville",
    "sg:classifiers":[
        {
            "category":"Professional",
            "subcategory":"Business Services",
            "type":"Services"
        }
    ],
    "sg:phone":"+1 770 205 8165",
    "sg:postcode":"30506",
    "sg:province":"GA",
    "wof:name":"Ceries",
    "wof:placetype":"venue"
},
  "geometry": {"coordinates":[-83.99917600000001,34.291369],"type":"Point"}
}