{
  "type": "Feature",
  "properties": {
    "iso:country":"US",
    "sg:address":"1276 Robin Rd NE",
    "sg:city":"Conyers",
    "sg:classifiers":[
        {
            "category":"Building & Trades",
            "subcategory":"Plumbing",
            "type":"Services"
        }
    ],
    "sg:phone":"+1 770 483 8136",
    "sg:postcode":"30012",
    "sg:province":"GA",
    "sg:tags":[
        "septic"
    ],
    "wof:name":"R W Hill Septic Tank Pumping",
    "wof:placetype":"venue"
},
  "geometry": {"coordinates":[-84.00317099999999,33.663498],"type":"Point"}
}