{
  "type": "Feature",
  "properties": {
    "addr:full":"2974 Sloans Way Marietta GA 30062",
    "addr:housenumber":"2974",
    "addr:postcode":"30062",
    "addr:street":"Sloans Way",
    "iso:country":"US",
    "sg:address":"2974 Sloans Way",
    "sg:city":"Marietta",
    "sg:classifiers":[
        {
            "category":"Health Services",
            "subcategory":"Chiropractor",
            "type":"Services"
        }
    ],
    "sg:phone":"+1 678 560 7733",
    "sg:postcode":"30062",
    "sg:province":"GA",
    "sg:tags":[
        "clinic"
    ],
    "wof:name":"Dynamic Lifeline Chiropractic",
    "wof:placetype":"venue"
},
  "geometry": {"coordinates":[-84.48306599999999,34.021024],"type":"Point"}
}