{
  "type": "Feature",
  "properties": {
    "iso:country":"US",
    "sg:address":"197 Andy St",
    "sg:city":"Washington",
    "sg:classifiers":[
        {
            "category":"Manufacturing",
            "subcategory":"Printing",
            "type":"Manufacturing & Wholesale Goods"
        }
    ],
    "sg:phone":"+1 706 678 1390",
    "sg:postcode":"30673",
    "sg:province":"GA",
    "sg:tags":[
        "commercial"
    ],
    "wof:name":"CTB Graphic",
    "wof:placetype":"venue"
},
  "geometry": {"coordinates":[-82.70329099999999,33.721064],"type":"Point"}
}