{
  "type": "Feature",
  "properties": {
    "iso:country":"US",
    "sg:address":"2958 Buford Hwy",
    "sg:city":"Cumming",
    "sg:classifiers":[
        {
            "category":"Food & Beverages",
            "subcategory":"Liquor & Beverages",
            "type":"Retail Goods"
        }
    ],
    "sg:phone":"+1 678 947 3003",
    "sg:postcode":"30041",
    "sg:province":"GA",
    "sg:tags":[
        "beer",
        "spirit",
        "wine"
    ],
    "wof:name":"Top Shelf Beverages",
    "wof:placetype":"venue"
},
  "geometry": {"coordinates":[-84.10305099999999,34.13814],"type":"Point"}
}