{
  "type": "Feature",
  "properties": {
    "iso:country":"US",
    "sg:address":"3629 Altama Ave",
    "sg:city":"Brunswick",
    "sg:classifiers":[
        {
            "category":"Insurance",
            "subcategory":"Hazard Insurance",
            "type":"Services"
        }
    ],
    "sg:phone":"+1 912 262 9393",
    "sg:postcode":"31520",
    "sg:province":"GA",
    "sg:tags":[
        "commercial",
        "business"
    ],
    "wof:name":"Direct General Insurance Agency, Inc",
    "wof:placetype":"venue"
},
  "geometry": {"coordinates":[-81.48938,31.180699],"type":"Point"}
}