{
  "type": "Feature",
  "properties": {
    "iso:country":"US",
    "sg:address":"103 Nassau Dr",
    "sg:city":"Savannah",
    "sg:classifiers":[
        {
            "category":"Professional",
            "subcategory":"Engineering",
            "type":"Services"
        }
    ],
    "sg:phone":"+1 912 897 6932",
    "sg:postcode":"31410",
    "sg:province":"GA",
    "sg:tags":[
        "engineer"
    ],
    "wof:name":"Boswell Design Svc",
    "wof:placetype":"venue"
},
  "geometry": {"coordinates":[-80.982517,32.01188],"type":"Point"}
}