{
  "type": "Feature",
  "properties": {
    "addr:full":"1669 Whippoorwill Trl Hartwell GA 30643",
    "addr:housenumber":"1669",
    "addr:postcode":"30643",
    "addr:street":"Whippoorwill Trl",
    "iso:country":"US",
    "sg:address":"1669 Whippoorwill Trl",
    "sg:city":"Hartwell",
    "sg:classifiers":[
        {
            "category":"Building & Trades",
            "subcategory":"Cleaning & Sanitation",
            "type":"Services"
        }
    ],
    "sg:phone":"+1 706 376 3001",
    "sg:postcode":"30643",
    "sg:province":"GA",
    "sg:tags":[
        "janitor"
    ],
    "wof:name":"Ayers Cleaning Svc",
    "wof:placetype":"venue"
},
  "geometry": {"coordinates":[-82.88056400000001,34.31816],"type":"Point"}
}