{
  "type": "Feature",
  "properties": {
    "addr:full":"336B Commerce St Hawkinsville GA 31036",
    "addr:housenumber":"336b",
    "addr:postcode":"31036",
    "addr:street":"Commerce St",
    "iso:country":"US",
    "sg:address":"336B Commerce St",
    "sg:city":"Hawkinsville",
    "sg:classifiers":[
        {
            "category":"Banks & Credit Unions",
            "subcategory":"Financial Services",
            "type":"Services"
        }
    ],
    "sg:phone":"+1 478 783 3225",
    "sg:postcode":"31036",
    "sg:province":"GA",
    "sg:tags":[
        "loan",
        "financing"
    ],
    "wof:name":"Greene Finance Co",
    "wof:placetype":"venue"
},
  "geometry": {"coordinates":[-83.482468,32.285606],"type":"Point"}
}