{
  "type": "Feature",
  "properties": {
    "iso:country":"US",
    "sg:address":"207 Angie Way",
    "sg:city":"Bethlehem",
    "sg:classifiers":[
        {
            "category":"Manufacturing",
            "subcategory":"Apparel",
            "type":"Manufacturing & Wholesale Goods"
        }
    ],
    "sg:phone":"+1 770 868 5268",
    "sg:postcode":"30620",
    "sg:province":"GA",
    "sg:tags":[
        "mfg"
    ],
    "wof:name":"Sports Cheer Unlimited",
    "wof:placetype":"venue"
},
  "geometry": {"coordinates":[-83.763131,33.933787],"type":"Point"}
}