{
  "type": "Feature",
  "properties": {
    "iso:country":"US",
    "sg:address":"2707 Palmyra Rd",
    "sg:city":"Albany",
    "sg:classifiers":[
        {
            "category":"Building & Trades",
            "subcategory":"Construction",
            "type":"Services"
        },
        {
            "category":"Utilities",
            "type":"Services"
        }
    ],
    "sg:phone":"+1 229 436 2501",
    "sg:postcode":"31707",
    "sg:province":"GA",
    "sg:tags":[
        "contractor",
        "water",
        "sewer",
        "storm",
        "drainage",
        "locating"
    ],
    "wof:name":"Flanigan Plumbing Co Inc",
    "wof:placetype":"venue"
},
  "geometry": {"coordinates":[-84.182366,31.616462],"type":"Point"}
}