{
  "type": "Feature",
  "properties": {
    "iso:country":"US",
    "sg:address":"2612 White Aster Ln",
    "sg:city":"Dacula",
    "sg:classifiers":[
        {
            "category":"Professional",
            "type":"Services"
        }
    ],
    "sg:phone":"+1 404 431 2981",
    "sg:postcode":"30019",
    "sg:province":"GA",
    "wof:name":"Greg Moffett",
    "wof:placetype":"venue"
},
  "geometry": {"coordinates":[-83.916357,34.013947],"type":"Point"}
}