{
  "type": "Feature",
  "properties": {
    "iso:country":"US",
    "sg:address":"13025 Birmingham Hwy",
    "sg:city":"Alpharetta",
    "sg:classifiers":[
        {
            "category":"Education",
            "subcategory":"School",
            "type":"Public Place"
        }
    ],
    "sg:phone":"+1 770 740 7000",
    "sg:postcode":"30004",
    "sg:province":"GA",
    "wof:name":"Milton High School",
    "wof:placetype":"venue"
},
  "geometry": {"coordinates":[-84.33936799999999,34.091069],"type":"Point"}
}