{
  "type": "Feature",
  "properties": {
    "addr:full":"8570 Cedar Creek Ridge Riverdale GA 30274",
    "addr:housenumber":"8570",
    "addr:postcode":"30274",
    "addr:street":"Cedar Creek Ridge",
    "iso:country":"US",
    "sg:address":"8570 Cedar Creek Ridge",
    "sg:city":"Riverdale",
    "sg:classifiers":[
        {
            "category":"Retail",
            "subcategory":"Repair Shop",
            "type":"Services"
        }
    ],
    "sg:phone":"+1 678 479 6200",
    "sg:postcode":"30274",
    "sg:province":"GA",
    "sg:tags":[
        "appliance"
    ],
    "wof:name":"Greynite Services",
    "wof:placetype":"venue"
},
  "geometry": {"coordinates":[-84.40450800000001,33.521816],"type":"Point"}
}