{
  "type": "Feature",
  "properties": {
    "iso:country":"US",
    "sg:address":"11575 Windbrooke Way",
    "sg:city":"Alpharetta",
    "sg:classifiers":[
        {
            "category":"Shopping",
            "subcategory":"Catalog Store",
            "type":"Retail Goods"
        }
    ],
    "sg:phone":"+1 770 475 9819",
    "sg:postcode":"30005",
    "sg:province":"GA",
    "sg:tags":[
        "mail",
        "merchandise",
        "house"
    ],
    "wof:name":"Quickwitt",
    "wof:placetype":"venue"
},
  "geometry": {"coordinates":[-84.19714500000001,34.065712],"type":"Point"}
}