{
  "type": "Feature",
  "properties": {
    "iso:country":"US",
    "sg:address":"4300 Peachtree Rd NE",
    "sg:city":"Atlanta",
    "sg:classifiers":[
        {
            "category":"Retail",
            "subcategory":"Auto Rental",
            "type":"Services"
        },
        {
            "category":"Building & Trades",
            "subcategory":"Equipment Rental",
            "type":"Services"
        },
        {
            "category":"Retail",
            "subcategory":"Storage",
            "type":"Services"
        }
    ],
    "sg:phone":"+1 404 816 7455",
    "sg:postcode":"30319",
    "sg:province":"GA",
    "sg:tags":[
        "renting",
        "moving-self",
        "van",
        "truck",
        "moving",
        "leasing",
        "trailer"
    ],
    "sg:website":"http://www.ryder.com/",
    "wof:name":"Ryder",
    "wof:placetype":"venue"
},
  "geometry": {"coordinates":[-84.334845,33.868461],"type":"Point"}
}