{
  "type": "Feature",
  "properties": {
    "iso:country":"US",
    "sg:address":"145 15th St NW Ste 1008",
    "sg:city":"Atlanta",
    "sg:classifiers":[
        {
            "category":"Professional",
            "subcategory":"Art Services",
            "type":"Services"
        }
    ],
    "sg:phone":"+1 404 355 3442",
    "sg:postcode":"30318",
    "sg:province":"GA",
    "sg:tags":[
        "graphic",
        "commercial",
        "designer",
        "artist"
    ],
    "wof:name":"Graphic Center Inc",
    "wof:placetype":"venue"
},
  "geometry": {"coordinates":[-84.393529,33.788728],"type":"Point"}
}