{
  "type": "Feature",
  "properties": {
    "addr:full":"4192 McClatchey Cir NE Atlanta GA 30342",
    "addr:housenumber":"4192",
    "addr:postcode":"30342",
    "addr:street":"Mcclatchey Cir Ne",
    "iso:country":"US",
    "sg:address":"4192 McClatchey Cir NE",
    "sg:city":"Atlanta",
    "sg:classifiers":[
        {
            "category":"Building & Trades",
            "subcategory":"Construction",
            "type":"Services"
        }
    ],
    "sg:phone":"+1 404 705 9302",
    "sg:postcode":"30342",
    "sg:province":"GA",
    "sg:tags":[
        "house"
    ],
    "wof:name":"McClure Construction Co Inc",
    "wof:placetype":"venue"
},
  "geometry": {"coordinates":[-84.367611,33.870442],"type":"Point"}
}