{
  "type": "Feature",
  "properties": {
    "addr:full":"235 Greencastle Rd Tyrone GA 30290",
    "addr:housenumber":"235",
    "addr:postcode":"30290",
    "addr:street":"Greencastle Rd",
    "iso:country":"US",
    "sg:address":"235 Greencastle Rd",
    "sg:city":"Tyrone",
    "sg:classifiers":[
        {
            "category":"Professional",
            "subcategory":"Management & Consulting",
            "type":"Services"
        },
        {
            "category":"Banks & Credit Unions",
            "subcategory":"Investment Brokerage",
            "type":"Services"
        },
        {
            "category":"Banks & Credit Unions",
            "subcategory":"Financial Services",
            "type":"Services"
        }
    ],
    "sg:phone":"+1 678 364 1959",
    "sg:postcode":"30290",
    "sg:province":"GA",
    "sg:tags":[
        "planning",
        "advisory",
        "financing",
        "planner",
        "consultant"
    ],
    "wof:name":"Peachtree Planning Corp",
    "wof:placetype":"venue"
},
  "geometry": {"coordinates":[-84.590366,33.449235],"type":"Point"}
}