{
  "type": "Feature",
  "properties": {
    "iso:country":"US",
    "sg:address":"1329 Heidt Ave",
    "sg:city":"Savannah",
    "sg:classifiers":[
        {
            "category":"Building & Trades",
            "subcategory":"Landscaping Services",
            "type":"Services"
        }
    ],
    "sg:phone":"+1 912 963 1196",
    "sg:postcode":"31408",
    "sg:province":"GA",
    "sg:tags":[
        "lawn",
        "maintenance",
        "grounds"
    ],
    "sg:website":"www.tidewater-lm.com",
    "wof:name":"Tidewater Landscape Solutions",
    "wof:placetype":"venue"
},
  "geometry": {"coordinates":[-81.157809,32.0909],"type":"Point"}
}