{
  "type": "Feature",
  "properties": {
    "iso:country":"US",
    "sg:address":"2696 Treadway Dr",
    "sg:city":"Decatur",
    "sg:classifiers":[
        {
            "category":"Professional",
            "type":"Services"
        }
    ],
    "sg:phone":"+1 404 246 8664",
    "sg:postcode":"30034",
    "sg:province":"GA",
    "wof:name":"Buy Faith Svc",
    "wof:placetype":"venue"
},
  "geometry": {"coordinates":[-84.203925,33.706176],"type":"Point"}
}