{
  "type": "Feature",
  "properties": {
    "iso:country":"US",
    "sg:address":"3285 New Hope Rd",
    "sg:city":"Dawson",
    "sg:classifiers":[
        {
            "category":"Professional",
            "type":"Services"
        }
    ],
    "sg:phone":"+1 229 995 3845",
    "sg:postcode":"39842",
    "sg:province":"GA",
    "wof:name":"Dorothy Ward",
    "wof:placetype":"venue"
},
  "geometry": {"coordinates":[-84.47506199999999,31.713237],"type":"Point"}
}