{
  "type": "Feature",
  "properties": {
    "iso:country":"US",
    "sg:address":"1266 Logan Cir NW",
    "sg:city":"Atlanta",
    "sg:classifiers":[
        {
            "category":"Shopping",
            "subcategory":"Stationery & Office Supplies",
            "type":"Retail Goods"
        },
        {
            "category":"Wholesale",
            "subcategory":"Office Equipment",
            "type":"Manufacturing & Wholesale Goods"
        }
    ],
    "sg:phone":"+1 404 352 1441",
    "sg:postcode":"30318",
    "sg:province":"GA",
    "sg:tags":[
        "equipment-installation",
        "furniture"
    ],
    "wof:name":"Office Installations",
    "wof:placetype":"venue"
},
  "geometry": {"coordinates":[-84.429306,33.805421],"type":"Point"}
}