{
  "type": "Feature",
  "properties": {
    "addr:full":"630 Old Waynesville Rd Jesup GA 31546",
    "addr:housenumber":"630",
    "addr:postcode":"31546",
    "addr:street":"Old Waynesville Rd",
    "iso:country":"US",
    "sg:address":"630 Old Waynesville Rd",
    "sg:city":"Jesup",
    "sg:classifiers":[
        {
            "category":"Professional",
            "subcategory":"Computer Services",
            "type":"Services"
        }
    ],
    "sg:phone":"+1 912 427 0159",
    "sg:postcode":"31546",
    "sg:province":"GA",
    "sg:tags":[
        "programing",
        "custom"
    ],
    "wof:name":"Insource Software Solutions",
    "wof:placetype":"venue"
},
  "geometry": {"coordinates":[-81.88218000000001,31.588986],"type":"Point"}
}