{
  "type": "Feature",
  "properties": {
    "addr:full":"5107 Oak St Eastman GA 31023",
    "addr:housenumber":"5107",
    "addr:postcode":"31023",
    "addr:street":"Oak St",
    "iso:country":"US",
    "sg:address":"5107 Oak St",
    "sg:city":"Eastman",
    "sg:classifiers":[
        {
            "category":"Organizations",
            "subcategory":"Religious Organization",
            "type":"Services"
        }
    ],
    "sg:phone":"+1 478 374 5427",
    "sg:postcode":"31023",
    "sg:province":"GA",
    "sg:tags":[
        "church"
    ],
    "wof:name":"First Baptist Church Inc",
    "wof:placetype":"venue"
},
  "geometry": {"coordinates":[-83.18013500000001,32.199022],"type":"Point"}
}