{
  "type": "Feature",
  "properties": {
    "iso:country":"US",
    "sg:address":"205 Mill St",
    "sg:city":"Bowdon",
    "sg:classifiers":[
        {
            "category":"Organizations",
            "subcategory":"Religious Organization",
            "type":"Services"
        }
    ],
    "sg:phone":"+1 770 258 3967",
    "sg:postcode":"30108",
    "sg:province":"GA",
    "sg:tags":[
        "church"
    ],
    "wof:name":"Bowdon Baptist Church",
    "wof:placetype":"venue"
},
  "geometry": {"coordinates":[-85.256596,33.53913],"type":"Point"}
}