{
  "type": "Feature",
  "properties": {
    "iso:country":"US",
    "sg:address":"137 Birchwood Pass",
    "sg:city":"Canton",
    "sg:classifiers":[
        {
            "category":"Professional",
            "type":"Services"
        }
    ],
    "sg:phone":"+1 770 704 0383",
    "sg:postcode":"30114",
    "sg:province":"GA",
    "wof:name":"Julia",
    "wof:placetype":"venue"
},
  "geometry": {"coordinates":[-84.562721,34.179781],"type":"Point"}
}