{
  "type": "Feature",
  "properties": {
    "iso:country":"US",
    "sg:address":"122 Lakes Blvd",
    "sg:city":"Lake Park",
    "sg:classifiers":[
        {
            "category":"Shopping",
            "subcategory":"Computers & Home Electronics",
            "type":"Retail Goods"
        }
    ],
    "sg:phone":"+1 229 559 7161",
    "sg:postcode":"31636",
    "sg:province":"GA",
    "wof:name":"R & R Satellite Co",
    "wof:placetype":"venue"
},
  "geometry": {"coordinates":[-83.19953700000001,30.686904],"type":"Point"}
}