{
  "type": "Feature",
  "properties": {
    "addr:full":"611 E Adair St Valdosta GA 31601",
    "addr:housenumber":"611",
    "addr:postcode":"31601",
    "addr:street":"E Adair St",
    "iso:country":"US",
    "sg:address":"611 E Adair St",
    "sg:city":"Valdosta",
    "sg:classifiers":[
        {
            "category":"Professional",
            "subcategory":"Business Services",
            "type":"Services"
        }
    ],
    "sg:phone":"+1 229 242 4328",
    "sg:postcode":"31601",
    "sg:province":"GA",
    "wof:name":"CNA Insurance",
    "wof:placetype":"venue"
},
  "geometry": {"coordinates":[-83.27296699999999,30.83952],"type":"Point"}
}