{
  "type": "Feature",
  "properties": {
    "addr:full":"3753 New MacLand Rd Powder Springs GA 30127",
    "addr:housenumber":"3753",
    "addr:postcode":"30127",
    "addr:street":"New Macland Rd",
    "iso:country":"US",
    "sg:address":"3753 New MacLand Rd",
    "sg:city":"Powder Springs",
    "sg:classifiers":[
        {
            "category":"Banks & Credit Unions",
            "subcategory":"Bank",
            "type":"Services"
        },
        {
            "category":"Banks & Credit Unions",
            "subcategory":"Financial Services",
            "type":"Services"
        }
    ],
    "sg:phone":"+1 770 439 4095",
    "sg:postcode":"30127",
    "sg:province":"GA",
    "sg:tags":[
        "broker",
        "mortgage"
    ],
    "wof:name":"Washington Mutual",
    "wof:placetype":"venue"
},
  "geometry": {"coordinates":[-84.675499,33.862301],"type":"Point"}
}