{
  "type": "Feature",
  "properties": {
    "addr:full":"5905 Houston Rd Macon GA 31216",
    "addr:housenumber":"5905",
    "addr:postcode":"31216",
    "addr:street":"Houston Rd",
    "iso:country":"US",
    "sg:address":"5905 Houston Rd",
    "sg:city":"Macon",
    "sg:classifiers":[
        {
            "category":"Social Services",
            "subcategory":"Child Care",
            "type":"Services"
        }
    ],
    "sg:phone":"+1 478 781 8532",
    "sg:postcode":"31216",
    "sg:province":"GA",
    "sg:tags":[
        "day"
    ],
    "wof:name":"Childrens Friend 28",
    "wof:placetype":"venue"
},
  "geometry": {"coordinates":[-83.67682600000001,32.737942],"type":"Point"}
}