{
  "type": "Feature",
  "properties": {
    "addr:full":"5846 Hwy 20 SE Cartersville GA 30121",
    "addr:housenumber":"5846",
    "addr:postcode":"30121",
    "addr:street":"Hwy 20 Se",
    "iso:country":"US",
    "sg:address":"5846 Hwy 20 SE",
    "sg:city":"Cartersville",
    "sg:classifiers":[
        {
            "category":"Food & Beverages",
            "subcategory":"Groceries & Convenience Stores",
            "type":"Retail Goods"
        }
    ],
    "sg:phone":"+1 678 986 5502",
    "sg:postcode":"30121",
    "sg:province":"GA",
    "wof:name":"ATL Home Pro",
    "wof:placetype":"venue"
},
  "geometry": {"coordinates":[-84.737521,34.219524],"type":"Point"}
}