{
  "type": "Feature",
  "properties": {
    "iso:country":"US",
    "sg:address":"214 Capitol Ave SE",
    "sg:city":"Atlanta",
    "sg:classifiers":[
        {
            "category":"Government",
            "subcategory":"Police Station",
            "type":"Public Place"
        }
    ],
    "sg:phone":"+1 404 656 3281",
    "sg:postcode":"30312",
    "sg:province":"GA",
    "sg:tags":[
        "state"
    ],
    "wof:name":"George State Patrol Capitol Po",
    "wof:placetype":"venue"
},
  "geometry": {"coordinates":[-84.38760000000001,33.748358],"type":"Point"}
}