{
  "type": "Feature",
  "properties": {
    "addr:full":"1757 Bristol Farms Ct Grayson GA 30017",
    "addr:housenumber":"1757",
    "addr:postcode":"30017",
    "addr:street":"Bristol Farms Ct",
    "iso:country":"US",
    "sg:address":"1757 Bristol Farms Ct",
    "sg:city":"Grayson",
    "sg:classifiers":[
        {
            "category":"Shopping",
            "subcategory":"Crafts & Fabrics",
            "type":"Retail Goods"
        }
    ],
    "sg:phone":"+1 770 985 8488",
    "sg:postcode":"30017",
    "sg:province":"GA",
    "sg:tags":[
        "sewing"
    ],
    "wof:name":"Village Quilt Shop",
    "wof:placetype":"venue"
},
  "geometry": {"coordinates":[-83.99157599999999,33.889637],"type":"Point"}
}