{
  "type": "Feature",
  "properties": {
    "addr:full":"5085 Morton Ferry Cir Alpharetta GA 30022",
    "addr:housenumber":"5085",
    "addr:postcode":"30022",
    "addr:street":"Morton Ferry Cir",
    "iso:country":"US",
    "sg:address":"5085 Morton Ferry Cir",
    "sg:city":"Alpharetta",
    "sg:classifiers":[
        {
            "category":"Travel",
            "subcategory":"Travel Agent",
            "type":"Entertainment"
        }
    ],
    "sg:phone":"+1 770 664 9010",
    "sg:postcode":"30022",
    "sg:province":"GA",
    "sg:tags":[
        "agency",
        "services-commercial"
    ],
    "sg:website":"http://www.cruiseone.com",
    "wof:name":"Cruise For Funds",
    "wof:placetype":"venue"
},
  "geometry": {"coordinates":[-84.211232,34.041088],"type":"Point"}
}