{
  "type": "Feature",
  "properties": {
    "iso:country":"US",
    "sg:address":"4130 Saint Marys Rd",
    "sg:city":"Columbus",
    "sg:classifiers":[
        {
            "category":"Personal",
            "subcategory":"Beauty Salon",
            "type":"Services"
        }
    ],
    "sg:phone":"+1 706 507 0294",
    "sg:postcode":"31907",
    "sg:province":"GA",
    "wof:name":"Toss It Up Hair Design",
    "wof:placetype":"venue"
},
  "geometry": {"coordinates":[-84.919179,32.443568],"type":"Point"}
}