{
  "type": "Feature",
  "properties": {
    "addr:full":"3133 Watson Blvd Warner Robins GA 31093",
    "addr:housenumber":"3133",
    "addr:postcode":"31093",
    "addr:street":"Watson Blvd",
    "iso:country":"US",
    "sg:address":"3133 Watson Blvd",
    "sg:city":"Warner Robins",
    "sg:classifiers":[
        {
            "category":"Restaurant",
            "type":"Food & Drink"
        }
    ],
    "sg:phone":"+1 478 971 4775",
    "sg:postcode":"31093",
    "sg:province":"GA",
    "sg:website":"www.mcdonalds.com",
    "wof:name":"McDonald's",
    "wof:placetype":"venue"
},
  "geometry": {"coordinates":[-83.695761,32.61626],"type":"Point"}
}