{
  "type": "Feature",
  "properties": {
    "addr:full":"4851 Georgia Highway 85 Forest Park GA 30297",
    "addr:housenumber":"4851",
    "addr:postcode":"30297",
    "addr:street":"Georgia Highway 85;Park",
    "iso:country":"US",
    "sg:address":"4851 Georgia Highway 85",
    "sg:city":"Forest Park",
    "sg:classifiers":[
        {
            "category":"Building & Trades",
            "subcategory":"Plumbing",
            "type":"Services"
        }
    ],
    "sg:phone":"+1 404 761 9798",
    "sg:postcode":"30297",
    "sg:province":"GA",
    "wof:name":"John Raulins Pipeline Cleaning",
    "wof:placetype":"venue"
},
  "geometry": {"coordinates":[-84.402603,33.621899],"type":"Point"}
}