{
  "type": "Feature",
  "properties": {
    "addr:full":"207 E Emory St Dalton GA 30721",
    "addr:housenumber":"207",
    "addr:postcode":"30721",
    "addr:street":"E Emory St",
    "iso:country":"US",
    "sg:address":"207 E Emory St",
    "sg:city":"Dalton",
    "sg:classifiers":[
        {
            "category":"Manufacturing",
            "subcategory":"Chemicals & Compounds",
            "type":"Manufacturing & Wholesale Goods"
        }
    ],
    "sg:phone":"+1 706 226 0610",
    "sg:postcode":"30721",
    "sg:province":"GA",
    "sg:tags":[
        "adhesive",
        "sealant"
    ],
    "sg:website":"www.aatglue.com",
    "wof:name":"Advanced Adhesive Technology",
    "wof:placetype":"venue"
},
  "geometry": {"coordinates":[-84.967297,34.766051],"type":"Point"}
}