{
  "type": "Feature",
  "properties": {
    "addr:full":"2575 Peachtree Road NE Atlanta GA 30305",
    "addr:housenumber":"2575",
    "addr:postcode":"30305",
    "addr:street":"Peachtree Road Ne",
    "iso:country":"US",
    "sg:address":"2575 Peachtree Road NE",
    "sg:city":"Atlanta",
    "sg:classifiers":[
        {
            "category":"Building & Trades",
            "subcategory":"Construction",
            "type":"Services"
        }
    ],
    "sg:phone":"+1 404 364 0393",
    "sg:postcode":"30305",
    "sg:province":"GA",
    "sg:tags":[
        "interior",
        "design"
    ],
    "wof:name":"Fincher Bettye Interiors",
    "wof:placetype":"venue"
},
  "geometry": {"coordinates":[-84.387416,33.824855],"type":"Point"}
}