{
  "type": "Feature",
  "properties": {
    "addr:full":"3055 Bolling Way NE Atlanta GA 30305",
    "addr:housenumber":"3055",
    "addr:postcode":"30305",
    "addr:street":"Bolling Way Ne",
    "iso:country":"US",
    "sg:address":"3055 Bolling Way NE",
    "sg:city":"Atlanta",
    "sg:classifiers":[
        {
            "category":"Restaurant",
            "type":"Food & Drink"
        }
    ],
    "sg:phone":"+1 404 264 0135",
    "sg:postcode":"30305",
    "sg:province":"GA",
    "sg:tags":[
        "pizza"
    ],
    "wof:name":"Jack Rabbit Lounge",
    "wof:placetype":"venue"
},
  "geometry": {"coordinates":[-84.37960099999999,33.838299],"type":"Point"}
}