{
  "type": "Feature",
  "properties": {
    "iso:country":"US",
    "sg:address":"2951 Hwy 212",
    "sg:city":"Covington",
    "sg:classifiers":[
        {
            "category":"Freight",
            "type":"Transportation"
        }
    ],
    "sg:phone":"+1 770 788 9729",
    "sg:postcode":"30016",
    "sg:province":"GA",
    "sg:tags":[
        "courier"
    ],
    "wof:name":"BDS Inc",
    "wof:placetype":"venue"
},
  "geometry": {"coordinates":[-83.919259,33.467456],"type":"Point"}
}