{
  "type": "Feature",
  "properties": {
    "iso:country":"US",
    "sg:address":"211 Industrial Blvd",
    "sg:city":"Thomasville",
    "sg:classifiers":[
        {
            "category":"Banks & Credit Unions",
            "subcategory":"Investment Brokerage",
            "type":"Services"
        }
    ],
    "sg:phone":"+1 229 985 0203",
    "sg:postcode":"31792",
    "sg:province":"GA",
    "sg:tags":[
        "commodity"
    ],
    "wof:name":"Southeast Commodities Corp",
    "wof:placetype":"venue"
},
  "geometry": {"coordinates":[-83.996938,30.825512],"type":"Point"}
}