{
  "type": "Feature",
  "properties": {
    "addr:full":"5171 Eisenhower Pkwy Macon GA 31206",
    "addr:housenumber":"5171",
    "addr:postcode":"31206",
    "addr:street":"Eisenhower Pkwy",
    "iso:country":"US",
    "sg:address":"5171 Eisenhower Pkwy",
    "sg:city":"Macon",
    "sg:classifiers":[
        {
            "category":"Professional",
            "type":"Services"
        },
        {
            "category":"Professional",
            "subcategory":"Advertising",
            "type":"Services"
        }
    ],
    "sg:phone":"+1 478 471 4381",
    "sg:postcode":"31206",
    "sg:province":"GA",
    "sg:tags":[
        "product",
        "fair",
        "trade",
        "exposition",
        "advertising-promotional",
        "shows"
    ],
    "sg:website":"http://www.edgarhospitality.com",
    "wof:name":"Anderson Conference Center",
    "wof:placetype":"venue"
},
  "geometry": {"coordinates":[-83.731706,32.806262],"type":"Point"}
}