{
  "type": "Feature",
  "properties": {
    "iso:country":"US",
    "sg:address":"2896 Co Rd 117",
    "sg:city":"Cadwell",
    "sg:classifiers":[
        {
            "category":"Personal",
            "subcategory":"Beauty Salon",
            "type":"Services"
        }
    ],
    "sg:phone":"+1 478 689 4296",
    "sg:postcode":"31009",
    "sg:province":"GA",
    "sg:tags":[
        "shop"
    ],
    "wof:name":"Dianne's Beauty Shop",
    "wof:placetype":"venue"
},
  "geometry": {"coordinates":[-83.04188499999999,32.339612],"type":"Point"}
}