{
  "type": "Feature",
  "properties": {
    "iso:country":"US",
    "sg:address":"6480 Roswell Rd",
    "sg:city":"Atlanta",
    "sg:classifiers":[
        {
            "category":"Professional",
            "type":"Services"
        }
    ],
    "sg:phone":"+1 404 267 1869",
    "sg:postcode":"30328",
    "sg:province":"GA",
    "wof:name":"Mt Gold",
    "wof:placetype":"venue"
},
  "geometry": {"coordinates":[-84.379622,33.934664],"type":"Point"}
}