{
  "type": "Feature",
  "properties": {
    "addr:full":"1755 Richard Dr Cochran GA 31014",
    "addr:housenumber":"1755",
    "addr:postcode":"31014",
    "addr:street":"Richard Dr",
    "iso:country":"US",
    "sg:address":"1755 Richard Dr",
    "sg:city":"Cochran",
    "sg:classifiers":[
        {
            "category":"Building & Trades",
            "subcategory":"Plumbing",
            "type":"Services"
        }
    ],
    "sg:phone":"+1 478 934 4415",
    "sg:postcode":"31014",
    "sg:province":"GA",
    "sg:tags":[
        "contracting",
        "electrical"
    ],
    "wof:name":"Purser Electric Inc",
    "wof:placetype":"venue"
},
  "geometry": {"coordinates":[-83.329543,32.394139],"type":"Point"}
}