{
  "type": "Feature",
  "properties": {
    "addr:full":"3951 Wedgefield Cir Decatur GA 30035",
    "addr:housenumber":"3951",
    "addr:postcode":"30035",
    "addr:street":"Wedgefield Cir",
    "iso:country":"US",
    "sg:address":"3951 Wedgefield Cir",
    "sg:city":"Decatur",
    "sg:classifiers":[
        {
            "category":"Building & Trades",
            "subcategory":"Cleaning & Sanitation",
            "type":"Services"
        }
    ],
    "sg:phone":"+1 404 284 9470",
    "sg:postcode":"30035",
    "sg:province":"GA",
    "sg:tags":[
        "maintenance"
    ],
    "wof:name":"South Star Cleaning Service",
    "wof:placetype":"venue"
},
  "geometry": {"coordinates":[-84.22830500000001,33.727165],"type":"Point"}
}