{
  "type": "Feature",
  "properties": {
    "iso:country":"US",
    "sg:address":"330 Drayton St",
    "sg:city":"Savannah",
    "sg:classifiers":[
        {
            "category":"Recreation",
            "type":"Entertainment"
        },
        {
            "category":"Shopping",
            "subcategory":"Gifts & Souvenirs",
            "type":"Retail Goods"
        }
    ],
    "sg:phone":"+1 912 232 8200",
    "sg:postcode":"31401",
    "sg:province":"GA",
    "sg:tags":[
        "amusement"
    ],
    "wof:name":"Girl Scout First Headquarters",
    "wof:placetype":"venue"
},
  "geometry": {"coordinates":[-81.09286,32.073012],"type":"Point"}
}