{
  "type": "Feature",
  "properties": {
    "iso:country":"US",
    "sg:address":"10525 Commerce St",
    "sg:city":"Summerville",
    "sg:classifiers":[
        {
            "category":"Shopping",
            "subcategory":"Hobbies, Toys, & Games",
            "type":"Retail Goods"
        }
    ],
    "sg:phone":"+1 706 857 7901",
    "sg:postcode":"30747",
    "sg:province":"GA",
    "wof:name":"Dolls Galore",
    "wof:placetype":"venue"
},
  "geometry": {"coordinates":[-85.34417000000001,34.48594],"type":"Point"}
}