{
  "type": "Feature",
  "properties": {
    "addr:full":"265 Della Glass Rd Smithville GA 31787",
    "addr:housenumber":"265",
    "addr:postcode":"31787",
    "addr:street":"Della Glass Rd",
    "iso:country":"US",
    "sg:address":"265 Della Glass Rd",
    "sg:city":"Smithville",
    "sg:classifiers":[
        {
            "category":"Farming",
            "subcategory":"Farm",
            "type":"Manufacturing & Wholesale Goods"
        }
    ],
    "sg:phone":"+1 229 846 8868",
    "sg:postcode":"31787",
    "sg:province":"GA",
    "sg:tags":[
        "crop",
        "general"
    ],
    "wof:name":"Hal Israel",
    "wof:placetype":"venue"
},
  "geometry": {"coordinates":[-84.29839699999999,31.924307],"type":"Point"}
}