{
  "type": "Feature",
  "properties": {
    "iso:country":"US",
    "sg:address":"5950 Jonesboro Rd",
    "sg:city":"Morrow",
    "sg:classifiers":[
        {
            "category":"Retail",
            "subcategory":"Repair Shop",
            "type":"Services"
        }
    ],
    "sg:phone":"+1 404 363 1302",
    "sg:postcode":"30260",
    "sg:province":"GA",
    "sg:tags":[
        "reupholstery",
        "furniture"
    ],
    "wof:name":"Autocraft Upholstery Co",
    "wof:placetype":"venue"
},
  "geometry": {"coordinates":[-84.3377,33.596199],"type":"Point"}
}