{
  "type": "Feature",
  "properties": {
    "addr:full":"3870 Lawrenceville Hwy NW Atlanta GA 30303",
    "addr:postcode":"3870;30303",
    "addr:street":"Lawrenceville Hwy Nw",
    "iso:country":"US",
    "sg:address":"3870 Lawrenceville Hwy NW",
    "sg:city":"Atlanta",
    "sg:classifiers":[
        {
            "category":"Restaurant",
            "type":"Food & Drink"
        }
    ],
    "sg:phone":"+1 770 564 2811",
    "sg:postcode":"30303",
    "sg:province":"GA",
    "sg:tags":[
        "chinese"
    ],
    "wof:name":"Bobo China Restaurant",
    "wof:placetype":"venue"
},
  "geometry": {"coordinates":[-84.39070100000001,33.756302],"type":"Point"}
}