{
  "type": "Feature",
  "properties": {
    "iso:country":"US",
    "sg:address":"47 State Hwy 138",
    "sg:city":"Riverdale",
    "sg:classifiers":[
        {
            "category":"Personal",
            "subcategory":"Beauty Salon",
            "type":"Services"
        }
    ],
    "sg:phone":"+1 678 479 9000",
    "sg:postcode":"30274",
    "sg:province":"GA",
    "wof:name":"Dooley Does It Beauty & Barber",
    "wof:placetype":"venue"
},
  "geometry": {"coordinates":[-84.394603,33.542056],"type":"Point"}
}