{
  "type": "Feature",
  "properties": {
    "iso:country":"US",
    "sg:address":"415 Morgan Falls Rd",
    "sg:city":"Atlanta",
    "sg:classifiers":[
        {
            "category":"Personal",
            "subcategory":"Massage",
            "type":"Services"
        }
    ],
    "sg:phone":"+1 678 886 1133",
    "sg:postcode":"30350",
    "sg:province":"GA",
    "sg:tags":[
        "therapist"
    ],
    "wof:name":"Aaaah Massage",
    "wof:placetype":"venue"
},
  "geometry": {"coordinates":[-84.37989399999999,33.970058],"type":"Point"}
}