{
  "type": "Feature",
  "properties": {
    "addr:full":"127 Temple Ave W Newnan GA 30263",
    "addr:housenumber":"127",
    "addr:postcode":"30263",
    "addr:street":"Temple Ave W",
    "iso:country":"US",
    "sg:address":"127 Temple Ave W",
    "sg:city":"Newnan",
    "sg:classifiers":[
        {
            "category":"Insurance",
            "subcategory":"Insurance Agent",
            "type":"Services"
        }
    ],
    "sg:phone":"+1 770 253 2341",
    "sg:postcode":"30263",
    "sg:province":"GA",
    "wof:name":"Williams Insurance & Realty",
    "wof:placetype":"venue"
},
  "geometry": {"coordinates":[-84.811465,33.38141],"type":"Point"}
}