{
  "type": "Feature",
  "properties": {
    "addr:full":"105 Baybrook St Thomasville GA 31792",
    "addr:housenumber":"105",
    "addr:postcode":"31792",
    "addr:street":"Baybrook St",
    "iso:country":"US",
    "sg:address":"105 Baybrook St",
    "sg:city":"Thomasville",
    "sg:classifiers":[
        {
            "category":"Home & Garden",
            "subcategory":"Furniture",
            "type":"Retail Goods"
        }
    ],
    "sg:phone":"+1 229 228 0099",
    "sg:postcode":"31792",
    "sg:province":"GA",
    "sg:website":"www.thomasvillehome.com",
    "wof:name":"Thomasville Home Furnishings",
    "wof:placetype":"venue"
},
  "geometry": {"coordinates":[-83.96393500000001,30.83421],"type":"Point"}
}