{
  "type": "Feature",
  "properties": {
    "addr:full":"1437 Roswell Rd Marietta GA 30062",
    "addr:housenumber":"1437",
    "addr:postcode":"30062",
    "addr:street":"Roswell Rd",
    "iso:country":"US",
    "sg:address":"1437 Roswell Rd",
    "sg:city":"Marietta",
    "sg:classifiers":[
        {
            "category":"Shopping",
            "subcategory":"Discount & Variety Stores",
            "type":"Retail Goods"
        }
    ],
    "sg:phone":"+1 770 565 0048",
    "sg:postcode":"30062",
    "sg:province":"GA",
    "wof:name":"Dollar General",
    "wof:placetype":"venue"
},
  "geometry": {"coordinates":[-84.510521,33.950864],"type":"Point"}
}