{
  "type": "Feature",
  "properties": {
    "addr:full":"2024 Atha Woods Dr Monroe GA 30655",
    "addr:housenumber":"2024",
    "addr:postcode":"30655",
    "addr:street":"Atha Woods Dr",
    "iso:country":"US",
    "sg:address":"2024 Atha Woods Dr",
    "sg:city":"Monroe",
    "sg:classifiers":[
        {
            "category":"Professional",
            "subcategory":"Business Services",
            "type":"Services"
        }
    ],
    "sg:phone":"+1 770 267 5168",
    "sg:postcode":"30655",
    "sg:province":"GA",
    "wof:name":"Refrigeration Equipment Sales",
    "wof:placetype":"venue"
},
  "geometry": {"coordinates":[-83.79497600000001,33.792302],"type":"Point"}
}