{
  "type": "Feature",
  "properties": {
    "addr:full":"1112 Pontiac Cir Austell GA 30168",
    "addr:housenumber":"1112",
    "addr:postcode":"30168",
    "addr:street":"Pontiac Cir",
    "iso:country":"US",
    "sg:address":"1112 Pontiac Cir",
    "sg:city":"Austell",
    "sg:classifiers":[
        {
            "category":"Building & Trades",
            "subcategory":"Cleaning & Sanitation",
            "type":"Services"
        }
    ],
    "sg:phone":"+1 678 464 5443",
    "sg:postcode":"30168",
    "sg:province":"GA",
    "sg:tags":[
        "window"
    ],
    "wof:name":"Pro Window Cleaning",
    "wof:placetype":"venue"
},
  "geometry": {"coordinates":[-84.622416,33.808017],"type":"Point"}
}