{
  "type": "Feature",
  "properties": {
    "addr:full":"5040 Doubletree Dr Cumming GA 30040",
    "addr:housenumber":"5040",
    "addr:postcode":"30040",
    "addr:street":"Doubletree Dr",
    "iso:country":"US",
    "sg:address":"5040 Doubletree Dr",
    "sg:city":"Cumming",
    "sg:classifiers":[
        {
            "category":"Professional",
            "type":"Services"
        }
    ],
    "sg:phone":"+1 678 947 5271",
    "sg:postcode":"30040",
    "sg:province":"GA",
    "sg:tags":[
        "camps-recreational"
    ],
    "wof:name":"Alan Camp Inc",
    "wof:placetype":"venue"
},
  "geometry": {"coordinates":[-84.212513,34.214994],"type":"Point"}
}