{
  "type": "Feature",
  "properties": {
    "iso:country":"US",
    "sg:address":"5409 Winding Glen Dr",
    "sg:city":"Lithonia",
    "sg:classifiers":[
        {
            "category":"Professional",
            "subcategory":"Business Services",
            "type":"Services"
        }
    ],
    "sg:phone":"+1 770 323 2644",
    "sg:postcode":"30038",
    "sg:province":"GA",
    "wof:name":"Ashco Enterprises",
    "wof:placetype":"venue"
},
  "geometry": {"coordinates":[-84.17638599999999,33.698673],"type":"Point"}
}