{
  "type": "Feature",
  "properties": {
    "addr:full":"328 Legacy Oaks Cir Roswell GA 30076",
    "addr:housenumber":"328",
    "addr:postcode":"30076",
    "addr:street":"Legacy Oaks Cir",
    "iso:country":"US",
    "sg:address":"328 Legacy Oaks Cir",
    "sg:city":"Roswell",
    "sg:classifiers":[
        {
            "category":"Professional",
            "subcategory":"Printing & Photocopies",
            "type":"Services"
        }
    ],
    "sg:phone":"+1 770 645 7776",
    "sg:postcode":"30076",
    "sg:province":"GA",
    "sg:tags":[
        "medal",
        "plaque",
        "trophies"
    ],
    "wof:name":"Alleventstrophy.Com",
    "wof:placetype":"venue"
},
  "geometry": {"coordinates":[-84.335617,34.039028],"type":"Point"}
}