{
  "type": "Feature",
  "properties": {
    "addr:full":"5850 New Calhoun Hwy NE Rome GA 30161",
    "addr:housenumber":"5850",
    "addr:postcode":"ga 30161",
    "addr:street":"New Calhoun Hwy Ne",
    "iso:country":"US",
    "sg:address":"5850 New Calhoun Hwy NE",
    "sg:city":"Rome",
    "sg:classifiers":[
        {
            "category":"Food & Beverages",
            "subcategory":"Groceries & Convenience Stores",
            "type":"Retail Goods"
        }
    ],
    "sg:phone":"+1 706 291 4688",
    "sg:postcode":"30161",
    "sg:province":"GA",
    "wof:name":"Village Shop",
    "wof:placetype":"venue"
},
  "geometry": {"coordinates":[-85.11720099999999,34.297944],"type":"Point"}
}