{
  "type": "Feature",
  "properties": {
    "iso:country":"US",
    "sg:address":"6615 Vogue Cir",
    "sg:city":"Fairburn",
    "sg:classifiers":[
        {
            "category":"Real Estate",
            "subcategory":"Real Estate Services",
            "type":"Services"
        },
        {
            "category":"Real Estate",
            "subcategory":"Real Estate Agent",
            "type":"Services"
        }
    ],
    "sg:phone":"+1 404 273 5243",
    "sg:postcode":"30213",
    "sg:province":"GA",
    "sg:tags":[
        "management"
    ],
    "wof:name":"Tucker Real Estate Business Opportunity",
    "wof:placetype":"venue"
},
  "geometry": {"coordinates":[-84.610021,33.576827],"type":"Point"}
}