{
  "type": "Feature",
  "properties": {
    "iso:country":"US",
    "sg:address":"4072 Hickory Fairway Dr",
    "sg:city":"Woodstock",
    "sg:classifiers":[
        {
            "category":"Professional",
            "subcategory":"Management & Consulting",
            "type":"Services"
        }
    ],
    "sg:phone":"+1 770 516 5031",
    "sg:postcode":"30188",
    "sg:province":"GA",
    "sg:tags":[
        "business"
    ],
    "wof:name":"Ultra Acoustics Inc",
    "wof:placetype":"venue"
},
  "geometry": {"coordinates":[-84.442402,34.158666],"type":"Point"}
}