{
  "type": "Feature",
  "properties": {
    "addr:full":"4967 Buena Vista Rd Columbus GA 31907",
    "addr:housenumber":"4967",
    "addr:postcode":"31907",
    "addr:street":"Buena Vista Rd",
    "iso:country":"US",
    "sg:address":"4967 Buena Vista Rd",
    "sg:city":"Columbus",
    "sg:classifiers":[
        {
            "category":"Retail",
            "subcategory":"Repair Shop",
            "type":"Services"
        }
    ],
    "sg:phone":"+1 706 561 2292",
    "sg:postcode":"31907",
    "sg:province":"GA",
    "wof:name":"R & R Small Engines",
    "wof:placetype":"venue"
},
  "geometry": {"coordinates":[-84.91019300000001,32.467698],"type":"Point"}
}