{
  "type": "Feature",
  "properties": {
    "addr:full":"261 Flowing Wells Rd Augusta GA 30907",
    "addr:housenumber":"261",
    "addr:postcode":"30907",
    "addr:street":"Flowing Wells Rd",
    "iso:country":"US",
    "sg:address":"261 Flowing Wells Rd",
    "sg:city":"Augusta",
    "sg:classifiers":[
        {
            "category":"Organizations",
            "subcategory":"Religious Organization",
            "type":"Services"
        }
    ],
    "sg:phone":"+1 706 868 5982",
    "sg:postcode":"30907",
    "sg:province":"GA",
    "sg:tags":[
        "church"
    ],
    "wof:name":"Westside Baptist Church",
    "wof:placetype":"venue"
},
  "geometry": {"coordinates":[-82.10806700000001,33.499041],"type":"Point"}
}