{
  "type": "Feature",
  "properties": {
    "addr:full":"105 George St Grovetown GA 30813",
    "addr:housenumber":"105",
    "addr:postcode":"30813",
    "addr:street":"George St",
    "iso:country":"US",
    "sg:address":"105 George St",
    "sg:city":"Grovetown",
    "sg:classifiers":[
        {
            "category":"Building & Trades",
            "subcategory":"Landscaping Services",
            "type":"Services"
        }
    ],
    "sg:phone":"+1 706 651 8350",
    "sg:postcode":"30813",
    "sg:province":"GA",
    "sg:tags":[
        "tree"
    ],
    "wof:name":"Neil Blalock Tree Svc",
    "wof:placetype":"venue"
},
  "geometry": {"coordinates":[-82.18826,33.455109],"type":"Point"}
}