{
  "type": "Feature",
  "properties": {
    "iso:country":"US",
    "sg:address":"555 Louisville Rd",
    "sg:city":"Grovetown",
    "sg:classifiers":[
        {
            "category":"Professional",
            "type":"Services"
        }
    ],
    "sg:phone":"+1 706 541 9523",
    "sg:postcode":"30813",
    "sg:province":"GA",
    "wof:name":"Huttos Office Support Services",
    "wof:placetype":"venue"
},
  "geometry": {"coordinates":[-82.277687,33.495371],"type":"Point"}
}