{
  "type": "Feature",
  "properties": {
    "iso:country":"US",
    "sg:address":"199 Armour Drive NE",
    "sg:city":"Atlanta",
    "sg:classifiers":[
        {
            "category":"Retail",
            "subcategory":"Repair Shop",
            "type":"Services"
        }
    ],
    "sg:phone":"+1 404 810 9081",
    "sg:postcode":"30324",
    "sg:province":"GA",
    "sg:tags":[
        "reupholstery",
        "furniture"
    ],
    "wof:name":"Tecnosedia",
    "wof:placetype":"venue"
},
  "geometry": {"coordinates":[-84.38094599999999,33.811158],"type":"Point"}
}