{
  "type": "Feature",
  "properties": {
    "addr:full":"1042 Manchester Expy Columbus GA 31904",
    "addr:housenumber":"1042",
    "addr:postcode":"31904",
    "addr:street":"Manchester Expy",
    "iso:country":"US",
    "sg:address":"1042 Manchester Expy",
    "sg:city":"Columbus",
    "sg:classifiers":[
        {
            "category":"Education",
            "subcategory":"School",
            "type":"Public Place"
        }
    ],
    "sg:phone":"+1 706 748 2590",
    "sg:postcode":"31904",
    "sg:province":"GA",
    "sg:website":"http://www.hardawayhawks.com",
    "wof:name":"Rose Hill",
    "wof:placetype":"venue"
},
  "geometry": {"coordinates":[-84.97653,32.507094],"type":"Point"}
}