{
  "type": "Feature",
  "properties": {
    "addr:full":"1744 Kanawha Trl Stone Mountain GA 30087",
    "addr:housenumber":"1744",
    "addr:postcode":"30087",
    "addr:street":"Kanawha Trl",
    "iso:country":"US",
    "sg:address":"1744 Kanawha Trl",
    "sg:city":"Stone Mountain",
    "sg:classifiers":[
        {
            "category":"Building & Trades",
            "subcategory":"Construction",
            "type":"Services"
        }
    ],
    "sg:phone":"+1 770 491 0397",
    "sg:postcode":"30087",
    "sg:province":"GA",
    "sg:tags":[
        "interior",
        "design"
    ],
    "wof:name":"Brown Vicki L Interiors",
    "wof:placetype":"venue"
},
  "geometry": {"coordinates":[-84.173103,33.834599],"type":"Point"}
}