{
  "type": "Feature",
  "properties": {
    "iso:country":"US",
    "sg:address":"141 Railroad St",
    "sg:city":"Canton",
    "sg:classifiers":[
        {
            "category":"Real Estate",
            "subcategory":"Real Estate Services",
            "type":"Services"
        }
    ],
    "sg:phone":"+1 770 479 2141",
    "sg:postcode":"30114",
    "sg:province":"GA",
    "sg:tags":[
        "management",
        "property"
    ],
    "wof:name":"Canton Tex Mills Inc",
    "wof:placetype":"venue"
},
  "geometry": {"coordinates":[-84.49430099999999,34.235199],"type":"Point"}
}