{
  "type": "Feature",
  "properties": {
    "iso:country":"US",
    "sg:address":"118 Ruby Ln",
    "sg:city":"Dawsonville",
    "sg:classifiers":[
        {
            "category":"Professional",
            "subcategory":"Business Services",
            "type":"Services"
        }
    ],
    "sg:phone":"+1 706 216 6452",
    "sg:postcode":"30534",
    "sg:province":"GA",
    "wof:name":"Anns Classic Designs",
    "wof:placetype":"venue"
},
  "geometry": {"coordinates":[-84.018699,34.357],"type":"Point"}
}