{
  "type": "Feature",
  "properties": {
    "addr:full":"101 Twin Springs Trl Norcross GA 30093",
    "addr:housenumber":"101",
    "addr:postcode":"30093",
    "addr:street":"Twin Springs Trl",
    "iso:country":"US",
    "sg:address":"101 Twin Springs Trl",
    "sg:city":"Norcross",
    "sg:classifiers":[
        {
            "category":"Real Estate",
            "subcategory":"Real Estate Operator",
            "type":"Services"
        }
    ],
    "sg:phone":"+1 770 925 3410",
    "sg:postcode":"30093",
    "sg:province":"GA",
    "sg:tags":[
        "apartment"
    ],
    "wof:name":"Harbin Springs Apartments",
    "wof:placetype":"venue"
},
  "geometry": {"coordinates":[-84.171527,33.901784],"type":"Point"}
}