{
  "type": "Feature",
  "properties": {
    "addr:full":"2788 Long Lake Dr Roswell GA 30075",
    "addr:housenumber":"2788",
    "addr:postcode":"30075",
    "addr:street":"Long Lake Dr",
    "iso:country":"US",
    "sg:address":"2788 Long Lake Dr",
    "sg:city":"Roswell",
    "sg:classifiers":[
        {
            "category":"Professional",
            "subcategory":"Art Services",
            "type":"Services"
        }
    ],
    "sg:phone":"+1 770 645 0226",
    "sg:postcode":"30075",
    "sg:province":"GA",
    "sg:tags":[
        "photographic",
        "studio"
    ],
    "wof:name":"Ford Smith Photography Studio",
    "wof:placetype":"venue"
},
  "geometry": {"coordinates":[-84.406657,34.017212],"type":"Point"}
}