{
  "type": "Feature",
  "properties": {
    "addr:full":"1501 Regency Way Woodstock GA 30189",
    "addr:housenumber":"1501",
    "addr:postcode":"30189",
    "addr:street":"Regency Way",
    "iso:country":"US",
    "sg:address":"1501 Regency Way",
    "sg:city":"Woodstock",
    "sg:classifiers":[
        {
            "category":"Education",
            "subcategory":"Library",
            "type":"Public Place"
        }
    ],
    "sg:phone":"+1 770 591 0089",
    "sg:postcode":"30189",
    "sg:province":"GA",
    "wof:name":"Library Corp The",
    "wof:placetype":"venue"
},
  "geometry": {"coordinates":[-84.58993599999999,34.129779],"type":"Point"}
}