{
  "type": "Feature",
  "properties": {
    "iso:country":"US",
    "sg:address":"98 Riverbranch Rd",
    "sg:city":"Bloomingdale",
    "sg:classifiers":[
        {
            "category":"Professional",
            "type":"Services"
        }
    ],
    "sg:phone":"+1 912 748 2042",
    "sg:postcode":"31302",
    "sg:province":"GA",
    "wof:name":"Melba J Jones",
    "wof:placetype":"venue"
},
  "geometry": {"coordinates":[-81.39985799999999,32.120816],"type":"Point"}
}