{
  "type": "Feature",
  "properties": {
    "addr:full":"35 Pruitt Rd Alpharetta GA 30004",
    "addr:housenumber":"35",
    "addr:postcode":"30004",
    "addr:street":"Pruitt Rd",
    "iso:country":"US",
    "sg:address":"35 Pruitt Rd",
    "sg:city":"Alpharetta",
    "sg:classifiers":[
        {
            "category":"Building & Trades",
            "subcategory":"Construction",
            "type":"Services"
        }
    ],
    "sg:phone":"+1 770 886 0209",
    "sg:postcode":"30004",
    "sg:province":"GA",
    "sg:tags":[
        "painter"
    ],
    "wof:name":"Heritage Painting/Restoration",
    "wof:placetype":"venue"
},
  "geometry": {"coordinates":[-84.290871,34.203417],"type":"Point"}
}