{
  "type": "Feature",
  "properties": {
    "addr:full":"3696 Largent Way Marietta GA 30064",
    "addr:housenumber":"3696",
    "addr:postcode":"30064",
    "addr:street":"Largent Way",
    "iso:country":"US",
    "sg:address":"3696 Largent Way",
    "sg:city":"Marietta",
    "sg:classifiers":[
        {
            "category":"Banks & Credit Unions",
            "subcategory":"Investment Brokerage",
            "type":"Services"
        }
    ],
    "sg:phone":"+1 770 420 0800",
    "sg:postcode":"30064",
    "sg:province":"GA",
    "sg:tags":[
        "consultant",
        "planning",
        "financial"
    ],
    "wof:name":"Peachtree Planning",
    "wof:placetype":"venue"
},
  "geometry": {"coordinates":[-84.65889,33.953454],"type":"Point"}
}