{
  "type": "Feature",
  "properties": {
    "addr:full":"1402 Bowens Mill Rd SE Douglas GA 31533",
    "addr:housenumber":"1402",
    "addr:postcode":"31533",
    "addr:street":"Bowens Mill Rd Se",
    "iso:country":"US",
    "sg:address":"1402 Bowens Mill Rd SE",
    "sg:city":"Douglas",
    "sg:classifiers":[
        {
            "category":"Wholesale",
            "subcategory":"Machinery & Supplies",
            "type":"Manufacturing & Wholesale Goods"
        }
    ],
    "sg:phone":"+1 912 384 4989",
    "sg:postcode":"31533",
    "sg:province":"GA",
    "sg:tags":[
        "equipment",
        "establishment"
    ],
    "wof:name":"Pamelas Beauty Supply",
    "wof:placetype":"venue"
},
  "geometry": {"coordinates":[-82.83624,31.489344],"type":"Point"}
}