{
  "type": "Feature",
  "properties": {
    "iso:country":"US",
    "sg:address":"7051 High Point Rd",
    "sg:city":"Douglasville",
    "sg:classifiers":[
        {
            "category":"Building & Trades",
            "subcategory":"Landscaping Services",
            "type":"Services"
        }
    ],
    "sg:phone":"+1 770 947 0892",
    "sg:postcode":"30134",
    "sg:province":"GA",
    "sg:tags":[
        "tree",
        "trimming"
    ],
    "wof:name":"Cedar Mountain Tree Service",
    "wof:placetype":"venue"
},
  "geometry": {"coordinates":[-84.80242200000001,33.779593],"type":"Point"}
}