{
  "type": "Feature",
  "properties": {
    "addr:full":"1546 Riverstone Pkwy Canton GA 30114",
    "addr:housenumber":"1546",
    "addr:postcode":"30114",
    "addr:street":"Riverstone Pkwy",
    "iso:country":"US",
    "sg:address":"1546 Riverstone Pkwy",
    "sg:city":"Canton",
    "sg:classifiers":[
        {
            "category":"Autos & Motor Vehicles",
            "subcategory":"Fuel & Gas Station",
            "type":"Retail Goods"
        }
    ],
    "sg:phone":"+1 770 479 8719",
    "sg:postcode":"30114",
    "sg:province":"GA",
    "sg:tags":[
        "oil"
    ],
    "wof:name":"Amoco Retail",
    "wof:placetype":"venue"
},
  "geometry": {"coordinates":[-84.46427300000001,34.257614],"type":"Point"}
}