{
  "type": "Feature",
  "properties": {
    "addr:full":"1447 N Expy Griffin GA 30223",
    "addr:housenumber":"1447",
    "addr:postcode":"30223",
    "addr:street":"N Expy",
    "iso:country":"US",
    "sg:address":"1447 N Expy",
    "sg:city":"Griffin",
    "sg:classifiers":[
        {
            "category":"Sports & Exercise",
            "subcategory":"Gym",
            "type":"Entertainment"
        }
    ],
    "sg:phone":"+1 770 228 5736",
    "sg:postcode":"30223",
    "sg:province":"GA",
    "sg:tags":[
        "club",
        "health"
    ],
    "wof:name":"Racquet House Fitness Center",
    "wof:placetype":"venue"
},
  "geometry": {"coordinates":[-84.288253,33.256468],"type":"Point"}
}