{
  "type": "Feature",
  "properties": {
    "addr:full":"6525 Sugarloaf Pkwy Duluth GA 30097",
    "addr:housenumber":"6525",
    "addr:postcode":"30097",
    "addr:street":"Sugarloaf Pkwy",
    "iso:country":"US",
    "sg:address":"6525 Sugarloaf Pkwy",
    "sg:city":"Duluth",
    "sg:classifiers":[
        {
            "category":"Shopping",
            "subcategory":"Jewelry",
            "type":"Retail Goods"
        }
    ],
    "sg:phone":"+1 770 623 1800",
    "sg:postcode":"30097",
    "sg:province":"GA",
    "wof:name":"Lalique",
    "wof:placetype":"venue"
},
  "geometry": {"coordinates":[-84.09115300000001,33.995031],"type":"Point"}
}