{
  "type": "Feature",
  "properties": {
    "addr:full":"30 Technology Pkwy S Ste 400 Norcross GA 30092",
    "addr:housenumber":"30",
    "addr:postcode":"30092",
    "addr:street":"Technology Pkwy S Ste 400",
    "iso:country":"US",
    "sg:address":"30 Technology Pkwy S Ste 400",
    "sg:city":"Norcross",
    "sg:classifiers":[
        {
            "category":"Wholesale",
            "subcategory":"Computers",
            "type":"Manufacturing & Wholesale Goods"
        }
    ],
    "sg:phone":"+1 770 368 4000",
    "sg:postcode":"30092",
    "sg:province":"GA",
    "sg:website":"www.ibisinc.com",
    "wof:name":"Ibis Inc",
    "wof:placetype":"venue"
},
  "geometry": {"coordinates":[-84.216797,33.960098],"type":"Point"}
}