{
  "type": "Feature",
  "properties": {
    "iso:country":"US",
    "sg:address":"3550 Preston Ridge Rd",
    "sg:city":"Alpharetta",
    "sg:classifiers":[
        {
            "category":"Health Services",
            "subcategory":"Doctor",
            "type":"Services"
        }
    ],
    "sg:phone":"+1 404 365 0966",
    "sg:postcode":"30005",
    "sg:province":"GA",
    "wof:name":"Kaiser Permanente Health Care",
    "wof:placetype":"venue"
},
  "geometry": {"coordinates":[-84.25599699999999,34.070702],"type":"Point"}
}