{
  "type": "Feature",
  "properties": {
    "addr:full":"312 S 1st St Warner Robins GA 31088",
    "addr:housenumber":"312",
    "addr:postcode":"31088",
    "addr:street":"S 1St St",
    "iso:country":"US",
    "sg:address":"312 S 1st St",
    "sg:city":"Warner Robins",
    "sg:classifiers":[
        {
            "category":"Restaurant",
            "type":"Food & Drink"
        }
    ],
    "sg:phone":"+1 478 329 0638",
    "sg:postcode":"31088",
    "sg:province":"GA",
    "sg:tags":[
        "mexican"
    ],
    "wof:name":"Roberto's",
    "wof:placetype":"venue"
},
  "geometry": {"coordinates":[-83.599003,32.615938],"type":"Point"}
}