{
  "type": "Feature",
  "properties": {
    "iso:country":"US",
    "sg:address":"3145 Peachtree Dr NE",
    "sg:city":"Atlanta",
    "sg:classifiers":[
        {
            "category":"Shopping",
            "subcategory":"Shoes",
            "type":"Retail Goods"
        }
    ],
    "sg:phone":"+1 404 365 0746",
    "sg:postcode":"30305",
    "sg:province":"GA",
    "sg:tags":[
        "child"
    ],
    "wof:name":"Buckles Inc",
    "wof:placetype":"venue"
},
  "geometry": {"coordinates":[-84.362872,33.842756],"type":"Point"}
}