{
  "type": "Feature",
  "properties": {
    "addr:full":"3633 Washington Rd East Point GA 30344",
    "addr:housenumber":"3633",
    "addr:postcode":"30344",
    "addr:street":"Washington Rd",
    "iso:country":"US",
    "sg:address":"3633 Washington Rd",
    "sg:city":"East Point",
    "sg:classifiers":[
        {
            "category":"Building & Trades",
            "subcategory":"Locksmith",
            "type":"Services"
        }
    ],
    "sg:phone":"+1 678 271 6702",
    "sg:postcode":"30344",
    "sg:province":"GA",
    "sg:tags":[
        "key"
    ],
    "wof:name":"Always Availabla 7 Day Locksmith",
    "wof:placetype":"venue"
},
  "geometry": {"coordinates":[-84.482426,33.656221],"type":"Point"}
}