{
  "type": "Feature",
  "properties": {
    "iso:country":"US",
    "sg:address":"308 S Grimes St",
    "sg:city":"Dalton",
    "sg:classifiers":[
        {
            "category":"Restaurant",
            "type":"Food & Drink"
        }
    ],
    "sg:phone":"+1 706 271 0710",
    "sg:postcode":"30721",
    "sg:province":"GA",
    "sg:tags":[
        "parlor",
        "ice",
        "cream"
    ],
    "wof:name":"LA Reyna Paleteria",
    "wof:placetype":"venue"
},
  "geometry": {"coordinates":[-84.947282,34.76839],"type":"Point"}
}