{
  "type": "Feature",
  "properties": {
    "addr:full":"3030 Headland Dr SW Atlanta GA 30311",
    "addr:housenumber":"3030",
    "addr:postcode":"30311",
    "addr:street":"Headland Dr Sw",
    "iso:country":"US",
    "sg:address":"3030 Headland Dr SW",
    "sg:city":"Atlanta",
    "sg:classifiers":[
        {
            "category":"Restaurant",
            "type":"Food & Drink"
        }
    ],
    "sg:menulink":"http://www.allmenus.com/ga/atlanta/81676-subway/menu/",
    "sg:phone":"+1 404 349 3557",
    "sg:postcode":"30311",
    "sg:province":"GA",
    "sg:tags":[
        "american",
        "sandwich"
    ],
    "wof:name":"Subway",
    "wof:placetype":"venue"
},
  "geometry": {"coordinates":[-84.487652,33.689435],"type":"Point"}
}