{
  "type": "Feature",
  "properties": {
    "iso:country":"US",
    "sg:address":"190 Lake Cir",
    "sg:city":"Carrollton",
    "sg:classifiers":[
        {
            "category":"Building & Trades",
            "subcategory":"Construction",
            "type":"Services"
        }
    ],
    "sg:phone":"+1 770 854 7251",
    "sg:postcode":"30116",
    "sg:province":"GA",
    "sg:tags":[
        "house"
    ],
    "wof:name":"Hulsey Construction",
    "wof:placetype":"venue"
},
  "geometry": {"coordinates":[-85.05250100000001,33.452476],"type":"Point"}
}