{
  "type": "Feature",
  "properties": {
    "iso:country":"US",
    "sg:address":"1809 Chatsworth Rd",
    "sg:city":"Dalton",
    "sg:classifiers":[
        {
            "category":"Shopping",
            "subcategory":"Clothing, Apparel, & Fashions",
            "type":"Retail Goods"
        }
    ],
    "sg:phone":"+1 706 279 4373",
    "sg:postcode":"30721",
    "sg:province":"GA",
    "wof:name":"Las Chicas Boutique",
    "wof:placetype":"venue"
},
  "geometry": {"coordinates":[-84.9376,34.761164],"type":"Point"}
}