{
  "type": "Feature",
  "properties": {
    "iso:country":"US",
    "sg:address":"296 S Main St",
    "sg:city":"Alpharetta",
    "sg:classifiers":[
        {
            "category":"Social Services",
            "type":"Services"
        }
    ],
    "sg:phone":"+1 770 569 7305",
    "sg:postcode":"30004",
    "sg:province":"GA",
    "wof:name":"Rebecca G Stanfields LPC",
    "wof:placetype":"venue"
},
  "geometry": {"coordinates":[-84.29996,34.068531],"type":"Point"}
}