{
  "type": "Feature",
  "properties": {
    "iso:country":"US",
    "sg:address":"632 County Line Rd",
    "sg:city":"Cumming",
    "sg:classifiers":[
        {
            "category":"Personal",
            "subcategory":"Beauty Salon",
            "type":"Services"
        }
    ],
    "sg:phone":"+1 770 380 3407",
    "sg:postcode":"30040",
    "sg:province":"GA",
    "wof:name":"Arriviste Salon",
    "wof:placetype":"venue"
},
  "geometry": {"coordinates":[-84.26974800000001,34.214638],"type":"Point"}
}