{
  "type": "Feature",
  "properties": {
    "iso:country":"US",
    "sg:address":"33 Sloan St",
    "sg:city":"Roswell",
    "sg:classifiers":[
        {
            "category":"Education",
            "subcategory":"Music School",
            "type":"Public Place"
        },
        {
            "category":"Communications",
            "type":"Services"
        }
    ],
    "sg:phone":"+1 678 739 7845",
    "sg:postcode":"30075",
    "sg:province":"GA",
    "sg:tags":[
        "rehearsal",
        "teacher",
        "recording",
        "instrument",
        "studio",
        "musical"
    ],
    "sg:website":"www.thunderroadstudios.com",
    "wof:name":"Thunder Road Music Studios",
    "wof:placetype":"venue"
},
  "geometry": {"coordinates":[-84.361639,34.015127],"type":"Point"}
}