{
  "type": "Feature",
  "properties": {
    "iso:country":"US",
    "sg:address":"1571 Barclay Pl NE",
    "sg:city":"Atlanta",
    "sg:classifiers":[
        {
            "category":"Government",
            "subcategory":"Office",
            "type":"Public Place"
        }
    ],
    "sg:phone":"+1 404 892 8095",
    "sg:postcode":"30306",
    "sg:province":"GA",
    "sg:tags":[
        "consulting",
        "economic"
    ],
    "wof:name":"James Robert Alm",
    "wof:placetype":"venue"
},
  "geometry": {"coordinates":[-84.35256800000001,33.798812],"type":"Point"}
}