{
  "type": "Feature",
  "properties": {
    "iso:country":"US",
    "sg:address":"1720 Danrich Dr",
    "sg:city":"Decatur",
    "sg:classifiers":[
        {
            "category":"Building & Trades",
            "subcategory":"Construction",
            "type":"Services"
        }
    ],
    "sg:phone":"+1 404 286 8850",
    "sg:postcode":"30032",
    "sg:province":"GA",
    "wof:name":"Johnny W Davis Jr",
    "wof:placetype":"venue"
},
  "geometry": {"coordinates":[-84.233386,33.741514],"type":"Point"}
}