{
  "type": "Feature",
  "properties": {
    "iso:country":"US",
    "sg:address":"2031 Abby Ln NE",
    "sg:city":"Atlanta",
    "sg:classifiers":[
        {
            "category":"Real Estate",
            "subcategory":"Real Estate Agent",
            "type":"Services"
        }
    ],
    "sg:phone":"+1 678 352 0272",
    "sg:postcode":"30345",
    "sg:province":"GA",
    "sg:tags":[
        "consultant"
    ],
    "wof:name":"Foreclosure Title Svc",
    "wof:placetype":"venue"
},
  "geometry": {"coordinates":[-84.294184,33.84372],"type":"Point"}
}