{
  "type": "Feature",
  "properties": {
    "iso:country":"US",
    "sg:address":"4129 Renfrew Ct SW",
    "sg:city":"Atlanta",
    "sg:classifiers":[
        {
            "category":"Professional",
            "type":"Services"
        }
    ],
    "sg:phone":"+1 404 696 2928",
    "sg:postcode":"30331",
    "sg:province":"GA",
    "wof:name":"Reid Resident",
    "wof:placetype":"venue"
},
  "geometry": {"coordinates":[-84.521074,33.755493],"type":"Point"}
}