{
  "type": "Feature",
  "properties": {
    "iso:country":"US",
    "sg:address":"2029 Pernoshal Ct",
    "sg:city":"Dunwoody",
    "sg:classifiers":[
        {
            "category":"Organizations",
            "subcategory":"Religious Organization",
            "type":"Services"
        }
    ],
    "sg:phone":"+1 770 457 9442",
    "sg:postcode":"30338",
    "sg:province":"GA",
    "sg:tags":[
        "church"
    ],
    "wof:name":"Evangelism By Fire Ministries",
    "wof:placetype":"venue"
},
  "geometry": {"coordinates":[-84.305328,33.925657],"type":"Point"}
}