{
  "type": "Feature",
  "properties": {
    "addr:full":"2832 1st Ave SW Atlanta GA 30315",
    "addr:housenumber":"2832",
    "addr:postcode":"30315",
    "addr:street":"1St Ave Sw",
    "iso:country":"US",
    "sg:address":"2832 1st Ave SW",
    "sg:city":"Atlanta",
    "sg:classifiers":[
        {
            "category":"Organizations",
            "subcategory":"Religious Organization",
            "type":"Services"
        }
    ],
    "sg:phone":"+1 404 763 9858",
    "sg:postcode":"30315",
    "sg:province":"GA",
    "wof:name":"New Jerusalem Enter Faith",
    "wof:placetype":"venue"
},
  "geometry": {"coordinates":[-84.40012900000001,33.676415],"type":"Point"}
}