{
  "type": "Feature",
  "properties": {
    "addr:full":"586 Woodward Ave SE Atlanta GA 30312",
    "addr:housenumber":"586",
    "addr:postcode":"30312",
    "addr:street":"Woodward Ave Se",
    "iso:country":"US",
    "sg:address":"586 Woodward Ave SE",
    "sg:city":"Atlanta",
    "sg:classifiers":[
        {
            "category":"Social Services",
            "type":"Services"
        }
    ],
    "sg:phone":"+1 404 523 0503",
    "sg:postcode":"30312",
    "sg:province":"GA",
    "wof:name":"Mr Wick Jr Inc",
    "wof:placetype":"venue"
},
  "geometry": {"coordinates":[-84.36914,33.745572],"type":"Point"}
}