{
  "type": "Feature",
  "properties": {
    "iso:country":"US",
    "sg:address":"1120 Cripple Creek Dr",
    "sg:city":"Lawrenceville",
    "sg:classifiers":[
        {
            "category":"Retail",
            "subcategory":"Auto Repair",
            "type":"Services"
        }
    ],
    "sg:phone":"+1 678 985 2253",
    "sg:postcode":"30043",
    "sg:province":"GA",
    "wof:name":"Douglas Domestic Auto Repair",
    "wof:placetype":"venue"
},
  "geometry": {"coordinates":[-83.989304,33.985802],"type":"Point"}
}