{
  "type": "Feature",
  "properties": {
    "addr:full":"2998 Stockbridge Hwy Dacula GA 30094",
    "addr:housenumber":"2998",
    "addr:postcode":"ga 30094",
    "addr:street":"Stockbridge Hwy",
    "iso:country":"US",
    "sg:address":"2998 Stockbridge Hwy",
    "sg:city":"Dacula",
    "sg:classifiers":[
        {
            "category":"Building & Trades",
            "subcategory":"Plumbing",
            "type":"Services"
        }
    ],
    "sg:phone":"+1 770 822 2541",
    "sg:postcode":"30094",
    "sg:province":"GA",
    "wof:name":"Faulkners Plumbing Service",
    "wof:placetype":"venue"
},
  "geometry": {"coordinates":[-84.089518,33.61767],"type":"Point"}
}