{
  "type": "Feature",
  "properties": {
    "addr:full":"2660 Godby Rd Atlanta GA 30349",
    "addr:housenumber":"2660",
    "addr:postcode":"30349",
    "addr:street":"Godby Rd",
    "iso:country":"US",
    "sg:address":"2660 Godby Rd",
    "sg:city":"Atlanta",
    "sg:classifiers":[
        {
            "category":"Shopping",
            "subcategory":"Jewelry",
            "type":"Retail Goods"
        }
    ],
    "sg:phone":"+1 404 305 0510",
    "sg:postcode":"30349",
    "sg:province":"GA",
    "wof:name":"Vam Jewelry",
    "wof:placetype":"venue"
},
  "geometry": {"coordinates":[-84.474593,33.616297],"type":"Point"}
}