{
  "type": "Feature",
  "properties": {
    "addr:full":"974 US Hwy 19 Zebulon GA 30295",
    "addr:housenumber":"974",
    "addr:postcode":"30295",
    "addr:street":"Us Hwy 19",
    "iso:country":"US",
    "sg:address":"974 US Hwy 19",
    "sg:city":"Zebulon",
    "sg:classifiers":[
        {
            "category":"Autos & Motor Vehicles",
            "subcategory":"Auto Supplies",
            "type":"Retail Goods"
        }
    ],
    "sg:phone":"+1 770 567 1229",
    "sg:postcode":"30295",
    "sg:province":"GA",
    "wof:name":"D & L 4 W D Parts Co",
    "wof:placetype":"venue"
},
  "geometry": {"coordinates":[-84.345788,33.054816],"type":"Point"}
}