{
  "type": "Feature",
  "properties": {
    "iso:country":"US",
    "sg:address":"104 Goddard Rd",
    "sg:city":"Athens",
    "sg:classifiers":[
        {
            "category":"Organizations",
            "subcategory":"Religious Organization",
            "type":"Services"
        }
    ],
    "sg:phone":"+1 706 548 8808",
    "sg:postcode":"30607",
    "sg:province":"GA",
    "wof:name":"Faith Evang Methdst Church",
    "wof:placetype":"venue"
},
  "geometry": {"coordinates":[-83.41815200000001,34.007742],"type":"Point"}
}