{
  "type": "Feature",
  "properties": {
    "iso:country":"US",
    "sg:address":"10060 Buice Rd",
    "sg:city":"Alpharetta",
    "sg:classifiers":[
        {
            "category":"Building & Trades",
            "subcategory":"Construction",
            "type":"Services"
        }
    ],
    "sg:phone":"+1 770 475 3259",
    "sg:postcode":"30022",
    "sg:province":"GA",
    "sg:tags":[
        "drywall",
        "contractor"
    ],
    "wof:name":"Northwest Drywall & Texture Co",
    "wof:placetype":"venue"
},
  "geometry": {"coordinates":[-84.22749899999999,34.028452],"type":"Point"}
}