{
  "type": "Feature",
  "properties": {
    "addr:full":"2142 Austell Rd SW Marietta GA 30008",
    "addr:housenumber":"2142",
    "addr:postcode":"30008",
    "addr:street":"Austell Rd Sw",
    "iso:country":"US",
    "sg:address":"2142 Austell Rd SW",
    "sg:city":"Marietta",
    "sg:phone":"+1 770 432 7155",
    "sg:postcode":"30008",
    "sg:province":"GA",
    "sg:website":"http://www.fairoaksvethospital.com",
    "wof:name":"Fair Oaks Veterinary Hospital",
    "wof:placetype":"venue"
},
  "geometry": {"coordinates":[-84.569777,33.901357],"type":"Point"}
}