{
  "type": "Feature",
  "properties": {
    "addr:full":"1301 Eager Dr Albany GA 31707",
    "addr:housenumber":"1301",
    "addr:postcode":"31707",
    "addr:street":"Eager Dr",
    "iso:country":"US",
    "sg:address":"1301 Eager Dr",
    "sg:city":"Albany",
    "sg:classifiers":[
        {
            "category":"Health Services",
            "subcategory":"Nursing And Care Facility",
            "type":"Services"
        }
    ],
    "sg:phone":"+1 229 420 4646",
    "sg:postcode":"31707",
    "sg:province":"GA",
    "wof:name":"Harris/Alice",
    "wof:placetype":"venue"
},
  "geometry": {"coordinates":[-84.183808,31.5878],"type":"Point"}
}