{
  "type": "Feature",
  "properties": {
    "addr:full":"219 Prince Rd Cairo GA 39827",
    "addr:housenumber":"219",
    "addr:postcode":"39827",
    "addr:street":"Prince Rd",
    "iso:country":"US",
    "sg:address":"219 Prince Rd",
    "sg:city":"Cairo",
    "sg:classifiers":[
        {
            "category":"Building & Trades",
            "subcategory":"Construction",
            "type":"Services"
        }
    ],
    "sg:phone":"+1 229 377 3981",
    "sg:postcode":"39827",
    "sg:province":"GA",
    "sg:tags":[
        "general",
        "contractor"
    ],
    "wof:name":"Poppell Construction",
    "wof:placetype":"venue"
},
  "geometry": {"coordinates":[-84.160602,30.922911],"type":"Point"}
}