{
  "type": "Feature",
  "properties": {
    "addr:full":"1285 Collier Rd NW Atlanta GA 30318",
    "addr:housenumber":"1285",
    "addr:postcode":"30318",
    "addr:street":"Collier Rd Nw",
    "iso:country":"US",
    "sg:address":"1285 Collier Rd NW",
    "sg:city":"Atlanta",
    "sg:classifiers":[
        {
            "category":"Freight",
            "type":"Transportation"
        }
    ],
    "sg:phone":"+1 404 350 9969",
    "sg:postcode":"30318",
    "sg:province":"GA",
    "sg:tags":[
        "delivery"
    ],
    "wof:name":"DSI Georgia",
    "wof:placetype":"venue"
},
  "geometry": {"coordinates":[-84.430205,33.812216],"type":"Point"}
}