{
  "type": "Feature",
  "properties": {
    "iso:country":"US",
    "sg:address":"2164 Marietta Blvd NW",
    "sg:city":"Atlanta",
    "sg:classifiers":[
        {
            "category":"Manufacturing",
            "subcategory":"Printing",
            "type":"Manufacturing & Wholesale Goods"
        }
    ],
    "sg:phone":"+1 404 351 7178",
    "sg:postcode":"30318",
    "sg:province":"GA",
    "sg:tags":[
        "screen"
    ],
    "wof:name":"Screenflex",
    "wof:placetype":"venue"
},
  "geometry": {"coordinates":[-84.43875800000001,33.810463],"type":"Point"}
}