{
  "type": "Feature",
  "properties": {
    "addr:full":"4000 Fulton Industrial Blvd SW Atlanta GA 30336",
    "addr:housenumber":"4000",
    "addr:postcode":"30336",
    "addr:street":"Fulton Industrial Blvd Sw",
    "iso:country":"US",
    "sg:address":"4000 Fulton Industrial Blvd SW",
    "sg:city":"Atlanta",
    "sg:classifiers":[
        {
            "category":"Building & Trades",
            "subcategory":"Locksmith",
            "type":"Services"
        }
    ],
    "sg:phone":"+1 404 982 7087",
    "sg:postcode":"30336",
    "sg:province":"GA",
    "sg:tags":[
        "key"
    ],
    "wof:name":"Collins Locksmith",
    "wof:placetype":"venue"
},
  "geometry": {"coordinates":[-84.520511,33.769325],"type":"Point"}
}