{
  "type": "Feature",
  "properties": {
    "iso:country":"US",
    "sg:address":"481 Tynsdale Dr",
    "sg:city":"Douglasville",
    "sg:classifiers":[
        {
            "category":"Professional",
            "subcategory":"Business Services",
            "type":"Services"
        }
    ],
    "sg:phone":"+1 770 949 7118",
    "sg:postcode":"30134",
    "sg:province":"GA",
    "wof:name":"Cole Enterprises",
    "wof:placetype":"venue"
},
  "geometry": {"coordinates":[-84.79780100000001,33.796326],"type":"Point"}
}