{
  "type": "Feature",
  "properties": {
    "addr:full":"160 Highlands Pt Newnan GA 30265",
    "addr:housenumber":"160",
    "addr:postcode":"30265",
    "addr:street":"Highlands Pt",
    "iso:country":"US",
    "sg:address":"160 Highlands Pt",
    "sg:city":"Newnan",
    "sg:classifiers":[
        {
            "category":"Building & Trades",
            "subcategory":"Landscaping Services",
            "type":"Services"
        }
    ],
    "sg:phone":"+1 678 423 0172",
    "sg:postcode":"30265",
    "sg:province":"GA",
    "wof:name":"Garcias Yard Service",
    "wof:placetype":"venue"
},
  "geometry": {"coordinates":[-84.72243,33.390704],"type":"Point"}
}