{
  "type": "Feature",
  "properties": {
    "iso:country":"US",
    "sg:address":"1810 Cumming Hwy Suite 1000",
    "sg:city":"Canton",
    "sg:classifiers":[
        {
            "category":"Restaurant",
            "type":"Food & Drink"
        }
    ],
    "sg:phone":"+1 770 479 8781",
    "sg:postcode":"30114",
    "sg:province":"GA",
    "sg:tags":[
        "mexican"
    ],
    "sg:website":"www.laparrilla.com",
    "wof:name":"La Parrilla",
    "wof:placetype":"venue"
},
  "geometry": {"coordinates":[-84.46069,34.238021],"type":"Point"}
}