{
  "type": "Feature",
  "properties": {
    "iso:country":"US",
    "sg:address":"2004 Metropolitan Pkwy SW",
    "sg:city":"Atlanta",
    "sg:classifiers":[
        {
            "category":"Retail",
            "subcategory":"Auto Repair",
            "type":"Services"
        }
    ],
    "sg:phone":"+1 404 275 3997",
    "sg:postcode":"30310",
    "sg:province":"GA",
    "wof:name":"Pit Stop Auto Service",
    "wof:placetype":"venue"
},
  "geometry": {"coordinates":[-84.408007,33.699902],"type":"Point"}
}