{
  "type": "Feature",
  "properties": {
    "addr:full":"428 Canton Rd Cumming GA 30040",
    "addr:housenumber":"428",
    "addr:postcode":"30040",
    "addr:street":"Canton Rd",
    "iso:country":"US",
    "sg:address":"428 Canton Rd",
    "sg:city":"Cumming",
    "sg:classifiers":[
        {
            "category":"Government",
            "subcategory":"Office",
            "type":"Public Place"
        }
    ],
    "sg:phone":"+1 770 781 6909",
    "sg:postcode":"30040",
    "sg:province":"GA",
    "sg:tags":[
        "county",
        "program"
    ],
    "wof:name":"Forsyth County Environmental",
    "wof:placetype":"venue"
},
  "geometry": {"coordinates":[-84.145798,34.21412],"type":"Point"}
}