{
  "type": "Feature",
  "properties": {
    "iso:country":"US",
    "sg:address":"120 S Robin Ln",
    "sg:city":"Newnan",
    "sg:classifiers":[
        {
            "category":"Professional",
            "type":"Services"
        }
    ],
    "sg:phone":"+1 770 251 5942",
    "sg:postcode":"30263",
    "sg:province":"GA",
    "wof:name":"Charles J Hanson",
    "wof:placetype":"venue"
},
  "geometry": {"coordinates":[-84.817137,33.325091],"type":"Point"}
}