{
  "type": "Feature",
  "properties": {
    "addr:full":"195 S Davis Rd Lagrange GA 30241",
    "addr:housenumber":"195",
    "addr:postcode":"30241",
    "addr:street":"S Davis Rd",
    "iso:country":"US",
    "sg:address":"195 S Davis Rd",
    "sg:city":"Lagrange",
    "sg:classifiers":[
        {
            "category":"Home & Garden",
            "subcategory":"Building Materials",
            "type":"Retail Goods"
        }
    ],
    "sg:phone":"+1 706 882 1428",
    "sg:postcode":"30241",
    "sg:province":"GA",
    "sg:tags":[
        "door"
    ],
    "sg:website":"www.buildersfirstsource.com",
    "wof:name":"Builders First Source",
    "wof:placetype":"venue"
},
  "geometry": {"coordinates":[-84.98550899999999,33.052896],"type":"Point"}
}