{
  "type": "Feature",
  "properties": {
    "iso:country":"US",
    "sg:address":"14 Chestnut Ridge Dr NE",
    "sg:city":"Cartersville",
    "sg:classifiers":[
        {
            "category":"Professional",
            "subcategory":"Engineering",
            "type":"Services"
        }
    ],
    "sg:phone":"+1 404 229 0031",
    "sg:postcode":"30121",
    "sg:province":"GA",
    "wof:name":"Dunagan Engineering Svcs Inc",
    "wof:placetype":"venue"
},
  "geometry": {"coordinates":[-84.80943000000001,34.242121],"type":"Point"}
}