{
  "type": "Feature",
  "properties": {
    "addr:full":"22 Rivers Bend Dr Savannah GA 31406",
    "addr:housenumber":"22",
    "addr:postcode":"31406",
    "addr:street":"Rivers Bend Dr",
    "iso:country":"US",
    "sg:address":"22 Rivers Bend Dr",
    "sg:city":"Savannah",
    "sg:classifiers":[
        {
            "category":"Professional",
            "type":"Services"
        }
    ],
    "sg:phone":"+1 912 354 3058",
    "sg:postcode":"31406",
    "sg:province":"GA",
    "wof:name":"William Goolsby",
    "wof:placetype":"venue"
},
  "geometry": {"coordinates":[-81.11156800000001,31.952912],"type":"Point"}
}