{
  "type": "Feature",
  "properties": {
    "iso:country":"US",
    "sg:address":"110 Columbus West Dr",
    "sg:city":"Macon",
    "sg:classifiers":[
        {
            "category":"Home & Garden",
            "subcategory":"Household Appliances",
            "type":"Retail Goods"
        },
        {
            "category":"Building & Trades",
            "subcategory":"Plumbing",
            "type":"Services"
        }
    ],
    "sg:phone":"+1 478 474 2424",
    "sg:postcode":"31206",
    "sg:province":"GA",
    "sg:tags":[
        "major",
        "industrial",
        "plumber",
        "contractors-commercial",
        "clean",
        "boilers-repair"
    ],
    "wof:name":"Mr Plumber",
    "wof:placetype":"venue"
},
  "geometry": {"coordinates":[-83.74867500000001,32.809745],"type":"Point"}
}