{
  "type": "Feature",
  "properties": {
    "addr:full":"6649 Roswell Road NE Atlanta GA 30328",
    "addr:housenumber":"6649",
    "addr:postcode":"30328",
    "addr:street":"Roswell Road Ne",
    "iso:country":"US",
    "sg:address":"6649 Roswell Road NE",
    "sg:city":"Atlanta",
    "sg:classifiers":[
        {
            "category":"Shopping",
            "subcategory":"Tobacco",
            "type":"Retail Goods"
        }
    ],
    "sg:phone":"+1 404 843 8339",
    "sg:postcode":"30328",
    "sg:province":"GA",
    "sg:tags":[
        "shop"
    ],
    "wof:name":"Cigars Sandy Springs",
    "wof:placetype":"venue"
},
  "geometry": {"coordinates":[-84.378894,33.936092],"type":"Point"}
}