{
  "type": "Feature",
  "properties": {
    "iso:country":"US",
    "sg:address":"236 Auburn Ave NE Ste 203",
    "sg:city":"Atlanta",
    "sg:classifiers":[
        {
            "category":"Professional",
            "subcategory":"Management & Consulting",
            "type":"Services"
        },
        {
            "category":"Professional",
            "subcategory":"Employment Agencies",
            "type":"Services"
        }
    ],
    "sg:phone":"+1 404 577 3392",
    "sg:postcode":"30303",
    "sg:province":"GA",
    "sg:tags":[
        "consultant",
        "temporary",
        "personnel"
    ],
    "wof:name":"First Step Staffing",
    "wof:placetype":"venue"
},
  "geometry": {"coordinates":[-84.37992,33.755524],"type":"Point"}
}