{
  "type": "Feature",
  "properties": {
    "addr:full":"215 E 6th St Waynesboro GA 30830",
    "addr:housenumber":"215",
    "addr:postcode":"30830",
    "addr:street":"E 6Th St",
    "iso:country":"US",
    "sg:address":"215 E 6th St",
    "sg:city":"Waynesboro",
    "sg:classifiers":[
        {
            "category":"Personal",
            "subcategory":"Beauty Salon",
            "type":"Services"
        }
    ],
    "sg:phone":"+1 706 437 8811",
    "sg:postcode":"30830",
    "sg:province":"GA",
    "sg:tags":[
        "shop"
    ],
    "wof:name":"Shear Expressions",
    "wof:placetype":"venue"
},
  "geometry": {"coordinates":[-82.013452,33.091286],"type":"Point"}
}