{
  "type": "Feature",
  "properties": {
    "iso:country":"US",
    "sg:address":"4859 Memorial Dr",
    "sg:city":"Stone Mountain",
    "sg:classifiers":[
        {
            "category":"Shopping",
            "subcategory":"Clothing, Apparel, & Fashions",
            "type":"Retail Goods"
        }
    ],
    "sg:phone":"+1 404 299 0033",
    "sg:postcode":"30083",
    "sg:province":"GA",
    "wof:name":"Fresh Fashions",
    "wof:placetype":"venue"
},
  "geometry": {"coordinates":[-84.232011,33.788315],"type":"Point"}
}