{
  "type": "Feature",
  "properties": {
    "iso:country":"US",
    "sg:address":"2748 Atlanta Hwy",
    "sg:city":"Cumming",
    "sg:classifiers":[
        {
            "category":"Retail",
            "subcategory":"Auto Repair",
            "type":"Services"
        }
    ],
    "sg:phone":"+1 770 889 5391",
    "sg:postcode":"30040",
    "sg:province":"GA",
    "sg:tags":[
        "repairing",
        "automobile"
    ],
    "wof:name":"Steve's Auto",
    "wof:placetype":"venue"
},
  "geometry": {"coordinates":[-84.184727,34.160693],"type":"Point"}
}