{
  "type": "Feature",
  "properties": {
    "iso:country":"US",
    "sg:address":"1955 US Hwy 129",
    "sg:city":"Cleveland",
    "sg:classifiers":[
        {
            "category":"Recreation",
            "type":"Entertainment"
        }
    ],
    "sg:phone":"+1 706 219 2700",
    "sg:postcode":"30528",
    "sg:province":"GA",
    "sg:tags":[
        "martial",
        "arts",
        "instruction"
    ],
    "wof:name":"International Martial Arts Ins",
    "wof:placetype":"venue"
},
  "geometry": {"coordinates":[-83.779794,34.613006],"type":"Point"}
}