{
  "type": "Feature",
  "properties": {
    "addr:full":"2997 N Druid Hills Rd NE Atlanta GA 30329",
    "addr:housenumber":"2997",
    "addr:postcode":"30329",
    "addr:street":"N Druid Hills Rd Ne",
    "iso:country":"US",
    "sg:address":"2997 N Druid Hills Rd NE",
    "sg:city":"Atlanta",
    "sg:classifiers":[
        {
            "category":"Shopping",
            "subcategory":"Shoes",
            "type":"Retail Goods"
        }
    ],
    "sg:phone":"+1 404 929 9333",
    "sg:postcode":"30329",
    "sg:province":"GA",
    "wof:name":"Foot Solutions",
    "wof:placetype":"venue"
},
  "geometry": {"coordinates":[-84.312014,33.817616],"type":"Point"}
}