{
  "type": "Feature",
  "properties": {
    "addr:full":"1117 S Wall St Calhoun GA 30701",
    "addr:housenumber":"1117",
    "addr:postcode":"30701",
    "addr:street":"S Wall St",
    "iso:country":"US",
    "sg:address":"1117 S Wall St",
    "sg:city":"Calhoun",
    "sg:classifiers":[
        {
            "category":"Autos & Motor Vehicles",
            "subcategory":"Auto Supplies",
            "type":"Retail Goods"
        }
    ],
    "sg:phone":"+1 706 629 4121",
    "sg:postcode":"30701",
    "sg:province":"GA",
    "sg:tags":[
        "automotive",
        "parts",
        "automobile"
    ],
    "wof:name":"Advance Auto Parts Inc",
    "wof:placetype":"venue"
},
  "geometry": {"coordinates":[-84.93919099999999,34.481797],"type":"Point"}
}