{
  "type": "Feature",
  "properties": {
    "addr:full":"630 Rosedown Way Alpharetta GA 30022",
    "addr:housenumber":"630",
    "addr:postcode":"30022",
    "addr:street":"Rosedown Way",
    "iso:country":"US",
    "sg:address":"630 Rosedown Way",
    "sg:city":"Alpharetta",
    "sg:classifiers":[
        {
            "category":"Banks & Credit Unions",
            "subcategory":"Investment Brokerage",
            "type":"Services"
        }
    ],
    "sg:phone":"+1 770 521 0296",
    "sg:postcode":"30022",
    "sg:province":"GA",
    "sg:tags":[
        "advisory"
    ],
    "wof:name":"First Atlantic Financial Svcs",
    "wof:placetype":"venue"
},
  "geometry": {"coordinates":[-84.258056,34.027003],"type":"Point"}
}