{
  "type": "Feature",
  "properties": {
    "addr:full":"3685 Las Olas Dr Atlanta GA 30349",
    "addr:housenumber":"3685",
    "addr:postcode":"30349",
    "addr:street":"Las Olas Dr",
    "iso:country":"US",
    "sg:address":"3685 Las Olas Dr",
    "sg:city":"Atlanta",
    "sg:classifiers":[
        {
            "category":"Professional",
            "type":"Services"
        }
    ],
    "sg:phone":"+1 404 762 9731",
    "sg:postcode":"30349",
    "sg:province":"GA",
    "sg:tags":[
        "literary",
        "writer",
        "agent"
    ],
    "wof:name":"Andre Mccoy, Michael",
    "wof:placetype":"venue"
},
  "geometry": {"coordinates":[-84.509895,33.623618],"type":"Point"}
}