{
  "type": "Feature",
  "properties": {
    "iso:country":"US",
    "sg:address":"1721 Douglas St",
    "sg:city":"Augusta",
    "sg:classifiers":[
        {
            "category":"Building & Trades",
            "subcategory":"Construction",
            "type":"Services"
        }
    ],
    "sg:phone":"+1 706 733 5428",
    "sg:postcode":"30901",
    "sg:province":"GA",
    "sg:tags":[
        "downspouts",
        "gutter"
    ],
    "wof:name":"Simon Roofing Co",
    "wof:placetype":"venue"
},
  "geometry": {"coordinates":[-81.998763,33.453782],"type":"Point"}
}