{
  "type": "Feature",
  "properties": {
    "addr:full":"815 Joe Frank Harris Pkwy SE Cartersville GA 30120",
    "addr:housenumber":"815",
    "addr:postcode":"30120",
    "addr:street":"Joe Frank Harris Pkwy Se",
    "iso:country":"US",
    "sg:address":"815 Joe Frank Harris Pkwy SE",
    "sg:city":"Cartersville",
    "sg:classifiers":[
        {
            "category":"Retail",
            "subcategory":"Veterinary Services",
            "type":"Services"
        }
    ],
    "sg:phone":"+1 770 386 4444",
    "sg:postcode":"30120",
    "sg:province":"GA",
    "sg:tags":[
        "veterinarian"
    ],
    "wof:name":"Animal Medical Ctr",
    "wof:placetype":"venue"
},
  "geometry": {"coordinates":[-84.789517,34.194466],"type":"Point"}
}