{
  "type": "Feature",
  "properties": {
    "addr:full":"305 Chandler St Hartwell GA 30643",
    "addr:housenumber":"305",
    "addr:postcode":"30643",
    "addr:street":"Chandler St",
    "iso:country":"US",
    "sg:address":"305 Chandler St",
    "sg:city":"Hartwell",
    "sg:classifiers":[
        {
            "category":"Freight",
            "type":"Transportation"
        }
    ],
    "sg:phone":"+1 706 376 9787",
    "sg:postcode":"30643",
    "sg:province":"GA",
    "sg:tags":[
        "operator",
        "trucking"
    ],
    "wof:name":"Goodwin Transportation Inc",
    "wof:placetype":"venue"
},
  "geometry": {"coordinates":[-82.93518899999999,34.35776],"type":"Point"}
}