{
  "type": "Feature",
  "properties": {
    "addr:full":"5390 Brooke Ridge Dr Atlanta GA 30338",
    "addr:housenumber":"5390",
    "addr:postcode":"30338",
    "addr:street":"Brooke Ridge Dr",
    "iso:country":"US",
    "sg:address":"5390 Brooke Ridge Dr",
    "sg:city":"Atlanta",
    "sg:classifiers":[
        {
            "category":"Retail",
            "subcategory":"Photofinishing",
            "type":"Services"
        }
    ],
    "sg:phone":"+1 770 481 0209",
    "sg:postcode":"30338",
    "sg:province":"GA",
    "sg:tags":[
        "laboratory"
    ],
    "wof:name":"Photo Chemical Systems Inc",
    "wof:placetype":"venue"
},
  "geometry": {"coordinates":[-84.294487,33.958931],"type":"Point"}
}