{
  "type": "Feature",
  "properties": {
    "iso:country":"US",
    "sg:address":"202 Sandhurst Ct",
    "sg:city":"Suwanee",
    "sg:classifiers":[
        {
            "category":"Building & Trades",
            "subcategory":"Construction",
            "type":"Services"
        }
    ],
    "sg:phone":"+1 678 546 5140",
    "sg:postcode":"30024",
    "sg:province":"GA",
    "sg:tags":[
        "house"
    ],
    "wof:name":"Pierce Builders Inc",
    "wof:placetype":"venue"
},
  "geometry": {"coordinates":[-84.080523,34.082888],"type":"Point"}
}