{
  "type": "Feature",
  "properties": {
    "addr:full":"5253 Ridge Forest Dr Stone Mountain GA 30083",
    "addr:housenumber":"5253",
    "addr:postcode":"30083",
    "addr:street":"Ridge Forest Dr",
    "iso:country":"US",
    "sg:address":"5253 Ridge Forest Dr",
    "sg:city":"Stone Mountain",
    "sg:classifiers":[
        {
            "category":"Real Estate",
            "subcategory":"Real Estate Operator",
            "type":"Services"
        }
    ],
    "sg:phone":"+1 770 498 3957",
    "sg:postcode":"30083",
    "sg:province":"GA",
    "sg:tags":[
        "building",
        "nonresidential"
    ],
    "wof:name":"Ridgemare Properties Inc",
    "wof:placetype":"venue"
},
  "geometry": {"coordinates":[-84.169853,33.795376],"type":"Point"}
}