{
  "type": "Feature",
  "properties": {
    "iso:country":"US",
    "sg:address":"1616 Milstead Rd NE",
    "sg:city":"Conyers",
    "sg:classifiers":[
        {
            "category":"Building & Trades",
            "subcategory":"Construction",
            "type":"Services"
        }
    ],
    "sg:phone":"+1 770 483 3595",
    "sg:postcode":"30012",
    "sg:province":"GA",
    "sg:tags":[
        "concrete",
        "paving",
        "contractor"
    ],
    "wof:name":"Upton & Son",
    "wof:placetype":"venue"
},
  "geometry": {"coordinates":[-83.99330399999999,33.682798],"type":"Point"}
}