{
  "type": "Feature",
  "properties": {
    "iso:country":"US",
    "sg:address":"1979 Lakeside Pkwy",
    "sg:city":"Tucker",
    "sg:classifiers":[
        {
            "category":"Wholesale",
            "subcategory":"Electrical",
            "type":"Manufacturing & Wholesale Goods"
        }
    ],
    "sg:phone":"+1 770 496 1555",
    "sg:postcode":"30084",
    "sg:province":"GA",
    "sg:tags":[
        "equipment",
        "parts",
        "electronic",
        "computer"
    ],
    "wof:name":"Hitachi High Technologies Amer",
    "wof:placetype":"venue"
},
  "geometry": {"coordinates":[-84.239446,33.838981],"type":"Point"}
}