{
  "type": "Feature",
  "properties": {
    "iso:country":"US",
    "sg:address":"1924 Regents Ct",
    "sg:city":"Marietta",
    "sg:classifiers":[
        {
            "category":"Manufacturing",
            "subcategory":"Jewelry",
            "type":"Manufacturing & Wholesale Goods"
        }
    ],
    "sg:phone":"+1 770 565 9722",
    "sg:postcode":"30062",
    "sg:province":"GA",
    "sg:tags":[
        "stone",
        "manufacturer",
        "jewelers-wholesale",
        "jewels-imitation"
    ],
    "wof:name":"Dazzl Ltd",
    "wof:placetype":"venue"
},
  "geometry": {"coordinates":[-84.469781,33.997041],"type":"Point"}
}