{
  "type": "Feature",
  "properties": {
    "addr:full":"193 US Hwy 19 Americus GA 31719",
    "addr:housenumber":"193",
    "addr:postcode":"31719",
    "addr:street":"Us Hwy 19 Americus",
    "iso:country":"US",
    "sg:address":"193 US Hwy 19",
    "sg:city":"Americus",
    "sg:classifiers":[
        {
            "category":"Home & Garden",
            "subcategory":"Garden Supply",
            "type":"Retail Goods"
        }
    ],
    "sg:phone":"+1 229 924 7400",
    "sg:postcode":"31719",
    "sg:province":"GA",
    "wof:name":"Markette Nursery",
    "wof:placetype":"venue"
},
  "geometry": {"coordinates":[-84.244243,32.100639],"type":"Point"}
}