{
  "type": "Feature",
  "properties": {
    "addr:full":"9459 State Rte 5 Douglasville GA 30135",
    "addr:housenumber":"9459",
    "addr:postcode":"30135",
    "addr:street":"State Rte 5",
    "iso:country":"US",
    "sg:address":"9459 State Rte 5",
    "sg:city":"Douglasville",
    "sg:classifiers":[
        {
            "category":"Real Estate",
            "subcategory":"Real Estate Agent",
            "type":"Services"
        }
    ],
    "sg:phone":"+1 770 293 1000",
    "sg:postcode":"30135",
    "sg:province":"GA",
    "wof:name":"Victory Realty & Insurance",
    "wof:placetype":"venue"
},
  "geometry": {"coordinates":[-84.76201399999999,33.72551],"type":"Point"}
}