{
  "type": "Feature",
  "properties": {
    "iso:country":"US",
    "sg:address":"607 Mauldin Dr",
    "sg:city":"Woodstock",
    "sg:classifiers":[
        {
            "category":"Retail",
            "subcategory":"Laundry & Dry Cleaning",
            "type":"Services"
        }
    ],
    "sg:phone":"+1 770 591 7021",
    "sg:postcode":"30188",
    "sg:province":"GA",
    "wof:name":"Towne Lake Chem-Dry",
    "wof:placetype":"venue"
},
  "geometry": {"coordinates":[-84.519195,34.083979],"type":"Point"}
}