{
  "type": "Feature",
  "properties": {
    "iso:country":"US",
    "sg:address":"200 Galleria Pkwy SE",
    "sg:city":"Atlanta",
    "sg:classifiers":[
        {
            "category":"Professional",
            "subcategory":"Lawyer & Legal Services",
            "type":"Services"
        }
    ],
    "sg:phone":"+1 770 952 6550",
    "sg:postcode":"30339",
    "sg:province":"GA",
    "sg:tags":[
        "attorney",
        "planning",
        "tax",
        "estate"
    ],
    "wof:name":"Merritt (P.C.), William J. W. - Merritt",
    "wof:placetype":"venue"
},
  "geometry": {"coordinates":[-84.464119,33.88541],"type":"Point"}
}