{
  "type": "Feature",
  "properties": {
    "addr:full":"1647 Canton Rd Marietta GA 30066",
    "addr:housenumber":"1647",
    "addr:postcode":"30066",
    "addr:street":"Canton Rd",
    "iso:country":"US",
    "sg:address":"1647 Canton Rd",
    "sg:city":"Marietta",
    "sg:classifiers":[
        {
            "category":"Manufacturing",
            "subcategory":"Tools & Machinery",
            "type":"Manufacturing & Wholesale Goods"
        }
    ],
    "sg:phone":"+1 770 424 0330",
    "sg:postcode":"30066",
    "sg:province":"GA",
    "sg:tags":[
        "engine",
        "rebuild"
    ],
    "wof:name":"Pro Motive Power",
    "wof:placetype":"venue"
},
  "geometry": {"coordinates":[-84.52908499999999,33.991695],"type":"Point"}
}