{
  "type": "Feature",
  "properties": {
    "iso:country":"US",
    "sg:address":"5195 Courton St",
    "sg:city":"Alpharetta",
    "sg:classifiers":[
        {
            "category":"Professional",
            "subcategory":"Computer Services",
            "type":"Services"
        }
    ],
    "sg:phone":"+1 770 777 7097",
    "sg:postcode":"30022",
    "sg:province":"GA",
    "sg:tags":[
        "development",
        "consulting",
        "software"
    ],
    "wof:name":"Coalescent Systems Inc",
    "wof:placetype":"venue"
},
  "geometry": {"coordinates":[-84.210111,34.056828],"type":"Point"}
}