{
  "type": "Feature",
  "properties": {
    "addr:full":"875 Flat Shoals Rd SE Conyers GA 30094",
    "addr:housenumber":"875",
    "addr:postcode":"30094",
    "addr:street":"Flat Shoals Rd Se",
    "iso:country":"US",
    "sg:address":"875 Flat Shoals Rd SE",
    "sg:city":"Conyers",
    "sg:classifiers":[
        {
            "category":"Deli",
            "type":"Food & Drink"
        }
    ],
    "sg:menulink":"http://www.allmenus.com/ga/conyers/126961-blimpie-subs--sandwiches/menu/",
    "sg:phone":"+1 770 929 3936",
    "sg:postcode":"30094",
    "sg:province":"GA",
    "sg:tags":[
        "wrap",
        "american",
        "sandwich"
    ],
    "wof:name":"Blimpie Subs & Sandwiches",
    "wof:placetype":"venue"
},
  "geometry": {"coordinates":[-84.016221,33.642699],"type":"Point"}
}