{
  "type": "Feature",
  "properties": {
    "iso:country":"US",
    "sg:address":"2897 N Druid Hills Rd NE",
    "sg:city":"Atlanta",
    "sg:classifiers":[
        {
            "category":"Real Estate",
            "subcategory":"Developer",
            "type":"Services"
        },
        {
            "category":"Real Estate",
            "subcategory":"Real Estate Agent",
            "type":"Services"
        }
    ],
    "sg:phone":"+1 404 529 0004",
    "sg:postcode":"30329",
    "sg:province":"GA",
    "sg:tags":[
        "investing"
    ],
    "wof:name":"Procomm Strategics",
    "wof:placetype":"venue"
},
  "geometry": {"coordinates":[-84.31083599999999,33.81623],"type":"Point"}
}