{
  "type": "Feature",
  "properties": {
    "iso:country":"US",
    "sg:address":"6334 Emerald Trl",
    "sg:city":"Acworth",
    "sg:classifiers":[
        {
            "category":"Building & Trades",
            "subcategory":"Construction",
            "type":"Services"
        }
    ],
    "sg:phone":"+1 770 975 3066",
    "sg:postcode":"30102",
    "sg:province":"GA",
    "sg:tags":[
        "contractor"
    ],
    "wof:name":"A1 Contracting Services Inc",
    "wof:placetype":"venue"
},
  "geometry": {"coordinates":[-84.672484,34.102801],"type":"Point"}
}