{
  "type": "Feature",
  "properties": {
    "iso:country":"US",
    "sg:address":"1600 Rolling Hills Trl SE",
    "sg:city":"Conyers",
    "sg:classifiers":[
        {
            "category":"Building & Trades",
            "subcategory":"Construction",
            "type":"Services"
        }
    ],
    "sg:phone":"+1 770 922 2479",
    "sg:postcode":"30094",
    "sg:province":"GA",
    "sg:tags":[
        "house"
    ],
    "wof:name":"Joes Home Repairs",
    "wof:placetype":"venue"
},
  "geometry": {"coordinates":[-84.034123,33.62379],"type":"Point"}
}