{
  "type": "Feature",
  "properties": {
    "addr:full":"1600 Rolling Hills Trl SE Conyers GA 30094",
    "addr:housenumber":"1600",
    "addr:postcode":"30094",
    "addr:street":"Rolling Hills Trl Se",
    "iso:country":"US",
    "sg:address":"1600 Rolling Hills Trl SE",
    "sg:city":"Conyers",
    "sg:classifiers":[
        {
            "category":"Building & Trades",
            "subcategory":"Construction",
            "type":"Services"
        }
    ],
    "sg:phone":"+1 770 922 2479",
    "sg:postcode":"30094",
    "sg:province":"GA",
    "sg:tags":[
        "house"
    ],
    "wof:name":"Joes Home Repairs",
    "wof:placetype":"venue"
},
  "geometry": {"coordinates":[-84.03412299999999,33.62379],"type":"Point"}
}