{
  "type": "Feature",
  "properties": {
    "addr:full":"449 Old Center Point Rd Carrollton GA 30117",
    "addr:housenumber":"449",
    "addr:postcode":"30117",
    "addr:street":"Old Center Point Rd",
    "iso:country":"US",
    "sg:address":"449 Old Center Point Rd",
    "sg:city":"Carrollton",
    "sg:classifiers":[
        {
            "category":"Building & Trades",
            "subcategory":"Construction",
            "type":"Services"
        }
    ],
    "sg:phone":"+1 770 830 6593",
    "sg:postcode":"30117",
    "sg:province":"GA",
    "sg:tags":[
        "wallcoverings-installation",
        "wallpaper",
        "painting",
        "contractor"
    ],
    "wof:name":"Johnson Painting",
    "wof:placetype":"venue"
},
  "geometry": {"coordinates":[-85.053361,33.669243],"type":"Point"}
}