{
  "type": "Feature",
  "properties": {
    "iso:country":"US",
    "sg:address":"3000 Commerce Way",
    "sg:city":"Atlanta",
    "sg:classifiers":[
        {
            "category":"Manufacturing",
            "subcategory":"Paper Products",
            "type":"Manufacturing & Wholesale Goods"
        }
    ],
    "sg:phone":"+1 404 765 0387",
    "sg:postcode":"30354",
    "sg:province":"GA",
    "sg:tags":[
        "embossing"
    ],
    "wof:name":"Nalmac Embossing",
    "wof:placetype":"venue"
},
  "geometry": {"coordinates":[-84.399368,33.672932],"type":"Point"}
}