{
  "type": "Feature",
  "properties": {
    "iso:country":"US",
    "sg:address":"68 Maret St",
    "sg:city":"Hartwell",
    "sg:classifiers":[
        {
            "category":"Social Services",
            "type":"Services"
        }
    ],
    "sg:phone":"+1 706 856 2711",
    "sg:postcode":"30643",
    "sg:province":"GA",
    "sg:tags":[
        "probation",
        "rehabilitation"
    ],
    "wof:name":"State Adult Probation Office",
    "wof:placetype":"venue"
},
  "geometry": {"coordinates":[-82.936341,34.355413],"type":"Point"}
}