{
  "type": "Feature",
  "properties": {
    "iso:country":"US",
    "sg:address":"20 Conkle Rd",
    "sg:city":"Hampton",
    "sg:classifiers":[
        {
            "category":"Professional",
            "subcategory":"Detective & Security Services",
            "type":"Services"
        }
    ],
    "sg:phone":"+1 770 946 9699",
    "sg:postcode":"30228",
    "sg:province":"GA",
    "sg:tags":[
        "system"
    ],
    "wof:name":"GW Contracting",
    "wof:placetype":"venue"
},
  "geometry": {"coordinates":[-84.27298399999999,33.435816],"type":"Point"}
}