{
  "type": "Feature",
  "properties": {
    "iso:country":"US",
    "sg:address":"104 Main St",
    "sg:city":"Eastman",
    "sg:classifiers":[
        {
            "category":"Professional",
            "type":"Services"
        }
    ],
    "sg:phone":"+1 478 374 5532",
    "sg:postcode":"31023",
    "sg:province":"GA",
    "sg:tags":[
        "establishment"
    ],
    "wof:name":"Gerry Mccranie Office",
    "wof:placetype":"venue"
},
  "geometry": {"coordinates":[-83.176524,32.198986],"type":"Point"}
}