{
  "type": "Feature",
  "properties": {
    "iso:country":"US",
    "sg:address":"3970 Peachtree Industrial Blvd Suite 400",
    "sg:city":"Duluth",
    "sg:classifiers":[
        {
            "category":"Shopping",
            "subcategory":"Computers & Home Electronics",
            "type":"Retail Goods"
        },
        {
            "category":"Shopping",
            "subcategory":"Discount & Variety Stores",
            "type":"Retail Goods"
        }
    ],
    "sg:phone":"+1 770 476 4611",
    "sg:postcode":"30071",
    "sg:province":"GA",
    "sg:tags":[
        "wholesale",
        "installation",
        "theatre"
    ],
    "wof:name":"MountsPro",
    "wof:placetype":"venue"
},
  "geometry": {"coordinates":[-84.173391,33.977904],"type":"Point"}
}