{
  "type": "Feature",
  "properties": {
    "iso:country":"US",
    "sg:address":"680 W Peachtree St NW",
    "sg:city":"Atlanta",
    "sg:classifiers":[
        {
            "category":"Place Of Worship",
            "subcategory":"Church",
            "type":"Public Place"
        },
        {
            "category":"Place Of Worship",
            "type":"Public Place"
        },
        {
            "category":"Education",
            "subcategory":"School",
            "type":"Public Place"
        }
    ],
    "sg:phone":"+1 404 888 7801",
    "sg:postcode":"30308",
    "sg:province":"GA",
    "sg:tags":[
        "churches-catholic-traditional",
        "churches-catholic",
        "private",
        "k-"
    ],
    "wof:name":"Archdiocese Of Atlanta",
    "wof:placetype":"venue"
},
  "geometry": {"coordinates":[-84.387327,33.772694],"type":"Point"}
}