{
  "type": "Feature",
  "properties": {
    "iso:country":"US",
    "sg:address":"805 Walker St SE Bldg B95",
    "sg:city":"Marietta",
    "sg:classifiers":[
        {
            "category":"Autos & Motor Vehicles",
            "subcategory":"Automobile Sales",
            "type":"Retail Goods"
        }
    ],
    "sg:phone":"+1 770 427 4086",
    "sg:postcode":"30060",
    "sg:province":"GA",
    "sg:tags":[
        "new",
        "car"
    ],
    "wof:name":"Allison Eng Co",
    "wof:placetype":"venue"
},
  "geometry": {"coordinates":[-84.536541,33.93176],"type":"Point"}
}