{
  "type": "Feature",
  "properties": {
    "iso:country":"US",
    "sg:address":"1588 Griffin Rd",
    "sg:city":"Macon",
    "sg:classifiers":[
        {
            "category":"Retail",
            "subcategory":"Auto Repair",
            "type":"Services"
        }
    ],
    "sg:phone":"+1 478 784 7906",
    "sg:postcode":"31216",
    "sg:province":"GA",
    "sg:tags":[
        "body",
        "shop"
    ],
    "wof:name":"Pio Nono Collision and Body Sp",
    "wof:placetype":"venue"
},
  "geometry": {"coordinates":[-83.630449,32.716295],"type":"Point"}
}