{
  "type": "Feature",
  "properties": {
    "iso:country":"US",
    "sg:address":"3193 Truelove Rd",
    "sg:city":"Gainesville",
    "sg:classifiers":[
        {
            "category":"Retail",
            "subcategory":"Auto Repair",
            "type":"Services"
        }
    ],
    "sg:phone":"+1 770 536 9606",
    "sg:postcode":"30507",
    "sg:province":"GA",
    "sg:tags":[
        "general"
    ],
    "wof:name":"Auto Research & Diagnositic",
    "wof:placetype":"venue"
},
  "geometry": {"coordinates":[-83.740961,34.259823],"type":"Point"}
}