{
  "type": "Feature",
  "properties": {
    "addr:full":"1345 Classic Dr NE Conyers GA 30013",
    "addr:housenumber":"1345",
    "addr:postcode":"30013",
    "addr:street":"Classic Dr Ne",
    "iso:country":"US",
    "sg:address":"1345 Classic Dr NE",
    "sg:city":"Conyers",
    "sg:classifiers":[
        {
            "category":"Building & Trades",
            "subcategory":"Construction",
            "type":"Services"
        }
    ],
    "sg:phone":"+1 770 929 1712",
    "sg:postcode":"30013",
    "sg:province":"GA",
    "sg:tags":[
        "concrete",
        "contractor"
    ],
    "wof:name":"J&K Concrete Work",
    "wof:placetype":"venue"
},
  "geometry": {"coordinates":[-83.97121799999999,33.676037],"type":"Point"}
}