{
  "type": "Feature",
  "properties": {
    "addr:full":"405 Lake Course Ct Augusta GA 30904",
    "addr:housenumber":"405",
    "addr:postcode":"30904",
    "addr:street":"Lake Course Ct",
    "iso:country":"US",
    "sg:address":"405 Lake Course Ct",
    "sg:city":"Augusta",
    "sg:classifiers":[
        {
            "category":"Organizations",
            "subcategory":"Religious Organization",
            "type":"Services"
        }
    ],
    "sg:phone":"+1 706 736 8134",
    "sg:postcode":"30904",
    "sg:province":"GA",
    "wof:name":"Boliek Paulwyn Rev",
    "wof:placetype":"venue"
},
  "geometry": {"coordinates":[-82.012095,33.491353],"type":"Point"}
}