{
  "type": "Feature",
  "properties": {
    "iso:country":"US",
    "sg:address":"149 Lamar St",
    "sg:city":"Macon",
    "sg:classifiers":[
        {
            "category":"Banks & Credit Unions",
            "subcategory":"Financial Services",
            "type":"Services"
        }
    ],
    "sg:phone":"+1 478 741 8742",
    "sg:postcode":"31204",
    "sg:province":"GA",
    "sg:tags":[
        "land",
        "investment"
    ],
    "wof:name":"Barrs Glawson Investments LLC",
    "wof:placetype":"venue"
},
  "geometry": {"coordinates":[-83.652697,32.844636],"type":"Point"}
}