{
  "type": "Feature",
  "properties": {
    "iso:country":"US",
    "sg:address":"1036 Pinetree Ct",
    "sg:city":"Powder Springs",
    "sg:classifiers":[
        {
            "category":"Professional",
            "subcategory":"Computer Services",
            "type":"Services"
        }
    ],
    "sg:phone":"+1 770 943 9150",
    "sg:postcode":"30127",
    "sg:province":"GA",
    "sg:tags":[
        "repair",
        "consulting"
    ],
    "wof:name":"Lan-Mark Computer Services",
    "wof:placetype":"venue"
},
  "geometry": {"coordinates":[-84.681602,33.867599],"type":"Point"}
}