{
  "type": "Feature",
  "properties": {
    "addr:full":"925 Gantt Rd Alpharetta GA 30004",
    "addr:housenumber":"925",
    "addr:postcode":"30004",
    "addr:street":"Gantt Rd",
    "iso:country":"US",
    "sg:address":"925 Gantt Rd",
    "sg:city":"Alpharetta",
    "sg:classifiers":[
        {
            "category":"Retail",
            "subcategory":"Auto Repair",
            "type":"Services"
        }
    ],
    "sg:phone":"+1 770 704 0939",
    "sg:postcode":"30004",
    "sg:province":"GA",
    "sg:tags":[
        "automotive"
    ],
    "wof:name":"Tuff Turf Inc",
    "wof:placetype":"venue"
},
  "geometry": {"coordinates":[-84.3708,34.18041],"type":"Point"}
}