{
  "type": "Feature",
  "properties": {
    "iso:country":"US",
    "sg:address":"1731 Atlanta Hwy",
    "sg:city":"Gainesville",
    "sg:classifiers":[
        {
            "category":"Autos & Motor Vehicles",
            "subcategory":"Automobile Sales",
            "type":"Retail Goods"
        }
    ],
    "sg:phone":"+1 770 536 4932",
    "sg:postcode":"30504",
    "sg:province":"GA",
    "sg:tags":[
        "car",
        "used",
        "dealer"
    ],
    "wof:name":"Peachtree Motors Inc",
    "wof:placetype":"venue"
},
  "geometry": {"coordinates":[-83.842072,34.265109],"type":"Point"}
}