{
  "type": "Feature",
  "properties": {
    "iso:country":"US",
    "sg:address":"131 Blitch St",
    "sg:city":"Statesboro",
    "sg:classifiers":[
        {
            "category":"Retail",
            "subcategory":"Funeral Services",
            "type":"Services"
        }
    ],
    "sg:phone":"+1 912 764 3533",
    "sg:postcode":"30458",
    "sg:province":"GA",
    "sg:tags":[
        "director"
    ],
    "wof:name":"Riggs Funeral Home",
    "wof:placetype":"venue"
},
  "geometry": {"coordinates":[-81.78918899999999,32.454307],"type":"Point"}
}