{
  "type": "Feature",
  "properties": {
    "iso:country":"US",
    "sg:address":"560 E Main St",
    "sg:city":"Statesboro",
    "sg:classifiers":[
        {
            "category":"Real Estate",
            "subcategory":"Real Estate Agent",
            "type":"Services"
        }
    ],
    "sg:phone":"+1 912 764 6998",
    "sg:postcode":"30461",
    "sg:province":"GA",
    "sg:tags":[
        "management"
    ],
    "wof:name":"Stuckey Property Management",
    "wof:placetype":"venue"
},
  "geometry": {"coordinates":[-81.752426,32.454263],"type":"Point"}
}