{
  "type": "Feature",
  "properties": {
    "iso:country":"US",
    "sg:address":"3731 Austell Rd SW",
    "sg:city":"Marietta",
    "sg:classifiers":[
        {
            "category":"Professional",
            "subcategory":"Business Services",
            "type":"Services"
        }
    ],
    "sg:phone":"+1 770 438 1453",
    "sg:postcode":"30008",
    "sg:province":"GA",
    "sg:tags":[
        "inspection"
    ],
    "wof:name":"Testing Wilson",
    "wof:placetype":"venue"
},
  "geometry": {"coordinates":[-84.596672,33.862431],"type":"Point"}
}