{
  "type": "Feature",
  "properties": {
    "addr:full":"2949 King Alfred Dr Macon GA 31204",
    "addr:housenumber":"2949",
    "addr:postcode":"31204",
    "addr:street":"King Alfred Dr",
    "iso:country":"US",
    "sg:address":"2949 King Alfred Dr",
    "sg:city":"Macon",
    "sg:classifiers":[
        {
            "category":"Building & Trades",
            "subcategory":"Construction",
            "type":"Services"
        }
    ],
    "sg:phone":"+1 478 474 7663",
    "sg:postcode":"31204",
    "sg:province":"GA",
    "sg:tags":[
        "roofing",
        "contractor"
    ],
    "wof:name":"O'Kelley's Roofing Co",
    "wof:placetype":"venue"
},
  "geometry": {"coordinates":[-83.66986199999999,32.879846],"type":"Point"}
}