{
  "type": "Feature",
  "properties": {
    "iso:country":"US",
    "sg:address":"610 Holcomb Bridge Rd",
    "sg:city":"Roswell",
    "sg:classifiers":[
        {
            "category":"Shopping",
            "subcategory":"Department Store",
            "type":"Retail Goods"
        }
    ],
    "sg:phone":"+1 770 993 0742",
    "sg:postcode":"30076",
    "sg:province":"GA",
    "sg:website":"www.valuecity.com",
    "wof:name":"Value City Department Store",
    "wof:placetype":"venue"
},
  "geometry": {"coordinates":[-84.343217,34.036682],"type":"Point"}
}