{
  "type": "Feature",
  "properties": {
    "addr:full":"440 10th Ave Columbus GA 31901",
    "addr:housenumber":"440",
    "addr:postcode":"31901",
    "addr:street":"10Th Ave",
    "iso:country":"US",
    "sg:address":"440 10th Ave",
    "sg:city":"Columbus",
    "sg:classifiers":[
        {
            "category":"Utilities",
            "subcategory":"Refuse",
            "type":"Services"
        },
        {
            "category":"Utilities",
            "subcategory":"Recycling",
            "type":"Services"
        },
        {
            "category":"Wholesale",
            "subcategory":"Scrap",
            "type":"Manufacturing & Wholesale Goods"
        },
        {
            "category":"Building & Trades",
            "subcategory":"Construction",
            "type":"Services"
        }
    ],
    "sg:phone":"+1 706 322 5435",
    "sg:postcode":"31901",
    "sg:province":"GA",
    "sg:tags":[
        "container",
        "garbage",
        "metal",
        "contractor",
        "rubbish",
        "removal",
        "demolition"
    ],
    "sg:website":"http://www.ejknightrecycling.com",
    "wof:name":"Knight E J Scrap Material Co",
    "wof:placetype":"venue"
},
  "geometry": {"coordinates":[-84.979828,32.453152],"type":"Point"}
}