{
  "type": "Feature",
  "properties": {
    "iso:country":"US",
    "sg:address":"890 Holmes Cannery Rd",
    "sg:city":"Tennille",
    "sg:classifiers":[
        {
            "category":"Professional",
            "subcategory":"Detective & Security Services",
            "type":"Services"
        }
    ],
    "sg:phone":"+1 478 553 9398",
    "sg:postcode":"31089",
    "sg:province":"GA",
    "sg:tags":[
        "information",
        "bureau"
    ],
    "wof:name":"Ita Services",
    "wof:placetype":"venue"
},
  "geometry": {"coordinates":[-82.7978,32.936981],"type":"Point"}
}