{
  "type": "Feature",
  "properties": {
    "iso:country":"US",
    "sg:address":"126 Vineyard Rd",
    "sg:city":"Griffin",
    "sg:classifiers":[
        {
            "category":"Organizations",
            "subcategory":"Religious Organization",
            "type":"Services"
        }
    ],
    "sg:phone":"+1 770 227 1646",
    "sg:postcode":"30223",
    "sg:province":"GA",
    "sg:tags":[
        "church"
    ],
    "sg:website":"www.vineyardbaptist.org",
    "wof:name":"Vineyard Baptist Church",
    "wof:placetype":"venue"
},
  "geometry": {"coordinates":[-84.290319,33.295362],"type":"Point"}
}