{
  "type": "Feature",
  "properties": {
    "addr:full":"2720 Waymar Dr Marietta GA 30008",
    "addr:postcode":"2720;30008",
    "addr:street":"Waymar Dr",
    "iso:country":"US",
    "sg:address":"2720 Waymar Dr",
    "sg:city":"Marietta",
    "sg:classifiers":[
        {
            "category":"Autos & Motor Vehicles",
            "subcategory":"Automobile Sales",
            "type":"Retail Goods"
        }
    ],
    "sg:phone":"+1 770 241 8026",
    "sg:postcode":"30008",
    "sg:province":"GA",
    "sg:tags":[
        "limo"
    ],
    "wof:name":"Dependable Limousine and Transportation",
    "wof:placetype":"venue"
},
  "geometry": {"coordinates":[-84.587895,33.88717],"type":"Point"}
}