{
  "type": "Feature",
  "properties": {
    "addr:full":"5445 Triangle Pkwy NW Norcross GA 30092",
    "addr:housenumber":"5445",
    "addr:postcode":"30092",
    "addr:street":"Triangle Pkwy Nw",
    "iso:country":"US",
    "sg:address":"5445 Triangle Pkwy NW",
    "sg:city":"Norcross",
    "sg:classifiers":[
        {
            "category":"Professional",
            "subcategory":"Accounting & Tax Preparation",
            "type":"Services"
        }
    ],
    "sg:phone":"+1 770 246 0793",
    "sg:postcode":"30092",
    "sg:province":"GA",
    "sg:tags":[
        "firm"
    ],
    "wof:name":"Jackson Reece & Scott PC",
    "wof:placetype":"venue"
},
  "geometry": {"coordinates":[-84.22321599999999,33.974273],"type":"Point"}
}