{
  "type": "Feature",
  "properties": {
    "addr:full":"1183 Sandy Creek Rd Fayetteville GA 30214",
    "addr:housenumber":"1183",
    "addr:postcode":"30214",
    "addr:street":"Sandy Creek Rd",
    "iso:country":"US",
    "sg:address":"1183 Sandy Creek Rd",
    "sg:city":"Fayetteville",
    "sg:classifiers":[
        {
            "category":"Building & Trades",
            "subcategory":"Construction",
            "type":"Services"
        }
    ],
    "sg:phone":"+1 678 898 0320",
    "sg:postcode":"30214",
    "sg:province":"GA",
    "wof:name":"RC Grading Inc",
    "wof:placetype":"venue"
},
  "geometry": {"coordinates":[-84.55955299999999,33.50018],"type":"Point"}
}