{
  "type": "Feature",
  "properties": {
    "addr:full":"5455 Mount Pleasant Church Rd Macon GA 31216",
    "addr:housenumber":"5455",
    "addr:postcode":"31216",
    "addr:street":"Mount Pleasant Church Rd",
    "iso:country":"US",
    "sg:address":"5455 Mount Pleasant Church Rd",
    "sg:city":"Macon",
    "sg:classifiers":[
        {
            "category":"Organizations",
            "subcategory":"Religious Organization",
            "type":"Services"
        }
    ],
    "sg:phone":"+1 478 781 4970",
    "sg:postcode":"31216",
    "sg:province":"GA",
    "sg:tags":[
        "church"
    ],
    "wof:name":"Mount Pleasant Baptist Church",
    "wof:placetype":"venue"
},
  "geometry": {"coordinates":[-83.740588,32.749555],"type":"Point"}
}