{
  "type": "Feature",
  "properties": {
    "addr:full":"4789 King Rd Patterson GA 31557",
    "addr:housenumber":"4789",
    "addr:postcode":"31557",
    "addr:street":"King Rd",
    "iso:country":"US",
    "sg:address":"4789 King Rd",
    "sg:city":"Patterson",
    "sg:classifiers":[
        {
            "category":"Professional",
            "subcategory":"Management & Consulting",
            "type":"Services"
        }
    ],
    "sg:phone":"+1 912 449 6710",
    "sg:postcode":"31557",
    "sg:province":"GA",
    "sg:tags":[
        "farm"
    ],
    "wof:name":"John Sapp",
    "wof:placetype":"venue"
},
  "geometry": {"coordinates":[-82.11979100000001,31.326749],"type":"Point"}
}