{
  "type": "Feature",
  "properties": {
    "addr:full":"2013 Cleveland Hwy Dalton GA 30721",
    "addr:housenumber":"2013",
    "addr:postcode":"30721",
    "addr:street":"Cleveland Hwy",
    "iso:country":"US",
    "sg:address":"2013 Cleveland Hwy",
    "sg:city":"Dalton",
    "sg:classifiers":[
        {
            "category":"Personal",
            "subcategory":"Beauty Salon",
            "type":"Services"
        }
    ],
    "sg:phone":"+1 706 259 9110",
    "sg:postcode":"30721",
    "sg:province":"GA",
    "wof:name":"Blades",
    "wof:placetype":"venue"
},
  "geometry": {"coordinates":[-84.945536,34.821886],"type":"Point"}
}