{
  "type": "Feature",
  "properties": {
    "iso:country":"US",
    "sg:address":"4281 Old Dixie Hwy",
    "sg:city":"Atlanta",
    "sg:classifiers":[
        {
            "category":"Wholesale",
            "subcategory":"Auto Parts",
            "type":"Manufacturing & Wholesale Goods"
        }
    ],
    "sg:phone":"+1 404 366 5476",
    "sg:postcode":"30354",
    "sg:province":"GA",
    "sg:tags":[
        "tire"
    ],
    "sg:website":"www.carrolltire.com",
    "wof:name":"Carroll Tire Co",
    "wof:placetype":"venue"
},
  "geometry": {"coordinates":[-84.39009900000001,33.639198],"type":"Point"}
}