{
  "type": "Feature",
  "properties": {
    "addr:full":"3027 Tignall Rd Washington GA 30673",
    "addr:housenumber":"3027",
    "addr:postcode":"30673",
    "addr:street":"Tignall Rd",
    "iso:country":"US",
    "sg:address":"3027 Tignall Rd",
    "sg:city":"Washington",
    "sg:classifiers":[
        {
            "category":"Building & Trades",
            "subcategory":"Construction",
            "type":"Services"
        }
    ],
    "sg:phone":"+1 706 678 1248",
    "sg:postcode":"30673",
    "sg:province":"GA",
    "sg:tags":[
        "contractor"
    ],
    "wof:name":"Rusty Howard Construction",
    "wof:placetype":"venue"
},
  "geometry": {"coordinates":[-82.761982,33.802549],"type":"Point"}
}