{
  "type": "Feature",
  "properties": {
    "iso:country":"US",
    "sg:address":"2319 State Rte 81",
    "sg:city":"Loganville",
    "sg:classifiers":[
        {
            "category":"Building & Trades",
            "subcategory":"Plumbing",
            "type":"Services"
        }
    ],
    "sg:phone":"+1 770 466 4888",
    "sg:postcode":"30052",
    "sg:province":"GA",
    "sg:tags":[
        "fire",
        "design",
        "sprinkler",
        "install",
        "system"
    ],
    "wof:name":"Accurate Fire Protection Inc",
    "wof:placetype":"venue"
},
  "geometry": {"coordinates":[-83.851133,33.760509],"type":"Point"}
}