{
  "type": "Feature",
  "properties": {
    "iso:country":"US",
    "sg:address":"345 Courtland St NE",
    "sg:city":"Atlanta",
    "sg:classifiers":[
        {
            "category":"Banks & Credit Unions",
            "subcategory":"Bank",
            "type":"Services"
        }
    ],
    "sg:phone":"+1 404 810 0078",
    "sg:postcode":"30308",
    "sg:province":"GA",
    "wof:name":"American Momentum Bank",
    "wof:placetype":"venue"
},
  "geometry": {"coordinates":[-84.383923,33.765423],"type":"Point"}
}