{
  "type": "Feature",
  "properties": {
    "addr:full":"1310 N Park St Carrollton GA 30117",
    "addr:housenumber":"1310",
    "addr:postcode":"30117",
    "addr:street":"N Park St",
    "iso:country":"US",
    "sg:address":"1310 N Park St",
    "sg:city":"Carrollton",
    "sg:classifiers":[
        {
            "category":"Place Of Worship",
            "type":"Public Place"
        }
    ],
    "sg:phone":"+1 770 834 3750",
    "sg:postcode":"30117",
    "sg:province":"GA",
    "sg:tags":[
        "church"
    ],
    "wof:name":"Church Of Christ-West Georgia",
    "wof:placetype":"venue"
},
  "geometry": {"coordinates":[-85.08087999999999,33.60402],"type":"Point"}
}