{
  "type": "Feature",
  "properties": {
    "iso:country":"US",
    "sg:address":"5952 Wellborn Trl",
    "sg:city":"Lithonia",
    "sg:classifiers":[
        {
            "category":"Restaurant",
            "type":"Food & Drink"
        }
    ],
    "sg:phone":"+1 770 593 1160",
    "sg:postcode":"30058",
    "sg:province":"GA",
    "sg:tags":[
        "eating"
    ],
    "wof:name":"Banana Cabana Restaurant",
    "wof:placetype":"venue"
},
  "geometry": {"coordinates":[-84.147514,33.723536],"type":"Point"}
}