{
  "type": "Feature",
  "properties": {
    "addr:full":"13800 Highway 9 N Ste E Alpharetta GA 30004",
    "addr:housenumber":"13800",
    "addr:postcode":"30004",
    "addr:street":"Highway 9 N Ste E",
    "iso:country":"US",
    "sg:address":"13800 Highway 9 N Ste E",
    "sg:city":"Alpharetta",
    "sg:classifiers":[
        {
            "category":"Food & Beverages",
            "subcategory":"Supermarket",
            "type":"Retail Goods"
        }
    ],
    "sg:phone":"+1 770 751 0312",
    "sg:postcode":"30004",
    "sg:province":"GA",
    "sg:tags":[
        "super",
        "store"
    ],
    "sg:website":"http://www.publix.com",
    "wof:name":"Publix 00762",
    "wof:placetype":"venue"
},
  "geometry": {"coordinates":[-84.270073,34.119034],"type":"Point"}
}