{
  "type": "Feature",
  "properties": {
    "iso:country":"US",
    "sg:address":"2296 Bonner Rd",
    "sg:city":"Atlanta",
    "sg:classifiers":[
        {
            "category":"Transit Center",
            "subcategory":"Freight",
            "type":"Transportation"
        },
        {
            "category":"Freight",
            "type":"Transportation"
        }
    ],
    "sg:phone":"+1 404 763 8904",
    "sg:postcode":"30344",
    "sg:province":"GA",
    "sg:tags":[
        "local",
        "trucking-motor",
        "trucking"
    ],
    "wof:name":"G Express Trucking Inc",
    "wof:placetype":"venue"
},
  "geometry": {"coordinates":[-84.46265200000001,33.691263],"type":"Point"}
}