{
  "type": "Feature",
  "properties": {
    "iso:country":"US",
    "sg:address":"316 Northgate Dr",
    "sg:city":"Dalton",
    "sg:classifiers":[
        {
            "category":"Retail",
            "subcategory":"Auto Repair",
            "type":"Services"
        }
    ],
    "sg:phone":"+1 706 226 5717",
    "sg:postcode":"30721",
    "sg:province":"GA",
    "sg:tags":[
        "exhaust"
    ],
    "wof:name":"Maxi Muffler & Brake",
    "wof:placetype":"venue"
},
  "geometry": {"coordinates":[-84.960307,34.797582],"type":"Point"}
}