{
  "type": "Feature",
  "properties": {
    "iso:country":"US",
    "sg:address":"878 Ralph David Abernathy Blvd SW",
    "sg:city":"Atlanta",
    "sg:classifiers":[
        {
            "category":"Restaurant",
            "type":"Food & Drink"
        }
    ],
    "sg:phone":"+1 404 758 6135",
    "sg:postcode":"30310",
    "sg:province":"GA",
    "sg:tags":[
        "vegetarian",
        "health"
    ],
    "wof:name":"E O P",
    "wof:placetype":"venue"
},
  "geometry": {"coordinates":[-84.41692500000001,33.738105],"type":"Point"}
}