{
  "type": "Feature",
  "properties": {
    "addr:full":"510 14th St NW Atlanta GA 30318",
    "addr:housenumber":"510",
    "addr:postcode":"30318",
    "addr:street":"14Th St Nw",
    "iso:country":"US",
    "sg:address":"510 14th St NW",
    "sg:city":"Atlanta",
    "sg:phone":"+1 404 607 7755",
    "sg:postcode":"30318",
    "sg:province":"GA",
    "sg:tags":[
        "video",
        "conferencing"
    ],
    "wof:name":"Dynamic Directions Inc",
    "wof:placetype":"venue"
},
  "geometry": {"coordinates":[-84.403339,33.786136],"type":"Point"}
}