{
  "type": "Feature",
  "properties": {
    "iso:country":"US",
    "sg:address":"215 Lake Pines Pointe",
    "sg:city":"Alpharetta",
    "sg:classifiers":[
        {
            "category":"Professional",
            "subcategory":"Accounting & Tax Preparation",
            "type":"Services"
        }
    ],
    "sg:phone":"+1 678 770 3829",
    "sg:postcode":"30005",
    "sg:province":"GA",
    "sg:tags":[
        "public",
        "accountants-certified"
    ],
    "sg:website":"http://www.weeksandweekscpa.com",
    "wof:name":"Weeks & Weeks Cpa",
    "wof:placetype":"venue"
},
  "geometry": {"coordinates":[-84.21640499999999,34.073867],"type":"Point"}
}