{
  "type": "Feature",
  "properties": {
    "iso:country":"US",
    "sg:address":"427 Waverly Dr",
    "sg:city":"Augusta",
    "sg:classifiers":[
        {
            "category":"Professional",
            "subcategory":"Management & Consulting",
            "type":"Services"
        }
    ],
    "sg:phone":"+1 706 731 0234",
    "sg:postcode":"30909",
    "sg:province":"GA",
    "sg:tags":[
        "business"
    ],
    "wof:name":"Mike Curtis Ventures LLC",
    "wof:placetype":"venue"
},
  "geometry": {"coordinates":[-82.066846,33.494491],"type":"Point"}
}