{
  "type": "Feature",
  "properties": {
    "iso:country":"US",
    "sg:address":"3124 Washington Rd",
    "sg:city":"Augusta",
    "sg:classifiers":[
        {
            "category":"Personal",
            "subcategory":"Beauty Salon",
            "type":"Services"
        }
    ],
    "sg:phone":"+1 706 860 0042",
    "sg:postcode":"30907",
    "sg:province":"GA",
    "wof:name":"1st Image Hair Salon",
    "wof:placetype":"venue"
},
  "geometry": {"coordinates":[-82.055508,33.513865],"type":"Point"}
}