{
  "type": "Feature",
  "properties": {
    "iso:country":"US",
    "sg:address":"579 N Highland Ave",
    "sg:city":"Atlanta",
    "sg:classifiers":[
        {
            "category":"Bars & Pubs",
            "type":"Food & Drink"
        },
        {
            "category":"Coffee & Tea",
            "type":"Food & Drink"
        },
        {
            "category":"Restaurant",
            "type":"Food & Drink"
        },
        {
            "category":"Bars & Pubs",
            "subcategory":"Wine Bar",
            "type":"Food & Drink"
        },
        {
            "category":"Tea Room",
            "subcategory":"None",
            "type":"Food & Drink"
        }
    ],
    "sg:phone":"+1 404 577 8673",
    "sg:postcode":"30307",
    "sg:province":"GA",
    "sg:tags":[
        "shop",
        "espresso"
    ],
    "sg:website":"www.javavino.com",
    "wof:name":"Java Vino",
    "wof:placetype":"venue"
},
  "geometry": {"coordinates":[-84.35230300000001,33.770401],"type":"Point"}
}