{
  "type": "Feature",
  "properties": {
    "iso:country":"US",
    "sg:address":"801 Inkberry Rd",
    "sg:city":"Canton",
    "sg:classifiers":[
        {
            "category":"Insurance",
            "subcategory":"Hazard Insurance",
            "type":"Services"
        }
    ],
    "sg:phone":"+1 770 841 1245",
    "sg:postcode":"30114",
    "sg:province":"GA",
    "wof:name":"Marina Insurance",
    "wof:placetype":"venue"
},
  "geometry": {"coordinates":[-84.512012,34.186042],"type":"Point"}
}