{
  "type": "Feature",
  "properties": {
    "addr:full":"205 W Broughton St Savannah GA 31401",
    "addr:housenumber":"205",
    "addr:postcode":"31401",
    "addr:street":"W Broughton St",
    "iso:country":"US",
    "sg:address":"205 W Broughton St",
    "sg:city":"Savannah",
    "sg:classifiers":[
        {
            "category":"Shopping",
            "subcategory":"Clothing, Apparel, & Fashions",
            "type":"Retail Goods"
        }
    ],
    "sg:phone":"+1 912 443 0011",
    "sg:postcode":"31401",
    "sg:province":"GA",
    "wof:name":"Bleu Belle",
    "wof:placetype":"venue"
},
  "geometry": {"coordinates":[-81.095299,32.079777],"type":"Point"}
}