{
  "type": "Feature",
  "properties": {
    "addr:full":"707 Hunter Ridge Dr Jonesboro GA 30238",
    "addr:housenumber":"707",
    "addr:postcode":"30238",
    "addr:street":"Hunter Ridge Dr",
    "iso:country":"US",
    "sg:address":"707 Hunter Ridge Dr",
    "sg:city":"Jonesboro",
    "sg:classifiers":[
        {
            "category":"Restaurant",
            "type":"Food & Drink"
        }
    ],
    "sg:phone":"+1 770 477 5366",
    "sg:postcode":"30238",
    "sg:province":"GA",
    "sg:tags":[
        "eating"
    ],
    "wof:name":"Papa Johns",
    "wof:placetype":"venue"
},
  "geometry": {"coordinates":[-84.36931,33.465304],"type":"Point"}
}