{
  "type": "Feature",
  "properties": {
    "iso:country":"US",
    "sg:address":"2235 Irwin Bridge Rd NW",
    "sg:city":"Conyers",
    "sg:classifiers":[
        {
            "category":"Building & Trades",
            "subcategory":"Construction",
            "type":"Services"
        }
    ],
    "sg:phone":"+1 678 413 2306",
    "sg:postcode":"30012",
    "sg:province":"GA",
    "sg:tags":[
        "house"
    ],
    "wof:name":"Francisco Acosta Construc",
    "wof:placetype":"venue"
},
  "geometry": {"coordinates":[-84.02236600000001,33.702521],"type":"Point"}
}