{
  "type": "Feature",
  "properties": {
    "addr:full":"642 W Church St Jasper GA 30143",
    "addr:housenumber":"642",
    "addr:postcode":"30143",
    "addr:street":"W Church St",
    "iso:country":"US",
    "sg:address":"642 W Church St",
    "sg:city":"Jasper",
    "sg:classifiers":[
        {
            "category":"Professional",
            "subcategory":"Lawyer & Legal Services",
            "type":"Services"
        }
    ],
    "sg:phone":"+1 706 692 7869",
    "sg:postcode":"30143",
    "sg:province":"GA",
    "wof:name":"Timothy Francis White",
    "wof:placetype":"venue"
},
  "geometry": {"coordinates":[-84.44116099999999,34.465935],"type":"Point"}
}