{
  "type": "Feature",
  "properties": {
    "iso:country":"US",
    "sg:address":"3125 Gateway Dr Ste H",
    "sg:city":"Norcross",
    "sg:classifiers":[
        {
            "category":"Home & Garden",
            "subcategory":"Carpets & Floor Coverings",
            "type":"Retail Goods"
        }
    ],
    "sg:phone":"+1 770 729 9779",
    "sg:postcode":"30071",
    "sg:province":"GA",
    "sg:tags":[
        "carpeting"
    ],
    "wof:name":"Kirkland Imports",
    "wof:placetype":"venue"
},
  "geometry": {"coordinates":[-84.203796,33.935902],"type":"Point"}
}