{
  "type": "Feature",
  "properties": {
    "iso:country":"US",
    "sg:address":"144 Sam Walker Dr",
    "sg:city":"Lagrange",
    "sg:classifiers":[
        {
            "category":"Government",
            "subcategory":"Office",
            "type":"Public Place"
        }
    ],
    "sg:phone":"+1 706 883 1710",
    "sg:postcode":"30240",
    "sg:province":"GA",
    "wof:name":"Troup County Shop",
    "wof:placetype":"venue"
},
  "geometry": {"coordinates":[-85.004492,32.989575],"type":"Point"}
}