{
  "type": "Feature",
  "properties": {
    "iso:country":"US",
    "sg:address":"271 17th St NW Suite 1900 NW",
    "sg:city":"Atlanta",
    "sg:classifiers":[
        {
            "category":"Professional",
            "subcategory":"Lawyer & Legal Services",
            "type":"Services"
        }
    ],
    "sg:phone":"+1 404 888 3800",
    "sg:postcode":"30363",
    "sg:province":"GA",
    "sg:tags":[
        "attorney",
        "business",
        "corporation",
        "partnership",
        "labor",
        "law",
        "employment"
    ],
    "wof:name":"Ford & Harrison Llp",
    "wof:placetype":"venue"
},
  "geometry": {"coordinates":[-84.394627,33.791273],"type":"Point"}
}