{
  "type": "Feature",
  "properties": {
    "addr:full":"5907 Marcelle Ln NW Norcross GA 30093",
    "addr:housenumber":"5907",
    "addr:postcode":"30093",
    "addr:street":"Marcelle Ln Nw",
    "iso:country":"US",
    "sg:address":"5907 Marcelle Ln NW",
    "sg:city":"Norcross",
    "sg:classifiers":[
        {
            "category":"Organizations",
            "subcategory":"Membership Organization",
            "type":"Services"
        }
    ],
    "sg:phone":"+1 770 923 7133",
    "sg:postcode":"30093",
    "sg:province":"GA",
    "wof:name":"Georgia Assn Enrolled Agents",
    "wof:placetype":"venue"
},
  "geometry": {"coordinates":[-84.188653,33.901628],"type":"Point"}
}