{
  "type": "Feature",
  "properties": {
    "iso:country":"US",
    "sg:address":"141 Preswick Park Dr",
    "sg:city":"Newnan",
    "sg:classifiers":[
        {
            "category":"Building & Trades",
            "subcategory":"Construction",
            "type":"Services"
        }
    ],
    "sg:phone":"+1 770 502 8398",
    "sg:postcode":"30265",
    "sg:province":"GA",
    "sg:tags":[
        "house"
    ],
    "wof:name":"JB Homes",
    "wof:placetype":"venue"
},
  "geometry": {"coordinates":[-84.722495,33.384656],"type":"Point"}
}