{
  "type": "Feature",
  "properties": {
    "addr:full":"17 E Park Ave Savannah GA 31401",
    "addr:housenumber":"17",
    "addr:postcode":"31401",
    "addr:street":"E Park Ave",
    "iso:country":"US",
    "sg:address":"17 E Park Ave",
    "sg:city":"Savannah",
    "sg:classifiers":[
        {
            "category":"Real Estate",
            "subcategory":"Real Estate Operator",
            "type":"Services"
        }
    ],
    "sg:phone":"+1 912 238 9899",
    "sg:postcode":"31401",
    "sg:province":"GA",
    "sg:tags":[
        "apartment"
    ],
    "wof:name":"Telfair Arms Apartments",
    "wof:placetype":"venue"
},
  "geometry": {"coordinates":[-81.097061,32.064814],"type":"Point"}
}