{
  "type": "Feature",
  "properties": {
    "addr:full":"621 N Westover Blvd Albany GA 31707",
    "addr:housenumber":"621",
    "addr:postcode":"31707",
    "addr:street":"N Westover Blvd",
    "iso:country":"US",
    "sg:address":"621 N Westover Blvd",
    "sg:city":"Albany",
    "sg:classifiers":[
        {
            "category":"Retail",
            "subcategory":"Laundry & Dry Cleaning",
            "type":"Services"
        }
    ],
    "sg:phone":"+1 229 435 3477",
    "sg:postcode":"31707",
    "sg:province":"GA",
    "sg:tags":[
        "cleaners",
        "plant",
        "drycleaning"
    ],
    "wof:name":"Debbies Dry Clean Express",
    "wof:placetype":"venue"
},
  "geometry": {"coordinates":[-84.223163,31.613194],"type":"Point"}
}