{
  "type": "Feature",
  "properties": {
    "iso:country":"US",
    "sg:address":"7 Piedmont Center, Suite 300  3525 Roswall Road",
    "sg:city":"Atlanta",
    "sg:classifiers":[
        {
            "category":"Professional",
            "subcategory":"Computer Services",
            "type":"Services"
        }
    ],
    "sg:phone":"+34 915 15 13 44",
    "sg:postcode":"30305",
    "sg:province":"GA",
    "sg:tags":[
        "ossim",
        "siem",
        "open-source",
        "security",
        "compliance",
        "ids",
        "ips",
        "vulnerability-scanning",
        "flows",
        "pci"
    ],
    "sg:website":"http://www.alienvault.com",
    "wof:name":"AlienVault",
    "wof:placetype":"venue"
},
  "geometry": {"coordinates":[-84.381694,33.854028],"type":"Point"}
}