{
  "type": "Feature",
  "properties": {
    "addr:full":"2219 Westpoint Rd Lagrange GA 30240",
    "addr:housenumber":"2219",
    "addr:postcode":"30240",
    "addr:street":"Westpoint Rd",
    "iso:country":"US",
    "sg:address":"2219 Westpoint Rd",
    "sg:city":"Lagrange",
    "sg:classifiers":[
        {
            "category":"Building & Trades",
            "subcategory":"Construction",
            "type":"Services"
        }
    ],
    "sg:phone":"+1 706 845 9101",
    "sg:postcode":"30240",
    "sg:province":"GA",
    "sg:tags":[
        "utility",
        "contractor"
    ],
    "wof:name":"Community Propane Inc",
    "wof:placetype":"venue"
},
  "geometry": {"coordinates":[-85.078327,33.023635],"type":"Point"}
}