{
  "type": "Feature",
  "properties": {
    "addr:full":"113 Patterson Ln Adairsville GA 30103",
    "addr:housenumber":"113",
    "addr:postcode":"30103",
    "addr:street":"Patterson Ln",
    "iso:country":"US",
    "sg:address":"113 Patterson Ln",
    "sg:city":"Adairsville",
    "sg:classifiers":[
        {
            "category":"Building & Trades",
            "subcategory":"Construction",
            "type":"Services"
        }
    ],
    "sg:phone":"+1 770 769 9080",
    "sg:postcode":"30103",
    "sg:province":"GA",
    "sg:tags":[
        "house"
    ],
    "wof:name":"Barnett Construction Comp",
    "wof:placetype":"venue"
},
  "geometry": {"coordinates":[-84.909952,34.365964],"type":"Point"}
}