{
  "type": "Feature",
  "properties": {
    "iso:country":"US",
    "sg:address":"2613 Heritage Cir",
    "sg:city":"Waycross",
    "sg:classifiers":[
        {
            "category":"Building & Trades",
            "subcategory":"Construction",
            "type":"Services"
        }
    ],
    "sg:phone":"+1 912 285 2922",
    "sg:postcode":"31501",
    "sg:province":"GA",
    "sg:tags":[
        "roofing",
        "contractor"
    ],
    "wof:name":"Nova's Metal Roofing Systems",
    "wof:placetype":"venue"
},
  "geometry": {"coordinates":[-82.372017,31.25347],"type":"Point"}
}