{
  "type": "Feature",
  "properties": {
    "addr:full":"6750 Veterans Pkwy Columbus GA 31909",
    "addr:housenumber":"6750",
    "addr:postcode":"31909",
    "addr:street":"Veterans Pkwy",
    "iso:country":"US",
    "sg:address":"6750 Veterans Pkwy",
    "sg:city":"Columbus",
    "sg:classifiers":[
        {
            "category":"Home & Garden",
            "subcategory":"Building Materials",
            "type":"Retail Goods"
        }
    ],
    "sg:phone":"+1 706 320 9292",
    "sg:postcode":"31909",
    "sg:province":"GA",
    "wof:name":"Lowes",
    "wof:placetype":"venue"
},
  "geometry": {"coordinates":[-84.957207,32.530499],"type":"Point"}
}