{
  "type": "Feature",
  "properties": {
    "iso:country":"US",
    "sg:address":"400 Lockheed Ave Suite C",
    "sg:city":"Marietta",
    "sg:classifiers":[
        {
            "category":"Personal",
            "type":"Services"
        }
    ],
    "sg:phone":"+1 770 218 9700",
    "sg:postcode":"30060",
    "sg:province":"GA",
    "sg:tags":[
        "mover"
    ],
    "wof:name":"Caring Heart Movers, Inc.",
    "wof:placetype":"venue"
},
  "geometry": {"coordinates":[-84.521944,33.942639],"type":"Point"}
}