{
  "type": "Feature",
  "properties": {
    "addr:full":"1790 Cheshire Bridge Rd NE Atlanta GA 30324",
    "addr:housenumber":"1790",
    "addr:postcode":"30324",
    "addr:street":"Cheshire Bridge Rd Ne",
    "iso:country":"US",
    "sg:address":"1790 Cheshire Bridge Rd NE",
    "sg:city":"Atlanta",
    "sg:classifiers":[
        {
            "category":"Insurance",
            "subcategory":"Hazard Insurance",
            "type":"Services"
        }
    ],
    "sg:phone":"+1 404 873 2536",
    "sg:postcode":"30324",
    "sg:province":"GA",
    "wof:name":"Barreto Insurance Agency",
    "wof:placetype":"venue"
},
  "geometry": {"coordinates":[-84.36408299999999,33.808486],"type":"Point"}
}