{
  "type": "Feature",
  "properties": {
    "addr:full":"739 Robinson Farms Dr Marietta GA 30068",
    "addr:housenumber":"739",
    "addr:postcode":"30068",
    "addr:street":"Robinson Farms Dr",
    "iso:country":"US",
    "sg:address":"739 Robinson Farms Dr",
    "sg:city":"Marietta",
    "sg:classifiers":[
        {
            "category":"Shopping",
            "type":"Retail Goods"
        },
        {
            "category":"Manufacturing",
            "subcategory":"Paper Products",
            "type":"Manufacturing & Wholesale Goods"
        }
    ],
    "sg:phone":"+1 770 977 4070",
    "sg:postcode":"30068",
    "sg:province":"GA",
    "sg:tags":[
        "packaging",
        "materials-wholesale",
        "material",
        "manufacturer"
    ],
    "wof:name":"Specialty Packaging Inc",
    "wof:placetype":"venue"
},
  "geometry": {"coordinates":[-84.45212600000001,33.966911],"type":"Point"}
}