{
  "type": "Feature",
  "properties": {
    "iso:country":"US",
    "sg:address":"6667 Vernon Woods Dr NE Ste A30",
    "sg:city":"Atlanta",
    "sg:classifiers":[
        {
            "category":"Health Services",
            "subcategory":"Doctor",
            "type":"Services"
        }
    ],
    "sg:phone":"+1 404 351 5711",
    "sg:postcode":"30328",
    "sg:province":"GA",
    "sg:tags":[
        "physician",
        "surgeon",
        "allergy",
        "immunology",
        "surgeons"
    ],
    "wof:name":"Tanner, David D, Md - Atlanta Allergy & Asthma Clnc",
    "wof:placetype":"venue"
},
  "geometry": {"coordinates":[-84.378356,33.929892],"type":"Point"}
}