{
  "type": "Feature",
  "properties": {
    "iso:country":"US",
    "sg:address":"7375 Walton Way",
    "sg:city":"Douglasville",
    "sg:classifiers":[
        {
            "category":"Structure",
            "subcategory":"Office Building",
            "type":"Public Place"
        }
    ],
    "sg:phone":"+1 770 489 7524",
    "sg:postcode":"30135",
    "sg:province":"GA",
    "sg:tags":[
        "park"
    ],
    "wof:name":"Cbw Properties",
    "wof:placetype":"venue"
},
  "geometry": {"coordinates":[-84.82532500000001,33.60102],"type":"Point"}
}