{
  "type": "Feature",
  "properties": {
    "iso:country":"US",
    "sg:address":"2475 Wire Bridge Rd",
    "sg:city":"Arnoldsville",
    "sg:classifiers":[
        {
            "category":"Building & Trades",
            "subcategory":"Landscaping Services",
            "type":"Services"
        }
    ],
    "sg:phone":"+1 706 543 3927",
    "sg:postcode":"30619",
    "sg:province":"GA",
    "sg:tags":[
        "landscape",
        "contractor"
    ],
    "sg:website":"www.piedmontmgmt.com",
    "wof:name":"Piedmont Landscape Management",
    "wof:placetype":"venue"
},
  "geometry": {"coordinates":[-83.27986300000001,33.839654],"type":"Point"}
}