{
  "type": "Feature",
  "properties": {
    "addr:full":"1216 Progress Rd Ellijay GA 30540",
    "addr:housenumber":"1216",
    "addr:postcode":"30540",
    "addr:street":"Progress Rd",
    "iso:country":"US",
    "sg:address":"1216 Progress Rd",
    "sg:city":"Ellijay",
    "sg:classifiers":[
        {
            "category":"Retail",
            "subcategory":"Auto Repair",
            "type":"Services"
        }
    ],
    "sg:phone":"+1 706 635 5301",
    "sg:postcode":"30540",
    "sg:province":"GA",
    "sg:tags":[
        "body",
        "painting",
        "repairing",
        "automobile"
    ],
    "sg:website":"http://www.collisiondecision.com",
    "wof:name":"Larry's Body Shop",
    "wof:placetype":"venue"
},
  "geometry": {"coordinates":[-84.489479,34.676587],"type":"Point"}
}