{
  "type": "Feature",
  "properties": {
    "iso:country":"US",
    "sg:address":"1172 Milford Church Rd SW",
    "sg:city":"Marietta",
    "sg:classifiers":[
        {
            "category":"Shopping",
            "subcategory":"Pharmacy",
            "type":"Retail Goods"
        }
    ],
    "sg:phone":"+1 770 319 2540",
    "sg:postcode":"30060",
    "sg:province":"GA",
    "sg:tags":[
        "drugstore"
    ],
    "sg:website":"www.cvs.com",
    "wof:name":"Cvs Pharmacy",
    "wof:placetype":"venue"
},
  "geometry": {"coordinates":[-84.586899,33.8815],"type":"Point"}
}