{
  "type": "Feature",
  "properties": {
    "addr:full":"22 Perimeter Center E Atlanta GA 30346",
    "addr:housenumber":"22",
    "addr:postcode":"30346",
    "addr:street":"Perimeter Center E",
    "iso:country":"US",
    "sg:address":"22 Perimeter Center E",
    "sg:city":"Atlanta",
    "sg:classifiers":[
        {
            "category":"Professional",
            "type":"Services"
        }
    ],
    "sg:phone":"+1 770 698 9000",
    "sg:postcode":"30346",
    "sg:province":"GA",
    "wof:name":"Welcomemat Services",
    "wof:placetype":"venue"
},
  "geometry": {"coordinates":[-84.32996,33.923444],"type":"Point"}
}