{
  "type": "Feature",
  "properties": {
    "addr:full":"5003 Jacksonville Hwy Waycross GA 31503",
    "addr:housenumber":"5003",
    "addr:postcode":"31503",
    "addr:street":"Jacksonville Hwy",
    "iso:country":"US",
    "sg:address":"5003 Jacksonville Hwy",
    "sg:city":"Waycross",
    "sg:classifiers":[
        {
            "category":"Manufacturing",
            "subcategory":"Lumber",
            "type":"Manufacturing & Wholesale Goods"
        }
    ],
    "sg:phone":"+1 912 287 4915",
    "sg:postcode":"31503",
    "sg:province":"GA",
    "sg:tags":[
        "government"
    ],
    "wof:name":"Forestry Dept District Ofc",
    "wof:placetype":"venue"
},
  "geometry": {"coordinates":[-82.254777,31.119786],"type":"Point"}
}