{
  "type": "Feature",
  "properties": {
    "addr:full":"1410 Tobesofkee Point Dr Macon GA 31220",
    "addr:housenumber":"1410",
    "addr:postcode":"31220",
    "addr:street":"Tobesofkee Point Dr",
    "iso:country":"US",
    "sg:address":"1410 Tobesofkee Point Dr",
    "sg:city":"Macon",
    "sg:classifiers":[
        {
            "category":"Professional",
            "type":"Services"
        }
    ],
    "sg:phone":"+1 478 474 2772",
    "sg:postcode":"31220",
    "sg:province":"GA",
    "wof:name":"Sharon Lindsey",
    "wof:placetype":"venue"
},
  "geometry": {"coordinates":[-83.79687300000001,32.841541],"type":"Point"}
}