{
  "type": "Feature",
  "properties": {
    "addr:full":"175 W. Wieuca Road. NE Atlanta GA 30342",
    "addr:housenumber":"175",
    "addr:postcode":"30342",
    "addr:street":"W. Wieuca Road. Ne",
    "iso:country":"US",
    "sg:address":"175 W. Wieuca Road. NE",
    "sg:city":"Atlanta",
    "sg:classifiers":[
        {
            "category":"Autos & Motor Vehicles",
            "subcategory":"Automobile Sales",
            "type":"Retail Goods"
        }
    ],
    "sg:phone":"+1 404 255 3955",
    "sg:postcode":"30342",
    "sg:province":"GA",
    "sg:tags":[
        "limo"
    ],
    "sg:website":"www.whiteglovelimo.com",
    "wof:name":"White Glove Limousine",
    "wof:placetype":"venue"
},
  "geometry": {"coordinates":[-84.381198,33.877035],"type":"Point"}
}