{
  "type": "Feature",
  "properties": {
    "addr:full":"2505 Tobacco Rd Hephzibah GA 30815",
    "addr:housenumber":"2505",
    "addr:postcode":"30815",
    "addr:street":"Tobacco Rd",
    "iso:country":"US",
    "sg:address":"2505 Tobacco Rd",
    "sg:city":"Hephzibah",
    "sg:classifiers":[
        {
            "category":"Restaurant",
            "type":"Food & Drink"
        }
    ],
    "sg:menulink":"http://www.allmenus.com/ga/gracewood/191533-sonic/menu/",
    "sg:phone":"+1 706 796 7654",
    "sg:postcode":"30815",
    "sg:province":"GA",
    "sg:tags":[
        "burger",
        "american"
    ],
    "wof:name":"Sonic",
    "wof:placetype":"venue"
},
  "geometry": {"coordinates":[-82.07647799999999,33.377443],"type":"Point"}
}