{
  "type": "Feature",
  "properties": {
    "addr:full":"3093 Turkey Oak Trl Loganville GA 30052",
    "addr:housenumber":"3093",
    "addr:postcode":"30052",
    "addr:street":"Turkey Oak Trl",
    "iso:country":"US",
    "sg:address":"3093 Turkey Oak Trl",
    "sg:city":"Loganville",
    "sg:classifiers":[
        {
            "category":"Real Estate",
            "subcategory":"Real Estate Services",
            "type":"Services"
        },
        {
            "category":"Real Estate",
            "subcategory":"Real Estate Agent",
            "type":"Services"
        }
    ],
    "sg:phone":"+1 770 823 1230",
    "sg:postcode":"30052",
    "sg:province":"GA",
    "sg:tags":[
        "buyer",
        "broker"
    ],
    "wof:name":"All Over Atlanta Realty",
    "wof:placetype":"venue"
},
  "geometry": {"coordinates":[-83.928056,33.872847],"type":"Point"}
}