{
  "type": "Feature",
  "properties": {
    "addr:full":"1407 Fort Lamar Rd Commerce GA 30530",
    "addr:housenumber":"1407",
    "addr:postcode":"30530",
    "addr:street":"Fort Lamar Rd",
    "iso:country":"US",
    "sg:address":"1407 Fort Lamar Rd",
    "sg:city":"Commerce",
    "sg:phone":"+1 706 335 3499",
    "sg:postcode":"30530",
    "sg:province":"GA",
    "sg:tags":[
        "gas"
    ],
    "wof:name":"Country Boys Gas Inc",
    "wof:placetype":"venue"
},
  "geometry": {"coordinates":[-83.382857,34.223096],"type":"Point"}
}