{
  "type": "Feature",
  "properties": {
    "addr:full":"125 N Stephens St Boston GA 31626",
    "addr:housenumber":"125",
    "addr:postcode":"31626",
    "addr:street":"N Stephens St",
    "iso:country":"US",
    "sg:address":"125 N Stephens St",
    "sg:city":"Boston",
    "sg:classifiers":[
        {
            "category":"Professional",
            "type":"Services"
        }
    ],
    "sg:phone":"+1 229 498 8392",
    "sg:postcode":"31626",
    "sg:province":"GA",
    "wof:name":"Cravings",
    "wof:placetype":"venue"
},
  "geometry": {"coordinates":[-83.78845800000001,30.792629],"type":"Point"}
}