{
  "type": "Feature",
  "properties": {
    "addr:full":"32 Lenox Pointe NE Atlanta GA 30324",
    "addr:housenumber":"32",
    "addr:postcode":"30324",
    "addr:street":"Lenox Pointe Ne",
    "iso:country":"US",
    "sg:address":"32 Lenox Pointe NE",
    "sg:city":"Atlanta",
    "sg:classifiers":[
        {
            "category":"Organizations",
            "subcategory":"Professional Association",
            "type":"Services"
        }
    ],
    "sg:phone":"+1 404 261 5528",
    "sg:postcode":"30324",
    "sg:province":"GA",
    "sg:website":"www.saortho.org",
    "wof:name":"Southern Association-Orthdntst",
    "wof:placetype":"venue"
},
  "geometry": {"coordinates":[-84.354112,33.826043],"type":"Point"}
}