{
  "type": "Feature",
  "properties": {
    "addr:full":"260 Polk St Menlo AL 30731",
    "addr:housenumber":"260",
    "addr:postcode":"30731",
    "addr:street":"Polk St",
    "iso:country":"US",
    "sg:address":"260 Polk St",
    "sg:city":"Menlo",
    "sg:classifiers":[
        {
            "category":"Food & Beverages",
            "subcategory":"Groceries & Convenience Stores",
            "type":"Retail Goods"
        }
    ],
    "sg:phone":"+1 706 862 2396",
    "sg:postcode":"30731",
    "sg:province":"AL",
    "wof:name":"Handi Mart",
    "wof:placetype":"venue"
},
  "geometry": {"coordinates":[-85.477998,34.490027],"type":"Point"}
}