{
  "type": "Feature",
  "properties": {
    "iso:country":"US",
    "sg:address":"2076 Lake Ridge Ter",
    "sg:city":"Lawrenceville",
    "sg:classifiers":[
        {
            "category":"Home & Garden",
            "subcategory":"Carpets & Floor Coverings",
            "type":"Retail Goods"
        }
    ],
    "sg:phone":"+1 770 682 0067",
    "sg:postcode":"30043",
    "sg:province":"GA",
    "sg:tags":[
        "hardwood",
        "flooring",
        "contractor"
    ],
    "wof:name":"Classic Wood Floors",
    "wof:placetype":"venue"
},
  "geometry": {"coordinates":[-84.00794999999999,34.016878],"type":"Point"}
}