{
  "type": "Feature",
  "properties": {
    "iso:country":"US",
    "sg:address":"195 Burnett St",
    "sg:city":"Athens",
    "sg:classifiers":[
        {
            "category":"Travel",
            "subcategory":"Hotels & Motels",
            "type":"Entertainment"
        }
    ],
    "sg:phone":"+1 706 546 6382",
    "sg:postcode":"30605",
    "sg:province":"GA",
    "sg:tags":[
        "membership",
        "association",
        "lodging"
    ],
    "wof:name":"Alpha PSI Frat",
    "wof:placetype":"venue"
},
  "geometry": {"coordinates":[-83.37789600000001,33.939409],"type":"Point"}
}