{
  "type": "Feature",
  "properties": {
    "addr:full":"180 Mountain Dr Dahlonega GA 30533",
    "addr:housenumber":"180",
    "addr:postcode":"30533",
    "addr:street":"Mountain Dr",
    "iso:country":"US",
    "sg:address":"180 Mountain Dr",
    "sg:city":"Dahlonega",
    "sg:classifiers":[
        {
            "category":"Farming",
            "subcategory":"Vineyard",
            "type":"Manufacturing & Wholesale Goods"
        },
        {
            "category":"Restaurant",
            "type":"Food & Drink"
        }
    ],
    "sg:phone":"+1 706 867 9862",
    "sg:postcode":"30533",
    "sg:province":"GA",
    "sg:tags":[
        "grape",
        "caterer"
    ],
    "wof:name":"Wolf Mountain Vineyards Lllp",
    "wof:placetype":"venue"
},
  "geometry": {"coordinates":[-83.976451,34.525404],"type":"Point"}
}