{
  "type": "Feature",
  "properties": {
    "iso:country":"US",
    "sg:address":"437 Walker St",
    "sg:city":"Augusta",
    "sg:classifiers":[
        {
            "category":"Professional",
            "subcategory":"Engineering",
            "type":"Services"
        },
        {
            "category":"Professional",
            "subcategory":"Management & Consulting",
            "type":"Services"
        }
    ],
    "sg:phone":"+1 706 821 3838",
    "sg:postcode":"30901",
    "sg:province":"GA",
    "sg:tags":[
        "environmental",
        "ecological",
        "consultant",
        "engineer"
    ],
    "wof:name":"Ridge Construction",
    "wof:placetype":"venue"
},
  "geometry": {"coordinates":[-81.95967899999999,33.468395],"type":"Point"}
}