{
  "type": "Feature",
  "properties": {
    "addr:full":"1530 Old Alabama Road Suite 200 Roswell GA 30076",
    "addr:housenumber":"1530",
    "addr:postcode":"30076",
    "addr:street":"Old Alabama Road Suite 200",
    "iso:country":"US",
    "sg:address":"1530 Old Alabama Road Suite 200",
    "sg:city":"Roswell",
    "sg:classifiers":[
        {
            "category":"Arena",
            "subcategory":"Sports Club",
            "type":"Entertainment"
        }
    ],
    "sg:phone":"+1 770 817 5728",
    "sg:postcode":"30076",
    "sg:province":"GA",
    "sg:tags":[
        "martial art"
    ],
    "sg:website":"atlantakravmaga.com/",
    "wof:name":"Atlanta Krav Maga & Fitness",
    "wof:placetype":"venue"
},
  "geometry": {"coordinates":[-84.31756300000001,34.020866],"type":"Point"}
}