{
  "type": "Feature",
  "properties": {
    "addr:full":"120 Haygood Dr Woodstock GA 30188",
    "addr:housenumber":"120",
    "addr:postcode":"30188",
    "addr:street":"Haygood Dr",
    "iso:country":"US",
    "sg:address":"120 Haygood Dr",
    "sg:city":"Woodstock",
    "sg:classifiers":[
        {
            "category":"Building & Trades",
            "subcategory":"Construction",
            "type":"Services"
        }
    ],
    "sg:phone":"+1 770 426 9577",
    "sg:postcode":"30188",
    "sg:province":"GA",
    "sg:tags":[
        "designer",
        "dealer",
        "pool",
        "swimming"
    ],
    "sg:website":"www.gapoolman.com",
    "wof:name":"Georgia Pool Plastering",
    "wof:placetype":"venue"
},
  "geometry": {"coordinates":[-84.50549100000001,34.143624],"type":"Point"}
}