{
  "type": "Feature",
  "properties": {
    "iso:country":"US",
    "sg:address":"1950 Luke Edwards Rd",
    "sg:city":"Dacula",
    "sg:classifiers":[
        {
            "category":"Personal",
            "type":"Services"
        }
    ],
    "sg:phone":"+1 770 682 1496",
    "sg:postcode":"30019",
    "sg:province":"GA",
    "wof:name":"Georgia Heartwood",
    "wof:placetype":"venue"
},
  "geometry": {"coordinates":[-83.87569499999999,33.943211],"type":"Point"}
}