{
  "type": "Feature",
  "properties": {
    "addr:full":"6 Hospital Park Moultrie GA 31768",
    "addr:housenumber":"6",
    "addr:postcode":"31768",
    "addr:street":"Hospital Park",
    "iso:country":"US",
    "sg:address":"6 Hospital Park",
    "sg:city":"Moultrie",
    "sg:classifiers":[
        {
            "category":"Health Services",
            "subcategory":"Doctor",
            "type":"Services"
        }
    ],
    "sg:phone":"+1 229 985 3320",
    "sg:postcode":"31768",
    "sg:province":"GA",
    "sg:tags":[
        "physician",
        "family",
        "practice",
        "surgeons",
        "medicine",
        "surgeon"
    ],
    "wof:name":"Lodge C Gary MD",
    "wof:placetype":"venue"
},
  "geometry": {"coordinates":[-83.77892,31.126969],"type":"Point"}
}