{
  "type": "Feature",
  "properties": {
    "addr:full":"2031 Gees Mill Rd NE Conyers GA 30013",
    "addr:housenumber":"2031",
    "addr:postcode":"30013",
    "addr:street":"Gees Mill Rd Ne",
    "iso:country":"US",
    "sg:address":"2031 Gees Mill Rd NE",
    "sg:city":"Conyers",
    "sg:classifiers":[
        {
            "category":"Home & Garden",
            "subcategory":"Home Furnishings",
            "type":"Retail Goods"
        }
    ],
    "sg:phone":"+1 770 760 1133",
    "sg:postcode":"30013",
    "sg:province":"GA",
    "sg:tags":[
        "curtain",
        "made",
        "drapery"
    ],
    "wof:name":"Custom Drapery Works",
    "wof:placetype":"venue"
},
  "geometry": {"coordinates":[-83.98319100000001,33.651337],"type":"Point"}
}