{
  "type": "Feature",
  "properties": {
    "addr:full":"5449 State Rte 20 Loganville GA 30052",
    "addr:housenumber":"5449",
    "addr:postcode":"30052",
    "addr:street":"State Rte 20",
    "iso:country":"US",
    "sg:address":"5449 State Rte 20",
    "sg:city":"Loganville",
    "sg:classifiers":[
        {
            "category":"Professional",
            "type":"Services"
        }
    ],
    "sg:phone":"+1 770 554 9629",
    "sg:postcode":"30052",
    "sg:province":"GA",
    "sg:tags":[
        "establishment"
    ],
    "wof:name":"SBA Inc",
    "wof:placetype":"venue"
},
  "geometry": {"coordinates":[-83.94817500000001,33.807301],"type":"Point"}
}