{
  "type": "Feature",
  "properties": {
    "addr:full":"101 Crestwood Dr Griffin GA 30223",
    "addr:housenumber":"101",
    "addr:postcode":"30223",
    "addr:street":"Crestwood Dr",
    "iso:country":"US",
    "sg:address":"101 Crestwood Dr",
    "sg:city":"Griffin",
    "sg:classifiers":[
        {
            "category":"Real Estate",
            "subcategory":"Real Estate Agent",
            "type":"Services"
        }
    ],
    "sg:phone":"+1 770 228 0246",
    "sg:postcode":"30223",
    "sg:province":"GA",
    "wof:name":"John Herbert Inc",
    "wof:placetype":"venue"
},
  "geometry": {"coordinates":[-84.291826,33.282685],"type":"Point"}
}