{
  "type": "Feature",
  "properties": {
    "addr:full":"1430 Frazier Copelan Rd Madison GA 30650",
    "addr:housenumber":"1430",
    "addr:postcode":"30650",
    "addr:street":"Frazier Copelan Rd",
    "iso:country":"US",
    "sg:address":"1430 Frazier Copelan Rd",
    "sg:city":"Madison",
    "sg:classifiers":[
        {
            "category":"Manufacturing",
            "subcategory":"Buildings",
            "type":"Manufacturing & Wholesale Goods"
        },
        {
            "category":"Building & Trades",
            "subcategory":"Construction",
            "type":"Services"
        }
    ],
    "sg:phone":"+1 706 453 4548",
    "sg:postcode":"30650",
    "sg:province":"GA",
    "sg:tags":[
        "home",
        "builder",
        "contractor"
    ],
    "wof:name":"Rick Casey Construction",
    "wof:placetype":"venue"
},
  "geometry": {"coordinates":[-83.312692,33.623291],"type":"Point"}
}