{
  "type": "Feature",
  "properties": {
    "addr:full":"4530 Sunlight Ct Lilburn GA 30047",
    "addr:housenumber":"4530",
    "addr:postcode":"30047",
    "addr:street":"Sunlight Ct",
    "iso:country":"US",
    "sg:address":"4530 Sunlight Ct",
    "sg:city":"Lilburn",
    "sg:classifiers":[
        {
            "category":"Professional",
            "subcategory":"Business Services",
            "type":"Services"
        }
    ],
    "sg:phone":"+1 770 982 6351",
    "sg:postcode":"30047",
    "sg:province":"GA",
    "wof:name":"Krishna & Associates Inc",
    "wof:placetype":"venue"
},
  "geometry": {"coordinates":[-84.095124,33.843213],"type":"Point"}
}