{
  "type": "Feature",
  "properties": {
    "addr:full":"4166 Deerwood Pkwy SE Smyrna GA 30082",
    "addr:housenumber":"4166",
    "addr:postcode":"30082",
    "addr:street":"Deerwood Pkwy Se",
    "iso:country":"US",
    "sg:address":"4166 Deerwood Pkwy SE",
    "sg:city":"Smyrna",
    "sg:classifiers":[
        {
            "category":"Building & Trades",
            "subcategory":"Locksmith",
            "type":"Services"
        }
    ],
    "sg:phone":"+1 770 308 0963",
    "sg:postcode":"30082",
    "sg:province":"GA",
    "sg:tags":[
        "key"
    ],
    "wof:name":"0 A A A 24 Hr Locksmith",
    "wof:placetype":"venue"
},
  "geometry": {"coordinates":[-84.549035,33.853033],"type":"Point"}
}