{
  "type": "Feature",
  "properties": {
    "iso:country":"US",
    "sg:address":"119 Pickens Dr",
    "sg:city":"Newnan",
    "sg:classifiers":[
        {
            "category":"Manufacturing",
            "subcategory":"Jewelry",
            "type":"Manufacturing & Wholesale Goods"
        }
    ],
    "sg:phone":"+1 404 934 0098",
    "sg:postcode":"30263",
    "sg:province":"GA",
    "sg:tags":[
        "jewelers-wholesale",
        "manufacturer"
    ],
    "wof:name":"Sonny & Reed",
    "wof:placetype":"venue"
},
  "geometry": {"coordinates":[-84.811699,33.391071],"type":"Point"}
}