{
  "type": "Feature",
  "properties": {
    "addr:full":"2263 County Camp Rd Appling GA 30802",
    "addr:housenumber":"2263",
    "addr:postcode":"30802",
    "addr:street":"County Camp Rd",
    "iso:country":"US",
    "sg:address":"2263 County Camp Rd",
    "sg:city":"Appling",
    "sg:classifiers":[
        {
            "category":"Government",
            "subcategory":"Office",
            "type":"Public Place"
        }
    ],
    "sg:phone":"+1 706 541 1924",
    "sg:postcode":"30802",
    "sg:province":"GA",
    "wof:name":"Columbia Central Shop",
    "wof:placetype":"venue"
},
  "geometry": {"coordinates":[-82.30739199999999,33.534078],"type":"Point"}
}