{
  "type": "Feature",
  "properties": {
    "addr:full":"451 Huff St Lawrenceville GA 30045",
    "addr:housenumber":"451",
    "addr:postcode":"30045",
    "addr:street":"Huff St",
    "iso:country":"US",
    "sg:address":"451 Huff St",
    "sg:city":"Lawrenceville",
    "sg:classifiers":[
        {
            "category":"Real Estate",
            "subcategory":"Real Estate Operator",
            "type":"Services"
        }
    ],
    "sg:phone":"+1 770 963 9264",
    "sg:postcode":"30045",
    "sg:province":"GA",
    "sg:tags":[
        "building",
        "apartment"
    ],
    "wof:name":"Virginian Apts",
    "wof:placetype":"venue"
},
  "geometry": {"coordinates":[-83.999787,33.955558],"type":"Point"}
}