{
  "type": "Feature",
  "properties": {
    "iso:country":"US",
    "sg:address":"14045 Abercorn St Exn",
    "sg:city":"Savannah",
    "sg:classifiers":[
        {
            "category":"Shopping",
            "subcategory":"Clothing, Apparel, & Fashions",
            "type":"Retail Goods"
        }
    ],
    "sg:phone":"+1 912 920 9922",
    "sg:postcode":"31419",
    "sg:province":"GA",
    "sg:tags":[
        "furnishing"
    ],
    "wof:name":"S&K Famous Brand Menswear",
    "wof:placetype":"venue"
},
  "geometry": {"coordinates":[-81.169061,31.980932],"type":"Point"}
}