{
  "type": "Feature",
  "properties": {
    "iso:country":"US",
    "sg:address":"4091 Woodridge Way",
    "sg:city":"Tucker",
    "sg:classifiers":[
        {
            "category":"Home & Garden",
            "subcategory":"Home Furnishings",
            "type":"Retail Goods"
        }
    ],
    "sg:phone":"+1 770 496 5835",
    "sg:postcode":"30084",
    "sg:province":"GA",
    "wof:name":"Knock 3xs",
    "wof:placetype":"venue"
},
  "geometry": {"coordinates":[-84.223702,33.888119],"type":"Point"}
}