{
  "type": "Feature",
  "properties": {
    "addr:full":"216 Northridge Dr Acworth GA 30101",
    "addr:housenumber":"216",
    "addr:postcode":"30101",
    "addr:street":"Northridge Dr",
    "iso:country":"US",
    "sg:address":"216 Northridge Dr",
    "sg:city":"Acworth",
    "sg:classifiers":[
        {
            "category":"Professional",
            "subcategory":"Computer Services",
            "type":"Services"
        }
    ],
    "sg:phone":"+1 770 966 5203",
    "sg:postcode":"30101",
    "sg:province":"GA",
    "sg:tags":[
        "wiring"
    ],
    "wof:name":"Net Comm Cabling Systems",
    "wof:placetype":"venue"
},
  "geometry": {"coordinates":[-84.65054000000001,34.075337],"type":"Point"}
}