{
  "type": "Feature",
  "properties": {
    "iso:country":"US",
    "sg:address":"5419 Forest Brook Pkwy",
    "sg:city":"Marietta",
    "sg:classifiers":[
        {
            "category":"Building & Trades",
            "subcategory":"Construction",
            "type":"Services"
        }
    ],
    "sg:phone":"+1 770 560 6899",
    "sg:postcode":"30068",
    "sg:province":"GA",
    "sg:tags":[
        "home",
        "builder",
        "residential"
    ],
    "wof:name":"Carolinia Homes",
    "wof:placetype":"venue"
},
  "geometry": {"coordinates":[-84.395127,33.976146],"type":"Point"}
}