{
  "type": "Feature",
  "properties": {
    "iso:country":"US",
    "sg:address":"1650 Dove Ct",
    "sg:city":"Marietta",
    "sg:classifiers":[
        {
            "category":"Manufacturing",
            "subcategory":"Tools & Machinery",
            "type":"Manufacturing & Wholesale Goods"
        }
    ],
    "sg:phone":"+1 770 499 9416",
    "sg:postcode":"30064",
    "sg:province":"GA",
    "sg:tags":[
        "mfg",
        "forklift",
        "accessory"
    ],
    "wof:name":"Jlc Industries Inc",
    "wof:placetype":"venue"
},
  "geometry": {"coordinates":[-84.63443599999999,33.914406],"type":"Point"}
}