{
  "type": "Feature",
  "properties": {
    "iso:country":"US",
    "sg:address":"290 Merchants Dr",
    "sg:city":"Dallas",
    "sg:classifiers":[
        {
            "category":"Health Services",
            "subcategory":"Chiropractor",
            "type":"Services"
        }
    ],
    "sg:phone":"+1 770 445 9161",
    "sg:postcode":"30132",
    "sg:province":"GA",
    "wof:name":"Penney Family Chiropractic",
    "wof:placetype":"venue"
},
  "geometry": {"coordinates":[-84.824078,33.913752],"type":"Point"}
}