{
  "type": "Feature",
  "properties": {
    "addr:full":"2500 Hospital Blvd Ste 250 Roswell GA 30076",
    "addr:housenumber":"2500",
    "addr:postcode":"30076",
    "addr:street":"Hospital Blvd Ste 250",
    "iso:country":"US",
    "sg:address":"2500 Hospital Blvd Ste 250",
    "sg:city":"Roswell",
    "sg:classifiers":[
        {
            "category":"Health Services",
            "subcategory":"Doctor",
            "type":"Services"
        }
    ],
    "sg:phone":"+1 770 442 1111",
    "sg:postcode":"30076",
    "sg:province":"GA",
    "sg:tags":[
        "medicine",
        "internal"
    ],
    "wof:name":"North Fulton Internal Medicine",
    "wof:placetype":"venue"
},
  "geometry": {"coordinates":[-84.320198,34.061901],"type":"Point"}
}