{
  "type": "Feature",
  "properties": {
    "addr:full":"6154 Memorial Dr Stone Mountain GA 30083",
    "addr:housenumber":"6154",
    "addr:postcode":"30083",
    "addr:street":"Memorial Dr",
    "iso:country":"US",
    "sg:address":"6154 Memorial Dr",
    "sg:city":"Stone Mountain",
    "sg:classifiers":[
        {
            "category":"Retail",
            "subcategory":"Auto Rental",
            "type":"Services"
        }
    ],
    "sg:phone":"+1 678 476 9193",
    "sg:postcode":"30083",
    "sg:province":"GA",
    "sg:tags":[
        "renting",
        "truck",
        "leasing"
    ],
    "wof:name":"Budget Truck Rental",
    "wof:placetype":"venue"
},
  "geometry": {"coordinates":[-84.19277200000001,33.803094],"type":"Point"}
}