{
  "type": "Feature",
  "properties": {
    "addr:full":"14845 US Hwy 27 Franklin GA 30217",
    "addr:housenumber":"14845",
    "addr:postcode":"30217",
    "addr:street":"Us Hwy 27",
    "iso:country":"US",
    "sg:address":"14845 US Hwy 27",
    "sg:city":"Franklin",
    "sg:classifiers":[
        {
            "category":"Autos & Motor Vehicles",
            "subcategory":"Auto Supplies",
            "type":"Retail Goods"
        }
    ],
    "sg:phone":"+1 770 854 4158",
    "sg:postcode":"30217",
    "sg:province":"GA",
    "sg:tags":[
        "machinery"
    ],
    "wof:name":"Sheldon Enterprises",
    "wof:placetype":"venue"
},
  "geometry": {"coordinates":[-85.10549899999999,33.363781],"type":"Point"}
}