{
  "type": "Feature",
  "properties": {
    "addr:full":"942 Waverly Dr Lawrenceville GA 30045",
    "addr:housenumber":"942",
    "addr:postcode":"30045",
    "addr:street":"Waverly Dr",
    "iso:country":"US",
    "sg:address":"942 Waverly Dr",
    "sg:city":"Lawrenceville",
    "sg:classifiers":[
        {
            "category":"Building & Trades",
            "subcategory":"Construction",
            "type":"Services"
        }
    ],
    "sg:phone":"+1 678 376 5328",
    "sg:postcode":"30045",
    "sg:province":"GA",
    "sg:tags":[
        "masonry",
        "contractor"
    ],
    "wof:name":"Uribe's Masonry Inc",
    "wof:placetype":"venue"
},
  "geometry": {"coordinates":[-83.965563,33.930654],"type":"Point"}
}