{
  "type": "Feature",
  "properties": {
    "addr:full":"2206 Hanfred Ln Tucker GA 30084",
    "addr:housenumber":"2206",
    "addr:postcode":"30084",
    "addr:street":"Hanfred Ln",
    "iso:country":"US",
    "sg:address":"2206 Hanfred Ln",
    "sg:city":"Tucker",
    "sg:classifiers":[
        {
            "category":"Health Services",
            "subcategory":"Nursing And Care Facility",
            "type":"Services"
        }
    ],
    "sg:phone":"+1 770 908 1999",
    "sg:postcode":"30084",
    "sg:province":"GA",
    "sg:tags":[
        "personal",
        "home"
    ],
    "wof:name":"Primary Home Health Care",
    "wof:placetype":"venue"
},
  "geometry": {"coordinates":[-84.210042,33.847851],"type":"Point"}
}