{
  "type": "Feature",
  "properties": {
    "iso:country":"US",
    "sg:address":"2100 Riveredge Pkwy NW",
    "sg:city":"Atlanta",
    "sg:classifiers":[
        {
            "category":"Building & Trades",
            "subcategory":"Construction",
            "type":"Services"
        }
    ],
    "sg:phone":"+1 770 980 8183",
    "sg:postcode":"30328",
    "sg:province":"GA",
    "sg:tags":[
        "contractor"
    ],
    "wof:name":"Mc Carthy Building Co",
    "wof:placetype":"venue"
},
  "geometry": {"coordinates":[-84.438748,33.909986],"type":"Point"}
}