{
  "type": "Feature",
  "properties": {
    "iso:country":"US",
    "sg:address":"2735 Princeton Trce",
    "sg:city":"Cumming",
    "sg:classifiers":[
        {
            "category":"Real Estate",
            "subcategory":"Real Estate Agent",
            "type":"Services"
        }
    ],
    "sg:phone":"+1 678 513 0624",
    "sg:postcode":"30041",
    "sg:province":"GA",
    "wof:name":"Princeton Square",
    "wof:placetype":"venue"
},
  "geometry": {"coordinates":[-84.093529,34.162245],"type":"Point"}
}