{
  "type": "Feature",
  "properties": {
    "iso:country":"US",
    "sg:address":"4584 Forest Green Dr",
    "sg:city":"Buford",
    "sg:classifiers":[
        {
            "category":"Organizations",
            "subcategory":"Non-profit Organization",
            "type":"Services"
        },
        {
            "category":"Professional",
            "subcategory":"Accounting & Tax Preparation",
            "type":"Services"
        }
    ],
    "sg:phone":"+1 770 614 6777",
    "sg:postcode":"30518",
    "sg:province":"GA",
    "sg:tags":[
        "medical",
        "management",
        "billing"
    ],
    "wof:name":"Pro Claims Medical Management",
    "wof:placetype":"venue"
},
  "geometry": {"coordinates":[-84.027781,34.096953],"type":"Point"}
}