{
  "type": "Feature",
  "properties": {
    "addr:full":"2129 Riverside Dr Macon GA 31204",
    "addr:housenumber":"2129",
    "addr:postcode":"31204",
    "addr:street":"Riverside Dr",
    "iso:country":"US",
    "sg:address":"2129 Riverside Dr",
    "sg:city":"Macon",
    "sg:classifiers":[
        {
            "category":"Professional",
            "subcategory":"Business Services",
            "type":"Services"
        }
    ],
    "sg:phone":"+1 478 745 0813",
    "sg:postcode":"31204",
    "sg:province":"GA",
    "sg:tags":[
        "financial"
    ],
    "wof:name":"Citifinancial",
    "wof:placetype":"venue"
},
  "geometry": {"coordinates":[-83.65056,32.862227],"type":"Point"}
}