{
  "type": "Feature",
  "properties": {
    "iso:country":"US",
    "sg:address":"2015 Dahlonega Hwy",
    "sg:city":"Cumming",
    "sg:classifiers":[
        {
            "category":"Utilities",
            "subcategory":"Refuse",
            "type":"Services"
        }
    ],
    "sg:phone":"+1 770 887 0030",
    "sg:postcode":"30040",
    "sg:province":"GA",
    "sg:tags":[
        "disposal",
        "waste"
    ],
    "wof:name":"Enviropro",
    "wof:placetype":"venue"
},
  "geometry": {"coordinates":[-84.106285,34.253997],"type":"Point"}
}