{
  "type": "Feature",
  "properties": {
    "addr:full":"236 Twin Oak Dr Guyton GA 31312",
    "addr:housenumber":"236",
    "addr:postcode":"31312",
    "addr:street":"Twin Oak Dr",
    "iso:country":"US",
    "sg:address":"236 Twin Oak Dr",
    "sg:city":"Guyton",
    "sg:classifiers":[
        {
            "category":"Health Services",
            "subcategory":"Doctor",
            "type":"Services"
        },
        {
            "category":"Health Services",
            "subcategory":"Hospital",
            "type":"Services"
        }
    ],
    "sg:phone":"+1 912 921 5482",
    "sg:postcode":"31312",
    "sg:province":"GA",
    "sg:tags":[
        "consultant",
        "medical",
        "practice",
        "nursing",
        "home"
    ],
    "wof:name":"Lefavi/Associates",
    "wof:placetype":"venue"
},
  "geometry": {"coordinates":[-81.30264699999999,32.182558],"type":"Point"}
}