{
  "type": "Feature",
  "properties": {
    "iso:country":"US",
    "sg:address":"333 Theodore Cox Cir",
    "sg:city":"Canton",
    "sg:classifiers":[
        {
            "category":"Building & Trades",
            "subcategory":"Construction",
            "type":"Services"
        }
    ],
    "sg:phone":"+1 678 493 2927",
    "sg:postcode":"30114",
    "sg:province":"GA",
    "sg:tags":[
        "house"
    ],
    "wof:name":"Dutchmen Home Repair",
    "wof:placetype":"venue"
},
  "geometry": {"coordinates":[-84.513592,34.306769],"type":"Point"}
}