{
  "type": "Feature",
  "properties": {
    "iso:country":"US",
    "sg:address":"7501 Midland Rd",
    "sg:city":"Midland",
    "sg:classifiers":[
        {
            "category":"Home & Garden",
            "subcategory":"Carpets & Floor Coverings",
            "type":"Retail Goods"
        }
    ],
    "sg:phone":"+1 706 561 4141",
    "sg:postcode":"31820",
    "sg:province":"GA",
    "wof:name":"A Cleaner Carpet",
    "wof:placetype":"venue"
},
  "geometry": {"coordinates":[-84.79554400000001,32.56492],"type":"Point"}
}