{
  "type": "Feature",
  "properties": {
    "iso:country":"US",
    "sg:address":"600 Brook Landing Ct",
    "sg:city":"Alpharetta",
    "sg:classifiers":[
        {
            "category":"Building & Trades",
            "subcategory":"Plumbing",
            "type":"Services"
        }
    ],
    "sg:phone":"+1 770 964 9068",
    "sg:postcode":"30005",
    "sg:province":"GA",
    "sg:tags":[
        "contractor"
    ],
    "wof:name":"Fulton Mechanical",
    "wof:placetype":"venue"
},
  "geometry": {"coordinates":[-84.242136,34.068384],"type":"Point"}
}