{
  "type": "Feature",
  "properties": {
    "iso:country":"US",
    "sg:address":"105 Bainbridge St",
    "sg:city":"Dublin",
    "sg:classifiers":[
        {
            "category":"Building & Trades",
            "subcategory":"Construction",
            "type":"Services"
        }
    ],
    "sg:phone":"+1 478 275 3350",
    "sg:postcode":"31021",
    "sg:province":"GA",
    "sg:tags":[
        "installs",
        "auto",
        "storefront",
        "glass"
    ],
    "wof:name":"Ricks Glass Company",
    "wof:placetype":"venue"
},
  "geometry": {"coordinates":[-82.899461,32.543122],"type":"Point"}
}