{
  "type": "Feature",
  "properties": {
    "addr:full":"4197 Summer Wood Dr Snellville GA 30039",
    "addr:housenumber":"4197",
    "addr:postcode":"30039",
    "addr:street":"Summer Wood Dr",
    "iso:country":"US",
    "sg:address":"4197 Summer Wood Dr",
    "sg:city":"Snellville",
    "sg:classifiers":[
        {
            "category":"Building & Trades",
            "subcategory":"Construction",
            "type":"Services"
        }
    ],
    "sg:phone":"+1 404 414 7007",
    "sg:postcode":"30039",
    "sg:province":"GA",
    "sg:tags":[
        "home",
        "improvement"
    ],
    "wof:name":"Southern Styling",
    "wof:placetype":"venue"
},
  "geometry": {"coordinates":[-84.012049,33.795477],"type":"Point"}
}