{
  "type": "Feature",
  "properties": {
    "iso:country":"US",
    "sg:address":"1431 N Columbia St",
    "sg:city":"Milledgeville",
    "sg:classifiers":[
        {
            "category":"Insurance",
            "subcategory":"Insurance Agent",
            "type":"Services"
        }
    ],
    "sg:phone":"+1 478 451 5338",
    "sg:postcode":"31061",
    "sg:province":"GA",
    "sg:tags":[
        "agency"
    ],
    "wof:name":"Direct General Insurance Agcy",
    "wof:placetype":"venue"
},
  "geometry": {"coordinates":[-83.240683,33.095794],"type":"Point"}
}