{
  "type": "Feature",
  "properties": {
    "addr:full":"125 Kingswood Dr Fayetteville GA 30215",
    "addr:housenumber":"125",
    "addr:postcode":"30215",
    "addr:street":"Kingswood Dr",
    "iso:country":"US",
    "sg:address":"125 Kingswood Dr",
    "sg:city":"Fayetteville",
    "sg:classifiers":[
        {
            "category":"Banks & Credit Unions",
            "subcategory":"Financial Services",
            "type":"Services"
        }
    ],
    "sg:phone":"+1 770 719 8385",
    "sg:postcode":"30215",
    "sg:province":"GA",
    "wof:name":"Ekklesia Financial Services",
    "wof:placetype":"venue"
},
  "geometry": {"coordinates":[-84.44451100000001,33.414939],"type":"Point"}
}