{
  "type": "Feature",
  "properties": {
    "iso:country":"US",
    "sg:address":"109 Bradford St S",
    "sg:city":"Gainesville",
    "sg:classifiers":[
        {
            "category":"Shopping",
            "type":"Retail Goods"
        }
    ],
    "sg:phone":"+1 770 297 0077",
    "sg:postcode":"30501",
    "sg:province":"GA",
    "sg:tags":[
        "art",
        "gallery",
        "dealer"
    ],
    "wof:name":"Side Street Studio Inc",
    "wof:placetype":"venue"
},
  "geometry": {"coordinates":[-83.82659099999999,34.299555],"type":"Point"}
}