{
  "type": "Feature",
  "properties": {
    "addr:full":"443 Highland Ave Augusta GA 30904",
    "addr:housenumber":"443",
    "addr:postcode":"30904",
    "addr:street":"Highland Ave",
    "iso:country":"US",
    "sg:address":"443 Highland Ave",
    "sg:city":"Augusta",
    "sg:classifiers":[
        {
            "category":"Shopping",
            "subcategory":"Gifts & Souvenirs",
            "type":"Retail Goods"
        }
    ],
    "sg:phone":"+1 706 738 8386",
    "sg:postcode":"30904",
    "sg:province":"GA",
    "sg:tags":[
        "shop"
    ],
    "wof:name":"Sweetbrier Fair",
    "wof:placetype":"venue"
},
  "geometry": {"coordinates":[-82.030038,33.484802],"type":"Point"}
}