{
  "type": "Feature",
  "properties": {
    "iso:country":"US",
    "sg:address":"1335 Kilgore Rd",
    "sg:city":"Lithonia",
    "sg:classifiers":[
        {
            "category":"Building & Trades",
            "subcategory":"Landscaping Services",
            "type":"Services"
        }
    ],
    "sg:phone":"+1 770 469 2420",
    "sg:postcode":"30058",
    "sg:province":"GA",
    "wof:name":"Durden Curtis Landscaping Co",
    "wof:placetype":"venue"
},
  "geometry": {"coordinates":[-84.1391,33.756211],"type":"Point"}
}