{
  "type": "Feature",
  "properties": {
    "addr:full":"198 Ponce de Leon Ave NE Atlanta GA 30308",
    "addr:housenumber":"198",
    "addr:postcode":"30308",
    "addr:street":"Ponce De Leon Ave Ne",
    "iso:country":"US",
    "sg:address":"198 Ponce de Leon Ave NE",
    "sg:city":"Atlanta",
    "sg:classifiers":[
        {
            "category":"Professional",
            "type":"Services"
        }
    ],
    "sg:phone":"+1 404 541 6606",
    "sg:postcode":"30308",
    "sg:province":"GA",
    "sg:tags":[
        "establishment"
    ],
    "wof:name":"Billmatrix",
    "wof:placetype":"venue"
},
  "geometry": {"coordinates":[-84.38113800000001,33.772599],"type":"Point"}
}