{
  "type": "Feature",
  "properties": {
    "addr:full":"920 Holly Springs Dr Thomasville GA 31792",
    "addr:housenumber":"920",
    "addr:postcode":"31792",
    "addr:street":"Holly Springs Dr",
    "iso:country":"US",
    "sg:address":"920 Holly Springs Dr",
    "sg:city":"Thomasville",
    "sg:classifiers":[
        {
            "category":"Manufacturing",
            "subcategory":"Buildings",
            "type":"Manufacturing & Wholesale Goods"
        }
    ],
    "sg:phone":"+1 229 226 0102",
    "sg:postcode":"31792",
    "sg:province":"GA",
    "sg:tags":[
        "home",
        "builder"
    ],
    "wof:name":"Foy Construction Co",
    "wof:placetype":"venue"
},
  "geometry": {"coordinates":[-83.98547600000001,30.902932],"type":"Point"}
}