{
  "type": "Feature",
  "properties": {
    "addr:full":"4250 Keith Bridge Rd Cumming GA 30041",
    "addr:housenumber":"4250",
    "addr:postcode":"30041",
    "addr:street":"Keith Bridge Rd",
    "iso:country":"US",
    "sg:address":"4250 Keith Bridge Rd",
    "sg:city":"Cumming",
    "sg:classifiers":[
        {
            "category":"Professional",
            "subcategory":"Detective & Security Services",
            "type":"Services"
        }
    ],
    "sg:phone":"+1 770 205 0789",
    "sg:postcode":"30041",
    "sg:province":"GA",
    "sg:tags":[
        "perimeter",
        "terrorist",
        "for",
        "barrier",
        "counter",
        "gov"
    ],
    "wof:name":"Secureusa Inc",
    "wof:placetype":"venue"
},
  "geometry": {"coordinates":[-84.054545,34.269404],"type":"Point"}
}