{
  "type": "Feature",
  "properties": {
    "addr:full":"1567 Mount Vernon Rd Atlanta GA 30338",
    "addr:housenumber":"1567",
    "addr:postcode":"30338",
    "addr:street":"Mount Vernon Rd",
    "iso:country":"US",
    "sg:address":"1567 Mount Vernon Rd",
    "sg:city":"Atlanta",
    "sg:classifiers":[
        {
            "category":"Building & Trades",
            "subcategory":"Plumbing",
            "type":"Services"
        },
        {
            "category":"Building & Trades",
            "subcategory":"Cleaning & Sanitation",
            "type":"Services"
        }
    ],
    "sg:phone":"+1 770 394 6729",
    "sg:postcode":"30338",
    "sg:province":"GA",
    "sg:tags":[
        "floor",
        "restaurant",
        "equipment-cleaning",
        "waxing",
        "polishing",
        "janitorial",
        "cleaners-interior"
    ],
    "sg:website":"http://customer_does_not_have_a_website",
    "wof:name":"Uptown Services",
    "wof:placetype":"venue"
},
  "geometry": {"coordinates":[-84.335617,33.945478],"type":"Point"}
}