{
  "type": "Feature",
  "properties": {
    "addr:full":"2359 Windy Hill Rd SE Ste 320 Marietta GA 30067",
    "addr:housenumber":"2359",
    "addr:postcode":"30067",
    "addr:street":"Windy Hill Rd Se Ste 320",
    "iso:country":"US",
    "sg:address":"2359 Windy Hill Rd SE Ste 320",
    "sg:city":"Marietta",
    "sg:classifiers":[
        {
            "category":"Health Services",
            "subcategory":"Doctor",
            "type":"Services"
        },
        {
            "category":"Health Services",
            "subcategory":"Chiropractor",
            "type":"Services"
        }
    ],
    "sg:phone":"+1 678 905 4436",
    "sg:postcode":"30067",
    "sg:province":"GA",
    "sg:tags":[
        "physician",
        "surgeon",
        "chiropractic"
    ],
    "sg:website":"http://atlanta.citysearch.com/profile/external/651230340/marietta_ga/dr_anthony_bartolo_cobb_pain_rehabilitat.html?publisher=yellowpages&reference_id=15&placement=ypwebsitemip",
    "wof:name":"Dr. Anthony Bartolo - Cobb Pain & Rehabilitat",
    "wof:placetype":"venue"
},
  "geometry": {"coordinates":[-84.48297100000001,33.903599],"type":"Point"}
}