{
  "type": "Feature",
  "properties": {
    "addr:full":"5727 Pinedale Cir Buford GA 30518",
    "addr:housenumber":"5727",
    "addr:postcode":"30518",
    "addr:street":"Pinedale Cir",
    "iso:country":"US",
    "sg:address":"5727 Pinedale Cir",
    "sg:city":"Buford",
    "sg:classifiers":[
        {
            "category":"Professional",
            "subcategory":"Art Services",
            "type":"Services"
        }
    ],
    "sg:phone":"+1 770 271 2719",
    "sg:postcode":"30518",
    "sg:province":"GA",
    "sg:tags":[
        "commercial",
        "graphic",
        "design",
        "designer"
    ],
    "wof:name":"Infinite Creation",
    "wof:placetype":"venue"
},
  "geometry": {"coordinates":[-84.05596199999999,34.113125],"type":"Point"}
}