{
  "type": "Feature",
  "properties": {
    "addr:full":"1133 Alabama St Carrollton GA 30117",
    "addr:housenumber":"1133",
    "addr:postcode":"30117",
    "addr:street":"Alabama St",
    "iso:country":"US",
    "sg:address":"1133 Alabama St",
    "sg:city":"Carrollton",
    "sg:phone":"+1 770 832 7762",
    "sg:postcode":"30117",
    "sg:province":"GA",
    "sg:tags":[
        "product",
        "petroleum"
    ],
    "wof:name":"Carl Fort Oil Co",
    "wof:placetype":"venue"
},
  "geometry": {"coordinates":[-85.104896,33.588591],"type":"Point"}
}