{
  "type": "Feature",
  "properties": {
    "iso:country":"US",
    "sg:address":"18 Shepard Ray Rd",
    "sg:city":"Hazlehurst",
    "sg:classifiers":[
        {
            "category":"Building & Trades",
            "subcategory":"Plumbing",
            "type":"Services"
        },
        {
            "category":"Home & Garden",
            "subcategory":"Building Materials",
            "type":"Retail Goods"
        },
        {
            "category":"Building & Trades",
            "subcategory":"Construction",
            "type":"Services"
        }
    ],
    "sg:phone":"+1 912 375 2636",
    "sg:postcode":"31539",
    "sg:province":"GA",
    "sg:tags":[
        "plumber",
        "industrial",
        "altering",
        "improvement",
        "contractors-commercial",
        "contractor",
        "remodeling"
    ],
    "wof:name":"Jeff Davis Plumbing Inc",
    "wof:placetype":"venue"
},
  "geometry": {"coordinates":[-82.468959,31.923504],"type":"Point"}
}