{
  "type": "Feature",
  "properties": {
    "addr:full":"25 Buck Trl Social Circle GA 30025",
    "addr:housenumber":"25",
    "addr:postcode":"30025",
    "addr:street":"Buck Trl;Circle",
    "iso:country":"US",
    "sg:address":"25 Buck Trl",
    "sg:city":"Social Circle",
    "sg:classifiers":[
        {
            "category":"Building & Trades",
            "subcategory":"Landscaping Services",
            "type":"Services"
        }
    ],
    "sg:phone":"+1 770 377 7989",
    "sg:postcode":"30025",
    "sg:province":"GA",
    "wof:name":"Frixs Lawn Care",
    "wof:placetype":"venue"
},
  "geometry": {"coordinates":[-83.714561,33.591212],"type":"Point"}
}