{
  "type": "Feature",
  "properties": {
    "addr:full":"5019 Old Ivy Rd NW Duluth GA 30096",
    "addr:housenumber":"5019",
    "addr:postcode":"30096",
    "addr:street":"Old Ivy Rd Nw",
    "iso:country":"US",
    "sg:address":"5019 Old Ivy Rd NW",
    "sg:city":"Duluth",
    "sg:classifiers":[
        {
            "category":"Professional",
            "subcategory":"Business Services",
            "type":"Services"
        }
    ],
    "sg:phone":"+1 770 448 4147",
    "sg:postcode":"30096",
    "sg:province":"GA",
    "sg:tags":[
        "plant",
        "design",
        "maintenance"
    ],
    "wof:name":"Petal Pushers Inc",
    "wof:placetype":"venue"
},
  "geometry": {"coordinates":[-84.20771999999999,33.982583],"type":"Point"}
}