{
  "type": "Feature",
  "properties": {
    "iso:country":"US",
    "sg:address":"4360 Commerce Cir SW",
    "sg:city":"Atlanta",
    "sg:classifiers":[
        {
            "category":"Wholesale",
            "subcategory":"Machinery & Supplies",
            "type":"Manufacturing & Wholesale Goods"
        }
    ],
    "sg:phone":"+1 404 505 8368",
    "sg:postcode":"30336",
    "sg:province":"GA",
    "sg:tags":[
        "baling",
        "equipment"
    ],
    "wof:name":"Baler Sales & Svc",
    "wof:placetype":"venue"
},
  "geometry": {"coordinates":[-84.53482,33.760888],"type":"Point"}
}