{
  "type": "Feature",
  "properties": {
    "addr:full":"603 Townsend Pl Powder Springs GA 30127",
    "addr:housenumber":"603",
    "addr:postcode":"30127",
    "addr:street":"Townsend Pl",
    "iso:country":"US",
    "sg:address":"603 Townsend Pl",
    "sg:city":"Powder Springs",
    "sg:classifiers":[
        {
            "category":"Insurance",
            "subcategory":"Insurance Agent",
            "type":"Services"
        }
    ],
    "sg:phone":"+1 770 422 9003",
    "sg:postcode":"30127",
    "sg:province":"GA",
    "wof:name":"Ron Dorminy Agency Inc",
    "wof:placetype":"venue"
},
  "geometry": {"coordinates":[-84.66519599999999,33.937787],"type":"Point"}
}