{
  "type": "Feature",
  "properties": {
    "addr:full":"326 Old Plantation Rd Augusta GA 30907",
    "addr:housenumber":"326",
    "addr:postcode":"30907",
    "addr:street":"Old Plantation Rd",
    "iso:country":"US",
    "sg:address":"326 Old Plantation Rd",
    "sg:city":"Augusta",
    "sg:classifiers":[
        {
            "category":"Building & Trades",
            "subcategory":"Cleaning & Sanitation",
            "type":"Services"
        }
    ],
    "sg:phone":"+1 706 860 5899",
    "sg:postcode":"30907",
    "sg:province":"GA",
    "sg:tags":[
        "maintenance"
    ],
    "wof:name":"Unique Cleaning Services",
    "wof:placetype":"venue"
},
  "geometry": {"coordinates":[-82.085286,33.523066],"type":"Point"}
}