{
  "type": "Feature",
  "properties": {
    "addr:full":"1109 Ferry Lake Rd Tifton GA 31794",
    "addr:housenumber":"1109",
    "addr:postcode":"31794",
    "addr:street":"Ferry Lake Rd",
    "iso:country":"US",
    "sg:address":"1109 Ferry Lake Rd",
    "sg:city":"Tifton",
    "sg:classifiers":[
        {
            "category":"Autos & Motor Vehicles",
            "subcategory":"Automobile Sales",
            "type":"Retail Goods"
        }
    ],
    "sg:phone":"+1 229 386 9057",
    "sg:postcode":"31794",
    "sg:province":"GA",
    "sg:tags":[
        "car",
        "dealer"
    ],
    "wof:name":"Brothers Auto Sales",
    "wof:placetype":"venue"
},
  "geometry": {"coordinates":[-83.489481,31.456647],"type":"Point"}
}