{
  "type": "Feature",
  "properties": {
    "addr:full":"5195 Battlefield Pkwy Ringgold GA 30736",
    "addr:housenumber":"5195",
    "addr:postcode":"30736",
    "addr:street":"Battlefield Pkwy",
    "iso:country":"US",
    "sg:address":"5195 Battlefield Pkwy",
    "sg:city":"Ringgold",
    "sg:classifiers":[
        {
            "category":"Health Services",
            "subcategory":"Doctor",
            "type":"Services"
        }
    ],
    "sg:phone":"+1 706 937 9292",
    "sg:postcode":"30736",
    "sg:province":"GA",
    "sg:tags":[
        "physician",
        "family",
        "practice",
        "surgeons",
        "medicine",
        "surgeon"
    ],
    "wof:name":"Haddock Chris MD",
    "wof:placetype":"venue"
},
  "geometry": {"coordinates":[-85.178128,34.930922],"type":"Point"}
}