{
  "type": "Feature",
  "properties": {
    "iso:country":"US",
    "sg:address":"404 Killian Hill Rd NW",
    "sg:city":"Lilburn",
    "sg:classifiers":[
        {
            "category":"Home & Garden",
            "subcategory":"Carpets & Floor Coverings",
            "type":"Retail Goods"
        }
    ],
    "sg:phone":"+1 770 923 2455",
    "sg:postcode":"30047",
    "sg:province":"GA",
    "sg:tags":[
        "carpeting",
        "store"
    ],
    "wof:name":"Gene Austin Carpet",
    "wof:placetype":"venue"
},
  "geometry": {"coordinates":[-84.137199,33.8946],"type":"Point"}
}