{
  "type": "Feature",
  "properties": {
    "iso:country":"US",
    "sg:address":"5235 Log Cabin Dr",
    "sg:city":"Macon",
    "sg:classifiers":[
        {
            "category":"Social Services",
            "subcategory":"Child Care",
            "type":"Services"
        }
    ],
    "sg:phone":"+1 478 788 5353",
    "sg:postcode":"31204",
    "sg:province":"GA",
    "sg:tags":[
        "day"
    ],
    "wof:name":"C N I 16",
    "wof:placetype":"venue"
},
  "geometry": {"coordinates":[-83.70746200000001,32.811355],"type":"Point"}
}