{
  "type": "Feature",
  "properties": {
    "iso:country":"US",
    "sg:address":"736 Kadi Dr",
    "sg:city":"Hinesville",
    "sg:classifiers":[
        {
            "category":"Freight",
            "type":"Transportation"
        }
    ],
    "sg:phone":"+1 912 877 0744",
    "sg:postcode":"31313",
    "sg:province":"GA",
    "sg:tags":[
        "operator",
        "trucking"
    ],
    "wof:name":"E J Trucking",
    "wof:placetype":"venue"
},
  "geometry": {"coordinates":[-81.61271600000001,31.815921],"type":"Point"}
}