{
  "type": "Feature",
  "properties": {
    "iso:country":"US",
    "sg:address":"1000 Windward Concourse",
    "sg:city":"Alpharetta",
    "sg:classifiers":[
        {
            "category":"Social Services",
            "type":"Services"
        }
    ],
    "sg:phone":"+1 678 393 7300",
    "sg:postcode":"30005",
    "sg:province":"GA",
    "sg:tags":[
        "organization",
        "welfare"
    ],
    "sg:website":"www.genesisadoptions.org",
    "wof:name":"Genesis Adoptions",
    "wof:placetype":"venue"
},
  "geometry": {"coordinates":[-84.24088999999999,34.099261],"type":"Point"}
}