{
  "type": "Feature",
  "properties": {
    "iso:country":"US",
    "sg:address":"115 Alford St",
    "sg:city":"La Grange",
    "sg:classifiers":[
        {
            "category":"Education",
            "subcategory":"Library",
            "type":"Public Place"
        }
    ],
    "sg:phone":"+1 706 882 7784",
    "sg:postcode":"30240",
    "sg:province":"GA",
    "sg:tags":[
        "book"
    ],
    "wof:name":"LA GRANGE MEMORIAL LIBRARY",
    "wof:placetype":"venue"
},
  "geometry": {"coordinates":[-85.038071,33.038535],"type":"Point"}
}