{
  "type": "Feature",
  "properties": {
    "addr:full":"1036 Legacy Walk Woodstock GA 30189",
    "addr:housenumber":"1036",
    "addr:postcode":"30189",
    "addr:street":"Legacy Walk",
    "iso:country":"US",
    "sg:address":"1036 Legacy Walk",
    "sg:city":"Woodstock",
    "sg:classifiers":[
        {
            "category":"Professional",
            "subcategory":"Management & Consulting",
            "type":"Services"
        }
    ],
    "sg:phone":"+1 770 924 6776",
    "sg:postcode":"30189",
    "sg:province":"GA",
    "sg:tags":[
        "business"
    ],
    "wof:name":"Employees Assessment Solutions",
    "wof:placetype":"venue"
},
  "geometry": {"coordinates":[-84.55723399999999,34.10353],"type":"Point"}
}