{
  "type": "Feature",
  "properties": {
    "iso:country":"US",
    "sg:address":"655 Highland Ave NE",
    "sg:city":"Atlanta",
    "sg:classifiers":[
        {
            "category":"Restaurant",
            "type":"Food & Drink"
        },
        {
            "category":"Bakery",
            "type":"Food & Drink"
        }
    ],
    "sg:phone":"+1 404 586 0772",
    "sg:postcode":"30312",
    "sg:province":"GA",
    "sg:tags":[
        "brunch",
        "breakfast"
    ],
    "sg:website":"www.highlandbakery.com",
    "wof:name":"Highland Bakery",
    "wof:placetype":"venue"
},
  "geometry": {"coordinates":[-84.36592899999999,33.760976],"type":"Point"}
}