{
  "type": "Feature",
  "properties": {
    "iso:country":"US",
    "sg:address":"500 S Broad St",
    "sg:city":"Cairo",
    "sg:classifiers":[
        {
            "category":"Social Services",
            "subcategory":"Child Care",
            "type":"Services"
        },
        {
            "category":"Education",
            "subcategory":"School",
            "type":"Public Place"
        }
    ],
    "sg:phone":"+1 229 377 8029",
    "sg:postcode":"39828",
    "sg:province":"GA",
    "sg:tags":[
        "kindergarten",
        "academic"
    ],
    "wof:name":"Children's Corner",
    "wof:placetype":"venue"
},
  "geometry": {"coordinates":[-84.208212,30.87127],"type":"Point"}
}