{
  "type": "Feature",
  "properties": {
    "iso:country":"US",
    "sg:address":"529 W Jackson St",
    "sg:city":"Thomasville",
    "sg:classifiers":[
        {
            "category":"Autos & Motor Vehicles",
            "subcategory":"Auto Supplies",
            "type":"Retail Goods"
        }
    ],
    "sg:phone":"+1 229 228 4200",
    "sg:postcode":"31792",
    "sg:province":"GA",
    "wof:name":"Amoco Auto Service Center",
    "wof:placetype":"venue"
},
  "geometry": {"coordinates":[-83.983958,30.832605],"type":"Point"}
}