{
  "type": "Feature",
  "properties": {
    "addr:full":"81 Barn St Gainesville GA 30501",
    "addr:housenumber":"81",
    "addr:postcode":"30501",
    "addr:street":"Barn St",
    "iso:country":"US",
    "sg:address":"81 Barn St",
    "sg:city":"Gainesville",
    "sg:classifiers":[
        {
            "category":"Organizations",
            "subcategory":"Religious Organization",
            "type":"Services"
        }
    ],
    "sg:phone":"+1 770 531 9002",
    "sg:postcode":"30501",
    "sg:province":"GA",
    "sg:tags":[
        "church"
    ],
    "wof:name":"New Holland Congregational",
    "wof:placetype":"venue"
},
  "geometry": {"coordinates":[-83.808876,34.303647],"type":"Point"}
}