{
  "type": "Feature",
  "properties": {
    "addr:full":"1830 Vassar St Savannah GA 31405",
    "addr:housenumber":"1830",
    "addr:postcode":"31405",
    "addr:street":"Vassar St",
    "iso:country":"US",
    "sg:address":"1830 Vassar St",
    "sg:city":"Savannah",
    "sg:classifiers":[
        {
            "category":"Professional",
            "type":"Services"
        }
    ],
    "sg:phone":"+1 912 233 7884",
    "sg:postcode":"31405",
    "sg:province":"GA",
    "wof:name":"Charles Johnson",
    "wof:placetype":"venue"
},
  "geometry": {"coordinates":[-81.138398,32.04321],"type":"Point"}
}