{
  "type": "Feature",
  "properties": {
    "addr:full":"4417 Village Square Ln Stone Mountain GA 30083",
    "addr:housenumber":"4417",
    "addr:postcode":"30083",
    "addr:street":"Village Square Ln",
    "iso:country":"US",
    "sg:address":"4417 Village Square Ln",
    "sg:city":"Stone Mountain",
    "sg:classifiers":[
        {
            "category":"Arts & Performance",
            "subcategory":"Theater",
            "type":"Entertainment"
        }
    ],
    "sg:phone":"+1 404 294 0479",
    "sg:postcode":"30083",
    "sg:province":"GA",
    "sg:tags":[
        "bureau"
    ],
    "wof:name":"Pioneer Productions",
    "wof:placetype":"venue"
},
  "geometry": {"coordinates":[-84.213801,33.790267],"type":"Point"}
}