{
  "type": "Feature",
  "properties": {
    "addr:full":"5300 Spalding Dr Norcross GA 30092",
    "addr:housenumber":"5300",
    "addr:postcode":"30092",
    "addr:street":"Spalding Dr",
    "iso:country":"US",
    "sg:address":"5300 Spalding Dr",
    "sg:city":"Norcross",
    "sg:classifiers":[
        {
            "category":"Education",
            "subcategory":"School",
            "type":"Public Place"
        }
    ],
    "sg:phone":"+1 770 448 3674",
    "sg:postcode":"30092",
    "sg:province":"GA",
    "sg:tags":[
        "high",
        "middle",
        "elementary"
    ],
    "wof:name":"Norcross High Community School",
    "wof:placetype":"venue"
},
  "geometry": {"coordinates":[-84.21219600000001,33.968201],"type":"Point"}
}