{
  "type": "Feature",
  "properties": {
    "addr:full":"1444 Broadway Ln Macon GA 31201",
    "addr:housenumber":"1444",
    "addr:postcode":"31201",
    "addr:street":"Broadway Ln",
    "iso:country":"US",
    "sg:address":"1444 Broadway Ln",
    "sg:city":"Macon",
    "sg:classifiers":[
        {
            "category":"Wholesale",
            "subcategory":"Non-durable Goods",
            "type":"Manufacturing & Wholesale Goods"
        },
        {
            "category":"Professional",
            "subcategory":"Business Services",
            "type":"Services"
        }
    ],
    "sg:phone":"+1 478 744 6367",
    "sg:postcode":"31201",
    "sg:province":"GA",
    "sg:tags":[
        "broker",
        "merchandise",
        "merchandise-wholesale"
    ],
    "wof:name":"Megan Discounts",
    "wof:placetype":"venue"
},
  "geometry": {"coordinates":[-83.635201,32.822452],"type":"Point"}
}