{
  "type": "Feature",
  "properties": {
    "iso:country":"US",
    "sg:address":"2020 Airport Ind Park Dr",
    "sg:city":"Marietta",
    "sg:classifiers":[
        {
            "category":"Building & Trades",
            "subcategory":"Construction",
            "type":"Services"
        }
    ],
    "sg:phone":"+1 770 933 9030",
    "sg:postcode":"30060",
    "sg:province":"GA",
    "sg:tags":[
        "work",
        "carpet"
    ],
    "wof:name":"Brumark",
    "wof:placetype":"venue"
},
  "geometry": {"coordinates":[-84.498655,33.902723],"type":"Point"}
}