{
  "type": "Feature",
  "properties": {
    "addr:full":"401 S Pecan St Cordele GA 31015",
    "addr:housenumber":"401",
    "addr:postcode":"31015",
    "addr:street":"S Pecan St",
    "iso:country":"US",
    "sg:address":"401 S Pecan St",
    "sg:city":"Cordele",
    "sg:classifiers":[
        {
            "category":"Communications",
            "subcategory":"Television Station",
            "type":"Services"
        },
        {
            "category":"Communications",
            "type":"Services"
        },
        {
            "category":"Shopping",
            "subcategory":"Computers & Home Electronics",
            "type":"Retail Goods"
        }
    ],
    "sg:phone":"+1 229 273 1027",
    "sg:postcode":"31015",
    "sg:province":"GA",
    "sg:tags":[
        "sound",
        "satellite",
        "cable",
        "system",
        "equipment",
        "carrier",
        "radio",
        "communications-common",
        "store"
    ],
    "wof:name":"Directtv & Dish Network By Bailey",
    "wof:placetype":"venue"
},
  "geometry": {"coordinates":[-83.76531,31.963552],"type":"Point"}
}