{
  "type": "Feature",
  "properties": {
    "iso:country":"US",
    "sg:address":"4113 Brownlee Dr",
    "sg:city":"Tucker",
    "sg:classifiers":[
        {
            "category":"Freight",
            "type":"Transportation"
        }
    ],
    "sg:phone":"+1 770 879 1000",
    "sg:postcode":"30084",
    "sg:province":"GA",
    "sg:tags":[
        "operator",
        "local",
        "trucking"
    ],
    "wof:name":"Shuttlexpress Inc",
    "wof:placetype":"venue"
},
  "geometry": {"coordinates":[-84.22261,33.842802],"type":"Point"}
}