{
  "type": "Feature",
  "properties": {
    "iso:country":"US",
    "sg:address":"8490 Sentinae Chase Dr",
    "sg:city":"Roswell",
    "sg:classifiers":[
        {
            "category":"Banks & Credit Unions",
            "subcategory":"Financial Services",
            "type":"Services"
        }
    ],
    "sg:phone":"+1 770 640 8808",
    "sg:postcode":"30076",
    "sg:province":"GA",
    "sg:tags":[
        "investment"
    ],
    "wof:name":"Nie Investments Ltd Partnr",
    "wof:placetype":"venue"
},
  "geometry": {"coordinates":[-84.305808,33.986983],"type":"Point"}
}