{
  "type": "Feature",
  "properties": {
    "addr:full":"1405 Peter Pan Rd Lookout Mountain GA 30750",
    "addr:housenumber":"1405",
    "addr:postcode":"30750",
    "addr:street":"Peter Pan Rd",
    "iso:country":"US",
    "sg:address":"1405 Peter Pan Rd",
    "sg:city":"Lookout Mountain",
    "sg:classifiers":[
        {
            "category":"Building & Trades",
            "subcategory":"Electrical",
            "type":"Services"
        }
    ],
    "sg:phone":"+1 706 820 0994",
    "sg:postcode":"30750",
    "sg:province":"GA",
    "sg:tags":[
        "control",
        "installs",
        "drive",
        "system",
        "access",
        "electrical"
    ],
    "wof:name":"T R Clarke Company Inc",
    "wof:placetype":"venue"
},
  "geometry": {"coordinates":[-85.35280400000001,34.974064],"type":"Point"}
}