{
  "type": "Feature",
  "properties": {
    "addr:full":"26 Northstar Dr Columbus GA 31907",
    "addr:housenumber":"26",
    "addr:postcode":"31907",
    "addr:street":"Northstar Dr",
    "iso:country":"US",
    "sg:address":"26 Northstar Dr",
    "sg:city":"Columbus",
    "sg:classifiers":[
        {
            "category":"Food & Beverages",
            "subcategory":"Groceries & Convenience Stores",
            "type":"Retail Goods"
        }
    ],
    "sg:phone":"+1 706 682 9182",
    "sg:postcode":"31907",
    "sg:province":"GA",
    "wof:name":"Twins Food Mart 2",
    "wof:placetype":"venue"
},
  "geometry": {"coordinates":[-84.91001,32.441896],"type":"Point"}
}