{
  "type": "Feature",
  "properties": {
    "addr:full":"408 16th Ave E Cordele GA 31015",
    "addr:housenumber":"408",
    "addr:postcode":"31015",
    "addr:street":"16Th Ave E",
    "iso:country":"US",
    "sg:address":"408 16th Ave E",
    "sg:city":"Cordele",
    "sg:classifiers":[
        {
            "category":"Banks & Credit Unions",
            "subcategory":"Bank",
            "type":"Services"
        }
    ],
    "sg:phone":"+1 229 273 2744",
    "sg:postcode":"31015",
    "sg:province":"GA",
    "sg:tags":[
        "personal",
        "institution"
    ],
    "wof:name":"World Finance",
    "wof:placetype":"venue"
},
  "geometry": {"coordinates":[-83.777756,31.963554],"type":"Point"}
}