{
  "type": "Feature",
  "properties": {
    "iso:country":"US",
    "sg:address":"170 Southwood Ct",
    "sg:city":"Fayetteville",
    "sg:classifiers":[
        {
            "category":"Professional",
            "type":"Services"
        }
    ],
    "sg:phone":"+1 770 460 9241",
    "sg:postcode":"30214",
    "sg:province":"GA",
    "wof:name":"Grw Services Inc",
    "wof:placetype":"venue"
},
  "geometry": {"coordinates":[-84.463961,33.509084],"type":"Point"}
}