{
  "type": "Feature",
  "properties": {
    "iso:country":"US",
    "sg:address":"405 Millbrook Trce",
    "sg:city":"Marietta",
    "sg:classifiers":[
        {
            "category":"Home & Garden",
            "subcategory":"Building Materials",
            "type":"Retail Goods"
        }
    ],
    "sg:phone":"+1 770 426 4100",
    "sg:postcode":"30068",
    "sg:province":"GA",
    "sg:tags":[
        "downspouts",
        "gutter"
    ],
    "wof:name":"Any Gutter Cleaned Inc",
    "wof:placetype":"venue"
},
  "geometry": {"coordinates":[-84.467826,33.942774],"type":"Point"}
}