{
  "type": "Feature",
  "properties": {
    "addr:full":"525 King St Rome GA 30161",
    "addr:housenumber":"525",
    "addr:postcode":"ga 30161",
    "addr:street":"King St",
    "iso:country":"US",
    "sg:address":"525 King St",
    "sg:city":"Rome",
    "sg:classifiers":[
        {
            "category":"Organizations",
            "subcategory":"Community Association",
            "type":"Services"
        }
    ],
    "sg:phone":"+1 706 291 2513",
    "sg:postcode":"30161",
    "sg:province":"GA",
    "sg:tags":[
        "fraternal"
    ],
    "wof:name":"Elks Lodge",
    "wof:placetype":"venue"
},
  "geometry": {"coordinates":[-85.15993899999999,34.231509],"type":"Point"}
}