{
  "type": "Feature",
  "properties": {
    "addr:full":"765 Tala Dr Roswell GA 30022",
    "addr:housenumber":"765",
    "addr:postcode":"30022",
    "addr:street":"Tala Dr",
    "iso:country":"US",
    "sg:address":"765 Tala Dr",
    "sg:city":"Roswell",
    "sg:classifiers":[
        {
            "category":"Professional",
            "subcategory":"Business Services",
            "type":"Services"
        }
    ],
    "sg:phone":"+1 678 352 0108",
    "sg:postcode":"30022",
    "sg:province":"GA",
    "wof:name":"Changs Family Assoc Inc A Pro",
    "wof:placetype":"venue"
},
  "geometry": {"coordinates":[-84.282888,34.010262],"type":"Point"}
}