{
  "type": "Feature",
  "properties": {
    "iso:country":"US",
    "sg:address":"453 Highland Ave",
    "sg:city":"Augusta",
    "sg:classifiers":[
        {
            "category":"Shopping",
            "subcategory":"Clothing, Apparel, & Fashions",
            "type":"Retail Goods"
        }
    ],
    "sg:phone":"+1 706 729 9125",
    "sg:postcode":"30904",
    "sg:province":"GA",
    "wof:name":"Village",
    "wof:placetype":"venue"
},
  "geometry": {"coordinates":[-82.030036,33.484834],"type":"Point"}
}