{
  "type": "Feature",
  "properties": {
    "addr:full":"3273 Deans Bridge Rd Augusta GA 30906",
    "addr:housenumber":"3273",
    "addr:postcode":"30906",
    "addr:street":"Deans Bridge Rd",
    "iso:country":"US",
    "sg:address":"3273 Deans Bridge Rd",
    "sg:city":"Augusta",
    "sg:classifiers":[
        {
            "category":"Home & Garden",
            "subcategory":"Household Appliances",
            "type":"Retail Goods"
        }
    ],
    "sg:phone":"+1 706 796 0500",
    "sg:postcode":"30906",
    "sg:province":"GA",
    "wof:name":"Davis Appliance",
    "wof:placetype":"venue"
},
  "geometry": {"coordinates":[-82.06673000000001,33.420792],"type":"Point"}
}