{
  "type": "Feature",
  "properties": {
    "addr:full":"1211 Laurel St Springfield GA 31329",
    "addr:housenumber":"1211",
    "addr:postcode":"31329",
    "addr:street":"Laurel St",
    "iso:country":"US",
    "sg:address":"1211 Laurel St",
    "sg:city":"Springfield",
    "sg:classifiers":[
        {
            "category":"Social Services",
            "subcategory":"Child Care",
            "type":"Services"
        }
    ],
    "sg:phone":"+1 912 754 3742",
    "sg:postcode":"31329",
    "sg:province":"GA",
    "wof:name":"Kathy's Day Kare",
    "wof:placetype":"venue"
},
  "geometry": {"coordinates":[-81.29416399999999,32.351022],"type":"Point"}
}