{
  "type": "Feature",
  "properties": {
    "addr:full":"1009 Adair Ave NE Atlanta GA 30306",
    "addr:housenumber":"1009",
    "addr:postcode":"30306",
    "addr:street":"Adair Ave Ne",
    "iso:country":"US",
    "sg:address":"1009 Adair Ave NE",
    "sg:city":"Atlanta",
    "sg:classifiers":[
        {
            "category":"Real Estate",
            "subcategory":"Real Estate Agent",
            "type":"Services"
        }
    ],
    "sg:phone":"+1 404 872 9590",
    "sg:postcode":"30306",
    "sg:province":"GA",
    "wof:name":"Eddy Street Partners",
    "wof:placetype":"venue"
},
  "geometry": {"coordinates":[-84.353692,33.780211],"type":"Point"}
}