{
  "type": "Feature",
  "properties": {
    "addr:full":"310 E 3rd St Donalsonville GA 39845",
    "addr:housenumber":"310",
    "addr:postcode":"39845",
    "addr:street":"E 3Rd St",
    "iso:country":"US",
    "sg:address":"310 E 3rd St",
    "sg:city":"Donalsonville",
    "sg:classifiers":[
        {
            "category":"Restaurant",
            "type":"Food & Drink"
        }
    ],
    "sg:menulink":"http://www.allmenus.com/ga/donalsonville/154415-hardees/menu/",
    "sg:phone":"+1 229 524 5059",
    "sg:postcode":"39845",
    "sg:province":"GA",
    "sg:tags":[
        "burger",
        "american"
    ],
    "wof:name":"Hardee's",
    "wof:placetype":"venue"
},
  "geometry": {"coordinates":[-84.877441,31.04037],"type":"Point"}
}