{
  "type": "Feature",
  "properties": {
    "iso:country":"US",
    "sg:address":"2140 Candler Rd",
    "sg:city":"Decatur",
    "sg:classifiers":[
        {
            "category":"Personal",
            "subcategory":"Barber",
            "type":"Services"
        }
    ],
    "sg:phone":"+1 404 289 9860",
    "sg:postcode":"30032",
    "sg:province":"GA",
    "sg:tags":[
        "shop"
    ],
    "wof:name":"Candler Plaza Barber Shop",
    "wof:placetype":"venue"
},
  "geometry": {"coordinates":[-84.280328,33.728208],"type":"Point"}
}