{
  "type": "Feature",
  "properties": {
    "iso:country":"US",
    "sg:address":"4913 Deans Bridge Rd",
    "sg:city":"Blythe",
    "sg:classifiers":[
        {
            "category":"Health Services",
            "subcategory":"Clinic",
            "type":"Services"
        }
    ],
    "sg:phone":"+1 706 592 9659",
    "sg:postcode":"30805",
    "sg:province":"GA",
    "wof:name":"Zion Manor Inc Personal Care",
    "wof:placetype":"venue"
},
  "geometry": {"coordinates":[-82.194221,33.313465],"type":"Point"}
}