{
  "type": "Feature",
  "properties": {
    "addr:full":"6586 Interstate Ct Ste B Norcross GA 30093",
    "addr:housenumber":"6586",
    "addr:postcode":"30093",
    "addr:street":"Interstate Ct Ste B",
    "iso:country":"US",
    "sg:address":"6586 Interstate Ct Ste B",
    "sg:city":"Norcross",
    "sg:classifiers":[
        {
            "category":"Building & Trades",
            "subcategory":"Cleaning & Sanitation",
            "type":"Services"
        },
        {
            "category":"Home & Garden",
            "subcategory":"Carpets & Floor Coverings",
            "type":"Retail Goods"
        }
    ],
    "sg:phone":"+1 678 468 1787",
    "sg:postcode":"30093",
    "sg:province":"GA",
    "sg:tags":[
        "repairing",
        "etc-repair",
        "shades-cleaning",
        "vertical",
        "blinds-venetian",
        "window"
    ],
    "wof:name":"Global Blinds",
    "wof:placetype":"venue"
},
  "geometry": {"coordinates":[-84.22381300000001,33.908481],"type":"Point"}
}