{
  "type": "Feature",
  "properties": {
    "iso:country":"US",
    "sg:address":"2311 S Patterson St",
    "sg:city":"Valdosta",
    "sg:classifiers":[
        {
            "category":"Autos & Motor Vehicles",
            "subcategory":"Auto Supplies",
            "type":"Retail Goods"
        }
    ],
    "sg:phone":"+1 229 244 8353",
    "sg:postcode":"31601",
    "sg:province":"GA",
    "sg:tags":[
        "tire"
    ],
    "wof:name":"Ne-Ro Tire & Brake Svc",
    "wof:placetype":"venue"
},
  "geometry": {"coordinates":[-83.247208,30.800215],"type":"Point"}
}