{
  "type": "Feature",
  "properties": {
    "iso:country":"US",
    "sg:address":"534 Pheasant Run Dr",
    "sg:city":"Evans",
    "sg:classifiers":[
        {
            "category":"Building & Trades",
            "subcategory":"Construction",
            "type":"Services"
        }
    ],
    "sg:phone":"+1 706 854 9605",
    "sg:postcode":"30809",
    "sg:province":"GA",
    "sg:tags":[
        "wallcoverings-installation",
        "wallpaper",
        "painting",
        "contractor"
    ],
    "wof:name":"Sbm Painting",
    "wof:placetype":"venue"
},
  "geometry": {"coordinates":[-82.13321999999999,33.536836],"type":"Point"}
}