{
  "type": "Feature",
  "properties": {
    "iso:country":"US",
    "sg:address":"2021 Stone Forest Dr",
    "sg:city":"Lawrenceville",
    "sg:classifiers":[
        {
            "category":"Professional",
            "type":"Services"
        }
    ],
    "sg:phone":"+1 770 513 0645",
    "sg:postcode":"30043",
    "sg:province":"GA",
    "wof:name":"Terrence R Reigers Etal",
    "wof:placetype":"venue"
},
  "geometry": {"coordinates":[-84.016892,34.009857],"type":"Point"}
}