{
  "type": "Feature",
  "properties": {
    "iso:country":"US",
    "sg:address":"318 W Pike St",
    "sg:city":"Lawrenceville",
    "sg:classifiers":[
        {
            "category":"Professional",
            "type":"Services"
        },
        {
            "category":"Social Services",
            "type":"Services"
        }
    ],
    "sg:phone":"+1 770 822 2370",
    "sg:postcode":"30045",
    "sg:province":"GA",
    "sg:tags":[
        "counseling",
        "establishment"
    ],
    "wof:name":"Families First",
    "wof:placetype":"venue"
},
  "geometry": {"coordinates":[-83.994867,33.956998],"type":"Point"}
}