{
  "type": "Feature",
  "properties": {
    "addr:full":"150 Covington St Jackson GA 30233",
    "addr:housenumber":"150",
    "addr:postcode":"30233",
    "addr:street":"Covington St",
    "iso:country":"US",
    "sg:address":"150 Covington St",
    "sg:city":"Jackson",
    "sg:classifiers":[
        {
            "category":"Banks & Credit Unions",
            "subcategory":"Bank",
            "type":"Services"
        }
    ],
    "sg:phone":"+1 770 504 1090",
    "sg:postcode":"30233",
    "sg:province":"GA",
    "sg:tags":[
        "saving",
        "commercial"
    ],
    "sg:website":"http://www.accessunited.com/",
    "wof:name":"United Bank",
    "wof:placetype":"venue"
},
  "geometry": {"coordinates":[-83.961652,33.295446],"type":"Point"}
}