{
  "type": "Feature",
  "properties": {
    "iso:country":"US",
    "sg:address":"5335 Shirewick Dr",
    "sg:city":"Lithonia",
    "sg:classifiers":[
        {
            "category":"Banks & Credit Unions",
            "subcategory":"Bank",
            "type":"Services"
        }
    ],
    "sg:phone":"+1 678 570 2532",
    "sg:postcode":"30058",
    "sg:province":"GA",
    "sg:tags":[
        "mortgage",
        "loan",
        "broker",
        "real estate"
    ],
    "sg:website":"www.elitehomemortgages.com",
    "wof:name":"Elite Home Mortgage Inc",
    "wof:placetype":"venue"
},
  "geometry": {"coordinates":[-84.164164,33.71189],"type":"Point"}
}