{
  "type": "Feature",
  "properties": {
    "addr:full":"26 N Jackson St Forsyth GA 31029",
    "addr:housenumber":"26",
    "addr:postcode":"31029",
    "addr:street":"N Jackson St",
    "iso:country":"US",
    "sg:address":"26 N Jackson St",
    "sg:city":"Forsyth",
    "sg:classifiers":[
        {
            "category":"Professional",
            "subcategory":"Computer Services",
            "type":"Services"
        }
    ],
    "sg:phone":"+1 478 992 5096",
    "sg:postcode":"31029",
    "sg:province":"GA",
    "sg:tags":[
        "isp",
        "provider",
        "internet"
    ],
    "wof:name":"Forsyth Cable Net",
    "wof:placetype":"venue"
},
  "geometry": {"coordinates":[-83.939379,33.036897],"type":"Point"}
}