{
  "type": "Feature",
  "properties": {
    "addr:full":"710 Lee Ave Rome GA 30161",
    "addr:housenumber":"710",
    "addr:postcode":"ga 30161",
    "addr:street":"Lee Ave",
    "iso:country":"US",
    "sg:address":"710 Lee Ave",
    "sg:city":"Rome",
    "sg:classifiers":[
        {
            "category":"Retail",
            "subcategory":"Portrait Studio",
            "type":"Services"
        }
    ],
    "sg:phone":"+1 706 295 9288",
    "sg:postcode":"30161",
    "sg:province":"GA",
    "sg:tags":[
        "photography"
    ],
    "wof:name":"Kim Mccullough Photography",
    "wof:placetype":"venue"
},
  "geometry": {"coordinates":[-85.16394699999999,34.243322],"type":"Point"}
}