{
  "type": "Feature",
  "properties": {
    "addr:full":"495 Smyrna Rd SW Conyers GA 30012",
    "addr:housenumber":"495",
    "addr:postcode":"30012",
    "addr:street":"Smyrna Rd Sw",
    "iso:country":"US",
    "sg:address":"495 Smyrna Rd SW",
    "sg:city":"Conyers",
    "sg:classifiers":[
        {
            "category":"Retail",
            "subcategory":"Auto Repair",
            "type":"Services"
        }
    ],
    "sg:phone":"+1 770 922 7697",
    "sg:postcode":"30012",
    "sg:province":"GA",
    "sg:tags":[
        "body",
        "shop"
    ],
    "sg:website":"www.hallsbodyshop.com",
    "wof:name":"Halls Body Shop",
    "wof:placetype":"venue"
},
  "geometry": {"coordinates":[-84.05770099999999,33.677601],"type":"Point"}
}