{
  "type": "Feature",
  "properties": {
    "iso:country":"US",
    "sg:address":"3675 Crestwood Pkwy",
    "sg:city":"Duluth",
    "sg:classifiers":[
        {
            "category":"Banks & Credit Unions",
            "subcategory":"Financial Services",
            "type":"Services"
        }
    ],
    "sg:phone":"+1 770 635 6031",
    "sg:postcode":"30096",
    "sg:province":"GA",
    "sg:tags":[
        "company",
        "holding"
    ],
    "wof:name":"Rbj Holding Inc",
    "wof:placetype":"venue"
},
  "geometry": {"coordinates":[-84.127937,33.946856],"type":"Point"}
}