{
  "type": "Feature",
  "properties": {
    "iso:country":"US",
    "sg:address":"1311 W Alden Ave",
    "sg:city":"Valdosta",
    "sg:classifiers":[
        {
            "category":"Organizations",
            "subcategory":"Religious Organization",
            "type":"Services"
        }
    ],
    "sg:phone":"+1 229 242 2300",
    "sg:postcode":"31602",
    "sg:province":"GA",
    "sg:tags":[
        "church"
    ],
    "wof:name":"Ch Of Jesus Christ Of LDS",
    "wof:placetype":"venue"
},
  "geometry": {"coordinates":[-83.310177,30.847998],"type":"Point"}
}