{
  "type": "Feature",
  "properties": {
    "iso:country":"US",
    "sg:address":"2281 Pine Warbler Ct NE",
    "sg:city":"Marietta",
    "sg:classifiers":[
        {
            "category":"Professional",
            "subcategory":"Business Services",
            "type":"Services"
        }
    ],
    "sg:phone":"+1 770 977 2960",
    "sg:postcode":"30062",
    "sg:province":"GA",
    "wof:name":"Kronawitter Associates Inc",
    "wof:placetype":"venue"
},
  "geometry": {"coordinates":[-84.485218,33.989937],"type":"Point"}
}