{
  "type": "Feature",
  "properties": {
    "addr:full":"4830B Redan Rd Stone Mountain GA 30088",
    "addr:housenumber":"4830b",
    "addr:postcode":"30088",
    "addr:street":"Redan Rd",
    "iso:country":"US",
    "sg:address":"4830B Redan Rd",
    "sg:city":"Stone Mountain",
    "sg:classifiers":[
        {
            "category":"Personal",
            "subcategory":"Barber",
            "type":"Services"
        }
    ],
    "sg:phone":"+1 404 508 9525",
    "sg:postcode":"30088",
    "sg:province":"GA",
    "wof:name":"Nicks Barber Shop",
    "wof:placetype":"venue"
},
  "geometry": {"coordinates":[-84.194942,33.761261],"type":"Point"}
}