{
  "type": "Feature",
  "properties": {
    "addr:full":"1559 Pope Rd Boston GA 31626",
    "addr:housenumber":"1559",
    "addr:postcode":"31626",
    "addr:street":"Pope Rd",
    "iso:country":"US",
    "sg:address":"1559 Pope Rd",
    "sg:city":"Boston",
    "sg:classifiers":[
        {
            "category":"Place Of Worship",
            "subcategory":"Church",
            "type":"Public Place"
        },
        {
            "category":"Place Of Worship",
            "type":"Public Place"
        }
    ],
    "sg:phone":"+1 229 227 1012",
    "sg:postcode":"31626",
    "sg:province":"GA",
    "sg:tags":[
        "churches-baptist-general",
        "churches-baptist"
    ],
    "wof:name":"Cedar Hill Missionary Baptist Church",
    "wof:placetype":"venue"
},
  "geometry": {"coordinates":[-83.786253,30.910792],"type":"Point"}
}