{
  "type": "Feature",
  "properties": {
    "iso:country":"US",
    "sg:address":"9795 Farmbrook Ln",
    "sg:city":"Alpharetta",
    "sg:classifiers":[
        {
            "category":"Building & Trades",
            "subcategory":"Construction",
            "type":"Services"
        }
    ],
    "sg:phone":"+1 770 416 6836",
    "sg:postcode":"30022",
    "sg:province":"GA",
    "sg:tags":[
        "house"
    ],
    "wof:name":"Hogan Construction Group LLC",
    "wof:placetype":"venue"
},
  "geometry": {"coordinates":[-84.21195899999999,34.017387],"type":"Point"}
}