{
  "type": "Feature",
  "properties": {
    "addr:full":"400 Crosstown Rd Peachtree City GA 30269",
    "addr:housenumber":"400",
    "addr:postcode":"30269",
    "addr:street":"Crosstown Rd",
    "iso:country":"US",
    "sg:address":"400 Crosstown Rd",
    "sg:city":"Peachtree City",
    "sg:classifiers":[
        {
            "category":"Shopping",
            "subcategory":"Department Store",
            "type":"Retail Goods"
        }
    ],
    "sg:phone":"+1 770 487 2295",
    "sg:postcode":"30269",
    "sg:province":"GA",
    "wof:name":"Kmart",
    "wof:placetype":"venue"
},
  "geometry": {"coordinates":[-84.54944399999999,33.380013],"type":"Point"}
}