{
  "type": "Feature",
  "properties": {
    "iso:country":"US",
    "sg:address":"1465 54th St",
    "sg:city":"Columbus",
    "sg:classifiers":[
        {
            "category":"Shopping",
            "subcategory":"Hobbies, Toys, & Games",
            "type":"Retail Goods"
        }
    ],
    "sg:phone":"+1 706 569 0905",
    "sg:postcode":"31904",
    "sg:province":"GA",
    "wof:name":"Doll World & Surroundings",
    "wof:placetype":"venue"
},
  "geometry": {"coordinates":[-84.966014,32.520765],"type":"Point"}
}