{
  "type": "Feature",
  "properties": {
    "addr:full":"1055 Winter Park Ln Norcross GA 30093",
    "addr:housenumber":"1055",
    "addr:postcode":"30093",
    "addr:street":"Winter Park Ln",
    "iso:country":"US",
    "sg:address":"1055 Winter Park Ln",
    "sg:city":"Norcross",
    "sg:classifiers":[
        {
            "category":"Manufacturing",
            "subcategory":"Printing",
            "type":"Manufacturing & Wholesale Goods"
        }
    ],
    "sg:phone":"+1 770 381 8536",
    "sg:postcode":"30093",
    "sg:province":"GA",
    "sg:tags":[
        "printer"
    ],
    "wof:name":"TNT Assoc",
    "wof:placetype":"venue"
},
  "geometry": {"coordinates":[-84.193984,33.891956],"type":"Point"}
}