{
  "type": "Feature",
  "properties": {
    "iso:country":"US",
    "sg:address":"4142 Jimmy Carter Blvd",
    "sg:city":"Norcross",
    "sg:classifiers":[
        {
            "category":"Retail",
            "subcategory":"Laundry & Dry Cleaning",
            "type":"Services"
        }
    ],
    "sg:phone":"+1 770 270 8979",
    "sg:postcode":"30093",
    "sg:province":"GA",
    "sg:tags":[
        "drycleaning",
        "plant"
    ],
    "wof:name":"Two Kings Cleaners",
    "wof:placetype":"venue"
},
  "geometry": {"coordinates":[-84.18822400000001,33.867702],"type":"Point"}
}