{
  "type": "Feature",
  "properties": {
    "iso:country":"US",
    "sg:address":"222 Hawkins Store Rd NE",
    "sg:city":"Kennesaw",
    "sg:classifiers":[
        {
            "category":"Personal",
            "subcategory":"Beauty Salon",
            "type":"Services"
        }
    ],
    "sg:phone":"+1 770 592 8208",
    "sg:postcode":"30144",
    "sg:province":"GA",
    "wof:name":"Virtuous Woman Beauty & Spa",
    "wof:placetype":"venue"
},
  "geometry": {"coordinates":[-84.55762199999999,34.057994],"type":"Point"}
}