{
  "type": "Feature",
  "properties": {
    "iso:country":"US",
    "sg:address":"5150 Stone Mountain Hwy",
    "sg:city":"Stone Mountain",
    "sg:classifiers":[
        {
            "category":"Restaurant",
            "type":"Food & Drink"
        }
    ],
    "sg:phone":"+1 678 344 2778",
    "sg:postcode":"30087",
    "sg:province":"GA",
    "sg:tags":[
        "chinese",
        "buffet"
    ],
    "wof:name":"Hong Kong King Buffet",
    "wof:placetype":"venue"
},
  "geometry": {"coordinates":[-84.107803,33.8242],"type":"Point"}
}