{
  "type": "Feature",
  "properties": {
    "addr:full":"2710 Jefferson St Austell GA 30168",
    "addr:housenumber":"2710",
    "addr:postcode":"30168",
    "addr:street":"Jefferson",
    "iso:country":"US",
    "sg:address":"2710 Jefferson St",
    "sg:city":"Austell",
    "sg:classifiers":[
        {
            "category":"Building & Trades",
            "subcategory":"Construction",
            "type":"Services"
        },
        {
            "category":"Real Estate",
            "subcategory":"Real Estate Operator",
            "type":"Services"
        }
    ],
    "sg:phone":"+1 770 948 3700",
    "sg:postcode":"30168",
    "sg:province":"GA",
    "sg:tags":[
        "property",
        "commercial",
        "maker",
        "lessor",
        "cabinet"
    ],
    "wof:name":"Austell Cabinet Co Inc",
    "wof:placetype":"venue"
},
  "geometry": {"coordinates":[-84.634246,33.812287],"type":"Point"}
}