{
  "type": "Feature",
  "properties": {
    "iso:country":"US",
    "sg:address":"5076 Winters Chapel Rd",
    "sg:city":"Atlanta",
    "sg:classifiers":[
        {
            "category":"Health Services",
            "subcategory":"Doctor",
            "type":"Services"
        }
    ],
    "sg:phone":"+1 770 394 7620",
    "sg:postcode":"30360",
    "sg:province":"GA",
    "sg:tags":[
        "consultant",
        "medical",
        "practice"
    ],
    "wof:name":"Practice Productivity Plus",
    "wof:placetype":"venue"
},
  "geometry": {"coordinates":[-84.27006900000001,33.945057],"type":"Point"}
}