{
  "type": "Feature",
  "properties": {
    "addr:full":"5950 Live Oak Pkwy Ste 170 Norcross GA 30093",
    "addr:housenumber":"5950",
    "addr:postcode":"30093",
    "addr:street":"Live Oak Pkwy Ste 170",
    "iso:country":"US",
    "sg:address":"5950 Live Oak Pkwy Ste 170",
    "sg:city":"Norcross",
    "sg:classifiers":[
        {
            "category":"Professional",
            "subcategory":"Accounting & Tax Preparation",
            "type":"Services"
        }
    ],
    "sg:phone":"+1 770 449 1049",
    "sg:postcode":"30093",
    "sg:province":"GA",
    "sg:tags":[
        "accountant"
    ],
    "wof:name":"Slesinger Joel S CPA PC",
    "wof:placetype":"venue"
},
  "geometry": {"coordinates":[-84.199303,33.910301],"type":"Point"}
}