{
  "type": "Feature",
  "properties": {
    "iso:country":"US",
    "sg:address":"2658 Farmington Dr SW",
    "sg:city":"Marietta",
    "sg:classifiers":[
        {
            "category":"Building & Trades",
            "subcategory":"Construction",
            "type":"Services"
        }
    ],
    "sg:phone":"+1 770 436 7203",
    "sg:postcode":"30008",
    "sg:province":"GA",
    "sg:tags":[
        "carpentry",
        "contractor"
    ],
    "wof:name":"W Myles Murry",
    "wof:placetype":"venue"
},
  "geometry": {"coordinates":[-84.59557599999999,33.888886],"type":"Point"}
}