{
  "type": "Feature",
  "properties": {
    "addr:full":"302 Turner St Statesboro GA 30458",
    "addr:housenumber":"302",
    "addr:postcode":"30458",
    "addr:street":"Turner St",
    "iso:country":"US",
    "sg:address":"302 Turner St",
    "sg:city":"Statesboro",
    "sg:classifiers":[
        {
            "category":"Organizations",
            "subcategory":"Religious Organization",
            "type":"Services"
        }
    ],
    "sg:phone":"+1 912 764 9026",
    "sg:postcode":"30458",
    "sg:province":"GA",
    "wof:name":"First Assembly of God Inc",
    "wof:placetype":"venue"
},
  "geometry": {"coordinates":[-81.77309099999999,32.454709],"type":"Point"}
}