{
  "type": "Feature",
  "properties": {
    "iso:country":"US",
    "sg:address":"1861 Lancaster Dr SE",
    "sg:city":"Conyers",
    "sg:classifiers":[
        {
            "category":"Professional",
            "subcategory":"Business Services",
            "type":"Services"
        }
    ],
    "sg:phone":"+1 770 679 4509",
    "sg:postcode":"30013",
    "sg:province":"GA",
    "wof:name":"Moores Home Inspection",
    "wof:placetype":"venue"
},
  "geometry": {"coordinates":[-84.002894,33.617274],"type":"Point"}
}