{
  "type": "Feature",
  "properties": {
    "iso:country":"US",
    "sg:address":"59 Cliff Haines Rd",
    "sg:city":"Sharpsburg",
    "sg:classifiers":[
        {
            "category":"Building & Trades",
            "subcategory":"Construction",
            "type":"Services"
        }
    ],
    "sg:phone":"+1 770 253 8118",
    "sg:postcode":"30277",
    "sg:province":"GA",
    "sg:tags":[
        "contractor"
    ],
    "wof:name":"JDF Catch Basin",
    "wof:placetype":"venue"
},
  "geometry": {"coordinates":[-84.66074500000001,33.354831],"type":"Point"}
}