{
  "type": "Feature",
  "properties": {
    "addr:full":"2251 Tilson Cir Decatur GA 30032",
    "addr:housenumber":"2251",
    "addr:postcode":"30032",
    "addr:street":"Tilson Cir",
    "iso:country":"US",
    "sg:address":"2251 Tilson Cir",
    "sg:city":"Decatur",
    "sg:classifiers":[
        {
            "category":"Professional",
            "type":"Services"
        }
    ],
    "sg:phone":"+1 404 241 5520",
    "sg:postcode":"30032",
    "sg:province":"GA",
    "wof:name":"Gresham Services Inc",
    "wof:placetype":"venue"
},
  "geometry": {"coordinates":[-84.296074,33.723245],"type":"Point"}
}