{
  "type": "Feature",
  "properties": {
    "addr:full":"2229 Bell St Waycross GA 31503",
    "addr:housenumber":"2229",
    "addr:postcode":"31503",
    "addr:street":"Bell St",
    "iso:country":"US",
    "sg:address":"2229 Bell St",
    "sg:city":"Waycross",
    "sg:classifiers":[
        {
            "category":"Retail",
            "subcategory":"Auto Repair",
            "type":"Services"
        }
    ],
    "sg:phone":"+1 912 283 3166",
    "sg:postcode":"31503",
    "sg:province":"GA",
    "sg:tags":[
        "general"
    ],
    "wof:name":"Pittman Garage & Trucking",
    "wof:placetype":"venue"
},
  "geometry": {"coordinates":[-82.390507,31.222544],"type":"Point"}
}