{
  "type": "Feature",
  "properties": {
    "iso:country":"US",
    "sg:address":"4043 River Ridge Chase",
    "sg:city":"Marietta",
    "sg:classifiers":[
        {
            "category":"Insurance",
            "subcategory":"Insurance Agent",
            "type":"Services"
        }
    ],
    "sg:phone":"+1 770 859 0086",
    "sg:postcode":"30067",
    "sg:province":"GA",
    "wof:name":"Optimal Consulting Group",
    "wof:placetype":"venue"
},
  "geometry": {"coordinates":[-84.437117,33.945202],"type":"Point"}
}