{
  "type": "Feature",
  "properties": {
    "addr:full":"853 4th St Stone Mountain GA 30083",
    "addr:housenumber":"853",
    "addr:postcode":"30083",
    "addr:street":"4Th St",
    "iso:country":"US",
    "sg:address":"853 4th St",
    "sg:city":"Stone Mountain",
    "sg:classifiers":[
        {
            "category":"Organizations",
            "subcategory":"Religious Organization",
            "type":"Services"
        }
    ],
    "sg:phone":"+1 770 469 1276",
    "sg:postcode":"30083",
    "sg:province":"GA",
    "sg:tags":[
        "church"
    ],
    "wof:name":"Bethsadia Baptist Church",
    "wof:placetype":"venue"
},
  "geometry": {"coordinates":[-84.167092,33.802606],"type":"Point"}
}