{
  "type": "Feature",
  "properties": {
    "iso:country":"US",
    "sg:address":"602 Brick Yard Ln",
    "sg:city":"Saint Simons Island",
    "sg:classifiers":[
        {
            "category":"Real Estate",
            "subcategory":"Real Estate Agent",
            "type":"Services"
        }
    ],
    "sg:phone":"+1 912 638 0971",
    "sg:postcode":"31522",
    "sg:province":"GA",
    "wof:name":"Sally Essig",
    "wof:placetype":"venue"
},
  "geometry": {"coordinates":[-81.39920600000001,31.174446],"type":"Point"}
}