{
  "type": "Feature",
  "properties": {
    "addr:full":"105 John Maddox Dr Rome GA 30165",
    "addr:housenumber":"105",
    "addr:postcode":"ga 30165",
    "addr:street":"John Maddox Dr",
    "iso:country":"US",
    "sg:address":"105 John Maddox Dr",
    "sg:city":"Rome",
    "sg:classifiers":[
        {
            "category":"Health Services",
            "subcategory":"Doctor",
            "type":"Services"
        }
    ],
    "sg:phone":"+1 706 290 0090",
    "sg:postcode":"30165",
    "sg:province":"GA",
    "sg:tags":[
        "physician",
        "surgeon",
        "medical"
    ],
    "wof:name":"Lawrence M Arkin MD PC",
    "wof:placetype":"venue"
},
  "geometry": {"coordinates":[-85.198956,34.275763],"type":"Point"}
}