{
  "type": "Feature",
  "properties": {
    "iso:country":"US",
    "sg:address":"140 Seville Chase",
    "sg:city":"Sandy Springs",
    "sg:classifiers":[
        {
            "category":"Professional",
            "subcategory":"Business Services",
            "type":"Services"
        }
    ],
    "sg:phone":"+1 770 394 4860",
    "sg:postcode":"30328",
    "sg:province":"GA",
    "sg:tags":[
        "lecture",
        "bureau",
        "seminar"
    ],
    "wof:name":"Ford Group Inc",
    "wof:placetype":"venue"
},
  "geometry": {"coordinates":[-84.381736,33.946321],"type":"Point"}
}