{
  "type": "Feature",
  "properties": {
    "addr:full":"118 Andrews Ct Eatonton GA 31024",
    "addr:housenumber":"118",
    "addr:postcode":"31024",
    "addr:street":"Andrews Ct",
    "iso:country":"US",
    "sg:address":"118 Andrews Ct",
    "sg:city":"Eatonton",
    "sg:classifiers":[
        {
            "category":"Shopping",
            "type":"Retail Goods"
        }
    ],
    "sg:phone":"+1 706 485 5610",
    "sg:postcode":"31024",
    "sg:province":"GA",
    "sg:tags":[
        "merchandise"
    ],
    "sg:website":"http://www.mcgassociates.com",
    "wof:name":"M C G & Associates",
    "wof:placetype":"venue"
},
  "geometry": {"coordinates":[-83.330555,33.337816],"type":"Point"}
}