{
  "type": "Feature",
  "properties": {
    "addr:full":"273 Central Ave SW Atlanta GA 30303",
    "addr:housenumber":"273",
    "addr:postcode":"30303",
    "addr:street":"Central Ave Sw",
    "iso:country":"US",
    "sg:address":"273 Central Ave SW",
    "sg:city":"Atlanta",
    "sg:phone":"+1 404 592 2666",
    "sg:postcode":"30303",
    "sg:province":"GA",
    "sg:website":"http://www.atlanta-locksmiths.net",
    "wof:name":"Locksmiths Atlanta GA",
    "wof:placetype":"venue"
},
  "geometry": {"coordinates":[-84.391274,33.748826],"type":"Point"}
}