{
  "type": "Feature",
  "properties": {
    "addr:full":"4775 Clarks Bridge Rd Gainesville GA 30506",
    "addr:housenumber":"4775",
    "addr:postcode":"30506",
    "addr:street":"Clarks Bridge Rd",
    "iso:country":"US",
    "sg:address":"4775 Clarks Bridge Rd",
    "sg:city":"Gainesville",
    "sg:classifiers":[
        {
            "category":"Organizations",
            "subcategory":"Political Organization",
            "type":"Services"
        }
    ],
    "sg:phone":"+1 770 718 9898",
    "sg:postcode":"30506",
    "sg:province":"GA",
    "wof:name":"Deal For Congress",
    "wof:placetype":"venue"
},
  "geometry": {"coordinates":[-83.771305,34.424607],"type":"Point"}
}