{
  "type": "Feature",
  "properties": {
    "iso:country":"US",
    "sg:address":"3015 Seagull Dr NW",
    "sg:city":"Duluth",
    "sg:classifiers":[
        {
            "category":"Professional",
            "subcategory":"Business Services",
            "type":"Services"
        }
    ],
    "sg:phone":"+1 770 476 8683",
    "sg:postcode":"30096",
    "sg:province":"GA",
    "wof:name":"Allstate Interior Contractors",
    "wof:placetype":"venue"
},
  "geometry": {"coordinates":[-84.120676,33.978489],"type":"Point"}
}