{
  "type": "Feature",
  "properties": {
    "iso:country":"US",
    "sg:address":"2160 Leach Rd",
    "sg:city":"Greensboro",
    "sg:classifiers":[
        {
            "category":"Social Services",
            "type":"Services"
        }
    ],
    "sg:phone":"+1 706 467 3578",
    "sg:postcode":"30678",
    "sg:province":"GA",
    "sg:tags":[
        "counseling"
    ],
    "wof:name":"Christian Families Today",
    "wof:placetype":"venue"
},
  "geometry": {"coordinates":[-83.137021,33.469277],"type":"Point"}
}