{
  "type": "Feature",
  "properties": {
    "iso:country":"US",
    "sg:address":"1067 Franklin Springs St",
    "sg:city":"Royston",
    "sg:classifiers":[
        {
            "category":"Personal",
            "subcategory":"Beauty Salon",
            "type":"Services"
        }
    ],
    "sg:phone":"+1 706 245 4242",
    "sg:postcode":"30662",
    "sg:province":"GA",
    "sg:tags":[
        "shop",
        "manicuring"
    ],
    "wof:name":"All Nails",
    "wof:placetype":"venue"
},
  "geometry": {"coordinates":[-83.123751,34.284514],"type":"Point"}
}