{
  "type": "Feature",
  "properties": {
    "iso:country":"US",
    "sg:address":"476 Clifton Rd NE",
    "sg:city":"Atlanta",
    "sg:classifiers":[
        {
            "category":"Professional",
            "subcategory":"Management & Consulting",
            "type":"Services"
        }
    ],
    "sg:phone":"+1 404 408 4451",
    "sg:postcode":"30307",
    "sg:province":"GA",
    "sg:tags":[
        "consultant"
    ],
    "wof:name":"English Imports",
    "wof:placetype":"venue"
},
  "geometry": {"coordinates":[-84.332995,33.76688],"type":"Point"}
}