{
  "type": "Feature",
  "properties": {
    "addr:full":"2433 Waterscape Trl Snellville GA 30078",
    "addr:housenumber":"2433",
    "addr:postcode":"30078",
    "addr:street":"Waterscape Trl",
    "iso:country":"US",
    "sg:address":"2433 Waterscape Trl",
    "sg:city":"Snellville",
    "sg:classifiers":[
        {
            "category":"Professional",
            "subcategory":"Lawyer & Legal Services",
            "type":"Services"
        }
    ],
    "sg:phone":"+1 678 344 4644",
    "sg:postcode":"30078",
    "sg:province":"GA",
    "wof:name":"Thompson Clay R",
    "wof:placetype":"venue"
},
  "geometry": {"coordinates":[-84.03479799999999,33.8909],"type":"Point"}
}