{
  "type": "Feature",
  "properties": {
    "addr:full":"801 S Georgia Pkwy E Waycross GA 31501",
    "addr:housenumber":"801",
    "addr:postcode":"31501",
    "addr:street":"S Georgia Pkwy E",
    "iso:country":"US",
    "sg:address":"801 S Georgia Pkwy E",
    "sg:city":"Waycross",
    "sg:classifiers":[
        {
            "category":"Organizations",
            "subcategory":"Religious Organization",
            "type":"Services"
        }
    ],
    "sg:phone":"+1 912 285 8489",
    "sg:postcode":"31501",
    "sg:province":"GA",
    "wof:name":"Gaines Chapel AME Waycross Inc",
    "wof:placetype":"venue"
},
  "geometry": {"coordinates":[-82.35320299999999,31.206412],"type":"Point"}
}