{
  "type": "Feature",
  "properties": {
    "iso:country":"US",
    "sg:address":"2687 McCollum Pkwy NW",
    "sg:city":"Kennesaw",
    "sg:classifiers":[
        {
            "category":"Wholesale",
            "subcategory":"Metals & Minerals",
            "type":"Manufacturing & Wholesale Goods"
        }
    ],
    "sg:phone":"+1 770 425 8399",
    "sg:postcode":"30144",
    "sg:province":"GA",
    "sg:tags":[
        "rolled",
        "flat",
        "steel"
    ],
    "wof:name":"M W Express Metals Inc",
    "wof:placetype":"venue"
},
  "geometry": {"coordinates":[-84.59995000000001,34.01778],"type":"Point"}
}