{
  "type": "Feature",
  "properties": {
    "iso:country":"US",
    "sg:address":"221 Hilltop Dr",
    "sg:city":"Peachtree City",
    "sg:classifiers":[
        {
            "category":"Freight",
            "type":"Transportation"
        }
    ],
    "sg:phone":"+1 678 472 4218",
    "sg:postcode":"30269",
    "sg:province":"GA",
    "sg:tags":[
        "operator",
        "trucking"
    ],
    "wof:name":"GA Carmovers",
    "wof:placetype":"venue"
},
  "geometry": {"coordinates":[-84.582781,33.396429],"type":"Point"}
}