{
  "type": "Feature",
  "properties": {
    "iso:country":"US",
    "sg:address":"1818 Wilson Ave",
    "sg:city":"Tifton",
    "sg:classifiers":[
        {
            "category":"Professional",
            "type":"Services"
        }
    ],
    "sg:phone":"+1 229 382 1247",
    "sg:postcode":"31794",
    "sg:province":"GA",
    "wof:name":"Educational Equipment Services",
    "wof:placetype":"venue"
},
  "geometry": {"coordinates":[-83.511,31.472464],"type":"Point"}
}