{
  "type": "Feature",
  "properties": {
    "addr:full":"361 17th St Atlanta GA 30363",
    "addr:housenumber":"361",
    "addr:postcode":"30363",
    "addr:street":"17Th St",
    "iso:country":"US",
    "sg:address":"361 17th St",
    "sg:city":"Atlanta",
    "sg:classifiers":[
        {
            "category":"Travel",
            "subcategory":"Hotels & Motels",
            "type":"Entertainment"
        }
    ],
    "sg:phone":"+1 404 961 1212",
    "sg:postcode":"30363",
    "sg:province":"GA",
    "sg:website":"www.twelveatlanticstation.com",
    "wof:name":"TWELVE Hotels",
    "wof:placetype":"venue"
},
  "geometry": {"coordinates":[-84.3984,33.791381],"type":"Point"}
}