{
  "type": "Feature",
  "properties": {
    "iso:country":"US",
    "sg:address":"5693 N Marble Top Rd",
    "sg:city":"Chickamauga",
    "sg:classifiers":[
        {
            "category":"Freight",
            "type":"Transportation"
        }
    ],
    "sg:phone":"+1 706 375 6997",
    "sg:postcode":"30707",
    "sg:province":"GA",
    "sg:tags":[
        "consultant"
    ],
    "wof:name":"National Freight Brokers",
    "wof:placetype":"venue"
},
  "geometry": {"coordinates":[-85.36577699999999,34.834006],"type":"Point"}
}