{
  "type": "Feature",
  "properties": {
    "iso:country":"US",
    "sg:address":"3690 Holcomb Bridge Rd",
    "sg:city":"Norcross",
    "sg:classifiers":[
        {
            "category":"Food & Beverages",
            "subcategory":"Groceries & Convenience Stores",
            "type":"Retail Goods"
        }
    ],
    "sg:phone":"+1 678 781 9080",
    "sg:postcode":"30092",
    "sg:province":"GA",
    "wof:name":"Blue Ribbon Foods",
    "wof:placetype":"venue"
},
  "geometry": {"coordinates":[-84.247765,33.960124],"type":"Point"}
}