{
  "type": "Feature",
  "properties": {
    "iso:country":"US",
    "sg:address":"2967 Holcomb Ct",
    "sg:city":"East Point",
    "sg:classifiers":[
        {
            "category":"Organizations",
            "subcategory":"Religious Organization",
            "type":"Services"
        }
    ],
    "sg:phone":"+1 404 768 0611",
    "sg:postcode":"30344",
    "sg:province":"GA",
    "sg:tags":[
        "church"
    ],
    "sg:website":"www.neriahbaptist.net",
    "wof:name":"Neriah Baptist Church",
    "wof:placetype":"venue"
},
  "geometry": {"coordinates":[-84.436238,33.674011],"type":"Point"}
}