{
  "type": "Feature",
  "properties": {
    "iso:country":"US",
    "sg:address":"612 Poplar St",
    "sg:city":"Macon",
    "sg:classifiers":[
        {
            "category":"Food & Beverages",
            "subcategory":"Groceries & Convenience Stores",
            "type":"Retail Goods"
        }
    ],
    "sg:phone":"+1 478 745 9733",
    "sg:postcode":"31201",
    "sg:province":"GA",
    "sg:tags":[
        "basket",
        "shop",
        "flower",
        "gift"
    ],
    "wof:name":"Georgia Market House",
    "wof:placetype":"venue"
},
  "geometry": {"coordinates":[-83.630394,32.835258],"type":"Point"}
}