{
  "type": "Feature",
  "properties": {
    "iso:country":"US",
    "sg:address":"142 Hampton Point Dr",
    "sg:city":"Saint Simons Island",
    "sg:classifiers":[
        {
            "category":"Professional",
            "type":"Services"
        }
    ],
    "sg:phone":"+1 912 638 6946",
    "sg:postcode":"31522",
    "sg:province":"GA",
    "wof:name":"George Dunbar Office",
    "wof:placetype":"venue"
},
  "geometry": {"coordinates":[-81.33932799999999,31.285266],"type":"Point"}
}