{
  "type": "Feature",
  "properties": {
    "iso:country":"US",
    "sg:address":"149 Davidson Cir",
    "sg:city":"Griffin",
    "sg:classifiers":[
        {
            "category":"Building & Trades",
            "subcategory":"Plumbing",
            "type":"Services"
        }
    ],
    "sg:phone":"+1 770 227 1783",
    "sg:postcode":"30223",
    "sg:province":"GA",
    "sg:tags":[
        "plumber",
        "industrial",
        "contractors-commercial"
    ],
    "wof:name":"Sykes Plumbing Thomas Sykes Dba",
    "wof:placetype":"venue"
},
  "geometry": {"coordinates":[-84.359951,33.30962],"type":"Point"}
}