{
  "type": "Feature",
  "properties": {
    "iso:country":"US",
    "sg:address":"5295 Stone Mountain Fwy SW",
    "sg:city":"Stone Mountain",
    "sg:classifiers":[
        {
            "category":"Retail",
            "subcategory":"Veterinary Services",
            "type":"Services"
        }
    ],
    "sg:phone":"+1 770 469 8240",
    "sg:postcode":"30087",
    "sg:province":"GA",
    "wof:name":"Ctr For Feline Medcn & Surg PC",
    "wof:placetype":"venue"
},
  "geometry": {"coordinates":[-84.11278299999999,33.823303],"type":"Point"}
}