{
  "type": "Feature",
  "properties": {
    "addr:full":"1480 Holly Manor Dr Loganville GA 30052",
    "addr:housenumber":"1480",
    "addr:postcode":"30052",
    "addr:street":"Holly Manor Dr",
    "iso:country":"US",
    "sg:address":"1480 Holly Manor Dr",
    "sg:city":"Loganville",
    "sg:classifiers":[
        {
            "category":"Organizations",
            "subcategory":"Community Association",
            "type":"Services"
        }
    ],
    "sg:phone":"+1 770 982 5647",
    "sg:postcode":"30052",
    "sg:province":"GA",
    "wof:name":"Frienship Chapter 513",
    "wof:placetype":"venue"
},
  "geometry": {"coordinates":[-83.955918,33.831451],"type":"Point"}
}