{
  "type": "Feature",
  "properties": {
    "addr:full":"555 Progress Center Ave Lawrenceville GA 30043",
    "addr:housenumber":"555",
    "addr:postcode":"30043",
    "addr:street":"Progress Center Ave",
    "iso:country":"US",
    "sg:address":"555 Progress Center Ave",
    "sg:city":"Lawrenceville",
    "sg:classifiers":[
        {
            "category":"Restaurant",
            "type":"Food & Drink"
        }
    ],
    "sg:phone":"+1 770 682 6822",
    "sg:postcode":"30043",
    "sg:province":"GA",
    "sg:tags":[
        "eating"
    ],
    "wof:name":"East Coast Grill",
    "wof:placetype":"venue"
},
  "geometry": {"coordinates":[-83.96670899999999,33.98779],"type":"Point"}
}