{
  "type": "Feature",
  "properties": {
    "addr:full":"1175 Hillary Ln Lawrenceville GA 30043",
    "addr:housenumber":"1175",
    "addr:postcode":"30043",
    "addr:street":"Hillary Ln",
    "iso:country":"US",
    "sg:address":"1175 Hillary Ln",
    "sg:city":"Lawrenceville",
    "sg:classifiers":[
        {
            "category":"Freight",
            "type":"Transportation"
        }
    ],
    "sg:phone":"+1 770 995 0652",
    "sg:postcode":"30043",
    "sg:province":"GA",
    "sg:tags":[
        "operator",
        "local",
        "trucking"
    ],
    "wof:name":"Cisse Trucking",
    "wof:placetype":"venue"
},
  "geometry": {"coordinates":[-84.041917,33.986762],"type":"Point"}
}