{
  "type": "Feature",
  "properties": {
    "addr:full":"931 Monroe Dr NE Atlanta GA 30308",
    "addr:housenumber":"931",
    "addr:postcode":"30308",
    "addr:street":"Monroe Dr Ne",
    "iso:country":"US",
    "sg:address":"931 Monroe Dr NE",
    "sg:city":"Atlanta",
    "sg:classifiers":[
        {
            "category":"Shopping",
            "subcategory":"Gifts & Souvenirs",
            "type":"Retail Goods"
        }
    ],
    "sg:phone":"+1 404 541 0621",
    "sg:postcode":"30308",
    "sg:province":"GA",
    "sg:tags":[
        "shop",
        "home",
        "decor"
    ],
    "wof:name":"Tuesday Morning",
    "wof:placetype":"venue"
},
  "geometry": {"coordinates":[-84.36930099999999,33.7798],"type":"Point"}
}