{
  "type": "Feature",
  "properties": {
    "iso:country":"US",
    "sg:address":"1531 N Expy",
    "sg:city":"Griffin",
    "sg:classifiers":[
        {
            "category":"Shopping",
            "subcategory":"Clothing, Apparel, & Fashions",
            "type":"Retail Goods"
        }
    ],
    "sg:phone":"+1 770 228 3239",
    "sg:postcode":"30223",
    "sg:province":"GA",
    "wof:name":"Dawgs N Jackets",
    "wof:placetype":"venue"
},
  "geometry": {"coordinates":[-84.288186,33.255979],"type":"Point"}
}