{
  "type": "Feature",
  "properties": {
    "addr:full":"1606 Staley Ave Savannah GA 31405",
    "addr:housenumber":"1606",
    "addr:postcode":"31405",
    "addr:street":"Staley Ave",
    "iso:country":"US",
    "sg:address":"1606 Staley Ave",
    "sg:city":"Savannah",
    "sg:classifiers":[
        {
            "category":"Building & Trades",
            "subcategory":"Construction",
            "type":"Services"
        }
    ],
    "sg:phone":"+1 912 236 2919",
    "sg:postcode":"31405",
    "sg:province":"GA",
    "sg:tags":[
        "painter"
    ],
    "wof:name":"Star Contracting",
    "wof:placetype":"venue"
},
  "geometry": {"coordinates":[-81.13564100000001,32.039235],"type":"Point"}
}