{
  "type": "Feature",
  "properties": {
    "addr:full":"3319 Old Milton Pkwy Alpharetta GA 30005",
    "addr:housenumber":"3319",
    "addr:postcode":"30005",
    "addr:street":"Old Milton Pkwy",
    "iso:country":"US",
    "sg:address":"3319 Old Milton Pkwy",
    "sg:city":"Alpharetta",
    "sg:classifiers":[
        {
            "category":"Restaurant",
            "type":"Food & Drink"
        }
    ],
    "sg:phone":"+1 770 754 1284",
    "sg:postcode":"30005",
    "sg:province":"GA",
    "sg:tags":[
        "style",
        "family",
        "lunch",
        "american",
        "brunch",
        "breakfast"
    ],
    "sg:website":"http://www.wafflehouse.com",
    "wof:name":"Waffle House",
    "wof:placetype":"venue"
},
  "geometry": {"coordinates":[-84.26769299999999,34.06871],"type":"Point"}
}