{
  "type": "Feature",
  "properties": {
    "addr:full":"125 Habersham Dr Fayetteville GA 30214",
    "addr:housenumber":"125",
    "addr:postcode":"30214",
    "addr:street":"Habersham Dr",
    "iso:country":"US",
    "sg:address":"125 Habersham Dr",
    "sg:city":"Fayetteville",
    "sg:classifiers":[
        {
            "category":"Shopping",
            "subcategory":"Catalog Store",
            "type":"Retail Goods"
        }
    ],
    "sg:phone":"+1 678 554 0208",
    "sg:postcode":"30214",
    "sg:province":"GA",
    "sg:tags":[
        "product",
        "internet",
        "sales",
        "software"
    ],
    "wof:name":"Zbestdeals",
    "wof:placetype":"venue"
},
  "geometry": {"coordinates":[-84.453548,33.458597],"type":"Point"}
}