{
  "type": "Feature",
  "properties": {
    "iso:country":"US",
    "sg:address":"105 River West Rd",
    "sg:city":"Bonaire",
    "sg:classifiers":[
        {
            "category":"Manufacturing",
            "subcategory":"Retail Goods",
            "type":"Manufacturing & Wholesale Goods"
        }
    ],
    "sg:phone":"+1 478 922 9060",
    "sg:postcode":"31005",
    "sg:province":"GA",
    "sg:tags":[
        "product",
        "mfg"
    ],
    "wof:name":"Tracys Custom Silks",
    "wof:placetype":"venue"
},
  "geometry": {"coordinates":[-83.55815800000001,32.529567],"type":"Point"}
}