{
  "type": "Feature",
  "properties": {
    "iso:country":"US",
    "sg:address":"326 Eichelberger Dr",
    "sg:city":"La Grange",
    "sg:classifiers":[
        {
            "category":"Building & Trades",
            "subcategory":"Construction",
            "type":"Services"
        }
    ],
    "sg:phone":"+1 706 882 0801",
    "sg:postcode":"30241",
    "sg:province":"GA",
    "sg:tags":[
        "excavation",
        "contractor"
    ],
    "wof:name":"Paul Morgan Backhoe Service",
    "wof:placetype":"venue"
},
  "geometry": {"coordinates":[-84.988011,33.045254],"type":"Point"}
}