{
  "type": "Feature",
  "properties": {
    "addr:full":"23 Jackson St Newnan GA 30263",
    "addr:housenumber":"23",
    "addr:postcode":"30263",
    "addr:street":"Jackson St",
    "iso:country":"US",
    "sg:address":"23 Jackson St",
    "sg:city":"Newnan",
    "sg:classifiers":[
        {
            "category":"Real Estate",
            "subcategory":"Real Estate Agent",
            "type":"Services"
        }
    ],
    "sg:phone":"+1 770 683 0361",
    "sg:postcode":"30263",
    "sg:province":"GA",
    "wof:name":"V I 360 Of Georgia",
    "wof:placetype":"venue"
},
  "geometry": {"coordinates":[-84.80050799999999,33.37446],"type":"Point"}
}