{
  "type": "Feature",
  "properties": {
    "addr:full":"1835 Wellbourne Dr NE Atlanta GA 30324",
    "addr:housenumber":"1835",
    "addr:postcode":"30324",
    "addr:street":"Wellbourne Dr Ne",
    "iso:country":"US",
    "sg:address":"1835 Wellbourne Dr NE",
    "sg:city":"Atlanta",
    "sg:classifiers":[
        {
            "category":"Arts & Performance",
            "subcategory":"Theater",
            "type":"Entertainment"
        }
    ],
    "sg:phone":"+1 404 685 8660",
    "sg:postcode":"30324",
    "sg:province":"GA",
    "sg:tags":[
        "theatrical",
        "manager",
        "producer"
    ],
    "wof:name":"Mud Puppy Productions Inc",
    "wof:placetype":"venue"
},
  "geometry": {"coordinates":[-84.360027,33.806362],"type":"Point"}
}