{
  "type": "Feature",
  "properties": {
    "iso:country":"US",
    "sg:address":"3340 Cobb Pkwy",
    "sg:city":"Atlanta",
    "sg:classifiers":[
        {
            "category":"Autos & Motor Vehicles",
            "subcategory":"Fuel & Gas Station",
            "type":"Retail Goods"
        }
    ],
    "sg:phone":"+1 770 953 1008",
    "sg:postcode":"30339",
    "sg:province":"GA",
    "wof:name":"Pds Vinings Llc",
    "wof:placetype":"venue"
},
  "geometry": {"coordinates":[-84.45663500000001,33.87184],"type":"Point"}
}