{
  "type": "Feature",
  "properties": {
    "iso:country":"US",
    "sg:address":"2870 N Berkeley Lake Rd NW Ste 6",
    "sg:city":"Duluth",
    "sg:classifiers":[
        {
            "category":"Professional",
            "subcategory":"Computer Services",
            "type":"Services"
        }
    ],
    "sg:phone":"+1 770 814 2868",
    "sg:postcode":"30096",
    "sg:province":"GA",
    "sg:tags":[
        "repair"
    ],
    "wof:name":"Capital Remarketing Services",
    "wof:placetype":"venue"
},
  "geometry": {"coordinates":[-84.162548,33.976169],"type":"Point"}
}