{
  "type": "Feature",
  "properties": {
    "addr:full":"3139 Victory Dr Columbus GA 31903",
    "addr:housenumber":"3139",
    "addr:postcode":"31903",
    "addr:street":"Victory Dr",
    "iso:country":"US",
    "sg:address":"3139 Victory Dr",
    "sg:city":"Columbus",
    "sg:classifiers":[
        {
            "category":"Home & Garden",
            "subcategory":"Mobile Homes",
            "type":"Retail Goods"
        }
    ],
    "sg:phone":"+1 706 321 0206",
    "sg:postcode":"31903",
    "sg:province":"GA",
    "sg:tags":[
        "sell",
        "manufactured"
    ],
    "wof:name":"Efficiency Homes",
    "wof:placetype":"venue"
},
  "geometry": {"coordinates":[-84.956281,32.434197],"type":"Point"}
}