{
  "type": "Feature",
  "properties": {
    "iso:country":"US",
    "sg:address":"106 Highlands Way",
    "sg:city":"Peachtree City",
    "sg:classifiers":[
        {
            "category":"Professional",
            "subcategory":"Business Services",
            "type":"Services"
        }
    ],
    "sg:phone":"+1 770 487 2296",
    "sg:postcode":"30269",
    "sg:province":"GA",
    "sg:tags":[
        "interior",
        "consultant",
        "design",
        "decorator"
    ],
    "wof:name":"Distinctions",
    "wof:placetype":"venue"
},
  "geometry": {"coordinates":[-84.573223,33.407205],"type":"Point"}
}