{
  "type": "Feature",
  "properties": {
    "addr:full":"3282 Florence Rd Powder Springs GA 30127",
    "addr:housenumber":"3282",
    "addr:postcode":"30127",
    "addr:street":"Florence Rd",
    "iso:country":"US",
    "sg:address":"3282 Florence Rd",
    "sg:city":"Powder Springs",
    "sg:classifiers":[
        {
            "category":"Organizations",
            "subcategory":"Community Association",
            "type":"Services"
        }
    ],
    "sg:phone":"+1 770 439 0956",
    "sg:postcode":"30127",
    "sg:province":"GA",
    "wof:name":"American Legion Post 294",
    "wof:placetype":"venue"
},
  "geometry": {"coordinates":[-84.701894,33.870127],"type":"Point"}
}