{
  "type": "Feature",
  "properties": {
    "addr:full":"1101 50th St Columbus GA 31904",
    "addr:housenumber":"1101",
    "addr:postcode":"31904",
    "addr:street":"50Th St",
    "iso:country":"US",
    "sg:address":"1101 50th St",
    "sg:city":"Columbus",
    "sg:classifiers":[
        {
            "category":"Manufacturing",
            "subcategory":"Tools & Machinery",
            "type":"Manufacturing & Wholesale Goods"
        }
    ],
    "sg:phone":"+1 706 324 6058",
    "sg:postcode":"31904",
    "sg:province":"GA",
    "sg:tags":[
        "machine",
        "shop"
    ],
    "wof:name":"Dykes' Machine Shop & Metal",
    "wof:placetype":"venue"
},
  "geometry": {"coordinates":[-84.97265299999999,32.513396],"type":"Point"}
}