{
  "type": "Feature",
  "properties": {
    "addr:full":"25 Dogwood Trl Senoia GA 30276",
    "addr:housenumber":"25",
    "addr:postcode":"30276",
    "addr:street":"Dogwood Trl",
    "iso:country":"US",
    "sg:address":"25 Dogwood Trl",
    "sg:city":"Senoia",
    "sg:classifiers":[
        {
            "category":"Building & Trades",
            "subcategory":"Plumbing",
            "type":"Services"
        }
    ],
    "sg:phone":"+1 770 599 1122",
    "sg:postcode":"30276",
    "sg:province":"GA",
    "sg:tags":[
        "contractor"
    ],
    "wof:name":"Tim Derrick Hvac",
    "wof:placetype":"venue"
},
  "geometry": {"coordinates":[-84.577764,33.320662],"type":"Point"}
}