{
  "type": "Feature",
  "properties": {
    "addr:full":"1156 Meriwether St Griffin GA 30224",
    "addr:housenumber":"1156",
    "addr:postcode":"30224",
    "addr:street":"Meriwether St",
    "iso:country":"US",
    "sg:address":"1156 Meriwether St",
    "sg:city":"Griffin",
    "sg:classifiers":[
        {
            "category":"Shopping",
            "subcategory":"Used Merchandise",
            "type":"Retail Goods"
        },
        {
            "category":"Banks & Credit Unions",
            "subcategory":"Bank",
            "type":"Services"
        }
    ],
    "sg:phone":"+1 770 228 1075",
    "sg:postcode":"30224",
    "sg:province":"GA",
    "sg:tags":[
        "cashing",
        "money",
        "pawnbroker",
        "check",
        "order"
    ],
    "wof:name":"Sams Check Cashing Store 2",
    "wof:placetype":"venue"
},
  "geometry": {"coordinates":[-84.28038100000001,33.239651],"type":"Point"}
}