{
  "type": "Feature",
  "properties": {
    "iso:country":"US",
    "sg:address":"780 Johnson Ferry Rd NE",
    "sg:city":"Atlanta",
    "sg:classifiers":[
        {
            "category":"Social Services",
            "subcategory":"Child Care",
            "type":"Services"
        },
        {
            "category":"Education",
            "subcategory":"Preschool",
            "type":"Public Place"
        },
        {
            "category":"Education",
            "subcategory":"School",
            "type":"Public Place"
        }
    ],
    "sg:phone":"+1 404 943 0740",
    "sg:postcode":"30342",
    "sg:province":"GA",
    "sg:tags":[
        "elementary",
        "day"
    ],
    "wof:name":"Creme De La Creme Home Office",
    "wof:placetype":"venue"
},
  "geometry": {"coordinates":[-84.361801,33.907101],"type":"Point"}
}