{
  "type": "Feature",
  "properties": {
    "iso:country":"US",
    "sg:address":"1241 Annapolis Way",
    "sg:city":"Grayson",
    "sg:classifiers":[
        {
            "category":"Real Estate",
            "subcategory":"Real Estate Services",
            "type":"Services"
        },
        {
            "category":"Real Estate",
            "subcategory":"Real Estate Agent",
            "type":"Services"
        }
    ],
    "sg:phone":"+1 770 369 4199",
    "sg:postcode":"30017",
    "sg:province":"GA",
    "sg:tags":[
        "buyer",
        "broker"
    ],
    "wof:name":"Team Harmony Real Estate Group Inc",
    "wof:placetype":"venue"
},
  "geometry": {"coordinates":[-83.993454,33.892727],"type":"Point"}
}