{
  "type": "Feature",
  "properties": {
    "iso:country":"US",
    "sg:address":"1605 Marietta Blvd NW",
    "sg:city":"Atlanta",
    "sg:classifiers":[
        {
            "category":"Wholesale",
            "subcategory":"Construction Materials",
            "type":"Manufacturing & Wholesale Goods"
        }
    ],
    "sg:phone":"+1 404 355 9219",
    "sg:postcode":"30318",
    "sg:province":"GA",
    "wof:name":"Cameron Ashley Building Pdts",
    "wof:placetype":"venue"
},
  "geometry": {"coordinates":[-84.434729,33.799304],"type":"Point"}
}