{
  "type": "Feature",
  "properties": {
    "iso:country":"US",
    "sg:address":"447 N Belair Rd",
    "sg:city":"Evans",
    "sg:classifiers":[
        {
            "category":"Wholesale",
            "subcategory":"Chemicals & Plastics",
            "type":"Manufacturing & Wholesale Goods"
        }
    ],
    "sg:phone":"+1 706 868 3225",
    "sg:postcode":"30809",
    "sg:province":"GA",
    "sg:tags":[
        "oxygen"
    ],
    "wof:name":"Sunrise Oxygen",
    "wof:placetype":"venue"
},
  "geometry": {"coordinates":[-82.13021500000001,33.533393],"type":"Point"}
}