{
  "type": "Feature",
  "properties": {
    "addr:full":"7631 N Point Pkwy Alpharetta GA 30022",
    "addr:housenumber":"7631",
    "addr:postcode":"30022",
    "addr:street":"N Point Pkwy",
    "iso:country":"US",
    "sg:address":"7631 N Point Pkwy",
    "sg:city":"Alpharetta",
    "sg:classifiers":[
        {
            "category":"Shopping",
            "subcategory":"Department Store",
            "type":"Retail Goods"
        }
    ],
    "sg:phone":"+1 770 640 0398",
    "sg:postcode":"30022",
    "sg:province":"GA",
    "sg:tags":[
        "shop"
    ],
    "sg:website":"www.tjmaxx.com",
    "wof:name":"T J Maxx",
    "wof:placetype":"venue"
},
  "geometry": {"coordinates":[-84.25736999999999,34.085695],"type":"Point"}
}