{
  "type": "Feature",
  "properties": {
    "addr:full":"100 Main St Franklin GA 30217",
    "addr:housenumber":"100",
    "addr:postcode":"30217",
    "addr:street":"Main St",
    "iso:country":"US",
    "sg:address":"100 Main St",
    "sg:city":"Franklin",
    "sg:classifiers":[
        {
            "category":"Banks & Credit Unions",
            "subcategory":"Bank",
            "type":"Services"
        },
        {
            "category":"Banks & Credit Unions",
            "subcategory":"Financial Services",
            "type":"Services"
        }
    ],
    "sg:phone":"+1 706 675 6161",
    "sg:postcode":"30217",
    "sg:province":"GA",
    "sg:tags":[
        "mortgage"
    ],
    "sg:website":"http://firstgabnk.com",
    "wof:name":"First Georgia Banking Co",
    "wof:placetype":"venue"
},
  "geometry": {"coordinates":[-85.099487,33.280046],"type":"Point"}
}