{
  "type": "Feature",
  "properties": {
    "addr:full":"2641 Autumn Lake Ln Decatur GA 30034",
    "addr:housenumber":"2641",
    "addr:postcode":"30034",
    "addr:street":"Autumn Lake Ln",
    "iso:country":"US",
    "sg:address":"2641 Autumn Lake Ln",
    "sg:city":"Decatur",
    "sg:classifiers":[
        {
            "category":"Professional",
            "subcategory":"Business Services",
            "type":"Services"
        }
    ],
    "sg:phone":"+1 404 534 0032",
    "sg:postcode":"30034",
    "sg:province":"GA",
    "wof:name":"Dezmal & Cole Interior & Flora",
    "wof:placetype":"venue"
},
  "geometry": {"coordinates":[-84.216882,33.702107],"type":"Point"}
}