{
  "type": "Feature",
  "properties": {
    "addr:full":"658 Grayson Hwy Lawrenceville GA 30045",
    "addr:housenumber":"658",
    "addr:postcode":"30045",
    "addr:street":"Grayson Hwy",
    "iso:country":"US",
    "sg:address":"658 Grayson Hwy",
    "sg:city":"Lawrenceville",
    "sg:classifiers":[
        {
            "category":"Shopping",
            "subcategory":"Bicycles & Sporting Goods",
            "type":"Retail Goods"
        }
    ],
    "sg:phone":"+1 678 377 0270",
    "sg:postcode":"30045",
    "sg:province":"GA",
    "wof:name":"Elite Sports",
    "wof:placetype":"venue"
},
  "geometry": {"coordinates":[-83.978798,33.934502],"type":"Point"}
}