{
  "type": "Feature",
  "properties": {
    "iso:country":"US",
    "sg:address":"1770 Dinsmore Rd",
    "sg:city":"Alpharetta",
    "sg:classifiers":[
        {
            "category":"Freight",
            "type":"Transportation"
        }
    ],
    "sg:phone":"+1 678 624 7657",
    "sg:postcode":"30004",
    "sg:province":"GA",
    "sg:tags":[
        "trucking"
    ],
    "wof:name":"Contract Freighters Inc",
    "wof:placetype":"venue"
},
  "geometry": {"coordinates":[-84.30826500000001,34.153338],"type":"Point"}
}