{
  "type": "Feature",
  "properties": {
    "addr:full":"141 State Rte 243 Ivey GA 31031",
    "addr:housenumber":"141",
    "addr:postcode":"31031",
    "addr:street":"State Rte 243 Ivey",
    "iso:country":"US",
    "sg:address":"141 State Rte 243",
    "sg:city":"Ivey",
    "sg:classifiers":[
        {
            "category":"Restaurant",
            "type":"Food & Drink"
        }
    ],
    "sg:phone":"+1 478 628 3735",
    "sg:postcode":"31031",
    "sg:province":"GA",
    "wof:name":"Ivey General Store",
    "wof:placetype":"venue"
},
  "geometry": {"coordinates":[-83.316911,32.888574],"type":"Point"}
}