{
  "type": "Feature",
  "properties": {
    "iso:country":"US",
    "sg:address":"10593 Barberry Dr",
    "sg:city":"Hampton",
    "sg:classifiers":[
        {
            "category":"Building & Trades",
            "subcategory":"Construction",
            "type":"Services"
        }
    ],
    "sg:phone":"+1 770 210 3083",
    "sg:postcode":"30228",
    "sg:province":"GA",
    "sg:tags":[
        "concrete",
        "contractor"
    ],
    "wof:name":"Mega Concrete",
    "wof:placetype":"venue"
},
  "geometry": {"coordinates":[-84.348983,33.467398],"type":"Point"}
}