{
  "type": "Feature",
  "properties": {
    "addr:full":"10820 Abbotts Bridge Rd Duluth GA 30097",
    "addr:housenumber":"10820",
    "addr:postcode":"30097",
    "addr:street":"Abbotts Bridge Rd",
    "iso:country":"US",
    "sg:address":"10820 Abbotts Bridge Rd",
    "sg:city":"Duluth",
    "sg:classifiers":[
        {
            "category":"Personal",
            "subcategory":"Beauty Salon",
            "type":"Services"
        }
    ],
    "sg:phone":"+1 770 497 9411",
    "sg:postcode":"30097",
    "sg:province":"GA",
    "sg:tags":[
        "shop"
    ],
    "wof:name":"Royal Clips Hair Salon",
    "wof:placetype":"venue"
},
  "geometry": {"coordinates":[-84.169411,34.03219],"type":"Point"}
}