{
  "type": "Feature",
  "properties": {
    "addr:full":"452 Hood Loop Rd Brooklet GA 31321",
    "addr:housenumber":"452",
    "addr:postcode":"31321",
    "addr:street":"Hood Loop Rd",
    "iso:country":"US",
    "sg:address":"452 Hood Loop Rd",
    "sg:city":"Brooklet",
    "sg:classifiers":[
        {
            "category":"Wholesale",
            "subcategory":"Electrical",
            "type":"Manufacturing & Wholesale Goods"
        }
    ],
    "sg:phone":"+1 912 823 3770",
    "sg:postcode":"31321",
    "sg:province":"GA",
    "sg:tags":[
        "electric",
        "motor"
    ],
    "wof:name":"Custom Control Panels",
    "wof:placetype":"venue"
},
  "geometry": {"coordinates":[-81.60764899999999,32.235766],"type":"Point"}
}