{
  "type": "Feature",
  "properties": {
    "iso:country":"US",
    "sg:address":"10 Glenlake Pkwy NE",
    "sg:city":"Atlanta",
    "sg:classifiers":[
        {
            "category":"Professional",
            "subcategory":"Management & Consulting",
            "type":"Services"
        }
    ],
    "sg:phone":"+1 678 222 3444",
    "sg:postcode":"30328",
    "sg:province":"GA",
    "sg:tags":[
        "consultant",
        "educational"
    ],
    "wof:name":"Fisher Educational Consultants",
    "wof:placetype":"venue"
},
  "geometry": {"coordinates":[-84.36077899999999,33.93576],"type":"Point"}
}