{
  "type": "Feature",
  "properties": {
    "addr:full":"59 Price Quarters Rd McDonough GA 30253",
    "addr:housenumber":"59",
    "addr:postcode":"30253",
    "addr:street":"Quarters Rd",
    "iso:country":"US",
    "sg:address":"59 Price Quarters Rd",
    "sg:city":"McDonough",
    "sg:classifiers":[
        {
            "category":"Retail",
            "subcategory":"Veterinary Services",
            "type":"Services"
        }
    ],
    "sg:phone":"+1 678 583 5938",
    "sg:postcode":"30253",
    "sg:province":"GA",
    "sg:tags":[
        "veterinarian"
    ],
    "wof:name":"Eagle's Landing Vet Express",
    "wof:placetype":"venue"
},
  "geometry": {"coordinates":[-84.141296,33.5075],"type":"Point"}
}