{
  "type": "Feature",
  "properties": {
    "addr:full":"1590 Roberts Rd N Kennesaw GA 30144",
    "addr:housenumber":"1590",
    "addr:postcode":"30144",
    "addr:street":"Roberts Rd N",
    "iso:country":"US",
    "sg:address":"1590 Roberts Rd N",
    "sg:city":"Kennesaw",
    "sg:classifiers":[
        {
            "category":"Shopping",
            "subcategory":"Tobacco",
            "type":"Retail Goods"
        },
        {
            "category":"Manufacturing",
            "subcategory":"Tools & Machinery",
            "type":"Manufacturing & Wholesale Goods"
        }
    ],
    "sg:phone":"+1 770 420 2121",
    "sg:postcode":"30144",
    "sg:province":"GA",
    "sg:tags":[
        "cigarette",
        "cigar",
        "dealer",
        "accessory",
        "mfg"
    ],
    "sg:website":"www.burningsolutions.com",
    "wof:name":"Burning Solutions Inc",
    "wof:placetype":"venue"
},
  "geometry": {"coordinates":[-84.59190099999999,34.0044],"type":"Point"}
}