{
  "type": "Feature",
  "properties": {
    "addr:full":"4170 Gables Pl NE Buford GA 30519",
    "addr:housenumber":"4170",
    "addr:postcode":"30519",
    "addr:street":"Gables Pl Ne",
    "iso:country":"US",
    "sg:address":"4170 Gables Pl NE",
    "sg:city":"Buford",
    "sg:classifiers":[
        {
            "category":"Professional",
            "subcategory":"Computer Services",
            "type":"Services"
        }
    ],
    "sg:phone":"+1 770 932 7073",
    "sg:postcode":"30519",
    "sg:province":"GA",
    "sg:tags":[
        "design",
        "system"
    ],
    "wof:name":"Russell Gibbs Inc",
    "wof:placetype":"venue"
},
  "geometry": {"coordinates":[-83.888991,34.07043],"type":"Point"}
}