{
  "type": "Feature",
  "properties": {
    "addr:full":"1013 Wheeler Ave S Douglas GA 31533",
    "addr:housenumber":"1013",
    "addr:postcode":"31533",
    "addr:street":"Wheeler Ave S",
    "iso:country":"US",
    "sg:address":"1013 Wheeler Ave S",
    "sg:city":"Douglas",
    "sg:classifiers":[
        {
            "category":"Home & Garden",
            "subcategory":"Building Materials",
            "type":"Retail Goods"
        },
        {
            "category":"Building & Trades",
            "subcategory":"Construction",
            "type":"Services"
        },
        {
            "category":"Military Area",
            "subcategory":"Armory",
            "type":"Public Place"
        }
    ],
    "sg:phone":"+1 912 384 4402",
    "sg:postcode":"31533",
    "sg:province":"GA",
    "sg:tags":[
        "repair",
        "fence-sales",
        "fence",
        "contractor"
    ],
    "wof:name":"Southland Fence Co",
    "wof:placetype":"venue"
},
  "geometry": {"coordinates":[-82.858891,31.49796],"type":"Point"}
}