{
  "type": "Feature",
  "properties": {
    "addr:full":"2531 Inverloch Cir Duluth GA 30096",
    "addr:housenumber":"2531",
    "addr:postcode":"30096",
    "addr:street":"Inverloch Cir",
    "iso:country":"US",
    "sg:address":"2531 Inverloch Cir",
    "sg:city":"Duluth",
    "sg:classifiers":[
        {
            "category":"Organizations",
            "subcategory":"Community Association",
            "type":"Services"
        }
    ],
    "sg:phone":"+1 770 497 8542",
    "sg:postcode":"30096",
    "sg:province":"GA",
    "wof:name":"Veterans of Foreign Wars",
    "wof:placetype":"venue"
},
  "geometry": {"coordinates":[-84.162938,33.969089],"type":"Point"}
}