{
  "type": "Feature",
  "properties": {
    "iso:country":"US",
    "sg:address":"5859 New Peachtree Rd",
    "sg:city":"Atlanta",
    "sg:classifiers":[
        {
            "category":"Wholesale",
            "subcategory":"Painting Supplies",
            "type":"Manufacturing & Wholesale Goods"
        }
    ],
    "sg:phone":"+1 770 986 8924",
    "sg:postcode":"30340",
    "sg:province":"GA",
    "wof:name":"Ruffs Graphic Enterprises",
    "wof:placetype":"venue"
},
  "geometry": {"coordinates":[-84.280261,33.901761],"type":"Point"}
}