{
  "type": "Feature",
  "properties": {
    "iso:country":"US",
    "sg:address":"4523 Plantation Rd",
    "sg:city":"Augusta",
    "sg:classifiers":[
        {
            "category":"Building & Trades",
            "subcategory":"Cleaning & Sanitation",
            "type":"Services"
        }
    ],
    "sg:phone":"+1 706 854 1446",
    "sg:postcode":"30907",
    "sg:province":"GA",
    "sg:tags":[
        "maintenance"
    ],
    "wof:name":"Anas Home Care Cleaning",
    "wof:placetype":"venue"
},
  "geometry": {"coordinates":[-82.14354299999999,33.493465],"type":"Point"}
}