{
  "type": "Feature",
  "properties": {
    "iso:country":"US",
    "sg:address":"785 Ingram Rd",
    "sg:city":"Barnesville",
    "sg:classifiers":[
        {
            "category":"Retail",
            "subcategory":"Animal Services",
            "type":"Services"
        }
    ],
    "sg:phone":"+1 770 358 0706",
    "sg:postcode":"30204",
    "sg:province":"GA",
    "wof:name":"Four Paws Grooming By Amy",
    "wof:placetype":"venue"
},
  "geometry": {"coordinates":[-84.06445100000001,33.037948],"type":"Point"}
}