{
  "type": "Feature",
  "properties": {
    "addr:full":"1325 Satellite Blvd NW Suwanee GA 30024",
    "addr:housenumber":"1325",
    "addr:postcode":"30024",
    "addr:street":"Satellite Blvd Nw",
    "iso:country":"US",
    "sg:address":"1325 Satellite Blvd NW",
    "sg:city":"Suwanee",
    "sg:classifiers":[
        {
            "category":"Building & Trades",
            "subcategory":"Locksmith",
            "type":"Services"
        }
    ],
    "sg:phone":"+1 888 373 1191",
    "sg:postcode":"30024",
    "sg:province":"GA",
    "sg:tags":[
        "key"
    ],
    "wof:name":"1 24 Hour Emergency Locksmith",
    "wof:placetype":"venue"
},
  "geometry": {"coordinates":[-84.073255,34.009539],"type":"Point"}
}