{
  "type": "Feature",
  "properties": {
    "iso:country":"US",
    "sg:address":"4835 Aldbury Ln",
    "sg:city":"Suwanee",
    "sg:classifiers":[
        {
            "category":"Real Estate",
            "subcategory":"Real Estate Agent",
            "type":"Services"
        }
    ],
    "sg:phone":"+1 770 886 7264",
    "sg:postcode":"30024",
    "sg:province":"GA",
    "sg:tags":[
        "inspection"
    ],
    "wof:name":"Homeowners Home Inspection Svc",
    "wof:placetype":"venue"
},
  "geometry": {"coordinates":[-84.141932,34.092917],"type":"Point"}
}