{
  "type": "Feature",
  "properties": {
    "iso:country":"US",
    "sg:address":"555 Colonial Park Dr Ste 200",
    "sg:city":"Roswell",
    "sg:classifiers":[
        {
            "category":"Travel",
            "subcategory":"Hotels & Motels",
            "type":"Entertainment"
        }
    ],
    "sg:phone":"+1 770 640 0011",
    "sg:postcode":"30075",
    "sg:province":"GA",
    "wof:name":"Coral Hospitality Georgia Llc",
    "wof:placetype":"venue"
},
  "geometry": {"coordinates":[-84.344971,34.032544],"type":"Point"}
}