{
  "type": "Feature",
  "properties": {
    "addr:full":"3157 Presidential Dr Atlanta GA 30340",
    "addr:housenumber":"3157",
    "addr:postcode":"30340",
    "addr:street":"Presidential Dr",
    "iso:country":"US",
    "sg:address":"3157 Presidential Dr",
    "sg:city":"Atlanta",
    "sg:phone":"+1 770 457 6548",
    "sg:postcode":"30340",
    "sg:province":"GA",
    "sg:tags":[
        "commercial",
        "representative",
        "for"
    ],
    "wof:name":"Cg Distributing",
    "wof:placetype":"venue"
},
  "geometry": {"coordinates":[-84.259828,33.886732],"type":"Point"}
}