{
  "type": "Feature",
  "properties": {
    "iso:country":"US",
    "sg:address":"435 Langley Oaks Dr SE",
    "sg:city":"Marietta",
    "sg:classifiers":[
        {
            "category":"Professional",
            "subcategory":"Business Services",
            "type":"Services"
        }
    ],
    "sg:phone":"+1 770 955 1591",
    "sg:postcode":"30067",
    "sg:province":"GA",
    "wof:name":"Cheryl Crawford Wade & Assoc",
    "wof:placetype":"venue"
},
  "geometry": {"coordinates":[-84.44846699999999,33.940716],"type":"Point"}
}