{
  "type": "Feature",
  "properties": {
    "iso:country":"US",
    "sg:address":"997 Commerce Dr SW",
    "sg:city":"Conyers",
    "sg:classifiers":[
        {
            "category":"Travel",
            "subcategory":"Hotels & Motels",
            "type":"Entertainment"
        }
    ],
    "sg:phone":"+1 770 761 2029",
    "sg:postcode":"30094",
    "sg:province":"GA",
    "sg:tags":[
        "resort"
    ],
    "wof:name":"RNR Resort",
    "wof:placetype":"venue"
},
  "geometry": {"coordinates":[-84.02352399999999,33.655732],"type":"Point"}
}