{
  "type": "Feature",
  "properties": {
    "addr:full":"310 Peachtree Industrial Blvd Sugar Hill GA 30518",
    "addr:housenumber":"310",
    "addr:postcode":"30518",
    "addr:street":"Peachtree Industrial Blvd;Hill",
    "iso:country":"US",
    "sg:address":"310 Peachtree Industrial Blvd",
    "sg:city":"Sugar Hill",
    "sg:classifiers":[
        {
            "category":"Professional",
            "type":"Services"
        }
    ],
    "sg:phone":"+1 770 271 4003",
    "sg:postcode":"30518",
    "sg:province":"GA",
    "sg:tags":[
        "establishment"
    ],
    "wof:name":"Ann Enterprises LLC",
    "wof:placetype":"venue"
},
  "geometry": {"coordinates":[-84.055415,34.081305],"type":"Point"}
}