{
  "type": "Feature",
  "properties": {
    "addr:full":"1711 Nixon Rd Augusta GA 30906",
    "addr:housenumber":"1711",
    "addr:postcode":"30906",
    "addr:street":"Nixon Rd",
    "iso:country":"US",
    "sg:address":"1711 Nixon Rd",
    "sg:city":"Augusta",
    "sg:classifiers":[
        {
            "category":"Building & Trades",
            "subcategory":"Cleaning & Sanitation",
            "type":"Services"
        }
    ],
    "sg:phone":"+1 706 790 1940",
    "sg:postcode":"30906",
    "sg:province":"GA",
    "sg:tags":[
        "maintenance"
    ],
    "wof:name":"MPW Industrial Services Inc",
    "wof:placetype":"venue"
},
  "geometry": {"coordinates":[-82.000455,33.427531],"type":"Point"}
}