{
  "type": "Feature",
  "properties": {
    "addr:full":"128 E Main St Irwinton GA 31042",
    "addr:housenumber":"128",
    "addr:postcode":"31042",
    "addr:street":"E Main St",
    "iso:country":"US",
    "sg:address":"128 E Main St",
    "sg:city":"Irwinton",
    "sg:classifiers":[
        {
            "category":"Shopping",
            "subcategory":"Florist",
            "type":"Retail Goods"
        }
    ],
    "sg:phone":"+1 478 946 2818",
    "sg:postcode":"31042",
    "sg:province":"GA",
    "wof:name":"Extra Hours",
    "wof:placetype":"venue"
},
  "geometry": {"coordinates":[-83.17111199999999,32.813616],"type":"Point"}
}