{
  "type": "Feature",
  "properties": {
    "iso:country":"US",
    "sg:address":"4153 Country Manor Ct NE",
    "sg:city":"Woodstock",
    "sg:classifiers":[
        {
            "category":"Professional",
            "subcategory":"Art Services",
            "type":"Services"
        }
    ],
    "sg:phone":"+1 770 516 0420",
    "sg:postcode":"30188",
    "sg:province":"GA",
    "sg:tags":[
        "commercial",
        "design"
    ],
    "wof:name":"Shiffler Graphics",
    "wof:placetype":"venue"
},
  "geometry": {"coordinates":[-84.430162,34.072978],"type":"Point"}
}