{
  "type": "Feature",
  "properties": {
    "addr:full":"5934 Roswell Road NE Atlanta GA 30328",
    "addr:housenumber":"5934",
    "addr:postcode":"30328",
    "addr:street":"Roswell Road Ne",
    "iso:country":"US",
    "sg:address":"5934 Roswell Road NE",
    "sg:city":"Atlanta",
    "sg:classifiers":[
        {
            "category":"Wholesale",
            "subcategory":"Computers",
            "type":"Manufacturing & Wholesale Goods"
        }
    ],
    "sg:phone":"+1 404 705 8809",
    "sg:postcode":"30328",
    "sg:province":"GA",
    "wof:name":"Office Depot",
    "wof:placetype":"venue"
},
  "geometry": {"coordinates":[-84.37902699999999,33.916627],"type":"Point"}
}