{
  "type": "Feature",
  "properties": {
    "addr:full":"343 State Rte 11 Monroe GA 30655",
    "addr:housenumber":"343",
    "addr:postcode":"30655",
    "addr:street":"State Rte 11",
    "iso:country":"US",
    "sg:address":"343 State Rte 11",
    "sg:city":"Monroe",
    "sg:classifiers":[
        {
            "category":"Real Estate",
            "subcategory":"Real Estate Agent",
            "type":"Services"
        }
    ],
    "sg:phone":"+1 770 464 9933",
    "sg:postcode":"30655",
    "sg:province":"GA",
    "wof:name":"Holder Land Action-Spring Rlty",
    "wof:placetype":"venue"
},
  "geometry": {"coordinates":[-83.71438499999999,33.79901],"type":"Point"}
}