{
  "type": "Feature",
  "properties": {
    "iso:country":"US",
    "sg:address":"625 W Taylor St",
    "sg:city":"Griffin",
    "sg:classifiers":[
        {
            "category":"Personal",
            "subcategory":"Beauty Salon",
            "type":"Services"
        }
    ],
    "sg:phone":"+1 678 688 1067",
    "sg:postcode":"30223",
    "sg:province":"GA",
    "wof:name":"L J's Salon",
    "wof:placetype":"venue"
},
  "geometry": {"coordinates":[-84.273144,33.247372],"type":"Point"}
}