{
  "type": "Feature",
  "properties": {
    "iso:country":"US",
    "sg:address":"440 Eddie Avery Rd",
    "sg:city":"Climax",
    "sg:classifiers":[
        {
            "category":"Building & Trades",
            "subcategory":"Construction",
            "type":"Services"
        }
    ],
    "sg:phone":"+1 229 246 8253",
    "sg:postcode":"39834",
    "sg:province":"GA",
    "sg:tags":[
        "wallcoverings-installation",
        "wallpaper",
        "painting",
        "contractor"
    ],
    "wof:name":"Anvar Painting",
    "wof:placetype":"venue"
},
  "geometry": {"coordinates":[-84.43952400000001,30.993084],"type":"Point"}
}