{
  "type": "Feature",
  "properties": {
    "iso:country":"US",
    "sg:address":"2628 Lawrenceville Hwy",
    "sg:city":"Decatur",
    "sg:classifiers":[
        {
            "category":"Autos & Motor Vehicles",
            "subcategory":"Automobile Sales",
            "type":"Retail Goods"
        }
    ],
    "sg:phone":"+1 770 270 0030",
    "sg:postcode":"30033",
    "sg:province":"GA",
    "sg:tags":[
        "car"
    ],
    "wof:name":"Shamrock Auto Sales",
    "wof:placetype":"venue"
},
  "geometry": {"coordinates":[-84.26149700000001,33.823502],"type":"Point"}
}