{
  "type": "Feature",
  "properties": {
    "addr:full":"106 Kay Ln Carrollton GA 30117",
    "addr:housenumber":"106",
    "addr:postcode":"30117",
    "addr:street":"Kay Ln",
    "iso:country":"US",
    "sg:address":"106 Kay Ln",
    "sg:city":"Carrollton",
    "sg:classifiers":[
        {
            "category":"Personal",
            "subcategory":"Beauty Salon",
            "type":"Services"
        }
    ],
    "sg:phone":"+1 770 836 8400",
    "sg:postcode":"30117",
    "sg:province":"GA",
    "wof:name":"Finished Looks",
    "wof:placetype":"venue"
},
  "geometry": {"coordinates":[-85.061915,33.601079],"type":"Point"}
}