{
  "type": "Feature",
  "properties": {
    "iso:country":"US",
    "sg:address":"1702 Duke Rd",
    "sg:city":"Atlanta",
    "sg:classifiers":[
        {
            "category":"Building & Trades",
            "subcategory":"Cleaning & Sanitation",
            "type":"Services"
        }
    ],
    "sg:phone":"+1 770 455 4154",
    "sg:postcode":"30341",
    "sg:province":"GA",
    "sg:tags":[
        "maintenance"
    ],
    "wof:name":"Complete Maintenance Inc",
    "wof:placetype":"venue"
},
  "geometry": {"coordinates":[-84.31905399999999,33.869725],"type":"Point"}
}