{
  "type": "Feature",
  "properties": {
    "addr:full":"1901 Chatham Ave Tybee Island GA 31328",
    "addr:housenumber":"1901",
    "addr:postcode":"31328",
    "addr:street":"Chatham Ave",
    "iso:country":"US",
    "sg:address":"1901 Chatham Ave",
    "sg:city":"Tybee Island",
    "sg:classifiers":[
        {
            "category":"Professional",
            "type":"Services"
        }
    ],
    "sg:phone":"+1 912 786 4091",
    "sg:postcode":"31328",
    "sg:province":"GA",
    "sg:tags":[
        "establishment"
    ],
    "wof:name":"JFC Myers Cottage",
    "wof:placetype":"venue"
},
  "geometry": {"coordinates":[-80.85137899999999,31.987003],"type":"Point"}
}