{
  "type": "Feature",
  "properties": {
    "addr:full":"172 Rollingwood Trl Sharpsburg GA 30277",
    "addr:housenumber":"172",
    "addr:postcode":"30277",
    "addr:street":"Rollingwood Trl",
    "iso:country":"US",
    "sg:address":"172 Rollingwood Trl",
    "sg:city":"Sharpsburg",
    "sg:classifiers":[
        {
            "category":"Arts & Performance",
            "subcategory":"Theater",
            "type":"Entertainment"
        }
    ],
    "sg:phone":"+1 770 252 9954",
    "sg:postcode":"30277",
    "sg:province":"GA",
    "sg:tags":[
        "live",
        "music"
    ],
    "wof:name":"Uptown Music DJ Svc",
    "wof:placetype":"venue"
},
  "geometry": {"coordinates":[-84.647949,33.435591],"type":"Point"}
}