{
  "type": "Feature",
  "properties": {
    "iso:country":"US",
    "sg:address":"315 Jackson Lake Inn Rd",
    "sg:city":"Jackson",
    "sg:classifiers":[
        {
            "category":"Real Estate",
            "subcategory":"Real Estate Agent",
            "type":"Services"
        }
    ],
    "sg:phone":"+1 678 432 5958",
    "sg:postcode":"30233",
    "sg:province":"GA",
    "wof:name":"Keystone Realty",
    "wof:placetype":"venue"
},
  "geometry": {"coordinates":[-83.87689899999999,33.341105],"type":"Point"}
}