{
  "type": "Feature",
  "properties": {
    "addr:full":"4152 Washington St SW Covington GA 30014",
    "addr:housenumber":"4152",
    "addr:postcode":"30014",
    "addr:street":"Washington St Sw",
    "iso:country":"US",
    "sg:address":"4152 Washington St SW",
    "sg:city":"Covington",
    "sg:classifiers":[
        {
            "category":"Food & Beverages",
            "subcategory":"Groceries & Convenience Stores",
            "type":"Retail Goods"
        }
    ],
    "sg:phone":"+1 770 786 9732",
    "sg:postcode":"30014",
    "sg:province":"GA",
    "sg:tags":[
        "grocer"
    ],
    "wof:name":"Johnson's Super Market",
    "wof:placetype":"venue"
},
  "geometry": {"coordinates":[-83.871314,33.593964],"type":"Point"}
}