{
  "type": "Feature",
  "properties": {
    "addr:full":"127 W Park St Buford GA 30518",
    "addr:housenumber":"127",
    "addr:postcode":"30518",
    "addr:street":"W Park St",
    "iso:country":"US",
    "sg:address":"127 W Park St",
    "sg:city":"Buford",
    "sg:classifiers":[
        {
            "category":"Building & Trades",
            "subcategory":"Construction",
            "type":"Services"
        }
    ],
    "sg:phone":"+1 770 932 7981",
    "sg:postcode":"30518",
    "sg:province":"GA",
    "sg:tags":[
        "marking",
        "maintenance",
        "parking"
    ],
    "wof:name":"Buford Public Works Dept",
    "wof:placetype":"venue"
},
  "geometry": {"coordinates":[-84.006514,34.117165],"type":"Point"}
}