{
  "type": "Feature",
  "properties": {
    "addr:full":"2041 Old Elbert Rd Royston GA 30662",
    "addr:housenumber":"2041",
    "addr:postcode":"30662",
    "addr:street":"Old Elbert Rd",
    "iso:country":"US",
    "sg:address":"2041 Old Elbert Rd",
    "sg:city":"Royston",
    "sg:classifiers":[
        {
            "category":"Manufacturing",
            "subcategory":"Wood Products",
            "type":"Manufacturing & Wholesale Goods"
        }
    ],
    "sg:phone":"+1 706 245 1069",
    "sg:postcode":"30662",
    "sg:province":"GA",
    "sg:tags":[
        "container",
        "mfg"
    ],
    "wof:name":"Royston Farms",
    "wof:placetype":"venue"
},
  "geometry": {"coordinates":[-83.082791,34.260566],"type":"Point"}
}