{
  "type": "Feature",
  "properties": {
    "iso:country":"US",
    "sg:address":"1153 Clarendon Dr",
    "sg:city":"Marietta",
    "sg:classifiers":[
        {
            "category":"Real Estate",
            "subcategory":"Real Estate Operator",
            "type":"Services"
        }
    ],
    "sg:phone":"+1 770 552 8895",
    "sg:postcode":"30068",
    "sg:province":"GA",
    "sg:tags":[
        "building",
        "nonresidential"
    ],
    "wof:name":"Sango Properties Inc",
    "wof:placetype":"venue"
},
  "geometry": {"coordinates":[-84.41016,33.976269],"type":"Point"}
}