{
  "type": "Feature",
  "properties": {
    "iso:country":"US",
    "sg:address":"3150 Spain Rd",
    "sg:city":"Snellville",
    "sg:classifiers":[
        {
            "category":"Education",
            "subcategory":"School",
            "type":"Public Place"
        }
    ],
    "sg:phone":"+1 770 979 2950",
    "sg:postcode":"30039",
    "sg:province":"GA",
    "sg:tags":[
        "elementary"
    ],
    "wof:name":"Annistown Elementary School",
    "wof:placetype":"venue"
},
  "geometry": {"coordinates":[-84.070579,33.803776],"type":"Point"}
}