{
  "type": "Feature",
  "properties": {
    "iso:country":"US",
    "sg:address":"601 Peterson Ave N",
    "sg:city":"Douglas",
    "sg:classifiers":[
        {
            "category":"Home & Garden",
            "subcategory":"Carpets & Floor Coverings",
            "type":"Retail Goods"
        }
    ],
    "sg:phone":"+1 912 384 1943",
    "sg:postcode":"31533",
    "sg:province":"GA",
    "sg:tags":[
        "rug"
    ],
    "wof:name":"Nellie's Interiors",
    "wof:placetype":"venue"
},
  "geometry": {"coordinates":[-82.85056299999999,31.514191],"type":"Point"}
}