{
  "type": "Feature",
  "properties": {
    "iso:country":"US",
    "sg:address":"1860 Flat Shoals Rd SE",
    "sg:city":"Conyers",
    "sg:classifiers":[
        {
            "category":"Banks & Credit Unions",
            "subcategory":"Financial Services",
            "type":"Services"
        }
    ],
    "sg:phone":"+1 770 922 8417",
    "sg:postcode":"30013",
    "sg:province":"GA",
    "sg:tags":[
        "trust",
        "management"
    ],
    "wof:name":"United Daughters of Confe",
    "wof:placetype":"venue"
},
  "geometry": {"coordinates":[-83.98169900000001,33.631425],"type":"Point"}
}