{
  "type": "Feature",
  "properties": {
    "addr:full":"122 N Springs Ct Macon GA 31210",
    "addr:housenumber":"122",
    "addr:postcode":"31210",
    "addr:street":"N Springs Ct",
    "iso:country":"US",
    "sg:address":"122 N Springs Ct",
    "sg:city":"Macon",
    "sg:classifiers":[
        {
            "category":"Insurance",
            "subcategory":"Insurance Agent",
            "type":"Services"
        }
    ],
    "sg:phone":"+1 478 474 5385",
    "sg:postcode":"31210",
    "sg:province":"GA",
    "wof:name":"Bridges & Associates",
    "wof:placetype":"venue"
},
  "geometry": {"coordinates":[-83.72754999999999,32.905401],"type":"Point"}
}