{
  "type": "Feature",
  "properties": {
    "addr:full":"1929 Manor Oak Ln Buford GA 30519",
    "addr:housenumber":"1929",
    "addr:postcode":"30519",
    "addr:street":"Manor Oak Ln",
    "iso:country":"US",
    "sg:address":"1929 Manor Oak Ln",
    "sg:city":"Buford",
    "sg:classifiers":[
        {
            "category":"Professional",
            "subcategory":"Business Services",
            "type":"Services"
        }
    ],
    "sg:phone":"+1 678 376 1185",
    "sg:postcode":"30519",
    "sg:province":"GA",
    "wof:name":"Business Web Site Fast",
    "wof:placetype":"venue"
},
  "geometry": {"coordinates":[-83.964191,34.048237],"type":"Point"}
}