{
  "type": "Feature",
  "properties": {
    "addr:full":"583 Conyers Rd Loganville GA 30052",
    "addr:housenumber":"583",
    "addr:postcode":"30052",
    "addr:street":"Conyers Rd",
    "iso:country":"US",
    "sg:address":"583 Conyers Rd",
    "sg:city":"Loganville",
    "sg:classifiers":[
        {
            "category":"Personal",
            "subcategory":"Beauty Salon",
            "type":"Services"
        }
    ],
    "sg:phone":"+1 770 554 1299",
    "sg:postcode":"30052",
    "sg:province":"GA",
    "wof:name":"Hair Razor",
    "wof:placetype":"venue"
},
  "geometry": {"coordinates":[-83.913094,33.830998],"type":"Point"}
}