{
  "type": "Feature",
  "properties": {
    "iso:country":"US",
    "sg:address":"159 Jefferson Pl",
    "sg:city":"Decatur",
    "sg:classifiers":[
        {
            "category":"Professional",
            "subcategory":"Business Services",
            "type":"Services"
        }
    ],
    "sg:phone":"+1 404 377 0977",
    "sg:postcode":"30030",
    "sg:province":"GA",
    "wof:name":"Rhame Enterprises Inc",
    "wof:placetype":"venue"
},
  "geometry": {"coordinates":[-84.30359,33.766267],"type":"Point"}
}