{
  "type": "Feature",
  "properties": {
    "addr:full":"758 Highway 155 S McDonough GA 30253",
    "addr:housenumber":"758",
    "addr:postcode":"30253",
    "addr:street":"Highway 155 S",
    "iso:country":"US",
    "sg:address":"758 Highway 155 S",
    "sg:city":"McDonough",
    "sg:classifiers":[
        {
            "category":"Autos & Motor Vehicles",
            "subcategory":"Fuel & Gas Station",
            "type":"Retail Goods"
        }
    ],
    "sg:phone":"+1 770 954 1486",
    "sg:postcode":"30253",
    "sg:province":"GA",
    "sg:website":"www.texaco.com",
    "wof:name":"Liberty Center Texaco",
    "wof:placetype":"venue"
},
  "geometry": {"coordinates":[-84.158798,33.4128],"type":"Point"}
}