{
  "type": "Feature",
  "properties": {
    "addr:full":"2808 Piney Grove Rd Blackshear GA 31516",
    "addr:housenumber":"2808",
    "addr:postcode":"31516",
    "addr:street":"Piney Grove Rd",
    "iso:country":"US",
    "sg:address":"2808 Piney Grove Rd",
    "sg:city":"Blackshear",
    "sg:classifiers":[
        {
            "category":"Place Of Worship",
            "subcategory":"Church",
            "type":"Public Place"
        },
        {
            "category":"Place Of Worship",
            "type":"Public Place"
        },
        {
            "category":"Place Of Worship",
            "subcategory":"Shrine",
            "type":"Public Place"
        }
    ],
    "sg:phone":"+1 912 449 6968",
    "sg:postcode":"31516",
    "sg:province":"GA",
    "sg:tags":[
        "churches-baptist-free",
        "churches-baptist"
    ],
    "wof:name":"Piney Grove Freewill Baptist Church",
    "wof:placetype":"venue"
},
  "geometry": {"coordinates":[-82.26979,31.302475],"type":"Point"}
}