{
  "type": "Feature",
  "properties": {
    "iso:country":"US",
    "sg:address":"3491 Buckhead Loop NE",
    "sg:city":"Atlanta",
    "sg:classifiers":[
        {
            "category":"Retail",
            "subcategory":"Auto Repair",
            "type":"Services"
        }
    ],
    "sg:phone":"+1 678 777 8622",
    "sg:postcode":"30326",
    "sg:province":"GA",
    "sg:tags":[
        "body",
        "shop"
    ],
    "wof:name":"Ultimate Appearance \u00a0Inc",
    "wof:placetype":"venue"
},
  "geometry": {"coordinates":[-84.372101,33.850498],"type":"Point"}
}