{
  "type": "Feature",
  "properties": {
    "iso:country":"US",
    "sg:address":"6399 State Rte 53",
    "sg:city":"Braselton",
    "sg:classifiers":[
        {
            "category":"Shopping",
            "subcategory":"Used Merchandise",
            "type":"Retail Goods"
        }
    ],
    "sg:phone":"+1 706 654 5644",
    "sg:postcode":"30517",
    "sg:province":"GA",
    "sg:tags":[
        "clothing"
    ],
    "wof:name":"Kathy's Boutique",
    "wof:placetype":"venue"
},
  "geometry": {"coordinates":[-83.76536900000001,34.127282],"type":"Point"}
}