{
  "type": "Feature",
  "properties": {
    "iso:country":"US",
    "sg:address":"4805 Trolley Ct SE",
    "sg:city":"Smyrna",
    "sg:classifiers":[
        {
            "category":"Real Estate",
            "subcategory":"Real Estate Agent",
            "type":"Services"
        }
    ],
    "sg:phone":"+1 404 261 2700",
    "sg:postcode":"30080",
    "sg:province":"GA",
    "wof:name":"Alison Schueneman Inc",
    "wof:placetype":"venue"
},
  "geometry": {"coordinates":[-84.49401899999999,33.849349],"type":"Point"}
}