{
  "type": "Feature",
  "properties": {
    "addr:full":"334 N Clayton St Lawrenceville GA 30045",
    "addr:housenumber":"334",
    "addr:postcode":"30045",
    "addr:street":"N Clayton St",
    "iso:country":"US",
    "sg:address":"334 N Clayton St",
    "sg:city":"Lawrenceville",
    "sg:classifiers":[
        {
            "category":"Building & Trades",
            "subcategory":"Construction",
            "type":"Services"
        },
        {
            "category":"Retail",
            "subcategory":"Auto Repair",
            "type":"Services"
        }
    ],
    "sg:phone":"+1 770 513 9080",
    "sg:postcode":"30045",
    "sg:province":"GA",
    "sg:tags":[
        "body",
        "house",
        "painting",
        "automobile"
    ],
    "wof:name":"Auto Collision Repair",
    "wof:placetype":"venue"
},
  "geometry": {"coordinates":[-83.98858799999999,33.959434],"type":"Point"}
}