{
  "type": "Feature",
  "properties": {
    "iso:country":"US",
    "sg:address":"4558 Windsor Oaks Ct",
    "sg:city":"Marietta",
    "sg:classifiers":[
        {
            "category":"Professional",
            "subcategory":"Business Services",
            "type":"Services"
        }
    ],
    "sg:phone":"+1 770 926 9746",
    "sg:postcode":"30066",
    "sg:province":"GA",
    "wof:name":"Bcb Enterprises",
    "wof:placetype":"venue"
},
  "geometry": {"coordinates":[-84.47089,34.05602],"type":"Point"}
}