{
  "type": "Feature",
  "properties": {
    "addr:full":"1015 State Rte 34 Newnan GA 30265",
    "addr:housenumber":"1015",
    "addr:postcode":"30265",
    "addr:street":"State Rte 34",
    "iso:country":"US",
    "sg:address":"1015 State Rte 34",
    "sg:city":"Newnan",
    "sg:classifiers":[
        {
            "category":"Restaurant",
            "type":"Food & Drink"
        }
    ],
    "sg:phone":"+1 678 423 8880",
    "sg:postcode":"30265",
    "sg:province":"GA",
    "wof:name":"Panda Express",
    "wof:placetype":"venue"
},
  "geometry": {"coordinates":[-84.732518,33.399112],"type":"Point"}
}