{
  "type": "Feature",
  "properties": {
    "iso:country":"US",
    "sg:address":"110 Paper Mill Rd",
    "sg:city":"Lawrenceville",
    "sg:classifiers":[
        {
            "category":"Organizations",
            "subcategory":"Religious Organization",
            "type":"Services"
        }
    ],
    "sg:phone":"+1 770 513 8862",
    "sg:postcode":"30045",
    "sg:province":"GA",
    "wof:name":"Victory Baptist Church",
    "wof:placetype":"venue"
},
  "geometry": {"coordinates":[-83.971733,33.956389],"type":"Point"}
}