{
  "type": "Feature",
  "properties": {
    "addr:full":"308 Ballew Rd Alto GA 30510",
    "addr:housenumber":"308",
    "addr:postcode":"30510",
    "addr:street":"Ballew Rd",
    "iso:country":"US",
    "sg:address":"308 Ballew Rd",
    "sg:city":"Alto",
    "sg:classifiers":[
        {
            "category":"Manufacturing",
            "subcategory":"Motor Vehicles & Parts",
            "type":"Manufacturing & Wholesale Goods"
        }
    ],
    "sg:phone":"+1 706 778 1813",
    "sg:postcode":"30510",
    "sg:province":"GA",
    "sg:tags":[
        "on",
        "screen",
        "printing",
        "fabric",
        "article"
    ],
    "wof:name":"Blue Graphics Inc",
    "wof:placetype":"venue"
},
  "geometry": {"coordinates":[-83.60399700000001,34.462019],"type":"Point"}
}