{
  "type": "Feature",
  "properties": {
    "addr:full":"25 Technology Pkwy NW Norcross GA 30092",
    "addr:housenumber":"25",
    "addr:postcode":"30092",
    "addr:street":"Technology Pkwy Nw",
    "iso:country":"US",
    "sg:address":"25 Technology Pkwy NW",
    "sg:city":"Norcross",
    "sg:classifiers":[
        {
            "category":"Real Estate",
            "subcategory":"Developer",
            "type":"Services"
        }
    ],
    "sg:phone":"+1 770 559 4821",
    "sg:postcode":"30092",
    "sg:province":"GA",
    "wof:name":"Commonwealth Properties",
    "wof:placetype":"venue"
},
  "geometry": {"coordinates":[-84.21789800000001,33.967285],"type":"Point"}
}