{
  "type": "Feature",
  "properties": {
    "iso:country":"US",
    "sg:address":"3101 Mercury Dr",
    "sg:city":"Columbus",
    "sg:classifiers":[
        {
            "category":"Retail",
            "subcategory":"Car Wash",
            "type":"Services"
        }
    ],
    "sg:phone":"+1 706 561 6013",
    "sg:postcode":"31906",
    "sg:province":"GA",
    "sg:tags":[
        "polishing",
        "washing"
    ],
    "wof:name":"Goo-Goo Car Wash",
    "wof:placetype":"venue"
},
  "geometry": {"coordinates":[-84.945544,32.480162],"type":"Point"}
}