{
  "type": "Feature",
  "properties": {
    "addr:full":"5050 Jimmy Carter Blvd Norcross GA 30093",
    "addr:housenumber":"5050",
    "addr:postcode":"30093",
    "addr:street":"Jimmy Carter Blvd",
    "iso:country":"US",
    "sg:address":"5050 Jimmy Carter Blvd",
    "sg:city":"Norcross",
    "sg:classifiers":[
        {
            "category":"Local Transit",
            "type":"Transportation"
        }
    ],
    "sg:phone":"+1 770 840 2110",
    "sg:postcode":"30093",
    "sg:province":"GA",
    "sg:tags":[
        "bus",
        "line"
    ],
    "wof:name":"U pS Shipping Outlet",
    "wof:placetype":"venue"
},
  "geometry": {"coordinates":[-84.198769,33.896992],"type":"Point"}
}