{
  "type": "Feature",
  "properties": {
    "addr:full":"700 Old Roswell Rd Roswell GA 30076",
    "addr:housenumber":"700",
    "addr:postcode":"30076",
    "addr:street":"Old Roswell Rd",
    "iso:country":"US",
    "sg:address":"700 Old Roswell Rd",
    "sg:city":"Roswell",
    "sg:classifiers":[
        {
            "category":"Professional",
            "subcategory":"Advertising",
            "type":"Services"
        }
    ],
    "sg:phone":"+1 770 998 5832",
    "sg:postcode":"30076",
    "sg:province":"GA",
    "wof:name":"X I Promotions Inc",
    "wof:placetype":"venue"
},
  "geometry": {"coordinates":[-84.339446,34.034423],"type":"Point"}
}