{
  "type": "Feature",
  "properties": {
    "addr:full":"1150 Hammond Dr NE B2100 Atlanta GA 30328",
    "addr:housenumber":"1150",
    "addr:postcode":"30328",
    "addr:street":"Hammond Dr Ne",
    "iso:country":"US",
    "sg:address":"1150 Hammond Dr NE B2100",
    "sg:city":"Atlanta",
    "sg:classifiers":[
        {
            "category":"Health Services",
            "subcategory":"Health Practitioner",
            "type":"Services"
        },
        {
            "category":"Communications",
            "type":"Services"
        }
    ],
    "sg:phone":"+1 770 673 0093",
    "sg:postcode":"30328",
    "sg:province":"GA",
    "sg:tags":[
        "pathologist",
        "speech-language",
        "myofunctional",
        "therapy"
    ],
    "sg:website":"http://www.foundationtherapy.com",
    "wof:name":"Foundation Therapy Center North Atlanta",
    "wof:placetype":"venue"
},
  "geometry": {"coordinates":[-84.34787799999999,33.919274],"type":"Point"}
}