{
  "type": "Feature",
  "properties": {
    "iso:country":"US",
    "sg:address":"322 Glenn Milner Blvd",
    "sg:city":"Rome",
    "sg:classifiers":[
        {
            "category":"Wholesale",
            "subcategory":"Office Equipment",
            "type":"Manufacturing & Wholesale Goods"
        }
    ],
    "sg:phone":"+1 706 291 0847",
    "sg:postcode":"30161",
    "sg:province":"GA",
    "sg:tags":[
        "machine",
        "duplicating",
        "copying"
    ],
    "sg:website":"www.rolans.com",
    "wof:name":"Rolan Business Machine Co",
    "wof:placetype":"venue"
},
  "geometry": {"coordinates":[-85.16664299999999,34.249764],"type":"Point"}
}