{
  "type": "Feature",
  "properties": {
    "iso:country":"US",
    "sg:address":"5172 Blunschi Dr",
    "sg:city":"Powder Springs",
    "sg:classifiers":[
        {
            "category":"Real Estate",
            "subcategory":"Real Estate Operator",
            "type":"Services"
        }
    ],
    "sg:phone":"+1 770 943 1173",
    "sg:postcode":"30127",
    "sg:province":"GA",
    "sg:tags":[
        "building",
        "nonresidential"
    ],
    "wof:name":"Lankford Properties Inc",
    "wof:placetype":"venue"
},
  "geometry": {"coordinates":[-84.70360599999999,33.84249],"type":"Point"}
}