{
  "type": "Feature",
  "properties": {
    "iso:country":"US",
    "sg:address":"3803 Washington Rd",
    "sg:city":"Augusta",
    "sg:classifiers":[
        {
            "category":"Restaurant",
            "type":"Food & Drink"
        }
    ],
    "sg:menulink":"http://www.allmenus.com/ga/evans/70795-pizza-hut/menu/",
    "sg:phone":"+1 706 860 9654",
    "sg:postcode":"30907",
    "sg:province":"GA",
    "sg:tags":[
        "american",
        "pizza"
    ],
    "wof:name":"Pizza Hut",
    "wof:placetype":"venue"
},
  "geometry": {"coordinates":[-82.086608,33.512951],"type":"Point"}
}