{
  "type": "Feature",
  "properties": {
    "addr:full":"2617 Carrington Dr Hephzibah GA 30815",
    "addr:housenumber":"2617",
    "addr:postcode":"30815",
    "addr:street":"Carrington Dr",
    "iso:country":"US",
    "sg:address":"2617 Carrington Dr",
    "sg:city":"Hephzibah",
    "sg:classifiers":[
        {
            "category":"Cinema",
            "subcategory":"Movie Rental",
            "type":"Entertainment"
        }
    ],
    "sg:phone":"+1 706 294 3923",
    "sg:postcode":"30815",
    "sg:province":"GA",
    "sg:tags":[
        "motion",
        "picture",
        "distributor",
        "film",
        "exchange"
    ],
    "wof:name":"Imperial Productions",
    "wof:placetype":"venue"
},
  "geometry": {"coordinates":[-82.09245199999999,33.372015],"type":"Point"}
}