{
  "type": "Feature",
  "properties": {
    "iso:country":"US",
    "sg:address":"2036 Bolton Dr NW",
    "sg:city":"Atlanta",
    "sg:classifiers":[
        {
            "category":"Professional",
            "type":"Services"
        }
    ],
    "sg:phone":"+1 404 350 3499",
    "sg:postcode":"30318",
    "sg:province":"GA",
    "wof:name":"Starmotor Accessories",
    "wof:placetype":"venue"
},
  "geometry": {"coordinates":[-84.439378,33.814521],"type":"Point"}
}