{
  "type": "Feature",
  "properties": {
    "addr:full":"918 Donald Lee Hollowell Atlanta GA 30318",
    "addr:housenumber":"918",
    "addr:postcode":"30318",
    "addr:street":"Donald Lee",
    "iso:country":"US",
    "sg:address":"918 Donald Lee Hollowell",
    "sg:city":"Atlanta",
    "sg:classifiers":[
        {
            "category":"Restaurant",
            "type":"Food & Drink"
        }
    ],
    "sg:phone":"+1 404 873 0085",
    "sg:postcode":"30318",
    "sg:province":"GA",
    "wof:name":"Sisters Hot Wings",
    "wof:placetype":"venue"
},
  "geometry": {"coordinates":[-84.417644,33.773145],"type":"Point"}
}