{
  "type": "Feature",
  "properties": {
    "iso:country":"US",
    "sg:address":"3116 Shrine Rd",
    "sg:city":"Brunswick",
    "sg:classifiers":[
        {
            "category":"Health Services",
            "subcategory":"Doctor",
            "type":"Services"
        }
    ],
    "sg:phone":"+1 912 466 0777",
    "sg:postcode":"31520",
    "sg:province":"GA",
    "sg:tags":[
        "physician",
        "surgeon",
        "medical"
    ],
    "wof:name":"Shirley D Wilson DO",
    "wof:placetype":"venue"
},
  "geometry": {"coordinates":[-81.481827,31.175884],"type":"Point"}
}