{
  "type": "Feature",
  "properties": {
    "iso:country":"US",
    "sg:address":"1130 Lake Rutledge Rd",
    "sg:city":"Rutledge",
    "sg:classifiers":[
        {
            "category":"Farming",
            "subcategory":"Farm",
            "type":"Manufacturing & Wholesale Goods"
        }
    ],
    "sg:phone":"+1 706 557 2277",
    "sg:postcode":"30663",
    "sg:province":"GA",
    "sg:tags":[
        "crop",
        "general"
    ],
    "wof:name":"Breedlove Farms",
    "wof:placetype":"venue"
},
  "geometry": {"coordinates":[-83.59697,33.643739],"type":"Point"}
}