{
  "type": "Feature",
  "properties": {
    "iso:country":"US",
    "sg:address":"5975 Roswell Rd., Ste. D-237",
    "sg:city":"Sandy Springs",
    "sg:classifiers":[
        {
            "category":"Personal",
            "subcategory":"Barber",
            "type":"Services"
        }
    ],
    "sg:phone":"+1 404 256 4358",
    "sg:postcode":"30328",
    "sg:province":"GA",
    "sg:website":"www.theclubhousebarbers.com",
    "wof:name":"Clubhouse Barbers",
    "wof:placetype":"venue"
},
  "geometry": {"coordinates":[-84.37906,33.918216],"type":"Point"}
}