{
  "type": "Feature",
  "properties": {
    "iso:country":"US",
    "sg:address":"241 Broadway St",
    "sg:city":"Saint Simons Island",
    "sg:classifiers":[
        {
            "category":"Real Estate",
            "subcategory":"Real Estate Agent",
            "type":"Services"
        }
    ],
    "sg:phone":"+1 912 638 6586",
    "sg:postcode":"31522",
    "sg:province":"GA",
    "wof:name":"Sj Carmical Inc",
    "wof:placetype":"venue"
},
  "geometry": {"coordinates":[-81.3824,31.161432],"type":"Point"}
}