{
  "type": "Feature",
  "properties": {
    "iso:country":"US",
    "sg:address":"2830 Windy Hill Rd SE",
    "sg:city":"Marietta",
    "sg:classifiers":[
        {
            "category":"Restaurant",
            "type":"Food & Drink"
        }
    ],
    "sg:menulink":"http://www.allmenus.com/ga/northeast-cobb/14697-pappadeaux/menu/",
    "sg:phone":"+1 770 984 8899",
    "sg:postcode":"30067",
    "sg:province":"GA",
    "sg:tags":[
        "seafood",
        "cajun",
        "creole",
        "american"
    ],
    "wof:name":"Pappadeaux",
    "wof:placetype":"venue"
},
  "geometry": {"coordinates":[-84.47049800000001,33.903902],"type":"Point"}
}