{
  "type": "Feature",
  "properties": {
    "addr:full":"64 Howell St SE Atlanta GA 30312",
    "addr:housenumber":"64",
    "addr:postcode":"30312",
    "addr:street":"Howell St Se",
    "iso:country":"US",
    "sg:address":"64 Howell St SE",
    "sg:city":"Atlanta",
    "sg:classifiers":[
        {
            "category":"Real Estate",
            "subcategory":"Developer",
            "type":"Services"
        }
    ],
    "sg:phone":"+1 404 223 6068",
    "sg:postcode":"30312",
    "sg:province":"GA",
    "wof:name":"Aim Development LLC",
    "wof:placetype":"venue"
},
  "geometry": {"coordinates":[-84.36970700000001,33.752406],"type":"Point"}
}