{
  "type": "Feature",
  "properties": {
    "iso:country":"US",
    "sg:address":"2165 Cheshire Bridge Rd",
    "sg:city":"Atlanta",
    "sg:classifiers":[
        {
            "category":"Insurance",
            "subcategory":"Insurance Agent",
            "type":"Services"
        }
    ],
    "sg:phone":"+1 404 320 2020",
    "sg:postcode":"30324",
    "sg:province":"GA",
    "wof:name":"Acceptance Insurance Co",
    "wof:placetype":"venue"
},
  "geometry": {"coordinates":[-84.353528,33.813777],"type":"Point"}
}