{
  "type": "Feature",
  "properties": {
    "addr:full":"4262 New Jesup Hwy Brunswick GA 31520",
    "addr:housenumber":"4262",
    "addr:postcode":"31520",
    "addr:street":"New Jesup Hwy",
    "iso:country":"US",
    "sg:address":"4262 New Jesup Hwy",
    "sg:city":"Brunswick",
    "sg:classifiers":[
        {
            "category":"Manufacturing",
            "subcategory":"Retail Goods",
            "type":"Manufacturing & Wholesale Goods"
        }
    ],
    "sg:phone":"+1 912 265 0012",
    "sg:postcode":"31520",
    "sg:province":"GA",
    "sg:tags":[
        "assembly",
        "fabricating"
    ],
    "wof:name":"Bryd Custom Fabrication",
    "wof:placetype":"venue"
},
  "geometry": {"coordinates":[-81.51297,31.210712],"type":"Point"}
}