{
  "type": "Feature",
  "properties": {
    "addr:full":"505 Childers Rd Smithville GA 31787",
    "addr:housenumber":"505",
    "addr:postcode":"31787",
    "addr:street":"Childers Rd",
    "iso:country":"US",
    "sg:address":"505 Childers Rd",
    "sg:city":"Smithville",
    "sg:classifiers":[
        {
            "category":"Farming",
            "subcategory":"Farm",
            "type":"Manufacturing & Wholesale Goods"
        }
    ],
    "sg:phone":"+1 229 846 2298",
    "sg:postcode":"31787",
    "sg:province":"GA",
    "sg:tags":[
        "crop",
        "general"
    ],
    "wof:name":"Steve Childers",
    "wof:placetype":"venue"
},
  "geometry": {"coordinates":[-84.25313300000001,31.840067],"type":"Point"}
}