{
  "type": "Feature",
  "properties": {
    "addr:full":"534 Keith Dr Canton GA 30114",
    "addr:housenumber":"534",
    "addr:postcode":"30114",
    "addr:street":"Keith Dr",
    "iso:country":"US",
    "sg:address":"534 Keith Dr",
    "sg:city":"Canton",
    "sg:classifiers":[
        {
            "category":"Shopping",
            "type":"Retail Goods"
        },
        {
            "category":"Building & Trades",
            "subcategory":"Equipment Rental",
            "type":"Services"
        }
    ],
    "sg:phone":"+1 770 345 4429",
    "sg:postcode":"30114",
    "sg:province":"GA",
    "sg:tags":[
        "home",
        "medical",
        "health",
        "rent",
        "care"
    ],
    "wof:name":"B & G Medical Equipment",
    "wof:placetype":"venue"
},
  "geometry": {"coordinates":[-84.46227399999999,34.253395],"type":"Point"}
}