{
  "type": "Feature",
  "properties": {
    "addr:full":"4920 Roswell Rd Atlanta GA 30342",
    "addr:housenumber":"4920",
    "addr:postcode":"30342",
    "addr:street":"Roswell Rd",
    "iso:country":"US",
    "sg:address":"4920 Roswell Rd",
    "sg:city":"Atlanta",
    "sg:classifiers":[
        {
            "category":"Shopping",
            "subcategory":"Computers & Home Electronics",
            "type":"Retail Goods"
        },
        {
            "category":"Professional",
            "subcategory":"Computer Services",
            "type":"Services"
        }
    ],
    "sg:phone":"+1 404 705 8278",
    "sg:postcode":"30342",
    "sg:province":"GA",
    "sg:tags":[
        "system",
        "equipment",
        "dealer",
        "re"
    ],
    "sg:website":"www.frontech.com",
    "wof:name":"Frontech Computers",
    "wof:placetype":"venue"
},
  "geometry": {"coordinates":[-84.38143700000001,33.890116],"type":"Point"}
}