{
  "type": "Feature",
  "properties": {
    "iso:country":"US",
    "sg:address":"5823 Mulberry St",
    "sg:city":"Austell",
    "sg:classifiers":[
        {
            "category":"Local Transit",
            "type":"Transportation"
        }
    ],
    "sg:phone":"+1 770 745 4270",
    "sg:postcode":"30168",
    "sg:province":"GA",
    "sg:tags":[
        "passenger"
    ],
    "wof:name":"Timeline Ambulance Service",
    "wof:placetype":"venue"
},
  "geometry": {"coordinates":[-84.633307,33.81369],"type":"Point"}
}