{
  "type": "Feature",
  "properties": {
    "addr:full":"2101 Kennedy Dr Augusta GA 30904",
    "addr:housenumber":"2101",
    "addr:postcode":"30904",
    "addr:street":"Kennedy Dr",
    "iso:country":"US",
    "sg:address":"2101 Kennedy Dr",
    "sg:city":"Augusta",
    "sg:classifiers":[
        {
            "category":"Organizations",
            "subcategory":"Religious Organization",
            "type":"Services"
        }
    ],
    "sg:phone":"+1 706 731 0096",
    "sg:postcode":"30904",
    "sg:province":"GA",
    "sg:tags":[
        "church"
    ],
    "wof:name":"Augusta Deliverance Evnglstc",
    "wof:placetype":"venue"
},
  "geometry": {"coordinates":[-82.013931,33.450147],"type":"Point"}
}