{
  "type": "Feature",
  "properties": {
    "iso:country":"US",
    "sg:address":"4820 Hopewell Rd",
    "sg:city":"Cumming",
    "sg:classifiers":[
        {
            "category":"Manufacturing",
            "subcategory":"Glass & Minerals",
            "type":"Manufacturing & Wholesale Goods"
        }
    ],
    "sg:phone":"+1 770 889 6328",
    "sg:postcode":"30028",
    "sg:province":"GA",
    "sg:tags":[
        "concrete",
        "product",
        "mfg"
    ],
    "wof:name":"M&G Concrete Products Inc",
    "wof:placetype":"venue"
},
  "geometry": {"coordinates":[-84.085014,34.295809],"type":"Point"}
}