{
  "type": "Feature",
  "properties": {
    "addr:full":"5431 Trentham Dr Atlanta GA 30338",
    "addr:housenumber":"5431",
    "addr:postcode":"30338",
    "addr:street":"Trentham Dr",
    "iso:country":"US",
    "sg:address":"5431 Trentham Dr",
    "sg:city":"Atlanta",
    "sg:classifiers":[
        {
            "category":"Professional",
            "subcategory":"Computer Services",
            "type":"Services"
        }
    ],
    "sg:phone":"+1 404 406 4064",
    "sg:postcode":"30338",
    "sg:province":"GA",
    "sg:tags":[
        "programing",
        "custom"
    ],
    "wof:name":"Entrigue Systems Inc",
    "wof:placetype":"venue"
},
  "geometry": {"coordinates":[-84.30516,33.958824],"type":"Point"}
}