{
  "type": "Feature",
  "properties": {
    "iso:country":"US",
    "sg:address":"4199 N Goddard Rd",
    "sg:city":"Lithonia",
    "sg:classifiers":[
        {
            "category":"Building & Trades",
            "subcategory":"Construction",
            "type":"Services"
        }
    ],
    "sg:phone":"+1 770 987 9686",
    "sg:postcode":"30038",
    "sg:province":"GA",
    "sg:tags":[
        "excavation",
        "contractor"
    ],
    "wof:name":"Milford Grading",
    "wof:placetype":"venue"
},
  "geometry": {"coordinates":[-84.129902,33.661817],"type":"Point"}
}