{
  "type": "Feature",
  "properties": {
    "iso:country":"US",
    "sg:address":"12245 Asbury Park Dr",
    "sg:city":"Roswell",
    "sg:classifiers":[
        {
            "category":"Professional",
            "subcategory":"Management & Consulting",
            "type":"Services"
        }
    ],
    "sg:phone":"+1 770 664 1914",
    "sg:postcode":"30075",
    "sg:province":"GA",
    "sg:tags":[
        "public",
        "relations"
    ],
    "wof:name":"All Things Promotional",
    "wof:placetype":"venue"
},
  "geometry": {"coordinates":[-84.371438,34.080196],"type":"Point"}
}