{
  "type": "Feature",
  "properties": {
    "iso:country":"US",
    "sg:address":"3857 Rose Ln",
    "sg:city":"Augusta",
    "sg:classifiers":[
        {
            "category":"Shopping",
            "subcategory":"Gifts & Souvenirs",
            "type":"Retail Goods"
        },
        {
            "category":"Shopping",
            "subcategory":"Books",
            "type":"Retail Goods"
        }
    ],
    "sg:phone":"+1 706 863 1235",
    "sg:postcode":"30907",
    "sg:province":"GA",
    "sg:tags":[
        "shop",
        "religious",
        "miscellaneous",
        "store"
    ],
    "sg:website":"http://www.saintlygifts.com",
    "wof:name":"Saintly Gifts",
    "wof:placetype":"venue"
},
  "geometry": {"coordinates":[-82.091455,33.509852],"type":"Point"}
}