{
  "type": "Feature",
  "properties": {
    "iso:country":"US",
    "sg:address":"673 Lane Rd",
    "sg:city":"Monticello",
    "sg:classifiers":[
        {
            "category":"Shopping",
            "subcategory":"Bicycles & Sporting Goods",
            "type":"Retail Goods"
        }
    ],
    "sg:phone":"+1 706 468 1453",
    "sg:postcode":"31064",
    "sg:province":"GA",
    "wof:name":"Sutton Gun Shop",
    "wof:placetype":"venue"
},
  "geometry": {"coordinates":[-83.78903699999999,33.274179],"type":"Point"}
}