{
  "type": "Feature",
  "properties": {
    "iso:country":"US",
    "sg:address":"976 Gazin Pl",
    "sg:city":"Stone Mountain",
    "sg:classifiers":[
        {
            "category":"Retail",
            "subcategory":"Auto Repair",
            "type":"Services"
        }
    ],
    "sg:phone":"+1 404 297 9010",
    "sg:postcode":"30083",
    "sg:province":"GA",
    "sg:tags":[
        "automotive"
    ],
    "wof:name":"Hall Towing Services",
    "wof:placetype":"venue"
},
  "geometry": {"coordinates":[-84.197041,33.766703],"type":"Point"}
}