{
  "type": "Feature",
  "properties": {
    "addr:full":"1500 Mayo Dr Bainbridge GA 39817",
    "addr:housenumber":"1500",
    "addr:postcode":"39817",
    "addr:street":"Mayo Dr",
    "iso:country":"US",
    "sg:address":"1500 Mayo Dr",
    "sg:city":"Bainbridge",
    "sg:classifiers":[
        {
            "category":"Professional",
            "type":"Services"
        }
    ],
    "sg:phone":"+1 229 246 4260",
    "sg:postcode":"39817",
    "sg:province":"GA",
    "wof:name":"Curt Hatcher",
    "wof:placetype":"venue"
},
  "geometry": {"coordinates":[-84.59577899999999,30.92144],"type":"Point"}
}