{
  "type": "Feature",
  "properties": {
    "iso:country":"US",
    "sg:address":"6140 Northbelt Pkwy",
    "sg:city":"Norcross",
    "sg:classifiers":[
        {
            "category":"Real Estate",
            "subcategory":"Surveying",
            "type":"Services"
        }
    ],
    "sg:phone":"+1 770 849 9604",
    "sg:postcode":"30071",
    "sg:province":"GA",
    "sg:tags":[
        "instrument"
    ],
    "wof:name":"Dudley Earl Associates Inc",
    "wof:placetype":"venue"
},
  "geometry": {"coordinates":[-84.21440800000001,33.925186],"type":"Point"}
}