{
  "type": "Feature",
  "properties": {
    "addr:full":"2500 Pleasant Hill Rd SW Atlanta GA 30349",
    "addr:housenumber":"2500",
    "addr:postcode":"30349",
    "addr:street":"Pleasant Hill Rd Sw",
    "iso:country":"US",
    "sg:address":"2500 Pleasant Hill Rd SW",
    "sg:city":"Atlanta",
    "sg:classifiers":[
        {
            "category":"Professional",
            "subcategory":"Business Services",
            "type":"Services"
        }
    ],
    "sg:phone":"+1 404 767 3253",
    "sg:postcode":"30349",
    "sg:province":"GA",
    "sg:tags":[
        "production",
        "music"
    ],
    "wof:name":"Warner Promotions",
    "wof:placetype":"venue"
},
  "geometry": {"coordinates":[-84.468391,33.600034],"type":"Point"}
}