{
  "type": "Feature",
  "properties": {
    "iso:country":"US",
    "sg:address":"907 Hillcrest Pkwy",
    "sg:city":"Dublin",
    "sg:classifiers":[
        {
            "category":"Personal",
            "subcategory":"Tanning Parlor",
            "type":"Services"
        }
    ],
    "sg:phone":"+1 478 296 2005",
    "sg:postcode":"31021",
    "sg:province":"GA",
    "sg:tags":[
        "salon"
    ],
    "wof:name":"Safari Quick Tan",
    "wof:placetype":"venue"
},
  "geometry": {"coordinates":[-82.926213,32.549298],"type":"Point"}
}