{
  "type": "Feature",
  "properties": {
    "addr:full":"2807 Heather Row Ridge SW Lilburn GA 30047",
    "addr:housenumber":"2807",
    "addr:postcode":"30047",
    "addr:street":"Heather Row Ridge Sw",
    "iso:country":"US",
    "sg:address":"2807 Heather Row Ridge SW",
    "sg:city":"Lilburn",
    "sg:classifiers":[
        {
            "category":"Professional",
            "subcategory":"Business Services",
            "type":"Services"
        }
    ],
    "sg:phone":"+1 678 858 3149",
    "sg:postcode":"30047",
    "sg:province":"GA",
    "wof:name":"Aqua V Home Inspection",
    "wof:placetype":"venue"
},
  "geometry": {"coordinates":[-84.07893799999999,33.81172],"type":"Point"}
}