{
  "type": "Feature",
  "properties": {
    "iso:country":"US",
    "sg:address":"4726 State Rte 65",
    "sg:city":"Pelham",
    "sg:classifiers":[
        {
            "category":"Professional",
            "type":"Services"
        }
    ],
    "sg:phone":"+1 229 294 9401",
    "sg:postcode":"31779",
    "sg:province":"GA",
    "wof:name":"Justice/Ronald",
    "wof:placetype":"venue"
},
  "geometry": {"coordinates":[-84.193532,31.129035],"type":"Point"}
}