{
  "type": "Feature",
  "properties": {
    "addr:full":"930 Linkside Ter Alpharetta GA 30005",
    "addr:housenumber":"930",
    "addr:postcode":"30005",
    "addr:street":"Linkside Ter",
    "iso:country":"US",
    "sg:address":"930 Linkside Ter",
    "sg:city":"Alpharetta",
    "sg:classifiers":[
        {
            "category":"Professional",
            "subcategory":"Lawyer & Legal Services",
            "type":"Services"
        }
    ],
    "sg:phone":"+1 770 777 7640",
    "sg:postcode":"30005",
    "sg:province":"GA",
    "sg:tags":[
        "attorney"
    ],
    "wof:name":"Stephanie F Goff",
    "wof:placetype":"venue"
},
  "geometry": {"coordinates":[-84.20703899999999,34.086118],"type":"Point"}
}