{
  "type": "Feature",
  "properties": {
    "iso:country":"US",
    "sg:address":"1780 Huntington Hill Trce NE",
    "sg:city":"Buford",
    "sg:classifiers":[
        {
            "category":"Communications",
            "type":"Services"
        }
    ],
    "sg:phone":"+1 770 316 1148",
    "sg:postcode":"30519",
    "sg:province":"GA",
    "wof:name":"A Plus Communications",
    "wof:placetype":"venue"
},
  "geometry": {"coordinates":[-83.886684,34.064373],"type":"Point"}
}