{
  "type": "Feature",
  "properties": {
    "addr:full":"4175 Ruby Forest Blvd Suwanee GA 30024",
    "addr:housenumber":"4175",
    "addr:postcode":"30024",
    "addr:street":"Ruby Forest Blvd",
    "iso:country":"US",
    "sg:address":"4175 Ruby Forest Blvd",
    "sg:city":"Suwanee",
    "sg:classifiers":[
        {
            "category":"Organizations",
            "subcategory":"Professional Association",
            "type":"Services"
        }
    ],
    "sg:phone":"+1 770 271 3484",
    "sg:postcode":"30024",
    "sg:province":"GA",
    "wof:name":"Ruby Forest Homeowners Assn",
    "wof:placetype":"venue"
},
  "geometry": {"coordinates":[-84.04671999999999,34.068336],"type":"Point"}
}