{
  "type": "Feature",
  "properties": {
    "addr:full":"2189 State Rte 114 Summerville GA 30747",
    "addr:housenumber":"2189",
    "addr:postcode":"30747",
    "addr:street":"State Rte 114",
    "iso:country":"US",
    "sg:address":"2189 State Rte 114",
    "sg:city":"Summerville",
    "sg:classifiers":[
        {
            "category":"Shopping",
            "type":"Retail Goods"
        }
    ],
    "sg:phone":"+1 706 857 8062",
    "sg:postcode":"30747",
    "sg:province":"GA",
    "sg:tags":[
        "monument"
    ],
    "wof:name":"Ellenburg Monument Co",
    "wof:placetype":"venue"
},
  "geometry": {"coordinates":[-85.375423,34.449152],"type":"Point"}
}