{
  "type": "Feature",
  "properties": {
    "iso:country":"US",
    "sg:address":"184 Cedarcrest Dr",
    "sg:city":"Acworth",
    "sg:classifiers":[
        {
            "category":"Professional",
            "subcategory":"Business Services",
            "type":"Services"
        }
    ],
    "sg:phone":"+1 678 574 4551",
    "sg:postcode":"30101",
    "sg:province":"GA",
    "wof:name":"Bracelets By Design",
    "wof:placetype":"venue"
},
  "geometry": {"coordinates":[-84.740359,34.055149],"type":"Point"}
}