{
  "type": "Feature",
  "properties": {
    "addr:full":"6300 Boat Rock Blvd SW Atlanta GA 30336",
    "addr:housenumber":"6300",
    "addr:postcode":"30336",
    "addr:street":"Boat Rock Blvd Sw",
    "iso:country":"US",
    "sg:address":"6300 Boat Rock Blvd SW",
    "sg:city":"Atlanta",
    "sg:classifiers":[
        {
            "category":"Wholesale",
            "subcategory":"Machinery & Supplies",
            "type":"Manufacturing & Wholesale Goods"
        }
    ],
    "sg:phone":"+1 404 349 0756",
    "sg:postcode":"30336",
    "sg:province":"GA",
    "sg:tags":[
        "salon",
        "beauty"
    ],
    "wof:name":"Alberto-CULVER USA",
    "wof:placetype":"venue"
},
  "geometry": {"coordinates":[-84.596082,33.710823],"type":"Point"}
}