{
  "type": "Feature",
  "properties": {
    "addr:full":"914 E Robert Toombs Ave Washington GA 30673",
    "addr:housenumber":"914",
    "addr:postcode":"30673",
    "addr:street":"E Robert Toombs Ave",
    "iso:country":"US",
    "sg:address":"914 E Robert Toombs Ave",
    "sg:city":"Washington",
    "sg:classifiers":[
        {
            "category":"Retail",
            "subcategory":"Auto Repair",
            "type":"Services"
        }
    ],
    "sg:phone":"+1 706 678 2842",
    "sg:postcode":"30673",
    "sg:province":"GA",
    "sg:tags":[
        "automotive",
        "general"
    ],
    "wof:name":"Ansley Garage Inc",
    "wof:placetype":"venue"
},
  "geometry": {"coordinates":[-82.719433,33.728854],"type":"Point"}
}