{
  "type": "Feature",
  "properties": {
    "addr:full":"884 Bramlett Shoals Rd Lawrenceville GA 30045",
    "addr:housenumber":"884",
    "addr:postcode":"30045",
    "addr:street":"Bramlett Shoals Rd",
    "iso:country":"US",
    "sg:address":"884 Bramlett Shoals Rd",
    "sg:city":"Lawrenceville",
    "sg:classifiers":[
        {
            "category":"Wholesale",
            "subcategory":"Machinery & Supplies",
            "type":"Manufacturing & Wholesale Goods"
        }
    ],
    "sg:phone":"+1 770 963 9805",
    "sg:postcode":"30045",
    "sg:province":"GA",
    "sg:tags":[
        "equipment"
    ],
    "wof:name":"Kirkland Co",
    "wof:placetype":"venue"
},
  "geometry": {"coordinates":[-83.92589099999999,33.956451],"type":"Point"}
}