{
  "type": "Feature",
  "properties": {
    "addr:full":"614 Thornton Rd Lithia Springs GA 30122",
    "addr:housenumber":"614",
    "addr:postcode":"30122",
    "addr:street":"Thornton Rd",
    "iso:country":"US",
    "sg:address":"614 Thornton Rd",
    "sg:city":"Lithia Springs",
    "sg:classifiers":[
        {
            "category":"Utilities",
            "subcategory":"Mobile Phone",
            "type":"Services"
        }
    ],
    "sg:phone":"+1 770 739 7550",
    "sg:postcode":"30122",
    "sg:province":"GA",
    "sg:tags":[
        "telephone",
        "cellular"
    ],
    "wof:name":"Verizon Wireless",
    "wof:placetype":"venue"
},
  "geometry": {"coordinates":[-84.62239,33.789166],"type":"Point"}
}