{
  "type": "Feature",
  "properties": {
    "iso:country":"US",
    "sg:address":"231 Bankhead Hwy",
    "sg:city":"Carrollton",
    "sg:classifiers":[
        {
            "category":"Professional",
            "subcategory":"Lawyer & Legal Services",
            "type":"Services"
        }
    ],
    "sg:phone":"+1 770 832 6335",
    "sg:postcode":"30117",
    "sg:province":"GA",
    "sg:tags":[
        "attorney"
    ],
    "wof:name":"Hardegree Law Firm",
    "wof:placetype":"venue"
},
  "geometry": {"coordinates":[-85.06260399999999,33.58172],"type":"Point"}
}