{
  "type": "Feature",
  "properties": {
    "iso:country":"US",
    "sg:address":"5772 Shadburn Ferry Rd",
    "sg:city":"Buford",
    "sg:classifiers":[
        {
            "category":"Autos & Motor Vehicles",
            "subcategory":"Boat Sales",
            "type":"Retail Goods"
        }
    ],
    "sg:phone":"+1 770 932 2628",
    "sg:postcode":"30518",
    "sg:province":"GA",
    "sg:tags":[
        "dealer",
        "sales"
    ],
    "wof:name":"All About Boats",
    "wof:placetype":"venue"
},
  "geometry": {"coordinates":[-84.011574,34.145675],"type":"Point"}
}