{
  "type": "Feature",
  "properties": {
    "addr:full":"1301 E Gordon Ave Albany GA 31705",
    "addr:housenumber":"1301",
    "addr:postcode":"31705",
    "addr:street":"E Gordon Ave",
    "iso:country":"US",
    "sg:address":"1301 E Gordon Ave",
    "sg:city":"Albany",
    "sg:classifiers":[
        {
            "category":"Wholesale",
            "subcategory":"Scrap",
            "type":"Manufacturing & Wholesale Goods"
        }
    ],
    "sg:phone":"+1 229 432 6255",
    "sg:postcode":"31705",
    "sg:province":"GA",
    "sg:tags":[
        "recycling",
        "center"
    ],
    "wof:name":"Albany Recycling Svc Inc",
    "wof:placetype":"venue"
},
  "geometry": {"coordinates":[-84.117684,31.569284],"type":"Point"}
}