{
  "type": "Feature",
  "properties": {
    "addr:full":"11164 State Bridge Rd Alpharetta GA 30022",
    "addr:housenumber":"11164",
    "addr:postcode":"30022",
    "addr:street":"State Bridge Rd",
    "iso:country":"US",
    "sg:address":"11164 State Bridge Rd",
    "sg:city":"Alpharetta",
    "sg:classifiers":[
        {
            "category":"Personal",
            "subcategory":"Nail Salon",
            "type":"Services"
        }
    ],
    "sg:phone":"+1 770 619 3414",
    "sg:postcode":"30022",
    "sg:province":"GA",
    "wof:name":"Nails Tips and Toes",
    "wof:placetype":"venue"
},
  "geometry": {"coordinates":[-84.228844,34.052808],"type":"Point"}
}