{
  "type": "Feature",
  "properties": {
    "addr:full":"80 Trelawney Cir Covington GA 30016",
    "addr:housenumber":"80",
    "addr:postcode":"30016",
    "addr:street":"Trelawney Cir",
    "iso:country":"US",
    "sg:address":"80 Trelawney Cir",
    "sg:city":"Covington",
    "sg:classifiers":[
        {
            "category":"Social Services",
            "type":"Services"
        }
    ],
    "sg:phone":"+1 770 787 2508",
    "sg:postcode":"30016",
    "sg:province":"GA",
    "sg:tags":[
        "substance",
        "education",
        "treatment",
        "abuse"
    ],
    "wof:name":"White and Associates",
    "wof:placetype":"venue"
},
  "geometry": {"coordinates":[-83.922045,33.577442],"type":"Point"}
}