{
  "type": "Feature",
  "properties": {
    "iso:country":"US",
    "sg:address":"4070 Casa Verde Dr",
    "sg:city":"Atlanta",
    "sg:classifiers":[
        {
            "category":"Retail",
            "subcategory":"Repair Shop",
            "type":"Services"
        },
        {
            "category":"Building & Trades",
            "subcategory":"Construction",
            "type":"Services"
        }
    ],
    "sg:phone":"+1 404 287 2707",
    "sg:postcode":"30349",
    "sg:province":"GA",
    "sg:tags":[
        "specialty",
        "handyman",
        "appliance",
        "heating",
        "system",
        "small",
        "contractor",
        "air conditioning"
    ],
    "sg:website":"http://www.rrhvachomerepair.com",
    "wof:name":"R&R HVAC & Home Repair",
    "wof:placetype":"venue"
},
  "geometry": {"coordinates":[-84.53137599999999,33.643964],"type":"Point"}
}