{
  "type": "Feature",
  "properties": {
    "addr:full":"3473 Old Norcross Rd #308 Duluth GA 30096",
    "addr:housenumber":"3473",
    "addr:postcode":"30096",
    "addr:street":"Old Norcross Rd # 308",
    "iso:country":"US",
    "sg:address":"3473 Old Norcross Rd #308",
    "sg:city":"Duluth",
    "sg:classifiers":[
        {
            "category":"Restaurant",
            "type":"Food & Drink"
        }
    ],
    "sg:phone":"+1 770 495 9997",
    "sg:postcode":"30096",
    "sg:province":"GA",
    "sg:tags":[
        "japanese"
    ],
    "wof:name":"Naru Japanese Restaurant",
    "wof:placetype":"venue"
},
  "geometry": {"coordinates":[-84.133983,33.965675],"type":"Point"}
}