{
  "type": "Feature",
  "properties": {
    "iso:country":"US",
    "sg:address":"235 Plantation Glen Ct",
    "sg:city":"Alpharetta",
    "sg:classifiers":[
        {
            "category":"Shopping",
            "subcategory":"Clothing, Apparel, & Fashions",
            "type":"Retail Goods"
        }
    ],
    "sg:phone":"+1 770 663 8871",
    "sg:postcode":"30022",
    "sg:province":"GA",
    "wof:name":"Cfranc Enterprises",
    "wof:placetype":"venue"
},
  "geometry": {"coordinates":[-84.245374,34.034249],"type":"Point"}
}