{
  "type": "Feature",
  "properties": {
    "iso:country":"US",
    "sg:address":"25 White St",
    "sg:city":"Homerville",
    "sg:classifiers":[
        {
            "category":"Manufacturing",
            "subcategory":"Lumber",
            "type":"Manufacturing & Wholesale Goods"
        }
    ],
    "sg:phone":"+1 912 487 2102",
    "sg:postcode":"31634",
    "sg:province":"GA",
    "sg:tags":[
        "logging"
    ],
    "wof:name":"Delk Post Company",
    "wof:placetype":"venue"
},
  "geometry": {"coordinates":[-82.76043799999999,31.048318],"type":"Point"}
}