{
  "type": "Feature",
  "properties": {
    "addr:full":"593 S Main St Moultrie GA 31768",
    "addr:housenumber":"593",
    "addr:postcode":"31768",
    "addr:street":"S Main St",
    "iso:country":"US",
    "sg:address":"593 S Main St",
    "sg:city":"Moultrie",
    "sg:classifiers":[
        {
            "category":"Insurance",
            "subcategory":"Insurance Agent",
            "type":"Services"
        }
    ],
    "sg:phone":"+1 229 985 1415",
    "sg:postcode":"31768",
    "sg:province":"GA",
    "wof:name":"BIC Insurance & Investments",
    "wof:placetype":"venue"
},
  "geometry": {"coordinates":[-83.78884600000001,31.173965],"type":"Point"}
}