{
  "type": "Feature",
  "properties": {
    "iso:country":"US",
    "sg:address":"140 Broadmeadow Cv",
    "sg:city":"Roswell",
    "sg:classifiers":[
        {
            "category":"Professional",
            "subcategory":"Computer Services",
            "type":"Services"
        }
    ],
    "sg:phone":"+1 770 587 2330",
    "sg:postcode":"30075",
    "sg:province":"GA",
    "sg:tags":[
        "repair"
    ],
    "wof:name":"Data Service Consultants",
    "wof:placetype":"venue"
},
  "geometry": {"coordinates":[-84.372299,34.0368],"type":"Point"}
}