{
  "type": "Feature",
  "properties": {
    "iso:country":"US",
    "sg:address":"4081 Lakeland Hills Dr",
    "sg:city":"Douglasville",
    "sg:classifiers":[
        {
            "category":"Professional",
            "subcategory":"Business Services",
            "type":"Services"
        }
    ],
    "sg:phone":"+1 770 949 7186",
    "sg:postcode":"30134",
    "sg:province":"GA",
    "wof:name":"Jme Enterprises Inc",
    "wof:placetype":"venue"
},
  "geometry": {"coordinates":[-84.706819,33.766279],"type":"Point"}
}