{
  "type": "Feature",
  "properties": {
    "iso:country":"US",
    "sg:address":"1841 W Oak Pkwy",
    "sg:city":"Marietta",
    "sg:classifiers":[
        {
            "category":"Education",
            "subcategory":"School",
            "type":"Public Place"
        }
    ],
    "sg:phone":"+1 770 427 9456",
    "sg:postcode":"30062",
    "sg:province":"GA",
    "wof:name":"Hygeia Laboratories Inc",
    "wof:placetype":"venue"
},
  "geometry": {"coordinates":[-84.52484200000001,33.989379],"type":"Point"}
}