{
  "type": "Feature",
  "properties": {
    "iso:country":"US",
    "sg:address":"2121 Martin Luther King Jr Dr",
    "sg:city":"Albany",
    "sg:classifiers":[
        {
            "category":"Health Services",
            "subcategory":"Nursing And Care Facility",
            "type":"Services"
        }
    ],
    "sg:phone":"+1 229 888 0682",
    "sg:postcode":"31701",
    "sg:province":"GA",
    "sg:tags":[
        "personal",
        "home"
    ],
    "wof:name":"Pines Personal Care Home",
    "wof:placetype":"venue"
},
  "geometry": {"coordinates":[-84.155286,31.547372],"type":"Point"}
}