{
  "type": "Feature",
  "properties": {
    "addr:full":"2551 Huntington Dr Macon GA 31204",
    "addr:housenumber":"2551",
    "addr:postcode":"31204",
    "addr:street":"Huntington Dr",
    "iso:country":"US",
    "sg:address":"2551 Huntington Dr",
    "sg:city":"Macon",
    "sg:classifiers":[
        {
            "category":"Professional",
            "subcategory":"Business Services",
            "type":"Services"
        }
    ],
    "sg:phone":"+1 478 743 9591",
    "sg:postcode":"31204",
    "sg:province":"GA",
    "sg:tags":[
        "technical",
        "support",
        "logistic"
    ],
    "wof:name":"Technical Logistic Solutions",
    "wof:placetype":"venue"
},
  "geometry": {"coordinates":[-83.658885,32.872357],"type":"Point"}
}