{
  "type": "Feature",
  "properties": {
    "addr:full":"214 10th St Ste A Columbus GA 31901",
    "addr:housenumber":"214",
    "addr:postcode":"31901",
    "addr:street":"10Th St Ste A",
    "iso:country":"US",
    "sg:address":"214 10th St Ste A",
    "sg:city":"Columbus",
    "sg:classifiers":[
        {
            "category":"Manufacturing",
            "subcategory":"Printing",
            "type":"Manufacturing & Wholesale Goods"
        }
    ],
    "sg:phone":"+1 706 324 6214",
    "sg:postcode":"31901",
    "sg:province":"GA",
    "sg:tags":[
        "magazines-distributors"
    ],
    "wof:name":"Chicken Dinner News Inc",
    "wof:placetype":"venue"
},
  "geometry": {"coordinates":[-84.99021,32.464792],"type":"Point"}
}