{
  "type": "Feature",
  "properties": {
    "iso:country":"US",
    "sg:address":"1917 Happy Valley Rd",
    "sg:city":"Rossville",
    "sg:classifiers":[
        {
            "category":"Organizations",
            "subcategory":"Religious Organization",
            "type":"Services"
        }
    ],
    "sg:phone":"+1 706 861 9227",
    "sg:postcode":"30741",
    "sg:province":"GA",
    "sg:tags":[
        "church"
    ],
    "wof:name":"Full Gospel Christian Church",
    "wof:placetype":"venue"
},
  "geometry": {"coordinates":[-85.30976099999999,34.957181],"type":"Point"}
}