{
  "type": "Feature",
  "properties": {
    "iso:country":"US",
    "sg:address":"377 Watson Bay",
    "sg:city":"Stone Mountain",
    "sg:classifiers":[
        {
            "category":"Building & Trades",
            "subcategory":"Construction",
            "type":"Services"
        }
    ],
    "sg:phone":"+1 770 469 9997",
    "sg:postcode":"30087",
    "sg:province":"GA",
    "sg:tags":[
        "house"
    ],
    "wof:name":"F & M Construction Services",
    "wof:placetype":"venue"
},
  "geometry": {"coordinates":[-84.085303,33.777967],"type":"Point"}
}