{
  "type": "Feature",
  "properties": {
    "iso:country":"US",
    "sg:address":"679 Birchwood Ln",
    "sg:city":"Marietta",
    "sg:classifiers":[
        {
            "category":"Professional",
            "subcategory":"Accounting & Tax Preparation",
            "type":"Services"
        }
    ],
    "sg:phone":"+1 770 438 2147",
    "sg:postcode":"30060",
    "sg:province":"GA",
    "wof:name":"Player Charles CPA Ea",
    "wof:placetype":"venue"
},
  "geometry": {"coordinates":[-84.57467,33.888615],"type":"Point"}
}