{
  "type": "Feature",
  "properties": {
    "addr:full":"3954 Whittington Dr NE Atlanta GA 30342",
    "addr:housenumber":"3954",
    "addr:postcode":"30342",
    "addr:street":"Whittington Dr Ne",
    "iso:country":"US",
    "sg:address":"3954 Whittington Dr NE",
    "sg:city":"Atlanta",
    "sg:classifiers":[
        {
            "category":"Professional",
            "subcategory":"Business Services",
            "type":"Services"
        }
    ],
    "sg:phone":"+1 404 261 7356",
    "sg:postcode":"30342",
    "sg:province":"GA",
    "wof:name":"Brighton Associates Inc",
    "wof:placetype":"venue"
},
  "geometry": {"coordinates":[-84.372269,33.864211],"type":"Point"}
}