{
  "type": "Feature",
  "properties": {
    "addr:full":"5671 State Rte 122 Hahira GA 31632",
    "addr:housenumber":"5671",
    "addr:postcode":"31632",
    "addr:street":"State Rte 122",
    "iso:country":"US",
    "sg:address":"5671 State Rte 122",
    "sg:city":"Hahira",
    "sg:classifiers":[
        {
            "category":"Organizations",
            "subcategory":"Professional Association",
            "type":"Services"
        }
    ],
    "sg:phone":"+1 229 794 2606",
    "sg:postcode":"31632",
    "sg:province":"GA",
    "wof:name":"Georgia Sheriff's Boys Ranch",
    "wof:placetype":"venue"
},
  "geometry": {"coordinates":[-83.277012,31.021617],"type":"Point"}
}