{
  "type": "Feature",
  "properties": {
    "addr:full":"20 Quail Trl Carrollton GA 30116",
    "addr:housenumber":"20",
    "addr:postcode":"30116",
    "addr:street":"Quail Trl",
    "iso:country":"US",
    "sg:address":"20 Quail Trl",
    "sg:city":"Carrollton",
    "sg:classifiers":[
        {
            "category":"Building & Trades",
            "subcategory":"Construction",
            "type":"Services"
        }
    ],
    "sg:phone":"+1 770 214 0368",
    "sg:postcode":"30116",
    "sg:province":"GA",
    "sg:tags":[
        "general",
        "contractor"
    ],
    "wof:name":"HMT Enterprises",
    "wof:placetype":"venue"
},
  "geometry": {"coordinates":[-85.031756,33.622657],"type":"Point"}
}