{
  "type": "Feature",
  "properties": {
    "addr:full":"79 W Paces Ferry Rd NW Atlanta GA 30305",
    "addr:housenumber":"79",
    "addr:postcode":"30305",
    "addr:street":"W Paces Ferry Rd Nw",
    "iso:country":"US",
    "sg:address":"79 W Paces Ferry Rd NW",
    "sg:city":"Atlanta",
    "sg:classifiers":[
        {
            "category":"Shopping",
            "subcategory":"Party Supplies",
            "type":"Retail Goods"
        },
        {
            "category":"Shopping",
            "subcategory":"Bridal",
            "type":"Retail Goods"
        }
    ],
    "sg:phone":"+1 404 873 8070",
    "sg:postcode":"30305",
    "sg:province":"GA",
    "sg:tags":[
        "shop",
        "wedding"
    ],
    "wof:name":"Anne Barge",
    "wof:placetype":"venue"
},
  "geometry": {"coordinates":[-84.382217,33.840408],"type":"Point"}
}