{
  "type": "Feature",
  "properties": {
    "addr:full":"1459 Montreal Rd Tucker GA 30084",
    "addr:housenumber":"1459",
    "addr:postcode":"30084",
    "addr:street":"Montreal Rd",
    "iso:country":"US",
    "sg:address":"1459 Montreal Rd",
    "sg:city":"Tucker",
    "sg:classifiers":[
        {
            "category":"Real Estate",
            "subcategory":"Real Estate Agent",
            "type":"Services"
        }
    ],
    "sg:phone":"+1 770 908 0300",
    "sg:postcode":"30084",
    "sg:province":"GA",
    "wof:name":"Lincoln Property Co",
    "wof:placetype":"venue"
},
  "geometry": {"coordinates":[-84.250086,33.826311],"type":"Point"}
}