{
  "type": "Feature",
  "properties": {
    "iso:country":"US",
    "sg:address":"3020 W Potomac Dr",
    "sg:city":"Atlanta",
    "sg:classifiers":[
        {
            "category":"Building & Trades",
            "subcategory":"Landscaping Services",
            "type":"Services"
        }
    ],
    "sg:phone":"+1 404 766 4459",
    "sg:postcode":"30344",
    "sg:province":"GA",
    "sg:tags":[
        "landscape",
        "contractor"
    ],
    "wof:name":"Ace Contracting Services",
    "wof:placetype":"venue"
},
  "geometry": {"coordinates":[-84.487724,33.656932],"type":"Point"}
}