{
  "type": "Feature",
  "properties": {
    "iso:country":"US",
    "sg:address":"3689 Waterford Pl",
    "sg:city":"Clarkston",
    "sg:classifiers":[
        {
            "category":"Professional",
            "subcategory":"Lawyer & Legal Services",
            "type":"Services"
        }
    ],
    "sg:phone":"+1 404 298 8771",
    "sg:postcode":"30021",
    "sg:province":"GA",
    "sg:tags":[
        "attorney"
    ],
    "wof:name":"Tamara Rorie Law Office PC",
    "wof:placetype":"venue"
},
  "geometry": {"coordinates":[-84.23719699999999,33.817396],"type":"Point"}
}