{
  "type": "Feature",
  "properties": {
    "addr:full":"64 Perimeter Center Pkwy NE Atlanta GA 30346",
    "addr:housenumber":"64",
    "addr:postcode":"30346",
    "addr:street":"Perimeter Center Pkwy Ne",
    "iso:country":"US",
    "sg:address":"64 Perimeter Center Pkwy NE",
    "sg:city":"Atlanta",
    "sg:classifiers":[
        {
            "category":"Banks & Credit Unions",
            "subcategory":"Bank",
            "type":"Services"
        }
    ],
    "sg:phone":"+1 678 281 6100",
    "sg:postcode":"30346",
    "sg:province":"GA",
    "sg:tags":[
        "broker",
        "mortgage"
    ],
    "wof:name":"Lenox Financial Mortgage Corp",
    "wof:placetype":"venue"
},
  "geometry": {"coordinates":[-84.345259,33.924579],"type":"Point"}
}