{
  "type": "Feature",
  "properties": {
    "addr:full":"3602 Buena Vista Rd Columbus GA 31906",
    "addr:housenumber":"3602",
    "addr:postcode":"31906",
    "addr:street":"Buena Vista Rd",
    "iso:country":"US",
    "sg:address":"3602 Buena Vista Rd",
    "sg:city":"Columbus",
    "sg:classifiers":[
        {
            "category":"Professional",
            "subcategory":"Accounting & Tax Preparation",
            "type":"Services"
        }
    ],
    "sg:phone":"+1 706 568 8453",
    "sg:postcode":"31906",
    "sg:province":"GA",
    "sg:tags":[
        "return"
    ],
    "wof:name":"Fort Valley Fast Tax",
    "wof:placetype":"venue"
},
  "geometry": {"coordinates":[-84.93409800000001,32.459436],"type":"Point"}
}