{
  "type": "Feature",
  "properties": {
    "iso:country":"US",
    "sg:address":"625 Andover Dr NW",
    "sg:city":"Atlanta",
    "sg:classifiers":[
        {
            "category":"Real Estate",
            "subcategory":"Real Estate Agent",
            "type":"Services"
        }
    ],
    "sg:phone":"+1 404 364 0159",
    "sg:postcode":"30327",
    "sg:province":"GA",
    "wof:name":"Ppop LLC",
    "wof:placetype":"venue"
},
  "geometry": {"coordinates":[-84.40928700000001,33.864209],"type":"Point"}
}