{
  "type": "Feature",
  "properties": {
    "addr:full":"974 Kingwood Rd Douglas GA 31533",
    "addr:housenumber":"974",
    "addr:postcode":"31533",
    "addr:street":"Kingwood Rd",
    "iso:country":"US",
    "sg:address":"974 Kingwood Rd",
    "sg:city":"Douglas",
    "sg:classifiers":[
        {
            "category":"Organizations",
            "subcategory":"Religious Organization",
            "type":"Services"
        }
    ],
    "sg:phone":"+1 912 384 3473",
    "sg:postcode":"31533",
    "sg:province":"GA",
    "wof:name":"JV McElhaney Ministries Inc",
    "wof:placetype":"venue"
},
  "geometry": {"coordinates":[-82.901633,31.574533],"type":"Point"}
}