{
  "type": "Feature",
  "properties": {
    "addr:full":"5150 Piney Grove Dr Cumming GA 30040",
    "addr:housenumber":"5150",
    "addr:postcode":"30040",
    "addr:street":"Piney Grove Dr",
    "iso:country":"US",
    "sg:address":"5150 Piney Grove Dr",
    "sg:city":"Cumming",
    "sg:classifiers":[
        {
            "category":"Home & Garden",
            "subcategory":"Home Furnishings",
            "type":"Retail Goods"
        }
    ],
    "sg:phone":"+1 770 886 9260",
    "sg:postcode":"30040",
    "sg:province":"GA",
    "wof:name":"Distinctive Environments",
    "wof:placetype":"venue"
},
  "geometry": {"coordinates":[-84.174414,34.188345],"type":"Point"}
}