{
  "type": "Feature",
  "properties": {
    "iso:country":"US",
    "sg:address":"5955 Shiloh Rd",
    "sg:city":"Alpharetta",
    "sg:classifiers":[
        {
            "category":"Manufacturing",
            "subcategory":"Rubber & Plastics",
            "type":"Manufacturing & Wholesale Goods"
        }
    ],
    "sg:phone":"+1 678 513 6778",
    "sg:postcode":"30005",
    "sg:province":"GA",
    "sg:tags":[
        "credit",
        "plan"
    ],
    "wof:name":"Paynet Systems",
    "wof:placetype":"venue"
},
  "geometry": {"coordinates":[-84.201795,34.117526],"type":"Point"}
}