{
  "type": "Feature",
  "properties": {
    "addr:full":"80 Savanna Ct Powder Springs GA 30127",
    "addr:housenumber":"80",
    "addr:postcode":"30127",
    "addr:street":"Savanna Ct",
    "iso:country":"US",
    "sg:address":"80 Savanna Ct",
    "sg:city":"Powder Springs",
    "sg:classifiers":[
        {
            "category":"Freight",
            "type":"Transportation"
        }
    ],
    "sg:phone":"+1 678 567 0023",
    "sg:postcode":"30127",
    "sg:province":"GA",
    "sg:tags":[
        "broker"
    ],
    "wof:name":"Cody Davis Trnsp Systems Inc",
    "wof:placetype":"venue"
},
  "geometry": {"coordinates":[-84.74491999999999,33.831236],"type":"Point"}
}