{
  "type": "Feature",
  "properties": {
    "addr:full":"6140 Central Church Rd Douglasville GA 30135",
    "addr:housenumber":"6140",
    "addr:postcode":"30135",
    "addr:street":"Church Rd",
    "iso:country":"US",
    "sg:address":"6140 Central Church Rd",
    "sg:city":"Douglasville",
    "sg:classifiers":[
        {
            "category":"Professional",
            "subcategory":"Secretarial Services",
            "type":"Services"
        },
        {
            "category":"Professional",
            "subcategory":"Employment Agencies",
            "type":"Services"
        }
    ],
    "sg:phone":"+1 770 947 5600",
    "sg:postcode":"30135",
    "sg:province":"GA",
    "sg:tags":[
        "typing"
    ],
    "wof:name":"Outsourcing Solutions Inc",
    "wof:placetype":"venue"
},
  "geometry": {"coordinates":[-84.775718,33.70651],"type":"Point"}
}