{
  "type": "Feature",
  "properties": {
    "addr:full":"8016 Red Bud Rd NE Ranger GA 30734",
    "addr:housenumber":"8016",
    "addr:postcode":"30734",
    "addr:street":"Red Bud Rd Ne Ranger",
    "iso:country":"US",
    "sg:address":"8016 Red Bud Rd NE",
    "sg:city":"Ranger",
    "sg:classifiers":[
        {
            "category":"Building & Trades",
            "subcategory":"Plumbing",
            "type":"Services"
        }
    ],
    "sg:phone":"+1 706 334 5567",
    "sg:postcode":"30734",
    "sg:province":"GA",
    "sg:tags":[
        "plumbing",
        "contractor"
    ],
    "wof:name":"Georgia North Plumbing",
    "wof:placetype":"venue"
},
  "geometry": {"coordinates":[-84.732855,34.537729],"type":"Point"}
}