{
  "type": "Feature",
  "properties": {
    "iso:country":"US",
    "sg:address":"21 Cobb St",
    "sg:city":"Jefferson",
    "sg:classifiers":[
        {
            "category":"Home & Garden",
            "subcategory":"Carpets & Floor Coverings",
            "type":"Retail Goods"
        }
    ],
    "sg:phone":"+1 706 367 8375",
    "sg:postcode":"30549",
    "sg:province":"GA",
    "sg:tags":[
        "dealer",
        "rug"
    ],
    "wof:name":"MSM Import",
    "wof:placetype":"venue"
},
  "geometry": {"coordinates":[-83.58338000000001,34.11746],"type":"Point"}
}