{
  "type": "Feature",
  "properties": {
    "addr:full":"3643 Walton Way Exd Augusta GA 30909",
    "addr:housenumber":"3643",
    "addr:postcode":"30909",
    "addr:street":"Walton Way Exd",
    "iso:country":"US",
    "sg:address":"3643 Walton Way Exd",
    "sg:city":"Augusta",
    "sg:classifiers":[
        {
            "category":"Banks & Credit Unions",
            "subcategory":"Investment Brokerage",
            "type":"Services"
        },
        {
            "category":"Professional",
            "subcategory":"Management & Consulting",
            "type":"Services"
        }
    ],
    "sg:phone":"+1 706 364 5050",
    "sg:postcode":"30909",
    "sg:province":"GA",
    "sg:tags":[
        "consultant",
        "planning",
        "financial"
    ],
    "wof:name":"Norwood Financial Group",
    "wof:placetype":"venue"
},
  "geometry": {"coordinates":[-82.073584,33.488197],"type":"Point"}
}