{
  "type": "Feature",
  "properties": {
    "iso:country":"US",
    "sg:address":"670 Canton Rd NE",
    "sg:city":"Marietta",
    "sg:classifiers":[
        {
            "category":"Health Services",
            "subcategory":"Doctor",
            "type":"Services"
        }
    ],
    "sg:phone":"+1 770 429 0033",
    "sg:postcode":"30060",
    "sg:province":"GA",
    "sg:tags":[
        "podiatrist"
    ],
    "wof:name":"Heden Robert I Dr",
    "wof:placetype":"venue"
},
  "geometry": {"coordinates":[-84.54789700000001,33.9683],"type":"Point"}
}