{
  "type": "Feature",
  "properties": {
    "iso:country":"US",
    "sg:address":"1002 Greene St",
    "sg:city":"Augusta",
    "sg:classifiers":[
        {
            "category":"Personal",
            "subcategory":"Beauty Salon",
            "type":"Services"
        }
    ],
    "sg:phone":"+1 706 774 6333",
    "sg:postcode":"30901",
    "sg:province":"GA",
    "sg:tags":[
        "shop"
    ],
    "wof:name":"Londons Beauty Barber",
    "wof:placetype":"venue"
},
  "geometry": {"coordinates":[-81.97193799999999,33.475268],"type":"Point"}
}