{
  "type": "Feature",
  "properties": {
    "iso:country":"US",
    "sg:address":"4603 Jonesboro Rd",
    "sg:city":"Forest Park",
    "sg:classifiers":[
        {
            "category":"Building & Trades",
            "subcategory":"Locksmith",
            "type":"Services"
        }
    ],
    "sg:phone":"+1 678 269 7303",
    "sg:postcode":"30297",
    "sg:province":"GA",
    "sg:tags":[
        "key"
    ],
    "wof:name":"Universal Emergency Locksmith",
    "wof:placetype":"venue"
},
  "geometry": {"coordinates":[-84.356245,33.629206],"type":"Point"}
}