{
  "type": "Feature",
  "properties": {
    "addr:full":"417 N 18th St Griffin GA 30223",
    "addr:housenumber":"417",
    "addr:postcode":"30223",
    "addr:street":"N 18Th St",
    "iso:country":"US",
    "sg:address":"417 N 18th St",
    "sg:city":"Griffin",
    "sg:classifiers":[
        {
            "category":"Professional",
            "type":"Services"
        }
    ],
    "sg:phone":"+1 678 688 5300",
    "sg:postcode":"30223",
    "sg:province":"GA",
    "sg:tags":[
        "establishment"
    ],
    "wof:name":"Tabitha's",
    "wof:placetype":"venue"
},
  "geometry": {"coordinates":[-84.28128700000001,33.254882],"type":"Point"}
}