{
  "type": "Feature",
  "properties": {
    "addr:full":"5672 Peachtree Pkwy NW Norcross GA 30092",
    "addr:housenumber":"5672",
    "addr:postcode":"30092",
    "addr:street":"Peachtree Pkwy Nw",
    "iso:country":"US",
    "sg:address":"5672 Peachtree Pkwy NW",
    "sg:city":"Norcross",
    "sg:classifiers":[
        {
            "category":"Professional",
            "subcategory":"Employment Agencies",
            "type":"Services"
        }
    ],
    "sg:phone":"+1 770 449 0181",
    "sg:postcode":"30092",
    "sg:province":"GA",
    "sg:tags":[
        "help",
        "contractor"
    ],
    "wof:name":"Spherion",
    "wof:placetype":"venue"
},
  "geometry": {"coordinates":[-84.22411700000001,33.964328],"type":"Point"}
}