{
  "type": "Feature",
  "properties": {
    "iso:country":"US",
    "sg:address":"215 Forest Ct",
    "sg:city":"Duluth",
    "sg:classifiers":[
        {
            "category":"Home & Garden",
            "subcategory":"Garden Supply",
            "type":"Retail Goods"
        }
    ],
    "sg:phone":"+1 770 814 8488",
    "sg:postcode":"30097",
    "sg:province":"GA",
    "wof:name":"Eastrom",
    "wof:placetype":"venue"
},
  "geometry": {"coordinates":[-84.18689500000001,34.050677],"type":"Point"}
}