{
  "type": "Feature",
  "properties": {
    "addr:full":"101 Brickstone Dr Atlanta GA 30327",
    "addr:housenumber":"101",
    "addr:postcode":"30327",
    "addr:street":"Brickstone Dr",
    "iso:country":"US",
    "sg:address":"101 Brickstone Dr",
    "sg:city":"Atlanta",
    "sg:classifiers":[
        {
            "category":"Professional",
            "type":"Services"
        }
    ],
    "sg:phone":"+1 770 859 0306",
    "sg:postcode":"30327",
    "sg:province":"GA",
    "wof:name":"Keith Hansen",
    "wof:placetype":"venue"
},
  "geometry": {"coordinates":[-84.425184,33.907931],"type":"Point"}
}