{
  "type": "Feature",
  "properties": {
    "addr:full":"540 Piper Rd Covington GA 30014",
    "addr:housenumber":"540",
    "addr:postcode":"30014",
    "addr:street":"Piper Rd",
    "iso:country":"US",
    "sg:address":"540 Piper Rd",
    "sg:city":"Covington",
    "sg:classifiers":[
        {
            "category":"Building & Trades",
            "subcategory":"Construction",
            "type":"Services"
        }
    ],
    "sg:phone":"+1 770 786 1986",
    "sg:postcode":"30014",
    "sg:province":"GA",
    "sg:tags":[
        "siding",
        "contractor"
    ],
    "wof:name":"Johnson's General Contracting",
    "wof:placetype":"venue"
},
  "geometry": {"coordinates":[-83.832905,33.560144],"type":"Point"}
}