{
  "type": "Feature",
  "properties": {
    "iso:country":"US",
    "sg:address":"409 Main St",
    "sg:city":"Thomson",
    "sg:classifiers":[
        {
            "category":"Personal",
            "subcategory":"Beauty Salon",
            "type":"Services"
        }
    ],
    "sg:phone":"+1 706 595 8889",
    "sg:postcode":"30824",
    "sg:province":"GA",
    "sg:tags":[
        "shop"
    ],
    "wof:name":"Blazer Nails",
    "wof:placetype":"venue"
},
  "geometry": {"coordinates":[-82.505233,33.47136],"type":"Point"}
}