{
  "type": "Feature",
  "properties": {
    "iso:country":"US",
    "sg:address":"78 Hampton Rd S",
    "sg:city":"Macon",
    "sg:classifiers":[
        {
            "category":"Real Estate",
            "subcategory":"Real Estate Agent",
            "type":"Services"
        }
    ],
    "sg:phone":"+1 478 742 0526",
    "sg:postcode":"31217",
    "sg:province":"GA",
    "wof:name":"Rancifer Judge",
    "wof:placetype":"venue"
},
  "geometry": {"coordinates":[-83.548608,32.712397],"type":"Point"}
}