{
  "type": "Feature",
  "properties": {
    "addr:full":"4065 Browns Bridge Rd Cumming GA 30041",
    "addr:housenumber":"4065",
    "addr:postcode":"30041",
    "addr:street":"Browns Bridge Rd",
    "iso:country":"US",
    "sg:address":"4065 Browns Bridge Rd",
    "sg:city":"Cumming",
    "sg:classifiers":[
        {
            "category":"Home & Garden",
            "subcategory":"Household Appliances",
            "type":"Retail Goods"
        }
    ],
    "sg:phone":"+1 770 887 4579",
    "sg:postcode":"30041",
    "sg:province":"GA",
    "wof:name":"Rakestraw Inc",
    "wof:placetype":"venue"
},
  "geometry": {"coordinates":[-84.079589,34.260792],"type":"Point"}
}