{
  "type": "Feature",
  "properties": {
    "addr:full":"520 Lakeland Plz Cumming GA 30040",
    "addr:housenumber":"520",
    "addr:postcode":"30040",
    "addr:street":"Lakeland Plz",
    "iso:country":"US",
    "sg:address":"520 Lakeland Plz",
    "sg:city":"Cumming",
    "sg:classifiers":[
        {
            "category":"Building & Trades",
            "subcategory":"Construction",
            "type":"Services"
        }
    ],
    "sg:phone":"+1 678 455 4445",
    "sg:postcode":"30040",
    "sg:province":"GA",
    "sg:tags":[
        "contractor"
    ],
    "wof:name":"Westwood Contractors Inc",
    "wof:placetype":"venue"
},
  "geometry": {"coordinates":[-84.14489500000001,34.182449],"type":"Point"}
}