{
  "type": "Feature",
  "properties": {
    "addr:full":"8880 Gordon Rd Hahira GA 31632",
    "addr:housenumber":"8880",
    "addr:postcode":"31632",
    "addr:street":"Gordon Rd",
    "iso:country":"US",
    "sg:address":"8880 Gordon Rd",
    "sg:city":"Hahira",
    "sg:classifiers":[
        {
            "category":"Building & Trades",
            "subcategory":"Construction",
            "type":"Services"
        }
    ],
    "sg:phone":"+1 229 794 3606",
    "sg:postcode":"31632",
    "sg:province":"GA",
    "sg:tags":[
        "contractor"
    ],
    "wof:name":"Coombs Insulation",
    "wof:placetype":"venue"
},
  "geometry": {"coordinates":[-83.425534,31.029307],"type":"Point"}
}