{
  "type": "Feature",
  "properties": {
    "iso:country":"US",
    "sg:address":"11525 Haynes Bridge Rd",
    "sg:city":"Alpharetta",
    "sg:classifiers":[
        {
            "category":"Deli",
            "type":"Food & Drink"
        }
    ],
    "sg:menulink":"http://www.allmenus.com/ga/roswell-alpharetta/245263-grouchys-deli/menu/",
    "sg:phone":"+1 770 667 6933",
    "sg:postcode":"30004",
    "sg:province":"GA",
    "sg:tags":[
        "american"
    ],
    "wof:name":"Grouchy's Deli",
    "wof:placetype":"venue"
},
  "geometry": {"coordinates":[-84.289834,34.061381],"type":"Point"}
}