{
  "type": "Feature",
  "properties": {
    "addr:full":"639 Fair Harbor Dr Lithonia GA 30058",
    "addr:housenumber":"639",
    "addr:postcode":"30058",
    "addr:street":"Fair Harbor Dr",
    "iso:country":"US",
    "sg:address":"639 Fair Harbor Dr",
    "sg:city":"Lithonia",
    "sg:classifiers":[
        {
            "category":"Professional",
            "subcategory":"Business Services",
            "type":"Services"
        }
    ],
    "sg:phone":"+1 770 469 0706",
    "sg:postcode":"30058",
    "sg:province":"GA",
    "sg:tags":[
        "event"
    ],
    "wof:name":"Fabulous Functions",
    "wof:placetype":"venue"
},
  "geometry": {"coordinates":[-84.09384900000001,33.777277],"type":"Point"}
}