{
  "type": "Feature",
  "properties": {
    "iso:country":"US",
    "sg:address":"245 W Ponce De Leon",
    "sg:city":"Decatur",
    "sg:classifiers":[
        {
            "category":"Banks & Credit Unions",
            "subcategory":"Bank",
            "type":"Services"
        }
    ],
    "sg:postcode":"30030",
    "sg:province":"GA",
    "sg:website":"www.deltacommunitycu.com",
    "wof:name":"Delta Community Credit Union",
    "wof:placetype":"venue"
},
  "geometry": {"coordinates":[-84.298806,33.775598],"type":"Point"}
}