{
  "type": "Feature",
  "properties": {
    "iso:country":"US",
    "sg:address":"3914 Glenwood Rd",
    "sg:city":"Decatur",
    "sg:classifiers":[
        {
            "category":"Retail",
            "subcategory":"Auto Repair",
            "type":"Services"
        }
    ],
    "sg:phone":"+1 404 289 4321",
    "sg:postcode":"30032",
    "sg:province":"GA",
    "sg:tags":[
        "automotive"
    ],
    "wof:name":"Good News Brake Shop",
    "wof:placetype":"venue"
},
  "geometry": {"coordinates":[-84.25679100000001,33.738099],"type":"Point"}
}