{
  "type": "Feature",
  "properties": {
    "addr:full":"1259 Carlisle Ct Grayson GA 30017",
    "addr:housenumber":"1259",
    "addr:postcode":"30017",
    "addr:street":"Carlisle Ct",
    "iso:country":"US",
    "sg:address":"1259 Carlisle Ct",
    "sg:city":"Grayson",
    "sg:classifiers":[
        {
            "category":"Health Services",
            "subcategory":"Clinic",
            "type":"Services"
        }
    ],
    "sg:phone":"+1 770 736 3919",
    "sg:postcode":"30017",
    "sg:province":"GA",
    "sg:tags":[
        "home"
    ],
    "wof:name":"Heaven's Heights Healthcare",
    "wof:placetype":"venue"
},
  "geometry": {"coordinates":[-83.990712,33.891555],"type":"Point"}
}