{
  "type": "Feature",
  "properties": {
    "addr:full":"4608 Jimmy Carter Blvd Norcross GA 30093",
    "addr:housenumber":"4608",
    "addr:postcode":"30093",
    "addr:street":"Jimmy Carter Blvd",
    "iso:country":"US",
    "sg:address":"4608 Jimmy Carter Blvd",
    "sg:city":"Norcross",
    "sg:classifiers":[
        {
            "category":"Professional",
            "type":"Services"
        }
    ],
    "sg:phone":"+1 770 414 9225",
    "sg:postcode":"30093",
    "sg:province":"GA",
    "sg:tags":[
        "establishment"
    ],
    "wof:name":"Beilla Brazilian",
    "wof:placetype":"venue"
},
  "geometry": {"coordinates":[-84.19391,33.88746],"type":"Point"}
}