{
  "type": "Feature",
  "properties": {
    "addr:full":"1514 Fordham Rd Brooklet GA 30415",
    "addr:housenumber":"1514",
    "addr:postcode":"30415",
    "addr:street":"Fordham Rd",
    "iso:country":"US",
    "sg:address":"1514 Fordham Rd",
    "sg:city":"Brooklet",
    "sg:classifiers":[
        {
            "category":"Restaurant",
            "type":"Food & Drink"
        }
    ],
    "sg:phone":"+1 912 489 3307",
    "sg:postcode":"30415",
    "sg:province":"GA",
    "wof:name":"The Friendly Diner",
    "wof:placetype":"venue"
},
  "geometry": {"coordinates":[-81.69130199999999,32.290071],"type":"Point"}
}