{
  "type": "Feature",
  "properties": {
    "addr:full":"100 Kedron Dr Peachtree City GA 30269",
    "addr:housenumber":"100",
    "addr:postcode":"30269",
    "addr:street":"Kedron Dr",
    "iso:country":"US",
    "sg:address":"100 Kedron Dr",
    "sg:city":"Peachtree City",
    "sg:classifiers":[
        {
            "category":"Banks & Credit Unions",
            "subcategory":"Bank",
            "type":"Services"
        }
    ],
    "sg:phone":"+1 770 631 3940",
    "sg:postcode":"30269",
    "sg:province":"GA",
    "sg:tags":[
        "state",
        "commercial"
    ],
    "wof:name":"Fayette County Bank Kedron",
    "wof:placetype":"venue"
},
  "geometry": {"coordinates":[-84.603808,33.431669],"type":"Point"}
}