{
  "type": "Feature",
  "properties": {
    "addr:full":"140 Ware St Athens GA 30601",
    "addr:housenumber":"140",
    "addr:postcode":"30601",
    "addr:street":"Ware St",
    "iso:country":"US",
    "sg:address":"140 Ware St",
    "sg:city":"Athens",
    "sg:classifiers":[
        {
            "category":"Wholesale",
            "subcategory":"Hardware",
            "type":"Manufacturing & Wholesale Goods"
        }
    ],
    "sg:phone":"+1 706 549 7282",
    "sg:postcode":"30601",
    "sg:province":"GA",
    "sg:tags":[
        "refrigerating"
    ],
    "wof:name":"Classic City Refrigeration",
    "wof:placetype":"venue"
},
  "geometry": {"coordinates":[-83.378652,33.965424],"type":"Point"}
}