{
  "type": "Feature",
  "properties": {
    "addr:full":"9234 Ferguson Ave Savannah GA 31406",
    "addr:housenumber":"9234",
    "addr:postcode":"31406",
    "addr:street":"Ferguson Ave",
    "iso:country":"US",
    "sg:address":"9234 Ferguson Ave",
    "sg:city":"Savannah",
    "sg:classifiers":[
        {
            "category":"Autos & Motor Vehicles",
            "subcategory":"Boat Sales",
            "type":"Retail Goods"
        }
    ],
    "sg:phone":"+1 912 354 4778",
    "sg:postcode":"31406",
    "sg:province":"GA",
    "sg:tags":[
        "top",
        "upholstery",
        "cover"
    ],
    "wof:name":"Islands Marine Inc",
    "wof:placetype":"venue"
},
  "geometry": {"coordinates":[-81.087329,31.970487],"type":"Point"}
}