{
  "type": "Feature",
  "properties": {
    "addr:full":"9270 Waits Ferry Xing Duluth GA 30097",
    "addr:housenumber":"9270",
    "addr:postcode":"30097",
    "addr:street":"Waits Ferry Xing",
    "iso:country":"US",
    "sg:address":"9270 Waits Ferry Xing",
    "sg:city":"Duluth",
    "sg:classifiers":[
        {
            "category":"Real Estate",
            "subcategory":"Real Estate Agent",
            "type":"Services"
        }
    ],
    "sg:phone":"+1 770 840 9782",
    "sg:postcode":"30097",
    "sg:province":"GA",
    "wof:name":"J Daniels & Associates Company",
    "wof:placetype":"venue"
},
  "geometry": {"coordinates":[-84.20562099999999,34.006602],"type":"Point"}
}