{
  "type": "Feature",
  "properties": {
    "addr:full":"1930 Airport Ind Park Dr SE Marietta GA 30060",
    "addr:housenumber":"1930",
    "addr:postcode":"30060",
    "addr:street":"Airport Ind Park Dr Se",
    "iso:country":"US",
    "sg:address":"1930 Airport Ind Park Dr SE",
    "sg:city":"Marietta",
    "sg:classifiers":[
        {
            "category":"Banks & Credit Unions",
            "subcategory":"Bureau De Change",
            "type":"Services"
        },
        {
            "category":"Wholesale",
            "subcategory":"Office Equipment",
            "type":"Manufacturing & Wholesale Goods"
        },
        {
            "category":"Professional",
            "subcategory":"Business Services",
            "type":"Services"
        },
        {
            "category":"Professional",
            "subcategory":"Printing & Photocopies",
            "type":"Services"
        },
        {
            "category":"Shopping",
            "subcategory":"Computers & Home Electronics",
            "type":"Retail Goods"
        }
    ],
    "sg:phone":"+1 770 953 8713",
    "sg:postcode":"30060",
    "sg:province":"GA",
    "sg:tags":[
        "scanning",
        "printer",
        "form",
        "supply",
        "services-commercial",
        "duplicating",
        "shipping",
        "printers-business",
        "copying",
        "mail",
        "plotting",
        "card"
    ],
    "sg:website":"http://www.kwikkopy.com",
    "wof:name":"Kwik Kopy Printing",
    "wof:placetype":"venue"
},
  "geometry": {"coordinates":[-84.466865,33.918148],"type":"Point"}
}