{
  "type": "Feature",
  "properties": {
    "addr:full":"2228 Austell Rd SW Marietta GA 30008",
    "addr:housenumber":"2228",
    "addr:postcode":"30008",
    "addr:street":"Austell Rd Sw",
    "iso:country":"US",
    "sg:address":"2228 Austell Rd SW",
    "sg:city":"Marietta",
    "sg:classifiers":[
        {
            "category":"Autos & Motor Vehicles",
            "subcategory":"Automobile Sales",
            "type":"Retail Goods"
        }
    ],
    "sg:phone":"+1 770 434 5780",
    "sg:postcode":"30008",
    "sg:province":"GA",
    "sg:tags":[
        "car"
    ],
    "wof:name":"J Bros Auto Sales Inc",
    "wof:placetype":"venue"
},
  "geometry": {"coordinates":[-84.571297,33.899899],"type":"Point"}
}