{
  "type": "Feature",
  "properties": {
    "iso:country":"US",
    "sg:address":"707 Edgehill Ave NW",
    "sg:city":"Atlanta",
    "sg:phone":"+1 678 973 4912",
    "sg:postcode":"30318",
    "sg:province":"GA",
    "sg:website":"http://atlanta.citysearch.com/profile/external/35718934/atlanta_ga/atlanta_dog_spa.html?publisher=yellowpages&reference_id=1&placement=ypwebsitemip",
    "wof:name":"ATLANTA DOG SPA",
    "wof:placetype":"venue"
},
  "geometry": {"coordinates":[-84.409645,33.782379],"type":"Point"}
}