{
  "type": "Feature",
  "properties": {
    "addr:full":"502 S Main St Fitzgerald GA 31750",
    "addr:housenumber":"502",
    "addr:postcode":"31750",
    "addr:street":"S Main St",
    "iso:country":"US",
    "sg:address":"502 S Main St",
    "sg:city":"Fitzgerald",
    "sg:classifiers":[
        {
            "category":"Insurance",
            "subcategory":"Insurance Agent",
            "type":"Services"
        }
    ],
    "sg:phone":"+1 229 423 8169",
    "sg:postcode":"31750",
    "sg:province":"GA",
    "wof:name":"Southern Marketing",
    "wof:placetype":"venue"
},
  "geometry": {"coordinates":[-83.25422500000001,31.710178],"type":"Point"}
}