{
  "type": "Feature",
  "properties": {
    "iso:country":"US",
    "sg:address":"1302 Juniper St",
    "sg:city":"Lagrange",
    "sg:classifiers":[
        {
            "category":"Shopping",
            "subcategory":"Hobbies, Toys, & Games",
            "type":"Retail Goods"
        },
        {
            "category":"Shopping",
            "subcategory":"Gifts & Souvenirs",
            "type":"Retail Goods"
        }
    ],
    "sg:phone":"+1 706 884 7733",
    "sg:postcode":"30240",
    "sg:province":"GA",
    "sg:tags":[
        "product",
        "ceramic"
    ],
    "wof:name":"Bledsoe Ceramics",
    "wof:placetype":"venue"
},
  "geometry": {"coordinates":[-85.04035,33.020607],"type":"Point"}
}