{
  "type": "Feature",
  "properties": {
    "iso:country":"US",
    "sg:address":"957 Baxter St",
    "sg:city":"Athens",
    "sg:classifiers":[
        {
            "category":"Health Services",
            "subcategory":"Clinic",
            "type":"Services"
        }
    ],
    "sg:phone":"+1 706 354 4245",
    "sg:postcode":"30606",
    "sg:province":"GA",
    "sg:tags":[
        "colonic",
        "irrigation"
    ],
    "wof:name":"Carol Martin",
    "wof:placetype":"venue"
},
  "geometry": {"coordinates":[-83.390942,33.948399],"type":"Point"}
}