{
  "type": "Feature",
  "properties": {
    "iso:country":"US",
    "sg:address":"3400 Oakcliff Rd",
    "sg:city":"Atlanta",
    "sg:classifiers":[
        {
            "category":"Wholesale",
            "subcategory":"Jewelry",
            "type":"Manufacturing & Wholesale Goods"
        }
    ],
    "sg:phone":"+1 678 381 0574",
    "sg:postcode":"30340",
    "sg:province":"GA",
    "sg:tags":[
        "jeweler"
    ],
    "wof:name":"Fancy Imports",
    "wof:placetype":"venue"
},
  "geometry": {"coordinates":[-84.254475,33.90574],"type":"Point"}
}