{
  "type": "Feature",
  "properties": {
    "iso:country":"US",
    "sg:address":"167 Fowler Dr",
    "sg:city":"Canton",
    "sg:classifiers":[
        {
            "category":"Professional",
            "subcategory":"Accounting & Tax Preparation",
            "type":"Services"
        }
    ],
    "sg:phone":"+1 678 454 1017",
    "sg:postcode":"30114",
    "sg:province":"GA",
    "sg:tags":[
        "accountant"
    ],
    "wof:name":"Daugharty & Co",
    "wof:placetype":"venue"
},
  "geometry": {"coordinates":[-84.50546900000001,34.209044],"type":"Point"}
}