{
  "type": "Feature",
  "properties": {
    "iso:country":"US",
    "sg:address":"961 Santa Fe Trl",
    "sg:city":"Macon",
    "sg:classifiers":[
        {
            "category":"Real Estate",
            "subcategory":"Real Estate Agent",
            "type":"Services"
        }
    ],
    "sg:phone":"+1 478 474 4200",
    "sg:postcode":"31220",
    "sg:province":"GA",
    "wof:name":"Smith & Smith Realtors",
    "wof:placetype":"venue"
},
  "geometry": {"coordinates":[-83.783354,32.858833],"type":"Point"}
}