{
  "type": "Feature",
  "properties": {
    "addr:full":"3100 Breckinridge Blvd Duluth GA 30096",
    "addr:housenumber":"3100",
    "addr:postcode":"30096",
    "addr:street":"Breckinridge Blvd",
    "iso:country":"US",
    "sg:address":"3100 Breckinridge Blvd",
    "sg:city":"Duluth",
    "sg:classifiers":[
        {
            "category":"Food & Beverages",
            "subcategory":"Groceries & Convenience Stores",
            "type":"Retail Goods"
        },
        {
            "category":"Insurance",
            "subcategory":"Insurance Agent",
            "type":"Services"
        }
    ],
    "sg:phone":"+1 770 381 8444",
    "sg:postcode":"30096",
    "sg:province":"GA",
    "wof:name":"Atlanta Data Systems Inc",
    "wof:placetype":"venue"
},
  "geometry": {"coordinates":[-84.105648,33.960103],"type":"Point"}
}