{
  "type": "Feature",
  "properties": {
    "iso:country":"US",
    "sg:address":"147 Brandywine Dr",
    "sg:city":"Forsyth",
    "sg:classifiers":[
        {
            "category":"Organizations",
            "subcategory":"Community Association",
            "type":"Services"
        }
    ],
    "sg:phone":"+1 478 994 9884",
    "sg:postcode":"31029",
    "sg:province":"GA",
    "wof:name":"Ancient & Accepted Scotti",
    "wof:placetype":"venue"
},
  "geometry": {"coordinates":[-83.950603,33.058851],"type":"Point"}
}