{
  "type": "Feature",
  "properties": {
    "addr:full":"407 E Tugalo St Toccoa GA 30577",
    "addr:housenumber":"407",
    "addr:postcode":"30577",
    "addr:street":"E Tugalo St",
    "iso:country":"US",
    "sg:address":"407 E Tugalo St",
    "sg:city":"Toccoa",
    "sg:classifiers":[
        {
            "category":"Organizations",
            "subcategory":"Religious Organization",
            "type":"Services"
        }
    ],
    "sg:phone":"+1 706 886 8783",
    "sg:postcode":"30577",
    "sg:province":"GA",
    "sg:tags":[
        "church"
    ],
    "wof:name":"First United Methodist Church",
    "wof:placetype":"venue"
},
  "geometry": {"coordinates":[-83.32799900000001,34.580274],"type":"Point"}
}