{
  "type": "Feature",
  "properties": {
    "iso:country":"US",
    "sg:address":"3040 Campbellton Rd SW",
    "sg:city":"Atlanta",
    "sg:classifiers":[
        {
            "category":"Organizations",
            "subcategory":"Religious Organization",
            "type":"Services"
        }
    ],
    "sg:phone":"+1 404 344 9757",
    "sg:postcode":"30311",
    "sg:province":"GA",
    "wof:name":"Mohammads Mosque",
    "wof:placetype":"venue"
},
  "geometry": {"coordinates":[-84.487815,33.694862],"type":"Point"}
}