{
  "type": "Feature",
  "properties": {
    "addr:full":"225 Governors Ct Cartersville GA 30121",
    "addr:housenumber":"225",
    "addr:postcode":"30121",
    "addr:street":"Governors Ct",
    "iso:country":"US",
    "sg:address":"225 Governors Ct",
    "sg:city":"Cartersville",
    "sg:classifiers":[
        {
            "category":"Freight",
            "type":"Transportation"
        }
    ],
    "sg:phone":"+1 770 606 0988",
    "sg:postcode":"30121",
    "sg:province":"GA",
    "sg:tags":[
        "operator",
        "local",
        "trucking"
    ],
    "wof:name":"Danny Harvey Trucking",
    "wof:placetype":"venue"
},
  "geometry": {"coordinates":[-84.816001,34.212273],"type":"Point"}
}