{
  "type": "Feature",
  "properties": {
    "iso:country":"US",
    "sg:address":"1571 Whisperwood Trl",
    "sg:city":"Stone Mountain",
    "sg:classifiers":[
        {
            "category":"Building & Trades",
            "subcategory":"Construction",
            "type":"Services"
        }
    ],
    "sg:phone":"+1 770 469 6307",
    "sg:postcode":"30088",
    "sg:province":"GA",
    "sg:tags":[
        "residential"
    ],
    "wof:name":"Emmett Smith Builders Inc",
    "wof:placetype":"venue"
},
  "geometry": {"coordinates":[-84.16662599999999,33.777776],"type":"Point"}
}