{
  "type": "Feature",
  "properties": {
    "iso:country":"US",
    "sg:address":"117 W Shotwell St",
    "sg:city":"Bainbridge",
    "sg:classifiers":[
        {
            "category":"Personal",
            "subcategory":"Beauty Salon",
            "type":"Services"
        }
    ],
    "sg:phone":"+1 229 243 9001",
    "sg:postcode":"39819",
    "sg:province":"GA",
    "sg:tags":[
        "hair",
        "shop",
        "stylist"
    ],
    "wof:name":"Hair Shapers",
    "wof:placetype":"venue"
},
  "geometry": {"coordinates":[-84.57661299999999,30.904018],"type":"Point"}
}