{
  "type": "Feature",
  "properties": {
    "addr:full":"121 Coondog Trl Morganton GA 30554",
    "addr:housenumber":"121",
    "addr:postcode":"30554",
    "addr:street":"Coondog Trl",
    "iso:country":"US",
    "sg:address":"121 Coondog Trl",
    "sg:city":"Morganton",
    "sg:classifiers":[
        {
            "category":"Organizations",
            "subcategory":"Religious Organization",
            "type":"Services"
        }
    ],
    "sg:phone":"+1 706 838 4838",
    "sg:postcode":"30554",
    "sg:province":"GA",
    "sg:tags":[
        "church"
    ],
    "wof:name":"Wilscot Baptist Church",
    "wof:placetype":"venue"
},
  "geometry": {"coordinates":[-83.55474700000001,34.387365],"type":"Point"}
}