{
  "type": "Feature",
  "properties": {
    "iso:country":"US",
    "sg:address":"3352 Sean Way",
    "sg:city":"Lawrenceville",
    "sg:classifiers":[
        {
            "category":"Professional",
            "subcategory":"Management & Consulting",
            "type":"Services"
        }
    ],
    "sg:phone":"+1 770 979 8962",
    "sg:postcode":"30044",
    "sg:province":"GA",
    "sg:tags":[
        "consultant",
        "transportation"
    ],
    "wof:name":"Cds Transport",
    "wof:placetype":"venue"
},
  "geometry": {"coordinates":[-84.07486400000001,33.882379],"type":"Point"}
}