{
  "type": "Feature",
  "properties": {
    "iso:country":"US",
    "sg:address":"2770 Stonesmith Ct",
    "sg:city":"Tucker",
    "sg:classifiers":[
        {
            "category":"Retail",
            "subcategory":"Animal Services",
            "type":"Services"
        }
    ],
    "sg:phone":"+1 770 270 1440",
    "sg:postcode":"30084",
    "sg:province":"GA",
    "sg:tags":[
        "pet",
        "breeder"
    ],
    "wof:name":"Lehaven Cattery",
    "wof:placetype":"venue"
},
  "geometry": {"coordinates":[-84.21086200000001,33.868451],"type":"Point"}
}