{
  "type": "Feature",
  "properties": {
    "iso:country":"US",
    "sg:address":"4605 Sylvester Hwy",
    "sg:city":"Sylvester",
    "sg:classifiers":[
        {
            "category":"Wholesale",
            "subcategory":"Auto Parts",
            "type":"Manufacturing & Wholesale Goods"
        }
    ],
    "sg:phone":"+1 229 438 1084",
    "sg:postcode":"31791",
    "sg:province":"GA",
    "wof:name":"Sylcree Industrial Tire",
    "wof:placetype":"venue"
},
  "geometry": {"coordinates":[-83.986051,31.554257],"type":"Point"}
}