{
  "type": "Feature",
  "properties": {
    "addr:full":"8 City Hall Ave Carrollton GA 30117",
    "addr:housenumber":"8",
    "addr:postcode":"30117",
    "addr:street":"City Hall Ave",
    "iso:country":"US",
    "sg:address":"8 City Hall Ave",
    "sg:city":"Carrollton",
    "sg:classifiers":[
        {
            "category":"Wholesale",
            "subcategory":"Hardware",
            "type":"Manufacturing & Wholesale Goods"
        }
    ],
    "sg:phone":"+1 770 832 6341",
    "sg:postcode":"30117",
    "sg:province":"GA",
    "sg:tags":[
        "plumbing",
        "fixture",
        "supply"
    ],
    "wof:name":"Smith Brothers Supply Co",
    "wof:placetype":"venue"
},
  "geometry": {"coordinates":[-85.074966,33.580949],"type":"Point"}
}