{
  "type": "Feature",
  "properties": {
    "iso:country":"US",
    "sg:address":"4216 Old Club Rd E",
    "sg:city":"Macon",
    "sg:classifiers":[
        {
            "category":"Real Estate",
            "subcategory":"Real Estate Agent",
            "type":"Services"
        }
    ],
    "sg:phone":"+1 478 477 6544",
    "sg:postcode":"31210",
    "sg:province":"GA",
    "wof:name":"Metal Enterprises Inc",
    "wof:placetype":"venue"
},
  "geometry": {"coordinates":[-83.700202,32.862186],"type":"Point"}
}