{
  "type": "Feature",
  "properties": {
    "iso:country":"US",
    "sg:address":"292 S Main St Ste 500",
    "sg:city":"Alpharetta",
    "sg:classifiers":[
        {
            "category":"Building & Trades",
            "subcategory":"Construction",
            "type":"Services"
        }
    ],
    "sg:phone":"+1 770 777 0055",
    "sg:postcode":"30009",
    "sg:province":"GA",
    "sg:tags":[
        "contractor"
    ],
    "wof:name":"Dove Contracting Inc",
    "wof:placetype":"venue"
},
  "geometry": {"coordinates":[-84.30079000000001,34.067983],"type":"Point"}
}