{
  "type": "Feature",
  "properties": {
    "iso:country":"US",
    "sg:address":"6226 Queens Rd",
    "sg:city":"Douglasville",
    "sg:classifiers":[
        {
            "category":"Autos & Motor Vehicles",
            "subcategory":"Automobile Sales",
            "type":"Retail Goods"
        }
    ],
    "sg:phone":"+1 770 943 1798",
    "sg:postcode":"30135",
    "sg:province":"GA",
    "sg:tags":[
        "car",
        "dealer"
    ],
    "wof:name":"Sony Max Used Car Sales",
    "wof:placetype":"venue"
},
  "geometry": {"coordinates":[-84.781164,33.683579],"type":"Point"}
}