{
  "type": "Feature",
  "properties": {
    "iso:country":"US",
    "sg:address":"902 Bowens Mill Rd SW",
    "sg:city":"Douglas",
    "sg:classifiers":[
        {
            "category":"Personal",
            "subcategory":"Tanning Parlor",
            "type":"Services"
        }
    ],
    "sg:phone":"+1 912 383 8890",
    "sg:postcode":"31533",
    "sg:province":"GA",
    "sg:tags":[
        "salon"
    ],
    "wof:name":"Bahama Tan",
    "wof:placetype":"venue"
},
  "geometry": {"coordinates":[-82.87298800000001,31.497472],"type":"Point"}
}