{
  "type": "Feature",
  "properties": {
    "addr:full":"5871 Glenridge Drive Suite 300 Atlanta GA 30328",
    "addr:housenumber":"5871",
    "addr:postcode":"30328",
    "addr:street":"Glenridge Drive Suite 300",
    "iso:country":"US",
    "sg:address":"5871 Glenridge Drive Suite 300",
    "sg:city":"Atlanta",
    "sg:classifiers":[
        {
            "category":"Professional",
            "subcategory":"Business Services",
            "type":"Services"
        }
    ],
    "sg:phone":"+1 770 375 7214",
    "sg:postcode":"30328",
    "sg:province":"GA",
    "sg:tags":[
        "open-source",
        "telephony",
        "ivr",
        "contact-center",
        "pbx",
        "supply-chain",
        "mass-communication",
        "unified-communication",
        "voip",
        "asterisk",
        "freeswitch"
    ],
    "sg:website":"http://www.starpound.net",
    "wof:name":"StarPound Technologies",
    "wof:placetype":"venue"
},
  "geometry": {"coordinates":[-84.36212500000001,33.912717],"type":"Point"}
}