{
  "type": "Feature",
  "properties": {
    "iso:country":"US",
    "sg:address":"621 Pony Lake Rd",
    "sg:city":"Dahlonega",
    "sg:classifiers":[
        {
            "category":"Building & Trades",
            "subcategory":"Construction",
            "type":"Services"
        }
    ],
    "sg:phone":"+1 770 287 7906",
    "sg:postcode":"30533",
    "sg:province":"GA",
    "sg:tags":[
        "contractor"
    ],
    "wof:name":"Inspired Builders Inc",
    "wof:placetype":"venue"
},
  "geometry": {"coordinates":[-83.931112,34.457698],"type":"Point"}
}