{
  "type": "Feature",
  "properties": {
    "iso:country":"US",
    "sg:address":"2201 Bethany Rd",
    "sg:city":"Madison",
    "sg:classifiers":[
        {
            "category":"Professional",
            "type":"Services"
        }
    ],
    "sg:phone":"+1 706 342 4009",
    "sg:postcode":"30650",
    "sg:province":"GA",
    "sg:tags":[
        "establishment"
    ],
    "wof:name":"Seed Production Inc",
    "wof:placetype":"venue"
},
  "geometry": {"coordinates":[-83.445364,33.565531],"type":"Point"}
}