{
  "type": "Feature",
  "properties": {
    "addr:full":"115 Satilla Ave Nahunta GA 31553",
    "addr:housenumber":"115",
    "addr:postcode":"31553",
    "addr:street":"Satilla Ave",
    "iso:country":"US",
    "sg:address":"115 Satilla Ave",
    "sg:city":"Nahunta",
    "sg:classifiers":[
        {
            "category":"Retail",
            "subcategory":"Funeral Services",
            "type":"Services"
        }
    ],
    "sg:phone":"+1 912 462 5151",
    "sg:postcode":"31553",
    "sg:province":"GA",
    "sg:tags":[
        "director"
    ],
    "wof:name":"Chambless Frye Funeral Home",
    "wof:placetype":"venue"
},
  "geometry": {"coordinates":[-81.97967,31.204458],"type":"Point"}
}