{
  "type": "Feature",
  "properties": {
    "addr:full":"1461 Benjamin Ct SW Marietta GA 30064",
    "addr:housenumber":"1461",
    "addr:postcode":"30064",
    "addr:street":"Benjamin Ct Sw",
    "iso:country":"US",
    "sg:address":"1461 Benjamin Ct SW",
    "sg:city":"Marietta",
    "sg:classifiers":[
        {
            "category":"Organizations",
            "subcategory":"Membership Organization",
            "type":"Services"
        }
    ],
    "sg:phone":"+1 770 528 6225",
    "sg:postcode":"30064",
    "sg:province":"GA",
    "sg:tags":[
        "club",
        "travel"
    ],
    "wof:name":"Smooth Landing Travel",
    "wof:placetype":"venue"
},
  "geometry": {"coordinates":[-84.63325399999999,33.918205],"type":"Point"}
}