{
  "type": "Feature",
  "properties": {
    "addr:full":"715 Kenion Forest Way Lilburn GA 30047",
    "addr:housenumber":"715",
    "addr:postcode":"30047",
    "addr:street":"Kenion Forest Way",
    "iso:country":"US",
    "sg:address":"715 Kenion Forest Way",
    "sg:city":"Lilburn",
    "sg:classifiers":[
        {
            "category":"Utilities",
            "subcategory":"Mobile Phone",
            "type":"Services"
        }
    ],
    "sg:phone":"+1 770 717 2777",
    "sg:postcode":"30047",
    "sg:province":"GA",
    "sg:tags":[
        "telephone",
        "cellular"
    ],
    "wof:name":"Nextel Communications Inc",
    "wof:placetype":"venue"
},
  "geometry": {"coordinates":[-84.10923099999999,33.869949],"type":"Point"}
}