{
  "type": "Feature",
  "properties": {
    "iso:country":"US",
    "sg:address":"7165 Doncaster Ct",
    "sg:city":"Cumming",
    "sg:classifiers":[
        {
            "category":"Communications",
            "subcategory":"Film & Video Production",
            "type":"Services"
        }
    ],
    "sg:phone":"+1 770 921 8939",
    "sg:postcode":"30040",
    "sg:province":"GA",
    "sg:tags":[
        "motion"
    ],
    "wof:name":"Dewitt Smith Video Productions",
    "wof:placetype":"venue"
},
  "geometry": {"coordinates":[-84.252531,34.180743],"type":"Point"}
}