{
  "type": "Feature",
  "properties": {
    "addr:full":"565 Donna Dr Smyrna GA 30082",
    "addr:housenumber":"565",
    "addr:postcode":"30082",
    "addr:street":"Donna Dr",
    "iso:country":"US",
    "sg:address":"565 Donna Dr",
    "sg:city":"Smyrna",
    "sg:classifiers":[
        {
            "category":"Wholesale",
            "subcategory":"Groceries",
            "type":"Manufacturing & Wholesale Goods"
        }
    ],
    "sg:phone":"+1 770 435 7538",
    "sg:postcode":"30082",
    "sg:province":"GA",
    "sg:tags":[
        "general"
    ],
    "wof:name":"Diversified Mktg Sls & Svcs",
    "wof:placetype":"venue"
},
  "geometry": {"coordinates":[-84.57042,33.859915],"type":"Point"}
}