{
  "type": "Feature",
  "properties": {
    "addr:full":"601 N Main St Wrens GA 30833",
    "addr:housenumber":"601",
    "addr:postcode":"30833",
    "addr:street":"N Main St",
    "iso:country":"US",
    "sg:address":"601 N Main St",
    "sg:city":"Wrens",
    "sg:classifiers":[
        {
            "category":"Autos & Motor Vehicles",
            "subcategory":"Auto Supplies",
            "type":"Retail Goods"
        }
    ],
    "sg:phone":"+1 706 547 6573",
    "sg:postcode":"30833",
    "sg:province":"GA",
    "sg:tags":[
        "repair",
        "general"
    ],
    "wof:name":"Lloyds Auto Parts",
    "wof:placetype":"venue"
},
  "geometry": {"coordinates":[-82.383589,33.215324],"type":"Point"}
}