{
  "type": "Feature",
  "properties": {
    "addr:full":"4063 Tiffany Dr Decatur GA 30035",
    "addr:housenumber":"4063",
    "addr:postcode":"30035",
    "addr:street":"Tiffany Dr",
    "iso:country":"US",
    "sg:address":"4063 Tiffany Dr",
    "sg:city":"Decatur",
    "sg:classifiers":[
        {
            "category":"Freight",
            "type":"Transportation"
        }
    ],
    "sg:phone":"+1 404 289 4711",
    "sg:postcode":"30035",
    "sg:province":"GA",
    "sg:tags":[
        "mover"
    ],
    "wof:name":"Anytime Moving Svc",
    "wof:placetype":"venue"
},
  "geometry": {"coordinates":[-84.22252899999999,33.716037],"type":"Point"}
}