{
  "type": "Feature",
  "properties": {
    "addr:full":"1766 Alexander Dr Decatur GA 30032",
    "addr:housenumber":"1766",
    "addr:postcode":"30032",
    "addr:street":"Alexander Dr",
    "iso:country":"US",
    "sg:address":"1766 Alexander Dr",
    "sg:city":"Decatur",
    "sg:classifiers":[
        {
            "category":"Shopping",
            "subcategory":"Florist",
            "type":"Retail Goods"
        }
    ],
    "sg:phone":"+1 404 534 9738",
    "sg:postcode":"30032",
    "sg:province":"GA",
    "wof:name":"Iris Flowers",
    "wof:placetype":"venue"
},
  "geometry": {"coordinates":[-84.287273,33.739459],"type":"Point"}
}