{
  "type": "Feature",
  "properties": {
    "addr:full":"318 Sandalin Ln Peachtree City GA 30269",
    "addr:housenumber":"318",
    "addr:postcode":"30269",
    "addr:street":"Sandalin Ln",
    "iso:country":"US",
    "sg:address":"318 Sandalin Ln",
    "sg:city":"Peachtree City",
    "sg:classifiers":[
        {
            "category":"Professional",
            "subcategory":"Management & Consulting",
            "type":"Services"
        }
    ],
    "sg:phone":"+1 770 632 2801",
    "sg:postcode":"30269",
    "sg:province":"GA",
    "wof:name":"Collaboration Mktg Inc",
    "wof:placetype":"venue"
},
  "geometry": {"coordinates":[-84.584519,33.423512],"type":"Point"}
}