{
  "type": "Feature",
  "properties": {
    "iso:country":"US",
    "sg:address":"1920 Glenhurst Dr",
    "sg:city":"Snellville",
    "sg:classifiers":[
        {
            "category":"Building & Trades",
            "subcategory":"Plumbing",
            "type":"Services"
        }
    ],
    "sg:phone":"+1 678 714 7474",
    "sg:postcode":"30078",
    "sg:province":"GA",
    "sg:tags":[
        "contractor"
    ],
    "wof:name":"Eastside Office Furn & ACC",
    "wof:placetype":"venue"
},
  "geometry": {"coordinates":[-84.02567500000001,33.874256],"type":"Point"}
}