{
  "type": "Feature",
  "properties": {
    "iso:country":"US",
    "sg:address":"2858 Ashton Hill Dr",
    "sg:city":"Dacula",
    "sg:classifiers":[
        {
            "category":"Professional",
            "subcategory":"Management & Consulting",
            "type":"Services"
        }
    ],
    "sg:phone":"+1 678 546 8427",
    "sg:postcode":"30019",
    "sg:province":"GA",
    "wof:name":"Louis Phillips and Associates",
    "wof:placetype":"venue"
},
  "geometry": {"coordinates":[-83.934498,34.059367],"type":"Point"}
}