{
  "type": "Feature",
  "properties": {
    "addr:full":"9756 Tara Blvd Jonesboro GA 30236",
    "addr:housenumber":"9756",
    "addr:postcode":"30236",
    "addr:street":"Tara Blvd",
    "iso:country":"US",
    "sg:address":"9756 Tara Blvd",
    "sg:city":"Jonesboro",
    "sg:classifiers":[
        {
            "category":"Manufacturing",
            "subcategory":"Metals",
            "type":"Manufacturing & Wholesale Goods"
        }
    ],
    "sg:phone":"+1 770 472 4452",
    "sg:postcode":"30236",
    "sg:province":"GA",
    "sg:tags":[
        "truss",
        "manufacturer"
    ],
    "wof:name":"Truss Works Inc",
    "wof:placetype":"venue"
},
  "geometry": {"coordinates":[-84.358594,33.512101],"type":"Point"}
}