{
  "type": "Feature",
  "properties": {
    "addr:full":"365 Swanson Rd Tyrone GA 30290",
    "addr:housenumber":"365",
    "addr:postcode":"30290",
    "addr:street":"Swanson Rd",
    "iso:country":"US",
    "sg:address":"365 Swanson Rd",
    "sg:city":"Tyrone",
    "sg:classifiers":[
        {
            "category":"Communications",
            "subcategory":"Radio Station",
            "type":"Services"
        }
    ],
    "sg:phone":"+1 770 486 8799",
    "sg:postcode":"30290",
    "sg:province":"GA",
    "sg:tags":[
        "broadcast"
    ],
    "wof:name":"USA Station Group of Ohio Inc",
    "wof:placetype":"venue"
},
  "geometry": {"coordinates":[-84.56899,33.484876],"type":"Point"}
}