{
  "type": "Feature",
  "properties": {
    "addr:full":"3398 E Whippoorwill Dr Duluth GA 30096",
    "addr:housenumber":"3398",
    "addr:postcode":"30096",
    "addr:street":"E Whippoorwill Dr",
    "iso:country":"US",
    "sg:address":"3398 E Whippoorwill Dr",
    "sg:city":"Duluth",
    "sg:classifiers":[
        {
            "category":"Health Services",
            "subcategory":"Doctor",
            "type":"Services"
        }
    ],
    "sg:phone":"+1 770 476 1619",
    "sg:postcode":"30096",
    "sg:province":"GA",
    "wof:name":"Mason Miles H III MD",
    "wof:placetype":"venue"
},
  "geometry": {"coordinates":[-84.169197,34.011398],"type":"Point"}
}