{
  "type": "Feature",
  "properties": {
    "iso:country":"US",
    "sg:address":"2345 Cobb Pkwy SE",
    "sg:city":"Smyrna",
    "sg:classifiers":[
        {
            "category":"Shopping",
            "subcategory":"Books",
            "type":"Retail Goods"
        }
    ],
    "sg:phone":"+1 770 850 0055",
    "sg:postcode":"30080",
    "sg:province":"GA",
    "sg:tags":[
        "bookstore"
    ],
    "wof:name":"Hidden Talent",
    "wof:placetype":"venue"
},
  "geometry": {"coordinates":[-84.47927799999999,33.894382],"type":"Point"}
}