{
  "type": "Feature",
  "properties": {
    "iso:country":"US",
    "sg:address":"3595 Napier Ave",
    "sg:city":"Macon",
    "sg:classifiers":[
        {
            "category":"Retail",
            "subcategory":"Repair Shop",
            "type":"Services"
        }
    ],
    "sg:phone":"+1 478 477 4676",
    "sg:postcode":"31204",
    "sg:province":"GA",
    "sg:tags":[
        "consumer",
        "television",
        "radio",
        "electron"
    ],
    "wof:name":"Windhams TV Sales & Service",
    "wof:placetype":"venue"
},
  "geometry": {"coordinates":[-83.68811700000001,32.84595],"type":"Point"}
}