{
  "type": "Feature",
  "properties": {
    "iso:country":"US",
    "sg:address":"5324 Five Forks Trickum Rd SW",
    "sg:city":"Lilburn",
    "sg:classifiers":[
        {
            "category":"Retail",
            "subcategory":"Veterinary Services",
            "type":"Services"
        }
    ],
    "sg:phone":"+1 770 921 2965",
    "sg:postcode":"30047",
    "sg:province":"GA",
    "sg:tags":[
        "hospital",
        "veterinarian",
        "clinic"
    ],
    "sg:website":"www.mpah.net",
    "wof:name":"Mountain Park Animal Hospital Lilburn",
    "wof:placetype":"venue"
},
  "geometry": {"coordinates":[-84.128114,33.843201],"type":"Point"}
}