{
  "type": "Feature",
  "properties": {
    "iso:country":"US",
    "sg:address":"7864 Fielder Rd",
    "sg:city":"Jonesboro",
    "sg:classifiers":[
        {
            "category":"Communications",
            "subcategory":"Film & Video Production",
            "type":"Services"
        }
    ],
    "sg:phone":"+1 770 478 2841",
    "sg:postcode":"30236",
    "sg:province":"GA",
    "sg:tags":[
        "motion"
    ],
    "wof:name":"J W Productions Inc",
    "wof:placetype":"venue"
},
  "geometry": {"coordinates":[-84.32139599999999,33.539046],"type":"Point"}
}