{
  "type": "Feature",
  "properties": {
    "addr:full":"1989 Terry Mill Rd SE Atlanta GA 30316",
    "addr:housenumber":"1989",
    "addr:postcode":"30316",
    "addr:street":"Terry Mill Rd Se",
    "iso:country":"US",
    "sg:address":"1989 Terry Mill Rd SE",
    "sg:city":"Atlanta",
    "sg:classifiers":[
        {
            "category":"Professional",
            "subcategory":"Business Services",
            "type":"Services"
        }
    ],
    "sg:phone":"+1 678 698 2733",
    "sg:postcode":"30316",
    "sg:province":"GA",
    "sg:tags":[
        "trade",
        "merchandise",
        "general"
    ],
    "wof:name":"Cache Enterprises",
    "wof:placetype":"venue"
},
  "geometry": {"coordinates":[-84.30994,33.73261],"type":"Point"}
}