{
  "type": "Feature",
  "properties": {
    "addr:full":"1224 Landmark Pl Gainesville GA 30501",
    "addr:housenumber":"1224",
    "addr:postcode":"30501",
    "addr:street":"Landmark Pl;Ga",
    "iso:country":"US",
    "sg:address":"1224 Landmark Pl",
    "sg:city":"Gainesville",
    "sg:classifiers":[
        {
            "category":"Organizations",
            "subcategory":"Religious Organization",
            "type":"Services"
        }
    ],
    "sg:phone":"+1 770 534 4079",
    "sg:postcode":"30501",
    "sg:province":"GA",
    "wof:name":"Good News Full Gospel Baptist",
    "wof:placetype":"venue"
},
  "geometry": {"coordinates":[-83.801445,34.29172],"type":"Point"}
}