{
  "type": "Feature",
  "properties": {
    "iso:country":"US",
    "sg:address":"5007 Pineview Ter",
    "sg:city":"Fayetteville",
    "sg:classifiers":[
        {
            "category":"Shopping",
            "subcategory":"Hobbies, Toys, & Games",
            "type":"Retail Goods"
        },
        {
            "category":"Shopping",
            "subcategory":"Crafts & Fabrics",
            "type":"Retail Goods"
        }
    ],
    "sg:phone":"+1 770 461 3376",
    "sg:postcode":"30214",
    "sg:province":"GA",
    "sg:tags":[
        "shop",
        "hobby",
        "model",
        "supply"
    ],
    "wof:name":"Busybee Woodcrafts",
    "wof:placetype":"venue"
},
  "geometry": {"coordinates":[-84.4907,33.455526],"type":"Point"}
}