{
  "type": "Feature",
  "properties": {
    "addr:full":"170 Central Ave Trion GA 30753",
    "addr:housenumber":"170",
    "addr:postcode":"30753",
    "addr:street":"Central Ave",
    "iso:country":"US",
    "sg:address":"170 Central Ave",
    "sg:city":"Trion",
    "sg:classifiers":[
        {
            "category":"Restaurant",
            "type":"Food & Drink"
        }
    ],
    "sg:phone":"+1 706 734 7768",
    "sg:postcode":"30753",
    "sg:province":"GA",
    "wof:name":"Mornin' Glory",
    "wof:placetype":"venue"
},
  "geometry": {"coordinates":[-85.30765700000001,34.533235],"type":"Point"}
}