{
  "type": "Feature",
  "properties": {
    "addr:full":"4261 Saint Marys Rd Columbus GA 31907",
    "addr:housenumber":"4261",
    "addr:postcode":"31907",
    "addr:street":"Saint Marys Rd",
    "iso:country":"US",
    "sg:address":"4261 Saint Marys Rd",
    "sg:city":"Columbus",
    "sg:classifiers":[
        {
            "category":"Social Services",
            "subcategory":"Child Care",
            "type":"Services"
        }
    ],
    "sg:phone":"+1 706 687 8050",
    "sg:postcode":"31907",
    "sg:province":"GA",
    "wof:name":"Kiddie Kollege Learning Ctr",
    "wof:placetype":"venue"
},
  "geometry": {"coordinates":[-84.924134,32.445447],"type":"Point"}
}