{
  "type": "Feature",
  "properties": {
    "addr:full":"240 Ketton Downs Duluth GA 30097",
    "addr:housenumber":"240",
    "addr:postcode":"30097",
    "addr:street":"Ketton Downs",
    "iso:country":"US",
    "sg:address":"240 Ketton Downs",
    "sg:city":"Duluth",
    "sg:classifiers":[
        {
            "category":"Manufacturing",
            "subcategory":"Rubber & Plastics",
            "type":"Manufacturing & Wholesale Goods"
        }
    ],
    "sg:phone":"+1 770 813 1807",
    "sg:postcode":"30097",
    "sg:province":"GA",
    "sg:tags":[
        "product"
    ],
    "sg:website":"http://www.crowncork.com",
    "wof:name":"Crown Closures",
    "wof:placetype":"venue"
},
  "geometry": {"coordinates":[-84.150454,34.045946],"type":"Point"}
}