{
  "type": "Feature",
  "properties": {
    "addr:full":"577 Seminole Dr Marietta GA 30060",
    "addr:housenumber":"577",
    "addr:postcode":"30060",
    "addr:street":"Seminole Dr",
    "iso:country":"US",
    "sg:address":"577 Seminole Dr",
    "sg:city":"Marietta",
    "sg:classifiers":[
        {
            "category":"Professional",
            "subcategory":"Accounting & Tax Preparation",
            "type":"Services"
        },
        {
            "category":"Professional",
            "subcategory":"Employment Agencies",
            "type":"Services"
        }
    ],
    "sg:phone":"+1 770 499 0398",
    "sg:postcode":"30060",
    "sg:province":"GA",
    "sg:tags":[
        "help",
        "billing",
        "supply"
    ],
    "sg:website":"www.mymedicaldirector.com",
    "wof:name":"Medical Director Solution Plus",
    "wof:placetype":"venue"
},
  "geometry": {"coordinates":[-84.533205,33.964912],"type":"Point"}
}