{
  "type": "Feature",
  "properties": {
    "iso:country":"US",
    "sg:address":"804 Grove Ave",
    "sg:city":"Waycross",
    "sg:classifiers":[
        {
            "category":"Government",
            "subcategory":"Jail",
            "type":"Public Place"
        }
    ],
    "sg:phone":"+1 912 287 4323",
    "sg:postcode":"31501",
    "sg:province":"GA",
    "sg:tags":[
        "county",
        "govt",
        "institution"
    ],
    "wof:name":"Ware County Jail",
    "wof:placetype":"venue"
},
  "geometry": {"coordinates":[-82.355411,31.215732],"type":"Point"}
}