{
  "type": "Feature",
  "properties": {
    "addr:full":"36 Arnoldsville Rd Crawford GA 30630",
    "addr:housenumber":"36",
    "addr:postcode":"30630",
    "addr:street":"Arnoldsville Rd",
    "iso:country":"US",
    "sg:address":"36 Arnoldsville Rd",
    "sg:city":"Crawford",
    "sg:classifiers":[
        {
            "category":"Farming",
            "subcategory":"Farm",
            "type":"Manufacturing & Wholesale Goods"
        }
    ],
    "sg:phone":"+1 706 742 9216",
    "sg:postcode":"30630",
    "sg:province":"GA",
    "wof:name":"Shealy Pork Inc",
    "wof:placetype":"venue"
},
  "geometry": {"coordinates":[-83.208704,33.895574],"type":"Point"}
}