{
  "type": "Feature",
  "properties": {
    "iso:country":"US",
    "sg:address":"1676 Mission Rd SW",
    "sg:city":"Cartersville",
    "sg:classifiers":[
        {
            "category":"Professional",
            "subcategory":"Engineering",
            "type":"Services"
        }
    ],
    "sg:phone":"+1 770 387 0270",
    "sg:postcode":"30120",
    "sg:province":"GA",
    "wof:name":"Aaron C Tatum Jr",
    "wof:placetype":"venue"
},
  "geometry": {"coordinates":[-84.912567,34.189918],"type":"Point"}
}