{
  "type": "Feature",
  "properties": {
    "addr:full":"1829 Gordon Hwy Augusta GA 30904",
    "addr:housenumber":"1829",
    "addr:postcode":"30904",
    "addr:street":"Gordon Hwy",
    "iso:country":"US",
    "sg:address":"1829 Gordon Hwy",
    "sg:city":"Augusta",
    "sg:classifiers":[
        {
            "category":"Wholesale",
            "subcategory":"Petroleum",
            "type":"Manufacturing & Wholesale Goods"
        }
    ],
    "sg:phone":"+1 706 738 7782",
    "sg:postcode":"30904",
    "sg:province":"GA",
    "sg:tags":[
        "bulk",
        "station",
        "gas"
    ],
    "wof:name":"Bennett Gas Co Inc",
    "wof:placetype":"venue"
},
  "geometry": {"coordinates":[-82.031527,33.447395],"type":"Point"}
}