{
  "type": "Feature",
  "properties": {
    "addr:full":"621 Broadway Ave Columbus GA 31901",
    "addr:housenumber":"621",
    "addr:postcode":"31901",
    "addr:street":"Broadway Ave",
    "iso:country":"US",
    "sg:address":"621 Broadway Ave",
    "sg:city":"Columbus",
    "sg:classifiers":[
        {
            "category":"Professional",
            "subcategory":"Secretarial Services",
            "type":"Services"
        }
    ],
    "sg:phone":"+1 706 327 3618",
    "sg:postcode":"31901",
    "sg:province":"GA",
    "sg:tags":[
        "convention",
        "court",
        "reporter"
    ],
    "wof:name":"Anderson Court Reporting",
    "wof:placetype":"venue"
},
  "geometry": {"coordinates":[-84.99332,32.458726],"type":"Point"}
}