{
  "type": "Feature",
  "properties": {
    "iso:country":"US",
    "sg:address":"3550 Broad St",
    "sg:city":"Atlanta",
    "sg:classifiers":[
        {
            "category":"Professional",
            "type":"Services"
        }
    ],
    "sg:phone":"+1 770 615 3919",
    "sg:postcode":"30341",
    "sg:province":"GA",
    "sg:tags":[
        "establishment"
    ],
    "wof:name":"Darkroom Inc",
    "wof:placetype":"venue"
},
  "geometry": {"coordinates":[-84.298367,33.895558],"type":"Point"}
}