{
  "type": "Feature",
  "properties": {
    "addr:full":"1200 4th Ave Lagrange GA 30240",
    "addr:housenumber":"1200",
    "addr:postcode":"30240",
    "addr:street":"4Th Ave",
    "iso:country":"US",
    "sg:address":"1200 4th Ave",
    "sg:city":"Lagrange",
    "sg:classifiers":[
        {
            "category":"Social Services",
            "type":"Services"
        }
    ],
    "sg:phone":"+1 706 298 2434",
    "sg:postcode":"30240",
    "sg:province":"GA",
    "sg:tags":[
        "organization",
        "welfare"
    ],
    "wof:name":"Big Brothers & Big Sisters",
    "wof:placetype":"venue"
},
  "geometry": {"coordinates":[-85.04821099999999,33.020623],"type":"Point"}
}