{
  "type": "Feature",
  "properties": {
    "iso:country":"US",
    "sg:address":"6241 Pine Grove Rd",
    "sg:city":"Riverdale",
    "sg:classifiers":[
        {
            "category":"Professional",
            "type":"Services"
        }
    ],
    "sg:phone":"+1 770 994 8027",
    "sg:postcode":"30274",
    "sg:province":"GA",
    "wof:name":"Sobriety",
    "wof:placetype":"venue"
},
  "geometry": {"coordinates":[-84.404061,33.587869],"type":"Point"}
}