{
  "type": "Feature",
  "properties": {
    "addr:full":"1935 Alison Ct SW Atlanta GA 30311",
    "addr:housenumber":"1935",
    "addr:postcode":"30311",
    "addr:street":"Alison Ct Sw",
    "iso:country":"US",
    "sg:address":"1935 Alison Ct SW",
    "sg:city":"Atlanta",
    "sg:classifiers":[
        {
            "category":"Social Services",
            "subcategory":"Child Care",
            "type":"Services"
        }
    ],
    "sg:phone":"+1 404 761 4800",
    "sg:postcode":"30311",
    "sg:province":"GA",
    "wof:name":"Games Childcare",
    "wof:placetype":"venue"
},
  "geometry": {"coordinates":[-84.45217700000001,33.700695],"type":"Point"}
}