{
  "type": "Feature",
  "properties": {
    "iso:country":"US",
    "sg:address":"550 S Zetterower Ave",
    "sg:city":"Statesboro",
    "sg:classifiers":[
        {
            "category":"Restaurant",
            "type":"Food & Drink"
        }
    ],
    "sg:phone":"+1 912 489 6609",
    "sg:postcode":"30458",
    "sg:province":"GA",
    "sg:tags":[
        "seafood"
    ],
    "wof:name":"Eagle Seafood",
    "wof:placetype":"venue"
},
  "geometry": {"coordinates":[-81.781673,32.43539],"type":"Point"}
}