{
  "type": "Feature",
  "properties": {
    "addr:full":"801 Pope Lake Rd Tallapoosa GA 30113",
    "addr:housenumber":"801",
    "addr:postcode":"30113",
    "addr:street":"Pope Lake Rd",
    "iso:country":"US",
    "sg:address":"801 Pope Lake Rd",
    "sg:city":"Tallapoosa",
    "sg:classifiers":[
        {
            "category":"Building & Trades",
            "subcategory":"Construction",
            "type":"Services"
        }
    ],
    "sg:phone":"+1 770 574 7246",
    "sg:postcode":"30113",
    "sg:province":"GA",
    "sg:tags":[
        "carpentry",
        "contractor"
    ],
    "wof:name":"Johnson Cabinet Shop",
    "wof:placetype":"venue"
},
  "geometry": {"coordinates":[-85.31721,33.8455],"type":"Point"}
}