{
  "type": "Feature",
  "properties": {
    "addr:full":"81 River St East Ellijay GA 30540",
    "addr:housenumber":"81",
    "addr:postcode":"30540",
    "addr:street":"River St",
    "iso:country":"US",
    "sg:address":"81 River St",
    "sg:city":"East Ellijay",
    "sg:classifiers":[
        {
            "category":"Home & Garden",
            "subcategory":"Garden Supply",
            "type":"Retail Goods"
        }
    ],
    "sg:phone":"+1 706 273 2198",
    "sg:postcode":"30540",
    "sg:province":"GA",
    "sg:tags":[
        "lawn",
        "mower"
    ],
    "wof:name":"Papa's Small Engine Svc & Rpr",
    "wof:placetype":"venue"
},
  "geometry": {"coordinates":[-84.479389,34.692918],"type":"Point"}
}