{
  "type": "Feature",
  "properties": {
    "addr:full":"1510 Ellsworth Industrial Dr NW Atlanta GA 30318",
    "addr:housenumber":"1510",
    "addr:postcode":"30318",
    "addr:street":"Ellsworth Industrial Dr Nw",
    "iso:country":"US",
    "sg:address":"1510 Ellsworth Industrial Dr NW",
    "sg:city":"Atlanta",
    "sg:classifiers":[
        {
            "category":"Home & Garden",
            "subcategory":"Carpets & Floor Coverings",
            "type":"Retail Goods"
        }
    ],
    "sg:phone":"+1 404 352 0072",
    "sg:postcode":"30318",
    "sg:province":"GA",
    "sg:tags":[
        "rug"
    ],
    "wof:name":"World of Rugs Inc",
    "wof:placetype":"venue"
},
  "geometry": {"coordinates":[-84.427098,33.79787],"type":"Point"}
}