{
  "type": "Feature",
  "properties": {
    "iso:country":"US",
    "sg:address":"7235 Wheeler Trl",
    "sg:city":"Lithonia",
    "sg:classifiers":[
        {
            "category":"Shopping",
            "subcategory":"Clothing, Apparel, & Fashions",
            "type":"Retail Goods"
        }
    ],
    "sg:phone":"+1 770 482 4759",
    "sg:postcode":"30058",
    "sg:province":"GA",
    "wof:name":"PTZ Designs",
    "wof:placetype":"venue"
},
  "geometry": {"coordinates":[-84.093416,33.762258],"type":"Point"}
}