{
  "type": "Feature",
  "properties": {
    "iso:country":"US",
    "sg:address":"190 Treadwell Rd",
    "sg:city":"Chatsworth",
    "sg:classifiers":[
        {
            "category":"Manufacturing",
            "subcategory":"Textiles",
            "type":"Manufacturing & Wholesale Goods"
        }
    ],
    "sg:phone":"+1 706 695 1085",
    "sg:postcode":"30705",
    "sg:province":"GA",
    "sg:tags":[
        "rug",
        "carpet"
    ],
    "wof:name":"American National Carpet",
    "wof:placetype":"venue"
},
  "geometry": {"coordinates":[-84.799694,34.781131],"type":"Point"}
}