{
  "type": "Feature",
  "properties": {
    "addr:full":"3310 Atlanta Rd SE Smyrna GA 30080",
    "addr:housenumber":"3310",
    "addr:postcode":"30080",
    "addr:street":"Atlanta Rd Se",
    "iso:country":"US",
    "sg:address":"3310 Atlanta Rd SE",
    "sg:city":"Smyrna",
    "sg:classifiers":[
        {
            "category":"Professional",
            "subcategory":"Accounting & Tax Preparation",
            "type":"Services"
        }
    ],
    "sg:phone":"+1 770 434 4040",
    "sg:postcode":"30080",
    "sg:province":"GA",
    "wof:name":"James H Ray CPA Cfp Pfs",
    "wof:placetype":"venue"
},
  "geometry": {"coordinates":[-84.497741,33.872041],"type":"Point"}
}