{
  "type": "Feature",
  "properties": {
    "addr:full":"870 Bear Creek Rd Lavonia GA 30553",
    "addr:housenumber":"870",
    "addr:postcode":"30553",
    "addr:street":"Bear Creek Rd",
    "iso:country":"US",
    "sg:address":"870 Bear Creek Rd",
    "sg:city":"Lavonia",
    "sg:classifiers":[
        {
            "category":"Organizations",
            "subcategory":"Membership Organization",
            "type":"Services"
        }
    ],
    "sg:phone":"+1 706 356 5363",
    "sg:postcode":"30553",
    "sg:province":"GA",
    "wof:name":"North East GA Animal Shelter",
    "wof:placetype":"venue"
},
  "geometry": {"coordinates":[-83.11166900000001,34.429134],"type":"Point"}
}