{
  "type": "Feature",
  "properties": {
    "iso:country":"US",
    "sg:address":"1040 Richwood Trl",
    "sg:city":"Bogart",
    "sg:classifiers":[
        {
            "category":"Real Estate",
            "subcategory":"Developer",
            "type":"Services"
        }
    ],
    "sg:phone":"+1 706 769 8342",
    "sg:postcode":"30622",
    "sg:province":"GA",
    "wof:name":"Homeland Developments Inc",
    "wof:placetype":"venue"
},
  "geometry": {"coordinates":[-83.50415099999999,33.882715],"type":"Point"}
}