{
  "type": "Feature",
  "properties": {
    "iso:country":"US",
    "sg:address":"115 Gilbert Dr",
    "sg:city":"Fort Oglethorpe",
    "sg:classifiers":[
        {
            "category":"Building & Trades",
            "subcategory":"Construction",
            "type":"Services"
        }
    ],
    "sg:phone":"+1 706 866 4541",
    "sg:postcode":"30742",
    "sg:province":"GA",
    "sg:tags":[
        "house"
    ],
    "wof:name":"Db Construction",
    "wof:placetype":"venue"
},
  "geometry": {"coordinates":[-85.25859199999999,34.952284],"type":"Point"}
}