{
  "type": "Feature",
  "properties": {
    "addr:full":"4062 Harmony Grove Church Rd Dallas GA 30132",
    "addr:housenumber":"4062",
    "addr:postcode":"30132",
    "addr:street":"Harmony Grove Church Rd",
    "iso:country":"US",
    "sg:address":"4062 Harmony Grove Church Rd",
    "sg:city":"Dallas",
    "sg:classifiers":[
        {
            "category":"Professional",
            "type":"Services"
        }
    ],
    "sg:phone":"+1 770 445 0066",
    "sg:postcode":"30132",
    "sg:province":"GA",
    "wof:name":"Davis Pick Up Service",
    "wof:placetype":"venue"
},
  "geometry": {"coordinates":[-84.81173699999999,34.064176],"type":"Point"}
}