{
  "type": "Feature",
  "properties": {
    "addr:full":"55 Kelsey Way Palmetto GA 30268",
    "addr:housenumber":"55",
    "addr:postcode":"30268",
    "addr:street":"Kelsey Way",
    "iso:country":"US",
    "sg:address":"55 Kelsey Way",
    "sg:city":"Palmetto",
    "sg:classifiers":[
        {
            "category":"Building & Trades",
            "subcategory":"Cleaning & Sanitation",
            "type":"Services"
        }
    ],
    "sg:phone":"+1 770 463 5779",
    "sg:postcode":"30268",
    "sg:province":"GA",
    "sg:tags":[
        "cleaning-industrial",
        "contractor"
    ],
    "wof:name":"Charlestons Cleaning Svc",
    "wof:placetype":"venue"
},
  "geometry": {"coordinates":[-84.709997,33.507227],"type":"Point"}
}