{
  "type": "Feature",
  "properties": {
    "addr:full":"3200 Cobb Galleria Suite 200 Atlanta GA 30339",
    "addr:housenumber":"3200",
    "addr:postcode":"30339",
    "addr:street":"Cobb Galleria Suite 200",
    "iso:country":"US",
    "sg:address":"3200 Cobb Galleria Suite 200",
    "sg:city":"Atlanta",
    "sg:classifiers":[
        {
            "category":"Building & Trades",
            "subcategory":"Construction",
            "type":"Services"
        }
    ],
    "sg:phone":"+1 404 935 6507",
    "sg:postcode":"30339",
    "sg:province":"GA",
    "sg:tags":[
        "contractor"
    ],
    "sg:website":"insulationinatlanta.info",
    "wof:name":"Energy Defenders",
    "wof:placetype":"venue"
},
  "geometry": {"coordinates":[-84.46003899999999,33.884687],"type":"Point"}
}