{
  "type": "Feature",
  "properties": {
    "iso:country":"US",
    "sg:address":"215 W Gordon St",
    "sg:city":"Dalton",
    "sg:classifiers":[
        {
            "category":"Professional",
            "subcategory":"Lawyer & Legal Services",
            "type":"Services"
        }
    ],
    "sg:phone":"+1 706 278 2488",
    "sg:postcode":"30720",
    "sg:province":"GA",
    "sg:tags":[
        "practice",
        "attorney",
        "criminal",
        "law"
    ],
    "sg:website":"http://www.hinmanlaw.com",
    "wof:name":"Hinman Ralph M",
    "wof:placetype":"venue"
},
  "geometry": {"coordinates":[-84.969425,34.770723],"type":"Point"}
}