{
  "type": "Feature",
  "properties": {
    "iso:country":"US",
    "sg:address":"1117 Perimeter Ctr W",
    "sg:city":"Atlanta",
    "sg:classifiers":[
        {
            "category":"Professional",
            "subcategory":"Employment Agencies",
            "type":"Services"
        }
    ],
    "sg:phone":"+1 770 399 3131",
    "sg:postcode":"30338",
    "sg:province":"GA",
    "sg:tags":[
        "opportunity"
    ],
    "wof:name":"Paragon Search Group",
    "wof:placetype":"venue"
},
  "geometry": {"coordinates":[-84.348983,33.93021],"type":"Point"}
}