{
  "type": "Feature",
  "properties": {
    "addr:full":"6401 Whitesville Rd Columbus GA 31904",
    "addr:housenumber":"6401",
    "addr:postcode":"31904",
    "addr:street":"Whitesville Rd",
    "iso:country":"US",
    "sg:address":"6401 Whitesville Rd",
    "sg:city":"Columbus",
    "sg:classifiers":[
        {
            "category":"Shopping",
            "subcategory":"Department Store",
            "type":"Retail Goods"
        }
    ],
    "sg:phone":"+1 706 320 1213",
    "sg:postcode":"31904",
    "sg:province":"GA",
    "wof:name":"Talbots",
    "wof:placetype":"venue"
},
  "geometry": {"coordinates":[-84.96626000000001,32.538482],"type":"Point"}
}