{
  "type": "Feature",
  "properties": {
    "addr:full":"6732 Highway 85 Riverdale GA 30274",
    "addr:housenumber":"6732",
    "addr:postcode":"30274",
    "addr:street":"Highway 85",
    "iso:country":"US",
    "sg:address":"6732 Highway 85",
    "sg:city":"Riverdale",
    "sg:classifiers":[
        {
            "category":"Arena",
            "subcategory":"Sports Club",
            "type":"Entertainment"
        }
    ],
    "sg:phone":"+1 678 709 3478",
    "sg:postcode":"30274",
    "sg:province":"GA",
    "sg:tags":[
        "martial art"
    ],
    "wof:name":"Asia Tic Marshall Arts",
    "wof:placetype":"venue"
},
  "geometry": {"coordinates":[-84.41280399999999,33.571301],"type":"Point"}
}