{
  "type": "Feature",
  "properties": {
    "addr:full":"2700 Midway Rd Lizella GA 31052",
    "addr:housenumber":"2700",
    "addr:postcode":"31052",
    "addr:street":"Midway Rd",
    "iso:country":"US",
    "sg:address":"2700 Midway Rd",
    "sg:city":"Lizella",
    "sg:classifiers":[
        {
            "category":"Real Estate",
            "subcategory":"Developer",
            "type":"Services"
        }
    ],
    "sg:phone":"+1 478 935 3070",
    "sg:postcode":"31052",
    "sg:province":"GA",
    "sg:tags":[
        "cemetery"
    ],
    "wof:name":"Cherry Blossom Cemetery",
    "wof:placetype":"venue"
},
  "geometry": {"coordinates":[-83.851665,32.819442],"type":"Point"}
}