{
  "type": "Feature",
  "properties": {
    "addr:full":"1350 Union Hill Rd Alpharetta GA 30004",
    "addr:housenumber":"1350",
    "addr:postcode":"30004",
    "addr:street":"Union Hill Rd",
    "iso:country":"US",
    "sg:address":"1350 Union Hill Rd",
    "sg:city":"Alpharetta",
    "sg:classifiers":[
        {
            "category":"Professional",
            "subcategory":"Credit Reporting & Collection",
            "type":"Services"
        }
    ],
    "sg:phone":"+1 770 442 8771",
    "sg:postcode":"30004",
    "sg:province":"GA",
    "wof:name":"Norman and Associates Inc",
    "wof:placetype":"venue"
},
  "geometry": {"coordinates":[-84.236801,34.114508],"type":"Point"}
}