{
  "type": "Feature",
  "properties": {
    "iso:country":"US",
    "sg:address":"4449 Dunmovin Dr",
    "sg:city":"Kennesaw",
    "sg:classifiers":[
        {
            "category":"Professional",
            "subcategory":"Computer Services",
            "type":"Services"
        }
    ],
    "sg:phone":"+1 770 924 1880",
    "sg:postcode":"30144",
    "sg:province":"GA",
    "wof:name":"Robert Blemer",
    "wof:placetype":"venue"
},
  "geometry": {"coordinates":[-84.564134,34.055032],"type":"Point"}
}