{
  "type": "Feature",
  "properties": {
    "addr:full":"460 Tanger Dr Commerce GA 30529",
    "addr:housenumber":"460",
    "addr:postcode":"30529",
    "addr:street":"Tanger Dr",
    "iso:country":"US",
    "sg:address":"460 Tanger Dr",
    "sg:city":"Commerce",
    "sg:classifiers":[
        {
            "category":"Restaurant",
            "type":"Food & Drink"
        }
    ],
    "sg:menulink":"http://www.allmenus.com/ga/maysville/80881-papa-johns-pizza/menu/",
    "sg:phone":"+1 706 335 2050",
    "sg:postcode":"30529",
    "sg:province":"GA",
    "sg:tags":[
        "american",
        "pizza"
    ],
    "wof:name":"Papa John's Pizza",
    "wof:placetype":"venue"
},
  "geometry": {"coordinates":[-83.468906,34.257158],"type":"Point"}
}