{
  "type": "Feature",
  "properties": {
    "addr:full":"3036 Katherine Valley Rd Decatur GA 30032",
    "addr:housenumber":"3036",
    "addr:postcode":"30032",
    "addr:street":"Katherine Valley Rd",
    "iso:country":"US",
    "sg:address":"3036 Katherine Valley Rd",
    "sg:city":"Decatur",
    "sg:classifiers":[
        {
            "category":"Building & Trades",
            "subcategory":"Construction",
            "type":"Services"
        }
    ],
    "sg:phone":"+1 404 284 5906",
    "sg:postcode":"30032",
    "sg:province":"GA",
    "sg:tags":[
        "home",
        "improvement"
    ],
    "wof:name":"William Scott Home Improvement",
    "wof:placetype":"venue"
},
  "geometry": {"coordinates":[-84.26768800000001,33.728239],"type":"Point"}
}