{
  "type": "Feature",
  "properties": {
    "addr:full":"405 W Main St Thomaston GA 30286",
    "addr:housenumber":"405",
    "addr:postcode":"30286",
    "addr:street":"W Main St",
    "iso:country":"US",
    "sg:address":"405 W Main St",
    "sg:city":"Thomaston",
    "sg:classifiers":[
        {
            "category":"Personal",
            "subcategory":"Beauty Salon",
            "type":"Services"
        }
    ],
    "sg:phone":"+1 706 647 1363",
    "sg:postcode":"30286",
    "sg:province":"GA",
    "sg:tags":[
        "shop"
    ],
    "wof:name":"Hair Hut",
    "wof:placetype":"venue"
},
  "geometry": {"coordinates":[-84.331762,32.889083],"type":"Point"}
}