{
  "type": "Feature",
  "properties": {
    "iso:country":"US",
    "sg:address":"1934 S Main St",
    "sg:city":"Moultrie",
    "sg:classifiers":[
        {
            "category":"Health Services",
            "subcategory":"Chiropractor",
            "type":"Services"
        }
    ],
    "sg:phone":"+1 229 985 1424",
    "sg:postcode":"31768",
    "sg:province":"GA",
    "wof:name":"Foland Family Chiropractic",
    "wof:placetype":"venue"
},
  "geometry": {"coordinates":[-83.788929,31.150378],"type":"Point"}
}