{
  "type": "Feature",
  "properties": {
    "iso:country":"US",
    "sg:address":"4387 Sandy Ridge Pl",
    "sg:city":"Augusta",
    "sg:classifiers":[
        {
            "category":"Professional",
            "subcategory":"Management & Consulting",
            "type":"Services"
        }
    ],
    "sg:phone":"+1 706 868 5515",
    "sg:postcode":"30909",
    "sg:province":"GA",
    "sg:tags":[
        "operator",
        "trucking"
    ],
    "wof:name":"K Ashe & Company Inc",
    "wof:placetype":"venue"
},
  "geometry": {"coordinates":[-82.12255399999999,33.48187],"type":"Point"}
}