{
  "type": "Feature",
  "properties": {
    "addr:full":"1130 Haynes Creek Dr NE Conyers GA 30012",
    "addr:housenumber":"1130",
    "addr:postcode":"30012",
    "addr:street":"Haynes Creek Dr Ne",
    "iso:country":"US",
    "sg:address":"1130 Haynes Creek Dr NE",
    "sg:city":"Conyers",
    "sg:classifiers":[
        {
            "category":"Professional",
            "type":"Services"
        }
    ],
    "sg:phone":"+1 770 760 0578",
    "sg:postcode":"30012",
    "sg:province":"GA",
    "sg:tags":[
        "used",
        "merchandise"
    ],
    "wof:name":"W E Coombs",
    "wof:placetype":"venue"
},
  "geometry": {"coordinates":[-83.977853,33.761709],"type":"Point"}
}