{
  "type": "Feature",
  "properties": {
    "addr:full":"1922 Preston Dr Columbus GA 31906",
    "addr:housenumber":"1922",
    "addr:postcode":"31906",
    "addr:street":"Preston Dr",
    "iso:country":"US",
    "sg:address":"1922 Preston Dr",
    "sg:city":"Columbus",
    "sg:classifiers":[
        {
            "category":"Real Estate",
            "subcategory":"Real Estate Agent",
            "type":"Services"
        }
    ],
    "sg:phone":"+1 706 660 9755",
    "sg:postcode":"31906",
    "sg:province":"GA",
    "wof:name":"Premier Realtors Columbus L",
    "wof:placetype":"venue"
},
  "geometry": {"coordinates":[-84.950964,32.480044],"type":"Point"}
}