{
  "type": "Feature",
  "properties": {
    "addr:full":"1060 Eagles Landing Pkwy Stockbridge GA 30281",
    "addr:housenumber":"1060",
    "addr:postcode":"30281",
    "addr:street":"Eagles Landing Pkwy",
    "iso:country":"US",
    "sg:address":"1060 Eagles Landing Pkwy",
    "sg:city":"Stockbridge",
    "sg:classifiers":[
        {
            "category":"Shopping",
            "subcategory":"Clothing, Apparel, & Fashions",
            "type":"Retail Goods"
        },
        {
            "category":"Shopping",
            "type":"Retail Goods"
        }
    ],
    "sg:phone":"+1 770 389 9700",
    "sg:postcode":"30281",
    "sg:province":"GA",
    "sg:tags":[
        "item",
        "boutique",
        "clothing",
        "store"
    ],
    "wof:name":"High Cotton Boutique",
    "wof:placetype":"venue"
},
  "geometry": {"coordinates":[-84.223445,33.511076],"type":"Point"}
}