{
  "type": "Feature",
  "properties": {
    "addr:full":"478 Forkwood Way Powder Springs GA 30127",
    "addr:housenumber":"478",
    "addr:postcode":"30127",
    "addr:street":"Forkwood Way",
    "iso:country":"US",
    "sg:address":"478 Forkwood Way",
    "sg:city":"Powder Springs",
    "sg:classifiers":[
        {
            "category":"Professional",
            "subcategory":"Business Services",
            "type":"Services"
        }
    ],
    "sg:phone":"+1 770 943 4290",
    "sg:postcode":"30127",
    "sg:province":"GA",
    "wof:name":"Rm Thorpe Associates Inc",
    "wof:placetype":"venue"
},
  "geometry": {"coordinates":[-84.738342,33.854449],"type":"Point"}
}