{
  "type": "Feature",
  "properties": {
    "addr:full":"5111 Spring St Flowery Branch GA 30542",
    "addr:housenumber":"5111",
    "addr:postcode":"30542",
    "addr:street":"Spring St",
    "iso:country":"US",
    "sg:address":"5111 Spring St",
    "sg:city":"Flowery Branch",
    "sg:classifiers":[
        {
            "category":"Social Services",
            "subcategory":"Child Care",
            "type":"Services"
        }
    ],
    "sg:phone":"+1 770 967 2572",
    "sg:postcode":"30542",
    "sg:province":"GA",
    "sg:tags":[
        "day"
    ],
    "wof:name":"Child Care Network Inc",
    "wof:placetype":"venue"
},
  "geometry": {"coordinates":[-83.922997,34.1861],"type":"Point"}
}