{
  "type": "Feature",
  "properties": {
    "iso:country":"US",
    "sg:address":"590 Firestone Ct",
    "sg:city":"Augusta",
    "sg:classifiers":[
        {
            "category":"Restaurant",
            "type":"Food & Drink"
        }
    ],
    "sg:phone":"+1 706 868 9553",
    "sg:postcode":"30907",
    "sg:province":"GA",
    "sg:tags":[
        "eating"
    ],
    "wof:name":"Cicis Pizza",
    "wof:placetype":"venue"
},
  "geometry": {"coordinates":[-82.06731000000001,33.538519],"type":"Point"}
}