{
  "type": "Feature",
  "properties": {
    "iso:country":"US",
    "sg:address":"5010 Flint Hill Rd",
    "sg:city":"Austell",
    "sg:classifiers":[
        {
            "category":"Manufacturing",
            "subcategory":"Tools & Machinery",
            "type":"Manufacturing & Wholesale Goods"
        }
    ],
    "sg:phone":"+1 770 944 1574",
    "sg:postcode":"30106",
    "sg:province":"GA",
    "sg:tags":[
        "disposal",
        "garbage",
        "equipment"
    ],
    "wof:name":"Mayo Co",
    "wof:placetype":"venue"
},
  "geometry": {"coordinates":[-84.623294,33.831635],"type":"Point"}
}