{
  "type": "Feature",
  "properties": {
    "iso:country":"US",
    "sg:address":"1905 Lumpkin Rd",
    "sg:city":"Augusta",
    "sg:classifiers":[
        {
            "category":"Building & Trades",
            "subcategory":"Construction",
            "type":"Services"
        }
    ],
    "sg:phone":"+1 706 833 3968",
    "sg:postcode":"30906",
    "sg:province":"GA",
    "sg:tags":[
        "general",
        "contractor"
    ],
    "wof:name":"Mid Dixie General Contractor",
    "wof:placetype":"venue"
},
  "geometry": {"coordinates":[-82.01126600000001,33.41738],"type":"Point"}
}