{
  "type": "Feature",
  "properties": {
    "addr:full":"4151 Memorial Dr Decatur GA 30032",
    "addr:housenumber":"4151",
    "addr:postcode":"30032",
    "addr:street":"Memorial Dr",
    "iso:country":"US",
    "sg:address":"4151 Memorial Dr",
    "sg:city":"Decatur",
    "sg:classifiers":[
        {
            "category":"Health Services",
            "subcategory":"Clinic",
            "type":"Services"
        }
    ],
    "sg:phone":"+1 404 296 9333",
    "sg:postcode":"30032",
    "sg:province":"GA",
    "sg:tags":[
        "counseling",
        "mental"
    ],
    "wof:name":"Royal-Bryant Psychological Services Inc",
    "wof:placetype":"venue"
},
  "geometry": {"coordinates":[-84.25140399999999,33.7687],"type":"Point"}
}