{
  "type": "Feature",
  "properties": {
    "addr:full":"1726 Montreal Cir Tucker GA 30084",
    "addr:housenumber":"1726",
    "addr:postcode":"30084",
    "addr:street":"Montreal Cir",
    "iso:country":"US",
    "sg:address":"1726 Montreal Cir",
    "sg:city":"Tucker",
    "sg:classifiers":[
        {
            "category":"Travel",
            "subcategory":"Hotels & Motels",
            "type":"Entertainment"
        }
    ],
    "sg:phone":"+1 770 270 1180",
    "sg:postcode":"30084",
    "sg:province":"GA",
    "wof:name":"Hospitality International Inc",
    "wof:placetype":"venue"
},
  "geometry": {"coordinates":[-84.25129699999999,33.8335],"type":"Point"}
}