{
  "type": "Feature",
  "properties": {
    "iso:country":"US",
    "sg:address":"3529 Northside Pkwy NW",
    "sg:city":"Atlanta",
    "sg:classifiers":[
        {
            "category":"Home & Garden",
            "subcategory":"Home Furnishings",
            "type":"Retail Goods"
        }
    ],
    "sg:phone":"+1 404 231 2160",
    "sg:postcode":"30327",
    "sg:province":"GA",
    "wof:name":"Aarons Lamp & Shade Center",
    "wof:placetype":"venue"
},
  "geometry": {"coordinates":[-84.430398,33.851157],"type":"Point"}
}