{
  "type": "Feature",
  "properties": {
    "iso:country":"US",
    "sg:address":"1198 Old Poor Robin Rd",
    "sg:city":"Sylvania",
    "sg:classifiers":[
        {
            "category":"Building & Trades",
            "subcategory":"Plumbing",
            "type":"Services"
        }
    ],
    "sg:phone":"+1 912 863 4457",
    "sg:postcode":"30467",
    "sg:province":"GA",
    "sg:tags":[
        "plumbing",
        "contractor"
    ],
    "wof:name":"Jimmy Scott Plumbing",
    "wof:placetype":"venue"
},
  "geometry": {"coordinates":[-81.56711,32.734306],"type":"Point"}
}