{
  "type": "Feature",
  "properties": {
    "iso:country":"US",
    "sg:address":"872 Harbins Rd",
    "sg:city":"Dacula",
    "sg:classifiers":[
        {
            "category":"Freight",
            "type":"Transportation"
        }
    ],
    "sg:phone":"+1 770 962 1275",
    "sg:postcode":"30019",
    "sg:province":"GA",
    "sg:tags":[
        "operator",
        "local",
        "trucking"
    ],
    "wof:name":"Jimmy Greeson Hauling",
    "wof:placetype":"venue"
},
  "geometry": {"coordinates":[-83.888715,33.969601],"type":"Point"}
}