{
  "type": "Feature",
  "properties": {
    "addr:full":"1901 Memorial Dr Waycross GA 31501",
    "addr:housenumber":"1901",
    "addr:postcode":"31501",
    "addr:street":"Memorial Dr",
    "iso:country":"US",
    "sg:address":"1901 Memorial Dr",
    "sg:city":"Waycross",
    "sg:classifiers":[
        {
            "category":"Restaurant",
            "type":"Food & Drink"
        }
    ],
    "sg:menulink":"http://www.allmenus.com/ga/waycross/84972-applebees/menu/",
    "sg:phone":"+1 912 285 9359",
    "sg:postcode":"31501",
    "sg:province":"GA",
    "sg:tags":[
        "burger",
        "american",
        "sandwich",
        "soup"
    ],
    "wof:name":"Applebee's",
    "wof:placetype":"venue"
},
  "geometry": {"coordinates":[-82.33121300000001,31.202457],"type":"Point"}
}