{
  "type": "Feature",
  "properties": {
    "iso:country":"US",
    "sg:address":"2469 Flat Shoals Rd",
    "sg:city":"Decatur",
    "sg:classifiers":[
        {
            "category":"Personal",
            "subcategory":"Beauty Salon",
            "type":"Services"
        }
    ],
    "sg:phone":"+1 404 241 4080",
    "sg:postcode":"30032",
    "sg:province":"GA",
    "wof:name":"T R's Coiffeurs",
    "wof:placetype":"venue"
},
  "geometry": {"coordinates":[-84.30627,33.715932],"type":"Point"}
}