{
  "type": "Feature",
  "properties": {
    "iso:country":"US",
    "sg:address":"3055 Kimball Bridge Rd",
    "sg:city":"Alpharetta",
    "sg:classifiers":[
        {
            "category":"Education",
            "subcategory":"School",
            "type":"Public Place"
        }
    ],
    "sg:phone":"+1 770 667 2800",
    "sg:postcode":"30022",
    "sg:province":"GA",
    "sg:tags":[
        "high",
        "middle",
        "elementary"
    ],
    "wof:name":"New Prospect Elementary School",
    "wof:placetype":"venue"
},
  "geometry": {"coordinates":[-84.273697,34.0527],"type":"Point"}
}