{
  "type": "Feature",
  "properties": {
    "iso:country":"US",
    "sg:address":"1800 Spring Rd SE",
    "sg:city":"Smyrna",
    "sg:classifiers":[
        {
            "category":"Real Estate",
            "subcategory":"Real Estate Operator",
            "type":"Services"
        }
    ],
    "sg:phone":"+1 678 842 0780",
    "sg:postcode":"30080",
    "sg:province":"GA",
    "sg:tags":[
        "condominium"
    ],
    "wof:name":"Heights Spring Rd Condo",
    "wof:placetype":"venue"
},
  "geometry": {"coordinates":[-84.50015399999999,33.883592],"type":"Point"}
}