{
  "type": "Feature",
  "properties": {
    "iso:country":"US",
    "sg:address":"3651 Arbor Hill Rd",
    "sg:city":"Canton",
    "sg:classifiers":[
        {
            "category":"Wholesale",
            "subcategory":"Farm Supplies",
            "type":"Manufacturing & Wholesale Goods"
        }
    ],
    "sg:phone":"+1 770 704 1957",
    "sg:postcode":"30115",
    "sg:province":"GA",
    "sg:tags":[
        "feed"
    ],
    "wof:name":"Arbor Hill Trading Post",
    "wof:placetype":"venue"
},
  "geometry": {"coordinates":[-84.326758,34.223918],"type":"Point"}
}