{
  "type": "Feature",
  "properties": {
    "iso:country":"US",
    "sg:address":"2520 Windy Hill Rd SE Ste 106",
    "sg:city":"Marietta",
    "sg:classifiers":[
        {
            "category":"Health Services",
            "subcategory":"Doctor",
            "type":"Services"
        },
        {
            "category":"Health Services",
            "subcategory":"Clinic",
            "type":"Services"
        }
    ],
    "sg:phone":"+1 770 952 3308",
    "sg:postcode":"30067",
    "sg:province":"GA",
    "sg:tags":[
        "counseling",
        "mental"
    ],
    "sg:website":"www.sandrahuttonphd.com",
    "wof:name":"Hutton Sandra P PHD",
    "wof:placetype":"venue"
},
  "geometry": {"coordinates":[-84.4804,33.9021],"type":"Point"}
}