{
  "type": "Feature",
  "properties": {
    "addr:full":"5110 Norman Blvd Atlanta GA 30349",
    "addr:housenumber":"5110",
    "addr:postcode":"30349",
    "addr:street":"Norman Blvd",
    "iso:country":"US",
    "sg:address":"5110 Norman Blvd",
    "sg:city":"Atlanta",
    "sg:classifiers":[
        {
            "category":"Personal",
            "subcategory":"Beauty Salon",
            "type":"Services"
        }
    ],
    "sg:phone":"+1 770 909 0100",
    "sg:postcode":"30349",
    "sg:province":"GA",
    "sg:tags":[
        "shop"
    ],
    "wof:name":"Brown Sug Hair & Braiding Svc",
    "wof:placetype":"venue"
},
  "geometry": {"coordinates":[-84.457429,33.613636],"type":"Point"}
}