{
  "type": "Feature",
  "properties": {
    "iso:country":"US",
    "sg:address":"2880 N Berkeley Lake Rd. NW Ste 4",
    "sg:city":"Duluth",
    "sg:classifiers":[
        {
            "category":"Building & Trades",
            "subcategory":"Construction",
            "type":"Services"
        }
    ],
    "sg:phone":"+1 770 418 2112",
    "sg:postcode":"30096",
    "sg:province":"GA",
    "sg:tags":[
        "contractor"
    ],
    "sg:website":"www.closetsbydesign.com",
    "wof:name":"Closets By Design",
    "wof:placetype":"venue"
},
  "geometry": {"coordinates":[-84.162369,33.975035],"type":"Point"}
}