{
  "type": "Feature",
  "properties": {
    "addr:full":"5390 Peachtree Industrial Blvd Norcross GA 30071",
    "addr:housenumber":"5390",
    "addr:postcode":"30071",
    "addr:street":"Peachtree Industrial Blvd",
    "iso:country":"US",
    "sg:address":"5390 Peachtree Industrial Blvd",
    "sg:city":"Norcross",
    "sg:classifiers":[
        {
            "category":"Building & Trades",
            "subcategory":"Locksmith",
            "type":"Services"
        }
    ],
    "sg:phone":"+1 888 544 7526",
    "sg:postcode":"30071",
    "sg:province":"GA",
    "sg:tags":[
        "key"
    ],
    "wof:name":"7 Day 24 Hour Emergency Locksmith",
    "wof:placetype":"venue"
},
  "geometry": {"coordinates":[-84.209424,33.960339],"type":"Point"}
}