{
  "type": "Feature",
  "properties": {
    "iso:country":"US",
    "sg:address":"411 Old Villanow Rd",
    "sg:city":"La Fayette",
    "sg:classifiers":[
        {
            "category":"Food & Beverages",
            "subcategory":"Liquor & Beverages",
            "type":"Retail Goods"
        }
    ],
    "sg:phone":"+1 706 638 8035",
    "sg:postcode":"30728",
    "sg:province":"GA",
    "wof:name":"Alpine Package Store",
    "wof:placetype":"venue"
},
  "geometry": {"coordinates":[-85.20030800000001,34.695894],"type":"Point"}
}