{
  "type": "Feature",
  "properties": {
    "iso:country":"US",
    "sg:address":"400 Glenn St SW",
    "sg:city":"Atlanta",
    "sg:classifiers":[
        {
            "category":"Professional",
            "subcategory":"Lawyer & Legal Services",
            "type":"Services"
        }
    ],
    "sg:phone":"+1 404 881 2825",
    "sg:postcode":"30312",
    "sg:province":"GA",
    "sg:tags":[
        "firm",
        "law"
    ],
    "wof:name":"Aitcheson Frank LLC",
    "wof:placetype":"venue"
},
  "geometry": {"coordinates":[-84.400999,33.73806],"type":"Point"}
}