{
  "type": "Feature",
  "properties": {
    "addr:full":"7183 Jonesboro Rd Ste 100 Morrow GA 30260",
    "addr:housenumber":"7183",
    "addr:postcode":"30260",
    "addr:street":"Jonesboro Rd Ste 100",
    "iso:country":"US",
    "sg:address":"7183 Jonesboro Rd Ste 100",
    "sg:city":"Morrow",
    "sg:classifiers":[
        {
            "category":"Health Services",
            "subcategory":"Doctor",
            "type":"Services"
        }
    ],
    "sg:phone":"+1 770 968 1171",
    "sg:postcode":"30260",
    "sg:province":"GA",
    "sg:tags":[
        "surgeon",
        "oral"
    ],
    "wof:name":"Reudelhuber David L DDS",
    "wof:placetype":"venue"
},
  "geometry": {"coordinates":[-84.34580200000001,33.558998],"type":"Point"}
}