{
  "type": "Feature",
  "properties": {
    "addr:full":"305 Old School Rd La Grange GA 30240",
    "addr:housenumber":"305",
    "addr:postcode":"30240",
    "addr:street":"Old School Rd",
    "iso:country":"US",
    "sg:address":"305 Old School Rd",
    "sg:city":"La Grange",
    "sg:classifiers":[
        {
            "category":"Retail",
            "subcategory":"Auto Repair",
            "type":"Services"
        }
    ],
    "sg:phone":"+1 706 884 2019",
    "sg:postcode":"30240",
    "sg:province":"GA",
    "sg:tags":[
        "body"
    ],
    "wof:name":"Abbotts Ford House",
    "wof:placetype":"venue"
},
  "geometry": {"coordinates":[-85.169377,33.047348],"type":"Point"}
}