{
  "type": "Feature",
  "properties": {
    "iso:country":"US",
    "sg:address":"1031 Shepherds Ln NE",
    "sg:city":"Atlanta",
    "sg:classifiers":[
        {
            "category":"Building & Trades",
            "subcategory":"Equipment Rental",
            "type":"Services"
        }
    ],
    "sg:phone":"+1 404 329 8700",
    "sg:postcode":"30324",
    "sg:province":"GA",
    "sg:tags":[
        "protection",
        "lightning"
    ],
    "sg:website":"http://www.atlantalightning.com",
    "wof:name":"A L P Supply",
    "wof:placetype":"venue"
},
  "geometry": {"coordinates":[-84.340523,33.80859],"type":"Point"}
}