{
  "type": "Feature",
  "properties": {
    "iso:country":"US",
    "sg:address":"1103 13th St",
    "sg:city":"Columbus",
    "sg:classifiers":[
        {
            "category":"Shopping",
            "subcategory":"Used Merchandise",
            "type":"Retail Goods"
        }
    ],
    "sg:phone":"+1 706 327 2330",
    "sg:postcode":"31901",
    "sg:province":"GA",
    "sg:tags":[
        "antique",
        "gift"
    ],
    "wof:name":"That Added Touch Of Columbus",
    "wof:placetype":"venue"
},
  "geometry": {"coordinates":[-84.97649800000001,32.470582],"type":"Point"}
}