{
  "type": "Feature",
  "properties": {
    "addr:full":"1070 Lake Welbrook Dr Athens GA 30606",
    "addr:housenumber":"1070",
    "addr:postcode":"30606",
    "addr:street":"Lake Welbrook Dr",
    "iso:country":"US",
    "sg:address":"1070 Lake Welbrook Dr",
    "sg:city":"Athens",
    "sg:classifiers":[
        {
            "category":"Restaurant",
            "type":"Food & Drink"
        }
    ],
    "sg:phone":"+1 706 769 1816",
    "sg:postcode":"30606",
    "sg:province":"GA",
    "sg:tags":[
        "chicken"
    ],
    "wof:name":"Chicken Brothers Leasing",
    "wof:placetype":"venue"
},
  "geometry": {"coordinates":[-83.437451,33.90028],"type":"Point"}
}