{
  "type": "Feature",
  "properties": {
    "iso:country":"US",
    "sg:address":"1545 E Montgomery Xrd",
    "sg:city":"Savannah",
    "sg:classifiers":[
        {
            "category":"Shopping",
            "subcategory":"Hobbies, Toys, & Games",
            "type":"Retail Goods"
        },
        {
            "category":"Shopping",
            "subcategory":"Gifts & Souvenirs",
            "type":"Retail Goods"
        }
    ],
    "sg:phone":"+1 912 356 1066",
    "sg:postcode":"31406",
    "sg:province":"GA",
    "sg:tags":[
        "supply"
    ],
    "wof:name":"Morning Star Games",
    "wof:placetype":"venue"
},
  "geometry": {"coordinates":[-81.096172,31.991707],"type":"Point"}
}