{
  "type": "Feature",
  "properties": {
    "iso:country":"US",
    "sg:address":"12155 Liberty Dr",
    "sg:city":"Covington",
    "sg:classifiers":[
        {
            "category":"Manufacturing",
            "subcategory":"Tools & Machinery",
            "type":"Manufacturing & Wholesale Goods"
        }
    ],
    "sg:phone":"+1 770 784 1948",
    "sg:postcode":"30014",
    "sg:province":"GA",
    "sg:tags":[
        "compressor",
        "gas",
        "air"
    ],
    "wof:name":"Atlas Copco",
    "wof:placetype":"venue"
},
  "geometry": {"coordinates":[-83.824634,33.614221],"type":"Point"}
}