{
  "type": "Feature",
  "properties": {
    "iso:country":"US",
    "sg:address":"2062 Skyhawk Ln",
    "sg:city":"Acworth",
    "sg:classifiers":[
        {
            "category":"Retail",
            "subcategory":"Repair Shop",
            "type":"Services"
        }
    ],
    "sg:phone":"+1 770 926 0380",
    "sg:postcode":"30102",
    "sg:province":"GA",
    "wof:name":"McCardell Food Repair Service",
    "wof:placetype":"venue"
},
  "geometry": {"coordinates":[-84.608149,34.122854],"type":"Point"}
}