{
  "type": "Feature",
  "properties": {
    "addr:full":"5939 Stewart Pkwy Douglasville GA 30135",
    "addr:housenumber":"5939",
    "addr:postcode":"30135",
    "addr:street":"Stewart Pkwy",
    "iso:country":"US",
    "sg:address":"5939 Stewart Pkwy",
    "sg:city":"Douglasville",
    "sg:classifiers":[
        {
            "category":"Arts & Performance",
            "subcategory":"Arts Center",
            "type":"Entertainment"
        }
    ],
    "sg:phone":"+1 770 577 9378",
    "sg:postcode":"30135",
    "sg:province":"GA",
    "sg:tags":[
        "performing"
    ],
    "sg:website":"www.adwestdance.com",
    "wof:name":"A D West Dance Company",
    "wof:placetype":"venue"
},
  "geometry": {"coordinates":[-84.768472,33.718707],"type":"Point"}
}