{
  "type": "Feature",
  "properties": {
    "addr:full":"1785 Westgate Pkwy SW Atlanta GA 30336",
    "addr:housenumber":"1785",
    "addr:postcode":"30336",
    "addr:street":"Westgate Pkwy Sw",
    "iso:country":"US",
    "sg:address":"1785 Westgate Pkwy SW",
    "sg:city":"Atlanta",
    "sg:classifiers":[
        {
            "category":"Wholesale",
            "subcategory":"Durable Goods & Equipment",
            "type":"Manufacturing & Wholesale Goods"
        }
    ],
    "sg:phone":"+1 404 344 4976",
    "sg:postcode":"30336",
    "sg:province":"GA",
    "sg:tags":[
        "importer"
    ],
    "wof:name":"APL Logistics",
    "wof:placetype":"venue"
},
  "geometry": {"coordinates":[-84.606632,33.709051],"type":"Point"}
}