{
  "type": "Feature",
  "properties": {
    "iso:country":"US",
    "sg:address":"135 Harben Pl",
    "sg:city":"Athens",
    "sg:classifiers":[
        {
            "category":"Building & Trades",
            "subcategory":"Construction",
            "type":"Services"
        }
    ],
    "sg:phone":"+1 706 549 2956",
    "sg:postcode":"30606",
    "sg:province":"GA",
    "sg:tags":[
        "home",
        "improvement",
        "general",
        "contractor"
    ],
    "wof:name":"Bell Construction Inc",
    "wof:placetype":"venue"
},
  "geometry": {"coordinates":[-83.41210700000001,33.937662],"type":"Point"}
}