{
  "type": "Feature",
  "properties": {
    "iso:country":"US",
    "sg:address":"5013 Harrison Rd",
    "sg:city":"Macon",
    "sg:classifiers":[
        {
            "category":"Food & Beverages",
            "subcategory":"Groceries & Convenience Stores",
            "type":"Retail Goods"
        }
    ],
    "sg:phone":"+1 478 405 0900",
    "sg:postcode":"31206",
    "sg:province":"GA",
    "sg:tags":[
        "grocer"
    ],
    "wof:name":"Carniceria El Jjido 11",
    "wof:placetype":"venue"
},
  "geometry": {"coordinates":[-83.724943,32.813237],"type":"Point"}
}