{
  "type": "Feature",
  "properties": {
    "addr:full":"1582 Williams Dr Marietta GA 30066",
    "addr:housenumber":"1582",
    "addr:postcode":"30066",
    "addr:street":"Williams Dr",
    "iso:country":"US",
    "sg:address":"1582 Williams Dr",
    "sg:city":"Marietta",
    "sg:classifiers":[
        {
            "category":"Building & Trades",
            "subcategory":"Landscaping Services",
            "type":"Services"
        }
    ],
    "sg:phone":"+1 770 420 8996",
    "sg:postcode":"30066",
    "sg:province":"GA",
    "sg:tags":[
        "tree"
    ],
    "wof:name":"Glory Maples",
    "wof:placetype":"venue"
},
  "geometry": {"coordinates":[-84.532015,33.997338],"type":"Point"}
}