{
  "type": "Feature",
  "properties": {
    "iso:country":"US",
    "sg:address":"812 Poindexter Dr",
    "sg:city":"Augusta",
    "sg:classifiers":[
        {
            "category":"Restaurant",
            "type":"Food & Drink"
        }
    ],
    "sg:phone":"+1 706 481 8735",
    "sg:postcode":"30909",
    "sg:province":"GA",
    "sg:tags":[
        "eating"
    ],
    "wof:name":"Harriets Kitchen Inc",
    "wof:placetype":"venue"
},
  "geometry": {"coordinates":[-82.054986,33.481825],"type":"Point"}
}