{
  "type": "Feature",
  "properties": {
    "addr:full":"249 Waddell St Athens GA 30605",
    "addr:housenumber":"249",
    "addr:postcode":"30605",
    "addr:street":"Waddell St",
    "iso:country":"US",
    "sg:address":"249 Waddell St",
    "sg:city":"Athens",
    "sg:classifiers":[
        {
            "category":"Place Of Worship",
            "type":"Public Place"
        }
    ],
    "sg:phone":"+1 706 353 3207",
    "sg:postcode":"30605",
    "sg:province":"GA",
    "sg:tags":[
        "church"
    ],
    "wof:name":"Church In Athens",
    "wof:placetype":"venue"
},
  "geometry": {"coordinates":[-83.37963999999999,33.954124],"type":"Point"}
}