{
  "type": "Feature",
  "properties": {
    "iso:country":"US",
    "sg:address":"4514 Forest Peak Cir",
    "sg:city":"Marietta",
    "sg:classifiers":[
        {
            "category":"Professional",
            "type":"Services"
        }
    ],
    "sg:phone":"+1 770 973 9771",
    "sg:postcode":"30066",
    "sg:province":"GA",
    "wof:name":"Classical Objects Inc",
    "wof:placetype":"venue"
},
  "geometry": {"coordinates":[-84.44981799999999,34.060641],"type":"Point"}
}