{
  "type": "Feature",
  "properties": {
    "iso:country":"US",
    "sg:address":"905 Hardy Ct",
    "sg:city":"Augusta",
    "sg:classifiers":[
        {
            "category":"Manufacturing",
            "subcategory":"Retail Goods",
            "type":"Manufacturing & Wholesale Goods"
        }
    ],
    "sg:phone":"+1 706 722 0016",
    "sg:postcode":"30901",
    "sg:province":"GA",
    "sg:tags":[
        "casket"
    ],
    "wof:name":"OIA Casket Co",
    "wof:placetype":"venue"
},
  "geometry": {"coordinates":[-81.95003699999999,33.456939],"type":"Point"}
}