{
  "type": "Feature",
  "properties": {
    "addr:full":"7950 Lanier Dr Cumming GA 30041",
    "addr:housenumber":"7950",
    "addr:postcode":"30041",
    "addr:street":"Lanier Dr",
    "iso:country":"US",
    "sg:address":"7950 Lanier Dr",
    "sg:city":"Cumming",
    "sg:classifiers":[
        {
            "category":"Wholesale",
            "subcategory":"Machinery & Supplies",
            "type":"Manufacturing & Wholesale Goods"
        }
    ],
    "sg:phone":"+1 770 887 3053",
    "sg:postcode":"30041",
    "sg:province":"GA",
    "sg:tags":[
        "equipment",
        "industrial",
        "bottler"
    ],
    "wof:name":"Marks Machinery Inc",
    "wof:placetype":"venue"
},
  "geometry": {"coordinates":[-84.05136299999999,34.204574],"type":"Point"}
}