{
  "type": "Feature",
  "properties": {
    "iso:country":"US",
    "sg:address":"8 US Hwy 19 S",
    "sg:city":"Camilla",
    "sg:classifiers":[
        {
            "category":"Food & Beverages",
            "subcategory":"Groceries & Convenience Stores",
            "type":"Retail Goods"
        }
    ],
    "sg:phone":"+1 229 336 0099",
    "sg:postcode":"31730",
    "sg:province":"GA",
    "wof:name":"Jack Rabbit Foods 7",
    "wof:placetype":"venue"
},
  "geometry": {"coordinates":[-84.200174,31.231012],"type":"Point"}
}