{
  "type": "Feature",
  "properties": {
    "addr:full":"2302 Henry Clower Blvd SW Snellville GA 30078",
    "addr:housenumber":"2302",
    "addr:postcode":"30078",
    "addr:street":"Henry Clower Blvd Sw",
    "iso:country":"US",
    "sg:address":"2302 Henry Clower Blvd SW",
    "sg:city":"Snellville",
    "sg:classifiers":[
        {
            "category":"Food & Beverages",
            "subcategory":"Specialty",
            "type":"Retail Goods"
        }
    ],
    "sg:phone":"+1 770 978 8878",
    "sg:postcode":"30078",
    "sg:province":"GA",
    "sg:tags":[
        "vitamin"
    ],
    "wof:name":"Herbs For Health",
    "wof:placetype":"venue"
},
  "geometry": {"coordinates":[-84.023995,33.853669],"type":"Point"}
}