{
  "type": "Feature",
  "properties": {
    "iso:country":"US",
    "sg:address":"4024 Treemont Ln",
    "sg:city":"Suwanee",
    "sg:classifiers":[
        {
            "category":"Insurance",
            "subcategory":"Insurance Agent",
            "type":"Services"
        }
    ],
    "sg:phone":"+1 770 932 6599",
    "sg:postcode":"30024",
    "sg:province":"GA",
    "wof:name":"Suwanee Consultant",
    "wof:placetype":"venue"
},
  "geometry": {"coordinates":[-84.05197099999999,34.064023],"type":"Point"}
}