{
  "type": "Feature",
  "properties": {
    "iso:country":"US",
    "sg:address":"2190 N Norcross Tucker Rd",
    "sg:city":"Norcross",
    "sg:classifiers":[
        {
            "category":"Utilities",
            "subcategory":"Recycling",
            "type":"Services"
        }
    ],
    "sg:phone":"+1 770 263 6330",
    "sg:postcode":"30071",
    "sg:province":"GA",
    "sg:tags":[
        "disposal",
        "reduction",
        "waste",
        "equipment"
    ],
    "sg:website":"http://www.conversiontechnology.com",
    "wof:name":"Conversion Technology Inc",
    "wof:placetype":"venue"
},
  "geometry": {"coordinates":[-84.211519,33.923171],"type":"Point"}
}