{
  "type": "Feature",
  "properties": {
    "addr:full":"3660 Swiftwater Park Dr Suwanee GA 30024",
    "addr:postcode":"3660;30024",
    "addr:street":"Swiftwater Park Dr",
    "iso:country":"US",
    "sg:address":"3660 Swiftwater Park Dr",
    "sg:city":"Suwanee",
    "sg:classifiers":[
        {
            "category":"Wholesale",
            "subcategory":"Metals & Minerals",
            "type":"Manufacturing & Wholesale Goods"
        }
    ],
    "sg:phone":"+1 404 523 1125",
    "sg:postcode":"30024",
    "sg:province":"GA",
    "sg:tags":[
        "durable"
    ],
    "wof:name":"Stewart Stainless Supply Inc",
    "wof:placetype":"venue"
},
  "geometry": {"coordinates":[-84.082812,34.036501],"type":"Point"}
}