{
  "type": "Feature",
  "properties": {
    "iso:country":"US",
    "sg:address":"151 Willow Bend Rd",
    "sg:city":"Peachtree City",
    "sg:classifiers":[
        {
            "category":"Government",
            "subcategory":"Office",
            "type":"Public Place"
        }
    ],
    "sg:phone":"+1 770 631 2508",
    "sg:postcode":"30269",
    "sg:province":"GA",
    "sg:tags":[
        "city"
    ],
    "wof:name":"Peachtree City Mayor",
    "wof:placetype":"venue"
},
  "geometry": {"coordinates":[-84.581557,33.399879],"type":"Point"}
}