{
  "type": "Feature",
  "properties": {
    "iso:country":"US",
    "sg:address":"7490 S Spalding Lake Dr",
    "sg:city":"Atlanta",
    "sg:classifiers":[
        {
            "category":"Building & Trades",
            "subcategory":"Construction",
            "type":"Services"
        }
    ],
    "sg:phone":"+1 404 456 6339",
    "sg:postcode":"30350",
    "sg:province":"GA",
    "sg:tags":[
        "framing",
        "contractor"
    ],
    "wof:name":"K Construction Management Inc",
    "wof:placetype":"venue"
},
  "geometry": {"coordinates":[-84.279866,33.96309],"type":"Point"}
}