{
  "type": "Feature",
  "properties": {
    "addr:full":"912 E Spring St Monroe GA 30655",
    "addr:housenumber":"912",
    "addr:postcode":"30655",
    "addr:street":"E Spring St",
    "iso:country":"US",
    "sg:address":"912 E Spring St",
    "sg:city":"Monroe",
    "sg:classifiers":[
        {
            "category":"Travel",
            "subcategory":"Hotels & Motels",
            "type":"Entertainment"
        }
    ],
    "sg:phone":"+1 770 267 9447",
    "sg:postcode":"30655",
    "sg:province":"GA",
    "sg:tags":[
        "operation"
    ],
    "wof:name":"Monroe Motor Inn",
    "wof:placetype":"venue"
},
  "geometry": {"coordinates":[-83.700345,33.801192],"type":"Point"}
}