{
  "type": "Feature",
  "properties": {
    "addr:full":"10 1st Ave SE Moultrie GA 31768",
    "addr:housenumber":"10",
    "addr:postcode":"31768",
    "addr:street":"1St Ave Se",
    "iso:country":"US",
    "sg:address":"10 1st Ave SE",
    "sg:city":"Moultrie",
    "sg:classifiers":[
        {
            "category":"Shopping",
            "subcategory":"Jewelry",
            "type":"Retail Goods"
        }
    ],
    "sg:phone":"+1 229 985 3500",
    "sg:postcode":"31768",
    "sg:province":"GA",
    "sg:tags":[
        "shop",
        "shoes",
        "pawn",
        "family",
        "firearm"
    ],
    "wof:name":"Kings Shoes",
    "wof:placetype":"venue"
},
  "geometry": {"coordinates":[-83.788783,31.179059],"type":"Point"}
}