{
  "type": "Feature",
  "properties": {
    "addr:full":"4919 Flat Shoals Pkwy Decatur GA 30034",
    "addr:housenumber":"4919",
    "addr:postcode":"30034",
    "addr:street":"Flat Shoals Pkwy",
    "iso:country":"US",
    "sg:address":"4919 Flat Shoals Pkwy",
    "sg:city":"Decatur",
    "sg:classifiers":[
        {
            "category":"Home & Garden",
            "subcategory":"Furniture",
            "type":"Retail Goods"
        }
    ],
    "sg:phone":"+1 770 492 2981",
    "sg:postcode":"30034",
    "sg:province":"GA",
    "wof:name":"Discounted Home Furn Design",
    "wof:placetype":"venue"
},
  "geometry": {"coordinates":[-84.22510800000001,33.680062],"type":"Point"}
}