{
  "type": "Feature",
  "properties": {
    "addr:full":"369 Johnson Ferry Rd Marietta GA 30068",
    "addr:housenumber":"369",
    "addr:postcode":"30068",
    "addr:street":"Johnson Ferry Rd",
    "iso:country":"US",
    "sg:address":"369 Johnson Ferry Rd",
    "sg:city":"Marietta",
    "sg:classifiers":[
        {
            "category":"Wholesale",
            "subcategory":"Machinery & Supplies",
            "type":"Manufacturing & Wholesale Goods"
        }
    ],
    "sg:phone":"+1 678 904 3380",
    "sg:postcode":"30068",
    "sg:province":"GA",
    "sg:tags":[
        "packaging"
    ],
    "wof:name":"Battle & Assoc",
    "wof:placetype":"venue"
},
  "geometry": {"coordinates":[-84.41177399999999,33.957397],"type":"Point"}
}