{
  "type": "Feature",
  "properties": {
    "addr:full":"1735 Kaolin Rd Sandersville GA 31082",
    "addr:housenumber":"1735",
    "addr:postcode":"31082",
    "addr:street":"Kaolin Rd",
    "iso:country":"US",
    "sg:address":"1735 Kaolin Rd",
    "sg:city":"Sandersville",
    "sg:classifiers":[
        {
            "category":"Government",
            "subcategory":"Police Station",
            "type":"Public Place"
        }
    ],
    "sg:phone":"+1 478 552 1225",
    "sg:postcode":"31082",
    "sg:province":"GA",
    "sg:tags":[
        "department"
    ],
    "wof:name":"Sheriff's Office",
    "wof:placetype":"venue"
},
  "geometry": {"coordinates":[-82.835707,32.962903],"type":"Point"}
}