{
  "type": "Feature",
  "properties": {
    "iso:country":"US",
    "sg:address":"160 Midland Manor Dr",
    "sg:city":"Midland",
    "sg:classifiers":[
        {
            "category":"Professional",
            "type":"Services"
        }
    ],
    "sg:phone":"+1 706 569 1100",
    "sg:postcode":"31820",
    "sg:province":"GA",
    "wof:name":"Georgia Nami Inc",
    "wof:placetype":"venue"
},
  "geometry": {"coordinates":[-84.828754,32.588421],"type":"Point"}
}