{
  "type": "Feature",
  "properties": {
    "addr:full":"1089 Culpepper Dr SW Conyers GA 30094",
    "addr:housenumber":"1089",
    "addr:postcode":"30094",
    "addr:street":"Culpepper Dr Sw",
    "iso:country":"US",
    "sg:address":"1089 Culpepper Dr SW",
    "sg:city":"Conyers",
    "sg:classifiers":[
        {
            "category":"Wholesale",
            "subcategory":"Office Equipment",
            "type":"Manufacturing & Wholesale Goods"
        }
    ],
    "sg:phone":"+1 770 785 7070",
    "sg:postcode":"30094",
    "sg:province":"GA",
    "sg:tags":[
        "distribution"
    ],
    "wof:name":"Innovage Inc",
    "wof:placetype":"venue"
},
  "geometry": {"coordinates":[-84.02600700000001,33.650645],"type":"Point"}
}