{
  "type": "Feature",
  "properties": {
    "addr:full":"717 Wynhollow Trce Apt 7 Norcross GA 30071",
    "addr:housenumber":"717;7",
    "addr:postcode":"30071",
    "addr:street":"Wynhollow Trce Apt",
    "iso:country":"US",
    "sg:address":"717 Wynhollow Trce Apt 7",
    "sg:city":"Norcross",
    "sg:classifiers":[
        {
            "category":"Building & Trades",
            "subcategory":"Construction",
            "type":"Services"
        }
    ],
    "sg:phone":"+1 678 368 1236",
    "sg:postcode":"30071",
    "sg:province":"GA",
    "sg:tags":[
        "drywall",
        "industrial",
        "painting",
        "contractors-commercial",
        "contractor"
    ],
    "sg:website":"http://www.lookingoodpainting.com",
    "wof:name":"Lookin Good Painting",
    "wof:placetype":"venue"
},
  "geometry": {"coordinates":[-84.19721199999999,33.939549],"type":"Point"}
}