{
  "type": "Feature",
  "properties": {
    "addr:full":"3578 Old Milton Pkwy Alpharetta GA 30005",
    "addr:housenumber":"3578",
    "addr:postcode":"30005",
    "addr:street":"Old Milton Pkwy",
    "iso:country":"US",
    "sg:address":"3578 Old Milton Pkwy",
    "sg:city":"Alpharetta",
    "sg:classifiers":[
        {
            "category":"Professional",
            "subcategory":"Engineering",
            "type":"Services"
        }
    ],
    "sg:phone":"+1 770 619 5216",
    "sg:postcode":"30005",
    "sg:province":"GA",
    "sg:tags":[
        "consultant",
        "construction"
    ],
    "wof:name":"McMeadoy Group Ltd",
    "wof:placetype":"venue"
},
  "geometry": {"coordinates":[-84.257194,34.066418],"type":"Point"}
}