{
  "type": "Feature",
  "properties": {
    "addr:full":"5600 Milgen Rd Columbus GA 31907",
    "addr:postcode":"5600;31907",
    "addr:street":"Milgen Rd",
    "iso:country":"US",
    "sg:address":"5600 Milgen Rd",
    "sg:city":"Columbus",
    "sg:classifiers":[
        {
            "category":"Retail",
            "subcategory":"Laundry & Dry Cleaning",
            "type":"Services"
        }
    ],
    "sg:phone":"+1 706 561 3700",
    "sg:postcode":"31907",
    "sg:province":"GA",
    "sg:tags":[
        "cleaners",
        "alteration",
        "power",
        "garment"
    ],
    "wof:name":"Continental Cleaners",
    "wof:placetype":"venue"
},
  "geometry": {"coordinates":[-84.88757099999999,32.52552],"type":"Point"}
}