{
  "type": "Feature",
  "properties": {
    "iso:country":"US",
    "sg:address":"2316 Lochinver Ln SW",
    "sg:city":"Conyers",
    "sg:classifiers":[
        {
            "category":"Real Estate",
            "subcategory":"Real Estate Agent",
            "type":"Services"
        }
    ],
    "sg:phone":"+1 770 922 9433",
    "sg:postcode":"30094",
    "sg:province":"GA",
    "wof:name":"Rbtr Inc",
    "wof:placetype":"venue"
},
  "geometry": {"coordinates":[-84.049825,33.628379],"type":"Point"}
}