{
  "type": "Feature",
  "properties": {
    "addr:full":"901 High Green Ct Marietta GA 30068",
    "addr:housenumber":"901",
    "addr:postcode":"30068",
    "addr:street":"High Green Ct",
    "iso:country":"US",
    "sg:address":"901 High Green Ct",
    "sg:city":"Marietta",
    "sg:classifiers":[
        {
            "category":"Shopping",
            "subcategory":"Computers & Home Electronics",
            "type":"Retail Goods"
        }
    ],
    "sg:phone":"+1 770 977 1733",
    "sg:postcode":"30068",
    "sg:province":"GA",
    "sg:tags":[
        "software"
    ],
    "wof:name":"Accelrys Inc",
    "wof:placetype":"venue"
},
  "geometry": {"coordinates":[-84.44301,33.971035],"type":"Point"}
}