{
  "type": "Feature",
  "properties": {
    "addr:full":"1514 US Hwy 29 West Point GA 31833",
    "addr:housenumber":"1514",
    "addr:postcode":"31833",
    "addr:street":"Us Hwy 29",
    "iso:country":"US",
    "sg:address":"1514 US Hwy 29",
    "sg:city":"West Point",
    "sg:classifiers":[
        {
            "category":"Organizations",
            "subcategory":"Religious Organization",
            "type":"Services"
        }
    ],
    "sg:phone":"+1 706 645 9512",
    "sg:postcode":"31833",
    "sg:province":"GA",
    "sg:tags":[
        "church"
    ],
    "wof:name":"New Bethel Baptist Church",
    "wof:placetype":"venue"
},
  "geometry": {"coordinates":[-85.16947500000001,32.885107],"type":"Point"}
}