{
  "type": "Feature",
  "properties": {
    "addr:full":"705 Hembree Pl Roswell GA 30076",
    "addr:housenumber":"705",
    "addr:postcode":"30076",
    "addr:street":"Hembree Pl",
    "iso:country":"US",
    "sg:address":"705 Hembree Pl",
    "sg:city":"Roswell",
    "sg:classifiers":[
        {
            "category":"Building & Trades",
            "subcategory":"Locksmith",
            "type":"Services"
        }
    ],
    "sg:phone":"+1 770 277 5227",
    "sg:postcode":"30076",
    "sg:province":"GA",
    "sg:tags":[
        "key"
    ],
    "wof:name":"24-Hours Emergency Locksmith",
    "wof:placetype":"venue"
},
  "geometry": {"coordinates":[-84.318549,34.059468],"type":"Point"}
}