{
  "type": "Feature",
  "properties": {
    "addr:full":"2851 Cole Ct Norcross GA 30071",
    "addr:housenumber":"2851",
    "addr:postcode":"30071",
    "addr:street":"Cole Ct",
    "iso:country":"US",
    "sg:address":"2851 Cole Ct",
    "sg:city":"Norcross",
    "sg:classifiers":[
        {
            "category":"Education",
            "subcategory":"Library",
            "type":"Public Place"
        }
    ],
    "sg:phone":"+1 678 969 0244",
    "sg:postcode":"30071",
    "sg:province":"GA",
    "wof:name":"Vernon Library Supplies",
    "wof:placetype":"venue"
},
  "geometry": {"coordinates":[-84.202797,33.952099],"type":"Point"}
}