{
  "type": "Feature",
  "properties": {
    "addr:full":"125 Industrial Park Cir Lawrenceville GA 30045",
    "addr:housenumber":"125",
    "addr:postcode":"30045",
    "addr:street":"Industrial Park Cir",
    "iso:country":"US",
    "sg:address":"125 Industrial Park Cir",
    "sg:city":"Lawrenceville",
    "sg:classifiers":[
        {
            "category":"Wholesale",
            "subcategory":"Construction Materials",
            "type":"Manufacturing & Wholesale Goods"
        }
    ],
    "sg:phone":"+1 770 495 9328",
    "sg:postcode":"30045",
    "sg:province":"GA",
    "wof:name":"GMS Select Products Inc",
    "wof:placetype":"venue"
},
  "geometry": {"coordinates":[-83.98117000000001,33.966497],"type":"Point"}
}