{
  "type": "Feature",
  "properties": {
    "addr:full":"110 Evans Mill Dr Ste 305 Dallas GA 30157",
    "addr:housenumber":"110",
    "addr:postcode":"30157",
    "addr:street":"Evans Mill Dr Ste 305",
    "iso:country":"US",
    "sg:address":"110 Evans Mill Dr Ste 305",
    "sg:city":"Dallas",
    "sg:classifiers":[
        {
            "category":"Health Services",
            "subcategory":"Clinic",
            "type":"Services"
        }
    ],
    "sg:phone":"+1 770 445 6358",
    "sg:postcode":"30157",
    "sg:province":"GA",
    "sg:tags":[
        "counseling",
        "mental"
    ],
    "wof:name":"Dallas Family Counseling Center",
    "wof:placetype":"venue"
},
  "geometry": {"coordinates":[-84.763271,33.916183],"type":"Point"}
}