{
  "type": "Feature",
  "properties": {
    "addr:full":"4419 S Main St Acworth GA 30101",
    "addr:housenumber":"4419",
    "addr:postcode":"30101",
    "addr:street":"S Main St",
    "iso:country":"US",
    "sg:address":"4419 S Main St",
    "sg:city":"Acworth",
    "sg:classifiers":[
        {
            "category":"Building & Trades",
            "subcategory":"Equipment Rental",
            "type":"Services"
        }
    ],
    "sg:phone":"+1 770 974 4132",
    "sg:postcode":"30101",
    "sg:province":"GA",
    "sg:tags":[
        "appliance",
        "furniture"
    ],
    "wof:name":"Pritchard Furniture & Appl",
    "wof:placetype":"venue"
},
  "geometry": {"coordinates":[-84.665667,34.061036],"type":"Point"}
}