{
  "type": "Feature",
  "properties": {
    "iso:country":"US",
    "sg:address":"409 Mead Rd",
    "sg:city":"Decatur",
    "sg:classifiers":[
        {
            "category":"Communications",
            "subcategory":"Film & Video Production",
            "type":"Services"
        }
    ],
    "sg:phone":"+1 404 377 8803",
    "sg:postcode":"30030",
    "sg:province":"GA",
    "sg:tags":[
        "taping"
    ],
    "wof:name":"Cat's Eye Editorial",
    "wof:placetype":"venue"
},
  "geometry": {"coordinates":[-84.304068,33.761064],"type":"Point"}
}