{
  "type": "Feature",
  "properties": {
    "addr:full":"3756 Misty Lake Ellenwood GA 30294",
    "addr:housenumber":"3756",
    "addr:postcode":"30294",
    "addr:street":"Misty Lake",
    "iso:country":"US",
    "sg:address":"3756 Misty Lake",
    "sg:city":"Ellenwood",
    "sg:classifiers":[
        {
            "category":"Social Services",
            "subcategory":"Adult Care",
            "type":"Services"
        }
    ],
    "sg:phone":"+1 404 244 0448",
    "sg:postcode":"30294",
    "sg:province":"GA",
    "sg:tags":[
        "home",
        "residential"
    ],
    "wof:name":"Assisted Living In Hm Care Inc",
    "wof:placetype":"venue"
},
  "geometry": {"coordinates":[-84.298635,33.67286],"type":"Point"}
}