{
  "type": "Feature",
  "properties": {
    "addr:full":"2755 Barrett Rd Gainesville GA 30507",
    "addr:housenumber":"2755",
    "addr:postcode":"30507",
    "addr:street":"Barrett Rd",
    "iso:country":"US",
    "sg:address":"2755 Barrett Rd",
    "sg:city":"Gainesville",
    "sg:classifiers":[
        {
            "category":"Retail",
            "subcategory":"Repair Shop",
            "type":"Services"
        }
    ],
    "sg:phone":"+1 770 365 0573",
    "sg:postcode":"30507",
    "sg:province":"GA",
    "wof:name":"Monoessys Cleaning",
    "wof:placetype":"venue"
},
  "geometry": {"coordinates":[-83.757139,34.249486],"type":"Point"}
}