{
  "type": "Feature",
  "properties": {
    "iso:country":"US",
    "sg:address":"1709 Scenic Hwy N",
    "sg:city":"Snellville",
    "sg:classifiers":[
        {
            "category":"Home & Garden",
            "subcategory":"Household Appliances",
            "type":"Retail Goods"
        },
        {
            "category":"Wholesale",
            "subcategory":"Computers",
            "type":"Manufacturing & Wholesale Goods"
        }
    ],
    "sg:phone":"+1 770 982 5467",
    "sg:postcode":"30078",
    "sg:province":"GA",
    "sg:website":"www.bestbuy.com",
    "wof:name":"Best Buy",
    "wof:placetype":"venue"
},
  "geometry": {"coordinates":[-84.011403,33.882328],"type":"Point"}
}