{
  "type": "Feature",
  "properties": {
    "iso:country":"US",
    "sg:address":"4000 Lexington Rd",
    "sg:city":"Athens",
    "sg:classifiers":[
        {
            "category":"Food & Beverages",
            "subcategory":"Groceries & Convenience Stores",
            "type":"Retail Goods"
        }
    ],
    "sg:phone":"+1 706 549 0080",
    "sg:postcode":"30605",
    "sg:province":"GA",
    "wof:name":"Quick Stop # 6",
    "wof:placetype":"venue"
},
  "geometry": {"coordinates":[-83.322502,33.938709],"type":"Point"}
}