{
  "type": "Feature",
  "properties": {
    "addr:full":"11 Gateway Blvd S Savannah GA 31419",
    "addr:housenumber":"11",
    "addr:postcode":"31419",
    "addr:street":"Gateway Blvd S",
    "iso:country":"US",
    "sg:address":"11 Gateway Blvd S",
    "sg:city":"Savannah",
    "sg:classifiers":[
        {
            "category":"Food & Beverages",
            "subcategory":"Specialty",
            "type":"Retail Goods"
        }
    ],
    "sg:phone":"+1 912 927 0696",
    "sg:postcode":"31419",
    "sg:province":"GA",
    "wof:name":"GNC",
    "wof:placetype":"venue"
},
  "geometry": {"coordinates":[-81.283249,32.000967],"type":"Point"}
}