{
  "type": "Feature",
  "properties": {
    "addr:full":"79 W Ridge Dr SE Cartersville GA 30121",
    "addr:housenumber":"79",
    "addr:postcode":"30121",
    "addr:street":"W Ridge Dr Se",
    "iso:country":"US",
    "sg:address":"79 W Ridge Dr SE",
    "sg:city":"Cartersville",
    "sg:classifiers":[
        {
            "category":"Retail",
            "subcategory":"Repair Shop",
            "type":"Services"
        }
    ],
    "sg:phone":"+1 770 606 8828",
    "sg:postcode":"30121",
    "sg:province":"GA",
    "sg:tags":[
        "tv",
        "radio",
        "television",
        "video"
    ],
    "wof:name":"Schell T V & Video",
    "wof:placetype":"venue"
},
  "geometry": {"coordinates":[-84.748941,34.201491],"type":"Point"}
}