{
  "type": "Feature",
  "properties": {
    "iso:country":"US",
    "sg:address":"330 Sidney Lanier Dr",
    "sg:city":"Oxford",
    "sg:classifiers":[
        {
            "category":"Freight",
            "type":"Transportation"
        }
    ],
    "sg:phone":"+1 770 787 6607",
    "sg:postcode":"30054",
    "sg:province":"GA",
    "sg:tags":[
        "operator",
        "trucking"
    ],
    "wof:name":"Vincent A Smith Trucking",
    "wof:placetype":"venue"
},
  "geometry": {"coordinates":[-83.890309,33.680751],"type":"Point"}
}