{
  "type": "Feature",
  "properties": {
    "addr:full":"5262 Bowman Springs Trl Flowery Branch GA 30542",
    "addr:housenumber":"5262",
    "addr:postcode":"30542",
    "addr:street":"Bowman Springs Trl",
    "iso:country":"US",
    "sg:address":"5262 Bowman Springs Trl",
    "sg:city":"Flowery Branch",
    "sg:classifiers":[
        {
            "category":"Shopping",
            "subcategory":"Beauty & Cosmetics",
            "type":"Retail Goods"
        }
    ],
    "sg:phone":"+1 770 967 8133",
    "sg:postcode":"30542",
    "sg:province":"GA",
    "sg:tags":[
        "merchandise"
    ],
    "wof:name":"Mary Kay",
    "wof:placetype":"venue"
},
  "geometry": {"coordinates":[-83.877482,34.157049],"type":"Point"}
}