{
  "type": "Feature",
  "properties": {
    "iso:country":"US",
    "sg:address":"8565 Bowden St",
    "sg:city":"Douglasville",
    "sg:classifiers":[
        {
            "category":"Professional",
            "subcategory":"Lawyer & Legal Services",
            "type":"Services"
        }
    ],
    "sg:phone":"+1 770 942 8075",
    "sg:postcode":"30134",
    "sg:province":"GA",
    "wof:name":"Wood Barry H Atty",
    "wof:placetype":"venue"
},
  "geometry": {"coordinates":[-84.74875400000001,33.747814],"type":"Point"}
}