{
  "type": "Feature",
  "properties": {
    "addr:full":"1770 Gordon Hwy Augusta GA 30904",
    "addr:housenumber":"1770",
    "addr:postcode":"30904",
    "addr:street":"Gordon Hwy",
    "iso:country":"US",
    "sg:address":"1770 Gordon Hwy",
    "sg:city":"Augusta",
    "sg:classifiers":[
        {
            "category":"Autos & Motor Vehicles",
            "subcategory":"Automobile Sales",
            "type":"Retail Goods"
        },
        {
            "category":"Autos & Motor Vehicles",
            "subcategory":"Auto Supplies",
            "type":"Retail Goods"
        },
        {
            "category":"Retail",
            "subcategory":"Auto Repair",
            "type":"Services"
        }
    ],
    "sg:phone":"+1 706 731 9000",
    "sg:postcode":"30904",
    "sg:province":"GA",
    "sg:tags":[
        "new",
        "part",
        "car",
        "accessory"
    ],
    "wof:name":"Saturn of Augusta",
    "wof:placetype":"venue"
},
  "geometry": {"coordinates":[-82.029838,33.444144],"type":"Point"}
}