{
  "type": "Feature",
  "properties": {
    "iso:country":"US",
    "sg:address":"2755 E Cherokee Dr",
    "sg:city":"Canton",
    "sg:classifiers":[
        {
            "category":"Education",
            "subcategory":"School",
            "type":"Public Place"
        }
    ],
    "sg:phone":"+1 770 345 6841",
    "sg:postcode":"30115",
    "sg:province":"GA",
    "sg:tags":[
        "high",
        "middle",
        "elementary"
    ],
    "wof:name":"Hickory Flat School",
    "wof:placetype":"venue"
},
  "geometry": {"coordinates":[-84.428299,34.158699],"type":"Point"}
}