{
  "type": "Feature",
  "properties": {
    "iso:country":"US",
    "sg:address":"1205 N Pearl Ave",
    "sg:city":"Douglas",
    "sg:classifiers":[
        {
            "category":"Retail",
            "subcategory":"Car Wash",
            "type":"Services"
        }
    ],
    "sg:phone":"+1 912 393 3393",
    "sg:postcode":"31533",
    "sg:province":"GA",
    "sg:tags":[
        "polishing",
        "washing"
    ],
    "wof:name":"John's Car Wash",
    "wof:placetype":"venue"
},
  "geometry": {"coordinates":[-82.84750699999999,31.521911],"type":"Point"}
}