{
  "type": "Feature",
  "properties": {
    "iso:country":"US",
    "sg:address":"106 Revis St",
    "sg:city":"Lagrange",
    "sg:classifiers":[
        {
            "category":"Organizations",
            "subcategory":"Religious Organization",
            "type":"Services"
        }
    ],
    "sg:phone":"+1 706 882 3858",
    "sg:postcode":"30241",
    "sg:province":"GA",
    "sg:tags":[
        "church"
    ],
    "wof:name":"St James Christian-Methodist",
    "wof:placetype":"venue"
},
  "geometry": {"coordinates":[-85.02456100000001,33.032339],"type":"Point"}
}