{
  "type": "Feature",
  "properties": {
    "iso:country":"US",
    "sg:address":"5215 Windward Pkwy",
    "sg:city":"Alpharetta",
    "sg:classifiers":[
        {
            "category":"Ice Cream",
            "type":"Food & Drink"
        }
    ],
    "sg:menulink":"http://www.allmenus.com/ga/roswell-alpharetta/221365-carvel/menu/",
    "sg:phone":"+1 770 751 9313",
    "sg:postcode":"30004",
    "sg:province":"GA",
    "sg:tags":[
        "american"
    ],
    "wof:name":"Carvel",
    "wof:placetype":"venue"
},
  "geometry": {"coordinates":[-84.275901,34.091058],"type":"Point"}
}