{
  "type": "Feature",
  "properties": {
    "iso:country":"US",
    "sg:address":"3480 Hearthstone Pl",
    "sg:city":"Douglasville",
    "sg:classifiers":[
        {
            "category":"Professional",
            "type":"Services"
        }
    ],
    "sg:phone":"+1 770 947 6681",
    "sg:postcode":"30135",
    "sg:province":"GA",
    "wof:name":"Best Home Services Inc",
    "wof:placetype":"venue"
},
  "geometry": {"coordinates":[-84.717584,33.710023],"type":"Point"}
}