{
  "type": "Feature",
  "properties": {
    "iso:country":"US",
    "sg:address":"701 Whitehead Rd",
    "sg:city":"Athens",
    "sg:classifiers":[
        {
            "category":"Building & Trades",
            "subcategory":"Landscaping Services",
            "type":"Services"
        }
    ],
    "sg:phone":"+1 706 353 2301",
    "sg:postcode":"30606",
    "sg:province":"GA",
    "wof:name":"Sartain Lawn Care",
    "wof:placetype":"venue"
},
  "geometry": {"coordinates":[-83.43647799999999,33.973561],"type":"Point"}
}