{
  "type": "Feature",
  "properties": {
    "addr:full":"114 E Main St Thomaston GA 30286",
    "addr:housenumber":"114",
    "addr:postcode":"30286",
    "addr:street":"E Main St",
    "iso:country":"US",
    "sg:address":"114 E Main St",
    "sg:city":"Thomaston",
    "sg:classifiers":[
        {
            "category":"Wholesale",
            "subcategory":"Apparel",
            "type":"Manufacturing & Wholesale Goods"
        }
    ],
    "sg:phone":"+1 706 647 3687",
    "sg:postcode":"30286",
    "sg:province":"GA",
    "wof:name":"Jere Greer Store For Men",
    "wof:placetype":"venue"
},
  "geometry": {"coordinates":[-84.32608500000001,32.887928],"type":"Point"}
}