{
  "type": "Feature",
  "properties": {
    "iso:country":"US",
    "sg:address":"4650 Park Brooke Trce",
    "sg:city":"Alpharetta",
    "sg:classifiers":[
        {
            "category":"Professional",
            "subcategory":"Business Services",
            "type":"Services"
        }
    ],
    "sg:phone":"+1 770 801 3559",
    "sg:postcode":"30022",
    "sg:province":"GA",
    "wof:name":"Jeffrey Twait",
    "wof:placetype":"venue"
},
  "geometry": {"coordinates":[-84.246441,34.056433],"type":"Point"}
}