{
  "type": "Feature",
  "properties": {
    "iso:country":"US",
    "sg:address":"3775 Sixes Rd",
    "sg:city":"Canton",
    "sg:classifiers":[
        {
            "category":"Building & Trades",
            "subcategory":"Locksmith",
            "type":"Services"
        }
    ],
    "sg:phone":"+1 678 369 5679",
    "sg:postcode":"30114",
    "sg:province":"GA",
    "sg:tags":[
        "key"
    ],
    "wof:name":"777 Emergency Locksmith",
    "wof:placetype":"venue"
},
  "geometry": {"coordinates":[-84.55021499999999,34.178019],"type":"Point"}
}