{
  "type": "Feature",
  "properties": {
    "iso:country":"US",
    "sg:address":"3332 Chattahoochee Cir",
    "sg:city":"Roswell",
    "sg:classifiers":[
        {
            "category":"Professional",
            "subcategory":"Business Services",
            "type":"Services"
        }
    ],
    "sg:phone":"+1 404 210 7914",
    "sg:postcode":"30075",
    "sg:province":"GA",
    "wof:name":"App Solutions",
    "wof:placetype":"venue"
},
  "geometry": {"coordinates":[-84.354186,34.006329],"type":"Point"}
}