{
  "type": "Feature",
  "properties": {
    "iso:country":"US",
    "sg:address":"11193 Hwy 53 E",
    "sg:city":"Marble Hill",
    "sg:classifiers":[
        {
            "category":"Autos & Motor Vehicles",
            "subcategory":"Automobile Sales",
            "type":"Retail Goods"
        }
    ],
    "sg:phone":"+1 770 893 1890",
    "sg:postcode":"30148",
    "sg:province":"GA",
    "sg:tags":[
        "car",
        "dealer"
    ],
    "wof:name":"Twin Oakes Automotive",
    "wof:placetype":"venue"
},
  "geometry": {"coordinates":[-84.31456300000001,34.417094],"type":"Point"}
}