{
  "type": "Feature",
  "properties": {
    "iso:country":"US",
    "sg:address":"449 Pleasant Hill Rd NW Ste 101",
    "sg:city":"Lilburn",
    "sg:classifiers":[
        {
            "category":"Health Services",
            "subcategory":"Dentist",
            "type":"Services"
        }
    ],
    "sg:phone":"+1 770 564 9906",
    "sg:postcode":"30047",
    "sg:province":"GA",
    "sg:website":"www.advancecosmeticdentistry.com",
    "wof:name":"Gardner Randolph DMD",
    "wof:placetype":"venue"
},
  "geometry": {"coordinates":[-84.11309799999999,33.909698],"type":"Point"}
}