{
  "type": "Feature",
  "properties": {
    "addr:full":"3673 Aldea Dr Decatur GA 30032",
    "addr:housenumber":"3673",
    "addr:postcode":"30032",
    "addr:street":"Aldea Dr",
    "iso:country":"US",
    "sg:address":"3673 Aldea Dr",
    "sg:city":"Decatur",
    "sg:classifiers":[
        {
            "category":"Shopping",
            "subcategory":"Discount & Variety Stores",
            "type":"Retail Goods"
        }
    ],
    "sg:phone":"+1 404 399 1172",
    "sg:postcode":"30032",
    "sg:province":"GA",
    "sg:tags":[
        "merchandise",
        "general"
    ],
    "wof:name":"D & A Enterprise",
    "wof:placetype":"venue"
},
  "geometry": {"coordinates":[-84.24021500000001,33.750721],"type":"Point"}
}