{
  "type": "Feature",
  "properties": {
    "iso:country":"US",
    "sg:address":"3354 Saddle Brook Dr",
    "sg:city":"Hephzibah",
    "sg:classifiers":[
        {
            "category":"Building & Trades",
            "subcategory":"Landscaping Services",
            "type":"Services"
        }
    ],
    "sg:phone":"+1 706 798 1402",
    "sg:postcode":"30815",
    "sg:province":"GA",
    "wof:name":"Countour Lawn Service",
    "wof:placetype":"venue"
},
  "geometry": {"coordinates":[-82.104105,33.394249],"type":"Point"}
}