{
  "type": "Feature",
  "properties": {
    "addr:full":"91 N 4th St Tennille GA 31089",
    "addr:housenumber":"91",
    "addr:postcode":"31089",
    "addr:street":"N 4Th St",
    "iso:country":"US",
    "sg:address":"91 N 4th St",
    "sg:city":"Tennille",
    "sg:classifiers":[
        {
            "category":"Food & Beverages",
            "subcategory":"Groceries & Convenience Stores",
            "type":"Retail Goods"
        }
    ],
    "sg:phone":"+1 478 552 9358",
    "sg:postcode":"31089",
    "sg:province":"GA",
    "wof:name":"Hungry Hunter",
    "wof:placetype":"venue"
},
  "geometry": {"coordinates":[-82.810236,32.93657],"type":"Point"}
}