{
  "type": "Feature",
  "properties": {
    "addr:full":"218 Leake St Cartersville GA 30120",
    "addr:housenumber":"218",
    "addr:postcode":"30120",
    "addr:street":"Leake St",
    "iso:country":"US",
    "sg:address":"218 Leake St",
    "sg:city":"Cartersville",
    "sg:classifiers":[
        {
            "category":"Professional",
            "subcategory":"Management & Consulting",
            "type":"Services"
        }
    ],
    "sg:phone":"+1 770 386 3147",
    "sg:postcode":"30120",
    "sg:province":"GA",
    "sg:tags":[
        "business"
    ],
    "wof:name":"Underwood & Associates LLC",
    "wof:placetype":"venue"
},
  "geometry": {"coordinates":[-84.799374,34.162557],"type":"Point"}
}