{
  "type": "Feature",
  "properties": {
    "addr:full":"7000 Central Parkway NE Atlanta GA 30328",
    "addr:housenumber":"7000",
    "addr:postcode":"30328",
    "addr:street":"Central Parkway Ne",
    "iso:country":"US",
    "sg:address":"7000 Central Parkway NE",
    "sg:city":"Atlanta",
    "sg:classifiers":[
        {
            "category":"Banks & Credit Unions",
            "subcategory":"Bank",
            "type":"Services"
        }
    ],
    "sg:phone":"+1 770 395 6408",
    "sg:postcode":"30328",
    "sg:province":"GA",
    "sg:website":"www.wellsfargo.com",
    "wof:name":"Wells Fargo Bank",
    "wof:placetype":"venue"
},
  "geometry": {"coordinates":[-84.349543,33.927167],"type":"Point"}
}