{
  "type": "Feature",
  "properties": {
    "iso:country":"US",
    "sg:address":"1881 Myrtle Dr SW Apt 216",
    "sg:city":"Atlanta",
    "sg:classifiers":[
        {
            "category":"Place Of Worship",
            "subcategory":"Church",
            "type":"Public Place"
        },
        {
            "category":"Place Of Worship",
            "type":"Public Place"
        }
    ],
    "sg:phone":"+1 404 758 4562",
    "sg:postcode":"30311",
    "sg:province":"GA",
    "sg:tags":[
        "churches-baptist-general",
        "churches-baptist"
    ],
    "wof:name":"Baptist Towers Corp",
    "wof:placetype":"venue"
},
  "geometry": {"coordinates":[-84.45497899999999,33.704598],"type":"Point"}
}