{
  "type": "Feature",
  "properties": {
    "addr:full":"5825 Timberlane Ter NE Atlanta GA 30328",
    "addr:housenumber":"5825",
    "addr:postcode":"30328",
    "addr:street":"Timberlane Ter Ne",
    "iso:country":"US",
    "sg:address":"5825 Timberlane Ter NE",
    "sg:city":"Atlanta",
    "sg:classifiers":[
        {
            "category":"Professional",
            "subcategory":"Business Services",
            "type":"Services"
        }
    ],
    "sg:phone":"+1 404 843 8088",
    "sg:postcode":"30328",
    "sg:province":"GA",
    "wof:name":"Oliver Home Solutions Inc",
    "wof:placetype":"venue"
},
  "geometry": {"coordinates":[-84.36389,33.913248],"type":"Point"}
}