{
  "type": "Feature",
  "properties": {
    "addr:full":"2601 Dawson Rd Albany GA 31707",
    "addr:housenumber":"2601",
    "addr:postcode":"31707",
    "addr:street":"Dawson Rd",
    "iso:country":"US",
    "sg:address":"2601 Dawson Rd",
    "sg:city":"Albany",
    "sg:classifiers":[
        {
            "category":"Home & Garden",
            "subcategory":"Building Materials",
            "type":"Retail Goods"
        }
    ],
    "sg:phone":"+1 229 435 2360",
    "sg:postcode":"31707",
    "sg:province":"GA",
    "sg:tags":[
        "furnishing",
        "accessory"
    ],
    "sg:website":"www.kirklands.com",
    "wof:name":"Kirkland's",
    "wof:placetype":"venue"
},
  "geometry": {"coordinates":[-84.217823,31.614867],"type":"Point"}
}