{
  "type": "Feature",
  "properties": {
    "addr:full":"2980 Cobb Parkway Suite 192 Atlanta GA 30339",
    "addr:housenumber":"2980",
    "addr:postcode":"30339",
    "addr:street":"Cobb Parkway Suite 192",
    "iso:country":"US",
    "sg:address":"2980 Cobb Parkway Suite 192",
    "sg:city":"Atlanta",
    "sg:classifiers":[
        {
            "category":"Shopping",
            "subcategory":"Jewelry",
            "type":"Retail Goods"
        }
    ],
    "sg:phone":"+1 770 951 8881",
    "sg:postcode":"30339",
    "sg:province":"GA",
    "sg:website":"www.cachetjewelry.com",
    "wof:name":"Cachet Fine Jewelry",
    "wof:placetype":"venue"
},
  "geometry": {"coordinates":[-84.462687,33.880733],"type":"Point"}
}