{
  "type": "Feature",
  "properties": {
    "iso:country":"US",
    "sg:address":"510 Shorter Ave",
    "sg:city":"Rome",
    "sg:classifiers":[
        {
            "category":"Restaurant",
            "type":"Food & Drink"
        }
    ],
    "sg:phone":"+1 706 563 8194",
    "sg:postcode":"30165",
    "sg:province":"GA",
    "sg:tags":[
        "eating"
    ],
    "sg:website":"www.dominos.com",
    "wof:name":"Domino's Pizza",
    "wof:placetype":"venue"
},
  "geometry": {"coordinates":[-85.197997,34.26507],"type":"Point"}
}