{
  "type": "Feature",
  "properties": {
    "iso:country":"US",
    "sg:address":"1232 State Rte 74",
    "sg:city":"Senoia",
    "sg:classifiers":[
        {
            "category":"Shopping",
            "subcategory":"Pharmacy",
            "type":"Retail Goods"
        }
    ],
    "sg:phone":"+1 770 631 3766",
    "sg:postcode":"30276",
    "sg:province":"GA",
    "wof:name":"Eckerd Drugs",
    "wof:placetype":"venue"
},
  "geometry": {"coordinates":[-84.520807,33.338854],"type":"Point"}
}