{
  "type": "Feature",
  "properties": {
    "addr:full":"4031 Covey Ln Douglasville GA 30135",
    "addr:housenumber":"4031",
    "addr:postcode":"30135",
    "addr:street":"Covey Ln",
    "iso:country":"US",
    "sg:address":"4031 Covey Ln",
    "sg:city":"Douglasville",
    "sg:classifiers":[
        {
            "category":"Building & Trades",
            "subcategory":"Construction",
            "type":"Services"
        }
    ],
    "sg:phone":"+1 770 577 6135",
    "sg:postcode":"30135",
    "sg:province":"GA",
    "sg:tags":[
        "concrete",
        "contractor"
    ],
    "wof:name":"Atlanta Concrete Cutting",
    "wof:placetype":"venue"
},
  "geometry": {"coordinates":[-84.767988,33.695679],"type":"Point"}
}