{
  "type": "Feature",
  "properties": {
    "iso:country":"US",
    "sg:address":"6344 Cash Ct NW",
    "sg:city":"Norcross",
    "sg:classifiers":[
        {
            "category":"Shopping",
            "type":"Retail Goods"
        }
    ],
    "sg:phone":"+1 770 449 6084",
    "sg:postcode":"30071",
    "sg:province":"GA",
    "sg:tags":[
        "merchandise"
    ],
    "wof:name":"Wireless Retail",
    "wof:placetype":"venue"
},
  "geometry": {"coordinates":[-84.239442,33.942977],"type":"Point"}
}