{
  "type": "Feature",
  "properties": {
    "iso:country":"US",
    "sg:address":"187 Roberson Ln",
    "sg:city":"Milledgeville",
    "sg:classifiers":[
        {
            "category":"Personal",
            "type":"Services"
        }
    ],
    "sg:phone":"+1 478 414 1395",
    "sg:postcode":"31027",
    "sg:province":"GA",
    "sg:tags":[
        "therapist",
        "massage"
    ],
    "wof:name":"Georgia Academy-Theraputic",
    "wof:placetype":"venue"
},
  "geometry": {"coordinates":[-82.87309500000001,32.553617],"type":"Point"}
}