{
  "type": "Feature",
  "properties": {
    "addr:full":"301 Monument St Augusta GA 30901",
    "addr:housenumber":"301",
    "addr:postcode":"30901",
    "addr:street":"Monument St",
    "iso:country":"US",
    "sg:address":"301 Monument St",
    "sg:city":"Augusta",
    "sg:classifiers":[
        {
            "category":"Professional",
            "subcategory":"Management & Consulting",
            "type":"Services"
        }
    ],
    "sg:phone":"+1 706 312 2000",
    "sg:postcode":"30901",
    "sg:province":"GA",
    "wof:name":"American Express",
    "wof:placetype":"venue"
},
  "geometry": {"coordinates":[-81.96148599999999,33.471738],"type":"Point"}
}