{
  "type": "Feature",
  "properties": {
    "addr:full":"4122 Pebble Creek Dr Valdosta GA 31605",
    "addr:housenumber":"4122",
    "addr:postcode":"31605",
    "addr:street":"Pebble Creek Dr",
    "iso:country":"US",
    "sg:address":"4122 Pebble Creek Dr",
    "sg:city":"Valdosta",
    "sg:classifiers":[
        {
            "category":"Local Transit",
            "type":"Transportation"
        }
    ],
    "sg:phone":"+1 229 245 9464",
    "sg:postcode":"31605",
    "sg:province":"GA",
    "sg:tags":[
        "public"
    ],
    "wof:name":"Flex-Tran Transportation",
    "wof:placetype":"venue"
},
  "geometry": {"coordinates":[-83.24795399999999,30.945362],"type":"Point"}
}