{
  "type": "Feature",
  "properties": {
    "addr:full":"4467 Lemon St Acworth GA 30101",
    "addr:housenumber":"4467",
    "addr:postcode":"30101",
    "addr:street":"Lemon St",
    "iso:country":"US",
    "sg:address":"4467 Lemon St",
    "sg:city":"Acworth",
    "sg:classifiers":[
        {
            "category":"Health Services",
            "subcategory":"Doctor",
            "type":"Services"
        },
        {
            "category":"Health Services",
            "subcategory":"Health Practitioner",
            "type":"Services"
        }
    ],
    "sg:phone":"+1 770 917 0948",
    "sg:postcode":"30101",
    "sg:province":"GA",
    "sg:tags":[
        "control",
        "physician",
        "management",
        "weight",
        "loss",
        "gynecology",
        "endocrinology",
        "surgeons",
        "gynecologist",
        "surgeon",
        "obstetrician",
        "metabolism",
        "diabetes"
    ],
    "sg:website":"http://www.realpagessites.com/martinralphh",
    "wof:name":"Martin Ralph H DO PC",
    "wof:placetype":"venue"
},
  "geometry": {"coordinates":[-84.6763,34.0662],"type":"Point"}
}