{
  "type": "Feature",
  "properties": {
    "addr:full":"100 Eagle Pkwy Adairsville GA 30103",
    "addr:housenumber":"100",
    "addr:postcode":"30103",
    "addr:street":"Eagle Pkwy",
    "iso:country":"US",
    "sg:address":"100 Eagle Pkwy",
    "sg:city":"Adairsville",
    "sg:classifiers":[
        {
            "category":"Manufacturing",
            "subcategory":"Tools & Machinery",
            "type":"Manufacturing & Wholesale Goods"
        }
    ],
    "sg:phone":"+1 770 773 3875",
    "sg:postcode":"30103",
    "sg:province":"GA",
    "sg:tags":[
        "industry"
    ],
    "sg:website":"www.eaglefloors.com",
    "wof:name":"Eagle Solutions",
    "wof:placetype":"venue"
},
  "geometry": {"coordinates":[-84.93017399999999,34.376927],"type":"Point"}
}