{
  "type": "Feature",
  "properties": {
    "iso:country":"US",
    "sg:address":"11125 Glenbarr Dr",
    "sg:city":"Duluth",
    "sg:classifiers":[
        {
            "category":"Professional",
            "subcategory":"Computer Services",
            "type":"Services"
        }
    ],
    "sg:phone":"+1 770 495 6497",
    "sg:postcode":"30097",
    "sg:province":"GA",
    "sg:tags":[
        "programing",
        "custom"
    ],
    "wof:name":"Sys Co Intl Inc",
    "wof:placetype":"venue"
},
  "geometry": {"coordinates":[-84.172523,34.040961],"type":"Point"}
}