{
  "type": "Feature",
  "properties": {
    "iso:country":"US",
    "sg:address":"1500 Market Place Blvd",
    "sg:city":"Cumming",
    "sg:classifiers":[
        {
            "category":"Personal",
            "subcategory":"Beauty Salon",
            "type":"Services"
        }
    ],
    "sg:phone":"+1 770 205 8155",
    "sg:postcode":"30041",
    "sg:province":"GA",
    "sg:tags":[
        "shop"
    ],
    "wof:name":"Regal Nails",
    "wof:placetype":"venue"
},
  "geometry": {"coordinates":[-84.130679,34.183185],"type":"Point"}
}