{
  "type": "Feature",
  "properties": {
    "iso:country":"US",
    "sg:address":"331 W Currahee St",
    "sg:city":"Toccoa",
    "sg:classifiers":[
        {
            "category":"Autos & Motor Vehicles",
            "subcategory":"Auto Supplies",
            "type":"Retail Goods"
        }
    ],
    "sg:phone":"+1 706 886 3111",
    "sg:postcode":"30577",
    "sg:province":"GA",
    "sg:tags":[
        "tire"
    ],
    "wof:name":"Toccoa Tire & Recapping Co",
    "wof:placetype":"venue"
},
  "geometry": {"coordinates":[-83.334281,34.577213],"type":"Point"}
}