{
  "type": "Feature",
  "properties": {
    "iso:country":"US",
    "sg:address":"3010 Royal Blvd S",
    "sg:city":"Alpharetta",
    "sg:classifiers":[
        {
            "category":"Health Services",
            "subcategory":"Clinic",
            "type":"Services"
        }
    ],
    "sg:phone":"+1 770 751 7858",
    "sg:postcode":"30022",
    "sg:province":"GA",
    "wof:name":"1 800 Health Plan",
    "wof:placetype":"venue"
},
  "geometry": {"coordinates":[-84.271378,34.054799],"type":"Point"}
}