{
  "type": "Feature",
  "properties": {
    "iso:country":"US",
    "sg:address":"501 Pulliam St SW Ste 144",
    "sg:city":"Atlanta",
    "sg:phone":"+1 404 522 2200",
    "sg:postcode":"30312",
    "sg:province":"GA",
    "wof:name":"Union Clinic Of Chiropractors",
    "wof:placetype":"venue"
},
  "geometry": {"coordinates":[-84.392601,33.742599],"type":"Point"}
}