{
  "type": "Feature",
  "properties": {
    "iso:country":"US",
    "sg:address":"1055 Ozora Rd",
    "sg:city":"Loganville",
    "sg:classifiers":[
        {
            "category":"Building & Trades",
            "subcategory":"Construction",
            "type":"Services"
        }
    ],
    "sg:phone":"+1 770 466 5460",
    "sg:postcode":"30052",
    "sg:province":"GA",
    "sg:tags":[
        "paving",
        "contractor"
    ],
    "wof:name":"Puckett Construction Co",
    "wof:placetype":"venue"
},
  "geometry": {"coordinates":[-83.89931199999999,33.891992],"type":"Point"}
}