{
  "type": "Feature",
  "properties": {
    "addr:full":"328 E Montgomery Xrd Savannah GA 31406",
    "addr:housenumber":"328",
    "addr:postcode":"31406",
    "addr:street":"E Montgomery Xrd",
    "iso:country":"US",
    "sg:address":"328 E Montgomery Xrd",
    "sg:city":"Savannah",
    "sg:classifiers":[
        {
            "category":"Professional",
            "type":"Services"
        }
    ],
    "sg:phone":"+1 912 691 1741",
    "sg:postcode":"31406",
    "sg:province":"GA",
    "sg:tags":[
        "establishment"
    ],
    "wof:name":"Ground Control",
    "wof:placetype":"venue"
},
  "geometry": {"coordinates":[-81.11260299999999,31.995879],"type":"Point"}
}