{
  "type": "Feature",
  "properties": {
    "addr:full":"133 Peachtree Street Atlanta GA 30303",
    "addr:housenumber":"133",
    "addr:postcode":"30303",
    "addr:street":"Peachtree Street",
    "iso:country":"US",
    "sg:address":"133 Peachtree Street",
    "sg:city":"Atlanta",
    "sg:classifiers":[
        {
            "category":"Building & Trades",
            "subcategory":"Construction",
            "type":"Services"
        }
    ],
    "sg:phone":"+1 770 872 4649",
    "sg:postcode":"30303",
    "sg:province":"GA",
    "sg:tags":[
        "interior",
        "design"
    ],
    "sg:website":"kitchenremodelerinatlanta.info",
    "wof:name":"All South Granite and Marble, LLC",
    "wof:placetype":"venue"
},
  "geometry": {"coordinates":[-84.39308,33.751204],"type":"Point"}
}