{
  "type": "Feature",
  "properties": {
    "iso:country":"US",
    "sg:address":"24 S East St",
    "sg:city":"Jasper",
    "sg:classifiers":[
        {
            "category":"Shopping",
            "subcategory":"Gifts & Souvenirs",
            "type":"Retail Goods"
        }
    ],
    "sg:phone":"+1 706 253 3218",
    "sg:postcode":"30143",
    "sg:province":"GA",
    "sg:tags":[
        "shop"
    ],
    "wof:name":"Jennifer Ann's Gifts",
    "wof:placetype":"venue"
},
  "geometry": {"coordinates":[-84.429261,34.468132],"type":"Point"}
}