{
  "type": "Feature",
  "properties": {
    "addr:full":"2711 Wagon Trl Marietta GA 30008",
    "addr:housenumber":"2711",
    "addr:postcode":"30008",
    "addr:street":"Wagon Trl",
    "iso:country":"US",
    "sg:address":"2711 Wagon Trl",
    "sg:city":"Marietta",
    "sg:classifiers":[
        {
            "category":"Retail",
            "subcategory":"Laundry & Dry Cleaning",
            "type":"Services"
        }
    ],
    "sg:phone":"+1 770 429 1978",
    "sg:postcode":"30008",
    "sg:province":"GA",
    "sg:tags":[
        "drycleaning",
        "plant"
    ],
    "wof:name":"King Service Cleaners",
    "wof:placetype":"venue"
},
  "geometry": {"coordinates":[-84.604219,33.888237],"type":"Point"}
}