{
  "type": "Feature",
  "properties": {
    "iso:country":"US",
    "sg:address":"380 Dahlonega Rd",
    "sg:city":"Cumming",
    "sg:classifiers":[
        {
            "category":"Banks & Credit Unions",
            "subcategory":"Bank",
            "type":"Services"
        }
    ],
    "sg:phone":"+1 770 205 1122",
    "sg:postcode":"30040",
    "sg:province":"GA",
    "sg:tags":[
        "financing",
        "consumer"
    ],
    "wof:name":"G & M Intl LLC",
    "wof:placetype":"venue"
},
  "geometry": {"coordinates":[-84.13209000000001,34.221612],"type":"Point"}
}