{
  "type": "Feature",
  "properties": {
    "iso:country":"US",
    "sg:address":"1938 Peachtree Rd NW",
    "sg:city":"Atlanta",
    "sg:classifiers":[
        {
            "category":"Health Services",
            "subcategory":"Doctor",
            "type":"Services"
        },
        {
            "category":"Health Services",
            "subcategory":"Dentist",
            "type":"Services"
        }
    ],
    "sg:phone":"+1 404 351 9307",
    "sg:postcode":"30309",
    "sg:province":"GA",
    "sg:tags":[
        "dentists-oral",
        "physician",
        "maxillofacial",
        "surgeons",
        "surgery",
        "oral"
    ],
    "wof:name":"Stafford Marion W DMD",
    "wof:placetype":"venue"
},
  "geometry": {"coordinates":[-84.393799,33.807499],"type":"Point"}
}