{
  "type": "Feature",
  "properties": {
    "iso:country":"US",
    "sg:address":"23 Edmondson St",
    "sg:city":"Summerville",
    "sg:classifiers":[
        {
            "category":"Social Services",
            "subcategory":"Child Care",
            "type":"Services"
        }
    ],
    "sg:phone":"+1 706 859 7961",
    "sg:postcode":"30747",
    "sg:province":"GA",
    "sg:tags":[
        "day"
    ],
    "wof:name":"Summerville Montessori School",
    "wof:placetype":"venue"
},
  "geometry": {"coordinates":[-85.343206,34.47383],"type":"Point"}
}