{
  "type": "Feature",
  "properties": {
    "iso:country":"US",
    "sg:address":"3759 Glenwood Rd",
    "sg:city":"Decatur",
    "sg:classifiers":[
        {
            "category":"Retail",
            "subcategory":"Animal Services",
            "type":"Services"
        }
    ],
    "sg:phone":"+1 770 333 7870",
    "sg:postcode":"30032",
    "sg:province":"GA",
    "sg:tags":[
        "training",
        "dog"
    ],
    "wof:name":"K Nine Express",
    "wof:placetype":"venue"
},
  "geometry": {"coordinates":[-84.264056,33.738049],"type":"Point"}
}