{
  "type": "Feature",
  "properties": {
    "iso:country":"US",
    "sg:address":"541 10th St NE 333",
    "sg:city":"Atlanta",
    "sg:classifiers":[
        {
            "category":"Real Estate",
            "subcategory":"Surveying",
            "type":"Services"
        }
    ],
    "sg:phone":"+1 404 438 3205",
    "sg:postcode":"30309",
    "sg:province":"GA",
    "sg:tags":[
        "planning",
        "land"
    ],
    "wof:name":"Ed Homeowners",
    "wof:placetype":"venue"
},
  "geometry": {"coordinates":[-84.370096,33.781771],"type":"Point"}
}