{
  "type": "Feature",
  "properties": {
    "addr:full":"3705 Trickum Rd NE Marietta GA 30066",
    "addr:housenumber":"3705",
    "addr:postcode":"30066",
    "addr:street":"Trickum Rd Ne",
    "iso:country":"US",
    "sg:address":"3705 Trickum Rd NE",
    "sg:city":"Marietta",
    "sg:classifiers":[
        {
            "category":"Retail",
            "subcategory":"Auto Repair",
            "type":"Services"
        }
    ],
    "sg:phone":"+1 770 928 0006",
    "sg:postcode":"30066",
    "sg:province":"GA",
    "wof:name":"Alpha & Omega Automotive Inc",
    "wof:placetype":"venue"
},
  "geometry": {"coordinates":[-84.481796,34.0411],"type":"Point"}
}