{
  "type": "Feature",
  "properties": {
    "addr:full":"5243 Snapfinger Woods Dr, Suite 103 Decatur GA 30035",
    "addr:housenumber":"5243",
    "addr:postcode":"30035",
    "addr:street":"Snapfinger Woods Dr Suite 103",
    "iso:country":"US",
    "sg:address":"5243 Snapfinger Woods Dr, Suite 103",
    "sg:city":"Decatur",
    "sg:classifiers":[
        {
            "category":"Health Services",
            "subcategory":"Doctor",
            "type":"Services"
        }
    ],
    "sg:phone":"+1 770 981 3511",
    "sg:postcode":"30035",
    "sg:province":"GA",
    "sg:tags":[
        "physician",
        "family",
        "practice",
        "surgeons",
        "internal",
        "medicine",
        "surgeon"
    ],
    "sg:website":"http://www.williammcgaritymd.com",
    "wof:name":"William C McGarity, Jr. M.D. PC",
    "wof:placetype":"venue"
},
  "geometry": {"coordinates":[-84.1754,33.709353],"type":"Point"}
}