{
  "type": "Feature",
  "properties": {
    "addr:full":"4022 Victory Dr Columbus GA 31903",
    "addr:housenumber":"4022",
    "addr:postcode":"31903",
    "addr:street":"Victory Dr",
    "iso:country":"US",
    "sg:address":"4022 Victory Dr",
    "sg:city":"Columbus",
    "sg:classifiers":[
        {
            "category":"Restaurant",
            "type":"Food & Drink"
        }
    ],
    "sg:menulink":"http://www.allmenus.com/ga/columbus/55795-subway/menu/",
    "sg:phone":"+1 706 689 3433",
    "sg:postcode":"31903",
    "sg:province":"GA",
    "sg:tags":[
        "american",
        "sandwich"
    ],
    "wof:name":"Subway",
    "wof:placetype":"venue"
},
  "geometry": {"coordinates":[-84.94070000000001,32.40934],"type":"Point"}
}