{
  "type": "Feature",
  "properties": {
    "addr:full":"3342 Pretty Branch Dr SE Smyrna GA 30080",
    "addr:housenumber":"3342",
    "addr:postcode":"30080",
    "addr:street":"Pretty Branch Dr Se",
    "iso:country":"US",
    "sg:address":"3342 Pretty Branch Dr SE",
    "sg:city":"Smyrna",
    "sg:classifiers":[
        {
            "category":"Professional",
            "subcategory":"Business Services",
            "type":"Services"
        }
    ],
    "sg:phone":"+1 770 432 3523",
    "sg:postcode":"30080",
    "sg:province":"GA",
    "sg:tags":[
        "embroidery"
    ],
    "wof:name":"Linda Couey Embroidery & Gifts",
    "wof:placetype":"venue"
},
  "geometry": {"coordinates":[-84.513181,33.872073],"type":"Point"}
}