{
  "type": "Feature",
  "properties": {
    "iso:country":"US",
    "sg:address":"307 E Jane St",
    "sg:city":"Valdosta",
    "sg:classifiers":[
        {
            "category":"Organizations",
            "subcategory":"Membership Organization",
            "type":"Services"
        }
    ],
    "sg:phone":"+1 229 247 3266",
    "sg:postcode":"31601",
    "sg:province":"GA",
    "sg:tags":[
        "society",
        "humane"
    ],
    "wof:name":"Humane Society Spay & Neuter",
    "wof:placetype":"venue"
},
  "geometry": {"coordinates":[-83.28170299999999,30.845834],"type":"Point"}
}