{
  "type": "Feature",
  "properties": {
    "iso:country":"US",
    "sg:address":"5340 Roswell Rd",
    "sg:city":"Atlanta",
    "sg:classifiers":[
        {
            "category":"Communications",
            "type":"Services"
        }
    ],
    "sg:phone":"+1 404 303 9997",
    "sg:postcode":"30342",
    "sg:province":"GA",
    "sg:tags":[
        "equipment",
        "satellite",
        "system"
    ],
    "wof:name":"Casa Brazil",
    "wof:placetype":"venue"
},
  "geometry": {"coordinates":[-84.379695,33.900931],"type":"Point"}
}