{
  "type": "Feature",
  "properties": {
    "addr:full":"601 Talmadge Ave Savannah GA 31408",
    "addr:housenumber":"601",
    "addr:postcode":"31408",
    "addr:street":"Talmadge Ave",
    "iso:country":"US",
    "sg:address":"601 Talmadge Ave",
    "sg:city":"Savannah",
    "sg:classifiers":[
        {
            "category":"Organizations",
            "subcategory":"Religious Organization",
            "type":"Services"
        }
    ],
    "sg:phone":"+1 912 965 1333",
    "sg:postcode":"31408",
    "sg:province":"GA",
    "wof:name":"Woodlawn United Methdst Church",
    "wof:placetype":"venue"
},
  "geometry": {"coordinates":[-81.176812,32.089334],"type":"Point"}
}