{
  "type": "Feature",
  "properties": {
    "addr:full":"1615 Charleston Walk SE Atlanta GA 30316",
    "addr:housenumber":"1615",
    "addr:postcode":"30316",
    "addr:street":"Charleston Walk Se",
    "iso:country":"US",
    "sg:address":"1615 Charleston Walk SE",
    "sg:city":"Atlanta",
    "sg:classifiers":[
        {
            "category":"Real Estate",
            "subcategory":"Real Estate Agent",
            "type":"Services"
        },
        {
            "category":"Banks & Credit Unions",
            "subcategory":"Financial Services",
            "type":"Services"
        }
    ],
    "sg:phone":"+1 404 212 2221",
    "sg:postcode":"30316",
    "sg:province":"GA",
    "sg:tags":[
        "investment"
    ],
    "wof:name":"Affiliation Holdings LLC",
    "wof:placetype":"venue"
},
  "geometry": {"coordinates":[-84.32401,33.721902],"type":"Point"}
}