{
  "type": "Feature",
  "properties": {
    "iso:country":"US",
    "sg:address":"2915 Watson Blvd",
    "sg:city":"Warner Robins",
    "sg:classifiers":[
        {
            "category":"Restaurant",
            "type":"Food & Drink"
        }
    ],
    "sg:phone":"+1 478 971 1527",
    "sg:postcode":"31093",
    "sg:province":"GA",
    "sg:tags":[
        "eating"
    ],
    "wof:name":"Cheddar's Casual Cafe",
    "wof:placetype":"venue"
},
  "geometry": {"coordinates":[-83.682999,32.618198],"type":"Point"}
}