{
  "type": "Feature",
  "properties": {
    "addr:full":"328 Osprey Dr Richmond Hill GA 31324",
    "addr:housenumber":"328",
    "addr:postcode":"31324",
    "addr:street":"Osprey Dr",
    "iso:country":"US",
    "sg:address":"328 Osprey Dr",
    "sg:city":"Richmond Hill",
    "sg:classifiers":[
        {
            "category":"Building & Trades",
            "subcategory":"Pest Control",
            "type":"Services"
        }
    ],
    "sg:phone":"+1 912 756 4636",
    "sg:postcode":"31324",
    "sg:province":"GA",
    "wof:name":"Ebners Exterminating",
    "wof:placetype":"venue"
},
  "geometry": {"coordinates":[-81.32320799999999,31.92388],"type":"Point"}
}