{
  "type": "Feature",
  "properties": {
    "iso:country":"US",
    "sg:address":"2571 Candler Rd",
    "sg:city":"Decatur",
    "sg:classifiers":[
        {
            "category":"Building & Trades",
            "subcategory":"Landscaping Services",
            "type":"Services"
        }
    ],
    "sg:phone":"+1 404 243 3448",
    "sg:postcode":"30032",
    "sg:province":"GA",
    "sg:tags":[
        "landscape"
    ],
    "wof:name":"Larry Holland",
    "wof:placetype":"venue"
},
  "geometry": {"coordinates":[-84.273212,33.714926],"type":"Point"}
}