{
  "type": "Feature",
  "properties": {
    "iso:country":"US",
    "sg:address":"5145 Buford Hwy NE",
    "sg:city":"Doraville",
    "sg:classifiers":[
        {
            "category":"Utilities",
            "subcategory":"Mobile Phone",
            "type":"Services"
        }
    ],
    "sg:phone":"+1 770 455 0355",
    "sg:postcode":"30329",
    "sg:province":"GA",
    "sg:tags":[
        "telephone",
        "cellular"
    ],
    "wof:name":"Pager Expo",
    "wof:placetype":"venue"
},
  "geometry": {"coordinates":[-84.283108,33.894688],"type":"Point"}
}