{
  "type": "Feature",
  "properties": {
    "addr:full":"4051 Singing Post Ln Roswell GA 30075",
    "addr:housenumber":"4051",
    "addr:postcode":"30075",
    "addr:street":"Singing Post Ln",
    "iso:country":"US",
    "sg:address":"4051 Singing Post Ln",
    "sg:city":"Roswell",
    "sg:classifiers":[
        {
            "category":"Professional",
            "subcategory":"Engineering",
            "type":"Services"
        }
    ],
    "sg:phone":"+1 770 998 5754",
    "sg:postcode":"30075",
    "sg:province":"GA",
    "wof:name":"James Downs Associates Inc",
    "wof:placetype":"venue"
},
  "geometry": {"coordinates":[-84.433162,34.036793],"type":"Point"}
}