{
  "type": "Feature",
  "properties": {
    "addr:full":"3576 Highway 138 SE Stockbridge GA 30281",
    "addr:housenumber":"3576",
    "addr:postcode":"30281",
    "addr:street":"Highway 138 Se",
    "iso:country":"US",
    "sg:address":"3576 Highway 138 SE",
    "sg:city":"Stockbridge",
    "sg:classifiers":[
        {
            "category":"Coffee & Tea",
            "type":"Food & Drink"
        },
        {
            "category":"Restaurant",
            "type":"Food & Drink"
        }
    ],
    "sg:phone":"+1 678 289 5080",
    "sg:postcode":"30281",
    "sg:province":"GA",
    "sg:tags":[
        "espresso"
    ],
    "wof:name":"Rainy's Cafe",
    "wof:placetype":"venue"
},
  "geometry": {"coordinates":[-84.27420600000001,33.550604],"type":"Point"}
}