{
  "type": "Feature",
  "properties": {
    "addr:full":"2111 Candler Rd Decatur GA 30032",
    "addr:housenumber":"2111",
    "addr:postcode":"30032",
    "addr:street":"Candler Rd",
    "iso:country":"US",
    "sg:address":"2111 Candler Rd",
    "sg:city":"Decatur",
    "sg:classifiers":[
        {
            "category":"Shopping",
            "subcategory":"Clothing, Apparel, & Fashions",
            "type":"Retail Goods"
        }
    ],
    "sg:phone":"+1 404 286 2900",
    "sg:postcode":"30032",
    "sg:province":"GA",
    "wof:name":"Browz Inc",
    "wof:placetype":"venue"
},
  "geometry": {"coordinates":[-84.28083700000001,33.728717],"type":"Point"}
}