{
  "type": "Feature",
  "properties": {
    "iso:country":"US",
    "sg:address":"120 W M L King Jr Dr",
    "sg:city":"Hinesville",
    "sg:classifiers":[
        {
            "category":"Personal",
            "subcategory":"Beauty Salon",
            "type":"Services"
        }
    ],
    "sg:phone":"+1 912 368 0101",
    "sg:postcode":"31313",
    "sg:province":"GA",
    "wof:name":"C & C's Beauty Box",
    "wof:placetype":"venue"
},
  "geometry": {"coordinates":[-81.59878399999999,31.847264],"type":"Point"}
}