{
  "type": "Feature",
  "properties": {
    "iso:country":"US",
    "sg:address":"1308 US Hwy 80",
    "sg:city":"Savannah",
    "sg:classifiers":[
        {
            "category":"Professional",
            "type":"Services"
        }
    ],
    "sg:phone":"+1 912 655 9731",
    "sg:postcode":"31408",
    "sg:province":"GA",
    "sg:tags":[
        "establishment"
    ],
    "wof:name":"Pete's Cycle & Outdoor Product",
    "wof:placetype":"venue"
},
  "geometry": {"coordinates":[-81.15987699999999,32.086763],"type":"Point"}
}