{
  "type": "Feature",
  "properties": {
    "addr:full":"4124 Atlanta Hwy Bogart GA 30622",
    "addr:housenumber":"4124",
    "addr:postcode":"30622",
    "addr:street":"Atlanta Hwy Bogart",
    "iso:country":"US",
    "sg:address":"4124 Atlanta Hwy",
    "sg:city":"Bogart",
    "sg:classifiers":[
        {
            "category":"Home & Garden",
            "subcategory":"Furniture",
            "type":"Retail Goods"
        }
    ],
    "sg:phone":"+1 706 354 0201",
    "sg:postcode":"30622",
    "sg:province":"GA",
    "sg:website":"www.mattressesandsofastoo.com",
    "wof:name":"Mattresses & Futons Too",
    "wof:placetype":"venue"
},
  "geometry": {"coordinates":[-83.479463,33.940509],"type":"Point"}
}