{
  "type": "Feature",
  "properties": {
    "addr:full":"14 E Vine St Statesboro GA 30458",
    "addr:housenumber":"14",
    "addr:postcode":"30458",
    "addr:street":"E Vine St",
    "iso:country":"US",
    "sg:address":"14 E Vine St",
    "sg:city":"Statesboro",
    "sg:classifiers":[
        {
            "category":"Autos & Motor Vehicles",
            "subcategory":"Motorcycle Sales",
            "type":"Retail Goods"
        }
    ],
    "sg:phone":"+1 912 764 2054",
    "sg:postcode":"30458",
    "sg:province":"GA",
    "sg:tags":[
        "scooter"
    ],
    "wof:name":"Sinkhole Customs",
    "wof:placetype":"venue"
},
  "geometry": {"coordinates":[-81.78225500000001,32.447816],"type":"Point"}
}