{
  "type": "Feature",
  "properties": {
    "iso:country":"US",
    "sg:address":"614 King Arnold St",
    "sg:city":"Atlanta",
    "sg:classifiers":[
        {
            "category":"Shopping",
            "subcategory":"Clothing, Apparel, & Fashions",
            "type":"Retail Goods"
        }
    ],
    "sg:phone":"+1 404 763 8744",
    "sg:postcode":"30354",
    "sg:province":"GA",
    "sg:tags":[
        "alterations-clothing"
    ],
    "wof:name":"Buttons & Bows Alterations",
    "wof:placetype":"venue"
},
  "geometry": {"coordinates":[-84.408457,33.659919],"type":"Point"}
}