{
  "type": "Feature",
  "properties": {
    "iso:country":"US",
    "sg:address":"3048 Lower Union Hill Rd",
    "sg:city":"Canton",
    "sg:classifiers":[
        {
            "category":"Professional",
            "subcategory":"Business Services",
            "type":"Services"
        }
    ],
    "sg:phone":"+1 770 475 7475",
    "sg:postcode":"30115",
    "sg:province":"GA",
    "wof:name":"Knox Bridge Partners Inc",
    "wof:placetype":"venue"
},
  "geometry": {"coordinates":[-84.37799099999999,34.19658],"type":"Point"}
}