{
  "type": "Feature",
  "properties": {
    "iso:country":"US",
    "sg:address":"560 Dutch Valley Rd NE",
    "sg:city":"Atlanta",
    "sg:classifiers":[
        {
            "category":"Fast Food",
            "type":"Food & Drink"
        },
        {
            "category":"Restaurant",
            "type":"Food & Drink"
        }
    ],
    "sg:phone":"+1 678 973 4110",
    "sg:postcode":"30324",
    "sg:province":"GA",
    "sg:tags":[
        "style",
        "family",
        "vegetarian",
        "mediterranean",
        "french",
        "lunch",
        "take",
        "brunch",
        "breakfast"
    ],
    "sg:website":"http://atlanta.citysearch.com/profile/external/603287692/atlanta_ga/amuse.html?publisher=yellowpages&reference_id=1&placement=ypwebsitemip",
    "wof:name":"Amuse",
    "wof:placetype":"venue"
},
  "geometry": {"coordinates":[-84.368416,33.792038],"type":"Point"}
}