{
  "type": "Feature",
  "properties": {
    "iso:country":"US",
    "sg:address":"878 Waterford Green",
    "sg:city":"Marietta",
    "sg:classifiers":[
        {
            "category":"Banks & Credit Unions",
            "subcategory":"Financial Services",
            "type":"Services"
        }
    ],
    "sg:phone":"+1 770 998 7641",
    "sg:postcode":"30068",
    "sg:province":"GA",
    "sg:tags":[
        "investment",
        "closed"
    ],
    "wof:name":"Pas Finiancial Corp",
    "wof:placetype":"venue"
},
  "geometry": {"coordinates":[-84.388452,33.982701],"type":"Point"}
}