{
  "type": "Feature",
  "properties": {
    "addr:full":"3220 Hwy 5 Douglasville GA 30135",
    "addr:housenumber":"3220",
    "addr:postcode":"30135",
    "addr:street":"Hwy 5",
    "iso:country":"US",
    "sg:address":"3220 Hwy 5",
    "sg:city":"Douglasville",
    "sg:classifiers":[
        {
            "category":"Personal",
            "subcategory":"Beauty Salon",
            "type":"Services"
        }
    ],
    "sg:phone":"+1 770 949 2214",
    "sg:postcode":"30135",
    "sg:province":"GA",
    "sg:tags":[
        "hair"
    ],
    "wof:name":"Pat's Hair Shop",
    "wof:placetype":"venue"
},
  "geometry": {"coordinates":[-84.76501399999999,33.717564],"type":"Point"}
}