{
  "type": "Feature",
  "properties": {
    "addr:full":"192 Gateway Dr Canton GA 30115",
    "addr:housenumber":"192",
    "addr:postcode":"30115",
    "addr:street":"Gateway Dr",
    "iso:country":"US",
    "sg:address":"192 Gateway Dr",
    "sg:city":"Canton",
    "sg:classifiers":[
        {
            "category":"Building & Trades",
            "subcategory":"Construction",
            "type":"Services"
        }
    ],
    "sg:phone":"+1 770 345 3777",
    "sg:postcode":"30115",
    "sg:province":"GA",
    "sg:tags":[
        "house",
        "general",
        "contractor"
    ],
    "wof:name":"Raytex Construction &",
    "wof:placetype":"venue"
},
  "geometry": {"coordinates":[-84.491062,34.197318],"type":"Point"}
}