{
  "type": "Feature",
  "properties": {
    "iso:country":"US",
    "sg:address":"1933 Sunset Blvd",
    "sg:city":"Jesup",
    "sg:classifiers":[
        {
            "category":"Freight",
            "type":"Transportation"
        }
    ],
    "sg:phone":"+1 912 427 2751",
    "sg:postcode":"31545",
    "sg:province":"GA",
    "sg:tags":[
        "commercial",
        "storage"
    ],
    "wof:name":"Sunset Storage",
    "wof:placetype":"venue"
},
  "geometry": {"coordinates":[-81.90727,31.603847],"type":"Point"}
}