{
  "type": "Feature",
  "properties": {
    "addr:full":"1436 Watson Blvd Warner Robins GA 31093",
    "addr:housenumber":"1436",
    "addr:postcode":"31093",
    "addr:street":"Watson Blvd",
    "iso:country":"US",
    "sg:address":"1436 Watson Blvd",
    "sg:city":"Warner Robins",
    "sg:classifiers":[
        {
            "category":"Travel",
            "subcategory":"Hotels & Motels",
            "type":"Entertainment"
        }
    ],
    "sg:phone":"+1 478 923 0768",
    "sg:postcode":"31093",
    "sg:province":"GA",
    "sg:tags":[
        "operation"
    ],
    "wof:name":"Howard Johnson",
    "wof:placetype":"venue"
},
  "geometry": {"coordinates":[-83.62250400000001,32.618229],"type":"Point"}
}