{
  "type": "Feature",
  "properties": {
    "addr:full":"96 Glenmark Ln Dallas GA 30157",
    "addr:housenumber":"96",
    "addr:postcode":"30157",
    "addr:street":"Glenmark Ln",
    "iso:country":"US",
    "sg:address":"96 Glenmark Ln",
    "sg:city":"Dallas",
    "sg:classifiers":[
        {
            "category":"Retail",
            "subcategory":"Auto Repair",
            "type":"Services"
        }
    ],
    "sg:phone":"+1 770 366 4835",
    "sg:postcode":"30157",
    "sg:province":"GA",
    "sg:tags":[
        "windshield"
    ],
    "wof:name":"Windshield Repair Of Atlanta",
    "wof:placetype":"venue"
},
  "geometry": {"coordinates":[-84.750389,33.956361],"type":"Point"}
}