{
  "type": "Feature",
  "properties": {
    "addr:full":"1369 Spring St SE Smyrna GA 30080",
    "addr:housenumber":"1369",
    "addr:postcode":"30080",
    "addr:street":"Spring St Se",
    "iso:country":"US",
    "sg:address":"1369 Spring St SE",
    "sg:city":"Smyrna",
    "sg:classifiers":[
        {
            "category":"Social Services",
            "type":"Services"
        },
        {
            "category":"Health Services",
            "subcategory":"Clinic",
            "type":"Services"
        },
        {
            "category":"Social Services",
            "subcategory":"Adult Care",
            "type":"Services"
        }
    ],
    "sg:phone":"+1 770 435 0308",
    "sg:postcode":"30080",
    "sg:province":"GA",
    "sg:tags":[
        "information",
        "suicide",
        "alcoholism",
        "treatment",
        "crisis",
        "prevention",
        "intervention"
    ],
    "wof:name":"Detox Abuse Action Addictin He",
    "wof:placetype":"venue"
},
  "geometry": {"coordinates":[-84.512861,33.88377],"type":"Point"}
}