{
  "type": "Feature",
  "properties": {
    "iso:country":"US",
    "sg:address":"355 Cross Creek Farms Rd",
    "sg:city":"Reidsville",
    "sg:classifiers":[
        {
            "category":"Sports & Exercise",
            "subcategory":"Golf",
            "type":"Entertainment"
        }
    ],
    "sg:phone":"+1 912 557 7068",
    "sg:postcode":"30458",
    "sg:province":"GA",
    "sg:tags":[
        "course",
        "conservation",
        "public"
    ],
    "wof:name":"Gordonia-Alatamaha State Park",
    "wof:placetype":"venue"
},
  "geometry": {"coordinates":[-81.72969399999999,32.299746],"type":"Point"}
}