{
  "type": "Feature",
  "properties": {
    "iso:country":"US",
    "sg:address":"226 Winter Ave",
    "sg:city":"Decatur",
    "sg:classifiers":[
        {
            "category":"Building & Trades",
            "subcategory":"Plumbing",
            "type":"Services"
        }
    ],
    "sg:phone":"+1 404 373 8032",
    "sg:postcode":"30030",
    "sg:province":"GA",
    "sg:tags":[
        "contractor"
    ],
    "wof:name":"George Gary Mech",
    "wof:placetype":"venue"
},
  "geometry": {"coordinates":[-84.312414,33.757486],"type":"Point"}
}