{
  "type": "Feature",
  "properties": {
    "addr:full":"8205 Mount Olive Rd Camilla GA 31730",
    "addr:housenumber":"8205",
    "addr:postcode":"31730",
    "addr:street":"Mount Olive Rd",
    "iso:country":"US",
    "sg:address":"8205 Mount Olive Rd",
    "sg:city":"Camilla",
    "sg:classifiers":[
        {
            "category":"Freight",
            "type":"Transportation"
        }
    ],
    "sg:phone":"+1 229 294 3931",
    "sg:postcode":"31730",
    "sg:province":"GA",
    "wof:name":"Dixieland Transport Inc",
    "wof:placetype":"venue"
},
  "geometry": {"coordinates":[-84.33132999999999,31.131678],"type":"Point"}
}