{
  "type": "Feature",
  "properties": {
    "iso:country":"US",
    "sg:address":"3502 Ruby H Harper Blvd",
    "sg:city":"Atlanta",
    "sg:classifiers":[
        {
            "category":"Professional",
            "type":"Services"
        }
    ],
    "sg:phone":"+1 404 968 3619",
    "sg:postcode":"30354",
    "sg:province":"GA",
    "wof:name":"Thats A Wrap",
    "wof:placetype":"venue"
},
  "geometry": {"coordinates":[-84.380334,33.660836],"type":"Point"}
}