{
  "type": "Feature",
  "properties": {
    "iso:country":"US",
    "sg:address":"1334 Boulevard SE",
    "sg:city":"Atlanta",
    "sg:classifiers":[
        {
            "category":"Food & Beverages",
            "subcategory":"Groceries & Convenience Stores",
            "type":"Retail Goods"
        }
    ],
    "sg:phone":"+1 404 624 0052",
    "sg:postcode":"30315",
    "sg:province":"GA",
    "wof:name":"Discount Grocery",
    "wof:placetype":"venue"
},
  "geometry": {"coordinates":[-84.368633,33.718664],"type":"Point"}
}