{
  "type": "Feature",
  "properties": {
    "iso:country":"US",
    "sg:address":"12 N Mcintosh St",
    "sg:city":"Elberton",
    "sg:classifiers":[
        {
            "category":"Deli",
            "type":"Food & Drink"
        },
        {
            "category":"Restaurant",
            "type":"Food & Drink"
        }
    ],
    "sg:phone":"+1 706 213 0077",
    "sg:postcode":"30635",
    "sg:province":"GA",
    "sg:tags":[
        "delicatessen"
    ],
    "wof:name":"Downtown Deli & Dessertery",
    "wof:placetype":"venue"
},
  "geometry": {"coordinates":[-82.866998,34.109867],"type":"Point"}
}