{
  "type": "Feature",
  "properties": {
    "addr:full":"2202 Lattimore Farm Dr Kennesaw GA 30152",
    "addr:housenumber":"2202",
    "addr:postcode":"30152",
    "addr:street":"Lattimore Farm Dr",
    "iso:country":"US",
    "sg:address":"2202 Lattimore Farm Dr",
    "sg:city":"Kennesaw",
    "sg:classifiers":[
        {
            "category":"Farming",
            "subcategory":"Farm",
            "type":"Manufacturing & Wholesale Goods"
        }
    ],
    "sg:phone":"+1 770 499 2225",
    "sg:postcode":"30152",
    "sg:province":"GA",
    "sg:tags":[
        "crop",
        "general"
    ],
    "wof:name":"CCC Farm Inc",
    "wof:placetype":"venue"
},
  "geometry": {"coordinates":[-84.62351099999999,33.981195],"type":"Point"}
}