{
  "type": "Feature",
  "properties": {
    "iso:country":"US",
    "sg:address":"1579 Baytree Rd",
    "sg:city":"Valdosta",
    "sg:classifiers":[
        {
            "category":"Home & Garden",
            "subcategory":"Furniture",
            "type":"Retail Goods"
        },
        {
            "category":"Shopping",
            "subcategory":"Clothing, Apparel, & Fashions",
            "type":"Retail Goods"
        }
    ],
    "sg:phone":"+1 229 241 1131",
    "sg:postcode":"31602",
    "sg:province":"GA",
    "sg:tags":[
        "baby",
        "accessory"
    ],
    "wof:name":"Children's Corner",
    "wof:placetype":"venue"
},
  "geometry": {"coordinates":[-83.31474,30.84687],"type":"Point"}
}