{
  "type": "Feature",
  "properties": {
    "addr:full":"4751 Julian Way Acworth GA 30101",
    "addr:housenumber":"4751",
    "addr:postcode":"30101",
    "addr:street":"Julian Way",
    "iso:country":"US",
    "sg:address":"4751 Julian Way",
    "sg:city":"Acworth",
    "sg:classifiers":[
        {
            "category":"Professional",
            "subcategory":"Art Services",
            "type":"Services"
        }
    ],
    "sg:phone":"+1 770 596 9696",
    "sg:postcode":"30101",
    "sg:province":"GA",
    "sg:tags":[
        "commercial",
        "design"
    ],
    "wof:name":"Southern Biographics Inc",
    "wof:placetype":"venue"
},
  "geometry": {"coordinates":[-84.64240100000001,34.067792],"type":"Point"}
}