{
  "type": "Feature",
  "properties": {
    "iso:country":"US",
    "sg:address":"9 Meadow Lake Cir NE",
    "sg:city":"Rome",
    "sg:classifiers":[
        {
            "category":"Professional",
            "type":"Services"
        }
    ],
    "sg:phone":"+1 706 234 1144",
    "sg:postcode":"30161",
    "sg:province":"GA",
    "wof:name":"Maloneys Autohaul Inc",
    "wof:placetype":"venue"
},
  "geometry": {"coordinates":[-85.107286,34.30002],"type":"Point"}
}