{
  "type": "Feature",
  "properties": {
    "addr:full":"24 Talley Cir Fort Oglethorpe GA 30742",
    "addr:housenumber":"24",
    "addr:postcode":"30742",
    "addr:street":"Talley Cir",
    "iso:country":"US",
    "sg:address":"24 Talley Cir",
    "sg:city":"Fort Oglethorpe",
    "sg:classifiers":[
        {
            "category":"Restaurant",
            "type":"Food & Drink"
        }
    ],
    "sg:phone":"+1 706 861 3569",
    "sg:postcode":"30742",
    "sg:province":"GA",
    "sg:tags":[
        "eating"
    ],
    "wof:name":"California Juice Bar & Eatery",
    "wof:placetype":"venue"
},
  "geometry": {"coordinates":[-85.254644,34.953944],"type":"Point"}
}