{
  "type": "Feature",
  "properties": {
    "iso:country":"US",
    "sg:address":"1869 Campbell Rd",
    "sg:city":"Covington",
    "sg:classifiers":[
        {
            "category":"Health Services",
            "subcategory":"Chiropractor",
            "type":"Services"
        }
    ],
    "sg:phone":"+1 770 787 6288",
    "sg:postcode":"30014",
    "sg:province":"GA",
    "sg:tags":[
        "chiropractic"
    ],
    "wof:name":"Dc Industries Inc",
    "wof:placetype":"venue"
},
  "geometry": {"coordinates":[-83.862239,33.374062],"type":"Point"}
}