{
  "type": "Feature",
  "properties": {
    "iso:country":"US",
    "sg:address":"123 S Broad St",
    "sg:city":"Thomasville",
    "sg:classifiers":[
        {
            "category":"Shopping",
            "subcategory":"Music",
            "type":"Retail Goods"
        }
    ],
    "sg:phone":"+1 229 226 1081",
    "sg:postcode":"31792",
    "sg:province":"GA",
    "sg:tags":[
        "compact",
        "record",
        "disc",
        "tape"
    ],
    "wof:name":"Sirens Inc",
    "wof:placetype":"venue"
},
  "geometry": {"coordinates":[-83.979967,30.837297],"type":"Point"}
}