{
  "type": "Feature",
  "properties": {
    "iso:country":"US",
    "sg:address":"55 Ivan Allen Jr Blvd NW",
    "sg:city":"Atlanta",
    "sg:classifiers":[
        {
            "category":"Banks & Credit Unions",
            "subcategory":"Investment Brokerage",
            "type":"Services"
        }
    ],
    "sg:phone":"+1 404 817 5827",
    "sg:postcode":"30308",
    "sg:province":"GA",
    "sg:tags":[
        "trust"
    ],
    "wof:name":"The Comm Foundation For G Atl",
    "wof:placetype":"venue"
},
  "geometry": {"coordinates":[-84.389218,33.764673],"type":"Point"}
}