{
  "type": "Feature",
  "properties": {
    "iso:country":"US",
    "sg:address":"8509 Hospital Dr",
    "sg:city":"Douglasville",
    "sg:classifiers":[
        {
            "category":"Health Services",
            "subcategory":"Health Practitioner",
            "type":"Services"
        }
    ],
    "sg:phone":"+1 770 947 5440",
    "sg:postcode":"30134",
    "sg:province":"GA",
    "wof:name":"Physiotherapy Associates Inc",
    "wof:placetype":"venue"
},
  "geometry": {"coordinates":[-84.73074099999999,33.750034],"type":"Point"}
}