{
  "type": "Feature",
  "properties": {
    "addr:full":"706 Foster Blvd La Fayette GA 30728",
    "addr:housenumber":"706",
    "addr:postcode":"30728",
    "addr:street":"Foster Blvd La Fayette",
    "iso:country":"US",
    "sg:address":"706 Foster Blvd",
    "sg:city":"La Fayette",
    "sg:classifiers":[
        {
            "category":"Government",
            "subcategory":"Police Station",
            "type":"Public Place"
        }
    ],
    "sg:phone":"+1 706 638 5571",
    "sg:postcode":"30728",
    "sg:province":"GA",
    "sg:tags":[
        "department"
    ],
    "wof:name":"Drug Task Force",
    "wof:placetype":"venue"
},
  "geometry": {"coordinates":[-85.273228,34.697831],"type":"Point"}
}