{
  "type": "Feature",
  "properties": {
    "addr:full":"901 Lancaster Way NW Atlanta GA 30328",
    "addr:housenumber":"901",
    "addr:postcode":"30328",
    "addr:street":"Lancaster Way Nw",
    "iso:country":"US",
    "sg:address":"901 Lancaster Way NW",
    "sg:city":"Atlanta",
    "sg:classifiers":[
        {
            "category":"Building & Trades",
            "subcategory":"Locksmith",
            "type":"Services"
        }
    ],
    "sg:phone":"+1 404 736 1598",
    "sg:postcode":"30328",
    "sg:province":"GA",
    "sg:tags":[
        "key"
    ],
    "wof:name":"1 Hour All A 24 Locksmith",
    "wof:placetype":"venue"
},
  "geometry": {"coordinates":[-84.3871,33.914427],"type":"Point"}
}