{
  "type": "Feature",
  "properties": {
    "addr:full":"1992 Barberrie Ln Decatur GA 30032",
    "addr:housenumber":"1992",
    "addr:postcode":"30032",
    "addr:street":"Barberrie Ln",
    "iso:country":"US",
    "sg:address":"1992 Barberrie Ln",
    "sg:city":"Decatur",
    "sg:classifiers":[
        {
            "category":"Travel",
            "subcategory":"Travel Agent",
            "type":"Entertainment"
        }
    ],
    "sg:phone":"+1 404 373 3920",
    "sg:postcode":"30032",
    "sg:province":"GA",
    "sg:tags":[
        "operator",
        "tour"
    ],
    "wof:name":"L&E Tours & Charters Inc",
    "wof:placetype":"venue"
},
  "geometry": {"coordinates":[-84.306943,33.73546],"type":"Point"}
}