{
  "type": "Feature",
  "properties": {
    "addr:full":"100 Hill St La Grange GA 30241",
    "addr:housenumber":"100",
    "addr:postcode":"30241",
    "addr:street":"Hill St",
    "iso:country":"US",
    "sg:address":"100 Hill St",
    "sg:city":"La Grange",
    "sg:classifiers":[
        {
            "category":"Travel",
            "subcategory":"Hotels & Motels",
            "type":"Entertainment"
        }
    ],
    "sg:phone":"+1 706 882 3595",
    "sg:postcode":"30241",
    "sg:province":"GA",
    "sg:tags":[
        "operation"
    ],
    "wof:name":"Budget Inn of Lagrange",
    "wof:placetype":"venue"
},
  "geometry": {"coordinates":[-85.026257,33.041181],"type":"Point"}
}