{
  "type": "Feature",
  "properties": {
    "addr:full":"2138 Cedar Grove Rd Conley GA 30288",
    "addr:housenumber":"2138",
    "addr:postcode":"30288",
    "addr:street":"Cedar Grove Rd",
    "iso:country":"US",
    "sg:address":"2138 Cedar Grove Rd",
    "sg:city":"Conley",
    "sg:classifiers":[
        {
            "category":"Personal",
            "subcategory":"Barber",
            "type":"Services"
        }
    ],
    "sg:phone":"+1 404 244 6770",
    "sg:postcode":"30288",
    "sg:province":"GA",
    "wof:name":"Headquarters Barbershop",
    "wof:placetype":"venue"
},
  "geometry": {"coordinates":[-84.305098,33.65892],"type":"Point"}
}