{
  "type": "Feature",
  "properties": {
    "addr:full":"260 Shady Marsh Trl Roswell GA 30075",
    "addr:housenumber":"260",
    "addr:postcode":"30075",
    "addr:street":"Shady Marsh Trl",
    "iso:country":"US",
    "sg:address":"260 Shady Marsh Trl",
    "sg:city":"Roswell",
    "sg:classifiers":[
        {
            "category":"Banks & Credit Unions",
            "subcategory":"Financial Services",
            "type":"Services"
        }
    ],
    "sg:phone":"+1 678 461 6675",
    "sg:postcode":"30075",
    "sg:province":"GA",
    "sg:tags":[
        "company",
        "holding"
    ],
    "wof:name":"Rollin Haven Holding Co LLC",
    "wof:placetype":"venue"
},
  "geometry": {"coordinates":[-84.40309999999999,34.03717],"type":"Point"}
}