{
  "type": "Feature",
  "properties": {
    "addr:full":"2320 Virginia Pl NE Atlanta GA 30305",
    "addr:housenumber":"2320",
    "addr:postcode":"30305",
    "addr:street":"Virginia Pl Ne",
    "iso:country":"US",
    "sg:address":"2320 Virginia Pl NE",
    "sg:city":"Atlanta",
    "sg:classifiers":[
        {
            "category":"Professional",
            "subcategory":"Research",
            "type":"Services"
        },
        {
            "category":"Professional",
            "subcategory":"Management & Consulting",
            "type":"Services"
        }
    ],
    "sg:phone":"+1 404 231 5522",
    "sg:postcode":"30305",
    "sg:province":"GA",
    "sg:tags":[
        "environmental",
        "ecological",
        "business"
    ],
    "wof:name":"Environmental Resource Svcs",
    "wof:placetype":"venue"
},
  "geometry": {"coordinates":[-84.381215,33.820609],"type":"Point"}
}