{
  "type": "Feature",
  "properties": {
    "iso:country":"US",
    "sg:address":"174 Palmetto Dr",
    "sg:city":"Rincon",
    "sg:classifiers":[
        {
            "category":"Food & Beverages",
            "subcategory":"Groceries & Convenience Stores",
            "type":"Retail Goods"
        }
    ],
    "sg:phone":"+1 912 826 0603",
    "sg:postcode":"31326",
    "sg:province":"GA",
    "wof:name":"Shyamgi Inc",
    "wof:placetype":"venue"
},
  "geometry": {"coordinates":[-81.215048,32.26483],"type":"Point"}
}