{
  "type": "Feature",
  "properties": {
    "addr:full":"970 McDonald St Waycross GA 31501",
    "addr:housenumber":"970",
    "addr:postcode":"31501",
    "addr:street":"Mcdonald St",
    "iso:country":"US",
    "sg:address":"970 McDonald St",
    "sg:city":"Waycross",
    "sg:classifiers":[
        {
            "category":"Retail",
            "subcategory":"Funeral Services",
            "type":"Services"
        }
    ],
    "sg:phone":"+1 912 283 1811",
    "sg:postcode":"31501",
    "sg:province":"GA",
    "wof:name":"Welch & Brinkley Funeral Home",
    "wof:placetype":"venue"
},
  "geometry": {"coordinates":[-82.361222,31.21995],"type":"Point"}
}