{
  "type": "Feature",
  "properties": {
    "addr:full":"8477 Hospital Dr Douglasville GA 30134",
    "addr:housenumber":"8477",
    "addr:postcode":"30134",
    "addr:street":"Hospital Dr",
    "iso:country":"US",
    "sg:address":"8477 Hospital Dr",
    "sg:city":"Douglasville",
    "sg:classifiers":[
        {
            "category":"Personal",
            "subcategory":"Tanning Parlor",
            "type":"Services"
        },
        {
            "category":"Personal",
            "subcategory":"Tattoo Parlor",
            "type":"Services"
        },
        {
            "category":"Personal",
            "subcategory":"Barber",
            "type":"Services"
        }
    ],
    "sg:phone":"+1 770 920 0303",
    "sg:postcode":"30134",
    "sg:province":"GA",
    "wof:name":"Alan Hair Designs",
    "wof:placetype":"venue"
},
  "geometry": {"coordinates":[-84.730698,33.749298],"type":"Point"}
}