{
  "type": "Feature",
  "properties": {
    "addr:full":"4990 Davis Academy Rd Rutledge GA 30663",
    "addr:housenumber":"4990",
    "addr:postcode":"30663",
    "addr:street":"Davis Academy Rd",
    "iso:country":"US",
    "sg:address":"4990 Davis Academy Rd",
    "sg:city":"Rutledge",
    "sg:classifiers":[
        {
            "category":"Freight",
            "type":"Transportation"
        }
    ],
    "sg:phone":"+1 706 557 7843",
    "sg:postcode":"30663",
    "sg:province":"GA",
    "sg:tags":[
        "operator",
        "local",
        "trucking"
    ],
    "wof:name":"A & H Trucking Co Inc",
    "wof:placetype":"venue"
},
  "geometry": {"coordinates":[-83.655044,33.615794],"type":"Point"}
}