{
  "type": "Feature",
  "properties": {
    "addr:full":"3128 Bemiss Rd Valdosta GA 31602",
    "addr:housenumber":"3128",
    "addr:postcode":"31602",
    "addr:street":"Bemiss Rd",
    "iso:country":"US",
    "sg:address":"3128 Bemiss Rd",
    "sg:city":"Valdosta",
    "sg:classifiers":[
        {
            "category":"Home & Garden",
            "subcategory":"Furniture",
            "type":"Retail Goods"
        }
    ],
    "sg:phone":"+1 229 244 0055",
    "sg:postcode":"31602",
    "sg:province":"GA",
    "wof:name":"Magnolia House Furn & Gifts",
    "wof:placetype":"venue"
},
  "geometry": {"coordinates":[-83.27405400000001,30.881121],"type":"Point"}
}