{
  "type": "Feature",
  "properties": {
    "iso:country":"US",
    "sg:address":"3330 Cobb Pkwy NW #17",
    "sg:city":"Acworth",
    "sg:classifiers":[
        {
            "category":"Retail",
            "subcategory":"Laundry & Dry Cleaning",
            "type":"Services"
        },
        {
            "category":"Building & Trades",
            "subcategory":"Cleaning & Sanitation",
            "type":"Services"
        }
    ],
    "sg:phone":"+1 404 439 0455",
    "sg:postcode":"30101",
    "sg:province":"GA",
    "sg:tags":[
        "cleaner",
        "upholstery",
        "rug",
        "carpet"
    ],
    "wof:name":"Jordan Commercial Cleaning",
    "wof:placetype":"venue"
},
  "geometry": {"coordinates":[-84.678968,34.035078],"type":"Point"}
}