{
  "type": "Feature",
  "properties": {
    "iso:country":"US",
    "sg:address":"3131 Lakecrest Dr",
    "sg:city":"Dacula",
    "sg:classifiers":[
        {
            "category":"Professional",
            "subcategory":"Detective & Security Services",
            "type":"Services"
        }
    ],
    "sg:phone":"+1 770 932 2881",
    "sg:postcode":"30019",
    "sg:province":"GA",
    "sg:tags":[
        "car"
    ],
    "wof:name":"Defect Detective Home Insptn",
    "wof:placetype":"venue"
},
  "geometry": {"coordinates":[-83.92109000000001,34.057615],"type":"Point"}
}