{
  "type": "Feature",
  "properties": {
    "iso:country":"US",
    "sg:address":"323 E Broad St",
    "sg:city":"Athens",
    "sg:classifiers":[
        {
            "category":"Restaurant",
            "type":"Food & Drink"
        }
    ],
    "sg:phone":"+1 706 546 6500",
    "sg:postcode":"30601",
    "sg:province":"GA",
    "sg:website":"www.gandolfos.com",
    "wof:name":"Gandolfo's New York Deli",
    "wof:placetype":"venue"
},
  "geometry": {"coordinates":[-83.37382599999999,33.958097],"type":"Point"}
}