{
  "type": "Feature",
  "properties": {
    "addr:full":"205 Axton Ct Roswell GA 30076",
    "addr:housenumber":"205",
    "addr:postcode":"30076",
    "addr:street":"Axton Ct",
    "iso:country":"US",
    "sg:address":"205 Axton Ct",
    "sg:city":"Roswell",
    "sg:classifiers":[
        {
            "category":"Wholesale",
            "subcategory":"Sporting Goods",
            "type":"Manufacturing & Wholesale Goods"
        }
    ],
    "sg:phone":"+1 770 751 9463",
    "sg:postcode":"30076",
    "sg:province":"GA",
    "wof:name":"Python Raquette Ball",
    "wof:placetype":"venue"
},
  "geometry": {"coordinates":[-84.288792,34.037111],"type":"Point"}
}