{
  "type": "Feature",
  "properties": {
    "addr:full":"10064 Main St Woodstock GA 30188",
    "addr:housenumber":"10064",
    "addr:postcode":"30188",
    "addr:street":"Main St",
    "iso:country":"US",
    "sg:address":"10064 Main St",
    "sg:city":"Woodstock",
    "sg:classifiers":[
        {
            "category":"Wholesale",
            "subcategory":"Electrical",
            "type":"Manufacturing & Wholesale Goods"
        }
    ],
    "sg:phone":"+1 770 516 4222",
    "sg:postcode":"30188",
    "sg:province":"GA",
    "sg:tags":[
        "supply"
    ],
    "wof:name":"Woodstock Electric Div 3501",
    "wof:placetype":"venue"
},
  "geometry": {"coordinates":[-84.52080100000001,34.079884],"type":"Point"}
}