{
  "type": "Feature",
  "properties": {
    "iso:country":"US",
    "sg:address":"3001 Northeast Expy NE",
    "sg:city":"Atlanta",
    "sg:classifiers":[
        {
            "category":"Real Estate",
            "subcategory":"Real Estate Operator",
            "type":"Services"
        }
    ],
    "sg:phone":"+1 770 455 1683",
    "sg:postcode":"30341",
    "sg:province":"GA",
    "sg:tags":[
        "apartment"
    ],
    "wof:name":"Heights At Peachtree Creek",
    "wof:placetype":"venue"
},
  "geometry": {"coordinates":[-84.285113,33.867186],"type":"Point"}
}