{
  "type": "Feature",
  "properties": {
    "iso:country":"US",
    "sg:address":"909 W Dykes St",
    "sg:city":"Cochran",
    "sg:classifiers":[
        {
            "category":"Education",
            "subcategory":"School",
            "type":"Public Place"
        }
    ],
    "sg:phone":"+1 478 934 2821",
    "sg:postcode":"31014",
    "sg:province":"GA",
    "sg:website":"www.bleckley.k12.ga.us",
    "wof:name":"Bleckley County School Dist",
    "wof:placetype":"venue"
},
  "geometry": {"coordinates":[-83.36465800000001,32.377877],"type":"Point"}
}