{
  "type": "Feature",
  "properties": {
    "addr:full":"5855 Mulberry St Austell GA 30168",
    "addr:housenumber":"5855",
    "addr:postcode":"30168",
    "addr:street":"Mulberry",
    "iso:country":"US",
    "sg:address":"5855 Mulberry St",
    "sg:city":"Austell",
    "sg:classifiers":[
        {
            "category":"Utilities",
            "subcategory":"Electric",
            "type":"Services"
        },
        {
            "category":"Retail",
            "subcategory":"Repair Shop",
            "type":"Services"
        },
        {
            "category":"Professional",
            "subcategory":"Employment Agencies",
            "type":"Services"
        }
    ],
    "sg:phone":"+1 770 739 4066",
    "sg:postcode":"30168",
    "sg:province":"GA",
    "sg:tags":[
        "television",
        "installation",
        "supplies-repair",
        "equipment",
        "equipment-repair",
        "radio-service",
        "electronic",
        "display"
    ],
    "wof:name":"Johnson Electronics",
    "wof:placetype":"venue"
},
  "geometry": {"coordinates":[-84.632976,33.812638],"type":"Point"}
}