{
  "type": "Feature",
  "properties": {
    "iso:country":"US",
    "sg:address":"11500 County Line Rd",
    "sg:city":"Midland",
    "sg:classifiers":[
        {
            "category":"Professional",
            "type":"Services"
        }
    ],
    "sg:phone":"+1 706 565 0516",
    "sg:postcode":"31820",
    "sg:province":"GA",
    "wof:name":"Geo M Adams Co Inc",
    "wof:placetype":"venue"
},
  "geometry": {"coordinates":[-84.801672,32.579506],"type":"Point"}
}