{
  "type": "Feature",
  "properties": {
    "iso:country":"US",
    "sg:address":"3662 Chamblee Tucker Rd",
    "sg:city":"Chamblee",
    "sg:classifiers":[
        {
            "category":"Building & Trades",
            "subcategory":"Locksmith",
            "type":"Services"
        }
    ],
    "sg:phone":"+1 678 814 0557",
    "sg:postcode":"30341",
    "sg:province":"GA",
    "sg:tags":[
        "key"
    ],
    "wof:name":"0 0 0 0 0 24 Hour 1 Emergency Locksmith",
    "wof:placetype":"venue"
},
  "geometry": {"coordinates":[-84.243422,33.88325],"type":"Point"}
}