{
  "type": "Feature",
  "properties": {
    "iso:country":"US",
    "sg:address":"215 Gleneagle Dr",
    "sg:city":"Byron",
    "sg:classifiers":[
        {
            "category":"Professional",
            "subcategory":"Computer Services",
            "type":"Services"
        }
    ],
    "sg:phone":"+1 478 396 8561",
    "sg:postcode":"31008",
    "sg:province":"GA",
    "sg:tags":[
        "consulting"
    ],
    "wof:name":"At Computer Consulting",
    "wof:placetype":"venue"
},
  "geometry": {"coordinates":[-83.71539799999999,32.639138],"type":"Point"}
}