{
  "type": "Feature",
  "properties": {
    "addr:full":"418 S Ashley St Valdosta GA 31601",
    "addr:housenumber":"418",
    "addr:postcode":"31601",
    "addr:street":"S Ashley St",
    "iso:country":"US",
    "sg:address":"418 S Ashley St",
    "sg:city":"Valdosta",
    "sg:classifiers":[
        {
            "category":"Personal",
            "subcategory":"Beauty Salon",
            "type":"Services"
        }
    ],
    "sg:phone":"+1 229 242 7836",
    "sg:postcode":"31601",
    "sg:province":"GA",
    "sg:tags":[
        "shop"
    ],
    "wof:name":"Freeman Barber Shop",
    "wof:placetype":"venue"
},
  "geometry": {"coordinates":[-83.276905,30.829044],"type":"Point"}
}