{
  "type": "Feature",
  "properties": {
    "addr:full":"5604 Kesteven Ln Macon GA 31210",
    "addr:housenumber":"5604",
    "addr:postcode":"31210",
    "addr:street":"Kesteven Ln",
    "iso:country":"US",
    "sg:address":"5604 Kesteven Ln",
    "sg:city":"Macon",
    "sg:classifiers":[
        {
            "category":"Building & Trades",
            "subcategory":"Landscaping Services",
            "type":"Services"
        }
    ],
    "sg:phone":"+1 478 390 7433",
    "sg:postcode":"31210",
    "sg:province":"GA",
    "sg:tags":[
        "landscape",
        "contractor"
    ],
    "wof:name":"Fertile Ground Lawn Care",
    "wof:placetype":"venue"
},
  "geometry": {"coordinates":[-83.748102,32.88442],"type":"Point"}
}