{
  "type": "Feature",
  "properties": {
    "iso:country":"US",
    "sg:address":"4535 Winters Chapel Rd",
    "sg:city":"Atlanta",
    "sg:classifiers":[
        {
            "category":"Professional",
            "subcategory":"Lawyer & Legal Services",
            "type":"Services"
        }
    ],
    "sg:phone":"+1 770 593 9593",
    "sg:postcode":"30360",
    "sg:province":"GA",
    "sg:tags":[
        "attorney"
    ],
    "wof:name":"James Kee",
    "wof:placetype":"venue"
},
  "geometry": {"coordinates":[-84.265204,33.928901],"type":"Point"}
}