{
  "type": "Feature",
  "properties": {
    "addr:full":"1708 Peachtree St NW # 210 Atlanta GA 30309",
    "addr:housenumber":"1708",
    "addr:postcode":"30309",
    "addr:street":"Peachtree St Nw # 210",
    "iso:country":"US",
    "sg:address":"1708 Peachtree St NW # 210",
    "sg:city":"Atlanta",
    "sg:classifiers":[
        {
            "category":"Shopping",
            "subcategory":"Computers & Home Electronics",
            "type":"Retail Goods"
        }
    ],
    "sg:phone":"+1 888 327 5157",
    "sg:postcode":"30309",
    "sg:province":"GA",
    "sg:tags":[
        "consumer"
    ],
    "wof:name":"Atlanta DISH Network Dealer",
    "wof:placetype":"venue"
},
  "geometry": {"coordinates":[-84.392646,33.800662],"type":"Point"}
}