{
  "type": "Feature",
  "properties": {
    "iso:country":"US",
    "sg:address":"2095 Highway 211 NW",
    "sg:city":"Braselton",
    "sg:classifiers":[
        {
            "category":"Retail",
            "subcategory":"Portrait Studio",
            "type":"Services"
        },
        {
            "category":"Professional",
            "subcategory":"Art Services",
            "type":"Services"
        }
    ],
    "sg:phone":"+1 770 967 2924",
    "sg:postcode":"30517",
    "sg:province":"GA",
    "sg:tags":[
        "rental",
        "photographers-portrait",
        "photographic",
        "darkroom"
    ],
    "wof:name":"Tj2 Photography",
    "wof:placetype":"venue"
},
  "geometry": {"coordinates":[-83.81724699999999,34.110947],"type":"Point"}
}