{
  "type": "Feature",
  "properties": {
    "addr:full":"2086 Fairburn Rd Douglasville GA 30135",
    "addr:housenumber":"2086",
    "addr:postcode":"30135",
    "addr:street":"Fairburn Rd",
    "iso:country":"US",
    "sg:address":"2086 Fairburn Rd",
    "sg:city":"Douglasville",
    "sg:classifiers":[
        {
            "category":"Building & Trades",
            "subcategory":"Construction",
            "type":"Services"
        }
    ],
    "sg:phone":"+1 770 489 8501",
    "sg:postcode":"30135",
    "sg:province":"GA",
    "sg:tags":[
        "contractor"
    ],
    "wof:name":"J A Brown Contracting",
    "wof:placetype":"venue"
},
  "geometry": {"coordinates":[-84.704499,33.748522],"type":"Point"}
}