{
  "type": "Feature",
  "properties": {
    "iso:country":"US",
    "sg:address":"6172 Mincey Rd",
    "sg:city":"Stone Mountain",
    "sg:classifiers":[
        {
            "category":"Wholesale",
            "subcategory":"Medical Equipment & Supplies",
            "type":"Manufacturing & Wholesale Goods"
        }
    ],
    "sg:phone":"+1 770 498 8555",
    "sg:postcode":"30087",
    "sg:province":"GA",
    "sg:tags":[
        "dental"
    ],
    "wof:name":"Burley Dental Co",
    "wof:placetype":"venue"
},
  "geometry": {"coordinates":[-84.13605,33.794689],"type":"Point"}
}