{
  "type": "Feature",
  "properties": {
    "iso:country":"US",
    "sg:address":"91 Sandbar Ferry Rd",
    "sg:city":"Augusta",
    "sg:classifiers":[
        {
            "category":"Home & Garden",
            "subcategory":"Furniture",
            "type":"Retail Goods"
        }
    ],
    "sg:phone":"+1 706 722 1720",
    "sg:postcode":"30901",
    "sg:province":"GA",
    "sg:tags":[
        "top",
        "counter"
    ],
    "wof:name":"Custom Counters",
    "wof:placetype":"venue"
},
  "geometry": {"coordinates":[-81.94712800000001,33.467565],"type":"Point"}
}