{
  "type": "Feature",
  "properties": {
    "iso:country":"US",
    "sg:address":"12390 Arnold Mill Rd",
    "sg:city":"Alpharetta",
    "sg:classifiers":[
        {
            "category":"Autos & Motor Vehicles",
            "subcategory":"Auto Supplies",
            "type":"Retail Goods"
        }
    ],
    "sg:phone":"+1 770 569 9121",
    "sg:postcode":"30004",
    "sg:province":"GA",
    "sg:tags":[
        "tire"
    ],
    "sg:website":"www.kauffmantire.com",
    "wof:name":"Kauffman Tire",
    "wof:placetype":"venue"
},
  "geometry": {"coordinates":[-84.35839799999999,34.084],"type":"Point"}
}