{
  "type": "Feature",
  "properties": {
    "iso:country":"US",
    "sg:address":"2314 Wilson Rd",
    "sg:city":"Albany",
    "sg:classifiers":[
        {
            "category":"Shopping",
            "subcategory":"Catalog Store",
            "type":"Retail Goods"
        }
    ],
    "sg:phone":"+1 229 436 5654",
    "sg:postcode":"31705",
    "sg:province":"GA",
    "sg:tags":[
        "mail",
        "order"
    ],
    "sg:website":"www.sunnylandfarms.com",
    "wof:name":"Sunnyland Farms",
    "wof:placetype":"venue"
},
  "geometry": {"coordinates":[-84.063109,31.50779],"type":"Point"}
}