{
  "type": "Feature",
  "properties": {
    "addr:full":"201 Gilbert Rd Elko GA 31025",
    "addr:housenumber":"201",
    "addr:postcode":"31025",
    "addr:street":"Gilbert Rd",
    "iso:country":"US",
    "sg:address":"201 Gilbert Rd",
    "sg:city":"Elko",
    "sg:classifiers":[
        {
            "category":"Farming",
            "subcategory":"Farm",
            "type":"Manufacturing & Wholesale Goods"
        }
    ],
    "sg:phone":"+1 478 987 5381",
    "sg:postcode":"31025",
    "sg:province":"GA",
    "sg:tags":[
        "crop",
        "general"
    ],
    "wof:name":"High Point Farm",
    "wof:placetype":"venue"
},
  "geometry": {"coordinates":[-83.743296,32.385801],"type":"Point"}
}