{
  "type": "Feature",
  "properties": {
    "iso:country":"US",
    "sg:address":"2100 Canton Rd",
    "sg:city":"Marietta",
    "sg:classifiers":[
        {
            "category":"Personal",
            "subcategory":"Tattoo Parlor",
            "type":"Services"
        },
        {
            "category":"Personal",
            "subcategory":"Piercing",
            "type":"Services"
        }
    ],
    "sg:phone":"+1 770 794 9110",
    "sg:postcode":"30066",
    "sg:province":"GA",
    "sg:tags":[
        "body"
    ],
    "sg:website":"www.electricbodyart.com",
    "wof:name":"Electric Body Art",
    "wof:placetype":"venue"
},
  "geometry": {"coordinates":[-84.524165,34.001967],"type":"Point"}
}