{
  "type": "Feature",
  "properties": {
    "addr:full":"160 Westwood Dr Calhoun GA 30701",
    "addr:housenumber":"160",
    "addr:postcode":"30701",
    "addr:street":"Westwood Dr",
    "iso:country":"US",
    "sg:address":"160 Westwood Dr",
    "sg:city":"Calhoun",
    "sg:classifiers":[
        {
            "category":"Wholesale",
            "subcategory":"Medical Equipment & Supplies",
            "type":"Manufacturing & Wholesale Goods"
        }
    ],
    "sg:phone":"+1 706 625 5507",
    "sg:postcode":"30701",
    "sg:province":"GA",
    "sg:tags":[
        "physician",
        "surgeon"
    ],
    "sg:website":"www.medicalinnovationsonline.com",
    "wof:name":"Medical Innovations",
    "wof:placetype":"venue"
},
  "geometry": {"coordinates":[-84.932658,34.519132],"type":"Point"}
}