{
  "type": "Feature",
  "properties": {
    "addr:full":"2723 Post Rd Cleveland GA 30528",
    "addr:housenumber":"2723",
    "addr:postcode":"30528",
    "addr:street":"Post Rd",
    "iso:country":"US",
    "sg:address":"2723 Post Rd",
    "sg:city":"Cleveland",
    "sg:classifiers":[
        {
            "category":"Building & Trades",
            "subcategory":"Construction",
            "type":"Services"
        }
    ],
    "sg:phone":"+1 706 219 4398",
    "sg:postcode":"30528",
    "sg:province":"GA",
    "sg:tags":[
        "paving",
        "contractor"
    ],
    "wof:name":"Superior Sealing Striping Inc",
    "wof:placetype":"venue"
},
  "geometry": {"coordinates":[-83.726692,34.552538],"type":"Point"}
}