{
  "type": "Feature",
  "properties": {
    "addr:full":"1205 Howell Rd Valdosta GA 31601",
    "addr:housenumber":"1205",
    "addr:postcode":"31601",
    "addr:street":"Howell Rd",
    "iso:country":"US",
    "sg:address":"1205 Howell Rd",
    "sg:city":"Valdosta",
    "sg:classifiers":[
        {
            "category":"Building & Trades",
            "subcategory":"Construction",
            "type":"Services"
        }
    ],
    "sg:phone":"+1 229 244 9325",
    "sg:postcode":"31601",
    "sg:province":"GA",
    "sg:tags":[
        "roofing",
        "contractor"
    ],
    "wof:name":"Harris Tim D",
    "wof:placetype":"venue"
},
  "geometry": {"coordinates":[-83.245293,30.821609],"type":"Point"}
}