{
  "type": "Feature",
  "properties": {
    "iso:country":"US",
    "sg:address":"1117 Chesterwick Trl",
    "sg:city":"Canton",
    "sg:classifiers":[
        {
            "category":"Mining & Drilling",
            "type":"Manufacturing & Wholesale Goods"
        }
    ],
    "sg:phone":"+1 770 720 8844",
    "sg:postcode":"30115",
    "sg:province":"GA",
    "sg:tags":[
        "well"
    ],
    "wof:name":"Boring In K&M Directional",
    "wof:placetype":"venue"
},
  "geometry": {"coordinates":[-84.468778,34.155694],"type":"Point"}
}