{
  "type": "Feature",
  "properties": {
    "addr:full":"2667 Durand Hwy Warm Springs GA 31830",
    "addr:housenumber":"2667",
    "addr:postcode":"31830",
    "addr:street":"Durand Hwy",
    "iso:country":"US",
    "sg:address":"2667 Durand Hwy",
    "sg:city":"Warm Springs",
    "sg:classifiers":[
        {
            "category":"Building & Trades",
            "subcategory":"Construction",
            "type":"Services"
        }
    ],
    "sg:phone":"+1 706 655 3922",
    "sg:postcode":"31830",
    "sg:province":"GA",
    "sg:tags":[
        "home",
        "improvement",
        "general",
        "contractor"
    ],
    "wof:name":"Phillips Construction Services",
    "wof:placetype":"venue"
},
  "geometry": {"coordinates":[-84.73914499999999,32.911722],"type":"Point"}
}