{
  "type": "Feature",
  "properties": {
    "addr:full":"4000 Smithtown Rd Suwanee GA 30024",
    "addr:postcode":"4000;30024",
    "addr:street":"Smithtown Rd",
    "iso:country":"US",
    "sg:address":"4000 Smithtown Rd",
    "sg:city":"Suwanee",
    "sg:classifiers":[
        {
            "category":"Real Estate",
            "subcategory":"Architect",
            "type":"Services"
        }
    ],
    "sg:phone":"+1 770 831 9000",
    "sg:postcode":"30024",
    "sg:province":"GA",
    "wof:name":"Clark Patterson Associates PC",
    "wof:placetype":"venue"
},
  "geometry": {"coordinates":[-84.057602,34.047798],"type":"Point"}
}