{
  "type": "Feature",
  "properties": {
    "addr:full":"1421 2nd St Dudley GA 31022",
    "addr:housenumber":"1421",
    "addr:postcode":"31022",
    "addr:street":"2Nd St",
    "iso:country":"US",
    "sg:address":"1421 2nd St",
    "sg:city":"Dudley",
    "sg:classifiers":[
        {
            "category":"Organizations",
            "subcategory":"Religious Organization",
            "type":"Services"
        }
    ],
    "sg:phone":"+1 478 676 3365",
    "sg:postcode":"31022",
    "sg:province":"GA",
    "sg:tags":[
        "clergy"
    ],
    "wof:name":"Frank Wood",
    "wof:placetype":"venue"
},
  "geometry": {"coordinates":[-83.073396,32.538586],"type":"Point"}
}