{
  "type": "Feature",
  "properties": {
    "addr:full":"312 Pine Ave Commerce GA 30529",
    "addr:housenumber":"312",
    "addr:postcode":"30529",
    "addr:street":"Pine Ave",
    "iso:country":"US",
    "sg:address":"312 Pine Ave",
    "sg:city":"Commerce",
    "sg:classifiers":[
        {
            "category":"Real Estate",
            "subcategory":"Real Estate Operator",
            "type":"Services"
        }
    ],
    "sg:phone":"+1 706 336 8084",
    "sg:postcode":"30529",
    "sg:province":"GA",
    "sg:tags":[
        "building",
        "apartment"
    ],
    "wof:name":"Mount Olive Apartments",
    "wof:placetype":"venue"
},
  "geometry": {"coordinates":[-83.466311,34.214246],"type":"Point"}
}