{
  "type": "Feature",
  "properties": {
    "addr:full":"327 London Dale Woodstock GA 30189",
    "addr:housenumber":"327",
    "addr:postcode":"30189",
    "addr:street":"London Dale",
    "iso:country":"US",
    "sg:address":"327 London Dale",
    "sg:city":"Woodstock",
    "sg:classifiers":[
        {
            "category":"Professional",
            "subcategory":"Business Services",
            "type":"Services"
        }
    ],
    "sg:phone":"+1 770 926 6264",
    "sg:postcode":"30189",
    "sg:province":"GA",
    "wof:name":"Melissas Interiors",
    "wof:placetype":"venue"
},
  "geometry": {"coordinates":[-84.551929,34.081285],"type":"Point"}
}