{
  "type": "Feature",
  "properties": {
    "addr:full":"4942 Suwanee Dam Rd Suwanee GA 30024",
    "addr:postcode":"4942;30024",
    "addr:street":"Dam Rd",
    "iso:country":"US",
    "sg:address":"4942 Suwanee Dam Rd",
    "sg:city":"Suwanee",
    "sg:classifiers":[
        {
            "category":"Building & Trades",
            "subcategory":"Construction",
            "type":"Services"
        }
    ],
    "sg:phone":"+1 770 945 2700",
    "sg:postcode":"30024",
    "sg:province":"GA",
    "sg:tags":[
        "house"
    ],
    "wof:name":"Perry Homes Inc",
    "wof:placetype":"venue"
},
  "geometry": {"coordinates":[-84.07323100000001,34.087116],"type":"Point"}
}