{
  "type": "Feature",
  "properties": {
    "addr:full":"The Village at Crooked Creek 6320 Hwy 9 Alpharetta GA 30004",
    "addr:housenumber":"6320",
    "addr:postcode":"30004",
    "addr:street":"Hwy 9",
    "iso:country":"US",
    "sg:address":"The Village at Crooked Creek 6320 Hwy 9",
    "sg:city":"Alpharetta",
    "sg:classifiers":[
        {
            "category":"Restaurant",
            "type":"Food & Drink"
        }
    ],
    "sg:phone":"+1 678 240 0316",
    "sg:postcode":"30004",
    "sg:province":"GA",
    "sg:tags":[
        "pizza"
    ],
    "wof:name":"Nick's Grand Slam Pizza",
    "wof:placetype":"venue"
},
  "geometry": {"coordinates":[-84.294515,34.075328],"type":"Point"}
}