{
  "type": "Feature",
  "properties": {
    "iso:country":"US",
    "sg:address":"5030 Sugarloaf Pkwy",
    "sg:city":"Lawrenceville",
    "sg:classifiers":[
        {
            "category":"Banks & Credit Unions",
            "subcategory":"Bank",
            "type":"Services"
        }
    ],
    "sg:phone":"+1 770 448 8200",
    "sg:postcode":"30044",
    "sg:province":"GA",
    "wof:name":"Associated Credit Union",
    "wof:placetype":"venue"
},
  "geometry": {"coordinates":[-84.058843,33.957457],"type":"Point"}
}