{
  "type": "Feature",
  "properties": {
    "iso:country":"US",
    "sg:address":"650 E Lake Dr",
    "sg:city":"Decatur",
    "sg:classifiers":[
        {
            "category":"Sports & Exercise",
            "subcategory":"Bicycle Rental",
            "type":"Entertainment"
        },
        {
            "category":"Personal",
            "subcategory":"Shoe Repair & Shine",
            "type":"Services"
        },
        {
            "category":"Shopping",
            "subcategory":"Shoes",
            "type":"Retail Goods"
        }
    ],
    "sg:phone":"+1 404 377 1030",
    "sg:postcode":"30030",
    "sg:province":"GA",
    "sg:tags":[
        "boots-custom",
        "made",
        "wear",
        "store"
    ],
    "sg:website":"www.1stepatatime.net/",
    "wof:name":"One Step At A Time",
    "wof:placetype":"venue"
},
  "geometry": {"coordinates":[-84.30439800000001,33.759602],"type":"Point"}
}