{
  "type": "Feature",
  "properties": {
    "addr:full":"6911 US Hwy 41 S Macon GA 31210",
    "addr:housenumber":"6911",
    "addr:postcode":"31210",
    "addr:street":"Us Hwy 41 S",
    "iso:country":"US",
    "sg:address":"6911 US Hwy 41 S",
    "sg:city":"Macon",
    "sg:classifiers":[
        {
            "category":"Building & Trades",
            "subcategory":"Construction",
            "type":"Services"
        }
    ],
    "sg:phone":"+1 478 994 9929",
    "sg:postcode":"31210",
    "sg:province":"GA",
    "sg:tags":[
        "hanging",
        "contractor"
    ],
    "wof:name":"A C Smith Painting Company",
    "wof:placetype":"venue"
},
  "geometry": {"coordinates":[-83.80214599999999,32.948836],"type":"Point"}
}