{
  "type": "Feature",
  "properties": {
    "addr:full":"6689 Peachtree Industrial Blvd Norcross GA 30092",
    "addr:housenumber":"6689",
    "addr:postcode":"30092",
    "addr:street":"Peachtree Industrial Blvd",
    "iso:country":"US",
    "sg:address":"6689 Peachtree Industrial Blvd",
    "sg:city":"Norcross",
    "sg:classifiers":[
        {
            "category":"Wholesale",
            "subcategory":"Apparel",
            "type":"Manufacturing & Wholesale Goods"
        }
    ],
    "sg:phone":"+1 770 449 1544",
    "sg:postcode":"30092",
    "sg:province":"GA",
    "sg:tags":[
        "fabric"
    ],
    "wof:name":"Creative Threads Inc",
    "wof:placetype":"venue"
},
  "geometry": {"coordinates":[-84.25012599999999,33.938424],"type":"Point"}
}