{
  "type": "Feature",
  "properties": {
    "addr:full":"1900 Buford Hwy Atlanta GA 30345",
    "addr:housenumber":"1900",
    "addr:postcode":"30345",
    "addr:street":"Buford Hwy",
    "iso:country":"US",
    "sg:address":"1900 Buford Hwy",
    "sg:city":"Atlanta",
    "sg:classifiers":[
        {
            "category":"Food & Beverages",
            "subcategory":"Specialty",
            "type":"Retail Goods"
        },
        {
            "category":"Restaurant",
            "type":"Food & Drink"
        }
    ],
    "sg:phone":"+1 404 509 2122",
    "sg:postcode":"30345",
    "sg:province":"GA",
    "sg:tags":[
        "vegetarian"
    ],
    "wof:name":"Harmony Cafe",
    "wof:placetype":"venue"
},
  "geometry": {"coordinates":[-84.306578,33.862784],"type":"Point"}
}