{
  "type": "Feature",
  "properties": {
    "addr:full":"420 Ponce De Leon Avenue NE Atlanta GA 30308",
    "addr:housenumber":"420",
    "addr:postcode":"30308",
    "addr:street":"Ponce De Leon Avenue Ne",
    "iso:country":"US",
    "sg:address":"420 Ponce De Leon Avenue NE",
    "sg:city":"Atlanta",
    "sg:classifiers":[
        {
            "category":"Social Services",
            "subcategory":"Child Care",
            "type":"Services"
        }
    ],
    "sg:phone":"+1 404 249 9605",
    "sg:postcode":"30308",
    "sg:province":"GA",
    "sg:tags":[
        "day"
    ],
    "wof:name":"Millunum Kids Early Learning Center",
    "wof:placetype":"venue"
},
  "geometry": {"coordinates":[-84.37369700000001,33.772764],"type":"Point"}
}