{
  "type": "Feature",
  "properties": {
    "iso:country":"US",
    "sg:address":"701 Indian Trl",
    "sg:city":"Folkston",
    "sg:classifiers":[
        {
            "category":"Education",
            "subcategory":"Library",
            "type":"Public Place"
        }
    ],
    "sg:phone":"+1 912 496 2041",
    "sg:postcode":"31516",
    "sg:province":"GA",
    "wof:name":"Charlton Public Library Inc",
    "wof:placetype":"venue"
},
  "geometry": {"coordinates":[-82.362358,31.276971],"type":"Point"}
}