{
  "type": "Feature",
  "properties": {
    "iso:country":"US",
    "sg:address":"330 Turner McCall Blvd",
    "sg:city":"Rome",
    "sg:classifiers":[
        {
            "category":"Social Services",
            "type":"Services"
        }
    ],
    "sg:phone":"+1 706 292 9024",
    "sg:postcode":"30165",
    "sg:province":"GA",
    "sg:tags":[
        "organization",
        "welfare"
    ],
    "wof:name":"Sexual Assault Ctr Nw Georgia",
    "wof:placetype":"venue"
},
  "geometry": {"coordinates":[-85.179326,34.260331],"type":"Point"}
}