{
  "type": "Feature",
  "properties": {
    "iso:country":"US",
    "sg:address":"4466 Whitecap Rd",
    "sg:city":"Marietta",
    "sg:classifiers":[
        {
            "category":"Professional",
            "subcategory":"Computer Services",
            "type":"Services"
        }
    ],
    "sg:phone":"+1 770 592 2028",
    "sg:postcode":"30066",
    "sg:province":"GA",
    "sg:tags":[
        "software"
    ],
    "wof:name":"Rg Technologies",
    "wof:placetype":"venue"
},
  "geometry": {"coordinates":[-84.505912,34.061134],"type":"Point"}
}