{
  "type": "Feature",
  "properties": {
    "iso:country":"US",
    "sg:address":"2075 Bethany Spring Trce",
    "sg:city":"Cumming",
    "sg:classifiers":[
        {
            "category":"Professional",
            "subcategory":"Art Services",
            "type":"Services"
        }
    ],
    "sg:phone":"+1 770 887 8363",
    "sg:postcode":"30041",
    "sg:province":"GA",
    "sg:tags":[
        "graphic",
        "designer"
    ],
    "wof:name":"Seipel Design",
    "wof:placetype":"venue"
},
  "geometry": {"coordinates":[-84.15331399999999,34.144249],"type":"Point"}
}