{
  "type": "Feature",
  "properties": {
    "addr:full":"1000 Tanger Dr Locust Grove GA 30248",
    "addr:housenumber":"1000",
    "addr:postcode":"30248",
    "addr:street":"Tanger Dr",
    "iso:country":"US",
    "sg:address":"1000 Tanger Dr",
    "sg:city":"Locust Grove",
    "sg:classifiers":[
        {
            "category":"Shopping",
            "subcategory":"Clothing, Apparel, & Fashions",
            "type":"Retail Goods"
        }
    ],
    "sg:phone":"+1 770 914 6501",
    "sg:postcode":"30248",
    "sg:province":"GA",
    "wof:name":"August Woman Annex",
    "wof:placetype":"venue"
},
  "geometry": {"coordinates":[-84.12136599999999,33.351501],"type":"Point"}
}