{
  "type": "Feature",
  "properties": {
    "iso:country":"US",
    "sg:address":"828 Broad St",
    "sg:city":"Augusta",
    "sg:classifiers":[
        {
            "category":"Restaurant",
            "type":"Food & Drink"
        }
    ],
    "sg:phone":"+1 706 823 6430",
    "sg:postcode":"30901",
    "sg:province":"GA",
    "wof:name":"Fish & More",
    "wof:placetype":"venue"
},
  "geometry": {"coordinates":[-81.965761,33.475401],"type":"Point"}
}