{
  "type": "Feature",
  "properties": {
    "addr:full":"395 Project St Jesup GA 31545",
    "addr:postcode":"31545",
    "addr:street":"Project St",
    "iso:country":"US",
    "sg:address":"395 Project St",
    "sg:city":"Jesup",
    "sg:classifiers":[
        {
            "category":"Manufacturing",
            "subcategory":"Tools & Machinery",
            "type":"Manufacturing & Wholesale Goods"
        }
    ],
    "sg:phone":"+1 912 530 8200",
    "sg:postcode":"31545",
    "sg:province":"GA",
    "sg:tags":[
        "equipment",
        "lighting"
    ],
    "wof:name":"Ross Lighting & Accessories",
    "wof:placetype":"venue"
},
  "geometry": {"coordinates":[-81.882914,31.613903],"type":"Point"}
}