{
  "type": "Feature",
  "properties": {
    "iso:country":"US",
    "sg:address":"2882 N Druid Hills Rd NE",
    "sg:city":"Atlanta",
    "sg:classifiers":[
        {
            "category":"Real Estate",
            "subcategory":"Real Estate Agent",
            "type":"Services"
        }
    ],
    "sg:phone":"+1 404 633 1484",
    "sg:postcode":"30329",
    "sg:province":"GA",
    "wof:name":"Northside Realty",
    "wof:placetype":"venue"
},
  "geometry": {"coordinates":[-84.309408,33.814687],"type":"Point"}
}