{
  "type": "Feature",
  "properties": {
    "addr:full":"135 E Commerce St Pineview GA 31071",
    "addr:housenumber":"135",
    "addr:postcode":"31071",
    "addr:street":"E Commerce St",
    "iso:country":"US",
    "sg:address":"135 E Commerce St",
    "sg:city":"Pineview",
    "sg:classifiers":[
        {
            "category":"Government",
            "subcategory":"Post Office",
            "type":"Public Place"
        }
    ],
    "sg:phone":"+1 229 624 2320",
    "sg:postcode":"31071",
    "sg:province":"GA",
    "sg:tags":[
        "postal",
        "us"
    ],
    "wof:name":"US Post Office",
    "wof:placetype":"venue"
},
  "geometry": {"coordinates":[-83.50075200000001,32.110062],"type":"Point"}
}