{
  "type": "Feature",
  "properties": {
    "addr:full":"210 Dix-Lee-on Dr Fairburn GA 30213",
    "addr:housenumber":"210",
    "addr:postcode":"30213",
    "addr:street":"Dix-Lee-On Dr",
    "iso:country":"US",
    "sg:address":"210 Dix-Lee-on Dr",
    "sg:city":"Fairburn",
    "sg:classifiers":[
        {
            "category":"Banks & Credit Unions",
            "subcategory":"Bank",
            "type":"Services"
        }
    ],
    "sg:phone":"+1 678 817 0380",
    "sg:postcode":"30213",
    "sg:province":"GA",
    "sg:tags":[
        "loan",
        "education",
        "student"
    ],
    "wof:name":"Sallie Mae Inc",
    "wof:placetype":"venue"
},
  "geometry": {"coordinates":[-84.462388,33.54515],"type":"Point"}
}