{
  "type": "Feature",
  "properties": {
    "addr:full":"2519 Martin Luther King Jr Dr Albany GA 31701",
    "addr:housenumber":"2519",
    "addr:postcode":"31701",
    "addr:street":"Martin Luther King Jr Dr",
    "iso:country":"US",
    "sg:address":"2519 Martin Luther King Jr Dr",
    "sg:city":"Albany",
    "sg:classifiers":[
        {
            "category":"Social Services",
            "subcategory":"Child Care",
            "type":"Services"
        },
        {
            "category":"Social Services",
            "type":"Services"
        }
    ],
    "sg:phone":"+1 229 889 0335",
    "sg:postcode":"31701",
    "sg:province":"GA",
    "wof:name":"Macklin Day Care",
    "wof:placetype":"venue"
},
  "geometry": {"coordinates":[-84.155338,31.538747],"type":"Point"}
}