{
  "type": "Feature",
  "properties": {
    "iso:country":"US",
    "sg:address":"3250 Kiowa Ct",
    "sg:city":"Rex",
    "sg:classifiers":[
        {
            "category":"Social Services",
            "type":"Services"
        }
    ],
    "sg:phone":"+1 404 704 6332",
    "sg:postcode":"30273",
    "sg:province":"GA",
    "wof:name":"Georgia End Homelessness Project",
    "wof:placetype":"venue"
},
  "geometry": {"coordinates":[-84.284228,33.584029],"type":"Point"}
}