{
  "type": "Feature",
  "properties": {
    "addr:full":"4651 Meadows Rd Powder Springs GA 30127",
    "addr:housenumber":"4651",
    "addr:postcode":"30127",
    "addr:street":"Meadows Rd",
    "iso:country":"US",
    "sg:address":"4651 Meadows Rd",
    "sg:city":"Powder Springs",
    "sg:classifiers":[
        {
            "category":"Manufacturing",
            "subcategory":"Printing",
            "type":"Manufacturing & Wholesale Goods"
        }
    ],
    "sg:phone":"+1 770 439 7914",
    "sg:postcode":"30127",
    "sg:province":"GA",
    "sg:tags":[
        "publishing"
    ],
    "wof:name":"Double Take Press",
    "wof:placetype":"venue"
},
  "geometry": {"coordinates":[-84.68813900000001,33.840563],"type":"Point"}
}