{
  "type": "Feature",
  "properties": {
    "iso:country":"US",
    "sg:address":"5335 Cool Springs Rd",
    "sg:city":"Gainesville",
    "sg:classifiers":[
        {
            "category":"Professional",
            "subcategory":"Business Services",
            "type":"Services"
        }
    ],
    "sg:phone":"+1 770 531 0775",
    "sg:postcode":"30506",
    "sg:province":"GA",
    "wof:name":"Circle H Sales Inc",
    "wof:placetype":"venue"
},
  "geometry": {"coordinates":[-83.948751,34.373357],"type":"Point"}
}