{
  "type": "Feature",
  "properties": {
    "addr:full":"5555 Glenridge Connector NE Suite 200 Atlanta GA 30342",
    "addr:housenumber":"5555",
    "addr:postcode":"30342",
    "addr:street":"Glenridge Connector Ne Suite 200",
    "iso:country":"US",
    "sg:address":"5555 Glenridge Connector NE Suite 200",
    "sg:city":"Atlanta",
    "sg:classifiers":[
        {
            "category":"Social Services",
            "type":"Services"
        },
        {
            "category":"Health Services",
            "subcategory":"Nursing And Care Facility",
            "type":"Services"
        },
        {
            "category":"Health Services",
            "subcategory":"Health Practitioner",
            "type":"Services"
        },
        {
            "category":"Social Services",
            "subcategory":"Adult Care",
            "type":"Services"
        }
    ],
    "sg:phone":"+1 404 459 0021",
    "sg:postcode":"30342",
    "sg:province":"GA",
    "sg:tags":[
        "living",
        "consulting",
        "geriatric",
        "alzheimer's",
        "assisted",
        "elder",
        "home",
        "nurse",
        "eldercare-home"
    ],
    "sg:website":"http://www.brightstarcare.com/find-a-location/ga/nw-atlanta/",
    "wof:name":"BrightStar - NW Atlanta",
    "wof:placetype":"venue"
},
  "geometry": {"coordinates":[-84.36061100000001,33.90379],"type":"Point"}
}