{
  "type": "Feature",
  "properties": {
    "addr:full":"409 W 10th St West Point GA 31833",
    "addr:housenumber":"409",
    "addr:postcode":"31833",
    "addr:street":"W 10Th St",
    "iso:country":"US",
    "sg:address":"409 W 10th St",
    "sg:city":"West Point",
    "sg:classifiers":[
        {
            "category":"Health Services",
            "subcategory":"Clinic",
            "type":"Services"
        }
    ],
    "sg:phone":"+1 706 643 4300",
    "sg:postcode":"31833",
    "sg:province":"GA",
    "wof:name":"Health Bridge",
    "wof:placetype":"venue"
},
  "geometry": {"coordinates":[-85.18410799999999,32.879418],"type":"Point"}
}