{
  "type": "Feature",
  "properties": {
    "addr:full":"3050 Ellis Rd NW Kennesaw GA 30152",
    "addr:housenumber":"3050",
    "addr:postcode":"30152",
    "addr:street":"Ellis Rd Nw",
    "iso:country":"US",
    "sg:address":"3050 Ellis Rd NW",
    "sg:city":"Kennesaw",
    "sg:classifiers":[
        {
            "category":"Manufacturing",
            "subcategory":"Lumber",
            "type":"Manufacturing & Wholesale Goods"
        }
    ],
    "sg:phone":"+1 770 422 9318",
    "sg:postcode":"30152",
    "sg:province":"GA",
    "sg:tags":[
        "farm",
        "operation",
        "timber",
        "equine",
        "tract"
    ],
    "wof:name":"Salacoa Valley Farms Inc",
    "wof:placetype":"venue"
},
  "geometry": {"coordinates":[-84.639548,34.012592],"type":"Point"}
}