{
  "type": "Feature",
  "properties": {
    "addr:full":"1400 Coleman Ave Macon GA 31207",
    "addr:housenumber":"1400",
    "addr:postcode":"31207",
    "addr:street":"Coleman Ave",
    "iso:country":"US",
    "sg:address":"1400 Coleman Ave",
    "sg:city":"Macon",
    "sg:classifiers":[
        {
            "category":"Fast Food",
            "type":"Food & Drink"
        },
        {
            "category":"Restaurant",
            "type":"Food & Drink"
        },
        {
            "category":"Food & Beverages",
            "subcategory":"Groceries & Convenience Stores",
            "type":"Retail Goods"
        }
    ],
    "sg:phone":"+1 478 301 2925",
    "sg:postcode":"31207",
    "sg:province":"GA",
    "sg:tags":[
        "shop",
        "american",
        "sandwich",
        "take"
    ],
    "sg:website":"http://www.subway.com",
    "wof:name":"Subway",
    "wof:placetype":"venue"
},
  "geometry": {"coordinates":[-83.64795700000001,32.832169],"type":"Point"}
}