{
  "type": "Feature",
  "properties": {
    "iso:country":"US",
    "sg:address":"65 S Park St",
    "sg:city":"Dahlonega",
    "sg:classifiers":[
        {
            "category":"Travel",
            "subcategory":"Hotels & Motels",
            "type":"Entertainment"
        }
    ],
    "sg:phone":"+1 706 864 1713",
    "sg:postcode":"30533",
    "sg:province":"GA",
    "sg:tags":[
        "breakfast",
        "accommodation",
        "bed"
    ],
    "wof:name":"Royal Guard Inn B & B",
    "wof:placetype":"venue"
},
  "geometry": {"coordinates":[-83.98376500000001,34.532133],"type":"Point"}
}