{
  "type": "Feature",
  "properties": {
    "addr:full":"148 Temple Ave Newnan GA 30263",
    "addr:housenumber":"148",
    "addr:postcode":"30263",
    "addr:street":"Temple Ave",
    "iso:country":"US",
    "sg:address":"148 Temple Ave",
    "sg:city":"Newnan",
    "sg:classifiers":[
        {
            "category":"Banks & Credit Unions",
            "subcategory":"Financial Services",
            "type":"Services"
        },
        {
            "category":"Shopping",
            "subcategory":"Jewelry",
            "type":"Retail Goods"
        },
        {
            "category":"Manufacturing",
            "subcategory":"Jewelry",
            "type":"Manufacturing & Wholesale Goods"
        },
        {
            "category":"Shopping",
            "subcategory":"Pawn Shop",
            "type":"Retail Goods"
        }
    ],
    "sg:phone":"+1 770 755 6671",
    "sg:postcode":"30263",
    "sg:province":"GA",
    "sg:tags":[
        "loan",
        "designer",
        "pawnbroker",
        "jeweler"
    ],
    "wof:name":"Complete Cash Discount Title Pawn",
    "wof:placetype":"venue"
},
  "geometry": {"coordinates":[-84.812561,33.38195],"type":"Point"}
}