{
  "type": "Feature",
  "properties": {
    "addr:full":"3027 Redwine Rd Atlanta GA 30344",
    "addr:housenumber":"3027",
    "addr:postcode":"30344",
    "addr:street":"Redwine Rd",
    "iso:country":"US",
    "sg:address":"3027 Redwine Rd",
    "sg:city":"Atlanta",
    "sg:classifiers":[
        {
            "category":"Professional",
            "subcategory":"Computer Services",
            "type":"Services"
        }
    ],
    "sg:phone":"+1 404 762 0670",
    "sg:postcode":"30344",
    "sg:province":"GA",
    "sg:tags":[
        "consulting",
        "technology"
    ],
    "wof:name":"Grandstone Enterprises LLC",
    "wof:placetype":"venue"
},
  "geometry": {"coordinates":[-84.486447,33.660018],"type":"Point"}
}