{
  "type": "Feature",
  "properties": {
    "iso:country":"US",
    "sg:address":"44 Sewell Rd",
    "sg:city":"Taylorsville",
    "sg:classifiers":[
        {
            "category":"Building & Trades",
            "subcategory":"Construction",
            "type":"Services"
        }
    ],
    "sg:phone":"+1 770 684 8880",
    "sg:postcode":"30178",
    "sg:province":"GA",
    "sg:tags":[
        "residential"
    ],
    "wof:name":"Sutton Homes",
    "wof:placetype":"venue"
},
  "geometry": {"coordinates":[-85.002854,34.101736],"type":"Point"}
}