{
  "type": "Feature",
  "properties": {
    "iso:country":"US",
    "sg:address":"7227 Citation Dr",
    "sg:city":"Columbus",
    "sg:classifiers":[
        {
            "category":"Building & Trades",
            "subcategory":"Landscaping Services",
            "type":"Services"
        }
    ],
    "sg:phone":"+1 706 561 3714",
    "sg:postcode":"31909",
    "sg:province":"GA",
    "sg:tags":[
        "landscape"
    ],
    "wof:name":"Residential Landscaping",
    "wof:placetype":"venue"
},
  "geometry": {"coordinates":[-84.91167900000001,32.551903],"type":"Point"}
}