{
  "type": "Feature",
  "properties": {
    "addr:full":"229 Peachtree St NE Atlanta GA 30303",
    "addr:housenumber":"229",
    "addr:postcode":"30303",
    "addr:street":"Peachtree St Ne",
    "iso:country":"US",
    "sg:address":"229 Peachtree St NE",
    "sg:city":"Atlanta",
    "sg:classifiers":[
        {
            "category":"Freight",
            "type":"Transportation"
        }
    ],
    "sg:phone":"+1 770 903 1485",
    "sg:postcode":"30303",
    "sg:province":"GA",
    "sg:tags":[
        "delivery"
    ],
    "wof:name":"Fedex",
    "wof:placetype":"venue"
},
  "geometry": {"coordinates":[-84.387479,33.761282],"type":"Point"}
}