{
  "type": "Feature",
  "properties": {
    "iso:country":"US",
    "sg:address":"200 Sentinel Pl",
    "sg:city":"Marietta",
    "sg:classifiers":[
        {
            "category":"Manufacturing",
            "subcategory":"Apparel",
            "type":"Manufacturing & Wholesale Goods"
        }
    ],
    "sg:phone":"+1 770 977 4007",
    "sg:postcode":"30067",
    "sg:province":"GA",
    "sg:tags":[
        "manufacturer",
        "fixture",
        "belt"
    ],
    "wof:name":"Fixtures Inc",
    "wof:placetype":"venue"
},
  "geometry": {"coordinates":[-84.438335,33.951257],"type":"Point"}
}