{
  "type": "Feature",
  "properties": {
    "iso:country":"US",
    "sg:address":"6583 Oak Valley Dr",
    "sg:city":"Riverdale",
    "sg:classifiers":[
        {
            "category":"Building & Trades",
            "subcategory":"Landscaping Services",
            "type":"Services"
        }
    ],
    "sg:phone":"+1 770 996 6042",
    "sg:postcode":"30274",
    "sg:province":"GA",
    "wof:name":"Professional Yard Care",
    "wof:placetype":"venue"
},
  "geometry": {"coordinates":[-84.406247,33.584713],"type":"Point"}
}