{
  "type": "Feature",
  "properties": {
    "addr:full":"1320 Waverland Dr Macon GA 31211",
    "addr:housenumber":"1320",
    "addr:postcode":"31211",
    "addr:street":"Waverland Dr",
    "iso:country":"US",
    "sg:address":"1320 Waverland Dr",
    "sg:city":"Macon",
    "sg:classifiers":[
        {
            "category":"Real Estate",
            "subcategory":"Real Estate Operator",
            "type":"Services"
        }
    ],
    "sg:phone":"+1 478 744 0974",
    "sg:postcode":"31211",
    "sg:province":"GA",
    "sg:tags":[
        "building",
        "nonresidential"
    ],
    "wof:name":"Mmalj Properties LLC",
    "wof:placetype":"venue"
},
  "geometry": {"coordinates":[-83.635211,32.863389],"type":"Point"}
}