{
  "type": "Feature",
  "properties": {
    "addr:full":"9650 Medlock Bridge Rd Duluth GA 30097",
    "addr:housenumber":"9650",
    "addr:postcode":"30097",
    "addr:street":"Medlock Bridge Rd",
    "iso:country":"US",
    "sg:address":"9650 Medlock Bridge Rd",
    "sg:city":"Duluth",
    "sg:classifiers":[
        {
            "category":"Restaurant",
            "type":"Food & Drink"
        }
    ],
    "sg:menulink":"http://www.allmenus.com/ga/roswell-alpharetta/55071-waffle-house/menu/",
    "sg:phone":"+1 770 814 2888",
    "sg:postcode":"30097",
    "sg:province":"GA",
    "sg:tags":[
        "american"
    ],
    "wof:name":"Waffle House",
    "wof:placetype":"venue"
},
  "geometry": {"coordinates":[-84.190697,34.016127],"type":"Point"}
}