{
  "type": "Feature",
  "properties": {
    "addr:full":"7307 Wood Hollow Way Stone Mountain GA 30087",
    "addr:housenumber":"7307",
    "addr:postcode":"30087",
    "addr:street":"Wood Hollow Way",
    "iso:country":"US",
    "sg:address":"7307 Wood Hollow Way",
    "sg:city":"Stone Mountain",
    "sg:classifiers":[
        {
            "category":"Professional",
            "subcategory":"Management & Consulting",
            "type":"Services"
        }
    ],
    "sg:phone":"+1 770 465 3503",
    "sg:postcode":"30087",
    "sg:province":"GA",
    "sg:tags":[
        "development",
        "real estate"
    ],
    "wof:name":"Thomas Settles Family Group LP",
    "wof:placetype":"venue"
},
  "geometry": {"coordinates":[-84.089634,33.786617],"type":"Point"}
}