{
  "type": "Feature",
  "properties": {
    "addr:full":"1367 Big Sky Dr Hamilton GA 31811",
    "addr:housenumber":"1367",
    "addr:postcode":"31811",
    "addr:street":"Big Sky Dr",
    "iso:country":"US",
    "sg:address":"1367 Big Sky Dr",
    "sg:city":"Hamilton",
    "sg:classifiers":[
        {
            "category":"Professional",
            "subcategory":"Business Services",
            "type":"Services"
        }
    ],
    "sg:phone":"+1 706 628 4046",
    "sg:postcode":"31811",
    "sg:province":"GA",
    "wof:name":"Littlebranch Enterprises Inc",
    "wof:placetype":"venue"
},
  "geometry": {"coordinates":[-84.928455,32.718949],"type":"Point"}
}