{
  "type": "Feature",
  "properties": {
    "iso:country":"US",
    "sg:address":"1150 S Slappey Blvd",
    "sg:city":"Albany",
    "sg:classifiers":[
        {
            "category":"Food & Beverages",
            "subcategory":"Specialty",
            "type":"Retail Goods"
        }
    ],
    "sg:phone":"+1 229 436 1600",
    "sg:postcode":"31701",
    "sg:province":"GA",
    "wof:name":"Rite Start Plus",
    "wof:placetype":"venue"
},
  "geometry": {"coordinates":[-84.17621200000001,31.563097],"type":"Point"}
}