{
  "type": "Feature",
  "properties": {
    "iso:country":"US",
    "sg:address":"1968 Mineral Springs Rd",
    "sg:city":"Dalton",
    "sg:classifiers":[
        {
            "category":"Organizations",
            "subcategory":"Religious Organization",
            "type":"Services"
        }
    ],
    "sg:phone":"+1 706 278 2173",
    "sg:postcode":"30720",
    "sg:province":"GA",
    "wof:name":"Churches of Christ",
    "wof:placetype":"venue"
},
  "geometry": {"coordinates":[-84.998402,34.754109],"type":"Point"}
}