{
  "type": "Feature",
  "properties": {
    "iso:country":"US",
    "sg:address":"145 Howard Rd",
    "sg:city":"Fayetteville",
    "sg:classifiers":[
        {
            "category":"Professional",
            "subcategory":"Accounting & Tax Preparation",
            "type":"Services"
        }
    ],
    "sg:phone":"+1 770 716 1650",
    "sg:postcode":"30276",
    "sg:province":"GA",
    "sg:tags":[
        "accountant"
    ],
    "sg:website":"www.refjcpas.com",
    "wof:name":"Robins Eskew Farmer & Jordan",
    "wof:placetype":"venue"
},
  "geometry": {"coordinates":[-84.56849800000001,33.294274],"type":"Point"}
}