{
  "type": "Feature",
  "properties": {
    "addr:full":"1325 Coffee Rd Thomasville GA 31757",
    "addr:housenumber":"1325",
    "addr:postcode":"31757",
    "addr:street":"Coffee Rd",
    "iso:country":"US",
    "sg:address":"1325 Coffee Rd",
    "sg:city":"Thomasville",
    "sg:classifiers":[
        {
            "category":"Professional",
            "subcategory":"Business Services",
            "type":"Services"
        }
    ],
    "sg:phone":"+1 229 227 0065",
    "sg:postcode":"31757",
    "sg:province":"GA",
    "sg:website":"www.hardmangroup.com",
    "wof:name":"Hardman Group",
    "wof:placetype":"venue"
},
  "geometry": {"coordinates":[-83.84774,30.880198],"type":"Point"}
}