{
  "type": "Feature",
  "properties": {
    "iso:country":"US",
    "sg:address":"1202 Karen Ln",
    "sg:city":"Douglas",
    "sg:classifiers":[
        {
            "category":"Professional",
            "type":"Services"
        }
    ],
    "sg:phone":"+1 912 389 1326",
    "sg:postcode":"31533",
    "sg:province":"GA",
    "wof:name":"Sherry Wright",
    "wof:placetype":"venue"
},
  "geometry": {"coordinates":[-82.86493299999999,31.52256],"type":"Point"}
}