{
  "type": "Feature",
  "properties": {
    "iso:country":"US",
    "sg:address":"4400 Lakeside Hills Pt",
    "sg:city":"Kennesaw",
    "sg:classifiers":[
        {
            "category":"Professional",
            "subcategory":"Business Services",
            "type":"Services"
        }
    ],
    "sg:phone":"+1 770 924 0705",
    "sg:postcode":"30144",
    "sg:province":"GA",
    "wof:name":"McNally Harold D & Assoc Inc",
    "wof:placetype":"venue"
},
  "geometry": {"coordinates":[-84.54361299999999,34.059196],"type":"Point"}
}