{
  "type": "Feature",
  "properties": {
    "addr:full":"195 Avory Ln Ellijay GA 30536",
    "addr:housenumber":"195",
    "addr:postcode":"30536",
    "addr:street":"Avory Ln",
    "iso:country":"US",
    "sg:address":"195 Avory Ln",
    "sg:city":"Ellijay",
    "sg:classifiers":[
        {
            "category":"Shopping",
            "subcategory":"Pets & Pet Supplies",
            "type":"Retail Goods"
        }
    ],
    "sg:phone":"+1 706 276 7888",
    "sg:postcode":"30536",
    "sg:province":"GA",
    "sg:tags":[
        "furnishing",
        "dog",
        "store",
        "cat"
    ],
    "wof:name":"Bluebird Housing",
    "wof:placetype":"venue"
},
  "geometry": {"coordinates":[-84.421645,34.59387],"type":"Point"}
}