{
  "type": "Feature",
  "properties": {
    "addr:full":"4844 Mount Vernon Rd Gainesville GA 30506",
    "addr:housenumber":"4844",
    "addr:postcode":"30506",
    "addr:street":"Mount Vernon Rd",
    "iso:country":"US",
    "sg:address":"4844 Mount Vernon Rd",
    "sg:city":"Gainesville",
    "sg:classifiers":[
        {
            "category":"Professional",
            "type":"Services"
        }
    ],
    "sg:phone":"+1 770 983 3326",
    "sg:postcode":"30506",
    "sg:province":"GA",
    "wof:name":"Free & Accepted Masons of",
    "wof:placetype":"venue"
},
  "geometry": {"coordinates":[-83.85073300000001,34.428975],"type":"Point"}
}