{
  "type": "Feature",
  "properties": {
    "addr:full":"2248 Mill Creek Rd Patterson GA 31557",
    "addr:housenumber":"2248",
    "addr:postcode":"31557",
    "addr:street":"Mill Creek Rd",
    "iso:country":"US",
    "sg:address":"2248 Mill Creek Rd",
    "sg:city":"Patterson",
    "sg:classifiers":[
        {
            "category":"Personal",
            "subcategory":"Beauty Salon",
            "type":"Services"
        }
    ],
    "sg:phone":"+1 912 647 0178",
    "sg:postcode":"31557",
    "sg:province":"GA",
    "wof:name":"Wendy's Hairstyle",
    "wof:placetype":"venue"
},
  "geometry": {"coordinates":[-82.133978,31.452088],"type":"Point"}
}