{
  "type": "Feature",
  "properties": {
    "addr:full":"1420 Gray Hwy Macon GA 31211",
    "addr:housenumber":"1420",
    "addr:postcode":"31211",
    "addr:street":"Gray Hwy",
    "iso:country":"US",
    "sg:address":"1420 Gray Hwy",
    "sg:city":"Macon",
    "sg:classifiers":[
        {
            "category":"Real Estate",
            "subcategory":"Real Estate Operator",
            "type":"Services"
        }
    ],
    "sg:phone":"+1 478 746 8808",
    "sg:postcode":"31211",
    "sg:province":"GA",
    "sg:tags":[
        "building",
        "apartment"
    ],
    "wof:name":"Glenwood Village Apartments",
    "wof:placetype":"venue"
},
  "geometry": {"coordinates":[-83.614603,32.860135],"type":"Point"}
}