{
  "type": "Feature",
  "properties": {
    "iso:country":"US",
    "sg:address":"2005 Danielsville Rd",
    "sg:city":"Athens",
    "sg:classifiers":[
        {
            "category":"Restaurant",
            "type":"Food & Drink"
        }
    ],
    "sg:phone":"+1 706 227 2100",
    "sg:postcode":"30601",
    "sg:province":"GA",
    "sg:tags":[
        "banquet",
        "rooms"
    ],
    "wof:name":"Suburban Country Club",
    "wof:placetype":"venue"
},
  "geometry": {"coordinates":[-83.348955,34.006197],"type":"Point"}
}