{
  "type": "Feature",
  "properties": {
    "iso:country":"US",
    "sg:address":"3948 Bright Star Rd",
    "sg:city":"Douglasville",
    "sg:classifiers":[
        {
            "category":"Real Estate",
            "subcategory":"Real Estate Agent",
            "type":"Services"
        }
    ],
    "sg:phone":"+1 770 942 2414",
    "sg:postcode":"30135",
    "sg:province":"GA",
    "wof:name":"B & N Properties Inc",
    "wof:placetype":"venue"
},
  "geometry": {"coordinates":[-84.79163699999999,33.697621],"type":"Point"}
}