{
  "type": "Feature",
  "properties": {
    "addr:full":"400 Camaron Way Snellville GA 30039",
    "addr:housenumber":"400",
    "addr:postcode":"30039",
    "addr:street":"Camaron Way",
    "iso:country":"US",
    "sg:address":"400 Camaron Way",
    "sg:city":"Snellville",
    "sg:classifiers":[
        {
            "category":"Shopping",
            "subcategory":"Music",
            "type":"Retail Goods"
        },
        {
            "category":"Arts & Performance",
            "subcategory":"Music",
            "type":"Entertainment"
        },
        {
            "category":"Recreation",
            "subcategory":"Dance Hall",
            "type":"Entertainment"
        },
        {
            "category":"Wholesale",
            "subcategory":"Music Publishers",
            "type":"Manufacturing & Wholesale Goods"
        },
        {
            "category":"Recreation",
            "type":"Entertainment"
        }
    ],
    "sg:phone":"+1 770 595 7953",
    "sg:postcode":"30039",
    "sg:province":"GA",
    "sg:tags":[
        "producer",
        "business",
        "club",
        "entertainers-family",
        "distribution",
        "store"
    ],
    "sg:website":"http://www.rhapsody.com/eugene-jackson",
    "wof:name":"Eugene Jackson",
    "wof:placetype":"venue"
},
  "geometry": {"coordinates":[-84.021828,33.798199],"type":"Point"}
}