{
  "type": "Feature",
  "properties": {
    "addr:full":"868 John Walker Rd Dahlonega GA 30533",
    "addr:housenumber":"868",
    "addr:postcode":"30533",
    "addr:street":"John Walker Rd",
    "iso:country":"US",
    "sg:address":"868 John Walker Rd",
    "sg:city":"Dahlonega",
    "sg:classifiers":[
        {
            "category":"Professional",
            "subcategory":"Computer Services",
            "type":"Services"
        }
    ],
    "sg:phone":"+1 706 867 6463",
    "sg:postcode":"30533",
    "sg:province":"GA",
    "sg:tags":[
        "related"
    ],
    "wof:name":"Haventouch Enterprises",
    "wof:placetype":"venue"
},
  "geometry": {"coordinates":[-84.026397,34.504073],"type":"Point"}
}