{
  "type": "Feature",
  "properties": {
    "iso:country":"US",
    "sg:address":"1903 Winding Creek Ln SW",
    "sg:city":"Marietta",
    "sg:classifiers":[
        {
            "category":"Building & Trades",
            "subcategory":"Locksmith",
            "type":"Services"
        }
    ],
    "sg:phone":"+1 770 250 0526",
    "sg:postcode":"30064",
    "sg:province":"GA",
    "sg:tags":[
        "key"
    ],
    "wof:name":"24 Hr Emerg A Locksmith",
    "wof:placetype":"venue"
},
  "geometry": {"coordinates":[-84.612534,33.935803],"type":"Point"}
}