{
  "type": "Feature",
  "properties": {
    "addr:full":"4053 Belair Rd Augusta GA 30909",
    "addr:housenumber":"4053",
    "addr:postcode":"30909",
    "addr:street":"Belair Rd",
    "iso:country":"US",
    "sg:address":"4053 Belair Rd",
    "sg:city":"Augusta",
    "sg:classifiers":[
        {
            "category":"Personal",
            "subcategory":"Beauty Salon",
            "type":"Services"
        }
    ],
    "sg:phone":"+1 706 868 5888",
    "sg:postcode":"30909",
    "sg:province":"GA",
    "wof:name":"Hair Designs By Patricia",
    "wof:placetype":"venue"
},
  "geometry": {"coordinates":[-82.12856499999999,33.472017],"type":"Point"}
}