{
  "type": "Feature",
  "properties": {
    "iso:country":"US",
    "sg:address":"208 North Ave NE",
    "sg:city":"Rome",
    "sg:classifiers":[
        {
            "category":"Place Of Worship",
            "type":"Public Place"
        }
    ],
    "sg:phone":"+1 706 766 4938",
    "sg:postcode":"30161",
    "sg:province":"GA",
    "sg:tags":[
        "church"
    ],
    "wof:name":"United Christian Church O",
    "wof:placetype":"venue"
},
  "geometry": {"coordinates":[-85.153099,34.273071],"type":"Point"}
}