{
  "type": "Feature",
  "properties": {
    "addr:full":"200 Galleria Pkwy Atlanta GA 30339",
    "addr:housenumber":"200",
    "addr:postcode":"30339",
    "addr:street":"Galleria Pkwy",
    "iso:country":"US",
    "sg:address":"200 Galleria Pkwy",
    "sg:city":"Atlanta",
    "sg:classifiers":[
        {
            "category":"Professional",
            "subcategory":"Management & Consulting",
            "type":"Services"
        }
    ],
    "sg:phone":"+1 770 563 8234",
    "sg:postcode":"30339",
    "sg:province":"GA",
    "sg:tags":[
        "consultant",
        "business"
    ],
    "wof:name":"Lydian Wealth Management",
    "wof:placetype":"venue"
},
  "geometry": {"coordinates":[-84.46521799999999,33.882865],"type":"Point"}
}