{
  "type": "Feature",
  "properties": {
    "addr:full":"21 Old Airport Rd Rome GA 30165",
    "addr:housenumber":"21",
    "addr:postcode":"ga 30165",
    "addr:street":"Old Airport Rd",
    "iso:country":"US",
    "sg:address":"21 Old Airport Rd",
    "sg:city":"Rome",
    "sg:classifiers":[
        {
            "category":"Building & Trades",
            "subcategory":"Construction",
            "type":"Services"
        }
    ],
    "sg:phone":"+1 706 291 1985",
    "sg:postcode":"30165",
    "sg:province":"GA",
    "sg:tags":[
        "fabricator",
        "metal"
    ],
    "wof:name":"Metal Fabrication Inc",
    "wof:placetype":"venue"
},
  "geometry": {"coordinates":[-85.221501,34.274283],"type":"Point"}
}