{
  "type": "Feature",
  "properties": {
    "iso:country":"US",
    "sg:address":"2401 Massachusetts Ave",
    "sg:city":"Waycross",
    "sg:classifiers":[
        {
            "category":"Restaurant",
            "type":"Food & Drink"
        }
    ],
    "sg:phone":"+1 912 284 0324",
    "sg:postcode":"31503",
    "sg:province":"GA",
    "sg:tags":[
        "house",
        "steak",
        "barbecue"
    ],
    "wof:name":"B & E Bar B Q 2",
    "wof:placetype":"venue"
},
  "geometry": {"coordinates":[-82.399818,31.192909],"type":"Point"}
}