{
  "type": "Feature",
  "properties": {
    "iso:country":"US",
    "sg:address":"4505 Canterbury Dr",
    "sg:city":"Cumming",
    "sg:classifiers":[
        {
            "category":"Recreation",
            "type":"Entertainment"
        }
    ],
    "sg:phone":"+1 770 889 7699",
    "sg:postcode":"30040",
    "sg:province":"GA",
    "sg:tags":[
        "pool",
        "swimming"
    ],
    "wof:name":"Canterbury Home Owners Assn",
    "wof:placetype":"venue"
},
  "geometry": {"coordinates":[-84.21916400000001,34.216841],"type":"Point"}
}