{
  "type": "Feature",
  "properties": {
    "iso:country":"US",
    "sg:address":"12370 Arnold Mill Rd",
    "sg:city":"Alpharetta",
    "sg:classifiers":[
        {
            "category":"Manufacturing",
            "subcategory":"Tools & Machinery",
            "type":"Manufacturing & Wholesale Goods"
        },
        {
            "category":"Building & Trades",
            "subcategory":"Construction",
            "type":"Services"
        },
        {
            "category":"Wholesale",
            "subcategory":"Painting Supplies",
            "type":"Manufacturing & Wholesale Goods"
        },
        {
            "category":"Home & Garden",
            "subcategory":"Building Materials",
            "type":"Retail Goods"
        },
        {
            "category":"Manufacturing",
            "subcategory":"Chemicals & Compounds",
            "type":"Manufacturing & Wholesale Goods"
        },
        {
            "category":"Autos & Motor Vehicles",
            "subcategory":"Auto Supplies",
            "type":"Retail Goods"
        },
        {
            "category":"Building & Trades",
            "subcategory":"Equipment Rental",
            "type":"Services"
        },
        {
            "category":"Manufacturing",
            "subcategory":"Building Materials",
            "type":"Manufacturing & Wholesale Goods"
        }
    ],
    "sg:phone":"+1 770 740 9717",
    "sg:postcode":"30004",
    "sg:province":"GA",
    "sg:tags":[
        "body",
        "shop",
        "paint",
        "wall",
        "wallcoverings-installation",
        "wallpaper",
        "coating",
        "contractor",
        "paint-wholesale",
        "spraying",
        "automobile",
        "wallcoverings",
        "equipment-renting",
        "painter",
        "manufacturer"
    ],
    "sg:website":"http://www.sherwin-williams.com/",
    "wof:name":"Sherwin-Williams",
    "wof:placetype":"venue"
},
  "geometry": {"coordinates":[-84.35846600000001,34.084052],"type":"Point"}
}