{
  "type": "Feature",
  "properties": {
    "addr:full":"5425 Buford Hwy NE Atlanta GA 30340",
    "addr:housenumber":"5425",
    "addr:postcode":"30340",
    "addr:street":"Buford Hwy Ne",
    "iso:country":"US",
    "sg:address":"5425 Buford Hwy NE",
    "sg:city":"Atlanta",
    "sg:classifiers":[
        {
            "category":"Bars & Pubs",
            "subcategory":"Lounge",
            "type":"Food & Drink"
        }
    ],
    "sg:phone":"+1 770 458 8661",
    "sg:postcode":"30340",
    "sg:province":"GA",
    "sg:tags":[
        "karaoke"
    ],
    "wof:name":"Hangbok - Happy Karaoke",
    "wof:placetype":"venue"
},
  "geometry": {"coordinates":[-84.277732,33.900096],"type":"Point"}
}