{
  "type": "Feature",
  "properties": {
    "iso:country":"US",
    "sg:address":"380 Dan Pl",
    "sg:city":"Smyrna",
    "sg:classifiers":[
        {
            "category":"Manufacturing",
            "subcategory":"Apparel",
            "type":"Manufacturing & Wholesale Goods"
        }
    ],
    "sg:phone":"+1 770 434 0136",
    "sg:postcode":"30082",
    "sg:province":"GA",
    "sg:tags":[
        "mfg"
    ],
    "wof:name":"Anns Drapery Service",
    "wof:placetype":"venue"
},
  "geometry": {"coordinates":[-84.54272899999999,33.872709],"type":"Point"}
}