{
  "type": "Feature",
  "properties": {
    "iso:country":"US",
    "sg:address":"4553 N Shallowford Rd Ste 20B",
    "sg:city":"Atlanta",
    "sg:classifiers":[
        {
            "category":"Health Services",
            "subcategory":"Doctor",
            "type":"Services"
        }
    ],
    "sg:phone":"+1 770 457 6303",
    "sg:postcode":"30338",
    "sg:province":"GA",
    "sg:tags":[
        "surgeon",
        "cosmetic"
    ],
    "wof:name":"Premier Image Cosmetic & Laser Surgery PA",
    "wof:placetype":"venue"
},
  "geometry": {"coordinates":[-84.306702,33.9235],"type":"Point"}
}