{
  "type": "Feature",
  "properties": {
    "addr:full":"1520 Clifton Rd NE Ste 402 Atlanta GA 30322",
    "addr:housenumber":"1520",
    "addr:postcode":"30322",
    "addr:street":"Clifton Rd Ne Ste 402",
    "iso:country":"US",
    "sg:address":"1520 Clifton Rd NE Ste 402",
    "sg:city":"Atlanta",
    "sg:classifiers":[
        {
            "category":"Education",
            "subcategory":"University",
            "type":"Public Place"
        }
    ],
    "sg:phone":"+1 404 727 6910",
    "sg:postcode":"30322",
    "sg:province":"GA",
    "sg:tags":[
        "college"
    ],
    "wof:name":"Emory University School-Nrsng",
    "wof:placetype":"venue"
},
  "geometry": {"coordinates":[-84.32245,33.797299],"type":"Point"}
}