{
  "type": "Feature",
  "properties": {
    "iso:country":"US",
    "sg:address":"565 Wimbish Rd",
    "sg:city":"Macon",
    "sg:classifiers":[
        {
            "category":"Organizations",
            "subcategory":"Religious Organization",
            "type":"Services"
        }
    ],
    "sg:phone":"+1 478 477 6646",
    "sg:postcode":"31210",
    "sg:province":"GA",
    "sg:tags":[
        "presbyterian",
        "church"
    ],
    "wof:name":"Northminister Presbt Church",
    "wof:placetype":"venue"
},
  "geometry": {"coordinates":[-83.69024400000001,32.87258],"type":"Point"}
}