{
  "type": "Feature",
  "properties": {
    "iso:country":"US",
    "sg:address":"401 W Peachtree St NW",
    "sg:city":"Atlanta",
    "sg:classifiers":[
        {
            "category":"Government",
            "subcategory":"Office",
            "type":"Public Place"
        }
    ],
    "sg:phone":"+1 404 730 3300",
    "sg:postcode":"30308",
    "sg:province":"GA",
    "sg:tags":[
        "federal",
        "program",
        "adm"
    ],
    "wof:name":"US Minority Business Dev Agcy",
    "wof:placetype":"venue"
},
  "geometry": {"coordinates":[-84.387439,33.764817],"type":"Point"}
}