{
  "type": "Feature",
  "properties": {
    "addr:full":"2524 Lithonia Industrial Blvd Lithonia GA 30058",
    "addr:housenumber":"2524",
    "addr:postcode":"30058",
    "addr:street":"Lithonia Industrial Blvd",
    "iso:country":"US",
    "sg:address":"2524 Lithonia Industrial Blvd",
    "sg:city":"Lithonia",
    "sg:classifiers":[
        {
            "category":"Building & Trades",
            "subcategory":"Construction",
            "type":"Services"
        }
    ],
    "sg:phone":"+1 678 526 8189",
    "sg:postcode":"30058",
    "sg:province":"GA",
    "sg:tags":[
        "house",
        "nonresidential",
        "general",
        "contractor"
    ],
    "wof:name":"Construction Works Inc",
    "wof:placetype":"venue"
},
  "geometry": {"coordinates":[-84.128659,33.710175],"type":"Point"}
}