{
  "type": "Feature",
  "properties": {
    "iso:country":"US",
    "sg:address":"4458 Atlas Pl",
    "sg:city":"Tucker",
    "sg:classifiers":[
        {
            "category":"Professional",
            "subcategory":"Business Services",
            "type":"Services"
        }
    ],
    "sg:phone":"+1 678 937 0545",
    "sg:postcode":"30084",
    "sg:province":"GA",
    "sg:tags":[
        "automobile",
        "appraiser"
    ],
    "wof:name":"Atlas Appraisal Group",
    "wof:placetype":"venue"
},
  "geometry": {"coordinates":[-84.205323,33.876769],"type":"Point"}
}