{
  "type": "Feature",
  "properties": {
    "addr:full":"10749 Alpharetta Hwy Roswell GA 30076",
    "addr:housenumber":"10749",
    "addr:postcode":"30076",
    "addr:street":"Alpharetta Hwy",
    "iso:country":"US",
    "sg:address":"10749 Alpharetta Hwy",
    "sg:city":"Roswell",
    "sg:classifiers":[
        {
            "category":"Health Services",
            "subcategory":"Dentist",
            "type":"Services"
        }
    ],
    "sg:phone":"+1 770 992 7790",
    "sg:postcode":"30076",
    "sg:province":"GA",
    "wof:name":"Sluss Larry E DDS PC",
    "wof:placetype":"venue"
},
  "geometry": {"coordinates":[-84.34169799999999,34.042198],"type":"Point"}
}