{
  "type": "Feature",
  "properties": {
    "iso:country":"US",
    "sg:address":"3915 Spalding Bluff Dr",
    "sg:city":"Norcross",
    "sg:classifiers":[
        {
            "category":"Wholesale",
            "subcategory":"Medical Equipment & Supplies",
            "type":"Manufacturing & Wholesale Goods"
        }
    ],
    "sg:phone":"+1 770 300 0750",
    "sg:postcode":"30092",
    "sg:province":"GA",
    "wof:name":"Inmex Medical",
    "wof:placetype":"venue"
},
  "geometry": {"coordinates":[-84.24596699999999,33.969235],"type":"Point"}
}