{
  "type": "Feature",
  "properties": {
    "iso:country":"US",
    "sg:address":"120 Pet Care Ct",
    "sg:city":"Cornelia",
    "sg:classifiers":[
        {
            "category":"Animal Shelter",
            "type":"Public Place"
        },
        {
            "category":"Retail",
            "subcategory":"Veterinary Services",
            "type":"Services"
        },
        {
            "category":"Retail",
            "subcategory":"Pet Boarding",
            "type":"Services"
        }
    ],
    "sg:phone":"+1 888 503 1876",
    "sg:postcode":"30531",
    "sg:province":"GA",
    "sg:tags":[
        "hospital",
        "veterinarian",
        "clinic",
        "laboratories-veterinary",
        "kennel"
    ],
    "sg:website":"http://local.ingenio.com/Listings/Details.aspx?NUM=a%3a9243957%3a13%3a4859924%3a14%3a0%3a7",
    "wof:name":"Northeast Veterinary Hospital",
    "wof:placetype":"venue"
},
  "geometry": {"coordinates":[-83.53845099999999,34.534824],"type":"Point"}
}