{
  "type": "Feature",
  "properties": {
    "iso:country":"US",
    "sg:address":"4416 Columbia Rd",
    "sg:city":"Martinez",
    "sg:classifiers":[
        {
            "category":"Building & Trades",
            "subcategory":"Construction",
            "type":"Services"
        }
    ],
    "sg:phone":"+1 706 210 8624",
    "sg:postcode":"30907",
    "sg:province":"GA",
    "sg:tags":[
        "general",
        "contractor"
    ],
    "wof:name":"Horizon Construction & Assoc",
    "wof:placetype":"venue"
},
  "geometry": {"coordinates":[-82.135398,33.507619],"type":"Point"}
}