{
  "type": "Feature",
  "properties": {
    "addr:full":"6033 Roosevelt Hwy Union City GA 30291",
    "addr:housenumber":"6033",
    "addr:postcode":"30291",
    "addr:street":"Roosevelt Hwy",
    "iso:country":"US",
    "sg:address":"6033 Roosevelt Hwy",
    "sg:city":"Union City",
    "sg:classifiers":[
        {
            "category":"Organizations",
            "subcategory":"Religious Organization",
            "type":"Services"
        }
    ],
    "sg:phone":"+1 770 969 7080",
    "sg:postcode":"30291",
    "sg:province":"GA",
    "sg:website":"www.churchofthelivingway.com",
    "wof:name":"Church of the Living Way",
    "wof:placetype":"venue"
},
  "geometry": {"coordinates":[-84.54879800000001,33.591702],"type":"Point"}
}