{
  "type": "Feature",
  "properties": {
    "addr:full":"3379 Highway 5 Douglasville GA 30135",
    "addr:housenumber":"3379",
    "addr:postcode":"30135",
    "addr:street":"Highway 5",
    "iso:country":"US",
    "sg:address":"3379 Highway 5",
    "sg:city":"Douglasville",
    "sg:classifiers":[
        {
            "category":"Professional",
            "subcategory":"Lawyer & Legal Services",
            "type":"Services"
        }
    ],
    "sg:phone":"+1 770 949 3200",
    "sg:postcode":"30135",
    "sg:province":"GA",
    "sg:tags":[
        "divorce",
        "law",
        "family"
    ],
    "wof:name":"Kunz Robert A Atty",
    "wof:placetype":"venue"
},
  "geometry": {"coordinates":[-84.769897,33.713001],"type":"Point"}
}