{
  "type": "Feature",
  "properties": {
    "iso:country":"US",
    "sg:address":"242 Highway 138 W",
    "sg:city":"Jonesboro",
    "sg:classifiers":[
        {
            "category":"Food & Beverages",
            "subcategory":"Groceries & Convenience Stores",
            "type":"Retail Goods"
        }
    ],
    "sg:phone":"+1 770 478 2824",
    "sg:postcode":"30238",
    "sg:province":"GA",
    "sg:website":"www.ingles-markets.com",
    "wof:name":"Ingles Supermarkets",
    "wof:placetype":"venue"
},
  "geometry": {"coordinates":[-84.38649700000001,33.540401],"type":"Point"}
}