{
  "type": "Feature",
  "properties": {
    "iso:country":"US",
    "sg:address":"1373 Beecher St SW",
    "sg:city":"Atlanta",
    "sg:classifiers":[
        {
            "category":"Social Services",
            "subcategory":"Child Care",
            "type":"Services"
        }
    ],
    "sg:phone":"+1 404 758 3738",
    "sg:postcode":"30310",
    "sg:province":"GA",
    "sg:tags":[
        "day"
    ],
    "wof:name":"Heavenly Angels Day Care Inc",
    "wof:placetype":"venue"
},
  "geometry": {"coordinates":[-84.432528,33.733286],"type":"Point"}
}