{
  "type": "Feature",
  "properties": {
    "addr:full":"14 W Jarrard St Cleveland GA 30528",
    "addr:housenumber":"14",
    "addr:postcode":"30528",
    "addr:street":"W Jarrard St",
    "iso:country":"US",
    "sg:address":"14 W Jarrard St",
    "sg:city":"Cleveland",
    "sg:classifiers":[
        {
            "category":"Restaurant",
            "type":"Food & Drink"
        }
    ],
    "sg:phone":"+1 706 219 1942",
    "sg:postcode":"30528",
    "sg:province":"GA",
    "wof:name":"Zanzo Italian Cafe",
    "wof:placetype":"venue"
},
  "geometry": {"coordinates":[-83.76577,34.597467],"type":"Point"}
}