{
  "type": "Feature",
  "properties": {
    "iso:country":"US",
    "sg:address":"1624 US Hwy 27",
    "sg:city":"Carrollton",
    "sg:classifiers":[
        {
            "category":"Shopping",
            "subcategory":"Discount & Variety Stores",
            "type":"Retail Goods"
        }
    ],
    "sg:phone":"+1 770 830 9060",
    "sg:postcode":"30117",
    "sg:province":"GA",
    "wof:name":"Surprise Variety Store",
    "wof:placetype":"venue"
},
  "geometry": {"coordinates":[-85.095371,33.618673],"type":"Point"}
}