{
  "type": "Feature",
  "properties": {
    "addr:full":"237 Jones Rd Reidsville GA 30473",
    "addr:housenumber":"237",
    "addr:postcode":"30473",
    "addr:street":"Jones Rd",
    "iso:country":"US",
    "sg:address":"237 Jones Rd",
    "sg:city":"Reidsville",
    "sg:classifiers":[
        {
            "category":"Insurance",
            "subcategory":"Insurance Agent",
            "type":"Services"
        }
    ],
    "sg:phone":"+1 912 654 2143",
    "sg:postcode":"30473",
    "sg:province":"GA",
    "wof:name":"Rick Jones Agency",
    "wof:placetype":"venue"
},
  "geometry": {"coordinates":[-82.497817,32.053074],"type":"Point"}
}