{
  "type": "Feature",
  "properties": {
    "iso:country":"US",
    "sg:address":"1453 Riverstone Pkwy # 150",
    "sg:city":"Canton",
    "sg:classifiers":[
        {
            "category":"Personal",
            "subcategory":"Beauty Salon",
            "type":"Services"
        }
    ],
    "sg:phone":"+1 770 720 2530",
    "sg:postcode":"30114",
    "sg:province":"GA",
    "sg:website":"http://www.ratnerco.com",
    "wof:name":"Creative Hairdressers",
    "wof:placetype":"venue"
},
  "geometry": {"coordinates":[-84.47286200000001,34.251673],"type":"Point"}
}