{
  "type": "Feature",
  "properties": {
    "iso:country":"US",
    "sg:address":"820 Harrington Dr",
    "sg:city":"Milledgeville",
    "sg:classifiers":[
        {
            "category":"Real Estate",
            "subcategory":"Real Estate Services",
            "type":"Services"
        },
        {
            "category":"Banks & Credit Unions",
            "subcategory":"Financial Services",
            "type":"Services"
        }
    ],
    "sg:phone":"+1 478 453 9066",
    "sg:postcode":"31061",
    "sg:province":"GA",
    "sg:tags":[
        "loan",
        "processing"
    ],
    "wof:name":"Mas",
    "wof:placetype":"venue"
},
  "geometry": {"coordinates":[-83.23774299999999,33.074388],"type":"Point"}
}