{
  "type": "Feature",
  "properties": {
    "iso:country":"US",
    "sg:address":"4121 Bullock Bridge Rd",
    "sg:city":"Loganville",
    "sg:classifiers":[
        {
            "category":"Communications",
            "type":"Services"
        }
    ],
    "sg:phone":"+1 770 466 8088",
    "sg:postcode":"30052",
    "sg:province":"GA",
    "sg:tags":[
        "communication"
    ],
    "wof:name":"Coastal Communication Service",
    "wof:placetype":"venue"
},
  "geometry": {"coordinates":[-83.818437,33.866117],"type":"Point"}
}