{
  "type": "Feature",
  "properties": {
    "addr:full":"2772 Cumberland Blvd Smyrna GA 30080",
    "addr:housenumber":"2772",
    "addr:postcode":"30080",
    "addr:street":"Cumberland Blvd",
    "iso:country":"US",
    "sg:address":"2772 Cumberland Blvd",
    "sg:city":"Smyrna",
    "sg:classifiers":[
        {
            "category":"Restaurant",
            "type":"Food & Drink"
        }
    ],
    "sg:postcode":"30080",
    "sg:province":"GA",
    "sg:tags":[
        "indian"
    ],
    "wof:name":"Udipi Cafe",
    "wof:placetype":"venue"
},
  "geometry": {"coordinates":[-84.476066,33.8871],"type":"Point"}
}