{
  "type": "Feature",
  "properties": {
    "iso:country":"US",
    "sg:address":"801 Commerce St",
    "sg:city":"Perry",
    "sg:classifiers":[
        {
            "category":"Social Services",
            "type":"Services"
        }
    ],
    "sg:phone":"+1 478 218 2274",
    "sg:postcode":"31069",
    "sg:province":"GA",
    "sg:tags":[
        "organization",
        "welfare"
    ],
    "wof:name":"Perry Volunteer Outreach",
    "wof:placetype":"venue"
},
  "geometry": {"coordinates":[-83.73393299999999,32.458965],"type":"Point"}
}