{
  "type": "Feature",
  "properties": {
    "addr:full":"905 Harris Ave Bowdon GA 30108",
    "addr:housenumber":"905",
    "addr:postcode":"30108",
    "addr:street":"Harris Ave",
    "iso:country":"US",
    "sg:address":"905 Harris Ave",
    "sg:city":"Bowdon",
    "sg:classifiers":[
        {
            "category":"Personal",
            "subcategory":"Beauty Salon",
            "type":"Services"
        }
    ],
    "sg:phone":"+1 770 258 3155",
    "sg:postcode":"30108",
    "sg:province":"GA",
    "wof:name":"Irene's Beauty Shop",
    "wof:placetype":"venue"
},
  "geometry": {"coordinates":[-85.268428,33.541039],"type":"Point"}
}