{
  "type": "Feature",
  "properties": {
    "addr:full":"157 Kestwick Dr E Augusta GA 30907",
    "addr:housenumber":"157",
    "addr:postcode":"30907",
    "addr:street":"Kestwick Dr E",
    "iso:country":"US",
    "sg:address":"157 Kestwick Dr E",
    "sg:city":"Augusta",
    "sg:classifiers":[
        {
            "category":"Professional",
            "subcategory":"Management & Consulting",
            "type":"Services"
        }
    ],
    "sg:phone":"+1 706 650 0507",
    "sg:postcode":"30907",
    "sg:province":"GA",
    "sg:tags":[
        "company",
        "construction"
    ],
    "wof:name":"Cmtech Inc",
    "wof:placetype":"venue"
},
  "geometry": {"coordinates":[-82.122666,33.495828],"type":"Point"}
}