{
  "type": "Feature",
  "properties": {
    "iso:country":"US",
    "sg:address":"4910 Ivandale Cir",
    "sg:city":"Lake Park",
    "sg:classifiers":[
        {
            "category":"Professional",
            "type":"Services"
        }
    ],
    "sg:phone":"+1 229 559 4949",
    "sg:postcode":"31636",
    "sg:province":"GA",
    "wof:name":"Sabra J Blanchett",
    "wof:placetype":"venue"
},
  "geometry": {"coordinates":[-83.21440800000001,30.689804],"type":"Point"}
}