{
  "type": "Feature",
  "properties": {
    "iso:country":"US",
    "sg:address":"413 Beechwood Ln",
    "sg:city":"Woodstock",
    "sg:classifiers":[
        {
            "category":"Wholesale",
            "subcategory":"Machinery & Supplies",
            "type":"Manufacturing & Wholesale Goods"
        }
    ],
    "sg:phone":"+1 770 924 3497",
    "sg:postcode":"30189",
    "sg:province":"GA",
    "wof:name":"Rain Aid Sprinkler Servic",
    "wof:placetype":"venue"
},
  "geometry": {"coordinates":[-84.560244,34.140551],"type":"Point"}
}