{
  "type": "Feature",
  "properties": {
    "iso:country":"US",
    "sg:address":"110 Athens W Pkwy",
    "sg:city":"Athens",
    "sg:classifiers":[
        {
            "category":"Shopping",
            "subcategory":"Used Merchandise",
            "type":"Retail Goods"
        }
    ],
    "sg:phone":"+1 706 548 2008",
    "sg:postcode":"30606",
    "sg:province":"GA",
    "wof:name":"Revamp",
    "wof:placetype":"venue"
},
  "geometry": {"coordinates":[-83.446516,33.941747],"type":"Point"}
}