{
  "type": "Feature",
  "properties": {
    "addr:full":"257 State Rte 314 Fayetteville GA 30214",
    "addr:housenumber":"257",
    "addr:postcode":"30214",
    "addr:street":"State Rte 314",
    "iso:country":"US",
    "sg:address":"257 State Rte 314",
    "sg:city":"Fayetteville",
    "sg:classifiers":[
        {
            "category":"Organizations",
            "subcategory":"Religious Organization",
            "type":"Services"
        }
    ],
    "sg:phone":"+1 770 461 3403",
    "sg:postcode":"30214",
    "sg:province":"GA",
    "sg:tags":[
        "church"
    ],
    "sg:website":"www.popdove.com",
    "wof:name":"Prince Of Peace Lutheran Chr",
    "wof:placetype":"venue"
},
  "geometry": {"coordinates":[-84.449474,33.47155],"type":"Point"}
}