{
  "type": "Feature",
  "properties": {
    "iso:country":"US",
    "sg:address":"2507 Thomas Ln",
    "sg:city":"Augusta",
    "sg:classifiers":[
        {
            "category":"Recreation",
            "type":"Entertainment"
        }
    ],
    "sg:phone":"+1 706 793 9944",
    "sg:postcode":"30906",
    "sg:province":"GA",
    "sg:tags":[
        "club",
        "sport"
    ],
    "wof:name":"Private I",
    "wof:placetype":"venue"
},
  "geometry": {"coordinates":[-82.03617800000001,33.43728],"type":"Point"}
}