{
  "type": "Feature",
  "properties": {
    "addr:full":"3768 Allenhurst Dr Norcross GA 30092",
    "addr:housenumber":"3768",
    "addr:postcode":"30092",
    "addr:street":"Allenhurst Dr",
    "iso:country":"US",
    "sg:address":"3768 Allenhurst Dr",
    "sg:city":"Norcross",
    "sg:classifiers":[
        {
            "category":"Shopping",
            "subcategory":"Gifts & Souvenirs",
            "type":"Retail Goods"
        }
    ],
    "sg:phone":"+1 770 448 3221",
    "sg:postcode":"30092",
    "sg:province":"GA",
    "wof:name":"Unique Gifts Inc",
    "wof:placetype":"venue"
},
  "geometry": {"coordinates":[-84.232837,33.969669],"type":"Point"}
}