{
  "type": "Feature",
  "properties": {
    "addr:full":"2724 Summers St NW Kennesaw GA 30144",
    "addr:housenumber":"2724",
    "addr:postcode":"30144",
    "addr:street":"Summers St Nw",
    "iso:country":"US",
    "sg:address":"2724 Summers St NW",
    "sg:city":"Kennesaw",
    "sg:classifiers":[
        {
            "category":"Shopping",
            "subcategory":"Florist",
            "type":"Retail Goods"
        }
    ],
    "sg:phone":"+1 770 422 1674",
    "sg:postcode":"30144",
    "sg:province":"GA",
    "wof:name":"Kennesaw Florist",
    "wof:placetype":"venue"
},
  "geometry": {"coordinates":[-84.612396,34.017399],"type":"Point"}
}