{
  "type": "Feature",
  "properties": {
    "iso:country":"US",
    "sg:address":"865 Senoia Rd Ste E",
    "sg:city":"Tyrone",
    "sg:classifiers":[
        {
            "category":"Sports & Exercise",
            "subcategory":"Gym",
            "type":"Entertainment"
        }
    ],
    "sg:phone":"+1 770 487 2105",
    "sg:postcode":"30290",
    "sg:province":"GA",
    "wof:name":"Big Dawg Fitness",
    "wof:placetype":"venue"
},
  "geometry": {"coordinates":[-84.59687700000001,33.474392],"type":"Point"}
}