{
  "type": "Feature",
  "properties": {
    "addr:full":"225 Mallory St St Simons Island GA 31522",
    "addr:housenumber":"225",
    "addr:postcode":"31522",
    "addr:street":"Mallory St",
    "iso:country":"US",
    "sg:address":"225 Mallory St",
    "sg:city":"St Simons Island",
    "sg:classifiers":[
        {
            "category":"Shopping",
            "subcategory":"Gifts & Souvenirs",
            "type":"Retail Goods"
        }
    ],
    "sg:phone":"+1 912 638 0887",
    "sg:postcode":"31522",
    "sg:province":"GA",
    "wof:name":"Beach Bum",
    "wof:placetype":"venue"
},
  "geometry": {"coordinates":[-81.39143,31.145157],"type":"Point"}
}