{
  "type": "Feature",
  "properties": {
    "addr:full":"3655 State Rte 5 Douglasville GA 30135",
    "addr:housenumber":"3655",
    "addr:postcode":"30135",
    "addr:street":"State Rte 5",
    "iso:country":"US",
    "sg:address":"3655 State Rte 5",
    "sg:city":"Douglasville",
    "sg:classifiers":[
        {
            "category":"Health Services",
            "subcategory":"Doctor",
            "type":"Services"
        }
    ],
    "sg:phone":"+1 770 949 7753",
    "sg:postcode":"30135",
    "sg:province":"GA",
    "sg:tags":[
        "dentist"
    ],
    "wof:name":"Peachtree Periodontics Dental",
    "wof:placetype":"venue"
},
  "geometry": {"coordinates":[-84.774067,33.705796],"type":"Point"}
}