{
  "type": "Feature",
  "properties": {
    "iso:country":"US",
    "sg:address":"6621 Bay Cir",
    "sg:city":"Norcross",
    "sg:classifiers":[
        {
            "category":"Professional",
            "type":"Services"
        }
    ],
    "sg:phone":"+1 678 969 7840",
    "sg:postcode":"30071",
    "sg:province":"GA",
    "sg:tags":[
        "establishment"
    ],
    "wof:name":"Patient Accounts Bureau",
    "wof:placetype":"venue"
},
  "geometry": {"coordinates":[-84.247828,33.938004],"type":"Point"}
}