{
  "type": "Feature",
  "properties": {
    "iso:country":"US",
    "sg:address":"5505 Sable Bay Pt 2",
    "sg:city":"Atlanta",
    "sg:classifiers":[
        {
            "category":"Manufacturing",
            "subcategory":"Textiles",
            "type":"Manufacturing & Wholesale Goods"
        }
    ],
    "sg:phone":"+1 404 254 5055",
    "sg:postcode":"30349",
    "sg:province":"GA",
    "sg:tags":[
        "textiles-manufacturers"
    ],
    "sg:website":"http://www.kaphmadadesign.com/",
    "wof:name":"Kaphmada International",
    "wof:placetype":"venue"
},
  "geometry": {"coordinates":[-84.49820699999999,33.60085],"type":"Point"}
}