{
  "type": "Feature",
  "properties": {
    "addr:full":"3620 Bankhead Hwy Douglasville GA 30134",
    "addr:housenumber":"3620",
    "addr:postcode":"30134",
    "addr:street":"Bankhead Hwy",
    "iso:country":"US",
    "sg:address":"3620 Bankhead Hwy",
    "sg:city":"Douglasville",
    "sg:classifiers":[
        {
            "category":"Autos & Motor Vehicles",
            "subcategory":"Automobile Sales",
            "type":"Retail Goods"
        }
    ],
    "sg:phone":"+1 770 947 3132",
    "sg:postcode":"30134",
    "sg:province":"GA",
    "sg:tags":[
        "car",
        "dealer"
    ],
    "wof:name":"Georgia's Finest Auto",
    "wof:placetype":"venue"
},
  "geometry": {"coordinates":[-84.661462,33.793755],"type":"Point"}
}