{
  "type": "Feature",
  "properties": {
    "iso:country":"US",
    "sg:address":"1707 Washington Ave",
    "sg:city":"Atlanta",
    "sg:classifiers":[
        {
            "category":"Personal",
            "subcategory":"Beauty Salon",
            "type":"Services"
        }
    ],
    "sg:phone":"+1 404 305 9600",
    "sg:postcode":"30344",
    "sg:province":"GA",
    "sg:tags":[
        "shop"
    ],
    "wof:name":"2 N 1 Hair Design",
    "wof:placetype":"venue"
},
  "geometry": {"coordinates":[-84.443449,33.675618],"type":"Point"}
}