{
  "type": "Feature",
  "properties": {
    "addr:full":"2920 Marietta Hwy Suite 146 Canton GA 30114",
    "addr:housenumber":"2920",
    "addr:postcode":"30114",
    "addr:street":"Marietta Hwy Suite 146",
    "iso:country":"US",
    "sg:address":"2920 Marietta Hwy Suite 146",
    "sg:city":"Canton",
    "sg:classifiers":[
        {
            "category":"Health Services",
            "subcategory":"Dentist",
            "type":"Services"
        }
    ],
    "sg:phone":"+1 770 704 6987",
    "sg:postcode":"30114",
    "sg:province":"GA",
    "sg:website":"www.cherokeefamilydental.com",
    "wof:name":"Johnson Nick DMD FAGD",
    "wof:placetype":"venue"
},
  "geometry": {"coordinates":[-84.50660000000001,34.208058],"type":"Point"}
}