{
  "type": "Feature",
  "properties": {
    "iso:country":"US",
    "sg:address":"76 Allie Blount Rd",
    "sg:city":"Fleming",
    "sg:classifiers":[
        {
            "category":"Retail",
            "subcategory":"Auto Repair",
            "type":"Services"
        }
    ],
    "sg:phone":"+1 912 884 9320",
    "sg:postcode":"31309",
    "sg:province":"GA",
    "sg:tags":[
        "wrecker"
    ],
    "wof:name":"Blount's Wrecker Svc",
    "wof:placetype":"venue"
},
  "geometry": {"coordinates":[-81.424261,31.886948],"type":"Point"}
}