{
  "type": "Feature",
  "properties": {
    "addr:full":"5067 Smokey Rd Newnan GA 30263",
    "addr:housenumber":"5067",
    "addr:postcode":"30263",
    "addr:street":"Smokey Rd",
    "iso:country":"US",
    "sg:address":"5067 Smokey Rd",
    "sg:city":"Newnan",
    "sg:classifiers":[
        {
            "category":"Farming",
            "subcategory":"Livestock Farm",
            "type":"Manufacturing & Wholesale Goods"
        }
    ],
    "sg:phone":"+1 770 251 3346",
    "sg:postcode":"30263",
    "sg:province":"GA",
    "sg:tags":[
        "equine"
    ],
    "wof:name":"Haralson Farms",
    "wof:placetype":"venue"
},
  "geometry": {"coordinates":[-84.930559,33.291315],"type":"Point"}
}