{
  "type": "Feature",
  "properties": {
    "addr:full":"2424 Lakeland Rd SE Dalton GA 30721",
    "addr:housenumber":"2424",
    "addr:postcode":"30721",
    "addr:street":"Lakeland Rd Se Dalton",
    "iso:country":"US",
    "sg:address":"2424 Lakeland Rd SE",
    "sg:city":"Dalton",
    "sg:classifiers":[
        {
            "category":"Wholesale",
            "subcategory":"Home Furnishings",
            "type":"Manufacturing & Wholesale Goods"
        }
    ],
    "sg:phone":"+1 706 370 7783",
    "sg:postcode":"30721",
    "sg:province":"GA",
    "wof:name":"Premier Tape Products Inc",
    "wof:placetype":"venue"
},
  "geometry": {"coordinates":[-84.962334,34.717973],"type":"Point"}
}