{
  "type": "Feature",
  "properties": {
    "iso:country":"US",
    "sg:address":"190 Bens Branch Rd",
    "sg:city":"Newington",
    "sg:classifiers":[
        {
            "category":"Farming",
            "subcategory":"Farm",
            "type":"Manufacturing & Wholesale Goods"
        }
    ],
    "sg:phone":"+1 912 857 6190",
    "sg:postcode":"30467",
    "sg:province":"GA",
    "wof:name":"Ben's Branch Farm",
    "wof:placetype":"venue"
},
  "geometry": {"coordinates":[-81.44885499999999,32.577707],"type":"Point"}
}