{
  "type": "Feature",
  "properties": {
    "iso:country":"US",
    "sg:address":"121 Brighton Cir",
    "sg:city":"Brunswick",
    "sg:classifiers":[
        {
            "category":"Home & Garden",
            "subcategory":"Building Materials",
            "type":"Retail Goods"
        },
        {
            "category":"Building & Trades",
            "subcategory":"Construction",
            "type":"Services"
        }
    ],
    "sg:phone":"+1 912 267 9880",
    "sg:postcode":"31525",
    "sg:province":"GA",
    "sg:tags":[
        "gutter",
        "deck",
        "builder",
        "contractor",
        "downspouts",
        "siding",
        "patio"
    ],
    "wof:name":"Coastal Gutters & Siding",
    "wof:placetype":"venue"
},
  "geometry": {"coordinates":[-81.515154,31.239957],"type":"Point"}
}