{
  "type": "Feature",
  "properties": {
    "iso:country":"US",
    "sg:address":"2095 Winsburg Way",
    "sg:city":"Kennesaw",
    "sg:classifiers":[
        {
            "category":"Shopping",
            "type":"Retail Goods"
        }
    ],
    "sg:phone":"+1 770 421 0080",
    "sg:postcode":"30144",
    "sg:province":"GA",
    "sg:tags":[
        "merchandise"
    ],
    "wof:name":"Fantastic Boosters Inc",
    "wof:placetype":"venue"
},
  "geometry": {"coordinates":[-84.62081000000001,34.040077],"type":"Point"}
}