{
  "type": "Feature",
  "properties": {
    "addr:full":"111 Raven Ridge Ct Bogart GA 30622",
    "addr:housenumber":"111",
    "addr:postcode":"30622",
    "addr:street":"Raven Ridge Ct",
    "iso:country":"US",
    "sg:address":"111 Raven Ridge Ct",
    "sg:city":"Bogart",
    "sg:classifiers":[
        {
            "category":"Manufacturing",
            "subcategory":"Glass & Minerals",
            "type":"Manufacturing & Wholesale Goods"
        }
    ],
    "sg:phone":"+1 706 542 8012",
    "sg:postcode":"30622",
    "sg:province":"GA",
    "sg:tags":[
        "product",
        "nonmetallic",
        "mfg"
    ],
    "wof:name":"Seebut Creations",
    "wof:placetype":"venue"
},
  "geometry": {"coordinates":[-83.52112200000001,33.954528],"type":"Point"}
}