{
  "type": "Feature",
  "properties": {
    "iso:country":"US",
    "sg:address":"116 N Patterson St",
    "sg:city":"Valdosta",
    "sg:classifiers":[
        {
            "category":"Professional",
            "type":"Services"
        }
    ],
    "sg:phone":"+1 229 241 0007",
    "sg:postcode":"31601",
    "sg:province":"GA",
    "wof:name":"Flirt Clothing LLC",
    "wof:placetype":"venue"
},
  "geometry": {"coordinates":[-83.278991,30.831209],"type":"Point"}
}