{
  "type": "Feature",
  "properties": {
    "addr:full":"545 Telford Pl NE Atlanta GA 30342",
    "addr:housenumber":"545",
    "addr:postcode":"30342",
    "addr:street":"Telford Pl Ne",
    "iso:country":"US",
    "sg:address":"545 Telford Pl NE",
    "sg:city":"Atlanta",
    "sg:classifiers":[
        {
            "category":"Social Services",
            "subcategory":"Child Care",
            "type":"Services"
        }
    ],
    "sg:phone":"+1 404 252 6335",
    "sg:postcode":"30342",
    "sg:province":"GA",
    "sg:tags":[
        "day"
    ],
    "wof:name":"Howell Station Academy",
    "wof:placetype":"venue"
},
  "geometry": {"coordinates":[-84.35351799999999,33.897558],"type":"Point"}
}