{
  "type": "Feature",
  "properties": {
    "addr:full":"3510 Buford Hwy NE Apt U1 Atlanta GA 30329",
    "addr:housenumber":"3510",
    "addr:postcode":"30329",
    "addr:street":"Buford Hwy Ne Apt U1",
    "iso:country":"US",
    "sg:address":"3510 Buford Hwy NE Apt U1",
    "sg:city":"Atlanta",
    "sg:classifiers":[
        {
            "category":"Personal",
            "type":"Services"
        }
    ],
    "sg:phone":"+1 404 644 6473",
    "sg:postcode":"30329",
    "sg:province":"GA",
    "sg:tags":[
        "towing"
    ],
    "wof:name":"Aaa Road Rescue Inc",
    "wof:placetype":"venue"
},
  "geometry": {"coordinates":[-84.322919,33.848145],"type":"Point"}
}