{
  "type": "Feature",
  "properties": {
    "iso:country":"US",
    "sg:address":"297 Industrial Park Dr",
    "sg:city":"Lawrenceville",
    "sg:classifiers":[
        {
            "category":"Wholesale",
            "subcategory":"Construction Materials",
            "type":"Manufacturing & Wholesale Goods"
        },
        {
            "category":"Home & Garden",
            "subcategory":"Hardware",
            "type":"Retail Goods"
        }
    ],
    "sg:phone":"+1 678 377 4996",
    "sg:postcode":"30045",
    "sg:province":"GA",
    "sg:website":"www.hardwareresources.com",
    "wof:name":"Hardware Resources LLC",
    "wof:placetype":"venue"
},
  "geometry": {"coordinates":[-83.97963799999999,33.96963],"type":"Point"}
}