{
  "type": "Feature",
  "properties": {
    "iso:country":"US",
    "sg:address":"14001 Deer Trl Unin",
    "sg:city":"Alpharetta",
    "sg:classifiers":[
        {
            "category":"Shopping",
            "subcategory":"Clothing, Apparel, & Fashions",
            "type":"Retail Goods"
        }
    ],
    "sg:phone":"+1 770 845 1266",
    "sg:postcode":"30004",
    "sg:province":"GA",
    "sg:tags":[
        "shirts-custom",
        "made",
        "alterations-clothing"
    ],
    "wof:name":"Pitwear, Inc",
    "wof:placetype":"venue"
},
  "geometry": {"coordinates":[-84.25479900000001,34.100713],"type":"Point"}
}