{
  "type": "Feature",
  "properties": {
    "addr:full":"5497 Christi Dr Douglasville GA 30135",
    "addr:housenumber":"5497",
    "addr:postcode":"30135",
    "addr:street":"Christi Dr",
    "iso:country":"US",
    "sg:address":"5497 Christi Dr",
    "sg:city":"Douglasville",
    "sg:classifiers":[
        {
            "category":"Home & Garden",
            "subcategory":"Garden Supply",
            "type":"Retail Goods"
        }
    ],
    "sg:phone":"+1 770 920 9429",
    "sg:postcode":"30135",
    "sg:province":"GA",
    "sg:tags":[
        "plant"
    ],
    "wof:name":"Wilks Nursery and Garden Shop",
    "wof:placetype":"venue"
},
  "geometry": {"coordinates":[-84.755962,33.710675],"type":"Point"}
}