{
  "type": "Feature",
  "properties": {
    "addr:full":"295 Saddlebrook Ter Roswell GA 30075",
    "addr:housenumber":"295",
    "addr:postcode":"30075",
    "addr:street":"Saddlebrook Ter",
    "iso:country":"US",
    "sg:address":"295 Saddlebrook Ter",
    "sg:city":"Roswell",
    "sg:classifiers":[
        {
            "category":"Professional",
            "subcategory":"Research",
            "type":"Services"
        }
    ],
    "sg:phone":"+1 770 518 5558",
    "sg:postcode":"30075",
    "sg:province":"GA",
    "sg:tags":[
        "development",
        "marketing",
        "product"
    ],
    "wof:name":"Robustelli Sports Event Mktng",
    "wof:placetype":"venue"
},
  "geometry": {"coordinates":[-84.362785,34.065721],"type":"Point"}
}