{
  "type": "Feature",
  "properties": {
    "iso:country":"US",
    "sg:address":"524 Julius Dr",
    "sg:city":"Stone Mountain",
    "sg:classifiers":[
        {
            "category":"Banks & Credit Unions",
            "subcategory":"Financial Services",
            "type":"Services"
        }
    ],
    "sg:phone":"+1 678 528 5074",
    "sg:postcode":"30087",
    "sg:province":"GA",
    "sg:tags":[
        "real estate"
    ],
    "wof:name":"New Age Investment Group LLC",
    "wof:placetype":"venue"
},
  "geometry": {"coordinates":[-84.155429,33.791758],"type":"Point"}
}