{
  "type": "Feature",
  "properties": {
    "addr:full":"4375 Day Rd NW Conyers GA 30012",
    "addr:housenumber":"4375",
    "addr:postcode":"30012",
    "addr:street":"Day Rd Nw",
    "iso:country":"US",
    "sg:address":"4375 Day Rd NW",
    "sg:city":"Conyers",
    "sg:classifiers":[
        {
            "category":"Building & Trades",
            "subcategory":"Construction",
            "type":"Services"
        }
    ],
    "sg:phone":"+1 770 843 6458",
    "sg:postcode":"30012",
    "sg:province":"GA",
    "sg:tags":[
        "deck",
        "patio",
        "fence",
        "carpentry"
    ],
    "wof:name":"S & B Construction",
    "wof:placetype":"venue"
},
  "geometry": {"coordinates":[-84.003558,33.75955],"type":"Point"}
}