{
  "type": "Feature",
  "properties": {
    "addr:full":"607 N Veterans Pkwy Moultrie GA 31788",
    "addr:housenumber":"607",
    "addr:postcode":"31788",
    "addr:street":"N Veterans Pkwy",
    "iso:country":"US",
    "sg:address":"607 N Veterans Pkwy",
    "sg:city":"Moultrie",
    "sg:classifiers":[
        {
            "category":"Personal",
            "subcategory":"Beauty Salon",
            "type":"Services"
        }
    ],
    "sg:phone":"+1 229 985 9009",
    "sg:postcode":"31788",
    "sg:province":"GA",
    "sg:tags":[
        "shop"
    ],
    "wof:name":"Lady Nails",
    "wof:placetype":"venue"
},
  "geometry": {"coordinates":[-83.763729,31.192271],"type":"Point"}
}