{
  "type": "Feature",
  "properties": {
    "addr:full":"471 Flat Shoals Avenue SE Atlanta GA 30316",
    "addr:housenumber":"471",
    "addr:postcode":"30316",
    "addr:street":"Flat Shoals Avenue Se",
    "iso:country":"US",
    "sg:address":"471 Flat Shoals Avenue SE",
    "sg:city":"Atlanta",
    "sg:classifiers":[
        {
            "category":"Shopping",
            "subcategory":"Beauty & Cosmetics",
            "type":"Retail Goods"
        }
    ],
    "sg:phone":"+1 404 659 3157",
    "sg:postcode":"30316",
    "sg:province":"GA",
    "sg:tags":[
        "supply"
    ],
    "wof:name":"Bnc Beauty Supply",
    "wof:placetype":"venue"
},
  "geometry": {"coordinates":[-84.346296,33.741159],"type":"Point"}
}