{
  "type": "Feature",
  "properties": {
    "addr:full":"102 E Fort St Chatsworth GA 30705",
    "addr:housenumber":"102",
    "addr:postcode":"30705",
    "addr:street":"E Fort St",
    "iso:country":"US",
    "sg:address":"102 E Fort St",
    "sg:city":"Chatsworth",
    "sg:classifiers":[
        {
            "category":"Autos & Motor Vehicles",
            "subcategory":"Fuel & Gas Station",
            "type":"Retail Goods"
        },
        {
            "category":"Food & Beverages",
            "subcategory":"Groceries & Convenience Stores",
            "type":"Retail Goods"
        }
    ],
    "sg:phone":"+1 706 695 3796",
    "sg:postcode":"30705",
    "sg:province":"GA",
    "sg:website":"http://www.thepantry.com/",
    "wof:name":"Kangaroo Express",
    "wof:placetype":"venue"
},
  "geometry": {"coordinates":[-84.769515,34.766121],"type":"Point"}
}