{
  "type": "Feature",
  "properties": {
    "addr:full":"223 Mallory St St Simons Island GA 31522",
    "addr:housenumber":"223",
    "addr:postcode":"31522",
    "addr:street":"Mallory St",
    "iso:country":"US",
    "sg:address":"223 Mallory St",
    "sg:city":"St Simons Island",
    "sg:classifiers":[
        {
            "category":"Restaurant",
            "type":"Food & Drink"
        }
    ],
    "sg:phone":"+1 912 634 1217",
    "sg:postcode":"31522",
    "sg:province":"GA",
    "sg:tags":[
        "eating"
    ],
    "wof:name":"Dressner's Village Cafe",
    "wof:placetype":"venue"
},
  "geometry": {"coordinates":[-81.39143,31.145158],"type":"Point"}
}