{
  "type": "Feature",
  "properties": {
    "iso:country":"US",
    "sg:address":"Kennesaw Due West Rd",
    "sg:city":"Kennesaw",
    "sg:classifiers":[
        {
            "category":"Restaurant",
            "type":"Food & Drink"
        }
    ],
    "sg:postcode":"30156",
    "sg:province":"GA",
    "wof:name":"Cuppy's Coffee",
    "wof:placetype":"venue"
},
  "geometry": {"coordinates":[-84.628629,33.993051],"type":"Point"}
}