{
  "type": "Feature",
  "properties": {
    "addr:full":"230 Vienna Way Douglasville GA 30134",
    "addr:housenumber":"230",
    "addr:postcode":"30134",
    "addr:street":"Vienna Way",
    "iso:country":"US",
    "sg:address":"230 Vienna Way",
    "sg:city":"Douglasville",
    "sg:classifiers":[
        {
            "category":"Building & Trades",
            "subcategory":"Construction",
            "type":"Services"
        }
    ],
    "sg:phone":"+1 770 489 6930",
    "sg:postcode":"30134",
    "sg:province":"GA",
    "sg:tags":[
        "hanging",
        "contractor"
    ],
    "wof:name":"Griffith Painting",
    "wof:placetype":"venue"
},
  "geometry": {"coordinates":[-84.80425200000001,33.816656],"type":"Point"}
}