{
  "type": "Feature",
  "properties": {
    "iso:country":"US",
    "sg:address":"5302 Cleveland Hwy",
    "sg:city":"Clermont",
    "sg:classifiers":[
        {
            "category":"Banks & Credit Unions",
            "subcategory":"Bank",
            "type":"Services"
        }
    ],
    "sg:phone":"+1 770 983 2201",
    "sg:postcode":"30527",
    "sg:province":"GA",
    "wof:name":"Mountain Valley Community Bank",
    "wof:placetype":"venue"
},
  "geometry": {"coordinates":[-83.79919,34.455172],"type":"Point"}
}