{
  "type": "Feature",
  "properties": {
    "addr:full":"7406 Etowah Dr Riverdale GA 30296",
    "addr:housenumber":"7406",
    "addr:postcode":"30296",
    "addr:street":"Etowah Dr",
    "iso:country":"US",
    "sg:address":"7406 Etowah Dr",
    "sg:city":"Riverdale",
    "sg:classifiers":[
        {
            "category":"Professional",
            "subcategory":"Business Services",
            "type":"Services"
        }
    ],
    "sg:phone":"+1 770 996 0171",
    "sg:postcode":"30296",
    "sg:province":"GA",
    "sg:tags":[
        "recording",
        "studio"
    ],
    "wof:name":"Slip Knot Records",
    "wof:placetype":"venue"
},
  "geometry": {"coordinates":[-84.457184,33.554274],"type":"Point"}
}