{
  "type": "Feature",
  "properties": {
    "addr:full":"220 Tawneywood Way Alpharetta GA 30022",
    "addr:housenumber":"220",
    "addr:postcode":"30022",
    "addr:street":"Tawneywood Way",
    "iso:country":"US",
    "sg:address":"220 Tawneywood Way",
    "sg:city":"Alpharetta",
    "sg:classifiers":[
        {
            "category":"Professional",
            "subcategory":"Art Services",
            "type":"Services"
        }
    ],
    "sg:phone":"+1 770 407 1536",
    "sg:postcode":"30022",
    "sg:province":"GA",
    "sg:tags":[
        "photographer"
    ],
    "sg:website":"www.shannonholden.com",
    "wof:name":"Shannon Holden Photography",
    "wof:placetype":"venue"
},
  "geometry": {"coordinates":[-84.262502,34.031318],"type":"Point"}
}