{
  "type": "Feature",
  "properties": {
    "iso:country":"US",
    "sg:address":"695 Miami Cir NE",
    "sg:city":"Atlanta",
    "sg:classifiers":[
        {
            "category":"Shopping",
            "subcategory":"Antiques",
            "type":"Retail Goods"
        }
    ],
    "sg:phone":"+1 404 262 1541",
    "sg:postcode":"30324",
    "sg:province":"GA",
    "wof:name":"Thames Valley Antiques",
    "wof:placetype":"venue"
},
  "geometry": {"coordinates":[-84.36442700000001,33.82888],"type":"Point"}
}