{
  "type": "Feature",
  "properties": {
    "iso:country":"US",
    "sg:address":"817 E College St",
    "sg:city":"Bowdon",
    "sg:classifiers":[
        {
            "category":"Professional",
            "subcategory":"Accounting & Tax Preparation",
            "type":"Services"
        }
    ],
    "sg:phone":"+1 770 258 5576",
    "sg:postcode":"30108",
    "sg:province":"GA",
    "sg:tags":[
        "accountant"
    ],
    "wof:name":"E Paul Widener CPA",
    "wof:placetype":"venue"
},
  "geometry": {"coordinates":[-85.240521,33.548139],"type":"Point"}
}