{
  "type": "Feature",
  "properties": {
    "addr:full":"6544 River Run Rd Riverdale GA 30274",
    "addr:housenumber":"6544",
    "addr:postcode":"30274",
    "addr:street":"River Run Rd",
    "iso:country":"US",
    "sg:address":"6544 River Run Rd",
    "sg:city":"Riverdale",
    "sg:classifiers":[
        {
            "category":"Organizations",
            "subcategory":"Membership Organization",
            "type":"Services"
        }
    ],
    "sg:phone":"+1 770 997 5823",
    "sg:postcode":"30274",
    "sg:province":"GA",
    "sg:tags":[
        "club",
        "travel"
    ],
    "wof:name":"Okinawa Kenjin Kai Atlanta",
    "wof:placetype":"venue"
},
  "geometry": {"coordinates":[-84.40625199999999,33.584534],"type":"Point"}
}