{
  "type": "Feature",
  "properties": {
    "iso:country":"US",
    "sg:address":"5433 Thompson Bridge Rd",
    "sg:city":"Murrayville",
    "sg:classifiers":[
        {
            "category":"Wholesale",
            "subcategory":"Durable Goods & Equipment",
            "type":"Manufacturing & Wholesale Goods"
        }
    ],
    "sg:phone":"+1 770 534 0101",
    "sg:postcode":"30564",
    "sg:province":"GA",
    "sg:tags":[
        "exporter"
    ],
    "wof:name":"Express Lube Quick Check",
    "wof:placetype":"venue"
},
  "geometry": {"coordinates":[-83.905906,34.419022],"type":"Point"}
}