{
  "type": "Feature",
  "properties": {
    "addr:full":"1755 Lexington Hwy Elberton GA 30635",
    "addr:housenumber":"1755",
    "addr:postcode":"30635",
    "addr:street":"Lexington Hwy",
    "iso:country":"US",
    "sg:address":"1755 Lexington Hwy",
    "sg:city":"Elberton",
    "sg:classifiers":[
        {
            "category":"Mining & Drilling",
            "type":"Manufacturing & Wholesale Goods"
        }
    ],
    "sg:phone":"+1 706 283 9808",
    "sg:postcode":"30635",
    "sg:province":"GA",
    "sg:tags":[
        "stone",
        "cut",
        "dimension",
        "quarry",
        "mfg"
    ],
    "wof:name":"Triple R Granite Sales Inc",
    "wof:placetype":"venue"
},
  "geometry": {"coordinates":[-82.86545099999999,34.044485],"type":"Point"}
}