{
  "type": "Feature",
  "properties": {
    "addr:full":"6110 Cedarcrest Rd NW Acworth GA 30101",
    "addr:housenumber":"6110",
    "addr:postcode":"30101",
    "addr:street":"Cedarcrest Rd Nw",
    "iso:country":"US",
    "sg:address":"6110 Cedarcrest Rd NW",
    "sg:city":"Acworth",
    "sg:classifiers":[
        {
            "category":"Restaurant",
            "type":"Food & Drink"
        }
    ],
    "sg:menulink":"http://www.allmenus.com/ga/acworth-kennesaw/205826-la-parrilla/menu/",
    "sg:phone":"+1 770 974 4600",
    "sg:postcode":"30101",
    "sg:province":"GA",
    "sg:tags":[
        "mexican"
    ],
    "wof:name":"La Parrilla",
    "wof:placetype":"venue"
},
  "geometry": {"coordinates":[-84.726052,34.063307],"type":"Point"}
}