{
  "type": "Feature",
  "properties": {
    "iso:country":"US",
    "sg:address":"1614 Crest Lane Dr SE",
    "sg:city":"Smyrna",
    "sg:classifiers":[
        {
            "category":"Banks & Credit Unions",
            "subcategory":"Financial Services",
            "type":"Services"
        }
    ],
    "sg:phone":"+1 404 734 8856",
    "sg:postcode":"30080",
    "sg:province":"GA",
    "sg:tags":[
        "property",
        "investment"
    ],
    "wof:name":"Jfitz Inc",
    "wof:placetype":"venue"
},
  "geometry": {"coordinates":[-84.47960399999999,33.872733],"type":"Point"}
}