{
  "type": "Feature",
  "properties": {
    "addr:full":"1204 N Point Cir Alpharetta GA 30022",
    "addr:housenumber":"1204",
    "addr:postcode":"30022",
    "addr:street":"N Point Cir",
    "iso:country":"US",
    "sg:address":"1204 N Point Cir",
    "sg:city":"Alpharetta",
    "sg:classifiers":[
        {
            "category":"Shopping",
            "subcategory":"Tobacco",
            "type":"Retail Goods"
        }
    ],
    "sg:phone":"+1 770 569 0059",
    "sg:postcode":"30022",
    "sg:province":"GA",
    "sg:tags":[
        "product"
    ],
    "wof:name":"Tinder Box",
    "wof:placetype":"venue"
},
  "geometry": {"coordinates":[-84.29774500000001,34.049744],"type":"Point"}
}