{
  "type": "Feature",
  "properties": {
    "iso:country":"US",
    "sg:address":"1159 Highway 36 E",
    "sg:city":"Barnesville",
    "sg:classifiers":[
        {
            "category":"Transit Center",
            "subcategory":"Freight",
            "type":"Transportation"
        },
        {
            "category":"Freight",
            "type":"Transportation"
        }
    ],
    "sg:phone":"+1 770 358 6829",
    "sg:postcode":"30204",
    "sg:province":"GA",
    "sg:tags":[
        "local",
        "trucking-motor",
        "trucking"
    ],
    "wof:name":"Henry D Eason",
    "wof:placetype":"venue"
},
  "geometry": {"coordinates":[-84.1546,33.105516],"type":"Point"}
}