{
  "type": "Feature",
  "properties": {
    "iso:country":"US",
    "sg:address":"3650 Riverside Dr",
    "sg:city":"Macon",
    "sg:classifiers":[
        {
            "category":"Restaurant",
            "type":"Food & Drink"
        }
    ],
    "sg:menulink":"http://www.allmenus.com/ga/macon/246118-krystal/menu/",
    "sg:phone":"+1 478 405 5819",
    "sg:postcode":"31210",
    "sg:province":"GA",
    "sg:tags":[
        "burger",
        "american"
    ],
    "wof:name":"Krystal",
    "wof:placetype":"venue"
},
  "geometry": {"coordinates":[-83.68639899999999,32.89995],"type":"Point"}
}