{
  "type": "Feature",
  "properties": {
    "iso:country":"US",
    "sg:address":"651 Main St",
    "sg:city":"Thomson",
    "sg:classifiers":[
        {
            "category":"Restaurant",
            "type":"Food & Drink"
        }
    ],
    "sg:menulink":"http://www.allmenus.com/ga/thomson/174874-popeyes-chicken--biscuits/menu/",
    "sg:phone":"+1 706 554 9951",
    "sg:postcode":"30824",
    "sg:province":"GA",
    "sg:tags":[
        "american",
        "wing"
    ],
    "wof:name":"Popeyes Chicken & Biscuits",
    "wof:placetype":"venue"
},
  "geometry": {"coordinates":[-82.505352,33.482756],"type":"Point"}
}