{
  "type": "Feature",
  "properties": {
    "iso:country":"US",
    "sg:address":"8147 Flamingo Dr",
    "sg:city":"Jonesboro",
    "sg:classifiers":[
        {
            "category":"Freight",
            "type":"Transportation"
        }
    ],
    "sg:phone":"+1 770 478 2176",
    "sg:postcode":"30238",
    "sg:province":"GA",
    "sg:tags":[
        "operator",
        "trucking"
    ],
    "wof:name":"White Tail Auto Transport LLC",
    "wof:placetype":"venue"
},
  "geometry": {"coordinates":[-84.38823600000001,33.533817],"type":"Point"}
}