{
  "type": "Feature",
  "properties": {
    "iso:country":"US",
    "sg:address":"615 Blackstock Rd",
    "sg:city":"Auburn",
    "sg:classifiers":[
        {
            "category":"Building & Trades",
            "subcategory":"Cleaning & Sanitation",
            "type":"Services"
        }
    ],
    "sg:phone":"+1 770 962 2677",
    "sg:postcode":"30011",
    "sg:province":"GA",
    "sg:tags":[
        "janitor"
    ],
    "wof:name":"Haroldene's Cleaning Team Inc",
    "wof:placetype":"venue"
},
  "geometry": {"coordinates":[-83.827035,34.050027],"type":"Point"}
}