{
  "type": "Feature",
  "properties": {
    "iso:country":"US",
    "sg:address":"5212 N Tubman Rd",
    "sg:city":"Appling",
    "sg:classifiers":[
        {
            "category":"Organizations",
            "subcategory":"Religious Organization",
            "type":"Services"
        }
    ],
    "sg:phone":"+1 706 541 1781",
    "sg:postcode":"30802",
    "sg:province":"GA",
    "wof:name":"Friendship Baptist Church",
    "wof:placetype":"venue"
},
  "geometry": {"coordinates":[-82.206373,33.598767],"type":"Point"}
}