{
  "type": "Feature",
  "properties": {
    "addr:full":"3175 Medlock Bridge Rd Norcross GA 30071",
    "addr:housenumber":"3175",
    "addr:postcode":"30071",
    "addr:street":"Medlock Bridge Rd",
    "iso:country":"US",
    "sg:address":"3175 Medlock Bridge Rd",
    "sg:city":"Norcross",
    "sg:classifiers":[
        {
            "category":"Travel",
            "subcategory":"Hotels & Motels",
            "type":"Entertainment"
        }
    ],
    "sg:phone":"+1 770 729 0767",
    "sg:postcode":"30071",
    "sg:province":"GA",
    "wof:name":"Allaround Suites",
    "wof:placetype":"venue"
},
  "geometry": {"coordinates":[-84.20849200000001,33.959765],"type":"Point"}
}