{
  "type": "Feature",
  "properties": {
    "iso:country":"US",
    "sg:address":"209 Simpson St",
    "sg:city":"Mcdonough",
    "sg:classifiers":[
        {
            "category":"Manufacturing",
            "subcategory":"Building Materials",
            "type":"Manufacturing & Wholesale Goods"
        },
        {
            "category":"Home & Garden",
            "subcategory":"Furniture",
            "type":"Retail Goods"
        }
    ],
    "sg:phone":"+1 770 914 4244",
    "sg:postcode":"30253",
    "sg:province":"GA",
    "sg:tags":[
        "cabinet",
        "manufacturer"
    ],
    "wof:name":"Aidan Custom Cabinets Inc",
    "wof:placetype":"venue"
},
  "geometry": {"coordinates":[-84.15234700000001,33.442129],"type":"Point"}
}