{
  "type": "Feature",
  "properties": {
    "iso:country":"US",
    "sg:address":"4352 Ridgefield Dr",
    "sg:city":"Columbus",
    "sg:classifiers":[
        {
            "category":"Building & Trades",
            "subcategory":"Pest Control",
            "type":"Services"
        }
    ],
    "sg:phone":"+1 706 324 4356",
    "sg:postcode":"31907",
    "sg:province":"GA",
    "wof:name":"Capital Pest Control Inc",
    "wof:placetype":"venue"
},
  "geometry": {"coordinates":[-84.919467,32.437382],"type":"Point"}
}