{
  "type": "Feature",
  "properties": {
    "addr:full":"509 S Court St Calhoun GA 30701",
    "addr:housenumber":"509",
    "addr:postcode":"30701",
    "addr:street":"S Court St",
    "iso:country":"US",
    "sg:address":"509 S Court St",
    "sg:city":"Calhoun",
    "sg:classifiers":[
        {
            "category":"Utilities",
            "subcategory":"Mobile Phone",
            "type":"Services"
        }
    ],
    "sg:phone":"+1 706 625 0222",
    "sg:postcode":"30701",
    "sg:province":"GA",
    "sg:tags":[
        "communication",
        "radiotelephone"
    ],
    "wof:name":"Wireless Warehouse",
    "wof:placetype":"venue"
},
  "geometry": {"coordinates":[-84.950695,34.502117],"type":"Point"}
}