{
  "type": "Feature",
  "properties": {
    "iso:country":"US",
    "sg:address":"3150 E Highway 34",
    "sg:city":"Atlanta",
    "sg:classifiers":[
        {
            "category":"Personal",
            "subcategory":"Beauty Salon",
            "type":"Services"
        }
    ],
    "sg:phone":"+1 770 304 0696",
    "sg:postcode":"30303",
    "sg:province":"GA",
    "sg:tags":[
        "hair"
    ],
    "sg:website":"www.greatclips.com",
    "wof:name":"Great Clips For Hair",
    "wof:placetype":"venue"
},
  "geometry": {"coordinates":[-84.69926700000001,33.430397],"type":"Point"}
}