{
  "type": "Feature",
  "properties": {
    "addr:full":"402 Puckett Creek Rd Canton GA 30114",
    "addr:housenumber":"402",
    "addr:postcode":"30114",
    "addr:street":"Puckett Creek Rd",
    "iso:country":"US",
    "sg:address":"402 Puckett Creek Rd",
    "sg:city":"Canton",
    "sg:classifiers":[
        {
            "category":"Building & Trades",
            "subcategory":"Construction",
            "type":"Services"
        }
    ],
    "sg:phone":"+1 770 479 7379",
    "sg:postcode":"30114",
    "sg:province":"GA",
    "sg:tags":[
        "house"
    ],
    "wof:name":"Padgett Homes LLC",
    "wof:placetype":"venue"
},
  "geometry": {"coordinates":[-84.51544,34.280598],"type":"Point"}
}