{
  "type": "Feature",
  "properties": {
    "addr:full":"3853 Lawrenceville Hwy Ste A Tucker GA 30084",
    "addr:housenumber":"3853",
    "addr:postcode":"30084",
    "addr:street":"Lawrenceville Hwy Ste A",
    "iso:country":"US",
    "sg:address":"3853 Lawrenceville Hwy Ste A",
    "sg:city":"Tucker",
    "sg:classifiers":[
        {
            "category":"Restaurant",
            "type":"Food & Drink"
        }
    ],
    "sg:phone":"+1 770 908 8197",
    "sg:postcode":"30084",
    "sg:province":"GA",
    "sg:tags":[
        "chinese"
    ],
    "wof:name":"China Panda",
    "wof:placetype":"venue"
},
  "geometry": {"coordinates":[-84.224118,33.848995],"type":"Point"}
}