{
  "type": "Feature",
  "properties": {
    "iso:country":"US",
    "sg:address":"630 Glynn St N",
    "sg:city":"Fayetteville",
    "sg:classifiers":[
        {
            "category":"Food & Beverages",
            "subcategory":"Groceries & Convenience Stores",
            "type":"Retail Goods"
        }
    ],
    "sg:phone":"+1 770 460 8521",
    "sg:postcode":"30214",
    "sg:province":"GA",
    "wof:name":"Pit Stop Convenience Ctr",
    "wof:placetype":"venue"
},
  "geometry": {"coordinates":[-84.452364,33.460123],"type":"Point"}
}