{
  "type": "Feature",
  "properties": {
    "iso:country":"US",
    "sg:address":"26 Rookery Rd",
    "sg:city":"Savannah",
    "sg:classifiers":[
        {
            "category":"Wholesale",
            "subcategory":"Farm Supplies",
            "type":"Manufacturing & Wholesale Goods"
        }
    ],
    "sg:phone":"+1 912 598 4887",
    "sg:postcode":"31411",
    "sg:province":"GA",
    "sg:tags":[
        "raw",
        "product",
        "material"
    ],
    "wof:name":"Chadwell Cotton",
    "wof:placetype":"venue"
},
  "geometry": {"coordinates":[-81.054644,31.890371],"type":"Point"}
}