{
  "type": "Feature",
  "properties": {
    "addr:full":"4125 Falls Ridge Dr Alpharetta GA 30022",
    "addr:housenumber":"4125",
    "addr:postcode":"30022",
    "addr:street":"Falls Ridge Dr",
    "iso:country":"US",
    "sg:address":"4125 Falls Ridge Dr",
    "sg:city":"Alpharetta",
    "sg:classifiers":[
        {
            "category":"Professional",
            "subcategory":"Management & Consulting",
            "type":"Services"
        }
    ],
    "sg:phone":"+1 770 855 0085",
    "sg:postcode":"30022",
    "sg:province":"GA",
    "wof:name":"D W Management",
    "wof:placetype":"venue"
},
  "geometry": {"coordinates":[-84.239672,34.026074],"type":"Point"}
}