{
  "type": "Feature",
  "properties": {
    "iso:country":"US",
    "sg:address":"2051 Flat Shoals Rd SE",
    "sg:city":"Atlanta",
    "sg:classifiers":[
        {
            "category":"Personal",
            "subcategory":"Nail Salon",
            "type":"Services"
        }
    ],
    "sg:phone":"+1 404 243 9090",
    "sg:postcode":"30316",
    "sg:province":"GA",
    "wof:name":"Styles & Nails By Nicole",
    "wof:placetype":"venue"
},
  "geometry": {"coordinates":[-84.32052,33.724768],"type":"Point"}
}