{
  "type": "Feature",
  "properties": {
    "iso:country":"US",
    "sg:address":"433 Owens Rd SE",
    "sg:city":"Calhoun",
    "sg:classifiers":[
        {
            "category":"Wholesale",
            "subcategory":"Meat",
            "type":"Manufacturing & Wholesale Goods"
        }
    ],
    "sg:phone":"+1 706 602 8010",
    "sg:postcode":"30701",
    "sg:province":"GA",
    "sg:tags":[
        "product",
        "plant",
        "packing"
    ],
    "wof:name":"Sheriff's Meat Processing",
    "wof:placetype":"venue"
},
  "geometry": {"coordinates":[-84.87895899999999,34.472451],"type":"Point"}
}