{
  "type": "Feature",
  "properties": {
    "addr:full":"2194 W Point Ave Atlanta GA 30337",
    "addr:housenumber":"2194",
    "addr:postcode":"30337",
    "addr:street":"W Point Ave",
    "iso:country":"US",
    "sg:address":"2194 W Point Ave",
    "sg:city":"Atlanta",
    "sg:classifiers":[
        {
            "category":"Wholesale",
            "subcategory":"Construction Materials",
            "type":"Manufacturing & Wholesale Goods"
        },
        {
            "category":"Manufacturing",
            "subcategory":"Building Materials",
            "type":"Manufacturing & Wholesale Goods"
        }
    ],
    "sg:phone":"+1 404 766 3845",
    "sg:postcode":"30337",
    "sg:province":"GA",
    "sg:tags":[
        "mixed",
        "aggregate",
        "concrete-ready",
        "concrete"
    ],
    "sg:website":"http://www.usainc.net",
    "wof:name":"Allied Ready Mix",
    "wof:placetype":"venue"
},
  "geometry": {"coordinates":[-84.45944299999999,33.638123],"type":"Point"}
}