{
  "type": "Feature",
  "properties": {
    "iso:country":"US",
    "sg:address":"1085 Cobb Parkway South",
    "sg:city":"Marietta",
    "sg:classifiers":[
        {
            "category":"Building & Trades",
            "subcategory":"Cleaning & Sanitation",
            "type":"Services"
        }
    ],
    "sg:phone":"+1 770 888 8088",
    "sg:postcode":"30060",
    "sg:province":"GA",
    "sg:tags":[
        "carpet"
    ],
    "sg:website":"www.kiwiservices.com/atlanta-car...",
    "wof:name":"Kiwi Atlanta Carpet Cleaners",
    "wof:placetype":"venue"
},
  "geometry": {"coordinates":[-84.506984,33.925549],"type":"Point"}
}