{
  "type": "Feature",
  "properties": {
    "addr:full":"298 Clopton Rd Cleveland GA 30528",
    "addr:housenumber":"298",
    "addr:postcode":"30528",
    "addr:street":"Clopton Rd",
    "iso:country":"US",
    "sg:address":"298 Clopton Rd",
    "sg:city":"Cleveland",
    "sg:classifiers":[
        {
            "category":"Utilities",
            "subcategory":"Refuse",
            "type":"Services"
        }
    ],
    "sg:phone":"+1 706 219 3380",
    "sg:postcode":"30528",
    "sg:province":"GA",
    "sg:tags":[
        "garbage",
        "collection"
    ],
    "wof:name":"B K's Trash Away",
    "wof:placetype":"venue"
},
  "geometry": {"coordinates":[-83.70878999999999,34.550565],"type":"Point"}
}