{
  "type": "Feature",
  "properties": {
    "iso:country":"US",
    "sg:address":"1395 Greentree Pkwy",
    "sg:city":"Macon",
    "sg:classifiers":[
        {
            "category":"Manufacturing",
            "subcategory":"Printing",
            "type":"Manufacturing & Wholesale Goods"
        }
    ],
    "sg:phone":"+1 478 475 7848",
    "sg:postcode":"31220",
    "sg:province":"GA",
    "wof:name":"Data and Imaging Solutions",
    "wof:placetype":"venue"
},
  "geometry": {"coordinates":[-83.780466,32.872967],"type":"Point"}
}