{
  "type": "Feature",
  "properties": {
    "iso:country":"US",
    "sg:address":"300 W Patten St",
    "sg:city":"La Fayette",
    "sg:classifiers":[
        {
            "category":"Sports & Exercise",
            "subcategory":"Gym",
            "type":"Entertainment"
        }
    ],
    "sg:phone":"+1 706 638 0429",
    "sg:postcode":"30728",
    "sg:province":"GA",
    "sg:tags":[
        "fitness",
        "physical",
        "facility"
    ],
    "wof:name":"Hard Bodies Gym",
    "wof:placetype":"venue"
},
  "geometry": {"coordinates":[-85.28455099999999,34.704789],"type":"Point"}
}