{
  "type": "Feature",
  "properties": {
    "iso:country":"US",
    "sg:address":"106 Jason Dr",
    "sg:city":"Cumming",
    "sg:classifiers":[
        {
            "category":"Building & Trades",
            "subcategory":"Construction",
            "type":"Services"
        }
    ],
    "sg:phone":"+1 770 205 2633",
    "sg:postcode":"30040",
    "sg:province":"GA",
    "sg:tags":[
        "retaining",
        "wall"
    ],
    "wof:name":"Paving Solutions",
    "wof:placetype":"venue"
},
  "geometry": {"coordinates":[-84.16213999999999,34.203608],"type":"Point"}
}