{
  "type": "Feature",
  "properties": {
    "addr:full":"557 Commerce St Hawkinsville GA 31036",
    "addr:housenumber":"557",
    "addr:postcode":"31036",
    "addr:street":"Commerce St",
    "iso:country":"US",
    "sg:address":"557 Commerce St",
    "sg:city":"Hawkinsville",
    "sg:classifiers":[
        {
            "category":"Organizations",
            "subcategory":"Religious Organization",
            "type":"Services"
        }
    ],
    "sg:phone":"+1 478 892 2500",
    "sg:postcode":"31036",
    "sg:province":"GA",
    "sg:tags":[
        "church"
    ],
    "wof:name":"Church Of God By Faith",
    "wof:placetype":"venue"
},
  "geometry": {"coordinates":[-83.478274,32.284824],"type":"Point"}
}