{
  "type": "Feature",
  "properties": {
    "iso:country":"US",
    "sg:address":"2627 Dawson Rd",
    "sg:city":"Albany",
    "sg:classifiers":[
        {
            "category":"Banks & Credit Unions",
            "subcategory":"Bank",
            "type":"Services"
        }
    ],
    "sg:phone":"+1 229 888 5600",
    "sg:postcode":"31707",
    "sg:province":"GA",
    "sg:website":"www.first-nationalbank.com",
    "wof:name":"First National Bank-SOUTH Ga",
    "wof:placetype":"venue"
},
  "geometry": {"coordinates":[-84.217332,31.614557],"type":"Point"}
}