{
  "type": "Feature",
  "properties": {
    "iso:country":"US",
    "sg:address":"1745 Corporate Dr",
    "sg:city":"Norcross",
    "sg:classifiers":[
        {
            "category":"Autos & Motor Vehicles",
            "subcategory":"Auto Supplies",
            "type":"Retail Goods"
        }
    ],
    "sg:phone":"+1 770 806 1919",
    "sg:postcode":"30093",
    "sg:province":"GA",
    "sg:tags":[
        "tire"
    ],
    "wof:name":"Bridgestone Firestone North America Tire Llc",
    "wof:placetype":"venue"
},
  "geometry": {"coordinates":[-84.141454,33.937536],"type":"Point"}
}