{
  "type": "Feature",
  "properties": {
    "addr:full":"125 N Lake Dr Woodstock GA 30115",
    "addr:housenumber":"125",
    "addr:postcode":"30115",
    "addr:street":"N Lake Dr",
    "iso:country":"US",
    "sg:address":"125 N Lake Dr",
    "sg:city":"Woodstock",
    "sg:classifiers":[
        {
            "category":"Building & Trades",
            "subcategory":"Construction",
            "type":"Services"
        }
    ],
    "sg:phone":"+1 770 591 5778",
    "sg:postcode":"30115",
    "sg:province":"GA",
    "sg:tags":[
        "home",
        "builder"
    ],
    "wof:name":"Cottage's Of Bridgemill",
    "wof:placetype":"venue"
},
  "geometry": {"coordinates":[-84.367873,34.209613],"type":"Point"}
}