{
  "type": "Feature",
  "properties": {
    "iso:country":"US",
    "sg:address":"3705 Thompson Mill Rd",
    "sg:city":"Buford",
    "sg:classifiers":[
        {
            "category":"Personal",
            "subcategory":"Beauty Salon",
            "type":"Services"
        }
    ],
    "sg:phone":"+1 770 945 2541",
    "sg:postcode":"30519",
    "sg:province":"GA",
    "wof:name":"Styling Nook",
    "wof:placetype":"venue"
},
  "geometry": {"coordinates":[-83.93526300000001,34.109239],"type":"Point"}
}