{
  "type": "Feature",
  "properties": {
    "addr:full":"400 W Peachtree St NW Atlanta GA 30308",
    "addr:housenumber":"400",
    "addr:postcode":"30308",
    "addr:street":"W Peachtree St Nw",
    "iso:country":"US",
    "sg:address":"400 W Peachtree St NW",
    "sg:city":"Atlanta",
    "sg:classifiers":[
        {
            "category":"Building & Trades",
            "subcategory":"Locksmith",
            "type":"Services"
        }
    ],
    "sg:phone":"+1 866 269 3543",
    "sg:postcode":"30308",
    "sg:province":"GA",
    "sg:tags":[
        "key"
    ],
    "wof:name":"24 Hour 7 Day Emergency Locksmith",
    "wof:placetype":"venue"
},
  "geometry": {"coordinates":[-84.387635,33.765283],"type":"Point"}
}