{
  "type": "Feature",
  "properties": {
    "iso:country":"US",
    "sg:address":"1550 Oglethorpe Ave",
    "sg:city":"Athens",
    "sg:classifiers":[
        {
            "category":"Autos & Motor Vehicles",
            "subcategory":"Auto Supplies",
            "type":"Retail Goods"
        }
    ],
    "sg:phone":"+1 706 353 0858",
    "sg:postcode":"30606",
    "sg:province":"GA",
    "sg:tags":[
        "automobile",
        "parts"
    ],
    "wof:name":"Parts Plus",
    "wof:placetype":"venue"
},
  "geometry": {"coordinates":[-83.424109,33.962724],"type":"Point"}
}