{
  "type": "Feature",
  "properties": {
    "iso:country":"US",
    "sg:address":"4255 Smokecreek Pkwy Pkwyl478",
    "sg:city":"Snellville",
    "sg:classifiers":[
        {
            "category":"Manufacturing",
            "subcategory":"Petroleum Products",
            "type":"Manufacturing & Wholesale Goods"
        },
        {
            "category":"Wholesale",
            "subcategory":"Petroleum",
            "type":"Manufacturing & Wholesale Goods"
        }
    ],
    "sg:phone":"+1 770 573 4641",
    "sg:postcode":"30039",
    "sg:province":"GA",
    "sg:tags":[
        "oil",
        "refiner",
        "products-wholesale",
        "manufacturer"
    ],
    "wof:name":"Residual Workers",
    "wof:placetype":"venue"
},
  "geometry": {"coordinates":[-84.05116,33.77379],"type":"Point"}
}