{
  "type": "Feature",
  "properties": {
    "iso:country":"US",
    "sg:address":"90 W Wieuca Rd NE",
    "sg:city":"Atlanta",
    "sg:classifiers":[
        {
            "category":"Banks & Credit Unions",
            "subcategory":"Investment Brokerage",
            "type":"Services"
        }
    ],
    "sg:phone":"+1 404 255 3331",
    "sg:postcode":"30342",
    "sg:province":"GA",
    "sg:tags":[
        "investing",
        "advisory",
        "financial"
    ],
    "wof:name":"Institutional Financial Management",
    "wof:placetype":"venue"
},
  "geometry": {"coordinates":[-84.384399,33.8773],"type":"Point"}
}