{
  "type": "Feature",
  "properties": {
    "iso:country":"US",
    "sg:address":"1730 Martin Dr",
    "sg:city":"Gainesville",
    "sg:classifiers":[
        {
            "category":"Personal",
            "subcategory":"Beauty Salon",
            "type":"Services"
        }
    ],
    "sg:phone":"+1 770 287 3166",
    "sg:postcode":"30501",
    "sg:province":"GA",
    "wof:name":"Under The Cherry Moon",
    "wof:placetype":"venue"
},
  "geometry": {"coordinates":[-83.80410000000001,34.292396],"type":"Point"}
}