{
  "type": "Feature",
  "properties": {
    "iso:country":"US",
    "sg:address":"6900 Roswell Rd",
    "sg:city":"Atlanta",
    "sg:classifiers":[
        {
            "category":"Professional",
            "subcategory":"Management & Consulting",
            "type":"Services"
        }
    ],
    "sg:phone":"+1 770 392 1016",
    "sg:postcode":"30328",
    "sg:province":"GA",
    "sg:tags":[
        "consultant",
        "lighting"
    ],
    "wof:name":"Majestic Design Lighting",
    "wof:placetype":"venue"
},
  "geometry": {"coordinates":[-84.37412399999999,33.941514],"type":"Point"}
}