{
  "type": "Feature",
  "properties": {
    "addr:full":"851 Walnut St Macon GA 31201",
    "addr:housenumber":"851",
    "addr:postcode":"31201",
    "addr:street":"Walnut St",
    "iso:country":"US",
    "sg:address":"851 Walnut St",
    "sg:city":"Macon",
    "sg:classifiers":[
        {
            "category":"Professional",
            "subcategory":"Lawyer & Legal Services",
            "type":"Services"
        }
    ],
    "sg:phone":"+1 478 741 1123",
    "sg:postcode":"31201",
    "sg:province":"GA",
    "sg:tags":[
        "attorney"
    ],
    "wof:name":"Woods-Miller & Assoc",
    "wof:placetype":"venue"
},
  "geometry": {"coordinates":[-83.631334,32.842058],"type":"Point"}
}