{
  "type": "Feature",
  "properties": {
    "addr:full":"3650 Jonesboro Rd SE Atlanta GA 30354",
    "addr:housenumber":"3650",
    "addr:postcode":"30354",
    "addr:street":"Jonesboro Rd Se",
    "iso:country":"US",
    "sg:address":"3650 Jonesboro Rd SE",
    "sg:city":"Atlanta",
    "sg:classifiers":[
        {
            "category":"Banks & Credit Unions",
            "subcategory":"Bank",
            "type":"Services"
        }
    ],
    "sg:phone":"+1 404 362 2982",
    "sg:postcode":"30354",
    "sg:province":"GA",
    "wof:name":"Credit Union Car Finders",
    "wof:placetype":"venue"
},
  "geometry": {"coordinates":[-84.368257,33.655147],"type":"Point"}
}