{
  "type": "Feature",
  "properties": {
    "addr:full":"1525 Crescent Dr Augusta GA 30909",
    "addr:housenumber":"1525",
    "addr:postcode":"30909",
    "addr:street":"Crescent Dr",
    "iso:country":"US",
    "sg:address":"1525 Crescent Dr",
    "sg:city":"Augusta",
    "sg:classifiers":[
        {
            "category":"Freight",
            "type":"Transportation"
        }
    ],
    "sg:phone":"+1 706 733 1756",
    "sg:postcode":"30909",
    "sg:province":"GA",
    "sg:tags":[
        "commercial",
        "storage"
    ],
    "wof:name":"Public Storage Inc",
    "wof:placetype":"venue"
},
  "geometry": {"coordinates":[-82.086348,33.464481],"type":"Point"}
}