{
  "type": "Feature",
  "properties": {
    "addr:full":"186 Ben Burton Cir Bogart GA 30622",
    "addr:housenumber":"186",
    "addr:postcode":"30622",
    "addr:street":"Ben Burton Cir Bogart",
    "iso:country":"US",
    "sg:address":"186 Ben Burton Cir",
    "sg:city":"Bogart",
    "sg:classifiers":[
        {
            "category":"Building & Trades",
            "subcategory":"Construction",
            "type":"Services"
        },
        {
            "category":"Wholesale",
            "subcategory":"Electrical",
            "type":"Manufacturing & Wholesale Goods"
        }
    ],
    "sg:phone":"+1 706 552 3350",
    "sg:postcode":"30622",
    "sg:province":"GA",
    "sg:tags":[
        "house",
        "alarm",
        "burglar",
        "system"
    ],
    "wof:name":"Custom Home Technologies Inc",
    "wof:placetype":"venue"
},
  "geometry": {"coordinates":[-83.47553000000001,33.947342],"type":"Point"}
}