{
  "type": "Feature",
  "properties": {
    "addr:full":"752 Orchard Rd Sylvania GA 30467",
    "addr:housenumber":"752",
    "addr:postcode":"30467",
    "addr:street":"Orchard Rd",
    "iso:country":"US",
    "sg:address":"752 Orchard Rd",
    "sg:city":"Sylvania",
    "sg:classifiers":[
        {
            "category":"Farming",
            "subcategory":"Crops",
            "type":"Manufacturing & Wholesale Goods"
        }
    ],
    "sg:phone":"+1 912 857 3186",
    "sg:postcode":"30467",
    "sg:province":"GA",
    "sg:tags":[
        "grove",
        "nut",
        "tree"
    ],
    "wof:name":"Huggins Pecan Farm",
    "wof:placetype":"venue"
},
  "geometry": {"coordinates":[-81.550538,32.5732],"type":"Point"}
}