{
  "type": "Feature",
  "properties": {
    "iso:country":"US",
    "sg:address":"250 Old Corinth Rd",
    "sg:city":"Newnan",
    "sg:classifiers":[
        {
            "category":"Shopping",
            "subcategory":"Gifts & Souvenirs",
            "type":"Retail Goods"
        }
    ],
    "sg:phone":"+1 770 251 8107",
    "sg:postcode":"30263",
    "sg:province":"GA",
    "sg:tags":[
        "shop"
    ],
    "wof:name":"Potting Shed",
    "wof:placetype":"venue"
},
  "geometry": {"coordinates":[-84.831579,33.353693],"type":"Point"}
}