{
  "type": "Feature",
  "properties": {
    "addr:full":"307 Stiles Ave Savannah GA 31415",
    "addr:housenumber":"307",
    "addr:postcode":"31415",
    "addr:street":"Stiles Ave",
    "iso:country":"US",
    "sg:address":"307 Stiles Ave",
    "sg:city":"Savannah",
    "sg:classifiers":[
        {
            "category":"Personal",
            "type":"Services"
        },
        {
            "category":"Professional",
            "subcategory":"Art Services",
            "type":"Services"
        }
    ],
    "sg:phone":"+1 912 234 2426",
    "sg:postcode":"31415",
    "sg:province":"GA",
    "sg:tags":[
        "photography",
        "videography",
        "wedding"
    ],
    "wof:name":"Inner Light Gallery",
    "wof:placetype":"venue"
},
  "geometry": {"coordinates":[-81.110744,32.078571],"type":"Point"}
}