{
  "type": "Feature",
  "properties": {
    "addr:full":"43 Dove St Ball Ground GA 30107",
    "addr:housenumber":"43",
    "addr:postcode":"30107",
    "addr:street":"Dove St",
    "iso:country":"US",
    "sg:address":"43 Dove St",
    "sg:city":"Ball Ground",
    "sg:classifiers":[
        {
            "category":"Professional",
            "type":"Services"
        }
    ],
    "sg:phone":"+1 770 893 4892",
    "sg:postcode":"30107",
    "sg:province":"GA",
    "wof:name":"Tommy Blackwell",
    "wof:placetype":"venue"
},
  "geometry": {"coordinates":[-84.27928900000001,34.393986],"type":"Point"}
}