{
  "type": "Feature",
  "properties": {
    "addr:full":"4080 McGinnis Ferry Rd Alpharetta GA 30005",
    "addr:housenumber":"4080",
    "addr:postcode":"30005",
    "addr:street":"Mcginnis Ferry Rd",
    "iso:country":"US",
    "sg:address":"4080 McGinnis Ferry Rd",
    "sg:city":"Alpharetta",
    "sg:classifiers":[
        {
            "category":"Building & Trades",
            "subcategory":"Construction",
            "type":"Services"
        }
    ],
    "sg:phone":"+1 770 518 4896",
    "sg:postcode":"30005",
    "sg:province":"GA",
    "sg:tags":[
        "home",
        "builder",
        "residential"
    ],
    "wof:name":"Sharp Residential LLC",
    "wof:placetype":"venue"
},
  "geometry": {"coordinates":[-84.240014,34.101517],"type":"Point"}
}