{
  "type": "Feature",
  "properties": {
    "addr:full":"1146 My Mountain Rd Morganton GA 30560",
    "addr:housenumber":"1146",
    "addr:postcode":"30560",
    "addr:street":"My Mountain Rd",
    "iso:country":"US",
    "sg:address":"1146 My Mountain Rd",
    "sg:city":"Morganton",
    "sg:classifiers":[
        {
            "category":"Travel",
            "subcategory":"Hotels & Motels",
            "type":"Entertainment"
        }
    ],
    "sg:phone":"+1 706 374 2057",
    "sg:postcode":"30560",
    "sg:province":"GA",
    "sg:tags":[
        "chalet",
        "rental",
        "cabin"
    ],
    "wof:name":"Above The Rest Luxury Rental",
    "wof:placetype":"venue"
},
  "geometry": {"coordinates":[-84.23345,34.917506],"type":"Point"}
}