{
  "type": "Feature",
  "properties": {
    "addr:full":"5145 Buford Hwy NE Doraville GA 30340",
    "addr:housenumber":"5145",
    "addr:postcode":"30340",
    "addr:street":"Buford Hwy Ne",
    "iso:country":"US",
    "sg:address":"5145 Buford Hwy NE",
    "sg:city":"Doraville",
    "sg:classifiers":[
        {
            "category":"Shopping",
            "subcategory":"Jewelry",
            "type":"Retail Goods"
        }
    ],
    "sg:phone":"+1 770 936 8500",
    "sg:postcode":"30340",
    "sg:province":"GA",
    "wof:name":"Ruby Jewelry",
    "wof:placetype":"venue"
},
  "geometry": {"coordinates":[-84.284328,33.892678],"type":"Point"}
}