{
  "type": "Feature",
  "properties": {
    "addr:full":"4010 Macedonia Rd Powder Springs GA 30127",
    "addr:postcode":"4010;30127",
    "addr:street":"Macedonia Rd",
    "iso:country":"US",
    "sg:address":"4010 Macedonia Rd",
    "sg:city":"Powder Springs",
    "sg:classifiers":[
        {
            "category":"Organizations",
            "subcategory":"Religious Organization",
            "type":"Services"
        }
    ],
    "sg:phone":"+1 770 222 1511",
    "sg:postcode":"30127",
    "sg:province":"GA",
    "wof:name":"Lakeview Seventh Day Adventist",
    "wof:placetype":"venue"
},
  "geometry": {"coordinates":[-84.671727,33.875353],"type":"Point"}
}