{
  "type": "Feature",
  "properties": {
    "addr:full":"793 Marietta St NW Atlanta GA 30318",
    "addr:housenumber":"793",
    "addr:postcode":"30318",
    "addr:street":"Marietta St Nw",
    "iso:country":"US",
    "sg:address":"793 Marietta St NW",
    "sg:city":"Atlanta",
    "sg:classifiers":[
        {
            "category":"Professional",
            "subcategory":"Business Services",
            "type":"Services"
        }
    ],
    "sg:phone":"+1 404 532 7431",
    "sg:postcode":"30318",
    "sg:province":"GA",
    "sg:tags":[
        "labeling"
    ],
    "wof:name":"Coin Wrap",
    "wof:placetype":"venue"
},
  "geometry": {"coordinates":[-84.404917,33.773744],"type":"Point"}
}