{
  "type": "Feature",
  "properties": {
    "addr:full":"5299 Purslane Way Acworth GA 30102",
    "addr:housenumber":"5299",
    "addr:postcode":"30102",
    "addr:street":"Purslane Way",
    "iso:country":"US",
    "sg:address":"5299 Purslane Way",
    "sg:city":"Acworth",
    "sg:classifiers":[
        {
            "category":"Wholesale",
            "subcategory":"Non-durable Goods",
            "type":"Manufacturing & Wholesale Goods"
        }
    ],
    "sg:phone":"+1 770 928 2624",
    "sg:postcode":"30102",
    "sg:province":"GA",
    "sg:tags":[
        "consulting",
        "management"
    ],
    "wof:name":"Premier Advantage Inc",
    "wof:placetype":"venue"
},
  "geometry": {"coordinates":[-84.571451,34.068983],"type":"Point"}
}