{
  "type": "Feature",
  "properties": {
    "iso:country":"US",
    "sg:address":"88 Skaggs Way",
    "sg:city":"Talking Rock",
    "sg:classifiers":[
        {
            "category":"Building & Trades",
            "subcategory":"Pest Control",
            "type":"Services"
        }
    ],
    "sg:phone":"+1 706 635 1200",
    "sg:postcode":"30175",
    "sg:province":"GA",
    "wof:name":"Daryl Skaggs Pest Control",
    "wof:placetype":"venue"
},
  "geometry": {"coordinates":[-84.43767,34.547047],"type":"Point"}
}