{
  "type": "Feature",
  "properties": {
    "iso:country":"US",
    "sg:address":"901 Carroll St",
    "sg:city":"Perry",
    "sg:classifiers":[
        {
            "category":"Professional",
            "subcategory":"Accounting & Tax Preparation",
            "type":"Services"
        }
    ],
    "sg:phone":"+1 478 987 4994",
    "sg:postcode":"31069",
    "sg:province":"GA",
    "sg:tags":[
        "accountant"
    ],
    "wof:name":"Chapman & Rodgers Cpas",
    "wof:placetype":"venue"
},
  "geometry": {"coordinates":[-83.73215399999999,32.458754],"type":"Point"}
}