{
  "type": "Feature",
  "properties": {
    "addr:full":"5225 Miller Rd Columbus GA 31909",
    "addr:housenumber":"5225",
    "addr:postcode":"31909",
    "addr:street":"Miller Rd",
    "iso:country":"US",
    "sg:address":"5225 Miller Rd",
    "sg:city":"Columbus",
    "sg:classifiers":[
        {
            "category":"Wholesale",
            "subcategory":"Petroleum",
            "type":"Manufacturing & Wholesale Goods"
        }
    ],
    "sg:phone":"+1 706 561 0160",
    "sg:postcode":"31909",
    "sg:province":"GA",
    "sg:tags":[
        "bulk",
        "station"
    ],
    "wof:name":"TransMontaigne",
    "wof:placetype":"venue"
},
  "geometry": {"coordinates":[-84.912285,32.522986],"type":"Point"}
}