{
  "type": "Feature",
  "properties": {
    "iso:country":"US",
    "sg:address":"106 Stillwater Rd",
    "sg:city":"Stockbridge",
    "sg:classifiers":[
        {
            "category":"Building & Trades",
            "subcategory":"Plumbing",
            "type":"Services"
        }
    ],
    "sg:phone":"+1 770 389 5199",
    "sg:postcode":"30281",
    "sg:province":"GA",
    "sg:tags":[
        "conditioning",
        "air",
        "system",
        "contractor"
    ],
    "wof:name":"Ed Mason Svc",
    "wof:placetype":"venue"
},
  "geometry": {"coordinates":[-84.216992,33.559769],"type":"Point"}
}