{
  "type": "Feature",
  "properties": {
    "addr:full":"701 Poplar Dr Thomaston GA 30286",
    "addr:housenumber":"701",
    "addr:postcode":"30286",
    "addr:street":"Poplar Dr",
    "iso:country":"US",
    "sg:address":"701 Poplar Dr",
    "sg:city":"Thomaston",
    "sg:classifiers":[
        {
            "category":"Real Estate",
            "subcategory":"Real Estate Operator",
            "type":"Services"
        }
    ],
    "sg:phone":"+1 706 647 7114",
    "sg:postcode":"30286",
    "sg:province":"GA",
    "sg:tags":[
        "building",
        "apartment"
    ],
    "wof:name":"Wood Valley Apts",
    "wof:placetype":"venue"
},
  "geometry": {"coordinates":[-84.338838,32.896974],"type":"Point"}
}