{
  "type": "Feature",
  "properties": {
    "addr:full":"441 Level Grove Rd Cornelia GA 30531",
    "addr:housenumber":"441",
    "addr:postcode":"30531",
    "addr:street":"Level Grove Rd",
    "iso:country":"US",
    "sg:address":"441 Level Grove Rd",
    "sg:city":"Cornelia",
    "sg:classifiers":[
        {
            "category":"Restaurant",
            "type":"Food & Drink"
        }
    ],
    "sg:menulink":"http://www.allmenus.com/ga/cornelia/180701-wendys/menu/",
    "sg:phone":"+1 706 778 8685",
    "sg:postcode":"30531",
    "sg:province":"GA",
    "sg:tags":[
        "burger",
        "american",
        "soup"
    ],
    "wof:name":"Wendy's",
    "wof:placetype":"venue"
},
  "geometry": {"coordinates":[-83.533176,34.51078],"type":"Point"}
}