{
  "type": "Feature",
  "properties": {
    "iso:country":"US",
    "sg:address":"2385 N Broad St",
    "sg:city":"Commerce",
    "sg:classifiers":[
        {
            "category":"Retail",
            "subcategory":"Auto Repair",
            "type":"Services"
        }
    ],
    "sg:phone":"+1 706 335 9022",
    "sg:postcode":"30530",
    "sg:province":"GA",
    "sg:tags":[
        "transmission"
    ],
    "wof:name":"Hills Transmission Svc & Rpr",
    "wof:placetype":"venue"
},
  "geometry": {"coordinates":[-83.468335,34.207717],"type":"Point"}
}