{
  "type": "Feature",
  "properties": {
    "iso:country":"US",
    "sg:address":"2698 McAfee Rd",
    "sg:city":"Decatur",
    "sg:classifiers":[
        {
            "category":"Real Estate",
            "subcategory":"Real Estate Agent",
            "type":"Services"
        }
    ],
    "sg:phone":"+1 404 288 0700",
    "sg:postcode":"30032",
    "sg:province":"GA",
    "wof:name":"Montague Realty & Assoc Inc",
    "wof:placetype":"venue"
},
  "geometry": {"coordinates":[-84.28010500000001,33.731899],"type":"Point"}
}