{
  "type": "Feature",
  "properties": {
    "iso:country":"US",
    "sg:address":"4365 Chastain Walk NE",
    "sg:city":"Atlanta",
    "sg:classifiers":[
        {
            "category":"Home & Garden",
            "subcategory":"Home Furnishings",
            "type":"Retail Goods"
        },
        {
            "category":"Food & Beverages",
            "subcategory":"Dairy",
            "type":"Retail Goods"
        },
        {
            "category":"Home & Garden",
            "subcategory":"Carpets & Floor Coverings",
            "type":"Retail Goods"
        },
        {
            "category":"Home & Garden",
            "subcategory":"Furniture",
            "type":"Retail Goods"
        }
    ],
    "sg:phone":"+1 404 847 0788",
    "sg:postcode":"30342",
    "sg:province":"GA",
    "sg:tags":[
        "set",
        "bed",
        "futon",
        "furniture-children's",
        "bedroom",
        "mattress",
        "store"
    ],
    "wof:name":"Mattress Plus",
    "wof:placetype":"venue"
},
  "geometry": {"coordinates":[-84.382014,33.87252],"type":"Point"}
}