{
  "type": "Feature",
  "properties": {
    "iso:country":"US",
    "sg:address":"2177 Roswell Rd",
    "sg:city":"Marietta",
    "sg:classifiers":[
        {
            "category":"Shopping",
            "subcategory":"Books",
            "type":"Retail Goods"
        }
    ],
    "sg:phone":"+1 770 565 8426",
    "sg:postcode":"30062",
    "sg:province":"GA",
    "sg:tags":[
        "dealer"
    ],
    "wof:name":"Little Coupon Book",
    "wof:placetype":"venue"
},
  "geometry": {"coordinates":[-84.487623,33.971445],"type":"Point"}
}