{
  "type": "Feature",
  "properties": {
    "iso:country":"US",
    "sg:address":"2001 Old Concord Rd SE",
    "sg:city":"Smyrna",
    "sg:classifiers":[
        {
            "category":"Professional",
            "subcategory":"Management & Consulting",
            "type":"Services"
        }
    ],
    "sg:phone":"+1 770 438 1204",
    "sg:postcode":"30080",
    "sg:province":"GA",
    "sg:tags":[
        "marketing",
        "consultant"
    ],
    "wof:name":"International Mktg & Concepts",
    "wof:placetype":"venue"
},
  "geometry": {"coordinates":[-84.539867,33.90354],"type":"Point"}
}