{
  "type": "Feature",
  "properties": {
    "iso:country":"US",
    "sg:address":"831 Odessa Rd",
    "sg:city":"Jesup",
    "sg:classifiers":[
        {
            "category":"Farming",
            "subcategory":"Farm",
            "type":"Manufacturing & Wholesale Goods"
        }
    ],
    "sg:phone":"+1 912 427 7517",
    "sg:postcode":"31546",
    "sg:province":"GA",
    "wof:name":"Freddy Swenson",
    "wof:placetype":"venue"
},
  "geometry": {"coordinates":[-81.80743,31.561554],"type":"Point"}
}