{
  "type": "Feature",
  "properties": {
    "iso:country":"US",
    "sg:address":"1100 Abernathy Rd NE",
    "sg:city":"Atlanta",
    "sg:classifiers":[
        {
            "category":"Banks & Credit Unions",
            "subcategory":"Investment Brokerage",
            "type":"Services"
        }
    ],
    "sg:phone":"+1 404 266 0663",
    "sg:postcode":"30328",
    "sg:province":"GA",
    "sg:tags":[
        "advisory",
        "financial"
    ],
    "sg:website":"www.relico.com",
    "wof:name":"Reliance Trust Co",
    "wof:placetype":"venue"
},
  "geometry": {"coordinates":[-84.351319,33.933799],"type":"Point"}
}