{
  "type": "Feature",
  "properties": {
    "addr:full":"195 Turnberry Cir Fayetteville GA 30215",
    "addr:housenumber":"195",
    "addr:postcode":"30215",
    "addr:street":"Turnberry Cir",
    "iso:country":"US",
    "sg:address":"195 Turnberry Cir",
    "sg:city":"Fayetteville",
    "sg:classifiers":[
        {
            "category":"Banks & Credit Unions",
            "subcategory":"Bank",
            "type":"Services"
        }
    ],
    "sg:phone":"+1 770 460 2231",
    "sg:postcode":"30215",
    "sg:province":"GA",
    "sg:tags":[
        "loan",
        "real estate"
    ],
    "wof:name":"Equity Lending Co",
    "wof:placetype":"venue"
},
  "geometry": {"coordinates":[-84.48602700000001,33.382011],"type":"Point"}
}