{
  "type": "Feature",
  "properties": {
    "addr:full":"10 Andrew Dr Stockbridge GA 30281",
    "addr:housenumber":"10",
    "addr:postcode":"30281",
    "addr:street":"Andrew Dr",
    "iso:country":"US",
    "sg:address":"10 Andrew Dr",
    "sg:city":"Stockbridge",
    "sg:classifiers":[
        {
            "category":"Autos & Motor Vehicles",
            "subcategory":"Boat Sales",
            "type":"Retail Goods"
        }
    ],
    "sg:phone":"+1 770 474 3383",
    "sg:postcode":"30281",
    "sg:province":"GA",
    "sg:tags":[
        "equipment",
        "marine",
        "supply"
    ],
    "wof:name":"Consolidated Marine Wholesale",
    "wof:placetype":"venue"
},
  "geometry": {"coordinates":[-84.241991,33.499707],"type":"Point"}
}