{
  "type": "Feature",
  "properties": {
    "iso:country":"US",
    "sg:address":"1770 Jonesboro Rd",
    "sg:city":"McDonough",
    "sg:classifiers":[
        {
            "category":"Fast Food",
            "type":"Food & Drink"
        },
        {
            "category":"Food & Beverages",
            "subcategory":"Meat & Fish",
            "type":"Retail Goods"
        }
    ],
    "sg:phone":"+1 770 898 8305",
    "sg:postcode":"30253",
    "sg:province":"GA",
    "sg:tags":[
        "burger",
        "hot",
        "dog"
    ],
    "sg:website":"www.burgerking.com",
    "wof:name":"Burger King Restaurant",
    "wof:placetype":"venue"
},
  "geometry": {"coordinates":[-84.21779600000001,33.4646],"type":"Point"}
}