{
  "type": "Feature",
  "properties": {
    "iso:country":"US",
    "sg:address":"465 Cascade Rise Ct SW",
    "sg:city":"Atlanta",
    "sg:classifiers":[
        {
            "category":"Professional",
            "subcategory":"Management & Consulting",
            "type":"Services"
        }
    ],
    "sg:phone":"+1 404 699 2873",
    "sg:postcode":"30331",
    "sg:province":"GA",
    "sg:tags":[
        "food",
        "beverage",
        "facility",
        "consultant"
    ],
    "wof:name":"Iso-Energy",
    "wof:placetype":"venue"
},
  "geometry": {"coordinates":[-84.563435,33.725839],"type":"Point"}
}