{
  "type": "Feature",
  "properties": {
    "iso:country":"US",
    "sg:address":"1007 N Chattanooga St",
    "sg:city":"La Fayette",
    "sg:classifiers":[
        {
            "category":"Utilities",
            "subcategory":"Refuse",
            "type":"Services"
        },
        {
            "category":"Wholesale",
            "subcategory":"Scrap",
            "type":"Manufacturing & Wholesale Goods"
        }
    ],
    "sg:phone":"+1 706 638 4344",
    "sg:postcode":"30728",
    "sg:province":"GA",
    "sg:tags":[
        "recycling",
        "center",
        "system"
    ],
    "wof:name":"Ballinger's Recycling",
    "wof:placetype":"venue"
},
  "geometry": {"coordinates":[-85.29894,34.713333],"type":"Point"}
}