{
  "type": "Feature",
  "properties": {
    "iso:country":"US",
    "sg:address":"6615 Rico Rd",
    "sg:city":"Palmetto",
    "sg:classifiers":[
        {
            "category":"Government",
            "subcategory":"Fire Station",
            "type":"Public Place"
        }
    ],
    "sg:phone":"+1 770 463 4571",
    "sg:postcode":"30268",
    "sg:province":"GA",
    "sg:tags":[
        "protection"
    ],
    "wof:name":"Fire Dept- Battalion 2",
    "wof:placetype":"venue"
},
  "geometry": {"coordinates":[-84.76839200000001,33.577574],"type":"Point"}
}