{
  "type": "Feature",
  "properties": {
    "addr:full":"10 Hudson Rd Fairburn GA 30224",
    "addr:housenumber":"10",
    "addr:postcode":"30224",
    "addr:street":"Hudson Rd",
    "iso:country":"US",
    "sg:address":"10 Hudson Rd",
    "sg:city":"Fairburn",
    "sg:classifiers":[
        {
            "category":"Shopping",
            "subcategory":"Discount & Variety Stores",
            "type":"Retail Goods"
        },
        {
            "category":"Shopping",
            "subcategory":"Department Store",
            "type":"Retail Goods"
        }
    ],
    "sg:phone":"+1 770 964 7021",
    "sg:postcode":"30224",
    "sg:province":"GA",
    "sg:tags":[
        "shop"
    ],
    "wof:name":"Family Dollar Stores",
    "wof:placetype":"venue"
},
  "geometry": {"coordinates":[-84.24502,33.229737],"type":"Point"}
}