{
  "type": "Feature",
  "properties": {
    "addr:full":"5155 Rosestone Dr NW Lilburn GA 30047",
    "addr:housenumber":"5155",
    "addr:postcode":"30047",
    "addr:street":"Rosestone Dr Nw",
    "iso:country":"US",
    "sg:address":"5155 Rosestone Dr NW",
    "sg:city":"Lilburn",
    "sg:classifiers":[
        {
            "category":"Building & Trades",
            "subcategory":"Construction",
            "type":"Services"
        }
    ],
    "sg:phone":"+1 678 580 2775",
    "sg:postcode":"30047",
    "sg:province":"GA",
    "sg:tags":[
        "hanging",
        "contractor"
    ],
    "wof:name":"Lc General Painting",
    "wof:placetype":"venue"
},
  "geometry": {"coordinates":[-84.15678800000001,33.899711],"type":"Point"}
}