{
  "type": "Feature",
  "properties": {
    "iso:country":"US",
    "sg:address":"409 Arrowhead Blvd",
    "sg:city":"Jonesboro",
    "sg:classifiers":[
        {
            "category":"Professional",
            "subcategory":"Management & Consulting",
            "type":"Services"
        }
    ],
    "sg:phone":"+1 678 435 0101",
    "sg:postcode":"30236",
    "sg:province":"GA",
    "sg:tags":[
        "town",
        "city",
        "regional",
        "planner"
    ],
    "wof:name":"ARC",
    "wof:placetype":"venue"
},
  "geometry": {"coordinates":[-84.37227900000001,33.575775],"type":"Point"}
}