{
  "type": "Feature",
  "properties": {
    "addr:full":"4850 US Hwy 17 Brunswick GA 31525",
    "addr:housenumber":"4850",
    "addr:postcode":"31525",
    "addr:street":"Us Hwy 17",
    "iso:country":"US",
    "sg:address":"4850 US Hwy 17",
    "sg:city":"Brunswick",
    "sg:classifiers":[
        {
            "category":"Organizations",
            "subcategory":"Religious Organization",
            "type":"Services"
        }
    ],
    "sg:phone":"+1 912 264 2923",
    "sg:postcode":"31525",
    "sg:province":"GA",
    "wof:name":"Ministry Center",
    "wof:placetype":"venue"
},
  "geometry": {"coordinates":[-81.44466,31.28802],"type":"Point"}
}