{
  "type": "Feature",
  "properties": {
    "iso:country":"US",
    "sg:address":"3855 Willow Hollow Dr",
    "sg:city":"Douglasville",
    "sg:classifiers":[
        {
            "category":"Building & Trades",
            "subcategory":"Construction",
            "type":"Services"
        }
    ],
    "sg:phone":"+1 678 283 1066",
    "sg:postcode":"30135",
    "sg:province":"GA",
    "sg:tags":[
        "fence",
        "contractor"
    ],
    "wof:name":"Turf Care Landscaping Svc",
    "wof:placetype":"venue"
},
  "geometry": {"coordinates":[-84.71381599999999,33.700302],"type":"Point"}
}