{
  "type": "Feature",
  "properties": {
    "addr:full":"1255 Canton St Roswell GA 30075",
    "addr:housenumber":"1255",
    "addr:postcode":"30075",
    "addr:street":"Canton St",
    "iso:country":"US",
    "sg:address":"1255 Canton St",
    "sg:city":"Roswell",
    "sg:classifiers":[
        {
            "category":"Shopping",
            "subcategory":"Computers & Home Electronics",
            "type":"Retail Goods"
        }
    ],
    "sg:phone":"+1 770 993 5796",
    "sg:postcode":"30075",
    "sg:province":"GA",
    "sg:tags":[
        "software"
    ],
    "sg:website":"www.himark.com",
    "wof:name":"Hi-Mark Travel Systems",
    "wof:placetype":"venue"
},
  "geometry": {"coordinates":[-84.361294,34.031899],"type":"Point"}
}