{
  "type": "Feature",
  "properties": {
    "iso:country":"US",
    "sg:address":"12060 King Rd",
    "sg:city":"Roswell",
    "sg:classifiers":[
        {
            "category":"Professional",
            "subcategory":"Detective & Security Services",
            "type":"Services"
        }
    ],
    "sg:phone":"+1 678 449 9961",
    "sg:postcode":"30075",
    "sg:province":"GA",
    "sg:tags":[
        "information",
        "bureau"
    ],
    "wof:name":"Specialized Re Services",
    "wof:placetype":"venue"
},
  "geometry": {"coordinates":[-84.38191999999999,34.075734],"type":"Point"}
}