{
  "type": "Feature",
  "properties": {
    "addr:full":"3011 Johnson Ferry Rd Marietta GA 30062",
    "addr:housenumber":"3011",
    "addr:postcode":"30062",
    "addr:street":"Johnson Ferry Rd",
    "iso:country":"US",
    "sg:address":"3011 Johnson Ferry Rd",
    "sg:city":"Marietta",
    "sg:classifiers":[
        {
            "category":"Restaurant",
            "type":"Food & Drink"
        }
    ],
    "sg:phone":"+1 770 998 3774",
    "sg:postcode":"30062",
    "sg:province":"GA",
    "wof:name":"Mc Donald's",
    "wof:placetype":"venue"
},
  "geometry": {"coordinates":[-84.42826700000001,34.019728],"type":"Point"}
}