{
  "type": "Feature",
  "properties": {
    "iso:country":"US",
    "sg:address":"2166 W Park Ct",
    "sg:city":"Stone Mountain",
    "sg:classifiers":[
        {
            "category":"Wholesale",
            "subcategory":"Sporting Goods",
            "type":"Manufacturing & Wholesale Goods"
        }
    ],
    "sg:phone":"+1 770 498 9316",
    "sg:postcode":"30087",
    "sg:province":"GA",
    "sg:tags":[
        "representative",
        "suppl"
    ],
    "wof:name":"EKA",
    "wof:placetype":"venue"
},
  "geometry": {"coordinates":[-84.11552399999999,33.817354],"type":"Point"}
}