{
  "type": "Feature",
  "properties": {
    "addr:full":"3667 Fowler Rdg Douglasville GA 30135",
    "addr:housenumber":"3667",
    "addr:postcode":"30135",
    "addr:street":"Fowler Rdg",
    "iso:country":"US",
    "sg:address":"3667 Fowler Rdg",
    "sg:city":"Douglasville",
    "sg:classifiers":[
        {
            "category":"Real Estate",
            "subcategory":"Surveying",
            "type":"Services"
        }
    ],
    "sg:phone":"+1 770 949 7078",
    "sg:postcode":"30135",
    "sg:province":"GA",
    "sg:tags":[
        "appraiser"
    ],
    "sg:website":"http://www.rapidappraisalservice.info",
    "wof:name":"Rapid Appraisal Service",
    "wof:placetype":"venue"
},
  "geometry": {"coordinates":[-84.730014,33.703556],"type":"Point"}
}