{
  "type": "Feature",
  "properties": {
    "addr:full":"2220 Atlanta Rd SE Smyrna GA 30080",
    "addr:housenumber":"2220",
    "addr:postcode":"30080",
    "addr:street":"Atlanta Rd Se",
    "iso:country":"US",
    "sg:address":"2220 Atlanta Rd SE",
    "sg:city":"Smyrna",
    "sg:classifiers":[
        {
            "category":"Personal",
            "type":"Services"
        }
    ],
    "sg:phone":"+1 770 433 1363",
    "sg:postcode":"30080",
    "sg:province":"GA",
    "sg:tags":[
        "therapist",
        "massage"
    ],
    "wof:name":"Susan Cox",
    "wof:placetype":"venue"
},
  "geometry": {"coordinates":[-84.524035,33.901589],"type":"Point"}
}