{
  "type": "Feature",
  "properties": {
    "iso:country":"US",
    "sg:address":"3431 US Hwy 441 S",
    "sg:city":"Douglas",
    "sg:classifiers":[
        {
            "category":"Autos & Motor Vehicles",
            "subcategory":"Automobile Sales",
            "type":"Retail Goods"
        }
    ],
    "sg:phone":"+1 912 389 1876",
    "sg:postcode":"31535",
    "sg:province":"GA",
    "sg:tags":[
        "car",
        "dealer"
    ],
    "wof:name":"Skipper Auto Sales",
    "wof:placetype":"venue"
},
  "geometry": {"coordinates":[-82.850696,31.465717],"type":"Point"}
}