{
  "type": "Feature",
  "properties": {
    "iso:country":"US",
    "sg:address":"350 Moores Dr",
    "sg:city":"Dahlonega",
    "sg:classifiers":[
        {
            "category":"Social Services",
            "subcategory":"Adult Care",
            "type":"Services"
        }
    ],
    "sg:phone":"+1 706 864 3136",
    "sg:postcode":"30533",
    "sg:province":"GA",
    "sg:tags":[
        "home",
        "residential"
    ],
    "wof:name":"Southern Assisted Living",
    "wof:placetype":"venue"
},
  "geometry": {"coordinates":[-83.987067,34.540513],"type":"Point"}
}