{
  "type": "Feature",
  "properties": {
    "addr:full":"9163 Settlers Grove Rd NE Covington GA 30014",
    "addr:housenumber":"9163",
    "addr:postcode":"30014",
    "addr:street":"Settlers Grove Rd Ne",
    "iso:country":"US",
    "sg:address":"9163 Settlers Grove Rd NE",
    "sg:city":"Covington",
    "sg:classifiers":[
        {
            "category":"Organizations",
            "subcategory":"Community Association",
            "type":"Services"
        }
    ],
    "sg:phone":"+1 770 786 2176",
    "sg:postcode":"30014",
    "sg:province":"GA",
    "wof:name":"Kiwanis International Inc",
    "wof:placetype":"venue"
},
  "geometry": {"coordinates":[-83.834615,33.607263],"type":"Point"}
}