{
  "type": "Feature",
  "properties": {
    "iso:country":"US",
    "sg:address":"1515 Johnson Ferry Rd",
    "sg:city":"Marietta",
    "sg:classifiers":[
        {
            "category":"Professional",
            "subcategory":"Management & Consulting",
            "type":"Services"
        }
    ],
    "sg:phone":"+1 770 977 9106",
    "sg:postcode":"30062",
    "sg:province":"GA",
    "sg:tags":[
        "fuel"
    ],
    "wof:name":"Equitable Management Group",
    "wof:placetype":"venue"
},
  "geometry": {"coordinates":[-84.427239,33.984879],"type":"Point"}
}