{
  "type": "Feature",
  "properties": {
    "iso:country":"US",
    "sg:address":"3404 Pierce Dr NE",
    "sg:city":"Atlanta",
    "sg:classifiers":[
        {
            "category":"Real Estate",
            "subcategory":"Architect",
            "type":"Services"
        }
    ],
    "sg:phone":"+1 770 458 4113",
    "sg:postcode":"30341",
    "sg:province":"GA",
    "wof:name":"Westall Architects Inc",
    "wof:placetype":"venue"
},
  "geometry": {"coordinates":[-84.302498,33.890701],"type":"Point"}
}