{
  "type": "Feature",
  "properties": {
    "iso:country":"US",
    "sg:address":"140 State Rte 203",
    "sg:city":"Kingsland",
    "sg:classifiers":[
        {
            "category":"Social Services",
            "type":"Services"
        }
    ],
    "sg:phone":"+1 912 576 7218",
    "sg:postcode":"31516",
    "sg:province":"GA",
    "sg:tags":[
        "counselor",
        "marriage",
        "family"
    ],
    "wof:name":"Center For Family Growth",
    "wof:placetype":"venue"
},
  "geometry": {"coordinates":[-82.247666,31.300804],"type":"Point"}
}