{
  "type": "Feature",
  "properties": {
    "addr:full":"305 River Knoll Dr NW Atlanta GA 30328",
    "addr:housenumber":"305",
    "addr:postcode":"30328",
    "addr:street":"River Knoll Dr Nw",
    "iso:country":"US",
    "sg:address":"305 River Knoll Dr NW",
    "sg:city":"Atlanta",
    "sg:classifiers":[
        {
            "category":"Recreation",
            "subcategory":"Marina",
            "type":"Entertainment"
        }
    ],
    "sg:phone":"+1 678 441 9090",
    "sg:postcode":"30328",
    "sg:province":"GA",
    "sg:tags":[
        "operation"
    ],
    "wof:name":"Marina 400 Building LLC",
    "wof:placetype":"venue"
},
  "geometry": {"coordinates":[-84.39324000000001,33.94669],"type":"Point"}
}