{
  "type": "Feature",
  "properties": {
    "addr:full":"546 Rock Quarry Rd Yatesville GA 31097",
    "addr:housenumber":"546",
    "addr:postcode":"31097",
    "addr:street":"Rock Quarry Rd",
    "iso:country":"US",
    "sg:address":"546 Rock Quarry Rd",
    "sg:city":"Yatesville",
    "sg:classifiers":[
        {
            "category":"Professional",
            "subcategory":"Business Services",
            "type":"Services"
        }
    ],
    "sg:phone":"+1 706 472 3133",
    "sg:postcode":"31097",
    "sg:province":"GA",
    "wof:name":"De Enterprises",
    "wof:placetype":"venue"
},
  "geometry": {"coordinates":[-84.11721300000001,32.92289],"type":"Point"}
}