{
  "type": "Feature",
  "properties": {
    "iso:country":"US",
    "sg:address":"1810 N Ashley St",
    "sg:city":"Valdosta",
    "sg:classifiers":[
        {
            "category":"Manufacturing",
            "subcategory":"Glass & Minerals",
            "type":"Manufacturing & Wholesale Goods"
        },
        {
            "category":"Manufacturing",
            "subcategory":"Building Materials",
            "type":"Manufacturing & Wholesale Goods"
        }
    ],
    "sg:phone":"+1 229 242 6865",
    "sg:postcode":"31602",
    "sg:province":"GA",
    "sg:tags":[
        "plate",
        "window",
        "glazier",
        "glass-auto"
    ],
    "wof:name":"Enclos Corporation",
    "wof:placetype":"venue"
},
  "geometry": {"coordinates":[-83.28080199999999,30.854388],"type":"Point"}
}