{
  "type": "Feature",
  "properties": {
    "addr:full":"114 Laurel Dr Barnesville GA 30204",
    "addr:housenumber":"114",
    "addr:postcode":"30204",
    "addr:street":"Laurel Dr",
    "iso:country":"US",
    "sg:address":"114 Laurel Dr",
    "sg:city":"Barnesville",
    "sg:classifiers":[
        {
            "category":"Building & Trades",
            "subcategory":"Construction",
            "type":"Services"
        }
    ],
    "sg:phone":"+1 770 358 6733",
    "sg:postcode":"30204",
    "sg:province":"GA",
    "sg:tags":[
        "wallcoverings-installation",
        "wallpaper",
        "painting",
        "contractor"
    ],
    "wof:name":"Mike Oxford Painting",
    "wof:placetype":"venue"
},
  "geometry": {"coordinates":[-84.149052,33.037503],"type":"Point"}
}