{
  "type": "Feature",
  "properties": {
    "iso:country":"US",
    "sg:address":"3341 Thomashire Ct",
    "sg:city":"Marietta",
    "sg:classifiers":[
        {
            "category":"Professional",
            "subcategory":"Business Services",
            "type":"Services"
        }
    ],
    "sg:phone":"+1 770 321 1906",
    "sg:postcode":"30066",
    "sg:province":"GA",
    "sg:tags":[
        "packaging",
        "wholesale",
        "industrial",
        "supply",
        "equipment"
    ],
    "wof:name":"A To Z Packaging Inc",
    "wof:placetype":"venue"
},
  "geometry": {"coordinates":[-84.471908,34.030967],"type":"Point"}
}