{
  "type": "Feature",
  "properties": {
    "iso:country":"US",
    "sg:address":"400 Village Green Cir SE",
    "sg:city":"Smyrna",
    "sg:classifiers":[
        {
            "category":"Restaurant",
            "type":"Food & Drink"
        }
    ],
    "sg:phone":"+1 678 213 2640",
    "sg:postcode":"30080",
    "sg:province":"GA",
    "sg:tags":[
        "steakhouse"
    ],
    "wof:name":"Shane's Rib Shack",
    "wof:placetype":"venue"
},
  "geometry": {"coordinates":[-84.51646599999999,33.885205],"type":"Point"}
}