{
  "type": "Feature",
  "properties": {
    "iso:country":"US",
    "sg:address":"7330 Lytham Trce",
    "sg:city":"Cumming",
    "sg:classifiers":[
        {
            "category":"Wholesale",
            "subcategory":"Toys & Hobbies",
            "type":"Manufacturing & Wholesale Goods"
        }
    ],
    "sg:phone":"+1 678 624 1069",
    "sg:postcode":"30041",
    "sg:province":"GA",
    "wof:name":"Import Dynamics",
    "wof:placetype":"venue"
},
  "geometry": {"coordinates":[-84.18130600000001,34.077327],"type":"Point"}
}