{
  "type": "Feature",
  "properties": {
    "iso:country":"US",
    "sg:address":"3121 Presidential Dr",
    "sg:city":"Atlanta",
    "sg:classifiers":[
        {
            "category":"Professional",
            "subcategory":"Testing Lab",
            "type":"Services"
        }
    ],
    "sg:phone":"+1 770 454 8000",
    "sg:postcode":"30340",
    "sg:province":"GA",
    "sg:tags":[
        "analytical",
        "laboratory"
    ],
    "wof:name":"Als Laboratory Group",
    "wof:placetype":"venue"
},
  "geometry": {"coordinates":[-84.26422599999999,33.886762],"type":"Point"}
}