{
  "type": "Feature",
  "properties": {
    "addr:full":"3693 Maple Forge Ln Gainesville GA 30504",
    "addr:housenumber":"3693",
    "addr:postcode":"30504",
    "addr:street":"Maple Forge Ln",
    "iso:country":"US",
    "sg:address":"3693 Maple Forge Ln",
    "sg:city":"Gainesville",
    "sg:classifiers":[
        {
            "category":"Shopping",
            "subcategory":"Books",
            "type":"Retail Goods"
        }
    ],
    "sg:phone":"+1 770 536 0390",
    "sg:postcode":"30504",
    "sg:province":"GA",
    "wof:name":"Book Ends Here",
    "wof:placetype":"venue"
},
  "geometry": {"coordinates":[-83.877413,34.263341],"type":"Point"}
}