{
  "type": "Feature",
  "properties": {
    "iso:country":"US",
    "sg:address":"28 Court Dr",
    "sg:city":"Camilla",
    "sg:classifiers":[
        {
            "category":"Government",
            "subcategory":"Office",
            "type":"Public Place"
        }
    ],
    "sg:phone":"+1 229 336 2066",
    "sg:postcode":"31730",
    "sg:province":"GA",
    "wof:name":"Mitchell County Ext Svc Agents",
    "wof:placetype":"venue"
},
  "geometry": {"coordinates":[-84.20945,31.218759],"type":"Point"}
}