{
  "type": "Feature",
  "properties": {
    "iso:country":"US",
    "sg:address":"909 Post Way",
    "sg:city":"Americus",
    "sg:classifiers":[
        {
            "category":"Personal",
            "subcategory":"Beauty Salon",
            "type":"Services"
        }
    ],
    "sg:phone":"+1 229 924 6703",
    "sg:postcode":"31709",
    "sg:province":"GA",
    "sg:tags":[
        "shop"
    ],
    "wof:name":"Styles By Trisha",
    "wof:placetype":"venue"
},
  "geometry": {"coordinates":[-84.222543,32.06726],"type":"Point"}
}