{
  "type": "Feature",
  "properties": {
    "iso:country":"US",
    "sg:address":"4429 Blackbirch Ln",
    "sg:city":"Decatur",
    "sg:classifiers":[
        {
            "category":"Organizations",
            "subcategory":"Religious Organization",
            "type":"Services"
        }
    ],
    "sg:phone":"+1 770 981 5085",
    "sg:postcode":"30034",
    "sg:province":"GA",
    "sg:tags":[
        "place",
        "worship",
        "church"
    ],
    "wof:name":"Emmanuel Chapel Word Of Faith Inc",
    "wof:placetype":"venue"
},
  "geometry": {"coordinates":[-84.206827,33.676521],"type":"Point"}
}