{
  "type": "Feature",
  "properties": {
    "iso:country":"US",
    "sg:address":"7370 Hodgson Memorial Dr",
    "sg:city":"Savannah",
    "sg:classifiers":[
        {
            "category":"Personal",
            "subcategory":"Beauty Salon",
            "type":"Services"
        }
    ],
    "sg:phone":"+1 912 356 5080",
    "sg:postcode":"31406",
    "sg:province":"GA",
    "sg:tags":[
        "shop"
    ],
    "wof:name":"Sherry Clark",
    "wof:placetype":"venue"
},
  "geometry": {"coordinates":[-81.11315999999999,32.001728],"type":"Point"}
}