{
  "type": "Feature",
  "properties": {
    "iso:country":"US",
    "sg:address":"7700 Little Mill Rd",
    "sg:city":"Cumming",
    "sg:classifiers":[
        {
            "category":"Recreation",
            "type":"Entertainment"
        }
    ],
    "sg:phone":"+1 770 844 1838",
    "sg:postcode":"30041",
    "sg:province":"GA",
    "sg:tags":[
        "stable"
    ],
    "wof:name":"Shadowbrook Farms Inc",
    "wof:placetype":"venue"
},
  "geometry": {"coordinates":[-84.024429,34.272983],"type":"Point"}
}