{
  "type": "Feature",
  "properties": {
    "addr:full":"2826 State Rte 20 Conyers GA 30013",
    "addr:housenumber":"2826",
    "addr:postcode":"30013",
    "addr:street":"State Rte 20",
    "iso:country":"US",
    "sg:address":"2826 State Rte 20",
    "sg:city":"Conyers",
    "sg:classifiers":[
        {
            "category":"Organizations",
            "subcategory":"Religious Organization",
            "type":"Services"
        }
    ],
    "sg:phone":"+1 770 483 5379",
    "sg:postcode":"30013",
    "sg:province":"GA",
    "sg:tags":[
        "church"
    ],
    "wof:name":"Hope Baptist Church",
    "wof:placetype":"venue"
},
  "geometry": {"coordinates":[-84.01461500000001,33.614775],"type":"Point"}
}