{
  "type": "Feature",
  "properties": {
    "addr:full":"1122 E Shotwell St Bainbridge GA 39819",
    "addr:housenumber":"1122",
    "addr:postcode":"39819",
    "addr:street":"E Shotwell St",
    "iso:country":"US",
    "sg:address":"1122 E Shotwell St",
    "sg:city":"Bainbridge",
    "sg:classifiers":[
        {
            "category":"Wholesale",
            "subcategory":"Medical Equipment & Supplies",
            "type":"Manufacturing & Wholesale Goods"
        }
    ],
    "sg:phone":"+1 229 243 7996",
    "sg:postcode":"39819",
    "sg:province":"GA",
    "wof:name":"Griffins Uniforms",
    "wof:placetype":"venue"
},
  "geometry": {"coordinates":[-84.56101200000001,30.903856],"type":"Point"}
}