{
  "type": "Feature",
  "properties": {
    "iso:country":"US",
    "sg:address":"3612 Grahams Port Ln",
    "sg:city":"Snellville",
    "sg:classifiers":[
        {
            "category":"Restaurant",
            "type":"Food & Drink"
        }
    ],
    "sg:phone":"+1 770 736 1697",
    "sg:postcode":"30039",
    "sg:province":"GA",
    "sg:tags":[
        "eating"
    ],
    "wof:name":"Pizza Cafe",
    "wof:placetype":"venue"
},
  "geometry": {"coordinates":[-84.030671,33.803625],"type":"Point"}
}