{
  "type": "Feature",
  "properties": {
    "addr:full":"146 Harp Rd Thomaston GA 30286",
    "addr:housenumber":"146",
    "addr:postcode":"30286",
    "addr:street":"Harp Rd",
    "iso:country":"US",
    "sg:address":"146 Harp Rd",
    "sg:city":"Thomaston",
    "sg:classifiers":[
        {
            "category":"Organizations",
            "subcategory":"Religious Organization",
            "type":"Services"
        }
    ],
    "sg:phone":"+1 706 648 3834",
    "sg:postcode":"30286",
    "sg:province":"GA",
    "sg:tags":[
        "church"
    ],
    "wof:name":"First Free Will Baptist Church",
    "wof:placetype":"venue"
},
  "geometry": {"coordinates":[-84.333884,32.934756],"type":"Point"}
}