{
  "type": "Feature",
  "properties": {
    "addr:full":"1580 Oleander Ln SW Lilburn GA 30047",
    "addr:housenumber":"1580",
    "addr:postcode":"30047",
    "addr:street":"Oleander Ln Sw",
    "iso:country":"US",
    "sg:address":"1580 Oleander Ln SW",
    "sg:city":"Lilburn",
    "sg:classifiers":[
        {
            "category":"Professional",
            "subcategory":"Management & Consulting",
            "type":"Services"
        }
    ],
    "sg:phone":"+1 770 972 1011",
    "sg:postcode":"30047",
    "sg:province":"GA",
    "sg:tags":[
        "fuel",
        "consultant"
    ],
    "wof:name":"Tyser Management Consulting",
    "wof:placetype":"venue"
},
  "geometry": {"coordinates":[-84.091087,33.848237],"type":"Point"}
}