{
  "type": "Feature",
  "properties": {
    "iso:country":"US",
    "sg:address":"5443 Bloomfield Rd",
    "sg:city":"Macon",
    "sg:classifiers":[
        {
            "category":"Wholesale",
            "subcategory":"Durable Goods & Equipment",
            "type":"Manufacturing & Wholesale Goods"
        }
    ],
    "sg:phone":"+1 478 784 9286",
    "sg:postcode":"31206",
    "sg:province":"GA",
    "wof:name":"Rs Wholesale",
    "wof:placetype":"venue"
},
  "geometry": {"coordinates":[-83.70768099999999,32.789553],"type":"Point"}
}