{
  "type": "Feature",
  "properties": {
    "iso:country":"US",
    "sg:address":"8651 S Main St",
    "sg:city":"Helen",
    "sg:classifiers":[
        {
            "category":"Wholesale",
            "subcategory":"Groceries",
            "type":"Manufacturing & Wholesale Goods"
        }
    ],
    "sg:phone":"+1 706 878 2443",
    "sg:postcode":"30545",
    "sg:province":"GA",
    "sg:tags":[
        "confectionery",
        "candy"
    ],
    "wof:name":"Hansel & Gretel Candy Kitchen",
    "wof:placetype":"venue"
},
  "geometry": {"coordinates":[-83.721171,34.69851],"type":"Point"}
}