{
  "type": "Feature",
  "properties": {
    "addr:full":"2260 N Druid Hills Rd NE Atlanta GA 30329",
    "addr:housenumber":"2260",
    "addr:postcode":"30329",
    "addr:street":"N Druid Hills Rd Ne",
    "iso:country":"US",
    "sg:address":"2260 N Druid Hills Rd NE",
    "sg:city":"Atlanta",
    "sg:classifiers":[
        {
            "category":"Real Estate",
            "subcategory":"Real Estate Agent",
            "type":"Services"
        }
    ],
    "sg:phone":"+1 404 325 5900",
    "sg:postcode":"30329",
    "sg:province":"GA",
    "wof:name":"Houston, Phil - Re/Max Executives",
    "wof:placetype":"venue"
},
  "geometry": {"coordinates":[-84.331534,33.828689],"type":"Point"}
}