{
  "type": "Feature",
  "properties": {
    "addr:full":"2192 Campbellton Rd SW Atlanta GA 30311",
    "addr:housenumber":"2192",
    "addr:postcode":"30311",
    "addr:street":"Campbellton Rd Sw",
    "iso:country":"US",
    "sg:address":"2192 Campbellton Rd SW",
    "sg:city":"Atlanta",
    "sg:classifiers":[
        {
            "category":"Taxi",
            "type":"Transportation"
        }
    ],
    "sg:phone":"+1 404 758 2007",
    "sg:postcode":"30311",
    "sg:province":"GA",
    "wof:name":"Wilson Taxi Co",
    "wof:placetype":"venue"
},
  "geometry": {"coordinates":[-84.46164,33.705036],"type":"Point"}
}