{
  "type": "Feature",
  "properties": {
    "addr:full":"4571 Arkwright Rd Macon GA 31210",
    "addr:housenumber":"4571",
    "addr:postcode":"31210",
    "addr:street":"Arkwright Rd",
    "iso:country":"US",
    "sg:address":"4571 Arkwright Rd",
    "sg:city":"Macon",
    "sg:classifiers":[
        {
            "category":"Professional",
            "subcategory":"Engineering",
            "type":"Services"
        }
    ],
    "sg:phone":"+1 478 757 1169",
    "sg:postcode":"31210",
    "sg:province":"GA",
    "sg:tags":[
        "engineer"
    ],
    "wof:name":"Hofstadter and Associates",
    "wof:placetype":"venue"
},
  "geometry": {"coordinates":[-83.69605199999999,32.914544],"type":"Point"}
}