{
  "type": "Feature",
  "properties": {
    "iso:country":"US",
    "sg:address":"208 Modoc Dr",
    "sg:city":"Cornelia",
    "sg:classifiers":[
        {
            "category":"Building & Trades",
            "subcategory":"Construction",
            "type":"Services"
        }
    ],
    "sg:phone":"+1 706 776 3787",
    "sg:postcode":"30531",
    "sg:province":"GA",
    "sg:tags":[
        "insulation",
        "heat",
        "contractor"
    ],
    "wof:name":"R & R Insulation Svc",
    "wof:placetype":"venue"
},
  "geometry": {"coordinates":[-83.539266,34.521422],"type":"Point"}
}