{
  "type": "Feature",
  "properties": {
    "iso:country":"US",
    "sg:address":"2190 Collins Rd",
    "sg:city":"Pinehurst",
    "sg:phone":"+1 229 645 3675",
    "sg:postcode":"31070",
    "sg:province":"GA",
    "sg:tags":[
        "farm",
        "cotton"
    ],
    "wof:name":"Nancy D Matthews",
    "wof:placetype":"venue"
},
  "geometry": {"coordinates":[-83.77149,32.216356],"type":"Point"}
}