{
  "type": "Feature",
  "properties": {
    "addr:full":"960 Highland Ave Summerville GA 30747",
    "addr:housenumber":"960",
    "addr:postcode":"30747",
    "addr:street":"Highland Ave",
    "iso:country":"US",
    "sg:address":"960 Highland Ave",
    "sg:city":"Summerville",
    "sg:classifiers":[
        {
            "category":"Health Services",
            "subcategory":"Nursing And Care Facility",
            "type":"Services"
        }
    ],
    "sg:phone":"+1 706 857 4761",
    "sg:postcode":"30747",
    "sg:province":"GA",
    "sg:tags":[
        "home",
        "convalescent"
    ],
    "sg:website":"www.caremore.com",
    "wof:name":"Oakview Nursing & Rehab Ctr",
    "wof:placetype":"venue"
},
  "geometry": {"coordinates":[-85.33848999999999,34.491567],"type":"Point"}
}