{
  "type": "Feature",
  "properties": {
    "addr:full":"100 Glen Way Carrollton GA 30117",
    "addr:housenumber":"100",
    "addr:postcode":"30117",
    "addr:street":"Glen Way",
    "iso:country":"US",
    "sg:address":"100 Glen Way",
    "sg:city":"Carrollton",
    "sg:classifiers":[
        {
            "category":"Insurance",
            "subcategory":"Insurance Agent",
            "type":"Services"
        }
    ],
    "sg:phone":"+1 770 834 0015",
    "sg:postcode":"30117",
    "sg:province":"GA",
    "sg:tags":[
        "agency",
        "general"
    ],
    "wof:name":"Britt/Paulk Insurance Agency",
    "wof:placetype":"venue"
},
  "geometry": {"coordinates":[-85.09850299999999,33.593685],"type":"Point"}
}