{
  "type": "Feature",
  "properties": {
    "addr:full":"825 Lakeview Dr Commerce GA 30529",
    "addr:housenumber":"825",
    "addr:postcode":"30529",
    "addr:street":"Lakeview Dr",
    "iso:country":"US",
    "sg:address":"825 Lakeview Dr",
    "sg:city":"Commerce",
    "sg:classifiers":[
        {
            "category":"Education",
            "subcategory":"School",
            "type":"Public Place"
        }
    ],
    "sg:phone":"+1 706 335 5594",
    "sg:postcode":"30529",
    "sg:province":"GA",
    "sg:tags":[
        "middle"
    ],
    "wof:name":"Commerce Middle School",
    "wof:placetype":"venue"
},
  "geometry": {"coordinates":[-83.462433,34.193392],"type":"Point"}
}