{
  "type": "Feature",
  "properties": {
    "addr:full":"5600 Fulton Industrial Blvd SW Atlanta GA 30336",
    "addr:housenumber":"5600",
    "addr:postcode":"30336",
    "addr:street":"Fulton Industrial Blvd Sw",
    "iso:country":"US",
    "sg:address":"5600 Fulton Industrial Blvd SW",
    "sg:city":"Atlanta",
    "sg:classifiers":[
        {
            "category":"Building & Trades",
            "subcategory":"Electrical",
            "type":"Services"
        }
    ],
    "sg:phone":"+1 404 346 6862",
    "sg:postcode":"30336",
    "sg:province":"GA",
    "sg:tags":[
        "control",
        "regulator",
        "system",
        "controls"
    ],
    "wof:name":"Eq Industrial Services Inc",
    "wof:placetype":"venue"
},
  "geometry": {"coordinates":[-84.568718,33.732189],"type":"Point"}
}