{
  "type": "Feature",
  "properties": {
    "addr:full":"1050 Marietta St NW Atlanta GA 30318",
    "addr:housenumber":"1050",
    "addr:postcode":"30318",
    "addr:street":"Marietta St Nw",
    "iso:country":"US",
    "sg:address":"1050 Marietta St NW",
    "sg:city":"Atlanta",
    "sg:classifiers":[
        {
            "category":"Bakery",
            "type":"Food & Drink"
        }
    ],
    "sg:phone":"+1 404 897 9338",
    "sg:postcode":"30318",
    "sg:province":"GA",
    "sg:tags":[
        "cake",
        "pastry",
        "wedding"
    ],
    "wof:name":"Caryns Cakes",
    "wof:placetype":"venue"
},
  "geometry": {"coordinates":[-84.411715,33.77968],"type":"Point"}
}