{
  "type": "Feature",
  "properties": {
    "iso:country":"US",
    "sg:address":"2270 Jones Mountain Rd",
    "sg:city":"Talking Rock",
    "sg:classifiers":[
        {
            "category":"Professional",
            "type":"Services"
        }
    ],
    "sg:phone":"+1 706 692 9331",
    "sg:postcode":"30175",
    "sg:province":"GA",
    "wof:name":"Jackson Robinsonl",
    "wof:placetype":"venue"
},
  "geometry": {"coordinates":[-84.47012599999999,34.556608],"type":"Point"}
}