{
  "type": "Feature",
  "properties": {
    "addr:full":"171 Saint Ives Dr Savannah GA 31419",
    "addr:housenumber":"171",
    "addr:postcode":"31419",
    "addr:street":"Saint Ives Dr",
    "iso:country":"US",
    "sg:address":"171 Saint Ives Dr",
    "sg:city":"Savannah",
    "sg:classifiers":[
        {
            "category":"Professional",
            "type":"Services"
        }
    ],
    "sg:phone":"+1 912 920 5717",
    "sg:postcode":"31419",
    "sg:province":"GA",
    "sg:tags":[
        "establishment"
    ],
    "wof:name":"D Ds Unlimited",
    "wof:placetype":"venue"
},
  "geometry": {"coordinates":[-81.22678500000001,31.976095],"type":"Point"}
}