{
  "type": "Feature",
  "properties": {
    "iso:country":"US",
    "sg:address":"3291 Coachmans Way NE",
    "sg:city":"Roswell",
    "sg:classifiers":[
        {
            "category":"Professional",
            "subcategory":"Management & Consulting",
            "type":"Services"
        }
    ],
    "sg:phone":"+1 770 518 4874",
    "sg:postcode":"30075",
    "sg:province":"GA",
    "sg:tags":[
        "logistics"
    ],
    "wof:name":"Jmc Consulting Company Inc",
    "wof:placetype":"venue"
},
  "geometry": {"coordinates":[-84.41070499999999,34.031326],"type":"Point"}
}