{
  "type": "Feature",
  "properties": {
    "iso:country":"US",
    "sg:address":"1000 Corporate Center Dr Ste 100",
    "sg:city":"Morrow",
    "sg:classifiers":[
        {
            "category":"Shopping",
            "subcategory":"Optical Goods",
            "type":"Retail Goods"
        },
        {
            "category":"Health Services",
            "subcategory":"Optometrist",
            "type":"Services"
        },
        {
            "category":"Health Services",
            "subcategory":"Doctor",
            "type":"Services"
        },
        {
            "category":"Shopping",
            "subcategory":"Optician",
            "type":"Retail Goods"
        },
        {
            "category":"Health Services",
            "subcategory":"Clinic",
            "type":"Services"
        }
    ],
    "sg:phone":"+1 770 968 8888",
    "sg:postcode":"30260",
    "sg:province":"GA",
    "sg:tags":[
        "eyeglass",
        "physician",
        "medical",
        "eyewear",
        "ophthalmologist",
        "surgeon"
    ],
    "sg:website":"http://www.claytoneyecenter.com",
    "wof:name":"Clayton Eye Center Optical",
    "wof:placetype":"venue"
},
  "geometry": {"coordinates":[-84.33229799999999,33.570202],"type":"Point"}
}