{
  "type": "Feature",
  "properties": {
    "addr:full":"213 Radium Springs Rd Albany GA 31705",
    "addr:housenumber":"213",
    "addr:postcode":"31705",
    "addr:street":"Radium Springs Rd",
    "iso:country":"US",
    "sg:address":"213 Radium Springs Rd",
    "sg:city":"Albany",
    "sg:classifiers":[
        {
            "category":"Autos & Motor Vehicles",
            "subcategory":"Auto Supplies",
            "type":"Retail Goods"
        }
    ],
    "sg:phone":"+1 229 438 5248",
    "sg:postcode":"31705",
    "sg:province":"GA",
    "sg:tags":[
        "tire"
    ],
    "wof:name":"Performance Motor Sports",
    "wof:placetype":"venue"
},
  "geometry": {"coordinates":[-84.142284,31.574741],"type":"Point"}
}