{
  "type": "Feature",
  "properties": {
    "addr:full":"1753 Twin Brooks Dr Marietta GA 30067",
    "addr:housenumber":"1753",
    "addr:postcode":"30067",
    "addr:street":"Twin Brooks Dr",
    "iso:country":"US",
    "sg:address":"1753 Twin Brooks Dr",
    "sg:city":"Marietta",
    "sg:classifiers":[
        {
            "category":"Professional",
            "type":"Services"
        }
    ],
    "sg:phone":"+1 678 290 1842",
    "sg:postcode":"30067",
    "sg:province":"GA",
    "wof:name":"Rehab Works of Texas Inc",
    "wof:placetype":"venue"
},
  "geometry": {"coordinates":[-84.50321700000001,33.93712],"type":"Point"}
}