{
  "type": "Feature",
  "properties": {
    "addr:full":"217 Crystal Ct Hampton GA 30228",
    "addr:housenumber":"217",
    "addr:postcode":"30228",
    "addr:street":"Crystal Ct",
    "iso:country":"US",
    "sg:address":"217 Crystal Ct",
    "sg:city":"Hampton",
    "sg:classifiers":[
        {
            "category":"Manufacturing",
            "subcategory":"Glass & Minerals",
            "type":"Manufacturing & Wholesale Goods"
        }
    ],
    "sg:phone":"+1 770 946 3430",
    "sg:postcode":"30228",
    "sg:province":"GA",
    "sg:tags":[
        "glass-wholesale",
        "plate",
        "window",
        "glass-auto",
        "manufacturer"
    ],
    "sg:website":"http://www.econoglass.net",
    "wof:name":"Econo Glass",
    "wof:placetype":"venue"
},
  "geometry": {"coordinates":[-84.271564,33.38804],"type":"Point"}
}