{
  "type": "Feature",
  "properties": {
    "addr:full":"3340 Peachtree Road NE Suite 1600 Atlanta GA 30326",
    "addr:housenumber":"3340",
    "addr:postcode":"30326",
    "addr:street":"Peachtree Road Ne Suite 1600",
    "iso:country":"US",
    "sg:address":"3340 Peachtree Road NE Suite 1600",
    "sg:city":"Atlanta",
    "sg:classifiers":[
        {
            "category":"Shopping",
            "subcategory":"Stationery & Office Supplies",
            "type":"Retail Goods"
        },
        {
            "category":"Building & Trades",
            "subcategory":"Locksmith",
            "type":"Services"
        }
    ],
    "sg:phone":"+1 404 467 8833",
    "sg:postcode":"30326",
    "sg:province":"GA",
    "sg:tags":[
        "equipment",
        "key"
    ],
    "wof:name":"Touch Wood Associates",
    "wof:placetype":"venue"
},
  "geometry": {"coordinates":[-84.368711,33.845419],"type":"Point"}
}