{
  "type": "Feature",
  "properties": {
    "addr:full":"2853 Henderson Mill Rd Atlanta GA 30341",
    "addr:housenumber":"2853",
    "addr:postcode":"30341",
    "addr:street":"Henderson Mill Rd",
    "iso:country":"US",
    "sg:address":"2853 Henderson Mill Rd",
    "sg:city":"Atlanta",
    "sg:classifiers":[
        {
            "category":"Professional",
            "subcategory":"Business Services",
            "type":"Services"
        }
    ],
    "sg:phone":"+1 770 723 7701",
    "sg:postcode":"30341",
    "sg:province":"GA",
    "sg:tags":[
        "export",
        "representative"
    ],
    "wof:name":"Chihade International Inc",
    "wof:placetype":"venue"
},
  "geometry": {"coordinates":[-84.25057,33.868676],"type":"Point"}
}