{
  "type": "Feature",
  "properties": {
    "iso:country":"US",
    "sg:address":"135 W Main St",
    "sg:city":"Hoboken",
    "sg:classifiers":[
        {
            "category":"Shopping",
            "subcategory":"Used Merchandise",
            "type":"Retail Goods"
        }
    ],
    "sg:phone":"+1 912 458 2488",
    "sg:postcode":"31542",
    "sg:province":"GA",
    "sg:tags":[
        "antique"
    ],
    "wof:name":"Anna's Antiques",
    "wof:placetype":"venue"
},
  "geometry": {"coordinates":[-82.12555500000001,31.181219],"type":"Point"}
}