{
  "type": "Feature",
  "properties": {
    "addr:full":"166 Cherryfield Ln Savannah GA 31419",
    "addr:housenumber":"166",
    "addr:postcode":"31419",
    "addr:street":"Cherryfield Ln",
    "iso:country":"US",
    "sg:address":"166 Cherryfield Ln",
    "sg:city":"Savannah",
    "sg:classifiers":[
        {
            "category":"Education",
            "subcategory":"Vocational School",
            "type":"Public Place"
        }
    ],
    "sg:phone":"+1 912 927 3658",
    "sg:postcode":"31419",
    "sg:province":"GA",
    "sg:tags":[
        "technical",
        "industrial",
        "business",
        "trade"
    ],
    "wof:name":"Global Tactical Training Group Inc",
    "wof:placetype":"venue"
},
  "geometry": {"coordinates":[-81.239216,31.970342],"type":"Point"}
}