{
  "type": "Feature",
  "properties": {
    "iso:country":"US",
    "sg:address":"1778 2nd St",
    "sg:city":"Macon",
    "sg:classifiers":[
        {
            "category":"Organizations",
            "subcategory":"Religious Organization",
            "type":"Services"
        }
    ],
    "sg:phone":"+1 478 741 2007",
    "sg:postcode":"31201",
    "sg:province":"GA",
    "wof:name":"Pathway To Hope Ministries",
    "wof:placetype":"venue"
},
  "geometry": {"coordinates":[-83.641369,32.821544],"type":"Point"}
}