{
  "type": "Feature",
  "properties": {
    "addr:full":"1322 Ellis St Augusta GA 30901",
    "addr:housenumber":"1322",
    "addr:postcode":"30901",
    "addr:street":"Ellis St",
    "iso:country":"US",
    "sg:address":"1322 Ellis St",
    "sg:city":"Augusta",
    "sg:classifiers":[
        {
            "category":"Social Services",
            "type":"Services"
        }
    ],
    "sg:phone":"+1 706 724 8481",
    "sg:postcode":"30901",
    "sg:province":"GA",
    "sg:tags":[
        "organization",
        "welfare"
    ],
    "wof:name":"American Red Cross",
    "wof:placetype":"venue"
},
  "geometry": {"coordinates":[-81.978053,33.478296],"type":"Point"}
}