{
  "type": "Feature",
  "properties": {
    "iso:country":"US",
    "sg:address":"1265 Minhinette Dr Ste 150",
    "sg:city":"Roswell",
    "sg:classifiers":[
        {
            "category":"Professional",
            "subcategory":"Lawyer & Legal Services",
            "type":"Services"
        }
    ],
    "sg:phone":"+1 678 461 5952",
    "sg:postcode":"30075",
    "sg:province":"GA",
    "wof:name":"Ross Gelfand Attorney At Law",
    "wof:placetype":"venue"
},
  "geometry": {"coordinates":[-84.358597,34.033401],"type":"Point"}
}