{
  "type": "Feature",
  "properties": {
    "addr:full":"137 Old Social Cir Social Circle GA 30025",
    "addr:housenumber":"137",
    "addr:postcode":"30025",
    "addr:street":"Old Social Cir;Circle",
    "iso:country":"US",
    "sg:address":"137 Old Social Cir",
    "sg:city":"Social Circle",
    "sg:classifiers":[
        {
            "category":"Professional",
            "subcategory":"Lawyer & Legal Services",
            "type":"Services"
        }
    ],
    "sg:phone":"+1 770 464 3330",
    "sg:postcode":"30025",
    "sg:province":"GA",
    "sg:tags":[
        "attorney"
    ],
    "wof:name":"Rebecca P Dally",
    "wof:placetype":"venue"
},
  "geometry": {"coordinates":[-83.717777,33.607623],"type":"Point"}
}