{
  "type": "Feature",
  "properties": {
    "addr:full":"1492 Liberty Hill Church Rd Hartwell GA 30643",
    "addr:housenumber":"1492",
    "addr:postcode":"30643",
    "addr:street":"Liberty Hill Church Rd",
    "iso:country":"US",
    "sg:address":"1492 Liberty Hill Church Rd",
    "sg:city":"Hartwell",
    "sg:classifiers":[
        {
            "category":"Retail",
            "subcategory":"Auto Repair",
            "type":"Services"
        },
        {
            "category":"Manufacturing",
            "subcategory":"Motor Vehicles & Parts",
            "type":"Manufacturing & Wholesale Goods"
        }
    ],
    "sg:phone":"+1 706 376 9807",
    "sg:postcode":"30643",
    "sg:province":"GA",
    "sg:tags":[
        "body",
        "automobile",
        "customizing",
        "mfg"
    ],
    "wof:name":"Skelton Frame & Body",
    "wof:placetype":"venue"
},
  "geometry": {"coordinates":[-82.895607,34.324427],"type":"Point"}
}