{
  "type": "Feature",
  "properties": {
    "iso:country":"US",
    "sg:address":"2627 Albion Farm Way",
    "sg:city":"Duluth",
    "sg:classifiers":[
        {
            "category":"Manufacturing",
            "subcategory":"Signs",
            "type":"Manufacturing & Wholesale Goods"
        }
    ],
    "sg:phone":"+1 770 418 0250",
    "sg:postcode":"30097",
    "sg:province":"GA",
    "sg:tags":[
        "security",
        "retail"
    ],
    "wof:name":"C G S",
    "wof:placetype":"venue"
},
  "geometry": {"coordinates":[-84.14572200000001,34.019808],"type":"Point"}
}