{
  "type": "Feature",
  "properties": {
    "iso:country":"US",
    "sg:address":"941 Veterans Pkwy",
    "sg:city":"Columbus",
    "sg:classifiers":[
        {
            "category":"Restaurant",
            "type":"Food & Drink"
        }
    ],
    "sg:menulink":"http://www.allmenus.com/ga/columbus/94260-ruth-anns-restaurant/menu/",
    "sg:phone":"+1 706 221 2154",
    "sg:postcode":"31901",
    "sg:province":"GA",
    "sg:tags":[
        "american"
    ],
    "wof:name":"Ruth Ann's Restaurant",
    "wof:placetype":"venue"
},
  "geometry": {"coordinates":[-84.987588,32.463648],"type":"Point"}
}