{
  "type": "Feature",
  "properties": {
    "addr:full":"473 Harrell Mill Rd Climax GA 39834",
    "addr:housenumber":"473",
    "addr:postcode":"39834",
    "addr:street":"Harrell Mill Rd",
    "iso:country":"US",
    "sg:address":"473 Harrell Mill Rd",
    "sg:city":"Climax",
    "sg:classifiers":[
        {
            "category":"Real Estate",
            "subcategory":"Real Estate Operator",
            "type":"Services"
        }
    ],
    "sg:phone":"+1 229 246 5388",
    "sg:postcode":"39834",
    "sg:province":"GA",
    "sg:tags":[
        "property",
        "lessor"
    ],
    "wof:name":"Better Cork Farm",
    "wof:placetype":"venue"
},
  "geometry": {"coordinates":[-84.43325400000001,30.842911],"type":"Point"}
}