{
  "type": "Feature",
  "properties": {
    "iso:country":"US",
    "sg:address":"130 W Wieuca Rd NE",
    "sg:city":"Atlanta",
    "sg:classifiers":[
        {
            "category":"Banks & Credit Unions",
            "subcategory":"Investment Brokerage",
            "type":"Services"
        },
        {
            "category":"Professional",
            "subcategory":"Management & Consulting",
            "type":"Services"
        }
    ],
    "sg:phone":"+1 404 843 3331",
    "sg:postcode":"30342",
    "sg:province":"GA",
    "sg:tags":[
        "consultant",
        "planning",
        "financial"
    ],
    "wof:name":"David L Dollar CPA",
    "wof:placetype":"venue"
},
  "geometry": {"coordinates":[-84.383698,33.877582],"type":"Point"}
}