{
  "type": "Feature",
  "properties": {
    "addr:full":"2524 Archwood Dr Albany GA 31707",
    "addr:housenumber":"2524",
    "addr:postcode":"31707",
    "addr:street":"Archwood Dr",
    "iso:country":"US",
    "sg:address":"2524 Archwood Dr",
    "sg:city":"Albany",
    "sg:classifiers":[
        {
            "category":"Bakery",
            "type":"Food & Drink"
        }
    ],
    "sg:menulink":"http://www.allmenus.com/ga/west-dougherty/100007-golden-corral/menu/",
    "sg:phone":"+1 229 446 0101",
    "sg:postcode":"31707",
    "sg:province":"GA",
    "sg:tags":[
        "american",
        "pastry"
    ],
    "wof:name":"Golden Corral",
    "wof:placetype":"venue"
},
  "geometry": {"coordinates":[-84.21289899999999,31.614421],"type":"Point"}
}