{
  "type": "Feature",
  "properties": {
    "iso:country":"US",
    "sg:address":"124 Atlanta St",
    "sg:city":"McDonough",
    "sg:classifiers":[
        {
            "category":"Professional",
            "subcategory":"Lawyer & Legal Services",
            "type":"Services"
        }
    ],
    "sg:phone":"+1 678 583 5332",
    "sg:postcode":"30253",
    "sg:province":"GA",
    "sg:website":"www.bettisandhoward.com",
    "wof:name":"Bettis & Howard",
    "wof:placetype":"venue"
},
  "geometry": {"coordinates":[-84.14735400000001,33.451155],"type":"Point"}
}