{
  "type": "Feature",
  "properties": {
    "iso:country":"US",
    "sg:address":"3833 Buford Dr",
    "sg:city":"Buford",
    "sg:classifiers":[
        {
            "category":"Autos & Motor Vehicles",
            "subcategory":"Fuel & Gas Station",
            "type":"Retail Goods"
        }
    ],
    "sg:phone":"+1 770 932 1022",
    "sg:postcode":"30519",
    "sg:province":"GA",
    "sg:website":"www.chevron.com",
    "wof:name":"Chevron Food Mart",
    "wof:placetype":"venue"
},
  "geometry": {"coordinates":[-83.991212,34.085876],"type":"Point"}
}