{
  "type": "Feature",
  "properties": {
    "iso:country":"US",
    "sg:address":"165 Courtland St NE",
    "sg:city":"Atlanta",
    "sg:classifiers":[
        {
            "category":"Local Transit",
            "type":"Transportation"
        }
    ],
    "sg:phone":"+1 404 589 8071",
    "sg:postcode":"30303",
    "sg:province":"GA",
    "sg:tags":[
        "limousine"
    ],
    "wof:name":"International Limousine",
    "wof:placetype":"venue"
},
  "geometry": {"coordinates":[-84.38413,33.759179],"type":"Point"}
}