{
  "type": "Feature",
  "properties": {
    "iso:country":"US",
    "sg:address":"103 Maple Dr",
    "sg:city":"Augusta",
    "sg:classifiers":[
        {
            "category":"Personal",
            "type":"Services"
        }
    ],
    "sg:phone":"+1 706 922 8326",
    "sg:postcode":"30907",
    "sg:province":"GA",
    "sg:tags":[
        "assistant"
    ],
    "wof:name":"Team Fit Personal Trainer",
    "wof:placetype":"venue"
},
  "geometry": {"coordinates":[-82.139044,33.507029],"type":"Point"}
}