{
  "type": "Feature",
  "properties": {
    "iso:country":"US",
    "sg:address":"3844 Atlanta Hwy",
    "sg:city":"Hiram",
    "sg:classifiers":[
        {
            "category":"Banks & Credit Unions",
            "subcategory":"Bank",
            "type":"Services"
        },
        {
            "category":"Banks & Credit Unions",
            "subcategory":"Financial Services",
            "type":"Services"
        }
    ],
    "sg:phone":"+1 770 445 1014",
    "sg:postcode":"30141",
    "sg:province":"GA",
    "sg:tags":[
        "financing",
        "loan"
    ],
    "sg:website":"http://www.SunTrust.com",
    "wof:name":"SunTrust Bank - Hiram",
    "wof:placetype":"venue"
},
  "geometry": {"coordinates":[-84.777379,33.908672],"type":"Point"}
}