{
  "type": "Feature",
  "properties": {
    "addr:full":"Perimeter Mall 4400 Ashford Dunwoody Rd Atlanta GA 30346",
    "addr:housenumber":"4400",
    "addr:postcode":"30346",
    "addr:street":"Ashford Dunwoody Rd",
    "iso:country":"US",
    "sg:address":"Perimeter Mall 4400 Ashford Dunwoody Rd",
    "sg:city":"Atlanta",
    "sg:classifiers":[
        {
            "category":"Wholesale",
            "subcategory":"Stationery",
            "type":"Manufacturing & Wholesale Goods"
        }
    ],
    "sg:phone":"+1 770 394 6182",
    "sg:postcode":"30346",
    "sg:province":"GA",
    "sg:tags":[
        "card"
    ],
    "sg:website":"www.hallmark.com",
    "wof:name":"Amy's Hallmark",
    "wof:placetype":"venue"
},
  "geometry": {"coordinates":[-84.340515,33.921742],"type":"Point"}
}