{
  "type": "Feature",
  "properties": {
    "iso:country":"US",
    "sg:address":"1607 Adams St",
    "sg:city":"Vidalia",
    "sg:classifiers":[
        {
            "category":"Building & Trades",
            "subcategory":"Construction",
            "type":"Services"
        }
    ],
    "sg:phone":"+1 912 537 0007",
    "sg:postcode":"30474",
    "sg:province":"GA",
    "sg:tags":[
        "fire",
        "restoration",
        "damage"
    ],
    "wof:name":"Joli's Remodeling Inc",
    "wof:placetype":"venue"
},
  "geometry": {"coordinates":[-82.424689,32.208062],"type":"Point"}
}