{
  "type": "Feature",
  "properties": {
    "addr:full":"1301 Industrial Blvd Ashburn GA 31714",
    "addr:housenumber":"1301",
    "addr:postcode":"31714",
    "addr:street":"Industrial Blvd",
    "iso:country":"US",
    "sg:address":"1301 Industrial Blvd",
    "sg:city":"Ashburn",
    "sg:classifiers":[
        {
            "category":"Professional",
            "subcategory":"Management & Consulting",
            "type":"Services"
        }
    ],
    "sg:phone":"+1 229 567 9058",
    "sg:postcode":"31714",
    "sg:province":"GA",
    "sg:tags":[
        "support",
        "facility"
    ],
    "wof:name":"Abl Management Inc",
    "wof:placetype":"venue"
},
  "geometry": {"coordinates":[-83.63999099999999,31.685457],"type":"Point"}
}