{
  "type": "Feature",
  "properties": {
    "addr:full":"1605 Pinebrook Dr Griffin GA 30224",
    "addr:housenumber":"1605",
    "addr:postcode":"30224",
    "addr:street":"Pinebrook Dr",
    "iso:country":"US",
    "sg:address":"1605 Pinebrook Dr",
    "sg:city":"Griffin",
    "sg:classifiers":[
        {
            "category":"Building & Trades",
            "subcategory":"Construction",
            "type":"Services"
        }
    ],
    "sg:phone":"+1 770 227 0570",
    "sg:postcode":"30224",
    "sg:province":"GA",
    "sg:tags":[
        "contractor"
    ],
    "wof:name":"Eadys Drywall",
    "wof:placetype":"venue"
},
  "geometry": {"coordinates":[-84.30100899999999,33.235959],"type":"Point"}
}