{
  "type": "Feature",
  "properties": {
    "addr:full":"707 Franklin Rd SE 6-5 Marietta GA 30067",
    "addr:housenumber":"707;6-5",
    "addr:postcode":"30067",
    "addr:street":"Franklin Rd Se",
    "iso:country":"US",
    "sg:address":"707 Franklin Rd SE 6-5",
    "sg:city":"Marietta",
    "sg:classifiers":[
        {
            "category":"Wholesale",
            "subcategory":"Medical Equipment & Supplies",
            "type":"Manufacturing & Wholesale Goods"
        }
    ],
    "sg:phone":"+1 678 887 0784",
    "sg:postcode":"30067",
    "sg:province":"GA",
    "sg:tags":[
        "pharmaceutical",
        "products-wholesale",
        "manufacturer"
    ],
    "wof:name":"Jomia",
    "wof:placetype":"venue"
},
  "geometry": {"coordinates":[-84.504132,33.935598],"type":"Point"}
}