{
  "type": "Feature",
  "properties": {
    "addr:full":"2153 Oakview Rd Atlanta GA 30317",
    "addr:housenumber":"2153",
    "addr:postcode":"30317",
    "addr:street":"Oakview Rd",
    "iso:country":"US",
    "sg:address":"2153 Oakview Rd",
    "sg:city":"Atlanta",
    "sg:classifiers":[
        {
            "category":"Real Estate",
            "subcategory":"Real Estate Services",
            "type":"Services"
        }
    ],
    "sg:phone":"+1 678 777 5922",
    "sg:postcode":"30317",
    "sg:province":"GA",
    "sg:tags":[
        "home",
        "inspector"
    ],
    "wof:name":"W Energy and Environmental",
    "wof:placetype":"venue"
},
  "geometry": {"coordinates":[-84.31714700000001,33.748725],"type":"Point"}
}