{
  "type": "Feature",
  "properties": {
    "iso:country":"US",
    "sg:address":"4570 State Rte 53",
    "sg:city":"Hoschton",
    "sg:classifiers":[
        {
            "category":"Real Estate",
            "subcategory":"Real Estate Operator",
            "type":"Services"
        }
    ],
    "sg:phone":"+1 706 654 3811",
    "sg:postcode":"30548",
    "sg:province":"GA",
    "sg:tags":[
        "building",
        "apartment"
    ],
    "wof:name":"Jackson West Villas",
    "wof:placetype":"venue"
},
  "geometry": {"coordinates":[-83.761638,34.103314],"type":"Point"}
}