{
  "type": "Feature",
  "properties": {
    "iso:country":"US",
    "sg:address":"3520 Walton Way Ext",
    "sg:city":"Augusta",
    "sg:classifiers":[
        {
            "category":"Health Services",
            "subcategory":"Doctor",
            "type":"Services"
        },
        {
            "category":"Health Services",
            "subcategory":"Health Practitioner",
            "type":"Services"
        }
    ],
    "sg:phone":"+1 706 481 9191",
    "sg:postcode":"30909",
    "sg:province":"GA",
    "sg:tags":[
        "physician",
        "ophthalmology",
        "surgeons",
        "surgeon"
    ],
    "sg:website":"http://www.retinaeyecenter.com",
    "wof:name":"Retina Eye Center The",
    "wof:placetype":"venue"
},
  "geometry": {"coordinates":[-82.072063,33.485888],"type":"Point"}
}