{
  "type": "Feature",
  "properties": {
    "iso:country":"US",
    "sg:address":"157 Merrell Rd",
    "sg:city":"Carrollton",
    "sg:classifiers":[
        {
            "category":"Professional",
            "type":"Services"
        }
    ],
    "sg:phone":"+1 770 834 6158",
    "sg:postcode":"30116",
    "sg:province":"GA",
    "wof:name":"Oliver D Ross",
    "wof:placetype":"venue"
},
  "geometry": {"coordinates":[-85.03247399999999,33.519871],"type":"Point"}
}