{
  "type": "Feature",
  "properties": {
    "iso:country":"US",
    "sg:address":"217 Valley Way",
    "sg:city":"Hampton",
    "sg:classifiers":[
        {
            "category":"Utilities",
            "subcategory":"Refuse",
            "type":"Services"
        }
    ],
    "sg:phone":"+1 770 946 9595",
    "sg:postcode":"30228",
    "sg:province":"GA",
    "sg:tags":[
        "industrial",
        "garbage",
        "disposal",
        "commercial",
        "collection",
        "equipment"
    ],
    "wof:name":"E-Z Waste Disposal",
    "wof:placetype":"venue"
},
  "geometry": {"coordinates":[-84.254274,33.372172],"type":"Point"}
}