{
  "type": "Feature",
  "properties": {
    "iso:country":"US",
    "sg:address":"293 Joyner Rd",
    "sg:city":"Cairo",
    "sg:classifiers":[
        {
            "category":"Utilities",
            "subcategory":"Fuel Oil & Lpg",
            "type":"Services"
        }
    ],
    "sg:phone":"+1 229 377 7442",
    "sg:postcode":"39828",
    "sg:province":"GA",
    "sg:tags":[
        "liquefied",
        "gas",
        "petroleum"
    ],
    "wof:name":"Quality L P Gas Co",
    "wof:placetype":"venue"
},
  "geometry": {"coordinates":[-84.189019,30.861691],"type":"Point"}
}