{
  "type": "Feature",
  "properties": {
    "iso:country":"US",
    "sg:address":"3901 Glenwood Rd",
    "sg:city":"Decatur",
    "sg:classifiers":[
        {
            "category":"Restaurant",
            "type":"Food & Drink"
        }
    ],
    "sg:phone":"+1 404 289 7661",
    "sg:postcode":"30032",
    "sg:province":"GA",
    "sg:tags":[
        "soul"
    ],
    "wof:name":"Jacky's Soul Food Restaurant",
    "wof:placetype":"venue"
},
  "geometry": {"coordinates":[-84.25831100000001,33.738051],"type":"Point"}
}