{
  "type": "Feature",
  "properties": {
    "iso:country":"US",
    "sg:address":"38 Ferrill St",
    "sg:city":"Savannah",
    "sg:classifiers":[
        {
            "category":"Organizations",
            "subcategory":"Religious Organization",
            "type":"Services"
        }
    ],
    "sg:phone":"+1 912 232 7628",
    "sg:postcode":"31415",
    "sg:province":"GA",
    "sg:tags":[
        "church"
    ],
    "wof:name":"Rose Of Sharon Baptist Church",
    "wof:placetype":"venue"
},
  "geometry": {"coordinates":[-81.113944,32.086208],"type":"Point"}
}