{
  "type": "Feature",
  "properties": {
    "addr:full":"190 N Macon St Jesup GA 31545",
    "addr:housenumber":"190",
    "addr:postcode":"31545",
    "addr:street":"N Macon St",
    "iso:country":"US",
    "sg:address":"190 N Macon St",
    "sg:city":"Jesup",
    "sg:classifiers":[
        {
            "category":"Shopping",
            "subcategory":"Baby Store",
            "type":"Retail Goods"
        },
        {
            "category":"Banks & Credit Unions",
            "subcategory":"Bank",
            "type":"Services"
        },
        {
            "category":"Shopping",
            "subcategory":"Used Merchandise",
            "type":"Retail Goods"
        }
    ],
    "sg:phone":"+1 912 427 7449",
    "sg:postcode":"31545",
    "sg:province":"GA",
    "sg:tags":[
        "shop",
        "infant",
        "hand",
        "resale",
        "children's",
        "second",
        "wear"
    ],
    "wof:name":"A Kids Korner",
    "wof:placetype":"venue"
},
  "geometry": {"coordinates":[-81.883544,31.606844],"type":"Point"}
}