{
  "type": "Feature",
  "properties": {
    "iso:country":"US",
    "sg:address":"1300 Atlanta Rd SE Ste 400",
    "sg:city":"Marietta",
    "sg:classifiers":[
        {
            "category":"Restaurant",
            "type":"Food & Drink"
        }
    ],
    "sg:phone":"+1 678 594 7524",
    "sg:postcode":"30060",
    "sg:province":"GA",
    "sg:tags":[
        "mexican"
    ],
    "wof:name":"Las Colines Mexican Restaurant",
    "wof:placetype":"venue"
},
  "geometry": {"coordinates":[-84.542821,33.921648],"type":"Point"}
}