{
  "type": "Feature",
  "properties": {
    "iso:country":"US",
    "sg:address":"5505 Sassafras Ave",
    "sg:city":"Albany",
    "sg:classifiers":[
        {
            "category":"Building & Trades",
            "subcategory":"Cleaning & Sanitation",
            "type":"Services"
        }
    ],
    "sg:phone":"+1 229 436 0528",
    "sg:postcode":"31705",
    "sg:province":"GA",
    "sg:tags":[
        "janitor"
    ],
    "wof:name":"Diamond Janitorial Svc",
    "wof:placetype":"venue"
},
  "geometry": {"coordinates":[-84.00108899999999,31.583906],"type":"Point"}
}