{
  "type": "Feature",
  "properties": {
    "iso:country":"US",
    "sg:address":"231 N Main St",
    "sg:city":"Dawson",
    "sg:classifiers":[
        {
            "category":"Personal",
            "subcategory":"Beauty Salon",
            "type":"Services"
        }
    ],
    "sg:phone":"+1 229 995 2092",
    "sg:postcode":"39842",
    "sg:province":"GA",
    "wof:name":"New Creations Hair Design",
    "wof:placetype":"venue"
},
  "geometry": {"coordinates":[-84.446781,31.775345],"type":"Point"}
}