{
  "type": "Feature",
  "properties": {
    "iso:country":"US",
    "sg:address":"3010 Spring Industrial Dr",
    "sg:city":"Powder Springs",
    "sg:classifiers":[
        {
            "category":"Manufacturing",
            "subcategory":"Tools & Machinery",
            "type":"Manufacturing & Wholesale Goods"
        }
    ],
    "sg:phone":"+1 770 948 6343",
    "sg:postcode":"30127",
    "sg:province":"GA",
    "sg:tags":[
        "product",
        "filing"
    ],
    "wof:name":"Diversified Assembly",
    "wof:placetype":"venue"
},
  "geometry": {"coordinates":[-84.707939,33.878559],"type":"Point"}
}