{
  "type": "Feature",
  "properties": {
    "iso:country":"US",
    "sg:address":"221 Tifton-Worth Co Line Rd",
    "sg:city":"Tifton",
    "sg:classifiers":[
        {
            "category":"Real Estate",
            "subcategory":"Real Estate Operator",
            "type":"Services"
        }
    ],
    "sg:phone":"+1 229 382 6578",
    "sg:postcode":"31793",
    "sg:province":"GA",
    "sg:tags":[
        "mobile",
        "home",
        "site"
    ],
    "wof:name":"Bar W Mobile Home Ranch",
    "wof:placetype":"venue"
},
  "geometry": {"coordinates":[-83.596735,31.493178],"type":"Point"}
}