{
  "type": "Feature",
  "properties": {
    "iso:country":"US",
    "sg:address":"1889 Beechwood Blvd NW",
    "sg:city":"Gainesville",
    "sg:classifiers":[
        {
            "category":"Professional",
            "subcategory":"Accounting & Tax Preparation",
            "type":"Services"
        }
    ],
    "sg:phone":"+1 770 297 9884",
    "sg:postcode":"30504",
    "sg:province":"GA",
    "sg:tags":[
        "accountant",
        "return"
    ],
    "wof:name":"A-Plus Accounting & Tax Svc",
    "wof:placetype":"venue"
},
  "geometry": {"coordinates":[-83.86375,34.297934],"type":"Point"}
}