{
  "type": "Feature",
  "properties": {
    "addr:full":"413 Industrial Blvd McDonough GA 30253",
    "addr:housenumber":"413",
    "addr:postcode":"30253",
    "addr:street":"Industrial Blvd",
    "iso:country":"US",
    "sg:address":"413 Industrial Blvd",
    "sg:city":"McDonough",
    "sg:classifiers":[
        {
            "category":"Autos & Motor Vehicles",
            "subcategory":"Automobile Sales",
            "type":"Retail Goods"
        }
    ],
    "sg:phone":"+1 770 914 3459",
    "sg:postcode":"30253",
    "sg:province":"GA",
    "sg:tags":[
        "body",
        "shop",
        "car"
    ],
    "sg:website":"www.legacyford.com",
    "wof:name":"Legacy Ford Mercury Inc Body Shop",
    "wof:placetype":"venue"
},
  "geometry": {"coordinates":[-84.168999,33.419601],"type":"Point"}
}