{
  "type": "Feature",
  "properties": {
    "addr:full":"226 32nd Ave Columbus GA 31903",
    "addr:housenumber":"226",
    "addr:postcode":"31903",
    "addr:street":"32Nd Ave",
    "iso:country":"US",
    "sg:address":"226 32nd Ave",
    "sg:city":"Columbus",
    "sg:classifiers":[
        {
            "category":"Transit Center",
            "subcategory":"Freight",
            "type":"Transportation"
        },
        {
            "category":"Freight",
            "type":"Transportation"
        }
    ],
    "sg:phone":"+1 706 682 7596",
    "sg:postcode":"31903",
    "sg:province":"GA",
    "sg:tags":[
        "local",
        "trucking-motor",
        "trucking"
    ],
    "wof:name":"Charles Spencer Trucking",
    "wof:placetype":"venue"
},
  "geometry": {"coordinates":[-84.951987,32.439792],"type":"Point"}
}