{
  "type": "Feature",
  "properties": {
    "iso:country":"US",
    "sg:address":"3453 Greystone Dr",
    "sg:city":"Loganville",
    "sg:classifiers":[
        {
            "category":"Professional",
            "type":"Services"
        }
    ],
    "sg:phone":"+1 770 554 8187",
    "sg:postcode":"30052",
    "sg:province":"GA",
    "sg:tags":[
        "establishment"
    ],
    "wof:name":"ZTZ Admin",
    "wof:placetype":"venue"
},
  "geometry": {"coordinates":[-83.833556,33.785557],"type":"Point"}
}