{
  "type": "Feature",
  "properties": {
    "iso:country":"US",
    "sg:address":"649 Brook Cir",
    "sg:city":"Griffin",
    "sg:classifiers":[
        {
            "category":"Food & Beverages",
            "subcategory":"Groceries & Convenience Stores",
            "type":"Retail Goods"
        }
    ],
    "sg:phone":"+1 770 227 5967",
    "sg:postcode":"30224",
    "sg:province":"GA",
    "sg:tags":[
        "gas"
    ],
    "wof:name":"Alans Gas & Grocery",
    "wof:placetype":"venue"
},
  "geometry": {"coordinates":[-84.249554,33.239492],"type":"Point"}
}