{
  "type": "Feature",
  "properties": {
    "addr:full":"615 US Hwy 80 Savannah GA 31408",
    "addr:housenumber":"615",
    "addr:postcode":"31408",
    "addr:street":"Us Hwy 80",
    "iso:country":"US",
    "sg:address":"615 US Hwy 80",
    "sg:city":"Savannah",
    "sg:classifiers":[
        {
            "category":"Professional",
            "subcategory":"Detective & Security Services",
            "type":"Services"
        }
    ],
    "sg:phone":"+1 912 964 2997",
    "sg:postcode":"31408",
    "sg:province":"GA",
    "sg:tags":[
        "guard",
        "patrol"
    ],
    "wof:name":"Four Star Security & Detective",
    "wof:placetype":"venue"
},
  "geometry": {"coordinates":[-81.149078,32.093163],"type":"Point"}
}