{
  "type": "Feature",
  "properties": {
    "iso:country":"US",
    "sg:address":"743 Pleasant Hill Rd NW",
    "sg:city":"Lilburn",
    "sg:classifiers":[
        {
            "category":"Restaurant",
            "type":"Food & Drink"
        }
    ],
    "sg:menulink":"http://www.allmenus.com/ga/lilburn/154002-zaxbys/menu/",
    "sg:phone":"+1 770 921 6161",
    "sg:postcode":"30047",
    "sg:province":"GA",
    "sg:tags":[
        "american",
        "wing"
    ],
    "wof:name":"Zaxby's",
    "wof:placetype":"venue"
},
  "geometry": {"coordinates":[-84.113679,33.918698],"type":"Point"}
}