{
  "type": "Feature",
  "properties": {
    "addr:full":"419 Merchants Dr Dallas GA 30132",
    "addr:housenumber":"419",
    "addr:postcode":"30132",
    "addr:street":"Merchants Dr",
    "iso:country":"US",
    "sg:address":"419 Merchants Dr",
    "sg:city":"Dallas",
    "sg:classifiers":[
        {
            "category":"Home & Garden",
            "subcategory":"Carpets & Floor Coverings",
            "type":"Retail Goods"
        }
    ],
    "sg:phone":"+1 770 445 7573",
    "sg:postcode":"30132",
    "sg:province":"GA",
    "wof:name":"Quality Carpets Sales & Svc",
    "wof:placetype":"venue"
},
  "geometry": {"coordinates":[-84.82373699999999,33.913409],"type":"Point"}
}