{
  "type": "Feature",
  "properties": {
    "iso:country":"US",
    "sg:address":"801 Broad St",
    "sg:city":"Augusta",
    "sg:classifiers":[
        {
            "category":"Utilities",
            "subcategory":"Telephone",
            "type":"Services"
        }
    ],
    "sg:phone":"+1 706 724 6627",
    "sg:postcode":"30901",
    "sg:province":"GA",
    "sg:tags":[
        "communications"
    ],
    "wof:name":"MCI",
    "wof:placetype":"venue"
},
  "geometry": {"coordinates":[-81.96632700000001,33.475702],"type":"Point"}
}