{
  "type": "Feature",
  "properties": {
    "iso:country":"US",
    "sg:address":"119 Roberta Dr",
    "sg:city":"Barnesville",
    "sg:classifiers":[
        {
            "category":"Retail",
            "subcategory":"Auto Repair",
            "type":"Services"
        }
    ],
    "sg:phone":"+1 770 358 1595",
    "sg:postcode":"30204",
    "sg:province":"GA",
    "sg:tags":[
        "filter",
        "automotive",
        "oil"
    ],
    "wof:name":"341 Quick Lube",
    "wof:placetype":"venue"
},
  "geometry": {"coordinates":[-84.17670099999999,33.040797],"type":"Point"}
}