{
  "type": "Feature",
  "properties": {
    "addr:full":"1008 Shorter Ave Rome GA 30165",
    "addr:housenumber":"1008",
    "addr:postcode":"ga 30165",
    "addr:street":"Shorter Ave",
    "iso:country":"US",
    "sg:address":"1008 Shorter Ave",
    "sg:city":"Rome",
    "sg:classifiers":[
        {
            "category":"Wholesale",
            "subcategory":"Farm Supplies",
            "type":"Manufacturing & Wholesale Goods"
        }
    ],
    "sg:phone":"+1 706 215 1116",
    "sg:postcode":"30165",
    "sg:province":"GA",
    "wof:name":"R & R Feed Co",
    "wof:placetype":"venue"
},
  "geometry": {"coordinates":[-85.20624599999999,34.267133],"type":"Point"}
}