{
  "type": "Feature",
  "properties": {
    "iso:country":"US",
    "sg:address":"47 Ida J Gadsen Dr",
    "sg:city":"Savannah",
    "sg:classifiers":[
        {
            "category":"Retail",
            "subcategory":"Auto Rental",
            "type":"Services"
        }
    ],
    "sg:phone":"+1 912 964 9186",
    "sg:postcode":"31408",
    "sg:province":"GA",
    "sg:tags":[
        "car"
    ],
    "sg:website":"http://www.budgetrentacar.com",
    "wof:name":"Budget Rent A Car",
    "wof:placetype":"venue"
},
  "geometry": {"coordinates":[-81.220573,32.137077],"type":"Point"}
}