{
  "type": "Feature",
  "properties": {
    "addr:full":"3644 Chamblee Tucker Rd Atlanta GA 30341",
    "addr:housenumber":"3644",
    "addr:postcode":"30341",
    "addr:street":"Chamblee Tucker Rd",
    "iso:country":"US",
    "sg:address":"3644 Chamblee Tucker Rd",
    "sg:city":"Atlanta",
    "sg:classifiers":[
        {
            "category":"Professional",
            "subcategory":"Business Services",
            "type":"Services"
        }
    ],
    "sg:phone":"+1 770 414 8404",
    "sg:postcode":"30341",
    "sg:province":"GA",
    "wof:name":"Wenner Enterprises LLC",
    "wof:placetype":"venue"
},
  "geometry": {"coordinates":[-84.24758799999999,33.885503],"type":"Point"}
}