{
  "type": "Feature",
  "properties": {
    "addr:full":"103 S Duke St La Fayette GA 30728",
    "addr:housenumber":"103",
    "addr:postcode":"30728",
    "addr:street":"S Duke St;Fayette",
    "iso:country":"US",
    "sg:address":"103 S Duke St",
    "sg:city":"La Fayette",
    "sg:classifiers":[
        {
            "category":"Government",
            "subcategory":"Office",
            "type":"Public Place"
        }
    ],
    "sg:phone":"+1 706 638 6394",
    "sg:postcode":"30728",
    "sg:province":"GA",
    "wof:name":"Honorable Ralph Hill",
    "wof:placetype":"venue"
},
  "geometry": {"coordinates":[-85.280567,34.705093],"type":"Point"}
}