{
  "type": "Feature",
  "properties": {
    "addr:full":"64 N Main St Watkinsville GA 30677",
    "addr:housenumber":"64",
    "addr:postcode":"30677",
    "addr:street":"N Main St",
    "iso:country":"US",
    "sg:address":"64 N Main St",
    "sg:city":"Watkinsville",
    "sg:classifiers":[
        {
            "category":"Home & Garden",
            "subcategory":"Household Appliances",
            "type":"Retail Goods"
        }
    ],
    "sg:phone":"+1 706 310 1400",
    "sg:postcode":"30677",
    "sg:province":"GA",
    "sg:tags":[
        "machine",
        "sewing"
    ],
    "sg:website":"www.classicsewing.com",
    "wof:name":"Classic Sewing Center",
    "wof:placetype":"venue"
},
  "geometry": {"coordinates":[-83.41115499999999,33.865974],"type":"Point"}
}