{
  "type": "Feature",
  "properties": {
    "iso:country":"US",
    "sg:address":"2423 Bullen Gap Rd",
    "sg:city":"Blue Ridge",
    "sg:classifiers":[
        {
            "category":"Building & Trades",
            "subcategory":"Construction",
            "type":"Services"
        }
    ],
    "sg:phone":"+1 706 632 8546",
    "sg:postcode":"30513",
    "sg:province":"GA",
    "sg:tags":[
        "contractor"
    ],
    "wof:name":"Manners Construction Inc",
    "wof:placetype":"venue"
},
  "geometry": {"coordinates":[-84.340974,34.85823],"type":"Point"}
}