{
  "type": "Feature",
  "properties": {
    "iso:country":"US",
    "sg:address":"320 E Montgomery Xrd",
    "sg:city":"Savannah",
    "sg:classifiers":[
        {
            "category":"Retail",
            "subcategory":"Repair Shop",
            "type":"Services"
        }
    ],
    "sg:phone":"+1 912 351 9888",
    "sg:postcode":"31406",
    "sg:province":"GA",
    "sg:tags":[
        "equipment",
        "golf",
        "refinishing"
    ],
    "sg:website":"www.isotechgolf.com",
    "wof:name":"Isotech Golf",
    "wof:placetype":"venue"
},
  "geometry": {"coordinates":[-81.112483,31.995848],"type":"Point"}
}