{
  "type": "Feature",
  "properties": {
    "iso:country":"US",
    "sg:address":"3722 S Dixie Rd",
    "sg:city":"Dalton",
    "sg:classifiers":[
        {
            "category":"Building & Trades",
            "subcategory":"Cleaning & Sanitation",
            "type":"Services"
        }
    ],
    "sg:phone":"+1 706 370 4097",
    "sg:postcode":"30721",
    "sg:province":"GA",
    "sg:tags":[
        "ventilating",
        "system"
    ],
    "wof:name":"Stansell Air Duct Cleaning",
    "wof:placetype":"venue"
},
  "geometry": {"coordinates":[-84.99155,34.689442],"type":"Point"}
}