{
  "type": "Feature",
  "properties": {
    "iso:country":"US",
    "sg:address":"2145 Roswell Rd Ste 280",
    "sg:city":"Marietta",
    "sg:classifiers":[
        {
            "category":"Personal",
            "subcategory":"Massage",
            "type":"Services"
        }
    ],
    "sg:phone":"+1 770 973 3285",
    "sg:postcode":"30062",
    "sg:province":"GA",
    "wof:name":"Whole Wellness",
    "wof:placetype":"venue"
},
  "geometry": {"coordinates":[-84.490196,33.9678],"type":"Point"}
}