{
  "type": "Feature",
  "properties": {
    "addr:full":"3254 Inner Perimeter Rd Valdosta GA 31602",
    "addr:housenumber":"3254",
    "addr:postcode":"31602",
    "addr:street":"Inner Perimeter Rd",
    "iso:country":"US",
    "sg:address":"3254 Inner Perimeter Rd",
    "sg:city":"Valdosta",
    "sg:classifiers":[
        {
            "category":"Restaurant",
            "type":"Food & Drink"
        }
    ],
    "sg:phone":"+1 229 257 0003",
    "sg:postcode":"31602",
    "sg:province":"GA",
    "wof:name":"Applebee's Neighborhood Grill",
    "wof:placetype":"venue"
},
  "geometry": {"coordinates":[-83.29237000000001,30.881884],"type":"Point"}
}