{
  "type": "Feature",
  "properties": {
    "addr:full":"850 Williams Dr Marietta GA 30066",
    "addr:housenumber":"850",
    "addr:postcode":"30066",
    "addr:street":"Williams Dr",
    "iso:country":"US",
    "sg:address":"850 Williams Dr",
    "sg:city":"Marietta",
    "sg:classifiers":[
        {
            "category":"Manufacturing",
            "subcategory":"Glass & Minerals",
            "type":"Manufacturing & Wholesale Goods"
        }
    ],
    "sg:phone":"+1 678 784 2100",
    "sg:postcode":"30066",
    "sg:province":"GA",
    "sg:tags":[
        "stone",
        "cut",
        "product"
    ],
    "sg:website":"www.roberts-shields.com",
    "wof:name":"Roberts-Shields Memorial Co",
    "wof:placetype":"venue"
},
  "geometry": {"coordinates":[-84.529376,33.998034],"type":"Point"}
}