{
  "type": "Feature",
  "properties": {
    "iso:country":"US",
    "sg:address":"500 Sun Valley Dr",
    "sg:city":"Roswell",
    "sg:classifiers":[
        {
            "category":"Wholesale",
            "subcategory":"Hardware",
            "type":"Manufacturing & Wholesale Goods"
        }
    ],
    "sg:phone":"+1 770 552 5532",
    "sg:postcode":"30076",
    "sg:province":"GA",
    "sg:tags":[
        "representative",
        "mfg"
    ],
    "wof:name":"Lowe Vp Inc",
    "wof:placetype":"venue"
},
  "geometry": {"coordinates":[-84.339178,34.05134],"type":"Point"}
}