{
  "type": "Feature",
  "properties": {
    "iso:country":"US",
    "sg:address":"1022 Cassville Rd SE",
    "sg:city":"Cartersville",
    "sg:classifiers":[
        {
            "category":"Travel",
            "subcategory":"Hotels & Motels",
            "type":"Entertainment"
        }
    ],
    "sg:phone":"+1 770 382 6677",
    "sg:postcode":"30121",
    "sg:province":"GA",
    "wof:name":"Scotts Motel",
    "wof:placetype":"venue"
},
  "geometry": {"coordinates":[-84.827384,34.200587],"type":"Point"}
}