{
  "type": "Feature",
  "properties": {
    "iso:country":"US",
    "sg:address":"815 Harmony Rd",
    "sg:city":"Eatonton",
    "sg:classifiers":[
        {
            "category":"Autos & Motor Vehicles",
            "subcategory":"Boat Sales",
            "type":"Retail Goods"
        }
    ],
    "sg:phone":"+1 706 485 4063",
    "sg:postcode":"31024",
    "sg:province":"GA",
    "sg:tags":[
        "dealer",
        "sales"
    ],
    "wof:name":"4 Seasons Marine Inc",
    "wof:placetype":"venue"
},
  "geometry": {"coordinates":[-83.282961,33.442759],"type":"Point"}
}