{
  "type": "Feature",
  "properties": {
    "addr:full":"1762 Jett Roberts Rd Jefferson GA 30549",
    "addr:housenumber":"1762",
    "addr:postcode":"30549",
    "addr:street":"Jett Roberts Rd",
    "iso:country":"US",
    "sg:address":"1762 Jett Roberts Rd",
    "sg:city":"Jefferson",
    "sg:classifiers":[
        {
            "category":"Recreation",
            "type":"Entertainment"
        }
    ],
    "sg:phone":"+1 706 367 9390",
    "sg:postcode":"30549",
    "sg:province":"GA",
    "sg:tags":[
        "stable"
    ],
    "wof:name":"South Wind Ranch Inc",
    "wof:placetype":"venue"
},
  "geometry": {"coordinates":[-83.58251300000001,34.151933],"type":"Point"}
}