{
  "type": "Feature",
  "properties": {
    "iso:country":"US",
    "sg:address":"345 Nichols Rd",
    "sg:city":"Suwanee",
    "sg:classifiers":[
        {
            "category":"Manufacturing",
            "subcategory":"Building Materials",
            "type":"Manufacturing & Wholesale Goods"
        }
    ],
    "sg:phone":"+1 770 889 3520",
    "sg:postcode":"30024",
    "sg:province":"GA",
    "sg:tags":[
        "mfg",
        "wood",
        "kitchen",
        "cabinet"
    ],
    "wof:name":"Lawson Cabinet Shop",
    "wof:placetype":"venue"
},
  "geometry": {"coordinates":[-84.13276399999999,34.117069],"type":"Point"}
}