{
  "type": "Feature",
  "properties": {
    "iso:country":"US",
    "sg:address":"108 E Lamar St",
    "sg:city":"Americus",
    "sg:classifiers":[
        {
            "category":"Banks & Credit Unions",
            "subcategory":"Bank",
            "type":"Services"
        }
    ],
    "sg:phone":"+1 229 924 7220",
    "sg:postcode":"31709",
    "sg:province":"GA",
    "wof:name":"Central Bank Of Georgia",
    "wof:placetype":"venue"
},
  "geometry": {"coordinates":[-84.231686,32.072167],"type":"Point"}
}