{
  "type": "Feature",
  "properties": {
    "addr:full":"286 S Main St Ste 600 Alpharetta GA 30004",
    "addr:housenumber":"286",
    "addr:postcode":"30004",
    "addr:street":"S Main St Ste 600",
    "iso:country":"US",
    "sg:address":"286 S Main St Ste 600",
    "sg:city":"Alpharetta",
    "sg:classifiers":[
        {
            "category":"Banks & Credit Unions",
            "subcategory":"Financial Services",
            "type":"Services"
        }
    ],
    "sg:phone":"+1 770 667 5155",
    "sg:postcode":"30004",
    "sg:province":"GA",
    "sg:tags":[
        "broker",
        "mortgage"
    ],
    "wof:name":"A A A Mortage Solutions",
    "wof:placetype":"venue"
},
  "geometry": {"coordinates":[-84.300697,34.068199],"type":"Point"}
}