{
  "type": "Feature",
  "properties": {
    "iso:country":"US",
    "sg:address":"101 Brookview Ter",
    "sg:city":"Valdosta",
    "sg:classifiers":[
        {
            "category":"Organizations",
            "subcategory":"Religious Organization",
            "type":"Services"
        }
    ],
    "sg:phone":"+1 229 245 1662",
    "sg:postcode":"31605",
    "sg:province":"GA",
    "wof:name":"Willie E Flowers Rev",
    "wof:placetype":"venue"
},
  "geometry": {"coordinates":[-83.29154200000001,30.893328],"type":"Point"}
}