{
  "type": "Feature",
  "properties": {
    "iso:country":"US",
    "sg:address":"2363 US Hwy 41 South SW",
    "sg:city":"Calhoun",
    "sg:classifiers":[
        {
            "category":"Freight",
            "type":"Transportation"
        }
    ],
    "sg:phone":"+1 706 629 2831",
    "sg:postcode":"30701",
    "sg:province":"GA",
    "sg:tags":[
        "warehouse",
        "merchandise"
    ],
    "wof:name":"North Georgia Warehousing Svc",
    "wof:placetype":"venue"
},
  "geometry": {"coordinates":[-84.935709,34.443562],"type":"Point"}
}