{
  "type": "Feature",
  "properties": {
    "iso:country":"US",
    "sg:address":"1921 Brogden Rd",
    "sg:city":"Waycross",
    "sg:classifiers":[
        {
            "category":"Freight",
            "type":"Transportation"
        }
    ],
    "sg:phone":"+1 912 285 2383",
    "sg:postcode":"31503",
    "sg:province":"GA",
    "sg:tags":[
        "mobile",
        "home",
        "transporting"
    ],
    "wof:name":"Hester Mobile Home Movers",
    "wof:placetype":"venue"
},
  "geometry": {"coordinates":[-82.381164,31.264797],"type":"Point"}
}