{
  "type": "Feature",
  "properties": {
    "iso:country":"US",
    "sg:address":"6125 Duquesne Dr SW",
    "sg:city":"Atlanta",
    "sg:classifiers":[
        {
            "category":"Freight",
            "type":"Transportation"
        }
    ],
    "sg:phone":"+1 404 346 8280",
    "sg:postcode":"30336",
    "sg:province":"GA",
    "sg:tags":[
        "operator",
        "local",
        "trucking"
    ],
    "wof:name":"Averitt Express Inc",
    "wof:placetype":"venue"
},
  "geometry": {"coordinates":[-84.599209,33.719728],"type":"Point"}
}