{
  "type": "Feature",
  "properties": {
    "addr:full":"2295 Oak Rd Snellville GA 30078",
    "addr:housenumber":"2295",
    "addr:postcode":"30078",
    "addr:street":"Oak Rd",
    "iso:country":"US",
    "sg:address":"2295 Oak Rd",
    "sg:city":"Snellville",
    "sg:classifiers":[
        {
            "category":"Shopping",
            "subcategory":"Pharmacy",
            "type":"Retail Goods"
        }
    ],
    "sg:phone":"+1 770 972 0700",
    "sg:postcode":"30078",
    "sg:province":"GA",
    "sg:tags":[
        "drugstore"
    ],
    "wof:name":"Snell's Pharmacy",
    "wof:placetype":"venue"
},
  "geometry": {"coordinates":[-84.016998,33.8596],"type":"Point"}
}