{
  "type": "Feature",
  "properties": {
    "addr:full":"4005 Stonewall Tell Rd Atlanta GA 30349",
    "addr:housenumber":"4005",
    "addr:postcode":"30349",
    "addr:street":"Stonewall Tell Rd",
    "iso:country":"US",
    "sg:address":"4005 Stonewall Tell Rd",
    "sg:city":"Atlanta",
    "sg:classifiers":[
        {
            "category":"Place Of Worship",
            "subcategory":"Church",
            "type":"Public Place"
        },
        {
            "category":"Place Of Worship",
            "type":"Public Place"
        }
    ],
    "sg:phone":"+1 770 964 9891",
    "sg:postcode":"30349",
    "sg:province":"GA",
    "sg:tags":[
        "churches-baptist-general",
        "churches-baptist-southern",
        "churches-baptist"
    ],
    "wof:name":"First Baptist Chr-Cliftondale",
    "wof:placetype":"venue"
},
  "geometry": {"coordinates":[-84.59197399999999,33.646237],"type":"Point"}
}