{
  "type": "Feature",
  "properties": {
    "addr:full":"406 E Mc Phearson Ave Nashville GA 31639",
    "addr:housenumber":"406",
    "addr:postcode":"31639",
    "addr:street":"E Mc Phearson Ave",
    "iso:country":"US",
    "sg:address":"406 E Mc Phearson Ave",
    "sg:city":"Nashville",
    "sg:classifiers":[
        {
            "category":"Shopping",
            "subcategory":"Optical Goods",
            "type":"Retail Goods"
        }
    ],
    "sg:phone":"+1 229 686 3849",
    "sg:postcode":"31639",
    "sg:province":"GA",
    "sg:tags":[
        "contact",
        "lense"
    ],
    "wof:name":"H J Decker III Optometrist",
    "wof:placetype":"venue"
},
  "geometry": {"coordinates":[-83.24564100000001,31.205395],"type":"Point"}
}