{
  "type": "Feature",
  "properties": {
    "iso:country":"US",
    "sg:address":"605 Glynn St N",
    "sg:city":"Fayetteville",
    "sg:classifiers":[
        {
            "category":"Banks & Credit Unions",
            "subcategory":"Investment Brokerage",
            "type":"Services"
        }
    ],
    "sg:phone":"+1 770 461 2991",
    "sg:postcode":"30214",
    "sg:province":"GA",
    "sg:tags":[
        "security"
    ],
    "wof:name":"Whitlock Melinda",
    "wof:placetype":"venue"
},
  "geometry": {"coordinates":[-84.452523,33.459424],"type":"Point"}
}