{
  "type": "Feature",
  "properties": {
    "iso:country":"US",
    "sg:address":"211 E Washington St",
    "sg:city":"Thomasville",
    "sg:classifiers":[
        {
            "category":"Professional",
            "subcategory":"Lawyer & Legal Services",
            "type":"Services"
        }
    ],
    "sg:phone":"+1 229 226 8033",
    "sg:postcode":"31792",
    "sg:province":"GA",
    "sg:tags":[
        "attorney"
    ],
    "wof:name":"Mc Graw & Mc Graw",
    "wof:placetype":"venue"
},
  "geometry": {"coordinates":[-83.97951,30.841075],"type":"Point"}
}