{
  "type": "Feature",
  "properties": {
    "iso:country":"US",
    "sg:address":"900 Circle 75 Pkwy SE Ste 682",
    "sg:city":"Atlanta",
    "sg:classifiers":[
        {
            "category":"Health Services",
            "subcategory":"Clinic",
            "type":"Services"
        }
    ],
    "sg:phone":"+1 770 850 4848",
    "sg:postcode":"30339",
    "sg:province":"GA",
    "sg:tags":[
        "counseling",
        "mental"
    ],
    "sg:website":"www.atlantapsychology.com/",
    "wof:name":"David Phillips, PHD",
    "wof:placetype":"venue"
},
  "geometry": {"coordinates":[-84.46774600000001,33.887557],"type":"Point"}
}