{
  "type": "Feature",
  "properties": {
    "iso:country":"US",
    "sg:address":"273 Glenwood Ave SE",
    "sg:city":"Atlanta",
    "sg:classifiers":[
        {
            "category":"Commercial Area",
            "type":"Public Place"
        }
    ],
    "sg:phone":"+1 404 223 0625",
    "sg:postcode":"30312",
    "sg:province":"GA",
    "sg:tags":[
        "front",
        "store"
    ],
    "wof:name":"AM PM Door Service",
    "wof:placetype":"venue"
},
  "geometry": {"coordinates":[-84.378671,33.742425],"type":"Point"}
}