{
  "type": "Feature",
  "properties": {
    "addr:full":"469 Laurel Xing Blue Ridge GA 30513",
    "addr:housenumber":"469",
    "addr:postcode":"30513",
    "addr:street":"Laurel Xing",
    "iso:country":"US",
    "sg:address":"469 Laurel Xing",
    "sg:city":"Blue Ridge",
    "sg:classifiers":[
        {
            "category":"Professional",
            "subcategory":"Accounting & Tax Preparation",
            "type":"Services"
        }
    ],
    "sg:phone":"+1 706 632 2494",
    "sg:postcode":"30513",
    "sg:province":"GA",
    "sg:tags":[
        "accountant"
    ],
    "wof:name":"Smith & Smith",
    "wof:placetype":"venue"
},
  "geometry": {"coordinates":[-84.393936,34.87505],"type":"Point"}
}