{
  "type": "Feature",
  "properties": {
    "addr:full":"2330 Scenic Hwy S Snellville GA 30078",
    "addr:housenumber":"2330",
    "addr:postcode":"30078",
    "addr:street":"Scenic Hwy S",
    "iso:country":"US",
    "sg:address":"2330 Scenic Hwy S",
    "sg:city":"Snellville",
    "sg:classifiers":[
        {
            "category":"Real Estate",
            "subcategory":"Real Estate Agent",
            "type":"Services"
        }
    ],
    "sg:phone":"+1 678 252 2158",
    "sg:postcode":"30078",
    "sg:province":"GA",
    "wof:name":"Realty World",
    "wof:placetype":"venue"
},
  "geometry": {"coordinates":[-84.02212,33.854467],"type":"Point"}
}