{
  "type": "Feature",
  "properties": {
    "addr:full":"440 Ernest W Barrett Pkwy Kennesaw GA 30144",
    "addr:housenumber":"440",
    "addr:postcode":"30144",
    "addr:street":"Ernest W Barrett Pkwy",
    "iso:country":"US",
    "sg:address":"440 Ernest W Barrett Pkwy",
    "sg:city":"Kennesaw",
    "sg:classifiers":[
        {
            "category":"Home & Garden",
            "subcategory":"Household Appliances",
            "type":"Retail Goods"
        }
    ],
    "sg:phone":"+1 770 218 1618",
    "sg:postcode":"30144",
    "sg:province":"GA",
    "sg:tags":[
        "cleaners",
        "vacuum"
    ],
    "wof:name":"Oreck Floor Care Ctr",
    "wof:placetype":"venue"
},
  "geometry": {"coordinates":[-84.56382499999999,34.012542],"type":"Point"}
}