{
  "type": "Feature",
  "properties": {
    "iso:country":"US",
    "sg:address":"551 E College Ave",
    "sg:city":"Decatur",
    "sg:classifiers":[
        {
            "category":"Building & Trades",
            "subcategory":"Landscaping Services",
            "type":"Services"
        }
    ],
    "sg:phone":"+1 404 377 5897",
    "sg:postcode":"30030",
    "sg:province":"GA",
    "sg:tags":[
        "machinery"
    ],
    "wof:name":"Memorial Lawn Industries Inc",
    "wof:placetype":"venue"
},
  "geometry": {"coordinates":[-84.287199,33.772813],"type":"Point"}
}