{
  "type": "Feature",
  "properties": {
    "iso:country":"US",
    "sg:address":"8531 Birdie Dr",
    "sg:city":"Midland",
    "sg:classifiers":[
        {
            "category":"Professional",
            "subcategory":"Engineering",
            "type":"Services"
        }
    ],
    "sg:phone":"+1 706 565 0522",
    "sg:postcode":"31820",
    "sg:province":"GA",
    "sg:tags":[
        "marketing",
        "consulting",
        "sales"
    ],
    "wof:name":"Turner D D & Associates",
    "wof:placetype":"venue"
},
  "geometry": {"coordinates":[-84.837433,32.555812],"type":"Point"}
}