{
  "type": "Feature",
  "properties": {
    "iso:country":"US",
    "sg:address":"1513 2nd Ave",
    "sg:city":"Albany",
    "sg:classifiers":[
        {
            "category":"Building & Trades",
            "subcategory":"Landscaping Services",
            "type":"Services"
        }
    ],
    "sg:phone":"+1 229 881 1574",
    "sg:postcode":"31707",
    "sg:province":"GA",
    "sg:tags":[
        "landscape",
        "contractor"
    ],
    "wof:name":"Landscape Solutions",
    "wof:placetype":"venue"
},
  "geometry": {"coordinates":[-84.187005,31.589831],"type":"Point"}
}