{
  "type": "Feature",
  "properties": {
    "addr:full":"804 Newnan Rd Carrollton GA 30117",
    "addr:housenumber":"804",
    "addr:postcode":"30117",
    "addr:street":"Newnan Rd",
    "iso:country":"US",
    "sg:address":"804 Newnan Rd",
    "sg:city":"Carrollton",
    "sg:classifiers":[
        {
            "category":"Retail",
            "subcategory":"Auto Repair",
            "type":"Services"
        }
    ],
    "sg:phone":"+1 770 834 6919",
    "sg:postcode":"30117",
    "sg:province":"GA",
    "sg:tags":[
        "body"
    ],
    "wof:name":"Phillips Paint & Body Shop",
    "wof:placetype":"venue"
},
  "geometry": {"coordinates":[-85.051367,33.571754],"type":"Point"}
}