{
  "type": "Feature",
  "properties": {
    "addr:full":"115 Fornum Dr Grovetown GA 30813",
    "addr:housenumber":"115",
    "addr:postcode":"30813",
    "addr:street":"Fornum Dr",
    "iso:country":"US",
    "sg:address":"115 Fornum Dr",
    "sg:city":"Grovetown",
    "sg:classifiers":[
        {
            "category":"Wholesale",
            "subcategory":"Vending Machines",
            "type":"Manufacturing & Wholesale Goods"
        }
    ],
    "sg:phone":"+1 706 863 6109",
    "sg:postcode":"30813",
    "sg:province":"GA",
    "sg:tags":[
        "operator"
    ],
    "wof:name":"Good Tasting Vending",
    "wof:placetype":"venue"
},
  "geometry": {"coordinates":[-82.20979,33.452504],"type":"Point"}
}