{
  "type": "Feature",
  "properties": {
    "addr:full":"4467 Hunters Way Stone Mountain GA 30083",
    "addr:housenumber":"4467",
    "addr:postcode":"30083",
    "addr:street":"Hunters Way",
    "iso:country":"US",
    "sg:address":"4467 Hunters Way",
    "sg:city":"Stone Mountain",
    "sg:classifiers":[
        {
            "category":"Professional",
            "subcategory":"Engineering",
            "type":"Services"
        }
    ],
    "sg:phone":"+1 404 644 6660",
    "sg:postcode":"30083",
    "sg:province":"GA",
    "sg:tags":[
        "engineer"
    ],
    "wof:name":"Adevans",
    "wof:placetype":"venue"
},
  "geometry": {"coordinates":[-84.204522,33.812327],"type":"Point"}
}