{
  "type": "Feature",
  "properties": {
    "iso:country":"US",
    "sg:address":"2710 Sandalwood Dr",
    "sg:city":"Atlanta",
    "sg:classifiers":[
        {
            "category":"Social Services",
            "type":"Services"
        }
    ],
    "sg:phone":"+1 770 352 0707",
    "sg:postcode":"30350",
    "sg:province":"GA",
    "wof:name":"African Leadership Merit Award",
    "wof:placetype":"venue"
},
  "geometry": {"coordinates":[-84.344596,33.99684],"type":"Point"}
}