{
  "type": "Feature",
  "properties": {
    "iso:country":"US",
    "sg:address":"396 Cotillion Dr",
    "sg:city":"Stockbridge",
    "sg:classifiers":[
        {
            "category":"Building & Trades",
            "subcategory":"Landscaping Services",
            "type":"Services"
        }
    ],
    "sg:phone":"+1 770 389 6515",
    "sg:postcode":"30281",
    "sg:province":"GA",
    "wof:name":"Quality Landscape & Lawn Mntnc",
    "wof:placetype":"venue"
},
  "geometry": {"coordinates":[-84.225335,33.6135],"type":"Point"}
}