{
  "type": "Feature",
  "properties": {
    "addr:full":"4974 Austell Rd Austell GA 30106",
    "addr:housenumber":"4974",
    "addr:postcode":"30106",
    "addr:street":"Austell Rd",
    "iso:country":"US",
    "sg:address":"4974 Austell Rd",
    "sg:city":"Austell",
    "sg:classifiers":[
        {
            "category":"Banks & Credit Unions",
            "subcategory":"Bank",
            "type":"Services"
        }
    ],
    "sg:phone":"+1 770 944 1744",
    "sg:postcode":"30106",
    "sg:province":"GA",
    "sg:tags":[
        "broker",
        "mortgage"
    ],
    "wof:name":"Kalb Mortgage",
    "wof:placetype":"venue"
},
  "geometry": {"coordinates":[-84.611878,33.833619],"type":"Point"}
}