{
  "type": "Feature",
  "properties": {
    "addr:full":"1522 Telfair St Dublin GA 31021",
    "addr:housenumber":"1522",
    "addr:postcode":"31021",
    "addr:street":"Telfair St",
    "iso:country":"US",
    "sg:address":"1522 Telfair St",
    "sg:city":"Dublin",
    "sg:classifiers":[
        {
            "category":"Food & Beverages",
            "subcategory":"Groceries & Convenience Stores",
            "type":"Retail Goods"
        }
    ],
    "sg:phone":"+1 478 275 7988",
    "sg:postcode":"31021",
    "sg:province":"GA",
    "wof:name":"A & W Convenience Store",
    "wof:placetype":"venue"
},
  "geometry": {"coordinates":[-82.918167,32.52213],"type":"Point"}
}