{
  "type": "Feature",
  "properties": {
    "addr:full":"3082 Old Mesena Rd Mesena GA 30824",
    "addr:housenumber":"3082",
    "addr:postcode":"30824",
    "addr:street":"Old Mesena Rd",
    "iso:country":"US",
    "sg:address":"3082 Old Mesena Rd",
    "sg:city":"Mesena",
    "sg:classifiers":[
        {
            "category":"Wholesale",
            "subcategory":"Auto Parts",
            "type":"Manufacturing & Wholesale Goods"
        }
    ],
    "sg:phone":"+1 706 595 7868",
    "sg:postcode":"30824",
    "sg:province":"GA",
    "sg:tags":[
        "automobile"
    ],
    "wof:name":"Youong's Auto Recyclers",
    "wof:placetype":"venue"
},
  "geometry": {"coordinates":[-82.58702099999999,33.45612],"type":"Point"}
}