{
  "type": "Feature",
  "properties": {
    "iso:country":"US",
    "sg:address":"40 S Scott St",
    "sg:city":"Camilla",
    "sg:classifiers":[
        {
            "category":"Personal",
            "subcategory":"Beauty Salon",
            "type":"Services"
        }
    ],
    "sg:phone":"+1 229 336 0900",
    "sg:postcode":"31730",
    "sg:province":"GA",
    "sg:tags":[
        "shop"
    ],
    "wof:name":"Nail Camilla",
    "wof:placetype":"venue"
},
  "geometry": {"coordinates":[-84.210577,31.229817],"type":"Point"}
}