{
  "type": "Feature",
  "properties": {
    "addr:full":"102 E Hall St Thomson GA 30824",
    "addr:housenumber":"102",
    "addr:postcode":"30824",
    "addr:street":"E Hall St",
    "iso:country":"US",
    "sg:address":"102 E Hall St",
    "sg:city":"Thomson",
    "sg:classifiers":[
        {
            "category":"Professional",
            "subcategory":"Lawyer & Legal Services",
            "type":"Services"
        }
    ],
    "sg:phone":"+1 706 597 8880",
    "sg:postcode":"30824",
    "sg:province":"GA",
    "wof:name":"Atkins Law Office",
    "wof:placetype":"venue"
},
  "geometry": {"coordinates":[-82.502017,33.469394],"type":"Point"}
}