{
  "type": "Feature",
  "properties": {
    "addr:full":"1406 E Jackson St Thomasville GA 31792",
    "addr:housenumber":"1406",
    "addr:postcode":"31792",
    "addr:street":"E Jackson St",
    "iso:country":"US",
    "sg:address":"1406 E Jackson St",
    "sg:city":"Thomasville",
    "sg:classifiers":[
        {
            "category":"Shopping",
            "subcategory":"Discount & Variety Stores",
            "type":"Retail Goods"
        },
        {
            "category":"Shopping",
            "subcategory":"Department Store",
            "type":"Retail Goods"
        }
    ],
    "sg:phone":"+1 229 558 9808",
    "sg:postcode":"31792",
    "sg:province":"GA",
    "sg:tags":[
        "shop"
    ],
    "wof:name":"Family Dollar Stores",
    "wof:placetype":"venue"
},
  "geometry": {"coordinates":[-83.955905,30.85415],"type":"Point"}
}