{
  "type": "Feature",
  "properties": {
    "iso:country":"US",
    "sg:address":"1594 Dellwood Cir",
    "sg:city":"Morrow",
    "sg:classifiers":[
        {
            "category":"Food & Beverages",
            "subcategory":"Groceries & Convenience Stores",
            "type":"Retail Goods"
        }
    ],
    "sg:phone":"+1 404 361 7786",
    "sg:postcode":"30260",
    "sg:province":"GA",
    "sg:tags":[
        "alcoholic"
    ],
    "wof:name":"Lake City Grocery Store",
    "wof:placetype":"venue"
},
  "geometry": {"coordinates":[-84.337355,33.605932],"type":"Point"}
}