{
  "type": "Feature",
  "properties": {
    "addr:full":"452 Airways Ave Savannah GA 31408",
    "addr:housenumber":"452",
    "addr:postcode":"31408",
    "addr:street":"Airways Ave",
    "iso:country":"US",
    "sg:address":"452 Airways Ave",
    "sg:city":"Savannah",
    "sg:classifiers":[
        {
            "category":"Autos & Motor Vehicles",
            "subcategory":"Automobile Sales",
            "type":"Retail Goods"
        },
        {
            "category":"Retail",
            "subcategory":"Auto Rental",
            "type":"Services"
        }
    ],
    "sg:phone":"+1 912 964 0171",
    "sg:postcode":"31408",
    "sg:province":"GA",
    "sg:tags":[
        "truck",
        "leasing",
        "car"
    ],
    "sg:website":"http://www.enterprise.com/car_rental/deeplinkmap.do?gpbr=267A&bid=004&cnty=US&arc=YPTRL01&cm_mmc=Yellowpages.com-_-IYP-_-Tradelisting-_-branch",
    "wof:name":"Enterprise Rent-A-Car",
    "wof:placetype":"venue"
},
  "geometry": {"coordinates":[-81.21673,32.138161],"type":"Point"}
}