{
  "type": "Feature",
  "properties": {
    "iso:country":"US",
    "sg:address":"2514 Ortega Way",
    "sg:city":"Atlanta",
    "sg:classifiers":[
        {
            "category":"Professional",
            "subcategory":"Lawyer & Legal Services",
            "type":"Services"
        }
    ],
    "sg:phone":"+1 678 205 5330",
    "sg:postcode":"30341",
    "sg:province":"GA",
    "wof:name":"Law Offices of W Bryant Green",
    "wof:placetype":"venue"
},
  "geometry": {"coordinates":[-84.28730899999999,33.881967],"type":"Point"}
}