{
  "type": "Feature",
  "properties": {
    "iso:country":"US",
    "sg:address":"1135 Prince Ave",
    "sg:city":"Athens",
    "sg:classifiers":[
        {
            "category":"Health Services",
            "subcategory":"Chiropractor",
            "type":"Services"
        }
    ],
    "sg:phone":"+1 706 543 2584",
    "sg:postcode":"30606",
    "sg:province":"GA",
    "wof:name":"Stewart Clinic",
    "wof:placetype":"venue"
},
  "geometry": {"coordinates":[-83.397401,33.962312],"type":"Point"}
}