{
  "type": "Feature",
  "properties": {
    "addr:full":"4530 Nelson Brogdon Blvd Buford GA 30518",
    "addr:housenumber":"4530",
    "addr:postcode":"30518",
    "addr:street":"Nelson Brogdon Blvd",
    "iso:country":"US",
    "sg:address":"4530 Nelson Brogdon Blvd",
    "sg:city":"Buford",
    "sg:classifiers":[
        {
            "category":"Manufacturing",
            "subcategory":"Furniture",
            "type":"Manufacturing & Wholesale Goods"
        }
    ],
    "sg:phone":"+1 770 271 7280",
    "sg:postcode":"30518",
    "sg:province":"GA",
    "sg:tags":[
        "building",
        "public",
        "mfg"
    ],
    "wof:name":"Virco Inc",
    "wof:placetype":"venue"
},
  "geometry": {"coordinates":[-84.018021,34.09926],"type":"Point"}
}