{
  "type": "Feature",
  "properties": {
    "iso:country":"US",
    "sg:address":"900 S Troup St",
    "sg:city":"Valdosta",
    "sg:classifiers":[
        {
            "category":"Social Services",
            "type":"Services"
        }
    ],
    "sg:phone":"+1 229 245 8820",
    "sg:postcode":"31601",
    "sg:province":"GA",
    "wof:name":"Lowndes County Nutrition Site",
    "wof:placetype":"venue"
},
  "geometry": {"coordinates":[-83.268714,30.820634],"type":"Point"}
}