{
  "type": "Feature",
  "properties": {
    "iso:country":"US",
    "sg:address":"1415 Stoney Field Pl",
    "sg:city":"Lawrenceville",
    "sg:classifiers":[
        {
            "category":"Professional",
            "subcategory":"Business Services",
            "type":"Services"
        }
    ],
    "sg:phone":"+1 770 237 3040",
    "sg:postcode":"30043",
    "sg:province":"GA",
    "wof:name":"Sid Lutz Sales",
    "wof:placetype":"venue"
},
  "geometry": {"coordinates":[-83.964423,34.017559],"type":"Point"}
}