{
  "type": "Feature",
  "properties": {
    "iso:country":"US",
    "sg:address":"1758 Century Blvd NE",
    "sg:city":"Atlanta",
    "sg:classifiers":[
        {
            "category":"Health Services",
            "subcategory":"Health Practitioner",
            "type":"Services"
        }
    ],
    "sg:phone":"+1 404 633 2000",
    "sg:postcode":"30345",
    "sg:province":"GA",
    "sg:tags":[
        "psychotherapist"
    ],
    "wof:name":"Darden Bynum",
    "wof:placetype":"venue"
},
  "geometry": {"coordinates":[-84.314925,33.845502],"type":"Point"}
}