{
  "type": "Feature",
  "properties": {
    "iso:country":"US",
    "sg:address":"6999 Roswell Rd",
    "sg:city":"Atlanta",
    "sg:classifiers":[
        {
            "category":"Shopping",
            "subcategory":"Musical Instruments",
            "type":"Retail Goods"
        }
    ],
    "sg:phone":"+1 770 351 6004",
    "sg:postcode":"30328",
    "sg:province":"GA",
    "sg:tags":[
        "piano"
    ],
    "wof:name":"North Metro Atlanta Piano",
    "wof:placetype":"venue"
},
  "geometry": {"coordinates":[-84.37215,33.943445],"type":"Point"}
}