{
  "type": "Feature",
  "properties": {
    "addr:full":"980 Johnson Ferry Rd NE # 450 Atlanta GA 30342",
    "addr:housenumber":"980",
    "addr:postcode":"30342",
    "addr:street":"Johnson Ferry Rd Ne # 450",
    "iso:country":"US",
    "sg:address":"980 Johnson Ferry Rd NE # 450",
    "sg:city":"Atlanta",
    "sg:classifiers":[
        {
            "category":"Health Services",
            "subcategory":"Doctor",
            "type":"Services"
        }
    ],
    "sg:phone":"+1 404 851 9576",
    "sg:postcode":"30342",
    "sg:province":"GA",
    "sg:tags":[
        "physician",
        "reconstructive",
        "surgeons",
        "cosmetic",
        "plastic",
        "surgeon",
        "surgery"
    ],
    "wof:name":"Northsd Cntr Fr Plstc Srgry",
    "wof:placetype":"venue"
},
  "geometry": {"coordinates":[-84.355908,33.907779],"type":"Point"}
}