{
  "type": "Feature",
  "properties": {
    "iso:country":"US",
    "sg:address":"55 Whitcher St",
    "sg:city":"Marietta",
    "sg:classifiers":[
        {
            "category":"Health Services",
            "subcategory":"Doctor",
            "type":"Services"
        }
    ],
    "sg:phone":"+1 770 427 3227",
    "sg:postcode":"30060",
    "sg:province":"GA",
    "sg:tags":[
        "physician",
        "surgeon"
    ],
    "wof:name":"Southeastern Gynecologic",
    "wof:placetype":"venue"
},
  "geometry": {"coordinates":[-84.55085699999999,33.967355],"type":"Point"}
}