{
  "type": "Feature",
  "properties": {
    "iso:country":"US",
    "sg:address":"206 Rogers St NE",
    "sg:city":"Atlanta",
    "sg:classifiers":[
        {
            "category":"Professional",
            "subcategory":"Business Services",
            "type":"Services"
        }
    ],
    "sg:phone":"+1 404 378 0119",
    "sg:postcode":"30317",
    "sg:province":"GA",
    "sg:tags":[
        "interior",
        "consultant",
        "design",
        "decorator"
    ],
    "wof:name":"Tackett Co",
    "wof:placetype":"venue"
},
  "geometry": {"coordinates":[-84.329232,33.759188],"type":"Point"}
}