{
  "type": "Feature",
  "properties": {
    "addr:full":"1165 Capri Ct Powder Springs GA 30127",
    "addr:housenumber":"1165",
    "addr:postcode":"30127",
    "addr:street":"Capri Ct",
    "iso:country":"US",
    "sg:address":"1165 Capri Ct",
    "sg:city":"Powder Springs",
    "sg:classifiers":[
        {
            "category":"Retail",
            "subcategory":"Funeral Services",
            "type":"Services"
        }
    ],
    "sg:phone":"+1 770 919 0007",
    "sg:postcode":"30127",
    "sg:province":"GA",
    "wof:name":"Baker Home Services Inc",
    "wof:placetype":"venue"
},
  "geometry": {"coordinates":[-84.655816,33.924456],"type":"Point"}
}