{
  "type": "Feature",
  "properties": {
    "addr:full":"189 Cobb Pkwy S Marietta GA 30067",
    "addr:housenumber":"189",
    "addr:postcode":"30067",
    "addr:street":"Cobb Pkwy S",
    "iso:country":"US",
    "sg:address":"189 Cobb Pkwy S",
    "sg:city":"Marietta",
    "sg:classifiers":[
        {
            "category":"Wholesale",
            "subcategory":"Toys & Hobbies",
            "type":"Manufacturing & Wholesale Goods"
        },
        {
            "category":"Wholesale",
            "subcategory":"Groceries",
            "type":"Manufacturing & Wholesale Goods"
        }
    ],
    "sg:phone":"+1 770 499 0059",
    "sg:postcode":"30067",
    "sg:province":"GA",
    "sg:tags":[
        "wholesaler"
    ],
    "wof:name":"Atlanta Wholesale Inc",
    "wof:placetype":"venue"
},
  "geometry": {"coordinates":[-84.517323,33.945284],"type":"Point"}
}