{
  "type": "Feature",
  "properties": {
    "iso:country":"US",
    "sg:address":"1489 Ridgewood Pl",
    "sg:city":"Lawrenceville",
    "sg:classifiers":[
        {
            "category":"Building & Trades",
            "subcategory":"Landscaping Services",
            "type":"Services"
        }
    ],
    "sg:phone":"+1 770 277 6740",
    "sg:postcode":"30043",
    "sg:province":"GA",
    "wof:name":"Mosley Lawn Svc",
    "wof:placetype":"venue"
},
  "geometry": {"coordinates":[-83.985355,34.006388],"type":"Point"}
}