{
  "type": "Feature",
  "properties": {
    "addr:full":"1784 Holly Springs Rd Marietta GA 30062",
    "addr:housenumber":"1784",
    "addr:postcode":"30062",
    "addr:street":"Holly Springs Rd",
    "iso:country":"US",
    "sg:address":"1784 Holly Springs Rd",
    "sg:city":"Marietta",
    "sg:classifiers":[
        {
            "category":"Food & Beverages",
            "subcategory":"Groceries & Convenience Stores",
            "type":"Retail Goods"
        },
        {
            "category":"Professional",
            "type":"Services"
        }
    ],
    "sg:phone":"+1 770 361 2772",
    "sg:postcode":"30062",
    "sg:province":"GA",
    "wof:name":"Best Food Svcs",
    "wof:placetype":"venue"
},
  "geometry": {"coordinates":[-84.47730900000001,33.992763],"type":"Point"}
}