{
  "type": "Feature",
  "properties": {
    "addr:full":"6595 Clarks Mill Rd Louisville GA 30434",
    "addr:housenumber":"6595",
    "addr:postcode":"30434",
    "addr:street":"Clarks Mill Rd",
    "iso:country":"US",
    "sg:address":"6595 Clarks Mill Rd",
    "sg:city":"Louisville",
    "sg:classifiers":[
        {
            "category":"Travel",
            "subcategory":"Campground",
            "type":"Entertainment"
        }
    ],
    "sg:phone":"+1 478 625 1222",
    "sg:postcode":"30434",
    "sg:province":"GA",
    "sg:tags":[
        "camp"
    ],
    "wof:name":"Dye's Fish Camp",
    "wof:placetype":"venue"
},
  "geometry": {"coordinates":[-82.47004699999999,33.077687],"type":"Point"}
}