{
  "type": "Feature",
  "properties": {
    "addr:full":"1191 Commerce Dr Morrow GA 30260",
    "addr:housenumber":"1191",
    "addr:postcode":"30260",
    "addr:street":"Commerce Dr",
    "iso:country":"US",
    "sg:address":"1191 Commerce Dr",
    "sg:city":"Morrow",
    "sg:classifiers":[
        {
            "category":"Professional",
            "type":"Services"
        }
    ],
    "sg:phone":"+1 678 422 4895",
    "sg:postcode":"30260",
    "sg:province":"GA",
    "wof:name":"Tritech Services",
    "wof:placetype":"venue"
},
  "geometry": {"coordinates":[-84.35298299999999,33.566867],"type":"Point"}
}