{
  "type": "Feature",
  "properties": {
    "iso:country":"US",
    "sg:address":"503 S Broad St",
    "sg:city":"Toccoa",
    "sg:classifiers":[
        {
            "category":"Taxi",
            "type":"Transportation"
        }
    ],
    "sg:phone":"+1 706 886 2839",
    "sg:postcode":"30577",
    "sg:province":"GA",
    "sg:tags":[
        "taxicab"
    ],
    "wof:name":"Grey Cab Co",
    "wof:placetype":"venue"
},
  "geometry": {"coordinates":[-83.332835,34.573486],"type":"Point"}
}