{
  "type": "Feature",
  "properties": {
    "iso:country":"US",
    "sg:address":"23 Matt Dillon Rd",
    "sg:city":"Tallapoosa",
    "sg:classifiers":[
        {
            "category":"Shopping",
            "subcategory":"Computers & Home Electronics",
            "type":"Retail Goods"
        }
    ],
    "sg:phone":"+1 770 646 2917",
    "sg:postcode":"30176",
    "sg:province":"GA",
    "sg:tags":[
        "television",
        "radio"
    ],
    "wof:name":"Jay's TV Repair",
    "wof:placetype":"venue"
},
  "geometry": {"coordinates":[-85.211613,33.789921],"type":"Point"}
}