{
  "type": "Feature",
  "properties": {
    "iso:country":"US",
    "sg:address":"2600 Lawrenceville Hwy",
    "sg:city":"Lawrenceville",
    "sg:classifiers":[
        {
            "category":"Freight",
            "type":"Transportation"
        }
    ],
    "sg:phone":"+1 770 921 3805",
    "sg:postcode":"30044",
    "sg:province":"GA",
    "sg:tags":[
        "commercial",
        "storage"
    ],
    "wof:name":"Gwinnett Self Storage",
    "wof:placetype":"venue"
},
  "geometry": {"coordinates":[-84.072171,33.923469],"type":"Point"}
}