{
  "type": "Feature",
  "properties": {
    "iso:country":"US",
    "sg:address":"2346 Wisteria Dr SW",
    "sg:city":"Snellville",
    "sg:classifiers":[
        {
            "category":"Banks & Credit Unions",
            "subcategory":"Bank",
            "type":"Services"
        }
    ],
    "sg:phone":"+1 770 982 4139",
    "sg:postcode":"30078",
    "sg:province":"GA",
    "sg:tags":[
        "loan",
        "real estate"
    ],
    "wof:name":"Homebanc",
    "wof:placetype":"venue"
},
  "geometry": {"coordinates":[-84.013459,33.85856],"type":"Point"}
}