{
  "type": "Feature",
  "properties": {
    "addr:full":"47 Carrington Dr Cartersville GA 30120",
    "addr:housenumber":"47",
    "addr:postcode":"30120",
    "addr:street":"Carrington Dr",
    "iso:country":"US",
    "sg:address":"47 Carrington Dr",
    "sg:city":"Cartersville",
    "sg:classifiers":[
        {
            "category":"Shopping",
            "subcategory":"Computers & Home Electronics",
            "type":"Retail Goods"
        }
    ],
    "sg:phone":"+1 678 721 6990",
    "sg:postcode":"30120",
    "sg:province":"GA",
    "sg:tags":[
        "equipment",
        "satellite",
        "system"
    ],
    "wof:name":"Install Sat",
    "wof:placetype":"venue"
},
  "geometry": {"coordinates":[-84.822733,34.138529],"type":"Point"}
}