{
  "type": "Feature",
  "properties": {
    "addr:full":"3450 Velma Dr Powder Springs GA 30127",
    "addr:housenumber":"3450",
    "addr:postcode":"30127",
    "addr:street":"Velma Dr",
    "iso:country":"US",
    "sg:address":"3450 Velma Dr",
    "sg:city":"Powder Springs",
    "sg:classifiers":[
        {
            "category":"Professional",
            "subcategory":"Computer Services",
            "type":"Services"
        }
    ],
    "sg:phone":"+1 678 570 7750",
    "sg:postcode":"30127",
    "sg:province":"GA",
    "sg:tags":[
        "datum"
    ],
    "wof:name":"Now You Know Inc",
    "wof:placetype":"venue"
},
  "geometry": {"coordinates":[-84.657746,33.907675],"type":"Point"}
}