{
  "type": "Feature",
  "properties": {
    "addr:full":"1320 Village Oaks Ln Lawrenceville GA 30043",
    "addr:housenumber":"1320",
    "addr:postcode":"30043",
    "addr:street":"Village Oaks Ln",
    "iso:country":"US",
    "sg:address":"1320 Village Oaks Ln",
    "sg:city":"Lawrenceville",
    "sg:classifiers":[
        {
            "category":"Wholesale",
            "subcategory":"Vending Machines",
            "type":"Manufacturing & Wholesale Goods"
        }
    ],
    "sg:phone":"+1 404 661 9524",
    "sg:postcode":"30043",
    "sg:province":"GA",
    "wof:name":"Tempting Treats Vending Svc",
    "wof:placetype":"venue"
},
  "geometry": {"coordinates":[-83.971144,34.004379],"type":"Point"}
}