{
  "type": "Feature",
  "properties": {
    "iso:country":"US",
    "sg:address":"3920 Arkwright Rd",
    "sg:city":"Macon",
    "sg:classifiers":[
        {
            "category":"Health Services",
            "subcategory":"Clinic",
            "type":"Services"
        }
    ],
    "sg:phone":"+1 478 314 2400",
    "sg:postcode":"31210",
    "sg:province":"GA",
    "sg:tags":[
        "organization",
        "managed",
        "care"
    ],
    "wof:name":"Secure Health Plans GA LLC",
    "wof:placetype":"venue"
},
  "geometry": {"coordinates":[-83.686787,32.903293],"type":"Point"}
}