{
  "type": "Feature",
  "properties": {
    "addr:full":"2735 Loganville Hwy SW Loganville GA 30052",
    "addr:housenumber":"2735",
    "addr:postcode":"30052",
    "addr:street":"Loganville Hwy Sw",
    "iso:country":"US",
    "sg:address":"2735 Loganville Hwy SW",
    "sg:city":"Loganville",
    "sg:classifiers":[
        {
            "category":"Banks & Credit Unions",
            "subcategory":"Bank",
            "type":"Services"
        }
    ],
    "sg:phone":"+1 770 682 8825",
    "sg:postcode":"30052",
    "sg:province":"GA",
    "wof:name":"Washington Mutual",
    "wof:placetype":"venue"
},
  "geometry": {"coordinates":[-83.937472,33.880488],"type":"Point"}
}