{
  "type": "Feature",
  "properties": {
    "addr:full":"157 Mountain Tops Rd Blue Ridge GA 30513",
    "addr:housenumber":"157",
    "addr:postcode":"30513",
    "addr:street":"Mountain Tops Rd",
    "iso:country":"US",
    "sg:address":"157 Mountain Tops Rd",
    "sg:city":"Blue Ridge",
    "sg:classifiers":[
        {
            "category":"Building & Trades",
            "subcategory":"Construction",
            "type":"Services"
        }
    ],
    "sg:phone":"+1 706 632 8387",
    "sg:postcode":"30513",
    "sg:province":"GA",
    "sg:tags":[
        "concrete",
        "contractor"
    ],
    "wof:name":"Unified Enterprises Inc",
    "wof:placetype":"venue"
},
  "geometry": {"coordinates":[-84.34057,34.856768],"type":"Point"}
}