{
  "type": "Feature",
  "properties": {
    "addr:full":"1776 McKenzie Dr Decatur GA 30032",
    "addr:housenumber":"1776",
    "addr:postcode":"30032",
    "addr:street":"Mckenzie Dr",
    "iso:country":"US",
    "sg:address":"1776 McKenzie Dr",
    "sg:city":"Decatur",
    "sg:classifiers":[
        {
            "category":"Professional",
            "subcategory":"Employment Agencies",
            "type":"Services"
        }
    ],
    "sg:phone":"+1 404 288 8824",
    "sg:postcode":"30032",
    "sg:province":"GA",
    "sg:tags":[
        "consultant",
        "search",
        "executive"
    ],
    "wof:name":"Edwards Consulting",
    "wof:placetype":"venue"
},
  "geometry": {"coordinates":[-84.25736999999999,33.7426],"type":"Point"}
}