{
  "type": "Feature",
  "properties": {
    "iso:country":"US",
    "sg:address":"2465 Enon Rd SW",
    "sg:city":"Atlanta",
    "sg:classifiers":[
        {
            "category":"Building & Trades",
            "subcategory":"Construction",
            "type":"Services"
        }
    ],
    "sg:phone":"+1 404 629 6220",
    "sg:postcode":"30331",
    "sg:province":"GA",
    "sg:tags":[
        "contractor"
    ],
    "wof:name":"Lee Construction & Consulting",
    "wof:placetype":"venue"
},
  "geometry": {"coordinates":[-84.55957600000001,33.689643],"type":"Point"}
}