{
  "type": "Feature",
  "properties": {
    "addr:full":"647 Lakes Blvd Lake Park GA 31636",
    "addr:housenumber":"647",
    "addr:postcode":"31636",
    "addr:street":"Lakes Blvd",
    "iso:country":"US",
    "sg:address":"647 Lakes Blvd",
    "sg:city":"Lake Park",
    "sg:classifiers":[
        {
            "category":"Health Services",
            "subcategory":"Chiropractor",
            "type":"Services"
        }
    ],
    "sg:phone":"+1 229 559 1734",
    "sg:postcode":"31636",
    "sg:province":"GA",
    "wof:name":"Wright Chiropractic",
    "wof:placetype":"venue"
},
  "geometry": {"coordinates":[-83.209096,30.684183],"type":"Point"}
}