{
  "type": "Feature",
  "properties": {
    "addr:full":"458 Brown Farm Rd SW Calhoun GA 30701",
    "addr:housenumber":"458",
    "addr:postcode":"30701",
    "addr:street":"Brown Farm Rd Sw",
    "iso:country":"US",
    "sg:address":"458 Brown Farm Rd SW",
    "sg:city":"Calhoun",
    "sg:classifiers":[
        {
            "category":"Utilities",
            "subcategory":"Mobile Phone",
            "type":"Services"
        }
    ],
    "sg:phone":"+1 706 625 5645",
    "sg:postcode":"30701",
    "sg:province":"GA",
    "sg:tags":[
        "telephone",
        "cellular"
    ],
    "wof:name":"M J Cellular",
    "wof:placetype":"venue"
},
  "geometry": {"coordinates":[-84.97481999999999,34.472219],"type":"Point"}
}