{
  "type": "Feature",
  "properties": {
    "addr:full":"100 Jacee Cir Canton GA 30115",
    "addr:housenumber":"100",
    "addr:postcode":"30115",
    "addr:street":"Jacee Cir",
    "iso:country":"US",
    "sg:address":"100 Jacee Cir",
    "sg:city":"Canton",
    "sg:classifiers":[
        {
            "category":"Retail",
            "subcategory":"Repair Shop",
            "type":"Services"
        }
    ],
    "sg:phone":"+1 770 479 0778",
    "sg:postcode":"30115",
    "sg:province":"GA",
    "sg:tags":[
        "reupholstery",
        "furniture"
    ],
    "wof:name":"Scott Upholstery",
    "wof:placetype":"venue"
},
  "geometry": {"coordinates":[-84.50751099999999,34.169252],"type":"Point"}
}