{
  "type": "Feature",
  "properties": {
    "addr:full":"4274 N Valdosta Rd Valdosta GA 31602",
    "addr:housenumber":"4274",
    "addr:postcode":"31602",
    "addr:street":"N Valdosta Rd",
    "iso:country":"US",
    "sg:address":"4274 N Valdosta Rd",
    "sg:city":"Valdosta",
    "sg:classifiers":[
        {
            "category":"Health Services",
            "subcategory":"Clinic",
            "type":"Services"
        }
    ],
    "sg:phone":"+1 229 242 1234",
    "sg:postcode":"31602",
    "sg:province":"GA",
    "sg:tags":[
        "welfare"
    ],
    "wof:name":"Js Medical Informatics",
    "wof:placetype":"venue"
},
  "geometry": {"coordinates":[-83.335312,30.896761],"type":"Point"}
}