{
  "type": "Feature",
  "properties": {
    "addr:full":"1133 Church St SE Covington GA 30014",
    "addr:housenumber":"1133",
    "addr:postcode":"30014",
    "addr:street":"Church St Se",
    "iso:country":"US",
    "sg:address":"1133 Church St SE",
    "sg:city":"Covington",
    "sg:classifiers":[
        {
            "category":"Place Of Worship",
            "type":"Public Place"
        }
    ],
    "sg:phone":"+1 678 212 0331",
    "sg:postcode":"30014",
    "sg:province":"GA",
    "sg:tags":[
        "church"
    ],
    "wof:name":"Church St Lofts",
    "wof:placetype":"venue"
},
  "geometry": {"coordinates":[-83.859436,33.595804],"type":"Point"}
}