{
  "type": "Feature",
  "properties": {
    "iso:country":"US",
    "sg:address":"2636 Martin Luther King Jr Dr SW Ste 6",
    "sg:city":"Atlanta",
    "sg:classifiers":[
        {
            "category":"Coffee & Tea",
            "type":"Food & Drink"
        },
        {
            "category":"Restaurant",
            "type":"Food & Drink"
        }
    ],
    "sg:phone":"+1 404 696 8449",
    "sg:postcode":"30311",
    "sg:province":"GA",
    "sg:tags":[
        "barbecue",
        "espresso"
    ],
    "wof:name":"Cafe Buffalo Wings",
    "wof:placetype":"venue"
},
  "geometry": {"coordinates":[-84.473378,33.753733],"type":"Point"}
}