{
  "type": "Feature",
  "properties": {
    "addr:full":"2374 Briarcliff Rd NE Atlanta GA 30329",
    "addr:housenumber":"2374",
    "addr:postcode":"30329",
    "addr:street":"Briarcliff Rd Ne",
    "iso:country":"US",
    "sg:address":"2374 Briarcliff Rd NE",
    "sg:city":"Atlanta",
    "sg:classifiers":[
        {
            "category":"Building & Trades",
            "subcategory":"Locksmith",
            "type":"Services"
        }
    ],
    "sg:phone":"+1 866 226 0573",
    "sg:postcode":"30329",
    "sg:province":"GA",
    "sg:tags":[
        "key"
    ],
    "wof:name":"A 1 Lock & Locksmith",
    "wof:placetype":"venue"
},
  "geometry": {"coordinates":[-84.334591,33.824107],"type":"Point"}
}