{
  "type": "Feature",
  "properties": {
    "addr:full":"431 W Ponce de Leon Ave Decatur GA 30030",
    "addr:housenumber":"431",
    "addr:postcode":"30030",
    "addr:street":"W Ponce De Leon Ave",
    "iso:country":"US",
    "sg:address":"431 W Ponce de Leon Ave",
    "sg:city":"Decatur",
    "sg:classifiers":[
        {
            "category":"Home & Garden",
            "subcategory":"Furniture",
            "type":"Retail Goods"
        }
    ],
    "sg:phone":"+1 404 371 1991",
    "sg:postcode":"30030",
    "sg:province":"GA",
    "sg:tags":[
        "interior",
        "design",
        "se",
        "store",
        "accessory"
    ],
    "wof:name":"Stanton Designs",
    "wof:placetype":"venue"
},
  "geometry": {"coordinates":[-84.30324400000001,33.775738],"type":"Point"}
}