{
  "type": "Feature",
  "properties": {
    "addr:full":"13 Downshire Cir Decatur GA 30033",
    "addr:housenumber":"13",
    "addr:postcode":"30033",
    "addr:street":"Downshire Cir",
    "iso:country":"US",
    "sg:address":"13 Downshire Cir",
    "sg:city":"Decatur",
    "sg:classifiers":[
        {
            "category":"Professional",
            "subcategory":"Lawyer & Legal Services",
            "type":"Services"
        }
    ],
    "sg:phone":"+1 404 248 3929",
    "sg:postcode":"30033",
    "sg:province":"GA",
    "wof:name":"Chesnut J David Atty",
    "wof:placetype":"venue"
},
  "geometry": {"coordinates":[-84.27582,33.836587],"type":"Point"}
}