{
  "type": "Feature",
  "properties": {
    "addr:full":"5445 Hwy 9 N Alpharetta GA 30004",
    "addr:housenumber":"5445",
    "addr:postcode":"30004",
    "addr:street":"Hwy 9 N",
    "iso:country":"US",
    "sg:address":"5445 Hwy 9 N",
    "sg:city":"Alpharetta",
    "sg:classifiers":[
        {
            "category":"Recreation",
            "type":"Entertainment"
        }
    ],
    "sg:phone":"+1 678 566 1934",
    "sg:postcode":"30004",
    "sg:province":"GA",
    "sg:tags":[
        "martial",
        "arts",
        "instruction"
    ],
    "wof:name":"Alpharetta Choong Sil Tae KWND",
    "wof:placetype":"venue"
},
  "geometry": {"coordinates":[-84.251836,34.151997],"type":"Point"}
}