{
  "type": "Feature",
  "properties": {
    "addr:full":"391 W Paces Ferry Rd NW Atlanta GA 30305",
    "addr:housenumber":"391",
    "addr:postcode":"30305",
    "addr:street":"W Paces Ferry Rd Nw",
    "iso:country":"US",
    "sg:address":"391 W Paces Ferry Rd NW",
    "sg:city":"Atlanta",
    "sg:classifiers":[
        {
            "category":"Community Center",
            "type":"Public Place"
        },
        {
            "category":"Government",
            "subcategory":"Office",
            "type":"Public Place"
        }
    ],
    "sg:phone":"+1 404 261 1776",
    "sg:postcode":"30305",
    "sg:province":"GA",
    "sg:tags":[
        "government-state",
        "recreation",
        "village",
        "township",
        "government-city"
    ],
    "wof:name":"Georgia Governor's Mansion",
    "wof:placetype":"venue"
},
  "geometry": {"coordinates":[-84.398335,33.844847],"type":"Point"}
}