{
  "type": "Feature",
  "properties": {
    "addr:full":"2906 Julia Dr Valdosta GA 31602",
    "addr:housenumber":"2906",
    "addr:postcode":"31602",
    "addr:street":"Julia Dr",
    "iso:country":"US",
    "sg:address":"2906 Julia Dr",
    "sg:city":"Valdosta",
    "sg:classifiers":[
        {
            "category":"Health Services",
            "subcategory":"Doctor",
            "type":"Services"
        }
    ],
    "sg:phone":"+1 229 244 4468",
    "sg:postcode":"31602",
    "sg:province":"GA",
    "sg:tags":[
        "physician",
        "surgeon"
    ],
    "wof:name":"Doctors Laboratory Inc",
    "wof:placetype":"venue"
},
  "geometry": {"coordinates":[-83.279034,30.875245],"type":"Point"}
}