{
  "type": "Feature",
  "properties": {
    "addr:full":"5091 Buford Hwy NE Atlanta GA 30340",
    "addr:housenumber":"5091",
    "addr:postcode":"30340",
    "addr:street":"Buford Hwy Ne",
    "iso:country":"US",
    "sg:address":"5091 Buford Hwy NE",
    "sg:city":"Atlanta",
    "sg:classifiers":[
        {
            "category":"Restaurant",
            "type":"Food & Drink"
        }
    ],
    "sg:phone":"+1 770 451 0192",
    "sg:postcode":"30340",
    "sg:province":"GA",
    "sg:tags":[
        "eating",
        "chinese"
    ],
    "sg:website":"www.littleszechuanchefkongs.com/",
    "wof:name":"Little Szechuan",
    "wof:placetype":"venue"
},
  "geometry": {"coordinates":[-84.285224,33.891106],"type":"Point"}
}