{
  "type": "Feature",
  "properties": {
    "addr:full":"421 W Marion Ave Lake Park GA 31636",
    "addr:housenumber":"421",
    "addr:postcode":"31636",
    "addr:street":"W Marion Ave",
    "iso:country":"US",
    "sg:address":"421 W Marion Ave",
    "sg:city":"Lake Park",
    "sg:classifiers":[
        {
            "category":"Organizations",
            "subcategory":"Religious Organization",
            "type":"Services"
        }
    ],
    "sg:phone":"+1 229 559 0410",
    "sg:postcode":"31636",
    "sg:province":"GA",
    "sg:tags":[
        "church"
    ],
    "sg:website":"www.lakeparkchurchofchrist.org",
    "wof:name":"Lake Park Church Of Christ",
    "wof:placetype":"venue"
},
  "geometry": {"coordinates":[-83.183543,30.685329],"type":"Point"}
}