{
  "type": "Feature",
  "properties": {
    "addr:full":"2407 Riverdale Rd Atlanta GA 30337",
    "addr:housenumber":"2407",
    "addr:postcode":"30337",
    "addr:street":"Riverdale Rd",
    "iso:country":"US",
    "sg:address":"2407 Riverdale Rd",
    "sg:city":"Atlanta",
    "sg:classifiers":[
        {
            "category":"Retail",
            "subcategory":"Auto Repair",
            "type":"Services"
        }
    ],
    "sg:phone":"+1 404 765 9427",
    "sg:postcode":"30337",
    "sg:province":"GA",
    "sg:tags":[
        "automotive"
    ],
    "wof:name":"Paso S Towing",
    "wof:placetype":"venue"
},
  "geometry": {"coordinates":[-84.46744700000001,33.634553],"type":"Point"}
}