{
  "type": "Feature",
  "properties": {
    "addr:full":"403 Cherokee St Marietta GA 30060",
    "addr:housenumber":"403",
    "addr:postcode":"30060",
    "addr:street":"Cherokee St",
    "iso:country":"US",
    "sg:address":"403 Cherokee St",
    "sg:city":"Marietta",
    "sg:classifiers":[
        {
            "category":"Professional",
            "subcategory":"Business Services",
            "type":"Services"
        }
    ],
    "sg:phone":"+1 770 422 7271",
    "sg:postcode":"30060",
    "sg:province":"GA",
    "sg:tags":[
        "interior",
        "designer"
    ],
    "wof:name":"Jvt Designs",
    "wof:placetype":"venue"
},
  "geometry": {"coordinates":[-84.54791,33.964718],"type":"Point"}
}