{
  "type": "Feature",
  "properties": {
    "iso:country":"US",
    "sg:address":"1518 Phoenix Blvd",
    "sg:city":"Atlanta",
    "sg:classifiers":[
        {
            "category":"Health Services",
            "subcategory":"Doctor",
            "type":"Services"
        }
    ],
    "sg:phone":"+1 770 475 0077",
    "sg:postcode":"30349",
    "sg:province":"GA",
    "sg:tags":[
        "obstetrician",
        "gynecologist"
    ],
    "wof:name":"Alpharetta Women's Healthcare",
    "wof:placetype":"venue"
},
  "geometry": {"coordinates":[-84.439697,33.614498],"type":"Point"}
}