{
  "type": "Feature",
  "properties": {
    "iso:country":"US",
    "sg:address":"2533 River Knoll Dr SW",
    "sg:city":"Lilburn",
    "sg:classifiers":[
        {
            "category":"Professional",
            "subcategory":"Business Services",
            "type":"Services"
        }
    ],
    "sg:phone":"+1 770 985 9884",
    "sg:postcode":"30047",
    "sg:province":"GA",
    "wof:name":"S&W Enterprises",
    "wof:placetype":"venue"
},
  "geometry": {"coordinates":[-84.08829299999999,33.817546],"type":"Point"}
}