{
  "type": "Feature",
  "properties": {
    "addr:full":"8040 Lakemont Close Mcdonough GA 30253",
    "addr:housenumber":"8040",
    "addr:postcode":"30253",
    "addr:street":"Lakemont Close",
    "iso:country":"US",
    "sg:address":"8040 Lakemont Close",
    "sg:city":"Mcdonough",
    "sg:classifiers":[
        {
            "category":"Banks & Credit Unions",
            "subcategory":"Bank",
            "type":"Services"
        }
    ],
    "sg:phone":"+1 770 389 9188",
    "sg:postcode":"30253",
    "sg:province":"GA",
    "sg:tags":[
        "loan",
        "real estate"
    ],
    "sg:website":"www.mamci.com",
    "wof:name":"Metro Funding Inc",
    "wof:placetype":"venue"
},
  "geometry": {"coordinates":[-84.15463699999999,33.480486],"type":"Point"}
}