{
  "type": "Feature",
  "properties": {
    "iso:country":"US",
    "sg:address":"125 Jonesboro Rd",
    "sg:city":"Jonesboro",
    "sg:classifiers":[
        {
            "category":"Professional",
            "subcategory":"Business Services",
            "type":"Services"
        }
    ],
    "sg:phone":"+1 678 479 0689",
    "sg:postcode":"30236",
    "sg:province":"GA",
    "sg:tags":[
        "recording",
        "studio"
    ],
    "wof:name":"Pro South Recording Studios",
    "wof:placetype":"venue"
},
  "geometry": {"coordinates":[-84.351755,33.535928],"type":"Point"}
}