{
  "type": "Feature",
  "properties": {
    "addr:full":"1101 N Wheeler Ave Douglas GA 31533",
    "addr:housenumber":"1101",
    "addr:postcode":"31533",
    "addr:street":"N Wheeler Ave",
    "iso:country":"US",
    "sg:address":"1101 N Wheeler Ave",
    "sg:city":"Douglas",
    "sg:classifiers":[
        {
            "category":"Wholesale",
            "subcategory":"Machinery & Supplies",
            "type":"Manufacturing & Wholesale Goods"
        }
    ],
    "sg:phone":"+1 912 384 8805",
    "sg:postcode":"31533",
    "sg:province":"GA",
    "sg:tags":[
        "welding"
    ],
    "wof:name":"Airco Welding Supply Co",
    "wof:placetype":"venue"
},
  "geometry": {"coordinates":[-82.85748100000001,31.519339],"type":"Point"}
}