{
  "type": "Feature",
  "properties": {
    "iso:country":"US",
    "sg:address":"95 Mitchell Farm Rd",
    "sg:city":"Colbert",
    "sg:classifiers":[
        {
            "category":"Building & Trades",
            "subcategory":"Cleaning & Sanitation",
            "type":"Services"
        },
        {
            "category":"Professional",
            "subcategory":"Management & Consulting",
            "type":"Services"
        }
    ],
    "sg:phone":"+1 706 742 5611",
    "sg:postcode":"30628",
    "sg:province":"GA",
    "sg:tags":[
        "house",
        "retail",
        "direct",
        "sales"
    ],
    "wof:name":"Classic Maids Inc",
    "wof:placetype":"venue"
},
  "geometry": {"coordinates":[-83.19933399999999,33.987246],"type":"Point"}
}