{
  "type": "Feature",
  "properties": {
    "addr:full":"269 S Davis Rd Lagrange GA 30241",
    "addr:housenumber":"269",
    "addr:postcode":"30241",
    "addr:street":"S Davis Rd",
    "iso:country":"US",
    "sg:address":"269 S Davis Rd",
    "sg:city":"Lagrange",
    "sg:classifiers":[
        {
            "category":"Manufacturing",
            "subcategory":"Chemicals & Compounds",
            "type":"Manufacturing & Wholesale Goods"
        },
        {
            "category":"Professional",
            "subcategory":"Business Services",
            "type":"Services"
        },
        {
            "category":"Building & Trades",
            "subcategory":"Pest Control",
            "type":"Services"
        }
    ],
    "sg:phone":"+1 706 407 4602",
    "sg:postcode":"30241",
    "sg:province":"GA",
    "sg:tags":[
        "industrial",
        "supply",
        "services-commercial",
        "termite",
        "bee",
        "equipment",
        "repellent",
        "mothproofing",
        "barriers",
        "removal",
        "inspection",
        "bird"
    ],
    "sg:website":"http://www.terminix.com",
    "wof:name":"Terminix",
    "wof:placetype":"venue"
},
  "geometry": {"coordinates":[-85.020093,33.043282],"type":"Point"}
}