{
  "type": "Feature",
  "properties": {
    "iso:country":"US",
    "sg:address":"58 Willie Parks Rd",
    "sg:city":"Newnan",
    "sg:classifiers":[
        {
            "category":"Building & Trades",
            "subcategory":"Construction",
            "type":"Services"
        }
    ],
    "sg:phone":"+1 770 253 6723",
    "sg:postcode":"30263",
    "sg:province":"GA",
    "sg:tags":[
        "general",
        "contractor"
    ],
    "wof:name":"Dwight Parks Contracting",
    "wof:placetype":"venue"
},
  "geometry": {"coordinates":[-84.79073200000001,33.422976],"type":"Point"}
}