{
  "type": "Feature",
  "properties": {
    "addr:full":"2677 Buford Hwy Atlanta GA 30324",
    "addr:housenumber":"2677",
    "addr:postcode":"30324",
    "addr:street":"Buford Hwy",
    "iso:country":"US",
    "sg:address":"2677 Buford Hwy",
    "sg:city":"Atlanta",
    "sg:classifiers":[
        {
            "category":"Building & Trades",
            "subcategory":"Plumbing",
            "type":"Services"
        }
    ],
    "sg:phone":"+1 404 836 2781",
    "sg:postcode":"30324",
    "sg:province":"GA",
    "sg:tags":[
        "air",
        "conditioning",
        "contractor"
    ],
    "wof:name":"American Standard Inc",
    "wof:placetype":"venue"
},
  "geometry": {"coordinates":[-84.346251,33.828147],"type":"Point"}
}