{
  "type": "Feature",
  "properties": {
    "addr:full":"103 Oak Forest Ln Warner Robins GA 31088",
    "addr:housenumber":"103",
    "addr:postcode":"31088",
    "addr:street":"Oak Forest Ln",
    "iso:country":"US",
    "sg:address":"103 Oak Forest Ln",
    "sg:city":"Warner Robins",
    "sg:classifiers":[
        {
            "category":"Building & Trades",
            "subcategory":"Plumbing",
            "type":"Services"
        }
    ],
    "sg:phone":"+1 478 922 5267",
    "sg:postcode":"31088",
    "sg:province":"GA",
    "sg:tags":[
        "heat",
        "pump",
        "contractor"
    ],
    "wof:name":"OHearn Heating & Air Condtng",
    "wof:placetype":"venue"
},
  "geometry": {"coordinates":[-83.634888,32.598641],"type":"Point"}
}