{
  "type": "Feature",
  "properties": {
    "addr:full":"1225 Kennestone Cir Marietta GA 30066",
    "addr:housenumber":"1225",
    "addr:postcode":"30066",
    "addr:street":"Kennestone Cir",
    "iso:country":"US",
    "sg:address":"1225 Kennestone Cir",
    "sg:city":"Marietta",
    "sg:classifiers":[
        {
            "category":"Manufacturing",
            "subcategory":"Printing",
            "type":"Manufacturing & Wholesale Goods"
        }
    ],
    "sg:phone":"+1 770 795 0000",
    "sg:postcode":"30066",
    "sg:province":"GA",
    "sg:tags":[
        "offset"
    ],
    "wof:name":"Reflections",
    "wof:placetype":"venue"
},
  "geometry": {"coordinates":[-84.55413299999999,33.982143],"type":"Point"}
}