{
  "type": "Feature",
  "properties": {
    "iso:country":"US",
    "sg:address":"231 Highbrook Rd",
    "sg:city":"Jesup",
    "sg:classifiers":[
        {
            "category":"Freight",
            "type":"Transportation"
        }
    ],
    "sg:phone":"+1 912 550 6048",
    "sg:postcode":"31545",
    "sg:province":"GA",
    "sg:tags":[
        "operator",
        "trucking"
    ],
    "wof:name":"Terry Trenerry Jr",
    "wof:placetype":"venue"
},
  "geometry": {"coordinates":[-81.86275999999999,31.650906],"type":"Point"}
}