{
  "type": "Feature",
  "properties": {
    "iso:country":"US",
    "sg:address":"4791 Macon Hwy",
    "sg:city":"Bishop",
    "sg:classifiers":[
        {
            "category":"Food & Beverages",
            "subcategory":"Groceries & Convenience Stores",
            "type":"Retail Goods"
        }
    ],
    "sg:phone":"+1 706 769 7215",
    "sg:postcode":"30621",
    "sg:province":"GA",
    "wof:name":"Golden Pantry Food Store",
    "wof:placetype":"venue"
},
  "geometry": {"coordinates":[-83.43540900000001,33.814439],"type":"Point"}
}