{
  "type": "Feature",
  "properties": {
    "iso:country":"US",
    "sg:address":"3001 Monroe Hwy",
    "sg:city":"Watkinsville",
    "sg:classifiers":[
        {
            "category":"Health Services",
            "subcategory":"Clinic",
            "type":"Services"
        }
    ],
    "sg:phone":"+1 770 725 9188",
    "sg:postcode":"30677",
    "sg:province":"GA",
    "wof:name":"Hieber Jeanette Dc",
    "wof:placetype":"venue"
},
  "geometry": {"coordinates":[-83.53125799999999,33.918789],"type":"Point"}
}