{
  "type": "Feature",
  "properties": {
    "iso:country":"US",
    "sg:address":"3451 Ernest W Barrett Pkwy NW Ste 170",
    "sg:city":"Marietta",
    "sg:phone":"+1 770 429 1929",
    "sg:postcode":"30064",
    "sg:province":"GA",
    "wof:name":"Cheryl Draa Interior Design",
    "wof:placetype":"venue"
},
  "geometry": {"coordinates":[-84.624054,33.946556],"type":"Point"}
}