{
  "type": "Feature",
  "properties": {
    "addr:full":"5435 Woodruff Farm Rd Columbus GA 31907",
    "addr:housenumber":"5435",
    "addr:postcode":"31907",
    "addr:street":"Woodruff Farm Rd",
    "iso:country":"US",
    "sg:address":"5435 Woodruff Farm Rd",
    "sg:city":"Columbus",
    "sg:classifiers":[
        {
            "category":"Cinema",
            "subcategory":"Movie Rental",
            "type":"Entertainment"
        }
    ],
    "sg:phone":"+1 706 568 6695",
    "sg:postcode":"31907",
    "sg:province":"GA",
    "sg:tags":[
        "video",
        "tape"
    ],
    "wof:name":"Prime Time Video",
    "wof:placetype":"venue"
},
  "geometry": {"coordinates":[-84.894087,32.513723],"type":"Point"}
}