{
  "type": "Feature",
  "properties": {
    "iso:country":"US",
    "sg:address":"926 Homewood Ct",
    "sg:city":"Decatur",
    "sg:classifiers":[
        {
            "category":"Professional",
            "subcategory":"Business Services",
            "type":"Services"
        }
    ],
    "sg:phone":"+1 404 634 5462",
    "sg:postcode":"30033",
    "sg:province":"GA",
    "wof:name":"Capley Enterprises Inc",
    "wof:placetype":"venue"
},
  "geometry": {"coordinates":[-84.284115,33.808674],"type":"Point"}
}