{
  "type": "Feature",
  "properties": {
    "addr:full":"3578 Five Forks Trickum Rd SW Lilburn GA 30047",
    "addr:housenumber":"3578",
    "addr:postcode":"30047",
    "addr:street":"Five Forks Trickum Rd Sw",
    "iso:country":"US",
    "sg:address":"3578 Five Forks Trickum Rd SW",
    "sg:city":"Lilburn",
    "sg:classifiers":[
        {
            "category":"Building & Trades",
            "subcategory":"Construction",
            "type":"Services"
        }
    ],
    "sg:phone":"+1 770 985 4343",
    "sg:postcode":"30047",
    "sg:province":"GA",
    "sg:tags":[
        "contractor"
    ],
    "wof:name":"Earthscapes LLC",
    "wof:placetype":"venue"
},
  "geometry": {"coordinates":[-84.079853,33.875665],"type":"Point"}
}