{
  "type": "Feature",
  "properties": {
    "addr:full":"3865 Washington Rd Augusta GA 30907",
    "addr:housenumber":"3865",
    "addr:postcode":"30907",
    "addr:street":"Washington Rd",
    "iso:country":"US",
    "sg:address":"3865 Washington Rd",
    "sg:city":"Augusta",
    "sg:classifiers":[
        {
            "category":"Fast Food",
            "type":"Food & Drink"
        },
        {
            "category":"Restaurant",
            "type":"Food & Drink"
        },
        {
            "category":"Food & Beverages",
            "subcategory":"Groceries & Convenience Stores",
            "type":"Retail Goods"
        }
    ],
    "sg:phone":"+1 706 854 1999",
    "sg:postcode":"30907",
    "sg:province":"GA",
    "sg:tags":[
        "shop",
        "sandwich",
        "take"
    ],
    "sg:website":"http://www.schlotzskys.com",
    "wof:name":"Schlotzsky's",
    "wof:placetype":"venue"
},
  "geometry": {"coordinates":[-82.09352800000001,33.511064],"type":"Point"}
}