{
  "type": "Feature",
  "properties": {
    "iso:country":"US",
    "sg:address":"3202 Bass St",
    "sg:city":"Brunswick",
    "sg:classifiers":[
        {
            "category":"Organizations",
            "subcategory":"Religious Organization",
            "type":"Services"
        }
    ],
    "sg:phone":"+1 912 265 5912",
    "sg:postcode":"31520",
    "sg:province":"GA",
    "wof:name":"Church of Christ of Latter",
    "wof:placetype":"venue"
},
  "geometry": {"coordinates":[-81.47426,31.185373],"type":"Point"}
}