{
  "type": "Feature",
  "properties": {
    "addr:full":"1255 Birkhall Dr Lawrenceville GA 30043",
    "addr:housenumber":"1255",
    "addr:postcode":"30043",
    "addr:street":"Birkhall Dr",
    "iso:country":"US",
    "sg:address":"1255 Birkhall Dr",
    "sg:city":"Lawrenceville",
    "sg:classifiers":[
        {
            "category":"Building & Trades",
            "subcategory":"Construction",
            "type":"Services"
        }
    ],
    "sg:phone":"+1 770 910 7740",
    "sg:postcode":"30043",
    "sg:province":"GA",
    "sg:tags":[
        "contractor"
    ],
    "wof:name":"Rng Construction",
    "wof:placetype":"venue"
},
  "geometry": {"coordinates":[-84.061746,34.003595],"type":"Point"}
}