{
  "type": "Feature",
  "properties": {
    "addr:full":"25 N Main St Statesboro GA 30458",
    "addr:housenumber":"25",
    "addr:postcode":"30458",
    "addr:street":"N Main St",
    "iso:country":"US",
    "sg:address":"25 N Main St",
    "sg:city":"Statesboro",
    "sg:classifiers":[
        {
            "category":"Shopping",
            "subcategory":"Baby Store",
            "type":"Retail Goods"
        }
    ],
    "sg:phone":"+1 912 764 9479",
    "sg:postcode":"30458",
    "sg:province":"GA",
    "sg:tags":[
        "children's",
        "infant",
        "wear"
    ],
    "wof:name":"Kids Korner Inc",
    "wof:placetype":"venue"
},
  "geometry": {"coordinates":[-81.78443900000001,32.44899],"type":"Point"}
}