{
  "type": "Feature",
  "properties": {
    "addr:full":"5524 Reynard Trl Lithonia GA 30038",
    "addr:housenumber":"5524",
    "addr:postcode":"30038",
    "addr:street":"Reynard Trl",
    "iso:country":"US",
    "sg:address":"5524 Reynard Trl",
    "sg:city":"Lithonia",
    "sg:classifiers":[
        {
            "category":"Insurance",
            "subcategory":"Title Insurance",
            "type":"Services"
        }
    ],
    "sg:phone":"+1 770 981 5537",
    "sg:postcode":"30038",
    "sg:province":"GA",
    "sg:tags":[
        "carrier"
    ],
    "wof:name":"East Bay Enterprise",
    "wof:placetype":"venue"
},
  "geometry": {"coordinates":[-84.16260800000001,33.681375],"type":"Point"}
}