{
  "type": "Feature",
  "properties": {
    "addr:full":"3851 Day Trail Ct Ellenwood GA 30294",
    "addr:housenumber":"3851",
    "addr:postcode":"30294",
    "addr:street":"Day Trail Ct",
    "iso:country":"US",
    "sg:address":"3851 Day Trail Ct",
    "sg:city":"Ellenwood",
    "sg:classifiers":[
        {
            "category":"Organizations",
            "subcategory":"Professional Association",
            "type":"Services"
        }
    ],
    "sg:phone":"+1 404 241 0170",
    "sg:postcode":"30294",
    "sg:province":"GA",
    "sg:tags":[
        "community"
    ],
    "wof:name":"Robe Vision",
    "wof:placetype":"venue"
},
  "geometry": {"coordinates":[-84.23123699999999,33.663416],"type":"Point"}
}