{
  "type": "Feature",
  "properties": {
    "iso:country":"US",
    "sg:address":"2220 Massey Dr",
    "sg:city":"Albany",
    "sg:classifiers":[
        {
            "category":"Professional",
            "subcategory":"Business Services",
            "type":"Services"
        }
    ],
    "sg:phone":"+1 229 888 7893",
    "sg:postcode":"31705",
    "sg:province":"GA",
    "sg:tags":[
        "house",
        "construction"
    ],
    "wof:name":"J & P Associates",
    "wof:placetype":"venue"
},
  "geometry": {"coordinates":[-84.098963,31.569232],"type":"Point"}
}