{
  "type": "Feature",
  "properties": {
    "iso:country":"US",
    "sg:address":"3242 Peachtree Dr NE",
    "sg:city":"Atlanta",
    "sg:classifiers":[
        {
            "category":"Education",
            "subcategory":"Vocational School",
            "type":"Public Place"
        }
    ],
    "sg:phone":"+1 404 816 5591",
    "sg:postcode":"30305",
    "sg:province":"GA",
    "sg:tags":[
        "training",
        "computer"
    ],
    "wof:name":"Savvis Global Knowledge",
    "wof:placetype":"venue"
},
  "geometry": {"coordinates":[-84.362897,33.841321],"type":"Point"}
}