{
  "type": "Feature",
  "properties": {
    "addr:full":"513 Carriage Walk Path Stone Mountain GA 30087",
    "addr:housenumber":"513",
    "addr:postcode":"30087",
    "addr:street":"Carriage Walk Path",
    "iso:country":"US",
    "sg:address":"513 Carriage Walk Path",
    "sg:city":"Stone Mountain",
    "sg:classifiers":[
        {
            "category":"Building & Trades",
            "subcategory":"Construction",
            "type":"Services"
        }
    ],
    "sg:phone":"+1 770 469 4158",
    "sg:postcode":"30087",
    "sg:province":"GA",
    "wof:name":"Jordan Firplace",
    "wof:placetype":"venue"
},
  "geometry": {"coordinates":[-84.161908,33.790302],"type":"Point"}
}