{
  "type": "Feature",
  "properties": {
    "iso:country":"US",
    "sg:address":"230 Marsh St",
    "sg:city":"Griffin",
    "sg:classifiers":[
        {
            "category":"Retail",
            "subcategory":"Repair Shop",
            "type":"Services"
        }
    ],
    "sg:phone":"+1 770 229 4298",
    "sg:postcode":"30224",
    "sg:province":"GA",
    "wof:name":"Cooks Piano Service",
    "wof:placetype":"venue"
},
  "geometry": {"coordinates":[-84.280061,33.218887],"type":"Point"}
}