{
  "type": "Feature",
  "properties": {
    "addr:full":"20 Executive Park Dr NE Atlanta GA 30303",
    "addr:housenumber":"20",
    "addr:postcode":"30303",
    "addr:street":"Executive Park Dr Ne",
    "iso:country":"US",
    "sg:address":"20 Executive Park Dr NE",
    "sg:city":"Atlanta",
    "sg:classifiers":[
        {
            "category":"Banks & Credit Unions",
            "subcategory":"Atm",
            "type":"Services"
        }
    ],
    "sg:phone":"+1 404 634 9509",
    "sg:postcode":"30303",
    "sg:province":"GA",
    "sg:tags":[
        "bankruptcy"
    ],
    "sg:website":"www.chriscarouthers.com",
    "wof:name":"Chris Carouthers and Associates",
    "wof:placetype":"venue"
},
  "geometry": {"coordinates":[-84.33950900000001,33.828419],"type":"Point"}
}