{
  "type": "Feature",
  "properties": {
    "addr:full":"416 E Mcpherson Ave Ste A Nashville GA 31639",
    "addr:housenumber":"416",
    "addr:postcode":"31639",
    "addr:street":"E Mcpherson Ave Ste A",
    "iso:country":"US",
    "sg:address":"416 E Mcpherson Ave Ste A",
    "sg:city":"Nashville",
    "sg:classifiers":[
        {
            "category":"Health Services",
            "subcategory":"Doctor",
            "type":"Services"
        }
    ],
    "sg:phone":"+1 229 686 2093",
    "sg:postcode":"31639",
    "sg:province":"GA",
    "sg:tags":[
        "medicine",
        "physician",
        "practice",
        "surgeons",
        "family"
    ],
    "wof:name":"The Doctors Clinic",
    "wof:placetype":"venue"
},
  "geometry": {"coordinates":[-83.244766,31.205291],"type":"Point"}
}