{
  "type": "Feature",
  "properties": {
    "iso:country":"US",
    "sg:address":"175 W Wieuca Rd NE",
    "sg:city":"Atlanta",
    "sg:classifiers":[
        {
            "category":"Shopping",
            "subcategory":"Jewelry",
            "type":"Retail Goods"
        }
    ],
    "sg:phone":"+1 404 531 0750",
    "sg:postcode":"30342",
    "sg:province":"GA",
    "sg:tags":[
        "appraisers-business",
        "industrial",
        "commercial",
        "jeweler"
    ],
    "wof:name":"Houghtaling Appraisal Service",
    "wof:placetype":"venue"
},
  "geometry": {"coordinates":[-84.380483,33.877132],"type":"Point"}
}