{
  "type": "Feature",
  "properties": {
    "addr:full":"621 Stephenson Ave Savannah GA 31405",
    "addr:housenumber":"621",
    "addr:postcode":"31405",
    "addr:street":"Stephenson Ave",
    "iso:country":"US",
    "sg:address":"621 Stephenson Ave",
    "sg:city":"Savannah",
    "sg:classifiers":[
        {
            "category":"Utilities",
            "subcategory":"Water",
            "type":"Services"
        }
    ],
    "sg:phone":"+1 912 352 9339",
    "sg:postcode":"31405",
    "sg:province":"GA",
    "sg:tags":[
        "company",
        "sewage"
    ],
    "wof:name":"Chatham Water Co",
    "wof:placetype":"venue"
},
  "geometry": {"coordinates":[-81.105902,32.011856],"type":"Point"}
}