{
  "type": "Feature",
  "properties": {
    "addr:full":"680 Deer Oaks Dr Lawrenceville GA 30044",
    "addr:housenumber":"680",
    "addr:postcode":"30044",
    "addr:street":"Deer Oaks Dr",
    "iso:country":"US",
    "sg:address":"680 Deer Oaks Dr",
    "sg:city":"Lawrenceville",
    "sg:classifiers":[
        {
            "category":"Education",
            "subcategory":"Music School",
            "type":"Public Place"
        },
        {
            "category":"Arts & Performance",
            "subcategory":"Arts Center",
            "type":"Entertainment"
        }
    ],
    "sg:phone":"+1 770 972 4054",
    "sg:postcode":"30044",
    "sg:province":"GA",
    "sg:tags":[
        "instrument",
        "musical",
        "teacher"
    ],
    "sg:website":"www.lamattinadrums.com/",
    "wof:name":"Lamattina Drum Studio",
    "wof:placetype":"venue"
},
  "geometry": {"coordinates":[-84.036131,33.906729],"type":"Point"}
}