{
  "type": "Feature",
  "properties": {
    "addr:full":"104 N Green St Thomaston GA 30286",
    "addr:housenumber":"104",
    "addr:postcode":"30286",
    "addr:street":"N Green St",
    "iso:country":"US",
    "sg:address":"104 N Green St",
    "sg:city":"Thomaston",
    "sg:classifiers":[
        {
            "category":"Travel",
            "subcategory":"Travel Agent",
            "type":"Entertainment"
        }
    ],
    "sg:phone":"+1 706 647 8747",
    "sg:postcode":"30286",
    "sg:province":"GA",
    "sg:tags":[
        "agency",
        "bureau"
    ],
    "wof:name":"Travel Connection",
    "wof:placetype":"venue"
},
  "geometry": {"coordinates":[-84.328197,32.888002],"type":"Point"}
}