{
  "type": "Feature",
  "properties": {
    "addr:full":"2605 Woodbine Hill Way Norcross GA 30071",
    "addr:housenumber":"2605",
    "addr:postcode":"30071",
    "addr:street":"Woodbine Hill Way",
    "iso:country":"US",
    "sg:address":"2605 Woodbine Hill Way",
    "sg:city":"Norcross",
    "sg:classifiers":[
        {
            "category":"Manufacturing",
            "subcategory":"Retail Goods",
            "type":"Manufacturing & Wholesale Goods"
        }
    ],
    "sg:phone":"+1 770 641 0529",
    "sg:postcode":"30071",
    "sg:province":"GA",
    "sg:tags":[
        "school",
        "supply"
    ],
    "wof:name":"Year Round School Supply",
    "wof:placetype":"venue"
},
  "geometry": {"coordinates":[-84.170553,33.965683],"type":"Point"}
}