{
  "type": "Feature",
  "properties": {
    "iso:country":"US",
    "sg:address":"4947 Winters Chapel Rd",
    "sg:city":"Atlanta",
    "sg:classifiers":[
        {
            "category":"Restaurant",
            "type":"Food & Drink"
        }
    ],
    "sg:phone":"+1 770 913 9633",
    "sg:postcode":"30360",
    "sg:province":"GA",
    "sg:tags":[
        "catering"
    ],
    "wof:name":"Renaissance Classic Caterers",
    "wof:placetype":"venue"
},
  "geometry": {"coordinates":[-84.271638,33.941243],"type":"Point"}
}