{
  "type": "Feature",
  "properties": {
    "iso:country":"US",
    "sg:address":"613 E Lamar St",
    "sg:city":"Americus",
    "sg:classifiers":[
        {
            "category":"Shopping",
            "subcategory":"Pharmacy",
            "type":"Retail Goods"
        }
    ],
    "sg:phone":"+1 229 928 9010",
    "sg:postcode":"31709",
    "sg:province":"GA",
    "wof:name":"Doctor's Pharmacy Vital Care",
    "wof:placetype":"venue"
},
  "geometry": {"coordinates":[-84.224101,32.071491],"type":"Point"}
}