{
  "type": "Feature",
  "properties": {
    "addr:full":"2255 Cumberland Parkway SE Atlanta GA 30339",
    "addr:housenumber":"2255",
    "addr:postcode":"30339",
    "addr:street":"Cumberland Parkway Se",
    "iso:country":"US",
    "sg:address":"2255 Cumberland Parkway SE",
    "sg:city":"Atlanta",
    "sg:classifiers":[
        {
            "category":"Professional",
            "subcategory":"Accounting & Tax Preparation",
            "type":"Services"
        }
    ],
    "sg:phone":"+1 770 437 0044",
    "sg:postcode":"30339",
    "sg:province":"GA",
    "sg:tags":[
        "accountant"
    ],
    "wof:name":"Ethridge & Miller PC",
    "wof:placetype":"venue"
},
  "geometry": {"coordinates":[-84.48087200000001,33.855713],"type":"Point"}
}