{
  "type": "Feature",
  "properties": {
    "iso:country":"US",
    "sg:address":"703 Harbor Pointe Pkwy",
    "sg:city":"Atlanta",
    "sg:classifiers":[
        {
            "category":"Professional",
            "subcategory":"Computer Services",
            "type":"Services"
        }
    ],
    "sg:phone":"+1 404 351 0998",
    "sg:postcode":"30350",
    "sg:province":"GA",
    "sg:tags":[
        "datum"
    ],
    "wof:name":"Powersource Communications",
    "wof:placetype":"venue"
},
  "geometry": {"coordinates":[-84.376453,33.969811],"type":"Point"}
}