{
  "type": "Feature",
  "properties": {
    "iso:country":"US",
    "sg:address":"1515 Country Ct",
    "sg:city":"Auburn",
    "sg:classifiers":[
        {
            "category":"Building & Trades",
            "subcategory":"Construction",
            "type":"Services"
        }
    ],
    "sg:phone":"+1 770 868 7316",
    "sg:postcode":"30011",
    "sg:province":"GA",
    "sg:tags":[
        "house"
    ],
    "wof:name":"A Home Improvement",
    "wof:placetype":"venue"
},
  "geometry": {"coordinates":[-83.837557,34.039053],"type":"Point"}
}