{
  "type": "Feature",
  "properties": {
    "addr:full":"2655 Cobb Pkwy Atlanta GA 30339",
    "addr:housenumber":"2655",
    "addr:postcode":"30339",
    "addr:street":"Cobb Pkwy",
    "iso:country":"US",
    "sg:address":"2655 Cobb Pkwy",
    "sg:city":"Atlanta",
    "sg:phone":"+1 770 956 7589",
    "sg:postcode":"30339",
    "sg:province":"GA",
    "sg:website":"http://www.swapnaindiancuisine.com",
    "wof:name":"Cuisine Swapna Indian",
    "wof:placetype":"venue"
},
  "geometry": {"coordinates":[-84.47395899999999,33.888512],"type":"Point"}
}