{
  "type": "Feature",
  "properties": {
    "addr:full":"135 Bull St Savannah GA 31401",
    "addr:housenumber":"135",
    "addr:postcode":"31401",
    "addr:street":"Bull St",
    "iso:country":"US",
    "sg:address":"135 Bull St",
    "sg:city":"Savannah",
    "sg:classifiers":[
        {
            "category":"Shopping",
            "subcategory":"Gifts & Souvenirs",
            "type":"Retail Goods"
        }
    ],
    "sg:phone":"+1 912 341 0061",
    "sg:postcode":"31401",
    "sg:province":"GA",
    "wof:name":"Urban Cargo",
    "wof:placetype":"venue"
},
  "geometry": {"coordinates":[-81.092563,32.07727],"type":"Point"}
}