{
  "type": "Feature",
  "properties": {
    "iso:country":"US",
    "sg:address":"4525 Roosevelt Hwy",
    "sg:city":"Atlanta",
    "sg:classifiers":[
        {
            "category":"Building & Trades",
            "subcategory":"Construction",
            "type":"Services"
        }
    ],
    "sg:phone":"+1 404 314 9627",
    "sg:postcode":"30349",
    "sg:province":"GA",
    "sg:tags":[
        "contractor"
    ],
    "wof:name":"Priority One Construction",
    "wof:placetype":"venue"
},
  "geometry": {"coordinates":[-84.53716900000001,33.604071],"type":"Point"}
}