{
  "type": "Feature",
  "properties": {
    "iso:country":"US",
    "sg:address":"6142 Luna Dr",
    "sg:city":"Columbus",
    "sg:classifiers":[
        {
            "category":"Building & Trades",
            "subcategory":"Electrical",
            "type":"Services"
        }
    ],
    "sg:phone":"+1 706 442 7064",
    "sg:postcode":"31907",
    "sg:province":"GA",
    "sg:tags":[
        "work",
        "electrical"
    ],
    "wof:name":"AS&r Electric",
    "wof:placetype":"venue"
},
  "geometry": {"coordinates":[-84.88547,32.471894],"type":"Point"}
}