{
  "type": "Feature",
  "properties": {
    "addr:full":"3328 Bemiss Rd Valdosta GA 31605",
    "addr:housenumber":"3328",
    "addr:postcode":"31605",
    "addr:street":"Bemiss Rd",
    "iso:country":"US",
    "sg:address":"3328 Bemiss Rd",
    "sg:city":"Valdosta",
    "sg:classifiers":[
        {
            "category":"Insurance",
            "subcategory":"Insurance Agent",
            "type":"Services"
        }
    ],
    "sg:phone":"+1 229 247 1974",
    "sg:postcode":"31605",
    "sg:province":"GA",
    "wof:name":"AFLAC",
    "wof:placetype":"venue"
},
  "geometry": {"coordinates":[-83.272851,30.884369],"type":"Point"}
}