{
  "type": "Feature",
  "properties": {
    "iso:country":"US",
    "sg:address":"3680 Clairmont Rd",
    "sg:city":"Atlanta",
    "sg:classifiers":[
        {
            "category":"Shopping",
            "type":"Retail Goods"
        }
    ],
    "sg:phone":"+1 770 457 5862",
    "sg:postcode":"30341",
    "sg:province":"GA",
    "sg:tags":[
        "picture",
        "frame"
    ],
    "wof:name":"Dunwoody Frames & Gallery",
    "wof:placetype":"venue"
},
  "geometry": {"coordinates":[-84.309523,33.867199],"type":"Point"}
}