{
  "type": "Feature",
  "properties": {
    "iso:country":"US",
    "sg:address":"796 Brogdon Rd",
    "sg:city":"Suwanee",
    "sg:classifiers":[
        {
            "category":"Building & Trades",
            "subcategory":"Plumbing",
            "type":"Services"
        },
        {
            "category":"Building & Trades",
            "subcategory":"Construction",
            "type":"Services"
        },
        {
            "category":"Utilities",
            "type":"Services"
        }
    ],
    "sg:phone":"+1 770 614 9664",
    "sg:postcode":"30024",
    "sg:province":"GA",
    "sg:tags":[
        "plumber",
        "industrial",
        "excavation",
        "contractor",
        "pipe",
        "contractors-commercial",
        "line"
    ],
    "sg:website":"http://www.pineenterprises.com",
    "wof:name":"Pine Enterprises, LLC",
    "wof:placetype":"venue"
},
  "geometry": {"coordinates":[-84.052226,34.078748],"type":"Point"}
}