{
  "type": "Feature",
  "properties": {
    "addr:full":"791 Deer Run Dr Stone Mountain GA 30087",
    "addr:housenumber":"791",
    "addr:postcode":"30087",
    "addr:street":"Deer Run Dr",
    "iso:country":"US",
    "sg:address":"791 Deer Run Dr",
    "sg:city":"Stone Mountain",
    "sg:classifiers":[
        {
            "category":"Professional",
            "subcategory":"Computer Services",
            "type":"Services"
        }
    ],
    "sg:phone":"+1 770 413 1418",
    "sg:postcode":"30087",
    "sg:province":"GA",
    "sg:tags":[
        "related"
    ],
    "wof:name":"Aja Computer Consultants",
    "wof:placetype":"venue"
},
  "geometry": {"coordinates":[-84.113917,33.799394],"type":"Point"}
}