{
  "type": "Feature",
  "properties": {
    "iso:country":"US",
    "sg:address":"2473 Shad Burn Ferry Dr",
    "sg:city":"Buford",
    "sg:classifiers":[
        {
            "category":"Professional",
            "type":"Services"
        }
    ],
    "sg:phone":"+1 770 945 7878",
    "sg:postcode":"30518",
    "sg:province":"GA",
    "wof:name":"Mickey Bruce Co",
    "wof:placetype":"venue"
},
  "geometry": {"coordinates":[-84.00185,34.137532],"type":"Point"}
}