{
  "type": "Feature",
  "properties": {
    "addr:full":"7970 Saint Marlo Fairway Dr Duluth GA 30097",
    "addr:housenumber":"7970",
    "addr:postcode":"30097",
    "addr:street":"Saint Marlo Fairway Dr",
    "iso:country":"US",
    "sg:address":"7970 Saint Marlo Fairway Dr",
    "sg:city":"Duluth",
    "sg:classifiers":[
        {
            "category":"Professional",
            "subcategory":"Employment Agencies",
            "type":"Services"
        }
    ],
    "sg:phone":"+1 770 495 3570",
    "sg:postcode":"30097",
    "sg:province":"GA",
    "sg:tags":[
        "opportunity"
    ],
    "wof:name":"United Pro Search",
    "wof:placetype":"venue"
},
  "geometry": {"coordinates":[-84.139957,34.069932],"type":"Point"}
}