{
  "type": "Feature",
  "properties": {
    "iso:country":"US",
    "sg:address":"1115 Lavista Rd",
    "sg:city":"Tucker",
    "sg:classifiers":[
        {
            "category":"Building & Trades",
            "subcategory":"Locksmith",
            "type":"Services"
        }
    ],
    "sg:phone":"+1 404 329 5569",
    "sg:postcode":"30084",
    "sg:province":"GA",
    "sg:tags":[
        "key"
    ],
    "wof:name":"A A Torpedo Locksmith",
    "wof:placetype":"venue"
},
  "geometry": {"coordinates":[-84.23285199999999,33.850603],"type":"Point"}
}