{
  "type": "Feature",
  "properties": {
    "addr:full":"50 Linkwood Rd NW Atlanta GA 30311",
    "addr:housenumber":"50",
    "addr:postcode":"30311",
    "addr:street":"Linkwood Rd Nw",
    "iso:country":"US",
    "sg:address":"50 Linkwood Rd NW",
    "sg:city":"Atlanta",
    "sg:classifiers":[
        {
            "category":"Government",
            "subcategory":"Court House",
            "type":"Public Place"
        },
        {
            "category":"Recreation",
            "type":"Entertainment"
        },
        {
            "category":"Travel",
            "subcategory":"Hotels & Motels",
            "type":"Entertainment"
        }
    ],
    "sg:phone":"+1 404 691 1986",
    "sg:postcode":"30311",
    "sg:province":"GA",
    "sg:tags":[
        "cottage",
        "chalet",
        "camps-recreational",
        "cabin"
    ],
    "wof:name":"Familys Enterprises",
    "wof:placetype":"venue"
},
  "geometry": {"coordinates":[-84.48223400000001,33.756327],"type":"Point"}
}