{
  "type": "Feature",
  "properties": {
    "iso:country":"US",
    "sg:address":"4345 Welcome All Road SW",
    "sg:city":"Atlanta",
    "sg:classifiers":[
        {
            "category":"Education",
            "subcategory":"School",
            "type":"Public Place"
        }
    ],
    "sg:phone":"+1 404 669 8030",
    "sg:postcode":"30349",
    "sg:province":"GA",
    "sg:tags":[
        "high",
        "middle",
        "elementary"
    ],
    "wof:name":"Fulton County School District",
    "wof:placetype":"venue"
},
  "geometry": {"coordinates":[-84.529263,33.63536],"type":"Point"}
}