{
  "type": "Feature",
  "properties": {
    "addr:full":"495 Commerce Dr Stockbridge GA 30281",
    "addr:housenumber":"495",
    "addr:postcode":"30281",
    "addr:street":"Commerce Dr",
    "iso:country":"US",
    "sg:address":"495 Commerce Dr",
    "sg:city":"Stockbridge",
    "sg:classifiers":[
        {
            "category":"Retail",
            "subcategory":"Auto Repair",
            "type":"Services"
        }
    ],
    "sg:phone":"+1 770 474 1214",
    "sg:postcode":"30281",
    "sg:province":"GA",
    "sg:tags":[
        "truck"
    ],
    "wof:name":"Hull Truck Repair",
    "wof:placetype":"venue"
},
  "geometry": {"coordinates":[-84.205476,33.535039],"type":"Point"}
}