{
  "type": "Feature",
  "properties": {
    "iso:country":"US",
    "sg:address":"16963 Middle Ground Rd",
    "sg:city":"Wrens",
    "sg:classifiers":[
        {
            "category":"Professional",
            "type":"Services"
        }
    ],
    "sg:phone":"+1 706 547 9457",
    "sg:postcode":"30833",
    "sg:province":"GA",
    "wof:name":"Wildlife Specialties",
    "wof:placetype":"venue"
},
  "geometry": {"coordinates":[-82.26713700000001,33.152653],"type":"Point"}
}