{
  "type": "Feature",
  "properties": {
    "addr:full":"506 Riverside Pkwy NE Rome GA 30161",
    "addr:housenumber":"506",
    "addr:postcode":"ga 30161",
    "addr:street":"Riverside Pkwy Ne",
    "iso:country":"US",
    "sg:address":"506 Riverside Pkwy NE",
    "sg:city":"Rome",
    "sg:classifiers":[
        {
            "category":"Health Services",
            "subcategory":"Doctor",
            "type":"Services"
        }
    ],
    "sg:phone":"+1 706 291 0200",
    "sg:postcode":"30161",
    "sg:province":"GA",
    "sg:tags":[
        "physician",
        "medical",
        "surgeon"
    ],
    "wof:name":"Aesthetic Plastic Surgery PC",
    "wof:placetype":"venue"
},
  "geometry": {"coordinates":[-85.170012,34.273581],"type":"Point"}
}