{
  "type": "Feature",
  "properties": {
    "iso:country":"US",
    "sg:address":"705 S Madison Ave",
    "sg:city":"Douglas",
    "sg:classifiers":[
        {
            "category":"Shopping",
            "subcategory":"Used Merchandise",
            "type":"Retail Goods"
        }
    ],
    "sg:phone":"+1 912 384 2099",
    "sg:postcode":"31533",
    "sg:province":"GA",
    "wof:name":"City Loan & Pawnshop Inc",
    "wof:placetype":"venue"
},
  "geometry": {"coordinates":[-82.84972399999999,31.501241],"type":"Point"}
}