{
  "type": "Feature",
  "properties": {
    "addr:full":"2951 Washington Rd Augusta GA 30909",
    "addr:housenumber":"2951",
    "addr:postcode":"30909",
    "addr:street":"Washington Rd",
    "iso:country":"US",
    "sg:address":"2951 Washington Rd",
    "sg:city":"Augusta",
    "sg:classifiers":[
        {
            "category":"Restaurant",
            "type":"Food & Drink"
        }
    ],
    "sg:menulink":"http://www.allmenus.com/ga/augusta/140535-waffle-house/menu/",
    "sg:phone":"+1 770 534 2786",
    "sg:postcode":"30909",
    "sg:province":"GA",
    "sg:tags":[
        "american"
    ],
    "wof:name":"Waffle House",
    "wof:placetype":"venue"
},
  "geometry": {"coordinates":[-82.040943,33.511794],"type":"Point"}
}