{
  "type": "Feature",
  "properties": {
    "iso:country":"US",
    "sg:address":"1070 Magnolia Dr",
    "sg:city":"Villa Rica",
    "sg:classifiers":[
        {
            "category":"Professional",
            "type":"Services"
        }
    ],
    "sg:phone":"+1 770 214 2063",
    "sg:postcode":"30180",
    "sg:province":"GA",
    "wof:name":"James S Eubanks",
    "wof:placetype":"venue"
},
  "geometry": {"coordinates":[-84.921212,33.64206],"type":"Point"}
}