{
  "type": "Feature",
  "properties": {
    "iso:country":"US",
    "sg:address":"771 Shallowford Rd NE",
    "sg:city":"Kennesaw",
    "sg:classifiers":[
        {
            "category":"Building & Trades",
            "subcategory":"Construction",
            "type":"Services"
        }
    ],
    "sg:phone":"+1 678 445 7300",
    "sg:postcode":"30144",
    "sg:province":"GA",
    "sg:tags":[
        "repairing",
        "remodeling",
        "contractor"
    ],
    "wof:name":"Expert Remodelers Inc",
    "wof:placetype":"venue"
},
  "geometry": {"coordinates":[-84.526454,34.067806],"type":"Point"}
}