{
  "type": "Feature",
  "properties": {
    "addr:full":"1180 Branch Water Ct Atlanta GA 30338",
    "addr:housenumber":"1180",
    "addr:postcode":"30338",
    "addr:street":"Branch Water Ct",
    "iso:country":"US",
    "sg:address":"1180 Branch Water Ct",
    "sg:city":"Atlanta",
    "sg:classifiers":[
        {
            "category":"Professional",
            "type":"Services"
        }
    ],
    "sg:phone":"+1 770 395 7196",
    "sg:postcode":"30338",
    "sg:province":"GA",
    "wof:name":"Twin Lynn Inc",
    "wof:placetype":"venue"
},
  "geometry": {"coordinates":[-84.340531,33.946606],"type":"Point"}
}