{
  "type": "Feature",
  "properties": {
    "iso:country":"US",
    "sg:address":"42 E Main St",
    "sg:city":"Forsyth",
    "sg:classifiers":[
        {
            "category":"Shopping",
            "subcategory":"Used Merchandise",
            "type":"Retail Goods"
        }
    ],
    "sg:phone":"+1 478 974 0122",
    "sg:postcode":"31029",
    "sg:province":"GA",
    "sg:tags":[
        "flea",
        "market"
    ],
    "wof:name":"Treasures Plus Consignment Shp",
    "wof:placetype":"venue"
},
  "geometry": {"coordinates":[-83.92506299999999,33.033598],"type":"Point"}
}