{
  "type": "Feature",
  "properties": {
    "addr:full":"606 Ga Highway 49 Macon GA 31211",
    "addr:housenumber":"606",
    "addr:postcode":"31211",
    "addr:street":"Ga Highway 49",
    "iso:country":"US",
    "sg:address":"606 Ga Highway 49",
    "sg:city":"Macon",
    "sg:classifiers":[
        {
            "category":"Building & Trades",
            "subcategory":"Plumbing",
            "type":"Services"
        }
    ],
    "sg:phone":"+1 478 956 4552",
    "sg:postcode":"31211",
    "sg:province":"GA",
    "sg:tags":[
        "tank",
        "system",
        "septic"
    ],
    "wof:name":"Abacus Construction Septic Division",
    "wof:placetype":"venue"
},
  "geometry": {"coordinates":[-83.528327,32.897979],"type":"Point"}
}