{
  "type": "Feature",
  "properties": {
    "addr:full":"445 Plasamour Dr NE Atlanta GA 30324",
    "addr:housenumber":"445",
    "addr:postcode":"30324",
    "addr:street":"Plasamour Dr Ne",
    "iso:country":"US",
    "sg:address":"445 Plasamour Dr NE",
    "sg:city":"Atlanta",
    "sg:classifiers":[
        {
            "category":"Home & Garden",
            "subcategory":"Home Furnishings",
            "type":"Retail Goods"
        }
    ],
    "sg:phone":"+1 404 876 1359",
    "sg:postcode":"30324",
    "sg:province":"GA",
    "sg:tags":[
        "decor"
    ],
    "wof:name":"Midpoint Limited",
    "wof:placetype":"venue"
},
  "geometry": {"coordinates":[-84.372272,33.813169],"type":"Point"}
}