{
  "type": "Feature",
  "properties": {
    "addr:full":"1585 Old Norcross Rd Lawrenceville GA 30046",
    "addr:housenumber":"1585",
    "addr:postcode":"30046",
    "addr:street":"Old Norcross Rd",
    "iso:country":"US",
    "sg:address":"1585 Old Norcross Rd",
    "sg:city":"Lawrenceville",
    "sg:classifiers":[
        {
            "category":"Banks & Credit Unions",
            "subcategory":"Financial Services",
            "type":"Services"
        }
    ],
    "sg:phone":"+1 678 336 1343",
    "sg:postcode":"30046",
    "sg:province":"GA",
    "sg:tags":[
        "broker",
        "mortgage"
    ],
    "wof:name":"Prime Mortgage",
    "wof:placetype":"venue"
},
  "geometry": {"coordinates":[-84.046359,33.953591],"type":"Point"}
}