{
  "type": "Feature",
  "properties": {
    "iso:country":"US",
    "sg:address":"745 Orr St NW",
    "sg:city":"Atlanta",
    "sg:classifiers":[
        {
            "category":"Social Services",
            "type":"Services"
        }
    ],
    "sg:phone":"+1 404 524 8466",
    "sg:postcode":"30314",
    "sg:province":"GA",
    "sg:tags":[
        "senior",
        "citizen"
    ],
    "wof:name":"Senior Citizen Svc",
    "wof:placetype":"venue"
},
  "geometry": {"coordinates":[-84.412102,33.762623],"type":"Point"}
}