{
  "type": "Feature",
  "properties": {
    "iso:country":"US",
    "sg:address":"7552 Woody Springs Dr",
    "sg:city":"Flowery Branch",
    "sg:classifiers":[
        {
            "category":"Building & Trades",
            "subcategory":"Construction",
            "type":"Services"
        }
    ],
    "sg:phone":"+1 770 965 0480",
    "sg:postcode":"30542",
    "sg:province":"GA",
    "sg:tags":[
        "family"
    ],
    "wof:name":"United Framing Contractors",
    "wof:placetype":"venue"
},
  "geometry": {"coordinates":[-83.894451,34.113679],"type":"Point"}
}