{
  "type": "Feature",
  "properties": {
    "iso:country":"US",
    "sg:address":"10761 Alpharetta Hwy",
    "sg:city":"Roswell",
    "sg:classifiers":[
        {
            "category":"Autos & Motor Vehicles",
            "subcategory":"Fuel & Gas Station",
            "type":"Retail Goods"
        }
    ],
    "sg:phone":"+1 770 650 0503",
    "sg:postcode":"30076",
    "sg:province":"GA",
    "sg:tags":[
        "oil"
    ],
    "wof:name":"Shell",
    "wof:placetype":"venue"
},
  "geometry": {"coordinates":[-84.33779800000001,34.049831],"type":"Point"}
}