{
  "type": "Feature",
  "properties": {
    "iso:country":"US",
    "sg:address":"2510 Redmond Cir",
    "sg:city":"Rome",
    "sg:classifiers":[
        {
            "category":"Cinema",
            "subcategory":"Movie Rental",
            "type":"Entertainment"
        }
    ],
    "sg:phone":"+1 706 290 0204",
    "sg:postcode":"30165",
    "sg:province":"GA",
    "sg:tags":[
        "video",
        "store"
    ],
    "wof:name":"Movie Gallery",
    "wof:placetype":"venue"
},
  "geometry": {"coordinates":[-85.229979,34.271795],"type":"Point"}
}