{
  "type": "Feature",
  "properties": {
    "iso:country":"US",
    "sg:address":"1808 Dean Ave",
    "sg:city":"Rome",
    "sg:classifiers":[
        {
            "category":"Food & Beverages",
            "subcategory":"Groceries & Convenience Stores",
            "type":"Retail Goods"
        }
    ],
    "sg:phone":"+1 706 291 4868",
    "sg:postcode":"30161",
    "sg:province":"GA",
    "wof:name":"Cowboys Food Mart 5",
    "wof:placetype":"venue"
},
  "geometry": {"coordinates":[-85.159841,34.23106],"type":"Point"}
}