{
  "type": "Feature",
  "properties": {
    "addr:full":"1619 Moody Rd Warner Robins GA 31088",
    "addr:housenumber":"1619",
    "addr:postcode":"31088",
    "addr:street":"Moody Rd",
    "iso:country":"US",
    "sg:address":"1619 Moody Rd",
    "sg:city":"Warner Robins",
    "sg:classifiers":[
        {
            "category":"Organizations",
            "subcategory":"Community Association",
            "type":"Services"
        }
    ],
    "sg:phone":"+1 478 328 2610",
    "sg:postcode":"31088",
    "sg:province":"GA",
    "sg:tags":[
        "club"
    ],
    "wof:name":"Club Eclipse",
    "wof:placetype":"venue"
},
  "geometry": {"coordinates":[-83.618061,32.596777],"type":"Point"}
}