{
  "type": "Feature",
  "properties": {
    "iso:country":"US",
    "sg:address":"112 Village Ln",
    "sg:city":"Eatonton",
    "sg:classifiers":[
        {
            "category":"Building & Trades",
            "subcategory":"Plumbing",
            "type":"Services"
        }
    ],
    "sg:phone":"+1 706 484 2123",
    "sg:postcode":"31024",
    "sg:province":"GA",
    "sg:tags":[
        "plumbing",
        "contractor"
    ],
    "wof:name":"D J More Plumbing",
    "wof:placetype":"venue"
},
  "geometry": {"coordinates":[-83.272408,33.422332],"type":"Point"}
}