{
  "type": "Feature",
  "properties": {
    "addr:full":"2728 Summers St NW Kennesaw GA 30144",
    "addr:housenumber":"2728",
    "addr:postcode":"30144",
    "addr:street":"Summers St Nw",
    "iso:country":"US",
    "sg:address":"2728 Summers St NW",
    "sg:city":"Kennesaw",
    "sg:classifiers":[
        {
            "category":"Bakery",
            "type":"Food & Drink"
        }
    ],
    "sg:phone":"+1 770 795 9076",
    "sg:postcode":"30144",
    "sg:province":"GA",
    "wof:name":"La Guadalupana Bakery Pasteleria",
    "wof:placetype":"venue"
},
  "geometry": {"coordinates":[-84.61199999999999,34.0168],"type":"Point"}
}