{
  "type": "Feature",
  "properties": {
    "iso:country":"US",
    "sg:address":"2502 Habersham St",
    "sg:city":"Savannah",
    "sg:classifiers":[
        {
            "category":"Shopping",
            "subcategory":"Used Merchandise",
            "type":"Retail Goods"
        }
    ],
    "sg:phone":"+1 912 238 5908",
    "sg:postcode":"31401",
    "sg:province":"GA",
    "wof:name":"Habersham Antq & Collectibles",
    "wof:placetype":"venue"
},
  "geometry": {"coordinates":[-81.09704600000001,32.052138],"type":"Point"}
}