{
  "type": "Feature",
  "properties": {
    "addr:full":"1630 Acworth Due West Rd NW Kennesaw GA 30152",
    "addr:housenumber":"1630",
    "addr:postcode":"30152",
    "addr:street":"Acworth Due West Rd Nw",
    "iso:country":"US",
    "sg:address":"1630 Acworth Due West Rd NW",
    "sg:city":"Kennesaw",
    "sg:classifiers":[
        {
            "category":"Building & Trades",
            "subcategory":"Construction",
            "type":"Services"
        }
    ],
    "sg:phone":"+1 770 424 2901",
    "sg:postcode":"30152",
    "sg:province":"GA",
    "sg:tags":[
        "h",
        "commercial",
        "painting",
        "residential",
        "remodeling",
        "painter"
    ],
    "wof:name":"Eagle Painting",
    "wof:placetype":"venue"
},
  "geometry": {"coordinates":[-84.67353,33.994107],"type":"Point"}
}