{
  "type": "Feature",
  "properties": {
    "addr:full":"100 Princeton Blvd Adairsville GA 30103",
    "addr:housenumber":"100",
    "addr:postcode":"30103",
    "addr:street":"Princeton Blvd",
    "iso:country":"US",
    "sg:address":"100 Princeton Blvd",
    "sg:city":"Adairsville",
    "sg:classifiers":[
        {
            "category":"Restaurant",
            "type":"Food & Drink"
        }
    ],
    "sg:menulink":"http://www.allmenus.com/ga/adairsville/203127-mcdonalds/menu/",
    "sg:postcode":"30103",
    "sg:province":"GA",
    "sg:tags":[
        "burger",
        "american"
    ],
    "wof:name":"McDonald's",
    "wof:placetype":"venue"
},
  "geometry": {"coordinates":[-84.91442000000001,34.37653],"type":"Point"}
}