{
  "type": "Feature",
  "properties": {
    "addr:full":"928 Mallory Dr Marietta GA 30062",
    "addr:housenumber":"928",
    "addr:postcode":"30062",
    "addr:street":"Mallory Dr",
    "iso:country":"US",
    "sg:address":"928 Mallory Dr",
    "sg:city":"Marietta",
    "sg:classifiers":[
        {
            "category":"Shopping",
            "subcategory":"Clothing, Apparel, & Fashions",
            "type":"Retail Goods"
        }
    ],
    "sg:phone":"+1 770 499 9509",
    "sg:postcode":"30062",
    "sg:province":"GA",
    "sg:tags":[
        "accessory"
    ],
    "wof:name":"T J's Fashions & Accessories",
    "wof:placetype":"venue"
},
  "geometry": {"coordinates":[-84.522415,33.973742],"type":"Point"}
}