{
  "type": "Feature",
  "properties": {
    "addr:full":"4355 Cobb Pkwy Ste J Atlanta GA 30339",
    "addr:housenumber":"4355",
    "addr:postcode":"30339",
    "addr:street":"Cobb Pkwy Ste J",
    "iso:country":"US",
    "sg:address":"4355 Cobb Pkwy Ste J",
    "sg:city":"Atlanta",
    "sg:classifiers":[
        {
            "category":"Shopping",
            "subcategory":"Clothing, Apparel, & Fashions",
            "type":"Retail Goods"
        }
    ],
    "sg:phone":"+1 404 396 9083",
    "sg:postcode":"30339",
    "sg:province":"GA",
    "sg:tags":[
        "clothing",
        "store"
    ],
    "wof:name":"Outershell Clothing",
    "wof:placetype":"venue"
},
  "geometry": {"coordinates":[-84.456424,33.87135],"type":"Point"}
}