{
  "type": "Feature",
  "properties": {
    "iso:country":"US",
    "sg:address":"1761 Hickory Lake Dr",
    "sg:city":"Snellville",
    "sg:classifiers":[
        {
            "category":"Professional",
            "type":"Services"
        }
    ],
    "sg:phone":"+1 770 736 5365",
    "sg:postcode":"30078",
    "sg:province":"GA",
    "wof:name":"Rae Jeans Specialties",
    "wof:placetype":"venue"
},
  "geometry": {"coordinates":[-84.03146,33.86976],"type":"Point"}
}