{
  "type": "Feature",
  "properties": {
    "iso:country":"US",
    "sg:address":"3011 Clark Ave",
    "sg:city":"Albany",
    "sg:classifiers":[
        {
            "category":"Transit Center",
            "subcategory":"Freight",
            "type":"Transportation"
        }
    ],
    "sg:phone":"+1 229 432 8238",
    "sg:postcode":"31705",
    "sg:province":"GA",
    "sg:tags":[
        "trucking-motor"
    ],
    "wof:name":"Fleetmaster Express",
    "wof:placetype":"venue"
},
  "geometry": {"coordinates":[-84.06355600000001,31.582695],"type":"Point"}
}