{
  "type": "Feature",
  "properties": {
    "addr:full":"2612 Holcomb Bridge Rd Ste 100 Alpharetta GA 30022",
    "addr:housenumber":"2612",
    "addr:postcode":"30022",
    "addr:street":"Holcomb Bridge Rd Ste 100",
    "iso:country":"US",
    "sg:address":"2612 Holcomb Bridge Rd Ste 100",
    "sg:city":"Alpharetta",
    "sg:classifiers":[
        {
            "category":"Health Services",
            "subcategory":"Doctor",
            "type":"Services"
        }
    ],
    "sg:phone":"+1 770 650 8980",
    "sg:postcode":"30022",
    "sg:province":"GA",
    "sg:tags":[
        "practice",
        "family"
    ],
    "sg:website":"www.northfultonprimarycare.com",
    "wof:name":"North Fulton Primary Care",
    "wof:placetype":"venue"
},
  "geometry": {"coordinates":[-84.282803,33.99646],"type":"Point"}
}