{
  "type": "Feature",
  "properties": {
    "addr:full":"4255 Trotters Way Alpharetta GA 30004",
    "addr:housenumber":"4255",
    "addr:postcode":"30004",
    "addr:street":"Trotters Way",
    "iso:country":"US",
    "sg:address":"4255 Trotters Way",
    "sg:city":"Alpharetta",
    "sg:classifiers":[
        {
            "category":"Building & Trades",
            "subcategory":"Landscaping Services",
            "type":"Services"
        }
    ],
    "sg:phone":"+1 770 360 0094",
    "sg:postcode":"30004",
    "sg:province":"GA",
    "sg:tags":[
        "landscape"
    ],
    "wof:name":"Paradise Landscaping",
    "wof:placetype":"venue"
},
  "geometry": {"coordinates":[-84.228752,34.12387],"type":"Point"}
}