{
  "type": "Feature",
  "properties": {
    "addr:full":"309 Mossy Way NW Kennesaw GA 30152",
    "addr:housenumber":"309",
    "addr:postcode":"30152",
    "addr:street":"Mossy Way Nw",
    "iso:country":"US",
    "sg:address":"309 Mossy Way NW",
    "sg:city":"Kennesaw",
    "sg:classifiers":[
        {
            "category":"Wholesale",
            "subcategory":"Non-durable Goods",
            "type":"Manufacturing & Wholesale Goods"
        }
    ],
    "sg:phone":"+1 770 423 0038",
    "sg:postcode":"30152",
    "sg:province":"GA",
    "wof:name":"A Universal Trade Organization",
    "wof:placetype":"venue"
},
  "geometry": {"coordinates":[-84.689356,33.960527],"type":"Point"}
}