{
  "type": "Feature",
  "properties": {
    "addr:full":"2910 Buford Dr Apt 325 Buford GA 30519",
    "addr:housenumber":"2910;325",
    "addr:postcode":"30519",
    "addr:street":"Buford Dr Apt",
    "iso:country":"US",
    "sg:address":"2910 Buford Dr Apt 325",
    "sg:city":"Buford",
    "sg:classifiers":[
        {
            "category":"Retail",
            "subcategory":"Car Wash",
            "type":"Services"
        }
    ],
    "sg:phone":"+1 678 714 2598",
    "sg:postcode":"30519",
    "sg:province":"GA",
    "wof:name":"Onsite Shine Professional Mobile Detailing",
    "wof:placetype":"venue"
},
  "geometry": {"coordinates":[-83.99400300000001,34.050701],"type":"Point"}
}