{
  "type": "Feature",
  "properties": {
    "addr:full":"1578 Asheforde Dr Marietta GA 30068",
    "addr:housenumber":"1578",
    "addr:postcode":"30068",
    "addr:street":"Asheforde Dr",
    "iso:country":"US",
    "sg:address":"1578 Asheforde Dr",
    "sg:city":"Marietta",
    "sg:classifiers":[
        {
            "category":"Professional",
            "type":"Services"
        }
    ],
    "sg:phone":"+1 770 575 5765",
    "sg:postcode":"30068",
    "sg:province":"GA",
    "wof:name":"Redmoon Systems Inc",
    "wof:placetype":"venue"
},
  "geometry": {"coordinates":[-84.388187,33.989655],"type":"Point"}
}