{
  "type": "Feature",
  "properties": {
    "addr:full":"138 Mickey Mouse Dr Cleveland GA 30528",
    "addr:housenumber":"138",
    "addr:postcode":"30528",
    "addr:street":"Mickey Mouse Dr",
    "iso:country":"US",
    "sg:address":"138 Mickey Mouse Dr",
    "sg:city":"Cleveland",
    "sg:classifiers":[
        {
            "category":"Retail",
            "subcategory":"Laundry & Dry Cleaning",
            "type":"Services"
        }
    ],
    "sg:phone":"+1 706 865 3317",
    "sg:postcode":"30528",
    "sg:province":"GA",
    "sg:tags":[
        "cleaners",
        "rug",
        "carpet"
    ],
    "wof:name":"J & N Carpet Cleaning & Floor",
    "wof:placetype":"venue"
},
  "geometry": {"coordinates":[-83.657899,34.597117],"type":"Point"}
}