{
  "type": "Feature",
  "properties": {
    "addr:full":"1649 S Flat Rock Rd Douglasville GA 30134",
    "addr:housenumber":"1649",
    "addr:postcode":"30134",
    "addr:street":"S Flat Rock Rd",
    "iso:country":"US",
    "sg:address":"1649 S Flat Rock Rd",
    "sg:city":"Douglasville",
    "sg:classifiers":[
        {
            "category":"Building & Trades",
            "subcategory":"Locksmith",
            "type":"Services"
        }
    ],
    "sg:phone":"+1 404 486 1313",
    "sg:postcode":"30134",
    "sg:province":"GA",
    "sg:tags":[
        "key"
    ],
    "wof:name":"A A Luther Locksmith",
    "wof:placetype":"venue"
},
  "geometry": {"coordinates":[-84.78086,33.759499],"type":"Point"}
}