{
  "type": "Feature",
  "properties": {
    "iso:country":"US",
    "sg:address":"475 Pineburr Ln",
    "sg:city":"Stone Mountain",
    "sg:classifiers":[
        {
            "category":"Building & Trades",
            "subcategory":"Construction",
            "type":"Services"
        }
    ],
    "sg:phone":"+1 770 355 2549",
    "sg:postcode":"30087",
    "sg:province":"GA",
    "sg:tags":[
        "house"
    ],
    "wof:name":"Kenny Construction Co",
    "wof:placetype":"venue"
},
  "geometry": {"coordinates":[-84.11445500000001,33.789477],"type":"Point"}
}