{
  "type": "Feature",
  "properties": {
    "iso:country":"US",
    "sg:address":"208 Hudson St",
    "sg:city":"Cumming",
    "sg:classifiers":[
        {
            "category":"Health Services",
            "subcategory":"Medical Lab",
            "type":"Services"
        }
    ],
    "sg:phone":"+1 770 886 3914",
    "sg:postcode":"30040",
    "sg:province":"GA",
    "sg:tags":[
        "laboratory"
    ],
    "wof:name":"Quest Diagnostics Inc",
    "wof:placetype":"venue"
},
  "geometry": {"coordinates":[-84.14138199999999,34.208657],"type":"Point"}
}