{
  "type": "Feature",
  "properties": {
    "addr:full":"316 W Hall St Thomson GA 30824",
    "addr:housenumber":"316",
    "addr:postcode":"30824",
    "addr:street":"W Hall St",
    "iso:country":"US",
    "sg:address":"316 W Hall St",
    "sg:city":"Thomson",
    "sg:classifiers":[
        {
            "category":"Shopping",
            "type":"Retail Goods"
        }
    ],
    "sg:phone":"+1 706 595 9921",
    "sg:postcode":"30824",
    "sg:province":"GA",
    "sg:tags":[
        "cosmetic",
        "perfume"
    ],
    "wof:name":"Merle Norman Cosmetic & Gifts",
    "wof:placetype":"venue"
},
  "geometry": {"coordinates":[-82.50657699999999,33.467515],"type":"Point"}
}