{
  "type": "Feature",
  "properties": {
    "addr:full":"7617 W County Line Rd Lula GA 30554",
    "addr:housenumber":"7617",
    "addr:postcode":"30554",
    "addr:street":"W County Line Rd",
    "iso:country":"US",
    "sg:address":"7617 W County Line Rd",
    "sg:city":"Lula",
    "sg:classifiers":[
        {
            "category":"Organizations",
            "subcategory":"Religious Organization",
            "type":"Services"
        }
    ],
    "sg:phone":"+1 706 677 4669",
    "sg:postcode":"30554",
    "sg:province":"GA",
    "sg:tags":[
        "clergy"
    ],
    "wof:name":"Donald Tritt",
    "wof:placetype":"venue"
},
  "geometry": {"coordinates":[-83.64838399999999,34.335941],"type":"Point"}
}