{
  "type": "Feature",
  "properties": {
    "iso:country":"US",
    "sg:address":"201 E Charlton St",
    "sg:city":"Savannah",
    "sg:classifiers":[
        {
            "category":"Travel",
            "subcategory":"Hotels & Motels",
            "type":"Entertainment"
        }
    ],
    "sg:phone":"+1 912 233 7815",
    "sg:postcode":"31401",
    "sg:province":"GA",
    "sg:tags":[
        "lodging"
    ],
    "sg:website":"http://www.suitesonlafayette.com",
    "wof:name":"Suites On Lafayette",
    "wof:placetype":"venue"
},
  "geometry": {"coordinates":[-81.09184999999999,32.072689],"type":"Point"}
}