{
  "type": "Feature",
  "properties": {
    "addr:full":"5616 Brady Dr SW Stone Mountain GA 30087",
    "addr:housenumber":"5616",
    "addr:postcode":"30087",
    "addr:street":"Brady Dr Sw",
    "iso:country":"US",
    "sg:address":"5616 Brady Dr SW",
    "sg:city":"Stone Mountain",
    "sg:classifiers":[
        {
            "category":"Banks & Credit Unions",
            "subcategory":"Financial Services",
            "type":"Services"
        }
    ],
    "sg:phone":"+1 770 921 4345",
    "sg:postcode":"30087",
    "sg:province":"GA",
    "sg:tags":[
        "trust",
        "management"
    ],
    "wof:name":"Garrison Horace J Et Al",
    "wof:placetype":"venue"
},
  "geometry": {"coordinates":[-84.138075,33.838681],"type":"Point"}
}