{
  "type": "Feature",
  "properties": {
    "iso:country":"US",
    "sg:address":"6227 Wellwater Way",
    "sg:city":"Lithonia",
    "sg:classifiers":[
        {
            "category":"Building & Trades",
            "subcategory":"Landscaping Services",
            "type":"Services"
        }
    ],
    "sg:phone":"+1 770 484 4906",
    "sg:postcode":"30058",
    "sg:province":"GA",
    "wof:name":"D & R Lawn Service",
    "wof:placetype":"venue"
},
  "geometry": {"coordinates":[-84.139544,33.736691],"type":"Point"}
}