{
  "type": "Feature",
  "properties": {
    "iso:country":"US",
    "sg:address":"165 Maple St",
    "sg:city":"Tifton",
    "sg:classifiers":[
        {
            "category":"Professional",
            "subcategory":"Research",
            "type":"Services"
        }
    ],
    "sg:phone":"+1 229 388 8488",
    "sg:postcode":"31794",
    "sg:province":"GA",
    "sg:tags":[
        "environmental",
        "ecological"
    ],
    "wof:name":"Southeastern Environmental",
    "wof:placetype":"venue"
},
  "geometry": {"coordinates":[-83.84113000000001,31.542499],"type":"Point"}
}