{
  "type": "Feature",
  "properties": {
    "iso:country":"US",
    "sg:address":"401 W Park Ct",
    "sg:city":"Peachtree City",
    "sg:classifiers":[
        {
            "category":"Insurance",
            "subcategory":"Insurance Agent",
            "type":"Services"
        }
    ],
    "sg:phone":"+1 678 783 0141",
    "sg:postcode":"30269",
    "sg:province":"GA",
    "wof:name":"Pure Risk Solutions LLC",
    "wof:placetype":"venue"
},
  "geometry": {"coordinates":[-84.58877699999999,33.400827],"type":"Point"}
}