{
  "type": "Feature",
  "properties": {
    "addr:full":"5163 Roswell Rd Atlanta GA 30342",
    "addr:housenumber":"5163",
    "addr:postcode":"30342",
    "addr:street":"Roswell Rd",
    "iso:country":"US",
    "sg:address":"5163 Roswell Rd",
    "sg:city":"Atlanta",
    "sg:classifiers":[
        {
            "category":"Real Estate",
            "subcategory":"Real Estate Agent",
            "type":"Services"
        }
    ],
    "sg:phone":"+1 404 231 1113",
    "sg:postcode":"30342",
    "sg:province":"GA",
    "wof:name":"Hinson The Real Estate Team",
    "wof:placetype":"venue"
},
  "geometry": {"coordinates":[-84.381353,33.895439],"type":"Point"}
}