{
  "type": "Feature",
  "properties": {
    "iso:country":"US",
    "sg:address":"816 Kenneth Ln NW",
    "sg:city":"Norcross",
    "sg:classifiers":[
        {
            "category":"Building & Trades",
            "subcategory":"Construction",
            "type":"Services"
        }
    ],
    "sg:phone":"+1 770 931 3598",
    "sg:postcode":"30093",
    "sg:province":"GA",
    "sg:tags":[
        "concrete",
        "contractor"
    ],
    "wof:name":"Aguirre Concrete Constr",
    "wof:placetype":"venue"
},
  "geometry": {"coordinates":[-84.18156500000001,33.892084],"type":"Point"}
}