{
  "type": "Feature",
  "properties": {
    "addr:full":"990 Hammond Dr NE # 1100 Atlanta GA 30328",
    "addr:housenumber":"990",
    "addr:postcode":"30328",
    "addr:street":"Hammond Dr Ne # 1100",
    "iso:country":"US",
    "sg:address":"990 Hammond Dr NE # 1100",
    "sg:city":"Atlanta",
    "sg:classifiers":[
        {
            "category":"Structure",
            "subcategory":"Warehouse",
            "type":"Public Place"
        }
    ],
    "sg:phone":"+1 770 955 8030",
    "sg:postcode":"30328",
    "sg:province":"GA",
    "sg:tags":[
        "warehouses-merchandise",
        "warehouses-public-commercial"
    ],
    "sg:website":"http://www.whiting-turner.com",
    "wof:name":"Whiting Turner Contracting Co",
    "wof:placetype":"venue"
},
  "geometry": {"coordinates":[-84.355028,33.918941],"type":"Point"}
}