{
  "type": "Feature",
  "properties": {
    "addr:full":"865 Highway 20-81 W Atlanta GA 30303",
    "addr:housenumber":"865",
    "addr:postcode":"30303",
    "addr:street":"Highway 20-81 W",
    "iso:country":"US",
    "sg:address":"865 Highway 20-81 W",
    "sg:city":"Atlanta",
    "sg:classifiers":[
        {
            "category":"Banks & Credit Unions",
            "subcategory":"Bank",
            "type":"Services"
        }
    ],
    "sg:phone":"+1 770 898 1988",
    "sg:postcode":"30303",
    "sg:province":"GA",
    "sg:website":"www.ucbi.com",
    "wof:name":"United Community Bank",
    "wof:placetype":"venue"
},
  "geometry": {"coordinates":[-84.38897,33.755418],"type":"Point"}
}