{
  "type": "Feature",
  "properties": {
    "iso:country":"US",
    "sg:address":"4517 E Kings Point Cir",
    "sg:city":"Atlanta",
    "sg:classifiers":[
        {
            "category":"Personal",
            "subcategory":"Massage",
            "type":"Services"
        }
    ],
    "sg:phone":"+1 770 457 0715",
    "sg:postcode":"30338",
    "sg:province":"GA",
    "wof:name":"Terra Bella Aromatherapy & Massage",
    "wof:placetype":"venue"
},
  "geometry": {"coordinates":[-84.290234,33.928571],"type":"Point"}
}