{
  "type": "Feature",
  "properties": {
    "addr:full":"2014 Powers Ferry Rd SE Atlanta GA 30339",
    "addr:housenumber":"2014",
    "addr:postcode":"30339",
    "addr:street":"Powers Ferry Rd Se",
    "iso:country":"US",
    "sg:address":"2014 Powers Ferry Rd SE",
    "sg:city":"Atlanta",
    "sg:classifiers":[
        {
            "category":"Shopping",
            "subcategory":"Pharmacy",
            "type":"Retail Goods"
        }
    ],
    "sg:phone":"+1 770 612 0958",
    "sg:postcode":"30339",
    "sg:province":"GA",
    "sg:tags":[
        "drugstore"
    ],
    "sg:website":"www.cvs.com",
    "wof:name":"Cvs Pharmacy",
    "wof:placetype":"venue"
},
  "geometry": {"coordinates":[-84.456733,33.902506],"type":"Point"}
}