{
  "type": "Feature",
  "properties": {
    "iso:country":"US",
    "sg:address":"630 Bluff Oak Ct",
    "sg:city":"Roswell",
    "sg:classifiers":[
        {
            "category":"Professional",
            "type":"Services"
        }
    ],
    "sg:phone":"+1 678 360 5587",
    "sg:postcode":"30076",
    "sg:province":"GA",
    "wof:name":"A Anton David PC",
    "wof:placetype":"venue"
},
  "geometry": {"coordinates":[-84.344835,34.059637],"type":"Point"}
}