{
  "type": "Feature",
  "properties": {
    "addr:full":"204 Brow Rd Trenton GA 30752",
    "addr:housenumber":"204",
    "addr:postcode":"30752",
    "addr:street":"Brow Rd",
    "iso:country":"US",
    "sg:address":"204 Brow Rd",
    "sg:city":"Trenton",
    "sg:classifiers":[
        {
            "category":"Building & Trades",
            "subcategory":"Pest Control",
            "type":"Services"
        }
    ],
    "sg:phone":"+1 706 657 6841",
    "sg:postcode":"30752",
    "sg:province":"GA",
    "wof:name":"Smith Exterminating Co",
    "wof:placetype":"venue"
},
  "geometry": {"coordinates":[-85.534108,34.878161],"type":"Point"}
}