{
  "type": "Feature",
  "properties": {
    "addr:full":"1590 Island Way Buford GA 30519",
    "addr:housenumber":"1590",
    "addr:postcode":"30519",
    "addr:street":"Island Way",
    "iso:country":"US",
    "sg:address":"1590 Island Way",
    "sg:city":"Buford",
    "sg:classifiers":[
        {
            "category":"Place Of Worship",
            "type":"Public Place"
        }
    ],
    "sg:phone":"+1 770 932 2439",
    "sg:postcode":"30519",
    "sg:province":"GA",
    "sg:tags":[
        "church"
    ],
    "wof:name":"Bethel & Bethel",
    "wof:placetype":"venue"
},
  "geometry": {"coordinates":[-83.977531,34.04818],"type":"Point"}
}