{
  "type": "Feature",
  "properties": {
    "iso:country":"US",
    "sg:address":"1070 Abingdon Ln",
    "sg:city":"Alpharetta",
    "sg:classifiers":[
        {
            "category":"Professional",
            "type":"Services"
        }
    ],
    "sg:phone":"+1 770 667 9863",
    "sg:postcode":"30022",
    "sg:province":"GA",
    "wof:name":"Kapali P & Lynne Eswaran",
    "wof:placetype":"venue"
},
  "geometry": {"coordinates":[-84.251068,34.012897],"type":"Point"}
}