{
  "type": "Feature",
  "properties": {
    "iso:country":"US",
    "sg:address":"3030 Dodson Dr",
    "sg:city":"Atlanta",
    "sg:classifiers":[
        {
            "category":"Professional",
            "subcategory":"Advertising",
            "type":"Services"
        }
    ],
    "sg:phone":"+1 404 629 1887",
    "sg:postcode":"30344",
    "sg:province":"GA",
    "sg:tags":[
        "agency",
        "specialty"
    ],
    "sg:website":"http://www.museusa.com",
    "wof:name":"Muse Communications, Inc.",
    "wof:placetype":"venue"
},
  "geometry": {"coordinates":[-84.47719600000001,33.672431],"type":"Point"}
}