{
  "type": "Feature",
  "properties": {
    "addr:full":"795 Grogan St Lavonia GA 30553",
    "addr:housenumber":"795",
    "addr:postcode":"30553",
    "addr:street":"Grogan St",
    "iso:country":"US",
    "sg:address":"795 Grogan St",
    "sg:city":"Lavonia",
    "sg:classifiers":[
        {
            "category":"Manufacturing",
            "subcategory":"Printing",
            "type":"Manufacturing & Wholesale Goods"
        }
    ],
    "sg:phone":"+1 706 779 7490",
    "sg:postcode":"30553",
    "sg:province":"GA",
    "sg:tags":[
        "newspaper"
    ],
    "wof:name":"Anderson Independent",
    "wof:placetype":"venue"
},
  "geometry": {"coordinates":[-83.106994,34.435307],"type":"Point"}
}