{
  "type": "Feature",
  "properties": {
    "addr:full":"865 Riverhaven Dr Suwanee GA 30024",
    "addr:housenumber":"865",
    "addr:postcode":"30024",
    "addr:street":"Riverhaven Dr",
    "iso:country":"US",
    "sg:address":"865 Riverhaven Dr",
    "sg:city":"Suwanee",
    "sg:classifiers":[
        {
            "category":"Building & Trades",
            "subcategory":"Construction",
            "type":"Services"
        }
    ],
    "sg:phone":"+1 770 889 3831",
    "sg:postcode":"30024",
    "sg:province":"GA",
    "sg:tags":[
        "house",
        "general",
        "contractor"
    ],
    "wof:name":"Accent Construction LLC",
    "wof:placetype":"venue"
},
  "geometry": {"coordinates":[-84.110922,34.101794],"type":"Point"}
}