{
  "type": "Feature",
  "properties": {
    "addr:full":"301 Wilson Dr Macon GA 31217",
    "addr:housenumber":"301",
    "addr:postcode":"31217",
    "addr:street":"Wilson Dr",
    "iso:country":"US",
    "sg:address":"301 Wilson Dr",
    "sg:city":"Macon",
    "sg:classifiers":[
        {
            "category":"Fast Food",
            "type":"Food & Drink"
        },
        {
            "category":"Restaurant",
            "type":"Food & Drink"
        },
        {
            "category":"Food & Beverages",
            "subcategory":"Groceries & Convenience Stores",
            "type":"Retail Goods"
        }
    ],
    "sg:phone":"+1 770 228 7700",
    "sg:postcode":"31217",
    "sg:province":"GA",
    "sg:tags":[
        "shop",
        "american",
        "sandwich",
        "take"
    ],
    "wof:name":"Subway",
    "wof:placetype":"venue"
},
  "geometry": {"coordinates":[-83.435052,32.827319],"type":"Point"}
}