{
  "type": "Feature",
  "properties": {
    "addr:full":"7646 Granite Dr Douglasville GA 30134",
    "addr:housenumber":"7646",
    "addr:postcode":"30134",
    "addr:street":"Granite Dr",
    "iso:country":"US",
    "sg:address":"7646 Granite Dr",
    "sg:city":"Douglasville",
    "sg:classifiers":[
        {
            "category":"Building & Trades",
            "subcategory":"Construction",
            "type":"Services"
        }
    ],
    "sg:phone":"+1 770 949 7638",
    "sg:postcode":"30134",
    "sg:province":"GA",
    "sg:tags":[
        "general",
        "contractor"
    ],
    "wof:name":"A B & G Fire Restoration",
    "wof:placetype":"venue"
},
  "geometry": {"coordinates":[-84.776161,33.738315],"type":"Point"}
}