{
  "type": "Feature",
  "properties": {
    "addr:full":"5302 State Rte 115 E Cleveland GA 30528",
    "addr:housenumber":"5302",
    "addr:postcode":"30528",
    "addr:street":"State Rte 115 E",
    "iso:country":"US",
    "sg:address":"5302 State Rte 115 E",
    "sg:city":"Cleveland",
    "sg:classifiers":[
        {
            "category":"Freight",
            "type":"Transportation"
        }
    ],
    "sg:phone":"+1 706 865 3600",
    "sg:postcode":"30528",
    "sg:province":"GA",
    "sg:tags":[
        "mail",
        "us",
        "contractor"
    ],
    "wof:name":"Lonnie M Nix Inc",
    "wof:placetype":"venue"
},
  "geometry": {"coordinates":[-83.67393300000001,34.578308],"type":"Point"}
}