{
  "type": "Feature",
  "properties": {
    "iso:country":"US",
    "sg:address":"3800 Broadway",
    "sg:city":"Macon",
    "sg:classifiers":[
        {
            "category":"Home & Garden",
            "subcategory":"Household Appliances",
            "type":"Retail Goods"
        },
        {
            "category":"Shopping",
            "subcategory":"Mobile Phones",
            "type":"Retail Goods"
        },
        {
            "category":"Building & Trades",
            "subcategory":"Construction",
            "type":"Services"
        },
        {
            "category":"Home & Garden",
            "subcategory":"Mobile Homes",
            "type":"Retail Goods"
        },
        {
            "category":"Utilities",
            "subcategory":"Mobile Phone",
            "type":"Services"
        }
    ],
    "sg:phone":"+1 478 781 7922",
    "sg:postcode":"31206",
    "sg:province":"GA",
    "sg:tags":[
        "homes-equipment",
        "specialty",
        "heating",
        "system",
        "pump",
        "part",
        "contractor",
        "homes-repair",
        "heat",
        "air conditioning"
    ],
    "sg:website":"http://www.oquinnmobilehomesupply.com",
    "wof:name":"O'Quinn Mobile Home Supply",
    "wof:placetype":"venue"
},
  "geometry": {"coordinates":[-83.642019,32.796141],"type":"Point"}
}