{
  "type": "Feature",
  "properties": {
    "addr:full":"1875 Lincolnton Hwy Elberton GA 30635",
    "addr:housenumber":"1875",
    "addr:postcode":"30635",
    "addr:street":"Lincolnton Hwy",
    "iso:country":"US",
    "sg:address":"1875 Lincolnton Hwy",
    "sg:city":"Elberton",
    "sg:classifiers":[
        {
            "category":"Retail",
            "subcategory":"Auto Repair",
            "type":"Services"
        }
    ],
    "sg:phone":"+1 706 283 5355",
    "sg:postcode":"30635",
    "sg:province":"GA",
    "sg:tags":[
        "automotive"
    ],
    "wof:name":"John A Rice",
    "wof:placetype":"venue"
},
  "geometry": {"coordinates":[-82.666763,34.022194],"type":"Point"}
}