{
  "type": "Feature",
  "properties": {
    "iso:country":"US",
    "sg:address":"22 Bennett St NW",
    "sg:city":"Atlanta",
    "sg:classifiers":[
        {
            "category":"Arts & Performance",
            "subcategory":"Art Gallery",
            "type":"Entertainment"
        }
    ],
    "sg:phone":"+1 404 352 3778",
    "sg:postcode":"30309",
    "sg:province":"GA",
    "sg:website":"www.britishwatercolors.com",
    "wof:name":"Thomas Deans Fine Art",
    "wof:placetype":"venue"
},
  "geometry": {"coordinates":[-84.393196,33.811991],"type":"Point"}
}