{
  "type": "Feature",
  "properties": {
    "addr:full":"708 E 1st St Rome GA 30161",
    "addr:housenumber":"708",
    "addr:postcode":"ga 30161",
    "addr:street":"E 1St St",
    "iso:country":"US",
    "sg:address":"708 E 1st St",
    "sg:city":"Rome",
    "sg:classifiers":[
        {
            "category":"Organizations",
            "subcategory":"Professional Association",
            "type":"Services"
        }
    ],
    "sg:phone":"+1 706 295 0045",
    "sg:postcode":"30161",
    "sg:province":"GA",
    "wof:name":"Building Industry Assn Of Rome",
    "wof:placetype":"venue"
},
  "geometry": {"coordinates":[-85.165685,34.255897],"type":"Point"}
}