{
  "type": "Feature",
  "properties": {
    "iso:country":"US",
    "sg:address":"2262 Jaycee Shack Rd",
    "sg:city":"Valdosta",
    "sg:classifiers":[
        {
            "category":"Building & Trades",
            "subcategory":"Electrical",
            "type":"Services"
        }
    ],
    "sg:phone":"+1 229 253 9700",
    "sg:postcode":"31602",
    "sg:province":"GA",
    "sg:tags":[
        "electric",
        "contractor"
    ],
    "wof:name":"All Star Electric & Ind Contrs",
    "wof:placetype":"venue"
},
  "geometry": {"coordinates":[-83.253664,30.871783],"type":"Point"}
}