{
  "type": "Feature",
  "properties": {
    "addr:full":"1716 US Hwy 80 Bloomingdale GA 31302",
    "addr:housenumber":"1716",
    "addr:postcode":"31302",
    "addr:street":"Us Hwy 80",
    "iso:country":"US",
    "sg:address":"1716 US Hwy 80",
    "sg:city":"Bloomingdale",
    "sg:classifiers":[
        {
            "category":"Freight",
            "type":"Transportation"
        }
    ],
    "sg:phone":"+1 912 748 9600",
    "sg:postcode":"31302",
    "sg:province":"GA",
    "sg:tags":[
        "general"
    ],
    "wof:name":"80 West Mini Storage Inc",
    "wof:placetype":"venue"
},
  "geometry": {"coordinates":[-81.32799199999999,32.141731],"type":"Point"}
}