{
  "type": "Feature",
  "properties": {
    "iso:country":"US",
    "sg:address":"2851 Washington Rd",
    "sg:city":"Augusta",
    "sg:classifiers":[
        {
            "category":"Banks & Credit Unions",
            "subcategory":"Investment Brokerage",
            "type":"Services"
        }
    ],
    "sg:phone":"+1 706 738 3475",
    "sg:postcode":"30904",
    "sg:province":"GA",
    "wof:name":"K W Investment",
    "wof:placetype":"venue"
},
  "geometry": {"coordinates":[-82.03613900000001,33.510972],"type":"Point"}
}