{
  "type": "Feature",
  "properties": {
    "addr:full":"1981 Long Ridge Dr Macon GA 31211",
    "addr:housenumber":"1981",
    "addr:postcode":"31211",
    "addr:street":"Long Ridge Dr",
    "iso:country":"US",
    "sg:address":"1981 Long Ridge Dr",
    "sg:city":"Macon",
    "sg:classifiers":[
        {
            "category":"Shopping",
            "subcategory":"Florist",
            "type":"Retail Goods"
        }
    ],
    "sg:phone":"+1 478 742 7146",
    "sg:postcode":"31211",
    "sg:province":"GA",
    "wof:name":"Moseley & Flowers Enterprise",
    "wof:placetype":"venue"
},
  "geometry": {"coordinates":[-83.61640800000001,32.870965],"type":"Point"}
}