{
  "type": "Feature",
  "properties": {
    "iso:country":"US",
    "sg:address":"208 Holt St",
    "sg:city":"Thomson",
    "sg:classifiers":[
        {
            "category":"Taxi",
            "type":"Transportation"
        }
    ],
    "sg:phone":"+1 706 597 0420",
    "sg:postcode":"30824",
    "sg:province":"GA",
    "sg:tags":[
        "taxicab"
    ],
    "wof:name":"Starvel Taxi Service",
    "wof:placetype":"venue"
},
  "geometry": {"coordinates":[-82.502658,33.471079],"type":"Point"}
}