{
  "type": "Feature",
  "properties": {
    "iso:country":"US",
    "sg:address":"51 S Fairground St SE",
    "sg:city":"Marietta",
    "sg:classifiers":[
        {
            "category":"Retail",
            "subcategory":"Auto Repair",
            "type":"Services"
        }
    ],
    "sg:phone":"+1 770 426 5167",
    "sg:postcode":"30060",
    "sg:province":"GA",
    "sg:tags":[
        "repairing",
        "automobile"
    ],
    "wof:name":"Auto Test Diagnostics & Oil Change",
    "wof:placetype":"venue"
},
  "geometry": {"coordinates":[-84.535797,33.949501],"type":"Point"}
}