{
  "type": "Feature",
  "properties": {
    "iso:country":"US",
    "sg:address":"4820 Clark Howell Hwy",
    "sg:city":"Atlanta",
    "sg:classifiers":[
        {
            "category":"Landmark",
            "subcategory":"Tourist Information",
            "type":"Public Place"
        }
    ],
    "sg:phone":"+1 404 765 9646",
    "sg:postcode":"30349",
    "sg:province":"GA",
    "sg:tags":[
        "promoter",
        "tours-operators"
    ],
    "wof:name":"Seibu Transportation Co LTD",
    "wof:placetype":"venue"
},
  "geometry": {"coordinates":[-84.408726,33.623789],"type":"Point"}
}