{
  "type": "Feature",
  "properties": {
    "addr:full":"48 Market Cir Newnan GA 30277",
    "addr:housenumber":"48",
    "addr:postcode":"30277",
    "addr:street":"Market Cir",
    "iso:country":"US",
    "sg:address":"48 Market Cir",
    "sg:city":"Newnan",
    "sg:classifiers":[
        {
            "category":"Health Services",
            "subcategory":"Doctor",
            "type":"Services"
        }
    ],
    "sg:phone":"+1 404 880 0777",
    "sg:postcode":"30277",
    "sg:province":"GA",
    "sg:tags":[
        "medical"
    ],
    "wof:name":"Med One Emf",
    "wof:placetype":"venue"
},
  "geometry": {"coordinates":[-84.64600299999999,33.3993],"type":"Point"}
}