{
  "type": "Feature",
  "properties": {
    "addr:full":"1258 Creekside Ct Smyrna GA 30080",
    "addr:housenumber":"1258",
    "addr:postcode":"30080",
    "addr:street":"Creekside Ct",
    "iso:country":"US",
    "sg:address":"1258 Creekside Ct",
    "sg:city":"Smyrna",
    "sg:classifiers":[
        {
            "category":"Professional",
            "type":"Services"
        }
    ],
    "sg:phone":"+1 770 805 9700",
    "sg:postcode":"30080",
    "sg:province":"GA",
    "wof:name":"Eclectic Surroundings",
    "wof:placetype":"venue"
},
  "geometry": {"coordinates":[-84.483075,33.887921],"type":"Point"}
}