{
  "type": "Feature",
  "properties": {
    "iso:country":"US",
    "sg:address":"2324 Acworth Due West Rd NW",
    "sg:city":"Acworth",
    "sg:classifiers":[
        {
            "category":"Building & Trades",
            "subcategory":"Plumbing",
            "type":"Services"
        }
    ],
    "sg:phone":"+1 770 529 0055",
    "sg:postcode":"30152",
    "sg:province":"GA",
    "sg:tags":[
        "tank",
        "septic"
    ],
    "wof:name":"Silas Payne Septic Tanks",
    "wof:placetype":"venue"
},
  "geometry": {"coordinates":[-84.678549,34.00922],"type":"Point"}
}