{
  "type": "Feature",
  "properties": {
    "addr:full":"2774 Candler Rd Decatur GA 30034",
    "addr:housenumber":"2774",
    "addr:postcode":"30034",
    "addr:street":"Candler Rd",
    "iso:country":"US",
    "sg:address":"2774 Candler Rd",
    "sg:city":"Decatur",
    "sg:classifiers":[
        {
            "category":"Shopping",
            "subcategory":"Clothing, Apparel, & Fashions",
            "type":"Retail Goods"
        }
    ],
    "sg:phone":"+1 404 212 3880",
    "sg:postcode":"30034",
    "sg:province":"GA",
    "sg:website":"www.simplyfashions.com",
    "wof:name":"Simply Fashions",
    "wof:placetype":"venue"
},
  "geometry": {"coordinates":[-84.27197200000001,33.708829],"type":"Point"}
}