{
  "type": "Feature",
  "properties": {
    "addr:full":"5548 Ogeechee Rd Savannah GA 31405",
    "addr:housenumber":"5548",
    "addr:postcode":"31405",
    "addr:street":"Ogeechee Rd",
    "iso:country":"US",
    "sg:address":"5548 Ogeechee Rd",
    "sg:city":"Savannah",
    "sg:classifiers":[
        {
            "category":"Wholesale",
            "subcategory":"Machinery & Supplies",
            "type":"Manufacturing & Wholesale Goods"
        },
        {
            "category":"Wholesale",
            "subcategory":"Scrap",
            "type":"Manufacturing & Wholesale Goods"
        }
    ],
    "sg:phone":"+1 912 234 4862",
    "sg:postcode":"31405",
    "sg:province":"GA",
    "sg:tags":[
        "s",
        "recycling",
        "refuse",
        "mach",
        "center"
    ],
    "wof:name":"A B C Crushing & Recycling",
    "wof:placetype":"venue"
},
  "geometry": {"coordinates":[-81.21172300000001,32.038852],"type":"Point"}
}