{
  "type": "Feature",
  "properties": {
    "addr:full":"301 N Peterson Ave Douglas GA 31533",
    "addr:housenumber":"301",
    "addr:postcode":"31533",
    "addr:street":"N Peterson Ave",
    "iso:country":"US",
    "sg:address":"301 N Peterson Ave",
    "sg:city":"Douglas",
    "sg:classifiers":[
        {
            "category":"Personal",
            "type":"Services"
        }
    ],
    "sg:phone":"+1 912 384 5353",
    "sg:postcode":"31533",
    "sg:province":"GA",
    "wof:name":"Pamper ME Please Salon",
    "wof:placetype":"venue"
},
  "geometry": {"coordinates":[-82.850385,31.510551],"type":"Point"}
}