{
  "type": "Feature",
  "properties": {
    "addr:full":"118 N Jefferson St Dublin GA 31021",
    "addr:housenumber":"118",
    "addr:postcode":"31021",
    "addr:street":"N Jefferson St",
    "iso:country":"US",
    "sg:address":"118 N Jefferson St",
    "sg:city":"Dublin",
    "sg:classifiers":[
        {
            "category":"Restaurant",
            "type":"Food & Drink"
        }
    ],
    "sg:phone":"+1 478 272 4948",
    "sg:postcode":"31021",
    "sg:province":"GA",
    "wof:name":"H & S Lunch Room",
    "wof:placetype":"venue"
},
  "geometry": {"coordinates":[-82.92153500000001,32.566765],"type":"Point"}
}