{
  "type": "Feature",
  "properties": {
    "addr:full":"675 Ponce de Leon Ave NE Atlanta GA 30308",
    "addr:housenumber":"675",
    "addr:postcode":"30308",
    "addr:street":"Ponce De Leon Ave Ne",
    "iso:country":"US",
    "sg:address":"675 Ponce de Leon Ave NE",
    "sg:city":"Atlanta",
    "sg:classifiers":[
        {
            "category":"Government",
            "subcategory":"Police Station",
            "type":"Public Place"
        }
    ],
    "sg:phone":"+1 404 817 2382",
    "sg:postcode":"30308",
    "sg:province":"GA",
    "sg:tags":[
        "department"
    ],
    "wof:name":"Atlanta Police-Communications",
    "wof:placetype":"venue"
},
  "geometry": {"coordinates":[-84.365825,33.773319],"type":"Point"}
}