{
  "type": "Feature",
  "properties": {
    "addr:full":"1875 Winder Hwy Jefferson GA 30549",
    "addr:housenumber":"1875",
    "addr:postcode":"30549",
    "addr:street":"Winder Hwy",
    "iso:country":"US",
    "sg:address":"1875 Winder Hwy",
    "sg:city":"Jefferson",
    "sg:classifiers":[
        {
            "category":"Restaurant",
            "type":"Food & Drink"
        }
    ],
    "sg:phone":"+1 706 367 0930",
    "sg:postcode":"30549",
    "sg:province":"GA",
    "sg:tags":[
        "eating"
    ],
    "wof:name":"El Camino Mexican Restaurant",
    "wof:placetype":"venue"
},
  "geometry": {"coordinates":[-83.59639900000001,34.10089],"type":"Point"}
}