{
  "type": "Feature",
  "properties": {
    "iso:country":"US",
    "sg:address":"1202 N Ashley St",
    "sg:city":"Valdosta",
    "sg:classifiers":[
        {
            "category":"Wholesale",
            "subcategory":"Hardware",
            "type":"Manufacturing & Wholesale Goods"
        }
    ],
    "sg:phone":"+1 229 259 0173",
    "sg:postcode":"31601",
    "sg:province":"GA",
    "wof:name":"Environmental Home Protection",
    "wof:placetype":"venue"
},
  "geometry": {"coordinates":[-83.280299,30.846049],"type":"Point"}
}