{
  "type": "Feature",
  "properties": {
    "iso:country":"US",
    "sg:address":"718 1st St",
    "sg:city":"Macon",
    "sg:classifiers":[
        {
            "category":"Health Services",
            "subcategory":"Doctor",
            "type":"Services"
        }
    ],
    "sg:phone":"+1 478 750 8777",
    "sg:postcode":"31201",
    "sg:province":"GA",
    "sg:tags":[
        "physician",
        "family",
        "practice",
        "surgeons",
        "medicine",
        "surgeon"
    ],
    "wof:name":"Bibb Family Practice",
    "wof:placetype":"venue"
},
  "geometry": {"coordinates":[-83.634085,32.833337],"type":"Point"}
}