{
  "type": "Feature",
  "properties": {
    "iso:country":"US",
    "sg:address":"1964 Neptune Dr",
    "sg:city":"Augusta",
    "sg:classifiers":[
        {
            "category":"Professional",
            "subcategory":"Business Services",
            "type":"Services"
        }
    ],
    "sg:phone":"+1 706 798 8991",
    "sg:postcode":"30906",
    "sg:province":"GA",
    "wof:name":"Industrial Truck Service Inc",
    "wof:placetype":"venue"
},
  "geometry": {"coordinates":[-82.01427200000001,33.398683],"type":"Point"}
}