{
  "type": "Feature",
  "properties": {
    "addr:full":"1165 Mitchell Bridge Rd Athens GA 30606",
    "addr:housenumber":"1165",
    "addr:postcode":"30606",
    "addr:street":"Mitchell Bridge Rd",
    "iso:country":"US",
    "sg:address":"1165 Mitchell Bridge Rd",
    "sg:city":"Athens",
    "sg:classifiers":[
        {
            "category":"Professional",
            "subcategory":"Accounting & Tax Preparation",
            "type":"Services"
        }
    ],
    "sg:phone":"+1 706 548 8666",
    "sg:postcode":"30606",
    "sg:province":"GA",
    "sg:tags":[
        "accountant"
    ],
    "wof:name":"Paul A Thomas CPA PC",
    "wof:placetype":"venue"
},
  "geometry": {"coordinates":[-83.450473,33.943673],"type":"Point"}
}