{
  "type": "Feature",
  "properties": {
    "iso:country":"US",
    "sg:address":"3146 Chamblee Dunwoody Road",
    "sg:city":"Atlanta",
    "sg:classifiers":[
        {
            "category":"Communications",
            "subcategory":"Newspaper",
            "type":"Services"
        }
    ],
    "sg:phone":"+1 678 209 0213",
    "sg:postcode":"30341",
    "sg:province":"GA",
    "sg:tags":[
        "print",
        "medium"
    ],
    "wof:name":"Land Hope Times",
    "wof:placetype":"venue"
},
  "geometry": {"coordinates":[-84.28777100000001,33.889795],"type":"Point"}
}