{
  "type": "Feature",
  "properties": {
    "addr:full":"28 Bell Ln Braselton GA 30517",
    "addr:housenumber":"28",
    "addr:postcode":"30517",
    "addr:street":"Bell Ln",
    "iso:country":"US",
    "sg:address":"28 Bell Ln",
    "sg:city":"Braselton",
    "sg:classifiers":[
        {
            "category":"Restaurant",
            "type":"Food & Drink"
        }
    ],
    "sg:phone":"+1 706 654 1380",
    "sg:postcode":"30517",
    "sg:province":"GA",
    "wof:name":"Hoschton Cafe",
    "wof:placetype":"venue"
},
  "geometry": {"coordinates":[-83.79160299999999,34.108345],"type":"Point"}
}