{
  "type": "Feature",
  "properties": {
    "addr:full":"5775 Glenridge Drive NE Atlanta GA 30328",
    "addr:housenumber":"5775",
    "addr:postcode":"30328",
    "addr:street":"Glenridge Drive Ne",
    "iso:country":"US",
    "sg:address":"5775 Glenridge Drive NE",
    "sg:city":"Atlanta",
    "sg:classifiers":[
        {
            "category":"Building & Trades",
            "subcategory":"Construction",
            "type":"Services"
        }
    ],
    "sg:phone":"+1 404 851 1889",
    "sg:postcode":"30328",
    "sg:province":"GA",
    "sg:tags":[
        "contractor"
    ],
    "wof:name":"The Peachtree Group",
    "wof:placetype":"venue"
},
  "geometry": {"coordinates":[-84.361784,33.912404],"type":"Point"}
}