{
  "type": "Feature",
  "properties": {
    "addr:full":"5555 Whittlesey Blvd Columbus GA 31909",
    "addr:postcode":"5555;31909",
    "addr:street":"Whittlesey Blvd",
    "iso:country":"US",
    "sg:address":"5555 Whittlesey Blvd",
    "sg:city":"Columbus",
    "sg:classifiers":[
        {
            "category":"Restaurant",
            "type":"Food & Drink"
        }
    ],
    "sg:phone":"+1 706 494 8144",
    "sg:postcode":"31909",
    "sg:province":"GA",
    "wof:name":"Carrabba's Italian Grill",
    "wof:placetype":"venue"
},
  "geometry": {"coordinates":[-84.94133100000001,32.544652],"type":"Point"}
}