{
  "type": "Feature",
  "properties": {
    "iso:country":"US",
    "sg:address":"7853 Kelly Bridge Rd",
    "sg:city":"Dawsonville",
    "sg:classifiers":[
        {
            "category":"Shopping",
            "subcategory":"Florist",
            "type":"Retail Goods"
        }
    ],
    "sg:phone":"+1 770 893 2520",
    "sg:postcode":"30534",
    "sg:province":"GA",
    "wof:name":"Hamilton Flowers",
    "wof:placetype":"venue"
},
  "geometry": {"coordinates":[-84.209551,34.363389],"type":"Point"}
}