{
  "type": "Feature",
  "properties": {
    "iso:country":"US",
    "sg:address":"1182 Pelly Cir NE",
    "sg:city":"Atlanta",
    "sg:classifiers":[
        {
            "category":"Professional",
            "subcategory":"Business Services",
            "type":"Services"
        }
    ],
    "sg:phone":"+1 404 442 9622",
    "sg:postcode":"30319",
    "sg:province":"GA",
    "wof:name":"Assoc LLC",
    "wof:placetype":"venue"
},
  "geometry": {"coordinates":[-84.33901299999999,33.866342],"type":"Point"}
}