{
  "type": "Feature",
  "properties": {
    "addr:full":"697 Walt Carmichael Rd Newnan GA 30263",
    "addr:housenumber":"697",
    "addr:postcode":"30263",
    "addr:street":"Walt Carmichael Rd",
    "iso:country":"US",
    "sg:address":"697 Walt Carmichael Rd",
    "sg:city":"Newnan",
    "sg:classifiers":[
        {
            "category":"Building & Trades",
            "subcategory":"Construction",
            "type":"Services"
        }
    ],
    "sg:phone":"+1 678 378 4978",
    "sg:postcode":"30263",
    "sg:province":"GA",
    "wof:name":"Robinson Home Solutions Inc",
    "wof:placetype":"venue"
},
  "geometry": {"coordinates":[-84.83838900000001,33.475932],"type":"Point"}
}