{
  "type": "Feature",
  "properties": {
    "addr:full":"130 Burnham Wood Ln Alpharetta GA 30022",
    "addr:housenumber":"130",
    "addr:postcode":"30022",
    "addr:street":"Burnham Wood Ln",
    "iso:country":"US",
    "sg:address":"130 Burnham Wood Ln",
    "sg:city":"Alpharetta",
    "sg:classifiers":[
        {
            "category":"Professional",
            "subcategory":"Business Services",
            "type":"Services"
        }
    ],
    "sg:phone":"+1 770 447 4942",
    "sg:postcode":"30022",
    "sg:province":"GA",
    "sg:tags":[
        "interior",
        "design"
    ],
    "wof:name":"Interior Source the",
    "wof:placetype":"venue"
},
  "geometry": {"coordinates":[-84.21869700000001,34.008701],"type":"Point"}
}