{
  "type": "Feature",
  "properties": {
    "iso:country":"US",
    "sg:address":"1225 Clark Rd",
    "sg:city":"Augusta",
    "sg:classifiers":[
        {
            "category":"Building & Trades",
            "subcategory":"Construction",
            "type":"Services"
        }
    ],
    "sg:phone":"+1 706 790 6650",
    "sg:postcode":"30906",
    "sg:province":"GA",
    "sg:tags":[
        "contractor"
    ],
    "wof:name":"Drummer's Enterprises",
    "wof:placetype":"venue"
},
  "geometry": {"coordinates":[-81.963888,33.285231],"type":"Point"}
}