{
  "type": "Feature",
  "properties": {
    "iso:country":"US",
    "sg:address":"130 Dickerson Rd",
    "sg:city":"Franklin",
    "sg:classifiers":[
        {
            "category":"Wholesale",
            "subcategory":"Machinery & Supplies",
            "type":"Manufacturing & Wholesale Goods"
        },
        {
            "category":"Wholesale",
            "subcategory":"Poultry",
            "type":"Manufacturing & Wholesale Goods"
        }
    ],
    "sg:phone":"+1 770 854 5221",
    "sg:postcode":"30217",
    "sg:province":"GA",
    "sg:tags":[
        "equipment"
    ],
    "wof:name":"Reeves Supply Inc",
    "wof:placetype":"venue"
},
  "geometry": {"coordinates":[-85.200853,33.381082],"type":"Point"}
}