{
  "type": "Feature",
  "properties": {
    "iso:country":"US",
    "sg:address":"1592 Johnson Rd",
    "sg:city":"Gainesville",
    "sg:classifiers":[
        {
            "category":"Professional",
            "subcategory":"Management & Consulting",
            "type":"Services"
        }
    ],
    "sg:phone":"+1 770 534 1155",
    "sg:postcode":"30504",
    "sg:province":"GA",
    "wof:name":"Association Resources Inc",
    "wof:placetype":"venue"
},
  "geometry": {"coordinates":[-83.872579,34.306986],"type":"Point"}
}