{
  "type": "Feature",
  "properties": {
    "addr:full":"6132 Covington Hwy Lithonia GA 30058",
    "addr:housenumber":"6132",
    "addr:postcode":"30058",
    "addr:street":"Covington Hwy",
    "iso:country":"US",
    "sg:address":"6132 Covington Hwy",
    "sg:city":"Lithonia",
    "sg:classifiers":[
        {
            "category":"Sports & Exercise",
            "subcategory":"Gym",
            "type":"Entertainment"
        }
    ],
    "sg:phone":"+1 770 808 9294",
    "sg:postcode":"30058",
    "sg:province":"GA",
    "sg:website":"www.ladiesworkoutexpress.com",
    "wof:name":"Ladies Workout Express",
    "wof:placetype":"venue"
},
  "geometry": {"coordinates":[-84.16419999999999,33.722401],"type":"Point"}
}