{
  "type": "Feature",
  "properties": {
    "addr:full":"140 Chase Dr Fayetteville GA 30214",
    "addr:housenumber":"140",
    "addr:postcode":"30214",
    "addr:street":"Chase Dr",
    "iso:country":"US",
    "sg:address":"140 Chase Dr",
    "sg:city":"Fayetteville",
    "sg:classifiers":[
        {
            "category":"Professional",
            "type":"Services"
        }
    ],
    "sg:phone":"+1 770 461 7859",
    "sg:postcode":"30214",
    "sg:province":"GA",
    "wof:name":"Ooddles of Fun Inc",
    "wof:placetype":"venue"
},
  "geometry": {"coordinates":[-84.471433,33.447427],"type":"Point"}
}