{
  "type": "Feature",
  "properties": {
    "iso:country":"US",
    "sg:address":"2008 W Highway 54",
    "sg:city":"Atlanta",
    "sg:classifiers":[
        {
            "category":"Banks & Credit Unions",
            "subcategory":"Bank",
            "type":"Services"
        },
        {
            "category":"Banks & Credit Unions",
            "subcategory":"Financial Services",
            "type":"Services"
        }
    ],
    "sg:phone":"+1 770 631 1114",
    "sg:postcode":"30303",
    "sg:province":"GA",
    "sg:tags":[
        "broker",
        "mortgage"
    ],
    "wof:name":"The Bank of Georgia",
    "wof:placetype":"venue"
},
  "geometry": {"coordinates":[-84.38897,33.755418],"type":"Point"}
}