{
  "type": "Feature",
  "properties": {
    "iso:country":"US",
    "sg:address":"130 Conway Dr",
    "sg:city":"Bogart",
    "sg:classifiers":[
        {
            "category":"Professional",
            "subcategory":"Detective & Security Services",
            "type":"Services"
        }
    ],
    "sg:phone":"+1 706 548 2100",
    "sg:postcode":"30622",
    "sg:province":"GA",
    "sg:tags":[
        "equipment",
        "electrical",
        "system"
    ],
    "wof:name":"Advantage Alarms",
    "wof:placetype":"venue"
},
  "geometry": {"coordinates":[-83.48094500000001,33.942034],"type":"Point"}
}