{
  "type": "Feature",
  "properties": {
    "addr:full":"2160 Satellite Blvd Ste 110 Duluth GA 30097",
    "addr:housenumber":"2160",
    "addr:postcode":"30097",
    "addr:street":"Satellite Blvd Ste 110",
    "iso:country":"US",
    "sg:address":"2160 Satellite Blvd Ste 110",
    "sg:city":"Duluth",
    "sg:classifiers":[
        {
            "category":"Professional",
            "subcategory":"Lawyer & Legal Services",
            "type":"Services"
        }
    ],
    "sg:phone":"+1 770 623 9000",
    "sg:postcode":"30097",
    "sg:province":"GA",
    "wof:name":"Buchanan C Steven Atty",
    "wof:placetype":"venue"
},
  "geometry": {"coordinates":[-84.092598,33.983898],"type":"Point"}
}