{
  "type": "Feature",
  "properties": {
    "addr:full":"5209 Buford Hwy NE Doraville GA 30340",
    "addr:housenumber":"5209",
    "addr:postcode":"30340",
    "addr:street":"Buford Hwy Ne",
    "iso:country":"US",
    "sg:address":"5209 Buford Hwy NE",
    "sg:city":"Doraville",
    "sg:classifiers":[
        {
            "category":"Food & Beverages",
            "subcategory":"Specialty",
            "type":"Retail Goods"
        }
    ],
    "sg:phone":"+1 770 458 6202",
    "sg:postcode":"30340",
    "sg:province":"GA",
    "sg:tags":[
        "herb"
    ],
    "wof:name":"Cindy's Herbs",
    "wof:placetype":"venue"
},
  "geometry": {"coordinates":[-84.28416900000001,33.89268],"type":"Point"}
}