{
  "type": "Feature",
  "properties": {
    "addr:full":"6573 Warren Dr NW Norcross GA 30093",
    "addr:housenumber":"6573",
    "addr:postcode":"30093",
    "addr:street":"Warren Dr Nw",
    "iso:country":"US",
    "sg:address":"6573 Warren Dr NW",
    "sg:city":"Norcross",
    "sg:classifiers":[
        {
            "category":"Manufacturing",
            "subcategory":"Paper Products",
            "type":"Manufacturing & Wholesale Goods"
        }
    ],
    "sg:phone":"+1 770 409 9009",
    "sg:postcode":"30093",
    "sg:province":"GA",
    "sg:tags":[
        "mfg",
        "printing",
        "commercial",
        "pack"
    ],
    "wof:name":"Diversified Tape & Graphics",
    "wof:placetype":"venue"
},
  "geometry": {"coordinates":[-84.221988,33.907746],"type":"Point"}
}