{
  "type": "Feature",
  "properties": {
    "iso:country":"US",
    "sg:address":"257 S Main St",
    "sg:city":"Madison",
    "sg:classifiers":[
        {
            "category":"Organizations",
            "subcategory":"Religious Organization",
            "type":"Services"
        }
    ],
    "sg:phone":"+1 706 343 0003",
    "sg:postcode":"30650",
    "sg:province":"GA",
    "sg:tags":[
        "church"
    ],
    "wof:name":"Christian Cornerstone Center",
    "wof:placetype":"venue"
},
  "geometry": {"coordinates":[-83.468863,33.594885],"type":"Point"}
}