{
  "type": "Feature",
  "properties": {
    "addr:full":"66 Northwood Drive NE Atlanta GA 30342",
    "addr:housenumber":"66",
    "addr:postcode":"30342",
    "addr:street":"Northwood Drive Ne",
    "iso:country":"US",
    "sg:address":"66 Northwood Drive NE",
    "sg:city":"Atlanta",
    "sg:classifiers":[
        {
            "category":"Real Estate",
            "subcategory":"Real Estate Operator",
            "type":"Services"
        }
    ],
    "sg:phone":"+1 404 255 9219",
    "sg:postcode":"30342",
    "sg:province":"GA",
    "sg:tags":[
        "apartment"
    ],
    "wof:name":"Sierraplace Apartments",
    "wof:placetype":"venue"
},
  "geometry": {"coordinates":[-84.38462,33.911066],"type":"Point"}
}