{
  "type": "Feature",
  "properties": {
    "iso:country":"US",
    "sg:address":"3230 Highway 5",
    "sg:city":"Douglasville",
    "sg:classifiers":[
        {
            "category":"Restaurant",
            "type":"Food & Drink"
        }
    ],
    "sg:phone":"+1 770 489 1285",
    "sg:postcode":"30135",
    "sg:province":"GA",
    "sg:tags":[
        "japanese"
    ],
    "wof:name":"Tokyo Japanese Seafood & Steak House",
    "wof:placetype":"venue"
},
  "geometry": {"coordinates":[-84.765297,33.7173],"type":"Point"}
}