{
  "type": "Feature",
  "properties": {
    "iso:country":"US",
    "sg:address":"100 Crescent Center Pkwy",
    "sg:city":"Tucker",
    "sg:classifiers":[
        {
            "category":"Professional",
            "subcategory":"Lawyer & Legal Services",
            "type":"Services"
        }
    ],
    "sg:phone":"+1 770 934 0018",
    "sg:postcode":"30084",
    "sg:province":"GA",
    "sg:tags":[
        "firm",
        "law"
    ],
    "wof:name":"Wilson & Associate Attys PC",
    "wof:placetype":"venue"
},
  "geometry": {"coordinates":[-84.247697,33.838285],"type":"Point"}
}