{
  "type": "Feature",
  "properties": {
    "addr:full":"645 Teague Dr Kennesaw GA 30152",
    "addr:housenumber":"645",
    "addr:postcode":"30152",
    "addr:street":"Teague Dr",
    "iso:country":"US",
    "sg:address":"645 Teague Dr",
    "sg:city":"Kennesaw",
    "sg:classifiers":[
        {
            "category":"Professional",
            "type":"Services"
        }
    ],
    "sg:phone":"+1 770 421 8491",
    "sg:postcode":"30152",
    "sg:province":"GA",
    "wof:name":"Barbara Sparks",
    "wof:placetype":"venue"
},
  "geometry": {"coordinates":[-84.72146499999999,33.971801],"type":"Point"}
}