{
  "type": "Feature",
  "properties": {
    "addr:full":"5900 Sugarloaf Pkwy # 554 Lawrenceville GA 30043",
    "addr:housenumber":"5900",
    "addr:postcode":"30043",
    "addr:street":"Sugarloaf Pkwy # 554",
    "iso:country":"US",
    "sg:address":"5900 Sugarloaf Pkwy # 554",
    "sg:city":"Lawrenceville",
    "sg:classifiers":[
        {
            "category":"Restaurant",
            "type":"Food & Drink"
        }
    ],
    "sg:phone":"+1 678 847 5940",
    "sg:postcode":"30043",
    "sg:province":"GA",
    "sg:tags":[
        "asian",
        "chinese",
        "pan"
    ],
    "sg:website":"http://www.pandaexpress.com",
    "wof:name":"Discover Mills - Panda Express",
    "wof:placetype":"venue"
},
  "geometry": {"coordinates":[-84.078461,33.984901],"type":"Point"}
}