{
  "type": "Feature",
  "properties": {
    "addr:full":"1254 Mile Post Dr Atlanta GA 30338",
    "addr:housenumber":"1254",
    "addr:postcode":"30338",
    "addr:street":"Mile Post Dr",
    "iso:country":"US",
    "sg:address":"1254 Mile Post Dr",
    "sg:city":"Atlanta",
    "sg:classifiers":[
        {
            "category":"Building & Trades",
            "subcategory":"Locksmith",
            "type":"Services"
        }
    ],
    "sg:phone":"+1 770 225 1722",
    "sg:postcode":"30338",
    "sg:province":"GA",
    "sg:tags":[
        "key"
    ],
    "wof:name":"A 1 2 3 24 Hour A Locksmith",
    "wof:placetype":"venue"
},
  "geometry": {"coordinates":[-84.34322,33.936464],"type":"Point"}
}