{
  "type": "Feature",
  "properties": {
    "addr:full":"3601 Jasmine Cove Ln Snellville GA 30039",
    "addr:housenumber":"3601",
    "addr:postcode":"30039",
    "addr:street":"Jasmine Cove Ln",
    "iso:country":"US",
    "sg:address":"3601 Jasmine Cove Ln",
    "sg:city":"Snellville",
    "sg:classifiers":[
        {
            "category":"Home & Garden",
            "subcategory":"Building Materials",
            "type":"Retail Goods"
        }
    ],
    "sg:phone":"+1 770 985 2295",
    "sg:postcode":"30039",
    "sg:province":"GA",
    "sg:tags":[
        "glass",
        "leaded"
    ],
    "wof:name":"Maury's Stained Glass",
    "wof:placetype":"venue"
},
  "geometry": {"coordinates":[-84.062764,33.790623],"type":"Point"}
}