{
  "type": "Feature",
  "properties": {
    "addr:full":"3 Sleepy Terrapin Ln Savannah GA 31411",
    "addr:housenumber":"3",
    "addr:postcode":"31411",
    "addr:street":"Sleepy Terrapin Ln",
    "iso:country":"US",
    "sg:address":"3 Sleepy Terrapin Ln",
    "sg:city":"Savannah",
    "sg:classifiers":[
        {
            "category":"Professional",
            "subcategory":"Business Services",
            "type":"Services"
        }
    ],
    "sg:phone":"+1 912 598 9343",
    "sg:postcode":"31411",
    "sg:province":"GA",
    "sg:tags":[
        "mediator"
    ],
    "wof:name":"William Runyan",
    "wof:placetype":"venue"
},
  "geometry": {"coordinates":[-81.048232,31.917677],"type":"Point"}
}