{
  "type": "Feature",
  "properties": {
    "addr:full":"221 S Main St Alpharetta GA 30004",
    "addr:housenumber":"221",
    "addr:postcode":"30004",
    "addr:street":"S Main St",
    "iso:country":"US",
    "sg:address":"221 S Main St",
    "sg:city":"Alpharetta",
    "sg:classifiers":[
        {
            "category":"Manufacturing",
            "subcategory":"Signs",
            "type":"Manufacturing & Wholesale Goods"
        }
    ],
    "sg:phone":"+1 770 751 0772",
    "sg:postcode":"30004",
    "sg:province":"GA",
    "sg:tags":[
        "mfg",
        "advertising",
        "specialty"
    ],
    "wof:name":"ASAP Signs & Banners Inc",
    "wof:placetype":"venue"
},
  "geometry": {"coordinates":[-84.299497,34.068843],"type":"Point"}
}