{
  "type": "Feature",
  "properties": {
    "iso:country":"US",
    "sg:address":"316 Nichols Rd",
    "sg:city":"Suwanee",
    "sg:classifiers":[
        {
            "category":"Building & Trades",
            "subcategory":"Construction",
            "type":"Services"
        }
    ],
    "sg:phone":"+1 770 757 0772",
    "sg:postcode":"30024",
    "sg:province":"GA",
    "sg:tags":[
        "home",
        "improvement"
    ],
    "wof:name":"Geyer Construction",
    "wof:placetype":"venue"
},
  "geometry": {"coordinates":[-84.132274,34.117323],"type":"Point"}
}