{
  "type": "Feature",
  "properties": {
    "iso:country":"US",
    "sg:address":"252 Shelburn Dr",
    "sg:city":"Riverdale",
    "sg:classifiers":[
        {
            "category":"Professional",
            "type":"Services"
        }
    ],
    "sg:phone":"+1 770 991 0456",
    "sg:postcode":"30274",
    "sg:province":"GA",
    "wof:name":"Henry G Hawkins",
    "wof:placetype":"venue"
},
  "geometry": {"coordinates":[-84.395747,33.583361],"type":"Point"}
}