{
  "type": "Feature",
  "properties": {
    "iso:country":"US",
    "sg:address":"502 W 6th St",
    "sg:city":"Waynesboro",
    "sg:classifiers":[
        {
            "category":"Autos & Motor Vehicles",
            "subcategory":"Automobile Sales",
            "type":"Retail Goods"
        }
    ],
    "sg:phone":"+1 706 554 2131",
    "sg:postcode":"30830",
    "sg:province":"GA",
    "sg:tags":[
        "car",
        "dealer"
    ],
    "sg:website":"www.linkauto.com",
    "wof:name":"Link Chevrolet-Pontiac",
    "wof:placetype":"venue"
},
  "geometry": {"coordinates":[-82.020595,33.087616],"type":"Point"}
}