{
  "type": "Feature",
  "properties": {
    "addr:full":"1918 Highway 74 N Atlanta GA 30303",
    "addr:housenumber":"1918",
    "addr:postcode":"30303",
    "addr:street":"Highway 74 N",
    "iso:country":"US",
    "sg:address":"1918 Highway 74 N",
    "sg:city":"Atlanta",
    "sg:classifiers":[
        {
            "category":"Banks & Credit Unions",
            "subcategory":"Atm",
            "type":"Services"
        }
    ],
    "sg:phone":"+1 770 964 2575",
    "sg:postcode":"30303",
    "sg:province":"GA",
    "sg:tags":[
        "bankruptcy"
    ],
    "wof:name":"Rogers and Cates P C",
    "wof:placetype":"venue"
},
  "geometry": {"coordinates":[-84.39070100000001,33.756302],"type":"Point"}
}