{
  "type": "Feature",
  "properties": {
    "iso:country":"US",
    "sg:address":"189 W Athens St",
    "sg:city":"Winder",
    "sg:classifiers":[
        {
            "category":"Restaurant",
            "type":"Food & Drink"
        }
    ],
    "sg:menulink":"http://www.allmenus.com/ga/winder/244397-safari/menu/",
    "sg:phone":"+1 770 868 1589",
    "sg:postcode":"30680",
    "sg:province":"GA",
    "sg:tags":[
        "american"
    ],
    "wof:name":"Safari",
    "wof:placetype":"venue"
},
  "geometry": {"coordinates":[-83.734425,33.995525],"type":"Point"}
}