{
  "type": "Feature",
  "properties": {
    "iso:country":"US",
    "sg:address":"345 E Lake Rd",
    "sg:city":"Mcdonough",
    "sg:classifiers":[
        {
            "category":"Place Of Worship",
            "subcategory":"Church",
            "type":"Public Place"
        },
        {
            "category":"Place Of Worship",
            "type":"Public Place"
        }
    ],
    "sg:phone":"+1 678 432 5138",
    "sg:postcode":"30252",
    "sg:province":"GA",
    "sg:tags":[
        "churches-baptist-general",
        "churches-baptist-southern",
        "churches-baptist"
    ],
    "sg:website":"http://www.glenhavenbaptist.com",
    "wof:name":"Glenn Haven Baptist Church",
    "wof:placetype":"venue"
},
  "geometry": {"coordinates":[-84.127605,33.507488],"type":"Point"}
}