{
  "type": "Feature",
  "properties": {
    "addr:full":"4270 Olde Mill Ln NE Atlanta GA 30342",
    "addr:housenumber":"4270",
    "addr:postcode":"30342",
    "addr:street":"Olde Mill Ln Ne",
    "iso:country":"US",
    "sg:address":"4270 Olde Mill Ln NE",
    "sg:city":"Atlanta",
    "sg:classifiers":[
        {
            "category":"Wholesale",
            "subcategory":"Painting Supplies",
            "type":"Manufacturing & Wholesale Goods"
        }
    ],
    "sg:phone":"+1 404 531 9456",
    "sg:postcode":"30342",
    "sg:province":"GA",
    "sg:tags":[
        "importing",
        "wholesaling",
        "consulting"
    ],
    "wof:name":"Horsley Marketing Services",
    "wof:placetype":"venue"
},
  "geometry": {"coordinates":[-84.37696800000001,33.874071],"type":"Point"}
}