{
  "type": "Feature",
  "properties": {
    "addr:full":"111 N Center St Lakeland GA 31635",
    "addr:housenumber":"111",
    "addr:postcode":"31635",
    "addr:street":"N Center St",
    "iso:country":"US",
    "sg:address":"111 N Center St",
    "sg:city":"Lakeland",
    "sg:classifiers":[
        {
            "category":"Building & Trades",
            "subcategory":"Construction",
            "type":"Services"
        }
    ],
    "sg:phone":"+1 229 482 3114",
    "sg:postcode":"31635",
    "sg:province":"GA",
    "sg:tags":[
        "tile",
        "dealer"
    ],
    "wof:name":"Lakeland Tile & Marble Co",
    "wof:placetype":"venue"
},
  "geometry": {"coordinates":[-83.07438999999999,31.042003],"type":"Point"}
}