{
  "type": "Feature",
  "properties": {
    "addr:full":"3211 Cherokee Rd Atlanta GA 30340",
    "addr:housenumber":"3211",
    "addr:postcode":"30340",
    "addr:street":"Cherokee Rd",
    "iso:country":"US",
    "sg:address":"3211 Cherokee Rd",
    "sg:city":"Atlanta",
    "sg:classifiers":[
        {
            "category":"Personal",
            "type":"Services"
        }
    ],
    "sg:phone":"+1 404 349 9832",
    "sg:postcode":"30340",
    "sg:province":"GA",
    "sg:tags":[
        "consultant",
        "program",
        "health",
        "fitness"
    ],
    "wof:name":"Health Care Staffing",
    "wof:placetype":"venue"
},
  "geometry": {"coordinates":[-84.268715,33.894741],"type":"Point"}
}