{
  "type": "Feature",
  "properties": {
    "addr:full":"5444 Panola Way Ln Lithonia GA 30058",
    "addr:housenumber":"5444",
    "addr:postcode":"30058",
    "addr:street":"Panola Way Ln",
    "iso:country":"US",
    "sg:address":"5444 Panola Way Ln",
    "sg:city":"Lithonia",
    "sg:classifiers":[
        {
            "category":"Retail",
            "subcategory":"Auto Repair",
            "type":"Services"
        }
    ],
    "sg:phone":"+1 770 987 1900",
    "sg:postcode":"30058",
    "sg:province":"GA",
    "sg:tags":[
        "wrecker"
    ],
    "wof:name":"Georgia Towing Svc",
    "wof:placetype":"venue"
},
  "geometry": {"coordinates":[-84.168494,33.730319],"type":"Point"}
}