{
  "type": "Feature",
  "properties": {
    "addr:full":"2711 Culverton Dr Augusta GA 30909",
    "addr:housenumber":"2711",
    "addr:postcode":"30909",
    "addr:street":"Culverton Dr",
    "iso:country":"US",
    "sg:address":"2711 Culverton Dr",
    "sg:city":"Augusta",
    "sg:classifiers":[
        {
            "category":"Wholesale",
            "subcategory":"Office Equipment",
            "type":"Manufacturing & Wholesale Goods"
        },
        {
            "category":"Professional",
            "subcategory":"Computer Services",
            "type":"Services"
        }
    ],
    "sg:phone":"+1 706 228 4616",
    "sg:postcode":"30909",
    "sg:province":"GA",
    "sg:tags":[
        "custom",
        "register",
        "cash",
        "programing",
        "supply"
    ],
    "wof:name":"Millennium Resources",
    "wof:placetype":"venue"
},
  "geometry": {"coordinates":[-82.111239,33.454737],"type":"Point"}
}