{
  "type": "Feature",
  "properties": {
    "iso:country":"US",
    "sg:address":"575 Old Norcross Rd",
    "sg:city":"Lawrenceville",
    "sg:classifiers":[
        {
            "category":"Building & Trades",
            "subcategory":"Construction",
            "type":"Services"
        }
    ],
    "sg:phone":"+1 770 682 9391",
    "sg:postcode":"30045",
    "sg:province":"GA",
    "sg:tags":[
        "general",
        "contractor"
    ],
    "wof:name":"Williams and Bowling Builders",
    "wof:placetype":"venue"
},
  "geometry": {"coordinates":[-84.005686,33.959624],"type":"Point"}
}