{
  "type": "Feature",
  "properties": {
    "iso:country":"US",
    "sg:address":"2511 Mahan Dr",
    "sg:city":"Waycross",
    "sg:classifiers":[
        {
            "category":"Professional",
            "subcategory":"Advertising",
            "type":"Services"
        }
    ],
    "sg:phone":"+1 912 285 1817",
    "sg:postcode":"31501",
    "sg:province":"GA",
    "wof:name":"Callaway Communications",
    "wof:placetype":"venue"
},
  "geometry": {"coordinates":[-82.356452,31.247402],"type":"Point"}
}