{
  "type": "Feature",
  "properties": {
    "addr:full":"1301 Ferncreek Dr Watkinsville GA 30677",
    "addr:housenumber":"1301",
    "addr:postcode":"30677",
    "addr:street":"Ferncreek Dr",
    "iso:country":"US",
    "sg:address":"1301 Ferncreek Dr",
    "sg:city":"Watkinsville",
    "sg:classifiers":[
        {
            "category":"Wholesale",
            "subcategory":"Durable Goods & Equipment",
            "type":"Manufacturing & Wholesale Goods"
        }
    ],
    "sg:phone":"+1 770 725 1770",
    "sg:postcode":"30677",
    "sg:province":"GA",
    "sg:tags":[
        "exporter"
    ],
    "wof:name":"Everword Media",
    "wof:placetype":"venue"
},
  "geometry": {"coordinates":[-83.536073,33.924544],"type":"Point"}
}