{
  "type": "Feature",
  "properties": {
    "addr:full":"621 Augusta Rd North Augusta SC 29822",
    "addr:housenumber":"621",
    "addr:postcode":"29822",
    "addr:street":"Augusta Rd",
    "iso:country":"US",
    "sg:address":"621 Augusta Rd",
    "sg:city":"North Augusta",
    "sg:classifiers":[
        {
            "category":"Professional",
            "subcategory":"Advertising",
            "type":"Services"
        }
    ],
    "sg:phone":"+1 803 278 3100",
    "sg:postcode":"29822",
    "sg:province":"SC",
    "sg:tags":[
        "distribution"
    ],
    "wof:name":"K & R Wholesale Distribution",
    "wof:placetype":"venue"
},
  "geometry": {"coordinates":[-81.89203000000001,33.49672],"type":"Point"}
}