{
  "type": "Feature",
  "properties": {
    "addr:full":"6163 Katherine Rd Rex GA 30273",
    "addr:housenumber":"6163",
    "addr:postcode":"30273",
    "addr:street":"Katherine Rd",
    "iso:country":"US",
    "sg:address":"6163 Katherine Rd",
    "sg:city":"Rex",
    "sg:classifiers":[
        {
            "category":"Banks & Credit Unions",
            "subcategory":"Financial Services",
            "type":"Services"
        }
    ],
    "sg:phone":"+1 770 507 5944",
    "sg:postcode":"30273",
    "sg:province":"GA",
    "sg:tags":[
        "investor"
    ],
    "wof:name":"Tb Real Estate Investors",
    "wof:placetype":"venue"
},
  "geometry": {"coordinates":[-84.273461,33.586135],"type":"Point"}
}