{
  "type": "Feature",
  "properties": {
    "addr:full":"2600 Skyland Dr NE Atlanta GA 30319",
    "addr:housenumber":"2600",
    "addr:postcode":"30319",
    "addr:street":"Skyland Dr Ne",
    "iso:country":"US",
    "sg:address":"2600 Skyland Dr NE",
    "sg:city":"Atlanta",
    "sg:classifiers":[
        {
            "category":"Organizations",
            "subcategory":"Professional Association",
            "type":"Services"
        }
    ],
    "sg:phone":"+1 404 656 9298",
    "sg:postcode":"30319",
    "sg:province":"GA",
    "sg:tags":[
        "business"
    ],
    "wof:name":"Assn For Vital Records",
    "wof:placetype":"venue"
},
  "geometry": {"coordinates":[-84.314989,33.86454],"type":"Point"}
}