{
  "type": "Feature",
  "properties": {
    "iso:country":"US",
    "sg:address":"75 Wyndham Dr NW",
    "sg:city":"Atlanta",
    "sg:classifiers":[
        {
            "category":"Real Estate",
            "subcategory":"Real Estate Agent",
            "type":"Services"
        }
    ],
    "sg:phone":"+1 404 252 0122",
    "sg:postcode":"30328",
    "sg:province":"GA",
    "wof:name":"CJP Realty Svc LLC",
    "wof:placetype":"venue"
},
  "geometry": {"coordinates":[-84.39052,33.944142],"type":"Point"}
}