{
  "type": "Feature",
  "properties": {
    "addr:full":"1990 Amber Leaf Ct Jonesboro GA 30236",
    "addr:housenumber":"1990",
    "addr:postcode":"30236",
    "addr:street":"Amber Leaf Ct",
    "iso:country":"US",
    "sg:address":"1990 Amber Leaf Ct",
    "sg:city":"Jonesboro",
    "sg:classifiers":[
        {
            "category":"Building & Trades",
            "subcategory":"Cleaning & Sanitation",
            "type":"Services"
        }
    ],
    "sg:phone":"+1 770 603 6695",
    "sg:postcode":"30236",
    "sg:province":"GA",
    "sg:tags":[
        "maintenance"
    ],
    "wof:name":"Nelsons Janitorial Service",
    "wof:placetype":"venue"
},
  "geometry": {"coordinates":[-84.326319,33.536402],"type":"Point"}
}