{
  "type": "Feature",
  "properties": {
    "addr:full":"2690 Lawrenceville Hwy Decatur GA 30033",
    "addr:housenumber":"2690",
    "addr:postcode":"30033",
    "addr:street":"Lawrenceville Hwy",
    "iso:country":"US",
    "sg:address":"2690 Lawrenceville Hwy",
    "sg:city":"Decatur",
    "sg:classifiers":[
        {
            "category":"Insurance",
            "subcategory":"Insurance Agent",
            "type":"Services"
        }
    ],
    "sg:phone":"+1 770 493 7213",
    "sg:postcode":"30033",
    "sg:province":"GA",
    "wof:name":"State Farm Insurance",
    "wof:placetype":"venue"
},
  "geometry": {"coordinates":[-84.26116500000001,33.823849],"type":"Point"}
}