{
  "type": "Feature",
  "properties": {
    "iso:country":"US",
    "sg:address":"955 Woodgate Rd",
    "sg:city":"Ringgold",
    "sg:classifiers":[
        {
            "category":"Professional",
            "subcategory":"Management & Consulting",
            "type":"Services"
        }
    ],
    "sg:phone":"+1 706 937 5755",
    "sg:postcode":"30736",
    "sg:province":"GA",
    "sg:tags":[
        "retail",
        "direct",
        "sales"
    ],
    "wof:name":"Anderson Sales Agency Inc",
    "wof:placetype":"venue"
},
  "geometry": {"coordinates":[-85.15677700000001,34.929715],"type":"Point"}
}