{
  "type": "Feature",
  "properties": {
    "iso:country":"US",
    "sg:address":"1012 Tanners Point Dr",
    "sg:city":"Lawrenceville",
    "sg:classifiers":[
        {
            "category":"Personal",
            "subcategory":"Nail Salon",
            "type":"Services"
        }
    ],
    "sg:phone":"+1 770 339 1490",
    "sg:postcode":"30044",
    "sg:province":"GA",
    "wof:name":"Nailed To The Cross",
    "wof:placetype":"venue"
},
  "geometry": {"coordinates":[-84.009995,33.91977],"type":"Point"}
}