{
  "type": "Feature",
  "properties": {
    "iso:country":"US",
    "sg:address":"6310 Lawrenceville Hwy",
    "sg:city":"Tucker",
    "sg:classifiers":[
        {
            "category":"Shopping",
            "subcategory":"Hobbies, Toys, & Games",
            "type":"Retail Goods"
        },
        {
            "category":"Food & Beverages",
            "subcategory":"Groceries & Convenience Stores",
            "type":"Retail Goods"
        }
    ],
    "sg:phone":"+1 770 939 0527",
    "sg:postcode":"30084",
    "sg:province":"GA",
    "sg:tags":[
        "ceramic",
        "gasoline",
        "supply"
    ],
    "wof:name":"Tucker Express",
    "wof:placetype":"venue"
},
  "geometry": {"coordinates":[-84.184601,33.8671],"type":"Point"}
}