{
  "type": "Feature",
  "properties": {
    "iso:country":"US",
    "sg:address":"230 Morning View Dr",
    "sg:city":"Athens",
    "sg:classifiers":[
        {
            "category":"Building & Trades",
            "subcategory":"Landscaping Services",
            "type":"Services"
        }
    ],
    "sg:phone":"+1 706 549 6896",
    "sg:postcode":"30605",
    "sg:province":"GA",
    "wof:name":"Living Lawns of Athens",
    "wof:placetype":"venue"
},
  "geometry": {"coordinates":[-83.31520500000001,33.939336],"type":"Point"}
}