{
  "type": "Feature",
  "properties": {
    "iso:country":"US",
    "sg:address":"751 Dekalb Industrial Way Bldg 4",
    "sg:city":"Decatur",
    "sg:classifiers":[
        {
            "category":"Restaurant",
            "type":"Food & Drink"
        }
    ],
    "sg:phone":"+1 404 424 9227",
    "sg:postcode":"30033",
    "sg:province":"GA",
    "sg:tags":[
        "pakistani",
        "indian"
    ],
    "sg:website":"www.tavaandgrill.com",
    "wof:name":"Tava & Grill",
    "wof:placetype":"venue"
},
  "geometry": {"coordinates":[-84.27825300000001,33.799114],"type":"Point"}
}