{
  "type": "Feature",
  "properties": {
    "iso:country":"US",
    "sg:address":"422 Laurian Way",
    "sg:city":"Kennesaw",
    "sg:classifiers":[
        {
            "category":"Professional",
            "type":"Services"
        }
    ],
    "sg:phone":"+1 770 591 5660",
    "sg:postcode":"30144",
    "sg:province":"GA",
    "sg:tags":[
        "establishment"
    ],
    "wof:name":"Canfor USA",
    "wof:placetype":"venue"
},
  "geometry": {"coordinates":[-84.561419,34.05825],"type":"Point"}
}