{
  "type": "Feature",
  "properties": {
    "addr:full":"3687 Fernbrook Dr Snellville GA 30039",
    "addr:housenumber":"3687",
    "addr:postcode":"30039",
    "addr:street":"Fernbrook Dr",
    "iso:country":"US",
    "sg:address":"3687 Fernbrook Dr",
    "sg:city":"Snellville",
    "sg:classifiers":[
        {
            "category":"Building & Trades",
            "subcategory":"Plumbing",
            "type":"Services"
        }
    ],
    "sg:phone":"+1 404 343 0047",
    "sg:postcode":"30039",
    "sg:province":"GA",
    "sg:tags":[
        "contractor"
    ],
    "wof:name":"Turner Plumbing Co",
    "wof:placetype":"venue"
},
  "geometry": {"coordinates":[-84.01052900000001,33.81706],"type":"Point"}
}