{
  "type": "Feature",
  "properties": {
    "iso:country":"US",
    "sg:address":"4255 Fairfax Dr",
    "sg:city":"Cumming",
    "sg:classifiers":[
        {
            "category":"Building & Trades",
            "subcategory":"Construction",
            "type":"Services"
        }
    ],
    "sg:phone":"+1 770 886 1591",
    "sg:postcode":"30028",
    "sg:province":"GA",
    "sg:tags":[
        "house"
    ],
    "wof:name":"Jimmys Remodeling Inc",
    "wof:placetype":"venue"
},
  "geometry": {"coordinates":[-84.119326,34.284299],"type":"Point"}
}