{
  "type": "Feature",
  "properties": {
    "iso:country":"US",
    "sg:address":"2640 Twin Lakes Way",
    "sg:city":"Marietta",
    "sg:classifiers":[
        {
            "category":"Shopping",
            "type":"Retail Goods"
        }
    ],
    "sg:phone":"+1 770 321 4561",
    "sg:postcode":"30062",
    "sg:province":"GA",
    "sg:tags":[
        "merchandise"
    ],
    "wof:name":"Pet Pantry",
    "wof:placetype":"venue"
},
  "geometry": {"coordinates":[-84.45671299999999,34.009831],"type":"Point"}
}