{
  "type": "Feature",
  "properties": {
    "addr:full":"3500 McDonough Pkwy McDonough GA 30253",
    "addr:postcode":"3500;30253",
    "addr:street":"Mcdonough Pkwy",
    "iso:country":"US",
    "sg:address":"3500 McDonough Pkwy",
    "sg:city":"McDonough",
    "sg:classifiers":[
        {
            "category":"Social Services",
            "subcategory":"Child Care",
            "type":"Services"
        }
    ],
    "sg:phone":"+1 770 288 2250",
    "sg:postcode":"30253",
    "sg:province":"GA",
    "sg:tags":[
        "day"
    ],
    "wof:name":"Bright Star At Walnut Creek",
    "wof:placetype":"venue"
},
  "geometry": {"coordinates":[-84.16954,33.449368],"type":"Point"}
}