{
  "type": "Feature",
  "properties": {
    "addr:full":"1445 E Tennessee Ave Mc Caysville GA 30555",
    "addr:housenumber":"1445",
    "addr:postcode":"30555",
    "addr:street":"E Tennessee Ave Mc Caysville",
    "iso:country":"US",
    "sg:address":"1445 E Tennessee Ave",
    "sg:city":"Mc Caysville",
    "sg:classifiers":[
        {
            "category":"Utilities",
            "subcategory":"Water",
            "type":"Services"
        }
    ],
    "sg:phone":"+1 706 492 4612",
    "sg:postcode":"30555",
    "sg:province":"GA",
    "sg:tags":[
        "company",
        "sewage"
    ],
    "wof:name":"Mc Caysville Water Works",
    "wof:placetype":"venue"
},
  "geometry": {"coordinates":[-84.364394,34.98513],"type":"Point"}
}