{
  "type": "Feature",
  "properties": {
    "addr:full":"2212 Watson Blvd Warner Robins GA 31093",
    "addr:housenumber":"2212",
    "addr:postcode":"31093",
    "addr:street":"Watson Blvd",
    "iso:country":"US",
    "sg:address":"2212 Watson Blvd",
    "sg:city":"Warner Robins",
    "sg:classifiers":[
        {
            "category":"Restaurant",
            "type":"Food & Drink"
        }
    ],
    "sg:phone":"+1 478 929 9849",
    "sg:postcode":"31093",
    "sg:province":"GA",
    "sg:tags":[
        "eating"
    ],
    "wof:name":"Captain Jacks Crab Shack",
    "wof:placetype":"venue"
},
  "geometry": {"coordinates":[-83.65843099999999,32.618288],"type":"Point"}
}