{
  "type": "Feature",
  "properties": {
    "addr:full":"3985 Berkeley View Dr Duluth GA 30096",
    "addr:housenumber":"3985",
    "addr:postcode":"30096",
    "addr:street":"Berkeley View Dr",
    "iso:country":"US",
    "sg:address":"3985 Berkeley View Dr",
    "sg:city":"Duluth",
    "sg:classifiers":[
        {
            "category":"Professional",
            "subcategory":"Computer Services",
            "type":"Services"
        }
    ],
    "sg:phone":"+1 678 584 5460",
    "sg:postcode":"30096",
    "sg:province":"GA",
    "sg:tags":[
        "prepackaged",
        "software"
    ],
    "wof:name":"Parametric Technology Corp",
    "wof:placetype":"venue"
},
  "geometry": {"coordinates":[-84.177925,33.987045],"type":"Point"}
}