{
  "type": "Feature",
  "properties": {
    "iso:country":"US",
    "sg:address":"80 Bradley Ct",
    "sg:city":"Newnan",
    "sg:classifiers":[
        {
            "category":"Professional",
            "type":"Services"
        }
    ],
    "sg:phone":"+1 770 253 4452",
    "sg:postcode":"30263",
    "sg:province":"GA",
    "wof:name":"Allan Zeiler Company",
    "wof:placetype":"venue"
},
  "geometry": {"coordinates":[-84.767715,33.444459],"type":"Point"}
}