{
  "type": "Feature",
  "properties": {
    "iso:country":"US",
    "sg:address":"79 E Jefferson St",
    "sg:city":"Hazlehurst",
    "sg:classifiers":[
        {
            "category":"Restaurant",
            "type":"Food & Drink"
        }
    ],
    "sg:phone":"+1 912 375 2517",
    "sg:postcode":"31539",
    "sg:province":"GA",
    "wof:name":"Rebel",
    "wof:placetype":"venue"
},
  "geometry": {"coordinates":[-82.598551,31.857554],"type":"Point"}
}