{
  "type": "Feature",
  "properties": {
    "addr:full":"2896 Caldwell Road NE Atlanta GA 30319",
    "addr:housenumber":"2896",
    "addr:postcode":"30319",
    "addr:street":"Caldwell Road Ne",
    "iso:country":"US",
    "sg:address":"2896 Caldwell Road NE",
    "sg:city":"Atlanta",
    "sg:classifiers":[
        {
            "category":"Real Estate",
            "subcategory":"Real Estate Operator",
            "type":"Services"
        }
    ],
    "sg:phone":"+1 404 264 9882",
    "sg:postcode":"30319",
    "sg:province":"GA",
    "sg:tags":[
        "apartment"
    ],
    "wof:name":"Post Apartments",
    "wof:placetype":"venue"
},
  "geometry": {"coordinates":[-84.33025600000001,33.870829],"type":"Point"}
}