{
  "type": "Feature",
  "properties": {
    "addr:full":"4801 Memorial Dr Decatur GA 30032",
    "addr:housenumber":"4801",
    "addr:postcode":"30032",
    "addr:street":"Memorial Dr",
    "iso:country":"US",
    "sg:address":"4801 Memorial Dr",
    "sg:city":"Decatur",
    "sg:classifiers":[
        {
            "category":"Professional",
            "subcategory":"Accounting & Tax Preparation",
            "type":"Services"
        }
    ],
    "sg:phone":"+1 404 296 7575",
    "sg:postcode":"30032",
    "sg:province":"GA",
    "sg:tags":[
        "return",
        "filing"
    ],
    "wof:name":"Instant Tax Svc",
    "wof:placetype":"venue"
},
  "geometry": {"coordinates":[-84.233588,33.786691],"type":"Point"}
}