{
  "type": "Feature",
  "properties": {
    "addr:full":"6483 Sage St Atlanta GA 30340",
    "addr:housenumber":"6483",
    "addr:postcode":"30340",
    "addr:street":"Sage St",
    "iso:country":"US",
    "sg:address":"6483 Sage St",
    "sg:city":"Atlanta",
    "sg:classifiers":[
        {
            "category":"Building & Trades",
            "subcategory":"Cleaning & Sanitation",
            "type":"Services"
        }
    ],
    "sg:phone":"+1 770 309 6291",
    "sg:postcode":"30340",
    "sg:province":"GA",
    "sg:tags":[
        "maintenance"
    ],
    "wof:name":"Hendrix Odd Jobs",
    "wof:placetype":"venue"
},
  "geometry": {"coordinates":[-84.23032600000001,33.923813],"type":"Point"}
}