{
  "type": "Feature",
  "properties": {
    "addr:full":"2 Ruby St Gainesville GA 30501",
    "addr:housenumber":"2",
    "addr:postcode":"30501",
    "addr:street":"Ruby St",
    "iso:country":"US",
    "sg:address":"2 Ruby St",
    "sg:city":"Gainesville",
    "sg:classifiers":[
        {
            "category":"Utilities",
            "subcategory":"Refuse",
            "type":"Services"
        }
    ],
    "sg:phone":"+1 770 343 9985",
    "sg:postcode":"30501",
    "sg:province":"GA",
    "sg:tags":[
        "system"
    ],
    "wof:name":"ACS",
    "wof:placetype":"venue"
},
  "geometry": {"coordinates":[-83.838804,34.269282],"type":"Point"}
}