{
  "type": "Feature",
  "properties": {
    "iso:country":"US",
    "sg:address":"6707 Maddox Rd",
    "sg:city":"Morrow",
    "sg:classifiers":[
        {
            "category":"Restaurant",
            "type":"Food & Drink"
        }
    ],
    "sg:phone":"+1 770 968 7955",
    "sg:postcode":"30260",
    "sg:province":"GA",
    "sg:tags":[
        "eating"
    ],
    "wof:name":"Sports Emporium Cafe",
    "wof:placetype":"venue"
},
  "geometry": {"coordinates":[-84.30819099999999,33.568362],"type":"Point"}
}