{
  "type": "Feature",
  "properties": {
    "addr:full":"1672 Bartley Rd Lagrange GA 30240",
    "addr:housenumber":"1672",
    "addr:postcode":"30240",
    "addr:street":"Bartley Rd",
    "iso:country":"US",
    "sg:address":"1672 Bartley Rd",
    "sg:city":"Lagrange",
    "sg:classifiers":[
        {
            "category":"Autos & Motor Vehicles",
            "subcategory":"Boat Sales",
            "type":"Retail Goods"
        }
    ],
    "sg:phone":"+1 706 882 7938",
    "sg:postcode":"30240",
    "sg:province":"GA",
    "sg:tags":[
        "top",
        "upholstery",
        "cover"
    ],
    "wof:name":"Buddy Mc Rae Upholstery",
    "wof:placetype":"venue"
},
  "geometry": {"coordinates":[-85.033174,32.949276],"type":"Point"}
}