{
  "type": "Feature",
  "properties": {
    "iso:country":"US",
    "sg:address":"400 Brookstone Centre Pkwy - Ste 100",
    "sg:city":"Columbus",
    "sg:classifiers":[
        {
            "category":"Insurance",
            "subcategory":"Insurance Agent",
            "type":"Services"
        },
        {
            "category":"Insurance",
            "subcategory":"Hazard Insurance",
            "type":"Services"
        },
        {
            "category":"Insurance",
            "subcategory":"Title Insurance",
            "type":"Services"
        },
        {
            "category":"Insurance",
            "subcategory":"Life Insurance",
            "type":"Services"
        }
    ],
    "sg:phone":"+1 706 256 8974",
    "sg:postcode":"31904",
    "sg:province":"GA",
    "sg:tags":[
        "auto",
        "renter",
        "homeowner"
    ],
    "sg:website":"http://www.libertymutual.com/local-office?officenumber=0506&src=YP_Local_0506",
    "wof:name":"Liberty Mutual Insurance Company",
    "wof:placetype":"venue"
},
  "geometry": {"coordinates":[-84.97942999999999,32.533291],"type":"Point"}
}