{
  "type": "Feature",
  "properties": {
    "addr:full":"3580 Macon Rd Columbus GA 31907",
    "addr:housenumber":"3580",
    "addr:postcode":"31907",
    "addr:street":"Macon Rd",
    "iso:country":"US",
    "sg:address":"3580 Macon Rd",
    "sg:city":"Columbus",
    "sg:classifiers":[
        {
            "category":"Restaurant",
            "type":"Food & Drink"
        },
        {
            "category":"Ice Cream",
            "type":"Food & Drink"
        }
    ],
    "sg:menulink":"http://www.allmenus.com/ga/columbus/172643-dairy-queen/menu/",
    "sg:phone":"+1 706 562 9156",
    "sg:postcode":"31907",
    "sg:province":"GA",
    "sg:tags":[
        "burger",
        "american",
        "ice",
        "cream"
    ],
    "wof:name":"Dairy Queen",
    "wof:placetype":"venue"
},
  "geometry": {"coordinates":[-84.934348,32.486405],"type":"Point"}
}