{
  "type": "Feature",
  "properties": {
    "addr:full":"84 E Broad St Camilla GA 31730",
    "addr:housenumber":"84",
    "addr:postcode":"31730",
    "addr:street":"E Broad St",
    "iso:country":"US",
    "sg:address":"84 E Broad St",
    "sg:city":"Camilla",
    "sg:classifiers":[
        {
            "category":"Government",
            "subcategory":"Office",
            "type":"Public Place"
        }
    ],
    "sg:phone":"+1 229 522 3625",
    "sg:postcode":"31730",
    "sg:province":"GA",
    "sg:tags":[
        "state",
        "resource"
    ],
    "wof:name":"Human Resources Dept",
    "wof:placetype":"venue"
},
  "geometry": {"coordinates":[-84.20572900000001,31.23122],"type":"Point"}
}