{
  "type": "Feature",
  "properties": {
    "iso:country":"US",
    "sg:address":"7267 Tara Blvd",
    "sg:city":"Jonesboro",
    "sg:classifiers":[
        {
            "category":"Shopping",
            "subcategory":"Pharmacy",
            "type":"Retail Goods"
        }
    ],
    "sg:phone":"+1 770 471 3180",
    "sg:postcode":"30236",
    "sg:province":"GA",
    "sg:website":"www.cvs.com",
    "wof:name":"CVS Pharmacy",
    "wof:placetype":"venue"
},
  "geometry": {"coordinates":[-84.37018500000001,33.550737],"type":"Point"}
}