{
  "type": "Feature",
  "properties": {
    "iso:country":"US",
    "sg:address":"3480 Greenbriar Pkwy SW",
    "sg:city":"Atlanta",
    "sg:classifiers":[
        {
            "category":"Health Services",
            "subcategory":"Clinic",
            "type":"Services"
        }
    ],
    "sg:phone":"+1 404 941 7901",
    "sg:postcode":"30331",
    "sg:province":"GA",
    "sg:tags":[
        "information",
        "mental"
    ],
    "wof:name":"Extented Families Counsel",
    "wof:placetype":"venue"
},
  "geometry": {"coordinates":[-84.502571,33.683781],"type":"Point"}
}