{
  "type": "Feature",
  "properties": {
    "iso:country":"US",
    "sg:address":"2113 Red Banks Dr",
    "sg:city":"Hiawassee",
    "sg:classifiers":[
        {
            "category":"Building & Trades",
            "subcategory":"Landscaping Services",
            "type":"Services"
        }
    ],
    "sg:phone":"+1 706 896 8004",
    "sg:postcode":"30546",
    "sg:province":"GA",
    "sg:tags":[
        "designer",
        "landscape"
    ],
    "wof:name":"WNC Landscaping & Design",
    "wof:placetype":"venue"
},
  "geometry": {"coordinates":[-83.816315,34.976836],"type":"Point"}
}