{
  "type": "Feature",
  "properties": {
    "addr:full":"1833 Rock Chapel Rd Lithonia GA 30058",
    "addr:housenumber":"1833",
    "addr:postcode":"30058",
    "addr:street":"Rock Chapel Rd",
    "iso:country":"US",
    "sg:address":"1833 Rock Chapel Rd",
    "sg:city":"Lithonia",
    "sg:classifiers":[
        {
            "category":"Wholesale",
            "subcategory":"Machinery & Supplies",
            "type":"Manufacturing & Wholesale Goods"
        }
    ],
    "sg:phone":"+1 770 482 7002",
    "sg:postcode":"30058",
    "sg:province":"GA",
    "sg:tags":[
        "packaging"
    ],
    "wof:name":"Rydell Co",
    "wof:placetype":"venue"
},
  "geometry": {"coordinates":[-84.087424,33.736289],"type":"Point"}
}