{
  "type": "Feature",
  "properties": {
    "addr:full":"1018 Drewery Ave Griffin GA 30223",
    "addr:housenumber":"1018",
    "addr:postcode":"30223",
    "addr:street":"Drewery Ave",
    "iso:country":"US",
    "sg:address":"1018 Drewery Ave",
    "sg:city":"Griffin",
    "sg:classifiers":[
        {
            "category":"Retail",
            "subcategory":"Auto Repair",
            "type":"Services"
        }
    ],
    "sg:phone":"+1 770 227 2506",
    "sg:postcode":"30223",
    "sg:province":"GA",
    "sg:tags":[
        "wrecker"
    ],
    "wof:name":"Brooks Wrecker Svc",
    "wof:placetype":"venue"
},
  "geometry": {"coordinates":[-84.280894,33.258421],"type":"Point"}
}