{
  "type": "Feature",
  "properties": {
    "addr:full":"5511 Williams Rd Norcross GA 30093",
    "addr:housenumber":"5511",
    "addr:postcode":"30093",
    "addr:street":"Williams Rd",
    "iso:country":"US",
    "sg:address":"5511 Williams Rd",
    "sg:city":"Norcross",
    "sg:classifiers":[
        {
            "category":"Place Of Worship",
            "subcategory":"Church",
            "type":"Public Place"
        },
        {
            "category":"Place Of Worship",
            "type":"Public Place"
        }
    ],
    "sg:phone":"+1 770 446 7585",
    "sg:postcode":"30093",
    "sg:province":"GA",
    "sg:tags":[
        "churches-charismatic"
    ],
    "wof:name":"All Nations Church",
    "wof:placetype":"venue"
},
  "geometry": {"coordinates":[-84.17323399999999,33.899212],"type":"Point"}
}