{
  "type": "Feature",
  "properties": {
    "addr:full":"504 Old Double Churches Rd Columbus GA 31904",
    "addr:housenumber":"504",
    "addr:postcode":"31904",
    "addr:street":"Old Double Churches Rd",
    "iso:country":"US",
    "sg:address":"504 Old Double Churches Rd",
    "sg:city":"Columbus",
    "sg:classifiers":[
        {
            "category":"Building & Trades",
            "subcategory":"Landscaping Services",
            "type":"Services"
        }
    ],
    "sg:phone":"+1 706 392 4988",
    "sg:postcode":"31904",
    "sg:province":"GA",
    "sg:tags":[
        "lawn",
        "maintenance",
        "grounds"
    ],
    "wof:name":"Curbworks Landscape",
    "wof:placetype":"venue"
},
  "geometry": {"coordinates":[-84.98672999999999,32.555152],"type":"Point"}
}