{
  "type": "Feature",
  "properties": {
    "addr:full":"2260 Pope Rd Douglasville GA 30135",
    "addr:housenumber":"2260",
    "addr:postcode":"30135",
    "addr:street":"Pope Rd",
    "iso:country":"US",
    "sg:address":"2260 Pope Rd",
    "sg:city":"Douglasville",
    "sg:classifiers":[
        {
            "category":"Shopping",
            "subcategory":"Used Merchandise",
            "type":"Retail Goods"
        }
    ],
    "sg:phone":"+1 770 949 2080",
    "sg:postcode":"30135",
    "sg:province":"GA",
    "sg:tags":[
        "antique"
    ],
    "wof:name":"A Quaint Little Shoppe",
    "wof:placetype":"venue"
},
  "geometry": {"coordinates":[-84.694845,33.746005],"type":"Point"}
}