{
  "type": "Feature",
  "properties": {
    "iso:country":"US",
    "sg:address":"312 Crosstown Rd",
    "sg:city":"Peachtree City",
    "sg:classifiers":[
        {
            "category":"Professional",
            "subcategory":"Accounting & Tax Preparation",
            "type":"Services"
        }
    ],
    "sg:phone":"+1 770 631 3911",
    "sg:postcode":"30269",
    "sg:province":"GA",
    "sg:tags":[
        "bookkeeping"
    ],
    "wof:name":"Mendola & Associates LLC",
    "wof:placetype":"venue"
},
  "geometry": {"coordinates":[-84.545536,33.380848],"type":"Point"}
}