{
  "type": "Feature",
  "properties": {
    "iso:country":"US",
    "sg:address":"10214 Hickory Flat Hwy",
    "sg:city":"Woodstock",
    "sg:classifiers":[
        {
            "category":"Restaurant",
            "type":"Food & Drink"
        }
    ],
    "sg:menulink":"http://www.allmenus.com/ga/holly-springs/221190-san-vitos/menu/",
    "sg:phone":"+1 770 777 7999",
    "sg:postcode":"30188",
    "sg:province":"GA",
    "sg:tags":[
        "italian"
    ],
    "wof:name":"San Vitos",
    "wof:placetype":"venue"
},
  "geometry": {"coordinates":[-84.39336400000001,34.12823],"type":"Point"}
}