{
  "type": "Feature",
  "properties": {
    "addr:full":"2350 Cheshire Bridge Rd Atlanta GA 30324",
    "addr:housenumber":"2350",
    "addr:postcode":"30324",
    "addr:street":"Cheshire Bridge Rd",
    "iso:country":"US",
    "sg:address":"2350 Cheshire Bridge Rd",
    "sg:city":"Atlanta",
    "sg:classifiers":[
        {
            "category":"Professional",
            "subcategory":"Employment Agencies",
            "type":"Services"
        }
    ],
    "sg:phone":"+1 404 329 5080",
    "sg:postcode":"30324",
    "sg:province":"GA",
    "sg:tags":[
        "opportunity"
    ],
    "wof:name":"Resource Employment Solutions",
    "wof:placetype":"venue"
},
  "geometry": {"coordinates":[-84.35138000000001,33.819694],"type":"Point"}
}