{
  "type": "Feature",
  "properties": {
    "iso:country":"US",
    "sg:address":"2175 Barrett Dr",
    "sg:city":"Cumming",
    "sg:classifiers":[
        {
            "category":"Professional",
            "subcategory":"Business Services",
            "type":"Services"
        }
    ],
    "sg:phone":"+1 770 886 3267",
    "sg:postcode":"30040",
    "sg:province":"GA",
    "sg:tags":[
        "interior",
        "consultant",
        "design",
        "decorator"
    ],
    "wof:name":"M C Designs",
    "wof:placetype":"venue"
},
  "geometry": {"coordinates":[-84.178096,34.20322],"type":"Point"}
}