{
  "type": "Feature",
  "properties": {
    "addr:full":"3540 Honeycomb Dr SE Conyers GA 30094",
    "addr:postcode":"3540;30094",
    "addr:street":"Honeycomb Dr Se",
    "iso:country":"US",
    "sg:address":"3540 Honeycomb Dr SE",
    "sg:city":"Conyers",
    "sg:classifiers":[
        {
            "category":"Health Services",
            "subcategory":"Health Practitioner",
            "type":"Services"
        }
    ],
    "sg:phone":"+1 770 860 0111",
    "sg:postcode":"30094",
    "sg:province":"GA",
    "sg:tags":[
        "psychologist"
    ],
    "wof:name":"Henry Allem PHD",
    "wof:placetype":"venue"
},
  "geometry": {"coordinates":[-84.02986300000001,33.5907],"type":"Point"}
}