{
  "type": "Feature",
  "properties": {
    "addr:full":"201 N Jefferson St Dublin GA 31021",
    "addr:housenumber":"201",
    "addr:postcode":"31021",
    "addr:street":"N Jefferson St",
    "iso:country":"US",
    "sg:address":"201 N Jefferson St",
    "sg:city":"Dublin",
    "sg:classifiers":[
        {
            "category":"Banks & Credit Unions",
            "subcategory":"Bank",
            "type":"Services"
        }
    ],
    "sg:phone":"+1 478 272 8874",
    "sg:postcode":"31021",
    "sg:province":"GA",
    "sg:tags":[
        "state",
        "commercial"
    ],
    "wof:name":"Knight State Bank",
    "wof:placetype":"venue"
},
  "geometry": {"coordinates":[-82.90486300000001,32.540701],"type":"Point"}
}