{
  "type": "Feature",
  "properties": {
    "addr:full":"4231 Macon Rd Columbus GA 31907",
    "addr:housenumber":"4231",
    "addr:postcode":"31907",
    "addr:street":"Macon Rd",
    "iso:country":"US",
    "sg:address":"4231 Macon Rd",
    "sg:city":"Columbus",
    "sg:classifiers":[
        {
            "category":"Food & Beverages",
            "subcategory":"Groceries & Convenience Stores",
            "type":"Retail Goods"
        }
    ],
    "sg:phone":"+1 706 561 9093",
    "sg:postcode":"31907",
    "sg:province":"GA",
    "sg:tags":[
        "photofinishing",
        "laboratory"
    ],
    "wof:name":"Winn-Dixie",
    "wof:placetype":"venue"
},
  "geometry": {"coordinates":[-84.91690699999999,32.490816],"type":"Point"}
}