{
  "type": "Feature",
  "properties": {
    "iso:country":"US",
    "sg:address":"690 Howard Roberts Rd",
    "sg:city":"Gray",
    "sg:classifiers":[
        {
            "category":"Personal",
            "subcategory":"Beauty Salon",
            "type":"Services"
        }
    ],
    "sg:phone":"+1 478 986 6465",
    "sg:postcode":"31032",
    "sg:province":"GA",
    "sg:tags":[
        "shop"
    ],
    "wof:name":"Ritas Beauty Shop",
    "wof:placetype":"venue"
},
  "geometry": {"coordinates":[-83.632756,33.001075],"type":"Point"}
}