{
  "type": "Feature",
  "properties": {
    "addr:full":"115 Townsend Dr Hoschton GA 30534",
    "addr:housenumber":"115",
    "addr:postcode":"30534",
    "addr:street":"Townsend Dr Hoschton",
    "iso:country":"US",
    "sg:address":"115 Townsend Dr",
    "sg:city":"Hoschton",
    "sg:classifiers":[
        {
            "category":"Real Estate",
            "subcategory":"Real Estate Agent",
            "type":"Services"
        }
    ],
    "sg:phone":"+1 706 658 2749",
    "sg:postcode":"30534",
    "sg:province":"GA",
    "wof:name":"MDM Real Estate Group LLC",
    "wof:placetype":"venue"
},
  "geometry": {"coordinates":[-83.997225,34.345111],"type":"Point"}
}