{
  "type": "Feature",
  "properties": {
    "addr:full":"164 Oostanaula Bend Rd SW Calhoun GA 30701",
    "addr:housenumber":"164",
    "addr:postcode":"30701",
    "addr:street":"Oostanaula Bend Rd Sw",
    "iso:country":"US",
    "sg:address":"164 Oostanaula Bend Rd SW",
    "sg:city":"Calhoun",
    "sg:classifiers":[
        {
            "category":"Real Estate",
            "subcategory":"Real Estate Operator",
            "type":"Services"
        }
    ],
    "sg:phone":"+1 678 986 5134",
    "sg:postcode":"30701",
    "sg:province":"GA",
    "sg:tags":[
        "building",
        "parks"
    ],
    "wof:name":"Georgia Steel Builders Inc",
    "wof:placetype":"venue"
},
  "geometry": {"coordinates":[-85.015636,34.489673],"type":"Point"}
}