{
  "type": "Feature",
  "properties": {
    "iso:country":"US",
    "sg:address":"2709 Gillionville Rd",
    "sg:city":"Albany",
    "sg:classifiers":[
        {
            "category":"Insurance",
            "subcategory":"Hazard Insurance",
            "type":"Services"
        },
        {
            "category":"Insurance",
            "subcategory":"Insurance Agent",
            "type":"Services"
        },
        {
            "category":"Insurance",
            "subcategory":"Life Insurance",
            "type":"Services"
        },
        {
            "category":"Insurance",
            "subcategory":"Health Insurance",
            "type":"Services"
        }
    ],
    "sg:phone":"+1 229 432 7203",
    "sg:postcode":"31721",
    "sg:province":"GA",
    "sg:tags":[
        "auto",
        "property",
        "casualty"
    ],
    "wof:name":"Taylor Insurance Agency",
    "wof:placetype":"venue"
},
  "geometry": {"coordinates":[-84.220961,31.585719],"type":"Point"}
}