{
  "type": "Feature",
  "properties": {
    "addr:full":"984 Main St Stone Mountain GA 30083",
    "addr:housenumber":"984",
    "addr:postcode":"30083",
    "addr:street":"Main St",
    "iso:country":"US",
    "sg:address":"984 Main St",
    "sg:city":"Stone Mountain",
    "sg:classifiers":[
        {
            "category":"Wholesale",
            "subcategory":"Electrical",
            "type":"Manufacturing & Wholesale Goods"
        }
    ],
    "sg:phone":"+1 770 879 6700",
    "sg:postcode":"30083",
    "sg:province":"GA",
    "sg:tags":[
        "electronic"
    ],
    "wof:name":"Replugged Inc",
    "wof:placetype":"venue"
},
  "geometry": {"coordinates":[-84.170868,33.809058],"type":"Point"}
}