{
  "type": "Feature",
  "properties": {
    "iso:country":"US",
    "sg:address":"4849 Paulsen St",
    "sg:city":"Savannah",
    "sg:classifiers":[
        {
            "category":"Real Estate",
            "subcategory":"Real Estate Agent",
            "type":"Services"
        }
    ],
    "sg:phone":"+1 912 353 7575",
    "sg:postcode":"31405",
    "sg:province":"GA",
    "wof:name":"E Simmons & Co",
    "wof:placetype":"venue"
},
  "geometry": {"coordinates":[-81.095822,32.031062],"type":"Point"}
}