{
  "type": "Feature",
  "properties": {
    "addr:full":"765 Oak Grove Rd Dahlonega GA 30533",
    "addr:housenumber":"765",
    "addr:postcode":"30533",
    "addr:street":"Oak Grove Rd",
    "iso:country":"US",
    "sg:address":"765 Oak Grove Rd",
    "sg:city":"Dahlonega",
    "sg:phone":"+1 706 864 2737",
    "sg:postcode":"30533",
    "sg:province":"GA",
    "sg:tags":[
        "gas",
        "product",
        "petroleum"
    ],
    "wof:name":"Georgia North Propane Inc",
    "wof:placetype":"venue"
},
  "geometry": {"coordinates":[-84.010159,34.545074],"type":"Point"}
}