{
  "type": "Feature",
  "properties": {
    "iso:country":"US",
    "sg:address":"2719 Buford Hwy",
    "sg:city":"Atlanta",
    "sg:classifiers":[
        {
            "category":"Professional",
            "subcategory":"Lawyer & Legal Services",
            "type":"Services"
        }
    ],
    "sg:phone":"+1 404 321 1700",
    "sg:postcode":"30324",
    "sg:province":"GA",
    "wof:name":"Ayres Tamara McDowell",
    "wof:placetype":"venue"
},
  "geometry": {"coordinates":[-84.34272900000001,33.831314],"type":"Point"}
}