{
  "type": "Feature",
  "properties": {
    "addr:full":"2968 N Decatur Rd Ste E Decatur GA 30033",
    "addr:housenumber":"2968",
    "addr:postcode":"30033",
    "addr:street":"N Decatur Rd Ste E",
    "iso:country":"US",
    "sg:address":"2968 N Decatur Rd Ste E",
    "sg:city":"Decatur",
    "sg:classifiers":[
        {
            "category":"Retail",
            "subcategory":"Auto Repair",
            "type":"Services"
        }
    ],
    "sg:phone":"+1 404 299 7810",
    "sg:postcode":"30033",
    "sg:province":"GA",
    "sg:website":"www.aamco.com",
    "wof:name":"Aamco Transmissions",
    "wof:placetype":"venue"
},
  "geometry": {"coordinates":[-84.271202,33.793701],"type":"Point"}
}