{
  "type": "Feature",
  "properties": {
    "addr:full":"111 Sunset Blvd Jesup GA 31545",
    "addr:housenumber":"111",
    "addr:postcode":"31545",
    "addr:street":"Sunset Blvd",
    "iso:country":"US",
    "sg:address":"111 Sunset Blvd",
    "sg:city":"Jesup",
    "sg:classifiers":[
        {
            "category":"Restaurant",
            "type":"Food & Drink"
        }
    ],
    "sg:menulink":"http://www.allmenus.com/ga/jesup/156432-krystal-burgers/menu/",
    "sg:phone":"+1 912 530 7422",
    "sg:postcode":"31545",
    "sg:province":"GA",
    "sg:tags":[
        "burger",
        "chicken",
        "american"
    ],
    "wof:name":"Krystal Burgers",
    "wof:placetype":"venue"
},
  "geometry": {"coordinates":[-81.901256,31.625482],"type":"Point"}
}