{
  "type": "Feature",
  "properties": {
    "iso:country":"US",
    "sg:address":"2359 Windy Hill Rd SE Ste 100",
    "sg:city":"Marietta",
    "sg:classifiers":[
        {
            "category":"Restaurant",
            "type":"Food & Drink"
        }
    ],
    "sg:phone":"+1 770 953 6382",
    "sg:postcode":"30067",
    "sg:province":"GA",
    "wof:name":"Taco Mac",
    "wof:placetype":"venue"
},
  "geometry": {"coordinates":[-84.485703,33.9035],"type":"Point"}
}