{
  "type": "Feature",
  "properties": {
    "iso:country":"US",
    "sg:address":"27 Golf Crest Dr",
    "sg:city":"Acworth",
    "sg:classifiers":[
        {
            "category":"Personal",
            "subcategory":"Tanning Parlor",
            "type":"Services"
        }
    ],
    "sg:phone":"+1 770 974 8004",
    "sg:postcode":"30101",
    "sg:province":"GA",
    "wof:name":"Brazilian Beach Tanning Studio",
    "wof:placetype":"venue"
},
  "geometry": {"coordinates":[-84.76070900000001,34.051177],"type":"Point"}
}