{
  "type": "Feature",
  "properties": {
    "iso:country":"US",
    "sg:address":"1006 Pine St",
    "sg:city":"Darien",
    "sg:classifiers":[
        {
            "category":"Retail",
            "subcategory":"Repair Shop",
            "type":"Services"
        }
    ],
    "sg:phone":"+1 912 437 4543",
    "sg:postcode":"31305",
    "sg:province":"GA",
    "sg:tags":[
        "appliance"
    ],
    "wof:name":"Pete's Appliance Repair",
    "wof:placetype":"venue"
},
  "geometry": {"coordinates":[-81.422462,31.373039],"type":"Point"}
}