{
  "type": "Feature",
  "properties": {
    "addr:full":"245 Peachtree Center Ave NE Atlanta GA 30303",
    "addr:housenumber":"245",
    "addr:postcode":"30303",
    "addr:street":"Peachtree Center Ave Ne",
    "iso:country":"US",
    "sg:address":"245 Peachtree Center Ave NE",
    "sg:city":"Atlanta",
    "sg:classifiers":[
        {
            "category":"Banks & Credit Unions",
            "subcategory":"Bank",
            "type":"Services"
        }
    ],
    "sg:phone":"+1 404 220 3919",
    "sg:postcode":"30303",
    "sg:province":"GA",
    "sg:tags":[
        "loan",
        "real estate"
    ],
    "wof:name":"GMAC Mortgage",
    "wof:placetype":"venue"
},
  "geometry": {"coordinates":[-84.385942,33.762159],"type":"Point"}
}