{
  "type": "Feature",
  "properties": {
    "addr:full":"3705 Washington Rd Augusta GA 30907",
    "addr:housenumber":"3705",
    "addr:postcode":"30907",
    "addr:street":"Washington Rd",
    "iso:country":"US",
    "sg:address":"3705 Washington Rd",
    "sg:city":"Augusta",
    "sg:classifiers":[
        {
            "category":"Personal",
            "subcategory":"Barber",
            "type":"Services"
        }
    ],
    "sg:phone":"+1 706 868 8788",
    "sg:postcode":"30907",
    "sg:province":"GA",
    "sg:tags":[
        "shop"
    ],
    "wof:name":"Silver Clipper Inc",
    "wof:placetype":"venue"
},
  "geometry": {"coordinates":[-82.07844900000001,33.515867],"type":"Point"}
}