{
  "type": "Feature",
  "properties": {
    "addr:full":"548 Crosstown Rd Peachtree City GA 30269",
    "addr:housenumber":"548",
    "addr:postcode":"30269",
    "addr:street":"Crosstown Rd",
    "iso:country":"US",
    "sg:address":"548 Crosstown Rd",
    "sg:city":"Peachtree City",
    "sg:classifiers":[
        {
            "category":"Food & Beverages",
            "subcategory":"Specialty",
            "type":"Retail Goods"
        }
    ],
    "sg:phone":"+1 770 487 1113",
    "sg:postcode":"30269",
    "sg:province":"GA",
    "wof:name":"GNC",
    "wof:placetype":"venue"
},
  "geometry": {"coordinates":[-84.55702599999999,33.377338],"type":"Point"}
}