{
  "type": "Feature",
  "properties": {
    "iso:country":"US",
    "sg:address":"73 Helen Camp Rd",
    "sg:city":"Sharpsburg",
    "sg:classifiers":[
        {
            "category":"Farming",
            "subcategory":"Livestock Farm",
            "type":"Manufacturing & Wholesale Goods"
        }
    ],
    "sg:phone":"+1 770 599 6750",
    "sg:postcode":"30277",
    "sg:province":"GA",
    "sg:tags":[
        "animal",
        "general"
    ],
    "wof:name":"Craig Smith",
    "wof:placetype":"venue"
},
  "geometry": {"coordinates":[-84.664911,33.358851],"type":"Point"}
}