{
  "type": "Feature",
  "properties": {
    "addr:full":"604 Holcomb Bridge Rd Roswell GA 30076",
    "addr:housenumber":"604",
    "addr:postcode":"30076",
    "addr:street":"Holcomb Bridge Rd",
    "iso:country":"US",
    "sg:address":"604 Holcomb Bridge Rd",
    "sg:city":"Roswell",
    "sg:classifiers":[
        {
            "category":"Restaurant",
            "type":"Food & Drink"
        }
    ],
    "sg:menulink":"http://www.allmenus.com/ga/roswell-alpharetta/179941-chick-fil-a/menu/",
    "sg:phone":"+1 770 641 8436",
    "sg:postcode":"30076",
    "sg:province":"GA",
    "sg:tags":[
        "wrap",
        "soup",
        "american",
        "sandwich",
        "salad"
    ],
    "wof:name":"Chick-fil-A",
    "wof:placetype":"venue"
},
  "geometry": {"coordinates":[-84.34278,34.03701],"type":"Point"}
}