{
  "type": "Feature",
  "properties": {
    "addr:full":"1565 N Decatur Rd Atlanta GA 30307",
    "addr:housenumber":"1565",
    "addr:postcode":"30307",
    "addr:street":"N Decatur Rd",
    "iso:country":"US",
    "sg:address":"1565 N Decatur Rd",
    "sg:city":"Atlanta",
    "sg:classifiers":[
        {
            "category":"Restaurant",
            "type":"Food & Drink"
        }
    ],
    "sg:phone":"+1 404 373 2118",
    "sg:postcode":"30307",
    "sg:province":"GA",
    "wof:name":"Cedar Tree The",
    "wof:placetype":"venue"
},
  "geometry": {"coordinates":[-84.32617500000001,33.788041],"type":"Point"}
}