{
  "type": "Feature",
  "properties": {
    "addr:full":"4855 Maysville Rd Commerce GA 30529",
    "addr:housenumber":"4855",
    "addr:postcode":"30529",
    "addr:street":"Maysville Rd",
    "iso:country":"US",
    "sg:address":"4855 Maysville Rd",
    "sg:city":"Commerce",
    "sg:classifiers":[
        {
            "category":"Autos & Motor Vehicles",
            "subcategory":"Fuel & Gas Station",
            "type":"Retail Goods"
        }
    ],
    "sg:phone":"+1 706 335 4030",
    "sg:postcode":"30529",
    "sg:province":"GA",
    "sg:tags":[
        "station",
        "gasoline"
    ],
    "wof:name":"Mapco Express Inc",
    "wof:placetype":"venue"
},
  "geometry": {"coordinates":[-83.49788700000001,34.226654],"type":"Point"}
}