{
  "type": "Feature",
  "properties": {
    "iso:country":"US",
    "sg:address":"640 S Rountree St",
    "sg:city":"Metter",
    "sg:classifiers":[
        {
            "category":"Retail",
            "subcategory":"Repair Shop",
            "type":"Services"
        },
        {
            "category":"Building & Trades",
            "subcategory":"Plumbing",
            "type":"Services"
        }
    ],
    "sg:phone":"+1 912 685 4171",
    "sg:postcode":"30439",
    "sg:province":"GA",
    "sg:tags":[
        "plumbing",
        "contractor"
    ],
    "wof:name":"Steve's Plumbing & Repairs",
    "wof:placetype":"venue"
},
  "geometry": {"coordinates":[-82.062635,32.386425],"type":"Point"}
}