{
  "type": "Feature",
  "properties": {
    "iso:country":"US",
    "sg:address":"504 Carver Rd",
    "sg:city":"Griffin",
    "sg:classifiers":[
        {
            "category":"Wholesale",
            "subcategory":"Furniture",
            "type":"Manufacturing & Wholesale Goods"
        }
    ],
    "sg:phone":"+1 678 967 2020",
    "sg:postcode":"30224",
    "sg:province":"GA",
    "sg:tags":[
        "textile",
        "distribution"
    ],
    "wof:name":"Innvision Hospitality Supply",
    "wof:placetype":"venue"
},
  "geometry": {"coordinates":[-84.297481,33.235722],"type":"Point"}
}