{
  "type": "Feature",
  "properties": {
    "iso:country":"US",
    "sg:address":"4929 N Main St",
    "sg:city":"Acworth",
    "sg:classifiers":[
        {
            "category":"Personal",
            "subcategory":"Beauty Salon",
            "type":"Services"
        }
    ],
    "sg:phone":"+1 770 974 1962",
    "sg:postcode":"30101",
    "sg:province":"GA",
    "wof:name":"Hair & Nail",
    "wof:placetype":"venue"
},
  "geometry": {"coordinates":[-84.68074,34.066978],"type":"Point"}
}