{
  "type": "Feature",
  "properties": {
    "iso:country":"US",
    "sg:address":"1525 E Park Place Blvd",
    "sg:city":"Stone Mountain",
    "sg:classifiers":[
        {
            "category":"Banks & Credit Unions",
            "subcategory":"Bank",
            "type":"Services"
        }
    ],
    "sg:phone":"+1 770 413 1413",
    "sg:postcode":"30087",
    "sg:province":"GA",
    "sg:tags":[
        "banker",
        "mortgage"
    ],
    "wof:name":"Avco Financial",
    "wof:placetype":"venue"
},
  "geometry": {"coordinates":[-84.11239999999999,33.824106],"type":"Point"}
}