{
  "type": "Feature",
  "properties": {
    "iso:country":"US",
    "sg:address":"40 Hickory St",
    "sg:city":"Metter",
    "sg:classifiers":[
        {
            "category":"Retail",
            "subcategory":"Laundry & Dry Cleaning",
            "type":"Services"
        }
    ],
    "sg:phone":"+1 912 685 5856",
    "sg:postcode":"30439",
    "sg:province":"GA",
    "sg:tags":[
        "drycleaning",
        "plant"
    ],
    "wof:name":"McCords Cleaners",
    "wof:placetype":"venue"
},
  "geometry": {"coordinates":[-82.064198,32.404483],"type":"Point"}
}