{
  "type": "Feature",
  "properties": {
    "addr:full":"302 E Ogeechee St Sylvania GA 30467",
    "addr:housenumber":"302",
    "addr:postcode":"30467",
    "addr:street":"E Ogeechee St",
    "iso:country":"US",
    "sg:address":"302 E Ogeechee St",
    "sg:city":"Sylvania",
    "sg:classifiers":[
        {
            "category":"Health Services",
            "subcategory":"Hospital",
            "type":"Services"
        }
    ],
    "sg:phone":"+1 912 564 7825",
    "sg:postcode":"30467",
    "sg:province":"GA",
    "sg:tags":[
        "mental"
    ],
    "wof:name":"Ogeechee Area Mental Health",
    "wof:placetype":"venue"
},
  "geometry": {"coordinates":[-81.632316,32.75168],"type":"Point"}
}