{
  "type": "Feature",
  "properties": {
    "iso:country":"US",
    "sg:address":"3535 Roswell Rd Ste 46",
    "sg:city":"Marietta",
    "sg:classifiers":[
        {
            "category":"Health Services",
            "subcategory":"Dentist",
            "type":"Services"
        }
    ],
    "sg:phone":"+1 678 560 4100",
    "sg:postcode":"30062",
    "sg:province":"GA",
    "wof:name":"Bradford Hank DMD",
    "wof:placetype":"venue"
},
  "geometry": {"coordinates":[-84.448573,33.979327],"type":"Point"}
}