{
  "type": "Feature",
  "properties": {
    "iso:country":"US",
    "sg:address":"405 W Mann St",
    "sg:city":"Glennville",
    "sg:classifiers":[
        {
            "category":"Food & Beverages",
            "subcategory":"Groceries & Convenience Stores",
            "type":"Retail Goods"
        }
    ],
    "sg:phone":"+1 912 654 2656",
    "sg:postcode":"30427",
    "sg:province":"GA",
    "sg:tags":[
        "meat"
    ],
    "wof:name":"Burkhalter IGA",
    "wof:placetype":"venue"
},
  "geometry": {"coordinates":[-81.930266,31.939432],"type":"Point"}
}