{
  "type": "Feature",
  "properties": {
    "addr:full":"322 Victory Dr Lyons GA 30436",
    "addr:housenumber":"322",
    "addr:postcode":"30436",
    "addr:street":"Victory Dr",
    "iso:country":"US",
    "sg:address":"322 Victory Dr",
    "sg:city":"Lyons",
    "sg:classifiers":[
        {
            "category":"Personal",
            "subcategory":"Beauty Salon",
            "type":"Services"
        }
    ],
    "sg:phone":"+1 912 526 6765",
    "sg:postcode":"30436",
    "sg:province":"GA",
    "sg:tags":[
        "shop"
    ],
    "wof:name":"Expressions Etc",
    "wof:placetype":"venue"
},
  "geometry": {"coordinates":[-82.32701299999999,32.19843],"type":"Point"}
}