{
  "type": "Feature",
  "properties": {
    "iso:country":"US",
    "sg:address":"2046 W Park Place Blvd",
    "sg:city":"Stone Mountain",
    "sg:classifiers":[
        {
            "category":"Professional",
            "subcategory":"Engineering",
            "type":"Services"
        },
        {
            "category":"Professional",
            "subcategory":"Management & Consulting",
            "type":"Services"
        }
    ],
    "sg:phone":"+1 770 413 0965",
    "sg:postcode":"30087",
    "sg:province":"GA",
    "sg:tags":[
        "firm",
        "engineer"
    ],
    "wof:name":"Tetra Tech Nus Inc",
    "wof:placetype":"venue"
},
  "geometry": {"coordinates":[-84.120364,33.81971],"type":"Point"}
}