{
  "type": "Feature",
  "properties": {
    "iso:country":"US",
    "sg:address":"1857 Newberry Ct",
    "sg:city":"Marietta",
    "sg:classifiers":[
        {
            "category":"Shopping",
            "subcategory":"Hobbies, Toys, & Games",
            "type":"Retail Goods"
        }
    ],
    "sg:phone":"+1 770 973 9930",
    "sg:postcode":"30062",
    "sg:province":"GA",
    "wof:name":"Pams Treasures",
    "wof:placetype":"venue"
},
  "geometry": {"coordinates":[-84.497147,33.989214],"type":"Point"}
}