{
  "type": "Feature",
  "properties": {
    "addr:full":"7105 State Hwy 92 Woodstock GA 30189",
    "addr:housenumber":"7105",
    "addr:postcode":"30189",
    "addr:street":"State Hwy 92",
    "iso:country":"US",
    "sg:address":"7105 State Hwy 92",
    "sg:city":"Woodstock",
    "sg:classifiers":[
        {
            "category":"Personal",
            "type":"Services"
        }
    ],
    "sg:phone":"+1 770 924 2333",
    "sg:postcode":"30189",
    "sg:province":"GA",
    "sg:tags":[
        "therapist",
        "massage"
    ],
    "wof:name":"Massage Therapy Center",
    "wof:placetype":"venue"
},
  "geometry": {"coordinates":[-84.569149,34.086059],"type":"Point"}
}