{
  "type": "Feature",
  "properties": {
    "addr:full":"348 S Main St Dawson GA 39842",
    "addr:housenumber":"348",
    "addr:postcode":"39842",
    "addr:street":"S Main St",
    "iso:country":"US",
    "sg:address":"348 S Main St",
    "sg:city":"Dawson",
    "sg:classifiers":[
        {
            "category":"Retail",
            "subcategory":"Auto Rental",
            "type":"Services"
        }
    ],
    "sg:phone":"+1 229 995 8474",
    "sg:postcode":"39842",
    "sg:province":"GA",
    "sg:tags":[
        "renting",
        "truck",
        "leasing"
    ],
    "wof:name":"U-Haul Co",
    "wof:placetype":"venue"
},
  "geometry": {"coordinates":[-84.44678999999999,31.770357],"type":"Point"}
}