{
  "type": "Feature",
  "properties": {
    "iso:country":"US",
    "sg:address":"2200 Habersham Marina Rd",
    "sg:city":"Cumming",
    "sg:classifiers":[
        {
            "category":"Recreation",
            "subcategory":"Marina",
            "type":"Entertainment"
        }
    ],
    "sg:phone":"+1 770 887 5432",
    "sg:postcode":"30041",
    "sg:province":"GA",
    "sg:tags":[
        "storage",
        "boat"
    ],
    "wof:name":"Habersham Marina",
    "wof:placetype":"venue"
},
  "geometry": {"coordinates":[-84.10217900000001,34.191596],"type":"Point"}
}