{
  "type": "Feature",
  "properties": {
    "iso:country":"US",
    "sg:address":"4500 Rushing Wind Ct",
    "sg:city":"Powder Springs",
    "sg:classifiers":[
        {
            "category":"Social Services",
            "subcategory":"Child Care",
            "type":"Services"
        }
    ],
    "sg:phone":"+1 770 439 9809",
    "sg:postcode":"30127",
    "sg:province":"GA",
    "sg:tags":[
        "day"
    ],
    "wof:name":"Betugo Loving Care Inc",
    "wof:placetype":"venue"
},
  "geometry": {"coordinates":[-84.68616299999999,33.883706],"type":"Point"}
}