{
  "type": "Feature",
  "properties": {
    "iso:country":"US",
    "sg:address":"1815 E Clay St",
    "sg:city":"Thomasville",
    "sg:classifiers":[
        {
            "category":"Social Services",
            "subcategory":"Adult Care",
            "type":"Services"
        }
    ],
    "sg:phone":"+1 229 226 4972",
    "sg:postcode":"31792",
    "sg:province":"GA",
    "sg:tags":[
        "residential"
    ],
    "wof:name":"Student Phone",
    "wof:placetype":"venue"
},
  "geometry": {"coordinates":[-83.963292,30.855563],"type":"Point"}
}