{
  "type": "Feature",
  "properties": {
    "addr:full":"7614 Auden Trl NE Atlanta GA 30350",
    "addr:housenumber":"7614",
    "addr:postcode":"30350",
    "addr:street":"Auden Trl Ne",
    "iso:country":"US",
    "sg:address":"7614 Auden Trl NE",
    "sg:city":"Atlanta",
    "sg:classifiers":[
        {
            "category":"Professional",
            "subcategory":"Business Services",
            "type":"Services"
        }
    ],
    "sg:phone":"+1 770 671 1178",
    "sg:postcode":"30350",
    "sg:province":"GA",
    "wof:name":"Mariana Enterprises Inc",
    "wof:placetype":"venue"
},
  "geometry": {"coordinates":[-84.34987,33.963662],"type":"Point"}
}