{
  "type": "Feature",
  "properties": {
    "addr:full":"662 Tibbitts Rd Dallas GA 30132",
    "addr:housenumber":"662",
    "addr:postcode":"30132",
    "addr:street":"Tibbitts Rd",
    "iso:country":"US",
    "sg:address":"662 Tibbitts Rd",
    "sg:city":"Dallas",
    "sg:classifiers":[
        {
            "category":"Building & Trades",
            "subcategory":"Electrical",
            "type":"Services"
        }
    ],
    "sg:phone":"+1 770 443 1749",
    "sg:postcode":"30132",
    "sg:province":"GA",
    "sg:tags":[
        "electrical",
        "contractor"
    ],
    "wof:name":"J & J Electrical Contractors",
    "wof:placetype":"venue"
},
  "geometry": {"coordinates":[-84.88391900000001,34.02154],"type":"Point"}
}