{
  "type": "Feature",
  "properties": {
    "iso:country":"US",
    "sg:address":"4848 Memorial Dr",
    "sg:city":"Stone Mountain",
    "sg:classifiers":[
        {
            "category":"Food & Beverages",
            "subcategory":"Groceries & Convenience Stores",
            "type":"Retail Goods"
        }
    ],
    "sg:phone":"+1 404 508 5557",
    "sg:postcode":"30083",
    "sg:province":"GA",
    "wof:name":"Ethio Market",
    "wof:placetype":"venue"
},
  "geometry": {"coordinates":[-84.232829,33.788011],"type":"Point"}
}