{
  "type": "Feature",
  "properties": {
    "iso:country":"US",
    "sg:address":"803 E Morris St",
    "sg:city":"Dalton",
    "sg:classifiers":[
        {
            "category":"Education",
            "subcategory":"School",
            "type":"Public Place"
        }
    ],
    "sg:phone":"+1 706 277 7807",
    "sg:postcode":"30721",
    "sg:province":"GA",
    "wof:name":"Brookwood Head Start Ctr",
    "wof:placetype":"venue"
},
  "geometry": {"coordinates":[-84.956834,34.768717],"type":"Point"}
}