{
  "type": "Feature",
  "properties": {
    "addr:full":"732 Murray Mc Cranie Rd Norman Park GA 31771",
    "addr:housenumber":"732",
    "addr:postcode":"31771",
    "addr:street":"Murray Mc Cranie Rd",
    "iso:country":"US",
    "sg:address":"732 Murray Mc Cranie Rd",
    "sg:city":"Norman Park",
    "sg:classifiers":[
        {
            "category":"Building & Trades",
            "subcategory":"Construction",
            "type":"Services"
        }
    ],
    "sg:phone":"+1 229 769 3068",
    "sg:postcode":"31771",
    "sg:province":"GA",
    "sg:tags":[
        "general",
        "contractor"
    ],
    "wof:name":"BMC Contractors Inc",
    "wof:placetype":"venue"
},
  "geometry": {"coordinates":[-83.567542,31.204748],"type":"Point"}
}