{
  "type": "Feature",
  "properties": {
    "iso:country":"US",
    "sg:address":"256 Commerce Dr",
    "sg:city":"Peachtree City",
    "sg:classifiers":[
        {
            "category":"Building & Trades",
            "subcategory":"Construction",
            "type":"Services"
        }
    ],
    "sg:phone":"+1 770 487 0922",
    "sg:postcode":"30269",
    "sg:province":"GA",
    "sg:tags":[
        "general",
        "contractor"
    ],
    "wof:name":"Rosetti Quality Custom Homes",
    "wof:placetype":"venue"
},
  "geometry": {"coordinates":[-84.592496,33.399417],"type":"Point"}
}