{
  "type": "Feature",
  "properties": {
    "addr:full":"3901 Davis Cir Duluth GA 30096",
    "addr:housenumber":"3901",
    "addr:postcode":"30096",
    "addr:street":"Davis Cir",
    "iso:country":"US",
    "sg:address":"3901 Davis Cir",
    "sg:city":"Duluth",
    "sg:classifiers":[
        {
            "category":"Building & Trades",
            "subcategory":"Locksmith",
            "type":"Services"
        }
    ],
    "sg:phone":"+1 770 325 3697",
    "sg:postcode":"30096",
    "sg:province":"GA",
    "sg:tags":[
        "key"
    ],
    "wof:name":"24 Hr Emergency Locksmith",
    "wof:placetype":"venue"
},
  "geometry": {"coordinates":[-84.148115,33.96036],"type":"Point"}
}