{
  "type": "Feature",
  "properties": {
    "addr:full":"4800 Briarcliff Rd NE Atlanta GA 30345",
    "addr:housenumber":"4800",
    "addr:postcode":"30345",
    "addr:street":"Briarcliff Rd Ne",
    "iso:country":"US",
    "sg:address":"4800 Briarcliff Rd NE",
    "sg:city":"Atlanta",
    "sg:classifiers":[
        {
            "category":"Deli",
            "type":"Food & Drink"
        }
    ],
    "sg:menulink":"http://www.allmenus.com/ga/tucker/244640-american-deli/menu/",
    "sg:phone":"+1 770 938 2211",
    "sg:postcode":"30345",
    "sg:province":"GA",
    "sg:tags":[
        "wrap",
        "american",
        "sandwich",
        "wing",
        "pub"
    ],
    "wof:name":"American Deli",
    "wof:placetype":"venue"
},
  "geometry": {"coordinates":[-84.25531700000001,33.849728],"type":"Point"}
}