{
  "type": "Feature",
  "properties": {
    "addr:full":"3056 Riverside Dr Macon GA 31210",
    "addr:housenumber":"3056",
    "addr:postcode":"31210",
    "addr:street":"Riverside Dr",
    "iso:country":"US",
    "sg:address":"3056 Riverside Dr",
    "sg:city":"Macon",
    "sg:classifiers":[
        {
            "category":"Autos & Motor Vehicles",
            "subcategory":"Automobile Sales",
            "type":"Retail Goods"
        },
        {
            "category":"Retail",
            "subcategory":"Auto Repair",
            "type":"Services"
        }
    ],
    "sg:phone":"+1 478 474 3700",
    "sg:postcode":"31210",
    "sg:province":"GA",
    "sg:tags":[
        "body",
        "repairing",
        "cars-wholesale",
        "used",
        "car",
        "dealers-used",
        "truck",
        "new",
        "painting"
    ],
    "sg:website":"http://www.fivestarmazda.com/",
    "wof:name":"Five Star Mazda",
    "wof:placetype":"venue"
},
  "geometry": {"coordinates":[-83.67572,32.889111],"type":"Point"}
}