{
  "type": "Feature",
  "properties": {
    "iso:country":"US",
    "sg:address":"821 Tree Farm Rd",
    "sg:city":"Moultrie",
    "sg:classifiers":[
        {
            "category":"Professional",
            "type":"Services"
        }
    ],
    "sg:phone":"+1 229 985 0649",
    "sg:postcode":"31768",
    "sg:province":"GA",
    "wof:name":"Jerry P Williams",
    "wof:placetype":"venue"
},
  "geometry": {"coordinates":[-83.829302,31.159309],"type":"Point"}
}