{
  "type": "Feature",
  "properties": {
    "iso:country":"US",
    "sg:address":"3451 Memorial Dr",
    "sg:city":"Decatur",
    "sg:classifiers":[
        {
            "category":"Home & Garden",
            "subcategory":"Home Furnishings",
            "type":"Retail Goods"
        },
        {
            "category":"Shopping",
            "subcategory":"Crafts & Fabrics",
            "type":"Retail Goods"
        }
    ],
    "sg:phone":"+1 404 289 8811",
    "sg:postcode":"30032",
    "sg:province":"GA",
    "sg:tags":[
        "drapery",
        "store",
        "trimming"
    ],
    "sg:website":"http://www.fabricworld.com",
    "wof:name":"Discount Fabric Centers",
    "wof:placetype":"venue"
},
  "geometry": {"coordinates":[-84.27159899999999,33.752602],"type":"Point"}
}