{
  "type": "Feature",
  "properties": {
    "addr:full":"192 Lafayette St Ringgold GA 30736",
    "addr:housenumber":"192",
    "addr:postcode":"30736",
    "addr:street":"Lafayette St",
    "iso:country":"US",
    "sg:address":"192 Lafayette St",
    "sg:city":"Ringgold",
    "sg:classifiers":[
        {
            "category":"Personal",
            "subcategory":"Beauty Salon",
            "type":"Services"
        }
    ],
    "sg:phone":"+1 706 965 4247",
    "sg:postcode":"30736",
    "sg:province":"GA",
    "wof:name":"Beaute N Motion",
    "wof:placetype":"venue"
},
  "geometry": {"coordinates":[-85.12318,34.912585],"type":"Point"}
}