{
  "type": "Feature",
  "properties": {
    "addr:full":"2899 Tejas Trl SW Atlanta GA 30331",
    "addr:housenumber":"2899",
    "addr:postcode":"30331",
    "addr:street":"Tejas Trl Sw",
    "iso:country":"US",
    "sg:address":"2899 Tejas Trl SW",
    "sg:city":"Atlanta",
    "sg:classifiers":[
        {
            "category":"Banks & Credit Unions",
            "subcategory":"Financial Services",
            "type":"Services"
        }
    ],
    "sg:phone":"+1 678 437 9108",
    "sg:postcode":"30331",
    "sg:province":"GA",
    "sg:tags":[
        "investment",
        "real estate"
    ],
    "wof:name":"Watkins RE Investments LLC",
    "wof:placetype":"venue"
},
  "geometry": {"coordinates":[-84.490351,33.676305],"type":"Point"}
}