{
  "type": "Feature",
  "properties": {
    "addr:full":"7107 Paces Park Dr Decatur GA 30033",
    "addr:housenumber":"7107",
    "addr:postcode":"30033",
    "addr:street":"Paces Park Dr",
    "iso:country":"US",
    "sg:address":"7107 Paces Park Dr",
    "sg:city":"Decatur",
    "sg:classifiers":[
        {
            "category":"Professional",
            "type":"Services"
        }
    ],
    "sg:phone":"+1 404 499 8529",
    "sg:postcode":"30033",
    "sg:province":"GA",
    "wof:name":"K S N Inc",
    "wof:placetype":"venue"
},
  "geometry": {"coordinates":[-84.276646,33.795156],"type":"Point"}
}