{
  "type": "Feature",
  "properties": {
    "iso:country":"US",
    "sg:address":"10560 Waters Ridge Dr",
    "sg:city":"Alpharetta",
    "sg:classifiers":[
        {
            "category":"Shopping",
            "subcategory":"Catalog Store",
            "type":"Retail Goods"
        }
    ],
    "sg:phone":"+1 678 300 1364",
    "sg:postcode":"30022",
    "sg:province":"GA",
    "sg:tags":[
        "mail",
        "house"
    ],
    "wof:name":"Fast & Hot LLC",
    "wof:placetype":"venue"
},
  "geometry": {"coordinates":[-84.255647,34.038186],"type":"Point"}
}