{
  "type": "Feature",
  "properties": {
    "addr:full":"1464 Spring St SE Smyrna GA 30080",
    "addr:housenumber":"1464",
    "addr:postcode":"30080",
    "addr:street":"Spring St Se",
    "iso:country":"US",
    "sg:address":"1464 Spring St SE",
    "sg:city":"Smyrna",
    "sg:classifiers":[
        {
            "category":"Organizations",
            "subcategory":"Religious Organization",
            "type":"Services"
        }
    ],
    "sg:phone":"+1 770 436 5403",
    "sg:postcode":"30080",
    "sg:province":"GA",
    "sg:tags":[
        "churches-baptist-independent"
    ],
    "wof:name":"Spring Street Baptist Church",
    "wof:placetype":"venue"
},
  "geometry": {"coordinates":[-84.510412,33.883724],"type":"Point"}
}