{
  "type": "Feature",
  "properties": {
    "addr:full":"4217 Marietta St Powder Springs GA 30127",
    "addr:housenumber":"4217",
    "addr:postcode":"30127",
    "addr:street":"Marietta St",
    "iso:country":"US",
    "sg:address":"4217 Marietta St",
    "sg:city":"Powder Springs",
    "sg:classifiers":[
        {
            "category":"Retail",
            "subcategory":"Portrait Studio",
            "type":"Services"
        }
    ],
    "sg:phone":"+1 770 222 1577",
    "sg:postcode":"30127",
    "sg:province":"GA",
    "sg:tags":[
        "photo"
    ],
    "wof:name":"Judith Ann Nelson Photogr",
    "wof:placetype":"venue"
},
  "geometry": {"coordinates":[-84.676557,33.858704],"type":"Point"}
}