{
  "type": "Feature",
  "properties": {
    "addr:full":"640 Walnut Rd Blairsville GA 30512",
    "addr:housenumber":"640",
    "addr:postcode":"30512",
    "addr:street":"Walnut Rd",
    "iso:country":"US",
    "sg:address":"640 Walnut Rd",
    "sg:city":"Blairsville",
    "sg:classifiers":[
        {
            "category":"Personal",
            "type":"Services"
        }
    ],
    "sg:phone":"+1 706 781 2971",
    "sg:postcode":"30512",
    "sg:province":"GA",
    "sg:tags":[
        "consultant",
        "wedding"
    ],
    "wof:name":"Unique Events",
    "wof:placetype":"venue"
},
  "geometry": {"coordinates":[-84.00563,34.866531],"type":"Point"}
}