{
  "type": "Feature",
  "properties": {
    "addr:full":"1156 Tennyson Pl NE Atlanta GA 30319",
    "addr:housenumber":"1156",
    "addr:postcode":"30319",
    "addr:street":"Tennyson Pl Ne",
    "iso:country":"US",
    "sg:address":"1156 Tennyson Pl NE",
    "sg:city":"Atlanta",
    "sg:classifiers":[
        {
            "category":"Restaurant",
            "type":"Food & Drink"
        }
    ],
    "sg:phone":"+1 404 303 8680",
    "sg:postcode":"30319",
    "sg:province":"GA",
    "sg:tags":[
        "dining",
        "management",
        "corporate"
    ],
    "wof:name":"Nico At The Depot",
    "wof:placetype":"venue"
},
  "geometry": {"coordinates":[-84.34287500000001,33.893061],"type":"Point"}
}