{
  "type": "Feature",
  "properties": {
    "iso:country":"US",
    "sg:address":"4890 Haydens Walk Dr",
    "sg:city":"Alpharetta",
    "sg:classifiers":[
        {
            "category":"Organizations",
            "subcategory":"Professional Association",
            "type":"Services"
        }
    ],
    "sg:phone":"+1 770 248 2982",
    "sg:postcode":"30022",
    "sg:province":"GA",
    "wof:name":"Hayden's Walk Assn",
    "wof:placetype":"venue"
},
  "geometry": {"coordinates":[-84.21634299999999,34.01033],"type":"Point"}
}