{
  "type": "Feature",
  "properties": {
    "iso:country":"US",
    "sg:address":"2775 Columbia Dr",
    "sg:city":"Decatur",
    "sg:classifiers":[
        {
            "category":"Social Services",
            "type":"Services"
        }
    ],
    "sg:phone":"+1 404 289 6366",
    "sg:postcode":"30034",
    "sg:province":"GA",
    "sg:tags":[
        "youth",
        "organization",
        "center"
    ],
    "wof:name":"Glenwood Hills Athletic Assn",
    "wof:placetype":"venue"
},
  "geometry": {"coordinates":[-84.25273300000001,33.703797],"type":"Point"}
}