{
  "type": "Feature",
  "properties": {
    "addr:full":"1130 Alabama St Carrollton GA 30117",
    "addr:housenumber":"1130",
    "addr:postcode":"30117",
    "addr:street":"Alabama St",
    "iso:country":"US",
    "sg:address":"1130 Alabama St",
    "sg:city":"Carrollton",
    "sg:classifiers":[
        {
            "category":"Utilities",
            "subcategory":"Electric",
            "type":"Services"
        }
    ],
    "sg:phone":"+1 770 214 5205",
    "sg:postcode":"30117",
    "sg:province":"GA",
    "sg:tags":[
        "company",
        "public"
    ],
    "wof:name":"Georgia Power Company",
    "wof:placetype":"venue"
},
  "geometry": {"coordinates":[-85.10492000000001,33.588515],"type":"Point"}
}