{
  "type": "Feature",
  "properties": {
    "iso:country":"US",
    "sg:address":"10150 N Coleman Rd",
    "sg:city":"Roswell",
    "sg:classifiers":[
        {
            "category":"Professional",
            "type":"Services"
        },
        {
            "category":"Real Estate",
            "subcategory":"Real Estate Agent",
            "type":"Services"
        }
    ],
    "sg:phone":"+1 770 518 4922",
    "sg:postcode":"30075",
    "sg:province":"GA",
    "sg:tags":[
        "reporting",
        "inspection"
    ],
    "wof:name":"J Peter Rushworth Inc",
    "wof:placetype":"venue"
},
  "geometry": {"coordinates":[-84.370519,34.027668],"type":"Point"}
}