{
  "type": "Feature",
  "properties": {
    "addr:full":"4890 Roswell Rd Atlanta GA 30342",
    "addr:housenumber":"4890",
    "addr:postcode":"30342",
    "addr:street":"Roswell Rd",
    "iso:country":"US",
    "sg:address":"4890 Roswell Rd",
    "sg:city":"Atlanta",
    "sg:classifiers":[
        {
            "category":"Health Services",
            "subcategory":"Doctor",
            "type":"Services"
        }
    ],
    "sg:phone":"+1 404 845 1235",
    "sg:postcode":"30342",
    "sg:province":"GA",
    "wof:name":"Promina Piedmont Medical",
    "wof:placetype":"venue"
},
  "geometry": {"coordinates":[-84.381758,33.886574],"type":"Point"}
}