{
  "type": "Feature",
  "properties": {
    "iso:country":"US",
    "sg:address":"1500 Aviation Blvd",
    "sg:city":"Atlanta",
    "sg:classifiers":[
        {
            "category":"Professional",
            "type":"Services"
        }
    ],
    "sg:phone":"+1 404 530 6492",
    "sg:postcode":"30354",
    "sg:province":"GA",
    "sg:tags":[
        "support",
        "airline"
    ],
    "wof:name":"Gate Gourmet",
    "wof:placetype":"venue"
},
  "geometry": {"coordinates":[-84.41176,33.640961],"type":"Point"}
}