{
  "type": "Feature",
  "properties": {
    "iso:country":"US",
    "sg:address":"576 Colonial Park Dr",
    "sg:city":"Roswell",
    "sg:classifiers":[
        {
            "category":"Building & Trades",
            "subcategory":"Equipment Rental",
            "type":"Services"
        }
    ],
    "sg:phone":"+1 770 587 1156",
    "sg:postcode":"30075",
    "sg:province":"GA",
    "sg:tags":[
        "medical"
    ],
    "wof:name":"Physicans Equipment Funding",
    "wof:placetype":"venue"
},
  "geometry": {"coordinates":[-84.34320099999999,34.032796],"type":"Point"}
}