{
  "type": "Feature",
  "properties": {
    "addr:full":"1098 Colony Dr Alpharetta GA 30004",
    "addr:housenumber":"1098",
    "addr:postcode":"30004",
    "addr:street":"Colony Dr",
    "iso:country":"US",
    "sg:address":"1098 Colony Dr",
    "sg:city":"Alpharetta",
    "sg:classifiers":[
        {
            "category":"Professional",
            "subcategory":"Accounting & Tax Preparation",
            "type":"Services"
        }
    ],
    "sg:phone":"+1 770 664 7969",
    "sg:postcode":"30004",
    "sg:province":"GA",
    "wof:name":"Dowis-Bradley Inc",
    "wof:placetype":"venue"
},
  "geometry": {"coordinates":[-84.314014,34.089582],"type":"Point"}
}