{
  "type": "Feature",
  "properties": {
    "iso:country":"US",
    "sg:address":"402 Broad St",
    "sg:city":"Hawkinsville",
    "sg:classifiers":[
        {
            "category":"Real Estate",
            "subcategory":"Real Estate Agent",
            "type":"Services"
        }
    ],
    "sg:phone":"+1 478 783 0620",
    "sg:postcode":"31036",
    "sg:province":"GA",
    "wof:name":"Ocmulgee Valley Land Co Inc",
    "wof:placetype":"venue"
},
  "geometry": {"coordinates":[-83.47023,32.281841],"type":"Point"}
}