{
  "type": "Feature",
  "properties": {
    "iso:country":"US",
    "sg:address":"2004 Wax Rd SE",
    "sg:city":"Aragon",
    "sg:classifiers":[
        {
            "category":"Building & Trades",
            "subcategory":"Construction",
            "type":"Services"
        }
    ],
    "sg:phone":"+1 706 235 4849",
    "sg:postcode":"30104",
    "sg:province":"GA",
    "sg:tags":[
        "house"
    ],
    "wof:name":"Smith Builders",
    "wof:placetype":"venue"
},
  "geometry": {"coordinates":[-85.09929200000001,34.140488],"type":"Point"}
}