{
  "type": "Feature",
  "properties": {
    "iso:country":"US",
    "sg:address":"9590 Medlock Bridge Rd",
    "sg:city":"Duluth",
    "sg:classifiers":[
        {
            "category":"Health Services",
            "subcategory":"Dentist",
            "type":"Services"
        }
    ],
    "sg:phone":"+1 770 476 9356",
    "sg:postcode":"30097",
    "sg:province":"GA",
    "sg:tags":[
        "orthodontist"
    ],
    "wof:name":"MacHemehl Charles DMD MSD",
    "wof:placetype":"venue"
},
  "geometry": {"coordinates":[-84.191902,34.012501],"type":"Point"}
}