{
  "type": "Feature",
  "properties": {
    "addr:full":"2900 Delk Rd SE Ste 1450 Marietta GA 30067",
    "addr:housenumber":"2900",
    "addr:postcode":"30067",
    "addr:street":"Delk Rd Se Ste 1450",
    "iso:country":"US",
    "sg:address":"2900 Delk Rd SE Ste 1450",
    "sg:city":"Marietta",
    "sg:classifiers":[
        {
            "category":"Insurance",
            "subcategory":"Health Insurance",
            "type":"Services"
        }
    ],
    "sg:phone":"+1 770 951 8555",
    "sg:postcode":"30067",
    "sg:province":"GA",
    "sg:tags":[
        "market"
    ],
    "sg:website":"www.smoothieking.com",
    "wof:name":"Smoothie King",
    "wof:placetype":"venue"
},
  "geometry": {"coordinates":[-84.46820099999999,33.923901],"type":"Point"}
}