{
  "type": "Feature",
  "properties": {
    "iso:country":"US",
    "sg:address":"6865 Glenlake Pkwy NE",
    "sg:city":"Atlanta",
    "sg:classifiers":[
        {
            "category":"Professional",
            "type":"Services"
        }
    ],
    "sg:phone":"+1 404 409 4587",
    "sg:postcode":"30328",
    "sg:province":"GA",
    "wof:name":"Tree Promotions/Bea",
    "wof:placetype":"venue"
},
  "geometry": {"coordinates":[-84.361239,33.934812],"type":"Point"}
}