{
  "type": "Feature",
  "properties": {
    "iso:country":"US",
    "sg:address":"1815 Windburn Ct SW",
    "sg:city":"Snellville",
    "sg:classifiers":[
        {
            "category":"Professional",
            "subcategory":"Computer Services",
            "type":"Services"
        }
    ],
    "sg:phone":"+1 678 344 1797",
    "sg:postcode":"30078",
    "sg:province":"GA",
    "sg:tags":[
        "processing",
        "datum"
    ],
    "wof:name":"Dp-Helper",
    "wof:placetype":"venue"
},
  "geometry": {"coordinates":[-84.00212399999999,33.877354],"type":"Point"}
}