{
  "type": "Feature",
  "properties": {
    "addr:full":"5628 Milgen Rd Columbus GA 31907",
    "addr:housenumber":"5628",
    "addr:postcode":"31907",
    "addr:street":"Milgen Rd",
    "iso:country":"US",
    "sg:address":"5628 Milgen Rd",
    "sg:city":"Columbus",
    "sg:classifiers":[
        {
            "category":"Restaurant",
            "type":"Food & Drink"
        }
    ],
    "sg:menulink":"http://www.allmenus.com/ga/columbus/203231-mcdonalds/menu/",
    "sg:postcode":"31907",
    "sg:province":"GA",
    "sg:tags":[
        "burger",
        "american"
    ],
    "wof:name":"McDonald's",
    "wof:placetype":"venue"
},
  "geometry": {"coordinates":[-84.888156,32.524885],"type":"Point"}
}