{
  "type": "Feature",
  "properties": {
    "iso:country":"US",
    "sg:address":"143 Cherry Point Dr",
    "sg:city":"St Marys",
    "sg:classifiers":[
        {
            "category":"Retail",
            "subcategory":"Repair Shop",
            "type":"Services"
        }
    ],
    "sg:phone":"+1 912 729 2845",
    "sg:postcode":"31558",
    "sg:province":"GA",
    "sg:tags":[
        "lock",
        "locksmith"
    ],
    "wof:name":"American Lock & Key",
    "wof:placetype":"venue"
},
  "geometry": {"coordinates":[-81.582611,30.807363],"type":"Point"}
}