{
  "type": "Feature",
  "properties": {
    "addr:full":"408 Northside Dr Warner Robins GA 31093",
    "addr:housenumber":"408",
    "addr:postcode":"31093",
    "addr:street":"Northside Dr",
    "iso:country":"US",
    "sg:address":"408 Northside Dr",
    "sg:city":"Warner Robins",
    "sg:classifiers":[
        {
            "category":"Organizations",
            "subcategory":"Religious Organization",
            "type":"Services"
        }
    ],
    "sg:phone":"+1 478 929 0005",
    "sg:postcode":"31093",
    "sg:province":"GA",
    "wof:name":"Resurrection Baptist Church",
    "wof:placetype":"venue"
},
  "geometry": {"coordinates":[-83.631798,32.630699],"type":"Point"}
}