{
  "type": "Feature",
  "properties": {
    "addr:full":"4141 Milgen Rd Columbus GA 31907",
    "addr:housenumber":"4141",
    "addr:postcode":"31907",
    "addr:street":"Milgen Rd",
    "iso:country":"US",
    "sg:address":"4141 Milgen Rd",
    "sg:city":"Columbus",
    "sg:classifiers":[
        {
            "category":"Wholesale",
            "subcategory":"Construction Materials",
            "type":"Manufacturing & Wholesale Goods"
        }
    ],
    "sg:phone":"+1 706 563 6165",
    "sg:postcode":"31907",
    "sg:province":"GA",
    "sg:tags":[
        "roofing"
    ],
    "wof:name":"ABC Supply Co",
    "wof:placetype":"venue"
},
  "geometry": {"coordinates":[-84.928844,32.511174],"type":"Point"}
}