{
  "type": "Feature",
  "properties": {
    "addr:full":"1501 Andrea Dr Waycross GA 31501",
    "addr:housenumber":"1501",
    "addr:postcode":"31501",
    "addr:street":"Andrea Dr",
    "iso:country":"US",
    "sg:address":"1501 Andrea Dr",
    "sg:city":"Waycross",
    "sg:classifiers":[
        {
            "category":"Building & Trades",
            "subcategory":"Construction",
            "type":"Services"
        }
    ],
    "sg:phone":"+1 912 283 2177",
    "sg:postcode":"31501",
    "sg:province":"GA",
    "sg:tags":[
        "roofing",
        "contractor"
    ],
    "wof:name":"Boatright Roofing & Gen Contr",
    "wof:placetype":"venue"
},
  "geometry": {"coordinates":[-82.326239,31.218535],"type":"Point"}
}