{
  "type": "Feature",
  "properties": {
    "addr:full":"131 N Main St Jonesboro GA 30236",
    "addr:housenumber":"131",
    "addr:postcode":"30236",
    "addr:street":"N Main St",
    "iso:country":"US",
    "sg:address":"131 N Main St",
    "sg:city":"Jonesboro",
    "sg:classifiers":[
        {
            "category":"Shopping",
            "subcategory":"Gifts & Souvenirs",
            "type":"Retail Goods"
        }
    ],
    "sg:phone":"+1 770 471 1725",
    "sg:postcode":"30236",
    "sg:province":"GA",
    "sg:tags":[
        "shop"
    ],
    "wof:name":"Trifles & Treasures Inc",
    "wof:placetype":"venue"
},
  "geometry": {"coordinates":[-84.354541,33.521188],"type":"Point"}
}