{
  "type": "Feature",
  "properties": {
    "iso:country":"US",
    "sg:address":"55 Hilliard St SE",
    "sg:city":"Atlanta",
    "sg:classifiers":[
        {
            "category":"Retail",
            "subcategory":"Auto Repair",
            "type":"Services"
        }
    ],
    "sg:phone":"+1 404 394 0213",
    "sg:postcode":"30312",
    "sg:province":"GA",
    "sg:tags":[
        "automotive"
    ],
    "wof:name":"C & C Jr Towing Services Inc",
    "wof:placetype":"venue"
},
  "geometry": {"coordinates":[-84.376732,33.752219],"type":"Point"}
}