{
  "type": "Feature",
  "properties": {
    "addr:full":"1855 Beecher Rd SW Atlanta GA 30310",
    "addr:housenumber":"1855",
    "addr:postcode":"30310",
    "addr:street":"Beecher Rd Sw",
    "iso:country":"US",
    "sg:address":"1855 Beecher Rd SW",
    "sg:city":"Atlanta",
    "sg:classifiers":[
        {
            "category":"Place Of Worship",
            "subcategory":"Church",
            "type":"Public Place"
        },
        {
            "category":"Place Of Worship",
            "type":"Public Place"
        }
    ],
    "sg:phone":"+1 404 758 1753",
    "sg:postcode":"30310",
    "sg:province":"GA",
    "sg:tags":[
        "churches-interdenominational",
        "churches-various",
        "denomination"
    ],
    "wof:name":"Christian Mission Holiness Church Inc",
    "wof:placetype":"venue"
},
  "geometry": {"coordinates":[-84.448227,33.733711],"type":"Point"}
}