{
  "type": "Feature",
  "properties": {
    "addr:full":"3617 Braselton Hwy Ste 102 Dacula GA 30019",
    "addr:housenumber":"3617",
    "addr:postcode":"ga 30019",
    "addr:street":"Braselton Hwy Ste 102",
    "iso:country":"US",
    "sg:address":"3617 Braselton Hwy Ste 102",
    "sg:city":"Dacula",
    "sg:classifiers":[
        {
            "category":"Health Services",
            "subcategory":"Dentist",
            "type":"Services"
        }
    ],
    "sg:phone":"+1 770 904 6088",
    "sg:postcode":"30019",
    "sg:province":"GA",
    "wof:name":"Elena E Kurz DMD PC",
    "wof:placetype":"venue"
},
  "geometry": {"coordinates":[-83.90532399999999,34.069047],"type":"Point"}
}