{
  "type": "Feature",
  "properties": {
    "addr:full":"1076 Concord Rd Smyrna GA 30080",
    "addr:housenumber":"1076",
    "addr:postcode":"30080",
    "addr:street":"Concord Rd",
    "iso:country":"US",
    "sg:address":"1076 Concord Rd",
    "sg:city":"Smyrna",
    "sg:classifiers":[
        {
            "category":"Social Services",
            "subcategory":"Child Care",
            "type":"Services"
        }
    ],
    "sg:phone":"+1 770 436 1040",
    "sg:postcode":"30080",
    "sg:province":"GA",
    "wof:name":"Smyrna Playskool",
    "wof:placetype":"venue"
},
  "geometry": {"coordinates":[-84.520804,33.876107],"type":"Point"}
}