{
  "type": "Feature",
  "properties": {
    "iso:country":"US",
    "sg:address":"410 Windship Pl NW",
    "sg:city":"Atlanta",
    "sg:classifiers":[
        {
            "category":"Social Services",
            "type":"Services"
        }
    ],
    "sg:phone":"+1 404 851 0080",
    "sg:postcode":"30327",
    "sg:province":"GA",
    "sg:tags":[
        "counselor",
        "marriage",
        "family"
    ],
    "wof:name":"Susan Boone",
    "wof:placetype":"venue"
},
  "geometry": {"coordinates":[-84.403465,33.898096],"type":"Point"}
}