{
  "type": "Feature",
  "properties": {
    "iso:country":"US",
    "sg:address":"2270 Lindmont Cir NE",
    "sg:city":"Atlanta",
    "sg:classifiers":[
        {
            "category":"Professional",
            "subcategory":"Management & Consulting",
            "type":"Services"
        }
    ],
    "sg:phone":"+1 770 262 2635",
    "sg:postcode":"30324",
    "sg:province":"GA",
    "sg:tags":[
        "music"
    ],
    "wof:name":"Blaquenese Management Inc",
    "wof:placetype":"venue"
},
  "geometry": {"coordinates":[-84.365696,33.818307],"type":"Point"}
}