{
  "type": "Feature",
  "properties": {
    "iso:country":"US",
    "sg:address":"6653 Rocky Ford Rd",
    "sg:city":"Garfield",
    "sg:classifiers":[
        {
            "category":"Building & Trades",
            "subcategory":"Plumbing",
            "type":"Services"
        }
    ],
    "sg:phone":"+1 912 865 9495",
    "sg:postcode":"30450",
    "sg:province":"GA",
    "sg:tags":[
        "contractor"
    ],
    "wof:name":"Anderson Heating & Air",
    "wof:placetype":"venue"
},
  "geometry": {"coordinates":[-81.858408,32.612526],"type":"Point"}
}