{
  "type": "Feature",
  "properties": {
    "iso:country":"US",
    "sg:address":"9 Oleander Ave",
    "sg:city":"Savannah",
    "sg:classifiers":[
        {
            "category":"Building & Trades",
            "subcategory":"Construction",
            "type":"Services"
        }
    ],
    "sg:phone":"+1 912 233 0901",
    "sg:postcode":"31404",
    "sg:province":"GA",
    "sg:tags":[
        "consultant",
        "industrial",
        "contractors-commercial"
    ],
    "wof:name":"J C Master Builders Inc",
    "wof:placetype":"venue"
},
  "geometry": {"coordinates":[-81.07446299999999,32.045453],"type":"Point"}
}