{
  "type": "Feature",
  "properties": {
    "addr:full":"845 W Broad St Athens GA 30606",
    "addr:housenumber":"845",
    "addr:postcode":"30606",
    "addr:street":"W Broad St",
    "iso:country":"US",
    "sg:address":"845 W Broad St",
    "sg:city":"Athens",
    "sg:classifiers":[
        {
            "category":"Wholesale",
            "subcategory":"Construction Materials",
            "type":"Manufacturing & Wholesale Goods"
        }
    ],
    "sg:phone":"+1 706 559 9544",
    "sg:postcode":"30606",
    "sg:province":"GA",
    "wof:name":"Kaptivating Window Fashions",
    "wof:placetype":"venue"
},
  "geometry": {"coordinates":[-83.386436,33.955319],"type":"Point"}
}