{
  "type": "Feature",
  "properties": {
    "iso:country":"US",
    "sg:address":"4870 Aldbury Ln",
    "sg:city":"Suwanee",
    "sg:classifiers":[
        {
            "category":"Real Estate",
            "subcategory":"Real Estate Operator",
            "type":"Services"
        }
    ],
    "sg:phone":"+1 770 844 9834",
    "sg:postcode":"30024",
    "sg:province":"GA",
    "sg:tags":[
        "building",
        "nonresidential"
    ],
    "wof:name":"Stahl Properties Inc",
    "wof:placetype":"venue"
},
  "geometry": {"coordinates":[-84.14237300000001,34.092696],"type":"Point"}
}