{
  "type": "Feature",
  "properties": {
    "iso:country":"US",
    "sg:address":"2800 Holly Springs Pkwy Ste 100",
    "sg:city":"Canton",
    "sg:classifiers":[
        {
            "category":"Retail",
            "subcategory":"Repair Shop",
            "type":"Services"
        }
    ],
    "sg:phone":"+1 770 423 0100",
    "sg:postcode":"30115",
    "sg:province":"GA",
    "sg:tags":[
        "reupholstery",
        "furniture"
    ],
    "wof:name":"Scott Upholstery",
    "wof:placetype":"venue"
},
  "geometry": {"coordinates":[-84.50141600000001,34.173885],"type":"Point"}
}