{
  "type": "Feature",
  "properties": {
    "iso:country":"US",
    "sg:address":"3650 Cameron Cir",
    "sg:city":"Gainesville",
    "sg:classifiers":[
        {
            "category":"Real Estate",
            "subcategory":"Architect",
            "type":"Services"
        }
    ],
    "sg:phone":"+1 678 450 0049",
    "sg:postcode":"30506",
    "sg:province":"GA",
    "sg:tags":[
        "home",
        "planning",
        "design"
    ],
    "wof:name":"Advanced Homes",
    "wof:placetype":"venue"
},
  "geometry": {"coordinates":[-83.904211,34.303374],"type":"Point"}
}