{
  "type": "Feature",
  "properties": {
    "addr:full":"301 4th Ave SE Moultrie GA 31768",
    "addr:housenumber":"301",
    "addr:postcode":"31768",
    "addr:street":"4Th Ave Se",
    "iso:country":"US",
    "sg:address":"301 4th Ave SE",
    "sg:city":"Moultrie",
    "sg:classifiers":[
        {
            "category":"Personal",
            "subcategory":"Beauty Salon",
            "type":"Services"
        }
    ],
    "sg:phone":"+1 229 985 7543",
    "sg:postcode":"31768",
    "sg:province":"GA",
    "sg:tags":[
        "shop"
    ],
    "wof:name":"Magic Mirror",
    "wof:placetype":"venue"
},
  "geometry": {"coordinates":[-83.78525399999999,31.175759],"type":"Point"}
}