{
  "type": "Feature",
  "properties": {
    "addr:full":"813 Love Ave Tifton GA 31794",
    "addr:housenumber":"813",
    "addr:postcode":"31794",
    "addr:street":"Love Ave",
    "iso:country":"US",
    "sg:address":"813 Love Ave",
    "sg:city":"Tifton",
    "sg:classifiers":[
        {
            "category":"Real Estate",
            "subcategory":"Real Estate Services",
            "type":"Services"
        },
        {
            "category":"Real Estate",
            "subcategory":"Surveying",
            "type":"Services"
        },
        {
            "category":"Real Estate",
            "subcategory":"Real Estate Agent",
            "type":"Services"
        },
        {
            "category":"Professional",
            "type":"Services"
        }
    ],
    "sg:phone":"+1 229 386 4222",
    "sg:postcode":"31794",
    "sg:province":"GA",
    "sg:tags":[
        "rental",
        "relocation",
        "appraiser"
    ],
    "sg:website":"http://www.tifton-ga-realestate.com",
    "wof:name":"D. Coleman Realty Group",
    "wof:placetype":"venue"
},
  "geometry": {"coordinates":[-83.50698,31.45971],"type":"Point"}
}