{
  "type": "Feature",
  "properties": {
    "addr:full":"30 Fawn Lake Trl NE White GA 30184",
    "addr:housenumber":"30",
    "addr:postcode":"30184",
    "addr:street":"Fawn Lake Trl Ne",
    "iso:country":"US",
    "sg:address":"30 Fawn Lake Trl NE",
    "sg:city":"White",
    "sg:classifiers":[
        {
            "category":"Professional",
            "type":"Services"
        }
    ],
    "sg:phone":"+1 770 607 5719",
    "sg:postcode":"30184",
    "sg:province":"GA",
    "wof:name":"Empress Arts",
    "wof:placetype":"venue"
},
  "geometry": {"coordinates":[-84.707311,34.229721],"type":"Point"}
}