{
  "type": "Feature",
  "properties": {
    "iso:country":"US",
    "sg:address":"2572 Apple Valley Rd NE # 200",
    "sg:city":"Atlanta",
    "sg:classifiers":[
        {
            "category":"Utilities",
            "subcategory":"Water",
            "type":"Services"
        }
    ],
    "sg:phone":"+1 404 364 0012",
    "sg:postcode":"30319",
    "sg:province":"GA",
    "sg:tags":[
        "bulk",
        "companies-bottled"
    ],
    "wof:name":"Water Resource Technologies",
    "wof:placetype":"venue"
},
  "geometry": {"coordinates":[-84.33714000000001,33.861696],"type":"Point"}
}