{
  "type": "Feature",
  "properties": {
    "addr:full":"205 E Central Ave Fitzgerald GA 31750",
    "addr:housenumber":"205",
    "addr:postcode":"31750",
    "addr:street":"E Central Ave",
    "iso:country":"US",
    "sg:address":"205 E Central Ave",
    "sg:city":"Fitzgerald",
    "sg:classifiers":[
        {
            "category":"Personal",
            "subcategory":"Beauty Salon",
            "type":"Services"
        }
    ],
    "sg:phone":"+1 229 423 5022",
    "sg:postcode":"31750",
    "sg:province":"GA",
    "wof:name":"Les's Beauty & Tanning Salon",
    "wof:placetype":"venue"
},
  "geometry": {"coordinates":[-83.252876,31.714793],"type":"Point"}
}