{
  "type": "Feature",
  "properties": {
    "iso:country":"US",
    "sg:address":"3566 Community Rd",
    "sg:city":"Brunswick",
    "sg:classifiers":[
        {
            "category":"Building & Trades",
            "subcategory":"Construction",
            "type":"Services"
        }
    ],
    "sg:phone":"+1 912 267 1823",
    "sg:postcode":"31520",
    "sg:province":"GA",
    "sg:tags":[
        "designer",
        "concrete",
        "hot",
        "spa",
        "tub",
        "dealer",
        "pool",
        "swimming"
    ],
    "sg:website":"www.coastalcooperage.com",
    "wof:name":"Coastal Cooperage Inc",
    "wof:placetype":"venue"
},
  "geometry": {"coordinates":[-81.496466,31.202806],"type":"Point"}
}