{
  "type": "Feature",
  "properties": {
    "iso:country":"US",
    "sg:address":"3144 Brookshire Way",
    "sg:city":"Duluth",
    "sg:classifiers":[
        {
            "category":"Personal",
            "subcategory":"Barber",
            "type":"Services"
        }
    ],
    "sg:phone":"+1 770 622 6500",
    "sg:postcode":"30096",
    "sg:province":"GA",
    "sg:tags":[
        "shop"
    ],
    "wof:name":"Whitlock William G Barbar",
    "wof:placetype":"venue"
},
  "geometry": {"coordinates":[-84.127787,33.997541],"type":"Point"}
}