{
  "type": "Feature",
  "properties": {
    "addr:full":"3501 Memorial Dr Decatur GA 30032",
    "addr:housenumber":"3501",
    "addr:postcode":"30032",
    "addr:street":"Memorial Dr",
    "iso:country":"US",
    "sg:address":"3501 Memorial Dr",
    "sg:city":"Decatur",
    "sg:classifiers":[
        {
            "category":"Personal",
            "subcategory":"Nail Salon",
            "type":"Services"
        }
    ],
    "sg:phone":"+1 404 534 0064",
    "sg:postcode":"30032",
    "sg:province":"GA",
    "wof:name":"Loc Truong",
    "wof:placetype":"venue"
},
  "geometry": {"coordinates":[-84.268963,33.753926],"type":"Point"}
}