{
  "type": "Feature",
  "properties": {
    "addr:full":"3485 N Desert Dr Ste 2220 Atlanta GA 30344",
    "addr:housenumber":"3485",
    "addr:postcode":"30344",
    "addr:street":"N Desert Dr Ste 2220",
    "iso:country":"US",
    "sg:address":"3485 N Desert Dr Ste 2220",
    "sg:city":"Atlanta",
    "sg:classifiers":[
        {
            "category":"Professional",
            "subcategory":"Lawyer & Legal Services",
            "type":"Services"
        }
    ],
    "sg:phone":"+1 404 765 6445",
    "sg:postcode":"30344",
    "sg:province":"GA",
    "wof:name":"Fuller Law Group",
    "wof:placetype":"venue"
},
  "geometry": {"coordinates":[-84.495451,33.662],"type":"Point"}
}