{
  "type": "Feature",
  "properties": {
    "addr:full":"417 Pine Ave Albany GA 31701",
    "addr:housenumber":"417",
    "addr:postcode":"31701",
    "addr:street":"Pine Ave",
    "iso:country":"US",
    "sg:address":"417 Pine Ave",
    "sg:city":"Albany",
    "sg:classifiers":[
        {
            "category":"Professional",
            "subcategory":"Lawyer & Legal Services",
            "type":"Services"
        }
    ],
    "sg:phone":"+1 229 888 1105",
    "sg:postcode":"31701",
    "sg:province":"GA",
    "wof:name":"Custer Custer & Clark",
    "wof:placetype":"venue"
},
  "geometry": {"coordinates":[-84.158519,31.578573],"type":"Point"}
}