{
  "type": "Feature",
  "properties": {
    "addr:full":"504 Lake Tomacheechee Dr Rincon GA 31326",
    "addr:housenumber":"504",
    "addr:postcode":"31326",
    "addr:street":"Lake Tomacheechee Dr",
    "iso:country":"US",
    "sg:address":"504 Lake Tomacheechee Dr",
    "sg:city":"Rincon",
    "sg:classifiers":[
        {
            "category":"Manufacturing",
            "subcategory":"Retail Goods",
            "type":"Manufacturing & Wholesale Goods"
        }
    ],
    "sg:phone":"+1 912 604 2160",
    "sg:postcode":"31326",
    "sg:province":"GA",
    "sg:tags":[
        "product",
        "mfg"
    ],
    "wof:name":"Cla Industries Inc",
    "wof:placetype":"venue"
},
  "geometry": {"coordinates":[-81.20995000000001,32.270913],"type":"Point"}
}