{
  "type": "Feature",
  "properties": {
    "iso:country":"US",
    "sg:address":"802 Ave B",
    "sg:city":"Rome",
    "sg:classifiers":[
        {
            "category":"Real Estate",
            "subcategory":"Real Estate Agent",
            "type":"Services"
        }
    ],
    "sg:phone":"+1 706 232 2034",
    "sg:postcode":"30165",
    "sg:province":"GA",
    "sg:tags":[
        "appraiser"
    ],
    "wof:name":"Hunt & Assoc Appraisal Svc",
    "wof:placetype":"venue"
},
  "geometry": {"coordinates":[-85.175062,34.262057],"type":"Point"}
}