{
  "type": "Feature",
  "properties": {
    "addr:full":"3070 Sylvan Rd Atlanta GA 30354",
    "addr:housenumber":"3070",
    "addr:postcode":"30354",
    "addr:street":"Sylvan Rd",
    "iso:country":"US",
    "sg:address":"3070 Sylvan Rd",
    "sg:city":"Atlanta",
    "sg:classifiers":[
        {
            "category":"Retail",
            "subcategory":"Auto Rental",
            "type":"Services"
        }
    ],
    "sg:phone":"+1 404 763 2454",
    "sg:postcode":"30354",
    "sg:province":"GA",
    "sg:tags":[
        "passenger",
        "leasing",
        "car"
    ],
    "wof:name":"Enterprise Leasing Company GA",
    "wof:placetype":"venue"
},
  "geometry": {"coordinates":[-84.418815,33.667325],"type":"Point"}
}