{
  "type": "Feature",
  "properties": {
    "iso:country":"US",
    "sg:address":"5920 Roswell Rd NE B107",
    "sg:city":"Atlanta",
    "sg:classifiers":[
        {
            "category":"Shopping",
            "subcategory":"Hobbies, Toys, & Games",
            "type":"Retail Goods"
        }
    ],
    "sg:phone":"+1 404 252 6812",
    "sg:postcode":"30328",
    "sg:province":"GA",
    "sg:tags":[
        "coin",
        "supply"
    ],
    "sg:website":"http://www.southerncoin.com",
    "wof:name":"Southern Coin Investments Inc",
    "wof:placetype":"venue"
},
  "geometry": {"coordinates":[-84.379171,33.916852],"type":"Point"}
}