{
  "type": "Feature",
  "properties": {
    "iso:country":"US",
    "sg:address":"4500 Hugh Howell Rd Ste 330",
    "sg:city":"Tucker",
    "sg:classifiers":[
        {
            "category":"Professional",
            "subcategory":"Accounting & Tax Preparation",
            "type":"Services"
        }
    ],
    "sg:phone":"+1 770 493 8146",
    "sg:postcode":"30084",
    "sg:province":"GA",
    "sg:tags":[
        "accountant"
    ],
    "wof:name":"Tate Clinton W CPA",
    "wof:placetype":"venue"
},
  "geometry": {"coordinates":[-84.204201,33.849098],"type":"Point"}
}