{
  "type": "Feature",
  "properties": {
    "iso:country":"US",
    "sg:address":"4403 Washington Rd",
    "sg:city":"Evans",
    "sg:classifiers":[
        {
            "category":"Professional",
            "type":"Services"
        }
    ],
    "sg:phone":"+1 706 863 0894",
    "sg:postcode":"30809",
    "sg:province":"GA",
    "wof:name":"Sentinel Offender Svc",
    "wof:placetype":"venue"
},
  "geometry": {"coordinates":[-82.13700300000001,33.542553],"type":"Point"}
}