{
  "type": "Feature",
  "properties": {
    "iso:country":"US",
    "sg:address":"406 Martin Luther King Jr Blvd",
    "sg:city":"Savannah",
    "sg:classifiers":[
        {
            "category":"Shopping",
            "subcategory":"Clothing, Apparel, & Fashions",
            "type":"Retail Goods"
        }
    ],
    "sg:phone":"+1 912 232 7459",
    "sg:postcode":"31401",
    "sg:province":"GA",
    "sg:tags":[
        "furnishing"
    ],
    "wof:name":"National Tailors",
    "wof:placetype":"venue"
},
  "geometry": {"coordinates":[-81.099676,32.073886],"type":"Point"}
}