{
  "type": "Feature",
  "properties": {
    "iso:country":"US",
    "sg:address":"173 Wells St",
    "sg:city":"Cusseta",
    "sg:classifiers":[
        {
            "category":"Government",
            "subcategory":"Post Office",
            "type":"Public Place"
        }
    ],
    "sg:phone":"+1 800 275 8777",
    "sg:postcode":"31805",
    "sg:province":"GA",
    "sg:website":"http://www.usps.com",
    "wof:name":"USPS - United States Post Office - Cusseta Post Office",
    "wof:placetype":"venue"
},
  "geometry": {"coordinates":[-84.777069,32.306142],"type":"Point"}
}