{
  "type": "Feature",
  "properties": {
    "addr:full":"6905 Virlyn B Smith Rd Fairburn GA 30213",
    "addr:housenumber":"6905",
    "addr:postcode":"30213",
    "addr:street":"Virlyn B Smith Rd",
    "iso:country":"US",
    "sg:address":"6905 Virlyn B Smith Rd",
    "sg:city":"Fairburn",
    "sg:classifiers":[
        {
            "category":"Arts & Performance",
            "subcategory":"Festival",
            "type":"Entertainment"
        }
    ],
    "sg:phone":"+1 770 964 8575",
    "sg:postcode":"30213",
    "sg:province":"GA",
    "sg:website":"georgiarenaissancefestival.com/",
    "wof:name":"Georgia Renaissance Festival",
    "wof:placetype":"venue"
},
  "geometry": {"coordinates":[-84.59989899999999,33.563702],"type":"Point"}
}