{
  "type": "Feature",
  "properties": {
    "addr:full":"2817 White Chapel Dr Columbus GA 31907",
    "addr:housenumber":"2817",
    "addr:postcode":"31907",
    "addr:street":"White Chapel Dr",
    "iso:country":"US",
    "sg:address":"2817 White Chapel Dr",
    "sg:city":"Columbus",
    "sg:classifiers":[
        {
            "category":"Social Services",
            "subcategory":"Child Care",
            "type":"Services"
        }
    ],
    "sg:phone":"+1 706 568 1940",
    "sg:postcode":"31907",
    "sg:province":"GA",
    "sg:tags":[
        "day"
    ],
    "wof:name":"Betty Ryles",
    "wof:placetype":"venue"
},
  "geometry": {"coordinates":[-84.90246399999999,32.489542],"type":"Point"}
}