{
  "type": "Feature",
  "properties": {
    "iso:country":"US",
    "sg:address":"6070 Poplar Spring Dr",
    "sg:city":"Norcross",
    "sg:classifiers":[
        {
            "category":"Shopping",
            "subcategory":"Catalog Store",
            "type":"Retail Goods"
        }
    ],
    "sg:phone":"+1 770 840 8766",
    "sg:postcode":"30092",
    "sg:province":"GA",
    "sg:tags":[
        "mail",
        "order",
        "provides"
    ],
    "wof:name":"Barn Art & Antiques",
    "wof:placetype":"venue"
},
  "geometry": {"coordinates":[-84.251366,33.973777],"type":"Point"}
}