{
  "type": "Feature",
  "properties": {
    "addr:full":"1417 Houston Lake Dr Perry GA 31069",
    "addr:housenumber":"1417",
    "addr:postcode":"31069",
    "addr:street":"Houston Lake Dr",
    "iso:country":"US",
    "sg:address":"1417 Houston Lake Dr",
    "sg:city":"Perry",
    "sg:classifiers":[
        {
            "category":"Home & Garden",
            "subcategory":"Home Furnishings",
            "type":"Retail Goods"
        }
    ],
    "sg:phone":"+1 478 287 7077",
    "sg:postcode":"31069",
    "sg:province":"GA",
    "sg:tags":[
        "set",
        "bed",
        "bedroom"
    ],
    "wof:name":"Bedroom Fantasy Fulfilled",
    "wof:placetype":"venue"
},
  "geometry": {"coordinates":[-83.722998,32.461396],"type":"Point"}
}