{
  "type": "Feature",
  "properties": {
    "addr:full":"1522 E Union St Vienna GA 31092",
    "addr:housenumber":"1522",
    "addr:postcode":"31092",
    "addr:street":"E Union St",
    "iso:country":"US",
    "sg:address":"1522 E Union St",
    "sg:city":"Vienna",
    "sg:classifiers":[
        {
            "category":"Fast Food",
            "type":"Food & Drink"
        },
        {
            "category":"Restaurant",
            "type":"Food & Drink"
        },
        {
            "category":"Food & Beverages",
            "subcategory":"Groceries & Convenience Stores",
            "type":"Retail Goods"
        }
    ],
    "sg:phone":"+1 229 268 4777",
    "sg:postcode":"31092",
    "sg:province":"GA",
    "sg:tags":[
        "shop",
        "american",
        "sandwich",
        "take"
    ],
    "sg:website":"http://www.subway.com",
    "wof:name":"Subway",
    "wof:placetype":"venue"
},
  "geometry": {"coordinates":[-83.765359,32.086647],"type":"Point"}
}