{
  "type": "Feature",
  "properties": {
    "iso:country":"US",
    "sg:address":"1401 Peachtree St",
    "sg:city":"Atlanta",
    "sg:classifiers":[
        {
            "category":"Professional",
            "subcategory":"Lawyer & Legal Services",
            "type":"Services"
        }
    ],
    "sg:phone":"+1 404 870 6711",
    "sg:postcode":"30309",
    "sg:province":"GA",
    "wof:name":"Bryan W Wheeler",
    "wof:placetype":"venue"
},
  "geometry": {"coordinates":[-84.38722300000001,33.794119],"type":"Point"}
}