{
  "type": "Feature",
  "properties": {
    "iso:country":"US",
    "sg:address":"120 S Meadowcliff Cir",
    "sg:city":"Carrollton",
    "sg:classifiers":[
        {
            "category":"Retail",
            "subcategory":"Repair Shop",
            "type":"Services"
        }
    ],
    "sg:phone":"+1 770 836 3222",
    "sg:postcode":"30116",
    "sg:province":"GA",
    "sg:tags":[
        "welding"
    ],
    "wof:name":"T & T Welding",
    "wof:placetype":"venue"
},
  "geometry": {"coordinates":[-85.07159,33.617915],"type":"Point"}
}