{
  "type": "Feature",
  "properties": {
    "iso:country":"US",
    "sg:address":"1750 Powder Springs Rd SW",
    "sg:city":"Marietta",
    "sg:classifiers":[
        {
            "category":"Retail",
            "subcategory":"Repair Shop",
            "type":"Services"
        },
        {
            "category":"Wholesale",
            "subcategory":"Construction Materials",
            "type":"Manufacturing & Wholesale Goods"
        },
        {
            "category":"Home & Garden",
            "subcategory":"Furniture",
            "type":"Retail Goods"
        }
    ],
    "sg:phone":"+1 866 479 9630",
    "sg:postcode":"30064",
    "sg:province":"GA",
    "sg:tags":[
        "upholsterer",
        "supply",
        "refinish",
        "caning",
        "store"
    ],
    "wof:name":"Furniture Medic",
    "wof:placetype":"venue"
},
  "geometry": {"coordinates":[-84.60292699999999,33.906457],"type":"Point"}
}