{
  "type": "Feature",
  "properties": {
    "addr:full":"875 Buford Dr Lawrenceville GA 30043",
    "addr:housenumber":"875",
    "addr:postcode":"30043",
    "addr:street":"Buford Dr",
    "iso:country":"US",
    "sg:address":"875 Buford Dr",
    "sg:city":"Lawrenceville",
    "sg:classifiers":[
        {
            "category":"Autos & Motor Vehicles",
            "subcategory":"Auto Supplies",
            "type":"Retail Goods"
        }
    ],
    "sg:phone":"+1 770 277 2210",
    "sg:postcode":"30043",
    "sg:province":"GA",
    "sg:tags":[
        "tire"
    ],
    "wof:name":"Kauffman Tire",
    "wof:placetype":"venue"
},
  "geometry": {"coordinates":[-83.984703,33.985802],"type":"Point"}
}