{
  "type": "Feature",
  "properties": {
    "iso:country":"US",
    "sg:address":"1425 Blair Bridge Rd",
    "sg:city":"Austell",
    "sg:classifiers":[
        {
            "category":"Social Services",
            "subcategory":"Child Care",
            "type":"Services"
        }
    ],
    "sg:phone":"+1 678 516 4319",
    "sg:postcode":"30168",
    "sg:province":"GA",
    "sg:tags":[
        "day"
    ],
    "wof:name":"D Vyne Care",
    "wof:placetype":"venue"
},
  "geometry": {"coordinates":[-84.598224,33.780555],"type":"Point"}
}