{
  "type": "Feature",
  "properties": {
    "iso:country":"US",
    "sg:address":"1570 Cedar Grove Rd",
    "sg:city":"Conley",
    "sg:classifiers":[
        {
            "category":"Bus Charters",
            "type":"Transportation"
        }
    ],
    "sg:phone":"+1 404 362 9339",
    "sg:postcode":"30288",
    "sg:province":"GA",
    "sg:tags":[
        "rental"
    ],
    "sg:website":"www.kingsmencoachlines.com",
    "wof:name":"Kingsmen Coach Line",
    "wof:placetype":"venue"
},
  "geometry": {"coordinates":[-84.325383,33.657877],"type":"Point"}
}