{
  "type": "Feature",
  "properties": {
    "iso:country":"US",
    "sg:address":"2951 Vineville Ave",
    "sg:city":"Macon",
    "sg:classifiers":[
        {
            "category":"Personal",
            "subcategory":"Beauty Salon",
            "type":"Services"
        }
    ],
    "sg:phone":"+1 478 750 8779",
    "sg:postcode":"31204",
    "sg:province":"GA",
    "sg:tags":[
        "shop"
    ],
    "wof:name":"Hair Mechanics",
    "wof:placetype":"venue"
},
  "geometry": {"coordinates":[-83.670896,32.847936],"type":"Point"}
}