{
  "type": "Feature",
  "properties": {
    "iso:country":"US",
    "sg:address":"325 S Hamilton St",
    "sg:city":"Dalton",
    "sg:classifiers":[
        {
            "category":"Shopping",
            "subcategory":"Luggage & Leather Goods",
            "type":"Retail Goods"
        }
    ],
    "sg:phone":"+1 706 278 8191",
    "sg:postcode":"30720",
    "sg:province":"GA",
    "wof:name":"Whitecotton Leather Co",
    "wof:placetype":"venue"
},
  "geometry": {"coordinates":[-84.967815,34.76956],"type":"Point"}
}