{
  "type": "Feature",
  "properties": {
    "addr:full":"1595 Peachtree Pkwy Cumming GA 30041",
    "addr:housenumber":"1595",
    "addr:postcode":"30041",
    "addr:street":"Peachtree Pkwy",
    "iso:country":"US",
    "sg:address":"1595 Peachtree Pkwy",
    "sg:city":"Cumming",
    "sg:classifiers":[
        {
            "category":"Banks & Credit Unions",
            "subcategory":"Bank",
            "type":"Services"
        }
    ],
    "sg:phone":"+1 678 513 3156",
    "sg:postcode":"30041",
    "sg:province":"GA",
    "wof:name":"Washington Mutual",
    "wof:placetype":"venue"
},
  "geometry": {"coordinates":[-84.171434,34.122346],"type":"Point"}
}