{
  "type": "Feature",
  "properties": {
    "iso:country":"US",
    "sg:address":"6 Decatur St SE",
    "sg:city":"Atlanta",
    "sg:classifiers":[
        {
            "category":"Manufacturing",
            "subcategory":"Printing",
            "type":"Manufacturing & Wholesale Goods"
        }
    ],
    "sg:phone":"+1 404 523 2679",
    "sg:postcode":"30312",
    "sg:province":"GA",
    "sg:tags":[
        "lithographic",
        "commercial"
    ],
    "wof:name":"Printshop The",
    "wof:placetype":"venue"
},
  "geometry": {"coordinates":[-84.388971,33.753952],"type":"Point"}
}