{
  "type": "Feature",
  "properties": {
    "addr:full":"2480 Briarcliff Rd NE Atlanta GA 30329",
    "addr:housenumber":"2480",
    "addr:postcode":"30329",
    "addr:street":"Briarcliff Rd Ne",
    "iso:country":"US",
    "sg:address":"2480 Briarcliff Rd NE",
    "sg:city":"Atlanta",
    "sg:classifiers":[
        {
            "category":"Professional",
            "subcategory":"Employment Agencies",
            "type":"Services"
        }
    ],
    "sg:phone":"+1 404 607 0094",
    "sg:postcode":"30329",
    "sg:province":"GA",
    "wof:name":"Intelligent Network Inc",
    "wof:placetype":"venue"
},
  "geometry": {"coordinates":[-84.33203899999999,33.826812],"type":"Point"}
}