{
  "type": "Feature",
  "properties": {
    "addr:full":"273 State Rte 9 N Dawsonville GA 30534",
    "addr:housenumber":"273",
    "addr:postcode":"30534",
    "addr:street":"State Rte 9 N",
    "iso:country":"US",
    "sg:address":"273 State Rte 9 N",
    "sg:city":"Dawsonville",
    "sg:classifiers":[
        {
            "category":"Manufacturing",
            "subcategory":"Tools & Machinery",
            "type":"Manufacturing & Wholesale Goods"
        }
    ],
    "sg:phone":"+1 706 531 0083",
    "sg:postcode":"30534",
    "sg:province":"GA",
    "sg:tags":[
        "machine",
        "shop"
    ],
    "wof:name":"Davis Machine Inc",
    "wof:placetype":"venue"
},
  "geometry": {"coordinates":[-84.11623899999999,34.42126],"type":"Point"}
}