{
  "type": "Feature",
  "properties": {
    "iso:country":"US",
    "sg:address":"1825 Delowe Dr SW",
    "sg:city":"Atlanta",
    "sg:classifiers":[
        {
            "category":"Retail",
            "subcategory":"Portrait Studio",
            "type":"Services"
        },
        {
            "category":"Professional",
            "subcategory":"Art Services",
            "type":"Services"
        }
    ],
    "sg:phone":"+1 404 752 8908",
    "sg:postcode":"30311",
    "sg:province":"GA",
    "sg:tags":[
        "rental",
        "photographers-portrait",
        "photographic",
        "darkroom"
    ],
    "wof:name":"Jr Gore Enterprises",
    "wof:placetype":"venue"
},
  "geometry": {"coordinates":[-84.457283,33.705745],"type":"Point"}
}