{
  "type": "Feature",
  "properties": {
    "iso:country":"US",
    "sg:address":"1445 Mount Vernon Rd",
    "sg:city":"Atlanta",
    "sg:classifiers":[
        {
            "category":"Organizations",
            "subcategory":"Religious Organization",
            "type":"Services"
        }
    ],
    "sg:phone":"+1 770 280 1200",
    "sg:postcode":"30338",
    "sg:province":"GA",
    "sg:tags":[
        "kindergarten",
        "counseling",
        "center",
        "church"
    ],
    "wof:name":"Dunwoody Baptist Church",
    "wof:placetype":"venue"
},
  "geometry": {"coordinates":[-84.340518,33.942036],"type":"Point"}
}