{
  "type": "Feature",
  "properties": {
    "addr:full":"904 Hancock Dr Americus GA 31709",
    "addr:housenumber":"904",
    "addr:postcode":"31709",
    "addr:street":"Hancock Dr",
    "iso:country":"US",
    "sg:address":"904 Hancock Dr",
    "sg:city":"Americus",
    "sg:classifiers":[
        {
            "category":"Manufacturing",
            "subcategory":"Lumber",
            "type":"Manufacturing & Wholesale Goods"
        }
    ],
    "sg:phone":"+1 229 928 0481",
    "sg:postcode":"31709",
    "sg:province":"GA",
    "sg:tags":[
        "operation",
        "timber",
        "tract"
    ],
    "wof:name":"Arnold Land Co",
    "wof:placetype":"venue"
},
  "geometry": {"coordinates":[-84.23022400000001,32.059893],"type":"Point"}
}