{
  "type": "Feature",
  "properties": {
    "iso:country":"US",
    "sg:address":"2026 Powers Ferry Trce SE",
    "sg:city":"Marietta",
    "sg:classifiers":[
        {
            "category":"Banks & Credit Unions",
            "subcategory":"Investment Brokerage",
            "type":"Services"
        }
    ],
    "sg:phone":"+1 770 612 5900",
    "sg:postcode":"30067",
    "sg:province":"GA",
    "sg:tags":[
        "advisory",
        "financial"
    ],
    "wof:name":"Mid Atlantic Financial",
    "wof:placetype":"venue"
},
  "geometry": {"coordinates":[-84.479473,33.931818],"type":"Point"}
}