{
  "type": "Feature",
  "properties": {
    "iso:country":"US",
    "sg:address":"599 S Houston Lake Rd",
    "sg:city":"Warner Robins",
    "sg:classifiers":[
        {
            "category":"Real Estate",
            "subcategory":"Surveying",
            "type":"Services"
        }
    ],
    "sg:phone":"+1 478 953 1491",
    "sg:postcode":"31088",
    "sg:province":"GA",
    "sg:tags":[
        "surveyor"
    ],
    "wof:name":"Scarborough Land Surveys",
    "wof:placetype":"venue"
},
  "geometry": {"coordinates":[-83.67248499999999,32.600634],"type":"Point"}
}