{
  "type": "Feature",
  "properties": {
    "iso:country":"US",
    "sg:address":"1066 Woodsedge Dr",
    "sg:city":"Augusta",
    "sg:classifiers":[
        {
            "category":"Shopping",
            "subcategory":"Department Store",
            "type":"Retail Goods"
        }
    ],
    "sg:phone":"+1 706 736 1007",
    "sg:postcode":"30904",
    "sg:province":"GA",
    "wof:name":"Marshalls Yard Work and Design",
    "wof:placetype":"venue"
},
  "geometry": {"coordinates":[-82.013131,33.502606],"type":"Point"}
}