{
  "type": "Feature",
  "properties": {
    "iso:country":"US",
    "sg:address":"109 W Valley St",
    "sg:city":"Valdosta",
    "sg:classifiers":[
        {
            "category":"Organizations",
            "subcategory":"Religious Organization",
            "type":"Services"
        }
    ],
    "sg:phone":"+1 229 242 6416",
    "sg:postcode":"31601",
    "sg:province":"GA",
    "sg:tags":[
        "church"
    ],
    "sg:website":"www.methodistvaldosta.org",
    "wof:name":"First United Methodist Church",
    "wof:placetype":"venue"
},
  "geometry": {"coordinates":[-83.27991900000001,30.832614],"type":"Point"}
}