{
  "type": "Feature",
  "properties": {
    "iso:country":"US",
    "sg:address":"228 Majestic Oak Cir",
    "sg:city":"Byron",
    "sg:classifiers":[
        {
            "category":"Building & Trades",
            "subcategory":"Landscaping Services",
            "type":"Services"
        }
    ],
    "sg:phone":"+1 478 956 2751",
    "sg:postcode":"31008",
    "sg:province":"GA",
    "sg:tags":[
        "landscape",
        "contractor"
    ],
    "wof:name":"Dunbar Farms",
    "wof:placetype":"venue"
},
  "geometry": {"coordinates":[-83.752869,32.63834],"type":"Point"}
}