{
  "type": "Feature",
  "properties": {
    "iso:country":"US",
    "sg:address":"218 Wrightsville Ave",
    "sg:city":"East Dublin",
    "sg:classifiers":[
        {
            "category":"Food & Beverages",
            "subcategory":"Specialty",
            "type":"Retail Goods"
        }
    ],
    "sg:phone":"+1 478 296 7455",
    "sg:postcode":"31027",
    "sg:province":"GA",
    "sg:tags":[
        "american",
        "latin",
        "mexican",
        "product"
    ],
    "wof:name":"LA Regiomontana Mexican Store",
    "wof:placetype":"venue"
},
  "geometry": {"coordinates":[-82.865039,32.552334],"type":"Point"}
}