{
  "type": "Feature",
  "properties": {
    "iso:country":"US",
    "sg:address":"4240 Crossland Dr",
    "sg:city":"Cumming",
    "sg:classifiers":[
        {
            "category":"Insurance",
            "subcategory":"Hazard Insurance",
            "type":"Services"
        }
    ],
    "sg:phone":"+1 678 455 6639",
    "sg:postcode":"30040",
    "sg:province":"GA",
    "sg:tags":[
        "commercial",
        "business"
    ],
    "sg:website":"http://www.lucyhayes.org",
    "wof:name":"Lucy Hayes",
    "wof:placetype":"venue"
},
  "geometry": {"coordinates":[-84.199208,34.206868],"type":"Point"}
}