{
  "type": "Feature",
  "properties": {
    "iso:country":"US",
    "sg:address":"1061 Cambridge Sq",
    "sg:city":"Alpharetta",
    "sg:classifiers":[
        {
            "category":"Manufacturing",
            "subcategory":"Paper Products",
            "type":"Manufacturing & Wholesale Goods"
        }
    ],
    "sg:phone":"+1 770 619 3523",
    "sg:postcode":"30004",
    "sg:province":"GA",
    "sg:tags":[
        "bag"
    ],
    "wof:name":"Bulk Lift Intl Inc",
    "wof:placetype":"venue"
},
  "geometry": {"coordinates":[-84.314858,34.068291],"type":"Point"}
}