{
  "type": "Feature",
  "properties": {
    "iso:country":"US",
    "sg:address":"523 Newnan St",
    "sg:city":"Carrollton",
    "sg:classifiers":[
        {
            "category":"Real Estate",
            "subcategory":"Real Estate Agent",
            "type":"Services"
        }
    ],
    "sg:phone":"+1 770 834 0072",
    "sg:postcode":"30117",
    "sg:province":"GA",
    "sg:tags":[
        "appraiser"
    ],
    "wof:name":"Butler Realty Inc",
    "wof:placetype":"venue"
},
  "geometry": {"coordinates":[-85.07010099999999,33.580121],"type":"Point"}
}