{
  "type": "Feature",
  "properties": {
    "addr:full":"600 Peachtree St NE Ste 4100 Atlanta GA 30308",
    "addr:housenumber":"600",
    "addr:postcode":"30308",
    "addr:street":"Peachtree St Ne Ste 4100",
    "iso:country":"US",
    "sg:address":"600 Peachtree St NE Ste 4100",
    "sg:city":"Atlanta",
    "sg:classifiers":[
        {
            "category":"Professional",
            "subcategory":"Lawyer & Legal Services",
            "type":"Services"
        }
    ],
    "sg:phone":"+1 404 888 4000",
    "sg:postcode":"30308",
    "sg:province":"GA",
    "sg:tags":[
        "litigation",
        "attorney",
        "tort"
    ],
    "wof:name":"Campanella, Kelly - Hunton & Williams LLP",
    "wof:placetype":"venue"
},
  "geometry": {"coordinates":[-84.385009,33.770909],"type":"Point"}
}