{
  "type": "Feature",
  "properties": {
    "addr:full":"510 Niagara Cir Alpharetta GA 30022",
    "addr:housenumber":"510",
    "addr:postcode":"30022",
    "addr:street":"Niagara Cir",
    "iso:country":"US",
    "sg:address":"510 Niagara Cir",
    "sg:city":"Alpharetta",
    "sg:classifiers":[
        {
            "category":"Wholesale",
            "subcategory":"Stationery",
            "type":"Manufacturing & Wholesale Goods"
        }
    ],
    "sg:phone":"+1 770 552 8960",
    "sg:postcode":"30022",
    "sg:province":"GA",
    "sg:tags":[
        "supply"
    ],
    "wof:name":"Fitzgibbon & Company",
    "wof:placetype":"venue"
},
  "geometry": {"coordinates":[-84.267927,33.995098],"type":"Point"}
}