{
  "type": "Feature",
  "properties": {
    "iso:country":"US",
    "sg:address":"1810 US Hwy 41 N",
    "sg:city":"Tifton",
    "sg:classifiers":[
        {
            "category":"Banks & Credit Unions",
            "subcategory":"Investment Brokerage",
            "type":"Services"
        },
        {
            "category":"Banks & Credit Unions",
            "subcategory":"Bank",
            "type":"Services"
        }
    ],
    "sg:phone":"+1 229 386 9797",
    "sg:postcode":"31794",
    "sg:province":"GA",
    "sg:tags":[
        "loan",
        "security",
        "real estate"
    ],
    "wof:name":"Merit Mortgage Services Inc",
    "wof:placetype":"venue"
},
  "geometry": {"coordinates":[-83.518913,31.471341],"type":"Point"}
}