{
  "type": "Feature",
  "properties": {
    "iso:country":"US",
    "sg:address":"10 Hummingbird Pl",
    "sg:city":"Rome",
    "sg:classifiers":[
        {
            "category":"Professional",
            "subcategory":"Employment Agencies",
            "type":"Services"
        }
    ],
    "sg:phone":"+1 706 378 7523",
    "sg:postcode":"30165",
    "sg:province":"GA",
    "sg:tags":[
        "medical"
    ],
    "wof:name":"Southeast Medial PC",
    "wof:placetype":"venue"
},
  "geometry": {"coordinates":[-85.17751699999999,34.346644],"type":"Point"}
}