{
  "type": "Feature",
  "properties": {
    "addr:full":"2400 Kinmor Ind Pkwy NW Conyers GA 30012",
    "addr:housenumber":"2400",
    "addr:postcode":"30012",
    "addr:street":"Kinmor Ind Pkwy Nw",
    "iso:country":"US",
    "sg:address":"2400 Kinmor Ind Pkwy NW",
    "sg:city":"Conyers",
    "sg:classifiers":[
        {
            "category":"Manufacturing",
            "subcategory":"Wood Products",
            "type":"Manufacturing & Wholesale Goods"
        }
    ],
    "sg:phone":"+1 770 929 3881",
    "sg:postcode":"30012",
    "sg:province":"GA",
    "sg:tags":[
        "household",
        "mfg"
    ],
    "wof:name":"Blackburn Designs Inc",
    "wof:placetype":"venue"
},
  "geometry": {"coordinates":[-84.065202,33.693195],"type":"Point"}
}