{
  "type": "Feature",
  "properties": {
    "iso:country":"US",
    "sg:address":"1195 Victory Dr SW",
    "sg:city":"Atlanta",
    "sg:classifiers":[
        {
            "category":"Manufacturing",
            "subcategory":"Motor Vehicles & Parts",
            "type":"Manufacturing & Wholesale Goods"
        }
    ],
    "sg:phone":"+1 404 755 2557",
    "sg:postcode":"30310",
    "sg:province":"GA",
    "sg:tags":[
        "car",
        "railroad"
    ],
    "wof:name":"Davidson Kennedy Co",
    "wof:placetype":"venue"
},
  "geometry": {"coordinates":[-84.427475,33.706757],"type":"Point"}
}