{
  "type": "Feature",
  "properties": {
    "addr:full":"3411 Pierce Dr NE Atlanta GA 30341",
    "addr:housenumber":"3411",
    "addr:postcode":"30341",
    "addr:street":"Pierce Dr Ne",
    "iso:country":"US",
    "sg:address":"3411 Pierce Dr NE",
    "sg:city":"Atlanta",
    "sg:classifiers":[
        {
            "category":"Wholesale",
            "subcategory":"Chemicals & Plastics",
            "type":"Manufacturing & Wholesale Goods"
        }
    ],
    "sg:phone":"+1 770 455 9999",
    "sg:postcode":"30341",
    "sg:province":"GA",
    "sg:tags":[
        "resistant",
        "product",
        "allergy"
    ],
    "sg:website":"http://www.AchooAllergy.com",
    "wof:name":"AchooAllergy.com",
    "wof:placetype":"venue"
},
  "geometry": {"coordinates":[-84.302834,33.890801],"type":"Point"}
}