{
  "type": "Feature",
  "properties": {
    "addr:full":"213 Bradley St Carrollton GA 30117",
    "addr:housenumber":"213",
    "addr:postcode":"30117",
    "addr:street":"Bradley St",
    "iso:country":"US",
    "sg:address":"213 Bradley St",
    "sg:city":"Carrollton",
    "sg:classifiers":[
        {
            "category":"Manufacturing",
            "subcategory":"Glass & Minerals",
            "type":"Manufacturing & Wholesale Goods"
        },
        {
            "category":"Professional",
            "subcategory":"Printing & Photocopies",
            "type":"Services"
        },
        {
            "category":"Professional",
            "subcategory":"Credit Reporting & Collection",
            "type":"Services"
        }
    ],
    "sg:phone":"+1 770 834 0077",
    "sg:postcode":"30117",
    "sg:province":"GA",
    "sg:tags":[
        "engraving",
        "trophies",
        "products-metal",
        "award",
        "medal",
        "plaque",
        "etched"
    ],
    "wof:name":"McEver's Awards, Trophies & Gifts",
    "wof:placetype":"venue"
},
  "geometry": {"coordinates":[-85.075219,33.579072],"type":"Point"}
}