{
  "type": "Feature",
  "properties": {
    "addr:full":"3265 Lanier Beach South Rd Cumming GA 30041",
    "addr:housenumber":"3265",
    "addr:postcode":"30041",
    "addr:street":"Lanier Beach South Rd",
    "iso:country":"US",
    "sg:address":"3265 Lanier Beach South Rd",
    "sg:city":"Cumming",
    "sg:classifiers":[
        {
            "category":"Professional",
            "subcategory":"Lawyer & Legal Services",
            "type":"Services"
        }
    ],
    "sg:phone":"+1 770 781 4700",
    "sg:postcode":"30041",
    "sg:province":"GA",
    "sg:tags":[
        "attorney"
    ],
    "wof:name":"Donald W Wagner & Assoc",
    "wof:placetype":"venue"
},
  "geometry": {"coordinates":[-84.08847900000001,34.190748],"type":"Point"}
}