{
  "type": "Feature",
  "properties": {
    "iso:country":"US",
    "sg:address":"74 Labelle Rd",
    "sg:city":"Villa Rica",
    "sg:classifiers":[
        {
            "category":"Arts & Performance",
            "subcategory":"Theater",
            "type":"Entertainment"
        }
    ],
    "sg:phone":"+1 770 459 0465",
    "sg:postcode":"30180",
    "sg:province":"GA",
    "sg:tags":[
        "group"
    ],
    "wof:name":"Clown Barn",
    "wof:placetype":"venue"
},
  "geometry": {"coordinates":[-84.966967,33.770114],"type":"Point"}
}