{
  "type": "Feature",
  "properties": {
    "iso:country":"US",
    "sg:address":"2010 Cypress St",
    "sg:city":"Valdosta",
    "sg:classifiers":[
        {
            "category":"Social Services",
            "type":"Services"
        }
    ],
    "sg:phone":"+1 229 245 1330",
    "sg:postcode":"31601",
    "sg:province":"GA",
    "sg:tags":[
        "organization",
        "welfare"
    ],
    "wof:name":"Habatit For Humanity Inc",
    "wof:placetype":"venue"
},
  "geometry": {"coordinates":[-83.254064,30.843822],"type":"Point"}
}