{
  "type": "Feature",
  "properties": {
    "addr:full":"84 Max Wehunt Rd Dahlonega GA 30533",
    "addr:housenumber":"84",
    "addr:postcode":"30533",
    "addr:street":"Max Wehunt Rd",
    "iso:country":"US",
    "sg:address":"84 Max Wehunt Rd",
    "sg:city":"Dahlonega",
    "sg:classifiers":[
        {
            "category":"Autos & Motor Vehicles",
            "subcategory":"Automobile Sales",
            "type":"Retail Goods"
        }
    ],
    "sg:phone":"+1 706 864 3065",
    "sg:postcode":"30533",
    "sg:province":"GA",
    "sg:tags":[
        "car",
        "used"
    ],
    "wof:name":"T Kendall Clent",
    "wof:placetype":"venue"
},
  "geometry": {"coordinates":[-84.176621,34.527572],"type":"Point"}
}