{
  "type": "Feature",
  "properties": {
    "addr:full":"1007 Memorial Dr Griffin GA 30223",
    "addr:housenumber":"1007",
    "addr:postcode":"30223",
    "addr:street":"Memorial Dr",
    "iso:country":"US",
    "sg:address":"1007 Memorial Dr",
    "sg:city":"Griffin",
    "sg:classifiers":[
        {
            "category":"Government",
            "subcategory":"Office",
            "type":"Public Place"
        }
    ],
    "sg:phone":"+1 770 467 4230",
    "sg:postcode":"30223",
    "sg:province":"GA",
    "sg:tags":[
        "county",
        "program"
    ],
    "wof:name":"Spalding County Environmental",
    "wof:placetype":"venue"
},
  "geometry": {"coordinates":[-84.25379,33.246108],"type":"Point"}
}