{
  "type": "Feature",
  "properties": {
    "addr:full":"626 Poplar St Macon GA 31201",
    "addr:housenumber":"626",
    "addr:postcode":"31201",
    "addr:street":"Poplar St",
    "iso:country":"US",
    "sg:address":"626 Poplar St",
    "sg:city":"Macon",
    "sg:classifiers":[
        {
            "category":"Shopping",
            "subcategory":"Clothing, Apparel, & Fashions",
            "type":"Retail Goods"
        }
    ],
    "sg:phone":"+1 478 741 2121",
    "sg:postcode":"31201",
    "sg:province":"GA",
    "sg:tags":[
        "woman",
        "hat",
        "jewelry",
        "outerwear"
    ],
    "wof:name":"Its Hats & Things",
    "wof:placetype":"venue"
},
  "geometry": {"coordinates":[-83.63067599999999,32.835302],"type":"Point"}
}