{
  "type": "Feature",
  "properties": {
    "iso:country":"US",
    "sg:address":"1403 Bailey Ct SW",
    "sg:city":"Conyers",
    "sg:classifiers":[
        {
            "category":"Shopping",
            "subcategory":"Used Merchandise",
            "type":"Retail Goods"
        }
    ],
    "sg:phone":"+1 770 388 0512",
    "sg:postcode":"30094",
    "sg:province":"GA",
    "wof:name":"Just One More",
    "wof:placetype":"venue"
},
  "geometry": {"coordinates":[-84.037954,33.557935],"type":"Point"}
}