{
  "type": "Feature",
  "properties": {
    "addr:full":"357 Millis Stone Rd Fairmount GA 30139",
    "addr:housenumber":"357",
    "addr:postcode":"30139",
    "addr:street":"Millis Stone Rd",
    "iso:country":"US",
    "sg:address":"357 Millis Stone Rd",
    "sg:city":"Fairmount",
    "sg:classifiers":[
        {
            "category":"Building & Trades",
            "subcategory":"Construction",
            "type":"Services"
        }
    ],
    "sg:phone":"+1 706 337 4426",
    "sg:postcode":"30139",
    "sg:province":"GA",
    "sg:tags":[
        "heavy"
    ],
    "wof:name":"Hughes Grading",
    "wof:placetype":"venue"
},
  "geometry": {"coordinates":[-84.57058600000001,34.422953],"type":"Point"}
}