{
  "type": "Feature",
  "properties": {
    "addr:full":"1401 Old Forge Ln Woodstock GA 30189",
    "addr:housenumber":"1401",
    "addr:postcode":"30189",
    "addr:street":"Old Forge Ln",
    "iso:country":"US",
    "sg:address":"1401 Old Forge Ln",
    "sg:city":"Woodstock",
    "sg:classifiers":[
        {
            "category":"Organizations",
            "subcategory":"Professional Association",
            "type":"Services"
        }
    ],
    "sg:phone":"+1 770 924 3559",
    "sg:postcode":"30189",
    "sg:province":"GA",
    "wof:name":"Eagle Watch Home Owners Assn",
    "wof:placetype":"venue"
},
  "geometry": {"coordinates":[-84.570201,34.140612],"type":"Point"}
}