{
  "type": "Feature",
  "properties": {
    "iso:country":"US",
    "sg:address":"2418 US Hwy 441",
    "sg:city":"Dublin",
    "sg:classifiers":[
        {
            "category":"Organizations",
            "subcategory":"Religious Organization",
            "type":"Services"
        }
    ],
    "sg:phone":"+1 478 275 8400",
    "sg:postcode":"31021",
    "sg:province":"GA",
    "sg:tags":[
        "church"
    ],
    "wof:name":"Sanctuary Of Dublin",
    "wof:placetype":"venue"
},
  "geometry": {"coordinates":[-83.000935,32.624737],"type":"Point"}
}