{
  "type": "Feature",
  "properties": {
    "iso:country":"US",
    "sg:address":"2500 Northwinds Pkwy Ste 330",
    "sg:city":"Alpharetta",
    "sg:classifiers":[
        {
            "category":"Professional",
            "subcategory":"Lawyer & Legal Services",
            "type":"Services"
        }
    ],
    "sg:phone":"+1 770 408 6364",
    "sg:postcode":"30009",
    "sg:province":"GA",
    "sg:website":"www.cwstevenslaw.com",
    "wof:name":"The Law Office of Casey W Stevens",
    "wof:placetype":"venue"
},
  "geometry": {"coordinates":[-84.286562,34.05929],"type":"Point"}
}