{
  "type": "Feature",
  "properties": {
    "addr:full":"17029 Abercorn St Savannah GA 31419",
    "addr:housenumber":"17029",
    "addr:postcode":"31419",
    "addr:street":"Abercorn St",
    "iso:country":"US",
    "sg:address":"17029 Abercorn St",
    "sg:city":"Savannah",
    "sg:classifiers":[
        {
            "category":"Restaurant",
            "type":"Food & Drink"
        }
    ],
    "sg:menulink":"http://www.allmenus.com/ga/pooler-burroughs/90673-houlihans/menu/",
    "sg:phone":"+1 912 921 5712",
    "sg:postcode":"31419",
    "sg:province":"GA",
    "sg:tags":[
        "new",
        "american"
    ],
    "wof:name":"Houlihan's",
    "wof:placetype":"venue"
},
  "geometry": {"coordinates":[-81.278325,32.003962],"type":"Point"}
}