{
  "type": "Feature",
  "properties": {
    "addr:full":"4945 Price Rd Gainesville GA 30506",
    "addr:housenumber":"4945",
    "addr:postcode":"30506",
    "addr:street":"Price Rd",
    "iso:country":"US",
    "sg:address":"4945 Price Rd",
    "sg:city":"Gainesville",
    "sg:classifiers":[
        {
            "category":"Retail",
            "subcategory":"Repair Shop",
            "type":"Services"
        }
    ],
    "sg:phone":"+1 770 532 1424",
    "sg:postcode":"30506",
    "sg:province":"GA",
    "wof:name":"Gils Quality Upholstery",
    "wof:placetype":"venue"
},
  "geometry": {"coordinates":[-83.93413099999999,34.402857],"type":"Point"}
}