{
  "type": "Feature",
  "properties": {
    "iso:country":"US",
    "sg:address":"580 E Crossville Rd",
    "sg:city":"Roswell",
    "sg:classifiers":[
        {
            "category":"Professional",
            "subcategory":"Business Services",
            "type":"Services"
        }
    ],
    "sg:phone":"+1 770 518 6763",
    "sg:postcode":"30075",
    "sg:province":"GA",
    "sg:tags":[
        "packaging"
    ],
    "wof:name":"Mail & More",
    "wof:placetype":"venue"
},
  "geometry": {"coordinates":[-84.346237,34.03815],"type":"Point"}
}