{
  "type": "Feature",
  "properties": {
    "addr:full":"100 Glenridge Point Pkwy N E Atlanta GA 30342",
    "addr:housenumber":"100",
    "addr:postcode":"30342",
    "addr:street":"Glenridge Point Pkwy N E",
    "iso:country":"US",
    "sg:address":"100 Glenridge Point Pkwy N E",
    "sg:city":"Atlanta",
    "sg:classifiers":[
        {
            "category":"Insurance",
            "subcategory":"Insurance Agent",
            "type":"Services"
        }
    ],
    "sg:phone":"+1 770 396 6888",
    "sg:postcode":"30342",
    "sg:province":"GA",
    "sg:tags":[
        "adjuster"
    ],
    "wof:name":"Crawford & Company",
    "wof:placetype":"venue"
},
  "geometry": {"coordinates":[-84.359674,33.906805],"type":"Point"}
}