{
  "type": "Feature",
  "properties": {
    "iso:country":"US",
    "sg:address":"4540 Memorial Dr",
    "sg:city":"Decatur",
    "sg:classifiers":[
        {
            "category":"Professional",
            "subcategory":"Management & Consulting",
            "type":"Services"
        }
    ],
    "sg:phone":"+1 404 298 5664",
    "sg:postcode":"30032",
    "sg:province":"GA",
    "wof:name":"Wizdum Management",
    "wof:placetype":"venue"
},
  "geometry": {"coordinates":[-84.240148,33.778741],"type":"Point"}
}