{
  "type": "Feature",
  "properties": {
    "iso:country":"US",
    "sg:address":"400 Ellis Rd",
    "sg:city":"Elko",
    "sg:phone":"+1 478 987 3829",
    "sg:postcode":"31025",
    "sg:province":"GA",
    "sg:tags":[
        "farm",
        "field",
        "crop"
    ],
    "wof:name":"Edward Allen",
    "wof:placetype":"venue"
},
  "geometry": {"coordinates":[-83.662374,32.345509],"type":"Point"}
}