{
  "type": "Feature",
  "properties": {
    "iso:country":"US",
    "sg:address":"118 E Main St",
    "sg:city":"Fort Valley",
    "sg:classifiers":[
        {
            "category":"Restaurant",
            "type":"Food & Drink"
        }
    ],
    "sg:phone":"+1 478 827 0234",
    "sg:postcode":"31030",
    "sg:province":"GA",
    "wof:name":"Sharpe's Kuntry Kitchen",
    "wof:placetype":"venue"
},
  "geometry": {"coordinates":[-83.886377,32.553384],"type":"Point"}
}