{
  "type": "Feature",
  "properties": {
    "addr:full":"16305 Henderson Rd Alpharetta GA 30004",
    "addr:housenumber":"16305",
    "addr:postcode":"30004",
    "addr:street":"Henderson Rd",
    "iso:country":"US",
    "sg:address":"16305 Henderson Rd",
    "sg:city":"Alpharetta",
    "sg:classifiers":[
        {
            "category":"Professional",
            "subcategory":"Management & Consulting",
            "type":"Services"
        }
    ],
    "sg:phone":"+1 770 754 5570",
    "sg:postcode":"30004",
    "sg:province":"GA",
    "sg:tags":[
        "coaching"
    ],
    "wof:name":"Pathfinder Coaching Services",
    "wof:placetype":"venue"
},
  "geometry": {"coordinates":[-84.302747,34.177888],"type":"Point"}
}