{
  "type": "Feature",
  "properties": {
    "addr:full":"2465 Warren Rd NW Atlanta GA 30318",
    "addr:housenumber":"2465",
    "addr:postcode":"30318",
    "addr:street":"Warren Rd Nw",
    "iso:country":"US",
    "sg:address":"2465 Warren Rd NW",
    "sg:city":"Atlanta",
    "sg:classifiers":[
        {
            "category":"Organizations",
            "subcategory":"Community Association",
            "type":"Services"
        }
    ],
    "sg:phone":"+1 404 355 9122",
    "sg:postcode":"30318",
    "sg:province":"GA",
    "sg:tags":[
        "military"
    ],
    "wof:name":"American Legion",
    "wof:placetype":"venue"
},
  "geometry": {"coordinates":[-84.445672,33.822416],"type":"Point"}
}