{
  "type": "Feature",
  "properties": {
    "addr:full":"3509 Baker Rd NW Ste 405 Acworth GA 30101",
    "addr:housenumber":"3509",
    "addr:postcode":"30101",
    "addr:street":"Baker Rd Nw Ste 405",
    "iso:country":"US",
    "sg:address":"3509 Baker Rd NW Ste 405",
    "sg:city":"Acworth",
    "sg:classifiers":[
        {
            "category":"Restaurant",
            "type":"Food & Drink"
        }
    ],
    "sg:phone":"+1 770 966 0290",
    "sg:postcode":"30101",
    "sg:province":"GA",
    "sg:tags":[
        "mexican"
    ],
    "wof:name":"Ricardo's Mexican Restaurant",
    "wof:placetype":"venue"
},
  "geometry": {"coordinates":[-84.651802,34.075901],"type":"Point"}
}