{
  "type": "Feature",
  "properties": {
    "iso:country":"US",
    "sg:address":"12 Medical Dr NE",
    "sg:city":"Cartersville",
    "sg:classifiers":[
        {
            "category":"Health Services",
            "subcategory":"Doctor",
            "type":"Services"
        }
    ],
    "sg:phone":"+1 770 386 1000",
    "sg:postcode":"30121",
    "sg:province":"GA",
    "sg:tags":[
        "physician",
        "family",
        "practice",
        "surgeons",
        "medicine"
    ],
    "wof:name":"Pippen, Lisa PA-C MD",
    "wof:placetype":"venue"
},
  "geometry": {"coordinates":[-84.795484,34.202039],"type":"Point"}
}