{
  "type": "Feature",
  "properties": {
    "iso:country":"US",
    "sg:address":"2392 Mount Vernon Road Suite 102",
    "sg:city":"Atlanta",
    "sg:classifiers":[
        {
            "category":"Professional",
            "subcategory":"Computer Services",
            "type":"Services"
        }
    ],
    "sg:phone":"+1 678 441 0020",
    "sg:postcode":"30338",
    "sg:province":"GA",
    "sg:tags":[
        "repair"
    ],
    "wof:name":"Service Strategies",
    "wof:placetype":"venue"
},
  "geometry": {"coordinates":[-84.30350799999999,33.95662],"type":"Point"}
}