{
  "type": "Feature",
  "properties": {
    "addr:full":"1590 Athens Hwy Gainesville GA 30507",
    "addr:housenumber":"1590",
    "addr:postcode":"30507",
    "addr:street":"Athens Hwy",
    "iso:country":"US",
    "sg:address":"1590 Athens Hwy",
    "sg:city":"Gainesville",
    "sg:classifiers":[
        {
            "category":"Wholesale",
            "subcategory":"Machinery & Supplies",
            "type":"Manufacturing & Wholesale Goods"
        }
    ],
    "sg:phone":"+1 770 536 3364",
    "sg:postcode":"30507",
    "sg:province":"GA",
    "sg:tags":[
        "equipment",
        "welding"
    ],
    "wof:name":"A L Welding Supply Inc",
    "wof:placetype":"venue"
},
  "geometry": {"coordinates":[-83.800563,34.283516],"type":"Point"}
}