{
  "type": "Feature",
  "properties": {
    "iso:country":"US",
    "sg:address":"2624 High St SW",
    "sg:city":"Conyers",
    "sg:classifiers":[
        {
            "category":"Utilities",
            "subcategory":"Telephone",
            "type":"Services"
        }
    ],
    "sg:phone":"+1 770 922 8421",
    "sg:postcode":"30094",
    "sg:province":"GA",
    "sg:tags":[
        "company"
    ],
    "wof:name":"A T & T Cits",
    "wof:placetype":"venue"
},
  "geometry": {"coordinates":[-84.060097,33.62802],"type":"Point"}
}