{
  "type": "Feature",
  "properties": {
    "iso:country":"US",
    "sg:address":"6275 Klondike River Rd",
    "sg:city":"Lithonia",
    "sg:classifiers":[
        {
            "category":"Social Services",
            "subcategory":"Job Training",
            "type":"Services"
        },
        {
            "category":"Animal Shelter",
            "type":"Public Place"
        }
    ],
    "sg:phone":"+1 678 620 2416",
    "sg:postcode":"30038",
    "sg:province":"GA",
    "sg:tags":[
        "employment"
    ],
    "wof:name":"Hills Of Life Inc",
    "wof:placetype":"venue"
},
  "geometry": {"coordinates":[-84.134426,33.637691],"type":"Point"}
}