{
  "type": "Feature",
  "properties": {
    "iso:country":"US",
    "sg:address":"775 Glenairy Dr NE",
    "sg:city":"Atlanta",
    "sg:classifiers":[
        {
            "category":"Professional",
            "subcategory":"Business Services",
            "type":"Services"
        }
    ],
    "sg:phone":"+1 404 252 5460",
    "sg:postcode":"30328",
    "sg:province":"GA",
    "sg:tags":[
        "appraiser"
    ],
    "wof:name":"Triserv",
    "wof:placetype":"venue"
},
  "geometry": {"coordinates":[-84.36278,33.923657],"type":"Point"}
}