{
  "type": "Feature",
  "properties": {
    "addr:full":"2355 Surrey Trl Atlanta GA 30349",
    "addr:housenumber":"2355",
    "addr:postcode":"30349",
    "addr:street":"Surrey Trl",
    "iso:country":"US",
    "sg:address":"2355 Surrey Trl",
    "sg:city":"Atlanta",
    "sg:classifiers":[
        {
            "category":"Social Services",
            "subcategory":"Child Care",
            "type":"Services"
        }
    ],
    "sg:phone":"+1 404 669 8283",
    "sg:postcode":"30349",
    "sg:province":"GA",
    "sg:tags":[
        "nursery",
        "day"
    ],
    "wof:name":"Nothing But Love",
    "wof:placetype":"venue"
},
  "geometry": {"coordinates":[-84.46744200000001,33.605316],"type":"Point"}
}