{
  "type": "Feature",
  "properties": {
    "addr:full":"507 Anthony Dr Sandersville GA 31082",
    "addr:housenumber":"507",
    "addr:postcode":"31082",
    "addr:street":"Anthony Dr",
    "iso:country":"US",
    "sg:address":"507 Anthony Dr",
    "sg:city":"Sandersville",
    "sg:classifiers":[
        {
            "category":"Organizations",
            "subcategory":"Religious Organization",
            "type":"Services"
        }
    ],
    "sg:phone":"+1 478 552 6200",
    "sg:postcode":"31082",
    "sg:province":"GA",
    "wof:name":"Bethlehem Baptist Church",
    "wof:placetype":"venue"
},
  "geometry": {"coordinates":[-82.794264,32.989651],"type":"Point"}
}