{
  "type": "Feature",
  "properties": {
    "iso:country":"US",
    "sg:address":"4803 Impala Ln",
    "sg:city":"Albany",
    "sg:classifiers":[
        {
            "category":"Building & Trades",
            "subcategory":"Cleaning & Sanitation",
            "type":"Services"
        }
    ],
    "sg:phone":"+1 229 344 3071",
    "sg:postcode":"31705",
    "sg:province":"GA",
    "sg:tags":[
        "maintenance"
    ],
    "wof:name":"New Ventures Cleaning Service",
    "wof:placetype":"venue"
},
  "geometry": {"coordinates":[-84.10438000000001,31.459662],"type":"Point"}
}