{
  "type": "Feature",
  "properties": {
    "addr:full":"3131 Maley Ct Marietta GA 30066",
    "addr:housenumber":"3131",
    "addr:postcode":"30066",
    "addr:street":"Maley Ct",
    "iso:country":"US",
    "sg:address":"3131 Maley Ct",
    "sg:city":"Marietta",
    "sg:classifiers":[
        {
            "category":"Professional",
            "type":"Services"
        }
    ],
    "sg:phone":"+1 770 579 1115",
    "sg:postcode":"30066",
    "sg:province":"GA",
    "wof:name":"Technical Lori Writing Boatman",
    "wof:placetype":"venue"
},
  "geometry": {"coordinates":[-84.459307,34.046738],"type":"Point"}
}