{
  "type": "Feature",
  "properties": {
    "iso:country":"US",
    "sg:address":"4444 New Jesup Hwy",
    "sg:city":"Brunswick",
    "sg:classifiers":[
        {
            "category":"Retail",
            "subcategory":"Auto Repair",
            "type":"Services"
        }
    ],
    "sg:phone":"+1 912 262 9022",
    "sg:postcode":"31520",
    "sg:province":"GA",
    "sg:tags":[
        "body",
        "painting",
        "repairing",
        "automobile"
    ],
    "wof:name":"Thomas, J M Transport",
    "wof:placetype":"venue"
},
  "geometry": {"coordinates":[-81.509405,31.206132],"type":"Point"}
}