{
  "type": "Feature",
  "properties": {
    "iso:country":"US",
    "sg:address":"484-C Moreland Ave NE",
    "sg:city":"Atlanta",
    "sg:classifiers":[
        {
            "category":"Shopping",
            "subcategory":"Books",
            "type":"Retail Goods"
        }
    ],
    "sg:phone":"+1 404 681 5128",
    "sg:postcode":"30307",
    "sg:province":"GA",
    "sg:tags":[
        "bookstore"
    ],
    "sg:website":"www.acappellabooks.com/",
    "wof:name":"A Cappella Books",
    "wof:placetype":"venue"
},
  "geometry": {"coordinates":[-84.349018,33.76746],"type":"Point"}
}