{
  "type": "Feature",
  "properties": {
    "iso:country":"US",
    "sg:address":"193 Pinehill Estates Rd",
    "sg:city":"Guyton",
    "sg:classifiers":[
        {
            "category":"Building & Trades",
            "subcategory":"Pest Control",
            "type":"Services"
        }
    ],
    "sg:phone":"+1 912 754 7166",
    "sg:postcode":"31312",
    "sg:province":"GA",
    "wof:name":"Orion Pest Control",
    "wof:placetype":"venue"
},
  "geometry": {"coordinates":[-81.326213,32.317704],"type":"Point"}
}