{
  "type": "Feature",
  "properties": {
    "addr:full":"1710 Teamon Rd Griffin GA 30223",
    "addr:housenumber":"1710",
    "addr:postcode":"30223",
    "addr:street":"Teamon Rd",
    "iso:country":"US",
    "sg:address":"1710 Teamon Rd",
    "sg:city":"Griffin",
    "sg:classifiers":[
        {
            "category":"Retail",
            "subcategory":"Repair Shop",
            "type":"Services"
        }
    ],
    "sg:phone":"+1 770 228 4150",
    "sg:postcode":"30223",
    "sg:province":"GA",
    "sg:tags":[
        "welding"
    ],
    "wof:name":"Tubalcain Welding",
    "wof:placetype":"venue"
},
  "geometry": {"coordinates":[-84.240073,33.329606],"type":"Point"}
}