{
  "type": "Feature",
  "properties": {
    "iso:country":"US",
    "sg:address":"3436 Dogwood Dr",
    "sg:city":"Atlanta",
    "sg:classifiers":[
        {
            "category":"Personal",
            "subcategory":"Shoe Repair & Shine",
            "type":"Services"
        }
    ],
    "sg:phone":"+1 404 767 3115",
    "sg:postcode":"30354",
    "sg:province":"GA",
    "wof:name":"Hapeville Shoe Repair",
    "wof:placetype":"venue"
},
  "geometry": {"coordinates":[-84.4105,33.660198],"type":"Point"}
}