{
  "type": "Feature",
  "properties": {
    "iso:country":"US",
    "sg:address":"1001 Alpharetta St",
    "sg:city":"Roswell",
    "sg:classifiers":[
        {
            "category":"Real Estate",
            "subcategory":"Architect",
            "type":"Services"
        }
    ],
    "sg:phone":"+1 770 998 1139",
    "sg:postcode":"30075",
    "sg:province":"GA",
    "wof:name":"Team Architects and Contractors Llc",
    "wof:placetype":"venue"
},
  "geometry": {"coordinates":[-84.36039700000001,34.025398],"type":"Point"}
}