{
  "type": "Feature",
  "properties": {
    "addr:full":"4333 Bemiss Rd Valdosta GA 31605",
    "addr:housenumber":"4333",
    "addr:postcode":"31605",
    "addr:street":"Bemiss Rd",
    "iso:country":"US",
    "sg:address":"4333 Bemiss Rd",
    "sg:city":"Valdosta",
    "sg:classifiers":[
        {
            "category":"Home & Garden",
            "subcategory":"Hardware",
            "type":"Retail Goods"
        }
    ],
    "sg:phone":"+1 229 293 0606",
    "sg:postcode":"31605",
    "sg:province":"GA",
    "wof:name":"Bemiss Trustworthy Hardware",
    "wof:placetype":"venue"
},
  "geometry": {"coordinates":[-83.25221999999999,30.921487],"type":"Point"}
}