{
  "type": "Feature",
  "properties": {
    "iso:country":"US",
    "sg:address":"718 Juliette Rd",
    "sg:city":"Hillsboro",
    "sg:classifiers":[
        {
            "category":"Government",
            "subcategory":"Office",
            "type":"Public Place"
        }
    ],
    "sg:phone":"+1 478 986 5441",
    "sg:postcode":"31029",
    "sg:province":"GA",
    "wof:name":"Piedmont National Wildlife",
    "wof:placetype":"venue"
},
  "geometry": {"coordinates":[-83.919798,33.037731],"type":"Point"}
}