{
  "type": "Feature",
  "properties": {
    "addr:full":"4416 Springfield Dr Norcross GA 30092",
    "addr:housenumber":"4416",
    "addr:postcode":"30092",
    "addr:street":"Springfield Dr",
    "iso:country":"US",
    "sg:address":"4416 Springfield Dr",
    "sg:city":"Norcross",
    "sg:classifiers":[
        {
            "category":"Building & Trades",
            "subcategory":"Landscaping Services",
            "type":"Services"
        }
    ],
    "sg:phone":"+1 770 417 1569",
    "sg:postcode":"30092",
    "sg:province":"GA",
    "sg:tags":[
        "landscape",
        "contractor"
    ],
    "wof:name":"Boger Landscape Management Inc",
    "wof:placetype":"venue"
},
  "geometry": {"coordinates":[-84.23497399999999,33.9919],"type":"Point"}
}