{
  "type": "Feature",
  "properties": {
    "iso:country":"US",
    "sg:address":"3024 Miller Rd",
    "sg:city":"Lithonia",
    "sg:classifiers":[
        {
            "category":"Professional",
            "subcategory":"Computer Services",
            "type":"Services"
        }
    ],
    "sg:phone":"+1 770 987 8881",
    "sg:postcode":"30038",
    "sg:province":"GA",
    "sg:tags":[
        "repair"
    ],
    "sg:website":"www.hpcomputers.com",
    "wof:name":"High-Point Computer Svc",
    "wof:placetype":"venue"
},
  "geometry": {"coordinates":[-84.184505,33.700935],"type":"Point"}
}