{
  "type": "Feature",
  "properties": {
    "iso:country":"US",
    "sg:address":"3145 Tucker Norcross Rd",
    "sg:city":"Tucker",
    "sg:classifiers":[
        {
            "category":"Insurance",
            "subcategory":"Insurance Agent",
            "type":"Services"
        }
    ],
    "sg:phone":"+1 770 491 3999",
    "sg:postcode":"30084",
    "sg:province":"GA",
    "wof:name":"State Farm Insurance",
    "wof:placetype":"venue"
},
  "geometry": {"coordinates":[-84.219317,33.881544],"type":"Point"}
}