{
  "type": "Feature",
  "properties": {
    "iso:country":"US",
    "sg:address":"122 Redfern Dr",
    "sg:city":"Saint Simons Island",
    "sg:classifiers":[
        {
            "category":"Professional",
            "subcategory":"Accounting & Tax Preparation",
            "type":"Services"
        }
    ],
    "sg:phone":"+1 912 638 7961",
    "sg:postcode":"31522",
    "sg:province":"GA",
    "wof:name":"Judith F Ledford CPA",
    "wof:placetype":"venue"
},
  "geometry": {"coordinates":[-81.38612000000001,31.166719],"type":"Point"}
}