{
  "type": "Feature",
  "properties": {
    "iso:country":"US",
    "sg:address":"1337 Palm Ridge Ct",
    "sg:city":"Canton",
    "sg:classifiers":[
        {
            "category":"Building & Trades",
            "subcategory":"Construction",
            "type":"Services"
        }
    ],
    "sg:phone":"+1 770 926 0777",
    "sg:postcode":"30115",
    "sg:province":"GA",
    "sg:tags":[
        "house"
    ],
    "wof:name":"Ccci",
    "wof:placetype":"venue"
},
  "geometry": {"coordinates":[-84.501426,34.15469],"type":"Point"}
}