{
  "type": "Feature",
  "properties": {
    "addr:full":"1520 Biggers Rd Columbus GA 31904",
    "addr:housenumber":"1520",
    "addr:postcode":"31904",
    "addr:street":"Biggers Rd",
    "iso:country":"US",
    "sg:address":"1520 Biggers Rd",
    "sg:city":"Columbus",
    "sg:classifiers":[
        {
            "category":"Building & Trades",
            "subcategory":"Cleaning & Sanitation",
            "type":"Services"
        }
    ],
    "sg:phone":"+1 706 315 1839",
    "sg:postcode":"31904",
    "sg:province":"GA",
    "sg:tags":[
        "landscaping",
        "security",
        "janitorial",
        "guard"
    ],
    "wof:name":"Pollard Agency Inc",
    "wof:placetype":"venue"
},
  "geometry": {"coordinates":[-84.98870599999999,32.590703],"type":"Point"}
}