{
  "type": "Feature",
  "properties": {
    "addr:full":"441 Columbia Dr Columbus GA 31907",
    "addr:housenumber":"441",
    "addr:postcode":"31907",
    "addr:street":"Columbia Dr",
    "iso:country":"US",
    "sg:address":"441 Columbia Dr",
    "sg:city":"Columbus",
    "sg:classifiers":[
        {
            "category":"Real Estate",
            "subcategory":"Real Estate Services",
            "type":"Services"
        },
        {
            "category":"Building & Trades",
            "subcategory":"Cleaning & Sanitation",
            "type":"Services"
        }
    ],
    "sg:phone":"+1 706 689 5490",
    "sg:postcode":"31907",
    "sg:province":"GA",
    "sg:tags":[
        "maintenance",
        "cleaners-interior"
    ],
    "wof:name":"Jeannies Housekeeping",
    "wof:placetype":"venue"
},
  "geometry": {"coordinates":[-84.904257,32.453227],"type":"Point"}
}