{
  "type": "Feature",
  "properties": {
    "iso:country":"US",
    "sg:address":"2070 Daniels Bridge Rd",
    "sg:city":"Athens",
    "sg:classifiers":[
        {
            "category":"Wholesale",
            "subcategory":"Durable Goods & Equipment",
            "type":"Manufacturing & Wholesale Goods"
        }
    ],
    "sg:phone":"+1 706 548 2776",
    "sg:postcode":"30606",
    "sg:province":"GA",
    "wof:name":"Rnl Inc",
    "wof:placetype":"venue"
},
  "geometry": {"coordinates":[-83.444847,33.908142],"type":"Point"}
}