{
  "type": "Feature",
  "properties": {
    "iso:country":"US",
    "sg:address":"5006 Forest Lake Dr W",
    "sg:city":"Tifton",
    "sg:classifiers":[
        {
            "category":"Restaurant",
            "type":"Food & Drink"
        }
    ],
    "sg:phone":"+1 229 386 5735",
    "sg:postcode":"31794",
    "sg:province":"GA",
    "wof:name":"Register Culpepper & Register Inc",
    "wof:placetype":"venue"
},
  "geometry": {"coordinates":[-83.431152,31.502951],"type":"Point"}
}