{
  "type": "Feature",
  "properties": {
    "addr:full":"1635 Oakwood Dr Roswell GA 30075",
    "addr:housenumber":"1635",
    "addr:postcode":"30075",
    "addr:street":"Oakwood Dr",
    "iso:country":"US",
    "sg:address":"1635 Oakwood Dr",
    "sg:city":"Roswell",
    "sg:classifiers":[
        {
            "category":"Health Services",
            "subcategory":"Nursing And Care Facility",
            "type":"Services"
        }
    ],
    "sg:phone":"+1 770 641 9759",
    "sg:postcode":"30075",
    "sg:province":"GA",
    "sg:tags":[
        "skilled"
    ],
    "wof:name":"Adams Arbor Care Inc",
    "wof:placetype":"venue"
},
  "geometry": {"coordinates":[-84.395053,34.017563],"type":"Point"}
}