{
  "type": "Feature",
  "properties": {
    "addr:full":"3169 Holcomb Bridge Rd Ste 210 Norcross GA 30071",
    "addr:housenumber":"3169",
    "addr:postcode":"30071",
    "addr:street":"Holcomb Bridge Rd Ste 210",
    "iso:country":"US",
    "sg:address":"3169 Holcomb Bridge Rd Ste 210",
    "sg:city":"Norcross",
    "sg:classifiers":[
        {
            "category":"Professional",
            "subcategory":"Employment Agencies",
            "type":"Services"
        }
    ],
    "sg:phone":"+1 770 447 4924",
    "sg:postcode":"30071",
    "sg:province":"GA",
    "sg:tags":[
        "temporary"
    ],
    "wof:name":"Medical Concepts Staffing",
    "wof:placetype":"venue"
},
  "geometry": {"coordinates":[-84.23096,33.948637],"type":"Point"}
}