{
  "type": "Feature",
  "properties": {
    "iso:country":"US",
    "sg:address":"117 Jesse Jewell Pkwy SE",
    "sg:city":"Gainesville",
    "sg:classifiers":[
        {
            "category":"Banks & Credit Unions",
            "subcategory":"Bank",
            "type":"Services"
        }
    ],
    "sg:phone":"+1 770 297 5401",
    "sg:postcode":"30501",
    "sg:province":"GA",
    "wof:name":"LANIER Federal Credit Union",
    "wof:placetype":"venue"
},
  "geometry": {"coordinates":[-83.823234,34.29848],"type":"Point"}
}