{
  "type": "Feature",
  "properties": {
    "addr:full":"1704 N Slappey Blvd Albany GA 31701",
    "addr:housenumber":"1704",
    "addr:postcode":"31701",
    "addr:street":"N Slappey Blvd",
    "iso:country":"US",
    "sg:address":"1704 N Slappey Blvd",
    "sg:city":"Albany",
    "sg:classifiers":[
        {
            "category":"Professional",
            "subcategory":"Business Services",
            "type":"Services"
        }
    ],
    "sg:phone":"+1 229 420 9328",
    "sg:postcode":"31701",
    "sg:province":"GA",
    "wof:name":"Partners In Real Estate I",
    "wof:placetype":"venue"
},
  "geometry": {"coordinates":[-84.17590199999999,31.599812],"type":"Point"}
}