{
  "type": "Feature",
  "properties": {
    "iso:country":"US",
    "sg:address":"1633 Edenfield Rd",
    "sg:city":"Sylvania",
    "sg:classifiers":[
        {
            "category":"Retail",
            "subcategory":"Car Wash",
            "type":"Services"
        }
    ],
    "sg:phone":"+1 912 564 0050",
    "sg:postcode":"30467",
    "sg:province":"GA",
    "sg:tags":[
        "carwash"
    ],
    "wof:name":"Whites Wash & Wax",
    "wof:placetype":"venue"
},
  "geometry": {"coordinates":[-81.715205,32.712423],"type":"Point"}
}