{
  "type": "Feature",
  "properties": {
    "iso:country":"US",
    "sg:address":"353 Ivy Place NE",
    "sg:city":"Atlanta",
    "sg:classifiers":[
        {
            "category":"Real Estate",
            "subcategory":"Real Estate Operator",
            "type":"Services"
        }
    ],
    "sg:phone":"+1 404 378 1370",
    "sg:postcode":"30307",
    "sg:province":"GA",
    "sg:tags":[
        "apartment"
    ],
    "wof:name":"Clifton Sancuary",
    "wof:placetype":"venue"
},
  "geometry": {"coordinates":[-84.328069,33.763876],"type":"Point"}
}