{
  "type": "Feature",
  "properties": {
    "addr:full":"285 Lawson Federal Rd Ball Ground GA 30107",
    "addr:housenumber":"285",
    "addr:postcode":"30107",
    "addr:street":"Lawson Federal Rd",
    "iso:country":"US",
    "sg:address":"285 Lawson Federal Rd",
    "sg:city":"Ball Ground",
    "sg:classifiers":[
        {
            "category":"Building & Trades",
            "subcategory":"Construction",
            "type":"Services"
        }
    ],
    "sg:phone":"+1 770 893 2548",
    "sg:postcode":"30107",
    "sg:province":"GA",
    "sg:tags":[
        "hanging",
        "contractor"
    ],
    "wof:name":"Marvin D Smith Painting C",
    "wof:placetype":"venue"
},
  "geometry": {"coordinates":[-84.311837,34.387326],"type":"Point"}
}