{
  "type": "Feature",
  "properties": {
    "addr:full":"1650 Roswell Road Marietta GA 30062",
    "addr:housenumber":"1650",
    "addr:postcode":"30062",
    "addr:street":"Roswell Road",
    "iso:country":"US",
    "sg:address":"1650 Roswell Road",
    "sg:city":"Marietta",
    "sg:classifiers":[
        {
            "category":"Health Services",
            "subcategory":"Clinic",
            "type":"Services"
        }
    ],
    "sg:phone":"+1 770 971 2020",
    "sg:postcode":"30062",
    "sg:province":"GA",
    "sg:tags":[
        "medical"
    ],
    "sg:website":"www.reachagoal.com",
    "wof:name":"Empowerment Strategies Hypnotherapy",
    "wof:placetype":"venue"
},
  "geometry": {"coordinates":[-84.50416,33.953823],"type":"Point"}
}