{
  "type": "Feature",
  "properties": {
    "addr:full":"1180 Ernest W Barrett Pkwy NW Kennesaw GA 30144",
    "addr:housenumber":"1180",
    "addr:postcode":"30144",
    "addr:street":"Ernest W Barrett Pkwy Nw",
    "iso:country":"US",
    "sg:address":"1180 Ernest W Barrett Pkwy NW",
    "sg:city":"Kennesaw",
    "sg:classifiers":[
        {
            "category":"Home & Garden",
            "subcategory":"Building Materials",
            "type":"Retail Goods"
        }
    ],
    "sg:phone":"+1 770 428 5424",
    "sg:postcode":"30144",
    "sg:province":"GA",
    "sg:tags":[
        "equipment",
        "fixture",
        "lighting"
    ],
    "sg:website":"www.progressivelighting.com",
    "wof:name":"Progressive Lighting",
    "wof:placetype":"venue"
},
  "geometry": {"coordinates":[-84.585019,33.999996],"type":"Point"}
}