{
  "type": "Feature",
  "properties": {
    "addr:full":"5226 Wrightsboro Rd Grovetown GA 30813",
    "addr:housenumber":"5226",
    "addr:postcode":"30813",
    "addr:street":"Wrightsboro Rd",
    "iso:country":"US",
    "sg:address":"5226 Wrightsboro Rd",
    "sg:city":"Grovetown",
    "sg:classifiers":[
        {
            "category":"Personal",
            "subcategory":"Beauty Salon",
            "type":"Services"
        }
    ],
    "sg:phone":"+1 706 868 6314",
    "sg:postcode":"30813",
    "sg:province":"GA",
    "sg:tags":[
        "shop"
    ],
    "wof:name":"Preference Hair Design",
    "wof:placetype":"venue"
},
  "geometry": {"coordinates":[-82.205257,33.45503],"type":"Point"}
}