{
  "type": "Feature",
  "properties": {
    "addr:full":"176 Atlanta St Mcdonough GA 30253",
    "addr:housenumber":"176",
    "addr:postcode":"30253",
    "addr:street":"Atlanta St",
    "iso:country":"US",
    "sg:address":"176 Atlanta St",
    "sg:city":"Mcdonough",
    "sg:classifiers":[
        {
            "category":"Insurance",
            "subcategory":"Hazard Insurance",
            "type":"Services"
        },
        {
            "category":"Banks & Credit Unions",
            "subcategory":"Financial Services",
            "type":"Services"
        },
        {
            "category":"Organizations",
            "subcategory":"Membership Organization",
            "type":"Services"
        }
    ],
    "sg:phone":"+1 678 814 4606",
    "sg:postcode":"30253",
    "sg:province":"GA",
    "sg:tags":[
        "consultant",
        "planning",
        "fraternal"
    ],
    "sg:website":"http://www.modern-woodmen.org",
    "wof:name":"Modern Woodmen of America",
    "wof:placetype":"venue"
},
  "geometry": {"coordinates":[-84.148698,33.452977],"type":"Point"}
}