{
  "type": "Feature",
  "properties": {
    "addr:full":"7030 Buford Hwy NE Atlanta GA 30340",
    "addr:housenumber":"7030",
    "addr:postcode":"30340",
    "addr:street":"Buford Hwy Ne",
    "iso:country":"US",
    "sg:address":"7030 Buford Hwy NE",
    "sg:city":"Atlanta",
    "sg:classifiers":[
        {
            "category":"Personal",
            "type":"Services"
        }
    ],
    "sg:phone":"+1 678 894 2748",
    "sg:postcode":"30340",
    "sg:province":"GA",
    "sg:tags":[
        "mover"
    ],
    "sg:website":"www.beltmann.com",
    "wof:name":"North American Van Lines Agent",
    "wof:placetype":"venue"
},
  "geometry": {"coordinates":[-84.252708,33.922446],"type":"Point"}
}