{
  "type": "Feature",
  "properties": {
    "addr:full":"5825 Holiday Rd Buford GA 30518",
    "addr:housenumber":"5825",
    "addr:postcode":"30518",
    "addr:street":"Holiday Rd",
    "iso:country":"US",
    "sg:address":"5825 Holiday Rd",
    "sg:city":"Buford",
    "sg:classifiers":[
        {
            "category":"Sports & Exercise",
            "subcategory":"Golf",
            "type":"Entertainment"
        }
    ],
    "sg:phone":"+1 770 614 0053",
    "sg:postcode":"30518",
    "sg:province":"GA",
    "sg:tags":[
        "course"
    ],
    "wof:name":"Hiline Golf Cart Inc",
    "wof:placetype":"venue"
},
  "geometry": {"coordinates":[-83.985827,34.153361],"type":"Point"}
}