{
  "type": "Feature",
  "properties": {
    "addr:full":"2515 Pleasant Ridge Rd Bremen GA 30110",
    "addr:housenumber":"2515",
    "addr:postcode":"30110",
    "addr:street":"Pleasant Ridge Rd",
    "iso:country":"US",
    "sg:address":"2515 Pleasant Ridge Rd",
    "sg:city":"Bremen",
    "sg:classifiers":[
        {
            "category":"Building & Trades",
            "subcategory":"Construction",
            "type":"Services"
        }
    ],
    "sg:phone":"+1 770 537 1060",
    "sg:postcode":"30110",
    "sg:province":"GA",
    "sg:tags":[
        "general",
        "contractor"
    ],
    "wof:name":"Richardson Construction Co",
    "wof:placetype":"venue"
},
  "geometry": {"coordinates":[-85.08640200000001,33.678958],"type":"Point"}
}