{
  "type": "Feature",
  "properties": {
    "iso:country":"US",
    "sg:address":"240 N Green St",
    "sg:city":"Thomaston",
    "sg:classifiers":[
        {
            "category":"Real Estate",
            "subcategory":"Real Estate Operator",
            "type":"Services"
        }
    ],
    "sg:phone":"+1 706 647 1361",
    "sg:postcode":"30286",
    "sg:province":"GA",
    "sg:tags":[
        "building",
        "apartment"
    ],
    "wof:name":"Avera Estates",
    "wof:placetype":"venue"
},
  "geometry": {"coordinates":[-84.328125,32.888787],"type":"Point"}
}