{
  "type": "Feature",
  "properties": {
    "iso:country":"US",
    "sg:address":"1535 Cheshire Ct NW",
    "sg:city":"Lawrenceville",
    "sg:classifiers":[
        {
            "category":"Farming",
            "subcategory":"Livestock Farm",
            "type":"Manufacturing & Wholesale Goods"
        }
    ],
    "sg:phone":"+1 678 442 6708",
    "sg:postcode":"30043",
    "sg:province":"GA",
    "sg:tags":[
        "abstract",
        "cattle",
        "beef",
        "feedlot",
        "title"
    ],
    "wof:name":"Genisus Unlimited",
    "wof:placetype":"venue"
},
  "geometry": {"coordinates":[-84.009784,33.995988],"type":"Point"}
}