{
  "type": "Feature",
  "properties": {
    "iso:country":"US",
    "sg:address":"145 Old Pelham Rd",
    "sg:city":"Bainbridge",
    "sg:classifiers":[
        {
            "category":"Wholesale",
            "subcategory":"Farm Supplies",
            "type":"Manufacturing & Wholesale Goods"
        }
    ],
    "sg:phone":"+1 229 246 5588",
    "sg:postcode":"39817",
    "sg:province":"GA",
    "sg:tags":[
        "auction",
        "livestock"
    ],
    "wof:name":"Bainbridge Auction Market",
    "wof:placetype":"venue"
},
  "geometry": {"coordinates":[-84.516419,30.938195],"type":"Point"}
}