{
  "type": "Feature",
  "properties": {
    "iso:country":"US",
    "sg:address":"1263 Rays Rd",
    "sg:city":"Stone Mountain",
    "sg:classifiers":[
        {
            "category":"Building & Trades",
            "subcategory":"Construction",
            "type":"Services"
        }
    ],
    "sg:phone":"+1 404 292 1897",
    "sg:postcode":"30083",
    "sg:province":"GA",
    "sg:tags":[
        "coating",
        "paper",
        "sandblasting",
        "hanging",
        "painting",
        "special"
    ],
    "wof:name":"Hutto Painting & Decorating",
    "wof:placetype":"venue"
},
  "geometry": {"coordinates":[-84.217512,33.816529],"type":"Point"}
}