{
  "type": "Feature",
  "properties": {
    "iso:country":"US",
    "sg:address":"690 Indn Trl Llbrn Rd NW",
    "sg:city":"Lilburn",
    "sg:classifiers":[
        {
            "category":"Retail",
            "subcategory":"Repair Shop",
            "type":"Services"
        }
    ],
    "sg:phone":"+1 770 279 9195",
    "sg:postcode":"30047",
    "sg:province":"GA",
    "sg:tags":[
        "reupholstery",
        "furniture"
    ],
    "wof:name":"Mack Southern Design & Upholstery",
    "wof:placetype":"venue"
},
  "geometry": {"coordinates":[-84.148697,33.9006],"type":"Point"}
}