{
  "type": "Feature",
  "properties": {
    "iso:country":"US",
    "sg:address":"1507 Korona Ct",
    "sg:city":"Woodstock",
    "sg:classifiers":[
        {
            "category":"Building & Trades",
            "subcategory":"Landscaping Services",
            "type":"Services"
        },
        {
            "category":"Home & Garden",
            "subcategory":"Garden Supply",
            "type":"Retail Goods"
        },
        {
            "category":"Sports & Exercise",
            "subcategory":"Swimming Pool",
            "type":"Entertainment"
        }
    ],
    "sg:phone":"+1 678 908 4151",
    "sg:postcode":"30188",
    "sg:province":"GA",
    "sg:tags":[
        "designer",
        "consultant",
        "water",
        "pond",
        "landscape"
    ],
    "wof:name":"PondScapes Atlanta",
    "wof:placetype":"venue"
},
  "geometry": {"coordinates":[-84.481166,34.098825],"type":"Point"}
}