{
  "type": "Feature",
  "properties": {
    "iso:country":"US",
    "sg:address":"601 W Elm St",
    "sg:city":"Wrightsville",
    "sg:classifiers":[
        {
            "category":"Education",
            "subcategory":"School",
            "type":"Public Place"
        }
    ],
    "sg:phone":"+1 478 864 3446",
    "sg:postcode":"31096",
    "sg:province":"GA",
    "sg:website":"www.johnsoncountyschools.org",
    "wof:name":"Johnson County Elementary Schl",
    "wof:placetype":"venue"
},
  "geometry": {"coordinates":[-82.731602,32.728586],"type":"Point"}
}