{
  "type": "Feature",
  "properties": {
    "addr:full":"371 Larry Dr Ringgold GA 30736",
    "addr:housenumber":"371",
    "addr:postcode":"30736",
    "addr:street":"Larry Dr",
    "iso:country":"US",
    "sg:address":"371 Larry Dr",
    "sg:city":"Ringgold",
    "sg:classifiers":[
        {
            "category":"Manufacturing",
            "subcategory":"Printing",
            "type":"Manufacturing & Wholesale Goods"
        }
    ],
    "sg:phone":"+1 706 891 6020",
    "sg:postcode":"30736",
    "sg:province":"GA",
    "sg:tags":[
        "lithographic",
        "commercial"
    ],
    "wof:name":"Southwood Naturals Inc",
    "wof:placetype":"venue"
},
  "geometry": {"coordinates":[-85.187021,34.967071],"type":"Point"}
}