{
  "type": "Feature",
  "properties": {
    "addr:full":"3959 Creel Dr Lithia Springs GA 30122",
    "addr:housenumber":"3959",
    "addr:postcode":"30122",
    "addr:street":"Creel Dr",
    "iso:country":"US",
    "sg:address":"3959 Creel Dr",
    "sg:city":"Lithia Springs",
    "sg:classifiers":[
        {
            "category":"Freight",
            "type":"Transportation"
        }
    ],
    "sg:phone":"+1 770 944 2383",
    "sg:postcode":"30122",
    "sg:province":"GA",
    "sg:tags":[
        "local",
        "storage",
        "trucking"
    ],
    "wof:name":"Als 13 Speed Transfer Inc",
    "wof:placetype":"venue"
},
  "geometry": {"coordinates":[-84.671558,33.798602],"type":"Point"}
}