{
  "type": "Feature",
  "properties": {
    "iso:country":"US",
    "sg:address":"1003 S Young Ave",
    "sg:city":"Warner Robins",
    "sg:classifiers":[
        {
            "category":"Professional",
            "subcategory":"Accounting & Tax Preparation",
            "type":"Services"
        }
    ],
    "sg:phone":"+1 478 922 2345",
    "sg:postcode":"31093",
    "sg:province":"GA",
    "sg:tags":[
        "accountant"
    ],
    "wof:name":"Wilson Accounting Inc",
    "wof:placetype":"venue"
},
  "geometry": {"coordinates":[-83.613023,32.621169],"type":"Point"}
}