{
  "type": "Feature",
  "properties": {
    "iso:country":"US",
    "sg:address":"1604 Newcastle St",
    "sg:city":"Brunswick",
    "sg:classifiers":[
        {
            "category":"Restaurant",
            "type":"Food & Drink"
        }
    ],
    "sg:phone":"+1 912 265 9637",
    "sg:postcode":"31520",
    "sg:province":"GA",
    "wof:name":"Scribbles",
    "wof:placetype":"venue"
},
  "geometry": {"coordinates":[-81.49635000000001,31.151734],"type":"Point"}
}