{
  "type": "Feature",
  "properties": {
    "iso:country":"US",
    "sg:address":"801 N Madison St",
    "sg:city":"Thomasville",
    "sg:classifiers":[
        {
            "category":"Retail",
            "subcategory":"Auto Repair",
            "type":"Services"
        }
    ],
    "sg:phone":"+1 229 225 9788",
    "sg:postcode":"31792",
    "sg:province":"GA",
    "sg:tags":[
        "body",
        "automobile",
        "painting"
    ],
    "wof:name":"Right Now Auto",
    "wof:placetype":"venue"
},
  "geometry": {"coordinates":[-83.988783,30.845264],"type":"Point"}
}