{
  "type": "Feature",
  "properties": {
    "addr:full":"4319 Covington Hwy Ste 214 Decatur GA 30035",
    "addr:housenumber":"4319",
    "addr:postcode":"30035",
    "addr:street":"Covington Hwy Ste 214",
    "iso:country":"US",
    "sg:address":"4319 Covington Hwy Ste 214",
    "sg:city":"Decatur",
    "sg:classifiers":[
        {
            "category":"Personal",
            "subcategory":"Massage",
            "type":"Services"
        },
        {
            "category":"Health Services",
            "subcategory":"Health Practitioner",
            "type":"Services"
        },
        {
            "category":"Personal",
            "subcategory":"Day Spa",
            "type":"Services"
        }
    ],
    "sg:phone":"+1 404 316 0153",
    "sg:postcode":"30035",
    "sg:province":"GA",
    "sg:tags":[
        "nutritionist"
    ],
    "sg:website":"www.setyourownfee.com/",
    "wof:name":"Affordable Holistic Healthcare",
    "wof:placetype":"venue"
},
  "geometry": {"coordinates":[-84.22744400000001,33.748888],"type":"Point"}
}