{
  "type": "Feature",
  "properties": {
    "iso:country":"US",
    "sg:address":"111 S Patterson St",
    "sg:city":"Valdosta",
    "sg:classifiers":[
        {
            "category":"Government",
            "subcategory":"Office",
            "type":"Public Place"
        }
    ],
    "sg:phone":"+1 229 249 4887",
    "sg:postcode":"31601",
    "sg:province":"GA",
    "sg:tags":[
        "state",
        "resource"
    ],
    "wof:name":"Child Support Enforcement",
    "wof:placetype":"venue"
},
  "geometry": {"coordinates":[-83.278733,30.830742],"type":"Point"}
}