{
  "type": "Feature",
  "properties": {
    "iso:country":"US",
    "sg:address":"774 Soaring Dr",
    "sg:city":"Marietta",
    "sg:classifiers":[
        {
            "category":"Travel",
            "subcategory":"Travel Agent",
            "type":"Entertainment"
        }
    ],
    "sg:phone":"+1 770 794 0777",
    "sg:postcode":"30062",
    "sg:province":"GA",
    "sg:tags":[
        "agency"
    ],
    "wof:name":"Worldwide Travel Coordinators",
    "wof:placetype":"venue"
},
  "geometry": {"coordinates":[-84.512024,33.971121],"type":"Point"}
}