{
  "type": "Feature",
  "properties": {
    "iso:country":"US",
    "sg:address":"1618 Hamilton Rd",
    "sg:city":"Lagrange",
    "sg:classifiers":[
        {
            "category":"Home & Garden",
            "subcategory":"Home Furnishings",
            "type":"Retail Goods"
        }
    ],
    "sg:phone":"+1 706 845 9583",
    "sg:postcode":"30241",
    "sg:province":"GA",
    "sg:tags":[
        "curtain",
        "made",
        "drapery"
    ],
    "wof:name":"Simply Beautiful Windows",
    "wof:placetype":"venue"
},
  "geometry": {"coordinates":[-85.020135,33.012859],"type":"Point"}
}