{
  "type": "Feature",
  "properties": {
    "addr:full":"980 Cobb Place Blvd NW Kennesaw GA 30144",
    "addr:housenumber":"980",
    "addr:postcode":"30144",
    "addr:street":"Cobb Place Blvd Nw",
    "iso:country":"US",
    "sg:address":"980 Cobb Place Blvd NW",
    "sg:city":"Kennesaw",
    "sg:classifiers":[
        {
            "category":"Manufacturing",
            "subcategory":"Tools & Machinery",
            "type":"Manufacturing & Wholesale Goods"
        }
    ],
    "sg:phone":"+1 678 819 2274",
    "sg:postcode":"30144",
    "sg:province":"GA",
    "sg:tags":[
        "air",
        "parts",
        "conditioning",
        "supply"
    ],
    "sg:website":"www.aftermkt.com",
    "wof:name":"Aftermarket Specialties Inc",
    "wof:placetype":"venue"
},
  "geometry": {"coordinates":[-84.582722,34.009033],"type":"Point"}
}