{
  "type": "Feature",
  "properties": {
    "iso:country":"US",
    "sg:address":"320 Hardscrabble Rd",
    "sg:city":"Roswell",
    "sg:classifiers":[
        {
            "category":"Place Of Worship",
            "subcategory":"Church",
            "type":"Public Place"
        },
        {
            "category":"Place Of Worship",
            "type":"Public Place"
        }
    ],
    "sg:phone":"+1 770 643 9223",
    "sg:postcode":"30075",
    "sg:province":"GA",
    "sg:tags":[
        "churches-charismatic"
    ],
    "sg:website":"http://www.worldharvestchurch.org",
    "wof:name":"World Havest Church",
    "wof:placetype":"venue"
},
  "geometry": {"coordinates":[-84.36639,34.072282],"type":"Point"}
}