{
  "type": "Feature",
  "properties": {
    "iso:country":"US",
    "sg:address":"2110 Rockbridge Rd",
    "sg:city":"Stone Mountain",
    "sg:classifiers":[
        {
            "category":"Professional",
            "subcategory":"Lawyer & Legal Services",
            "type":"Services"
        }
    ],
    "sg:phone":"+1 770 879 5959",
    "sg:postcode":"30087",
    "sg:province":"GA",
    "sg:tags":[
        "personal",
        "injury"
    ],
    "wof:name":"Cicala John G Jr Atty",
    "wof:placetype":"venue"
},
  "geometry": {"coordinates":[-84.11170199999999,33.820499],"type":"Point"}
}