{
  "type": "Feature",
  "properties": {
    "addr:full":"532 Wyatt Rd Canton GA 30115",
    "addr:housenumber":"532",
    "addr:postcode":"30115",
    "addr:street":"Wyatt Rd",
    "iso:country":"US",
    "sg:address":"532 Wyatt Rd",
    "sg:city":"Canton",
    "sg:classifiers":[
        {
            "category":"Professional",
            "type":"Services"
        },
        {
            "category":"Building & Trades",
            "subcategory":"Construction",
            "type":"Services"
        }
    ],
    "sg:phone":"+1 770 889 8570",
    "sg:postcode":"30115",
    "sg:province":"GA",
    "sg:tags":[
        "residential",
        "establishment"
    ],
    "wof:name":"Clay Nichols & Assoc Inc",
    "wof:placetype":"venue"
},
  "geometry": {"coordinates":[-84.30326700000001,34.229351],"type":"Point"}
}