{
  "type": "Feature",
  "properties": {
    "addr:full":"4160 Jody Ct NE Marietta GA 30066",
    "addr:housenumber":"4160",
    "addr:postcode":"30066",
    "addr:street":"Jody Ct Ne",
    "iso:country":"US",
    "sg:address":"4160 Jody Ct NE",
    "sg:city":"Marietta",
    "sg:classifiers":[
        {
            "category":"Building & Trades",
            "subcategory":"Construction",
            "type":"Services"
        }
    ],
    "sg:phone":"+1 770 592 1124",
    "sg:postcode":"30066",
    "sg:province":"GA",
    "sg:tags":[
        "road",
        "contractor"
    ],
    "wof:name":"Advanced Building Concepts",
    "wof:placetype":"venue"
},
  "geometry": {"coordinates":[-84.50013800000001,34.0523],"type":"Point"}
}