{
  "type": "Feature",
  "properties": {
    "addr:full":"530A Lakeland Plz Cumming GA 30040",
    "addr:housenumber":"530a",
    "addr:postcode":"30040",
    "addr:street":"Lakeland Plz",
    "iso:country":"US",
    "sg:address":"530A Lakeland Plz",
    "sg:city":"Cumming",
    "sg:classifiers":[
        {
            "category":"Wholesale",
            "subcategory":"Office Equipment",
            "type":"Manufacturing & Wholesale Goods"
        },
        {
            "category":"Shopping",
            "subcategory":"Stationery & Office Supplies",
            "type":"Retail Goods"
        },
        {
            "category":"Shopping",
            "subcategory":"Computers & Home Electronics",
            "type":"Retail Goods"
        },
        {
            "category":"Professional",
            "subcategory":"Printing & Photocopies",
            "type":"Services"
        },
        {
            "category":"Wholesale",
            "subcategory":"Computers",
            "type":"Manufacturing & Wholesale Goods"
        }
    ],
    "sg:phone":"+1 678 455 3622",
    "sg:postcode":"30040",
    "sg:province":"GA",
    "sg:tags":[
        "register",
        "autographic",
        "duplicating",
        "copying",
        "typewriter",
        "furniture"
    ],
    "sg:website":"http://www.officedepot.com",
    "wof:name":"Office Depot",
    "wof:placetype":"venue"
},
  "geometry": {"coordinates":[-84.1434,34.186082],"type":"Point"}
}