{
  "type": "Feature",
  "properties": {
    "addr:full":"1025 Howell Mill Rd Atlanta GA 30318",
    "addr:housenumber":"1025",
    "addr:postcode":"30318",
    "addr:street":"Howell Mill Rd",
    "iso:country":"US",
    "sg:address":"1025 Howell Mill Rd",
    "sg:city":"Atlanta",
    "sg:classifiers":[
        {
            "category":"Restaurant",
            "type":"Food & Drink"
        }
    ],
    "sg:phone":"+1 404 817 7153",
    "sg:postcode":"30318",
    "sg:province":"GA",
    "sg:tags":[
        "eating"
    ],
    "wof:name":"Piazza Slice",
    "wof:placetype":"venue"
},
  "geometry": {"coordinates":[-84.411582,33.782924],"type":"Point"}
}