{
  "type": "Feature",
  "properties": {
    "addr:full":"2315 Wingfoot Pl Decatur GA 30035",
    "addr:housenumber":"2315",
    "addr:postcode":"30035",
    "addr:street":"Wingfoot Pl",
    "iso:country":"US",
    "sg:address":"2315 Wingfoot Pl",
    "sg:city":"Decatur",
    "sg:classifiers":[
        {
            "category":"Building & Trades",
            "subcategory":"Cleaning & Sanitation",
            "type":"Services"
        }
    ],
    "sg:phone":"+1 770 374 4994",
    "sg:postcode":"30035",
    "sg:province":"GA",
    "sg:tags":[
        "janitor"
    ],
    "wof:name":"Jay's Cleaning Svc",
    "wof:placetype":"venue"
},
  "geometry": {"coordinates":[-84.21648999999999,33.72008],"type":"Point"}
}