{
  "type": "Feature",
  "properties": {
    "addr:full":"3301 Saint Marys Rd Columbus GA 31906",
    "addr:housenumber":"3301",
    "addr:postcode":"31906",
    "addr:street":"Saint Marys Rd",
    "iso:country":"US",
    "sg:address":"3301 Saint Marys Rd",
    "sg:city":"Columbus",
    "sg:classifiers":[
        {
            "category":"Restaurant",
            "type":"Food & Drink"
        }
    ],
    "sg:phone":"+1 706 682 9607",
    "sg:postcode":"31906",
    "sg:province":"GA",
    "sg:tags":[
        "fast"
    ],
    "wof:name":"KFC",
    "wof:placetype":"venue"
},
  "geometry": {"coordinates":[-84.940956,32.452618],"type":"Point"}
}