{
  "type": "Feature",
  "properties": {
    "iso:country":"US",
    "sg:address":"2969 E Ponce De Leon Ave",
    "sg:city":"Decatur",
    "sg:classifiers":[
        {
            "category":"Retail",
            "subcategory":"Repair Shop",
            "type":"Services"
        }
    ],
    "sg:phone":"+1 404 377 9521",
    "sg:postcode":"30030",
    "sg:province":"GA",
    "sg:tags":[
        "reupholstery",
        "furniture"
    ],
    "sg:website":"www.customslipcoverupholstery.com",
    "wof:name":"Custom Slipcover & Upholstery",
    "wof:placetype":"venue"
},
  "geometry": {"coordinates":[-84.27264,33.783176],"type":"Point"}
}