{
  "type": "Feature",
  "properties": {
    "addr:full":"503 Commerce Park Dr Marietta GA 30060",
    "addr:housenumber":"503",
    "addr:postcode":"30060",
    "addr:street":"Commerce Park Dr",
    "iso:country":"US",
    "sg:address":"503 Commerce Park Dr",
    "sg:city":"Marietta",
    "sg:classifiers":[
        {
            "category":"Manufacturing",
            "subcategory":"Printing",
            "type":"Manufacturing & Wholesale Goods"
        }
    ],
    "sg:phone":"+1 770 422 4221",
    "sg:postcode":"30060",
    "sg:province":"GA",
    "sg:tags":[
        "printer"
    ],
    "sg:website":"www.perfectimageprinting.com",
    "wof:name":"Perfect Image",
    "wof:placetype":"venue"
},
  "geometry": {"coordinates":[-84.53340799999999,33.939405],"type":"Point"}
}