{
  "type": "Feature",
  "properties": {
    "addr:full":"200 Mooty Bridge Rd La Grange GA 30240",
    "addr:housenumber":"200",
    "addr:postcode":"30240",
    "addr:street":"Mooty Bridge Rd",
    "iso:country":"US",
    "sg:address":"200 Mooty Bridge Rd",
    "sg:city":"La Grange",
    "sg:classifiers":[
        {
            "category":"Professional",
            "subcategory":"Management & Consulting",
            "type":"Services"
        }
    ],
    "sg:phone":"+1 706 812 7920",
    "sg:postcode":"30240",
    "sg:province":"GA",
    "wof:name":"Instructional Support Services",
    "wof:placetype":"venue"
},
  "geometry": {"coordinates":[-85.031639,33.054085],"type":"Point"}
}