{
  "type": "Feature",
  "properties": {
    "addr:full":"1041 Honey Creek Rd SE Conyers GA 30013",
    "addr:housenumber":"1041",
    "addr:postcode":"30013",
    "addr:street":"Honey Creek Rd Se",
    "iso:country":"US",
    "sg:address":"1041 Honey Creek Rd SE",
    "sg:city":"Conyers",
    "sg:classifiers":[
        {
            "category":"Professional",
            "subcategory":"Business Services",
            "type":"Services"
        }
    ],
    "sg:phone":"+1 404 822 6014",
    "sg:postcode":"30013",
    "sg:province":"GA",
    "wof:name":"Cognovis Group LLC",
    "wof:placetype":"venue"
},
  "geometry": {"coordinates":[-84.01253,33.59635],"type":"Point"}
}