{
  "type": "Feature",
  "properties": {
    "addr:full":"1767 Thompson Rd Dawsonville GA 30534",
    "addr:housenumber":"1767",
    "addr:postcode":"30534",
    "addr:street":"Thompson Rd",
    "iso:country":"US",
    "sg:address":"1767 Thompson Rd",
    "sg:city":"Dawsonville",
    "sg:classifiers":[
        {
            "category":"Manufacturing",
            "subcategory":"Chemicals & Compounds",
            "type":"Manufacturing & Wholesale Goods"
        }
    ],
    "sg:phone":"+1 706 265 2778",
    "sg:postcode":"30534",
    "sg:province":"GA",
    "sg:tags":[
        "mfg"
    ],
    "wof:name":"Americas First Choice Window",
    "wof:placetype":"venue"
},
  "geometry": {"coordinates":[-84.09104499999999,34.378642],"type":"Point"}
}