{
  "type": "Feature",
  "properties": {
    "addr:full":"225 Deer Trl Fayetteville GA 30214",
    "addr:housenumber":"225",
    "addr:postcode":"30214",
    "addr:street":"Deer Trl",
    "iso:country":"US",
    "sg:address":"225 Deer Trl",
    "sg:city":"Fayetteville",
    "sg:classifiers":[
        {
            "category":"Professional",
            "subcategory":"Art Services",
            "type":"Services"
        }
    ],
    "sg:phone":"+1 770 719 5361",
    "sg:postcode":"30214",
    "sg:province":"GA",
    "sg:tags":[
        "designer",
        "display",
        "producer"
    ],
    "wof:name":"Marybella Posh Designs",
    "wof:placetype":"venue"
},
  "geometry": {"coordinates":[-84.441507,33.466435],"type":"Point"}
}