{
  "type": "Feature",
  "properties": {
    "iso:country":"US",
    "sg:address":"3475 Oak Valley Rd NE",
    "sg:city":"Atlanta",
    "sg:classifiers":[
        {
            "category":"Autos & Motor Vehicles",
            "subcategory":"Automobile Sales",
            "type":"Retail Goods"
        }
    ],
    "sg:phone":"+1 404 233 9200",
    "sg:postcode":"30326",
    "sg:province":"GA",
    "sg:tags":[
        "limo"
    ],
    "wof:name":"Buckhead Transportation & Limousine",
    "wof:placetype":"venue"
},
  "geometry": {"coordinates":[-84.359703,33.849899],"type":"Point"}
}