{
  "type": "Feature",
  "properties": {
    "addr:full":"530 Terry St SE Atlanta GA 30312",
    "addr:housenumber":"530",
    "addr:postcode":"30312",
    "addr:street":"Terry St Se",
    "iso:country":"US",
    "sg:address":"530 Terry St SE",
    "sg:city":"Atlanta",
    "sg:classifiers":[
        {
            "category":"Building & Trades",
            "subcategory":"Construction",
            "type":"Services"
        }
    ],
    "sg:phone":"+1 404 381 1140",
    "sg:postcode":"30312",
    "sg:province":"GA",
    "sg:tags":[
        "contractor"
    ],
    "sg:website":"www.atlantamasonry.org",
    "wof:name":"Tile and Masonry Contracting",
    "wof:placetype":"venue"
},
  "geometry": {"coordinates":[-84.384835,33.739393],"type":"Point"}
}