{
  "type": "Feature",
  "properties": {
    "addr:full":"1167 Zonolite Pl NE Atlanta GA 30306",
    "addr:housenumber":"1167",
    "addr:postcode":"30306",
    "addr:street":"Zonolite Pl Ne",
    "iso:country":"US",
    "sg:address":"1167 Zonolite Pl NE",
    "sg:city":"Atlanta",
    "sg:classifiers":[
        {
            "category":"Professional",
            "subcategory":"Employment Agencies",
            "type":"Services"
        }
    ],
    "sg:phone":"+1 404 815 1080",
    "sg:postcode":"30306",
    "sg:province":"GA",
    "sg:tags":[
        "help",
        "supply"
    ],
    "wof:name":"Trp Enterprise",
    "wof:placetype":"venue"
},
  "geometry": {"coordinates":[-84.340958,33.805445],"type":"Point"}
}