{
  "type": "Feature",
  "properties": {
    "addr:full":"5043 New Jesup Hwy Brunswick GA 31520",
    "addr:housenumber":"5043",
    "addr:postcode":"31520",
    "addr:street":"New Jesup Hwy",
    "iso:country":"US",
    "sg:address":"5043 New Jesup Hwy",
    "sg:city":"Brunswick",
    "sg:classifiers":[
        {
            "category":"Autos & Motor Vehicles",
            "subcategory":"Fuel & Gas Station",
            "type":"Retail Goods"
        }
    ],
    "sg:phone":"+1 912 264 1792",
    "sg:postcode":"31520",
    "sg:province":"GA",
    "sg:tags":[
        "gasoline"
    ],
    "wof:name":"Mobil",
    "wof:placetype":"venue"
},
  "geometry": {"coordinates":[-81.52010799999999,31.218254],"type":"Point"}
}