{
  "type": "Feature",
  "properties": {
    "addr:full":"1007 Center Dr Vidalia GA 30474",
    "addr:housenumber":"1007",
    "addr:postcode":"30474",
    "addr:street":"Center Dr Vidalia",
    "iso:country":"US",
    "sg:address":"1007 Center Dr",
    "sg:city":"Vidalia",
    "sg:classifiers":[
        {
            "category":"Professional",
            "subcategory":"Secretarial Services",
            "type":"Services"
        }
    ],
    "sg:phone":"+1 912 537 8205",
    "sg:postcode":"30474",
    "sg:province":"GA",
    "sg:tags":[
        "reporting"
    ],
    "wof:name":"Holland Court Reporting Svc",
    "wof:placetype":"venue"
},
  "geometry": {"coordinates":[-82.416312,32.207461],"type":"Point"}
}