{
  "type": "Feature",
  "properties": {
    "iso:country":"US",
    "sg:address":"1452 Foote McClellan Rd",
    "sg:city":"Colbert",
    "sg:classifiers":[
        {
            "category":"Building & Trades",
            "subcategory":"Landscaping Services",
            "type":"Services"
        }
    ],
    "sg:phone":"+1 706 543 2640",
    "sg:postcode":"30628",
    "sg:province":"GA",
    "wof:name":"Grass Cathers The",
    "wof:placetype":"venue"
},
  "geometry": {"coordinates":[-83.25226499999999,34.041776],"type":"Point"}
}