{
  "type": "Feature",
  "properties": {
    "addr:full":"1104 Nickle Plate Ct Lawrenceville GA 30043",
    "addr:housenumber":"1104",
    "addr:postcode":"30043",
    "addr:street":"Nickle Plate Ct",
    "iso:country":"US",
    "sg:address":"1104 Nickle Plate Ct",
    "sg:city":"Lawrenceville",
    "sg:classifiers":[
        {
            "category":"Freight",
            "type":"Transportation"
        }
    ],
    "sg:phone":"+1 678 985 3616",
    "sg:postcode":"30043",
    "sg:province":"GA",
    "wof:name":"Logistics Christian & Dist",
    "wof:placetype":"venue"
},
  "geometry": {"coordinates":[-83.997167,33.98672],"type":"Point"}
}