{
  "type": "Feature",
  "properties": {
    "iso:country":"US",
    "sg:address":"474 Cedar Ridge Dr",
    "sg:city":"Winder",
    "sg:classifiers":[
        {
            "category":"Building & Trades",
            "subcategory":"Construction",
            "type":"Services"
        }
    ],
    "sg:phone":"+1 770 867 5854",
    "sg:postcode":"30680",
    "sg:province":"GA",
    "sg:tags":[
        "residential"
    ],
    "wof:name":"J&R Construction",
    "wof:placetype":"venue"
},
  "geometry": {"coordinates":[-83.781666,34.016865],"type":"Point"}
}