{
  "type": "Feature",
  "properties": {
    "iso:country":"US",
    "sg:address":"4279 Roswell Rd",
    "sg:city":"Atlanta",
    "sg:classifiers":[
        {
            "category":"Building & Trades",
            "subcategory":"Locksmith",
            "type":"Services"
        }
    ],
    "sg:phone":"+1 404 965 0700",
    "sg:postcode":"30342",
    "sg:province":"GA",
    "sg:tags":[
        "key"
    ],
    "wof:name":"0 Hassle Atlanta Locksmith Service",
    "wof:placetype":"venue"
},
  "geometry": {"coordinates":[-84.380883,33.871719],"type":"Point"}
}