{
  "type": "Feature",
  "properties": {
    "iso:country":"US",
    "sg:address":"5131 S Royal Atlanta Dr",
    "sg:city":"Tucker",
    "sg:classifiers":[
        {
            "category":"Real Estate",
            "subcategory":"Real Estate Agent",
            "type":"Services"
        }
    ],
    "sg:phone":"+1 770 934 1238",
    "sg:postcode":"30084",
    "sg:province":"GA",
    "wof:name":"Cabot Industrial Properties",
    "wof:placetype":"venue"
},
  "geometry": {"coordinates":[-84.186668,33.856272],"type":"Point"}
}