{
  "type": "Feature",
  "properties": {
    "addr:full":"5176 Baldwin Ter Marietta GA 30068",
    "addr:housenumber":"5176",
    "addr:postcode":"30068",
    "addr:street":"Baldwin Ter",
    "iso:country":"US",
    "sg:address":"5176 Baldwin Ter",
    "sg:city":"Marietta",
    "sg:classifiers":[
        {
            "category":"Professional",
            "subcategory":"Management & Consulting",
            "type":"Services"
        }
    ],
    "sg:phone":"+1 678 461 7820",
    "sg:postcode":"30068",
    "sg:province":"GA",
    "sg:tags":[
        "business"
    ],
    "wof:name":"Medco",
    "wof:placetype":"venue"
},
  "geometry": {"coordinates":[-84.402496,33.995035],"type":"Point"}
}