{
  "type": "Feature",
  "properties": {
    "iso:country":"US",
    "sg:address":"8295 State Rte 17",
    "sg:city":"Bowersville",
    "sg:classifiers":[
        {
            "category":"Organizations",
            "subcategory":"Religious Organization",
            "type":"Services"
        }
    ],
    "sg:phone":"+1 706 245 4348",
    "sg:postcode":"30516",
    "sg:province":"GA",
    "sg:tags":[
        "church"
    ],
    "wof:name":"Lifeline Church",
    "wof:placetype":"venue"
},
  "geometry": {"coordinates":[-83.086226,34.371162],"type":"Point"}
}