{
  "type": "Feature",
  "properties": {
    "iso:country":"US",
    "sg:address":"21 S Oaks Dr",
    "sg:city":"Cartersville",
    "sg:classifiers":[
        {
            "category":"Professional",
            "type":"Services"
        }
    ],
    "sg:phone":"+1 770 607 8018",
    "sg:postcode":"30121",
    "sg:province":"GA",
    "wof:name":"Danny Burdette",
    "wof:placetype":"venue"
},
  "geometry": {"coordinates":[-84.73575099999999,34.21769],"type":"Point"}
}