{
  "type": "Feature",
  "properties": {
    "addr:full":"2059 Northlake Parkway 1 NE S Tucker GA 30084",
    "addr:housenumber":"2059;1",
    "addr:postcode":"30084",
    "addr:street":"Northlake Parkway;Ne S",
    "iso:country":"US",
    "sg:address":"2059 Northlake Parkway 1 NE S",
    "sg:city":"Tucker",
    "sg:classifiers":[
        {
            "category":"Banks & Credit Unions",
            "subcategory":"Financial Services",
            "type":"Services"
        }
    ],
    "sg:phone":"+1 770 491 4016",
    "sg:postcode":"30084",
    "sg:province":"GA",
    "sg:tags":[
        "broker",
        "mortgage"
    ],
    "sg:website":"www.bankofamerica.com",
    "wof:name":"Bank of America",
    "wof:placetype":"venue"
},
  "geometry": {"coordinates":[-84.241687,33.842958],"type":"Point"}
}