{
  "type": "Feature",
  "properties": {
    "addr:full":"1965 W Broad St Athens GA 30606",
    "addr:housenumber":"1965",
    "addr:postcode":"30606",
    "addr:street":"W Broad St",
    "iso:country":"US",
    "sg:address":"1965 W Broad St",
    "sg:city":"Athens",
    "sg:classifiers":[
        {
            "category":"Restaurant",
            "type":"Food & Drink"
        }
    ],
    "sg:menulink":"http://www.allmenus.com/ga/athens/241896-food-for-the-soul/menu/",
    "sg:phone":"+1 706 546 0052",
    "sg:postcode":"30606",
    "sg:province":"GA",
    "sg:tags":[
        "american",
        "soul"
    ],
    "wof:name":"Food For The Soul",
    "wof:placetype":"venue"
},
  "geometry": {"coordinates":[-83.403012,33.951292],"type":"Point"}
}