{
  "type": "Feature",
  "properties": {
    "iso:country":"US",
    "sg:address":"634 Hightower Rd",
    "sg:city":"Hogansville",
    "sg:classifiers":[
        {
            "category":"Farming",
            "subcategory":"Livestock Farm",
            "type":"Manufacturing & Wholesale Goods"
        },
        {
            "category":"Farming",
            "subcategory":"Farm",
            "type":"Manufacturing & Wholesale Goods"
        }
    ],
    "sg:phone":"+1 706 637 6655",
    "sg:postcode":"30230",
    "sg:province":"GA",
    "sg:tags":[
        "feeding",
        "ranch"
    ],
    "wof:name":"Faloaw Ranch",
    "wof:placetype":"venue"
},
  "geometry": {"coordinates":[-84.94761699999999,33.144144],"type":"Point"}
}