{
  "type": "Feature",
  "properties": {
    "iso:country":"US",
    "sg:address":"340 Boulevard NE",
    "sg:city":"Atlanta",
    "sg:classifiers":[
        {
            "category":"Health Services",
            "subcategory":"Doctor",
            "type":"Services"
        }
    ],
    "sg:phone":"+1 404 588 0130",
    "sg:postcode":"30312",
    "sg:province":"GA",
    "sg:tags":[
        "orthopedist"
    ],
    "wof:name":"Orthopaedic Associates PC",
    "wof:placetype":"venue"
},
  "geometry": {"coordinates":[-84.37197999999999,33.76378],"type":"Point"}
}