{
  "type": "Feature",
  "properties": {
    "iso:country":"US",
    "sg:address":"2115 Shorter Ave SW",
    "sg:city":"Rome",
    "sg:classifiers":[
        {
            "category":"Restaurant",
            "type":"Food & Drink"
        }
    ],
    "sg:menulink":"http://www.allmenus.com/ga/rome/71001-pizza-hut/menu/",
    "sg:phone":"+1 706 235 7420",
    "sg:postcode":"30165",
    "sg:province":"GA",
    "sg:tags":[
        "american",
        "pizza"
    ],
    "wof:name":"Pizza Hut",
    "wof:placetype":"venue"
},
  "geometry": {"coordinates":[-85.22314900000001,34.270964],"type":"Point"}
}