{
  "type": "Feature",
  "properties": {
    "addr:full":"620 Peachtree St Atlanta GA 30308",
    "addr:housenumber":"620",
    "addr:postcode":"30308",
    "addr:street":"Peachtree St",
    "iso:country":"US",
    "sg:address":"620 Peachtree St",
    "sg:city":"Atlanta",
    "sg:classifiers":[
        {
            "category":"Food & Beverages",
            "subcategory":"Bakery",
            "type":"Retail Goods"
        }
    ],
    "sg:phone":"+1 404 541 9944",
    "sg:postcode":"30308",
    "sg:province":"GA",
    "sg:tags":[
        "sandwich"
    ],
    "sg:website":"www.tjssubs.com",
    "wof:name":"TJ's Subs",
    "wof:placetype":"venue"
},
  "geometry": {"coordinates":[-84.384979,33.771524],"type":"Point"}
}