{
  "type": "Feature",
  "properties": {
    "iso:country":"US",
    "sg:address":"363 Lawrence Place",
    "sg:city":"Atlanta",
    "sg:classifiers":[
        {
            "category":"Professional",
            "subcategory":"Lawyer & Legal Services",
            "type":"Services"
        }
    ],
    "sg:phone":"+1 770 422 0574",
    "sg:postcode":"30349",
    "sg:province":"GA",
    "wof:name":"Croy Kennth R Atty",
    "wof:placetype":"venue"
},
  "geometry": {"coordinates":[-84.626848,33.663435],"type":"Point"}
}