{
  "type": "Feature",
  "properties": {
    "iso:country":"US",
    "sg:address":"210 Beech St",
    "sg:city":"Cochran",
    "sg:classifiers":[
        {
            "category":"Personal",
            "subcategory":"Beauty Salon",
            "type":"Services"
        }
    ],
    "sg:phone":"+1 478 934 7445",
    "sg:postcode":"31014",
    "sg:province":"GA",
    "wof:name":"Net's Beauty Shop",
    "wof:placetype":"venue"
},
  "geometry": {"coordinates":[-83.35811200000001,32.387745],"type":"Point"}
}