{
  "type": "Feature",
  "properties": {
    "addr:full":"4467 Highway 42 Ellenwood GA 30294",
    "addr:housenumber":"4467",
    "addr:postcode":"30294",
    "addr:street":"Highway 42",
    "iso:country":"US",
    "sg:address":"4467 Highway 42",
    "sg:city":"Ellenwood",
    "sg:classifiers":[
        {
            "category":"Building & Trades",
            "subcategory":"Plumbing",
            "type":"Services"
        },
        {
            "category":"Wholesale",
            "subcategory":"Construction Materials",
            "type":"Manufacturing & Wholesale Goods"
        },
        {
            "category":"Manufacturing",
            "subcategory":"Building Materials",
            "type":"Manufacturing & Wholesale Goods"
        }
    ],
    "sg:phone":"+1 404 363 2050",
    "sg:postcode":"30294",
    "sg:province":"GA",
    "sg:tags":[
        "product",
        "grease",
        "tank",
        "septic",
        "cover",
        "system",
        "systems-wholesale",
        "concrete",
        "trap",
        "manufacturer",
        "manhole"
    ],
    "sg:website":"http://www.realpages.com/coleconcrete",
    "wof:name":"Cole Concrete Products Inc",
    "wof:placetype":"venue"
},
  "geometry": {"coordinates":[-84.316315,33.632793],"type":"Point"}
}