{
  "type": "Feature",
  "properties": {
    "addr:full":"1324 Laney Walker Blvd Augusta GA 30901",
    "addr:housenumber":"1324",
    "addr:postcode":"30901",
    "addr:street":"Laney Walker Blvd",
    "iso:country":"US",
    "sg:address":"1324 Laney Walker Blvd",
    "sg:city":"Augusta",
    "sg:classifiers":[
        {
            "category":"Education",
            "subcategory":"School",
            "type":"Public Place"
        }
    ],
    "sg:phone":"+1 706 823 6933",
    "sg:postcode":"30901",
    "sg:province":"GA",
    "sg:website":"http://www.richmond.k12.ga.us",
    "wof:name":"Magnet High School",
    "wof:placetype":"venue"
},
  "geometry": {"coordinates":[-81.981965,33.466631],"type":"Point"}
}