{
  "type": "Feature",
  "properties": {
    "addr:full":"123 Huddleston Rd Peachtree City GA 30269",
    "addr:housenumber":"123",
    "addr:postcode":"30269",
    "addr:street":"Huddleston Rd",
    "iso:country":"US",
    "sg:address":"123 Huddleston Rd",
    "sg:city":"Peachtree City",
    "sg:classifiers":[
        {
            "category":"Retail",
            "subcategory":"Auto Repair",
            "type":"Services"
        }
    ],
    "sg:phone":"+1 770 486 7650",
    "sg:postcode":"30269",
    "sg:province":"GA",
    "sg:tags":[
        "repairing",
        "automobile"
    ],
    "wof:name":"Mark & Theo's Auto Svc",
    "wof:placetype":"venue"
},
  "geometry": {"coordinates":[-84.596278,33.396553],"type":"Point"}
}