{
  "type": "Feature",
  "properties": {
    "addr:full":"2879 Wood Park Trce NW Kennesaw GA 30152",
    "addr:housenumber":"2879",
    "addr:postcode":"30152",
    "addr:street":"Wood Park Trce Nw",
    "iso:country":"US",
    "sg:address":"2879 Wood Park Trce NW",
    "sg:city":"Kennesaw",
    "sg:classifiers":[
        {
            "category":"Professional",
            "subcategory":"Business Services",
            "type":"Services"
        }
    ],
    "sg:phone":"+1 770 420 9244",
    "sg:postcode":"30152",
    "sg:province":"GA",
    "wof:name":"Homewise Inspection Servi",
    "wof:placetype":"venue"
},
  "geometry": {"coordinates":[-84.63724499999999,33.984001],"type":"Point"}
}