{
  "type": "Feature",
  "properties": {
    "addr:full":"3110 Arrowhead Dr Gainesville GA 30506",
    "addr:housenumber":"3110",
    "addr:postcode":"30506",
    "addr:street":"Arrowhead Dr",
    "iso:country":"US",
    "sg:address":"3110 Arrowhead Dr",
    "sg:city":"Gainesville",
    "sg:classifiers":[
        {
            "category":"Professional",
            "subcategory":"Art Services",
            "type":"Services"
        }
    ],
    "sg:phone":"+1 678 521 3807",
    "sg:postcode":"30506",
    "sg:province":"GA",
    "sg:tags":[
        "commercial",
        "design"
    ],
    "wof:name":"Hope Graphics & Design",
    "wof:placetype":"venue"
},
  "geometry": {"coordinates":[-83.922375,34.339092],"type":"Point"}
}