{
  "type": "Feature",
  "properties": {
    "addr:full":"1252 North Avenue NE Atlanta GA 30307",
    "addr:housenumber":"1252",
    "addr:postcode":"30307",
    "addr:street":"North Avenue Ne",
    "iso:country":"US",
    "sg:address":"1252 North Avenue NE",
    "sg:city":"Atlanta",
    "sg:classifiers":[
        {
            "category":"Health Services",
            "subcategory":"Doctor",
            "type":"Services"
        }
    ],
    "sg:phone":"+1 404 233 5363",
    "sg:postcode":"30307",
    "sg:province":"GA",
    "wof:name":"Buckhead Sportsmedicine & Spine Center",
    "wof:placetype":"venue"
},
  "geometry": {"coordinates":[-84.345636,33.770973],"type":"Point"}
}