{
  "type": "Feature",
  "properties": {
    "addr:full":"1350 Cameron Glen Dr Marietta GA 30062",
    "addr:housenumber":"1350",
    "addr:postcode":"30062",
    "addr:street":"Cameron Glen Dr",
    "iso:country":"US",
    "sg:address":"1350 Cameron Glen Dr",
    "sg:city":"Marietta",
    "sg:classifiers":[
        {
            "category":"Professional",
            "subcategory":"Management & Consulting",
            "type":"Services"
        }
    ],
    "sg:phone":"+1 770 330 7007",
    "sg:postcode":"30062",
    "sg:province":"GA",
    "wof:name":"Newell Net Works Inc",
    "wof:placetype":"venue"
},
  "geometry": {"coordinates":[-84.51219,33.982407],"type":"Point"}
}