{
  "type": "Feature",
  "properties": {
    "addr:full":"4104 Tate St NE Covington GA 30014",
    "addr:housenumber":"4104",
    "addr:postcode":"30014",
    "addr:street":"Tate St Ne",
    "iso:country":"US",
    "sg:address":"4104 Tate St NE",
    "sg:city":"Covington",
    "sg:classifiers":[
        {
            "category":"Shopping",
            "subcategory":"Pharmacy",
            "type":"Retail Goods"
        }
    ],
    "sg:phone":"+1 770 786 2284",
    "sg:postcode":"30014",
    "sg:province":"GA",
    "sg:tags":[
        "drug",
        "store"
    ],
    "wof:name":"Peoples Drug Stores Inc",
    "wof:placetype":"venue"
},
  "geometry": {"coordinates":[-83.85012500000001,33.600472],"type":"Point"}
}