{
  "type": "Feature",
  "properties": {
    "addr:full":"7019 Mableton Pkwy SE Mableton GA 30126",
    "addr:housenumber":"7019",
    "addr:postcode":"30126",
    "addr:street":"Mableton Pkwy Se",
    "iso:country":"US",
    "sg:address":"7019 Mableton Pkwy SE",
    "sg:city":"Mableton",
    "sg:classifiers":[
        {
            "category":"Manufacturing",
            "subcategory":"Printing",
            "type":"Manufacturing & Wholesale Goods"
        }
    ],
    "sg:phone":"+1 770 941 3131",
    "sg:postcode":"30126",
    "sg:province":"GA",
    "sg:tags":[
        "commercial",
        "offset"
    ],
    "wof:name":"A-1 Printers Inc",
    "wof:placetype":"venue"
},
  "geometry": {"coordinates":[-84.539207,33.782751],"type":"Point"}
}