{
  "type": "Feature",
  "properties": {
    "iso:country":"US",
    "sg:address":"3843 Crest Dr",
    "sg:city":"Hephzibah",
    "sg:classifiers":[
        {
            "category":"Communications",
            "subcategory":"Film & Video Production",
            "type":"Services"
        }
    ],
    "sg:phone":"+1 706 798 5733",
    "sg:postcode":"30815",
    "sg:province":"GA",
    "sg:tags":[
        "motion"
    ],
    "wof:name":"Bam Bam Production",
    "wof:placetype":"venue"
},
  "geometry": {"coordinates":[-82.109247,33.378324],"type":"Point"}
}