{
  "type": "Feature",
  "properties": {
    "addr:full":"2885 Ball Ground Hwy Canton GA 30114",
    "addr:housenumber":"2885",
    "addr:postcode":"30114",
    "addr:street":"Ball Ground Hwy",
    "iso:country":"US",
    "sg:address":"2885 Ball Ground Hwy",
    "sg:city":"Canton",
    "sg:classifiers":[
        {
            "category":"Home & Garden",
            "subcategory":"Carpets & Floor Coverings",
            "type":"Retail Goods"
        }
    ],
    "sg:phone":"+1 770 479 9624",
    "sg:postcode":"30114",
    "sg:province":"GA",
    "wof:name":"Country Carpets",
    "wof:placetype":"venue"
},
  "geometry": {"coordinates":[-84.45338,34.272678],"type":"Point"}
}