{
  "type": "Feature",
  "properties": {
    "iso:country":"US",
    "sg:address":"2607 N Slappey Blvd",
    "sg:city":"Albany",
    "sg:classifiers":[
        {
            "category":"Wholesale",
            "subcategory":"Machinery & Supplies",
            "type":"Manufacturing & Wholesale Goods"
        }
    ],
    "sg:phone":"+1 229 436 7744",
    "sg:postcode":"31701",
    "sg:province":"GA",
    "sg:tags":[
        "equipment",
        "industrial"
    ],
    "wof:name":"Brungart Equipment",
    "wof:placetype":"venue"
},
  "geometry": {"coordinates":[-84.176129,31.613666],"type":"Point"}
}