{
  "type": "Feature",
  "properties": {
    "addr:full":"120 Carnegie Pl Fayetteville GA 30214",
    "addr:housenumber":"120",
    "addr:postcode":"30214",
    "addr:street":"Carnegie Pl",
    "iso:country":"US",
    "sg:address":"120 Carnegie Pl",
    "sg:city":"Fayetteville",
    "sg:classifiers":[
        {
            "category":"Manufacturing",
            "subcategory":"Textiles",
            "type":"Manufacturing & Wholesale Goods"
        }
    ],
    "sg:phone":"+1 770 719 4330",
    "sg:postcode":"30214",
    "sg:province":"GA",
    "sg:tags":[
        "sheet",
        "fabric",
        "mfg",
        "bedding",
        "related",
        "item",
        "other",
        "mill"
    ],
    "wof:name":"Signature Textiles",
    "wof:placetype":"venue"
},
  "geometry": {"coordinates":[-84.429468,33.509439],"type":"Point"}
}