{
  "type": "Feature",
  "properties": {
    "addr:full":"3620 Community Rd Brunswick GA 31520",
    "addr:housenumber":"3620",
    "addr:postcode":"31520",
    "addr:street":"Community Rd",
    "iso:country":"US",
    "sg:address":"3620 Community Rd",
    "sg:city":"Brunswick",
    "sg:classifiers":[
        {
            "category":"Retail",
            "subcategory":"Auto Repair",
            "type":"Services"
        }
    ],
    "sg:phone":"+1 912 261 0111",
    "sg:postcode":"31520",
    "sg:province":"GA",
    "sg:tags":[
        "body",
        "automobile",
        "painting",
        "general"
    ],
    "wof:name":"Advanced Collision Center Inc",
    "wof:placetype":"venue"
},
  "geometry": {"coordinates":[-81.495924,31.202606],"type":"Point"}
}