{
  "type": "Feature",
  "properties": {
    "addr:full":"1919 Chambers Rd Mc Donough GA 30253",
    "addr:housenumber":"1919",
    "addr:postcode":"30253",
    "addr:street":"Chambers Rd",
    "iso:country":"US",
    "sg:address":"1919 Chambers Rd",
    "sg:city":"Mc Donough",
    "sg:classifiers":[
        {
            "category":"Building & Trades",
            "subcategory":"Construction",
            "type":"Services"
        }
    ],
    "sg:phone":"+1 770 914 0879",
    "sg:postcode":"30253",
    "sg:province":"GA",
    "sg:tags":[
        "house"
    ],
    "wof:name":"Burdette Remodeling",
    "wof:placetype":"venue"
},
  "geometry": {"coordinates":[-84.230256,33.469271],"type":"Point"}
}