{
  "type": "Feature",
  "properties": {
    "addr:full":"207 W Harris St Pine Mountain GA 31822",
    "addr:housenumber":"207",
    "addr:postcode":"31822",
    "addr:street":"W Harris St",
    "iso:country":"US",
    "sg:address":"207 W Harris St",
    "sg:city":"Pine Mountain",
    "sg:classifiers":[
        {
            "category":"Travel",
            "subcategory":"Hotels & Motels",
            "type":"Entertainment"
        }
    ],
    "sg:phone":"+1 706 663 9801",
    "sg:postcode":"31822",
    "sg:province":"GA",
    "sg:tags":[
        "breakfast",
        "accommodation",
        "bed"
    ],
    "wof:name":"Chipley-Murrah House B & B",
    "wof:placetype":"venue"
},
  "geometry": {"coordinates":[-84.85517,32.8645],"type":"Point"}
}