{
  "type": "Feature",
  "properties": {
    "iso:country":"US",
    "sg:address":"420 Sycamore St",
    "sg:city":"Decatur",
    "sg:classifiers":[
        {
            "category":"Health Services",
            "subcategory":"Doctor",
            "type":"Services"
        }
    ],
    "sg:phone":"+1 404 373 0162",
    "sg:postcode":"30030",
    "sg:province":"GA",
    "wof:name":"John G Herbert, MD",
    "wof:placetype":"venue"
},
  "geometry": {"coordinates":[-84.290802,33.774502],"type":"Point"}
}