{
  "type": "Feature",
  "properties": {
    "iso:country":"US",
    "sg:address":"1697 Woodland Ave SE",
    "sg:city":"Atlanta",
    "sg:classifiers":[
        {
            "category":"Building & Trades",
            "subcategory":"Pest Control",
            "type":"Services"
        }
    ],
    "sg:phone":"+1 404 622 6326",
    "sg:postcode":"30315",
    "sg:province":"GA",
    "wof:name":"Leachel Pest Control",
    "wof:placetype":"venue"
},
  "geometry": {"coordinates":[-84.35191399999999,33.707831],"type":"Point"}
}