{
  "type": "Feature",
  "properties": {
    "iso:country":"US",
    "sg:address":"2101 Chatham Dr",
    "sg:city":"Dalton",
    "sg:classifiers":[
        {
            "category":"Professional",
            "type":"Services"
        }
    ],
    "sg:phone":"+1 706 278 4779",
    "sg:postcode":"30720",
    "sg:province":"GA",
    "wof:name":"Cindy & Sam OBrien",
    "wof:placetype":"venue"
},
  "geometry": {"coordinates":[-84.995043,34.809649],"type":"Point"}
}