{
  "type": "Feature",
  "properties": {
    "iso:country":"US",
    "sg:address":"3985 Metcalf Beachton Rd",
    "sg:city":"Thomasville",
    "sg:classifiers":[
        {
            "category":"Organizations",
            "subcategory":"Religious Organization",
            "type":"Services"
        }
    ],
    "sg:phone":"+1 229 226 3953",
    "sg:postcode":"31792",
    "sg:province":"GA",
    "wof:name":"Antioch Mssonary Baptst Church",
    "wof:placetype":"venue"
},
  "geometry": {"coordinates":[-84.037811,30.708526],"type":"Point"}
}