{
  "type": "Feature",
  "properties": {
    "iso:country":"US",
    "sg:address":"4356 Stonington Cir",
    "sg:city":"Atlanta",
    "sg:classifiers":[
        {
            "category":"Manufacturing",
            "subcategory":"Paper Products",
            "type":"Manufacturing & Wholesale Goods"
        }
    ],
    "sg:phone":"+1 770 457 8391",
    "sg:postcode":"30338",
    "sg:province":"GA",
    "sg:tags":[
        "paper-wholesale",
        "manufacturer"
    ],
    "wof:name":"Air Force Photo Mapping Associaton",
    "wof:placetype":"venue"
},
  "geometry": {"coordinates":[-84.286573,33.923971],"type":"Point"}
}