{
  "type": "Feature",
  "properties": {
    "addr:full":"15 W 55th St Savannah GA 31405",
    "addr:housenumber":"15",
    "addr:postcode":"31405",
    "addr:street":"W 55Th St",
    "iso:country":"US",
    "sg:address":"15 W 55th St",
    "sg:city":"Savannah",
    "sg:classifiers":[
        {
            "category":"Retail",
            "subcategory":"Auto Repair",
            "type":"Services"
        }
    ],
    "sg:phone":"+1 912 233 7295",
    "sg:postcode":"31405",
    "sg:province":"GA",
    "sg:tags":[
        "automotive"
    ],
    "wof:name":"Wells Towing & Auto Repair",
    "wof:placetype":"venue"
},
  "geometry": {"coordinates":[-81.106837,32.043807],"type":"Point"}
}