{
  "type": "Feature",
  "properties": {
    "addr:full":"2255 Hwy 42 N Mcdonough GA 30253",
    "addr:housenumber":"2255",
    "addr:postcode":"30253",
    "addr:street":"Hwy 42 N",
    "iso:country":"US",
    "sg:address":"2255 Hwy 42 N",
    "sg:city":"Mcdonough",
    "sg:classifiers":[
        {
            "category":"Building & Trades",
            "subcategory":"Plumbing",
            "type":"Services"
        }
    ],
    "sg:phone":"+1 770 507 3990",
    "sg:postcode":"30253",
    "sg:province":"GA",
    "sg:tags":[
        "conditioning",
        "air",
        "system",
        "contractor"
    ],
    "wof:name":"Logan Heating & Air",
    "wof:placetype":"venue"
},
  "geometry": {"coordinates":[-84.186649,33.50572],"type":"Point"}
}