{
  "type": "Feature",
  "properties": {
    "iso:country":"US",
    "sg:address":"4200 Wade Green Rd NW",
    "sg:city":"Kennesaw",
    "sg:classifiers":[
        {
            "category":"Shopping",
            "subcategory":"Jewelry",
            "type":"Retail Goods"
        },
        {
            "category":"Manufacturing",
            "subcategory":"Jewelry",
            "type":"Manufacturing & Wholesale Goods"
        },
        {
            "category":"Retail",
            "subcategory":"Repair Shop",
            "type":"Services"
        }
    ],
    "sg:phone":"+1 770 422 0845",
    "sg:postcode":"30144",
    "sg:province":"GA",
    "sg:tags":[
        "repairing",
        "diamond",
        "gold",
        "watch",
        "platinum",
        "buyer",
        "jeweler",
        "silver"
    ],
    "sg:website":"http://www.diamondsrforever.net",
    "wof:name":"Diamonds R Forever",
    "wof:placetype":"venue"
},
  "geometry": {"coordinates":[-84.59329200000001,34.055061],"type":"Point"}
}