{
  "type": "Feature",
  "properties": {
    "iso:country":"US",
    "sg:address":"102 Trickum Hills Dr",
    "sg:city":"Woodstock",
    "sg:classifiers":[
        {
            "category":"Organizations",
            "subcategory":"Labor Organization",
            "type":"Services"
        }
    ],
    "sg:phone":"+1 770 517 9239",
    "sg:postcode":"30188",
    "sg:province":"GA",
    "wof:name":"Local Connections Inc",
    "wof:placetype":"venue"
},
  "geometry": {"coordinates":[-84.48570599999999,34.079222],"type":"Point"}
}