{
  "type": "Feature",
  "properties": {
    "addr:full":"102 S Belair Rd Martinez GA 30907",
    "addr:housenumber":"102",
    "addr:postcode":"30907",
    "addr:street":"S Belair Rd",
    "iso:country":"US",
    "sg:address":"102 S Belair Rd",
    "sg:city":"Martinez",
    "sg:classifiers":[
        {
            "category":"Food & Beverages",
            "subcategory":"Liquor & Beverages",
            "type":"Retail Goods"
        }
    ],
    "sg:phone":"+1 706 868 8382",
    "sg:postcode":"30907",
    "sg:province":"GA",
    "wof:name":"Ok Wine & Spirits",
    "wof:placetype":"venue"
},
  "geometry": {"coordinates":[-82.141423,33.506659],"type":"Point"}
}