{
  "type": "Feature",
  "properties": {
    "addr:full":"5652 Fulton Industrial Blvd SW Atlanta GA 30336",
    "addr:housenumber":"5652",
    "addr:postcode":"30336",
    "addr:street":"Fulton Industrial Blvd Sw",
    "iso:country":"US",
    "sg:address":"5652 Fulton Industrial Blvd SW",
    "sg:city":"Atlanta",
    "sg:classifiers":[
        {
            "category":"Building & Trades",
            "subcategory":"Locksmith",
            "type":"Services"
        }
    ],
    "sg:phone":"+1 678 271 6231",
    "sg:postcode":"30336",
    "sg:province":"GA",
    "sg:tags":[
        "key"
    ],
    "wof:name":"24 Hour Locksmith",
    "wof:placetype":"venue"
},
  "geometry": {"coordinates":[-84.570829,33.73067],"type":"Point"}
}