{
  "type": "Feature",
  "properties": {
    "iso:country":"US",
    "sg:address":"444 Plum St",
    "sg:city":"Macon",
    "sg:classifiers":[
        {
            "category":"Building & Trades",
            "subcategory":"Electrical",
            "type":"Services"
        }
    ],
    "sg:phone":"+1 478 745 5400",
    "sg:postcode":"31201",
    "sg:province":"GA",
    "sg:tags":[
        "repair",
        "generators-electric-service",
        "e",
        "contractor"
    ],
    "sg:website":"http://www.metropower.com",
    "wof:name":"Macon Power",
    "wof:placetype":"venue"
},
  "geometry": {"coordinates":[-83.62882999999999,32.832528],"type":"Point"}
}