{
  "type": "Feature",
  "properties": {
    "iso:country":"US",
    "sg:address":"107 Southside Dr",
    "sg:city":"Tifton",
    "sg:classifiers":[
        {
            "category":"Building & Trades",
            "subcategory":"Cleaning & Sanitation",
            "type":"Services"
        }
    ],
    "sg:phone":"+1 229 382 4578",
    "sg:postcode":"31794",
    "sg:province":"GA",
    "sg:tags":[
        "janitor"
    ],
    "wof:name":"Golson's Enterprises Inc",
    "wof:placetype":"venue"
},
  "geometry": {"coordinates":[-83.498124,31.447182],"type":"Point"}
}