{
  "type": "Feature",
  "properties": {
    "iso:country":"US",
    "sg:address":"1506 Brookridge Dr",
    "sg:city":"Woodstock",
    "sg:classifiers":[
        {
            "category":"Real Estate",
            "subcategory":"Real Estate Agent",
            "type":"Services"
        }
    ],
    "sg:phone":"+1 770 924 8421",
    "sg:postcode":"30189",
    "sg:province":"GA",
    "sg:website":"www.singletonrealestate.com",
    "wof:name":"Singleton & Co Real Estate",
    "wof:placetype":"venue"
},
  "geometry": {"coordinates":[-84.571412,34.124485],"type":"Point"}
}