{
  "type": "Feature",
  "properties": {
    "addr:full":"4540 Atwater Ct Buford GA 30519",
    "addr:housenumber":"4540",
    "addr:postcode":"30519",
    "addr:street":"Atwater Ct",
    "iso:country":"US",
    "sg:address":"4540 Atwater Ct",
    "sg:city":"Buford",
    "sg:classifiers":[
        {
            "category":"Professional",
            "type":"Services"
        }
    ],
    "sg:phone":"+1 678 482 1788",
    "sg:postcode":"30519",
    "sg:province":"GA",
    "sg:tags":[
        "establishment"
    ],
    "wof:name":"World Auto Group",
    "wof:placetype":"venue"
},
  "geometry": {"coordinates":[-84.01559,34.09895],"type":"Point"}
}