{
  "type": "Feature",
  "properties": {
    "addr:full":"3830 Washington Rd Augusta GA 30907",
    "addr:housenumber":"3830",
    "addr:postcode":"30907",
    "addr:street":"Washington Rd",
    "iso:country":"US",
    "sg:address":"3830 Washington Rd",
    "sg:city":"Augusta",
    "sg:classifiers":[
        {
            "category":"Banks & Credit Unions",
            "subcategory":"Bank",
            "type":"Services"
        }
    ],
    "sg:phone":"+1 706 210 9510",
    "sg:postcode":"30907",
    "sg:province":"GA",
    "sg:tags":[
        "financing"
    ],
    "wof:name":"Security Finance Corp",
    "wof:placetype":"venue"
},
  "geometry": {"coordinates":[-82.093378,33.511123],"type":"Point"}
}