{
  "type": "Feature",
  "properties": {
    "iso:country":"US",
    "sg:address":"3313 Artesia Dr",
    "sg:city":"Clarkston",
    "sg:classifiers":[
        {
            "category":"Professional",
            "type":"Services"
        }
    ],
    "sg:phone":"+1 404 389 0413",
    "sg:postcode":"30021",
    "sg:province":"GA",
    "wof:name":"Jemal Aytac",
    "wof:placetype":"venue"
},
  "geometry": {"coordinates":[-84.25277,33.808109],"type":"Point"}
}