{
  "type": "Feature",
  "properties": {
    "addr:full":"500 Avenue A SW Rome GA 30165",
    "addr:housenumber":"500",
    "addr:postcode":"ga 30165",
    "addr:street":"Avenue A Sw",
    "iso:country":"US",
    "sg:address":"500 Avenue A SW",
    "sg:city":"Rome",
    "sg:classifiers":[
        {
            "category":"Personal",
            "subcategory":"Beauty Salon",
            "type":"Services"
        }
    ],
    "sg:phone":"+1 706 291 6080",
    "sg:postcode":"30165",
    "sg:province":"GA",
    "wof:name":"Carriage House Beauty Shop",
    "wof:placetype":"venue"
},
  "geometry": {"coordinates":[-85.17366,34.258438],"type":"Point"}
}