{
  "type": "Feature",
  "properties": {
    "addr:full":"1755 Watson Blvd Warner Robins GA 31093",
    "addr:housenumber":"1755",
    "addr:postcode":"31093",
    "addr:street":"Watson Blvd",
    "iso:country":"US",
    "sg:address":"1755 Watson Blvd",
    "sg:city":"Warner Robins",
    "sg:classifiers":[
        {
            "category":"Shopping",
            "subcategory":"Pawn Shop",
            "type":"Retail Goods"
        }
    ],
    "sg:phone":"+1 478 923 3628",
    "sg:postcode":"31093",
    "sg:province":"GA",
    "sg:website":"www.titlecash.com",
    "wof:name":"Ez Title Pawn Inc",
    "wof:placetype":"venue"
},
  "geometry": {"coordinates":[-83.636101,32.618099],"type":"Point"}
}