{
  "type": "Feature",
  "properties": {
    "addr:full":"626 Glen Crest Way Stone Mountain GA 30087",
    "addr:housenumber":"626",
    "addr:postcode":"30087",
    "addr:street":"Glen Crest Way",
    "iso:country":"US",
    "sg:address":"626 Glen Crest Way",
    "sg:city":"Stone Mountain",
    "sg:classifiers":[
        {
            "category":"Insurance",
            "subcategory":"Insurance Agent",
            "type":"Services"
        }
    ],
    "sg:phone":"+1 770 413 2274",
    "sg:postcode":"30087",
    "sg:province":"GA",
    "wof:name":"Allstate Insurance",
    "wof:placetype":"venue"
},
  "geometry": {"coordinates":[-84.14789399999999,33.777525],"type":"Point"}
}