{
  "type": "Feature",
  "properties": {
    "addr:full":"123 Westview St Canton GA 30114",
    "addr:housenumber":"123",
    "addr:postcode":"30114",
    "addr:street":"Westview St",
    "iso:country":"US",
    "sg:address":"123 Westview St",
    "sg:city":"Canton",
    "sg:classifiers":[
        {
            "category":"Real Estate",
            "subcategory":"Real Estate Agent",
            "type":"Services"
        }
    ],
    "sg:phone":"+1 770 479 5787",
    "sg:postcode":"30114",
    "sg:province":"GA",
    "wof:name":"Ojs Properties Inc",
    "wof:placetype":"venue"
},
  "geometry": {"coordinates":[-84.49911899999999,34.240558],"type":"Point"}
}