{
  "type": "Feature",
  "properties": {
    "iso:country":"US",
    "sg:address":"10 Andrew Dr",
    "sg:city":"Stockbridge",
    "sg:classifiers":[
        {
            "category":"Home & Garden",
            "subcategory":"Home Furnishings",
            "type":"Retail Goods"
        }
    ],
    "sg:phone":"+1 770 507 0709",
    "sg:postcode":"30281",
    "sg:province":"GA",
    "sg:tags":[
        "pottery"
    ],
    "wof:name":"Allisons Pottery & Crmc Supply",
    "wof:placetype":"venue"
},
  "geometry": {"coordinates":[-84.241991,33.499707],"type":"Point"}
}