{
  "type": "Feature",
  "properties": {
    "addr:full":"4940 Atlanta Hwy Alpharetta GA 30004",
    "addr:housenumber":"4940",
    "addr:postcode":"30004",
    "addr:street":"Atlanta Hwy",
    "iso:country":"US",
    "sg:address":"4940 Atlanta Hwy",
    "sg:city":"Alpharetta",
    "sg:classifiers":[
        {
            "category":"Insurance",
            "subcategory":"Hazard Insurance",
            "type":"Services"
        },
        {
            "category":"Insurance",
            "subcategory":"Insurance Agent",
            "type":"Services"
        },
        {
            "category":"Insurance",
            "subcategory":"Life Insurance",
            "type":"Services"
        }
    ],
    "sg:phone":"+1 610 692 4438",
    "sg:postcode":"30004",
    "sg:province":"GA",
    "sg:tags":[
        "auto"
    ],
    "sg:website":"http://statefarm.mqgroup.com/url.asp?usr=112007",
    "wof:name":"Gupton, Mark - State Farm Insurance Agent",
    "wof:placetype":"venue"
},
  "geometry": {"coordinates":[-84.239402,34.15787],"type":"Point"}
}