{
  "type": "Feature",
  "properties": {
    "addr:full":"1034 Ironwood Dr Grayson GA 30017",
    "addr:housenumber":"1034",
    "addr:postcode":"30017",
    "addr:street":"Ironwood Dr",
    "iso:country":"US",
    "sg:address":"1034 Ironwood Dr",
    "sg:city":"Grayson",
    "sg:classifiers":[
        {
            "category":"Professional",
            "type":"Services"
        }
    ],
    "sg:phone":"+1 770 978 6279",
    "sg:postcode":"30017",
    "sg:province":"GA",
    "wof:name":"Thomas Bros Bldrs",
    "wof:placetype":"venue"
},
  "geometry": {"coordinates":[-83.988899,33.902356],"type":"Point"}
}