{
  "type": "Feature",
  "properties": {
    "addr:full":"718 Prospect Rd Rockmart GA 30153",
    "addr:housenumber":"718",
    "addr:postcode":"30153",
    "addr:street":"Prospect Rd",
    "iso:country":"US",
    "sg:address":"718 Prospect Rd",
    "sg:city":"Rockmart",
    "sg:classifiers":[
        {
            "category":"Building & Trades",
            "subcategory":"Electrical",
            "type":"Services"
        }
    ],
    "sg:phone":"+1 770 684 6779",
    "sg:postcode":"30153",
    "sg:province":"GA",
    "sg:tags":[
        "electrical",
        "contractor"
    ],
    "wof:name":"Dukes Electric",
    "wof:placetype":"venue"
},
  "geometry": {"coordinates":[-85.069571,34.024312],"type":"Point"}
}