{
  "type": "Feature",
  "properties": {
    "iso:country":"US",
    "sg:address":"4514 Chamblee Dunwoody Rd",
    "sg:city":"Atlanta",
    "sg:classifiers":[
        {
            "category":"Restaurant",
            "type":"Food & Drink"
        }
    ],
    "sg:phone":"+1 770 458 6122",
    "sg:postcode":"30338",
    "sg:province":"GA",
    "sg:tags":[
        "eating"
    ],
    "wof:name":"Garcia's Mexican Restaurant",
    "wof:placetype":"venue"
},
  "geometry": {"coordinates":[-84.314318,33.92266],"type":"Point"}
}