{
  "type": "Feature",
  "properties": {
    "addr:full":"134 Panola Rd Ellenwood GA 30294",
    "addr:housenumber":"134",
    "addr:postcode":"30294",
    "addr:street":"Panola Rd",
    "iso:country":"US",
    "sg:address":"134 Panola Rd",
    "sg:city":"Ellenwood",
    "sg:classifiers":[
        {
            "category":"Professional",
            "subcategory":"Engineering",
            "type":"Services"
        }
    ],
    "sg:phone":"+1 678 418 7890",
    "sg:postcode":"30294",
    "sg:province":"GA",
    "sg:tags":[
        "design",
        "engineer"
    ],
    "wof:name":"Precision Engineering & Design",
    "wof:placetype":"venue"
},
  "geometry": {"coordinates":[-84.18999599999999,33.644627],"type":"Point"}
}