{
  "type": "Feature",
  "properties": {
    "addr:full":"405 W Huntington Rd Athens GA 30606",
    "addr:housenumber":"405",
    "addr:postcode":"30606",
    "addr:street":"W Huntington Rd",
    "iso:country":"US",
    "sg:address":"405 W Huntington Rd",
    "sg:city":"Athens",
    "sg:classifiers":[
        {
            "category":"Professional",
            "subcategory":"Accounting & Tax Preparation",
            "type":"Services"
        }
    ],
    "sg:phone":"+1 706 353 3081",
    "sg:postcode":"30606",
    "sg:province":"GA",
    "sg:tags":[
        "accountant"
    ],
    "wof:name":"Arthur Smith & Co",
    "wof:placetype":"venue"
},
  "geometry": {"coordinates":[-83.463553,33.949513],"type":"Point"}
}