{
  "type": "Feature",
  "properties": {
    "iso:country":"US",
    "sg:address":"1135 Gables Dr NE",
    "sg:city":"Atlanta",
    "sg:classifiers":[
        {
            "category":"Manufacturing",
            "subcategory":"Buildings",
            "type":"Manufacturing & Wholesale Goods"
        },
        {
            "category":"Professional",
            "type":"Services"
        },
        {
            "category":"Personal",
            "type":"Services"
        }
    ],
    "sg:phone":"+1 404 822 6703",
    "sg:postcode":"30319",
    "sg:province":"GA",
    "sg:tags":[
        "full",
        "house",
        "material",
        "storage",
        "moving",
        "services-labor",
        "mover",
        "raising"
    ],
    "wof:name":"Atlanta Promove",
    "wof:placetype":"venue"
},
  "geometry": {"coordinates":[-84.344632,33.84634],"type":"Point"}
}