{
  "type": "Feature",
  "properties": {
    "iso:country":"US",
    "sg:address":"426 Epps Bridge Pkwy",
    "sg:city":"Athens",
    "sg:classifiers":[
        {
            "category":"Personal",
            "subcategory":"Nail Salon",
            "type":"Services"
        }
    ],
    "sg:phone":"+1 706 353 1787",
    "sg:postcode":"30606",
    "sg:province":"GA",
    "wof:name":"California Creations-Athens",
    "wof:placetype":"venue"
},
  "geometry": {"coordinates":[-83.43263,33.938837],"type":"Point"}
}