{
  "type": "Feature",
  "properties": {
    "addr:full":"11 The Fairway Woodstock GA 30188",
    "addr:housenumber":"11",
    "addr:postcode":"30188",
    "addr:street":"The Fairway",
    "iso:country":"US",
    "sg:address":"11 The Fairway",
    "sg:city":"Woodstock",
    "sg:classifiers":[
        {
            "category":"Professional",
            "type":"Services"
        }
    ],
    "sg:phone":"+1 770 751 0574",
    "sg:postcode":"30188",
    "sg:province":"GA",
    "wof:name":"Donald & Carol Mitchum",
    "wof:placetype":"venue"
},
  "geometry": {"coordinates":[-84.362306,34.136825],"type":"Point"}
}