{
  "type": "Feature",
  "properties": {
    "iso:country":"US",
    "sg:address":"2676 Baker Ridge Dr NW",
    "sg:city":"Atlanta",
    "sg:classifiers":[
        {
            "category":"Place Of Worship",
            "subcategory":"Church",
            "type":"Public Place"
        },
        {
            "category":"Place Of Worship",
            "type":"Public Place"
        }
    ],
    "sg:phone":"+1 404 799 9235",
    "sg:postcode":"30318",
    "sg:province":"GA",
    "sg:tags":[
        "christ",
        "churches-community"
    ],
    "wof:name":"Vision Of Hope Community Church",
    "wof:placetype":"venue"
},
  "geometry": {"coordinates":[-84.475645,33.768256],"type":"Point"}
}