{
  "type": "Feature",
  "properties": {
    "iso:country":"US",
    "sg:address":"1509 Virginia Ave",
    "sg:city":"Atlanta",
    "sg:classifiers":[
        {
            "category":"Food & Beverages",
            "subcategory":"Groceries & Convenience Stores",
            "type":"Retail Goods"
        }
    ],
    "sg:phone":"+1 404 768 7777",
    "sg:postcode":"30337",
    "sg:province":"GA",
    "wof:name":"Stop and Save Food Mart",
    "wof:placetype":"venue"
},
  "geometry": {"coordinates":[-84.43856100000001,33.659407],"type":"Point"}
}