{
  "type": "Feature",
  "properties": {
    "iso:country":"US",
    "sg:address":"4760 Leo Pl",
    "sg:city":"Macon",
    "sg:classifiers":[
        {
            "category":"Professional",
            "subcategory":"Computer Services",
            "type":"Services"
        }
    ],
    "sg:phone":"+1 478 318 2954",
    "sg:postcode":"31210",
    "sg:province":"GA",
    "sg:tags":[
        "programing",
        "custom"
    ],
    "sg:website":"www.slatersolutions.com",
    "wof:name":"Slater Solutions",
    "wof:placetype":"venue"
},
  "geometry": {"coordinates":[-83.71544,32.893693],"type":"Point"}
}