{
  "type": "Feature",
  "properties": {
    "iso:country":"US",
    "sg:address":"150 Elysian Way NW",
    "sg:city":"Atlanta",
    "sg:classifiers":[
        {
            "category":"Professional",
            "subcategory":"Business Services",
            "type":"Services"
        }
    ],
    "sg:phone":"+1 404 355 7575",
    "sg:postcode":"30327",
    "sg:province":"GA",
    "wof:name":"Lucretia Arpad Interiors",
    "wof:placetype":"venue"
},
  "geometry": {"coordinates":[-84.423727,33.822239],"type":"Point"}
}