{
  "type": "Feature",
  "properties": {
    "iso:country":"US",
    "sg:address":"306 Glenn Milner Blvd",
    "sg:city":"Rome",
    "sg:classifiers":[
        {
            "category":"Utilities",
            "subcategory":"Mobile Phone",
            "type":"Services"
        }
    ],
    "sg:phone":"+1 706 235 1700",
    "sg:postcode":"30161",
    "sg:province":"GA",
    "sg:tags":[
        "paging"
    ],
    "wof:name":"Metrocall Holdings Inc",
    "wof:placetype":"venue"
},
  "geometry": {"coordinates":[-85.16679499999999,34.249352],"type":"Point"}
}