{
  "type": "Feature",
  "properties": {
    "addr:full":"903 Cordele Rd Albany GA 31705",
    "addr:housenumber":"903",
    "addr:postcode":"31705",
    "addr:street":"Cordele Rd",
    "iso:country":"US",
    "sg:address":"903 Cordele Rd",
    "sg:city":"Albany",
    "sg:classifiers":[
        {
            "category":"Manufacturing",
            "subcategory":"Metals",
            "type":"Manufacturing & Wholesale Goods"
        },
        {
            "category":"Manufacturing",
            "subcategory":"Building Materials",
            "type":"Manufacturing & Wholesale Goods"
        }
    ],
    "sg:phone":"+1 229 436 0144",
    "sg:postcode":"31705",
    "sg:province":"GA",
    "sg:tags":[
        "fabricator",
        "work",
        "sheet"
    ],
    "wof:name":"Coston Sheet Metal Works",
    "wof:placetype":"venue"
},
  "geometry": {"coordinates":[-84.06535,31.59472],"type":"Point"}
}