{
  "type": "Feature",
  "properties": {
    "addr:full":"6515 Spout Springs Rd Flowery Branch GA 30542",
    "addr:housenumber":"6515",
    "addr:postcode":"30542",
    "addr:street":"Spout Springs Rd",
    "iso:country":"US",
    "sg:address":"6515 Spout Springs Rd",
    "sg:city":"Flowery Branch",
    "sg:classifiers":[
        {
            "category":"Building & Trades",
            "subcategory":"Electrical",
            "type":"Services"
        }
    ],
    "sg:phone":"+1 770 967 1472",
    "sg:postcode":"30542",
    "sg:province":"GA",
    "sg:tags":[
        "electrical"
    ],
    "wof:name":"Moores Electrical Cnstr Co",
    "wof:placetype":"venue"
},
  "geometry": {"coordinates":[-83.89281200000001,34.151372],"type":"Point"}
}