{
  "type": "Feature",
  "properties": {
    "addr:full":"315 Coates Rd Hinesville GA 31313",
    "addr:housenumber":"315",
    "addr:postcode":"31313",
    "addr:street":"Coates Rd",
    "iso:country":"US",
    "sg:address":"315 Coates Rd",
    "sg:city":"Hinesville",
    "sg:classifiers":[
        {
            "category":"Education",
            "subcategory":"School",
            "type":"Public Place"
        }
    ],
    "sg:phone":"+1 912 368 3114",
    "sg:postcode":"31313",
    "sg:province":"GA",
    "sg:website":"www.liberty.k12.ga.us",
    "wof:name":"Joseph Martin Elementary Schl",
    "wof:placetype":"venue"
},
  "geometry": {"coordinates":[-81.580519,31.865068],"type":"Point"}
}