{
  "type": "Feature",
  "properties": {
    "iso:country":"US",
    "sg:address":"916 Lafayette Rd",
    "sg:city":"Rossville",
    "sg:classifiers":[
        {
            "category":"Professional",
            "subcategory":"Accounting & Tax Preparation",
            "type":"Services"
        }
    ],
    "sg:phone":"+1 706 861 5477",
    "sg:postcode":"30741",
    "sg:province":"GA",
    "sg:tags":[
        "accountant"
    ],
    "wof:name":"T & T Tax Svc",
    "wof:placetype":"venue"
},
  "geometry": {"coordinates":[-85.269305,34.884005],"type":"Point"}
}