{
  "type": "Feature",
  "properties": {
    "iso:country":"US",
    "sg:address":"1058 Claussen Rd",
    "sg:city":"Augusta",
    "sg:classifiers":[
        {
            "category":"Shopping",
            "subcategory":"Clothing, Apparel, & Fashions",
            "type":"Retail Goods"
        }
    ],
    "sg:phone":"+1 716 297 4911",
    "sg:postcode":"30907",
    "sg:province":"GA",
    "wof:name":"Forlmerly John Henry & Friends",
    "wof:placetype":"venue"
},
  "geometry": {"coordinates":[-82.03380199999999,33.520946],"type":"Point"}
}