{
  "type": "Feature",
  "properties": {
    "iso:country":"US",
    "sg:address":"4954 High Point Rd NE",
    "sg:city":"Atlanta",
    "sg:classifiers":[
        {
            "category":"Home & Garden",
            "subcategory":"Household Appliances",
            "type":"Retail Goods"
        },
        {
            "category":"Wholesale",
            "subcategory":"Durable Goods & Equipment",
            "type":"Manufacturing & Wholesale Goods"
        }
    ],
    "sg:phone":"+1 770 477 0426",
    "sg:postcode":"30342",
    "sg:province":"GA",
    "sg:tags":[
        "appliances-major-wholesale",
        "major",
        "manufacturer"
    ],
    "wof:name":"Whirlpool Appliance Repair & Service Tod",
    "wof:placetype":"venue"
},
  "geometry": {"coordinates":[-84.36769700000001,33.889978],"type":"Point"}
}