{
  "type": "Feature",
  "properties": {
    "addr:full":"3973 Atlanta Hwy Loganville GA 30052",
    "addr:housenumber":"3973",
    "addr:postcode":"30052",
    "addr:street":"Atlanta Hwy",
    "iso:country":"US",
    "sg:address":"3973 Atlanta Hwy",
    "sg:city":"Loganville",
    "sg:classifiers":[
        {
            "category":"Health Services",
            "subcategory":"Medical Lab",
            "type":"Services"
        }
    ],
    "sg:phone":"+1 770 554 2442",
    "sg:postcode":"30052",
    "sg:province":"GA",
    "sg:tags":[
        "laboratory"
    ],
    "wof:name":"Dental Arts",
    "wof:placetype":"venue"
},
  "geometry": {"coordinates":[-83.913853,33.847742],"type":"Point"}
}