{
  "type": "Feature",
  "properties": {
    "iso:country":"US",
    "sg:address":"420 Hollyberry Dr",
    "sg:city":"Roswell",
    "sg:classifiers":[
        {
            "category":"Building & Trades",
            "subcategory":"Construction",
            "type":"Services"
        }
    ],
    "sg:phone":"+1 770 640 1381",
    "sg:postcode":"30076",
    "sg:province":"GA",
    "sg:tags":[
        "general",
        "contractor"
    ],
    "wof:name":"Gulf South Construction Inc",
    "wof:placetype":"venue"
},
  "geometry": {"coordinates":[-84.35027100000001,34.056532],"type":"Point"}
}