{
  "type": "Feature",
  "properties": {
    "addr:full":"5071 Post Road Ct Stone Mountain GA 30088",
    "addr:housenumber":"5071",
    "addr:postcode":"30088",
    "addr:street":"Post Road Ct",
    "iso:country":"US",
    "sg:address":"5071 Post Road Ct",
    "sg:city":"Stone Mountain",
    "sg:classifiers":[
        {
            "category":"Building & Trades",
            "subcategory":"Construction",
            "type":"Services"
        }
    ],
    "sg:phone":"+1 770 879 6312",
    "sg:postcode":"30088",
    "sg:province":"GA",
    "sg:tags":[
        "residential"
    ],
    "wof:name":"MSE Ultimate Inc",
    "wof:placetype":"venue"
},
  "geometry": {"coordinates":[-84.184105,33.770383],"type":"Point"}
}