{
  "type": "Feature",
  "properties": {
    "addr:full":"1084 Victoria St NE Atlanta GA 30319",
    "addr:housenumber":"1084",
    "addr:postcode":"30319",
    "addr:street":"Victoria St Ne",
    "iso:country":"US",
    "sg:address":"1084 Victoria St NE",
    "sg:city":"Atlanta",
    "sg:classifiers":[
        {
            "category":"Building & Trades",
            "subcategory":"Construction",
            "type":"Services"
        }
    ],
    "sg:phone":"+1 404 255 0390",
    "sg:postcode":"30319",
    "sg:province":"GA",
    "sg:tags":[
        "company"
    ],
    "wof:name":"User Construction",
    "wof:placetype":"venue"
},
  "geometry": {"coordinates":[-84.343711,33.882077],"type":"Point"}
}