{
  "type": "Feature",
  "properties": {
    "addr:full":"17 Augusta Dr Newnan GA 30263",
    "addr:postcode":"30263",
    "addr:street":"17 Augusta Dr",
    "iso:country":"US",
    "sg:address":"17 Augusta Dr",
    "sg:city":"Newnan",
    "sg:classifiers":[
        {
            "category":"Professional",
            "subcategory":"Business Services",
            "type":"Services"
        }
    ],
    "sg:phone":"+1 770 254 1130",
    "sg:postcode":"30263",
    "sg:province":"GA",
    "sg:tags":[
        "packaging"
    ],
    "sg:website":"www.multecpkging.com",
    "wof:name":"Multec Industrial Packaging",
    "wof:placetype":"venue"
},
  "geometry": {"coordinates":[-84.798164,33.379739],"type":"Point"}
}