{
  "type": "Feature",
  "properties": {
    "iso:country":"US",
    "sg:address":"1002 Kingsland Dr",
    "sg:city":"Folkston",
    "sg:classifiers":[
        {
            "category":"Building & Trades",
            "subcategory":"Construction",
            "type":"Services"
        }
    ],
    "sg:phone":"+1 912 496 2659",
    "sg:postcode":"31537",
    "sg:province":"GA",
    "sg:tags":[
        "carpenter"
    ],
    "wof:name":"John V Webb",
    "wof:placetype":"venue"
},
  "geometry": {"coordinates":[-81.99980100000001,30.832432],"type":"Point"}
}