{
  "type": "Feature",
  "properties": {
    "addr:full":"611 Spencer St Barnesville GA 30204",
    "addr:housenumber":"611",
    "addr:postcode":"30204",
    "addr:street":"Spencer St",
    "iso:country":"US",
    "sg:address":"611 Spencer St",
    "sg:city":"Barnesville",
    "sg:classifiers":[
        {
            "category":"Professional",
            "type":"Services"
        }
    ],
    "sg:phone":"+1 770 358 0605",
    "sg:postcode":"30204",
    "sg:province":"GA",
    "wof:name":"Edith D Goggins",
    "wof:placetype":"venue"
},
  "geometry": {"coordinates":[-84.14885099999999,33.043262],"type":"Point"}
}