{
  "type": "Feature",
  "properties": {
    "addr:full":"2637 Austell Rd SW Marietta GA 30008",
    "addr:housenumber":"2637",
    "addr:postcode":"30008",
    "addr:street":"Austell Rd Sw",
    "iso:country":"US",
    "sg:address":"2637 Austell Rd SW",
    "sg:city":"Marietta",
    "sg:classifiers":[
        {
            "category":"Manufacturing",
            "subcategory":"Lumber",
            "type":"Manufacturing & Wholesale Goods"
        }
    ],
    "sg:phone":"+1 770 333 3031",
    "sg:postcode":"30008",
    "sg:province":"GA",
    "sg:tags":[
        "pipe",
        "coating",
        "lining"
    ],
    "wof:name":"Mr Liner Plus",
    "wof:placetype":"venue"
},
  "geometry": {"coordinates":[-84.583307,33.888385],"type":"Point"}
}