{
  "type": "Feature",
  "properties": {
    "iso:country":"US",
    "sg:address":"655 Vernon Woods Dr NE",
    "sg:city":"Atlanta",
    "sg:classifiers":[
        {
            "category":"Retail",
            "subcategory":"Portrait Studio",
            "type":"Services"
        }
    ],
    "sg:phone":"+1 404 255 8440",
    "sg:postcode":"30328",
    "sg:province":"GA",
    "sg:tags":[
        "photo"
    ],
    "wof:name":"Elite Photography Inc",
    "wof:placetype":"venue"
},
  "geometry": {"coordinates":[-84.37160299999999,33.926479],"type":"Point"}
}