{
  "type": "Feature",
  "properties": {
    "addr:full":"2334 Fuller Way Tucker GA 30084",
    "addr:housenumber":"2334",
    "addr:postcode":"30084",
    "addr:street":"Fuller Way",
    "iso:country":"US",
    "sg:address":"2334 Fuller Way",
    "sg:city":"Tucker",
    "sg:classifiers":[
        {
            "category":"Real Estate",
            "subcategory":"Real Estate Operator",
            "type":"Services"
        }
    ],
    "sg:phone":"+1 770 908 8510",
    "sg:postcode":"30084",
    "sg:province":"GA",
    "sg:tags":[
        "apartment"
    ],
    "sg:website":"www.dupontplace.com",
    "wof:name":"Dupont Place Apartments",
    "wof:placetype":"venue"
},
  "geometry": {"coordinates":[-84.20488400000001,33.852336],"type":"Point"}
}