{
  "type": "Feature",
  "properties": {
    "addr:full":"532 Grayson Hwy Lawrenceville GA 30045",
    "addr:housenumber":"532",
    "addr:postcode":"30045",
    "addr:street":"Grayson Hwy",
    "iso:country":"US",
    "sg:address":"532 Grayson Hwy",
    "sg:city":"Lawrenceville",
    "sg:classifiers":[
        {
            "category":"Wholesale",
            "subcategory":"Meat",
            "type":"Manufacturing & Wholesale Goods"
        }
    ],
    "sg:phone":"+1 770 237 9317",
    "sg:postcode":"30045",
    "sg:province":"GA",
    "sg:tags":[
        "butchering"
    ],
    "wof:name":"Carnicereia El Novillo",
    "wof:placetype":"venue"
},
  "geometry": {"coordinates":[-83.98041499999999,33.937504],"type":"Point"}
}