{
  "type": "Feature",
  "properties": {
    "iso:country":"US",
    "sg:address":"2277 Peachtree Rd NE",
    "sg:city":"Atlanta",
    "sg:classifiers":[
        {
            "category":"Restaurant",
            "type":"Food & Drink"
        }
    ],
    "sg:phone":"+1 404 355 0321",
    "sg:postcode":"30309",
    "sg:province":"GA",
    "sg:tags":[
        "new",
        "american"
    ],
    "sg:website":"www.restauranteugene.com",
    "wof:name":"Restaurant Eugene",
    "wof:placetype":"venue"
},
  "geometry": {"coordinates":[-84.39013799999999,33.816032],"type":"Point"}
}