{
  "type": "Feature",
  "properties": {
    "addr:full":"105 Braided Blanket Bluff Alpharetta GA 30022",
    "addr:housenumber":"105",
    "addr:postcode":"30022",
    "addr:street":"Braided Blanket Bluff",
    "iso:country":"US",
    "sg:address":"105 Braided Blanket Bluff",
    "sg:city":"Alpharetta",
    "sg:classifiers":[
        {
            "category":"Professional",
            "subcategory":"Business Services",
            "type":"Services"
        }
    ],
    "sg:phone":"+1 770 475 8198",
    "sg:postcode":"30022",
    "sg:province":"GA",
    "wof:name":"S&S Sign Svcs",
    "wof:placetype":"venue"
},
  "geometry": {"coordinates":[-84.22976300000001,34.049675],"type":"Point"}
}