{
  "type": "Feature",
  "properties": {
    "addr:full":"1807 Sandtown Rd SW Atlanta GA 30311",
    "addr:housenumber":"1807",
    "addr:postcode":"30311",
    "addr:street":"Sandtown Rd Sw",
    "iso:country":"US",
    "sg:address":"1807 Sandtown Rd SW",
    "sg:city":"Atlanta",
    "sg:classifiers":[
        {
            "category":"Building & Trades",
            "subcategory":"Locksmith",
            "type":"Services"
        }
    ],
    "sg:phone":"+1 404 974 9057",
    "sg:postcode":"30311",
    "sg:province":"GA",
    "sg:tags":[
        "key"
    ],
    "wof:name":"1 2 3 24 Hr A A A Locksmith",
    "wof:placetype":"venue"
},
  "geometry": {"coordinates":[-84.446957,33.718323],"type":"Point"}
}