{
  "type": "Feature",
  "properties": {
    "iso:country":"US",
    "sg:address":"1320 Guy Paine Rd",
    "sg:city":"Macon",
    "sg:classifiers":[
        {
            "category":"Professional",
            "type":"Services"
        }
    ],
    "sg:phone":"+1 478 784 5640",
    "sg:postcode":"31206",
    "sg:province":"GA",
    "wof:name":"Nalley Motor Trucks",
    "wof:placetype":"venue"
},
  "geometry": {"coordinates":[-83.663042,32.780475],"type":"Point"}
}