{
  "type": "Feature",
  "properties": {
    "addr:full":"3318 Hwy 5 Ste 436 Douglasville GA 30135",
    "addr:housenumber":"3318",
    "addr:postcode":"30135",
    "addr:street":"Hwy 5 Ste 436",
    "iso:country":"US",
    "sg:address":"3318 Hwy 5 Ste 436",
    "sg:city":"Douglasville",
    "sg:classifiers":[
        {
            "category":"Personal",
            "type":"Services"
        }
    ],
    "sg:phone":"+1 678 890 2955",
    "sg:postcode":"30135",
    "sg:province":"GA",
    "sg:tags":[
        "home"
    ],
    "wof:name":"Aries Cleaning Solutions LLC",
    "wof:placetype":"venue"
},
  "geometry": {"coordinates":[-84.763486,33.721085],"type":"Point"}
}