{
  "type": "Feature",
  "properties": {
    "iso:country":"US",
    "sg:address":"1308 Fairview Trl NW",
    "sg:city":"Lawrenceville",
    "sg:classifiers":[
        {
            "category":"Communications",
            "type":"Services"
        }
    ],
    "sg:phone":"+1 678 442 9672",
    "sg:postcode":"30043",
    "sg:province":"GA",
    "sg:tags":[
        "communication"
    ],
    "wof:name":"Visual Next Communications",
    "wof:placetype":"venue"
},
  "geometry": {"coordinates":[-84.029104,33.980459],"type":"Point"}
}