{
  "type": "Feature",
  "properties": {
    "iso:country":"US",
    "sg:address":"1450 General Arts Rd NW",
    "sg:city":"Conyers",
    "sg:classifiers":[
        {
            "category":"Building & Trades",
            "subcategory":"Construction",
            "type":"Services"
        }
    ],
    "sg:phone":"+1 770 483 4148",
    "sg:postcode":"30012",
    "sg:province":"GA",
    "sg:tags":[
        "roofing",
        "contractor"
    ],
    "wof:name":"Arrack Roofing Inc",
    "wof:placetype":"venue"
},
  "geometry": {"coordinates":[-84.054585,33.682283],"type":"Point"}
}