{
  "type": "Feature",
  "properties": {
    "iso:country":"US",
    "sg:address":"4376 Raven Valley Ct",
    "sg:city":"Decatur",
    "sg:classifiers":[
        {
            "category":"Professional",
            "type":"Services"
        }
    ],
    "sg:phone":"+1 404 617 2049",
    "sg:postcode":"30035",
    "sg:province":"GA",
    "wof:name":"Larita Middlebrooks",
    "wof:placetype":"venue"
},
  "geometry": {"coordinates":[-84.210173,33.745345],"type":"Point"}
}