{
  "type": "Feature",
  "properties": {
    "iso:country":"US",
    "sg:address":"567 N Central Ave",
    "sg:city":"Atlanta",
    "sg:classifiers":[
        {
            "category":"Shopping",
            "subcategory":"Clothing, Apparel, & Fashions",
            "type":"Retail Goods"
        },
        {
            "category":"Shopping",
            "subcategory":"Used Merchandise",
            "type":"Retail Goods"
        }
    ],
    "sg:phone":"+1 404 761 9582",
    "sg:postcode":"30354",
    "sg:province":"GA",
    "sg:tags":[
        "vintage",
        "consignment",
        "costume"
    ],
    "wof:name":"Twice Is Nice Vintage Clothing & Costumes",
    "wof:placetype":"venue"
},
  "geometry": {"coordinates":[-84.40770000000001,33.658001],"type":"Point"}
}