{
  "type": "Feature",
  "properties": {
    "addr:full":"122 Clifton Dr Athens GA 30606",
    "addr:housenumber":"122",
    "addr:postcode":"30606",
    "addr:street":"Clifton Dr",
    "iso:country":"US",
    "sg:address":"122 Clifton Dr",
    "sg:city":"Athens",
    "sg:classifiers":[
        {
            "category":"Arts & Performance",
            "subcategory":"Theater",
            "type":"Entertainment"
        }
    ],
    "sg:phone":"+1 706 549 0471",
    "sg:postcode":"30606",
    "sg:province":"GA",
    "sg:tags":[
        "organist",
        "church"
    ],
    "wof:name":"Bettie Pittman",
    "wof:placetype":"venue"
},
  "geometry": {"coordinates":[-83.43039899999999,33.975744],"type":"Point"}
}