{
  "type": "Feature",
  "properties": {
    "addr:full":"2877 Bainbridge Way Atlanta GA 30339",
    "addr:housenumber":"2877",
    "addr:postcode":"30339",
    "addr:street":"Bainbridge Way",
    "iso:country":"US",
    "sg:address":"2877 Bainbridge Way",
    "sg:city":"Atlanta",
    "sg:classifiers":[
        {
            "category":"Wholesale",
            "subcategory":"Office Equipment",
            "type":"Manufacturing & Wholesale Goods"
        }
    ],
    "sg:phone":"+1 770 432 3004",
    "sg:postcode":"30339",
    "sg:province":"GA",
    "sg:tags":[
        "electrical",
        "contractor"
    ],
    "wof:name":"Ra Whipple Group Inc",
    "wof:placetype":"venue"
},
  "geometry": {"coordinates":[-84.466795,33.860424],"type":"Point"}
}