{
  "type": "Feature",
  "properties": {
    "addr:full":"119 N Broad St Cairo GA 39828",
    "addr:housenumber":"119",
    "addr:postcode":"39828",
    "addr:street":"N Broad St",
    "iso:country":"US",
    "sg:address":"119 N Broad St",
    "sg:city":"Cairo",
    "sg:classifiers":[
        {
            "category":"Building & Trades",
            "subcategory":"Cleaning & Sanitation",
            "type":"Services"
        }
    ],
    "sg:phone":"+1 229 377 3435",
    "sg:postcode":"39828",
    "sg:province":"GA",
    "sg:tags":[
        "janitor"
    ],
    "wof:name":"Cairo Crady Clean & Beautiful",
    "wof:placetype":"venue"
},
  "geometry": {"coordinates":[-84.20822,30.877227],"type":"Point"}
}