{
  "type": "Feature",
  "properties": {
    "iso:country":"US",
    "sg:address":"1 Savannah St",
    "sg:city":"Newnan",
    "sg:classifiers":[
        {
            "category":"Professional",
            "subcategory":"Lawyer & Legal Services",
            "type":"Services"
        }
    ],
    "sg:phone":"+1 770 683 1111",
    "sg:postcode":"30263",
    "sg:province":"GA",
    "sg:tags":[
        "attorney"
    ],
    "wof:name":"Ike Hudson",
    "wof:placetype":"venue"
},
  "geometry": {"coordinates":[-84.797505,33.37086],"type":"Point"}
}