{
  "type": "Feature",
  "properties": {
    "addr:full":"34 Hudgen Rd Newnan GA 30265",
    "addr:housenumber":"34",
    "addr:postcode":"30265",
    "addr:street":"Hudgen Rd",
    "iso:country":"US",
    "sg:address":"34 Hudgen Rd",
    "sg:city":"Newnan",
    "sg:classifiers":[
        {
            "category":"Retail",
            "subcategory":"Auto Repair",
            "type":"Services"
        }
    ],
    "sg:phone":"+1 770 463 5645",
    "sg:postcode":"30265",
    "sg:province":"GA",
    "sg:tags":[
        "automotive"
    ],
    "wof:name":"South Fulton Towing & Recovery",
    "wof:placetype":"venue"
},
  "geometry": {"coordinates":[-84.659114,33.483263],"type":"Point"}
}