{
  "type": "Feature",
  "properties": {
    "iso:country":"US",
    "sg:address":"3768 Green Industrial Way",
    "sg:city":"Atlanta",
    "sg:classifiers":[
        {
            "category":"Professional",
            "subcategory":"Computer Services",
            "type":"Services"
        }
    ],
    "sg:phone":"+1 770 936 3445",
    "sg:postcode":"30341",
    "sg:province":"GA",
    "sg:tags":[
        "stereo",
        "installation"
    ],
    "wof:name":"Auto Radio Center",
    "wof:placetype":"venue"
},
  "geometry": {"coordinates":[-84.296531,33.903718],"type":"Point"}
}