{
  "type": "Feature",
  "properties": {
    "addr:full":"130 Peachtree St Atlanta GA 30303",
    "addr:housenumber":"130",
    "addr:postcode":"30303",
    "addr:street":"Peachtree St",
    "iso:country":"US",
    "sg:address":"130 Peachtree St",
    "sg:city":"Atlanta",
    "sg:classifiers":[
        {
            "category":"Insurance",
            "subcategory":"Hazard Insurance",
            "type":"Services"
        },
        {
            "category":"Insurance",
            "subcategory":"Insurance Agent",
            "type":"Services"
        },
        {
            "category":"Insurance",
            "subcategory":"Life Insurance",
            "type":"Services"
        },
        {
            "category":"Insurance",
            "subcategory":"Title Insurance",
            "type":"Services"
        },
        {
            "category":"Insurance",
            "subcategory":"Health Insurance",
            "type":"Services"
        }
    ],
    "sg:phone":"+1 404 671 8364",
    "sg:postcode":"30303",
    "sg:province":"GA",
    "sg:tags":[
        "auto",
        "dental",
        "homeowner"
    ],
    "sg:website":"www.atlantainsurancequotehq.com",
    "wof:name":"Atlanta Insurance Quote HQ",
    "wof:placetype":"venue"
},
  "geometry": {"coordinates":[-84.3882,33.757188],"type":"Point"}
}