{
  "type": "Feature",
  "properties": {
    "iso:country":"US",
    "sg:address":"2801 Candler Rd",
    "sg:city":"Decatur",
    "sg:classifiers":[
        {
            "category":"Shopping",
            "subcategory":"Clothing, Apparel, & Fashions",
            "type":"Retail Goods"
        }
    ],
    "sg:phone":"+1 404 244 1466",
    "sg:postcode":"30034",
    "sg:province":"GA",
    "wof:name":"Pener Harold Man of Fashion",
    "wof:placetype":"venue"
},
  "geometry": {"coordinates":[-84.272021,33.706961],"type":"Point"}
}