{
  "type": "Feature",
  "properties": {
    "addr:full":"604 Highview Cir Grovetown GA 30813",
    "addr:housenumber":"604",
    "addr:postcode":"30813",
    "addr:street":"Highview Cir",
    "iso:country":"US",
    "sg:address":"604 Highview Cir",
    "sg:city":"Grovetown",
    "sg:classifiers":[
        {
            "category":"Building & Trades",
            "subcategory":"Construction",
            "type":"Services"
        }
    ],
    "sg:phone":"+1 706 860 9463",
    "sg:postcode":"30813",
    "sg:province":"GA",
    "wof:name":"PM Brock Homes & Development",
    "wof:placetype":"venue"
},
  "geometry": {"coordinates":[-82.175894,33.469817],"type":"Point"}
}