{
  "type": "Feature",
  "properties": {
    "addr:full":"731 Buck Creek Rd Griffin GA 30224",
    "addr:housenumber":"731",
    "addr:postcode":"30224",
    "addr:street":"Buck Creek Rd",
    "iso:country":"US",
    "sg:address":"731 Buck Creek Rd",
    "sg:city":"Griffin",
    "sg:classifiers":[
        {
            "category":"Retail",
            "subcategory":"Auto Repair",
            "type":"Services"
        }
    ],
    "sg:phone":"+1 770 228 4177",
    "sg:postcode":"30224",
    "sg:province":"GA",
    "sg:tags":[
        "repairing",
        "automobile"
    ],
    "wof:name":"Bradley Automotive",
    "wof:placetype":"venue"
},
  "geometry": {"coordinates":[-84.129693,33.195607],"type":"Point"}
}