{
  "type": "Feature",
  "properties": {
    "iso:country":"US",
    "sg:address":"775 Pleasant Grove Church Rd",
    "sg:city":"Albany",
    "sg:classifiers":[
        {
            "category":"Organizations",
            "subcategory":"Religious Organization",
            "type":"Services"
        }
    ],
    "sg:phone":"+1 229 436 9394",
    "sg:postcode":"31705",
    "sg:province":"GA",
    "sg:tags":[
        "church"
    ],
    "wof:name":"Pleasant Grove Baptist Church",
    "wof:placetype":"venue"
},
  "geometry": {"coordinates":[-84.029315,31.425288],"type":"Point"}
}