{
  "type": "Feature",
  "properties": {
    "iso:country":"US",
    "sg:address":"264 Pharr Rd NE",
    "sg:city":"Atlanta",
    "sg:classifiers":[
        {
            "category":"Restaurant",
            "type":"Food & Drink"
        }
    ],
    "sg:phone":"+1 404 816 7332",
    "sg:postcode":"30305",
    "sg:province":"GA",
    "sg:tags":[
        "fusion",
        "sushi",
        "bar",
        "asian"
    ],
    "sg:website":"www.aquabistroatl.com",
    "wof:name":"Aqua Bistro",
    "wof:placetype":"venue"
},
  "geometry": {"coordinates":[-84.385706,33.839301],"type":"Point"}
}