{
  "type": "Feature",
  "properties": {
    "addr:full":"1050 Shiloh Rd NW Kennesaw GA 30144",
    "addr:housenumber":"1050",
    "addr:postcode":"30144",
    "addr:street":"Shiloh Rd Nw",
    "iso:country":"US",
    "sg:address":"1050 Shiloh Rd NW",
    "sg:city":"Kennesaw",
    "sg:classifiers":[
        {
            "category":"Banks & Credit Unions",
            "subcategory":"Financial Services",
            "type":"Services"
        }
    ],
    "sg:phone":"+1 770 874 1369",
    "sg:postcode":"30144",
    "sg:province":"GA",
    "sg:tags":[
        "broker",
        "mortgage"
    ],
    "wof:name":"Lighthouse Mortgage Group Llc",
    "wof:placetype":"venue"
},
  "geometry": {"coordinates":[-84.580218,34.050921],"type":"Point"}
}