{
  "type": "Feature",
  "properties": {
    "iso:country":"US",
    "sg:address":"500 Industrial Dr NE",
    "sg:city":"White",
    "sg:classifiers":[
        {
            "category":"Building & Trades",
            "subcategory":"Construction",
            "type":"Services"
        }
    ],
    "sg:phone":"+1 770 382 7494",
    "sg:postcode":"30184",
    "sg:province":"GA",
    "sg:tags":[
        "welder"
    ],
    "sg:website":"http://www.llind.com",
    "wof:name":"L & L Industries Inc",
    "wof:placetype":"venue"
},
  "geometry": {"coordinates":[-84.741612,34.286154],"type":"Point"}
}