{
  "type": "Feature",
  "properties": {
    "iso:country":"US",
    "sg:address":"505 Ashleaf Pl",
    "sg:city":"Alpharetta",
    "sg:classifiers":[
        {
            "category":"Social Services",
            "subcategory":"Job Training",
            "type":"Services"
        }
    ],
    "sg:phone":"+1 770 346 9027",
    "sg:postcode":"30005",
    "sg:province":"GA",
    "wof:name":"Philson & Associates",
    "wof:placetype":"venue"
},
  "geometry": {"coordinates":[-84.195939,34.067504],"type":"Point"}
}