{
  "type": "Feature",
  "properties": {
    "iso:country":"US",
    "sg:address":"2679 Caladium Dr NE",
    "sg:city":"Atlanta",
    "sg:classifiers":[
        {
            "category":"Utilities",
            "type":"Services"
        }
    ],
    "sg:phone":"+1 678 437 2727",
    "sg:postcode":"30345",
    "sg:province":"GA",
    "wof:name":"The Mad Scrap'r",
    "wof:placetype":"venue"
},
  "geometry": {"coordinates":[-84.27449799999999,33.865009],"type":"Point"}
}