{
  "type": "Feature",
  "properties": {
    "addr:full":"325 N Belair Rd Evans GA 30809",
    "addr:housenumber":"325",
    "addr:postcode":"30809",
    "addr:street":"N Belair Rd",
    "iso:country":"US",
    "sg:address":"325 N Belair Rd",
    "sg:city":"Evans",
    "sg:classifiers":[
        {
            "category":"Education",
            "subcategory":"School",
            "type":"Public Place"
        }
    ],
    "sg:phone":"+1 706 863 8724",
    "sg:postcode":"30809",
    "sg:province":"GA",
    "sg:website":"www.ccboe.net",
    "wof:name":"Bel Air Elementary School",
    "wof:placetype":"venue"
},
  "geometry": {"coordinates":[-82.14110599999999,33.522842],"type":"Point"}
}