{
  "type": "Feature",
  "properties": {
    "addr:full":"515 US Hwy 80 Garden City GA 31408",
    "addr:housenumber":"515",
    "addr:postcode":"31408",
    "addr:street":"Us Hwy 80",
    "iso:country":"US",
    "sg:address":"515 US Hwy 80",
    "sg:city":"Garden City",
    "sg:classifiers":[
        {
            "category":"Retail",
            "subcategory":"Auto Rental",
            "type":"Services"
        }
    ],
    "sg:phone":"+1 912 966 1540",
    "sg:postcode":"31408",
    "sg:province":"GA",
    "sg:tags":[
        "renting",
        "truck",
        "leasing"
    ],
    "wof:name":"Penske Truck Rental",
    "wof:placetype":"venue"
},
  "geometry": {"coordinates":[-81.147508,32.09402],"type":"Point"}
}