{
  "type": "Feature",
  "properties": {
    "addr:full":"13 Vickwood Ct Marietta GA 30068",
    "addr:housenumber":"13",
    "addr:postcode":"30068",
    "addr:street":"Vickwood Ct",
    "iso:country":"US",
    "sg:address":"13 Vickwood Ct",
    "sg:city":"Marietta",
    "sg:classifiers":[
        {
            "category":"Wholesale",
            "subcategory":"Furniture",
            "type":"Manufacturing & Wholesale Goods"
        }
    ],
    "sg:phone":"+1 678 613 1561",
    "sg:postcode":"30068",
    "sg:province":"GA",
    "sg:tags":[
        "furniture-wholesale",
        "manufacturer"
    ],
    "wof:name":"Demand Plus Office Systems",
    "wof:placetype":"venue"
},
  "geometry": {"coordinates":[-84.459335,33.949327],"type":"Point"}
}