{
  "type": "Feature",
  "properties": {
    "iso:country":"US",
    "sg:address":"1774 State Rte 315",
    "sg:city":"Fortson",
    "sg:classifiers":[
        {
            "category":"Building & Trades",
            "subcategory":"Construction",
            "type":"Services"
        }
    ],
    "sg:phone":"+1 706 660 8193",
    "sg:postcode":"31808",
    "sg:province":"GA",
    "sg:tags":[
        "carpentry",
        "contractor"
    ],
    "wof:name":"Batchelor Quality Homes Inc",
    "wof:placetype":"venue"
},
  "geometry": {"coordinates":[-85.017973,32.646016],"type":"Point"}
}