{
  "type": "Feature",
  "properties": {
    "iso:country":"US",
    "sg:address":"47 Professional Dr",
    "sg:city":"Brunswick",
    "sg:classifiers":[
        {
            "category":"Personal",
            "subcategory":"Massage",
            "type":"Services"
        },
        {
            "category":"Personal",
            "subcategory":"Beauty Salon",
            "type":"Services"
        },
        {
            "category":"Personal",
            "subcategory":"Day Spa",
            "type":"Services"
        }
    ],
    "sg:phone":"+1 912 342 7153",
    "sg:postcode":"31520",
    "sg:province":"GA",
    "sg:tags":[
        "therapist"
    ],
    "wof:name":"Elements Salon And Spa",
    "wof:placetype":"venue"
},
  "geometry": {"coordinates":[-81.471836,31.18312],"type":"Point"}
}