{
  "type": "Feature",
  "properties": {
    "addr:full":"513 13th St Augusta GA 30901",
    "addr:housenumber":"513",
    "addr:postcode":"30901",
    "addr:street":"13Th St",
    "iso:country":"US",
    "sg:address":"513 13th St",
    "sg:city":"Augusta",
    "sg:classifiers":[
        {
            "category":"Health Services",
            "subcategory":"Clinic",
            "type":"Services"
        }
    ],
    "sg:phone":"+1 706 724 7746",
    "sg:postcode":"30901",
    "sg:province":"GA",
    "sg:tags":[
        "specialty",
        "outpatient"
    ],
    "wof:name":"Harison Heights",
    "wof:placetype":"venue"
},
  "geometry": {"coordinates":[-81.977114,33.475293],"type":"Point"}
}