{
  "type": "Feature",
  "properties": {
    "iso:country":"US",
    "sg:address":"State Farmers Mkt",
    "sg:city":"Forest Park",
    "sg:classifiers":[
        {
            "category":"Restaurant",
            "type":"Food & Drink"
        }
    ],
    "sg:phone":"+1 404 366 4805",
    "sg:postcode":"30297",
    "sg:province":"GA",
    "wof:name":"Market Grocery Co",
    "wof:placetype":"venue"
},
  "geometry": {"coordinates":[-84.363602,33.610001],"type":"Point"}
}