{
  "type": "Feature",
  "properties": {
    "addr:full":"1920 N Leg Rd Augusta GA 30909",
    "addr:housenumber":"1920",
    "addr:postcode":"30909",
    "addr:street":"N Leg Rd",
    "iso:country":"US",
    "sg:address":"1920 N Leg Rd",
    "sg:city":"Augusta",
    "sg:classifiers":[
        {
            "category":"Building & Trades",
            "subcategory":"Construction",
            "type":"Services"
        },
        {
            "category":"Home & Garden",
            "subcategory":"Carpets & Floor Coverings",
            "type":"Retail Goods"
        }
    ],
    "sg:phone":"+1 800 394 3064",
    "sg:postcode":"30909",
    "sg:province":"GA",
    "sg:tags":[
        "material",
        "tile-contractors",
        "rug",
        "flooring",
        "contractor"
    ],
    "sg:website":"http://www.filitrac.com/Click.aspx?tid=BDEDC5D5EF8BAE3541B5938870DA3DDECE60F60FEE115906&FiliAff=15016&sid=99202&utm_source=YellowPages&utm_medium=ppc&utm_campaign=national&utm_term=30909",
    "wof:name":"American Carpet One Floor & Home",
    "wof:placetype":"venue"
},
  "geometry": {"coordinates":[-82.06624600000001,33.455835],"type":"Point"}
}