{
  "type": "Feature",
  "properties": {
    "addr:full":"105 Moss St Tallulah Falls GA 30531",
    "addr:housenumber":"105",
    "addr:postcode":"30531",
    "addr:street":"Moss St",
    "iso:country":"US",
    "sg:address":"105 Moss St",
    "sg:city":"Tallulah Falls",
    "sg:classifiers":[
        {
            "category":"Shopping",
            "subcategory":"Gifts & Souvenirs",
            "type":"Retail Goods"
        }
    ],
    "sg:phone":"+1 706 754 6810",
    "sg:postcode":"30531",
    "sg:province":"GA",
    "sg:tags":[
        "shop"
    ],
    "sg:website":"www.co-opcraftstores.com",
    "wof:name":"Co-Op Craft Store",
    "wof:placetype":"venue"
},
  "geometry": {"coordinates":[-83.52705400000001,34.509564],"type":"Point"}
}