{
  "type": "Feature",
  "properties": {
    "iso:country":"US",
    "sg:address":"800 Mount Vernon Hwy NE",
    "sg:city":"Atlanta",
    "sg:classifiers":[
        {
            "category":"Professional",
            "subcategory":"Employment Agencies",
            "type":"Services"
        }
    ],
    "sg:phone":"+1 770 671 0444",
    "sg:postcode":"30328",
    "sg:province":"GA",
    "wof:name":"Cortech",
    "wof:placetype":"venue"
},
  "geometry": {"coordinates":[-84.37857200000001,33.936604],"type":"Point"}
}