{
  "type": "Feature",
  "properties": {
    "addr:full":"7843 Roswell Road Atlanta GA 30350",
    "addr:housenumber":"7843",
    "addr:postcode":"30350",
    "addr:street":"Roswell Road",
    "iso:country":"US",
    "sg:address":"7843 Roswell Road",
    "sg:city":"Atlanta",
    "sg:classifiers":[
        {
            "category":"Real Estate",
            "subcategory":"Real Estate Operator",
            "type":"Services"
        }
    ],
    "sg:phone":"+1 770 395 0732",
    "sg:postcode":"30350",
    "sg:province":"GA",
    "sg:tags":[
        "apartment"
    ],
    "wof:name":"Morgan's Landing Apartments",
    "wof:placetype":"venue"
},
  "geometry": {"coordinates":[-84.36018799999999,33.969781],"type":"Point"}
}