{
  "type": "Feature",
  "properties": {
    "addr:full":"7140 Doncaster Ct Cumming GA 30040",
    "addr:housenumber":"7140",
    "addr:postcode":"30040",
    "addr:street":"Doncaster Ct",
    "iso:country":"US",
    "sg:address":"7140 Doncaster Ct",
    "sg:city":"Cumming",
    "sg:classifiers":[
        {
            "category":"Professional",
            "subcategory":"Computer Services",
            "type":"Services"
        }
    ],
    "sg:phone":"+1 678 637 6463",
    "sg:postcode":"30040",
    "sg:province":"GA",
    "sg:tags":[
        "datum"
    ],
    "wof:name":"C C Geek",
    "wof:placetype":"venue"
},
  "geometry": {"coordinates":[-84.252376,34.180957],"type":"Point"}
}