{
  "type": "Feature",
  "properties": {
    "addr:full":"1692 Niskey Lake Trl SW Atlanta GA 30331",
    "addr:housenumber":"1692",
    "addr:postcode":"30331",
    "addr:street":"Niskey Lake Trl Sw",
    "iso:country":"US",
    "sg:address":"1692 Niskey Lake Trl SW",
    "sg:city":"Atlanta",
    "sg:classifiers":[
        {
            "category":"Professional",
            "subcategory":"Computer Services",
            "type":"Services"
        }
    ],
    "sg:phone":"+1 404 217 7419",
    "sg:postcode":"30331",
    "sg:province":"GA",
    "sg:tags":[
        "designer",
        "network",
        "technical",
        "consultant",
        "assistance",
        "system",
        "design",
        "support"
    ],
    "wof:name":"Micro Market Solutions",
    "wof:placetype":"venue"
},
  "geometry": {"coordinates":[-84.53085900000001,33.710963],"type":"Point"}
}