{
  "type": "Feature",
  "properties": {
    "iso:country":"US",
    "sg:address":"435 Peachtree St NE",
    "sg:city":"Atlanta",
    "sg:classifiers":[
        {
            "category":"Education",
            "subcategory":"Special Training",
            "type":"Public Place"
        }
    ],
    "sg:phone":"+1 404 873 7621",
    "sg:postcode":"30308",
    "sg:province":"GA",
    "sg:tags":[
        "educational"
    ],
    "wof:name":"\"I Have A Dream\"(R) Of Atlanta, Inc - A D Williams Chapter",
    "wof:placetype":"venue"
},
  "geometry": {"coordinates":[-84.385411,33.766563],"type":"Point"}
}