{
  "type": "Feature",
  "properties": {
    "iso:country":"US",
    "sg:address":"610 Malcom Rd",
    "sg:city":"Covington",
    "sg:classifiers":[
        {
            "category":"Communications",
            "subcategory":"Film & Video Production",
            "type":"Services"
        }
    ],
    "sg:phone":"+1 770 385 8300",
    "sg:postcode":"30014",
    "sg:province":"GA",
    "sg:tags":[
        "motion"
    ],
    "wof:name":"Twisted River Productions",
    "wof:placetype":"venue"
},
  "geometry": {"coordinates":[-83.86955500000001,33.401763],"type":"Point"}
}