{
  "type": "Feature",
  "properties": {
    "addr:full":"158 E Wilson St Villa Rica GA 30180",
    "addr:housenumber":"158",
    "addr:postcode":"30180",
    "addr:street":"E Wilson St",
    "iso:country":"US",
    "sg:address":"158 E Wilson St",
    "sg:city":"Villa Rica",
    "sg:classifiers":[
        {
            "category":"Government",
            "subcategory":"Office",
            "type":"Public Place"
        }
    ],
    "sg:phone":"+1 770 459 0031",
    "sg:postcode":"30180",
    "sg:province":"GA",
    "sg:tags":[
        "city",
        "program",
        "health"
    ],
    "wof:name":"Health Dept",
    "wof:placetype":"venue"
},
  "geometry": {"coordinates":[-84.918305,33.729625],"type":"Point"}
}