{
  "type": "Feature",
  "properties": {
    "iso:country":"US",
    "sg:address":"400 Captain Wylly Rd",
    "sg:city":"Jekyll Island",
    "sg:classifiers":[
        {
            "category":"Recreation",
            "type":"Entertainment"
        }
    ],
    "sg:phone":"+1 912 635 3154",
    "sg:postcode":"31527",
    "sg:province":"GA",
    "sg:tags":[
        "tennis",
        "court"
    ],
    "wof:name":"Jekyll Island Tennis Ctr",
    "wof:placetype":"venue"
},
  "geometry": {"coordinates":[-81.42395,31.069155],"type":"Point"}
}