{
  "type": "Feature",
  "properties": {
    "iso:country":"US",
    "sg:address":"2222 Hwy 212",
    "sg:city":"Covington",
    "sg:classifiers":[
        {
            "category":"Freight",
            "type":"Transportation"
        },
        {
            "category":"Recreation",
            "subcategory":"Marina",
            "type":"Entertainment"
        }
    ],
    "sg:phone":"+1 770 385 7322",
    "sg:postcode":"30016",
    "sg:province":"GA",
    "sg:tags":[
        "commercial",
        "operation",
        "storage"
    ],
    "wof:name":"Four Deuces Mini Storage",
    "wof:placetype":"venue"
},
  "geometry": {"coordinates":[-83.904296,33.463538],"type":"Point"}
}