{
  "type": "Feature",
  "properties": {
    "iso:country":"US",
    "sg:address":"7553 Highway 85",
    "sg:city":"Riverdale",
    "sg:classifiers":[
        {
            "category":"Personal",
            "subcategory":"Barber",
            "type":"Services"
        }
    ],
    "sg:phone":"+1 770 991 1119",
    "sg:postcode":"30274",
    "sg:province":"GA",
    "sg:website":"www.futurecutsatl.com",
    "wof:name":"Dutch Cuts & Styles",
    "wof:placetype":"venue"
},
  "geometry": {"coordinates":[-84.414497,33.551601],"type":"Point"}
}