{
  "type": "Feature",
  "properties": {
    "iso:country":"US",
    "sg:address":"4515 US Hwy 78",
    "sg:city":"Lawrenceville",
    "sg:classifiers":[
        {
            "category":"Social Services",
            "subcategory":"Child Care",
            "type":"Services"
        },
        {
            "category":"Education",
            "subcategory":"School",
            "type":"Public Place"
        }
    ],
    "sg:phone":"+1 770 736 8938",
    "sg:postcode":"30047",
    "sg:province":"GA",
    "sg:tags":[
        "day"
    ],
    "wof:name":"Evergreen Montessori School",
    "wof:placetype":"venue"
},
  "geometry": {"coordinates":[-84.08920999999999,33.831865],"type":"Point"}
}