{
  "type": "Feature",
  "properties": {
    "iso:country":"US",
    "sg:address":"2012 Dobbins Dr",
    "sg:city":"Kennesaw",
    "sg:classifiers":[
        {
            "category":"Building & Trades",
            "subcategory":"Landscaping Services",
            "type":"Services"
        }
    ],
    "sg:phone":"+1 770 421 9799",
    "sg:postcode":"30144",
    "sg:province":"GA",
    "sg:tags":[
        "landscaper"
    ],
    "wof:name":"Jones Landscaping",
    "wof:placetype":"venue"
},
  "geometry": {"coordinates":[-84.608019,34.038719],"type":"Point"}
}