{
  "type": "Feature",
  "properties": {
    "addr:full":"2532 S Hairston Rd Decatur GA 30035",
    "addr:housenumber":"2532",
    "addr:postcode":"30035",
    "addr:street":"S Hairston Rd",
    "iso:country":"US",
    "sg:address":"2532 S Hairston Rd",
    "sg:city":"Decatur",
    "sg:classifiers":[
        {
            "category":"Food & Beverages",
            "subcategory":"Ethnic Foods",
            "type":"Retail Goods"
        }
    ],
    "sg:phone":"+1 770 987 7005",
    "sg:postcode":"30035",
    "sg:province":"GA",
    "wof:name":"Island Foods",
    "wof:placetype":"venue"
},
  "geometry": {"coordinates":[-84.211107,33.718634],"type":"Point"}
}