{
  "type": "Feature",
  "properties": {
    "iso:country":"US",
    "sg:address":"2299 Alnwick Dr",
    "sg:city":"Duluth",
    "sg:classifiers":[
        {
            "category":"Professional",
            "subcategory":"Business Services",
            "type":"Services"
        }
    ],
    "sg:phone":"+1 770 476 8651",
    "sg:postcode":"30096",
    "sg:province":"GA",
    "sg:tags":[
        "holding"
    ],
    "wof:name":"Bbb Domestic Holdings Inc",
    "wof:placetype":"venue"
},
  "geometry": {"coordinates":[-84.117859,33.979309],"type":"Point"}
}