{
  "type": "Feature",
  "properties": {
    "iso:country":"US",
    "sg:address":"9001 N Main St",
    "sg:city":"Helen",
    "sg:classifiers":[
        {
            "category":"Restaurant",
            "type":"Food & Drink"
        }
    ],
    "sg:phone":"+1 706 878 2248",
    "sg:postcode":"30545",
    "sg:province":"GA",
    "sg:tags":[
        "german"
    ],
    "wof:name":"Hofbrauhaus Restaurant",
    "wof:placetype":"venue"
},
  "geometry": {"coordinates":[-83.736412,34.702683],"type":"Point"}
}