{
  "type": "Feature",
  "properties": {
    "iso:country":"US",
    "sg:address":"12665 Crabapple Rd",
    "sg:city":"Alpharetta",
    "sg:classifiers":[
        {
            "category":"Social Services",
            "subcategory":"Child Care",
            "type":"Services"
        }
    ],
    "sg:phone":"+1 678 366 6161",
    "sg:postcode":"30004",
    "sg:province":"GA",
    "sg:tags":[
        "school",
        "specialty"
    ],
    "sg:website":"www.goddardschool.com/Schools/Al...",
    "wof:name":"The Goddard School",
    "wof:placetype":"venue"
},
  "geometry": {"coordinates":[-84.34150099999999,34.089547],"type":"Point"}
}