{
  "type": "Feature",
  "properties": {
    "addr:full":"1640 Old Doerun Rd Moultrie GA 31768",
    "addr:housenumber":"1640",
    "addr:postcode":"31768",
    "addr:street":"Old Doerun Rd",
    "iso:country":"US",
    "sg:address":"1640 Old Doerun Rd",
    "sg:city":"Moultrie",
    "sg:classifiers":[
        {
            "category":"Personal",
            "subcategory":"Barber",
            "type":"Services"
        }
    ],
    "sg:phone":"+1 229 873 9784",
    "sg:postcode":"31768",
    "sg:province":"GA",
    "wof:name":"Carrien Barber Shop",
    "wof:placetype":"venue"
},
  "geometry": {"coordinates":[-83.80282699999999,31.201722],"type":"Point"}
}