{
  "type": "Feature",
  "properties": {
    "iso:country":"US",
    "sg:address":"220 Beechwood Dr",
    "sg:city":"Clayton",
    "sg:classifiers":[
        {
            "category":"Restaurant",
            "type":"Food & Drink"
        }
    ],
    "sg:phone":"+1 706 782 5485",
    "sg:postcode":"30525",
    "sg:province":"GA",
    "sg:tags":[
        "american"
    ],
    "sg:website":"http://www.beechwoodinn.ws",
    "wof:name":"Beechwood Inn",
    "wof:placetype":"venue"
},
  "geometry": {"coordinates":[-83.39582,34.871717],"type":"Point"}
}