{
  "type": "Feature",
  "properties": {
    "iso:country":"US",
    "sg:address":"11 College Plz",
    "sg:city":"Statesboro",
    "sg:classifiers":[
        {
            "category":"Shopping",
            "subcategory":"Clothing, Apparel, & Fashions",
            "type":"Retail Goods"
        }
    ],
    "sg:phone":"+1 912 681 7311",
    "sg:postcode":"30458",
    "sg:province":"GA",
    "wof:name":"Statesboro Fashions",
    "wof:placetype":"venue"
},
  "geometry": {"coordinates":[-81.78085799999999,32.433651],"type":"Point"}
}