{
  "type": "Feature",
  "properties": {
    "iso:country":"US",
    "sg:address":"401 Walton Way",
    "sg:city":"Augusta",
    "sg:classifiers":[
        {
            "category":"Health Services",
            "subcategory":"Doctor",
            "type":"Services"
        }
    ],
    "sg:phone":"+1 706 828 3045",
    "sg:postcode":"30901",
    "sg:province":"GA",
    "sg:tags":[
        "clinic"
    ],
    "wof:name":"Correctional Medical Svc",
    "wof:placetype":"venue"
},
  "geometry": {"coordinates":[-81.961426,33.465628],"type":"Point"}
}