{
  "type": "Feature",
  "properties": {
    "iso:country":"US",
    "sg:address":"720 S Pleasant Hill Rd",
    "sg:city":"Warner Robins",
    "sg:classifiers":[
        {
            "category":"Retail",
            "subcategory":"Auto Repair",
            "type":"Services"
        }
    ],
    "sg:phone":"+1 478 929 5196",
    "sg:postcode":"31088",
    "sg:province":"GA",
    "wof:name":"Ken's Quality Auto Services",
    "wof:placetype":"venue"
},
  "geometry": {"coordinates":[-83.619102,32.597801],"type":"Point"}
}