{
  "type": "Feature",
  "properties": {
    "iso:country":"US",
    "sg:address":"445 Arborshade Trce",
    "sg:city":"Duluth",
    "sg:classifiers":[
        {
            "category":"Building & Trades",
            "subcategory":"Plumbing",
            "type":"Services"
        }
    ],
    "sg:phone":"+1 770 476 8055",
    "sg:postcode":"30097",
    "sg:province":"GA",
    "sg:tags":[
        "contractor"
    ],
    "wof:name":"Booth Mechanical Inc",
    "wof:placetype":"venue"
},
  "geometry": {"coordinates":[-84.173794,34.037934],"type":"Point"}
}