{
  "type": "Feature",
  "properties": {
    "addr:full":"3680 Ryans Bluff Dr Cumming GA 30040",
    "addr:housenumber":"3680",
    "addr:postcode":"30040",
    "addr:street":"Ryans Bluff Dr",
    "iso:country":"US",
    "sg:address":"3680 Ryans Bluff Dr",
    "sg:city":"Cumming",
    "sg:classifiers":[
        {
            "category":"Professional",
            "subcategory":"Research",
            "type":"Services"
        }
    ],
    "sg:phone":"+1 706 864 6304",
    "sg:postcode":"30040",
    "sg:province":"GA",
    "sg:tags":[
        "physical"
    ],
    "wof:name":"Short Watch",
    "wof:placetype":"venue"
},
  "geometry": {"coordinates":[-84.229648,34.204116],"type":"Point"}
}