{
  "type": "Feature",
  "properties": {
    "iso:country":"US",
    "sg:address":"240 Bohler Dr",
    "sg:city":"Evans",
    "sg:classifiers":[
        {
            "category":"Building & Trades",
            "subcategory":"Electrical",
            "type":"Services"
        }
    ],
    "sg:phone":"+1 706 399 3059",
    "sg:postcode":"30809",
    "sg:province":"GA",
    "sg:tags":[
        "electrician"
    ],
    "wof:name":"S M G Electrical",
    "wof:placetype":"venue"
},
  "geometry": {"coordinates":[-82.133476,33.523911],"type":"Point"}
}