{
  "type": "Feature",
  "properties": {
    "addr:full":"1895 Commerce Rd Athens GA 30607",
    "addr:housenumber":"1895",
    "addr:postcode":"30607",
    "addr:street":"Commerce Rd",
    "iso:country":"US",
    "sg:address":"1895 Commerce Rd",
    "sg:city":"Athens",
    "sg:classifiers":[
        {
            "category":"Building & Trades",
            "subcategory":"Electrical",
            "type":"Services"
        },
        {
            "category":"Professional",
            "subcategory":"Management & Consulting",
            "type":"Services"
        }
    ],
    "sg:phone":"+1 706 548 6922",
    "sg:postcode":"30607",
    "sg:province":"GA",
    "sg:tags":[
        "consultant",
        "automation",
        "electrical",
        "contractor"
    ],
    "wof:name":"All Automation Technologies",
    "wof:placetype":"venue"
},
  "geometry": {"coordinates":[-83.383015,33.998954],"type":"Point"}
}