{
  "type": "Feature",
  "properties": {
    "addr:full":"59 Carlton Dr NE Atlanta GA 30342",
    "addr:housenumber":"59",
    "addr:postcode":"30342",
    "addr:street":"Carlton Dr Ne",
    "iso:country":"US",
    "sg:address":"59 Carlton Dr NE",
    "sg:city":"Atlanta",
    "sg:classifiers":[
        {
            "category":"Wholesale",
            "subcategory":"Jewelry",
            "type":"Manufacturing & Wholesale Goods"
        }
    ],
    "sg:phone":"+1 404 256 9382",
    "sg:postcode":"30342",
    "sg:province":"GA",
    "sg:tags":[
        "precious",
        "metal",
        "representative",
        "mfg"
    ],
    "wof:name":"Karlan Inc",
    "wof:placetype":"venue"
},
  "geometry": {"coordinates":[-84.38747600000001,33.87236],"type":"Point"}
}