{
  "type": "Feature",
  "properties": {
    "addr:full":"5825 Glenridge Dr NE Sandy Springs GA 30328",
    "addr:housenumber":"5825",
    "addr:postcode":"30328",
    "addr:street":"Glenridge Dr Ne",
    "iso:country":"US",
    "sg:address":"5825 Glenridge Dr NE",
    "sg:city":"Sandy Springs",
    "sg:classifiers":[
        {
            "category":"Taxi",
            "type":"Transportation"
        }
    ],
    "sg:phone":"+1 770 960 0000",
    "sg:postcode":"30328",
    "sg:province":"GA",
    "sg:tags":[
        "taxicab"
    ],
    "wof:name":"A Suburban Transport Inc",
    "wof:placetype":"venue"
},
  "geometry": {"coordinates":[-84.362297,33.91632],"type":"Point"}
}