{
  "type": "Feature",
  "properties": {
    "iso:country":"US",
    "sg:address":"6838 Holly Springs Rd",
    "sg:city":"Clermont",
    "sg:classifiers":[
        {
            "category":"Banks & Credit Unions",
            "subcategory":"Financial Services",
            "type":"Services"
        }
    ],
    "sg:phone":"+1 770 983 3642",
    "sg:postcode":"30527",
    "sg:province":"GA",
    "sg:tags":[
        "investor"
    ],
    "wof:name":"Wauka Mnt Dvloping Investments",
    "wof:placetype":"venue"
},
  "geometry": {"coordinates":[-83.740385,34.472592],"type":"Point"}
}