{
  "type": "Feature",
  "properties": {
    "addr:full":"4495 S Cobb Dr SE Smyrna GA 30080",
    "addr:housenumber":"4495",
    "addr:postcode":"30080",
    "addr:street":"S Cobb Dr Se",
    "iso:country":"US",
    "sg:address":"4495 S Cobb Dr SE",
    "sg:city":"Smyrna",
    "sg:classifiers":[
        {
            "category":"Food & Beverages",
            "subcategory":"Groceries & Convenience Stores",
            "type":"Retail Goods"
        }
    ],
    "sg:phone":"+1 770 434 9569",
    "sg:postcode":"30080",
    "sg:province":"GA",
    "wof:name":"L & S Food Mart Inc",
    "wof:placetype":"venue"
},
  "geometry": {"coordinates":[-84.50099899999999,33.8442],"type":"Point"}
}