{
  "type": "Feature",
  "properties": {
    "iso:country":"US",
    "sg:address":"200 Eldorado Dr",
    "sg:city":"Carrollton",
    "sg:classifiers":[
        {
            "category":"Real Estate",
            "subcategory":"Real Estate Agent",
            "type":"Services"
        }
    ],
    "sg:phone":"+1 770 830 8523",
    "sg:postcode":"30116",
    "sg:province":"GA",
    "sg:tags":[
        "inspection"
    ],
    "wof:name":"Professional Home Inspection",
    "wof:placetype":"venue"
},
  "geometry": {"coordinates":[-85.011786,33.597097],"type":"Point"}
}