{
  "type": "Feature",
  "properties": {
    "addr:full":"371 Crossroads Church Rd Rockmart GA 30153",
    "addr:housenumber":"371",
    "addr:postcode":"30153",
    "addr:street":"Crossroads Church Rd",
    "iso:country":"US",
    "sg:address":"371 Crossroads Church Rd",
    "sg:city":"Rockmart",
    "sg:classifiers":[
        {
            "category":"Building & Trades",
            "subcategory":"Electrical",
            "type":"Services"
        }
    ],
    "sg:phone":"+1 770 445 7102",
    "sg:postcode":"30153",
    "sg:province":"GA",
    "sg:tags":[
        "electrical",
        "electric",
        "contractor"
    ],
    "wof:name":"Lost Mountain Electric Co Inc",
    "wof:placetype":"venue"
},
  "geometry": {"coordinates":[-85.00317099999999,33.926356],"type":"Point"}
}