{
  "type": "Feature",
  "properties": {
    "iso:country":"US",
    "sg:address":"1475 Alpharetta Hwy",
    "sg:city":"Alpharetta",
    "sg:classifiers":[
        {
            "category":"Retail",
            "subcategory":"Auto Rental",
            "type":"Services"
        }
    ],
    "sg:phone":"+1 770 346 8411",
    "sg:postcode":"30009",
    "sg:province":"GA",
    "sg:tags":[
        "car"
    ],
    "wof:name":"Hertz",
    "wof:placetype":"venue"
},
  "geometry": {"coordinates":[-84.31679200000001,34.066427],"type":"Point"}
}