{
  "type": "Feature",
  "properties": {
    "iso:country":"US",
    "sg:address":"2011 Jonesboro Rd",
    "sg:city":"Mcdonough",
    "sg:classifiers":[
        {
            "category":"Restaurant",
            "type":"Food & Drink"
        },
        {
            "category":"Ice Cream",
            "type":"Food & Drink"
        }
    ],
    "sg:phone":"+1 770 320 9600",
    "sg:postcode":"30253",
    "sg:province":"GA",
    "sg:tags":[
        "frozen",
        "dessert"
    ],
    "sg:website":"http://www.marbleslab.com/",
    "wof:name":"The Marble Slab Creamery",
    "wof:placetype":"venue"
},
  "geometry": {"coordinates":[-84.221566,33.464471],"type":"Point"}
}