{
  "type": "Feature",
  "properties": {
    "iso:country":"US",
    "sg:address":"2709 Holly Springs Pkwy",
    "sg:city":"Canton",
    "sg:classifiers":[
        {
            "category":"Wholesale",
            "subcategory":"Motor Vehicles",
            "type":"Manufacturing & Wholesale Goods"
        }
    ],
    "sg:phone":"+1 770 704 0505",
    "sg:postcode":"30115",
    "sg:province":"GA",
    "wof:name":"Autosmart Usa LLC",
    "wof:placetype":"venue"
},
  "geometry": {"coordinates":[-84.501148,34.173977],"type":"Point"}
}