{
  "type": "Feature",
  "properties": {
    "iso:country":"US",
    "sg:address":"333 S 9th St",
    "sg:city":"Griffin",
    "sg:classifiers":[
        {
            "category":"Health Services",
            "subcategory":"Doctor",
            "type":"Services"
        }
    ],
    "sg:phone":"+1 770 229 8721",
    "sg:postcode":"30224",
    "sg:province":"GA",
    "sg:tags":[
        "clinic"
    ],
    "wof:name":"Griffin Outpatient Svc",
    "wof:placetype":"venue"
},
  "geometry": {"coordinates":[-84.26718200000001,33.245596],"type":"Point"}
}