{
  "type": "Feature",
  "properties": {
    "addr:full":"127 Winding Way Leesburg GA 31763",
    "addr:housenumber":"127",
    "addr:postcode":"31763",
    "addr:street":"Winding Way",
    "iso:country":"US",
    "sg:address":"127 Winding Way",
    "sg:city":"Leesburg",
    "sg:classifiers":[
        {
            "category":"Building & Trades",
            "subcategory":"Construction",
            "type":"Services"
        }
    ],
    "sg:phone":"+1 229 436 9043",
    "sg:postcode":"31763",
    "sg:province":"GA",
    "sg:tags":[
        "contractor"
    ],
    "wof:name":"Ryals Home Builders",
    "wof:placetype":"venue"
},
  "geometry": {"coordinates":[-84.169156,31.639395],"type":"Point"}
}