{
  "type": "Feature",
  "properties": {
    "iso:country":"US",
    "sg:address":"2615 Gresham Rd SE",
    "sg:city":"Atlanta",
    "sg:classifiers":[
        {
            "category":"Retail",
            "subcategory":"Auto Repair",
            "type":"Services"
        }
    ],
    "sg:phone":"+1 404 243 5009",
    "sg:postcode":"30316",
    "sg:province":"GA",
    "sg:tags":[
        "repairing",
        "automobile"
    ],
    "wof:name":"D-Tech Automotive Specialists",
    "wof:placetype":"venue"
},
  "geometry": {"coordinates":[-84.31046000000001,33.713263],"type":"Point"}
}