{
  "type": "Feature",
  "properties": {
    "iso:country":"US",
    "sg:address":"623 Dixie St",
    "sg:city":"Carrollton",
    "sg:classifiers":[
        {
            "category":"Shopping",
            "subcategory":"Pharmacy",
            "type":"Retail Goods"
        }
    ],
    "sg:phone":"+1 770 834 3393",
    "sg:postcode":"30117",
    "sg:province":"GA",
    "sg:tags":[
        "drug",
        "store"
    ],
    "wof:name":"Haneys Drug Corner Inc",
    "wof:placetype":"venue"
},
  "geometry": {"coordinates":[-85.072498,33.571521],"type":"Point"}
}