{
  "type": "Feature",
  "properties": {
    "addr:full":"1648 Atlanta Rd SW Marietta GA 30060",
    "addr:housenumber":"1648",
    "addr:postcode":"30060",
    "addr:street":"Atlanta Rd Sw",
    "iso:country":"US",
    "sg:address":"1648 Atlanta Rd SW",
    "sg:city":"Marietta",
    "sg:classifiers":[
        {
            "category":"Building & Trades",
            "subcategory":"Plumbing",
            "type":"Services"
        }
    ],
    "sg:phone":"+1 770 433 1970",
    "sg:postcode":"30060",
    "sg:province":"GA",
    "sg:tags":[
        "air",
        "heating",
        "contractor",
        "system",
        "conditioning"
    ],
    "wof:name":"Daco Services Inc",
    "wof:placetype":"venue"
},
  "geometry": {"coordinates":[-84.53666200000001,33.913814],"type":"Point"}
}