{
  "type": "Feature",
  "properties": {
    "iso:country":"US",
    "sg:address":"131 Ponce de Leon Ave NE",
    "sg:city":"Atlanta",
    "sg:classifiers":[
        {
            "category":"Professional",
            "type":"Services"
        }
    ],
    "sg:phone":"+1 404 389 0104",
    "sg:postcode":"30308",
    "sg:province":"GA",
    "sg:tags":[
        "establishment"
    ],
    "wof:name":"Same",
    "wof:placetype":"venue"
},
  "geometry": {"coordinates":[-84.38195,33.772416],"type":"Point"}
}