{
  "type": "Feature",
  "properties": {
    "addr:full":"413 Mead Rd Decatur GA 30030",
    "addr:housenumber":"413",
    "addr:postcode":"30030",
    "addr:street":"Mead Rd",
    "iso:country":"US",
    "sg:address":"413 Mead Rd",
    "sg:city":"Decatur",
    "sg:classifiers":[
        {
            "category":"Building & Trades",
            "subcategory":"Construction",
            "type":"Services"
        }
    ],
    "sg:phone":"+1 404 373 0409",
    "sg:postcode":"30030",
    "sg:province":"GA",
    "sg:tags":[
        "house"
    ],
    "wof:name":"On The Level Renovations",
    "wof:placetype":"venue"
},
  "geometry": {"coordinates":[-84.304084,33.7611],"type":"Point"}
}