{
  "type": "Feature",
  "properties": {
    "iso:country":"US",
    "sg:address":"5012 Austell Rd SW",
    "sg:city":"Atlanta",
    "sg:classifiers":[
        {
            "category":"Organizations",
            "subcategory":"Religious Organization",
            "type":"Services"
        }
    ],
    "sg:phone":"+1 770 745 2211",
    "sg:postcode":"30303",
    "sg:province":"GA",
    "wof:name":"Latter Rain Christian Church",
    "wof:placetype":"venue"
},
  "geometry": {"coordinates":[-84.61237199999999,33.832177],"type":"Point"}
}