{
  "type": "Feature",
  "properties": {
    "iso:country":"US",
    "sg:address":"1190 Oxford Dr SE",
    "sg:city":"Conyers",
    "sg:classifiers":[
        {
            "category":"Real Estate",
            "subcategory":"Real Estate Agent",
            "type":"Services"
        },
        {
            "category":"Professional",
            "subcategory":"Business Services",
            "type":"Services"
        }
    ],
    "sg:phone":"+1 770 483 9035",
    "sg:postcode":"30013",
    "sg:province":"GA",
    "sg:tags":[
        "appraiser"
    ],
    "wof:name":"Murray Appraisal Inc",
    "wof:placetype":"venue"
},
  "geometry": {"coordinates":[-84.00609799999999,33.619768],"type":"Point"}
}