{
  "type": "Feature",
  "properties": {
    "iso:country":"US",
    "sg:address":"105 Collier Rd NW",
    "sg:city":"Atlanta",
    "sg:classifiers":[
        {
            "category":"Health Services",
            "subcategory":"Doctor",
            "type":"Services"
        }
    ],
    "sg:phone":"+1 404 351 6864",
    "sg:postcode":"30309",
    "sg:province":"GA",
    "sg:tags":[
        "physician",
        "surgeon",
        "urologist"
    ],
    "wof:name":"Atlanta Urology Associates P C",
    "wof:placetype":"venue"
},
  "geometry": {"coordinates":[-84.397173,33.808253],"type":"Point"}
}