{
  "type": "Feature",
  "properties": {
    "iso:country":"US",
    "sg:address":"2524 Lithonia West Dr",
    "sg:city":"Lithonia",
    "sg:classifiers":[
        {
            "category":"Building & Trades",
            "subcategory":"Construction",
            "type":"Services"
        }
    ],
    "sg:phone":"+1 770 484 3429",
    "sg:postcode":"30058",
    "sg:province":"GA",
    "sg:tags":[
        "general",
        "contractor"
    ],
    "wof:name":"F & J Construction Co",
    "wof:placetype":"venue"
},
  "geometry": {"coordinates":[-84.128651,33.713815],"type":"Point"}
}