{
  "type": "Feature",
  "properties": {
    "addr:full":"3670 Old Petersburg Rd Augusta GA 30907",
    "addr:housenumber":"3670",
    "addr:postcode":"30907",
    "addr:street":"Old Petersburg Rd",
    "iso:country":"US",
    "sg:address":"3670 Old Petersburg Rd",
    "sg:city":"Augusta",
    "sg:classifiers":[
        {
            "category":"Personal",
            "subcategory":"Beauty Salon",
            "type":"Services"
        }
    ],
    "sg:phone":"+1 706 210 3000",
    "sg:postcode":"30907",
    "sg:province":"GA",
    "sg:website":"www.jillwagners.com",
    "wof:name":"Jill Wagner's Salon & Day Spa",
    "wof:placetype":"venue"
},
  "geometry": {"coordinates":[-82.08702099999999,33.521698],"type":"Point"}
}