{
  "type": "Feature",
  "properties": {
    "iso:country":"US",
    "sg:address":"5040 Lake Fjord Pass",
    "sg:city":"Marietta",
    "sg:classifiers":[
        {
            "category":"Professional",
            "subcategory":"Management & Consulting",
            "type":"Services"
        }
    ],
    "sg:phone":"+1 770 650 4625",
    "sg:postcode":"30068",
    "sg:province":"GA",
    "sg:tags":[
        "consultant"
    ],
    "wof:name":"IB Medsupply Inc",
    "wof:placetype":"venue"
},
  "geometry": {"coordinates":[-84.405068,33.987045],"type":"Point"}
}