{
  "type": "Feature",
  "properties": {
    "iso:country":"US",
    "sg:address":"1861 Peeler Road",
    "sg:city":"Atlanta",
    "sg:classifiers":[
        {
            "category":"Health Services",
            "subcategory":"Doctor",
            "type":"Services"
        }
    ],
    "sg:phone":"+1 770 730 8219",
    "sg:postcode":"30338",
    "sg:province":"GA",
    "sg:tags":[
        "cardiologist"
    ],
    "wof:name":"Georgia Clinic",
    "wof:placetype":"venue"
},
  "geometry": {"coordinates":[-84.311982,33.930106],"type":"Point"}
}