{
  "type": "Feature",
  "properties": {
    "iso:country":"US",
    "sg:address":"4199 Paces Ferry Rd SE",
    "sg:city":"Atlanta",
    "sg:classifiers":[
        {
            "category":"Shopping",
            "subcategory":"Used Merchandise",
            "type":"Retail Goods"
        }
    ],
    "sg:phone":"+1 770 436 4800",
    "sg:postcode":"30339",
    "sg:province":"GA",
    "sg:tags":[
        "resale",
        "shop"
    ],
    "wof:name":"Label Resale Boutique",
    "wof:placetype":"venue"
},
  "geometry": {"coordinates":[-84.455788,33.859268],"type":"Point"}
}