{
  "type": "Feature",
  "properties": {
    "iso:country":"US",
    "sg:address":"4545 Stonegate Industrial Blvd",
    "sg:city":"Stone Mountain",
    "sg:classifiers":[
        {
            "category":"Professional",
            "subcategory":"Art Services",
            "type":"Services"
        }
    ],
    "sg:phone":"+1 404 296 7660",
    "sg:postcode":"30083",
    "sg:province":"GA",
    "sg:tags":[
        "commercial",
        "design"
    ],
    "wof:name":"Stone Mountain",
    "wof:placetype":"venue"
},
  "geometry": {"coordinates":[-84.20222800000001,33.822561],"type":"Point"}
}