{
  "type": "Feature",
  "properties": {
    "addr:full":"4030 Mundy Mill Rd Oakwood GA 30566",
    "addr:housenumber":"4030",
    "addr:postcode":"30566",
    "addr:street":"Mundy Mill Rd",
    "iso:country":"US",
    "sg:address":"4030 Mundy Mill Rd",
    "sg:city":"Oakwood",
    "sg:classifiers":[
        {
            "category":"Home & Garden",
            "subcategory":"Building Materials",
            "type":"Retail Goods"
        }
    ],
    "sg:phone":"+1 770 532 7929",
    "sg:postcode":"30566",
    "sg:province":"GA",
    "sg:tags":[
        "h",
        "covering",
        "floor",
        "paint"
    ],
    "wof:name":"South Hall Paint & Decorating",
    "wof:placetype":"venue"
},
  "geometry": {"coordinates":[-83.878103,34.240235],"type":"Point"}
}