{
  "type": "Feature",
  "properties": {
    "iso:country":"US",
    "sg:address":"821 Holly Dr",
    "sg:city":"Albany",
    "sg:classifiers":[
        {
            "category":"Building & Trades",
            "subcategory":"Electrical",
            "type":"Services"
        }
    ],
    "sg:phone":"+1 229 432 6626",
    "sg:postcode":"31705",
    "sg:province":"GA",
    "sg:tags":[
        "electric",
        "contractor"
    ],
    "wof:name":"Emerson & Sons Electric Co",
    "wof:placetype":"venue"
},
  "geometry": {"coordinates":[-84.11271499999999,31.529912],"type":"Point"}
}