{
  "type": "Feature",
  "properties": {
    "iso:country":"US",
    "sg:address":"1930 Cusseta Rd",
    "sg:city":"Columbus",
    "sg:classifiers":[
        {
            "category":"Manufacturing",
            "subcategory":"Buildings",
            "type":"Manufacturing & Wholesale Goods"
        },
        {
            "category":"Building & Trades",
            "subcategory":"Construction",
            "type":"Services"
        }
    ],
    "sg:phone":"+1 706 243 7833",
    "sg:postcode":"31903",
    "sg:province":"GA",
    "sg:tags":[
        "industrial",
        "system",
        "specialty",
        "builder",
        "heating",
        "contractor",
        "contractors-commercial",
        "home",
        "air conditioning"
    ],
    "wof:name":"Steven Mainor Builder",
    "wof:placetype":"venue"
},
  "geometry": {"coordinates":[-84.965867,32.453287],"type":"Point"}
}