{
  "type": "Feature",
  "properties": {
    "addr:full":"3449 Johnson Ferry Rd Roswell GA 30075",
    "addr:housenumber":"3449",
    "addr:postcode":"30075",
    "addr:street":"Johnson Ferry Rd",
    "iso:country":"US",
    "sg:address":"3449 Johnson Ferry Rd",
    "sg:city":"Roswell",
    "sg:classifiers":[
        {
            "category":"Manufacturing",
            "subcategory":"Printing",
            "type":"Manufacturing & Wholesale Goods"
        }
    ],
    "sg:phone":"+1 678 585 9976",
    "sg:postcode":"30075",
    "sg:province":"GA",
    "wof:name":"Graphic Partners Group",
    "wof:placetype":"venue"
},
  "geometry": {"coordinates":[-84.42001399999999,34.038621],"type":"Point"}
}