{
  "type": "Feature",
  "properties": {
    "iso:country":"US",
    "sg:address":"4824 Lawrenceville Hwy",
    "sg:city":"Lilburn",
    "sg:classifiers":[
        {
            "category":"Insurance",
            "subcategory":"Hazard Insurance",
            "type":"Services"
        }
    ],
    "sg:phone":"+1 770 931 4232",
    "sg:postcode":"30047",
    "sg:province":"GA",
    "sg:tags":[
        "warranty",
        "automobile",
        "processing"
    ],
    "wof:name":"Warranty Distributors",
    "wof:placetype":"venue"
},
  "geometry": {"coordinates":[-84.140291,33.895177],"type":"Point"}
}