{
  "type": "Feature",
  "properties": {
    "addr:full":"615 S Georgia Pkwy E Waycross GA 31501",
    "addr:housenumber":"615",
    "addr:postcode":"31501",
    "addr:street":"S Georgia Pkwy E",
    "iso:country":"US",
    "sg:address":"615 S Georgia Pkwy E",
    "sg:city":"Waycross",
    "sg:classifiers":[
        {
            "category":"Retail",
            "subcategory":"Repair Shop",
            "type":"Services"
        }
    ],
    "sg:phone":"+1 912 283 0105",
    "sg:postcode":"31501",
    "sg:province":"GA",
    "sg:tags":[
        "used",
        "merchandise"
    ],
    "wof:name":"Lariscys Upholstery Shop",
    "wof:placetype":"venue"
},
  "geometry": {"coordinates":[-82.352137,31.206367],"type":"Point"}
}