{
  "type": "Feature",
  "properties": {
    "addr:full":"14045 Abercorn St # 1206 Savannah GA 31419",
    "addr:housenumber":"14045",
    "addr:postcode":"31419",
    "addr:street":"Abercorn St # 1206",
    "iso:country":"US",
    "sg:address":"14045 Abercorn St # 1206",
    "sg:city":"Savannah",
    "sg:classifiers":[
        {
            "category":"Shopping",
            "subcategory":"Gifts & Souvenirs",
            "type":"Retail Goods"
        },
        {
            "category":"Manufacturing",
            "subcategory":"Jewelry",
            "type":"Manufacturing & Wholesale Goods"
        }
    ],
    "sg:phone":"+1 912 921 7871",
    "sg:postcode":"31419",
    "sg:province":"GA",
    "sg:tags":[
        "shop",
        "novelty"
    ],
    "sg:website":"http://www.spencergifts.com",
    "wof:name":"Spencer's",
    "wof:placetype":"venue"
},
  "geometry": {"coordinates":[-81.172729,31.98184],"type":"Point"}
}