{
  "type": "Feature",
  "properties": {
    "iso:country":"US",
    "sg:address":"4557 Crane Mill Rd",
    "sg:city":"Cornelia",
    "sg:classifiers":[
        {
            "category":"Professional",
            "subcategory":"Accounting & Tax Preparation",
            "type":"Services"
        }
    ],
    "sg:phone":"+1 706 778 7367",
    "sg:postcode":"30531",
    "sg:province":"GA",
    "sg:tags":[
        "accountant"
    ],
    "wof:name":"Suggs Accounting Svc",
    "wof:placetype":"venue"
},
  "geometry": {"coordinates":[-83.63882099999999,34.484201],"type":"Point"}
}