{
  "type": "Feature",
  "properties": {
    "addr:full":"3034 Bankhead Hwy Austell GA 30116",
    "addr:housenumber":"3034",
    "addr:postcode":"30116",
    "addr:street":"Bankhead Hwy",
    "iso:country":"US",
    "sg:address":"3034 Bankhead Hwy",
    "sg:city":"Austell",
    "sg:classifiers":[
        {
            "category":"Food & Beverages",
            "subcategory":"Liquor & Beverages",
            "type":"Retail Goods"
        }
    ],
    "sg:phone":"+1 770 941 5799",
    "sg:postcode":"30116",
    "sg:province":"GA",
    "sg:tags":[
        "beer"
    ],
    "wof:name":"Joe's Bottle Shop",
    "wof:placetype":"venue"
},
  "geometry": {"coordinates":[-84.98217200000001,33.614093],"type":"Point"}
}