{
  "type": "Feature",
  "properties": {
    "addr:full":"1380 Cleveland Ave Atlanta GA 30344",
    "addr:housenumber":"1380",
    "addr:postcode":"30344",
    "addr:street":"Cleveland Ave",
    "iso:country":"US",
    "sg:address":"1380 Cleveland Ave",
    "sg:city":"Atlanta",
    "sg:classifiers":[
        {
            "category":"Health Services",
            "subcategory":"Chiropractor",
            "type":"Services"
        }
    ],
    "sg:phone":"+1 404 765 0021",
    "sg:postcode":"30344",
    "sg:province":"GA",
    "wof:name":"Main Street Clinic",
    "wof:placetype":"venue"
},
  "geometry": {"coordinates":[-84.434196,33.6796],"type":"Point"}
}