{
  "type": "Feature",
  "properties": {
    "addr:full":"1690 Olive Rd Augusta GA 30904",
    "addr:housenumber":"1690",
    "addr:postcode":"30904",
    "addr:street":"Olive Rd",
    "iso:country":"US",
    "sg:address":"1690 Olive Rd",
    "sg:city":"Augusta",
    "sg:classifiers":[
        {
            "category":"Government",
            "subcategory":"Office",
            "type":"Public Place"
        }
    ],
    "sg:phone":"+1 706 733 2609",
    "sg:postcode":"30904",
    "sg:province":"GA",
    "sg:tags":[
        "government-city",
        "government-united",
        "township",
        "state",
        "village"
    ],
    "wof:name":"Housing Authority Of The City Of Augusta",
    "wof:placetype":"venue"
},
  "geometry": {"coordinates":[-82.007244,33.454174],"type":"Point"}
}