{
  "type": "Feature",
  "properties": {
    "iso:country":"US",
    "sg:address":"203 W 6th St",
    "sg:city":"Waynesboro",
    "sg:classifiers":[
        {
            "category":"Autos & Motor Vehicles",
            "subcategory":"Auto Supplies",
            "type":"Retail Goods"
        }
    ],
    "sg:phone":"+1 706 554 1114",
    "sg:postcode":"30830",
    "sg:province":"GA",
    "sg:tags":[
        "automobile",
        "part",
        "batteries-storage"
    ],
    "sg:website":"http://www.advanceautoparts.com",
    "wof:name":"Advance Auto Parts",
    "wof:placetype":"venue"
},
  "geometry": {"coordinates":[-82.016789,33.089529],"type":"Point"}
}