{
  "type": "Feature",
  "properties": {
    "iso:country":"US",
    "sg:address":"101 N Young St Apt A",
    "sg:city":"Thomasville",
    "sg:classifiers":[
        {
            "category":"Professional",
            "subcategory":"Detective & Security Services",
            "type":"Services"
        }
    ],
    "sg:phone":"+1 229 224 9874",
    "sg:postcode":"31792",
    "sg:province":"GA",
    "sg:tags":[
        "information",
        "bureau"
    ],
    "wof:name":"Vanessa Cleanin Service",
    "wof:placetype":"venue"
},
  "geometry": {"coordinates":[-83.97807299999999,30.841961],"type":"Point"}
}