{
  "type": "Feature",
  "properties": {
    "iso:country":"US",
    "sg:address":"248 Lafayette Dr",
    "sg:city":"Augusta",
    "sg:classifiers":[
        {
            "category":"Organizations",
            "subcategory":"Religious Organization",
            "type":"Services"
        }
    ],
    "sg:phone":"+1 706 738 8753",
    "sg:postcode":"30909",
    "sg:province":"GA",
    "wof:name":"Rev Willie Jackson",
    "wof:placetype":"venue"
},
  "geometry": {"coordinates":[-82.036597,33.504989],"type":"Point"}
}