{
  "type": "Feature",
  "properties": {
    "iso:country":"US",
    "sg:address":"2299 Peachtree Rd NE",
    "sg:city":"Atlanta",
    "sg:classifiers":[
        {
            "category":"Professional",
            "subcategory":"Lawyer & Legal Services",
            "type":"Services"
        }
    ],
    "sg:phone":"+1 404 367 9513",
    "sg:postcode":"30309",
    "sg:province":"GA",
    "wof:name":"Law Office",
    "wof:placetype":"venue"
},
  "geometry": {"coordinates":[-84.389019,33.817608],"type":"Point"}
}