{
  "type": "Feature",
  "properties": {
    "addr:full":"525 Clubhouse Dr Peachtree City GA 30269",
    "addr:housenumber":"525",
    "addr:postcode":"30269",
    "addr:street":"Clubhouse Dr",
    "iso:country":"US",
    "sg:address":"525 Clubhouse Dr",
    "sg:city":"Peachtree City",
    "sg:classifiers":[
        {
            "category":"Banks & Credit Unions",
            "subcategory":"Investment Brokerage",
            "type":"Services"
        },
        {
            "category":"Professional",
            "subcategory":"Management & Consulting",
            "type":"Services"
        }
    ],
    "sg:phone":"+1 770 631 4007",
    "sg:postcode":"30269",
    "sg:province":"GA",
    "sg:tags":[
        "advisory",
        "financial"
    ],
    "wof:name":"Derbend Asset Management LLC",
    "wof:placetype":"venue"
},
  "geometry": {"coordinates":[-84.579087,33.3705],"type":"Point"}
}