{
  "type": "Feature",
  "properties": {
    "addr:full":"6428 US Hwy 29 Palmetto GA 30268",
    "addr:housenumber":"6428",
    "addr:postcode":"30268",
    "addr:street":"Us Hwy 29",
    "iso:country":"US",
    "sg:address":"6428 US Hwy 29",
    "sg:city":"Palmetto",
    "sg:classifiers":[
        {
            "category":"Retail",
            "subcategory":"Auto Repair",
            "type":"Services"
        }
    ],
    "sg:phone":"+1 770 463 0020",
    "sg:postcode":"30268",
    "sg:province":"GA",
    "sg:tags":[
        "repairing",
        "automobile"
    ],
    "wof:name":"ABR Auto",
    "wof:placetype":"venue"
},
  "geometry": {"coordinates":[-84.671374,33.506068],"type":"Point"}
}