{
  "type": "Feature",
  "properties": {
    "addr:full":"1665 W Lake Ct NW Atlanta GA 30314",
    "addr:housenumber":"1665",
    "addr:postcode":"30314",
    "addr:street":"W Lake Ct Nw",
    "iso:country":"US",
    "sg:address":"1665 W Lake Ct NW",
    "sg:city":"Atlanta",
    "sg:classifiers":[
        {
            "category":"Restaurant",
            "type":"Food & Drink"
        }
    ],
    "sg:phone":"+1 770 923 2313",
    "sg:postcode":"30314",
    "sg:province":"GA",
    "sg:tags":[
        "pizza"
    ],
    "wof:name":"Kurani Pizza Inc",
    "wof:placetype":"venue"
},
  "geometry": {"coordinates":[-84.443133,33.759245],"type":"Point"}
}