{
  "type": "Feature",
  "properties": {
    "iso:country":"US",
    "sg:address":"9510 Poole Rd",
    "sg:city":"Villa Rica",
    "sg:classifiers":[
        {
            "category":"Building & Trades",
            "subcategory":"Landscaping Services",
            "type":"Services"
        }
    ],
    "sg:phone":"+1 770 456 2174",
    "sg:postcode":"30180",
    "sg:province":"GA",
    "sg:tags":[
        "landscape"
    ],
    "wof:name":"Brigham Landscape Designs",
    "wof:placetype":"venue"
},
  "geometry": {"coordinates":[-84.887846,33.710726],"type":"Point"}
}