{
  "type": "Feature",
  "properties": {
    "addr:full":"86 Center Rd SE Cartersville GA 30121",
    "addr:housenumber":"86",
    "addr:postcode":"30121",
    "addr:street":"Center Rd Se",
    "iso:country":"US",
    "sg:address":"86 Center Rd SE",
    "sg:city":"Cartersville",
    "sg:classifiers":[
        {
            "category":"Wholesale",
            "subcategory":"Computers",
            "type":"Manufacturing & Wholesale Goods"
        }
    ],
    "sg:phone":"+1 770 606 9700",
    "sg:postcode":"30121",
    "sg:province":"GA",
    "sg:tags":[
        "communications",
        "datum"
    ],
    "wof:name":"Telenet Systems Inc",
    "wof:placetype":"venue"
},
  "geometry": {"coordinates":[-84.78146599999999,34.183553],"type":"Point"}
}