{
  "type": "Feature",
  "properties": {
    "addr:full":"6628 Eubank Dr Appling GA 30802",
    "addr:housenumber":"6628",
    "addr:postcode":"30802",
    "addr:street":"Eubank Dr",
    "iso:country":"US",
    "sg:address":"6628 Eubank Dr",
    "sg:city":"Appling",
    "sg:classifiers":[
        {
            "category":"Recreation",
            "type":"Entertainment"
        }
    ],
    "sg:phone":"+1 706 309 9312",
    "sg:postcode":"30802",
    "sg:province":"GA",
    "sg:tags":[
        "fitness",
        "physical",
        "facility"
    ],
    "wof:name":"Martial Arts America",
    "wof:placetype":"venue"
},
  "geometry": {"coordinates":[-82.33177999999999,33.644477],"type":"Point"}
}