{
  "type": "Feature",
  "properties": {
    "addr:full":"80 Guinn Dr Oxford GA 30054",
    "addr:housenumber":"80",
    "addr:postcode":"30054",
    "addr:street":"Guinn Dr",
    "iso:country":"US",
    "sg:address":"80 Guinn Dr",
    "sg:city":"Oxford",
    "sg:classifiers":[
        {
            "category":"Professional",
            "subcategory":"Computer Services",
            "type":"Services"
        }
    ],
    "sg:phone":"+1 770 788 8333",
    "sg:postcode":"30054",
    "sg:province":"GA",
    "wof:name":"Tech Neque Inc",
    "wof:placetype":"venue"
},
  "geometry": {"coordinates":[-83.86970100000001,33.679213],"type":"Point"}
}