{
  "type": "Feature",
  "properties": {
    "iso:country":"US",
    "sg:address":"129 W Walnut St",
    "sg:city":"Jesup",
    "sg:classifiers":[
        {
            "category":"Organizations",
            "subcategory":"Religious Organization",
            "type":"Services"
        }
    ],
    "sg:phone":"+1 912 530 6699",
    "sg:postcode":"31545",
    "sg:province":"GA",
    "wof:name":"Leola Wilson Resurctn Bptst Ch",
    "wof:placetype":"venue"
},
  "geometry": {"coordinates":[-81.8828,31.60697],"type":"Point"}
}