{
  "type": "Feature",
  "properties": {
    "iso:country":"US",
    "sg:address":"201 Three Oaks Dr",
    "sg:city":"Lawrenceville",
    "sg:classifiers":[
        {
            "category":"Freight",
            "type":"Transportation"
        }
    ],
    "sg:phone":"+1 770 277 1150",
    "sg:postcode":"30045",
    "sg:province":"GA",
    "wof:name":"ALP",
    "wof:placetype":"venue"
},
  "geometry": {"coordinates":[-83.973919,33.931549],"type":"Point"}
}