{
  "type": "Feature",
  "properties": {
    "addr:full":"875 Oakwood Dr East Dublin GA 31027",
    "addr:housenumber":"875",
    "addr:postcode":"31027",
    "addr:street":"Oakwood Dr East",
    "iso:country":"US",
    "sg:address":"875 Oakwood Dr",
    "sg:city":"East Dublin",
    "sg:classifiers":[
        {
            "category":"Bars & Pubs",
            "type":"Food & Drink"
        }
    ],
    "sg:phone":"+1 478 274 8866",
    "sg:postcode":"31027",
    "sg:province":"GA",
    "wof:name":"Hawg Wild Salon",
    "wof:placetype":"venue"
},
  "geometry": {"coordinates":[-82.86865899999999,32.527766],"type":"Point"}
}