{
  "type": "Feature",
  "properties": {
    "iso:country":"US",
    "sg:address":"300 Oakland Rd",
    "sg:city":"Leesburg",
    "sg:classifiers":[
        {
            "category":"Professional",
            "subcategory":"Advertising",
            "type":"Services"
        }
    ],
    "sg:phone":"+1 229 888 1229",
    "sg:postcode":"31763",
    "sg:province":"GA",
    "sg:tags":[
        "distribution"
    ],
    "wof:name":"ACC Distributors",
    "wof:placetype":"venue"
},
  "geometry": {"coordinates":[-84.25747699999999,31.681614],"type":"Point"}
}