{
  "type": "Feature",
  "properties": {
    "iso:country":"US",
    "sg:address":"419 S Glenwood Ave",
    "sg:city":"Dalton",
    "sg:classifiers":[
        {
            "category":"Manufacturing",
            "subcategory":"Textiles",
            "type":"Manufacturing & Wholesale Goods"
        }
    ],
    "sg:phone":"+1 706 275 0257",
    "sg:postcode":"30721",
    "sg:province":"GA",
    "sg:tags":[
        "finishing"
    ],
    "wof:name":"Trinity Textiles Finishers Inc",
    "wof:placetype":"venue"
},
  "geometry": {"coordinates":[-84.965414,34.767945],"type":"Point"}
}