{
  "type": "Feature",
  "properties": {
    "iso:country":"US",
    "sg:address":"2973 Old River Rd",
    "sg:city":"Broxton",
    "sg:classifiers":[
        {
            "category":"Farming",
            "subcategory":"Farm",
            "type":"Manufacturing & Wholesale Goods"
        }
    ],
    "sg:phone":"+1 912 359 3230",
    "sg:postcode":"31519",
    "sg:province":"GA",
    "sg:tags":[
        "crop",
        "general"
    ],
    "wof:name":"Archie Rish",
    "wof:placetype":"venue"
},
  "geometry": {"coordinates":[-82.87540799999999,31.689816],"type":"Point"}
}