{
  "type": "Feature",
  "properties": {
    "iso:country":"US",
    "sg:address":"318 Pine Forest St",
    "sg:city":"Dublin",
    "sg:classifiers":[
        {
            "category":"Retail",
            "subcategory":"Repair Shop",
            "type":"Services"
        }
    ],
    "sg:phone":"+1 478 272 7264",
    "sg:postcode":"31021",
    "sg:province":"GA",
    "sg:tags":[
        "machine",
        "copying"
    ],
    "wof:name":"ABC Business Machines",
    "wof:placetype":"venue"
},
  "geometry": {"coordinates":[-82.935329,32.54174],"type":"Point"}
}