{
  "type": "Feature",
  "properties": {
    "addr:full":"110 Rocky Creek Ct Fayetteville GA 30214",
    "addr:housenumber":"110",
    "addr:postcode":"30214",
    "addr:street":"Rocky Creek Ct",
    "iso:country":"US",
    "sg:address":"110 Rocky Creek Ct",
    "sg:city":"Fayetteville",
    "sg:classifiers":[
        {
            "category":"Health Services",
            "subcategory":"Clinic",
            "type":"Services"
        }
    ],
    "sg:phone":"+1 770 719 1510",
    "sg:postcode":"30214",
    "sg:province":"GA",
    "wof:name":"Innerflex Medical Inc",
    "wof:placetype":"venue"
},
  "geometry": {"coordinates":[-84.481539,33.504036],"type":"Point"}
}