{
  "type": "Feature",
  "properties": {
    "iso:country":"US",
    "sg:address":"9270 Stonemist Trce",
    "sg:city":"Roswell",
    "sg:classifiers":[
        {
            "category":"Professional",
            "subcategory":"Advertising",
            "type":"Services"
        }
    ],
    "sg:phone":"+1 770 998 8815",
    "sg:postcode":"30076",
    "sg:province":"GA",
    "sg:tags":[
        "agency"
    ],
    "wof:name":"Renaissance Comm Group Inc",
    "wof:placetype":"venue"
},
  "geometry": {"coordinates":[-84.315881,33.991796],"type":"Point"}
}