{
  "type": "Feature",
  "properties": {
    "iso:country":"US",
    "sg:address":"2550 Sandy Plains Rd Suite 114",
    "sg:city":"Marietta",
    "sg:classifiers":[
        {
            "category":"Personal",
            "subcategory":"Beauty Salon",
            "type":"Services"
        }
    ],
    "sg:phone":"+1 404 808 6744",
    "sg:postcode":"30066",
    "sg:province":"GA",
    "sg:tags":[
        "hair"
    ],
    "sg:website":"www.rose-lees.com/index.html",
    "wof:name":"Roselee's Natural Hair Care",
    "wof:placetype":"venue"
},
  "geometry": {"coordinates":[-84.493527,34.011759],"type":"Point"}
}