{
  "type": "Feature",
  "properties": {
    "addr:full":"4005 Windward Plz Alpharetta GA 30005",
    "addr:housenumber":"4005",
    "addr:postcode":"30005",
    "addr:street":"Windward Plz",
    "iso:country":"US",
    "sg:address":"4005 Windward Plz",
    "sg:city":"Alpharetta",
    "sg:classifiers":[
        {
            "category":"Banks & Credit Unions",
            "subcategory":"Investment Brokerage",
            "type":"Services"
        }
    ],
    "sg:phone":"+1 678 319 7040",
    "sg:postcode":"30005",
    "sg:province":"GA",
    "sg:tags":[
        "brokerage"
    ],
    "wof:name":"E Trade Financial Corp",
    "wof:placetype":"venue"
},
  "geometry": {"coordinates":[-84.239301,34.094271],"type":"Point"}
}