{
  "type": "Feature",
  "properties": {
    "addr:full":"5836 Buford Hwy Norcross GA 30071",
    "addr:housenumber":"5836",
    "addr:postcode":"30071",
    "addr:street":"Buford Hwy",
    "iso:country":"US",
    "sg:address":"5836 Buford Hwy",
    "sg:city":"Norcross",
    "sg:classifiers":[
        {
            "category":"Health Services",
            "subcategory":"Dentist",
            "type":"Services"
        }
    ],
    "sg:phone":"+1 770 248 1100",
    "sg:postcode":"30071",
    "sg:province":"GA",
    "wof:name":"Family Dental Lab",
    "wof:placetype":"venue"
},
  "geometry": {"coordinates":[-84.212799,33.937801],"type":"Point"}
}