{
  "type": "Feature",
  "properties": {
    "iso:country":"US",
    "sg:address":"8835 Camp Ave",
    "sg:city":"Jonesboro",
    "sg:classifiers":[
        {
            "category":"Personal",
            "subcategory":"Beauty Salon",
            "type":"Services"
        }
    ],
    "sg:phone":"+1 770 210 1300",
    "sg:postcode":"30236",
    "sg:province":"GA",
    "wof:name":"Pizzazz Hair Salon",
    "wof:placetype":"venue"
},
  "geometry": {"coordinates":[-84.322497,33.515537],"type":"Point"}
}