{
  "type": "Feature",
  "properties": {
    "addr:full":"785 Shugart Rd Dalton GA 30720",
    "addr:housenumber":"785",
    "addr:postcode":"30720",
    "addr:street":"Shugart Rd",
    "iso:country":"US",
    "sg:address":"785 Shugart Rd",
    "sg:city":"Dalton",
    "sg:classifiers":[
        {
            "category":"Personal",
            "subcategory":"Beauty Salon",
            "type":"Services"
        }
    ],
    "sg:phone":"+1 706 260 2547",
    "sg:postcode":"30720",
    "sg:province":"GA",
    "wof:name":"Great Clips",
    "wof:placetype":"venue"
},
  "geometry": {"coordinates":[-84.996965,34.784205],"type":"Point"}
}