{
  "type": "Feature",
  "properties": {
    "addr:full":"210 E Main St Canton GA 30114",
    "addr:housenumber":"210",
    "addr:postcode":"30114",
    "addr:street":"E Main St",
    "iso:country":"US",
    "sg:address":"210 E Main St",
    "sg:city":"Canton",
    "sg:classifiers":[
        {
            "category":"Professional",
            "type":"Services"
        }
    ],
    "sg:phone":"+1 678 493 5936",
    "sg:postcode":"30114",
    "sg:province":"GA",
    "wof:name":"Simply Scrapping",
    "wof:placetype":"venue"
},
  "geometry": {"coordinates":[-84.487487,34.236406],"type":"Point"}
}