{
  "type": "Feature",
  "properties": {
    "iso:country":"US",
    "sg:address":"5082 Rosestone Dr NW",
    "sg:city":"Lilburn",
    "sg:classifiers":[
        {
            "category":"Building & Trades",
            "subcategory":"Construction",
            "type":"Services"
        }
    ],
    "sg:phone":"+1 770 231 6870",
    "sg:postcode":"30047",
    "sg:province":"GA",
    "sg:tags":[
        "hanging",
        "contractor"
    ],
    "wof:name":"Carlos Martinez",
    "wof:placetype":"venue"
},
  "geometry": {"coordinates":[-84.15660699999999,33.901708],"type":"Point"}
}