{
  "type": "Feature",
  "properties": {
    "addr:full":"248 Commerce Dr Peachtree City GA 30269",
    "addr:housenumber":"248",
    "addr:postcode":"30269",
    "addr:street":"Commerce Dr",
    "iso:country":"US",
    "sg:address":"248 Commerce Dr",
    "sg:city":"Peachtree City",
    "sg:classifiers":[
        {
            "category":"Retail",
            "subcategory":"Laundry & Dry Cleaning",
            "type":"Services"
        }
    ],
    "sg:phone":"+1 770 487 6718",
    "sg:postcode":"30269",
    "sg:province":"GA",
    "sg:tags":[
        "garment",
        "agent"
    ],
    "wof:name":"Professional Cleaners",
    "wof:placetype":"venue"
},
  "geometry": {"coordinates":[-84.592496,33.399417],"type":"Point"}
}