{
  "type": "Feature",
  "properties": {
    "addr:full":"202 McKinney Rd Blue Ridge GA 30513",
    "addr:housenumber":"202",
    "addr:postcode":"30513",
    "addr:street":"Mckinney Rd",
    "iso:country":"US",
    "sg:address":"202 McKinney Rd",
    "sg:city":"Blue Ridge",
    "sg:classifiers":[
        {
            "category":"Real Estate",
            "subcategory":"Real Estate Operator",
            "type":"Services"
        }
    ],
    "sg:phone":"+1 706 632 5981",
    "sg:postcode":"30513",
    "sg:province":"GA",
    "sg:tags":[
        "apartment"
    ],
    "wof:name":"Dogwood Apartments",
    "wof:placetype":"venue"
},
  "geometry": {"coordinates":[-84.29196899999999,34.87808],"type":"Point"}
}