{
  "type": "Feature",
  "properties": {
    "iso:country":"US",
    "sg:address":"7413 Taejon Ct",
    "sg:city":"Fort Stewart",
    "sg:classifiers":[
        {
            "category":"Professional",
            "subcategory":"Business Services",
            "type":"Services"
        }
    ],
    "sg:phone":"+1 912 876 6519",
    "sg:postcode":"31315",
    "sg:province":"GA",
    "sg:tags":[
        "clerk"
    ],
    "wof:name":"Linda Gifford",
    "wof:placetype":"venue"
},
  "geometry": {"coordinates":[-81.593932,31.896345],"type":"Point"}
}