{
  "type": "Feature",
  "properties": {
    "iso:country":"US",
    "sg:address":"352 Seed Tick Rd",
    "sg:city":"Dawsonville",
    "sg:classifiers":[
        {
            "category":"Professional",
            "type":"Services"
        }
    ],
    "sg:phone":"+1 706 265 6046",
    "sg:postcode":"30534",
    "sg:province":"GA",
    "wof:name":"Scott A Barnhart",
    "wof:placetype":"venue"
},
  "geometry": {"coordinates":[-84.06005500000001,34.395584],"type":"Point"}
}