{
  "type": "Feature",
  "properties": {
    "iso:country":"US",
    "sg:address":"1120 Airport Pkwy",
    "sg:city":"Gainesville",
    "sg:classifiers":[
        {
            "category":"Manufacturing",
            "subcategory":"Rubber & Plastics",
            "type":"Manufacturing & Wholesale Goods"
        }
    ],
    "sg:phone":"+1 770 532 9101",
    "sg:postcode":"30501",
    "sg:province":"GA",
    "sg:tags":[
        "product"
    ],
    "wof:name":"Fastco Products Corp",
    "wof:placetype":"venue"
},
  "geometry": {"coordinates":[-83.824207,34.276277],"type":"Point"}
}