{
  "type": "Feature",
  "properties": {
    "addr:full":"1627 Old River Rd SW Rome GA 30165",
    "addr:housenumber":"1627",
    "addr:postcode":"ga 30165",
    "addr:street":"Old River Rd Sw",
    "iso:country":"US",
    "sg:address":"1627 Old River Rd SW",
    "sg:city":"Rome",
    "sg:classifiers":[
        {
            "category":"Professional",
            "subcategory":"Advertising",
            "type":"Services"
        }
    ],
    "sg:phone":"+1 706 234 9445",
    "sg:postcode":"30165",
    "sg:province":"GA",
    "wof:name":"TV Facts",
    "wof:placetype":"venue"
},
  "geometry": {"coordinates":[-85.423796,34.250359],"type":"Point"}
}