{
  "type": "Feature",
  "properties": {
    "iso:country":"US",
    "sg:address":"1797 Lakewood Ter SE",
    "sg:city":"Atlanta",
    "sg:classifiers":[
        {
            "category":"Professional",
            "subcategory":"Advertising",
            "type":"Services"
        },
        {
            "category":"Manufacturing",
            "subcategory":"Signs",
            "type":"Manufacturing & Wholesale Goods"
        }
    ],
    "sg:phone":"+1 404 627 8778",
    "sg:postcode":"30315",
    "sg:province":"GA",
    "sg:tags":[
        "specialty"
    ],
    "wof:name":"2001 Art Studio",
    "wof:placetype":"venue"
},
  "geometry": {"coordinates":[-84.37908899999999,33.705035],"type":"Point"}
}