{
  "type": "Feature",
  "properties": {
    "addr:full":"330 Alcovy Way Covington GA 30014",
    "addr:housenumber":"330",
    "addr:postcode":"30014",
    "addr:street":"Alcovy Way",
    "iso:country":"US",
    "sg:address":"330 Alcovy Way",
    "sg:city":"Covington",
    "sg:classifiers":[
        {
            "category":"Professional",
            "subcategory":"Art Services",
            "type":"Services"
        }
    ],
    "sg:phone":"+1 404 409 8144",
    "sg:postcode":"30014",
    "sg:province":"GA",
    "sg:tags":[
        "commercial",
        "design"
    ],
    "wof:name":"Rogers Graphic Machinery",
    "wof:placetype":"venue"
},
  "geometry": {"coordinates":[-83.80083399999999,33.600351],"type":"Point"}
}