{
  "type": "Feature",
  "properties": {
    "addr:full":"6715 Greenbower Ln Atlanta GA 30349",
    "addr:housenumber":"6715",
    "addr:postcode":"30349",
    "addr:street":"Greenbower Ln",
    "iso:country":"US",
    "sg:address":"6715 Greenbower Ln",
    "sg:city":"Atlanta",
    "sg:classifiers":[
        {
            "category":"Professional",
            "subcategory":"Business Services",
            "type":"Services"
        }
    ],
    "sg:phone":"+1 770 996 8886",
    "sg:postcode":"30349",
    "sg:province":"GA",
    "wof:name":"Jarco Business Svc Inc",
    "wof:placetype":"venue"
},
  "geometry": {"coordinates":[-84.478926,33.572255],"type":"Point"}
}