{
  "type": "Feature",
  "properties": {
    "iso:country":"US",
    "sg:address":"3468 Edgewood Cir",
    "sg:city":"Gainesville",
    "sg:classifiers":[
        {
            "category":"Farming",
            "subcategory":"Farm",
            "type":"Manufacturing & Wholesale Goods"
        }
    ],
    "sg:phone":"+1 770 536 4734",
    "sg:postcode":"30506",
    "sg:province":"GA",
    "sg:tags":[
        "crop",
        "general"
    ],
    "wof:name":"Joe Pethel",
    "wof:placetype":"venue"
},
  "geometry": {"coordinates":[-83.866043,34.358489],"type":"Point"}
}