{
  "type": "Feature",
  "properties": {
    "iso:country":"US",
    "sg:address":"718 US Hwy 78",
    "sg:city":"Temple",
    "sg:classifiers":[
        {
            "category":"Building & Trades",
            "subcategory":"Construction",
            "type":"Services"
        }
    ],
    "sg:phone":"+1 770 562 5505",
    "sg:postcode":"30179",
    "sg:province":"GA",
    "sg:tags":[
        "contractor"
    ],
    "wof:name":"Construction Dimentions",
    "wof:placetype":"venue"
},
  "geometry": {"coordinates":[-85.00983600000001,33.733973],"type":"Point"}
}