{
  "type": "Feature",
  "properties": {
    "addr:full":"228 College Ave Hartwell GA 30643",
    "addr:housenumber":"228",
    "addr:postcode":"30643",
    "addr:street":"College Ave",
    "iso:country":"US",
    "sg:address":"228 College Ave",
    "sg:city":"Hartwell",
    "sg:classifiers":[
        {
            "category":"Building & Trades",
            "subcategory":"Construction",
            "type":"Services"
        }
    ],
    "sg:phone":"+1 706 376 2093",
    "sg:postcode":"30643",
    "sg:province":"GA",
    "sg:tags":[
        "general",
        "contractor"
    ],
    "wof:name":"Matrix Admin & Constr LLC",
    "wof:placetype":"venue"
},
  "geometry": {"coordinates":[-82.928057,34.353735],"type":"Point"}
}