{
  "type": "Feature",
  "properties": {
    "iso:country":"US",
    "sg:address":"2581 Betty Jean Dr",
    "sg:city":"Jonesboro",
    "sg:classifiers":[
        {
            "category":"Real Estate",
            "subcategory":"Real Estate Operator",
            "type":"Services"
        }
    ],
    "sg:phone":"+1 770 473 1913",
    "sg:postcode":"30236",
    "sg:province":"GA",
    "sg:tags":[
        "property",
        "lessor"
    ],
    "wof:name":"Exousia Corporation",
    "wof:placetype":"venue"
},
  "geometry": {"coordinates":[-84.306293,33.53037],"type":"Point"}
}