{
  "type": "Feature",
  "properties": {
    "addr:full":"1208 Martin Luther King Jr Blvd Savannah GA 31415",
    "addr:housenumber":"1208",
    "addr:postcode":"31415",
    "addr:street":"Martin Luther King Jr Blvd",
    "iso:country":"US",
    "sg:address":"1208 Martin Luther King Jr Blvd",
    "sg:city":"Savannah",
    "sg:classifiers":[
        {
            "category":"Real Estate",
            "subcategory":"Real Estate Agent",
            "type":"Services"
        }
    ],
    "sg:phone":"+1 912 236 1689",
    "sg:postcode":"31415",
    "sg:province":"GA",
    "sg:tags":[
        "management"
    ],
    "wof:name":"E F Thornton Realty",
    "wof:placetype":"venue"
},
  "geometry": {"coordinates":[-81.102847,32.065354],"type":"Point"}
}