{
  "type": "Feature",
  "properties": {
    "addr:full":"6779 Bells Ferry Rd Woodstock GA 30189",
    "addr:housenumber":"6779",
    "addr:postcode":"30189",
    "addr:street":"Bells Ferry Rd",
    "iso:country":"US",
    "sg:address":"6779 Bells Ferry Rd",
    "sg:city":"Woodstock",
    "sg:classifiers":[
        {
            "category":"Professional",
            "subcategory":"Management & Consulting",
            "type":"Services"
        }
    ],
    "sg:phone":"+1 770 635 8870",
    "sg:postcode":"30189",
    "sg:province":"GA",
    "sg:tags":[
        "science",
        "consultant",
        "academic"
    ],
    "wof:name":"Nova Consulting Group",
    "wof:placetype":"venue"
},
  "geometry": {"coordinates":[-84.588077,34.15157],"type":"Point"}
}