{
  "type": "Feature",
  "properties": {
    "addr:full":"2167 Northlake Pkwy Tucker GA 30084",
    "addr:housenumber":"2167",
    "addr:postcode":"30084",
    "addr:street":"Northlake Pkwy",
    "iso:country":"US",
    "sg:address":"2167 Northlake Pkwy",
    "sg:city":"Tucker",
    "sg:classifiers":[
        {
            "category":"Professional",
            "subcategory":"Lawyer & Legal Services",
            "type":"Services"
        }
    ],
    "sg:phone":"+1 770 270 9214",
    "sg:postcode":"30084",
    "sg:province":"GA",
    "sg:tags":[
        "attorney"
    ],
    "wof:name":"Laxavier Reddick-Hood Law Ofc",
    "wof:placetype":"venue"
},
  "geometry": {"coordinates":[-84.24452599999999,33.848192],"type":"Point"}
}