{
  "type": "Feature",
  "properties": {
    "iso:country":"US",
    "sg:address":"5040 State Hwy 92",
    "sg:city":"Acworth",
    "sg:classifiers":[
        {
            "category":"Restaurant",
            "type":"Food & Drink"
        }
    ],
    "sg:phone":"+1 770 974 5420",
    "sg:postcode":"30102",
    "sg:province":"GA",
    "wof:name":"KFC",
    "wof:placetype":"venue"
},
  "geometry": {"coordinates":[-84.60571299999999,34.089162],"type":"Point"}
}