{
  "type": "Feature",
  "properties": {
    "iso:country":"US",
    "sg:address":"2389 Atkinson Rd",
    "sg:city":"Loganville",
    "sg:classifiers":[
        {
            "category":"Sports & Exercise",
            "subcategory":"Bowling",
            "type":"Entertainment"
        }
    ],
    "sg:phone":"+1 770 466 9293",
    "sg:postcode":"30052",
    "sg:province":"GA",
    "sg:tags":[
        "center"
    ],
    "wof:name":"Bowling Enterprises Inc",
    "wof:placetype":"venue"
},
  "geometry": {"coordinates":[-83.859396,33.796776],"type":"Point"}
}