{
  "type": "Feature",
  "properties": {
    "addr:full":"4110 Cove Dr Lake Park GA 31636",
    "addr:housenumber":"4110",
    "addr:postcode":"31636",
    "addr:street":"Cove Dr",
    "iso:country":"US",
    "sg:address":"4110 Cove Dr",
    "sg:city":"Lake Park",
    "sg:classifiers":[
        {
            "category":"Freight",
            "type":"Transportation"
        }
    ],
    "sg:phone":"+1 229 559 3058",
    "sg:postcode":"31636",
    "sg:province":"GA",
    "sg:tags":[
        "firm",
        "over",
        "road",
        "trucking"
    ],
    "wof:name":"N and J Transportation",
    "wof:placetype":"venue"
},
  "geometry": {"coordinates":[-83.23317400000001,30.716691],"type":"Point"}
}