{
  "type": "Feature",
  "properties": {
    "iso:country":"US",
    "sg:address":"4470 N Shallowford Rd",
    "sg:city":"Atlanta",
    "sg:classifiers":[
        {
            "category":"Health Services",
            "subcategory":"Doctor",
            "type":"Services"
        }
    ],
    "sg:phone":"+1 770 458 1218",
    "sg:postcode":"30338",
    "sg:province":"GA",
    "wof:name":"Miller Alan B MD",
    "wof:placetype":"venue"
},
  "geometry": {"coordinates":[-84.305801,33.922001],"type":"Point"}
}