{
  "type": "Feature",
  "properties": {
    "addr:full":"192 Marietta Hwy Canton GA 30114",
    "addr:housenumber":"192",
    "addr:postcode":"30114",
    "addr:street":"Marietta Hwy",
    "iso:country":"US",
    "sg:address":"192 Marietta Hwy",
    "sg:city":"Canton",
    "sg:classifiers":[
        {
            "category":"Building & Trades",
            "subcategory":"Locksmith",
            "type":"Services"
        }
    ],
    "sg:phone":"+1 678 321 4153",
    "sg:postcode":"30114",
    "sg:province":"GA",
    "sg:tags":[
        "key"
    ],
    "wof:name":"B&h Emergency Locksmith",
    "wof:placetype":"venue"
},
  "geometry": {"coordinates":[-84.49524,34.243029],"type":"Point"}
}