{
  "type": "Feature",
  "properties": {
    "iso:country":"US",
    "sg:address":"2291 Fairburn Road SW",
    "sg:city":"Atlanta",
    "sg:classifiers":[
        {
            "category":"Health Services",
            "subcategory":"Dentist",
            "type":"Services"
        }
    ],
    "sg:phone":"+1 404 349 4343",
    "sg:postcode":"30331",
    "sg:province":"GA",
    "wof:name":"White Mae T DDS",
    "wof:placetype":"venue"
},
  "geometry": {"coordinates":[-84.511065,33.691909],"type":"Point"}
}