{
  "type": "Feature",
  "properties": {
    "addr:full":"272 Veterans Memorial Pkwy SW Mableton GA 30126",
    "addr:housenumber":"272",
    "addr:postcode":"30126",
    "addr:street":"Veterans Memorial Pkwy Sw",
    "iso:country":"US",
    "sg:address":"272 Veterans Memorial Pkwy SW",
    "sg:city":"Mableton",
    "sg:classifiers":[
        {
            "category":"Home & Garden",
            "subcategory":"Carpets & Floor Coverings",
            "type":"Retail Goods"
        }
    ],
    "sg:phone":"+1 770 732 0777",
    "sg:postcode":"30126",
    "sg:province":"GA",
    "sg:tags":[
        "dealer",
        "rug"
    ],
    "wof:name":"Carpet Depot",
    "wof:placetype":"venue"
},
  "geometry": {"coordinates":[-84.56184399999999,33.814702],"type":"Point"}
}