{
  "type": "Feature",
  "properties": {
    "iso:country":"US",
    "sg:address":"210 W Broad St",
    "sg:city":"Louisville",
    "sg:classifiers":[
        {
            "category":"Banks & Credit Unions",
            "subcategory":"Bank",
            "type":"Services"
        }
    ],
    "sg:phone":"+1 478 625 0260",
    "sg:postcode":"30434",
    "sg:province":"GA",
    "sg:tags":[
        "personal",
        "institution"
    ],
    "wof:name":"Primerica",
    "wof:placetype":"venue"
},
  "geometry": {"coordinates":[-82.41136,33.001442],"type":"Point"}
}