{
  "type": "Feature",
  "properties": {
    "addr:full":"4055 Five Oaks Ct Powder Springs GA 30127",
    "addr:housenumber":"4055",
    "addr:postcode":"30127",
    "addr:street":"Five Oaks Ct",
    "iso:country":"US",
    "sg:address":"4055 Five Oaks Ct",
    "sg:city":"Powder Springs",
    "sg:classifiers":[
        {
            "category":"Professional",
            "type":"Services"
        }
    ],
    "sg:phone":"+1 770 900 0042",
    "sg:postcode":"30127",
    "sg:province":"GA",
    "wof:name":"BMS Roadside Svc",
    "wof:placetype":"venue"
},
  "geometry": {"coordinates":[-84.673669,33.839206],"type":"Point"}
}