{
  "type": "Feature",
  "properties": {
    "addr:full":"988 Vendue Dr Lawrenceville GA 30044",
    "addr:housenumber":"988",
    "addr:postcode":"30044",
    "addr:street":"Vendue Dr",
    "iso:country":"US",
    "sg:address":"988 Vendue Dr",
    "sg:city":"Lawrenceville",
    "sg:classifiers":[
        {
            "category":"Communications",
            "type":"Services"
        }
    ],
    "sg:phone":"+1 770 979 4534",
    "sg:postcode":"30044",
    "sg:province":"GA",
    "sg:tags":[
        "communication"
    ],
    "wof:name":"Grandstand Communications Inc",
    "wof:placetype":"venue"
},
  "geometry": {"coordinates":[-84.022797,33.901924],"type":"Point"}
}