{
  "type": "Feature",
  "properties": {
    "iso:country":"US",
    "sg:address":"614 Love Ave",
    "sg:city":"Tifton",
    "sg:classifiers":[
        {
            "category":"Shopping",
            "subcategory":"Discount & Variety Stores",
            "type":"Retail Goods"
        },
        {
            "category":"Shopping",
            "subcategory":"Department Store",
            "type":"Retail Goods"
        }
    ],
    "sg:phone":"+1 229 386 0902",
    "sg:postcode":"31794",
    "sg:province":"GA",
    "sg:tags":[
        "shop"
    ],
    "wof:name":"Family Dollar Stores",
    "wof:placetype":"venue"
},
  "geometry": {"coordinates":[-83.507125,31.45937],"type":"Point"}
}