{
  "type": "Feature",
  "properties": {
    "iso:country":"US",
    "sg:address":"625 Braselton Pkwy",
    "sg:city":"Braselton",
    "sg:classifiers":[
        {
            "category":"Home & Garden",
            "subcategory":"Home Furnishings",
            "type":"Retail Goods"
        }
    ],
    "sg:phone":"+1 770 476 8537",
    "sg:postcode":"30517",
    "sg:province":"GA",
    "sg:tags":[
        "fixture",
        "lighting"
    ],
    "sg:website":"http://www.lee-lighting.com",
    "wof:name":"Lee Lighting",
    "wof:placetype":"venue"
},
  "geometry": {"coordinates":[-83.767956,34.120875],"type":"Point"}
}