{
  "type": "Feature",
  "properties": {
    "iso:country":"US",
    "sg:address":"2971 Flowers Rd S",
    "sg:city":"Atlanta",
    "sg:classifiers":[
        {
            "category":"Professional",
            "type":"Services"
        }
    ],
    "sg:phone":"+1 770 457 5888",
    "sg:postcode":"30341",
    "sg:province":"GA",
    "wof:name":"Zhang & Yan PC",
    "wof:placetype":"venue"
},
  "geometry": {"coordinates":[-84.264127,33.870263],"type":"Point"}
}