{
  "type": "Feature",
  "properties": {
    "iso:country":"US",
    "sg:address":"336 Dahlonega Rd",
    "sg:city":"Cumming",
    "sg:classifiers":[
        {
            "category":"Restaurant",
            "type":"Food & Drink"
        }
    ],
    "sg:phone":"+1 770 205 3382",
    "sg:postcode":"30040",
    "sg:province":"GA",
    "wof:name":"El Ranchito",
    "wof:placetype":"venue"
},
  "geometry": {"coordinates":[-84.135243,34.215787],"type":"Point"}
}