{
  "type": "Feature",
  "properties": {
    "addr:full":"2612 Dogwood Ave Thunderbolt GA 31404",
    "addr:housenumber":"2612",
    "addr:postcode":"31404",
    "addr:street":"Dogwood Ave",
    "iso:country":"US",
    "sg:address":"2612 Dogwood Ave",
    "sg:city":"Thunderbolt",
    "sg:classifiers":[
        {
            "category":"Building & Trades",
            "subcategory":"Construction",
            "type":"Services"
        }
    ],
    "sg:phone":"+1 912 352 2701",
    "sg:postcode":"31404",
    "sg:province":"GA",
    "sg:tags":[
        "downspouts",
        "gutter"
    ],
    "wof:name":"Georgia Seamless Gutters",
    "wof:placetype":"venue"
},
  "geometry": {"coordinates":[-81.049881,32.034567],"type":"Point"}
}