{
  "type": "Feature",
  "properties": {
    "iso:country":"US",
    "sg:address":"12 Regency Way",
    "sg:city":"Mableton",
    "sg:classifiers":[
        {
            "category":"Food & Beverages",
            "subcategory":"Specialty",
            "type":"Retail Goods"
        }
    ],
    "sg:phone":"+1 678 945 0836",
    "sg:postcode":"30126",
    "sg:province":"GA",
    "wof:name":"Hollys Health Nutrition",
    "wof:placetype":"venue"
},
  "geometry": {"coordinates":[-84.552829,33.80389],"type":"Point"}
}