{
  "type": "Feature",
  "properties": {
    "iso:country":"US",
    "sg:address":"459 Allana Ct",
    "sg:city":"Stone Mountain",
    "sg:classifiers":[
        {
            "category":"Building & Trades",
            "subcategory":"Construction",
            "type":"Services"
        }
    ],
    "sg:phone":"+1 770 498 7727",
    "sg:postcode":"30087",
    "sg:province":"GA",
    "sg:tags":[
        "nonresidential"
    ],
    "wof:name":"Artis Group Inc",
    "wof:placetype":"venue"
},
  "geometry": {"coordinates":[-84.13503300000001,33.785918],"type":"Point"}
}