{
  "type": "Feature",
  "properties": {
    "iso:country":"US",
    "sg:address":"900 Circle 75 Pkwy",
    "sg:city":"Atlanta",
    "sg:classifiers":[
        {
            "category":"Organizations",
            "subcategory":"Professional Association",
            "type":"Services"
        }
    ],
    "sg:phone":"+1 678 424 5750",
    "sg:postcode":"30339",
    "sg:province":"GA",
    "sg:tags":[
        "group",
        "advocacy"
    ],
    "wof:name":"National Peanut Board",
    "wof:placetype":"venue"
},
  "geometry": {"coordinates":[-84.473236,33.89843],"type":"Point"}
}