{
  "type": "Feature",
  "properties": {
    "iso:country":"US",
    "sg:address":"3695 Glennvale Ct",
    "sg:city":"Cumming",
    "sg:classifiers":[
        {
            "category":"Building & Trades",
            "subcategory":"Construction",
            "type":"Services"
        }
    ],
    "sg:phone":"+1 770 356 2392",
    "sg:postcode":"30041",
    "sg:province":"GA",
    "sg:tags":[
        "house"
    ],
    "wof:name":"Hodgepodge Home Improvements",
    "wof:placetype":"venue"
},
  "geometry": {"coordinates":[-84.18732900000001,34.090334],"type":"Point"}
}