{
  "type": "Feature",
  "properties": {
    "iso:country":"US",
    "sg:address":"1826 Patricia Ln",
    "sg:city":"Loganville",
    "sg:classifiers":[
        {
            "category":"Building & Trades",
            "subcategory":"Plumbing",
            "type":"Services"
        }
    ],
    "sg:phone":"+1 770 466 6958",
    "sg:postcode":"30052",
    "sg:province":"GA",
    "sg:tags":[
        "conditioning",
        "contractor",
        "system",
        "air"
    ],
    "wof:name":"Sandman Heating & Air Cond",
    "wof:placetype":"venue"
},
  "geometry": {"coordinates":[-83.845889,33.783543],"type":"Point"}
}