{
  "type": "Feature",
  "properties": {
    "addr:full":"2809 Glynn Ave Brunswick GA 31520",
    "addr:housenumber":"2809",
    "addr:postcode":"31520",
    "addr:street":"Glynn Ave",
    "iso:country":"US",
    "sg:address":"2809 Glynn Ave",
    "sg:city":"Brunswick",
    "sg:classifiers":[
        {
            "category":"Professional",
            "type":"Services"
        },
        {
            "category":"Restaurant",
            "type":"Food & Drink"
        }
    ],
    "sg:phone":"+1 912 264 0605",
    "sg:postcode":"31520",
    "sg:province":"GA",
    "sg:tags":[
        "barbecue",
        "style",
        "family",
        "caterer"
    ],
    "wof:name":"MacK's Barbecue Place",
    "wof:placetype":"venue"
},
  "geometry": {"coordinates":[-81.47474800000001,31.16956],"type":"Point"}
}