{
  "type": "Feature",
  "properties": {
    "addr:full":"474 Mount Pleasant Rd Hampton GA 30228",
    "addr:housenumber":"474",
    "addr:postcode":"30228",
    "addr:street":"Mount Pleasant Rd",
    "iso:country":"US",
    "sg:address":"474 Mount Pleasant Rd",
    "sg:city":"Hampton",
    "sg:classifiers":[
        {
            "category":"Airport",
            "type":"Transportation"
        }
    ],
    "sg:phone":"+1 770 946 9309",
    "sg:postcode":"30228",
    "sg:province":"GA",
    "sg:tags":[
        "aircraft",
        "maintenance"
    ],
    "wof:name":"Trade Winds Aviation",
    "wof:placetype":"venue"
},
  "geometry": {"coordinates":[-84.325006,33.395793],"type":"Point"}
}