{
  "type": "Feature",
  "properties": {
    "iso:country":"US",
    "sg:address":"1100 Lake Hearn Dr NE",
    "sg:city":"Atlanta",
    "sg:classifiers":[
        {
            "category":"Health Services",
            "subcategory":"Health Practitioner",
            "type":"Services"
        }
    ],
    "sg:phone":"+1 404 847 9560",
    "sg:postcode":"30342",
    "sg:province":"GA",
    "sg:tags":[
        "psychologist"
    ],
    "wof:name":"Atlanta Psychological Conslnts",
    "wof:placetype":"venue"
},
  "geometry": {"coordinates":[-84.348288,33.912604],"type":"Point"}
}