{
  "type": "Feature",
  "properties": {
    "addr:full":"323 Benton Rd Carlton GA 30627",
    "addr:housenumber":"323",
    "addr:postcode":"30627",
    "addr:street":"Benton Rd",
    "iso:country":"US",
    "sg:address":"323 Benton Rd",
    "sg:city":"Carlton",
    "sg:classifiers":[
        {
            "category":"Home & Garden",
            "subcategory":"Carpets & Floor Coverings",
            "type":"Retail Goods"
        }
    ],
    "sg:phone":"+1 706 255 1263",
    "sg:postcode":"30627",
    "sg:province":"GA",
    "sg:tags":[
        "flooring",
        "contractor"
    ],
    "wof:name":"L & R Construction",
    "wof:placetype":"venue"
},
  "geometry": {"coordinates":[-82.96820099999999,34.005742],"type":"Point"}
}