{
  "type": "Feature",
  "properties": {
    "addr:full":"1495 Monticello Hwy Gray GA 31032",
    "addr:housenumber":"1495",
    "addr:postcode":"31032",
    "addr:street":"Monticello Hwy",
    "iso:country":"US",
    "sg:address":"1495 Monticello Hwy",
    "sg:city":"Gray",
    "sg:classifiers":[
        {
            "category":"Retail",
            "subcategory":"Auto Repair",
            "type":"Services"
        }
    ],
    "sg:phone":"+1 478 986 0231",
    "sg:postcode":"31032",
    "sg:province":"GA",
    "sg:tags":[
        "general"
    ],
    "wof:name":"Craig Automotive & Speed Shop",
    "wof:placetype":"venue"
},
  "geometry": {"coordinates":[-83.60842599999999,33.072401],"type":"Point"}
}