{
  "type": "Feature",
  "properties": {
    "addr:full":"1805 Hephzibah Church Rd Lincolnton GA 30817",
    "addr:housenumber":"1805",
    "addr:postcode":"30817",
    "addr:street":"Hephzibah Church Rd",
    "iso:country":"US",
    "sg:address":"1805 Hephzibah Church Rd",
    "sg:city":"Lincolnton",
    "sg:classifiers":[
        {
            "category":"Retail",
            "subcategory":"Auto Repair",
            "type":"Services"
        }
    ],
    "sg:phone":"+1 706 359 2400",
    "sg:postcode":"30817",
    "sg:province":"GA",
    "sg:tags":[
        "body",
        "automobile",
        "painting",
        "repairing"
    ],
    "wof:name":"Johnson's Paint & Body Shop",
    "wof:placetype":"venue"
},
  "geometry": {"coordinates":[-82.534824,33.740785],"type":"Point"}
}