{
  "type": "Feature",
  "properties": {
    "iso:country":"US",
    "sg:address":"7812 Mount Olive Rd",
    "sg:city":"Camilla",
    "sg:classifiers":[
        {
            "category":"Farming",
            "subcategory":"Farm",
            "type":"Manufacturing & Wholesale Goods"
        }
    ],
    "sg:phone":"+1 229 294 4114",
    "sg:postcode":"31730",
    "sg:province":"GA",
    "sg:tags":[
        "crop",
        "general"
    ],
    "wof:name":"Brent C Faircloth",
    "wof:placetype":"venue"
},
  "geometry": {"coordinates":[-84.307607,31.131812],"type":"Point"}
}