{
  "type": "Feature",
  "properties": {
    "iso:country":"US",
    "sg:address":"119 State Rte 34",
    "sg:city":"Newnan",
    "sg:classifiers":[
        {
            "category":"Wholesale",
            "subcategory":"Farm Supplies",
            "type":"Manufacturing & Wholesale Goods"
        }
    ],
    "sg:phone":"+1 770 251 1224",
    "sg:postcode":"30263",
    "sg:province":"GA",
    "sg:tags":[
        "feed",
        "masonry"
    ],
    "wof:name":"Farm & Masonry Supply",
    "wof:placetype":"venue"
},
  "geometry": {"coordinates":[-84.826583,33.38562],"type":"Point"}
}