{
  "type": "Feature",
  "properties": {
    "addr:full":"5403 Veterans Pkwy Columbus GA 31904",
    "addr:housenumber":"5403",
    "addr:postcode":"31904",
    "addr:street":"Veterans Pkwy",
    "iso:country":"US",
    "sg:address":"5403 Veterans Pkwy",
    "sg:city":"Columbus",
    "sg:classifiers":[
        {
            "category":"Autos & Motor Vehicles",
            "subcategory":"Auto Supplies",
            "type":"Retail Goods"
        }
    ],
    "sg:phone":"+1 706 323 5251",
    "sg:postcode":"31904",
    "sg:province":"GA",
    "sg:tags":[
        "tire"
    ],
    "wof:name":"Bross Tire Sales Inc",
    "wof:placetype":"venue"
},
  "geometry": {"coordinates":[-84.964037,32.522148],"type":"Point"}
}