{
  "type": "Feature",
  "properties": {
    "iso:country":"US",
    "sg:address":"1318 Ethridge Mill Rd",
    "sg:city":"Griffin",
    "sg:classifiers":[
        {
            "category":"Building & Trades",
            "subcategory":"Cleaning & Sanitation",
            "type":"Services"
        }
    ],
    "sg:phone":"+1 770 227 1862",
    "sg:postcode":"30224",
    "sg:province":"GA",
    "sg:tags":[
        "maintenance"
    ],
    "wof:name":"Mary Ruth Thomas",
    "wof:placetype":"venue"
},
  "geometry": {"coordinates":[-84.268128,33.204073],"type":"Point"}
}