{
  "type": "Feature",
  "properties": {
    "iso:country":"US",
    "sg:address":"2008 Old Guard Rd",
    "sg:city":"Columbus",
    "sg:classifiers":[
        {
            "category":"Education",
            "subcategory":"School",
            "type":"Public Place"
        }
    ],
    "sg:phone":"+1 706 748 3203",
    "sg:postcode":"31909",
    "sg:province":"GA",
    "sg:tags":[
        "high",
        "middle",
        "elementary"
    ],
    "sg:website":"www.mcsdga.net",
    "wof:name":"Muscogee County School District",
    "wof:placetype":"venue"
},
  "geometry": {"coordinates":[-84.92880599999999,32.575611],"type":"Point"}
}