{
  "type": "Feature",
  "properties": {
    "addr:full":"540 Avignon Ct Atlanta GA 30350",
    "addr:housenumber":"540",
    "addr:postcode":"30350",
    "addr:street":"Avignon Ct",
    "iso:country":"US",
    "sg:address":"540 Avignon Ct",
    "sg:city":"Atlanta",
    "sg:classifiers":[
        {
            "category":"Professional",
            "subcategory":"Computer Services",
            "type":"Services"
        }
    ],
    "sg:phone":"+1 770 350 6030",
    "sg:postcode":"30350",
    "sg:province":"GA",
    "sg:tags":[
        "software",
        "manufacturer"
    ],
    "wof:name":"Solutianet Inc",
    "wof:placetype":"venue"
},
  "geometry": {"coordinates":[-84.27915900000001,33.966292],"type":"Point"}
}