{
  "type": "Feature",
  "properties": {
    "iso:country":"US",
    "sg:address":"6440 Hillandale Dr Ste 134",
    "sg:city":"Lithonia",
    "sg:classifiers":[
        {
            "category":"Shopping",
            "subcategory":"Clothing, Apparel, & Fashions",
            "type":"Retail Goods"
        }
    ],
    "sg:phone":"+1 770 484 9971",
    "sg:postcode":"30058",
    "sg:province":"GA",
    "sg:tags":[
        "designer"
    ],
    "wof:name":"Heavenly Wear Incorporated",
    "wof:placetype":"venue"
},
  "geometry": {"coordinates":[-84.12445,33.705139],"type":"Point"}
}