{
  "type": "Feature",
  "properties": {
    "addr:full":"814 Hill St Lagrange GA 30241",
    "addr:housenumber":"814",
    "addr:postcode":"30241",
    "addr:street":"Hill St",
    "iso:country":"US",
    "sg:address":"814 Hill St",
    "sg:city":"Lagrange",
    "sg:classifiers":[
        {
            "category":"Shopping",
            "subcategory":"Used Merchandise",
            "type":"Retail Goods"
        }
    ],
    "sg:phone":"+1 706 882 4370",
    "sg:postcode":"30241",
    "sg:province":"GA",
    "sg:tags":[
        "furniture"
    ],
    "wof:name":"East Furniture & Appliance Sls",
    "wof:placetype":"venue"
},
  "geometry": {"coordinates":[-85.014927,33.045171],"type":"Point"}
}