{
  "type": "Feature",
  "properties": {
    "iso:country":"US",
    "sg:address":"790 Quarterpath Ln",
    "sg:city":"Alpharetta",
    "sg:classifiers":[
        {
            "category":"Wholesale",
            "subcategory":"Hardware",
            "type":"Manufacturing & Wholesale Goods"
        }
    ],
    "sg:phone":"+1 770 442 6691",
    "sg:postcode":"30004",
    "sg:province":"GA",
    "sg:tags":[
        "plumbing"
    ],
    "wof:name":"Community Supply Chain",
    "wof:placetype":"venue"
},
  "geometry": {"coordinates":[-84.319209,34.141802],"type":"Point"}
}