{
  "type": "Feature",
  "properties": {
    "addr:full":"228 Water Tank Rd Dallas GA 30132",
    "addr:housenumber":"228",
    "addr:postcode":"30132",
    "addr:street":"Water Tank Rd",
    "iso:country":"US",
    "sg:address":"228 Water Tank Rd",
    "sg:city":"Dallas",
    "sg:classifiers":[
        {
            "category":"Professional",
            "type":"Services"
        }
    ],
    "sg:phone":"+1 770 505 4412",
    "sg:postcode":"30132",
    "sg:province":"GA",
    "wof:name":"New Orleans Theater Co Inc",
    "wof:placetype":"venue"
},
  "geometry": {"coordinates":[-84.846022,33.934096],"type":"Point"}
}