{
  "type": "Feature",
  "properties": {
    "iso:country":"US",
    "sg:address":"3351 Hwy 411 NE",
    "sg:city":"White",
    "sg:classifiers":[
        {
            "category":"Personal",
            "subcategory":"Beauty Salon",
            "type":"Services"
        }
    ],
    "sg:phone":"+1 770 382 2115",
    "sg:postcode":"30184",
    "sg:province":"GA",
    "sg:tags":[
        "shop"
    ],
    "wof:name":"Terris Place Hair & Tan Salon",
    "wof:placetype":"venue"
},
  "geometry": {"coordinates":[-84.74367700000001,34.280382],"type":"Point"}
}