{
  "type": "Feature",
  "properties": {
    "iso:country":"US",
    "sg:address":"560 Atlanta South Pkwy # 400",
    "sg:city":"Atlanta",
    "sg:classifiers":[
        {
            "category":"Social Services",
            "subcategory":"Job Training",
            "type":"Services"
        }
    ],
    "sg:phone":"+1 404 767 5202",
    "sg:postcode":"30349",
    "sg:province":"GA",
    "sg:tags":[
        "consultant"
    ],
    "sg:website":"http://www.vw.com",
    "wof:name":"Volkswagen Group Of America, Inc.",
    "wof:placetype":"venue"
},
  "geometry": {"coordinates":[-84.41265199999999,33.615967],"type":"Point"}
}