{
  "type": "Feature",
  "properties": {
    "iso:country":"US",
    "sg:address":"3975 Arkwright Rd",
    "sg:city":"Macon",
    "sg:classifiers":[
        {
            "category":"Restaurant",
            "type":"Food & Drink"
        }
    ],
    "sg:phone":"+1 478 471 0456",
    "sg:postcode":"31210",
    "sg:province":"GA",
    "sg:tags":[
        "chinese"
    ],
    "wof:name":"China Gourmet Chinese Restaurant",
    "wof:placetype":"venue"
},
  "geometry": {"coordinates":[-83.68765500000001,32.907764],"type":"Point"}
}