{
  "type": "Feature",
  "properties": {
    "addr:full":"720 Doug Davis Dr Atlanta GA 30354",
    "addr:housenumber":"720",
    "addr:postcode":"30354",
    "addr:street":"Doug Davis Dr",
    "iso:country":"US",
    "sg:address":"720 Doug Davis Dr",
    "sg:city":"Atlanta",
    "sg:classifiers":[
        {
            "category":"Professional",
            "subcategory":"Computer Services",
            "type":"Services"
        }
    ],
    "sg:phone":"+1 404 559 4316",
    "sg:postcode":"30354",
    "sg:province":"GA",
    "wof:name":"CIT",
    "wof:placetype":"venue"
},
  "geometry": {"coordinates":[-84.412361,33.656461],"type":"Point"}
}