{
  "type": "Feature",
  "properties": {
    "addr:full":"4016 S Berkeley Lake Rd Duluth GA 30096",
    "addr:housenumber":"4016",
    "addr:postcode":"30096",
    "addr:street":"S Berkeley Lake Rd",
    "iso:country":"US",
    "sg:address":"4016 S Berkeley Lake Rd",
    "sg:city":"Duluth",
    "sg:classifiers":[
        {
            "category":"Professional",
            "subcategory":"Business Services",
            "type":"Services"
        }
    ],
    "sg:phone":"+1 770 246 1500",
    "sg:postcode":"30096",
    "sg:province":"GA",
    "sg:tags":[
        "independent",
        "record",
        "label"
    ],
    "wof:name":"Star DOT Entertainment Ltd",
    "wof:placetype":"venue"
},
  "geometry": {"coordinates":[-84.18942,33.985976],"type":"Point"}
}