{
  "type": "Feature",
  "properties": {
    "iso:country":"US",
    "sg:address":"25 Oak Leaf Dr",
    "sg:city":"Dallas",
    "sg:classifiers":[
        {
            "category":"Building & Trades",
            "subcategory":"Pest Control",
            "type":"Services"
        }
    ],
    "sg:phone":"+1 770 443 0756",
    "sg:postcode":"30157",
    "sg:province":"GA",
    "wof:name":"Holland Termite & Pest Control",
    "wof:placetype":"venue"
},
  "geometry": {"coordinates":[-84.881545,33.823115],"type":"Point"}
}