{
  "type": "Feature",
  "properties": {
    "addr:full":"2141 Jockey Hollow Dr NW Kennesaw GA 30152",
    "addr:housenumber":"2141",
    "addr:postcode":"30152",
    "addr:street":"Jockey Hollow Dr Nw",
    "iso:country":"US",
    "sg:address":"2141 Jockey Hollow Dr NW",
    "sg:city":"Kennesaw",
    "sg:classifiers":[
        {
            "category":"Professional",
            "subcategory":"Business Services",
            "type":"Services"
        }
    ],
    "sg:phone":"+1 770 422 0355",
    "sg:postcode":"30152",
    "sg:province":"GA",
    "wof:name":"Marketing Partnerships",
    "wof:placetype":"venue"
},
  "geometry": {"coordinates":[-84.662266,34.008871],"type":"Point"}
}