{
  "type": "Feature",
  "properties": {
    "iso:country":"US",
    "sg:address":"2302 Parklake Dr NE",
    "sg:city":"Atlanta",
    "sg:classifiers":[
        {
            "category":"Social Services",
            "type":"Services"
        },
        {
            "category":"Personal",
            "type":"Services"
        }
    ],
    "sg:phone":"+1 770 621 0469",
    "sg:postcode":"30345",
    "sg:province":"GA",
    "sg:tags":[
        "family",
        "counselors-licensed",
        "individual",
        "marriage",
        "child",
        "professional",
        "counselor"
    ],
    "wof:name":"Transitional Family Services",
    "wof:placetype":"venue"
},
  "geometry": {"coordinates":[-84.24932099999999,33.853321],"type":"Point"}
}