{
  "type": "Feature",
  "properties": {
    "addr:full":"1104 Alta Ave NE Atlanta GA 30307",
    "addr:housenumber":"1104",
    "addr:postcode":"30307",
    "addr:street":"Alta Ave Ne",
    "iso:country":"US",
    "sg:address":"1104 Alta Ave NE",
    "sg:city":"Atlanta",
    "sg:classifiers":[
        {
            "category":"Communications",
            "subcategory":"Film & Video Production",
            "type":"Services"
        }
    ],
    "sg:phone":"+1 404 524 9756",
    "sg:postcode":"30307",
    "sg:province":"GA",
    "sg:tags":[
        "audio-visual",
        "taping"
    ],
    "wof:name":"Burst Video-Film Inc",
    "wof:placetype":"venue"
},
  "geometry": {"coordinates":[-84.35187000000001,33.760857],"type":"Point"}
}