{
  "type": "Feature",
  "properties": {
    "addr:full":"248 Greenville St S Newnan GA 30263",
    "addr:housenumber":"248",
    "addr:postcode":"30263",
    "addr:street":"Greenville St S",
    "iso:country":"US",
    "sg:address":"248 Greenville St S",
    "sg:city":"Newnan",
    "sg:classifiers":[
        {
            "category":"Building & Trades",
            "subcategory":"Equipment Rental",
            "type":"Services"
        }
    ],
    "sg:phone":"+1 770 502 0447",
    "sg:postcode":"30263",
    "sg:province":"GA",
    "sg:tags":[
        "yard"
    ],
    "wof:name":"Newnan Tool Rental",
    "wof:placetype":"venue"
},
  "geometry": {"coordinates":[-84.790888,33.357819],"type":"Point"}
}