{
  "type": "Feature",
  "properties": {
    "iso:country":"US",
    "sg:address":"3341 Lexington Rd",
    "sg:city":"Athens",
    "sg:classifiers":[
        {
            "category":"Building & Trades",
            "subcategory":"Construction",
            "type":"Services"
        }
    ],
    "sg:phone":"+1 706 613 6660",
    "sg:postcode":"30605",
    "sg:province":"GA",
    "sg:tags":[
        "carpentry",
        "contractor"
    ],
    "wof:name":"Covenant Carpenter",
    "wof:placetype":"venue"
},
  "geometry": {"coordinates":[-83.323292,33.939271],"type":"Point"}
}