{
  "type": "Feature",
  "properties": {
    "addr:full":"3326 Wesley Chapel Rd Decatur GA 30034",
    "addr:housenumber":"3326",
    "addr:postcode":"30034",
    "addr:street":"Wesley Chapel Rd",
    "iso:country":"US",
    "sg:address":"3326 Wesley Chapel Rd",
    "sg:city":"Decatur",
    "sg:classifiers":[
        {
            "category":"Organizations",
            "subcategory":"Religious Organization",
            "type":"Services"
        }
    ],
    "sg:phone":"+1 770 322 1101",
    "sg:postcode":"30034",
    "sg:province":"GA",
    "wof:name":"Chapel Hill New Horizons",
    "wof:placetype":"venue"
},
  "geometry": {"coordinates":[-84.22691,33.690175],"type":"Point"}
}