{
  "type": "Feature",
  "properties": {
    "addr:full":"510 Martin Luther King Jr Blvd Savannah GA 31401",
    "addr:housenumber":"510",
    "addr:postcode":"31401",
    "addr:street":"Martin Luther King Jr Blvd",
    "iso:country":"US",
    "sg:address":"510 Martin Luther King Jr Blvd",
    "sg:city":"Savannah",
    "sg:classifiers":[
        {
            "category":"Shopping",
            "subcategory":"Gifts & Souvenirs",
            "type":"Retail Goods"
        }
    ],
    "sg:phone":"+1 912 232 2626",
    "sg:postcode":"31401",
    "sg:province":"GA",
    "sg:tags":[
        "shop"
    ],
    "wof:name":"Diaspora Marketplace",
    "wof:placetype":"venue"
},
  "geometry": {"coordinates":[-81.10059,32.071377],"type":"Point"}
}