{
  "type": "Feature",
  "properties": {
    "iso:country":"US",
    "sg:address":"128 E Forsyth St",
    "sg:city":"Americus",
    "sg:classifiers":[
        {
            "category":"Professional",
            "subcategory":"Detective & Security Services",
            "type":"Services"
        }
    ],
    "sg:phone":"+1 229 931 0301",
    "sg:postcode":"31709",
    "sg:province":"GA",
    "sg:tags":[
        "information",
        "bureau"
    ],
    "wof:name":"F V S U Extension Service",
    "wof:placetype":"venue"
},
  "geometry": {"coordinates":[-84.232004,32.07328],"type":"Point"}
}