{
  "type": "Feature",
  "properties": {
    "iso:country":"US",
    "sg:address":"2150 E Walnut Ave",
    "sg:city":"Dalton",
    "sg:classifiers":[
        {
            "category":"Shopping",
            "subcategory":"Gifts & Souvenirs",
            "type":"Retail Goods"
        }
    ],
    "sg:phone":"+1 706 275 7240",
    "sg:postcode":"30721",
    "sg:province":"GA",
    "sg:tags":[
        "shop"
    ],
    "wof:name":"Flashback",
    "wof:placetype":"venue"
},
  "geometry": {"coordinates":[-84.931392,34.762548],"type":"Point"}
}