{
  "type": "Feature",
  "properties": {
    "addr:full":"1093 Greensboro Rd Eatonton GA 31024",
    "addr:housenumber":"1093",
    "addr:postcode":"31024",
    "addr:street":"Greensboro Rd",
    "iso:country":"US",
    "sg:address":"1093 Greensboro Rd",
    "sg:city":"Eatonton",
    "sg:classifiers":[
        {
            "category":"Shopping",
            "subcategory":"Optical Goods",
            "type":"Retail Goods"
        }
    ],
    "sg:phone":"+1 706 484 2121",
    "sg:postcode":"31024",
    "sg:province":"GA",
    "wof:name":"Top Sight Inc",
    "wof:placetype":"venue"
},
  "geometry": {"coordinates":[-83.26311099999999,33.441629],"type":"Point"}
}