{
  "type": "Feature",
  "properties": {
    "iso:country":"US",
    "sg:address":"1205 Charles Johnson Rd",
    "sg:city":"Forsyth",
    "sg:classifiers":[
        {
            "category":"Building & Trades",
            "subcategory":"Construction",
            "type":"Services"
        }
    ],
    "sg:phone":"+1 478 992 9558",
    "sg:postcode":"31029",
    "sg:province":"GA",
    "sg:tags":[
        "builder",
        "operative"
    ],
    "wof:name":"Hartman Homes Inc",
    "wof:placetype":"venue"
},
  "geometry": {"coordinates":[-83.935501,32.922328],"type":"Point"}
}