{
  "type": "Feature",
  "properties": {
    "iso:country":"US",
    "sg:address":"1767 Fellowship Rd",
    "sg:city":"Tucker",
    "sg:phone":"+1 770 908 8999",
    "sg:postcode":"30084",
    "sg:province":"GA",
    "sg:website":"http://www.evisionscapes.com",
    "wof:name":"Visionscapes, Inc.",
    "wof:placetype":"venue"
},
  "geometry": {"coordinates":[-84.210004,33.835913],"type":"Point"}
}