{
  "type": "Feature",
  "properties": {
    "addr:full":"610 S 8th St Griffin GA 30224",
    "addr:housenumber":"610",
    "addr:postcode":"30224",
    "addr:street":"S 8Th St",
    "iso:country":"US",
    "sg:address":"610 S 8th St",
    "sg:city":"Griffin",
    "sg:classifiers":[
        {
            "category":"Health Services",
            "subcategory":"Doctor",
            "type":"Services"
        }
    ],
    "sg:phone":"+1 678 688 1155",
    "sg:postcode":"30224",
    "sg:province":"GA",
    "sg:tags":[
        "physician",
        "surgeon"
    ],
    "wof:name":"Grace Medical Clinic",
    "wof:placetype":"venue"
},
  "geometry": {"coordinates":[-84.265621,33.239831],"type":"Point"}
}