{
  "type": "Feature",
  "properties": {
    "iso:country":"US",
    "sg:address":"4145 Lavista Rd",
    "sg:city":"Tucker",
    "sg:classifiers":[
        {
            "category":"Building & Trades",
            "subcategory":"Locksmith",
            "type":"Services"
        }
    ],
    "sg:phone":"+1 678 369 5746",
    "sg:postcode":"30084",
    "sg:province":"GA",
    "sg:tags":[
        "key"
    ],
    "wof:name":"555 Emergency Locksmith",
    "wof:placetype":"venue"
},
  "geometry": {"coordinates":[-84.24957999999999,33.846207],"type":"Point"}
}