{
  "type": "Feature",
  "properties": {
    "iso:country":"US",
    "sg:address":"3360 Regalwoods Dr",
    "sg:city":"Atlanta",
    "sg:classifiers":[
        {
            "category":"Health Services",
            "subcategory":"Clinic",
            "type":"Services"
        }
    ],
    "sg:phone":"+1 770 493 7194",
    "sg:postcode":"30340",
    "sg:province":"GA",
    "sg:tags":[
        "information",
        "mental"
    ],
    "wof:name":"Free Recovery Inc Support Group",
    "wof:placetype":"venue"
},
  "geometry": {"coordinates":[-84.246437,33.887855],"type":"Point"}
}