{
  "type": "Feature",
  "properties": {
    "iso:country":"US",
    "sg:address":"4800 Briarcliff Rd NE",
    "sg:city":"Atlanta",
    "sg:classifiers":[
        {
            "category":"Shopping",
            "subcategory":"Jewelry",
            "type":"Retail Goods"
        }
    ],
    "sg:phone":"+1 770 270 5434",
    "sg:postcode":"30345",
    "sg:province":"GA",
    "wof:name":"Touch of Gold",
    "wof:placetype":"venue"
},
  "geometry": {"coordinates":[-84.255785,33.848165],"type":"Point"}
}