{
  "type": "Feature",
  "properties": {
    "addr:full":"3795 Jackson Rd Griffin GA 30223",
    "addr:housenumber":"3795",
    "addr:postcode":"30223",
    "addr:street":"Jackson Rd",
    "iso:country":"US",
    "sg:address":"3795 Jackson Rd",
    "sg:city":"Griffin",
    "sg:classifiers":[
        {
            "category":"Personal",
            "subcategory":"Beauty Salon",
            "type":"Services"
        }
    ],
    "sg:phone":"+1 770 467 0667",
    "sg:postcode":"30223",
    "sg:province":"GA",
    "wof:name":"Shamelia's Braids",
    "wof:placetype":"venue"
},
  "geometry": {"coordinates":[-84.181014,33.29033],"type":"Point"}
}