{
  "type": "Feature",
  "properties": {
    "iso:country":"US",
    "sg:address":"714 Green St",
    "sg:city":"Fort Valley",
    "sg:classifiers":[
        {
            "category":"Personal",
            "type":"Services"
        }
    ],
    "sg:phone":"+1 478 825 8600",
    "sg:postcode":"31030",
    "sg:province":"GA",
    "sg:tags":[
        "business"
    ],
    "wof:name":"Magnolia Terrace",
    "wof:placetype":"venue"
},
  "geometry": {"coordinates":[-83.89570999999999,32.5464],"type":"Point"}
}