{
  "type": "Feature",
  "properties": {
    "addr:full":"1303 Telhurst Ct NW Kennesaw GA 30144",
    "addr:housenumber":"1303",
    "addr:postcode":"30144",
    "addr:street":"Telhurst Ct Nw",
    "iso:country":"US",
    "sg:address":"1303 Telhurst Ct NW",
    "sg:city":"Kennesaw",
    "sg:classifiers":[
        {
            "category":"Communications",
            "type":"Services"
        }
    ],
    "sg:phone":"+1 770 919 8662",
    "sg:postcode":"30144",
    "sg:province":"GA",
    "sg:tags":[
        "communication"
    ],
    "wof:name":"Comsel Communications",
    "wof:placetype":"venue"
},
  "geometry": {"coordinates":[-84.595822,34.057826],"type":"Point"}
}