{
  "type": "Feature",
  "properties": {
    "addr:full":"4511 Olde Perimeter Way Atlanta GA 30346",
    "addr:housenumber":"4511",
    "addr:postcode":"30346",
    "addr:street":"Olde Perimeter Way",
    "iso:country":"US",
    "sg:address":"4511 Olde Perimeter Way",
    "sg:city":"Atlanta",
    "sg:classifiers":[
        {
            "category":"Shopping Center",
            "type":"Public Place"
        }
    ],
    "sg:phone":"+1 770 522 8974",
    "sg:postcode":"30346",
    "sg:province":"GA",
    "wof:name":"Retail",
    "wof:placetype":"venue"
},
  "geometry": {"coordinates":[-84.343406,33.928132],"type":"Point"}
}