{
  "type": "Feature",
  "properties": {
    "addr:full":"4787 Alabama Rd NE Roswell GA 30075",
    "addr:housenumber":"4787",
    "addr:postcode":"30075",
    "addr:street":"Alabama Rd Ne",
    "iso:country":"US",
    "sg:address":"4787 Alabama Rd NE",
    "sg:city":"Roswell",
    "sg:classifiers":[
        {
            "category":"Food & Beverages",
            "subcategory":"Liquor & Beverages",
            "type":"Retail Goods"
        }
    ],
    "sg:phone":"+1 770 993 3662",
    "sg:postcode":"30075",
    "sg:province":"GA",
    "sg:tags":[
        "beer",
        "spirit",
        "wine"
    ],
    "wof:name":"Good Times Package Store",
    "wof:placetype":"venue"
},
  "geometry": {"coordinates":[-84.425003,34.066502],"type":"Point"}
}