{
  "type": "Feature",
  "properties": {
    "iso:country":"US",
    "sg:address":"180 S Jeff Davis Dr",
    "sg:city":"Fayetteville",
    "sg:classifiers":[
        {
            "category":"Shopping",
            "subcategory":"Florist",
            "type":"Retail Goods"
        }
    ],
    "sg:phone":"+1 770 716 7480",
    "sg:postcode":"30214",
    "sg:province":"GA",
    "wof:name":"Tropical Gardens",
    "wof:placetype":"venue"
},
  "geometry": {"coordinates":[-84.44979499999999,33.446554],"type":"Point"}
}