{
  "type": "Feature",
  "properties": {
    "iso:country":"US",
    "sg:address":"2020 Norwich St",
    "sg:city":"Brunswick",
    "sg:classifiers":[
        {
            "category":"Retail",
            "subcategory":"Auto Repair",
            "type":"Services"
        }
    ],
    "sg:phone":"+1 912 264 2458",
    "sg:postcode":"31520",
    "sg:province":"GA",
    "sg:tags":[
        "body",
        "automobile",
        "painting"
    ],
    "wof:name":"Grant Brothers Detail Paint",
    "wof:placetype":"venue"
},
  "geometry": {"coordinates":[-81.494207,31.157864],"type":"Point"}
}