{
  "type": "Feature",
  "properties": {
    "addr:full":"1467 Reynolds St Augusta GA 30901",
    "addr:housenumber":"1467",
    "addr:postcode":"30901",
    "addr:street":"Reynolds St",
    "iso:country":"US",
    "sg:address":"1467 Reynolds St",
    "sg:city":"Augusta",
    "sg:classifiers":[
        {
            "category":"Wholesale",
            "subcategory":"Medical Equipment & Supplies",
            "type":"Manufacturing & Wholesale Goods"
        }
    ],
    "sg:phone":"+1 706 722 5016",
    "sg:postcode":"30901",
    "sg:province":"GA",
    "sg:tags":[
        "physician",
        "surgeon"
    ],
    "wof:name":"Vitalaire",
    "wof:placetype":"venue"
},
  "geometry": {"coordinates":[-81.981111,33.48216],"type":"Point"}
}