{
  "type": "Feature",
  "properties": {
    "iso:country":"US",
    "sg:address":"6939 US Hwy 80",
    "sg:city":"Brooklet",
    "sg:classifiers":[
        {
            "category":"Wholesale",
            "subcategory":"Machinery & Supplies",
            "type":"Manufacturing & Wholesale Goods"
        },
        {
            "category":"Retail",
            "subcategory":"Repair Shop",
            "type":"Services"
        }
    ],
    "sg:phone":"+1 912 823 3737",
    "sg:postcode":"30415",
    "sg:province":"GA",
    "sg:tags":[
        "drive",
        "hydraulic",
        "system",
        "equipment",
        "line",
        "tractor"
    ],
    "wof:name":"Equipment Maintenance Co",
    "wof:placetype":"venue"
},
  "geometry": {"coordinates":[-81.54708599999999,32.317264],"type":"Point"}
}