{
  "type": "Feature",
  "properties": {
    "iso:country":"US",
    "sg:address":"335 McKees Rock Ln",
    "sg:city":"Lawrenceville",
    "sg:classifiers":[
        {
            "category":"Professional",
            "subcategory":"Computer Services",
            "type":"Services"
        }
    ],
    "sg:phone":"+1 770 736 5565",
    "sg:postcode":"30044",
    "sg:province":"GA",
    "sg:tags":[
        "related"
    ],
    "wof:name":"Bionic Solutions",
    "wof:placetype":"venue"
},
  "geometry": {"coordinates":[-84.05353700000001,33.911325],"type":"Point"}
}