{
  "type": "Feature",
  "properties": {
    "iso:country":"US",
    "sg:address":"300 Bullsboro Dr",
    "sg:city":"Newnan",
    "sg:classifiers":[
        {
            "category":"Professional",
            "subcategory":"Management & Consulting",
            "type":"Services"
        }
    ],
    "sg:phone":"+1 770 251 0192",
    "sg:postcode":"30263",
    "sg:province":"GA",
    "sg:tags":[
        "business"
    ],
    "wof:name":"Byers Engineering Co",
    "wof:placetype":"venue"
},
  "geometry": {"coordinates":[-84.766859,33.392592],"type":"Point"}
}