{
  "type": "Feature",
  "properties": {
    "iso:country":"US",
    "sg:address":"1370 Thompson Bridge Rd",
    "sg:city":"Gainesville",
    "sg:classifiers":[
        {
            "category":"Professional",
            "subcategory":"Lawyer & Legal Services",
            "type":"Services"
        }
    ],
    "sg:phone":"+1 770 534 3770",
    "sg:postcode":"30501",
    "sg:province":"GA",
    "sg:tags":[
        "divorce",
        "attorney",
        "practice",
        "family",
        "law"
    ],
    "wof:name":"Candace, M Williams",
    "wof:placetype":"venue"
},
  "geometry": {"coordinates":[-83.83242300000001,34.320501],"type":"Point"}
}