{
  "type": "Feature",
  "properties": {
    "addr:full":"1244 Plantation Rd Elberton GA 30635",
    "addr:housenumber":"1244",
    "addr:postcode":"30635",
    "addr:street":"Plantation Rd",
    "iso:country":"US",
    "sg:address":"1244 Plantation Rd",
    "sg:city":"Elberton",
    "sg:classifiers":[
        {
            "category":"Real Estate",
            "subcategory":"Real Estate Operator",
            "type":"Services"
        }
    ],
    "sg:phone":"+1 706 283 7780",
    "sg:postcode":"30635",
    "sg:province":"GA",
    "sg:tags":[
        "property",
        "lessor"
    ],
    "wof:name":"Peggy Paramore Rentals",
    "wof:placetype":"venue"
},
  "geometry": {"coordinates":[-82.87004399999999,34.2164],"type":"Point"}
}