{
  "type": "Feature",
  "properties": {
    "addr:full":"6197 Fairburn Rd Douglasville GA 30134",
    "addr:housenumber":"6197",
    "addr:postcode":"30134",
    "addr:street":"Fairburn Rd",
    "iso:country":"US",
    "sg:address":"6197 Fairburn Rd",
    "sg:city":"Douglasville",
    "sg:classifiers":[
        {
            "category":"Banks & Credit Unions",
            "subcategory":"Bank",
            "type":"Services"
        }
    ],
    "sg:phone":"+1 770 577 2577",
    "sg:postcode":"30134",
    "sg:province":"GA",
    "sg:tags":[
        "loan"
    ],
    "wof:name":"A-1 Action Cash",
    "wof:placetype":"venue"
},
  "geometry": {"coordinates":[-84.738484,33.750893],"type":"Point"}
}