{
  "type": "Feature",
  "properties": {
    "addr:full":"659 auburn ave suite 125 Atlanta GA 30312",
    "addr:housenumber":"659",
    "addr:postcode":"30312",
    "addr:street":"Auburn Ave Suite 125",
    "iso:country":"US",
    "sg:address":"659 auburn ave suite 125",
    "sg:city":"Atlanta",
    "sg:classifiers":[
        {
            "category":"Personal",
            "subcategory":"Beauty Salon",
            "type":"Services"
        }
    ],
    "sg:phone":"+1 404 840 9915",
    "sg:postcode":"30312",
    "sg:province":"GA",
    "sg:tags":[
        "hair"
    ],
    "sg:website":"www.theplumsalon.com",
    "wof:name":"The Plum Salon",
    "wof:placetype":"venue"
},
  "geometry": {"coordinates":[-84.366851,33.756553],"type":"Point"}
}