{
  "type": "Feature",
  "properties": {
    "addr:full":"893 N Hairston Rd Stone Mountain GA 30083",
    "addr:housenumber":"893",
    "addr:postcode":"30083",
    "addr:street":"N Hairston Rd",
    "iso:country":"US",
    "sg:address":"893 N Hairston Rd",
    "sg:city":"Stone Mountain",
    "sg:classifiers":[
        {
            "category":"Restaurant",
            "type":"Food & Drink"
        }
    ],
    "sg:phone":"+1 404 296 8887",
    "sg:postcode":"30083",
    "sg:province":"GA",
    "wof:name":"Mrs Winner's Chicken & Biscuits",
    "wof:placetype":"venue"
},
  "geometry": {"coordinates":[-84.19380200000001,33.803902],"type":"Point"}
}