{
  "type": "Feature",
  "properties": {
    "iso:country":"US",
    "sg:address":"356 Northside Dr E",
    "sg:city":"Statesboro",
    "sg:classifiers":[
        {
            "category":"Health Services",
            "subcategory":"Doctor",
            "type":"Services"
        }
    ],
    "sg:phone":"+1 912 764 5463",
    "sg:postcode":"30458",
    "sg:province":"GA",
    "sg:tags":[
        "physician",
        "surgeon"
    ],
    "wof:name":"Stephen M Jordan MD",
    "wof:placetype":"venue"
},
  "geometry": {"coordinates":[-81.76855500000001,32.443504],"type":"Point"}
}