{
  "type": "Feature",
  "properties": {
    "addr:full":"101 Peachtree St Jesup GA 31545",
    "addr:housenumber":"101",
    "addr:postcode":"31545",
    "addr:street":"Peachtree St",
    "iso:country":"US",
    "sg:address":"101 Peachtree St",
    "sg:city":"Jesup",
    "sg:classifiers":[
        {
            "category":"Shopping",
            "subcategory":"Pharmacy",
            "type":"Retail Goods"
        }
    ],
    "sg:phone":"+1 912 427 9566",
    "sg:postcode":"31545",
    "sg:province":"GA",
    "wof:name":"Bishops Pharmacy",
    "wof:placetype":"venue"
},
  "geometry": {"coordinates":[-81.899058,31.59949],"type":"Point"}
}