{
  "type": "Feature",
  "properties": {
    "iso:country":"US",
    "sg:address":"411 Rockhouse Rd E",
    "sg:city":"Cordele",
    "sg:classifiers":[
        {
            "category":"Sports & Exercise",
            "subcategory":"Gym",
            "type":"Entertainment"
        }
    ],
    "sg:phone":"+1 229 271 2999",
    "sg:postcode":"31015",
    "sg:province":"GA",
    "sg:tags":[
        "spa"
    ],
    "wof:name":"V I P Spa",
    "wof:placetype":"venue"
},
  "geometry": {"coordinates":[-83.738799,31.906727],"type":"Point"}
}