{
  "type": "Feature",
  "properties": {
    "addr:full":"50 Perimeter Ctr E Atlanta GA 30346",
    "addr:housenumber":"50",
    "addr:postcode":"30346",
    "addr:street":"Perimeter Ctr E",
    "iso:country":"US",
    "sg:address":"50 Perimeter Ctr E",
    "sg:city":"Atlanta",
    "sg:classifiers":[
        {
            "category":"Building & Trades",
            "subcategory":"Construction",
            "type":"Services"
        }
    ],
    "sg:phone":"+1 770 604 9032",
    "sg:postcode":"30346",
    "sg:province":"GA",
    "sg:tags":[
        "contractor"
    ],
    "wof:name":"Griggs Contracting",
    "wof:placetype":"venue"
},
  "geometry": {"coordinates":[-84.33271000000001,33.922688],"type":"Point"}
}