{
  "type": "Feature",
  "properties": {
    "addr:full":"5003 Saint Clair Dr NE Atlanta GA 30329",
    "addr:housenumber":"5003",
    "addr:postcode":"30329",
    "addr:street":"Saint Clair Dr Ne",
    "iso:country":"US",
    "sg:address":"5003 Saint Clair Dr NE",
    "sg:city":"Atlanta",
    "sg:classifiers":[
        {
            "category":"Retail",
            "subcategory":"Auto Rental",
            "type":"Services"
        }
    ],
    "sg:phone":"+1 404 219 3456",
    "sg:postcode":"30329",
    "sg:province":"GA",
    "sg:tags":[
        "limousine"
    ],
    "wof:name":"Midtown Limousine Inc",
    "wof:placetype":"venue"
},
  "geometry": {"coordinates":[-84.313517,33.838171],"type":"Point"}
}