{
  "type": "Feature",
  "properties": {
    "addr:full":"315 E Gordon St Thomaston GA 30286",
    "addr:housenumber":"315",
    "addr:postcode":"30286",
    "addr:street":"E Gordon St",
    "iso:country":"US",
    "sg:address":"315 E Gordon St",
    "sg:city":"Thomaston",
    "sg:classifiers":[
        {
            "category":"Government",
            "subcategory":"Office",
            "type":"Public Place"
        }
    ],
    "sg:phone":"+1 706 647 7020",
    "sg:postcode":"30286",
    "sg:province":"GA",
    "sg:tags":[
        "county"
    ],
    "wof:name":"Georgia Public Defenders Ofc",
    "wof:placetype":"venue"
},
  "geometry": {"coordinates":[-84.322338,32.88726],"type":"Point"}
}