{
  "type": "Feature",
  "properties": {
    "addr:full":"3330 Town Point Dr NW Kennesaw GA 30144",
    "addr:housenumber":"3330",
    "addr:postcode":"30144",
    "addr:street":"Town Point Dr Nw",
    "iso:country":"US",
    "sg:address":"3330 Town Point Dr NW",
    "sg:city":"Kennesaw",
    "sg:classifiers":[
        {
            "category":"Government",
            "subcategory":"Office",
            "type":"Public Place"
        }
    ],
    "sg:phone":"+1 770 429 9998",
    "sg:postcode":"30144",
    "sg:province":"GA",
    "wof:name":"Prc Desto Intl",
    "wof:placetype":"venue"
},
  "geometry": {"coordinates":[-84.579525,34.023798],"type":"Point"}
}