{
  "type": "Feature",
  "properties": {
    "iso:country":"US",
    "sg:address":"2349 Locust Ln",
    "sg:city":"Austell",
    "sg:classifiers":[
        {
            "category":"Professional",
            "subcategory":"Business Services",
            "type":"Services"
        }
    ],
    "sg:phone":"+1 770 948 8649",
    "sg:postcode":"30168",
    "sg:province":"GA",
    "wof:name":"Extreme Interiors Inc",
    "wof:placetype":"venue"
},
  "geometry": {"coordinates":[-84.621437,33.809162],"type":"Point"}
}