{
  "type": "Feature",
  "properties": {
    "iso:country":"US",
    "sg:address":"2840 New Home Rd",
    "sg:city":"Trenton",
    "sg:classifiers":[
        {
            "category":"Recreation",
            "subcategory":"Arcade",
            "type":"Entertainment"
        }
    ],
    "sg:phone":"+1 706 657 4298",
    "sg:postcode":"30752",
    "sg:province":"GA",
    "sg:tags":[
        "device",
        "operator",
        "amusement"
    ],
    "wof:name":"Dixie Amusement Leasing",
    "wof:placetype":"venue"
},
  "geometry": {"coordinates":[-85.53498399999999,34.958878],"type":"Point"}
}