{
  "type": "Feature",
  "properties": {
    "iso:country":"US",
    "sg:address":"1001 Diamond Hill Neese Rd",
    "sg:city":"Colbert",
    "sg:classifiers":[
        {
            "category":"Professional",
            "subcategory":"Detective & Security Services",
            "type":"Services"
        }
    ],
    "sg:phone":"+1 706 788 2731",
    "sg:postcode":"30628",
    "sg:province":"GA",
    "sg:tags":[
        "information",
        "bureau"
    ],
    "wof:name":"Scarborough Services Center",
    "wof:placetype":"venue"
},
  "geometry": {"coordinates":[-83.29597,34.067567],"type":"Point"}
}