{
  "type": "Feature",
  "properties": {
    "addr:full":"205 S Belair Rd Augusta GA 30907",
    "addr:housenumber":"205",
    "addr:postcode":"30907",
    "addr:street":"S Belair Rd",
    "iso:country":"US",
    "sg:address":"205 S Belair Rd",
    "sg:city":"Augusta",
    "sg:classifiers":[
        {
            "category":"Personal",
            "subcategory":"Beauty Salon",
            "type":"Services"
        }
    ],
    "sg:phone":"+1 706 364 7879",
    "sg:postcode":"30907",
    "sg:province":"GA",
    "sg:tags":[
        "shop"
    ],
    "wof:name":"Suzette's Salon",
    "wof:placetype":"venue"
},
  "geometry": {"coordinates":[-82.137967,33.495273],"type":"Point"}
}