{
  "type": "Feature",
  "properties": {
    "addr:full":"1490 S Broad St Commerce GA 30529",
    "addr:housenumber":"1490",
    "addr:postcode":"30529",
    "addr:street":"S Broad St",
    "iso:country":"US",
    "sg:address":"1490 S Broad St",
    "sg:city":"Commerce",
    "sg:classifiers":[
        {
            "category":"Autos & Motor Vehicles",
            "subcategory":"Automobile Sales",
            "type":"Retail Goods"
        }
    ],
    "sg:phone":"+1 706 335 6032",
    "sg:postcode":"30529",
    "sg:province":"GA",
    "sg:tags":[
        "car",
        "dealer"
    ],
    "wof:name":"J B's Auto Sales",
    "wof:placetype":"venue"
},
  "geometry": {"coordinates":[-83.45334099999999,34.199879],"type":"Point"}
}