{
  "type": "Feature",
  "properties": {
    "iso:country":"US",
    "sg:address":"775 Lake Ave Ste 3",
    "sg:city":"Atlanta",
    "sg:classifiers":[
        {
            "category":"Shopping",
            "subcategory":"Jewelry",
            "type":"Retail Goods"
        },
        {
            "category":"Home & Garden",
            "subcategory":"Home Furnishings",
            "type":"Retail Goods"
        },
        {
            "category":"Shopping",
            "subcategory":"Discount & Variety Stores",
            "type":"Retail Goods"
        }
    ],
    "sg:phone":"+1 404 909 8176",
    "sg:postcode":"30307",
    "sg:province":"GA",
    "sg:tags":[
        "wholesale",
        "decor"
    ],
    "sg:website":"www.propueblo.org",
    "wof:name":"Propueblo Fair Trade",
    "wof:placetype":"venue"
},
  "geometry": {"coordinates":[-84.362154,33.758054],"type":"Point"}
}