{
  "type": "Feature",
  "properties": {
    "addr:full":"2941 Mcmanus Rd Macon GA 31220",
    "addr:housenumber":"2941",
    "addr:postcode":"31220",
    "addr:street":"Mcmanus Rd",
    "iso:country":"US",
    "sg:address":"2941 Mcmanus Rd",
    "sg:city":"Macon",
    "sg:classifiers":[
        {
            "category":"Shopping",
            "subcategory":"Clothing, Apparel, & Fashions",
            "type":"Retail Goods"
        }
    ],
    "sg:phone":"+1 478 314 6555",
    "sg:postcode":"31220",
    "sg:province":"GA",
    "sg:tags":[
        "uniforms-accessories",
        "uniform"
    ],
    "wof:name":"Buckhead Uniforms",
    "wof:placetype":"venue"
},
  "geometry": {"coordinates":[-83.738827,32.833795],"type":"Point"}
}