{
  "type": "Feature",
  "properties": {
    "iso:country":"US",
    "sg:address":"498 Harper St",
    "sg:city":"Jesup",
    "sg:classifiers":[
        {
            "category":"Home & Garden",
            "subcategory":"Garden Supply",
            "type":"Retail Goods"
        }
    ],
    "sg:phone":"+1 912 427 0022",
    "sg:postcode":"31546",
    "sg:province":"GA",
    "sg:tags":[
        "nurseryman"
    ],
    "wof:name":"O'Quinn Tree Farm Inc",
    "wof:placetype":"venue"
},
  "geometry": {"coordinates":[-81.88378,31.590857],"type":"Point"}
}