{
  "type": "Feature",
  "properties": {
    "iso:country":"US",
    "sg:address":"220 Pritchett Dr",
    "sg:city":"Woodstock",
    "sg:classifiers":[
        {
            "category":"Wholesale",
            "subcategory":"Durable Goods & Equipment",
            "type":"Manufacturing & Wholesale Goods"
        }
    ],
    "sg:phone":"+1 770 926 2698",
    "sg:postcode":"30189",
    "sg:province":"GA",
    "sg:tags":[
        "exporter"
    ],
    "wof:name":"Newberry's Repair Svc",
    "wof:placetype":"venue"
},
  "geometry": {"coordinates":[-84.57330399999999,34.099073],"type":"Point"}
}