{
  "type": "Feature",
  "properties": {
    "iso:country":"US",
    "sg:address":"4708 Old Peachtree Rd NW",
    "sg:city":"Norcross",
    "sg:classifiers":[
        {
            "category":"Building & Trades",
            "subcategory":"Landscaping Services",
            "type":"Services"
        }
    ],
    "sg:phone":"+1 770 242 7366",
    "sg:postcode":"30360",
    "sg:province":"GA",
    "sg:tags":[
        "lawn",
        "maintenance",
        "grounds"
    ],
    "wof:name":"Per-Fect-A-Lawn",
    "wof:placetype":"venue"
},
  "geometry": {"coordinates":[-84.23025699999999,33.931798],"type":"Point"}
}