{
  "type": "Feature",
  "properties": {
    "addr:full":"1189 W Mill Dr NW Kennesaw GA 30152",
    "addr:housenumber":"1189",
    "addr:postcode":"30152",
    "addr:street":"W Mill Dr Nw",
    "iso:country":"US",
    "sg:address":"1189 W Mill Dr NW",
    "sg:city":"Kennesaw",
    "sg:classifiers":[
        {
            "category":"Professional",
            "subcategory":"Advertising",
            "type":"Services"
        }
    ],
    "sg:phone":"+1 770 794 7018",
    "sg:postcode":"30152",
    "sg:province":"GA",
    "sg:tags":[
        "mail",
        "direct"
    ],
    "wof:name":"Rainmaker Lists",
    "wof:placetype":"venue"
},
  "geometry": {"coordinates":[-84.678693,33.977577],"type":"Point"}
}