{
  "type": "Feature",
  "properties": {
    "addr:full":"539 10th St NW Atlanta GA 30318",
    "addr:housenumber":"539",
    "addr:postcode":"30318",
    "addr:street":"10Th St Nw",
    "iso:country":"US",
    "sg:address":"539 10th St NW",
    "sg:city":"Atlanta",
    "sg:classifiers":[
        {
            "category":"Sports & Exercise",
            "subcategory":"Gym",
            "type":"Entertainment"
        }
    ],
    "sg:postcode":"30318",
    "sg:province":"GA",
    "sg:website":"www.bodydesignpersonaltraining.c...",
    "wof:name":"Body Design Midtown",
    "wof:placetype":"venue"
},
  "geometry": {"coordinates":[-84.405412,33.781562],"type":"Point"}
}