{
  "type": "Feature",
  "properties": {
    "addr:full":"101 Orchard Pkwy Cumming GA 30040",
    "addr:housenumber":"101",
    "addr:postcode":"30040",
    "addr:street":"Orchard Pkwy",
    "iso:country":"US",
    "sg:address":"101 Orchard Pkwy",
    "sg:city":"Cumming",
    "sg:classifiers":[
        {
            "category":"Retail",
            "subcategory":"Auto Repair",
            "type":"Services"
        }
    ],
    "sg:phone":"+1 770 888 4522",
    "sg:postcode":"30040",
    "sg:province":"GA",
    "sg:tags":[
        "automotive"
    ],
    "wof:name":"Protect Collision",
    "wof:placetype":"venue"
},
  "geometry": {"coordinates":[-84.13930499999999,34.193121],"type":"Point"}
}