{
  "type": "Feature",
  "properties": {
    "addr:full":"2821 Pine Log Way Buford GA 30519",
    "addr:housenumber":"2821",
    "addr:postcode":"30519",
    "addr:street":"Pine Log Way",
    "iso:country":"US",
    "sg:address":"2821 Pine Log Way",
    "sg:city":"Buford",
    "sg:classifiers":[
        {
            "category":"Building & Trades",
            "subcategory":"Construction",
            "type":"Services"
        }
    ],
    "sg:phone":"+1 678 377 7088",
    "sg:postcode":"30519",
    "sg:province":"GA",
    "sg:tags":[
        "stucco",
        "contractor"
    ],
    "wof:name":"Five Star Stucco",
    "wof:placetype":"venue"
},
  "geometry": {"coordinates":[-83.980581,34.053451],"type":"Point"}
}