{
  "type": "Feature",
  "properties": {
    "addr:full":"2001 Professional Way Woodstock GA 30188",
    "addr:housenumber":"2001",
    "addr:postcode":"30188",
    "addr:street":"Professional Way",
    "iso:country":"US",
    "sg:address":"2001 Professional Way",
    "sg:city":"Woodstock",
    "sg:classifiers":[
        {
            "category":"Health Services",
            "subcategory":"Doctor",
            "type":"Services"
        }
    ],
    "sg:phone":"+1 770 926 3465",
    "sg:postcode":"30188",
    "sg:province":"GA",
    "sg:website":"www.urologyatlanta.com",
    "wof:name":"Atlanta Urology Associates PC",
    "wof:placetype":"venue"
},
  "geometry": {"coordinates":[-84.5224,34.082802],"type":"Point"}
}