{
  "type": "Feature",
  "properties": {
    "addr:full":"2586 Satellite Blvd Duluth GA 30096",
    "addr:housenumber":"2586",
    "addr:postcode":"30096",
    "addr:street":"Satellite Blvd",
    "iso:country":"US",
    "sg:address":"2586 Satellite Blvd",
    "sg:city":"Duluth",
    "sg:classifiers":[
        {
            "category":"Retail",
            "subcategory":"Auto Rental",
            "type":"Services"
        }
    ],
    "sg:phone":"+1 770 623 4065",
    "sg:postcode":"30096",
    "sg:province":"GA",
    "sg:tags":[
        "car"
    ],
    "sg:website":"www.hertz.com",
    "wof:name":"Hertz Local Edition",
    "wof:placetype":"venue"
},
  "geometry": {"coordinates":[-84.09953,33.96838],"type":"Point"}
}