{
  "type": "Feature",
  "properties": {
    "addr:full":"107 Alexander St La Grange GA 30241",
    "addr:housenumber":"107",
    "addr:postcode":"30241",
    "addr:street":"Alexander St",
    "iso:country":"US",
    "sg:address":"107 Alexander St",
    "sg:city":"La Grange",
    "sg:classifiers":[
        {
            "category":"Shopping",
            "subcategory":"Used Merchandise",
            "type":"Retail Goods"
        }
    ],
    "sg:phone":"+1 706 884 5600",
    "sg:postcode":"30241",
    "sg:province":"GA",
    "sg:tags":[
        "shop",
        "pawn"
    ],
    "wof:name":"Traylors Pawn & Jewelry",
    "wof:placetype":"venue"
},
  "geometry": {"coordinates":[-85.027023,33.039767],"type":"Point"}
}