{
  "type": "Feature",
  "properties": {
    "addr:full":"1781 Veterans Memorial Hwy Austell GA 30168",
    "addr:housenumber":"1781",
    "addr:postcode":"30168",
    "addr:street":"Veterans Memorial Hwy",
    "iso:country":"US",
    "sg:address":"1781 Veterans Memorial Hwy",
    "sg:city":"Austell",
    "sg:classifiers":[
        {
            "category":"Health Services",
            "subcategory":"Chiropractor",
            "type":"Services"
        }
    ],
    "sg:phone":"+1 770 941 3802",
    "sg:postcode":"30168",
    "sg:province":"GA",
    "wof:name":"Siegrist Harry E III Dr Chiroprctr",
    "wof:placetype":"venue"
},
  "geometry": {"coordinates":[-84.606109,33.817275],"type":"Point"}
}