{
  "type": "Feature",
  "properties": {
    "addr:full":"510 Lower Brookfield Rd Tifton GA 31794",
    "addr:housenumber":"510",
    "addr:postcode":"31794",
    "addr:street":"Lower Brookfield Rd",
    "iso:country":"US",
    "sg:address":"510 Lower Brookfield Rd",
    "sg:city":"Tifton",
    "sg:classifiers":[
        {
            "category":"Manufacturing",
            "subcategory":"Glass & Minerals",
            "type":"Manufacturing & Wholesale Goods"
        }
    ],
    "sg:phone":"+1 229 382 4239",
    "sg:postcode":"31794",
    "sg:province":"GA",
    "sg:tags":[
        "concrete",
        "brick",
        "prod",
        "block"
    ],
    "sg:website":"www.americanstatuary.com",
    "wof:name":"American Statuary",
    "wof:placetype":"venue"
},
  "geometry": {"coordinates":[-83.431997,31.415149],"type":"Point"}
}