{
  "type": "Feature",
  "properties": {
    "addr:full":"4896 N Royal Atlanta Dr Tucker GA 30084",
    "addr:housenumber":"4896",
    "addr:postcode":"30084",
    "addr:street":"N Royal Atlanta Dr",
    "iso:country":"US",
    "sg:address":"4896 N Royal Atlanta Dr",
    "sg:city":"Tucker",
    "sg:classifiers":[
        {
            "category":"Professional",
            "subcategory":"Management & Consulting",
            "type":"Services"
        }
    ],
    "sg:phone":"+1 770 938 7731",
    "sg:postcode":"30084",
    "sg:province":"GA",
    "sg:tags":[
        "equipment",
        "electrical"
    ],
    "wof:name":"L M Getz Co",
    "wof:placetype":"venue"
},
  "geometry": {"coordinates":[-84.186505,33.858691],"type":"Point"}
}