{
  "type": "Feature",
  "properties": {
    "addr:full":"721 N Main St Glennville GA 30427",
    "addr:housenumber":"721",
    "addr:postcode":"30427",
    "addr:street":"N Main St",
    "iso:country":"US",
    "sg:address":"721 N Main St",
    "sg:city":"Glennville",
    "sg:classifiers":[
        {
            "category":"Health Services",
            "subcategory":"Nursing And Care Facility",
            "type":"Services"
        }
    ],
    "sg:phone":"+1 912 654 2138",
    "sg:postcode":"30427",
    "sg:province":"GA",
    "sg:tags":[
        "skilled",
        "intermediate"
    ],
    "wof:name":"Glenview Nursing Home",
    "wof:placetype":"venue"
},
  "geometry": {"coordinates":[-81.925258,31.946311],"type":"Point"}
}