{
  "type": "Feature",
  "properties": {
    "addr:full":"25 S Terrell St Metter GA 30439",
    "addr:housenumber":"25",
    "addr:postcode":"30439",
    "addr:street":"S Terrell St",
    "iso:country":"US",
    "sg:address":"25 S Terrell St",
    "sg:city":"Metter",
    "sg:classifiers":[
        {
            "category":"Wholesale",
            "subcategory":"Construction Materials",
            "type":"Manufacturing & Wholesale Goods"
        }
    ],
    "sg:phone":"+1 912 685 6415",
    "sg:postcode":"30439",
    "sg:province":"GA",
    "sg:tags":[
        "timberland",
        "company",
        "timber"
    ],
    "wof:name":"Candler Timber Co",
    "wof:placetype":"venue"
},
  "geometry": {"coordinates":[-82.057286,32.396923],"type":"Point"}
}