{
  "type": "Feature",
  "properties": {
    "addr:full":"1100 Hickory Level Rd Villa Rica GA 30180",
    "addr:housenumber":"1100",
    "addr:postcode":"30180",
    "addr:street":"Hickory Level Rd",
    "iso:country":"US",
    "sg:address":"1100 Hickory Level Rd",
    "sg:city":"Villa Rica",
    "sg:classifiers":[
        {
            "category":"Real Estate",
            "subcategory":"Developer",
            "type":"Services"
        }
    ],
    "sg:phone":"+1 770 459 6494",
    "sg:postcode":"30180",
    "sg:province":"GA",
    "sg:tags":[
        "cemetery"
    ],
    "sg:website":"www.jones-wynn.com",
    "wof:name":"Meadowbrook Memory Garden",
    "wof:placetype":"venue"
},
  "geometry": {"coordinates":[-84.94757300000001,33.714811],"type":"Point"}
}