{
  "type": "Feature",
  "properties": {
    "iso:country":"US",
    "sg:address":"303 Mandeville Ave",
    "sg:city":"Carrollton",
    "sg:classifiers":[
        {
            "category":"Social Services",
            "type":"Services"
        }
    ],
    "sg:phone":"+1 770 834 5755",
    "sg:postcode":"30117",
    "sg:province":"GA",
    "sg:tags":[
        "food",
        "banks"
    ],
    "wof:name":"Manna House",
    "wof:placetype":"venue"
},
  "geometry": {"coordinates":[-85.062752,33.578085],"type":"Point"}
}