{
  "type": "Feature",
  "properties": {
    "iso:country":"US",
    "sg:address":"3050 Five Forks Trickum Rd SW",
    "sg:city":"Lilburn",
    "sg:classifiers":[
        {
            "category":"Personal",
            "subcategory":"Tanning Parlor",
            "type":"Services"
        }
    ],
    "sg:phone":"+1 770 972 6651",
    "sg:postcode":"30047",
    "sg:province":"GA",
    "sg:website":"www.tropixtanningsalon.com",
    "wof:name":"Tropix Tanning Salon",
    "wof:placetype":"venue"
},
  "geometry": {"coordinates":[-84.06151199999999,33.885033],"type":"Point"}
}