{
  "type": "Feature",
  "properties": {
    "addr:full":"6199 Highway 92 Acworth GA 30102",
    "addr:housenumber":"6199",
    "addr:postcode":"30102",
    "addr:street":"Highway 92",
    "iso:country":"US",
    "sg:address":"6199 Highway 92",
    "sg:city":"Acworth",
    "sg:classifiers":[
        {
            "category":"Restaurant",
            "type":"Food & Drink"
        }
    ],
    "sg:menulink":"http://www.allmenus.com/ga/woodstock/241862-china-house/menu/",
    "sg:phone":"+1 770 926 7662",
    "sg:postcode":"30102",
    "sg:province":"GA",
    "sg:tags":[
        "asian",
        "chinese"
    ],
    "wof:name":"China House",
    "wof:placetype":"venue"
},
  "geometry": {"coordinates":[-84.624374,34.120468],"type":"Point"}
}