{
  "type": "Feature",
  "properties": {
    "addr:full":"88 Woodhaven Dr Eatonton GA 31024",
    "addr:housenumber":"88",
    "addr:postcode":"31024",
    "addr:street":"Woodhaven Dr",
    "iso:country":"US",
    "sg:address":"88 Woodhaven Dr",
    "sg:city":"Eatonton",
    "sg:classifiers":[
        {
            "category":"Professional",
            "subcategory":"Printing & Photocopies",
            "type":"Services"
        },
        {
            "category":"Manufacturing",
            "subcategory":"Apparel",
            "type":"Manufacturing & Wholesale Goods"
        }
    ],
    "sg:phone":"+1 706 485 3519",
    "sg:postcode":"31024",
    "sg:province":"GA",
    "sg:tags":[
        "accessories-wholesale",
        "flag",
        "flags",
        "pennant",
        "flagpole",
        "banners",
        "manufacturer"
    ],
    "sg:website":"http://www.rebelprideband.com",
    "wof:name":"Rebel John's Pride",
    "wof:placetype":"venue"
},
  "geometry": {"coordinates":[-83.261869,33.267852],"type":"Point"}
}