{
  "type": "Feature",
  "properties": {
    "iso:country":"US",
    "sg:address":"1395 Ambercrest Way",
    "sg:city":"Austell",
    "sg:classifiers":[
        {
            "category":"Shopping",
            "subcategory":"Discount & Variety Stores",
            "type":"Retail Goods"
        }
    ],
    "sg:phone":"+1 770 745 5575",
    "sg:postcode":"30126",
    "sg:province":"GA",
    "sg:tags":[
        "merchandise",
        "general"
    ],
    "wof:name":"Unlimited Exchange",
    "wof:placetype":"venue"
},
  "geometry": {"coordinates":[-84.59567,33.779827],"type":"Point"}
}