{
  "type": "Feature",
  "properties": {
    "iso:country":"US",
    "sg:address":"3343 Country Club Rd",
    "sg:city":"Valdosta",
    "sg:classifiers":[
        {
            "category":"Personal",
            "subcategory":"Barber",
            "type":"Services"
        }
    ],
    "sg:phone":"+1 229 242 6994",
    "sg:postcode":"31605",
    "sg:province":"GA",
    "sg:tags":[
        "shop"
    ],
    "wof:name":"Perimeter Road Barber Shop",
    "wof:placetype":"venue"
},
  "geometry": {"coordinates":[-83.297488,30.880995],"type":"Point"}
}