{
  "type": "Feature",
  "properties": {
    "addr:full":"1963 State Rte 54 Fayetteville GA 30214",
    "addr:housenumber":"1963",
    "addr:postcode":"30214",
    "addr:street":"State Rte 54",
    "iso:country":"US",
    "sg:address":"1963 State Rte 54",
    "sg:city":"Fayetteville",
    "sg:classifiers":[
        {
            "category":"Retail",
            "subcategory":"Veterinary Services",
            "type":"Services"
        }
    ],
    "sg:phone":"+1 770 487 5354",
    "sg:postcode":"30214",
    "sg:province":"GA",
    "sg:tags":[
        "veterinarian"
    ],
    "wof:name":"Flat Creek Animal Clinic",
    "wof:placetype":"venue"
},
  "geometry": {"coordinates":[-84.55529799999999,33.430595],"type":"Point"}
}