{
  "type": "Feature",
  "properties": {
    "addr:full":"1680 Roberts Blvd. Suite 403 Kennesaw GA 30144",
    "addr:housenumber":"1680",
    "addr:postcode":"30144",
    "addr:street":"Roberts Blvd. Suite 403",
    "iso:country":"US",
    "sg:address":"1680 Roberts Blvd. Suite 403",
    "sg:city":"Kennesaw",
    "sg:classifiers":[
        {
            "category":"Home & Garden",
            "subcategory":"Hardware",
            "type":"Retail Goods"
        }
    ],
    "sg:phone":"+1 800 366 7235",
    "sg:postcode":"30144",
    "sg:province":"GA",
    "sg:tags":[
        "store"
    ],
    "sg:website":"www.security2020.net",
    "wof:name":"Security2020.net",
    "wof:placetype":"venue"
},
  "geometry": {"coordinates":[-84.59033700000001,34.004392],"type":"Point"}
}