{
  "type": "Feature",
  "properties": {
    "addr:full":"1064 Holbrook Campground Rd Cumming GA 30040",
    "addr:housenumber":"1064",
    "addr:postcode":"30040",
    "addr:street":"Holbrook Campground Rd",
    "iso:country":"US",
    "sg:address":"1064 Holbrook Campground Rd",
    "sg:city":"Cumming",
    "sg:classifiers":[
        {
            "category":"Professional",
            "subcategory":"Computer Services",
            "type":"Services"
        }
    ],
    "sg:phone":"+1 770 844 1667",
    "sg:postcode":"30040",
    "sg:province":"GA",
    "sg:tags":[
        "related"
    ],
    "wof:name":"Corporate Data Partners",
    "wof:placetype":"venue"
},
  "geometry": {"coordinates":[-84.272486,34.229838],"type":"Point"}
}