{
  "type": "Feature",
  "properties": {
    "addr:full":"2457 Wheeler Rd Augusta GA 30904",
    "addr:housenumber":"2457",
    "addr:postcode":"30904",
    "addr:street":"Wheeler Rd",
    "iso:country":"US",
    "sg:address":"2457 Wheeler Rd",
    "sg:city":"Augusta",
    "sg:classifiers":[
        {
            "category":"Restaurant",
            "type":"Food & Drink"
        }
    ],
    "sg:phone":"+1 706 481 8689",
    "sg:postcode":"30904",
    "sg:province":"GA",
    "wof:name":"Sand Hill Grill",
    "wof:placetype":"venue"
},
  "geometry": {"coordinates":[-82.02176799999999,33.482627],"type":"Point"}
}