{
  "type": "Feature",
  "properties": {
    "iso:country":"US",
    "sg:address":"1103 Creatwood Cir SE",
    "sg:city":"Smyrna",
    "sg:classifiers":[
        {
            "category":"Wholesale",
            "subcategory":"Medical Equipment & Supplies",
            "type":"Manufacturing & Wholesale Goods"
        },
        {
            "category":"Building & Trades",
            "subcategory":"Construction",
            "type":"Services"
        },
        {
            "category":"Home & Garden",
            "subcategory":"Carpets & Floor Coverings",
            "type":"Retail Goods"
        }
    ],
    "sg:phone":"+1 770 434 1006",
    "sg:postcode":"30080",
    "sg:province":"GA",
    "sg:tags":[
        "trusses-construction",
        "industrial",
        "roofing",
        "roof",
        "contractor",
        "contractors-commercial",
        "truss",
        "structure"
    ],
    "wof:name":"Salter Associates",
    "wof:placetype":"venue"
},
  "geometry": {"coordinates":[-84.50181499999999,33.875288],"type":"Point"}
}