{
  "type": "Feature",
  "properties": {
    "iso:country":"US",
    "sg:address":"124 Monterey Dr",
    "sg:city":"Peachtree City",
    "sg:classifiers":[
        {
            "category":"Freight",
            "type":"Transportation"
        }
    ],
    "sg:phone":"+1 770 632 6414",
    "sg:postcode":"30269",
    "sg:province":"GA",
    "wof:name":"Seven Sons Transportation",
    "wof:placetype":"venue"
},
  "geometry": {"coordinates":[-84.548455,33.368071],"type":"Point"}
}