{
  "type": "Feature",
  "properties": {
    "addr:full":"1102 Reynolds St Augusta GA 30901",
    "addr:housenumber":"1102",
    "addr:postcode":"30901",
    "addr:street":"Reynolds St",
    "iso:country":"US",
    "sg:address":"1102 Reynolds St",
    "sg:city":"Augusta",
    "sg:classifiers":[
        {
            "category":"Banks & Credit Unions",
            "subcategory":"Bank",
            "type":"Services"
        }
    ],
    "sg:phone":"+1 706 823 2850",
    "sg:postcode":"30901",
    "sg:province":"GA",
    "wof:name":"Wachovia Bank",
    "wof:placetype":"venue"
},
  "geometry": {"coordinates":[-81.971935,33.479139],"type":"Point"}
}