{
  "type": "Feature",
  "properties": {
    "iso:country":"US",
    "sg:address":"957 Canton St",
    "sg:city":"Roswell",
    "sg:classifiers":[
        {
            "category":"Shopping",
            "subcategory":"Clothing, Apparel, & Fashions",
            "type":"Retail Goods"
        }
    ],
    "sg:phone":"+1 770 518 6011",
    "sg:postcode":"30075",
    "sg:province":"GA",
    "sg:tags":[
        "accessory",
        "clothing",
        "women's"
    ],
    "wof:name":"Magnolia",
    "wof:placetype":"venue"
},
  "geometry": {"coordinates":[-84.361603,34.024502],"type":"Point"}
}