{
  "type": "Feature",
  "properties": {
    "addr:full":"1403 Swift Ct Albany GA 31705",
    "addr:housenumber":"1403",
    "addr:postcode":"31705",
    "addr:street":"Swift Ct",
    "iso:country":"US",
    "sg:address":"1403 Swift Ct",
    "sg:city":"Albany",
    "sg:classifiers":[
        {
            "category":"Building & Trades",
            "subcategory":"Construction",
            "type":"Services"
        }
    ],
    "sg:phone":"+1 229 888 0090",
    "sg:postcode":"31705",
    "sg:province":"GA",
    "sg:tags":[
        "general",
        "contractor"
    ],
    "wof:name":"H Williams Lee Co",
    "wof:placetype":"venue"
},
  "geometry": {"coordinates":[-84.126893,31.588416],"type":"Point"}
}