{
  "type": "Feature",
  "properties": {
    "iso:country":"US",
    "sg:address":"2324 S Patterson St",
    "sg:city":"Valdosta",
    "sg:classifiers":[
        {
            "category":"Building & Trades",
            "subcategory":"Construction",
            "type":"Services"
        }
    ],
    "sg:phone":"+1 229 671 1904",
    "sg:postcode":"31601",
    "sg:province":"GA",
    "sg:tags":[
        "home",
        "builder"
    ],
    "wof:name":"Keith Allsbrook Constr Co",
    "wof:placetype":"venue"
},
  "geometry": {"coordinates":[-83.24706399999999,30.799856],"type":"Point"}
}