{
  "type": "Feature",
  "properties": {
    "iso:country":"US",
    "sg:address":"243 N 5th Ave",
    "sg:city":"Rome",
    "sg:classifiers":[
        {
            "category":"Wholesale",
            "subcategory":"Electrical",
            "type":"Manufacturing & Wholesale Goods"
        }
    ],
    "sg:phone":"+1 706 291 0002",
    "sg:postcode":"30165",
    "sg:province":"GA",
    "sg:tags":[
        "appliance"
    ],
    "wof:name":"AAPCO Appliance Parts Co",
    "wof:placetype":"venue"
},
  "geometry": {"coordinates":[-85.173301,34.258036],"type":"Point"}
}