{
  "type": "Feature",
  "properties": {
    "addr:full":"1036 Canton St Roswell GA 30075",
    "addr:housenumber":"1036",
    "addr:postcode":"30075",
    "addr:street":"Canton St",
    "iso:country":"US",
    "sg:address":"1036 Canton St",
    "sg:city":"Roswell",
    "sg:classifiers":[
        {
            "category":"Personal",
            "subcategory":"Beauty Salon",
            "type":"Services"
        }
    ],
    "sg:phone":"+1 770 645 0451",
    "sg:postcode":"30075",
    "sg:province":"GA",
    "sg:tags":[
        "spa"
    ],
    "sg:website":"plumtreesalonandspa.com",
    "wof:name":"Plum Tree Salon & Spa",
    "wof:placetype":"venue"
},
  "geometry": {"coordinates":[-84.36129800000001,34.0266],"type":"Point"}
}