{
  "type": "Feature",
  "properties": {
    "addr:full":"278 Sawgrass Way Fayetteville GA 30215",
    "addr:housenumber":"278",
    "addr:postcode":"30215",
    "addr:street":"Sawgrass Way",
    "iso:country":"US",
    "sg:address":"278 Sawgrass Way",
    "sg:city":"Fayetteville",
    "sg:classifiers":[
        {
            "category":"Building & Trades",
            "subcategory":"Electrical",
            "type":"Services"
        }
    ],
    "sg:phone":"+1 770 719 3981",
    "sg:postcode":"30215",
    "sg:province":"GA",
    "sg:tags":[
        "electrical",
        "contractor"
    ],
    "wof:name":"Can Do Additions",
    "wof:placetype":"venue"
},
  "geometry": {"coordinates":[-84.39859300000001,33.430999],"type":"Point"}
}