{
  "type": "Feature",
  "properties": {
    "iso:country":"US",
    "sg:address":"4806 Upper Brandon Pl",
    "sg:city":"Marietta",
    "sg:classifiers":[
        {
            "category":"Professional",
            "subcategory":"Detective & Security Services",
            "type":"Services"
        }
    ],
    "sg:phone":"+1 770 587 4085",
    "sg:postcode":"30068",
    "sg:province":"GA",
    "sg:tags":[
        "system"
    ],
    "wof:name":"Remote Security Systems",
    "wof:placetype":"venue"
},
  "geometry": {"coordinates":[-84.408928,33.975947],"type":"Point"}
}