{
  "type": "Feature",
  "properties": {
    "iso:country":"US",
    "sg:address":"2849 State Rte 297",
    "sg:city":"Vidalia",
    "sg:classifiers":[
        {
            "category":"Shopping",
            "type":"Retail Goods"
        }
    ],
    "sg:phone":"+1 912 537 7030",
    "sg:postcode":"30474",
    "sg:province":"GA",
    "sg:tags":[
        "equipment",
        "telephone",
        "supply"
    ],
    "wof:name":"Bradmark Co",
    "wof:placetype":"venue"
},
  "geometry": {"coordinates":[-82.408761,32.265124],"type":"Point"}
}