{
  "type": "Feature",
  "properties": {
    "iso:country":"US",
    "sg:address":"12428 Largo Dr",
    "sg:city":"Savannah",
    "sg:classifiers":[
        {
            "category":"Freight",
            "type":"Transportation"
        }
    ],
    "sg:phone":"+1 912 925 8685",
    "sg:postcode":"31419",
    "sg:province":"GA",
    "sg:tags":[
        "roofing",
        "material",
        "hauling",
        "asphalt"
    ],
    "wof:name":"CB Trucking",
    "wof:placetype":"venue"
},
  "geometry": {"coordinates":[-81.149928,31.977866],"type":"Point"}
}