{
  "type": "Feature",
  "properties": {
    "addr:full":"950 Overbrook Cir Marietta GA 30062",
    "addr:housenumber":"950",
    "addr:postcode":"30062",
    "addr:street":"Overbrook Cir",
    "iso:country":"US",
    "sg:address":"950 Overbrook Cir",
    "sg:city":"Marietta",
    "sg:classifiers":[
        {
            "category":"Building & Trades",
            "subcategory":"Cleaning & Sanitation",
            "type":"Services"
        }
    ],
    "sg:phone":"+1 770 590 0587",
    "sg:postcode":"30062",
    "sg:province":"GA",
    "sg:tags":[
        "maintenance"
    ],
    "wof:name":"Agape Cleaning Svcs",
    "wof:placetype":"venue"
},
  "geometry": {"coordinates":[-84.525322,33.976217],"type":"Point"}
}