{
  "type": "Feature",
  "properties": {
    "addr:full":"1141 Nona Dr Athens GA 30606",
    "addr:housenumber":"1141",
    "addr:postcode":"30606",
    "addr:street":"Nona Dr",
    "iso:country":"US",
    "sg:address":"1141 Nona Dr",
    "sg:city":"Athens",
    "sg:classifiers":[
        {
            "category":"Building & Trades",
            "subcategory":"Landscaping Services",
            "type":"Services"
        }
    ],
    "sg:phone":"+1 706 542 0062",
    "sg:postcode":"30606",
    "sg:province":"GA",
    "sg:tags":[
        "consultant",
        "designer",
        "landscape"
    ],
    "wof:name":"Sawhill And Associates",
    "wof:placetype":"venue"
},
  "geometry": {"coordinates":[-83.442413,33.901131],"type":"Point"}
}