{
  "type": "Feature",
  "properties": {
    "iso:country":"US",
    "sg:address":"2844 Cottonwood Dr",
    "sg:city":"Marietta",
    "sg:classifiers":[
        {
            "category":"Real Estate",
            "subcategory":"Real Estate Services",
            "type":"Services"
        }
    ],
    "sg:phone":"+1 770 423 7577",
    "sg:postcode":"30066",
    "sg:province":"GA",
    "wof:name":"American Institute of Real Estate",
    "wof:placetype":"venue"
},
  "geometry": {"coordinates":[-84.54789700000001,34.0201],"type":"Point"}
}