{
  "type": "Feature",
  "properties": {
    "iso:country":"US",
    "sg:address":"100 Arthur J Moore Dr",
    "sg:city":"St Simons Island",
    "sg:classifiers":[
        {
            "category":"Organizations",
            "subcategory":"Community Association",
            "type":"Services"
        }
    ],
    "sg:phone":"+1 912 638 3849",
    "sg:postcode":"31522",
    "sg:province":"GA",
    "sg:tags":[
        "environmental",
        "org"
    ],
    "wof:name":"Driftwood Education Ctr",
    "wof:placetype":"venue"
},
  "geometry": {"coordinates":[-81.404549,31.177704],"type":"Point"}
}