{
  "type": "Feature",
  "properties": {
    "addr:full":"26 Redcomb Dr Cartersville GA 30120",
    "addr:housenumber":"26",
    "addr:postcode":"30120",
    "addr:street":"Redcomb Dr",
    "iso:country":"US",
    "sg:address":"26 Redcomb Dr",
    "sg:city":"Cartersville",
    "sg:classifiers":[
        {
            "category":"Professional",
            "type":"Services"
        }
    ],
    "sg:phone":"+1 770 607 9121",
    "sg:postcode":"30120",
    "sg:province":"GA",
    "sg:tags":[
        "establishment"
    ],
    "wof:name":"Bartow County Wood Yard Inc",
    "wof:placetype":"venue"
},
  "geometry": {"coordinates":[-84.804242,34.178453],"type":"Point"}
}