{
  "type": "Feature",
  "properties": {
    "iso:country":"US",
    "sg:address":"2954 Surrey Ln",
    "sg:city":"Atlanta",
    "sg:classifiers":[
        {
            "category":"Professional",
            "subcategory":"Business Services",
            "type":"Services"
        }
    ],
    "sg:phone":"+1 770 457 0991",
    "sg:postcode":"30341",
    "sg:province":"GA",
    "wof:name":"Dekreek Enterprises Inc",
    "wof:placetype":"venue"
},
  "geometry": {"coordinates":[-84.31818800000001,33.876588],"type":"Point"}
}