{
  "type": "Feature",
  "properties": {
    "iso:country":"US",
    "sg:address":"4524 Forsyth Rd",
    "sg:city":"Macon",
    "sg:classifiers":[
        {
            "category":"Shopping",
            "subcategory":"Florist",
            "type":"Retail Goods"
        },
        {
            "category":"Shopping",
            "subcategory":"Gifts & Souvenirs",
            "type":"Retail Goods"
        }
    ],
    "sg:phone":"+1 478 475 5511",
    "sg:postcode":"31210",
    "sg:province":"GA",
    "wof:name":"Allisons Florist & Gifts Grdn",
    "wof:placetype":"venue"
},
  "geometry": {"coordinates":[-83.703715,32.87118],"type":"Point"}
}