{
  "type": "Feature",
  "properties": {
    "iso:country":"US",
    "sg:address":"811 Old Tails Creek Rd",
    "sg:city":"Ellijay",
    "sg:classifiers":[
        {
            "category":"Building & Trades",
            "subcategory":"Construction",
            "type":"Services"
        }
    ],
    "sg:phone":"+1 706 636 2594",
    "sg:postcode":"30540",
    "sg:province":"GA",
    "sg:tags":[
        "concrete",
        "contractor"
    ],
    "wof:name":"Colwell Walls & Foundations",
    "wof:placetype":"venue"
},
  "geometry": {"coordinates":[-84.501848,34.702734],"type":"Point"}
}