{
  "type": "Feature",
  "properties": {
    "iso:country":"US",
    "sg:address":"3114 Augusta Tech Dr",
    "sg:city":"Augusta",
    "sg:classifiers":[
        {
            "category":"Personal",
            "subcategory":"Beauty Salon",
            "type":"Services"
        },
        {
            "category":"Personal",
            "subcategory":"Barber",
            "type":"Services"
        }
    ],
    "sg:phone":"+1 706 793 6500",
    "sg:postcode":"30906",
    "sg:province":"GA",
    "sg:tags":[
        "hair",
        "stylist"
    ],
    "wof:name":"Wrights Touch Beauty & Ba",
    "wof:placetype":"venue"
},
  "geometry": {"coordinates":[-82.054233,33.425205],"type":"Point"}
}