{
  "type": "Feature",
  "properties": {
    "addr:full":"1401 Johnson Ferry Rd Marietta GA 30062",
    "addr:housenumber":"1401",
    "addr:postcode":"30062",
    "addr:street":"Johnson Ferry Rd",
    "iso:country":"US",
    "sg:address":"1401 Johnson Ferry Rd",
    "sg:city":"Marietta",
    "sg:classifiers":[
        {
            "category":"Shopping",
            "subcategory":"Computers & Home Electronics",
            "type":"Retail Goods"
        }
    ],
    "sg:phone":"+1 678 560 6553",
    "sg:postcode":"30062",
    "sg:province":"GA",
    "sg:tags":[
        "game",
        "video"
    ],
    "wof:name":"Game Stop Corp",
    "wof:placetype":"venue"
},
  "geometry": {"coordinates":[-84.42715699999999,33.984781],"type":"Point"}
}