{
  "type": "Feature",
  "properties": {
    "iso:country":"US",
    "sg:address":"340 Hood Pkwy NW",
    "sg:city":"Kennesaw",
    "sg:classifiers":[
        {
            "category":"Retail",
            "subcategory":"Repair Shop",
            "type":"Services"
        }
    ],
    "sg:phone":"+1 770 428 6006",
    "sg:postcode":"30152",
    "sg:province":"GA",
    "wof:name":"Clean Rite Maid Service",
    "wof:placetype":"venue"
},
  "geometry": {"coordinates":[-84.595393,33.995819],"type":"Point"}
}