{
  "type": "Feature",
  "properties": {
    "addr:full":"3775 Buford Hwy Duluth GA 30096",
    "addr:housenumber":"3775",
    "addr:postcode":"30096",
    "addr:street":"Buford Hwy",
    "iso:country":"US",
    "sg:address":"3775 Buford Hwy",
    "sg:city":"Duluth",
    "sg:classifiers":[
        {
            "category":"Autos & Motor Vehicles",
            "subcategory":"Fuel & Gas Station",
            "type":"Retail Goods"
        }
    ],
    "sg:phone":"+1 770 497 9107",
    "sg:postcode":"30096",
    "sg:province":"GA",
    "sg:tags":[
        "oil"
    ],
    "wof:name":"Citgo",
    "wof:placetype":"venue"
},
  "geometry": {"coordinates":[-84.15938800000001,33.979664],"type":"Point"}
}