{
  "type": "Feature",
  "properties": {
    "iso:country":"US",
    "sg:address":"2470 Martin Luther King Jr Dr SW",
    "sg:city":"Atlanta",
    "sg:classifiers":[
        {
            "category":"Banks & Credit Unions",
            "subcategory":"Investment Brokerage",
            "type":"Services"
        },
        {
            "category":"Insurance",
            "subcategory":"Hazard Insurance",
            "type":"Services"
        }
    ],
    "sg:phone":"+1 404 691 6642",
    "sg:postcode":"30311",
    "sg:province":"GA",
    "sg:tags":[
        "agent",
        "resume"
    ],
    "wof:name":"Auto Town Insurance Agency",
    "wof:placetype":"venue"
},
  "geometry": {"coordinates":[-84.468356,33.752129],"type":"Point"}
}