{
  "type": "Feature",
  "properties": {
    "addr:full":"2290 Pio Nono Ave Macon GA 31206",
    "addr:housenumber":"2290",
    "addr:postcode":"31206",
    "addr:street":"Pio Nono Ave",
    "iso:country":"US",
    "sg:address":"2290 Pio Nono Ave",
    "sg:city":"Macon",
    "sg:classifiers":[
        {
            "category":"Personal",
            "subcategory":"Barber",
            "type":"Services"
        }
    ],
    "sg:phone":"+1 478 781 4526",
    "sg:postcode":"31206",
    "sg:province":"GA",
    "wof:name":"Hillman's Imperial Barber",
    "wof:placetype":"venue"
},
  "geometry": {"coordinates":[-83.662683,32.818846],"type":"Point"}
}