{
  "type": "Feature",
  "properties": {
    "addr:full":"336 Sang Rd Cleveland GA 30528",
    "addr:housenumber":"336",
    "addr:postcode":"30528",
    "addr:street":"Sang Rd",
    "iso:country":"US",
    "sg:address":"336 Sang Rd",
    "sg:city":"Cleveland",
    "sg:classifiers":[
        {
            "category":"Professional",
            "subcategory":"Lawyer & Legal Services",
            "type":"Services"
        }
    ],
    "sg:phone":"+1 706 865 1460",
    "sg:postcode":"30528",
    "sg:province":"GA",
    "sg:tags":[
        "plan"
    ],
    "wof:name":"Acr Attorney",
    "wof:placetype":"venue"
},
  "geometry": {"coordinates":[-83.65297,34.639519],"type":"Point"}
}