{
  "type": "Feature",
  "properties": {
    "addr:full":"2117 Shirley Ave Augusta GA 30904",
    "addr:housenumber":"2117",
    "addr:postcode":"30904",
    "addr:street":"Shirley Ave",
    "iso:country":"US",
    "sg:address":"2117 Shirley Ave",
    "sg:city":"Augusta",
    "sg:classifiers":[
        {
            "category":"Organizations",
            "subcategory":"Membership Organization",
            "type":"Services"
        }
    ],
    "sg:phone":"+1 706 790 3800",
    "sg:postcode":"30904",
    "sg:province":"GA",
    "wof:name":"Good Vocations Inc",
    "wof:placetype":"venue"
},
  "geometry": {"coordinates":[-82.012247,33.452609],"type":"Point"}
}