{
  "type": "Feature",
  "properties": {
    "iso:country":"US",
    "sg:address":"4646 Buford Hwy NE",
    "sg:city":"Atlanta",
    "sg:classifiers":[
        {
            "category":"Recreation",
            "type":"Entertainment"
        }
    ],
    "sg:phone":"+1 770 455 6510",
    "sg:postcode":"30341",
    "sg:province":"GA",
    "wof:name":"1 Billiards",
    "wof:placetype":"venue"
},
  "geometry": {"coordinates":[-84.293888,33.875392],"type":"Point"}
}