{
  "type": "Feature",
  "properties": {
    "addr:full":"140 Baxley Rd Pooler GA 31322",
    "addr:housenumber":"140",
    "addr:postcode":"31322",
    "addr:street":"Baxley Rd",
    "iso:country":"US",
    "sg:address":"140 Baxley Rd",
    "sg:city":"Pooler",
    "sg:classifiers":[
        {
            "category":"Personal",
            "subcategory":"Beauty Salon",
            "type":"Services"
        }
    ],
    "sg:phone":"+1 912 964 5837",
    "sg:postcode":"31322",
    "sg:province":"GA",
    "sg:website":"http://www.frankcooper.com",
    "wof:name":"Frank Cooper Inc",
    "wof:placetype":"venue"
},
  "geometry": {"coordinates":[-81.206548,32.084071],"type":"Point"}
}