{
  "type": "Feature",
  "properties": {
    "iso:country":"US",
    "sg:address":"7885 Hiram Acworth Hwy",
    "sg:city":"Dallas",
    "sg:classifiers":[
        {
            "category":"Building & Trades",
            "subcategory":"Plumbing",
            "type":"Services"
        }
    ],
    "sg:phone":"+1 770 966 7696",
    "sg:postcode":"30157",
    "sg:province":"GA",
    "sg:tags":[
        "contractor"
    ],
    "wof:name":"Rawlins Heat & AC Service",
    "wof:placetype":"venue"
},
  "geometry": {"coordinates":[-84.751355,34.002892],"type":"Point"}
}