{
  "type": "Feature",
  "properties": {
    "iso:country":"US",
    "sg:address":"4730 Hwy 9 N",
    "sg:city":"Alpharetta",
    "sg:classifiers":[
        {
            "category":"Building & Trades",
            "subcategory":"Construction",
            "type":"Services"
        }
    ],
    "sg:phone":"+1 770 569 5787",
    "sg:postcode":"30004",
    "sg:province":"GA",
    "sg:tags":[
        "special",
        "contractor"
    ],
    "wof:name":"A & D Enviromental Fabrics",
    "wof:placetype":"venue"
},
  "geometry": {"coordinates":[-84.230476,34.158181],"type":"Point"}
}