{
  "type": "Feature",
  "properties": {
    "iso:country":"US",
    "sg:address":"490 State Rte 109",
    "sg:city":"Meansville",
    "sg:classifiers":[
        {
            "category":"Health Services",
            "subcategory":"Clinic",
            "type":"Services"
        }
    ],
    "sg:phone":"+1 770 567 8266",
    "sg:postcode":"30256",
    "sg:province":"GA",
    "wof:name":"A P Health Care Recruiting",
    "wof:placetype":"venue"
},
  "geometry": {"coordinates":[-84.30598500000001,33.049265],"type":"Point"}
}