{
  "type": "Feature",
  "properties": {
    "addr:full":"2750 Welcome Hill Cir Dalton GA 30721",
    "addr:housenumber":"2750",
    "addr:postcode":"30721",
    "addr:street":"Welcome Hill Cir",
    "iso:country":"US",
    "sg:address":"2750 Welcome Hill Cir",
    "sg:city":"Dalton",
    "sg:classifiers":[
        {
            "category":"Home & Garden",
            "subcategory":"Garden Supply",
            "type":"Retail Goods"
        }
    ],
    "sg:phone":"+1 706 275 8871",
    "sg:postcode":"30721",
    "sg:province":"GA",
    "sg:tags":[
        "f"
    ],
    "wof:name":"Preferred Lawn & Landscaping",
    "wof:placetype":"venue"
},
  "geometry": {"coordinates":[-84.927887,34.769015],"type":"Point"}
}