{
  "type": "Feature",
  "properties": {
    "addr:full":"5307 Lealand Place Ln Lawrenceville GA 30044",
    "addr:postcode":"5307;30044",
    "addr:street":"Lealand Place Ln",
    "iso:country":"US",
    "sg:address":"5307 Lealand Place Ln",
    "sg:city":"Lawrenceville",
    "sg:classifiers":[
        {
            "category":"Professional",
            "type":"Services"
        }
    ],
    "sg:phone":"+1 770 381 7244",
    "sg:postcode":"30044",
    "sg:province":"GA",
    "wof:name":"All About You",
    "wof:placetype":"venue"
},
  "geometry": {"coordinates":[-84.09191,33.936966],"type":"Point"}
}