{
  "type": "Feature",
  "properties": {
    "addr:full":"728 Skyline Dr Mdsn Madison GA 30650",
    "addr:housenumber":"728",
    "addr:postcode":"30650",
    "addr:street":"Skyline Dr",
    "iso:country":"US",
    "sg:address":"728 Skyline Dr Mdsn",
    "sg:city":"Madison",
    "sg:classifiers":[
        {
            "category":"Food & Beverages",
            "subcategory":"Groceries & Convenience Stores",
            "type":"Retail Goods"
        }
    ],
    "sg:phone":"+1 404 525 1223",
    "sg:postcode":"30650",
    "sg:province":"GA",
    "wof:name":"Fred's Great-Valu",
    "wof:placetype":"venue"
},
  "geometry": {"coordinates":[-83.47421799999999,33.58611],"type":"Point"}
}