{
  "type": "Feature",
  "properties": {
    "addr:full":"6075 Barfield Road NE Atlanta GA 30328",
    "addr:housenumber":"6075",
    "addr:postcode":"30328",
    "addr:street":"Barfield Road Ne",
    "iso:country":"US",
    "sg:address":"6075 Barfield Road NE",
    "sg:city":"Atlanta",
    "sg:classifiers":[
        {
            "category":"Building & Trades",
            "subcategory":"Construction",
            "type":"Services"
        }
    ],
    "sg:phone":"+1 404 252 3142",
    "sg:postcode":"30328",
    "sg:province":"GA",
    "sg:tags":[
        "contractor"
    ],
    "wof:name":"Cambridge Builders",
    "wof:placetype":"venue"
},
  "geometry": {"coordinates":[-84.359848,33.92239],"type":"Point"}
}