{
  "type": "Feature",
  "properties": {
    "iso:country":"US",
    "sg:address":"4656A Rollins Rd",
    "sg:city":"Augusta",
    "sg:classifiers":[
        {
            "category":"Building & Trades",
            "subcategory":"Construction",
            "type":"Services"
        }
    ],
    "sg:phone":"+1 706 771 9412",
    "sg:postcode":"30906",
    "sg:province":"GA",
    "sg:tags":[
        "wallcoverings-installation",
        "wallpaper",
        "painting",
        "contractor"
    ],
    "wof:name":"A C M E Painting",
    "wof:placetype":"venue"
},
  "geometry": {"coordinates":[-81.966921,33.292199],"type":"Point"}
}