{
  "type": "Feature",
  "properties": {
    "addr:full":"1745 Corporate Dr Norcross GA 30093",
    "addr:housenumber":"1745",
    "addr:postcode":"30093",
    "addr:street":"Corporate Dr",
    "iso:country":"US",
    "sg:address":"1745 Corporate Dr",
    "sg:city":"Norcross",
    "sg:classifiers":[
        {
            "category":"Freight",
            "type":"Transportation"
        }
    ],
    "sg:phone":"+1 404 982 5082",
    "sg:postcode":"30093",
    "sg:province":"GA",
    "sg:tags":[
        "warehouse"
    ],
    "wof:name":"AT&T",
    "wof:placetype":"venue"
},
  "geometry": {"coordinates":[-84.148229,33.940204],"type":"Point"}
}