{
  "type": "Feature",
  "properties": {
    "iso:country":"US",
    "sg:address":"164 Washington Plz",
    "sg:city":"Washington",
    "sg:classifiers":[
        {
            "category":"Shopping",
            "subcategory":"Discount & Variety Stores",
            "type":"Retail Goods"
        },
        {
            "category":"Shopping",
            "subcategory":"Department Store",
            "type":"Retail Goods"
        }
    ],
    "sg:phone":"+1 706 678 7050",
    "sg:postcode":"30673",
    "sg:province":"GA",
    "sg:tags":[
        "shop"
    ],
    "wof:name":"Family Dollar Stores",
    "wof:placetype":"venue"
},
  "geometry": {"coordinates":[-82.71789800000001,33.727736],"type":"Point"}
}