{
  "type": "Feature",
  "properties": {
    "addr:full":"1058 Bramwell Ln Stone Mountain GA 30083",
    "addr:housenumber":"1058",
    "addr:postcode":"30083",
    "addr:street":"Bramwell Ln",
    "iso:country":"US",
    "sg:address":"1058 Bramwell Ln",
    "sg:city":"Stone Mountain",
    "sg:classifiers":[
        {
            "category":"Shopping",
            "subcategory":"Discount & Variety Stores",
            "type":"Retail Goods"
        }
    ],
    "sg:phone":"+1 404 292 7611",
    "sg:postcode":"30083",
    "sg:province":"GA",
    "sg:tags":[
        "merchandise",
        "general"
    ],
    "wof:name":"Resource International",
    "wof:placetype":"venue"
},
  "geometry": {"coordinates":[-84.210272,33.806762],"type":"Point"}
}