{
  "type": "Feature",
  "properties": {
    "iso:country":"US",
    "sg:address":"155 Market Ave",
    "sg:city":"Cordele",
    "sg:classifiers":[
        {
            "category":"Home & Garden",
            "subcategory":"Building Materials",
            "type":"Retail Goods"
        }
    ],
    "sg:phone":"+1 229 273 2132",
    "sg:postcode":"31015",
    "sg:province":"GA",
    "wof:name":"Concrete Company",
    "wof:placetype":"venue"
},
  "geometry": {"coordinates":[-83.795636,31.987107],"type":"Point"}
}