{
  "type": "Feature",
  "properties": {
    "iso:country":"US",
    "sg:address":"3590 Cherokee St NW",
    "sg:city":"Kennesaw",
    "sg:classifiers":[
        {
            "category":"Manufacturing",
            "subcategory":"Tools & Machinery",
            "type":"Manufacturing & Wholesale Goods"
        }
    ],
    "sg:phone":"+1 770 919 1913",
    "sg:postcode":"30144",
    "sg:province":"GA",
    "sg:tags":[
        "equipment",
        "system",
        "automation"
    ],
    "wof:name":"Industrial Apparatus Co",
    "wof:placetype":"venue"
},
  "geometry": {"coordinates":[-84.604123,34.040422],"type":"Point"}
}