{
  "type": "Feature",
  "properties": {
    "addr:full":"5303 Adams St NE Covington GA 30014",
    "addr:housenumber":"5303",
    "addr:postcode":"30014",
    "addr:street":"Adams St Ne",
    "iso:country":"US",
    "sg:address":"5303 Adams St NE",
    "sg:city":"Covington",
    "sg:classifiers":[
        {
            "category":"Health Services",
            "subcategory":"Doctor",
            "type":"Services"
        }
    ],
    "sg:phone":"+1 770 786 0077",
    "sg:postcode":"30014",
    "sg:province":"GA",
    "sg:tags":[
        "medical"
    ],
    "wof:name":"Mark C Hanson MD",
    "wof:placetype":"venue"
},
  "geometry": {"coordinates":[-83.84397300000001,33.601636],"type":"Point"}
}