{
  "type": "Feature",
  "properties": {
    "addr:full":"160 6th St NW Atlanta GA 30313",
    "addr:housenumber":"160",
    "addr:postcode":"30313",
    "addr:street":"6Th St Nw",
    "iso:country":"US",
    "sg:address":"160 6th St NW",
    "sg:city":"Atlanta",
    "sg:classifiers":[
        {
            "category":"Organizations",
            "subcategory":"Community Association",
            "type":"Services"
        }
    ],
    "sg:phone":"+1 404 817 7192",
    "sg:postcode":"30313",
    "sg:province":"GA",
    "sg:tags":[
        "sorority",
        "fraternity"
    ],
    "wof:name":"Phi Kappa Psi",
    "wof:placetype":"venue"
},
  "geometry": {"coordinates":[-84.391696,33.778064],"type":"Point"}
}