{
  "type": "Feature",
  "properties": {
    "iso:country":"US",
    "sg:address":"4336 Covington Hwy",
    "sg:city":"Decatur",
    "sg:classifiers":[
        {
            "category":"Insurance",
            "subcategory":"Insurance Agent",
            "type":"Services"
        }
    ],
    "sg:phone":"+1 404 286 4162",
    "sg:postcode":"30035",
    "sg:province":"GA",
    "wof:name":"Associated Benefits & Services",
    "wof:placetype":"venue"
},
  "geometry": {"coordinates":[-84.22909799999999,33.751236],"type":"Point"}
}