{
  "type": "Feature",
  "properties": {
    "addr:full":"459 Grayson Pkwy Grayson GA 30017",
    "addr:housenumber":"459",
    "addr:postcode":"30017",
    "addr:street":"Grayson Pkwy",
    "iso:country":"US",
    "sg:address":"459 Grayson Pkwy",
    "sg:city":"Grayson",
    "sg:classifiers":[
        {
            "category":"Professional",
            "subcategory":"Engineering",
            "type":"Services"
        }
    ],
    "sg:phone":"+1 770 985 8098",
    "sg:postcode":"30017",
    "sg:province":"GA",
    "sg:tags":[
        "engineer"
    ],
    "wof:name":"Thomason Engineering LLC",
    "wof:placetype":"venue"
},
  "geometry": {"coordinates":[-83.957379,33.89352],"type":"Point"}
}