{
  "type": "Feature",
  "properties": {
    "addr:full":"106 W Martin Luther King Jr Blvd Swainsboro GA 30401",
    "addr:housenumber":"106",
    "addr:postcode":"30401",
    "addr:street":"W Martin Luther King Jr Blvd",
    "iso:country":"US",
    "sg:address":"106 W Martin Luther King Jr Blvd",
    "sg:city":"Swainsboro",
    "sg:classifiers":[
        {
            "category":"Restaurant",
            "type":"Food & Drink"
        }
    ],
    "sg:phone":"+1 478 289 0012",
    "sg:postcode":"30401",
    "sg:province":"GA",
    "sg:tags":[
        "eating"
    ],
    "wof:name":"Coach's Kitchen",
    "wof:placetype":"venue"
},
  "geometry": {"coordinates":[-82.34119200000001,32.605033],"type":"Point"}
}