{
  "type": "Feature",
  "properties": {
    "iso:country":"US",
    "sg:address":"812 N Tennessee St",
    "sg:city":"Cartersville",
    "sg:classifiers":[
        {
            "category":"Home & Garden",
            "subcategory":"Household Appliances",
            "type":"Retail Goods"
        }
    ],
    "sg:phone":"+1 770 387 1408",
    "sg:postcode":"30120",
    "sg:province":"GA",
    "wof:name":"Garner's Used Appliances",
    "wof:placetype":"venue"
},
  "geometry": {"coordinates":[-84.794303,34.181599],"type":"Point"}
}