{
  "type": "Feature",
  "properties": {
    "iso:country":"US",
    "sg:address":"12390 Arnold Mill Rd",
    "sg:city":"Alpharetta",
    "sg:classifiers":[
        {
            "category":"Building & Trades",
            "subcategory":"Construction",
            "type":"Services"
        }
    ],
    "sg:phone":"+1 770 569 0910",
    "sg:postcode":"30004",
    "sg:province":"GA",
    "sg:tags":[
        "contractor"
    ],
    "wof:name":"Pre Engineered Builders",
    "wof:placetype":"venue"
},
  "geometry": {"coordinates":[-84.35841499999999,34.083792],"type":"Point"}
}