{
  "type": "Feature",
  "properties": {
    "iso:country":"US",
    "sg:address":"180 Brickleberry Ridge",
    "sg:city":"Athens",
    "sg:classifiers":[
        {
            "category":"Professional",
            "subcategory":"Business Services",
            "type":"Services"
        }
    ],
    "sg:phone":"+1 706 208 0353",
    "sg:postcode":"30605",
    "sg:province":"GA",
    "wof:name":"Altius Corp",
    "wof:placetype":"venue"
},
  "geometry": {"coordinates":[-83.312501,33.893482],"type":"Point"}
}