{
  "type": "Feature",
  "properties": {
    "addr:full":"10240 Jones Bridge Rd Alpharetta GA 30022",
    "addr:housenumber":"10240",
    "addr:postcode":"30022",
    "addr:street":"Jones Bridge Rd",
    "iso:country":"US",
    "sg:address":"10240 Jones Bridge Rd",
    "sg:city":"Alpharetta",
    "sg:classifiers":[
        {
            "category":"Social Services",
            "subcategory":"Child Care",
            "type":"Services"
        }
    ],
    "sg:phone":"+1 770 360 1375",
    "sg:postcode":"30022",
    "sg:province":"GA",
    "sg:tags":[
        "day"
    ],
    "sg:website":"www.brooksideacademy.com",
    "wof:name":"Brookside Academy",
    "wof:placetype":"venue"
},
  "geometry": {"coordinates":[-84.24398600000001,34.032488],"type":"Point"}
}