{
  "type": "Feature",
  "properties": {
    "addr:full":"169 New St Macon GA 31201",
    "addr:housenumber":"169",
    "addr:postcode":"31201",
    "addr:street":"New St",
    "iso:country":"US",
    "sg:address":"169 New St",
    "sg:city":"Macon",
    "sg:classifiers":[
        {
            "category":"Real Estate",
            "subcategory":"Real Estate Agent",
            "type":"Services"
        }
    ],
    "sg:phone":"+1 478 743 3395",
    "sg:postcode":"31201",
    "sg:province":"GA",
    "wof:name":"Prime Service Realtors",
    "wof:placetype":"venue"
},
  "geometry": {"coordinates":[-83.62973599999999,32.841368],"type":"Point"}
}