{
  "type": "Feature",
  "properties": {
    "iso:country":"US",
    "sg:address":"282 Hawk Hammock Rd",
    "sg:city":"Springfield",
    "sg:classifiers":[
        {
            "category":"Building & Trades",
            "subcategory":"Landscaping Services",
            "type":"Services"
        }
    ],
    "sg:phone":"+1 912 754 1762",
    "sg:postcode":"31329",
    "sg:province":"GA",
    "sg:tags":[
        "landscape"
    ],
    "wof:name":"Geralds Landscaping",
    "wof:placetype":"venue"
},
  "geometry": {"coordinates":[-81.308257,32.381313],"type":"Point"}
}