{
  "type": "Feature",
  "properties": {
    "iso:country":"US",
    "sg:address":"355 Fenbrook Way SW",
    "sg:city":"Marietta",
    "sg:classifiers":[
        {
            "category":"Real Estate",
            "subcategory":"Real Estate Agent",
            "type":"Services"
        }
    ],
    "sg:phone":"+1 770 426 8173",
    "sg:postcode":"30064",
    "sg:province":"GA",
    "wof:name":"Won By One Inc",
    "wof:placetype":"venue"
},
  "geometry": {"coordinates":[-84.665944,33.945474],"type":"Point"}
}