{
  "type": "Feature",
  "properties": {
    "iso:country":"US",
    "sg:address":"1358 Boone Ave",
    "sg:city":"Kingsland",
    "sg:classifiers":[
        {
            "category":"Restaurant",
            "type":"Food & Drink"
        }
    ],
    "sg:menulink":"http://www.allmenus.com/ga/kingsland/245307-new-hong-kong/menu/",
    "sg:phone":"+1 912 882 2220",
    "sg:postcode":"31548",
    "sg:province":"GA",
    "sg:tags":[
        "asian",
        "chinese"
    ],
    "wof:name":"New Hong Kong",
    "wof:placetype":"venue"
},
  "geometry": {"coordinates":[-81.663049,30.791453],"type":"Point"}
}