{
  "type": "Feature",
  "properties": {
    "iso:country":"US",
    "sg:address":"4514 Mill Place Ct",
    "sg:city":"Columbus",
    "sg:classifiers":[
        {
            "category":"Professional",
            "subcategory":"Management & Consulting",
            "type":"Services"
        }
    ],
    "sg:phone":"+1 706 689 5395",
    "sg:postcode":"31907",
    "sg:province":"GA",
    "sg:tags":[
        "property",
        "redevelop"
    ],
    "wof:name":"Platinum Properties Inc",
    "wof:placetype":"venue"
},
  "geometry": {"coordinates":[-84.911461,32.453833],"type":"Point"}
}