{
  "type": "Feature",
  "properties": {
    "iso:country":"US",
    "sg:address":"1209 E 59th St",
    "sg:city":"Savannah",
    "sg:classifiers":[
        {
            "category":"Building & Trades",
            "subcategory":"Plumbing",
            "type":"Services"
        }
    ],
    "sg:phone":"+1 912 352 9827",
    "sg:postcode":"31404",
    "sg:province":"GA",
    "sg:tags":[
        "plumbing",
        "contractor"
    ],
    "wof:name":"Henry Plumbing Co Inc",
    "wof:placetype":"venue"
},
  "geometry": {"coordinates":[-81.08775,32.034838],"type":"Point"}
}