{
  "type": "Feature",
  "properties": {
    "addr:full":"1413 Belfaire Trce Dacula GA 30019",
    "addr:housenumber":"1413",
    "addr:postcode":"ga 30019",
    "addr:street":"Belfaire Trce",
    "iso:country":"US",
    "sg:address":"1413 Belfaire Trce",
    "sg:city":"Dacula",
    "sg:classifiers":[
        {
            "category":"Professional",
            "subcategory":"Business Services",
            "type":"Services"
        }
    ],
    "sg:phone":"+1 770 513 4585",
    "sg:postcode":"30019",
    "sg:province":"GA",
    "wof:name":"Tonyas Interior Design",
    "wof:placetype":"venue"
},
  "geometry": {"coordinates":[-83.91596800000001,34.039335],"type":"Point"}
}