{
  "type": "Feature",
  "properties": {
    "iso:country":"US",
    "sg:address":"129 Centennial Dr",
    "sg:city":"Stockbridge",
    "sg:classifiers":[
        {
            "category":"Professional",
            "subcategory":"Business Services",
            "type":"Services"
        }
    ],
    "sg:phone":"+1 770 289 0345",
    "sg:postcode":"30281",
    "sg:province":"GA",
    "wof:name":"Centennial Enterprises",
    "wof:placetype":"venue"
},
  "geometry": {"coordinates":[-84.23293,33.611591],"type":"Point"}
}