{
  "type": "Feature",
  "properties": {
    "addr:full":"1025 Virginia Ave Atlanta GA 30354",
    "addr:housenumber":"1025",
    "addr:postcode":"30354",
    "addr:street":"Virginia Ave",
    "iso:country":"US",
    "sg:address":"1025 Virginia Ave",
    "sg:city":"Atlanta",
    "sg:classifiers":[
        {
            "category":"Autos & Motor Vehicles",
            "subcategory":"Automobile Sales",
            "type":"Retail Goods"
        }
    ],
    "sg:phone":"+1 770 621 2293",
    "sg:postcode":"30354",
    "sg:province":"GA",
    "sg:tags":[
        "business"
    ],
    "wof:name":"Car Solutions",
    "wof:placetype":"venue"
},
  "geometry": {"coordinates":[-84.425394,33.659012],"type":"Point"}
}