{
  "type": "Feature",
  "properties": {
    "iso:country":"US",
    "sg:address":"28 Hartwell Rd",
    "sg:city":"Lavonia",
    "sg:classifiers":[
        {
            "category":"Education",
            "subcategory":"Library",
            "type":"Public Place"
        }
    ],
    "sg:phone":"+1 706 356 4307",
    "sg:postcode":"30553",
    "sg:province":"GA",
    "wof:name":"Lavonia-Carnegie Library",
    "wof:placetype":"venue"
},
  "geometry": {"coordinates":[-83.102671,34.434697],"type":"Point"}
}