{
  "type": "Feature",
  "properties": {
    "iso:country":"US",
    "sg:address":"2997 Cumberland Blvd SE",
    "sg:city":"Atlanta",
    "sg:classifiers":[
        {
            "category":"Personal",
            "subcategory":"Beauty Salon",
            "type":"Services"
        }
    ],
    "sg:phone":"+1 770 432 9966",
    "sg:postcode":"30339",
    "sg:province":"GA",
    "sg:tags":[
        "shop",
        "manicuring"
    ],
    "wof:name":"Nail Fervour",
    "wof:placetype":"venue"
},
  "geometry": {"coordinates":[-84.461251,33.877401],"type":"Point"}
}