{
  "type": "Feature",
  "properties": {
    "iso:country":"US",
    "sg:address":"4040 Houston Ave",
    "sg:city":"Macon",
    "sg:classifiers":[
        {
            "category":"Organizations",
            "subcategory":"Religious Organization",
            "type":"Services"
        }
    ],
    "sg:phone":"+1 478 781 2424",
    "sg:postcode":"31206",
    "sg:province":"GA",
    "sg:tags":[
        "church"
    ],
    "wof:name":"St James Church Of God-Christ",
    "wof:placetype":"venue"
},
  "geometry": {"coordinates":[-83.654645,32.793915],"type":"Point"}
}