{
  "type": "Feature",
  "properties": {
    "iso:country":"US",
    "sg:address":"4704 Post Rd",
    "sg:city":"Winston",
    "sg:classifiers":[
        {
            "category":"Retail",
            "subcategory":"Repair Shop",
            "type":"Services"
        }
    ],
    "sg:phone":"+1 770 942 5591",
    "sg:postcode":"30187",
    "sg:province":"GA",
    "sg:tags":[
        "welding"
    ],
    "wof:name":"K & K Iron Works",
    "wof:placetype":"venue"
},
  "geometry": {"coordinates":[-84.86352599999999,33.677075],"type":"Point"}
}