{
  "type": "Feature",
  "properties": {
    "iso:country":"US",
    "sg:address":"5766 Westwind Ct NW",
    "sg:city":"Kennesaw",
    "sg:classifiers":[
        {
            "category":"Professional",
            "subcategory":"Secretarial Services",
            "type":"Services"
        }
    ],
    "sg:phone":"+1 770 528 9052",
    "sg:postcode":"30152",
    "sg:province":"GA",
    "sg:tags":[
        "reporting"
    ],
    "wof:name":"West Cobb Secretarial Service",
    "wof:placetype":"venue"
},
  "geometry": {"coordinates":[-84.719182,33.965596],"type":"Point"}
}