{
  "type": "Feature",
  "properties": {
    "iso:country":"US",
    "sg:address":"1994 Sourwood Dr",
    "sg:city":"Dalton",
    "sg:classifiers":[
        {
            "category":"Professional",
            "subcategory":"Business Services",
            "type":"Services"
        }
    ],
    "sg:phone":"+1 706 278 2748",
    "sg:postcode":"30720",
    "sg:province":"GA",
    "wof:name":"LKM Associates Inc",
    "wof:placetype":"venue"
},
  "geometry": {"coordinates":[-85.008456,34.726201],"type":"Point"}
}