{
  "type": "Feature",
  "properties": {
    "addr:full":"6724 Waters Ave Savannah GA 31406",
    "addr:housenumber":"6724",
    "addr:postcode":"31406",
    "addr:street":"Waters Ave",
    "iso:country":"US",
    "sg:address":"6724 Waters Ave",
    "sg:city":"Savannah",
    "sg:classifiers":[
        {
            "category":"Restaurant",
            "type":"Food & Drink"
        }
    ],
    "sg:menulink":"http://www.allmenus.com/ga/savannah/31016-the-dawg-house-grill/menu/",
    "sg:phone":"+1 912 692 0824",
    "sg:postcode":"31406",
    "sg:province":"GA",
    "sg:tags":[
        "american"
    ],
    "wof:name":"The Dawg House Grill",
    "wof:placetype":"venue"
},
  "geometry": {"coordinates":[-81.100041,32.007974],"type":"Point"}
}