{
  "type": "Feature",
  "properties": {
    "addr:full":"520 Cameron Manor Way NW Atlanta GA 30328",
    "addr:housenumber":"520",
    "addr:postcode":"30328",
    "addr:street":"Cameron Manor Way Nw",
    "iso:country":"US",
    "sg:address":"520 Cameron Manor Way NW",
    "sg:city":"Atlanta",
    "sg:classifiers":[
        {
            "category":"Health Services",
            "subcategory":"Doctor",
            "type":"Services"
        }
    ],
    "sg:phone":"+1 404 843 8010",
    "sg:postcode":"30328",
    "sg:province":"GA",
    "sg:tags":[
        "physician",
        "family",
        "medical",
        "practice",
        "surgeons",
        "medicine"
    ],
    "wof:name":"Gordon Robert D Md",
    "wof:placetype":"venue"
},
  "geometry": {"coordinates":[-84.387229,33.918222],"type":"Point"}
}