{
  "type": "Feature",
  "properties": {
    "addr:full":"232 E Broughton St Savannah GA 31401",
    "addr:housenumber":"232",
    "addr:postcode":"31401",
    "addr:street":"E Broughton St",
    "iso:country":"US",
    "sg:address":"232 E Broughton St",
    "sg:city":"Savannah",
    "sg:classifiers":[
        {
            "category":"Health Services",
            "subcategory":"Clinic",
            "type":"Services"
        }
    ],
    "sg:phone":"+1 912 231 9956",
    "sg:postcode":"31401",
    "sg:province":"GA",
    "sg:tags":[
        "medical"
    ],
    "wof:name":"Memorial Health",
    "wof:placetype":"venue"
},
  "geometry": {"coordinates":[-81.08932299999999,32.078252],"type":"Point"}
}