{
  "type": "Feature",
  "properties": {
    "iso:country":"US",
    "sg:address":"1730 Evans Dr SW",
    "sg:city":"Atlanta",
    "sg:classifiers":[
        {
            "category":"Personal",
            "type":"Services"
        }
    ],
    "sg:phone":"+1 404 755 1809",
    "sg:postcode":"30310",
    "sg:province":"GA",
    "wof:name":"Absolute Thrpeutic Massage Ctr",
    "wof:placetype":"venue"
},
  "geometry": {"coordinates":[-84.423125,33.706969],"type":"Point"}
}