{
  "type": "Feature",
  "properties": {
    "addr:full":"1010 Sampler Way Atlanta GA 30344",
    "addr:housenumber":"1010",
    "addr:postcode":"30344",
    "addr:street":"Sampler Way",
    "iso:country":"US",
    "sg:address":"1010 Sampler Way",
    "sg:city":"Atlanta",
    "sg:classifiers":[
        {
            "category":"Retail",
            "subcategory":"Auto Repair",
            "type":"Services"
        }
    ],
    "sg:phone":"+1 678 704 0700",
    "sg:postcode":"30344",
    "sg:province":"GA",
    "sg:tags":[
        "body",
        "painting",
        "repairing",
        "automobile"
    ],
    "wof:name":"Affordable Auto",
    "wof:placetype":"venue"
},
  "geometry": {"coordinates":[-84.421905,33.695521],"type":"Point"}
}