{
  "type": "Feature",
  "properties": {
    "addr:full":"2665 Sugarloaf Pkwy Lawrenceville GA 30045",
    "addr:housenumber":"2665",
    "addr:postcode":"30045",
    "addr:street":"Sugarloaf Pkwy",
    "iso:country":"US",
    "sg:address":"2665 Sugarloaf Pkwy",
    "sg:city":"Lawrenceville",
    "sg:classifiers":[
        {
            "category":"Building & Trades",
            "subcategory":"Landscaping Services",
            "type":"Services"
        }
    ],
    "sg:phone":"+1 678 793 7907",
    "sg:postcode":"30045",
    "sg:province":"GA",
    "sg:tags":[
        "gardener"
    ],
    "wof:name":"Professional Ground Cover",
    "wof:placetype":"venue"
},
  "geometry": {"coordinates":[-83.997184,33.916326],"type":"Point"}
}