{
  "type": "Feature",
  "properties": {
    "addr:full":"561 Thornton Rd Ste C Lithia Springs GA 30122",
    "addr:housenumber":"561",
    "addr:postcode":"30122",
    "addr:street":"Thornton Rd Ste C",
    "iso:country":"US",
    "sg:address":"561 Thornton Rd Ste C",
    "sg:city":"Lithia Springs",
    "sg:classifiers":[
        {
            "category":"Building & Trades",
            "subcategory":"Pest Control",
            "type":"Services"
        }
    ],
    "sg:phone":"+1 770 732 0300",
    "sg:postcode":"30122",
    "sg:province":"GA",
    "sg:website":"www.arrowexterminators.com",
    "wof:name":"Arrow Exterminators Inc",
    "wof:placetype":"venue"
},
  "geometry": {"coordinates":[-84.62640399999999,33.790501],"type":"Point"}
}