{
  "type": "Feature",
  "properties": {
    "iso:country":"US",
    "sg:address":"4891 Roosevelt Hwy",
    "sg:city":"Atlanta",
    "sg:classifiers":[
        {
            "category":"Restaurant",
            "type":"Food & Drink"
        }
    ],
    "sg:phone":"+1 770 306 9663",
    "sg:postcode":"30349",
    "sg:province":"GA",
    "sg:tags":[
        "out"
    ],
    "wof:name":"Fish & More",
    "wof:placetype":"venue"
},
  "geometry": {"coordinates":[-84.54794,33.597861],"type":"Point"}
}