{
  "type": "Feature",
  "properties": {
    "iso:country":"US",
    "sg:address":"235 Mackey Rd",
    "sg:city":"Mc Donough",
    "sg:classifiers":[
        {
            "category":"Building & Trades",
            "subcategory":"Plumbing",
            "type":"Services"
        }
    ],
    "sg:phone":"+1 770 954 0730",
    "sg:postcode":"30252",
    "sg:province":"GA",
    "sg:tags":[
        "contractor"
    ],
    "wof:name":"Hays Htg & AC",
    "wof:placetype":"venue"
},
  "geometry": {"coordinates":[-84.009326,33.429207],"type":"Point"}
}