{
  "type": "Feature",
  "properties": {
    "iso:country":"US",
    "sg:address":"3010 Robinson Rd",
    "sg:city":"Moody Afb",
    "sg:classifiers":[
        {
            "category":"Education",
            "subcategory":"School",
            "type":"Public Place"
        }
    ],
    "sg:phone":"+1 229 244 7323",
    "sg:postcode":"31699",
    "sg:province":"GA",
    "sg:tags":[
        "military",
        "college"
    ],
    "wof:name":"Georgia Military College",
    "wof:placetype":"venue"
},
  "geometry": {"coordinates":[-83.20226599999999,30.979317],"type":"Point"}
}