{
  "type": "Feature",
  "properties": {
    "addr:full":"1362 Washington Ave Atlanta GA 30344",
    "addr:housenumber":"1362",
    "addr:postcode":"30344",
    "addr:street":"Washington Ave",
    "iso:country":"US",
    "sg:address":"1362 Washington Ave",
    "sg:city":"Atlanta",
    "sg:classifiers":[
        {
            "category":"Organizations",
            "subcategory":"Religious Organization",
            "type":"Services"
        }
    ],
    "sg:phone":"+1 404 559 6116",
    "sg:postcode":"30344",
    "sg:province":"GA",
    "wof:name":"Prophetic World Ministries",
    "wof:placetype":"venue"
},
  "geometry": {"coordinates":[-84.42930800000001,33.675777],"type":"Point"}
}