{
  "type": "Feature",
  "properties": {
    "iso:country":"US",
    "sg:address":"5210 Island Dr",
    "sg:city":"Stone Mountain",
    "sg:classifiers":[
        {
            "category":"Professional",
            "subcategory":"Management & Consulting",
            "type":"Services"
        }
    ],
    "sg:phone":"+1 770 469 7075",
    "sg:postcode":"30087",
    "sg:province":"GA",
    "wof:name":"Ross Eleanor M & Assoc Inc",
    "wof:placetype":"venue"
},
  "geometry": {"coordinates":[-84.089476,33.794786],"type":"Point"}
}