{
  "type": "Feature",
  "properties": {
    "addr:full":"5730 Sugar Crossing Dr Buford GA 30518",
    "addr:housenumber":"5730",
    "addr:postcode":"30518",
    "addr:street":"Sugar Crossing Dr",
    "iso:country":"US",
    "sg:address":"5730 Sugar Crossing Dr",
    "sg:city":"Buford",
    "sg:classifiers":[
        {
            "category":"Professional",
            "type":"Services"
        }
    ],
    "sg:phone":"+1 770 614 8750",
    "sg:postcode":"30518",
    "sg:province":"GA",
    "wof:name":"A-1 Amerihome Exteriors",
    "wof:placetype":"venue"
},
  "geometry": {"coordinates":[-84.05420700000001,34.121395],"type":"Point"}
}