{
  "type": "Feature",
  "properties": {
    "iso:country":"US",
    "sg:address":"25 Enterprise Blvd SW",
    "sg:city":"Atlanta",
    "sg:classifiers":[
        {
            "category":"Food & Beverages",
            "subcategory":"Candy",
            "type":"Retail Goods"
        }
    ],
    "sg:phone":"+1 404 691 1211",
    "sg:postcode":"30336",
    "sg:province":"GA",
    "sg:tags":[
        "store"
    ],
    "sg:website":"www.classicconfections.com",
    "wof:name":"Classic Confections Inc",
    "wof:placetype":"venue"
},
  "geometry": {"coordinates":[-84.55064,33.75461],"type":"Point"}
}