{
  "type": "Feature",
  "properties": {
    "iso:country":"US",
    "sg:address":"2459 Roosevelt Hwy",
    "sg:city":"College Park",
    "sg:classifiers":[
        {
            "category":"Shopping",
            "type":"Retail Goods"
        }
    ],
    "sg:phone":"+1 404 768 5636",
    "sg:postcode":"30337",
    "sg:province":"GA",
    "sg:tags":[
        "incense"
    ],
    "wof:name":"Modibo's All Natural",
    "wof:placetype":"venue"
},
  "geometry": {"coordinates":[-84.47131299999999,33.629628],"type":"Point"}
}