{
  "type": "Feature",
  "properties": {
    "iso:country":"US",
    "sg:address":"1009 E Rogers St",
    "sg:city":"Valdosta",
    "sg:classifiers":[
        {
            "category":"Social Services",
            "subcategory":"Child Care",
            "type":"Services"
        }
    ],
    "sg:phone":"+1 229 249 9999",
    "sg:postcode":"31601",
    "sg:province":"GA",
    "wof:name":"Vision Hope Child Care Dev Ctr",
    "wof:placetype":"venue"
},
  "geometry": {"coordinates":[-83.264522,30.837696],"type":"Point"}
}