{
  "type": "Feature",
  "properties": {
    "iso:country":"US",
    "sg:address":"285 Brackenwood Cir NE",
    "sg:city":"Atlanta",
    "sg:classifiers":[
        {
            "category":"Real Estate",
            "subcategory":"Architect",
            "type":"Services"
        }
    ],
    "sg:phone":"+1 770 698 8026",
    "sg:postcode":"30328",
    "sg:province":"GA",
    "sg:tags":[
        "design",
        "architectural"
    ],
    "wof:name":"Pentastyle Inc",
    "wof:placetype":"venue"
},
  "geometry": {"coordinates":[-84.363867,33.948299],"type":"Point"}
}