{
  "type": "Feature",
  "properties": {
    "addr:full":"55 Jacoway St Trenton GA 30752",
    "addr:housenumber":"55",
    "addr:postcode":"30752",
    "addr:street":"Jacoway St",
    "iso:country":"US",
    "sg:address":"55 Jacoway St",
    "sg:city":"Trenton",
    "sg:classifiers":[
        {
            "category":"Manufacturing",
            "subcategory":"Rubber & Plastics",
            "type":"Manufacturing & Wholesale Goods"
        },
        {
            "category":"Autos & Motor Vehicles",
            "subcategory":"Auto Supplies",
            "type":"Retail Goods"
        },
        {
            "category":"Retail",
            "subcategory":"Auto Repair",
            "type":"Services"
        }
    ],
    "sg:phone":"+1 706 657 2147",
    "sg:postcode":"30752",
    "sg:province":"GA",
    "sg:tags":[
        "recap",
        "retread",
        "tires-wholesale",
        "tire",
        "manufacturer"
    ],
    "sg:website":"http://www.coopertire.com/html/",
    "wof:name":"Dade Tire",
    "wof:placetype":"venue"
},
  "geometry": {"coordinates":[-85.504649,34.87958],"type":"Point"}
}