{
  "type": "Feature",
  "properties": {
    "addr:full":"565 Orchard Ct SE Atlanta GA 30312",
    "addr:housenumber":"565",
    "addr:postcode":"30312",
    "addr:street":"Orchard Ct Se",
    "iso:country":"US",
    "sg:address":"565 Orchard Ct SE",
    "sg:city":"Atlanta",
    "sg:classifiers":[
        {
            "category":"Real Estate",
            "subcategory":"Real Estate Services",
            "type":"Services"
        },
        {
            "category":"Real Estate",
            "subcategory":"Real Estate Agent",
            "type":"Services"
        }
    ],
    "sg:phone":"+1 404 289 2466",
    "sg:postcode":"30312",
    "sg:province":"GA",
    "sg:tags":[
        "buyer",
        "broker"
    ],
    "wof:name":"Chase Mgmt. & Consulting",
    "wof:placetype":"venue"
},
  "geometry": {"coordinates":[-84.38328199999999,33.738807],"type":"Point"}
}