{
  "type": "Feature",
  "properties": {
    "addr:full":"4717 N Henry Blvd Stockbridge GA 30281",
    "addr:housenumber":"4717",
    "addr:postcode":"30281",
    "addr:street":"N Henry Blvd",
    "iso:country":"US",
    "sg:address":"4717 N Henry Blvd",
    "sg:city":"Stockbridge",
    "sg:classifiers":[
        {
            "category":"Sports & Exercise",
            "subcategory":"Gym",
            "type":"Entertainment"
        }
    ],
    "sg:phone":"+1 770 507 1480",
    "sg:postcode":"30281",
    "sg:province":"GA",
    "sg:tags":[
        "club",
        "health",
        "studio",
        "gymnasium"
    ],
    "wof:name":"Body Garage",
    "wof:placetype":"venue"
},
  "geometry": {"coordinates":[-84.233834,33.54418],"type":"Point"}
}