{
  "type": "Feature",
  "properties": {
    "addr:full":"4062 Liska Cir Valdosta GA 31605",
    "addr:housenumber":"4062",
    "addr:postcode":"31605",
    "addr:street":"Liska Cir",
    "iso:country":"US",
    "sg:address":"4062 Liska Cir",
    "sg:city":"Valdosta",
    "sg:classifiers":[
        {
            "category":"Professional",
            "subcategory":"Accounting & Tax Preparation",
            "type":"Services"
        }
    ],
    "sg:phone":"+1 229 244 2142",
    "sg:postcode":"31605",
    "sg:province":"GA",
    "sg:tags":[
        "public",
        "accountants-certified"
    ],
    "wof:name":"Ted Gaskins",
    "wof:placetype":"venue"
},
  "geometry": {"coordinates":[-83.260323,30.938067],"type":"Point"}
}