{
  "type": "Feature",
  "properties": {
    "addr:full":"56 Overlook Ct Dawsonville GA 30534",
    "addr:housenumber":"56",
    "addr:postcode":"30534",
    "addr:street":"Overlook Ct",
    "iso:country":"US",
    "sg:address":"56 Overlook Ct",
    "sg:city":"Dawsonville",
    "sg:classifiers":[
        {
            "category":"Professional",
            "subcategory":"Management & Consulting",
            "type":"Services"
        }
    ],
    "sg:phone":"+1 706 216 1886",
    "sg:postcode":"30534",
    "sg:province":"GA",
    "wof:name":"D & M Management Corporation",
    "wof:placetype":"venue"
},
  "geometry": {"coordinates":[-83.993061,34.363283],"type":"Point"}
}