{
  "type": "Feature",
  "properties": {
    "addr:full":"211 Peachtree St SW Atlanta GA 30303",
    "addr:housenumber":"211",
    "addr:postcode":"30303",
    "addr:street":"Peachtree St Sw",
    "iso:country":"US",
    "sg:address":"211 Peachtree St SW",
    "sg:city":"Atlanta",
    "sg:classifiers":[
        {
            "category":"Retail",
            "subcategory":"Repair Shop",
            "type":"Services"
        }
    ],
    "sg:phone":"+1 404 352 3933",
    "sg:postcode":"30303",
    "sg:province":"GA",
    "sg:tags":[
        "waste",
        "management"
    ],
    "wof:name":"Junk Free America Inc",
    "wof:placetype":"venue"
},
  "geometry": {"coordinates":[-84.39389199999999,33.749846],"type":"Point"}
}