{
  "type": "Feature",
  "properties": {
    "addr:full":"1442 Hydaborg Ln Norcross GA 30093",
    "addr:housenumber":"1442",
    "addr:postcode":"30093",
    "addr:street":"Hydaborg Ln",
    "iso:country":"US",
    "sg:address":"1442 Hydaborg Ln",
    "sg:city":"Norcross",
    "sg:classifiers":[
        {
            "category":"Building & Trades",
            "subcategory":"Landscaping Services",
            "type":"Services"
        }
    ],
    "sg:phone":"+1 770 279 7470",
    "sg:postcode":"30093",
    "sg:province":"GA",
    "sg:tags":[
        "landscape",
        "contractor"
    ],
    "wof:name":"Master Mowers",
    "wof:placetype":"venue"
},
  "geometry": {"coordinates":[-84.17198999999999,33.914908],"type":"Point"}
}