{
  "type": "Feature",
  "properties": {
    "addr:full":"212 Bethesda Church Rd Lawrenceville GA 30044",
    "addr:housenumber":"212",
    "addr:postcode":"30044",
    "addr:street":"Bethesda Church Rd",
    "iso:country":"US",
    "sg:address":"212 Bethesda Church Rd",
    "sg:city":"Lawrenceville",
    "sg:classifiers":[
        {
            "category":"Organizations",
            "subcategory":"Religious Organization",
            "type":"Services"
        }
    ],
    "sg:phone":"+1 770 381 7700",
    "sg:postcode":"30044",
    "sg:province":"GA",
    "sg:tags":[
        "church"
    ],
    "wof:name":"Belgian Evangelical Mission",
    "wof:placetype":"venue"
},
  "geometry": {"coordinates":[-84.08454999999999,33.914607],"type":"Point"}
}