{
  "type": "Feature",
  "properties": {
    "iso:country":"US",
    "sg:address":"24 E Robert Toombs Ave",
    "sg:city":"Washington",
    "sg:classifiers":[
        {
            "category":"Utilities",
            "subcategory":"Mobile Phone",
            "type":"Services"
        }
    ],
    "sg:phone":"+1 706 678 7011",
    "sg:postcode":"30673",
    "sg:province":"GA",
    "sg:tags":[
        "telephone",
        "cellular"
    ],
    "wof:name":"L & M Connection",
    "wof:placetype":"venue"
},
  "geometry": {"coordinates":[-82.737228,33.736686],"type":"Point"}
}