{
  "type": "Feature",
  "properties": {
    "iso:country":"US",
    "sg:address":"278 Triborough Hollow Rd",
    "sg:city":"Lawrenceville",
    "sg:classifiers":[
        {
            "category":"Professional",
            "subcategory":"Business Services",
            "type":"Services"
        }
    ],
    "sg:phone":"+1 770 736 6698",
    "sg:postcode":"30044",
    "sg:province":"GA",
    "wof:name":"Harmony Grove Academy",
    "wof:placetype":"venue"
},
  "geometry": {"coordinates":[-84.053054,33.912336],"type":"Point"}
}