{
  "type": "Feature",
  "properties": {
    "iso:country":"US",
    "sg:address":"1100 E Walnut Ave",
    "sg:city":"Dalton",
    "sg:classifiers":[
        {
            "category":"Health Services",
            "subcategory":"Optometrist",
            "type":"Services"
        }
    ],
    "sg:phone":"+1 706 278 6599",
    "sg:postcode":"30721",
    "sg:province":"GA",
    "wof:name":"Braun Eyecare Ctr",
    "wof:placetype":"venue"
},
  "geometry": {"coordinates":[-84.94752699999999,34.761033],"type":"Point"}
}