{
  "type": "Feature",
  "properties": {
    "addr:full":"1421 Luke Rd Augusta GA 30909",
    "addr:housenumber":"1421",
    "addr:postcode":"30909",
    "addr:street":"Luke Rd",
    "iso:country":"US",
    "sg:address":"1421 Luke Rd",
    "sg:city":"Augusta",
    "sg:classifiers":[
        {
            "category":"Organizations",
            "subcategory":"Religious Organization",
            "type":"Services"
        }
    ],
    "sg:phone":"+1 706 860 3864",
    "sg:postcode":"30909",
    "sg:province":"GA",
    "sg:tags":[
        "church"
    ],
    "wof:name":"Hindu Temple Society",
    "wof:placetype":"venue"
},
  "geometry": {"coordinates":[-82.118236,33.469071],"type":"Point"}
}