{
  "type": "Feature",
  "properties": {
    "iso:country":"US",
    "sg:address":"642 Puckett Dr",
    "sg:city":"Mableton",
    "sg:classifiers":[
        {
            "category":"Building & Trades",
            "subcategory":"Construction",
            "type":"Services"
        }
    ],
    "sg:phone":"+1 770 948 0933",
    "sg:postcode":"30126",
    "sg:province":"GA",
    "sg:tags":[
        "contractor"
    ],
    "wof:name":"Shirah Contracting Co Inc",
    "wof:placetype":"venue"
},
  "geometry": {"coordinates":[-84.57409699999999,33.8172],"type":"Point"}
}