{
  "type": "Feature",
  "properties": {
    "addr:full":"1833 Empress Ct Augusta GA 30906",
    "addr:housenumber":"1833",
    "addr:postcode":"30906",
    "addr:street":"Empress Ct",
    "iso:country":"US",
    "sg:address":"1833 Empress Ct",
    "sg:city":"Augusta",
    "sg:classifiers":[
        {
            "category":"Personal",
            "type":"Services"
        }
    ],
    "sg:phone":"+1 706 771 5305",
    "sg:postcode":"30906",
    "sg:province":"GA",
    "sg:tags":[
        "miscellaneous"
    ],
    "wof:name":"A 1 Belinda Winfrey Personal",
    "wof:placetype":"venue"
},
  "geometry": {"coordinates":[-82.019188,33.399623],"type":"Point"}
}