{
  "type": "Feature",
  "properties": {
    "addr:full":"3231 Cypress Mill Rd Brunswick GA 31525",
    "addr:housenumber":"3231",
    "addr:postcode":"31525",
    "addr:street":"Cypress Mill Rd",
    "iso:country":"US",
    "sg:address":"3231 Cypress Mill Rd",
    "sg:city":"Brunswick",
    "sg:classifiers":[
        {
            "category":"Building & Trades",
            "subcategory":"Pest Control",
            "type":"Services"
        }
    ],
    "sg:phone":"+1 912 265 9700",
    "sg:postcode":"31525",
    "sg:province":"GA",
    "wof:name":"Peachtree Pest Control Co Inc",
    "wof:placetype":"venue"
},
  "geometry": {"coordinates":[-81.476192,31.193304],"type":"Point"}
}