{
  "type": "Feature",
  "properties": {
    "addr:full":"2312 Peachford Road Atlanta GA 30338",
    "addr:housenumber":"2312",
    "addr:postcode":"30338",
    "addr:street":"Peachford Road",
    "iso:country":"US",
    "sg:address":"2312 Peachford Road",
    "sg:city":"Atlanta",
    "sg:classifiers":[
        {
            "category":"Professional",
            "subcategory":"Lawyer & Legal Services",
            "type":"Services"
        }
    ],
    "sg:phone":"+1 770 936 8888",
    "sg:postcode":"30338",
    "sg:province":"GA",
    "sg:tags":[
        "litigation"
    ],
    "wof:name":"Gates and Associates",
    "wof:placetype":"venue"
},
  "geometry": {"coordinates":[-84.297754,33.92761],"type":"Point"}
}