{
  "type": "Feature",
  "properties": {
    "addr:full":"1860 Spring Rd SE Smyrna GA 30080",
    "addr:housenumber":"1860",
    "addr:postcode":"30080",
    "addr:street":"Spring Rd Se",
    "iso:country":"US",
    "sg:address":"1860 Spring Rd SE",
    "sg:city":"Smyrna",
    "sg:classifiers":[
        {
            "category":"Home & Garden",
            "subcategory":"Furniture",
            "type":"Retail Goods"
        }
    ],
    "sg:phone":"+1 770 432 6162",
    "sg:postcode":"30080",
    "sg:province":"GA",
    "wof:name":"Precision Sleep Diagnostics",
    "wof:placetype":"venue"
},
  "geometry": {"coordinates":[-84.49957999999999,33.883601],"type":"Point"}
}