{
  "type": "Feature",
  "properties": {
    "iso:country":"US",
    "sg:address":"375 Club Dr",
    "sg:city":"Athens",
    "sg:classifiers":[
        {
            "category":"Retail",
            "subcategory":"Laundry & Dry Cleaning",
            "type":"Services"
        }
    ],
    "sg:phone":"+1 706 543 8323",
    "sg:postcode":"30607",
    "sg:province":"GA",
    "sg:tags":[
        "cleaner",
        "rug",
        "carpet"
    ],
    "wof:name":"Above And Beyond Carpet Cleani",
    "wof:placetype":"venue"
},
  "geometry": {"coordinates":[-83.411727,33.989389],"type":"Point"}
}