{
  "type": "Feature",
  "properties": {
    "addr:full":"404 Palace St Griffin GA 30223",
    "addr:housenumber":"404",
    "addr:postcode":"30223",
    "addr:street":"Palace St",
    "iso:country":"US",
    "sg:address":"404 Palace St",
    "sg:city":"Griffin",
    "sg:classifiers":[
        {
            "category":"Personal",
            "subcategory":"Beauty Salon",
            "type":"Services"
        }
    ],
    "sg:phone":"+1 770 228 9972",
    "sg:postcode":"30223",
    "sg:province":"GA",
    "wof:name":"Kerra & Tim's Beauty",
    "wof:placetype":"venue"
},
  "geometry": {"coordinates":[-84.268891,33.254337],"type":"Point"}
}