{
  "type": "Feature",
  "properties": {
    "addr:full":"2914 Cherokee St NW Kennesaw GA 30144",
    "addr:housenumber":"2914",
    "addr:postcode":"30144",
    "addr:street":"Cherokee St Nw",
    "iso:country":"US",
    "sg:address":"2914 Cherokee St NW",
    "sg:city":"Kennesaw",
    "sg:classifiers":[
        {
            "category":"Professional",
            "subcategory":"Management & Consulting",
            "type":"Services"
        }
    ],
    "sg:phone":"+1 678 239 3900",
    "sg:postcode":"30144",
    "sg:province":"GA",
    "sg:tags":[
        "fuel"
    ],
    "wof:name":"Management Recruiters",
    "wof:placetype":"venue"
},
  "geometry": {"coordinates":[-84.61275000000001,34.023837],"type":"Point"}
}