{
  "type": "Feature",
  "properties": {
    "addr:full":"5103 Jimmy Carter Blvd Norcross GA 30093",
    "addr:housenumber":"5103",
    "addr:postcode":"30093",
    "addr:street":"Jimmy Carter Blvd",
    "iso:country":"US",
    "sg:address":"5103 Jimmy Carter Blvd",
    "sg:city":"Norcross",
    "sg:classifiers":[
        {
            "category":"Retail",
            "subcategory":"Auto Repair",
            "type":"Services"
        }
    ],
    "sg:phone":"+1 770 448 9667",
    "sg:postcode":"30093",
    "sg:province":"GA",
    "sg:website":"www.midas.com",
    "wof:name":"Midas Auto Service",
    "wof:placetype":"venue"
},
  "geometry": {"coordinates":[-84.200543,33.898031],"type":"Point"}
}