{
  "type": "Feature",
  "properties": {
    "addr:full":"320 Forest Hill Rd Macon GA 31210",
    "addr:housenumber":"320",
    "addr:postcode":"31210",
    "addr:street":"Forest Hill Rd",
    "iso:country":"US",
    "sg:address":"320 Forest Hill Rd",
    "sg:city":"Macon",
    "sg:classifiers":[
        {
            "category":"Health Services",
            "subcategory":"Doctor",
            "type":"Services"
        }
    ],
    "sg:phone":"+1 478 474 1375",
    "sg:postcode":"31210",
    "sg:province":"GA",
    "sg:tags":[
        "medical"
    ],
    "wof:name":"Harry Linkous MD",
    "wof:placetype":"venue"
},
  "geometry": {"coordinates":[-83.689432,32.864565],"type":"Point"}
}