{
  "type": "Feature",
  "properties": {
    "iso:country":"US",
    "sg:address":"2093 Phillips Rd",
    "sg:city":"Lithonia",
    "sg:classifiers":[
        {
            "category":"Home & Garden",
            "subcategory":"Hardware",
            "type":"Retail Goods"
        }
    ],
    "sg:phone":"+1 770 808 8302",
    "sg:postcode":"30058",
    "sg:province":"GA",
    "wof:name":"Chain Saw Tree",
    "wof:placetype":"venue"
},
  "geometry": {"coordinates":[-84.131855,33.728037],"type":"Point"}
}