{
  "type": "Feature",
  "properties": {
    "addr:full":"521 Lax Hwy Ocilla GA 31774",
    "addr:housenumber":"521",
    "addr:postcode":"31774",
    "addr:street":"Lax Hwy",
    "iso:country":"US",
    "sg:address":"521 Lax Hwy",
    "sg:city":"Ocilla",
    "sg:classifiers":[
        {
            "category":"Education",
            "subcategory":"School",
            "type":"Public Place"
        }
    ],
    "sg:phone":"+1 229 468 9476",
    "sg:postcode":"31774",
    "sg:province":"GA",
    "wof:name":"Irwin County Elementary School",
    "wof:placetype":"venue"
},
  "geometry": {"coordinates":[-83.228149,31.574275],"type":"Point"}
}