{
  "type": "Feature",
  "properties": {
    "iso:country":"US",
    "sg:address":"1212 Webster Ave",
    "sg:city":"Columbus",
    "sg:classifiers":[
        {
            "category":"Wholesale",
            "subcategory":"Hardware",
            "type":"Manufacturing & Wholesale Goods"
        },
        {
            "category":"Home & Garden",
            "subcategory":"Household Appliances",
            "type":"Retail Goods"
        }
    ],
    "sg:phone":"+1 706 653 1731",
    "sg:postcode":"31901",
    "sg:province":"GA",
    "sg:tags":[
        "parts",
        "refrigerating"
    ],
    "wof:name":"Wittichen Supply Company",
    "wof:placetype":"venue"
},
  "geometry": {"coordinates":[-84.97837199999999,32.470358],"type":"Point"}
}