{
  "type": "Feature",
  "properties": {
    "iso:country":"US",
    "sg:address":"999 Whitlock Ave SW Ste 11",
    "sg:city":"Marietta",
    "sg:classifiers":[
        {
            "category":"Health Services",
            "subcategory":"Chiropractor",
            "type":"Services"
        }
    ],
    "sg:phone":"+1 770 590 7771",
    "sg:postcode":"30064",
    "sg:province":"GA",
    "wof:name":"Center For Health & Healing",
    "wof:placetype":"venue"
},
  "geometry": {"coordinates":[-84.579047,33.952082],"type":"Point"}
}