{
  "type": "Feature",
  "properties": {
    "addr:full":"1225 Brookside Dr NE Conyers GA 30012",
    "addr:housenumber":"1225",
    "addr:postcode":"30012",
    "addr:street":"Brookside Dr Ne",
    "iso:country":"US",
    "sg:address":"1225 Brookside Dr NE",
    "sg:city":"Conyers",
    "sg:classifiers":[
        {
            "category":"Manufacturing",
            "subcategory":"Tools & Machinery",
            "type":"Manufacturing & Wholesale Goods"
        }
    ],
    "sg:phone":"+1 770 483 4576",
    "sg:postcode":"30012",
    "sg:province":"GA",
    "sg:tags":[
        "metal",
        "fabrication"
    ],
    "wof:name":"W B George Manufacturing Co",
    "wof:placetype":"venue"
},
  "geometry": {"coordinates":[-84.006045,33.675248],"type":"Point"}
}