{
  "type": "Feature",
  "properties": {
    "iso:country":"US",
    "sg:address":"704 Woodbury Rd",
    "sg:city":"Greenville",
    "sg:classifiers":[
        {
            "category":"Freight",
            "type":"Transportation"
        }
    ],
    "sg:phone":"+1 706 672 1400",
    "sg:postcode":"30222",
    "sg:province":"GA",
    "sg:tags":[
        "commercial",
        "storage"
    ],
    "wof:name":"Greenville Mini Storage",
    "wof:placetype":"venue"
},
  "geometry": {"coordinates":[-84.710689,33.029187],"type":"Point"}
}