{
  "type": "Feature",
  "properties": {
    "iso:country":"US",
    "sg:address":"840 Church St Exd",
    "sg:city":"Marietta",
    "sg:classifiers":[
        {
            "category":"Health Services",
            "subcategory":"Health Practitioner",
            "type":"Services"
        }
    ],
    "sg:phone":"+1 770 422 6610",
    "sg:postcode":"30060",
    "sg:province":"GA",
    "sg:tags":[
        "psychologist"
    ],
    "wof:name":"Frederick Huff PHD",
    "wof:placetype":"venue"
},
  "geometry": {"coordinates":[-84.554939,33.9771],"type":"Point"}
}