{
  "type": "Feature",
  "properties": {
    "addr:full":"3025 State Rte 154 Newnan GA 30265",
    "addr:housenumber":"3025",
    "addr:postcode":"30265",
    "addr:street":"State Rte 154",
    "iso:country":"US",
    "sg:address":"3025 State Rte 154",
    "sg:city":"Newnan",
    "sg:classifiers":[
        {
            "category":"Building & Trades",
            "subcategory":"Construction",
            "type":"Services"
        }
    ],
    "sg:phone":"+1 770 683 3860",
    "sg:postcode":"30265",
    "sg:province":"GA",
    "sg:tags":[
        "contractor"
    ],
    "wof:name":"Inex Homes",
    "wof:placetype":"venue"
},
  "geometry": {"coordinates":[-84.68252200000001,33.413855],"type":"Point"}
}