{
  "type": "Feature",
  "properties": {
    "addr:full":"711 W Pinson St Sylvester GA 31791",
    "addr:housenumber":"711",
    "addr:postcode":"31791",
    "addr:street":"W Pinson St",
    "iso:country":"US",
    "sg:address":"711 W Pinson St",
    "sg:city":"Sylvester",
    "sg:classifiers":[
        {
            "category":"Organizations",
            "subcategory":"Religious Organization",
            "type":"Services"
        }
    ],
    "sg:phone":"+1 229 776 4854",
    "sg:postcode":"31791",
    "sg:province":"GA",
    "wof:name":"Spring Hl Mssnary Bptst Church",
    "wof:placetype":"venue"
},
  "geometry": {"coordinates":[-83.84831699999999,31.533956],"type":"Point"}
}