{
  "type": "Feature",
  "properties": {
    "addr:full":"619 Highway 138 W Stockbridge GA 30281",
    "addr:housenumber":"619",
    "addr:postcode":"30281",
    "addr:street":"Highway 138 W",
    "iso:country":"US",
    "sg:address":"619 Highway 138 W",
    "sg:city":"Stockbridge",
    "sg:classifiers":[
        {
            "category":"Travel",
            "subcategory":"Hotels & Motels",
            "type":"Entertainment"
        },
        {
            "category":"Restaurant",
            "type":"Food & Drink"
        }
    ],
    "sg:phone":"+1 770 474 8771",
    "sg:postcode":"30281",
    "sg:province":"GA",
    "sg:website":"http://www.bestwestern.com",
    "wof:name":"Best Western",
    "wof:placetype":"venue"
},
  "geometry": {"coordinates":[-84.281156,33.544657],"type":"Point"}
}