{
  "type": "Feature",
  "properties": {
    "iso:country":"US",
    "sg:address":"3520 Piedmont Rd NE",
    "sg:city":"Atlanta",
    "sg:classifiers":[
        {
            "category":"Banks & Credit Unions",
            "subcategory":"Investment Brokerage",
            "type":"Services"
        },
        {
            "category":"Professional",
            "subcategory":"Management & Consulting",
            "type":"Services"
        }
    ],
    "sg:phone":"+1 404 841 0712",
    "sg:postcode":"30305",
    "sg:province":"GA",
    "sg:tags":[
        "consultant",
        "planning",
        "financial"
    ],
    "sg:website":"www.piedmont-center.com",
    "wof:name":"Piedmont Consulting Group",
    "wof:placetype":"venue"
},
  "geometry": {"coordinates":[-84.373098,33.847264],"type":"Point"}
}