{
  "type": "Feature",
  "properties": {
    "addr:full":"906 S Thornton Ave Dalton GA 30720",
    "addr:housenumber":"906",
    "addr:postcode":"30720",
    "addr:street":"S Thornton Ave",
    "iso:country":"US",
    "sg:address":"906 S Thornton Ave",
    "sg:city":"Dalton",
    "sg:classifiers":[
        {
            "category":"Personal",
            "subcategory":"Beauty Salon",
            "type":"Services"
        }
    ],
    "sg:phone":"+1 706 370 7713",
    "sg:postcode":"30720",
    "sg:province":"GA",
    "sg:tags":[
        "shop"
    ],
    "wof:name":"Twisted Sister Hair Salon & Bo",
    "wof:placetype":"venue"
},
  "geometry": {"coordinates":[-84.97171299999999,34.764226],"type":"Point"}
}