{
  "type": "Feature",
  "properties": {
    "addr:full":"329 Bell Park Dr Woodstock GA 30188",
    "addr:housenumber":"329",
    "addr:postcode":"30188",
    "addr:street":"Bell Park Dr",
    "iso:country":"US",
    "sg:address":"329 Bell Park Dr",
    "sg:city":"Woodstock",
    "sg:classifiers":[
        {
            "category":"Building & Trades",
            "subcategory":"Pest Control",
            "type":"Services"
        }
    ],
    "sg:phone":"+1 770 591 1892",
    "sg:postcode":"30188",
    "sg:province":"GA",
    "wof:name":"APC Equipment Svc Ctr",
    "wof:placetype":"venue"
},
  "geometry": {"coordinates":[-84.51258300000001,34.125985],"type":"Point"}
}