{
  "type": "Feature",
  "properties": {
    "addr:full":"101 N Speer Rd Stockbridge GA 30281",
    "addr:housenumber":"101",
    "addr:postcode":"30281",
    "addr:street":"N Speer Rd",
    "iso:country":"US",
    "sg:address":"101 N Speer Rd",
    "sg:city":"Stockbridge",
    "sg:classifiers":[
        {
            "category":"Banks & Credit Unions",
            "subcategory":"Bank",
            "type":"Services"
        }
    ],
    "sg:phone":"+1 770 474 3306",
    "sg:postcode":"30281",
    "sg:province":"GA",
    "sg:website":"www.statefarm.com",
    "wof:name":"Ronnie Simmons Insurance",
    "wof:placetype":"venue"
},
  "geometry": {"coordinates":[-84.25720200000001,33.551601],"type":"Point"}
}