{
  "type": "Feature",
  "properties": {
    "addr:full":"1960 Fairview Church Rd Blairsville GA 30512",
    "addr:housenumber":"1960",
    "addr:postcode":"30512",
    "addr:street":"Fairview Church Rd",
    "iso:country":"US",
    "sg:address":"1960 Fairview Church Rd",
    "sg:city":"Blairsville",
    "sg:classifiers":[
        {
            "category":"Personal",
            "subcategory":"Beauty Salon",
            "type":"Services"
        }
    ],
    "sg:phone":"+1 706 745 4686",
    "sg:postcode":"30512",
    "sg:province":"GA",
    "wof:name":"Pat's Beauty Salon",
    "wof:placetype":"venue"
},
  "geometry": {"coordinates":[-83.983802,34.847225],"type":"Point"}
}