{
  "type": "Feature",
  "properties": {
    "iso:country":"US",
    "sg:address":"671 Rockbridge Rd SW",
    "sg:city":"Lilburn",
    "sg:classifiers":[
        {
            "category":"Building & Trades",
            "subcategory":"Construction",
            "type":"Services"
        }
    ],
    "sg:phone":"+1 770 935 4059",
    "sg:postcode":"30047",
    "sg:province":"GA",
    "sg:tags":[
        "hanging",
        "contractor"
    ],
    "wof:name":"Lux Painting Co J",
    "wof:placetype":"venue"
},
  "geometry": {"coordinates":[-84.140959,33.857193],"type":"Point"}
}