{
  "type": "Feature",
  "properties": {
    "iso:country":"US",
    "sg:address":"800 Sycamore Dr",
    "sg:city":"Canton",
    "sg:classifiers":[
        {
            "category":"Manufacturing",
            "subcategory":"Tools & Machinery",
            "type":"Manufacturing & Wholesale Goods"
        }
    ],
    "sg:phone":"+1 770 475 4340",
    "sg:postcode":"30115",
    "sg:province":"GA",
    "sg:tags":[
        "machine",
        "parts",
        "mfg"
    ],
    "wof:name":"Machined Cunningham Products",
    "wof:placetype":"venue"
},
  "geometry": {"coordinates":[-84.364051,34.196525],"type":"Point"}
}