{
  "type": "Feature",
  "properties": {
    "addr:full":"356 Taylor Rowland Rd Dexter GA 31019",
    "addr:housenumber":"356",
    "addr:postcode":"31019",
    "addr:street":"Taylor Rowland Rd",
    "iso:country":"US",
    "sg:address":"356 Taylor Rowland Rd",
    "sg:city":"Dexter",
    "sg:classifiers":[
        {
            "category":"Food & Beverages",
            "subcategory":"Groceries & Convenience Stores",
            "type":"Retail Goods"
        }
    ],
    "sg:phone":"+1 478 875 3206",
    "sg:postcode":"31019",
    "sg:province":"GA",
    "sg:tags":[
        "market"
    ],
    "wof:name":"Taylor Rowland's Farm",
    "wof:placetype":"venue"
},
  "geometry": {"coordinates":[-83.041455,32.431992],"type":"Point"}
}