{
  "type": "Feature",
  "properties": {
    "addr:full":"4634 Holly Springs Rd Pendergrass GA 30567",
    "addr:housenumber":"4634",
    "addr:postcode":"30567",
    "addr:street":"Holly Springs Rd",
    "iso:country":"US",
    "sg:address":"4634 Holly Springs Rd",
    "sg:city":"Pendergrass",
    "sg:classifiers":[
        {
            "category":"Communications",
            "type":"Services"
        }
    ],
    "sg:phone":"+1 706 693 2167",
    "sg:postcode":"30567",
    "sg:province":"GA",
    "wof:name":"Pinnacle Towers Inc",
    "wof:placetype":"venue"
},
  "geometry": {"coordinates":[-83.62299299999999,34.20192],"type":"Point"}
}