{
  "type": "Feature",
  "properties": {
    "iso:country":"US",
    "sg:address":"1217 Kenilworth Trce",
    "sg:city":"Snellville",
    "sg:classifiers":[
        {
            "category":"Professional",
            "subcategory":"Business Services",
            "type":"Services"
        }
    ],
    "sg:phone":"+1 770 982 7114",
    "sg:postcode":"30078",
    "sg:province":"GA",
    "wof:name":"Rainstreet Solutions Inc",
    "wof:placetype":"venue"
},
  "geometry": {"coordinates":[-84.01785599999999,33.896384],"type":"Point"}
}