{
  "type": "Feature",
  "properties": {
    "addr:full":"2856 Old Peachtree Rd Dacula GA 30019",
    "addr:housenumber":"2856",
    "addr:postcode":"ga 30019",
    "addr:street":"Old Peachtree Rd",
    "iso:country":"US",
    "sg:address":"2856 Old Peachtree Rd",
    "sg:city":"Dacula",
    "sg:classifiers":[
        {
            "category":"Building & Trades",
            "subcategory":"Construction",
            "type":"Services"
        }
    ],
    "sg:phone":"+1 770 682 7522",
    "sg:postcode":"30019",
    "sg:province":"GA",
    "sg:tags":[
        "general",
        "contractor"
    ],
    "wof:name":"Ward Construction Company Inc",
    "wof:placetype":"venue"
},
  "geometry": {"coordinates":[-83.930927,34.019572],"type":"Point"}
}