{
  "type": "Feature",
  "properties": {
    "iso:country":"US",
    "sg:address":"1025 E Spring St",
    "sg:city":"Monroe",
    "sg:classifiers":[
        {
            "category":"Food & Beverages",
            "subcategory":"Groceries & Convenience Stores",
            "type":"Retail Goods"
        }
    ],
    "sg:phone":"+1 770 267 4214",
    "sg:postcode":"30655",
    "sg:province":"GA",
    "wof:name":"Southern Family Markets",
    "wof:placetype":"venue"
},
  "geometry": {"coordinates":[-83.72932,33.793355],"type":"Point"}
}