{
  "type": "Feature",
  "properties": {
    "addr:full":"1430 Five Forks Trickum Rd Ste 260 Lawrenceville GA 30044",
    "addr:housenumber":"1430",
    "addr:postcode":"30044",
    "addr:street":"Five Forks Trickum Rd Ste 260",
    "iso:country":"US",
    "sg:address":"1430 Five Forks Trickum Rd Ste 260",
    "sg:city":"Lawrenceville",
    "sg:classifiers":[
        {
            "category":"Restaurant",
            "type":"Food & Drink"
        }
    ],
    "sg:phone":"+1 678 985 2203",
    "sg:postcode":"30044",
    "sg:province":"GA",
    "sg:tags":[
        "fusion",
        "asian"
    ],
    "sg:website":"www.totorigrill.com_broken_link",
    "wof:name":"Totori Fresh Grill & Sushi",
    "wof:placetype":"venue"
},
  "geometry": {"coordinates":[-84.016339,33.919723],"type":"Point"}
}