{
  "type": "Feature",
  "properties": {
    "iso:country":"US",
    "sg:address":"2633 Yale Ter",
    "sg:city":"Decatur",
    "sg:classifiers":[
        {
            "category":"Organizations",
            "subcategory":"Religious Organization",
            "type":"Services"
        }
    ],
    "sg:phone":"+1 404 243 3385",
    "sg:postcode":"30032",
    "sg:province":"GA",
    "sg:tags":[
        "clergy"
    ],
    "wof:name":"Minister Eugene Gunn Sr",
    "wof:placetype":"venue"
},
  "geometry": {"coordinates":[-84.28263099999999,33.71999],"type":"Point"}
}