{
  "type": "Feature",
  "properties": {
    "iso:country":"US",
    "sg:address":"426 Sherwood Oaks Rd",
    "sg:city":"Stone Mountain",
    "sg:classifiers":[
        {
            "category":"Education",
            "subcategory":"Special Training",
            "type":"Public Place"
        }
    ],
    "sg:phone":"+1 404 944 2865",
    "sg:postcode":"30087",
    "sg:province":"GA",
    "wof:name":"A Sheppards Guidance Tutoring",
    "wof:placetype":"venue"
},
  "geometry": {"coordinates":[-84.154472,33.781068],"type":"Point"}
}