{
  "type": "Feature",
  "properties": {
    "addr:full":"1851 Alderbrook Rd NE Atlanta GA 30345",
    "addr:housenumber":"1851",
    "addr:postcode":"30345",
    "addr:street":"Alderbrook Rd Ne",
    "iso:country":"US",
    "sg:address":"1851 Alderbrook Rd NE",
    "sg:city":"Atlanta",
    "sg:classifiers":[
        {
            "category":"Building & Trades",
            "subcategory":"Locksmith",
            "type":"Services"
        }
    ],
    "sg:phone":"+1 404 682 9655",
    "sg:postcode":"30345",
    "sg:province":"GA",
    "sg:tags":[
        "key"
    ],
    "wof:name":"1 24 7 A Locksmith",
    "wof:placetype":"venue"
},
  "geometry": {"coordinates":[-84.30409400000001,33.832029],"type":"Point"}
}