{
  "type": "Feature",
  "properties": {
    "addr:full":"5671 Peachtree Atlanta GA 30338",
    "addr:housenumber":"5671",
    "addr:postcode":"30338",
    "addr:street":"Peachtree",
    "iso:country":"US",
    "sg:address":"5671 Peachtree",
    "sg:city":"Atlanta",
    "sg:classifiers":[
        {
            "category":"Health Services",
            "subcategory":"Doctor",
            "type":"Services"
        }
    ],
    "sg:phone":"+1 770 822 5560",
    "sg:postcode":"30338",
    "sg:province":"GA",
    "wof:name":"Friedman Richard J MD",
    "wof:placetype":"venue"
},
  "geometry": {"coordinates":[-84.318093,33.939877],"type":"Point"}
}