{
  "type": "Feature",
  "properties": {
    "addr:full":"9529 Fernandina Dr Douglasville GA 30135",
    "addr:housenumber":"9529",
    "addr:postcode":"30135",
    "addr:street":"Fernandina Dr",
    "iso:country":"US",
    "sg:address":"9529 Fernandina Dr",
    "sg:city":"Douglasville",
    "sg:classifiers":[
        {
            "category":"Shopping",
            "subcategory":"Jewelry",
            "type":"Retail Goods"
        }
    ],
    "sg:phone":"+1 678 838 7471",
    "sg:postcode":"30135",
    "sg:province":"GA",
    "sg:tags":[
        "pearl"
    ],
    "wof:name":"Pearl Of Wisdom",
    "wof:placetype":"venue"
},
  "geometry": {"coordinates":[-84.70954999999999,33.722728],"type":"Point"}
}