{
  "type": "Feature",
  "properties": {
    "iso:country":"US",
    "sg:address":"2 Macon St",
    "sg:city":"Mcdonough",
    "sg:classifiers":[
        {
            "category":"Professional",
            "subcategory":"Business Services",
            "type":"Services"
        }
    ],
    "sg:phone":"+1 678 432 8845",
    "sg:postcode":"30253",
    "sg:province":"GA",
    "sg:tags":[
        "interior",
        "consultant",
        "design",
        "decorator"
    ],
    "wof:name":"Devine Design Interiors By Amy",
    "wof:placetype":"venue"
},
  "geometry": {"coordinates":[-84.146373,33.447007],"type":"Point"}
}