{
  "type": "Feature",
  "properties": {
    "addr:full":"900 W Pine St Hinesville GA 31313",
    "addr:housenumber":"900",
    "addr:postcode":"31313",
    "addr:street":"W Pine St",
    "iso:country":"US",
    "sg:address":"900 W Pine St",
    "sg:city":"Hinesville",
    "sg:classifiers":[
        {
            "category":"Professional",
            "subcategory":"Computer Services",
            "type":"Services"
        }
    ],
    "sg:phone":"+1 912 925 7850",
    "sg:postcode":"31313",
    "sg:province":"GA",
    "sg:tags":[
        "related"
    ],
    "wof:name":"Kealohas Computer Consulting",
    "wof:placetype":"venue"
},
  "geometry": {"coordinates":[-81.62625800000001,31.823227],"type":"Point"}
}