{
  "type": "Feature",
  "properties": {
    "iso:country":"US",
    "sg:address":"401 Church St",
    "sg:city":"Guyton",
    "sg:phone":"+1 912 772 5099",
    "sg:postcode":"31312",
    "sg:province":"GA",
    "wof:name":"Guyton United Methodist Church",
    "wof:placetype":"venue"
},
  "geometry": {"coordinates":[-81.39122,32.335178],"type":"Point"}
}