{
  "type": "Feature",
  "properties": {
    "iso:country":"US",
    "sg:address":"1039 Sugar Pike Way",
    "sg:city":"Canton",
    "sg:classifiers":[
        {
            "category":"Banks & Credit Unions",
            "subcategory":"Investment Brokerage",
            "type":"Services"
        }
    ],
    "sg:phone":"+1 770 559 0591",
    "sg:postcode":"30115",
    "sg:province":"GA",
    "sg:tags":[
        "advisory"
    ],
    "wof:name":"Redwood Financial Service",
    "wof:placetype":"venue"
},
  "geometry": {"coordinates":[-84.384187,34.177038],"type":"Point"}
}