{
  "type": "Feature",
  "properties": {
    "addr:full":"1111 Mooty Bridge Rd Lagrange GA 30240",
    "addr:housenumber":"1111",
    "addr:postcode":"30240",
    "addr:street":"Mooty Bridge Rd",
    "iso:country":"US",
    "sg:address":"1111 Mooty Bridge Rd",
    "sg:city":"Lagrange",
    "sg:classifiers":[
        {
            "category":"Real Estate",
            "subcategory":"Real Estate Agent",
            "type":"Services"
        }
    ],
    "sg:phone":"+1 706 883 6357",
    "sg:postcode":"30240",
    "sg:province":"GA",
    "wof:name":"Sprinks Durand Realtors",
    "wof:placetype":"venue"
},
  "geometry": {"coordinates":[-85.03787199999999,33.063423],"type":"Point"}
}