{
  "type": "Feature",
  "properties": {
    "addr:full":"50 Cotton Xing W Savannah GA 31411",
    "addr:housenumber":"50",
    "addr:postcode":"31411",
    "addr:street":"Cotton Xing W",
    "iso:country":"US",
    "sg:address":"50 Cotton Xing W",
    "sg:city":"Savannah",
    "sg:classifiers":[
        {
            "category":"Manufacturing",
            "subcategory":"Printing",
            "type":"Manufacturing & Wholesale Goods"
        }
    ],
    "sg:phone":"+1 912 598 8090",
    "sg:postcode":"31411",
    "sg:province":"GA",
    "sg:tags":[
        "publisher"
    ],
    "wof:name":"Prahlstein",
    "wof:placetype":"venue"
},
  "geometry": {"coordinates":[-81.052328,31.906903],"type":"Point"}
}