{
  "type": "Feature",
  "properties": {
    "iso:country":"US",
    "sg:address":"209 Laura Lake Rd",
    "sg:city":"Marietta",
    "sg:classifiers":[
        {
            "category":"Social Services",
            "subcategory":"Adult Care",
            "type":"Services"
        }
    ],
    "sg:phone":"+1 770 590 1616",
    "sg:postcode":"30066",
    "sg:province":"GA",
    "sg:tags":[
        "home",
        "residential"
    ],
    "wof:name":"Laura Lake Assisted Living",
    "wof:placetype":"venue"
},
  "geometry": {"coordinates":[-84.55110999999999,34.002889],"type":"Point"}
}