{
  "type": "Feature",
  "properties": {
    "addr:full":"2708 Hillcrest Ave Augusta GA 30909",
    "addr:housenumber":"2708",
    "addr:postcode":"30909",
    "addr:street":"Hillcrest Ave",
    "iso:country":"US",
    "sg:address":"2708 Hillcrest Ave",
    "sg:city":"Augusta",
    "sg:classifiers":[
        {
            "category":"Building & Trades",
            "subcategory":"Construction",
            "type":"Services"
        }
    ],
    "sg:phone":"+1 706 736 6707",
    "sg:postcode":"30909",
    "sg:province":"GA",
    "sg:tags":[
        "general",
        "contractor"
    ],
    "wof:name":"Adams Porter Construction Co",
    "wof:placetype":"venue"
},
  "geometry": {"coordinates":[-82.032982,33.477635],"type":"Point"}
}