{
  "type": "Feature",
  "properties": {
    "addr:full":"2722 Old Tilton Rd SE Dalton GA 30721",
    "addr:housenumber":"2722",
    "addr:postcode":"30721",
    "addr:street":"Old Tilton Rd Se Dalton",
    "iso:country":"US",
    "sg:address":"2722 Old Tilton Rd SE",
    "sg:city":"Dalton",
    "sg:classifiers":[
        {
            "category":"Building & Trades",
            "subcategory":"Construction",
            "type":"Services"
        }
    ],
    "sg:phone":"+1 706 277 9269",
    "sg:postcode":"30721",
    "sg:province":"GA",
    "sg:tags":[
        "specializing",
        "clearing",
        "small",
        "land",
        "contractor"
    ],
    "wof:name":"Mason Construction",
    "wof:placetype":"venue"
},
  "geometry": {"coordinates":[-84.93473899999999,34.694278],"type":"Point"}
}