{
  "type": "Feature",
  "properties": {
    "iso:country":"US",
    "sg:address":"5500 White Bluff Rd",
    "sg:city":"Savannah",
    "sg:classifiers":[
        {
            "category":"Professional",
            "subcategory":"Accounting & Tax Preparation",
            "type":"Services"
        },
        {
            "category":"Banks & Credit Unions",
            "subcategory":"Financial Services",
            "type":"Services"
        }
    ],
    "sg:phone":"+1 912 354 7788",
    "sg:postcode":"31405",
    "sg:province":"GA",
    "sg:tags":[
        "loan",
        "return",
        "preparation-business"
    ],
    "wof:name":"Budget Finance Co",
    "wof:placetype":"venue"
},
  "geometry": {"coordinates":[-81.111259,32.027821],"type":"Point"}
}