{
  "type": "Feature",
  "properties": {
    "addr:full":"201 Gillespie Dr Dalton GA 30721",
    "addr:housenumber":"201",
    "addr:postcode":"30721",
    "addr:street":"Gillespie Dr",
    "iso:country":"US",
    "sg:address":"201 Gillespie Dr",
    "sg:city":"Dalton",
    "sg:classifiers":[
        {
            "category":"Wholesale",
            "subcategory":"Scrap",
            "type":"Manufacturing & Wholesale Goods"
        }
    ],
    "sg:phone":"+1 706 278 3008",
    "sg:postcode":"30721",
    "sg:province":"GA",
    "sg:tags":[
        "material"
    ],
    "wof:name":"Shelton Waste Co",
    "wof:placetype":"venue"
},
  "geometry": {"coordinates":[-84.924165,34.749346],"type":"Point"}
}