{
  "type": "Feature",
  "properties": {
    "addr:full":"318 Sydney St SE Atlanta GA 30312",
    "addr:housenumber":"318",
    "addr:postcode":"30312",
    "addr:street":"Sydney St Se",
    "iso:country":"US",
    "sg:address":"318 Sydney St SE",
    "sg:city":"Atlanta",
    "sg:classifiers":[
        {
            "category":"Building & Trades",
            "subcategory":"Construction",
            "type":"Services"
        }
    ],
    "sg:phone":"+1 404 589 0010",
    "sg:postcode":"30312",
    "sg:province":"GA",
    "sg:tags":[
        "general",
        "contractor"
    ],
    "wof:name":"Remodeling Group",
    "wof:placetype":"venue"
},
  "geometry": {"coordinates":[-84.376864,33.741276],"type":"Point"}
}