{
  "type": "Feature",
  "properties": {
    "iso:country":"US",
    "sg:address":"4601 Lakeview Ln",
    "sg:city":"Gainesville",
    "sg:classifiers":[
        {
            "category":"Professional",
            "type":"Services"
        }
    ],
    "sg:phone":"+1 770 718 9533",
    "sg:postcode":"30504",
    "sg:province":"GA",
    "wof:name":"David J Nichol",
    "wof:placetype":"venue"
},
  "geometry": {"coordinates":[-83.91670499999999,34.264908],"type":"Point"}
}