{
  "type": "Feature",
  "properties": {
    "addr:full":"3148 Fulwood Rd Tifton GA 31794",
    "addr:housenumber":"3148",
    "addr:postcode":"31794",
    "addr:street":"Fulwood Rd",
    "iso:country":"US",
    "sg:address":"3148 Fulwood Rd",
    "sg:city":"Tifton",
    "sg:classifiers":[
        {
            "category":"Social Services",
            "subcategory":"Child Care",
            "type":"Services"
        }
    ],
    "sg:phone":"+1 229 382 5588",
    "sg:postcode":"31794",
    "sg:province":"GA",
    "wof:name":"Mother's Love Too Child Care",
    "wof:placetype":"venue"
},
  "geometry": {"coordinates":[-83.505949,31.485335],"type":"Point"}
}