{
  "type": "Feature",
  "properties": {
    "addr:full":"208 N Main St Wrens GA 30833",
    "addr:housenumber":"208",
    "addr:postcode":"30833",
    "addr:street":"N Main St",
    "iso:country":"US",
    "sg:address":"208 N Main St",
    "sg:city":"Wrens",
    "sg:classifiers":[
        {
            "category":"Insurance",
            "subcategory":"Insurance Agent",
            "type":"Services"
        }
    ],
    "sg:phone":"+1 706 547 6501",
    "sg:postcode":"30833",
    "sg:province":"GA",
    "sg:tags":[
        "real estate"
    ],
    "wof:name":"Ricketson Insurance & Realty",
    "wof:placetype":"venue"
},
  "geometry": {"coordinates":[-82.386805,33.210089],"type":"Point"}
}