{
  "type": "Feature",
  "properties": {
    "addr:full":"992 Senoia Rd Tyrone GA 30290",
    "addr:housenumber":"992",
    "addr:postcode":"30290",
    "addr:street":"Senoia Rd",
    "iso:country":"US",
    "sg:address":"992 Senoia Rd",
    "sg:city":"Tyrone",
    "sg:classifiers":[
        {
            "category":"Shopping",
            "subcategory":"Pharmacy",
            "type":"Retail Goods"
        }
    ],
    "sg:phone":"+1 770 487 4226",
    "sg:postcode":"30290",
    "sg:province":"GA",
    "wof:name":"Mundy's Tyrone Pharmacy",
    "wof:placetype":"venue"
},
  "geometry": {"coordinates":[-84.58950400000001,33.479589],"type":"Point"}
}