{
  "type": "Feature",
  "properties": {
    "addr:full":"1424 Roswell Rd Marietta GA 30062",
    "addr:housenumber":"1424",
    "addr:postcode":"30062",
    "addr:street":"Roswell Rd",
    "iso:country":"US",
    "sg:address":"1424 Roswell Rd",
    "sg:city":"Marietta",
    "sg:classifiers":[
        {
            "category":"Cinema",
            "subcategory":"Movie Rental",
            "type":"Entertainment"
        }
    ],
    "sg:phone":"+1 770 578 0399",
    "sg:postcode":"30062",
    "sg:province":"GA",
    "sg:tags":[
        "game",
        "video"
    ],
    "wof:name":"Starship Enterprises of Atlanta",
    "wof:placetype":"venue"
},
  "geometry": {"coordinates":[-84.510498,33.9506],"type":"Point"}
}