{
  "type": "Feature",
  "properties": {
    "iso:country":"US",
    "sg:address":"1655 Spectrum Dr",
    "sg:city":"Lawrenceville",
    "sg:classifiers":[
        {
            "category":"Building & Trades",
            "subcategory":"Locksmith",
            "type":"Services"
        }
    ],
    "sg:phone":"+1 888 229 5977",
    "sg:postcode":"30043",
    "sg:province":"GA",
    "sg:tags":[
        "key"
    ],
    "wof:name":"24 Hour 1 Emergency Locksmith",
    "wof:placetype":"venue"
},
  "geometry": {"coordinates":[-84.06446800000001,33.972084],"type":"Point"}
}