{
  "type": "Feature",
  "properties": {
    "iso:country":"US",
    "sg:address":"110 Whitney Way",
    "sg:city":"Fayetteville",
    "sg:classifiers":[
        {
            "category":"Shopping",
            "subcategory":"Gifts & Souvenirs",
            "type":"Retail Goods"
        }
    ],
    "sg:phone":"+1 770 460 0277",
    "sg:postcode":"30214",
    "sg:province":"GA",
    "sg:tags":[
        "shop"
    ],
    "wof:name":"F M Gifts F 9036",
    "wof:placetype":"venue"
},
  "geometry": {"coordinates":[-84.480473,33.499088],"type":"Point"}
}