{
  "type": "Feature",
  "properties": {
    "addr:full":"5866 Buford Hwy Norcross GA 30071",
    "addr:housenumber":"5866",
    "addr:postcode":"30071",
    "addr:street":"Buford Hwy",
    "iso:country":"US",
    "sg:address":"5866 Buford Hwy",
    "sg:city":"Norcross",
    "sg:classifiers":[
        {
            "category":"Home & Garden",
            "subcategory":"Carpets & Floor Coverings",
            "type":"Retail Goods"
        }
    ],
    "sg:phone":"+1 770 446 6432",
    "sg:postcode":"30071",
    "sg:province":"GA",
    "sg:tags":[
        "carpeting"
    ],
    "sg:website":"www.daltoncarpetcenter.com",
    "wof:name":"Dalton Carpet Center",
    "wof:placetype":"venue"
},
  "geometry": {"coordinates":[-84.213402,33.937199],"type":"Point"}
}