{
  "type": "Feature",
  "properties": {
    "iso:country":"US",
    "sg:address":"1430 Marietta Blvd NW",
    "sg:city":"Atlanta",
    "sg:classifiers":[
        {
            "category":"Home & Garden",
            "subcategory":"Building Materials",
            "type":"Retail Goods"
        }
    ],
    "sg:phone":"+1 404 355 8196",
    "sg:postcode":"30318",
    "sg:province":"GA",
    "sg:tags":[
        "mixed",
        "concrete"
    ],
    "sg:website":"www.thomasconcrete.com",
    "wof:name":"Thomas Concrete Of Georgia Inc",
    "wof:placetype":"venue"
},
  "geometry": {"coordinates":[-84.432276,33.795186],"type":"Point"}
}