{
  "type": "Feature",
  "properties": {
    "iso:country":"US",
    "sg:address":"3240 Old Salem Rd SE",
    "sg:city":"Conyers",
    "sg:classifiers":[
        {
            "category":"Wholesale",
            "subcategory":"Home Furnishings",
            "type":"Manufacturing & Wholesale Goods"
        }
    ],
    "sg:phone":"+1 678 413 4728",
    "sg:postcode":"30013",
    "sg:province":"GA",
    "sg:tags":[
        "manufacturer",
        "baskets-wholesale"
    ],
    "wof:name":"The Basket Place",
    "wof:placetype":"venue"
},
  "geometry": {"coordinates":[-83.989649,33.605705],"type":"Point"}
}