{
  "type": "Feature",
  "properties": {
    "addr:full":"240 S Dixie Ave Cartersville GA 30120",
    "addr:housenumber":"240",
    "addr:postcode":"30120",
    "addr:street":"S Dixie Ave",
    "iso:country":"US",
    "sg:address":"240 S Dixie Ave",
    "sg:city":"Cartersville",
    "sg:classifiers":[
        {
            "category":"Shopping",
            "subcategory":"Computers & Home Electronics",
            "type":"Retail Goods"
        }
    ],
    "sg:phone":"+1 770 382 9562",
    "sg:postcode":"30120",
    "sg:province":"GA",
    "wof:name":"Radio Shack",
    "wof:placetype":"venue"
},
  "geometry": {"coordinates":[-84.788894,34.160225],"type":"Point"}
}