{
  "type": "Feature",
  "properties": {
    "addr:full":"2067 Spicers Ln Woodstock GA 30189",
    "addr:housenumber":"2067",
    "addr:postcode":"30189",
    "addr:street":"Spicers Ln",
    "iso:country":"US",
    "sg:address":"2067 Spicers Ln",
    "sg:city":"Woodstock",
    "sg:classifiers":[
        {
            "category":"Wholesale",
            "subcategory":"Machinery & Supplies",
            "type":"Manufacturing & Wholesale Goods"
        }
    ],
    "sg:phone":"+1 770 517 5458",
    "sg:postcode":"30189",
    "sg:province":"GA",
    "sg:tags":[
        "industrial"
    ],
    "wof:name":"Wagener Schwelm Corp",
    "wof:placetype":"venue"
},
  "geometry": {"coordinates":[-84.57253799999999,34.111457],"type":"Point"}
}