{
  "type": "Feature",
  "properties": {
    "addr:full":"4045 Old Milton Pkwy Alpharetta GA 30005",
    "addr:housenumber":"4045",
    "addr:postcode":"30005",
    "addr:street":"Old Milton Pkwy",
    "iso:country":"US",
    "sg:address":"4045 Old Milton Pkwy",
    "sg:city":"Alpharetta",
    "sg:classifiers":[
        {
            "category":"Food & Beverages",
            "subcategory":"Liquor & Beverages",
            "type":"Retail Goods"
        }
    ],
    "sg:phone":"+1 678 393 8988",
    "sg:postcode":"30005",
    "sg:province":"GA",
    "sg:tags":[
        "beer",
        "spirit",
        "wine"
    ],
    "wof:name":"Old Milton Beverage",
    "wof:placetype":"venue"
},
  "geometry": {"coordinates":[-84.24364199999999,34.060814],"type":"Point"}
}