{
  "type": "Feature",
  "properties": {
    "addr:full":"2575 Snapfinger Rd Decatur GA 30034",
    "addr:housenumber":"2575",
    "addr:postcode":"30034",
    "addr:street":"Snapfinger Rd",
    "iso:country":"US",
    "sg:address":"2575 Snapfinger Rd",
    "sg:city":"Decatur",
    "sg:classifiers":[
        {
            "category":"Restaurant",
            "type":"Food & Drink"
        }
    ],
    "sg:phone":"+1 770 987 2111",
    "sg:postcode":"30034",
    "sg:province":"GA",
    "wof:name":"Wingin It",
    "wof:placetype":"venue"
},
  "geometry": {"coordinates":[-84.214996,33.7048],"type":"Point"}
}