{
  "type": "Feature",
  "properties": {
    "addr:full":"475 Saddlebrook Dr Roswell GA 30075",
    "addr:housenumber":"475",
    "addr:postcode":"30075",
    "addr:street":"Saddlebrook Dr",
    "iso:country":"US",
    "sg:address":"475 Saddlebrook Dr",
    "sg:city":"Roswell",
    "sg:classifiers":[
        {
            "category":"Communications",
            "subcategory":"Film & Video Production",
            "type":"Services"
        }
    ],
    "sg:phone":"+1 770 650 0743",
    "sg:postcode":"30075",
    "sg:province":"GA",
    "sg:tags":[
        "motion"
    ],
    "wof:name":"Sayla Productions Intl",
    "wof:placetype":"venue"
},
  "geometry": {"coordinates":[-84.362218,34.068566],"type":"Point"}
}