{
  "type": "Feature",
  "properties": {
    "addr:full":"28 Wolfpen Pass NE White GA 30184",
    "addr:housenumber":"28",
    "addr:postcode":"30184",
    "addr:street":"Wolfpen Pass Ne",
    "iso:country":"US",
    "sg:address":"28 Wolfpen Pass NE",
    "sg:city":"White",
    "sg:classifiers":[
        {
            "category":"Building & Trades",
            "subcategory":"Construction",
            "type":"Services"
        }
    ],
    "sg:phone":"+1 770 386 8567",
    "sg:postcode":"30184",
    "sg:province":"GA",
    "sg:tags":[
        "house"
    ],
    "wof:name":"Jordan Construction Co",
    "wof:placetype":"venue"
},
  "geometry": {"coordinates":[-84.73869999999999,34.232578],"type":"Point"}
}