{
  "type": "Feature",
  "properties": {
    "iso:country":"US",
    "sg:address":"312 1st St SW",
    "sg:city":"Moultrie",
    "sg:classifiers":[
        {
            "category":"Professional",
            "type":"Services"
        }
    ],
    "sg:phone":"+1 229 891 3159",
    "sg:postcode":"31768",
    "sg:province":"GA",
    "sg:tags":[
        "establishment"
    ],
    "wof:name":"Gaint Yshaka",
    "wof:placetype":"venue"
},
  "geometry": {"coordinates":[-83.79015099999999,31.176799],"type":"Point"}
}