{
  "type": "Feature",
  "properties": {
    "addr:full":"3195 Barnett Shoals Rd Athens GA 30605",
    "addr:housenumber":"3195",
    "addr:postcode":"30605",
    "addr:street":"Barnett Shoals Rd",
    "iso:country":"US",
    "sg:address":"3195 Barnett Shoals Rd",
    "sg:city":"Athens",
    "sg:classifiers":[
        {
            "category":"Organizations",
            "subcategory":"Religious Organization",
            "type":"Services"
        }
    ],
    "sg:phone":"+1 706 546 7553",
    "sg:postcode":"30605",
    "sg:province":"GA",
    "sg:tags":[
        "episcopal",
        "church"
    ],
    "wof:name":"Episcpal Prtestent Church Amer",
    "wof:placetype":"venue"
},
  "geometry": {"coordinates":[-83.334942,33.898891],"type":"Point"}
}