{
  "type": "Feature",
  "properties": {
    "iso:country":"US",
    "sg:address":"2100 Mc Gee Rd SW",
    "sg:city":"Snellville",
    "sg:classifiers":[
        {
            "category":"Insurance",
            "subcategory":"Insurance Agent",
            "type":"Services"
        }
    ],
    "sg:phone":"+1 770 979 0030",
    "sg:postcode":"30078",
    "sg:province":"GA",
    "wof:name":"Charles Dorman Insurance",
    "wof:placetype":"venue"
},
  "geometry": {"coordinates":[-84.035624,33.856684],"type":"Point"}
}