{
  "type": "Feature",
  "properties": {
    "addr:full":"1696 Connally Dr Atlanta GA 30344",
    "addr:housenumber":"1696",
    "addr:postcode":"30344",
    "addr:street":"Connally Dr",
    "iso:country":"US",
    "sg:address":"1696 Connally Dr",
    "sg:city":"Atlanta",
    "sg:classifiers":[
        {
            "category":"Autos & Motor Vehicles",
            "subcategory":"Auto Supplies",
            "type":"Retail Goods"
        }
    ],
    "sg:phone":"+1 404 763 2953",
    "sg:postcode":"30344",
    "sg:province":"GA",
    "wof:name":"Byrd Heating and AC",
    "wof:placetype":"venue"
},
  "geometry": {"coordinates":[-84.44485899999999,33.688471],"type":"Point"}
}