{
  "type": "Feature",
  "properties": {
    "addr:full":"140 Greenwood Rd Mc Donough GA 30253",
    "addr:housenumber":"140",
    "addr:postcode":"30253",
    "addr:street":"Greenwood Rd",
    "iso:country":"US",
    "sg:address":"140 Greenwood Rd",
    "sg:city":"Mc Donough",
    "sg:classifiers":[
        {
            "category":"Freight",
            "type":"Transportation"
        }
    ],
    "sg:phone":"+1 678 583 0686",
    "sg:postcode":"30253",
    "sg:province":"GA",
    "sg:tags":[
        "warehousing"
    ],
    "wof:name":"DSC Logistics Inc",
    "wof:placetype":"venue"
},
  "geometry": {"coordinates":[-84.18987300000001,33.427273],"type":"Point"}
}