{
  "type": "Feature",
  "properties": {
    "addr:full":"4753 Jennifer Ct Monroe GA 30656",
    "addr:housenumber":"4753",
    "addr:postcode":"30656",
    "addr:street":"Jennifer Ct",
    "iso:country":"US",
    "sg:address":"4753 Jennifer Ct",
    "sg:city":"Monroe",
    "sg:classifiers":[
        {
            "category":"Wholesale",
            "subcategory":"Plants",
            "type":"Manufacturing & Wholesale Goods"
        }
    ],
    "sg:phone":"+1 770 207 6649",
    "sg:postcode":"30656",
    "sg:province":"GA",
    "sg:tags":[
        "trees-silk",
        "flowers",
        "etc-wholesale",
        "dried"
    ],
    "wof:name":"Connie Y Mauldin",
    "wof:placetype":"venue"
},
  "geometry": {"coordinates":[-83.810698,33.888888],"type":"Point"}
}