{
  "type": "Feature",
  "properties": {
    "addr:full":"2254 Baywood Dr SE Atlanta GA 30315",
    "addr:housenumber":"2254",
    "addr:postcode":"30315",
    "addr:street":"Baywood Dr Se",
    "iso:country":"US",
    "sg:address":"2254 Baywood Dr SE",
    "sg:city":"Atlanta",
    "sg:classifiers":[
        {
            "category":"Professional",
            "subcategory":"Management & Consulting",
            "type":"Services"
        }
    ],
    "sg:phone":"+1 404 748 0002",
    "sg:postcode":"30315",
    "sg:province":"GA",
    "sg:tags":[
        "consultant"
    ],
    "wof:name":"Strategic Solutions Consltng",
    "wof:placetype":"venue"
},
  "geometry": {"coordinates":[-84.387501,33.692303],"type":"Point"}
}