{
  "type": "Feature",
  "properties": {
    "addr:full":"1260 Killian Shoals Way SW Lilburn GA 30047",
    "addr:housenumber":"1260",
    "addr:postcode":"30047",
    "addr:street":"Killian Shoals Way Sw",
    "iso:country":"US",
    "sg:address":"1260 Killian Shoals Way SW",
    "sg:city":"Lilburn",
    "sg:classifiers":[
        {
            "category":"Professional",
            "subcategory":"Computer Services",
            "type":"Services"
        }
    ],
    "sg:phone":"+1 770 931 3538",
    "sg:postcode":"30047",
    "sg:province":"GA",
    "sg:tags":[
        "programing",
        "custom"
    ],
    "wof:name":"Azeem Technologies Inc",
    "wof:placetype":"venue"
},
  "geometry": {"coordinates":[-84.08411,33.864224],"type":"Point"}
}