{
  "type": "Feature",
  "properties": {
    "iso:country":"US",
    "sg:address":"1650 Austell Rd SW",
    "sg:city":"Marietta",
    "sg:classifiers":[
        {
            "category":"Building & Trades",
            "subcategory":"Construction",
            "type":"Services"
        }
    ],
    "sg:phone":"+1 770 218 0812",
    "sg:postcode":"30008",
    "sg:province":"GA",
    "sg:tags":[
        "contractor"
    ],
    "wof:name":"Walton Construction Services",
    "wof:placetype":"venue"
},
  "geometry": {"coordinates":[-84.55523100000001,33.913679],"type":"Point"}
}