{
  "type": "Feature",
  "properties": {
    "iso:country":"US",
    "sg:address":"6934 Highway 106 S",
    "sg:city":"Hull",
    "sg:classifiers":[
        {
            "category":"Farming",
            "subcategory":"Farm",
            "type":"Manufacturing & Wholesale Goods"
        }
    ],
    "sg:phone":"+1 706 548 2877",
    "sg:postcode":"30646",
    "sg:province":"GA",
    "wof:name":"Billy Faulkner Farm Epuip Co",
    "wof:placetype":"venue"
},
  "geometry": {"coordinates":[-83.31843600000001,34.06585],"type":"Point"}
}