{
  "type": "Feature",
  "properties": {
    "iso:country":"US",
    "sg:address":"1214 N Peterson Ave",
    "sg:city":"Douglas",
    "sg:classifiers":[
        {
            "category":"Recreation",
            "type":"Entertainment"
        }
    ],
    "sg:phone":"+1 912 384 5425",
    "sg:postcode":"31533",
    "sg:province":"GA",
    "sg:tags":[
        "martial",
        "arts",
        "instruction"
    ],
    "wof:name":"Douglas Tang Soo Do Academy",
    "wof:placetype":"venue"
},
  "geometry": {"coordinates":[-82.850418,31.522793],"type":"Point"}
}