{
  "type": "Feature",
  "properties": {
    "addr:full":"4126 Rocky Ford Rd Sylvania GA 30467",
    "addr:housenumber":"4126",
    "addr:postcode":"30467",
    "addr:street":"Rocky Ford Rd",
    "iso:country":"US",
    "sg:address":"4126 Rocky Ford Rd",
    "sg:city":"Sylvania",
    "sg:classifiers":[
        {
            "category":"Organizations",
            "subcategory":"Religious Organization",
            "type":"Services"
        }
    ],
    "sg:phone":"+1 912 863 7209",
    "sg:postcode":"30467",
    "sg:province":"GA",
    "sg:tags":[
        "church"
    ],
    "wof:name":"New Life Christian Fellowship",
    "wof:placetype":"venue"
},
  "geometry": {"coordinates":[-81.764416,32.739614],"type":"Point"}
}