{
  "type": "Feature",
  "properties": {
    "addr:full":"3 Central Plz Rome GA 30161",
    "addr:housenumber":"3",
    "addr:postcode":"ga 30161",
    "addr:street":"Central Plz",
    "iso:country":"US",
    "sg:address":"3 Central Plz",
    "sg:city":"Rome",
    "sg:classifiers":[
        {
            "category":"Sports & Exercise",
            "subcategory":"Gym",
            "type":"Entertainment"
        }
    ],
    "sg:phone":"+1 706 506 3932",
    "sg:postcode":"30161",
    "sg:province":"GA",
    "sg:tags":[
        "fitness",
        "physical",
        "facility"
    ],
    "wof:name":"Curves For Women",
    "wof:placetype":"venue"
},
  "geometry": {"coordinates":[-85.16922099999999,34.246885],"type":"Point"}
}