{
  "type": "Feature",
  "properties": {
    "addr:full":"1757 Gordon Hwy Augusta GA 30904",
    "addr:housenumber":"1757",
    "addr:postcode":"30904",
    "addr:street":"Gordon Hwy",
    "iso:country":"US",
    "sg:address":"1757 Gordon Hwy",
    "sg:city":"Augusta",
    "sg:classifiers":[
        {
            "category":"Banks & Credit Unions",
            "subcategory":"Bank",
            "type":"Services"
        }
    ],
    "sg:phone":"+1 706 737 2889",
    "sg:postcode":"30904",
    "sg:province":"GA",
    "sg:tags":[
        "personal",
        "institution"
    ],
    "wof:name":"Advance America",
    "wof:placetype":"venue"
},
  "geometry": {"coordinates":[-82.028171,33.441626],"type":"Point"}
}