{
  "type": "Feature",
  "properties": {
    "addr:full":"1077 Parkway Dr Macon GA 31220",
    "addr:housenumber":"1077",
    "addr:postcode":"31220",
    "addr:street":"Parkway Dr",
    "iso:country":"US",
    "sg:address":"1077 Parkway Dr",
    "sg:city":"Macon",
    "sg:classifiers":[
        {
            "category":"Wholesale",
            "subcategory":"Machinery & Supplies",
            "type":"Manufacturing & Wholesale Goods"
        }
    ],
    "sg:phone":"+1 478 477 7095",
    "sg:postcode":"31220",
    "sg:province":"GA",
    "sg:tags":[
        "aircraft",
        "parts"
    ],
    "wof:name":"B & M Aircraft Parts LLC",
    "wof:placetype":"venue"
},
  "geometry": {"coordinates":[-83.736256,32.829376],"type":"Point"}
}