{
  "type": "Feature",
  "properties": {
    "addr:full":"4526 High Grove Ct Acworth GA 30102",
    "addr:housenumber":"4526",
    "addr:postcode":"30102",
    "addr:street":"High Grove Ct",
    "iso:country":"US",
    "sg:address":"4526 High Grove Ct",
    "sg:city":"Acworth",
    "sg:classifiers":[
        {
            "category":"Professional",
            "subcategory":"Accounting & Tax Preparation",
            "type":"Services"
        }
    ],
    "sg:phone":"+1 770 428 6140",
    "sg:postcode":"30102",
    "sg:province":"GA",
    "sg:tags":[
        "consultant",
        "return"
    ],
    "wof:name":"Optimum Consulting & Tax Servi",
    "wof:placetype":"venue"
},
  "geometry": {"coordinates":[-84.598842,34.06373],"type":"Point"}
}