{
  "type": "Feature",
  "properties": {
    "addr:full":"3541 Montgomery Dr Gainesville GA 30504",
    "addr:housenumber":"3541",
    "addr:postcode":"30504",
    "addr:street":"Montgomery Dr",
    "iso:country":"US",
    "sg:address":"3541 Montgomery Dr",
    "sg:city":"Gainesville",
    "sg:classifiers":[
        {
            "category":"Building & Trades",
            "subcategory":"Construction",
            "type":"Services"
        }
    ],
    "sg:phone":"+1 770 534 0689",
    "sg:postcode":"30504",
    "sg:province":"GA",
    "sg:tags":[
        "consultant",
        "management"
    ],
    "wof:name":"Cbc Church Seating, Inc",
    "wof:placetype":"venue"
},
  "geometry": {"coordinates":[-83.89357800000001,34.267811],"type":"Point"}
}