{
  "type": "Feature",
  "properties": {
    "iso:country":"US",
    "sg:address":"5374 Whitehall Pl",
    "sg:city":"Mableton",
    "sg:classifiers":[
        {
            "category":"Professional",
            "subcategory":"Advertising",
            "type":"Services"
        }
    ],
    "sg:phone":"+1 770 819 9748",
    "sg:postcode":"30126",
    "sg:province":"GA",
    "wof:name":"Foodcrafter",
    "wof:placetype":"venue"
},
  "geometry": {"coordinates":[-84.547873,33.823207],"type":"Point"}
}