{
  "type": "Feature",
  "properties": {
    "addr:full":"638 Goldenwood Ct Powder Springs GA 30127",
    "addr:housenumber":"638",
    "addr:postcode":"30127",
    "addr:street":"Goldenwood Ct",
    "iso:country":"US",
    "sg:address":"638 Goldenwood Ct",
    "sg:city":"Powder Springs",
    "sg:classifiers":[
        {
            "category":"Social Services",
            "subcategory":"Child Care",
            "type":"Services"
        }
    ],
    "sg:phone":"+1 770 423 9775",
    "sg:postcode":"30127",
    "sg:province":"GA",
    "sg:tags":[
        "day"
    ],
    "wof:name":"Goals To Grow Therapy",
    "wof:placetype":"venue"
},
  "geometry": {"coordinates":[-84.687938,33.937576],"type":"Point"}
}