{
  "type": "Feature",
  "properties": {
    "addr:full":"3663 Community Rd Brunswick GA 31520",
    "addr:housenumber":"3663",
    "addr:postcode":"31520",
    "addr:street":"Community Rd",
    "iso:country":"US",
    "sg:address":"3663 Community Rd",
    "sg:city":"Brunswick",
    "sg:classifiers":[
        {
            "category":"Autos & Motor Vehicles",
            "subcategory":"Boat Sales",
            "type":"Retail Goods"
        }
    ],
    "sg:phone":"+1 912 264 0150",
    "sg:postcode":"31520",
    "sg:province":"GA",
    "sg:tags":[
        "repair"
    ],
    "wof:name":"Atlantic Marine",
    "wof:placetype":"venue"
},
  "geometry": {"coordinates":[-81.496814,31.203088],"type":"Point"}
}