{
  "type": "Feature",
  "properties": {
    "addr:full":"1303 W Gordon Ave Albany GA 31707",
    "addr:housenumber":"1303",
    "addr:postcode":"31707",
    "addr:street":"W Gordon Ave",
    "iso:country":"US",
    "sg:address":"1303 W Gordon Ave",
    "sg:city":"Albany",
    "sg:classifiers":[
        {
            "category":"Building & Trades",
            "subcategory":"Landscaping Services",
            "type":"Services"
        }
    ],
    "sg:phone":"+1 229 446 8669",
    "sg:postcode":"31707",
    "sg:province":"GA",
    "wof:name":"W C Lawn Care",
    "wof:placetype":"venue"
},
  "geometry": {"coordinates":[-84.183564,31.568107],"type":"Point"}
}