{
  "type": "Feature",
  "properties": {
    "addr:full":"496 Crosstown Rd Peachtree City GA 30269",
    "addr:housenumber":"496",
    "addr:postcode":"30269",
    "addr:street":"Crosstown Rd",
    "iso:country":"US",
    "sg:address":"496 Crosstown Rd",
    "sg:city":"Peachtree City",
    "sg:classifiers":[
        {
            "category":"Banks & Credit Unions",
            "subcategory":"Bank",
            "type":"Services"
        }
    ],
    "sg:phone":"+1 770 631 3224",
    "sg:postcode":"30269",
    "sg:province":"GA",
    "sg:tags":[
        "federal",
        "savings",
        "institution"
    ],
    "wof:name":"Bank Of America",
    "wof:placetype":"venue"
},
  "geometry": {"coordinates":[-84.55588299999999,33.377779],"type":"Point"}
}