{
  "type": "Feature",
  "properties": {
    "iso:country":"US",
    "sg:address":"5898 Hwy 20 SE",
    "sg:city":"Cartersville",
    "sg:classifiers":[
        {
            "category":"Professional",
            "subcategory":"Engineering",
            "type":"Services"
        }
    ],
    "sg:phone":"+1 770 606 1789",
    "sg:postcode":"30121",
    "sg:province":"GA",
    "wof:name":"Jenkins Planning Ltd",
    "wof:placetype":"venue"
},
  "geometry": {"coordinates":[-84.725859,34.220064],"type":"Point"}
}