{
  "type": "Feature",
  "properties": {
    "addr:full":"711 Fulton Ter SE Atlanta GA 30316",
    "addr:housenumber":"711",
    "addr:postcode":"30316",
    "addr:street":"Fulton Ter Se",
    "iso:country":"US",
    "sg:address":"711 Fulton Ter SE",
    "sg:city":"Atlanta",
    "sg:classifiers":[
        {
            "category":"Banks & Credit Unions",
            "subcategory":"Bank",
            "type":"Services"
        },
        {
            "category":"Banks & Credit Unions",
            "subcategory":"Financial Services",
            "type":"Services"
        }
    ],
    "sg:phone":"+1 404 699 3990",
    "sg:postcode":"30316",
    "sg:province":"GA",
    "sg:tags":[
        "saving",
        "loan",
        "commercial"
    ],
    "sg:website":"http://www.suntrustbank.com",
    "wof:name":"SunTrust Bank",
    "wof:placetype":"venue"
},
  "geometry": {"coordinates":[-84.36217499999999,33.748626],"type":"Point"}
}