{
  "type": "Feature",
  "properties": {
    "iso:country":"US",
    "sg:address":"312 E Lake Ave",
    "sg:city":"Rossville",
    "sg:classifiers":[
        {
            "category":"Health Services",
            "subcategory":"Doctor",
            "type":"Services"
        }
    ],
    "sg:phone":"+1 706 861 1446",
    "sg:postcode":"30741",
    "sg:province":"GA",
    "sg:tags":[
        "medical"
    ],
    "wof:name":"Rossville Physical Therapy Ctr",
    "wof:placetype":"venue"
},
  "geometry": {"coordinates":[-85.28439899999999,34.98171],"type":"Point"}
}