{
  "type": "Feature",
  "properties": {
    "iso:country":"US",
    "sg:address":"44 Barber Dr",
    "sg:city":"Villa Rica",
    "sg:classifiers":[
        {
            "category":"Organizations",
            "subcategory":"Religious Organization",
            "type":"Services"
        }
    ],
    "sg:phone":"+1 770 459 5352",
    "sg:postcode":"30180",
    "sg:province":"GA",
    "wof:name":"Bud Wix Rev",
    "wof:placetype":"venue"
},
  "geometry": {"coordinates":[-84.904578,33.749826],"type":"Point"}
}