{
  "type": "Feature",
  "properties": {
    "addr:full":"1054 Hopewell Rd Cohutta GA 30710",
    "addr:housenumber":"1054",
    "addr:postcode":"30710",
    "addr:street":"Hopewell Rd",
    "iso:country":"US",
    "sg:address":"1054 Hopewell Rd",
    "sg:city":"Cohutta",
    "sg:classifiers":[
        {
            "category":"Organizations",
            "subcategory":"Religious Organization",
            "type":"Services"
        }
    ],
    "sg:phone":"+1 706 694 8618",
    "sg:postcode":"30710",
    "sg:province":"GA",
    "wof:name":"Concord Baptist Church",
    "wof:placetype":"venue"
},
  "geometry": {"coordinates":[-84.89472000000001,34.95148],"type":"Point"}
}