{
  "type": "Feature",
  "properties": {
    "iso:country":"US",
    "sg:address":"730 Concord Rd SE",
    "sg:city":"Smyrna",
    "sg:phone":"+1 770 434 2432",
    "sg:postcode":"30082",
    "sg:province":"GA",
    "wof:name":"Timbers",
    "wof:placetype":"venue"
},
  "geometry": {"coordinates":[-84.53268,33.872711],"type":"Point"}
}