{
  "type": "Feature",
  "properties": {
    "iso:country":"US",
    "sg:address":"2044 Lower Roswell Rd Ste 300",
    "sg:city":"Marietta",
    "sg:classifiers":[
        {
            "category":"Food & Beverages",
            "subcategory":"Bakery",
            "type":"Retail Goods"
        }
    ],
    "sg:phone":"+1 678 560 3332",
    "sg:postcode":"30068",
    "sg:province":"GA",
    "sg:tags":[
        "sandwich"
    ],
    "sg:website":"www.subway.com",
    "wof:name":"Subway",
    "wof:placetype":"venue"
},
  "geometry": {"coordinates":[-84.49260700000001,33.949228],"type":"Point"}
}