{
  "type": "Feature",
  "properties": {
    "addr:full":"1850 N Columbia St Milledgeville GA 31061",
    "addr:housenumber":"1850",
    "addr:postcode":"31061",
    "addr:street":"N Columbia St",
    "iso:country":"US",
    "sg:address":"1850 N Columbia St",
    "sg:city":"Milledgeville",
    "sg:classifiers":[
        {
            "category":"Shopping",
            "subcategory":"Bicycles & Sporting Goods",
            "type":"Retail Goods"
        }
    ],
    "sg:phone":"+1 478 454 2280",
    "sg:postcode":"31061",
    "sg:province":"GA",
    "sg:tags":[
        "shoes"
    ],
    "wof:name":"Hibbett Sports",
    "wof:placetype":"venue"
},
  "geometry": {"coordinates":[-83.252543,33.106619],"type":"Point"}
}