{
  "type": "Feature",
  "properties": {
    "iso:country":"US",
    "sg:address":"6220 Westchester Pl",
    "sg:city":"Cumming",
    "sg:classifiers":[
        {
            "category":"Banks & Credit Unions",
            "subcategory":"Financial Services",
            "type":"Services"
        }
    ],
    "sg:phone":"+1 770 889 7322",
    "sg:postcode":"30040",
    "sg:province":"GA",
    "sg:tags":[
        "investor"
    ],
    "wof:name":"Westchester Investment Inc",
    "wof:placetype":"venue"
},
  "geometry": {"coordinates":[-84.20608300000001,34.183882],"type":"Point"}
}