{
  "type": "Feature",
  "properties": {
    "iso:country":"US",
    "sg:address":"914 Kite Lake Trl",
    "sg:city":"Fairburn",
    "sg:classifiers":[
        {
            "category":"Professional",
            "type":"Services"
        }
    ],
    "sg:phone":"+1 770 306 0415",
    "sg:postcode":"30213",
    "sg:province":"GA",
    "wof:name":"Burgess Creative Concepts",
    "wof:placetype":"venue"
},
  "geometry": {"coordinates":[-84.485113,33.52594],"type":"Point"}
}