{
  "type": "Feature",
  "properties": {
    "addr:full":"20 Riverbend Dr Rome GA 30161",
    "addr:housenumber":"20",
    "addr:postcode":"ga 30161",
    "addr:street":"Riverbend Dr",
    "iso:country":"US",
    "sg:address":"20 Riverbend Dr",
    "sg:city":"Rome",
    "sg:classifiers":[
        {
            "category":"Health Services",
            "subcategory":"Doctor",
            "type":"Services"
        }
    ],
    "sg:phone":"+1 706 291 4151",
    "sg:postcode":"30161",
    "sg:province":"GA",
    "sg:tags":[
        "clinic"
    ],
    "wof:name":"Coosa Clinics Inc",
    "wof:placetype":"venue"
},
  "geometry": {"coordinates":[-85.164051,34.251934],"type":"Point"}
}