{
  "type": "Feature",
  "properties": {
    "addr:full":"328 E McCarty St Sandersville GA 31082",
    "addr:housenumber":"328",
    "addr:postcode":"31082",
    "addr:street":"E Mccarty St",
    "iso:country":"US",
    "sg:address":"328 E McCarty St",
    "sg:city":"Sandersville",
    "sg:classifiers":[
        {
            "category":"Insurance",
            "subcategory":"Insurance Agent",
            "type":"Services"
        }
    ],
    "sg:phone":"+1 478 552 1142",
    "sg:postcode":"31082",
    "sg:province":"GA",
    "wof:name":"Black's Insurance",
    "wof:placetype":"venue"
},
  "geometry": {"coordinates":[-82.806629,32.988618],"type":"Point"}
}