{
  "type": "Feature",
  "properties": {
    "iso:country":"US",
    "sg:address":"10800 Alpharetta Hwy",
    "sg:city":"Roswell",
    "sg:classifiers":[
        {
            "category":"Shopping",
            "subcategory":"Tobacco",
            "type":"Retail Goods"
        }
    ],
    "sg:phone":"+1 770 642 1221",
    "sg:postcode":"30076",
    "sg:province":"GA",
    "sg:tags":[
        "cigarette",
        "cigar",
        "dealer"
    ],
    "wof:name":"Cigar Merchant",
    "wof:placetype":"venue"
},
  "geometry": {"coordinates":[-84.33456,34.051852],"type":"Point"}
}