{
  "type": "Feature",
  "properties": {
    "iso:country":"US",
    "sg:address":"3326 S Dixie Rd",
    "sg:city":"Dalton",
    "sg:classifiers":[
        {
            "category":"Home & Garden",
            "subcategory":"Carpets & Floor Coverings",
            "type":"Retail Goods"
        }
    ],
    "sg:phone":"+1 706 428 9248",
    "sg:postcode":"30720",
    "sg:province":"GA",
    "sg:tags":[
        "dealer",
        "rug"
    ],
    "wof:name":"Rug Source",
    "wof:placetype":"venue"
},
  "geometry": {"coordinates":[-84.985466,34.70228],"type":"Point"}
}