{
  "type": "Feature",
  "properties": {
    "addr:full":"350 Franklin Rd SE Ste 350 Marietta GA 30067",
    "addr:housenumber":"350",
    "addr:postcode":"30067",
    "addr:street":"Franklin Rd Se Ste 350",
    "iso:country":"US",
    "sg:address":"350 Franklin Rd SE Ste 350",
    "sg:city":"Marietta",
    "sg:classifiers":[
        {
            "category":"Building & Trades",
            "subcategory":"Construction",
            "type":"Services"
        }
    ],
    "sg:phone":"+1 770 421 1532",
    "sg:postcode":"30067",
    "sg:province":"GA",
    "sg:tags":[
        "contractor"
    ],
    "wof:name":"Kda Holdings Inc",
    "wof:placetype":"venue"
},
  "geometry": {"coordinates":[-84.51081600000001,33.944232],"type":"Point"}
}