{
  "type": "Feature",
  "properties": {
    "iso:country":"US",
    "sg:address":"2355 Cumberland Parkway SE",
    "sg:city":"Atlanta",
    "sg:classifiers":[
        {
            "category":"Personal",
            "subcategory":"Nail Salon",
            "type":"Services"
        }
    ],
    "sg:phone":"+1 770 431 9666",
    "sg:postcode":"30339",
    "sg:province":"GA",
    "wof:name":"Vinings Nails",
    "wof:placetype":"venue"
},
  "geometry": {"coordinates":[-84.480321,33.859064],"type":"Point"}
}