{
  "type": "Feature",
  "properties": {
    "addr:full":"3290 Minuit Ct Loganville GA 30052",
    "addr:housenumber":"3290",
    "addr:postcode":"30052",
    "addr:street":"Minuit Ct",
    "iso:country":"US",
    "sg:address":"3290 Minuit Ct",
    "sg:city":"Loganville",
    "sg:classifiers":[
        {
            "category":"Professional",
            "type":"Services"
        }
    ],
    "sg:phone":"+1 770 466 8207",
    "sg:postcode":"30052",
    "sg:province":"GA",
    "wof:name":"Doug Switzer",
    "wof:placetype":"venue"
},
  "geometry": {"coordinates":[-83.912802,33.871402],"type":"Point"}
}