{
  "type": "Feature",
  "properties": {
    "iso:country":"US",
    "sg:address":"4275 Matt Hwy",
    "sg:city":"Cumming",
    "sg:classifiers":[
        {
            "category":"Freight",
            "type":"Transportation"
        }
    ],
    "sg:phone":"+1 770 781 5964",
    "sg:postcode":"30040",
    "sg:province":"GA",
    "sg:tags":[
        "operator",
        "trucking"
    ],
    "wof:name":"Nelson L Bennett Trucking Inc",
    "wof:placetype":"venue"
},
  "geometry": {"coordinates":[-84.125282,34.283985],"type":"Point"}
}