{
  "type": "Feature",
  "properties": {
    "addr:full":"1928 Albany Ave Waycross GA 31503",
    "addr:housenumber":"1928",
    "addr:postcode":"31503",
    "addr:street":"Albany Ave",
    "iso:country":"US",
    "sg:address":"1928 Albany Ave",
    "sg:city":"Waycross",
    "sg:classifiers":[
        {
            "category":"Wholesale",
            "subcategory":"Motor Vehicles",
            "type":"Manufacturing & Wholesale Goods"
        }
    ],
    "sg:phone":"+1 912 287 0711",
    "sg:postcode":"31503",
    "sg:province":"GA",
    "wof:name":"Waycross Auto Brokers",
    "wof:placetype":"venue"
},
  "geometry": {"coordinates":[-82.387777,31.223685],"type":"Point"}
}