{
  "type": "Feature",
  "properties": {
    "addr:full":"1011 Underwood St Dalton GA 30721",
    "addr:housenumber":"1011",
    "addr:postcode":"30721",
    "addr:street":"Underwood St",
    "iso:country":"US",
    "sg:address":"1011 Underwood St",
    "sg:city":"Dalton",
    "sg:classifiers":[
        {
            "category":"Place Of Worship",
            "subcategory":"Church",
            "type":"Public Place"
        },
        {
            "category":"Place Of Worship",
            "type":"Public Place"
        },
        {
            "category":"Organizations",
            "subcategory":"Religious Organization",
            "type":"Services"
        }
    ],
    "sg:phone":"+1 706 271 0293",
    "sg:postcode":"30721",
    "sg:province":"GA",
    "sg:tags":[
        "god",
        "churches-church",
        "churches-pentecostal"
    ],
    "wof:name":"Harbor House",
    "wof:placetype":"venue"
},
  "geometry": {"coordinates":[-84.95181700000001,34.779101],"type":"Point"}
}