{
  "type": "Feature",
  "properties": {
    "addr:full":"14345 Wyndham Farms Dr Alpharetta GA 30004",
    "addr:housenumber":"14345",
    "addr:postcode":"30004",
    "addr:street":"Wyndham Farms Dr",
    "iso:country":"US",
    "sg:address":"14345 Wyndham Farms Dr",
    "sg:city":"Alpharetta",
    "sg:classifiers":[
        {
            "category":"Professional",
            "type":"Services"
        }
    ],
    "sg:phone":"+1 678 297 0030",
    "sg:postcode":"30004",
    "sg:province":"GA",
    "sg:tags":[
        "establishment"
    ],
    "wof:name":"Saic",
    "wof:placetype":"venue"
},
  "geometry": {"coordinates":[-84.282034,34.12721],"type":"Point"}
}