{
  "type": "Feature",
  "properties": {
    "iso:country":"US",
    "sg:address":"934 Pine Cir",
    "sg:city":"Woodstock",
    "sg:classifiers":[
        {
            "category":"Manufacturing",
            "subcategory":"Printing",
            "type":"Manufacturing & Wholesale Goods"
        }
    ],
    "sg:phone":"+1 770 516 3479",
    "sg:postcode":"30189",
    "sg:province":"GA",
    "sg:tags":[
        "lithographic",
        "commercial"
    ],
    "wof:name":"Print Production Management",
    "wof:placetype":"venue"
},
  "geometry": {"coordinates":[-84.605172,34.136291],"type":"Point"}
}