{
  "type": "Feature",
  "properties": {
    "addr:full":"7905 Saddle Ridge Dr Atlanta GA 30350",
    "addr:housenumber":"7905",
    "addr:postcode":"30350",
    "addr:street":"Saddle Ridge Dr",
    "iso:country":"US",
    "sg:address":"7905 Saddle Ridge Dr",
    "sg:city":"Atlanta",
    "sg:classifiers":[
        {
            "category":"Professional",
            "subcategory":"Management & Consulting",
            "type":"Services"
        }
    ],
    "sg:phone":"+1 770 393 4939",
    "sg:postcode":"30350",
    "sg:province":"GA",
    "wof:name":"Infradyn Inc",
    "wof:placetype":"venue"
},
  "geometry": {"coordinates":[-84.32053999999999,33.971732],"type":"Point"}
}