{
  "type": "Feature",
  "properties": {
    "addr:full":"510 Mount Pleasant Rd Hampton GA 30228",
    "addr:housenumber":"510",
    "addr:postcode":"30228",
    "addr:street":"Mount Pleasant Rd",
    "iso:country":"US",
    "sg:address":"510 Mount Pleasant Rd",
    "sg:city":"Hampton",
    "sg:classifiers":[
        {
            "category":"Professional",
            "subcategory":"Business Services",
            "type":"Services"
        }
    ],
    "sg:phone":"+1 770 946 8888",
    "sg:postcode":"30228",
    "sg:province":"GA",
    "wof:name":"Rbs Aviation Group Inc",
    "wof:placetype":"venue"
},
  "geometry": {"coordinates":[-84.32342300000001,33.395069],"type":"Point"}
}