{
  "type": "Feature",
  "properties": {
    "iso:country":"US",
    "sg:address":"6227 Columbia Rd",
    "sg:city":"Appling",
    "sg:classifiers":[
        {
            "category":"Organizations",
            "subcategory":"Religious Organization",
            "type":"Services"
        }
    ],
    "sg:phone":"+1 706 541 0892",
    "sg:postcode":"30802",
    "sg:province":"GA",
    "wof:name":"Olive Grove Baptist Church",
    "wof:placetype":"venue"
},
  "geometry": {"coordinates":[-82.28478200000001,33.530138],"type":"Point"}
}