{
  "type": "Feature",
  "properties": {
    "addr:full":"3000 Trotters Pkwy Alpharetta GA 30004",
    "addr:housenumber":"3000",
    "addr:postcode":"30004",
    "addr:street":"Trotters Pkwy",
    "iso:country":"US",
    "sg:address":"3000 Trotters Pkwy",
    "sg:city":"Alpharetta",
    "sg:classifiers":[
        {
            "category":"Wholesale",
            "subcategory":"Machinery & Supplies",
            "type":"Manufacturing & Wholesale Goods"
        },
        {
            "category":"Wholesale",
            "subcategory":"Farm Supplies",
            "type":"Manufacturing & Wholesale Goods"
        }
    ],
    "sg:phone":"+1 770 475 4403",
    "sg:postcode":"30004",
    "sg:province":"GA",
    "sg:tags":[
        "fertilizer"
    ],
    "wof:name":"Lesco Service Center",
    "wof:placetype":"venue"
},
  "geometry": {"coordinates":[-84.22801200000001,34.126792],"type":"Point"}
}