{
  "type": "Feature",
  "properties": {
    "iso:country":"US",
    "sg:address":"474 S Deshon Rd",
    "sg:city":"Lithonia",
    "sg:classifiers":[
        {
            "category":"Social Services",
            "subcategory":"Child Care",
            "type":"Services"
        }
    ],
    "sg:phone":"+1 770 879 2021",
    "sg:postcode":"30058",
    "sg:province":"GA",
    "sg:tags":[
        "day"
    ],
    "wof:name":"Chestnut Treehouse",
    "wof:placetype":"venue"
},
  "geometry": {"coordinates":[-84.102647,33.781989],"type":"Point"}
}