{
  "type": "Feature",
  "properties": {
    "iso:country":"US",
    "sg:address":"230 Old Pioneer Trl",
    "sg:city":"Canton",
    "sg:classifiers":[
        {
            "category":"Retail",
            "subcategory":"Auto Repair",
            "type":"Services"
        }
    ],
    "sg:phone":"+1 770 846 4865",
    "sg:postcode":"30115",
    "sg:province":"GA",
    "sg:tags":[
        "general"
    ],
    "wof:name":"Tims Mobile Auto Repair",
    "wof:placetype":"venue"
},
  "geometry": {"coordinates":[-84.451503,34.197243],"type":"Point"}
}