{
  "type": "Feature",
  "properties": {
    "iso:country":"US",
    "sg:address":"315 N Tibbs Rd",
    "sg:city":"Dalton",
    "sg:classifiers":[
        {
            "category":"Travel",
            "subcategory":"Travel Agent",
            "type":"Entertainment"
        }
    ],
    "sg:phone":"+1 706 278 6841",
    "sg:postcode":"30720",
    "sg:province":"GA",
    "sg:tags":[
        "agency"
    ],
    "wof:name":"Stevens Frank Family LLP",
    "wof:placetype":"venue"
},
  "geometry": {"coordinates":[-84.995199,34.778485],"type":"Point"}
}