{
  "type": "Feature",
  "properties": {
    "addr:full":"6019 Main St Lula GA 30554",
    "addr:housenumber":"6019",
    "addr:postcode":"30554",
    "addr:street":"Main St",
    "iso:country":"US",
    "sg:address":"6019 Main St",
    "sg:city":"Lula",
    "sg:classifiers":[
        {
            "category":"Autos & Motor Vehicles",
            "subcategory":"Auto Supplies",
            "type":"Retail Goods"
        }
    ],
    "sg:phone":"+1 770 869 3200",
    "sg:postcode":"30554",
    "sg:province":"GA",
    "sg:tags":[
        "tire"
    ],
    "wof:name":"Autry's Tire Shop",
    "wof:placetype":"venue"
},
  "geometry": {"coordinates":[-83.665723,34.388364],"type":"Point"}
}