{
  "type": "Feature",
  "properties": {
    "addr:full":"5000 Harrington Rd Alpharetta GA 30022",
    "addr:housenumber":"5000",
    "addr:postcode":"30022",
    "addr:street":"Harrington Rd",
    "iso:country":"US",
    "sg:address":"5000 Harrington Rd",
    "sg:city":"Alpharetta",
    "sg:classifiers":[
        {
            "category":"Building & Trades",
            "subcategory":"Locksmith",
            "type":"Services"
        }
    ],
    "sg:phone":"+1 678 804 5760",
    "sg:postcode":"30022",
    "sg:province":"GA",
    "sg:tags":[
        "key"
    ],
    "wof:name":"Locksmith 24 Hr Emerg A",
    "wof:placetype":"venue"
},
  "geometry": {"coordinates":[-84.24156499999999,34.00998],"type":"Point"}
}