{
  "type": "Feature",
  "properties": {
    "addr:full":"5174- B Performance Dr Cumming GA 30040",
    "addr:housenumber":"5174 b",
    "addr:postcode":"30040",
    "addr:street":"Performance Dr",
    "iso:country":"US",
    "sg:address":"5174- B Performance Dr",
    "sg:city":"Cumming",
    "sg:phone":"+1 770 886 0686",
    "sg:postcode":"30040",
    "sg:province":"GA",
    "sg:website":"http://www.motorwerksracing.com",
    "wof:name":"Motor Werks Racing Inc- Exclusively Porsche",
    "wof:placetype":"venue"
},
  "geometry": {"coordinates":[-84.169709,34.170651],"type":"Point"}
}