{
  "type": "Feature",
  "properties": {
    "iso:country":"US",
    "sg:address":"2036 Johnson Ferry Rd NE",
    "sg:city":"Atlanta",
    "sg:classifiers":[
        {
            "category":"Building & Trades",
            "subcategory":"Locksmith",
            "type":"Services"
        }
    ],
    "sg:phone":"+1 678 865 8069",
    "sg:postcode":"30319",
    "sg:province":"GA",
    "sg:tags":[
        "key"
    ],
    "wof:name":"Locksmith Emergency Available",
    "wof:placetype":"venue"
},
  "geometry": {"coordinates":[-84.32701400000001,33.892911],"type":"Point"}
}