{
  "type": "Feature",
  "properties": {
    "iso:country":"US",
    "sg:address":"333 Riverview Dr",
    "sg:city":"Savannah",
    "sg:classifiers":[
        {
            "category":"Building & Trades",
            "subcategory":"Cleaning & Sanitation",
            "type":"Services"
        }
    ],
    "sg:phone":"+1 912 236 9787",
    "sg:postcode":"31404",
    "sg:province":"GA",
    "sg:tags":[
        "maintenance"
    ],
    "wof:name":"Randall Greens Cleaning",
    "wof:placetype":"venue"
},
  "geometry": {"coordinates":[-81.045119,32.06284],"type":"Point"}
}