{
  "type": "Feature",
  "properties": {
    "addr:full":"3494 N Henry Blvd Hwy 42 Stockbridge GA 30281",
    "addr:housenumber":"3494",
    "addr:postcode":"30281",
    "addr:street":"N Henry Blvd Hwy 42",
    "iso:country":"US",
    "sg:address":"3494 N Henry Blvd Hwy 42",
    "sg:city":"Stockbridge",
    "sg:classifiers":[
        {
            "category":"Arena",
            "subcategory":"Sports Club",
            "type":"Entertainment"
        }
    ],
    "sg:phone":"+1 678 289 1020",
    "sg:postcode":"30281",
    "sg:province":"GA",
    "sg:website":"www.southside-sports-club.com/",
    "wof:name":"Southside Sports Indoor Batting Cages",
    "wof:placetype":"venue"
},
  "geometry": {"coordinates":[-84.19998200000001,33.535325],"type":"Point"}
}