{
  "type": "Feature",
  "properties": {
    "addr:full":"3549 Paces Ferry Rd NW Atlanta GA 30327",
    "addr:housenumber":"3549",
    "addr:postcode":"30327",
    "addr:street":"Paces Ferry Rd Nw",
    "iso:country":"US",
    "sg:address":"3549 Paces Ferry Rd NW",
    "sg:city":"Atlanta",
    "sg:classifiers":[
        {
            "category":"Professional",
            "subcategory":"Business Services",
            "type":"Services"
        }
    ],
    "sg:phone":"+1 404 233 3564",
    "sg:postcode":"30327",
    "sg:province":"GA",
    "wof:name":"Dorothy Gay Pool Inc",
    "wof:placetype":"venue"
},
  "geometry": {"coordinates":[-84.437956,33.854157],"type":"Point"}
}