{
  "type": "Feature",
  "properties": {
    "iso:country":"US",
    "sg:address":"179 Freeman St",
    "sg:city":"Tallapoosa",
    "sg:classifiers":[
        {
            "category":"Building & Trades",
            "subcategory":"Construction",
            "type":"Services"
        }
    ],
    "sg:phone":"+1 770 574 9535",
    "sg:postcode":"30176",
    "sg:province":"GA",
    "sg:tags":[
        "designer",
        "dealer",
        "pool",
        "swimming"
    ],
    "wof:name":"Fantasy Pool & Spa",
    "wof:placetype":"venue"
},
  "geometry": {"coordinates":[-85.28631300000001,33.745587],"type":"Point"}
}