{
  "type": "Feature",
  "properties": {
    "iso:country":"US",
    "sg:address":"3330 Piedmont Rd NE Ste 1",
    "sg:city":"Atlanta",
    "sg:classifiers":[
        {
            "category":"Health Services",
            "subcategory":"Optometrist",
            "type":"Services"
        }
    ],
    "sg:phone":"+1 404 231 3772",
    "sg:postcode":"30305",
    "sg:province":"GA",
    "sg:tags":[
        "good",
        "optical"
    ],
    "wof:name":"Eye Gallery At Buckhead",
    "wof:placetype":"venue"
},
  "geometry": {"coordinates":[-84.37267900000001,33.846328],"type":"Point"}
}