{
  "type": "Feature",
  "properties": {
    "addr:full":"3623 Albany Ave Waycross GA 31503",
    "addr:housenumber":"3623",
    "addr:postcode":"31503",
    "addr:street":"Albany Ave",
    "iso:country":"US",
    "sg:address":"3623 Albany Ave",
    "sg:city":"Waycross",
    "sg:classifiers":[
        {
            "category":"Arts & Performance",
            "subcategory":"Theater",
            "type":"Entertainment"
        }
    ],
    "sg:phone":"+1 912 283 9244",
    "sg:postcode":"31503",
    "sg:province":"GA",
    "sg:tags":[
        "group"
    ],
    "wof:name":"Kirkland Josh & Texas Flood",
    "wof:placetype":"venue"
},
  "geometry": {"coordinates":[-82.438168,31.238181],"type":"Point"}
}