{
  "type": "Feature",
  "properties": {
    "addr:full":"552 Hampton Rd Mcdonough GA 30253",
    "addr:housenumber":"552",
    "addr:postcode":"30253",
    "addr:street":"Hampton Rd",
    "iso:country":"US",
    "sg:address":"552 Hampton Rd",
    "sg:city":"Mcdonough",
    "sg:classifiers":[
        {
            "category":"Personal",
            "subcategory":"Beauty Salon",
            "type":"Services"
        }
    ],
    "sg:phone":"+1 770 898 0830",
    "sg:postcode":"30253",
    "sg:province":"GA",
    "wof:name":"Designer Hair",
    "wof:placetype":"venue"
},
  "geometry": {"coordinates":[-84.170485,33.43378],"type":"Point"}
}