{
  "type": "Feature",
  "properties": {
    "addr:full":"980 Litchfield Pl Roswell GA 30076",
    "addr:housenumber":"980",
    "addr:postcode":"30076",
    "addr:street":"Litchfield Pl",
    "iso:country":"US",
    "sg:address":"980 Litchfield Pl",
    "sg:city":"Roswell",
    "sg:classifiers":[
        {
            "category":"Professional",
            "type":"Services"
        }
    ],
    "sg:phone":"+1 770 642 4138",
    "sg:postcode":"30076",
    "sg:province":"GA",
    "wof:name":"Metro Music Art & Movement",
    "wof:placetype":"venue"
},
  "geometry": {"coordinates":[-84.345837,34.050774],"type":"Point"}
}