{
  "type": "Feature",
  "properties": {
    "addr:full":"215 Clairemont Ave Decatur GA 30030",
    "addr:housenumber":"215",
    "addr:postcode":"30030",
    "addr:street":"Clairemont Ave",
    "iso:country":"US",
    "sg:address":"215 Clairemont Ave",
    "sg:city":"Decatur",
    "sg:classifiers":[
        {
            "category":"Shopping",
            "subcategory":"Stationery & Office Supplies",
            "type":"Retail Goods"
        },
        {
            "category":"Manufacturing",
            "subcategory":"Electronics",
            "type":"Manufacturing & Wholesale Goods"
        },
        {
            "category":"Professional",
            "subcategory":"Printing & Photocopies",
            "type":"Services"
        }
    ],
    "sg:phone":"+1 404 377 0988",
    "sg:postcode":"30030",
    "sg:province":"GA",
    "sg:tags":[
        "equipment",
        "printers-equipment",
        "services-commercial"
    ],
    "wof:name":"Printmaster Of Decatur, Inc.",
    "wof:placetype":"venue"
},
  "geometry": {"coordinates":[-84.29648,33.777571],"type":"Point"}
}