{
  "type": "Feature",
  "properties": {
    "iso:country":"US",
    "sg:address":"3055 Ebenezer Rd",
    "sg:city":"Marietta",
    "sg:classifiers":[
        {
            "category":"Building & Trades",
            "subcategory":"Construction",
            "type":"Services"
        }
    ],
    "sg:phone":"+1 770 973 4038",
    "sg:postcode":"30066",
    "sg:province":"GA",
    "sg:tags":[
        "general",
        "contractor"
    ],
    "wof:name":"Mooney Construction",
    "wof:placetype":"venue"
},
  "geometry": {"coordinates":[-84.49098600000001,34.026635],"type":"Point"}
}