{
  "type": "Feature",
  "properties": {
    "iso:country":"US",
    "sg:address":"395 Perry Pkwy Ofc",
    "sg:city":"Perry",
    "sg:classifiers":[
        {
            "category":"Real Estate",
            "subcategory":"Real Estate Operator",
            "type":"Services"
        }
    ],
    "sg:phone":"+1 478 987 8179",
    "sg:postcode":"31069",
    "sg:province":"GA",
    "sg:tags":[
        "apartment"
    ],
    "wof:name":"Marberry Properties",
    "wof:placetype":"venue"
},
  "geometry": {"coordinates":[-83.710431,32.480138],"type":"Point"}
}