{
  "type": "Feature",
  "properties": {
    "addr:full":"233 Cooler Rd Bainbridge GA 39817",
    "addr:housenumber":"233",
    "addr:postcode":"39817",
    "addr:street":"Cooler Rd",
    "iso:country":"US",
    "sg:address":"233 Cooler Rd",
    "sg:city":"Bainbridge",
    "sg:classifiers":[
        {
            "category":"Farming",
            "subcategory":"Farm",
            "type":"Manufacturing & Wholesale Goods"
        }
    ],
    "sg:phone":"+1 229 246 1724",
    "sg:postcode":"39817",
    "sg:province":"GA",
    "wof:name":"PGC Farms",
    "wof:placetype":"venue"
},
  "geometry": {"coordinates":[-84.64868800000001,30.936417],"type":"Point"}
}