{
  "type": "Feature",
  "properties": {
    "iso:country":"US",
    "sg:address":"1072 Green St",
    "sg:city":"Roswell",
    "sg:classifiers":[
        {
            "category":"Restaurant",
            "type":"Food & Drink"
        }
    ],
    "sg:phone":"+1 770 642 6668",
    "sg:postcode":"30075",
    "sg:province":"GA",
    "sg:tags":[
        "eating"
    ],
    "wof:name":"Gore-Moss Corp",
    "wof:placetype":"venue"
},
  "geometry": {"coordinates":[-84.359628,34.0299],"type":"Point"}
}