{
  "type": "Feature",
  "properties": {
    "addr:full":"65 Alpine Dr Ringgold GA 30736",
    "addr:housenumber":"65",
    "addr:postcode":"30736",
    "addr:street":"Alpine Dr",
    "iso:country":"US",
    "sg:address":"65 Alpine Dr",
    "sg:city":"Ringgold",
    "sg:classifiers":[
        {
            "category":"Autos & Motor Vehicles",
            "subcategory":"Auto Supplies",
            "type":"Retail Goods"
        }
    ],
    "sg:phone":"+1 706 937 7620",
    "sg:postcode":"30736",
    "sg:province":"GA",
    "sg:tags":[
        "accessories-wholesale",
        "automobile",
        "part",
        "parts",
        "manufacturer"
    ],
    "wof:name":"Fastire Supply Equipment",
    "wof:placetype":"venue"
},
  "geometry": {"coordinates":[-85.173486,34.917171],"type":"Point"}
}