{
  "type": "Feature",
  "properties": {
    "iso:country":"US",
    "sg:address":"1721 Lynwood Ln",
    "sg:city":"Albany",
    "sg:classifiers":[
        {
            "category":"Professional",
            "subcategory":"Advertising",
            "type":"Services"
        },
        {
            "category":"Banks & Credit Unions",
            "subcategory":"Bank",
            "type":"Services"
        }
    ],
    "sg:phone":"+1 229 446 8527",
    "sg:postcode":"31707",
    "sg:province":"GA",
    "sg:tags":[
        "depository",
        "banking",
        "counselor"
    ],
    "wof:name":"Starmarketing",
    "wof:placetype":"venue"
},
  "geometry": {"coordinates":[-84.19762299999999,31.59216],"type":"Point"}
}