{
  "type": "Feature",
  "properties": {
    "iso:country":"US",
    "sg:address":"892 Ponce de Leon Ave NE",
    "sg:city":"Atlanta",
    "sg:classifiers":[
        {
            "category":"Real Estate",
            "subcategory":"Real Estate Operator",
            "type":"Services"
        }
    ],
    "sg:phone":"+1 404 892 2344",
    "sg:postcode":"30306",
    "sg:province":"GA",
    "sg:tags":[
        "apartment"
    ],
    "wof:name":"Lake Apartments",
    "wof:placetype":"venue"
},
  "geometry": {"coordinates":[-84.357642,33.773892],"type":"Point"}
}