{
  "type": "Feature",
  "properties": {
    "iso:country":"US",
    "sg:address":"116 14th Ave W",
    "sg:city":"Cordele",
    "sg:classifiers":[
        {
            "category":"Professional",
            "subcategory":"Accounting & Tax Preparation",
            "type":"Services"
        }
    ],
    "sg:phone":"+1 229 271 3139",
    "sg:postcode":"31015",
    "sg:province":"GA",
    "sg:tags":[
        "bookkeeping",
        "general"
    ],
    "wof:name":"Johnson's Family Tax Svc",
    "wof:placetype":"venue"
},
  "geometry": {"coordinates":[-83.783359,31.965836],"type":"Point"}
}