{
  "type": "Feature",
  "properties": {
    "addr:full":"3145 W Main St Royston GA 30662",
    "addr:housenumber":"3145",
    "addr:postcode":"30662",
    "addr:street":"W Main St",
    "iso:country":"US",
    "sg:address":"3145 W Main St",
    "sg:city":"Royston",
    "sg:classifiers":[
        {
            "category":"Freight",
            "type":"Transportation"
        }
    ],
    "sg:phone":"+1 706 245 9533",
    "sg:postcode":"30662",
    "sg:province":"GA",
    "sg:tags":[
        "special",
        "general"
    ],
    "wof:name":"Arctic Air Mini Storage Inc",
    "wof:placetype":"venue"
},
  "geometry": {"coordinates":[-83.159265,34.285948],"type":"Point"}
}