{
  "type": "Feature",
  "properties": {
    "addr:full":"4355 Washington Rd Evans GA 30809",
    "addr:housenumber":"4355",
    "addr:postcode":"30809",
    "addr:street":"Washington Rd",
    "iso:country":"US",
    "sg:address":"4355 Washington Rd",
    "sg:city":"Evans",
    "sg:classifiers":[
        {
            "category":"Banks & Credit Unions",
            "subcategory":"Bank",
            "type":"Services"
        }
    ],
    "sg:phone":"+1 706 868 4200",
    "sg:postcode":"30809",
    "sg:province":"GA",
    "sg:tags":[
        "state"
    ],
    "wof:name":"South Trust Bank",
    "wof:placetype":"venue"
},
  "geometry": {"coordinates":[-82.134834,33.541707],"type":"Point"}
}