{
  "type": "Feature",
  "properties": {
    "iso:country":"US",
    "sg:address":"431 Jefferies Ave",
    "sg:city":"Albany",
    "sg:classifiers":[
        {
            "category":"Education",
            "subcategory":"School",
            "type":"Public Place"
        }
    ],
    "sg:phone":"+1 229 883 2136",
    "sg:postcode":"31701",
    "sg:province":"GA",
    "sg:tags":[
        "kindergarten",
        "care",
        "center",
        "day"
    ],
    "wof:name":"Albanys Jack & Jill Day Care",
    "wof:placetype":"venue"
},
  "geometry": {"coordinates":[-84.15817699999999,31.559657],"type":"Point"}
}