{
  "type": "Feature",
  "properties": {
    "iso:country":"US",
    "sg:address":"3083 Martin Luther King Jr Dr SW",
    "sg:city":"Atlanta",
    "sg:classifiers":[
        {
            "category":"Restaurant",
            "type":"Food & Drink"
        }
    ],
    "sg:phone":"+1 404 696 1330",
    "sg:postcode":"30311",
    "sg:province":"GA",
    "wof:name":"Caribbean Wing Hut & Bbq Grill",
    "wof:placetype":"venue"
},
  "geometry": {"coordinates":[-84.482373,33.754466],"type":"Point"}
}