{
  "type": "Feature",
  "properties": {
    "addr:full":"6991 Peachtree Industrial Blvd Norcross GA 30092",
    "addr:housenumber":"6991",
    "addr:postcode":"30092",
    "addr:street":"Peachtree Industrial Blvd",
    "iso:country":"US",
    "sg:address":"6991 Peachtree Industrial Blvd",
    "sg:city":"Norcross",
    "sg:classifiers":[
        {
            "category":"Organizations",
            "subcategory":"Religious Organization",
            "type":"Services"
        }
    ],
    "sg:phone":"+1 770 840 1198",
    "sg:postcode":"30092",
    "sg:province":"GA",
    "sg:tags":[
        "church"
    ],
    "wof:name":"Iglesia Misionera",
    "wof:placetype":"venue"
},
  "geometry": {"coordinates":[-84.261274,33.932673],"type":"Point"}
}