{
  "type": "Feature",
  "properties": {
    "addr:full":"460 Morrow Rd Forest Park GA 30297",
    "addr:housenumber":"460",
    "addr:postcode":"30297",
    "addr:street":"Morrow Rd",
    "iso:country":"US",
    "sg:address":"460 Morrow Rd",
    "sg:city":"Forest Park",
    "sg:classifiers":[
        {
            "category":"Building & Trades",
            "subcategory":"Construction",
            "type":"Services"
        }
    ],
    "sg:phone":"+1 404 748 2010",
    "sg:postcode":"30297",
    "sg:province":"GA",
    "sg:tags":[
        "contractor"
    ],
    "sg:website":"www.bedrockmechanical.com",
    "wof:name":"Bedrock Mechanical Contractors Llc",
    "wof:placetype":"venue"
},
  "geometry": {"coordinates":[-84.37534599999999,33.591017],"type":"Point"}
}