{
  "type": "Feature",
  "properties": {
    "addr:full":"5920 Roswell Rd NE Ste A205 Atlanta GA 30328",
    "addr:housenumber":"5920;rd",
    "addr:postcode":"30328",
    "addr:street":"Roswell;Ne Ste A205",
    "iso:country":"US",
    "sg:address":"5920 Roswell Rd NE Ste A205",
    "sg:city":"Atlanta",
    "sg:classifiers":[
        {
            "category":"Health Services",
            "subcategory":"Doctor",
            "type":"Services"
        }
    ],
    "sg:phone":"+1 770 991 8803",
    "sg:postcode":"30328",
    "sg:province":"GA",
    "wof:name":"Smith Walter DO",
    "wof:placetype":"venue"
},
  "geometry": {"coordinates":[-84.37938,33.916234],"type":"Point"}
}