{
  "type": "Feature",
  "properties": {
    "addr:full":"122 Windy Hill Ct Dublin GA 31021",
    "addr:housenumber":"122",
    "addr:postcode":"31021",
    "addr:street":"Windy Hill Ct",
    "iso:country":"US",
    "sg:address":"122 Windy Hill Ct",
    "sg:city":"Dublin",
    "sg:classifiers":[
        {
            "category":"Recreation",
            "type":"Entertainment"
        }
    ],
    "sg:phone":"+1 478 296 7701",
    "sg:postcode":"31021",
    "sg:province":"GA",
    "sg:tags":[
        "guide"
    ],
    "sg:website":"www.corporatehunts.com",
    "wof:name":"CORPORATEHUNTS.COM",
    "wof:placetype":"venue"
},
  "geometry": {"coordinates":[-82.952444,32.572283],"type":"Point"}
}