{
  "type": "Feature",
  "properties": {
    "iso:country":"US",
    "sg:address":"3939 Roswell Rd",
    "sg:city":"Marietta",
    "sg:classifiers":[
        {
            "category":"Social Services",
            "type":"Services"
        }
    ],
    "sg:phone":"+1 770 971 5244",
    "sg:postcode":"30062",
    "sg:province":"GA",
    "sg:tags":[
        "health"
    ],
    "wof:name":"Nix Alice P",
    "wof:placetype":"venue"
},
  "geometry": {"coordinates":[-84.436071,33.978511],"type":"Point"}
}