{
  "type": "Feature",
  "properties": {
    "addr:full":"1032 Cobb Pkwy Atlanta GA 30336",
    "addr:housenumber":"1032",
    "addr:postcode":"30336",
    "addr:street":"Cobb Pkwy",
    "iso:country":"US",
    "sg:address":"1032 Cobb Pkwy",
    "sg:city":"Atlanta",
    "sg:classifiers":[
        {
            "category":"Autos & Motor Vehicles",
            "subcategory":"Auto Supplies",
            "type":"Retail Goods"
        },
        {
            "category":"Building & Trades",
            "subcategory":"Construction",
            "type":"Services"
        }
    ],
    "sg:phone":"+1 404 914 5575",
    "sg:postcode":"30336",
    "sg:province":"GA",
    "sg:tags":[
        "glass",
        "window",
        "installation"
    ],
    "sg:website":"atlantatintshop.com",
    "wof:name":"Sun Screen Window Tinting",
    "wof:placetype":"venue"
},
  "geometry": {"coordinates":[-84.569659,33.732804],"type":"Point"}
}