{
  "type": "Feature",
  "properties": {
    "iso:country":"US",
    "sg:address":"50 Skin Alley St",
    "sg:city":"Norcross",
    "sg:classifiers":[
        {
            "category":"Professional",
            "type":"Services"
        }
    ],
    "sg:phone":"+1 770 449 9600",
    "sg:postcode":"30071",
    "sg:province":"GA",
    "sg:tags":[
        "establishment"
    ],
    "wof:name":"Gaijin Studios",
    "wof:placetype":"venue"
},
  "geometry": {"coordinates":[-84.212862,33.94151],"type":"Point"}
}