{
  "type": "Feature",
  "properties": {
    "addr:full":"535 N Oakland Cir Mcdonough GA 30253",
    "addr:housenumber":"535",
    "addr:postcode":"30253",
    "addr:street":"N Oakland Cir",
    "iso:country":"US",
    "sg:address":"535 N Oakland Cir",
    "sg:city":"Mcdonough",
    "sg:classifiers":[
        {
            "category":"Retail",
            "subcategory":"Portrait Studio",
            "type":"Services"
        },
        {
            "category":"Professional",
            "subcategory":"Art Services",
            "type":"Services"
        }
    ],
    "sg:phone":"+1 770 914 1697",
    "sg:postcode":"30253",
    "sg:province":"GA",
    "sg:tags":[
        "photographer",
        "photography",
        "commercial"
    ],
    "wof:name":"Picture This Studio Inc",
    "wof:placetype":"venue"
},
  "geometry": {"coordinates":[-84.225331,33.430868],"type":"Point"}
}