{
  "type": "Feature",
  "properties": {
    "iso:country":"US",
    "sg:address":"3807 Val Tech Rd",
    "sg:city":"Valdosta",
    "sg:classifiers":[
        {
            "category":"Real Estate",
            "subcategory":"Real Estate Agent",
            "type":"Services"
        }
    ],
    "sg:phone":"+1 229 242 4683",
    "sg:postcode":"31602",
    "sg:province":"GA",
    "wof:name":"Flythe RE Partners Lllp",
    "wof:placetype":"venue"
},
  "geometry": {"coordinates":[-83.344172,30.869517],"type":"Point"}
}