{
  "type": "Feature",
  "properties": {
    "iso:country":"US",
    "sg:address":"806 Newnan Rd",
    "sg:city":"Carrollton",
    "sg:classifiers":[
        {
            "category":"Retail",
            "subcategory":"Auto Repair",
            "type":"Services"
        }
    ],
    "sg:phone":"+1 770 834 6466",
    "sg:postcode":"30117",
    "sg:province":"GA",
    "sg:tags":[
        "body",
        "automobile",
        "painting"
    ],
    "wof:name":"Wes Phillips Auto Sales",
    "wof:placetype":"venue"
},
  "geometry": {"coordinates":[-85.05135799999999,33.571743],"type":"Point"}
}