{
  "type": "Feature",
  "properties": {
    "iso:country":"US",
    "sg:address":"8859 Chattsworth Rd",
    "sg:city":"Midland",
    "sg:classifiers":[
        {
            "category":"Building & Trades",
            "subcategory":"Landscaping Services",
            "type":"Services"
        }
    ],
    "sg:phone":"+1 706 561 2987",
    "sg:postcode":"31820",
    "sg:province":"GA",
    "sg:tags":[
        "tree"
    ],
    "wof:name":"Tree Care Solutions Dba",
    "wof:placetype":"venue"
},
  "geometry": {"coordinates":[-84.838601,32.532166],"type":"Point"}
}