{
  "type": "Feature",
  "properties": {
    "iso:country":"US",
    "sg:address":"5060 Sugar Pike Rd",
    "sg:city":"Canton",
    "sg:classifiers":[
        {
            "category":"Professional",
            "subcategory":"Advertising",
            "type":"Services"
        }
    ],
    "sg:phone":"+1 770 640 7711",
    "sg:postcode":"30115",
    "sg:province":"GA",
    "sg:tags":[
        "distribution"
    ],
    "wof:name":"Alfa Electronics LTD",
    "wof:placetype":"venue"
},
  "geometry": {"coordinates":[-84.38070500000001,34.18476],"type":"Point"}
}