{
  "type": "Feature",
  "properties": {
    "iso:country":"US",
    "sg:address":"989 Ashebrook Way",
    "sg:city":"Marietta",
    "sg:classifiers":[
        {
            "category":"Wholesale",
            "subcategory":"Hardware",
            "type":"Manufacturing & Wholesale Goods"
        }
    ],
    "sg:phone":"+1 678 560 1690",
    "sg:postcode":"30068",
    "sg:province":"GA",
    "sg:tags":[
        "air",
        "equipment",
        "export",
        "conditioning",
        "refrigeration",
        "chem"
    ],
    "wof:name":"Aaco Corp",
    "wof:placetype":"venue"
},
  "geometry": {"coordinates":[-84.466589,33.97296],"type":"Point"}
}