{
  "type": "Feature",
  "properties": {
    "addr:full":"424 S Jefferson St Ashburn GA 31714",
    "addr:housenumber":"424",
    "addr:postcode":"31714",
    "addr:street":"S Jefferson St",
    "iso:country":"US",
    "sg:address":"424 S Jefferson St",
    "sg:city":"Ashburn",
    "sg:classifiers":[
        {
            "category":"Social Services",
            "type":"Services"
        }
    ],
    "sg:phone":"+1 229 567 3996",
    "sg:postcode":"31714",
    "sg:province":"GA",
    "sg:tags":[
        "youth",
        "organization",
        "center"
    ],
    "wof:name":"Youth Resource Building",
    "wof:placetype":"venue"
},
  "geometry": {"coordinates":[-83.656784,31.701053],"type":"Point"}
}