{
  "type": "Feature",
  "properties": {
    "iso:country":"US",
    "sg:address":"1986 Hosea L Williams Dr NE",
    "sg:city":"Atlanta",
    "sg:classifiers":[
        {
            "category":"Personal",
            "subcategory":"Beauty Salon",
            "type":"Services"
        }
    ],
    "sg:phone":"+1 404 370 6199",
    "sg:postcode":"30317",
    "sg:province":"GA",
    "sg:tags":[
        "shop"
    ],
    "wof:name":"Braiding Heads Up",
    "wof:placetype":"venue"
},
  "geometry": {"coordinates":[-84.322282,33.751219],"type":"Point"}
}