{
  "type": "Feature",
  "properties": {
    "iso:country":"US",
    "sg:address":"56 E Andrews Drive NW",
    "sg:city":"Atlanta",
    "sg:classifiers":[
        {
            "category":"Personal",
            "subcategory":"Beauty Salon",
            "type":"Services"
        }
    ],
    "sg:phone":"+1 404 231 3841",
    "sg:postcode":"30305",
    "sg:province":"GA",
    "sg:tags":[
        "hair"
    ],
    "wof:name":"Felicity Hair Design",
    "wof:placetype":"venue"
},
  "geometry": {"coordinates":[-84.38069299999999,33.843552],"type":"Point"}
}