{
  "type": "Feature",
  "properties": {
    "iso:country":"US",
    "sg:address":"4310 Parks Rd",
    "sg:city":"Cumming",
    "sg:classifiers":[
        {
            "category":"Professional",
            "type":"Services"
        }
    ],
    "sg:phone":"+1 770 886 0971",
    "sg:postcode":"30041",
    "sg:province":"GA",
    "wof:name":"Tim Ware",
    "wof:placetype":"venue"
},
  "geometry": {"coordinates":[-84.054636,34.265267],"type":"Point"}
}