{
  "type": "Feature",
  "properties": {
    "iso:country":"US",
    "sg:address":"3405 Lenox Rd NE",
    "sg:city":"Atlanta",
    "sg:classifiers":[
        {
            "category":"Communications",
            "subcategory":"Film & Video Production",
            "type":"Services"
        },
        {
            "category":"Building & Trades",
            "subcategory":"Equipment Rental",
            "type":"Services"
        }
    ],
    "sg:phone":"+1 404 467 1810",
    "sg:postcode":"30326",
    "sg:province":"GA",
    "sg:tags":[
        "leasing",
        "equipment-renting",
        "audio-visual"
    ],
    "wof:name":"Presentation Services Inc",
    "wof:placetype":"venue"
},
  "geometry": {"coordinates":[-84.360122,33.847849],"type":"Point"}
}