{
  "type": "Feature",
  "properties": {
    "addr:full":"8 King St Savannah GA 31408",
    "addr:housenumber":"8",
    "addr:postcode":"31408",
    "addr:street":"King St",
    "iso:country":"US",
    "sg:address":"8 King St",
    "sg:city":"Savannah",
    "sg:classifiers":[
        {
            "category":"Retail",
            "subcategory":"Auto Repair",
            "type":"Services"
        }
    ],
    "sg:phone":"+1 912 349 1479",
    "sg:postcode":"31408",
    "sg:province":"GA",
    "sg:tags":[
        "body",
        "painting",
        "repairing",
        "automobile"
    ],
    "wof:name":"Arthurs Collision Center",
    "wof:placetype":"venue"
},
  "geometry": {"coordinates":[-81.135103,32.087262],"type":"Point"}
}