{
  "type": "Feature",
  "properties": {
    "iso:country":"US",
    "sg:address":"King Plow Arts Center 887 W Marietta St Ste J-107",
    "sg:city":"Atlanta",
    "sg:classifiers":[
        {
            "category":"Arts & Performance",
            "subcategory":"Arts Center",
            "type":"Entertainment"
        }
    ],
    "sg:phone":"+1 404 607 7469",
    "sg:postcode":"30318",
    "sg:province":"GA",
    "sg:tags":[
        "performing"
    ],
    "sg:website":"www.actors-express.com",
    "wof:name":"Actor's Express",
    "wof:placetype":"venue"
},
  "geometry": {"coordinates":[-84.407403,33.776657],"type":"Point"}
}