{
  "type": "Feature",
  "properties": {
    "addr:full":"1145 Sanctuary Pkwy Alpharetta GA 30009",
    "addr:housenumber":"1145",
    "addr:postcode":"30009",
    "addr:street":"Sanctuary Pkwy",
    "iso:country":"US",
    "sg:address":"1145 Sanctuary Pkwy",
    "sg:city":"Alpharetta",
    "sg:classifiers":[
        {
            "category":"Real Estate",
            "subcategory":"Real Estate Services",
            "type":"Services"
        }
    ],
    "sg:phone":"+1 770 569 9876",
    "sg:postcode":"30009",
    "sg:province":"GA",
    "sg:tags":[
        "management",
        "property"
    ],
    "wof:name":"Sanctuary Park",
    "wof:placetype":"venue"
},
  "geometry": {"coordinates":[-84.311336,34.04691],"type":"Point"}
}