{
  "type": "Feature",
  "properties": {
    "iso:country":"US",
    "sg:address":"209 S Church St",
    "sg:city":"Thomaston",
    "sg:classifiers":[
        {
            "category":"Travel",
            "subcategory":"Travel Agent",
            "type":"Entertainment"
        },
        {
            "category":"Taxi",
            "type":"Transportation"
        }
    ],
    "sg:phone":"+1 706 647 8818",
    "sg:postcode":"30286",
    "sg:province":"GA",
    "sg:tags":[
        "taxicab",
        "agency"
    ],
    "wof:name":"Eastern Travels",
    "wof:placetype":"venue"
},
  "geometry": {"coordinates":[-84.327122,32.887091],"type":"Point"}
}