{
  "type": "Feature",
  "properties": {
    "addr:full":"49 Krog St Atlanta GA 30307",
    "addr:housenumber":"49",
    "addr:postcode":"30307",
    "addr:street":"Krog St",
    "iso:country":"US",
    "sg:address":"49 Krog St",
    "sg:city":"Atlanta",
    "sg:classifiers":[
        {
            "category":"Building & Trades",
            "subcategory":"Construction",
            "type":"Services"
        }
    ],
    "sg:phone":"+1 678 894 2848",
    "sg:postcode":"30307",
    "sg:province":"GA",
    "sg:tags":[
        "contractor"
    ],
    "sg:website":"www.atlantacommercialroofing.org",
    "wof:name":"UpGrade Roofing, Inc.",
    "wof:placetype":"venue"
},
  "geometry": {"coordinates":[-84.363941,33.755412],"type":"Point"}
}