{
  "type": "Feature",
  "properties": {
    "addr:full":"264 Lee Rd Cedartown GA 30125",
    "addr:housenumber":"264",
    "addr:postcode":"30125",
    "addr:street":"Lee Rd",
    "iso:country":"US",
    "sg:address":"264 Lee Rd",
    "sg:city":"Cedartown",
    "sg:classifiers":[
        {
            "category":"Building & Trades",
            "subcategory":"Construction",
            "type":"Services"
        }
    ],
    "sg:phone":"+1 770 749 0705",
    "sg:postcode":"30125",
    "sg:province":"GA",
    "wof:name":"Presley Grading",
    "wof:placetype":"venue"
},
  "geometry": {"coordinates":[-85.196889,33.927924],"type":"Point"}
}