{
  "type": "Feature",
  "properties": {
    "addr:full":"621 12th St Augusta GA 30901",
    "addr:housenumber":"621",
    "addr:postcode":"30901",
    "addr:street":"12Th St",
    "iso:country":"US",
    "sg:address":"621 12th St",
    "sg:city":"Augusta",
    "sg:classifiers":[
        {
            "category":"Freight",
            "type":"Transportation"
        }
    ],
    "sg:phone":"+1 706 722 6276",
    "sg:postcode":"30901",
    "sg:province":"GA",
    "sg:tags":[
        "trucking"
    ],
    "wof:name":"Fed Ex Freight",
    "wof:placetype":"venue"
},
  "geometry": {"coordinates":[-81.97506,33.47325],"type":"Point"}
}