{
  "type": "Feature",
  "properties": {
    "addr:full":"1851 Bishops Green Dr Marietta GA 30062",
    "addr:housenumber":"1851",
    "addr:postcode":"30062",
    "addr:street":"Bishops Green Dr",
    "iso:country":"US",
    "sg:address":"1851 Bishops Green Dr",
    "sg:city":"Marietta",
    "sg:classifiers":[
        {
            "category":"Professional",
            "subcategory":"Management & Consulting",
            "type":"Services"
        }
    ],
    "sg:phone":"+1 770 971 2615",
    "sg:postcode":"30062",
    "sg:province":"GA",
    "wof:name":"The Harbour Group Inc",
    "wof:placetype":"venue"
},
  "geometry": {"coordinates":[-84.427525,33.998164],"type":"Point"}
}