{
  "type": "Feature",
  "properties": {
    "iso:country":"US",
    "sg:address":"2155 Sandown Ct",
    "sg:city":"Lawrenceville",
    "sg:classifiers":[
        {
            "category":"Home & Garden",
            "subcategory":"Household Appliances",
            "type":"Retail Goods"
        }
    ],
    "sg:phone":"+1 770 822 1111",
    "sg:postcode":"30043",
    "sg:province":"GA",
    "sg:tags":[
        "a",
        "fabric",
        "sewing",
        "well",
        "accessory",
        "machine",
        "as",
        "lace"
    ],
    "wof:name":"Olde Sew N So",
    "wof:placetype":"venue"
},
  "geometry": {"coordinates":[-84.05642400000001,33.997364],"type":"Point"}
}