{
  "type": "Feature",
  "properties": {
    "addr:full":"4517 Canton Rd Marietta GA 30066",
    "addr:housenumber":"4517",
    "addr:postcode":"30066",
    "addr:street":"Canton Rd",
    "iso:country":"US",
    "sg:address":"4517 Canton Rd",
    "sg:city":"Marietta",
    "sg:classifiers":[
        {
            "category":"Building & Trades",
            "subcategory":"Plumbing",
            "type":"Services"
        }
    ],
    "sg:phone":"+1 770 579 3361",
    "sg:postcode":"30066",
    "sg:province":"GA",
    "sg:tags":[
        "contractor"
    ],
    "wof:name":"C & W Mechanical Contractors",
    "wof:placetype":"venue"
},
  "geometry": {"coordinates":[-84.52173999999999,34.061331],"type":"Point"}
}