{
  "type": "Feature",
  "properties": {
    "addr:full":"4364 Martha Berry Hwy Rome GA 30165",
    "addr:housenumber":"4364",
    "addr:postcode":"ga 30165",
    "addr:street":"Martha Berry Hwy",
    "iso:country":"US",
    "sg:address":"4364 Martha Berry Hwy",
    "sg:city":"Rome",
    "sg:classifiers":[
        {
            "category":"Wholesale",
            "subcategory":"Farm Supplies",
            "type":"Manufacturing & Wholesale Goods"
        }
    ],
    "sg:phone":"+1 706 290 7741",
    "sg:postcode":"30165",
    "sg:province":"GA",
    "sg:tags":[
        "feed"
    ],
    "wof:name":"B T Feed Supply",
    "wof:placetype":"venue"
},
  "geometry": {"coordinates":[-85.172321,34.346309],"type":"Point"}
}