{
  "type": "Feature",
  "properties": {
    "addr:full":"3840 Hwy 42 Locust Grove GA 30248",
    "addr:housenumber":"3840",
    "addr:postcode":"30248",
    "addr:street":"Hwy 42",
    "iso:country":"US",
    "sg:address":"3840 Hwy 42",
    "sg:city":"Locust Grove",
    "sg:classifiers":[
        {
            "category":"Food & Beverages",
            "subcategory":"Fruits & Vegetables",
            "type":"Retail Goods"
        }
    ],
    "sg:phone":"+1 770 957 4912",
    "sg:postcode":"30248",
    "sg:province":"GA",
    "sg:tags":[
        "produce"
    ],
    "wof:name":"Gardener Farms",
    "wof:placetype":"venue"
},
  "geometry": {"coordinates":[-84.10847800000001,33.344591],"type":"Point"}
}