{
  "type": "Feature",
  "properties": {
    "iso:country":"US",
    "sg:address":"3253 Deans Bridge Rd",
    "sg:city":"Augusta",
    "sg:classifiers":[
        {
            "category":"Restaurant",
            "type":"Food & Drink"
        }
    ],
    "sg:phone":"+1 706 790 0022",
    "sg:postcode":"30906",
    "sg:province":"GA",
    "sg:tags":[
        "eating"
    ],
    "wof:name":"Golden Garden Restaurant",
    "wof:placetype":"venue"
},
  "geometry": {"coordinates":[-82.063108,33.421942],"type":"Point"}
}