{
  "type": "Feature",
  "properties": {
    "addr:full":"2480 Windy Hill Rd SE # 307 Marietta GA 30067",
    "addr:housenumber":"2480",
    "addr:postcode":"30067",
    "addr:street":"Windy Hill Rd Se # 307",
    "iso:country":"US",
    "sg:address":"2480 Windy Hill Rd SE # 307",
    "sg:city":"Marietta",
    "sg:classifiers":[
        {
            "category":"Health Services",
            "subcategory":"Dentist",
            "type":"Services"
        }
    ],
    "sg:phone":"+1 770 952 0222",
    "sg:postcode":"30067",
    "sg:province":"GA",
    "wof:name":"Dan Stephens Dds Inc",
    "wof:placetype":"venue"
},
  "geometry": {"coordinates":[-84.480619,33.902286],"type":"Point"}
}