{
  "type": "Feature",
  "properties": {
    "addr:full":"105 State Rte 49 Byron GA 31008",
    "addr:housenumber":"105",
    "addr:postcode":"31008",
    "addr:street":"State Rte 49",
    "iso:country":"US",
    "sg:address":"105 State Rte 49",
    "sg:city":"Byron",
    "sg:classifiers":[
        {
            "category":"Food & Beverages",
            "subcategory":"Groceries & Convenience Stores",
            "type":"Retail Goods"
        }
    ],
    "sg:phone":"+1 478 956 3798",
    "sg:postcode":"31008",
    "sg:province":"GA",
    "wof:name":"Flash Foods",
    "wof:placetype":"venue"
},
  "geometry": {"coordinates":[-83.754626,32.653241],"type":"Point"}
}