{
  "type": "Feature",
  "properties": {
    "addr:full":"231 Tift Ave N Tifton GA 31794",
    "addr:housenumber":"231",
    "addr:postcode":"31794",
    "addr:street":"Tift Ave N",
    "iso:country":"US",
    "sg:address":"231 Tift Ave N",
    "sg:city":"Tifton",
    "sg:classifiers":[
        {
            "category":"Health Services",
            "subcategory":"Doctor",
            "type":"Services"
        }
    ],
    "sg:phone":"+1 229 386 8384",
    "sg:postcode":"31794",
    "sg:province":"GA",
    "wof:name":"Mott Alfred T DMD PC",
    "wof:placetype":"venue"
},
  "geometry": {"coordinates":[-83.50394799999999,31.462647],"type":"Point"}
}