{
  "type": "Feature",
  "properties": {
    "addr:full":"8458 Campbellton St Douglasville GA 30134",
    "addr:housenumber":"8458",
    "addr:postcode":"30134",
    "addr:street":"Campbellton St",
    "iso:country":"US",
    "sg:address":"8458 Campbellton St",
    "sg:city":"Douglasville",
    "sg:classifiers":[
        {
            "category":"Banks & Credit Unions",
            "subcategory":"Bank",
            "type":"Services"
        }
    ],
    "sg:phone":"+1 770 489 5135",
    "sg:postcode":"30134",
    "sg:province":"GA",
    "sg:website":"http://www.bbt.com",
    "wof:name":"BB&T Mortgage",
    "wof:placetype":"venue"
},
  "geometry": {"coordinates":[-84.746572,33.750155],"type":"Point"}
}