{
  "type": "Feature",
  "properties": {
    "addr:full":"1762 Briarlake Cir Decatur GA 30033",
    "addr:housenumber":"1762",
    "addr:postcode":"30033",
    "addr:street":"Briarlake Cir",
    "iso:country":"US",
    "sg:address":"1762 Briarlake Cir",
    "sg:city":"Decatur",
    "sg:classifiers":[
        {
            "category":"Home & Garden",
            "subcategory":"Home Furnishings",
            "type":"Retail Goods"
        }
    ],
    "sg:phone":"+1 404 597 6030",
    "sg:postcode":"30033",
    "sg:province":"GA",
    "sg:tags":[
        "refinish",
        "bathtub",
        "sinks-repair"
    ],
    "wof:name":"Georgia Tub & Tile",
    "wof:placetype":"venue"
},
  "geometry": {"coordinates":[-84.266115,33.836029],"type":"Point"}
}