{
  "type": "Feature",
  "properties": {
    "addr:full":"1319 Ponderosa Dr Valdosta GA 31602",
    "addr:housenumber":"1319",
    "addr:postcode":"31602",
    "addr:street":"Ponderosa Dr",
    "iso:country":"US",
    "sg:address":"1319 Ponderosa Dr",
    "sg:city":"Valdosta",
    "sg:classifiers":[
        {
            "category":"Building & Trades",
            "subcategory":"Cleaning & Sanitation",
            "type":"Services"
        }
    ],
    "sg:phone":"+1 229 245 1922",
    "sg:postcode":"31602",
    "sg:province":"GA",
    "sg:tags":[
        "janitor"
    ],
    "wof:name":"Cobb Cleaning Svc",
    "wof:placetype":"venue"
},
  "geometry": {"coordinates":[-83.26030900000001,30.855881],"type":"Point"}
}