{
  "type": "Feature",
  "properties": {
    "addr:full":"1940 Queens Way Atlanta GA 30341",
    "addr:housenumber":"1940",
    "addr:postcode":"30341",
    "addr:street":"Queens Way",
    "iso:country":"US",
    "sg:address":"1940 Queens Way",
    "sg:city":"Atlanta",
    "sg:classifiers":[
        {
            "category":"Professional",
            "type":"Services"
        }
    ],
    "sg:phone":"+1 770 451 5180",
    "sg:postcode":"30341",
    "sg:province":"GA",
    "wof:name":"Erick Emde",
    "wof:placetype":"venue"
},
  "geometry": {"coordinates":[-84.30779099999999,33.91725],"type":"Point"}
}