{
  "type": "Feature",
  "properties": {
    "iso:country":"US",
    "sg:address":"20 Little Haynes Dr",
    "sg:city":"Loganville",
    "sg:classifiers":[
        {
            "category":"Professional",
            "subcategory":"Engineering",
            "type":"Services"
        },
        {
            "category":"Manufacturing",
            "subcategory":"Electronics",
            "type":"Manufacturing & Wholesale Goods"
        }
    ],
    "sg:phone":"+1 678 625 5853",
    "sg:postcode":"30052",
    "sg:province":"GA",
    "sg:tags":[
        "control",
        "system",
        "automation",
        "electronic",
        "controls-manufacturers",
        "engineer"
    ],
    "wof:name":"Jaco, Inc",
    "wof:placetype":"venue"
},
  "geometry": {"coordinates":[-83.91289999999999,33.724268],"type":"Point"}
}