{
  "type": "Feature",
  "properties": {
    "iso:country":"US",
    "sg:address":"690 S Lumpkin St",
    "sg:city":"Athens",
    "sg:classifiers":[
        {
            "category":"Professional",
            "type":"Services"
        }
    ],
    "sg:phone":"+1 706 613 2065",
    "sg:postcode":"30605",
    "sg:province":"GA",
    "wof:name":"Ashley S Dillard",
    "wof:placetype":"venue"
},
  "geometry": {"coordinates":[-83.37657900000001,33.952874],"type":"Point"}
}