{
  "type": "Feature",
  "properties": {
    "addr:full":"1916 Chamdun Way Atlanta GA 30341",
    "addr:housenumber":"1916",
    "addr:postcode":"30341",
    "addr:street":"Chamdun Way",
    "iso:country":"US",
    "sg:address":"1916 Chamdun Way",
    "sg:city":"Atlanta",
    "sg:classifiers":[
        {
            "category":"Professional",
            "subcategory":"Management & Consulting",
            "type":"Services"
        }
    ],
    "sg:phone":"+1 770 936 0909",
    "sg:postcode":"30341",
    "sg:province":"GA",
    "wof:name":"Splash Street Marketing",
    "wof:placetype":"venue"
},
  "geometry": {"coordinates":[-84.309152,33.904916],"type":"Point"}
}