{
  "type": "Feature",
  "properties": {
    "addr:full":"885 Walnut Street Ln Macon GA 31201",
    "addr:housenumber":"885",
    "addr:postcode":"31201",
    "addr:street":"Walnut Street Ln",
    "iso:country":"US",
    "sg:address":"885 Walnut Street Ln",
    "sg:city":"Macon",
    "sg:classifiers":[
        {
            "category":"Professional",
            "subcategory":"Employment Agencies",
            "type":"Services"
        }
    ],
    "sg:phone":"+1 478 755 9893",
    "sg:postcode":"31201",
    "sg:province":"GA",
    "wof:name":"Georgia Personnel Services",
    "wof:placetype":"venue"
},
  "geometry": {"coordinates":[-83.630872,32.841703],"type":"Point"}
}