{
  "type": "Feature",
  "properties": {
    "addr:full":"717 Loral Pines Ct Lawrenceville GA 30044",
    "addr:housenumber":"717",
    "addr:postcode":"30044",
    "addr:street":"Loral Pines Ct",
    "iso:country":"US",
    "sg:address":"717 Loral Pines Ct",
    "sg:city":"Lawrenceville",
    "sg:classifiers":[
        {
            "category":"Professional",
            "subcategory":"Business Services",
            "type":"Services"
        }
    ],
    "sg:phone":"+1 770 935 4292",
    "sg:postcode":"30044",
    "sg:province":"GA",
    "wof:name":"Multichoice Group Inc",
    "wof:placetype":"venue"
},
  "geometry": {"coordinates":[-84.084295,33.933792],"type":"Point"}
}