{
  "type": "Feature",
  "properties": {
    "iso:country":"US",
    "sg:address":"3950 Austell Rd",
    "sg:city":"Austell",
    "sg:classifiers":[
        {
            "category":"Health Services",
            "subcategory":"Hospital",
            "type":"Services"
        }
    ],
    "sg:phone":"+1 770 732 3880",
    "sg:postcode":"30106",
    "sg:province":"GA",
    "wof:name":"C HV Occupational Health",
    "wof:placetype":"venue"
},
  "geometry": {"coordinates":[-84.60199,33.855999],"type":"Point"}
}