{
  "type": "Feature",
  "properties": {
    "iso:country":"US",
    "sg:address":"1401 Peachtree Street NE",
    "sg:city":"Atlanta",
    "sg:classifiers":[
        {
            "category":"Professional",
            "subcategory":"Lawyer & Legal Services",
            "type":"Services"
        }
    ],
    "sg:phone":"+1 404 870 8074",
    "sg:postcode":"30309",
    "sg:province":"GA",
    "wof:name":"Tew & Associates",
    "wof:placetype":"venue"
},
  "geometry": {"coordinates":[-84.386633,33.792907],"type":"Point"}
}