{
  "type": "Feature",
  "properties": {
    "iso:country":"US",
    "sg:address":"3157 Bouchard Way NE",
    "sg:city":"Marietta",
    "sg:classifiers":[
        {
            "category":"Building & Trades",
            "subcategory":"Construction",
            "type":"Services"
        }
    ],
    "sg:phone":"+1 770 971 4575",
    "sg:postcode":"30066",
    "sg:province":"GA",
    "sg:tags":[
        "residential",
        "inside",
        "family"
    ],
    "wof:name":"Vastola Construction Corp",
    "wof:placetype":"venue"
},
  "geometry": {"coordinates":[-84.457742,34.052707],"type":"Point"}
}