{
  "type": "Feature",
  "properties": {
    "iso:country":"US",
    "sg:address":"73 Quail Hollow Dr",
    "sg:city":"Dallas",
    "sg:classifiers":[
        {
            "category":"Professional",
            "subcategory":"Accounting & Tax Preparation",
            "type":"Services"
        }
    ],
    "sg:phone":"+1 770 445 2926",
    "sg:postcode":"30157",
    "sg:province":"GA",
    "wof:name":"Advantage Tax & Accounting",
    "wof:placetype":"venue"
},
  "geometry": {"coordinates":[-84.734911,33.937701],"type":"Point"}
}