{
  "type": "Feature",
  "properties": {
    "iso:country":"US",
    "sg:address":"130 Chesterfield Ct SW",
    "sg:city":"Atlanta",
    "sg:classifiers":[
        {
            "category":"Freight",
            "type":"Transportation"
        }
    ],
    "sg:phone":"+1 770 991 0119",
    "sg:postcode":"30349",
    "sg:province":"GA",
    "wof:name":"A First Class Transportation",
    "wof:placetype":"venue"
},
  "geometry": {"coordinates":[-84.46222,33.590212],"type":"Point"}
}