{
  "type": "Feature",
  "properties": {
    "iso:country":"US",
    "sg:address":"7891 Taylor Downs Way",
    "sg:city":"Riverdale",
    "sg:classifiers":[
        {
            "category":"Building & Trades",
            "subcategory":"Construction",
            "type":"Services"
        }
    ],
    "sg:phone":"+1 770 477 5760",
    "sg:postcode":"30274",
    "sg:province":"GA",
    "sg:tags":[
        "contractor"
    ],
    "sg:website":"www.allurehomeandbusiness.org",
    "wof:name":"Allure Home & Business Reconstruction",
    "wof:placetype":"venue"
},
  "geometry": {"coordinates":[-84.401927,33.539481],"type":"Point"}
}