{
  "type": "Feature",
  "properties": {
    "iso:country":"US",
    "sg:address":"1475 Gabriel Dr",
    "sg:city":"Lawrenceville",
    "sg:classifiers":[
        {
            "category":"Professional",
            "type":"Services"
        }
    ],
    "sg:phone":"+1 770 338 2011",
    "sg:postcode":"30043",
    "sg:province":"GA",
    "sg:tags":[
        "establishment"
    ],
    "wof:name":"Focus Soft",
    "wof:placetype":"venue"
},
  "geometry": {"coordinates":[-84.03273299999999,33.981809],"type":"Point"}
}