{
  "type": "Feature",
  "properties": {
    "iso:country":"US",
    "sg:address":"154 Rosa St",
    "sg:city":"Rossville",
    "sg:classifiers":[
        {
            "category":"Wholesale",
            "subcategory":"Apparel",
            "type":"Manufacturing & Wholesale Goods"
        }
    ],
    "sg:phone":"+1 706 858 7517",
    "sg:postcode":"30741",
    "sg:province":"GA",
    "sg:tags":[
        "clothing"
    ],
    "wof:name":"Little Darlings",
    "wof:placetype":"venue"
},
  "geometry": {"coordinates":[-85.26481200000001,34.982262],"type":"Point"}
}