{
  "type": "Feature",
  "properties": {
    "iso:country":"US",
    "sg:address":"500 E 66th St",
    "sg:city":"Savannah",
    "sg:classifiers":[
        {
            "category":"Health Services",
            "subcategory":"Doctor",
            "type":"Services"
        }
    ],
    "sg:phone":"+1 912 354 9774",
    "sg:postcode":"31405",
    "sg:province":"GA",
    "sg:tags":[
        "medical"
    ],
    "wof:name":"David M Chalikian MD PHD",
    "wof:placetype":"venue"
},
  "geometry": {"coordinates":[-81.09764699999999,32.030012],"type":"Point"}
}