{
  "type": "Feature",
  "properties": {
    "addr:full":"724 Wounded Knee Cir Peachtree City GA 30269",
    "addr:housenumber":"724",
    "addr:postcode":"30269",
    "addr:street":"Wounded Knee Cir",
    "iso:country":"US",
    "sg:address":"724 Wounded Knee Cir",
    "sg:city":"Peachtree City",
    "sg:classifiers":[
        {
            "category":"Shopping",
            "subcategory":"Department Store",
            "type":"Retail Goods"
        }
    ],
    "sg:phone":"+1 770 631 4041",
    "sg:postcode":"30269",
    "sg:province":"GA",
    "wof:name":"Taz Mania Gutters",
    "wof:placetype":"venue"
},
  "geometry": {"coordinates":[-84.553883,33.42301],"type":"Point"}
}