{
  "type": "Feature",
  "properties": {
    "addr:full":"201 Fleetwood Ave Willacoochee GA 31650",
    "addr:housenumber":"201",
    "addr:postcode":"31650",
    "addr:street":"Fleetwood Ave",
    "iso:country":"US",
    "sg:address":"201 Fleetwood Ave",
    "sg:city":"Willacoochee",
    "sg:classifiers":[
        {
            "category":"Home & Garden",
            "subcategory":"Hardware",
            "type":"Retail Goods"
        }
    ],
    "sg:phone":"+1 912 534 5154",
    "sg:postcode":"31650",
    "sg:province":"GA",
    "wof:name":"Corbitt Hardware & Furniture",
    "wof:placetype":"venue"
},
  "geometry": {"coordinates":[-83.04763199999999,31.340663],"type":"Point"}
}