{
  "type": "Feature",
  "properties": {
    "addr:full":"7124 Peachtree Indstrial Blvd Norcross GA 30071",
    "addr:housenumber":"7124",
    "addr:postcode":"30071",
    "addr:street":"Peachtree Indstrial Blvd",
    "iso:country":"US",
    "sg:address":"7124 Peachtree Indstrial Blvd",
    "sg:city":"Norcross",
    "sg:classifiers":[
        {
            "category":"Restaurant",
            "type":"Food & Drink"
        }
    ],
    "sg:phone":"+1 770 903 9348",
    "sg:postcode":"30071",
    "sg:province":"GA",
    "sg:tags":[
        "sushi",
        "bar",
        "japanese"
    ],
    "sg:website":"www.sushiyoko.com",
    "wof:name":"Sushi Yoko",
    "wof:placetype":"venue"
},
  "geometry": {"coordinates":[-84.263429,33.930849],"type":"Point"}
}