{
  "type": "Feature",
  "properties": {
    "addr:full":"580 Creekwood Crossing E Roswell GA 30076",
    "addr:housenumber":"580",
    "addr:postcode":"30076",
    "addr:street":"Creekwood Crossing E",
    "iso:country":"US",
    "sg:address":"580 Creekwood Crossing E",
    "sg:city":"Roswell",
    "sg:classifiers":[
        {
            "category":"Communications",
            "type":"Services"
        }
    ],
    "sg:phone":"+1 678 231 3615",
    "sg:postcode":"30076",
    "sg:province":"GA",
    "sg:tags":[
        "web",
        "design"
    ],
    "sg:website":"www.zowbie.com",
    "wof:name":"Zowbie Consulting",
    "wof:placetype":"venue"
},
  "geometry": {"coordinates":[-84.30471300000001,34.017452],"type":"Point"}
}