{
  "type": "Feature",
  "properties": {
    "addr:full":"61 Broad Street NW Atlanta GA 30303",
    "addr:housenumber":"61",
    "addr:postcode":"30303",
    "addr:street":"Broad Street Nw",
    "iso:country":"US",
    "sg:address":"61 Broad Street NW",
    "sg:city":"Atlanta",
    "sg:classifiers":[
        {
            "category":"Restaurant",
            "type":"Food & Drink"
        }
    ],
    "sg:phone":"+1 404 523 4976",
    "sg:postcode":"30303",
    "sg:province":"GA",
    "wof:name":"Kentucky Fried Chicken",
    "wof:placetype":"venue"
},
  "geometry": {"coordinates":[-84.38965399999999,33.755686],"type":"Point"}
}