{
  "type": "Feature",
  "properties": {
    "iso:country":"US",
    "sg:address":"1140 Cockrell Dr NW",
    "sg:city":"Kennesaw",
    "sg:classifiers":[
        {
            "category":"Shopping",
            "type":"Retail Goods"
        }
    ],
    "sg:phone":"+1 770 590 5175",
    "sg:postcode":"30152",
    "sg:province":"GA",
    "sg:tags":[
        "merchandise"
    ],
    "wof:name":"Envision Home Theater",
    "wof:placetype":"venue"
},
  "geometry": {"coordinates":[-84.615054,33.981131],"type":"Point"}
}