{
  "type": "Feature",
  "properties": {
    "iso:country":"US",
    "sg:address":"1291 Fairmont Ave NW",
    "sg:city":"Atlanta",
    "sg:classifiers":[
        {
            "category":"Manufacturing",
            "subcategory":"Glass & Minerals",
            "type":"Manufacturing & Wholesale Goods"
        }
    ],
    "sg:phone":"+1 404 355 1441",
    "sg:postcode":"30318",
    "sg:province":"GA",
    "sg:tags":[
        "cut",
        "wood",
        "mfg"
    ],
    "sg:website":"www.silestoneusa.com",
    "wof:name":"Silestone Of Atlanta",
    "wof:placetype":"venue"
},
  "geometry": {"coordinates":[-84.422051,33.791541],"type":"Point"}
}