{
  "type": "Feature",
  "properties": {
    "iso:country":"US",
    "sg:address":"3111 Peachtree Dr NE",
    "sg:city":"Atlanta",
    "sg:classifiers":[
        {
            "category":"Shopping",
            "subcategory":"Clothing, Apparel, & Fashions",
            "type":"Retail Goods"
        }
    ],
    "sg:phone":"+1 404 237 3322",
    "sg:postcode":"30305",
    "sg:province":"GA",
    "sg:tags":[
        "alteration"
    ],
    "wof:name":"Garland's Cleaners & Laundry",
    "wof:placetype":"venue"
},
  "geometry": {"coordinates":[-84.36411699999999,33.840053],"type":"Point"}
}