{
  "type": "Feature",
  "properties": {
    "iso:country":"US",
    "sg:address":"488 Ponderosa Dr",
    "sg:city":"Ocilla",
    "sg:classifiers":[
        {
            "category":"Real Estate",
            "subcategory":"Real Estate Operator",
            "type":"Services"
        }
    ],
    "sg:phone":"+1 229 831 2945",
    "sg:postcode":"31774",
    "sg:province":"GA",
    "sg:tags":[
        "property",
        "lessor"
    ],
    "wof:name":"Amos Fletcher",
    "wof:placetype":"venue"
},
  "geometry": {"coordinates":[-83.384224,31.602973],"type":"Point"}
}