{
  "type": "Feature",
  "properties": {
    "iso:country":"US",
    "sg:address":"3180 Clairmont Rd NE # 311",
    "sg:city":"Atlanta",
    "sg:classifiers":[
        {
            "category":"Shopping",
            "subcategory":"Crafts & Fabrics",
            "type":"Retail Goods"
        }
    ],
    "sg:phone":"+1 404 634 3030",
    "sg:postcode":"30329",
    "sg:province":"GA",
    "sg:tags":[
        "adhesive",
        "glue"
    ],
    "wof:name":"Tape Specialties Co",
    "wof:placetype":"venue"
},
  "geometry": {"coordinates":[-84.31511399999999,33.851467],"type":"Point"}
}