{
  "type": "Feature",
  "properties": {
    "iso:country":"US",
    "sg:address":"1886 S Cobb Dr SE",
    "sg:city":"Marietta",
    "sg:classifiers":[
        {
            "category":"Retail",
            "subcategory":"Laundry & Dry Cleaning",
            "type":"Services"
        }
    ],
    "sg:phone":"+1 770 801 1669",
    "sg:postcode":"30060",
    "sg:province":"GA",
    "sg:tags":[
        "laundries-self",
        "operated",
        "washer",
        "dryer",
        "coin"
    ],
    "wof:name":"Magic Coin Laundry",
    "wof:placetype":"venue"
},
  "geometry": {"coordinates":[-84.54359599999999,33.907764],"type":"Point"}
}