{
  "type": "Feature",
  "properties": {
    "iso:country":"US",
    "sg:address":"1100 Johnson Ferry Road, Suite 400",
    "sg:city":"Atlanta",
    "sg:classifiers":[
        {
            "category":"Professional",
            "subcategory":"Employment Agencies",
            "type":"Services"
        }
    ],
    "sg:phone":"+1 678 412 0202",
    "sg:postcode":"30342",
    "sg:province":"GA",
    "sg:tags":[
        "technical"
    ],
    "sg:website":"http://www.comforce.com/index.asp",
    "wof:name":"COMFORCE",
    "wof:placetype":"venue"
},
  "geometry": {"coordinates":[-84.352699,33.907242],"type":"Point"}
}