{
  "type": "Feature",
  "properties": {
    "iso:country":"US",
    "sg:address":"6940 Mableton Pkwy SE",
    "sg:city":"Mableton",
    "sg:classifiers":[
        {
            "category":"Autos & Motor Vehicles",
            "subcategory":"Motorcycle Sales",
            "type":"Retail Goods"
        }
    ],
    "sg:phone":"+1 770 948 7330",
    "sg:postcode":"30126",
    "sg:province":"GA",
    "wof:name":"Advanced Cycles Sales & Service",
    "wof:placetype":"venue"
},
  "geometry": {"coordinates":[-84.5411,33.783901],"type":"Point"}
}