{
  "type": "Feature",
  "properties": {
    "iso:country":"US",
    "sg:address":"2759 Delk Rd SE # 2115",
    "sg:city":"Marietta",
    "sg:classifiers":[
        {
            "category":"Professional",
            "type":"Services"
        },
        {
            "category":"Freight",
            "type":"Transportation"
        },
        {
            "category":"Retail",
            "subcategory":"Auto Rental",
            "type":"Services"
        }
    ],
    "sg:phone":"+1 770 792 9956",
    "sg:postcode":"30067",
    "sg:province":"GA",
    "sg:tags":[
        "limousine",
        "trucking"
    ],
    "wof:name":"D & A Transportation",
    "wof:placetype":"venue"
},
  "geometry": {"coordinates":[-84.473046,33.923086],"type":"Point"}
}