{
  "type": "Feature",
  "properties": {
    "iso:country":"US",
    "sg:address":"344 Timber Mill Cir",
    "sg:city":"Carrollton",
    "sg:classifiers":[
        {
            "category":"Retail",
            "subcategory":"Repair Shop",
            "type":"Services"
        }
    ],
    "sg:phone":"+1 770 834 6751",
    "sg:postcode":"30116",
    "sg:province":"GA",
    "sg:tags":[
        "refrigeration"
    ],
    "wof:name":"Adamson Refrigeration",
    "wof:placetype":"venue"
},
  "geometry": {"coordinates":[-85.00221999999999,33.602423],"type":"Point"}
}