{
  "type": "Feature",
  "properties": {
    "addr:full":"1525 Spring Valley Rd Athens GA 30605",
    "addr:housenumber":"1525",
    "addr:postcode":"30605",
    "addr:street":"Spring Valley Rd",
    "iso:country":"US",
    "sg:address":"1525 Spring Valley Rd",
    "sg:city":"Athens",
    "sg:classifiers":[
        {
            "category":"Real Estate",
            "subcategory":"Real Estate Agent",
            "type":"Services"
        }
    ],
    "sg:phone":"+1 706 543 5457",
    "sg:postcode":"30605",
    "sg:province":"GA",
    "wof:name":"Rl Hall Inc",
    "wof:placetype":"venue"
},
  "geometry": {"coordinates":[-83.316532,33.964194],"type":"Point"}
}