{
  "type": "Feature",
  "properties": {
    "iso:country":"US",
    "sg:address":"852 Avon Ave SW",
    "sg:city":"Atlanta",
    "sg:classifiers":[
        {
            "category":"Building & Trades",
            "subcategory":"Construction",
            "type":"Services"
        }
    ],
    "sg:phone":"+1 404 758 9208",
    "sg:postcode":"30310",
    "sg:province":"GA",
    "sg:tags":[
        "welder"
    ],
    "wof:name":"Roebuck Welding & Machine Co",
    "wof:placetype":"venue"
},
  "geometry": {"coordinates":[-84.416033,33.722217],"type":"Point"}
}