{
  "type": "Feature",
  "properties": {
    "iso:country":"US",
    "sg:address":"3421 Land Rd",
    "sg:city":"Canton",
    "sg:classifiers":[
        {
            "category":"Food & Beverages",
            "subcategory":"Groceries & Convenience Stores",
            "type":"Retail Goods"
        }
    ],
    "sg:phone":"+1 770 479 8316",
    "sg:postcode":"30114",
    "sg:province":"GA",
    "sg:tags":[
        "station",
        "gasoline"
    ],
    "wof:name":"Clayton Food Store",
    "wof:placetype":"venue"
},
  "geometry": {"coordinates":[-84.48933100000001,34.33023],"type":"Point"}
}