{
  "type": "Feature",
  "properties": {
    "addr:full":"2364 Mills Bend Decatur GA 30034",
    "addr:housenumber":"2364",
    "addr:postcode":"30034",
    "addr:street":"Mills Bend",
    "iso:country":"US",
    "sg:address":"2364 Mills Bend",
    "sg:city":"Decatur",
    "sg:classifiers":[
        {
            "category":"Shopping",
            "subcategory":"Clothing, Apparel, & Fashions",
            "type":"Retail Goods"
        }
    ],
    "sg:phone":"+1 404 241 7311",
    "sg:postcode":"30034",
    "sg:province":"GA",
    "wof:name":"Haberdashery Collections",
    "wof:placetype":"venue"
},
  "geometry": {"coordinates":[-84.29375899999999,33.708936],"type":"Point"}
}