{
  "type": "Feature",
  "properties": {
    "addr:full":"5389 New Peachtree Rd Atlanta GA 30341",
    "addr:housenumber":"5389",
    "addr:postcode":"30341",
    "addr:street":"New Peachtree Rd",
    "iso:country":"US",
    "sg:address":"5389 New Peachtree Rd",
    "sg:city":"Atlanta",
    "sg:classifiers":[
        {
            "category":"Utilities",
            "subcategory":"Mobile Phone",
            "type":"Services"
        }
    ],
    "sg:phone":"+1 770 454 9477",
    "sg:postcode":"30341",
    "sg:province":"GA",
    "sg:tags":[
        "communication",
        "cellular",
        "telephone",
        "merchandise",
        "radiotelephone"
    ],
    "wof:name":"Infinite Communications",
    "wof:placetype":"venue"
},
  "geometry": {"coordinates":[-84.30006400000001,33.890692],"type":"Point"}
}