{
  "type": "Feature",
  "properties": {
    "iso:country":"US",
    "sg:address":"6651 Covington Hwy",
    "sg:city":"Lithonia",
    "sg:classifiers":[
        {
            "category":"Personal",
            "subcategory":"Barber",
            "type":"Services"
        }
    ],
    "sg:phone":"+1 678 518 0945",
    "sg:postcode":"30058",
    "sg:province":"GA",
    "wof:name":"Raykel Precision Cuts",
    "wof:placetype":"venue"
},
  "geometry": {"coordinates":[-84.1464,33.717602],"type":"Point"}
}