{
  "type": "Feature",
  "properties": {
    "iso:country":"US",
    "sg:address":"160 Clairemont Ave",
    "sg:city":"Decatur",
    "sg:classifiers":[
        {
            "category":"Retail",
            "subcategory":"Auto Rental",
            "type":"Services"
        }
    ],
    "sg:phone":"+1 404 377 5550",
    "sg:postcode":"30030",
    "sg:province":"GA",
    "sg:tags":[
        "truck"
    ],
    "wof:name":"Phoenix Enterprises",
    "wof:placetype":"venue"
},
  "geometry": {"coordinates":[-84.296588,33.776489],"type":"Point"}
}