{
  "type": "Feature",
  "properties": {
    "iso:country":"US",
    "sg:address":"1695 Lebanon Rd NW",
    "sg:city":"Lawrenceville",
    "sg:classifiers":[
        {
            "category":"Professional",
            "subcategory":"Computer Services",
            "type":"Services"
        },
        {
            "category":"Wholesale",
            "subcategory":"Auto Parts",
            "type":"Manufacturing & Wholesale Goods"
        }
    ],
    "sg:phone":"+1 770 822 6973",
    "sg:postcode":"30043",
    "sg:province":"GA",
    "sg:tags":[
        "engine",
        "development",
        "automotive",
        "testing",
        "sales",
        "equipment",
        "electrical",
        "software"
    ],
    "wof:name":"Southern Automotive Test Inc",
    "wof:placetype":"venue"
},
  "geometry": {"coordinates":[-84.065862,33.976609],"type":"Point"}
}