{
  "type": "Feature",
  "properties": {
    "addr:full":"2403 Dawson Rd Albany GA 31707",
    "addr:housenumber":"2403",
    "addr:postcode":"31707",
    "addr:street":"Dawson Rd",
    "iso:country":"US",
    "sg:address":"2403 Dawson Rd",
    "sg:city":"Albany",
    "sg:classifiers":[
        {
            "category":"Autos & Motor Vehicles",
            "subcategory":"Fuel & Gas Station",
            "type":"Retail Goods"
        }
    ],
    "sg:phone":"+1 229 446 4406",
    "sg:postcode":"31707",
    "sg:province":"GA",
    "sg:tags":[
        "oil"
    ],
    "wof:name":"Bay Station",
    "wof:placetype":"venue"
},
  "geometry": {"coordinates":[-84.20772599999999,31.606769],"type":"Point"}
}