{
  "type": "Feature",
  "properties": {
    "iso:country":"US",
    "sg:address":"105 W 14th St",
    "sg:city":"Rincon",
    "sg:classifiers":[
        {
            "category":"Personal",
            "subcategory":"Beauty Salon",
            "type":"Services"
        }
    ],
    "sg:phone":"+1 912 826 1776",
    "sg:postcode":"31326",
    "sg:province":"GA",
    "wof:name":"N Styles Cuts",
    "wof:placetype":"venue"
},
  "geometry": {"coordinates":[-81.233921,32.283606],"type":"Point"}
}