{
  "type": "Feature",
  "properties": {
    "iso:country":"US",
    "sg:address":"1129 Trailridge Ln",
    "sg:city":"Atlanta",
    "sg:classifiers":[
        {
            "category":"Professional",
            "type":"Services"
        }
    ],
    "sg:phone":"+1 678 443 9000",
    "sg:postcode":"30338",
    "sg:province":"GA",
    "wof:name":"Barker Home",
    "wof:placetype":"venue"
},
  "geometry": {"coordinates":[-84.342817,33.942886],"type":"Point"}
}