{
  "type": "Feature",
  "properties": {
    "addr:full":"2026 Mount Zion Rd Morrow GA 30260",
    "addr:housenumber":"2026",
    "addr:postcode":"30260",
    "addr:street":"Mount Zion Rd",
    "iso:country":"US",
    "sg:address":"2026 Mount Zion Rd",
    "sg:city":"Morrow",
    "sg:classifiers":[
        {
            "category":"Autos & Motor Vehicles",
            "subcategory":"Auto Supplies",
            "type":"Retail Goods"
        }
    ],
    "sg:phone":"+1 770 603 9966",
    "sg:postcode":"30260",
    "sg:province":"GA",
    "sg:tags":[
        "repair",
        "brake",
        "tire"
    ],
    "sg:website":"http://www.ntb.com",
    "wof:name":"Ntb-National Tire & Battery",
    "wof:placetype":"venue"
},
  "geometry": {"coordinates":[-84.322701,33.561501],"type":"Point"}
}