{
  "type": "Feature",
  "properties": {
    "iso:country":"US",
    "sg:address":"800 Greenwood Trl SE",
    "sg:city":"Conyers",
    "sg:classifiers":[
        {
            "category":"Professional",
            "subcategory":"Business Services",
            "type":"Services"
        }
    ],
    "sg:phone":"+1 770 483 4368",
    "sg:postcode":"30094",
    "sg:province":"GA",
    "wof:name":"Abrazar Interiors",
    "wof:placetype":"venue"
},
  "geometry": {"coordinates":[-84.022764,33.559044],"type":"Point"}
}