{
  "type": "Feature",
  "properties": {
    "addr:full":"4480 Riverside Dr Macon GA 31210",
    "addr:housenumber":"4480",
    "addr:postcode":"31210",
    "addr:street":"Riverside Dr",
    "iso:country":"US",
    "sg:address":"4480 Riverside Dr",
    "sg:city":"Macon",
    "sg:classifiers":[
        {
            "category":"Building & Trades",
            "subcategory":"Construction",
            "type":"Services"
        },
        {
            "category":"Wholesale",
            "subcategory":"Metals & Minerals",
            "type":"Manufacturing & Wholesale Goods"
        }
    ],
    "sg:phone":"+1 478 475 4220",
    "sg:postcode":"31210",
    "sg:province":"GA",
    "sg:tags":[
        "steel",
        "industrial",
        "center",
        "equipment",
        "fabrication",
        "welding"
    ],
    "wof:name":"Industrial Steel & Machinery",
    "wof:placetype":"venue"
},
  "geometry": {"coordinates":[-83.703458,32.913744],"type":"Point"}
}