{
  "type": "Feature",
  "properties": {
    "addr:full":"1105 Russell Pkwy Warner Robins GA 31088",
    "addr:housenumber":"1105",
    "addr:postcode":"31088",
    "addr:street":"Russell Pkwy",
    "iso:country":"US",
    "sg:address":"1105 Russell Pkwy",
    "sg:city":"Warner Robins",
    "sg:classifiers":[
        {
            "category":"Organizations",
            "subcategory":"Religious Organization",
            "type":"Services"
        }
    ],
    "sg:phone":"+1 478 923 1829",
    "sg:postcode":"31088",
    "sg:province":"GA",
    "wof:name":"Harvest Church",
    "wof:placetype":"venue"
},
  "geometry": {"coordinates":[-83.644448,32.593823],"type":"Point"}
}