{
  "type": "Feature",
  "properties": {
    "iso:country":"US",
    "sg:address":"4507 Exmoor Dr",
    "sg:city":"Marietta",
    "sg:classifiers":[
        {
            "category":"Shopping",
            "subcategory":"Gifts & Souvenirs",
            "type":"Retail Goods"
        }
    ],
    "sg:phone":"+1 678 560 3797",
    "sg:postcode":"30067",
    "sg:province":"GA",
    "wof:name":"Campbell Card Co",
    "wof:placetype":"venue"
},
  "geometry": {"coordinates":[-84.41777399999999,33.953877],"type":"Point"}
}