{
  "type": "Feature",
  "properties": {
    "addr:full":"516 US Hwy 80 Savannah GA 31408",
    "addr:housenumber":"516",
    "addr:postcode":"31408",
    "addr:street":"Us Hwy 80",
    "iso:country":"US",
    "sg:address":"516 US Hwy 80",
    "sg:city":"Savannah",
    "sg:classifiers":[
        {
            "category":"Shopping",
            "subcategory":"Pharmacy",
            "type":"Retail Goods"
        }
    ],
    "sg:phone":"+1 912 966 1416",
    "sg:postcode":"31408",
    "sg:province":"GA",
    "wof:name":"Quick Rx Drugs Inc",
    "wof:placetype":"venue"
},
  "geometry": {"coordinates":[-81.147131,32.094382],"type":"Point"}
}