{
  "type": "Feature",
  "properties": {
    "addr:full":"425 Loneoak Dr Senoia GA 30276",
    "addr:housenumber":"425",
    "addr:postcode":"30276",
    "addr:street":"Loneoak Dr",
    "iso:country":"US",
    "sg:address":"425 Loneoak Dr",
    "sg:city":"Senoia",
    "sg:classifiers":[
        {
            "category":"Freight",
            "type":"Transportation"
        }
    ],
    "sg:phone":"+1 770 719 7711",
    "sg:postcode":"30276",
    "sg:province":"GA",
    "sg:tags":[
        "operator",
        "trucking",
        "care",
        "day",
        "child"
    ],
    "wof:name":"Day At A Time Inc",
    "wof:placetype":"venue"
},
  "geometry": {"coordinates":[-84.51369699999999,33.314978],"type":"Point"}
}