{
  "type": "Feature",
  "properties": {
    "addr:full":"1000 Katie Kerr Dr Decatur GA 30030",
    "addr:housenumber":"1000",
    "addr:postcode":"30030",
    "addr:street":"Katie Kerr Dr",
    "iso:country":"US",
    "sg:address":"1000 Katie Kerr Dr",
    "sg:city":"Decatur",
    "sg:classifiers":[
        {
            "category":"Shopping",
            "subcategory":"Pets & Pet Supplies",
            "type":"Retail Goods"
        }
    ],
    "sg:phone":"+1 404 234 2105",
    "sg:postcode":"30030",
    "sg:province":"GA",
    "sg:tags":[
        "furnishing",
        "dog",
        "store",
        "cat"
    ],
    "wof:name":"The Veriuni Store",
    "wof:placetype":"venue"
},
  "geometry": {"coordinates":[-84.27571399999999,33.765526],"type":"Point"}
}