{
  "type": "Feature",
  "properties": {
    "addr:full":"235 Gwinnett St Fayetteville GA 30214",
    "addr:housenumber":"235",
    "addr:postcode":"30214",
    "addr:street":"Gwinnett St",
    "iso:country":"US",
    "sg:address":"235 Gwinnett St",
    "sg:city":"Fayetteville",
    "sg:classifiers":[
        {
            "category":"Retail",
            "subcategory":"Auto Repair",
            "type":"Services"
        }
    ],
    "sg:phone":"+1 770 460 7517",
    "sg:postcode":"30214",
    "sg:province":"GA",
    "sg:tags":[
        "glass",
        "replacement"
    ],
    "wof:name":"Arrow Auto Glass Co",
    "wof:placetype":"venue"
},
  "geometry": {"coordinates":[-84.442492,33.452628],"type":"Point"}
}