{
  "type": "Feature",
  "properties": {
    "iso:country":"US",
    "sg:address":"1103 Lewis Roberts Rd",
    "sg:city":"Jefferson",
    "sg:classifiers":[
        {
            "category":"Manufacturing",
            "subcategory":"Retail Goods",
            "type":"Manufacturing & Wholesale Goods"
        }
    ],
    "sg:phone":"+1 706 367 0800",
    "sg:postcode":"30549",
    "sg:province":"GA",
    "sg:tags":[
        "product",
        "mfg"
    ],
    "wof:name":"Wac Industries Inc",
    "wof:placetype":"venue"
},
  "geometry": {"coordinates":[-83.661601,34.088596],"type":"Point"}
}