{
  "type": "Feature",
  "properties": {
    "addr:full":"705 W Jones St Savannah GA 31401",
    "addr:housenumber":"705",
    "addr:postcode":"31401",
    "addr:street":"W Jones St",
    "iso:country":"US",
    "sg:address":"705 W Jones St",
    "sg:city":"Savannah",
    "sg:classifiers":[
        {
            "category":"Wholesale",
            "subcategory":"Electrical",
            "type":"Manufacturing & Wholesale Goods"
        }
    ],
    "sg:phone":"+1 912 965 0060",
    "sg:postcode":"31401",
    "sg:province":"GA",
    "sg:tags":[
        "parts",
        "supply"
    ],
    "wof:name":"GE",
    "wof:placetype":"venue"
},
  "geometry": {"coordinates":[-81.10461100000001,32.075328],"type":"Point"}
}