{
  "type": "Feature",
  "properties": {
    "iso:country":"US",
    "sg:address":"1950 N Park Pl NW",
    "sg:city":"Atlanta",
    "sg:classifiers":[
        {
            "category":"Banks & Credit Unions",
            "subcategory":"Bank",
            "type":"Services"
        }
    ],
    "sg:phone":"+1 770 955 6282",
    "sg:postcode":"30339",
    "sg:province":"GA",
    "sg:tags":[
        "broker",
        "mortgage"
    ],
    "wof:name":"Kingston Mortgage Inc",
    "wof:placetype":"venue"
},
  "geometry": {"coordinates":[-84.48011,33.903185],"type":"Point"}
}