{
  "type": "Feature",
  "properties": {
    "iso:country":"US",
    "sg:address":"5235 Buford Hwy NE",
    "sg:city":"Atlanta",
    "sg:classifiers":[
        {
            "category":"Shopping",
            "subcategory":"Clothing, Apparel, & Fashions",
            "type":"Retail Goods"
        },
        {
            "category":"Shopping",
            "subcategory":"Baby Store",
            "type":"Retail Goods"
        }
    ],
    "sg:phone":"+1 770 457 3446",
    "sg:postcode":"30340",
    "sg:province":"GA",
    "sg:tags":[
        "children's",
        "infant",
        "clothing",
        "wear"
    ],
    "wof:name":"Happy Land II",
    "wof:placetype":"venue"
},
  "geometry": {"coordinates":[-84.2826,33.895901],"type":"Point"}
}