{
  "type": "Feature",
  "properties": {
    "addr:full":"5700 Buford Hwy NE Atlanta GA 30340",
    "addr:housenumber":"5700",
    "addr:postcode":"30340",
    "addr:street":"Buford Hwy Ne",
    "iso:country":"US",
    "sg:address":"5700 Buford Hwy NE",
    "sg:city":"Atlanta",
    "sg:classifiers":[
        {
            "category":"Fast Food",
            "type":"Food & Drink"
        }
    ],
    "sg:phone":"+1 770 936 9701",
    "sg:postcode":"30340",
    "sg:province":"GA",
    "wof:name":"Chick-Fil-A",
    "wof:placetype":"venue"
},
  "geometry": {"coordinates":[-84.26988799999999,33.906547],"type":"Point"}
}