{
  "type": "Feature",
  "properties": {
    "iso:country":"US",
    "sg:address":"2145 Old Milton Pkwy",
    "sg:city":"Alpharetta",
    "sg:classifiers":[
        {
            "category":"Retail",
            "subcategory":"Car Wash",
            "type":"Services"
        }
    ],
    "sg:phone":"+1 770 521 0599",
    "sg:postcode":"30009",
    "sg:province":"GA",
    "wof:name":"New Mammoth Detail Salon",
    "wof:placetype":"venue"
},
  "geometry": {"coordinates":[-84.297033,34.071022],"type":"Point"}
}