{
  "type": "Feature",
  "properties": {
    "iso:country":"US",
    "sg:address":"487 N Leard St",
    "sg:city":"Hartwell",
    "sg:classifiers":[
        {
            "category":"Manufacturing",
            "subcategory":"Rubber & Plastics",
            "type":"Manufacturing & Wholesale Goods"
        }
    ],
    "sg:phone":"+1 706 376 6909",
    "sg:postcode":"30643",
    "sg:province":"GA",
    "wof:name":"Toccoa Injection Molding",
    "wof:placetype":"venue"
},
  "geometry": {"coordinates":[-82.937906,34.362014],"type":"Point"}
}