{
  "type": "Feature",
  "properties": {
    "addr:full":"707 S 3rd Ave Chatsworth GA 30705",
    "addr:housenumber":"707",
    "addr:postcode":"30705",
    "addr:street":"S 3Rd Ave",
    "iso:country":"US",
    "sg:address":"707 S 3rd Ave",
    "sg:city":"Chatsworth",
    "sg:classifiers":[
        {
            "category":"Real Estate",
            "subcategory":"Real Estate Agent",
            "type":"Services"
        }
    ],
    "sg:phone":"+1 706 695 2911",
    "sg:postcode":"30705",
    "sg:province":"GA",
    "wof:name":"Martha Young Realty",
    "wof:placetype":"venue"
},
  "geometry": {"coordinates":[-84.76951699999999,34.756911],"type":"Point"}
}