{
  "type": "Feature",
  "properties": {
    "addr:full":"571 Dallas Hwy SE Cartersville GA 30120",
    "addr:housenumber":"571",
    "addr:postcode":"30120",
    "addr:street":"Dallas Hwy Se",
    "iso:country":"US",
    "sg:address":"571 Dallas Hwy SE",
    "sg:city":"Cartersville",
    "sg:classifiers":[
        {
            "category":"Personal",
            "subcategory":"Tanning Parlor",
            "type":"Services"
        }
    ],
    "sg:phone":"+1 770 606 1940",
    "sg:postcode":"30120",
    "sg:province":"GA",
    "sg:tags":[
        "salon"
    ],
    "wof:name":"Long Weekends",
    "wof:placetype":"venue"
},
  "geometry": {"coordinates":[-84.847354,34.098587],"type":"Point"}
}