{
  "type": "Feature",
  "properties": {
    "iso:country":"US",
    "sg:address":"757 Ocilla Hwy",
    "sg:city":"Fitzgerald",
    "sg:classifiers":[
        {
            "category":"Building & Trades",
            "subcategory":"Construction",
            "type":"Services"
        }
    ],
    "sg:phone":"+1 229 423 0960",
    "sg:postcode":"31750",
    "sg:province":"GA",
    "sg:tags":[
        "general",
        "contractor"
    ],
    "wof:name":"Southern Rock & Construction",
    "wof:placetype":"venue"
},
  "geometry": {"coordinates":[-83.240973,31.65733],"type":"Point"}
}