{
  "type": "Feature",
  "properties": {
    "addr:full":"4757 Canton Rd Marietta GA 30066",
    "addr:housenumber":"4757",
    "addr:postcode":"30066",
    "addr:street":"Canton Rd",
    "iso:country":"US",
    "sg:address":"4757 Canton Rd",
    "sg:city":"Marietta",
    "sg:classifiers":[
        {
            "category":"Banks & Credit Unions",
            "subcategory":"Financial Services",
            "type":"Services"
        }
    ],
    "sg:phone":"+1 770 517 5800",
    "sg:postcode":"30066",
    "sg:province":"GA",
    "sg:tags":[
        "broker",
        "mortgage"
    ],
    "wof:name":"Dependable Mortgage Service Inc",
    "wof:placetype":"venue"
},
  "geometry": {"coordinates":[-84.521452,34.067355],"type":"Point"}
}