{
  "type": "Feature",
  "properties": {
    "addr:full":"25 Bretts Bend Sharpsburg GA 30277",
    "addr:housenumber":"25",
    "addr:postcode":"30277",
    "addr:street":"Bretts Bend",
    "iso:country":"US",
    "sg:address":"25 Bretts Bend",
    "sg:city":"Sharpsburg",
    "sg:classifiers":[
        {
            "category":"Building & Trades",
            "subcategory":"Construction",
            "type":"Services"
        }
    ],
    "sg:phone":"+1 770 252 0851",
    "sg:postcode":"30277",
    "sg:province":"GA",
    "sg:tags":[
        "house"
    ],
    "wof:name":"Law Builders",
    "wof:placetype":"venue"
},
  "geometry": {"coordinates":[-84.653188,33.35457],"type":"Point"}
}