{
  "type": "Feature",
  "properties": {
    "iso:country":"US",
    "sg:address":"8667 Shoreline Dr",
    "sg:city":"Jonesboro",
    "sg:classifiers":[
        {
            "category":"Home & Garden",
            "subcategory":"Furniture",
            "type":"Retail Goods"
        }
    ],
    "sg:phone":"+1 770 471 9373",
    "sg:postcode":"30236",
    "sg:province":"GA",
    "wof:name":"Grapetree Furniture",
    "wof:placetype":"venue"
},
  "geometry": {"coordinates":[-84.3107,33.520115],"type":"Point"}
}