{
  "type": "Feature",
  "properties": {
    "iso:country":"US",
    "sg:address":"115 Ashley Dr",
    "sg:city":"McDonough",
    "sg:classifiers":[
        {
            "category":"Building & Trades",
            "subcategory":"Construction",
            "type":"Services"
        }
    ],
    "sg:phone":"+1 678 432 1842",
    "sg:postcode":"30252",
    "sg:province":"GA",
    "sg:tags":[
        "contractor"
    ],
    "wof:name":"Atlanta Coring",
    "wof:placetype":"venue"
},
  "geometry": {"coordinates":[-84.12143,33.468767],"type":"Point"}
}