{
  "type": "Feature",
  "properties": {
    "iso:country":"US",
    "sg:address":"980 Cobb Place Blvd NW",
    "sg:city":"Kennesaw",
    "sg:classifiers":[
        {
            "category":"Wholesale",
            "subcategory":"Furniture",
            "type":"Manufacturing & Wholesale Goods"
        }
    ],
    "sg:phone":"+1 770 590 7575",
    "sg:postcode":"30144",
    "sg:province":"GA",
    "wof:name":"US Designs",
    "wof:placetype":"venue"
},
  "geometry": {"coordinates":[-84.582722,34.009033],"type":"Point"}
}