{
  "type": "Feature",
  "properties": {
    "addr:full":"2184 McGee Rd Snellville GA 30078",
    "addr:housenumber":"2184",
    "addr:postcode":"30078",
    "addr:street":"Mcgee Rd",
    "iso:country":"US",
    "sg:address":"2184 McGee Rd",
    "sg:city":"Snellville",
    "sg:classifiers":[
        {
            "category":"Retail",
            "subcategory":"Veterinary Services",
            "type":"Services"
        }
    ],
    "sg:phone":"+1 770 972 0447",
    "sg:postcode":"30078",
    "sg:province":"GA",
    "sg:tags":[
        "veterinarian"
    ],
    "wof:name":"Strong Ashley DVM",
    "wof:placetype":"venue"
},
  "geometry": {"coordinates":[-84.033384,33.854612],"type":"Point"}
}