{
  "type": "Feature",
  "properties": {
    "addr:full":"1703 Norman Dr Valdosta GA 31601",
    "addr:housenumber":"1703",
    "addr:postcode":"31601",
    "addr:street":"Norman Dr",
    "iso:country":"US",
    "sg:address":"1703 Norman Dr",
    "sg:city":"Valdosta",
    "sg:classifiers":[
        {
            "category":"Professional",
            "subcategory":"Accounting & Tax Preparation",
            "type":"Services"
        }
    ],
    "sg:phone":"+1 229 242 9485",
    "sg:postcode":"31601",
    "sg:province":"GA",
    "sg:tags":[
        "return",
        "filing"
    ],
    "wof:name":"Jackson Hewitt Tax Svc",
    "wof:placetype":"venue"
},
  "geometry": {"coordinates":[-83.32066399999999,30.840121],"type":"Point"}
}