{
  "type": "Feature",
  "properties": {
    "addr:full":"2797 Campbellton Road SW Atlanta GA 30311",
    "addr:housenumber":"2797",
    "addr:postcode":"30311",
    "addr:street":"Campbellton Road Sw",
    "iso:country":"US",
    "sg:address":"2797 Campbellton Road SW",
    "sg:city":"Atlanta",
    "sg:classifiers":[
        {
            "category":"Health Services",
            "subcategory":"Dentist",
            "type":"Services"
        }
    ],
    "sg:phone":"+1 404 346 1120",
    "sg:postcode":"30311",
    "sg:province":"GA",
    "wof:name":"Weaver John T DMD",
    "wof:placetype":"venue"
},
  "geometry": {"coordinates":[-84.48027500000001,33.700491],"type":"Point"}
}