{
  "type": "Feature",
  "properties": {
    "addr:full":"11585 Jones Bridge Rd Alpharetta GA 30022",
    "addr:housenumber":"11585",
    "addr:postcode":"30022",
    "addr:street":"Jones Bridge Rd",
    "iso:country":"US",
    "sg:address":"11585 Jones Bridge Rd",
    "sg:city":"Alpharetta",
    "sg:classifiers":[
        {
            "category":"Health Services",
            "subcategory":"Doctor",
            "type":"Services"
        }
    ],
    "sg:phone":"+1 770 663 0955",
    "sg:postcode":"30022",
    "sg:province":"GA",
    "sg:tags":[
        "dentist"
    ],
    "wof:name":"Matt T Walton DDS",
    "wof:placetype":"venue"
},
  "geometry": {"coordinates":[-84.21512,34.061854],"type":"Point"}
}