{
  "type": "Feature",
  "properties": {
    "addr:full":"120 Commerce Cir Fayetteville GA 30214",
    "addr:housenumber":"120",
    "addr:postcode":"30214",
    "addr:street":"Commerce Cir",
    "iso:country":"US",
    "sg:address":"120 Commerce Cir",
    "sg:city":"Fayetteville",
    "sg:classifiers":[
        {
            "category":"Professional",
            "subcategory":"Accounting & Tax Preparation",
            "type":"Services"
        }
    ],
    "sg:phone":"+1 770 460 0022",
    "sg:postcode":"30214",
    "sg:province":"GA",
    "sg:tags":[
        "return"
    ],
    "wof:name":"Lee John E Accounting Tax Svc",
    "wof:placetype":"venue"
},
  "geometry": {"coordinates":[-84.45414,33.464153],"type":"Point"}
}