{
  "type": "Feature",
  "properties": {
    "addr:full":"4366 Sardis Rd Gainesville GA 30506",
    "addr:housenumber":"4366",
    "addr:postcode":"30506",
    "addr:street":"Sardis Rd",
    "iso:country":"US",
    "sg:address":"4366 Sardis Rd",
    "sg:city":"Gainesville",
    "sg:classifiers":[
        {
            "category":"Manufacturing",
            "subcategory":"Printing",
            "type":"Manufacturing & Wholesale Goods"
        }
    ],
    "sg:phone":"+1 770 531 0468",
    "sg:postcode":"30506",
    "sg:province":"GA",
    "sg:tags":[
        "printer"
    ],
    "wof:name":"Lanier Envelope Printing",
    "wof:placetype":"venue"
},
  "geometry": {"coordinates":[-83.899748,34.371409],"type":"Point"}
}