{
  "type": "Feature",
  "properties": {
    "addr:full":"1231 Gracewood Ave SE Atlanta GA 30316",
    "addr:housenumber":"1231",
    "addr:postcode":"30316",
    "addr:street":"Gracewood Ave Se",
    "iso:country":"US",
    "sg:address":"1231 Gracewood Ave SE",
    "sg:city":"Atlanta",
    "sg:classifiers":[
        {
            "category":"Professional",
            "subcategory":"Business Services",
            "type":"Services"
        }
    ],
    "sg:phone":"+1 404 624 4501",
    "sg:postcode":"30316",
    "sg:province":"GA",
    "wof:name":"A & Home Inspection",
    "wof:placetype":"venue"
},
  "geometry": {"coordinates":[-84.34658899999999,33.732864],"type":"Point"}
}