{
  "type": "Feature",
  "properties": {
    "addr:full":"2922 Watson Blvd Centerville GA 31028",
    "addr:housenumber":"2922",
    "addr:postcode":"31028",
    "addr:street":"Watson Blvd",
    "iso:country":"US",
    "sg:address":"2922 Watson Blvd",
    "sg:city":"Centerville",
    "sg:classifiers":[
        {
            "category":"Shopping",
            "subcategory":"Department Store",
            "type":"Retail Goods"
        }
    ],
    "sg:phone":"+1 478 953 8828",
    "sg:postcode":"31028",
    "sg:province":"GA",
    "sg:tags":[
        "shop"
    ],
    "wof:name":"Lesley's Fashion Plus",
    "wof:placetype":"venue"
},
  "geometry": {"coordinates":[-83.684315,32.618335],"type":"Point"}
}