{
  "type": "Feature",
  "properties": {
    "addr:full":"1233 Elegance Ct Stone Mountain GA 30083",
    "addr:housenumber":"1233",
    "addr:postcode":"30083",
    "addr:street":"Elegance Ct",
    "iso:country":"US",
    "sg:address":"1233 Elegance Ct",
    "sg:city":"Stone Mountain",
    "sg:classifiers":[
        {
            "category":"Shopping",
            "subcategory":"Computers & Home Electronics",
            "type":"Retail Goods"
        }
    ],
    "sg:phone":"+1 404 299 8496",
    "sg:postcode":"30083",
    "sg:province":"GA",
    "sg:tags":[
        "equipment"
    ],
    "wof:name":"1st Class Electronics",
    "wof:placetype":"venue"
},
  "geometry": {"coordinates":[-84.21088899999999,33.815908],"type":"Point"}
}