{
  "type": "Feature",
  "properties": {
    "addr:full":"6615 Millwood Rd Cumming GA 30041",
    "addr:housenumber":"6615",
    "addr:postcode":"30041",
    "addr:street":"Millwood Rd",
    "iso:country":"US",
    "sg:address":"6615 Millwood Rd",
    "sg:city":"Cumming",
    "sg:classifiers":[
        {
            "category":"Professional",
            "subcategory":"Business Services",
            "type":"Services"
        }
    ],
    "sg:phone":"+1 770 889 1465",
    "sg:postcode":"30041",
    "sg:province":"GA",
    "wof:name":"Dhd Enterprises Inc",
    "wof:placetype":"venue"
},
  "geometry": {"coordinates":[-84.01631,34.273748],"type":"Point"}
}