{
  "type": "Feature",
  "properties": {
    "addr:full":"712 Kennolia Dr SW Atlanta GA 30310",
    "addr:housenumber":"712",
    "addr:postcode":"30310",
    "addr:street":"Kennolia Dr Sw",
    "iso:country":"US",
    "sg:address":"712 Kennolia Dr SW",
    "sg:city":"Atlanta",
    "sg:classifiers":[
        {
            "category":"Arts & Performance",
            "subcategory":"Theater",
            "type":"Entertainment"
        }
    ],
    "sg:phone":"+1 404 897 1895",
    "sg:postcode":"30310",
    "sg:province":"GA",
    "sg:tags":[
        "entertainer"
    ],
    "wof:name":"Crossroads Jazz Entertainment",
    "wof:placetype":"venue"
},
  "geometry": {"coordinates":[-84.448904,33.735537],"type":"Point"}
}