{
  "type": "Feature",
  "properties": {
    "addr:full":"703 E Hill Ave Valdosta GA 31601",
    "addr:housenumber":"703",
    "addr:postcode":"31601",
    "addr:street":"E Hill Ave",
    "iso:country":"US",
    "sg:address":"703 E Hill Ave",
    "sg:city":"Valdosta",
    "sg:classifiers":[
        {
            "category":"Retail",
            "subcategory":"Auto Repair",
            "type":"Services"
        }
    ],
    "sg:phone":"+1 229 247 8698",
    "sg:postcode":"31601",
    "sg:province":"GA",
    "sg:tags":[
        "body",
        "automotive",
        "painting",
        "automobile"
    ],
    "wof:name":"John's Body Shop",
    "wof:placetype":"venue"
},
  "geometry": {"coordinates":[-83.26765,30.834881],"type":"Point"}
}