{
  "type": "Feature",
  "properties": {
    "iso:country":"US",
    "sg:address":"3151 Williams Rd",
    "sg:city":"Columbus",
    "sg:classifiers":[
        {
            "category":"Professional",
            "subcategory":"Accounting & Tax Preparation",
            "type":"Services"
        }
    ],
    "sg:phone":"+1 706 324 1622",
    "sg:postcode":"31909",
    "sg:province":"GA",
    "sg:tags":[
        "return",
        "filing"
    ],
    "wof:name":"Express Tax Consultants",
    "wof:placetype":"venue"
},
  "geometry": {"coordinates":[-84.965287,32.568415],"type":"Point"}
}