{
  "type": "Feature",
  "properties": {
    "iso:country":"US",
    "sg:address":"361 Upper Riverdale Rd",
    "sg:city":"Jonesboro",
    "sg:classifiers":[
        {
            "category":"Retail",
            "subcategory":"Car Wash",
            "type":"Services"
        }
    ],
    "sg:phone":"+1 770 994 1071",
    "sg:postcode":"30236",
    "sg:province":"GA",
    "sg:tags":[
        "carwash"
    ],
    "wof:name":"Tidal Wave Express Car Wash",
    "wof:placetype":"venue"
},
  "geometry": {"coordinates":[-84.377821,33.583333],"type":"Point"}
}