{
  "type": "Feature",
  "properties": {
    "iso:country":"US",
    "sg:address":"1209 Tracy Ln",
    "sg:city":"Valdosta",
    "sg:classifiers":[
        {
            "category":"Building & Trades",
            "subcategory":"Electrical",
            "type":"Services"
        }
    ],
    "sg:phone":"+1 229 251 4877",
    "sg:postcode":"31601",
    "sg:province":"GA",
    "sg:tags":[
        "electric",
        "contractor"
    ],
    "wof:name":"B & B Electric Contractors",
    "wof:placetype":"venue"
},
  "geometry": {"coordinates":[-83.30279,30.834374],"type":"Point"}
}