{
  "type": "Feature",
  "properties": {
    "addr:full":"3270 Millwright St Douglasville GA 30135",
    "addr:postcode":"3270;30135",
    "addr:street":"Millwright St",
    "iso:country":"US",
    "sg:address":"3270 Millwright St",
    "sg:city":"Douglasville",
    "sg:classifiers":[
        {
            "category":"Manufacturing",
            "subcategory":"Printing",
            "type":"Manufacturing & Wholesale Goods"
        }
    ],
    "sg:phone":"+1 770 942 7255",
    "sg:postcode":"30135",
    "sg:province":"GA",
    "sg:tags":[
        "commercial",
        "lithographic"
    ],
    "wof:name":"Latham Printing Company",
    "wof:placetype":"venue"
},
  "geometry": {"coordinates":[-84.782602,33.715964],"type":"Point"}
}