{
  "type": "Feature",
  "properties": {
    "iso:country":"US",
    "sg:address":"65 Mathews St",
    "sg:city":"Fort Valley",
    "sg:classifiers":[
        {
            "category":"Social Services",
            "subcategory":"Child Care",
            "type":"Services"
        }
    ],
    "sg:phone":"+1 478 827 0827",
    "sg:postcode":"31030",
    "sg:province":"GA",
    "sg:tags":[
        "day"
    ],
    "wof:name":"Miracles Learning World",
    "wof:placetype":"venue"
},
  "geometry": {"coordinates":[-83.904426,32.527229],"type":"Point"}
}