{
  "type": "Feature",
  "properties": {
    "iso:country":"US",
    "sg:address":"715 5th St",
    "sg:city":"Columbus",
    "sg:classifiers":[
        {
            "category":"Wholesale",
            "subcategory":"Scrap",
            "type":"Manufacturing & Wholesale Goods"
        }
    ],
    "sg:phone":"+1 706 322 6567",
    "sg:postcode":"31901",
    "sg:province":"GA",
    "sg:tags":[
        "metal",
        "iron"
    ],
    "wof:name":"E Cohn Co",
    "wof:placetype":"venue"
},
  "geometry": {"coordinates":[-84.983484,32.455331],"type":"Point"}
}