{
  "type": "Feature",
  "properties": {
    "addr:full":"11760 Haynes Bridge Rd Alpharetta GA 30004",
    "addr:housenumber":"11760",
    "addr:postcode":"30004",
    "addr:street":"Haynes Bridge Rd",
    "iso:country":"US",
    "sg:address":"11760 Haynes Bridge Rd",
    "sg:city":"Alpharetta",
    "sg:classifiers":[
        {
            "category":"Personal",
            "subcategory":"Beauty Salon",
            "type":"Services"
        }
    ],
    "sg:phone":"+1 770 663 4722",
    "sg:postcode":"30004",
    "sg:province":"GA",
    "sg:tags":[
        "shop"
    ],
    "wof:name":"Sebastions Hair & Nails",
    "wof:placetype":"venue"
},
  "geometry": {"coordinates":[-84.29349499999999,34.06924],"type":"Point"}
}