{
  "type": "Feature",
  "properties": {
    "iso:country":"US",
    "sg:address":"2458 Mount Vernon Rd",
    "sg:city":"Dunwoody",
    "sg:classifiers":[
        {
            "category":"Building & Trades",
            "subcategory":"Construction",
            "type":"Services"
        }
    ],
    "sg:phone":"+1 770 351 0409",
    "sg:postcode":"30338",
    "sg:province":"GA",
    "sg:tags":[
        "contractor"
    ],
    "wof:name":"John Wieland Homes",
    "wof:placetype":"venue"
},
  "geometry": {"coordinates":[-84.301885,33.958041],"type":"Point"}
}