{
  "type": "Feature",
  "properties": {
    "addr:full":"103 E Pine St Swainsboro GA 30401",
    "addr:housenumber":"103",
    "addr:postcode":"30401",
    "addr:street":"E Pine St",
    "iso:country":"US",
    "sg:address":"103 E Pine St",
    "sg:city":"Swainsboro",
    "sg:classifiers":[
        {
            "category":"Shopping",
            "subcategory":"Pharmacy",
            "type":"Retail Goods"
        }
    ],
    "sg:phone":"+1 478 237 2605",
    "sg:postcode":"30401",
    "sg:province":"GA",
    "wof:name":"Rite Aid Pharmacy",
    "wof:placetype":"venue"
},
  "geometry": {"coordinates":[-82.33335,32.59901],"type":"Point"}
}