{
  "type": "Feature",
  "properties": {
    "iso:country":"US",
    "sg:address":"941 State Rte 34",
    "sg:city":"Newnan",
    "sg:classifiers":[
        {
            "category":"Restaurant",
            "type":"Food & Drink"
        }
    ],
    "sg:phone":"+1 770 253 7880",
    "sg:postcode":"30265",
    "sg:province":"GA",
    "wof:name":"Fire Mountain",
    "wof:placetype":"venue"
},
  "geometry": {"coordinates":[-84.72928400000001,33.399345],"type":"Point"}
}