{
  "type": "Feature",
  "properties": {
    "iso:country":"US",
    "sg:address":"7163 Mount Zion Blvd",
    "sg:city":"Jonesboro",
    "sg:classifiers":[
        {
            "category":"Bakery",
            "type":"Food & Drink"
        }
    ],
    "sg:phone":"+1 678 334 7903",
    "sg:postcode":"30236",
    "sg:province":"GA",
    "sg:website":"www.sweetflavorsbakery.com",
    "wof:name":"Sweet Flavors Bakery",
    "wof:placetype":"venue"
},
  "geometry": {"coordinates":[-84.32574099999999,33.558095],"type":"Point"}
}