{
  "type": "Feature",
  "properties": {
    "addr:full":"210 Andrews Subdiv Lavonia GA 30553",
    "addr:housenumber":"210",
    "addr:postcode":"30553",
    "addr:street":"Andrews Subdiv Lavonia",
    "iso:country":"US",
    "sg:address":"210 Andrews Subdiv",
    "sg:city":"Lavonia",
    "sg:classifiers":[
        {
            "category":"Professional",
            "subcategory":"Management & Consulting",
            "type":"Services"
        }
    ],
    "sg:phone":"+1 706 356 1355",
    "sg:postcode":"30553",
    "sg:province":"GA",
    "wof:name":"J&J Safety Service",
    "wof:placetype":"venue"
},
  "geometry": {"coordinates":[-83.07681700000001,34.484369],"type":"Point"}
}