{
  "type": "Feature",
  "properties": {
    "addr:full":"245 Tyson Cir Roswell GA 30076",
    "addr:housenumber":"245",
    "addr:postcode":"30076",
    "addr:street":"Tyson Cir",
    "iso:country":"US",
    "sg:address":"245 Tyson Cir",
    "sg:city":"Roswell",
    "sg:classifiers":[
        {
            "category":"Building & Trades",
            "subcategory":"Construction",
            "type":"Services"
        }
    ],
    "sg:phone":"+1 770 640 6401",
    "sg:postcode":"30076",
    "sg:province":"GA",
    "sg:tags":[
        "hanging",
        "contractor"
    ],
    "wof:name":"Marvel Painting",
    "wof:placetype":"venue"
},
  "geometry": {"coordinates":[-84.30614799999999,34.028021],"type":"Point"}
}