{
  "type": "Feature",
  "properties": {
    "iso:country":"US",
    "sg:address":"5653 Murphy Hwy",
    "sg:city":"Blairsville",
    "sg:classifiers":[
        {
            "category":"Structure",
            "subcategory":"Warehouse",
            "type":"Public Place"
        },
        {
            "category":"Retail",
            "subcategory":"Storage",
            "type":"Services"
        }
    ],
    "sg:phone":"+1 706 745 3752",
    "sg:postcode":"30512",
    "sg:province":"GA",
    "sg:tags":[
        "self",
        "commercial",
        "warehouses-public-commercial",
        "household"
    ],
    "wof:name":"A-P Storage",
    "wof:placetype":"venue"
},
  "geometry": {"coordinates":[-84.057124,34.958843],"type":"Point"}
}