{
  "type": "Feature",
  "properties": {
    "addr:full":"982 Shadwell Dr Evans GA 30809",
    "addr:housenumber":"982",
    "addr:postcode":"30809",
    "addr:street":"Shadwell Dr",
    "iso:country":"US",
    "sg:address":"982 Shadwell Dr",
    "sg:city":"Evans",
    "sg:classifiers":[
        {
            "category":"Professional",
            "type":"Services"
        }
    ],
    "sg:phone":"+1 706 860 1737",
    "sg:postcode":"30809",
    "sg:province":"GA",
    "wof:name":"J Hartwell Cliatt",
    "wof:placetype":"venue"
},
  "geometry": {"coordinates":[-82.141355,33.557183],"type":"Point"}
}