{
  "type": "Feature",
  "properties": {
    "iso:country":"US",
    "sg:address":"7344 State Rte 120",
    "sg:city":"Buchanan",
    "sg:classifiers":[
        {
            "category":"Manufacturing",
            "subcategory":"Watercraft",
            "type":"Manufacturing & Wholesale Goods"
        }
    ],
    "sg:phone":"+1 770 646 0023",
    "sg:postcode":"30113",
    "sg:province":"GA",
    "wof:name":"All Pro Marine",
    "wof:placetype":"venue"
},
  "geometry": {"coordinates":[-85.088554,33.820022],"type":"Point"}
}