{
  "type": "Feature",
  "properties": {
    "iso:country":"US",
    "sg:address":"890 Chestnut St SE",
    "sg:city":"Gainesville",
    "sg:classifiers":[
        {
            "category":"Building & Trades",
            "subcategory":"Construction",
            "type":"Services"
        }
    ],
    "sg:phone":"+1 770 535 8095",
    "sg:postcode":"30501",
    "sg:province":"GA",
    "sg:tags":[
        "contractor"
    ],
    "wof:name":"Allisons Sandblasting Services",
    "wof:placetype":"venue"
},
  "geometry": {"coordinates":[-83.819275,34.2915],"type":"Point"}
}