{
  "type": "Feature",
  "properties": {
    "addr:full":"430 Cherry St Macon GA 31201",
    "addr:housenumber":"430",
    "addr:postcode":"31201",
    "addr:street":"Cherry St",
    "iso:country":"US",
    "sg:address":"430 Cherry St",
    "sg:city":"Macon",
    "sg:classifiers":[
        {
            "category":"Bars & Pubs",
            "type":"Food & Drink"
        }
    ],
    "sg:phone":"+1 478 741 9130",
    "sg:postcode":"31201",
    "sg:province":"GA",
    "sg:tags":[
        "club",
        "night"
    ],
    "wof:name":"Hummingbird Night Club",
    "wof:placetype":"venue"
},
  "geometry": {"coordinates":[-83.626335,32.834822],"type":"Point"}
}