{
  "type": "Feature",
  "properties": {
    "iso:country":"US",
    "sg:address":"125 Mimosa Rd",
    "sg:city":"Griffin",
    "sg:classifiers":[
        {
            "category":"Retail",
            "subcategory":"Auto Repair",
            "type":"Services"
        }
    ],
    "sg:phone":"+1 770 412 0561",
    "sg:postcode":"30223",
    "sg:province":"GA",
    "sg:tags":[
        "automotive"
    ],
    "wof:name":"Samantha Smith",
    "wof:placetype":"venue"
},
  "geometry": {"coordinates":[-84.145758,33.277601],"type":"Point"}
}