{
  "type": "Feature",
  "properties": {
    "addr:full":"4200 Steve Reynolds Blvd Norcross GA 30093",
    "addr:housenumber":"4200",
    "addr:postcode":"30093",
    "addr:street":"Steve Reynolds Blvd",
    "iso:country":"US",
    "sg:address":"4200 Steve Reynolds Blvd",
    "sg:city":"Norcross",
    "sg:classifiers":[
        {
            "category":"Home & Garden",
            "subcategory":"Home Furnishings",
            "type":"Retail Goods"
        }
    ],
    "sg:phone":"+1 770 381 6100",
    "sg:postcode":"30093",
    "sg:province":"GA",
    "sg:tags":[
        "decor"
    ],
    "wof:name":"Home Decor Liquidators LLC",
    "wof:placetype":"venue"
},
  "geometry": {"coordinates":[-84.147633,33.926971],"type":"Point"}
}