{
  "type": "Feature",
  "properties": {
    "addr:full":"5880 Buford Hwy NE Atlanta GA 30340",
    "addr:housenumber":"5880",
    "addr:postcode":"30340",
    "addr:street":"Buford Hwy Ne",
    "iso:country":"US",
    "sg:address":"5880 Buford Hwy NE",
    "sg:city":"Atlanta",
    "sg:classifiers":[
        {
            "category":"Restaurant",
            "type":"Food & Drink"
        }
    ],
    "sg:phone":"+1 770 458 4553",
    "sg:postcode":"30340",
    "sg:province":"GA",
    "sg:tags":[
        "eating"
    ],
    "wof:name":"Grandma's Biscuits",
    "wof:placetype":"venue"
},
  "geometry": {"coordinates":[-84.266193,33.909303],"type":"Point"}
}