{
  "type": "Feature",
  "properties": {
    "addr:full":"300 Maltbie Industrial Dr Lawrenceville GA 30045",
    "addr:housenumber":"300",
    "addr:postcode":"30045",
    "addr:street":"Maltbie Industrial Dr",
    "iso:country":"US",
    "sg:address":"300 Maltbie Industrial Dr",
    "sg:city":"Lawrenceville",
    "sg:classifiers":[
        {
            "category":"Building & Trades",
            "subcategory":"Construction",
            "type":"Services"
        }
    ],
    "sg:phone":"+1 770 513 2204",
    "sg:postcode":"30045",
    "sg:province":"GA",
    "sg:tags":[
        "concrete",
        "contractor"
    ],
    "wof:name":"D P Concrete",
    "wof:placetype":"venue"
},
  "geometry": {"coordinates":[-83.99481299999999,33.962486],"type":"Point"}
}