{
  "type": "Feature",
  "properties": {
    "addr:full":"7638 Connell Dr Jonesboro GA 30236",
    "addr:housenumber":"7638",
    "addr:postcode":"30236",
    "addr:street":"Connell Dr",
    "iso:country":"US",
    "sg:address":"7638 Connell Dr",
    "sg:city":"Jonesboro",
    "sg:classifiers":[
        {
            "category":"Building & Trades",
            "subcategory":"Construction",
            "type":"Services"
        }
    ],
    "sg:phone":"+1 770 478 7036",
    "sg:postcode":"30236",
    "sg:province":"GA",
    "sg:tags":[
        "line",
        "sewer",
        "contractor"
    ],
    "wof:name":"Savage Pipeline Co",
    "wof:placetype":"venue"
},
  "geometry": {"coordinates":[-84.366967,33.546355],"type":"Point"}
}