{
  "type": "Feature",
  "properties": {
    "iso:country":"US",
    "sg:address":"2680 Lakeland Rd SE",
    "sg:city":"Dalton",
    "sg:classifiers":[
        {
            "category":"Shopping",
            "subcategory":"Discount & Variety Stores",
            "type":"Retail Goods"
        }
    ],
    "sg:phone":"+1 706 277 1012",
    "sg:postcode":"30721",
    "sg:province":"GA",
    "sg:tags":[
        "merchandise",
        "general"
    ],
    "wof:name":"Crystal Products",
    "wof:placetype":"venue"
},
  "geometry": {"coordinates":[-84.96066500000001,34.714275],"type":"Point"}
}