{
  "type": "Feature",
  "properties": {
    "addr:full":"3201 S Cherokee Ln Woodstock GA 30188",
    "addr:housenumber":"3201",
    "addr:postcode":"30188",
    "addr:street":"S Cherokee Ln",
    "iso:country":"US",
    "sg:address":"3201 S Cherokee Ln",
    "sg:city":"Woodstock",
    "sg:classifiers":[
        {
            "category":"Professional",
            "type":"Services"
        }
    ],
    "sg:phone":"+1 678 494 0006",
    "sg:postcode":"30188",
    "sg:province":"GA",
    "sg:tags":[
        "establishment"
    ],
    "wof:name":"Loren Construction Co Inc",
    "wof:placetype":"venue"
},
  "geometry": {"coordinates":[-84.471513,34.084574],"type":"Point"}
}