{
  "type": "Feature",
  "properties": {
    "addr:full":"1345 Jones St Augusta GA 30901",
    "addr:housenumber":"1345",
    "addr:postcode":"30901",
    "addr:street":"Jones St",
    "iso:country":"US",
    "sg:address":"1345 Jones St",
    "sg:city":"Augusta",
    "sg:classifiers":[
        {
            "category":"Manufacturing",
            "subcategory":"Chemicals & Compounds",
            "type":"Manufacturing & Wholesale Goods"
        }
    ],
    "sg:phone":"+1 706 722 2020",
    "sg:postcode":"30901",
    "sg:province":"GA",
    "sg:tags":[
        "material",
        "fireproofing"
    ],
    "wof:name":"Specialty Products & Insltn",
    "wof:placetype":"venue"
},
  "geometry": {"coordinates":[-81.976854,33.480032],"type":"Point"}
}