{
  "type": "Feature",
  "properties": {
    "iso:country":"US",
    "sg:address":"3420 Creekside Way",
    "sg:city":"Cumming",
    "sg:classifiers":[
        {
            "category":"Professional",
            "subcategory":"Business Services",
            "type":"Services"
        }
    ],
    "sg:phone":"+1 770 889 5064",
    "sg:postcode":"30041",
    "sg:province":"GA",
    "wof:name":"Torion Enterprise",
    "wof:placetype":"venue"
},
  "geometry": {"coordinates":[-84.08527100000001,34.171279],"type":"Point"}
}