{
  "type": "Feature",
  "properties": {
    "iso:country":"US",
    "sg:address":"179 E Athens St",
    "sg:city":"Winder",
    "sg:classifiers":[
        {
            "category":"Wholesale",
            "subcategory":"Non-durable Goods",
            "type":"Manufacturing & Wholesale Goods"
        },
        {
            "category":"Wholesale",
            "subcategory":"Durable Goods & Equipment",
            "type":"Manufacturing & Wholesale Goods"
        }
    ],
    "sg:phone":"+1 770 586 5358",
    "sg:postcode":"30680",
    "sg:province":"GA",
    "sg:tags":[
        "importer"
    ],
    "wof:name":"Paragon Sourcing Inc",
    "wof:placetype":"venue"
},
  "geometry": {"coordinates":[-83.719371,33.991128],"type":"Point"}
}