{
  "type": "Feature",
  "properties": {
    "addr:full":"225 Buckeye Ln Fayetteville GA 30214",
    "addr:housenumber":"225",
    "addr:postcode":"30214",
    "addr:street":"Buckeye Ln",
    "iso:country":"US",
    "sg:address":"225 Buckeye Ln",
    "sg:city":"Fayetteville",
    "sg:classifiers":[
        {
            "category":"Professional",
            "subcategory":"Detective & Security Services",
            "type":"Services"
        }
    ],
    "sg:phone":"+1 770 461 5585",
    "sg:postcode":"30214",
    "sg:province":"GA",
    "sg:tags":[
        "car"
    ],
    "wof:name":"Progressive Investigative Svcs",
    "wof:placetype":"venue"
},
  "geometry": {"coordinates":[-84.43725000000001,33.458064],"type":"Point"}
}