{
  "type": "Feature",
  "properties": {
    "addr:full":"6585 Pine Ridge Cir Cumming GA 30041",
    "addr:housenumber":"6585",
    "addr:postcode":"30041",
    "addr:street":"Pine Ridge Cir",
    "iso:country":"US",
    "sg:address":"6585 Pine Ridge Cir",
    "sg:city":"Cumming",
    "sg:classifiers":[
        {
            "category":"Professional",
            "type":"Services"
        }
    ],
    "sg:phone":"+1 770 205 5061",
    "sg:postcode":"30041",
    "sg:province":"GA",
    "wof:name":"Kathleen Cooper",
    "wof:placetype":"venue"
},
  "geometry": {"coordinates":[-84.053562,34.226031],"type":"Point"}
}