{
  "type": "Feature",
  "properties": {
    "iso:country":"US",
    "sg:address":"2012 Patterson Park Dr",
    "sg:city":"Lawrenceville",
    "sg:classifiers":[
        {
            "category":"Building & Trades",
            "subcategory":"Construction",
            "type":"Services"
        }
    ],
    "sg:phone":"+1 770 605 2125",
    "sg:postcode":"30044",
    "sg:province":"GA",
    "sg:tags":[
        "downspouts",
        "gutter"
    ],
    "wof:name":"Adan's Gutter",
    "wof:placetype":"venue"
},
  "geometry": {"coordinates":[-84.039209,33.926334],"type":"Point"}
}