{
  "type": "Feature",
  "properties": {
    "addr:full":"1117 Perimeter Center W Rd Atlanta GA 30338",
    "addr:housenumber":"1117",
    "addr:postcode":"30338",
    "addr:street":"Perimeter Center W Rd",
    "iso:country":"US",
    "sg:address":"1117 Perimeter Center W Rd",
    "sg:city":"Atlanta",
    "sg:classifiers":[
        {
            "category":"Real Estate",
            "subcategory":"Real Estate Agent",
            "type":"Services"
        }
    ],
    "sg:phone":"+1 770 913 0013",
    "sg:postcode":"30338",
    "sg:province":"GA",
    "sg:tags":[
        "management"
    ],
    "wof:name":"Archon Management",
    "wof:placetype":"venue"
},
  "geometry": {"coordinates":[-84.350588,33.931084],"type":"Point"}
}