{
  "type": "Feature",
  "properties": {
    "iso:country":"US",
    "sg:address":"3271 Hamilton Blvd SW",
    "sg:city":"Atlanta",
    "sg:classifiers":[
        {
            "category":"Manufacturing",
            "subcategory":"Printing",
            "type":"Manufacturing & Wholesale Goods"
        }
    ],
    "sg:phone":"+1 404 761 2100",
    "sg:postcode":"30354",
    "sg:province":"GA",
    "sg:tags":[
        "offset"
    ],
    "wof:name":"Vertis Retail & Newspaper Serv",
    "wof:placetype":"venue"
},
  "geometry": {"coordinates":[-84.38556800000001,33.662982],"type":"Point"}
}