{
  "type": "Feature",
  "properties": {
    "iso:country":"US",
    "sg:address":"1969 Baker Rd NW",
    "sg:city":"Atlanta",
    "sg:classifiers":[
        {
            "category":"Professional",
            "subcategory":"Business Services",
            "type":"Services"
        }
    ],
    "sg:phone":"+1 404 792 3360",
    "sg:postcode":"30318",
    "sg:province":"GA",
    "sg:tags":[
        "holding"
    ],
    "wof:name":"Adoya Holdings Inc.",
    "wof:placetype":"venue"
},
  "geometry": {"coordinates":[-84.4515,33.77039],"type":"Point"}
}