{
  "type": "Feature",
  "properties": {
    "addr:full":"2480 Lehaven Dr Tucker GA 30084",
    "addr:postcode":"2480;30084",
    "addr:street":"Lehaven Dr",
    "iso:country":"US",
    "sg:address":"2480 Lehaven Dr",
    "sg:city":"Tucker",
    "sg:classifiers":[
        {
            "category":"Banks & Credit Unions",
            "subcategory":"Bank",
            "type":"Services"
        }
    ],
    "sg:phone":"+1 770 938 0616",
    "sg:postcode":"30084",
    "sg:province":"GA",
    "sg:tags":[
        "mortgage"
    ],
    "wof:name":"Cfic Home Mortgage",
    "wof:placetype":"venue"
},
  "geometry": {"coordinates":[-84.212498,33.857241],"type":"Point"}
}