{
  "type": "Feature",
  "properties": {
    "iso:country":"US",
    "sg:address":"1580 Victoria Walk",
    "sg:city":"Cumming",
    "sg:classifiers":[
        {
            "category":"Professional",
            "type":"Services"
        }
    ],
    "sg:phone":"+1 770 886 6668",
    "sg:postcode":"30041",
    "sg:province":"GA",
    "wof:name":"Burke Howard",
    "wof:placetype":"venue"
},
  "geometry": {"coordinates":[-84.123508,34.165824],"type":"Point"}
}