{
  "type": "Feature",
  "properties": {
    "iso:country":"US",
    "sg:address":"1005 Milstead Ave NE",
    "sg:city":"Conyers",
    "sg:classifiers":[
        {
            "category":"Organizations",
            "subcategory":"Community Association",
            "type":"Services"
        }
    ],
    "sg:phone":"+1 770 922 8926",
    "sg:postcode":"30012",
    "sg:province":"GA",
    "sg:tags":[
        "fraternal"
    ],
    "wof:name":"Philologia Lodge F & AM",
    "wof:placetype":"venue"
},
  "geometry": {"coordinates":[-84.01634900000001,33.669484],"type":"Point"}
}