{
  "type": "Feature",
  "properties": {
    "addr:full":"109 Addington Dr Rome GA 30165",
    "addr:housenumber":"109",
    "addr:postcode":"ga 30165",
    "addr:street":"Addington Dr",
    "iso:country":"US",
    "sg:address":"109 Addington Dr",
    "sg:city":"Rome",
    "sg:classifiers":[
        {
            "category":"Home & Garden",
            "subcategory":"Building Materials",
            "type":"Retail Goods"
        }
    ],
    "sg:phone":"+1 706 232 8880",
    "sg:postcode":"30165",
    "sg:province":"GA",
    "sg:tags":[
        "mobile"
    ],
    "wof:name":"Builders Salvage Inc",
    "wof:placetype":"venue"
},
  "geometry": {"coordinates":[-85.221957,34.285705],"type":"Point"}
}