{
  "type": "Feature",
  "properties": {
    "addr:full":"119 Darian Dr Sumner GA 31763",
    "addr:housenumber":"119",
    "addr:postcode":"31763",
    "addr:street":"Darian Dr",
    "iso:country":"US",
    "sg:address":"119 Darian Dr",
    "sg:city":"Sumner",
    "sg:classifiers":[
        {
            "category":"Building & Trades",
            "subcategory":"Pest Control",
            "type":"Services"
        }
    ],
    "sg:phone":"+1 229 777 0345",
    "sg:postcode":"31763",
    "sg:province":"GA",
    "wof:name":"Tifton Termite & Pest Svc",
    "wof:placetype":"venue"
},
  "geometry": {"coordinates":[-84.10277499999999,31.645403],"type":"Point"}
}