{
  "type": "Feature",
  "properties": {
    "addr:full":"1280 W Paces Ferry Road NW Atlanta GA 30327",
    "addr:housenumber":"1280",
    "addr:postcode":"30327",
    "addr:street":"W Paces Ferry Road Nw",
    "iso:country":"US",
    "sg:address":"1280 W Paces Ferry Road NW",
    "sg:city":"Atlanta",
    "sg:classifiers":[
        {
            "category":"Banks & Credit Unions",
            "subcategory":"Bank",
            "type":"Services"
        },
        {
            "category":"Banks & Credit Unions",
            "subcategory":"Financial Services",
            "type":"Services"
        }
    ],
    "sg:phone":"+1 404 264 2900",
    "sg:postcode":"30327",
    "sg:province":"GA",
    "sg:tags":[
        "commercial",
        "loan",
        "internet",
        "saving",
        "banking"
    ],
    "sg:website":"http://www.bofa.com",
    "wof:name":"Bank of America",
    "wof:placetype":"venue"
},
  "geometry": {"coordinates":[-84.42946499999999,33.849341],"type":"Point"}
}