{
  "type": "Feature",
  "properties": {
    "iso:country":"US",
    "sg:address":"773 State Rte 138",
    "sg:city":"Riverdale",
    "sg:classifiers":[
        {
            "category":"Manufacturing",
            "subcategory":"Electronics",
            "type":"Manufacturing & Wholesale Goods"
        }
    ],
    "sg:phone":"+1 770 994 5917",
    "sg:postcode":"30296",
    "sg:province":"GA",
    "sg:tags":[
        "electronic",
        "component",
        "mfg"
    ],
    "wof:name":"Cellular Circuits Inc",
    "wof:placetype":"venue"
},
  "geometry": {"coordinates":[-84.41500000000001,33.549825],"type":"Point"}
}