{
  "type": "Feature",
  "properties": {
    "iso:country":"US",
    "sg:address":"5263 New Jesup Hwy",
    "sg:city":"Brunswick",
    "sg:classifiers":[
        {
            "category":"Autos & Motor Vehicles",
            "subcategory":"Automobile Sales",
            "type":"Retail Goods"
        },
        {
            "category":"Retail",
            "subcategory":"Auto Repair",
            "type":"Services"
        }
    ],
    "sg:phone":"+1 912 275 8929",
    "sg:postcode":"31523",
    "sg:province":"GA",
    "sg:tags":[
        "car",
        "used"
    ],
    "wof:name":"Quality Pre Owned Auto",
    "wof:placetype":"venue"
},
  "geometry": {"coordinates":[-81.52512,31.223405],"type":"Point"}
}