{
  "type": "Feature",
  "properties": {
    "iso:country":"US",
    "sg:address":"8170 Odessa Pl",
    "sg:city":"Douglasville",
    "sg:classifiers":[
        {
            "category":"Building & Trades",
            "subcategory":"Construction",
            "type":"Services"
        }
    ],
    "sg:phone":"+1 770 920 1482",
    "sg:postcode":"30134",
    "sg:province":"GA",
    "sg:tags":[
        "fabricator",
        "metal"
    ],
    "wof:name":"Omega Metals",
    "wof:placetype":"venue"
},
  "geometry": {"coordinates":[-84.73917,33.756809],"type":"Point"}
}