{
  "type": "Feature",
  "properties": {
    "addr:full":"4385 Johns Creek Pkwy Suwanee GA 30024",
    "addr:housenumber":"4385",
    "addr:postcode":"30024",
    "addr:street":"Johns Creek Pkwy",
    "iso:country":"US",
    "sg:address":"4385 Johns Creek Pkwy",
    "sg:city":"Suwanee",
    "sg:classifiers":[
        {
            "category":"Health Services",
            "subcategory":"Doctor",
            "type":"Services"
        },
        {
            "category":"Health Services",
            "subcategory":"Hospital",
            "type":"Services"
        }
    ],
    "sg:phone":"+1 770 814 9455",
    "sg:postcode":"30024",
    "sg:province":"GA",
    "sg:tags":[
        "physician",
        "surgeons",
        "sleep",
        "treatment",
        "surgeon",
        "disorder",
        "disorders-information"
    ],
    "wof:name":"Georgia Neurology & Sleep Medicine Associates",
    "wof:placetype":"venue"
},
  "geometry": {"coordinates":[-84.172297,34.071648],"type":"Point"}
}