{
  "type": "Feature",
  "properties": {
    "iso:country":"US",
    "sg:address":"6720 State Rte 95",
    "sg:city":"La Fayette",
    "sg:classifiers":[
        {
            "category":"Utilities",
            "subcategory":"Refuse",
            "type":"Services"
        }
    ],
    "sg:phone":"+1 706 764 1840",
    "sg:postcode":"30728",
    "sg:province":"GA",
    "sg:tags":[
        "system"
    ],
    "wof:name":"Ledford Cone",
    "wof:placetype":"venue"
},
  "geometry": {"coordinates":[-85.186145,34.745764],"type":"Point"}
}