{
  "type": "Feature",
  "properties": {
    "addr:full":"2365 Rocky Water Trl Buford GA 30519",
    "addr:housenumber":"2365",
    "addr:postcode":"30519",
    "addr:street":"Rocky Water Trl",
    "iso:country":"US",
    "sg:address":"2365 Rocky Water Trl",
    "sg:city":"Buford",
    "sg:classifiers":[
        {
            "category":"Professional",
            "subcategory":"Business Services",
            "type":"Services"
        }
    ],
    "sg:phone":"+1 770 962 8589",
    "sg:postcode":"30519",
    "sg:province":"GA",
    "wof:name":"Red Horse Technical Services",
    "wof:placetype":"venue"
},
  "geometry": {"coordinates":[-83.95881,34.048942],"type":"Point"}
}