{
  "type": "Feature",
  "properties": {
    "iso:country":"US",
    "sg:address":"4200 McEver Industrial Dr NW",
    "sg:city":"Acworth",
    "sg:classifiers":[
        {
            "category":"Government",
            "subcategory":"Post Office",
            "type":"Public Place"
        }
    ],
    "sg:phone":"+1 770 966 8123",
    "sg:postcode":"30101",
    "sg:province":"GA",
    "sg:tags":[
        "postal",
        "us"
    ],
    "wof:name":"US Post Office",
    "wof:placetype":"venue"
},
  "geometry": {"coordinates":[-84.657872,34.061288],"type":"Point"}
}