{
  "type": "Feature",
  "properties": {
    "addr:full":"255 Sunset Ter Athens GA 30606",
    "addr:housenumber":"255",
    "addr:postcode":"30606",
    "addr:street":"Sunset Ter",
    "iso:country":"US",
    "sg:address":"255 Sunset Ter",
    "sg:city":"Athens",
    "sg:classifiers":[
        {
            "category":"Building & Trades",
            "subcategory":"Pest Control",
            "type":"Services"
        }
    ],
    "sg:phone":"+1 706 543 6782",
    "sg:postcode":"30606",
    "sg:province":"GA",
    "wof:name":"Currys Termite",
    "wof:placetype":"venue"
},
  "geometry": {"coordinates":[-83.406223,33.953626],"type":"Point"}
}