{
  "type": "Feature",
  "properties": {
    "iso:country":"US",
    "sg:address":"102 Nightingale Ln",
    "sg:city":"Brunswick",
    "sg:classifiers":[
        {
            "category":"Autos & Motor Vehicles",
            "subcategory":"Automobile Sales",
            "type":"Retail Goods"
        }
    ],
    "sg:phone":"+1 912 264 4195",
    "sg:postcode":"31525",
    "sg:province":"GA",
    "wof:name":"Tom Jones Aircraft",
    "wof:placetype":"venue"
},
  "geometry": {"coordinates":[-81.446732,31.243741],"type":"Point"}
}