{
  "type": "Feature",
  "properties": {
    "addr:full":"4224 Bloomfield Rd Macon GA 31206",
    "addr:housenumber":"4224",
    "addr:postcode":"31206",
    "addr:street":"Bloomfield Rd",
    "iso:country":"US",
    "sg:address":"4224 Bloomfield Rd",
    "sg:city":"Macon",
    "sg:classifiers":[
        {
            "category":"Food & Beverages",
            "subcategory":"Groceries & Convenience Stores",
            "type":"Retail Goods"
        }
    ],
    "sg:phone":"+1 478 788 8074",
    "sg:postcode":"31206",
    "sg:province":"GA",
    "wof:name":"Flash Foods Inc",
    "wof:placetype":"venue"
},
  "geometry": {"coordinates":[-83.699997,32.81379],"type":"Point"}
}