{
  "type": "Feature",
  "properties": {
    "iso:country":"US",
    "sg:address":"102 S Zetterower Ave",
    "sg:city":"Statesboro",
    "sg:classifiers":[
        {
            "category":"Health Services",
            "subcategory":"Health Practitioner",
            "type":"Services"
        }
    ],
    "sg:phone":"+1 912 764 6731",
    "sg:postcode":"30458",
    "sg:province":"GA",
    "wof:name":"John C Adams PC",
    "wof:placetype":"venue"
},
  "geometry": {"coordinates":[-81.778176,32.446273],"type":"Point"}
}