{
  "type": "Feature",
  "properties": {
    "addr:full":"2048 Hosea L Williams Dr NE Atlanta GA 30317",
    "addr:housenumber":"2048",
    "addr:postcode":"30317",
    "addr:street":"Hosea L Williams Dr Ne",
    "iso:country":"US",
    "sg:address":"2048 Hosea L Williams Dr NE",
    "sg:city":"Atlanta",
    "sg:classifiers":[
        {
            "category":"Building & Trades",
            "subcategory":"Landscaping Services",
            "type":"Services"
        }
    ],
    "sg:phone":"+1 404 732 2396",
    "sg:postcode":"30317",
    "sg:province":"GA",
    "sg:tags":[
        "aged",
        "homes-institutional"
    ],
    "wof:name":"Families Uplifting Families Inc.",
    "wof:placetype":"venue"
},
  "geometry": {"coordinates":[-84.32088400000001,33.751144],"type":"Point"}
}