{
  "type": "Feature",
  "properties": {
    "iso:country":"US",
    "sg:address":"76 Cooper Lake Rd SE",
    "sg:city":"Mableton",
    "sg:classifiers":[
        {
            "category":"Communications",
            "type":"Services"
        }
    ],
    "sg:phone":"+1 770 948 7623",
    "sg:postcode":"30126",
    "sg:province":"GA",
    "sg:tags":[
        "communication"
    ],
    "wof:name":"Ronnies Sales",
    "wof:placetype":"venue"
},
  "geometry": {"coordinates":[-84.551248,33.825832],"type":"Point"}
}