{
  "type": "Feature",
  "properties": {
    "iso:country":"US",
    "sg:address":"9 Cambridge Ct",
    "sg:city":"Savannah",
    "sg:classifiers":[
        {
            "category":"Professional",
            "subcategory":"Research",
            "type":"Services"
        }
    ],
    "sg:phone":"+1 912 925 2304",
    "sg:postcode":"31419",
    "sg:province":"GA",
    "sg:tags":[
        "nonphysical",
        "commercial"
    ],
    "wof:name":"Tommie Pullins",
    "wof:placetype":"venue"
},
  "geometry": {"coordinates":[-81.204488,31.98791],"type":"Point"}
}