{
  "type": "Feature",
  "properties": {
    "iso:country":"US",
    "sg:address":"912 Killian Hill Rd SW",
    "sg:city":"Lilburn",
    "sg:classifiers":[
        {
            "category":"Professional",
            "subcategory":"Business Services",
            "type":"Services"
        }
    ],
    "sg:phone":"+1 770 925 8100",
    "sg:postcode":"30047",
    "sg:province":"GA",
    "wof:name":"Lilburn Prof Ctr Gwinnett",
    "wof:placetype":"venue"
},
  "geometry": {"coordinates":[-84.095922,33.869033],"type":"Point"}
}