{
  "type": "Feature",
  "properties": {
    "addr:full":"7308 Chastain Dr NE Atlanta GA 30342",
    "addr:housenumber":"7308",
    "addr:postcode":"30342",
    "addr:street":"Chastain Dr Ne",
    "iso:country":"US",
    "sg:address":"7308 Chastain Dr NE",
    "sg:city":"Atlanta",
    "sg:classifiers":[
        {
            "category":"Professional",
            "subcategory":"Engineering",
            "type":"Services"
        },
        {
            "category":"Home & Garden",
            "subcategory":"Building Materials",
            "type":"Retail Goods"
        },
        {
            "category":"Building & Trades",
            "subcategory":"Construction",
            "type":"Services"
        }
    ],
    "sg:phone":"+1 678 908 9972",
    "sg:postcode":"30342",
    "sg:province":"GA",
    "sg:tags":[
        "repair",
        "system",
        "systems-repairing",
        "heating",
        "equipment",
        "maintenance",
        "air conditioning"
    ],
    "wof:name":"Complete House Maintenance",
    "wof:placetype":"venue"
},
  "geometry": {"coordinates":[-84.384079,33.866482],"type":"Point"}
}