{
  "type": "Feature",
  "properties": {
    "iso:country":"US",
    "sg:address":"1438 W Peachtree St NW",
    "sg:city":"Atlanta",
    "sg:classifiers":[
        {
            "category":"Organizations",
            "subcategory":"Professional Association",
            "type":"Services"
        }
    ],
    "sg:phone":"+1 404 892 0943",
    "sg:postcode":"30309",
    "sg:province":"GA",
    "sg:tags":[
        "business",
        "trade"
    ],
    "sg:website":"http://www.solinet.net",
    "wof:name":"Lyrasis Inc.",
    "wof:placetype":"venue"
},
  "geometry": {"coordinates":[-84.387753,33.793741],"type":"Point"}
}