{
  "type": "Feature",
  "properties": {
    "addr:full":"1059 Gaines School Rd Athens GA 30605",
    "addr:housenumber":"1059",
    "addr:postcode":"30605",
    "addr:street":"Gaines School Rd",
    "iso:country":"US",
    "sg:address":"1059 Gaines School Rd",
    "sg:city":"Athens",
    "sg:classifiers":[
        {
            "category":"Banks & Credit Unions",
            "subcategory":"Bank",
            "type":"Services"
        }
    ],
    "sg:phone":"+1 706 354 5410",
    "sg:postcode":"30605",
    "sg:province":"GA",
    "wof:name":"South Trust Bank",
    "wof:placetype":"venue"
},
  "geometry": {"coordinates":[-83.337159,33.927828],"type":"Point"}
}