{
  "type": "Feature",
  "properties": {
    "addr:full":"2260 Peachtree Rd NW Atlanta GA 30309",
    "addr:housenumber":"2260",
    "addr:postcode":"30309",
    "addr:street":"Peachtree Rd Nw",
    "iso:country":"US",
    "sg:address":"2260 Peachtree Rd NW",
    "sg:city":"Atlanta",
    "sg:classifiers":[
        {
            "category":"Shopping",
            "subcategory":"Hobbies, Toys, & Games",
            "type":"Retail Goods"
        }
    ],
    "sg:phone":"+1 404 605 0694",
    "sg:postcode":"30309",
    "sg:province":"GA",
    "sg:tags":[
        "coin",
        "supply"
    ],
    "wof:name":"Hancock & Harwell Rare Coins",
    "wof:placetype":"venue"
},
  "geometry": {"coordinates":[-84.390343,33.816238],"type":"Point"}
}