{
  "type": "Feature",
  "properties": {
    "iso:country":"US",
    "sg:address":"2500 Radium Springs Rd",
    "sg:city":"Albany",
    "sg:classifiers":[
        {
            "category":"Organizations",
            "subcategory":"Religious Organization",
            "type":"Services"
        }
    ],
    "sg:phone":"+1 229 435 4009",
    "sg:postcode":"31705",
    "sg:province":"GA",
    "wof:name":"Faith & Hope Baptist Church",
    "wof:placetype":"venue"
},
  "geometry": {"coordinates":[-84.13591,31.526432],"type":"Point"}
}