{
  "type": "Feature",
  "properties": {
    "iso:country":"US",
    "sg:address":"1353 Sam Nunn Blvd",
    "sg:city":"Perry",
    "sg:classifiers":[
        {
            "category":"Shopping",
            "subcategory":"Department Store",
            "type":"Retail Goods"
        }
    ],
    "sg:phone":"+1 478 987 4746",
    "sg:postcode":"31069",
    "sg:province":"GA",
    "wof:name":"Fred's Store",
    "wof:placetype":"venue"
},
  "geometry": {"coordinates":[-83.73901600000001,32.466535],"type":"Point"}
}