{
  "type": "Feature",
  "properties": {
    "iso:country":"US",
    "sg:address":"3940 Pechtre Indstrl Blvd",
    "sg:city":"Duluth",
    "sg:classifiers":[
        {
            "category":"Autos & Motor Vehicles",
            "subcategory":"Auto Supplies",
            "type":"Retail Goods"
        }
    ],
    "sg:phone":"+1 678 417 9003",
    "sg:postcode":"30096",
    "sg:province":"GA",
    "sg:tags":[
        "glass"
    ],
    "wof:name":"Glasfit USA Inc",
    "wof:placetype":"venue"
},
  "geometry": {"coordinates":[-84.17089799999999,33.985699],"type":"Point"}
}