{
  "type": "Feature",
  "properties": {
    "addr:full":"1888 Wycliff Rd NW Atlanta GA 30309",
    "addr:housenumber":"1888",
    "addr:postcode":"30309",
    "addr:street":"Wycliff Rd Nw",
    "iso:country":"US",
    "sg:address":"1888 Wycliff Rd NW",
    "sg:city":"Atlanta",
    "sg:classifiers":[
        {
            "category":"Professional",
            "subcategory":"Business Services",
            "type":"Services"
        }
    ],
    "sg:phone":"+1 404 262 1731",
    "sg:postcode":"30309",
    "sg:province":"GA",
    "sg:tags":[
        "interior",
        "consultant",
        "design",
        "decorator"
    ],
    "wof:name":"Lauren Deloach Creative Studio",
    "wof:placetype":"venue"
},
  "geometry": {"coordinates":[-84.396163,33.805783],"type":"Point"}
}