{
  "type": "Feature",
  "properties": {
    "addr:full":"7906 US Hwy 80 Savannah GA 31410",
    "addr:housenumber":"7906",
    "addr:postcode":"31410",
    "addr:street":"Us Hwy 80",
    "iso:country":"US",
    "sg:address":"7906 US Hwy 80",
    "sg:city":"Savannah",
    "sg:classifiers":[
        {
            "category":"Health Services",
            "subcategory":"Doctor",
            "type":"Services"
        }
    ],
    "sg:phone":"+1 912 897 5486",
    "sg:postcode":"31410",
    "sg:province":"GA",
    "sg:tags":[
        "medical"
    ],
    "wof:name":"Wilmington Island Family Med",
    "wof:placetype":"venue"
},
  "geometry": {"coordinates":[-80.96826799999999,32.031524],"type":"Point"}
}