{
  "type": "Feature",
  "properties": {
    "iso:country":"US",
    "sg:address":"4575 Brownsville Rd",
    "sg:city":"Powder Springs",
    "sg:classifiers":[
        {
            "category":"Building & Trades",
            "subcategory":"Electrical",
            "type":"Services"
        }
    ],
    "sg:phone":"+1 770 439 0000",
    "sg:postcode":"30127",
    "sg:province":"GA",
    "sg:tags":[
        "electrical",
        "electric",
        "contractor"
    ],
    "wof:name":"Jim Luca Electrical Contrs",
    "wof:placetype":"venue"
},
  "geometry": {"coordinates":[-84.70052699999999,33.842226],"type":"Point"}
}