{
  "type": "Feature",
  "properties": {
    "iso:country":"US",
    "sg:address":"172 Tyson Rd",
    "sg:city":"Douglas",
    "sg:classifiers":[
        {
            "category":"Retail",
            "subcategory":"Repair Shop",
            "type":"Services"
        }
    ],
    "sg:phone":"+1 912 389 1993",
    "sg:postcode":"31533",
    "sg:province":"GA",
    "wof:name":"Outlaws Saddle Repair & Tack",
    "wof:placetype":"venue"
},
  "geometry": {"coordinates":[-82.814301,31.535413],"type":"Point"}
}