{
  "type": "Feature",
  "properties": {
    "addr:full":"2860 Piedmont Road Suite C Atlanta GA 30305",
    "addr:housenumber":"2860",
    "addr:postcode":"30305",
    "addr:street":"Piedmont Road Suite C",
    "iso:country":"US",
    "sg:address":"2860 Piedmont Road Suite C",
    "sg:city":"Atlanta",
    "sg:classifiers":[
        {
            "category":"Professional",
            "subcategory":"Art Services",
            "type":"Services"
        }
    ],
    "sg:phone":"+1 404 231 9233",
    "sg:postcode":"30305",
    "sg:province":"GA",
    "sg:tags":[
        "interior",
        "designer",
        "decorator"
    ],
    "sg:website":"http://www.leachassoc.com",
    "wof:name":"Leach Associates, Inc.",
    "wof:placetype":"venue"
},
  "geometry": {"coordinates":[-84.368016,33.832781],"type":"Point"}
}