{
  "type": "Feature",
  "properties": {
    "addr:full":"585 Glynn St N Fayetteville GA 30214",
    "addr:housenumber":"585",
    "addr:postcode":"30214",
    "addr:street":"Glynn St N",
    "iso:country":"US",
    "sg:address":"585 Glynn St N",
    "sg:city":"Fayetteville",
    "sg:classifiers":[
        {
            "category":"Retail",
            "subcategory":"Laundry & Dry Cleaning",
            "type":"Services"
        }
    ],
    "sg:phone":"+1 770 461 3873",
    "sg:postcode":"30214",
    "sg:province":"GA",
    "wof:name":"Daisy Fresh Dry Cleaners",
    "wof:placetype":"venue"
},
  "geometry": {"coordinates":[-84.454002,33.457401],"type":"Point"}
}