{
  "type": "Feature",
  "properties": {
    "addr:full":"2150 Brandon Trl Alpharetta GA 30004",
    "addr:housenumber":"2150",
    "addr:postcode":"30004",
    "addr:street":"Brandon Trl",
    "iso:country":"US",
    "sg:address":"2150 Brandon Trl",
    "sg:city":"Alpharetta",
    "sg:classifiers":[
        {
            "category":"Real Estate",
            "subcategory":"Real Estate Agent",
            "type":"Services"
        }
    ],
    "sg:phone":"+1 770 754 0707",
    "sg:postcode":"30004",
    "sg:province":"GA",
    "wof:name":"Geoghagan Real Estate LLC",
    "wof:placetype":"venue"
},
  "geometry": {"coordinates":[-84.23951599999999,34.140845],"type":"Point"}
}