{
  "type": "Feature",
  "properties": {
    "iso:country":"US",
    "sg:address":"4816 Old Dixie Hwy",
    "sg:city":"Forest Park",
    "sg:classifiers":[
        {
            "category":"Autos & Motor Vehicles",
            "subcategory":"Auto Supplies",
            "type":"Retail Goods"
        }
    ],
    "sg:phone":"+1 404 361 4440",
    "sg:postcode":"30297",
    "sg:province":"GA",
    "sg:tags":[
        "tire"
    ],
    "wof:name":"C & R New & Used Tire Services",
    "wof:placetype":"venue"
},
  "geometry": {"coordinates":[-84.383883,33.623251],"type":"Point"}
}