{
  "type": "Feature",
  "properties": {
    "iso:country":"US",
    "sg:address":"113 Dixie Dr",
    "sg:city":"Woodstock",
    "sg:classifiers":[
        {
            "category":"Building & Trades",
            "subcategory":"Construction",
            "type":"Services"
        }
    ],
    "sg:phone":"+1 770 516 5889",
    "sg:postcode":"30189",
    "sg:province":"GA",
    "sg:tags":[
        "contractor"
    ],
    "wof:name":"Done Rite Gutters",
    "wof:placetype":"venue"
},
  "geometry": {"coordinates":[-84.563811,34.084305],"type":"Point"}
}