{
  "type": "Feature",
  "properties": {
    "iso:country":"US",
    "sg:address":"530 Quail Run Dr",
    "sg:city":"Warner Robins",
    "sg:classifiers":[
        {
            "category":"Professional",
            "type":"Services"
        }
    ],
    "sg:phone":"+1 478 953 9559",
    "sg:postcode":"31088",
    "sg:province":"GA",
    "wof:name":"Southern Built LLC",
    "wof:placetype":"venue"
},
  "geometry": {"coordinates":[-83.707582,32.589901],"type":"Point"}
}