{
  "type": "Feature",
  "properties": {
    "addr:full":"2470 Windy Hill Rd SE Marietta GA 30067",
    "addr:housenumber":"2470",
    "addr:postcode":"30067",
    "addr:street":"Windy Hill Rd Se",
    "iso:country":"US",
    "sg:address":"2470 Windy Hill Rd SE",
    "sg:city":"Marietta",
    "sg:classifiers":[
        {
            "category":"Professional",
            "subcategory":"Lawyer & Legal Services",
            "type":"Services"
        }
    ],
    "sg:phone":"+1 770 955 1785",
    "sg:postcode":"30067",
    "sg:province":"GA",
    "sg:tags":[
        "attorney"
    ],
    "wof:name":"Robert H Beer",
    "wof:placetype":"venue"
},
  "geometry": {"coordinates":[-84.481274,33.902883],"type":"Point"}
}