{
  "type": "Feature",
  "properties": {
    "iso:country":"US",
    "sg:address":"590 US Hwy 441 Bus",
    "sg:city":"Demorest",
    "sg:classifiers":[
        {
            "category":"Health Services",
            "subcategory":"Health Practitioner",
            "type":"Services"
        }
    ],
    "sg:phone":"+1 706 754 6611",
    "sg:postcode":"30535",
    "sg:province":"GA",
    "sg:tags":[
        "therapist",
        "physical"
    ],
    "wof:name":"Pro Therapy Svc",
    "wof:placetype":"venue"
},
  "geometry": {"coordinates":[-83.547595,34.559802],"type":"Point"}
}