{
  "type": "Feature",
  "properties": {
    "addr:full":"2000 Powers Ferry Rd SE Marietta GA 30067",
    "addr:housenumber":"2000",
    "addr:postcode":"30067",
    "addr:street":"Powers Ferry Rd Se",
    "iso:country":"US",
    "sg:address":"2000 Powers Ferry Rd SE",
    "sg:city":"Marietta",
    "sg:classifiers":[
        {
            "category":"Health Services",
            "subcategory":"Doctor",
            "type":"Services"
        },
        {
            "category":"Health Services",
            "subcategory":"Clinic",
            "type":"Services"
        },
        {
            "category":"Health Services",
            "subcategory":"Chiropractor",
            "type":"Services"
        }
    ],
    "sg:phone":"+1 770 859 9579",
    "sg:postcode":"30067",
    "sg:province":"GA",
    "sg:tags":[
        "physician",
        "medical",
        "surgeon",
        "chiropractic"
    ],
    "sg:website":"http://www.in-balancechiro.com",
    "wof:name":"Beckerman Alan DC",
    "wof:placetype":"venue"
},
  "geometry": {"coordinates":[-84.4646,33.906349],"type":"Point"}
}