{
  "type": "Feature",
  "properties": {
    "addr:full":"3400 Shallowford Rd NE Atlanta GA 30341",
    "addr:housenumber":"3400",
    "addr:postcode":"30341",
    "addr:street":"Shallowford Rd Ne",
    "iso:country":"US",
    "sg:address":"3400 Shallowford Rd NE",
    "sg:city":"Atlanta",
    "sg:classifiers":[
        {
            "category":"Organizations",
            "subcategory":"Religious Organization",
            "type":"Services"
        }
    ],
    "sg:phone":"+1 678 547 0600",
    "sg:postcode":"30341",
    "sg:province":"GA",
    "sg:tags":[
        "church"
    ],
    "wof:name":"Apostolic Church",
    "wof:placetype":"venue"
},
  "geometry": {"coordinates":[-84.28534000000001,33.887459],"type":"Point"}
}