{
  "type": "Feature",
  "properties": {
    "iso:country":"US",
    "sg:address":"14747 Appalachian Hwy",
    "sg:city":"Morganton",
    "sg:classifiers":[
        {
            "category":"Autos & Motor Vehicles",
            "subcategory":"Automobile Sales",
            "type":"Retail Goods"
        }
    ],
    "sg:phone":"+1 706 374 2275",
    "sg:postcode":"30560",
    "sg:province":"GA",
    "sg:tags":[
        "used"
    ],
    "wof:name":"Parks Auto Sales",
    "wof:placetype":"venue"
},
  "geometry": {"coordinates":[-84.150993,34.883885],"type":"Point"}
}