{
  "type": "Feature",
  "properties": {
    "iso:country":"US",
    "sg:address":"145 N Gross Rd",
    "sg:city":"Kingsland",
    "sg:classifiers":[
        {
            "category":"Travel",
            "subcategory":"Hotels & Motels",
            "type":"Entertainment"
        }
    ],
    "sg:phone":"+1 912 729 4988",
    "sg:postcode":"31548",
    "sg:province":"GA",
    "wof:name":"M'kynli's Ranch",
    "wof:placetype":"venue"
},
  "geometry": {"coordinates":[-81.64435400000001,30.78959],"type":"Point"}
}