{
  "type": "Feature",
  "properties": {
    "addr:full":"537 Monnie St Ashburn GA 31714",
    "addr:housenumber":"537",
    "addr:postcode":"31714",
    "addr:street":"Monnie St",
    "iso:country":"US",
    "sg:address":"537 Monnie St",
    "sg:city":"Ashburn",
    "sg:classifiers":[
        {
            "category":"Professional",
            "type":"Services"
        }
    ],
    "sg:phone":"+1 229 567 0527",
    "sg:postcode":"31714",
    "sg:province":"GA",
    "wof:name":"Hank J Pate",
    "wof:placetype":"venue"
},
  "geometry": {"coordinates":[-83.65067000000001,31.710997],"type":"Point"}
}