{
  "type": "Feature",
  "properties": {
    "addr:full":"980 Johnson Ferry Rd NE Atlanta GA 30342",
    "addr:housenumber":"980",
    "addr:postcode":"30342",
    "addr:street":"Johnson Ferry Rd Ne",
    "iso:country":"US",
    "sg:address":"980 Johnson Ferry Rd NE",
    "sg:city":"Atlanta",
    "sg:classifiers":[
        {
            "category":"Health Services",
            "subcategory":"Doctor",
            "type":"Services"
        },
        {
            "category":"Personal",
            "subcategory":"Adult",
            "type":"Services"
        }
    ],
    "sg:phone":"+1 404 255 8022",
    "sg:postcode":"30342",
    "sg:province":"GA",
    "sg:tags":[
        "midwife"
    ],
    "wof:name":"Howard H Kit MD",
    "wof:placetype":"venue"
},
  "geometry": {"coordinates":[-84.355003,33.907894],"type":"Point"}
}