{
  "type": "Feature",
  "properties": {
    "iso:country":"US",
    "sg:address":"555 Marietta Rd",
    "sg:city":"Canton",
    "sg:classifiers":[
        {
            "category":"Restaurant",
            "type":"Food & Drink"
        }
    ],
    "sg:phone":"+1 770 479 1160",
    "sg:postcode":"30114",
    "sg:province":"GA",
    "sg:tags":[
        "eating"
    ],
    "wof:name":"Ray's Country Kitchen",
    "wof:placetype":"venue"
},
  "geometry": {"coordinates":[-84.492879,34.227388],"type":"Point"}
}