{
  "type": "Feature",
  "properties": {
    "addr:full":"149 Alexander Ct Winder GA 30680",
    "addr:housenumber":"149",
    "addr:postcode":"30680",
    "addr:street":"Alexander Ct",
    "iso:country":"US",
    "sg:address":"149 Alexander Ct",
    "sg:city":"Winder",
    "sg:classifiers":[
        {
            "category":"Restaurant",
            "type":"Food & Drink"
        }
    ],
    "sg:phone":"+1 770 867 0794",
    "sg:postcode":"30680",
    "sg:province":"GA",
    "sg:tags":[
        "eating"
    ],
    "wof:name":"Tri Lors Inc",
    "wof:placetype":"venue"
},
  "geometry": {"coordinates":[-83.716269,34.005473],"type":"Point"}
}