{
  "type": "Feature",
  "properties": {
    "iso:country":"US",
    "sg:address":"300 Lynhurst Dr SW",
    "sg:city":"Atlanta",
    "sg:classifiers":[
        {
            "category":"Building & Trades",
            "subcategory":"Landscaping Services",
            "type":"Services"
        }
    ],
    "sg:phone":"+1 404 691 6589",
    "sg:postcode":"30311",
    "sg:province":"GA",
    "wof:name":"Lamar Lawn Care",
    "wof:placetype":"venue"
},
  "geometry": {"coordinates":[-84.48939900000001,33.745954],"type":"Point"}
}