{
  "type": "Feature",
  "properties": {
    "addr:full":"2115 Woodlake Blvd Monroe GA 30655",
    "addr:housenumber":"2115",
    "addr:postcode":"30655",
    "addr:street":"Woodlake Blvd",
    "iso:country":"US",
    "sg:address":"2115 Woodlake Blvd",
    "sg:city":"Monroe",
    "sg:classifiers":[
        {
            "category":"Professional",
            "subcategory":"Detective & Security Services",
            "type":"Services"
        }
    ],
    "sg:phone":"+1 770 207 8666",
    "sg:postcode":"30655",
    "sg:province":"GA",
    "sg:tags":[
        "car",
        "system",
        "investigator"
    ],
    "wof:name":"Godwin Agency Inc",
    "wof:placetype":"venue"
},
  "geometry": {"coordinates":[-83.78822599999999,33.787442],"type":"Point"}
}