{
  "type": "Feature",
  "properties": {
    "addr:full":"215 Industrial Way Fayetteville GA 30215",
    "addr:housenumber":"215",
    "addr:postcode":"30215",
    "addr:street":"Industrial Way",
    "iso:country":"US",
    "sg:address":"215 Industrial Way",
    "sg:city":"Fayetteville",
    "sg:classifiers":[
        {
            "category":"Retail",
            "subcategory":"Auto Repair",
            "type":"Services"
        }
    ],
    "sg:phone":"+1 770 461 3044",
    "sg:postcode":"30215",
    "sg:province":"GA",
    "sg:tags":[
        "towing",
        "wrecker"
    ],
    "wof:name":"Fayette Wrecker Inc",
    "wof:placetype":"venue"
},
  "geometry": {"coordinates":[-84.442258,33.443465],"type":"Point"}
}