{
  "type": "Feature",
  "properties": {
    "addr:full":"1602 McFarland Ave Rossville GA 30741",
    "addr:housenumber":"1602",
    "addr:postcode":"30741",
    "addr:street":"Mcfarland Ave",
    "iso:country":"US",
    "sg:address":"1602 McFarland Ave",
    "sg:city":"Rossville",
    "sg:classifiers":[
        {
            "category":"Building & Trades",
            "subcategory":"Cleaning & Sanitation",
            "type":"Services"
        }
    ],
    "sg:phone":"+1 706 858 8690",
    "sg:postcode":"30741",
    "sg:province":"GA",
    "sg:tags":[
        "janitor"
    ],
    "wof:name":"Hygafem-Georgia Inc",
    "wof:placetype":"venue"
},
  "geometry": {"coordinates":[-85.296629,34.964857],"type":"Point"}
}