{
  "type": "Feature",
  "properties": {
    "iso:country":"US",
    "sg:address":"155 Foe Creek Ct",
    "sg:city":"Roswell",
    "sg:classifiers":[
        {
            "category":"Social Services",
            "subcategory":"Child Care",
            "type":"Services"
        }
    ],
    "sg:phone":"+1 770 442 6991",
    "sg:postcode":"30076",
    "sg:province":"GA",
    "wof:name":"Teensy Tadpoles Day Care",
    "wof:placetype":"venue"
},
  "geometry": {"coordinates":[-84.33196100000001,34.070759],"type":"Point"}
}