{
  "type": "Feature",
  "properties": {
    "iso:country":"US",
    "sg:address":"1797 Spring Rd SE Ste 4",
    "sg:city":"Smyrna",
    "sg:classifiers":[
        {
            "category":"Professional",
            "type":"Services"
        },
        {
            "category":"Personal",
            "type":"Services"
        }
    ],
    "sg:phone":"+1 770 384 1904",
    "sg:postcode":"30080",
    "sg:province":"GA",
    "sg:tags":[
        "chef",
        "caterer"
    ],
    "sg:website":"time-to-dine.com/",
    "wof:name":"Time To Dine -Chefs and Caterers",
    "wof:placetype":"venue"
},
  "geometry": {"coordinates":[-84.500624,33.883708],"type":"Point"}
}