{
  "type": "Feature",
  "properties": {
    "iso:country":"US",
    "sg:address":"2824 Pontiac Cir",
    "sg:city":"Doraville",
    "sg:classifiers":[
        {
            "category":"Building & Trades",
            "subcategory":"Plumbing",
            "type":"Services"
        }
    ],
    "sg:phone":"+1 770 457 9905",
    "sg:postcode":"30360",
    "sg:province":"GA",
    "sg:tags":[
        "plumbing",
        "contractor"
    ],
    "wof:name":"Free Flow Plumbing & Drain Svc",
    "wof:placetype":"venue"
},
  "geometry": {"coordinates":[-84.278746,33.916413],"type":"Point"}
}