{
  "type": "Feature",
  "properties": {
    "addr:full":"2965 Pharr Court South NW Atlanta GA 30305",
    "addr:housenumber":"2965",
    "addr:postcode":"30305",
    "addr:street":"Pharr Court South Nw",
    "iso:country":"US",
    "sg:address":"2965 Pharr Court South NW",
    "sg:city":"Atlanta",
    "sg:classifiers":[
        {
            "category":"Retail",
            "subcategory":"Photofinishing",
            "type":"Services"
        }
    ],
    "sg:phone":"+1 404 467 4866",
    "sg:postcode":"30305",
    "sg:province":"GA",
    "sg:tags":[
        "photo",
        "restoration",
        "retouching"
    ],
    "wof:name":"Earthly Images",
    "wof:placetype":"venue"
},
  "geometry": {"coordinates":[-84.38552199999999,33.835722],"type":"Point"}
}