{
  "type": "Feature",
  "properties": {
    "iso:country":"US",
    "sg:address":"2190 Cobb Pkwy S",
    "sg:city":"Marietta",
    "sg:classifiers":[
        {
            "category":"Home & Garden",
            "subcategory":"Furniture",
            "type":"Retail Goods"
        }
    ],
    "sg:phone":"+1 770 989 0123",
    "sg:postcode":"30080",
    "sg:province":"GA",
    "wof:name":"Rooms To Go",
    "wof:placetype":"venue"
},
  "geometry": {"coordinates":[-84.480401,33.895194],"type":"Point"}
}