{
  "type": "Feature",
  "properties": {
    "iso:country":"US",
    "sg:address":"671 S Main St",
    "sg:city":"Baxley",
    "sg:classifiers":[
        {
            "category":"Home & Garden",
            "subcategory":"Hardware",
            "type":"Retail Goods"
        }
    ],
    "sg:phone":"+1 912 367 3664",
    "sg:postcode":"31513",
    "sg:province":"GA",
    "wof:name":"Bob's Do It Best",
    "wof:placetype":"venue"
},
  "geometry": {"coordinates":[-82.352785,31.768611],"type":"Point"}
}