{
  "type": "Feature",
  "properties": {
    "iso:country":"US",
    "sg:address":"132 N Oakley Dr",
    "sg:city":"Columbus",
    "sg:classifiers":[
        {
            "category":"Banks & Credit Unions",
            "subcategory":"Bank",
            "type":"Services"
        }
    ],
    "sg:phone":"+1 706 507 4824",
    "sg:postcode":"31906",
    "sg:province":"GA",
    "wof:name":"MEA Federal Credit Union",
    "wof:placetype":"venue"
},
  "geometry": {"coordinates":[-84.928763,32.445413],"type":"Point"}
}