{
  "type": "Feature",
  "properties": {
    "iso:country":"US",
    "sg:address":"253 Roundtree Rd",
    "sg:city":"Thomasville",
    "sg:classifiers":[
        {
            "category":"Professional",
            "type":"Services"
        }
    ],
    "sg:phone":"+1 229 227 9637",
    "sg:postcode":"31792",
    "sg:province":"GA",
    "sg:tags":[
        "establishment"
    ],
    "wof:name":"Office Barry Gursky",
    "wof:placetype":"venue"
},
  "geometry": {"coordinates":[-84.01271300000001,30.797887],"type":"Point"}
}