{
  "type": "Feature",
  "properties": {
    "iso:country":"US",
    "sg:address":"7 Dunwoody Park S",
    "sg:city":"Atlanta",
    "sg:classifiers":[
        {
            "category":"Communications",
            "type":"Services"
        }
    ],
    "sg:phone":"+1 770 352 0738",
    "sg:postcode":"30338",
    "sg:province":"GA",
    "wof:name":"Clear Communications",
    "wof:placetype":"venue"
},
  "geometry": {"coordinates":[-84.311268,33.923978],"type":"Point"}
}