{
  "type": "Feature",
  "properties": {
    "addr:full":"554 Lakeland Plz Cumming GA 30040",
    "addr:housenumber":"554",
    "addr:postcode":"30040",
    "addr:street":"Lakeland Plz",
    "iso:country":"US",
    "sg:address":"554 Lakeland Plz",
    "sg:city":"Cumming",
    "sg:classifiers":[
        {
            "category":"Personal",
            "type":"Services"
        }
    ],
    "sg:phone":"+1 770 844 0055",
    "sg:postcode":"30040",
    "sg:province":"GA",
    "sg:tags":[
        "tanning"
    ],
    "wof:name":"Sun City Tanning",
    "wof:placetype":"venue"
},
  "geometry": {"coordinates":[-84.145616,34.182457],"type":"Point"}
}