{
  "type": "Feature",
  "properties": {
    "iso:country":"US",
    "sg:address":"500 S Sage St",
    "sg:city":"Toccoa",
    "sg:classifiers":[
        {
            "category":"Organizations",
            "subcategory":"Religious Organization",
            "type":"Services"
        }
    ],
    "sg:phone":"+1 706 886 1814",
    "sg:postcode":"30577",
    "sg:province":"GA",
    "wof:name":"Friendship Baptist Church",
    "wof:placetype":"venue"
},
  "geometry": {"coordinates":[-83.32973699999999,34.574244],"type":"Point"}
}