{
  "type": "Feature",
  "properties": {
    "addr:full":"4405 Helen Hwy Cleveland GA 30528",
    "addr:housenumber":"4405",
    "addr:postcode":"30528",
    "addr:street":"Helen Hwy",
    "iso:country":"US",
    "sg:address":"4405 Helen Hwy",
    "sg:city":"Cleveland",
    "sg:classifiers":[
        {
            "category":"Bars & Pubs",
            "type":"Food & Drink"
        }
    ],
    "sg:phone":"+1 706 219 4776",
    "sg:postcode":"30528",
    "sg:province":"GA",
    "wof:name":"Beaux Cheveux Saloon",
    "wof:placetype":"venue"
},
  "geometry": {"coordinates":[-83.75771,34.608774],"type":"Point"}
}