{
  "type": "Feature",
  "properties": {
    "iso:country":"US",
    "sg:address":"614 Swan Lake Rd",
    "sg:city":"Stockbridge",
    "sg:classifiers":[
        {
            "category":"Building & Trades",
            "subcategory":"Plumbing",
            "type":"Services"
        }
    ],
    "sg:phone":"+1 770 389 0999",
    "sg:postcode":"30281",
    "sg:province":"GA",
    "wof:name":"White's Herbert Plumbing Company",
    "wof:placetype":"venue"
},
  "geometry": {"coordinates":[-84.18940000000001,33.593498],"type":"Point"}
}