{
  "type": "Feature",
  "properties": {
    "addr:full":"3833 Peachtree Rd NE # 705 Atlanta GA 30319",
    "addr:housenumber":"3833",
    "addr:postcode":"30319",
    "addr:street":"Peachtree Rd Ne # 705",
    "iso:country":"US",
    "sg:address":"3833 Peachtree Rd NE # 705",
    "sg:city":"Atlanta",
    "sg:classifiers":[
        {
            "category":"Shopping",
            "type":"Retail Goods"
        },
        {
            "category":"Organizations",
            "subcategory":"Non-profit Organization",
            "type":"Services"
        }
    ],
    "sg:phone":"+1 404 759 3172",
    "sg:postcode":"30319",
    "sg:province":"GA",
    "sg:tags":[
        "supply",
        "fund",
        "games",
        "merchandise",
        "raising"
    ],
    "wof:name":"Kcam Gordon Capital Group",
    "wof:placetype":"venue"
},
  "geometry": {"coordinates":[-84.34697199999999,33.857783],"type":"Point"}
}