{
  "type": "Feature",
  "properties": {
    "addr:full":"145 Temple Ave W Newnan GA 30263",
    "addr:housenumber":"145",
    "addr:postcode":"30263",
    "addr:street":"Temple Ave W",
    "iso:country":"US",
    "sg:address":"145 Temple Ave W",
    "sg:city":"Newnan",
    "sg:classifiers":[
        {
            "category":"Government",
            "subcategory":"Jail",
            "type":"Public Place"
        }
    ],
    "sg:phone":"+1 770 254 7247",
    "sg:postcode":"30263",
    "sg:province":"GA",
    "sg:tags":[
        "parole",
        "board",
        "pardon"
    ],
    "wof:name":"Pardons & Paroles GA State Bd",
    "wof:placetype":"venue"
},
  "geometry": {"coordinates":[-84.812438,33.381949],"type":"Point"}
}