{
  "type": "Feature",
  "properties": {
    "iso:country":"US",
    "sg:address":"609 Brookside Pass",
    "sg:city":"Woodstock",
    "sg:classifiers":[
        {
            "category":"Professional",
            "subcategory":"Computer Services",
            "type":"Services"
        }
    ],
    "sg:phone":"+1 770 516 2142",
    "sg:postcode":"30188",
    "sg:province":"GA",
    "sg:tags":[
        "programing",
        "custom"
    ],
    "wof:name":"Mimsware Corporation",
    "wof:placetype":"venue"
},
  "geometry": {"coordinates":[-84.481067,34.136345],"type":"Point"}
}