{
  "type": "Feature",
  "properties": {
    "iso:country":"US",
    "sg:address":"324 Corder Rd",
    "sg:city":"Warner Robins",
    "sg:classifiers":[
        {
            "category":"Manufacturing",
            "subcategory":"Aerospace",
            "type":"Manufacturing & Wholesale Goods"
        }
    ],
    "sg:phone":"+1 478 929 5090",
    "sg:postcode":"31088",
    "sg:province":"GA",
    "sg:tags":[
        "aircraft",
        "mfg"
    ],
    "wof:name":"Sikorsky Aircraft Corporation",
    "wof:placetype":"venue"
},
  "geometry": {"coordinates":[-83.65140100000001,32.613772],"type":"Point"}
}