{
  "type": "Feature",
  "properties": {
    "addr:full":"1275 Powers Ferry Rd SE Ste 250 Marietta GA 30067",
    "addr:housenumber":"1275",
    "addr:postcode":"30067",
    "addr:street":"Powers Ferry Rd Se Ste 250",
    "iso:country":"US",
    "sg:address":"1275 Powers Ferry Rd SE Ste 250",
    "sg:city":"Marietta",
    "sg:classifiers":[
        {
            "category":"Health Services",
            "subcategory":"Dentist",
            "type":"Services"
        }
    ],
    "sg:phone":"+1 770 955 3878",
    "sg:postcode":"30067",
    "sg:province":"GA",
    "sg:tags":[
        "orthodontist"
    ],
    "sg:website":"www.atlantadentalspecialists.com",
    "wof:name":"Atlanta Dental Specialists",
    "wof:placetype":"venue"
},
  "geometry": {"coordinates":[-84.46770100000001,33.921958],"type":"Point"}
}