{
  "type": "Feature",
  "properties": {
    "addr:full":"1402 Walke Dairy Rd Dublin GA 31021",
    "addr:housenumber":"1402",
    "addr:postcode":"31021",
    "addr:street":"Walke Dairy Rd",
    "iso:country":"US",
    "sg:address":"1402 Walke Dairy Rd",
    "sg:city":"Dublin",
    "sg:classifiers":[
        {
            "category":"Shopping",
            "subcategory":"Catalog Store",
            "type":"Retail Goods"
        }
    ],
    "sg:phone":"+1 478 676 4391",
    "sg:postcode":"31021",
    "sg:province":"GA",
    "sg:tags":[
        "mail",
        "house"
    ],
    "wof:name":"Acebuyscom",
    "wof:placetype":"venue"
},
  "geometry": {"coordinates":[-83.029319,32.514448],"type":"Point"}
}