{
  "type": "Feature",
  "properties": {
    "iso:country":"US",
    "sg:address":"4416 Trailwood Dr",
    "sg:city":"Cohutta",
    "sg:classifiers":[
        {
            "category":"Professional",
            "subcategory":"Accounting & Tax Preparation",
            "type":"Services"
        }
    ],
    "sg:phone":"+1 706 694 8931",
    "sg:postcode":"30710",
    "sg:province":"GA",
    "sg:tags":[
        "public",
        "accountants-certified"
    ],
    "wof:name":"James D Halpin",
    "wof:placetype":"venue"
},
  "geometry": {"coordinates":[-84.95626799999999,34.925605],"type":"Point"}
}