{
  "type": "Feature",
  "properties": {
    "addr:full":"717 Atlanta Rd Gainesville GA 30501",
    "addr:housenumber":"717",
    "addr:postcode":"30501",
    "addr:street":"Atlanta Rd",
    "iso:country":"US",
    "sg:address":"717 Atlanta Rd",
    "sg:city":"Gainesville",
    "sg:classifiers":[
        {
            "category":"Professional",
            "subcategory":"Business Services",
            "type":"Services"
        }
    ],
    "sg:phone":"+1 678 450 0068",
    "sg:postcode":"30501",
    "sg:province":"GA",
    "wof:name":"American Automotive Solutions",
    "wof:placetype":"venue"
},
  "geometry": {"coordinates":[-83.840007,34.279111],"type":"Point"}
}