{
  "type": "Feature",
  "properties": {
    "iso:country":"US",
    "sg:address":"1899 Lonergan Hulme Rd",
    "sg:city":"Harlem",
    "sg:classifiers":[
        {
            "category":"Building & Trades",
            "subcategory":"Construction",
            "type":"Services"
        }
    ],
    "sg:phone":"+1 706 541 1028",
    "sg:postcode":"30802",
    "sg:province":"GA",
    "sg:tags":[
        "house"
    ],
    "wof:name":"Kelley S Home Improvement",
    "wof:placetype":"venue"
},
  "geometry": {"coordinates":[-82.30720700000001,33.504015],"type":"Point"}
}