{
  "type": "Feature",
  "properties": {
    "iso:country":"US",
    "sg:address":"4509 Pine St",
    "sg:city":"Smyrna",
    "sg:classifiers":[
        {
            "category":"Retail",
            "subcategory":"Laundry & Dry Cleaning",
            "type":"Services"
        }
    ],
    "sg:phone":"+1 770 438 0407",
    "sg:postcode":"30080",
    "sg:province":"GA",
    "sg:tags":[
        "cleaners",
        "rug",
        "carpet"
    ],
    "wof:name":"Economic Carpet & Upholstery",
    "wof:placetype":"venue"
},
  "geometry": {"coordinates":[-84.491255,33.844416],"type":"Point"}
}