{
  "type": "Feature",
  "properties": {
    "iso:country":"US",
    "sg:address":"699 N Davis Dr",
    "sg:city":"Warner Robins",
    "sg:classifiers":[
        {
            "category":"Food & Beverages",
            "subcategory":"Groceries & Convenience Stores",
            "type":"Retail Goods"
        }
    ],
    "sg:phone":"+1 478 922 8019",
    "sg:postcode":"31093",
    "sg:province":"GA",
    "sg:tags":[
        "product"
    ],
    "wof:name":"Lolo Foods #4",
    "wof:placetype":"venue"
},
  "geometry": {"coordinates":[-83.612905,32.63686],"type":"Point"}
}