{
  "type": "Feature",
  "properties": {
    "iso:country":"US",
    "sg:address":"2266 Riverside Rd",
    "sg:city":"Valdosta",
    "sg:classifiers":[
        {
            "category":"Personal",
            "subcategory":"Beauty Salon",
            "type":"Services"
        }
    ],
    "sg:phone":"+1 229 242 9393",
    "sg:postcode":"31601",
    "sg:province":"GA",
    "wof:name":"Johnsons Beauty",
    "wof:placetype":"venue"
},
  "geometry": {"coordinates":[-83.33931,30.811212],"type":"Point"}
}