{
  "type": "Feature",
  "properties": {
    "addr:full":"215 Lake Mirror Rd Forest Park GA 30297",
    "addr:housenumber":"215",
    "addr:postcode":"30297",
    "addr:street":"Lake Mirror Rd",
    "iso:country":"US",
    "sg:address":"215 Lake Mirror Rd",
    "sg:city":"Forest Park",
    "sg:classifiers":[
        {
            "category":"Wholesale",
            "subcategory":"Machinery & Supplies",
            "type":"Manufacturing & Wholesale Goods"
        }
    ],
    "sg:phone":"+1 404 363 1061",
    "sg:postcode":"30297",
    "sg:province":"GA",
    "sg:tags":[
        "equipment"
    ],
    "sg:website":"www.pcshd.com",
    "wof:name":"Patent Construction Systems",
    "wof:placetype":"venue"
},
  "geometry": {"coordinates":[-84.394864,33.627468],"type":"Point"}
}