{
  "type": "Feature",
  "properties": {
    "iso:country":"US",
    "sg:address":"2030 Savannah Hwy",
    "sg:city":"Jesup",
    "sg:classifiers":[
        {
            "category":"Building & Trades",
            "subcategory":"Construction",
            "type":"Services"
        }
    ],
    "sg:phone":"+1 912 427 8576",
    "sg:postcode":"31545",
    "sg:province":"GA",
    "wof:name":"Ratliff Asphalt Paving",
    "wof:placetype":"venue"
},
  "geometry": {"coordinates":[-81.864901,31.629883],"type":"Point"}
}