{
  "type": "Feature",
  "properties": {
    "addr:full":"211 Maddox Rd Griffin GA 30224",
    "addr:housenumber":"211",
    "addr:postcode":"30224",
    "addr:street":"Maddox Rd",
    "iso:country":"US",
    "sg:address":"211 Maddox Rd",
    "sg:city":"Griffin",
    "sg:classifiers":[
        {
            "category":"Wholesale",
            "subcategory":"Machinery & Supplies",
            "type":"Manufacturing & Wholesale Goods"
        }
    ],
    "sg:phone":"+1 770 233 8929",
    "sg:postcode":"30224",
    "sg:province":"GA",
    "sg:tags":[
        "funeral"
    ],
    "wof:name":"Georgia Funeral Supply",
    "wof:placetype":"venue"
},
  "geometry": {"coordinates":[-84.26431100000001,33.216137],"type":"Point"}
}