{
  "type": "Feature",
  "properties": {
    "addr:full":"100 Galleria Pkwy SE Atlanta GA 30339",
    "addr:housenumber":"100",
    "addr:postcode":"30339",
    "addr:street":"Galleria Pkwy Se",
    "iso:country":"US",
    "sg:address":"100 Galleria Pkwy SE",
    "sg:city":"Atlanta",
    "sg:classifiers":[
        {
            "category":"Professional",
            "subcategory":"Accounting & Tax Preparation",
            "type":"Services"
        }
    ],
    "sg:phone":"+1 770 859 0859",
    "sg:postcode":"30339",
    "sg:province":"GA",
    "sg:tags":[
        "accountant"
    ],
    "wof:name":"Professional Accounting Sales",
    "wof:placetype":"venue"
},
  "geometry": {"coordinates":[-84.465401,33.882599],"type":"Point"}
}