{
  "type": "Feature",
  "properties": {
    "iso:country":"US",
    "sg:address":"1205 Newcastle St",
    "sg:city":"Brunswick",
    "sg:classifiers":[
        {
            "category":"Wholesale",
            "subcategory":"Furniture",
            "type":"Manufacturing & Wholesale Goods"
        }
    ],
    "sg:phone":"+1 912 265 8827",
    "sg:postcode":"31520",
    "sg:province":"GA",
    "wof:name":"Golden Isles Office Equipment",
    "wof:placetype":"venue"
},
  "geometry": {"coordinates":[-81.49486899999999,31.147778],"type":"Point"}
}