{
  "type": "Feature",
  "properties": {
    "iso:country":"US",
    "sg:address":"6820 Roswell Rd NE",
    "sg:city":"Atlanta",
    "sg:classifiers":[
        {
            "category":"Organizations",
            "subcategory":"Religious Organization",
            "type":"Services"
        }
    ],
    "sg:phone":"+1 770 671 0505",
    "sg:postcode":"30328",
    "sg:province":"GA",
    "wof:name":"Izunome Association USA",
    "wof:placetype":"venue"
},
  "geometry": {"coordinates":[-84.37370300000001,33.941898],"type":"Point"}
}