{
  "type": "Feature",
  "properties": {
    "addr:full":"825 Jamerson Rd NE Marietta GA 30066",
    "addr:housenumber":"825",
    "addr:postcode":"30066",
    "addr:street":"Jamerson Rd Ne",
    "iso:country":"US",
    "sg:address":"825 Jamerson Rd NE",
    "sg:city":"Marietta",
    "sg:classifiers":[
        {
            "category":"Professional",
            "subcategory":"Management & Consulting",
            "type":"Services"
        }
    ],
    "sg:phone":"+1 770 592 0616",
    "sg:postcode":"30066",
    "sg:province":"GA",
    "sg:tags":[
        "business"
    ],
    "wof:name":"Safety Plus ISS Inc",
    "wof:placetype":"venue"
},
  "geometry": {"coordinates":[-84.527367,34.068233],"type":"Point"}
}