{
  "type": "Feature",
  "properties": {
    "iso:country":"US",
    "sg:address":"2495 E West Connector",
    "sg:city":"Austell",
    "sg:classifiers":[
        {
            "category":"Restaurant",
            "type":"Food & Drink"
        }
    ],
    "sg:phone":"+1 678 384 1169",
    "sg:postcode":"30106",
    "sg:province":"GA",
    "sg:tags":[
        "italian"
    ],
    "sg:website":"www.giovannisgenuineitalian.com",
    "wof:name":"Giovanni's Restaurant",
    "wof:placetype":"venue"
},
  "geometry": {"coordinates":[-84.620637,33.860912],"type":"Point"}
}