{
  "type": "Feature",
  "properties": {
    "iso:country":"US",
    "sg:address":"526 Billingswood Dr",
    "sg:city":"Macon",
    "sg:classifiers":[
        {
            "category":"Real Estate",
            "subcategory":"Real Estate Agent",
            "type":"Services"
        }
    ],
    "sg:phone":"+1 478 477 4564",
    "sg:postcode":"31210",
    "sg:province":"GA",
    "wof:name":"Southern Realty Assoc",
    "wof:placetype":"venue"
},
  "geometry": {"coordinates":[-83.727897,32.89434],"type":"Point"}
}