{
  "type": "Feature",
  "properties": {
    "iso:country":"US",
    "sg:address":"113 Blackbird Ln",
    "sg:city":"Darien",
    "sg:classifiers":[
        {
            "category":"Shopping",
            "subcategory":"Computers & Home Electronics",
            "type":"Retail Goods"
        }
    ],
    "sg:phone":"+1 912 437 3600",
    "sg:postcode":"31321",
    "sg:province":"GA",
    "wof:name":"Fullhouse Media Solutions",
    "wof:placetype":"venue"
},
  "geometry": {"coordinates":[-81.565178,32.131167],"type":"Point"}
}