{
  "type": "Feature",
  "properties": {
    "addr:full":"183 Cherokee Pl Cartersville GA 30121",
    "addr:housenumber":"183",
    "addr:postcode":"30121",
    "addr:street":"Cherokee Pl",
    "iso:country":"US",
    "sg:address":"183 Cherokee Pl",
    "sg:city":"Cartersville",
    "sg:classifiers":[
        {
            "category":"Ice Cream",
            "type":"Food & Drink"
        }
    ],
    "sg:menulink":"http://www.allmenus.com/ga/cartersville/171625-brusters/menu/",
    "sg:phone":"+1 770 606 0553",
    "sg:postcode":"30121",
    "sg:province":"GA",
    "sg:tags":[
        "american"
    ],
    "wof:name":"Brusters",
    "wof:placetype":"venue"
},
  "geometry": {"coordinates":[-84.782495,34.171806],"type":"Point"}
}