{
  "type": "Feature",
  "properties": {
    "addr:full":"211 Hamilton Ave Bremen GA 30110",
    "addr:housenumber":"211",
    "addr:postcode":"30110",
    "addr:street":"Hamilton Ave",
    "iso:country":"US",
    "sg:address":"211 Hamilton Ave",
    "sg:city":"Bremen",
    "sg:classifiers":[
        {
            "category":"Banks & Credit Unions",
            "subcategory":"Bank",
            "type":"Services"
        }
    ],
    "sg:phone":"+1 770 537 5581",
    "sg:postcode":"30110",
    "sg:province":"GA",
    "sg:tags":[
        "state"
    ],
    "wof:name":"South Trust Bank",
    "wof:placetype":"venue"
},
  "geometry": {"coordinates":[-85.147537,33.723456],"type":"Point"}
}