{
  "type": "Feature",
  "properties": {
    "addr:full":"3405 Sweetwater Rd Lawrenceville GA 30044",
    "addr:housenumber":"3405",
    "addr:postcode":"30044",
    "addr:street":"Sweetwater Rd",
    "iso:country":"US",
    "sg:address":"3405 Sweetwater Rd",
    "sg:city":"Lawrenceville",
    "sg:classifiers":[
        {
            "category":"Retail",
            "subcategory":"Repair Shop",
            "type":"Services"
        }
    ],
    "sg:phone":"+1 770 923 2827",
    "sg:postcode":"30044",
    "sg:province":"GA",
    "wof:name":"Hummingbird Cleaner",
    "wof:placetype":"venue"
},
  "geometry": {"coordinates":[-84.117594,33.944819],"type":"Point"}
}