{
  "type": "Feature",
  "properties": {
    "addr:full":"325 Birch Hollow Ct Roswell GA 30075",
    "addr:housenumber":"325",
    "addr:postcode":"30075",
    "addr:street":"Birch Hollow Ct",
    "iso:country":"US",
    "sg:address":"325 Birch Hollow Ct",
    "sg:city":"Roswell",
    "sg:classifiers":[
        {
            "category":"Wholesale",
            "subcategory":"Construction Materials",
            "type":"Manufacturing & Wholesale Goods"
        }
    ],
    "sg:phone":"+1 770 993 7692",
    "sg:postcode":"30075",
    "sg:province":"GA",
    "wof:name":"Polaris Aggregates Inc",
    "wof:placetype":"venue"
},
  "geometry": {"coordinates":[-84.412952,34.067715],"type":"Point"}
}