{
  "type": "Feature",
  "properties": {
    "addr:full":"122 E Lake Dr Decatur GA 30030",
    "addr:housenumber":"122",
    "addr:postcode":"30030",
    "addr:street":"E Lake Dr",
    "iso:country":"US",
    "sg:address":"122 E Lake Dr",
    "sg:city":"Decatur",
    "sg:classifiers":[
        {
            "category":"Shopping",
            "subcategory":"Musical Instruments",
            "type":"Retail Goods"
        }
    ],
    "sg:phone":"+1 404 378 1132",
    "sg:postcode":"30030",
    "sg:province":"GA",
    "sg:tags":[
        "instruments-supplies",
        "music",
        "accessory"
    ],
    "wof:name":"Opus Winds Music",
    "wof:placetype":"venue"
},
  "geometry": {"coordinates":[-84.311142,33.763908],"type":"Point"}
}