{
  "type": "Feature",
  "properties": {
    "addr:full":"719 Scenic Hwy Ste B Lawrenceville GA 30046",
    "addr:housenumber":"719",
    "addr:postcode":"30046",
    "addr:street":"Scenic Hwy Ste B",
    "iso:country":"US",
    "sg:address":"719 Scenic Hwy Ste B",
    "sg:city":"Lawrenceville",
    "sg:classifiers":[
        {
            "category":"Health Services",
            "subcategory":"Dentist",
            "type":"Services"
        }
    ],
    "sg:phone":"+1 678 377 6830",
    "sg:postcode":"30046",
    "sg:province":"GA",
    "wof:name":"Fawole S Alaba DDS MD PC",
    "wof:placetype":"venue"
},
  "geometry": {"coordinates":[-83.998887,33.921812],"type":"Point"}
}