{
  "type": "Feature",
  "properties": {
    "iso:country":"US",
    "sg:address":"5150 Willow Oak Trl",
    "sg:city":"Norcross",
    "sg:classifiers":[
        {
            "category":"Travel",
            "subcategory":"Hotels & Motels",
            "type":"Entertainment"
        }
    ],
    "sg:phone":"+1 770 931 5353",
    "sg:postcode":"30093",
    "sg:province":"GA",
    "sg:website":"www.super8.com",
    "wof:name":"Super 8 Motel",
    "wof:placetype":"venue"
},
  "geometry": {"coordinates":[-84.175301,33.925598],"type":"Point"}
}