{
  "type": "Feature",
  "properties": {
    "addr:full":"374 Maynard Ter SE Atlanta GA 30316",
    "addr:housenumber":"374",
    "addr:postcode":"30316",
    "addr:street":"Maynard Ter Se",
    "iso:country":"US",
    "sg:address":"374 Maynard Ter SE",
    "sg:city":"Atlanta",
    "sg:classifiers":[
        {
            "category":"Building & Trades",
            "subcategory":"Plumbing",
            "type":"Services"
        },
        {
            "category":"Organizations",
            "subcategory":"Labor Organization",
            "type":"Services"
        },
        {
            "category":"Organizations",
            "subcategory":"Community Association",
            "type":"Services"
        },
        {
            "category":"Organizations",
            "subcategory":"Professional Association",
            "type":"Services"
        }
    ],
    "sg:phone":"+1 404 373 5778",
    "sg:postcode":"30316",
    "sg:province":"GA",
    "sg:tags":[
        "plumber",
        "business"
    ],
    "sg:website":"http://www.ua72.org",
    "wof:name":"Plumbers Steamfitters & Service Technicians Local Union No 72",
    "wof:placetype":"venue"
},
  "geometry": {"coordinates":[-84.334673,33.744004],"type":"Point"}
}