{
  "type": "Feature",
  "properties": {
    "iso:country":"US",
    "sg:address":"199 14th St NE",
    "sg:city":"Atlanta",
    "sg:classifiers":[
        {
            "category":"Professional",
            "subcategory":"Management & Consulting",
            "type":"Services"
        }
    ],
    "sg:phone":"+1 404 892 5547",
    "sg:postcode":"30309",
    "sg:province":"GA",
    "sg:tags":[
        "fuel"
    ],
    "wof:name":"Huang Priest Inc",
    "wof:placetype":"venue"
},
  "geometry": {"coordinates":[-84.37984899999999,33.786409],"type":"Point"}
}