{
  "type": "Feature",
  "properties": {
    "addr:full":"751 Dekalb Industrial Way Decatur GA 30033",
    "addr:housenumber":"751",
    "addr:postcode":"30033",
    "addr:street":"Dekalb Industrial Way",
    "iso:country":"US",
    "sg:address":"751 Dekalb Industrial Way",
    "sg:city":"Decatur",
    "sg:classifiers":[
        {
            "category":"Shopping",
            "subcategory":"Crafts & Fabrics",
            "type":"Retail Goods"
        },
        {
            "category":"Shopping",
            "subcategory":"Clothing, Apparel, & Fashions",
            "type":"Retail Goods"
        }
    ],
    "sg:phone":"+1 404 297 9898",
    "sg:postcode":"30033",
    "sg:province":"GA",
    "sg:tags":[
        "shop"
    ],
    "wof:name":"India Silk House",
    "wof:placetype":"venue"
},
  "geometry": {"coordinates":[-84.279023,33.797049],"type":"Point"}
}