{
  "type": "Feature",
  "properties": {
    "addr:full":"4691 Maroney Mill Rd Douglasville GA 30134",
    "addr:housenumber":"4691",
    "addr:postcode":"30134",
    "addr:street":"Maroney Mill Rd",
    "iso:country":"US",
    "sg:address":"4691 Maroney Mill Rd",
    "sg:city":"Douglasville",
    "sg:classifiers":[
        {
            "category":"Restaurant",
            "type":"Food & Drink"
        }
    ],
    "sg:phone":"+1 770 949 9051",
    "sg:postcode":"30134",
    "sg:province":"GA",
    "sg:tags":[
        "eating"
    ],
    "wof:name":"Chucks Catering",
    "wof:placetype":"venue"
},
  "geometry": {"coordinates":[-84.73101699999999,33.782488],"type":"Point"}
}