{
  "type": "Feature",
  "properties": {
    "iso:country":"US",
    "sg:address":"1740 Taylor Ave",
    "sg:city":"Atlanta",
    "sg:classifiers":[
        {
            "category":"Banks & Credit Unions",
            "subcategory":"Investment Brokerage",
            "type":"Services"
        }
    ],
    "sg:phone":"+1 917 569 2560",
    "sg:postcode":"30344",
    "sg:province":"GA",
    "sg:tags":[
        "tape",
        "video",
        "sale",
        "dvds-rental"
    ],
    "wof:name":"Ttp Productions",
    "wof:placetype":"venue"
},
  "geometry": {"coordinates":[-84.445615,33.673445],"type":"Point"}
}