{
  "type": "Feature",
  "properties": {
    "addr:full":"3119 Tadmore Ct Dacula GA 30019",
    "addr:housenumber":"3119",
    "addr:postcode":"ga 30019",
    "addr:street":"Tadmore Ct",
    "iso:country":"US",
    "sg:address":"3119 Tadmore Ct",
    "sg:city":"Dacula",
    "sg:classifiers":[
        {
            "category":"Retail",
            "subcategory":"Animal Services",
            "type":"Services"
        }
    ],
    "sg:phone":"+1 770 932 5461",
    "sg:postcode":"30019",
    "sg:province":"GA",
    "wof:name":"Lawrenceville Kennel Club Inc",
    "wof:placetype":"venue"
},
  "geometry": {"coordinates":[-83.919606,34.063092],"type":"Point"}
}