{
  "type": "Feature",
  "properties": {
    "addr:full":"6335 Highway 85 Riverdale GA 30274",
    "addr:housenumber":"6335",
    "addr:postcode":"30274",
    "addr:street":"Highway 85",
    "iso:country":"US",
    "sg:address":"6335 Highway 85",
    "sg:city":"Riverdale",
    "sg:classifiers":[
        {
            "category":"Restaurant",
            "type":"Food & Drink"
        }
    ],
    "sg:phone":"+1 770 907 0575",
    "sg:postcode":"30274",
    "sg:province":"GA",
    "sg:tags":[
        "chinese",
        "barbeque"
    ],
    "wof:name":"Ming's Bbq & Noodle",
    "wof:placetype":"venue"
},
  "geometry": {"coordinates":[-84.411507,33.582719],"type":"Point"}
}