{
  "type": "Feature",
  "properties": {
    "iso:country":"US",
    "sg:address":"9660 State Rte 242",
    "sg:city":"Harrison",
    "sg:classifiers":[
        {
            "category":"Shopping",
            "subcategory":"Discount & Variety Stores",
            "type":"Retail Goods"
        },
        {
            "category":"Shopping",
            "subcategory":"Clothing, Apparel, & Fashions",
            "type":"Retail Goods"
        }
    ],
    "sg:phone":"+1 478 553 1170",
    "sg:postcode":"31035",
    "sg:province":"GA",
    "sg:tags":[
        "salvage",
        "surplus",
        "merchandise",
        "general"
    ],
    "wof:name":"T & M Sales",
    "wof:placetype":"venue"
},
  "geometry": {"coordinates":[-82.65959700000001,32.901478],"type":"Point"}
}