{
  "type": "Feature",
  "properties": {
    "addr:full":"123 Sequoia Dr Eatonton GA 31024",
    "addr:housenumber":"123",
    "addr:postcode":"31024",
    "addr:street":"Sequoia Dr",
    "iso:country":"US",
    "sg:address":"123 Sequoia Dr",
    "sg:city":"Eatonton",
    "sg:classifiers":[
        {
            "category":"Real Estate",
            "subcategory":"Real Estate Agent",
            "type":"Services"
        }
    ],
    "sg:phone":"+1 706 485 6118",
    "sg:postcode":"31024",
    "sg:province":"GA",
    "wof:name":"Stevens Properties",
    "wof:placetype":"venue"
},
  "geometry": {"coordinates":[-83.26661199999999,33.442496],"type":"Point"}
}