{
  "type": "Feature",
  "properties": {
    "addr:full":"2500 Hospital Blvd Ste 260 Roswell GA 30076",
    "addr:housenumber":"2500",
    "addr:postcode":"30076",
    "addr:street":"Hospital Blvd Ste 260",
    "iso:country":"US",
    "sg:address":"2500 Hospital Blvd Ste 260",
    "sg:city":"Roswell",
    "sg:classifiers":[
        {
            "category":"Health Services",
            "subcategory":"Doctor",
            "type":"Services"
        }
    ],
    "sg:phone":"+1 770 410 4649",
    "sg:postcode":"30076",
    "sg:province":"GA",
    "wof:name":"Ditter Susan MD",
    "wof:placetype":"venue"
},
  "geometry": {"coordinates":[-84.320198,34.061901],"type":"Point"}
}