{
  "type": "Feature",
  "properties": {
    "addr:full":"526 Highway 11 SW Monroe GA 30655",
    "addr:housenumber":"526",
    "addr:postcode":"30655",
    "addr:street":"Highway 11 Sw",
    "iso:country":"US",
    "sg:address":"526 Highway 11 SW",
    "sg:city":"Monroe",
    "sg:classifiers":[
        {
            "category":"Place Of Worship",
            "type":"Public Place"
        }
    ],
    "sg:phone":"+1 770 267 2028",
    "sg:postcode":"30655",
    "sg:province":"GA",
    "sg:tags":[
        "church"
    ],
    "wof:name":"Pleasant Valley United Methodist Church",
    "wof:placetype":"venue"
},
  "geometry": {"coordinates":[-83.701775,33.75176],"type":"Point"}
}