{
  "type": "Feature",
  "properties": {
    "iso:country":"US",
    "sg:address":"161 Village Pkwy NE",
    "sg:city":"Marietta",
    "sg:classifiers":[
        {
            "category":"Professional",
            "subcategory":"Computer Services",
            "type":"Services"
        }
    ],
    "sg:phone":"+1 770 953 3443",
    "sg:postcode":"30067",
    "sg:province":"GA",
    "sg:tags":[
        "information",
        "technology"
    ],
    "wof:name":"Skybridge Global",
    "wof:placetype":"venue"
},
  "geometry": {"coordinates":[-84.41195,33.950997],"type":"Point"}
}