{
  "type": "Feature",
  "properties": {
    "addr:full":"180 Bulloch Ave Roswell GA 30075",
    "addr:housenumber":"180",
    "addr:postcode":"30075",
    "addr:street":"Bulloch Ave",
    "iso:country":"US",
    "sg:address":"180 Bulloch Ave",
    "sg:city":"Roswell",
    "sg:classifiers":[
        {
            "category":"Landmark",
            "subcategory":"Historic",
            "type":"Public Place"
        },
        {
            "category":"Landmark",
            "subcategory":"Tourist Information",
            "type":"Public Place"
        },
        {
            "category":"Museum",
            "type":"Entertainment"
        }
    ],
    "sg:phone":"+1 770 992 1731",
    "sg:postcode":"30075",
    "sg:province":"GA",
    "sg:tags":[
        "building",
        "tour",
        "historical"
    ],
    "sg:website":"www.bullochhall.org",
    "wof:name":"Bulloch Hall",
    "wof:placetype":"venue"
},
  "geometry": {"coordinates":[-84.36640199999999,34.015301],"type":"Point"}
}