{
  "type": "Feature",
  "properties": {
    "iso:country":"US",
    "sg:address":"226 Bovine Rd",
    "sg:city":"Sylvania",
    "sg:classifiers":[
        {
            "category":"Building & Trades",
            "subcategory":"Construction",
            "type":"Services"
        }
    ],
    "sg:phone":"+1 912 863 6373",
    "sg:postcode":"30467",
    "sg:province":"GA",
    "sg:tags":[
        "house",
        "excavating",
        "contractor"
    ],
    "wof:name":"Gary Crews Construction Inc",
    "wof:placetype":"venue"
},
  "geometry": {"coordinates":[-81.567291,32.719191],"type":"Point"}
}