{
  "type": "Feature",
  "properties": {
    "iso:country":"US",
    "sg:address":"3106 Nails Ferry Rd",
    "sg:city":"Baxley",
    "sg:classifiers":[
        {
            "category":"Freight",
            "type":"Transportation"
        }
    ],
    "sg:phone":"+1 912 367 9766",
    "sg:postcode":"31513",
    "sg:province":"GA",
    "sg:tags":[
        "operator",
        "local",
        "trucking"
    ],
    "wof:name":"Pfau Trucking Inc",
    "wof:placetype":"venue"
},
  "geometry": {"coordinates":[-82.378927,31.828392],"type":"Point"}
}