{
  "type": "Feature",
  "properties": {
    "addr:full":"3320 Centerville Hwy Snellville GA 30039",
    "addr:housenumber":"3320",
    "addr:postcode":"30039",
    "addr:street":"Centerville Hwy",
    "iso:country":"US",
    "sg:address":"3320 Centerville Hwy",
    "sg:city":"Snellville",
    "sg:classifiers":[
        {
            "category":"Social Services",
            "subcategory":"Child Care",
            "type":"Services"
        }
    ],
    "sg:phone":"+1 770 978 0523",
    "sg:postcode":"30039",
    "sg:province":"GA",
    "sg:tags":[
        "day"
    ],
    "sg:website":"www.aclass-scholars.com",
    "wof:name":"A Class Scholars Child Development",
    "wof:placetype":"venue"
},
  "geometry": {"coordinates":[-84.04225,33.811127],"type":"Point"}
}