{
  "type": "Feature",
  "properties": {
    "addr:full":"100 Miller Ln Thomasville GA 31791",
    "addr:housenumber":"100",
    "addr:postcode":"31791",
    "addr:street":"Miller Ln",
    "iso:country":"US",
    "sg:address":"100 Miller Ln",
    "sg:city":"Thomasville",
    "sg:classifiers":[
        {
            "category":"Organizations",
            "subcategory":"Community Association",
            "type":"Services"
        }
    ],
    "sg:phone":"+1 229 226 0090",
    "sg:postcode":"31791",
    "sg:province":"GA",
    "sg:tags":[
        "fraternal"
    ],
    "wof:name":"Mill Creek Plantation",
    "wof:placetype":"venue"
},
  "geometry": {"coordinates":[-83.842069,31.56376],"type":"Point"}
}