{
  "type": "Feature",
  "properties": {
    "iso:country":"US",
    "sg:address":"699 11th Street Suite 100",
    "sg:city":"Atlanta",
    "sg:classifiers":[
        {
            "category":"Professional",
            "subcategory":"Management & Consulting",
            "type":"Services"
        }
    ],
    "sg:phone":"+1 404 541 2255",
    "sg:postcode":"30318",
    "sg:province":"GA",
    "sg:tags":[
        "freeworld-media",
        "social-media",
        "socialmedia",
        "social-responsibility",
        "csr",
        "atlanta",
        "social-business",
        "strategic",
        "digital",
        "marketing"
    ],
    "sg:website":"http://www.freeworldmedia.com",
    "wof:name":"Freeworld Media",
    "wof:placetype":"venue"
},
  "geometry": {"coordinates":[-84.410208,33.782927],"type":"Point"}
}