{
  "type": "Feature",
  "properties": {
    "addr:full":"1932 Cobblewood Dr Kennesaw GA 30152",
    "addr:housenumber":"1932",
    "addr:postcode":"30152",
    "addr:street":"Cobblewood Dr",
    "iso:country":"US",
    "sg:address":"1932 Cobblewood Dr",
    "sg:city":"Kennesaw",
    "sg:classifiers":[
        {
            "category":"Wholesale",
            "subcategory":"Vending Machines",
            "type":"Manufacturing & Wholesale Goods"
        }
    ],
    "sg:phone":"+1 770 420 3526",
    "sg:postcode":"30152",
    "sg:province":"GA",
    "wof:name":"East Coast Vending",
    "wof:placetype":"venue"
},
  "geometry": {"coordinates":[-84.639426,33.998548],"type":"Point"}
}