{
  "type": "Feature",
  "properties": {
    "iso:country":"US",
    "sg:address":"13697 US Hwy 17",
    "sg:city":"Woodbine",
    "sg:classifiers":[
        {
            "category":"Wholesale",
            "subcategory":"Construction Materials",
            "type":"Manufacturing & Wholesale Goods"
        }
    ],
    "sg:phone":"+1 912 882 4941",
    "sg:postcode":"31569",
    "sg:province":"GA",
    "sg:tags":[
        "sand",
        "gravel"
    ],
    "wof:name":"Quick Sand Co",
    "wof:placetype":"venue"
},
  "geometry": {"coordinates":[-81.71866900000001,30.943032],"type":"Point"}
}