{
  "type": "Feature",
  "properties": {
    "iso:country":"US",
    "sg:address":"334 S Hamilton St",
    "sg:city":"Dalton",
    "sg:classifiers":[
        {
            "category":"Shopping",
            "subcategory":"Hobbies, Toys, & Games",
            "type":"Retail Goods"
        }
    ],
    "sg:phone":"+1 706 275 6142",
    "sg:postcode":"30720",
    "sg:province":"GA",
    "wof:name":"Dannys",
    "wof:placetype":"venue"
},
  "geometry": {"coordinates":[-84.96796000000001,34.76943],"type":"Point"}
}