{
  "type": "Feature",
  "properties": {
    "addr:full":"1696 Alderbrook Rd NE Atlanta GA 30345",
    "addr:housenumber":"1696",
    "addr:postcode":"30345",
    "addr:street":"Alderbrook Rd Ne",
    "iso:country":"US",
    "sg:address":"1696 Alderbrook Rd NE",
    "sg:city":"Atlanta",
    "sg:classifiers":[
        {
            "category":"Sports & Exercise",
            "subcategory":"Gym",
            "type":"Entertainment"
        }
    ],
    "sg:phone":"+1 770 458 6693",
    "sg:postcode":"30345",
    "sg:province":"GA",
    "sg:tags":[
        "fitness",
        "physical",
        "facility"
    ],
    "wof:name":"Holiday Spa",
    "wof:placetype":"venue"
},
  "geometry": {"coordinates":[-84.298894,33.827016],"type":"Point"}
}