{
  "type": "Feature",
  "properties": {
    "iso:country":"US",
    "sg:address":"85 Bellamy Pl",
    "sg:city":"Stockbridge",
    "sg:classifiers":[
        {
            "category":"Recreation",
            "subcategory":"Amusement Park",
            "type":"Entertainment"
        }
    ],
    "sg:phone":"+1 770 389 0809",
    "sg:postcode":"30281",
    "sg:province":"GA",
    "wof:name":"Old South Amusements",
    "wof:placetype":"venue"
},
  "geometry": {"coordinates":[-84.20287399999999,33.537912],"type":"Point"}
}