{
  "type": "Feature",
  "properties": {
    "addr:full":"2468 Brow Rd Trenton GA 30752",
    "addr:housenumber":"2468",
    "addr:postcode":"30752",
    "addr:street":"Brow Rd",
    "iso:country":"US",
    "sg:address":"2468 Brow Rd",
    "sg:city":"Trenton",
    "sg:classifiers":[
        {
            "category":"Organizations",
            "subcategory":"Religious Organization",
            "type":"Services"
        }
    ],
    "sg:phone":"+1 706 657 7287",
    "sg:postcode":"30752",
    "sg:province":"GA",
    "sg:tags":[
        "church"
    ],
    "wof:name":"Cornerstone Baptist Church",
    "wof:placetype":"venue"
},
  "geometry": {"coordinates":[-85.51559899999999,34.903406],"type":"Point"}
}