{
  "type": "Feature",
  "properties": {
    "addr:full":"3700 Browns Bridge Rd Gainesville GA 30504",
    "addr:housenumber":"3700",
    "addr:postcode":"30504",
    "addr:street":"Browns Bridge Rd",
    "iso:country":"US",
    "sg:address":"3700 Browns Bridge Rd",
    "sg:city":"Gainesville",
    "sg:classifiers":[
        {
            "category":"Autos & Motor Vehicles",
            "subcategory":"Automobile Sales",
            "type":"Retail Goods"
        }
    ],
    "sg:phone":"+1 770 503 0089",
    "sg:postcode":"30504",
    "sg:province":"GA",
    "sg:tags":[
        "car",
        "used"
    ],
    "wof:name":"Alfredo Motors Inc.",
    "wof:placetype":"venue"
},
  "geometry": {"coordinates":[-83.90728,34.274811],"type":"Point"}
}