{
  "type": "Feature",
  "properties": {
    "addr:full":"4025 Welcome All Rd Atlanta GA 30349",
    "addr:housenumber":"4025",
    "addr:postcode":"30349",
    "addr:street":"Welcome All Rd",
    "iso:country":"US",
    "sg:address":"4025 Welcome All Rd",
    "sg:city":"Atlanta",
    "sg:classifiers":[
        {
            "category":"Wholesale",
            "subcategory":"Machinery & Supplies",
            "type":"Manufacturing & Wholesale Goods"
        }
    ],
    "sg:phone":"+1 404 629 9117",
    "sg:postcode":"30349",
    "sg:province":"GA",
    "sg:tags":[
        "abrasive"
    ],
    "wof:name":"Abmast Abrasives Corp",
    "wof:placetype":"venue"
},
  "geometry": {"coordinates":[-84.522042,33.644153],"type":"Point"}
}