{
  "type": "Feature",
  "properties": {
    "iso:country":"US",
    "sg:address":"600 Lincoln Cir",
    "sg:city":"Washington",
    "sg:classifiers":[
        {
            "category":"Education",
            "subcategory":"Vocational School",
            "type":"Public Place"
        }
    ],
    "sg:phone":"+1 706 678 1073",
    "sg:postcode":"30673",
    "sg:province":"GA",
    "sg:tags":[
        "technical",
        "trade"
    ],
    "wof:name":"DOAS Athens Area Tech",
    "wof:placetype":"venue"
},
  "geometry": {"coordinates":[-82.769711,33.738066],"type":"Point"}
}