{
  "type": "Feature",
  "properties": {
    "iso:country":"US",
    "sg:address":"303 Peachtree Center Ave NE",
    "sg:city":"Atlanta",
    "sg:classifiers":[
        {
            "category":"Professional",
            "subcategory":"Business Services",
            "type":"Services"
        }
    ],
    "sg:phone":"+1 404 813 7636",
    "sg:postcode":"30303",
    "sg:province":"GA",
    "sg:tags":[
        "organizing",
        "services-household"
    ],
    "wof:name":"Silvant Cap Mgmt",
    "wof:placetype":"venue"
},
  "geometry": {"coordinates":[-84.386038,33.76221],"type":"Point"}
}