{
  "type": "Feature",
  "properties": {
    "iso:country":"US",
    "sg:address":"3309 Waters Ave",
    "sg:city":"Savannah",
    "sg:classifiers":[
        {
            "category":"Personal",
            "subcategory":"Beauty Salon",
            "type":"Services"
        }
    ],
    "sg:phone":"+1 912 354 7533",
    "sg:postcode":"31404",
    "sg:province":"GA",
    "sg:tags":[
        "shop"
    ],
    "wof:name":"Du Charme Beauty Salon",
    "wof:placetype":"venue"
},
  "geometry": {"coordinates":[-81.087172,32.042878],"type":"Point"}
}