{
  "type": "Feature",
  "properties": {
    "iso:country":"US",
    "sg:address":"502 N Jackson St",
    "sg:city":"Albany",
    "sg:classifiers":[
        {
            "category":"Freight",
            "type":"Transportation"
        }
    ],
    "sg:phone":"+1 229 639 1290",
    "sg:postcode":"31701",
    "sg:province":"GA",
    "sg:tags":[
        "sea",
        "foreign"
    ],
    "wof:name":"New Hope Exports LLC",
    "wof:placetype":"venue"
},
  "geometry": {"coordinates":[-84.153662,31.584572],"type":"Point"}
}