{
  "type": "Feature",
  "properties": {
    "addr:full":"101 Hill St Summerville GA 30747",
    "addr:housenumber":"101",
    "addr:postcode":"30747",
    "addr:street":"Hill St",
    "iso:country":"US",
    "sg:address":"101 Hill St",
    "sg:city":"Summerville",
    "sg:classifiers":[
        {
            "category":"Social Services",
            "subcategory":"Adult Care",
            "type":"Services"
        }
    ],
    "sg:phone":"+1 706 857 4515",
    "sg:postcode":"30747",
    "sg:province":"GA",
    "sg:tags":[
        "home"
    ],
    "wof:name":"Golden Age Place",
    "wof:placetype":"venue"
},
  "geometry": {"coordinates":[-85.353618,34.478163],"type":"Point"}
}