{
  "type": "Feature",
  "properties": {
    "addr:full":"2034 Clipper Straits Snellville GA 30078",
    "addr:housenumber":"2034",
    "addr:postcode":"30078",
    "addr:street":"Clipper Straits",
    "iso:country":"US",
    "sg:address":"2034 Clipper Straits",
    "sg:city":"Snellville",
    "sg:classifiers":[
        {
            "category":"Real Estate",
            "subcategory":"Real Estate Operator",
            "type":"Services"
        }
    ],
    "sg:phone":"+1 770 985 8085",
    "sg:postcode":"30078",
    "sg:province":"GA",
    "sg:tags":[
        "property",
        "management",
        "lessor"
    ],
    "wof:name":"Gma Lighting",
    "wof:placetype":"venue"
},
  "geometry": {"coordinates":[-84.021112,33.86789],"type":"Point"}
}