{
  "type": "Feature",
  "properties": {
    "addr:full":"3213 Ivy Chase Way Atlanta GA 30342",
    "addr:housenumber":"3213",
    "addr:postcode":"30342",
    "addr:street":"Ivy Chase Way",
    "iso:country":"US",
    "sg:address":"3213 Ivy Chase Way",
    "sg:city":"Atlanta",
    "sg:classifiers":[
        {
            "category":"Professional",
            "subcategory":"Lawyer & Legal Services",
            "type":"Services"
        }
    ],
    "sg:phone":"+1 404 610 5032",
    "sg:postcode":"30342",
    "sg:province":"GA",
    "sg:tags":[
        "notary"
    ],
    "wof:name":"Mobile Notary",
    "wof:placetype":"venue"
},
  "geometry": {"coordinates":[-84.373966,33.851011],"type":"Point"}
}