{
  "type": "Feature",
  "properties": {
    "addr:full":"5439 Center Hill Church Rd Loganville GA 30052",
    "addr:housenumber":"5439",
    "addr:postcode":"30052",
    "addr:street":"Center Hill Church Rd",
    "iso:country":"US",
    "sg:address":"5439 Center Hill Church Rd",
    "sg:city":"Loganville",
    "sg:classifiers":[
        {
            "category":"Building & Trades",
            "subcategory":"Construction",
            "type":"Services"
        }
    ],
    "sg:phone":"+1 770 466 8786",
    "sg:postcode":"30052",
    "sg:province":"GA",
    "sg:tags":[
        "house"
    ],
    "wof:name":"R P D Construction Inc",
    "wof:placetype":"venue"
},
  "geometry": {"coordinates":[-83.89917199999999,33.765203],"type":"Point"}
}