{
  "type": "Feature",
  "properties": {
    "addr:full":"121 N Chilton Cres La Grange GA 30240",
    "addr:housenumber":"121",
    "addr:postcode":"30240",
    "addr:street":"N Chilton Cres",
    "iso:country":"US",
    "sg:address":"121 N Chilton Cres",
    "sg:city":"La Grange",
    "sg:classifiers":[
        {
            "category":"Personal",
            "subcategory":"Beauty Salon",
            "type":"Services"
        }
    ],
    "sg:phone":"+1 706 882 3287",
    "sg:postcode":"30240",
    "sg:province":"GA",
    "sg:tags":[
        "shop"
    ],
    "wof:name":"Cosmetique Beauty Shop",
    "wof:placetype":"venue"
},
  "geometry": {"coordinates":[-85.038369,33.063504],"type":"Point"}
}