{
  "type": "Feature",
  "properties": {
    "iso:country":"US",
    "sg:address":"806 Thomas St",
    "sg:city":"Nashville",
    "sg:classifiers":[
        {
            "category":"Building & Trades",
            "subcategory":"Construction",
            "type":"Services"
        }
    ],
    "sg:phone":"+1 229 686 3432",
    "sg:postcode":"31639",
    "sg:province":"GA",
    "sg:tags":[
        "house"
    ],
    "wof:name":"Four Seasons",
    "wof:placetype":"venue"
},
  "geometry": {"coordinates":[-83.237478,31.217532],"type":"Point"}
}