{
  "type": "Feature",
  "properties": {
    "addr:full":"807 Chickamauga Ave Rossville GA 30741",
    "addr:housenumber":"807",
    "addr:postcode":"30741",
    "addr:street":"Chickamauga Ave",
    "iso:country":"US",
    "sg:address":"807 Chickamauga Ave",
    "sg:city":"Rossville",
    "sg:classifiers":[
        {
            "category":"Building & Trades",
            "subcategory":"Construction",
            "type":"Services"
        }
    ],
    "sg:phone":"+1 706 861 2906",
    "sg:postcode":"30741",
    "sg:province":"GA",
    "sg:tags":[
        "downspouts",
        "gutter",
        "contractor"
    ],
    "wof:name":"Abacon Gutters Inc",
    "wof:placetype":"venue"
},
  "geometry": {"coordinates":[-85.277565,34.979465],"type":"Point"}
}