{
  "type": "Feature",
  "properties": {
    "addr:full":"2300 Windy Ridge Parkway SE Suite 60 Atlanta GA 30339",
    "addr:housenumber":"2300;60",
    "addr:postcode":"30339",
    "addr:street":"Windy Ridge Parkway Se Suite",
    "iso:country":"US",
    "sg:address":"2300 Windy Ridge Parkway SE Suite 60",
    "sg:city":"Atlanta",
    "sg:classifiers":[
        {
            "category":"Shopping",
            "subcategory":"Stationery & Office Supplies",
            "type":"Retail Goods"
        }
    ],
    "sg:phone":"+1 770 951 1994",
    "sg:postcode":"30339",
    "sg:province":"GA",
    "sg:tags":[
        "equipment"
    ],
    "sg:website":"www.officedepot.com",
    "wof:name":"Office Depot",
    "wof:placetype":"venue"
},
  "geometry": {"coordinates":[-84.46145799999999,33.906198],"type":"Point"}
}