{
  "type": "Feature",
  "properties": {
    "iso:country":"US",
    "sg:address":"523 E Gwinnett St",
    "sg:city":"Savannah",
    "sg:classifiers":[
        {
            "category":"Travel",
            "subcategory":"Hotels & Motels",
            "type":"Entertainment"
        }
    ],
    "sg:phone":"+1 912 239 9950",
    "sg:postcode":"31401",
    "sg:province":"GA",
    "wof:name":"Ampersand Inn",
    "wof:placetype":"venue"
},
  "geometry": {"coordinates":[-81.08950299999999,32.065395],"type":"Point"}
}