{
  "type": "Feature",
  "properties": {
    "addr:full":"4781 Covington Hwy Decatur GA 30035",
    "addr:housenumber":"4781",
    "addr:postcode":"30035",
    "addr:street":"Covington Hwy",
    "iso:country":"US",
    "sg:address":"4781 Covington Hwy",
    "sg:city":"Decatur",
    "sg:classifiers":[
        {
            "category":"Retail",
            "subcategory":"Laundry & Dry Cleaning",
            "type":"Services"
        }
    ],
    "sg:phone":"+1 404 284 7374",
    "sg:postcode":"30035",
    "sg:province":"GA",
    "sg:tags":[
        "cleaners"
    ],
    "wof:name":"Whistle Cleaners",
    "wof:placetype":"venue"
},
  "geometry": {"coordinates":[-84.21775700000001,33.738672],"type":"Point"}
}