{
  "type": "Feature",
  "properties": {
    "iso:country":"US",
    "sg:address":"305 Stephenson St",
    "sg:city":"Waycross",
    "sg:classifiers":[
        {
            "category":"Shopping",
            "type":"Retail Goods"
        }
    ],
    "sg:phone":"+1 912 285 0800",
    "sg:postcode":"31501",
    "sg:province":"GA",
    "sg:tags":[
        "merchandise"
    ],
    "wof:name":"Frames By Mary Ann",
    "wof:placetype":"venue"
},
  "geometry": {"coordinates":[-82.358509,31.208978],"type":"Point"}
}