{
  "type": "Feature",
  "properties": {
    "addr:full":"2077 Cliffton Ter Snellville GA 30039",
    "addr:housenumber":"2077",
    "addr:postcode":"30039",
    "addr:street":"Cliffton Ter",
    "iso:country":"US",
    "sg:address":"2077 Cliffton Ter",
    "sg:city":"Snellville",
    "sg:classifiers":[
        {
            "category":"Professional",
            "subcategory":"Business Services",
            "type":"Services"
        }
    ],
    "sg:phone":"+1 678 344 9023",
    "sg:postcode":"30039",
    "sg:province":"GA",
    "wof:name":"Sheela Design",
    "wof:placetype":"venue"
},
  "geometry": {"coordinates":[-84.073122,33.841742],"type":"Point"}
}