{
  "type": "Feature",
  "properties": {
    "addr:full":"1802 Hull Ave Rome GA 30161",
    "addr:housenumber":"1802",
    "addr:postcode":"ga 30161",
    "addr:street":"Hull Ave",
    "iso:country":"US",
    "sg:address":"1802 Hull Ave",
    "sg:city":"Rome",
    "sg:classifiers":[
        {
            "category":"Freight",
            "type":"Transportation"
        }
    ],
    "sg:phone":"+1 706 234 7548",
    "sg:postcode":"30161",
    "sg:province":"GA",
    "sg:tags":[
        "operator",
        "local",
        "trucking"
    ],
    "wof:name":"Gresham Trucking",
    "wof:placetype":"venue"
},
  "geometry": {"coordinates":[-85.171628,34.229703],"type":"Point"}
}