{
  "type": "Feature",
  "properties": {
    "iso:country":"US",
    "sg:address":"20 Old Ivy Sq NE",
    "sg:city":"Atlanta",
    "sg:classifiers":[
        {
            "category":"Health Services",
            "subcategory":"Doctor",
            "type":"Services"
        },
        {
            "category":"Health Services",
            "subcategory":"Hospital",
            "type":"Services"
        }
    ],
    "sg:phone":"+1 678 472 0556",
    "sg:postcode":"30342",
    "sg:province":"GA",
    "sg:tags":[
        "nursing",
        "consultant",
        "medical",
        "practice",
        "home"
    ],
    "wof:name":"Post Acute Advisors",
    "wof:placetype":"venue"
},
  "geometry": {"coordinates":[-84.381894,33.854462],"type":"Point"}
}