{
  "type": "Feature",
  "properties": {
    "addr:full":"30 Wings Rd Savannah GA 31408",
    "addr:housenumber":"30",
    "addr:postcode":"31408",
    "addr:street":"Wings Rd",
    "iso:country":"US",
    "sg:address":"30 Wings Rd",
    "sg:city":"Savannah",
    "sg:classifiers":[
        {
            "category":"Professional",
            "type":"Services"
        }
    ],
    "sg:phone":"+1 912 964 5698",
    "sg:postcode":"31408",
    "sg:province":"GA",
    "sg:tags":[
        "establishment"
    ],
    "wof:name":"Jepson Hangar",
    "wof:placetype":"venue"
},
  "geometry": {"coordinates":[-81.19721699999999,32.114088],"type":"Point"}
}