{
  "type": "Feature",
  "properties": {
    "addr:full":"809 Camden Way Tifton GA 31794",
    "addr:housenumber":"809",
    "addr:postcode":"31794",
    "addr:street":"Camden Way",
    "iso:country":"US",
    "sg:address":"809 Camden Way",
    "sg:city":"Tifton",
    "sg:classifiers":[
        {
            "category":"Retail",
            "subcategory":"Car Wash",
            "type":"Services"
        }
    ],
    "sg:phone":"+1 229 382 0982",
    "sg:postcode":"31794",
    "sg:province":"GA",
    "sg:tags":[
        "polishing",
        "washing"
    ],
    "wof:name":"Splash N Dash Car Wash & Quick",
    "wof:placetype":"venue"
},
  "geometry": {"coordinates":[-83.526933,31.456053],"type":"Point"}
}