{
  "type": "Feature",
  "properties": {
    "iso:country":"US",
    "sg:address":"1015 Tumlin Street NW",
    "sg:city":"Atlanta",
    "sg:classifiers":[
        {
            "category":"Education",
            "subcategory":"University",
            "type":"Public Place"
        }
    ],
    "sg:phone":"+1 404 249 1500",
    "sg:postcode":"30318",
    "sg:province":"GA",
    "sg:tags":[
        "college"
    ],
    "wof:name":"Georgia Institute of Technology",
    "wof:placetype":"venue"
},
  "geometry": {"coordinates":[-84.400704,33.782205],"type":"Point"}
}