{
  "type": "Feature",
  "properties": {
    "iso:country":"US",
    "sg:address":"203 N Main St",
    "sg:city":"Cleveland",
    "sg:classifiers":[
        {
            "category":"Shopping",
            "subcategory":"Jewelry",
            "type":"Retail Goods"
        }
    ],
    "sg:phone":"+1 706 865 4436",
    "sg:postcode":"30528",
    "sg:province":"GA",
    "wof:name":"Jewels of Mine",
    "wof:placetype":"venue"
},
  "geometry": {"coordinates":[-83.764369,34.600678],"type":"Point"}
}