{
  "type": "Feature",
  "properties": {
    "iso:country":"US",
    "sg:address":"4755 Mercer University Dr",
    "sg:city":"Macon",
    "sg:classifiers":[
        {
            "category":"Building & Trades",
            "subcategory":"Construction",
            "type":"Services"
        }
    ],
    "sg:phone":"+1 478 471 9110",
    "sg:postcode":"31210",
    "sg:province":"GA",
    "sg:tags":[
        "commercial"
    ],
    "wof:name":"Renfroe Construction",
    "wof:placetype":"venue"
},
  "geometry": {"coordinates":[-83.72384599999999,32.83001],"type":"Point"}
}