{
  "type": "Feature",
  "properties": {
    "addr:full":"5810 Powell Dr Mableton GA 30126",
    "addr:housenumber":"5810",
    "addr:postcode":"30126",
    "addr:street":"Powell Dr",
    "iso:country":"US",
    "sg:address":"5810 Powell Dr",
    "sg:city":"Mableton",
    "sg:classifiers":[
        {
            "category":"Retail",
            "subcategory":"Repair Shop",
            "type":"Services"
        }
    ],
    "sg:phone":"+1 770 944 6535",
    "sg:postcode":"30126",
    "sg:province":"GA",
    "sg:tags":[
        "compressor"
    ],
    "wof:name":"W W Equipment & Svc",
    "wof:placetype":"venue"
},
  "geometry": {"coordinates":[-84.595338,33.813104],"type":"Point"}
}