{
  "type": "Feature",
  "properties": {
    "addr:full":"3002 Jessica Ave Decatur GA 30032",
    "addr:housenumber":"3002",
    "addr:postcode":"30032",
    "addr:street":"Jessica Ave",
    "iso:country":"US",
    "sg:address":"3002 Jessica Ave",
    "sg:city":"Decatur",
    "sg:classifiers":[
        {
            "category":"Professional",
            "subcategory":"Business Services",
            "type":"Services"
        }
    ],
    "sg:phone":"+1 404 578 3884",
    "sg:postcode":"30032",
    "sg:province":"GA",
    "sg:tags":[
        "clothing",
        "store"
    ],
    "wof:name":"Theodore Bullard",
    "wof:placetype":"venue"
},
  "geometry": {"coordinates":[-84.3103,33.735147],"type":"Point"}
}