{
  "type": "Feature",
  "properties": {
    "iso:country":"US",
    "sg:address":"1005 Union Hill Rd",
    "sg:city":"Alpharetta",
    "sg:classifiers":[
        {
            "category":"Shopping",
            "subcategory":"Stationery & Office Supplies",
            "type":"Retail Goods"
        }
    ],
    "sg:phone":"+1 770 569 5800",
    "sg:postcode":"30004",
    "sg:province":"GA",
    "sg:tags":[
        "furniture"
    ],
    "wof:name":"Sandy Springs Office Supplies",
    "wof:placetype":"venue"
},
  "geometry": {"coordinates":[-84.233383,34.12269],"type":"Point"}
}