{
  "type": "Feature",
  "properties": {
    "iso:country":"US",
    "sg:address":"1625 Lexington Rd",
    "sg:city":"Athens",
    "sg:classifiers":[
        {
            "category":"Manufacturing",
            "subcategory":"Signs",
            "type":"Manufacturing & Wholesale Goods"
        }
    ],
    "sg:phone":"+1 706 548 5389",
    "sg:postcode":"30605",
    "sg:province":"GA",
    "wof:name":"Ako Signs",
    "wof:placetype":"venue"
},
  "geometry": {"coordinates":[-83.35267899999999,33.946377],"type":"Point"}
}