{
  "type": "Feature",
  "properties": {
    "iso:country":"US",
    "sg:address":"395 Providence Oaks Cir",
    "sg:city":"Alpharetta",
    "sg:classifiers":[
        {
            "category":"Professional",
            "subcategory":"Research",
            "type":"Services"
        }
    ],
    "sg:phone":"+1 678 339 0440",
    "sg:postcode":"30004",
    "sg:province":"GA",
    "sg:tags":[
        "marketing"
    ],
    "wof:name":"Hilker RES & Consulting Inc",
    "wof:placetype":"venue"
},
  "geometry": {"coordinates":[-84.30079499999999,34.098669],"type":"Point"}
}