{
  "type": "Feature",
  "properties": {
    "addr:full":"3901 Knights Academy Rd Valdosta GA 31605",
    "addr:housenumber":"3901",
    "addr:postcode":"31605",
    "addr:street":"Knights Academy Rd",
    "iso:country":"US",
    "sg:address":"3901 Knights Academy Rd",
    "sg:city":"Valdosta",
    "sg:classifiers":[
        {
            "category":"Real Estate",
            "subcategory":"Real Estate Agent",
            "type":"Services"
        }
    ],
    "sg:phone":"+1 229 249 9448",
    "sg:postcode":"31605",
    "sg:province":"GA",
    "wof:name":"George Properties Inc",
    "wof:placetype":"venue"
},
  "geometry": {"coordinates":[-83.225328,30.906236],"type":"Point"}
}