{
  "type": "Feature",
  "properties": {
    "addr:full":"1932 Railroad St Statham GA 30680",
    "addr:housenumber":"1932",
    "addr:postcode":"30680",
    "addr:street":"Railroad St",
    "iso:country":"US",
    "sg:address":"1932 Railroad St",
    "sg:city":"Statham",
    "sg:classifiers":[
        {
            "category":"Home & Garden",
            "subcategory":"Furniture",
            "type":"Retail Goods"
        }
    ],
    "sg:phone":"+1 678 753 1776",
    "sg:postcode":"30680",
    "sg:province":"GA",
    "wof:name":"Homestyle",
    "wof:placetype":"venue"
},
  "geometry": {"coordinates":[-83.59927999999999,33.966727],"type":"Point"}
}