{
  "type": "Feature",
  "properties": {
    "addr:full":"621 Bellenden Dr Peachtree City GA 30269",
    "addr:housenumber":"621",
    "addr:postcode":"30269",
    "addr:street":"Bellenden Dr",
    "iso:country":"US",
    "sg:address":"621 Bellenden Dr",
    "sg:city":"Peachtree City",
    "sg:classifiers":[
        {
            "category":"Building & Trades",
            "subcategory":"Cleaning & Sanitation",
            "type":"Services"
        }
    ],
    "sg:phone":"+1 770 486 0211",
    "sg:postcode":"30269",
    "sg:province":"GA",
    "sg:tags":[
        "maintenance"
    ],
    "wof:name":"Ceiling Cleaning Co",
    "wof:placetype":"venue"
},
  "geometry": {"coordinates":[-84.5913,33.425764],"type":"Point"}
}