{
  "type": "Feature",
  "properties": {
    "iso:country":"US",
    "sg:address":"102 S Dandy St",
    "sg:city":"St Marys",
    "sg:classifiers":[
        {
            "category":"Personal",
            "subcategory":"Beauty Salon",
            "type":"Services"
        }
    ],
    "sg:phone":"+1 912 673 6339",
    "sg:postcode":"31558",
    "sg:province":"GA",
    "wof:name":"Hair Designs & Co",
    "wof:placetype":"venue"
},
  "geometry": {"coordinates":[-81.561353,30.745915],"type":"Point"}
}