{
  "type": "Feature",
  "properties": {
    "addr:full":"2454 Jett Ferry Road Atlanta GA 30338",
    "addr:housenumber":"2454",
    "addr:postcode":"30338",
    "addr:street":"Jett Ferry Road",
    "iso:country":"US",
    "sg:address":"2454 Jett Ferry Road",
    "sg:city":"Atlanta",
    "sg:classifiers":[
        {
            "category":"Banks & Credit Unions",
            "subcategory":"Bank",
            "type":"Services"
        },
        {
            "category":"Banks & Credit Unions",
            "subcategory":"Financial Services",
            "type":"Services"
        }
    ],
    "sg:phone":"+1 770 392 2971",
    "sg:postcode":"30338",
    "sg:province":"GA",
    "sg:tags":[
        "saving",
        "mortgage",
        "loan",
        "commercial",
        "broker",
        "banking",
        "internet"
    ],
    "sg:website":"www.bankofamerica.com",
    "wof:name":"Bank of America",
    "wof:placetype":"venue"
},
  "geometry": {"coordinates":[-84.302404,33.958423],"type":"Point"}
}