{
  "type": "Feature",
  "properties": {
    "addr:full":"697 Lower Bethany Rd Canton GA 30114",
    "addr:housenumber":"697",
    "addr:postcode":"30114",
    "addr:street":"Lower Bethany Rd",
    "iso:country":"US",
    "sg:address":"697 Lower Bethany Rd",
    "sg:city":"Canton",
    "sg:classifiers":[
        {
            "category":"Retail",
            "subcategory":"Repair Shop",
            "type":"Services"
        }
    ],
    "sg:phone":"+1 770 479 9132",
    "sg:postcode":"30114",
    "sg:province":"GA",
    "sg:tags":[
        "welding"
    ],
    "wof:name":"Any Kind Anytime Welding",
    "wof:placetype":"venue"
},
  "geometry": {"coordinates":[-84.436628,34.292227],"type":"Point"}
}