{
  "type": "Feature",
  "properties": {
    "iso:country":"US",
    "sg:address":"857 Fairwood Pointe",
    "sg:city":"Acworth",
    "sg:classifiers":[
        {
            "category":"Professional",
            "subcategory":"Business Services",
            "type":"Services"
        }
    ],
    "sg:phone":"+1 770 423 1408",
    "sg:postcode":"30101",
    "sg:province":"GA",
    "wof:name":"Slz Enterprise Inc",
    "wof:placetype":"venue"
},
  "geometry": {"coordinates":[-84.72286800000001,33.9754],"type":"Point"}
}