{
  "type": "Feature",
  "properties": {
    "addr:full":"140 Marble Mill Rd NW Ste B Marietta GA 30060",
    "addr:housenumber":"140",
    "addr:postcode":"30060",
    "addr:street":"Marble Mill Rd Nw Ste B",
    "iso:country":"US",
    "sg:address":"140 Marble Mill Rd NW Ste B",
    "sg:city":"Marietta",
    "sg:classifiers":[
        {
            "category":"Health Services",
            "subcategory":"Dentist",
            "type":"Services"
        }
    ],
    "sg:phone":"+1 770 590 9854",
    "sg:postcode":"30060",
    "sg:province":"GA",
    "wof:name":"Complete Family Dentistry",
    "wof:placetype":"venue"
},
  "geometry": {"coordinates":[-84.55470699999999,33.975597],"type":"Point"}
}