{
  "type": "Feature",
  "properties": {
    "addr:full":"5648 Old Dixie Hwy Forest Park GA 30297",
    "addr:housenumber":"5648",
    "addr:postcode":"30297",
    "addr:street":"Old Dixie Hwy",
    "iso:country":"US",
    "sg:address":"5648 Old Dixie Hwy",
    "sg:city":"Forest Park",
    "sg:classifiers":[
        {
            "category":"Retail",
            "subcategory":"Auto Repair",
            "type":"Services"
        }
    ],
    "sg:phone":"+1 404 363 3360",
    "sg:postcode":"30297",
    "sg:province":"GA",
    "wof:name":"Dj's Auto Service",
    "wof:placetype":"venue"
},
  "geometry": {"coordinates":[-84.37930299999999,33.6007],"type":"Point"}
}