{
  "type": "Feature",
  "properties": {
    "iso:country":"US",
    "sg:address":"7135 Bemiss Rd",
    "sg:city":"Ray City",
    "sg:classifiers":[
        {
            "category":"Retail",
            "subcategory":"Auto Repair",
            "type":"Services"
        }
    ],
    "sg:phone":"+1 229 242 9694",
    "sg:postcode":"31645",
    "sg:province":"GA",
    "sg:tags":[
        "automotive"
    ],
    "wof:name":"Kelly Automotive",
    "wof:placetype":"venue"
},
  "geometry": {"coordinates":[-83.19801,31.022336],"type":"Point"}
}