{
  "type": "Feature",
  "properties": {
    "iso:country":"US",
    "sg:address":"3925 Pleasant Hill Rd",
    "sg:city":"Duluth",
    "sg:classifiers":[
        {
            "category":"Restaurant",
            "type":"Food & Drink"
        }
    ],
    "sg:phone":"+1 770 622 1445",
    "sg:postcode":"30044",
    "sg:province":"GA",
    "wof:name":"Bamboo Garden",
    "wof:placetype":"venue"
},
  "geometry": {"coordinates":[-84.161973,33.997555],"type":"Point"}
}