{
  "type": "Feature",
  "properties": {
    "addr:full":"684 W Church St Jasper GA 30143",
    "addr:housenumber":"684",
    "addr:postcode":"30143",
    "addr:street":"W Church St",
    "iso:country":"US",
    "sg:address":"684 W Church St",
    "sg:city":"Jasper",
    "sg:classifiers":[
        {
            "category":"Restaurant",
            "type":"Food & Drink"
        }
    ],
    "sg:menulink":"http://www.allmenus.com/ga/jasper/124604-quiznos-sub/menu/",
    "sg:phone":"+1 706 253 6373",
    "sg:postcode":"30143",
    "sg:province":"GA",
    "sg:tags":[
        "wrap",
        "american",
        "sandwich"
    ],
    "wof:name":"Quiznos Sub",
    "wof:placetype":"venue"
},
  "geometry": {"coordinates":[-84.436635,34.465955],"type":"Point"}
}