{
  "type": "Feature",
  "properties": {
    "addr:full":"131 Duane Dr Fitzgerald GA 31750",
    "addr:housenumber":"131",
    "addr:postcode":"31750",
    "addr:street":"Duane Dr",
    "iso:country":"US",
    "sg:address":"131 Duane Dr",
    "sg:city":"Fitzgerald",
    "sg:classifiers":[
        {
            "category":"Social Services",
            "subcategory":"Child Care",
            "type":"Services"
        }
    ],
    "sg:phone":"+1 229 423 9295",
    "sg:postcode":"31750",
    "sg:province":"GA",
    "sg:tags":[
        "day"
    ],
    "wof:name":"Sylvias Wee Day Care",
    "wof:placetype":"venue"
},
  "geometry": {"coordinates":[-83.277497,31.71832],"type":"Point"}
}