{
  "type": "Feature",
  "properties": {
    "addr:full":"4826 Bland Dairy Dr Valdosta GA 31601",
    "addr:housenumber":"4826",
    "addr:postcode":"31601",
    "addr:street":"Bland Dairy Dr",
    "iso:country":"US",
    "sg:address":"4826 Bland Dairy Dr",
    "sg:city":"Valdosta",
    "sg:classifiers":[
        {
            "category":"Freight",
            "type":"Transportation"
        }
    ],
    "sg:phone":"+1 229 244 0087",
    "sg:postcode":"31601",
    "sg:province":"GA",
    "sg:tags":[
        "operator",
        "local",
        "trucking"
    ],
    "wof:name":"Hires Trucking Co",
    "wof:placetype":"venue"
},
  "geometry": {"coordinates":[-83.343053,30.723837],"type":"Point"}
}