{
  "type": "Feature",
  "properties": {
    "addr:full":"2020 7th Ave Columbus GA 31904",
    "addr:housenumber":"2020",
    "addr:postcode":"31904",
    "addr:street":"7Th Ave",
    "iso:country":"US",
    "sg:address":"2020 7th Ave",
    "sg:city":"Columbus",
    "sg:classifiers":[
        {
            "category":"Health Services",
            "subcategory":"Chiropractor",
            "type":"Services"
        }
    ],
    "sg:phone":"+1 706 323 1873",
    "sg:postcode":"31904",
    "sg:province":"GA",
    "wof:name":"Mosley Clinic of Chiropractic",
    "wof:placetype":"venue"
},
  "geometry": {"coordinates":[-84.98333700000001,32.483817],"type":"Point"}
}