{
  "type": "Feature",
  "properties": {
    "iso:country":"US",
    "sg:address":"12335 Arnold Mill Rd",
    "sg:city":"Alpharetta",
    "sg:classifiers":[
        {
            "category":"Autos & Motor Vehicles",
            "subcategory":"Fuel & Gas Station",
            "type":"Retail Goods"
        }
    ],
    "sg:phone":"+1 770 740 8113",
    "sg:postcode":"30004",
    "sg:province":"GA",
    "wof:name":"Bp Oil Company",
    "wof:placetype":"venue"
},
  "geometry": {"coordinates":[-84.358299,34.083599],"type":"Point"}
}