{
  "type": "Feature",
  "properties": {
    "iso:country":"US",
    "sg:address":"994 Alpharetta Hwy",
    "sg:city":"Roswell",
    "sg:classifiers":[
        {
            "category":"Retail",
            "subcategory":"Auto Repair",
            "type":"Services"
        }
    ],
    "sg:phone":"+1 770 993 1059",
    "sg:postcode":"30075",
    "sg:province":"GA",
    "sg:tags":[
        "general"
    ],
    "wof:name":"Marcuss Repair Service",
    "wof:placetype":"venue"
},
  "geometry": {"coordinates":[-84.360084,34.02563],"type":"Point"}
}