{
  "type": "Feature",
  "properties": {
    "addr:full":"1050 E Piedmont Rd Marietta GA 30062",
    "addr:housenumber":"1050",
    "addr:postcode":"30062",
    "addr:street":"E Piedmont Rd",
    "iso:country":"US",
    "sg:address":"1050 E Piedmont Rd",
    "sg:city":"Marietta",
    "sg:classifiers":[
        {
            "category":"Communications",
            "type":"Services"
        },
        {
            "category":"Professional",
            "subcategory":"Computer Services",
            "type":"Services"
        }
    ],
    "sg:phone":"+1 678 223 3394",
    "sg:postcode":"30062",
    "sg:province":"GA",
    "sg:tags":[
        "repair",
        "design",
        "web"
    ],
    "sg:website":"www.TheNetworkFolks.com",
    "wof:name":"The Network Folks",
    "wof:placetype":"venue"
},
  "geometry": {"coordinates":[-84.479676,33.976739],"type":"Point"}
}