{
  "type": "Feature",
  "properties": {
    "iso:country":"US",
    "sg:address":"5068 Tarry Glen Dr",
    "sg:city":"Suwanee",
    "sg:classifiers":[
        {
            "category":"Organizations",
            "subcategory":"Religious Organization",
            "type":"Services"
        }
    ],
    "sg:phone":"+1 770 904 4276",
    "sg:postcode":"30024",
    "sg:province":"GA",
    "sg:tags":[
        "clergy"
    ],
    "wof:name":"Dallape/Kyle",
    "wof:placetype":"venue"
},
  "geometry": {"coordinates":[-84.105408,34.070179],"type":"Point"}
}