{
  "type": "Feature",
  "properties": {
    "addr:full":"802 Anne St Griffin GA 30224",
    "addr:housenumber":"802",
    "addr:postcode":"30224",
    "addr:street":"Anne St",
    "iso:country":"US",
    "sg:address":"802 Anne St",
    "sg:city":"Griffin",
    "sg:classifiers":[
        {
            "category":"Education",
            "subcategory":"School",
            "type":"Public Place"
        }
    ],
    "sg:phone":"+1 770 229 3746",
    "sg:postcode":"30224",
    "sg:province":"GA",
    "sg:tags":[
        "elementary"
    ],
    "wof:name":"Anne Street Elementary",
    "wof:placetype":"venue"
},
  "geometry": {"coordinates":[-84.277884,33.238689],"type":"Point"}
}