{
  "type": "Feature",
  "properties": {
    "addr:full":"96 Bryan Woods Rd Savannah GA 31410",
    "addr:housenumber":"96",
    "addr:postcode":"31410",
    "addr:street":"Bryan Woods Rd",
    "iso:country":"US",
    "sg:address":"96 Bryan Woods Rd",
    "sg:city":"Savannah",
    "sg:classifiers":[
        {
            "category":"Building & Trades",
            "subcategory":"Construction",
            "type":"Services"
        }
    ],
    "sg:phone":"+1 912 897 3150",
    "sg:postcode":"31410",
    "sg:province":"GA",
    "sg:tags":[
        "paving",
        "contractor"
    ],
    "wof:name":"APAC Georgia Inc",
    "wof:placetype":"venue"
},
  "geometry": {"coordinates":[-80.989637,32.038745],"type":"Point"}
}