{
  "type": "Feature",
  "properties": {
    "iso:country":"US",
    "sg:address":"204 Stuart St",
    "sg:city":"Savannah",
    "sg:classifiers":[
        {
            "category":"Professional",
            "subcategory":"Management & Consulting",
            "type":"Services"
        }
    ],
    "sg:phone":"+1 912 236 4711",
    "sg:postcode":"31405",
    "sg:province":"GA",
    "sg:tags":[
        "business"
    ],
    "wof:name":"Environmental Services Inc",
    "wof:placetype":"venue"
},
  "geometry": {"coordinates":[-81.104608,32.016938],"type":"Point"}
}