{
  "type": "Feature",
  "properties": {
    "iso:country":"US",
    "sg:address":"120 Airport Park Dr",
    "sg:city":"Savannah",
    "sg:classifiers":[
        {
            "category":"Home & Garden",
            "subcategory":"Home Furnishings",
            "type":"Retail Goods"
        },
        {
            "category":"Home & Garden",
            "subcategory":"Building Materials",
            "type":"Retail Goods"
        },
        {
            "category":"Manufacturing",
            "subcategory":"Glass & Minerals",
            "type":"Manufacturing & Wholesale Goods"
        },
        {
            "category":"Manufacturing",
            "subcategory":"Building Materials",
            "type":"Manufacturing & Wholesale Goods"
        }
    ],
    "sg:phone":"+1 912 964 4464",
    "sg:postcode":"31408",
    "sg:province":"GA",
    "sg:tags":[
        "plate",
        "door",
        "doors-glass",
        "glass-auto",
        "accessory",
        "shower",
        "window",
        "doors",
        "mirror",
        "frames",
        "enclosure"
    ],
    "wof:name":"J & L Glass Inc",
    "wof:placetype":"venue"
},
  "geometry": {"coordinates":[-81.195376,32.075538],"type":"Point"}
}