{
  "type": "Feature",
  "properties": {
    "addr:full":"6861 Main St Lithonia GA 30058",
    "addr:housenumber":"6861",
    "addr:postcode":"30058",
    "addr:street":"Main St",
    "iso:country":"US",
    "sg:address":"6861 Main St",
    "sg:city":"Lithonia",
    "sg:classifiers":[
        {
            "category":"Retail",
            "subcategory":"Funeral Services",
            "type":"Services"
        }
    ],
    "sg:phone":"+1 770 482 2358",
    "sg:postcode":"30058",
    "sg:province":"GA",
    "sg:tags":[
        "director"
    ],
    "wof:name":"Tri-Cities Funeral Home Inc",
    "wof:placetype":"venue"
},
  "geometry": {"coordinates":[-84.109572,33.709542],"type":"Point"}
}