{
  "type": "Feature",
  "properties": {
    "addr:full":"115 Holloman Rd Gray GA 31032",
    "addr:housenumber":"115",
    "addr:postcode":"31032",
    "addr:street":"Holloman Rd",
    "iso:country":"US",
    "sg:address":"115 Holloman Rd",
    "sg:city":"Gray",
    "sg:classifiers":[
        {
            "category":"Organizations",
            "subcategory":"Religious Organization",
            "type":"Services"
        }
    ],
    "sg:phone":"+1 478 986 0365",
    "sg:postcode":"31032",
    "sg:province":"GA",
    "wof:name":"Salem AME Church",
    "wof:placetype":"venue"
},
  "geometry": {"coordinates":[-83.67931900000001,32.98439],"type":"Point"}
}