{
  "type": "Feature",
  "properties": {
    "addr:full":"1000 Powers Pl Alpharetta GA 30009",
    "addr:housenumber":"1000",
    "addr:postcode":"30009",
    "addr:street":"Powers Pl",
    "iso:country":"US",
    "sg:address":"1000 Powers Pl",
    "sg:city":"Alpharetta",
    "sg:classifiers":[
        {
            "category":"Personal",
            "subcategory":"Massage",
            "type":"Services"
        }
    ],
    "sg:phone":"+1 770 740 1344",
    "sg:postcode":"30009",
    "sg:province":"GA",
    "wof:name":"Healing Touch Day Spa",
    "wof:placetype":"venue"
},
  "geometry": {"coordinates":[-84.29459,34.079793],"type":"Point"}
}