{
  "type": "Feature",
  "properties": {
    "iso:country":"US",
    "sg:address":"787 Hospital Dr",
    "sg:city":"Gainesville",
    "sg:phone":"+1 770 536 3759",
    "sg:postcode":"30501",
    "sg:province":"GA",
    "wof:name":"Top of Gainesville Inc",
    "wof:placetype":"venue"
},
  "geometry": {"coordinates":[-83.838486,34.278977],"type":"Point"}
}