{
  "type": "Feature",
  "properties": {
    "addr:full":"1298 S Perimeter Hwy Atlanta GA 30349",
    "addr:housenumber":"1298",
    "addr:postcode":"30349",
    "addr:street":"S Perimeter Hwy",
    "iso:country":"US",
    "sg:address":"1298 S Perimeter Hwy",
    "sg:city":"Atlanta",
    "sg:classifiers":[
        {
            "category":"Freight",
            "type":"Transportation"
        }
    ],
    "sg:phone":"+1 770 994 6672",
    "sg:postcode":"30349",
    "sg:province":"GA",
    "sg:tags":[
        "operator",
        "trucking"
    ],
    "wof:name":"Alternative Transport",
    "wof:placetype":"venue"
},
  "geometry": {"coordinates":[-84.432361,33.618688],"type":"Point"}
}