{
  "type": "Feature",
  "properties": {
    "addr:full":"101 Marietta St NW Atlanta GA 30303",
    "addr:housenumber":"101",
    "addr:postcode":"30303",
    "addr:street":"Marietta St Nw",
    "iso:country":"US",
    "sg:address":"101 Marietta St NW",
    "sg:city":"Atlanta",
    "sg:classifiers":[
        {
            "category":"Professional",
            "subcategory":"Lawyer & Legal Services",
            "type":"Services"
        }
    ],
    "sg:phone":"+1 404 688 8810",
    "sg:postcode":"30303",
    "sg:province":"GA",
    "sg:tags":[
        "litigation",
        "attorney",
        "tort"
    ],
    "wof:name":"Strickland , Melissa - Kessler, Schwarz",
    "wof:placetype":"venue"
},
  "geometry": {"coordinates":[-84.39209700000001,33.756451],"type":"Point"}
}