{
  "type": "Feature",
  "properties": {
    "addr:full":"6635 Willie Timmy St Harlem GA 30814",
    "addr:housenumber":"6635",
    "addr:postcode":"30814",
    "addr:street":"Willie Timmy St",
    "iso:country":"US",
    "sg:address":"6635 Willie Timmy St",
    "sg:city":"Harlem",
    "sg:classifiers":[
        {
            "category":"Personal",
            "subcategory":"Beauty Salon",
            "type":"Services"
        }
    ],
    "sg:phone":"+1 706 556 6272",
    "sg:postcode":"30814",
    "sg:province":"GA",
    "wof:name":"Marcelle's",
    "wof:placetype":"venue"
},
  "geometry": {"coordinates":[-82.328141,33.406527],"type":"Point"}
}