{
  "type": "Feature",
  "properties": {
    "iso:country":"US",
    "sg:address":"194 N Morningside Dr",
    "sg:city":"Cartersville",
    "sg:classifiers":[
        {
            "category":"Autos & Motor Vehicles",
            "subcategory":"Automobile Sales",
            "type":"Retail Goods"
        },
        {
            "category":"Retail",
            "subcategory":"Auto Repair",
            "type":"Services"
        }
    ],
    "sg:phone":"+1 770 607 1227",
    "sg:postcode":"30121",
    "sg:province":"GA",
    "sg:tags":[
        "body",
        "repairing",
        "cars-wholesale",
        "used",
        "car",
        "dealers-used",
        "painting"
    ],
    "wof:name":"Atlanta Auto Plex",
    "wof:placetype":"venue"
},
  "geometry": {"coordinates":[-84.786919,34.161715],"type":"Point"}
}