{
  "type": "Feature",
  "properties": {
    "iso:country":"US",
    "sg:address":"3483 Satellite Blvd Ste 310",
    "sg:city":"Duluth",
    "sg:classifiers":[
        {
            "category":"Real Estate",
            "subcategory":"Architect",
            "type":"Services"
        }
    ],
    "sg:phone":"+1 770 497 0404",
    "sg:postcode":"30096",
    "sg:province":"GA",
    "wof:name":"Yung Architecture",
    "wof:placetype":"venue"
},
  "geometry": {"coordinates":[-84.13239299999999,33.962542],"type":"Point"}
}