{
  "type": "Feature",
  "properties": {
    "addr:full":"273 W Howell St Hartwell GA 30643",
    "addr:housenumber":"273",
    "addr:postcode":"30643",
    "addr:street":"W Howell St",
    "iso:country":"US",
    "sg:address":"273 W Howell St",
    "sg:city":"Hartwell",
    "sg:classifiers":[
        {
            "category":"Shopping",
            "subcategory":"Used Merchandise",
            "type":"Retail Goods"
        }
    ],
    "sg:phone":"+1 706 376 5217",
    "sg:postcode":"30643",
    "sg:province":"GA",
    "wof:name":"Hartwell Pawn & Sports",
    "wof:placetype":"venue"
},
  "geometry": {"coordinates":[-82.943269,34.356642],"type":"Point"}
}