{
  "type": "Feature",
  "properties": {
    "addr:full":"305 Birkdale Dr Fayetteville GA 30215",
    "addr:housenumber":"305",
    "addr:postcode":"30215",
    "addr:street":"Birkdale Dr",
    "iso:country":"US",
    "sg:address":"305 Birkdale Dr",
    "sg:city":"Fayetteville",
    "sg:classifiers":[
        {
            "category":"Professional",
            "subcategory":"Management & Consulting",
            "type":"Services"
        }
    ],
    "sg:phone":"+1 770 460 1762",
    "sg:postcode":"30215",
    "sg:province":"GA",
    "sg:tags":[
        "business"
    ],
    "wof:name":"Jbcr LLC",
    "wof:placetype":"venue"
},
  "geometry": {"coordinates":[-84.488446,33.381009],"type":"Point"}
}