{
  "type": "Feature",
  "properties": {
    "iso:country":"US",
    "sg:address":"1854 Independence Sq",
    "sg:city":"Atlanta",
    "sg:classifiers":[
        {
            "category":"Professional",
            "type":"Services"
        }
    ],
    "sg:phone":"+1 770 396 0441",
    "sg:postcode":"30338",
    "sg:province":"GA",
    "wof:name":"Janette Berne Ms Lpc",
    "wof:placetype":"venue"
},
  "geometry": {"coordinates":[-84.313069,33.930705],"type":"Point"}
}