{
  "type": "Feature",
  "properties": {
    "iso:country":"US",
    "sg:address":"525 Parker-Banks Rd",
    "sg:city":"Lyons",
    "sg:classifiers":[
        {
            "category":"Farming",
            "subcategory":"Farm",
            "type":"Manufacturing & Wholesale Goods"
        }
    ],
    "sg:phone":"+1 912 565 7842",
    "sg:postcode":"30436",
    "sg:province":"GA",
    "sg:tags":[
        "crop",
        "general"
    ],
    "wof:name":"R Banks",
    "wof:placetype":"venue"
},
  "geometry": {"coordinates":[-82.30498799999999,32.02895],"type":"Point"}
}