{
  "type": "Feature",
  "properties": {
    "addr:full":"2400 Herodian Way Smyrna GA 30080",
    "addr:housenumber":"2400",
    "addr:postcode":"30080",
    "addr:street":"Herodian Way",
    "iso:country":"US",
    "sg:address":"2400 Herodian Way",
    "sg:city":"Smyrna",
    "sg:classifiers":[
        {
            "category":"Shopping",
            "subcategory":"Crafts & Fabrics",
            "type":"Retail Goods"
        }
    ],
    "sg:phone":"+1 678 244 2130",
    "sg:postcode":"30080",
    "sg:province":"GA",
    "sg:tags":[
        "sewing"
    ],
    "wof:name":"American Fibers and Yarns Co",
    "wof:placetype":"venue"
},
  "geometry": {"coordinates":[-84.472629,33.894313],"type":"Point"}
}