{
  "type": "Feature",
  "properties": {
    "iso:country":"US",
    "sg:address":"853 Blackshear Ferry Rd W",
    "sg:city":"Dublin",
    "sg:classifiers":[
        {
            "category":"Building & Trades",
            "subcategory":"Construction",
            "type":"Services"
        }
    ],
    "sg:phone":"+1 478 272 0604",
    "sg:postcode":"31021",
    "sg:province":"GA",
    "sg:tags":[
        "house"
    ],
    "wof:name":"Jimmy Rogers Construction Co I",
    "wof:placetype":"venue"
},
  "geometry": {"coordinates":[-82.941401,32.603085],"type":"Point"}
}