{
  "type": "Feature",
  "properties": {
    "iso:country":"US",
    "sg:address":"89 Green St",
    "sg:city":"Warner Robins",
    "sg:classifiers":[
        {
            "category":"Retail",
            "subcategory":"Auto Repair",
            "type":"Services"
        }
    ],
    "sg:phone":"+1 478 923 5111",
    "sg:postcode":"31093",
    "sg:province":"GA",
    "sg:tags":[
        "transmission",
        "exhaust"
    ],
    "wof:name":"Transmission & Muffler Shop",
    "wof:placetype":"venue"
},
  "geometry": {"coordinates":[-83.608824,32.629143],"type":"Point"}
}