{
  "type": "Feature",
  "properties": {
    "iso:country":"US",
    "sg:address":"729 Northside Dr E",
    "sg:city":"Statesboro",
    "sg:classifiers":[
        {
            "category":"Restaurant",
            "type":"Food & Drink"
        }
    ],
    "sg:phone":"+1 912 489 0649",
    "sg:postcode":"30458",
    "sg:province":"GA",
    "wof:name":"Original Friendly Diner",
    "wof:placetype":"venue"
},
  "geometry": {"coordinates":[-81.7559,32.434126],"type":"Point"}
}