{
  "type": "Feature",
  "properties": {
    "iso:country":"US",
    "sg:address":"795 Jones Wood Rd",
    "sg:city":"Monroe",
    "sg:classifiers":[
        {
            "category":"Organizations",
            "subcategory":"Religious Organization",
            "type":"Services"
        }
    ],
    "sg:phone":"+1 770 267 3506",
    "sg:postcode":"30655",
    "sg:province":"GA",
    "wof:name":"Good Hope Christian Church",
    "wof:placetype":"venue"
},
  "geometry": {"coordinates":[-83.578036,33.826627],"type":"Point"}
}