{
  "type": "Feature",
  "properties": {
    "addr:full":"3909 Green Industrial Way Atlanta GA 30341",
    "addr:housenumber":"3909",
    "addr:postcode":"30341",
    "addr:street":"Green Industrial Way",
    "iso:country":"US",
    "sg:address":"3909 Green Industrial Way",
    "sg:city":"Atlanta",
    "sg:classifiers":[
        {
            "category":"Wholesale",
            "subcategory":"Electrical",
            "type":"Manufacturing & Wholesale Goods"
        }
    ],
    "sg:phone":"+1 770 455 8551",
    "sg:postcode":"30341",
    "sg:province":"GA",
    "sg:tags":[
        "import",
        "distributes",
        "gas",
        "cooking",
        "heating"
    ],
    "wof:name":"P & T International Services",
    "wof:placetype":"venue"
},
  "geometry": {"coordinates":[-84.298171,33.904148],"type":"Point"}
}