{
  "type": "Feature",
  "properties": {
    "addr:full":"3665 Westchase Village Ln Norcross GA 30092",
    "addr:housenumber":"3665",
    "addr:postcode":"30092",
    "addr:street":"Westchase Village Ln",
    "iso:country":"US",
    "sg:address":"3665 Westchase Village Ln",
    "sg:city":"Norcross",
    "sg:classifiers":[
        {
            "category":"Building & Trades",
            "subcategory":"Cleaning & Sanitation",
            "type":"Services"
        }
    ],
    "sg:phone":"+1 770 734 0833",
    "sg:postcode":"30092",
    "sg:province":"GA",
    "sg:tags":[
        "janitor"
    ],
    "wof:name":"Sunflower Cleaning Svc",
    "wof:placetype":"venue"
},
  "geometry": {"coordinates":[-84.25124099999999,33.954864],"type":"Point"}
}