{
  "type": "Feature",
  "properties": {
    "iso:country":"US",
    "sg:address":"210 S King St",
    "sg:city":"Calhoun",
    "sg:classifiers":[
        {
            "category":"Government",
            "subcategory":"Jail",
            "type":"Public Place"
        }
    ],
    "sg:phone":"+1 706 624 1414",
    "sg:postcode":"30701",
    "sg:province":"GA",
    "sg:tags":[
        "govt",
        "state",
        "institution"
    ],
    "wof:name":"Corrections Dept Probation Ofc",
    "wof:placetype":"venue"
},
  "geometry": {"coordinates":[-84.954162,34.498929],"type":"Point"}
}