{
  "type": "Feature",
  "properties": {
    "addr:full":"109 Mc Farland Rd Dalton GA 30721",
    "addr:housenumber":"109",
    "addr:postcode":"30721",
    "addr:street":"Mc Farland Rd",
    "iso:country":"US",
    "sg:address":"109 Mc Farland Rd",
    "sg:city":"Dalton",
    "sg:classifiers":[
        {
            "category":"Freight",
            "type":"Transportation"
        }
    ],
    "sg:phone":"+1 706 277 2915",
    "sg:postcode":"30721",
    "sg:province":"GA",
    "sg:tags":[
        "operator",
        "local",
        "trucking"
    ],
    "wof:name":"Bridge Terminal Transport",
    "wof:placetype":"venue"
},
  "geometry": {"coordinates":[-84.965603,34.729178],"type":"Point"}
}