{
  "type": "Feature",
  "properties": {
    "addr:full":"1220 Cumberland Mall SE Atlanta GA 30339",
    "addr:housenumber":"1220",
    "addr:postcode":"30339",
    "addr:street":"Cumberland Mall Se",
    "iso:country":"US",
    "sg:address":"1220 Cumberland Mall SE",
    "sg:city":"Atlanta",
    "sg:classifiers":[
        {
            "category":"Shopping",
            "subcategory":"Mobile Phones",
            "type":"Retail Goods"
        }
    ],
    "sg:phone":"+1 770 437 1323",
    "sg:postcode":"30339",
    "sg:province":"GA",
    "wof:name":"Wireless Universe",
    "wof:placetype":"venue"
},
  "geometry": {"coordinates":[-84.470619,33.880308],"type":"Point"}
}