{
  "type": "Feature",
  "properties": {
    "addr:full":"7423 Sherman Rd Jonesboro GA 30236",
    "addr:housenumber":"7423",
    "addr:postcode":"30236",
    "addr:street":"Sherman Rd",
    "iso:country":"US",
    "sg:address":"7423 Sherman Rd",
    "sg:city":"Jonesboro",
    "sg:classifiers":[
        {
            "category":"Health Services",
            "subcategory":"Clinic",
            "type":"Services"
        }
    ],
    "sg:phone":"+1 678 479 5269",
    "sg:postcode":"30236",
    "sg:province":"GA",
    "sg:tags":[
        "home",
        "care"
    ],
    "wof:name":"Expert Outreach Services Inc",
    "wof:placetype":"venue"
},
  "geometry": {"coordinates":[-84.32468799999999,33.547033],"type":"Point"}
}