{
  "type": "Feature",
  "properties": {
    "addr:full":"430 Prior St SE Gainesville GA 30501",
    "addr:housenumber":"430",
    "addr:postcode":"30501",
    "addr:street":"Prior St Se;Ga",
    "iso:country":"US",
    "sg:address":"430 Prior St SE",
    "sg:city":"Gainesville",
    "sg:classifiers":[
        {
            "category":"Social Services",
            "type":"Services"
        }
    ],
    "sg:phone":"+1 770 534 3337",
    "sg:postcode":"30501",
    "sg:province":"GA",
    "sg:tags":[
        "organization",
        "welfare"
    ],
    "wof:name":"Catholic Social Svs",
    "wof:placetype":"venue"
},
  "geometry": {"coordinates":[-83.81892999999999,34.300231],"type":"Point"}
}