{
  "type": "Feature",
  "properties": {
    "iso:country":"US",
    "sg:address":"6659 Peachtree Industrial Blvd Ste F",
    "sg:city":"Norcross",
    "sg:classifiers":[
        {
            "category":"Building & Trades",
            "subcategory":"Cleaning & Sanitation",
            "type":"Services"
        }
    ],
    "sg:phone":"+1 678 502 7162",
    "sg:postcode":"30092",
    "sg:province":"GA",
    "sg:tags":[
        "carpet"
    ],
    "wof:name":"Pro Kleen Carpet Services Inc",
    "wof:placetype":"venue"
},
  "geometry": {"coordinates":[-84.251563,33.93801],"type":"Point"}
}