{
  "type": "Feature",
  "properties": {
    "addr:full":"702 Valley Dr Dalton GA 30720",
    "addr:housenumber":"702",
    "addr:postcode":"30720",
    "addr:street":"Valley Dr",
    "iso:country":"US",
    "sg:address":"702 Valley Dr",
    "sg:city":"Dalton",
    "sg:classifiers":[
        {
            "category":"Building & Trades",
            "subcategory":"Electrical",
            "type":"Services"
        }
    ],
    "sg:phone":"+1 706 217 6553",
    "sg:postcode":"30720",
    "sg:province":"GA",
    "sg:tags":[
        "electrical",
        "contractor"
    ],
    "wof:name":"Western Financial Service Inc",
    "wof:placetype":"venue"
},
  "geometry": {"coordinates":[-84.973851,34.763109],"type":"Point"}
}