{
  "type": "Feature",
  "properties": {
    "addr:full":"225 Main St Hiram GA 30141",
    "addr:housenumber":"225",
    "addr:postcode":"30141",
    "addr:street":"Main St",
    "iso:country":"US",
    "sg:address":"225 Main St",
    "sg:city":"Hiram",
    "sg:classifiers":[
        {
            "category":"Government",
            "subcategory":"Post Office",
            "type":"Public Place"
        }
    ],
    "sg:phone":"+1 770 222 0425",
    "sg:postcode":"30141",
    "sg:province":"GA",
    "sg:website":"www.usps.com",
    "wof:name":"US Post Office",
    "wof:placetype":"venue"
},
  "geometry": {"coordinates":[-84.759642,33.875891],"type":"Point"}
}