{
  "type": "Feature",
  "properties": {
    "addr:full":"1901 Terrell Mill Rd SE Ste 100 Marietta GA 30067",
    "addr:housenumber":"1901",
    "addr:postcode":"30067",
    "addr:street":"Terrell Mill Rd Se Ste 100",
    "iso:country":"US",
    "sg:address":"1901 Terrell Mill Rd SE Ste 100",
    "sg:city":"Marietta",
    "sg:classifiers":[
        {
            "category":"Shopping",
            "subcategory":"Department Store",
            "type":"Retail Goods"
        }
    ],
    "sg:phone":"+1 678 247 2106",
    "sg:postcode":"30067",
    "sg:province":"GA",
    "sg:website":"www.burlingtoncoatfactory.com",
    "wof:name":"Burlington Coat Factory",
    "wof:placetype":"venue"
},
  "geometry": {"coordinates":[-84.48864,33.905897],"type":"Point"}
}