{
  "type": "Feature",
  "properties": {
    "addr:full":"237 Trinity Rd Whigham GA 39897",
    "addr:housenumber":"237",
    "addr:postcode":"39897",
    "addr:street":"Trinity Rd",
    "iso:country":"US",
    "sg:address":"237 Trinity Rd",
    "sg:city":"Whigham",
    "sg:classifiers":[
        {
            "category":"Food & Beverages",
            "subcategory":"Candy",
            "type":"Retail Goods"
        },
        {
            "category":"Manufacturing",
            "subcategory":"Food",
            "type":"Manufacturing & Wholesale Goods"
        }
    ],
    "sg:phone":"+1 229 762 3725",
    "sg:postcode":"39897",
    "sg:province":"GA",
    "sg:tags":[
        "confectionery-wholesale",
        "confectionery",
        "manufacturer"
    ],
    "sg:website":"http://cheriesdelights.com/",
    "wof:name":"Cherie's Delights",
    "wof:placetype":"venue"
},
  "geometry": {"coordinates":[-84.312848,30.915334],"type":"Point"}
}