{
  "type": "Feature",
  "properties": {
    "addr:full":"152 Scrubby Bluff Rd Kingsland GA 31548",
    "addr:housenumber":"152",
    "addr:postcode":"31548",
    "addr:street":"Scrubby Bluff Rd",
    "iso:country":"US",
    "sg:address":"152 Scrubby Bluff Rd",
    "sg:city":"Kingsland",
    "sg:classifiers":[
        {
            "category":"Manufacturing",
            "subcategory":"Pet Food",
            "type":"Manufacturing & Wholesale Goods"
        }
    ],
    "sg:phone":"+1 912 729 3951",
    "sg:postcode":"31548",
    "sg:province":"GA",
    "sg:tags":[
        "housing-distributors",
        "manufactured",
        "manufacturer"
    ],
    "wof:name":"Hhd Inc",
    "wof:placetype":"venue"
},
  "geometry": {"coordinates":[-81.67935,30.777342],"type":"Point"}
}