{
  "type": "Feature",
  "properties": {
    "addr:full":"3700 Holcomb Bridge Rd Norcross GA 30092",
    "addr:housenumber":"3700",
    "addr:postcode":"30092",
    "addr:street":"Holcomb Bridge Rd",
    "iso:country":"US",
    "sg:address":"3700 Holcomb Bridge Rd",
    "sg:city":"Norcross",
    "sg:classifiers":[
        {
            "category":"Health Services",
            "subcategory":"Doctor",
            "type":"Services"
        }
    ],
    "sg:phone":"+1 770 368 8702",
    "sg:postcode":"30092",
    "sg:province":"GA",
    "sg:tags":[
        "physician",
        "surgeon"
    ],
    "wof:name":"Matthew J Britton MD",
    "wof:placetype":"venue"
},
  "geometry": {"coordinates":[-84.247451,33.95954],"type":"Point"}
}