{
  "type": "Feature",
  "properties": {
    "addr:full":"1174 Brookhaven North Cir Atlanta GA 30319",
    "addr:housenumber":"1174",
    "addr:postcode":"30319",
    "addr:street":"Brookhaven North Cir",
    "iso:country":"US",
    "sg:address":"1174 Brookhaven North Cir",
    "sg:city":"Atlanta",
    "sg:classifiers":[
        {
            "category":"Travel",
            "subcategory":"Travel Agent",
            "type":"Entertainment"
        }
    ],
    "sg:phone":"+1 404 266 2726",
    "sg:postcode":"30319",
    "sg:province":"GA",
    "sg:tags":[
        "agency"
    ],
    "wof:name":"Fep Travel",
    "wof:placetype":"venue"
},
  "geometry": {"coordinates":[-84.34045399999999,33.867854],"type":"Point"}
}