{
  "type": "Feature",
  "properties": {
    "addr:full":"2 Marsh Island Ln Savannah GA 31411",
    "addr:housenumber":"2",
    "addr:postcode":"31411",
    "addr:street":"Marsh Island Ln",
    "iso:country":"US",
    "sg:address":"2 Marsh Island Ln",
    "sg:city":"Savannah",
    "sg:classifiers":[
        {
            "category":"Wholesale",
            "subcategory":"Non-durable Goods",
            "type":"Manufacturing & Wholesale Goods"
        }
    ],
    "sg:phone":"+1 912 598 5479",
    "sg:postcode":"31411",
    "sg:province":"GA",
    "wof:name":"Davis Art",
    "wof:placetype":"venue"
},
  "geometry": {"coordinates":[-81.055374,31.917106],"type":"Point"}
}