{
  "type": "Feature",
  "properties": {
    "iso:country":"US",
    "sg:address":"106 South Ave",
    "sg:city":"Fairmount",
    "sg:classifiers":[
        {
            "category":"Home & Garden",
            "subcategory":"Furniture",
            "type":"Retail Goods"
        }
    ],
    "sg:phone":"+1 706 337 2239",
    "sg:postcode":"30139",
    "sg:province":"GA",
    "wof:name":"Watts Store",
    "wof:placetype":"venue"
},
  "geometry": {"coordinates":[-84.701734,34.435185],"type":"Point"}
}