{
  "type": "Feature",
  "properties": {
    "addr:full":"284 Highway 74 N Peachtree Cty GA 30269",
    "addr:housenumber":"284",
    "addr:postcode":"30269",
    "addr:street":"Highway 74 N Peachtree",
    "iso:country":"US",
    "sg:address":"284 Highway 74 N",
    "sg:city":"Peachtree Cty",
    "sg:classifiers":[
        {
            "category":"Personal",
            "subcategory":"Beauty Salon",
            "type":"Services"
        }
    ],
    "sg:phone":"+1 678 364 0025",
    "sg:postcode":"30269",
    "sg:province":"GA",
    "sg:tags":[
        "hair"
    ],
    "wof:name":"Carlos Salon",
    "wof:placetype":"venue"
},
  "geometry": {"coordinates":[-84.60189800000001,33.409302],"type":"Point"}
}