{
  "type": "Feature",
  "properties": {
    "iso:country":"US",
    "sg:address":"710 Georgia Ave Apt 181",
    "sg:city":"Statesboro",
    "sg:classifiers":[
        {
            "category":"Building & Trades",
            "subcategory":"Electrical",
            "type":"Services"
        }
    ],
    "sg:phone":"+1 912 681 7281",
    "sg:postcode":"30458",
    "sg:province":"GA",
    "sg:tags":[
        "electrician"
    ],
    "wof:name":"Gaver Electric",
    "wof:placetype":"venue"
},
  "geometry": {"coordinates":[-81.773138,32.41915],"type":"Point"}
}