{
  "type": "Feature",
  "properties": {
    "iso:country":"US",
    "sg:address":"3631 Ledan Rd",
    "sg:city":"Gainesville",
    "sg:classifiers":[
        {
            "category":"Building & Trades",
            "subcategory":"Landscaping Services",
            "type":"Services"
        }
    ],
    "sg:phone":"+1 770 519 1718",
    "sg:postcode":"30506",
    "sg:province":"GA",
    "sg:tags":[
        "designer",
        "landscape"
    ],
    "wof:name":"Cutting Edge Creative Lndscpng",
    "wof:placetype":"venue"
},
  "geometry": {"coordinates":[-83.88961999999999,34.356495],"type":"Point"}
}