{
  "type": "Feature",
  "properties": {
    "addr:full":"204 Cumberland Woods Ter Warner Robins GA 31088",
    "addr:housenumber":"204",
    "addr:postcode":"31088",
    "addr:street":"Cumberland Woods Ter",
    "iso:country":"US",
    "sg:address":"204 Cumberland Woods Ter",
    "sg:city":"Warner Robins",
    "sg:classifiers":[
        {
            "category":"Professional",
            "subcategory":"Accounting & Tax Preparation",
            "type":"Services"
        }
    ],
    "sg:phone":"+1 478 953 6456",
    "sg:postcode":"31088",
    "sg:province":"GA",
    "sg:tags":[
        "consulting",
        "business"
    ],
    "wof:name":"Mitchell Consulting Group",
    "wof:placetype":"venue"
},
  "geometry": {"coordinates":[-83.656851,32.579984],"type":"Point"}
}