{
  "type": "Feature",
  "properties": {
    "iso:country":"US",
    "sg:address":"1125 Woodstock Rd",
    "sg:city":"Roswell",
    "sg:classifiers":[
        {
            "category":"Personal",
            "subcategory":"Beauty Salon",
            "type":"Services"
        }
    ],
    "sg:phone":"+1 770 518 7440",
    "sg:postcode":"30075",
    "sg:province":"GA",
    "wof:name":"Great Clips",
    "wof:placetype":"venue"
},
  "geometry": {"coordinates":[-84.39156699999999,34.062552],"type":"Point"}
}