{
  "type": "Feature",
  "properties": {
    "iso:country":"US",
    "sg:address":"1006 E Broad St",
    "sg:city":"Savannah",
    "sg:classifiers":[
        {
            "category":"Wholesale",
            "subcategory":"Groceries",
            "type":"Manufacturing & Wholesale Goods"
        }
    ],
    "sg:phone":"+1 912 238 9822",
    "sg:postcode":"31401",
    "sg:province":"GA",
    "sg:tags":[
        "confectionery"
    ],
    "wof:name":"Que Confectionary & Games",
    "wof:placetype":"venue"
},
  "geometry": {"coordinates":[-81.089721,32.0635],"type":"Point"}
}