{
  "type": "Feature",
  "properties": {
    "iso:country":"US",
    "sg:address":"15245 Birmingham Hwy",
    "sg:city":"Alpharetta",
    "sg:classifiers":[
        {
            "category":"Building & Trades",
            "subcategory":"Construction",
            "type":"Services"
        }
    ],
    "sg:phone":"+1 770 475 0804",
    "sg:postcode":"30004",
    "sg:province":"GA",
    "sg:tags":[
        "contractor"
    ],
    "wof:name":"Ray Lamanac Roofing",
    "wof:placetype":"venue"
},
  "geometry": {"coordinates":[-84.342716,34.153765],"type":"Point"}
}