{
  "type": "Feature",
  "properties": {
    "iso:country":"US",
    "sg:address":"1105 Upper Hembree Rd",
    "sg:city":"Roswell",
    "sg:classifiers":[
        {
            "category":"Health Services",
            "subcategory":"Doctor",
            "type":"Services"
        }
    ],
    "sg:phone":"+1 770 664 4449",
    "sg:postcode":"30076",
    "sg:province":"GA",
    "wof:name":"John Attokaren MD PC",
    "wof:placetype":"venue"
},
  "geometry": {"coordinates":[-84.32654100000001,34.068228],"type":"Point"}
}