{
  "type": "Feature",
  "properties": {
    "iso:country":"US",
    "sg:address":"3570 Dallas Mill Rd",
    "sg:city":"La Grange",
    "sg:classifiers":[
        {
            "category":"Professional",
            "subcategory":"Management & Consulting",
            "type":"Services"
        }
    ],
    "sg:phone":"+1 706 884 7034",
    "sg:postcode":"30241",
    "sg:province":"GA",
    "wof:name":"A B S Restoration & Design",
    "wof:placetype":"venue"
},
  "geometry": {"coordinates":[-84.87148500000001,32.943559],"type":"Point"}
}