{
  "type": "Feature",
  "properties": {
    "addr:full":"5116 Kings Camp Rd SE Acworth GA 30102",
    "addr:housenumber":"5116",
    "addr:postcode":"30102",
    "addr:street":"Kings Camp Rd Se",
    "iso:country":"US",
    "sg:address":"5116 Kings Camp Rd SE",
    "sg:city":"Acworth",
    "sg:classifiers":[
        {
            "category":"Retail",
            "subcategory":"Auto Repair",
            "type":"Services"
        }
    ],
    "sg:phone":"+1 770 974 4689",
    "sg:postcode":"30102",
    "sg:province":"GA",
    "sg:tags":[
        "automotive"
    ],
    "wof:name":"A J Wrecker Service",
    "wof:placetype":"venue"
},
  "geometry": {"coordinates":[-84.68589299999999,34.115878],"type":"Point"}
}