{
  "type": "Feature",
  "properties": {
    "iso:country":"US",
    "sg:address":"3252 Wrightsboro Rd",
    "sg:city":"Augusta",
    "sg:classifiers":[
        {
            "category":"Shopping",
            "subcategory":"Clothing, Apparel, & Fashions",
            "type":"Retail Goods"
        }
    ],
    "sg:phone":"+1 706 731 9150",
    "sg:postcode":"30909",
    "sg:province":"GA",
    "wof:name":"It's Fashion",
    "wof:placetype":"venue"
},
  "geometry": {"coordinates":[-82.065833,33.469342],"type":"Point"}
}