{
  "type": "Feature",
  "properties": {
    "addr:full":"3101 Hwy 53 E Jasper GA 30143",
    "addr:housenumber":"3101",
    "addr:postcode":"30143",
    "addr:street":"Hwy 53 E",
    "iso:country":"US",
    "sg:address":"3101 Hwy 53 E",
    "sg:city":"Jasper",
    "sg:classifiers":[
        {
            "category":"Retail",
            "subcategory":"Repair Shop",
            "type":"Services"
        }
    ],
    "sg:phone":"+1 770 735 6587",
    "sg:postcode":"30143",
    "sg:province":"GA",
    "sg:tags":[
        "repairing",
        "lawn",
        "mower"
    ],
    "wof:name":"Kenny's Repair Svc",
    "wof:placetype":"venue"
},
  "geometry": {"coordinates":[-84.39691999999999,34.436816],"type":"Point"}
}