{
  "type": "Feature",
  "properties": {
    "iso:country":"US",
    "sg:address":"408 Creek Side Ln",
    "sg:city":"Woodstock",
    "sg:classifiers":[
        {
            "category":"Professional",
            "subcategory":"Lawyer & Legal Services",
            "type":"Services"
        }
    ],
    "sg:phone":"+1 770 422 7406",
    "sg:postcode":"30188",
    "sg:province":"GA",
    "sg:tags":[
        "attorney"
    ],
    "wof:name":"Gayle Camp Keener PC",
    "wof:placetype":"venue"
},
  "geometry": {"coordinates":[-84.49999699999999,34.090583],"type":"Point"}
}