{
  "type": "Feature",
  "properties": {
    "iso:country":"US",
    "sg:address":"3242 Lenora Church Rd",
    "sg:city":"Snellville",
    "sg:classifiers":[
        {
            "category":"Retail",
            "subcategory":"Portrait Studio",
            "type":"Services"
        }
    ],
    "sg:phone":"+1 770 736 3214",
    "sg:postcode":"30039",
    "sg:province":"GA",
    "sg:tags":[
        "photo"
    ],
    "wof:name":"Robin Ewing Fine Photography",
    "wof:placetype":"venue"
},
  "geometry": {"coordinates":[-84.010048,33.82876],"type":"Point"}
}