{
  "type": "Feature",
  "properties": {
    "addr:full":"101 Walton Green Way NW Kennesaw GA 30144",
    "addr:housenumber":"101",
    "addr:postcode":"30144",
    "addr:street":"Walton Green Way Nw",
    "iso:country":"US",
    "sg:address":"101 Walton Green Way NW",
    "sg:city":"Kennesaw",
    "sg:classifiers":[
        {
            "category":"Social Services",
            "type":"Services"
        }
    ],
    "sg:phone":"+1 770 428 5685",
    "sg:postcode":"30144",
    "sg:province":"GA",
    "wof:name":"Best Parenting Resources LLC",
    "wof:placetype":"venue"
},
  "geometry": {"coordinates":[-84.596137,34.052845],"type":"Point"}
}