{
  "type": "Feature",
  "properties": {
    "addr:full":"133 Simmons St Eatonton GA 31024",
    "addr:housenumber":"133",
    "addr:postcode":"31024",
    "addr:street":"Simmons St",
    "iso:country":"US",
    "sg:address":"133 Simmons St",
    "sg:city":"Eatonton",
    "sg:classifiers":[
        {
            "category":"Social Services",
            "subcategory":"Child Care",
            "type":"Services"
        }
    ],
    "sg:phone":"+1 706 485 6628",
    "sg:postcode":"31024",
    "sg:province":"GA",
    "sg:tags":[
        "day"
    ],
    "wof:name":"Schell Family Day Care",
    "wof:placetype":"venue"
},
  "geometry": {"coordinates":[-83.392231,33.319175],"type":"Point"}
}