{
  "type": "Feature",
  "properties": {
    "addr:full":"2500 Old Alabama Rd Ste 8 Roswell GA 30076",
    "addr:housenumber":"2500",
    "addr:postcode":"30076",
    "addr:street":"Old Alabama Rd Ste 8",
    "iso:country":"US",
    "sg:address":"2500 Old Alabama Rd Ste 8",
    "sg:city":"Roswell",
    "sg:classifiers":[
        {
            "category":"Wholesale",
            "subcategory":"Computers",
            "type":"Manufacturing & Wholesale Goods"
        },
        {
            "category":"Professional",
            "subcategory":"Computer Services",
            "type":"Services"
        }
    ],
    "sg:phone":"+1 770 998 4663",
    "sg:postcode":"30076",
    "sg:province":"GA",
    "sg:tags":[
        "repair"
    ],
    "sg:website":"www.nticomputers.com",
    "wof:name":"Nti Computers",
    "wof:placetype":"venue"
},
  "geometry": {"coordinates":[-84.28668999999999,34.022066],"type":"Point"}
}