{
  "type": "Feature",
  "properties": {
    "iso:country":"US",
    "sg:address":"355 Lakeridge Ct",
    "sg:city":"Mcdonough",
    "sg:classifiers":[
        {
            "category":"Wholesale",
            "subcategory":"Stationery",
            "type":"Manufacturing & Wholesale Goods"
        },
        {
            "category":"Professional",
            "subcategory":"Advertising",
            "type":"Services"
        }
    ],
    "sg:phone":"+1 404 456 1523",
    "sg:postcode":"30253",
    "sg:province":"GA",
    "sg:tags":[
        "distribution",
        "supply"
    ],
    "wof:name":"Occasions",
    "wof:placetype":"venue"
},
  "geometry": {"coordinates":[-84.186052,33.474335],"type":"Point"}
}