{
  "type": "Feature",
  "properties": {
    "addr:full":"4300 Buford Dr Buford GA 30518",
    "addr:housenumber":"4300",
    "addr:postcode":"30518",
    "addr:street":"Buford Dr",
    "iso:country":"US",
    "sg:address":"4300 Buford Dr",
    "sg:city":"Buford",
    "sg:classifiers":[
        {
            "category":"Professional",
            "subcategory":"Employment Agencies",
            "type":"Services"
        }
    ],
    "sg:phone":"+1 770 271 1738",
    "sg:postcode":"30518",
    "sg:province":"GA",
    "sg:website":"www.selectstaffing.com",
    "wof:name":"Select Staffing",
    "wof:placetype":"venue"
},
  "geometry": {"coordinates":[-84.010093,34.093787],"type":"Point"}
}