{
  "type": "Feature",
  "properties": {
    "iso:country":"US",
    "sg:address":"1377 Briarwood Rd NE",
    "sg:city":"Atlanta",
    "sg:classifiers":[
        {
            "category":"Shopping",
            "type":"Retail Goods"
        }
    ],
    "sg:phone":"+1 404 233 2387",
    "sg:postcode":"30319",
    "sg:province":"GA",
    "sg:tags":[
        "merchandise"
    ],
    "wof:name":"Reef Cay",
    "wof:placetype":"venue"
},
  "geometry": {"coordinates":[-84.33407200000001,33.850814],"type":"Point"}
}