{
  "type": "Feature",
  "properties": {
    "addr:full":"6209 Westridge Trce Acworth GA 30102",
    "addr:housenumber":"6209",
    "addr:postcode":"30102",
    "addr:street":"Westridge Trce",
    "iso:country":"US",
    "sg:address":"6209 Westridge Trce",
    "sg:city":"Acworth",
    "sg:classifiers":[
        {
            "category":"Building & Trades",
            "subcategory":"Construction",
            "type":"Services"
        }
    ],
    "sg:phone":"+1 404 867 9860",
    "sg:postcode":"30102",
    "sg:province":"GA",
    "sg:tags":[
        "restoration",
        "cleaning",
        "patio",
        "deck"
    ],
    "wof:name":"Georgia Pressure Washing Co",
    "wof:placetype":"venue"
},
  "geometry": {"coordinates":[-84.621583,34.108301],"type":"Point"}
}