{
  "type": "Feature",
  "properties": {
    "addr:full":"49 Hurricane Shoals Rd NW Lawrenceville GA 30046",
    "addr:housenumber":"49",
    "addr:postcode":"30046",
    "addr:street":"Hurricane Shoals Rd Nw",
    "iso:country":"US",
    "sg:address":"49 Hurricane Shoals Rd NW",
    "sg:city":"Lawrenceville",
    "sg:classifiers":[
        {
            "category":"Food & Beverages",
            "subcategory":"Groceries & Convenience Stores",
            "type":"Retail Goods"
        }
    ],
    "sg:phone":"+1 770 339 1230",
    "sg:postcode":"30046",
    "sg:province":"GA",
    "sg:website":"www.exxon.com",
    "wof:name":"Exxon Food Mart",
    "wof:placetype":"venue"
},
  "geometry": {"coordinates":[-83.99368699999999,33.97031],"type":"Point"}
}