{
  "type": "Feature",
  "properties": {
    "addr:full":"319 E 8th St Rome GA 30161",
    "addr:housenumber":"319",
    "addr:postcode":"ga 30161",
    "addr:street":"E 8Th St",
    "iso:country":"US",
    "sg:address":"319 E 8th St",
    "sg:city":"Rome",
    "sg:classifiers":[
        {
            "category":"Insurance",
            "subcategory":"Insurance Agent",
            "type":"Services"
        }
    ],
    "sg:phone":"+1 706 292 0965",
    "sg:postcode":"30161",
    "sg:province":"GA",
    "wof:name":"North Georgia Insurance",
    "wof:placetype":"venue"
},
  "geometry": {"coordinates":[-85.161644,34.24318],"type":"Point"}
}