{
  "type": "Feature",
  "properties": {
    "addr:full":"600 N Boulevard Baxley GA 31513",
    "addr:housenumber":"600",
    "addr:postcode":"31513",
    "addr:street":"N Boulevard",
    "iso:country":"US",
    "sg:address":"600 N Boulevard",
    "sg:city":"Baxley",
    "sg:classifiers":[
        {
            "category":"Place Of Worship",
            "type":"Public Place"
        }
    ],
    "sg:phone":"+1 912 367 8565",
    "sg:postcode":"31513",
    "sg:province":"GA",
    "sg:tags":[
        "church"
    ],
    "wof:name":"Shephard Light Harvest Outreach",
    "wof:placetype":"venue"
},
  "geometry": {"coordinates":[-82.350647,31.787239],"type":"Point"}
}