{
  "type": "Feature",
  "properties": {
    "addr:full":"2523 Roosevelt Hwy Atlanta GA 30337",
    "addr:housenumber":"2523",
    "addr:postcode":"30337",
    "addr:street":"Roosevelt Hwy",
    "iso:country":"US",
    "sg:address":"2523 Roosevelt Hwy",
    "sg:city":"Atlanta",
    "sg:classifiers":[
        {
            "category":"Professional",
            "subcategory":"Management & Consulting",
            "type":"Services"
        },
        {
            "category":"Wholesale",
            "subcategory":"Durable Goods & Equipment",
            "type":"Manufacturing & Wholesale Goods"
        }
    ],
    "sg:phone":"+1 404 768 0488",
    "sg:postcode":"30337",
    "sg:province":"GA",
    "sg:tags":[
        "compact",
        "record",
        "disc",
        "tape"
    ],
    "wof:name":"Gunsmoke Records",
    "wof:placetype":"venue"
},
  "geometry": {"coordinates":[-84.469437,33.63143],"type":"Point"}
}