{
  "type": "Feature",
  "properties": {
    "iso:country":"US",
    "sg:address":"1520 Austin Dr",
    "sg:city":"Decatur",
    "sg:classifiers":[
        {
            "category":"Freight",
            "type":"Transportation"
        }
    ],
    "sg:phone":"+1 404 289 7626",
    "sg:postcode":"30032",
    "sg:province":"GA",
    "sg:tags":[
        "commercial",
        "storage",
        "general"
    ],
    "wof:name":"Austin Drive Self Storage",
    "wof:placetype":"venue"
},
  "geometry": {"coordinates":[-84.23396,33.750244],"type":"Point"}
}