{
  "type": "Feature",
  "properties": {
    "addr:full":"1109 Russell Pkwy Warner Robins GA 31088",
    "addr:housenumber":"1109",
    "addr:postcode":"31088",
    "addr:street":"Russell Pkwy",
    "iso:country":"US",
    "sg:address":"1109 Russell Pkwy",
    "sg:city":"Warner Robins",
    "sg:classifiers":[
        {
            "category":"Professional",
            "subcategory":"Business Services",
            "type":"Services"
        }
    ],
    "sg:phone":"+1 478 929 2342",
    "sg:postcode":"31088",
    "sg:province":"GA",
    "wof:name":"Offtec Express",
    "wof:placetype":"venue"
},
  "geometry": {"coordinates":[-83.645974,32.593906],"type":"Point"}
}