{
  "type": "Feature",
  "properties": {
    "iso:country":"US",
    "sg:address":"4226 Columbia Rd",
    "sg:city":"Martinez",
    "sg:classifiers":[
        {
            "category":"Banks & Credit Unions",
            "subcategory":"Bank",
            "type":"Services"
        }
    ],
    "sg:phone":"+1 706 863 2000",
    "sg:postcode":"30907",
    "sg:province":"GA",
    "sg:website":"www.fnbtrust.com",
    "wof:name":"First National Bank & Trust Co",
    "wof:placetype":"venue"
},
  "geometry": {"coordinates":[-82.117085,33.50786],"type":"Point"}
}