{
  "type": "Feature",
  "properties": {
    "iso:country":"US",
    "sg:address":"1397 Moore Rd",
    "sg:city":"Newnan",
    "sg:classifiers":[
        {
            "category":"Professional",
            "subcategory":"Business Services",
            "type":"Services"
        }
    ],
    "sg:phone":"+1 770 253 9878",
    "sg:postcode":"30263",
    "sg:province":"GA",
    "wof:name":"Brandley Enterprises",
    "wof:placetype":"venue"
},
  "geometry": {"coordinates":[-84.71247099999999,33.2958],"type":"Point"}
}