{
  "type": "Feature",
  "properties": {
    "addr:full":"301 Telfair St Dublin GA 31021",
    "addr:housenumber":"301",
    "addr:postcode":"31021",
    "addr:street":"Telfair St",
    "iso:country":"US",
    "sg:address":"301 Telfair St",
    "sg:city":"Dublin",
    "sg:classifiers":[
        {
            "category":"Autos & Motor Vehicles",
            "subcategory":"Auto Supplies",
            "type":"Retail Goods"
        }
    ],
    "sg:phone":"+1 478 272 5404",
    "sg:postcode":"31021",
    "sg:province":"GA",
    "sg:tags":[
        "repair",
        "tire",
        "automobile",
        "equipment-service",
        "air conditioning"
    ],
    "sg:website":"www.duncantire.com",
    "wof:name":"Duncan Tire Co. Inc.",
    "wof:placetype":"venue"
},
  "geometry": {"coordinates":[-82.906764,32.53542],"type":"Point"}
}