{
  "type": "Feature",
  "properties": {
    "iso:country":"US",
    "sg:address":"1929 Ga Highway 37 E",
    "sg:city":"Moultrie",
    "sg:classifiers":[
        {
            "category":"Building & Trades",
            "subcategory":"Electrical",
            "type":"Services"
        }
    ],
    "sg:phone":"+1 229 589 1405",
    "sg:postcode":"31788",
    "sg:province":"GA",
    "sg:tags":[
        "electrician"
    ],
    "wof:name":"Goodno Electrical Service",
    "wof:placetype":"venue"
},
  "geometry": {"coordinates":[-83.75255,31.192732],"type":"Point"}
}