{
  "type": "Feature",
  "properties": {
    "iso:country":"US",
    "sg:address":"2895 Co Rd 117",
    "sg:city":"Cadwell",
    "sg:classifiers":[
        {
            "category":"Retail",
            "subcategory":"Auto Repair",
            "type":"Services"
        }
    ],
    "sg:phone":"+1 478 689 4000",
    "sg:postcode":"31009",
    "sg:province":"GA",
    "sg:tags":[
        "repairing",
        "automobile"
    ],
    "wof:name":"D & T Auto Repair",
    "wof:placetype":"venue"
},
  "geometry": {"coordinates":[-83.04186,32.339656],"type":"Point"}
}