{
  "type": "Feature",
  "properties": {
    "addr:full":"75 Piedmont Ave SE Atlanta GA 30303",
    "addr:housenumber":"75",
    "addr:postcode":"30303",
    "addr:street":"Piedmont Ave Se",
    "iso:country":"US",
    "sg:address":"75 Piedmont Ave SE",
    "sg:city":"Atlanta",
    "sg:classifiers":[
        {
            "category":"Organizations",
            "subcategory":"Religious Organization",
            "type":"Services"
        }
    ],
    "sg:phone":"+1 404 215 3383",
    "sg:postcode":"30303",
    "sg:province":"GA",
    "wof:name":"T D Jakes Ministries",
    "wof:placetype":"venue"
},
  "geometry": {"coordinates":[-84.38337799999999,33.753364],"type":"Point"}
}