{
  "type": "Feature",
  "properties": {
    "addr:full":"3226 Hamilton Rd Columbus GA 31904",
    "addr:housenumber":"3226",
    "addr:postcode":"31904",
    "addr:street":"Hamilton Rd",
    "iso:country":"US",
    "sg:address":"3226 Hamilton Rd",
    "sg:city":"Columbus",
    "sg:classifiers":[
        {
            "category":"Shopping",
            "subcategory":"Used Merchandise",
            "type":"Retail Goods"
        },
        {
            "category":"Professional",
            "subcategory":"Business Services",
            "type":"Services"
        }
    ],
    "sg:phone":"+1 706 653 6240",
    "sg:postcode":"31904",
    "sg:province":"GA",
    "sg:tags":[
        "antique",
        "gallery"
    ],
    "wof:name":"Rivermarket Antiques & Art Ctr",
    "wof:placetype":"venue"
},
  "geometry": {"coordinates":[-84.979691,32.494396],"type":"Point"}
}