{
  "type": "Feature",
  "properties": {
    "iso:country":"US",
    "sg:address":"872 Buford Rd",
    "sg:city":"Buford",
    "sg:classifiers":[
        {
            "category":"Bars & Pubs",
            "type":"Food & Drink"
        },
        {
            "category":"Restaurant",
            "type":"Food & Drink"
        }
    ],
    "sg:phone":"+1 770 889 4664",
    "sg:postcode":"30518",
    "sg:province":"GA",
    "sg:tags":[
        "seafood"
    ],
    "sg:website":"www.cummingfishmarket.com/",
    "wof:name":"Cumming Fish Market",
    "wof:placetype":"venue"
},
  "geometry": {"coordinates":[-84.073404,34.159792],"type":"Point"}
}