{
  "type": "Feature",
  "properties": {
    "iso:country":"US",
    "sg:address":"1497 Fair Rd",
    "sg:city":"Statesboro",
    "sg:classifiers":[
        {
            "category":"Health Services",
            "subcategory":"Doctor",
            "type":"Services"
        }
    ],
    "sg:phone":"+1 912 871 8700",
    "sg:postcode":"30458",
    "sg:province":"GA",
    "sg:tags":[
        "physician",
        "surgeon"
    ],
    "wof:name":"East Georgia Cancer Ctr",
    "wof:placetype":"venue"
},
  "geometry": {"coordinates":[-81.76774899999999,32.413602],"type":"Point"}
}