{
  "type": "Feature",
  "properties": {
    "iso:country":"US",
    "sg:address":"4800 Castlewood Dr SW",
    "sg:city":"Lilburn",
    "sg:classifiers":[
        {
            "category":"Professional",
            "subcategory":"Advertising",
            "type":"Services"
        }
    ],
    "sg:phone":"+1 770 979 6039",
    "sg:postcode":"30047",
    "sg:province":"GA",
    "sg:tags":[
        "counselor",
        "agency"
    ],
    "wof:name":"Raintree Marketing Group",
    "wof:placetype":"venue"
},
  "geometry": {"coordinates":[-84.088059,33.819393],"type":"Point"}
}