{
  "type": "Feature",
  "properties": {
    "iso:country":"US",
    "sg:address":"2119 Fellowship Rd",
    "sg:city":"Tucker",
    "sg:classifiers":[
        {
            "category":"Organizations",
            "subcategory":"Professional Association",
            "type":"Services"
        },
        {
            "category":"Arts & Performance",
            "subcategory":"Theater",
            "type":"Entertainment"
        }
    ],
    "sg:phone":"+1 770 676 7527",
    "sg:postcode":"30084",
    "sg:province":"GA",
    "sg:tags":[
        "theatrical",
        "agency",
        "bureau"
    ],
    "wof:name":"Productions Hare-Brained",
    "wof:placetype":"venue"
},
  "geometry": {"coordinates":[-84.21635000000001,33.845686],"type":"Point"}
}