{
  "type": "Feature",
  "properties": {
    "iso:country":"US",
    "sg:address":"2000 Cheshire Brg Rd NE",
    "sg:city":"Atlanta",
    "sg:classifiers":[
        {
            "category":"Sports & Exercise",
            "subcategory":"Gym",
            "type":"Entertainment"
        }
    ],
    "sg:phone":"+1 404 636 7535",
    "sg:postcode":"30324",
    "sg:province":"GA",
    "sg:tags":[
        "yoga"
    ],
    "wof:name":"Yoga College of India",
    "wof:placetype":"venue"
},
  "geometry": {"coordinates":[-84.361198,33.820702],"type":"Point"}
}