{
  "type": "Feature",
  "properties": {
    "addr:full":"1308 W Solomon St Griffin GA 30223",
    "addr:housenumber":"1308",
    "addr:postcode":"30223",
    "addr:street":"W Solomon St",
    "iso:country":"US",
    "sg:address":"1308 W Solomon St",
    "sg:city":"Griffin",
    "sg:classifiers":[
        {
            "category":"Organizations",
            "subcategory":"Religious Organization",
            "type":"Services"
        }
    ],
    "sg:phone":"+1 770 412 1175",
    "sg:postcode":"30223",
    "sg:province":"GA",
    "wof:name":"United Holiness Church",
    "wof:placetype":"venue"
},
  "geometry": {"coordinates":[-84.286124,33.248725],"type":"Point"}
}