{
  "type": "Feature",
  "properties": {
    "addr:full":"1710 Appalachian Hwy Blue Ridge GA 30513",
    "addr:housenumber":"1710",
    "addr:postcode":"30513",
    "addr:street":"Appalachian Hwy",
    "iso:country":"US",
    "sg:address":"1710 Appalachian Hwy",
    "sg:city":"Blue Ridge",
    "sg:classifiers":[
        {
            "category":"Home & Garden",
            "subcategory":"Furniture",
            "type":"Retail Goods"
        }
    ],
    "sg:phone":"+1 706 632 9082",
    "sg:postcode":"30513",
    "sg:province":"GA",
    "sg:tags":[
        "cabinet"
    ],
    "wof:name":"Tipton Cabinets",
    "wof:placetype":"venue"
},
  "geometry": {"coordinates":[-84.33716099999999,34.840394],"type":"Point"}
}