{
  "type": "Feature",
  "properties": {
    "addr:full":"346 Manget St SE Marietta GA 30060",
    "addr:housenumber":"346",
    "addr:postcode":"30060",
    "addr:street":"Manget St Se",
    "iso:country":"US",
    "sg:address":"346 Manget St SE",
    "sg:city":"Marietta",
    "sg:classifiers":[
        {
            "category":"Retail",
            "subcategory":"Auto Repair",
            "type":"Services"
        }
    ],
    "sg:phone":"+1 770 429 8473",
    "sg:postcode":"30060",
    "sg:province":"GA",
    "sg:tags":[
        "automotive",
        "tire"
    ],
    "sg:website":"www.fairgroundauto.com",
    "wof:name":"Fairground Automotive & Tire",
    "wof:placetype":"venue"
},
  "geometry": {"coordinates":[-84.539902,33.944302],"type":"Point"}
}