{
  "type": "Feature",
  "properties": {
    "addr:full":"4620 Kimball Bridge Rd Ste 7 Alpharetta GA 30005",
    "addr:housenumber":"4620",
    "addr:postcode":"30005",
    "addr:street":"Kimball Bridge Rd Ste 7",
    "iso:country":"US",
    "sg:address":"4620 Kimball Bridge Rd Ste 7",
    "sg:city":"Alpharetta",
    "sg:classifiers":[
        {
            "category":"Retail",
            "subcategory":"Laundry & Dry Cleaning",
            "type":"Services"
        }
    ],
    "sg:phone":"+1 770 772 3050",
    "sg:postcode":"30005",
    "sg:province":"GA",
    "wof:name":"Pro Cleaners",
    "wof:placetype":"venue"
},
  "geometry": {"coordinates":[-84.225758,34.060877],"type":"Point"}
}