{
  "type": "Feature",
  "properties": {
    "addr:full":"731 Collins Hill Rd Lawrenceville GA 30045",
    "addr:housenumber":"731",
    "addr:postcode":"30045",
    "addr:street":"Collins Hill Rd",
    "iso:country":"US",
    "sg:address":"731 Collins Hill Rd",
    "sg:city":"Lawrenceville",
    "sg:classifiers":[
        {
            "category":"Home & Garden",
            "subcategory":"Building Materials",
            "type":"Retail Goods"
        }
    ],
    "sg:phone":"+1 770 963 6258",
    "sg:postcode":"30045",
    "sg:province":"GA",
    "wof:name":"Pittsburgh Paints",
    "wof:placetype":"venue"
},
  "geometry": {"coordinates":[-83.993968,33.97458],"type":"Point"}
}