{
  "type": "Feature",
  "properties": {
    "iso:country":"US",
    "sg:address":"1345 Milton Pl SE",
    "sg:city":"Atlanta",
    "sg:classifiers":[
        {
            "category":"Professional",
            "subcategory":"Employment Agencies",
            "type":"Services"
        }
    ],
    "sg:phone":"+1 404 228 2789",
    "sg:postcode":"30316",
    "sg:province":"GA",
    "sg:tags":[
        "commercial",
        "cleaning"
    ],
    "wof:name":"Wrights Building Service",
    "wof:placetype":"venue"
},
  "geometry": {"coordinates":[-84.343006,33.735584],"type":"Point"}
}