{
  "type": "Feature",
  "properties": {
    "iso:country":"US",
    "sg:address":"4550 Jonesboro Rd",
    "sg:city":"Union City",
    "sg:classifiers":[
        {
            "category":"Insurance",
            "subcategory":"Insurance Agent",
            "type":"Services"
        }
    ],
    "sg:phone":"+1 770 306 7400",
    "sg:postcode":"30291",
    "sg:province":"GA",
    "wof:name":"Direct General Ins Agency",
    "wof:placetype":"venue"
},
  "geometry": {"coordinates":[-84.53600299999999,33.56754],"type":"Point"}
}