{
  "type": "Feature",
  "properties": {
    "iso:country":"US",
    "sg:address":"208 Smithville Church Rd",
    "sg:city":"Warner Robins",
    "sg:classifiers":[
        {
            "category":"Building & Trades",
            "subcategory":"Construction",
            "type":"Services"
        }
    ],
    "sg:phone":"+1 478 256 2965",
    "sg:postcode":"31088",
    "sg:province":"GA",
    "sg:tags":[
        "home",
        "family"
    ],
    "wof:name":"Prestige Builders Inc",
    "wof:placetype":"venue"
},
  "geometry": {"coordinates":[-83.68557699999999,32.609654],"type":"Point"}
}