{
  "type": "Feature",
  "properties": {
    "iso:country":"US",
    "sg:address":"509 N Patterson St",
    "sg:city":"Valdosta",
    "sg:classifiers":[
        {
            "category":"Professional",
            "subcategory":"Lawyer & Legal Services",
            "type":"Services"
        }
    ],
    "sg:phone":"+1 229 259 0062",
    "sg:postcode":"31601",
    "sg:province":"GA",
    "sg:tags":[
        "attorney"
    ],
    "wof:name":"Valerie T Bryant",
    "wof:placetype":"venue"
},
  "geometry": {"coordinates":[-83.281744,30.836195],"type":"Point"}
}