{
  "type": "Feature",
  "properties": {
    "iso:country":"US",
    "sg:address":"1001 S Madison St",
    "sg:city":"Albany",
    "sg:classifiers":[
        {
            "category":"Organizations",
            "subcategory":"Community Association",
            "type":"Services"
        }
    ],
    "sg:phone":"+1 229 432 5745",
    "sg:postcode":"31701",
    "sg:province":"GA",
    "sg:tags":[
        "fraternal"
    ],
    "wof:name":"King Solomon Lodge #14",
    "wof:placetype":"venue"
},
  "geometry": {"coordinates":[-84.161883,31.564497],"type":"Point"}
}