{
  "type": "Feature",
  "properties": {
    "iso:country":"US",
    "sg:address":"14 Iron Brigade Dr",
    "sg:city":"Marietta",
    "sg:classifiers":[
        {
            "category":"Professional",
            "subcategory":"Business Services",
            "type":"Services"
        }
    ],
    "sg:phone":"+1 678 698 6504",
    "sg:postcode":"30064",
    "sg:province":"GA",
    "sg:tags":[
        "management",
        "advertising"
    ],
    "wof:name":"Fox Enterprises",
    "wof:placetype":"venue"
},
  "geometry": {"coordinates":[-84.618846,33.953068],"type":"Point"}
}