{
  "type": "Feature",
  "properties": {
    "iso:country":"US",
    "sg:address":"2022 Riverwood Dr",
    "sg:city":"Gainesville",
    "sg:classifiers":[
        {
            "category":"Manufacturing",
            "subcategory":"Tools & Machinery",
            "type":"Manufacturing & Wholesale Goods"
        }
    ],
    "sg:phone":"+1 770 534 2227",
    "sg:postcode":"30501",
    "sg:province":"GA",
    "sg:tags":[
        "mfg"
    ],
    "wof:name":"MD Wellness LLC",
    "wof:placetype":"venue"
},
  "geometry": {"coordinates":[-83.81437099999999,34.340576],"type":"Point"}
}