{
  "type": "Feature",
  "properties": {
    "iso:country":"US",
    "sg:address":"2920 Hearthstone Dr",
    "sg:city":"Cumming",
    "sg:classifiers":[
        {
            "category":"Building & Trades",
            "subcategory":"Construction",
            "type":"Services"
        }
    ],
    "sg:phone":"+1 770 446 7004",
    "sg:postcode":"30041",
    "sg:province":"GA",
    "sg:tags":[
        "painter"
    ],
    "sg:website":"www.pricepropainting.com",
    "wof:name":"Price Pro Painting",
    "wof:placetype":"venue"
},
  "geometry": {"coordinates":[-84.092499,34.175201],"type":"Point"}
}