{
  "type": "Feature",
  "properties": {
    "iso:country":"US",
    "sg:address":"216 Crowell Rd SE",
    "sg:city":"Conyers",
    "sg:classifiers":[
        {
            "category":"Building & Trades",
            "subcategory":"Construction",
            "type":"Services"
        }
    ],
    "sg:phone":"+1 770 760 8238",
    "sg:postcode":"30094",
    "sg:province":"GA",
    "sg:tags":[
        "house"
    ],
    "wof:name":"Campilango Construction",
    "wof:placetype":"venue"
},
  "geometry": {"coordinates":[-84.04118200000001,33.567595],"type":"Point"}
}