{
  "type": "Feature",
  "properties": {
    "iso:country":"US",
    "sg:address":"201 North Ave",
    "sg:city":"Rossville",
    "sg:classifiers":[
        {
            "category":"Building & Trades",
            "subcategory":"Plumbing",
            "type":"Services"
        }
    ],
    "sg:phone":"+1 706 858 0970",
    "sg:postcode":"30741",
    "sg:province":"GA",
    "sg:tags":[
        "contractor"
    ],
    "wof:name":"Vann-Air Systems Co",
    "wof:placetype":"venue"
},
  "geometry": {"coordinates":[-85.226894,34.963124],"type":"Point"}
}