{
  "type": "Feature",
  "properties": {
    "addr:full":"4597 Martin Ln Valdosta GA 31601",
    "addr:housenumber":"4597",
    "addr:postcode":"31601",
    "addr:street":"Martin Ln",
    "iso:country":"US",
    "sg:address":"4597 Martin Ln",
    "sg:city":"Valdosta",
    "sg:classifiers":[
        {
            "category":"Transit Center",
            "subcategory":"Freight",
            "type":"Transportation"
        },
        {
            "category":"Freight",
            "type":"Transportation"
        }
    ],
    "sg:phone":"+1 229 244 4436",
    "sg:postcode":"31601",
    "sg:province":"GA",
    "sg:tags":[
        "local",
        "trucking-motor",
        "trucking"
    ],
    "wof:name":"Jw Trucking",
    "wof:placetype":"venue"
},
  "geometry": {"coordinates":[-83.445081,30.788638],"type":"Point"}
}