{
  "type": "Feature",
  "properties": {
    "iso:country":"US",
    "sg:address":"311 Pete Phillips Dr",
    "sg:city":"Vidalia",
    "sg:classifiers":[
        {
            "category":"Health Services",
            "subcategory":"Dentist",
            "type":"Services"
        }
    ],
    "sg:phone":"+1 912 537 7048",
    "sg:postcode":"30474",
    "sg:province":"GA",
    "sg:website":"http://www.dentalcentervidalia.com",
    "wof:name":"Dental Center Of Vidalia.",
    "wof:placetype":"venue"
},
  "geometry": {"coordinates":[-82.368623,32.20008],"type":"Point"}
}