{
  "type": "Feature",
  "properties": {
    "addr:full":"50 S Main St Clayton GA 30525",
    "addr:housenumber":"50",
    "addr:postcode":"30525",
    "addr:street":"S Main St",
    "iso:country":"US",
    "sg:address":"50 S Main St",
    "sg:city":"Clayton",
    "sg:classifiers":[
        {
            "category":"Shopping",
            "subcategory":"Hobbies, Toys, & Games",
            "type":"Retail Goods"
        },
        {
            "category":"Shopping",
            "subcategory":"Crafts & Fabrics",
            "type":"Retail Goods"
        }
    ],
    "sg:phone":"+1 706 782 0036",
    "sg:postcode":"30525",
    "sg:province":"GA",
    "sg:tags":[
        "shop",
        "hobby",
        "model",
        "supply"
    ],
    "wof:name":"Mountain Crafts Co-Op",
    "wof:placetype":"venue"
},
  "geometry": {"coordinates":[-83.401031,34.877328],"type":"Point"}
}