{
  "type": "Feature",
  "properties": {
    "addr:full":"9782 River Rd Camilla GA 31730",
    "addr:housenumber":"9782",
    "addr:postcode":"31730",
    "addr:street":"River Rd",
    "iso:country":"US",
    "sg:address":"9782 River Rd",
    "sg:city":"Camilla",
    "sg:classifiers":[
        {
            "category":"Farming",
            "subcategory":"Dairy Farm",
            "type":"Manufacturing & Wholesale Goods"
        }
    ],
    "sg:phone":"+1 229 336 7702",
    "sg:postcode":"31730",
    "sg:province":"GA",
    "wof:name":"Lamar Cooper",
    "wof:placetype":"venue"
},
  "geometry": {"coordinates":[-84.20843000000001,31.315931],"type":"Point"}
}