{
  "type": "Feature",
  "properties": {
    "addr:full":"3197 Summer Rd Tunnel Hill GA 30755",
    "addr:housenumber":"3197",
    "addr:postcode":"30755",
    "addr:street":"Summer Rd",
    "iso:country":"US",
    "sg:address":"3197 Summer Rd",
    "sg:city":"Tunnel Hill",
    "sg:classifiers":[
        {
            "category":"Professional",
            "subcategory":"Business Services",
            "type":"Services"
        }
    ],
    "sg:phone":"+1 706 673 6473",
    "sg:postcode":"30755",
    "sg:province":"GA",
    "wof:name":"Haney Enterprises Inc",
    "wof:placetype":"venue"
},
  "geometry": {"coordinates":[-85.014022,34.871193],"type":"Point"}
}