{
  "type": "Feature",
  "properties": {
    "addr:full":"1202 Haven Brook Way NE Atlanta GA 30319",
    "addr:housenumber":"1202",
    "addr:postcode":"30319",
    "addr:street":"Haven Brook Way Ne",
    "iso:country":"US",
    "sg:address":"1202 Haven Brook Way NE",
    "sg:city":"Atlanta",
    "sg:classifiers":[
        {
            "category":"Social Services",
            "type":"Services"
        }
    ],
    "sg:phone":"+1 404 233 6782",
    "sg:postcode":"30319",
    "sg:province":"GA",
    "wof:name":"Visits Inc",
    "wof:placetype":"venue"
},
  "geometry": {"coordinates":[-84.34056200000001,33.876647],"type":"Point"}
}