{
  "type": "Feature",
  "properties": {
    "addr:full":"15 Rivershyre Cir Lawrenceville GA 30043",
    "addr:housenumber":"15",
    "addr:postcode":"30043",
    "addr:street":"Rivershyre Cir",
    "iso:country":"US",
    "sg:address":"15 Rivershyre Cir",
    "sg:city":"Lawrenceville",
    "sg:classifiers":[
        {
            "category":"Building & Trades",
            "subcategory":"Cleaning & Sanitation",
            "type":"Services"
        }
    ],
    "sg:phone":"+1 770 513 7329",
    "sg:postcode":"30043",
    "sg:province":"GA",
    "sg:tags":[
        "maintenance"
    ],
    "wof:name":"Jover Miguel F Et Al",
    "wof:placetype":"venue"
},
  "geometry": {"coordinates":[-84.00390400000001,33.990853],"type":"Point"}
}