{
  "type": "Feature",
  "properties": {
    "iso:country":"US",
    "sg:address":"6380 Pleasant Dr",
    "sg:city":"Winston",
    "sg:classifiers":[
        {
            "category":"Bus Charters",
            "type":"Transportation"
        }
    ],
    "sg:phone":"+1 770 575 1098",
    "sg:postcode":"30187",
    "sg:province":"GA",
    "wof:name":"Sunways",
    "wof:placetype":"venue"
},
  "geometry": {"coordinates":[-84.783006,33.709395],"type":"Point"}
}