{
  "type": "Feature",
  "properties": {
    "iso:country":"US",
    "sg:address":"315 W Solomon St",
    "sg:city":"Griffin",
    "sg:classifiers":[
        {
            "category":"Place Of Worship",
            "type":"Public Place"
        }
    ],
    "sg:phone":"+1 770 468 0465",
    "sg:postcode":"30223",
    "sg:province":"GA",
    "sg:tags":[
        "church"
    ],
    "wof:name":"Journey Church",
    "wof:placetype":"venue"
},
  "geometry": {"coordinates":[-84.26719900000001,33.248677],"type":"Point"}
}