{
  "type": "Feature",
  "properties": {
    "iso:country":"US",
    "sg:address":"6055 Barfield Rd NE",
    "sg:city":"Atlanta",
    "sg:classifiers":[
        {
            "category":"Freight",
            "type":"Transportation"
        }
    ],
    "sg:phone":"+1 404 257 0399",
    "sg:postcode":"30328",
    "sg:province":"GA",
    "sg:tags":[
        "arrangement"
    ],
    "wof:name":"Exel Transportation Services",
    "wof:placetype":"venue"
},
  "geometry": {"coordinates":[-84.35983899999999,33.91909],"type":"Point"}
}