{
  "type": "Feature",
  "properties": {
    "iso:country":"US",
    "sg:address":"5809 Joe Frank Harris Pkwy NW",
    "sg:city":"Adairsville",
    "sg:classifiers":[
        {
            "category":"Autos & Motor Vehicles",
            "subcategory":"Automobile Sales",
            "type":"Retail Goods"
        }
    ],
    "sg:phone":"+1 770 769 9395",
    "sg:postcode":"30103",
    "sg:province":"GA",
    "sg:tags":[
        "car",
        "dealer"
    ],
    "wof:name":"Good Buys Auto Sales Inc",
    "wof:placetype":"venue"
},
  "geometry": {"coordinates":[-84.92655499999999,34.366807],"type":"Point"}
}