{
  "type": "Feature",
  "properties": {
    "addr:full":"551 Thornton Rd Lithia Springs GA 30122",
    "addr:housenumber":"551",
    "addr:postcode":"30122",
    "addr:street":"Thornton Rd",
    "iso:country":"US",
    "sg:address":"551 Thornton Rd",
    "sg:city":"Lithia Springs",
    "sg:classifiers":[
        {
            "category":"Insurance",
            "subcategory":"Insurance Agent",
            "type":"Services"
        }
    ],
    "sg:phone":"+1 770 739 3500",
    "sg:postcode":"30122",
    "sg:province":"GA",
    "sg:tags":[
        "claim"
    ],
    "wof:name":"State Farm Insurance",
    "wof:placetype":"venue"
},
  "geometry": {"coordinates":[-84.62589,33.790198],"type":"Point"}
}