{
  "type": "Feature",
  "properties": {
    "addr:full":"205 Banks Station Fayetteville GA 30214",
    "addr:housenumber":"205",
    "addr:postcode":"30214",
    "addr:street":"Banks Station",
    "iso:country":"US",
    "sg:address":"205 Banks Station",
    "sg:city":"Fayetteville",
    "sg:classifiers":[
        {
            "category":"Banks & Credit Unions",
            "subcategory":"Bank",
            "type":"Services"
        }
    ],
    "sg:phone":"+1 770 716 0444",
    "sg:postcode":"30214",
    "sg:province":"GA",
    "sg:tags":[
        "personal",
        "institution"
    ],
    "wof:name":"Beneficial",
    "wof:placetype":"venue"
},
  "geometry": {"coordinates":[-84.438064,33.469674],"type":"Point"}
}