{
  "type": "Feature",
  "properties": {
    "addr:full":"3185 Vineville Ave Macon GA 31204",
    "addr:housenumber":"3185",
    "addr:postcode":"31204",
    "addr:street":"Vineville Ave",
    "iso:country":"US",
    "sg:address":"3185 Vineville Ave",
    "sg:city":"Macon",
    "sg:classifiers":[
        {
            "category":"Autos & Motor Vehicles",
            "subcategory":"Auto Supplies",
            "type":"Retail Goods"
        }
    ],
    "sg:phone":"+1 478 474 7850",
    "sg:postcode":"31204",
    "sg:province":"GA",
    "sg:tags":[
        "parts",
        "store",
        "accessory"
    ],
    "wof:name":"Autozone 182",
    "wof:placetype":"venue"
},
  "geometry": {"coordinates":[-83.675845,32.85174],"type":"Point"}
}