{
  "type": "Feature",
  "properties": {
    "iso:country":"US",
    "sg:address":"122 E Liberty St",
    "sg:city":"Savannah",
    "sg:classifiers":[
        {
            "category":"Restaurant",
            "type":"Food & Drink"
        }
    ],
    "sg:menulink":"http://www.allmenus.com/ga/savannah/284740-j-christophers/menu/",
    "sg:phone":"+1 912 236 7494",
    "sg:postcode":"31401",
    "sg:province":"GA",
    "sg:tags":[
        "american"
    ],
    "wof:name":"J. Christopher's",
    "wof:placetype":"venue"
},
  "geometry": {"coordinates":[-81.091482,32.074495],"type":"Point"}
}