{
  "type": "Feature",
  "properties": {
    "addr:full":"910 Oak Valley Rd Dacula GA 30019",
    "addr:housenumber":"910",
    "addr:postcode":"ga 30019",
    "addr:street":"Oak Valley Rd",
    "iso:country":"US",
    "sg:address":"910 Oak Valley Rd",
    "sg:city":"Dacula",
    "sg:classifiers":[
        {
            "category":"Building & Trades",
            "subcategory":"Cleaning & Sanitation",
            "type":"Services"
        }
    ],
    "sg:phone":"+1 770 338 0842",
    "sg:postcode":"30019",
    "sg:province":"GA",
    "sg:tags":[
        "maintenance"
    ],
    "wof:name":"Veska Petrakieva",
    "wof:placetype":"venue"
},
  "geometry": {"coordinates":[-83.878305,33.972626],"type":"Point"}
}