{
  "type": "Feature",
  "properties": {
    "addr:full":"3938 Stratford Cir Valdosta GA 31605",
    "addr:housenumber":"3938",
    "addr:postcode":"31605",
    "addr:street":"Stratford Cir",
    "iso:country":"US",
    "sg:address":"3938 Stratford Cir",
    "sg:city":"Valdosta",
    "sg:classifiers":[
        {
            "category":"Building & Trades",
            "subcategory":"Construction",
            "type":"Services"
        }
    ],
    "sg:phone":"+1 229 219 7899",
    "sg:postcode":"31605",
    "sg:province":"GA",
    "sg:tags":[
        "contractor"
    ],
    "wof:name":"Ceramic Tile & More",
    "wof:placetype":"venue"
},
  "geometry": {"coordinates":[-83.242525,30.927903],"type":"Point"}
}