{
  "type": "Feature",
  "properties": {
    "iso:country":"US",
    "sg:address":"322 Atlanta Rd",
    "sg:city":"Gainesville",
    "sg:classifiers":[
        {
            "category":"Real Estate",
            "subcategory":"Real Estate Agent",
            "type":"Services"
        }
    ],
    "sg:phone":"+1 770 536 4757",
    "sg:postcode":"30501",
    "sg:province":"GA",
    "wof:name":"Westside Investment Corp",
    "wof:placetype":"venue"
},
  "geometry": {"coordinates":[-83.838792,34.284002],"type":"Point"}
}