{
  "type": "Feature",
  "properties": {
    "iso:country":"US",
    "sg:address":"3261 Sugar Creek Falls Ave SE",
    "sg:city":"Atlanta",
    "sg:classifiers":[
        {
            "category":"Shopping",
            "subcategory":"Computers & Home Electronics",
            "type":"Retail Goods"
        }
    ],
    "sg:phone":"+1 404 212 8482",
    "sg:postcode":"30316",
    "sg:province":"GA",
    "sg:tags":[
        "equipment",
        "dealer"
    ],
    "wof:name":"Jones Computer Systems",
    "wof:placetype":"venue"
},
  "geometry": {"coordinates":[-84.305004,33.688713],"type":"Point"}
}