{
  "type": "Feature",
  "properties": {
    "iso:country":"US",
    "sg:address":"4870 Leland Dr",
    "sg:city":"Cumming",
    "sg:classifiers":[
        {
            "category":"Wholesale",
            "subcategory":"Construction Materials",
            "type":"Manufacturing & Wholesale Goods"
        }
    ],
    "sg:phone":"+1 770 889 5244",
    "sg:postcode":"30041",
    "sg:province":"GA",
    "sg:tags":[
        "sand",
        "gravel"
    ],
    "wof:name":"Buckhorn Sand Mfg",
    "wof:placetype":"venue"
},
  "geometry": {"coordinates":[-84.05018200000001,34.27836],"type":"Point"}
}