{
  "type": "Feature",
  "properties": {
    "iso:country":"US",
    "sg:address":"4003 Oak Harbour Ct",
    "sg:city":"Gainesville",
    "sg:classifiers":[
        {
            "category":"Building & Trades",
            "subcategory":"Construction",
            "type":"Services"
        }
    ],
    "sg:phone":"+1 770 533 9388",
    "sg:postcode":"30506",
    "sg:province":"GA",
    "sg:tags":[
        "contractor"
    ],
    "wof:name":"L S Building Svc Inc",
    "wof:placetype":"venue"
},
  "geometry": {"coordinates":[-83.868177,34.384408],"type":"Point"}
}