{
  "type": "Feature",
  "properties": {
    "iso:country":"US",
    "sg:address":"5 Grimsley Rd",
    "sg:city":"Tifton",
    "sg:classifiers":[
        {
            "category":"Professional",
            "type":"Services"
        }
    ],
    "sg:phone":"+1 229 387 6987",
    "sg:postcode":"31794",
    "sg:province":"GA",
    "wof:name":"Danny White",
    "wof:placetype":"venue"
},
  "geometry": {"coordinates":[-83.45477700000001,31.438331],"type":"Point"}
}