{
  "type": "Feature",
  "properties": {
    "iso:country":"US",
    "sg:address":"1700 Montreal Cir",
    "sg:city":"Tucker",
    "sg:classifiers":[
        {
            "category":"Real Estate",
            "subcategory":"Real Estate Services",
            "type":"Services"
        }
    ],
    "sg:phone":"+1 770 934 2700",
    "sg:postcode":"30084",
    "sg:province":"GA",
    "wof:name":"Summers Company the Rl Est",
    "wof:placetype":"venue"
},
  "geometry": {"coordinates":[-84.25279999999999,33.832699],"type":"Point"}
}