{
  "type": "Feature",
  "properties": {
    "addr:full":"1700 Norman Dr Valdosta GA 31601",
    "addr:housenumber":"1700",
    "addr:postcode":"31601",
    "addr:street":"Norman Dr",
    "iso:country":"US",
    "sg:address":"1700 Norman Dr",
    "sg:city":"Valdosta",
    "sg:classifiers":[
        {
            "category":"Restaurant",
            "type":"Food & Drink"
        }
    ],
    "sg:menulink":"http://www.allmenus.com/ga/valdosta/103554-ruby-tuesdays/menu/",
    "sg:phone":"+1 229 247 8947",
    "sg:postcode":"31601",
    "sg:province":"GA",
    "sg:tags":[
        "burger",
        "american"
    ],
    "wof:name":"Ruby Tuesdays",
    "wof:placetype":"venue"
},
  "geometry": {"coordinates":[-83.318718,30.841822],"type":"Point"}
}