{
  "type": "Feature",
  "properties": {
    "addr:full":"8005 Meadowsweet Trce Roswell GA 30076",
    "addr:housenumber":"8005",
    "addr:postcode":"30076",
    "addr:street":"Meadowsweet Trce",
    "iso:country":"US",
    "sg:address":"8005 Meadowsweet Trce",
    "sg:city":"Roswell",
    "sg:classifiers":[
        {
            "category":"Professional",
            "subcategory":"Art Services",
            "type":"Services"
        }
    ],
    "sg:phone":"+1 770 594 9098",
    "sg:postcode":"30076",
    "sg:province":"GA",
    "sg:tags":[
        "commercial",
        "design"
    ],
    "wof:name":"Art & Design Inc",
    "wof:placetype":"venue"
},
  "geometry": {"coordinates":[-84.303319,34.003366],"type":"Point"}
}