{
  "type": "Feature",
  "properties": {
    "addr:full":"676 Highway 138 SW Riverdale GA 30274",
    "addr:housenumber":"676",
    "addr:postcode":"30274",
    "addr:street":"Highway 138 Sw",
    "iso:country":"US",
    "sg:address":"676 Highway 138 SW",
    "sg:city":"Riverdale",
    "sg:classifiers":[
        {
            "category":"Autos & Motor Vehicles",
            "subcategory":"Auto Supplies",
            "type":"Retail Goods"
        }
    ],
    "sg:phone":"+1 770 997 9208",
    "sg:postcode":"30274",
    "sg:province":"GA",
    "sg:tags":[
        "tire"
    ],
    "sg:website":"www.kauffmantire.com",
    "wof:name":"Kauffman Tire",
    "wof:placetype":"venue"
},
  "geometry": {"coordinates":[-84.412948,33.548593],"type":"Point"}
}