{
  "type": "Feature",
  "properties": {
    "iso:country":"US",
    "sg:address":"7909 Smith Rd",
    "sg:city":"Winston",
    "sg:classifiers":[
        {
            "category":"Manufacturing",
            "subcategory":"Metals",
            "type":"Manufacturing & Wholesale Goods"
        }
    ],
    "sg:phone":"+1 770 942 0027",
    "sg:postcode":"30180",
    "sg:province":"GA",
    "sg:tags":[
        "downspouts",
        "gutter"
    ],
    "wof:name":"Sheehan Metal Products Inc",
    "wof:placetype":"venue"
},
  "geometry": {"coordinates":[-84.84396599999999,33.728345],"type":"Point"}
}