{
  "type": "Feature",
  "properties": {
    "addr:full":"3685 Braselton Hwy Dacula GA 30019",
    "addr:housenumber":"3685",
    "addr:postcode":"ga 30019",
    "addr:street":"Braselton Hwy",
    "iso:country":"US",
    "sg:address":"3685 Braselton Hwy",
    "sg:city":"Dacula",
    "sg:classifiers":[
        {
            "category":"Ice Cream",
            "type":"Food & Drink"
        }
    ],
    "sg:menulink":"http://www.allmenus.com/ga/dacula-rocky-creek/221369-carvel/menu/",
    "sg:phone":"+1 770 945 1750",
    "sg:postcode":"30019",
    "sg:province":"GA",
    "sg:tags":[
        "american"
    ],
    "wof:name":"Carvel",
    "wof:placetype":"venue"
},
  "geometry": {"coordinates":[-83.90205,34.0696],"type":"Point"}
}