{
  "type": "Feature",
  "properties": {
    "iso:country":"US",
    "sg:address":"5809 Monarda Ct NW",
    "sg:city":"Acworth",
    "sg:classifiers":[
        {
            "category":"Professional",
            "subcategory":"Computer Services",
            "type":"Services"
        }
    ],
    "sg:phone":"+1 770 517 7010",
    "sg:postcode":"30102",
    "sg:province":"GA",
    "sg:tags":[
        "datum"
    ],
    "wof:name":"Campbell Creations",
    "wof:placetype":"venue"
},
  "geometry": {"coordinates":[-84.57118199999999,34.065734],"type":"Point"}
}