{
  "type": "Feature",
  "properties": {
    "iso:country":"US",
    "sg:address":"1690 S Lumpkin St",
    "sg:city":"Athens",
    "sg:classifiers":[
        {
            "category":"Real Estate",
            "subcategory":"Real Estate Agent",
            "type":"Services"
        }
    ],
    "sg:phone":"+1 706 543 8299",
    "sg:postcode":"30606",
    "sg:province":"GA",
    "sg:website":"www.athensclassicproperties.com",
    "wof:name":"Athens Classic Properties Inc",
    "wof:placetype":"venue"
},
  "geometry": {"coordinates":[-83.387511,33.937645],"type":"Point"}
}