{
  "type": "Feature",
  "properties": {
    "addr:full":"115 Old Muse Rd Carrollton GA 30116",
    "addr:housenumber":"115",
    "addr:postcode":"30116",
    "addr:street":"Old Muse Rd",
    "iso:country":"US",
    "sg:address":"115 Old Muse Rd",
    "sg:city":"Carrollton",
    "sg:classifiers":[
        {
            "category":"Education",
            "subcategory":"School",
            "type":"Public Place"
        }
    ],
    "sg:phone":"+1 770 214 8848",
    "sg:postcode":"30116",
    "sg:province":"GA",
    "sg:tags":[
        "elementary"
    ],
    "sg:website":"www.carrollcountyschools.com",
    "wof:name":"Sharp Creek Elementary School",
    "wof:placetype":"venue"
},
  "geometry": {"coordinates":[-85.04656,33.649205],"type":"Point"}
}