{
  "type": "Feature",
  "properties": {
    "addr:full":"2453 Emery Hwy Macon GA 31217",
    "addr:housenumber":"2453",
    "addr:postcode":"31217",
    "addr:street":"Emery Hwy",
    "iso:country":"US",
    "sg:address":"2453 Emery Hwy",
    "sg:city":"Macon",
    "sg:classifiers":[
        {
            "category":"Utilities",
            "subcategory":"Refuse",
            "type":"Services"
        }
    ],
    "sg:phone":"+1 478 745 6281",
    "sg:postcode":"31217",
    "sg:province":"GA",
    "sg:tags":[
        "system"
    ],
    "wof:name":"Bobby Posey",
    "wof:placetype":"venue"
},
  "geometry": {"coordinates":[-83.58569300000001,32.841645],"type":"Point"}
}