{
  "type": "Feature",
  "properties": {
    "iso:country":"US",
    "sg:address":"739 Main St",
    "sg:city":"Stone Mountain",
    "sg:classifiers":[
        {
            "category":"Manufacturing",
            "subcategory":"Printing",
            "type":"Manufacturing & Wholesale Goods"
        }
    ],
    "sg:phone":"+1 678 476 9670",
    "sg:postcode":"30083",
    "sg:province":"GA",
    "sg:tags":[
        "newspaper",
        "publishing"
    ],
    "wof:name":"An Nour",
    "wof:placetype":"venue"
},
  "geometry": {"coordinates":[-84.169511,33.801184],"type":"Point"}
}