{
  "type": "Feature",
  "properties": {
    "iso:country":"US",
    "sg:address":"1825 Windy Hill Rd SE",
    "sg:city":"Smyrna",
    "sg:classifiers":[
        {
            "category":"Sports & Exercise",
            "subcategory":"Golf",
            "type":"Entertainment"
        }
    ],
    "sg:phone":"+1 770 434 6331",
    "sg:postcode":"30080",
    "sg:province":"GA",
    "wof:name":"Legacy Golf Windy Hill",
    "wof:placetype":"venue"
},
  "geometry": {"coordinates":[-84.4991,33.896301],"type":"Point"}
}