{
  "type": "Feature",
  "properties": {
    "addr:full":"4490 Commerce Cir SW Atlanta GA 30336",
    "addr:housenumber":"4490",
    "addr:postcode":"30336",
    "addr:street":"Commerce Cir Sw",
    "iso:country":"US",
    "sg:address":"4490 Commerce Cir SW",
    "sg:city":"Atlanta",
    "sg:classifiers":[
        {
            "category":"Wholesale",
            "subcategory":"Beer",
            "type":"Manufacturing & Wholesale Goods"
        }
    ],
    "sg:phone":"+1 404 505 0002",
    "sg:postcode":"30336",
    "sg:province":"GA",
    "sg:tags":[
        "equipment",
        "maker",
        "supply"
    ],
    "sg:website":"http://www.crosby-baker.com",
    "wof:name":"Crosby & Baker",
    "wof:placetype":"venue"
},
  "geometry": {"coordinates":[-84.53322799999999,33.75967],"type":"Point"}
}