{
  "type": "Feature",
  "properties": {
    "addr:full":"123 Kathi Ave Fayetteville GA 30214",
    "addr:housenumber":"123",
    "addr:postcode":"30214",
    "addr:street":"Kathi Ave",
    "iso:country":"US",
    "sg:address":"123 Kathi Ave",
    "sg:city":"Fayetteville",
    "sg:classifiers":[
        {
            "category":"Shopping",
            "subcategory":"Optical Goods",
            "type":"Retail Goods"
        }
    ],
    "sg:phone":"+1 678 817 4631",
    "sg:postcode":"30214",
    "sg:province":"GA",
    "wof:name":"National Vision",
    "wof:placetype":"venue"
},
  "geometry": {"coordinates":[-84.450603,33.456355],"type":"Point"}
}