{
  "type": "Feature",
  "properties": {
    "addr:full":"540 W Crossville Rd Roswell GA 30075",
    "addr:housenumber":"540",
    "addr:postcode":"30075",
    "addr:street":"W Crossville Rd",
    "iso:country":"US",
    "sg:address":"540 W Crossville Rd",
    "sg:city":"Roswell",
    "sg:classifiers":[
        {
            "category":"Banks & Credit Unions",
            "subcategory":"Investment Brokerage",
            "type":"Services"
        }
    ],
    "sg:phone":"+1 770 993 1153",
    "sg:postcode":"30075",
    "sg:province":"GA",
    "sg:tags":[
        "security"
    ],
    "wof:name":"Edwards Jones Investments",
    "wof:placetype":"venue"
},
  "geometry": {"coordinates":[-84.37779999999999,34.055611],"type":"Point"}
}