{
  "type": "Feature",
  "properties": {
    "iso:country":"US",
    "sg:address":"1809 Lightwood Ln NW",
    "sg:city":"Acworth",
    "sg:classifiers":[
        {
            "category":"Manufacturing",
            "subcategory":"Printing",
            "type":"Manufacturing & Wholesale Goods"
        }
    ],
    "sg:phone":"+1 770 529 0664",
    "sg:postcode":"30102",
    "sg:province":"GA",
    "sg:tags":[
        "publishes",
        "pamphlet"
    ],
    "wof:name":"All About Atlanta Inc",
    "wof:placetype":"venue"
},
  "geometry": {"coordinates":[-84.604159,34.07349],"type":"Point"}
}