{
  "type": "Feature",
  "properties": {
    "addr:full":"2088 Chrysler Dr NE Atlanta GA 30345",
    "addr:housenumber":"2088",
    "addr:postcode":"30345",
    "addr:street":"Chrysler Dr Ne",
    "iso:country":"US",
    "sg:address":"2088 Chrysler Dr NE",
    "sg:city":"Atlanta",
    "sg:classifiers":[
        {
            "category":"Professional",
            "subcategory":"Management & Consulting",
            "type":"Services"
        }
    ],
    "sg:phone":"+1 404 325 7117",
    "sg:postcode":"30345",
    "sg:province":"GA",
    "sg:tags":[
        "consultant",
        "health"
    ],
    "wof:name":"Program Management Consultants",
    "wof:placetype":"venue"
},
  "geometry": {"coordinates":[-84.298942,33.843352],"type":"Point"}
}