{
  "type": "Feature",
  "properties": {
    "iso:country":"US",
    "sg:address":"129 Anita Pl",
    "sg:city":"Mableton",
    "sg:classifiers":[
        {
            "category":"Manufacturing",
            "subcategory":"Lumber",
            "type":"Manufacturing & Wholesale Goods"
        }
    ],
    "sg:phone":"+1 770 745 2761",
    "sg:postcode":"30126",
    "sg:province":"GA",
    "sg:tags":[
        "logging"
    ],
    "wof:name":"All Pro Stump Grinding",
    "wof:placetype":"venue"
},
  "geometry": {"coordinates":[-84.55017700000001,33.829743],"type":"Point"}
}