{
  "type": "Feature",
  "properties": {
    "iso:country":"US",
    "sg:address":"721 Miami Cir NE",
    "sg:city":"Atlanta",
    "sg:classifiers":[
        {
            "category":"Wholesale",
            "subcategory":"Furniture",
            "type":"Manufacturing & Wholesale Goods"
        },
        {
            "category":"Home & Garden",
            "subcategory":"Furniture",
            "type":"Retail Goods"
        }
    ],
    "sg:phone":"+1 404 841 5777",
    "sg:postcode":"30324",
    "sg:province":"GA",
    "sg:tags":[
        "store",
        "furniture-wholesale",
        "manufacturer"
    ],
    "wof:name":"Belvedere/Furniture",
    "wof:placetype":"venue"
},
  "geometry": {"coordinates":[-84.366496,33.828652],"type":"Point"}
}