{
  "type": "Feature",
  "properties": {
    "iso:country":"US",
    "sg:address":"3531 Memorial Dr",
    "sg:city":"Decatur",
    "sg:classifiers":[
        {
            "category":"Shopping",
            "subcategory":"Shoes",
            "type":"Retail Goods"
        }
    ],
    "sg:phone":"+1 404 286 4956",
    "sg:postcode":"30032",
    "sg:province":"GA",
    "sg:tags":[
        "store"
    ],
    "wof:name":"Shoe Time International Inc Dba Shoetime 22",
    "wof:placetype":"venue"
},
  "geometry": {"coordinates":[-84.26889799999999,33.754299],"type":"Point"}
}