{
  "type": "Feature",
  "properties": {
    "addr:full":"1719 Mccook Ct NW Kennesaw GA 30144",
    "addr:housenumber":"1719",
    "addr:postcode":"30144",
    "addr:street":"Mccook Ct Nw",
    "iso:country":"US",
    "sg:address":"1719 Mccook Ct NW",
    "sg:city":"Kennesaw",
    "sg:classifiers":[
        {
            "category":"Communications",
            "subcategory":"Film & Video Production",
            "type":"Services"
        },
        {
            "category":"Communications",
            "subcategory":"Radio Station",
            "type":"Services"
        }
    ],
    "sg:phone":"+1 770 420 0762",
    "sg:postcode":"30144",
    "sg:province":"GA",
    "sg:tags":[
        "motion",
        "picture",
        "medium",
        "broker"
    ],
    "wof:name":"Forrester Media Inc",
    "wof:placetype":"venue"
},
  "geometry": {"coordinates":[-84.565003,33.996682],"type":"Point"}
}