{
  "type": "Feature",
  "properties": {
    "addr:full":"5869 Washington Rd Appling GA 30802",
    "addr:housenumber":"5869",
    "addr:postcode":"30802",
    "addr:street":"Washington Rd",
    "iso:country":"US",
    "sg:address":"5869 Washington Rd",
    "sg:city":"Appling",
    "sg:classifiers":[
        {
            "category":"Utilities",
            "subcategory":"Telephone",
            "type":"Services"
        }
    ],
    "sg:phone":"+1 706 541 0308",
    "sg:postcode":"30802",
    "sg:province":"GA",
    "sg:tags":[
        "telecommunication"
    ],
    "wof:name":"Crown Castle USA",
    "wof:placetype":"venue"
},
  "geometry": {"coordinates":[-82.27045,33.618091],"type":"Point"}
}