{
  "type": "Feature",
  "properties": {
    "addr:full":"1267 Cobb Industrial Dr Marietta GA 30066",
    "addr:housenumber":"1267",
    "addr:postcode":"30066",
    "addr:street":"Cobb Industrial Dr",
    "iso:country":"US",
    "sg:address":"1267 Cobb Industrial Dr",
    "sg:city":"Marietta",
    "sg:classifiers":[
        {
            "category":"Manufacturing",
            "subcategory":"Food",
            "type":"Manufacturing & Wholesale Goods"
        }
    ],
    "sg:phone":"+1 770 428 5555",
    "sg:postcode":"30066",
    "sg:province":"GA",
    "sg:tags":[
        "tea",
        "coffee",
        "blend",
        "package"
    ],
    "wof:name":"Southern Tea",
    "wof:placetype":"venue"
},
  "geometry": {"coordinates":[-84.531502,33.980301],"type":"Point"}
}