{
  "type": "Feature",
  "properties": {
    "iso:country":"US",
    "sg:address":"211 Piney Woods Rd",
    "sg:city":"Ellijay",
    "sg:classifiers":[
        {
            "category":"Shopping",
            "subcategory":"Beauty & Cosmetics",
            "type":"Retail Goods"
        }
    ],
    "sg:phone":"+1 706 635 7311",
    "sg:postcode":"30536",
    "sg:province":"GA",
    "sg:tags":[
        "merchandise"
    ],
    "wof:name":"Mary Kay Consultant",
    "wof:placetype":"venue"
},
  "geometry": {"coordinates":[-84.46158200000001,34.676694],"type":"Point"}
}