{
  "type": "Feature",
  "properties": {
    "addr:full":"130 Gerri Dr Newnan GA 30263",
    "addr:housenumber":"130",
    "addr:postcode":"30263",
    "addr:street":"Gerri Dr",
    "iso:country":"US",
    "sg:address":"130 Gerri Dr",
    "sg:city":"Newnan",
    "sg:classifiers":[
        {
            "category":"Building & Trades",
            "subcategory":"Construction",
            "type":"Services"
        }
    ],
    "sg:phone":"+1 770 252 2898",
    "sg:postcode":"30263",
    "sg:province":"GA",
    "sg:tags":[
        "roofing",
        "contractor"
    ],
    "wof:name":"Brazos Urethane Inc",
    "wof:placetype":"venue"
},
  "geometry": {"coordinates":[-84.911969,33.386113],"type":"Point"}
}