{
  "type": "Feature",
  "properties": {
    "iso:country":"US",
    "sg:address":"111 Grove Ave SE",
    "sg:city":"Lindale",
    "sg:classifiers":[
        {
            "category":"Government",
            "subcategory":"Office",
            "type":"Public Place"
        }
    ],
    "sg:phone":"+1 706 295 6349",
    "sg:postcode":"30147",
    "sg:province":"GA",
    "wof:name":"Group Home",
    "wof:placetype":"venue"
},
  "geometry": {"coordinates":[-85.174211,34.185583],"type":"Point"}
}