{
  "type": "Feature",
  "properties": {
    "iso:country":"US",
    "sg:address":"1100 Eagles Landing Pkwy",
    "sg:city":"Stockbridge",
    "sg:classifiers":[
        {
            "category":"Social Services",
            "subcategory":"Job Training",
            "type":"Services"
        }
    ],
    "sg:phone":"+1 770 474 8177",
    "sg:postcode":"30281",
    "sg:province":"GA",
    "sg:tags":[
        "technician",
        "assistant",
        "school",
        "dental",
        "medical"
    ],
    "wof:name":"National Trichology Training Institute",
    "wof:placetype":"venue"
},
  "geometry": {"coordinates":[-84.224709,33.510181],"type":"Point"}
}