{
  "type": "Feature",
  "properties": {
    "iso:country":"US",
    "sg:address":"1083 Euclid Ave NE",
    "sg:city":"Atlanta",
    "sg:classifiers":[
        {
            "category":"Retail",
            "subcategory":"Auto Repair",
            "type":"Services"
        }
    ],
    "sg:phone":"+1 404 688 2123",
    "sg:postcode":"30307",
    "sg:province":"GA",
    "sg:tags":[
        "general"
    ],
    "wof:name":"Wilsons Automotive",
    "wof:placetype":"venue"
},
  "geometry": {"coordinates":[-84.34917,33.765337],"type":"Point"}
}