{
  "type": "Feature",
  "properties": {
    "iso:country":"US",
    "sg:address":"10339 Flat Shoals Rd",
    "sg:city":"Covington",
    "sg:classifiers":[
        {
            "category":"Building & Trades",
            "subcategory":"Construction",
            "type":"Services"
        }
    ],
    "sg:phone":"+1 770 786 8079",
    "sg:postcode":"30014",
    "sg:province":"GA",
    "sg:tags":[
        "house"
    ],
    "wof:name":"MD Payne Home & Farm Service",
    "wof:placetype":"venue"
},
  "geometry": {"coordinates":[-83.87248099999999,33.570223],"type":"Point"}
}