{
  "type": "Feature",
  "properties": {
    "iso:country":"US",
    "sg:address":"3060 Cobb Pkwy NW",
    "sg:city":"Kennesaw",
    "sg:classifiers":[
        {
            "category":"Building & Trades",
            "subcategory":"Locksmith",
            "type":"Services"
        }
    ],
    "sg:phone":"+1 678 269 7256",
    "sg:postcode":"30152",
    "sg:province":"GA",
    "sg:tags":[
        "key"
    ],
    "wof:name":"All Day Emergency Locksmith",
    "wof:placetype":"venue"
},
  "geometry": {"coordinates":[-84.64510900000001,34.028555],"type":"Point"}
}