{
  "type": "Feature",
  "properties": {
    "iso:country":"US",
    "sg:address":"1317 Johnson Ferry Rd",
    "sg:city":"Marietta",
    "sg:classifiers":[
        {
            "category":"Shopping",
            "subcategory":"Books",
            "type":"Retail Goods"
        }
    ],
    "sg:phone":"+1 770 565 5909",
    "sg:postcode":"30068",
    "sg:province":"GA",
    "sg:tags":[
        "computer",
        "video",
        "software"
    ],
    "wof:name":"Media Play",
    "wof:placetype":"venue"
},
  "geometry": {"coordinates":[-84.422573,33.97969],"type":"Point"}
}