{
  "type": "Feature",
  "properties": {
    "addr:full":"3221 Peachtree Road NE Atlanta GA 30305",
    "addr:housenumber":"3221",
    "addr:postcode":"30305",
    "addr:street":"Peachtree Road Ne",
    "iso:country":"US",
    "sg:address":"3221 Peachtree Road NE",
    "sg:city":"Atlanta",
    "sg:classifiers":[
        {
            "category":"Shopping",
            "subcategory":"Bicycles & Sporting Goods",
            "type":"Retail Goods"
        }
    ],
    "sg:phone":"+1 404 814 0710",
    "sg:postcode":"30305",
    "sg:province":"GA",
    "sg:website":"www.sportsauthority.com",
    "wof:name":"Sports Authority",
    "wof:placetype":"venue"
},
  "geometry": {"coordinates":[-84.37342099999999,33.842381],"type":"Point"}
}