{
  "type": "Feature",
  "properties": {
    "addr:full":"106 Rose St Warner Robins GA 31093",
    "addr:housenumber":"106",
    "addr:postcode":"31093",
    "addr:street":"Rose St",
    "iso:country":"US",
    "sg:address":"106 Rose St",
    "sg:city":"Warner Robins",
    "sg:classifiers":[
        {
            "category":"Professional",
            "type":"Services"
        }
    ],
    "sg:phone":"+1 478 329 0436",
    "sg:postcode":"31093",
    "sg:province":"GA",
    "wof:name":"Faye Jones",
    "wof:placetype":"venue"
},
  "geometry": {"coordinates":[-83.603437,32.627648],"type":"Point"}
}