{
  "type": "Feature",
  "properties": {
    "addr:full":"525 Peachtree Industrial Blvd Suwanee GA 30024",
    "addr:housenumber":"525",
    "addr:postcode":"30024",
    "addr:street":"Peachtree Industrial Blvd",
    "iso:country":"US",
    "sg:address":"525 Peachtree Industrial Blvd",
    "sg:city":"Suwanee",
    "sg:classifiers":[
        {
            "category":"Restaurant",
            "type":"Food & Drink"
        }
    ],
    "sg:phone":"+1 770 614 1335",
    "sg:postcode":"30024",
    "sg:province":"GA",
    "sg:tags":[
        "eating"
    ],
    "wof:name":"Tanner's Chicken Rotisserie",
    "wof:placetype":"venue"
},
  "geometry": {"coordinates":[-84.087856,34.052661],"type":"Point"}
}