{
  "type": "Feature",
  "properties": {
    "addr:full":"3044 Hickory Hills Dr Gainesville GA 30506",
    "addr:housenumber":"3044",
    "addr:postcode":"30506",
    "addr:street":"Hickory Hills Dr",
    "iso:country":"US",
    "sg:address":"3044 Hickory Hills Dr",
    "sg:city":"Gainesville",
    "sg:classifiers":[
        {
            "category":"Building & Trades",
            "subcategory":"Construction",
            "type":"Services"
        }
    ],
    "sg:phone":"+1 770 536 2159",
    "sg:postcode":"30506",
    "sg:province":"GA",
    "sg:tags":[
        "house"
    ],
    "wof:name":"Bluevalley Builders LLC",
    "wof:placetype":"venue"
},
  "geometry": {"coordinates":[-83.875767,34.351588],"type":"Point"}
}