{
  "type": "Feature",
  "properties": {
    "addr:full":"125 Paradise Blvd Athens GA 30607",
    "addr:housenumber":"125",
    "addr:postcode":"30607",
    "addr:street":"Paradise Blvd",
    "iso:country":"US",
    "sg:address":"125 Paradise Blvd",
    "sg:city":"Athens",
    "sg:classifiers":[
        {
            "category":"Retail",
            "subcategory":"Auto Repair",
            "type":"Services"
        }
    ],
    "sg:phone":"+1 706 543 1797",
    "sg:postcode":"30607",
    "sg:province":"GA",
    "sg:tags":[
        "body",
        "automotive",
        "mfg",
        "motor",
        "vehicle"
    ],
    "wof:name":"Comprent Motor Sports Inc",
    "wof:placetype":"venue"
},
  "geometry": {"coordinates":[-83.398752,33.981277],"type":"Point"}
}