{
  "type": "Feature",
  "properties": {
    "iso:country":"US",
    "sg:address":"136 Industrial Dr",
    "sg:city":"Moultrie",
    "sg:classifiers":[
        {
            "category":"Freight",
            "type":"Transportation"
        }
    ],
    "sg:phone":"+1 229 985 6683",
    "sg:postcode":"31788",
    "sg:province":"GA",
    "sg:tags":[
        "commercial",
        "storage"
    ],
    "wof:name":"Adams & Adams Storage",
    "wof:placetype":"venue"
},
  "geometry": {"coordinates":[-83.74954700000001,31.174552],"type":"Point"}
}