{
  "type": "Feature",
  "properties": {
    "iso:country":"US",
    "sg:address":"105 Airport Rd",
    "sg:city":"St Simons Island",
    "sg:classifiers":[
        {
            "category":"Retail",
            "subcategory":"Repair Shop",
            "type":"Services"
        }
    ],
    "sg:phone":"+1 912 638 6536",
    "sg:postcode":"31522",
    "sg:province":"GA",
    "sg:tags":[
        "equipment",
        "electronic",
        "electrical",
        "supply"
    ],
    "wof:name":"Forbes Electronic Repairs",
    "wof:placetype":"venue"
},
  "geometry": {"coordinates":[-81.385795,31.15763],"type":"Point"}
}