{
  "type": "Feature",
  "properties": {
    "addr:full":"1527 S Elm St Commerce GA 30529",
    "addr:housenumber":"1527",
    "addr:postcode":"30529",
    "addr:street":"S Elm St",
    "iso:country":"US",
    "sg:address":"1527 S Elm St",
    "sg:city":"Commerce",
    "sg:classifiers":[
        {
            "category":"Health Services",
            "subcategory":"Doctor",
            "type":"Services"
        }
    ],
    "sg:phone":"+1 706 335 3895",
    "sg:postcode":"30529",
    "sg:province":"GA",
    "sg:tags":[
        "county",
        "clinic"
    ],
    "wof:name":"Commerce Clinic",
    "wof:placetype":"venue"
},
  "geometry": {"coordinates":[-83.45535099999999,34.201211],"type":"Point"}
}