{
  "type": "Feature",
  "properties": {
    "addr:full":"2761 Loring Rd NW Kennesaw GA 30152",
    "addr:housenumber":"2761",
    "addr:postcode":"30152",
    "addr:street":"Loring Rd Nw",
    "iso:country":"US",
    "sg:address":"2761 Loring Rd NW",
    "sg:city":"Kennesaw",
    "sg:classifiers":[
        {
            "category":"Wholesale",
            "subcategory":"Durable Goods & Equipment",
            "type":"Manufacturing & Wholesale Goods"
        }
    ],
    "sg:phone":"+1 770 974 4344",
    "sg:postcode":"30152",
    "sg:province":"GA",
    "wof:name":"Hanes Supply Co Inc",
    "wof:placetype":"venue"
},
  "geometry": {"coordinates":[-84.660856,34.014387],"type":"Point"}
}