{
  "type": "Feature",
  "properties": {
    "addr:full":"2440 Cardinal Way Tucker GA 30084",
    "addr:housenumber":"2440",
    "addr:postcode":"30084",
    "addr:street":"Cardinal Way",
    "iso:country":"US",
    "sg:address":"2440 Cardinal Way",
    "sg:city":"Tucker",
    "sg:classifiers":[
        {
            "category":"Health Services",
            "subcategory":"Health Practitioner",
            "type":"Services"
        }
    ],
    "sg:phone":"+1 770 938 4549",
    "sg:postcode":"30084",
    "sg:province":"GA",
    "wof:name":"Brassell David Ld MD PC",
    "wof:placetype":"venue"
},
  "geometry": {"coordinates":[-84.228989,33.856537],"type":"Point"}
}