{
  "type": "Feature",
  "properties": {
    "iso:country":"US",
    "sg:address":"200 Morgan Falls Rd",
    "sg:city":"Sandy Springs",
    "sg:classifiers":[
        {
            "category":"Park",
            "type":"Public Place"
        }
    ],
    "sg:postcode":"30350",
    "sg:province":"GA",
    "wof:name":"Morgan Falls Overlook Park",
    "wof:placetype":"venue"
},
  "geometry": {"coordinates":[-84.37974199999999,33.970093],"type":"Point"}
}