{
  "type": "Feature",
  "properties": {
    "iso:country":"US",
    "sg:address":"202 E 5th St",
    "sg:city":"Alma",
    "sg:classifiers":[
        {
            "category":"Building & Trades",
            "subcategory":"Construction",
            "type":"Services"
        }
    ],
    "sg:phone":"+1 912 632 9288",
    "sg:postcode":"31510",
    "sg:province":"GA",
    "sg:tags":[
        "general",
        "contractor"
    ],
    "wof:name":"WBM Construction Inc",
    "wof:placetype":"venue"
},
  "geometry": {"coordinates":[-82.45975900000001,31.546232],"type":"Point"}
}