{
  "type": "Feature",
  "properties": {
    "addr:full":"275 Carpenter Dr NE Ste 320 Atlanta GA 30328",
    "addr:housenumber":"275",
    "addr:postcode":"30328",
    "addr:street":"Carpenter Dr Ne Ste 320",
    "iso:country":"US",
    "sg:address":"275 Carpenter Dr NE Ste 320",
    "sg:city":"Atlanta",
    "sg:classifiers":[
        {
            "category":"Professional",
            "subcategory":"Lawyer & Legal Services",
            "type":"Services"
        }
    ],
    "sg:phone":"+1 404 845 2294",
    "sg:postcode":"30328",
    "sg:province":"GA",
    "wof:name":"Fierman Robert Attorney",
    "wof:placetype":"venue"
},
  "geometry": {"coordinates":[-84.379031,33.915239],"type":"Point"}
}