{
  "type": "Feature",
  "properties": {
    "iso:country":"US",
    "sg:address":"1395 US Hwy 27",
    "sg:city":"Carrollton",
    "sg:classifiers":[
        {
            "category":"Shopping",
            "subcategory":"Bicycles & Sporting Goods",
            "type":"Retail Goods"
        }
    ],
    "sg:phone":"+1 770 832 0801",
    "sg:postcode":"30117",
    "sg:province":"GA",
    "wof:name":"Newman Sports",
    "wof:placetype":"venue"
},
  "geometry": {"coordinates":[-85.085195,33.609157],"type":"Point"}
}