{
  "type": "Feature",
  "properties": {
    "addr:full":"4810 Dawsonville Hwy Gainesville GA 30506",
    "addr:postcode":"4810;30506",
    "addr:street":"Dawsonville Hwy",
    "iso:country":"US",
    "sg:address":"4810 Dawsonville Hwy",
    "sg:city":"Gainesville",
    "sg:classifiers":[
        {
            "category":"Shopping",
            "type":"Retail Goods"
        }
    ],
    "sg:phone":"+1 770 781 4950",
    "sg:postcode":"30506",
    "sg:province":"GA",
    "sg:tags":[
        "merchandise"
    ],
    "wof:name":"Walters Monument Co",
    "wof:placetype":"venue"
},
  "geometry": {"coordinates":[-83.97624399999999,34.303884],"type":"Point"}
}