{
  "type": "Feature",
  "properties": {
    "iso:country":"US",
    "sg:address":"1100 Piedmont Rd",
    "sg:city":"Marietta",
    "sg:classifiers":[
        {
            "category":"Organizations",
            "subcategory":"Religious Organization",
            "type":"Services"
        }
    ],
    "sg:phone":"+1 770 973 0063",
    "sg:postcode":"30066",
    "sg:province":"GA",
    "sg:tags":[
        "baptist",
        "church"
    ],
    "wof:name":"Calvary Baptist Church",
    "wof:placetype":"venue"
},
  "geometry": {"coordinates":[-84.52004700000001,34.020491],"type":"Point"}
}