{
  "type": "Feature",
  "properties": {
    "addr:full":"1074 Wash Lee Dr SW Lilburn GA 30047",
    "addr:housenumber":"1074",
    "addr:postcode":"30047",
    "addr:street":"Wash Lee Dr Sw",
    "iso:country":"US",
    "sg:address":"1074 Wash Lee Dr SW",
    "sg:city":"Lilburn",
    "sg:classifiers":[
        {
            "category":"Building & Trades",
            "subcategory":"Construction",
            "type":"Services"
        }
    ],
    "sg:phone":"+1 770 564 8788",
    "sg:postcode":"30047",
    "sg:province":"GA",
    "sg:tags":[
        "residential"
    ],
    "wof:name":"Bj Construction",
    "wof:placetype":"venue"
},
  "geometry": {"coordinates":[-84.091899,33.865493],"type":"Point"}
}