{
  "type": "Feature",
  "properties": {
    "addr:full":"304 Stanfill Rd Moultrie GA 31788",
    "addr:housenumber":"304",
    "addr:postcode":"31788",
    "addr:street":"Stanfill Rd",
    "iso:country":"US",
    "sg:address":"304 Stanfill Rd",
    "sg:city":"Moultrie",
    "sg:phone":"+1 229 324 2197",
    "sg:postcode":"31788",
    "sg:province":"GA",
    "sg:tags":[
        "farm",
        "tobacco"
    ],
    "wof:name":"Alvin Williams Farm",
    "wof:placetype":"venue"
},
  "geometry": {"coordinates":[-83.607643,31.149392],"type":"Point"}
}