{
  "type": "Feature",
  "properties": {
    "iso:country":"US",
    "sg:address":"W. Peachtree Street",
    "sg:city":"Atlanta",
    "sg:classifiers":[
        {
            "category":"Professional",
            "subcategory":"Advertising",
            "type":"Services"
        },
        {
            "category":"Professional",
            "subcategory":"Art Services",
            "type":"Services"
        },
        {
            "category":"Professional",
            "subcategory":"Computer Services",
            "type":"Services"
        }
    ],
    "sg:phone":"+1 404 910 3124",
    "sg:postcode":"30309",
    "sg:province":"GA",
    "sg:tags":[
        "web",
        "graphic",
        "marketing",
        "agency",
        "site",
        "hosting",
        "designer",
        "design",
        "internet"
    ],
    "sg:website":"http://www.megamarketingmamis.com",
    "wof:name":"Mega Marketing Mamis",
    "wof:placetype":"venue"
},
  "geometry": {"coordinates":[-84.38385,33.788481],"type":"Point"}
}