{
  "type": "Feature",
  "properties": {
    "addr:full":"4310 Mink Livsey Rd Snellville GA 30039",
    "addr:housenumber":"4310",
    "addr:postcode":"30039",
    "addr:street":"Mink Livsey Rd",
    "iso:country":"US",
    "sg:address":"4310 Mink Livsey Rd",
    "sg:city":"Snellville",
    "sg:classifiers":[
        {
            "category":"Building & Trades",
            "subcategory":"Construction",
            "type":"Services"
        }
    ],
    "sg:phone":"+1 770 785 9211",
    "sg:postcode":"30039",
    "sg:province":"GA",
    "sg:tags":[
        "contractor"
    ],
    "wof:name":"Villegas Masonry",
    "wof:placetype":"venue"
},
  "geometry": {"coordinates":[-84.015452,33.788374],"type":"Point"}
}