{
  "type": "Feature",
  "properties": {
    "addr:full":"1736 Candler Rd Decatur GA 30032",
    "addr:postcode":"1736;30032",
    "addr:street":"Candler Rd",
    "iso:country":"US",
    "sg:address":"1736 Candler Rd",
    "sg:city":"Decatur",
    "sg:classifiers":[
        {
            "category":"Professional",
            "type":"Services"
        }
    ],
    "sg:phone":"+1 404 289 8777",
    "sg:postcode":"30032",
    "sg:province":"GA",
    "wof:name":"Silver Jubilee Inc",
    "wof:placetype":"venue"
},
  "geometry": {"coordinates":[-84.28818,33.739205],"type":"Point"}
}