{
  "type": "Feature",
  "properties": {
    "iso:country":"US",
    "sg:address":"1009 Georgian Park",
    "sg:city":"Peachtree City",
    "sg:classifiers":[
        {
            "category":"Food & Beverages",
            "subcategory":"Groceries & Convenience Stores",
            "type":"Retail Goods"
        }
    ],
    "sg:phone":"+1 770 486 1500",
    "sg:postcode":"30269",
    "sg:province":"GA",
    "wof:name":"Kedron Village Store",
    "wof:placetype":"venue"
},
  "geometry": {"coordinates":[-84.586304,33.4408],"type":"Point"}
}