{
  "type": "Feature",
  "properties": {
    "addr:full":"210 Fiddlers Ridge Fairburn GA 30213",
    "addr:housenumber":"210",
    "addr:postcode":"30213",
    "addr:street":"Fiddlers Ridge",
    "iso:country":"US",
    "sg:address":"210 Fiddlers Ridge",
    "sg:city":"Fairburn",
    "sg:classifiers":[
        {
            "category":"Shopping",
            "type":"Retail Goods"
        }
    ],
    "sg:phone":"+1 770 719 7921",
    "sg:postcode":"30213",
    "sg:province":"GA",
    "sg:tags":[
        "juvenile",
        "merchandise"
    ],
    "wof:name":"PSI",
    "wof:placetype":"venue"
},
  "geometry": {"coordinates":[-84.46352,33.529531],"type":"Point"}
}