{
  "type": "Feature",
  "properties": {
    "addr:full":"4920 Roswell Rd Atlanta GA 30342",
    "addr:housenumber":"4920",
    "addr:postcode":"30342",
    "addr:street":"Roswell Rd",
    "iso:country":"US",
    "sg:address":"4920 Roswell Rd",
    "sg:city":"Atlanta",
    "sg:classifiers":[
        {
            "category":"Personal",
            "subcategory":"Tanning Parlor",
            "type":"Services"
        },
        {
            "category":"Personal",
            "type":"Services"
        }
    ],
    "sg:phone":"+1 404 497 9444",
    "sg:postcode":"30342",
    "sg:province":"GA",
    "sg:tags":[
        "salon"
    ],
    "wof:name":"Planet Beach Tanning Salon",
    "wof:placetype":"venue"
},
  "geometry": {"coordinates":[-84.38143700000001,33.890116],"type":"Point"}
}