{
  "type": "Feature",
  "properties": {
    "iso:country":"US",
    "sg:address":"337 Antioch Rd",
    "sg:city":"Dallas",
    "sg:classifiers":[
        {
            "category":"Building & Trades",
            "subcategory":"Construction",
            "type":"Services"
        }
    ],
    "sg:phone":"+1 770 443 0072",
    "sg:postcode":"30157",
    "sg:province":"GA",
    "wof:name":"Goodson Grading Co Inc",
    "wof:placetype":"venue"
},
  "geometry": {"coordinates":[-84.733456,33.944561],"type":"Point"}
}