{
  "type": "Feature",
  "properties": {
    "iso:country":"US",
    "sg:address":"719 Carroll St",
    "sg:city":"Perry",
    "sg:classifiers":[
        {
            "category":"Food & Beverages",
            "subcategory":"Groceries & Convenience Stores",
            "type":"Retail Goods"
        }
    ],
    "sg:phone":"+1 478 987 3300",
    "sg:postcode":"31069",
    "sg:province":"GA",
    "sg:tags":[
        "grocer"
    ],
    "wof:name":"Perry Food Mart",
    "wof:placetype":"venue"
},
  "geometry": {"coordinates":[-83.73595899999999,32.457499],"type":"Point"}
}