{
  "type": "Feature",
  "properties": {
    "addr:full":"2866 Chapel Hill Rd Douglasville GA 30135",
    "addr:housenumber":"2866",
    "addr:postcode":"30135",
    "addr:street":"Chapel Hill Rd",
    "iso:country":"US",
    "sg:address":"2866 Chapel Hill Rd",
    "sg:city":"Douglasville",
    "sg:classifiers":[
        {
            "category":"Shopping",
            "subcategory":"Beauty & Cosmetics",
            "type":"Retail Goods"
        }
    ],
    "sg:phone":"+1 770 942 0282",
    "sg:postcode":"30135",
    "sg:province":"GA",
    "sg:tags":[
        "clothing",
        "merchandise"
    ],
    "wof:name":"Merle Norman Cosmetics",
    "wof:placetype":"venue"
},
  "geometry": {"coordinates":[-84.736952,33.72773],"type":"Point"}
}