{
  "type": "Feature",
  "properties": {
    "iso:country":"US",
    "sg:address":"215 Napoleon Dr SW",
    "sg:city":"Atlanta",
    "sg:classifiers":[
        {
            "category":"Place Of Worship",
            "type":"Public Place"
        }
    ],
    "sg:phone":"+1 404 756 0707",
    "sg:postcode":"30314",
    "sg:province":"GA",
    "sg:tags":[
        "church"
    ],
    "wof:name":"Soul Winners For Christ Spiritual Assoc",
    "wof:placetype":"venue"
},
  "geometry": {"coordinates":[-84.42749499999999,33.748097],"type":"Point"}
}