{
  "type": "Feature",
  "properties": {
    "iso:country":"US",
    "sg:address":"612 W Gordon St",
    "sg:city":"Thomaston",
    "sg:classifiers":[
        {
            "category":"Health Services",
            "subcategory":"Doctor",
            "type":"Services"
        }
    ],
    "sg:phone":"+1 706 647 9433",
    "sg:postcode":"30286",
    "sg:province":"GA",
    "sg:tags":[
        "physician",
        "surgeon"
    ],
    "wof:name":"Flint River Surgical Assoc",
    "wof:placetype":"venue"
},
  "geometry": {"coordinates":[-84.334518,32.8873],"type":"Point"}
}