{
  "type": "Feature",
  "properties": {
    "iso:country":"US",
    "sg:address":"4158 Klondike Rd",
    "sg:city":"Lithonia",
    "sg:classifiers":[
        {
            "category":"Animal Shelter",
            "type":"Public Place"
        }
    ],
    "sg:phone":"+1 678 418 1111",
    "sg:postcode":"30038",
    "sg:province":"GA",
    "sg:tags":[
        "removal"
    ],
    "wof:name":"Aware",
    "wof:placetype":"venue"
},
  "geometry": {"coordinates":[-84.12452399999999,33.660079],"type":"Point"}
}