{
  "type": "Feature",
  "properties": {
    "addr:full":"23 Christopher Rdg NW Cartersville GA 30121",
    "addr:housenumber":"23",
    "addr:postcode":"30121",
    "addr:street":"Christopher Rdg Nw",
    "iso:country":"US",
    "sg:address":"23 Christopher Rdg NW",
    "sg:city":"Cartersville",
    "sg:classifiers":[
        {
            "category":"Personal",
            "type":"Services"
        },
        {
            "category":"Professional",
            "subcategory":"Detective & Security Services",
            "type":"Services"
        },
        {
            "category":"Manufacturing",
            "subcategory":"Building Materials",
            "type":"Manufacturing & Wholesale Goods"
        }
    ],
    "sg:phone":"+1 770 386 3863",
    "sg:postcode":"30121",
    "sg:province":"GA",
    "sg:tags":[
        "control",
        "monitoring",
        "fire",
        "consultant",
        "alarm",
        "system",
        "systems-wholesale",
        "equipment",
        "medical",
        "manufacturer"
    ],
    "wof:name":"Masterguard",
    "wof:placetype":"venue"
},
  "geometry": {"coordinates":[-84.841745,34.26025],"type":"Point"}
}