{
  "type": "Feature",
  "properties": {
    "addr:full":"6155 Boat Rock Blvd SW Atlanta GA 30336",
    "addr:housenumber":"6155",
    "addr:postcode":"30336",
    "addr:street":"Boat Rock Blvd Sw",
    "iso:country":"US",
    "sg:address":"6155 Boat Rock Blvd SW",
    "sg:city":"Atlanta",
    "sg:classifiers":[
        {
            "category":"Airline",
            "type":"Transportation"
        }
    ],
    "sg:phone":"+1 404 344 7648",
    "sg:postcode":"30336",
    "sg:province":"GA",
    "wof:name":"Spring Air South",
    "wof:placetype":"venue"
},
  "geometry": {"coordinates":[-84.59377000000001,33.727119],"type":"Point"}
}