{
  "type": "Feature",
  "properties": {
    "addr:full":"1239 Murray Ave Dalton GA 30721",
    "addr:housenumber":"1239",
    "addr:postcode":"30721",
    "addr:street":"Murray Ave",
    "iso:country":"US",
    "sg:address":"1239 Murray Ave",
    "sg:city":"Dalton",
    "sg:classifiers":[
        {
            "category":"Manufacturing",
            "subcategory":"Signs",
            "type":"Manufacturing & Wholesale Goods"
        }
    ],
    "sg:phone":"+1 706 275 8808",
    "sg:postcode":"30721",
    "sg:province":"GA",
    "sg:website":"www.signsandsigns.com",
    "wof:name":"Signs & Signs Inc",
    "wof:placetype":"venue"
},
  "geometry": {"coordinates":[-84.948842,34.767113],"type":"Point"}
}