{
  "type": "Feature",
  "properties": {
    "iso:country":"US",
    "sg:address":"1337 Waterton Trl",
    "sg:city":"Douglasville",
    "sg:classifiers":[
        {
            "category":"Building & Trades",
            "subcategory":"Cleaning & Sanitation",
            "type":"Services"
        }
    ],
    "sg:phone":"+1 770 489 4075",
    "sg:postcode":"30134",
    "sg:province":"GA",
    "sg:tags":[
        "maintenance"
    ],
    "wof:name":"Chris Howards Cleaning",
    "wof:placetype":"venue"
},
  "geometry": {"coordinates":[-84.767912,33.768097],"type":"Point"}
}