{
  "type": "Feature",
  "properties": {
    "iso:country":"US",
    "sg:address":"100 Heather St",
    "sg:city":"Warner Robins",
    "sg:classifiers":[
        {
            "category":"Farming",
            "subcategory":"Farm",
            "type":"Manufacturing & Wholesale Goods"
        }
    ],
    "sg:phone":"+1 478 923 4483",
    "sg:postcode":"31093",
    "sg:province":"GA",
    "sg:tags":[
        "crop",
        "general"
    ],
    "wof:name":"Barfield Farm",
    "wof:placetype":"venue"
},
  "geometry": {"coordinates":[-83.66080599999999,32.631406],"type":"Point"}
}