{
  "type": "Feature",
  "properties": {
    "iso:country":"US",
    "sg:address":"303 E 1st St",
    "sg:city":"Rome",
    "sg:classifiers":[
        {
            "category":"Real Estate",
            "subcategory":"Real Estate Agent",
            "type":"Services"
        }
    ],
    "sg:phone":"+1 706 235 7171",
    "sg:postcode":"30161",
    "sg:province":"GA",
    "sg:tags":[
        "inspection"
    ],
    "wof:name":"House Master Of America",
    "wof:placetype":"venue"
},
  "geometry": {"coordinates":[-85.170928,34.253887],"type":"Point"}
}