{
  "type": "Feature",
  "properties": {
    "iso:country":"US",
    "sg:address":"5393 Kemper Pl",
    "sg:city":"Stone Mountain",
    "sg:classifiers":[
        {
            "category":"Shopping",
            "subcategory":"Books",
            "type":"Retail Goods"
        }
    ],
    "sg:phone":"+1 770 498 1733",
    "sg:postcode":"30088",
    "sg:province":"GA",
    "sg:tags":[
        "dealer"
    ],
    "wof:name":"West Indian Book",
    "wof:placetype":"venue"
},
  "geometry": {"coordinates":[-84.17066699999999,33.755304],"type":"Point"}
}