{
  "type": "Feature",
  "properties": {
    "addr:full":"9118 Westview Dr SW Covington GA 30014",
    "addr:housenumber":"9118",
    "addr:postcode":"30014",
    "addr:street":"Westview Dr Sw",
    "iso:country":"US",
    "sg:address":"9118 Westview Dr SW",
    "sg:city":"Covington",
    "sg:classifiers":[
        {
            "category":"Building & Trades",
            "subcategory":"Electrical",
            "type":"Services"
        }
    ],
    "sg:phone":"+1 770 385 9137",
    "sg:postcode":"30014",
    "sg:province":"GA",
    "sg:tags":[
        "electrical",
        "contractor"
    ],
    "wof:name":"Hegwood Alarms & Low Voltage C",
    "wof:placetype":"venue"
},
  "geometry": {"coordinates":[-83.885808,33.593315],"type":"Point"}
}