{
  "type": "Feature",
  "properties": {
    "iso:country":"US",
    "sg:address":"501 Collett Ave",
    "sg:city":"Mableton",
    "sg:classifiers":[
        {
            "category":"Building & Trades",
            "subcategory":"Construction",
            "type":"Services"
        }
    ],
    "sg:phone":"+1 770 941 4851",
    "sg:postcode":"30126",
    "sg:province":"GA",
    "sg:tags":[
        "hanging",
        "painter",
        "contractor"
    ],
    "wof:name":"Cheryl's Face Painting",
    "wof:placetype":"venue"
},
  "geometry": {"coordinates":[-84.539005,33.808157],"type":"Point"}
}