{
  "type": "Feature",
  "properties": {
    "addr:full":"23 Carmichael Cir Newnan GA 30263",
    "addr:housenumber":"23",
    "addr:postcode":"30263",
    "addr:street":"Carmichael Cir",
    "iso:country":"US",
    "sg:address":"23 Carmichael Cir",
    "sg:city":"Newnan",
    "sg:classifiers":[
        {
            "category":"Building & Trades",
            "subcategory":"Construction",
            "type":"Services"
        }
    ],
    "sg:phone":"+1 678 662 2905",
    "sg:postcode":"30263",
    "sg:province":"GA",
    "sg:tags":[
        "hanging",
        "contractor"
    ],
    "wof:name":"Artcraft Painting Contractors",
    "wof:placetype":"venue"
},
  "geometry": {"coordinates":[-84.802959,33.382912],"type":"Point"}
}