{
  "type": "Feature",
  "properties": {
    "iso:country":"US",
    "sg:address":"1413 Newcastle St",
    "sg:city":"Brunswick",
    "sg:classifiers":[
        {
            "category":"Manufacturing",
            "subcategory":"Printing",
            "type":"Manufacturing & Wholesale Goods"
        }
    ],
    "sg:phone":"+1 912 265 7668",
    "sg:postcode":"31520",
    "sg:province":"GA",
    "sg:tags":[
        "offset"
    ],
    "wof:name":"Insty-Prints",
    "wof:placetype":"venue"
},
  "geometry": {"coordinates":[-81.495733,31.150324],"type":"Point"}
}