{
  "type": "Feature",
  "properties": {
    "addr:full":"7846 Stonecrest Sq Lithonia GA 30038",
    "addr:housenumber":"7846",
    "addr:postcode":"30038",
    "addr:street":"Stonecrest Sq",
    "iso:country":"US",
    "sg:address":"7846 Stonecrest Sq",
    "sg:city":"Lithonia",
    "sg:classifiers":[
        {
            "category":"Travel",
            "subcategory":"Hotels & Motels",
            "type":"Entertainment"
        }
    ],
    "sg:phone":"+1 678 325 4830",
    "sg:postcode":"30038",
    "sg:province":"GA",
    "sg:website":"www.choicehotels.com",
    "wof:name":"Comfort Suites",
    "wof:placetype":"venue"
},
  "geometry": {"coordinates":[-84.100683,33.701351],"type":"Point"}
}