{
  "type": "Feature",
  "properties": {
    "addr:full":"3505 Mount Zion Rd Stockbridge GA 30236",
    "addr:housenumber":"3505",
    "addr:postcode":"30236",
    "addr:street":"Mount Zion Rd",
    "iso:country":"US",
    "sg:address":"3505 Mount Zion Rd",
    "sg:city":"Stockbridge",
    "sg:classifiers":[
        {
            "category":"Professional",
            "type":"Services"
        }
    ],
    "sg:phone":"+1 678 289 0239",
    "sg:postcode":"30236",
    "sg:province":"GA",
    "wof:name":"Huffy Service First",
    "wof:placetype":"venue"
},
  "geometry": {"coordinates":[-84.280123,33.551409],"type":"Point"}
}