{
  "type": "Feature",
  "properties": {
    "addr:full":"352 Mathews Ave NE Atlanta GA 30307",
    "addr:housenumber":"352",
    "addr:postcode":"30307",
    "addr:street":"Mathews Ave Ne",
    "iso:country":"US",
    "sg:address":"352 Mathews Ave NE",
    "sg:city":"Atlanta",
    "sg:classifiers":[
        {
            "category":"Professional",
            "type":"Services"
        }
    ],
    "sg:phone":"+1 404 378 8839",
    "sg:postcode":"30307",
    "sg:province":"GA",
    "wof:name":"R Schatzel/Glenn",
    "wof:placetype":"venue"
},
  "geometry": {"coordinates":[-84.327338,33.762617],"type":"Point"}
}