{
  "type": "Feature",
  "properties": {
    "iso:country":"US",
    "sg:address":"1426 Briarcliff Dr",
    "sg:city":"Woodstock",
    "sg:classifiers":[
        {
            "category":"Professional",
            "subcategory":"Detective & Security Services",
            "type":"Services"
        }
    ],
    "sg:phone":"+1 678 493 8383",
    "sg:postcode":"30189",
    "sg:province":"GA",
    "sg:tags":[
        "control",
        "monitoring",
        "system"
    ],
    "wof:name":"AAA Security Shredding, Inc.",
    "wof:placetype":"venue"
},
  "geometry": {"coordinates":[-84.57144700000001,34.125703],"type":"Point"}
}