{
  "type": "Feature",
  "properties": {
    "iso:country":"US",
    "sg:address":"121 S Mock Rd",
    "sg:city":"Albany",
    "sg:classifiers":[
        {
            "category":"Place Of Worship",
            "subcategory":"Church",
            "type":"Public Place"
        },
        {
            "category":"Place Of Worship",
            "type":"Public Place"
        }
    ],
    "sg:phone":"+1 229 435 8471",
    "sg:postcode":"31705",
    "sg:province":"GA",
    "sg:tags":[
        "churches-united",
        "methodist",
        "churches-methodist"
    ],
    "wof:name":"Morningside United Methodist Church",
    "wof:placetype":"venue"
},
  "geometry": {"coordinates":[-84.094689,31.574128],"type":"Point"}
}