{
  "type": "Feature",
  "properties": {
    "addr:full":"536 3rd St Macon GA 31201",
    "addr:housenumber":"536",
    "addr:postcode":"31201",
    "addr:street":"3Rd St",
    "iso:country":"US",
    "sg:address":"536 3rd St",
    "sg:city":"Macon",
    "sg:classifiers":[
        {
            "category":"Home & Garden",
            "subcategory":"Hardware",
            "type":"Retail Goods"
        }
    ],
    "sg:phone":"+1 478 745 3306",
    "sg:postcode":"31201",
    "sg:province":"GA",
    "sg:tags":[
        "feed",
        "farm",
        "lawn",
        "sup",
        "supply"
    ],
    "wof:name":"Karsten-Denson Company",
    "wof:placetype":"venue"
},
  "geometry": {"coordinates":[-83.628934,32.834134],"type":"Point"}
}