{
  "type": "Feature",
  "properties": {
    "iso:country":"US",
    "sg:address":"1316 Powers Ferry Rd SE",
    "sg:city":"Marietta",
    "sg:classifiers":[
        {
            "category":"Personal",
            "subcategory":"Barber",
            "type":"Services"
        }
    ],
    "sg:phone":"+1 770 818 0052",
    "sg:postcode":"30067",
    "sg:province":"GA",
    "sg:tags":[
        "shop"
    ],
    "wof:name":"Appleberry's Barber Shop",
    "wof:placetype":"venue"
},
  "geometry": {"coordinates":[-84.467457,33.920466],"type":"Point"}
}