{
  "type": "Feature",
  "properties": {
    "iso:country":"US",
    "sg:address":"3151 N Sharon Church Rd",
    "sg:city":"Loganville",
    "sg:classifiers":[
        {
            "category":"Retail",
            "subcategory":"Repair Shop",
            "type":"Services"
        }
    ],
    "sg:phone":"+1 770 554 8991",
    "sg:postcode":"30052",
    "sg:province":"GA",
    "sg:tags":[
        "building",
        "maintenance"
    ],
    "wof:name":"Southern Maintenance",
    "wof:placetype":"venue"
},
  "geometry": {"coordinates":[-83.91792100000001,33.784115],"type":"Point"}
}