{
  "type": "Feature",
  "properties": {
    "iso:country":"US",
    "sg:address":"11673 Hastings Bridge Rd",
    "sg:city":"Lovejoy",
    "sg:classifiers":[
        {
            "category":"Food & Beverages",
            "subcategory":"Groceries & Convenience Stores",
            "type":"Retail Goods"
        }
    ],
    "sg:phone":"+1 770 478 0211",
    "sg:postcode":"30250",
    "sg:province":"GA",
    "wof:name":"Lovejoy Conoco",
    "wof:placetype":"venue"
},
  "geometry": {"coordinates":[-84.3134,33.4366],"type":"Point"}
}