{
  "type": "Feature",
  "properties": {
    "addr:full":"400 W Peachtree St NW # 3 Atlanta GA 30308",
    "addr:housenumber":"400",
    "addr:postcode":"30308",
    "addr:street":"W Peachtree St Nw # 3",
    "iso:country":"US",
    "sg:address":"400 W Peachtree St NW # 3",
    "sg:city":"Atlanta",
    "sg:classifiers":[
        {
            "category":"Professional",
            "subcategory":"Detective & Security Services",
            "type":"Services"
        }
    ],
    "sg:phone":"+1 404 474 4610",
    "sg:postcode":"30308",
    "sg:province":"GA",
    "sg:tags":[
        "guard",
        "patrol"
    ],
    "wof:name":"C360 Security & Investigations",
    "wof:placetype":"venue"
},
  "geometry": {"coordinates":[-84.387497,33.76479],"type":"Point"}
}