{
  "type": "Feature",
  "properties": {
    "iso:country":"US",
    "sg:address":"44 Legion Rd",
    "sg:city":"Mcdonough",
    "sg:classifiers":[
        {
            "category":"Professional",
            "type":"Services"
        }
    ],
    "sg:phone":"+1 770 898 6398",
    "sg:postcode":"30253",
    "sg:province":"GA",
    "sg:tags":[
        "establishment"
    ],
    "wof:name":"Mcdonough City",
    "wof:placetype":"venue"
},
  "geometry": {"coordinates":[-84.140981,33.429676],"type":"Point"}
}