{
  "type": "Feature",
  "properties": {
    "addr:full":"100 Hamilton Dr Peachtree City GA 30269",
    "addr:housenumber":"100",
    "addr:postcode":"30269",
    "addr:street":"Hamilton Dr",
    "iso:country":"US",
    "sg:address":"100 Hamilton Dr",
    "sg:city":"Peachtree City",
    "sg:classifiers":[
        {
            "category":"Professional",
            "subcategory":"Business Services",
            "type":"Services"
        }
    ],
    "sg:phone":"+1 770 631 4471",
    "sg:postcode":"30269",
    "sg:province":"GA",
    "wof:name":"Creative Accents Studio",
    "wof:placetype":"venue"
},
  "geometry": {"coordinates":[-84.563417,33.406751],"type":"Point"}
}