{
  "type": "Feature",
  "properties": {
    "iso:country":"US",
    "sg:address":"2251 Penfield Rd",
    "sg:city":"Greensboro",
    "sg:classifiers":[
        {
            "category":"Place Of Worship",
            "subcategory":"Church",
            "type":"Public Place"
        },
        {
            "category":"Place Of Worship",
            "type":"Public Place"
        }
    ],
    "sg:phone":"+1 706 453 1351",
    "sg:postcode":"30642",
    "sg:province":"GA",
    "sg:tags":[
        "churches-baptist-general",
        "churches-baptist"
    ],
    "wof:name":"Boswell Baptist Church",
    "wof:placetype":"venue"
},
  "geometry": {"coordinates":[-83.160797,33.603886],"type":"Point"}
}