{
  "type": "Feature",
  "properties": {
    "addr:full":"1125 S Green St Thomaston GA 30286",
    "addr:housenumber":"1125",
    "addr:postcode":"30286",
    "addr:street":"S Green St",
    "iso:country":"US",
    "sg:address":"1125 S Green St",
    "sg:city":"Thomaston",
    "sg:classifiers":[
        {
            "category":"Building & Trades",
            "subcategory":"Equipment Rental",
            "type":"Services"
        }
    ],
    "sg:phone":"+1 706 648 2054",
    "sg:postcode":"30286",
    "sg:province":"GA",
    "wof:name":"Quinton Equipment Rental & Sls",
    "wof:placetype":"venue"
},
  "geometry": {"coordinates":[-84.347768,32.876497],"type":"Point"}
}