{
  "type": "Feature",
  "properties": {
    "addr:full":"602 Dogwood Trl Tyrone GA 30290",
    "addr:housenumber":"602",
    "addr:postcode":"30290",
    "addr:street":"Dogwood Trl",
    "iso:country":"US",
    "sg:address":"602 Dogwood Trl",
    "sg:city":"Tyrone",
    "sg:classifiers":[
        {
            "category":"Professional",
            "subcategory":"Computer Services",
            "type":"Services"
        }
    ],
    "sg:phone":"+1 678 364 9396",
    "sg:postcode":"30290",
    "sg:province":"GA",
    "sg:tags":[
        "internet"
    ],
    "wof:name":"Internet Business Solutions",
    "wof:placetype":"venue"
},
  "geometry": {"coordinates":[-84.588159,33.454317],"type":"Point"}
}