{
  "type": "Feature",
  "properties": {
    "addr:full":"3227 Victory Dr Columbus GA 31903",
    "addr:housenumber":"3227",
    "addr:postcode":"31903",
    "addr:street":"Victory Dr",
    "iso:country":"US",
    "sg:address":"3227 Victory Dr",
    "sg:city":"Columbus",
    "sg:classifiers":[
        {
            "category":"Building & Trades",
            "subcategory":"Plumbing",
            "type":"Services"
        },
        {
            "category":"Building & Trades",
            "subcategory":"Construction",
            "type":"Services"
        }
    ],
    "sg:phone":"+1 706 689 4002",
    "sg:postcode":"31903",
    "sg:province":"GA",
    "sg:tags":[
        "pipe",
        "line",
        "contractor"
    ],
    "wof:name":"Northern Pipeline Construction",
    "wof:placetype":"venue"
},
  "geometry": {"coordinates":[-84.95458600000001,32.432219],"type":"Point"}
}