{
  "type": "Feature",
  "properties": {
    "iso:country":"US",
    "sg:address":"450 Franklin Rd SE # 170",
    "sg:city":"Marietta",
    "sg:classifiers":[
        {
            "category":"Home & Garden",
            "subcategory":"Kitchen Supply",
            "type":"Retail Goods"
        }
    ],
    "sg:phone":"+1 770 693 0061",
    "sg:postcode":"30067",
    "sg:province":"GA",
    "sg:tags":[
        "food",
        "processing",
        "equipment"
    ],
    "wof:name":"Desmet Ballestra",
    "wof:placetype":"venue"
},
  "geometry": {"coordinates":[-84.50849700000001,33.941825],"type":"Point"}
}