{
  "type": "Feature",
  "properties": {
    "iso:country":"US",
    "sg:address":"5288 Cumberland Way SW",
    "sg:city":"Stone Mountain",
    "sg:classifiers":[
        {
            "category":"Manufacturing",
            "subcategory":"Furniture",
            "type":"Manufacturing & Wholesale Goods"
        }
    ],
    "sg:phone":"+1 770 465 0748",
    "sg:postcode":"30087",
    "sg:province":"GA",
    "sg:tags":[
        "build",
        "cabinet"
    ],
    "wof:name":"E & H Cabinets",
    "wof:placetype":"venue"
},
  "geometry": {"coordinates":[-84.096766,33.798467],"type":"Point"}
}