{
  "type": "Feature",
  "properties": {
    "iso:country":"US",
    "sg:address":"60 Gwinnett St",
    "sg:city":"Buford",
    "sg:classifiers":[
        {
            "category":"Building & Trades",
            "subcategory":"Plumbing",
            "type":"Services"
        }
    ],
    "sg:phone":"+1 678 776 5205",
    "sg:postcode":"30518",
    "sg:province":"GA",
    "sg:tags":[
        "contractor"
    ],
    "wof:name":"Tim Lancaster Plumbing",
    "wof:placetype":"venue"
},
  "geometry": {"coordinates":[-84.005737,34.124318],"type":"Point"}
}