{
  "type": "Feature",
  "properties": {
    "addr:full":"5005 Roxburgh Dr Roswell GA 30076",
    "addr:housenumber":"5005",
    "addr:postcode":"30076",
    "addr:street":"Roxburgh Dr",
    "iso:country":"US",
    "sg:address":"5005 Roxburgh Dr",
    "sg:city":"Roswell",
    "sg:classifiers":[
        {
            "category":"Insurance",
            "subcategory":"Insurance Agent",
            "type":"Services"
        }
    ],
    "sg:phone":"+1 770 752 9944",
    "sg:postcode":"30076",
    "sg:province":"GA",
    "wof:name":"Boardman Agency",
    "wof:placetype":"venue"
},
  "geometry": {"coordinates":[-84.285358,34.028281],"type":"Point"}
}