{
  "type": "Feature",
  "properties": {
    "addr:full":"311 Park Ave SE Atlanta GA 30312",
    "addr:housenumber":"311",
    "addr:postcode":"30312",
    "addr:street":"Park Ave Se",
    "iso:country":"US",
    "sg:address":"311 Park Ave SE",
    "sg:city":"Atlanta",
    "sg:classifiers":[
        {
            "category":"Wholesale",
            "subcategory":"Medical Equipment & Supplies",
            "type":"Manufacturing & Wholesale Goods"
        },
        {
            "category":"Shopping",
            "subcategory":"Clothing, Apparel, & Fashions",
            "type":"Retail Goods"
        }
    ],
    "sg:phone":"+1 404 605 0077",
    "sg:postcode":"30312",
    "sg:province":"GA",
    "sg:tags":[
        "clothes",
        "work",
        "uniform"
    ],
    "wof:name":"Uniforms Of Atlanta",
    "wof:placetype":"venue"
},
  "geometry": {"coordinates":[-84.369663,33.745696],"type":"Point"}
}