{
  "type": "Feature",
  "properties": {
    "addr:full":"1413 Tift Ave N Tifton GA 31794",
    "addr:housenumber":"1413",
    "addr:postcode":"31794",
    "addr:street":"Tift Ave N",
    "iso:country":"US",
    "sg:address":"1413 Tift Ave N",
    "sg:city":"Tifton",
    "sg:classifiers":[
        {
            "category":"Health Services",
            "subcategory":"Doctor",
            "type":"Services"
        }
    ],
    "sg:phone":"+1 229 382 0803",
    "sg:postcode":"31794",
    "sg:province":"GA",
    "sg:tags":[
        "dentist"
    ],
    "wof:name":"Arthur W Baldwin Jr DDS",
    "wof:placetype":"venue"
},
  "geometry": {"coordinates":[-83.502877,31.466205],"type":"Point"}
}