{
  "type": "Feature",
  "properties": {
    "addr:full":"271 Howard Hill Rd Riceboro GA 31323",
    "addr:housenumber":"271",
    "addr:postcode":"31323",
    "addr:street":"Howard Hill Rd",
    "iso:country":"US",
    "sg:address":"271 Howard Hill Rd",
    "sg:city":"Riceboro",
    "sg:classifiers":[
        {
            "category":"Building & Trades",
            "subcategory":"Construction",
            "type":"Services"
        }
    ],
    "sg:phone":"+1 912 884 7199",
    "sg:postcode":"31323",
    "sg:province":"GA",
    "sg:tags":[
        "paving",
        "contractor"
    ],
    "wof:name":"Howard Paving",
    "wof:placetype":"venue"
},
  "geometry": {"coordinates":[-81.493049,31.721269],"type":"Point"}
}