{
  "type": "Feature",
  "properties": {
    "iso:country":"US",
    "sg:address":"3320 Deans Bridge Rd",
    "sg:city":"Augusta",
    "sg:classifiers":[
        {
            "category":"Travel",
            "subcategory":"Hotels & Motels",
            "type":"Entertainment"
        }
    ],
    "sg:phone":"+1 706 793 9600",
    "sg:postcode":"30906",
    "sg:province":"GA",
    "sg:tags":[
        "lodging"
    ],
    "sg:website":"http://www.daysinn.com",
    "wof:name":"Days Inn - Augusta / Deans Bridge Road",
    "wof:placetype":"venue"
},
  "geometry": {"coordinates":[-82.075378,33.419338],"type":"Point"}
}