{
  "type": "Feature",
  "properties": {
    "iso:country":"US",
    "sg:address":"602 Tift Ave N",
    "sg:city":"Tifton",
    "sg:classifiers":[
        {
            "category":"Personal",
            "subcategory":"Beauty Salon",
            "type":"Services"
        }
    ],
    "sg:phone":"+1 229 382 2636",
    "sg:postcode":"31794",
    "sg:province":"GA",
    "sg:tags":[
        "shop"
    ],
    "wof:name":"College Hill Beauty Salon",
    "wof:placetype":"venue"
},
  "geometry": {"coordinates":[-83.503308,31.46445],"type":"Point"}
}