{
  "type": "Feature",
  "properties": {
    "iso:country":"US",
    "sg:address":"100 Willow Ln",
    "sg:city":"McDonough",
    "sg:classifiers":[
        {
            "category":"Restaurant",
            "type":"Food & Drink"
        }
    ],
    "sg:phone":"+1 770 957 2100",
    "sg:postcode":"30253",
    "sg:province":"GA",
    "sg:tags":[
        "japanese"
    ],
    "sg:website":"www.tokyoinmcdonough.com",
    "wof:name":"Tokyo Japanese Steakhouse",
    "wof:placetype":"venue"
},
  "geometry": {"coordinates":[-84.180099,33.4324],"type":"Point"}
}