{
  "type": "Feature",
  "properties": {
    "iso:country":"US",
    "sg:address":"711 S 3rd Ave",
    "sg:city":"Chatsworth",
    "sg:classifiers":[
        {
            "category":"Shopping",
            "subcategory":"Hobbies, Toys, & Games",
            "type":"Retail Goods"
        }
    ],
    "sg:phone":"+1 706 695 8242",
    "sg:postcode":"30705",
    "sg:province":"GA",
    "sg:tags":[
        "doll"
    ],
    "sg:website":"www.collectorsunited.com",
    "wof:name":"Green's/Collectors United",
    "wof:placetype":"venue"
},
  "geometry": {"coordinates":[-84.769515,34.756855],"type":"Point"}
}