{
  "type": "Feature",
  "properties": {
    "iso:country":"US",
    "sg:address":"201 17th St NW",
    "sg:city":"Atlanta",
    "sg:classifiers":[
        {
            "category":"Professional",
            "subcategory":"Lawyer & Legal Services",
            "type":"Services"
        }
    ],
    "sg:phone":"+1 404 322 6106",
    "sg:postcode":"30363",
    "sg:province":"GA",
    "wof:name":"Sturm Glenn W Atty",
    "wof:placetype":"venue"
},
  "geometry": {"coordinates":[-84.3951,33.791407],"type":"Point"}
}