{
  "type": "Feature",
  "properties": {
    "addr:full":"118 Lakeview Estates Ln Eatonton GA 31024",
    "addr:housenumber":"118",
    "addr:postcode":"31024",
    "addr:street":"Lakeview Estates Ln",
    "iso:country":"US",
    "sg:address":"118 Lakeview Estates Ln",
    "sg:city":"Eatonton",
    "sg:classifiers":[
        {
            "category":"Retail",
            "subcategory":"Repair Shop",
            "type":"Services"
        }
    ],
    "sg:phone":"+1 706 485 9123",
    "sg:postcode":"31024",
    "sg:province":"GA",
    "sg:tags":[
        "welding"
    ],
    "wof:name":"J C Welding Cod",
    "wof:placetype":"venue"
},
  "geometry": {"coordinates":[-83.256987,33.42167],"type":"Point"}
}