{
  "type": "Feature",
  "properties": {
    "iso:country":"US",
    "sg:address":"925 Adel Hwy",
    "sg:city":"Nashville",
    "sg:classifiers":[
        {
            "category":"Professional",
            "subcategory":"Accounting & Tax Preparation",
            "type":"Services"
        }
    ],
    "sg:phone":"+1 229 686 3462",
    "sg:postcode":"31639",
    "sg:province":"GA",
    "sg:tags":[
        "return"
    ],
    "wof:name":"Griffin Wes H",
    "wof:placetype":"venue"
},
  "geometry": {"coordinates":[-83.25867599999999,31.196952],"type":"Point"}
}