{
  "type": "Feature",
  "properties": {
    "iso:country":"US",
    "sg:address":"3925 Peachtree Rd NE",
    "sg:city":"Atlanta",
    "sg:classifiers":[
        {
            "category":"Insurance",
            "subcategory":"Insurance Agent",
            "type":"Services"
        }
    ],
    "sg:phone":"+1 404 364 9927",
    "sg:postcode":"30319",
    "sg:province":"GA",
    "wof:name":"Allstate",
    "wof:placetype":"venue"
},
  "geometry": {"coordinates":[-84.34082100000001,33.858481],"type":"Point"}
}