{
  "type": "Feature",
  "properties": {
    "addr:full":"3846 Blackstone Camp Rd Augusta GA 30907",
    "addr:housenumber":"3846",
    "addr:postcode":"30907",
    "addr:street":"Blackstone Camp Rd",
    "iso:country":"US",
    "sg:address":"3846 Blackstone Camp Rd",
    "sg:city":"Augusta",
    "sg:classifiers":[
        {
            "category":"Home & Garden",
            "subcategory":"Building Materials",
            "type":"Retail Goods"
        },
        {
            "category":"Building & Trades",
            "subcategory":"Construction",
            "type":"Services"
        }
    ],
    "sg:phone":"+1 706 855 5482",
    "sg:postcode":"30907",
    "sg:province":"GA",
    "sg:tags":[
        "concrete",
        "staining",
        "contractor"
    ],
    "wof:name":"World Wide Concrete",
    "wof:placetype":"venue"
},
  "geometry": {"coordinates":[-82.083747,33.558683],"type":"Point"}
}