{
  "type": "Feature",
  "properties": {
    "iso:country":"US",
    "sg:address":"3815 Shoal Creek Ct",
    "sg:city":"Augusta",
    "sg:classifiers":[
        {
            "category":"Professional",
            "type":"Services"
        }
    ],
    "sg:phone":"+1 706 738 6638",
    "sg:postcode":"30907",
    "sg:province":"GA",
    "wof:name":"Mm Ltd",
    "wof:placetype":"venue"
},
  "geometry": {"coordinates":[-82.07370899999999,33.543282],"type":"Point"}
}