{
  "type": "Feature",
  "properties": {
    "iso:country":"US",
    "sg:address":"5025 Old Ellis Pt",
    "sg:city":"Roswell",
    "sg:classifiers":[
        {
            "category":"Manufacturing",
            "subcategory":"Tools & Machinery",
            "type":"Manufacturing & Wholesale Goods"
        }
    ],
    "sg:phone":"+1 770 667 9994",
    "sg:postcode":"30076",
    "sg:province":"GA",
    "sg:tags":[
        "laundry",
        "mfg",
        "commercial",
        "rug",
        "equipment",
        "cleaning",
        "establish",
        "carpet"
    ],
    "sg:website":"www.cleaningtechnologies.com",
    "wof:name":"Cleaning Technologies Inc",
    "wof:placetype":"venue"
},
  "geometry": {"coordinates":[-84.32633800000001,34.052448],"type":"Point"}
}