{
  "type": "Feature",
  "properties": {
    "iso:country":"US",
    "sg:address":"152 Lakeshore Dr",
    "sg:city":"Jackson",
    "sg:classifiers":[
        {
            "category":"Professional",
            "type":"Services"
        }
    ],
    "sg:phone":"+1 770 775 5582",
    "sg:postcode":"30233",
    "sg:province":"GA",
    "wof:name":"Alan Crockarell",
    "wof:placetype":"venue"
},
  "geometry": {"coordinates":[-84.021254,33.183102],"type":"Point"}
}