{
  "type": "Feature",
  "properties": {
    "addr:full":"4576 Arbour Dr Powder Springs GA 30127",
    "addr:housenumber":"4576",
    "addr:postcode":"30127",
    "addr:street":"Arbour Dr",
    "iso:country":"US",
    "sg:address":"4576 Arbour Dr",
    "sg:city":"Powder Springs",
    "sg:classifiers":[
        {
            "category":"Professional",
            "subcategory":"Art Services",
            "type":"Services"
        }
    ],
    "sg:phone":"+1 770 514 8131",
    "sg:postcode":"30127",
    "sg:province":"GA",
    "sg:tags":[
        "commercial",
        "design"
    ],
    "wof:name":"Bytes To Remember",
    "wof:placetype":"venue"
},
  "geometry": {"coordinates":[-84.683031,33.921488],"type":"Point"}
}