{
  "type": "Feature",
  "properties": {
    "addr:full":"555 Sun Valley Dr Roswell GA 30076",
    "addr:housenumber":"555",
    "addr:postcode":"30076",
    "addr:street":"Sun Valley Dr",
    "iso:country":"US",
    "sg:address":"555 Sun Valley Dr",
    "sg:city":"Roswell",
    "sg:classifiers":[
        {
            "category":"Professional",
            "subcategory":"Management & Consulting",
            "type":"Services"
        }
    ],
    "sg:phone":"+1 770 552 3252",
    "sg:postcode":"30076",
    "sg:province":"GA",
    "sg:tags":[
        "tax"
    ],
    "wof:name":"Monarch Financial Services",
    "wof:placetype":"venue"
},
  "geometry": {"coordinates":[-84.339,34.051191],"type":"Point"}
}