{
  "type": "Feature",
  "properties": {
    "iso:country":"US",
    "sg:address":"3245 Creek Dr A",
    "sg:city":"Marietta",
    "sg:classifiers":[
        {
            "category":"Professional",
            "subcategory":"Employment Agencies",
            "type":"Services"
        },
        {
            "category":"Professional",
            "subcategory":"Lawyer & Legal Services",
            "type":"Services"
        }
    ],
    "sg:phone":"+1 770 578 0345",
    "sg:postcode":"30062",
    "sg:province":"GA",
    "sg:tags":[
        "convention",
        "secretarial",
        "reporters-court"
    ],
    "wof:name":"That Personal Touch",
    "wof:placetype":"venue"
},
  "geometry": {"coordinates":[-84.44869199999999,34.029077],"type":"Point"}
}