{
  "type": "Feature",
  "properties": {
    "addr:full":"1039 Buford Hwy Buford GA 30518",
    "addr:housenumber":"1039",
    "addr:postcode":"30518",
    "addr:street":"Buford Hwy",
    "iso:country":"US",
    "sg:address":"1039 Buford Hwy",
    "sg:city":"Buford",
    "sg:classifiers":[
        {
            "category":"Freight",
            "type":"Transportation"
        }
    ],
    "sg:phone":"+1 770 271 7595",
    "sg:postcode":"30518",
    "sg:province":"GA",
    "sg:tags":[
        "operator",
        "local",
        "trucking"
    ],
    "wof:name":"Davis Hauling",
    "wof:placetype":"venue"
},
  "geometry": {"coordinates":[-84.08386299999999,34.037182],"type":"Point"}
}