{
  "type": "Feature",
  "properties": {
    "addr:full":"217 Douglas Hwy Fitzgerald GA 31750",
    "addr:housenumber":"217",
    "addr:postcode":"31750",
    "addr:street":"Douglas Hwy Fitzgerald",
    "iso:country":"US",
    "sg:address":"217 Douglas Hwy",
    "sg:city":"Fitzgerald",
    "sg:classifiers":[
        {
            "category":"Professional",
            "type":"Services"
        }
    ],
    "sg:phone":"+1 229 423 7744",
    "sg:postcode":"31750",
    "sg:province":"GA",
    "sg:tags":[
        "establishment"
    ],
    "wof:name":"King Louie",
    "wof:placetype":"venue"
},
  "geometry": {"coordinates":[-83.05009,31.685869],"type":"Point"}
}