{
  "type": "Feature",
  "properties": {
    "addr:full":"931 Centennial Rd Thomasville GA 31757",
    "addr:housenumber":"931",
    "addr:postcode":"31757",
    "addr:street":"Centennial Rd",
    "iso:country":"US",
    "sg:address":"931 Centennial Rd",
    "sg:city":"Thomasville",
    "sg:phone":"+1 229 228 0879",
    "sg:postcode":"31757",
    "sg:province":"GA",
    "sg:tags":[
        "farm",
        "corn",
        "soybean",
        "tobacco",
        "cotton"
    ],
    "wof:name":"Carlie Williams",
    "wof:placetype":"venue"
},
  "geometry": {"coordinates":[-83.857015,30.894956],"type":"Point"}
}