{
  "type": "Feature",
  "properties": {
    "iso:country":"US",
    "sg:address":"179 Macland Rd",
    "sg:city":"Dallas",
    "sg:classifiers":[
        {
            "category":"Professional",
            "type":"Services"
        }
    ],
    "sg:phone":"+1 770 505 1411",
    "sg:postcode":"30132",
    "sg:province":"GA",
    "wof:name":"Complete Tan",
    "wof:placetype":"venue"
},
  "geometry": {"coordinates":[-84.784898,33.918864],"type":"Point"}
}