{
  "type": "Feature",
  "properties": {
    "iso:country":"US",
    "sg:address":"1155 Woodstock Rd",
    "sg:city":"Roswell",
    "sg:classifiers":[
        {
            "category":"Manufacturing",
            "subcategory":"Textiles",
            "type":"Manufacturing & Wholesale Goods"
        },
        {
            "category":"Building & Trades",
            "subcategory":"Construction",
            "type":"Services"
        }
    ],
    "sg:phone":"+1 678 461 7715",
    "sg:postcode":"30075",
    "sg:province":"GA",
    "sg:tags":[
        "tile-wholesale",
        "tile-contractors",
        "manufacturer"
    ],
    "wof:name":"Giovanni's Tile Design",
    "wof:placetype":"venue"
},
  "geometry": {"coordinates":[-84.398667,34.061825],"type":"Point"}
}