{
  "type": "Feature",
  "properties": {
    "addr:full":"314 Cash Memorial Blvd Forest Park GA 30297",
    "addr:housenumber":"314",
    "addr:postcode":"30297",
    "addr:street":"Cash Memorial Blvd",
    "iso:country":"US",
    "sg:address":"314 Cash Memorial Blvd",
    "sg:city":"Forest Park",
    "sg:classifiers":[
        {
            "category":"Retail",
            "subcategory":"Auto Repair",
            "type":"Services"
        }
    ],
    "sg:phone":"+1 404 361 8468",
    "sg:postcode":"30297",
    "sg:province":"GA",
    "sg:tags":[
        "truck"
    ],
    "wof:name":"C & N Truck Repair",
    "wof:placetype":"venue"
},
  "geometry": {"coordinates":[-84.37973100000001,33.608248],"type":"Point"}
}