{
  "type": "Feature",
  "properties": {
    "addr:full":"52 Bullsboro Dr Newnan GA 30263",
    "addr:housenumber":"52",
    "addr:postcode":"30263",
    "addr:street":"Bullsboro Dr",
    "iso:country":"US",
    "sg:address":"52 Bullsboro Dr",
    "sg:city":"Newnan",
    "sg:classifiers":[
        {
            "category":"Fast Food",
            "type":"Food & Drink"
        },
        {
            "category":"Restaurant",
            "type":"Food & Drink"
        }
    ],
    "sg:phone":"+1 770 253 0135",
    "sg:postcode":"30263",
    "sg:province":"GA",
    "sg:tags":[
        "seafood"
    ],
    "sg:website":"http://www.ljsilvers.com",
    "wof:name":"Long John Silver's",
    "wof:placetype":"venue"
},
  "geometry": {"coordinates":[-84.78582,33.383919],"type":"Point"}
}