{
  "type": "Feature",
  "properties": {
    "iso:country":"US",
    "sg:address":"395 Cedar Hill Ave SE",
    "sg:city":"Dawson",
    "sg:classifiers":[
        {
            "category":"Retail",
            "subcategory":"Funeral Services",
            "type":"Services"
        }
    ],
    "sg:phone":"+1 229 995 5895",
    "sg:postcode":"39842",
    "sg:province":"GA",
    "sg:tags":[
        "director"
    ],
    "wof:name":"Albritten's Funeral Svc",
    "wof:placetype":"venue"
},
  "geometry": {"coordinates":[-84.443505,31.768033],"type":"Point"}
}