{
  "type": "Feature",
  "properties": {
    "addr:full":"915 Thornton Hollow La Fayette GA 30728",
    "addr:housenumber":"915",
    "addr:postcode":"30728",
    "addr:street":"Thornton Hollow La Fayette",
    "iso:country":"US",
    "sg:address":"915 Thornton Hollow",
    "sg:city":"La Fayette",
    "sg:classifiers":[
        {
            "category":"Organizations",
            "subcategory":"Non-profit Organization",
            "type":"Services"
        }
    ],
    "sg:phone":"+1 706 638 0426",
    "sg:postcode":"30728",
    "sg:province":"GA",
    "sg:tags":[
        "social"
    ],
    "wof:name":"Even Start",
    "wof:placetype":"venue"
},
  "geometry": {"coordinates":[-85.284632,34.710816],"type":"Point"}
}