{
  "type": "Feature",
  "properties": {
    "addr:full":"13846 Panhandle Ln Hampton GA 30228",
    "addr:postcode":"13846;30228",
    "addr:street":"Panhandle Ln",
    "iso:country":"US",
    "sg:address":"13846 Panhandle Ln",
    "sg:city":"Hampton",
    "sg:classifiers":[
        {
            "category":"Banks & Credit Unions",
            "subcategory":"Investment Brokerage",
            "type":"Services"
        }
    ],
    "sg:phone":"+1 770 487 8198",
    "sg:postcode":"30228",
    "sg:province":"GA",
    "sg:tags":[
        "security"
    ],
    "wof:name":"Edward Jones 22801",
    "wof:placetype":"venue"
},
  "geometry": {"coordinates":[-84.377663,33.376802],"type":"Point"}
}