{
  "type": "Feature",
  "properties": {
    "iso:country":"US",
    "sg:address":"350 Cherokee Pl",
    "sg:city":"Cartersville",
    "sg:classifiers":[
        {
            "category":"Personal",
            "subcategory":"Nail Salon",
            "type":"Services"
        }
    ],
    "sg:phone":"+1 770 386 6345",
    "sg:postcode":"30121",
    "sg:province":"GA",
    "wof:name":"Q Nail",
    "wof:placetype":"venue"
},
  "geometry": {"coordinates":[-84.78348200000001,34.17343],"type":"Point"}
}