{
  "type": "Feature",
  "properties": {
    "addr:full":"790 Church St NE Marietta GA 30060",
    "addr:housenumber":"790",
    "addr:postcode":"30060",
    "addr:street":"Church St Ne",
    "iso:country":"US",
    "sg:address":"790 Church St NE",
    "sg:city":"Marietta",
    "sg:classifiers":[
        {
            "category":"Health Services",
            "subcategory":"Doctor",
            "type":"Services"
        }
    ],
    "sg:phone":"+1 770 590 8313",
    "sg:postcode":"30060",
    "sg:province":"GA",
    "wof:name":"Volas-Redd Gena MD",
    "wof:placetype":"venue"
},
  "geometry": {"coordinates":[-84.55059799999999,33.971401],"type":"Point"}
}