{
  "type": "Feature",
  "properties": {
    "iso:country":"US",
    "sg:address":"756 Veterans Pkwy",
    "sg:city":"Jonesboro",
    "sg:classifiers":[
        {
            "category":"Home & Garden",
            "subcategory":"Building Materials",
            "type":"Retail Goods"
        }
    ],
    "sg:phone":"+1 770 471 8272",
    "sg:postcode":"30238",
    "sg:province":"GA",
    "wof:name":"Service Auto Glass",
    "wof:placetype":"venue"
},
  "geometry": {"coordinates":[-84.363356,33.525731],"type":"Point"}
}