{
  "type": "Feature",
  "properties": {
    "addr:full":"390 Sweetwater Rd North Augusta SC 29860",
    "addr:housenumber":"390",
    "addr:postcode":"29860",
    "addr:street":"Sweetwater Rd",
    "iso:country":"US",
    "sg:address":"390 Sweetwater Rd",
    "sg:city":"North Augusta",
    "sg:classifiers":[
        {
            "category":"Wholesale",
            "subcategory":"Machinery & Supplies",
            "type":"Manufacturing & Wholesale Goods"
        }
    ],
    "sg:phone":"+1 803 279 0023",
    "sg:postcode":"29860",
    "sg:province":"SC",
    "sg:tags":[
        "farm",
        "equipment"
    ],
    "wof:name":"Sweetwater Farm Equipment",
    "wof:placetype":"venue"
},
  "geometry": {"coordinates":[-81.968885,33.620361],"type":"Point"}
}