{
  "type": "Feature",
  "properties": {
    "addr:full":"234 Main St La Grange GA 30240",
    "addr:housenumber":"234",
    "addr:postcode":"30240",
    "addr:street":"Main St",
    "iso:country":"US",
    "sg:address":"234 Main St",
    "sg:city":"La Grange",
    "sg:classifiers":[
        {
            "category":"Social Services",
            "type":"Services"
        }
    ],
    "sg:phone":"+1 706 884 5818",
    "sg:postcode":"30240",
    "sg:province":"GA",
    "wof:name":"Red Cross",
    "wof:placetype":"venue"
},
  "geometry": {"coordinates":[-85.03107,33.038101],"type":"Point"}
}