{
  "type": "Feature",
  "properties": {
    "addr:full":"173 Meador Way SE Atlanta GA 30315",
    "addr:housenumber":"173",
    "addr:postcode":"30315",
    "addr:street":"Meador Way Se",
    "iso:country":"US",
    "sg:address":"173 Meador Way SE",
    "sg:city":"Atlanta",
    "sg:classifiers":[
        {
            "category":"Professional",
            "subcategory":"Business Services",
            "type":"Services"
        }
    ],
    "sg:phone":"+1 404 627 7673",
    "sg:postcode":"30315",
    "sg:province":"GA",
    "sg:tags":[
        "vintage",
        "used",
        "records",
        "tapes",
        "cd's"
    ],
    "wof:name":"Alchemical Healing",
    "wof:placetype":"venue"
},
  "geometry": {"coordinates":[-84.382496,33.698029],"type":"Point"}
}