{
  "type": "Feature",
  "properties": {
    "iso:country":"US",
    "sg:address":"2934 Mill Creek Rd",
    "sg:city":"Hiawassee",
    "sg:classifiers":[
        {
            "category":"Home & Garden",
            "subcategory":"Furniture",
            "type":"Retail Goods"
        }
    ],
    "sg:phone":"+1 706 896 1923",
    "sg:postcode":"30546",
    "sg:province":"GA",
    "sg:tags":[
        "cabinet"
    ],
    "wof:name":"Compton Cabinetry",
    "wof:placetype":"venue"
},
  "geometry": {"coordinates":[-83.700451,34.862519],"type":"Point"}
}