{
  "type": "Feature",
  "properties": {
    "iso:country":"US",
    "sg:address":"1311 Powers Ferry Rd SE",
    "sg:city":"Marietta",
    "sg:classifiers":[
        {
            "category":"Personal",
            "subcategory":"Beauty Salon",
            "type":"Services"
        }
    ],
    "sg:phone":"+1 770 937 0607",
    "sg:postcode":"30067",
    "sg:province":"GA",
    "wof:name":"Special Efx Hair Studio",
    "wof:placetype":"venue"
},
  "geometry": {"coordinates":[-84.467493,33.921091],"type":"Point"}
}