{
  "type": "Feature",
  "properties": {
    "addr:full":"490 S Main St Dawson GA 39842",
    "addr:housenumber":"490",
    "addr:postcode":"39842",
    "addr:street":"S Main St",
    "iso:country":"US",
    "sg:address":"490 S Main St",
    "sg:city":"Dawson",
    "sg:classifiers":[
        {
            "category":"Insurance",
            "subcategory":"Insurance Agent",
            "type":"Services"
        }
    ],
    "sg:phone":"+1 229 995 7071",
    "sg:postcode":"39842",
    "sg:province":"GA",
    "wof:name":"Clyde Aldridge Insurance",
    "wof:placetype":"venue"
},
  "geometry": {"coordinates":[-84.446932,31.767384],"type":"Point"}
}