{
  "type": "Feature",
  "properties": {
    "addr:full":"1173 Country Club Rd Newnan GA 30263",
    "addr:housenumber":"1173",
    "addr:postcode":"30263",
    "addr:street":"Country Club Rd",
    "iso:country":"US",
    "sg:address":"1173 Country Club Rd",
    "sg:city":"Newnan",
    "sg:classifiers":[
        {
            "category":"Building & Trades",
            "subcategory":"Construction",
            "type":"Services"
        }
    ],
    "sg:phone":"+1 770 254 9708",
    "sg:postcode":"30263",
    "sg:province":"GA",
    "sg:tags":[
        "house"
    ],
    "wof:name":"ACS Construction",
    "wof:placetype":"venue"
},
  "geometry": {"coordinates":[-84.81134299999999,33.429674],"type":"Point"}
}