{
  "type": "Feature",
  "properties": {
    "addr:full":"1000 Marietta St NW Ste 118 Atlanta GA 30318",
    "addr:housenumber":"1000",
    "addr:postcode":"30318",
    "addr:street":"Marietta St Nw Ste 118",
    "iso:country":"US",
    "sg:address":"1000 Marietta St NW Ste 118",
    "sg:city":"Atlanta",
    "sg:classifiers":[
        {
            "category":"Personal",
            "subcategory":"Hair Removal",
            "type":"Services"
        }
    ],
    "sg:phone":"+1 770 321 8714",
    "sg:postcode":"30318",
    "sg:province":"GA",
    "wof:name":"Saida LaJara at Lola Ricci Salon",
    "wof:placetype":"venue"
},
  "geometry": {"coordinates":[-84.410403,33.779118],"type":"Point"}
}