{
  "type": "Feature",
  "properties": {
    "iso:country":"US",
    "sg:address":"2106 Lee St SW",
    "sg:city":"Covington",
    "sg:classifiers":[
        {
            "category":"Personal",
            "subcategory":"Beauty Salon",
            "type":"Services"
        }
    ],
    "sg:phone":"+1 770 385 8402",
    "sg:postcode":"30014",
    "sg:province":"GA",
    "sg:tags":[
        "shop"
    ],
    "wof:name":"Peggy Nail Boutique",
    "wof:placetype":"venue"
},
  "geometry": {"coordinates":[-83.86284999999999,33.596647],"type":"Point"}
}