{
  "type": "Feature",
  "properties": {
    "iso:country":"US",
    "sg:address":"471 Thigpen Dr",
    "sg:city":"Swainsboro",
    "sg:classifiers":[
        {
            "category":"Building & Trades",
            "subcategory":"Plumbing",
            "type":"Services"
        }
    ],
    "sg:phone":"+1 478 237 2415",
    "sg:postcode":"30401",
    "sg:province":"GA",
    "sg:tags":[
        "plumber",
        "industrial",
        "contractors-commercial"
    ],
    "wof:name":"Griner Plumbing",
    "wof:placetype":"venue"
},
  "geometry": {"coordinates":[-82.317741,32.588802],"type":"Point"}
}