{
  "type": "Feature",
  "properties": {
    "iso:country":"US",
    "sg:address":"383 Bandy Ln",
    "sg:city":"Ringgold",
    "sg:classifiers":[
        {
            "category":"Home & Garden",
            "subcategory":"Furniture",
            "type":"Retail Goods"
        }
    ],
    "sg:phone":"+1 706 965 7222",
    "sg:postcode":"30736",
    "sg:province":"GA",
    "sg:tags":[
        "used",
        "merchandise"
    ],
    "wof:name":"Autumn Oak Antique Mall",
    "wof:placetype":"venue"
},
  "geometry": {"coordinates":[-85.07467200000001,34.895049],"type":"Point"}
}