{
  "type": "Feature",
  "properties": {
    "iso:country":"US",
    "sg:address":"221 Dabbs Bridge Rd",
    "sg:city":"Dallas",
    "sg:classifiers":[
        {
            "category":"Organizations",
            "subcategory":"Religious Organization",
            "type":"Services"
        }
    ],
    "sg:phone":"+1 770 445 6382",
    "sg:postcode":"30132",
    "sg:province":"GA",
    "wof:name":"Hickory Heights Baptist Church",
    "wof:placetype":"venue"
},
  "geometry": {"coordinates":[-84.828097,34.051736],"type":"Point"}
}