{
  "type": "Feature",
  "properties": {
    "addr:full":"218 Beverly Rd NE Atlanta GA 30309",
    "addr:housenumber":"218",
    "addr:postcode":"30309",
    "addr:street":"Beverly Rd Ne",
    "iso:country":"US",
    "sg:address":"218 Beverly Rd NE",
    "sg:city":"Atlanta",
    "sg:classifiers":[
        {
            "category":"Professional",
            "subcategory":"Business Services",
            "type":"Services"
        }
    ],
    "sg:phone":"+1 404 876 7181",
    "sg:postcode":"30309",
    "sg:province":"GA",
    "wof:name":"Ejr Interiors",
    "wof:placetype":"venue"
},
  "geometry": {"coordinates":[-84.379603,33.796811],"type":"Point"}
}