{
  "type": "Feature",
  "properties": {
    "addr:full":"521 Baxter St Athens GA 30602",
    "addr:housenumber":"521",
    "addr:postcode":"30602",
    "addr:street":"Baxter St",
    "iso:country":"US",
    "sg:address":"521 Baxter St",
    "sg:city":"Athens",
    "sg:classifiers":[
        {
            "category":"Shopping",
            "subcategory":"Gifts & Souvenirs",
            "type":"Retail Goods"
        }
    ],
    "sg:phone":"+1 706 549 1533",
    "sg:postcode":"30602",
    "sg:province":"GA",
    "sg:tags":[
        "news",
        "book"
    ],
    "wof:name":"Komix Castle Games & Comics",
    "wof:placetype":"venue"
},
  "geometry": {"coordinates":[-83.383636,33.950054],"type":"Point"}
}