{
  "type": "Feature",
  "properties": {
    "addr:full":"1800 N Loop Rd Vidalia GA 30474",
    "addr:housenumber":"1800",
    "addr:postcode":"30474",
    "addr:street":"N Loop Rd",
    "iso:country":"US",
    "sg:address":"1800 N Loop Rd",
    "sg:city":"Vidalia",
    "sg:classifiers":[
        {
            "category":"Recreation",
            "type":"Entertainment"
        }
    ],
    "sg:phone":"+1 912 537 4788",
    "sg:postcode":"30474",
    "sg:province":"GA",
    "sg:tags":[
        "course",
        "golf"
    ],
    "wof:name":"Vidalia Country Club",
    "wof:placetype":"venue"
},
  "geometry": {"coordinates":[-82.38761100000001,32.230734],"type":"Point"}
}