{
  "type": "Feature",
  "properties": {
    "iso:country":"US",
    "sg:address":"635 Oj Blvd",
    "sg:city":"Waynesboro",
    "sg:classifiers":[
        {
            "category":"Retail",
            "subcategory":"Auto Repair",
            "type":"Services"
        }
    ],
    "sg:phone":"+1 706 399 4735",
    "sg:postcode":"30830",
    "sg:province":"GA",
    "sg:tags":[
        "truck"
    ],
    "wof:name":"Roadside Truck Repair Inc",
    "wof:placetype":"venue"
},
  "geometry": {"coordinates":[-81.986672,33.143198],"type":"Point"}
}