{
  "type": "Feature",
  "properties": {
    "addr:full":"316 Graysville Rd Ringgold GA 30736",
    "addr:housenumber":"316",
    "addr:postcode":"30736",
    "addr:street":"Graysville Rd",
    "iso:country":"US",
    "sg:address":"316 Graysville Rd",
    "sg:city":"Ringgold",
    "sg:classifiers":[
        {
            "category":"Personal",
            "subcategory":"Beauty Salon",
            "type":"Services"
        }
    ],
    "sg:phone":"+1 706 937 5330",
    "sg:postcode":"30736",
    "sg:province":"GA",
    "wof:name":"Linda's Beauty Salon",
    "wof:placetype":"venue"
},
  "geometry": {"coordinates":[-85.163652,34.958349],"type":"Point"}
}