{
  "type": "Feature",
  "properties": {
    "iso:country":"US",
    "sg:address":"3245 Peachtree Pkwy",
    "sg:city":"Suwanee",
    "sg:classifiers":[
        {
            "category":"Personal",
            "subcategory":"Beauty Salon",
            "type":"Services"
        }
    ],
    "sg:phone":"+1 678 208 2111",
    "sg:postcode":"30024",
    "sg:province":"GA",
    "sg:tags":[
        "hair"
    ],
    "wof:name":"Royal Cuts Hair Salon",
    "wof:placetype":"venue"
},
  "geometry": {"coordinates":[-84.161118,34.083694],"type":"Point"}
}