{
  "type": "Feature",
  "properties": {
    "iso:country":"US",
    "sg:address":"3046 Peachtree Dr NE",
    "sg:city":"Atlanta",
    "sg:classifiers":[
        {
            "category":"Professional",
            "subcategory":"Business Services",
            "type":"Services"
        }
    ],
    "sg:phone":"+1 404 239 5934",
    "sg:postcode":"30305",
    "sg:province":"GA",
    "wof:name":"Burke Connelly Enterprises",
    "wof:placetype":"venue"
},
  "geometry": {"coordinates":[-84.36794500000001,33.837682],"type":"Point"}
}