{
  "type": "Feature",
  "properties": {
    "addr:full":"5461 N Lake Dr Morrow GA 30260",
    "addr:housenumber":"5461",
    "addr:postcode":"30260",
    "addr:street":"N Lake Dr",
    "iso:country":"US",
    "sg:address":"5461 N Lake Dr",
    "sg:city":"Morrow",
    "sg:classifiers":[
        {
            "category":"Retail",
            "subcategory":"Repair Shop",
            "type":"Services"
        }
    ],
    "sg:phone":"+1 404 361 3507",
    "sg:postcode":"30260",
    "sg:province":"GA",
    "wof:name":"B & B Outdoor Power Repair",
    "wof:placetype":"venue"
},
  "geometry": {"coordinates":[-84.334731,33.605524],"type":"Point"}
}