{
  "type": "Feature",
  "properties": {
    "addr:full":"2265 Childress Dr SW Atlanta GA 30311",
    "addr:housenumber":"2265",
    "addr:postcode":"30311",
    "addr:street":"Childress Dr Sw",
    "iso:country":"US",
    "sg:address":"2265 Childress Dr SW",
    "sg:city":"Atlanta",
    "sg:classifiers":[
        {
            "category":"Real Estate",
            "subcategory":"Real Estate Agent",
            "type":"Services"
        }
    ],
    "sg:phone":"+1 404 344 5691",
    "sg:postcode":"30311",
    "sg:province":"GA",
    "wof:name":"A Realty Exchange",
    "wof:placetype":"venue"
},
  "geometry": {"coordinates":[-84.486341,33.694131],"type":"Point"}
}