{
  "type": "Feature",
  "properties": {
    "addr:full":"220 Cherokee Pl Cartersville GA 30121",
    "addr:housenumber":"220",
    "addr:postcode":"30121",
    "addr:street":"Cherokee Pl",
    "iso:country":"US",
    "sg:address":"220 Cherokee Pl",
    "sg:city":"Cartersville",
    "sg:classifiers":[
        {
            "category":"Shopping",
            "subcategory":"Optical Goods",
            "type":"Retail Goods"
        }
    ],
    "sg:phone":"+1 770 606 0116",
    "sg:postcode":"30121",
    "sg:province":"GA",
    "wof:name":"Sears Optical",
    "wof:placetype":"venue"
},
  "geometry": {"coordinates":[-84.78286799999999,34.172437],"type":"Point"}
}