{
  "type": "Feature",
  "properties": {
    "addr:full":"3200 Riverside Dr Ste A350 Macon GA 31210",
    "addr:housenumber":"3200",
    "addr:postcode":"31210",
    "addr:street":"Riverside Dr Ste A350",
    "iso:country":"US",
    "sg:address":"3200 Riverside Dr Ste A350",
    "sg:city":"Macon",
    "sg:classifiers":[
        {
            "category":"Structure",
            "subcategory":"Office Building",
            "type":"Public Place"
        }
    ],
    "sg:phone":"+1 478 746 6661",
    "sg:postcode":"31210",
    "sg:province":"GA",
    "sg:tags":[
        "park"
    ],
    "wof:name":"Coon Gulf Properties",
    "wof:placetype":"venue"
},
  "geometry": {"coordinates":[-83.679883,32.894216],"type":"Point"}
}