{
  "type": "Feature",
  "properties": {
    "addr:full":"2921 State Rte 18 West Point GA 31833",
    "addr:housenumber":"2921",
    "addr:postcode":"31833",
    "addr:street":"State Rte 18",
    "iso:country":"US",
    "sg:address":"2921 State Rte 18",
    "sg:city":"West Point",
    "sg:classifiers":[
        {
            "category":"Organizations",
            "subcategory":"Religious Organization",
            "type":"Services"
        }
    ],
    "sg:phone":"+1 706 645 2400",
    "sg:postcode":"31833",
    "sg:province":"GA",
    "sg:tags":[
        "church"
    ],
    "wof:name":"Davidson Baptist Church",
    "wof:placetype":"venue"
},
  "geometry": {"coordinates":[-85.121965,32.87715],"type":"Point"}
}