{
  "type": "Feature",
  "properties": {
    "addr:full":"2211 E Oglethorpe Blvd Albany GA 31705",
    "addr:housenumber":"2211",
    "addr:postcode":"31705",
    "addr:street":"E Oglethorpe Blvd",
    "iso:country":"US",
    "sg:address":"2211 E Oglethorpe Blvd",
    "sg:city":"Albany",
    "sg:classifiers":[
        {
            "category":"Restaurant",
            "type":"Food & Drink"
        }
    ],
    "sg:menulink":"http://www.allmenus.com/ga/east-dougherty/76093-dominos-pizza/menu/",
    "sg:phone":"+1 229 431 2000",
    "sg:postcode":"31705",
    "sg:province":"GA",
    "sg:tags":[
        "american",
        "wing",
        "pizza"
    ],
    "wof:name":"Domino's Pizza",
    "wof:placetype":"venue"
},
  "geometry": {"coordinates":[-84.097999,31.573525],"type":"Point"}
}