{
  "type": "Feature",
  "properties": {
    "addr:full":"1462 Winston Pl Decatur GA 30033",
    "addr:housenumber":"1462",
    "addr:postcode":"30033",
    "addr:street":"Winston Pl",
    "iso:country":"US",
    "sg:address":"1462 Winston Pl",
    "sg:city":"Decatur",
    "sg:classifiers":[
        {
            "category":"Real Estate",
            "subcategory":"Real Estate Agent",
            "type":"Services"
        }
    ],
    "sg:phone":"+1 404 633 4666",
    "sg:postcode":"30033",
    "sg:province":"GA",
    "wof:name":"Ivory Real Estate Group Inc",
    "wof:placetype":"venue"
},
  "geometry": {"coordinates":[-84.30036699999999,33.821337],"type":"Point"}
}