{
  "type": "Feature",
  "properties": {
    "addr:full":"1463 N Van Wert Rd Villa Rica GA 30180",
    "addr:housenumber":"1463",
    "addr:postcode":"30180",
    "addr:street":"N Van Wert Rd",
    "iso:country":"US",
    "sg:address":"1463 N Van Wert Rd",
    "sg:city":"Villa Rica",
    "sg:classifiers":[
        {
            "category":"Building & Trades",
            "subcategory":"Construction",
            "type":"Services"
        }
    ],
    "sg:phone":"+1 770 459 5491",
    "sg:postcode":"30180",
    "sg:province":"GA",
    "sg:tags":[
        "fabricator",
        "metal"
    ],
    "wof:name":"Diamond Metals",
    "wof:placetype":"venue"
},
  "geometry": {"coordinates":[-84.96575799999999,33.767025],"type":"Point"}
}