{
  "type": "Feature",
  "properties": {
    "iso:country":"US",
    "sg:address":"5806 Horse Shoe Rd",
    "sg:city":"Camilla",
    "sg:phone":"+1 229 336 7767",
    "sg:postcode":"31730",
    "sg:province":"GA",
    "sg:tags":[
        "farm",
        "field",
        "corn",
        "crop",
        "cotton"
    ],
    "wof:name":"David Holton Farms",
    "wof:placetype":"venue"
},
  "geometry": {"coordinates":[-84.26804799999999,31.271049],"type":"Point"}
}