{
  "type": "Feature",
  "properties": {
    "iso:country":"US",
    "sg:address":"1193 Collier Rd NW",
    "sg:city":"Atlanta",
    "sg:classifiers":[
        {
            "category":"Personal",
            "type":"Services"
        }
    ],
    "sg:phone":"+1 404 605 0001",
    "sg:postcode":"30318",
    "sg:province":"GA",
    "sg:tags":[
        "consultant",
        "program",
        "health",
        "fitness"
    ],
    "wof:name":"Bio Sculpt Enterprises",
    "wof:placetype":"venue"
},
  "geometry": {"coordinates":[-84.424916,33.811371],"type":"Point"}
}