{
  "type": "Feature",
  "properties": {
    "iso:country":"US",
    "sg:address":"1301 W Austin Rd",
    "sg:city":"Decatur",
    "sg:classifiers":[
        {
            "category":"Building & Trades",
            "subcategory":"Locksmith",
            "type":"Services"
        }
    ],
    "sg:phone":"+1 404 965 0535",
    "sg:postcode":"30032",
    "sg:province":"GA",
    "sg:tags":[
        "key"
    ],
    "wof:name":"A A Emerg A A A Locksmith",
    "wof:placetype":"venue"
},
  "geometry": {"coordinates":[-84.234677,33.754208],"type":"Point"}
}