{
  "type": "Feature",
  "properties": {
    "iso:country":"US",
    "sg:address":"102 N Broad St",
    "sg:city":"Thomasville",
    "sg:classifiers":[
        {
            "category":"Shopping",
            "subcategory":"Clothing, Apparel, & Fashions",
            "type":"Retail Goods"
        }
    ],
    "sg:phone":"+1 229 558 9014",
    "sg:postcode":"31792",
    "sg:province":"GA",
    "sg:tags":[
        "wear"
    ],
    "wof:name":"Frills & Freckles",
    "wof:placetype":"venue"
},
  "geometry": {"coordinates":[-83.981172,30.838675],"type":"Point"}
}