{
  "type": "Feature",
  "properties": {
    "addr:full":"1951 N Akin Dr NE Atlanta GA 30345",
    "addr:housenumber":"1951",
    "addr:postcode":"30345",
    "addr:street":"N Akin Dr Ne",
    "iso:country":"US",
    "sg:address":"1951 N Akin Dr NE",
    "sg:city":"Atlanta",
    "sg:classifiers":[
        {
            "category":"Shopping",
            "type":"Retail Goods"
        }
    ],
    "sg:phone":"+1 404 325 0688",
    "sg:postcode":"30345",
    "sg:province":"GA",
    "sg:tags":[
        "merchandise"
    ],
    "wof:name":"Acculine",
    "wof:placetype":"venue"
},
  "geometry": {"coordinates":[-84.28634,33.837675],"type":"Point"}
}