{
  "type": "Feature",
  "properties": {
    "iso:country":"US",
    "sg:address":"1621 Lucille Ave SW",
    "sg:city":"Stone Mountain",
    "sg:classifiers":[
        {
            "category":"Building & Trades",
            "subcategory":"Construction",
            "type":"Services"
        }
    ],
    "sg:phone":"+1 770 921 8615",
    "sg:postcode":"30087",
    "sg:province":"GA",
    "sg:tags":[
        "house"
    ],
    "wof:name":"Haneys Home Repair & Rmdlg",
    "wof:placetype":"venue"
},
  "geometry": {"coordinates":[-84.128247,33.829249],"type":"Point"}
}