{
  "type": "Feature",
  "properties": {
    "addr:full":"124 Pecan Ave Thomson GA 30824",
    "addr:housenumber":"124",
    "addr:postcode":"30824",
    "addr:street":"Pecan Ave",
    "iso:country":"US",
    "sg:address":"124 Pecan Ave",
    "sg:city":"Thomson",
    "sg:classifiers":[
        {
            "category":"Personal",
            "subcategory":"Beauty Salon",
            "type":"Services"
        }
    ],
    "sg:phone":"+1 706 597 3981",
    "sg:postcode":"30824",
    "sg:province":"GA",
    "wof:name":"Janae's Styleon",
    "wof:placetype":"venue"
},
  "geometry": {"coordinates":[-82.478684,33.474816],"type":"Point"}
}