{
  "type": "Feature",
  "properties": {
    "iso:country":"US",
    "sg:address":"217 S Elm St",
    "sg:city":"Adel",
    "sg:classifiers":[
        {
            "category":"Wholesale",
            "subcategory":"Auto Parts",
            "type":"Manufacturing & Wholesale Goods"
        }
    ],
    "sg:phone":"+1 229 896 4955",
    "sg:postcode":"31620",
    "sg:province":"GA",
    "sg:tags":[
        "truck",
        "accessory"
    ],
    "wof:name":"Weeks Wholesale",
    "wof:placetype":"venue"
},
  "geometry": {"coordinates":[-83.433407,31.132995],"type":"Point"}
}