{
  "type": "Feature",
  "properties": {
    "addr:full":"653 Pearce St SW Atlanta GA 30310",
    "addr:housenumber":"653",
    "addr:postcode":"30310",
    "addr:street":"Pearce St Sw",
    "iso:country":"US",
    "sg:address":"653 Pearce St SW",
    "sg:city":"Atlanta",
    "sg:classifiers":[
        {
            "category":"Organizations",
            "subcategory":"Non-profit Organization",
            "type":"Services"
        }
    ],
    "sg:phone":"+1 404 755 3208",
    "sg:postcode":"30310",
    "sg:province":"GA",
    "wof:name":"Adair Park Community Dev Corp",
    "wof:placetype":"venue"
},
  "geometry": {"coordinates":[-84.408266,33.729737],"type":"Point"}
}