{
  "type": "Feature",
  "properties": {
    "addr:full":"804 S Dixon St Alma GA 31510",
    "addr:housenumber":"804",
    "addr:postcode":"31510",
    "addr:street":"S Dixon St",
    "iso:country":"US",
    "sg:address":"804 S Dixon St",
    "sg:city":"Alma",
    "sg:classifiers":[
        {
            "category":"Restaurant",
            "type":"Food & Drink"
        }
    ],
    "sg:phone":"+1 912 632 1233",
    "sg:postcode":"31510",
    "sg:province":"GA",
    "wof:name":"Sandra's Home Cooking",
    "wof:placetype":"venue"
},
  "geometry": {"coordinates":[-82.465146,31.534122],"type":"Point"}
}