{
  "type": "Feature",
  "properties": {
    "addr:full":"4673 Presidential Pkwy Macon GA 31206",
    "addr:housenumber":"4673",
    "addr:postcode":"31206",
    "addr:street":"Presidential Pkwy",
    "iso:country":"US",
    "sg:address":"4673 Presidential Pkwy",
    "sg:city":"Macon",
    "sg:classifiers":[
        {
            "category":"Shopping",
            "subcategory":"Clothing, Apparel, & Fashions",
            "type":"Retail Goods"
        }
    ],
    "sg:phone":"+1 478 477 0840",
    "sg:postcode":"31206",
    "sg:province":"GA",
    "wof:name":"Avenue",
    "wof:placetype":"venue"
},
  "geometry": {"coordinates":[-83.715288,32.816528],"type":"Point"}
}