{
  "type": "Feature",
  "properties": {
    "addr:full":"1823 Thomas Mill Rd Plains GA 31780",
    "addr:housenumber":"1823",
    "addr:postcode":"31780",
    "addr:street":"Thomas Mill Rd",
    "iso:country":"US",
    "sg:address":"1823 Thomas Mill Rd",
    "sg:city":"Plains",
    "sg:classifiers":[
        {
            "category":"Wholesale",
            "subcategory":"Machinery & Supplies",
            "type":"Manufacturing & Wholesale Goods"
        }
    ],
    "sg:phone":"+1 229 824 5364",
    "sg:postcode":"31780",
    "sg:province":"GA",
    "sg:tags":[
        "engine"
    ],
    "wof:name":"Peek's Diesel Svc",
    "wof:placetype":"venue"
},
  "geometry": {"coordinates":[-84.42255900000001,31.968848],"type":"Point"}
}