{
  "type": "Feature",
  "properties": {
    "addr:full":"1217 Southlake Mall Morrow GA 30260",
    "addr:housenumber":"1217",
    "addr:postcode":"30260",
    "addr:street":"Southlake Mall",
    "iso:country":"US",
    "sg:address":"1217 Southlake Mall",
    "sg:city":"Morrow",
    "sg:classifiers":[
        {
            "category":"Shopping",
            "subcategory":"Shoes",
            "type":"Retail Goods"
        }
    ],
    "sg:phone":"+1 678 422 1143",
    "sg:postcode":"30260",
    "sg:province":"GA",
    "sg:tags":[
        "store"
    ],
    "wof:name":"Underground Station",
    "wof:placetype":"venue"
},
  "geometry": {"coordinates":[-84.34989899999999,33.573601],"type":"Point"}
}