{
  "type": "Feature",
  "properties": {
    "addr:full":"1011 Hicksmil Ct SW Marietta GA 30060",
    "addr:housenumber":"1011",
    "addr:postcode":"30060",
    "addr:street":"Hicksmil Ct Sw",
    "iso:country":"US",
    "sg:address":"1011 Hicksmil Ct SW",
    "sg:city":"Marietta",
    "sg:classifiers":[
        {
            "category":"Building & Trades",
            "subcategory":"Construction",
            "type":"Services"
        }
    ],
    "sg:phone":"+1 770 434 5128",
    "sg:postcode":"30060",
    "sg:province":"GA",
    "sg:tags":[
        "hanging",
        "contractor"
    ],
    "wof:name":"Olivares Painting",
    "wof:placetype":"venue"
},
  "geometry": {"coordinates":[-84.58244999999999,33.882575],"type":"Point"}
}