{
  "type": "Feature",
  "properties": {
    "iso:country":"US",
    "sg:address":"808 Club Place NW",
    "sg:city":"Atlanta",
    "sg:classifiers":[
        {
            "category":"Retail",
            "subcategory":"Laundry & Dry Cleaning",
            "type":"Services"
        }
    ],
    "sg:phone":"+1 770 497 8176",
    "sg:postcode":"30303",
    "sg:province":"GA",
    "wof:name":"Yvette Slay",
    "wof:placetype":"venue"
},
  "geometry": {"coordinates":[-84.38897,33.755418],"type":"Point"}
}