{
  "type": "Feature",
  "properties": {
    "addr:full":"161 Whisperwood Ln Marietta GA 30064",
    "addr:housenumber":"161",
    "addr:postcode":"30064",
    "addr:street":"Whisperwood Ln",
    "iso:country":"US",
    "sg:address":"161 Whisperwood Ln",
    "sg:city":"Marietta",
    "sg:classifiers":[
        {
            "category":"Manufacturing",
            "subcategory":"Retail Goods",
            "type":"Manufacturing & Wholesale Goods"
        }
    ],
    "sg:phone":"+1 770 919 7591",
    "sg:postcode":"30064",
    "sg:province":"GA",
    "sg:tags":[
        "product",
        "mfg"
    ],
    "wof:name":"Pdgi",
    "wof:placetype":"venue"
},
  "geometry": {"coordinates":[-84.657775,33.956337],"type":"Point"}
}