{
  "type": "Feature",
  "properties": {
    "iso:country":"US",
    "sg:address":"3129 Cobb Pkwy NW",
    "sg:city":"Kennesaw",
    "sg:classifiers":[
        {
            "category":"Food & Beverages",
            "subcategory":"Groceries & Convenience Stores",
            "type":"Retail Goods"
        }
    ],
    "sg:phone":"+1 770 974 3502",
    "sg:postcode":"30152",
    "sg:province":"GA",
    "sg:website":"www.circlek.com",
    "wof:name":"Circle K",
    "wof:placetype":"venue"
},
  "geometry": {"coordinates":[-84.650497,34.029202],"type":"Point"}
}