{
  "type": "Feature",
  "properties": {
    "iso:country":"US",
    "sg:address":"1830 Water Pl SE Ste #295",
    "sg:city":"Atlanta",
    "sg:classifiers":[
        {
            "category":"Health Services",
            "subcategory":"Clinic",
            "type":"Services"
        }
    ],
    "sg:phone":"+1 770 933 0213",
    "sg:postcode":"30339",
    "sg:province":"GA",
    "sg:tags":[
        "medical"
    ],
    "sg:website":"www.premierhealthandwellness.org",
    "wof:name":"Premiere Health and Wellness",
    "wof:placetype":"venue"
},
  "geometry": {"coordinates":[-84.484472,33.907295],"type":"Point"}
}