{
  "type": "Feature",
  "properties": {
    "iso:country":"US",
    "sg:address":"460 Tribble Gap Rd",
    "sg:city":"Cumming",
    "sg:classifiers":[
        {
            "category":"Professional",
            "subcategory":"Business Services",
            "type":"Services"
        }
    ],
    "sg:phone":"+1 770 886 5355",
    "sg:postcode":"30040",
    "sg:province":"GA",
    "wof:name":"Maroney Associates",
    "wof:placetype":"venue"
},
  "geometry": {"coordinates":[-84.13982300000001,34.21218],"type":"Point"}
}