{
  "type": "Feature",
  "properties": {
    "addr:full":"801 Doug Davis Drive Atlanta GA 30354",
    "addr:housenumber":"801",
    "addr:postcode":"30354",
    "addr:street":"Doug Davis Drive",
    "iso:country":"US",
    "sg:address":"801 Doug Davis Drive",
    "sg:city":"Atlanta",
    "sg:classifiers":[
        {
            "category":"Shopping",
            "subcategory":"Mobile Phones",
            "type":"Retail Goods"
        }
    ],
    "sg:phone":"+1 404 870 0160",
    "sg:postcode":"30354",
    "sg:province":"GA",
    "wof:name":"Nextel",
    "wof:placetype":"venue"
},
  "geometry": {"coordinates":[-84.41425700000001,33.657599],"type":"Point"}
}