{
  "type": "Feature",
  "properties": {
    "iso:country":"US",
    "sg:address":"1202 Columbia Dr Ste A",
    "sg:city":"Decatur",
    "sg:classifiers":[
        {
            "category":"Wholesale",
            "subcategory":"Office Equipment",
            "type":"Manufacturing & Wholesale Goods"
        },
        {
            "category":"Professional",
            "subcategory":"Accounting & Tax Preparation",
            "type":"Services"
        }
    ],
    "sg:phone":"+1 404 289 1047",
    "sg:postcode":"30032",
    "sg:province":"GA",
    "sg:tags":[
        "machine",
        "bookkeeping",
        "return",
        "supply"
    ],
    "wof:name":"Liberty Tax",
    "wof:placetype":"venue"
},
  "geometry": {"coordinates":[-84.266645,33.753863],"type":"Point"}
}