{
  "type": "Feature",
  "properties": {
    "addr:full":"217 Bradwell St Hinesville GA 31313",
    "addr:housenumber":"217",
    "addr:postcode":"31313",
    "addr:street":"Bradwell St",
    "iso:country":"US",
    "sg:address":"217 Bradwell St",
    "sg:city":"Hinesville",
    "sg:classifiers":[
        {
            "category":"Real Estate",
            "subcategory":"Real Estate Operator",
            "type":"Services"
        }
    ],
    "sg:phone":"+1 912 369 8255",
    "sg:postcode":"31313",
    "sg:province":"GA",
    "sg:tags":[
        "building",
        "apartment"
    ],
    "wof:name":"Baytree Apts",
    "wof:placetype":"venue"
},
  "geometry": {"coordinates":[-81.59210899999999,31.851766],"type":"Point"}
}