{
  "type": "Feature",
  "properties": {
    "iso:country":"US",
    "sg:address":"320 Lee Blvd",
    "sg:city":"Savannah",
    "sg:classifiers":[
        {
            "category":"Organizations",
            "subcategory":"Non-profit Organization",
            "type":"Services"
        }
    ],
    "sg:phone":"+1 912 354 9639",
    "sg:postcode":"31405",
    "sg:province":"GA",
    "sg:tags":[
        "social"
    ],
    "wof:name":"Multiple Sclerosis Group",
    "wof:placetype":"venue"
},
  "geometry": {"coordinates":[-81.10689600000001,32.018632],"type":"Point"}
}