{
  "type": "Feature",
  "properties": {
    "iso:country":"US",
    "sg:address":"1563 Richard Stokes Dr",
    "sg:city":"Decatur",
    "sg:classifiers":[
        {
            "category":"Shopping",
            "subcategory":"Jewelry",
            "type":"Retail Goods"
        },
        {
            "category":"Manufacturing",
            "subcategory":"Jewelry",
            "type":"Manufacturing & Wholesale Goods"
        }
    ],
    "sg:phone":"+1 404 486 7047",
    "sg:postcode":"30033",
    "sg:province":"GA",
    "sg:tags":[
        "manufacturer",
        "jewelers-wholesale",
        "jeweler"
    ],
    "wof:name":"Dazzling Dsign Seed Bead Works",
    "wof:placetype":"venue"
},
  "geometry": {"coordinates":[-84.282516,33.824898],"type":"Point"}
}