{
  "type": "Feature",
  "properties": {
    "addr:full":"2855 Candler Rd Ste 12 Decatur GA 30034",
    "addr:housenumber":"2855",
    "addr:postcode":"30034",
    "addr:street":"Candler Rd Ste 12",
    "iso:country":"US",
    "sg:address":"2855 Candler Rd Ste 12",
    "sg:city":"Decatur",
    "sg:classifiers":[
        {
            "category":"Health Services",
            "subcategory":"Doctor",
            "type":"Services"
        },
        {
            "category":"Health Services",
            "subcategory":"Dentist",
            "type":"Services"
        }
    ],
    "sg:phone":"+1 404 243 3210",
    "sg:postcode":"30034",
    "sg:province":"GA",
    "sg:tags":[
        "surgeon",
        "oral",
        "orthodontist"
    ],
    "wof:name":"Williams Craig B DDS",
    "wof:placetype":"venue"
},
  "geometry": {"coordinates":[-84.272003,33.706799],"type":"Point"}
}