{
  "type": "Feature",
  "properties": {
    "addr:full":"7 Allison Cir Cartersville GA 30120",
    "addr:housenumber":"7",
    "addr:postcode":"30120",
    "addr:street":"Allison Cir",
    "iso:country":"US",
    "sg:address":"7 Allison Cir",
    "sg:city":"Cartersville",
    "sg:classifiers":[
        {
            "category":"Professional",
            "type":"Services"
        }
    ],
    "sg:phone":"+1 770 386 3297",
    "sg:postcode":"30120",
    "sg:province":"GA",
    "wof:name":"Ernest Reade",
    "wof:placetype":"venue"
},
  "geometry": {"coordinates":[-84.80157199999999,34.154149],"type":"Point"}
}