{
  "type": "Feature",
  "properties": {
    "iso:country":"US",
    "sg:address":"4454 Harris Valley Rd NW",
    "sg:city":"Atlanta",
    "sg:classifiers":[
        {
            "category":"Professional",
            "subcategory":"Business Services",
            "type":"Services"
        }
    ],
    "sg:phone":"+1 404 261 3191",
    "sg:postcode":"30327",
    "sg:province":"GA",
    "wof:name":"Seitz Family Partnership LP",
    "wof:placetype":"venue"
},
  "geometry": {"coordinates":[-84.43516200000001,33.876343],"type":"Point"}
}