{
  "type": "Feature",
  "properties": {
    "addr:full":"101 New Franklin Rd Lagrange GA 30240",
    "addr:housenumber":"101",
    "addr:postcode":"30240",
    "addr:street":"New Franklin Rd",
    "iso:country":"US",
    "sg:address":"101 New Franklin Rd",
    "sg:city":"Lagrange",
    "sg:classifiers":[
        {
            "category":"Health Services",
            "subcategory":"Doctor",
            "type":"Services"
        }
    ],
    "sg:phone":"+1 706 845 4409",
    "sg:postcode":"30240",
    "sg:province":"GA",
    "sg:tags":[
        "clinic"
    ],
    "wof:name":"Spot",
    "wof:placetype":"venue"
},
  "geometry": {"coordinates":[-85.028582,33.057384],"type":"Point"}
}