{
  "type": "Feature",
  "properties": {
    "iso:country":"US",
    "sg:address":"6859 Duncan Rd",
    "sg:city":"Lula",
    "sg:classifiers":[
        {
            "category":"Shopping",
            "subcategory":"Stationery & Office Supplies",
            "type":"Retail Goods"
        }
    ],
    "sg:phone":"+1 770 869 7077",
    "sg:postcode":"30554",
    "sg:province":"GA",
    "wof:name":"Long Hall Office Supplies",
    "wof:placetype":"venue"
},
  "geometry": {"coordinates":[-83.66183700000001,34.408728],"type":"Point"}
}