{
  "type": "Feature",
  "properties": {
    "iso:country":"US",
    "sg:address":"130 Jarrell Hogg Rd",
    "sg:city":"West Point",
    "sg:classifiers":[
        {
            "category":"Building & Trades",
            "subcategory":"Cleaning & Sanitation",
            "type":"Services"
        },
        {
            "category":"Retail",
            "subcategory":"Repair Shop",
            "type":"Services"
        }
    ],
    "sg:phone":"+1 706 885 0469",
    "sg:postcode":"31833",
    "sg:province":"GA",
    "sg:tags":[
        "janitor",
        "maintenance"
    ],
    "wof:name":"Need A Break Cleaning Services",
    "wof:placetype":"venue"
},
  "geometry": {"coordinates":[-85.085279,32.919004],"type":"Point"}
}