{
  "type": "Feature",
  "properties": {
    "iso:country":"US",
    "sg:address":"3015 Dawsonville Hwy",
    "sg:city":"Gainesville",
    "sg:classifiers":[
        {
            "category":"Wholesale",
            "subcategory":"Machinery & Supplies",
            "type":"Manufacturing & Wholesale Goods"
        }
    ],
    "sg:phone":"+1 770 536 1455",
    "sg:postcode":"30506",
    "sg:province":"GA",
    "sg:tags":[
        "farm",
        "equipment",
        "tractor"
    ],
    "wof:name":"Vaughters Tractor Company Inc",
    "wof:placetype":"venue"
},
  "geometry": {"coordinates":[-83.92431500000001,34.330841],"type":"Point"}
}