{
  "type": "Feature",
  "properties": {
    "addr:full":"3243 Stone Road SW Atlanta GA 30331",
    "addr:housenumber":"3243",
    "addr:postcode":"30331",
    "addr:street":"Stone Road Sw",
    "iso:country":"US",
    "sg:address":"3243 Stone Road SW",
    "sg:city":"Atlanta",
    "sg:classifiers":[
        {
            "category":"Organizations",
            "subcategory":"Religious Organization",
            "type":"Services"
        }
    ],
    "sg:phone":"+1 404 349 2852",
    "sg:postcode":"30331",
    "sg:province":"GA",
    "wof:name":"Greenbriar Church of Christ",
    "wof:placetype":"venue"
},
  "geometry": {"coordinates":[-84.495249,33.670024],"type":"Point"}
}