{
  "type": "Feature",
  "properties": {
    "addr:full":"209 Blue Creek Ln Loganville GA 30052",
    "addr:housenumber":"209",
    "addr:postcode":"30052",
    "addr:street":"Blue Creek Ln",
    "iso:country":"US",
    "sg:address":"209 Blue Creek Ln",
    "sg:city":"Loganville",
    "sg:classifiers":[
        {
            "category":"Building & Trades",
            "subcategory":"Construction",
            "type":"Services"
        }
    ],
    "sg:phone":"+1 770 466 7927",
    "sg:postcode":"30052",
    "sg:province":"GA",
    "sg:tags":[
        "repair",
        "altering",
        "contractor",
        "maintenance",
        "home",
        "remodeling"
    ],
    "wof:name":"Midland Home Inspection Svc",
    "wof:placetype":"venue"
},
  "geometry": {"coordinates":[-83.932351,33.875351],"type":"Point"}
}