{
  "type": "Feature",
  "properties": {
    "addr:full":"195 Oak Shadow Way Fayetteville GA 30215",
    "addr:housenumber":"195",
    "addr:postcode":"30215",
    "addr:street":"Oak Shadow Way",
    "iso:country":"US",
    "sg:address":"195 Oak Shadow Way",
    "sg:city":"Fayetteville",
    "sg:classifiers":[
        {
            "category":"Wholesale",
            "subcategory":"Durable Goods & Equipment",
            "type":"Manufacturing & Wholesale Goods"
        }
    ],
    "sg:phone":"+1 770 461 6756",
    "sg:postcode":"30215",
    "sg:province":"GA",
    "wof:name":"Beaver Parts Supply Inc",
    "wof:placetype":"venue"
},
  "geometry": {"coordinates":[-84.51334799999999,33.354807],"type":"Point"}
}