{
  "type": "Feature",
  "properties": {
    "iso:country":"US",
    "sg:address":"835 Oglethorpe Ave SW",
    "sg:city":"Atlanta",
    "sg:classifiers":[
        {
            "category":"Shopping",
            "subcategory":"Jewelry",
            "type":"Retail Goods"
        }
    ],
    "sg:phone":"+1 404 756 0348",
    "sg:postcode":"30310",
    "sg:province":"GA",
    "wof:name":"Ly Silver",
    "wof:placetype":"venue"
},
  "geometry": {"coordinates":[-84.41561900000001,33.735907],"type":"Point"}
}