{
  "type": "Feature",
  "properties": {
    "addr:full":"1700 Water Pl SE Atlanta GA 30339",
    "addr:housenumber":"1700",
    "addr:postcode":"30339",
    "addr:street":"Water Pl Se",
    "iso:country":"US",
    "sg:address":"1700 Water Pl SE",
    "sg:city":"Atlanta",
    "sg:classifiers":[
        {
            "category":"Professional",
            "subcategory":"Management & Consulting",
            "type":"Services"
        }
    ],
    "sg:phone":"+1 770 951 9906",
    "sg:postcode":"30339",
    "sg:province":"GA",
    "wof:name":"Thacker & Loucks Fincl Svcs",
    "wof:placetype":"venue"
},
  "geometry": {"coordinates":[-84.484335,33.909245],"type":"Point"}
}