{
  "type": "Feature",
  "properties": {
    "addr:full":"13585 Birmingham Hwy Alpharetta GA 30004",
    "addr:housenumber":"13585",
    "addr:postcode":"30004",
    "addr:street":"Birmingham Hwy",
    "iso:country":"US",
    "sg:address":"13585 Birmingham Hwy",
    "sg:city":"Alpharetta",
    "sg:classifiers":[
        {
            "category":"Wholesale",
            "subcategory":"Farm Supplies",
            "type":"Manufacturing & Wholesale Goods"
        }
    ],
    "sg:phone":"+1 770 772 9635",
    "sg:postcode":"30004",
    "sg:province":"GA",
    "sg:tags":[
        "raw",
        "product",
        "material"
    ],
    "wof:name":"Premier Sporthorses",
    "wof:placetype":"venue"
},
  "geometry": {"coordinates":[-84.338026,34.113496],"type":"Point"}
}