{
  "type": "Feature",
  "properties": {
    "addr:full":"6128 Covington Hwy Lithonia GA 30058",
    "addr:housenumber":"6128",
    "addr:postcode":"30058",
    "addr:street":"Covington Hwy",
    "iso:country":"US",
    "sg:address":"6128 Covington Hwy",
    "sg:city":"Lithonia",
    "sg:classifiers":[
        {
            "category":"Food & Beverages",
            "subcategory":"Meat & Fish",
            "type":"Retail Goods"
        }
    ],
    "sg:phone":"+1 678 418 7001",
    "sg:postcode":"30058",
    "sg:province":"GA",
    "wof:name":"Fish & More",
    "wof:placetype":"venue"
},
  "geometry": {"coordinates":[-84.16201700000001,33.722128],"type":"Point"}
}