{
  "type": "Feature",
  "properties": {
    "iso:country":"US",
    "sg:address":"2176 Highpoint Rd",
    "sg:city":"Snellville",
    "sg:classifiers":[
        {
            "category":"Professional",
            "type":"Services"
        }
    ],
    "sg:phone":"+1 770 972 9794",
    "sg:postcode":"30078",
    "sg:province":"GA",
    "wof:name":"Richard E Lenhardt Jr Inc",
    "wof:placetype":"venue"
},
  "geometry": {"coordinates":[-84.041467,33.849205],"type":"Point"}
}