{
  "type": "Feature",
  "properties": {
    "addr:full":"1360 Union Hill Rd Alpharetta GA 30004",
    "addr:housenumber":"1360",
    "addr:postcode":"30004",
    "addr:street":"Union Hill Rd",
    "iso:country":"US",
    "sg:address":"1360 Union Hill Rd",
    "sg:city":"Alpharetta",
    "sg:classifiers":[
        {
            "category":"Real Estate",
            "subcategory":"Real Estate Agent",
            "type":"Services"
        }
    ],
    "sg:phone":"+1 770 844 7166",
    "sg:postcode":"30004",
    "sg:province":"GA",
    "wof:name":"Union Hill Property Management",
    "wof:placetype":"venue"
},
  "geometry": {"coordinates":[-84.236805,34.114236],"type":"Point"}
}