{
  "type": "Feature",
  "properties": {
    "iso:country":"US",
    "sg:address":"3581 Briar Dr",
    "sg:city":"Lithia Springs",
    "sg:classifiers":[
        {
            "category":"Building & Trades",
            "subcategory":"Landscaping Services",
            "type":"Services"
        }
    ],
    "sg:phone":"+1 770 732 9760",
    "sg:postcode":"30122",
    "sg:province":"GA",
    "wof:name":"Ratz Stump Grinding Lawn",
    "wof:placetype":"venue"
},
  "geometry": {"coordinates":[-84.662863,33.747956],"type":"Point"}
}