{
  "type": "Feature",
  "properties": {
    "addr:full":"2033 Buford Hwy Ste 111 Buford GA 30518",
    "addr:housenumber":"2033",
    "addr:postcode":"30518",
    "addr:street":"Buford Hwy Ste 111",
    "iso:country":"US",
    "sg:address":"2033 Buford Hwy Ste 111",
    "sg:city":"Buford",
    "sg:classifiers":[
        {
            "category":"Restaurant",
            "type":"Food & Drink"
        }
    ],
    "sg:phone":"+1 770 932 1188",
    "sg:postcode":"30518",
    "sg:province":"GA",
    "sg:tags":[
        "pizza"
    ],
    "wof:name":"Little Caesar's",
    "wof:placetype":"venue"
},
  "geometry": {"coordinates":[-84.00009,34.10912],"type":"Point"}
}