{
  "type": "Feature",
  "properties": {
    "iso:country":"US",
    "sg:address":"1470 Webster Lake Rd",
    "sg:city":"Cleveland",
    "sg:classifiers":[
        {
            "category":"Organizations",
            "subcategory":"Religious Organization",
            "type":"Services"
        }
    ],
    "sg:phone":"+1 706 865 1567",
    "sg:postcode":"30528",
    "sg:province":"GA",
    "sg:website":"www.whitecreekbaptistchurch.com",
    "wof:name":"White Creek Baptist Church",
    "wof:placetype":"venue"
},
  "geometry": {"coordinates":[-83.667896,34.530713],"type":"Point"}
}