{
  "type": "Feature",
  "properties": {
    "iso:country":"US",
    "sg:address":"520 6th Ave",
    "sg:city":"Columbus",
    "sg:phone":"+1 706 322 3297",
    "sg:postcode":"31901",
    "sg:province":"GA",
    "sg:tags":[
        "oil",
        "gasoline"
    ],
    "wof:name":"Fletcher Oil",
    "wof:placetype":"venue"
},
  "geometry": {"coordinates":[-84.984757,32.456731],"type":"Point"}
}