{
  "type": "Feature",
  "properties": {
    "iso:country":"US",
    "sg:address":"3680 Hickory Ridge Ct NE",
    "sg:city":"Marietta",
    "sg:classifiers":[
        {
            "category":"Freight",
            "type":"Transportation"
        }
    ],
    "sg:phone":"+1 770 977 9525",
    "sg:postcode":"30066",
    "sg:province":"GA",
    "sg:tags":[
        "operator",
        "local",
        "trucking"
    ],
    "wof:name":"Simpson Hauling Inc",
    "wof:placetype":"venue"
},
  "geometry": {"coordinates":[-84.507606,34.040945],"type":"Point"}
}