{
  "type": "Feature",
  "properties": {
    "iso:country":"US",
    "sg:address":"6740 Shannon Pkwy",
    "sg:city":"Union City",
    "sg:classifiers":[
        {
            "category":"Personal",
            "subcategory":"Barber",
            "type":"Services"
        }
    ],
    "sg:phone":"+1 770 969 4110",
    "sg:postcode":"30291",
    "sg:province":"GA",
    "sg:tags":[
        "shop"
    ],
    "wof:name":"J B and Company Barber Studio",
    "wof:placetype":"venue"
},
  "geometry": {"coordinates":[-84.539255,33.571339],"type":"Point"}
}