{
  "type": "Feature",
  "properties": {
    "addr:full":"2379 Radio Station Rd Alma GA 31510",
    "addr:housenumber":"2379",
    "addr:postcode":"31510",
    "addr:street":"Station Rd",
    "iso:country":"US",
    "sg:address":"2379 Radio Station Rd",
    "sg:city":"Alma",
    "sg:classifiers":[
        {
            "category":"Manufacturing",
            "subcategory":"Food",
            "type":"Manufacturing & Wholesale Goods"
        },
        {
            "category":"Home & Garden",
            "subcategory":"Garden Supply",
            "type":"Retail Goods"
        }
    ],
    "sg:phone":"+1 912 632 6731",
    "sg:postcode":"31510",
    "sg:province":"GA",
    "sg:tags":[
        "canned",
        "nurseryman",
        "mfg"
    ],
    "wof:name":"Wade Blueberry Nursery Inc",
    "wof:placetype":"venue"
},
  "geometry": {"coordinates":[-82.373482,31.437585],"type":"Point"}
}