{
  "type": "Feature",
  "properties": {
    "iso:country":"US",
    "sg:address":"110 E Oglethorpe Ave",
    "sg:city":"Savannah",
    "sg:classifiers":[
        {
            "category":"Professional",
            "subcategory":"Lawyer & Legal Services",
            "type":"Services"
        }
    ],
    "sg:phone":"+1 912 233 7961",
    "sg:postcode":"31401",
    "sg:province":"GA",
    "sg:tags":[
        "attorney",
        "criminal",
        "law"
    ],
    "wof:name":"Mahoney, Thomas J III",
    "wof:placetype":"venue"
},
  "geometry": {"coordinates":[-81.09114,32.076571],"type":"Point"}
}