{
  "type": "Feature",
  "properties": {
    "addr:full":"4636 Hickory Creek Cir Valdosta GA 31602",
    "addr:housenumber":"4636",
    "addr:postcode":"31602",
    "addr:street":"Hickory Creek Cir",
    "iso:country":"US",
    "sg:address":"4636 Hickory Creek Cir",
    "sg:city":"Valdosta",
    "sg:classifiers":[
        {
            "category":"Wholesale",
            "subcategory":"Construction Materials",
            "type":"Manufacturing & Wholesale Goods"
        }
    ],
    "sg:phone":"+1 229 244 5535",
    "sg:postcode":"31602",
    "sg:province":"GA",
    "sg:tags":[
        "lumber"
    ],
    "wof:name":"Di Pietro Inc",
    "wof:placetype":"venue"
},
  "geometry": {"coordinates":[-83.356191,30.917946],"type":"Point"}
}