{
  "type": "Feature",
  "properties": {
    "addr:full":"12417 White Bluff Rd Savannah GA 31419",
    "addr:housenumber":"12417",
    "addr:postcode":"31419",
    "addr:street":"White Bluff Rd",
    "iso:country":"US",
    "sg:address":"12417 White Bluff Rd",
    "sg:city":"Savannah",
    "sg:classifiers":[
        {
            "category":"Restaurant",
            "type":"Food & Drink"
        }
    ],
    "sg:phone":"+1 912 921 7800",
    "sg:postcode":"31419",
    "sg:province":"GA",
    "sg:tags":[
        "pizza",
        "italian"
    ],
    "wof:name":"Vincenzo's Pizzeria and Pastas",
    "wof:placetype":"venue"
},
  "geometry": {"coordinates":[-81.13256199999999,31.974651],"type":"Point"}
}