{
  "type": "Feature",
  "properties": {
    "iso:country":"US",
    "sg:address":"55 Kathy Ct",
    "sg:city":"Canton",
    "sg:classifiers":[
        {
            "category":"Building & Trades",
            "subcategory":"Construction",
            "type":"Services"
        }
    ],
    "sg:phone":"+1 770 479 0062",
    "sg:postcode":"30114",
    "sg:province":"GA",
    "sg:tags":[
        "home",
        "improvement"
    ],
    "wof:name":"Integrity Plus Contracting",
    "wof:placetype":"venue"
},
  "geometry": {"coordinates":[-84.521874,34.155073],"type":"Point"}
}