{
  "type": "Feature",
  "properties": {
    "addr:full":"1313 W 3rd St Jackson GA 30233",
    "addr:housenumber":"1313",
    "addr:postcode":"30233",
    "addr:street":"W 3Rd St",
    "iso:country":"US",
    "sg:address":"1313 W 3rd St",
    "sg:city":"Jackson",
    "sg:phone":"+1 770 504 0509",
    "sg:postcode":"30233",
    "sg:province":"GA",
    "sg:website":"http://www.dollargeneral.com",
    "wof:name":"Dollar General",
    "wof:placetype":"venue"
},
  "geometry": {"coordinates":[-83.983178,33.292904],"type":"Point"}
}