{
  "type": "Feature",
  "properties": {
    "addr:full":"4959 Jonesboro Rd Forest Park GA 30297",
    "addr:housenumber":"4959",
    "addr:postcode":"30297",
    "addr:street":"Jonesboro Rd",
    "iso:country":"US",
    "sg:address":"4959 Jonesboro Rd",
    "sg:city":"Forest Park",
    "sg:classifiers":[
        {
            "category":"Fast Food",
            "type":"Food & Drink"
        }
    ],
    "sg:phone":"+1 404 361 3443",
    "sg:postcode":"30297",
    "sg:province":"GA",
    "sg:website":"www.chick-fil-a.com",
    "wof:name":"Chick-Fil-A Inc",
    "wof:placetype":"venue"
},
  "geometry": {"coordinates":[-84.351097,33.6194],"type":"Point"}
}