{
  "type": "Feature",
  "properties": {
    "iso:country":"US",
    "sg:address":"82 Galilee Church Rd",
    "sg:city":"Jefferson",
    "sg:classifiers":[
        {
            "category":"Manufacturing",
            "subcategory":"Rubber & Plastics",
            "type":"Manufacturing & Wholesale Goods"
        }
    ],
    "sg:phone":"+1 706 367 2616",
    "sg:postcode":"30549",
    "sg:province":"GA",
    "sg:tags":[
        "packaging",
        "mfg",
        "material",
        "polystyrene"
    ],
    "sg:website":"www.foamfabricators.com",
    "wof:name":"Foam Fabricators Inc",
    "wof:placetype":"venue"
},
  "geometry": {"coordinates":[-83.572923,34.095548],"type":"Point"}
}