{
  "type": "Feature",
  "properties": {
    "addr:full":"605 W Broad Ave Doerun GA 31744",
    "addr:housenumber":"605",
    "addr:postcode":"31744",
    "addr:street":"W Broad Ave",
    "iso:country":"US",
    "sg:address":"605 W Broad Ave",
    "sg:city":"Doerun",
    "sg:classifiers":[
        {
            "category":"Shopping",
            "subcategory":"Discount & Variety Stores",
            "type":"Retail Goods"
        }
    ],
    "sg:phone":"+1 229 782 5229",
    "sg:postcode":"31744",
    "sg:province":"GA",
    "wof:name":"Dollar General",
    "wof:placetype":"venue"
},
  "geometry": {"coordinates":[-83.922251,31.319726],"type":"Point"}
}