{
  "type": "Feature",
  "properties": {
    "iso:country":"US",
    "sg:address":"1323 E Shotwell St",
    "sg:city":"Bainbridge",
    "sg:classifiers":[
        {
            "category":"Health Services",
            "subcategory":"Doctor",
            "type":"Services"
        }
    ],
    "sg:phone":"+1 229 246 2900",
    "sg:postcode":"39819",
    "sg:province":"FL",
    "sg:tags":[
        "physician",
        "surgeon"
    ],
    "wof:name":"Urology Institute & Continence",
    "wof:placetype":"venue"
},
  "geometry": {"coordinates":[-84.557472,30.903981],"type":"Point"}
}