{
  "type": "Feature",
  "properties": {
    "iso:country":"US",
    "sg:address":"1110 N 5th Ave",
    "sg:city":"Rome",
    "sg:classifiers":[
        {
            "category":"Social Services",
            "subcategory":"Child Care",
            "type":"Services"
        }
    ],
    "sg:phone":"+1 706 295 1990",
    "sg:postcode":"30165",
    "sg:province":"GA",
    "sg:tags":[
        "kindergarten",
        "academic",
        "school",
        "day"
    ],
    "wof:name":"Sunshine Montessori School Inc",
    "wof:placetype":"venue"
},
  "geometry": {"coordinates":[-85.179356,34.265846],"type":"Point"}
}