{
  "type": "Feature",
  "properties": {
    "addr:full":"100 Travelers Way Saint Simons Island GA 31522",
    "addr:housenumber":"100",
    "addr:postcode":"31522",
    "addr:street":"Travelers Way",
    "iso:country":"US",
    "sg:address":"100 Travelers Way",
    "sg:city":"Saint Simons Island",
    "sg:classifiers":[
        {
            "category":"Health Services",
            "subcategory":"Optometrist",
            "type":"Services"
        }
    ],
    "sg:phone":"+1 912 634 1230",
    "sg:postcode":"31522",
    "sg:province":"GA",
    "wof:name":"Milmot Lewis Dr",
    "wof:placetype":"venue"
},
  "geometry": {"coordinates":[-81.395656,31.164773],"type":"Point"}
}