{
  "type": "Feature",
  "properties": {
    "iso:country":"US",
    "sg:address":"4343 N Shallowford Rd",
    "sg:city":"Atlanta",
    "sg:classifiers":[
        {
            "category":"Utilities",
            "subcategory":"Telephone",
            "type":"Services"
        }
    ],
    "sg:phone":"+1 678 352 2311",
    "sg:postcode":"30341",
    "sg:province":"GA",
    "sg:tags":[
        "telecommunication"
    ],
    "wof:name":"1 Source Intl",
    "wof:placetype":"venue"
},
  "geometry": {"coordinates":[-84.30512400000001,33.920218],"type":"Point"}
}