{
  "type": "Feature",
  "properties": {
    "iso:country":"US",
    "sg:address":"2753 Waters Rd",
    "sg:city":"Atlanta",
    "sg:classifiers":[
        {
            "category":"Social Services",
            "type":"Services"
        }
    ],
    "sg:phone":"+1 404 875 8444",
    "sg:postcode":"30354",
    "sg:province":"GA",
    "sg:tags":[
        "senior",
        "citizen"
    ],
    "wof:name":"ACT Express",
    "wof:placetype":"venue"
},
  "geometry": {"coordinates":[-84.39010399999999,33.679721],"type":"Point"}
}