{
  "type": "Feature",
  "properties": {
    "addr:full":"1 Golf Club Dr Alpharetta GA 30005",
    "addr:housenumber":"1",
    "addr:postcode":"30005",
    "addr:street":"Golf Club Dr",
    "iso:country":"US",
    "sg:address":"1 Golf Club Dr",
    "sg:city":"Alpharetta",
    "sg:classifiers":[
        {
            "category":"Sports & Exercise",
            "subcategory":"Golf",
            "type":"Entertainment"
        }
    ],
    "sg:phone":"+1 770 664 8644",
    "sg:postcode":"30005",
    "sg:province":"GA",
    "sg:tags":[
        "course",
        "courses-private"
    ],
    "sg:website":"http://www.golfclubofgeorgia.com",
    "wof:name":"Golf Club Of Georgia, Inc.",
    "wof:placetype":"venue"
},
  "geometry": {"coordinates":[-84.220062,34.087219],"type":"Point"}
}