{
  "type": "Feature",
  "properties": {
    "addr:full":"2215 D and B Dr SE Marietta GA 30067",
    "addr:housenumber":"2215 d",
    "addr:postcode":"30067",
    "addr:street":"And B Dr Se",
    "iso:country":"US",
    "sg:address":"2215 D and B Dr SE",
    "sg:city":"Marietta",
    "sg:classifiers":[
        {
            "category":"Restaurant",
            "type":"Food & Drink"
        }
    ],
    "sg:menulink":"http://www.allmenus.com/ga/marietta/105756-dave--busters/menu/",
    "sg:phone":"+1 770 951 5554",
    "sg:postcode":"30067",
    "sg:province":"GA",
    "sg:tags":[
        "american",
        "pub"
    ],
    "wof:name":"Dave & Buster's",
    "wof:placetype":"venue"
},
  "geometry": {"coordinates":[-84.486727,33.919306],"type":"Point"}
}