{
  "type": "Feature",
  "properties": {
    "addr:full":"779 Locks Way Ct Augusta GA 30907",
    "addr:housenumber":"779",
    "addr:postcode":"30907",
    "addr:street":"Locks Way Ct",
    "iso:country":"US",
    "sg:address":"779 Locks Way Ct",
    "sg:city":"Augusta",
    "sg:classifiers":[
        {
            "category":"Education",
            "subcategory":"Vocational School",
            "type":"Public Place"
        }
    ],
    "sg:phone":"+1 706 855 6267",
    "sg:postcode":"30907",
    "sg:province":"GA",
    "sg:tags":[
        "processing",
        "datum",
        "business"
    ],
    "wof:name":"Fenco Computer Training & Services",
    "wof:placetype":"venue"
},
  "geometry": {"coordinates":[-82.073159,33.55687],"type":"Point"}
}