{
  "type": "Feature",
  "properties": {
    "addr:full":"568 Briar Hill Ct Riverdale GA 30274",
    "addr:housenumber":"568",
    "addr:postcode":"30274",
    "addr:street":"Briar Hill Ct",
    "iso:country":"US",
    "sg:address":"568 Briar Hill Ct",
    "sg:city":"Riverdale",
    "sg:classifiers":[
        {
            "category":"Professional",
            "subcategory":"Business Services",
            "type":"Services"
        }
    ],
    "sg:phone":"+1 770 909 9562",
    "sg:postcode":"30274",
    "sg:province":"GA",
    "wof:name":"Distinee Enterprise",
    "wof:placetype":"venue"
},
  "geometry": {"coordinates":[-84.41063200000001,33.592114],"type":"Point"}
}