{
  "type": "Feature",
  "properties": {
    "addr:full":"3893 N Druid Hills Rd Decatur GA 30033",
    "addr:housenumber":"3893",
    "addr:postcode":"30033",
    "addr:street":"N Druid Hills Rd",
    "iso:country":"US",
    "sg:address":"3893 N Druid Hills Rd",
    "sg:city":"Decatur",
    "sg:classifiers":[
        {
            "category":"Restaurant",
            "type":"Food & Drink"
        }
    ],
    "sg:phone":"+1 404 248 0507",
    "sg:postcode":"30033",
    "sg:province":"GA",
    "sg:tags":[
        "eating"
    ],
    "wof:name":"McDonalds",
    "wof:placetype":"venue"
},
  "geometry": {"coordinates":[-84.273608,33.810339],"type":"Point"}
}