{
  "type": "Feature",
  "properties": {
    "iso:country":"US",
    "sg:address":"3360 Satellite Blvd Ste 14",
    "sg:city":"Duluth",
    "sg:classifiers":[
        {
            "category":"Shopping",
            "subcategory":"Hobbies, Toys, & Games",
            "type":"Retail Goods"
        }
    ],
    "sg:phone":"+1 770 418 0850",
    "sg:postcode":"30096",
    "sg:province":"GA",
    "sg:tags":[
        "shop",
        "hobby",
        "model",
        "toy",
        "store"
    ],
    "sg:website":"www.hobbytownduluth.com",
    "wof:name":"Hobbytown USA",
    "wof:placetype":"venue"
},
  "geometry": {"coordinates":[-84.128502,33.9645],"type":"Point"}
}