{
  "type": "Feature",
  "properties": {
    "addr:full":"4955 N Henry Blvd Stockbridge GA 30281",
    "addr:housenumber":"4955",
    "addr:postcode":"30281",
    "addr:street":"N Henry Blvd",
    "iso:country":"US",
    "sg:address":"4955 N Henry Blvd",
    "sg:city":"Stockbridge",
    "sg:classifiers":[
        {
            "category":"Wholesale",
            "subcategory":"Furniture",
            "type":"Manufacturing & Wholesale Goods"
        }
    ],
    "sg:phone":"+1 770 506 9007",
    "sg:postcode":"30281",
    "sg:province":"GA",
    "sg:tags":[
        "equipment",
        "sporting",
        "playground"
    ],
    "wof:name":"Swings Etc",
    "wof:placetype":"venue"
},
  "geometry": {"coordinates":[-84.24078799999999,33.544365],"type":"Point"}
}