{
  "type": "Feature",
  "properties": {
    "iso:country":"US",
    "sg:address":"4664 Jimmy Carter Blvd",
    "sg:city":"Norcross",
    "sg:classifiers":[
        {
            "category":"Home & Garden",
            "subcategory":"Furniture",
            "type":"Retail Goods"
        }
    ],
    "sg:phone":"+1 770 925 1525",
    "sg:postcode":"30093",
    "sg:province":"GA",
    "wof:name":"Town & Country Furniture",
    "wof:placetype":"venue"
},
  "geometry": {"coordinates":[-84.19458,33.889068],"type":"Point"}
}