{
  "type": "Feature",
  "properties": {
    "iso:country":"US",
    "sg:address":"2964 Peachtree Road NW",
    "sg:city":"Atlanta",
    "sg:classifiers":[
        {
            "category":"Professional",
            "subcategory":"Accounting & Tax Preparation",
            "type":"Services"
        }
    ],
    "sg:phone":"+1 404 261 5822",
    "sg:postcode":"30305",
    "sg:province":"GA",
    "sg:tags":[
        "accountant"
    ],
    "wof:name":"Solomon Edward D CPA",
    "wof:placetype":"venue"
},
  "geometry": {"coordinates":[-84.381944,33.83577],"type":"Point"}
}