{
  "type": "Feature",
  "properties": {
    "iso:country":"US",
    "sg:address":"31 Kriswood Dr",
    "sg:city":"Rossville",
    "sg:classifiers":[
        {
            "category":"Building & Trades",
            "subcategory":"Construction",
            "type":"Services"
        }
    ],
    "sg:phone":"+1 706 861 6538",
    "sg:postcode":"30741",
    "sg:province":"GA",
    "sg:tags":[
        "downspouts",
        "gutter"
    ],
    "wof:name":"Dunn & Son Guttering",
    "wof:placetype":"venue"
},
  "geometry": {"coordinates":[-85.270528,34.964919],"type":"Point"}
}