{
  "type": "Feature",
  "properties": {
    "addr:full":"1495 Alpharetta Hwy Alpharetta GA 30004",
    "addr:housenumber":"1495",
    "addr:postcode":"30004",
    "addr:street":"Alpharetta Hwy",
    "iso:country":"US",
    "sg:address":"1495 Alpharetta Hwy",
    "sg:city":"Alpharetta",
    "sg:classifiers":[
        {
            "category":"Insurance",
            "subcategory":"Insurance Agent",
            "type":"Services"
        }
    ],
    "sg:phone":"+1 770 442 1086",
    "sg:postcode":"30004",
    "sg:province":"GA",
    "wof:name":"Gupton Mark Cpcu CLU",
    "wof:placetype":"venue"
},
  "geometry": {"coordinates":[-84.307805,34.066189],"type":"Point"}
}