{
  "type": "Feature",
  "properties": {
    "addr:full":"114 W Patten St La Fayette GA 30728",
    "addr:housenumber":"114",
    "addr:postcode":"30728",
    "addr:street":"W Patten St;Fayette",
    "iso:country":"US",
    "sg:address":"114 W Patten St",
    "sg:city":"La Fayette",
    "sg:classifiers":[
        {
            "category":"Government",
            "subcategory":"Jail",
            "type":"Public Place"
        }
    ],
    "sg:phone":"+1 706 638 5531",
    "sg:postcode":"30728",
    "sg:province":"GA",
    "sg:tags":[
        "probation"
    ],
    "wof:name":"Probation Office",
    "wof:placetype":"venue"
},
  "geometry": {"coordinates":[-85.28230000000001,34.704502],"type":"Point"}
}