{
  "type": "Feature",
  "properties": {
    "addr:full":"5030 Red Bud Dr Grovetown GA 30813",
    "addr:housenumber":"5030",
    "addr:postcode":"30813",
    "addr:street":"Red Bud Dr",
    "iso:country":"US",
    "sg:address":"5030 Red Bud Dr",
    "sg:city":"Grovetown",
    "sg:classifiers":[
        {
            "category":"Building & Trades",
            "subcategory":"Landscaping Services",
            "type":"Services"
        }
    ],
    "sg:phone":"+1 706 863 9266",
    "sg:postcode":"30813",
    "sg:province":"GA",
    "wof:name":"Mims Tree Service",
    "wof:placetype":"venue"
},
  "geometry": {"coordinates":[-82.185827,33.485898],"type":"Point"}
}