{
  "type": "Feature",
  "properties": {
    "iso:country":"US",
    "sg:address":"116 Weaver Rd",
    "sg:city":"Warner Robins",
    "sg:classifiers":[
        {
            "category":"Shopping",
            "subcategory":"Hobbies, Toys, & Games",
            "type":"Retail Goods"
        }
    ],
    "sg:phone":"+1 478 953 3782",
    "sg:postcode":"31093",
    "sg:province":"GA",
    "sg:tags":[
        "railroad"
    ],
    "sg:website":"www.grampas-trains.com",
    "wof:name":"Grandpa's Trains",
    "wof:placetype":"venue"
},
  "geometry": {"coordinates":[-83.67568,32.639878],"type":"Point"}
}