{
  "type": "Feature",
  "properties": {
    "addr:full":"3625 Dallas Hwy SW Marietta GA 30064",
    "addr:housenumber":"3625",
    "addr:postcode":"30064",
    "addr:street":"Dallas Hwy Sw",
    "iso:country":"US",
    "sg:address":"3625 Dallas Hwy SW",
    "sg:city":"Marietta",
    "sg:classifiers":[
        {
            "category":"Personal",
            "subcategory":"Beauty Salon",
            "type":"Services"
        },
        {
            "category":"Personal",
            "subcategory":"Day Spa",
            "type":"Services"
        }
    ],
    "sg:phone":"+1 678 581 8783",
    "sg:postcode":"30064",
    "sg:province":"GA",
    "sg:tags":[
        "hair"
    ],
    "sg:website":"www.truesalonatlanta.com",
    "wof:name":"True Aveda Salon",
    "wof:placetype":"venue"
},
  "geometry": {"coordinates":[-84.657917,33.953442],"type":"Point"}
}