{
  "type": "Feature",
  "properties": {
    "addr:full":"100 Cameron Pt Ct Lagrange GA 30240",
    "addr:housenumber":"100",
    "addr:postcode":"30240",
    "addr:street":"Cameron Pt Ct",
    "iso:country":"US",
    "sg:address":"100 Cameron Pt Ct",
    "sg:city":"Lagrange",
    "sg:classifiers":[
        {
            "category":"Organizations",
            "subcategory":"Professional Association",
            "type":"Services"
        }
    ],
    "sg:phone":"+1 706 845 9991",
    "sg:postcode":"30240",
    "sg:province":"GA",
    "wof:name":"Cameron Point Homeowners Assn",
    "wof:placetype":"venue"
},
  "geometry": {"coordinates":[-85.091178,33.096499],"type":"Point"}
}