{
  "type": "Feature",
  "properties": {
    "addr:full":"2475 Village Dr Kingsland GA 31548",
    "addr:housenumber":"2475",
    "addr:postcode":"31548",
    "addr:street":"Village Dr",
    "iso:country":"US",
    "sg:address":"2475 Village Dr",
    "sg:city":"Kingsland",
    "sg:classifiers":[
        {
            "category":"Health Services",
            "subcategory":"Doctor",
            "type":"Services"
        }
    ],
    "sg:phone":"+1 912 673 8415",
    "sg:postcode":"31548",
    "sg:province":"GA",
    "sg:tags":[
        "physician",
        "surgeon"
    ],
    "wof:name":"B.I.O Inc",
    "wof:placetype":"venue"
},
  "geometry": {"coordinates":[-81.619264,30.771886],"type":"Point"}
}