{
  "type": "Feature",
  "properties": {
    "addr:full":"1470 Dale Ct Austell GA 30168",
    "addr:housenumber":"1470",
    "addr:postcode":"30168",
    "addr:street":"Dale Ct",
    "iso:country":"US",
    "sg:address":"1470 Dale Ct",
    "sg:city":"Austell",
    "sg:classifiers":[
        {
            "category":"Building & Trades",
            "subcategory":"Construction",
            "type":"Services"
        }
    ],
    "sg:phone":"+1 404 351 2202",
    "sg:postcode":"30168",
    "sg:province":"GA",
    "sg:tags":[
        "steel",
        "detailers",
        "structural"
    ],
    "wof:name":"Lcmi",
    "wof:placetype":"venue"
},
  "geometry": {"coordinates":[-84.621647,33.798568],"type":"Point"}
}