{
  "type": "Feature",
  "properties": {
    "addr:full":"45 Wynn Dr Hampton GA 30228",
    "addr:housenumber":"45",
    "addr:postcode":"30228",
    "addr:street":"Wynn Dr",
    "iso:country":"US",
    "sg:address":"45 Wynn Dr",
    "sg:city":"Hampton",
    "sg:classifiers":[
        {
            "category":"Building & Trades",
            "subcategory":"Construction",
            "type":"Services"
        }
    ],
    "sg:phone":"+1 770 946 9739",
    "sg:postcode":"30228",
    "sg:province":"GA",
    "sg:tags":[
        "house"
    ],
    "wof:name":"Jj Associates",
    "wof:placetype":"venue"
},
  "geometry": {"coordinates":[-84.26130499999999,33.418244],"type":"Point"}
}