{
  "type": "Feature",
  "properties": {
    "iso:country":"US",
    "sg:address":"145 Alcovy Forest Dr",
    "sg:city":"Covington",
    "sg:classifiers":[
        {
            "category":"Building & Trades",
            "subcategory":"Plumbing",
            "type":"Services"
        }
    ],
    "sg:phone":"+1 770 788 3005",
    "sg:postcode":"30014",
    "sg:province":"GA",
    "sg:tags":[
        "air",
        "heating",
        "conditioning",
        "contractor"
    ],
    "wof:name":"Airmax Inc",
    "wof:placetype":"venue"
},
  "geometry": {"coordinates":[-83.78487699999999,33.652796],"type":"Point"}
}