{
  "type": "Feature",
  "properties": {
    "iso:country":"US",
    "sg:address":"1111 Clairemont Ave",
    "sg:city":"Decatur",
    "sg:classifiers":[
        {
            "category":"Professional",
            "subcategory":"Management & Consulting",
            "type":"Services"
        }
    ],
    "sg:phone":"+1 404 633 3888",
    "sg:postcode":"30030",
    "sg:province":"GA",
    "sg:tags":[
        "public",
        "relations"
    ],
    "wof:name":"Pandemonium Promotions",
    "wof:placetype":"venue"
},
  "geometry": {"coordinates":[-84.30635700000001,33.786865],"type":"Point"}
}