{
  "type": "Feature",
  "properties": {
    "addr:full":"806 Clifton Way NE Atlanta GA 30329",
    "addr:housenumber":"806",
    "addr:postcode":"30329",
    "addr:street":"Clifton Way Ne",
    "iso:country":"US",
    "sg:address":"806 Clifton Way NE",
    "sg:city":"Atlanta",
    "sg:classifiers":[
        {
            "category":"Building & Trades",
            "subcategory":"Construction",
            "type":"Services"
        }
    ],
    "sg:phone":"+1 404 417 0950",
    "sg:postcode":"30329",
    "sg:province":"GA",
    "sg:tags":[
        "home",
        "builder"
    ],
    "wof:name":"Sharon Mcswain Homes",
    "wof:placetype":"venue"
},
  "geometry": {"coordinates":[-84.328283,33.797347],"type":"Point"}
}