{
  "type": "Feature",
  "properties": {
    "addr:full":"845 Spring St NW Unit 330 Atlanta GA 30308",
    "addr:housenumber":"845;330",
    "addr:postcode":"30308",
    "addr:street":"Spring St Nw Unit",
    "iso:country":"US",
    "sg:address":"845 Spring St NW Unit 330",
    "sg:city":"Atlanta",
    "sg:classifiers":[
        {
            "category":"Professional",
            "subcategory":"Art Services",
            "type":"Services"
        }
    ],
    "sg:phone":"+1 404 575 4360",
    "sg:postcode":"30308",
    "sg:province":"GA",
    "sg:tags":[
        "designer",
        "display",
        "producer"
    ],
    "wof:name":"Tipton 360 Design, Inc .",
    "wof:placetype":"venue"
},
  "geometry": {"coordinates":[-84.388786,33.777569],"type":"Point"}
}