{
  "type": "Feature",
  "properties": {
    "iso:country":"US",
    "sg:address":"610 Russell Pkwy",
    "sg:city":"Warner Robins",
    "sg:classifiers":[
        {
            "category":"Shopping",
            "subcategory":"Jewelry",
            "type":"Retail Goods"
        }
    ],
    "sg:phone":"+1 478 929 1016",
    "sg:postcode":"31088",
    "sg:province":"GA",
    "sg:tags":[
        "jeweler"
    ],
    "wof:name":"J Bryan Jewelers",
    "wof:placetype":"venue"
},
  "geometry": {"coordinates":[-83.634292,32.594014],"type":"Point"}
}