{
  "type": "Feature",
  "properties": {
    "addr:full":"5457 Roswell Road NE Suite 104 Atlanta GA 30342",
    "addr:housenumber":"5457",
    "addr:postcode":"30342",
    "addr:street":"Roswell Road Ne Suite 104",
    "iso:country":"US",
    "sg:address":"5457 Roswell Road NE Suite 104",
    "sg:city":"Atlanta",
    "sg:classifiers":[
        {
            "category":"Banks & Credit Unions",
            "subcategory":"Financial Services",
            "type":"Services"
        }
    ],
    "sg:phone":"+1 404 250 0434",
    "sg:postcode":"30342",
    "sg:province":"GA",
    "sg:tags":[
        "broker",
        "mortgage"
    ],
    "wof:name":"Apple Mortgage",
    "wof:placetype":"venue"
},
  "geometry": {"coordinates":[-84.37857099999999,33.904272],"type":"Point"}
}