{
  "type": "Feature",
  "properties": {
    "addr:full":"3313 Trickum Rd Marietta GA 30066",
    "addr:housenumber":"3313",
    "addr:postcode":"30066",
    "addr:street":"Trickum Rd",
    "iso:country":"US",
    "sg:address":"3313 Trickum Rd",
    "sg:city":"Marietta",
    "sg:classifiers":[
        {
            "category":"Building & Trades",
            "subcategory":"Construction",
            "type":"Services"
        }
    ],
    "sg:phone":"+1 678 445 9907",
    "sg:postcode":"30066",
    "sg:province":"GA",
    "sg:tags":[
        "house"
    ],
    "wof:name":"Centennial Homes",
    "wof:placetype":"venue"
},
  "geometry": {"coordinates":[-84.480937,34.031009],"type":"Point"}
}