{
  "type": "Feature",
  "properties": {
    "iso:country":"US",
    "sg:address":"305 Shawnee North Dr",
    "sg:city":"Suwanee",
    "sg:classifiers":[
        {
            "category":"Building & Trades",
            "subcategory":"Pest Control",
            "type":"Services"
        }
    ],
    "sg:phone":"+1 770 904 3626",
    "sg:postcode":"30024",
    "sg:province":"GA",
    "wof:name":"Pro Pest Products Inc",
    "wof:placetype":"venue"
},
  "geometry": {"coordinates":[-84.05688499999999,34.043099],"type":"Point"}
}