{
  "type": "Feature",
  "properties": {
    "iso:country":"US",
    "sg:address":"348 Academy Dr",
    "sg:city":"Dallas",
    "sg:classifiers":[
        {
            "category":"Social Services",
            "type":"Services"
        }
    ],
    "sg:phone":"+1 770 443 7810",
    "sg:postcode":"30132",
    "sg:province":"GA",
    "wof:name":"Child Abuse And Neglect Reports",
    "wof:placetype":"venue"
},
  "geometry": {"coordinates":[-84.83156099999999,33.910271],"type":"Point"}
}