{
  "type": "Feature",
  "properties": {
    "iso:country":"US",
    "sg:address":"300 Oak Hill Ln",
    "sg:city":"Canton",
    "sg:classifiers":[
        {
            "category":"Building & Trades",
            "subcategory":"Construction",
            "type":"Services"
        }
    ],
    "sg:phone":"+1 770 475 7489",
    "sg:postcode":"30115",
    "sg:province":"GA",
    "sg:tags":[
        "house"
    ],
    "wof:name":"Capitella Homes Ltd",
    "wof:placetype":"venue"
},
  "geometry": {"coordinates":[-84.388052,34.178723],"type":"Point"}
}