{
  "type": "Feature",
  "properties": {
    "iso:country":"US",
    "sg:address":"4017 Indian Hills Dr",
    "sg:city":"Augusta",
    "sg:classifiers":[
        {
            "category":"Professional",
            "subcategory":"Management & Consulting",
            "type":"Services"
        }
    ],
    "sg:phone":"+1 706 793 5340",
    "sg:postcode":"30906",
    "sg:province":"GA",
    "sg:tags":[
        "business"
    ],
    "wof:name":"Mg Enterprises",
    "wof:placetype":"venue"
},
  "geometry": {"coordinates":[-82.00177600000001,33.339354],"type":"Point"}
}