{
  "type": "Feature",
  "properties": {
    "iso:country":"US",
    "sg:address":"746 Dan Green Rd",
    "sg:city":"De Soto",
    "sg:classifiers":[
        {
            "category":"Building & Trades",
            "subcategory":"Construction",
            "type":"Services"
        }
    ],
    "sg:phone":"+1 229 874 7147",
    "sg:postcode":"31743",
    "sg:province":"GA",
    "sg:tags":[
        "tower",
        "microwave",
        "contractor"
    ],
    "wof:name":"L & R Howell Inc",
    "wof:placetype":"venue"
},
  "geometry": {"coordinates":[-84.023934,31.873039],"type":"Point"}
}