{
  "type": "Feature",
  "properties": {
    "addr:full":"4306 Thomas Dr Douglasville GA 30134",
    "addr:housenumber":"4306",
    "addr:postcode":"30134",
    "addr:street":"Thomas Dr",
    "iso:country":"US",
    "sg:address":"4306 Thomas Dr",
    "sg:city":"Douglasville",
    "sg:classifiers":[
        {
            "category":"Professional",
            "type":"Services"
        }
    ],
    "sg:phone":"+1 770 942 9904",
    "sg:postcode":"30134",
    "sg:province":"GA",
    "wof:name":"Willadean Pelzer",
    "wof:placetype":"venue"
},
  "geometry": {"coordinates":[-84.71623599999999,33.798047],"type":"Point"}
}