{
  "type": "Feature",
  "properties": {
    "iso:country":"US",
    "sg:address":"320 Kelly Davis Rd",
    "sg:city":"Richmond Hill",
    "sg:classifiers":[
        {
            "category":"Utilities",
            "subcategory":"Telephone",
            "type":"Services"
        }
    ],
    "sg:phone":"+1 912 756 7561",
    "sg:postcode":"31324",
    "sg:province":"GA",
    "sg:tags":[
        "communications"
    ],
    "wof:name":"Christian Telephone Network",
    "wof:placetype":"venue"
},
  "geometry": {"coordinates":[-81.359369,31.915798],"type":"Point"}
}