{
  "type": "Feature",
  "properties": {
    "iso:country":"US",
    "sg:address":"145 N Marietta Pkwy NE",
    "sg:city":"Marietta",
    "sg:classifiers":[
        {
            "category":"Retail",
            "subcategory":"Laundry & Dry Cleaning",
            "type":"Services"
        }
    ],
    "sg:phone":"+1 770 428 5533",
    "sg:postcode":"30060",
    "sg:province":"GA",
    "wof:name":"Professional Touch Cleaners 3",
    "wof:placetype":"venue"
},
  "geometry": {"coordinates":[-84.5485,33.959],"type":"Point"}
}