{
  "type": "Feature",
  "properties": {
    "addr:full":"1530 Cooledge Rd Tucker GA 30084",
    "addr:housenumber":"1530",
    "addr:postcode":"30084",
    "addr:street":"Cooledge Rd",
    "iso:country":"US",
    "sg:address":"1530 Cooledge Rd",
    "sg:city":"Tucker",
    "sg:classifiers":[
        {
            "category":"Organizations",
            "subcategory":"Professional Association",
            "type":"Services"
        }
    ],
    "sg:phone":"+1 770 493 9401",
    "sg:postcode":"30084",
    "sg:province":"GA",
    "sg:tags":[
        "trade"
    ],
    "wof:name":"US Poultry & Egg Association",
    "wof:placetype":"venue"
},
  "geometry": {"coordinates":[-84.235394,33.827053],"type":"Point"}
}