{
  "type": "Feature",
  "properties": {
    "iso:country":"US",
    "sg:address":"3029 Libby Dr",
    "sg:city":"Augusta",
    "sg:classifiers":[
        {
            "category":"Shopping",
            "subcategory":"Clothing, Apparel, & Fashions",
            "type":"Retail Goods"
        }
    ],
    "sg:phone":"+1 706 798 6096",
    "sg:postcode":"30906",
    "sg:province":"GA",
    "wof:name":"Joanns Dress Making Shop",
    "wof:placetype":"venue"
},
  "geometry": {"coordinates":[-82.08052499999999,33.413707],"type":"Point"}
}