{
  "type": "Feature",
  "properties": {
    "addr:full":"809 Oak Ave Americus GA 31709",
    "addr:housenumber":"809",
    "addr:postcode":"31709",
    "addr:street":"Oak Ave",
    "iso:country":"US",
    "sg:address":"809 Oak Ave",
    "sg:city":"Americus",
    "sg:classifiers":[
        {
            "category":"Recreation",
            "type":"Entertainment"
        }
    ],
    "sg:phone":"+1 229 924 4878",
    "sg:postcode":"31709",
    "sg:province":"GA",
    "sg:tags":[
        "playground"
    ],
    "wof:name":"Americus Recreation Dept",
    "wof:placetype":"venue"
},
  "geometry": {"coordinates":[-84.235275,32.061955],"type":"Point"}
}