{
  "type": "Feature",
  "properties": {
    "iso:country":"US",
    "sg:address":"2022 E Pinetree Blvd",
    "sg:city":"Thomasville",
    "sg:classifiers":[
        {
            "category":"Social Services",
            "subcategory":"Adult Care",
            "type":"Services"
        }
    ],
    "sg:phone":"+1 229 226 8682",
    "sg:postcode":"31792",
    "sg:province":"GA",
    "sg:tags":[
        "home",
        "residential"
    ],
    "wof:name":"Suites Of Woodleaf",
    "wof:placetype":"venue"
},
  "geometry": {"coordinates":[-83.94747,30.847002],"type":"Point"}
}