{
  "type": "Feature",
  "properties": {
    "addr:full":"1006 Saint Patricks Dr Perry GA 31069",
    "addr:housenumber":"1006",
    "addr:postcode":"31069",
    "addr:street":"Saint Patricks Dr",
    "iso:country":"US",
    "sg:address":"1006 Saint Patricks Dr",
    "sg:city":"Perry",
    "sg:classifiers":[
        {
            "category":"Travel",
            "subcategory":"Hotels & Motels",
            "type":"Entertainment"
        }
    ],
    "sg:phone":"+1 478 987 5600",
    "sg:postcode":"31069",
    "sg:province":"GA",
    "sg:tags":[
        "operation",
        "eating"
    ],
    "wof:name":"Great Inn",
    "wof:placetype":"venue"
},
  "geometry": {"coordinates":[-83.74231399999999,32.474428],"type":"Point"}
}