{
  "type": "Feature",
  "properties": {
    "addr:full":"5253 Crystal Ln Atlanta GA 30349",
    "addr:housenumber":"5253",
    "addr:postcode":"30349",
    "addr:street":"Crystal Ln",
    "iso:country":"US",
    "sg:address":"5253 Crystal Ln",
    "sg:city":"Atlanta",
    "sg:classifiers":[
        {
            "category":"Wholesale",
            "subcategory":"Scrap",
            "type":"Manufacturing & Wholesale Goods"
        }
    ],
    "sg:phone":"+1 770 994 9567",
    "sg:postcode":"30349",
    "sg:province":"GA",
    "sg:tags":[
        "resale",
        "to",
        "for",
        "secondary"
    ],
    "wof:name":"Ahmose",
    "wof:placetype":"venue"
},
  "geometry": {"coordinates":[-84.444092,33.609465],"type":"Point"}
}