{
  "type": "Feature",
  "properties": {
    "addr:full":"7000 Peachtree Dunwoody Rd NE Atlanta GA 30328",
    "addr:housenumber":"7000",
    "addr:postcode":"30328",
    "addr:street":"Peachtree Dunwoody Rd Ne",
    "iso:country":"US",
    "sg:address":"7000 Peachtree Dunwoody Rd NE",
    "sg:city":"Atlanta",
    "sg:classifiers":[
        {
            "category":"Social Services",
            "type":"Services"
        }
    ],
    "sg:phone":"+1 770 396 5253",
    "sg:postcode":"30328",
    "sg:province":"GA",
    "sg:tags":[
        "employee",
        "assistance",
        "program"
    ],
    "sg:website":"www.corpcareeap.com",
    "wof:name":"Corpcare Associates Inc",
    "wof:placetype":"venue"
},
  "geometry": {"coordinates":[-84.35391199999999,33.949818],"type":"Point"}
}