{
  "type": "Feature",
  "properties": {
    "iso:country":"US",
    "sg:address":"4383 Inner Perimeter Rd",
    "sg:city":"Valdosta",
    "sg:classifiers":[
        {
            "category":"Building & Trades",
            "subcategory":"Equipment Rental",
            "type":"Services"
        }
    ],
    "sg:phone":"+1 229 242 7797",
    "sg:postcode":"31602",
    "sg:province":"GA",
    "sg:tags":[
        "party",
        "supply"
    ],
    "wof:name":"RSC 245",
    "wof:placetype":"venue"
},
  "geometry": {"coordinates":[-83.229917,30.854989],"type":"Point"}
}