{
  "type": "Feature",
  "properties": {
    "addr:full":"70 Perimeter Ctr E Atlanta GA 30346",
    "addr:housenumber":"70",
    "addr:postcode":"30346",
    "addr:street":"Perimeter Ctr E",
    "iso:country":"US",
    "sg:address":"70 Perimeter Ctr E",
    "sg:city":"Atlanta",
    "sg:classifiers":[
        {
            "category":"Real Estate",
            "subcategory":"Real Estate Operator",
            "type":"Services"
        }
    ],
    "sg:phone":"+1 866 408 3450",
    "sg:postcode":"30346",
    "sg:province":"GA",
    "sg:tags":[
        "apartment"
    ],
    "sg:website":"http://local.ingenio.com/Listings/Details.aspx?NUM=a%3a10248634%3a13%3a4859924%3a14%3a0%3a7",
    "wof:name":"The Alexander at the Perimeter",
    "wof:placetype":"venue"
},
  "geometry": {"coordinates":[-84.33268700000001,33.922749],"type":"Point"}
}