{
  "type": "Feature",
  "properties": {
    "addr:full":"2146 Lawrenceville Hwy Decatur GA 30033",
    "addr:housenumber":"2146",
    "addr:postcode":"30033",
    "addr:street":"Lawrenceville Hwy",
    "iso:country":"US",
    "sg:address":"2146 Lawrenceville Hwy",
    "sg:city":"Decatur",
    "sg:classifiers":[
        {
            "category":"Building & Trades",
            "subcategory":"Locksmith",
            "type":"Services"
        }
    ],
    "sg:phone":"+1 678 365 0366",
    "sg:postcode":"30033",
    "sg:province":"GA",
    "sg:tags":[
        "key"
    ],
    "wof:name":"1 After Drinking Locksmith Rescue",
    "wof:placetype":"venue"
},
  "geometry": {"coordinates":[-84.273274,33.810266],"type":"Point"}
}