{
  "type": "Feature",
  "properties": {
    "iso:country":"US",
    "sg:address":"4375 Cascade Rd SW D28",
    "sg:city":"Atlanta",
    "sg:classifiers":[
        {
            "category":"Professional",
            "subcategory":"Business Services",
            "type":"Services"
        }
    ],
    "sg:phone":"+1 404 454 8443",
    "sg:postcode":"30331",
    "sg:province":"GA",
    "sg:tags":[
        "organizing",
        "services-household"
    ],
    "wof:name":"Lyrical Boxing Management Group",
    "wof:placetype":"venue"
},
  "geometry": {"coordinates":[-84.532708,33.734051],"type":"Point"}
}