{
  "type": "Feature",
  "properties": {
    "addr:full":"333 Creel Ct NW Kennesaw GA 30144",
    "addr:housenumber":"333",
    "addr:postcode":"30144",
    "addr:street":"Creel Ct Nw",
    "iso:country":"US",
    "sg:address":"333 Creel Ct NW",
    "sg:city":"Kennesaw",
    "sg:classifiers":[
        {
            "category":"Building & Trades",
            "subcategory":"Cleaning & Sanitation",
            "type":"Services"
        }
    ],
    "sg:phone":"+1 404 406 6793",
    "sg:postcode":"30144",
    "sg:province":"GA",
    "sg:tags":[
        "maintenance"
    ],
    "wof:name":"Preferred Building Maintenance",
    "wof:placetype":"venue"
},
  "geometry": {"coordinates":[-84.66934999999999,34.038242],"type":"Point"}
}