{
  "type": "Feature",
  "properties": {
    "addr:full":"1018 13th St Columbus GA 31901",
    "addr:housenumber":"1018",
    "addr:postcode":"31901",
    "addr:street":"13Th St",
    "iso:country":"US",
    "sg:address":"1018 13th St",
    "sg:city":"Columbus",
    "sg:classifiers":[
        {
            "category":"Taxi",
            "type":"Transportation"
        }
    ],
    "sg:phone":"+1 706 653 8294",
    "sg:postcode":"31901",
    "sg:province":"GA",
    "sg:tags":[
        "taxicab"
    ],
    "wof:name":"City Cab Co",
    "wof:placetype":"venue"
},
  "geometry": {"coordinates":[-84.9794,32.470396],"type":"Point"}
}