{
  "type": "Feature",
  "properties": {
    "addr:full":"3050 Martin Luther King Jr Dr SW Atlanta GA 30311",
    "addr:housenumber":"3050",
    "addr:postcode":"30311",
    "addr:street":"Martin Luther King Jr Dr Sw",
    "iso:country":"US",
    "sg:address":"3050 Martin Luther King Jr Dr SW",
    "sg:city":"Atlanta",
    "sg:classifiers":[
        {
            "category":"Shopping",
            "subcategory":"Discount & Variety Stores",
            "type":"Retail Goods"
        },
        {
            "category":"Shopping",
            "subcategory":"Department Store",
            "type":"Retail Goods"
        }
    ],
    "sg:phone":"+1 404 691 8449",
    "sg:postcode":"30311",
    "sg:province":"GA",
    "sg:tags":[
        "shop"
    ],
    "wof:name":"Family Dollar Stores",
    "wof:placetype":"venue"
},
  "geometry": {"coordinates":[-84.48341499999999,33.754199],"type":"Point"}
}