{
  "type": "Feature",
  "properties": {
    "addr:full":"1425 Market Blvd Roswell GA 30076",
    "addr:housenumber":"1425",
    "addr:postcode":"30076",
    "addr:street":"Market Blvd",
    "iso:country":"US",
    "sg:address":"1425 Market Blvd",
    "sg:city":"Roswell",
    "sg:classifiers":[
        {
            "category":"Shopping",
            "subcategory":"Department Store",
            "type":"Retail Goods"
        }
    ],
    "sg:phone":"+1 770 641 7949",
    "sg:postcode":"30076",
    "sg:province":"GA",
    "sg:tags":[
        "shop",
        "discount"
    ],
    "wof:name":"Marshalls",
    "wof:placetype":"venue"
},
  "geometry": {"coordinates":[-84.322631,34.016641],"type":"Point"}
}