{
  "type": "Feature",
  "properties": {
    "iso:country":"US",
    "sg:address":"1558 Ball Ground Hwy",
    "sg:city":"Canton",
    "sg:classifiers":[
        {
            "category":"Restaurant",
            "type":"Food & Drink"
        }
    ],
    "sg:phone":"+1 770 720 6017",
    "sg:postcode":"30114",
    "sg:province":"GA",
    "wof:name":"Dos Hombres Mexican Rest No 3",
    "wof:placetype":"venue"
},
  "geometry": {"coordinates":[-84.463855,34.258415],"type":"Point"}
}