{
  "type": "Feature",
  "properties": {
    "iso:country":"US",
    "sg:address":"810 Windy Hill Rd SE",
    "sg:city":"Smyrna",
    "sg:classifiers":[
        {
            "category":"Real Estate",
            "subcategory":"Real Estate Operator",
            "type":"Services"
        }
    ],
    "sg:phone":"+1 877 884 0914",
    "sg:postcode":"30080",
    "sg:province":"GA",
    "sg:tags":[
        "apartment"
    ],
    "sg:website":"http://local.ingenio.com/Listings/Details.aspx?NUM=a%3a10248594%3a13%3a4859924%3a14%3a0%3a7",
    "wof:name":"Carriage House",
    "wof:placetype":"venue"
},
  "geometry": {"coordinates":[-84.52908100000001,33.894382],"type":"Point"}
}