{
  "type": "Feature",
  "properties": {
    "addr:full":"5052 Post Road Ct Stone Mountain GA 30088",
    "addr:housenumber":"5052",
    "addr:postcode":"30088",
    "addr:street":"Post Road Ct",
    "iso:country":"US",
    "sg:address":"5052 Post Road Ct",
    "sg:city":"Stone Mountain",
    "sg:classifiers":[
        {
            "category":"Professional",
            "subcategory":"Computer Services",
            "type":"Services"
        }
    ],
    "sg:phone":"+1 770 498 5062",
    "sg:postcode":"30088",
    "sg:province":"GA",
    "wof:name":"Exeed Tech Svc",
    "wof:placetype":"venue"
},
  "geometry": {"coordinates":[-84.183531,33.770452],"type":"Point"}
}