{
  "type": "Feature",
  "properties": {
    "addr:full":"3825 Atlanta Hwy Bogart GA 30622",
    "addr:housenumber":"3825",
    "addr:postcode":"30622",
    "addr:street":"Atlanta Hwy Bogart",
    "iso:country":"US",
    "sg:address":"3825 Atlanta Hwy",
    "sg:city":"Bogart",
    "sg:classifiers":[
        {
            "category":"Restaurant",
            "type":"Food & Drink"
        }
    ],
    "sg:menulink":"http://www.allmenus.com/ga/bogart/203187-mcdonalds/menu/",
    "sg:postcode":"30622",
    "sg:province":"GA",
    "sg:tags":[
        "burger",
        "american"
    ],
    "wof:name":"McDonald's",
    "wof:placetype":"venue"
},
  "geometry": {"coordinates":[-83.469437,33.940957],"type":"Point"}
}