{
  "type": "Feature",
  "properties": {
    "iso:country":"US",
    "sg:address":"2453 Bouldercliff Way SE",
    "sg:city":"Atlanta",
    "sg:classifiers":[
        {
            "category":"Professional",
            "subcategory":"Management & Consulting",
            "type":"Services"
        }
    ],
    "sg:phone":"+1 404 381 4956",
    "sg:postcode":"30316",
    "sg:province":"GA",
    "wof:name":"Empire Estates",
    "wof:placetype":"venue"
},
  "geometry": {"coordinates":[-84.32225800000001,33.718748],"type":"Point"}
}