{
  "type": "Feature",
  "properties": {
    "iso:country":"US",
    "sg:address":"2900 Creel Rd",
    "sg:city":"Atlanta",
    "sg:classifiers":[
        {
            "category":"Real Estate",
            "subcategory":"Real Estate Operator",
            "type":"Services"
        }
    ],
    "sg:phone":"+1 770 991 1902",
    "sg:postcode":"30349",
    "sg:province":"GA",
    "sg:tags":[
        "condominium"
    ],
    "wof:name":"Pinetree Condominium",
    "wof:placetype":"venue"
},
  "geometry": {"coordinates":[-84.48157999999999,33.568643],"type":"Point"}
}