{
  "type": "Feature",
  "properties": {
    "iso:country":"US",
    "sg:address":"132 Hurricane Shoals Rd NE",
    "sg:city":"Lawrenceville",
    "sg:classifiers":[
        {
            "category":"Professional",
            "subcategory":"Lawyer & Legal Services",
            "type":"Services"
        }
    ],
    "sg:phone":"+1 770 736 0845",
    "sg:postcode":"30045",
    "sg:province":"GA",
    "wof:name":"Randall S Rolader",
    "wof:placetype":"venue"
},
  "geometry": {"coordinates":[-83.988151,33.973664],"type":"Point"}
}