{
  "type": "Feature",
  "properties": {
    "addr:full":"5687 Marion Rd Macon GA 31217",
    "addr:housenumber":"5687",
    "addr:postcode":"31217",
    "addr:street":"Marion Rd",
    "iso:country":"US",
    "sg:address":"5687 Marion Rd",
    "sg:city":"Macon",
    "sg:classifiers":[
        {
            "category":"Organizations",
            "subcategory":"Religious Organization",
            "type":"Services"
        }
    ],
    "sg:phone":"+1 478 750 0475",
    "sg:postcode":"31217",
    "sg:province":"GA",
    "wof:name":"Ocmulgee Baptist Church",
    "wof:placetype":"venue"
},
  "geometry": {"coordinates":[-83.562011,32.776552],"type":"Point"}
}