{
  "type": "Feature",
  "properties": {
    "addr:full":"624 Old Perkins Rd Millen GA 30442",
    "addr:housenumber":"624",
    "addr:postcode":"30442",
    "addr:street":"Old Perkins Rd",
    "iso:country":"US",
    "sg:address":"624 Old Perkins Rd",
    "sg:city":"Millen",
    "sg:classifiers":[
        {
            "category":"Restaurant",
            "type":"Food & Drink"
        }
    ],
    "sg:phone":"+1 478 982 2608",
    "sg:postcode":"30442",
    "sg:province":"GA",
    "sg:tags":[
        "eating"
    ],
    "wof:name":"Krystal's Taste Of Kountry",
    "wof:placetype":"venue"
},
  "geometry": {"coordinates":[-81.93657,32.852641],"type":"Point"}
}