{
  "type": "Feature",
  "properties": {
    "iso:country":"US",
    "sg:address":"1402 Greenbrier Ct",
    "sg:city":"Albany",
    "sg:classifiers":[
        {
            "category":"Building & Trades",
            "subcategory":"Construction",
            "type":"Services"
        }
    ],
    "sg:phone":"+1 229 420 3986",
    "sg:postcode":"31705",
    "sg:province":"GA",
    "sg:tags":[
        "general",
        "contractor"
    ],
    "wof:name":"Merritt Construction",
    "wof:placetype":"venue"
},
  "geometry": {"coordinates":[-84.11880499999999,31.604705],"type":"Point"}
}