{
  "type": "Feature",
  "properties": {
    "addr:full":"205 N Davis Dr Warner Robins GA 31093",
    "addr:housenumber":"205",
    "addr:postcode":"31093",
    "addr:street":"N Davis Dr",
    "iso:country":"US",
    "sg:address":"205 N Davis Dr",
    "sg:city":"Warner Robins",
    "sg:classifiers":[
        {
            "category":"Social Services",
            "subcategory":"Child Care",
            "type":"Services"
        }
    ],
    "sg:phone":"+1 478 922 8448",
    "sg:postcode":"31093",
    "sg:province":"GA",
    "sg:tags":[
        "elementary",
        "kindergarten",
        "school",
        "academic"
    ],
    "wof:name":"Cheerful Cherub Preschool",
    "wof:placetype":"venue"
},
  "geometry": {"coordinates":[-83.613197,32.6208],"type":"Point"}
}