{
  "type": "Feature",
  "properties": {
    "addr:full":"682 Hemlock St Macon GA 31201",
    "addr:housenumber":"682",
    "addr:postcode":"31201",
    "addr:street":"Hemlock St",
    "iso:country":"US",
    "sg:address":"682 Hemlock St",
    "sg:city":"Macon",
    "sg:classifiers":[
        {
            "category":"Health Services",
            "subcategory":"Doctor",
            "type":"Services"
        }
    ],
    "sg:phone":"+1 478 743 2000",
    "sg:postcode":"31201",
    "sg:province":"GA",
    "sg:tags":[
        "physician",
        "surgeon"
    ],
    "wof:name":"Georgia Eye Care Ctr",
    "wof:placetype":"venue"
},
  "geometry": {"coordinates":[-83.634593,32.8319],"type":"Point"}
}