{
  "type": "Feature",
  "properties": {
    "iso:country":"US",
    "sg:address":"4520 Broadway",
    "sg:city":"Macon",
    "sg:classifiers":[
        {
            "category":"Manufacturing",
            "subcategory":"Building Materials",
            "type":"Manufacturing & Wholesale Goods"
        }
    ],
    "sg:phone":"+1 478 788 4811",
    "sg:postcode":"31206",
    "sg:province":"GA",
    "sg:tags":[
        "recap",
        "repair",
        "retread",
        "tire"
    ],
    "sg:website":"http://www.armstrong.com",
    "wof:name":"Armstrong World Industries Inc",
    "wof:placetype":"venue"
},
  "geometry": {"coordinates":[-83.65554,32.779405],"type":"Point"}
}