{
  "type": "Feature",
  "properties": {
    "addr:full":"6690 Jones Mill Ct Norcross GA 30092",
    "addr:housenumber":"6690",
    "addr:postcode":"30092",
    "addr:street":"Jones Mill Ct",
    "iso:country":"US",
    "sg:address":"6690 Jones Mill Ct",
    "sg:city":"Norcross",
    "sg:classifiers":[
        {
            "category":"Wholesale",
            "subcategory":"Machinery & Supplies",
            "type":"Manufacturing & Wholesale Goods"
        }
    ],
    "sg:phone":"+1 770 836 0097",
    "sg:postcode":"30092",
    "sg:province":"GA",
    "sg:tags":[
        "equipment",
        "industrial"
    ],
    "wof:name":"T Squares",
    "wof:placetype":"venue"
},
  "geometry": {"coordinates":[-84.253288,33.943159],"type":"Point"}
}