{
  "type": "Feature",
  "properties": {
    "addr:full":"206 King St Cusseta GA 31805",
    "addr:housenumber":"206",
    "addr:postcode":"31805",
    "addr:street":"King St",
    "iso:country":"US",
    "sg:address":"206 King St",
    "sg:city":"Cusseta",
    "sg:classifiers":[
        {
            "category":"Professional",
            "subcategory":"Detective & Security Services",
            "type":"Services"
        }
    ],
    "sg:phone":"+1 706 989 3331",
    "sg:postcode":"31805",
    "sg:province":"GA",
    "sg:tags":[
        "information",
        "bureau"
    ],
    "wof:name":"Public Service Towers Inc",
    "wof:placetype":"venue"
},
  "geometry": {"coordinates":[-84.765514,32.314293],"type":"Point"}
}