{
  "type": "Feature",
  "properties": {
    "addr:full":"124 N 2nd Ave Chatsworth GA 30705",
    "addr:housenumber":"124",
    "addr:postcode":"30705",
    "addr:street":"N 2Nd Ave",
    "iso:country":"US",
    "sg:address":"124 N 2nd Ave",
    "sg:city":"Chatsworth",
    "sg:classifiers":[
        {
            "category":"Manufacturing",
            "subcategory":"Tools & Machinery",
            "type":"Manufacturing & Wholesale Goods"
        }
    ],
    "sg:phone":"+1 706 695 8637",
    "sg:postcode":"30705",
    "sg:province":"GA",
    "sg:tags":[
        "textile",
        "parts"
    ],
    "sg:website":"www.eagleparts.com",
    "wof:name":"Eagle Parts & Machinery Inc",
    "wof:placetype":"venue"
},
  "geometry": {"coordinates":[-84.768457,34.767153],"type":"Point"}
}