{
  "type": "Feature",
  "properties": {
    "addr:full":"1940 State Rte 85 Jonesboro GA 30238",
    "addr:housenumber":"1940",
    "addr:postcode":"30238",
    "addr:street":"State Rte 85",
    "iso:country":"US",
    "sg:address":"1940 State Rte 85",
    "sg:city":"Jonesboro",
    "sg:classifiers":[
        {
            "category":"Wholesale",
            "subcategory":"Electrical",
            "type":"Manufacturing & Wholesale Goods"
        }
    ],
    "sg:phone":"+1 770 460 7477",
    "sg:postcode":"30238",
    "sg:province":"GA",
    "wof:name":"Climatic Corporation",
    "wof:placetype":"venue"
},
  "geometry": {"coordinates":[-84.427617,33.502437],"type":"Point"}
}