{
  "type": "Feature",
  "properties": {
    "iso:country":"US",
    "sg:address":"749 Jackson St",
    "sg:city":"Locust Grove",
    "sg:classifiers":[
        {
            "category":"Retail",
            "subcategory":"Auto Repair",
            "type":"Services"
        }
    ],
    "sg:phone":"+1 678 432 2200",
    "sg:postcode":"30248",
    "sg:province":"GA",
    "sg:tags":[
        "body",
        "automobile",
        "painting"
    ],
    "wof:name":"Locust Grove Collision Center",
    "wof:placetype":"venue"
},
  "geometry": {"coordinates":[-84.108047,33.345371],"type":"Point"}
}