{
  "type": "Feature",
  "properties": {
    "iso:country":"US",
    "sg:address":"3690 Hamilton Dam Rd",
    "sg:city":"Dacula",
    "sg:classifiers":[
        {
            "category":"Professional",
            "subcategory":"Computer Services",
            "type":"Services"
        }
    ],
    "sg:phone":"+1 770 271 3022",
    "sg:postcode":"30019",
    "sg:province":"GA",
    "wof:name":"Custom Computing Service",
    "wof:placetype":"venue"
},
  "geometry": {"coordinates":[-83.904342,34.061416],"type":"Point"}
}