{
  "type": "Feature",
  "properties": {
    "iso:country":"US",
    "sg:address":"3000 Hospital Blvd",
    "sg:city":"Roswell",
    "sg:classifiers":[
        {
            "category":"Health Services",
            "subcategory":"Medical Lab",
            "type":"Services"
        }
    ],
    "sg:phone":"+1 770 751 2529",
    "sg:postcode":"30076",
    "sg:province":"GA",
    "sg:tags":[
        "laboratory"
    ],
    "wof:name":"Pathology Dept",
    "wof:placetype":"venue"
},
  "geometry": {"coordinates":[-84.320691,34.06243],"type":"Point"}
}