{
  "type": "Feature",
  "properties": {
    "addr:full":"3751 Greensboro Hwy Watkinsville GA 30677",
    "addr:housenumber":"3751",
    "addr:postcode":"30677",
    "addr:street":"Greensboro Hwy",
    "iso:country":"US",
    "sg:address":"3751 Greensboro Hwy",
    "sg:city":"Watkinsville",
    "sg:classifiers":[
        {
            "category":"Wholesale",
            "subcategory":"Plants",
            "type":"Manufacturing & Wholesale Goods"
        }
    ],
    "sg:phone":"+1 706 769 0400",
    "sg:postcode":"30677",
    "sg:province":"GA",
    "sg:tags":[
        "nursery",
        "tree"
    ],
    "wof:name":"Noles Tree Farm",
    "wof:placetype":"venue"
},
  "geometry": {"coordinates":[-83.34398299999999,33.804739],"type":"Point"}
}