{
  "type": "Feature",
  "properties": {
    "iso:country":"US",
    "sg:address":"813 Indian Mound Rd SE",
    "sg:city":"Cartersville",
    "sg:classifiers":[
        {
            "category":"Government",
            "subcategory":"Office",
            "type":"Public Place"
        }
    ],
    "sg:phone":"+1 770 387 3747",
    "sg:postcode":"30120",
    "sg:province":"GA",
    "sg:tags":[
        "state"
    ],
    "wof:name":"Natural Resources Dept",
    "wof:placetype":"venue"
},
  "geometry": {"coordinates":[-84.806978,34.132759],"type":"Point"}
}