{
  "type": "Feature",
  "properties": {
    "addr:full":"528 King Circle Dr Swainsboro GA 30401",
    "addr:housenumber":"528",
    "addr:postcode":"30401",
    "addr:street":"King Circle Dr",
    "iso:country":"US",
    "sg:address":"528 King Circle Dr",
    "sg:city":"Swainsboro",
    "sg:classifiers":[
        {
            "category":"Professional",
            "type":"Services"
        }
    ],
    "sg:phone":"+1 478 289 6442",
    "sg:postcode":"30401",
    "sg:province":"GA",
    "wof:name":"Nicole Mahone",
    "wof:placetype":"venue"
},
  "geometry": {"coordinates":[-82.32545399999999,32.614734],"type":"Point"}
}