{
  "type": "Feature",
  "properties": {
    "iso:country":"US",
    "sg:address":"5402 Jimmy Carter Blvd # A",
    "sg:city":"Norcross",
    "sg:classifiers":[
        {
            "category":"Retail",
            "subcategory":"Auto Repair",
            "type":"Services"
        }
    ],
    "sg:phone":"+1 770 448 4553",
    "sg:postcode":"30093",
    "sg:province":"GA",
    "wof:name":"Green's Corner Auto Service 2",
    "wof:placetype":"venue"
},
  "geometry": {"coordinates":[-84.20590199999999,33.9058],"type":"Point"}
}