{
  "type": "Feature",
  "properties": {
    "iso:country":"US",
    "sg:address":"608 Bay St",
    "sg:city":"Baxley",
    "sg:classifiers":[
        {
            "category":"Personal",
            "subcategory":"Beauty Salon",
            "type":"Services"
        }
    ],
    "sg:phone":"+1 912 366 9032",
    "sg:postcode":"31513",
    "sg:province":"GA",
    "wof:name":"Lightsey, Angie",
    "wof:placetype":"venue"
},
  "geometry": {"coordinates":[-82.358621,31.778528],"type":"Point"}
}