{
  "type": "Feature",
  "properties": {
    "addr:full":"2233 Milledgeville Rd Augusta GA 30904",
    "addr:housenumber":"2233",
    "addr:postcode":"30904",
    "addr:street":"Milledgeville Rd",
    "iso:country":"US",
    "sg:address":"2233 Milledgeville Rd",
    "sg:city":"Augusta",
    "sg:classifiers":[
        {
            "category":"Personal",
            "subcategory":"Beauty Salon",
            "type":"Services"
        }
    ],
    "sg:phone":"+1 706 733 6318",
    "sg:postcode":"30904",
    "sg:province":"GA",
    "sg:tags":[
        "shop"
    ],
    "wof:name":"Hair Chefs Unisex Shop Inc",
    "wof:placetype":"venue"
},
  "geometry": {"coordinates":[-82.005145,33.44864],"type":"Point"}
}