{
  "type": "Feature",
  "properties": {
    "iso:country":"US",
    "sg:address":"3335 Hutchinson Rd",
    "sg:city":"Cumming",
    "sg:classifiers":[
        {
            "category":"Building & Trades",
            "subcategory":"Construction",
            "type":"Services"
        }
    ],
    "sg:phone":"+1 770 887 8646",
    "sg:postcode":"30040",
    "sg:province":"GA",
    "sg:tags":[
        "roofing",
        "contractor"
    ],
    "wof:name":"Forsyth Roofing Company",
    "wof:placetype":"venue"
},
  "geometry": {"coordinates":[-84.152249,34.191237],"type":"Point"}
}