{
  "type": "Feature",
  "properties": {
    "addr:full":"5900 Bells Ferry Rd Acworth GA 30102",
    "addr:housenumber":"5900",
    "addr:postcode":"30102",
    "addr:street":"Bells Ferry Rd",
    "iso:country":"US",
    "sg:address":"5900 Bells Ferry Rd",
    "sg:city":"Acworth",
    "sg:classifiers":[
        {
            "category":"Cinema",
            "subcategory":"Movie Rental",
            "type":"Entertainment"
        }
    ],
    "sg:phone":"+1 770 924 6528",
    "sg:postcode":"30102",
    "sg:province":"GA",
    "sg:tags":[
        "video",
        "tape"
    ],
    "wof:name":"Fantastic Video Store",
    "wof:placetype":"venue"
},
  "geometry": {"coordinates":[-84.581355,34.09757],"type":"Point"}
}