{
  "type": "Feature",
  "properties": {
    "iso:country":"US",
    "sg:address":"106 Hemlock St",
    "sg:city":"Valdosta",
    "sg:classifiers":[
        {
            "category":"Manufacturing",
            "subcategory":"Tools & Machinery",
            "type":"Manufacturing & Wholesale Goods"
        }
    ],
    "sg:phone":"+1 229 244 4548",
    "sg:postcode":"31601",
    "sg:province":"GA",
    "sg:tags":[
        "transmission",
        "power"
    ],
    "sg:website":"www.motionmro.com",
    "wof:name":"Motion Industries Inc",
    "wof:placetype":"venue"
},
  "geometry": {"coordinates":[-83.30412699999999,30.823095],"type":"Point"}
}