{
  "type": "Feature",
  "properties": {
    "addr:full":"118 Walnut St Montezuma GA 31063",
    "addr:housenumber":"118",
    "addr:postcode":"31063",
    "addr:street":"Walnut St",
    "iso:country":"US",
    "sg:address":"118 Walnut St",
    "sg:city":"Montezuma",
    "sg:classifiers":[
        {
            "category":"Banks & Credit Unions",
            "subcategory":"Bank",
            "type":"Services"
        }
    ],
    "sg:phone":"+1 478 472 2393",
    "sg:postcode":"31063",
    "sg:province":"GA",
    "wof:name":"B B & T",
    "wof:placetype":"venue"
},
  "geometry": {"coordinates":[-84.02220199999999,32.293457],"type":"Point"}
}