{
  "type": "Feature",
  "properties": {
    "addr:full":"245 N Highland Ave NE Ste 227 Atlanta GA 30307",
    "addr:housenumber":"245",
    "addr:postcode":"30307",
    "addr:street":"N Highland Ave Ne Ste 227",
    "iso:country":"US",
    "sg:address":"245 N Highland Ave NE Ste 227",
    "sg:city":"Atlanta",
    "sg:classifiers":[
        {
            "category":"Coffee & Tea",
            "type":"Food & Drink"
        },
        {
            "category":"Food & Beverages",
            "subcategory":"Bakery",
            "type":"Retail Goods"
        },
        {
            "category":"Deli",
            "type":"Food & Drink"
        }
    ],
    "sg:phone":"+1 404 525 2611",
    "sg:postcode":"30307",
    "sg:province":"GA",
    "sg:tags":[
        "sandwich"
    ],
    "wof:name":"Blue Mountain Cafe",
    "wof:placetype":"venue"
},
  "geometry": {"coordinates":[-84.355188,33.75662],"type":"Point"}
}