{
  "type": "Feature",
  "properties": {
    "addr:full":"403 Canterbury Dr Wrens GA 30833",
    "addr:housenumber":"403",
    "addr:postcode":"30833",
    "addr:street":"Canterbury Dr",
    "iso:country":"US",
    "sg:address":"403 Canterbury Dr",
    "sg:city":"Wrens",
    "sg:classifiers":[
        {
            "category":"Health Services",
            "subcategory":"Doctor",
            "type":"Services"
        },
        {
            "category":"Health Services",
            "subcategory":"Dentist",
            "type":"Services"
        }
    ],
    "sg:phone":"+1 706 547 3148",
    "sg:postcode":"30833",
    "sg:province":"GA",
    "sg:tags":[
        "dentists-oral",
        "physician",
        "maxillofacial",
        "surgeons",
        "surgery",
        "oral"
    ],
    "wof:name":"Real, William E Jr Dmd",
    "wof:placetype":"venue"
},
  "geometry": {"coordinates":[-82.372728,33.21823],"type":"Point"}
}