{
  "type": "Feature",
  "properties": {
    "iso:country":"US",
    "sg:address":"3528 Bramblevine Cir",
    "sg:city":"Lithonia",
    "sg:classifiers":[
        {
            "category":"Professional",
            "subcategory":"Management & Consulting",
            "type":"Services"
        }
    ],
    "sg:phone":"+1 770 981 0857",
    "sg:postcode":"30038",
    "sg:province":"GA",
    "wof:name":"Christ & Walker Consultanting",
    "wof:placetype":"venue"
},
  "geometry": {"coordinates":[-84.155835,33.676515],"type":"Point"}
}