{
  "type": "Feature",
  "properties": {
    "addr:full":"1365 Twin Bridge Ln Lawrenceville GA 30043",
    "addr:housenumber":"1365",
    "addr:postcode":"30043",
    "addr:street":"Twin Bridge Ln",
    "iso:country":"US",
    "sg:address":"1365 Twin Bridge Ln",
    "sg:city":"Lawrenceville",
    "sg:classifiers":[
        {
            "category":"Shopping",
            "subcategory":"Clothing, Apparel, & Fashions",
            "type":"Retail Goods"
        }
    ],
    "sg:phone":"+1 770 338 4969",
    "sg:postcode":"30043",
    "sg:province":"GA",
    "wof:name":"Dunigan Designs",
    "wof:placetype":"venue"
},
  "geometry": {"coordinates":[-84.044799,33.973352],"type":"Point"}
}