{
  "type": "Feature",
  "properties": {
    "iso:country":"US",
    "sg:address":"2951 Norris Rd",
    "sg:city":"Columbus",
    "sg:classifiers":[
        {
            "category":"Organizations",
            "subcategory":"Religious Organization",
            "type":"Services"
        }
    ],
    "sg:phone":"+1 706 568 9191",
    "sg:postcode":"31907",
    "sg:province":"GA",
    "sg:tags":[
        "church"
    ],
    "wof:name":"St Andrews Presbyterian Church",
    "wof:placetype":"venue"
},
  "geometry": {"coordinates":[-84.937163,32.491868],"type":"Point"}
}