{
  "type": "Feature",
  "properties": {
    "addr:full":"875 Burrus Rd Macon GA 31204",
    "addr:housenumber":"875",
    "addr:postcode":"31204",
    "addr:street":"Burrus Rd",
    "iso:country":"US",
    "sg:address":"875 Burrus Rd",
    "sg:city":"Macon",
    "sg:classifiers":[
        {
            "category":"Home & Garden",
            "subcategory":"Furniture",
            "type":"Retail Goods"
        }
    ],
    "sg:phone":"+1 478 743 8669",
    "sg:postcode":"31204",
    "sg:province":"GA",
    "wof:name":"Fuerniss Furniture Showcase",
    "wof:placetype":"venue"
},
  "geometry": {"coordinates":[-83.664948,32.874731],"type":"Point"}
}