{
  "type": "Feature",
  "properties": {
    "iso:country":"US",
    "sg:address":"3500 Atlanta Industrial Dr NW",
    "sg:city":"Atlanta",
    "sg:classifiers":[
        {
            "category":"Wholesale",
            "subcategory":"Apparel",
            "type":"Manufacturing & Wholesale Goods"
        }
    ],
    "sg:phone":"+1 770 447 0088",
    "sg:postcode":"30331",
    "sg:province":"GA",
    "sg:tags":[
        "piece"
    ],
    "wof:name":"American Dawn Inc",
    "wof:placetype":"venue"
},
  "geometry": {"coordinates":[-84.494697,33.796763],"type":"Point"}
}