{
  "type": "Feature",
  "properties": {
    "addr:full":"1175 State Rte 138 Conyers GA 30094",
    "addr:housenumber":"1175",
    "addr:postcode":"30094",
    "addr:street":"State Rte 138",
    "iso:country":"US",
    "sg:address":"1175 State Rte 138",
    "sg:city":"Conyers",
    "sg:classifiers":[
        {
            "category":"Shopping",
            "subcategory":"Used Merchandise",
            "type":"Retail Goods"
        }
    ],
    "sg:phone":"+1 770 922 5105",
    "sg:postcode":"30094",
    "sg:province":"GA",
    "sg:tags":[
        "antique"
    ],
    "wof:name":"Roer Corporation",
    "wof:placetype":"venue"
},
  "geometry": {"coordinates":[-84.024252,33.635009],"type":"Point"}
}