{
  "type": "Feature",
  "properties": {
    "iso:country":"US",
    "sg:address":"3630 Peachtree Pkwy",
    "sg:city":"Suwanee",
    "sg:classifiers":[
        {
            "category":"Manufacturing",
            "subcategory":"Building Materials",
            "type":"Manufacturing & Wholesale Goods"
        }
    ],
    "sg:phone":"+1 770 418 0424",
    "sg:postcode":"30024",
    "sg:province":"GA",
    "sg:tags":[
        "mfg"
    ],
    "wof:name":"Devonshire Woodworks LLC",
    "wof:placetype":"venue"
},
  "geometry": {"coordinates":[-84.167046,34.070982],"type":"Point"}
}