{
  "type": "Feature",
  "properties": {
    "iso:country":"US",
    "sg:address":"1618 E Oglethorpe Blvd",
    "sg:city":"Albany",
    "sg:classifiers":[
        {
            "category":"Personal",
            "subcategory":"Beauty Salon",
            "type":"Services"
        }
    ],
    "sg:phone":"+1 229 436 4540",
    "sg:postcode":"31705",
    "sg:province":"GA",
    "sg:tags":[
        "shop"
    ],
    "wof:name":"Nail Art",
    "wof:placetype":"venue"
},
  "geometry": {"coordinates":[-84.107649,31.570809],"type":"Point"}
}