{
  "type": "Feature",
  "properties": {
    "iso:country":"US",
    "sg:address":"6050 Singleton Rd",
    "sg:city":"Norcross",
    "sg:classifiers":[
        {
            "category":"Shopping Center",
            "type":"Public Place"
        }
    ],
    "sg:phone":"+1 678 291 0972",
    "sg:postcode":"30093",
    "sg:province":"GA",
    "wof:name":"Singleton Shopping Plaza",
    "wof:placetype":"venue"
},
  "geometry": {"coordinates":[-84.199963,33.90519],"type":"Point"}
}