{
  "type": "Feature",
  "properties": {
    "addr:full":"2224 Gamble Rd Savannah GA 31405",
    "addr:housenumber":"2224",
    "addr:postcode":"31405",
    "addr:street":"Gamble Rd",
    "iso:country":"US",
    "sg:address":"2224 Gamble Rd",
    "sg:city":"Savannah",
    "sg:classifiers":[
        {
            "category":"Wholesale",
            "subcategory":"Groceries",
            "type":"Manufacturing & Wholesale Goods"
        }
    ],
    "sg:phone":"+1 912 233 3035",
    "sg:postcode":"31405",
    "sg:province":"GA",
    "sg:tags":[
        "food",
        "product"
    ],
    "wof:name":"J C Specialty Foods",
    "wof:placetype":"venue"
},
  "geometry": {"coordinates":[-81.148348,32.042937],"type":"Point"}
}