{
  "type": "Feature",
  "properties": {
    "iso:country":"US",
    "sg:address":"88 Edgewood Dr",
    "sg:city":"Hiram",
    "sg:classifiers":[
        {
            "category":"Real Estate",
            "subcategory":"Real Estate Agent",
            "type":"Services"
        }
    ],
    "sg:phone":"+1 770 577 6703",
    "sg:postcode":"30125",
    "sg:province":"GA",
    "wof:name":"S Dasher Enterprises Inc",
    "wof:placetype":"venue"
},
  "geometry": {"coordinates":[-85.23661199999999,34.020511],"type":"Point"}
}