{
  "type": "Feature",
  "properties": {
    "iso:country":"US",
    "sg:address":"1117 Cochran Ave",
    "sg:city":"Macon",
    "sg:classifiers":[
        {
            "category":"Professional",
            "type":"Services"
        }
    ],
    "sg:phone":"+1 478 621 5300",
    "sg:postcode":"31217",
    "sg:province":"GA",
    "wof:name":"Green House of Stlyes",
    "wof:placetype":"venue"
},
  "geometry": {"coordinates":[-83.604355,32.85506],"type":"Point"}
}