{
  "type": "Feature",
  "properties": {
    "addr:full":"4290 International Blvd Norcross GA 30093",
    "addr:housenumber":"4290",
    "addr:postcode":"30093",
    "addr:street":"International Blvd",
    "iso:country":"US",
    "sg:address":"4290 International Blvd",
    "sg:city":"Norcross",
    "sg:classifiers":[
        {
            "category":"Home & Garden",
            "subcategory":"Household Appliances",
            "type":"Retail Goods"
        },
        {
            "category":"Restaurant",
            "type":"Food & Drink"
        },
        {
            "category":"Home & Garden",
            "subcategory":"Hardware",
            "type":"Retail Goods"
        },
        {
            "category":"Home & Garden",
            "subcategory":"Carpets & Floor Coverings",
            "type":"Retail Goods"
        },
        {
            "category":"Autos & Motor Vehicles",
            "subcategory":"Auto Supplies",
            "type":"Retail Goods"
        },
        {
            "category":"Manufacturing",
            "subcategory":"Paper Products",
            "type":"Manufacturing & Wholesale Goods"
        },
        {
            "category":"Building & Trades",
            "subcategory":"Cleaning & Sanitation",
            "type":"Services"
        }
    ],
    "sg:phone":"+1 770 448 2408",
    "sg:postcode":"30093",
    "sg:province":"GA",
    "sg:tags":[
        "cleaners-industrial",
        "cleaners-household-dealers",
        "commercial",
        "rug",
        "machine",
        "equipment",
        "paper-wholesale",
        "vacuum",
        "sweepers-power",
        "janitor",
        "manufacturer"
    ],
    "sg:website":"http://www.americas1stmaintenance.com",
    "wof:name":"America's 1st Maintenance",
    "wof:placetype":"venue"
},
  "geometry": {"coordinates":[-84.14703,33.933207],"type":"Point"}
}