{
  "type": "Feature",
  "properties": {
    "iso:country":"US",
    "sg:address":"1630 Buford Hwy NE",
    "sg:city":"Buford",
    "sg:classifiers":[
        {
            "category":"Personal",
            "subcategory":"Beauty Salon",
            "type":"Services"
        }
    ],
    "sg:phone":"+1 770 945 2220",
    "sg:postcode":"30518",
    "sg:province":"GA",
    "sg:tags":[
        "nail"
    ],
    "wof:name":"You Nique Salon",
    "wof:placetype":"venue"
},
  "geometry": {"coordinates":[-84.011036,34.098095],"type":"Point"}
}