{
  "type": "Feature",
  "properties": {
    "iso:country":"US",
    "sg:address":"3896 Riverside Dr",
    "sg:city":"Macon",
    "sg:classifiers":[
        {
            "category":"Real Estate",
            "subcategory":"Real Estate Operator",
            "type":"Services"
        }
    ],
    "sg:phone":"+1 478 474 1427",
    "sg:postcode":"31210",
    "sg:province":"GA",
    "sg:tags":[
        "building",
        "apartment"
    ],
    "wof:name":"River Ridge Apartments",
    "wof:placetype":"venue"
},
  "geometry": {"coordinates":[-83.683831,32.898785],"type":"Point"}
}