{
  "type": "Feature",
  "properties": {
    "iso:country":"US",
    "sg:address":"511 Teal Lake Dr",
    "sg:city":"Richmond Hill",
    "sg:classifiers":[
        {
            "category":"Professional",
            "type":"Services"
        }
    ],
    "sg:phone":"+1 912 756 5242",
    "sg:postcode":"31324",
    "sg:province":"GA",
    "wof:name":"James M Chase",
    "wof:placetype":"venue"
},
  "geometry": {"coordinates":[-81.32367600000001,31.922417],"type":"Point"}
}