{
  "type": "Feature",
  "properties": {
    "addr:full":"28 Vanns Valley Rd SW Rome GA 30161",
    "addr:housenumber":"28",
    "addr:postcode":"ga 30161",
    "addr:street":"Vanns Valley Rd Sw",
    "iso:country":"US",
    "sg:address":"28 Vanns Valley Rd SW",
    "sg:city":"Rome",
    "sg:classifiers":[
        {
            "category":"Organizations",
            "subcategory":"Religious Organization",
            "type":"Services"
        }
    ],
    "sg:phone":"+1 706 234 8353",
    "sg:postcode":"30161",
    "sg:province":"GA",
    "wof:name":"Vanns Valley Baptist Church",
    "wof:placetype":"venue"
},
  "geometry": {"coordinates":[-85.206785,34.179205],"type":"Point"}
}