{
  "type": "Feature",
  "properties": {
    "addr:full":"6790 Highway 92 Acworth GA 30102",
    "addr:housenumber":"6790",
    "addr:postcode":"30102",
    "addr:street":"Highway 92",
    "iso:country":"US",
    "sg:address":"6790 Highway 92",
    "sg:city":"Acworth",
    "sg:classifiers":[
        {
            "category":"Shopping",
            "subcategory":"Jewelry",
            "type":"Retail Goods"
        }
    ],
    "sg:phone":"+1 678 445 2626",
    "sg:postcode":"30102",
    "sg:province":"GA",
    "wof:name":"Rudi Fine Jewelry",
    "wof:placetype":"venue"
},
  "geometry": {"coordinates":[-84.574799,34.087502],"type":"Point"}
}