{
  "type": "Feature",
  "properties": {
    "addr:full":"208 Bell Pl Woodstock GA 30188",
    "addr:housenumber":"208",
    "addr:postcode":"30188",
    "addr:street":"Bell Pl",
    "iso:country":"US",
    "sg:address":"208 Bell Pl",
    "sg:city":"Woodstock",
    "sg:classifiers":[
        {
            "category":"Wholesale",
            "subcategory":"Machinery & Supplies",
            "type":"Manufacturing & Wholesale Goods"
        }
    ],
    "sg:phone":"+1 770 928 0424",
    "sg:postcode":"30188",
    "sg:province":"GA",
    "sg:tags":[
        "rubbish",
        "removal"
    ],
    "wof:name":"Municipal Equipment Sales",
    "wof:placetype":"venue"
},
  "geometry": {"coordinates":[-84.509359,34.120834],"type":"Point"}
}