{
  "type": "Feature",
  "properties": {
    "iso:country":"US",
    "sg:address":"505 Bankhead Hwy",
    "sg:city":"Carrollton",
    "sg:classifiers":[
        {
            "category":"Shopping",
            "subcategory":"Discount & Variety Stores",
            "type":"Retail Goods"
        }
    ],
    "sg:phone":"+1 770 836 8357",
    "sg:postcode":"30117",
    "sg:province":"GA",
    "wof:name":"Dollar General",
    "wof:placetype":"venue"
},
  "geometry": {"coordinates":[-85.058605,33.586564],"type":"Point"}
}