{
  "type": "Feature",
  "properties": {
    "iso:country":"US",
    "sg:address":"1199 Oleander St NW",
    "sg:city":"Atlanta",
    "sg:classifiers":[
        {
            "category":"Professional",
            "type":"Services"
        }
    ],
    "sg:phone":"+1 404 758 2271",
    "sg:postcode":"30314",
    "sg:province":"GA",
    "wof:name":"GL Stewart & Williams Inc",
    "wof:placetype":"venue"
},
  "geometry": {"coordinates":[-84.42720199999999,33.755159],"type":"Point"}
}