{
  "type": "Feature",
  "properties": {
    "addr:full":"1475 Radstone Ct Lawrenceville GA 30044",
    "addr:housenumber":"1475",
    "addr:postcode":"30044",
    "addr:street":"Radstone Ct",
    "iso:country":"US",
    "sg:address":"1475 Radstone Ct",
    "sg:city":"Lawrenceville",
    "sg:classifiers":[
        {
            "category":"Banks & Credit Unions",
            "subcategory":"Investment Brokerage",
            "type":"Services"
        }
    ],
    "sg:phone":"+1 770 982 3290",
    "sg:postcode":"30044",
    "sg:province":"GA",
    "sg:tags":[
        "advisory"
    ],
    "wof:name":"Freedom Financial Services",
    "wof:placetype":"venue"
},
  "geometry": {"coordinates":[-84.01724,33.904285],"type":"Point"}
}