{
  "type": "Feature",
  "properties": {
    "addr:full":"6709 Powers St Riverdale GA 30274",
    "addr:housenumber":"6709",
    "addr:postcode":"30274",
    "addr:street":"Powers St",
    "iso:country":"US",
    "sg:address":"6709 Powers St",
    "sg:city":"Riverdale",
    "sg:classifiers":[
        {
            "category":"Wholesale",
            "subcategory":"Chemicals & Plastics",
            "type":"Manufacturing & Wholesale Goods"
        }
    ],
    "sg:phone":"+1 770 997 0913",
    "sg:postcode":"30274",
    "sg:province":"GA",
    "sg:tags":[
        "oxygen"
    ],
    "wof:name":"CYD Home Health Svc",
    "wof:placetype":"venue"
},
  "geometry": {"coordinates":[-84.413698,33.570954],"type":"Point"}
}