{
  "type": "Feature",
  "properties": {
    "addr:full":"2967 Cobb Pkwy S Atlanta GA 30339",
    "addr:housenumber":"2967",
    "addr:postcode":"30339",
    "addr:street":"Cobb Pkwy S",
    "iso:country":"US",
    "sg:address":"2967 Cobb Pkwy S",
    "sg:city":"Atlanta",
    "sg:classifiers":[
        {
            "category":"Personal",
            "subcategory":"Beauty Salon",
            "type":"Services"
        }
    ],
    "sg:phone":"+1 770 818 9424",
    "sg:postcode":"30339",
    "sg:province":"GA",
    "sg:tags":[
        "shop"
    ],
    "wof:name":"Natova Hair Salon",
    "wof:placetype":"venue"
},
  "geometry": {"coordinates":[-84.462509,33.880799],"type":"Point"}
}