{
  "type": "Feature",
  "properties": {
    "iso:country":"US",
    "sg:address":"737 Cooper Pit Rd",
    "sg:city":"Trion",
    "sg:classifiers":[
        {
            "category":"Building & Trades",
            "subcategory":"Landscaping Services",
            "type":"Services"
        }
    ],
    "sg:phone":"+1 706 734 7593",
    "sg:postcode":"30753",
    "sg:province":"GA",
    "wof:name":"Tudors Exterior Services LLC",
    "wof:placetype":"venue"
},
  "geometry": {"coordinates":[-85.311656,34.578286],"type":"Point"}
}