{
  "type": "Feature",
  "properties": {
    "addr:full":"3772 Pleasantdale Rd NW Atlanta GA 30340",
    "addr:housenumber":"3772",
    "addr:postcode":"30340",
    "addr:street":"Pleasantdale Rd Nw",
    "iso:country":"US",
    "sg:address":"3772 Pleasantdale Rd NW",
    "sg:city":"Atlanta",
    "sg:classifiers":[
        {
            "category":"Wholesale",
            "subcategory":"Electrical",
            "type":"Manufacturing & Wholesale Goods"
        }
    ],
    "sg:phone":"+1 770 270 0822",
    "sg:postcode":"30340",
    "sg:province":"GA",
    "sg:tags":[
        "control",
        "security",
        "system"
    ],
    "wof:name":"Maxpro Security",
    "wof:placetype":"venue"
},
  "geometry": {"coordinates":[-84.246633,33.912847],"type":"Point"}
}