{
  "type": "Feature",
  "properties": {
    "iso:country":"US",
    "sg:address":"277 Old Lake Rd",
    "sg:city":"Guyton",
    "sg:classifiers":[
        {
            "category":"Manufacturing",
            "subcategory":"Signs",
            "type":"Manufacturing & Wholesale Goods"
        }
    ],
    "sg:phone":"+1 912 728 4915",
    "sg:postcode":"31312",
    "sg:province":"GA",
    "sg:tags":[
        "specialty",
        "mfg"
    ],
    "wof:name":"All Brite Signs",
    "wof:placetype":"venue"
},
  "geometry": {"coordinates":[-81.341667,32.195293],"type":"Point"}
}