{
  "type": "Feature",
  "properties": {
    "iso:country":"US",
    "sg:address":"1175 Kenesaw Springs Dr",
    "sg:city":"Kennesaw",
    "sg:classifiers":[
        {
            "category":"Professional",
            "subcategory":"Business Services",
            "type":"Services"
        }
    ],
    "sg:phone":"+1 770 428 1922",
    "sg:postcode":"30144",
    "sg:province":"GA",
    "wof:name":"Gamsol Enterprises",
    "wof:placetype":"venue"
},
  "geometry": {"coordinates":[-84.622663,34.030084],"type":"Point"}
}