{
  "type": "Feature",
  "properties": {
    "addr:full":"2970 Peachtree Rd NW # 856 Atlanta GA 30305",
    "addr:housenumber":"2970",
    "addr:postcode":"30305",
    "addr:street":"Peachtree Rd Nw # 856",
    "iso:country":"US",
    "sg:address":"2970 Peachtree Rd NW # 856",
    "sg:city":"Atlanta",
    "sg:classifiers":[
        {
            "category":"Professional",
            "subcategory":"Advertising",
            "type":"Services"
        }
    ],
    "sg:phone":"+1 404 266 9991",
    "sg:postcode":"30305",
    "sg:province":"GA",
    "sg:tags":[
        "agency",
        "specialty"
    ],
    "sg:website":"http://www.bayardad.com",
    "wof:name":"Bayard Advertising",
    "wof:placetype":"venue"
},
  "geometry": {"coordinates":[-84.382082,33.835568],"type":"Point"}
}