{
  "type": "Feature",
  "properties": {
    "iso:country":"US",
    "sg:address":"2401 Waters Edge Ct NW",
    "sg:city":"Acworth",
    "sg:classifiers":[
        {
            "category":"Professional",
            "type":"Services"
        }
    ],
    "sg:phone":"+1 770 966 1671",
    "sg:postcode":"30101",
    "sg:province":"GA",
    "wof:name":"Web Net Services Inc",
    "wof:placetype":"venue"
},
  "geometry": {"coordinates":[-84.623059,34.066303],"type":"Point"}
}