{
  "type": "Feature",
  "properties": {
    "addr:full":"672 King Taylor Rd Evans GA 30809",
    "addr:housenumber":"672",
    "addr:postcode":"30809",
    "addr:street":"King Taylor Rd",
    "iso:country":"US",
    "sg:address":"672 King Taylor Rd",
    "sg:city":"Evans",
    "sg:classifiers":[
        {
            "category":"Health Services",
            "subcategory":"Nursing And Care Facility",
            "type":"Services"
        }
    ],
    "sg:phone":"+1 706 868 6703",
    "sg:postcode":"30809",
    "sg:province":"GA",
    "sg:tags":[
        "home",
        "retirement",
        "community"
    ],
    "wof:name":"Gospel Water Br Elderly Hsng",
    "wof:placetype":"venue"
},
  "geometry": {"coordinates":[-82.09854900000001,33.544729],"type":"Point"}
}