{
  "type": "Feature",
  "properties": {
    "addr:full":"1160 Old Farm Rd Watkinsville GA 30677",
    "addr:housenumber":"1160",
    "addr:postcode":"30677",
    "addr:street":"Old Farm Rd",
    "iso:country":"US",
    "sg:address":"1160 Old Farm Rd",
    "sg:city":"Watkinsville",
    "sg:classifiers":[
        {
            "category":"Organizations",
            "subcategory":"Professional Association",
            "type":"Services"
        }
    ],
    "sg:phone":"+1 706 769 4357",
    "sg:postcode":"30677",
    "sg:province":"GA",
    "wof:name":"Oconee Parents Union Inc",
    "wof:placetype":"venue"
},
  "geometry": {"coordinates":[-83.464895,33.891636],"type":"Point"}
}