{
  "type": "Feature",
  "properties": {
    "iso:country":"US",
    "sg:address":"519 Shorter Ave SW",
    "sg:city":"Rome",
    "sg:classifiers":[
        {
            "category":"Restaurant",
            "type":"Food & Drink"
        }
    ],
    "sg:menulink":"http://www.allmenus.com/ga/rome/156461-krystal-burgers/menu/",
    "sg:phone":"+1 706 234 4507",
    "sg:postcode":"30165",
    "sg:province":"GA",
    "sg:tags":[
        "burger",
        "chicken",
        "american"
    ],
    "wof:name":"Krystal Burgers",
    "wof:placetype":"venue"
},
  "geometry": {"coordinates":[-85.198053,34.265108],"type":"Point"}
}