{
  "type": "Feature",
  "properties": {
    "addr:full":"1630 Atlanta Rd Gainesville GA 30504",
    "addr:housenumber":"1630",
    "addr:postcode":"30504",
    "addr:street":"Atlanta Rd",
    "iso:country":"US",
    "sg:address":"1630 Atlanta Rd",
    "sg:city":"Gainesville",
    "sg:classifiers":[
        {
            "category":"Travel",
            "subcategory":"Hotels & Motels",
            "type":"Entertainment"
        }
    ],
    "sg:phone":"+1 770 534 7361",
    "sg:postcode":"30504",
    "sg:province":"GA",
    "wof:name":"Georgianna Motel",
    "wof:placetype":"venue"
},
  "geometry": {"coordinates":[-83.841037,34.267424],"type":"Point"}
}