{
  "type": "Feature",
  "properties": {
    "addr:full":"411 Maxham Rd Austell GA 30168",
    "addr:housenumber":"411",
    "addr:postcode":"30168",
    "addr:street":"Maxham Rd",
    "iso:country":"US",
    "sg:address":"411 Maxham Rd",
    "sg:city":"Austell",
    "sg:classifiers":[
        {
            "category":"Wholesale",
            "subcategory":"Office Equipment",
            "type":"Manufacturing & Wholesale Goods"
        },
        {
            "category":"Professional",
            "subcategory":"Advertising",
            "type":"Services"
        },
        {
            "category":"Shopping",
            "subcategory":"Computers & Home Electronics",
            "type":"Retail Goods"
        },
        {
            "category":"Manufacturing",
            "subcategory":"Signs",
            "type":"Manufacturing & Wholesale Goods"
        },
        {
            "category":"Professional",
            "subcategory":"Printing & Photocopies",
            "type":"Services"
        }
    ],
    "sg:phone":"+1 770 941 4115",
    "sg:postcode":"30168",
    "sg:province":"GA",
    "sg:tags":[
        "scanning",
        "printer",
        "supply",
        "services-commercial",
        "specialty",
        "plotting"
    ],
    "wof:name":"Impressions Signs",
    "wof:placetype":"venue"
},
  "geometry": {"coordinates":[-84.620206,33.794832],"type":"Point"}
}