{
  "type": "Feature",
  "properties": {
    "iso:country":"US",
    "sg:address":"432 Hillbridge Rd",
    "sg:city":"Dublin",
    "sg:classifiers":[
        {
            "category":"Organizations",
            "subcategory":"Religious Organization",
            "type":"Services"
        }
    ],
    "sg:phone":"+1 478 875 1418",
    "sg:postcode":"31021",
    "sg:province":"GA",
    "sg:tags":[
        "church"
    ],
    "wof:name":"Beulah Hill Baptist Church",
    "wof:placetype":"venue"
},
  "geometry": {"coordinates":[-83.027439,32.477104],"type":"Point"}
}