{
  "type": "Feature",
  "properties": {
    "iso:country":"US",
    "sg:address":"10 W 11th St",
    "sg:city":"Columbus",
    "sg:classifiers":[
        {
            "category":"Professional",
            "subcategory":"Lawyer & Legal Services",
            "type":"Services"
        }
    ],
    "sg:phone":"+1 706 323 9220",
    "sg:postcode":"31901",
    "sg:province":"GA",
    "sg:tags":[
        "plan"
    ],
    "wof:name":"Georgia Probation Svc Inc",
    "wof:placetype":"venue"
},
  "geometry": {"coordinates":[-84.994499,32.466792],"type":"Point"}
}