{
  "type": "Feature",
  "properties": {
    "addr:full":"723 E Broad Ave Albany GA 31705",
    "addr:housenumber":"723",
    "addr:postcode":"31705",
    "addr:street":"E Broad Ave",
    "iso:country":"US",
    "sg:address":"723 E Broad Ave",
    "sg:city":"Albany",
    "sg:classifiers":[
        {
            "category":"Food & Beverages",
            "subcategory":"Liquor & Beverages",
            "type":"Retail Goods"
        }
    ],
    "sg:phone":"+1 229 883 3281",
    "sg:postcode":"31705",
    "sg:province":"GA",
    "sg:tags":[
        "alcoholic"
    ],
    "wof:name":"Adams Enterprises",
    "wof:placetype":"venue"
},
  "geometry": {"coordinates":[-84.13530299999999,31.576332],"type":"Point"}
}