{
  "type": "Feature",
  "properties": {
    "iso:country":"US",
    "sg:address":"1240 Peacock Ave",
    "sg:city":"Columbus",
    "sg:classifiers":[
        {
            "category":"Personal",
            "subcategory":"Beauty Salon",
            "type":"Services"
        }
    ],
    "sg:phone":"+1 706 660 9011",
    "sg:postcode":"31906",
    "sg:province":"GA",
    "wof:name":"Hair Works On Peacock",
    "wof:placetype":"venue"
},
  "geometry": {"coordinates":[-84.96198699999999,32.470803],"type":"Point"}
}