{
  "type": "Feature",
  "properties": {
    "iso:country":"US",
    "sg:address":"1910 Dean Ave",
    "sg:city":"Rome",
    "sg:classifiers":[
        {
            "category":"Personal",
            "subcategory":"Beauty Salon",
            "type":"Services"
        }
    ],
    "sg:phone":"+1 706 233 9797",
    "sg:postcode":"30161",
    "sg:province":"GA",
    "wof:name":"Hair Structure",
    "wof:placetype":"venue"
},
  "geometry": {"coordinates":[-85.159891,34.229064],"type":"Point"}
}