{
  "type": "Feature",
  "properties": {
    "addr:full":"425 Melrose Ave Griffin GA 30223",
    "addr:housenumber":"425",
    "addr:postcode":"30223",
    "addr:street":"Melrose Ave",
    "iso:country":"US",
    "sg:address":"425 Melrose Ave",
    "sg:city":"Griffin",
    "sg:classifiers":[
        {
            "category":"Retail",
            "subcategory":"Auto Repair",
            "type":"Services"
        }
    ],
    "sg:phone":"+1 770 228 2215",
    "sg:postcode":"30223",
    "sg:province":"GA",
    "sg:tags":[
        "car",
        "foreign"
    ],
    "wof:name":"Coates Collision Center",
    "wof:placetype":"venue"
},
  "geometry": {"coordinates":[-84.28666800000001,33.256614],"type":"Point"}
}