{
  "type": "Feature",
  "properties": {
    "iso:country":"US",
    "sg:address":"127 N Ashley St",
    "sg:city":"Valdosta",
    "sg:classifiers":[
        {
            "category":"Shopping",
            "subcategory":"Florist",
            "type":"Retail Goods"
        }
    ],
    "sg:phone":"+1 229 242 1001",
    "sg:postcode":"31601",
    "sg:province":"GA",
    "wof:name":"Flower Gallery",
    "wof:placetype":"venue"
},
  "geometry": {"coordinates":[-83.27829800000001,30.831439],"type":"Point"}
}