{
  "type": "Feature",
  "properties": {
    "addr:full":"4571 Cox Rd Ste B Evans GA 30809",
    "addr:housenumber":"4571",
    "addr:postcode":"30809",
    "addr:street":"Cox Rd Ste B",
    "iso:country":"US",
    "sg:address":"4571 Cox Rd Ste B",
    "sg:city":"Evans",
    "sg:classifiers":[
        {
            "category":"Insurance",
            "subcategory":"Insurance Agent",
            "type":"Services"
        },
        {
            "category":"Insurance",
            "subcategory":"Hazard Insurance",
            "type":"Services"
        }
    ],
    "sg:phone":"+1 706 651 8050",
    "sg:postcode":"30809",
    "sg:province":"GA",
    "sg:tags":[
        "consultant",
        "analyst"
    ],
    "sg:website":"http://www.selectbenefitconsultants.com",
    "wof:name":"Select Benifit Consultants",
    "wof:placetype":"venue"
},
  "geometry": {"coordinates":[-82.14732100000001,33.526395],"type":"Point"}
}