{
  "type": "Feature",
  "properties": {
    "iso:country":"US",
    "sg:address":"560 Thompson Rd",
    "sg:city":"Dexter",
    "sg:classifiers":[
        {
            "category":"Building & Trades",
            "subcategory":"Landscaping Services",
            "type":"Services"
        }
    ],
    "sg:phone":"+1 478 875 3520",
    "sg:postcode":"31019",
    "sg:province":"GA",
    "wof:name":"Hesters Lawn Care Inc",
    "wof:placetype":"venue"
},
  "geometry": {"coordinates":[-83.119241,32.440307],"type":"Point"}
}