{
  "type": "Feature",
  "properties": {
    "iso:country":"US",
    "sg:address":"8 Roberts St",
    "sg:city":"Savannah",
    "sg:classifiers":[
        {
            "category":"Banks & Credit Unions",
            "subcategory":"Investment Brokerage",
            "type":"Services"
        }
    ],
    "sg:phone":"+1 912 201 9774",
    "sg:postcode":"31408",
    "sg:province":"GA",
    "sg:tags":[
        "advisory"
    ],
    "wof:name":"Compass Group Corp",
    "wof:placetype":"venue"
},
  "geometry": {"coordinates":[-81.138282,32.093757],"type":"Point"}
}