{
  "type": "Feature",
  "properties": {
    "addr:full":"2561 Chamblee Tucker Rd Atlanta GA 30341",
    "addr:housenumber":"2561",
    "addr:postcode":"30341",
    "addr:street":"Chamblee Tucker Rd",
    "iso:country":"US",
    "sg:address":"2561 Chamblee Tucker Rd",
    "sg:city":"Atlanta",
    "sg:classifiers":[
        {
            "category":"Professional",
            "type":"Services"
        },
        {
            "category":"Professional",
            "subcategory":"Lawyer & Legal Services",
            "type":"Services"
        }
    ],
    "sg:phone":"+1 770 458 1851",
    "sg:postcode":"30341",
    "sg:province":"GA",
    "sg:tags":[
        "naturalization",
        "immigration"
    ],
    "wof:name":"Immigration Services Plus",
    "wof:placetype":"venue"
},
  "geometry": {"coordinates":[-84.28357099999999,33.884579],"type":"Point"}
}