{
  "type": "Feature",
  "properties": {
    "addr:full":"736 Ponce De Leon Ave NE Atlanta GA 30306",
    "addr:housenumber":"736",
    "addr:postcode":"30306",
    "addr:street":"Ponce De Leon Ave Ne",
    "iso:country":"US",
    "sg:address":"736 Ponce De Leon Ave NE",
    "sg:city":"Atlanta",
    "sg:classifiers":[
        {
            "category":"Personal",
            "subcategory":"Nail Salon",
            "type":"Services"
        }
    ],
    "sg:phone":"+1 404 881 8709",
    "sg:postcode":"30306",
    "sg:province":"GA",
    "wof:name":"Fresh Nails",
    "wof:placetype":"venue"
},
  "geometry": {"coordinates":[-84.362999,33.7738],"type":"Point"}
}