{
  "type": "Feature",
  "properties": {
    "addr:full":"201 E 3rd St Springfield GA 31329",
    "addr:housenumber":"201",
    "addr:postcode":"31329",
    "addr:street":"E 3Rd St",
    "iso:country":"US",
    "sg:address":"201 E 3rd St",
    "sg:city":"Springfield",
    "sg:classifiers":[
        {
            "category":"Building & Trades",
            "subcategory":"Construction",
            "type":"Services"
        }
    ],
    "sg:phone":"+1 912 754 9120",
    "sg:postcode":"31329",
    "sg:province":"GA",
    "sg:tags":[
        "general",
        "contractor"
    ],
    "wof:name":"Kieffer Construction Co",
    "wof:placetype":"venue"
},
  "geometry": {"coordinates":[-81.308077,32.367637],"type":"Point"}
}