{
  "type": "Feature",
  "properties": {
    "iso:country":"US",
    "sg:address":"1903 Sandlewood Ln",
    "sg:city":"Atlanta",
    "sg:classifiers":[
        {
            "category":"Retail",
            "subcategory":"Repair Shop",
            "type":"Services"
        }
    ],
    "sg:phone":"+1 770 451 2485",
    "sg:postcode":"30341",
    "sg:province":"GA",
    "wof:name":"Everett Handmade Guitars",
    "wof:placetype":"venue"
},
  "geometry": {"coordinates":[-84.310941,33.8957],"type":"Point"}
}