{
  "type": "Feature",
  "properties": {
    "iso:country":"US",
    "sg:address":"101 Sellers St",
    "sg:city":"Douglas",
    "sg:classifiers":[
        {
            "category":"Food & Beverages",
            "subcategory":"Bakery",
            "type":"Retail Goods"
        }
    ],
    "sg:phone":"+1 912 384 2202",
    "sg:postcode":"31533",
    "sg:province":"GA",
    "sg:tags":[
        "pr",
        "baker",
        "mfg"
    ],
    "wof:name":"Holt's Bakery Inc",
    "wof:placetype":"venue"
},
  "geometry": {"coordinates":[-82.85035499999999,31.509942],"type":"Point"}
}