{
  "type": "Feature",
  "properties": {
    "iso:country":"US",
    "sg:address":"335 Sharon Industrial Way NW",
    "sg:city":"Suwanee",
    "sg:classifiers":[
        {
            "category":"Manufacturing",
            "subcategory":"Tools & Machinery",
            "type":"Manufacturing & Wholesale Goods"
        }
    ],
    "sg:phone":"+1 770 271 0812",
    "sg:postcode":"30024",
    "sg:province":"GA",
    "sg:tags":[
        "machine",
        "shop"
    ],
    "wof:name":"Innovative Machining Solutions",
    "wof:placetype":"venue"
},
  "geometry": {"coordinates":[-84.05958699999999,34.04908],"type":"Point"}
}