{
  "type": "Feature",
  "properties": {
    "addr:full":"143 Fite Bend Rd NE Resaca GA 30735",
    "addr:housenumber":"143",
    "addr:postcode":"30735",
    "addr:street":"Fite Bend Rd Ne",
    "iso:country":"US",
    "sg:address":"143 Fite Bend Rd NE",
    "sg:city":"Resaca",
    "sg:classifiers":[
        {
            "category":"Retail",
            "subcategory":"Repair Shop",
            "type":"Services"
        }
    ],
    "sg:phone":"+1 706 629 9848",
    "sg:postcode":"30735",
    "sg:province":"GA",
    "sg:tags":[
        "appliance"
    ],
    "wof:name":"Ray's Appliance Svc",
    "wof:placetype":"venue"
},
  "geometry": {"coordinates":[-84.935327,34.585919],"type":"Point"}
}