{
  "type": "Feature",
  "properties": {
    "addr:full":"3860 Houston Ave Macon GA 31206",
    "addr:housenumber":"3860",
    "addr:postcode":"31206",
    "addr:street":"Houston Ave",
    "iso:country":"US",
    "sg:address":"3860 Houston Ave",
    "sg:city":"Macon",
    "sg:classifiers":[
        {
            "category":"Restaurant",
            "type":"Food & Drink"
        }
    ],
    "sg:phone":"+1 478 788 0460",
    "sg:postcode":"31206",
    "sg:province":"GA",
    "sg:tags":[
        "eating"
    ],
    "wof:name":"Church's Chicken",
    "wof:placetype":"venue"
},
  "geometry": {"coordinates":[-83.653389,32.796563],"type":"Point"}
}