{
  "type": "Feature",
  "properties": {
    "iso:country":"US",
    "sg:address":"4561 Lamore St",
    "sg:city":"Columbus",
    "sg:classifiers":[
        {
            "category":"Retail",
            "subcategory":"Auto Repair",
            "type":"Services"
        }
    ],
    "sg:phone":"+1 706 565 7700",
    "sg:postcode":"31907",
    "sg:province":"GA",
    "sg:tags":[
        "repairing",
        "automobile",
        "general"
    ],
    "wof:name":"John's Auto Repair",
    "wof:placetype":"venue"
},
  "geometry": {"coordinates":[-84.912841,32.481985],"type":"Point"}
}