{
  "type": "Feature",
  "properties": {
    "iso:country":"US",
    "sg:address":"303 Peachtree St NE Ste 4540",
    "sg:city":"Atlanta",
    "sg:classifiers":[
        {
            "category":"Professional",
            "subcategory":"Lawyer & Legal Services",
            "type":"Services"
        }
    ],
    "sg:phone":"+1 404 880 7180",
    "sg:postcode":"30308",
    "sg:province":"GA",
    "wof:name":"Meeks Harold R Jr",
    "wof:placetype":"venue"
},
  "geometry": {"coordinates":[-84.385803,33.7645],"type":"Point"}
}