{
  "type": "Feature",
  "properties": {
    "addr:full":"4765 Truman Mountain Rd Gainesville GA 30506",
    "addr:housenumber":"4765",
    "addr:postcode":"30506",
    "addr:street":"Truman Mountain Rd",
    "iso:country":"US",
    "sg:address":"4765 Truman Mountain Rd",
    "sg:city":"Gainesville",
    "sg:classifiers":[
        {
            "category":"Retail",
            "subcategory":"Auto Repair",
            "type":"Services"
        }
    ],
    "sg:phone":"+1 770 781 2742",
    "sg:postcode":"30506",
    "sg:province":"GA",
    "sg:tags":[
        "general"
    ],
    "wof:name":"Earls Auto",
    "wof:placetype":"venue"
},
  "geometry": {"coordinates":[-83.958158,34.314228],"type":"Point"}
}