{
  "type": "Feature",
  "properties": {
    "iso:country":"US",
    "sg:address":"1000 Moreland Ave SE",
    "sg:city":"Atlanta",
    "sg:classifiers":[
        {
            "category":"Building & Trades",
            "subcategory":"Landscaping Services",
            "type":"Services"
        }
    ],
    "sg:phone":"+1 404 551 4034",
    "sg:postcode":"30316",
    "sg:province":"GA",
    "sg:tags":[
        "tree"
    ],
    "wof:name":"Southland Tree Service Inc",
    "wof:placetype":"venue"
},
  "geometry": {"coordinates":[-84.349367,33.727167],"type":"Point"}
}