{
  "type": "Feature",
  "properties": {
    "iso:country":"US",
    "sg:address":"5832 Stewart Pkwy",
    "sg:city":"Douglasville",
    "sg:classifiers":[
        {
            "category":"Real Estate",
            "subcategory":"Real Estate Operator",
            "type":"Services"
        }
    ],
    "sg:phone":"+1 770 577 7710",
    "sg:postcode":"30135",
    "sg:province":"GA",
    "sg:tags":[
        "building",
        "apartment"
    ],
    "wof:name":"Lenox At Arbor Place Apts",
    "wof:placetype":"venue"
},
  "geometry": {"coordinates":[-84.76488999999999,33.718451],"type":"Point"}
}