{
  "type": "Feature",
  "properties": {
    "addr:full":"190 Grandchester Way Fayetteville GA 30215",
    "addr:housenumber":"190",
    "addr:postcode":"30215",
    "addr:street":"Grandchester Way",
    "iso:country":"US",
    "sg:address":"190 Grandchester Way",
    "sg:city":"Fayetteville",
    "sg:classifiers":[
        {
            "category":"Insurance",
            "subcategory":"Insurance Agent",
            "type":"Services"
        }
    ],
    "sg:phone":"+1 770 460 9726",
    "sg:postcode":"30215",
    "sg:province":"GA",
    "wof:name":"McBroom Assoc Inc",
    "wof:placetype":"venue"
},
  "geometry": {"coordinates":[-84.462459,33.401705],"type":"Point"}
}