{
  "type": "Feature",
  "properties": {
    "addr:full":"1131 Cumberland Mall SE Atlanta GA 30339",
    "addr:housenumber":"1131",
    "addr:postcode":"30339",
    "addr:street":"Cumberland Mall Se",
    "iso:country":"US",
    "sg:address":"1131 Cumberland Mall SE",
    "sg:city":"Atlanta",
    "sg:classifiers":[
        {
            "category":"Building & Trades",
            "subcategory":"Locksmith",
            "type":"Services"
        }
    ],
    "sg:phone":"+1 770 250 0823",
    "sg:postcode":"30339",
    "sg:province":"GA",
    "sg:tags":[
        "key"
    ],
    "wof:name":"1 Day 1 Time Atlanta Locksmith",
    "wof:placetype":"venue"
},
  "geometry": {"coordinates":[-84.471817,33.880953],"type":"Point"}
}