{
  "type": "Feature",
  "properties": {
    "addr:full":"645 NW Frontage Rd Augusta GA 30907",
    "addr:housenumber":"645",
    "addr:postcode":"30907",
    "addr:street":"Nw Frontage Rd",
    "iso:country":"US",
    "sg:address":"645 NW Frontage Rd",
    "sg:city":"Augusta",
    "sg:classifiers":[
        {
            "category":"Professional",
            "subcategory":"Computer Services",
            "type":"Services"
        }
    ],
    "sg:phone":"+1 706 828 3858",
    "sg:postcode":"30907",
    "sg:province":"GA",
    "sg:tags":[
        "website",
        "design"
    ],
    "sg:website":"www.augustabusiness.com",
    "wof:name":"E-Business Solutions",
    "wof:placetype":"venue"
},
  "geometry": {"coordinates":[-82.087367,33.493429],"type":"Point"}
}