{
  "type": "Feature",
  "properties": {
    "iso:country":"US",
    "sg:address":"346 Smith Store Rd",
    "sg:city":"Covington",
    "sg:classifiers":[
        {
            "category":"Building & Trades",
            "subcategory":"Plumbing",
            "type":"Services"
        }
    ],
    "sg:phone":"+1 770 787 7155",
    "sg:postcode":"30016",
    "sg:province":"GA",
    "sg:tags":[
        "contractor"
    ],
    "wof:name":"Shepherd Mechanical Services",
    "wof:placetype":"venue"
},
  "geometry": {"coordinates":[-83.96640600000001,33.565381],"type":"Point"}
}