{
  "type": "Feature",
  "properties": {
    "addr:full":"1720 Wrightsboro Rd Augusta GA 30904",
    "addr:housenumber":"1720",
    "addr:postcode":"30904",
    "addr:street":"Wrightsboro Rd",
    "iso:country":"US",
    "sg:address":"1720 Wrightsboro Rd",
    "sg:city":"Augusta",
    "sg:classifiers":[
        {
            "category":"Personal",
            "subcategory":"Beauty Salon",
            "type":"Services"
        }
    ],
    "sg:phone":"+1 706 733 9202",
    "sg:postcode":"30904",
    "sg:province":"GA",
    "wof:name":"Hairstyles By San",
    "wof:placetype":"venue"
},
  "geometry": {"coordinates":[-81.999987,33.465765],"type":"Point"}
}