{
  "type": "Feature",
  "properties": {
    "addr:full":"6785 Marlborough Cir S Atlanta GA 30349",
    "addr:housenumber":"6785",
    "addr:postcode":"30349",
    "addr:street":"Marlborough Cir S",
    "iso:country":"US",
    "sg:address":"6785 Marlborough Cir S",
    "sg:city":"Atlanta",
    "sg:classifiers":[
        {
            "category":"Professional",
            "subcategory":"Management & Consulting",
            "type":"Services"
        }
    ],
    "sg:phone":"+1 770 994 7404",
    "sg:postcode":"30349",
    "sg:province":"GA",
    "sg:tags":[
        "communications",
        "consultant"
    ],
    "wof:name":"Southpaw Communications Inc",
    "wof:placetype":"venue"
},
  "geometry": {"coordinates":[-84.475489,33.569255],"type":"Point"}
}