{
  "type": "Feature",
  "properties": {
    "addr:full":"4205 Falls Ridge Dr Alpharetta GA 30022",
    "addr:housenumber":"4205",
    "addr:postcode":"30022",
    "addr:street":"Falls Ridge Dr",
    "iso:country":"US",
    "sg:address":"4205 Falls Ridge Dr",
    "sg:city":"Alpharetta",
    "sg:classifiers":[
        {
            "category":"Professional",
            "subcategory":"Management & Consulting",
            "type":"Services"
        }
    ],
    "sg:phone":"+1 678 393 6233",
    "sg:postcode":"30022",
    "sg:province":"GA",
    "sg:tags":[
        "consultant"
    ],
    "wof:name":"R & S Consulting",
    "wof:placetype":"venue"
},
  "geometry": {"coordinates":[-84.237306,34.025711],"type":"Point"}
}