{
  "type": "Feature",
  "properties": {
    "iso:country":"US",
    "sg:address":"72 Landing Ln",
    "sg:city":"Powder Springs",
    "sg:classifiers":[
        {
            "category":"Social Services",
            "subcategory":"Child Care",
            "type":"Services"
        }
    ],
    "sg:phone":"+1 770 949 8758",
    "sg:postcode":"30127",
    "sg:province":"GA",
    "sg:tags":[
        "day"
    ],
    "wof:name":"Loving Arms Childcare",
    "wof:placetype":"venue"
},
  "geometry": {"coordinates":[-84.752151,33.802264],"type":"Point"}
}