{
  "type": "Feature",
  "properties": {
    "addr:full":"5788 Roswell Rd NE Atlanta GA 30328",
    "addr:housenumber":"5788;rd",
    "addr:postcode":"30328",
    "addr:street":"Roswell;Ne",
    "iso:country":"US",
    "sg:address":"5788 Roswell Rd NE",
    "sg:city":"Atlanta",
    "sg:classifiers":[
        {
            "category":"Restaurant",
            "type":"Food & Drink"
        }
    ],
    "sg:phone":"+1 404 255 0035",
    "sg:postcode":"30328",
    "sg:province":"GA",
    "sg:tags":[
        "steakhouse"
    ],
    "sg:website":"http://www.ruthschris.com/",
    "wof:name":"Ruth's Chris Steak House",
    "wof:placetype":"venue"
},
  "geometry": {"coordinates":[-84.379868,33.913202],"type":"Point"}
}