{
  "type": "Feature",
  "properties": {
    "addr:full":"1318 Grantland Rd Griffin GA 30224",
    "addr:housenumber":"1318",
    "addr:postcode":"30224",
    "addr:street":"Grantland Rd",
    "iso:country":"US",
    "sg:address":"1318 Grantland Rd",
    "sg:city":"Griffin",
    "sg:classifiers":[
        {
            "category":"Shopping",
            "type":"Retail Goods"
        }
    ],
    "sg:phone":"+1 770 228 3103",
    "sg:postcode":"30224",
    "sg:province":"GA",
    "sg:tags":[
        "equipment",
        "telephone",
        "supply"
    ],
    "wof:name":"A V Communications",
    "wof:placetype":"venue"
},
  "geometry": {"coordinates":[-84.242132,33.220243],"type":"Point"}
}