{
  "type": "Feature",
  "properties": {
    "addr:full":"2150 Peachford Ln Lawrenceville GA 30043",
    "addr:housenumber":"2150",
    "addr:postcode":"30043",
    "addr:street":"Peachford Ln",
    "iso:country":"US",
    "sg:address":"2150 Peachford Ln",
    "sg:city":"Lawrenceville",
    "sg:classifiers":[
        {
            "category":"Food & Beverages",
            "subcategory":"Groceries & Convenience Stores",
            "type":"Retail Goods"
        }
    ],
    "sg:phone":"+1 770 822 0616",
    "sg:postcode":"30043",
    "sg:province":"GA",
    "wof:name":"Wilson Food Co Inc",
    "wof:placetype":"venue"
},
  "geometry": {"coordinates":[-83.94008100000001,34.035062],"type":"Point"}
}