{
  "type": "Feature",
  "properties": {
    "addr:full":"1901 Kimberly Park Dr Dalton GA 30720",
    "addr:housenumber":"1901",
    "addr:postcode":"30720",
    "addr:street":"Kimberly Park Dr",
    "iso:country":"US",
    "sg:address":"1901 Kimberly Park Dr",
    "sg:city":"Dalton",
    "sg:classifiers":[
        {
            "category":"Shopping",
            "type":"Retail Goods"
        }
    ],
    "sg:phone":"+1 706 226 2081",
    "sg:postcode":"30720",
    "sg:province":"GA",
    "sg:tags":[
        "chemical"
    ],
    "wof:name":"Tri-F Industries",
    "wof:placetype":"venue"
},
  "geometry": {"coordinates":[-85.000218,34.800126],"type":"Point"}
}