{
  "type": "Feature",
  "properties": {
    "addr:full":"4642 Glory Maple Trce Powder Springs GA 30127",
    "addr:housenumber":"4642",
    "addr:postcode":"30127",
    "addr:street":"Glory Maple Trce",
    "iso:country":"US",
    "sg:address":"4642 Glory Maple Trce",
    "sg:city":"Powder Springs",
    "sg:classifiers":[
        {
            "category":"Professional",
            "type":"Services"
        }
    ],
    "sg:phone":"+1 770 616 0874",
    "sg:postcode":"30127",
    "sg:province":"GA",
    "wof:name":"Sntshelving Mirrors",
    "wof:placetype":"venue"
},
  "geometry": {"coordinates":[-84.68594899999999,33.931075],"type":"Point"}
}