{
  "type": "Feature",
  "properties": {
    "iso:country":"US",
    "sg:address":"100 W Oglethorpe Blvd",
    "sg:city":"Albany",
    "sg:classifiers":[
        {
            "category":"Recreation",
            "type":"Entertainment"
        }
    ],
    "sg:phone":"+1 229 430 5204",
    "sg:postcode":"31701",
    "sg:province":"GA",
    "sg:tags":[
        "hall",
        "auditorium"
    ],
    "sg:website":"www.albany.ga.us",
    "wof:name":"Civic Center Complex",
    "wof:placetype":"venue"
},
  "geometry": {"coordinates":[-84.151383,31.575302],"type":"Point"}
}