{
  "type": "Feature",
  "properties": {
    "addr:full":"6 Helena Ave SW Atlanta GA 30310",
    "addr:housenumber":"6",
    "addr:postcode":"30310",
    "addr:street":"Helena Ave Sw",
    "iso:country":"US",
    "sg:address":"6 Helena Ave SW",
    "sg:city":"Atlanta",
    "sg:classifiers":[
        {
            "category":"Building & Trades",
            "subcategory":"Locksmith",
            "type":"Services"
        }
    ],
    "sg:phone":"+1 866 299 5106",
    "sg:postcode":"30310",
    "sg:province":"GA",
    "sg:tags":[
        "key"
    ],
    "wof:name":"1 & A Emergency Locksmith",
    "wof:placetype":"venue"
},
  "geometry": {"coordinates":[-84.447132,33.75108],"type":"Point"}
}