{
  "type": "Feature",
  "properties": {
    "addr:full":"413 E Robert Toombs Ave Washington GA 30673",
    "addr:housenumber":"413",
    "addr:postcode":"30673",
    "addr:street":"E Robert Toombs Ave",
    "iso:country":"US",
    "sg:address":"413 E Robert Toombs Ave",
    "sg:city":"Washington",
    "sg:classifiers":[
        {
            "category":"Professional",
            "type":"Services"
        }
    ],
    "sg:phone":"+1 706 678 3681",
    "sg:postcode":"30673",
    "sg:province":"GA",
    "wof:name":"George M Winfrey",
    "wof:placetype":"venue"
},
  "geometry": {"coordinates":[-82.73017900000001,33.735063],"type":"Point"}
}