{
  "type": "Feature",
  "properties": {
    "iso:country":"US",
    "sg:address":"1018 W Oglethorpe Hwy",
    "sg:city":"Hinesville",
    "sg:classifiers":[
        {
            "category":"Freight",
            "type":"Transportation"
        }
    ],
    "sg:phone":"+1 912 369 3636",
    "sg:postcode":"31313",
    "sg:province":"GA",
    "sg:tags":[
        "commercial",
        "storage"
    ],
    "wof:name":"A-1 Mini Storage",
    "wof:placetype":"venue"
},
  "geometry": {"coordinates":[-81.60541000000001,31.801084],"type":"Point"}
}