{
  "type": "Feature",
  "properties": {
    "addr:full":"533 Pinecrest Rd Canton GA 30115",
    "addr:housenumber":"533",
    "addr:postcode":"30115",
    "addr:street":"Pinecrest Rd",
    "iso:country":"US",
    "sg:address":"533 Pinecrest Rd",
    "sg:city":"Canton",
    "sg:classifiers":[
        {
            "category":"Organizations",
            "subcategory":"Community Association",
            "type":"Services"
        }
    ],
    "sg:phone":"+1 770 345 4974",
    "sg:postcode":"30115",
    "sg:province":"GA",
    "sg:tags":[
        "environmental",
        "org"
    ],
    "wof:name":"Enviro Air Inc",
    "wof:placetype":"venue"
},
  "geometry": {"coordinates":[-84.500922,34.180425],"type":"Point"}
}