{
  "type": "Feature",
  "properties": {
    "addr:full":"6 Concourse Pkwy NE Atlanta GA 30328",
    "addr:housenumber":"6",
    "addr:postcode":"30328",
    "addr:street":"Concourse Pkwy Ne",
    "iso:country":"US",
    "sg:address":"6 Concourse Pkwy NE",
    "sg:city":"Atlanta",
    "sg:classifiers":[
        {
            "category":"Professional",
            "subcategory":"Management & Consulting",
            "type":"Services"
        }
    ],
    "sg:phone":"+1 770 901 9664",
    "sg:postcode":"30328",
    "sg:province":"GA",
    "sg:tags":[
        "public",
        "relations"
    ],
    "wof:name":"Newsmakers",
    "wof:placetype":"venue"
},
  "geometry": {"coordinates":[-84.350949,33.916401],"type":"Point"}
}