{
  "type": "Feature",
  "properties": {
    "iso:country":"US",
    "sg:address":"103 Remington Ct",
    "sg:city":"Woodstock",
    "sg:classifiers":[
        {
            "category":"Recreation",
            "type":"Entertainment"
        }
    ],
    "sg:phone":"+1 770 235 0903",
    "sg:postcode":"30188",
    "sg:province":"GA",
    "sg:tags":[
        "amusement"
    ],
    "wof:name":"Real Tennis In Atlanta",
    "wof:placetype":"venue"
},
  "geometry": {"coordinates":[-84.507336,34.092786],"type":"Point"}
}