{
  "type": "Feature",
  "properties": {
    "addr:full":"5435 Francis Ave Stone Mountain GA 30087",
    "addr:housenumber":"5435",
    "addr:postcode":"30087",
    "addr:street":"Francis Ave",
    "iso:country":"US",
    "sg:address":"5435 Francis Ave",
    "sg:city":"Stone Mountain",
    "sg:classifiers":[
        {
            "category":"Utilities",
            "subcategory":"Telephone",
            "type":"Services"
        }
    ],
    "sg:phone":"+1 404 791 3093",
    "sg:postcode":"30087",
    "sg:province":"GA",
    "sg:tags":[
        "communications"
    ],
    "wof:name":"Sanocki & Assoc Inc",
    "wof:placetype":"venue"
},
  "geometry": {"coordinates":[-84.12682100000001,33.834372],"type":"Point"}
}