{
  "type": "Feature",
  "properties": {
    "iso:country":"US",
    "sg:address":"6670 Jones Mill Ct",
    "sg:city":"Norcross",
    "sg:classifiers":[
        {
            "category":"Wholesale",
            "subcategory":"Sporting Goods",
            "type":"Manufacturing & Wholesale Goods"
        }
    ],
    "sg:phone":"+1 770 300 9022",
    "sg:postcode":"30092",
    "sg:province":"GA",
    "sg:tags":[
        "equipment",
        "bowling",
        "supply"
    ],
    "wof:name":"Maxeys Jim Bowling & Trophy Sp",
    "wof:placetype":"venue"
},
  "geometry": {"coordinates":[-84.253798,33.942982],"type":"Point"}
}