{
  "type": "Feature",
  "properties": {
    "iso:country":"US",
    "sg:address":"101 Petrol Pt",
    "sg:city":"Peachtree City",
    "sg:classifiers":[
        {
            "category":"Food & Beverages",
            "subcategory":"Liquor & Beverages",
            "type":"Retail Goods"
        }
    ],
    "sg:phone":"+1 770 487 9998",
    "sg:postcode":"30269",
    "sg:province":"GA",
    "sg:tags":[
        "beer",
        "spirit",
        "wine"
    ],
    "wof:name":"Brandon's Package Store",
    "wof:placetype":"venue"
},
  "geometry": {"coordinates":[-84.560799,33.4114],"type":"Point"}
}