{
  "type": "Feature",
  "properties": {
    "addr:full":"1495 Alpharetta Hwy Ste D Alpharetta GA 30004",
    "addr:housenumber":"1495",
    "addr:postcode":"30004",
    "addr:street":"Alpharetta Hwy Ste D",
    "iso:country":"US",
    "sg:address":"1495 Alpharetta Hwy Ste D",
    "sg:city":"Alpharetta",
    "sg:classifiers":[
        {
            "category":"Health Services",
            "subcategory":"Chiropractor",
            "type":"Services"
        }
    ],
    "sg:phone":"+1 770 521 1114",
    "sg:postcode":"30004",
    "sg:province":"GA",
    "sg:website":"www.starmanchiropractic.com",
    "wof:name":"Starman Chiropractic Center",
    "wof:placetype":"venue"
},
  "geometry": {"coordinates":[-84.31650399999999,34.066706],"type":"Point"}
}