{
  "type": "Feature",
  "properties": {
    "addr:full":"47 Wyman St NE Atlanta GA 30317",
    "addr:housenumber":"47",
    "addr:postcode":"30317",
    "addr:street":"Wyman St Ne",
    "iso:country":"US",
    "sg:address":"47 Wyman St NE",
    "sg:city":"Atlanta",
    "sg:classifiers":[
        {
            "category":"Wholesale",
            "subcategory":"Home Furnishings",
            "type":"Manufacturing & Wholesale Goods"
        }
    ],
    "sg:phone":"+1 404 234 8201",
    "sg:postcode":"30317",
    "sg:province":"GA",
    "sg:tags":[
        "blind",
        "shade"
    ],
    "sg:website":"www.stitchbig.com",
    "wof:name":"StitchBig",
    "wof:placetype":"venue"
},
  "geometry": {"coordinates":[-84.33269,33.754775],"type":"Point"}
}