{
  "type": "Feature",
  "properties": {
    "iso:country":"US",
    "sg:address":"1553 Old Farmington Rd",
    "sg:city":"Watkinsville",
    "sg:classifiers":[
        {
            "category":"Professional",
            "type":"Services"
        }
    ],
    "sg:phone":"+1 706 769 8168",
    "sg:postcode":"30677",
    "sg:province":"GA",
    "wof:name":"Gerald K Scoggins",
    "wof:placetype":"venue"
},
  "geometry": {"coordinates":[-83.41480199999999,33.798094],"type":"Point"}
}