{
  "type": "Feature",
  "properties": {
    "iso:country":"US",
    "sg:address":"1813 Boy Scout Camp Rd",
    "sg:city":"Riceboro",
    "sg:classifiers":[
        {
            "category":"Travel",
            "subcategory":"Campground",
            "type":"Entertainment"
        }
    ],
    "sg:phone":"+1 912 884 3001",
    "sg:postcode":"31323",
    "sg:province":"GA",
    "sg:tags":[
        "camp"
    ],
    "wof:name":"Coastal Empire Council",
    "wof:placetype":"venue"
},
  "geometry": {"coordinates":[-81.388665,31.711927],"type":"Point"}
}