{
  "type": "Feature",
  "properties": {
    "addr:full":"70 Bullsboro Dr Newnan GA 30263",
    "addr:housenumber":"70",
    "addr:postcode":"30263",
    "addr:street":"Bullsboro Dr",
    "iso:country":"US",
    "sg:address":"70 Bullsboro Dr",
    "sg:city":"Newnan",
    "sg:classifiers":[
        {
            "category":"Retail",
            "subcategory":"Auto Rental",
            "type":"Services"
        }
    ],
    "sg:phone":"+1 770 252 1077",
    "sg:postcode":"30263",
    "sg:province":"GA",
    "sg:tags":[
        "renting",
        "automobile",
        "passenger",
        "car"
    ],
    "wof:name":"Enterprise Rent-A-Car Company",
    "wof:placetype":"venue"
},
  "geometry": {"coordinates":[-84.78605,33.383675],"type":"Point"}
}