{
  "type": "Feature",
  "properties": {
    "addr:full":"711 Atlanta Rd Gainesville GA 30501",
    "addr:housenumber":"711",
    "addr:postcode":"30501",
    "addr:street":"Atlanta Rd",
    "iso:country":"US",
    "sg:address":"711 Atlanta Rd",
    "sg:city":"Gainesville",
    "sg:classifiers":[
        {
            "category":"Wholesale",
            "subcategory":"Motor Vehicles",
            "type":"Manufacturing & Wholesale Goods"
        }
    ],
    "sg:phone":"+1 678 450 0161",
    "sg:postcode":"30501",
    "sg:province":"GA",
    "sg:tags":[
        "automobile",
        "truck",
        "broker"
    ],
    "wof:name":"Hott Wheels Auto Brokers",
    "wof:placetype":"venue"
},
  "geometry": {"coordinates":[-83.839989,34.279192],"type":"Point"}
}