{
  "type": "Feature",
  "properties": {
    "iso:country":"US",
    "sg:address":"307 Grand Island Dr",
    "sg:city":"Albany",
    "sg:classifiers":[
        {
            "category":"Wholesale",
            "subcategory":"Medical Equipment & Supplies",
            "type":"Manufacturing & Wholesale Goods"
        },
        {
            "category":"Retail",
            "subcategory":"Repair Shop",
            "type":"Services"
        }
    ],
    "sg:phone":"+1 229 434 0213",
    "sg:postcode":"31707",
    "sg:province":"GA",
    "sg:tags":[
        "repairing",
        "aids-parts",
        "hearing",
        "device",
        "assistive",
        "aid"
    ],
    "sg:website":"http://www.yourhearing.net",
    "wof:name":"Albany Hearing Aid Center",
    "wof:placetype":"venue"
},
  "geometry": {"coordinates":[-84.20419800000001,31.623754],"type":"Point"}
}