{
  "type": "Feature",
  "properties": {
    "iso:country":"US",
    "sg:address":"3343 Brickey Ln",
    "sg:city":"Marietta",
    "sg:classifiers":[
        {
            "category":"Shopping",
            "subcategory":"Catalog Store",
            "type":"Retail Goods"
        }
    ],
    "sg:phone":"+1 770 425 6688",
    "sg:postcode":"30068",
    "sg:province":"GA",
    "sg:tags":[
        "mail",
        "house"
    ],
    "wof:name":"Home To Home Inc",
    "wof:placetype":"venue"
},
  "geometry": {"coordinates":[-84.458405,33.951252],"type":"Point"}
}