{
  "type": "Feature",
  "properties": {
    "iso:country":"US",
    "sg:address":"200 Village Center Pkwy",
    "sg:city":"Stockbridge",
    "sg:classifiers":[
        {
            "category":"Real Estate",
            "subcategory":"Real Estate Services",
            "type":"Services"
        }
    ],
    "sg:phone":"+1 770 474 4981",
    "sg:postcode":"30281",
    "sg:province":"GA",
    "sg:tags":[
        "management",
        "property"
    ],
    "wof:name":"Group Six Property Management",
    "wof:placetype":"venue"
},
  "geometry": {"coordinates":[-84.230003,33.5252],"type":"Point"}
}