{
  "type": "Feature",
  "properties": {
    "addr:full":"4400 Ashford-Dunwoody Rd Dunwoody GA 30346",
    "addr:housenumber":"4400",
    "addr:postcode":"30346",
    "addr:street":"Ashford-Dunwoody Rd",
    "iso:country":"US",
    "sg:address":"4400 Ashford-Dunwoody Rd",
    "sg:city":"Dunwoody",
    "sg:classifiers":[
        {
            "category":"Shopping",
            "subcategory":"Beauty & Cosmetics",
            "type":"Retail Goods"
        }
    ],
    "sg:phone":"+1 770 394 7510",
    "sg:postcode":"30346",
    "sg:province":"GA",
    "sg:tags":[
        "supply"
    ],
    "sg:website":"bareescentuals.com/",
    "wof:name":"Bare Escentuals",
    "wof:placetype":"venue"
},
  "geometry": {"coordinates":[-84.340515,33.921742],"type":"Point"}
}