{
  "type": "Feature",
  "properties": {
    "iso:country":"US",
    "sg:address":"1601 Fair Rd",
    "sg:city":"Statesboro",
    "sg:classifiers":[
        {
            "category":"Health Services",
            "subcategory":"Doctor",
            "type":"Services"
        }
    ],
    "sg:phone":"+1 912 354 6190",
    "sg:postcode":"30458",
    "sg:province":"GA",
    "sg:tags":[
        "physician",
        "surgeon"
    ],
    "wof:name":"Coastal Allergy & Asthma",
    "wof:placetype":"venue"
},
  "geometry": {"coordinates":[-81.764808,32.409647],"type":"Point"}
}