{
  "type": "Feature",
  "properties": {
    "iso:country":"US",
    "sg:address":"2175 W Broad St",
    "sg:city":"Athens",
    "sg:classifiers":[
        {
            "category":"Manufacturing",
            "subcategory":"Printing",
            "type":"Manufacturing & Wholesale Goods"
        }
    ],
    "sg:phone":"+1 706 353 2225",
    "sg:postcode":"30606",
    "sg:province":"GA",
    "sg:tags":[
        "offset"
    ],
    "wof:name":"A B C Printing",
    "wof:placetype":"venue"
},
  "geometry": {"coordinates":[-83.409136,33.949838],"type":"Point"}
}