{
  "type": "Feature",
  "properties": {
    "iso:country":"US",
    "sg:address":"3946 Glen Park Dr",
    "sg:city":"Lithonia",
    "sg:classifiers":[
        {
            "category":"Wholesale",
            "subcategory":"Plants",
            "type":"Manufacturing & Wholesale Goods"
        },
        {
            "category":"Shopping",
            "subcategory":"Crafts & Fabrics",
            "type":"Retail Goods"
        }
    ],
    "sg:phone":"+1 770 322 1811",
    "sg:postcode":"30038",
    "sg:province":"GA",
    "sg:tags":[
        "florists'",
        "supply",
        "florists-wholesale",
        "florist",
        "supplies-wholesale",
        "manufacturer"
    ],
    "wof:name":"Palace Enterprises",
    "wof:placetype":"venue"
},
  "geometry": {"coordinates":[-84.205991,33.666674],"type":"Point"}
}