{
  "type": "Feature",
  "properties": {
    "addr:full":"1515 Sheridan Rd NE Atlanta GA 30324",
    "addr:housenumber":"1515",
    "addr:postcode":"30324",
    "addr:street":"Sheridan Rd Ne",
    "iso:country":"US",
    "sg:address":"1515 Sheridan Rd NE",
    "sg:city":"Atlanta",
    "sg:classifiers":[
        {
            "category":"Sports & Exercise",
            "subcategory":"Gym",
            "type":"Entertainment"
        },
        {
            "category":"Sports & Exercise",
            "subcategory":"Playing Field",
            "type":"Entertainment"
        }
    ],
    "sg:phone":"+1 404 325 2700",
    "sg:postcode":"30324",
    "sg:province":"GA",
    "sg:tags":[
        "trainer",
        "instruction",
        "fitness"
    ],
    "sg:website":"www.athleticclubnortheast.com",
    "wof:name":"Atlanta Athletic Club Northeast",
    "wof:placetype":"venue"
},
  "geometry": {"coordinates":[-84.33774099999999,33.824106],"type":"Point"}
}