{
  "type": "Feature",
  "properties": {
    "iso:country":"US",
    "sg:address":"54 Saddle Field Cir NW",
    "sg:city":"Cartersville",
    "sg:classifiers":[
        {
            "category":"Arts & Performance",
            "subcategory":"Theater",
            "type":"Entertainment"
        }
    ],
    "sg:phone":"+1 770 387 1386",
    "sg:postcode":"30121",
    "sg:province":"GA",
    "sg:tags":[
        "group"
    ],
    "wof:name":"Collier Mc Productions Inc",
    "wof:placetype":"venue"
},
  "geometry": {"coordinates":[-84.837932,34.252829],"type":"Point"}
}