{
  "type": "Feature",
  "properties": {
    "addr:full":"5019 Jimmy Carter Blvd Norcross GA 30093",
    "addr:housenumber":"5019",
    "addr:postcode":"30093",
    "addr:street":"Jimmy Carter Blvd",
    "iso:country":"US",
    "sg:address":"5019 Jimmy Carter Blvd",
    "sg:city":"Norcross",
    "sg:classifiers":[
        {
            "category":"Restaurant",
            "type":"Food & Drink"
        }
    ],
    "sg:menulink":"http://www.allmenus.com/ga/lilburn/64225-chuck-e-cheeses/menu/",
    "sg:phone":"+1 770 449 1767",
    "sg:postcode":"30093",
    "sg:province":"GA",
    "sg:tags":[
        "american",
        "pizza"
    ],
    "wof:name":"Chuck E. Cheese's",
    "wof:placetype":"venue"
},
  "geometry": {"coordinates":[-84.19711599999999,33.897303],"type":"Point"}
}