{
  "type": "Feature",
  "properties": {
    "iso:country":"US",
    "sg:address":"2052 S Cobb Dr",
    "sg:city":"Marietta",
    "sg:classifiers":[
        {
            "category":"Retail",
            "subcategory":"Self-service Laundry",
            "type":"Services"
        }
    ],
    "sg:phone":"+1 770 805 4083",
    "sg:postcode":"30060",
    "sg:province":"GA",
    "wof:name":"Lee's One Coin Laundry",
    "wof:placetype":"venue"
},
  "geometry": {"coordinates":[-84.540459,33.899113],"type":"Point"}
}