{
  "type": "Feature",
  "properties": {
    "iso:country":"US",
    "sg:address":"1225 Broadrick Dr",
    "sg:city":"Dalton",
    "sg:classifiers":[
        {
            "category":"Social Services",
            "subcategory":"Job Training",
            "type":"Services"
        }
    ],
    "sg:phone":"+1 706 272 6199",
    "sg:postcode":"30720",
    "sg:province":"GA",
    "sg:tags":[
        "rehabilitation"
    ],
    "sg:website":"www.hhcs.org",
    "wof:name":"Hamilton Bradley Ctr",
    "wof:placetype":"venue"
},
  "geometry": {"coordinates":[-84.985984,34.787323],"type":"Point"}
}