{
  "type": "Feature",
  "properties": {
    "iso:country":"US",
    "sg:address":"316 W Pike St Ste 100",
    "sg:city":"Lawrenceville",
    "sg:classifiers":[
        {
            "category":"Health Services",
            "subcategory":"Doctor",
            "type":"Services"
        }
    ],
    "sg:phone":"+1 770 682 8442",
    "sg:postcode":"30045",
    "sg:province":"GA",
    "sg:tags":[
        "medicine",
        "internal"
    ],
    "wof:name":"Deutsch Samuel MD",
    "wof:placetype":"venue"
},
  "geometry": {"coordinates":[-83.99569700000001,33.957199],"type":"Point"}
}