{
  "type": "Feature",
  "properties": {
    "iso:country":"US",
    "sg:address":"2490 Meadow Grove Way SW",
    "sg:city":"Lilburn",
    "sg:classifiers":[
        {
            "category":"Building & Trades",
            "subcategory":"Construction",
            "type":"Services"
        }
    ],
    "sg:phone":"+1 770 465 8710",
    "sg:postcode":"30047",
    "sg:province":"GA",
    "sg:tags":[
        "wallcoverings-installation",
        "wallpaper",
        "painting",
        "contractor"
    ],
    "wof:name":"A1 Decorating & Consulting",
    "wof:placetype":"venue"
},
  "geometry": {"coordinates":[-84.095806,33.814347],"type":"Point"}
}