{
  "type": "Feature",
  "properties": {
    "addr:full":"100 Pinnacle Way Norcross GA 30071",
    "addr:housenumber":"100",
    "addr:postcode":"30071",
    "addr:street":"Pinnacle Way",
    "iso:country":"US",
    "sg:address":"100 Pinnacle Way",
    "sg:city":"Norcross",
    "sg:classifiers":[
        {
            "category":"Professional",
            "type":"Services"
        }
    ],
    "sg:phone":"+1 770 263 8840",
    "sg:postcode":"30071",
    "sg:province":"GA",
    "sg:tags":[
        "establishment"
    ],
    "wof:name":"Solution Dynamics",
    "wof:placetype":"venue"
},
  "geometry": {"coordinates":[-84.18342,33.927899],"type":"Point"}
}