{
  "type": "Feature",
  "properties": {
    "addr:full":"349 Decatur St Atlanta GA 30312",
    "addr:housenumber":"349",
    "addr:postcode":"30312",
    "addr:street":"Decatur St",
    "iso:country":"US",
    "sg:address":"349 Decatur St",
    "sg:city":"Atlanta",
    "sg:classifiers":[
        {
            "category":"Coffee & Tea",
            "type":"Food & Drink"
        },
        {
            "category":"Wholesale",
            "subcategory":"Home Furnishings",
            "type":"Manufacturing & Wholesale Goods"
        }
    ],
    "sg:postcode":"30312",
    "sg:province":"GA",
    "sg:tags":[
        "plate",
        "tapas/small"
    ],
    "wof:name":"Marlee's Coffee Tea & Tapas",
    "wof:placetype":"venue"
},
  "geometry": {"coordinates":[-84.378648,33.749928],"type":"Point"}
}