{
  "type": "Feature",
  "properties": {
    "iso:country":"US",
    "sg:address":"157 Kettlewood Dr SW",
    "sg:city":"Lilburn",
    "sg:classifiers":[
        {
            "category":"Building & Trades",
            "subcategory":"Pest Control",
            "type":"Services"
        }
    ],
    "sg:phone":"+1 770 885 2007",
    "sg:postcode":"30047",
    "sg:province":"GA",
    "wof:name":"Udonso Pest Control",
    "wof:placetype":"venue"
},
  "geometry": {"coordinates":[-84.13441,33.876486],"type":"Point"}
}