{
  "type": "Feature",
  "properties": {
    "iso:country":"US",
    "sg:address":"105 Victory Ln",
    "sg:city":"Rincon",
    "sg:classifiers":[
        {
            "category":"Building & Trades",
            "subcategory":"Construction",
            "type":"Services"
        }
    ],
    "sg:phone":"+1 912 826 6639",
    "sg:postcode":"31326",
    "sg:province":"GA",
    "sg:tags":[
        "fabricator",
        "metal"
    ],
    "wof:name":"Metal Clad Industries",
    "wof:placetype":"venue"
},
  "geometry": {"coordinates":[-81.237506,32.312388],"type":"Point"}
}