{
  "type": "Feature",
  "properties": {
    "iso:country":"US",
    "sg:address":"3960 Halls Chapel Rd",
    "sg:city":"Crandall",
    "sg:classifiers":[
        {
            "category":"Real Estate",
            "subcategory":"Developer",
            "type":"Services"
        }
    ],
    "sg:phone":"+1 706 695 5504",
    "sg:postcode":"30711",
    "sg:province":"GA",
    "wof:name":"Whitfield Development Co",
    "wof:placetype":"venue"
},
  "geometry": {"coordinates":[-84.77991,34.941849],"type":"Point"}
}