{
  "type": "Feature",
  "properties": {
    "iso:country":"US",
    "sg:address":"822 Heritage Sq",
    "sg:city":"Decatur",
    "sg:classifiers":[
        {
            "category":"Professional",
            "type":"Services"
        }
    ],
    "sg:phone":"+1 404 929 0276",
    "sg:postcode":"30033",
    "sg:province":"GA",
    "wof:name":"James Helton",
    "wof:placetype":"venue"
},
  "geometry": {"coordinates":[-84.30122900000001,33.802714],"type":"Point"}
}