{
  "type": "Feature",
  "properties": {
    "addr:full":"1814 Kolb Farm Cir SW Marietta GA 30008",
    "addr:housenumber":"1814",
    "addr:postcode":"30008",
    "addr:street":"Kolb Farm Cir Sw",
    "iso:country":"US",
    "sg:address":"1814 Kolb Farm Cir SW",
    "sg:city":"Marietta",
    "sg:classifiers":[
        {
            "category":"Health Services",
            "subcategory":"Chiropractor",
            "type":"Services"
        }
    ],
    "sg:phone":"+1 770 423 4230",
    "sg:postcode":"30008",
    "sg:province":"GA",
    "wof:name":"Performance For Life",
    "wof:placetype":"venue"
},
  "geometry": {"coordinates":[-84.597206,33.908563],"type":"Point"}
}