{
  "type": "Feature",
  "properties": {
    "addr:full":"106 Bleeker St SW Lawrenceville GA 30044",
    "addr:housenumber":"106",
    "addr:postcode":"30044",
    "addr:street":"Bleeker St Sw",
    "iso:country":"US",
    "sg:address":"106 Bleeker St SW",
    "sg:city":"Lawrenceville",
    "sg:classifiers":[
        {
            "category":"Shopping",
            "subcategory":"Clothing, Apparel, & Fashions",
            "type":"Retail Goods"
        }
    ],
    "sg:phone":"+1 770 846 0237",
    "sg:postcode":"30044",
    "sg:province":"GA",
    "wof:name":"Classic Cabinet Designs",
    "wof:placetype":"venue"
},
  "geometry": {"coordinates":[-84.078757,33.905033],"type":"Point"}
}