{
  "type": "Feature",
  "properties": {
    "addr:full":"3520 Victory Dr Columbus GA 31903",
    "addr:housenumber":"3520",
    "addr:postcode":"31903",
    "addr:street":"Victory Dr",
    "iso:country":"US",
    "sg:address":"3520 Victory Dr",
    "sg:city":"Columbus",
    "sg:classifiers":[
        {
            "category":"Restaurant",
            "type":"Food & Drink"
        }
    ],
    "sg:phone":"+1 706 682 2440",
    "sg:postcode":"31903",
    "sg:province":"GA",
    "sg:tags":[
        "eating"
    ],
    "wof:name":"KFC",
    "wof:placetype":"venue"
},
  "geometry": {"coordinates":[-84.94716099999999,32.422871],"type":"Point"}
}