{
  "type": "Feature",
  "properties": {
    "iso:country":"US",
    "sg:address":"145 Belmont Trce NW",
    "sg:city":"Atlanta",
    "sg:classifiers":[
        {
            "category":"Real Estate",
            "subcategory":"Real Estate Operator",
            "type":"Services"
        }
    ],
    "sg:phone":"+1 404 255 0737",
    "sg:postcode":"30328",
    "sg:province":"GA",
    "sg:tags":[
        "mobile",
        "manufactured",
        "housing-communities",
        "park",
        "home"
    ],
    "wof:name":"Ansley Park Cartersville",
    "wof:placetype":"venue"
},
  "geometry": {"coordinates":[-84.387671,33.932472],"type":"Point"}
}