{
  "type": "Feature",
  "properties": {
    "addr:full":"4750 Cambridge Park Ct NW Duluth GA 30096",
    "addr:housenumber":"4750",
    "addr:postcode":"30096",
    "addr:street":"Cambridge Park Ct Nw",
    "iso:country":"US",
    "sg:address":"4750 Cambridge Park Ct NW",
    "sg:city":"Duluth",
    "sg:classifiers":[
        {
            "category":"Wholesale",
            "subcategory":"Electrical",
            "type":"Manufacturing & Wholesale Goods"
        }
    ],
    "sg:phone":"+1 678 969 9278",
    "sg:postcode":"30096",
    "sg:province":"GA",
    "sg:tags":[
        "electronic"
    ],
    "wof:name":"Sunday Communications",
    "wof:placetype":"venue"
},
  "geometry": {"coordinates":[-84.17815400000001,33.958057],"type":"Point"}
}