{
  "type": "Feature",
  "properties": {
    "addr:full":"1326 White St SW Atlanta GA 30310",
    "addr:housenumber":"1326",
    "addr:postcode":"30310",
    "addr:street":"White St Sw",
    "iso:country":"US",
    "sg:address":"1326 White St SW",
    "sg:city":"Atlanta",
    "sg:classifiers":[
        {
            "category":"Shopping",
            "subcategory":"Used Merchandise",
            "type":"Retail Goods"
        }
    ],
    "sg:phone":"+1 404 549 9108",
    "sg:postcode":"30310",
    "sg:province":"GA",
    "sg:tags":[
        "resale",
        "shop"
    ],
    "wof:name":"Attic Close Out",
    "wof:placetype":"venue"
},
  "geometry": {"coordinates":[-84.430836,33.73786],"type":"Point"}
}