{
  "type": "Feature",
  "properties": {
    "addr:full":"4274 Gray Hwy Ste B Gray GA 31032",
    "addr:housenumber":"4274",
    "addr:postcode":"31032",
    "addr:street":"Gray Hwy Ste B",
    "iso:country":"US",
    "sg:address":"4274 Gray Hwy Ste B",
    "sg:city":"Gray",
    "sg:classifiers":[
        {
            "category":"Personal",
            "subcategory":"Beauty Salon",
            "type":"Services"
        }
    ],
    "sg:phone":"+1 478 986 0055",
    "sg:postcode":"31032",
    "sg:province":"GA",
    "sg:tags":[
        "hair",
        "stylist"
    ],
    "wof:name":"Snip'z Hair Studio",
    "wof:placetype":"venue"
},
  "geometry": {"coordinates":[-83.560044,32.995626],"type":"Point"}
}