{
  "type": "Feature",
  "properties": {
    "iso:country":"US",
    "sg:address":"4555 Best Rd",
    "sg:city":"College Park",
    "sg:classifiers":[
        {
            "category":"Wholesale",
            "subcategory":"Metals & Minerals",
            "type":"Manufacturing & Wholesale Goods"
        }
    ],
    "sg:phone":"+1 404 684 0400",
    "sg:postcode":"30337",
    "sg:province":"GA",
    "sg:tags":[
        "pipe"
    ],
    "wof:name":"Hughes Supply Inc",
    "wof:placetype":"venue"
},
  "geometry": {"coordinates":[-84.458005,33.639359],"type":"Point"}
}