{
  "type": "Feature",
  "properties": {
    "addr:full":"712 Mall Blvd Savannah GA 31406",
    "addr:housenumber":"712",
    "addr:postcode":"31406",
    "addr:street":"Mall Blvd",
    "iso:country":"US",
    "sg:address":"712 Mall Blvd",
    "sg:city":"Savannah",
    "sg:classifiers":[
        {
            "category":"Organizations",
            "subcategory":"Community Association",
            "type":"Services"
        }
    ],
    "sg:phone":"+1 912 352 8222",
    "sg:postcode":"31406",
    "sg:province":"GA",
    "sg:tags":[
        "club"
    ],
    "sg:website":"www.aaa.com",
    "wof:name":"AAA Auto Club South",
    "wof:placetype":"venue"
},
  "geometry": {"coordinates":[-81.10563500000001,32.000748],"type":"Point"}
}