{
  "type": "Feature",
  "properties": {
    "iso:country":"US",
    "sg:address":"5000 Cedar St",
    "sg:city":"Valdosta",
    "sg:classifiers":[
        {
            "category":"Government",
            "subcategory":"Fire Station",
            "type":"Public Place"
        }
    ],
    "sg:phone":"+1 229 559 7044",
    "sg:postcode":"31601",
    "sg:province":"GA",
    "sg:tags":[
        "department"
    ],
    "wof:name":"Lowndes County Fire Dept",
    "wof:placetype":"venue"
},
  "geometry": {"coordinates":[-83.31401099999999,30.697542],"type":"Point"}
}