{
  "type": "Feature",
  "properties": {
    "addr:full":"27 George Craven Rd Baxley GA 31513",
    "addr:housenumber":"27",
    "addr:postcode":"31513",
    "addr:street":"George Craven Rd",
    "iso:country":"US",
    "sg:address":"27 George Craven Rd",
    "sg:city":"Baxley",
    "sg:classifiers":[
        {
            "category":"Professional",
            "type":"Services"
        }
    ],
    "sg:phone":"+1 912 367 0839",
    "sg:postcode":"31513",
    "sg:province":"GA",
    "wof:name":"Pat H White",
    "wof:placetype":"venue"
},
  "geometry": {"coordinates":[-82.315166,31.836352],"type":"Point"}
}