{
  "type": "Feature",
  "properties": {
    "addr:full":"6300 Powers Ferry Rd NW Atlanta GA 30327",
    "addr:housenumber":"6300",
    "addr:postcode":"30327",
    "addr:street":"Powers Ferry Rd Nw",
    "iso:country":"US",
    "sg:address":"6300 Powers Ferry Rd NW",
    "sg:city":"Atlanta",
    "sg:classifiers":[
        {
            "category":"Professional",
            "subcategory":"Advertising",
            "type":"Services"
        }
    ],
    "sg:phone":"+1 770 952 5057",
    "sg:postcode":"30327",
    "sg:province":"GA",
    "sg:tags":[
        "mailing",
        "shipping"
    ],
    "wof:name":"UPS Store",
    "wof:placetype":"venue"
},
  "geometry": {"coordinates":[-84.429402,33.905739],"type":"Point"}
}