{
  "type": "Feature",
  "properties": {
    "addr:full":"2101 Flat Shoals Rd SW Conyers GA 30094",
    "addr:housenumber":"2101",
    "addr:postcode":"30094",
    "addr:street":"Flat Shoals Rd Sw",
    "iso:country":"US",
    "sg:address":"2101 Flat Shoals Rd SW",
    "sg:city":"Conyers",
    "sg:classifiers":[
        {
            "category":"Restaurant",
            "type":"Food & Drink"
        }
    ],
    "sg:phone":"+1 770 929 1905",
    "sg:postcode":"30094",
    "sg:province":"GA",
    "sg:tags":[
        "eating"
    ],
    "wof:name":"Hardees",
    "wof:placetype":"venue"
},
  "geometry": {"coordinates":[-84.056984,33.652532],"type":"Point"}
}