{
  "type": "Feature",
  "properties": {
    "iso:country":"US",
    "sg:address":"2170 Westpoint Rd",
    "sg:city":"Lagrange",
    "sg:classifiers":[
        {
            "category":"Manufacturing",
            "subcategory":"Apparel",
            "type":"Manufacturing & Wholesale Goods"
        }
    ],
    "sg:phone":"+1 706 884 4699",
    "sg:postcode":"30240",
    "sg:province":"GA",
    "sg:tags":[
        "sewing",
        "contractor"
    ],
    "wof:name":"Yong's Sewing",
    "wof:placetype":"venue"
},
  "geometry": {"coordinates":[-85.077405,33.024793],"type":"Point"}
}