{
  "type": "Feature",
  "properties": {
    "addr:full":"9870 Highway 92 Woodstock GA 30188",
    "addr:housenumber":"9870",
    "addr:postcode":"30188",
    "addr:street":"Highway 92",
    "iso:country":"US",
    "sg:address":"9870 Highway 92",
    "sg:city":"Woodstock",
    "sg:classifiers":[
        {
            "category":"Professional",
            "subcategory":"Management & Consulting",
            "type":"Services"
        }
    ],
    "sg:phone":"+1 770 926 1131",
    "sg:postcode":"30188",
    "sg:province":"GA",
    "sg:tags":[
        "consultant",
        "safety"
    ],
    "sg:website":"http://www.vitran.com",
    "wof:name":"Conger & Elsea Inc",
    "wof:placetype":"venue"
},
  "geometry": {"coordinates":[-84.521947,34.085914],"type":"Point"}
}