{
  "type": "Feature",
  "properties": {
    "iso:country":"US",
    "sg:address":"375 PHARR RD NE SUITE 104",
    "sg:city":"ATLANTA",
    "sg:classifiers":[
        {
            "category":"Personal",
            "subcategory":"Beauty Salon",
            "type":"Services"
        }
    ],
    "sg:phone":"+1 404 812 0032",
    "sg:postcode":"30305",
    "sg:province":"GA",
    "sg:website":"http://www.dianapagan.com",
    "wof:name":"Diana Pagan's Hair Designs",
    "wof:placetype":"venue"
},
  "geometry": {"coordinates":[-84.375531,33.837034],"type":"Point"}
}