{
  "type": "Feature",
  "properties": {
    "addr:full":"4979 Ogeechee Rd Sylvania GA 30467",
    "addr:housenumber":"4979",
    "addr:postcode":"30467",
    "addr:street":"Ogeechee Rd",
    "iso:country":"US",
    "sg:address":"4979 Ogeechee Rd",
    "sg:city":"Sylvania",
    "sg:classifiers":[
        {
            "category":"Retail",
            "subcategory":"Repair Shop",
            "type":"Services"
        }
    ],
    "sg:phone":"+1 912 863 4250",
    "sg:postcode":"30467",
    "sg:province":"GA",
    "sg:tags":[
        "upholsterer"
    ],
    "wof:name":"Mills Upholstery",
    "wof:placetype":"venue"
},
  "geometry": {"coordinates":[-81.747893,32.652934],"type":"Point"}
}