{
  "type": "Feature",
  "properties": {
    "iso:country":"US",
    "sg:address":"3750 Namasco Dr",
    "sg:city":"Suwanee",
    "sg:classifiers":[
        {
            "category":"Professional",
            "subcategory":"Advertising",
            "type":"Services"
        },
        {
            "category":"Manufacturing",
            "subcategory":"Signs",
            "type":"Manufacturing & Wholesale Goods"
        }
    ],
    "sg:phone":"+1 678 482 0490",
    "sg:postcode":"30024",
    "sg:province":"GA",
    "sg:tags":[
        "signs-erectors",
        "hanger",
        "specialty"
    ],
    "sg:website":"http://www.2candesign.com",
    "wof:name":"Toucan Super Graphics",
    "wof:placetype":"venue"
},
  "geometry": {"coordinates":[-84.08817500000001,34.035842],"type":"Point"}
}