{
  "type": "Feature",
  "properties": {
    "addr:full":"2962 Taramore Way Suwanee GA 30024",
    "addr:housenumber":"2962",
    "addr:postcode":"30024",
    "addr:street":"Taramore Way",
    "iso:country":"US",
    "sg:address":"2962 Taramore Way",
    "sg:city":"Suwanee",
    "sg:classifiers":[
        {
            "category":"Restaurant",
            "type":"Food & Drink"
        }
    ],
    "sg:phone":"+1 404 589 9800",
    "sg:postcode":"30024",
    "sg:province":"GA",
    "sg:tags":[
        "eating"
    ],
    "wof:name":"Amdg Restaurants Inc",
    "wof:placetype":"venue"
},
  "geometry": {"coordinates":[-84.079322,34.01251],"type":"Point"}
}