{
  "type": "Feature",
  "properties": {
    "iso:country":"US",
    "sg:address":"457 Lake Joy Rd",
    "sg:city":"Kathleen",
    "sg:classifiers":[
        {
            "category":"Professional",
            "type":"Services"
        }
    ],
    "sg:phone":"+1 478 987 5064",
    "sg:postcode":"31047",
    "sg:province":"GA",
    "wof:name":"Jimmy Womack Inc",
    "wof:placetype":"venue"
},
  "geometry": {"coordinates":[-83.691151,32.521343],"type":"Point"}
}