{
  "type": "Feature",
  "properties": {
    "iso:country":"US",
    "sg:address":"2112 Eisenhower St",
    "sg:city":"Cordele",
    "sg:classifiers":[
        {
            "category":"Retail",
            "subcategory":"Laundry & Dry Cleaning",
            "type":"Services"
        }
    ],
    "sg:phone":"+1 229 273 0573",
    "sg:postcode":"31015",
    "sg:province":"GA",
    "sg:tags":[
        "garment",
        "plant",
        "agent",
        "drycleaning"
    ],
    "wof:name":"Uptown Cleaners",
    "wof:placetype":"venue"
},
  "geometry": {"coordinates":[-83.801551,31.99281],"type":"Point"}
}