{
  "type": "Feature",
  "properties": {
    "iso:country":"US",
    "sg:address":"1030 Marietta Hwy",
    "sg:city":"Roswell",
    "sg:classifiers":[
        {
            "category":"Government",
            "subcategory":"Office",
            "type":"Public Place"
        }
    ],
    "sg:phone":"+1 770 640 3061",
    "sg:postcode":"30075",
    "sg:province":"GA",
    "sg:tags":[
        "parish",
        "government-county"
    ],
    "wof:name":"Fulton County Water & Sewer",
    "wof:placetype":"venue"
},
  "geometry": {"coordinates":[-84.39350899999999,34.003029],"type":"Point"}
}