{
  "type": "Feature",
  "properties": {
    "addr:full":"4227 Buford Dr Buford GA 30518",
    "addr:housenumber":"4227",
    "addr:postcode":"30518",
    "addr:street":"Buford Dr",
    "iso:country":"US",
    "sg:address":"4227 Buford Dr",
    "sg:city":"Buford",
    "sg:classifiers":[
        {
            "category":"Retail",
            "subcategory":"Car Wash",
            "type":"Services"
        }
    ],
    "sg:phone":"+1 770 932 6263",
    "sg:postcode":"30518",
    "sg:province":"GA",
    "sg:tags":[
        "polishing",
        "carwash",
        "washing"
    ],
    "wof:name":"Buford Express Lube & Wash",
    "wof:placetype":"venue"
},
  "geometry": {"coordinates":[-84.01153100000001,34.095095],"type":"Point"}
}