{
  "type": "Feature",
  "properties": {
    "iso:country":"US",
    "sg:address":"369 Faison Rd",
    "sg:city":"Hartsfield",
    "sg:classifiers":[
        {
            "category":"Farming",
            "subcategory":"Livestock Farm",
            "type":"Manufacturing & Wholesale Goods"
        }
    ],
    "sg:phone":"+1 229 941 5227",
    "sg:postcode":"31756",
    "sg:province":"GA",
    "sg:tags":[
        "beef",
        "feedlot",
        "cattle"
    ],
    "wof:name":"Richard Kleedehn",
    "wof:placetype":"venue"
},
  "geometry": {"coordinates":[-83.941007,31.201713],"type":"Point"}
}