{
  "type": "Feature",
  "properties": {
    "addr:full":"2107 E Broad Ave Albany GA 31705",
    "addr:housenumber":"2107",
    "addr:postcode":"31705",
    "addr:street":"E Broad Ave",
    "iso:country":"US",
    "sg:address":"2107 E Broad Ave",
    "sg:city":"Albany",
    "sg:classifiers":[
        {
            "category":"Personal",
            "subcategory":"Beauty Salon",
            "type":"Services"
        }
    ],
    "sg:phone":"+1 229 434 0267",
    "sg:postcode":"31705",
    "sg:province":"GA",
    "sg:tags":[
        "shop"
    ],
    "wof:name":"Hair Pazazz",
    "wof:placetype":"venue"
},
  "geometry": {"coordinates":[-84.097874,31.574916],"type":"Point"}
}