{
  "type": "Feature",
  "properties": {
    "addr:full":"2302 Southlake Mall Morrow GA 30260",
    "addr:housenumber":"2302",
    "addr:postcode":"30260",
    "addr:street":"Southlake Mall",
    "iso:country":"US",
    "sg:address":"2302 Southlake Mall",
    "sg:city":"Morrow",
    "sg:classifiers":[
        {
            "category":"Shopping",
            "subcategory":"Stationery & Office Supplies",
            "type":"Retail Goods"
        }
    ],
    "sg:phone":"+1 770 961 5555",
    "sg:postcode":"30260",
    "sg:province":"GA",
    "sg:tags":[
        "stationer"
    ],
    "wof:name":"Social Expressions",
    "wof:placetype":"venue"
},
  "geometry": {"coordinates":[-84.35362000000001,33.577262],"type":"Point"}
}