{
  "type": "Feature",
  "properties": {
    "iso:country":"US",
    "sg:address":"1896 Highway 20 SE",
    "sg:city":"Conyers",
    "sg:classifiers":[
        {
            "category":"Shopping",
            "subcategory":"Pawn Shop",
            "type":"Retail Goods"
        }
    ],
    "sg:phone":"+1 770 483 0088",
    "sg:postcode":"30013",
    "sg:province":"GA",
    "wof:name":"Title Max",
    "wof:placetype":"venue"
},
  "geometry": {"coordinates":[-84.014127,33.637147],"type":"Point"}
}