{
  "type": "Feature",
  "properties": {
    "addr:full":"7662 State Rte 18 Pine Mountain GA 31822",
    "addr:housenumber":"7662",
    "addr:postcode":"31822",
    "addr:street":"State Rte 18",
    "iso:country":"US",
    "sg:address":"7662 State Rte 18",
    "sg:city":"Pine Mountain",
    "sg:classifiers":[
        {
            "category":"Organizations",
            "subcategory":"Religious Organization",
            "type":"Services"
        }
    ],
    "sg:phone":"+1 770 964 0085",
    "sg:postcode":"31822",
    "sg:province":"GA",
    "sg:tags":[
        "church"
    ],
    "wof:name":"Union Baptist Church",
    "wof:placetype":"venue"
},
  "geometry": {"coordinates":[-84.999966,32.860831],"type":"Point"}
}