{
  "type": "Feature",
  "properties": {
    "iso:country":"US",
    "sg:address":"2645 N Berkeley Lake Rd NW",
    "sg:city":"Duluth",
    "sg:classifiers":[
        {
            "category":"Building & Trades",
            "subcategory":"Locksmith",
            "type":"Services"
        }
    ],
    "sg:phone":"+1 678 269 7237",
    "sg:postcode":"30096",
    "sg:province":"GA",
    "sg:tags":[
        "key"
    ],
    "wof:name":"7 Days Emergency Locksmith",
    "wof:placetype":"venue"
},
  "geometry": {"coordinates":[-84.15596600000001,33.9722],"type":"Point"}
}