{
  "type": "Feature",
  "properties": {
    "iso:country":"US",
    "sg:address":"722 N Westover Blvd",
    "sg:city":"Albany",
    "sg:classifiers":[
        {
            "category":"Restaurant",
            "type":"Food & Drink"
        }
    ],
    "sg:menulink":"http://www.allmenus.com/ga/west-dougherty/140692-waffle-house/menu/",
    "sg:phone":"+1 770 985 8074",
    "sg:postcode":"31707",
    "sg:province":"GA",
    "sg:tags":[
        "american"
    ],
    "wof:name":"Waffle House",
    "wof:placetype":"venue"
},
  "geometry": {"coordinates":[-84.21953600000001,31.590737],"type":"Point"}
}