{
  "type": "Feature",
  "properties": {
    "iso:country":"US",
    "sg:address":"365 Northridge Rd Ste 230",
    "sg:city":"Atlanta",
    "sg:classifiers":[
        {
            "category":"Banks & Credit Unions",
            "subcategory":"Financial Services",
            "type":"Services"
        }
    ],
    "sg:phone":"+1 770 481 0503",
    "sg:postcode":"30350",
    "sg:province":"GA",
    "sg:tags":[
        "broker",
        "mortgage"
    ],
    "wof:name":"Key Commercial Mortgage",
    "wof:placetype":"venue"
},
  "geometry": {"coordinates":[-84.34760300000001,33.981701],"type":"Point"}
}