{
  "type": "Feature",
  "properties": {
    "addr:full":"300 Village Green Cir SE Smyrna GA 30080",
    "addr:housenumber":"300",
    "addr:postcode":"30080",
    "addr:street":"Village Green Cir Se",
    "iso:country":"US",
    "sg:address":"300 Village Green Cir SE",
    "sg:city":"Smyrna",
    "sg:classifiers":[
        {
            "category":"Food & Beverages",
            "subcategory":"Groceries & Convenience Stores",
            "type":"Retail Goods"
        }
    ],
    "sg:phone":"+1 770 434 7334",
    "sg:postcode":"30080",
    "sg:province":"GA",
    "sg:tags":[
        "market"
    ],
    "wof:name":"Market Designs",
    "wof:placetype":"venue"
},
  "geometry": {"coordinates":[-84.51642699999999,33.88518],"type":"Point"}
}