{
  "type": "Feature",
  "properties": {
    "addr:full":"4869 Sandstone Ct Evans GA 30809",
    "addr:housenumber":"4869",
    "addr:postcode":"30809",
    "addr:street":"Sandstone Ct",
    "iso:country":"US",
    "sg:address":"4869 Sandstone Ct",
    "sg:city":"Evans",
    "sg:classifiers":[
        {
            "category":"Shopping",
            "subcategory":"Gifts & Souvenirs",
            "type":"Retail Goods"
        }
    ],
    "sg:phone":"+1 706 650 2953",
    "sg:postcode":"30809",
    "sg:province":"GA",
    "sg:tags":[
        "basket",
        "parcel"
    ],
    "wof:name":"Gift Baskets Etc",
    "wof:placetype":"venue"
},
  "geometry": {"coordinates":[-82.17938100000001,33.525982],"type":"Point"}
}