{
  "type": "Feature",
  "properties": {
    "addr:full":"209 Administration Building 201 Dowman Dr, Mailstop 1000-001-1AF Atlanta GA 30322",
    "addr:housenumber":"209;201;1000-001-1af",
    "addr:postcode":"30322",
    "addr:street":"Dowman Dr Mailstop",
    "iso:country":"US",
    "sg:address":"209 Administration Building 201 Dowman Dr, Mailstop 1000-001-1AF",
    "sg:city":"Atlanta",
    "sg:classifiers":[
        {
            "category":"Education",
            "subcategory":"University",
            "type":"Public Place"
        }
    ],
    "sg:phone":"+1 404 727 6999",
    "sg:postcode":"30322",
    "sg:province":"GA",
    "sg:tags":[
        "college"
    ],
    "sg:website":"www.emory.edu/home/index.html",
    "wof:name":"Emory Laney Graduate School",
    "wof:placetype":"venue"
},
  "geometry": {"coordinates":[-84.321416,33.7945],"type":"Point"}
}