{
  "type": "Feature",
  "properties": {
    "addr:full":"567 Valley Hill Rd SW Riverdale GA 30274",
    "addr:housenumber":"567",
    "addr:postcode":"30274",
    "addr:street":"Valley Hill Rd Sw",
    "iso:country":"US",
    "sg:address":"567 Valley Hill Rd SW",
    "sg:city":"Riverdale",
    "sg:classifiers":[
        {
            "category":"Banks & Credit Unions",
            "subcategory":"Bank",
            "type":"Services"
        }
    ],
    "sg:phone":"+1 770 991 5370",
    "sg:postcode":"30274",
    "sg:province":"GA",
    "sg:tags":[
        "national",
        "commercial"
    ],
    "wof:name":"Bank of America",
    "wof:placetype":"venue"
},
  "geometry": {"coordinates":[-84.40915,33.572394],"type":"Point"}
}