{
  "type": "Feature",
  "properties": {
    "iso:country":"US",
    "sg:address":"1332 Holcomb Avenue",
    "sg:city":"Atlanta",
    "sg:classifiers":[
        {
            "category":"Place Of Worship",
            "subcategory":"Church",
            "type":"Public Place"
        },
        {
            "category":"Place Of Worship",
            "type":"Public Place"
        },
        {
            "category":"Organizations",
            "subcategory":"Religious Organization",
            "type":"Services"
        }
    ],
    "sg:phone":"+1 404 762 9175",
    "sg:postcode":"30344",
    "sg:province":"GA",
    "sg:tags":[
        "churches-baptist-general",
        "churches-baptist"
    ],
    "wof:name":"Siloam International Church",
    "wof:placetype":"venue"
},
  "geometry": {"coordinates":[-84.43207200000001,33.674022],"type":"Point"}
}