{
  "type": "Feature",
  "properties": {
    "iso:country":"US",
    "sg:address":"132 Aztec Way SE",
    "sg:city":"Acworth",
    "sg:classifiers":[
        {
            "category":"Building & Trades",
            "subcategory":"Cleaning & Sanitation",
            "type":"Services"
        }
    ],
    "sg:phone":"+1 770 974 7918",
    "sg:postcode":"30102",
    "sg:province":"GA",
    "sg:tags":[
        "home"
    ],
    "wof:name":"Cleaning Pro's Inc the",
    "wof:placetype":"venue"
},
  "geometry": {"coordinates":[-84.675697,34.087799],"type":"Point"}
}