{
  "type": "Feature",
  "properties": {
    "addr:full":"745 S Lee St Valdosta GA 31601",
    "addr:housenumber":"745",
    "addr:postcode":"31601",
    "addr:street":"S Lee St",
    "iso:country":"US",
    "sg:address":"745 S Lee St",
    "sg:city":"Valdosta",
    "sg:classifiers":[
        {
            "category":"Organizations",
            "subcategory":"Religious Organization",
            "type":"Services"
        }
    ],
    "sg:phone":"+1 229 249 0988",
    "sg:postcode":"31601",
    "sg:province":"GA",
    "sg:tags":[
        "church"
    ],
    "wof:name":"House Bread Church Ministry",
    "wof:placetype":"venue"
},
  "geometry": {"coordinates":[-83.27143,30.822787],"type":"Point"}
}