{
  "type": "Feature",
  "properties": {
    "addr:full":"106 Colony Park Dr Cumming GA 30040",
    "addr:housenumber":"106",
    "addr:postcode":"30040",
    "addr:street":"Colony Park Dr",
    "iso:country":"US",
    "sg:address":"106 Colony Park Dr",
    "sg:city":"Cumming",
    "sg:classifiers":[
        {
            "category":"Local Transit",
            "type":"Transportation"
        }
    ],
    "sg:phone":"+1 770 720 4444",
    "sg:postcode":"30040",
    "sg:province":"GA",
    "sg:tags":[
        "ambulance"
    ],
    "wof:name":"Advanced Ambulance Svc",
    "wof:placetype":"venue"
},
  "geometry": {"coordinates":[-84.13430200000001,34.193855],"type":"Point"}
}