{
  "type": "Feature",
  "properties": {
    "addr:full":"4646 Forsyth Rd Macon GA 31210",
    "addr:housenumber":"4646",
    "addr:postcode":"31210",
    "addr:street":"Forsyth Rd",
    "iso:country":"US",
    "sg:address":"4646 Forsyth Rd",
    "sg:city":"Macon",
    "sg:classifiers":[
        {
            "category":"Arena",
            "subcategory":"Sports Club",
            "type":"Entertainment"
        }
    ],
    "sg:phone":"+1 478 254 2274",
    "sg:postcode":"31210",
    "sg:province":"GA",
    "sg:tags":[
        "health"
    ],
    "wof:name":"North Macon Crossfit",
    "wof:placetype":"venue"
},
  "geometry": {"coordinates":[-83.708713,32.873945],"type":"Point"}
}