{
  "type": "Feature",
  "properties": {
    "addr:full":"155 Forrest Park Dr Chickamauga GA 30707",
    "addr:housenumber":"155",
    "addr:postcode":"30707",
    "addr:street":"Forrest Park Dr Chickamauga",
    "iso:country":"US",
    "sg:address":"155 Forrest Park Dr",
    "sg:city":"Chickamauga",
    "sg:classifiers":[
        {
            "category":"Organizations",
            "subcategory":"Religious Organization",
            "type":"Services"
        }
    ],
    "sg:phone":"+1 706 375 4751",
    "sg:postcode":"30707",
    "sg:province":"GA",
    "sg:tags":[
        "clergy"
    ],
    "wof:name":"Blackstock Billy Rev",
    "wof:placetype":"venue"
},
  "geometry": {"coordinates":[-85.281848,34.893813],"type":"Point"}
}