{
  "type": "Feature",
  "properties": {
    "addr:full":"436 Broad St Rome GA 30161",
    "addr:housenumber":"436",
    "addr:postcode":"ga 30161",
    "addr:street":"Broad St",
    "iso:country":"US",
    "sg:address":"436 Broad St",
    "sg:city":"Rome",
    "sg:classifiers":[
        {
            "category":"Restaurant",
            "type":"Food & Drink"
        }
    ],
    "sg:phone":"+1 706 291 4321",
    "sg:postcode":"30161",
    "sg:province":"GA",
    "sg:tags":[
        "banquet",
        "rooms"
    ],
    "wof:name":"Forrest Place",
    "wof:placetype":"venue"
},
  "geometry": {"coordinates":[-85.170664,34.255118],"type":"Point"}
}