{
  "type": "Feature",
  "properties": {
    "addr:full":"4203 Herme Pl Valdosta GA 31605",
    "addr:housenumber":"4203",
    "addr:postcode":"31605",
    "addr:street":"Herme Pl",
    "iso:country":"US",
    "sg:address":"4203 Herme Pl",
    "sg:city":"Valdosta",
    "sg:classifiers":[
        {
            "category":"Real Estate",
            "subcategory":"Real Estate Operator",
            "type":"Services"
        }
    ],
    "sg:phone":"+1 229 247 4566",
    "sg:postcode":"31605",
    "sg:province":"GA",
    "sg:tags":[
        "apartment"
    ],
    "wof:name":"Birchwood Apartments",
    "wof:placetype":"venue"
},
  "geometry": {"coordinates":[-83.278797,30.892643],"type":"Point"}
}