{
  "type": "Feature",
  "properties": {
    "addr:full":"115 Stanfield Rd Screven GA 31560",
    "addr:housenumber":"115",
    "addr:postcode":"31560",
    "addr:street":"Stanfield Rd",
    "iso:country":"US",
    "sg:address":"115 Stanfield Rd",
    "sg:city":"Screven",
    "sg:classifiers":[
        {
            "category":"Wholesale",
            "subcategory":"Meat",
            "type":"Manufacturing & Wholesale Goods"
        }
    ],
    "sg:phone":"+1 912 579 6731",
    "sg:postcode":"31560",
    "sg:province":"GA",
    "sg:tags":[
        "slaughterhouse"
    ],
    "wof:name":"A & D Slaughterhouse Inc",
    "wof:placetype":"venue"
},
  "geometry": {"coordinates":[-82.043403,31.505102],"type":"Point"}
}