{
  "type": "Feature",
  "properties": {
    "addr:full":"4271 Lawrenceville Hwy Tucker GA 30084",
    "addr:housenumber":"4271",
    "addr:postcode":"30084",
    "addr:street":"Lawrenceville Hwy",
    "iso:country":"US",
    "sg:address":"4271 Lawrenceville Hwy",
    "sg:city":"Tucker",
    "sg:classifiers":[
        {
            "category":"Banks & Credit Unions",
            "subcategory":"Bank",
            "type":"Services"
        }
    ],
    "sg:phone":"+1 770 270 1512",
    "sg:postcode":"30084",
    "sg:province":"GA",
    "wof:name":"Washington Mutual",
    "wof:placetype":"venue"
},
  "geometry": {"coordinates":[-84.209548,33.854259],"type":"Point"}
}