{
  "type": "Feature",
  "properties": {
    "addr:full":"2734 Roanoke Rd Lagrange GA 30240",
    "addr:housenumber":"2734",
    "addr:postcode":"30240",
    "addr:street":"Roanoke Rd",
    "iso:country":"US",
    "sg:address":"2734 Roanoke Rd",
    "sg:city":"Lagrange",
    "sg:classifiers":[
        {
            "category":"Building & Trades",
            "subcategory":"Construction",
            "type":"Services"
        }
    ],
    "sg:phone":"+1 706 845 1014",
    "sg:postcode":"30240",
    "sg:province":"GA",
    "sg:tags":[
        "general",
        "contractor"
    ],
    "wof:name":"Whitewater Construction",
    "wof:placetype":"venue"
},
  "geometry": {"coordinates":[-85.09591899999999,33.033794],"type":"Point"}
}