{
  "type": "Feature",
  "properties": {
    "addr:full":"3006 Oak Hampton Ct NW Duluth GA 30096",
    "addr:housenumber":"3006",
    "addr:postcode":"30096",
    "addr:street":"Oak Hampton Ct Nw",
    "iso:country":"US",
    "sg:address":"3006 Oak Hampton Ct NW",
    "sg:city":"Duluth",
    "sg:classifiers":[
        {
            "category":"Professional",
            "subcategory":"Business Services",
            "type":"Services"
        }
    ],
    "sg:phone":"+1 770 495 6412",
    "sg:postcode":"30096",
    "sg:province":"GA",
    "wof:name":"American Express",
    "wof:placetype":"venue"
},
  "geometry": {"coordinates":[-84.12409599999999,33.974376],"type":"Point"}
}