{
  "type": "Feature",
  "properties": {
    "addr:full":"1262 Summerstone Trce Austell GA 30168",
    "addr:housenumber":"1262",
    "addr:postcode":"30168",
    "addr:street":"Summerstone Trce",
    "iso:country":"US",
    "sg:address":"1262 Summerstone Trce",
    "sg:city":"Austell",
    "sg:classifiers":[
        {
            "category":"Building & Trades",
            "subcategory":"Landscaping Services",
            "type":"Services"
        }
    ],
    "sg:phone":"+1 770 745 9025",
    "sg:postcode":"30168",
    "sg:province":"GA",
    "wof:name":"Cut Buddies",
    "wof:placetype":"venue"
},
  "geometry": {"coordinates":[-84.591759,33.777627],"type":"Point"}
}