{
  "type": "Feature",
  "properties": {
    "addr:full":"111 Brentwood Ln Woodstock GA 30188",
    "addr:housenumber":"111",
    "addr:postcode":"30188",
    "addr:street":"Brentwood Ln",
    "iso:country":"US",
    "sg:address":"111 Brentwood Ln",
    "sg:city":"Woodstock",
    "sg:classifiers":[
        {
            "category":"Organizations",
            "subcategory":"Community Association",
            "type":"Services"
        }
    ],
    "sg:phone":"+1 770 926 3661",
    "sg:postcode":"30188",
    "sg:province":"GA",
    "wof:name":"Brentwood Homeowners Assn",
    "wof:placetype":"venue"
},
  "geometry": {"coordinates":[-84.49356400000001,34.091755],"type":"Point"}
}