{
  "type": "Feature",
  "properties": {
    "iso:country":"US",
    "sg:address":"104 N 3rd Ave",
    "sg:city":"Chatsworth",
    "sg:classifiers":[
        {
            "category":"Professional",
            "subcategory":"Lawyer & Legal Services",
            "type":"Services"
        }
    ],
    "sg:phone":"+1 706 517 0196",
    "sg:postcode":"30705",
    "sg:province":"GA",
    "sg:tags":[
        "information",
        "attorney",
        "practice",
        "referral"
    ],
    "wof:name":"Richard L Yancey",
    "wof:placetype":"venue"
},
  "geometry": {"coordinates":[-84.76957,34.766136],"type":"Point"}
}