{
  "type": "Feature",
  "properties": {
    "iso:country":"US",
    "sg:address":"1201 Dean Ave",
    "sg:city":"Rome",
    "sg:classifiers":[
        {
            "category":"Shopping",
            "type":"Retail Goods"
        }
    ],
    "sg:phone":"+1 706 232 9500",
    "sg:postcode":"30161",
    "sg:province":"GA",
    "sg:tags":[
        "pet",
        "food",
        "supply"
    ],
    "wof:name":"Bone Bag",
    "wof:placetype":"venue"
},
  "geometry": {"coordinates":[-85.159621,34.236582],"type":"Point"}
}