{
  "type": "Feature",
  "properties": {
    "iso:country":"US",
    "sg:address":"3679 Stewart Rd",
    "sg:city":"Atlanta",
    "sg:classifiers":[
        {
            "category":"Retail",
            "subcategory":"Portrait Studio",
            "type":"Services"
        }
    ],
    "sg:phone":"+1 770 457 3480",
    "sg:postcode":"30340",
    "sg:province":"GA",
    "sg:tags":[
        "photography",
        "train",
        "photographic",
        "model",
        "supply"
    ],
    "wof:name":"J & FM Enterprises",
    "wof:placetype":"venue"
},
  "geometry": {"coordinates":[-84.27422900000001,33.898821],"type":"Point"}
}