{
  "type": "Feature",
  "properties": {
    "iso:country":"US",
    "sg:address":"4290 Bells Ferry Rd NW",
    "sg:city":"Kennesaw",
    "sg:classifiers":[
        {
            "category":"Retail",
            "subcategory":"Laundry & Dry Cleaning",
            "type":"Services"
        }
    ],
    "sg:phone":"+1 770 579 8654",
    "sg:postcode":"30144",
    "sg:province":"GA",
    "sg:tags":[
        "repairing",
        "rug",
        "carpet"
    ],
    "wof:name":"Water Damage Inc",
    "wof:placetype":"venue"
},
  "geometry": {"coordinates":[-84.556185,34.052431],"type":"Point"}
}