{
  "type": "Feature",
  "properties": {
    "addr:full":"75 N Main St Jasper GA 30143",
    "addr:housenumber":"75",
    "addr:postcode":"30143",
    "addr:street":"N Main St",
    "iso:country":"US",
    "sg:address":"75 N Main St",
    "sg:city":"Jasper",
    "sg:classifiers":[
        {
            "category":"Home & Garden",
            "subcategory":"Furniture",
            "type":"Retail Goods"
        }
    ],
    "sg:phone":"+1 706 692 2031",
    "sg:postcode":"30143",
    "sg:province":"GA",
    "wof:name":"Moore Furniture Co Inc",
    "wof:placetype":"venue"
},
  "geometry": {"coordinates":[-84.43057,34.469046],"type":"Point"}
}