{
  "type": "Feature",
  "properties": {
    "iso:country":"US",
    "sg:address":"613 Chattahoochee St",
    "sg:city":"La Grange",
    "sg:classifiers":[
        {
            "category":"Professional",
            "type":"Services"
        }
    ],
    "sg:phone":"+1 706 845 8641",
    "sg:postcode":"30241",
    "sg:province":"GA",
    "wof:name":"Loraine Boone",
    "wof:placetype":"venue"
},
  "geometry": {"coordinates":[-85.018531,33.042969],"type":"Point"}
}