{
  "type": "Feature",
  "properties": {
    "iso:country":"US",
    "sg:address":"1355 Sam Nunn Blvd",
    "sg:city":"Perry",
    "sg:classifiers":[
        {
            "category":"Retail",
            "subcategory":"Portrait Studio",
            "type":"Services"
        }
    ],
    "sg:phone":"+1 478 988 0111",
    "sg:postcode":"31069",
    "sg:province":"GA",
    "wof:name":"Olan Mills Inc",
    "wof:placetype":"venue"
},
  "geometry": {"coordinates":[-83.739,32.466516],"type":"Point"}
}