{
  "type": "Feature",
  "properties": {
    "iso:country":"US",
    "sg:address":"110 7th St N",
    "sg:city":"Cordele",
    "sg:classifiers":[
        {
            "category":"Manufacturing",
            "subcategory":"Printing",
            "type":"Manufacturing & Wholesale Goods"
        }
    ],
    "sg:phone":"+1 229 273 4136",
    "sg:postcode":"31015",
    "sg:province":"GA",
    "sg:tags":[
        "printer"
    ],
    "wof:name":"Murray Printing Co Inc",
    "wof:placetype":"venue"
},
  "geometry": {"coordinates":[-83.78266000000001,31.969092],"type":"Point"}
}