{
  "type": "Feature",
  "properties": {
    "iso:country":"US",
    "sg:address":"29 W Ridge Dr SE",
    "sg:city":"Cartersville",
    "sg:classifiers":[
        {
            "category":"Manufacturing",
            "subcategory":"Metals",
            "type":"Manufacturing & Wholesale Goods"
        }
    ],
    "sg:phone":"+1 770 386 2513",
    "sg:postcode":"30121",
    "sg:province":"GA",
    "sg:tags":[
        "engraver"
    ],
    "wof:name":"Gifts Remembered",
    "wof:placetype":"venue"
},
  "geometry": {"coordinates":[-84.747829,34.201603],"type":"Point"}
}