{
  "type": "Feature",
  "properties": {
    "addr:full":"4085 Kilarney Cir Valdosta GA 31602",
    "addr:housenumber":"4085",
    "addr:postcode":"31602",
    "addr:street":"Kilarney Cir",
    "iso:country":"US",
    "sg:address":"4085 Kilarney Cir",
    "sg:city":"Valdosta",
    "sg:classifiers":[
        {
            "category":"Education",
            "subcategory":"Vocational School",
            "type":"Public Place"
        }
    ],
    "sg:phone":"+1 229 253 9082",
    "sg:postcode":"31602",
    "sg:province":"GA",
    "wof:name":"Kent Medical & Safety",
    "wof:placetype":"venue"
},
  "geometry": {"coordinates":[-83.339769,30.907078],"type":"Point"}
}