{
  "type": "Feature",
  "properties": {
    "addr:full":"4575 Bedgood Ave Arabi GA 31712",
    "addr:housenumber":"4575",
    "addr:postcode":"31712",
    "addr:street":"Bedgood Ave",
    "iso:country":"US",
    "sg:address":"4575 Bedgood Ave",
    "sg:city":"Arabi",
    "sg:classifiers":[
        {
            "category":"Restaurant",
            "type":"Food & Drink"
        }
    ],
    "sg:phone":"+1 229 271 9166",
    "sg:postcode":"31712",
    "sg:province":"GA",
    "wof:name":"B J's Diner",
    "wof:placetype":"venue"
},
  "geometry": {"coordinates":[-83.72983600000001,31.819775],"type":"Point"}
}