{
  "type": "Feature",
  "properties": {
    "addr:full":"24 Rose Hill Dr Savannah GA 31419",
    "addr:housenumber":"24",
    "addr:postcode":"31419",
    "addr:street":"Rose Hill Dr",
    "iso:country":"US",
    "sg:address":"24 Rose Hill Dr",
    "sg:city":"Savannah",
    "sg:classifiers":[
        {
            "category":"Building & Trades",
            "subcategory":"Cleaning & Sanitation",
            "type":"Services"
        }
    ],
    "sg:phone":"+1 912 961 9614",
    "sg:postcode":"31419",
    "sg:province":"GA",
    "sg:tags":[
        "janitor",
        "maintenance"
    ],
    "wof:name":"Sterling Cleaning Service Inc",
    "wof:placetype":"venue"
},
  "geometry": {"coordinates":[-81.1468,31.947014],"type":"Point"}
}