{
  "type": "Feature",
  "properties": {
    "iso:country":"US",
    "sg:address":"4221 Quail Ridge Way",
    "sg:city":"Norcross",
    "sg:classifiers":[
        {
            "category":"Shopping",
            "subcategory":"Clothing, Apparel, & Fashions",
            "type":"Retail Goods"
        }
    ],
    "sg:phone":"+1 770 447 6267",
    "sg:postcode":"30092",
    "sg:province":"GA",
    "wof:name":"Israel Inc",
    "wof:placetype":"venue"
},
  "geometry": {"coordinates":[-84.249075,33.978596],"type":"Point"}
}