{
  "type": "Feature",
  "properties": {
    "addr:full":"1830 Norman Dr Valdosta GA 31601",
    "addr:housenumber":"1830",
    "addr:postcode":"31601",
    "addr:street":"Norman Dr",
    "iso:country":"US",
    "sg:address":"1830 Norman Dr",
    "sg:city":"Valdosta",
    "sg:classifiers":[
        {
            "category":"Shopping",
            "subcategory":"Clothing, Apparel, & Fashions",
            "type":"Retail Goods"
        }
    ],
    "sg:phone":"+1 229 247 2494",
    "sg:postcode":"31601",
    "sg:province":"GA",
    "sg:tags":[
        "apparel",
        "handbag",
        "accessory",
        "sportswear",
        "women's"
    ],
    "sg:website":"http://www.talbots.com",
    "wof:name":"Talbots",
    "wof:placetype":"venue"
},
  "geometry": {"coordinates":[-83.317879,30.844633],"type":"Point"}
}