{
  "type": "Feature",
  "properties": {
    "addr:full":"840 S Peachtree St Norcross GA 30071",
    "addr:housenumber":"840",
    "addr:postcode":"30071",
    "addr:street":"S Peachtree St",
    "iso:country":"US",
    "sg:address":"840 S Peachtree St",
    "sg:city":"Norcross",
    "sg:classifiers":[
        {
            "category":"Organizations",
            "subcategory":"Religious Organization",
            "type":"Services"
        }
    ],
    "sg:phone":"+1 678 969 0064",
    "sg:postcode":"30071",
    "sg:province":"GA",
    "wof:name":"Ambassadores For Christ",
    "wof:placetype":"venue"
},
  "geometry": {"coordinates":[-84.221789,33.934715],"type":"Point"}
}