{
  "type": "Feature",
  "properties": {
    "iso:country":"US",
    "sg:address":"1001 Alpharetta Hwy",
    "sg:city":"Roswell",
    "sg:classifiers":[
        {
            "category":"Manufacturing",
            "subcategory":"Paper Products",
            "type":"Manufacturing & Wholesale Goods"
        }
    ],
    "sg:phone":"+1 770 645 7905",
    "sg:postcode":"30075",
    "sg:province":"GA",
    "sg:tags":[
        "packaging",
        "material"
    ],
    "wof:name":"Tamanet USA",
    "wof:placetype":"venue"
},
  "geometry": {"coordinates":[-84.360237,34.025471],"type":"Point"}
}