{
  "type": "Feature",
  "properties": {
    "addr:full":"5505 Peachtree Dunwoody Rd NE Atlanta GA 30342",
    "addr:housenumber":"5505",
    "addr:postcode":"30342",
    "addr:street":"Peachtree Dunwoody Rd Ne",
    "iso:country":"US",
    "sg:address":"5505 Peachtree Dunwoody Rd NE",
    "sg:city":"Atlanta",
    "sg:classifiers":[
        {
            "category":"Health Services",
            "subcategory":"Hospital",
            "type":"Services"
        }
    ],
    "sg:phone":"+1 404 389 0618",
    "sg:postcode":"30342",
    "sg:province":"GA",
    "sg:tags":[
        "surgery"
    ],
    "wof:name":"Ocuplastic Inc",
    "wof:placetype":"venue"
},
  "geometry": {"coordinates":[-84.352721,33.903329],"type":"Point"}
}