{
  "type": "Feature",
  "properties": {
    "iso:country":"US",
    "sg:address":"2065 Peachtree Industrial Ct",
    "sg:city":"Atlanta",
    "sg:classifiers":[
        {
            "category":"Manufacturing",
            "subcategory":"Pottery",
            "type":"Manufacturing & Wholesale Goods"
        }
    ],
    "sg:phone":"+1 770 452 1155",
    "sg:postcode":"30341",
    "sg:province":"GA",
    "sg:website":"http://www.bctradingcorp.com",
    "wof:name":"Cresc Corp",
    "wof:placetype":"venue"
},
  "geometry": {"coordinates":[-84.298715,33.899603],"type":"Point"}
}