{
  "type": "Feature",
  "properties": {
    "iso:country":"US",
    "sg:address":"1496 Church St",
    "sg:city":"Decatur",
    "sg:classifiers":[
        {
            "category":"Shopping",
            "subcategory":"Clothing, Apparel, & Fashions",
            "type":"Retail Goods"
        }
    ],
    "sg:phone":"+1 404 370 0993",
    "sg:postcode":"30030",
    "sg:province":"GA",
    "sg:tags":[
        "uniform",
        "shoes",
        "accessory"
    ],
    "wof:name":"A Uniform & Shoe World",
    "wof:placetype":"venue"
},
  "geometry": {"coordinates":[-84.28726399999999,33.789769],"type":"Point"}
}