{
  "type": "Feature",
  "properties": {
    "addr:full":"2545 Bexford Vw Cumming GA 30041",
    "addr:housenumber":"2545",
    "addr:postcode":"30041",
    "addr:street":"Bexford Vw",
    "iso:country":"US",
    "sg:address":"2545 Bexford Vw",
    "sg:city":"Cumming",
    "sg:classifiers":[
        {
            "category":"Wholesale",
            "subcategory":"Durable Goods & Equipment",
            "type":"Manufacturing & Wholesale Goods"
        }
    ],
    "sg:phone":"+1 770 887 2826",
    "sg:postcode":"30041",
    "sg:province":"GA",
    "sg:tags":[
        "representative",
        "manufacturer"
    ],
    "wof:name":"W C Sessions & Associates Inc",
    "wof:placetype":"venue"
},
  "geometry": {"coordinates":[-84.155806,34.131983],"type":"Point"}
}