{
  "type": "Feature",
  "properties": {
    "addr:full":"132 Longstreet Cir Oxford GA 30054",
    "addr:housenumber":"132",
    "addr:postcode":"30054",
    "addr:street":"Longstreet Cir",
    "iso:country":"US",
    "sg:address":"132 Longstreet Cir",
    "sg:city":"Oxford",
    "sg:classifiers":[
        {
            "category":"Retail",
            "subcategory":"Repair Shop",
            "type":"Services"
        }
    ],
    "sg:phone":"+1 770 787 8871",
    "sg:postcode":"30054",
    "sg:province":"GA",
    "wof:name":"Gloria Cleaning",
    "wof:placetype":"venue"
},
  "geometry": {"coordinates":[-83.879521,33.619036],"type":"Point"}
}