{
  "type": "Feature",
  "properties": {
    "addr:full":"3894 Old Portal Rd Portal GA 30450",
    "addr:housenumber":"3894",
    "addr:postcode":"30450",
    "addr:street":"Old Portal Rd",
    "iso:country":"US",
    "sg:address":"3894 Old Portal Rd",
    "sg:city":"Portal",
    "sg:phone":"+1 912 865 2939",
    "sg:postcode":"30450",
    "sg:province":"GA",
    "sg:tags":[
        "farm",
        "field",
        "crop",
        "soybean",
        "cotton"
    ],
    "wof:name":"Charles Finch",
    "wof:placetype":"venue"
},
  "geometry": {"coordinates":[-81.945837,32.611823],"type":"Point"}
}