{
  "type": "Feature",
  "properties": {
    "addr:full":"95 Cummings Dr Ringgold GA 30736",
    "addr:housenumber":"95",
    "addr:postcode":"30736",
    "addr:street":"Cummings Dr",
    "iso:country":"US",
    "sg:address":"95 Cummings Dr",
    "sg:city":"Ringgold",
    "sg:classifiers":[
        {
            "category":"Home & Garden",
            "subcategory":"Carpets & Floor Coverings",
            "type":"Retail Goods"
        }
    ],
    "sg:phone":"+1 706 279 1772",
    "sg:postcode":"30736",
    "sg:province":"GA",
    "sg:tags":[
        "dealer",
        "rug"
    ],
    "wof:name":"Red's Carpet & Appliances",
    "wof:placetype":"venue"
},
  "geometry": {"coordinates":[-85.148143,34.904753],"type":"Point"}
}