{
  "type": "Feature",
  "properties": {
    "iso:country":"US",
    "sg:address":"1132 Brinson Rd",
    "sg:city":"Brooklet",
    "sg:classifiers":[
        {
            "category":"Building & Trades",
            "subcategory":"Landscaping Services",
            "type":"Services"
        }
    ],
    "sg:phone":"+1 912 842 5520",
    "sg:postcode":"30415",
    "sg:province":"GA",
    "sg:tags":[
        "tree"
    ],
    "wof:name":"Walker's Total Tree Svc",
    "wof:placetype":"venue"
},
  "geometry": {"coordinates":[-81.666763,32.321447],"type":"Point"}
}