{
  "type": "Feature",
  "properties": {
    "iso:country":"US",
    "sg:address":"1118 County Line Rd",
    "sg:city":"Cumming",
    "sg:classifiers":[
        {
            "category":"Retail",
            "subcategory":"Car Wash",
            "type":"Services"
        }
    ],
    "sg:phone":"+1 770 888 7162",
    "sg:postcode":"30040",
    "sg:province":"GA",
    "sg:tags":[
        "carwash"
    ],
    "wof:name":"Gilberts Pressure Washing",
    "wof:placetype":"venue"
},
  "geometry": {"coordinates":[-84.260064,34.231356],"type":"Point"}
}