{
  "type": "Feature",
  "properties": {
    "addr:full":"108 Arnold Mill Rd Bldg C Woodstock GA 30188",
    "addr:housenumber":"108",
    "addr:postcode":"30188",
    "addr:street":"Arnold Mill Rd Bldg C",
    "iso:country":"US",
    "sg:address":"108 Arnold Mill Rd Bldg C",
    "sg:city":"Woodstock",
    "sg:classifiers":[
        {
            "category":"Community Center",
            "subcategory":"Senior",
            "type":"Public Place"
        },
        {
            "category":"Social Services",
            "subcategory":"Adult Care",
            "type":"Services"
        },
        {
            "category":"Community Center",
            "type":"Public Place"
        }
    ],
    "sg:phone":"+1 678 445 6518",
    "sg:postcode":"30188",
    "sg:province":"GA",
    "sg:tags":[
        "counseling",
        "recreation",
        "citizen"
    ],
    "wof:name":"William G Long Sr Ctzn Ctr",
    "wof:placetype":"venue"
},
  "geometry": {"coordinates":[-84.515129,34.1012],"type":"Point"}
}