{
  "type": "Feature",
  "properties": {
    "iso:country":"US",
    "sg:address":"4018 N Valdosta Rd",
    "sg:city":"Valdosta",
    "sg:classifiers":[
        {
            "category":"Wholesale",
            "subcategory":"Vending Machines",
            "type":"Manufacturing & Wholesale Goods"
        }
    ],
    "sg:phone":"+1 229 242 6517",
    "sg:postcode":"31602",
    "sg:province":"GA",
    "sg:tags":[
        "operator"
    ],
    "wof:name":"Variety Vending Co",
    "wof:placetype":"venue"
},
  "geometry": {"coordinates":[-83.325299,30.897607],"type":"Point"}
}