{
  "type": "Feature",
  "properties": {
    "addr:full":"278 Levi's Rd Moultrie GA 31788",
    "addr:housenumber":"278",
    "addr:postcode":"31788",
    "addr:street":"Levi'S Rd",
    "iso:country":"US",
    "sg:address":"278 Levi's Rd",
    "sg:city":"Moultrie",
    "sg:classifiers":[
        {
            "category":"Farming",
            "subcategory":"Livestock Farm",
            "type":"Manufacturing & Wholesale Goods"
        },
        {
            "category":"Farming",
            "subcategory":"Farm",
            "type":"Manufacturing & Wholesale Goods"
        }
    ],
    "sg:phone":"+1 229 891 2251",
    "sg:postcode":"31788",
    "sg:province":"GA",
    "sg:tags":[
        "hog",
        "or",
        "feedlot"
    ],
    "wof:name":"Wynn's Swine Farm",
    "wof:placetype":"venue"
},
  "geometry": {"coordinates":[-83.731026,31.121576],"type":"Point"}
}