{
  "type": "Feature",
  "properties": {
    "iso:country":"US",
    "sg:address":"3334 Mill River Cove",
    "sg:city":"Buford",
    "sg:classifiers":[
        {
            "category":"Building & Trades",
            "subcategory":"Construction",
            "type":"Services"
        }
    ],
    "sg:phone":"+1 678 546 2991",
    "sg:postcode":"30519",
    "sg:province":"GA",
    "sg:tags":[
        "contractor"
    ],
    "wof:name":"Bryn Way Premier Homes Inc",
    "wof:placetype":"venue"
},
  "geometry": {"coordinates":[-83.925467,34.077421],"type":"Point"}
}