{
  "type": "Feature",
  "properties": {
    "addr:full":"4903 Twin Branches Way Atlanta GA 30338",
    "addr:housenumber":"4903",
    "addr:postcode":"30338",
    "addr:street":"Twin Branches Way",
    "iso:country":"US",
    "sg:address":"4903 Twin Branches Way",
    "sg:city":"Atlanta",
    "sg:classifiers":[
        {
            "category":"Professional",
            "subcategory":"Management & Consulting",
            "type":"Services"
        }
    ],
    "sg:phone":"+1 770 352 0662",
    "sg:postcode":"30338",
    "sg:province":"GA",
    "wof:name":"Plumtree Marketing",
    "wof:placetype":"venue"
},
  "geometry": {"coordinates":[-84.343324,33.944785],"type":"Point"}
}