{
  "type": "Feature",
  "properties": {
    "iso:country":"US",
    "sg:address":"26 Red Fox Dr",
    "sg:city":"Savannah",
    "sg:classifiers":[
        {
            "category":"Retail",
            "subcategory":"Animal Services",
            "type":"Services"
        }
    ],
    "sg:phone":"+1 912 961 7419",
    "sg:postcode":"31419",
    "sg:province":"GA",
    "sg:tags":[
        "pet",
        "boarding",
        "sitting"
    ],
    "wof:name":"Georgetown Pet Sitting Svc",
    "wof:placetype":"venue"
},
  "geometry": {"coordinates":[-81.229677,31.980991],"type":"Point"}
}