{
  "type": "Feature",
  "properties": {
    "addr:full":"310 Plantation Rd SW Smyrna GA 30082",
    "addr:housenumber":"310",
    "addr:postcode":"30082",
    "addr:street":"Plantation Rd Sw",
    "iso:country":"US",
    "sg:address":"310 Plantation Rd SW",
    "sg:city":"Smyrna",
    "sg:classifiers":[
        {
            "category":"Professional",
            "type":"Services"
        }
    ],
    "sg:phone":"+1 770 434 4551",
    "sg:postcode":"30082",
    "sg:province":"GA",
    "wof:name":"Southern Chillers Inc",
    "wof:placetype":"venue"
},
  "geometry": {"coordinates":[-84.563559,33.863811],"type":"Point"}
}