{
  "type": "Feature",
  "properties": {
    "iso:country":"US",
    "sg:address":"1910 Forsyth St",
    "sg:city":"Macon",
    "sg:classifiers":[
        {
            "category":"Professional",
            "subcategory":"Detective & Security Services",
            "type":"Services"
        },
        {
            "category":"Wholesale",
            "subcategory":"Electrical",
            "type":"Manufacturing & Wholesale Goods"
        }
    ],
    "sg:phone":"+1 478 743 1800",
    "sg:postcode":"31201",
    "sg:province":"GA",
    "sg:tags":[
        "alarm",
        "burglar",
        "system"
    ],
    "wof:name":"Integrated Control Systems",
    "wof:placetype":"venue"
},
  "geometry": {"coordinates":[-83.649385,32.841529],"type":"Point"}
}