{
  "type": "Feature",
  "properties": {
    "iso:country":"US",
    "sg:address":"793 Allgood Rd",
    "sg:city":"Marietta",
    "sg:classifiers":[
        {
            "category":"Food & Beverages",
            "subcategory":"Groceries & Convenience Stores",
            "type":"Retail Goods"
        }
    ],
    "sg:phone":"+1 770 424 7703",
    "sg:postcode":"30062",
    "sg:province":"GA",
    "sg:tags":[
        "station",
        "gasoline"
    ],
    "wof:name":"Food Basket",
    "wof:placetype":"venue"
},
  "geometry": {"coordinates":[-84.528126,33.973649],"type":"Point"}
}