{
  "type": "Feature",
  "properties": {
    "iso:country":"US",
    "sg:address":"4375 Highway 27",
    "sg:city":"Summerville",
    "sg:classifiers":[
        {
            "category":"Food & Beverages",
            "subcategory":"Groceries & Convenience Stores",
            "type":"Retail Goods"
        }
    ],
    "sg:phone":"+1 706 857 1524",
    "sg:postcode":"30747",
    "sg:province":"GA",
    "wof:name":"Reese Enterprises",
    "wof:placetype":"venue"
},
  "geometry": {"coordinates":[-85.33179199999999,34.499386],"type":"Point"}
}