{
  "type": "Feature",
  "properties": {
    "addr:full":"3800 N Camp Creek Pkwy SW Atlanta GA 30344",
    "addr:housenumber":"3800",
    "addr:postcode":"30344",
    "addr:street":"N Camp Creek Pkwy Sw",
    "iso:country":"US",
    "sg:address":"3800 N Camp Creek Pkwy SW",
    "sg:city":"Atlanta",
    "sg:classifiers":[
        {
            "category":"Manufacturing",
            "subcategory":"Building Materials",
            "type":"Manufacturing & Wholesale Goods"
        }
    ],
    "sg:phone":"+1 404 346 0755",
    "sg:postcode":"30344",
    "sg:province":"GA",
    "sg:website":"www.essbeta.com",
    "wof:name":"STO Corp",
    "wof:placetype":"venue"
},
  "geometry": {"coordinates":[-84.51384400000001,33.675425],"type":"Point"}
}