{
  "type": "Feature",
  "properties": {
    "addr:full":"365 Lakes Blvd Lake Park GA 31636",
    "addr:housenumber":"365",
    "addr:postcode":"31636",
    "addr:street":"Lakes Blvd",
    "iso:country":"US",
    "sg:address":"365 Lakes Blvd",
    "sg:city":"Lake Park",
    "sg:classifiers":[
        {
            "category":"Shopping",
            "subcategory":"Department Store",
            "type":"Retail Goods"
        }
    ],
    "sg:phone":"+1 229 559 0555",
    "sg:postcode":"31636",
    "sg:province":"GA",
    "wof:name":"Fred's Store",
    "wof:placetype":"venue"
},
  "geometry": {"coordinates":[-83.204179,30.684983],"type":"Point"}
}