{
  "type": "Feature",
  "properties": {
    "iso:country":"US",
    "sg:address":"1730 Woodnymph Trl",
    "sg:city":"Lookout Mountain",
    "sg:classifiers":[
        {
            "category":"Shopping",
            "subcategory":"Clothing, Apparel, & Fashions",
            "type":"Retail Goods"
        }
    ],
    "sg:phone":"+1 706 820 0719",
    "sg:postcode":"30750",
    "sg:province":"GA",
    "sg:tags":[
        "shop",
        "golf"
    ],
    "wof:name":"Buchanan Collection LLC",
    "wof:placetype":"venue"
},
  "geometry": {"coordinates":[-85.35675999999999,34.96175],"type":"Point"}
}