{
  "type": "Feature",
  "properties": {
    "addr:full":"1100 Belmont Pl Braselton GA 30517",
    "addr:housenumber":"1100",
    "addr:postcode":"30517",
    "addr:street":"Belmont Pl",
    "iso:country":"US",
    "sg:address":"1100 Belmont Pl",
    "sg:city":"Braselton",
    "sg:classifiers":[
        {
            "category":"Shopping",
            "type":"Retail Goods"
        }
    ],
    "sg:phone":"+1 770 307 1218",
    "sg:postcode":"30517",
    "sg:province":"GA",
    "sg:tags":[
        "equipment",
        "medical",
        "sales"
    ],
    "wof:name":"Technological Horizons Entps",
    "wof:placetype":"venue"
},
  "geometry": {"coordinates":[-83.818202,34.098729],"type":"Point"}
}