{
  "type": "Feature",
  "properties": {
    "iso:country":"US",
    "sg:address":"1105 Furys Ln",
    "sg:city":"Augusta",
    "sg:classifiers":[
        {
            "category":"Organizations",
            "subcategory":"Religious Organization",
            "type":"Services"
        }
    ],
    "sg:phone":"+1 706 210 1133",
    "sg:postcode":"30907",
    "sg:province":"GA",
    "sg:tags":[
        "church"
    ],
    "wof:name":"Church Of The Holy Comforter",
    "wof:placetype":"venue"
},
  "geometry": {"coordinates":[-82.074905,33.529722],"type":"Point"}
}