{
  "type": "Feature",
  "properties": {
    "iso:country":"US",
    "sg:address":"365 Chaffin Ridge Ct",
    "sg:city":"Roswell",
    "sg:classifiers":[
        {
            "category":"Cinema",
            "subcategory":"Movie Rental",
            "type":"Entertainment"
        }
    ],
    "sg:phone":"+1 404 216 4161",
    "sg:postcode":"30075",
    "sg:province":"GA",
    "sg:tags":[
        "video",
        "tape"
    ],
    "wof:name":"Core 5 Film & Video Production",
    "wof:placetype":"venue"
},
  "geometry": {"coordinates":[-84.375469,34.062894],"type":"Point"}
}