{
  "type": "Feature",
  "properties": {
    "iso:country":"US",
    "sg:address":"3952 Shirley Dr SW",
    "sg:city":"Atlanta",
    "sg:classifiers":[
        {
            "category":"Professional",
            "subcategory":"Art Services",
            "type":"Services"
        }
    ],
    "sg:phone":"+1 404 691 8010",
    "sg:postcode":"30336",
    "sg:province":"GA",
    "sg:tags":[
        "designer",
        "display",
        "producer"
    ],
    "wof:name":"Exhibit Works",
    "wof:placetype":"venue"
},
  "geometry": {"coordinates":[-84.516391,33.764311],"type":"Point"}
}