{
  "type": "Feature",
  "properties": {
    "addr:full":"595 Six Flags Dr Austell GA 30168",
    "addr:housenumber":"595",
    "addr:postcode":"30168",
    "addr:street":"Six Flags Dr",
    "iso:country":"US",
    "sg:address":"595 Six Flags Dr",
    "sg:city":"Austell",
    "sg:classifiers":[
        {
            "category":"Personal",
            "subcategory":"Beauty Salon",
            "type":"Services"
        }
    ],
    "sg:phone":"+1 770 997 3383",
    "sg:postcode":"30168",
    "sg:province":"GA",
    "wof:name":"Quandra's Hair & Cosmetics",
    "wof:placetype":"venue"
},
  "geometry": {"coordinates":[-84.57299999999999,33.778097],"type":"Point"}
}