{
  "type": "Feature",
  "properties": {
    "iso:country":"US",
    "sg:address":"604 Washington St W",
    "sg:city":"Gainesville",
    "sg:classifiers":[
        {
            "category":"Personal",
            "subcategory":"Beauty Salon",
            "type":"Services"
        }
    ],
    "sg:phone":"+1 770 536 5001",
    "sg:postcode":"30501",
    "sg:province":"GA",
    "sg:tags":[
        "treatment",
        "skin"
    ],
    "wof:name":"Kyera Skin Care",
    "wof:placetype":"venue"
},
  "geometry": {"coordinates":[-83.832178,34.298007],"type":"Point"}
}