{
  "type": "Feature",
  "properties": {
    "addr:full":"454 Pebblestone Dr Ringgold GA 30736",
    "addr:housenumber":"454",
    "addr:postcode":"30736",
    "addr:street":"Pebblestone Dr",
    "iso:country":"US",
    "sg:address":"454 Pebblestone Dr",
    "sg:city":"Ringgold",
    "sg:classifiers":[
        {
            "category":"Shopping",
            "subcategory":"Clothing, Apparel, & Fashions",
            "type":"Retail Goods"
        }
    ],
    "sg:phone":"+1 706 965 8896",
    "sg:postcode":"30736",
    "sg:province":"GA",
    "wof:name":"Two Men & Paintbrush",
    "wof:placetype":"venue"
},
  "geometry": {"coordinates":[-85.14312200000001,34.891755],"type":"Point"}
}