{
  "type": "Feature",
  "properties": {
    "iso:country":"US",
    "sg:address":"882 Ooltewah-Ringgold Rd",
    "sg:city":"Ringgold",
    "sg:classifiers":[
        {
            "category":"Retail",
            "subcategory":"Repair Shop",
            "type":"Services"
        }
    ],
    "sg:phone":"+1 706 935 2831",
    "sg:postcode":"30736",
    "sg:province":"GA",
    "sg:tags":[
        "water",
        "equipment",
        "dr",
        "industrial",
        "well"
    ],
    "wof:name":"Kittle Drilling & Pump Supply",
    "wof:placetype":"venue"
},
  "geometry": {"coordinates":[-85.096924,34.982254],"type":"Point"}
}