{
  "type": "Feature",
  "properties": {
    "addr:full":"755 Almon Rd Covington GA 30014",
    "addr:housenumber":"755",
    "addr:postcode":"30014",
    "addr:street":"Almon Rd",
    "iso:country":"US",
    "sg:address":"755 Almon Rd",
    "sg:city":"Covington",
    "sg:classifiers":[
        {
            "category":"Organizations",
            "subcategory":"Religious Organization",
            "type":"Services"
        }
    ],
    "sg:phone":"+1 770 787 6507",
    "sg:postcode":"30014",
    "sg:province":"GA",
    "wof:name":"Gospel Mission Church",
    "wof:placetype":"venue"
},
  "geometry": {"coordinates":[-83.93027600000001,33.622595],"type":"Point"}
}