{
  "type": "Feature",
  "properties": {
    "addr:full":"829 Bay St Brunswick GA 31520",
    "addr:housenumber":"829",
    "addr:postcode":"31520",
    "addr:street":"Bay St",
    "iso:country":"US",
    "sg:address":"829 Bay St",
    "sg:city":"Brunswick",
    "sg:classifiers":[
        {
            "category":"Government",
            "subcategory":"Office",
            "type":"Public Place"
        }
    ],
    "sg:phone":"+1 912 267 3720",
    "sg:postcode":"31520",
    "sg:province":"GA",
    "sg:tags":[
        "village"
    ],
    "wof:name":"Brunswick City Streets & Drain",
    "wof:placetype":"venue"
},
  "geometry": {"coordinates":[-81.49738600000001,31.151636],"type":"Point"}
}