{
  "type": "Feature",
  "properties": {
    "iso:country":"US",
    "sg:address":"1601 Statesboro Place Cir",
    "sg:city":"Statesboro",
    "sg:classifiers":[
        {
            "category":"Restaurant",
            "type":"Food & Drink"
        }
    ],
    "sg:phone":"+1 912 681 1371",
    "sg:postcode":"30458",
    "sg:province":"GA",
    "wof:name":"Shell House",
    "wof:placetype":"venue"
},
  "geometry": {"coordinates":[-81.77704199999999,32.406202],"type":"Point"}
}