{
  "type": "Feature",
  "properties": {
    "iso:country":"US",
    "sg:address":"1990 Hughes Dr",
    "sg:city":"Cumming",
    "sg:classifiers":[
        {
            "category":"Banks & Credit Unions",
            "subcategory":"Financial Services",
            "type":"Services"
        }
    ],
    "sg:phone":"+1 770 887 9665",
    "sg:postcode":"30040",
    "sg:province":"GA",
    "sg:tags":[
        "investor"
    ],
    "wof:name":"Cjt Investments Inc",
    "wof:placetype":"venue"
},
  "geometry": {"coordinates":[-84.125136,34.250189],"type":"Point"}
}