{
  "type": "Feature",
  "properties": {
    "addr:full":"4923 Jonesboro Rd Forest Park GA 30297",
    "addr:housenumber":"4923",
    "addr:postcode":"30297",
    "addr:street":"Jonesboro Rd",
    "iso:country":"US",
    "sg:address":"4923 Jonesboro Rd",
    "sg:city":"Forest Park",
    "sg:classifiers":[
        {
            "category":"Building & Trades",
            "subcategory":"Locksmith",
            "type":"Services"
        }
    ],
    "sg:phone":"+1 678 369 5805",
    "sg:postcode":"30297",
    "sg:province":"GA",
    "sg:tags":[
        "key"
    ],
    "wof:name":"555 Emergency Locksmith",
    "wof:placetype":"venue"
},
  "geometry": {"coordinates":[-84.35209399999999,33.620156],"type":"Point"}
}