{
  "type": "Feature",
  "properties": {
    "addr:full":"763 W 3rd St Jackson GA 30233",
    "addr:housenumber":"763",
    "addr:postcode":"30233",
    "addr:street":"W 3Rd St",
    "iso:country":"US",
    "sg:address":"763 W 3rd St",
    "sg:city":"Jackson",
    "sg:classifiers":[
        {
            "category":"Professional",
            "type":"Services"
        }
    ],
    "sg:phone":"+1 770 775 5324",
    "sg:postcode":"30233",
    "sg:province":"GA",
    "wof:name":"Es Settle Family Ltd Part",
    "wof:placetype":"venue"
},
  "geometry": {"coordinates":[-83.975116,33.294007],"type":"Point"}
}