{
  "type": "Feature",
  "properties": {
    "iso:country":"US",
    "sg:address":"11 Dover Trl",
    "sg:city":"Peachtree City",
    "sg:classifiers":[
        {
            "category":"Professional",
            "type":"Services"
        }
    ],
    "sg:phone":"+1 770 487 3657",
    "sg:postcode":"30269",
    "sg:province":"GA",
    "wof:name":"Joan M Sevigny",
    "wof:placetype":"venue"
},
  "geometry": {"coordinates":[-84.58282,33.402316],"type":"Point"}
}