{
  "type": "Feature",
  "properties": {
    "iso:country":"US",
    "sg:address":"8215 Roswell Rd",
    "sg:city":"Atlanta",
    "sg:classifiers":[
        {
            "category":"Manufacturing",
            "subcategory":"Tools & Machinery",
            "type":"Manufacturing & Wholesale Goods"
        }
    ],
    "sg:phone":"+1 770 396 6080",
    "sg:postcode":"30350",
    "sg:province":"GA",
    "sg:tags":[
        "equipment",
        "testing"
    ],
    "wof:name":"Ballistics Research Inc",
    "wof:placetype":"venue"
},
  "geometry": {"coordinates":[-84.351786,33.976625],"type":"Point"}
}