{
  "type": "Feature",
  "properties": {
    "iso:country":"US",
    "sg:address":"3750 Jesse Rice St",
    "sg:city":"Macon",
    "sg:classifiers":[
        {
            "category":"Education",
            "subcategory":"School",
            "type":"Public Place"
        }
    ],
    "sg:phone":"+1 478 784 3147",
    "sg:postcode":"31206",
    "sg:province":"GA",
    "wof:name":"Jessie Rice Elementary School",
    "wof:placetype":"venue"
},
  "geometry": {"coordinates":[-83.692859,32.796156],"type":"Point"}
}