{
  "type": "Feature",
  "properties": {
    "addr:full":"2545 Atlanta Hwy Athens GA 30606",
    "addr:housenumber":"2545",
    "addr:postcode":"30606",
    "addr:street":"Atlanta Hwy",
    "iso:country":"US",
    "sg:address":"2545 Atlanta Hwy",
    "sg:city":"Athens",
    "sg:classifiers":[
        {
            "category":"Food & Beverages",
            "subcategory":"Groceries & Convenience Stores",
            "type":"Retail Goods"
        }
    ],
    "sg:phone":"+1 706 546 5560",
    "sg:postcode":"30606",
    "sg:province":"GA",
    "wof:name":"Sam's Food Mart",
    "wof:placetype":"venue"
},
  "geometry": {"coordinates":[-83.425456,33.946527],"type":"Point"}
}