{
  "type": "Feature",
  "properties": {
    "addr:full":"803 Cobb Pkwy N Marietta GA 30062",
    "addr:housenumber":"803",
    "addr:postcode":"30062",
    "addr:street":"Cobb Pkwy N",
    "iso:country":"US",
    "sg:address":"803 Cobb Pkwy N",
    "sg:city":"Marietta",
    "sg:classifiers":[
        {
            "category":"Restaurant",
            "type":"Food & Drink"
        }
    ],
    "sg:menulink":"http://www.allmenus.com/ga/marietta/237042-new-china-house/menu/",
    "sg:phone":"+1 770 428 6409",
    "sg:postcode":"30062",
    "sg:province":"GA",
    "sg:tags":[
        "asian",
        "chinese"
    ],
    "wof:name":"New China House",
    "wof:placetype":"venue"
},
  "geometry": {"coordinates":[-84.539185,33.969502],"type":"Point"}
}