{
  "type": "Feature",
  "properties": {
    "iso:country":"US",
    "sg:address":"2284 Bear Mountain Dr NE",
    "sg:city":"Conyers",
    "sg:classifiers":[
        {
            "category":"Restaurant",
            "type":"Food & Drink"
        }
    ],
    "sg:phone":"+1 770 761 2042",
    "sg:postcode":"30013",
    "sg:province":"GA",
    "sg:tags":[
        "eating"
    ],
    "wof:name":"Orient Exprss China Bft",
    "wof:placetype":"venue"
},
  "geometry": {"coordinates":[-83.96800500000001,33.674321],"type":"Point"}
}