{
  "type": "Feature",
  "properties": {
    "addr:full":"607 W Solomon St Griffin GA 30223",
    "addr:housenumber":"607",
    "addr:postcode":"30223",
    "addr:street":"W Solomon St",
    "iso:country":"US",
    "sg:address":"607 W Solomon St",
    "sg:city":"Griffin",
    "sg:classifiers":[
        {
            "category":"Professional",
            "subcategory":"Management & Consulting",
            "type":"Services"
        }
    ],
    "sg:phone":"+1 770 229 9718",
    "sg:postcode":"30223",
    "sg:province":"GA",
    "sg:tags":[
        "construction",
        "commercial"
    ],
    "wof:name":"Tht Inc",
    "wof:placetype":"venue"
},
  "geometry": {"coordinates":[-84.273343,33.248919],"type":"Point"}
}