{
  "type": "Feature",
  "properties": {
    "iso:country":"US",
    "sg:address":"4635 Riversound Dr",
    "sg:city":"Snellville",
    "sg:classifiers":[
        {
            "category":"Health Services",
            "subcategory":"Clinic",
            "type":"Services"
        }
    ],
    "sg:phone":"+1 770 979 5441",
    "sg:postcode":"30039",
    "sg:province":"GA",
    "wof:name":"Rls Med Support Inc",
    "wof:placetype":"venue"
},
  "geometry": {"coordinates":[-84.071394,33.8012],"type":"Point"}
}