{
  "type": "Feature",
  "properties": {
    "iso:country":"US",
    "sg:address":"215 S Commercial Cir",
    "sg:city":"Warner Robins",
    "sg:classifiers":[
        {
            "category":"Retail",
            "subcategory":"Auto Repair",
            "type":"Services"
        }
    ],
    "sg:phone":"+1 478 954 2298",
    "sg:postcode":"31088",
    "sg:province":"GA",
    "sg:tags":[
        "automobile",
        "customizing"
    ],
    "wof:name":"Matt's Mobile Headliners Plus",
    "wof:placetype":"venue"
},
  "geometry": {"coordinates":[-83.61394300000001,32.618112],"type":"Point"}
}