{
  "type": "Feature",
  "properties": {
    "addr:full":"2823 Tobacco Rd Hephzibah GA 30815",
    "addr:housenumber":"2823",
    "addr:postcode":"30815",
    "addr:street":"Tobacco Rd",
    "iso:country":"US",
    "sg:address":"2823 Tobacco Rd",
    "sg:city":"Hephzibah",
    "sg:classifiers":[
        {
            "category":"Retail",
            "subcategory":"Auto Repair",
            "type":"Services"
        }
    ],
    "sg:phone":"+1 706 736 2234",
    "sg:postcode":"30815",
    "sg:province":"GA",
    "sg:tags":[
        "body",
        "automobile",
        "painting"
    ],
    "wof:name":"Davis Paint & Body",
    "wof:placetype":"venue"
},
  "geometry": {"coordinates":[-82.100801,33.387402],"type":"Point"}
}