{
  "type": "Feature",
  "properties": {
    "iso:country":"US",
    "sg:address":"545 Hood Ave",
    "sg:city":"Fayetteville",
    "sg:classifiers":[
        {
            "category":"Personal",
            "type":"Services"
        }
    ],
    "sg:phone":"+1 678 817 0954",
    "sg:postcode":"30214",
    "sg:province":"GA",
    "wof:name":"Everyones Handy Man Inc",
    "wof:placetype":"venue"
},
  "geometry": {"coordinates":[-84.465031,33.456852],"type":"Point"}
}