{
  "type": "Feature",
  "properties": {
    "addr:full":"3154 State Rte 317 Suwanee GA 30024",
    "addr:housenumber":"3154",
    "addr:postcode":"30024",
    "addr:street":"State Rte 317",
    "iso:country":"US",
    "sg:address":"3154 State Rte 317",
    "sg:city":"Suwanee",
    "sg:classifiers":[
        {
            "category":"Autos & Motor Vehicles",
            "subcategory":"Fuel & Gas Station",
            "type":"Retail Goods"
        }
    ],
    "sg:phone":"+1 770 932 0303",
    "sg:postcode":"30024",
    "sg:province":"GA",
    "sg:tags":[
        "convenience",
        "station"
    ],
    "wof:name":"Chevron",
    "wof:placetype":"venue"
},
  "geometry": {"coordinates":[-84.051474,34.033791],"type":"Point"}
}