{
  "type": "Feature",
  "properties": {
    "iso:country":"US",
    "sg:address":"4153 Flat Shoals Pkwy",
    "sg:city":"Decatur",
    "sg:classifiers":[
        {
            "category":"Professional",
            "subcategory":"Accounting & Tax Preparation",
            "type":"Services"
        }
    ],
    "sg:phone":"+1 404 381 0138",
    "sg:postcode":"30034",
    "sg:province":"GA",
    "sg:tags":[
        "accountant"
    ],
    "wof:name":"W 3 Cpas & Consultants",
    "wof:placetype":"venue"
},
  "geometry": {"coordinates":[-84.259844,33.692012],"type":"Point"}
}