{
  "type": "Feature",
  "properties": {
    "iso:country":"US",
    "sg:address":"3785 Patterstone Dr",
    "sg:city":"Alpharetta",
    "sg:classifiers":[
        {
            "category":"Wholesale",
            "subcategory":"Drugs",
            "type":"Manufacturing & Wholesale Goods"
        }
    ],
    "sg:phone":"+1 770 205 2236",
    "sg:postcode":"30022",
    "sg:province":"GA",
    "wof:name":"T R International LLC",
    "wof:placetype":"venue"
},
  "geometry": {"coordinates":[-84.253545,34.026666],"type":"Point"}
}