{
  "type": "Feature",
  "properties": {
    "iso:country":"US",
    "sg:address":"915 Goebel Ave",
    "sg:city":"Savannah",
    "sg:classifiers":[
        {
            "category":"Professional",
            "type":"Services"
        }
    ],
    "sg:phone":"+1 912 944 0998",
    "sg:postcode":"31404",
    "sg:province":"GA",
    "wof:name":"Cambodia Corps Inc",
    "wof:placetype":"venue"
},
  "geometry": {"coordinates":[-81.06808100000001,32.058159],"type":"Point"}
}