{
  "type": "Feature",
  "properties": {
    "addr:full":"637 Dill Ave SW Atlanta GA 30310",
    "addr:housenumber":"637",
    "addr:postcode":"30310",
    "addr:street":"Dill Ave Sw",
    "iso:country":"US",
    "sg:address":"637 Dill Ave SW",
    "sg:city":"Atlanta",
    "sg:classifiers":[
        {
            "category":"Food & Beverages",
            "subcategory":"Groceries & Convenience Stores",
            "type":"Retail Goods"
        }
    ],
    "sg:phone":"+1 404 758 2450",
    "sg:postcode":"30310",
    "sg:province":"GA",
    "wof:name":"Geralds Grocery",
    "wof:placetype":"venue"
},
  "geometry": {"coordinates":[-84.40807,33.718348],"type":"Point"}
}