{
  "type": "Feature",
  "properties": {
    "addr:full":"2245 Gaines Mill Rd Gainesville GA 30507",
    "addr:housenumber":"2245",
    "addr:postcode":"30507",
    "addr:street":"Gaines Mill Rd",
    "iso:country":"US",
    "sg:address":"2245 Gaines Mill Rd",
    "sg:city":"Gainesville",
    "sg:classifiers":[
        {
            "category":"Bus Charters",
            "type":"Transportation"
        },
        {
            "category":"Travel",
            "subcategory":"Travel Agent",
            "type":"Entertainment"
        }
    ],
    "sg:phone":"+1 770 536 0079",
    "sg:postcode":"30507",
    "sg:province":"GA",
    "sg:tags":[
        "operator",
        "tour",
        "rental"
    ],
    "wof:name":"T & D Charter Bus Service",
    "wof:placetype":"venue"
},
  "geometry": {"coordinates":[-83.77928300000001,34.27498],"type":"Point"}
}