{
  "type": "Feature",
  "properties": {
    "addr:full":"181 Hoss Ct Riverdale GA 30274",
    "addr:housenumber":"181",
    "addr:postcode":"30274",
    "addr:street":"Hoss Ct",
    "iso:country":"US",
    "sg:address":"181 Hoss Ct",
    "sg:city":"Riverdale",
    "sg:classifiers":[
        {
            "category":"Personal",
            "type":"Services"
        }
    ],
    "sg:phone":"+1 678 755 2131",
    "sg:postcode":"30274",
    "sg:province":"GA",
    "sg:tags":[
        "miscellaneous"
    ],
    "wof:name":"Eazy Does It",
    "wof:placetype":"venue"
},
  "geometry": {"coordinates":[-84.396418,33.559079],"type":"Point"}
}