{
  "type": "Feature",
  "properties": {
    "addr:full":"2220 Sunny Hill Rd Lawrenceville GA 30043",
    "addr:housenumber":"2220",
    "addr:postcode":"30043",
    "addr:street":"Sunny Hill Rd",
    "iso:country":"US",
    "sg:address":"2220 Sunny Hill Rd",
    "sg:city":"Lawrenceville",
    "sg:classifiers":[
        {
            "category":"Organizations",
            "subcategory":"Religious Organization",
            "type":"Services"
        }
    ],
    "sg:phone":"+1 770 338 7677",
    "sg:postcode":"30043",
    "sg:province":"GA",
    "sg:tags":[
        "church"
    ],
    "wof:name":"Outreach Church",
    "wof:placetype":"venue"
},
  "geometry": {"coordinates":[-83.960138,34.036542],"type":"Point"}
}