{
  "type": "Feature",
  "properties": {
    "iso:country":"US",
    "sg:address":"1124 Brook View Ave",
    "sg:city":"Atlanta",
    "sg:classifiers":[
        {
            "category":"Professional",
            "type":"Services"
        }
    ],
    "sg:phone":"+1 770 939 5292",
    "sg:postcode":"30340",
    "sg:province":"GA",
    "wof:name":"Reelstekisha",
    "wof:placetype":"venue"
},
  "geometry": {"coordinates":[-84.236593,33.901051],"type":"Point"}
}