{
  "type": "Feature",
  "properties": {
    "addr:full":"7185 Rockbridge Rd Stone Mountain GA 30087",
    "addr:housenumber":"7185",
    "addr:postcode":"30087",
    "addr:street":"Rockbridge Rd",
    "iso:country":"US",
    "sg:address":"7185 Rockbridge Rd",
    "sg:city":"Stone Mountain",
    "sg:classifiers":[
        {
            "category":"Building & Trades",
            "subcategory":"Locksmith",
            "type":"Services"
        }
    ],
    "sg:phone":"+1 888 343 1964",
    "sg:postcode":"30087",
    "sg:province":"GA",
    "sg:tags":[
        "key"
    ],
    "wof:name":"1 24 Hour Emergency Locksmith",
    "wof:placetype":"venue"
},
  "geometry": {"coordinates":[-84.103364,33.785141],"type":"Point"}
}