{
  "type": "Feature",
  "properties": {
    "iso:country":"US",
    "sg:address":"1120 Pine Ridge Rd NE",
    "sg:city":"Atlanta",
    "sg:classifiers":[
        {
            "category":"Professional",
            "subcategory":"Management & Consulting",
            "type":"Services"
        }
    ],
    "sg:phone":"+1 404 237 4879",
    "sg:postcode":"30324",
    "sg:province":"GA",
    "wof:name":"Roxboro Capital",
    "wof:placetype":"venue"
},
  "geometry": {"coordinates":[-84.348671,33.844056],"type":"Point"}
}