{
  "type": "Feature",
  "properties": {
    "addr:full":"301 Robinwood Dr Dalton GA 30721",
    "addr:housenumber":"301",
    "addr:postcode":"30721",
    "addr:street":"Robinwood Dr",
    "iso:country":"US",
    "sg:address":"301 Robinwood Dr",
    "sg:city":"Dalton",
    "sg:classifiers":[
        {
            "category":"Building & Trades",
            "subcategory":"Construction",
            "type":"Services"
        }
    ],
    "sg:phone":"+1 706 275 8635",
    "sg:postcode":"30721",
    "sg:province":"GA",
    "sg:tags":[
        "contractor"
    ],
    "wof:name":"Georgia North Envmtl Svcs",
    "wof:placetype":"venue"
},
  "geometry": {"coordinates":[-84.94480900000001,34.76803],"type":"Point"}
}