{
  "type": "Feature",
  "properties": {
    "addr:full":"10029 State Hwy 92 Woodstock GA 30188",
    "addr:housenumber":"10029",
    "addr:postcode":"30188",
    "addr:street":"State Hwy 92",
    "iso:country":"US",
    "sg:address":"10029 State Hwy 92",
    "sg:city":"Woodstock",
    "sg:classifiers":[
        {
            "category":"Utilities",
            "subcategory":"Mobile Phone",
            "type":"Services"
        },
        {
            "category":"Shopping",
            "subcategory":"Computers & Home Electronics",
            "type":"Retail Goods"
        }
    ],
    "sg:phone":"+1 770 592 7176",
    "sg:postcode":"30188",
    "sg:province":"GA",
    "sg:tags":[
        "telephone",
        "cellular"
    ],
    "wof:name":"Radio Shack",
    "wof:placetype":"venue"
},
  "geometry": {"coordinates":[-84.522558,34.086147],"type":"Point"}
}