{
  "type": "Feature",
  "properties": {
    "iso:country":"US",
    "sg:address":"122 E Main St",
    "sg:city":"Fort Valley",
    "sg:classifiers":[
        {
            "category":"Museum",
            "type":"Entertainment"
        }
    ],
    "sg:phone":"+1 478 825 8544",
    "sg:postcode":"31030",
    "sg:province":"GA",
    "sg:tags":[
        "organization",
        "arts",
        "information"
    ],
    "wof:name":"Bliss & Feet Ctr For The Arts",
    "wof:placetype":"venue"
},
  "geometry": {"coordinates":[-83.886326,32.553361],"type":"Point"}
}