{
  "type": "Feature",
  "properties": {
    "iso:country":"US",
    "sg:address":"400 W Pike St",
    "sg:city":"Lawrenceville",
    "sg:classifiers":[
        {
            "category":"Food & Beverages",
            "subcategory":"Groceries & Convenience Stores",
            "type":"Retail Goods"
        }
    ],
    "sg:phone":"+1 678 376 1123",
    "sg:postcode":"30045",
    "sg:province":"GA",
    "wof:name":"Hillmond Corp",
    "wof:placetype":"venue"
},
  "geometry": {"coordinates":[-84.00137700000001,33.958205],"type":"Point"}
}