{
  "type": "Feature",
  "properties": {
    "addr:full":"564 Old Club Rd S Macon GA 31210",
    "addr:housenumber":"564",
    "addr:postcode":"31210",
    "addr:street":"Old Club Rd S",
    "iso:country":"US",
    "sg:address":"564 Old Club Rd S",
    "sg:city":"Macon",
    "sg:classifiers":[
        {
            "category":"Professional",
            "type":"Services"
        }
    ],
    "sg:phone":"+1 478 474 4786",
    "sg:postcode":"31210",
    "sg:province":"GA",
    "wof:name":"Robert W Stribling LLC",
    "wof:placetype":"venue"
},
  "geometry": {"coordinates":[-83.707461,32.864087],"type":"Point"}
}