{
  "type": "Feature",
  "properties": {
    "iso:country":"US",
    "sg:address":"1 Ghost Crab Ct",
    "sg:city":"Savannah",
    "sg:classifiers":[
        {
            "category":"Health Services",
            "subcategory":"Clinic",
            "type":"Services"
        }
    ],
    "sg:phone":"+1 912 598 4045",
    "sg:postcode":"31411",
    "sg:province":"GA",
    "wof:name":"Shared Healthcare",
    "wof:placetype":"venue"
},
  "geometry": {"coordinates":[-81.071635,31.938557],"type":"Point"}
}