{
  "type": "Feature",
  "properties": {
    "iso:country":"US",
    "sg:address":"1200 Toffie Ter",
    "sg:city":"Atlanta",
    "sg:classifiers":[
        {
            "category":"Freight",
            "type":"Transportation"
        }
    ],
    "sg:phone":"+1 404 768 5501",
    "sg:postcode":"30354",
    "sg:province":"GA",
    "sg:tags":[
        "operator",
        "trucking",
        "local",
        "courier",
        "air"
    ],
    "wof:name":"Airnet Express",
    "wof:placetype":"venue"
},
  "geometry": {"coordinates":[-84.425273,33.653191],"type":"Point"}
}