{
  "type": "Feature",
  "properties": {
    "addr:full":"3719 Blackstock Rd Talmo GA 30575",
    "addr:housenumber":"3719",
    "addr:postcode":"30575",
    "addr:street":"Blackstock Rd",
    "iso:country":"US",
    "sg:address":"3719 Blackstock Rd",
    "sg:city":"Talmo",
    "sg:classifiers":[
        {
            "category":"Building & Trades",
            "subcategory":"Landscaping Services",
            "type":"Services"
        }
    ],
    "sg:phone":"+1 770 718 9452",
    "sg:postcode":"30575",
    "sg:province":"GA",
    "sg:tags":[
        "lawn",
        "maintenance",
        "grounds"
    ],
    "wof:name":"Lanier Lawn Svc",
    "wof:placetype":"venue"
},
  "geometry": {"coordinates":[-83.722751,34.22012],"type":"Point"}
}