{
  "type": "Feature",
  "properties": {
    "iso:country":"US",
    "sg:address":"4000 Randall Mill Rd NW",
    "sg:city":"Atlanta",
    "sg:classifiers":[
        {
            "category":"Real Estate",
            "subcategory":"Real Estate Operator",
            "type":"Services"
        }
    ],
    "sg:phone":"+1 404 869 3640",
    "sg:postcode":"30327",
    "sg:province":"GA",
    "sg:tags":[
        "building",
        "nonresidential"
    ],
    "wof:name":"Bda Properties Inc",
    "wof:placetype":"venue"
},
  "geometry": {"coordinates":[-84.429194,33.867336],"type":"Point"}
}