{
  "type": "Feature",
  "properties": {
    "iso:country":"US",
    "sg:address":"330 Duncan Springs Rd",
    "sg:city":"Athens",
    "sg:classifiers":[
        {
            "category":"Professional",
            "subcategory":"Business Services",
            "type":"Services"
        }
    ],
    "sg:phone":"+1 706 549 3794",
    "sg:postcode":"30606",
    "sg:province":"GA",
    "wof:name":"Rivercrest Partners LLC",
    "wof:placetype":"venue"
},
  "geometry": {"coordinates":[-83.397702,33.925406],"type":"Point"}
}