{
  "type": "Feature",
  "properties": {
    "iso:country":"US",
    "sg:address":"535 Brooks Dr",
    "sg:city":"Nicholson",
    "sg:phone":"+1 706 757 3396",
    "sg:postcode":"30565",
    "sg:province":"GA",
    "sg:tags":[
        "farm",
        "corn",
        "soybean"
    ],
    "wof:name":"Donald Brooks",
    "wof:placetype":"venue"
},
  "geometry": {"coordinates":[-83.412768,34.072273],"type":"Point"}
}