{
  "type": "Feature",
  "properties": {
    "iso:country":"US",
    "sg:address":"721 E Shotwell St",
    "sg:city":"Bainbridge",
    "sg:classifiers":[
        {
            "category":"Personal",
            "subcategory":"Beauty Salon",
            "type":"Services"
        },
        {
            "category":"Personal",
            "subcategory":"Barber",
            "type":"Services"
        }
    ],
    "sg:phone":"+1 229 246 2193",
    "sg:postcode":"39819",
    "sg:province":"GA",
    "wof:name":"Mac & Mia's Haircutters",
    "wof:placetype":"venue"
},
  "geometry": {"coordinates":[-84.537407,30.902835],"type":"Point"}
}