{
  "type": "Feature",
  "properties": {
    "addr:full":"2100 Clairmont Ter NE Atlanta GA 30345",
    "addr:housenumber":"2100",
    "addr:postcode":"30345",
    "addr:street":"Clairmont Ter Ne",
    "iso:country":"US",
    "sg:address":"2100 Clairmont Ter NE",
    "sg:city":"Atlanta",
    "sg:classifiers":[
        {
            "category":"Banks & Credit Unions",
            "subcategory":"Bank",
            "type":"Services"
        }
    ],
    "sg:phone":"+1 404 315 1546",
    "sg:postcode":"30345",
    "sg:province":"GA",
    "wof:name":"Decatur First Bank",
    "wof:placetype":"venue"
},
  "geometry": {"coordinates":[-84.306348,33.85251],"type":"Point"}
}