{
  "type": "Feature",
  "properties": {
    "iso:country":"US",
    "sg:address":"6025 Professional Pkwy",
    "sg:city":"Douglasville",
    "sg:classifiers":[
        {
            "category":"Health Services",
            "subcategory":"Doctor",
            "type":"Services"
        }
    ],
    "sg:phone":"+1 770 489 7011",
    "sg:postcode":"30134",
    "sg:province":"GA",
    "sg:tags":[
        "obstetrician",
        "gynecologist"
    ],
    "wof:name":"Neuman Alan MD",
    "wof:placetype":"venue"
},
  "geometry": {"coordinates":[-84.733002,33.742599],"type":"Point"}
}