{
  "type": "Feature",
  "properties": {
    "iso:country":"US",
    "sg:address":"2505 Sylvester Hwy",
    "sg:city":"Albany",
    "sg:classifiers":[
        {
            "category":"Retail",
            "subcategory":"Auto Repair",
            "type":"Services"
        }
    ],
    "sg:phone":"+1 229 639 4221",
    "sg:postcode":"31705",
    "sg:province":"GA",
    "sg:tags":[
        "body"
    ],
    "wof:name":"Professnl Rstratn Cllsn Cntr I",
    "wof:placetype":"venue"
},
  "geometry": {"coordinates":[-84.084361,31.574817],"type":"Point"}
}