{
  "type": "Feature",
  "properties": {
    "addr:full":"1230 S Hairston Rd Stone Mountain GA 30088",
    "addr:housenumber":"1230",
    "addr:postcode":"30088",
    "addr:street":"S Hairston Rd",
    "iso:country":"US",
    "sg:address":"1230 S Hairston Rd",
    "sg:city":"Stone Mountain",
    "sg:classifiers":[
        {
            "category":"Retail",
            "subcategory":"Self-service Laundry",
            "type":"Services"
        }
    ],
    "sg:phone":"+1 404 296 1943",
    "sg:postcode":"30088",
    "sg:province":"GA",
    "sg:tags":[
        "coin",
        "power"
    ],
    "wof:name":"C & Y Laundry Corp",
    "wof:placetype":"venue"
},
  "geometry": {"coordinates":[-84.196676,33.759711],"type":"Point"}
}