{
  "type": "Feature",
  "properties": {
    "iso:country":"US",
    "sg:address":"719 Mulberry St",
    "sg:city":"Macon",
    "sg:classifiers":[
        {
            "category":"Social Services",
            "type":"Services"
        }
    ],
    "sg:phone":"+1 478 743 8026",
    "sg:postcode":"31201",
    "sg:province":"GA",
    "sg:tags":[
        "organization",
        "welfare"
    ],
    "wof:name":"Mulberry St United Methodist",
    "wof:placetype":"venue"
},
  "geometry": {"coordinates":[-83.629994,32.839081],"type":"Point"}
}