{
  "type": "Feature",
  "properties": {
    "iso:country":"US",
    "sg:address":"1360 5th St",
    "sg:city":"Macon",
    "sg:classifiers":[
        {
            "category":"Professional",
            "type":"Services"
        }
    ],
    "sg:phone":"+1 478 746 2701",
    "sg:postcode":"31201",
    "sg:province":"GA",
    "sg:tags":[
        "establishment"
    ],
    "wof:name":"Hatcher Milling Co LLC",
    "wof:placetype":"venue"
},
  "geometry": {"coordinates":[-83.633724,32.82294],"type":"Point"}
}