{
  "type": "Feature",
  "properties": {
    "iso:country":"US",
    "sg:address":"1740 Defoor Pl NW",
    "sg:city":"Atlanta",
    "sg:classifiers":[
        {
            "category":"Arts & Performance",
            "subcategory":"Theater",
            "type":"Entertainment"
        }
    ],
    "sg:phone":"+1 404 609 9976",
    "sg:postcode":"30318",
    "sg:province":"GA",
    "sg:tags":[
        "group"
    ],
    "wof:name":"Depwudz Entertainment",
    "wof:placetype":"venue"
},
  "geometry": {"coordinates":[-84.421728,33.80226],"type":"Point"}
}