{
  "type": "Feature",
  "properties": {
    "addr:full":"109 Adams Ln Grovetown GA 30813",
    "addr:housenumber":"109",
    "addr:postcode":"30813",
    "addr:street":"Adams Ln",
    "iso:country":"US",
    "sg:address":"109 Adams Ln",
    "sg:city":"Grovetown",
    "sg:classifiers":[
        {
            "category":"Retail",
            "subcategory":"Portrait Studio",
            "type":"Services"
        }
    ],
    "sg:phone":"+1 706 650 2741",
    "sg:postcode":"30813",
    "sg:province":"GA",
    "sg:tags":[
        "photo"
    ],
    "wof:name":"Stan Rawlins Photography",
    "wof:placetype":"venue"
},
  "geometry": {"coordinates":[-82.21093399999999,33.453904],"type":"Point"}
}