{
  "type": "Feature",
  "properties": {
    "addr:full":"360 Champions View Dr Alpharetta GA 30004",
    "addr:housenumber":"360",
    "addr:postcode":"30004",
    "addr:street":"Champions View Dr",
    "iso:country":"US",
    "sg:address":"360 Champions View Dr",
    "sg:city":"Alpharetta",
    "sg:classifiers":[
        {
            "category":"Professional",
            "subcategory":"Business Services",
            "type":"Services"
        }
    ],
    "sg:phone":"+1 770 475 0375",
    "sg:postcode":"30004",
    "sg:province":"GA",
    "wof:name":"Leisure Time Agency Inc",
    "wof:placetype":"venue"
},
  "geometry": {"coordinates":[-84.27413199999999,34.144661],"type":"Point"}
}