{
  "type": "Feature",
  "properties": {
    "iso:country":"US",
    "sg:address":"2260 Chrysler Ter NE",
    "sg:city":"Atlanta",
    "sg:classifiers":[
        {
            "category":"Real Estate",
            "subcategory":"Real Estate Agent",
            "type":"Services"
        }
    ],
    "sg:phone":"+1 404 633 3139",
    "sg:postcode":"30345",
    "sg:province":"GA",
    "wof:name":"Sovereign Realty",
    "wof:placetype":"venue"
},
  "geometry": {"coordinates":[-84.296976,33.837604],"type":"Point"}
}