{
  "type": "Feature",
  "properties": {
    "addr:full":"2420 Cumberland Dr SE Smyrna GA 30080",
    "addr:housenumber":"2420",
    "addr:postcode":"30080",
    "addr:street":"Cumberland Dr Se",
    "iso:country":"US",
    "sg:address":"2420 Cumberland Dr SE",
    "sg:city":"Smyrna",
    "sg:classifiers":[
        {
            "category":"Wholesale",
            "subcategory":"Electrical",
            "type":"Manufacturing & Wholesale Goods"
        }
    ],
    "sg:phone":"+1 770 435 2523",
    "sg:postcode":"30080",
    "sg:province":"GA",
    "wof:name":"W S Lacefield",
    "wof:placetype":"venue"
},
  "geometry": {"coordinates":[-84.482871,33.873478],"type":"Point"}
}