{
  "type": "Feature",
  "properties": {
    "iso:country":"US",
    "sg:address":"2488 Tuckerstone Pkwy",
    "sg:city":"Tucker",
    "sg:classifiers":[
        {
            "category":"Professional",
            "subcategory":"Advertising",
            "type":"Services"
        },
        {
            "category":"Shopping",
            "subcategory":"Used Merchandise",
            "type":"Retail Goods"
        }
    ],
    "sg:phone":"+1 770 939 2707",
    "sg:postcode":"30084",
    "sg:province":"GA",
    "sg:tags":[
        "producer",
        "designer",
        "display",
        "business",
        "millwork"
    ],
    "sg:website":"http://www.itagedesign.com",
    "wof:name":"Itage Design Group",
    "wof:placetype":"venue"
},
  "geometry": {"coordinates":[-84.198633,33.857548],"type":"Point"}
}