{
  "type": "Feature",
  "properties": {
    "iso:country":"US",
    "sg:address":"1401 N Columbia St",
    "sg:city":"Milledgeville",
    "sg:classifiers":[
        {
            "category":"Real Estate",
            "subcategory":"Real Estate Agent",
            "type":"Services"
        }
    ],
    "sg:phone":"+1 478 453 9411",
    "sg:postcode":"31061",
    "sg:province":"GA",
    "sg:tags":[
        "broker"
    ],
    "wof:name":"Chamber Realty & Appraisel Svc",
    "wof:placetype":"venue"
},
  "geometry": {"coordinates":[-83.24100199999999,33.095887],"type":"Point"}
}