{
  "type": "Feature",
  "properties": {
    "iso:country":"US",
    "sg:address":"4644 Jonesboro Rd",
    "sg:city":"Union City",
    "sg:classifiers":[
        {
            "category":"Restaurant",
            "type":"Food & Drink"
        }
    ],
    "sg:phone":"+1 770 969 1680",
    "sg:postcode":"30291",
    "sg:province":"GA",
    "sg:website":"www.krystal.com",
    "wof:name":"Krystal Company the",
    "wof:placetype":"venue"
},
  "geometry": {"coordinates":[-84.539597,33.568802],"type":"Point"}
}