{
  "type": "Feature",
  "properties": {
    "addr:full":"1224 Willow Dr Auburn GA 30011",
    "addr:housenumber":"1224",
    "addr:postcode":"30011",
    "addr:street":"Willow Dr",
    "iso:country":"US",
    "sg:address":"1224 Willow Dr",
    "sg:city":"Auburn",
    "sg:classifiers":[
        {
            "category":"Building & Trades",
            "subcategory":"Construction",
            "type":"Services"
        }
    ],
    "sg:phone":"+1 770 868 1885",
    "sg:postcode":"30011",
    "sg:province":"GA",
    "sg:tags":[
        "hanging",
        "contractor"
    ],
    "wof:name":"Brock Painting",
    "wof:placetype":"venue"
},
  "geometry": {"coordinates":[-83.818944,33.981197],"type":"Point"}
}