{
  "type": "Feature",
  "properties": {
    "addr:full":"1107 Broadrick Dr Dalton GA 30720",
    "addr:housenumber":"1107",
    "addr:postcode":"30720",
    "addr:street":"Broadrick Dr",
    "iso:country":"US",
    "sg:address":"1107 Broadrick Dr",
    "sg:city":"Dalton",
    "sg:classifiers":[
        {
            "category":"Health Services",
            "subcategory":"Doctor",
            "type":"Services"
        }
    ],
    "sg:phone":"+1 706 278 5558",
    "sg:postcode":"30720",
    "sg:province":"GA",
    "sg:tags":[
        "physician",
        "surgeon"
    ],
    "sg:website":"http://www.activefootcare.net",
    "wof:name":"Active Foot Care",
    "wof:placetype":"venue"
},
  "geometry": {"coordinates":[-84.985546,34.781598],"type":"Point"}
}