{
  "type": "Feature",
  "properties": {
    "addr:full":"5907 Coral Gables Dr Lake Park GA 31636",
    "addr:housenumber":"5907",
    "addr:postcode":"31636",
    "addr:street":"Coral Gables Dr",
    "iso:country":"US",
    "sg:address":"5907 Coral Gables Dr",
    "sg:city":"Lake Park",
    "sg:classifiers":[
        {
            "category":"Shopping",
            "subcategory":"Bicycles & Sporting Goods",
            "type":"Retail Goods"
        }
    ],
    "sg:phone":"+1 229 559 5328",
    "sg:postcode":"31636",
    "sg:province":"GA",
    "wof:name":"Sportsmans Haven",
    "wof:placetype":"venue"
},
  "geometry": {"coordinates":[-83.200768,30.698117],"type":"Point"}
}