{
  "type": "Feature",
  "properties": {
    "iso:country":"US",
    "sg:address":"861 Joe Frank Harris Pkwy SE",
    "sg:city":"Cartersville",
    "sg:classifiers":[
        {
            "category":"Health Services",
            "subcategory":"Chiropractor",
            "type":"Services"
        }
    ],
    "sg:phone":"+1 770 386 7707",
    "sg:postcode":"30120",
    "sg:province":"GA",
    "sg:tags":[
        "chiropractic"
    ],
    "wof:name":"Garber Chiropractic Center",
    "wof:placetype":"venue"
},
  "geometry": {"coordinates":[-84.789565,34.194977],"type":"Point"}
}