{
  "type": "Feature",
  "properties": {
    "addr:full":"1127 Renee Dr Decatur GA 30035",
    "addr:housenumber":"1127",
    "addr:postcode":"30035",
    "addr:street":"Renee Dr",
    "iso:country":"US",
    "sg:address":"1127 Renee Dr",
    "sg:city":"Decatur",
    "sg:classifiers":[
        {
            "category":"Professional",
            "type":"Services"
        }
    ],
    "sg:phone":"+1 404 534 0225",
    "sg:postcode":"30035",
    "sg:province":"GA",
    "wof:name":"LCR",
    "wof:placetype":"venue"
},
  "geometry": {"coordinates":[-84.231274,33.760432],"type":"Point"}
}