{
  "type": "Feature",
  "properties": {
    "addr:full":"2001 Airport Rd Atlanta GA 30341",
    "addr:housenumber":"2001",
    "addr:postcode":"30341",
    "addr:street":"Airport Rd",
    "iso:country":"US",
    "sg:address":"2001 Airport Rd",
    "sg:city":"Atlanta",
    "sg:classifiers":[
        {
            "category":"Education",
            "subcategory":"Special Training",
            "type":"Public Place"
        }
    ],
    "sg:phone":"+1 678 691 3283",
    "sg:postcode":"30341",
    "sg:province":"GA",
    "sg:tags":[
        "aircraft",
        "flight",
        "school"
    ],
    "wof:name":"Skybound Aviation",
    "wof:placetype":"venue"
},
  "geometry": {"coordinates":[-84.304833,33.876644],"type":"Point"}
}