{
  "type": "Feature",
  "properties": {
    "addr:full":"6335 Shannon Pkwy Union City GA 30291",
    "addr:housenumber":"6335",
    "addr:postcode":"30291",
    "addr:street":"Shannon Pkwy",
    "iso:country":"US",
    "sg:address":"6335 Shannon Pkwy",
    "sg:city":"Union City",
    "sg:phone":"+1 770 964 0074",
    "sg:postcode":"30291",
    "sg:province":"GA",
    "sg:tags":[
        "equipment",
        "retail",
        "commercial"
    ],
    "wof:name":"Ray Hill & Associates Inc",
    "wof:placetype":"venue"
},
  "geometry": {"coordinates":[-84.540217,33.583176],"type":"Point"}
}