{
  "type": "Feature",
  "properties": {
    "addr:full":"106 Mcfarland Ave Rossville GA 30741",
    "addr:housenumber":"106",
    "addr:postcode":"30741",
    "addr:street":"Mcfarland Ave",
    "iso:country":"US",
    "sg:address":"106 Mcfarland Ave",
    "sg:city":"Rossville",
    "sg:classifiers":[
        {
            "category":"Personal",
            "subcategory":"Beauty Salon",
            "type":"Services"
        }
    ],
    "sg:phone":"+1 706 866 9076",
    "sg:postcode":"30741",
    "sg:province":"GA",
    "wof:name":"Vickys Beauty Roundup",
    "wof:placetype":"venue"
},
  "geometry": {"coordinates":[-85.286805,34.983055],"type":"Point"}
}