{
  "type": "Feature",
  "properties": {
    "iso:country":"US",
    "sg:address":"3535 Chamblee Dunwoody Rd",
    "sg:city":"Atlanta",
    "sg:classifiers":[
        {
            "category":"Retail",
            "subcategory":"Auto Repair",
            "type":"Services"
        }
    ],
    "sg:phone":"+1 770 452 0850",
    "sg:postcode":"30341",
    "sg:province":"GA",
    "sg:website":"www.mecautoatlanta.com",
    "wof:name":"Mecauto Auto Repair",
    "wof:placetype":"venue"
},
  "geometry": {"coordinates":[-84.302696,33.894001],"type":"Point"}
}