{
  "type": "Feature",
  "properties": {
    "addr:full":"4807 Patterson Ln Gainesville GA 30506",
    "addr:housenumber":"4807",
    "addr:postcode":"30506",
    "addr:street":"Patterson Ln",
    "iso:country":"US",
    "sg:address":"4807 Patterson Ln",
    "sg:city":"Gainesville",
    "sg:classifiers":[
        {
            "category":"Organizations",
            "subcategory":"Religious Organization",
            "type":"Services"
        }
    ],
    "sg:phone":"+1 770 297 2800",
    "sg:postcode":"30506",
    "sg:province":"GA",
    "sg:tags":[
        "church"
    ],
    "wof:name":"Master's Table",
    "wof:placetype":"venue"
},
  "geometry": {"coordinates":[-83.92636899999999,34.396987],"type":"Point"}
}