{
  "type": "Feature",
  "properties": {
    "iso:country":"US",
    "sg:address":"326 Soperton Ave",
    "sg:city":"Dublin",
    "sg:classifiers":[
        {
            "category":"Freight",
            "type":"Transportation"
        }
    ],
    "sg:phone":"+1 478 296 7777",
    "sg:postcode":"31027",
    "sg:province":"GA",
    "sg:tags":[
        "trucking"
    ],
    "wof:name":"Acme Truck Line Inc",
    "wof:placetype":"venue"
},
  "geometry": {"coordinates":[-82.867079,32.544894],"type":"Point"}
}