{
  "type": "Feature",
  "properties": {
    "iso:country":"US",
    "sg:address":"3904 N Druid Hills Rd",
    "sg:city":"Decatur",
    "sg:classifiers":[
        {
            "category":"Building & Trades",
            "subcategory":"Electrical",
            "type":"Services"
        }
    ],
    "sg:phone":"+1 404 292 4996",
    "sg:postcode":"30033",
    "sg:province":"GA",
    "sg:tags":[
        "electrical",
        "contractor"
    ],
    "wof:name":"Laurence Electrical Contrs",
    "wof:placetype":"venue"
},
  "geometry": {"coordinates":[-84.273929,33.810607],"type":"Point"}
}