{
  "type": "Feature",
  "properties": {
    "addr:full":"42 Forsyth St NW Atlanta GA 30303",
    "addr:housenumber":"42",
    "addr:postcode":"30303",
    "addr:street":"Forsyth St Nw",
    "iso:country":"US",
    "sg:address":"42 Forsyth St NW",
    "sg:city":"Atlanta",
    "sg:classifiers":[
        {
            "category":"Retail",
            "subcategory":"Portrait Studio",
            "type":"Services"
        }
    ],
    "sg:phone":"+1 404 688 2815",
    "sg:postcode":"30303",
    "sg:province":"GA",
    "sg:tags":[
        "photo"
    ],
    "wof:name":"Harrys Photography",
    "wof:placetype":"venue"
},
  "geometry": {"coordinates":[-84.39084,33.755613],"type":"Point"}
}