{
  "type": "Feature",
  "properties": {
    "addr:full":"300 Parkbrooke Pl Woodstock GA 30189",
    "addr:housenumber":"300",
    "addr:postcode":"30189",
    "addr:street":"Parkbrooke Pl",
    "iso:country":"US",
    "sg:address":"300 Parkbrooke Pl",
    "sg:city":"Woodstock",
    "sg:classifiers":[
        {
            "category":"Professional",
            "subcategory":"Lawyer & Legal Services",
            "type":"Services"
        }
    ],
    "sg:phone":"+1 770 592 3372",
    "sg:postcode":"30189",
    "sg:province":"GA",
    "sg:tags":[
        "attorney",
        "real estate"
    ],
    "wof:name":"Morris Hardwick Schneider Towne Lake",
    "wof:placetype":"venue"
},
  "geometry": {"coordinates":[-84.556049,34.11116],"type":"Point"}
}