{
  "type": "Feature",
  "properties": {
    "iso:country":"US",
    "sg:address":"814 Cape Cod Ct",
    "sg:city":"Evans",
    "sg:classifiers":[
        {
            "category":"Wholesale",
            "subcategory":"Home Furnishings",
            "type":"Manufacturing & Wholesale Goods"
        }
    ],
    "sg:phone":"+1 706 863 4739",
    "sg:postcode":"30809",
    "sg:province":"GA",
    "sg:tags":[
        "durable"
    ],
    "wof:name":"Global Imports",
    "wof:placetype":"venue"
},
  "geometry": {"coordinates":[-82.132378,33.555948],"type":"Point"}
}