{
  "type": "Feature",
  "properties": {
    "iso:country":"US",
    "sg:address":"5815 Westwood Dr",
    "sg:city":"Cumming",
    "sg:classifiers":[
        {
            "category":"Building & Trades",
            "subcategory":"Construction",
            "type":"Services"
        }
    ],
    "sg:phone":"+1 678 947 6048",
    "sg:postcode":"30040",
    "sg:province":"GA",
    "sg:tags":[
        "house"
    ],
    "wof:name":"Bridgeton Homes Properties",
    "wof:placetype":"venue"
},
  "geometry": {"coordinates":[-84.16691299999999,34.273312],"type":"Point"}
}