{
  "type": "Feature",
  "properties": {
    "iso:country":"US",
    "sg:address":"3658 Windy Ct",
    "sg:city":"Tucker",
    "sg:classifiers":[
        {
            "category":"Professional",
            "subcategory":"Computer Services",
            "type":"Services"
        }
    ],
    "sg:phone":"+1 770 414 8834",
    "sg:postcode":"30084",
    "sg:province":"GA",
    "sg:tags":[
        "datum",
        "programing",
        "custom"
    ],
    "wof:name":"Merit Online Systems Inc",
    "wof:placetype":"venue"
},
  "geometry": {"coordinates":[-84.23837399999999,33.854316],"type":"Point"}
}