{
  "type": "Feature",
  "properties": {
    "iso:country":"US",
    "sg:address":"1007 Mansell Rd",
    "sg:city":"Roswell",
    "sg:classifiers":[
        {
            "category":"Education",
            "subcategory":"Dance Studio",
            "type":"Public Place"
        }
    ],
    "sg:phone":"+1 770 552 8002",
    "sg:postcode":"30076",
    "sg:province":"GA",
    "wof:name":"Ballet Rotaru",
    "wof:placetype":"venue"
},
  "geometry": {"coordinates":[-84.330817,34.042612],"type":"Point"}
}