{
  "type": "Feature",
  "properties": {
    "iso:country":"US",
    "sg:address":"410 W Roosevelt Ave",
    "sg:city":"Albany",
    "sg:classifiers":[
        {
            "category":"Professional",
            "subcategory":"Credit Reporting & Collection",
            "type":"Services"
        }
    ],
    "sg:phone":"+1 229 420 0602",
    "sg:postcode":"31701",
    "sg:province":"GA",
    "sg:tags":[
        "agency"
    ],
    "wof:name":"Credit Managemnet Svc",
    "wof:placetype":"venue"
},
  "geometry": {"coordinates":[-84.1587,31.58147],"type":"Point"}
}