{
  "type": "Feature",
  "properties": {
    "addr:full":"5982 Old Dixie Hwy Forest Park GA 30297",
    "addr:housenumber":"5982",
    "addr:postcode":"30297",
    "addr:street":"Old Dixie Hwy",
    "iso:country":"US",
    "sg:address":"5982 Old Dixie Hwy",
    "sg:city":"Forest Park",
    "sg:classifiers":[
        {
            "category":"Restaurant",
            "type":"Food & Drink"
        }
    ],
    "sg:phone":"+1 404 363 3222",
    "sg:postcode":"30297",
    "sg:province":"GA",
    "sg:tags":[
        "eating"
    ],
    "wof:name":"Los Jarritos",
    "wof:placetype":"venue"
},
  "geometry": {"coordinates":[-84.377398,33.59476],"type":"Point"}
}