{
  "type": "Feature",
  "properties": {
    "addr:full":"110 Carnegie Pl Fayetteville GA 30214",
    "addr:housenumber":"110",
    "addr:postcode":"30214",
    "addr:street":"Carnegie Pl",
    "iso:country":"US",
    "sg:address":"110 Carnegie Pl",
    "sg:city":"Fayetteville",
    "sg:classifiers":[
        {
            "category":"Home & Garden",
            "subcategory":"Home Furnishings",
            "type":"Retail Goods"
        }
    ],
    "sg:phone":"+1 770 716 3399",
    "sg:postcode":"30214",
    "sg:province":"GA",
    "sg:tags":[
        "bath",
        "cutlery",
        "kitchen"
    ],
    "sg:website":"www.cutco.com",
    "wof:name":"Cutco Cutlery Distributors",
    "wof:placetype":"venue"
},
  "geometry": {"coordinates":[-84.429104,33.509592],"type":"Point"}
}