{
  "type": "Feature",
  "properties": {
    "addr:full":"3581 McDonald St Atlanta GA 30337",
    "addr:housenumber":"3581",
    "addr:postcode":"30337",
    "addr:street":"Mcdonald St",
    "iso:country":"US",
    "sg:address":"3581 McDonald St",
    "sg:city":"Atlanta",
    "sg:classifiers":[
        {
            "category":"Organizations",
            "subcategory":"Religious Organization",
            "type":"Services"
        }
    ],
    "sg:phone":"+1 404 768 5090",
    "sg:postcode":"30337",
    "sg:province":"GA",
    "sg:tags":[
        "church"
    ],
    "wof:name":"Liberty Church God In Christ",
    "wof:placetype":"venue"
},
  "geometry": {"coordinates":[-84.45870499999999,33.656411],"type":"Point"}
}