{
  "type": "Feature",
  "properties": {
    "addr:full":"631 Mitchell Rd Norcross GA 30071",
    "addr:housenumber":"631",
    "addr:postcode":"30071",
    "addr:street":"Mitchell Rd",
    "iso:country":"US",
    "sg:address":"631 Mitchell Rd",
    "sg:city":"Norcross",
    "sg:classifiers":[
        {
            "category":"Organizations",
            "subcategory":"Religious Organization",
            "type":"Services"
        }
    ],
    "sg:phone":"+1 770 849 3100",
    "sg:postcode":"30071",
    "sg:province":"GA",
    "wof:name":"Myung Sung Presbyterian Church",
    "wof:placetype":"venue"
},
  "geometry": {"coordinates":[-84.2015,33.933899],"type":"Point"}
}