{
  "type": "Feature",
  "properties": {
    "iso:country":"US",
    "sg:address":"2072 Hampton Trl SE",
    "sg:city":"Conyers",
    "sg:classifiers":[
        {
            "category":"Building & Trades",
            "subcategory":"Landscaping Services",
            "type":"Services"
        }
    ],
    "sg:phone":"+1 770 388 0193",
    "sg:postcode":"30013",
    "sg:province":"GA",
    "wof:name":"Country Classic Landscaping",
    "wof:placetype":"venue"
},
  "geometry": {"coordinates":[-83.98585799999999,33.59966],"type":"Point"}
}