{
  "type": "Feature",
  "properties": {
    "iso:country":"US",
    "sg:address":"4405 International Blvd NW",
    "sg:city":"Norcross",
    "sg:classifiers":[
        {
            "category":"Wholesale",
            "subcategory":"Apparel",
            "type":"Manufacturing & Wholesale Goods"
        }
    ],
    "sg:phone":"+1 770 564 2000",
    "sg:postcode":"30093",
    "sg:province":"GA",
    "sg:tags":[
        "piece"
    ],
    "wof:name":"Lodhia Center",
    "wof:placetype":"venue"
},
  "geometry": {"coordinates":[-84.14886199999999,33.931959],"type":"Point"}
}