{
  "type": "Feature",
  "properties": {
    "iso:country":"US",
    "sg:address":"1282 Industrial Blvd",
    "sg:city":"Gainesville",
    "sg:classifiers":[
        {
            "category":"Food & Beverages",
            "subcategory":"Groceries & Convenience Stores",
            "type":"Retail Goods"
        }
    ],
    "sg:phone":"+1 770 534 3176",
    "sg:postcode":"30501",
    "sg:province":"GA",
    "sg:tags":[
        "grocer"
    ],
    "wof:name":"LA Mexicana Supermarket",
    "wof:placetype":"venue"
},
  "geometry": {"coordinates":[-83.837581,34.273279],"type":"Point"}
}