{
  "type": "Feature",
  "properties": {
    "iso:country":"US",
    "sg:address":"971 Bramlett Way",
    "sg:city":"Powder Springs",
    "sg:classifiers":[
        {
            "category":"Professional",
            "subcategory":"Business Services",
            "type":"Services"
        }
    ],
    "sg:phone":"+1 770 947 8260",
    "sg:postcode":"30127",
    "sg:province":"GA",
    "wof:name":"Telecom Solutions of Georgia",
    "wof:placetype":"venue"
},
  "geometry": {"coordinates":[-84.732088,33.810199],"type":"Point"}
}