{
  "type": "Feature",
  "properties": {
    "iso:country":"US",
    "sg:address":"207 Summerwalk Pkwy",
    "sg:city":"Tucker",
    "sg:classifiers":[
        {
            "category":"Banks & Credit Unions",
            "subcategory":"Financial Services",
            "type":"Services"
        }
    ],
    "sg:phone":"+1 770 414 0566",
    "sg:postcode":"30084",
    "sg:province":"GA",
    "sg:tags":[
        "investor"
    ],
    "wof:name":"Al Noor Investments Inc",
    "wof:placetype":"venue"
},
  "geometry": {"coordinates":[-84.181541,33.865167],"type":"Point"}
}