{
  "type": "Feature",
  "properties": {
    "iso:country":"US",
    "sg:address":"777 Butts Mill Rd",
    "sg:city":"Pine Mountain",
    "sg:classifiers":[
        {
            "category":"Personal",
            "type":"Services"
        }
    ],
    "sg:phone":"+1 706 663 7672",
    "sg:postcode":"31822",
    "sg:province":"GA",
    "sg:tags":[
        "wedding",
        "chapel"
    ],
    "wof:name":"Greenwood Lodge LLC",
    "wof:placetype":"venue"
},
  "geometry": {"coordinates":[-84.871773,32.868689],"type":"Point"}
}