{
  "type": "Feature",
  "properties": {
    "addr:full":"5 Lakeview Dr Newnan GA 30263",
    "addr:housenumber":"5",
    "addr:postcode":"30263",
    "addr:street":"Lakeview Dr",
    "iso:country":"US",
    "sg:address":"5 Lakeview Dr",
    "sg:city":"Newnan",
    "sg:classifiers":[
        {
            "category":"Building & Trades",
            "subcategory":"Construction",
            "type":"Services"
        }
    ],
    "sg:phone":"+1 770 502 7779",
    "sg:postcode":"30263",
    "sg:province":"GA",
    "sg:tags":[
        "contractor"
    ],
    "wof:name":"Loftin General Contracting",
    "wof:placetype":"venue"
},
  "geometry": {"coordinates":[-84.807547,33.395126],"type":"Point"}
}