{
  "type": "Feature",
  "properties": {
    "iso:country":"US",
    "sg:address":"6240 Weatherly Dr NW",
    "sg:city":"Atlanta",
    "sg:classifiers":[
        {
            "category":"Professional",
            "type":"Services"
        }
    ],
    "sg:phone":"+1 404 255 2953",
    "sg:postcode":"30328",
    "sg:province":"GA",
    "sg:tags":[
        "arts",
        "artist"
    ],
    "wof:name":"Studio 7 North Visual Arts",
    "wof:placetype":"venue"
},
  "geometry": {"coordinates":[-84.414609,33.925392],"type":"Point"}
}