{
  "type": "Feature",
  "properties": {
    "iso:country":"US",
    "sg:address":"174 Henderson Ave",
    "sg:city":"Athens",
    "sg:classifiers":[
        {
            "category":"Social Services",
            "type":"Services"
        }
    ],
    "sg:phone":"+1 706 208 8066",
    "sg:postcode":"30605",
    "sg:province":"GA",
    "sg:tags":[
        "organization",
        "welfare"
    ],
    "wof:name":"Light",
    "wof:placetype":"venue"
},
  "geometry": {"coordinates":[-83.38466200000001,33.951173],"type":"Point"}
}