{
  "type": "Feature",
  "properties": {
    "addr:full":"3080 Jonquil Dr Smyrna GA 30080",
    "addr:housenumber":"3080",
    "addr:postcode":"30080",
    "addr:street":"Jonquil Dr",
    "iso:country":"US",
    "sg:address":"3080 Jonquil Dr",
    "sg:city":"Smyrna",
    "sg:classifiers":[
        {
            "category":"Wholesale",
            "subcategory":"Machinery & Supplies",
            "type":"Manufacturing & Wholesale Goods"
        }
    ],
    "sg:phone":"+1 770 919 7505",
    "sg:postcode":"30080",
    "sg:province":"GA",
    "sg:tags":[
        "sprinkler"
    ],
    "wof:name":"Roberts Fire Protection",
    "wof:placetype":"venue"
},
  "geometry": {"coordinates":[-84.504627,33.881499],"type":"Point"}
}