{
  "type": "Feature",
  "properties": {
    "iso:country":"US",
    "sg:address":"152 Birchwood Pass",
    "sg:city":"Canton",
    "sg:classifiers":[
        {
            "category":"Retail",
            "subcategory":"Portrait Studio",
            "type":"Services"
        }
    ],
    "sg:phone":"+1 770 720 8179",
    "sg:postcode":"30114",
    "sg:province":"GA",
    "sg:tags":[
        "photo"
    ],
    "wof:name":"Lamar Gee Photography",
    "wof:placetype":"venue"
},
  "geometry": {"coordinates":[-84.56206,34.179255],"type":"Point"}
}