{
  "type": "Feature",
  "properties": {
    "iso:country":"US",
    "sg:address":"3003 Rutledge Rd NW",
    "sg:city":"Kennesaw",
    "sg:classifiers":[
        {
            "category":"Personal",
            "type":"Services"
        },
        {
            "category":"Retail",
            "subcategory":"Storage",
            "type":"Services"
        }
    ],
    "sg:phone":"+1 877 258 8230",
    "sg:postcode":"30144",
    "sg:province":"GA",
    "sg:tags":[
        "self",
        "full",
        "commercial",
        "mover",
        "household"
    ],
    "sg:website":"http://www.publicstorage.com/?pid=ypcomCPCingenio",
    "wof:name":"Public Storage",
    "wof:placetype":"venue"
},
  "geometry": {"coordinates":[-84.63754400000001,34.026961],"type":"Point"}
}