{
  "type": "Feature",
  "properties": {
    "addr:full":"19 E Jones St Savannah GA 31401",
    "addr:housenumber":"19",
    "addr:postcode":"31401",
    "addr:street":"E Jones St",
    "iso:country":"US",
    "sg:address":"19 E Jones St",
    "sg:city":"Savannah",
    "sg:classifiers":[
        {
            "category":"Wholesale",
            "subcategory":"Durable Goods & Equipment",
            "type":"Manufacturing & Wholesale Goods"
        }
    ],
    "sg:phone":"+1 912 233 4756",
    "sg:postcode":"31401",
    "sg:province":"GA",
    "sg:tags":[
        "exporter"
    ],
    "sg:website":"www.intercitytransport.com",
    "wof:name":"Intercity Transport",
    "wof:placetype":"venue"
},
  "geometry": {"coordinates":[-81.09344900000001,32.072135],"type":"Point"}
}