{
  "type": "Feature",
  "properties": {
    "iso:country":"US",
    "sg:address":"495 E Broad St",
    "sg:city":"Metter",
    "sg:phone":"+1 912 685 3881",
    "sg:postcode":"30439",
    "sg:province":"GA",
    "sg:tags":[
        "gas"
    ],
    "wof:name":"Altamaha Propane Co",
    "wof:placetype":"venue"
},
  "geometry": {"coordinates":[-82.067044,32.397597],"type":"Point"}
}