{
  "type": "Feature",
  "properties": {
    "addr:full":"4401 Shallowford Rd Roswell GA 30075",
    "addr:housenumber":"4401",
    "addr:postcode":"30075",
    "addr:street":"Shallowford Rd",
    "iso:country":"US",
    "sg:address":"4401 Shallowford Rd",
    "sg:city":"Roswell",
    "sg:classifiers":[
        {
            "category":"Building & Trades",
            "subcategory":"Locksmith",
            "type":"Services"
        }
    ],
    "sg:phone":"+1 404 890 7285",
    "sg:postcode":"30075",
    "sg:province":"GA",
    "sg:tags":[
        "key"
    ],
    "wof:name":"24-Hours Emergency Locksmith",
    "wof:placetype":"venue"
},
  "geometry": {"coordinates":[-84.42388,34.027477],"type":"Point"}
}