{
  "type": "Feature",
  "properties": {
    "iso:country":"US",
    "sg:address":"3105 Mary Ann Way",
    "sg:city":"Lake Park",
    "sg:classifiers":[
        {
            "category":"Freight",
            "type":"Transportation"
        }
    ],
    "sg:phone":"+1 229 247 7528",
    "sg:postcode":"31636",
    "sg:province":"GA",
    "sg:tags":[
        "operator",
        "local",
        "trucking"
    ],
    "wof:name":"Ryanco Transport Inc",
    "wof:placetype":"venue"
},
  "geometry": {"coordinates":[-83.248959,30.740462],"type":"Point"}
}