{
  "type": "Feature",
  "properties": {
    "iso:country":"US",
    "sg:address":"755 Hank Aaron Dr SW",
    "sg:city":"Atlanta",
    "sg:classifiers":[
        {
            "category":"Communications",
            "subcategory":"Radio Station",
            "type":"Services"
        }
    ],
    "sg:phone":"+1 404 525 5713",
    "sg:postcode":"30315",
    "sg:province":"GA",
    "wof:name":"V-103 Radio Station",
    "wof:placetype":"venue"
},
  "geometry": {"coordinates":[-84.38804500000001,33.734431],"type":"Point"}
}