{
  "type": "Feature",
  "properties": {
    "addr:full":"610 Winans Walk Alpharetta GA 30022",
    "addr:housenumber":"610",
    "addr:postcode":"30022",
    "addr:street":"Winans Walk",
    "iso:country":"US",
    "sg:address":"610 Winans Walk",
    "sg:city":"Alpharetta",
    "sg:classifiers":[
        {
            "category":"Professional",
            "type":"Services"
        }
    ],
    "sg:phone":"+1 770 442 1341",
    "sg:postcode":"30022",
    "sg:province":"GA",
    "sg:tags":[
        "employee",
        "communications",
        "benefit",
        "corporate"
    ],
    "wof:name":"Lingo Inc Corporate",
    "wof:placetype":"venue"
},
  "geometry": {"coordinates":[-84.239783,34.042925],"type":"Point"}
}