{
  "type": "Feature",
  "properties": {
    "addr:full":"230 Lovett Ln Brunswick GA 31523",
    "addr:housenumber":"230",
    "addr:postcode":"31523",
    "addr:street":"Lovett Ln",
    "iso:country":"US",
    "sg:address":"230 Lovett Ln",
    "sg:city":"Brunswick",
    "sg:classifiers":[
        {
            "category":"Arts & Performance",
            "subcategory":"Theater",
            "type":"Entertainment"
        }
    ],
    "sg:phone":"+1 912 265 9340",
    "sg:postcode":"31523",
    "sg:province":"GA",
    "sg:tags":[
        "group"
    ],
    "wof:name":"E & C Entertainment Inc",
    "wof:placetype":"venue"
},
  "geometry": {"coordinates":[-81.63611,31.248223],"type":"Point"}
}