{
  "type": "Feature",
  "properties": {
    "addr:full":"2498 Grady School Rd Canon GA 30520",
    "addr:housenumber":"2498",
    "addr:postcode":"30520",
    "addr:street":"Grady School Rd",
    "iso:country":"US",
    "sg:address":"2498 Grady School Rd",
    "sg:city":"Canon",
    "sg:classifiers":[
        {
            "category":"Retail",
            "subcategory":"Repair Shop",
            "type":"Services"
        }
    ],
    "sg:phone":"+1 706 356 8565",
    "sg:postcode":"30520",
    "sg:province":"GA",
    "sg:tags":[
        "welding"
    ],
    "wof:name":"Herring Company",
    "wof:placetype":"venue"
},
  "geometry": {"coordinates":[-83.130966,34.393659],"type":"Point"}
}