{
  "type": "Feature",
  "properties": {
    "addr:full":"64 Broad Street NW Atlanta GA 30303",
    "addr:housenumber":"64",
    "addr:postcode":"30303",
    "addr:street":"Broad Street Nw",
    "iso:country":"US",
    "sg:address":"64 Broad Street NW",
    "sg:city":"Atlanta",
    "sg:classifiers":[
        {
            "category":"Restaurant",
            "type":"Food & Drink"
        }
    ],
    "sg:phone":"+1 404 688 8819",
    "sg:postcode":"30303",
    "sg:province":"GA",
    "wof:name":"Michaels' Deli Peachtree",
    "wof:placetype":"venue"
},
  "geometry": {"coordinates":[-84.389498,33.755668],"type":"Point"}
}