{
  "type": "Feature",
  "properties": {
    "iso:country":"US",
    "sg:address":"8385 Tatum Rd",
    "sg:city":"Palmetto",
    "sg:classifiers":[
        {
            "category":"Building & Trades",
            "subcategory":"Construction",
            "type":"Services"
        }
    ],
    "sg:phone":"+1 770 463 2974",
    "sg:postcode":"30268",
    "sg:province":"GA",
    "sg:tags":[
        "general",
        "contractor"
    ],
    "wof:name":"AVA Ind Contractors Inc",
    "wof:placetype":"venue"
},
  "geometry": {"coordinates":[-84.640568,33.531234],"type":"Point"}
}