{
  "type": "Feature",
  "properties": {
    "addr:full":"1914 Skidaway Rd Savannah GA 31404",
    "addr:housenumber":"1914",
    "addr:postcode":"31404",
    "addr:street":"Skidaway Rd",
    "iso:country":"US",
    "sg:address":"1914 Skidaway Rd",
    "sg:city":"Savannah",
    "sg:classifiers":[
        {
            "category":"Social Services",
            "subcategory":"Adult Care",
            "type":"Services"
        }
    ],
    "sg:phone":"+1 912 232 2070",
    "sg:postcode":"31404",
    "sg:province":"GA",
    "sg:tags":[
        "home",
        "group"
    ],
    "wof:name":"Palani's Group Home",
    "wof:placetype":"venue"
},
  "geometry": {"coordinates":[-81.066755,32.052871],"type":"Point"}
}