{
  "type": "Feature",
  "properties": {
    "addr:full":"4523 Hunting Hound Ln Marietta GA 30062",
    "addr:housenumber":"4523",
    "addr:postcode":"30062",
    "addr:street":"Hunting Hound Ln",
    "iso:country":"US",
    "sg:address":"4523 Hunting Hound Ln",
    "sg:city":"Marietta",
    "sg:classifiers":[
        {
            "category":"Building & Trades",
            "subcategory":"Landscaping Services",
            "type":"Services"
        }
    ],
    "sg:phone":"+1 770 993 2100",
    "sg:postcode":"30062",
    "sg:province":"GA",
    "wof:name":"Beaver Creek Farms",
    "wof:placetype":"venue"
},
  "geometry": {"coordinates":[-84.415391,34.004417],"type":"Point"}
}