{
  "type": "Feature",
  "properties": {
    "iso:country":"US",
    "sg:address":"316 Cooper Rd",
    "sg:city":"Pelham",
    "sg:classifiers":[
        {
            "category":"Freight",
            "type":"Transportation"
        }
    ],
    "sg:phone":"+1 229 294 7084",
    "sg:postcode":"31779",
    "sg:province":"GA",
    "sg:tags":[
        "operator",
        "local",
        "trucking"
    ],
    "wof:name":"White Trucking Co",
    "wof:placetype":"venue"
},
  "geometry": {"coordinates":[-84.16162799999999,31.033408],"type":"Point"}
}