{
  "type": "Feature",
  "properties": {
    "addr:full":"101 Devant St Fayetteville GA 30214",
    "addr:housenumber":"101",
    "addr:postcode":"30214",
    "addr:street":"Devant St",
    "iso:country":"US",
    "sg:address":"101 Devant St",
    "sg:city":"Fayetteville",
    "sg:classifiers":[
        {
            "category":"Building & Trades",
            "subcategory":"Construction",
            "type":"Services"
        }
    ],
    "sg:phone":"+1 770 460 7858",
    "sg:postcode":"30214",
    "sg:province":"GA",
    "sg:tags":[
        "interior",
        "design"
    ],
    "wof:name":"Paradise Interiors",
    "wof:placetype":"venue"
},
  "geometry": {"coordinates":[-84.482314,33.449397],"type":"Point"}
}