{
  "type": "Feature",
  "properties": {
    "addr:full":"5433 Goshen Springs Rd Norcross GA 30093",
    "addr:housenumber":"5433",
    "addr:postcode":"30093",
    "addr:street":"Goshen Springs Rd",
    "iso:country":"US",
    "sg:address":"5433 Goshen Springs Rd",
    "sg:city":"Norcross",
    "sg:classifiers":[
        {
            "category":"Wholesale",
            "subcategory":"Machinery & Supplies",
            "type":"Manufacturing & Wholesale Goods"
        }
    ],
    "sg:phone":"+1 770 925 3031",
    "sg:postcode":"30093",
    "sg:province":"GA",
    "sg:tags":[
        "contractor"
    ],
    "wof:name":"Georgia Industrial Trading Co",
    "wof:placetype":"venue"
},
  "geometry": {"coordinates":[-84.183296,33.923676],"type":"Point"}
}