{
  "type": "Feature",
  "properties": {
    "iso:country":"US",
    "sg:address":"6920 McGinnis Ferry Rd",
    "sg:city":"Suwanee",
    "sg:classifiers":[
        {
            "category":"Health Services",
            "subcategory":"Doctor",
            "type":"Services"
        }
    ],
    "sg:phone":"+1 770 521 2229",
    "sg:postcode":"30024",
    "sg:province":"GA",
    "sg:tags":[
        "obstetrician",
        "gynecologist"
    ],
    "sg:website":"www.isisobgyn.com",
    "wof:name":"ISIS Ob/gyn",
    "wof:placetype":"venue"
},
  "geometry": {"coordinates":[-84.16595100000001,34.067444],"type":"Point"}
}