{
  "type": "Feature",
  "properties": {
    "addr:full":"1203 Hollywood Rd NW Atlanta GA 30318",
    "addr:housenumber":"1203",
    "addr:postcode":"30318",
    "addr:street":"Hollywood Rd Nw",
    "iso:country":"US",
    "sg:address":"1203 Hollywood Rd NW",
    "sg:city":"Atlanta",
    "sg:classifiers":[
        {
            "category":"Organizations",
            "subcategory":"Religious Organization",
            "type":"Services"
        }
    ],
    "sg:phone":"+1 404 792 1329",
    "sg:postcode":"30318",
    "sg:province":"GA",
    "wof:name":"New Cedar Creek Baptist Church",
    "wof:placetype":"venue"
},
  "geometry": {"coordinates":[-84.46349600000001,33.787363],"type":"Point"}
}