{
  "type": "Feature",
  "properties": {
    "iso:country":"US",
    "sg:address":"6301 Meryton Park",
    "sg:city":"Dallas",
    "sg:classifiers":[
        {
            "category":"Professional",
            "subcategory":"Computer Services",
            "type":"Services"
        }
    ],
    "sg:phone":"+1 770 445 8385",
    "sg:postcode":"30157",
    "sg:province":"GA",
    "sg:tags":[
        "related"
    ],
    "wof:name":"Solomon Consulting Inc",
    "wof:placetype":"venue"
},
  "geometry": {"coordinates":[-84.73654399999999,33.948741],"type":"Point"}
}