{
  "type": "Feature",
  "properties": {
    "iso:country":"US",
    "sg:address":"106 Plantation Dr",
    "sg:city":"Waycross",
    "sg:phone":"+1 912 285 1327",
    "sg:postcode":"31501",
    "sg:province":"GA",
    "sg:tags":[
        "equipment",
        "commercial"
    ],
    "wof:name":"Raines Equipment Corporation",
    "wof:placetype":"venue"
},
  "geometry": {"coordinates":[-82.32673699999999,31.218439],"type":"Point"}
}