{
  "type": "Feature",
  "properties": {
    "addr:full":"240 Bayberry Run Fairburn GA 30213",
    "addr:housenumber":"240",
    "addr:postcode":"30213",
    "addr:street":"Bayberry Run",
    "iso:country":"US",
    "sg:address":"240 Bayberry Run",
    "sg:city":"Fairburn",
    "sg:classifiers":[
        {
            "category":"Professional",
            "type":"Services"
        }
    ],
    "sg:phone":"+1 678 817 9710",
    "sg:postcode":"30213",
    "sg:province":"GA",
    "wof:name":"A Matter of Money Inc",
    "wof:placetype":"venue"
},
  "geometry": {"coordinates":[-84.46307899999999,33.529668],"type":"Point"}
}