{
  "type": "Feature",
  "properties": {
    "addr:full":"420 Springwood Ct Canton GA 30115",
    "addr:housenumber":"420",
    "addr:postcode":"30115",
    "addr:street":"Springwood Ct",
    "iso:country":"US",
    "sg:address":"420 Springwood Ct",
    "sg:city":"Canton",
    "sg:classifiers":[
        {
            "category":"Professional",
            "type":"Services"
        }
    ],
    "sg:phone":"+1 770 345 7265",
    "sg:postcode":"30115",
    "sg:province":"GA",
    "sg:tags":[
        "business"
    ],
    "wof:name":"Zellman Productions",
    "wof:placetype":"venue"
},
  "geometry": {"coordinates":[-84.47632900000001,34.190862],"type":"Point"}
}