{
  "type": "Feature",
  "properties": {
    "iso:country":"US",
    "sg:address":"76 Salem Rd",
    "sg:city":"Culloden",
    "sg:classifiers":[
        {
            "category":"Professional",
            "type":"Services"
        }
    ],
    "sg:phone":"+1 478 836 5927",
    "sg:postcode":"31016",
    "sg:province":"GA",
    "wof:name":"Christine Jordan",
    "wof:placetype":"venue"
},
  "geometry": {"coordinates":[-84.177413,32.751878],"type":"Point"}
}