{
  "type": "Feature",
  "properties": {
    "addr:full":"2685 Metropolitan Pkwy SW Atlanta GA 30315",
    "addr:housenumber":"2685",
    "addr:postcode":"30315",
    "addr:street":"Metropolitan Pkwy Sw",
    "iso:country":"US",
    "sg:address":"2685 Metropolitan Pkwy SW",
    "sg:city":"Atlanta",
    "sg:classifiers":[
        {
            "category":"Banks & Credit Unions",
            "subcategory":"Bank",
            "type":"Services"
        }
    ],
    "sg:phone":"+1 404 768 9696",
    "sg:postcode":"30315",
    "sg:province":"GA",
    "sg:tags":[
        "financing"
    ],
    "wof:name":"Sneedgo Business Capital",
    "wof:placetype":"venue"
},
  "geometry": {"coordinates":[-84.40784499999999,33.68264],"type":"Point"}
}