{
  "type": "Feature",
  "properties": {
    "iso:country":"US",
    "sg:address":"68 N Main St",
    "sg:city":"Clayton",
    "sg:classifiers":[
        {
            "category":"Shopping",
            "subcategory":"Gifts & Souvenirs",
            "type":"Retail Goods"
        }
    ],
    "sg:phone":"+1 706 212 0081",
    "sg:postcode":"30525",
    "sg:province":"GA",
    "sg:tags":[
        "shop"
    ],
    "wof:name":"Blossom Creek Gifts",
    "wof:placetype":"venue"
},
  "geometry": {"coordinates":[-83.400842,34.87927],"type":"Point"}
}