{
  "type": "Feature",
  "properties": {
    "iso:country":"US",
    "sg:address":"3819 Oak Dr",
    "sg:city":"Augusta",
    "sg:classifiers":[
        {
            "category":"Wholesale",
            "subcategory":"Office Equipment",
            "type":"Manufacturing & Wholesale Goods"
        },
        {
            "category":"Wholesale",
            "subcategory":"Electrical",
            "type":"Manufacturing & Wholesale Goods"
        }
    ],
    "sg:phone":"+1 706 651 9600",
    "sg:postcode":"30907",
    "sg:province":"GA",
    "sg:tags":[
        "fire",
        "alarm",
        "electronic",
        "system"
    ],
    "wof:name":"Southeastern System Tchnlgs",
    "wof:placetype":"venue"
},
  "geometry": {"coordinates":[-82.085525,33.50882],"type":"Point"}
}