{
  "type": "Feature",
  "properties": {
    "addr:full":"1119 Forrester Dr SE Dawson GA 39842",
    "addr:housenumber":"1119",
    "addr:postcode":"39842",
    "addr:street":"Forrester Dr Se",
    "iso:country":"US",
    "sg:address":"1119 Forrester Dr SE",
    "sg:city":"Dawson",
    "sg:classifiers":[
        {
            "category":"Autos & Motor Vehicles",
            "subcategory":"Automobile Sales",
            "type":"Retail Goods"
        }
    ],
    "sg:phone":"+1 229 995 2156",
    "sg:postcode":"39842",
    "sg:province":"GA",
    "sg:tags":[
        "car",
        "dealer"
    ],
    "wof:name":"Childre Chevrolet Olds Pontiac",
    "wof:placetype":"venue"
},
  "geometry": {"coordinates":[-84.432481,31.75946],"type":"Point"}
}