{
  "type": "Feature",
  "properties": {
    "addr:full":"229 E College St Griffin GA 30224",
    "addr:housenumber":"229",
    "addr:postcode":"30224",
    "addr:street":"E College St",
    "iso:country":"US",
    "sg:address":"229 E College St",
    "sg:city":"Griffin",
    "sg:classifiers":[
        {
            "category":"Real Estate",
            "subcategory":"Real Estate Agent",
            "type":"Services"
        }
    ],
    "sg:phone":"+1 770 229 9348",
    "sg:postcode":"30224",
    "sg:province":"GA",
    "wof:name":"Anthony R Singletary & Assoc",
    "wof:placetype":"venue"
},
  "geometry": {"coordinates":[-84.258465,33.243304],"type":"Point"}
}