{
  "type": "Feature",
  "properties": {
    "addr:full":"1442 Johnson Mill Rd Jefferson GA 30549",
    "addr:housenumber":"1442",
    "addr:postcode":"30549",
    "addr:street":"Johnson Mill Rd",
    "iso:country":"US",
    "sg:address":"1442 Johnson Mill Rd",
    "sg:city":"Jefferson",
    "sg:classifiers":[
        {
            "category":"Health Services",
            "subcategory":"Nursing And Care Facility",
            "type":"Services"
        },
        {
            "category":"Social Services",
            "subcategory":"Retirement Home",
            "type":"Services"
        }
    ],
    "sg:phone":"+1 706 367 0300",
    "sg:postcode":"30549",
    "sg:province":"GA",
    "sg:tags":[
        "personal",
        "convalescent"
    ],
    "wof:name":"Serenity At Jefferson",
    "wof:placetype":"venue"
},
  "geometry": {"coordinates":[-83.594776,34.06972],"type":"Point"}
}