{
  "type": "Feature",
  "properties": {
    "iso:country":"US",
    "sg:address":"4371 Glenwood Rd",
    "sg:city":"Decatur",
    "sg:classifiers":[
        {
            "category":"Real Estate",
            "subcategory":"Real Estate Operator",
            "type":"Services"
        }
    ],
    "sg:phone":"+1 404 288 1087",
    "sg:postcode":"30032",
    "sg:province":"GA",
    "sg:tags":[
        "apartment"
    ],
    "wof:name":"Victory Crossing Apartments",
    "wof:placetype":"venue"
},
  "geometry": {"coordinates":[-84.242339,33.737604],"type":"Point"}
}