{
  "type": "Feature",
  "properties": {
    "addr:full":"2451 Peachtree Road NE Atlanta GA 30305",
    "addr:housenumber":"2451",
    "addr:postcode":"30305",
    "addr:street":"Peachtree Road Ne",
    "iso:country":"US",
    "sg:address":"2451 Peachtree Road NE",
    "sg:city":"Atlanta",
    "sg:classifiers":[
        {
            "category":"Food & Beverages",
            "subcategory":"Groceries & Convenience Stores",
            "type":"Retail Goods"
        }
    ],
    "sg:phone":"+1 404 233 3799",
    "sg:postcode":"30305",
    "sg:province":"GA",
    "wof:name":"E-Z Serve Convenience Stores",
    "wof:placetype":"venue"
},
  "geometry": {"coordinates":[-84.388189,33.821102],"type":"Point"}
}