{
  "type": "Feature",
  "properties": {
    "addr:full":"957 Mcdonald Cir Commerce GA 30529",
    "addr:housenumber":"957",
    "addr:postcode":"30529",
    "addr:street":"Mcdonald Cir",
    "iso:country":"US",
    "sg:address":"957 Mcdonald Cir",
    "sg:city":"Commerce",
    "sg:classifiers":[
        {
            "category":"Farming",
            "subcategory":"Livestock Farm",
            "type":"Manufacturing & Wholesale Goods"
        }
    ],
    "sg:phone":"+1 706 870 0532",
    "sg:postcode":"30529",
    "sg:province":"GA",
    "wof:name":"Wayne Coker",
    "wof:placetype":"venue"
},
  "geometry": {"coordinates":[-83.483283,34.290133],"type":"Point"}
}