{
  "type": "Feature",
  "properties": {
    "iso:country":"US",
    "sg:address":"5125 Highway 85",
    "sg:city":"Atlanta",
    "sg:classifiers":[
        {
            "category":"Wholesale",
            "subcategory":"Machinery & Supplies",
            "type":"Manufacturing & Wholesale Goods"
        }
    ],
    "sg:phone":"+1 404 763 0233",
    "sg:postcode":"30349",
    "sg:province":"GA",
    "sg:tags":[
        "generators-electric"
    ],
    "wof:name":"Cummins-Onan South Inc",
    "wof:placetype":"venue"
},
  "geometry": {"coordinates":[-84.402962,33.614059],"type":"Point"}
}