{
  "type": "Feature",
  "properties": {
    "iso:country":"US",
    "sg:address":"2700 Main St S",
    "sg:city":"Tifton",
    "sg:classifiers":[
        {
            "category":"Wholesale",
            "subcategory":"Auto Parts",
            "type":"Manufacturing & Wholesale Goods"
        }
    ],
    "sg:phone":"+1 229 387 6283",
    "sg:postcode":"31794",
    "sg:province":"GA",
    "sg:tags":[
        "tire"
    ],
    "wof:name":"Southside Used Tires",
    "wof:placetype":"venue"
},
  "geometry": {"coordinates":[-83.502956,31.43733],"type":"Point"}
}