{
  "type": "Feature",
  "properties": {
    "iso:country":"US",
    "sg:address":"2220 Atlanta Rd SE",
    "sg:city":"Smyrna",
    "sg:classifiers":[
        {
            "category":"Professional",
            "subcategory":"Business Services",
            "type":"Services"
        }
    ],
    "sg:phone":"+1 678 305 1144",
    "sg:postcode":"30080",
    "sg:province":"GA",
    "sg:tags":[
        "translator",
        "interpreter"
    ],
    "wof:name":"Servicios Hispanos En General",
    "wof:placetype":"venue"
},
  "geometry": {"coordinates":[-84.524035,33.901589],"type":"Point"}
}