{
  "type": "Feature",
  "properties": {
    "iso:country":"US",
    "sg:address":"5535 Chamblee Dunwoody Rd",
    "sg:city":"Atlanta",
    "sg:classifiers":[
        {
            "category":"Personal",
            "subcategory":"Barber",
            "type":"Services"
        }
    ],
    "sg:phone":"+1 770 396 4805",
    "sg:postcode":"30338",
    "sg:province":"GA",
    "wof:name":"Dunwoody Village Barber & Style Shop",
    "wof:placetype":"venue"
},
  "geometry": {"coordinates":[-84.33609800000001,33.948898],"type":"Point"}
}