{
  "type": "Feature",
  "properties": {
    "addr:full":"2307 Desmond Dr Decatur GA 30033",
    "addr:housenumber":"2307",
    "addr:postcode":"30033",
    "addr:street":"Desmond Dr",
    "iso:country":"US",
    "sg:address":"2307 Desmond Dr",
    "sg:city":"Decatur",
    "sg:classifiers":[
        {
            "category":"Health Services",
            "subcategory":"Clinic",
            "type":"Services"
        }
    ],
    "sg:phone":"+1 404 320 9548",
    "sg:postcode":"30033",
    "sg:province":"GA",
    "sg:tags":[
        "counseling",
        "mental"
    ],
    "sg:website":"www.debelkin.com",
    "wof:name":"Deb Elkin, LPC",
    "wof:placetype":"venue"
},
  "geometry": {"coordinates":[-84.29462700000001,33.80004],"type":"Point"}
}