{
  "type": "Feature",
  "properties": {
    "iso:country":"US",
    "sg:address":"6712 W Fayetteville Rd",
    "sg:city":"Riverdale",
    "sg:classifiers":[
        {
            "category":"Organizations",
            "subcategory":"Religious Organization",
            "type":"Services"
        }
    ],
    "sg:phone":"+1 770 997 0079",
    "sg:postcode":"30296",
    "sg:province":"GA",
    "sg:tags":[
        "church"
    ],
    "wof:name":"Fountain Of Faith Missionary",
    "wof:placetype":"venue"
},
  "geometry": {"coordinates":[-84.448221,33.570814],"type":"Point"}
}