{
  "type": "Feature",
  "properties": {
    "iso:country":"US",
    "sg:address":"7073 Mount Carmel Rd",
    "sg:city":"Gay",
    "sg:classifiers":[
        {
            "category":"Building & Trades",
            "subcategory":"Cleaning & Sanitation",
            "type":"Services"
        }
    ],
    "sg:phone":"+1 706 538 0294",
    "sg:postcode":"30218",
    "sg:province":"GA",
    "sg:tags":[
        "janitor"
    ],
    "wof:name":"All Clean Cleaning Svc",
    "wof:placetype":"venue"
},
  "geometry": {"coordinates":[-84.536616,33.157909],"type":"Point"}
}