{
  "type": "Feature",
  "properties": {
    "addr:full":"116 Stephen Dr Toccoa GA 30577",
    "addr:housenumber":"116",
    "addr:postcode":"30577",
    "addr:street":"Stephen Dr",
    "iso:country":"US",
    "sg:address":"116 Stephen Dr",
    "sg:city":"Toccoa",
    "sg:classifiers":[
        {
            "category":"Wholesale",
            "subcategory":"Electrical",
            "type":"Manufacturing & Wholesale Goods"
        }
    ],
    "sg:phone":"+1 706 886 9754",
    "sg:postcode":"30577",
    "sg:province":"GA",
    "sg:tags":[
        "alarm",
        "burglar",
        "system"
    ],
    "sg:website":"www.absolutesecuritysystems.com",
    "wof:name":"Absolute Security Systems Inc",
    "wof:placetype":"venue"
},
  "geometry": {"coordinates":[-83.312748,34.570116],"type":"Point"}
}