{
  "type": "Feature",
  "properties": {
    "iso:country":"US",
    "sg:address":"8829 Gurley Rd",
    "sg:city":"Douglasville",
    "sg:classifiers":[
        {
            "category":"Autos & Motor Vehicles",
            "subcategory":"Automobile Sales",
            "type":"Retail Goods"
        }
    ],
    "sg:phone":"+1 678 715 7733",
    "sg:postcode":"30134",
    "sg:province":"GA",
    "sg:tags":[
        "car",
        "dealer"
    ],
    "wof:name":"Modern Auto Design",
    "wof:placetype":"venue"
},
  "geometry": {"coordinates":[-84.77146999999999,33.743521],"type":"Point"}
}