{
  "type": "Feature",
  "properties": {
    "addr:full":"200 W Park Dr Peachtree City GA 30269",
    "addr:housenumber":"200",
    "addr:postcode":"30269",
    "addr:street":"W Park Dr",
    "iso:country":"US",
    "sg:address":"200 W Park Dr",
    "sg:city":"Peachtree City",
    "sg:classifiers":[
        {
            "category":"Manufacturing",
            "subcategory":"Tools & Machinery",
            "type":"Manufacturing & Wholesale Goods"
        }
    ],
    "sg:phone":"+1 770 631 0909",
    "sg:postcode":"30269",
    "sg:province":"GA",
    "sg:tags":[
        "computer",
        "mfg"
    ],
    "wof:name":"S G I",
    "wof:placetype":"venue"
},
  "geometry": {"coordinates":[-84.59481,33.400529],"type":"Point"}
}