{
  "type": "Feature",
  "properties": {
    "addr:full":"270 Graystone Way Alpharetta GA 30005",
    "addr:housenumber":"270",
    "addr:postcode":"30005",
    "addr:street":"Graystone Way",
    "iso:country":"US",
    "sg:address":"270 Graystone Way",
    "sg:city":"Alpharetta",
    "sg:classifiers":[
        {
            "category":"Wholesale",
            "subcategory":"Machinery & Supplies",
            "type":"Manufacturing & Wholesale Goods"
        }
    ],
    "sg:phone":"+1 770 664 4290",
    "sg:postcode":"30005",
    "sg:province":"GA",
    "sg:tags":[
        "food",
        "equipment",
        "processing",
        "baking"
    ],
    "wof:name":"Reading Bakery System",
    "wof:placetype":"venue"
},
  "geometry": {"coordinates":[-84.221018,34.092416],"type":"Point"}
}