{
  "type": "Feature",
  "properties": {
    "iso:country":"US",
    "sg:address":"4530 S Berkeley Lake Rd Ste B",
    "sg:city":"Norcross",
    "sg:classifiers":[
        {
            "category":"Health Services",
            "subcategory":"Doctor",
            "type":"Services"
        }
    ],
    "sg:phone":"+1 770 446 5642",
    "sg:postcode":"30071",
    "sg:province":"GA",
    "sg:tags":[
        "psychiatrist"
    ],
    "wof:name":"Bower Susan L MD",
    "wof:placetype":"venue"
},
  "geometry": {"coordinates":[-84.183587,33.971459],"type":"Point"}
}