{
  "type": "Feature",
  "properties": {
    "addr:full":"85 Riverside Lndg Macon GA 31210",
    "addr:housenumber":"85",
    "addr:postcode":"31210",
    "addr:street":"Riverside Lndg",
    "iso:country":"US",
    "sg:address":"85 Riverside Lndg",
    "sg:city":"Macon",
    "sg:classifiers":[
        {
            "category":"Structure",
            "subcategory":"Office Building",
            "type":"Public Place"
        }
    ],
    "sg:phone":"+1 478 238 0488",
    "sg:postcode":"31210",
    "sg:province":"GA",
    "sg:tags":[
        "park"
    ],
    "wof:name":"Polla Properties One",
    "wof:placetype":"venue"
},
  "geometry": {"coordinates":[-83.74101,32.955691],"type":"Point"}
}