{
  "type": "Feature",
  "properties": {
    "iso:country":"US",
    "sg:address":"7411 Airport Dr",
    "sg:city":"Macon",
    "sg:classifiers":[
        {
            "category":"Professional",
            "subcategory":"Engineering",
            "type":"Services"
        }
    ],
    "sg:phone":"+1 478 784 0777",
    "sg:postcode":"31216",
    "sg:province":"GA",
    "sg:tags":[
        "engineer"
    ],
    "wof:name":"Richard Funk & Assoc",
    "wof:placetype":"venue"
},
  "geometry": {"coordinates":[-83.649269,32.710405],"type":"Point"}
}