{
  "type": "Feature",
  "properties": {
    "addr:full":"1700 McCoba Dr SE Smyrna GA 30080",
    "addr:housenumber":"1700",
    "addr:postcode":"30080",
    "addr:street":"Mccoba Dr Se",
    "iso:country":"US",
    "sg:address":"1700 McCoba Dr SE",
    "sg:city":"Smyrna",
    "sg:classifiers":[
        {
            "category":"Wholesale",
            "subcategory":"Durable Goods & Equipment",
            "type":"Manufacturing & Wholesale Goods"
        }
    ],
    "sg:phone":"+1 678 305 7400",
    "sg:postcode":"30080",
    "sg:province":"GA",
    "sg:tags":[
        "importer"
    ],
    "wof:name":"Tiger Import Export LLC",
    "wof:placetype":"venue"
},
  "geometry": {"coordinates":[-84.505105,33.890025],"type":"Point"}
}