{
  "type": "Feature",
  "properties": {
    "iso:country":"US",
    "sg:address":"1144 State Rte 81 E",
    "sg:city":"Mcdonough",
    "sg:classifiers":[
        {
            "category":"Shopping",
            "subcategory":"Computers & Home Electronics",
            "type":"Retail Goods"
        }
    ],
    "sg:phone":"+1 678 432 6748",
    "sg:postcode":"30252",
    "sg:province":"GA",
    "sg:tags":[
        "game",
        "video"
    ],
    "wof:name":"Game Stop Corp",
    "wof:placetype":"venue"
},
  "geometry": {"coordinates":[-84.113541,33.433438],"type":"Point"}
}