{
  "type": "Feature",
  "properties": {
    "addr:full":"7214 Douglas Blvd Douglasville GA 30135",
    "addr:housenumber":"7214",
    "addr:postcode":"30135",
    "addr:street":"Douglas Blvd",
    "iso:country":"US",
    "sg:address":"7214 Douglas Blvd",
    "sg:city":"Douglasville",
    "sg:classifiers":[
        {
            "category":"Personal",
            "subcategory":"Beauty Salon",
            "type":"Services"
        }
    ],
    "sg:phone":"+1 770 949 1086",
    "sg:postcode":"30135",
    "sg:province":"GA",
    "wof:name":"Crown & Glory",
    "wof:placetype":"venue"
},
  "geometry": {"coordinates":[-84.766374,33.724831],"type":"Point"}
}