{
  "type": "Feature",
  "properties": {
    "iso:country":"US",
    "sg:address":"30 Mansell Ct",
    "sg:city":"Roswell",
    "sg:classifiers":[
        {
            "category":"Real Estate",
            "subcategory":"Real Estate Agent",
            "type":"Services"
        }
    ],
    "sg:phone":"+1 678 822 2113",
    "sg:postcode":"30076",
    "sg:province":"GA",
    "wof:name":"Colonial Properties Trust",
    "wof:placetype":"venue"
},
  "geometry": {"coordinates":[-84.331678,34.04023],"type":"Point"}
}