{
  "type": "Feature",
  "properties": {
    "addr:full":"358 Oneal Rd Waverly Hall GA 31833",
    "addr:housenumber":"358",
    "addr:postcode":"31833",
    "addr:street":"Oneal Rd",
    "iso:country":"US",
    "sg:address":"358 Oneal Rd",
    "sg:city":"Waverly Hall",
    "sg:classifiers":[
        {
            "category":"Personal",
            "subcategory":"Beauty Salon",
            "type":"Services"
        }
    ],
    "sg:phone":"+1 706 582 2999",
    "sg:postcode":"31833",
    "sg:province":"GA",
    "wof:name":"Laurie's KLIP-N-KURL",
    "wof:placetype":"venue"
},
  "geometry": {"coordinates":[-85.060631,32.840105],"type":"Point"}
}