{
  "type": "Feature",
  "properties": {
    "addr:full":"3537 Riverchase Dr Valdosta GA 31602",
    "addr:housenumber":"3537",
    "addr:postcode":"31602",
    "addr:street":"Riverchase Dr",
    "iso:country":"US",
    "sg:address":"3537 Riverchase Dr",
    "sg:city":"Valdosta",
    "sg:classifiers":[
        {
            "category":"Building & Trades",
            "subcategory":"Landscaping Services",
            "type":"Services"
        }
    ],
    "sg:phone":"+1 229 241 1614",
    "sg:postcode":"31602",
    "sg:province":"GA",
    "sg:tags":[
        "lawn",
        "maintenance",
        "grounds"
    ],
    "wof:name":"Cliff Hewett's Landscape",
    "wof:placetype":"venue"
},
  "geometry": {"coordinates":[-83.31542399999999,30.90603],"type":"Point"}
}