{
  "type": "Feature",
  "properties": {
    "addr:full":"4058 Winters Chapel Rd Atlanta GA 30360",
    "addr:housenumber":"4058",
    "addr:postcode":"30360",
    "addr:street":"Winters Chapel Rd",
    "iso:country":"US",
    "sg:address":"4058 Winters Chapel Rd",
    "sg:city":"Atlanta",
    "sg:classifiers":[
        {
            "category":"Autos & Motor Vehicles",
            "subcategory":"Recreational Vehicle Sales",
            "type":"Retail Goods"
        },
        {
            "category":"Building & Trades",
            "subcategory":"Construction",
            "type":"Services"
        }
    ],
    "sg:phone":"+1 770 452 1100",
    "sg:postcode":"30360",
    "sg:province":"GA",
    "sg:tags":[
        "industrial",
        "parts",
        "trailer",
        "contractor"
    ],
    "wof:name":"Werts Welding & Tank Service",
    "wof:placetype":"venue"
},
  "geometry": {"coordinates":[-84.27019199999999,33.913183],"type":"Point"}
}