{
  "type": "Feature",
  "properties": {
    "iso:country":"US",
    "sg:address":"355 Ralph G Hendrix",
    "sg:city":"Statesboro",
    "sg:classifiers":[
        {
            "category":"Wholesale",
            "subcategory":"Machinery & Supplies",
            "type":"Manufacturing & Wholesale Goods"
        }
    ],
    "sg:phone":"+1 912 964 5622",
    "sg:postcode":"30458",
    "sg:province":"GA",
    "sg:tags":[
        "compressor",
        "sales",
        "air"
    ],
    "wof:name":"Southeast Compressor",
    "wof:placetype":"venue"
},
  "geometry": {"coordinates":[-81.816543,32.405768],"type":"Point"}
}