{
  "type": "Feature",
  "properties": {
    "iso:country":"US",
    "sg:address":"1481 Jeffersonville Rd",
    "sg:city":"Macon",
    "sg:classifiers":[
        {
            "category":"Building & Trades",
            "subcategory":"Cleaning & Sanitation",
            "type":"Services"
        }
    ],
    "sg:phone":"+1 478 318 4298",
    "sg:postcode":"31217",
    "sg:province":"GA",
    "sg:tags":[
        "janitor"
    ],
    "wof:name":"K J Windows",
    "wof:placetype":"venue"
},
  "geometry": {"coordinates":[-83.59570100000001,32.851347],"type":"Point"}
}