{
  "type": "Feature",
  "properties": {
    "iso:country":"US",
    "sg:address":"11100 Surrey Park Trl",
    "sg:city":"Duluth",
    "sg:classifiers":[
        {
            "category":"Building & Trades",
            "subcategory":"Landscaping Services",
            "type":"Services"
        }
    ],
    "sg:phone":"+1 770 664 6350",
    "sg:postcode":"30097",
    "sg:province":"GA",
    "sg:tags":[
        "landscape"
    ],
    "wof:name":"Brumley Larry D & Assoc I",
    "wof:placetype":"venue"
},
  "geometry": {"coordinates":[-84.194236,34.051989],"type":"Point"}
}