{
  "type": "Feature",
  "properties": {
    "addr:full":"650 Atlanta South Pkwy Atlanta GA 30349",
    "addr:housenumber":"650",
    "addr:postcode":"30349",
    "addr:street":"Atlanta South Pkwy",
    "iso:country":"US",
    "sg:address":"650 Atlanta South Pkwy",
    "sg:city":"Atlanta",
    "sg:classifiers":[
        {
            "category":"Freight",
            "type":"Transportation"
        }
    ],
    "sg:phone":"+1 404 766 8935",
    "sg:postcode":"30349",
    "sg:province":"GA",
    "sg:tags":[
        "forwarder",
        "domestic"
    ],
    "wof:name":"Transgroup Worldwide Logistics",
    "wof:placetype":"venue"
},
  "geometry": {"coordinates":[-84.405359,33.611711],"type":"Point"}
}