{
  "type": "Feature",
  "properties": {
    "iso:country":"US",
    "sg:address":"106 W Walnut St",
    "sg:city":"Jesup",
    "sg:classifiers":[
        {
            "category":"Communications",
            "subcategory":"Radio Station",
            "type":"Services"
        }
    ],
    "sg:phone":"+1 912 588 1821",
    "sg:postcode":"31545",
    "sg:province":"GA",
    "sg:tags":[
        "broadcast"
    ],
    "wof:name":"Wtlb FM",
    "wof:placetype":"venue"
},
  "geometry": {"coordinates":[-81.882912,31.607294],"type":"Point"}
}