{
  "type": "Feature",
  "properties": {
    "addr:full":"1924 Poplar Rdg Lawrenceville GA 30044",
    "addr:housenumber":"1924",
    "addr:postcode":"30044",
    "addr:street":"Poplar Rdg",
    "iso:country":"US",
    "sg:address":"1924 Poplar Rdg",
    "sg:city":"Lawrenceville",
    "sg:classifiers":[
        {
            "category":"Banks & Credit Unions",
            "subcategory":"Investment Brokerage",
            "type":"Services"
        },
        {
            "category":"Banks & Credit Unions",
            "subcategory":"Financial Services",
            "type":"Services"
        }
    ],
    "sg:phone":"+1 770 822 5910",
    "sg:postcode":"30044",
    "sg:province":"GA",
    "sg:tags":[
        "advisory",
        "planner"
    ],
    "wof:name":"Rivergreen Financial Group",
    "wof:placetype":"venue"
},
  "geometry": {"coordinates":[-84.055336,33.944338],"type":"Point"}
}