{
  "type": "Feature",
  "properties": {
    "iso:country":"US",
    "sg:address":"170 Mark Trl NW",
    "sg:city":"Atlanta",
    "sg:classifiers":[
        {
            "category":"Professional",
            "subcategory":"Management & Consulting",
            "type":"Services"
        }
    ],
    "sg:phone":"+1 404 257 9559",
    "sg:postcode":"30328",
    "sg:province":"GA",
    "wof:name":"F McLoughlin/Assoc",
    "wof:placetype":"venue"
},
  "geometry": {"coordinates":[-84.38239900000001,33.944044],"type":"Point"}
}