{
  "type": "Feature",
  "properties": {
    "iso:country":"US",
    "sg:address":"1265 Lee St SW",
    "sg:city":"Atlanta",
    "sg:classifiers":[
        {
            "category":"Food & Beverages",
            "subcategory":"Meat & Fish",
            "type":"Retail Goods"
        }
    ],
    "sg:phone":"+1 404 753 3611",
    "sg:postcode":"30310",
    "sg:province":"GA",
    "sg:tags":[
        "shop",
        "market"
    ],
    "wof:name":"Big Daddy's Discount Meat",
    "wof:placetype":"venue"
},
  "geometry": {"coordinates":[-84.423698,33.721199],"type":"Point"}
}