{
  "type": "Feature",
  "properties": {
    "addr:full":"1965 Hwy 138 NE Conyers GA 30013",
    "addr:housenumber":"1965",
    "addr:postcode":"30013",
    "addr:street":"Hwy 138 Ne",
    "iso:country":"US",
    "sg:address":"1965 Hwy 138 NE",
    "sg:city":"Conyers",
    "sg:classifiers":[
        {
            "category":"Restaurant",
            "type":"Food & Drink"
        }
    ],
    "sg:phone":"+1 770 785 7554",
    "sg:postcode":"30013",
    "sg:province":"GA",
    "sg:tags":[
        "mexican"
    ],
    "wof:name":"Los Charros",
    "wof:placetype":"venue"
},
  "geometry": {"coordinates":[-84.014492,33.643766],"type":"Point"}
}