{
  "type": "Feature",
  "properties": {
    "iso:country":"US",
    "sg:address":"4787 Alabama Rd NE",
    "sg:city":"Roswell",
    "sg:classifiers":[
        {
            "category":"Autos & Motor Vehicles",
            "subcategory":"Auto Supplies",
            "type":"Retail Goods"
        }
    ],
    "sg:phone":"+1 770 992 4050",
    "sg:postcode":"30075",
    "sg:province":"GA",
    "sg:tags":[
        "tire"
    ],
    "wof:name":"East Cobb Auto Rental and Sales",
    "wof:placetype":"venue"
},
  "geometry": {"coordinates":[-84.424936,34.066264],"type":"Point"}
}