{
  "type": "Feature",
  "properties": {
    "iso:country":"US",
    "sg:address":"545 Tollwood Dr",
    "sg:city":"Roswell",
    "sg:classifiers":[
        {
            "category":"Food & Beverages",
            "subcategory":"Specialty",
            "type":"Retail Goods"
        }
    ],
    "sg:phone":"+1 770 992 6051",
    "sg:postcode":"30075",
    "sg:province":"GA",
    "sg:tags":[
        "miscellaneous",
        "store"
    ],
    "wof:name":"Herbal Life Distr",
    "wof:placetype":"venue"
},
  "geometry": {"coordinates":[-84.37830700000001,34.030733],"type":"Point"}
}