{
  "type": "Feature",
  "properties": {
    "addr:full":"608 Louis Ave Albany GA 31701",
    "addr:housenumber":"608",
    "addr:postcode":"31701",
    "addr:street":"Louis Ave",
    "iso:country":"US",
    "sg:address":"608 Louis Ave",
    "sg:city":"Albany",
    "sg:classifiers":[
        {
            "category":"Building & Trades",
            "subcategory":"Construction",
            "type":"Services"
        }
    ],
    "sg:phone":"+1 229 435 7455",
    "sg:postcode":"31701",
    "sg:province":"GA",
    "sg:tags":[
        "concrete",
        "contractor"
    ],
    "wof:name":"Willie J Tinson Con Finishes",
    "wof:placetype":"venue"
},
  "geometry": {"coordinates":[-84.161445,31.556034],"type":"Point"}
}