{
  "type": "Feature",
  "properties": {
    "iso:country":"US",
    "sg:address":"2000 Flat Shoals Rd SE",
    "sg:city":"Atlanta",
    "sg:classifiers":[
        {
            "category":"Autos & Motor Vehicles",
            "subcategory":"Fuel & Gas Station",
            "type":"Retail Goods"
        }
    ],
    "sg:phone":"+1 404 241 5503",
    "sg:postcode":"30316",
    "sg:province":"GA",
    "sg:tags":[
        "oil"
    ],
    "wof:name":"Shell",
    "wof:placetype":"venue"
},
  "geometry": {"coordinates":[-84.322214,33.725815],"type":"Point"}
}