{
  "type": "Feature",
  "properties": {
    "iso:country":"US",
    "sg:address":"3500 Peachtree Rd NE On 2nd level next to Belks",
    "sg:city":"Atlanta",
    "sg:classifiers":[
        {
            "category":"Shopping",
            "subcategory":"Bicycles & Sporting Goods",
            "type":"Retail Goods"
        },
        {
            "category":"Sports & Exercise",
            "subcategory":"Gym",
            "type":"Entertainment"
        }
    ],
    "sg:phone":"+1 404 816 2228",
    "sg:postcode":"30326",
    "sg:province":"GA",
    "sg:website":"www.lowcountryfitness.net",
    "wof:name":"Low Country Fitness",
    "wof:placetype":"venue"
},
  "geometry": {"coordinates":[-84.362683,33.852954],"type":"Point"}
}