{
  "type": "Feature",
  "properties": {
    "addr:full":"3665 James Rd Acworth GA 30102",
    "addr:housenumber":"3665",
    "addr:postcode":"30102",
    "addr:street":"James Rd",
    "iso:country":"US",
    "sg:address":"3665 James Rd",
    "sg:city":"Acworth",
    "sg:classifiers":[
        {
            "category":"Wholesale",
            "subcategory":"Machinery & Supplies",
            "type":"Manufacturing & Wholesale Goods"
        },
        {
            "category":"Building & Trades",
            "subcategory":"Equipment Rental",
            "type":"Services"
        }
    ],
    "sg:phone":"+1 770 975 7907",
    "sg:postcode":"30102",
    "sg:province":"GA",
    "sg:tags":[
        "industrial",
        "contractor"
    ],
    "wof:name":"Southeast Equipment Plus",
    "wof:placetype":"venue"
},
  "geometry": {"coordinates":[-84.65530200000001,34.094232],"type":"Point"}
}