{
  "type": "Feature",
  "properties": {
    "addr:full":"110 W Gazebo Ln Savannah GA 31410",
    "addr:housenumber":"110",
    "addr:postcode":"31410",
    "addr:street":"W Gazebo Ln",
    "iso:country":"US",
    "sg:address":"110 W Gazebo Ln",
    "sg:city":"Savannah",
    "sg:classifiers":[
        {
            "category":"Professional",
            "subcategory":"Management & Consulting",
            "type":"Services"
        }
    ],
    "sg:phone":"+1 912 655 1565",
    "sg:postcode":"31410",
    "sg:province":"GA",
    "sg:tags":[
        "consultant",
        "sale",
        "marketing"
    ],
    "sg:website":"http://www.bowlinggreenassemblyplant.com",
    "wof:name":"General Motors",
    "wof:placetype":"venue"
},
  "geometry": {"coordinates":[-80.983329,32.005447],"type":"Point"}
}