{
  "type": "Feature",
  "properties": {
    "iso:country":"US",
    "sg:address":"3400 Madison St",
    "sg:city":"Atlanta",
    "sg:classifiers":[
        {
            "category":"Real Estate",
            "subcategory":"Real Estate Operator",
            "type":"Services"
        }
    ],
    "sg:phone":"+1 770 804 1883",
    "sg:postcode":"30337",
    "sg:province":"GA",
    "sg:tags":[
        "apartment",
        "complex"
    ],
    "wof:name":"Gables At Metropolitan",
    "wof:placetype":"venue"
},
  "geometry": {"coordinates":[-84.439189,33.663973],"type":"Point"}
}