{
  "type": "Feature",
  "properties": {
    "addr:full":"454 Hwy 225 Chatsworth GA 30705",
    "addr:housenumber":"454",
    "addr:postcode":"30705",
    "addr:street":"Hwy 225",
    "iso:country":"US",
    "sg:address":"454 Hwy 225",
    "sg:city":"Chatsworth",
    "sg:classifiers":[
        {
            "category":"Professional",
            "subcategory":"Advertising",
            "type":"Services"
        }
    ],
    "sg:phone":"+1 706 695 0960",
    "sg:postcode":"30705",
    "sg:province":"GA",
    "sg:tags":[
        "sample",
        "cards",
        "book"
    ],
    "wof:name":"Sample Works",
    "wof:placetype":"venue"
},
  "geometry": {"coordinates":[-84.82384399999999,34.772192],"type":"Point"}
}