{
  "type": "Feature",
  "properties": {
    "addr:full":"440 Stone Edge Rd Macon GA 31210",
    "addr:housenumber":"440",
    "addr:postcode":"31210",
    "addr:street":"Stone Edge Rd",
    "iso:country":"US",
    "sg:address":"440 Stone Edge Rd",
    "sg:city":"Macon",
    "sg:classifiers":[
        {
            "category":"Real Estate",
            "subcategory":"Architect",
            "type":"Services"
        }
    ],
    "sg:phone":"+1 478 741 8818",
    "sg:postcode":"31210",
    "sg:province":"GA",
    "wof:name":"Wolf & Assoc",
    "wof:placetype":"venue"
},
  "geometry": {"coordinates":[-83.74985100000001,32.884789],"type":"Point"}
}