{
  "type": "Feature",
  "properties": {
    "iso:country":"US",
    "sg:address":"1689 15th St",
    "sg:city":"Augusta",
    "sg:classifiers":[
        {
            "category":"Retail",
            "subcategory":"Auto Repair",
            "type":"Services"
        }
    ],
    "sg:phone":"+1 706 834 3640",
    "sg:postcode":"30901",
    "sg:province":"GA",
    "sg:tags":[
        "general"
    ],
    "wof:name":"Fifteenth Street Garage",
    "wof:placetype":"venue"
},
  "geometry": {"coordinates":[-81.99841000000001,33.456583],"type":"Point"}
}