{
  "type": "Feature",
  "properties": {
    "addr:full":"4226 Cagle Rd Lula GA 30554",
    "addr:housenumber":"4226",
    "addr:postcode":"30554",
    "addr:street":"Cagle Rd",
    "iso:country":"US",
    "sg:address":"4226 Cagle Rd",
    "sg:city":"Lula",
    "sg:classifiers":[
        {
            "category":"Utilities",
            "subcategory":"Electric",
            "type":"Services"
        }
    ],
    "sg:phone":"+1 770 869 9483",
    "sg:postcode":"30554",
    "sg:province":"GA",
    "sg:tags":[
        "company"
    ],
    "wof:name":"Oglethorpe Power Corp",
    "wof:placetype":"venue"
},
  "geometry": {"coordinates":[-83.73411900000001,34.376014],"type":"Point"}
}