{
  "type": "Feature",
  "properties": {
    "iso:country":"US",
    "sg:address":"315 N Main St",
    "sg:city":"La Fayette",
    "sg:classifiers":[
        {
            "category":"Restaurant",
            "type":"Food & Drink"
        }
    ],
    "sg:phone":"+1 706 638 3144",
    "sg:postcode":"30728",
    "sg:province":"GA",
    "sg:tags":[
        "eating"
    ],
    "wof:name":"Western Sizzlin Steakhouse",
    "wof:placetype":"venue"
},
  "geometry": {"coordinates":[-85.281586,34.70807],"type":"Point"}
}