{
  "type": "Feature",
  "properties": {
    "addr:full":"5142 Washington Rd Evans GA 30809",
    "addr:housenumber":"5142",
    "addr:postcode":"30809",
    "addr:street":"Washington Rd",
    "iso:country":"US",
    "sg:address":"5142 Washington Rd",
    "sg:city":"Evans",
    "sg:classifiers":[
        {
            "category":"Restaurant",
            "type":"Food & Drink"
        }
    ],
    "sg:menulink":"http://www.allmenus.com/ga/evans/153441-bojangles/menu/",
    "sg:phone":"+1 706 650 2520",
    "sg:postcode":"30809",
    "sg:province":"GA",
    "sg:tags":[
        "chicken",
        "sandwich",
        "american"
    ],
    "wof:name":"Bojangle's",
    "wof:placetype":"venue"
},
  "geometry": {"coordinates":[-82.200953,33.575012],"type":"Point"}
}