{
  "type": "Feature",
  "properties": {
    "iso:country":"US",
    "sg:address":"20 Knollwood Dr",
    "sg:city":"Mc Donough",
    "sg:classifiers":[
        {
            "category":"Building & Trades",
            "subcategory":"Landscaping Services",
            "type":"Services"
        }
    ],
    "sg:phone":"+1 770 898 7971",
    "sg:postcode":"30252",
    "sg:province":"GA",
    "sg:tags":[
        "landscape"
    ],
    "wof:name":"Skys Edge Aquatic Gardens",
    "wof:placetype":"venue"
},
  "geometry": {"coordinates":[-84.10896700000001,33.437752],"type":"Point"}
}