{
  "type": "Feature",
  "properties": {
    "iso:country":"US",
    "sg:address":"1725 Reynolds St",
    "sg:city":"Brunswick",
    "sg:classifiers":[
        {
            "category":"Professional",
            "subcategory":"Management & Consulting",
            "type":"Services"
        }
    ],
    "sg:phone":"+1 912 554 7127",
    "sg:postcode":"31520",
    "sg:province":"GA",
    "sg:tags":[
        "business"
    ],
    "wof:name":"Glynn County Bd Commissioners",
    "wof:placetype":"venue"
},
  "geometry": {"coordinates":[-81.495589,31.15307],"type":"Point"}
}