{
  "type": "Feature",
  "properties": {
    "iso:country":"US",
    "sg:address":"12152 Hwy 92",
    "sg:city":"Woodstock",
    "sg:classifiers":[
        {
            "category":"Coffee & Tea",
            "type":"Food & Drink"
        },
        {
            "category":"Cafe",
            "type":"Food & Drink"
        }
    ],
    "sg:menulink":"http://www.allmenus.com/ga/woodstock/93878-wild-bean-cafe/menu/",
    "sg:phone":"+1 770 517 5755",
    "sg:postcode":"30188",
    "sg:province":"GA",
    "sg:tags":[
        "wrap",
        "american",
        "sandwich"
    ],
    "wof:name":"Wild Bean Cafe",
    "wof:placetype":"venue"
},
  "geometry": {"coordinates":[-84.48392200000001,34.087577],"type":"Point"}
}