{
  "type": "Feature",
  "properties": {
    "iso:country":"US",
    "sg:address":"895 College Ave",
    "sg:city":"Athens",
    "sg:classifiers":[
        {
            "category":"Manufacturing",
            "subcategory":"Printing",
            "type":"Manufacturing & Wholesale Goods"
        }
    ],
    "sg:phone":"+1 706 546 6245",
    "sg:postcode":"30601",
    "sg:province":"GA",
    "sg:tags":[
        "duplicating",
        "copying",
        "offset"
    ],
    "sg:website":"http://www.georgianpress.com",
    "wof:name":"Georgian Press The",
    "wof:placetype":"venue"
},
  "geometry": {"coordinates":[-83.378226,33.965696],"type":"Point"}
}