{
  "type": "Feature",
  "properties": {
    "iso:country":"US",
    "sg:address":"5411 Northland Dr NE",
    "sg:city":"Atlanta",
    "sg:classifiers":[
        {
            "category":"Health Services",
            "subcategory":"Clinic",
            "type":"Services"
        }
    ],
    "sg:phone":"+1 404 250 8703",
    "sg:postcode":"30342",
    "sg:province":"GA",
    "sg:tags":[
        "home",
        "skilled",
        "nursing",
        "care",
        "facility"
    ],
    "sg:website":"www.vitas.com",
    "wof:name":"Haven House Hospice",
    "wof:placetype":"venue"
},
  "geometry": {"coordinates":[-84.37092800000001,33.904022],"type":"Point"}
}