{
  "type": "Feature",
  "properties": {
    "iso:country":"US",
    "sg:address":"2770 Woodbine Hill Way",
    "sg:city":"Norcross",
    "sg:classifiers":[
        {
            "category":"Home & Garden",
            "subcategory":"Building Materials",
            "type":"Retail Goods"
        }
    ],
    "sg:phone":"+1 770 263 9447",
    "sg:postcode":"30071",
    "sg:province":"GA",
    "wof:name":"A-Tonys Auto Glass",
    "wof:placetype":"venue"
},
  "geometry": {"coordinates":[-84.171738,33.967496],"type":"Point"}
}