{
  "type": "Feature",
  "properties": {
    "addr:full":"3440 Camp Creek Pkwy Ste 1130 Atlanta GA 30344",
    "addr:housenumber":"3440",
    "addr:postcode":"30344",
    "addr:street":"Camp Creek Pkwy Ste 1130",
    "iso:country":"US",
    "sg:address":"3440 Camp Creek Pkwy Ste 1130",
    "sg:city":"Atlanta",
    "sg:classifiers":[
        {
            "category":"Food & Beverages",
            "subcategory":"Specialty",
            "type":"Retail Goods"
        },
        {
            "category":"Food & Beverages",
            "subcategory":"Fruits & Vegetables",
            "type":"Retail Goods"
        }
    ],
    "sg:phone":"+1 404 494 3125",
    "sg:postcode":"30344",
    "sg:province":"GA",
    "sg:tags":[
        "herb",
        "supplement",
        "vitamin"
    ],
    "sg:website":"http://www.vitaminshoppe.com/",
    "wof:name":"Vitamin Shoppe",
    "wof:placetype":"venue"
},
  "geometry": {"coordinates":[-84.502214,33.655582],"type":"Point"}
}