{
  "type": "Feature",
  "properties": {
    "iso:country":"US",
    "sg:address":"4678 Longman Way",
    "sg:city":"Stone Mountain",
    "sg:classifiers":[
        {
            "category":"Professional",
            "subcategory":"Management & Consulting",
            "type":"Services"
        }
    ],
    "sg:phone":"+1 404 296 1488",
    "sg:postcode":"30083",
    "sg:province":"GA",
    "wof:name":"Mortenson Enterprises",
    "wof:placetype":"venue"
},
  "geometry": {"coordinates":[-84.197644,33.822782],"type":"Point"}
}