{
  "type": "Feature",
  "properties": {
    "addr:full":"1151 Veterans Memorial Pkwy SW Mableton GA 30126",
    "addr:housenumber":"1151",
    "addr:postcode":"30126",
    "addr:street":"Veterans Memorial Pkwy Sw",
    "iso:country":"US",
    "sg:address":"1151 Veterans Memorial Pkwy SW",
    "sg:city":"Mableton",
    "sg:classifiers":[
        {
            "category":"Shopping",
            "type":"Retail Goods"
        }
    ],
    "sg:phone":"+1 770 819 9310",
    "sg:postcode":"30126",
    "sg:province":"GA",
    "sg:tags":[
        "plant",
        "flower",
        "tree",
        "artificial"
    ],
    "wof:name":"Lucky Star Wholesale",
    "wof:placetype":"venue"
},
  "geometry": {"coordinates":[-84.590763,33.816421],"type":"Point"}
}