{
  "type": "Feature",
  "properties": {
    "iso:country":"US",
    "sg:address":"1410 N Slappey Blvd",
    "sg:city":"Albany",
    "sg:classifiers":[
        {
            "category":"Organizations",
            "subcategory":"Religious Organization",
            "type":"Services"
        }
    ],
    "sg:phone":"+1 229 888 7012",
    "sg:postcode":"31701",
    "sg:province":"GA",
    "sg:tags":[
        "church"
    ],
    "wof:name":"Institutional First Baptist Ch",
    "wof:placetype":"venue"
},
  "geometry": {"coordinates":[-84.175878,31.596942],"type":"Point"}
}