{
  "type": "Feature",
  "properties": {
    "iso:country":"US",
    "sg:address":"7605 State Rte 46",
    "sg:city":"Statesboro",
    "sg:classifiers":[
        {
            "category":"Government",
            "subcategory":"Office",
            "type":"Public Place"
        }
    ],
    "sg:phone":"+1 912 839 2416",
    "sg:postcode":"30458",
    "sg:province":"GA",
    "wof:name":"Sinkhole Recycling Ctr",
    "wof:placetype":"venue"
},
  "geometry": {"coordinates":[-81.80233,32.326212],"type":"Point"}
}