{
  "type": "Feature",
  "properties": {
    "iso:country":"US",
    "sg:address":"707 Whitlock Ave SW",
    "sg:city":"Marietta",
    "sg:classifiers":[
        {
            "category":"Insurance",
            "subcategory":"Insurance Agent",
            "type":"Services"
        }
    ],
    "sg:phone":"+1 770 952 3522",
    "sg:postcode":"30064",
    "sg:province":"GA",
    "sg:tags":[
        "independent"
    ],
    "sg:website":"www.tomgiddens.com",
    "wof:name":"AFLAC",
    "wof:placetype":"venue"
},
  "geometry": {"coordinates":[-84.577974,33.952231],"type":"Point"}
}