{
  "type": "Feature",
  "properties": {
    "addr:full":"6606 Abercorn St Exn Savannah GA 31405",
    "addr:housenumber":"6606",
    "addr:postcode":"31405",
    "addr:street":"Abercorn St Exn",
    "iso:country":"US",
    "sg:address":"6606 Abercorn St Exn",
    "sg:city":"Savannah",
    "sg:classifiers":[
        {
            "category":"Professional",
            "subcategory":"Business Services",
            "type":"Services"
        },
        {
            "category":"Organizations",
            "subcategory":"Professional Association",
            "type":"Services"
        }
    ],
    "sg:phone":"+1 912 354 7521",
    "sg:postcode":"31405",
    "sg:province":"GA",
    "sg:tags":[
        "legal"
    ],
    "wof:name":"Better Business Bureau",
    "wof:placetype":"venue"
},
  "geometry": {"coordinates":[-81.112493,32.015902],"type":"Point"}
}