{
  "type": "Feature",
  "properties": {
    "iso:country":"US",
    "sg:address":"5225 Yeager Rd",
    "sg:city":"Douglasville",
    "sg:classifiers":[
        {
            "category":"Professional",
            "type":"Services"
        }
    ],
    "sg:phone":"+1 770 949 0539",
    "sg:postcode":"30135",
    "sg:province":"GA",
    "wof:name":"Johnny C Ponder",
    "wof:placetype":"venue"
},
  "geometry": {"coordinates":[-84.761358,33.665561],"type":"Point"}
}