{
  "type": "Feature",
  "properties": {
    "addr:full":"881 Memorial Dr SE Atlanta GA 30316",
    "addr:housenumber":"881",
    "addr:postcode":"30316",
    "addr:street":"Memorial Dr Se",
    "iso:country":"US",
    "sg:address":"881 Memorial Dr SE",
    "sg:city":"Atlanta",
    "sg:classifiers":[
        {
            "category":"Real Estate",
            "subcategory":"Real Estate Operator",
            "type":"Services"
        }
    ],
    "sg:phone":"+1 404 586 0783",
    "sg:postcode":"30316",
    "sg:province":"GA",
    "sg:tags":[
        "apartment"
    ],
    "wof:name":"A and P Lofts",
    "wof:placetype":"venue"
},
  "geometry": {"coordinates":[-84.358597,33.746601],"type":"Point"}
}