{
  "type": "Feature",
  "properties": {
    "iso:country":"US",
    "sg:address":"245 Old Corinth Rd",
    "sg:city":"Buchanan",
    "sg:classifiers":[
        {
            "category":"Professional",
            "type":"Services"
        }
    ],
    "sg:phone":"+1 770 646 3115",
    "sg:postcode":"30113",
    "sg:province":"GA",
    "wof:name":"Lord & B Ltd",
    "wof:placetype":"venue"
},
  "geometry": {"coordinates":[-85.09509,33.821439],"type":"Point"}
}