{
  "type": "Feature",
  "properties": {
    "addr:full":"804 Thomaston Dr Dublin GA 31021",
    "addr:housenumber":"804",
    "addr:postcode":"31021",
    "addr:street":"Thomaston Dr",
    "iso:country":"US",
    "sg:address":"804 Thomaston Dr",
    "sg:city":"Dublin",
    "sg:classifiers":[
        {
            "category":"Professional",
            "subcategory":"Secretarial Services",
            "type":"Services"
        }
    ],
    "sg:phone":"+1 478 272 8765",
    "sg:postcode":"31021",
    "sg:province":"GA",
    "sg:tags":[
        "reporting"
    ],
    "wof:name":"Josephine Howard Pro Typist",
    "wof:placetype":"venue"
},
  "geometry": {"coordinates":[-82.94439,32.560542],"type":"Point"}
}