{
  "type": "Feature",
  "properties": {
    "addr:full":"220 Ellis Rd Rossville GA 30741",
    "addr:housenumber":"220",
    "addr:postcode":"30741",
    "addr:street":"Ellis Rd",
    "iso:country":"US",
    "sg:address":"220 Ellis Rd",
    "sg:city":"Rossville",
    "sg:classifiers":[
        {
            "category":"Government",
            "subcategory":"Office",
            "type":"Public Place"
        }
    ],
    "sg:phone":"+1 706 861 1735",
    "sg:postcode":"30741",
    "sg:province":"GA",
    "sg:tags":[
        "village"
    ],
    "wof:name":"Rossville Maintenance Dept",
    "wof:placetype":"venue"
},
  "geometry": {"coordinates":[-85.298199,34.966145],"type":"Point"}
}