{
  "type": "Feature",
  "properties": {
    "iso:country":"US",
    "sg:address":"5441 Riverdale Rd",
    "sg:city":"Atlanta",
    "sg:classifiers":[
        {
            "category":"Building & Trades",
            "subcategory":"Construction",
            "type":"Services"
        }
    ],
    "sg:phone":"+1 678 760 4090",
    "sg:postcode":"30349",
    "sg:province":"GA",
    "sg:tags":[
        "contracting",
        "general"
    ],
    "wof:name":"Rushco General Contracting",
    "wof:placetype":"venue"
},
  "geometry": {"coordinates":[-84.435232,33.605609],"type":"Point"}
}