{
  "type": "Feature",
  "properties": {
    "addr:full":"5414 Amherst Way Flowery Branch GA 30542",
    "addr:housenumber":"5414",
    "addr:postcode":"30542",
    "addr:street":"Amherst Way",
    "iso:country":"US",
    "sg:address":"5414 Amherst Way",
    "sg:city":"Flowery Branch",
    "sg:classifiers":[
        {
            "category":"Shopping",
            "type":"Retail Goods"
        }
    ],
    "sg:phone":"+1 770 967 9432",
    "sg:postcode":"30542",
    "sg:province":"GA",
    "sg:tags":[
        "picture"
    ],
    "wof:name":"Cherished Treasures",
    "wof:placetype":"venue"
},
  "geometry": {"coordinates":[-83.885076,34.153831],"type":"Point"}
}