{
  "type": "Feature",
  "properties": {
    "addr:full":"2757 Bob Bettis Rd Marietta GA 30066",
    "addr:housenumber":"2757",
    "addr:postcode":"30066",
    "addr:street":"Bob Bettis Rd",
    "iso:country":"US",
    "sg:address":"2757 Bob Bettis Rd",
    "sg:city":"Marietta",
    "sg:classifiers":[
        {
            "category":"Organizations",
            "subcategory":"Community Association",
            "type":"Services"
        }
    ],
    "sg:phone":"+1 404 713 2128",
    "sg:postcode":"30066",
    "sg:province":"GA",
    "sg:tags":[
        "club"
    ],
    "sg:website":"www.atlantatravelandsocial.com",
    "wof:name":"Atlanta Travel & Social Club",
    "wof:placetype":"venue"
},
  "geometry": {"coordinates":[-84.50318799999999,34.020417],"type":"Point"}
}