{
  "type": "Feature",
  "properties": {
    "iso:country":"US",
    "sg:address":"2720 Old Spanish Trl SW",
    "sg:city":"Atlanta",
    "sg:classifiers":[
        {
            "category":"Shopping",
            "subcategory":"Gifts & Souvenirs",
            "type":"Retail Goods"
        }
    ],
    "sg:phone":"+1 770 907 4563",
    "sg:postcode":"30349",
    "sg:province":"GA",
    "wof:name":"J&C Gift Shop",
    "wof:placetype":"venue"
},
  "geometry": {"coordinates":[-84.477,33.593305],"type":"Point"}
}