{
  "type": "Feature",
  "properties": {
    "iso:country":"US",
    "sg:address":"975 Old Andersonville Rd",
    "sg:city":"Hartwell",
    "sg:classifiers":[
        {
            "category":"Shopping",
            "subcategory":"Department Store",
            "type":"Retail Goods"
        }
    ],
    "sg:phone":"+1 706 376 0114",
    "sg:postcode":"30643",
    "sg:province":"GA",
    "wof:name":"Beall's",
    "wof:placetype":"venue"
},
  "geometry": {"coordinates":[-82.878496,34.439897],"type":"Point"}
}