{
  "type": "Feature",
  "properties": {
    "addr:full":"1850 Parkway Pl SE Ste 200 Marietta GA 30067",
    "addr:housenumber":"1850",
    "addr:postcode":"30067",
    "addr:street":"Parkway Pl Se Ste 200",
    "iso:country":"US",
    "sg:address":"1850 Parkway Pl SE Ste 200",
    "sg:city":"Marietta",
    "sg:classifiers":[
        {
            "category":"Education",
            "subcategory":"University",
            "type":"Public Place"
        }
    ],
    "sg:phone":"+1 770 218 3177",
    "sg:postcode":"30067",
    "sg:province":"GA",
    "sg:tags":[
        "college"
    ],
    "sg:website":"www.phoenix.edu",
    "wof:name":"University of Phoenix",
    "wof:placetype":"venue"
},
  "geometry": {"coordinates":[-84.503879,33.939204],"type":"Point"}
}