{
  "type": "Feature",
  "properties": {
    "iso:country":"US",
    "sg:address":"5659 Hunters Chase Dr",
    "sg:city":"Lithonia",
    "sg:classifiers":[
        {
            "category":"Professional",
            "type":"Services"
        }
    ],
    "sg:phone":"+1 770 808 1124",
    "sg:postcode":"30038",
    "sg:province":"GA",
    "wof:name":"Jones Atlanta Services",
    "wof:placetype":"venue"
},
  "geometry": {"coordinates":[-84.15885900000001,33.685421],"type":"Point"}
}