{
  "type": "Feature",
  "properties": {
    "addr:full":"564 Marietta St Atlanta GA 30313",
    "addr:housenumber":"564",
    "addr:postcode":"30313",
    "addr:street":"Marietta St",
    "iso:country":"US",
    "sg:address":"564 Marietta St",
    "sg:city":"Atlanta",
    "sg:classifiers":[
        {
            "category":"Professional",
            "subcategory":"Business Services",
            "type":"Services"
        }
    ],
    "sg:phone":"+1 404 577 4355",
    "sg:postcode":"30313",
    "sg:province":"GA",
    "wof:name":"S House Inc",
    "wof:placetype":"venue"
},
  "geometry": {"coordinates":[-84.39866000000001,33.769017],"type":"Point"}
}