{
  "type": "Feature",
  "properties": {
    "iso:country":"US",
    "sg:address":"52 Crawford Hill Rd",
    "sg:city":"Newnan",
    "sg:classifiers":[
        {
            "category":"Personal",
            "subcategory":"Beauty Salon",
            "type":"Services"
        }
    ],
    "sg:phone":"+1 770 251 4599",
    "sg:postcode":"30265",
    "sg:province":"GA",
    "wof:name":"Braids By Cassandra",
    "wof:placetype":"venue"
},
  "geometry": {"coordinates":[-84.693318,33.447201],"type":"Point"}
}