{
  "type": "Feature",
  "properties": {
    "iso:country":"US",
    "sg:address":"1807 S Patterson St",
    "sg:city":"Valdosta",
    "sg:classifiers":[
        {
            "category":"Retail",
            "subcategory":"Animal Services",
            "type":"Services"
        }
    ],
    "sg:phone":"+1 229 253 8779",
    "sg:postcode":"31601",
    "sg:province":"GA",
    "sg:tags":[
        "pet",
        "grooming",
        "washing"
    ],
    "wof:name":"Puppy Love Grooming Salon",
    "wof:placetype":"venue"
},
  "geometry": {"coordinates":[-83.261763,30.811756],"type":"Point"}
}