{
  "type": "Feature",
  "properties": {
    "addr:full":"4294 Memorial Dr Decatur GA 30032",
    "addr:housenumber":"4294",
    "addr:postcode":"30032",
    "addr:street":"Memorial Dr",
    "iso:country":"US",
    "sg:address":"4294 Memorial Dr",
    "sg:city":"Decatur",
    "sg:classifiers":[
        {
            "category":"Health Services",
            "subcategory":"Chiropractor",
            "type":"Services"
        }
    ],
    "sg:phone":"+1 404 296 3200",
    "sg:postcode":"30032",
    "sg:province":"GA",
    "wof:name":"Benson Clinic PC",
    "wof:placetype":"venue"
},
  "geometry": {"coordinates":[-84.249218,33.772666],"type":"Point"}
}