{
  "type": "Feature",
  "properties": {
    "addr:full":"3155 Spring Dr Atlanta GA 30360",
    "addr:housenumber":"3155",
    "addr:postcode":"30360",
    "addr:street":"Spring Dr",
    "iso:country":"US",
    "sg:address":"3155 Spring Dr",
    "sg:city":"Atlanta",
    "sg:classifiers":[
        {
            "category":"Utilities",
            "subcategory":"Water",
            "type":"Services"
        },
        {
            "category":"Building & Trades",
            "subcategory":"Cleaning & Sanitation",
            "type":"Services"
        },
        {
            "category":"Building & Trades",
            "subcategory":"Plumbing",
            "type":"Services"
        },
        {
            "category":"Home & Garden",
            "subcategory":"Carpets & Floor Coverings",
            "type":"Retail Goods"
        }
    ],
    "sg:phone":"+1 678 620 3767",
    "sg:postcode":"30360",
    "sg:province":"GA",
    "sg:tags":[
        "emergency",
        "cleaners-water",
        "damage",
        "rug",
        "extraction",
        "restoration",
        "dyer",
        "plumbing-drain",
        "sewer"
    ],
    "sg:website":"http://www.floodmasters.org",
    "wof:name":"FloodMasters",
    "wof:placetype":"venue"
},
  "geometry": {"coordinates":[-84.263481,33.933479],"type":"Point"}
}