{
  "type": "Feature",
  "properties": {
    "addr:full":"3281 Highway 5 Douglasville GA 30135",
    "addr:housenumber":"3281",
    "addr:postcode":"30135",
    "addr:street":"Highway 5",
    "iso:country":"US",
    "sg:address":"3281 Highway 5",
    "sg:city":"Douglasville",
    "sg:classifiers":[
        {
            "category":"Restaurant",
            "type":"Food & Drink"
        }
    ],
    "sg:phone":"+1 678 715 7234",
    "sg:postcode":"30135",
    "sg:province":"GA",
    "sg:tags":[
        "mexican"
    ],
    "wof:name":"Cinco De Mayo Mexican Grill",
    "wof:placetype":"venue"
},
  "geometry": {"coordinates":[-84.76561100000001,33.717262],"type":"Point"}
}