{
  "type": "Feature",
  "properties": {
    "addr:full":"216 River Park North Dr Woodstock GA 30188",
    "addr:housenumber":"216",
    "addr:postcode":"30188",
    "addr:street":"River Park North Dr",
    "iso:country":"US",
    "sg:address":"216 River Park North Dr",
    "sg:city":"Woodstock",
    "sg:classifiers":[
        {
            "category":"Health Services",
            "subcategory":"Chiropractor",
            "type":"Services"
        }
    ],
    "sg:phone":"+1 678 445 2746",
    "sg:postcode":"30188",
    "sg:province":"GA",
    "sg:tags":[
        "chiropractic"
    ],
    "wof:name":"Abundant Health & Wellness Center",
    "wof:placetype":"venue"
},
  "geometry": {"coordinates":[-84.511329,34.140499],"type":"Point"}
}