{
  "type": "Feature",
  "properties": {
    "addr:full":"366 N Hooker St Pavo GA 31750",
    "addr:housenumber":"366",
    "addr:postcode":"31750",
    "addr:street":"N Hooker St",
    "iso:country":"US",
    "sg:address":"366 N Hooker St",
    "sg:city":"Pavo",
    "sg:classifiers":[
        {
            "category":"Retail",
            "subcategory":"Animal Services",
            "type":"Services"
        }
    ],
    "sg:phone":"+1 229 859 9080",
    "sg:postcode":"31750",
    "sg:province":"GA",
    "wof:name":"S Merlock Kennels",
    "wof:placetype":"venue"
},
  "geometry": {"coordinates":[-83.24527,31.717699],"type":"Point"}
}