{
  "type": "Feature",
  "properties": {
    "iso:country":"US",
    "sg:address":"741 Stonehill Ct",
    "sg:city":"Stone Mountain",
    "sg:classifiers":[
        {
            "category":"Retail",
            "subcategory":"Portrait Studio",
            "type":"Services"
        }
    ],
    "sg:phone":"+1 770 465 0771",
    "sg:postcode":"30083",
    "sg:province":"GA",
    "sg:tags":[
        "photo"
    ],
    "wof:name":"Dth Portrait Creations",
    "wof:placetype":"venue"
},
  "geometry": {"coordinates":[-84.18517900000001,33.798355],"type":"Point"}
}