{
  "type": "Feature",
  "properties": {
    "iso:country":"US",
    "sg:address":"Vinings on the Chattahoochee",
    "sg:city":"Atlanta",
    "sg:classifiers":[
        {
            "category":"Real Estate",
            "subcategory":"Real Estate Services",
            "type":"Services"
        }
    ],
    "sg:postcode":"30318",
    "sg:province":"GA",
    "sg:tags":[
        "management",
        "property"
    ],
    "sg:website":"sharonmcswainhomes.com",
    "wof:name":"Sharon McSwain Homes",
    "wof:placetype":"venue"
},
  "geometry": {"coordinates":[-84.478266,33.812498],"type":"Point"}
}