{
  "type": "Feature",
  "properties": {
    "iso:country":"US",
    "sg:address":"2330 Kingsland Dr",
    "sg:city":"Atlanta",
    "sg:classifiers":[
        {
            "category":"Professional",
            "subcategory":"Business Services",
            "type":"Services"
        }
    ],
    "sg:phone":"+1 770 399 5368",
    "sg:postcode":"30360",
    "sg:province":"GA",
    "wof:name":"Scarab Group Inc",
    "wof:placetype":"venue"
},
  "geometry": {"coordinates":[-84.28767499999999,33.951472],"type":"Point"}
}