{
  "type": "Feature",
  "properties": {
    "addr:full":"1109 N Main St La Fayette GA 30728",
    "addr:housenumber":"1109",
    "addr:postcode":"30728",
    "addr:street":"N Main St;Fayette",
    "iso:country":"US",
    "sg:address":"1109 N Main St",
    "sg:city":"La Fayette",
    "sg:classifiers":[
        {
            "category":"Shopping",
            "subcategory":"Tobacco",
            "type":"Retail Goods"
        }
    ],
    "sg:phone":"+1 706 639 3590",
    "sg:postcode":"30728",
    "sg:province":"GA",
    "sg:tags":[
        "product"
    ],
    "wof:name":"Tobacco Outlet",
    "wof:placetype":"venue"
},
  "geometry": {"coordinates":[-85.279708,34.725942],"type":"Point"}
}