{
  "type": "Feature",
  "properties": {
    "addr:full":"100 Ashley Creek Dr Newnan GA 30263",
    "addr:housenumber":"100",
    "addr:postcode":"30263",
    "addr:street":"Ashley Creek Dr",
    "iso:country":"US",
    "sg:address":"100 Ashley Creek Dr",
    "sg:city":"Newnan",
    "sg:classifiers":[
        {
            "category":"Food & Beverages",
            "subcategory":"Specialty",
            "type":"Retail Goods"
        }
    ],
    "sg:phone":"+1 770 502 7747",
    "sg:postcode":"30263",
    "sg:province":"GA",
    "sg:tags":[
        "herb"
    ],
    "wof:name":"Herbs To Go",
    "wof:placetype":"venue"
},
  "geometry": {"coordinates":[-84.74499400000001,33.464699],"type":"Point"}
}