{
  "type": "Feature",
  "properties": {
    "addr:full":"6540 Douglas Blvd Douglasville GA 30135",
    "addr:housenumber":"6540",
    "addr:postcode":"30135",
    "addr:street":"Douglas Blvd",
    "iso:country":"US",
    "sg:address":"6540 Douglas Blvd",
    "sg:city":"Douglasville",
    "sg:classifiers":[
        {
            "category":"Home & Garden",
            "subcategory":"Furniture",
            "type":"Retail Goods"
        }
    ],
    "sg:phone":"+1 678 838 1788",
    "sg:postcode":"30135",
    "sg:province":"GA",
    "wof:name":"Rooms To Go",
    "wof:placetype":"venue"
},
  "geometry": {"coordinates":[-84.762243,33.724823],"type":"Point"}
}