{
  "type": "Feature",
  "properties": {
    "iso:country":"US",
    "sg:address":"371 Commerce Dr",
    "sg:city":"Peachtree City",
    "sg:classifiers":[
        {
            "category":"Banks & Credit Unions",
            "subcategory":"Bank",
            "type":"Services"
        }
    ],
    "sg:phone":"+1 770 487 2400",
    "sg:postcode":"30269",
    "sg:province":"GA",
    "sg:tags":[
        "state",
        "commercial"
    ],
    "wof:name":"Fifth Third Bank",
    "wof:placetype":"venue"
},
  "geometry": {"coordinates":[-84.589995,33.398947],"type":"Point"}
}