{
  "type": "Feature",
  "properties": {
    "addr:full":"3935 Woodyhill Dr Lithonia GA 30038",
    "addr:housenumber":"3935",
    "addr:postcode":"30038",
    "addr:street":"Woodyhill Dr",
    "iso:country":"US",
    "sg:address":"3935 Woodyhill Dr",
    "sg:city":"Lithonia",
    "sg:classifiers":[
        {
            "category":"Building & Trades",
            "subcategory":"Construction",
            "type":"Services"
        }
    ],
    "sg:phone":"+1 770 322 5383",
    "sg:postcode":"30038",
    "sg:province":"GA",
    "sg:tags":[
        "restoration",
        "cleaning",
        "patio",
        "deck"
    ],
    "wof:name":"Maximum Pressure Washing",
    "wof:placetype":"venue"
},
  "geometry": {"coordinates":[-84.200913,33.666957],"type":"Point"}
}