{
  "type": "Feature",
  "properties": {
    "iso:country":"US",
    "sg:address":"1621 Beaumont Dr NW",
    "sg:city":"Kennesaw",
    "sg:classifiers":[
        {
            "category":"Insurance",
            "subcategory":"Title Insurance",
            "type":"Services"
        }
    ],
    "sg:phone":"+1 770 425 7139",
    "sg:postcode":"30152",
    "sg:province":"GA",
    "sg:tags":[
        "carrier"
    ],
    "wof:name":"Georgia Title Service",
    "wof:placetype":"venue"
},
  "geometry": {"coordinates":[-84.645201,33.989224],"type":"Point"}
}