{
  "type": "Feature",
  "properties": {
    "addr:full":"1535 Thoreau Dr Suwanee GA 30024",
    "addr:housenumber":"1535",
    "addr:postcode":"30024",
    "addr:street":"Thoreau Dr",
    "iso:country":"US",
    "sg:address":"1535 Thoreau Dr",
    "sg:city":"Suwanee",
    "sg:classifiers":[
        {
            "category":"Professional",
            "subcategory":"Business Services",
            "type":"Services"
        }
    ],
    "sg:phone":"+1 770 418 1732",
    "sg:postcode":"30024",
    "sg:province":"GA",
    "wof:name":"Mobile Enterprises Inc C",
    "wof:placetype":"venue"
},
  "geometry": {"coordinates":[-84.09099000000001,34.018631],"type":"Point"}
}