{
  "type": "Feature",
  "properties": {
    "addr:full":"586 Main St Palmetto GA 30268",
    "addr:housenumber":"586",
    "addr:postcode":"30268",
    "addr:street":"Main St",
    "iso:country":"US",
    "sg:address":"586 Main St",
    "sg:city":"Palmetto",
    "sg:classifiers":[
        {
            "category":"Professional",
            "subcategory":"Accounting & Tax Preparation",
            "type":"Services"
        }
    ],
    "sg:phone":"+1 770 463 2781",
    "sg:postcode":"30268",
    "sg:province":"GA",
    "sg:tags":[
        "return",
        "filing"
    ],
    "wof:name":"Palmetto Tax Svc",
    "wof:placetype":"venue"
},
  "geometry": {"coordinates":[-84.670906,33.509792],"type":"Point"}
}