{
  "type": "Feature",
  "properties": {
    "iso:country":"US",
    "sg:address":"3901 Roswell Rd Ste 207",
    "sg:city":"Marietta",
    "sg:classifiers":[
        {
            "category":"Professional",
            "subcategory":"Computer Services",
            "type":"Services"
        }
    ],
    "sg:phone":"+1 770 579 1591",
    "sg:postcode":"30062",
    "sg:province":"GA",
    "sg:tags":[
        "repair"
    ],
    "wof:name":"Preston Aviation Solution",
    "wof:placetype":"venue"
},
  "geometry": {"coordinates":[-84.425797,33.984699],"type":"Point"}
}