{
  "type": "Feature",
  "properties": {
    "iso:country":"US",
    "sg:address":"4623 Canton Hwy",
    "sg:city":"Cumming",
    "sg:classifiers":[
        {
            "category":"Professional",
            "type":"Services"
        }
    ],
    "sg:phone":"+1 678 947 5278",
    "sg:postcode":"30040",
    "sg:province":"GA",
    "wof:name":"Black Dog Art Studio Inc",
    "wof:placetype":"venue"
},
  "geometry": {"coordinates":[-84.25501199999999,34.237484],"type":"Point"}
}