{
  "type": "Feature",
  "properties": {
    "iso:country":"US",
    "sg:address":"1345 Terrell Mill Rd.",
    "sg:city":"Marietta",
    "sg:classifiers":[
        {
            "category":"Personal",
            "subcategory":"Beauty Salon",
            "type":"Services"
        }
    ],
    "sg:phone":"+1 404 552 7747",
    "sg:postcode":"30067",
    "sg:province":"GA",
    "sg:tags":[
        "spa"
    ],
    "sg:website":"www.b-flawless.com",
    "wof:name":"Flawless Extensions",
    "wof:placetype":"venue"
},
  "geometry": {"coordinates":[-84.46544400000001,33.918931],"type":"Point"}
}