{
  "type": "Feature",
  "properties": {
    "addr:full":"6231 Benbrooke Dr NW Acworth GA 30101",
    "addr:housenumber":"6231",
    "addr:postcode":"30101",
    "addr:street":"Benbrooke Dr Nw",
    "iso:country":"US",
    "sg:address":"6231 Benbrooke Dr NW",
    "sg:city":"Acworth",
    "sg:classifiers":[
        {
            "category":"Health Services",
            "subcategory":"Chiropractor",
            "type":"Services"
        }
    ],
    "sg:phone":"+1 770 419 5775",
    "sg:postcode":"30101",
    "sg:province":"GA",
    "wof:name":"Thomas Tumbarello DC",
    "wof:placetype":"venue"
},
  "geometry": {"coordinates":[-84.73391100000001,33.986205],"type":"Point"}
}