{
  "type": "Feature",
  "properties": {
    "iso:country":"US",
    "sg:address":"1475 Buford Dr",
    "sg:city":"Lawrenceville",
    "sg:classifiers":[
        {
            "category":"Personal",
            "subcategory":"Beauty Salon",
            "type":"Services"
        }
    ],
    "sg:phone":"+1 770 995 7732",
    "sg:postcode":"30043",
    "sg:province":"GA",
    "sg:tags":[
        "shop"
    ],
    "wof:name":"Great Clips",
    "wof:placetype":"venue"
},
  "geometry": {"coordinates":[-83.988214,34.004108],"type":"Point"}
}