{
  "type": "Feature",
  "properties": {
    "iso:country":"US",
    "sg:address":"699 Hadden Pond Rd",
    "sg:city":"Waynesboro",
    "sg:classifiers":[
        {
            "category":"Retail",
            "subcategory":"Repair Shop",
            "type":"Services"
        }
    ],
    "sg:phone":"+1 706 554 5088",
    "sg:postcode":"30830",
    "sg:province":"GA",
    "sg:tags":[
        "lithographic",
        "printing",
        "commercial",
        "electrical"
    ],
    "wof:name":"Sapps Office Machine & Prtg",
    "wof:placetype":"venue"
},
  "geometry": {"coordinates":[-82.02866,33.137488],"type":"Point"}
}