{
  "type": "Feature",
  "properties": {
    "iso:country":"US",
    "sg:address":"5434 Tally Green Dr",
    "sg:city":"Marietta",
    "sg:classifiers":[
        {
            "category":"Home & Garden",
            "subcategory":"Home Furnishings",
            "type":"Retail Goods"
        }
    ],
    "sg:phone":"+1 770 649 8260",
    "sg:postcode":"30068",
    "sg:province":"GA",
    "sg:tags":[
        "utensil",
        "cooking"
    ],
    "wof:name":"Pampered Chef Of Marietta",
    "wof:placetype":"venue"
},
  "geometry": {"coordinates":[-84.391898,33.980808],"type":"Point"}
}