{
  "type": "Feature",
  "properties": {
    "addr:full":"5249 N Lake Dr Morrow GA 30260",
    "addr:housenumber":"5249",
    "addr:postcode":"30260",
    "addr:street":"N Lake Dr",
    "iso:country":"US",
    "sg:address":"5249 N Lake Dr",
    "sg:city":"Morrow",
    "sg:classifiers":[
        {
            "category":"Retail",
            "subcategory":"Auto Repair",
            "type":"Services"
        }
    ],
    "sg:phone":"+1 404 362 1010",
    "sg:postcode":"30260",
    "sg:province":"GA",
    "sg:tags":[
        "repairing",
        "automobile"
    ],
    "wof:name":"Highway 42 Auto Repair",
    "wof:placetype":"venue"
},
  "geometry": {"coordinates":[-84.335992,33.608653],"type":"Point"}
}