{
  "type": "Feature",
  "properties": {
    "addr:full":"2355 Main Street Atlanta GA 30344",
    "addr:housenumber":"2355",
    "addr:postcode":"30344",
    "addr:street":"Main Street",
    "iso:country":"US",
    "sg:address":"2355 Main Street",
    "sg:city":"Atlanta",
    "sg:classifiers":[
        {
            "category":"Banks & Credit Unions",
            "subcategory":"Bank",
            "type":"Services"
        }
    ],
    "sg:phone":"+1 404 495 6400",
    "sg:postcode":"30344",
    "sg:province":"GA",
    "wof:name":"Rbc Centura Bank",
    "wof:placetype":"venue"
},
  "geometry": {"coordinates":[-84.45915100000001,33.671827],"type":"Point"}
}