{
  "type": "Feature",
  "properties": {
    "addr:full":"170 Upper Riverdale Rd SW Riverdale GA 30274",
    "addr:housenumber":"170",
    "addr:postcode":"30274",
    "addr:street":"Upper Riverdale Rd Sw",
    "iso:country":"US",
    "sg:address":"170 Upper Riverdale Rd SW",
    "sg:city":"Riverdale",
    "sg:classifiers":[
        {
            "category":"Place Of Worship",
            "subcategory":"Church",
            "type":"Public Place"
        }
    ],
    "sg:phone":"+1 770 991 2076",
    "sg:postcode":"30274",
    "sg:province":"GA",
    "sg:tags":[
        "churches-baptist"
    ],
    "wof:name":"Eastside Baptist Church",
    "wof:placetype":"venue"
},
  "geometry": {"coordinates":[-84.395966,33.574723],"type":"Point"}
}