{
  "type": "Feature",
  "properties": {
    "iso:country":"US",
    "sg:address":"1714 Olive Rd",
    "sg:city":"Augusta",
    "sg:classifiers":[
        {
            "category":"Organizations",
            "subcategory":"Religious Organization",
            "type":"Services"
        }
    ],
    "sg:phone":"+1 706 733 0341",
    "sg:postcode":"30904",
    "sg:province":"GA",
    "sg:tags":[
        "church"
    ],
    "wof:name":"Good Shepherd Baptist Church",
    "wof:placetype":"venue"
},
  "geometry": {"coordinates":[-82.007069,33.451733],"type":"Point"}
}