{
  "type": "Feature",
  "properties": {
    "addr:full":"294 S Main St #300 Alpharetta GA 30004",
    "addr:housenumber":"294",
    "addr:postcode":"30004",
    "addr:street":"S Main St # 300",
    "iso:country":"US",
    "sg:address":"294 S Main St #300",
    "sg:city":"Alpharetta",
    "sg:classifiers":[
        {
            "category":"Social Services",
            "type":"Services"
        },
        {
            "category":"Health Services",
            "subcategory":"Nursing And Care Facility",
            "type":"Services"
        },
        {
            "category":"Health Services",
            "subcategory":"Health Practitioner",
            "type":"Services"
        },
        {
            "category":"Social Services",
            "subcategory":"Adult Care",
            "type":"Services"
        }
    ],
    "sg:phone":"+1 770 442 6959",
    "sg:postcode":"30004",
    "sg:province":"GA",
    "sg:tags":[
        "living",
        "consulting",
        "geriatric",
        "home",
        "assisted",
        "elder",
        "citizen",
        "counseling",
        "senior",
        "eldercare-home"
    ],
    "sg:website":"http://www.seniorhelpers.com",
    "wof:name":"Senior Helpers",
    "wof:placetype":"venue"
},
  "geometry": {"coordinates":[-84.30081300000001,34.06814],"type":"Point"}
}