{
  "type": "Feature",
  "properties": {
    "addr:full":"2459 Elm Dr Columbus GA 31907",
    "addr:housenumber":"2459",
    "addr:postcode":"31907",
    "addr:street":"Elm Dr",
    "iso:country":"US",
    "sg:address":"2459 Elm Dr",
    "sg:city":"Columbus",
    "sg:classifiers":[
        {
            "category":"Freight",
            "type":"Transportation"
        }
    ],
    "sg:phone":"+1 706 323 0800",
    "sg:postcode":"31907",
    "sg:province":"GA",
    "sg:tags":[
        "delivery"
    ],
    "wof:name":"Quicksilver Express Inc",
    "wof:placetype":"venue"
},
  "geometry": {"coordinates":[-84.928755,32.488857],"type":"Point"}
}