{
  "type": "Feature",
  "properties": {
    "addr:full":"1038 Byrnwyck Rd NE Atlanta GA 30319",
    "addr:housenumber":"1038",
    "addr:postcode":"30319",
    "addr:street":"Byrnwyck Rd Ne",
    "iso:country":"US",
    "sg:address":"1038 Byrnwyck Rd NE",
    "sg:city":"Atlanta",
    "sg:classifiers":[
        {
            "category":"Professional",
            "subcategory":"Lawyer & Legal Services",
            "type":"Services"
        }
    ],
    "sg:phone":"+1 404 668 2320",
    "sg:postcode":"30319",
    "sg:province":"GA",
    "sg:tags":[
        "information",
        "attorney",
        "referral"
    ],
    "wof:name":"Agostino Mcghee",
    "wof:placetype":"venue"
},
  "geometry": {"coordinates":[-84.34563799999999,33.909306],"type":"Point"}
}