{
  "type": "Feature",
  "properties": {
    "addr:full":"5205 Riverdale Rd Atlanta GA 30349",
    "addr:housenumber":"5205",
    "addr:postcode":"30349",
    "addr:street":"Riverdale Rd",
    "iso:country":"US",
    "sg:address":"5205 Riverdale Rd",
    "sg:city":"Atlanta",
    "sg:classifiers":[
        {
            "category":"Airline",
            "type":"Transportation"
        }
    ],
    "sg:phone":"+1 678 489 2047",
    "sg:postcode":"30349",
    "sg:province":"GA",
    "sg:tags":[
        "airport"
    ],
    "wof:name":"Vision Enterprise Airport",
    "wof:placetype":"venue"
},
  "geometry": {"coordinates":[-84.437713,33.613097],"type":"Point"}
}