{
  "type": "Feature",
  "properties": {
    "iso:country":"US",
    "sg:address":"3540 Wheeler Rd Ste 102",
    "sg:city":"Augusta",
    "sg:classifiers":[
        {
            "category":"Food & Beverages",
            "subcategory":"Supermarket",
            "type":"Retail Goods"
        },
        {
            "category":"Food & Beverages",
            "subcategory":"Groceries & Convenience Stores",
            "type":"Retail Goods"
        }
    ],
    "sg:phone":"+1 706 364 8860",
    "sg:postcode":"30909",
    "sg:province":"GA",
    "sg:tags":[
        "super"
    ],
    "wof:name":"Georgia Carolina Foods",
    "wof:placetype":"venue"
},
  "geometry": {"coordinates":[-82.07789099999999,33.485202],"type":"Point"}
}