{
  "type": "Feature",
  "properties": {
    "addr:full":"1602 Lake Harbin Rd Ste A Morrow GA 30260",
    "addr:housenumber":"1602",
    "addr:postcode":"30260",
    "addr:street":"Lake Harbin Rd Ste A",
    "iso:country":"US",
    "sg:address":"1602 Lake Harbin Rd Ste A",
    "sg:city":"Morrow",
    "sg:classifiers":[
        {
            "category":"Shopping",
            "subcategory":"Crafts & Fabrics",
            "type":"Retail Goods"
        }
    ],
    "sg:phone":"+1 770 961 0803",
    "sg:postcode":"30260",
    "sg:province":"GA",
    "sg:tags":[
        "store"
    ],
    "sg:website":"www.hancockfabrics.com",
    "wof:name":"Hancock Fabrics",
    "wof:placetype":"venue"
},
  "geometry": {"coordinates":[-84.338825,33.583341],"type":"Point"}
}