{
  "type": "Feature",
  "properties": {
    "addr:full":"808 Thurmond St NW Atlanta GA 30314",
    "addr:housenumber":"808",
    "addr:postcode":"30314",
    "addr:street":"Thurmond St Nw",
    "iso:country":"US",
    "sg:address":"808 Thurmond St NW",
    "sg:city":"Atlanta",
    "sg:classifiers":[
        {
            "category":"Food & Beverages",
            "subcategory":"Groceries & Convenience Stores",
            "type":"Retail Goods"
        }
    ],
    "sg:phone":"+1 404 753 1186",
    "sg:postcode":"30314",
    "sg:province":"GA",
    "sg:tags":[
        "grocer"
    ],
    "wof:name":"Family",
    "wof:placetype":"venue"
},
  "geometry": {"coordinates":[-84.414575,33.760365],"type":"Point"}
}