{
  "type": "Feature",
  "properties": {
    "iso:country":"US",
    "sg:address":"3 Government Plz",
    "sg:city":"Rome",
    "sg:classifiers":[
        {
            "category":"Government",
            "subcategory":"Office",
            "type":"Public Place"
        }
    ],
    "sg:phone":"+1 706 291 5107",
    "sg:postcode":"30161",
    "sg:province":"GA",
    "wof:name":"Floyd County Payroll",
    "wof:placetype":"venue"
},
  "geometry": {"coordinates":[-85.212114,34.168606],"type":"Point"}
}