{
  "type": "Feature",
  "properties": {
    "addr:full":"905 McCarty-dodd Rd Colbert GA 30628",
    "addr:housenumber":"905",
    "addr:postcode":"30628",
    "addr:street":"Mccarty-Dodd Rd",
    "iso:country":"US",
    "sg:address":"905 McCarty-dodd Rd",
    "sg:city":"Colbert",
    "sg:classifiers":[
        {
            "category":"Building & Trades",
            "subcategory":"Construction",
            "type":"Services"
        }
    ],
    "sg:phone":"+1 706 788 2325",
    "sg:postcode":"30628",
    "sg:province":"GA",
    "sg:tags":[
        "contractor"
    ],
    "wof:name":"McCarty Masonry",
    "wof:placetype":"venue"
},
  "geometry": {"coordinates":[-83.18377599999999,34.054898],"type":"Point"}
}