{
  "type": "Feature",
  "properties": {
    "addr:full":"3515 Harfield Dr SE Bethlehem GA 30620",
    "addr:housenumber":"3515",
    "addr:postcode":"30620",
    "addr:street":"Harfield Dr Se",
    "iso:country":"US",
    "sg:address":"3515 Harfield Dr SE",
    "sg:city":"Bethlehem",
    "sg:classifiers":[
        {
            "category":"Professional",
            "subcategory":"Management & Consulting",
            "type":"Services"
        }
    ],
    "sg:phone":"+1 770 277 0043",
    "sg:postcode":"30620",
    "sg:province":"GA",
    "wof:name":"Primitive Extra Dimension",
    "wof:placetype":"venue"
},
  "geometry": {"coordinates":[-83.83368900000001,33.953676],"type":"Point"}
}