{
  "type": "Feature",
  "properties": {
    "iso:country":"US",
    "sg:address":"566 Bell Telephone Rd",
    "sg:city":"Hazlehurst",
    "sg:classifiers":[
        {
            "category":"Shopping",
            "subcategory":"Gifts & Souvenirs",
            "type":"Retail Goods"
        }
    ],
    "sg:phone":"+1 912 375 4641",
    "sg:postcode":"31539",
    "sg:province":"GA",
    "sg:tags":[
        "shop"
    ],
    "wof:name":"Olde Red Barn Gift Shoppe",
    "wof:placetype":"venue"
},
  "geometry": {"coordinates":[-82.61453400000001,31.828075],"type":"Point"}
}