{
  "type": "Feature",
  "properties": {
    "addr:full":"5555 Oakbrook Pkwy Norcross GA 30093",
    "addr:housenumber":"5555",
    "addr:postcode":"30093",
    "addr:street":"Oakbrook Pkwy",
    "iso:country":"US",
    "sg:address":"5555 Oakbrook Pkwy",
    "sg:city":"Norcross",
    "sg:classifiers":[
        {
            "category":"Retail",
            "subcategory":"Repair Shop",
            "type":"Services"
        }
    ],
    "sg:phone":"+1 770 564 3310",
    "sg:postcode":"30093",
    "sg:province":"GA",
    "sg:tags":[
        "equipment",
        "photographic"
    ],
    "wof:name":"Camera Repair Japan",
    "wof:placetype":"venue"
},
  "geometry": {"coordinates":[-84.18322000000001,33.919611],"type":"Point"}
}