{
  "type": "Feature",
  "properties": {
    "iso:country":"US",
    "sg:address":"160 Country Club Dr",
    "sg:city":"Stockbridge",
    "sg:classifiers":[
        {
            "category":"Organizations",
            "subcategory":"Professional Association",
            "type":"Services"
        }
    ],
    "sg:phone":"+1 678 289 6555",
    "sg:postcode":"30281",
    "sg:province":"GA",
    "sg:tags":[
        "trade"
    ],
    "wof:name":"Georgia Nursing Home Assn",
    "wof:placetype":"venue"
},
  "geometry": {"coordinates":[-84.225328,33.506033],"type":"Point"}
}