{
  "type": "Feature",
  "properties": {
    "iso:country":"US",
    "sg:address":"1265 Woodington Cir",
    "sg:city":"Lawrenceville",
    "sg:classifiers":[
        {
            "category":"Building & Trades",
            "subcategory":"Landscaping Services",
            "type":"Services"
        }
    ],
    "sg:phone":"+1 404 914 2279",
    "sg:postcode":"30044",
    "sg:province":"GA",
    "sg:tags":[
        "lawn",
        "maintenance",
        "grounds"
    ],
    "wof:name":"Amigos Landscaping & Mntnc",
    "wof:placetype":"venue"
},
  "geometry": {"coordinates":[-84.12605000000001,33.938383],"type":"Point"}
}