{
  "type": "Feature",
  "properties": {
    "addr:full":"8665 Tara Blvd Jonesboro GA 30236",
    "addr:housenumber":"8665",
    "addr:postcode":"30236",
    "addr:street":"Tara Blvd",
    "iso:country":"US",
    "sg:address":"8665 Tara Blvd",
    "sg:city":"Jonesboro",
    "sg:classifiers":[
        {
            "category":"Shopping",
            "subcategory":"Discount & Variety Stores",
            "type":"Retail Goods"
        }
    ],
    "sg:phone":"+1 770 477 2722",
    "sg:postcode":"30236",
    "sg:province":"GA",
    "wof:name":"Big Lots",
    "wof:placetype":"venue"
},
  "geometry": {"coordinates":[-84.36254099999999,33.51502],"type":"Point"}
}