{
  "type": "Feature",
  "properties": {
    "addr:full":"1060 Kirkland Rd Covington GA 30016",
    "addr:housenumber":"1060",
    "addr:postcode":"30016",
    "addr:street":"Kirkland Rd",
    "iso:country":"US",
    "sg:address":"1060 Kirkland Rd",
    "sg:city":"Covington",
    "sg:classifiers":[
        {
            "category":"Building & Trades",
            "subcategory":"Construction",
            "type":"Services"
        }
    ],
    "sg:phone":"+1 770 385 5773",
    "sg:postcode":"30016",
    "sg:province":"GA",
    "sg:tags":[
        "carpentry",
        "general",
        "contractor"
    ],
    "wof:name":"Dale's Construction",
    "wof:placetype":"venue"
},
  "geometry": {"coordinates":[-83.943933,33.593906],"type":"Point"}
}