{
  "type": "Feature",
  "properties": {
    "iso:country":"US",
    "sg:address":"318 Martin Rd",
    "sg:city":"Twin City",
    "sg:classifiers":[
        {
            "category":"Organizations",
            "subcategory":"Religious Organization",
            "type":"Services"
        }
    ],
    "sg:phone":"+1 478 237 2645",
    "sg:postcode":"30471",
    "sg:province":"GA",
    "sg:tags":[
        "church"
    ],
    "wof:name":"Church Of Jesus Christ Of Lds",
    "wof:placetype":"venue"
},
  "geometry": {"coordinates":[-82.24054700000001,32.45237],"type":"Point"}
}