{
  "type": "Feature",
  "properties": {
    "iso:country":"US",
    "sg:address":"7000 Peachtree Dunwoody Rd NE",
    "sg:city":"Atlanta",
    "sg:classifiers":[
        {
            "category":"Health Services",
            "subcategory":"Dentist",
            "type":"Services"
        }
    ],
    "sg:phone":"+1 770 392 0766",
    "sg:postcode":"30328",
    "sg:province":"GA",
    "wof:name":"Dunwoody Family Dentistry DDS PC",
    "wof:placetype":"venue"
},
  "geometry": {"coordinates":[-84.354276,33.945713],"type":"Point"}
}