{
  "type": "Feature",
  "properties": {
    "iso:country":"US",
    "sg:address":"714 Avrett Cir",
    "sg:city":"Evans",
    "sg:classifiers":[
        {
            "category":"Manufacturing",
            "subcategory":"Chemicals & Compounds",
            "type":"Manufacturing & Wholesale Goods"
        }
    ],
    "sg:phone":"+1 706 228 2589",
    "sg:postcode":"30809",
    "sg:province":"GA",
    "sg:tags":[
        "body",
        "product",
        "bath",
        "natural",
        "care"
    ],
    "wof:name":"Asrai Springs Body & Spirits",
    "wof:placetype":"venue"
},
  "geometry": {"coordinates":[-82.18841500000001,33.557178],"type":"Point"}
}