{
  "type": "Feature",
  "properties": {
    "iso:country":"US",
    "sg:address":"1655 Georgia Highway 120",
    "sg:city":"Tallapoosa",
    "sg:classifiers":[
        {
            "category":"Education",
            "subcategory":"School",
            "type":"Public Place"
        }
    ],
    "sg:phone":"+1 770 574 5200",
    "sg:postcode":"30176",
    "sg:province":"GA",
    "sg:tags":[
        "high",
        "k-",
        "private"
    ],
    "wof:name":"Haralson County High School Vocational Office",
    "wof:placetype":"venue"
},
  "geometry": {"coordinates":[-85.249747,33.76743],"type":"Point"}
}