{
  "type": "Feature",
  "properties": {
    "iso:country":"US",
    "sg:address":"753 Broad St",
    "sg:city":"Augusta",
    "sg:classifiers":[
        {
            "category":"Health Services",
            "subcategory":"Doctor",
            "type":"Services"
        }
    ],
    "sg:phone":"+1 706 821 3356",
    "sg:postcode":"30901",
    "sg:province":"GA",
    "sg:tags":[
        "physician",
        "surgeon"
    ],
    "wof:name":"Charlotte Evans MD",
    "wof:placetype":"venue"
},
  "geometry": {"coordinates":[-81.965091,33.47535],"type":"Point"}
}