{
  "type": "Feature",
  "properties": {
    "iso:country":"US",
    "sg:address":"102 Walker Dr",
    "sg:city":"Centerville",
    "sg:classifiers":[
        {
            "category":"Organizations",
            "subcategory":"Religious Organization",
            "type":"Services"
        }
    ],
    "sg:phone":"+1 478 953 3422",
    "sg:postcode":"31028",
    "sg:province":"GA",
    "wof:name":"Eugene Barlow",
    "wof:placetype":"venue"
},
  "geometry": {"coordinates":[-83.687496,32.634146],"type":"Point"}
}