{
  "type": "Feature",
  "properties": {
    "iso:country":"US",
    "sg:address":"1605 Mars Hill Rd NW",
    "sg:city":"Acworth",
    "sg:classifiers":[
        {
            "category":"Place Of Worship",
            "subcategory":"Church",
            "type":"Public Place"
        }
    ],
    "sg:phone":"+1 770 428 5122",
    "sg:postcode":"30101",
    "sg:province":"GA",
    "sg:tags":[
        "churches-baptist"
    ],
    "wof:name":"Piney Grove Baptist Church",
    "wof:placetype":"venue"
},
  "geometry": {"coordinates":[-84.70723,33.994272],"type":"Point"}
}