{
  "type": "Feature",
  "properties": {
    "iso:country":"US",
    "sg:address":"449 Bettis Rd",
    "sg:city":"Chatsworth",
    "sg:classifiers":[
        {
            "category":"Organizations",
            "subcategory":"Religious Organization",
            "type":"Services"
        }
    ],
    "sg:phone":"+1 706 517 5844",
    "sg:postcode":"30705",
    "sg:province":"GA",
    "sg:tags":[
        "clergy"
    ],
    "wof:name":"Charles E Rogers",
    "wof:placetype":"venue"
},
  "geometry": {"coordinates":[-84.868453,34.775487],"type":"Point"}
}