{
  "type": "Feature",
  "properties": {
    "iso:country":"US",
    "sg:address":"2600 Century Parkway NE",
    "sg:city":"Atlanta",
    "sg:classifiers":[
        {
            "category":"Banks & Credit Unions",
            "subcategory":"Atm",
            "type":"Services"
        }
    ],
    "sg:phone":"+1 404 633 3030",
    "sg:postcode":"30345",
    "sg:province":"GA",
    "sg:tags":[
        "bankruptcy"
    ],
    "wof:name":"Jordan Carolyn Atty",
    "wof:placetype":"venue"
},
  "geometry": {"coordinates":[-84.29035399999999,33.857675],"type":"Point"}
}