{
  "type": "Feature",
  "properties": {
    "addr:full":"34 S Ellis St Camilla GA 31730",
    "addr:housenumber":"34",
    "addr:postcode":"31730",
    "addr:street":"S Ellis St",
    "iso:country":"US",
    "sg:address":"34 S Ellis St",
    "sg:city":"Camilla",
    "sg:classifiers":[
        {
            "category":"Health Services",
            "subcategory":"Hospital",
            "type":"Services"
        }
    ],
    "sg:phone":"+1 229 228 4225",
    "sg:postcode":"31730",
    "sg:province":"GA",
    "wof:name":"Archbold Hospital",
    "wof:placetype":"venue"
},
  "geometry": {"coordinates":[-84.204865,31.230528],"type":"Point"}
}