{
  "type": "Feature",
  "properties": {
    "addr:full":"118 Towson Ln Stone Mountain GA 30083",
    "addr:housenumber":"118",
    "addr:postcode":"30083",
    "addr:street":"Towson Ln",
    "iso:country":"US",
    "sg:address":"118 Towson Ln",
    "sg:city":"Stone Mountain",
    "sg:classifiers":[
        {
            "category":"Professional",
            "subcategory":"Business Services",
            "type":"Services"
        }
    ],
    "sg:phone":"+1 770 469 3662",
    "sg:postcode":"30083",
    "sg:province":"GA",
    "sg:tags":[
        "interior",
        "consultant",
        "design",
        "decorator"
    ],
    "wof:name":"Soho Interior Decorating",
    "wof:placetype":"venue"
},
  "geometry": {"coordinates":[-84.191545,33.813988],"type":"Point"}
}