{
  "type": "Feature",
  "properties": {
    "iso:country":"US",
    "sg:address":"6140 Old National Hwy",
    "sg:city":"Atlanta",
    "sg:classifiers":[
        {
            "category":"Insurance",
            "subcategory":"Insurance Agent",
            "type":"Services"
        },
        {
            "category":"Insurance",
            "subcategory":"Hazard Insurance",
            "type":"Services"
        },
        {
            "category":"Insurance",
            "subcategory":"Title Insurance",
            "type":"Services"
        },
        {
            "category":"Insurance",
            "subcategory":"Health Insurance",
            "type":"Services"
        },
        {
            "category":"Insurance",
            "subcategory":"Life Insurance",
            "type":"Services"
        }
    ],
    "sg:phone":"+1 770 996 4430",
    "sg:postcode":"30349",
    "sg:province":"GA",
    "sg:tags":[
        "business",
        "auto",
        "recreational",
        "disability",
        "homeowner",
        "casualty",
        "compensation",
        "commercial",
        "motorcycle",
        "vehicle",
        "worker",
        "property",
        "marine",
        "boat"
    ],
    "wof:name":"Franks & Associates Insurance Agency",
    "wof:placetype":"venue"
},
  "geometry": {"coordinates":[-84.46916400000001,33.587156],"type":"Point"}
}