{
  "type": "Feature",
  "properties": {
    "addr:full":"140 Woodstock Square Ave Woodstock GA 30189",
    "addr:housenumber":"140",
    "addr:postcode":"30189",
    "addr:street":"Woodstock Square Ave",
    "iso:country":"US",
    "sg:address":"140 Woodstock Square Ave",
    "sg:city":"Woodstock",
    "sg:classifiers":[
        {
            "category":"Coffee & Tea",
            "type":"Food & Drink"
        }
    ],
    "sg:menulink":"http://www.allmenus.com/ga/woodstock/107965-starbucks-coffee/menu/",
    "sg:phone":"+1 678 494 5307",
    "sg:postcode":"30189",
    "sg:province":"GA",
    "sg:tags":[
        "american"
    ],
    "wof:name":"Starbucks Coffee",
    "wof:placetype":"venue"
},
  "geometry": {"coordinates":[-84.543935,34.084122],"type":"Point"}
}