{
  "type": "Feature",
  "properties": {
    "addr:full":"953 Harrison Rd Carrollton GA 30117",
    "addr:housenumber":"953",
    "addr:postcode":"30117",
    "addr:street":"Harrison Rd",
    "iso:country":"US",
    "sg:address":"953 Harrison Rd",
    "sg:city":"Carrollton",
    "sg:classifiers":[
        {
            "category":"Professional",
            "type":"Services"
        }
    ],
    "sg:phone":"+1 770 562 2722",
    "sg:postcode":"30117",
    "sg:province":"GA",
    "wof:name":"Charles Campbell",
    "wof:placetype":"venue"
},
  "geometry": {"coordinates":[-85.17797400000001,33.609359],"type":"Point"}
}