{
  "type": "Feature",
  "properties": {
    "iso:country":"US",
    "sg:address":"2001 W 52nd St",
    "sg:city":"Savannah",
    "sg:classifiers":[
        {
            "category":"Building & Trades",
            "subcategory":"Construction",
            "type":"Services"
        }
    ],
    "sg:phone":"+1 912 233 9181",
    "sg:postcode":"31405",
    "sg:province":"GA",
    "sg:tags":[
        "heavy"
    ],
    "wof:name":"E & D Gen Cntrct Srv",
    "wof:placetype":"venue"
},
  "geometry": {"coordinates":[-81.1407,32.053445],"type":"Point"}
}