{
  "type": "Feature",
  "properties": {
    "addr:full":"119 Calloway Dr Macon GA 31204",
    "addr:housenumber":"119",
    "addr:postcode":"31204",
    "addr:street":"Calloway Dr",
    "iso:country":"US",
    "sg:address":"119 Calloway Dr",
    "sg:city":"Macon",
    "sg:classifiers":[
        {
            "category":"Insurance",
            "subcategory":"Insurance Agent",
            "type":"Services"
        }
    ],
    "sg:phone":"+1 912 742 1667",
    "sg:postcode":"31204",
    "sg:province":"GA",
    "wof:name":"Rosen & Associates Inc",
    "wof:placetype":"venue"
},
  "geometry": {"coordinates":[-83.658124,32.848504],"type":"Point"}
}