{
  "type": "Feature",
  "properties": {
    "addr:full":"1935 Watercrest Cir Lawrenceville GA 30043",
    "addr:housenumber":"1935",
    "addr:postcode":"30043",
    "addr:street":"Watercrest Cir",
    "iso:country":"US",
    "sg:address":"1935 Watercrest Cir",
    "sg:city":"Lawrenceville",
    "sg:classifiers":[
        {
            "category":"Building & Trades",
            "subcategory":"Construction",
            "type":"Services"
        }
    ],
    "sg:phone":"+1 770 822 9717",
    "sg:postcode":"30043",
    "sg:province":"GA",
    "sg:tags":[
        "interior",
        "design"
    ],
    "wof:name":"Shipman Design",
    "wof:placetype":"venue"
},
  "geometry": {"coordinates":[-84.01750199999999,33.9823],"type":"Point"}
}