{
  "type": "Feature",
  "properties": {
    "iso:country":"US",
    "sg:address":"1306 Us Highway 82 E",
    "sg:city":"Tifton",
    "sg:classifiers":[
        {
            "category":"Restaurant",
            "type":"Food & Drink"
        }
    ],
    "sg:menulink":"http://www.allmenus.com/ga/tifton/50750-ruby-tuesdays/menu/",
    "sg:phone":"+1 912 393 7829",
    "sg:postcode":"31794",
    "sg:province":"GA",
    "sg:tags":[
        "burger",
        "american"
    ],
    "wof:name":"Ruby Tuesdays",
    "wof:placetype":"venue"
},
  "geometry": {"coordinates":[-83.517769,31.472917],"type":"Point"}
}