{
  "type": "Feature",
  "properties": {
    "addr:full":"1155 5th St Augusta GA 30901",
    "addr:housenumber":"1155",
    "addr:postcode":"30901",
    "addr:street":"5Th St",
    "iso:country":"US",
    "sg:address":"1155 5th St",
    "sg:city":"Augusta",
    "sg:classifiers":[
        {
            "category":"Retail",
            "subcategory":"Auto Repair",
            "type":"Services"
        }
    ],
    "sg:phone":"+1 706 724 5341",
    "sg:postcode":"30901",
    "sg:province":"GA",
    "sg:tags":[
        "body",
        "automotive"
    ],
    "wof:name":"Richards Body Works Inc",
    "wof:placetype":"venue"
},
  "geometry": {"coordinates":[-81.965137,33.460536],"type":"Point"}
}