{
  "type": "Feature",
  "properties": {
    "iso:country":"US",
    "sg:address":"6724 Bells Ferry Rd",
    "sg:city":"Woodstock",
    "sg:classifiers":[
        {
            "category":"Government",
            "subcategory":"Office",
            "type":"Public Place"
        }
    ],
    "sg:phone":"+1 770 926 7155",
    "sg:postcode":"30189",
    "sg:province":"GA",
    "wof:name":"Cherokee County Fire Dist",
    "wof:placetype":"venue"
},
  "geometry": {"coordinates":[-84.586089,34.13391],"type":"Point"}
}