{
  "type": "Feature",
  "properties": {
    "iso:country":"US",
    "sg:address":"6540 State Rte 315",
    "sg:city":"Cataula",
    "sg:classifiers":[
        {
            "category":"Building & Trades",
            "subcategory":"Construction",
            "type":"Services"
        }
    ],
    "sg:phone":"+1 706 324 6900",
    "sg:postcode":"31804",
    "sg:province":"GA",
    "sg:tags":[
        "home",
        "contractor",
        "family",
        "general"
    ],
    "wof:name":"Jim Mc Clung Builders Inc",
    "wof:placetype":"venue"
},
  "geometry": {"coordinates":[-84.94777000000001,32.670903],"type":"Point"}
}