{
  "type": "Feature",
  "properties": {
    "addr:full":"1174 West Ave SW Conyers GA 30012",
    "addr:housenumber":"1174",
    "addr:postcode":"30012",
    "addr:street":"West Ave Sw",
    "iso:country":"US",
    "sg:address":"1174 West Ave SW",
    "sg:city":"Conyers",
    "sg:classifiers":[
        {
            "category":"Restaurant",
            "type":"Food & Drink"
        }
    ],
    "sg:menulink":"http://www.allmenus.com/ga/conyers/140387-waffle-house/menu/",
    "sg:phone":"+1 678 354 7741",
    "sg:postcode":"30012",
    "sg:province":"GA",
    "sg:tags":[
        "american"
    ],
    "wof:name":"Waffle House",
    "wof:placetype":"venue"
},
  "geometry": {"coordinates":[-84.02668199999999,33.666274],"type":"Point"}
}