{
  "type": "Feature",
  "properties": {
    "addr:full":"123 Peachtree Pl Byron GA 31088",
    "addr:housenumber":"123",
    "addr:postcode":"31088",
    "addr:street":"Peachtree Pl",
    "iso:country":"US",
    "sg:address":"123 Peachtree Pl",
    "sg:city":"Byron",
    "sg:classifiers":[
        {
            "category":"Autos & Motor Vehicles",
            "subcategory":"Recreational Vehicle Sales",
            "type":"Retail Goods"
        }
    ],
    "sg:phone":"+1 478 956 5535",
    "sg:postcode":"31088",
    "sg:province":"GA",
    "wof:name":"Not Just Parts",
    "wof:placetype":"venue"
},
  "geometry": {"coordinates":[-83.620408,32.610399],"type":"Point"}
}