{
  "type": "Feature",
  "properties": {
    "iso:country":"US",
    "sg:address":"8450 Cochran Rd SW",
    "sg:city":"Fairburn",
    "sg:classifiers":[
        {
            "category":"Building & Trades",
            "subcategory":"Landscaping Services",
            "type":"Services"
        }
    ],
    "sg:phone":"+1 770 964 2879",
    "sg:postcode":"30213",
    "sg:province":"GA",
    "sg:tags":[
        "lawn",
        "maintenance",
        "grounds"
    ],
    "wof:name":"Southern Lawn Svc",
    "wof:placetype":"venue"
},
  "geometry": {"coordinates":[-84.65537500000001,33.657469],"type":"Point"}
}