{
  "type": "Feature",
  "properties": {
    "addr:full":"200 Cobb Pkwy N Bldg 200 Marietta GA 30062",
    "addr:housenumber":"200;200",
    "addr:postcode":"30062",
    "addr:street":"Cobb Pkwy N Bldg",
    "iso:country":"US",
    "sg:address":"200 Cobb Pkwy N Bldg 200",
    "sg:city":"Marietta",
    "sg:phone":"+1 770 642 2273",
    "sg:postcode":"30062",
    "sg:province":"GA",
    "wof:name":"Southwest Greens International",
    "wof:placetype":"venue"
},
  "geometry": {"coordinates":[-84.523836,33.956399],"type":"Point"}
}