{
  "type": "Feature",
  "properties": {
    "addr:full":"180 Westwood Dr Athens GA 30606",
    "addr:housenumber":"180",
    "addr:postcode":"30606",
    "addr:street":"Westwood Dr",
    "iso:country":"US",
    "sg:address":"180 Westwood Dr",
    "sg:city":"Athens",
    "sg:classifiers":[
        {
            "category":"Building & Trades",
            "subcategory":"Pest Control",
            "type":"Services"
        }
    ],
    "sg:phone":"+1 706 369 3630",
    "sg:postcode":"30606",
    "sg:province":"GA",
    "wof:name":"PAR Six Pest & Termite Control",
    "wof:placetype":"venue"
},
  "geometry": {"coordinates":[-83.43771,33.972909],"type":"Point"}
}