{
  "type": "Feature",
  "properties": {
    "iso:country":"US",
    "sg:address":"1825 Grassland Pkwy",
    "sg:city":"Alpharetta",
    "sg:classifiers":[
        {
            "category":"Building & Trades",
            "subcategory":"Electrical",
            "type":"Services"
        }
    ],
    "sg:phone":"+1 770 442 3161",
    "sg:postcode":"30004",
    "sg:province":"GA",
    "sg:tags":[
        "installs",
        "home",
        "security",
        "theater",
        "system"
    ],
    "wof:name":"Willett Security Systems",
    "wof:placetype":"venue"
},
  "geometry": {"coordinates":[-84.244801,34.142892],"type":"Point"}
}