{
  "type": "Feature",
  "properties": {
    "iso:country":"US",
    "sg:address":"6096 Gumlog Rd",
    "sg:city":"Martin",
    "sg:classifiers":[
        {
            "category":"Building & Trades",
            "subcategory":"Construction",
            "type":"Services"
        }
    ],
    "sg:phone":"+1 706 356 5629",
    "sg:postcode":"30557",
    "sg:province":"GA",
    "sg:tags":[
        "house"
    ],
    "wof:name":"Apex Quality Homes Inc",
    "wof:placetype":"venue"
},
  "geometry": {"coordinates":[-83.132187,34.508505],"type":"Point"}
}