{
  "type": "Feature",
  "properties": {
    "addr:full":"4200 Snapfinger Woods Dr Decatur GA 30035",
    "addr:housenumber":"4200",
    "addr:postcode":"30035",
    "addr:street":"Snapfinger Woods Dr",
    "iso:country":"US",
    "sg:address":"4200 Snapfinger Woods Dr",
    "sg:city":"Decatur",
    "sg:classifiers":[
        {
            "category":"Freight",
            "type":"Transportation"
        }
    ],
    "sg:phone":"+1 404 284 6697",
    "sg:postcode":"30035",
    "sg:province":"GA",
    "sg:tags":[
        "warehouse",
        "mini",
        "commercial",
        "storage"
    ],
    "wof:name":"Public Storage Inc",
    "wof:placetype":"venue"
},
  "geometry": {"coordinates":[-84.217788,33.714901],"type":"Point"}
}