{
  "type": "Feature",
  "properties": {
    "addr:full":"2662 Cottonwood Dr Marietta GA 30066",
    "addr:housenumber":"2662",
    "addr:postcode":"30066",
    "addr:street":"Cottonwood Dr",
    "iso:country":"US",
    "sg:address":"2662 Cottonwood Dr",
    "sg:city":"Marietta",
    "sg:classifiers":[
        {
            "category":"Professional",
            "subcategory":"Management & Consulting",
            "type":"Services"
        }
    ],
    "sg:phone":"+1 770 425 2553",
    "sg:postcode":"30066",
    "sg:province":"GA",
    "sg:tags":[
        "aviation",
        "consultant"
    ],
    "wof:name":"The Aviation Dept Llc",
    "wof:placetype":"venue"
},
  "geometry": {"coordinates":[-84.544072,34.016358],"type":"Point"}
}