{
  "type": "Feature",
  "properties": {
    "addr:full":"943 Thomaston St Barnesville GA 30204",
    "addr:housenumber":"943",
    "addr:postcode":"30204",
    "addr:street":"Thomaston St",
    "iso:country":"US",
    "sg:address":"943 Thomaston St",
    "sg:city":"Barnesville",
    "sg:classifiers":[
        {
            "category":"Insurance",
            "subcategory":"Hazard Insurance",
            "type":"Services"
        }
    ],
    "sg:phone":"+1 770 358 1108",
    "sg:postcode":"30204",
    "sg:province":"GA",
    "sg:website":"http://statefarm.mqgroup.com/url.asp?usr=112214",
    "wof:name":"State Farm Insurance Agent-Phillip Bell",
    "wof:placetype":"venue"
},
  "geometry": {"coordinates":[-84.163455,33.041284],"type":"Point"}
}