{
  "type": "Feature",
  "properties": {
    "iso:country":"US",
    "sg:address":"742 Milledgeville Rd",
    "sg:city":"Eatonton",
    "sg:classifiers":[
        {
            "category":"Autos & Motor Vehicles",
            "subcategory":"Fuel & Gas Station",
            "type":"Retail Goods"
        }
    ],
    "sg:phone":"+1 706 485 9740",
    "sg:postcode":"31024",
    "sg:province":"GA",
    "sg:tags":[
        "food",
        "convenience",
        "gasoline",
        "store"
    ],
    "wof:name":"Golden Pantry Store Number 106",
    "wof:placetype":"venue"
},
  "geometry": {"coordinates":[-83.316676,33.235244],"type":"Point"}
}