{
  "type": "Feature",
  "properties": {
    "addr:full":"464 Patricia Way Marietta GA 30064",
    "addr:housenumber":"464",
    "addr:postcode":"30064",
    "addr:street":"Patricia Way",
    "iso:country":"US",
    "sg:address":"464 Patricia Way",
    "sg:city":"Marietta",
    "sg:classifiers":[
        {
            "category":"Professional",
            "subcategory":"Engineering",
            "type":"Services"
        }
    ],
    "sg:phone":"+1 770 590 7307",
    "sg:postcode":"30064",
    "sg:province":"GA",
    "wof:name":"All Design & Graphics",
    "wof:placetype":"venue"
},
  "geometry": {"coordinates":[-84.566644,33.956773],"type":"Point"}
}