{
  "type": "Feature",
  "properties": {
    "addr:full":"534 Spring Head Rd Colquitt GA 39837",
    "addr:housenumber":"534",
    "addr:postcode":"39837",
    "addr:street":"Spring Head Rd",
    "iso:country":"US",
    "sg:address":"534 Spring Head Rd",
    "sg:city":"Colquitt",
    "sg:classifiers":[
        {
            "category":"Professional",
            "subcategory":"Detective & Security Services",
            "type":"Services"
        }
    ],
    "sg:phone":"+1 229 416 7785",
    "sg:postcode":"39837",
    "sg:province":"GA",
    "sg:tags":[
        "information",
        "bureau"
    ],
    "wof:name":"Brand Professional Services, Inc.",
    "wof:placetype":"venue"
},
  "geometry": {"coordinates":[-84.812999,31.201348],"type":"Point"}
}