{
  "type": "Feature",
  "properties": {
    "addr:full":"1210 Ridge Rd Cairo GA 39827",
    "addr:housenumber":"1210",
    "addr:postcode":"39827",
    "addr:street":"Ridge Rd",
    "iso:country":"US",
    "sg:address":"1210 Ridge Rd",
    "sg:city":"Cairo",
    "sg:classifiers":[
        {
            "category":"Building & Trades",
            "subcategory":"Landscaping Services",
            "type":"Services"
        }
    ],
    "sg:phone":"+1 229 377 6831",
    "sg:postcode":"39827",
    "sg:province":"GA",
    "wof:name":"Pearson Stump Removal",
    "wof:placetype":"venue"
},
  "geometry": {"coordinates":[-84.227524,30.963502],"type":"Point"}
}