{
  "type": "Feature",
  "properties": {
    "iso:country":"US",
    "sg:address":"412 Thomas Dr",
    "sg:city":"Forest Park",
    "sg:classifiers":[
        {
            "category":"Wholesale",
            "subcategory":"Fruits & Vegetables",
            "type":"Manufacturing & Wholesale Goods"
        }
    ],
    "sg:phone":"+1 404 363 8619",
    "sg:postcode":"30297",
    "sg:province":"GA",
    "wof:name":"Moss Produce",
    "wof:placetype":"venue"
},
  "geometry": {"coordinates":[-84.377819,33.588401],"type":"Point"}
}