{
  "type": "Feature",
  "properties": {
    "iso:country":"US",
    "sg:address":"639 Garden Walk Blvd # 1906",
    "sg:city":"Atlanta",
    "sg:classifiers":[
        {
            "category":"Real Estate",
            "subcategory":"Architect",
            "type":"Services"
        }
    ],
    "sg:phone":"+1 770 996 2119",
    "sg:postcode":"30349",
    "sg:province":"GA",
    "sg:tags":[
        "architects'",
        "specification",
        "construction",
        "builders'",
        "architectural"
    ],
    "wof:name":"Michael Tchouaffe Architects, Inc.",
    "wof:placetype":"venue"
},
  "geometry": {"coordinates":[-84.410858,33.594429],"type":"Point"}
}