{
  "type": "Feature",
  "properties": {
    "addr:full":"2443 Hamilton Mill Pkwy Dacula GA 30019",
    "addr:housenumber":"2443",
    "addr:postcode":"ga 30019",
    "addr:street":"Hamilton Mill Pkwy",
    "iso:country":"US",
    "sg:address":"2443 Hamilton Mill Pkwy",
    "sg:city":"Dacula",
    "sg:classifiers":[
        {
            "category":"Restaurant",
            "type":"Food & Drink"
        }
    ],
    "sg:phone":"+1 770 614 3500",
    "sg:postcode":"30019",
    "sg:province":"GA",
    "wof:name":"Mc Donald's",
    "wof:placetype":"venue"
},
  "geometry": {"coordinates":[-83.913764,34.058214],"type":"Point"}
}