{
  "type": "Feature",
  "properties": {
    "addr:full":"1319 W Hill Ave Valdosta GA 31601",
    "addr:housenumber":"1319",
    "addr:postcode":"31601",
    "addr:street":"W Hill Ave",
    "iso:country":"US",
    "sg:address":"1319 W Hill Ave",
    "sg:city":"Valdosta",
    "sg:classifiers":[
        {
            "category":"Retail",
            "subcategory":"Auto Repair",
            "type":"Services"
        }
    ],
    "sg:phone":"+1 229 244 8987",
    "sg:postcode":"31601",
    "sg:province":"GA",
    "sg:tags":[
        "repairing",
        "automobile"
    ],
    "wof:name":"Lee Millers' Auto Svc Ctr",
    "wof:placetype":"venue"
},
  "geometry": {"coordinates":[-83.29637,30.823883],"type":"Point"}
}