{
  "type": "Feature",
  "properties": {
    "iso:country":"US",
    "sg:address":"1901 Montreal Rd",
    "sg:city":"Tucker",
    "sg:classifiers":[
        {
            "category":"Organizations",
            "subcategory":"Religious Organization",
            "type":"Services"
        }
    ],
    "sg:phone":"+1 678 205 5376",
    "sg:postcode":"30084",
    "sg:province":"GA",
    "sg:website":"www.newhopeforyourlife.com",
    "wof:name":"New Hope Ministries International",
    "wof:placetype":"venue"
},
  "geometry": {"coordinates":[-84.256619,33.838648],"type":"Point"}
}