{
  "type": "Feature",
  "properties": {
    "addr:full":"1530 Dunwoody Village Pkw Atlanta GA 30338",
    "addr:housenumber":"1530",
    "addr:postcode":"30338",
    "addr:street":"Dunwoody Village",
    "iso:country":"US",
    "sg:address":"1530 Dunwoody Village Pkw",
    "sg:city":"Atlanta",
    "sg:classifiers":[
        {
            "category":"Professional",
            "subcategory":"Lawyer & Legal Services",
            "type":"Services"
        }
    ],
    "sg:phone":"+1 770 390 9935",
    "sg:postcode":"30338",
    "sg:province":"GA",
    "wof:name":"Norvell Ray C Atty Jr",
    "wof:placetype":"venue"
},
  "geometry": {"coordinates":[-84.331654,33.947862],"type":"Point"}
}