{
  "type": "Feature",
  "properties": {
    "addr:full":"4111 Bankhead Hwy Lithia Springs GA 30122",
    "addr:housenumber":"4111",
    "addr:postcode":"30122",
    "addr:street":"Bankhead Hwy",
    "iso:country":"US",
    "sg:address":"4111 Bankhead Hwy",
    "sg:city":"Lithia Springs",
    "sg:classifiers":[
        {
            "category":"Professional",
            "type":"Services"
        }
    ],
    "sg:phone":"+1 770 948 4787",
    "sg:postcode":"30122",
    "sg:province":"GA",
    "wof:name":"Rhino Linings",
    "wof:placetype":"venue"
},
  "geometry": {"coordinates":[-84.673346,33.793365],"type":"Point"}
}