{
  "type": "Feature",
  "properties": {
    "addr:full":"925 Victoria Landing Dr Woodstock GA 30189",
    "addr:housenumber":"925",
    "addr:postcode":"30189",
    "addr:street":"Victoria Landing Dr",
    "iso:country":"US",
    "sg:address":"925 Victoria Landing Dr",
    "sg:city":"Woodstock",
    "sg:classifiers":[
        {
            "category":"Real Estate",
            "subcategory":"Real Estate Services",
            "type":"Services"
        },
        {
            "category":"Banks & Credit Unions",
            "subcategory":"Financial Services",
            "type":"Services"
        }
    ],
    "sg:phone":"+1 770 516 8025",
    "sg:postcode":"30189",
    "sg:province":"GA",
    "sg:tags":[
        "loan",
        "processing"
    ],
    "wof:name":"Prime Mortgage Financial Center, Inc",
    "wof:placetype":"venue"
},
  "geometry": {"coordinates":[-84.60874200000001,34.148312],"type":"Point"}
}