{
  "type": "Feature",
  "properties": {
    "addr:full":"1091 Stovall Blvd NE Atlanta GA 30319",
    "addr:housenumber":"1091",
    "addr:postcode":"30319",
    "addr:street":"Stovall Blvd Ne",
    "iso:country":"US",
    "sg:address":"1091 Stovall Blvd NE",
    "sg:city":"Atlanta",
    "sg:classifiers":[
        {
            "category":"Communications",
            "subcategory":"Film & Video Production",
            "type":"Services"
        }
    ],
    "sg:phone":"+1 404 841 0534",
    "sg:postcode":"30319",
    "sg:province":"GA",
    "sg:tags":[
        "taping"
    ],
    "wof:name":"Video Assest Inc",
    "wof:placetype":"venue"
},
  "geometry": {"coordinates":[-84.35378799999999,33.860254],"type":"Point"}
}