{
  "type": "Feature",
  "properties": {
    "addr:full":"2920 Oak Cir Columbus GA 31907",
    "addr:housenumber":"2920",
    "addr:postcode":"31907",
    "addr:street":"Oak Cir",
    "iso:country":"US",
    "sg:address":"2920 Oak Cir",
    "sg:city":"Columbus",
    "sg:classifiers":[
        {
            "category":"Building & Trades",
            "subcategory":"Construction",
            "type":"Services"
        }
    ],
    "sg:phone":"+1 706 561 9400",
    "sg:postcode":"31907",
    "sg:province":"GA",
    "sg:tags":[
        "home",
        "builder"
    ],
    "wof:name":"Ronald A Edwards Construction",
    "wof:placetype":"venue"
},
  "geometry": {"coordinates":[-84.93176099999999,32.491761],"type":"Point"}
}