{
  "type": "Feature",
  "properties": {
    "addr:full":"4989 Lanes Bridge Rd Jesup GA 31545",
    "addr:housenumber":"4989",
    "addr:postcode":"31545",
    "addr:street":"Lanes Bridge Rd",
    "iso:country":"US",
    "sg:address":"4989 Lanes Bridge Rd",
    "sg:city":"Jesup",
    "sg:classifiers":[
        {
            "category":"Building & Trades",
            "subcategory":"Construction",
            "type":"Services"
        }
    ],
    "sg:phone":"+1 912 230 4778",
    "sg:postcode":"31545",
    "sg:province":"GA",
    "sg:tags":[
        "wallcoverings-installation",
        "wallpaper",
        "painting",
        "contractor"
    ],
    "wof:name":"Cox Painting",
    "wof:placetype":"venue"
},
  "geometry": {"coordinates":[-81.931208,31.678392],"type":"Point"}
}