{
  "type": "Feature",
  "properties": {
    "iso:country":"US",
    "sg:address":"1780 Hephzibah Church Rd",
    "sg:city":"Lincolnton",
    "sg:classifiers":[
        {
            "category":"Organizations",
            "subcategory":"Religious Organization",
            "type":"Services"
        }
    ],
    "sg:phone":"+1 706 359 6989",
    "sg:postcode":"30817",
    "sg:province":"GA",
    "sg:tags":[
        "clergy"
    ],
    "wof:name":"Danner Allen Rev",
    "wof:placetype":"venue"
},
  "geometry": {"coordinates":[-82.53524299999999,33.741302],"type":"Point"}
}