{
  "type": "Feature",
  "properties": {
    "addr:full":"105 Walnut St Montezuma GA 31063",
    "addr:housenumber":"105",
    "addr:postcode":"31063",
    "addr:street":"Walnut St",
    "iso:country":"US",
    "sg:address":"105 Walnut St",
    "sg:city":"Montezuma",
    "sg:classifiers":[
        {
            "category":"Health Services",
            "subcategory":"Doctor",
            "type":"Services"
        }
    ],
    "sg:phone":"+1 478 472 4633",
    "sg:postcode":"31063",
    "sg:province":"GA",
    "sg:tags":[
        "physician",
        "surgeon"
    ],
    "wof:name":"Sumter Pediatrics Montezuma",
    "wof:placetype":"venue"
},
  "geometry": {"coordinates":[-84.022234,32.293457],"type":"Point"}
}