{
  "type": "Feature",
  "properties": {
    "iso:country":"US",
    "sg:address":"1910 Devon Dr",
    "sg:city":"Albany",
    "sg:classifiers":[
        {
            "category":"Manufacturing",
            "subcategory":"Chemicals & Compounds",
            "type":"Manufacturing & Wholesale Goods"
        }
    ],
    "sg:phone":"+1 229 439 4198",
    "sg:postcode":"31721",
    "sg:province":"GA",
    "sg:tags":[
        "leather",
        "finisher"
    ],
    "wof:name":"Leather Medic",
    "wof:placetype":"venue"
},
  "geometry": {"coordinates":[-84.227234,31.597662],"type":"Point"}
}