{
  "type": "Feature",
  "properties": {
    "addr:full":"4918 Covington Hwy Decatur GA 30035",
    "addr:housenumber":"4918",
    "addr:postcode":"30035",
    "addr:street":"Covington Hwy",
    "iso:country":"US",
    "sg:address":"4918 Covington Hwy",
    "sg:city":"Decatur",
    "sg:classifiers":[
        {
            "category":"Shopping",
            "subcategory":"Pawn Shop",
            "type":"Retail Goods"
        }
    ],
    "sg:phone":"+1 404 289 1860",
    "sg:postcode":"30035",
    "sg:province":"GA",
    "wof:name":"Title Max",
    "wof:placetype":"venue"
},
  "geometry": {"coordinates":[-84.213227,33.734507],"type":"Point"}
}