{
  "type": "Feature",
  "properties": {
    "addr:full":"3321 Piney Cove Loganville GA 30052",
    "addr:housenumber":"3321",
    "addr:postcode":"30052",
    "addr:street":"Piney Cove",
    "iso:country":"US",
    "sg:address":"3321 Piney Cove",
    "sg:city":"Loganville",
    "sg:classifiers":[
        {
            "category":"Professional",
            "type":"Services"
        }
    ],
    "sg:phone":"+1 770 554 9889",
    "sg:postcode":"30052",
    "sg:province":"GA",
    "wof:name":"Sharons Transcripts",
    "wof:placetype":"venue"
},
  "geometry": {"coordinates":[-83.879012,33.885012],"type":"Point"}
}