{
  "type": "Feature",
  "properties": {
    "addr:full":"4890 Ocmulgee East Blvd Macon GA 31217",
    "addr:housenumber":"4890",
    "addr:postcode":"31217",
    "addr:street":"Ocmulgee East Blvd",
    "iso:country":"US",
    "sg:address":"4890 Ocmulgee East Blvd",
    "sg:city":"Macon",
    "sg:classifiers":[
        {
            "category":"Restaurant",
            "type":"Food & Drink"
        }
    ],
    "sg:menulink":"http://www.allmenus.com/ga/swift-creek/101700-huddle-house/menu/",
    "sg:phone":"+1 478 745 1145",
    "sg:postcode":"31217",
    "sg:province":"GA",
    "sg:tags":[
        "american",
        "diner"
    ],
    "wof:name":"Huddle House",
    "wof:placetype":"venue"
},
  "geometry": {"coordinates":[-83.569219,32.796708],"type":"Point"}
}