{
  "type": "Feature",
  "properties": {
    "addr:full":"2115 Windsor Spring Rd Augusta GA 30906",
    "addr:housenumber":"2115",
    "addr:postcode":"30906",
    "addr:street":"Windsor Spring Rd",
    "iso:country":"US",
    "sg:address":"2115 Windsor Spring Rd",
    "sg:city":"Augusta",
    "sg:classifiers":[
        {
            "category":"Shopping",
            "subcategory":"Department Store",
            "type":"Retail Goods"
        }
    ],
    "sg:phone":"+1 706 793 9748",
    "sg:postcode":"30906",
    "sg:province":"GA",
    "sg:tags":[
        "discount"
    ],
    "wof:name":"Wal-Mart",
    "wof:placetype":"venue"
},
  "geometry": {"coordinates":[-82.029861,33.407651],"type":"Point"}
}