{
  "type": "Feature",
  "properties": {
    "addr:full":"4750 Keith Bridge Rd Cumming GA 30041",
    "addr:housenumber":"4750",
    "addr:postcode":"30041",
    "addr:street":"Keith Bridge Rd",
    "iso:country":"US",
    "sg:address":"4750 Keith Bridge Rd",
    "sg:city":"Cumming",
    "sg:classifiers":[
        {
            "category":"Real Estate",
            "subcategory":"Surveying",
            "type":"Services"
        }
    ],
    "sg:phone":"+1 770 887 5018",
    "sg:postcode":"30041",
    "sg:province":"GA",
    "wof:name":"Hillis A Bennett",
    "wof:placetype":"venue"
},
  "geometry": {"coordinates":[-84.04677599999999,34.278811],"type":"Point"}
}