{
  "type": "Feature",
  "properties": {
    "addr:full":"566 16th Ave Albany GA 31701",
    "addr:housenumber":"566",
    "addr:postcode":"31701",
    "addr:street":"16Th Ave",
    "iso:country":"US",
    "sg:address":"566 16th Ave",
    "sg:city":"Albany",
    "sg:classifiers":[
        {
            "category":"Real Estate",
            "subcategory":"Real Estate Operator",
            "type":"Services"
        }
    ],
    "sg:phone":"+1 229 888 7696",
    "sg:postcode":"31701",
    "sg:province":"GA",
    "sg:tags":[
        "building",
        "apartment"
    ],
    "wof:name":"Dmr Retirement Center",
    "wof:placetype":"venue"
},
  "geometry": {"coordinates":[-84.164091,31.608766],"type":"Point"}
}