{
  "type": "Feature",
  "properties": {
    "addr:full":"3805 Pleasant Hill Rd Duluth GA 30096",
    "addr:housenumber":"3805",
    "addr:postcode":"30096",
    "addr:street":"Pleasant Hill Rd",
    "iso:country":"US",
    "sg:address":"3805 Pleasant Hill Rd",
    "sg:city":"Duluth",
    "sg:classifiers":[
        {
            "category":"Community Center",
            "type":"Public Place"
        }
    ],
    "sg:phone":"+1 678 584 7000",
    "sg:postcode":"30096",
    "sg:province":"GA",
    "sg:tags":[
        "medical"
    ],
    "wof:name":"Gwinnett Health System-1000 Medical Center Blvd NW",
    "wof:placetype":"venue"
},
  "geometry": {"coordinates":[-84.16269699999999,33.9953],"type":"Point"}
}