{
  "type": "Feature",
  "properties": {
    "iso:country":"US",
    "sg:address":"3675 Crestwood Pkwy NW",
    "sg:city":"Duluth",
    "sg:classifiers":[
        {
            "category":"Wholesale",
            "subcategory":"Computers",
            "type":"Manufacturing & Wholesale Goods"
        }
    ],
    "sg:phone":"+1 678 473 3020",
    "sg:postcode":"30096",
    "sg:province":"GA",
    "wof:name":"Magenic Tech",
    "wof:placetype":"venue"
},
  "geometry": {"coordinates":[-84.129986,33.947251],"type":"Point"}
}