{
  "type": "Feature",
  "properties": {
    "iso:country":"US",
    "sg:address":"2463 Cedartown Hwy",
    "sg:city":"Rockmart",
    "sg:classifiers":[
        {
            "category":"Food & Beverages",
            "subcategory":"Specialty",
            "type":"Retail Goods"
        }
    ],
    "sg:phone":"+1 770 684 7727",
    "sg:postcode":"30153",
    "sg:province":"GA",
    "sg:tags":[
        "health",
        "diet"
    ],
    "wof:name":"Mary's Health Cupboard",
    "wof:placetype":"venue"
},
  "geometry": {"coordinates":[-85.11153,34.009096],"type":"Point"}
}