{
  "type": "Feature",
  "properties": {
    "addr:full":"1819 Emory Stephens Rd Murrayville GA 30564",
    "addr:housenumber":"1819",
    "addr:postcode":"30564",
    "addr:street":"Emory Stephens Rd",
    "iso:country":"US",
    "sg:address":"1819 Emory Stephens Rd",
    "sg:city":"Murrayville",
    "sg:classifiers":[
        {
            "category":"Personal",
            "subcategory":"Beauty Salon",
            "type":"Services"
        }
    ],
    "sg:phone":"+1 706 864 3290",
    "sg:postcode":"30564",
    "sg:province":"GA",
    "sg:tags":[
        "shop"
    ],
    "wof:name":"Susie's Cut & Style",
    "wof:placetype":"venue"
},
  "geometry": {"coordinates":[-83.85942300000001,34.522352],"type":"Point"}
}