{
  "type": "Feature",
  "properties": {
    "iso:country":"US",
    "sg:address":"1070 Appling Harlem Rd",
    "sg:city":"Harlem",
    "sg:classifiers":[
        {
            "category":"Education",
            "subcategory":"School",
            "type":"Public Place"
        }
    ],
    "sg:phone":"+1 706 556 5980",
    "sg:postcode":"30814",
    "sg:province":"GA",
    "wof:name":"Harlem High School",
    "wof:placetype":"venue"
},
  "geometry": {"coordinates":[-82.31569500000001,33.479702],"type":"Point"}
}