{
  "type": "Feature",
  "properties": {
    "iso:country":"US",
    "sg:address":"1821 Carrollton Villa Rica Hwy",
    "sg:city":"Villa Rica",
    "sg:classifiers":[
        {
            "category":"Food & Beverages",
            "subcategory":"Bakery",
            "type":"Retail Goods"
        }
    ],
    "sg:phone":"+1 770 456 1588",
    "sg:postcode":"30180",
    "sg:province":"GA",
    "sg:tags":[
        "baker"
    ],
    "wof:name":"Mary Anns Bakery & Sandwich S",
    "wof:placetype":"venue"
},
  "geometry": {"coordinates":[-84.945926,33.683795],"type":"Point"}
}