{
  "type": "Feature",
  "properties": {
    "addr:full":"1809 Antioch Rd Cordele GA 31015",
    "addr:housenumber":"1809",
    "addr:postcode":"31015",
    "addr:street":"Antioch Rd",
    "iso:country":"US",
    "sg:address":"1809 Antioch Rd",
    "sg:city":"Cordele",
    "sg:classifiers":[
        {
            "category":"Banks & Credit Unions",
            "subcategory":"Investment Brokerage",
            "type":"Services"
        }
    ],
    "sg:phone":"+1 229 535 6204",
    "sg:postcode":"31015",
    "sg:province":"GA",
    "sg:tags":[
        "advisory"
    ],
    "wof:name":"Patrick Investment Corporation",
    "wof:placetype":"venue"
},
  "geometry": {"coordinates":[-83.90009000000001,31.869121],"type":"Point"}
}