{
  "type": "Feature",
  "properties": {
    "iso:country":"US",
    "sg:address":"641 Hospital Rd",
    "sg:city":"Commerce",
    "sg:classifiers":[
        {
            "category":"Health Services",
            "subcategory":"Doctor",
            "type":"Services"
        }
    ],
    "sg:phone":"+1 706 335 2992",
    "sg:postcode":"30529",
    "sg:province":"GA",
    "sg:tags":[
        "clinic"
    ],
    "wof:name":"Commerce Women's Clinic",
    "wof:placetype":"venue"
},
  "geometry": {"coordinates":[-83.469486,34.215835],"type":"Point"}
}