{
  "type": "Feature",
  "properties": {
    "iso:country":"US",
    "sg:address":"2841 Vernon Rd NW",
    "sg:city":"Atlanta",
    "sg:classifiers":[
        {
            "category":"Wholesale",
            "subcategory":"Farm Supplies",
            "type":"Manufacturing & Wholesale Goods"
        }
    ],
    "sg:phone":"+1 404 963 1883",
    "sg:postcode":"30305",
    "sg:province":"GA",
    "wof:name":"Atlanta Ecom Incorporated",
    "wof:placetype":"venue"
},
  "geometry": {"coordinates":[-84.391176,33.832031],"type":"Point"}
}