{
  "type": "Feature",
  "properties": {
    "iso:country":"US",
    "sg:address":"944 Burnt Hickory Rd NW",
    "sg:city":"Marietta",
    "sg:classifiers":[
        {
            "category":"Real Estate",
            "subcategory":"Real Estate Operator",
            "type":"Services"
        }
    ],
    "sg:phone":"+1 770 919 0317",
    "sg:postcode":"30064",
    "sg:province":"GA",
    "sg:tags":[
        "building",
        "nonresidential"
    ],
    "wof:name":"Palatine Properties Inc",
    "wof:placetype":"venue"
},
  "geometry": {"coordinates":[-84.57988400000001,33.954651],"type":"Point"}
}