{
  "type": "Feature",
  "properties": {
    "addr:full":"310 Walton Mill Rd Appling GA 30802",
    "addr:housenumber":"310",
    "addr:postcode":"30802",
    "addr:street":"Walton Mill Rd",
    "iso:country":"US",
    "sg:address":"310 Walton Mill Rd",
    "sg:city":"Appling",
    "sg:classifiers":[
        {
            "category":"Health Services",
            "subcategory":"Clinic",
            "type":"Services"
        }
    ],
    "sg:phone":"+1 706 760 0006",
    "sg:postcode":"30802",
    "sg:province":"GA",
    "sg:tags":[
        "welfare"
    ],
    "wof:name":"Global Medical Executives",
    "wof:placetype":"venue"
},
  "geometry": {"coordinates":[-82.23523299999999,33.570394],"type":"Point"}
}