{
  "type": "Feature",
  "properties": {
    "addr:full":"3146 Ray Owens Rd Appling GA 30802",
    "addr:housenumber":"3146",
    "addr:postcode":"30802",
    "addr:street":"Ray Owens Rd",
    "iso:country":"US",
    "sg:address":"3146 Ray Owens Rd",
    "sg:city":"Appling",
    "sg:classifiers":[
        {
            "category":"Food & Beverages",
            "subcategory":"Groceries & Convenience Stores",
            "type":"Retail Goods"
        }
    ],
    "sg:phone":"+1 706 541 2488",
    "sg:postcode":"30802",
    "sg:province":"GA",
    "wof:name":"Corner Store",
    "wof:placetype":"venue"
},
  "geometry": {"coordinates":[-82.33139,33.616352],"type":"Point"}
}