{
  "type": "Feature",
  "properties": {
    "addr:full":"26 Linden Ave NE Atlanta GA 30308",
    "addr:housenumber":"26",
    "addr:postcode":"30308",
    "addr:street":"Linden Ave Ne",
    "iso:country":"US",
    "sg:address":"26 Linden Ave NE",
    "sg:city":"Atlanta",
    "sg:classifiers":[
        {
            "category":"Manufacturing",
            "subcategory":"Tools & Machinery",
            "type":"Manufacturing & Wholesale Goods"
        }
    ],
    "sg:phone":"+1 404 815 5040",
    "sg:postcode":"30308",
    "sg:province":"GA",
    "sg:tags":[
        "automobile",
        "industry",
        "mfg",
        "parking"
    ],
    "wof:name":"Interpark Parking Facility",
    "wof:placetype":"venue"
},
  "geometry": {"coordinates":[-84.38514000000001,33.769814],"type":"Point"}
}