{
  "type": "Feature",
  "properties": {
    "addr:full":"3629 Lawrenceville Hwy Lawrenceville GA 30044",
    "addr:housenumber":"3629",
    "addr:postcode":"30044",
    "addr:street":"Lawrenceville Hwy",
    "iso:country":"US",
    "sg:address":"3629 Lawrenceville Hwy",
    "sg:city":"Lawrenceville",
    "sg:classifiers":[
        {
            "category":"Personal",
            "subcategory":"Beauty Salon",
            "type":"Services"
        }
    ],
    "sg:phone":"+1 770 279 2990",
    "sg:postcode":"30044",
    "sg:province":"GA",
    "sg:tags":[
        "shop",
        "manicuring"
    ],
    "wof:name":"Concept Nails",
    "wof:placetype":"venue"
},
  "geometry": {"coordinates":[-84.098826,33.913697],"type":"Point"}
}