{
  "type": "Feature",
  "properties": {
    "addr:full":"17 Lenox Pointe NE Atlanta GA 30324",
    "addr:housenumber":"17",
    "addr:postcode":"30324",
    "addr:street":"Lenox Pointe Ne",
    "iso:country":"US",
    "sg:address":"17 Lenox Pointe NE",
    "sg:city":"Atlanta",
    "sg:classifiers":[
        {
            "category":"Social Services",
            "type":"Services"
        }
    ],
    "sg:phone":"+1 404 231 0404",
    "sg:postcode":"30324",
    "sg:province":"GA",
    "sg:tags":[
        "counselor",
        "marriage",
        "family"
    ],
    "wof:name":"Almond Counseling Svc",
    "wof:placetype":"venue"
},
  "geometry": {"coordinates":[-84.353731,33.8261],"type":"Point"}
}