{
  "type": "Feature",
  "properties": {
    "iso:country":"US",
    "sg:address":"1054 Mount Zion Rd",
    "sg:city":"Homer",
    "sg:classifiers":[
        {
            "category":"Wholesale",
            "subcategory":"Construction Materials",
            "type":"Manufacturing & Wholesale Goods"
        }
    ],
    "sg:phone":"+1 706 677 2274",
    "sg:postcode":"30536",
    "sg:province":"GA",
    "sg:tags":[
        "timberland",
        "company",
        "timber"
    ],
    "wof:name":"Temple-Inland Forest Products",
    "wof:placetype":"venue"
},
  "geometry": {"coordinates":[-84.423575,34.664659],"type":"Point"}
}