{
  "type": "Feature",
  "properties": {
    "addr:full":"113 College Dr Barnesville GA 30204",
    "addr:housenumber":"113",
    "addr:postcode":"30204",
    "addr:street":"College Dr",
    "iso:country":"US",
    "sg:address":"113 College Dr",
    "sg:city":"Barnesville",
    "sg:classifiers":[
        {
            "category":"Building & Trades",
            "subcategory":"Cleaning & Sanitation",
            "type":"Services"
        }
    ],
    "sg:phone":"+1 770 358 3144",
    "sg:postcode":"30204",
    "sg:province":"GA",
    "sg:tags":[
        "maintenance"
    ],
    "wof:name":"Phoclyn Brite",
    "wof:placetype":"venue"
},
  "geometry": {"coordinates":[-84.143417,33.062117],"type":"Point"}
}