{
  "type": "Feature",
  "properties": {
    "addr:full":"160 Oak Manor Fayetteville GA 30214",
    "addr:housenumber":"160",
    "addr:postcode":"30214",
    "addr:street":"Oak Manor",
    "iso:country":"US",
    "sg:address":"160 Oak Manor",
    "sg:city":"Fayetteville",
    "sg:classifiers":[
        {
            "category":"Building & Trades",
            "subcategory":"Construction",
            "type":"Services"
        }
    ],
    "sg:phone":"+1 770 318 5666",
    "sg:postcode":"30214",
    "sg:province":"GA",
    "sg:tags":[
        "home",
        "builder"
    ],
    "wof:name":"Mikoy Custom Homes",
    "wof:placetype":"venue"
},
  "geometry": {"coordinates":[-84.41141,33.470015],"type":"Point"}
}