{
  "type": "Feature",
  "properties": {
    "addr:full":"572 Daniels Rd Jakin GA 31778",
    "addr:housenumber":"572",
    "addr:postcode":"31778",
    "addr:street":"Daniels Rd",
    "iso:country":"US",
    "sg:address":"572 Daniels Rd",
    "sg:city":"Jakin",
    "sg:phone":"+1 229 793 2156",
    "sg:postcode":"31778",
    "sg:province":"GA",
    "sg:tags":[
        "farm",
        "field",
        "crop",
        "general"
    ],
    "wof:name":"Arthur Daniels",
    "wof:placetype":"venue"
},
  "geometry": {"coordinates":[-83.79584,31.003046],"type":"Point"}
}