{
  "type": "Feature",
  "properties": {
    "iso:country":"US",
    "sg:address":"5475 Longmeadow Ln SW",
    "sg:city":"Atlanta",
    "sg:classifiers":[
        {
            "category":"Building & Trades",
            "subcategory":"Construction",
            "type":"Services"
        }
    ],
    "sg:phone":"+1 404 768 8922",
    "sg:postcode":"30349",
    "sg:province":"GA",
    "sg:tags":[
        "miscellaneous",
        "doe",
        "also",
        "r",
        "home",
        "contractor",
        "special"
    ],
    "wof:name":"Bradleys Home Care & Repr Svc",
    "wof:placetype":"venue"
},
  "geometry": {"coordinates":[-84.478048,33.608866],"type":"Point"}
}