{
  "type": "Feature",
  "properties": {
    "iso:country":"US",
    "sg:address":"3891 Stone Mountain Hwy S",
    "sg:city":"Snellville",
    "sg:classifiers":[
        {
            "category":"Health Services",
            "subcategory":"Doctor",
            "type":"Services"
        }
    ],
    "sg:phone":"+1 770 972 4764",
    "sg:postcode":"30078",
    "sg:province":"GA",
    "sg:tags":[
        "practice",
        "family"
    ],
    "wof:name":"Freeman Glenn MD",
    "wof:placetype":"venue"
},
  "geometry": {"coordinates":[-84.01950100000001,33.8568],"type":"Point"}
}