{
  "type": "Feature",
  "properties": {
    "addr:full":"1690 Roberts Blvd Ste 116 Kennesaw GA 30144",
    "addr:housenumber":"1690",
    "addr:postcode":"30144",
    "addr:street":"Roberts Blvd Ste 116",
    "iso:country":"US",
    "sg:address":"1690 Roberts Blvd Ste 116",
    "sg:city":"Kennesaw",
    "sg:classifiers":[
        {
            "category":"Shopping",
            "subcategory":"Bicycles & Sporting Goods",
            "type":"Retail Goods"
        }
    ],
    "sg:phone":"+1 866 481 7665",
    "sg:postcode":"30144",
    "sg:province":"GA",
    "sg:tags":[
        "outdoor",
        "gear"
    ],
    "sg:website":"www.ozonebilliards.com",
    "wof:name":"Ozone Billiards",
    "wof:placetype":"venue"
},
  "geometry": {"coordinates":[-84.596064,34.003709],"type":"Point"}
}