{
  "type": "Feature",
  "properties": {
    "addr:full":"199 Upper Riverdale Rd Jonesboro GA 30236",
    "addr:housenumber":"199",
    "addr:postcode":"30236",
    "addr:street":"Upper Riverdale Rd",
    "iso:country":"US",
    "sg:address":"199 Upper Riverdale Rd",
    "sg:city":"Jonesboro",
    "sg:classifiers":[
        {
            "category":"Banks & Credit Unions",
            "subcategory":"Bank",
            "type":"Services"
        }
    ],
    "sg:phone":"+1 770 991 1613",
    "sg:postcode":"30236",
    "sg:province":"GA",
    "sg:tags":[
        "cashing",
        "check"
    ],
    "wof:name":"Check Cashing Svc",
    "wof:placetype":"venue"
},
  "geometry": {"coordinates":[-84.378799,33.581205],"type":"Point"}
}