{
  "type": "Feature",
  "properties": {
    "iso:country":"US",
    "sg:address":"1280 W Peachtree St NW",
    "sg:city":"Atlanta",
    "sg:classifiers":[
        {
            "category":"Professional",
            "subcategory":"Accounting & Tax Preparation",
            "type":"Services"
        }
    ],
    "sg:phone":"+1 404 874 6696",
    "sg:postcode":"30309",
    "sg:province":"GA",
    "sg:tags":[
        "consulting",
        "cost"
    ],
    "wof:name":"D G Maximum",
    "wof:placetype":"venue"
},
  "geometry": {"coordinates":[-84.387863,33.789114],"type":"Point"}
}