{
  "type": "Feature",
  "properties": {
    "iso:country":"US",
    "sg:address":"1002 Thornfield Ct",
    "sg:city":"Norcross",
    "sg:classifiers":[
        {
            "category":"Professional",
            "subcategory":"Art Services",
            "type":"Services"
        }
    ],
    "sg:phone":"+1 770 717 8078",
    "sg:postcode":"30093",
    "sg:province":"GA",
    "sg:tags":[
        "design",
        "graphic",
        "painting",
        "custom"
    ],
    "wof:name":"Mad Cartoonist",
    "wof:placetype":"venue"
},
  "geometry": {"coordinates":[-84.154703,33.911195],"type":"Point"}
}