{
  "type": "Feature",
  "properties": {
    "addr:full":"4245 Iris Brooke Ln Snellville GA 30039",
    "addr:housenumber":"4245",
    "addr:postcode":"30039",
    "addr:street":"Iris Brooke Ln",
    "iso:country":"US",
    "sg:address":"4245 Iris Brooke Ln",
    "sg:city":"Snellville",
    "sg:classifiers":[
        {
            "category":"Professional",
            "subcategory":"Computer Services",
            "type":"Services"
        }
    ],
    "sg:phone":"+1 770 609 2664",
    "sg:postcode":"30039",
    "sg:province":"GA",
    "sg:tags":[
        "web",
        "software",
        "designer",
        "page",
        "writing"
    ],
    "wof:name":"Working Mediacom",
    "wof:placetype":"venue"
},
  "geometry": {"coordinates":[-84.051605,33.786613],"type":"Point"}
}