{
  "type": "Feature",
  "properties": {
    "iso:country":"US",
    "sg:address":"1570 Dogwood Dr SE",
    "sg:city":"Conyers",
    "sg:classifiers":[
        {
            "category":"Restaurant",
            "type":"Food & Drink"
        }
    ],
    "sg:menulink":"http://www.allmenus.com/ga/conyers/110125-chilis/menu/",
    "sg:phone":"+1 770 602 1301",
    "sg:postcode":"30013",
    "sg:province":"GA",
    "sg:tags":[
        "burger",
        "american",
        "sandwich",
        "tex-mex",
        "soup"
    ],
    "wof:name":"Chili's",
    "wof:placetype":"venue"
},
  "geometry": {"coordinates":[-83.99506,33.64793],"type":"Point"}
}