{
  "type": "Feature",
  "properties": {
    "addr:full":"1322 Briarhill Ln NE Atlanta GA 30324",
    "addr:housenumber":"1322",
    "addr:postcode":"30324",
    "addr:street":"Briarhill Ln Ne",
    "iso:country":"US",
    "sg:address":"1322 Briarhill Ln NE",
    "sg:city":"Atlanta",
    "sg:classifiers":[
        {
            "category":"Travel",
            "subcategory":"Travel Agent",
            "type":"Entertainment"
        }
    ],
    "sg:phone":"+1 770 936 8056",
    "sg:postcode":"30324",
    "sg:province":"GA",
    "sg:tags":[
        "agency",
        "bureau"
    ],
    "wof:name":"Travelex Canada",
    "wof:placetype":"venue"
},
  "geometry": {"coordinates":[-84.33936199999999,33.825507],"type":"Point"}
}