{
  "type": "Feature",
  "properties": {
    "iso:country":"US",
    "sg:address":"2301 Dawson Rd",
    "sg:city":"Albany",
    "sg:classifiers":[
        {
            "category":"Insurance",
            "subcategory":"Hazard Insurance",
            "type":"Services"
        },
        {
            "category":"Insurance",
            "subcategory":"Insurance Agent",
            "type":"Services"
        },
        {
            "category":"Insurance",
            "subcategory":"Life Insurance",
            "type":"Services"
        },
        {
            "category":"Insurance",
            "subcategory":"Title Insurance",
            "type":"Services"
        }
    ],
    "sg:phone":"+1 229 888 2040",
    "sg:postcode":"31707",
    "sg:province":"GA",
    "sg:tags":[
        "auto",
        "commercial",
        "business",
        "homeowner"
    ],
    "sg:website":"http://progressive.com",
    "wof:name":"Doherty Duggan & Rouse",
    "wof:placetype":"venue"
},
  "geometry": {"coordinates":[-84.204323,31.60334],"type":"Point"}
}