{
  "type": "Feature",
  "properties": {
    "addr:full":"6689 Peachtree Industrial Suite A Atlanta GA 30360",
    "addr:housenumber":"6689",
    "addr:postcode":"30360",
    "addr:street":"Peachtree Industrial Suite A",
    "iso:country":"US",
    "sg:address":"6689 Peachtree Industrial Suite A",
    "sg:city":"Atlanta",
    "sg:classifiers":[
        {
            "category":"Home & Garden",
            "subcategory":"Hardware",
            "type":"Retail Goods"
        },
        {
            "category":"Building & Trades",
            "subcategory":"Locksmith",
            "type":"Services"
        }
    ],
    "sg:phone":"+1 770 447 5888",
    "sg:postcode":"30360",
    "sg:province":"GA",
    "sg:tags":[
        "store",
        "key"
    ],
    "wof:name":"Arrington Lock & Safe",
    "wof:placetype":"venue"
},
  "geometry": {"coordinates":[-84.27172400000001,33.92772],"type":"Point"}
}