{
  "type": "Feature",
  "properties": {
    "iso:country":"US",
    "sg:address":"813 W Shadburn Ave",
    "sg:city":"Buford",
    "sg:classifiers":[
        {
            "category":"Personal",
            "subcategory":"Beauty Salon",
            "type":"Services"
        }
    ],
    "sg:phone":"+1 678 546 3399",
    "sg:postcode":"30518",
    "sg:province":"GA",
    "wof:name":"L And L Appearence Solutions",
    "wof:placetype":"venue"
},
  "geometry": {"coordinates":[-84.01634,34.113382],"type":"Point"}
}