{
  "type": "Feature",
  "properties": {
    "iso:country":"US",
    "sg:address":"3490 Piedmont Rd NE Ste 230",
    "sg:city":"Atlanta",
    "sg:classifiers":[
        {
            "category":"Health Services",
            "subcategory":"Dentist",
            "type":"Services"
        }
    ],
    "sg:phone":"+1 404 233 4900",
    "sg:postcode":"30305",
    "sg:province":"GA",
    "wof:name":"Piedmont Dental Group",
    "wof:placetype":"venue"
},
  "geometry": {"coordinates":[-84.377197,33.849701],"type":"Point"}
}