{
  "type": "Feature",
  "properties": {
    "addr:full":"124 Crittenden Ave Chickamauga GA 30707",
    "addr:housenumber":"124",
    "addr:postcode":"30707",
    "addr:street":"Crittenden Ave",
    "iso:country":"US",
    "sg:address":"124 Crittenden Ave",
    "sg:city":"Chickamauga",
    "sg:classifiers":[
        {
            "category":"Shopping",
            "subcategory":"Music",
            "type":"Retail Goods"
        }
    ],
    "sg:phone":"+1 706 375 7287",
    "sg:postcode":"30707",
    "sg:province":"GA",
    "sg:tags":[
        "video",
        "disc",
        "tape",
        "cassette"
    ],
    "wof:name":"Video Entertainment",
    "wof:placetype":"venue"
},
  "geometry": {"coordinates":[-85.282663,34.882498],"type":"Point"}
}