{
  "type": "Feature",
  "properties": {
    "iso:country":"US",
    "sg:address":"1060 E Piedmont Rd",
    "sg:city":"Marietta",
    "sg:classifiers":[
        {
            "category":"Restaurant",
            "type":"Food & Drink"
        }
    ],
    "sg:menulink":"http://www.allmenus.com/ga/northeast-cobb/157849-el-toro/menu/",
    "sg:phone":"+1 770 973 3173",
    "sg:postcode":"30062",
    "sg:province":"GA",
    "sg:tags":[
        "mexican"
    ],
    "wof:name":"El Toro",
    "wof:placetype":"venue"
},
  "geometry": {"coordinates":[-84.47998699999999,33.978837],"type":"Point"}
}