{
  "type": "Feature",
  "properties": {
    "iso:country":"US",
    "sg:address":"160 Clairemont Ave",
    "sg:city":"Decatur",
    "sg:classifiers":[
        {
            "category":"Professional",
            "subcategory":"Lawyer & Legal Services",
            "type":"Services"
        }
    ],
    "sg:phone":"+1 404 378 4549",
    "sg:postcode":"30030",
    "sg:province":"GA",
    "wof:name":"Hudson William T Jr Atty",
    "wof:placetype":"venue"
},
  "geometry": {"coordinates":[-84.29650100000001,33.7771],"type":"Point"}
}