{
  "type": "Feature",
  "properties": {
    "addr:full":"3200 Town Point Pkwy NW Kennesaw GA 30144",
    "addr:housenumber":"3200",
    "addr:postcode":"30144",
    "addr:street":"Town Point Pkwy Nw",
    "iso:country":"US",
    "sg:address":"3200 Town Point Pkwy NW",
    "sg:city":"Kennesaw",
    "sg:classifiers":[
        {
            "category":"Social Services",
            "type":"Services"
        }
    ],
    "sg:phone":"+1 678 819 0490",
    "sg:postcode":"30144",
    "sg:province":"GA",
    "sg:tags":[
        "organization",
        "welfare"
    ],
    "wof:name":"American Red Cross",
    "wof:placetype":"venue"
},
  "geometry": {"coordinates":[-84.583513,34.029095],"type":"Point"}
}