{
  "type": "Feature",
  "properties": {
    "iso:country":"US",
    "sg:address":"912 Windmill Ln",
    "sg:city":"Evans",
    "sg:classifiers":[
        {
            "category":"Insurance",
            "subcategory":"Hazard Insurance",
            "type":"Services"
        }
    ],
    "sg:phone":"+1 706 868 3777",
    "sg:postcode":"30809",
    "sg:province":"GA",
    "wof:name":"Hartford Life",
    "wof:placetype":"venue"
},
  "geometry": {"coordinates":[-82.20324100000001,33.566831],"type":"Point"}
}