{
  "type": "Feature",
  "properties": {
    "addr:full":"1406 Sheba Ct Columbus GA 31904",
    "addr:housenumber":"1406",
    "addr:postcode":"31904",
    "addr:street":"Sheba Ct",
    "iso:country":"US",
    "sg:address":"1406 Sheba Ct",
    "sg:city":"Columbus",
    "sg:classifiers":[
        {
            "category":"Professional",
            "subcategory":"Business Services",
            "type":"Services"
        }
    ],
    "sg:phone":"+1 706 322 6261",
    "sg:postcode":"31904",
    "sg:province":"GA",
    "wof:name":"Homecheck Inspection Service",
    "wof:placetype":"venue"
},
  "geometry": {"coordinates":[-84.969269,32.5549],"type":"Point"}
}