{
  "type": "Feature",
  "properties": {
    "addr:full":"970 Pechtre Indstrl Blvd Suwanee GA 30024",
    "addr:housenumber":"970",
    "addr:postcode":"30024",
    "addr:street":"Pechtre Indstrl Blvd",
    "iso:country":"US",
    "sg:address":"970 Pechtre Indstrl Blvd",
    "sg:city":"Suwanee",
    "sg:classifiers":[
        {
            "category":"Banks & Credit Unions",
            "subcategory":"Financial Services",
            "type":"Services"
        }
    ],
    "sg:phone":"+1 678 714 4949",
    "sg:postcode":"30024",
    "sg:province":"GA",
    "sg:tags":[
        "broker",
        "mortgage"
    ],
    "wof:name":"Home America Mortgage",
    "wof:placetype":"venue"
},
  "geometry": {"coordinates":[-84.081001,34.057499],"type":"Point"}
}