{
  "type": "Feature",
  "properties": {
    "iso:country":"US",
    "sg:address":"1062 Thompson Bridge Rd",
    "sg:city":"Gainesville",
    "sg:classifiers":[
        {
            "category":"Shopping",
            "subcategory":"Gifts & Souvenirs",
            "type":"Retail Goods"
        }
    ],
    "sg:phone":"+1 404 264 4334",
    "sg:postcode":"30501",
    "sg:province":"GA",
    "sg:tags":[
        "party",
        "supply"
    ],
    "wof:name":"Big John's Christmas Trees",
    "wof:placetype":"venue"
},
  "geometry": {"coordinates":[-83.829691,34.315754],"type":"Point"}
}