{
  "type": "Feature",
  "properties": {
    "addr:full":"330 Research Ct Norcross GA 30092",
    "addr:housenumber":"330",
    "addr:postcode":"30092",
    "addr:street":"Research Ct",
    "iso:country":"US",
    "sg:address":"330 Research Ct",
    "sg:city":"Norcross",
    "sg:classifiers":[
        {
            "category":"Manufacturing",
            "subcategory":"Electronics",
            "type":"Manufacturing & Wholesale Goods"
        }
    ],
    "sg:phone":"+1 770 729 7100",
    "sg:postcode":"30092",
    "sg:province":"GA",
    "sg:tags":[
        "devices",
        "mfg"
    ],
    "wof:name":"Motorola",
    "wof:placetype":"venue"
},
  "geometry": {"coordinates":[-84.215462,33.964655],"type":"Point"}
}