{
  "type": "Feature",
  "properties": {
    "iso:country":"US",
    "sg:address":"1780 Presidential Cir",
    "sg:city":"Snellville",
    "sg:classifiers":[
        {
            "category":"Health Services",
            "subcategory":"Doctor",
            "type":"Services"
        },
        {
            "category":"Health Services",
            "subcategory":"Clinic",
            "type":"Services"
        }
    ],
    "sg:phone":"+1 678 280 0202",
    "sg:postcode":"30078",
    "sg:province":"GA",
    "sg:tags":[
        "physician",
        "immunology",
        "medical",
        "allergy",
        "surgeons",
        "treatment",
        "surgeon"
    ],
    "sg:website":"www.atlantaallergy.com",
    "wof:name":"Atlanta Allergy & Asthma Clinic PA",
    "wof:placetype":"venue"
},
  "geometry": {"coordinates":[-84.01753100000001,33.876011],"type":"Point"}
}