{
  "type": "Feature",
  "properties": {
    "iso:country":"US",
    "sg:address":"2150 Allen Way",
    "sg:city":"Ellenwood",
    "sg:classifiers":[
        {
            "category":"Professional",
            "subcategory":"Management & Consulting",
            "type":"Services"
        }
    ],
    "sg:phone":"+1 404 381 0573",
    "sg:postcode":"30294",
    "sg:province":"GA",
    "sg:tags":[
        "small",
        "business",
        "for"
    ],
    "wof:name":"Callaway Business Group Inc",
    "wof:placetype":"venue"
},
  "geometry": {"coordinates":[-84.301311,33.667767],"type":"Point"}
}