{
  "type": "Feature",
  "properties": {
    "iso:country":"US",
    "sg:address":"511 Veterans Memorial Pkwy SE",
    "sg:city":"Mableton",
    "sg:classifiers":[
        {
            "category":"Insurance",
            "subcategory":"Insurance Agent",
            "type":"Services"
        }
    ],
    "sg:phone":"+1 770 739 0123",
    "sg:postcode":"30126",
    "sg:province":"GA",
    "wof:name":"Action Auto Agency",
    "wof:placetype":"venue"
},
  "geometry": {"coordinates":[-84.53526599999999,33.810932],"type":"Point"}
}