{
  "type": "Feature",
  "properties": {
    "addr:full":"981 Milstead Ave NE Conyers GA 30012",
    "addr:housenumber":"981",
    "addr:postcode":"30012",
    "addr:street":"Milstead Ave Ne",
    "iso:country":"US",
    "sg:address":"981 Milstead Ave NE",
    "sg:city":"Conyers",
    "sg:classifiers":[
        {
            "category":"Government",
            "subcategory":"Office",
            "type":"Public Place"
        }
    ],
    "sg:phone":"+1 770 929 4030",
    "sg:postcode":"30012",
    "sg:province":"GA",
    "wof:name":"Rockdale County Human Resource",
    "wof:placetype":"venue"
},
  "geometry": {"coordinates":[-84.016147,33.67028],"type":"Point"}
}