{
  "type": "Feature",
  "properties": {
    "iso:country":"US",
    "sg:address":"1800 Century Pl NE",
    "sg:city":"Atlanta",
    "sg:classifiers":[
        {
            "category":"Government",
            "subcategory":"Office",
            "type":"Public Place"
        }
    ],
    "sg:phone":"+1 404 679 1625",
    "sg:postcode":"30345",
    "sg:province":"GA",
    "sg:tags":[
        "state",
        "program"
    ],
    "sg:website":"www.gatcda.org",
    "wof:name":"Ga Dept-Technical & Adult Ed",
    "wof:placetype":"venue"
},
  "geometry": {"coordinates":[-84.315494,33.848208],"type":"Point"}
}