{
  "type": "Feature",
  "properties": {
    "iso:country":"US",
    "sg:address":"7000 N Point Pkwy",
    "sg:city":"Alpharetta",
    "sg:classifiers":[
        {
            "category":"Retail",
            "subcategory":"Car Wash",
            "type":"Services"
        }
    ],
    "sg:phone":"+1 770 410 9685",
    "sg:postcode":"30022",
    "sg:province":"GA",
    "wof:name":"Auto Indulgence",
    "wof:placetype":"venue"
},
  "geometry": {"coordinates":[-84.29969800000001,34.043999],"type":"Point"}
}