{
  "type": "Feature",
  "properties": {
    "addr:full":"100 Glenridge Point Pkwy N E Atlanta GA 30342",
    "addr:housenumber":"100",
    "addr:postcode":"30342",
    "addr:street":"Glenridge Point Pkwy N E",
    "iso:country":"US",
    "sg:address":"100 Glenridge Point Pkwy N E",
    "sg:city":"Atlanta",
    "sg:classifiers":[
        {
            "category":"Professional",
            "subcategory":"Lawyer & Legal Services",
            "type":"Services"
        }
    ],
    "sg:phone":"+1 404 256 0002",
    "sg:postcode":"30342",
    "sg:province":"GA",
    "wof:name":"Fudge McGowan",
    "wof:placetype":"venue"
},
  "geometry": {"coordinates":[-84.359674,33.906805],"type":"Point"}
}