{
  "type": "Feature",
  "properties": {
    "addr:full":"4022 Cochran Rd Gainesville GA 30506",
    "addr:housenumber":"4022",
    "addr:postcode":"30506",
    "addr:street":"Cochran Rd",
    "iso:country":"US",
    "sg:address":"4022 Cochran Rd",
    "sg:city":"Gainesville",
    "sg:classifiers":[
        {
            "category":"Building & Trades",
            "subcategory":"Construction",
            "type":"Services"
        }
    ],
    "sg:phone":"+1 770 536 3492",
    "sg:postcode":"30506",
    "sg:province":"GA",
    "sg:tags":[
        "surveying"
    ],
    "wof:name":"Frances D Hulsey Cnstr Layout",
    "wof:placetype":"venue"
},
  "geometry": {"coordinates":[-83.847461,34.370006],"type":"Point"}
}