{
  "type": "Feature",
  "properties": {
    "iso:country":"US",
    "sg:address":"4180 Liberty Trce",
    "sg:city":"Marietta",
    "sg:classifiers":[
        {
            "category":"Manufacturing",
            "subcategory":"Rubber & Plastics",
            "type":"Manufacturing & Wholesale Goods"
        }
    ],
    "sg:phone":"+1 770 928 8840",
    "sg:postcode":"30066",
    "sg:province":"GA",
    "sg:tags":[
        "manufacture",
        "closure"
    ],
    "wof:name":"Owens-Illinois Closure Inc",
    "wof:placetype":"venue"
},
  "geometry": {"coordinates":[-84.463581,34.051032],"type":"Point"}
}