{
  "type": "Feature",
  "properties": {
    "iso:country":"US",
    "sg:address":"510 10th St",
    "sg:city":"Columbus",
    "sg:classifiers":[
        {
            "category":"Government",
            "subcategory":"Fire Station",
            "type":"Public Place"
        }
    ],
    "sg:phone":"+1 706 653 3511",
    "sg:postcode":"31901",
    "sg:province":"GA",
    "sg:tags":[
        "protection"
    ],
    "wof:name":"Deputy Chief Personnel",
    "wof:placetype":"venue"
},
  "geometry": {"coordinates":[-84.984909,32.464673],"type":"Point"}
}