{
  "type": "Feature",
  "properties": {
    "addr:full":"49 Mary Freeman Rd Newnan GA 30265",
    "addr:housenumber":"49",
    "addr:postcode":"30265",
    "addr:street":"Mary Freeman Rd",
    "iso:country":"US",
    "sg:address":"49 Mary Freeman Rd",
    "sg:city":"Newnan",
    "sg:classifiers":[
        {
            "category":"Utilities",
            "subcategory":"Refuse",
            "type":"Services"
        }
    ],
    "sg:phone":"+1 770 251 7361",
    "sg:postcode":"30265",
    "sg:province":"GA",
    "sg:tags":[
        "recycling",
        "metal"
    ],
    "wof:name":"SRI",
    "wof:placetype":"venue"
},
  "geometry": {"coordinates":[-84.712209,33.358546],"type":"Point"}
}