{
  "type": "Feature",
  "properties": {
    "addr:full":"3790 Redcoat Way Alpharetta GA 30022",
    "addr:housenumber":"3790",
    "addr:postcode":"30022",
    "addr:street":"Redcoat Way",
    "iso:country":"US",
    "sg:address":"3790 Redcoat Way",
    "sg:city":"Alpharetta",
    "sg:classifiers":[
        {
            "category":"Professional",
            "type":"Services"
        }
    ],
    "sg:phone":"+1 770 754 9137",
    "sg:postcode":"30022",
    "sg:province":"GA",
    "wof:name":"Epperson Prorerties Inc",
    "wof:placetype":"venue"
},
  "geometry": {"coordinates":[-84.24965,34.017351],"type":"Point"}
}