{
  "type": "Feature",
  "properties": {
    "iso:country":"US",
    "sg:address":"10820 Abbotts Bridge Rd",
    "sg:city":"Duluth",
    "sg:classifiers":[
        {
            "category":"Personal",
            "subcategory":"Beauty Salon",
            "type":"Services"
        }
    ],
    "sg:phone":"+1 770 623 6422",
    "sg:postcode":"30097",
    "sg:province":"GA",
    "sg:tags":[
        "manicuring"
    ],
    "wof:name":"Abbotts Bridge Nail & Tan",
    "wof:placetype":"venue"
},
  "geometry": {"coordinates":[-84.169411,34.03219],"type":"Point"}
}