{
  "type": "Feature",
  "properties": {
    "addr:full":"1629 Norwich St Brunswick GA 31520",
    "addr:housenumber":"1629",
    "addr:postcode":"31520",
    "addr:street":"Norwich St",
    "iso:country":"US",
    "sg:address":"1629 Norwich St",
    "sg:city":"Brunswick",
    "sg:classifiers":[
        {
            "category":"Banks & Credit Unions",
            "subcategory":"Bank",
            "type":"Services"
        }
    ],
    "sg:phone":"+1 912 466 9901",
    "sg:postcode":"31520",
    "sg:province":"GA",
    "sg:tags":[
        "loan",
        "real estate"
    ],
    "wof:name":"Absolute Lending & Mtg LLC",
    "wof:placetype":"venue"
},
  "geometry": {"coordinates":[-81.49236000000001,31.152385],"type":"Point"}
}