{
  "type": "Feature",
  "properties": {
    "addr:full":"4019 Carter Dr NW Lilburn GA 30047",
    "addr:housenumber":"4019",
    "addr:postcode":"30047",
    "addr:street":"Carter Dr Nw",
    "iso:country":"US",
    "sg:address":"4019 Carter Dr NW",
    "sg:city":"Lilburn",
    "sg:classifiers":[
        {
            "category":"Building & Trades",
            "subcategory":"Construction",
            "type":"Services"
        }
    ],
    "sg:phone":"+1 770 921 0745",
    "sg:postcode":"30047",
    "sg:province":"GA",
    "sg:tags":[
        "house"
    ],
    "wof:name":"Dave Pelton Renovations",
    "wof:placetype":"venue"
},
  "geometry": {"coordinates":[-84.117268,33.908211],"type":"Point"}
}