{
  "type": "Feature",
  "properties": {
    "iso:country":"US",
    "sg:address":"320 Hospital Rd",
    "sg:city":"Canton",
    "sg:classifiers":[
        {
            "category":"Professional",
            "type":"Services"
        }
    ],
    "sg:phone":"+1 770 345 1705",
    "sg:postcode":"30114",
    "sg:province":"GA",
    "sg:tags":[
        "establishment"
    ],
    "wof:name":"SBP",
    "wof:placetype":"venue"
},
  "geometry": {"coordinates":[-84.491873,34.248076],"type":"Point"}
}