{
  "type": "Feature",
  "properties": {
    "addr:full":"3024 Tift Ave N Tifton GA 31794",
    "addr:housenumber":"3024",
    "addr:postcode":"31794",
    "addr:street":"Tift Ave N",
    "iso:country":"US",
    "sg:address":"3024 Tift Ave N",
    "sg:city":"Tifton",
    "sg:classifiers":[
        {
            "category":"Organizations",
            "subcategory":"Religious Organization",
            "type":"Services"
        }
    ],
    "sg:phone":"+1 229 382 3441",
    "sg:postcode":"31794",
    "sg:province":"GA",
    "sg:tags":[
        "church"
    ],
    "wof:name":"Church Of The Nazarene",
    "wof:placetype":"venue"
},
  "geometry": {"coordinates":[-83.502728,31.484446],"type":"Point"}
}