{
  "type": "Feature",
  "properties": {
    "iso:country":"US",
    "sg:address":"811 Hardman Rd",
    "sg:city":"Clarkesville",
    "sg:classifiers":[
        {
            "category":"Building & Trades",
            "subcategory":"Cleaning & Sanitation",
            "type":"Services"
        }
    ],
    "sg:phone":"+1 706 754 6378",
    "sg:postcode":"30523",
    "sg:province":"GA",
    "sg:tags":[
        "janitorial"
    ],
    "wof:name":"Joseph E McCall",
    "wof:placetype":"venue"
},
  "geometry": {"coordinates":[-83.514292,34.65376],"type":"Point"}
}