{
  "type": "Feature",
  "properties": {
    "iso:country":"US",
    "sg:address":"608 Walton Green Way NW",
    "sg:city":"Kennesaw",
    "sg:classifiers":[
        {
            "category":"Professional",
            "type":"Services"
        }
    ],
    "sg:phone":"+1 770 420 1848",
    "sg:postcode":"30144",
    "sg:province":"GA",
    "wof:name":"TLC The Location Connection",
    "wof:placetype":"venue"
},
  "geometry": {"coordinates":[-84.59795,34.054961],"type":"Point"}
}