{
  "type": "Feature",
  "properties": {
    "iso:country":"US",
    "sg:address":"352 Whittington Rd",
    "sg:city":"Omega",
    "sg:classifiers":[
        {
            "category":"Building & Trades",
            "subcategory":"Landscaping Services",
            "type":"Services"
        }
    ],
    "sg:phone":"+1 229 528 4676",
    "sg:postcode":"31775",
    "sg:province":"GA",
    "sg:tags":[
        "landscape",
        "contractor"
    ],
    "wof:name":"South Georgia Landscape",
    "wof:placetype":"venue"
},
  "geometry": {"coordinates":[-83.656591,31.353126],"type":"Point"}
}