{
  "type": "Feature",
  "properties": {
    "iso:country":"US",
    "sg:address":"5047 Woodridge Way",
    "sg:city":"Tucker",
    "sg:classifiers":[
        {
            "category":"Professional",
            "subcategory":"Business Services",
            "type":"Services"
        }
    ],
    "sg:phone":"+1 770 939 2143",
    "sg:postcode":"30084",
    "sg:province":"GA",
    "sg:tags":[
        "piano"
    ],
    "wof:name":"Johnstone Piano",
    "wof:placetype":"venue"
},
  "geometry": {"coordinates":[-84.224794,33.887484],"type":"Point"}
}