{
  "type": "Feature",
  "properties": {
    "addr:full":"911 State Rte 120 Lawrenceville GA 30043",
    "addr:housenumber":"911",
    "addr:postcode":"30043",
    "addr:street":"State Rte 120",
    "iso:country":"US",
    "sg:address":"911 State Rte 120",
    "sg:city":"Lawrenceville",
    "sg:classifiers":[
        {
            "category":"Professional",
            "subcategory":"Business Services",
            "type":"Services"
        }
    ],
    "sg:phone":"+1 770 339 7414",
    "sg:postcode":"30043",
    "sg:province":"GA",
    "sg:tags":[
        "event"
    ],
    "wof:name":"Celebrations & Reunions Inc",
    "wof:placetype":"venue"
},
  "geometry": {"coordinates":[-84.02510599999999,33.968379],"type":"Point"}
}