{
  "type": "Feature",
  "properties": {
    "iso:country":"US",
    "sg:address":"430 Lovena Dr SE",
    "sg:city":"Marietta",
    "sg:classifiers":[
        {
            "category":"Building & Trades",
            "subcategory":"Construction",
            "type":"Services"
        }
    ],
    "sg:phone":"+1 770 514 6480",
    "sg:postcode":"30067",
    "sg:province":"GA",
    "wof:name":"Palm Harbor Homes",
    "wof:placetype":"venue"
},
  "geometry": {"coordinates":[-84.509997,33.939855],"type":"Point"}
}