{
  "type": "Feature",
  "properties": {
    "iso:country":"US",
    "sg:address":"2158 Bankhead Hwy",
    "sg:city":"Carrollton",
    "sg:classifiers":[
        {
            "category":"Retail",
            "subcategory":"Auto Repair",
            "type":"Services"
        }
    ],
    "sg:phone":"+1 770 836 1874",
    "sg:postcode":"30116",
    "sg:province":"GA",
    "sg:tags":[
        "muffler",
        "exhaust",
        "system",
        "general"
    ],
    "wof:name":"Jerry's Muffler & Brake",
    "wof:placetype":"venue"
},
  "geometry": {"coordinates":[-85.008735,33.610705],"type":"Point"}
}