{
  "type": "Feature",
  "properties": {
    "addr:full":"2524 Lumpkin Rd Augusta GA 30906",
    "addr:housenumber":"2524",
    "addr:postcode":"30906",
    "addr:street":"Lumpkin Rd",
    "iso:country":"US",
    "sg:address":"2524 Lumpkin Rd",
    "sg:city":"Augusta",
    "sg:classifiers":[
        {
            "category":"Retail",
            "subcategory":"Funeral Services",
            "type":"Services"
        }
    ],
    "sg:phone":"+1 706 793 0123",
    "sg:postcode":"30906",
    "sg:province":"GA",
    "sg:tags":[
        "director"
    ],
    "wof:name":"Elliott Sons Funeral Homes",
    "wof:placetype":"venue"
},
  "geometry": {"coordinates":[-82.04656799999999,33.42252],"type":"Point"}
}