{
  "type": "Feature",
  "properties": {
    "iso:country":"US",
    "sg:address":"910 S Indian Creek Dr",
    "sg:city":"Stone Mountain",
    "sg:classifiers":[
        {
            "category":"Shopping",
            "subcategory":"Computers & Home Electronics",
            "type":"Retail Goods"
        }
    ],
    "sg:phone":"+1 404 292 1119",
    "sg:postcode":"30083",
    "sg:province":"GA",
    "wof:name":"Sound Investment",
    "wof:placetype":"venue"
},
  "geometry": {"coordinates":[-84.225588,33.771291],"type":"Point"}
}