{
  "type": "Feature",
  "properties": {
    "iso:country":"US",
    "sg:address":"160 S Railroad St",
    "sg:city":"Pembroke",
    "sg:classifiers":[
        {
            "category":"Travel",
            "subcategory":"Hotels & Motels",
            "type":"Entertainment"
        }
    ],
    "sg:phone":"+1 912 653 4199",
    "sg:postcode":"31321",
    "sg:province":"GA",
    "wof:name":"Inns Of Pembroke",
    "wof:placetype":"venue"
},
  "geometry": {"coordinates":[-81.627334,32.135702],"type":"Point"}
}