{
  "type": "Feature",
  "properties": {
    "iso:country":"US",
    "sg:address":"367 Fisk Dr SW",
    "sg:city":"Atlanta",
    "sg:classifiers":[
        {
            "category":"Professional",
            "subcategory":"Business Services",
            "type":"Services"
        }
    ],
    "sg:phone":"+1 404 344 8488",
    "sg:postcode":"30336",
    "sg:province":"GA",
    "sg:tags":[
        "import",
        "importer",
        "representative"
    ],
    "wof:name":"S S Sarna Inc",
    "wof:placetype":"venue"
},
  "geometry": {"coordinates":[-84.58521399999999,33.724421],"type":"Point"}
}