{
  "type": "Feature",
  "properties": {
    "iso:country":"US",
    "sg:address":"4201 Gillionville Rd",
    "sg:city":"Albany",
    "sg:classifiers":[
        {
            "category":"Building & Trades",
            "subcategory":"Construction",
            "type":"Services"
        }
    ],
    "sg:phone":"+1 229 438 7331",
    "sg:postcode":"31721",
    "sg:province":"GA",
    "sg:tags":[
        "general",
        "contractor"
    ],
    "wof:name":"Cothran Construction",
    "wof:placetype":"venue"
},
  "geometry": {"coordinates":[-84.26369,31.585766],"type":"Point"}
}