{
  "type": "Feature",
  "properties": {
    "addr:full":"3816 Stone Rd SW Atlanta GA 30331",
    "addr:housenumber":"3816",
    "addr:postcode":"30331",
    "addr:street":"Stone Rd Sw",
    "iso:country":"US",
    "sg:address":"3816 Stone Rd SW",
    "sg:city":"Atlanta",
    "sg:classifiers":[
        {
            "category":"Retail",
            "subcategory":"Auto Rental",
            "type":"Services"
        },
        {
            "category":"Retail",
            "subcategory":"Storage",
            "type":"Services"
        }
    ],
    "sg:phone":"+1 404 494 3696",
    "sg:postcode":"30331",
    "sg:province":"GA",
    "sg:tags":[
        "renting",
        "moving-self",
        "leasing",
        "truck",
        "trailer"
    ],
    "sg:website":"http://www.uhaul.com/Locations/Rentals-near-Atlanta-GA-30331/023408",
    "wof:name":"U-Haul Neighborhood Dealer - Layover Studios",
    "wof:placetype":"venue"
},
  "geometry": {"coordinates":[-84.509726,33.683835],"type":"Point"}
}