{
  "type": "Feature",
  "properties": {
    "addr:full":"4411 Roswell Rd Atlanta GA 30342",
    "addr:housenumber":"4411",
    "addr:postcode":"30342",
    "addr:street":"Roswell Rd",
    "iso:country":"US",
    "sg:address":"4411 Roswell Rd",
    "sg:city":"Atlanta",
    "sg:classifiers":[
        {
            "category":"Shopping",
            "subcategory":"Pharmacy",
            "type":"Retail Goods"
        }
    ],
    "sg:phone":"+1 404 255 3022",
    "sg:postcode":"30342",
    "sg:province":"GA",
    "sg:website":"http://www.tuxedopharmacy.net",
    "wof:name":"Tuxedo Pharmacy",
    "wof:placetype":"venue"
},
  "geometry": {"coordinates":[-84.380673,33.875285],"type":"Point"}
}