{
  "type": "Feature",
  "properties": {
    "addr:full":"1800 Phoenix Blvd Ste 120 Atlanta GA 30349",
    "addr:housenumber":"1800",
    "addr:postcode":"30349",
    "addr:street":"Phoenix Blvd Ste 120",
    "iso:country":"US",
    "sg:address":"1800 Phoenix Blvd Ste 120",
    "sg:city":"Atlanta",
    "sg:classifiers":[
        {
            "category":"Freight",
            "type":"Transportation"
        },
        {
            "category":"Local Transit",
            "type":"Transportation"
        }
    ],
    "sg:phone":"+1 770 907 7596",
    "sg:postcode":"30349",
    "sg:province":"GA",
    "sg:tags":[
        "provider",
        "broker",
        "trucking"
    ],
    "wof:name":"Logisticare",
    "wof:placetype":"venue"
},
  "geometry": {"coordinates":[-84.44603499999999,33.614504],"type":"Point"}
}