{
  "type": "Feature",
  "properties": {
    "iso:country":"US",
    "sg:address":"26564 Morganton Hwy",
    "sg:city":"Suches",
    "sg:classifiers":[
        {
            "category":"Building & Trades",
            "subcategory":"Construction",
            "type":"Services"
        }
    ],
    "sg:phone":"+1 706 838 4722",
    "sg:postcode":"30572",
    "sg:province":"GA",
    "sg:tags":[
        "house"
    ],
    "wof:name":"Doug Galloway Construction",
    "wof:placetype":"venue"
},
  "geometry": {"coordinates":[-84.14412400000001,34.748145],"type":"Point"}
}