{
  "type": "Feature",
  "properties": {
    "iso:country":"US",
    "sg:address":"33 Morse St",
    "sg:city":"Menlo",
    "sg:classifiers":[
        {
            "category":"Professional",
            "type":"Services"
        }
    ],
    "sg:phone":"+1 706 378 4279",
    "sg:postcode":"30731",
    "sg:province":"AL",
    "wof:name":"Nick M Hedgis",
    "wof:placetype":"venue"
},
  "geometry": {"coordinates":[-85.477075,34.482288],"type":"Point"}
}