{
  "type": "Feature",
  "properties": {
    "iso:country":"US",
    "sg:address":"611 Old Berlin Rd",
    "sg:city":"Moultrie",
    "sg:classifiers":[
        {
            "category":"Building & Trades",
            "subcategory":"Construction",
            "type":"Services"
        }
    ],
    "sg:phone":"+1 229 985 9094",
    "sg:postcode":"31788",
    "sg:province":"GA",
    "sg:tags":[
        "concrete",
        "contractor"
    ],
    "wof:name":"Wamco",
    "wof:placetype":"venue"
},
  "geometry": {"coordinates":[-83.731047,31.100992],"type":"Point"}
}