{
  "type": "Feature",
  "properties": {
    "iso:country":"US",
    "sg:address":"1154 Euclid Ave NE",
    "sg:city":"Atlanta",
    "sg:classifiers":[
        {
            "category":"Communications",
            "subcategory":"Newspaper",
            "type":"Services"
        },
        {
            "category":"Shopping",
            "subcategory":"Music",
            "type":"Retail Goods"
        },
        {
            "category":"Shopping",
            "subcategory":"Comic Books",
            "type":"Retail Goods"
        }
    ],
    "sg:phone":"+1 404 215 9511",
    "sg:postcode":"30307",
    "sg:province":"GA",
    "sg:tags":[
        "magazine",
        "dvd's"
    ],
    "wof:name":"Aurora Coffee",
    "wof:placetype":"venue"
},
  "geometry": {"coordinates":[-84.34997300000001,33.764982],"type":"Point"}
}