{
  "type": "Feature",
  "properties": {
    "addr:full":"115 Perimeter Center Pkwy NE Atlanta GA 30346",
    "addr:housenumber":"115",
    "addr:postcode":"30346",
    "addr:street":"Perimeter Center Pkwy Ne",
    "iso:country":"US",
    "sg:address":"115 Perimeter Center Pkwy NE",
    "sg:city":"Atlanta",
    "sg:classifiers":[
        {
            "category":"Banks & Credit Unions",
            "subcategory":"Bank",
            "type":"Services"
        }
    ],
    "sg:phone":"+1 770 551 0026",
    "sg:postcode":"30346",
    "sg:province":"GA",
    "sg:tags":[
        "provide",
        "to",
        "dealership",
        "auto"
    ],
    "wof:name":"Dealer Resources Inc",
    "wof:placetype":"venue"
},
  "geometry": {"coordinates":[-84.344083,33.926832],"type":"Point"}
}