{
  "type": "Feature",
  "properties": {
    "addr:full":"3273 Owens Meadow Ln NW Kennesaw GA 30152",
    "addr:housenumber":"3273",
    "addr:postcode":"30152",
    "addr:street":"Owens Meadow Ln Nw",
    "iso:country":"US",
    "sg:address":"3273 Owens Meadow Ln NW",
    "sg:city":"Kennesaw",
    "sg:classifiers":[
        {
            "category":"Building & Trades",
            "subcategory":"Landscaping Services",
            "type":"Services"
        }
    ],
    "sg:phone":"+1 770 520 8791",
    "sg:postcode":"30152",
    "sg:province":"GA",
    "sg:tags":[
        "lawn"
    ],
    "wof:name":"Sunshade Gardens",
    "wof:placetype":"venue"
},
  "geometry": {"coordinates":[-84.64832699999999,34.026399],"type":"Point"}
}