{
  "type": "Feature",
  "properties": {
    "addr:full":"3571 Oakvale Falls Ct Decatur GA 30034",
    "addr:housenumber":"3571",
    "addr:postcode":"30034",
    "addr:street":"Oakvale Falls Ct",
    "iso:country":"US",
    "sg:address":"3571 Oakvale Falls Ct",
    "sg:city":"Decatur",
    "sg:classifiers":[
        {
            "category":"Building & Trades",
            "subcategory":"Construction",
            "type":"Services"
        }
    ],
    "sg:phone":"+1 404 244 8312",
    "sg:postcode":"30034",
    "sg:province":"GA",
    "sg:tags":[
        "house"
    ],
    "wof:name":"Decatur Decks & Ponds",
    "wof:placetype":"venue"
},
  "geometry": {"coordinates":[-84.274491,33.678181],"type":"Point"}
}