{
  "type": "Feature",
  "properties": {
    "iso:country":"US",
    "sg:address":"150 Coggins Loop NW",
    "sg:city":"Calhoun",
    "sg:classifiers":[
        {
            "category":"Building & Trades",
            "subcategory":"Pest Control",
            "type":"Services"
        }
    ],
    "sg:phone":"+1 770 773 7708",
    "sg:postcode":"30701",
    "sg:province":"GA",
    "wof:name":"Rogers Exterminating Co",
    "wof:placetype":"venue"
},
  "geometry": {"coordinates":[-84.980109,34.536997],"type":"Point"}
}