{
  "type": "Feature",
  "properties": {
    "iso:country":"US",
    "sg:address":"3543 King Dr",
    "sg:city":"Douglasville",
    "sg:classifiers":[
        {
            "category":"Building & Trades",
            "subcategory":"Cleaning & Sanitation",
            "type":"Services"
        }
    ],
    "sg:phone":"+1 770 947 8303",
    "sg:postcode":"30135",
    "sg:province":"GA",
    "sg:tags":[
        "maintenance"
    ],
    "wof:name":"Dry Pro Floor Care",
    "wof:placetype":"venue"
},
  "geometry": {"coordinates":[-84.641722,33.706972],"type":"Point"}
}