{
  "type": "Feature",
  "properties": {
    "addr:full":"4290 Newnan Rd Griffin GA 30223",
    "addr:housenumber":"4290",
    "addr:postcode":"30223",
    "addr:street":"Newnan Rd",
    "iso:country":"US",
    "sg:address":"4290 Newnan Rd",
    "sg:city":"Griffin",
    "sg:classifiers":[
        {
            "category":"Personal",
            "subcategory":"Beauty Salon",
            "type":"Services"
        },
        {
            "category":"Personal",
            "subcategory":"Skin Care",
            "type":"Services"
        }
    ],
    "sg:phone":"+1 770 412 8671",
    "sg:postcode":"30223",
    "sg:province":"GA",
    "wof:name":"Tan 16 West",
    "wof:placetype":"venue"
},
  "geometry": {"coordinates":[-84.38265800000001,33.24091],"type":"Point"}
}