{
  "type": "Feature",
  "properties": {
    "iso:country":"US",
    "sg:address":"6603 W Armuchee Rd",
    "sg:city":"Summerville",
    "sg:classifiers":[
        {
            "category":"Farming",
            "subcategory":"Poultry Farm",
            "type":"Manufacturing & Wholesale Goods"
        }
    ],
    "sg:phone":"+1 706 397 8131",
    "sg:postcode":"30747",
    "sg:province":"GA",
    "sg:tags":[
        "egg"
    ],
    "wof:name":"Bobby & April Davis",
    "wof:placetype":"venue"
},
  "geometry": {"coordinates":[-85.205341,34.592803],"type":"Point"}
}