{
  "type": "Feature",
  "properties": {
    "iso:country":"US",
    "sg:address":"993D Johnson Ferry Rd NE",
    "sg:city":"Atlanta",
    "sg:classifiers":[
        {
            "category":"Health Services",
            "subcategory":"Dentist",
            "type":"Services"
        }
    ],
    "sg:phone":"+1 404 252 3170",
    "sg:postcode":"30342",
    "sg:province":"GA",
    "wof:name":"Stewart, Walter EJr DDS",
    "wof:placetype":"venue"
},
  "geometry": {"coordinates":[-84.35543800000001,33.907829],"type":"Point"}
}