{
  "type": "Feature",
  "properties": {
    "iso:country":"US",
    "sg:address":"836 Scott Nixon Memorial Dr",
    "sg:city":"Augusta",
    "sg:classifiers":[
        {
            "category":"Retail",
            "subcategory":"Repair Shop",
            "type":"Services"
        }
    ],
    "sg:phone":"+1 706 364 8948",
    "sg:postcode":"30907",
    "sg:province":"GA",
    "sg:tags":[
        "welding"
    ],
    "wof:name":"Allen Welding",
    "wof:placetype":"venue"
},
  "geometry": {"coordinates":[-82.091796,33.494598],"type":"Point"}
}