{
  "type": "Feature",
  "properties": {
    "addr:full":"3955 Buford Hwy Duluth GA 30096",
    "addr:housenumber":"3955",
    "addr:postcode":"30096",
    "addr:street":"Buford Hwy",
    "iso:country":"US",
    "sg:address":"3955 Buford Hwy",
    "sg:city":"Duluth",
    "sg:classifiers":[
        {
            "category":"Manufacturing",
            "subcategory":"Glass & Minerals",
            "type":"Manufacturing & Wholesale Goods"
        }
    ],
    "sg:phone":"+1 770 476 3781",
    "sg:postcode":"30096",
    "sg:province":"GA",
    "sg:tags":[
        "cement"
    ],
    "wof:name":"Holcim Inc",
    "wof:placetype":"venue"
},
  "geometry": {"coordinates":[-84.16314300000001,33.97681],"type":"Point"}
}