{
  "type": "Feature",
  "properties": {
    "addr:full":"200 S Woolfork Ave Donalsonville GA 39845",
    "addr:housenumber":"200",
    "addr:postcode":"39845",
    "addr:street":"S Woolfork Ave",
    "iso:country":"US",
    "sg:address":"200 S Woolfork Ave",
    "sg:city":"Donalsonville",
    "sg:classifiers":[
        {
            "category":"Building & Trades",
            "subcategory":"Construction",
            "type":"Services"
        }
    ],
    "sg:phone":"+1 866 686 7591",
    "sg:postcode":"39845",
    "sg:province":"GA",
    "sg:tags":[
        "plastering",
        "drywall",
        "painting",
        "contractor"
    ],
    "wof:name":"Rios Painting",
    "wof:placetype":"venue"
},
  "geometry": {"coordinates":[-84.880821,31.041849],"type":"Point"}
}