{
  "type": "Feature",
  "properties": {
    "iso:country":"US",
    "sg:address":"4495 Keheley Dr",
    "sg:city":"Marietta",
    "sg:classifiers":[
        {
            "category":"Building & Trades",
            "subcategory":"Electrical",
            "type":"Services"
        }
    ],
    "sg:phone":"+1 770 924 4857",
    "sg:postcode":"30066",
    "sg:province":"GA",
    "sg:tags":[
        "electrical",
        "contractor"
    ],
    "wof:name":"Jordan Electrical Design Inc",
    "wof:placetype":"venue"
},
  "geometry": {"coordinates":[-84.497855,34.057658],"type":"Point"}
}