{
  "type": "Feature",
  "properties": {
    "addr:full":"10 Chert Rd Marietta GA 30062",
    "addr:housenumber":"10",
    "addr:postcode":"30062",
    "addr:street":"Chert Rd",
    "iso:country":"US",
    "sg:address":"10 Chert Rd",
    "sg:city":"Marietta",
    "sg:classifiers":[
        {
            "category":"Restaurant",
            "type":"Food & Drink"
        }
    ],
    "sg:menulink":"http://www.allmenus.com/ga/marietta/232807-chicago-delights/menu/",
    "sg:phone":"+1 770 420 1151",
    "sg:postcode":"30062",
    "sg:province":"GA",
    "sg:tags":[
        "american"
    ],
    "wof:name":"Chicago Delights",
    "wof:placetype":"venue"
},
  "geometry": {"coordinates":[-84.51711299999999,33.951446],"type":"Point"}
}