{
  "type": "Feature",
  "properties": {
    "iso:country":"US",
    "sg:address":"1115 Crosstown Ct",
    "sg:city":"Peachtree City",
    "sg:classifiers":[
        {
            "category":"Food & Beverages",
            "subcategory":"Liquor & Beverages",
            "type":"Retail Goods"
        }
    ],
    "sg:phone":"+1 770 487 8068",
    "sg:postcode":"30269",
    "sg:province":"GA",
    "wof:name":"Arnie's Fine Wine & Liquor",
    "wof:placetype":"venue"
},
  "geometry": {"coordinates":[-84.56147300000001,33.375934],"type":"Point"}
}