{
  "type": "Feature",
  "properties": {
    "addr:full":"420 W Broughton St Savannah GA 31401",
    "addr:housenumber":"420",
    "addr:postcode":"31401",
    "addr:street":"W Broughton St",
    "iso:country":"US",
    "sg:address":"420 W Broughton St",
    "sg:city":"Savannah",
    "sg:classifiers":[
        {
            "category":"Professional",
            "subcategory":"Lawyer & Legal Services",
            "type":"Services"
        }
    ],
    "sg:phone":"+1 912 231 1116",
    "sg:postcode":"31401",
    "sg:province":"GA",
    "sg:tags":[
        "attorney"
    ],
    "wof:name":"Thomas M Hunter",
    "wof:placetype":"venue"
},
  "geometry": {"coordinates":[-81.097059,32.080379],"type":"Point"}
}