{
  "type": "Feature",
  "properties": {
    "iso:country":"US",
    "sg:address":"2124 Lindley Ln",
    "sg:city":"Kennesaw",
    "sg:classifiers":[
        {
            "category":"Shopping",
            "subcategory":"Clothing, Apparel, & Fashions",
            "type":"Retail Goods"
        }
    ],
    "sg:phone":"+1 770 794 4559",
    "sg:postcode":"30144",
    "sg:province":"GA",
    "sg:tags":[
        "family"
    ],
    "wof:name":"Reynas Fashion",
    "wof:placetype":"venue"
},
  "geometry": {"coordinates":[-84.62165899999999,34.038702],"type":"Point"}
}