{
  "type": "Feature",
  "properties": {
    "addr:full":"1062 Saint Andrews Rd Macon GA 31210",
    "addr:housenumber":"1062",
    "addr:postcode":"31210",
    "addr:street":"Saint Andrews Rd",
    "iso:country":"US",
    "sg:address":"1062 Saint Andrews Rd",
    "sg:city":"Macon",
    "sg:classifiers":[
        {
            "category":"Wholesale",
            "subcategory":"Non-durable Goods",
            "type":"Manufacturing & Wholesale Goods"
        }
    ],
    "sg:phone":"+1 478 477 7069",
    "sg:postcode":"31210",
    "sg:province":"GA",
    "sg:tags":[
        "merchandise-wholesale"
    ],
    "wof:name":"Fine China Gifts Imports",
    "wof:placetype":"venue"
},
  "geometry": {"coordinates":[-83.738024,32.864761],"type":"Point"}
}