{
  "type": "Feature",
  "properties": {
    "iso:country":"US",
    "sg:address":"5200 Dallas Hwy Ste 250",
    "sg:city":"Powder Springs",
    "sg:classifiers":[
        {
            "category":"Personal",
            "subcategory":"Barber",
            "type":"Services"
        }
    ],
    "sg:phone":"+1 770 422 9829",
    "sg:postcode":"30127",
    "sg:province":"GA",
    "sg:website":"www.haircuttery.com",
    "wof:name":"Hair Cuttery",
    "wof:placetype":"venue"
},
  "geometry": {"coordinates":[-84.703796,33.9403],"type":"Point"}
}