{
  "type": "Feature",
  "properties": {
    "iso:country":"US",
    "sg:address":"4004 Longview Dr",
    "sg:city":"Atlanta",
    "sg:classifiers":[
        {
            "category":"Arena",
            "subcategory":"Sports Club",
            "type":"Entertainment"
        }
    ],
    "sg:phone":"+1 770 986 3692",
    "sg:postcode":"30341",
    "sg:province":"GA",
    "wof:name":"Tahuichi Way Usn",
    "wof:placetype":"venue"
},
  "geometry": {"coordinates":[-84.305452,33.910783],"type":"Point"}
}