{
  "type": "Feature",
  "properties": {
    "iso:country":"US",
    "sg:address":"110 Selig Dr SW",
    "sg:city":"Atlanta",
    "sg:classifiers":[
        {
            "category":"Manufacturing",
            "subcategory":"Tools & Machinery",
            "type":"Manufacturing & Wholesale Goods"
        },
        {
            "category":"Industrial Area",
            "type":"Public Place"
        }
    ],
    "sg:phone":"+1 404 969 9366",
    "sg:postcode":"30336",
    "sg:province":"GA",
    "sg:tags":[
        "repair",
        "equipment-repairing",
        "machinery-rebuild"
    ],
    "wof:name":"Industrial Machinery Creations",
    "wof:placetype":"venue"
},
  "geometry": {"coordinates":[-84.540903,33.756923],"type":"Point"}
}