{
  "type": "Feature",
  "properties": {
    "addr:full":"3990 Wax Rd SE Aragon GA 30104",
    "addr:postcode":"3990;30104",
    "addr:street":"Wax Rd Se Aragon",
    "iso:country":"US",
    "sg:address":"3990 Wax Rd SE",
    "sg:city":"Aragon",
    "sg:classifiers":[
        {
            "category":"Professional",
            "subcategory":"Management & Consulting",
            "type":"Services"
        }
    ],
    "sg:phone":"+1 706 295 9677",
    "sg:postcode":"30104",
    "sg:province":"GA",
    "sg:tags":[
        "support",
        "facility"
    ],
    "wof:name":"Real Probing Services Inc",
    "wof:placetype":"venue"
},
  "geometry": {"coordinates":[-85.07847700000001,34.100967],"type":"Point"}
}