{
  "type": "Feature",
  "properties": {
    "iso:country":"US",
    "sg:address":"230 State Rte 20 Spr",
    "sg:city":"Cartersville",
    "sg:classifiers":[
        {
            "category":"Professional",
            "subcategory":"Management & Consulting",
            "type":"Services"
        }
    ],
    "sg:phone":"+1 770 382 0553",
    "sg:postcode":"30121",
    "sg:province":"GA",
    "sg:tags":[
        "business"
    ],
    "wof:name":"Sue L Cantrell",
    "wof:placetype":"venue"
},
  "geometry": {"coordinates":[-84.746713,34.204788],"type":"Point"}
}