{
  "type": "Feature",
  "properties": {
    "iso:country":"US",
    "sg:address":"6465 Winder Hwy",
    "sg:city":"Jefferson",
    "sg:classifiers":[
        {
            "category":"Wholesale",
            "subcategory":"Electrical",
            "type":"Manufacturing & Wholesale Goods"
        }
    ],
    "sg:phone":"+1 706 367 8934",
    "sg:postcode":"30549",
    "sg:province":"GA",
    "sg:tags":[
        "alarm",
        "burglar",
        "system"
    ],
    "wof:name":"Manifold Electronics",
    "wof:placetype":"venue"
},
  "geometry": {"coordinates":[-83.661631,34.064738],"type":"Point"}
}