{
  "type": "Feature",
  "properties": {
    "iso:country":"US",
    "sg:address":"445 Serrant Ct",
    "sg:city":"Alpharetta",
    "sg:classifiers":[
        {
            "category":"Building & Trades",
            "subcategory":"Landscaping Services",
            "type":"Services"
        }
    ],
    "sg:phone":"+1 770 269 8733",
    "sg:postcode":"30022",
    "sg:province":"GA",
    "sg:tags":[
        "tree"
    ],
    "wof:name":"T T Tree Services Inc",
    "wof:placetype":"venue"
},
  "geometry": {"coordinates":[-84.204432,34.056812],"type":"Point"}
}