{
  "type": "Feature",
  "properties": {
    "iso:country":"US",
    "sg:address":"8695 Torrington Dr",
    "sg:city":"Roswell",
    "sg:classifiers":[
        {
            "category":"Professional",
            "subcategory":"Management & Consulting",
            "type":"Services"
        }
    ],
    "sg:phone":"+1 770 552 8980",
    "sg:postcode":"30076",
    "sg:province":"GA",
    "sg:tags":[
        "training",
        "sales"
    ],
    "sg:website":"www.hownet.com",
    "wof:name":"Edmond-Howard Network",
    "wof:placetype":"venue"
},
  "geometry": {"coordinates":[-84.29825,33.995163],"type":"Point"}
}