{
  "type": "Feature",
  "properties": {
    "addr:full":"190 Sunrise Cir Riverdale GA 30274",
    "addr:housenumber":"190",
    "addr:postcode":"30274",
    "addr:street":"Sunrise Cir",
    "iso:country":"US",
    "sg:address":"190 Sunrise Cir",
    "sg:city":"Riverdale",
    "sg:classifiers":[
        {
            "category":"Building & Trades",
            "subcategory":"Construction",
            "type":"Services"
        }
    ],
    "sg:phone":"+1 770 991 9961",
    "sg:postcode":"30274",
    "sg:province":"GA",
    "sg:tags":[
        "contractor"
    ],
    "wof:name":"All Weather Roofing & Gutters",
    "wof:placetype":"venue"
},
  "geometry": {"coordinates":[-84.386616,33.57058],"type":"Point"}
}