{
  "type": "Feature",
  "properties": {
    "addr:full":"1570 Holcomb Bridge Rd Ste 309 Roswell GA 30076",
    "addr:housenumber":"1570",
    "addr:postcode":"30076",
    "addr:street":"Holcomb Bridge Rd Ste 309",
    "iso:country":"US",
    "sg:address":"1570 Holcomb Bridge Rd Ste 309",
    "sg:city":"Roswell",
    "sg:classifiers":[
        {
            "category":"Arts & Performance",
            "subcategory":"Jazz & Blues",
            "type":"Entertainment"
        }
    ],
    "sg:phone":"+1 678 795 9100",
    "sg:postcode":"30076",
    "sg:province":"GA",
    "sg:website":"www.londzellsjazzandblues.com",
    "wof:name":"Londzells Jazz & Blues Cafe",
    "wof:placetype":"venue"
},
  "geometry": {"coordinates":[-84.312653,34.019385],"type":"Point"}
}