{
  "type": "Feature",
  "properties": {
    "iso:country":"US",
    "sg:address":"105 E Kelly St",
    "sg:city":"Sylvester",
    "sg:classifiers":[
        {
            "category":"Insurance",
            "subcategory":"Insurance Agent",
            "type":"Services"
        }
    ],
    "sg:phone":"+1 229 776 3324",
    "sg:postcode":"31791",
    "sg:province":"GA",
    "wof:name":"Williams Insurance",
    "wof:placetype":"venue"
},
  "geometry": {"coordinates":[-83.837563,31.52771],"type":"Point"}
}