{
  "type": "Feature",
  "properties": {
    "addr:full":"1985 Forest Pkwy Morrow GA 30260",
    "addr:housenumber":"1985",
    "addr:postcode":"30260",
    "addr:street":"Forest Pkwy",
    "iso:country":"US",
    "sg:address":"1985 Forest Pkwy",
    "sg:city":"Morrow",
    "sg:classifiers":[
        {
            "category":"Retail",
            "subcategory":"Auto Repair",
            "type":"Services"
        }
    ],
    "sg:phone":"+1 404 366 3503",
    "sg:postcode":"30260",
    "sg:province":"GA",
    "sg:tags":[
        "trailer"
    ],
    "wof:name":"P & D Enterprises",
    "wof:placetype":"venue"
},
  "geometry": {"coordinates":[-84.324854,33.610417],"type":"Point"}
}