{
  "type": "Feature",
  "properties": {
    "iso:country":"US",
    "sg:address":"9925 Haynes Bridge Rd Ste 700",
    "sg:city":"Alpharetta",
    "sg:classifiers":[
        {
            "category":"Health Services",
            "subcategory":"Dentist",
            "type":"Services"
        }
    ],
    "sg:phone":"+1 770 663 0333",
    "sg:postcode":"30022",
    "sg:province":"GA",
    "wof:name":"Parsa Mehrdod A DMD",
    "wof:placetype":"venue"
},
  "geometry": {"coordinates":[-84.269897,34.021999],"type":"Point"}
}