{
  "type": "Feature",
  "properties": {
    "iso:country":"US",
    "sg:address":"5436 Mallard Walk",
    "sg:city":"Gainesville",
    "sg:classifiers":[
        {
            "category":"Professional",
            "type":"Services"
        }
    ],
    "sg:phone":"+1 678 450 0312",
    "sg:postcode":"30504",
    "sg:province":"GA",
    "wof:name":"Harbor Light",
    "wof:placetype":"venue"
},
  "geometry": {"coordinates":[-83.920085,34.240087],"type":"Point"}
}