{
  "type": "Feature",
  "properties": {
    "addr:full":"1945 Savoy Dr Apt 6301 Atlanta GA 30341",
    "addr:housenumber":"1945;6301",
    "addr:postcode":"30341",
    "addr:street":"Savoy Dr Apt",
    "iso:country":"US",
    "sg:address":"1945 Savoy Dr Apt 6301",
    "sg:city":"Atlanta",
    "sg:classifiers":[
        {
            "category":"Retail",
            "subcategory":"Portrait Studio",
            "type":"Services"
        },
        {
            "category":"Professional",
            "subcategory":"Art Services",
            "type":"Services"
        }
    ],
    "sg:phone":"+1 404 438 5141",
    "sg:postcode":"30341",
    "sg:province":"GA",
    "sg:tags":[
        "rental",
        "photographers-portrait",
        "photographic",
        "darkroom"
    ],
    "wof:name":"S & L Photography",
    "wof:placetype":"venue"
},
  "geometry": {"coordinates":[-84.308258,33.919868],"type":"Point"}
}