{
  "type": "Feature",
  "properties": {
    "addr:full":"6740 State Rte 85 Riverdale GA 30274",
    "addr:housenumber":"6740",
    "addr:postcode":"30274",
    "addr:street":"State Rte 85",
    "iso:country":"US",
    "sg:address":"6740 State Rte 85",
    "sg:city":"Riverdale",
    "sg:classifiers":[
        {
            "category":"Professional",
            "subcategory":"Management & Consulting",
            "type":"Services"
        }
    ],
    "sg:phone":"+1 770 994 2281",
    "sg:postcode":"30274",
    "sg:province":"GA",
    "sg:tags":[
        "fuel"
    ],
    "wof:name":"M & M Management",
    "wof:placetype":"venue"
},
  "geometry": {"coordinates":[-84.411579,33.580101],"type":"Point"}
}