{
  "type": "Feature",
  "properties": {
    "iso:country":"US",
    "sg:address":"157 Shannon Mall",
    "sg:city":"Union City",
    "sg:classifiers":[
        {
            "category":"Shopping",
            "subcategory":"Shoes",
            "type":"Retail Goods"
        }
    ],
    "sg:phone":"+1 770 306 2460",
    "sg:postcode":"30291",
    "sg:province":"GA",
    "sg:tags":[
        "store"
    ],
    "sg:website":"www.footlocker.com",
    "wof:name":"Foot Locker",
    "wof:placetype":"venue"
},
  "geometry": {"coordinates":[-84.513959,33.56969],"type":"Point"}
}