{
  "type": "Feature",
  "properties": {
    "addr:full":"111 Henry St Warner Robins GA 31088",
    "addr:housenumber":"111",
    "addr:postcode":"31088",
    "addr:street":"Henry St",
    "iso:country":"US",
    "sg:address":"111 Henry St",
    "sg:city":"Warner Robins",
    "sg:classifiers":[
        {
            "category":"Professional",
            "subcategory":"Employment Agencies",
            "type":"Services"
        }
    ],
    "sg:phone":"+1 478 918 0843",
    "sg:postcode":"31088",
    "sg:province":"GA",
    "wof:name":"Psychiatric Nursing Services",
    "wof:placetype":"venue"
},
  "geometry": {"coordinates":[-83.654976,32.600122],"type":"Point"}
}