{
  "type": "Feature",
  "properties": {
    "addr:full":"3 Skidaway Village Sq Savannah GA 31411",
    "addr:housenumber":"3",
    "addr:postcode":"31411",
    "addr:street":"Skidaway Village Sq",
    "iso:country":"US",
    "sg:address":"3 Skidaway Village Sq",
    "sg:city":"Savannah",
    "sg:classifiers":[
        {
            "category":"Building & Trades",
            "subcategory":"Construction",
            "type":"Services"
        }
    ],
    "sg:phone":"+1 912 598 5258",
    "sg:postcode":"31411",
    "sg:province":"GA",
    "sg:tags":[
        "steel",
        "fabrication",
        "welding"
    ],
    "wof:name":"Enduro Steel Products",
    "wof:placetype":"venue"
},
  "geometry": {"coordinates":[-81.052256,31.940742],"type":"Point"}
}