{
  "type": "Feature",
  "properties": {
    "addr:full":"19120 Birmingham Hwy Alpharetta GA 30004",
    "addr:housenumber":"19120",
    "addr:postcode":"30004",
    "addr:street":"Birmingham Hwy",
    "iso:country":"US",
    "sg:address":"19120 Birmingham Hwy",
    "sg:city":"Alpharetta",
    "sg:classifiers":[
        {
            "category":"Building & Trades",
            "subcategory":"Construction",
            "type":"Services"
        }
    ],
    "sg:phone":"+1 770 887 9617",
    "sg:postcode":"30004",
    "sg:province":"GA",
    "wof:name":"Braswell Grading Co",
    "wof:placetype":"venue"
},
  "geometry": {"coordinates":[-84.28727000000001,34.206576],"type":"Point"}
}