{
  "type": "Feature",
  "properties": {
    "addr:full":"500 Cedar Ln Monroe GA 30655",
    "addr:housenumber":"500",
    "addr:postcode":"30655",
    "addr:street":"Cedar Ln",
    "iso:country":"US",
    "sg:address":"500 Cedar Ln",
    "sg:city":"Monroe",
    "sg:classifiers":[
        {
            "category":"Education",
            "subcategory":"Library",
            "type":"Public Place"
        }
    ],
    "sg:phone":"+1 770 267 5420",
    "sg:postcode":"30655",
    "sg:province":"GA",
    "wof:name":"Cedrick Branch",
    "wof:placetype":"venue"
},
  "geometry": {"coordinates":[-83.683779,33.799628],"type":"Point"}
}