{
  "type": "Feature",
  "properties": {
    "addr:full":"4421 Paradise Cir SE Atlanta GA 30339",
    "addr:housenumber":"4421",
    "addr:postcode":"30339",
    "addr:street":"Paradise Cir Se",
    "iso:country":"US",
    "sg:address":"4421 Paradise Cir SE",
    "sg:city":"Atlanta",
    "sg:classifiers":[
        {
            "category":"Professional",
            "subcategory":"Printing & Photocopies",
            "type":"Services"
        }
    ],
    "sg:phone":"+1 404 603 8895",
    "sg:postcode":"30339",
    "sg:province":"GA",
    "sg:tags":[
        "photographers-commercial"
    ],
    "wof:name":"Atlantaphotos.Com",
    "wof:placetype":"venue"
},
  "geometry": {"coordinates":[-84.47393700000001,33.84746],"type":"Point"}
}