{
  "type": "Feature",
  "properties": {
    "addr:full":"1475 Terrell Mill Rd SE Marietta GA 30067",
    "addr:housenumber":"1475",
    "addr:postcode":"30067",
    "addr:street":"Terrell Mill Rd Se",
    "iso:country":"US",
    "sg:address":"1475 Terrell Mill Rd SE",
    "sg:city":"Marietta",
    "sg:classifiers":[
        {
            "category":"Health Services",
            "subcategory":"Chiropractor",
            "type":"Services"
        }
    ],
    "sg:phone":"+1 770 984 2813",
    "sg:postcode":"30067",
    "sg:province":"GA",
    "wof:name":"Russo Diane RN DC Bsn",
    "wof:placetype":"venue"
},
  "geometry": {"coordinates":[-84.46913000000001,33.916488],"type":"Point"}
}