{
  "type": "Feature",
  "properties": {
    "iso:country":"US",
    "sg:address":"4095 Pio Nono Ave",
    "sg:city":"Macon",
    "sg:classifiers":[
        {
            "category":"Food & Beverages",
            "subcategory":"Liquor & Beverages",
            "type":"Retail Goods"
        }
    ],
    "sg:phone":"+1 478 781 4885",
    "sg:postcode":"31206",
    "sg:province":"GA",
    "sg:tags":[
        "alcoholic"
    ],
    "wof:name":"Silly Willy's",
    "wof:placetype":"venue"
},
  "geometry": {"coordinates":[-83.668434,32.792805],"type":"Point"}
}