{
  "type": "Feature",
  "properties": {
    "addr:full":"5044 Clark Howell Hwy Atlanta GA 30349",
    "addr:housenumber":"5044",
    "addr:postcode":"30349",
    "addr:street":"Clark Howell Hwy",
    "iso:country":"US",
    "sg:address":"5044 Clark Howell Hwy",
    "sg:city":"Atlanta",
    "sg:classifiers":[
        {
            "category":"Health Services",
            "subcategory":"Doctor",
            "type":"Services"
        }
    ],
    "sg:phone":"+1 404 765 2400",
    "sg:postcode":"30349",
    "sg:province":"GA",
    "sg:tags":[
        "physician",
        "medical",
        "surgeon",
        "center"
    ],
    "sg:website":"www.concentra.com",
    "wof:name":"Concentra Medical Centers",
    "wof:placetype":"venue"
},
  "geometry": {"coordinates":[-84.404574,33.616252],"type":"Point"}
}