{
  "type": "Feature",
  "properties": {
    "addr:full":"209 Overlook Dr-2 Woodstock GA 30188",
    "addr:housenumber":"209",
    "addr:postcode":"30188",
    "addr:street":"Overlook Dr-2",
    "iso:country":"US",
    "sg:address":"209 Overlook Dr-2",
    "sg:city":"Woodstock",
    "sg:classifiers":[
        {
            "category":"Building & Trades",
            "subcategory":"Landscaping Services",
            "type":"Services"
        }
    ],
    "sg:phone":"+1 770 516 6078",
    "sg:postcode":"30188",
    "sg:province":"GA",
    "sg:tags":[
        "landscape"
    ],
    "wof:name":"Beldens Landscaping",
    "wof:placetype":"venue"
},
  "geometry": {"coordinates":[-84.450856,34.086584],"type":"Point"}
}