{
  "type": "Feature",
  "properties": {
    "iso:country":"US",
    "sg:address":"3145 Tucker Norcross Rd",
    "sg:city":"Tucker",
    "sg:classifiers":[
        {
            "category":"Professional",
            "subcategory":"Employment Agencies",
            "type":"Services"
        }
    ],
    "sg:phone":"+1 770 934 1710",
    "sg:postcode":"30084",
    "sg:province":"GA",
    "sg:tags":[
        "temporary",
        "help"
    ],
    "wof:name":"Coporate Temps 2000",
    "wof:placetype":"venue"
},
  "geometry": {"coordinates":[-84.219317,33.881544],"type":"Point"}
}