{
  "type": "Feature",
  "properties": {
    "addr:full":"571 S Ashby St Atlanta GA 30310",
    "addr:housenumber":"571",
    "addr:postcode":"30310",
    "addr:street":"S Ashby St",
    "iso:country":"US",
    "sg:address":"571 S Ashby St",
    "sg:city":"Atlanta",
    "sg:classifiers":[
        {
            "category":"Shopping",
            "subcategory":"Department Store",
            "type":"Retail Goods"
        }
    ],
    "sg:phone":"+1 404 752 6610",
    "sg:postcode":"30310",
    "sg:province":"GA",
    "sg:tags":[
        "shop"
    ],
    "wof:name":"BNS Variety Discount Store",
    "wof:placetype":"venue"
},
  "geometry": {"coordinates":[-84.417771,33.739017],"type":"Point"}
}