{
  "type": "Feature",
  "properties": {
    "addr:full":"5071 Lincolnton Rd Washington GA 30673",
    "addr:housenumber":"5071",
    "addr:postcode":"30673",
    "addr:street":"Lincolnton Rd",
    "iso:country":"US",
    "sg:address":"5071 Lincolnton Rd",
    "sg:city":"Washington",
    "sg:classifiers":[
        {
            "category":"Building & Trades",
            "subcategory":"Plumbing",
            "type":"Services"
        }
    ],
    "sg:phone":"+1 706 678 4398",
    "sg:postcode":"30673",
    "sg:province":"GA",
    "sg:tags":[
        "conditioning",
        "air",
        "system",
        "contractor"
    ],
    "wof:name":"Smith Ronnie Heating & AC",
    "wof:placetype":"venue"
},
  "geometry": {"coordinates":[-82.591415,33.723214],"type":"Point"}
}