{
  "type": "Feature",
  "properties": {
    "addr:full":"110 Eisenhower Dr Savannah GA 31406",
    "addr:housenumber":"110",
    "addr:postcode":"31406",
    "addr:street":"Eisenhower Dr",
    "iso:country":"US",
    "sg:address":"110 Eisenhower Dr",
    "sg:city":"Savannah",
    "sg:classifiers":[
        {
            "category":"Restaurant",
            "type":"Food & Drink"
        }
    ],
    "sg:menulink":"http://www.allmenus.com/ga/savannah/31589-madras--saravana-bhavan/menu/",
    "sg:phone":"+1 912 356 0344",
    "sg:postcode":"31406",
    "sg:province":"GA",
    "sg:tags":[
        "indian",
        "asian"
    ],
    "wof:name":"Madras & Saravana Bhavan",
    "wof:placetype":"venue"
},
  "geometry": {"coordinates":[-81.113941,32.010058],"type":"Point"}
}