{
  "type": "Feature",
  "properties": {
    "addr:full":"5750 Plantation Ct Acworth GA 30102",
    "addr:housenumber":"5750",
    "addr:postcode":"30102",
    "addr:street":"Plantation Ct",
    "iso:country":"US",
    "sg:address":"5750 Plantation Ct",
    "sg:city":"Acworth",
    "sg:classifiers":[
        {
            "category":"Professional",
            "subcategory":"Business Services",
            "type":"Services"
        }
    ],
    "sg:phone":"+1 770 917 1826",
    "sg:postcode":"30102",
    "sg:province":"GA",
    "wof:name":"Fantco Enterprises",
    "wof:placetype":"venue"
},
  "geometry": {"coordinates":[-84.64787699999999,34.090021],"type":"Point"}
}