{
  "type": "Feature",
  "properties": {
    "addr:full":"1526 E Forrest Ave Atlanta GA 30344",
    "addr:housenumber":"1526",
    "addr:postcode":"30344",
    "addr:street":"E Forrest Ave",
    "iso:country":"US",
    "sg:address":"1526 E Forrest Ave",
    "sg:city":"Atlanta",
    "sg:classifiers":[
        {
            "category":"Real Estate",
            "subcategory":"Real Estate Services",
            "type":"Services"
        },
        {
            "category":"Structure",
            "subcategory":"Office Building",
            "type":"Public Place"
        }
    ],
    "sg:phone":"+1 404 684 7038",
    "sg:postcode":"30344",
    "sg:province":"GA",
    "sg:tags":[
        "vacancy",
        "park",
        "rental",
        "commercial",
        "listing"
    ],
    "wof:name":"Jefferson Station",
    "wof:placetype":"venue"
},
  "geometry": {"coordinates":[-84.438552,33.682884],"type":"Point"}
}