{
  "type": "Feature",
  "properties": {
    "iso:country":"US",
    "sg:address":"427 E River St",
    "sg:city":"Savannah",
    "sg:classifiers":[
        {
            "category":"Restaurant",
            "type":"Food & Drink"
        }
    ],
    "sg:phone":"+1 912 232 9082",
    "sg:postcode":"31401",
    "sg:province":"GA",
    "sg:tags":[
        "eating"
    ],
    "wof:name":"Riverstreet Deli",
    "wof:placetype":"venue"
},
  "geometry": {"coordinates":[-81.084609,32.079876],"type":"Point"}
}