{
  "type": "Feature",
  "properties": {
    "iso:country":"US",
    "sg:address":"207 White Leaf Dr",
    "sg:city":"Dallas",
    "sg:classifiers":[
        {
            "category":"Utilities",
            "subcategory":"Telephone",
            "type":"Services"
        }
    ],
    "sg:phone":"+1 678 363 3468",
    "sg:postcode":"30157",
    "sg:province":"GA",
    "sg:tags":[
        "telecommunication"
    ],
    "wof:name":"A T & T",
    "wof:placetype":"venue"
},
  "geometry": {"coordinates":[-84.881545,33.823115],"type":"Point"}
}