{
  "type": "Feature",
  "properties": {
    "iso:country":"US",
    "sg:address":"102 Hicks Dr SE",
    "sg:city":"Rome",
    "sg:classifiers":[
        {
            "category":"Personal",
            "type":"Services"
        },
        {
            "category":"Retail",
            "subcategory":"Portrait Studio",
            "type":"Services"
        },
        {
            "category":"Professional",
            "subcategory":"Art Services",
            "type":"Services"
        }
    ],
    "sg:phone":"+1 706 295 1422",
    "sg:postcode":"30161",
    "sg:province":"GA",
    "sg:tags":[
        "photographers-portrait",
        "videography",
        "darkroom",
        "rental",
        "photography",
        "wedding",
        "photographic"
    ],
    "sg:website":"http://www.olanmills.com",
    "wof:name":"Olan Mills",
    "wof:placetype":"venue"
},
  "geometry": {"coordinates":[-85.163381,34.25229],"type":"Point"}
}