{
  "type": "Feature",
  "properties": {
    "iso:country":"US",
    "sg:address":"706 Vandeford Rd",
    "sg:city":"Royston",
    "sg:classifiers":[
        {
            "category":"Farming",
            "subcategory":"Livestock Farm",
            "type":"Manufacturing & Wholesale Goods"
        }
    ],
    "sg:phone":"+1 706 245 9584",
    "sg:postcode":"30662",
    "sg:province":"GA",
    "sg:tags":[
        "beef",
        "feedlot",
        "cattle"
    ],
    "wof:name":"Rays Cattle Co",
    "wof:placetype":"venue"
},
  "geometry": {"coordinates":[-83.05207299999999,34.268582],"type":"Point"}
}