{
  "type": "Feature",
  "properties": {
    "iso:country":"US",
    "sg:address":"1029 Bay St",
    "sg:city":"Brunswick",
    "sg:classifiers":[
        {
            "category":"Wholesale",
            "subcategory":"Construction Materials",
            "type":"Manufacturing & Wholesale Goods"
        }
    ],
    "sg:phone":"+1 912 554 8000",
    "sg:postcode":"31520",
    "sg:province":"GA",
    "sg:tags":[
        "concrete",
        "product"
    ],
    "wof:name":"Gisco Tabby Hardscapes",
    "wof:placetype":"venue"
},
  "geometry": {"coordinates":[-81.49711499999999,31.152544],"type":"Point"}
}