{
  "type": "Feature",
  "properties": {
    "addr:full":"4 S Lee St Baxley GA 31513",
    "addr:housenumber":"4",
    "addr:postcode":"31513",
    "addr:street":"S Lee St",
    "iso:country":"US",
    "sg:address":"4 S Lee St",
    "sg:city":"Baxley",
    "sg:classifiers":[
        {
            "category":"Professional",
            "subcategory":"Lawyer & Legal Services",
            "type":"Services"
        }
    ],
    "sg:phone":"+1 912 367 2500",
    "sg:postcode":"31513",
    "sg:province":"GA",
    "sg:tags":[
        "attorney",
        "practice"
    ],
    "wof:name":"Tillman, Steven E Attorney At Law",
    "wof:placetype":"venue"
},
  "geometry": {"coordinates":[-82.353275,31.776782],"type":"Point"}
}