{
  "type": "Feature",
  "properties": {
    "addr:full":"413 Mossy Acres Dr Cleveland GA 30528",
    "addr:housenumber":"413",
    "addr:postcode":"30528",
    "addr:street":"Mossy Acres Dr",
    "iso:country":"US",
    "sg:address":"413 Mossy Acres Dr",
    "sg:city":"Cleveland",
    "sg:classifiers":[
        {
            "category":"Structure",
            "subcategory":"Office Building",
            "type":"Public Place"
        }
    ],
    "sg:phone":"+1 706 968 1700",
    "sg:postcode":"30528",
    "sg:province":"GA",
    "sg:tags":[
        "park"
    ],
    "wof:name":"Northeast Georgia Properties",
    "wof:placetype":"venue"
},
  "geometry": {"coordinates":[-83.68772300000001,34.519401],"type":"Point"}
}