{
  "type": "Feature",
  "properties": {
    "iso:country":"US",
    "sg:address":"4158 Washington Rd",
    "sg:city":"Augusta",
    "sg:classifiers":[
        {
            "category":"Personal",
            "subcategory":"Nail Salon",
            "type":"Services"
        }
    ],
    "sg:phone":"+1 706 854 0707",
    "sg:postcode":"30907",
    "sg:province":"GA",
    "wof:name":"Exotic Nails",
    "wof:placetype":"venue"
},
  "geometry": {"coordinates":[-82.04396800000001,33.512199],"type":"Point"}
}