{
  "type": "Feature",
  "properties": {
    "addr:full":"137 Tumbleweed Trl Jasper GA 30143",
    "addr:housenumber":"137",
    "addr:postcode":"30143",
    "addr:street":"Tumbleweed Trl",
    "iso:country":"US",
    "sg:address":"137 Tumbleweed Trl",
    "sg:city":"Jasper",
    "sg:classifiers":[
        {
            "category":"Building & Trades",
            "subcategory":"Plumbing",
            "type":"Services"
        }
    ],
    "sg:phone":"+1 770 735 4060",
    "sg:postcode":"30143",
    "sg:province":"GA",
    "sg:tags":[
        "plumbing",
        "contractor"
    ],
    "wof:name":"Welchel Plumbing & Heating Inc",
    "wof:placetype":"venue"
},
  "geometry": {"coordinates":[-84.54168799999999,34.426315],"type":"Point"}
}