{
  "type": "Feature",
  "properties": {
    "addr:full":"731 Progress Rd Ellijay GA 30540",
    "addr:housenumber":"731",
    "addr:postcode":"30540",
    "addr:street":"Progress Rd",
    "iso:country":"US",
    "sg:address":"731 Progress Rd",
    "sg:city":"Ellijay",
    "sg:classifiers":[
        {
            "category":"Utilities",
            "subcategory":"Refuse",
            "type":"Services"
        }
    ],
    "sg:phone":"+1 706 276 6338",
    "sg:postcode":"30540",
    "sg:province":"GA",
    "sg:tags":[
        "disposal",
        "waste"
    ],
    "wof:name":"First Source Inc",
    "wof:placetype":"venue"
},
  "geometry": {"coordinates":[-84.494625,34.667366],"type":"Point"}
}