{
  "type": "Feature",
  "properties": {
    "iso:country":"US",
    "sg:address":"7773 Strickland St",
    "sg:city":"Douglasville",
    "sg:classifiers":[
        {
            "category":"Autos & Motor Vehicles",
            "subcategory":"Auto Supplies",
            "type":"Retail Goods"
        }
    ],
    "sg:phone":"+1 770 942 8444",
    "sg:postcode":"30134",
    "sg:province":"GA",
    "sg:tags":[
        "automobile",
        "parts",
        "part",
        "supplies-used",
        "accessories-wholesale",
        "rebuilt",
        "manufacturer"
    ],
    "wof:name":"Bud's Benz",
    "wof:placetype":"venue"
},
  "geometry": {"coordinates":[-84.77819100000001,33.74276],"type":"Point"}
}