{
  "type": "Feature",
  "properties": {
    "iso:country":"US",
    "sg:address":"15900 Westbrook Rd",
    "sg:city":"Alpharetta",
    "sg:classifiers":[
        {
            "category":"Home & Garden",
            "subcategory":"Home Furnishings",
            "type":"Retail Goods"
        }
    ],
    "sg:phone":"+1 770 772 6693",
    "sg:postcode":"30004",
    "sg:province":"GA",
    "sg:tags":[
        "pottery"
    ],
    "wof:name":"Clay Fetish LTD",
    "wof:placetype":"venue"
},
  "geometry": {"coordinates":[-84.282369,34.16457],"type":"Point"}
}