{
  "type": "Feature",
  "properties": {
    "iso:country":"US",
    "sg:address":"3395 Northeast Expressway #150",
    "sg:city":"Atlanta",
    "sg:classifiers":[
        {
            "category":"Social Services",
            "subcategory":"Adult Care",
            "type":"Services"
        }
    ],
    "sg:phone":"+1 678 894 7876",
    "sg:postcode":"30341",
    "sg:province":"GA",
    "sg:tags":[
        "nurses-home"
    ],
    "sg:website":"http://homehealthcareatlanta.com",
    "wof:name":"Choice In Home Senior Care of Atlanta",
    "wof:placetype":"venue"
},
  "geometry": {"coordinates":[-84.274193,33.876442],"type":"Point"}
}