{
  "type": "Feature",
  "properties": {
    "iso:country":"US",
    "sg:address":"198 Tracy Ter",
    "sg:city":"Warner Robins",
    "sg:classifiers":[
        {
            "category":"Retail",
            "subcategory":"Laundry & Dry Cleaning",
            "type":"Services"
        }
    ],
    "sg:phone":"+1 478 329 0990",
    "sg:postcode":"31088",
    "sg:province":"GA",
    "sg:tags":[
        "drycleaning",
        "plant"
    ],
    "wof:name":"Foxys Cleaners",
    "wof:placetype":"venue"
},
  "geometry": {"coordinates":[-83.642639,32.596751],"type":"Point"}
}