{
  "type": "Feature",
  "properties": {
    "iso:country":"US",
    "sg:address":"300 Willow Dell Dr",
    "sg:city":"Senoia",
    "sg:classifiers":[
        {
            "category":"Retail",
            "subcategory":"Photofinishing",
            "type":"Services"
        }
    ],
    "sg:phone":"+1 770 599 3912",
    "sg:postcode":"30276",
    "sg:province":"GA",
    "sg:tags":[
        "photo",
        "restoration",
        "retouching"
    ],
    "wof:name":"B Art Britt Clearie Photo",
    "wof:placetype":"venue"
},
  "geometry": {"coordinates":[-84.564283,33.305457],"type":"Point"}
}