{
  "type": "Feature",
  "properties": {
    "addr:full":"155 Story Rd Warner Robins GA 31093",
    "addr:housenumber":"155",
    "addr:postcode":"31093",
    "addr:street":"Story Rd",
    "iso:country":"US",
    "sg:address":"155 Story Rd",
    "sg:city":"Warner Robins",
    "sg:classifiers":[
        {
            "category":"Government",
            "subcategory":"Office",
            "type":"Public Place"
        }
    ],
    "sg:phone":"+1 478 328 1080",
    "sg:postcode":"31093",
    "sg:province":"GA",
    "sg:tags":[
        "city",
        "program"
    ],
    "wof:name":"Warner Robins Sanitation Dept",
    "wof:placetype":"venue"
},
  "geometry": {"coordinates":[-83.622016,32.658169],"type":"Point"}
}