{
  "type": "Feature",
  "properties": {
    "iso:country":"US",
    "sg:address":"7257 Turner Lake Rd NW",
    "sg:city":"Covington",
    "sg:classifiers":[
        {
            "category":"Retail",
            "subcategory":"Laundry & Dry Cleaning",
            "type":"Services"
        }
    ],
    "sg:phone":"+1 770 786 6737",
    "sg:postcode":"30014",
    "sg:province":"GA",
    "sg:tags":[
        "delivery",
        "cleaner",
        "pick"
    ],
    "wof:name":"Perfect Care Cleaners",
    "wof:placetype":"venue"
},
  "geometry": {"coordinates":[-83.875958,33.605451],"type":"Point"}
}