{
  "type": "Feature",
  "properties": {
    "iso:country":"US",
    "sg:address":"7610 Granite Dr",
    "sg:city":"Douglasville",
    "sg:classifiers":[
        {
            "category":"Building & Trades",
            "subcategory":"Construction",
            "type":"Services"
        }
    ],
    "sg:phone":"+1 770 942 7459",
    "sg:postcode":"30134",
    "sg:province":"GA",
    "wof:name":"CSC Enterprises",
    "wof:placetype":"venue"
},
  "geometry": {"coordinates":[-84.775547,33.738353],"type":"Point"}
}