{
  "type": "Feature",
  "properties": {
    "iso:country":"US",
    "sg:address":"1086 Piedmont Ave NE",
    "sg:city":"Atlanta",
    "sg:classifiers":[
        {
            "category":"Shopping",
            "subcategory":"Bicycles & Sporting Goods",
            "type":"Retail Goods"
        }
    ],
    "sg:phone":"+1 404 892 1292",
    "sg:postcode":"30309",
    "sg:province":"GA",
    "sg:tags":[
        "bike"
    ],
    "sg:website":"www.skateescape.com",
    "wof:name":"Skate Escape Bike Shop",
    "wof:placetype":"venue"
},
  "geometry": {"coordinates":[-84.378873,33.784382],"type":"Point"}
}