{
  "type": "Feature",
  "properties": {
    "addr:full":"11202 White Bluff Rd Savannah GA 31419",
    "addr:housenumber":"11202",
    "addr:postcode":"31419",
    "addr:street":"White Bluff Rd",
    "iso:country":"US",
    "sg:address":"11202 White Bluff Rd",
    "sg:city":"Savannah",
    "sg:classifiers":[
        {
            "category":"Freight",
            "type":"Transportation"
        }
    ],
    "sg:phone":"+1 912 961 6611",
    "sg:postcode":"31419",
    "sg:province":"GA",
    "sg:tags":[
        "real estate"
    ],
    "wof:name":"Gn Realty Inc",
    "wof:placetype":"venue"
},
  "geometry": {"coordinates":[-81.13015900000001,31.982773],"type":"Point"}
}