{
  "type": "Feature",
  "properties": {
    "iso:country":"US",
    "sg:address":"2878 Pine Valley Cir",
    "sg:city":"Atlanta",
    "sg:classifiers":[
        {
            "category":"Professional",
            "type":"Services"
        }
    ],
    "sg:phone":"+1 404 344 6442",
    "sg:postcode":"30344",
    "sg:province":"GA",
    "wof:name":"Narolds Inc",
    "wof:placetype":"venue"
},
  "geometry": {"coordinates":[-84.484296,33.672626],"type":"Point"}
}