{
  "type": "Feature",
  "properties": {
    "addr:full":"633 Fulton Rd NE Kingston GA 30145",
    "addr:housenumber":"633",
    "addr:postcode":"30145",
    "addr:street":"Fulton Rd Ne",
    "iso:country":"US",
    "sg:address":"633 Fulton Rd NE",
    "sg:city":"Kingston",
    "sg:classifiers":[
        {
            "category":"Building & Trades",
            "subcategory":"Construction",
            "type":"Services"
        }
    ],
    "sg:phone":"+1 706 291 7169",
    "sg:postcode":"30145",
    "sg:province":"GA",
    "sg:tags":[
        "home",
        "improvement"
    ],
    "wof:name":"Duvall Home Improvement",
    "wof:placetype":"venue"
},
  "geometry": {"coordinates":[-85.029856,34.274669],"type":"Point"}
}