{
  "type": "Feature",
  "properties": {
    "iso:country":"US",
    "sg:address":"4742 Maple Ridge Trl",
    "sg:city":"Columbus",
    "sg:classifiers":[
        {
            "category":"Building & Trades",
            "subcategory":"Construction",
            "type":"Services"
        }
    ],
    "sg:phone":"+1 706 565 9992",
    "sg:postcode":"31909",
    "sg:province":"GA",
    "sg:tags":[
        "carpentry",
        "contractor"
    ],
    "wof:name":"Hammerhead Carpentry",
    "wof:placetype":"venue"
},
  "geometry": {"coordinates":[-84.91365399999999,32.562255],"type":"Point"}
}