{
  "type": "Feature",
  "properties": {
    "addr:full":"265 N Clarendon Ave Scottdale GA 30079",
    "addr:housenumber":"265",
    "addr:postcode":"30079",
    "addr:street":"N Clarendon Ave",
    "iso:country":"US",
    "sg:address":"265 N Clarendon Ave",
    "sg:city":"Scottdale",
    "sg:classifiers":[
        {
            "category":"Organizations",
            "subcategory":"Religious Organization",
            "type":"Services"
        }
    ],
    "sg:phone":"+1 404 299 3968",
    "sg:postcode":"30079",
    "sg:province":"GA",
    "wof:name":"World Outreach Ministries",
    "wof:placetype":"venue"
},
  "geometry": {"coordinates":[-84.26316300000001,33.782386],"type":"Point"}
}