{
  "type": "Feature",
  "properties": {
    "addr:full":"6162 Hacklebarney Rd Blackshear GA 31516",
    "addr:housenumber":"6162",
    "addr:postcode":"31516",
    "addr:street":"Hacklebarney Rd",
    "iso:country":"US",
    "sg:address":"6162 Hacklebarney Rd",
    "sg:city":"Blackshear",
    "sg:classifiers":[
        {
            "category":"Personal",
            "subcategory":"Beauty Salon",
            "type":"Services"
        }
    ],
    "sg:phone":"+1 912 449 0690",
    "sg:postcode":"31516",
    "sg:province":"GA",
    "wof:name":"Pam's Shear Designs",
    "wof:placetype":"venue"
},
  "geometry": {"coordinates":[-82.34125400000001,31.282023],"type":"Point"}
}