{
  "type": "Feature",
  "properties": {
    "iso:country":"US",
    "sg:address":"5405 Metric Pl",
    "sg:city":"Norcross",
    "sg:classifiers":[
        {
            "category":"Professional",
            "subcategory":"Management & Consulting",
            "type":"Services"
        }
    ],
    "sg:phone":"+1 770 441 9201",
    "sg:postcode":"30092",
    "sg:province":"GA",
    "sg:tags":[
        "public",
        "relations"
    ],
    "wof:name":"M C A Promotion",
    "wof:placetype":"venue"
},
  "geometry": {"coordinates":[-84.223361,33.975699],"type":"Point"}
}