{
  "type": "Feature",
  "properties": {
    "iso:country":"US",
    "sg:address":"2015 Gainsborough Dr",
    "sg:city":"Atlanta",
    "sg:classifiers":[
        {
            "category":"Manufacturing",
            "subcategory":"Paper Products",
            "type":"Manufacturing & Wholesale Goods"
        }
    ],
    "sg:phone":"+1 678 209 1403",
    "sg:postcode":"30341",
    "sg:province":"GA",
    "sg:tags":[
        "marketing",
        "promotion",
        "display",
        "signage"
    ],
    "wof:name":"Tandem Solutions LLC",
    "wof:placetype":"venue"
},
  "geometry": {"coordinates":[-84.30892799999999,33.91649],"type":"Point"}
}