{
  "type": "Feature",
  "properties": {
    "addr:full":"2142 Hamilton Rd Lagrange GA 30241",
    "addr:housenumber":"2142",
    "addr:postcode":"30241",
    "addr:street":"Hamilton Rd",
    "iso:country":"US",
    "sg:address":"2142 Hamilton Rd",
    "sg:city":"Lagrange",
    "sg:classifiers":[
        {
            "category":"Freight",
            "type":"Transportation"
        }
    ],
    "sg:phone":"+1 706 883 8247",
    "sg:postcode":"30241",
    "sg:province":"GA",
    "sg:tags":[
        "trucking"
    ],
    "wof:name":"Wild Heavy Haul",
    "wof:placetype":"venue"
},
  "geometry": {"coordinates":[-85.009709,32.99673],"type":"Point"}
}