{
  "type": "Feature",
  "properties": {
    "iso:country":"US",
    "sg:address":"3920 Spring Creek Ln",
    "sg:city":"Atlanta",
    "sg:classifiers":[
        {
            "category":"Professional",
            "subcategory":"Management & Consulting",
            "type":"Services"
        }
    ],
    "sg:phone":"+1 770 399 9181",
    "sg:postcode":"30350",
    "sg:province":"GA",
    "wof:name":"Remix",
    "wof:placetype":"venue"
},
  "geometry": {"coordinates":[-84.366083,33.973577],"type":"Point"}
}