{
  "type": "Feature",
  "properties": {
    "addr:full":"152 Eisenhower Dr Commerce GA 30529",
    "addr:housenumber":"152",
    "addr:postcode":"30529",
    "addr:street":"Eisenhower Dr",
    "iso:country":"US",
    "sg:address":"152 Eisenhower Dr",
    "sg:city":"Commerce",
    "sg:classifiers":[
        {
            "category":"Travel",
            "subcategory":"Hotels & Motels",
            "type":"Entertainment"
        }
    ],
    "sg:phone":"+1 706 336 8008",
    "sg:postcode":"30529",
    "sg:province":"GA",
    "sg:tags":[
        "lodging"
    ],
    "sg:website":"http://www.super8commerce.com",
    "wof:name":"Super 8 Motel",
    "wof:placetype":"venue"
},
  "geometry": {"coordinates":[-83.46189200000001,34.257746],"type":"Point"}
}