{
  "type": "Feature",
  "properties": {
    "iso:country":"US",
    "sg:address":"4291 Briarcliff Rd NE",
    "sg:city":"Atlanta",
    "sg:classifiers":[
        {
            "category":"Professional",
            "subcategory":"Business Services",
            "type":"Services"
        }
    ],
    "sg:phone":"+1 404 320 7275",
    "sg:postcode":"30345",
    "sg:province":"GA",
    "sg:tags":[
        "auction"
    ],
    "wof:name":"Hawkins, Philip H Isa",
    "wof:placetype":"venue"
},
  "geometry": {"coordinates":[-84.273915,33.854801],"type":"Point"}
}