{
  "type": "Feature",
  "properties": {
    "addr:full":"1 Powersports Cir Cartersville GA 30121",
    "addr:housenumber":"1",
    "addr:postcode":"30121",
    "addr:street":"Powersports Cir",
    "iso:country":"US",
    "sg:address":"1 Powersports Cir",
    "sg:city":"Cartersville",
    "sg:classifiers":[
        {
            "category":"Wholesale",
            "subcategory":"Motor Vehicles",
            "type":"Manufacturing & Wholesale Goods"
        },
        {
            "category":"Autos & Motor Vehicles",
            "subcategory":"Automobile Sales",
            "type":"Retail Goods"
        },
        {
            "category":"Autos & Motor Vehicles",
            "subcategory":"Motorcycle Sales",
            "type":"Retail Goods"
        },
        {
            "category":"Retail",
            "subcategory":"Auto Repair",
            "type":"Services"
        },
        {
            "category":"Autos & Motor Vehicles",
            "subcategory":"Recreational Vehicle Sales",
            "type":"Retail Goods"
        }
    ],
    "sg:phone":"+1 678 535 3016",
    "sg:postcode":"30121",
    "sg:province":"GA",
    "sg:tags":[
        "scooters-repairing",
        "scooter",
        "camper",
        "all-terrain"
    ],
    "sg:website":"http://atlanta.citysearch.com/profile/external/40945521/cartersville_ga/bartow_powersports.html?publisher=yellowpages&reference_id=1&placement=ypwebsitemip",
    "wof:name":"Bartow Powersports",
    "wof:placetype":"venue"
},
  "geometry": {"coordinates":[-84.76339299999999,34.174761],"type":"Point"}
}