{
  "type": "Feature",
  "properties": {
    "addr:full":"2003 Riverside Pkwy Lawrenceville GA 30043",
    "addr:housenumber":"2003",
    "addr:postcode":"30043",
    "addr:street":"Riverside Pkwy",
    "iso:country":"US",
    "sg:address":"2003 Riverside Pkwy",
    "sg:city":"Lawrenceville",
    "sg:classifiers":[
        {
            "category":"Utilities",
            "subcategory":"Mobile Phone",
            "type":"Services"
        }
    ],
    "sg:phone":"+1 678 377 6393",
    "sg:postcode":"30043",
    "sg:province":"GA",
    "sg:tags":[
        "telephone",
        "cellular"
    ],
    "wof:name":"Money Talks Communications",
    "wof:placetype":"venue"
},
  "geometry": {"coordinates":[-84.023729,33.984305],"type":"Point"}
}