{
  "type": "Feature",
  "properties": {
    "addr:full":"446 E Paces Ferry Rd NE Atlanta GA 30305",
    "addr:housenumber":"446",
    "addr:postcode":"30305",
    "addr:street":"E Paces Ferry Rd Ne",
    "iso:country":"US",
    "sg:address":"446 E Paces Ferry Rd NE",
    "sg:city":"Atlanta",
    "sg:classifiers":[
        {
            "category":"Professional",
            "subcategory":"Business Services",
            "type":"Services"
        }
    ],
    "sg:phone":"+1 404 264 1155",
    "sg:postcode":"30305",
    "sg:province":"GA",
    "sg:tags":[
        "interior",
        "consultant",
        "design",
        "decorator"
    ],
    "wof:name":"Ashton Trente Interiors LLC",
    "wof:placetype":"venue"
},
  "geometry": {"coordinates":[-84.373518,33.838317],"type":"Point"}
}