{
  "type": "Feature",
  "properties": {
    "iso:country":"US",
    "sg:address":"312 S Main St",
    "sg:city":"Glennville",
    "sg:classifiers":[
        {
            "category":"Professional",
            "subcategory":"Accounting & Tax Preparation",
            "type":"Services"
        }
    ],
    "sg:phone":"+1 912 654 1944",
    "sg:postcode":"30427",
    "sg:province":"GA",
    "sg:tags":[
        "return"
    ],
    "wof:name":"Complete Income Tax",
    "wof:placetype":"venue"
},
  "geometry": {"coordinates":[-81.92998900000001,31.933299],"type":"Point"}
}