{
  "type": "Feature",
  "properties": {
    "iso:country":"US",
    "sg:address":"2700 E Ponce De Leon Ave",
    "sg:city":"Decatur",
    "sg:classifiers":[
        {
            "category":"Retail",
            "subcategory":"Auto Repair",
            "type":"Services"
        }
    ],
    "sg:phone":"+1 404 378 2817",
    "sg:postcode":"30030",
    "sg:province":"GA",
    "wof:name":"Mustang by Vintage",
    "wof:placetype":"venue"
},
  "geometry": {"coordinates":[-84.27889999999999,33.776798],"type":"Point"}
}