{
  "type": "Feature",
  "properties": {
    "addr:full":"119 E Jackson St Thomasville GA 31792",
    "addr:housenumber":"119",
    "addr:postcode":"31792",
    "addr:street":"E Jackson St",
    "iso:country":"US",
    "sg:address":"119 E Jackson St",
    "sg:city":"Thomasville",
    "sg:classifiers":[
        {
            "category":"Professional",
            "subcategory":"Computer Services",
            "type":"Services"
        }
    ],
    "sg:phone":"+1 229 226 2110",
    "sg:postcode":"31792",
    "sg:province":"GA",
    "sg:website":"www.networkts.com",
    "wof:name":"Network Technology Solutions",
    "wof:placetype":"venue"
},
  "geometry": {"coordinates":[-83.97918900000001,30.838305],"type":"Point"}
}