{
  "type": "Feature",
  "properties": {
    "iso:country":"US",
    "sg:address":"235 E Ponce de Leon Ave",
    "sg:city":"Decatur",
    "sg:classifiers":[
        {
            "category":"Education",
            "subcategory":"School",
            "type":"Public Place"
        }
    ],
    "sg:phone":"+1 404 373 3940",
    "sg:postcode":"30030",
    "sg:province":"GA",
    "sg:tags":[
        "educational",
        "program"
    ],
    "wof:name":"Medtec Learning Ctr",
    "wof:placetype":"venue"
},
  "geometry": {"coordinates":[-84.293298,33.775513],"type":"Point"}
}