{
  "type": "Feature",
  "properties": {
    "addr:full":"1912 W Hampton Pointe Statesboro GA 30458",
    "addr:housenumber":"1912",
    "addr:postcode":"30458",
    "addr:street":"W Hampton",
    "iso:country":"US",
    "sg:address":"1912 W Hampton Pointe",
    "sg:city":"Statesboro",
    "sg:classifiers":[
        {
            "category":"Health Services",
            "subcategory":"Clinic",
            "type":"Services"
        }
    ],
    "sg:phone":"+1 912 764 3788",
    "sg:postcode":"30458",
    "sg:province":"GA",
    "wof:name":"Classic Medical Inc",
    "wof:placetype":"venue"
},
  "geometry": {"coordinates":[-81.83380699999999,32.442312],"type":"Point"}
}