{
  "type": "Feature",
  "properties": {
    "iso:country":"US",
    "sg:address":"1594 Veterans Memorial Pkwy SW",
    "sg:city":"Austell",
    "sg:classifiers":[
        {
            "category":"Autos & Motor Vehicles",
            "subcategory":"Auto Supplies",
            "type":"Retail Goods"
        }
    ],
    "sg:phone":"+1 770 433 1346",
    "sg:postcode":"30168",
    "sg:province":"GA",
    "sg:tags":[
        "automobile",
        "stereo",
        "radio"
    ],
    "wof:name":"K & J Custom Car Sound",
    "wof:placetype":"venue"
},
  "geometry": {"coordinates":[-84.602279,33.816091],"type":"Point"}
}