{
  "type": "Feature",
  "properties": {
    "iso:country":"US",
    "sg:address":"2870 Peachtree Rd NW PMB 626",
    "sg:city":"Atlanta",
    "sg:classifiers":[
        {
            "category":"Banks & Credit Unions",
            "subcategory":"Investment Brokerage",
            "type":"Services"
        },
        {
            "category":"Insurance",
            "subcategory":"Life Insurance",
            "type":"Services"
        },
        {
            "category":"Banks & Credit Unions",
            "subcategory":"Financial Services",
            "type":"Services"
        },
        {
            "category":"Insurance",
            "subcategory":"Health Insurance",
            "type":"Services"
        }
    ],
    "sg:phone":"+1 404 806 8162",
    "sg:postcode":"30305",
    "sg:province":"GA",
    "sg:tags":[
        "advisory",
        "dental",
        "management"
    ],
    "sg:website":"http://www.atravircapital.com",
    "wof:name":"Atra Vir Capital LLC",
    "wof:placetype":"venue"
},
  "geometry": {"coordinates":[-84.383199,33.833637],"type":"Point"}
}