{
  "type": "Feature",
  "properties": {
    "iso:country":"US",
    "sg:address":"6059 Boylston Dr NE",
    "sg:city":"Atlanta",
    "sg:classifiers":[
        {
            "category":"Professional",
            "subcategory":"Engineering",
            "type":"Services"
        }
    ],
    "sg:phone":"+1 404 255 2650",
    "sg:postcode":"30328",
    "sg:province":"GA",
    "sg:tags":[
        "engineer"
    ],
    "wof:name":"Peoples & Quigley Inc",
    "wof:placetype":"venue"
},
  "geometry": {"coordinates":[-84.377122,33.921848],"type":"Point"}
}