{
  "type": "Feature",
  "properties": {
    "iso:country":"US",
    "sg:address":"367 McDonough Pkwy",
    "sg:city":"Mcdonough",
    "sg:classifiers":[
        {
            "category":"Shopping",
            "subcategory":"Computers & Home Electronics",
            "type":"Retail Goods"
        }
    ],
    "sg:phone":"+1 770 898 8511",
    "sg:postcode":"30253",
    "sg:province":"GA",
    "sg:tags":[
        "system"
    ],
    "wof:name":"Home Theatre Store",
    "wof:placetype":"venue"
},
  "geometry": {"coordinates":[-84.167063,33.441105],"type":"Point"}
}