{
  "type": "Feature",
  "properties": {
    "iso:country":"US",
    "sg:address":"3060 Baxley Ct",
    "sg:city":"Atlanta",
    "sg:classifiers":[
        {
            "category":"Social Services",
            "subcategory":"Child Care",
            "type":"Services"
        }
    ],
    "sg:phone":"+1 770 994 0327",
    "sg:postcode":"30349",
    "sg:province":"GA",
    "sg:tags":[
        "day"
    ],
    "wof:name":"Terry Tots Daycare",
    "wof:placetype":"venue"
},
  "geometry": {"coordinates":[-84.48958500000001,33.56755],"type":"Point"}
}