{
  "type": "Feature",
  "properties": {
    "addr:full":"1650 W Oak Dr Marietta GA 30062",
    "addr:housenumber":"1650",
    "addr:postcode":"30062",
    "addr:street":"W Oak Dr",
    "iso:country":"US",
    "sg:address":"1650 W Oak Dr",
    "sg:city":"Marietta",
    "sg:classifiers":[
        {
            "category":"Professional",
            "type":"Services"
        }
    ],
    "sg:phone":"+1 770 426 1244",
    "sg:postcode":"30062",
    "sg:province":"GA",
    "sg:tags":[
        "establishment"
    ],
    "wof:name":"Vinings Industries Inc",
    "wof:placetype":"venue"
},
  "geometry": {"coordinates":[-84.52794799999999,33.99159],"type":"Point"}
}