{
  "type": "Feature",
  "properties": {
    "iso:country":"US",
    "sg:address":"9663 Jackson Trail Rd",
    "sg:city":"Hoschton",
    "sg:classifiers":[
        {
            "category":"Professional",
            "subcategory":"Management & Consulting",
            "type":"Services"
        }
    ],
    "sg:phone":"+1 706 654 3232",
    "sg:postcode":"30548",
    "sg:province":"GA",
    "sg:tags":[
        "consultant"
    ],
    "sg:website":"http://www.ibis-usa.com",
    "wof:name":"Ibis International",
    "wof:placetype":"venue"
},
  "geometry": {"coordinates":[-83.743549,34.086976],"type":"Point"}
}