{
  "type": "Feature",
  "properties": {
    "addr:full":"5991 Spencer Oaks Ct Lithonia GA 30058",
    "addr:housenumber":"5991",
    "addr:postcode":"30058",
    "addr:street":"Spencer Oaks Ct",
    "iso:country":"US",
    "sg:address":"5991 Spencer Oaks Ct",
    "sg:city":"Lithonia",
    "sg:classifiers":[
        {
            "category":"Building & Trades",
            "subcategory":"Landscaping Services",
            "type":"Services"
        }
    ],
    "sg:phone":"+1 770 808 4131",
    "sg:postcode":"30058",
    "sg:province":"GA",
    "wof:name":"Berry Mowing Service",
    "wof:placetype":"venue"
},
  "geometry": {"coordinates":[-84.14407199999999,33.730981],"type":"Point"}
}