{
  "type": "Feature",
  "properties": {
    "iso:country":"US",
    "sg:address":"6746 Ridge Moore Dr NW",
    "sg:city":"Atlanta",
    "sg:classifiers":[
        {
            "category":"Professional",
            "subcategory":"Business Services",
            "type":"Services"
        }
    ],
    "sg:phone":"+1 404 358 5399",
    "sg:postcode":"30360",
    "sg:province":"GA",
    "wof:name":"Bassett Group LLC",
    "wof:placetype":"venue"
},
  "geometry": {"coordinates":[-84.262935,33.952731],"type":"Point"}
}