{
  "type": "Feature",
  "properties": {
    "addr:full":"2976 Ask Kay Dr SE Ste A Smyrna GA 30082",
    "addr:housenumber":"2976",
    "addr:postcode":"30082",
    "addr:street":"Kay Dr Se Ste A",
    "iso:country":"US",
    "sg:address":"2976 Ask Kay Dr SE Ste A",
    "sg:city":"Smyrna",
    "sg:classifiers":[
        {
            "category":"Building & Trades",
            "subcategory":"Equipment Rental",
            "type":"Services"
        }
    ],
    "sg:phone":"+1 404 353 4014",
    "sg:postcode":"30082",
    "sg:province":"GA",
    "sg:tags":[
        "yard",
        "leasing",
        "store"
    ],
    "wof:name":"A1 Tent Party Rentals",
    "wof:placetype":"venue"
},
  "geometry": {"coordinates":[-84.5338,33.880959],"type":"Point"}
}