{
  "type": "Feature",
  "properties": {
    "iso:country":"US",
    "sg:address":"7465 Westwood Rd",
    "sg:city":"Douglasville",
    "sg:classifiers":[
        {
            "category":"Building & Trades",
            "subcategory":"Plumbing",
            "type":"Services"
        }
    ],
    "sg:phone":"+1 770 949 2284",
    "sg:postcode":"30134",
    "sg:province":"GA",
    "sg:tags":[
        "air",
        "heating",
        "conditioning",
        "contractor"
    ],
    "wof:name":"Long Fred Heating & AC",
    "wof:placetype":"venue"
},
  "geometry": {"coordinates":[-84.765914,33.756292],"type":"Point"}
}