{
  "type": "Feature",
  "properties": {
    "addr:full":"2047 Grayson Hwy Grayson GA 30017",
    "addr:housenumber":"2047",
    "addr:postcode":"30017",
    "addr:street":"Grayson Hwy",
    "iso:country":"US",
    "sg:address":"2047 Grayson Hwy",
    "sg:city":"Grayson",
    "sg:classifiers":[
        {
            "category":"Insurance",
            "subcategory":"Insurance Agent",
            "type":"Services"
        }
    ],
    "sg:phone":"+1 770 338 4444",
    "sg:postcode":"30017",
    "sg:province":"GA",
    "wof:name":"Stuart G Allen Insurance",
    "wof:placetype":"venue"
},
  "geometry": {"coordinates":[-83.957624,33.895284],"type":"Point"}
}