{
  "type": "Feature",
  "properties": {
    "iso:country":"US",
    "sg:address":"970 Hill Rd",
    "sg:city":"Thomasville",
    "sg:classifiers":[
        {
            "category":"Organizations",
            "subcategory":"Religious Organization",
            "type":"Services"
        }
    ],
    "sg:phone":"+1 229 228 5025",
    "sg:postcode":"31757",
    "sg:province":"GA",
    "sg:tags":[
        "church"
    ],
    "wof:name":"Rebecca Missionary Baptist Chr",
    "wof:placetype":"venue"
},
  "geometry": {"coordinates":[-83.92813099999999,30.867837],"type":"Point"}
}