{
  "type": "Feature",
  "properties": {
    "addr:full":"3411 Turkey Mountain Rd NE Rome GA 30161",
    "addr:housenumber":"3411",
    "addr:postcode":"ga 30161",
    "addr:street":"Turkey Mountain Rd Ne",
    "iso:country":"US",
    "sg:address":"3411 Turkey Mountain Rd NE",
    "sg:city":"Rome",
    "sg:classifiers":[
        {
            "category":"Wholesale",
            "subcategory":"Machinery & Supplies",
            "type":"Manufacturing & Wholesale Goods"
        }
    ],
    "sg:phone":"+1 706 291 3778",
    "sg:postcode":"30161",
    "sg:province":"GA",
    "sg:tags":[
        "equipment",
        "safety",
        "clothing"
    ],
    "wof:name":"Safety South Supplies Inc",
    "wof:placetype":"venue"
},
  "geometry": {"coordinates":[-85.072377,34.368586],"type":"Point"}
}