{
  "type": "Feature",
  "properties": {
    "addr:full":"1220 Six Flags Rd Austell GA 30168",
    "addr:housenumber":"1220",
    "addr:postcode":"30168",
    "addr:street":"Six Flags Rd",
    "iso:country":"US",
    "sg:address":"1220 Six Flags Rd",
    "sg:city":"Austell",
    "sg:classifiers":[
        {
            "category":"Building & Trades",
            "subcategory":"Landscaping Services",
            "type":"Services"
        }
    ],
    "sg:phone":"+1 770 739 5048",
    "sg:postcode":"30168",
    "sg:province":"GA",
    "sg:tags":[
        "tree"
    ],
    "wof:name":"Tree Of Life",
    "wof:placetype":"venue"
},
  "geometry": {"coordinates":[-84.58147200000001,33.751893],"type":"Point"}
}