{
  "type": "Feature",
  "properties": {
    "iso:country":"US",
    "sg:address":"960 Eagle Pointe Dr NW",
    "sg:city":"Lawrenceville",
    "sg:classifiers":[
        {
            "category":"Banks & Credit Unions",
            "subcategory":"Financial Services",
            "type":"Services"
        }
    ],
    "sg:phone":"+1 678 377 9735",
    "sg:postcode":"30044",
    "sg:province":"GA",
    "sg:tags":[
        "investment",
        "closed"
    ],
    "wof:name":"Investor of New Age & Assoc",
    "wof:placetype":"venue"
},
  "geometry": {"coordinates":[-84.06961099999999,33.946019],"type":"Point"}
}