{
  "type": "Feature",
  "properties": {
    "iso:country":"US",
    "sg:address":"271 Connecticut Ave NE",
    "sg:city":"Atlanta",
    "sg:classifiers":[
        {
            "category":"Professional",
            "subcategory":"Management & Consulting",
            "type":"Services"
        }
    ],
    "sg:phone":"+1 404 371 9757",
    "sg:postcode":"30307",
    "sg:province":"GA",
    "sg:tags":[
        "business"
    ],
    "wof:name":"Quartles Sttistical Consulting",
    "wof:placetype":"venue"
},
  "geometry": {"coordinates":[-84.329252,33.76086],"type":"Point"}
}