{
  "type": "Feature",
  "properties": {
    "addr:full":"705 N Caswell St Glennville GA 30427",
    "addr:housenumber":"705",
    "addr:postcode":"30427",
    "addr:street":"N Caswell St",
    "iso:country":"US",
    "sg:address":"705 N Caswell St",
    "sg:city":"Glennville",
    "sg:classifiers":[
        {
            "category":"Government",
            "subcategory":"Office",
            "type":"Public Place"
        }
    ],
    "sg:phone":"+1 912 654 5060",
    "sg:postcode":"30427",
    "sg:province":"GA",
    "sg:tags":[
        "state",
        "inspection"
    ],
    "wof:name":"Labor Dept",
    "wof:placetype":"venue"
},
  "geometry": {"coordinates":[-81.925011,31.946648],"type":"Point"}
}