{
  "type": "Feature",
  "properties": {
    "iso:country":"US",
    "sg:address":"1016 Virginia St",
    "sg:city":"Columbus",
    "sg:classifiers":[
        {
            "category":"Freight",
            "type":"Transportation"
        }
    ],
    "sg:phone":"+1 706 653 2302",
    "sg:postcode":"31901",
    "sg:province":"GA",
    "sg:tags":[
        "farm",
        "raw",
        "product",
        "general"
    ],
    "wof:name":"Allenberg Cotton Co",
    "wof:placetype":"venue"
},
  "geometry": {"coordinates":[-84.977361,32.473485],"type":"Point"}
}