{
  "type": "Feature",
  "properties": {
    "iso:country":"US",
    "sg:address":"178 Hogan Rd",
    "sg:city":"Sumner",
    "sg:classifiers":[
        {
            "category":"Farming",
            "subcategory":"Farm",
            "type":"Manufacturing & Wholesale Goods"
        }
    ],
    "sg:phone":"+1 229 776 9737",
    "sg:postcode":"31789",
    "sg:province":"GA",
    "sg:tags":[
        "crop",
        "general"
    ],
    "wof:name":"Hogan Farms",
    "wof:placetype":"venue"
},
  "geometry": {"coordinates":[-83.68610200000001,31.462017],"type":"Point"}
}