{
  "type": "Feature",
  "properties": {
    "addr:full":"2949 Nestle Creek Dr Marietta GA 30062",
    "addr:housenumber":"2949",
    "addr:postcode":"30062",
    "addr:street":"Nestle Creek Dr",
    "iso:country":"US",
    "sg:address":"2949 Nestle Creek Dr",
    "sg:city":"Marietta",
    "sg:classifiers":[
        {
            "category":"Real Estate",
            "subcategory":"Real Estate Operator",
            "type":"Services"
        }
    ],
    "sg:phone":"+1 770 973 3949",
    "sg:postcode":"30062",
    "sg:province":"GA",
    "sg:tags":[
        "building",
        "nonresidential"
    ],
    "wof:name":"Cavan Properties Inc",
    "wof:placetype":"venue"
},
  "geometry": {"coordinates":[-84.469071,33.990108],"type":"Point"}
}