{
  "type": "Feature",
  "properties": {
    "addr:full":"6175 Poplar Spring Dr Norcross GA 30092",
    "addr:housenumber":"6175",
    "addr:postcode":"30092",
    "addr:street":"Poplar Spring Dr",
    "iso:country":"US",
    "sg:address":"6175 Poplar Spring Dr",
    "sg:city":"Norcross",
    "sg:classifiers":[
        {
            "category":"Professional",
            "type":"Services"
        }
    ],
    "sg:phone":"+1 770 729 0380",
    "sg:postcode":"30092",
    "sg:province":"GA",
    "wof:name":"Ga400 Inc",
    "wof:placetype":"venue"
},
  "geometry": {"coordinates":[-84.25321,33.974521],"type":"Point"}
}