{
  "type": "Feature",
  "properties": {
    "iso:country":"US",
    "sg:address":"515 River Oak Loop",
    "sg:city":"Lawrenceville",
    "sg:classifiers":[
        {
            "category":"Professional",
            "subcategory":"Management & Consulting",
            "type":"Services"
        }
    ],
    "sg:phone":"+1 678 344 2305",
    "sg:postcode":"30044",
    "sg:province":"GA",
    "sg:tags":[
        "business"
    ],
    "wof:name":"Teamxl",
    "wof:placetype":"venue"
},
  "geometry": {"coordinates":[-84.075552,33.892007],"type":"Point"}
}