{
  "type": "Feature",
  "properties": {
    "iso:country":"US",
    "sg:address":"1560 Oglethorpe Ave",
    "sg:city":"Athens",
    "sg:classifiers":[
        {
            "category":"Autos & Motor Vehicles",
            "subcategory":"Fuel & Gas Station",
            "type":"Retail Goods"
        }
    ],
    "sg:phone":"+1 706 548 9060",
    "sg:postcode":"30606",
    "sg:province":"GA",
    "sg:tags":[
        "station",
        "gasoline"
    ],
    "wof:name":"Oglethorpe Avenue 66",
    "wof:placetype":"venue"
},
  "geometry": {"coordinates":[-83.42402,33.962641],"type":"Point"}
}