{
  "type": "Feature",
  "properties": {
    "addr:full":"130 Eagle Spring Ct Stockbridge GA 30281",
    "addr:housenumber":"130",
    "addr:postcode":"30281",
    "addr:street":"Eagle Spring Ct",
    "iso:country":"US",
    "sg:address":"130 Eagle Spring Ct",
    "sg:city":"Stockbridge",
    "sg:classifiers":[
        {
            "category":"Health Services",
            "subcategory":"Doctor",
            "type":"Services"
        }
    ],
    "sg:phone":"+1 770 474 2200",
    "sg:postcode":"30281",
    "sg:province":"GA",
    "sg:tags":[
        "medical"
    ],
    "wof:name":"Mohamad Kassem MD",
    "wof:placetype":"venue"
},
  "geometry": {"coordinates":[-84.227992,33.509697],"type":"Point"}
}