{
  "type": "Feature",
  "properties": {
    "addr:full":"119 Hardie St Gordon GA 31031",
    "addr:housenumber":"119",
    "addr:postcode":"31031",
    "addr:street":"Hardie St",
    "iso:country":"US",
    "sg:address":"119 Hardie St",
    "sg:city":"Gordon",
    "sg:classifiers":[
        {
            "category":"Building & Trades",
            "subcategory":"Landscaping Services",
            "type":"Services"
        }
    ],
    "sg:phone":"+1 478 718 7371",
    "sg:postcode":"31031",
    "sg:province":"GA",
    "sg:tags":[
        "lawn",
        "maintenance"
    ],
    "wof:name":"Rooftop Lawncare",
    "wof:placetype":"venue"
},
  "geometry": {"coordinates":[-83.34437800000001,32.88432],"type":"Point"}
}