{
  "type": "Feature",
  "properties": {
    "iso:country":"US",
    "sg:address":"195 Lodge Trl",
    "sg:city":"Fayetteville",
    "sg:classifiers":[
        {
            "category":"Banks & Credit Unions",
            "subcategory":"Bank",
            "type":"Services"
        }
    ],
    "sg:phone":"+1 770 716 5020",
    "sg:postcode":"30215",
    "sg:province":"GA",
    "sg:tags":[
        "personal",
        "institution"
    ],
    "wof:name":"Household In A Hurry LLC",
    "wof:placetype":"venue"
},
  "geometry": {"coordinates":[-84.51594,33.338843],"type":"Point"}
}