{
  "type": "Feature",
  "properties": {
    "iso:country":"US",
    "sg:address":"1820 Bentbrooke Trl",
    "sg:city":"Lawrenceville",
    "sg:classifiers":[
        {
            "category":"Building & Trades",
            "subcategory":"Construction",
            "type":"Services"
        }
    ],
    "sg:phone":"+1 770 480 7302",
    "sg:postcode":"30043",
    "sg:province":"GA",
    "sg:tags":[
        "house"
    ],
    "wof:name":"Mg Construction",
    "wof:placetype":"venue"
},
  "geometry": {"coordinates":[-83.98553200000001,34.023739],"type":"Point"}
}