{
  "type": "Feature",
  "properties": {
    "addr:full":"1027 Walnut St Louisville GA 30434",
    "addr:housenumber":"1027",
    "addr:postcode":"30434",
    "addr:street":"Walnut St",
    "iso:country":"US",
    "sg:address":"1027 Walnut St",
    "sg:city":"Louisville",
    "sg:classifiers":[
        {
            "category":"Professional",
            "type":"Services"
        }
    ],
    "sg:phone":"+1 478 625 8835",
    "sg:postcode":"30434",
    "sg:province":"GA",
    "wof:name":"Ellen Hawthorne",
    "wof:placetype":"venue"
},
  "geometry": {"coordinates":[-82.40121499999999,33.007948],"type":"Point"}
}