{
  "type": "Feature",
  "properties": {
    "iso:country":"US",
    "sg:address":"307 Church Sawmill Rd",
    "sg:city":"Demorest",
    "sg:classifiers":[
        {
            "category":"Personal",
            "subcategory":"Beauty Salon",
            "type":"Services"
        }
    ],
    "sg:phone":"+1 706 754 6416",
    "sg:postcode":"30535",
    "sg:province":"GA",
    "wof:name":"Country Curls",
    "wof:placetype":"venue"
},
  "geometry": {"coordinates":[-83.52779099999999,34.581586],"type":"Point"}
}