{
  "type": "Feature",
  "properties": {
    "addr:full":"5023 Peachtree Rd Atlanta GA 30341",
    "addr:housenumber":"5023",
    "addr:postcode":"30341",
    "addr:street":"Peachtree Rd",
    "iso:country":"US",
    "sg:address":"5023 Peachtree Rd",
    "sg:city":"Atlanta",
    "sg:classifiers":[
        {
            "category":"Retail",
            "subcategory":"Auto Rental",
            "type":"Services"
        }
    ],
    "sg:phone":"+1 770 455 8318",
    "sg:postcode":"30341",
    "sg:province":"GA",
    "sg:tags":[
        "renting",
        "leasing",
        "trailer"
    ],
    "sg:website":"http://www.uhaul.com",
    "wof:name":"U-Haul Co",
    "wof:placetype":"venue"
},
  "geometry": {"coordinates":[-84.315428,33.883714],"type":"Point"}
}