{
  "type": "Feature",
  "properties": {
    "addr:full":"1000 Corporate Center Dr Morrow GA 30260",
    "addr:housenumber":"1000",
    "addr:postcode":"30260",
    "addr:street":"Corporate Center Dr",
    "iso:country":"US",
    "sg:address":"1000 Corporate Center Dr",
    "sg:city":"Morrow",
    "sg:classifiers":[
        {
            "category":"Health Services",
            "subcategory":"Optometrist",
            "type":"Services"
        },
        {
            "category":"Shopping",
            "subcategory":"Optician",
            "type":"Retail Goods"
        }
    ],
    "sg:phone":"+1 770 968 8888",
    "sg:postcode":"30260",
    "sg:province":"GA",
    "sg:tags":[
        "ophthalmologist",
        "eyewear"
    ],
    "sg:website":"www.claytoneyecenter.com",
    "wof:name":"New James E OD",
    "wof:placetype":"venue"
},
  "geometry": {"coordinates":[-84.332397,33.570599],"type":"Point"}
}