{
  "type": "Feature",
  "properties": {
    "iso:country":"US",
    "sg:address":"6524 Buford Hwy NE",
    "sg:city":"Atlanta",
    "sg:classifiers":[
        {
            "category":"Retail",
            "subcategory":"Auto Repair",
            "type":"Services"
        }
    ],
    "sg:phone":"+1 770 242 8777",
    "sg:postcode":"30340",
    "sg:province":"GA",
    "wof:name":"Grand Shop",
    "wof:placetype":"venue"
},
  "geometry": {"coordinates":[-84.236386,33.929093],"type":"Point"}
}