{
  "type": "Feature",
  "properties": {
    "iso:country":"US",
    "sg:address":"623 Crawford Ave",
    "sg:city":"Augusta",
    "sg:classifiers":[
        {
            "category":"Place Of Worship",
            "subcategory":"Church",
            "type":"Public Place"
        },
        {
            "category":"Place Of Worship",
            "type":"Public Place"
        }
    ],
    "sg:phone":"+1 706 736 4060",
    "sg:postcode":"30904",
    "sg:province":"GA",
    "sg:tags":[
        "episcopal",
        "churches-african",
        "ame",
        "methodist"
    ],
    "wof:name":"Bethel African Methodist Episcopal Church",
    "wof:placetype":"venue"
},
  "geometry": {"coordinates":[-81.995903,33.479519],"type":"Point"}
}