{
  "type": "Feature",
  "properties": {
    "iso:country":"US",
    "sg:address":"4503 Lost Mountain Ct",
    "sg:city":"Powder Springs",
    "sg:classifiers":[
        {
            "category":"Building & Trades",
            "subcategory":"Construction",
            "type":"Services"
        }
    ],
    "sg:phone":"+1 770 514 0144",
    "sg:postcode":"30127",
    "sg:province":"GA",
    "sg:tags":[
        "hanging",
        "contractor"
    ],
    "wof:name":"Sanders Paint Contr",
    "wof:placetype":"venue"
},
  "geometry": {"coordinates":[-84.687141,33.920421],"type":"Point"}
}