{
  "type": "Feature",
  "properties": {
    "iso:country":"US",
    "sg:address":"17 Market Cir",
    "sg:city":"Barnesville",
    "sg:classifiers":[
        {
            "category":"Restaurant",
            "type":"Food & Drink"
        }
    ],
    "sg:phone":"+1 770 872 2272",
    "sg:postcode":"30277",
    "sg:province":"GA",
    "wof:name":"Richard's Restaurant",
    "wof:placetype":"venue"
},
  "geometry": {"coordinates":[-84.64579500000001,33.399342],"type":"Point"}
}