{
  "type": "Feature",
  "properties": {
    "addr:full":"710B N Church St Ste B Thomaston GA 30286",
    "addr:housenumber":"710b",
    "addr:postcode":"30286",
    "addr:street":"N Church St Ste B",
    "iso:country":"US",
    "sg:address":"710B N Church St Ste B",
    "sg:city":"Thomaston",
    "sg:classifiers":[
        {
            "category":"Home & Garden",
            "subcategory":"Furniture",
            "type":"Retail Goods"
        }
    ],
    "sg:phone":"+1 706 648 3700",
    "sg:postcode":"30286",
    "sg:province":"GA",
    "sg:tags":[
        "store"
    ],
    "sg:website":"http://www.farmersfurniture.com",
    "wof:name":"Farmers Furniture",
    "wof:placetype":"venue"
},
  "geometry": {"coordinates":[-84.32937200000001,32.902487],"type":"Point"}
}