{
  "type": "Feature",
  "properties": {
    "iso:country":"US",
    "sg:address":"2911 Veazey Rd",
    "sg:city":"Greensboro",
    "sg:classifiers":[
        {
            "category":"Wholesale",
            "subcategory":"Durable Goods & Equipment",
            "type":"Manufacturing & Wholesale Goods"
        }
    ],
    "sg:phone":"+1 706 453 1348",
    "sg:postcode":"30642",
    "sg:province":"GA",
    "sg:tags":[
        "antique",
        "new",
        "furniture"
    ],
    "wof:name":"Tymes Furniture Co",
    "wof:placetype":"venue"
},
  "geometry": {"coordinates":[-83.168752,33.546032],"type":"Point"}
}