{
  "type": "Feature",
  "properties": {
    "iso:country":"US",
    "sg:address":"212 Adair St",
    "sg:city":"Decatur",
    "sg:classifiers":[
        {
            "category":"Real Estate",
            "subcategory":"Real Estate Operator",
            "type":"Services"
        }
    ],
    "sg:phone":"+1 404 373 4368",
    "sg:postcode":"30030",
    "sg:province":"GA",
    "sg:tags":[
        "apartment"
    ],
    "wof:name":"Adair Oaks Apartments",
    "wof:placetype":"venue"
},
  "geometry": {"coordinates":[-84.30660899999999,33.769711],"type":"Point"}
}