{
  "type": "Feature",
  "properties": {
    "addr:full":"4197 Thurmond Tanner Rd Flowery Branch GA 30542",
    "addr:housenumber":"4197",
    "addr:postcode":"30542",
    "addr:street":"Thurmond Tanner Rd",
    "iso:country":"US",
    "sg:address":"4197 Thurmond Tanner Rd",
    "sg:city":"Flowery Branch",
    "sg:classifiers":[
        {
            "category":"Wholesale",
            "subcategory":"Construction Materials",
            "type":"Manufacturing & Wholesale Goods"
        }
    ],
    "sg:phone":"+1 770 967 9996",
    "sg:postcode":"30542",
    "sg:province":"GA",
    "sg:tags":[
        "lumber"
    ],
    "wof:name":"Builder Ready Products",
    "wof:placetype":"venue"
},
  "geometry": {"coordinates":[-83.88922700000001,34.209279],"type":"Point"}
}