{
  "type": "Feature",
  "properties": {
    "iso:country":"US",
    "sg:address":"1575 Dahlonega Hwy",
    "sg:city":"Cumming",
    "sg:classifiers":[
        {
            "category":"Shopping",
            "subcategory":"Used Merchandise",
            "type":"Retail Goods"
        }
    ],
    "sg:phone":"+1 770 887 5320",
    "sg:postcode":"30040",
    "sg:province":"GA",
    "wof:name":"Ja & L Antiques",
    "wof:placetype":"venue"
},
  "geometry": {"coordinates":[-84.122451,34.237415],"type":"Point"}
}