{
  "type": "Feature",
  "properties": {
    "addr:full":"3781 Happy Valley Cir Newnan GA 30263",
    "addr:housenumber":"3781",
    "addr:postcode":"30263",
    "addr:street":"Happy Valley Cir",
    "iso:country":"US",
    "sg:address":"3781 Happy Valley Cir",
    "sg:city":"Newnan",
    "sg:classifiers":[
        {
            "category":"Wholesale",
            "subcategory":"Farm Supplies",
            "type":"Manufacturing & Wholesale Goods"
        }
    ],
    "sg:phone":"+1 770 253 8100",
    "sg:postcode":"30263",
    "sg:province":"GA",
    "sg:tags":[
        "horse",
        "dealer"
    ],
    "wof:name":"Redwine Farms",
    "wof:placetype":"venue"
},
  "geometry": {"coordinates":[-84.752107,33.466471],"type":"Point"}
}