{
  "type": "Feature",
  "properties": {
    "iso:country":"US",
    "sg:address":"655 Atlanta Rd",
    "sg:city":"Cumming",
    "sg:classifiers":[
        {
            "category":"Retail",
            "subcategory":"Repair Shop",
            "type":"Services"
        }
    ],
    "sg:phone":"+1 770 888 5130",
    "sg:postcode":"30040",
    "sg:province":"GA",
    "wof:name":"Jetlag Inc",
    "wof:placetype":"venue"
},
  "geometry": {"coordinates":[-84.13862899999999,34.18916],"type":"Point"}
}