{
  "type": "Feature",
  "properties": {
    "iso:country":"US",
    "sg:address":"4236 Tilly Mill Road",
    "sg:city":"Atlanta",
    "sg:classifiers":[
        {
            "category":"Education",
            "subcategory":"School",
            "type":"Public Place"
        }
    ],
    "sg:phone":"+1 678 676 7302",
    "sg:postcode":"30360",
    "sg:province":"GA",
    "sg:tags":[
        "high",
        "middle",
        "elementary"
    ],
    "wof:name":"Dekalb County School District",
    "wof:placetype":"venue"
},
  "geometry": {"coordinates":[-84.279864,33.918207],"type":"Point"}
}