{
  "type": "Feature",
  "properties": {
    "addr:full":"510 Bellevue Ave Dublin GA 31021",
    "addr:housenumber":"510",
    "addr:postcode":"31021",
    "addr:street":"Bellevue Ave",
    "iso:country":"US",
    "sg:address":"510 Bellevue Ave",
    "sg:city":"Dublin",
    "sg:classifiers":[
        {
            "category":"Professional",
            "subcategory":"Credit Reporting & Collection",
            "type":"Services"
        }
    ],
    "sg:phone":"+1 478 274 8222",
    "sg:postcode":"31021",
    "sg:province":"GA",
    "sg:tags":[
        "agency"
    ],
    "wof:name":"Credit Bureau Assoc Of Ga",
    "wof:placetype":"venue"
},
  "geometry": {"coordinates":[-82.909961,32.53842],"type":"Point"}
}