{
  "type": "Feature",
  "properties": {
    "iso:country":"US",
    "sg:address":"1919 Atlanta Hwy SE",
    "sg:city":"Statham",
    "sg:classifiers":[
        {
            "category":"Restaurant",
            "type":"Food & Drink"
        }
    ],
    "sg:phone":"+1 770 725 4525",
    "sg:postcode":"30666",
    "sg:province":"GA",
    "wof:name":"Papa's Pizza To Go",
    "wof:placetype":"venue"
},
  "geometry": {"coordinates":[-83.61133599999999,33.972842],"type":"Point"}
}