{
  "type": "Feature",
  "properties": {
    "addr:full":"426 W Highland Ave Monroe GA 30655",
    "addr:housenumber":"426",
    "addr:postcode":"30655",
    "addr:street":"W Highland Ave",
    "iso:country":"US",
    "sg:address":"426 W Highland Ave",
    "sg:city":"Monroe",
    "sg:classifiers":[
        {
            "category":"Real Estate",
            "subcategory":"Real Estate Agent",
            "type":"Services"
        }
    ],
    "sg:phone":"+1 770 267 8553",
    "sg:postcode":"30655",
    "sg:province":"GA",
    "wof:name":"Re/Max Preferred",
    "wof:placetype":"venue"
},
  "geometry": {"coordinates":[-83.720811,33.795295],"type":"Point"}
}