{
  "type": "Feature",
  "properties": {
    "addr:full":"3065 Bugle Dr Duluth GA 30096",
    "addr:housenumber":"3065",
    "addr:postcode":"30096",
    "addr:street":"Bugle Dr",
    "iso:country":"US",
    "sg:address":"3065 Bugle Dr",
    "sg:city":"Duluth",
    "sg:classifiers":[
        {
            "category":"Health Services",
            "subcategory":"Medical Lab",
            "type":"Services"
        }
    ],
    "sg:phone":"+1 770 814 0881",
    "sg:postcode":"30096",
    "sg:province":"GA",
    "sg:tags":[
        "laboratory",
        "dental"
    ],
    "wof:name":"Nu Way Dental Labs",
    "wof:placetype":"venue"
},
  "geometry": {"coordinates":[-84.136256,33.988881],"type":"Point"}
}