{
  "type": "Feature",
  "properties": {
    "addr:full":"6010 Colt Ridge Trl SE Mableton GA 30126",
    "addr:housenumber":"6010",
    "addr:postcode":"30126",
    "addr:street":"Colt Ridge Trl Se",
    "iso:country":"US",
    "sg:address":"6010 Colt Ridge Trl SE",
    "sg:city":"Mableton",
    "sg:classifiers":[
        {
            "category":"Personal",
            "type":"Services"
        }
    ],
    "sg:phone":"+1 404 557 5140",
    "sg:postcode":"30126",
    "sg:province":"GA",
    "wof:name":"ADS",
    "wof:placetype":"venue"
},
  "geometry": {"coordinates":[-84.51145200000001,33.809507],"type":"Point"}
}