{
  "type": "Feature",
  "properties": {
    "iso:country":"US",
    "sg:address":"136 Peachtree Memorial Dr NW",
    "sg:city":"Atlanta",
    "sg:classifiers":[
        {
            "category":"Home & Garden",
            "subcategory":"Furniture",
            "type":"Retail Goods"
        }
    ],
    "sg:phone":"+1 404 351 0290",
    "sg:postcode":"30309",
    "sg:province":"GA",
    "sg:tags":[
        "store"
    ],
    "wof:name":"Texicraft Outdoor Furniture Inc",
    "wof:placetype":"venue"
},
  "geometry": {"coordinates":[-84.39447699999999,33.817647],"type":"Point"}
}