{
  "type": "Feature",
  "properties": {
    "iso:country":"US",
    "sg:address":"4345 Commerce Dr SW",
    "sg:city":"Atlanta",
    "sg:classifiers":[
        {
            "category":"Wholesale",
            "subcategory":"Chemicals & Plastics",
            "type":"Manufacturing & Wholesale Goods"
        }
    ],
    "sg:phone":"+1 404 691 1721",
    "sg:postcode":"30336",
    "sg:province":"GA",
    "wof:name":"Peach State Plastics Inc",
    "wof:placetype":"venue"
},
  "geometry": {"coordinates":[-84.531588,33.76345],"type":"Point"}
}