{
  "type": "Feature",
  "properties": {
    "addr:full":"1049 Stevens Creek Rd Augusta GA 30907",
    "addr:housenumber":"1049",
    "addr:postcode":"30907",
    "addr:street":"Stevens Creek Rd",
    "iso:country":"US",
    "sg:address":"1049 Stevens Creek Rd",
    "sg:city":"Augusta",
    "sg:phone":"+1 706 738 3131",
    "sg:postcode":"30907",
    "sg:province":"GA",
    "sg:website":"http://www.homewood-suites.com",
    "wof:name":"Homewood Suites",
    "wof:placetype":"venue"
},
  "geometry": {"coordinates":[-82.042158,33.51434],"type":"Point"}
}