{
  "type": "Feature",
  "properties": {
    "addr:full":"1418 Dresden Dr NE Atlanta GA 30319",
    "addr:housenumber":"1418",
    "addr:postcode":"30319",
    "addr:street":"Dresden Dr Ne",
    "iso:country":"US",
    "sg:address":"1418 Dresden Dr NE",
    "sg:city":"Atlanta",
    "sg:classifiers":[
        {
            "category":"Professional",
            "subcategory":"Lawyer & Legal Services",
            "type":"Services"
        }
    ],
    "sg:phone":"+1 404 816 9724",
    "sg:postcode":"30319",
    "sg:province":"GA",
    "wof:name":"Thomaslaw Group Llc",
    "wof:placetype":"venue"
},
  "geometry": {"coordinates":[-84.331041,33.86094],"type":"Point"}
}