{
  "type": "Feature",
  "properties": {
    "addr:full":"77 Peachtree Street SW Atlanta GA 30303",
    "addr:housenumber":"77",
    "addr:postcode":"30303",
    "addr:street":"Peachtree Street Sw",
    "iso:country":"US",
    "sg:address":"77 Peachtree Street SW",
    "sg:city":"Atlanta",
    "sg:classifiers":[
        {
            "category":"Shopping",
            "subcategory":"Bicycles & Sporting Goods",
            "type":"Retail Goods"
        }
    ],
    "sg:phone":"+1 404 659 4126",
    "sg:postcode":"30303",
    "sg:province":"GA",
    "wof:name":"Sports City",
    "wof:placetype":"venue"
},
  "geometry": {"coordinates":[-84.391773,33.752207],"type":"Point"}
}