{
  "type": "Feature",
  "properties": {
    "addr:full":"312 Inman Rd Fayetteville GA 30215",
    "addr:housenumber":"312",
    "addr:postcode":"30215",
    "addr:street":"Inman Rd",
    "iso:country":"US",
    "sg:address":"312 Inman Rd",
    "sg:city":"Fayetteville",
    "sg:classifiers":[
        {
            "category":"Building & Trades",
            "subcategory":"Construction",
            "type":"Services"
        }
    ],
    "sg:phone":"+1 770 461 7979",
    "sg:postcode":"30215",
    "sg:province":"GA",
    "sg:tags":[
        "contractor"
    ],
    "wof:name":"Paul Betsill",
    "wof:placetype":"venue"
},
  "geometry": {"coordinates":[-84.40946700000001,33.411801],"type":"Point"}
}