{
  "type": "Feature",
  "properties": {
    "iso:country":"US",
    "sg:address":"1633 Waldrop Rd",
    "sg:city":"Lawrenceville",
    "sg:classifiers":[
        {
            "category":"Professional",
            "subcategory":"Management & Consulting",
            "type":"Services"
        },
        {
            "category":"Professional",
            "subcategory":"Engineering",
            "type":"Services"
        }
    ],
    "sg:phone":"+1 770 962 4417",
    "sg:postcode":"30043",
    "sg:province":"GA",
    "sg:tags":[
        "environmental",
        "ecological",
        "engineer",
        "consultant"
    ],
    "wof:name":"Environmental Consulting",
    "wof:placetype":"venue"
},
  "geometry": {"coordinates":[-83.973754,34.04603],"type":"Point"}
}