{
  "type": "Feature",
  "properties": {
    "iso:country":"US",
    "sg:address":"4070 Briar Cliff RD NE",
    "sg:city":"Atlanta",
    "sg:classifiers":[
        {
            "category":"Building & Trades",
            "subcategory":"Construction",
            "type":"Services"
        }
    ],
    "sg:phone":"+1 404 895 5852",
    "sg:postcode":"30345",
    "sg:province":"GA",
    "sg:tags":[
        "contractor"
    ],
    "wof:name":"Warrington Renovation, Roofing, and Repair",
    "wof:placetype":"venue"
},
  "geometry": {"coordinates":[-84.28187699999999,33.854404],"type":"Point"}
}