{
  "type": "Feature",
  "properties": {
    "addr:full":"1244 Clairemont Rd Decatur GA 30030",
    "addr:housenumber":"1244",
    "addr:postcode":"30030",
    "addr:street":"Clairemont Rd",
    "iso:country":"US",
    "sg:address":"1244 Clairemont Rd",
    "sg:city":"Decatur",
    "sg:classifiers":[
        {
            "category":"Professional",
            "subcategory":"Accounting & Tax Preparation",
            "type":"Services"
        }
    ],
    "sg:phone":"+1 404 320 7989",
    "sg:postcode":"30030",
    "sg:province":"GA",
    "wof:name":"Victor S Notrica",
    "wof:placetype":"venue"
},
  "geometry": {"coordinates":[-84.306749,33.789296],"type":"Point"}
}