{
  "type": "Feature",
  "properties": {
    "addr:full":"214 2nd St Bonaire GA 31005",
    "addr:housenumber":"214",
    "addr:postcode":"31005",
    "addr:street":"2Nd St",
    "iso:country":"US",
    "sg:address":"214 2nd St",
    "sg:city":"Bonaire",
    "sg:classifiers":[
        {
            "category":"Social Services",
            "type":"Services"
        },
        {
            "category":"Shopping",
            "subcategory":"Used Merchandise",
            "type":"Retail Goods"
        },
        {
            "category":"Banks & Credit Unions",
            "subcategory":"Bank",
            "type":"Services"
        },
        {
            "category":"Shopping",
            "subcategory":"Thrift Store",
            "type":"Retail Goods"
        },
        {
            "category":"Organizations",
            "subcategory":"Non-profit Organization",
            "type":"Services"
        }
    ],
    "sg:phone":"+1 478 923 8272",
    "sg:postcode":"31005",
    "sg:province":"GA",
    "sg:tags":[
        "shop",
        "foundations-educational",
        "philanthropic",
        "research",
        "resale",
        "second",
        "hand",
        "furniture",
        "charity"
    ],
    "sg:website":"http://www.goodwill.org",
    "wof:name":"Goodwill Stores",
    "wof:placetype":"venue"
},
  "geometry": {"coordinates":[-83.608362,32.544928],"type":"Point"}
}