{
  "type": "Feature",
  "properties": {
    "iso:country":"US",
    "sg:address":"6061 Oakbrook Pkwy",
    "sg:city":"Norcross",
    "sg:classifiers":[
        {
            "category":"Manufacturing",
            "subcategory":"Printing",
            "type":"Manufacturing & Wholesale Goods"
        }
    ],
    "sg:phone":"+1 770 449 1919",
    "sg:postcode":"30093",
    "sg:province":"GA",
    "sg:tags":[
        "newspaper"
    ],
    "sg:website":"www.lavozdelpueblo.com",
    "wof:name":"Lavoz Del Pueblo",
    "wof:placetype":"venue"
},
  "geometry": {"coordinates":[-84.20437800000001,33.911508],"type":"Point"}
}