{
  "type": "Feature",
  "properties": {
    "addr:full":"6252 Susan Ln Atlanta GA 30340",
    "addr:housenumber":"6252",
    "addr:postcode":"30340",
    "addr:street":"Susan Ln",
    "iso:country":"US",
    "sg:address":"6252 Susan Ln",
    "sg:city":"Atlanta",
    "sg:classifiers":[
        {
            "category":"Building & Trades",
            "subcategory":"Construction",
            "type":"Services"
        }
    ],
    "sg:phone":"+1 770 840 7991",
    "sg:postcode":"30340",
    "sg:province":"GA",
    "sg:tags":[
        "dry wall",
        "contractor"
    ],
    "wof:name":"Peralta's Drywall Construction",
    "wof:placetype":"venue"
},
  "geometry": {"coordinates":[-84.24190299999999,33.926345],"type":"Point"}
}