{
  "type": "Feature",
  "properties": {
    "addr:full":"2921 Airport Throughway Columbus GA 31909",
    "addr:housenumber":"2921",
    "addr:postcode":"31909",
    "addr:street":"Airport Throughway",
    "iso:country":"US",
    "sg:address":"2921 Airport Throughway",
    "sg:city":"Columbus",
    "sg:classifiers":[
        {
            "category":"Banks & Credit Unions",
            "subcategory":"Bank",
            "type":"Services"
        }
    ],
    "sg:phone":"+1 706 571 7993",
    "sg:postcode":"31909",
    "sg:province":"GA",
    "sg:tags":[
        "state"
    ],
    "wof:name":"South Trust Bank",
    "wof:placetype":"venue"
},
  "geometry": {"coordinates":[-84.947366,32.520851],"type":"Point"}
}