{
  "type": "Feature",
  "properties": {
    "iso:country":"US",
    "sg:address":"340 Roscoe Rd",
    "sg:city":"Newnan",
    "sg:classifiers":[
        {
            "category":"Professional",
            "subcategory":"Business Services",
            "type":"Services"
        }
    ],
    "sg:phone":"+1 770 253 0282",
    "sg:postcode":"30263",
    "sg:province":"GA",
    "wof:name":"Collins & Wood",
    "wof:placetype":"venue"
},
  "geometry": {"coordinates":[-84.81078100000001,33.405671],"type":"Point"}
}