{
  "type": "Feature",
  "properties": {
    "iso:country":"US",
    "sg:address":"1083 Forest East Dr",
    "sg:city":"Stone Mountain",
    "sg:classifiers":[
        {
            "category":"Retail",
            "subcategory":"Laundry & Dry Cleaning",
            "type":"Services"
        }
    ],
    "sg:phone":"+1 404 421 6064",
    "sg:postcode":"30088",
    "sg:province":"GA",
    "wof:name":"Sam Carpet Cleaning",
    "wof:placetype":"venue"
},
  "geometry": {"coordinates":[-84.16715499999999,33.762839],"type":"Point"}
}