{
  "type": "Feature",
  "properties": {
    "addr:full":"3225 Shallowford Rd Marietta GA 30062",
    "addr:housenumber":"3225",
    "addr:postcode":"30062",
    "addr:street":"Shallowford Rd",
    "iso:country":"US",
    "sg:address":"3225 Shallowford Rd",
    "sg:city":"Marietta",
    "sg:classifiers":[
        {
            "category":"Manufacturing",
            "subcategory":"Signs",
            "type":"Manufacturing & Wholesale Goods"
        }
    ],
    "sg:phone":"+1 770 977 4416",
    "sg:postcode":"30062",
    "sg:province":"GA",
    "sg:tags":[
        "advertising",
        "specialty"
    ],
    "wof:name":"Priority Sign Inc",
    "wof:placetype":"venue"
},
  "geometry": {"coordinates":[-84.452022,34.037372],"type":"Point"}
}