{
  "type": "Feature",
  "properties": {
    "iso:country":"US",
    "sg:address":"27 Hudson Rd",
    "sg:city":"Fayetteville",
    "sg:classifiers":[
        {
            "category":"Shopping",
            "subcategory":"Hobbies, Toys, & Games",
            "type":"Retail Goods"
        }
    ],
    "sg:phone":"+1 706 461 6300",
    "sg:postcode":"30240",
    "sg:province":"GA",
    "sg:tags":[
        "arts",
        "craft",
        "specialty"
    ],
    "wof:name":"Michaels 9564",
    "wof:placetype":"venue"
},
  "geometry": {"coordinates":[-85.115454,32.994811],"type":"Point"}
}