{
  "type": "Feature",
  "properties": {
    "iso:country":"US",
    "sg:address":"311 Park Leaf",
    "sg:city":"Peachtree City",
    "sg:classifiers":[
        {
            "category":"Manufacturing",
            "subcategory":"Electronics",
            "type":"Manufacturing & Wholesale Goods"
        }
    ],
    "sg:phone":"+1 770 486 9930",
    "sg:postcode":"30269",
    "sg:province":"GA",
    "sg:tags":[
        "equipment",
        "mfg",
        "communications"
    ],
    "wof:name":"Digital Monitoring Produc",
    "wof:placetype":"venue"
},
  "geometry": {"coordinates":[-84.56556,33.386563],"type":"Point"}
}