{
  "type": "Feature",
  "properties": {
    "iso:country":"US",
    "sg:address":"1017 Stevens Creek Rd",
    "sg:city":"Augusta",
    "sg:classifiers":[
        {
            "category":"Professional",
            "type":"Services"
        }
    ],
    "sg:phone":"+1 706 860 4444",
    "sg:postcode":"30907",
    "sg:province":"GA",
    "wof:name":"In A Seasons Basket",
    "wof:placetype":"venue"
},
  "geometry": {"coordinates":[-82.045354,33.520646],"type":"Point"}
}