{
  "type": "Feature",
  "properties": {
    "iso:country":"US",
    "sg:address":"400 Holt Ave",
    "sg:city":"Macon",
    "sg:classifiers":[
        {
            "category":"Wholesale",
            "subcategory":"Electrical",
            "type":"Manufacturing & Wholesale Goods"
        }
    ],
    "sg:phone":"+1 478 746 4341",
    "sg:postcode":"31204",
    "sg:province":"GA",
    "sg:tags":[
        "supply"
    ],
    "wof:name":"Macon Electric Div 002e",
    "wof:placetype":"venue"
},
  "geometry": {"coordinates":[-83.651951,32.839543],"type":"Point"}
}