{
  "type": "Feature",
  "properties": {
    "addr:full":"3106 Wrightsboro Rd Augusta GA 30909",
    "addr:housenumber":"3106",
    "addr:postcode":"30909",
    "addr:street":"Wrightsboro Rd",
    "iso:country":"US",
    "sg:address":"3106 Wrightsboro Rd",
    "sg:city":"Augusta",
    "sg:classifiers":[
        {
            "category":"Professional",
            "type":"Services"
        },
        {
            "category":"Education",
            "subcategory":"Special Training",
            "type":"Public Place"
        }
    ],
    "sg:phone":"+1 706 738 4357",
    "sg:postcode":"30909",
    "sg:province":"GA",
    "sg:tags":[
        "instruction",
        "driving"
    ],
    "wof:name":"Accurate Certified Evaluations",
    "wof:placetype":"venue"
},
  "geometry": {"coordinates":[-82.051033,33.470173],"type":"Point"}
}