{
  "type": "Feature",
  "properties": {
    "addr:full":"819 Russ Rumsey Rd Maysville GA 30558",
    "addr:housenumber":"819",
    "addr:postcode":"30558",
    "addr:street":"Russ Rumsey Rd",
    "iso:country":"US",
    "sg:address":"819 Russ Rumsey Rd",
    "sg:city":"Maysville",
    "sg:classifiers":[
        {
            "category":"Personal",
            "subcategory":"Beauty Salon",
            "type":"Services"
        }
    ],
    "sg:phone":"+1 706 677 7493",
    "sg:postcode":"30558",
    "sg:province":"GA",
    "wof:name":"Kts Kuts & Kurls",
    "wof:placetype":"venue"
},
  "geometry": {"coordinates":[-83.538434,34.341755],"type":"Point"}
}