{
  "type": "Feature",
  "properties": {
    "iso:country":"US",
    "sg:address":"1211 Ridgeway Rd",
    "sg:city":"Bogart",
    "sg:classifiers":[
        {
            "category":"Coffee & Tea",
            "type":"Food & Drink"
        },
        {
            "category":"Food & Beverages",
            "subcategory":"Liquor & Beverages",
            "type":"Retail Goods"
        },
        {
            "category":"Manufacturing",
            "subcategory":"Food",
            "type":"Manufacturing & Wholesale Goods"
        }
    ],
    "sg:phone":"+1 706 769 1996",
    "sg:postcode":"30622",
    "sg:province":"GA",
    "sg:tags":[
        "tea-wholesale",
        "manufacturer"
    ],
    "wof:name":"Grancoffee",
    "wof:placetype":"venue"
},
  "geometry": {"coordinates":[-83.55972300000001,33.865144],"type":"Point"}
}