{
  "type": "Feature",
  "properties": {
    "iso:country":"US",
    "sg:address":"171 Star Lndg",
    "sg:city":"Forsyth",
    "sg:classifiers":[
        {
            "category":"Real Estate",
            "subcategory":"Real Estate Operator",
            "type":"Services"
        }
    ],
    "sg:phone":"+1 478 994 2005",
    "sg:postcode":"31029",
    "sg:province":"GA",
    "sg:tags":[
        "mobile",
        "home",
        "site"
    ],
    "wof:name":"Creekside M H P",
    "wof:placetype":"venue"
},
  "geometry": {"coordinates":[-83.88169499999999,33.050016],"type":"Point"}
}