{
  "type": "Feature",
  "properties": {
    "iso:country":"US",
    "sg:address":"3915 Jiles Way",
    "sg:city":"Kennesaw",
    "sg:classifiers":[
        {
            "category":"Retail",
            "subcategory":"Car Wash",
            "type":"Services"
        }
    ],
    "sg:phone":"+1 770 218 7110",
    "sg:postcode":"30144",
    "sg:province":"GA",
    "sg:tags":[
        "polishing",
        "carwash",
        "washing"
    ],
    "wof:name":"Chalmers Four Seasons Car Wash",
    "wof:placetype":"venue"
},
  "geometry": {"coordinates":[-84.613193,34.0506],"type":"Point"}
}