{
  "type": "Feature",
  "properties": {
    "iso:country":"US",
    "sg:address":"401 16th Street NW Unit 1269",
    "sg:city":"Atlanta",
    "sg:classifiers":[
        {
            "category":"Professional",
            "subcategory":"Employment Agencies",
            "type":"Services"
        }
    ],
    "sg:phone":"+1 404 892 6620",
    "sg:postcode":"30363",
    "sg:province":"GA",
    "wof:name":"Aks",
    "wof:placetype":"venue"
},
  "geometry": {"coordinates":[-84.39117400000001,33.648571],"type":"Point"}
}