{
  "type": "Feature",
  "properties": {
    "addr:full":"1622 Madison Ave Tifton GA 31794",
    "addr:housenumber":"1622",
    "addr:postcode":"31794",
    "addr:street":"Madison Ave",
    "iso:country":"US",
    "sg:address":"1622 Madison Ave",
    "sg:city":"Tifton",
    "sg:classifiers":[
        {
            "category":"Health Services",
            "subcategory":"Doctor",
            "type":"Services"
        }
    ],
    "sg:phone":"+1 229 386 0888",
    "sg:postcode":"31794",
    "sg:province":"GA",
    "sg:tags":[
        "clinic"
    ],
    "wof:name":"Tifton Orthopedic Clinic",
    "wof:placetype":"venue"
},
  "geometry": {"coordinates":[-83.48971400000001,31.468356],"type":"Point"}
}