{
  "type": "Feature",
  "properties": {
    "addr:full":"663 Hickory Dr Marietta GA 30064",
    "addr:housenumber":"663",
    "addr:postcode":"30064",
    "addr:street":"Hickory Dr",
    "iso:country":"US",
    "sg:address":"663 Hickory Dr",
    "sg:city":"Marietta",
    "sg:classifiers":[
        {
            "category":"Professional",
            "type":"Services"
        }
    ],
    "sg:phone":"+1 770 422 3415",
    "sg:postcode":"30064",
    "sg:province":"GA",
    "wof:name":"Stephen Stanley",
    "wof:placetype":"venue"
},
  "geometry": {"coordinates":[-84.5668,33.93754],"type":"Point"}
}