{
  "type": "Feature",
  "properties": {
    "iso:country":"US",
    "sg:address":"2100 2nd Ave",
    "sg:city":"Columbus",
    "sg:classifiers":[
        {
            "category":"Home & Garden",
            "subcategory":"Building Materials",
            "type":"Retail Goods"
        }
    ],
    "sg:phone":"+1 706 322 7792",
    "sg:postcode":"31901",
    "sg:province":"GA",
    "sg:tags":[
        "glass",
        "window",
        "plate"
    ],
    "wof:name":"Stephens Auto Glass & Paint",
    "wof:placetype":"venue"
},
  "geometry": {"coordinates":[-84.99014099999999,32.484749],"type":"Point"}
}