{
  "type": "Feature",
  "properties": {
    "addr:full":"878 Wild Turkey Trl Monroe GA 30655",
    "addr:housenumber":"878",
    "addr:postcode":"30655",
    "addr:street":"Wild Turkey Trl",
    "iso:country":"US",
    "sg:address":"878 Wild Turkey Trl",
    "sg:city":"Monroe",
    "sg:classifiers":[
        {
            "category":"Shopping",
            "subcategory":"Used Merchandise",
            "type":"Retail Goods"
        }
    ],
    "sg:phone":"+1 770 267 4208",
    "sg:postcode":"30655",
    "sg:province":"GA",
    "wof:name":"Primitive Touch Inc",
    "wof:placetype":"venue"
},
  "geometry": {"coordinates":[-83.676266,33.776203],"type":"Point"}
}