{
  "type": "Feature",
  "properties": {
    "addr:full":"6783 Veterans Pkwy Columbus GA 31909",
    "addr:housenumber":"6783",
    "addr:postcode":"31909",
    "addr:street":"Veterans Pkwy",
    "iso:country":"US",
    "sg:address":"6783 Veterans Pkwy",
    "sg:city":"Columbus",
    "sg:classifiers":[
        {
            "category":"Coffee & Tea",
            "type":"Food & Drink"
        }
    ],
    "sg:menulink":"http://www.allmenus.com/ga/columbus/107984-starbucks-coffee/menu/",
    "sg:phone":"+1 706 653 5520",
    "sg:postcode":"31909",
    "sg:province":"GA",
    "sg:tags":[
        "american"
    ],
    "wof:name":"Starbucks Coffee",
    "wof:placetype":"venue"
},
  "geometry": {"coordinates":[-84.94942,32.551262],"type":"Point"}
}