{
  "type": "Feature",
  "properties": {
    "iso:country":"US",
    "sg:address":"3200 Candace Dr SE",
    "sg:city":"Atlanta",
    "sg:classifiers":[
        {
            "category":"Transit Center",
            "subcategory":"Freight",
            "type":"Transportation"
        },
        {
            "category":"Freight",
            "type":"Transportation"
        }
    ],
    "sg:phone":"+1 404 241 2138",
    "sg:postcode":"30316",
    "sg:province":"GA",
    "sg:tags":[
        "local",
        "trucking-motor",
        "trucking"
    ],
    "wof:name":"Wyatt & Son Trucking Inc",
    "wof:placetype":"venue"
},
  "geometry": {"coordinates":[-84.306783,33.691571],"type":"Point"}
}