{
  "type": "Feature",
  "properties": {
    "addr:full":"6128 Prestley Mill Rd Douglasville GA 30134",
    "addr:housenumber":"6128",
    "addr:postcode":"30134",
    "addr:street":"Prestley Mill Rd",
    "iso:country":"US",
    "sg:address":"6128 Prestley Mill Rd",
    "sg:city":"Douglasville",
    "sg:classifiers":[
        {
            "category":"Health Services",
            "subcategory":"Doctor",
            "type":"Services"
        }
    ],
    "sg:phone":"+1 770 949 0434",
    "sg:postcode":"30134",
    "sg:province":"GA",
    "sg:tags":[
        "dentist"
    ],
    "wof:name":"Jigisha K Patel & Assoc",
    "wof:placetype":"venue"
},
  "geometry": {"coordinates":[-84.730907,33.737736],"type":"Point"}
}