{
  "type": "Feature",
  "properties": {
    "addr:full":"132 Cotton Dr Ocilla GA 31774",
    "addr:housenumber":"132",
    "addr:postcode":"31774",
    "addr:street":"Cotton Dr Ocilla",
    "iso:country":"US",
    "sg:address":"132 Cotton Dr",
    "sg:city":"Ocilla",
    "sg:classifiers":[
        {
            "category":"Professional",
            "subcategory":"Engineering",
            "type":"Services"
        }
    ],
    "sg:phone":"+1 229 468 4120",
    "sg:postcode":"31774",
    "sg:province":"GA",
    "sg:tags":[
        "consulting",
        "engineer"
    ],
    "sg:website":"http://www.irwincdc.com",
    "wof:name":"Croft Michael Enterprises Inc",
    "wof:placetype":"venue"
},
  "geometry": {"coordinates":[-83.25444299999999,31.580884],"type":"Point"}
}