{
  "type": "Feature",
  "properties": {
    "iso:country":"US",
    "sg:address":"1312 W Taylor St",
    "sg:city":"Griffin",
    "sg:classifiers":[
        {
            "category":"Communications",
            "subcategory":"Film & Video Production",
            "type":"Services"
        }
    ],
    "sg:phone":"+1 770 233 6234",
    "sg:postcode":"30223",
    "sg:province":"GA",
    "sg:tags":[
        "motion"
    ],
    "wof:name":"Video Warehouse",
    "wof:placetype":"venue"
},
  "geometry": {"coordinates":[-84.284387,33.247308],"type":"Point"}
}