{
  "type": "Feature",
  "properties": {
    "addr:full":"2593 Mural Drive Chamblee GA 30341",
    "addr:housenumber":"2593",
    "addr:postcode":"30341",
    "addr:street":"Mural Drive",
    "iso:country":"US",
    "sg:address":"2593 Mural Drive",
    "sg:city":"Chamblee",
    "sg:classifiers":[
        {
            "category":"Retail",
            "subcategory":"Repair Shop",
            "type":"Services"
        },
        {
            "category":"Professional",
            "subcategory":"Computer Services",
            "type":"Services"
        }
    ],
    "sg:phone":"+1 404 324 0728",
    "sg:postcode":"30341",
    "sg:province":"GA",
    "sg:tags":[
        "electronics"
    ],
    "sg:website":"www.nobsconsulting.com",
    "wof:name":"BSConsulting Technology Associates",
    "wof:placetype":"venue"
},
  "geometry": {"coordinates":[-84.298177,33.896392],"type":"Point"}
}