{
  "type": "Feature",
  "properties": {
    "addr:full":"3548 Habersham at Northlake Rd Tucker GA 30084",
    "addr:housenumber":"3548",
    "addr:postcode":"30084",
    "addr:street":"Northlake Rd",
    "iso:country":"US",
    "sg:address":"3548 Habersham at Northlake Rd",
    "sg:city":"Tucker",
    "sg:classifiers":[
        {
            "category":"Social Services",
            "type":"Services"
        }
    ],
    "sg:phone":"+1 678 860 3621",
    "sg:postcode":"30084",
    "sg:province":"GA",
    "sg:tags":[
        "business"
    ],
    "wof:name":"Attachment & Bonding Center",
    "wof:placetype":"venue"
},
  "geometry": {"coordinates":[-84.243814,33.853625],"type":"Point"}
}