{
  "type": "Feature",
  "properties": {
    "addr:full":"2005 Lawrenceville Suwanee Rd Suwanee GA 30024",
    "addr:housenumber":"2005",
    "addr:postcode":"30024",
    "addr:street":"Lawrenceville Suwanee Rd",
    "iso:country":"US",
    "sg:address":"2005 Lawrenceville Suwanee Rd",
    "sg:city":"Suwanee",
    "sg:classifiers":[
        {
            "category":"Shopping",
            "subcategory":"Clothing, Apparel, & Fashions",
            "type":"Retail Goods"
        }
    ],
    "sg:phone":"+1 770 995 2760",
    "sg:postcode":"30024",
    "sg:province":"GA",
    "sg:tags":[
        "tailor",
        "alterations-clothing"
    ],
    "wof:name":"40 Years Tailor & Alteration",
    "wof:placetype":"venue"
},
  "geometry": {"coordinates":[-84.03737099999999,33.999184],"type":"Point"}
}