{
  "type": "Feature",
  "properties": {
    "iso:country":"US",
    "sg:address":"3481 Kenland Rd",
    "sg:city":"Smyrna",
    "sg:classifiers":[
        {
            "category":"Professional",
            "subcategory":"Business Services",
            "type":"Services"
        }
    ],
    "sg:phone":"+1 770 432 1278",
    "sg:postcode":"30082",
    "sg:province":"GA",
    "wof:name":"Atlanta Residential Inspection",
    "wof:placetype":"venue"
},
  "geometry": {"coordinates":[-84.541696,33.869236],"type":"Point"}
}