{
  "type": "Feature",
  "properties": {
    "iso:country":"US",
    "sg:address":"817 Riverview Dr",
    "sg:city":"Brunswick",
    "sg:classifiers":[
        {
            "category":"Organizations",
            "subcategory":"Religious Organization",
            "type":"Services"
        }
    ],
    "sg:phone":"+1 912 635 2780",
    "sg:postcode":"31527",
    "sg:province":"GA",
    "wof:name":"Parsonage Jekyll Baptist",
    "wof:placetype":"venue"
},
  "geometry": {"coordinates":[-81.41944599999999,31.089867],"type":"Point"}
}