{
  "type": "Feature",
  "properties": {
    "addr:full":"805 Glynn St S Ste 137 Fayetteville GA 30214",
    "addr:housenumber":"805",
    "addr:postcode":"30214",
    "addr:street":"Glynn St S Ste 137",
    "iso:country":"US",
    "sg:address":"805 Glynn St S Ste 137",
    "sg:city":"Fayetteville",
    "sg:classifiers":[
        {
            "category":"Personal",
            "subcategory":"Nail Salon",
            "type":"Services"
        }
    ],
    "sg:phone":"+1 770 716 1997",
    "sg:postcode":"30214",
    "sg:province":"GA",
    "wof:name":"V Nails",
    "wof:placetype":"venue"
},
  "geometry": {"coordinates":[-84.456902,33.4338],"type":"Point"}
}