{
  "type": "Feature",
  "properties": {
    "iso:country":"US",
    "sg:address":"7185 Chappell Cir NW",
    "sg:city":"Atlanta",
    "sg:classifiers":[
        {
            "category":"Building & Trades",
            "subcategory":"Construction",
            "type":"Services"
        }
    ],
    "sg:phone":"+1 404 391 2423",
    "sg:postcode":"30360",
    "sg:province":"GA",
    "sg:tags":[
        "industrial"
    ],
    "wof:name":"MRC Industrial Contractors",
    "wof:placetype":"venue"
},
  "geometry": {"coordinates":[-84.26091099999999,33.937194],"type":"Point"}
}