{
  "type": "Feature",
  "properties": {
    "addr:full":"4932 Wedgewood Pl Stone Mountain GA 30088",
    "addr:housenumber":"4932",
    "addr:postcode":"30088",
    "addr:street":"Wedgewood Pl",
    "iso:country":"US",
    "sg:address":"4932 Wedgewood Pl",
    "sg:city":"Stone Mountain",
    "sg:classifiers":[
        {
            "category":"Professional",
            "type":"Services"
        }
    ],
    "sg:phone":"+1 770 808 6351",
    "sg:postcode":"30088",
    "sg:province":"GA",
    "wof:name":"Community Resurgent Dev Corp",
    "wof:placetype":"venue"
},
  "geometry": {"coordinates":[-84.18553900000001,33.739484],"type":"Point"}
}