{
  "type": "Feature",
  "properties": {
    "addr:full":"5740 Austell Powder Springs Rd Austell GA 30106",
    "addr:housenumber":"5740",
    "addr:postcode":"30106",
    "addr:street":"Austell Powder Springs Rd",
    "iso:country":"US",
    "sg:address":"5740 Austell Powder Springs Rd",
    "sg:city":"Austell",
    "sg:classifiers":[
        {
            "category":"Professional",
            "subcategory":"Management & Consulting",
            "type":"Services"
        },
        {
            "category":"Professional",
            "subcategory":"Employment Agencies",
            "type":"Services"
        }
    ],
    "sg:phone":"+1 770 944 6696",
    "sg:postcode":"30106",
    "sg:province":"GA",
    "sg:tags":[
        "personnel",
        "consultant"
    ],
    "wof:name":"First Staffing Employment",
    "wof:placetype":"venue"
},
  "geometry": {"coordinates":[-84.635411,33.815647],"type":"Point"}
}