{
  "type": "Feature",
  "properties": {
    "addr:full":"19 W Railroad St Reynolds GA 31076",
    "addr:housenumber":"19",
    "addr:postcode":"31076",
    "addr:street":"W Railroad St",
    "iso:country":"US",
    "sg:address":"19 W Railroad St",
    "sg:city":"Reynolds",
    "sg:classifiers":[
        {
            "category":"Manufacturing",
            "subcategory":"Textiles",
            "type":"Manufacturing & Wholesale Goods"
        }
    ],
    "sg:phone":"+1 478 847 2741",
    "sg:postcode":"31076",
    "sg:province":"GA",
    "sg:tags":[
        "broker",
        "cotton"
    ],
    "wof:name":"Shaw Cotton Co",
    "wof:placetype":"venue"
},
  "geometry": {"coordinates":[-84.096031,32.560713],"type":"Point"}
}