{
  "type": "Feature",
  "properties": {
    "addr:full":"1971 S Cobb Dr Marietta GA 30060",
    "addr:housenumber":"1971",
    "addr:postcode":"30060",
    "addr:street":"S Cobb Dr",
    "iso:country":"US",
    "sg:address":"1971 S Cobb Dr",
    "sg:city":"Marietta",
    "sg:classifiers":[
        {
            "category":"Banks & Credit Unions",
            "subcategory":"Bank",
            "type":"Services"
        }
    ],
    "sg:phone":"+1 770 435 1200",
    "sg:postcode":"30060",
    "sg:province":"GA",
    "sg:tags":[
        "consumer",
        "finance"
    ],
    "wof:name":"Associates Financial",
    "wof:placetype":"venue"
},
  "geometry": {"coordinates":[-84.542992,33.906702],"type":"Point"}
}