{
  "type": "Feature",
  "properties": {
    "iso:country":"US",
    "sg:address":"8811 Channing Dr",
    "sg:city":"Jonesboro",
    "sg:classifiers":[
        {
            "category":"Building & Trades",
            "subcategory":"Cleaning & Sanitation",
            "type":"Services"
        }
    ],
    "sg:phone":"+1 770 315 4426",
    "sg:postcode":"30238",
    "sg:province":"GA",
    "sg:tags":[
        "maintenance"
    ],
    "wof:name":"B & R Maintenance",
    "wof:placetype":"venue"
},
  "geometry": {"coordinates":[-84.390535,33.515511],"type":"Point"}
}