{
  "type": "Feature",
  "properties": {
    "addr:full":"3724 Atlanta Hwy Bogart GA 30606",
    "addr:housenumber":"3724",
    "addr:postcode":"30606",
    "addr:street":"Atlanta Hwy Bogart",
    "iso:country":"US",
    "sg:address":"3724 Atlanta Hwy",
    "sg:city":"Bogart",
    "sg:classifiers":[
        {
            "category":"Professional",
            "type":"Services"
        }
    ],
    "sg:phone":"+1 770 725 1750",
    "sg:postcode":"30606",
    "sg:province":"GA",
    "sg:tags":[
        "establishment"
    ],
    "wof:name":"Solo Corp",
    "wof:placetype":"venue"
},
  "geometry": {"coordinates":[-83.46527399999999,33.940751],"type":"Point"}
}