{
  "type": "Feature",
  "properties": {
    "addr:full":"328 N Main St Cedartown GA 30125",
    "addr:housenumber":"328",
    "addr:postcode":"30125",
    "addr:street":"N Main St",
    "iso:country":"US",
    "sg:address":"328 N Main St",
    "sg:city":"Cedartown",
    "sg:classifiers":[
        {
            "category":"Restaurant",
            "type":"Food & Drink"
        }
    ],
    "sg:menulink":"http://www.allmenus.com/ga/cedartown/203216-mcdonalds/menu/",
    "sg:postcode":"30125",
    "sg:province":"GA",
    "sg:tags":[
        "burger",
        "american"
    ],
    "wof:name":"McDonald's",
    "wof:placetype":"venue"
},
  "geometry": {"coordinates":[-85.253614,34.017911],"type":"Point"}
}