{
  "type": "Feature",
  "properties": {
    "addr:full":"2100 George Brown Rd Franklin GA 30217",
    "addr:housenumber":"2100",
    "addr:postcode":"30217",
    "addr:street":"George Brown Rd",
    "iso:country":"US",
    "sg:address":"2100 George Brown Rd",
    "sg:city":"Franklin",
    "sg:classifiers":[
        {
            "category":"Building & Trades",
            "subcategory":"Electrical",
            "type":"Services"
        }
    ],
    "sg:phone":"+1 770 251 8242",
    "sg:postcode":"30217",
    "sg:province":"GA",
    "sg:tags":[
        "electrical",
        "contractor"
    ],
    "wof:name":"GE",
    "wof:placetype":"venue"
},
  "geometry": {"coordinates":[-84.99949599999999,33.355773],"type":"Point"}
}