{
  "type": "Feature",
  "properties": {
    "addr:full":"665 Thornton Way Austell GA 30168",
    "addr:housenumber":"665",
    "addr:postcode":"30168",
    "addr:street":"Thornton Way",
    "iso:country":"US",
    "sg:address":"665 Thornton Way",
    "sg:city":"Austell",
    "sg:classifiers":[
        {
            "category":"Health Services",
            "subcategory":"Doctor",
            "type":"Services"
        }
    ],
    "sg:phone":"+1 770 739 5888",
    "sg:postcode":"30168",
    "sg:province":"GA",
    "sg:tags":[
        "medicine",
        "sport"
    ],
    "wof:name":"Progressive Sports Medcne & Physcl Thrpy of W Grga",
    "wof:placetype":"venue"
},
  "geometry": {"coordinates":[-84.595901,33.785999],"type":"Point"}
}