{
  "type": "Feature",
  "properties": {
    "addr:full":"400 Ernest W Barrett Pkwy NW Ste 220 Kennesaw GA 30144",
    "addr:housenumber":"400",
    "addr:postcode":"30144",
    "addr:street":"Ernest W Barrett Pkwy Nw Ste 220",
    "iso:country":"US",
    "sg:address":"400 Ernest W Barrett Pkwy NW Ste 220",
    "sg:city":"Kennesaw",
    "sg:classifiers":[
        {
            "category":"Shopping",
            "subcategory":"Jewelry",
            "type":"Retail Goods"
        }
    ],
    "sg:phone":"+1 770 423 1441",
    "sg:postcode":"30144",
    "sg:province":"GA",
    "sg:tags":[
        "watch"
    ],
    "wof:name":"It's About Time",
    "wof:placetype":"venue"
},
  "geometry": {"coordinates":[-84.56139899999999,34.013988],"type":"Point"}
}