{
  "type": "Feature",
  "properties": {
    "addr:full":"284 Spruce Broxton GA 31519",
    "addr:housenumber":"284",
    "addr:postcode":"31519",
    "addr:street":"Spruce Broxton",
    "iso:country":"US",
    "sg:address":"284 Spruce",
    "sg:city":"Broxton",
    "sg:phone":"+1 912 359 2120",
    "sg:postcode":"31519",
    "sg:province":"GA",
    "sg:tags":[
        "farm",
        "tobacco"
    ],
    "wof:name":"Robert Jones",
    "wof:placetype":"venue"
},
  "geometry": {"coordinates":[-82.907754,31.662193],"type":"Point"}
}