{
  "type": "Feature",
  "properties": {
    "addr:full":"3402 Water Vistas Pkwy Lawrenceville GA 30044",
    "addr:housenumber":"3402",
    "addr:postcode":"30044",
    "addr:street":"Water Vistas Pkwy",
    "iso:country":"US",
    "sg:address":"3402 Water Vistas Pkwy",
    "sg:city":"Lawrenceville",
    "sg:classifiers":[
        {
            "category":"Real Estate",
            "subcategory":"Real Estate Operator",
            "type":"Services"
        }
    ],
    "sg:phone":"+1 770 923 8000",
    "sg:postcode":"30044",
    "sg:province":"GA",
    "sg:tags":[
        "apartment"
    ],
    "wof:name":"Water Vistas Apartments",
    "wof:placetype":"venue"
},
  "geometry": {"coordinates":[-84.11509700000001,33.942402],"type":"Point"}
}