{
  "type": "Feature",
  "properties": {
    "addr:full":"875 Thornton Rd Lithia Springs GA 30122",
    "addr:housenumber":"875",
    "addr:postcode":"30122",
    "addr:street":"Thornton Rd",
    "iso:country":"US",
    "sg:address":"875 Thornton Rd",
    "sg:city":"Lithia Springs",
    "sg:classifiers":[
        {
            "category":"Retail",
            "subcategory":"Veterinary Services",
            "type":"Services"
        }
    ],
    "sg:phone":"+1 770 819 1090",
    "sg:postcode":"30122",
    "sg:province":"GA",
    "sg:tags":[
        "veterinarian"
    ],
    "wof:name":"Westside Animal Emergency Clinic",
    "wof:placetype":"venue"
},
  "geometry": {"coordinates":[-84.607553,33.780153],"type":"Point"}
}