{
  "type": "Feature",
  "properties": {
    "iso:country":"US",
    "sg:address":"1770 Jeffersonville Rd",
    "sg:city":"Macon",
    "sg:classifiers":[
        {
            "category":"Restaurant",
            "type":"Food & Drink"
        }
    ],
    "sg:phone":"+1 478 742 6852",
    "sg:postcode":"31217",
    "sg:province":"GA",
    "wof:name":"Odyssey South",
    "wof:placetype":"venue"
},
  "geometry": {"coordinates":[-83.592795,32.852374],"type":"Point"}
}