{
  "type": "Feature",
  "properties": {
    "addr:full":"1145 Main St S Tifton GA 31794",
    "addr:housenumber":"1145",
    "addr:postcode":"31794",
    "addr:street":"Main St S",
    "iso:country":"US",
    "sg:address":"1145 Main St S",
    "sg:city":"Tifton",
    "sg:classifiers":[
        {
            "category":"Shopping",
            "subcategory":"Bicycles & Sporting Goods",
            "type":"Retail Goods"
        }
    ],
    "sg:phone":"+1 229 382 8979",
    "sg:postcode":"31794",
    "sg:province":"GA",
    "sg:tags":[
        "tackle",
        "bait"
    ],
    "wof:name":"Sports Center",
    "wof:placetype":"venue"
},
  "geometry": {"coordinates":[-83.506418,31.443871],"type":"Point"}
}