{
  "type": "Feature",
  "properties": {
    "addr:full":"30 E Park Sq Marietta GA 30060",
    "addr:housenumber":"30",
    "addr:postcode":"30060",
    "addr:street":"E Park Sq",
    "iso:country":"US",
    "sg:address":"30 E Park Sq",
    "sg:city":"Marietta",
    "sg:classifiers":[
        {
            "category":"Professional",
            "subcategory":"Lawyer & Legal Services",
            "type":"Services"
        }
    ],
    "sg:phone":"+1 770 421 1995",
    "sg:postcode":"30060",
    "sg:province":"GA",
    "wof:name":"Legal Online Inc",
    "wof:placetype":"venue"
},
  "geometry": {"coordinates":[-84.548902,33.95287],"type":"Point"}
}