{
  "type": "Feature",
  "properties": {
    "iso:country":"US",
    "sg:address":"165 Cassville Rd",
    "sg:city":"Cartersville",
    "sg:classifiers":[
        {
            "category":"Food & Beverages",
            "subcategory":"Groceries & Convenience Stores",
            "type":"Retail Goods"
        }
    ],
    "sg:phone":"+1 770 386 3035",
    "sg:postcode":"30120",
    "sg:province":"GA",
    "wof:name":"Cartersville Food Store",
    "wof:placetype":"venue"
},
  "geometry": {"coordinates":[-84.80939499999999,34.173785],"type":"Point"}
}