{
  "type": "Feature",
  "properties": {
    "addr:full":"340 Corder Rd Warner Robins GA 31088",
    "addr:housenumber":"340",
    "addr:postcode":"31088",
    "addr:street":"Corder Rd",
    "iso:country":"US",
    "sg:address":"340 Corder Rd",
    "sg:city":"Warner Robins",
    "sg:classifiers":[
        {
            "category":"Retail",
            "subcategory":"Laundry & Dry Cleaning",
            "type":"Services"
        }
    ],
    "sg:phone":"+1 478 328 8996",
    "sg:postcode":"31088",
    "sg:province":"GA",
    "sg:tags":[
        "drycleaning",
        "plant"
    ],
    "wof:name":"1 Alterations & Dry Cleaning",
    "wof:placetype":"venue"
},
  "geometry": {"coordinates":[-83.65207599999999,32.613432],"type":"Point"}
}