{
  "type": "Feature",
  "properties": {
    "iso:country":"US",
    "sg:address":"343 Raka Dr",
    "sg:city":"Dublin",
    "sg:classifiers":[
        {
            "category":"Home & Garden",
            "subcategory":"Furniture",
            "type":"Retail Goods"
        }
    ],
    "sg:phone":"+1 478 275 0361",
    "sg:postcode":"31027",
    "sg:province":"GA",
    "wof:name":"Jj Custom Woodworks",
    "wof:placetype":"venue"
},
  "geometry": {"coordinates":[-82.846254,32.534843],"type":"Point"}
}