{
  "type": "Feature",
  "properties": {
    "addr:full":"5535 Jimmy Carter Blvd Norcross GA 30093",
    "addr:housenumber":"5535",
    "addr:postcode":"30093",
    "addr:street":"Jimmy Carter Blvd",
    "iso:country":"US",
    "sg:address":"5535 Jimmy Carter Blvd",
    "sg:city":"Norcross",
    "sg:classifiers":[
        {
            "category":"Shopping",
            "subcategory":"Pawn Shop",
            "type":"Retail Goods"
        }
    ],
    "sg:phone":"+1 770 248 5600",
    "sg:postcode":"30093",
    "sg:province":"GA",
    "wof:name":"Easy Pay Financial",
    "wof:placetype":"venue"
},
  "geometry": {"coordinates":[-84.206461,33.909657],"type":"Point"}
}