{
  "type": "Feature",
  "properties": {
    "iso:country":"US",
    "sg:address":"108 Honeysuckle Dr",
    "sg:city":"Albany",
    "sg:classifiers":[
        {
            "category":"Professional",
            "subcategory":"Engineering",
            "type":"Services"
        }
    ],
    "sg:phone":"+1 229 436 9157",
    "sg:postcode":"31705",
    "sg:province":"GA",
    "wof:name":"Inferrera Services Inc",
    "wof:placetype":"venue"
},
  "geometry": {"coordinates":[-84.124679,31.516681],"type":"Point"}
}