{
  "type": "Feature",
  "properties": {
    "addr:full":"2545 Upper Big Springs Rd Lagrange GA 30241",
    "addr:housenumber":"2545",
    "addr:postcode":"30241",
    "addr:street":"Upper Big Springs Rd",
    "iso:country":"US",
    "sg:address":"2545 Upper Big Springs Rd",
    "sg:city":"Lagrange",
    "sg:classifiers":[
        {
            "category":"Structure",
            "subcategory":"Warehouse",
            "type":"Public Place"
        },
        {
            "category":"Retail",
            "subcategory":"Storage",
            "type":"Services"
        }
    ],
    "sg:phone":"+1 706 885 1248",
    "sg:postcode":"30241",
    "sg:province":"GA",
    "sg:tags":[
        "self",
        "warehouses-merchandise"
    ],
    "wof:name":"C'sons",
    "wof:placetype":"venue"
},
  "geometry": {"coordinates":[-84.9605,33.013323],"type":"Point"}
}