{
  "type": "Feature",
  "properties": {
    "iso:country":"US",
    "sg:address":"1805 Gleneden Ct SW",
    "sg:city":"Grayson",
    "sg:classifiers":[
        {
            "category":"Professional",
            "subcategory":"Management & Consulting",
            "type":"Services"
        }
    ],
    "sg:phone":"+1 770 979 2297",
    "sg:postcode":"30017",
    "sg:province":"GA",
    "sg:tags":[
        "consultant",
        "business"
    ],
    "wof:name":"P M Consulting Inc",
    "wof:placetype":"venue"
},
  "geometry": {"coordinates":[-83.991681,33.870178],"type":"Point"}
}