{
  "type": "Feature",
  "properties": {
    "iso:country":"US",
    "sg:address":"857 Carbondale Rd SW",
    "sg:city":"Dalton",
    "sg:classifiers":[
        {
            "category":"Retail",
            "subcategory":"Laundry & Dry Cleaning",
            "type":"Services"
        }
    ],
    "sg:phone":"+1 706 277 2003",
    "sg:postcode":"30721",
    "sg:province":"GA",
    "wof:name":"Mountain Valley Carpet Inc",
    "wof:placetype":"venue"
},
  "geometry": {"coordinates":[-84.993908,34.622341],"type":"Point"}
}