{
  "type": "Feature",
  "properties": {
    "iso:country":"US",
    "sg:address":"2709 Hamilton Rd",
    "sg:city":"La Grange",
    "sg:classifiers":[
        {
            "category":"Professional",
            "type":"Services"
        }
    ],
    "sg:phone":"+1 706 812 1676",
    "sg:postcode":"30241",
    "sg:province":"GA",
    "wof:name":"Tammy S Winkles",
    "wof:placetype":"venue"
},
  "geometry": {"coordinates":[-84.99832499999999,32.984636],"type":"Point"}
}