{
  "type": "Feature",
  "properties": {
    "iso:country":"US",
    "sg:address":"404 Church St",
    "sg:city":"Macon",
    "sg:classifiers":[
        {
            "category":"Organizations",
            "subcategory":"Religious Organization",
            "type":"Services"
        }
    ],
    "sg:phone":"+1 478 743 9072",
    "sg:postcode":"31217",
    "sg:province":"GA",
    "wof:name":"United Methodist Church",
    "wof:placetype":"venue"
},
  "geometry": {"coordinates":[-83.616218,32.844772],"type":"Point"}
}