{
  "type": "Feature",
  "properties": {
    "addr:full":"62 Indian Hills Dr Rydal GA 30171",
    "addr:housenumber":"62",
    "addr:postcode":"30171",
    "addr:street":"Indian Hills Dr",
    "iso:country":"US",
    "sg:address":"62 Indian Hills Dr",
    "sg:city":"Rydal",
    "sg:classifiers":[
        {
            "category":"Manufacturing",
            "subcategory":"Building Materials",
            "type":"Manufacturing & Wholesale Goods"
        }
    ],
    "sg:phone":"+1 770 607 8717",
    "sg:postcode":"30171",
    "sg:province":"GA",
    "sg:tags":[
        "mfg"
    ],
    "wof:name":"Woodworks",
    "wof:placetype":"venue"
},
  "geometry": {"coordinates":[-84.718255,34.306664],"type":"Point"}
}