{
  "type": "Feature",
  "properties": {
    "iso:country":"US",
    "sg:address":"6991 Flagstone Dr",
    "sg:city":"Austell",
    "sg:classifiers":[
        {
            "category":"Professional",
            "subcategory":"Computer Services",
            "type":"Services"
        }
    ],
    "sg:phone":"+1 770 948 4640",
    "sg:postcode":"30168",
    "sg:province":"GA",
    "sg:tags":[
        "related"
    ],
    "wof:name":"Techee Support",
    "wof:placetype":"venue"
},
  "geometry": {"coordinates":[-84.564243,33.777845],"type":"Point"}
}