{
  "type": "Feature",
  "properties": {
    "iso:country":"US",
    "sg:address":"507 Ocean Blvd",
    "sg:city":"St Simons Island",
    "sg:classifiers":[
        {
            "category":"Building & Trades",
            "subcategory":"Construction",
            "type":"Services"
        }
    ],
    "sg:phone":"+1 912 638 6353",
    "sg:postcode":"31522",
    "sg:province":"GA",
    "sg:tags":[
        "general",
        "contractor"
    ],
    "wof:name":"Coastal Design Build",
    "wof:placetype":"venue"
},
  "geometry": {"coordinates":[-81.39496800000001,31.136804],"type":"Point"}
}