{
  "type": "Feature",
  "properties": {
    "iso:country":"US",
    "sg:address":"2885 Preston Dr",
    "sg:city":"Rex",
    "sg:classifiers":[
        {
            "category":"Manufacturing",
            "subcategory":"Chemicals & Compounds",
            "type":"Manufacturing & Wholesale Goods"
        }
    ],
    "sg:phone":"+1 770 961 1500",
    "sg:postcode":"30273",
    "sg:province":"GA",
    "sg:tags":[
        "product",
        "mfg"
    ],
    "wof:name":"Soltech Corporation",
    "wof:placetype":"venue"
},
  "geometry": {"coordinates":[-84.296392,33.565491],"type":"Point"}
}