{
  "type": "Feature",
  "properties": {
    "iso:country":"US",
    "sg:address":"1111 Griffin Ave",
    "sg:city":"Eastman",
    "sg:classifiers":[
        {
            "category":"Health Services",
            "subcategory":"Doctor",
            "type":"Services"
        }
    ],
    "sg:phone":"+1 478 374 7654",
    "sg:postcode":"31023",
    "sg:province":"GA",
    "sg:tags":[
        "physician",
        "surgeon"
    ],
    "wof:name":"Salvat Oscar MD",
    "wof:placetype":"venue"
},
  "geometry": {"coordinates":[-83.17919000000001,32.184736],"type":"Point"}
}