{
  "type": "Feature",
  "properties": {
    "iso:country":"US",
    "sg:address":"2361 Dillon Rd",
    "sg:city":"Thomasville",
    "sg:classifiers":[
        {
            "category":"Building & Trades",
            "subcategory":"Construction",
            "type":"Services"
        }
    ],
    "sg:phone":"+1 229 227 0333",
    "sg:postcode":"31757",
    "sg:province":"GA",
    "sg:tags":[
        "general",
        "contractor"
    ],
    "wof:name":"A & H Construction",
    "wof:placetype":"venue"
},
  "geometry": {"coordinates":[-83.91059799999999,30.894817],"type":"Point"}
}