{
  "type": "Feature",
  "properties": {
    "addr:full":"100 Riverview Dr Jonesboro GA 30240",
    "addr:housenumber":"100",
    "addr:postcode":"30240",
    "addr:street":"Riverview Dr",
    "iso:country":"US",
    "sg:address":"100 Riverview Dr",
    "sg:city":"Jonesboro",
    "sg:classifiers":[
        {
            "category":"Real Estate",
            "subcategory":"Real Estate Agent",
            "type":"Services"
        }
    ],
    "sg:phone":"+1 770 603 2019",
    "sg:postcode":"30240",
    "sg:province":"GA",
    "wof:name":"Villages On River",
    "wof:placetype":"venue"
},
  "geometry": {"coordinates":[-85.16482999999999,33.04854],"type":"Point"}
}