{
  "type": "Feature",
  "properties": {
    "iso:country":"US",
    "sg:address":"3212 E Wood Valley Rd NW",
    "sg:city":"Atlanta",
    "sg:classifiers":[
        {
            "category":"Building & Trades",
            "subcategory":"Construction",
            "type":"Services"
        }
    ],
    "sg:phone":"+1 404 237 1218",
    "sg:postcode":"30327",
    "sg:province":"GA",
    "sg:tags":[
        "contractor"
    ],
    "wof:name":"Palisades Shutter Co",
    "wof:placetype":"venue"
},
  "geometry": {"coordinates":[-84.412812,33.845895],"type":"Point"}
}