{
  "type": "Feature",
  "properties": {
    "iso:country":"US",
    "sg:address":"17 Andrew St",
    "sg:city":"Newnan",
    "sg:classifiers":[
        {
            "category":"Retail",
            "subcategory":"Auto Repair",
            "type":"Services"
        }
    ],
    "sg:phone":"+1 770 253 0602",
    "sg:postcode":"30263",
    "sg:province":"GA",
    "sg:tags":[
        "body"
    ],
    "wof:name":"Newnan Collision Center Inc",
    "wof:placetype":"venue"
},
  "geometry": {"coordinates":[-84.79650700000001,33.376705],"type":"Point"}
}