{
  "type": "Feature",
  "properties": {
    "addr:full":"3530 Mall Blvd NW Duluth GA 30096",
    "addr:housenumber":"3530",
    "addr:postcode":"30096",
    "addr:street":"Mall Blvd Nw",
    "iso:country":"US",
    "sg:address":"3530 Mall Blvd NW",
    "sg:city":"Duluth",
    "sg:classifiers":[
        {
            "category":"Health Services",
            "subcategory":"Doctor",
            "type":"Services"
        }
    ],
    "sg:phone":"+1 770 622 9291",
    "sg:postcode":"30096",
    "sg:province":"GA",
    "wof:name":"Affordable Braces",
    "wof:placetype":"venue"
},
  "geometry": {"coordinates":[-84.129722,33.959296],"type":"Point"}
}