{
  "type": "Feature",
  "properties": {
    "iso:country":"US",
    "sg:address":"7855 N Point Pkwy",
    "sg:city":"Alpharetta",
    "sg:classifiers":[
        {
            "category":"Banks & Credit Unions",
            "subcategory":"Bank",
            "type":"Services"
        }
    ],
    "sg:phone":"+1 770 649 0916",
    "sg:postcode":"30022",
    "sg:province":"GA",
    "sg:tags":[
        "loan",
        "real estate"
    ],
    "wof:name":"Academy Financial Svc",
    "wof:placetype":"venue"
},
  "geometry": {"coordinates":[-84.25662699999999,34.087476],"type":"Point"}
}