{
  "type": "Feature",
  "properties": {
    "addr:full":"67 Mount Olive Rd Carrollton GA 30108",
    "addr:housenumber":"67",
    "addr:postcode":"30108",
    "addr:street":"Mount Olive Rd",
    "iso:country":"US",
    "sg:address":"67 Mount Olive Rd",
    "sg:city":"Carrollton",
    "sg:classifiers":[
        {
            "category":"Social Services",
            "subcategory":"Child Care",
            "type":"Services"
        }
    ],
    "sg:phone":"+1 404 441 3067",
    "sg:postcode":"30108",
    "sg:province":"GA",
    "sg:tags":[
        "day"
    ],
    "wof:name":"Start Somin Contractor Svcs",
    "wof:placetype":"venue"
},
  "geometry": {"coordinates":[-85.293482,33.457184],"type":"Point"}
}