{
  "type": "Feature",
  "properties": {
    "addr:full":"2447 Shorter Ave Rome GA 30165",
    "addr:housenumber":"2447",
    "addr:postcode":"ga 30165",
    "addr:street":"Shorter Ave",
    "iso:country":"US",
    "sg:address":"2447 Shorter Ave",
    "sg:city":"Rome",
    "sg:classifiers":[
        {
            "category":"Retail",
            "subcategory":"Auto Rental",
            "type":"Services"
        }
    ],
    "sg:phone":"+1 706 232 9778",
    "sg:postcode":"30165",
    "sg:province":"GA",
    "sg:tags":[
        "renting",
        "truck",
        "leasing"
    ],
    "wof:name":"U-Haul Co",
    "wof:placetype":"venue"
},
  "geometry": {"coordinates":[-85.23647800000001,34.271752],"type":"Point"}
}