{
  "type": "Feature",
  "properties": {
    "iso:country":"US",
    "sg:address":"107 Sir Lancelot St",
    "sg:city":"Lagrange",
    "sg:classifiers":[
        {
            "category":"Utilities",
            "subcategory":"Refuse",
            "type":"Services"
        }
    ],
    "sg:phone":"+1 706 884 2761",
    "sg:postcode":"30241",
    "sg:province":"GA",
    "sg:tags":[
        "garbage",
        "collection"
    ],
    "wof:name":"Big Johns Sanitation",
    "wof:placetype":"venue"
},
  "geometry": {"coordinates":[-84.994446,33.06024],"type":"Point"}
}