{
  "type": "Feature",
  "properties": {
    "iso:country":"US",
    "sg:address":"242 Stockbridge Rd",
    "sg:city":"Jonesboro",
    "sg:classifiers":[
        {
            "category":"Restaurant",
            "type":"Food & Drink"
        }
    ],
    "sg:phone":"+1 770 473 1020",
    "sg:postcode":"30236",
    "sg:province":"GA",
    "wof:name":"Yammys Pizza & Subs",
    "wof:placetype":"venue"
},
  "geometry": {"coordinates":[-84.346538,33.526269],"type":"Point"}
}