{
  "type": "Feature",
  "properties": {
    "iso:country":"US",
    "sg:address":"978 Spur 138",
    "sg:city":"Jonesboro",
    "sg:classifiers":[
        {
            "category":"Restaurant",
            "type":"Food & Drink"
        }
    ],
    "sg:phone":"+1 770 478 1004",
    "sg:postcode":"30236",
    "sg:province":"GA",
    "sg:tags":[
        "steakhouse"
    ],
    "wof:name":"Ribs To Go",
    "wof:placetype":"venue"
},
  "geometry": {"coordinates":[-84.358594,33.539157],"type":"Point"}
}