{
  "type": "Feature",
  "properties": {
    "iso:country":"US",
    "sg:address":"1358 Welborn Rd",
    "sg:city":"Gillsville",
    "sg:classifiers":[
        {
            "category":"Retail",
            "subcategory":"Car Wash",
            "type":"Services"
        }
    ],
    "sg:phone":"+1 706 215 4399",
    "sg:postcode":"30558",
    "sg:province":"GA",
    "sg:tags":[
        "carwash"
    ],
    "wof:name":"Spotless Pressure Washing",
    "wof:placetype":"venue"
},
  "geometry": {"coordinates":[-83.588145,34.322754],"type":"Point"}
}