{
  "type": "Feature",
  "properties": {
    "addr:full":"6849 Peachtree Dunwoody R Bldg B2 Atlanta GA 30328",
    "addr:housenumber":"6849",
    "addr:postcode":"30328",
    "addr:street":"Peachtree Dunwoody R Bldg B2",
    "iso:country":"US",
    "sg:address":"6849 Peachtree Dunwoody R Bldg B2",
    "sg:city":"Atlanta",
    "sg:classifiers":[
        {
            "category":"Professional",
            "subcategory":"Accounting & Tax Preparation",
            "type":"Services"
        }
    ],
    "sg:phone":"+1 770 671 1533",
    "sg:postcode":"30328",
    "sg:province":"GA",
    "sg:tags":[
        "accountant"
    ],
    "wof:name":"Gilbert Rhonda M C*P*A",
    "wof:placetype":"venue"
},
  "geometry": {"coordinates":[-84.352463,33.942353],"type":"Point"}
}