{
  "type": "Feature",
  "properties": {
    "addr:full":"509 Center St Palmetto GA 30268",
    "addr:housenumber":"509",
    "addr:postcode":"30268",
    "addr:street":"Center St",
    "iso:country":"US",
    "sg:address":"509 Center St",
    "sg:city":"Palmetto",
    "sg:classifiers":[
        {
            "category":"Organizations",
            "subcategory":"Religious Organization",
            "type":"Services"
        }
    ],
    "sg:phone":"+1 770 463 0603",
    "sg:postcode":"30268",
    "sg:province":"GA",
    "wof:name":"Faith In Jesus Christ Family Ministries",
    "wof:placetype":"venue"
},
  "geometry": {"coordinates":[-84.66909800000001,33.519501],"type":"Point"}
}