{
  "type": "Feature",
  "properties": {
    "iso:country":"US",
    "sg:address":"31 Emerald Pines Ct",
    "sg:city":"Dallas",
    "sg:classifiers":[
        {
            "category":"Personal",
            "type":"Services"
        }
    ],
    "sg:phone":"+1 404 483 3600",
    "sg:postcode":"30157",
    "sg:province":"GA",
    "wof:name":"Flag Home Improvements",
    "wof:placetype":"venue"
},
  "geometry": {"coordinates":[-84.828369,33.871426],"type":"Point"}
}