{
  "type": "Feature",
  "properties": {
    "iso:country":"US",
    "sg:address":"1180 Franklin Rd SE # 102",
    "sg:city":"Marietta",
    "sg:classifiers":[
        {
            "category":"Wholesale",
            "subcategory":"Construction Materials",
            "type":"Manufacturing & Wholesale Goods"
        },
        {
            "category":"Manufacturing",
            "subcategory":"Building Materials",
            "type":"Manufacturing & Wholesale Goods"
        }
    ],
    "sg:phone":"+1 770 457 9733",
    "sg:postcode":"30067",
    "sg:province":"GA",
    "sg:tags":[
        "mixed",
        "aggregate",
        "concrete-ready",
        "concrete"
    ],
    "wof:name":"Robinson Rehabilitation Inc",
    "wof:placetype":"venue"
},
  "geometry": {"coordinates":[-84.49202699999999,33.923969],"type":"Point"}
}