{
  "type": "Feature",
  "properties": {
    "iso:country":"US",
    "sg:address":"3034 Coach Ln",
    "sg:city":"Marietta",
    "sg:classifiers":[
        {
            "category":"Professional",
            "subcategory":"Business Services",
            "type":"Services"
        }
    ],
    "sg:phone":"+1 678 468 2825",
    "sg:postcode":"30062",
    "sg:province":"GA",
    "wof:name":"All Nations Design Studio",
    "wof:placetype":"venue"
},
  "geometry": {"coordinates":[-84.431718,34.025537],"type":"Point"}
}