{
  "type": "Feature",
  "properties": {
    "addr:full":"3516 Billingsley Dr Marietta GA 30062",
    "addr:housenumber":"3516",
    "addr:postcode":"30062",
    "addr:street":"Billingsley Dr",
    "iso:country":"US",
    "sg:address":"3516 Billingsley Dr",
    "sg:city":"Marietta",
    "sg:classifiers":[
        {
            "category":"Shopping",
            "subcategory":"Used Merchandise",
            "type":"Retail Goods"
        }
    ],
    "sg:phone":"+1 678 236 8786",
    "sg:postcode":"30062",
    "sg:province":"GA",
    "wof:name":"This & That",
    "wof:placetype":"venue"
},
  "geometry": {"coordinates":[-84.461535,33.982355],"type":"Point"}
}