{
  "type": "Feature",
  "properties": {
    "addr:full":"19 Jones St NW Norcross GA 30071",
    "addr:housenumber":"19",
    "addr:postcode":"30071",
    "addr:street":"Jones St Nw",
    "iso:country":"US",
    "sg:address":"19 Jones St NW",
    "sg:city":"Norcross",
    "sg:classifiers":[
        {
            "category":"Shopping",
            "type":"Retail Goods"
        }
    ],
    "sg:phone":"+1 770 263 9509",
    "sg:postcode":"30071",
    "sg:province":"GA",
    "sg:tags":[
        "art",
        "gallery",
        "dealer"
    ],
    "wof:name":"Royal The",
    "wof:placetype":"venue"
},
  "geometry": {"coordinates":[-84.212366,33.942074],"type":"Point"}
}