{
  "type": "Feature",
  "properties": {
    "iso:country":"US",
    "sg:address":"3352 Ardley Rd SW",
    "sg:city":"Atlanta",
    "sg:classifiers":[
        {
            "category":"Real Estate",
            "subcategory":"Real Estate Agent",
            "type":"Services"
        }
    ],
    "sg:phone":"+1 404 696 0401",
    "sg:postcode":"30311",
    "sg:province":"GA",
    "wof:name":"Limbar & Associates",
    "wof:placetype":"venue"
},
  "geometry": {"coordinates":[-84.49981,33.728726],"type":"Point"}
}