{
  "type": "Feature",
  "properties": {
    "iso:country":"US",
    "sg:address":"995 Baxter St",
    "sg:city":"Athens",
    "sg:classifiers":[
        {
            "category":"Health Services",
            "subcategory":"Doctor",
            "type":"Services"
        }
    ],
    "sg:phone":"+1 706 546 8480",
    "sg:postcode":"30606",
    "sg:province":"GA",
    "sg:tags":[
        "dentist"
    ],
    "wof:name":"Mc Rae Matthew Jr DMD PC",
    "wof:placetype":"venue"
},
  "geometry": {"coordinates":[-83.389606,33.948771],"type":"Point"}
}