{
  "type": "Feature",
  "properties": {
    "iso:country":"US",
    "sg:address":"341 S Midway Rd",
    "sg:city":"Hawkinsville",
    "sg:classifiers":[
        {
            "category":"Farming",
            "subcategory":"Farm",
            "type":"Manufacturing & Wholesale Goods"
        }
    ],
    "sg:phone":"+1 478 892 2902",
    "sg:postcode":"31015",
    "sg:province":"GA",
    "wof:name":"B & B Farms",
    "wof:placetype":"venue"
},
  "geometry": {"coordinates":[-83.745806,31.961769],"type":"Point"}
}