{
  "type": "Feature",
  "properties": {
    "addr:full":"275 Briarwood Ln Hull GA 30646",
    "addr:housenumber":"275",
    "addr:postcode":"30646",
    "addr:street":"Briarwood Ln",
    "iso:country":"US",
    "sg:address":"275 Briarwood Ln",
    "sg:city":"Hull",
    "sg:classifiers":[
        {
            "category":"Professional",
            "type":"Services"
        }
    ],
    "sg:phone":"+1 706 788 3542",
    "sg:postcode":"30646",
    "sg:province":"GA",
    "wof:name":"Regina Baughcum",
    "wof:placetype":"venue"
},
  "geometry": {"coordinates":[-83.298857,34.038898],"type":"Point"}
}