{
  "type": "Feature",
  "properties": {
    "iso:country":"US",
    "sg:address":"1658 Fort Connors Way",
    "sg:city":"Dacula",
    "sg:classifiers":[
        {
            "category":"Professional",
            "subcategory":"Art Services",
            "type":"Services"
        }
    ],
    "sg:phone":"+1 770 366 1130",
    "sg:postcode":"30019",
    "sg:province":"GA",
    "sg:tags":[
        "designer",
        "display",
        "producer"
    ],
    "wof:name":"Designs By Jenny",
    "wof:placetype":"venue"
},
  "geometry": {"coordinates":[-83.93294,34.038088],"type":"Point"}
}