{
  "type": "Feature",
  "properties": {
    "addr:full":"105 Willowcrest Way Lagrange GA 30240",
    "addr:housenumber":"105",
    "addr:postcode":"30240",
    "addr:street":"Willowcrest Way",
    "iso:country":"US",
    "sg:address":"105 Willowcrest Way",
    "sg:city":"Lagrange",
    "sg:classifiers":[
        {
            "category":"Professional",
            "subcategory":"Advertising",
            "type":"Services"
        }
    ],
    "sg:phone":"+1 706 812 0439",
    "sg:postcode":"30240",
    "sg:province":"GA",
    "sg:tags":[
        "distribution"
    ],
    "wof:name":"Stanford Sales & Marketing Inc",
    "wof:placetype":"venue"
},
  "geometry": {"coordinates":[-85.093316,33.060207],"type":"Point"}
}