{
  "type": "Feature",
  "properties": {
    "iso:country":"US",
    "sg:address":"350 Vickery Cir",
    "sg:city":"Roswell",
    "sg:classifiers":[
        {
            "category":"Education",
            "subcategory":"Dance Studio",
            "type":"Public Place"
        }
    ],
    "sg:phone":"+1 770 242 6379",
    "sg:postcode":"30075",
    "sg:province":"GA",
    "wof:name":"Academy of Ballet Inc",
    "wof:placetype":"venue"
},
  "geometry": {"coordinates":[-84.332505,34.014757],"type":"Point"}
}