{
  "type": "Feature",
  "properties": {
    "iso:country":"US",
    "sg:address":"309 3rd St",
    "sg:city":"Vienna",
    "sg:classifiers":[
        {
            "category":"Utilities",
            "subcategory":"Telephone",
            "type":"Services"
        }
    ],
    "sg:phone":"+1 229 268 3620",
    "sg:postcode":"31092",
    "sg:province":"GA",
    "sg:tags":[
        "company"
    ],
    "wof:name":"Equity Pay Telephone",
    "wof:placetype":"venue"
},
  "geometry": {"coordinates":[-83.79689,32.095217],"type":"Point"}
}