{
  "type": "Feature",
  "properties": {
    "addr:full":"3500 Peachtree Rd NE Atlanta GA 30326",
    "addr:housenumber":"3500",
    "addr:postcode":"30326",
    "addr:street":"Peachtree Rd Ne",
    "iso:country":"US",
    "sg:address":"3500 Peachtree Rd NE",
    "sg:city":"Atlanta",
    "sg:classifiers":[
        {
            "category":"Restaurant",
            "type":"Food & Drink"
        }
    ],
    "sg:menulink":"http://www.allmenus.com/ga/atlanta/23345-twist/menu/",
    "sg:phone":"+1 404 869 1191",
    "sg:postcode":"30326",
    "sg:province":"GA",
    "sg:tags":[
        "spanish"
    ],
    "wof:name":"Twist",
    "wof:placetype":"venue"
},
  "geometry": {"coordinates":[-84.360597,33.852261],"type":"Point"}
}