{
  "type": "Feature",
  "properties": {
    "iso:country":"US",
    "sg:address":"2400 Barrett Creek Blvd",
    "sg:city":"Marietta",
    "sg:classifiers":[
        {
            "category":"Health Services",
            "subcategory":"Health Practitioner",
            "type":"Services"
        }
    ],
    "sg:phone":"+1 770 514 9154",
    "sg:postcode":"30066",
    "sg:province":"GA",
    "wof:name":"Jeanette Ferris Franis",
    "wof:placetype":"venue"
},
  "geometry": {"coordinates":[-84.554563,34.012302],"type":"Point"}
}