{
  "type": "Feature",
  "properties": {
    "iso:country":"US",
    "sg:address":"235 Silver Birch Ct",
    "sg:city":"Alpharetta",
    "sg:classifiers":[
        {
            "category":"Professional",
            "subcategory":"Computer Services",
            "type":"Services"
        }
    ],
    "sg:phone":"+1 678 513 4320",
    "sg:postcode":"30004",
    "sg:province":"GA",
    "sg:tags":[
        "consultant",
        "designer",
        "system"
    ],
    "wof:name":"Mmb And Associates",
    "wof:placetype":"venue"
},
  "geometry": {"coordinates":[-84.261257,34.205248],"type":"Point"}
}