{
  "type": "Feature",
  "properties": {
    "iso:country":"US",
    "sg:address":"902 Commerce St",
    "sg:city":"Perry",
    "sg:classifiers":[
        {
            "category":"Home & Garden",
            "subcategory":"Building Materials",
            "type":"Retail Goods"
        }
    ],
    "sg:phone":"+1 478 987 2675",
    "sg:postcode":"31069",
    "sg:province":"GA",
    "wof:name":"Spray-Tech",
    "wof:placetype":"venue"
},
  "geometry": {"coordinates":[-83.73252599999999,32.4595],"type":"Point"}
}