{
  "type": "Feature",
  "properties": {
    "addr:full":"212 N Jefferson St Albany GA 31701",
    "addr:housenumber":"212",
    "addr:postcode":"31701",
    "addr:street":"N Jefferson St",
    "iso:country":"US",
    "sg:address":"212 N Jefferson St",
    "sg:city":"Albany",
    "sg:classifiers":[
        {
            "category":"Restaurant",
            "type":"Food & Drink"
        }
    ],
    "sg:phone":"+1 229 886 3105",
    "sg:postcode":"31701",
    "sg:province":"GA",
    "wof:name":"Simply Delicious",
    "wof:placetype":"venue"
},
  "geometry": {"coordinates":[-84.155992,31.578637],"type":"Point"}
}