{
  "type": "Feature",
  "properties": {
    "addr:full":"7561 Industrial Ct Alpharetta GA 30004",
    "addr:housenumber":"7561",
    "addr:postcode":"30004",
    "addr:street":"Industrial Ct",
    "iso:country":"US",
    "sg:address":"7561 Industrial Ct",
    "sg:city":"Alpharetta",
    "sg:classifiers":[
        {
            "category":"Wholesale",
            "subcategory":"Chemicals & Plastics",
            "type":"Manufacturing & Wholesale Goods"
        }
    ],
    "sg:phone":"+1 770 475 8199",
    "sg:postcode":"30004",
    "sg:province":"GA",
    "sg:tags":[
        "protective",
        "coating"
    ],
    "wof:name":"Madewell Products Corporation",
    "wof:placetype":"venue"
},
  "geometry": {"coordinates":[-84.25102099999999,34.136868],"type":"Point"}
}