{
  "type": "Feature",
  "properties": {
    "iso:country":"US",
    "sg:address":"4584 Jonesboro Rd",
    "sg:city":"Forest Park",
    "sg:classifiers":[
        {
            "category":"Education",
            "subcategory":"Kindergarten",
            "type":"Public Place"
        }
    ],
    "sg:phone":"+1 404 608 8458",
    "sg:postcode":"30297",
    "sg:province":"GA",
    "sg:tags":[
        "school",
        "driving"
    ],
    "wof:name":"Alfa Hispanic Center Dui School",
    "wof:placetype":"venue"
},
  "geometry": {"coordinates":[-84.3563,33.629601],"type":"Point"}
}