{
  "type": "Feature",
  "properties": {
    "addr:full":"41 Irby Ave NW Atlanta GA 30305",
    "addr:housenumber":"41",
    "addr:postcode":"30305",
    "addr:street":"Irby Ave Nw",
    "iso:country":"US",
    "sg:address":"41 Irby Ave NW",
    "sg:city":"Atlanta",
    "sg:classifiers":[
        {
            "category":"Travel",
            "subcategory":"Hotels & Motels",
            "type":"Entertainment"
        }
    ],
    "sg:phone":"+1 404 365 0777",
    "sg:postcode":"30305",
    "sg:province":"GA",
    "sg:tags":[
        "bar",
        "diva"
    ],
    "wof:name":"Five Paces Inn",
    "wof:placetype":"venue"
},
  "geometry": {"coordinates":[-84.38009599999999,33.841099],"type":"Point"}
}