{
  "type": "Feature",
  "properties": {
    "iso:country":"US",
    "sg:address":"2845 Greenbriar Pkwy SW",
    "sg:city":"Atlanta",
    "sg:classifiers":[
        {
            "category":"Restaurant",
            "type":"Food & Drink"
        }
    ],
    "sg:menulink":"http://www.allmenus.com/ga/atlanta/100628-captain-ds-seafood/menu/",
    "sg:phone":"+1 404 344 6331",
    "sg:postcode":"30331",
    "sg:province":"GA",
    "sg:tags":[
        "seafood",
        "american"
    ],
    "wof:name":"Captain D's Seafood",
    "wof:placetype":"venue"
},
  "geometry": {"coordinates":[-84.49568600000001,33.68628],"type":"Point"}
}