{
  "type": "Feature",
  "properties": {
    "iso:country":"US",
    "sg:address":"5008 10th Ave",
    "sg:city":"Eastman",
    "sg:classifiers":[
        {
            "category":"Shopping",
            "type":"Retail Goods"
        }
    ],
    "sg:phone":"+1 478 374 1212",
    "sg:postcode":"31023",
    "sg:province":"GA",
    "sg:tags":[
        "hearing",
        "equipment",
        "supply",
        "merchandise",
        "impaired"
    ],
    "wof:name":"Bashuk Beltone Hearing Aid Ctr",
    "wof:placetype":"venue"
},
  "geometry": {"coordinates":[-83.18210500000001,32.202693],"type":"Point"}
}