{
  "type": "Feature",
  "properties": {
    "iso:country":"US",
    "sg:address":"8015 Clearview Cir",
    "sg:city":"Riverdale",
    "sg:classifiers":[
        {
            "category":"Building & Trades",
            "subcategory":"Construction",
            "type":"Services"
        }
    ],
    "sg:phone":"+1 678 618 5228",
    "sg:postcode":"30296",
    "sg:province":"GA",
    "sg:tags":[
        "house"
    ],
    "wof:name":"J Walton Construction LLC",
    "wof:placetype":"venue"
},
  "geometry": {"coordinates":[-84.430038,33.541717],"type":"Point"}
}