{
  "type": "Feature",
  "properties": {
    "addr:full":"1345 Bowens Mill Rd SW Ste C Douglas GA 31533",
    "addr:housenumber":"1345",
    "addr:postcode":"31533",
    "addr:street":"Bowens Mill Rd Sw Ste C",
    "iso:country":"US",
    "sg:address":"1345 Bowens Mill Rd SW Ste C",
    "sg:city":"Douglas",
    "sg:classifiers":[
        {
            "category":"Shopping",
            "subcategory":"Clothing, Apparel, & Fashions",
            "type":"Retail Goods"
        }
    ],
    "sg:phone":"+1 912 384 0654",
    "sg:postcode":"31533",
    "sg:province":"GA",
    "sg:tags":[
        "men's",
        "accessory",
        "apparel",
        "girls'",
        "women's",
        "clothing",
        "boys'",
        "store"
    ],
    "sg:website":"http://www.rue21.com",
    "wof:name":"Rue21",
    "wof:placetype":"venue"
},
  "geometry": {"coordinates":[-82.853661,31.487881],"type":"Point"}
}