{
  "type": "Feature",
  "properties": {
    "addr:full":"1131 W College St Exd Griffin GA 30224",
    "addr:housenumber":"1131",
    "addr:postcode":"30224",
    "addr:street":"W College St Exd",
    "iso:country":"US",
    "sg:address":"1131 W College St Exd",
    "sg:city":"Griffin",
    "sg:classifiers":[
        {
            "category":"Professional",
            "type":"Services"
        }
    ],
    "sg:phone":"+1 770 228 2361",
    "sg:postcode":"30224",
    "sg:province":"GA",
    "wof:name":"Small One",
    "wof:placetype":"venue"
},
  "geometry": {"coordinates":[-84.281148,33.241501],"type":"Point"}
}