{
  "type": "Feature",
  "properties": {
    "iso:country":"US",
    "sg:address":"3009 Cheshire Ct",
    "sg:city":"Woodstock",
    "sg:classifiers":[
        {
            "category":"Professional",
            "subcategory":"Business Services",
            "type":"Services"
        }
    ],
    "sg:phone":"+1 678 445 8175",
    "sg:postcode":"30189",
    "sg:province":"GA",
    "wof:name":"Adamma Landscape Group",
    "wof:placetype":"venue"
},
  "geometry": {"coordinates":[-84.57933199999999,34.14031],"type":"Point"}
}