{
  "type": "Feature",
  "properties": {
    "addr:full":"9281 State Rte 5 Douglasville GA 30134",
    "addr:housenumber":"9281",
    "addr:postcode":"30134",
    "addr:street":"State Rte 5",
    "iso:country":"US",
    "sg:address":"9281 State Rte 5",
    "sg:city":"Douglasville",
    "sg:classifiers":[
        {
            "category":"Building & Trades",
            "subcategory":"Construction",
            "type":"Services"
        },
        {
            "category":"Real Estate",
            "subcategory":"Real Estate Operator",
            "type":"Services"
        }
    ],
    "sg:phone":"+1 770 489 4800",
    "sg:postcode":"30134",
    "sg:province":"GA",
    "sg:tags":[
        "parks",
        "nonresidential"
    ],
    "wof:name":"Classic Manner Builders Inc",
    "wof:placetype":"venue"
},
  "geometry": {"coordinates":[-84.762209,33.730472],"type":"Point"}
}