{
  "type": "Feature",
  "properties": {
    "addr:full":"249 Braden Dr Tucker GA 30084",
    "addr:housenumber":"249",
    "addr:postcode":"30084",
    "addr:street":"Braden Dr",
    "iso:country":"US",
    "sg:address":"249 Braden Dr",
    "sg:city":"Tucker",
    "sg:classifiers":[
        {
            "category":"Insurance",
            "subcategory":"Insurance Agent",
            "type":"Services"
        }
    ],
    "sg:phone":"+1 404 617 8191",
    "sg:postcode":"30084",
    "sg:province":"GA",
    "wof:name":"CK Brokers Inc",
    "wof:placetype":"venue"
},
  "geometry": {"coordinates":[-84.166736,33.87771],"type":"Point"}
}