{
  "type": "Feature",
  "properties": {
    "addr:full":"5431 Clinchfield Trl Norcross GA 30092",
    "addr:housenumber":"5431",
    "addr:postcode":"30092",
    "addr:street":"Clinchfield Trl",
    "iso:country":"US",
    "sg:address":"5431 Clinchfield Trl",
    "sg:city":"Norcross",
    "sg:classifiers":[
        {
            "category":"Manufacturing",
            "subcategory":"Glass & Minerals",
            "type":"Manufacturing & Wholesale Goods"
        }
    ],
    "sg:phone":"+1 770 417 3490",
    "sg:postcode":"30092",
    "sg:province":"GA",
    "sg:tags":[
        "ready",
        "concrete",
        "mfg"
    ],
    "wof:name":"Acm Chemistries Inc",
    "wof:placetype":"venue"
},
  "geometry": {"coordinates":[-84.230814,33.984091],"type":"Point"}
}