{
  "type": "Feature",
  "properties": {
    "addr:full":"1101 Maple Ridge Ct Evans GA 30809",
    "addr:housenumber":"1101",
    "addr:postcode":"30809",
    "addr:street":"Maple Ridge Ct",
    "iso:country":"US",
    "sg:address":"1101 Maple Ridge Ct",
    "sg:city":"Evans",
    "sg:classifiers":[
        {
            "category":"Professional",
            "subcategory":"Management & Consulting",
            "type":"Services"
        }
    ],
    "sg:phone":"+1 706 869 0939",
    "sg:postcode":"30809",
    "sg:province":"GA",
    "sg:tags":[
        "business"
    ],
    "wof:name":"Campbells Security Consulting",
    "wof:placetype":"venue"
},
  "geometry": {"coordinates":[-82.14748400000001,33.57945],"type":"Point"}
}