{
  "type": "Feature",
  "properties": {
    "addr:full":"5922 Fairburn Rd Douglasville GA 30134",
    "addr:housenumber":"5922",
    "addr:postcode":"30134",
    "addr:street":"Fairburn Rd",
    "iso:country":"US",
    "sg:address":"5922 Fairburn Rd",
    "sg:city":"Douglasville",
    "sg:classifiers":[
        {
            "category":"Autos & Motor Vehicles",
            "subcategory":"Recreational Vehicle Sales",
            "type":"Retail Goods"
        }
    ],
    "sg:phone":"+1 678 715 8022",
    "sg:postcode":"30134",
    "sg:province":"GA",
    "wof:name":"Super 1 Rv Douglasville",
    "wof:placetype":"venue"
},
  "geometry": {"coordinates":[-84.73921300000001,33.750936],"type":"Point"}
}