{
  "type": "Feature",
  "properties": {
    "addr:full":"2049 Stroud Rd Jackson GA 30233",
    "addr:housenumber":"2049",
    "addr:postcode":"30233",
    "addr:street":"Stroud Rd",
    "iso:country":"US",
    "sg:address":"2049 Stroud Rd",
    "sg:city":"Jackson",
    "sg:classifiers":[
        {
            "category":"Building & Trades",
            "subcategory":"Construction",
            "type":"Services"
        }
    ],
    "sg:phone":"+1 770 957 4105",
    "sg:postcode":"30233",
    "sg:province":"GA",
    "sg:tags":[
        "repairing",
        "remodeling",
        "contractor"
    ],
    "wof:name":"Phillips Nelms Assoc",
    "wof:placetype":"venue"
},
  "geometry": {"coordinates":[-83.982618,33.413655],"type":"Point"}
}