{
  "type": "Feature",
  "properties": {
    "addr:full":"624 Holcomb Bridge Rd Ste 1 Roswell GA 30076",
    "addr:housenumber":"624",
    "addr:postcode":"30076",
    "addr:street":"Holcomb Bridge Rd Ste 1",
    "iso:country":"US",
    "sg:address":"624 Holcomb Bridge Rd Ste 1",
    "sg:city":"Roswell",
    "sg:classifiers":[
        {
            "category":"Professional",
            "subcategory":"Accounting & Tax Preparation",
            "type":"Services"
        }
    ],
    "sg:phone":"+1 770 642 9855",
    "sg:postcode":"30076",
    "sg:province":"GA",
    "sg:tags":[
        "accountant"
    ],
    "sg:website":"www.ewmcpapc.com",
    "wof:name":"Morrow Earl W CPA PC",
    "wof:placetype":"venue"
},
  "geometry": {"coordinates":[-84.322098,34.025902],"type":"Point"}
}