{
  "type": "Feature",
  "properties": {
    "addr:full":"1550 Mars Hill Rd Watkinsville GA 30677",
    "addr:housenumber":"1550",
    "addr:postcode":"30677",
    "addr:street":"Mars Hill Rd",
    "iso:country":"US",
    "sg:address":"1550 Mars Hill Rd",
    "sg:city":"Watkinsville",
    "sg:classifiers":[
        {
            "category":"Health Services",
            "subcategory":"Doctor",
            "type":"Services"
        }
    ],
    "sg:phone":"+1 706 769 4852",
    "sg:postcode":"30677",
    "sg:province":"GA",
    "sg:tags":[
        "physician",
        "surgeon"
    ],
    "wof:name":"Greater Athens Physicians Inc",
    "wof:placetype":"venue"
},
  "geometry": {"coordinates":[-83.45402199999999,33.880988],"type":"Point"}
}