{
  "type": "Feature",
  "properties": {
    "iso:country":"US",
    "sg:address":"5115 New Peachtree Rd",
    "sg:city":"Atlanta",
    "sg:classifiers":[
        {
            "category":"Manufacturing",
            "subcategory":"Food",
            "type":"Manufacturing & Wholesale Goods"
        },
        {
            "category":"Health Services",
            "subcategory":"Health Practitioner",
            "type":"Services"
        }
    ],
    "sg:phone":"+1 770 451 8820",
    "sg:postcode":"30341",
    "sg:province":"GA",
    "sg:tags":[
        "nutritionist",
        "wellness"
    ],
    "wof:name":"Altasource Nutraceuticals",
    "wof:placetype":"venue"
},
  "geometry": {"coordinates":[-84.30970000000001,33.885601],"type":"Point"}
}