{
  "type": "Feature",
  "properties": {
    "iso:country":"US",
    "sg:address":"1846 Columbia Dr",
    "sg:city":"Decatur",
    "sg:classifiers":[
        {
            "category":"Autos & Motor Vehicles",
            "subcategory":"Auto Supplies",
            "type":"Retail Goods"
        }
    ],
    "sg:phone":"+1 404 288 2861",
    "sg:postcode":"30032",
    "sg:province":"GA",
    "sg:tags":[
        "tire"
    ],
    "wof:name":"Big 316 Tire Service",
    "wof:placetype":"venue"
},
  "geometry": {"coordinates":[-84.251823,33.736802],"type":"Point"}
}