{
  "type": "Feature",
  "properties": {
    "addr:full":"3059 Springside Run Decatur GA 30034",
    "addr:housenumber":"3059",
    "addr:postcode":"30034",
    "addr:street":"Springside Run",
    "iso:country":"US",
    "sg:address":"3059 Springside Run",
    "sg:city":"Decatur",
    "sg:classifiers":[
        {
            "category":"Retail",
            "subcategory":"Auto Repair",
            "type":"Services"
        }
    ],
    "sg:phone":"+1 404 284 6942",
    "sg:postcode":"30034",
    "sg:province":"GA",
    "sg:tags":[
        "exhaust"
    ],
    "wof:name":"Midas Touch Construction",
    "wof:placetype":"venue"
},
  "geometry": {"coordinates":[-84.251229,33.696442],"type":"Point"}
}