{
  "type": "Feature",
  "properties": {
    "addr:full":"102 Wendell Ct Warner Robins GA 31093",
    "addr:housenumber":"102",
    "addr:postcode":"31093",
    "addr:street":"Wendell Ct",
    "iso:country":"US",
    "sg:address":"102 Wendell Ct",
    "sg:city":"Warner Robins",
    "sg:classifiers":[
        {
            "category":"Personal",
            "type":"Services"
        }
    ],
    "sg:phone":"+1 478 923 1230",
    "sg:postcode":"31093",
    "sg:province":"GA",
    "wof:name":"Mr Fix It",
    "wof:placetype":"venue"
},
  "geometry": {"coordinates":[-83.648297,32.64402],"type":"Point"}
}