{
  "type": "Feature",
  "properties": {
    "iso:country":"US",
    "sg:address":"3273 Timberloch Dr",
    "sg:city":"Marietta",
    "sg:classifiers":[
        {
            "category":"Professional",
            "subcategory":"Management & Consulting",
            "type":"Services"
        },
        {
            "category":"Professional",
            "subcategory":"Employment Agencies",
            "type":"Services"
        }
    ],
    "sg:phone":"+1 770 565 6839",
    "sg:postcode":"30068",
    "sg:province":"GA",
    "sg:tags":[
        "consultant",
        "resource",
        "human"
    ],
    "sg:website":"http://www.qmiconsulting.com",
    "wof:name":"Quality Management Intl",
    "wof:placetype":"venue"
},
  "geometry": {"coordinates":[-84.460988,33.950101],"type":"Point"}
}