{
  "type": "Feature",
  "properties": {
    "iso:country":"US",
    "sg:address":"5836 Mableton Pkwy SW",
    "sg:city":"Mableton",
    "sg:classifiers":[
        {
            "category":"Home & Garden",
            "subcategory":"Carpets & Floor Coverings",
            "type":"Retail Goods"
        }
    ],
    "sg:phone":"+1 770 941 2011",
    "sg:postcode":"30126",
    "sg:province":"GA",
    "sg:tags":[
        "carpeting"
    ],
    "sg:website":"www.benjaminmoore.com",
    "wof:name":"Creative Paint & Wallpaper Inc",
    "wof:placetype":"venue"
},
  "geometry": {"coordinates":[-84.572109,33.811526],"type":"Point"}
}