{
  "type": "Feature",
  "properties": {
    "iso:country":"US",
    "sg:address":"2405 Botany Woods Dr",
    "sg:city":"Dalton",
    "sg:classifiers":[
        {
            "category":"Real Estate",
            "subcategory":"Real Estate Operator",
            "type":"Services"
        }
    ],
    "sg:phone":"+1 706 226 7084",
    "sg:postcode":"30720",
    "sg:province":"GA",
    "sg:tags":[
        "building",
        "nonresidential"
    ],
    "wof:name":"Sewell Properties LLC",
    "wof:placetype":"venue"
},
  "geometry": {"coordinates":[-85.009246,34.764805],"type":"Point"}
}