{
  "type": "Feature",
  "properties": {
    "addr:full":"799 Beaver Ln NW Lilburn GA 30047",
    "addr:housenumber":"799",
    "addr:postcode":"30047",
    "addr:street":"Beaver Ln Nw",
    "iso:country":"US",
    "sg:address":"799 Beaver Ln NW",
    "sg:city":"Lilburn",
    "sg:classifiers":[
        {
            "category":"Professional",
            "type":"Services"
        }
    ],
    "sg:phone":"+1 770 931 7953",
    "sg:postcode":"30047",
    "sg:province":"GA",
    "wof:name":"Northside Home Services Inc",
    "wof:placetype":"venue"
},
  "geometry": {"coordinates":[-84.12716399999999,33.9197],"type":"Point"}
}