{
  "type": "Feature",
  "properties": {
    "iso:country":"US",
    "sg:address":"2856 Belvedere Ln",
    "sg:city":"Decatur",
    "sg:classifiers":[
        {
            "category":"Government",
            "subcategory":"City Hall",
            "type":"Public Place"
        },
        {
            "category":"Government",
            "subcategory":"Office",
            "type":"Public Place"
        }
    ],
    "sg:phone":"+1 404 534 3244",
    "sg:postcode":"30032",
    "sg:province":"GA",
    "sg:tags":[
        "town",
        "township",
        "planner",
        "government-city",
        "village"
    ],
    "wof:name":"City Of Refuge",
    "wof:placetype":"venue"
},
  "geometry": {"coordinates":[-84.274056,33.75034],"type":"Point"}
}