{
  "type": "Feature",
  "properties": {
    "iso:country":"US",
    "sg:address":"3606 Indigo Creek Trl",
    "sg:city":"Kennesaw",
    "sg:classifiers":[
        {
            "category":"Professional",
            "type":"Services"
        }
    ],
    "sg:phone":"+1 770 529 0747",
    "sg:postcode":"30144",
    "sg:province":"GA",
    "wof:name":"Mark W Hoell",
    "wof:placetype":"venue"
},
  "geometry": {"coordinates":[-84.657927,34.036966],"type":"Point"}
}