{
  "type": "Feature",
  "properties": {
    "addr:full":"2794 Emerald Dr Jonesboro GA 30236",
    "addr:housenumber":"2794",
    "addr:postcode":"30236",
    "addr:street":"Emerald Dr",
    "iso:country":"US",
    "sg:address":"2794 Emerald Dr",
    "sg:city":"Jonesboro",
    "sg:classifiers":[
        {
            "category":"Building & Trades",
            "subcategory":"Landscaping Services",
            "type":"Services"
        }
    ],
    "sg:phone":"+1 770 603 6181",
    "sg:postcode":"30236",
    "sg:province":"GA",
    "wof:name":"Spivey Lawn Care Inc",
    "wof:placetype":"venue"
},
  "geometry": {"coordinates":[-84.301149,33.513379],"type":"Point"}
}