{
  "type": "Feature",
  "properties": {
    "addr:full":"344 Standard Ln Springfield GA 31329",
    "addr:housenumber":"344",
    "addr:postcode":"31329",
    "addr:street":"Standard Ln",
    "iso:country":"US",
    "sg:address":"344 Standard Ln",
    "sg:city":"Springfield",
    "sg:classifiers":[
        {
            "category":"Real Estate",
            "subcategory":"Real Estate Operator",
            "type":"Services"
        }
    ],
    "sg:phone":"+1 912 754 3500",
    "sg:postcode":"31329",
    "sg:province":"GA",
    "sg:tags":[
        "mobile",
        "home",
        "community"
    ],
    "wof:name":"Quail Run Mobile Home Park",
    "wof:placetype":"venue"
},
  "geometry": {"coordinates":[-81.326041,32.36943],"type":"Point"}
}