{
  "type": "Feature",
  "properties": {
    "iso:country":"US",
    "sg:address":"3 E Montgomery Xrd",
    "sg:city":"Savannah",
    "sg:classifiers":[
        {
            "category":"Recreation",
            "type":"Entertainment"
        }
    ],
    "sg:phone":"+1 912 921 8933",
    "sg:postcode":"31406",
    "sg:province":"GA",
    "sg:tags":[
        "diving",
        "instruction"
    ],
    "wof:name":"Fantasia Scuba",
    "wof:placetype":"venue"
},
  "geometry": {"coordinates":[-81.121717,31.998153],"type":"Point"}
}