{
  "type": "Feature",
  "properties": {
    "addr:full":"514 Bellevue Ave Dublin GA 31021",
    "addr:housenumber":"514",
    "addr:postcode":"31021",
    "addr:street":"Bellevue Ave",
    "iso:country":"US",
    "sg:address":"514 Bellevue Ave",
    "sg:city":"Dublin",
    "sg:classifiers":[
        {
            "category":"Government",
            "subcategory":"Court House",
            "type":"Public Place"
        }
    ],
    "sg:phone":"+1 478 272 2121",
    "sg:postcode":"31021",
    "sg:province":"GA",
    "sg:tags":[
        "federal"
    ],
    "wof:name":"US District Court Clerk",
    "wof:placetype":"venue"
},
  "geometry": {"coordinates":[-82.910062,32.538399],"type":"Point"}
}