{
  "type": "Feature",
  "properties": {
    "iso:country":"US",
    "sg:address":"324 Independence Way",
    "sg:city":"Woodstock",
    "sg:classifiers":[
        {
            "category":"Building & Trades",
            "subcategory":"Construction",
            "type":"Services"
        }
    ],
    "sg:phone":"+1 770 928 2590",
    "sg:postcode":"30188",
    "sg:province":"GA",
    "sg:tags":[
        "rent",
        "real estate",
        "home",
        "rental"
    ],
    "wof:name":"Rocam Inc",
    "wof:placetype":"venue"
},
  "geometry": {"coordinates":[-84.500846,34.1004],"type":"Point"}
}