{
  "type": "Feature",
  "properties": {
    "addr:full":"640 Village Trce NE Ste C Marietta GA 30067",
    "addr:housenumber":"640",
    "addr:postcode":"30067",
    "addr:street":"Village Trce Ne Ste C",
    "iso:country":"US",
    "sg:address":"640 Village Trce NE Ste C",
    "sg:city":"Marietta",
    "sg:classifiers":[
        {
            "category":"Freight",
            "type":"Transportation"
        }
    ],
    "sg:phone":"+1 770 933 9991",
    "sg:postcode":"30067",
    "sg:province":"GA",
    "sg:tags":[
        "broker",
        "trucking"
    ],
    "wof:name":"Deter Logistics",
    "wof:placetype":"venue"
},
  "geometry": {"coordinates":[-84.414158,33.950627],"type":"Point"}
}