{
  "type": "Feature",
  "properties": {
    "iso:country":"US",
    "sg:address":"2255 Pleasant Hill Rd",
    "sg:city":"Duluth",
    "sg:classifiers":[
        {
            "category":"Shopping",
            "subcategory":"Department Store",
            "type":"Retail Goods"
        }
    ],
    "sg:phone":"+1 770 623 4797",
    "sg:postcode":"30096",
    "sg:province":"GA",
    "wof:name":"Old Navy Clothing Co",
    "wof:placetype":"venue"
},
  "geometry": {"coordinates":[-84.136803,33.961899],"type":"Point"}
}