{
  "type": "Feature",
  "properties": {
    "addr:full":"33 W Park Sq NE Marietta GA 30060",
    "addr:housenumber":"33",
    "addr:postcode":"30060",
    "addr:street":"W Park Sq Ne",
    "iso:country":"US",
    "sg:address":"33 W Park Sq NE",
    "sg:city":"Marietta",
    "sg:classifiers":[
        {
            "category":"Wholesale",
            "subcategory":"Stationery",
            "type":"Manufacturing & Wholesale Goods"
        }
    ],
    "sg:phone":"+1 770 425 8990",
    "sg:postcode":"30060",
    "sg:province":"GA",
    "sg:tags":[
        "card"
    ],
    "wof:name":"Kathy's Too",
    "wof:placetype":"venue"
},
  "geometry": {"coordinates":[-84.550301,33.9529],"type":"Point"}
}