{
  "type": "Feature",
  "properties": {
    "iso:country":"US",
    "sg:address":"15 River Birch Ct SE",
    "sg:city":"Cartersville",
    "sg:classifiers":[
        {
            "category":"Retail",
            "subcategory":"Repair Shop",
            "type":"Services"
        }
    ],
    "sg:phone":"+1 770 975 0190",
    "sg:postcode":"30120",
    "sg:province":"GA",
    "sg:tags":[
        "lock",
        "locksmith"
    ],
    "wof:name":"Aabc Quality Locksmith",
    "wof:placetype":"venue"
},
  "geometry": {"coordinates":[-84.748267,34.104536],"type":"Point"}
}