{
  "type": "Feature",
  "properties": {
    "addr:full":"1937 Morgan Rd Canton GA 30115",
    "addr:housenumber":"1937",
    "addr:postcode":"30115",
    "addr:street":"Morgan Rd",
    "iso:country":"US",
    "sg:address":"1937 Morgan Rd",
    "sg:city":"Canton",
    "sg:classifiers":[
        {
            "category":"Building & Trades",
            "subcategory":"Construction",
            "type":"Services"
        }
    ],
    "sg:phone":"+1 770 345 5590",
    "sg:postcode":"30115",
    "sg:province":"GA",
    "sg:tags":[
        "residential"
    ],
    "wof:name":"Morgan Road Enterprises Inc",
    "wof:placetype":"venue"
},
  "geometry": {"coordinates":[-84.478804,34.168704],"type":"Point"}
}