{
  "type": "Feature",
  "properties": {
    "iso:country":"US",
    "sg:address":"375 Rockbridge Rd SW",
    "sg:city":"Lilburn",
    "sg:classifiers":[
        {
            "category":"Food & Beverages",
            "subcategory":"Groceries & Convenience Stores",
            "type":"Retail Goods"
        }
    ],
    "sg:phone":"+1 770 806 4040",
    "sg:postcode":"30047",
    "sg:province":"GA",
    "sg:tags":[
        "grocer"
    ],
    "wof:name":"Publix Super Market",
    "wof:placetype":"venue"
},
  "geometry": {"coordinates":[-84.145321,33.863907],"type":"Point"}
}