{
  "type": "Feature",
  "properties": {
    "addr:full":"6365 Spalding Dr Ste D Norcross GA 30092",
    "addr:housenumber":"6365",
    "addr:postcode":"30092",
    "addr:street":"Spalding Dr Ste D",
    "iso:country":"US",
    "sg:address":"6365 Spalding Dr Ste D",
    "sg:city":"Norcross",
    "sg:classifiers":[
        {
            "category":"Food & Beverages",
            "subcategory":"Chocolate",
            "type":"Retail Goods"
        }
    ],
    "sg:phone":"+1 678 728 0100",
    "sg:postcode":"30092",
    "sg:province":"GA",
    "sg:tags":[
        "shop",
        "chocolatiers"
    ],
    "sg:website":"chamberlainschocolate.com",
    "wof:name":"Chamberlain's Chocolate Factory",
    "wof:placetype":"venue"
},
  "geometry": {"coordinates":[-84.257609,33.968391],"type":"Point"}
}