{
  "type": "Feature",
  "properties": {
    "addr:full":"115 Softwood Cir Roswell GA 30076",
    "addr:housenumber":"115",
    "addr:postcode":"30076",
    "addr:street":"Softwood Cir",
    "iso:country":"US",
    "sg:address":"115 Softwood Cir",
    "sg:city":"Roswell",
    "sg:classifiers":[
        {
            "category":"Professional",
            "type":"Services"
        }
    ],
    "sg:phone":"+1 678 585 0144",
    "sg:postcode":"30076",
    "sg:province":"GA",
    "sg:tags":[
        "it",
        "sales"
    ],
    "wof:name":"Castle Creative Services LLC",
    "wof:placetype":"venue"
},
  "geometry": {"coordinates":[-84.31438300000001,34.011874],"type":"Point"}
}