{
  "type": "Feature",
  "properties": {
    "addr:full":"486 Williams St Buford GA 30518",
    "addr:housenumber":"486",
    "addr:postcode":"30518",
    "addr:street":"Williams St",
    "iso:country":"US",
    "sg:address":"486 Williams St",
    "sg:city":"Buford",
    "sg:classifiers":[
        {
            "category":"Professional",
            "subcategory":"Secretarial Services",
            "type":"Services"
        }
    ],
    "sg:phone":"+1 770 831 0936",
    "sg:postcode":"30518",
    "sg:province":"GA",
    "sg:tags":[
        "transcription",
        "medical"
    ],
    "wof:name":"Diversified Transcription Svcs",
    "wof:placetype":"venue"
},
  "geometry": {"coordinates":[-83.99789199999999,34.120028],"type":"Point"}
}