{
  "type": "Feature",
  "properties": {
    "iso:country":"US",
    "sg:address":"292 Pike Dr",
    "sg:city":"Ellerslie",
    "sg:classifiers":[
        {
            "category":"Insurance",
            "subcategory":"Hazard Insurance",
            "type":"Services"
        }
    ],
    "sg:phone":"+1 706 561 2109",
    "sg:postcode":"31807",
    "sg:province":"GA",
    "wof:name":"Ronald Allen Spall",
    "wof:placetype":"venue"
},
  "geometry": {"coordinates":[-84.79135599999999,32.62576],"type":"Point"}
}