{
  "type": "Feature",
  "properties": {
    "iso:country":"US",
    "sg:address":"3063 Sylvan Rd",
    "sg:city":"Atlanta",
    "sg:classifiers":[
        {
            "category":"Building & Trades",
            "subcategory":"Locksmith",
            "type":"Services"
        }
    ],
    "sg:phone":"+1 678 271 6486",
    "sg:postcode":"30354",
    "sg:province":"GA",
    "sg:tags":[
        "key"
    ],
    "wof:name":"Locksmith Emergency 24 7",
    "wof:placetype":"venue"
},
  "geometry": {"coordinates":[-84.419044,33.671401],"type":"Point"}
}