{
  "type": "Feature",
  "properties": {
    "addr:full":"5155 Erin Rd SW Atlanta GA 30331",
    "addr:housenumber":"5155",
    "addr:postcode":"30331",
    "addr:street":"Erin Rd Sw",
    "iso:country":"US",
    "sg:address":"5155 Erin Rd SW",
    "sg:city":"Atlanta",
    "sg:classifiers":[
        {
            "category":"Shopping",
            "subcategory":"Used Merchandise",
            "type":"Retail Goods"
        }
    ],
    "sg:phone":"+1 404 344 5734",
    "sg:postcode":"30331",
    "sg:province":"GA",
    "wof:name":"Treadwell House",
    "wof:placetype":"venue"
},
  "geometry": {"coordinates":[-84.556262,33.690739],"type":"Point"}
}