{
  "type": "Feature",
  "properties": {
    "addr:full":"2814 Eastfield Rd Smyrna GA 30080",
    "addr:housenumber":"2814",
    "addr:postcode":"30080",
    "addr:street":"Eastfield Rd",
    "iso:country":"US",
    "sg:address":"2814 Eastfield Rd",
    "sg:city":"Smyrna",
    "sg:classifiers":[
        {
            "category":"Building & Trades",
            "subcategory":"Cleaning & Sanitation",
            "type":"Services"
        }
    ],
    "sg:phone":"+1 678 754 7455",
    "sg:postcode":"30080",
    "sg:province":"GA",
    "sg:tags":[
        "janitor"
    ],
    "wof:name":"Kennesaw Office Cleaning",
    "wof:placetype":"venue"
},
  "geometry": {"coordinates":[-84.528425,33.885252],"type":"Point"}
}