{
  "type": "Feature",
  "properties": {
    "addr:full":"2805 Peachtree Industrial Blvd Duluth GA 30097",
    "addr:housenumber":"2805",
    "addr:postcode":"30097",
    "addr:street":"Peachtree Industrial Blvd",
    "iso:country":"US",
    "sg:address":"2805 Peachtree Industrial Blvd",
    "sg:city":"Duluth",
    "sg:classifiers":[
        {
            "category":"Health Services",
            "subcategory":"Dentist",
            "type":"Services"
        }
    ],
    "sg:phone":"+1 770 476 2252",
    "sg:postcode":"30097",
    "sg:province":"GA",
    "wof:name":"Stevens James A DMD",
    "wof:placetype":"venue"
},
  "geometry": {"coordinates":[-84.117824,34.024442],"type":"Point"}
}