{
  "type": "Feature",
  "properties": {
    "addr:full":"2505 W Gordon Ave Albany GA 31707",
    "addr:housenumber":"2505",
    "addr:postcode":"31707",
    "addr:street":"W Gordon Ave",
    "iso:country":"US",
    "sg:address":"2505 W Gordon Ave",
    "sg:city":"Albany",
    "sg:classifiers":[
        {
            "category":"Wholesale",
            "subcategory":"Electrical",
            "type":"Manufacturing & Wholesale Goods"
        }
    ],
    "sg:phone":"+1 229 435 6111",
    "sg:postcode":"31707",
    "sg:province":"GA",
    "sg:tags":[
        "control"
    ],
    "sg:website":"www.johnsoncontrols.com",
    "wof:name":"Johnson Controls Inc",
    "wof:placetype":"venue"
},
  "geometry": {"coordinates":[-84.21960199999999,31.562794],"type":"Point"}
}