{
  "type": "Feature",
  "properties": {
    "addr:full":"1400 W Paces Ferry Road NW Atlanta GA 30327",
    "addr:housenumber":"1400",
    "addr:postcode":"30327",
    "addr:street":"W Paces Ferry Road Nw",
    "iso:country":"US",
    "sg:address":"1400 W Paces Ferry Road NW",
    "sg:city":"Atlanta",
    "sg:classifiers":[
        {
            "category":"Autos & Motor Vehicles",
            "subcategory":"Fuel & Gas Station",
            "type":"Retail Goods"
        },
        {
            "category":"Autos & Motor Vehicles",
            "subcategory":"Auto Supplies",
            "type":"Retail Goods"
        },
        {
            "category":"Retail",
            "subcategory":"Auto Repair",
            "type":"Services"
        }
    ],
    "sg:phone":"+1 404 237 5040",
    "sg:postcode":"30327",
    "sg:province":"GA",
    "sg:tags":[
        "tire"
    ],
    "wof:name":"Paces Ferry Exxon",
    "wof:placetype":"venue"
},
  "geometry": {"coordinates":[-84.432215,33.848569],"type":"Point"}
}