{
  "type": "Feature",
  "properties": {
    "iso:country":"US",
    "sg:address":"1550 Eldora Rd",
    "sg:city":"Ellabell",
    "sg:classifiers":[
        {
            "category":"Building & Trades",
            "subcategory":"Landscaping Services",
            "type":"Services"
        }
    ],
    "sg:phone":"+1 912 858 3693",
    "sg:postcode":"31308",
    "sg:province":"GA",
    "sg:tags":[
        "landscape",
        "contractor"
    ],
    "wof:name":"Hagan Landscape Management",
    "wof:placetype":"venue"
},
  "geometry": {"coordinates":[-81.444042,32.219013],"type":"Point"}
}