{
  "type": "Feature",
  "properties": {
    "addr:full":"645 Parsons St SW Atlanta GA 30314",
    "addr:housenumber":"645",
    "addr:postcode":"30314",
    "addr:street":"Parsons St Sw",
    "iso:country":"US",
    "sg:address":"645 Parsons St SW",
    "sg:city":"Atlanta",
    "sg:classifiers":[
        {
            "category":"Social Services",
            "type":"Services"
        }
    ],
    "sg:phone":"+1 404 524 8305",
    "sg:postcode":"30314",
    "sg:province":"GA",
    "wof:name":"Community Outreach & Service",
    "wof:placetype":"venue"
},
  "geometry": {"coordinates":[-84.41128399999999,33.751331],"type":"Point"}
}