{
  "type": "Feature",
  "properties": {
    "iso:country":"US",
    "sg:address":"2500 Lumpkin Rd",
    "sg:city":"Augusta",
    "sg:classifiers":[
        {
            "category":"Education",
            "subcategory":"School",
            "type":"Public Place"
        }
    ],
    "sg:phone":"+1 706 796 4777",
    "sg:postcode":"30906",
    "sg:province":"GA",
    "wof:name":"Richmond County Board Educatn",
    "wof:placetype":"venue"
},
  "geometry": {"coordinates":[-82.044642,33.421613],"type":"Point"}
}