{
  "type": "Feature",
  "properties": {
    "iso:country":"US",
    "sg:address":"105 Radick Dr",
    "sg:city":"Savannah",
    "sg:classifiers":[
        {
            "category":"Professional",
            "type":"Services"
        }
    ],
    "sg:phone":"+1 912 355 3900",
    "sg:postcode":"31406",
    "sg:province":"GA",
    "wof:name":"John Adam Mrrson Fundation Inc",
    "wof:placetype":"venue"
},
  "geometry": {"coordinates":[-81.03439899999999,32.002531],"type":"Point"}
}