{
  "type": "Feature",
  "properties": {
    "iso:country":"US",
    "sg:address":"114 Jacksonville Loop",
    "sg:city":"Tallapoosa",
    "sg:classifiers":[
        {
            "category":"Retail",
            "subcategory":"Auto Repair",
            "type":"Services"
        }
    ],
    "sg:phone":"+1 770 574 7191",
    "sg:postcode":"30176",
    "sg:province":"GA",
    "sg:tags":[
        "body"
    ],
    "wof:name":"Morgan Len Body Shop",
    "wof:placetype":"venue"
},
  "geometry": {"coordinates":[-85.339285,33.786056],"type":"Point"}
}