{
  "type": "Feature",
  "properties": {
    "addr:full":"1760 Marlborough Dr Atlanta GA 30350",
    "addr:housenumber":"1760",
    "addr:postcode":"30350",
    "addr:street":"Marlborough Dr",
    "iso:country":"US",
    "sg:address":"1760 Marlborough Dr",
    "sg:city":"Atlanta",
    "sg:classifiers":[
        {
            "category":"Shopping",
            "subcategory":"Jewelry",
            "type":"Retail Goods"
        }
    ],
    "sg:phone":"+1 770 394 3598",
    "sg:postcode":"30350",
    "sg:province":"GA",
    "sg:tags":[
        "designer"
    ],
    "sg:website":"www.baby-gift-jewelry.com",
    "wof:name":"Classy Creations Inc",
    "wof:placetype":"venue"
},
  "geometry": {"coordinates":[-84.31180999999999,33.972762],"type":"Point"}
}