{
  "type": "Feature",
  "properties": {
    "iso:country":"US",
    "sg:address":"506 Marion St",
    "sg:city":"Reynolds",
    "sg:classifiers":[
        {
            "category":"Banks & Credit Unions",
            "subcategory":"Bank",
            "type":"Services"
        }
    ],
    "sg:phone":"+1 478 847 2628",
    "sg:postcode":"31076",
    "sg:province":"GA",
    "sg:tags":[
        "financing"
    ],
    "wof:name":"Citizens Finance Of Reynolds",
    "wof:placetype":"venue"
},
  "geometry": {"coordinates":[-84.102357,32.558677],"type":"Point"}
}