{
  "type": "Feature",
  "properties": {
    "addr:full":"2940 Mansell Rd Alpharetta GA 30022",
    "addr:housenumber":"2940",
    "addr:postcode":"30022",
    "addr:street":"Mansell Rd",
    "iso:country":"US",
    "sg:address":"2940 Mansell Rd",
    "sg:city":"Alpharetta",
    "sg:classifiers":[
        {
            "category":"Restaurant",
            "type":"Food & Drink"
        }
    ],
    "sg:menulink":"http://www.allmenus.com/ga/roswell-alpharetta/140534-waffle-house/menu/",
    "sg:phone":"+1 706 216 2824",
    "sg:postcode":"30022",
    "sg:province":"GA",
    "sg:tags":[
        "american"
    ],
    "wof:name":"Waffle House",
    "wof:placetype":"venue"
},
  "geometry": {"coordinates":[-84.297785,34.037959],"type":"Point"}
}