{
  "type": "Feature",
  "properties": {
    "iso:country":"US",
    "sg:address":"4126 Pleasantdale Rd",
    "sg:city":"Atlanta",
    "sg:classifiers":[
        {
            "category":"Education",
            "subcategory":"Special Training",
            "type":"Public Place"
        }
    ],
    "sg:phone":"+1 770 263 0220",
    "sg:postcode":"30340",
    "sg:province":"GA",
    "sg:tags":[
        "instruction",
        "music"
    ],
    "wof:name":"Silver Star Music Studio",
    "wof:placetype":"venue"
},
  "geometry": {"coordinates":[-84.245249,33.903377],"type":"Point"}
}