{
  "type": "Feature",
  "properties": {
    "addr:full":"2655 Lake Rd Tucker GA 30084",
    "addr:housenumber":"2655",
    "addr:postcode":"30084",
    "addr:street":"Lake Rd",
    "iso:country":"US",
    "sg:address":"2655 Lake Rd",
    "sg:city":"Tucker",
    "sg:classifiers":[
        {
            "category":"Travel",
            "subcategory":"Hotels & Motels",
            "type":"Entertainment"
        }
    ],
    "sg:phone":"+1 770 414 5224",
    "sg:postcode":"30084",
    "sg:province":"GA",
    "sg:tags":[
        "membership",
        "lodging"
    ],
    "wof:name":"Alpha Delta PI Fdtn",
    "wof:placetype":"venue"
},
  "geometry": {"coordinates":[-84.241527,33.86559],"type":"Point"}
}