{
  "type": "Feature",
  "properties": {
    "addr:full":"1322 W Orange St Jesup GA 31545",
    "addr:housenumber":"1322",
    "addr:postcode":"31545",
    "addr:street":"W Orange St",
    "iso:country":"US",
    "sg:address":"1322 W Orange St",
    "sg:city":"Jesup",
    "sg:classifiers":[
        {
            "category":"Insurance",
            "subcategory":"Hazard Insurance",
            "type":"Services"
        }
    ],
    "sg:phone":"+1 912 427 9312",
    "sg:postcode":"31545",
    "sg:province":"GA",
    "wof:name":"Georgia Farm Bureau Mutual And Casualty Insurance Co",
    "wof:placetype":"venue"
},
  "geometry": {"coordinates":[-81.899461,31.614873],"type":"Point"}
}