{
  "type": "Feature",
  "properties": {
    "iso:country":"US",
    "sg:address":"700 Galleria Pkwy",
    "sg:city":"Atlanta",
    "sg:classifiers":[
        {
            "category":"Utilities",
            "subcategory":"Mobile Phone",
            "type":"Services"
        },
        {
            "category":"Shopping",
            "type":"Retail Goods"
        }
    ],
    "sg:phone":"+1 706 495 0675",
    "sg:postcode":"30339",
    "sg:province":"GA",
    "sg:tags":[
        "cellular",
        "telephone",
        "merchandise"
    ],
    "wof:name":"Vision Wireless LLC",
    "wof:placetype":"venue"
},
  "geometry": {"coordinates":[-84.46481,33.883273],"type":"Point"}
}