{
  "type": "Feature",
  "properties": {
    "addr:full":"1771 Airline Rd Mcdonough GA 30252",
    "addr:housenumber":"1771",
    "addr:postcode":"30252",
    "addr:street":"Airline Rd",
    "iso:country":"US",
    "sg:address":"1771 Airline Rd",
    "sg:city":"Mcdonough",
    "sg:classifiers":[
        {
            "category":"Farming",
            "subcategory":"Farm",
            "type":"Manufacturing & Wholesale Goods"
        },
        {
            "category":"Home & Garden",
            "subcategory":"Garden Supply",
            "type":"Retail Goods"
        }
    ],
    "sg:phone":"+1 770 957 2155",
    "sg:postcode":"30252",
    "sg:province":"GA",
    "sg:tags":[
        "nurseryman",
        "crop",
        "general"
    ],
    "wof:name":"Renfroe Valley Farms  LLC",
    "wof:placetype":"venue"
},
  "geometry": {"coordinates":[-84.099267,33.501263],"type":"Point"}
}