{
  "type": "Feature",
  "properties": {
    "addr:full":"1167 14th Pl NE Atlanta GA 30309",
    "addr:housenumber":"1167",
    "addr:postcode":"30309",
    "addr:street":"14Th Pl Ne",
    "iso:country":"US",
    "sg:address":"1167 14th Pl NE",
    "sg:city":"Atlanta",
    "sg:classifiers":[
        {
            "category":"Shopping",
            "subcategory":"Musical Instruments",
            "type":"Retail Goods"
        }
    ],
    "sg:phone":"+1 404 541 0777",
    "sg:postcode":"30309",
    "sg:province":"GA",
    "sg:tags":[
        "music",
        "dealer"
    ],
    "wof:name":"Beacon Street Music",
    "wof:placetype":"venue"
},
  "geometry": {"coordinates":[-84.379204,33.787274],"type":"Point"}
}