{
  "type": "Feature",
  "properties": {
    "iso:country":"US",
    "sg:address":"6321 U S Highway 76",
    "sg:city":"Young Harris",
    "sg:classifiers":[
        {
            "category":"Restaurant",
            "type":"Food & Drink"
        }
    ],
    "sg:menulink":"http://www.allmenus.com/ga/young-harris/243932-brasstown-valley/menu/",
    "sg:phone":"+1 800 201 3205",
    "sg:postcode":"30582",
    "sg:province":"GA",
    "sg:tags":[
        "american"
    ],
    "wof:name":"Brasstown Valley",
    "wof:placetype":"venue"
},
  "geometry": {"coordinates":[-83.846174,34.958583],"type":"Point"}
}