{
  "type": "Feature",
  "properties": {
    "addr:full":"2134 N Decatur Rd Decatur GA 30033",
    "addr:housenumber":"2134",
    "addr:postcode":"30033",
    "addr:street":"N Decatur Rd",
    "iso:country":"US",
    "sg:address":"2134 N Decatur Rd",
    "sg:city":"Decatur",
    "sg:classifiers":[
        {
            "category":"Restaurant",
            "type":"Food & Drink"
        }
    ],
    "sg:phone":"+1 404 634 1128",
    "sg:postcode":"30033",
    "sg:province":"GA",
    "sg:website":"mexicocitygourmet.com",
    "wof:name":"Mexico City Gourmet",
    "wof:placetype":"venue"
},
  "geometry": {"coordinates":[-84.304703,33.790199],"type":"Point"}
}