{
  "type": "Feature",
  "properties": {
    "iso:country":"US",
    "sg:address":"90 Shipp Rd",
    "sg:city":"Hiram",
    "sg:classifiers":[
        {
            "category":"Manufacturing",
            "subcategory":"Paper Products",
            "type":"Manufacturing & Wholesale Goods"
        }
    ],
    "sg:phone":"+1 770 943 3884",
    "sg:postcode":"30141",
    "sg:province":"GA",
    "sg:tags":[
        "mill"
    ],
    "wof:name":"Renew Your Walls",
    "wof:placetype":"venue"
},
  "geometry": {"coordinates":[-84.778526,33.832492],"type":"Point"}
}