{
  "type": "Feature",
  "properties": {
    "iso:country":"US",
    "sg:address":"3300 Buckeye Rd",
    "sg:city":"Atlanta",
    "sg:classifiers":[
        {
            "category":"Professional",
            "subcategory":"Business Services",
            "type":"Services"
        }
    ],
    "sg:phone":"+1 770 454 7273",
    "sg:postcode":"30341",
    "sg:province":"GA",
    "wof:name":"Harris Hubbard Skip Traci",
    "wof:placetype":"venue"
},
  "geometry": {"coordinates":[-84.25778699999999,33.885342],"type":"Point"}
}