{
  "type": "Feature",
  "properties": {
    "addr:full":"238 Holmes Ave Athens GA 30606",
    "addr:housenumber":"238",
    "addr:postcode":"30606",
    "addr:street":"Holmes Ave",
    "iso:country":"US",
    "sg:address":"238 Holmes Ave",
    "sg:city":"Athens",
    "sg:classifiers":[
        {
            "category":"Organizations",
            "subcategory":"Religious Organization",
            "type":"Services"
        }
    ],
    "sg:phone":"+1 706 548 4310",
    "sg:postcode":"30606",
    "sg:province":"GA",
    "wof:name":"Greater Bethel AME Church",
    "wof:placetype":"venue"
},
  "geometry": {"coordinates":[-83.39882900000001,33.921132],"type":"Point"}
}