{
  "type": "Feature",
  "properties": {
    "addr:full":"1085 Mockingbird Ln Cumming GA 30041",
    "addr:housenumber":"1085",
    "addr:postcode":"30041",
    "addr:street":"Mockingbird Ln",
    "iso:country":"US",
    "sg:address":"1085 Mockingbird Ln",
    "sg:city":"Cumming",
    "sg:classifiers":[
        {
            "category":"Manufacturing",
            "subcategory":"Printing",
            "type":"Manufacturing & Wholesale Goods"
        }
    ],
    "sg:phone":"+1 770 205 1661",
    "sg:postcode":"30041",
    "sg:province":"GA",
    "sg:tags":[
        "publishing"
    ],
    "wof:name":"Dna Makers Inc",
    "wof:placetype":"venue"
},
  "geometry": {"coordinates":[-84.114014,34.190695],"type":"Point"}
}