{
  "type": "Feature",
  "properties": {
    "addr:full":"281 Congress Pkwy Lawrenceville GA 30044",
    "addr:housenumber":"281",
    "addr:postcode":"30044",
    "addr:street":"Congress Pkwy",
    "iso:country":"US",
    "sg:address":"281 Congress Pkwy",
    "sg:city":"Lawrenceville",
    "sg:classifiers":[
        {
            "category":"Building & Trades",
            "subcategory":"Landscaping Services",
            "type":"Services"
        }
    ],
    "sg:phone":"+1 770 822 1580",
    "sg:postcode":"30044",
    "sg:province":"GA",
    "sg:tags":[
        "landscape"
    ],
    "wof:name":"Dickens Landscapes",
    "wof:placetype":"venue"
},
  "geometry": {"coordinates":[-84.03818099999999,33.917771],"type":"Point"}
}