{
  "type": "Feature",
  "properties": {
    "addr:full":"428 S Enota Dr NE Gainesville GA 30501",
    "addr:housenumber":"428",
    "addr:postcode":"30501",
    "addr:street":"S Enota Dr Ne;Ga",
    "iso:country":"US",
    "sg:address":"428 S Enota Dr NE",
    "sg:city":"Gainesville",
    "sg:classifiers":[
        {
            "category":"Banks & Credit Unions",
            "subcategory":"Bank",
            "type":"Services"
        }
    ],
    "sg:phone":"+1 770 532 0068",
    "sg:postcode":"30501",
    "sg:province":"GA",
    "sg:tags":[
        "loan"
    ],
    "wof:name":"Old World Financial",
    "wof:placetype":"venue"
},
  "geometry": {"coordinates":[-83.815462,34.308907],"type":"Point"}
}