{
  "type": "Feature",
  "properties": {
    "addr:full":"401 Fertilla St Carrollton GA 30117",
    "addr:housenumber":"401",
    "addr:postcode":"30117",
    "addr:street":"Fertilla St",
    "iso:country":"US",
    "sg:address":"401 Fertilla St",
    "sg:city":"Carrollton",
    "sg:classifiers":[
        {
            "category":"Professional",
            "type":"Services"
        }
    ],
    "sg:phone":"+1 404 209 9777",
    "sg:postcode":"30117",
    "sg:province":"GA",
    "sg:tags":[
        "establishment"
    ],
    "wof:name":"Railrunner Na Inc",
    "wof:placetype":"venue"
},
  "geometry": {"coordinates":[-85.06749000000001,33.568031],"type":"Point"}
}