{
  "type": "Feature",
  "properties": {
    "iso:country":"US",
    "sg:address":"433 Canton Rd",
    "sg:city":"Cumming",
    "sg:classifiers":[
        {
            "category":"Manufacturing",
            "subcategory":"Printing",
            "type":"Manufacturing & Wholesale Goods"
        }
    ],
    "sg:phone":"+1 770 889 3298",
    "sg:postcode":"30040",
    "sg:province":"GA",
    "sg:tags":[
        "printer"
    ],
    "wof:name":"North Georgia Reprographics",
    "wof:placetype":"venue"
},
  "geometry": {"coordinates":[-84.145612,34.214121],"type":"Point"}
}