{
  "type": "Feature",
  "properties": {
    "iso:country":"US",
    "sg:address":"210 Carol St",
    "sg:city":"Waycross",
    "sg:classifiers":[
        {
            "category":"Professional",
            "type":"Services"
        }
    ],
    "sg:phone":"+1 912 285 5013",
    "sg:postcode":"31501",
    "sg:province":"GA",
    "wof:name":"Christopher Hackett",
    "wof:placetype":"venue"
},
  "geometry": {"coordinates":[-82.331521,31.234786],"type":"Point"}
}