{
  "type": "Feature",
  "properties": {
    "iso:country":"US",
    "sg:address":"284 State Rte 314",
    "sg:city":"Fayetteville",
    "sg:classifiers":[
        {
            "category":"Personal",
            "subcategory":"Beauty Salon",
            "type":"Services"
        }
    ],
    "sg:phone":"+1 770 461 4001",
    "sg:postcode":"30214",
    "sg:province":"GA",
    "wof:name":"Polonia",
    "wof:placetype":"venue"
},
  "geometry": {"coordinates":[-84.449669,33.473438],"type":"Point"}
}