{
  "type": "Feature",
  "properties": {
    "addr:full":"1750 Powder Springs St S Marietta GA 30064",
    "addr:housenumber":"1750",
    "addr:postcode":"30064",
    "addr:street":"Powder Springs St S",
    "iso:country":"US",
    "sg:address":"1750 Powder Springs St S",
    "sg:city":"Marietta",
    "sg:classifiers":[
        {
            "category":"Insurance",
            "subcategory":"Insurance Agent",
            "type":"Services"
        }
    ],
    "sg:phone":"+1 770 426 1932",
    "sg:postcode":"30064",
    "sg:province":"GA",
    "wof:name":"Allstate Insurance",
    "wof:placetype":"venue"
},
  "geometry": {"coordinates":[-84.605559,33.902048],"type":"Point"}
}