{
  "type": "Feature",
  "properties": {
    "addr:full":"1791 Harper St NW Atlanta GA 30318",
    "addr:housenumber":"1791",
    "addr:postcode":"30318",
    "addr:street":"Harper St Nw",
    "iso:country":"US",
    "sg:address":"1791 Harper St NW",
    "sg:city":"Atlanta",
    "sg:classifiers":[
        {
            "category":"Professional",
            "subcategory":"Art Services",
            "type":"Services"
        }
    ],
    "sg:phone":"+1 404 808 4825",
    "sg:postcode":"30318",
    "sg:province":"GA",
    "sg:tags":[
        "graphic",
        "designer"
    ],
    "wof:name":"Unit B Creative",
    "wof:placetype":"venue"
},
  "geometry": {"coordinates":[-84.419843,33.804582],"type":"Point"}
}