{
  "type": "Feature",
  "properties": {
    "addr:full":"2100 Riveredge Pkwy NW Atlanta GA 30328",
    "addr:housenumber":"2100",
    "addr:postcode":"30328",
    "addr:street":"Riveredge Pkwy Nw",
    "iso:country":"US",
    "sg:address":"2100 Riveredge Pkwy NW",
    "sg:city":"Atlanta",
    "sg:classifiers":[
        {
            "category":"Professional",
            "subcategory":"Business Services",
            "type":"Services"
        }
    ],
    "sg:phone":"+1 770 738 2147",
    "sg:postcode":"30328",
    "sg:province":"GA",
    "wof:name":"Highland Advisors",
    "wof:placetype":"venue"
},
  "geometry": {"coordinates":[-84.438748,33.909986],"type":"Point"}
}