{
  "type": "Feature",
  "properties": {
    "iso:country":"US",
    "sg:address":"7409 Taylor Rd",
    "sg:city":"Riverdale",
    "sg:classifiers":[
        {
            "category":"Real Estate",
            "subcategory":"Real Estate Agent",
            "type":"Services"
        }
    ],
    "sg:phone":"+1 770 478 1726",
    "sg:postcode":"30274",
    "sg:province":"GA",
    "wof:name":"Dedicated Realty Services",
    "wof:placetype":"venue"
},
  "geometry": {"coordinates":[-84.401984,33.551128],"type":"Point"}
}