{
  "type": "Feature",
  "properties": {
    "addr:full":"215 Robinson Dr Fayetteville GA 30214",
    "addr:housenumber":"215",
    "addr:postcode":"30214",
    "addr:street":"Robinson Dr",
    "iso:country":"US",
    "sg:address":"215 Robinson Dr",
    "sg:city":"Fayetteville",
    "sg:classifiers":[
        {
            "category":"Building & Trades",
            "subcategory":"Locksmith",
            "type":"Services"
        }
    ],
    "sg:phone":"+1 877 697 1686",
    "sg:postcode":"30214",
    "sg:province":"GA",
    "sg:tags":[
        "key"
    ],
    "wof:name":"7 Day 24 Hour Emergency Locksmith",
    "wof:placetype":"venue"
},
  "geometry": {"coordinates":[-84.430126,33.455059],"type":"Point"}
}