{
  "type": "Feature",
  "properties": {
    "iso:country":"US",
    "sg:address":"1992 Winterville Rd",
    "sg:city":"Athens",
    "sg:classifiers":[
        {
            "category":"Organizations",
            "subcategory":"Religious Organization",
            "type":"Services"
        }
    ],
    "sg:phone":"+1 706 546 1000",
    "sg:postcode":"30683",
    "sg:province":"GA",
    "wof:name":"First Pentecostal Church",
    "wof:placetype":"venue"
},
  "geometry": {"coordinates":[-83.321265,33.955933],"type":"Point"}
}