{
  "type": "Feature",
  "properties": {
    "iso:country":"US",
    "sg:address":"120 Declaration Dr",
    "sg:city":"Mcdonough",
    "sg:classifiers":[
        {
            "category":"Freight",
            "type":"Transportation"
        }
    ],
    "sg:phone":"+1 770 305 9693",
    "sg:postcode":"30253",
    "sg:province":"GA",
    "sg:tags":[
        "warehouse",
        "merchandise"
    ],
    "wof:name":"K W Plastics Warehouse",
    "wof:placetype":"venue"
},
  "geometry": {"coordinates":[-84.16295100000001,33.397705],"type":"Point"}
}