{
  "type": "Feature",
  "properties": {
    "iso:country":"US",
    "sg:address":"2145 Cobb Pkwy SE",
    "sg:city":"Smyrna",
    "sg:classifiers":[
        {
            "category":"Autos & Motor Vehicles",
            "subcategory":"Automobile Sales",
            "type":"Retail Goods"
        },
        {
            "category":"Retail",
            "subcategory":"Auto Repair",
            "type":"Services"
        }
    ],
    "sg:phone":"+1 770 952 8881",
    "sg:postcode":"30080",
    "sg:province":"GA",
    "sg:tags":[
        "car"
    ],
    "wof:name":"Ed Voyles Subaru",
    "wof:placetype":"venue"
},
  "geometry": {"coordinates":[-84.483101,33.898499],"type":"Point"}
}