{
  "type": "Feature",
  "properties": {
    "addr:full":"1420 S Hairston Rd Stone Mountain GA 30088",
    "addr:housenumber":"1420",
    "addr:postcode":"30088",
    "addr:street":"S Hairston Rd",
    "iso:country":"US",
    "sg:address":"1420 S Hairston Rd",
    "sg:city":"Stone Mountain",
    "sg:classifiers":[
        {
            "category":"Real Estate",
            "subcategory":"Real Estate Operator",
            "type":"Services"
        }
    ],
    "sg:phone":"+1 770 593 0424",
    "sg:postcode":"30088",
    "sg:province":"GA",
    "sg:tags":[
        "apartment"
    ],
    "sg:website":"www.landmarkresidentialapts.com/...",
    "wof:name":"The Reserve at Stone Creek",
    "wof:placetype":"venue"
},
  "geometry": {"coordinates":[-84.196941,33.754002],"type":"Point"}
}