{
  "type": "Feature",
  "properties": {
    "addr:full":"929 Mountain Industrial Dr NW Marietta GA 30060",
    "addr:housenumber":"929",
    "addr:postcode":"30060",
    "addr:street":"Mountain Industrial Dr Nw",
    "iso:country":"US",
    "sg:address":"929 Mountain Industrial Dr NW",
    "sg:city":"Marietta",
    "sg:classifiers":[
        {
            "category":"Manufacturing",
            "subcategory":"Tools & Machinery",
            "type":"Manufacturing & Wholesale Goods"
        }
    ],
    "sg:phone":"+1 770 792 7790",
    "sg:postcode":"30060",
    "sg:province":"GA",
    "sg:tags":[
        "provide",
        "utility"
    ],
    "wof:name":"Bermex",
    "wof:placetype":"venue"
},
  "geometry": {"coordinates":[-84.576562,33.986003],"type":"Point"}
}