{
  "type": "Feature",
  "properties": {
    "addr:full":"5575 Mableton Pkwy SW Mableton GA 30126",
    "addr:housenumber":"5575",
    "addr:postcode":"30126",
    "addr:street":"Mableton Pkwy Sw",
    "iso:country":"US",
    "sg:address":"5575 Mableton Pkwy SW",
    "sg:city":"Mableton",
    "sg:classifiers":[
        {
            "category":"Health Services",
            "subcategory":"Doctor",
            "type":"Services"
        },
        {
            "category":"Health Services",
            "subcategory":"Chiropractor",
            "type":"Services"
        }
    ],
    "sg:phone":"+1 770 944 2300",
    "sg:postcode":"30126",
    "sg:province":"GA",
    "wof:name":"Underset Craig MD",
    "wof:placetype":"venue"
},
  "geometry": {"coordinates":[-84.575975,33.818128],"type":"Point"}
}