{
  "type": "Feature",
  "properties": {
    "iso:country":"US",
    "sg:address":"1815 Hembree Rd",
    "sg:city":"Alpharetta",
    "sg:classifiers":[
        {
            "category":"Building & Trades",
            "subcategory":"Construction",
            "type":"Services"
        }
    ],
    "sg:phone":"+1 770 754 0780",
    "sg:postcode":"30009",
    "sg:province":"GA",
    "sg:tags":[
        "contractor"
    ],
    "wof:name":"J T L Landscape Service",
    "wof:placetype":"venue"
},
  "geometry": {"coordinates":[-84.306111,34.060753],"type":"Point"}
}