{
  "type": "Feature",
  "properties": {
    "iso:country":"US",
    "sg:address":"103 S Main St",
    "sg:city":"Hinesville",
    "sg:classifiers":[
        {
            "category":"Insurance",
            "subcategory":"Insurance Agent",
            "type":"Services"
        }
    ],
    "sg:phone":"+1 912 369 5217",
    "sg:postcode":"31321",
    "sg:province":"GA",
    "wof:name":"AFLAC",
    "wof:placetype":"venue"
},
  "geometry": {"coordinates":[-81.62263799999999,32.134435],"type":"Point"}
}