{
  "type": "Feature",
  "properties": {
    "iso:country":"US",
    "sg:address":"2615 Bankhead Hwy NW",
    "sg:city":"Atlanta",
    "sg:classifiers":[
        {
            "category":"Autos & Motor Vehicles",
            "subcategory":"Auto Supplies",
            "type":"Retail Goods"
        }
    ],
    "sg:phone":"+1 404 792 4105",
    "sg:postcode":"30318",
    "sg:province":"GA",
    "sg:tags":[
        "automobile",
        "parts"
    ],
    "wof:name":"Advance Auto Parts Inc",
    "wof:placetype":"venue"
},
  "geometry": {"coordinates":[-84.472256,33.775653],"type":"Point"}
}