{
  "type": "Feature",
  "properties": {
    "addr:full":"2605 Bomar Rd Douglasville GA 30135",
    "addr:housenumber":"2605",
    "addr:postcode":"30135",
    "addr:street":"Bomar Rd",
    "iso:country":"US",
    "sg:address":"2605 Bomar Rd",
    "sg:city":"Douglasville",
    "sg:classifiers":[
        {
            "category":"Home & Garden",
            "subcategory":"Building Materials",
            "type":"Retail Goods"
        },
        {
            "category":"Insurance",
            "subcategory":"Insurance Agent",
            "type":"Services"
        }
    ],
    "sg:phone":"+1 770 920 9591",
    "sg:postcode":"30135",
    "sg:province":"GA",
    "sg:tags":[
        "door"
    ],
    "wof:name":"T & T Millwork Installations",
    "wof:placetype":"venue"
},
  "geometry": {"coordinates":[-84.68649499999999,33.731558],"type":"Point"}
}