{
  "type": "Feature",
  "properties": {
    "addr:full":"6126 Industrial Site Cir Toccoa GA 30577",
    "addr:housenumber":"6126",
    "addr:postcode":"30577",
    "addr:street":"Industrial Site Cir",
    "iso:country":"US",
    "sg:address":"6126 Industrial Site Cir",
    "sg:city":"Toccoa",
    "sg:classifiers":[
        {
            "category":"Manufacturing",
            "subcategory":"Furniture",
            "type":"Manufacturing & Wholesale Goods"
        }
    ],
    "sg:phone":"+1 706 282 1307",
    "sg:postcode":"30577",
    "sg:province":"GA",
    "wof:name":"Heavy Wood Furniture Co Inc",
    "wof:placetype":"venue"
},
  "geometry": {"coordinates":[-83.31697699999999,34.556321],"type":"Point"}
}