{
  "type": "Feature",
  "properties": {
    "iso:country":"US",
    "sg:address":"3379 Woodtree Ln",
    "sg:city":"Buford",
    "sg:classifiers":[
        {
            "category":"Sports & Exercise",
            "subcategory":"Golf",
            "type":"Entertainment"
        }
    ],
    "sg:phone":"+1 770 932 0501",
    "sg:postcode":"30519",
    "sg:province":"GA",
    "sg:tags":[
        "course",
        "public"
    ],
    "wof:name":"Victoria Park",
    "wof:placetype":"venue"
},
  "geometry": {"coordinates":[-83.93444700000001,34.093563],"type":"Point"}
}