{
  "type": "Feature",
  "properties": {
    "iso:country":"US",
    "sg:address":"1070 S Dogwood Dr",
    "sg:city":"Nashville",
    "sg:classifiers":[
        {
            "category":"Real Estate",
            "subcategory":"Real Estate Agent",
            "type":"Services"
        }
    ],
    "sg:phone":"+1 229 543 1510",
    "sg:postcode":"31639",
    "sg:province":"GA",
    "wof:name":"Dogwood Real Estate Services",
    "wof:placetype":"venue"
},
  "geometry": {"coordinates":[-83.260712,31.194746],"type":"Point"}
}