{
  "type": "Feature",
  "properties": {
    "iso:country":"US",
    "sg:address":"10 Huntington Rd",
    "sg:city":"Athens",
    "sg:classifiers":[
        {
            "category":"Coffee & Tea",
            "type":"Food & Drink"
        }
    ],
    "sg:menulink":"http://www.allmenus.com/ga/bogart/107980-starbucks-coffee/menu/",
    "sg:phone":"+1 706 353 6632",
    "sg:postcode":"30606",
    "sg:province":"GA",
    "sg:tags":[
        "american"
    ],
    "wof:name":"Starbucks Coffee",
    "wof:placetype":"venue"
},
  "geometry": {"coordinates":[-83.464961,33.939708],"type":"Point"}
}