{
  "type": "Feature",
  "properties": {
    "addr:full":"1 Glenlake Pkwy NE Atlanta GA 30328",
    "addr:housenumber":"1",
    "addr:postcode":"30328",
    "addr:street":"Glenlake Pkwy Ne",
    "iso:country":"US",
    "sg:address":"1 Glenlake Pkwy NE",
    "sg:city":"Atlanta",
    "sg:classifiers":[
        {
            "category":"Banks & Credit Unions",
            "subcategory":"Bank",
            "type":"Services"
        }
    ],
    "sg:phone":"+1 678 638 6138",
    "sg:postcode":"30328",
    "sg:province":"GA",
    "wof:name":"Afinity Banking",
    "wof:placetype":"venue"
},
  "geometry": {"coordinates":[-84.36143800000001,33.934653],"type":"Point"}
}