{
  "type": "Feature",
  "properties": {
    "iso:country":"US",
    "sg:address":"5700 Holloman Road",
    "sg:city":"Powder Springs",
    "sg:classifiers":[
        {
            "category":"Sports & Exercise",
            "subcategory":"Stables",
            "type":"Entertainment"
        }
    ],
    "sg:phone":"+1 770 894 9849",
    "sg:postcode":"30127",
    "sg:province":"GA",
    "sg:tags":[
        "riding",
        "horseback"
    ],
    "sg:website":"www.dreambigequestrian.com",
    "wof:name":"Dream Big Equestrian",
    "wof:placetype":"venue"
},
  "geometry": {"coordinates":[-84.691551,33.815711],"type":"Point"}
}