{
  "type": "Feature",
  "properties": {
    "iso:country":"US",
    "sg:address":"2755 Cambridge Hills Rd",
    "sg:city":"Cumming",
    "sg:classifiers":[
        {
            "category":"Building & Trades",
            "subcategory":"Construction",
            "type":"Services"
        }
    ],
    "sg:phone":"+1 770 887 5194",
    "sg:postcode":"30041",
    "sg:province":"GA",
    "sg:tags":[
        "house"
    ],
    "wof:name":"Rv Renovation",
    "wof:placetype":"venue"
},
  "geometry": {"coordinates":[-84.11236700000001,34.149359],"type":"Point"}
}