{
  "type": "Feature",
  "properties": {
    "addr:full":"678 Stagecoach Rd Stockbridge GA 30281",
    "addr:housenumber":"678",
    "addr:postcode":"30281",
    "addr:street":"Stagecoach Rd",
    "iso:country":"US",
    "sg:address":"678 Stagecoach Rd",
    "sg:city":"Stockbridge",
    "sg:classifiers":[
        {
            "category":"Organizations",
            "subcategory":"Religious Organization",
            "type":"Services"
        }
    ],
    "sg:phone":"+1 770 474 3482",
    "sg:postcode":"30281",
    "sg:province":"GA",
    "wof:name":"Pine Grove Baptist Church",
    "wof:placetype":"venue"
},
  "geometry": {"coordinates":[-84.24047400000001,33.575704],"type":"Point"}
}