{
  "type": "Feature",
  "properties": {
    "iso:country":"US",
    "sg:address":"3905 Vanderbilt Dr",
    "sg:city":"Albany",
    "sg:classifiers":[
        {
            "category":"Professional",
            "type":"Services"
        }
    ],
    "sg:phone":"+1 229 883 7722",
    "sg:postcode":"31721",
    "sg:province":"GA",
    "wof:name":"US 19 Co Op Resources Inc",
    "wof:placetype":"venue"
},
  "geometry": {"coordinates":[-84.242482,31.488684],"type":"Point"}
}