{
  "type": "Feature",
  "properties": {
    "iso:country":"US",
    "sg:address":"510 Martin Luther King Jr Blvd",
    "sg:city":"Savannah",
    "sg:classifiers":[
        {
            "category":"Education",
            "subcategory":"Dance Studio",
            "type":"Public Place"
        }
    ],
    "sg:phone":"+1 912 233 0707",
    "sg:postcode":"31401",
    "sg:province":"GA",
    "sg:tags":[
        "instruction",
        "dancing"
    ],
    "wof:name":"Rebecca Padgett School Perf",
    "wof:placetype":"venue"
},
  "geometry": {"coordinates":[-81.10059,32.071377],"type":"Point"}
}