{
  "type": "Feature",
  "properties": {
    "addr:full":"5180 Roswell Rd NE Ste S201 Atlanta GA 30342",
    "addr:housenumber":"5180;rd",
    "addr:postcode":"30342",
    "addr:street":"Roswell;Ne Ste S201",
    "iso:country":"US",
    "sg:address":"5180 Roswell Rd NE Ste S201",
    "sg:city":"Atlanta",
    "sg:classifiers":[
        {
            "category":"Professional",
            "subcategory":"Lawyer & Legal Services",
            "type":"Services"
        }
    ],
    "sg:phone":"+1 404 256 3600",
    "sg:postcode":"30342",
    "sg:province":"GA",
    "wof:name":"Valente John G Atty",
    "wof:placetype":"venue"
},
  "geometry": {"coordinates":[-84.3815,33.896301],"type":"Point"}
}