{
  "type": "Feature",
  "properties": {
    "iso:country":"US",
    "sg:address":"1586 Cloverdale Dr SE",
    "sg:city":"Marietta",
    "sg:classifiers":[
        {
            "category":"Building & Trades",
            "subcategory":"Construction",
            "type":"Services"
        }
    ],
    "sg:phone":"+1 770 321 8601",
    "sg:postcode":"30067",
    "sg:province":"GA",
    "sg:tags":[
        "contractor"
    ],
    "sg:website":"www.allsouthrenovations.com",
    "wof:name":"Allsouth Renovations Inc",
    "wof:placetype":"venue"
},
  "geometry": {"coordinates":[-84.505501,33.949001],"type":"Point"}
}