{
  "type": "Feature",
  "properties": {
    "iso:country":"US",
    "sg:address":"5530 Thomaston Rd",
    "sg:city":"Macon",
    "sg:classifiers":[
        {
            "category":"Organizations",
            "subcategory":"Community Association",
            "type":"Services"
        }
    ],
    "sg:phone":"+1 478 474 7799",
    "sg:postcode":"31220",
    "sg:province":"GA",
    "sg:tags":[
        "military"
    ],
    "wof:name":"American Legion",
    "wof:placetype":"venue"
},
  "geometry": {"coordinates":[-83.742226,32.833915],"type":"Point"}
}