{
  "type": "Feature",
  "properties": {
    "addr:full":"222 Lyman Hall Savannah GA 31410",
    "addr:housenumber":"222",
    "addr:postcode":"31410",
    "addr:street":"Lyman Hall",
    "iso:country":"US",
    "sg:address":"222 Lyman Hall",
    "sg:city":"Savannah",
    "sg:classifiers":[
        {
            "category":"Professional",
            "type":"Services"
        }
    ],
    "sg:phone":"+1 912 897 3099",
    "sg:postcode":"31410",
    "sg:province":"GA",
    "wof:name":"Gail L Wright",
    "wof:placetype":"venue"
},
  "geometry": {"coordinates":[-81.024022,32.034481],"type":"Point"}
}