{
  "type": "Feature",
  "properties": {
    "addr:full":"3825 Martingale Dr SE Conyers GA 30094",
    "addr:housenumber":"3825",
    "addr:postcode":"30094",
    "addr:street":"Martingale Dr Se",
    "iso:country":"US",
    "sg:address":"3825 Martingale Dr SE",
    "sg:city":"Conyers",
    "sg:classifiers":[
        {
            "category":"Autos & Motor Vehicles",
            "subcategory":"Auto Supplies",
            "type":"Retail Goods"
        },
        {
            "category":"Wholesale",
            "subcategory":"Auto Parts",
            "type":"Manufacturing & Wholesale Goods"
        }
    ],
    "sg:phone":"+1 404 499 0080",
    "sg:postcode":"30094",
    "sg:province":"GA",
    "sg:tags":[
        "bearing",
        "bearings-wholesale"
    ],
    "wof:name":"Inf Bearing, Inc.",
    "wof:placetype":"venue"
},
  "geometry": {"coordinates":[-84.02744800000001,33.577049],"type":"Point"}
}