{
  "type": "Feature",
  "properties": {
    "iso:country":"US",
    "sg:address":"1867 Forsyth St",
    "sg:city":"Macon",
    "sg:classifiers":[
        {
            "category":"Health Services",
            "subcategory":"Doctor",
            "type":"Services"
        }
    ],
    "sg:phone":"+1 478 745 2867",
    "sg:postcode":"31201",
    "sg:province":"GA",
    "sg:tags":[
        "medical"
    ],
    "wof:name":"Gary M Carter MD",
    "wof:placetype":"venue"
},
  "geometry": {"coordinates":[-83.64769099999999,32.840384],"type":"Point"}
}