{
  "type": "Feature",
  "properties": {
    "addr:full":"389 Lumpkin County Pkwy # 100 Dahlonega GA 30533",
    "addr:housenumber":"389",
    "addr:postcode":"30533",
    "addr:street":"Lumpkin County Pkwy # 100",
    "iso:country":"US",
    "sg:address":"389 Lumpkin County Pkwy # 100",
    "sg:city":"Dahlonega",
    "sg:classifiers":[
        {
            "category":"Autos & Motor Vehicles",
            "subcategory":"Motorcycle Sales",
            "type":"Retail Goods"
        }
    ],
    "sg:phone":"+1 706 864 7800",
    "sg:postcode":"30533",
    "sg:province":"GA",
    "sg:tags":[
        "parts-wholesale",
        "scooters-supplies",
        "manufacturer"
    ],
    "sg:website":"http://www.hawghalters.com",
    "wof:name":"Hawg Halters Inc.",
    "wof:placetype":"venue"
},
  "geometry": {"coordinates":[-83.983954,34.438554],"type":"Point"}
}