{
  "type": "Feature",
  "properties": {
    "iso:country":"US",
    "sg:address":"1990 Defoor Ave NW",
    "sg:city":"Atlanta",
    "sg:classifiers":[
        {
            "category":"Retail",
            "subcategory":"Auto Repair",
            "type":"Services"
        }
    ],
    "sg:phone":"+1 404 350 1800",
    "sg:postcode":"30318",
    "sg:province":"GA",
    "sg:tags":[
        "audio-visual"
    ],
    "wof:name":"Total Audio Visual Services Inc",
    "wof:placetype":"venue"
},
  "geometry": {"coordinates":[-84.42603200000001,33.809266],"type":"Point"}
}