{
  "type": "Feature",
  "properties": {
    "iso:country":"US",
    "sg:address":"136 State Rte 300 NE",
    "sg:city":"Warwick",
    "sg:classifiers":[
        {
            "category":"Real Estate",
            "subcategory":"Real Estate Agent",
            "type":"Services"
        }
    ],
    "sg:phone":"+1 229 535 4338",
    "sg:postcode":"31796",
    "sg:province":"GA",
    "wof:name":"Ivey Real Estate",
    "wof:placetype":"venue"
},
  "geometry": {"coordinates":[-83.925388,31.833921],"type":"Point"}
}