{
  "type": "Feature",
  "properties": {
    "iso:country":"US",
    "sg:address":"962 Glen Chase Dr",
    "sg:city":"Lawrenceville",
    "sg:classifiers":[
        {
            "category":"Building & Trades",
            "subcategory":"Cleaning & Sanitation",
            "type":"Services"
        }
    ],
    "sg:phone":"+1 770 338 1496",
    "sg:postcode":"30044",
    "sg:province":"GA",
    "sg:tags":[
        "maintenance"
    ],
    "wof:name":"Jordan Building Services",
    "wof:placetype":"venue"
},
  "geometry": {"coordinates":[-84.077359,33.94785],"type":"Point"}
}