{
  "type": "Feature",
  "properties": {
    "iso:country":"US",
    "sg:address":"630 S Orange Edwards Blvd",
    "sg:city":"Kingsland",
    "sg:classifiers":[
        {
            "category":"Retail",
            "subcategory":"Auto Repair",
            "type":"Services"
        }
    ],
    "sg:phone":"+1 912 576 6899",
    "sg:postcode":"31548",
    "sg:province":"GA",
    "sg:tags":[
        "vehicle",
        "recreational",
        "general"
    ],
    "wof:name":"Henry B's Rv Repair",
    "wof:placetype":"venue"
},
  "geometry": {"coordinates":[-81.689098,30.787921],"type":"Point"}
}