{
  "type": "Feature",
  "properties": {
    "addr:full":"5150 Buford Hwy Norcross GA 30071",
    "addr:housenumber":"5150",
    "addr:postcode":"30071",
    "addr:street":"Buford Hwy",
    "iso:country":"US",
    "sg:address":"5150 Buford Hwy",
    "sg:city":"Norcross",
    "sg:classifiers":[
        {
            "category":"Education",
            "subcategory":"Kindergarten",
            "type":"Public Place"
        }
    ],
    "sg:phone":"+1 770 447 4373",
    "sg:postcode":"30071",
    "sg:province":"GA",
    "sg:tags":[
        "school",
        "driving"
    ],
    "sg:website":"www.ginadrivingschool.com",
    "wof:name":"Gina Driving School",
    "wof:placetype":"venue"
},
  "geometry": {"coordinates":[-84.194838,33.952087],"type":"Point"}
}