{
  "type": "Feature",
  "properties": {
    "iso:country":"US",
    "sg:address":"1963 Bergerac Ct SW",
    "sg:city":"Marietta",
    "sg:classifiers":[
        {
            "category":"Arts & Performance",
            "subcategory":"Theater",
            "type":"Entertainment"
        }
    ],
    "sg:phone":"+1 770 226 8335",
    "sg:postcode":"30008",
    "sg:province":"GA",
    "sg:tags":[
        "theatrical",
        "agency"
    ],
    "wof:name":"Nate Smith Entertainment",
    "wof:placetype":"venue"
},
  "geometry": {"coordinates":[-84.596486,33.904123],"type":"Point"}
}