{
  "type": "Feature",
  "properties": {
    "addr:full":"16104 Masters Way Alpharetta GA 30005",
    "addr:housenumber":"16104",
    "addr:postcode":"30005",
    "addr:street":"Masters Way",
    "iso:country":"US",
    "sg:address":"16104 Masters Way",
    "sg:city":"Alpharetta",
    "sg:classifiers":[
        {
            "category":"Professional",
            "type":"Services"
        }
    ],
    "sg:phone":"+1 770 569 1947",
    "sg:postcode":"30005",
    "sg:province":"GA",
    "wof:name":"Derek Pang",
    "wof:placetype":"venue"
},
  "geometry": {"coordinates":[-84.234021,34.094171],"type":"Point"}
}