{
  "type": "Feature",
  "properties": {
    "addr:full":"3418 N Expy Griffin GA 30223",
    "addr:housenumber":"3418",
    "addr:postcode":"30223",
    "addr:street":"N Expy",
    "iso:country":"US",
    "sg:address":"3418 N Expy",
    "sg:city":"Griffin",
    "sg:classifiers":[
        {
            "category":"Retail",
            "subcategory":"Auto Repair",
            "type":"Services"
        }
    ],
    "sg:phone":"+1 770 228 7782",
    "sg:postcode":"30223",
    "sg:province":"GA",
    "sg:tags":[
        "merchandise",
        "general"
    ],
    "wof:name":"Mid-Knight Auto Repair",
    "wof:placetype":"venue"
},
  "geometry": {"coordinates":[-84.289225,33.321114],"type":"Point"}
}