{
  "type": "Feature",
  "properties": {
    "iso:country":"US",
    "sg:address":"189 Keys Ferry Rd",
    "sg:city":"Mcdonough",
    "sg:classifiers":[
        {
            "category":"Personal",
            "subcategory":"Beauty Salon",
            "type":"Services"
        }
    ],
    "sg:phone":"+1 770 898 7991",
    "sg:postcode":"30252",
    "sg:province":"GA",
    "sg:tags":[
        "manicuring"
    ],
    "wof:name":"French Manicure",
    "wof:placetype":"venue"
},
  "geometry": {"coordinates":[-84.031811,33.436034],"type":"Point"}
}