{
  "type": "Feature",
  "properties": {
    "addr:full":"2317 Norwood Ave Savannah GA 31406",
    "addr:housenumber":"2317",
    "addr:postcode":"31406",
    "addr:street":"Norwood Ave",
    "iso:country":"US",
    "sg:address":"2317 Norwood Ave",
    "sg:city":"Savannah",
    "sg:classifiers":[
        {
            "category":"Retail",
            "subcategory":"Repair Shop",
            "type":"Services"
        }
    ],
    "sg:phone":"+1 912 354 4566",
    "sg:postcode":"31406",
    "sg:province":"GA",
    "wof:name":"Sandfly Locksmith",
    "wof:placetype":"venue"
},
  "geometry": {"coordinates":[-81.067898,31.991272],"type":"Point"}
}