{
  "type": "Feature",
  "properties": {
    "iso:country":"US",
    "sg:address":"6083 Oakbrook Pkwy",
    "sg:city":"Norcross",
    "sg:classifiers":[
        {
            "category":"Professional",
            "subcategory":"Computer Services",
            "type":"Services"
        }
    ],
    "sg:phone":"+1 770 263 0979",
    "sg:postcode":"30093",
    "sg:province":"GA",
    "sg:tags":[
        "consultant",
        "designer"
    ],
    "wof:name":"Cleaner Source Group Inc",
    "wof:placetype":"venue"
},
  "geometry": {"coordinates":[-84.203979,33.911845],"type":"Point"}
}