{
  "type": "Feature",
  "properties": {
    "iso:country":"US",
    "sg:address":"903 Peachtree St NE #500",
    "sg:city":"Atlanta",
    "sg:classifiers":[
        {
            "category":"Shopping",
            "subcategory":"Mobile Phones",
            "type":"Retail Goods"
        }
    ],
    "sg:phone":"+1 404 815 7404",
    "sg:postcode":"30309",
    "sg:province":"GA",
    "sg:website":"www.tmobile.com",
    "wof:name":"T Mobile",
    "wof:placetype":"venue"
},
  "geometry": {"coordinates":[-84.38381,33.779262],"type":"Point"}
}