{
  "type": "Feature",
  "properties": {
    "iso:country":"US",
    "sg:address":"1525 Waring Rd NW",
    "sg:city":"Dalton",
    "sg:classifiers":[
        {
            "category":"Shopping",
            "subcategory":"Department Store",
            "type":"Retail Goods"
        },
        {
            "category":"Shopping",
            "type":"Retail Goods"
        }
    ],
    "sg:phone":"+1 706 278 2003",
    "sg:postcode":"30721",
    "sg:province":"GA",
    "sg:tags":[
        "shop",
        "merchandise"
    ],
    "wof:name":"Discount Values LLC",
    "wof:placetype":"venue"
},
  "geometry": {"coordinates":[-84.96232999999999,34.801998],"type":"Point"}
}