{
  "type": "Feature",
  "properties": {
    "iso:country":"US",
    "sg:address":"2350 Cheshire Bridge Rd",
    "sg:city":"Atlanta",
    "sg:classifiers":[
        {
            "category":"Shopping",
            "subcategory":"Clothing, Apparel, & Fashions",
            "type":"Retail Goods"
        }
    ],
    "sg:phone":"+1 404 633 1711",
    "sg:postcode":"30324",
    "sg:province":"GA",
    "wof:name":"Great Bgnnngs Mtrnity Slutions",
    "wof:placetype":"venue"
},
  "geometry": {"coordinates":[-84.35138000000001,33.819694],"type":"Point"}
}