{
  "type": "Feature",
  "properties": {
    "addr:full":"1976 US Hwy 19 Dahlonega GA 30533",
    "addr:housenumber":"1976",
    "addr:postcode":"30533",
    "addr:street":"Us Hwy 19",
    "iso:country":"US",
    "sg:address":"1976 US Hwy 19",
    "sg:city":"Dahlonega",
    "sg:classifiers":[
        {
            "category":"Home & Garden",
            "subcategory":"Garden Supply",
            "type":"Retail Goods"
        }
    ],
    "sg:phone":"+1 706 864 4878",
    "sg:postcode":"30533",
    "sg:province":"GA",
    "sg:tags":[
        "engine"
    ],
    "wof:name":"Northeast Georgia Power Equip",
    "wof:placetype":"venue"
},
  "geometry": {"coordinates":[-83.97210200000001,34.506806],"type":"Point"}
}