{
  "type": "Feature",
  "properties": {
    "addr:full":"1136 Joe Louis Ave Moultrie GA 31768",
    "addr:housenumber":"1136",
    "addr:postcode":"31768",
    "addr:street":"Joe Louis Ave",
    "iso:country":"US",
    "sg:address":"1136 Joe Louis Ave",
    "sg:city":"Moultrie",
    "sg:classifiers":[
        {
            "category":"Place Of Worship",
            "subcategory":"Church",
            "type":"Public Place"
        },
        {
            "category":"Place Of Worship",
            "type":"Public Place"
        }
    ],
    "sg:phone":"+1 229 890 2076",
    "sg:postcode":"31768",
    "sg:province":"GA",
    "sg:tags":[
        "churches-interdenominational",
        "churches-various",
        "denomination"
    ],
    "wof:name":"St Matthews Overcomming C",
    "wof:placetype":"venue"
},
  "geometry": {"coordinates":[-83.801365,31.182892],"type":"Point"}
}