{
  "type": "Feature",
  "properties": {
    "addr:full":"4332 Chamblee Tucker Rd Tucker GA 30084",
    "addr:housenumber":"4332",
    "addr:postcode":"30084",
    "addr:street":"Chamblee Tucker Rd",
    "iso:country":"US",
    "sg:address":"4332 Chamblee Tucker Rd",
    "sg:city":"Tucker",
    "sg:classifiers":[
        {
            "category":"Fast Food",
            "type":"Food & Drink"
        },
        {
            "category":"Restaurant",
            "type":"Food & Drink"
        }
    ],
    "sg:phone":"+1 770 414 0651",
    "sg:postcode":"30084",
    "sg:province":"GA",
    "sg:tags":[
        "american",
        "hot",
        "hamburger",
        "dog",
        "take"
    ],
    "sg:website":"http://www.hardees.com",
    "wof:name":"Hardee's",
    "wof:placetype":"venue"
},
  "geometry": {"coordinates":[-84.21917000000001,33.880989],"type":"Point"}
}