{
  "type": "Feature",
  "properties": {
    "addr:full":"675 Peachtree St Atlanta GA 30308",
    "addr:housenumber":"675",
    "addr:postcode":"30308",
    "addr:street":"Peachtree St",
    "iso:country":"US",
    "sg:address":"675 Peachtree St",
    "sg:city":"Atlanta",
    "sg:classifiers":[
        {
            "category":"Professional",
            "subcategory":"Lawyer & Legal Services",
            "type":"Services"
        }
    ],
    "sg:phone":"+1 404 335 0737",
    "sg:postcode":"30308",
    "sg:province":"GA",
    "wof:name":"J Lloyd Nault 2d Atty",
    "wof:placetype":"venue"
},
  "geometry": {"coordinates":[-84.38477399999999,33.773678],"type":"Point"}
}