{
  "type": "Feature",
  "properties": {
    "addr:full":"2655 Dallas Hwy Marietta GA 30064",
    "addr:housenumber":"2655",
    "addr:postcode":"30064",
    "addr:street":"Dallas Hwy",
    "iso:country":"US",
    "sg:address":"2655 Dallas Hwy",
    "sg:city":"Marietta",
    "sg:classifiers":[
        {
            "category":"Wholesale",
            "subcategory":"Stationery",
            "type":"Manufacturing & Wholesale Goods"
        }
    ],
    "sg:phone":"+1 770 426 0500",
    "sg:postcode":"30064",
    "sg:province":"GA",
    "sg:tags":[
        "business",
        "form",
        "system"
    ],
    "wof:name":"Pinnacle Products & Svc",
    "wof:placetype":"venue"
},
  "geometry": {"coordinates":[-84.62500300000001,33.946052],"type":"Point"}
}