{
  "type": "Feature",
  "properties": {
    "iso:country":"US",
    "sg:address":"2 Television Cir",
    "sg:city":"Savannah",
    "sg:classifiers":[
        {
            "category":"Manufacturing",
            "subcategory":"Furniture",
            "type":"Manufacturing & Wholesale Goods"
        },
        {
            "category":"Home & Garden",
            "subcategory":"Furniture",
            "type":"Retail Goods"
        }
    ],
    "sg:phone":"+1 912 920 1620",
    "sg:postcode":"31406",
    "sg:province":"GA",
    "sg:tags":[
        "furniture-unfinished",
        "store"
    ],
    "wof:name":"House Of Wood Inc",
    "wof:placetype":"venue"
},
  "geometry": {"coordinates":[-81.12809,31.99086],"type":"Point"}
}