{
  "type": "Feature",
  "properties": {
    "addr:full":"816 Kent Rd Bowdon GA 30108",
    "addr:housenumber":"816",
    "addr:postcode":"30108",
    "addr:street":"Kent Rd",
    "iso:country":"US",
    "sg:address":"816 Kent Rd",
    "sg:city":"Bowdon",
    "sg:classifiers":[
        {
            "category":"Autos & Motor Vehicles",
            "subcategory":"Auto Supplies",
            "type":"Retail Goods"
        }
    ],
    "sg:phone":"+1 770 258 3470",
    "sg:postcode":"30108",
    "sg:province":"GA",
    "sg:tags":[
        "automobile",
        "rebuilt",
        "part",
        "supplies-used"
    ],
    "wof:name":"B & K Exhaust",
    "wof:placetype":"venue"
},
  "geometry": {"coordinates":[-85.23407899999999,33.520572],"type":"Point"}
}