{
  "type": "Feature",
  "properties": {
    "addr:full":"1718 Watson Blvd Warner Robins GA 31088",
    "addr:housenumber":"1718",
    "addr:postcode":"31088",
    "addr:street":"Watson Blvd",
    "iso:country":"US",
    "sg:address":"1718 Watson Blvd",
    "sg:city":"Warner Robins",
    "sg:classifiers":[
        {
            "category":"Shopping",
            "subcategory":"Books",
            "type":"Retail Goods"
        }
    ],
    "sg:phone":"+1 478 923 3724",
    "sg:postcode":"31088",
    "sg:province":"GA",
    "sg:tags":[
        "comic"
    ],
    "wof:name":"Last Castle",
    "wof:placetype":"venue"
},
  "geometry": {"coordinates":[-83.63564,32.618128],"type":"Point"}
}