{
  "type": "Feature",
  "properties": {
    "addr:full":"15019 US Hwy 441 Mc Intyre GA 31042",
    "addr:housenumber":"15019",
    "addr:postcode":"31042",
    "addr:street":"Us Hwy 441",
    "iso:country":"US",
    "sg:address":"15019 US Hwy 441",
    "sg:city":"Mc Intyre",
    "sg:classifiers":[
        {
            "category":"Travel",
            "subcategory":"Hotels & Motels",
            "type":"Entertainment"
        }
    ],
    "sg:phone":"+1 478 946 1111",
    "sg:postcode":"31042",
    "sg:province":"GA",
    "sg:tags":[
        "management"
    ],
    "wof:name":"Project Adventure Assessment",
    "wof:placetype":"venue"
},
  "geometry": {"coordinates":[-83.19085699999999,32.843942],"type":"Point"}
}