{
  "type": "Feature",
  "properties": {
    "addr:full":"996 Washington Ave Macon GA 31201",
    "addr:housenumber":"996",
    "addr:postcode":"31201",
    "addr:street":"Washington Ave",
    "iso:country":"US",
    "sg:address":"996 Washington Ave",
    "sg:city":"Macon",
    "sg:classifiers":[
        {
            "category":"Insurance",
            "subcategory":"Insurance Agent",
            "type":"Services"
        }
    ],
    "sg:phone":"+1 478 746 5411",
    "sg:postcode":"31201",
    "sg:province":"GA",
    "wof:name":"Sheftall & Assoc Insurance",
    "wof:placetype":"venue"
},
  "geometry": {"coordinates":[-83.63776300000001,32.838702],"type":"Point"}
}