{
  "type": "Feature",
  "properties": {
    "iso:country":"US",
    "sg:address":"1112 Anne St",
    "sg:city":"Griffin",
    "sg:classifiers":[
        {
            "category":"Wholesale",
            "subcategory":"Machinery & Supplies",
            "type":"Manufacturing & Wholesale Goods"
        }
    ],
    "sg:phone":"+1 770 227 5431",
    "sg:postcode":"30224",
    "sg:province":"GA",
    "sg:tags":[
        "mill"
    ],
    "wof:name":"Talladega McHy Sup Company-Gri",
    "wof:placetype":"venue"
},
  "geometry": {"coordinates":[-84.281876,33.231804],"type":"Point"}
}