{
  "type": "Feature",
  "properties": {
    "iso:country":"US",
    "sg:address":"3095 Canton Rd",
    "sg:city":"Marietta",
    "sg:classifiers":[
        {
            "category":"Wholesale",
            "subcategory":"Painting Supplies",
            "type":"Manufacturing & Wholesale Goods"
        }
    ],
    "sg:phone":"+1 770 427 7311",
    "sg:postcode":"30066",
    "sg:province":"GA",
    "sg:tags":[
        "wall",
        "paint",
        "coating"
    ],
    "wof:name":"Glidden Professional Paint Center",
    "wof:placetype":"venue"
},
  "geometry": {"coordinates":[-84.528425,34.02638],"type":"Point"}
}