{
  "type": "Feature",
  "properties": {
    "iso:country":"US",
    "sg:address":"6428 N Highway 29",
    "sg:city":"Palmetto",
    "sg:classifiers":[
        {
            "category":"Retail",
            "subcategory":"Auto Repair",
            "type":"Services"
        }
    ],
    "sg:phone":"+1 770 463 0020",
    "sg:postcode":"30268",
    "sg:province":"GA",
    "sg:tags":[
        "body",
        "shop"
    ],
    "wof:name":"Abr Auto Inc",
    "wof:placetype":"venue"
},
  "geometry": {"coordinates":[-84.695396,33.505501],"type":"Point"}
}