{
  "type": "Feature",
  "properties": {
    "iso:country":"US",
    "sg:address":"1189 Tony Rd",
    "sg:city":"Metter",
    "sg:classifiers":[
        {
            "category":"Social Services",
            "subcategory":"Child Care",
            "type":"Services"
        }
    ],
    "sg:phone":"+1 912 685 6177",
    "sg:postcode":"30439",
    "sg:province":"GA",
    "sg:tags":[
        "day"
    ],
    "wof:name":"Frances Home Day Care",
    "wof:placetype":"venue"
},
  "geometry": {"coordinates":[-82.08114,32.413113],"type":"Point"}
}