{
  "type": "Feature",
  "properties": {
    "addr:full":"218 Mayfield Cir Alpharetta GA 30004",
    "addr:housenumber":"218",
    "addr:postcode":"30004",
    "addr:street":"Mayfield Cir",
    "iso:country":"US",
    "sg:address":"218 Mayfield Cir",
    "sg:city":"Alpharetta",
    "sg:classifiers":[
        {
            "category":"Communications",
            "subcategory":"Film & Video Production",
            "type":"Services"
        },
        {
            "category":"Communications",
            "type":"Services"
        }
    ],
    "sg:phone":"+1 770 410 1488",
    "sg:postcode":"30004",
    "sg:province":"GA",
    "sg:tags":[
        "web",
        "design",
        "video/film"
    ],
    "sg:website":"leveltenstudios.com",
    "wof:name":"Level Ten Studios",
    "wof:placetype":"venue"
},
  "geometry": {"coordinates":[-84.304238,34.083615],"type":"Point"}
}