{
  "type": "Feature",
  "properties": {
    "iso:country":"US",
    "sg:address":"14 Cedar Rd",
    "sg:city":"Cartersville",
    "sg:classifiers":[
        {
            "category":"Manufacturing",
            "subcategory":"Textiles",
            "type":"Manufacturing & Wholesale Goods"
        }
    ],
    "sg:phone":"+1 770 386 4673",
    "sg:postcode":"30120",
    "sg:province":"GA",
    "sg:tags":[
        "mill",
        "knit",
        "outerwear"
    ],
    "wof:name":"Shepherd Manufacturing",
    "wof:placetype":"venue"
},
  "geometry": {"coordinates":[-84.82379299999999,34.194696],"type":"Point"}
}