{
  "type": "Feature",
  "properties": {
    "addr:full":"100 S Liberty St Waynesboro GA 30830",
    "addr:housenumber":"100",
    "addr:postcode":"30830",
    "addr:street":"S Liberty St",
    "iso:country":"US",
    "sg:address":"100 S Liberty St",
    "sg:city":"Waynesboro",
    "sg:classifiers":[
        {
            "category":"Restaurant",
            "type":"Food & Drink"
        }
    ],
    "sg:phone":"+1 706 554 3303",
    "sg:postcode":"30830",
    "sg:province":"GA",
    "sg:tags":[
        "style",
        "family"
    ],
    "wof:name":"Lake View Restaurant",
    "wof:placetype":"venue"
},
  "geometry": {"coordinates":[-82.00685900000001,33.078678],"type":"Point"}
}