{
  "type": "Feature",
  "properties": {
    "addr:full":"3150 Oak Leaf Ct Marietta GA 30064",
    "addr:housenumber":"3150",
    "addr:postcode":"30064",
    "addr:street":"Oak Leaf Ct",
    "iso:country":"US",
    "sg:address":"3150 Oak Leaf Ct",
    "sg:city":"Marietta",
    "sg:classifiers":[
        {
            "category":"Building & Trades",
            "subcategory":"Construction",
            "type":"Services"
        }
    ],
    "sg:phone":"+1 770 439 6711",
    "sg:postcode":"30064",
    "sg:province":"GA",
    "sg:tags":[
        "hanging",
        "contractor"
    ],
    "wof:name":"DC Sign Painting",
    "wof:placetype":"venue"
},
  "geometry": {"coordinates":[-84.63034,33.877668],"type":"Point"}
}