{
  "type": "Feature",
  "properties": {
    "iso:country":"US",
    "sg:address":"112 Oak Forest Ln",
    "sg:city":"Warner Robins",
    "sg:classifiers":[
        {
            "category":"Building & Trades",
            "subcategory":"Construction",
            "type":"Services"
        }
    ],
    "sg:phone":"+1 478 923 6512",
    "sg:postcode":"31088",
    "sg:province":"GA",
    "sg:tags":[
        "heavy",
        "concrete",
        "contractor"
    ],
    "wof:name":"David Brown Enterprises",
    "wof:placetype":"venue"
},
  "geometry": {"coordinates":[-83.634773,32.598486],"type":"Point"}
}