{
  "type": "Feature",
  "properties": {
    "addr:full":"554 Grimsley Bridge Rd Colquitt GA 39837",
    "addr:housenumber":"554",
    "addr:postcode":"39837",
    "addr:street":"Grimsley Bridge Rd",
    "iso:country":"US",
    "sg:address":"554 Grimsley Bridge Rd",
    "sg:city":"Colquitt",
    "sg:classifiers":[
        {
            "category":"Banks & Credit Unions",
            "subcategory":"Financial Services",
            "type":"Services"
        }
    ],
    "sg:phone":"+1 229 758 2033",
    "sg:postcode":"39837",
    "sg:province":"GA",
    "sg:tags":[
        "management",
        "investment"
    ],
    "wof:name":"Dhm Tech Services",
    "wof:placetype":"venue"
},
  "geometry": {"coordinates":[-84.77672,31.134051],"type":"Point"}
}