{
  "type": "Feature",
  "properties": {
    "addr:full":"416 Old Roanoke Rd Lagrange GA 30240",
    "addr:housenumber":"416",
    "addr:postcode":"30240",
    "addr:street":"Old Roanoke Rd",
    "iso:country":"US",
    "sg:address":"416 Old Roanoke Rd",
    "sg:city":"Lagrange",
    "sg:classifiers":[
        {
            "category":"Travel",
            "subcategory":"Travel Agent",
            "type":"Entertainment"
        }
    ],
    "sg:phone":"+1 770 574 4943",
    "sg:postcode":"30240",
    "sg:province":"GA",
    "sg:tags":[
        "agency",
        "services-commercial"
    ],
    "wof:name":"Superior Travel And Tour",
    "wof:placetype":"venue"
},
  "geometry": {"coordinates":[-85.118786,33.048732],"type":"Point"}
}