{
  "type": "Feature",
  "properties": {
    "addr:full":"123 Lafayette Dr Riverdale GA 30296",
    "addr:housenumber":"123",
    "addr:postcode":"30296",
    "addr:street":"Lafayette Dr",
    "iso:country":"US",
    "sg:address":"123 Lafayette Dr",
    "sg:city":"Riverdale",
    "sg:classifiers":[
        {
            "category":"Banks & Credit Unions",
            "subcategory":"Investment Brokerage",
            "type":"Services"
        }
    ],
    "sg:phone":"+1 770 460 0790",
    "sg:postcode":"30296",
    "sg:province":"GA",
    "sg:tags":[
        "advisory"
    ],
    "wof:name":"Alert Financial Services Inc",
    "wof:placetype":"venue"
},
  "geometry": {"coordinates":[-84.458011,33.536491],"type":"Point"}
}