{
  "type": "Feature",
  "properties": {
    "iso:country":"US",
    "sg:address":"1736 Monroe Dr NE",
    "sg:city":"Atlanta",
    "sg:classifiers":[
        {
            "category":"Professional",
            "subcategory":"Accounting & Tax Preparation",
            "type":"Services"
        }
    ],
    "sg:phone":"+1 404 872 1040",
    "sg:postcode":"30324",
    "sg:province":"GA",
    "sg:tags":[
        "return",
        "filing"
    ],
    "wof:name":"Perry O Lemmons & Assoc",
    "wof:placetype":"venue"
},
  "geometry": {"coordinates":[-84.37263,33.802206],"type":"Point"}
}