{
  "type": "Feature",
  "properties": {
    "addr:full":"200 Washington St SW Gainesville GA 30501",
    "addr:housenumber":"200",
    "addr:postcode":"30501",
    "addr:street":"Washington St Sw",
    "iso:country":"US",
    "sg:address":"200 Washington St SW",
    "sg:city":"Gainesville",
    "sg:classifiers":[
        {
            "category":"Sports & Exercise",
            "subcategory":"Gym",
            "type":"Entertainment"
        }
    ],
    "sg:phone":"+1 770 531 5528",
    "sg:postcode":"30501",
    "sg:province":"GA",
    "sg:tags":[
        "facility",
        "club",
        "gymnasium",
        "health",
        "fitness",
        "studio",
        "physical"
    ],
    "wof:name":"Extreme You",
    "wof:placetype":"venue"
},
  "geometry": {"coordinates":[-83.82749200000001,34.299456],"type":"Point"}
}