{
  "type": "Feature",
  "properties": {
    "addr:full":"6823 Duncan Rd Lula GA 30554",
    "addr:housenumber":"6823",
    "addr:postcode":"30554",
    "addr:street":"Duncan Rd",
    "iso:country":"US",
    "sg:address":"6823 Duncan Rd",
    "sg:city":"Lula",
    "sg:classifiers":[
        {
            "category":"Professional",
            "type":"Services"
        }
    ],
    "sg:phone":"+1 770 869 1450",
    "sg:postcode":"30554",
    "sg:province":"GA",
    "wof:name":"Trencing Turner and Pump",
    "wof:placetype":"venue"
},
  "geometry": {"coordinates":[-83.664174,34.408723],"type":"Point"}
}