{
  "type": "Feature",
  "properties": {
    "iso:country":"US",
    "sg:address":"3507 Oakview Pl",
    "sg:city":"Hephzibah",
    "sg:classifiers":[
        {
            "category":"Organizations",
            "subcategory":"Religious Organization",
            "type":"Services"
        }
    ],
    "sg:phone":"+1 706 798 0820",
    "sg:postcode":"30815",
    "sg:province":"GA",
    "wof:name":"L D S Church",
    "wof:placetype":"venue"
},
  "geometry": {"coordinates":[-82.064931,33.390518],"type":"Point"}
}