{
  "type": "Feature",
  "properties": {
    "iso:country":"US",
    "sg:address":"887 Spring St NW",
    "sg:city":"Atlanta",
    "sg:classifiers":[
        {
            "category":"Restaurant",
            "type":"Food & Drink"
        }
    ],
    "sg:menulink":"http://www.allmenus.com/ga/atlanta/244931-alluvia-at-the-cheetah/menu/",
    "sg:phone":"+1 404 892 3037",
    "sg:postcode":"30308",
    "sg:province":"GA",
    "sg:tags":[
        "burger",
        "seafood",
        "southern",
        "american",
        "new"
    ],
    "wof:name":"Alluvia At The Cheetah",
    "wof:placetype":"venue"
},
  "geometry": {"coordinates":[-84.388375,33.779079],"type":"Point"}
}