{
  "type": "Feature",
  "properties": {
    "iso:country":"US",
    "sg:address":"3014 Cusseta Rd",
    "sg:city":"Columbus",
    "sg:classifiers":[
        {
            "category":"Health Services",
            "subcategory":"Doctor",
            "type":"Services"
        }
    ],
    "sg:phone":"+1 706 682 0147",
    "sg:postcode":"31903",
    "sg:province":"GA",
    "sg:tags":[
        "clinic"
    ],
    "wof:name":"Med Care South Family Practice",
    "wof:placetype":"venue"
},
  "geometry": {"coordinates":[-84.949687,32.441797],"type":"Point"}
}