{
  "type": "Feature",
  "properties": {
    "iso:country":"US",
    "sg:address":"3141 Camp Rd",
    "sg:city":"Jasper",
    "sg:classifiers":[
        {
            "category":"Government",
            "subcategory":"Office",
            "type":"Public Place"
        }
    ],
    "sg:phone":"+1 706 253 8871",
    "sg:postcode":"30143",
    "sg:province":"GA",
    "wof:name":"Pickens County Recycling",
    "wof:placetype":"venue"
},
  "geometry": {"coordinates":[-84.448819,34.456134],"type":"Point"}
}