{
  "type": "Feature",
  "properties": {
    "addr:full":"185 Shirley Ln Jesup GA 31546",
    "addr:housenumber":"185",
    "addr:postcode":"31546",
    "addr:street":"Shirley Ln",
    "iso:country":"US",
    "sg:address":"185 Shirley Ln",
    "sg:city":"Jesup",
    "sg:classifiers":[
        {
            "category":"Building & Trades",
            "subcategory":"Pest Control",
            "type":"Services"
        }
    ],
    "sg:phone":"+1 912 427 7820",
    "sg:postcode":"31546",
    "sg:province":"GA",
    "wof:name":"Blanton Pest Control",
    "wof:placetype":"venue"
},
  "geometry": {"coordinates":[-81.88316,31.593584],"type":"Point"}
}