{
  "type": "Feature",
  "properties": {
    "addr:full":"3416 Belmont Heights Dr Gainesville GA 30507",
    "addr:housenumber":"3416",
    "addr:postcode":"30507",
    "addr:street":"Belmont Heights Dr",
    "iso:country":"US",
    "sg:address":"3416 Belmont Heights Dr",
    "sg:city":"Gainesville",
    "sg:classifiers":[
        {
            "category":"Personal",
            "subcategory":"Beauty Salon",
            "type":"Services"
        }
    ],
    "sg:phone":"+1 404 944 0198",
    "sg:postcode":"30507",
    "sg:province":"GA",
    "wof:name":"Look No More Lingerie",
    "wof:placetype":"venue"
},
  "geometry": {"coordinates":[-83.765137,34.185509],"type":"Point"}
}