{
  "type": "Feature",
  "properties": {
    "addr:full":"2343 Howe Ave Columbus GA 31903",
    "addr:housenumber":"2343",
    "addr:postcode":"31903",
    "addr:street":"Howe Ave",
    "iso:country":"US",
    "sg:address":"2343 Howe Ave",
    "sg:city":"Columbus",
    "sg:classifiers":[
        {
            "category":"Organizations",
            "subcategory":"Religious Organization",
            "type":"Services"
        }
    ],
    "sg:phone":"+1 706 689 6036",
    "sg:postcode":"31903",
    "sg:province":"GA",
    "sg:tags":[
        "church"
    ],
    "wof:name":"Southside Baptist Church Inc",
    "wof:placetype":"venue"
},
  "geometry": {"coordinates":[-84.95881300000001,32.409668],"type":"Point"}
}