{
  "type": "Feature",
  "properties": {
    "addr:full":"3280 McEver Rd Buford GA 30518",
    "addr:housenumber":"3280",
    "addr:postcode":"30518",
    "addr:street":"Mcever Rd",
    "iso:country":"US",
    "sg:address":"3280 McEver Rd",
    "sg:city":"Buford",
    "sg:classifiers":[
        {
            "category":"Real Estate",
            "subcategory":"Real Estate Services",
            "type":"Services"
        }
    ],
    "sg:phone":"+1 678 482 5654",
    "sg:postcode":"30518",
    "sg:province":"GA",
    "sg:tags":[
        "management",
        "property"
    ],
    "wof:name":"Holiday Crossing Property Management",
    "wof:placetype":"venue"
},
  "geometry": {"coordinates":[-83.973505,34.148161],"type":"Point"}
}