{
  "type": "Feature",
  "properties": {
    "addr:full":"2823 Misty Rock Cve Dacula GA 30019",
    "addr:housenumber":"2823",
    "addr:postcode":"ga 30019",
    "addr:street":"Misty Rock Cve",
    "iso:country":"US",
    "sg:address":"2823 Misty Rock Cve",
    "sg:city":"Dacula",
    "sg:classifiers":[
        {
            "category":"Professional",
            "subcategory":"Advertising",
            "type":"Services"
        }
    ],
    "sg:phone":"+1 770 330 6639",
    "sg:postcode":"30019",
    "sg:province":"GA",
    "wof:name":"Safemkt",
    "wof:placetype":"venue"
},
  "geometry": {"coordinates":[-83.915927,34.015282],"type":"Point"}
}