{
  "type": "Feature",
  "properties": {
    "addr:full":"167 Bud Hardy Rd SE Calhoun GA 30701",
    "addr:housenumber":"167 bud",
    "addr:postcode":"30701",
    "addr:street":"Hardy Rd Se",
    "iso:country":"US",
    "sg:address":"167 Bud Hardy Rd SE",
    "sg:city":"Calhoun",
    "sg:classifiers":[
        {
            "category":"Taxi",
            "type":"Transportation"
        }
    ],
    "sg:phone":"+1 706 624 0304",
    "sg:postcode":"30701",
    "sg:province":"GA",
    "sg:tags":[
        "taxicab"
    ],
    "wof:name":"Los Buenos Amigo",
    "wof:placetype":"venue"
},
  "geometry": {"coordinates":[-84.82895600000001,34.446407],"type":"Point"}
}