{
  "type": "Feature",
  "properties": {
    "addr:full":"1199 Curtis Rd Hinesville GA 31313",
    "addr:housenumber":"1199",
    "addr:postcode":"31313",
    "addr:street":"Curtis Rd",
    "iso:country":"US",
    "sg:address":"1199 Curtis Rd",
    "sg:city":"Hinesville",
    "sg:classifiers":[
        {
            "category":"Organizations",
            "subcategory":"Religious Organization",
            "type":"Services"
        }
    ],
    "sg:phone":"+1 912 369 6683",
    "sg:postcode":"31313",
    "sg:province":"GA",
    "wof:name":"Korean Mission Church",
    "wof:placetype":"venue"
},
  "geometry": {"coordinates":[-81.652051,31.830105],"type":"Point"}
}