{
  "type": "Feature",
  "properties": {
    "addr:full":"1115 Bowens Mill Rd SW Douglas GA 31533",
    "addr:housenumber":"1115",
    "addr:postcode":"31533",
    "addr:street":"Bowens Mill Rd Sw",
    "iso:country":"US",
    "sg:address":"1115 Bowens Mill Rd SW",
    "sg:city":"Douglas",
    "sg:classifiers":[
        {
            "category":"Home & Garden",
            "subcategory":"Garden Supply",
            "type":"Retail Goods"
        }
    ],
    "sg:phone":"+1 912 383 7698",
    "sg:postcode":"31533",
    "sg:province":"GA",
    "wof:name":"Garden Depot",
    "wof:placetype":"venue"
},
  "geometry": {"coordinates":[-82.867155,31.489308],"type":"Point"}
}