{
  "type": "Feature",
  "properties": {
    "addr:full":"3020 Canton Rd Marietta GA 30066",
    "addr:housenumber":"3020",
    "addr:postcode":"30066",
    "addr:street":"Canton Rd",
    "iso:country":"US",
    "sg:address":"3020 Canton Rd",
    "sg:city":"Marietta",
    "sg:classifiers":[
        {
            "category":"Personal",
            "type":"Services"
        },
        {
            "category":"Personal",
            "subcategory":"Tattoo Parlor",
            "type":"Services"
        }
    ],
    "sg:phone":"+1 770 794 0818",
    "sg:postcode":"30066",
    "sg:province":"GA",
    "sg:tags":[
        "tattooing"
    ],
    "wof:name":"Illustrator",
    "wof:placetype":"venue"
},
  "geometry": {"coordinates":[-84.52802,34.027902],"type":"Point"}
}