{
  "type": "Feature",
  "properties": {
    "addr:full":"178 Morningside Dr Jackson GA 30240",
    "addr:housenumber":"178",
    "addr:postcode":"30240",
    "addr:street":"Morningside Dr",
    "iso:country":"US",
    "sg:address":"178 Morningside Dr",
    "sg:city":"Jackson",
    "sg:classifiers":[
        {
            "category":"Building & Trades",
            "subcategory":"Landscaping Services",
            "type":"Services"
        }
    ],
    "sg:phone":"+1 770 478 7757",
    "sg:postcode":"30240",
    "sg:province":"GA",
    "sg:tags":[
        "lawn",
        "maintenance",
        "grounds"
    ],
    "wof:name":"Reliable Lawn Svc",
    "wof:placetype":"venue"
},
  "geometry": {"coordinates":[-85.07598299999999,33.02687],"type":"Point"}
}