{
  "type": "Feature",
  "properties": {
    "addr:full":"1624 Squire Dr SW Marietta GA 30008",
    "addr:housenumber":"1624",
    "addr:postcode":"30008",
    "addr:street":"Squire Dr Sw",
    "iso:country":"US",
    "sg:address":"1624 Squire Dr SW",
    "sg:city":"Marietta",
    "sg:classifiers":[
        {
            "category":"Building & Trades",
            "subcategory":"Construction",
            "type":"Services"
        }
    ],
    "sg:phone":"+1 770 435 0949",
    "sg:postcode":"30008",
    "sg:province":"GA",
    "sg:tags":[
        "house"
    ],
    "wof:name":"B&S Contracting",
    "wof:placetype":"venue"
},
  "geometry": {"coordinates":[-84.599931,33.86987],"type":"Point"}
}