{
  "type": "Feature",
  "properties": {
    "iso:country":"US",
    "sg:address":"2675 Paces Ferry Rd SE",
    "sg:city":"Atlanta",
    "sg:classifiers":[
        {
            "category":"Insurance",
            "subcategory":"Insurance Agent",
            "type":"Services"
        }
    ],
    "sg:phone":"+1 770 434 4009",
    "sg:postcode":"30339",
    "sg:province":"GA",
    "sg:tags":[
        "adjuster"
    ],
    "wof:name":"Brasher & Zweigel",
    "wof:placetype":"venue"
},
  "geometry": {"coordinates":[-84.475064,33.865423],"type":"Point"}
}