{
  "type": "Feature",
  "properties": {
    "iso:country":"US",
    "sg:address":"4860 Raley Rd",
    "sg:city":"Macon",
    "sg:classifiers":[
        {
            "category":"Home & Garden",
            "subcategory":"Building Materials",
            "type":"Retail Goods"
        }
    ],
    "sg:phone":"+1 478 477 9110",
    "sg:postcode":"31206",
    "sg:province":"GA",
    "wof:name":"Majestic Stone & Ldscp Sup LLC",
    "wof:placetype":"venue"
},
  "geometry": {"coordinates":[-83.731358,32.799973],"type":"Point"}
}