{
  "type": "Feature",
  "properties": {
    "addr:full":"1481 Hudson Bridge Rd Stockbridge GA 30281",
    "addr:housenumber":"1481",
    "addr:postcode":"30281",
    "addr:street":"Hudson Bridge Rd",
    "iso:country":"US",
    "sg:address":"1481 Hudson Bridge Rd",
    "sg:city":"Stockbridge",
    "sg:classifiers":[
        {
            "category":"Wholesale",
            "subcategory":"Machinery & Supplies",
            "type":"Manufacturing & Wholesale Goods"
        }
    ],
    "sg:phone":"+1 770 389 4711",
    "sg:postcode":"30281",
    "sg:province":"GA",
    "sg:tags":[
        "tool",
        "fastener"
    ],
    "wof:name":"Ed",
    "wof:placetype":"venue"
},
  "geometry": {"coordinates":[-84.23844699999999,33.50362],"type":"Point"}
}