{
  "type": "Feature",
  "properties": {
    "addr:full":"219 Asbury Mill Rd Cleveland GA 30528",
    "addr:housenumber":"219",
    "addr:postcode":"30528",
    "addr:street":"Asbury Mill Rd",
    "iso:country":"US",
    "sg:address":"219 Asbury Mill Rd",
    "sg:city":"Cleveland",
    "sg:classifiers":[
        {
            "category":"Structure",
            "subcategory":"Office Building",
            "type":"Public Place"
        }
    ],
    "sg:phone":"+1 706 865 4402",
    "sg:postcode":"30528",
    "sg:province":"GA",
    "sg:tags":[
        "park"
    ],
    "sg:website":"http://www.huntproperties.com",
    "wof:name":"Hunt Properties Inc",
    "wof:placetype":"venue"
},
  "geometry": {"coordinates":[-83.80019299999999,34.579046],"type":"Point"}
}