{
  "type": "Feature",
  "properties": {
    "addr:full":"1441 N Park St Carrollton GA 30117",
    "addr:housenumber":"1441",
    "addr:postcode":"30117",
    "addr:street":"N Park St",
    "iso:country":"US",
    "sg:address":"1441 N Park St",
    "sg:city":"Carrollton",
    "sg:classifiers":[
        {
            "category":"Arts & Performance",
            "subcategory":"Theater",
            "type":"Entertainment"
        }
    ],
    "sg:phone":"+1 678 520 6381",
    "sg:postcode":"30117",
    "sg:province":"GA",
    "sg:tags":[
        "live",
        "music"
    ],
    "wof:name":"D J Retro",
    "wof:placetype":"venue"
},
  "geometry": {"coordinates":[-85.088634,33.612718],"type":"Point"}
}