{
  "type": "Feature",
  "properties": {
    "addr:full":"Northeast Plaza 3285 Buford Hwy NE Atlanta GA 30329",
    "addr:housenumber":"3285",
    "addr:postcode":"30329",
    "addr:street":"Northeast;Buford Hwy Ne",
    "iso:country":"US",
    "sg:address":"Northeast Plaza 3285 Buford Hwy NE",
    "sg:city":"Atlanta",
    "sg:classifiers":[
        {
            "category":"Shopping",
            "subcategory":"Department Store",
            "type":"Retail Goods"
        },
        {
            "category":"Shopping",
            "subcategory":"Clothing, Apparel, & Fashions",
            "type":"Retail Goods"
        }
    ],
    "sg:postcode":"30329",
    "sg:province":"GA",
    "sg:tags":[
        "children's",
        "clothing"
    ],
    "wof:name":"PCX Clothing Co.",
    "wof:placetype":"venue"
},
  "geometry": {"coordinates":[-84.329131,33.842527],"type":"Point"}
}