{
  "type": "Feature",
  "properties": {
    "addr:full":"1230 Old Canton Rd Marietta GA 30062",
    "addr:housenumber":"1230",
    "addr:postcode":"30062",
    "addr:street":"Old Canton Rd",
    "iso:country":"US",
    "sg:address":"1230 Old Canton Rd",
    "sg:city":"Marietta",
    "sg:classifiers":[
        {
            "category":"Shopping",
            "subcategory":"Crafts & Fabrics",
            "type":"Retail Goods"
        }
    ],
    "sg:phone":"+1 770 973 0685",
    "sg:postcode":"30062",
    "sg:province":"GA",
    "sg:tags":[
        "sewing"
    ],
    "wof:name":"Sew & So Inc",
    "wof:placetype":"venue"
},
  "geometry": {"coordinates":[-84.46141799999999,33.979431],"type":"Point"}
}