{
  "type": "Feature",
  "properties": {
    "addr:full":"301 W Main St Swainsboro GA 30401",
    "addr:housenumber":"301",
    "addr:postcode":"30401",
    "addr:street":"W Main St",
    "iso:country":"US",
    "sg:address":"301 W Main St",
    "sg:city":"Swainsboro",
    "sg:classifiers":[
        {
            "category":"Professional",
            "subcategory":"Lawyer & Legal Services",
            "type":"Services"
        }
    ],
    "sg:phone":"+1 478 237 3050",
    "sg:postcode":"30401",
    "sg:province":"GA",
    "sg:tags":[
        "attorney"
    ],
    "wof:name":"Clay Tapley Attorney At Law",
    "wof:placetype":"venue"
},
  "geometry": {"coordinates":[-82.33832099999999,32.595126],"type":"Point"}
}