{
  "type": "Feature",
  "properties": {
    "addr:full":"627 Gainesville Hwy Blairsville GA 30512",
    "addr:housenumber":"627",
    "addr:postcode":"30512",
    "addr:street":"Gainesville Hwy",
    "iso:country":"US",
    "sg:address":"627 Gainesville Hwy",
    "sg:city":"Blairsville",
    "sg:classifiers":[
        {
            "category":"Real Estate",
            "subcategory":"Real Estate Agent",
            "type":"Services"
        }
    ],
    "sg:phone":"+1 706 835 2652",
    "sg:postcode":"30512",
    "sg:province":"GA",
    "wof:name":"Exit Realty Mtn Properties",
    "wof:placetype":"venue"
},
  "geometry": {"coordinates":[-83.950332,34.866474],"type":"Point"}
}