{
  "type": "Feature",
  "properties": {
    "iso:country":"US",
    "sg:address":"250 Colony Rd",
    "sg:city":"Dillard",
    "sg:classifiers":[
        {
            "category":"Autos & Motor Vehicles",
            "subcategory":"Automobile Sales",
            "type":"Retail Goods"
        }
    ],
    "sg:phone":"+1 706 746 5408",
    "sg:postcode":"30537",
    "sg:province":"NC",
    "sg:tags":[
        "car",
        "used",
        "dealer"
    ],
    "wof:name":"E & A Auto Sales",
    "wof:placetype":"venue"
},
  "geometry": {"coordinates":[-83.394752,34.973514],"type":"Point"}
}