{
  "type": "Feature",
  "properties": {
    "iso:country":"US",
    "sg:address":"351 Main St S",
    "sg:city":"Tifton",
    "sg:classifiers":[
        {
            "category":"Health Services",
            "subcategory":"Optometrist",
            "type":"Services"
        }
    ],
    "sg:phone":"+1 229 391 9951",
    "sg:postcode":"31794",
    "sg:province":"GA",
    "wof:name":"Mark Moore OD",
    "wof:placetype":"venue"
},
  "geometry": {"coordinates":[-83.50950899999999,31.45215],"type":"Point"}
}