{
  "type": "Feature",
  "properties": {
    "addr:full":"2575 Whitehaven Dr SW Marietta GA 30064",
    "addr:housenumber":"2575",
    "addr:postcode":"30064",
    "addr:street":"Whitehaven Dr Sw",
    "iso:country":"US",
    "sg:address":"2575 Whitehaven Dr SW",
    "sg:city":"Marietta",
    "sg:classifiers":[
        {
            "category":"Personal",
            "subcategory":"Beauty Salon",
            "type":"Services"
        }
    ],
    "sg:phone":"+1 770 439 1193",
    "sg:postcode":"30064",
    "sg:province":"GA",
    "sg:tags":[
        "hair"
    ],
    "wof:name":"True Skills Barber Shop",
    "wof:placetype":"venue"
},
  "geometry": {"coordinates":[-84.629805,33.870031],"type":"Point"}
}