{
  "type": "Feature",
  "properties": {
    "iso:country":"US",
    "sg:address":"1190 King George Blvd",
    "sg:city":"Savannah",
    "sg:classifiers":[
        {
            "category":"Building & Trades",
            "subcategory":"Construction",
            "type":"Services"
        }
    ],
    "sg:phone":"+1 912 961 9004",
    "sg:postcode":"31419",
    "sg:province":"GA",
    "sg:tags":[
        "residential"
    ],
    "wof:name":"Rande Duke Construction Inc",
    "wof:placetype":"venue"
},
  "geometry": {"coordinates":[-81.220615,31.984505],"type":"Point"}
}