{
  "type": "Feature",
  "properties": {
    "addr:full":"85 Quail Ct Cartersville GA 30120",
    "addr:housenumber":"85",
    "addr:postcode":"30120",
    "addr:street":"Quail Ct",
    "iso:country":"US",
    "sg:address":"85 Quail Ct",
    "sg:city":"Cartersville",
    "sg:classifiers":[
        {
            "category":"Retail",
            "subcategory":"Repair Shop",
            "type":"Services"
        }
    ],
    "sg:phone":"+1 770 382 0955",
    "sg:postcode":"30120",
    "sg:province":"GA",
    "sg:tags":[
        "appliance"
    ],
    "wof:name":"Appliance Repair Svc",
    "wof:placetype":"venue"
},
  "geometry": {"coordinates":[-84.799537,34.19149],"type":"Point"}
}