{
  "type": "Feature",
  "properties": {
    "addr:full":"577 Bray Rd SW Calhoun GA 30701",
    "addr:housenumber":"577",
    "addr:postcode":"30701",
    "addr:street":"Bray Rd Sw",
    "iso:country":"US",
    "sg:address":"577 Bray Rd SW",
    "sg:city":"Calhoun",
    "sg:classifiers":[
        {
            "category":"Farming",
            "subcategory":"Farm",
            "type":"Manufacturing & Wholesale Goods"
        }
    ],
    "sg:phone":"+1 706 625 5016",
    "sg:postcode":"30701",
    "sg:province":"GA",
    "wof:name":"H Farms",
    "wof:placetype":"venue"
},
  "geometry": {"coordinates":[-84.96699700000001,34.443781],"type":"Point"}
}