{
  "type": "Feature",
  "properties": {
    "iso:country":"US",
    "sg:address":"1241 Indian Trail Lilburn Rd",
    "sg:city":"Norcross",
    "sg:classifiers":[
        {
            "category":"Personal",
            "subcategory":"Tattoo Parlor",
            "type":"Services"
        }
    ],
    "sg:phone":"+1 770 806 0054",
    "sg:postcode":"30093",
    "sg:province":"GA",
    "wof:name":"Sacred Heart Tattoo 3",
    "wof:placetype":"venue"
},
  "geometry": {"coordinates":[-84.162059,33.914325],"type":"Point"}
}