{
  "type": "Feature",
  "properties": {
    "addr:full":"3610 Mars Hill Rd NW Acworth GA 30101",
    "addr:housenumber":"3610",
    "addr:postcode":"30101",
    "addr:street":"Mars Hill Rd Nw",
    "iso:country":"US",
    "sg:address":"3610 Mars Hill Rd NW",
    "sg:city":"Acworth",
    "sg:classifiers":[
        {
            "category":"Building & Trades",
            "subcategory":"Construction",
            "type":"Services"
        }
    ],
    "sg:phone":"+1 770 917 5009",
    "sg:postcode":"30101",
    "sg:province":"GA",
    "sg:tags":[
        "house"
    ],
    "wof:name":"Hobgood Construction",
    "wof:placetype":"venue"
},
  "geometry": {"coordinates":[-84.69295700000001,34.042886],"type":"Point"}
}