{
  "type": "Feature",
  "properties": {
    "iso:country":"US",
    "sg:address":"1500 Klondike Rd SW",
    "sg:city":"Conyers",
    "sg:classifiers":[
        {
            "category":"Government",
            "subcategory":"Office",
            "type":"Public Place"
        }
    ],
    "sg:phone":"+1 770 761 3020",
    "sg:postcode":"30094",
    "sg:province":"GA",
    "sg:tags":[
        "state"
    ],
    "wof:name":"Soil & Water Conservation",
    "wof:placetype":"venue"
},
  "geometry": {"coordinates":[-84.037229,33.66468],"type":"Point"}
}