{
  "type": "Feature",
  "properties": {
    "iso:country":"US",
    "sg:address":"830 Grayson Pkwy",
    "sg:city":"Grayson",
    "sg:classifiers":[
        {
            "category":"Place Of Worship",
            "subcategory":"Church",
            "type":"Public Place"
        },
        {
            "category":"Place Of Worship",
            "type":"Public Place"
        }
    ],
    "sg:phone":"+1 770 978 3001",
    "sg:postcode":"30017",
    "sg:province":"GA",
    "sg:tags":[
        "presbyterian",
        "churches-reformed"
    ],
    "wof:name":"Highlands Presbyterian Church Associate Reformed Synod",
    "wof:placetype":"venue"
},
  "geometry": {"coordinates":[-83.96756000000001,33.884789],"type":"Point"}
}