{
  "type": "Feature",
  "properties": {
    "iso:country":"US",
    "sg:address":"2234 Rawlins St",
    "sg:city":"Snellville",
    "sg:classifiers":[
        {
            "category":"Manufacturing",
            "subcategory":"Signs",
            "type":"Manufacturing & Wholesale Goods"
        }
    ],
    "sg:phone":"+1 770 979 8387",
    "sg:postcode":"30078",
    "sg:province":"GA",
    "sg:tags":[
        "specialty",
        "mfg"
    ],
    "wof:name":"A Better Sign",
    "wof:placetype":"venue"
},
  "geometry": {"coordinates":[-84.02103,33.858056],"type":"Point"}
}