{
  "type": "Feature",
  "properties": {
    "iso:country":"US",
    "sg:address":"146 Montgomery St",
    "sg:city":"Savannah",
    "sg:classifiers":[
        {
            "category":"Restaurant",
            "type":"Food & Drink"
        }
    ],
    "sg:phone":"+1 912 232 4155",
    "sg:postcode":"31401",
    "sg:province":"GA",
    "sg:tags":[
        "eating"
    ],
    "wof:name":"Ray's Famous Cafe",
    "wof:placetype":"venue"
},
  "geometry": {"coordinates":[-81.09705,32.078002],"type":"Point"}
}