{
  "type": "Feature",
  "properties": {
    "addr:full":"684 South Hairston Stone Mountain GA 30088",
    "addr:housenumber":"684",
    "addr:postcode":"30088",
    "addr:street":"South Hairston",
    "iso:country":"US",
    "sg:address":"684 South Hairston",
    "sg:city":"Stone Mountain",
    "sg:classifiers":[
        {
            "category":"Building & Trades",
            "subcategory":"Cleaning & Sanitation",
            "type":"Services"
        }
    ],
    "sg:phone":"+1 678 933 1540",
    "sg:postcode":"30088",
    "sg:province":"GA",
    "sg:tags":[
        "carpet"
    ],
    "sg:website":"eipurepridecarpetcleaning.com",
    "wof:name":"Pure Pride Carpet Cleaning & Home Improvement",
    "wof:placetype":"venue"
},
  "geometry": {"coordinates":[-84.191822,33.777866],"type":"Point"}
}