{
  "type": "Feature",
  "properties": {
    "iso:country":"US",
    "sg:address":"412 Adamson Sq",
    "sg:city":"Carrollton",
    "sg:classifiers":[
        {
            "category":"Restaurant",
            "type":"Food & Drink"
        }
    ],
    "sg:phone":"+1 770 830 8535",
    "sg:postcode":"30117",
    "sg:province":"GA",
    "wof:name":"Millers",
    "wof:placetype":"venue"
},
  "geometry": {"coordinates":[-85.075112,33.580382],"type":"Point"}
}