{
  "type": "Feature",
  "properties": {
    "iso:country":"US",
    "sg:address":"3644 Campbellton Road SW",
    "sg:city":"Atlanta",
    "sg:classifiers":[
        {
            "category":"Fast Food",
            "type":"Food & Drink"
        }
    ],
    "sg:phone":"+1 404 344 8040",
    "sg:postcode":"30331",
    "sg:province":"GA",
    "sg:tags":[
        "chicken",
        "wing"
    ],
    "sg:website":"www.wingranch.com",
    "wof:name":"Wing Depot",
    "wof:placetype":"venue"
},
  "geometry": {"coordinates":[-84.507891,33.690122],"type":"Point"}
}