{
  "type": "Feature",
  "properties": {
    "addr:full":"3700 Atlanta Hwy Athens GA 30606",
    "addr:housenumber":"3700",
    "addr:postcode":"30606",
    "addr:street":"Atlanta Hwy",
    "iso:country":"US",
    "sg:address":"3700 Atlanta Hwy",
    "sg:city":"Athens",
    "sg:classifiers":[
        {
            "category":"Shopping",
            "subcategory":"Clothing, Apparel, & Fashions",
            "type":"Retail Goods"
        }
    ],
    "sg:phone":"+1 706 613 2802",
    "sg:postcode":"30606",
    "sg:province":"GA",
    "sg:tags":[
        "lingerie"
    ],
    "wof:name":"Victoria's Secret",
    "wof:placetype":"venue"
},
  "geometry": {"coordinates":[-83.466112,33.940778],"type":"Point"}
}