{
  "type": "Feature",
  "properties": {
    "iso:country":"US",
    "sg:address":"2705 Sawnee Ave",
    "sg:city":"Buford",
    "sg:classifiers":[
        {
            "category":"Building & Trades",
            "subcategory":"Construction",
            "type":"Services"
        }
    ],
    "sg:phone":"+1 770 831 9430",
    "sg:postcode":"30518",
    "sg:province":"GA",
    "sg:tags":[
        "general",
        "contractor"
    ],
    "wof:name":"Charles Black Construction",
    "wof:placetype":"venue"
},
  "geometry": {"coordinates":[-83.981452,34.128519],"type":"Point"}
}