{
  "type": "Feature",
  "properties": {
    "addr:full":"5529 Atlanta Hwy Flowery Branch GA 30542",
    "addr:housenumber":"5529",
    "addr:postcode":"30542",
    "addr:street":"Atlanta Hwy",
    "iso:country":"US",
    "sg:address":"5529 Atlanta Hwy",
    "sg:city":"Flowery Branch",
    "sg:classifiers":[
        {
            "category":"Professional",
            "subcategory":"Business Services",
            "type":"Services"
        }
    ],
    "sg:phone":"+1 770 965 7696",
    "sg:postcode":"30542",
    "sg:province":"GA",
    "sg:tags":[
        "repossession"
    ],
    "wof:name":"3d Recovery",
    "wof:placetype":"venue"
},
  "geometry": {"coordinates":[-83.927289,34.181076],"type":"Point"}
}