{
  "type": "Feature",
  "properties": {
    "iso:country":"US",
    "sg:address":"535 Augusta Rd",
    "sg:city":"North Augusta",
    "sg:classifiers":[
        {
            "category":"Organizations",
            "subcategory":"Religious Organization",
            "type":"Services"
        }
    ],
    "sg:phone":"+1 803 442 6388",
    "sg:postcode":"29822",
    "sg:province":"SC",
    "sg:tags":[
        "church"
    ],
    "sg:website":"www.belvederechurchofchrist.org",
    "wof:name":"Belvedere Church Of Christ",
    "wof:placetype":"venue"
},
  "geometry": {"coordinates":[-81.892043,33.496713],"type":"Point"}
}