{
  "type": "Feature",
  "properties": {
    "iso:country":"US",
    "sg:address":"200 Jacquelyn St",
    "sg:city":"Hahira",
    "sg:classifiers":[
        {
            "category":"Professional",
            "type":"Services"
        }
    ],
    "sg:phone":"+1 229 794 2082",
    "sg:postcode":"31632",
    "sg:province":"GA",
    "wof:name":"Stephen Lastinger",
    "wof:placetype":"venue"
},
  "geometry": {"coordinates":[-83.36940199999999,30.987588],"type":"Point"}
}