{
  "type": "Feature",
  "properties": {
    "addr:full":"27 Woodland Rd Griffin GA 30224",
    "addr:housenumber":"27",
    "addr:postcode":"30224",
    "addr:street":"Woodland Rd",
    "iso:country":"US",
    "sg:address":"27 Woodland Rd",
    "sg:city":"Griffin",
    "sg:classifiers":[
        {
            "category":"Home & Garden",
            "subcategory":"Mobile Homes",
            "type":"Retail Goods"
        }
    ],
    "sg:phone":"+1 770 227 1084",
    "sg:postcode":"30224",
    "sg:province":"GA",
    "sg:tags":[
        "parts"
    ],
    "wof:name":"Cal's Mobile Home Svc",
    "wof:placetype":"venue"
},
  "geometry": {"coordinates":[-84.15163699999999,33.231335],"type":"Point"}
}