{
  "type": "Feature",
  "properties": {
    "addr:full":"1213 1st Ave SE Moultrie GA 31768",
    "addr:housenumber":"1213",
    "addr:postcode":"31768",
    "addr:street":"1St Ave Se",
    "iso:country":"US",
    "sg:address":"1213 1st Ave SE",
    "sg:city":"Moultrie",
    "sg:classifiers":[
        {
            "category":"Shopping",
            "subcategory":"Used Merchandise",
            "type":"Retail Goods"
        },
        {
            "category":"Shopping",
            "subcategory":"Jewelry",
            "type":"Retail Goods"
        }
    ],
    "sg:phone":"+1 229 985 7296",
    "sg:postcode":"31768",
    "sg:province":"GA",
    "sg:tags":[
        "pawnbroker"
    ],
    "wof:name":"American Pawn & Jewelry Inc",
    "wof:placetype":"venue"
},
  "geometry": {"coordinates":[-83.77341300000001,31.178747],"type":"Point"}
}