{
  "type": "Feature",
  "properties": {
    "iso:country":"US",
    "sg:address":"844 Chapman Cir",
    "sg:city":"Stone Mountain",
    "sg:classifiers":[
        {
            "category":"Organizations",
            "subcategory":"Religious Organization",
            "type":"Services"
        }
    ],
    "sg:phone":"+1 770 498 1287",
    "sg:postcode":"30088",
    "sg:province":"GA",
    "wof:name":"Keepers of The Spring Mnstries",
    "wof:placetype":"venue"
},
  "geometry": {"coordinates":[-84.17207500000001,33.763361],"type":"Point"}
}