{
  "type": "Feature",
  "properties": {
    "iso:country":"US",
    "sg:address":"1825 Gordon Hwy",
    "sg:city":"Augusta",
    "sg:classifiers":[
        {
            "category":"Home & Garden",
            "subcategory":"Building Materials",
            "type":"Retail Goods"
        }
    ],
    "sg:phone":"+1 706 733 2207",
    "sg:postcode":"30904",
    "sg:province":"GA",
    "wof:name":"Hope Lumber",
    "wof:placetype":"venue"
},
  "geometry": {"coordinates":[-82.034021,33.450471],"type":"Point"}
}