{
  "type": "Feature",
  "properties": {
    "addr:full":"210 Valley Dr Roswell GA 30075",
    "addr:housenumber":"210",
    "addr:postcode":"30075",
    "addr:street":"Valley Dr",
    "iso:country":"US",
    "sg:address":"210 Valley Dr",
    "sg:city":"Roswell",
    "sg:classifiers":[
        {
            "category":"Building & Trades",
            "subcategory":"Landscaping Services",
            "type":"Services"
        }
    ],
    "sg:phone":"+1 770 998 5549",
    "sg:postcode":"30075",
    "sg:province":"GA",
    "sg:tags":[
        "lawn",
        "maintenance"
    ],
    "wof:name":"North Fulton Lawn Service Inc",
    "wof:placetype":"venue"
},
  "geometry": {"coordinates":[-84.35378900000001,34.032966],"type":"Point"}
}