{
  "type": "Feature",
  "properties": {
    "addr:full":"560 Valley Hall Dr Atlanta GA 30350",
    "addr:housenumber":"560",
    "addr:postcode":"30350",
    "addr:street":"Valley Hall Dr",
    "iso:country":"US",
    "sg:address":"560 Valley Hall Dr",
    "sg:city":"Atlanta",
    "sg:classifiers":[
        {
            "category":"Professional",
            "subcategory":"Management & Consulting",
            "type":"Services"
        }
    ],
    "sg:phone":"+1 770 394 6741",
    "sg:postcode":"30350",
    "sg:province":"GA",
    "sg:tags":[
        "finance"
    ],
    "wof:name":"Andrews John",
    "wof:placetype":"venue"
},
  "geometry": {"coordinates":[-84.301785,33.975283],"type":"Point"}
}