{
  "type": "Feature",
  "properties": {
    "iso:country":"US",
    "sg:address":"1831 Veterans Blvd Ste D",
    "sg:city":"Dublin",
    "sg:classifiers":[
        {
            "category":"Professional",
            "subcategory":"Accounting & Tax Preparation",
            "type":"Services"
        },
        {
            "category":"Banks & Credit Unions",
            "subcategory":"Financial Services",
            "type":"Services"
        }
    ],
    "sg:phone":"+1 478 272 1609",
    "sg:postcode":"31021",
    "sg:province":"GA",
    "sg:tags":[
        "return",
        "preparation-business",
        "taxes-consultants",
        "loan",
        "reporting",
        "representative",
        "alternative",
        "bookkeeping"
    ],
    "sg:website":"http://www.hrblock.com",
    "wof:name":"H&R Block",
    "wof:placetype":"venue"
},
  "geometry": {"coordinates":[-82.937459,32.53758],"type":"Point"}
}