{
  "type": "Feature",
  "properties": {
    "iso:country":"US",
    "sg:address":"3212 Summit Springs Ct",
    "sg:city":"Loganville",
    "sg:classifiers":[
        {
            "category":"Professional",
            "type":"Services"
        }
    ],
    "sg:phone":"+1 678 344 6249",
    "sg:postcode":"30052",
    "sg:province":"GA",
    "wof:name":"GA State Govt",
    "wof:placetype":"venue"
},
  "geometry": {"coordinates":[-83.97823,33.844036],"type":"Point"}
}