{
  "type": "Feature",
  "properties": {
    "iso:country":"US",
    "sg:address":"741 Townpark Ln NW",
    "sg:city":"Kennesaw",
    "sg:classifiers":[
        {
            "category":"Food & Beverages",
            "subcategory":"Liquor & Beverages",
            "type":"Retail Goods"
        }
    ],
    "sg:phone":"+1 770 420 2434",
    "sg:postcode":"30144",
    "sg:province":"GA",
    "sg:tags":[
        "beer",
        "spirit",
        "wine"
    ],
    "wof:name":"Crown Bottle Shop",
    "wof:placetype":"venue"
},
  "geometry": {"coordinates":[-84.56849699999999,34.038601],"type":"Point"}
}