{
  "type": "Feature",
  "properties": {
    "addr:full":"400 Montgomery St Savannah GA 31401",
    "addr:housenumber":"400",
    "addr:postcode":"31401",
    "addr:street":"Montgomery St",
    "iso:country":"US",
    "sg:address":"400 Montgomery St",
    "sg:city":"Savannah",
    "sg:classifiers":[
        {
            "category":"Retail",
            "subcategory":"Laundry & Dry Cleaning",
            "type":"Services"
        }
    ],
    "sg:phone":"+1 912 232 7449",
    "sg:postcode":"31401",
    "sg:province":"GA",
    "sg:tags":[
        "drycleaning",
        "plant"
    ],
    "wof:name":"Customer One Dry Cleaners",
    "wof:placetype":"venue"
},
  "geometry": {"coordinates":[-81.098809,32.07322],"type":"Point"}
}