{
  "type": "Feature",
  "properties": {
    "iso:country":"US",
    "sg:address":"1372 Summit Ln",
    "sg:city":"Acworth",
    "sg:classifiers":[
        {
            "category":"Professional",
            "type":"Services"
        }
    ],
    "sg:phone":"+1 770 425 0135",
    "sg:postcode":"30102",
    "sg:province":"GA",
    "wof:name":"Electronic Filing Service",
    "wof:placetype":"venue"
},
  "geometry": {"coordinates":[-84.583384,34.072087],"type":"Point"}
}