{
  "type": "Feature",
  "properties": {
    "addr:full":"1433 Hiram Douglasville Hwy Hiram GA 30141",
    "addr:housenumber":"1433",
    "addr:postcode":"30141",
    "addr:street":"Hiram Douglasville Hwy",
    "iso:country":"US",
    "sg:address":"1433 Hiram Douglasville Hwy",
    "sg:city":"Hiram",
    "sg:classifiers":[
        {
            "category":"Health Services",
            "subcategory":"Chiropractor",
            "type":"Services"
        }
    ],
    "sg:phone":"+1 770 943 4872",
    "sg:postcode":"30141",
    "sg:province":"GA",
    "wof:name":"McPherson Chiropractic Inc",
    "wof:placetype":"venue"
},
  "geometry": {"coordinates":[-84.7559,33.888647],"type":"Point"}
}