{
  "type": "Feature",
  "properties": {
    "addr:full":"3822 Crest Dr Hephzibah GA 30815",
    "addr:housenumber":"3822",
    "addr:postcode":"30815",
    "addr:street":"Crest Dr",
    "iso:country":"US",
    "sg:address":"3822 Crest Dr",
    "sg:city":"Hephzibah",
    "sg:classifiers":[
        {
            "category":"Organizations",
            "subcategory":"Religious Organization",
            "type":"Services"
        }
    ],
    "sg:phone":"+1 706 793 9711",
    "sg:postcode":"30815",
    "sg:province":"GA",
    "sg:tags":[
        "church"
    ],
    "wof:name":"Rock Of Ages Baptist Church",
    "wof:placetype":"venue"
},
  "geometry": {"coordinates":[-82.107983,33.376463],"type":"Point"}
}