{
  "type": "Feature",
  "properties": {
    "iso:country":"US",
    "sg:address":"1650 Jacksonville Rd",
    "sg:city":"Union Point",
    "sg:classifiers":[
        {
            "category":"Professional",
            "type":"Services"
        }
    ],
    "sg:phone":"+1 706 486 2703",
    "sg:postcode":"30669",
    "sg:province":"GA",
    "wof:name":"C B Aletha",
    "wof:placetype":"venue"
},
  "geometry": {"coordinates":[-83.021859,33.640063],"type":"Point"}
}