{
  "type": "Feature",
  "properties": {
    "addr:full":"2 Cedar Run Atlanta GA 30350",
    "addr:housenumber":"2",
    "addr:postcode":"30350",
    "addr:street":"Cedar Run",
    "iso:country":"US",
    "sg:address":"2 Cedar Run",
    "sg:city":"Atlanta",
    "sg:classifiers":[
        {
            "category":"Professional",
            "type":"Services"
        }
    ],
    "sg:phone":"+1 678 587 1310",
    "sg:postcode":"30350",
    "sg:province":"GA",
    "wof:name":"Larry Sneed",
    "wof:placetype":"venue"
},
  "geometry": {"coordinates":[-84.345221,33.993103],"type":"Point"}
}