{
  "type": "Feature",
  "properties": {
    "iso:country":"US",
    "sg:address":"583 Mount Zion Rd",
    "sg:city":"Danielsville",
    "sg:classifiers":[
        {
            "category":"Building & Trades",
            "subcategory":"Electrical",
            "type":"Services"
        }
    ],
    "sg:phone":"+1 706 789 3525",
    "sg:postcode":"30633",
    "sg:province":"GA",
    "sg:tags":[
        "electric",
        "contractor"
    ],
    "wof:name":"Hicks Electrical Svc",
    "wof:placetype":"venue"
},
  "geometry": {"coordinates":[-83.333928,34.200984],"type":"Point"}
}