{
  "type": "Feature",
  "properties": {
    "addr:full":"5525 Bermuda Rd Stone Mountain GA 30087",
    "addr:housenumber":"5525",
    "addr:postcode":"30087",
    "addr:street":"Bermuda Rd",
    "iso:country":"US",
    "sg:address":"5525 Bermuda Rd",
    "sg:city":"Stone Mountain",
    "sg:classifiers":[
        {
            "category":"Restaurant",
            "type":"Food & Drink"
        }
    ],
    "sg:phone":"+1 770 498 5700",
    "sg:postcode":"30087",
    "sg:province":"GA",
    "sg:tags":[
        "banquet",
        "rooms"
    ],
    "sg:website":"www.stonemountainpark.com",
    "wof:name":"Stone Mountain Park",
    "wof:placetype":"venue"
},
  "geometry": {"coordinates":[-84.120535,33.821192],"type":"Point"}
}