{
  "type": "Feature",
  "properties": {
    "iso:country":"US",
    "sg:address":"205 US Hwy 341",
    "sg:city":"Lumber City",
    "sg:classifiers":[
        {
            "category":"Shopping",
            "subcategory":"Discount & Variety Stores",
            "type":"Retail Goods"
        },
        {
            "category":"Shopping",
            "subcategory":"Department Store",
            "type":"Retail Goods"
        }
    ],
    "sg:phone":"+1 912 363 1359",
    "sg:postcode":"31545",
    "sg:province":"GA",
    "sg:tags":[
        "shop"
    ],
    "wof:name":"Dollar General",
    "wof:placetype":"venue"
},
  "geometry": {"coordinates":[-81.885345,31.607134],"type":"Point"}
}