{
  "type": "Feature",
  "properties": {
    "iso:country":"US",
    "sg:address":"8049 Webb Rd",
    "sg:city":"Riverdale",
    "sg:classifiers":[
        {
            "category":"Organizations",
            "subcategory":"Religious Organization",
            "type":"Services"
        }
    ],
    "sg:phone":"+1 770 477 6464",
    "sg:postcode":"30274",
    "sg:province":"GA",
    "sg:tags":[
        "church"
    ],
    "wof:name":"Pointe South Community Church",
    "wof:placetype":"venue"
},
  "geometry": {"coordinates":[-84.41694200000001,33.533582],"type":"Point"}
}