{
  "type": "Feature",
  "properties": {
    "addr:full":"4809 Canberry Way Flowery Branch GA 30542",
    "addr:housenumber":"4809",
    "addr:postcode":"30542",
    "addr:street":"Canberry Way",
    "iso:country":"US",
    "sg:address":"4809 Canberry Way",
    "sg:city":"Flowery Branch",
    "sg:classifiers":[
        {
            "category":"Retail",
            "subcategory":"Repair Shop",
            "type":"Services"
        }
    ],
    "sg:phone":"+1 770 965 0658",
    "sg:postcode":"30542",
    "sg:province":"GA",
    "sg:tags":[
        "welding"
    ],
    "wof:name":"Farm Doctor Mechanic",
    "wof:placetype":"venue"
},
  "geometry": {"coordinates":[-83.89392700000001,34.173778],"type":"Point"}
}