{
  "type": "Feature",
  "properties": {
    "iso:country":"US",
    "sg:address":"1420 Duncan Ave",
    "sg:city":"Perry",
    "sg:classifiers":[
        {
            "category":"Home & Garden",
            "subcategory":"Furniture",
            "type":"Retail Goods"
        }
    ],
    "sg:phone":"+1 478 987 2489",
    "sg:postcode":"31069",
    "sg:province":"GA",
    "sg:tags":[
        "store"
    ],
    "wof:name":"Harper Furnishing Restorat",
    "wof:placetype":"venue"
},
  "geometry": {"coordinates":[-83.716972,32.454788],"type":"Point"}
}