{
  "type": "Feature",
  "properties": {
    "iso:country":"US",
    "sg:address":"1585 Twin Bridge Ln",
    "sg:city":"Lawrenceville",
    "sg:classifiers":[
        {
            "category":"Professional",
            "subcategory":"Engineering",
            "type":"Services"
        }
    ],
    "sg:phone":"+1 678 377 9400",
    "sg:postcode":"30043",
    "sg:province":"GA",
    "sg:tags":[
        "engineer"
    ],
    "wof:name":"L M Consultants Inc",
    "wof:placetype":"venue"
},
  "geometry": {"coordinates":[-84.046735,33.973949],"type":"Point"}
}