{
  "type": "Feature",
  "properties": {
    "addr:full":"30 Owltown Rd Ellijay GA 30536",
    "addr:housenumber":"30",
    "addr:postcode":"30536",
    "addr:street":"Owltown Rd",
    "iso:country":"US",
    "sg:address":"30 Owltown Rd",
    "sg:city":"Ellijay",
    "sg:classifiers":[
        {
            "category":"Autos & Motor Vehicles",
            "subcategory":"Automobile Sales",
            "type":"Retail Goods"
        }
    ],
    "sg:phone":"+1 706 635 2005",
    "sg:postcode":"30536",
    "sg:province":"GA",
    "sg:tags":[
        "dealers-used",
        "used",
        "cars-wholesale",
        "car"
    ],
    "wof:name":"1st Choice Automotive Group",
    "wof:placetype":"venue"
},
  "geometry": {"coordinates":[-84.456872,34.673496],"type":"Point"}
}