{
  "type": "Feature",
  "properties": {
    "iso:country":"US",
    "sg:address":"5891 New Peachtree Rd",
    "sg:city":"Atlanta",
    "sg:classifiers":[
        {
            "category":"Wholesale",
            "subcategory":"Apparel",
            "type":"Manufacturing & Wholesale Goods"
        },
        {
            "category":"Shopping",
            "subcategory":"Shoes",
            "type":"Retail Goods"
        }
    ],
    "sg:phone":"+1 770 234 0003",
    "sg:postcode":"30340",
    "sg:province":"GA",
    "sg:tags":[
        "footwear"
    ],
    "wof:name":"Granos De Oro Boots",
    "wof:placetype":"venue"
},
  "geometry": {"coordinates":[-84.28096600000001,33.90096],"type":"Point"}
}