{
  "type": "Feature",
  "properties": {
    "iso:country":"US",
    "sg:address":"1545 US Hwy 27",
    "sg:city":"Carrollton",
    "sg:classifiers":[
        {
            "category":"Professional",
            "type":"Services"
        }
    ],
    "sg:phone":"+1 770 838 9555",
    "sg:postcode":"30117",
    "sg:province":"GA",
    "wof:name":"Sunshineenterprises",
    "wof:placetype":"venue"
},
  "geometry": {"coordinates":[-85.093608,33.617264],"type":"Point"}
}