{
  "type": "Feature",
  "properties": {
    "iso:country":"US",
    "sg:address":"612 Moreland Ave SE",
    "sg:city":"Atlanta",
    "sg:classifiers":[
        {
            "category":"Building & Trades",
            "subcategory":"Construction",
            "type":"Services"
        }
    ],
    "sg:phone":"+1 404 627 5148",
    "sg:postcode":"30316",
    "sg:province":"GA",
    "sg:tags":[
        "management"
    ],
    "wof:name":"Omega Pav & Enviornmental MGT",
    "wof:placetype":"venue"
},
  "geometry": {"coordinates":[-84.349182,33.736989],"type":"Point"}
}