{
  "type": "Feature",
  "properties": {
    "iso:country":"US",
    "sg:address":"5690 Riverview Rd SE",
    "sg:city":"Mableton",
    "sg:classifiers":[
        {
            "category":"Freight",
            "type":"Transportation"
        }
    ],
    "sg:phone":"+1 404 505 0039",
    "sg:postcode":"30126",
    "sg:province":"GA",
    "sg:tags":[
        "cargo",
        "containerized"
    ],
    "wof:name":"Conex Freight Systems",
    "wof:placetype":"venue"
},
  "geometry": {"coordinates":[-84.49095800000001,33.813834],"type":"Point"}
}