{
  "type": "Feature",
  "properties": {
    "addr:full":"80 Walnut St SW Atlanta GA 30314",
    "addr:housenumber":"80",
    "addr:postcode":"30314",
    "addr:street":"Walnut St Sw",
    "iso:country":"US",
    "sg:address":"80 Walnut St SW",
    "sg:city":"Atlanta",
    "sg:classifiers":[
        {
            "category":"Shopping",
            "subcategory":"Clothing, Apparel, & Fashions",
            "type":"Retail Goods"
        }
    ],
    "sg:phone":"+1 404 221 1222",
    "sg:postcode":"30314",
    "sg:province":"GA",
    "sg:tags":[
        "clothing",
        "boys'"
    ],
    "wof:name":"Priority Male Program",
    "wof:placetype":"venue"
},
  "geometry": {"coordinates":[-84.40652300000001,33.752553],"type":"Point"}
}