{
  "type": "Feature",
  "properties": {
    "addr:full":"3920 Willowmeade Dr Snellville GA 30039",
    "addr:housenumber":"3920",
    "addr:postcode":"30039",
    "addr:street":"Willowmeade Dr",
    "iso:country":"US",
    "sg:address":"3920 Willowmeade Dr",
    "sg:city":"Snellville",
    "sg:classifiers":[
        {
            "category":"Travel",
            "subcategory":"Travel Agent",
            "type":"Entertainment"
        }
    ],
    "sg:phone":"+1 770 979 7743",
    "sg:postcode":"30039",
    "sg:province":"GA",
    "wof:name":"Soul & Spice Travel",
    "wof:placetype":"venue"
},
  "geometry": {"coordinates":[-84.05679000000001,33.824368],"type":"Point"}
}