{
  "type": "Feature",
  "properties": {
    "iso:country":"US",
    "sg:address":"1438 W Peachtree St NW",
    "sg:city":"Atlanta",
    "sg:classifiers":[
        {
            "category":"Professional",
            "subcategory":"Detective & Security Services",
            "type":"Services"
        }
    ],
    "sg:phone":"+1 404 898 1600",
    "sg:postcode":"30309",
    "sg:province":"GA",
    "sg:tags":[
        "bodyguard",
        "patrol",
        "guard"
    ],
    "wof:name":"AlliedBarton Security Services",
    "wof:placetype":"venue"
},
  "geometry": {"coordinates":[-84.387753,33.793741],"type":"Point"}
}