{
  "type": "Feature",
  "properties": {
    "iso:country":"US",
    "sg:address":"1355 Peachtree St NE # 200",
    "sg:city":"Atlanta",
    "sg:classifiers":[
        {
            "category":"Organizations",
            "subcategory":"Non-profit Organization",
            "type":"Services"
        }
    ],
    "sg:phone":"+1 404 898 2000",
    "sg:postcode":"30309",
    "sg:province":"GA",
    "sg:tags":[
        "charity",
        "foundations-educational",
        "philanthropic",
        "research"
    ],
    "wof:name":"The Windham Brannon Fnd Inc",
    "wof:placetype":"venue"
},
  "geometry": {"coordinates":[-84.385606,33.791376],"type":"Point"}
}