{
  "type": "Feature",
  "properties": {
    "iso:country":"US",
    "sg:address":"4816 Silver Lake Dr",
    "sg:city":"Evans",
    "sg:classifiers":[
        {
            "category":"Building & Trades",
            "subcategory":"Construction",
            "type":"Services"
        }
    ],
    "sg:phone":"+1 706 840 3301",
    "sg:postcode":"30809",
    "sg:province":"GA",
    "sg:tags":[
        "general",
        "contractor"
    ],
    "wof:name":"DPM Construction Svc",
    "wof:placetype":"venue"
},
  "geometry": {"coordinates":[-82.15099499999999,33.563922],"type":"Point"}
}