{
  "type": "Feature",
  "properties": {
    "iso:country":"US",
    "sg:address":"3575 Greystone Cir",
    "sg:city":"Atlanta",
    "sg:classifiers":[
        {
            "category":"Social Services",
            "subcategory":"Child Care",
            "type":"Services"
        }
    ],
    "sg:phone":"+1 770 723 0240",
    "sg:postcode":"30341",
    "sg:province":"GA",
    "sg:tags":[
        "day"
    ],
    "wof:name":"Learning Orbit Inc",
    "wof:placetype":"venue"
},
  "geometry": {"coordinates":[-84.247883,33.872061],"type":"Point"}
}