{
  "type": "Feature",
  "properties": {
    "iso:country":"US",
    "sg:address":"3012 Macon Rd",
    "sg:city":"Columbus",
    "sg:classifiers":[
        {
            "category":"Retail",
            "subcategory":"Portrait Studio",
            "type":"Services"
        }
    ],
    "sg:phone":"+1 706 562 1069",
    "sg:postcode":"31906",
    "sg:province":"GA",
    "sg:tags":[
        "photo"
    ],
    "wof:name":"Sears Portrait Studio C40",
    "wof:placetype":"venue"
},
  "geometry": {"coordinates":[-84.94646,32.478142],"type":"Point"}
}