{
  "type": "Feature",
  "properties": {
    "iso:country":"US",
    "sg:address":"1004 Mill Creek Run",
    "sg:city":"Suwanee",
    "sg:classifiers":[
        {
            "category":"Professional",
            "type":"Services"
        }
    ],
    "sg:phone":"+1 770 945 7274",
    "sg:postcode":"30024",
    "sg:province":"GA",
    "sg:tags":[
        "establishment"
    ],
    "wof:name":"Precision Piping",
    "wof:placetype":"venue"
},
  "geometry": {"coordinates":[-84.072807,34.03347],"type":"Point"}
}