{
  "type": "Feature",
  "properties": {
    "iso:country":"US",
    "sg:address":"1045 Delaware Avenue SE",
    "sg:city":"Atlanta",
    "sg:classifiers":[
        {
            "category":"Professional",
            "subcategory":"Employment Agencies",
            "type":"Services"
        }
    ],
    "sg:phone":"+1 404 622 4852",
    "sg:postcode":"30316",
    "sg:province":"GA",
    "wof:name":"Resultz",
    "wof:placetype":"venue"
},
  "geometry": {"coordinates":[-84.35203300000001,33.731812],"type":"Point"}
}