{
  "type": "Feature",
  "properties": {
    "addr:full":"4867 Helga Way Woodstock GA 30188",
    "addr:housenumber":"4867",
    "addr:postcode":"30188",
    "addr:street":"Helga Way",
    "iso:country":"US",
    "sg:address":"4867 Helga Way",
    "sg:city":"Woodstock",
    "sg:classifiers":[
        {
            "category":"Retail",
            "subcategory":"Laundry & Dry Cleaning",
            "type":"Services"
        }
    ],
    "sg:phone":"+1 770 924 2033",
    "sg:postcode":"30188",
    "sg:province":"GA",
    "sg:tags":[
        "cleaners",
        "rug",
        "carpet"
    ],
    "wof:name":"Chem-Dry A-Plus Carpet Cleaner",
    "wof:placetype":"venue"
},
  "geometry": {"coordinates":[-84.531789,34.070692],"type":"Point"}
}