{
  "type": "Feature",
  "properties": {
    "iso:country":"US",
    "sg:address":"731 Simon Park Cir",
    "sg:city":"Lawrenceville",
    "sg:classifiers":[
        {
            "category":"Professional",
            "type":"Services"
        }
    ],
    "sg:phone":"+1 678 376 9688",
    "sg:postcode":"30045",
    "sg:province":"GA",
    "wof:name":"Mbs Svcs",
    "wof:placetype":"venue"
},
  "geometry": {"coordinates":[-83.944255,33.947414],"type":"Point"}
}