{
  "type": "Feature",
  "properties": {
    "iso:country":"US",
    "sg:address":"3855 Holcomb Bridge Rd",
    "sg:city":"Norcross",
    "sg:classifiers":[
        {
            "category":"Professional",
            "type":"Services"
        }
    ],
    "sg:phone":"+1 770 281 8700",
    "sg:postcode":"30092",
    "sg:province":"GA",
    "sg:tags":[
        "establishment"
    ],
    "wof:name":"World Wide Express",
    "wof:placetype":"venue"
},
  "geometry": {"coordinates":[-84.253894,33.965211],"type":"Point"}
}