{
  "type": "Feature",
  "properties": {
    "addr:full":"2500 Dallas Hwy Marietta GA 30064",
    "addr:housenumber":"2500",
    "addr:postcode":"30064",
    "addr:street":"Dallas Hwy",
    "iso:country":"US",
    "sg:address":"2500 Dallas Hwy",
    "sg:city":"Marietta",
    "sg:classifiers":[
        {
            "category":"Shopping",
            "subcategory":"Clothing, Apparel, & Fashions",
            "type":"Retail Goods"
        }
    ],
    "sg:phone":"+1 770 427 4654",
    "sg:postcode":"30064",
    "sg:province":"GA",
    "sg:tags":[
        "wedding",
        "accessory"
    ],
    "wof:name":"Weddings Etc",
    "wof:placetype":"venue"
},
  "geometry": {"coordinates":[-84.627056,33.946463],"type":"Point"}
}