{
  "type": "Feature",
  "properties": {
    "addr:full":"7042 Ivy Pointe Row Austell GA 30168",
    "addr:housenumber":"7042",
    "addr:postcode":"30168",
    "addr:street":"Ivy Pointe Row",
    "iso:country":"US",
    "sg:address":"7042 Ivy Pointe Row",
    "sg:city":"Austell",
    "sg:classifiers":[
        {
            "category":"Health Services",
            "subcategory":"Doctor",
            "type":"Services"
        }
    ],
    "sg:phone":"+1 770 745 9483",
    "sg:postcode":"30168",
    "sg:province":"GA",
    "sg:tags":[
        "care"
    ],
    "wof:name":"Neighborhood Health Care GA",
    "wof:placetype":"venue"
},
  "geometry": {"coordinates":[-84.602513,33.78422],"type":"Point"}
}