{
  "type": "Feature",
  "properties": {
    "iso:country":"US",
    "sg:address":"210 S Calhoun St",
    "sg:city":"Dublin",
    "sg:classifiers":[
        {
            "category":"Building & Trades",
            "subcategory":"Construction",
            "type":"Services"
        }
    ],
    "sg:phone":"+1 478 296 9645",
    "sg:postcode":"31021",
    "sg:province":"GA",
    "sg:tags":[
        "residential"
    ],
    "wof:name":"Foskey and Sons Cnstr LLC",
    "wof:placetype":"venue"
},
  "geometry": {"coordinates":[-82.91341,32.535692],"type":"Point"}
}