{
  "type": "Feature",
  "properties": {
    "addr:full":"1424 Grovehurst Dr Marietta GA 30062",
    "addr:housenumber":"1424",
    "addr:postcode":"30062",
    "addr:street":"Grovehurst Dr",
    "iso:country":"US",
    "sg:address":"1424 Grovehurst Dr",
    "sg:city":"Marietta",
    "sg:classifiers":[
        {
            "category":"Restaurant",
            "type":"Food & Drink"
        }
    ],
    "sg:phone":"+1 770 321 8458",
    "sg:postcode":"30062",
    "sg:province":"GA",
    "sg:tags":[
        "eating"
    ],
    "wof:name":"China Net Inc",
    "wof:placetype":"venue"
},
  "geometry": {"coordinates":[-84.430796,33.985283],"type":"Point"}
}