{
  "type": "Feature",
  "properties": {
    "iso:country":"US",
    "sg:address":"6642 State Rte 85",
    "sg:city":"Riverdale",
    "sg:classifiers":[
        {
            "category":"Food & Beverages",
            "subcategory":"Groceries & Convenience Stores",
            "type":"Retail Goods"
        }
    ],
    "sg:phone":"+1 770 991 3628",
    "sg:postcode":"30274",
    "sg:province":"GA",
    "sg:tags":[
        "product"
    ],
    "wof:name":"Food Depot",
    "wof:placetype":"venue"
},
  "geometry": {"coordinates":[-84.411519,33.580468],"type":"Point"}
}