{
  "type": "Feature",
  "properties": {
    "addr:full":"6438 Dawson Blvd Ste D Norcross GA 30093",
    "addr:housenumber":"6438",
    "addr:postcode":"30093",
    "addr:street":"Dawson Blvd Ste D",
    "iso:country":"US",
    "sg:address":"6438 Dawson Blvd Ste D",
    "sg:city":"Norcross",
    "sg:classifiers":[
        {
            "category":"Shopping",
            "subcategory":"Stationery & Office Supplies",
            "type":"Retail Goods"
        },
        {
            "category":"Manufacturing",
            "subcategory":"Furniture",
            "type":"Manufacturing & Wholesale Goods"
        },
        {
            "category":"Home & Garden",
            "subcategory":"Furniture",
            "type":"Retail Goods"
        }
    ],
    "sg:phone":"+1 770 417 1233",
    "sg:postcode":"30093",
    "sg:province":"GA",
    "sg:tags":[
        "furniture-unfinished",
        "equipment",
        "store"
    ],
    "sg:website":"www.wood-n-choices.com",
    "wof:name":"Wood-N Choices",
    "wof:placetype":"venue"
},
  "geometry": {"coordinates":[-84.21959699999999,33.910099],"type":"Point"}
}