{
  "type": "Feature",
  "properties": {
    "iso:country":"US",
    "sg:address":"3535 Roswell Road NE",
    "sg:city":"Atlanta",
    "sg:classifiers":[
        {
            "category":"Communications",
            "type":"Services"
        }
    ],
    "sg:phone":"+1 678 560 9775",
    "sg:postcode":"30305",
    "sg:province":"GA",
    "sg:tags":[
        "web",
        "design"
    ],
    "wof:name":"Internet Commerce Corporation",
    "wof:placetype":"venue"
},
  "geometry": {"coordinates":[-84.383014,33.851184],"type":"Point"}
}