{
  "type": "Feature",
  "properties": {
    "iso:country":"US",
    "sg:address":"118 E Maple St",
    "sg:city":"Decatur",
    "sg:classifiers":[
        {
            "category":"Professional",
            "subcategory":"Lawyer & Legal Services",
            "type":"Services"
        }
    ],
    "sg:phone":"+1 404 373 5551",
    "sg:postcode":"30030",
    "sg:province":"GA",
    "wof:name":"Johnson Richard PC",
    "wof:placetype":"venue"
},
  "geometry": {"coordinates":[-84.29516700000001,33.771891],"type":"Point"}
}