{
  "type": "Feature",
  "properties": {
    "iso:country":"US",
    "sg:address":"2497 Lovejoy Rd",
    "sg:city":"Hampton",
    "sg:classifiers":[
        {
            "category":"Wholesale",
            "subcategory":"Construction Materials",
            "type":"Manufacturing & Wholesale Goods"
        }
    ],
    "sg:phone":"+1 770 603 9745",
    "sg:postcode":"30228",
    "sg:province":"GA",
    "sg:tags":[
        "fence"
    ],
    "sg:website":"www.nationsfence.com",
    "wof:name":"Nations Fence Inc",
    "wof:placetype":"venue"
},
  "geometry": {"coordinates":[-84.309747,33.431748],"type":"Point"}
}