{
  "type": "Feature",
  "properties": {
    "addr:full":"125 Ruben Dr NE Calhoun GA 30701",
    "addr:housenumber":"125",
    "addr:postcode":"30701",
    "addr:street":"Ruben Dr Ne",
    "iso:country":"US",
    "sg:address":"125 Ruben Dr NE",
    "sg:city":"Calhoun",
    "sg:classifiers":[
        {
            "category":"Building & Trades",
            "subcategory":"Plumbing",
            "type":"Services"
        }
    ],
    "sg:phone":"+1 706 629 8630",
    "sg:postcode":"30701",
    "sg:province":"GA",
    "sg:tags":[
        "contractor"
    ],
    "wof:name":"Jack Balliew Plumbing & Elec",
    "wof:placetype":"venue"
},
  "geometry": {"coordinates":[-84.91371700000001,34.505346],"type":"Point"}
}