{
  "type": "Feature",
  "properties": {
    "iso:country":"US",
    "sg:address":"3669 Valley Hill Rd NW",
    "sg:city":"Kennesaw",
    "sg:classifiers":[
        {
            "category":"Professional",
            "subcategory":"Management & Consulting",
            "type":"Services"
        },
        {
            "category":"Professional",
            "subcategory":"Advertising",
            "type":"Services"
        }
    ],
    "sg:phone":"+1 770 425 7292",
    "sg:postcode":"30152",
    "sg:province":"GA",
    "sg:tags":[
        "marketing",
        "program",
        "consultant"
    ],
    "sg:website":"http://www.strohauermarketing.com",
    "wof:name":"Strohauer Marketing Group Inc",
    "wof:placetype":"venue"
},
  "geometry": {"coordinates":[-84.658387,34.008091],"type":"Point"}
}