{
  "type": "Feature",
  "properties": {
    "addr:full":"20 Marietta St Atlanta GA 30303",
    "addr:housenumber":"20",
    "addr:postcode":"30303",
    "addr:street":"Marietta St",
    "iso:country":"US",
    "sg:address":"20 Marietta St",
    "sg:city":"Atlanta",
    "sg:classifiers":[
        {
            "category":"Shopping",
            "subcategory":"Clothing, Apparel, & Fashions",
            "type":"Retail Goods"
        }
    ],
    "sg:phone":"+1 404 222 0059",
    "sg:postcode":"30303",
    "sg:province":"GA",
    "wof:name":"Ashley Stewart Ltd",
    "wof:placetype":"venue"
},
  "geometry": {"coordinates":[-84.39110100000001,33.755396],"type":"Point"}
}