{
  "type": "Feature",
  "properties": {
    "addr:full":"731 McEntyre Loop SE Calhoun GA 30701",
    "addr:housenumber":"731",
    "addr:postcode":"30701",
    "addr:street":"Mcentyre Loop Se",
    "iso:country":"US",
    "sg:address":"731 McEntyre Loop SE",
    "sg:city":"Calhoun",
    "sg:classifiers":[
        {
            "category":"Retail",
            "subcategory":"Auto Repair",
            "type":"Services"
        }
    ],
    "sg:phone":"+1 706 629 1732",
    "sg:postcode":"30701",
    "sg:province":"GA",
    "sg:tags":[
        "general"
    ],
    "wof:name":"Patterson Diesel Service",
    "wof:placetype":"venue"
},
  "geometry": {"coordinates":[-84.80195399999999,34.46525],"type":"Point"}
}