{
  "type": "Feature",
  "properties": {
    "addr:full":"3391 Fairburn Rd SW Atlanta GA 30331",
    "addr:housenumber":"3391",
    "addr:postcode":"30331",
    "addr:street":"Fairburn Rd Sw",
    "iso:country":"US",
    "sg:address":"3391 Fairburn Rd SW",
    "sg:city":"Atlanta",
    "sg:classifiers":[
        {
            "category":"Food & Beverages",
            "subcategory":"Groceries & Convenience Stores",
            "type":"Retail Goods"
        }
    ],
    "sg:phone":"+1 404 349 5238",
    "sg:postcode":"30331",
    "sg:province":"GA",
    "wof:name":"Town & Country Food Mart",
    "wof:placetype":"venue"
},
  "geometry": {"coordinates":[-84.523003,33.663898],"type":"Point"}
}