{
  "type": "Feature",
  "properties": {
    "addr:full":"4636 Gilhams Rd Roswell GA 30075",
    "addr:housenumber":"4636",
    "addr:postcode":"30075",
    "addr:street":"Gilhams Rd",
    "iso:country":"US",
    "sg:address":"4636 Gilhams Rd",
    "sg:city":"Roswell",
    "sg:classifiers":[
        {
            "category":"Building & Trades",
            "subcategory":"Construction",
            "type":"Services"
        }
    ],
    "sg:phone":"+1 678 665 3935",
    "sg:postcode":"30075",
    "sg:province":"GA",
    "sg:tags":[
        "house"
    ],
    "wof:name":"Carli A Construction LLC",
    "wof:placetype":"venue"
},
  "geometry": {"coordinates":[-84.41399699999999,34.048618],"type":"Point"}
}