{
  "type": "Feature",
  "properties": {
    "addr:full":"50 Rumson Way NE Atlanta GA 30305",
    "addr:housenumber":"50",
    "addr:postcode":"30305",
    "addr:street":"Rumson Way Ne",
    "iso:country":"US",
    "sg:address":"50 Rumson Way NE",
    "sg:city":"Atlanta",
    "sg:classifiers":[
        {
            "category":"Professional",
            "subcategory":"Computer Services",
            "type":"Services"
        }
    ],
    "sg:phone":"+1 404 266 1501",
    "sg:postcode":"30305",
    "sg:province":"GA",
    "sg:tags":[
        "programing",
        "custom"
    ],
    "wof:name":"William Moore Consulting",
    "wof:placetype":"venue"
},
  "geometry": {"coordinates":[-84.38315299999999,33.830644],"type":"Point"}
}