{
  "type": "Feature",
  "properties": {
    "addr:full":"1109 Roswell Rd Marietta GA 30062",
    "addr:housenumber":"1109",
    "addr:postcode":"30062",
    "addr:street":"Roswell Rd",
    "iso:country":"US",
    "sg:address":"1109 Roswell Rd",
    "sg:city":"Marietta",
    "sg:classifiers":[
        {
            "category":"Retail",
            "subcategory":"Auto Repair",
            "type":"Services"
        }
    ],
    "sg:phone":"+1 770 428 3935",
    "sg:postcode":"30062",
    "sg:province":"GA",
    "sg:tags":[
        "muffler",
        "exhaust",
        "system"
    ],
    "wof:name":"Marietta Muffler",
    "wof:placetype":"venue"
},
  "geometry": {"coordinates":[-84.519302,33.951],"type":"Point"}
}