{
  "type": "Feature",
  "properties": {
    "addr:full":"8345 Belton Bridge Rd Lula GA 30554",
    "addr:housenumber":"8345",
    "addr:postcode":"30554",
    "addr:street":"Belton Bridge Rd",
    "iso:country":"US",
    "sg:address":"8345 Belton Bridge Rd",
    "sg:city":"Lula",
    "sg:classifiers":[
        {
            "category":"Organizations",
            "subcategory":"Membership Organization",
            "type":"Services"
        }
    ],
    "sg:phone":"+1 770 983 2164",
    "sg:postcode":"30554",
    "sg:province":"GA",
    "wof:name":"D & L Scoreboard Service",
    "wof:placetype":"venue"
},
  "geometry": {"coordinates":[-83.71153099999999,34.465051],"type":"Point"}
}