{
  "type": "Feature",
  "properties": {
    "iso:country":"US",
    "sg:address":"540 Charlie Fuller Rd",
    "sg:city":"Luthersville",
    "sg:classifiers":[
        {
            "category":"Professional",
            "type":"Services"
        }
    ],
    "sg:phone":"+1 770 927 6044",
    "sg:postcode":"30251",
    "sg:province":"GA",
    "wof:name":"Snakeproof Mill Saw Services",
    "wof:placetype":"venue"
},
  "geometry": {"coordinates":[-84.76828999999999,33.16898],"type":"Point"}
}