{
  "type": "Feature",
  "properties": {
    "iso:country":"US",
    "sg:address":"2048 Headland Drive",
    "sg:city":"East Point",
    "sg:classifiers":[
        {
            "category":"Arts & Performance",
            "subcategory":"Arts Center",
            "type":"Entertainment"
        }
    ],
    "sg:phone":"+1 404 559 2956",
    "sg:postcode":"30344",
    "sg:province":"GA",
    "sg:tags":[
        "performing"
    ],
    "wof:name":"Marlene Rounds Christian School of Dance",
    "wof:placetype":"venue"
},
  "geometry": {"coordinates":[-84.45464800000001,33.688576],"type":"Point"}
}