{
  "type": "Feature",
  "properties": {
    "addr:full":"220 E Troupe St Bainbridge GA 39817",
    "addr:housenumber":"220",
    "addr:postcode":"39817",
    "addr:street":"E Troupe St",
    "iso:country":"US",
    "sg:address":"220 E Troupe St",
    "sg:city":"Bainbridge",
    "sg:classifiers":[
        {
            "category":"Arts & Performance",
            "subcategory":"Theater",
            "type":"Entertainment"
        }
    ],
    "sg:phone":"+1 229 246 8345",
    "sg:postcode":"39817",
    "sg:province":"GA",
    "wof:name":"Bainbridge Little Theatre",
    "wof:placetype":"venue"
},
  "geometry": {"coordinates":[-84.57517199999999,30.90511],"type":"Point"}
}