{
  "type": "Feature",
  "properties": {
    "addr:full":"3947 Darien Hwy Brunswick GA 31525",
    "addr:housenumber":"3947",
    "addr:postcode":"31525",
    "addr:street":"Darien Hwy",
    "iso:country":"US",
    "sg:address":"3947 Darien Hwy",
    "sg:city":"Brunswick",
    "sg:classifiers":[
        {
            "category":"Professional",
            "subcategory":"Accounting & Tax Preparation",
            "type":"Services"
        }
    ],
    "sg:phone":"+1 912 267 0211",
    "sg:postcode":"31525",
    "sg:province":"GA",
    "sg:tags":[
        "accountant"
    ],
    "wof:name":"Carmichael Clay & Barrs LLC",
    "wof:placetype":"venue"
},
  "geometry": {"coordinates":[-81.46618599999999,31.212108],"type":"Point"}
}