{
  "type": "Feature",
  "properties": {
    "addr:full":"3891 Prospect Rd Rutledge GA 30650",
    "addr:housenumber":"3891",
    "addr:postcode":"30650",
    "addr:street":"Prospect Rd",
    "iso:country":"US",
    "sg:address":"3891 Prospect Rd",
    "sg:city":"Rutledge",
    "sg:classifiers":[
        {
            "category":"Building & Trades",
            "subcategory":"Construction",
            "type":"Services"
        }
    ],
    "sg:phone":"+1 706 343 0082",
    "sg:postcode":"30650",
    "sg:province":"GA",
    "sg:tags":[
        "coping",
        "plastering",
        "tiling",
        "pool",
        "swimming"
    ],
    "wof:name":"Poolaide Service & Maintenance",
    "wof:placetype":"venue"
},
  "geometry": {"coordinates":[-83.60011900000001,33.698899],"type":"Point"}
}