{
  "type": "Feature",
  "properties": {
    "iso:country":"US",
    "sg:address":"8097 Appalachian Hwy",
    "sg:city":"Mineral Bluff",
    "sg:classifiers":[
        {
            "category":"Manufacturing",
            "subcategory":"Wood Products",
            "type":"Manufacturing & Wholesale Goods"
        }
    ],
    "sg:phone":"+1 706 374 3284",
    "sg:postcode":"30559",
    "sg:province":"GA",
    "sg:tags":[
        "mfg"
    ],
    "wof:name":"Horizion Auto Sales Inc",
    "wof:placetype":"venue"
},
  "geometry": {"coordinates":[-84.26063000000001,34.893395],"type":"Point"}
}