{
  "type": "Feature",
  "properties": {
    "addr:full":"6525 Carriage Ct Cumming GA 30040",
    "addr:housenumber":"6525",
    "addr:postcode":"30040",
    "addr:street":"Carriage Ct",
    "iso:country":"US",
    "sg:address":"6525 Carriage Ct",
    "sg:city":"Cumming",
    "sg:classifiers":[
        {
            "category":"Utilities",
            "subcategory":"Telephone",
            "type":"Services"
        }
    ],
    "sg:phone":"+1 770 889 1309",
    "sg:postcode":"30040",
    "sg:province":"GA",
    "sg:tags":[
        "company"
    ],
    "wof:name":"Viehl Comm",
    "wof:placetype":"venue"
},
  "geometry": {"coordinates":[-84.15939,34.294968],"type":"Point"}
}