{
  "type": "Feature",
  "properties": {
    "iso:country":"US",
    "sg:address":"4080 McGinnis Ferry Rd",
    "sg:city":"Alpharetta",
    "sg:classifiers":[
        {
            "category":"Professional",
            "subcategory":"Computer Services",
            "type":"Services"
        }
    ],
    "sg:phone":"+1 770 346 9566",
    "sg:postcode":"30005",
    "sg:province":"GA",
    "sg:tags":[
        "development",
        "consulting",
        "wire",
        "voice",
        "staffing",
        "software"
    ],
    "wof:name":"Icon Technology Group",
    "wof:placetype":"venue"
},
  "geometry": {"coordinates":[-84.240014,34.101517],"type":"Point"}
}