{
  "type": "Feature",
  "properties": {
    "addr:full":"220 Mills Rd Franklin GA 30217",
    "addr:housenumber":"220",
    "addr:postcode":"30217",
    "addr:street":"Mills Rd",
    "iso:country":"US",
    "sg:address":"220 Mills Rd",
    "sg:city":"Franklin",
    "sg:classifiers":[
        {
            "category":"Fast Food",
            "type":"Food & Drink"
        },
        {
            "category":"Restaurant",
            "type":"Food & Drink"
        }
    ],
    "sg:phone":"+1 770 304 8704",
    "sg:postcode":"30217",
    "sg:province":"GA",
    "wof:name":"Burger Grande Inc",
    "wof:placetype":"venue"
},
  "geometry": {"coordinates":[-85.01067399999999,33.383728],"type":"Point"}
}