{
  "type": "Feature",
  "properties": {
    "iso:country":"US",
    "sg:address":"6030 Highway 85 Ste 524",
    "sg:city":"Riverdale",
    "sg:classifiers":[
        {
            "category":"Retail",
            "subcategory":"Auto Repair",
            "type":"Services"
        }
    ],
    "sg:phone":"+1 770 997 4782",
    "sg:postcode":"30274",
    "sg:province":"GA",
    "wof:name":"Ambica Auto Services",
    "wof:placetype":"venue"
},
  "geometry": {"coordinates":[-84.40860000000001,33.5909],"type":"Point"}
}