{
  "type": "Feature",
  "properties": {
    "addr:full":"107 Garland Rose Ln Dallas GA 30157",
    "addr:housenumber":"107",
    "addr:postcode":"30157",
    "addr:street":"Garland Rose Ln",
    "iso:country":"US",
    "sg:address":"107 Garland Rose Ln",
    "sg:city":"Dallas",
    "sg:classifiers":[
        {
            "category":"Real Estate",
            "subcategory":"Real Estate Services",
            "type":"Services"
        },
        {
            "category":"Real Estate",
            "subcategory":"Real Estate Agent",
            "type":"Services"
        }
    ],
    "sg:phone":"+1 678 732 6252",
    "sg:postcode":"30157",
    "sg:province":"GA",
    "sg:tags":[
        "management"
    ],
    "wof:name":"Commercial Management Professionals",
    "wof:placetype":"venue"
},
  "geometry": {"coordinates":[-84.750299,34.01164],"type":"Point"}
}