{
  "type": "Feature",
  "properties": {
    "addr:full":"403 US Hwy 80 Garden City GA 31408",
    "addr:housenumber":"403",
    "addr:postcode":"31408",
    "addr:street":"Us Hwy 80",
    "iso:country":"US",
    "sg:address":"403 US Hwy 80",
    "sg:city":"Garden City",
    "sg:classifiers":[
        {
            "category":"Shopping",
            "subcategory":"Used Merchandise",
            "type":"Retail Goods"
        }
    ],
    "sg:phone":"+1 912 966 2444",
    "sg:postcode":"31408",
    "sg:province":"GA",
    "sg:tags":[
        "pawnbroker"
    ],
    "wof:name":"Title Pawn",
    "wof:placetype":"venue"
},
  "geometry": {"coordinates":[-81.143939,32.096347],"type":"Point"}
}