{
  "type": "Feature",
  "properties": {
    "addr:full":"2405 Castlemaine Ct NW Duluth GA 30097",
    "addr:housenumber":"2405",
    "addr:postcode":"30097",
    "addr:street":"Castlemaine Ct Nw",
    "iso:country":"US",
    "sg:address":"2405 Castlemaine Ct NW",
    "sg:city":"Duluth",
    "sg:classifiers":[
        {
            "category":"Professional",
            "subcategory":"Business Services",
            "type":"Services"
        }
    ],
    "sg:phone":"+1 770 495 9417",
    "sg:postcode":"30097",
    "sg:province":"GA",
    "wof:name":"Interiors Consulting Service",
    "wof:placetype":"venue"
},
  "geometry": {"coordinates":[-84.12938800000001,34.023762],"type":"Point"}
}