{
  "type": "Feature",
  "properties": {
    "addr:full":"705 Whisper Trl Austell GA 30168",
    "addr:housenumber":"705",
    "addr:postcode":"30168",
    "addr:street":"Whisper Trl",
    "iso:country":"US",
    "sg:address":"705 Whisper Trl",
    "sg:city":"Austell",
    "sg:classifiers":[
        {
            "category":"Arts & Performance",
            "subcategory":"Theater",
            "type":"Entertainment"
        }
    ],
    "sg:phone":"+1 678 945 0919",
    "sg:postcode":"30168",
    "sg:province":"GA",
    "sg:tags":[
        "bureau"
    ],
    "wof:name":"Piceri Entertainment",
    "wof:placetype":"venue"
},
  "geometry": {"coordinates":[-84.57598400000001,33.776697],"type":"Point"}
}