{
  "type": "Feature",
  "properties": {
    "iso:country":"US",
    "sg:address":"1757 Terry Mill Rd SE",
    "sg:city":"Atlanta",
    "sg:classifiers":[
        {
            "category":"Building & Trades",
            "subcategory":"Landscaping Services",
            "type":"Services"
        }
    ],
    "sg:phone":"+1 404 373 1001",
    "sg:postcode":"30316",
    "sg:province":"GA",
    "wof:name":"Watkins Lawn Svc",
    "wof:placetype":"venue"
},
  "geometry": {"coordinates":[-84.32208799999999,33.738119],"type":"Point"}
}