{
  "type": "Feature",
  "properties": {
    "iso:country":"US",
    "sg:address":"2 Skidway Village Walk",
    "sg:city":"Savannah",
    "sg:classifiers":[
        {
            "category":"Banks & Credit Unions",
            "subcategory":"Investment Brokerage",
            "type":"Services"
        }
    ],
    "sg:phone":"+1 912 598 0089",
    "sg:postcode":"31411",
    "sg:province":"GA",
    "sg:tags":[
        "security",
        "stock",
        "bond"
    ],
    "wof:name":"Wachobis Securities",
    "wof:placetype":"venue"
},
  "geometry": {"coordinates":[-81.052238,31.940838],"type":"Point"}
}