{
  "type": "Feature",
  "properties": {
    "addr:full":"1341 Canton Rd Marietta GA 30066",
    "addr:housenumber":"1341",
    "addr:postcode":"30066",
    "addr:street":"Canton Rd",
    "iso:country":"US",
    "sg:address":"1341 Canton Rd",
    "sg:city":"Marietta",
    "sg:classifiers":[
        {
            "category":"Professional",
            "subcategory":"Research",
            "type":"Services"
        },
        {
            "category":"Utilities",
            "type":"Services"
        }
    ],
    "sg:phone":"+1 770 528 0200",
    "sg:postcode":"30066",
    "sg:province":"GA",
    "sg:tags":[
        "environmental",
        "ecological",
        "consulting",
        "business",
        "sanitary"
    ],
    "sg:website":"www.epicconsulting.com",
    "wof:name":"Epic Engineering Inc",
    "wof:placetype":"venue"
},
  "geometry": {"coordinates":[-84.536582,33.984054],"type":"Point"}
}