{
  "type": "Feature",
  "properties": {
    "addr:full":"114 Peterson Ave N Douglas GA 31533",
    "addr:housenumber":"114",
    "addr:postcode":"ga 31533",
    "addr:street":"Peterson Ave N",
    "iso:country":"US",
    "sg:address":"114 Peterson Ave N",
    "sg:city":"Douglas",
    "sg:classifiers":[
        {
            "category":"Personal",
            "subcategory":"Beauty Salon",
            "type":"Services"
        }
    ],
    "sg:phone":"+1 912 383 0005",
    "sg:postcode":"31533",
    "sg:province":"GA",
    "sg:website":"http://www.skintasticskin.com",
    "wof:name":"Skintastic",
    "wof:placetype":"venue"
},
  "geometry": {"coordinates":[-82.85036700000001,31.509055],"type":"Point"}
}