{
  "type": "Feature",
  "properties": {
    "iso:country":"US",
    "sg:address":"105 Banks Dr",
    "sg:city":"Carrollton",
    "sg:classifiers":[
        {
            "category":"Health Services",
            "subcategory":"Health Practitioner",
            "type":"Services"
        }
    ],
    "sg:phone":"+1 770 834 6393",
    "sg:postcode":"30117",
    "sg:province":"GA",
    "sg:tags":[
        "psychologist"
    ],
    "wof:name":"Transpersonal Counseling",
    "wof:placetype":"venue"
},
  "geometry": {"coordinates":[-85.064908,33.596174],"type":"Point"}
}