{
  "type": "Feature",
  "properties": {
    "iso:country":"US",
    "sg:address":"250 Laurel Hts Dr",
    "sg:city":"Dahlonega",
    "sg:classifiers":[
        {
            "category":"Manufacturing",
            "subcategory":"Aerospace",
            "type":"Manufacturing & Wholesale Goods"
        }
    ],
    "sg:phone":"+1 706 782 4245",
    "sg:postcode":"30533",
    "sg:province":"GA",
    "sg:tags":[
        "aircraft",
        "component"
    ],
    "sg:website":"www.advmetservgrp.com",
    "wof:name":"Aid Corp",
    "wof:placetype":"venue"
},
  "geometry": {"coordinates":[-83.998182,34.542112],"type":"Point"}
}