{
  "type": "Feature",
  "properties": {
    "addr:full":"5004 Augusta Rd Savannah GA 31408",
    "addr:housenumber":"5004",
    "addr:postcode":"31408",
    "addr:street":"Augusta Rd",
    "iso:country":"US",
    "sg:address":"5004 Augusta Rd",
    "sg:city":"Savannah",
    "sg:classifiers":[
        {
            "category":"Restaurant",
            "type":"Food & Drink"
        },
        {
            "category":"Ice Cream",
            "type":"Food & Drink"
        }
    ],
    "sg:menulink":"http://www.allmenus.com/ga/savannah/172629-dairy-queen/menu/",
    "sg:phone":"+1 912 966 0868",
    "sg:postcode":"31408",
    "sg:province":"GA",
    "sg:tags":[
        "burger",
        "american",
        "ice",
        "cream"
    ],
    "wof:name":"Dairy Queen",
    "wof:placetype":"venue"
},
  "geometry": {"coordinates":[-81.16194400000001,32.112502],"type":"Point"}
}