{
  "type": "Feature",
  "properties": {
    "iso:country":"US",
    "sg:address":"3338 Cherokee St NW",
    "sg:city":"Kennesaw",
    "sg:classifiers":[
        {
            "category":"Food & Beverages",
            "subcategory":"Groceries & Convenience Stores",
            "type":"Retail Goods"
        }
    ],
    "sg:phone":"+1 770 425 9599",
    "sg:postcode":"30144",
    "sg:province":"GA",
    "wof:name":"Nasy",
    "wof:placetype":"venue"
},
  "geometry": {"coordinates":[-84.605301,34.035],"type":"Point"}
}