{
  "type": "Feature",
  "properties": {
    "addr:full":"2839 Paces Ferry Rd.  Suite 370 Atlanta GA 30339 ",
    "addr:housenumber":"2839",
    "addr:postcode":"30339",
    "addr:street":"Paces Ferry Rd. Suite 370",
    "iso:country":"US",
    "sg:address":"2839 Paces Ferry Rd.  Suite 370",
    "sg:city":"Atlanta",
    "sg:classifiers":[
        {
            "category":"Professional",
            "subcategory":"Computer Services",
            "type":"Services"
        }
    ],
    "sg:phone":"+1 925 681 2326",
    "sg:postcode":"30339 ",
    "sg:province":"GA",
    "sg:tags":[
        "system-design-software",
        "av-estimation-software",
        "av-project-management-software",
        "data-driven-process"
    ],
    "sg:website":"http://www.d-tools.com",
    "wof:name":"D-Tools",
    "wof:placetype":"venue"
},
  "geometry": {"coordinates":[-84.470737,33.865786],"type":"Point"}
}