{
  "type": "Feature",
  "properties": {
    "iso:country":"US",
    "sg:address":"3118 Victory Dr",
    "sg:city":"Columbus",
    "sg:classifiers":[
        {
            "category":"Home & Garden",
            "subcategory":"Mobile Homes",
            "type":"Retail Goods"
        }
    ],
    "sg:phone":"+1 706 687 3360",
    "sg:postcode":"31903",
    "sg:province":"GA",
    "wof:name":"Palm Harbor Villiage",
    "wof:placetype":"venue"
},
  "geometry": {"coordinates":[-84.95356099999999,32.430703],"type":"Point"}
}