{
  "type": "Feature",
  "properties": {
    "addr:full":"70 Bullsboro Dr Newnan GA 30263",
    "addr:housenumber":"70",
    "addr:postcode":"30263",
    "addr:street":"Bullsboro Dr",
    "iso:country":"US",
    "sg:address":"70 Bullsboro Dr",
    "sg:city":"Newnan",
    "sg:classifiers":[
        {
            "category":"Professional",
            "subcategory":"Employment Agencies",
            "type":"Services"
        }
    ],
    "sg:phone":"+1 770 304 2311",
    "sg:postcode":"30263",
    "sg:province":"GA",
    "sg:tags":[
        "temporary"
    ],
    "wof:name":"Spherion Corporation",
    "wof:placetype":"venue"
},
  "geometry": {"coordinates":[-84.78605,33.383675],"type":"Point"}
}