{
  "type": "Feature",
  "properties": {
    "addr:full":"415 W Liberty St Savannah GA 31401",
    "addr:housenumber":"415",
    "addr:postcode":"31401",
    "addr:street":"W Liberty St",
    "iso:country":"US",
    "sg:address":"415 W Liberty St",
    "sg:city":"Savannah",
    "sg:classifiers":[
        {
            "category":"Travel",
            "subcategory":"Hotels & Motels",
            "type":"Entertainment"
        }
    ],
    "sg:phone":"+1 912 790 8287",
    "sg:postcode":"31401",
    "sg:province":"GA",
    "wof:name":"Courtyard-Savannah Hstrc Dist",
    "wof:placetype":"venue"
},
  "geometry": {"coordinates":[-81.098128,32.075458],"type":"Point"}
}