{
  "type": "Feature",
  "properties": {
    "addr:full":"890 Cooper Lake Rd SE Smyrna GA 30082",
    "addr:housenumber":"890",
    "addr:postcode":"30082",
    "addr:street":"Cooper Lake Rd Se",
    "iso:country":"US",
    "sg:address":"890 Cooper Lake Rd SE",
    "sg:city":"Smyrna",
    "sg:classifiers":[
        {
            "category":"Education",
            "subcategory":"Special Training",
            "type":"Public Place"
        }
    ],
    "sg:phone":"+1 770 431 6910",
    "sg:postcode":"30082",
    "sg:province":"GA",
    "sg:tags":[
        "vocational",
        "expert"
    ],
    "wof:name":"Burl G Robertson Jr",
    "wof:placetype":"venue"
},
  "geometry": {"coordinates":[-84.528477,33.845349],"type":"Point"}
}