{
  "type": "Feature",
  "properties": {
    "iso:country":"US",
    "sg:address":"2435 Hinton Rd",
    "sg:city":"Dacula",
    "sg:classifiers":[
        {
            "category":"Professional",
            "type":"Services"
        }
    ],
    "sg:phone":"+1 770 339 4610",
    "sg:postcode":"30019",
    "sg:province":"GA",
    "wof:name":"Constance Kitchen Denise",
    "wof:placetype":"venue"
},
  "geometry": {"coordinates":[-83.90544,33.995674],"type":"Point"}
}