{
  "type": "Feature",
  "properties": {
    "addr:full":"4004 Tradeport Blvd Atlanta GA 30354",
    "addr:housenumber":"4004",
    "addr:postcode":"30354",
    "addr:street":"Tradeport Blvd",
    "iso:country":"US",
    "sg:address":"4004 Tradeport Blvd",
    "sg:city":"Atlanta",
    "sg:classifiers":[
        {
            "category":"Autos & Motor Vehicles",
            "subcategory":"Automobile Sales",
            "type":"Retail Goods"
        }
    ],
    "sg:phone":"+1 404 835 1420",
    "sg:postcode":"30354",
    "sg:province":"GA",
    "sg:tags":[
        "limo"
    ],
    "wof:name":"Cooper-Atlanta 2",
    "wof:placetype":"venue"
},
  "geometry": {"coordinates":[-84.39595300000001,33.645268],"type":"Point"}
}