{
  "type": "Feature",
  "properties": {
    "iso:country":"US",
    "sg:address":"249 Peters St SW",
    "sg:city":"Atlanta",
    "sg:classifiers":[
        {
            "category":"Personal",
            "type":"Services"
        }
    ],
    "sg:phone":"+1 404 523 4247",
    "sg:postcode":"30313",
    "sg:province":"GA",
    "wof:name":"Kim Millers Hair Gallery",
    "wof:placetype":"venue"
},
  "geometry": {"coordinates":[-84.401796,33.747489],"type":"Point"}
}