{
  "type": "Feature",
  "properties": {
    "iso:country":"US",
    "sg:address":"124 Industrial Dr",
    "sg:city":"Sandersville",
    "sg:classifiers":[
        {
            "category":"Insurance",
            "subcategory":"Hazard Insurance",
            "type":"Services"
        }
    ],
    "sg:phone":"+1 478 552 3491",
    "sg:postcode":"31082",
    "sg:province":"GA",
    "sg:tags":[
        "commercial",
        "business"
    ],
    "sg:website":"http://www.gfb.org",
    "wof:name":"Washington County Farm Bureau",
    "wof:placetype":"venue"
},
  "geometry": {"coordinates":[-82.808725,32.965858],"type":"Point"}
}