{
  "type": "Feature",
  "properties": {
    "iso:country":"US",
    "sg:address":"1574 Stone Ridge Dr",
    "sg:city":"Stone Mountain",
    "sg:classifiers":[
        {
            "category":"Farming",
            "subcategory":"Farm & Veterinary Services",
            "type":"Manufacturing & Wholesale Goods"
        }
    ],
    "sg:phone":"+1 770 908 9439",
    "sg:postcode":"30083",
    "sg:province":"GA",
    "sg:tags":[
        "distributor",
        "equipment"
    ],
    "sg:website":"www.implementsalesga.com",
    "wof:name":"Implement Sales LLC",
    "wof:placetype":"venue"
},
  "geometry": {"coordinates":[-84.19066599999999,33.82461],"type":"Point"}
}