{
  "type": "Feature",
  "properties": {
    "addr:full":"3575 Piedmont Rd NE Atlanta GA 30305",
    "addr:housenumber":"3575",
    "addr:postcode":"30305",
    "addr:street":"Piedmont Rd Ne",
    "iso:country":"US",
    "sg:address":"3575 Piedmont Rd NE",
    "sg:city":"Atlanta",
    "sg:classifiers":[
        {
            "category":"Professional",
            "subcategory":"Computer Services",
            "type":"Services"
        }
    ],
    "sg:phone":"+1 404 365 0396",
    "sg:postcode":"30305",
    "sg:province":"GA",
    "sg:tags":[
        "development",
        "software"
    ],
    "wof:name":"Govconnect Inc",
    "wof:placetype":"venue"
},
  "geometry": {"coordinates":[-84.380162,33.851817],"type":"Point"}
}