{
  "type": "Feature",
  "properties": {
    "addr:full":"876 Buford Hwy Cumming GA 30041",
    "addr:housenumber":"876",
    "addr:postcode":"30041",
    "addr:street":"Buford Hwy",
    "iso:country":"US",
    "sg:address":"876 Buford Hwy",
    "sg:city":"Cumming",
    "sg:classifiers":[
        {
            "category":"Utilities",
            "subcategory":"Mobile Phone",
            "type":"Services"
        }
    ],
    "sg:phone":"+1 678 455 4041",
    "sg:postcode":"30041",
    "sg:province":"GA",
    "sg:tags":[
        "telephone",
        "cellular"
    ],
    "wof:name":"Verizon Wireless",
    "wof:placetype":"venue"
},
  "geometry": {"coordinates":[-84.13330999999999,34.179611],"type":"Point"}
}