{
  "type": "Feature",
  "properties": {
    "iso:country":"US",
    "sg:address":"1700 Northside Dr",
    "sg:city":"Atlanta",
    "sg:classifiers":[
        {
            "category":"Food & Beverages",
            "subcategory":"Bakery",
            "type":"Retail Goods"
        }
    ],
    "sg:phone":"+1 404 351 2881",
    "sg:postcode":"30318",
    "sg:province":"GA",
    "sg:tags":[
        "sandwich"
    ],
    "sg:website":"www.risingroll.com",
    "wof:name":"Rising Roll Gourmet",
    "wof:placetype":"venue"
},
  "geometry": {"coordinates":[-84.407882,33.800689],"type":"Point"}
}