{
  "type": "Feature",
  "properties": {
    "addr:full":"1000 Blairs Bridge Rd Lithia Springs GA 30122",
    "addr:housenumber":"1000",
    "addr:postcode":"30122",
    "addr:street":"Blairs Bridge Rd",
    "iso:country":"US",
    "sg:address":"1000 Blairs Bridge Rd",
    "sg:city":"Lithia Springs",
    "sg:classifiers":[
        {
            "category":"Retail",
            "subcategory":"Auto Rental",
            "type":"Services"
        }
    ],
    "sg:phone":"+1 678 945 4528",
    "sg:postcode":"30122",
    "sg:province":"GA",
    "sg:tags":[
        "car"
    ],
    "sg:website":"www.enterprise.com",
    "wof:name":"Enterprise Rent-A-Car",
    "wof:placetype":"venue"
},
  "geometry": {"coordinates":[-84.606157,33.772349],"type":"Point"}
}