{
  "type": "Feature",
  "properties": {
    "addr:full":"2650 Marietta Hwy Ste 180 Canton GA 30114",
    "addr:housenumber":"2650",
    "addr:postcode":"30114",
    "addr:street":"Marietta Hwy Ste 180",
    "iso:country":"US",
    "sg:address":"2650 Marietta Hwy Ste 180",
    "sg:city":"Canton",
    "sg:classifiers":[
        {
            "category":"Personal",
            "type":"Services"
        },
        {
            "category":"Retail",
            "subcategory":"Auto Repair",
            "type":"Services"
        }
    ],
    "sg:phone":"+1 770 720 1107",
    "sg:postcode":"30114",
    "sg:province":"GA",
    "sg:tags":[
        "body",
        "shop",
        "towing"
    ],
    "sg:website":"www.howardsautobody.net",
    "wof:name":"Howard's Auto Body",
    "wof:placetype":"venue"
},
  "geometry": {"coordinates":[-84.506203,34.221401],"type":"Point"}
}