{
  "type": "Feature",
  "properties": {
    "iso:country":"US",
    "sg:address":"156 Mount Carmel Rd",
    "sg:city":"Newnan",
    "sg:classifiers":[
        {
            "category":"Insurance",
            "subcategory":"Insurance Agent",
            "type":"Services"
        }
    ],
    "sg:phone":"+1 770 253 3095",
    "sg:postcode":"30263",
    "sg:province":"GA",
    "wof:name":"Alliance Insurance Associates",
    "wof:placetype":"venue"
},
  "geometry": {"coordinates":[-84.88298899999999,33.395426],"type":"Point"}
}