{
  "type": "Feature",
  "properties": {
    "iso:country":"US",
    "sg:address":"1820 N Brown Rd",
    "sg:city":"Lawrenceville",
    "sg:classifiers":[
        {
            "category":"Restaurant",
            "type":"Food & Drink"
        }
    ],
    "sg:menulink":"http://www.allmenus.com/ga/lawrenceville/93759-chonas-mexican-grill/menu/",
    "sg:phone":"+1 678 847 0072",
    "sg:postcode":"30043",
    "sg:province":"GA",
    "sg:tags":[
        "mexican"
    ],
    "wof:name":"Chona's Mexican Grill",
    "wof:placetype":"venue"
},
  "geometry": {"coordinates":[-84.079027,33.988593],"type":"Point"}
}