{
  "type": "Feature",
  "properties": {
    "iso:country":"US",
    "sg:address":"45 Woodstock Rd",
    "sg:city":"Roswell",
    "sg:classifiers":[
        {
            "category":"Professional",
            "subcategory":"Lawyer & Legal Services",
            "type":"Services"
        }
    ],
    "sg:phone":"+1 770 645 4990",
    "sg:postcode":"30075",
    "sg:province":"GA",
    "sg:tags":[
        "attorney"
    ],
    "wof:name":"Patrick J Gibbs PC",
    "wof:placetype":"venue"
},
  "geometry": {"coordinates":[-84.365374,34.033764],"type":"Point"}
}