{
  "type": "Feature",
  "properties": {
    "addr:full":"300 Parkbrooke Pl Woodstock GA 30189",
    "addr:housenumber":"300",
    "addr:postcode":"30189",
    "addr:street":"Parkbrooke Pl",
    "iso:country":"US",
    "sg:address":"300 Parkbrooke Pl",
    "sg:city":"Woodstock",
    "sg:classifiers":[
        {
            "category":"Professional",
            "subcategory":"Lawyer & Legal Services",
            "type":"Services"
        }
    ],
    "sg:phone":"+1 678 494 1599",
    "sg:postcode":"30189",
    "sg:province":"GA",
    "wof:name":"Weissman Nowack Curry & Wilco PC",
    "wof:placetype":"venue"
},
  "geometry": {"coordinates":[-84.55439800000001,34.081402],"type":"Point"}
}