{
  "type": "Feature",
  "properties": {
    "iso:country":"US",
    "sg:address":"1584 Sandpoint Dr",
    "sg:city":"Roswell",
    "sg:classifiers":[
        {
            "category":"Local Transit",
            "type":"Transportation"
        }
    ],
    "sg:phone":"+1 678 461 8166",
    "sg:postcode":"30075",
    "sg:province":"GA",
    "sg:tags":[
        "passenger"
    ],
    "wof:name":"Atlanta North Transport Inc",
    "wof:placetype":"venue"
},
  "geometry": {"coordinates":[-84.40616900000001,34.013449],"type":"Point"}
}