{
  "type": "Feature",
  "properties": {
    "iso:country":"US",
    "sg:address":"1945 Lexington Rd",
    "sg:city":"Athens",
    "sg:classifiers":[
        {
            "category":"Shopping",
            "subcategory":"Computers & Home Electronics",
            "type":"Retail Goods"
        }
    ],
    "sg:phone":"+1 706 546 1416",
    "sg:postcode":"30605",
    "sg:province":"GA",
    "sg:tags":[
        "equipment",
        "electronic",
        "supply"
    ],
    "wof:name":"Group II Management Inc",
    "wof:placetype":"venue"
},
  "geometry": {"coordinates":[-83.343203,33.944801],"type":"Point"}
}