{
  "type": "Feature",
  "properties": {
    "iso:country":"US",
    "sg:address":"5020 Hudson Rd",
    "sg:city":"Loganville",
    "sg:classifiers":[
        {
            "category":"Building & Trades",
            "subcategory":"Plumbing",
            "type":"Services"
        }
    ],
    "sg:phone":"+1 770 554 2886",
    "sg:postcode":"30052",
    "sg:province":"GA",
    "sg:tags":[
        "contractor"
    ],
    "wof:name":"Piedmont Mechanical Contractor",
    "wof:placetype":"venue"
},
  "geometry": {"coordinates":[-83.843166,33.88423],"type":"Point"}
}