{
  "type": "Feature",
  "properties": {
    "iso:country":"US",
    "sg:address":"185 Old Brookfield Rd",
    "sg:city":"Tifton",
    "sg:classifiers":[
        {
            "category":"Building & Trades",
            "subcategory":"Electrical",
            "type":"Services"
        }
    ],
    "sg:phone":"+1 229 382 2129",
    "sg:postcode":"31794",
    "sg:province":"GA",
    "sg:tags":[
        "electric",
        "contractor"
    ],
    "wof:name":"W W Temples Electrical",
    "wof:placetype":"venue"
},
  "geometry": {"coordinates":[-83.500752,31.450109],"type":"Point"}
}