{
  "type": "Feature",
  "properties": {
    "iso:country":"US",
    "sg:address":"245 Buck Creek Rd",
    "sg:city":"Sylvania",
    "sg:classifiers":[
        {
            "category":"Place Of Worship",
            "subcategory":"Church",
            "type":"Public Place"
        },
        {
            "category":"Place Of Worship",
            "type":"Public Place"
        }
    ],
    "sg:phone":"+1 912 863 4786",
    "sg:postcode":"30467",
    "sg:province":"GA",
    "sg:tags":[
        "churches-baptist-general",
        "churches-baptist"
    ],
    "wof:name":"Kemp Grove Baptist Church",
    "wof:placetype":"venue"
},
  "geometry": {"coordinates":[-81.592409,32.75177],"type":"Point"}
}