{
  "type": "Feature",
  "properties": {
    "iso:country":"US",
    "sg:address":"2827 Dover Rd NW",
    "sg:city":"Atlanta",
    "sg:classifiers":[
        {
            "category":"Professional",
            "subcategory":"Business Services",
            "type":"Services"
        }
    ],
    "sg:phone":"+1 404 367 0072",
    "sg:postcode":"30327",
    "sg:province":"GA",
    "wof:name":"Molly Pastor Interiors",
    "wof:placetype":"venue"
},
  "geometry": {"coordinates":[-84.409305,33.832189],"type":"Point"}
}