{
  "type": "Feature",
  "properties": {
    "addr:full":"507 Martin Luther King Jr Dr Tifton GA 31794",
    "addr:housenumber":"507",
    "addr:postcode":"31794",
    "addr:street":"Martin Luther King Jr Dr",
    "iso:country":"US",
    "sg:address":"507 Martin Luther King Jr Dr",
    "sg:city":"Tifton",
    "sg:classifiers":[
        {
            "category":"Organizations",
            "subcategory":"Religious Organization",
            "type":"Services"
        }
    ],
    "sg:phone":"+1 229 387 8170",
    "sg:postcode":"31794",
    "sg:province":"GA",
    "sg:tags":[
        "church"
    ],
    "wof:name":"Springfield Baptist Church",
    "wof:placetype":"venue"
},
  "geometry": {"coordinates":[-83.508422,31.438002],"type":"Point"}
}