{
  "type": "Feature",
  "properties": {
    "addr:full":"321 W Central Ave Moultrie GA 31768",
    "addr:housenumber":"321",
    "addr:postcode":"31768",
    "addr:street":"W Central Ave",
    "iso:country":"US",
    "sg:address":"321 W Central Ave",
    "sg:city":"Moultrie",
    "sg:classifiers":[
        {
            "category":"Retail",
            "subcategory":"Auto Repair",
            "type":"Services"
        }
    ],
    "sg:phone":"+1 229 217 4800",
    "sg:postcode":"31768",
    "sg:province":"GA",
    "sg:tags":[
        "general"
    ],
    "wof:name":"Flemming Garage",
    "wof:placetype":"venue"
},
  "geometry": {"coordinates":[-83.794425,31.179866],"type":"Point"}
}