{
  "type": "Feature",
  "properties": {
    "iso:country":"US",
    "sg:address":"1535 Old Covington Rd NE",
    "sg:city":"Conyers",
    "sg:classifiers":[
        {
            "category":"Manufacturing",
            "subcategory":"Chemicals & Compounds",
            "type":"Manufacturing & Wholesale Goods"
        }
    ],
    "sg:phone":"+1 770 922 3293",
    "sg:postcode":"30013",
    "sg:province":"GA",
    "sg:tags":[
        "industrial",
        "gas",
        "mfg"
    ],
    "wof:name":"Air Products",
    "wof:placetype":"venue"
},
  "geometry": {"coordinates":[-83.99888300000001,33.658485],"type":"Point"}
}