{
  "type": "Feature",
  "properties": {
    "iso:country":"US",
    "sg:address":"19 Whitewater Pl",
    "sg:city":"Sharpsburg",
    "sg:classifiers":[
        {
            "category":"Professional",
            "subcategory":"Computer Services",
            "type":"Services"
        }
    ],
    "sg:phone":"+1 770 502 0878",
    "sg:postcode":"30277",
    "sg:province":"GA",
    "sg:tags":[
        "home",
        "consulting",
        "page",
        "dev",
        "internet"
    ],
    "wof:name":"World Enterprise",
    "wof:placetype":"venue"
},
  "geometry": {"coordinates":[-84.6519,33.424346],"type":"Point"}
}