{
  "type": "Feature",
  "properties": {
    "iso:country":"US",
    "sg:address":"4035 Lendy Ln",
    "sg:city":"Atlanta",
    "sg:classifiers":[
        {
            "category":"Organizations",
            "subcategory":"Community Association",
            "type":"Services"
        }
    ],
    "sg:phone":"+1 404 344 6480",
    "sg:postcode":"30349",
    "sg:province":"GA",
    "wof:name":"Thaxton Pnte Homeowners Assn I",
    "wof:placetype":"venue"
},
  "geometry": {"coordinates":[-84.543313,33.643855],"type":"Point"}
}