{
  "type": "Feature",
  "properties": {
    "iso:country":"US",
    "sg:address":"5992 Old Dixie Hwy",
    "sg:city":"Forest Park",
    "sg:classifiers":[
        {
            "category":"Autos & Motor Vehicles",
            "subcategory":"Auto Supplies",
            "type":"Retail Goods"
        }
    ],
    "sg:phone":"+1 404 361 5352",
    "sg:postcode":"30297",
    "sg:province":"GA",
    "sg:tags":[
        "tire"
    ],
    "wof:name":"Mark's New & Used Tires",
    "wof:placetype":"venue"
},
  "geometry": {"coordinates":[-84.376999,33.591099],"type":"Point"}
}