{
  "type": "Feature",
  "properties": {
    "iso:country":"US",
    "sg:address":"5240 Kirk Dr",
    "sg:city":"Atlanta",
    "sg:classifiers":[
        {
            "category":"Professional",
            "type":"Services"
        },
        {
            "category":"Farming",
            "subcategory":"Fish & Marine Products",
            "type":"Manufacturing & Wholesale Goods"
        }
    ],
    "sg:phone":"+1 678 489 2755",
    "sg:postcode":"30349",
    "sg:province":"GA",
    "sg:tags":[
        "harvesting-contract"
    ],
    "wof:name":"Nehemiah General Contracting Company",
    "wof:placetype":"venue"
},
  "geometry": {"coordinates":[-84.430492,33.612462],"type":"Point"}
}