{
  "type": "Feature",
  "properties": {
    "addr:full":"3030 Bankhead Hwy Austell GA 30116",
    "addr:housenumber":"3030",
    "addr:postcode":"30116",
    "addr:street":"Bankhead Hwy",
    "iso:country":"US",
    "sg:address":"3030 Bankhead Hwy",
    "sg:city":"Austell",
    "sg:classifiers":[
        {
            "category":"Food & Beverages",
            "subcategory":"Groceries & Convenience Stores",
            "type":"Retail Goods"
        }
    ],
    "sg:phone":"+1 770 944 1839",
    "sg:postcode":"30116",
    "sg:province":"GA",
    "wof:name":"Winn-Dixie",
    "wof:placetype":"venue"
},
  "geometry": {"coordinates":[-84.982298,33.614116],"type":"Point"}
}