{
  "type": "Feature",
  "properties": {
    "addr:full":"2730 N Berkeley Lake Rd Duluth GA 30096",
    "addr:housenumber":"2730",
    "addr:postcode":"30096",
    "addr:street":"N Berkeley Lake Rd",
    "iso:country":"US",
    "sg:address":"2730 N Berkeley Lake Rd",
    "sg:city":"Duluth",
    "sg:classifiers":[
        {
            "category":"Home & Garden",
            "subcategory":"Carpets & Floor Coverings",
            "type":"Retail Goods"
        }
    ],
    "sg:phone":"+1 678 665 3752",
    "sg:postcode":"30096",
    "sg:province":"GA",
    "sg:tags":[
        "flooring"
    ],
    "sg:website":"checkmateflooring.com/",
    "wof:name":"Checkmate Flooring",
    "wof:placetype":"venue"
},
  "geometry": {"coordinates":[-84.161372,33.975305],"type":"Point"}
}