{
  "type": "Feature",
  "properties": {
    "addr:full":"310 Brookhollow Rd SE Dalton GA 30721",
    "addr:housenumber":"310",
    "addr:postcode":"30721",
    "addr:street":"Brookhollow Rd Se Dalton",
    "iso:country":"US",
    "sg:address":"310 Brookhollow Rd SE",
    "sg:city":"Dalton",
    "sg:classifiers":[
        {
            "category":"Manufacturing",
            "subcategory":"Retail Goods",
            "type":"Manufacturing & Wholesale Goods"
        }
    ],
    "sg:phone":"+1 706 226 1662",
    "sg:postcode":"30721",
    "sg:province":"GA",
    "sg:tags":[
        "manufacturer"
    ],
    "wof:name":"AMC Intl",
    "wof:placetype":"venue"
},
  "geometry": {"coordinates":[-84.960387,34.709749],"type":"Point"}
}