{
  "type": "Feature",
  "properties": {
    "addr:full":"7510 Wentworth Dr Duluth GA 30097",
    "addr:housenumber":"7510",
    "addr:postcode":"30097",
    "addr:street":"Wentworth Dr",
    "iso:country":"US",
    "sg:address":"7510 Wentworth Dr",
    "sg:city":"Duluth",
    "sg:classifiers":[
        {
            "category":"Real Estate",
            "subcategory":"Real Estate Agent",
            "type":"Services"
        }
    ],
    "sg:phone":"+1 770 232 8711",
    "sg:postcode":"30097",
    "sg:province":"GA",
    "sg:tags":[
        "business"
    ],
    "wof:name":"Appraisal Services Inc",
    "wof:placetype":"venue"
},
  "geometry": {"coordinates":[-84.151611,34.066801],"type":"Point"}
}