{
  "type": "Feature",
  "properties": {
    "addr:full":"5340 Connor Miles Dr Sugar Hill GA 30518",
    "addr:housenumber":"5340",
    "addr:postcode":"30518",
    "addr:street":"Connor Miles Dr",
    "iso:country":"US",
    "sg:address":"5340 Connor Miles Dr",
    "sg:city":"Sugar Hill",
    "sg:classifiers":[
        {
            "category":"Autos & Motor Vehicles",
            "subcategory":"Automobile Sales",
            "type":"Retail Goods"
        }
    ],
    "sg:phone":"+1 770 831 0109",
    "sg:postcode":"30518",
    "sg:province":"GA",
    "sg:tags":[
        "limo"
    ],
    "wof:name":"Personal Touch Limousine Service",
    "wof:placetype":"venue"
},
  "geometry": {"coordinates":[-84.04678699999999,34.113749],"type":"Point"}
}