{
  "type": "Feature",
  "properties": {
    "iso:country":"US",
    "sg:address":"604 15th Ave W",
    "sg:city":"Cordele",
    "sg:classifiers":[
        {
            "category":"Health Services",
            "subcategory":"Doctor",
            "type":"Services"
        }
    ],
    "sg:phone":"+1 229 273 5753",
    "sg:postcode":"31015",
    "sg:province":"GA",
    "sg:tags":[
        "dentist"
    ],
    "wof:name":"Willie R Bennett DDS",
    "wof:placetype":"venue"
},
  "geometry": {"coordinates":[-83.78955000000001,31.964631],"type":"Point"}
}