{
  "type": "Feature",
  "properties": {
    "addr:full":"3596 W Hill St Clarkston GA 30021",
    "addr:housenumber":"3596",
    "addr:postcode":"30021",
    "addr:street":"W Hill St",
    "iso:country":"US",
    "sg:address":"3596 W Hill St",
    "sg:city":"Clarkston",
    "sg:classifiers":[
        {
            "category":"Health Services",
            "subcategory":"Doctor",
            "type":"Services"
        }
    ],
    "sg:phone":"+1 404 499 2216",
    "sg:postcode":"30021",
    "sg:province":"GA",
    "wof:name":"Gentle Dental PC",
    "wof:placetype":"venue"
},
  "geometry": {"coordinates":[-84.244336,33.81167],"type":"Point"}
}