{
  "type": "Feature",
  "properties": {
    "iso:country":"US",
    "sg:address":"3430 Hapsburg Ct",
    "sg:city":"Snellville",
    "sg:classifiers":[
        {
            "category":"Sports & Exercise",
            "subcategory":"Race Track",
            "type":"Entertainment"
        }
    ],
    "sg:phone":"+1 770 602 0876",
    "sg:postcode":"30039",
    "sg:province":"GA",
    "sg:tags":[
        "promotion",
        "event"
    ],
    "wof:name":"Ride Out",
    "wof:placetype":"venue"
},
  "geometry": {"coordinates":[-84.011715,33.790972],"type":"Point"}
}