{
  "type": "Feature",
  "properties": {
    "addr:full":"153 Acorn St Douglas GA 31533",
    "addr:housenumber":"153",
    "addr:postcode":"31533",
    "addr:street":"Acorn St",
    "iso:country":"US",
    "sg:address":"153 Acorn St",
    "sg:city":"Douglas",
    "sg:classifiers":[
        {
            "category":"Building & Trades",
            "subcategory":"Construction",
            "type":"Services"
        }
    ],
    "sg:phone":"+1 912 383 6260",
    "sg:postcode":"31533",
    "sg:province":"GA",
    "sg:tags":[
        "concrete",
        "contractor"
    ],
    "wof:name":"Real S Concrete Creations",
    "wof:placetype":"venue"
},
  "geometry": {"coordinates":[-82.81932500000001,31.544827],"type":"Point"}
}