{
  "type": "Feature",
  "properties": {
    "addr:full":"925 Glynn St N Fayetteville GA 30214",
    "addr:housenumber":"925",
    "addr:postcode":"30214",
    "addr:street":"Glynn St N",
    "iso:country":"US",
    "sg:address":"925 Glynn St N",
    "sg:city":"Fayetteville",
    "sg:classifiers":[
        {
            "category":"Shopping",
            "subcategory":"Gifts & Souvenirs",
            "type":"Retail Goods"
        }
    ],
    "sg:phone":"+1 770 719 9512",
    "sg:postcode":"30214",
    "sg:province":"GA",
    "sg:tags":[
        "shop"
    ],
    "wof:name":"Clessie Jane's Cottage",
    "wof:placetype":"venue"
},
  "geometry": {"coordinates":[-84.447422,33.466991],"type":"Point"}
}