{
  "type": "Feature",
  "properties": {
    "addr:full":"322 Spaulding Rd Montezuma GA 31063",
    "addr:housenumber":"322",
    "addr:postcode":"31063",
    "addr:street":"Spaulding Rd",
    "iso:country":"US",
    "sg:address":"322 Spaulding Rd",
    "sg:city":"Montezuma",
    "sg:classifiers":[
        {
            "category":"Food & Beverages",
            "subcategory":"Groceries & Convenience Stores",
            "type":"Retail Goods"
        }
    ],
    "sg:phone":"+1 478 472 7211",
    "sg:postcode":"31063",
    "sg:province":"GA",
    "wof:name":"Qwik Stop",
    "wof:placetype":"venue"
},
  "geometry": {"coordinates":[-84.02607399999999,32.296701],"type":"Point"}
}