{
  "type": "Feature",
  "properties": {
    "iso:country":"US",
    "sg:address":"3672 Columbia Pkwy",
    "sg:city":"Decatur",
    "sg:classifiers":[
        {
            "category":"Shopping",
            "subcategory":"Gifts & Souvenirs",
            "type":"Retail Goods"
        }
    ],
    "sg:phone":"+1 404 914 0671",
    "sg:postcode":"30034",
    "sg:province":"GA",
    "wof:name":"Amazing Balloons",
    "wof:placetype":"venue"
},
  "geometry": {"coordinates":[-84.23820000000001,33.697942],"type":"Point"}
}