{
  "type": "Feature",
  "properties": {
    "iso:country":"US",
    "sg:address":"1958 Smyrna Church Rd",
    "sg:city":"Chatsworth",
    "sg:classifiers":[
        {
            "category":"Shopping",
            "type":"Retail Goods"
        }
    ],
    "sg:phone":"+1 706 422 8198",
    "sg:postcode":"30705",
    "sg:province":"GA",
    "sg:tags":[
        "merchandise"
    ],
    "wof:name":"Holly Dollar",
    "wof:placetype":"venue"
},
  "geometry": {"coordinates":[-84.782366,34.729621],"type":"Point"}
}