{
  "type": "Feature",
  "properties": {
    "iso:country":"US",
    "sg:address":"7 Middleton Rd",
    "sg:city":"Savannah",
    "sg:classifiers":[
        {
            "category":"Health Services",
            "subcategory":"Clinic",
            "type":"Services"
        }
    ],
    "sg:phone":"+1 912 598 9001",
    "sg:postcode":"31411",
    "sg:province":"GA",
    "wof:name":"A Fitness Affair",
    "wof:placetype":"venue"
},
  "geometry": {"coordinates":[-81.033625,31.932883],"type":"Point"}
}