{
  "type": "Feature",
  "properties": {
    "addr:full":"122 Angela Ln Dallas GA 30132",
    "addr:housenumber":"122",
    "addr:postcode":"30132",
    "addr:street":"Angela Ln",
    "iso:country":"US",
    "sg:address":"122 Angela Ln",
    "sg:city":"Dallas",
    "sg:classifiers":[
        {
            "category":"Professional",
            "subcategory":"Engineering",
            "type":"Services"
        }
    ],
    "sg:phone":"+1 770 443 6933",
    "sg:postcode":"30132",
    "sg:province":"GA",
    "wof:name":"Camp Engineering",
    "wof:placetype":"venue"
},
  "geometry": {"coordinates":[-84.834216,34.039647],"type":"Point"}
}