{
  "type": "Feature",
  "properties": {
    "addr:full":"2530 State Rte 51 S Lula GA 30554",
    "addr:housenumber":"2530",
    "addr:postcode":"30554",
    "addr:street":"State Rte 51 S Lula",
    "iso:country":"US",
    "sg:address":"2530 State Rte 51 S",
    "sg:city":"Lula",
    "sg:classifiers":[
        {
            "category":"Organizations",
            "subcategory":"Religious Organization",
            "type":"Services"
        }
    ],
    "sg:phone":"+1 770 725 4004",
    "sg:postcode":"30554",
    "sg:province":"GA",
    "wof:name":"Believers Tabernacle",
    "wof:placetype":"venue"
},
  "geometry": {"coordinates":[-83.57733399999999,34.352974],"type":"Point"}
}