{
  "type": "Feature",
  "properties": {
    "iso:country":"US",
    "sg:address":"40 Gwinnett St",
    "sg:city":"Buford",
    "sg:classifiers":[
        {
            "category":"Home & Garden",
            "subcategory":"Building Materials",
            "type":"Retail Goods"
        }
    ],
    "sg:phone":"+1 678 482 0388",
    "sg:postcode":"30518",
    "sg:province":"GA",
    "sg:tags":[
        "door"
    ],
    "wof:name":"Metro Garage Doors",
    "wof:placetype":"venue"
},
  "geometry": {"coordinates":[-84.00582799999999,34.124492],"type":"Point"}
}