{
  "type": "Feature",
  "properties": {
    "iso:country":"US",
    "sg:address":"5176 Pelican Dr",
    "sg:city":"Atlanta",
    "sg:classifiers":[
        {
            "category":"Travel",
            "subcategory":"Travel Agent",
            "type":"Entertainment"
        }
    ],
    "sg:phone":"+1 770 997 1915",
    "sg:postcode":"30349",
    "sg:province":"GA",
    "sg:tags":[
        "consultant",
        "transportation"
    ],
    "wof:name":"Nippon Express USA Inc",
    "wof:placetype":"venue"
},
  "geometry": {"coordinates":[-84.425377,33.61364],"type":"Point"}
}