{
  "type": "Feature",
  "properties": {
    "addr:full":"1505 Hog Mountain Rd Winder GA 30680",
    "addr:housenumber":"1505",
    "addr:postcode":"30680",
    "addr:street":"Hog Mountain Rd",
    "iso:country":"US",
    "sg:address":"1505 Hog Mountain Rd",
    "sg:city":"Winder",
    "sg:classifiers":[
        {
            "category":"Wholesale",
            "subcategory":"Construction Materials",
            "type":"Manufacturing & Wholesale Goods"
        },
        {
            "category":"Building & Trades",
            "subcategory":"Landscaping Services",
            "type":"Services"
        }
    ],
    "sg:phone":"+1 770 725 2374",
    "sg:postcode":"30680",
    "sg:province":"GA",
    "sg:tags":[
        "supp",
        "tr",
        "special",
        "fence"
    ],
    "wof:name":"Tapp's Landscape & Fence",
    "wof:placetype":"venue"
},
  "geometry": {"coordinates":[-83.635676,33.938465],"type":"Point"}
}