{
  "type": "Feature",
  "properties": {
    "iso:country":"US",
    "sg:address":"64 Hamp Mill Rd",
    "sg:city":"Dahlonega",
    "sg:classifiers":[
        {
            "category":"Building & Trades",
            "subcategory":"Construction",
            "type":"Services"
        }
    ],
    "sg:phone":"+1 706 864 0851",
    "sg:postcode":"30533",
    "sg:province":"GA",
    "sg:tags":[
        "roofing",
        "gutter",
        "sheet",
        "work",
        "metal",
        "downspouts",
        "siding"
    ],
    "wof:name":"Georgia North Aluminum Inc",
    "wof:placetype":"venue"
},
  "geometry": {"coordinates":[-84.00765800000001,34.532278],"type":"Point"}
}