{
  "type": "Feature",
  "properties": {
    "addr:full":"3028 Washington Rd Atlanta GA 30344",
    "addr:housenumber":"3028",
    "addr:postcode":"30344",
    "addr:street":"Washington Rd",
    "iso:country":"US",
    "sg:address":"3028 Washington Rd",
    "sg:city":"Atlanta",
    "sg:classifiers":[
        {
            "category":"Real Estate",
            "subcategory":"Real Estate Agent",
            "type":"Services"
        }
    ],
    "sg:phone":"+1 404 766 6612",
    "sg:postcode":"30344",
    "sg:province":"GA",
    "wof:name":"Advantage One Realty Inc",
    "wof:placetype":"venue"
},
  "geometry": {"coordinates":[-84.456946,33.672615],"type":"Point"}
}