{
  "type": "Feature",
  "properties": {
    "addr:full":"1780 Corporate Dr Norcross GA 30093",
    "addr:housenumber":"1780",
    "addr:postcode":"30093",
    "addr:street":"Corporate Dr",
    "iso:country":"US",
    "sg:address":"1780 Corporate Dr",
    "sg:city":"Norcross",
    "sg:classifiers":[
        {
            "category":"Building & Trades",
            "subcategory":"Cleaning & Sanitation",
            "type":"Services"
        }
    ],
    "sg:phone":"+1 770 921 6594",
    "sg:postcode":"30093",
    "sg:province":"GA",
    "wof:name":"CBM Inc",
    "wof:placetype":"venue"
},
  "geometry": {"coordinates":[-84.14837799999999,33.940223],"type":"Point"}
}