{
  "type": "Feature",
  "properties": {
    "iso:country":"US",
    "sg:address":"2014 Iris Dr SE",
    "sg:city":"Conyers",
    "sg:classifiers":[
        {
            "category":"Autos & Motor Vehicles",
            "subcategory":"Automobile Sales",
            "type":"Retail Goods"
        }
    ],
    "sg:phone":"+1 770 922 9557",
    "sg:postcode":"30013",
    "sg:province":"GA",
    "sg:tags":[
        "new",
        "car"
    ],
    "wof:name":"Prime Auto Finance",
    "wof:placetype":"venue"
},
  "geometry": {"coordinates":[-83.980986,33.637054],"type":"Point"}
}