{
  "type": "Feature",
  "properties": {
    "iso:country":"US",
    "sg:address":"3725 E Bay St",
    "sg:city":"Duluth",
    "sg:classifiers":[
        {
            "category":"Building & Trades",
            "subcategory":"Cleaning & Sanitation",
            "type":"Services"
        }
    ],
    "sg:phone":"+1 770 495 1766",
    "sg:postcode":"30096",
    "sg:province":"GA",
    "sg:tags":[
        "home"
    ],
    "sg:website":"www.topqualitysvs.com",
    "wof:name":"Top Quality Services Inc",
    "wof:placetype":"venue"
},
  "geometry": {"coordinates":[-84.163597,33.996601],"type":"Point"}
}