{
  "type": "Feature",
  "properties": {
    "iso:country":"US",
    "sg:address":"342 29th St",
    "sg:city":"Columbus",
    "sg:classifiers":[
        {
            "category":"Building & Trades",
            "subcategory":"Electrical",
            "type":"Services"
        }
    ],
    "sg:phone":"+1 706 327 5144",
    "sg:postcode":"31904",
    "sg:province":"GA",
    "sg:tags":[
        "repair",
        "electrical",
        "contractor"
    ],
    "wof:name":"Industrial Controls & Electric",
    "wof:placetype":"venue"
},
  "geometry": {"coordinates":[-84.98694500000001,32.490622],"type":"Point"}
}