{
  "type": "Feature",
  "properties": {
    "addr:full":"6009 Betty Dr Savannah GA 31406",
    "addr:housenumber":"6009",
    "addr:postcode":"31406",
    "addr:street":"Betty Dr",
    "iso:country":"US",
    "sg:address":"6009 Betty Dr",
    "sg:city":"Savannah",
    "sg:classifiers":[
        {
            "category":"Building & Trades",
            "subcategory":"Construction",
            "type":"Services"
        }
    ],
    "sg:phone":"+1 912 354 4821",
    "sg:postcode":"31406",
    "sg:province":"GA",
    "sg:tags":[
        "floor",
        "laying",
        "contractor"
    ],
    "wof:name":"Michael Jordan Carpet",
    "wof:placetype":"venue"
},
  "geometry": {"coordinates":[-81.07361299999999,32.007928],"type":"Point"}
}