{
  "type": "Feature",
  "properties": {
    "addr:full":"113 College St Cuthbert GA 31774",
    "addr:housenumber":"113",
    "addr:postcode":"31774",
    "addr:street":"College St",
    "iso:country":"US",
    "sg:address":"113 College St",
    "sg:city":"Cuthbert",
    "sg:classifiers":[
        {
            "category":"Health Services",
            "subcategory":"Clinic",
            "type":"Services"
        }
    ],
    "sg:phone":"+1 229 732 3734",
    "sg:postcode":"31774",
    "sg:province":"GA",
    "wof:name":"Phoebe Home Care",
    "wof:placetype":"venue"
},
  "geometry": {"coordinates":[-83.24064799999999,31.594177],"type":"Point"}
}