{
  "type": "Feature",
  "properties": {
    "iso:country":"US",
    "sg:address":"1945 Godby Rd",
    "sg:city":"Atlanta",
    "sg:classifiers":[
        {
            "category":"Real Estate",
            "subcategory":"Real Estate Agent",
            "type":"Services"
        }
    ],
    "sg:phone":"+1 770 996 5600",
    "sg:postcode":"30349",
    "sg:province":"GA",
    "wof:name":"Jogm's Properties",
    "wof:placetype":"venue"
},
  "geometry": {"coordinates":[-84.450346,33.613446],"type":"Point"}
}