{
  "type": "Feature",
  "properties": {
    "iso:country":"US",
    "sg:address":"25 Brookside Dr",
    "sg:city":"Newnan",
    "sg:classifiers":[
        {
            "category":"Professional",
            "subcategory":"Lawyer & Legal Services",
            "type":"Services"
        }
    ],
    "sg:phone":"+1 770 253 8248",
    "sg:postcode":"30263",
    "sg:province":"GA",
    "wof:name":"James C Strippling",
    "wof:placetype":"venue"
},
  "geometry": {"coordinates":[-84.805768,33.390753],"type":"Point"}
}