{
  "type": "Feature",
  "properties": {
    "addr:full":"1708 Scenic Hwy N Snellville GA 30078",
    "addr:housenumber":"1708",
    "addr:postcode":"30078",
    "addr:street":"Scenic Hwy N",
    "iso:country":"US",
    "sg:address":"1708 Scenic Hwy N",
    "sg:city":"Snellville",
    "sg:classifiers":[
        {
            "category":"Restaurant",
            "type":"Food & Drink"
        }
    ],
    "sg:menulink":"http://www.allmenus.com/ga/snellville-grayson/54411-atlanta-bread-company/menu/",
    "sg:phone":"+1 678 344 9099",
    "sg:postcode":"30078",
    "sg:province":"GA",
    "sg:tags":[
        "american"
    ],
    "wof:name":"Atlanta Bread Company",
    "wof:placetype":"venue"
},
  "geometry": {"coordinates":[-84.011313,33.881675],"type":"Point"}
}