{
  "type": "Feature",
  "properties": {
    "addr:full":"4157 US Hwy 27 Cataula GA 31804",
    "addr:housenumber":"4157",
    "addr:postcode":"31804",
    "addr:street":"Us Hwy 27 Cataula",
    "iso:country":"US",
    "sg:address":"4157 US Hwy 27",
    "sg:city":"Cataula",
    "sg:classifiers":[
        {
            "category":"Autos & Motor Vehicles",
            "subcategory":"Automobile Sales",
            "type":"Retail Goods"
        }
    ],
    "sg:phone":"+1 706 596 1155",
    "sg:postcode":"31804",
    "sg:province":"GA",
    "sg:tags":[
        "car",
        "dealer"
    ],
    "wof:name":"Cataula Auto Sales",
    "wof:placetype":"venue"
},
  "geometry": {"coordinates":[-84.872818,32.650426],"type":"Point"}
}