{
  "type": "Feature",
  "properties": {
    "addr:full":"3515 Chamblee Tucker Rd Atlanta GA 30341",
    "addr:housenumber":"3515",
    "addr:postcode":"30341",
    "addr:street":"Chamblee Tucker Rd",
    "iso:country":"US",
    "sg:address":"3515 Chamblee Tucker Rd",
    "sg:city":"Atlanta",
    "sg:classifiers":[
        {
            "category":"Banks & Credit Unions",
            "subcategory":"Bank",
            "type":"Services"
        }
    ],
    "sg:phone":"+1 770 454 0359",
    "sg:postcode":"30341",
    "sg:province":"GA",
    "wof:name":"Washington Mutual",
    "wof:placetype":"venue"
},
  "geometry": {"coordinates":[-84.249342,33.885516],"type":"Point"}
}