{
  "type": "Feature",
  "properties": {
    "iso:country":"US",
    "sg:address":"1429 Holly Ln NE",
    "sg:city":"Atlanta",
    "sg:classifiers":[
        {
            "category":"Manufacturing",
            "subcategory":"Apparel",
            "type":"Manufacturing & Wholesale Goods"
        }
    ],
    "sg:phone":"+1 404 634 5353",
    "sg:postcode":"30329",
    "sg:province":"GA",
    "sg:tags":[
        "household",
        "furnishing",
        "mfg"
    ],
    "wof:name":"Elegant Covers",
    "wof:placetype":"venue"
},
  "geometry": {"coordinates":[-84.32219600000001,33.821306],"type":"Point"}
}