{
  "type": "Feature",
  "properties": {
    "iso:country":"US",
    "sg:address":"223 S Sims St",
    "sg:city":"Bainbridge",
    "sg:classifiers":[
        {
            "category":"Food & Beverages",
            "subcategory":"Bakery",
            "type":"Retail Goods"
        }
    ],
    "sg:phone":"+1 229 246 7108",
    "sg:postcode":"39817",
    "sg:province":"GA",
    "sg:tags":[
        "baker"
    ],
    "wof:name":"Flowers Discount Bakery",
    "wof:placetype":"venue"
},
  "geometry": {"coordinates":[-84.56153500000001,30.904596],"type":"Point"}
}