{
  "type": "Feature",
  "properties": {
    "addr:full":"415 W Railroad St S Pelham GA 31779",
    "addr:housenumber":"415",
    "addr:postcode":"31779",
    "addr:street":"W Railroad St S",
    "iso:country":"US",
    "sg:address":"415 W Railroad St S",
    "sg:city":"Pelham",
    "sg:classifiers":[
        {
            "category":"Government",
            "subcategory":"City Hall",
            "type":"Public Place"
        },
        {
            "category":"Government",
            "subcategory":"Office",
            "type":"Public Place"
        }
    ],
    "sg:phone":"+1 229 294 7900",
    "sg:postcode":"31779",
    "sg:province":"GA",
    "sg:tags":[
        "town",
        "township",
        "planner",
        "government-city",
        "village"
    ],
    "wof:name":"Pelham City Of",
    "wof:placetype":"venue"
},
  "geometry": {"coordinates":[-84.151118,31.118656],"type":"Point"}
}