{
  "type": "Feature",
  "properties": {
    "iso:country":"US",
    "sg:address":"134 N Main St",
    "sg:city":"Alpharetta",
    "sg:classifiers":[
        {
            "category":"Health Services",
            "subcategory":"Doctor",
            "type":"Services"
        }
    ],
    "sg:phone":"+1 770 664 6245",
    "sg:postcode":"30004",
    "sg:province":"GA",
    "sg:tags":[
        "surgeon",
        "oral"
    ],
    "wof:name":"Robert J O'donnell, DDS",
    "wof:placetype":"venue"
},
  "geometry": {"coordinates":[-84.294403,34.079601],"type":"Point"}
}