{
  "type": "Feature",
  "properties": {
    "addr:full":"418 Whigham Dairy Rd Bainbridge GA 39817",
    "addr:housenumber":"418",
    "addr:postcode":"39817",
    "addr:street":"Whigham Dairy Rd",
    "iso:country":"US",
    "sg:address":"418 Whigham Dairy Rd",
    "sg:city":"Bainbridge",
    "sg:classifiers":[
        {
            "category":"Retail",
            "subcategory":"Auto Repair",
            "type":"Services"
        }
    ],
    "sg:phone":"+1 229 243 8867",
    "sg:postcode":"39817",
    "sg:province":"GA",
    "sg:tags":[
        "body",
        "automobile",
        "painting"
    ],
    "wof:name":"Tim's Automotive & Paint",
    "wof:placetype":"venue"
},
  "geometry": {"coordinates":[-84.53584600000001,30.927622],"type":"Point"}
}