{
  "type": "Feature",
  "properties": {
    "iso:country":"US",
    "sg:address":"2392 N Decatur Rd",
    "sg:city":"Decatur",
    "sg:classifiers":[
        {
            "category":"Professional",
            "subcategory":"Lawyer & Legal Services",
            "type":"Services"
        }
    ],
    "sg:phone":"+1 404 633 3797",
    "sg:postcode":"30033",
    "sg:province":"GA",
    "sg:website":"www.msheinlaw.com",
    "wof:name":"National Legal Services",
    "wof:placetype":"venue"
},
  "geometry": {"coordinates":[-84.295147,33.793318],"type":"Point"}
}