{
  "type": "Feature",
  "properties": {
    "addr:full":"145 Essex Cir Fayetteville GA 30215",
    "addr:housenumber":"145",
    "addr:postcode":"30215",
    "addr:street":"Essex Cir",
    "iso:country":"US",
    "sg:address":"145 Essex Cir",
    "sg:city":"Fayetteville",
    "sg:classifiers":[
        {
            "category":"Professional",
            "subcategory":"Engineering",
            "type":"Services"
        }
    ],
    "sg:phone":"+1 770 461 0914",
    "sg:postcode":"30215",
    "sg:province":"GA",
    "wof:name":"Dennis S Poore",
    "wof:placetype":"venue"
},
  "geometry": {"coordinates":[-84.449934,33.418613],"type":"Point"}
}