{
  "type": "Feature",
  "properties": {
    "iso:country":"US",
    "sg:address":"504 9th St E",
    "sg:city":"Tifton",
    "sg:classifiers":[
        {
            "category":"Building & Trades",
            "subcategory":"Construction",
            "type":"Services"
        }
    ],
    "sg:phone":"+1 229 382 3808",
    "sg:postcode":"31794",
    "sg:province":"GA",
    "sg:tags":[
        "general",
        "contractor"
    ],
    "wof:name":"Sunbelt Investment Properties",
    "wof:placetype":"venue"
},
  "geometry": {"coordinates":[-83.50712799999999,31.449164],"type":"Point"}
}