{
  "type": "Feature",
  "properties": {
    "addr:full":"254 Johnson Ferry Rd NE Atlanta GA 30328",
    "addr:housenumber":"254",
    "addr:postcode":"30328",
    "addr:street":"Johnson Ferry Rd Ne",
    "iso:country":"US",
    "sg:address":"254 Johnson Ferry Rd NE",
    "sg:city":"Atlanta",
    "sg:classifiers":[
        {
            "category":"Government",
            "subcategory":"Office",
            "type":"Public Place"
        }
    ],
    "sg:phone":"+1 404 303 6172",
    "sg:postcode":"30328",
    "sg:province":"GA",
    "sg:tags":[
        "gallery"
    ],
    "wof:name":"Arts Council",
    "wof:placetype":"venue"
},
  "geometry": {"coordinates":[-84.376859,33.924474],"type":"Point"}
}