{
  "type": "Feature",
  "properties": {
    "addr:full":"3266 Greenvale Way Decatur GA 30034",
    "addr:housenumber":"3266",
    "addr:postcode":"30034",
    "addr:street":"Greenvale Way",
    "iso:country":"US",
    "sg:address":"3266 Greenvale Way",
    "sg:city":"Decatur",
    "sg:classifiers":[
        {
            "category":"Banks & Credit Unions",
            "subcategory":"Financial Services",
            "type":"Services"
        }
    ],
    "sg:phone":"+1 770 313 1518",
    "sg:postcode":"30034",
    "sg:province":"GA",
    "sg:tags":[
        "development",
        "investment",
        "real estate"
    ],
    "wof:name":"Newton Capital LLC",
    "wof:placetype":"venue"
},
  "geometry": {"coordinates":[-84.213213,33.688804],"type":"Point"}
}