{
  "type": "Feature",
  "properties": {
    "iso:country":"US",
    "sg:address":"809 Windsor Rd",
    "sg:city":"Macon",
    "sg:classifiers":[
        {
            "category":"Home & Garden",
            "subcategory":"Building Materials",
            "type":"Retail Goods"
        }
    ],
    "sg:phone":"+1 478 476 8535",
    "sg:postcode":"31204",
    "sg:province":"GA",
    "wof:name":"Mr Handyman Home Imprv Svcs",
    "wof:placetype":"venue"
},
  "geometry": {"coordinates":[-83.677086,32.883096],"type":"Point"}
}