{
  "type": "Feature",
  "properties": {
    "iso:country":"US",
    "sg:address":"9 W Johnston St",
    "sg:city":"Forsyth",
    "sg:classifiers":[
        {
            "category":"Professional",
            "subcategory":"Credit Reporting & Collection",
            "type":"Services"
        }
    ],
    "sg:phone":"+1 478 994 3441",
    "sg:postcode":"31029",
    "sg:province":"GA",
    "sg:tags":[
        "agency"
    ],
    "wof:name":"Monroe County Collection Svcs",
    "wof:placetype":"venue"
},
  "geometry": {"coordinates":[-83.939312,33.035005],"type":"Point"}
}