{
  "type": "Feature",
  "properties": {
    "addr:full":"8465 Holcomb Bridge Rd Alpharetta GA 30022",
    "addr:housenumber":"8465",
    "addr:postcode":"30022",
    "addr:street":"Holcomb Bridge Rd",
    "iso:country":"US",
    "sg:address":"8465 Holcomb Bridge Rd",
    "sg:city":"Alpharetta",
    "sg:classifiers":[
        {
            "category":"Cinema",
            "subcategory":"Movie Rental",
            "type":"Entertainment"
        }
    ],
    "sg:phone":"+1 770 650 1414",
    "sg:postcode":"30022",
    "sg:province":"GA",
    "sg:tags":[
        "video",
        "tape"
    ],
    "wof:name":"Blockbuster",
    "wof:placetype":"venue"
},
  "geometry": {"coordinates":[-84.270566,33.986069],"type":"Point"}
}