{
  "type": "Feature",
  "properties": {
    "addr:full":"2300 Holcomb Bridge Rd Roswell GA 30076",
    "addr:housenumber":"2300",
    "addr:postcode":"30076",
    "addr:street":"Holcomb Bridge Rd",
    "iso:country":"US",
    "sg:address":"2300 Holcomb Bridge Rd",
    "sg:city":"Roswell",
    "sg:classifiers":[
        {
            "category":"Personal",
            "subcategory":"Barber",
            "type":"Services"
        }
    ],
    "sg:phone":"+1 770 645 8011",
    "sg:postcode":"30076",
    "sg:province":"GA",
    "wof:name":"Great Clips For Hair",
    "wof:placetype":"venue"
},
  "geometry": {"coordinates":[-84.29450199999999,34.003502],"type":"Point"}
}