{
  "type": "Feature",
  "properties": {
    "addr:full":"106 Callaway St Leesburg GA 31763",
    "addr:housenumber":"106",
    "addr:postcode":"31763",
    "addr:street":"Callaway St",
    "iso:country":"US",
    "sg:address":"106 Callaway St",
    "sg:city":"Leesburg",
    "sg:classifiers":[
        {
            "category":"Place Of Worship",
            "subcategory":"Church",
            "type":"Public Place"
        },
        {
            "category":"Place Of Worship",
            "type":"Public Place"
        }
    ],
    "sg:phone":"+1 229 759 2030",
    "sg:postcode":"31763",
    "sg:province":"GA",
    "sg:tags":[
        "testament",
        "christ-new",
        "churches-church",
        "christ"
    ],
    "sg:website":"http://www.leesburgcofc.org",
    "wof:name":"Leesburg Church Of Christ, Inc.",
    "wof:placetype":"venue"
},
  "geometry": {"coordinates":[-84.17314500000001,31.731279],"type":"Point"}
}