{
  "type": "Feature",
  "properties": {
    "iso:country":"US",
    "sg:address":"5131 Old National Hwy",
    "sg:city":"Atlanta",
    "sg:classifiers":[
        {
            "category":"Professional",
            "subcategory":"Business Services",
            "type":"Services"
        }
    ],
    "sg:phone":"+1 404 766 7377",
    "sg:postcode":"30349",
    "sg:province":"GA",
    "wof:name":"Down 4 Life LLC",
    "wof:placetype":"venue"
},
  "geometry": {"coordinates":[-84.472825,33.616099],"type":"Point"}
}