{
  "type": "Feature",
  "properties": {
    "iso:country":"US",
    "sg:address":"1135 Duncan Rd",
    "sg:city":"Oxford",
    "sg:classifiers":[
        {
            "category":"Professional",
            "subcategory":"Management & Consulting",
            "type":"Services"
        }
    ],
    "sg:phone":"+1 770 786 6836",
    "sg:postcode":"30054",
    "sg:province":"GA",
    "sg:tags":[
        "business"
    ],
    "wof:name":"Reinhardt Enterprises Inc",
    "wof:placetype":"venue"
},
  "geometry": {"coordinates":[-83.882953,33.686288],"type":"Point"}
}