{
  "type": "Feature",
  "properties": {
    "addr:full":"9575 Red Bird Ln Alpharetta GA 30022",
    "addr:housenumber":"9575",
    "addr:postcode":"30022",
    "addr:street":"Red Bird Ln",
    "iso:country":"US",
    "sg:address":"9575 Red Bird Ln",
    "sg:city":"Alpharetta",
    "sg:classifiers":[
        {
            "category":"Professional",
            "subcategory":"Computer Services",
            "type":"Services"
        }
    ],
    "sg:phone":"+1 678 867 0524",
    "sg:postcode":"30022",
    "sg:province":"GA",
    "sg:tags":[
        "related"
    ],
    "wof:name":"Dataflo Inc",
    "wof:placetype":"venue"
},
  "geometry": {"coordinates":[-84.21603500000001,34.015996],"type":"Point"}
}