{
  "type": "Feature",
  "properties": {
    "addr:full":"1003 Brown St Dalton GA 30720",
    "addr:housenumber":"1003",
    "addr:postcode":"30720",
    "addr:street":"Brown St",
    "iso:country":"US",
    "sg:address":"1003 Brown St",
    "sg:city":"Dalton",
    "sg:classifiers":[
        {
            "category":"Wholesale",
            "subcategory":"Electrical",
            "type":"Manufacturing & Wholesale Goods"
        }
    ],
    "sg:phone":"+1 706 370 5822",
    "sg:postcode":"30720",
    "sg:province":"GA",
    "sg:tags":[
        "equipment"
    ],
    "wof:name":"Southeastern Lighting Electric",
    "wof:placetype":"venue"
},
  "geometry": {"coordinates":[-84.97403799999999,34.75796],"type":"Point"}
}