{
  "type": "Feature",
  "properties": {
    "addr:full":"1725 Poplar Springs Rd SW Hiram GA 30141",
    "addr:housenumber":"1725",
    "addr:postcode":"30141",
    "addr:street":"Poplar Springs Rd Sw",
    "iso:country":"US",
    "sg:address":"1725 Poplar Springs Rd SW",
    "sg:city":"Hiram",
    "sg:classifiers":[
        {
            "category":"Building & Trades",
            "subcategory":"Construction",
            "type":"Services"
        }
    ],
    "sg:phone":"+1 770 943 1593",
    "sg:postcode":"30141",
    "sg:province":"GA",
    "sg:tags":[
        "home",
        "builder"
    ],
    "wof:name":"Helton Homes",
    "wof:placetype":"venue"
},
  "geometry": {"coordinates":[-84.723736,33.917202],"type":"Point"}
}