{
  "type": "Feature",
  "properties": {
    "iso:country":"US",
    "sg:address":"11423 Hwy 53 E",
    "sg:city":"Marble Hill",
    "sg:classifiers":[
        {
            "category":"Retail",
            "subcategory":"Veterinary Services",
            "type":"Services"
        }
    ],
    "sg:phone":"+1 770 893 4865",
    "sg:postcode":"30148",
    "sg:province":"GA",
    "wof:name":"Marble Hill Veterinary Clinic",
    "wof:placetype":"venue"
},
  "geometry": {"coordinates":[-84.31527199999999,34.416928],"type":"Point"}
}