{
  "type": "Feature",
  "properties": {
    "iso:country":"US",
    "sg:address":"15 Peachtree St NE",
    "sg:city":"Atlanta",
    "sg:classifiers":[
        {
            "category":"Parking",
            "type":"Transportation"
        }
    ],
    "sg:phone":"+1 404 577 1502",
    "sg:postcode":"30303",
    "sg:province":"GA",
    "sg:tags":[
        "automobile"
    ],
    "wof:name":"Selig Parking Inc",
    "wof:placetype":"venue"
},
  "geometry": {"coordinates":[-84.38746999999999,33.762199],"type":"Point"}
}