{
  "type": "Feature",
  "properties": {
    "iso:country":"US",
    "sg:address":"1296 Johnson Brady Rd",
    "sg:city":"Canton",
    "sg:classifiers":[
        {
            "category":"Farming",
            "subcategory":"Livestock Farm",
            "type":"Manufacturing & Wholesale Goods"
        }
    ],
    "sg:phone":"+1 770 479 3883",
    "sg:postcode":"30115",
    "sg:province":"GA",
    "sg:tags":[
        "primarily",
        "animal",
        "general"
    ],
    "wof:name":"Butterfly Farms",
    "wof:placetype":"venue"
},
  "geometry": {"coordinates":[-84.382848,34.232804],"type":"Point"}
}