{
  "type": "Feature",
  "properties": {
    "addr:full":"425 Park Way Augusta GA 30907",
    "addr:housenumber":"425",
    "addr:postcode":"30907",
    "addr:street":"Park Way",
    "iso:country":"US",
    "sg:address":"425 Park Way",
    "sg:city":"Augusta",
    "sg:classifiers":[
        {
            "category":"Professional",
            "type":"Services"
        }
    ],
    "sg:phone":"+1 706 868 7088",
    "sg:postcode":"30907",
    "sg:province":"GA",
    "sg:tags":[
        "establishment"
    ],
    "wof:name":"Bomark Sportwear",
    "wof:placetype":"venue"
},
  "geometry": {"coordinates":[-82.125646,33.500115],"type":"Point"}
}