{
  "type": "Feature",
  "properties": {
    "iso:country":"US",
    "sg:address":"2209 Mitchell Rd",
    "sg:city":"Warrenton",
    "sg:classifiers":[
        {
            "category":"Restaurant",
            "type":"Food & Drink"
        }
    ],
    "sg:phone":"+1 706 465 2865",
    "sg:postcode":"30820",
    "sg:province":"GA",
    "sg:tags":[
        "eating"
    ],
    "wof:name":"Shirley Cheeley",
    "wof:placetype":"venue"
},
  "geometry": {"coordinates":[-82.697993,33.348425],"type":"Point"}
}