{
  "type": "Feature",
  "properties": {
    "addr:full":"195 Ishman Ballard Rd Newnan GA 30263",
    "addr:housenumber":"195",
    "addr:postcode":"30263",
    "addr:street":"Ishman Ballard Rd",
    "iso:country":"US",
    "sg:address":"195 Ishman Ballard Rd",
    "sg:city":"Newnan",
    "sg:classifiers":[
        {
            "category":"Bars & Pubs",
            "type":"Food & Drink"
        }
    ],
    "sg:phone":"+1 678 423 3377",
    "sg:postcode":"30263",
    "sg:province":"GA",
    "wof:name":"High Definition Sports Bar",
    "wof:placetype":"venue"
},
  "geometry": {"coordinates":[-84.85077,33.376597],"type":"Point"}
}