{
  "type": "Feature",
  "properties": {
    "iso:country":"US",
    "sg:address":"280 Sandy Springs Cir NE",
    "sg:city":"Atlanta",
    "sg:classifiers":[
        {
            "category":"Banks & Credit Unions",
            "subcategory":"Bank",
            "type":"Services"
        }
    ],
    "sg:phone":"+1 404 255 7131",
    "sg:postcode":"30328",
    "sg:province":"GA",
    "wof:name":"Bank of North Georgia",
    "wof:placetype":"venue"
},
  "geometry": {"coordinates":[-84.38301800000001,33.926431],"type":"Point"}
}