{
  "type": "Feature",
  "properties": {
    "iso:country":"US",
    "sg:address":"1016 Lafayette Rd",
    "sg:city":"Chickamauga",
    "sg:classifiers":[
        {
            "category":"Restaurant",
            "type":"Food & Drink"
        }
    ],
    "sg:phone":"+1 706 375 1550",
    "sg:postcode":"30707",
    "sg:province":"GA",
    "sg:tags":[
        "eating"
    ],
    "wof:name":"Sonic Chickamauga GA L",
    "wof:placetype":"venue"
},
  "geometry": {"coordinates":[-85.26853300000001,34.872957],"type":"Point"}
}