{
  "type": "Feature",
  "properties": {
    "iso:country":"US",
    "sg:address":"2112 Meade Ave",
    "sg:city":"Valdosta",
    "sg:classifiers":[
        {
            "category":"Professional",
            "subcategory":"Secretarial Services",
            "type":"Services"
        }
    ],
    "sg:phone":"+1 229 253 0282",
    "sg:postcode":"31602",
    "sg:province":"GA",
    "sg:tags":[
        "reporting"
    ],
    "wof:name":"Sanders Shalonda",
    "wof:placetype":"venue"
},
  "geometry": {"coordinates":[-83.253987,30.876129],"type":"Point"}
}