{
  "type": "Feature",
  "properties": {
    "iso:country":"US",
    "sg:address":"160 Pace Dr",
    "sg:city":"Hiram",
    "sg:classifiers":[
        {
            "category":"Autos & Motor Vehicles",
            "subcategory":"Automobile Sales",
            "type":"Retail Goods"
        }
    ],
    "sg:phone":"+1 678 384 1000",
    "sg:postcode":"30141",
    "sg:province":"GA",
    "sg:tags":[
        "limo"
    ],
    "wof:name":"Limo Link Inc",
    "wof:placetype":"venue"
},
  "geometry": {"coordinates":[-84.75701100000001,33.897803],"type":"Point"}
}