{
  "type": "Feature",
  "properties": {
    "iso:country":"US",
    "sg:address":"3500 Narcissus Trl",
    "sg:city":"Millwood",
    "sg:classifiers":[
        {
            "category":"Professional",
            "subcategory":"Detective & Security Services",
            "type":"Services"
        }
    ],
    "sg:phone":"+1 912 283 2781",
    "sg:postcode":"31552",
    "sg:province":"GA",
    "sg:tags":[
        "gate",
        "attendant"
    ],
    "wof:name":"Robert Brannon",
    "wof:placetype":"venue"
},
  "geometry": {"coordinates":[-82.632908,31.258851],"type":"Point"}
}