{
  "type": "Feature",
  "properties": {
    "iso:country":"US",
    "sg:address":"1000 Stevens Entry",
    "sg:city":"Peachtree City",
    "sg:classifiers":[
        {
            "category":"Shopping",
            "subcategory":"Catalog Store",
            "type":"Retail Goods"
        }
    ],
    "sg:phone":"+1 770 251 3389",
    "sg:postcode":"30269",
    "sg:province":"GA",
    "sg:tags":[
        "mail",
        "order"
    ],
    "wof:name":"B K Products Inc",
    "wof:placetype":"venue"
},
  "geometry": {"coordinates":[-84.56913299999999,33.415588],"type":"Point"}
}