{
  "type": "Feature",
  "properties": {
    "addr:full":"1065 Columbia Dr Decatur GA 30030",
    "addr:housenumber":"1065",
    "addr:postcode":"30030",
    "addr:street":"Columbia Dr",
    "iso:country":"US",
    "sg:address":"1065 Columbia Dr",
    "sg:city":"Decatur",
    "sg:classifiers":[
        {
            "category":"Building & Trades",
            "subcategory":"Locksmith",
            "type":"Services"
        }
    ],
    "sg:phone":"+1 877 521 5438",
    "sg:postcode":"30030",
    "sg:province":"GA",
    "sg:tags":[
        "key"
    ],
    "wof:name":"7 Day 24 Hour Emergency Locksmith",
    "wof:placetype":"venue"
},
  "geometry": {"coordinates":[-84.27074,33.75639],"type":"Point"}
}