{
  "type": "Feature",
  "properties": {
    "iso:country":"US",
    "sg:address":"385 Pine St",
    "sg:city":"Marietta",
    "sg:classifiers":[
        {
            "category":"Organizations",
            "subcategory":"Religious Organization",
            "type":"Services"
        }
    ],
    "sg:phone":"+1 770 427 0515",
    "sg:postcode":"30060",
    "sg:province":"GA",
    "sg:tags":[
        "church"
    ],
    "wof:name":"Pine Street Baptist Church",
    "wof:placetype":"venue"
},
  "geometry": {"coordinates":[-84.541078,33.962615],"type":"Point"}
}