{
  "type": "Feature",
  "properties": {
    "iso:country":"US",
    "sg:address":"6715 Church St",
    "sg:city":"Douglasville",
    "sg:classifiers":[
        {
            "category":"Professional",
            "subcategory":"Business Services",
            "type":"Services"
        }
    ],
    "sg:phone":"+1 770 942 2000",
    "sg:postcode":"30134",
    "sg:province":"GA",
    "sg:tags":[
        "bonding"
    ],
    "wof:name":"Best Bonding Service Inc",
    "wof:placetype":"venue"
},
  "geometry": {"coordinates":[-84.749515,33.750104],"type":"Point"}
}