{
  "type": "Feature",
  "properties": {
    "iso:country":"US",
    "sg:address":"700 Green St NE",
    "sg:city":"Gainesville",
    "sg:classifiers":[
        {
            "category":"Restaurant",
            "type":"Food & Drink"
        }
    ],
    "sg:menulink":"http://www.allmenus.com/ga/gainesville/241906-rudolphs/menu/",
    "sg:phone":"+1 770 534 2226",
    "sg:postcode":"30501",
    "sg:province":"GA",
    "sg:tags":[
        "american"
    ],
    "wof:name":"Rudolph's",
    "wof:placetype":"venue"
},
  "geometry": {"coordinates":[-83.826964,34.308521],"type":"Point"}
}