{
  "type": "Feature",
  "properties": {
    "iso:country":"US",
    "sg:address":"422 Courtney Ln",
    "sg:city":"Cairo",
    "sg:classifiers":[
        {
            "category":"Professional",
            "subcategory":"Detective & Security Services",
            "type":"Services"
        }
    ],
    "sg:phone":"+1 229 377 1449",
    "sg:postcode":"39827",
    "sg:province":"GA",
    "sg:tags":[
        "information",
        "bureau"
    ],
    "wof:name":"Grady Computer Services",
    "wof:placetype":"venue"
},
  "geometry": {"coordinates":[-84.188962,30.968843],"type":"Point"}
}