{
  "type": "Feature",
  "properties": {
    "iso:country":"US",
    "sg:address":"62 Montgomery St SE",
    "sg:city":"Atlanta",
    "sg:classifiers":[
        {
            "category":"Wholesale",
            "subcategory":"Computers",
            "type":"Manufacturing & Wholesale Goods"
        }
    ],
    "sg:phone":"+1 404 286 7696",
    "sg:postcode":"30317",
    "sg:province":"GA",
    "sg:tags":[
        "equipment"
    ],
    "sg:website":"http://www.ttandtincomputers.com",
    "wof:name":"This That & The Other In Computers",
    "wof:placetype":"venue"
},
  "geometry": {"coordinates":[-84.339609,33.752221],"type":"Point"}
}