{
  "type": "Feature",
  "properties": {
    "addr:full":"401 E Park Ave Valdosta GA 31602",
    "addr:housenumber":"401",
    "addr:postcode":"31602",
    "addr:street":"E Park Ave",
    "iso:country":"US",
    "sg:address":"401 E Park Ave",
    "sg:city":"Valdosta",
    "sg:classifiers":[
        {
            "category":"Organizations",
            "subcategory":"Religious Organization",
            "type":"Services"
        }
    ],
    "sg:phone":"+1 229 333 0124",
    "sg:postcode":"31602",
    "sg:province":"GA",
    "wof:name":"Grace Bible Church",
    "wof:placetype":"venue"
},
  "geometry": {"coordinates":[-83.28086399999999,30.856783],"type":"Point"}
}