{
  "type": "Feature",
  "properties": {
    "addr:full":"213 Stockyard Rd Statesboro GA 30458",
    "addr:housenumber":"213",
    "addr:postcode":"30458",
    "addr:street":"Stockyard Rd",
    "iso:country":"US",
    "sg:address":"213 Stockyard Rd",
    "sg:city":"Statesboro",
    "sg:classifiers":[
        {
            "category":"Building & Trades",
            "subcategory":"Construction",
            "type":"Services"
        }
    ],
    "sg:phone":"+1 912 764 5387",
    "sg:postcode":"30458",
    "sg:province":"GA",
    "sg:tags":[
        "contractor"
    ],
    "wof:name":"Taylor Built Products",
    "wof:placetype":"venue"
},
  "geometry": {"coordinates":[-81.799322,32.462337],"type":"Point"}
}