{
  "type": "Feature",
  "properties": {
    "iso:country":"US",
    "sg:address":"4220 Shallowford Rd",
    "sg:city":"Marietta",
    "sg:classifiers":[
        {
            "category":"Education",
            "subcategory":"Special Training",
            "type":"Public Place"
        }
    ],
    "sg:phone":"+1 770 649 7874",
    "sg:postcode":"30062",
    "sg:province":"GA",
    "sg:tags":[
        "tutoring"
    ],
    "sg:website":"www.academicsolutionsga.com",
    "wof:name":"Academic Solutions Inc",
    "wof:placetype":"venue"
},
  "geometry": {"coordinates":[-84.427498,34.027302],"type":"Point"}
}