{
  "type": "Feature",
  "properties": {
    "iso:country":"US",
    "sg:address":"510 Plaza Dr",
    "sg:city":"Atlanta",
    "sg:classifiers":[
        {
            "category":"Freight",
            "type":"Transportation"
        }
    ],
    "sg:phone":"+1 404 763 9906",
    "sg:postcode":"30349",
    "sg:province":"GA",
    "sg:tags":[
        "brokerage",
        "custom"
    ],
    "wof:name":"Lois Sproul Chb",
    "wof:placetype":"venue"
},
  "geometry": {"coordinates":[-84.407118,33.620355],"type":"Point"}
}