{
  "type": "Feature",
  "properties": {
    "addr:full":"819 N 9th St Griffin GA 30223",
    "addr:housenumber":"819",
    "addr:postcode":"30223",
    "addr:street":"N 9Th St",
    "iso:country":"US",
    "sg:address":"819 N 9th St",
    "sg:city":"Griffin",
    "sg:classifiers":[
        {
            "category":"Personal",
            "subcategory":"Beauty Salon",
            "type":"Services"
        }
    ],
    "sg:phone":"+1 770 227 7158",
    "sg:postcode":"30223",
    "sg:province":"GA",
    "wof:name":"Pat's Hair",
    "wof:placetype":"venue"
},
  "geometry": {"coordinates":[-84.267059,33.261868],"type":"Point"}
}