{
  "type": "Feature",
  "properties": {
    "iso:country":"US",
    "sg:address":"225 Merritt Dr",
    "sg:city":"Roswell",
    "sg:classifiers":[
        {
            "category":"Communications",
            "subcategory":"Film & Video Production",
            "type":"Services"
        }
    ],
    "sg:phone":"+1 770 649 6349",
    "sg:postcode":"30076",
    "sg:province":"GA",
    "sg:tags":[
        "motion"
    ],
    "wof:name":"Kgt Productions Inc",
    "wof:placetype":"venue"
},
  "geometry": {"coordinates":[-84.279228,33.9838],"type":"Point"}
}