{
  "type": "Feature",
  "properties": {
    "addr:full":"1816 Independence Sq Dunwoody GA 30338",
    "addr:housenumber":"1816",
    "addr:postcode":"30338",
    "addr:street":"Independence Sq",
    "iso:country":"US",
    "sg:address":"1816 Independence Sq",
    "sg:city":"Dunwoody",
    "sg:classifiers":[
        {
            "category":"Real Estate",
            "subcategory":"Real Estate Agent",
            "type":"Services"
        }
    ],
    "sg:phone":"+1 770 396 6100",
    "sg:postcode":"30338",
    "sg:province":"GA",
    "wof:name":"Potts Realty Inc",
    "wof:placetype":"venue"
},
  "geometry": {"coordinates":[-84.311989,33.930445],"type":"Point"}
}