{
  "type": "Feature",
  "properties": {
    "addr:full":"2233 Medfield Trl NE Atlanta GA 30345",
    "addr:housenumber":"2233",
    "addr:postcode":"30345",
    "addr:street":"Medfield Trl Ne",
    "iso:country":"US",
    "sg:address":"2233 Medfield Trl NE",
    "sg:city":"Atlanta",
    "sg:classifiers":[
        {
            "category":"Banks & Credit Unions",
            "subcategory":"Bank",
            "type":"Services"
        }
    ],
    "sg:phone":"+1 404 664 3846",
    "sg:postcode":"30345",
    "sg:province":"GA",
    "sg:tags":[
        "depository",
        "banking",
        "atm",
        "location"
    ],
    "wof:name":"Fast Trans",
    "wof:placetype":"venue"
},
  "geometry": {"coordinates":[-84.308093,33.849771],"type":"Point"}
}