{
  "type": "Feature",
  "properties": {
    "iso:country":"US",
    "sg:address":"1688 Norman Dr",
    "sg:city":"Valdosta",
    "sg:classifiers":[
        {
            "category":"Ice Cream",
            "type":"Food & Drink"
        }
    ],
    "sg:menulink":"http://www.allmenus.com/ga/valdosta/220790-braums-ice-cream--dairy-stores/menu/",
    "sg:phone":"+1 229 219 7622",
    "sg:postcode":"31601",
    "sg:province":"GA",
    "sg:tags":[
        "american"
    ],
    "wof:name":"Braum's Ice Cream & Dairy Stores",
    "wof:placetype":"venue"
},
  "geometry": {"coordinates":[-83.31894800000001,30.841565],"type":"Point"}
}