{
  "type": "Feature",
  "properties": {
    "iso:country":"US",
    "sg:address":"4130 Mill Vale Ct",
    "sg:city":"Atlanta",
    "sg:classifiers":[
        {
            "category":"Professional",
            "subcategory":"Business Services",
            "type":"Services"
        }
    ],
    "sg:phone":"+1 404 216 6358",
    "sg:postcode":"30360",
    "sg:province":"GA",
    "wof:name":"Diecast Studios",
    "wof:placetype":"venue"
},
  "geometry": {"coordinates":[-84.27737999999999,33.914949],"type":"Point"}
}