{
  "type": "Feature",
  "properties": {
    "iso:country":"US",
    "sg:address":"3863 Cherokee Ford",
    "sg:city":"Gainesville",
    "sg:classifiers":[
        {
            "category":"Real Estate",
            "subcategory":"Real Estate Agent",
            "type":"Services"
        }
    ],
    "sg:phone":"+1 770 534 8288",
    "sg:postcode":"30506",
    "sg:province":"GA",
    "sg:website":"www.housenetwork.com",
    "wof:name":"HOUSENETWORK.COM",
    "wof:placetype":"venue"
},
  "geometry": {"coordinates":[-83.855575,34.375794],"type":"Point"}
}