{
  "type": "Feature",
  "properties": {
    "addr:full":"14 W Broad St Camilla GA 31730",
    "addr:housenumber":"14",
    "addr:postcode":"31730",
    "addr:street":"W Broad St",
    "iso:country":"US",
    "sg:address":"14 W Broad St",
    "sg:city":"Camilla",
    "sg:classifiers":[
        {
            "category":"Personal",
            "subcategory":"Beauty Salon",
            "type":"Services"
        }
    ],
    "sg:phone":"+1 229 336 8420",
    "sg:postcode":"31730",
    "sg:province":"GA",
    "sg:tags":[
        "shop"
    ],
    "wof:name":"Sarahs Scissors",
    "wof:placetype":"venue"
},
  "geometry": {"coordinates":[-84.20907200000001,31.231193],"type":"Point"}
}