{
  "type": "Feature",
  "properties": {
    "addr:full":"2907 Moorings Pkwy Snellville GA 30039",
    "addr:housenumber":"2907",
    "addr:postcode":"30039",
    "addr:street":"Moorings Pkwy",
    "iso:country":"US",
    "sg:address":"2907 Moorings Pkwy",
    "sg:city":"Snellville",
    "sg:classifiers":[
        {
            "category":"Shopping",
            "subcategory":"Hobbies, Toys, & Games",
            "type":"Retail Goods"
        }
    ],
    "sg:phone":"+1 404 502 4365",
    "sg:postcode":"30039",
    "sg:province":"GA",
    "sg:tags":[
        "toy",
        "store",
        "supply"
    ],
    "wof:name":"Gail Thornton's If I Were President Game, Inc.",
    "wof:placetype":"venue"
},
  "geometry": {"coordinates":[-84.076151,33.809495],"type":"Point"}
}