{
  "type": "Feature",
  "properties": {
    "iso:country":"US",
    "sg:address":"3855 Southgate St SW",
    "sg:city":"Lilburn",
    "sg:classifiers":[
        {
            "category":"Building & Trades",
            "subcategory":"Construction",
            "type":"Services"
        }
    ],
    "sg:phone":"+1 770 309 7945",
    "sg:postcode":"30044",
    "sg:province":"GA",
    "wof:name":"Multiplex LLC",
    "wof:placetype":"venue"
},
  "geometry": {"coordinates":[-84.088713,33.882869],"type":"Point"}
}