{
  "type": "Feature",
  "properties": {
    "addr:full":"391 Spring St Commerce GA 30529",
    "addr:housenumber":"391",
    "addr:postcode":"30529",
    "addr:street":"Spring St",
    "iso:country":"US",
    "sg:address":"391 Spring St",
    "sg:city":"Commerce",
    "sg:classifiers":[
        {
            "category":"Personal",
            "subcategory":"Beauty Salon",
            "type":"Services"
        }
    ],
    "sg:phone":"+1 706 983 9213",
    "sg:postcode":"30529",
    "sg:province":"GA",
    "sg:tags":[
        "shop"
    ],
    "wof:name":"Allbright's Artistry",
    "wof:placetype":"venue"
},
  "geometry": {"coordinates":[-83.446252,34.194766],"type":"Point"}
}