{
  "type": "Feature",
  "properties": {
    "addr:full":"1550 Owens Store Rd Canton GA 30115",
    "addr:housenumber":"1550",
    "addr:postcode":"30115",
    "addr:street":"Owens Store Rd",
    "iso:country":"US",
    "sg:address":"1550 Owens Store Rd",
    "sg:city":"Canton",
    "sg:classifiers":[
        {
            "category":"Building & Trades",
            "subcategory":"Electrical",
            "type":"Services"
        }
    ],
    "sg:phone":"+1 770 720 7521",
    "sg:postcode":"30115",
    "sg:province":"GA",
    "sg:tags":[
        "electrical",
        "contractor"
    ],
    "wof:name":"Wayne J Griffin Electric Corp",
    "wof:placetype":"venue"
},
  "geometry": {"coordinates":[-84.33343000000001,34.232609],"type":"Point"}
}