{
  "type": "Feature",
  "properties": {
    "addr:full":"2947 Canton Chase Dr Marietta GA 30062",
    "addr:housenumber":"2947",
    "addr:postcode":"30062",
    "addr:street":"Canton Chase Dr",
    "iso:country":"US",
    "sg:address":"2947 Canton Chase Dr",
    "sg:city":"Marietta",
    "sg:classifiers":[
        {
            "category":"Professional",
            "subcategory":"Lawyer & Legal Services",
            "type":"Services"
        }
    ],
    "sg:phone":"+1 770 971 0656",
    "sg:postcode":"30062",
    "sg:province":"GA",
    "wof:name":"Jack I Klein Attorney",
    "wof:placetype":"venue"
},
  "geometry": {"coordinates":[-84.469024,33.991565],"type":"Point"}
}