{
  "type": "Feature",
  "properties": {
    "iso:country":"US",
    "sg:address":"3708 High Gables",
    "sg:city":"Cumming",
    "sg:classifiers":[
        {
            "category":"Building & Trades",
            "subcategory":"Construction",
            "type":"Services"
        }
    ],
    "sg:phone":"+1 770 886 3377",
    "sg:postcode":"30041",
    "sg:province":"GA",
    "sg:tags":[
        "concrete",
        "contractor"
    ],
    "wof:name":"D C Concrete Services Inc",
    "wof:placetype":"venue"
},
  "geometry": {"coordinates":[-84.075237,34.253907],"type":"Point"}
}