{
  "type": "Feature",
  "properties": {
    "addr:full":"782 Ee Butler Pkwy Gainesville GA 30501",
    "addr:housenumber":"782",
    "addr:postcode":"30501",
    "addr:street":"Butler Pkwy",
    "iso:country":"US",
    "sg:address":"782 Ee Butler Pkwy",
    "sg:city":"Gainesville",
    "sg:classifiers":[
        {
            "category":"Autos & Motor Vehicles",
            "subcategory":"Automobile Sales",
            "type":"Retail Goods"
        }
    ],
    "sg:phone":"+1 678 450 9090",
    "sg:postcode":"30501",
    "sg:province":"GA",
    "sg:tags":[
        "dealers-used",
        "car",
        "used",
        "cars-wholesale"
    ],
    "wof:name":"Gainesville Auto Mall",
    "wof:placetype":"venue"
},
  "geometry": {"coordinates":[-83.816406,34.294471],"type":"Point"}
}