{
  "type": "Feature",
  "properties": {
    "addr:full":"233 Roxbury Dr Riverdale GA 30274",
    "addr:housenumber":"233",
    "addr:postcode":"30274",
    "addr:street":"Roxbury Dr",
    "iso:country":"US",
    "sg:address":"233 Roxbury Dr",
    "sg:city":"Riverdale",
    "sg:classifiers":[
        {
            "category":"Building & Trades",
            "subcategory":"Construction",
            "type":"Services"
        }
    ],
    "sg:phone":"+1 770 991 1749",
    "sg:postcode":"30274",
    "sg:province":"GA",
    "sg:tags":[
        "contractor"
    ],
    "wof:name":"National Hydro Prod Inc",
    "wof:placetype":"venue"
},
  "geometry": {"coordinates":[-84.395938,33.572771],"type":"Point"}
}