{
  "type": "Feature",
  "properties": {
    "iso:country":"US",
    "sg:address":"1218 Acme St",
    "sg:city":"Dalton",
    "sg:classifiers":[
        {
            "category":"Retail",
            "subcategory":"Auto Repair",
            "type":"Services"
        }
    ],
    "sg:phone":"+1 706 226 2705",
    "sg:postcode":"30721",
    "sg:province":"GA",
    "sg:tags":[
        "truck"
    ],
    "wof:name":"Up-State Truck Repair",
    "wof:placetype":"venue"
},
  "geometry": {"coordinates":[-84.963729,34.789036],"type":"Point"}
}