{
  "type": "Feature",
  "properties": {
    "addr:full":"2839 Meadow Dr Marietta GA 30062",
    "addr:housenumber":"2839",
    "addr:postcode":"30062",
    "addr:street":"Meadow Dr",
    "iso:country":"US",
    "sg:address":"2839 Meadow Dr",
    "sg:city":"Marietta",
    "sg:classifiers":[
        {
            "category":"Home & Garden",
            "subcategory":"Furniture",
            "type":"Retail Goods"
        }
    ],
    "sg:phone":"+1 678 602 6892",
    "sg:postcode":"30062",
    "sg:province":"GA",
    "sg:tags":[
        "equipment-household",
        "kitchen",
        "cabinet"
    ],
    "wof:name":"J Wood Metal Art",
    "wof:placetype":"venue"
},
  "geometry": {"coordinates":[-84.446564,34.022179],"type":"Point"}
}