{
  "type": "Feature",
  "properties": {
    "addr:full":"4955 Avalon Ridge Pkwy Norcross GA 30071",
    "addr:housenumber":"4955",
    "addr:postcode":"30071",
    "addr:street":"Avalon Ridge Pkwy",
    "iso:country":"US",
    "sg:address":"4955 Avalon Ridge Pkwy",
    "sg:city":"Norcross",
    "sg:classifiers":[
        {
            "category":"Wholesale",
            "subcategory":"Medical Equipment & Supplies",
            "type":"Manufacturing & Wholesale Goods"
        }
    ],
    "sg:phone":"+1 770 242 8723",
    "sg:postcode":"30071",
    "sg:province":"GA",
    "sg:tags":[
        "hospital"
    ],
    "sg:website":"www.spectrx.com",
    "wof:name":"Spect Rx Inc",
    "wof:placetype":"venue"
},
  "geometry": {"coordinates":[-84.191631,33.961577],"type":"Point"}
}