{
  "type": "Feature",
  "properties": {
    "iso:country":"US",
    "sg:address":"1720 Indian Trail Rd",
    "sg:city":"Norcross",
    "sg:classifiers":[
        {
            "category":"Fast Food",
            "type":"Food & Drink"
        }
    ],
    "sg:phone":"+1 770 923 5830",
    "sg:postcode":"30093",
    "sg:province":"GA",
    "sg:website":"www.tacobell.com",
    "wof:name":"Taco Bell",
    "wof:placetype":"venue"
},
  "geometry": {"coordinates":[-84.17409499999999,33.925239],"type":"Point"}
}