{
  "type": "Feature",
  "properties": {
    "iso:country":"US",
    "sg:address":"500 Highway 138 W",
    "sg:city":"Jonesboro",
    "sg:classifiers":[
        {
            "category":"Education",
            "subcategory":"School",
            "type":"Public Place"
        }
    ],
    "sg:phone":"+1 770 473 2780",
    "sg:postcode":"30238",
    "sg:province":"GA",
    "sg:tags":[
        "high",
        "middle",
        "elementary"
    ],
    "wof:name":"Clayton County Board of Education",
    "wof:placetype":"venue"
},
  "geometry": {"coordinates":[-84.374177,33.535931],"type":"Point"}
}