{
  "type": "Feature",
  "properties": {
    "addr:full":"575 Windy Hill Rd SE Smyrna GA 30082",
    "addr:housenumber":"575",
    "addr:postcode":"30082",
    "addr:street":"Windy Hill Rd Se",
    "iso:country":"US",
    "sg:address":"575 Windy Hill Rd SE",
    "sg:city":"Smyrna",
    "sg:classifiers":[
        {
            "category":"Professional",
            "subcategory":"Business Services",
            "type":"Services"
        }
    ],
    "sg:phone":"+1 770 435 7090",
    "sg:postcode":"30082",
    "sg:province":"GA",
    "wof:name":"Urgente Express Intl Courier",
    "wof:placetype":"venue"
},
  "geometry": {"coordinates":[-84.537949,33.89443],"type":"Point"}
}