{
  "type": "Feature",
  "properties": {
    "addr:full":"3400 Saint Marys Rd Columbus GA 31906",
    "addr:housenumber":"3400",
    "addr:postcode":"31906",
    "addr:street":"Saint Marys Rd",
    "iso:country":"US",
    "sg:address":"3400 Saint Marys Rd",
    "sg:city":"Columbus",
    "sg:classifiers":[
        {
            "category":"Restaurant",
            "type":"Food & Drink"
        }
    ],
    "sg:phone":"+1 706 322 2100",
    "sg:postcode":"31906",
    "sg:province":"GA",
    "wof:name":"Top Hat",
    "wof:placetype":"venue"
},
  "geometry": {"coordinates":[-84.94207,32.45354],"type":"Point"}
}