{
  "type": "Feature",
  "properties": {
    "addr:full":"1708 Norwich St Brunswick GA 31520",
    "addr:housenumber":"1708",
    "addr:postcode":"31520",
    "addr:street":"Norwich St",
    "iso:country":"US",
    "sg:address":"1708 Norwich St",
    "sg:city":"Brunswick",
    "sg:classifiers":[
        {
            "category":"Professional",
            "subcategory":"Accounting & Tax Preparation",
            "type":"Services"
        }
    ],
    "sg:phone":"+1 912 262 6645",
    "sg:postcode":"31520",
    "sg:province":"GA",
    "wof:name":"Rhodes & Assoc Inc",
    "wof:placetype":"venue"
},
  "geometry": {"coordinates":[-81.492779,31.15405],"type":"Point"}
}