{
  "type": "Feature",
  "properties": {
    "addr:full":"817 W Highland Ave Albany GA 31701",
    "addr:housenumber":"817",
    "addr:postcode":"31701",
    "addr:street":"W Highland Ave",
    "iso:country":"US",
    "sg:address":"817 W Highland Ave",
    "sg:city":"Albany",
    "sg:classifiers":[
        {
            "category":"Organizations",
            "subcategory":"Community Association",
            "type":"Services"
        }
    ],
    "sg:phone":"+1 229 888 6030",
    "sg:postcode":"31701",
    "sg:province":"GA",
    "sg:tags":[
        "club"
    ],
    "wof:name":"Holiday Society Club",
    "wof:placetype":"venue"
},
  "geometry": {"coordinates":[-84.17026199999999,31.573862],"type":"Point"}
}