{
  "type": "Feature",
  "properties": {
    "iso:country":"US",
    "sg:address":"215 Hardin Rd",
    "sg:city":"Cedartown",
    "sg:classifiers":[
        {
            "category":"Government",
            "subcategory":"Post Office",
            "type":"Public Place"
        }
    ],
    "sg:phone":"+1 770 749 0681",
    "sg:postcode":"30125",
    "sg:province":"GA",
    "wof:name":"US Post Office",
    "wof:placetype":"venue"
},
  "geometry": {"coordinates":[-85.388333,33.949195],"type":"Point"}
}