{
  "type": "Feature",
  "properties": {
    "addr:full":"101 Court St Calhoun GA 30701",
    "addr:housenumber":"101",
    "addr:postcode":"30701",
    "addr:street":"Court St",
    "iso:country":"US",
    "sg:address":"101 Court St",
    "sg:city":"Calhoun",
    "sg:classifiers":[
        {
            "category":"Social Services",
            "type":"Services"
        },
        {
            "category":"Personal",
            "type":"Services"
        }
    ],
    "sg:phone":"+1 706 383 6346",
    "sg:postcode":"30701",
    "sg:province":"GA",
    "sg:tags":[
        "counseling"
    ],
    "wof:name":"Counseling Life",
    "wof:placetype":"venue"
},
  "geometry": {"coordinates":[-84.95127100000001,34.502541],"type":"Point"}
}