{
  "type": "Feature",
  "properties": {
    "iso:country":"US",
    "sg:address":"901 Rock Quarry Rd",
    "sg:city":"Stockbridge",
    "sg:classifiers":[
        {
            "category":"Restaurant",
            "type":"Food & Drink"
        }
    ],
    "sg:phone":"+1 770 507 6840",
    "sg:postcode":"30281",
    "sg:province":"GA",
    "sg:tags":[
        "eating"
    ],
    "wof:name":"Wings & Things",
    "wof:placetype":"venue"
},
  "geometry": {"coordinates":[-84.22795499999999,33.527725],"type":"Point"}
}