{
  "type": "Feature",
  "properties": {
    "iso:country":"US",
    "sg:address":"464 Stekoa Falls Rd",
    "sg:city":"Clayton",
    "sg:classifiers":[
        {
            "category":"Building & Trades",
            "subcategory":"Construction",
            "type":"Services"
        }
    ],
    "sg:phone":"+1 706 782 2614",
    "sg:postcode":"30525",
    "sg:province":"GA",
    "sg:tags":[
        "concrete",
        "contractor"
    ],
    "wof:name":"G & R Concrete Inc",
    "wof:placetype":"venue"
},
  "geometry": {"coordinates":[-83.39899200000001,34.859098],"type":"Point"}
}