{
  "type": "Feature",
  "properties": {
    "addr:full":"409 W Highland Ave Albany GA 31701",
    "addr:housenumber":"409",
    "addr:postcode":"31701",
    "addr:street":"W Highland Ave",
    "iso:country":"US",
    "sg:address":"409 W Highland Ave",
    "sg:city":"Albany",
    "sg:classifiers":[
        {
            "category":"Professional",
            "subcategory":"Accounting & Tax Preparation",
            "type":"Services"
        }
    ],
    "sg:phone":"+1 229 883 7071",
    "sg:postcode":"31701",
    "sg:province":"GA",
    "sg:tags":[
        "return",
        "filing"
    ],
    "wof:name":"Triple AAA Tax & Payment Svc",
    "wof:placetype":"venue"
},
  "geometry": {"coordinates":[-84.15671500000001,31.573891],"type":"Point"}
}