{
  "type": "Feature",
  "properties": {
    "addr:full":"125 Venture Dr Brunswick GA 31525",
    "addr:housenumber":"125",
    "addr:postcode":"31525",
    "addr:street":"Venture Dr",
    "iso:country":"US",
    "sg:address":"125 Venture Dr",
    "sg:city":"Brunswick",
    "sg:classifiers":[
        {
            "category":"Travel",
            "subcategory":"Hotels & Motels",
            "type":"Entertainment"
        }
    ],
    "sg:phone":"+1 912 265 4600",
    "sg:postcode":"31525",
    "sg:province":"GA",
    "wof:name":"Quality Inn",
    "wof:placetype":"venue"
},
  "geometry": {"coordinates":[-81.50528199999999,31.245659],"type":"Point"}
}