{
  "type": "Feature",
  "properties": {
    "iso:country":"US",
    "sg:address":"90 Bermuda Cir",
    "sg:city":"Covington",
    "sg:classifiers":[
        {
            "category":"Government",
            "subcategory":"Fire Station",
            "type":"Public Place"
        },
        {
            "category":"Building & Trades",
            "subcategory":"Cleaning & Sanitation",
            "type":"Services"
        }
    ],
    "sg:phone":"+1 678 557 6790",
    "sg:postcode":"30016",
    "sg:province":"GA",
    "sg:tags":[
        "recovery",
        "janitorial",
        "disaster",
        "relief"
    ],
    "wof:name":"Flood Tek Masters",
    "wof:placetype":"venue"
},
  "geometry": {"coordinates":[-83.932548,33.597335],"type":"Point"}
}