{
  "type": "Feature",
  "properties": {
    "addr:full":"57 Executive Park S NE Atlanta GA 30329",
    "addr:housenumber":"57",
    "addr:postcode":"30329",
    "addr:street":"Executive Park S Ne",
    "iso:country":"US",
    "sg:address":"57 Executive Park S NE",
    "sg:city":"Atlanta",
    "sg:classifiers":[
        {
            "category":"Social Services",
            "subcategory":"Child Care",
            "type":"Services"
        },
        {
            "category":"Real Estate",
            "subcategory":"Real Estate Agent",
            "type":"Services"
        }
    ],
    "sg:phone":"+1 404 634 4049",
    "sg:postcode":"30329",
    "sg:province":"GA",
    "sg:tags":[
        "management",
        "day"
    ],
    "wof:name":"Early Learning Property Mgmt",
    "wof:placetype":"venue"
},
  "geometry": {"coordinates":[-84.340896,33.828277],"type":"Point"}
}