{
  "type": "Feature",
  "properties": {
    "addr:full":"1000 Shannon Mall Union City GA 30291",
    "addr:housenumber":"1000",
    "addr:postcode":"30291",
    "addr:street":"Shannon Mall",
    "iso:country":"US",
    "sg:address":"1000 Shannon Mall",
    "sg:city":"Union City",
    "sg:classifiers":[
        {
            "category":"Shopping Center",
            "type":"Public Place"
        }
    ],
    "sg:phone":"+1 770 964 2200",
    "sg:postcode":"30291",
    "sg:province":"GA",
    "sg:website":"www.unionstationmallga.com/",
    "wof:name":"Union Station Mall",
    "wof:placetype":"venue"
},
  "geometry": {"coordinates":[-84.53264299999999,33.570649],"type":"Point"}
}