{
  "type": "Feature",
  "properties": {
    "iso:country":"US",
    "sg:address":"106 Tallassee Rd",
    "sg:city":"Athens",
    "sg:classifiers":[
        {
            "category":"Building & Trades",
            "subcategory":"Construction",
            "type":"Services"
        }
    ],
    "sg:phone":"+1 706 316 0728",
    "sg:postcode":"30606",
    "sg:province":"GA",
    "sg:tags":[
        "contractor"
    ],
    "wof:name":"J & J Electric",
    "wof:placetype":"venue"
},
  "geometry": {"coordinates":[-83.429132,33.965343],"type":"Point"}
}