{
  "type": "Feature",
  "properties": {
    "iso:country":"US",
    "sg:address":"1106 Overpass Ln",
    "sg:city":"Warner Robins",
    "sg:classifiers":[
        {
            "category":"Professional",
            "type":"Services"
        }
    ],
    "sg:phone":"+1 478 971 7868",
    "sg:postcode":"31088",
    "sg:province":"GA",
    "wof:name":"Jerry R Maine",
    "wof:placetype":"venue"
},
  "geometry": {"coordinates":[-83.676146,32.573936],"type":"Point"}
}