{
  "type": "Feature",
  "properties": {
    "iso:country":"US",
    "sg:address":"203 Brumbelow Rd",
    "sg:city":"Carrollton",
    "sg:classifiers":[
        {
            "category":"Freight",
            "type":"Transportation"
        }
    ],
    "sg:phone":"+1 770 832 3658",
    "sg:postcode":"30117",
    "sg:province":"GA",
    "sg:tags":[
        "courier"
    ],
    "wof:name":"UPS",
    "wof:placetype":"venue"
},
  "geometry": {"coordinates":[-85.09858,33.57981],"type":"Point"}
}