{
  "type": "Feature",
  "properties": {
    "addr:full":"6459 Highway 42 Rex GA 30273",
    "addr:housenumber":"6459",
    "addr:postcode":"30273",
    "addr:street":"Highway 42",
    "iso:country":"US",
    "sg:address":"6459 Highway 42",
    "sg:city":"Rex",
    "sg:classifiers":[
        {
            "category":"Personal",
            "subcategory":"Beauty Salon",
            "type":"Services"
        }
    ],
    "sg:phone":"+1 678 284 0084",
    "sg:postcode":"30273",
    "sg:province":"GA",
    "sg:tags":[
        "hair"
    ],
    "wof:name":"Next Beauty Salon",
    "wof:placetype":"venue"
},
  "geometry": {"coordinates":[-84.281097,33.5774],"type":"Point"}
}