{
  "type": "Feature",
  "properties": {
    "addr:full":"67 Bowden St Commerce GA 30529",
    "addr:housenumber":"67",
    "addr:postcode":"30529",
    "addr:street":"Bowden St",
    "iso:country":"US",
    "sg:address":"67 Bowden St",
    "sg:city":"Commerce",
    "sg:classifiers":[
        {
            "category":"Professional",
            "type":"Services"
        }
    ],
    "sg:phone":"+1 706 335 4544",
    "sg:postcode":"30529",
    "sg:province":"GA",
    "wof:name":"Savory Sensations",
    "wof:placetype":"venue"
},
  "geometry": {"coordinates":[-83.453095,34.203443],"type":"Point"}
}