{
  "type": "Feature",
  "properties": {
    "iso:country":"US",
    "sg:address":"875 Yankton Dr",
    "sg:city":"Lawrenceville",
    "sg:classifiers":[
        {
            "category":"Personal",
            "type":"Services"
        }
    ],
    "sg:phone":"+1 770 962 7688",
    "sg:postcode":"30044",
    "sg:province":"GA",
    "sg:tags":[
        "party",
        "planning",
        "event"
    ],
    "wof:name":"Elegant Events By Renae",
    "wof:placetype":"venue"
},
  "geometry": {"coordinates":[-84.01602099999999,33.917817],"type":"Point"}
}