{
  "type": "Feature",
  "properties": {
    "addr:full":"5214 N Hampton Rdg Norcross GA 30092",
    "addr:housenumber":"5214",
    "addr:postcode":"30092",
    "addr:street":"N Hampton Rdg",
    "iso:country":"US",
    "sg:address":"5214 N Hampton Rdg",
    "sg:city":"Norcross",
    "sg:classifiers":[
        {
            "category":"Professional",
            "subcategory":"Computer Services",
            "type":"Services"
        }
    ],
    "sg:phone":"+1 770 296 0541",
    "sg:postcode":"30092",
    "sg:province":"GA",
    "sg:tags":[
        "technical",
        "assistance",
        "support"
    ],
    "wof:name":"Norcross Networks",
    "wof:placetype":"venue"
},
  "geometry": {"coordinates":[-84.21163199999999,33.972462],"type":"Point"}
}