{
  "type": "Feature",
  "properties": {
    "iso:country":"US",
    "sg:address":"2690 Sandy Plains Rd",
    "sg:city":"Marietta",
    "sg:classifiers":[
        {
            "category":"Professional",
            "type":"Services"
        }
    ],
    "sg:phone":"+1 678 213 5196",
    "sg:postcode":"30066",
    "sg:province":"GA",
    "sg:tags":[
        "establishment"
    ],
    "wof:name":"Ganeshiji Inc",
    "wof:placetype":"venue"
},
  "geometry": {"coordinates":[-84.49043899999999,34.019289],"type":"Point"}
}