{
  "type": "Feature",
  "properties": {
    "iso:country":"US",
    "sg:address":"2734 Bomar Rd",
    "sg:city":"Douglasville",
    "sg:classifiers":[
        {
            "category":"Professional",
            "subcategory":"Detective & Security Services",
            "type":"Services"
        }
    ],
    "sg:phone":"+1 770 942 7023",
    "sg:postcode":"30135",
    "sg:province":"GA",
    "sg:tags":[
        "car"
    ],
    "wof:name":"Jds Security Inc",
    "wof:placetype":"venue"
},
  "geometry": {"coordinates":[-84.686059,33.732183],"type":"Point"}
}