{
  "type": "Feature",
  "properties": {
    "addr:full":"1320 Old Klondike Rd Conyers GA 30013",
    "addr:housenumber":"1320",
    "addr:postcode":"30013",
    "addr:street":"Old Klondike Rd",
    "iso:country":"US",
    "sg:address":"1320 Old Klondike Rd",
    "sg:city":"Conyers",
    "sg:classifiers":[
        {
            "category":"Restaurant",
            "type":"Food & Drink"
        }
    ],
    "sg:phone":"+1 770 483 0564",
    "sg:postcode":"30013",
    "sg:province":"GA",
    "sg:website":"www.mcdonalds.com",
    "wof:name":"McDonald's Restaurants",
    "wof:placetype":"venue"
},
  "geometry": {"coordinates":[-83.992699,33.624199],"type":"Point"}
}