{
  "type": "Feature",
  "properties": {
    "iso:country":"US",
    "sg:address":"6085 Old National Hwy",
    "sg:city":"Atlanta",
    "sg:classifiers":[
        {
            "category":"Personal",
            "subcategory":"Nail Salon",
            "type":"Services"
        }
    ],
    "sg:phone":"+1 770 996 5824",
    "sg:postcode":"30349",
    "sg:province":"GA",
    "wof:name":"Vip Nails",
    "wof:placetype":"venue"
},
  "geometry": {"coordinates":[-84.468857,33.589362],"type":"Point"}
}