{
  "type": "Feature",
  "properties": {
    "addr:full":"4616 E Ponce de Leon Ave Clarkston GA 30021",
    "addr:housenumber":"4616",
    "addr:postcode":"30021",
    "addr:street":"E Ponce De Leon Ave",
    "iso:country":"US",
    "sg:address":"4616 E Ponce de Leon Ave",
    "sg:city":"Clarkston",
    "sg:classifiers":[
        {
            "category":"Restaurant",
            "type":"Food & Drink"
        }
    ],
    "sg:phone":"+1 770 908 0979",
    "sg:postcode":"30021",
    "sg:province":"GA",
    "sg:tags":[
        "eating"
    ],
    "wof:name":"Red China Chinese Restaurant",
    "wof:placetype":"venue"
},
  "geometry": {"coordinates":[-84.228021,33.819118],"type":"Point"}
}