{
  "type": "Feature",
  "properties": {
    "iso:country":"US",
    "sg:address":"5232 Rokefield Way NW",
    "sg:city":"Norcross",
    "sg:classifiers":[
        {
            "category":"Manufacturing",
            "subcategory":"Petroleum Products",
            "type":"Manufacturing & Wholesale Goods"
        }
    ],
    "sg:phone":"+1 770 662 8223",
    "sg:postcode":"30092",
    "sg:province":"GA",
    "sg:tags":[
        "refiner",
        "oil",
        "gasoline"
    ],
    "wof:name":"Motiva Enterprises LLC",
    "wof:placetype":"venue"
},
  "geometry": {"coordinates":[-84.23087700000001,33.997],"type":"Point"}
}