{
  "type": "Feature",
  "properties": {
    "addr:full":"3279 Bandy Rd Ringgold GA 30736",
    "addr:housenumber":"3279",
    "addr:postcode":"30736",
    "addr:street":"Bandy Rd",
    "iso:country":"US",
    "sg:address":"3279 Bandy Rd",
    "sg:city":"Ringgold",
    "sg:classifiers":[
        {
            "category":"Building & Trades",
            "subcategory":"Construction",
            "type":"Services"
        }
    ],
    "sg:phone":"+1 706 935 5075",
    "sg:postcode":"30736",
    "sg:province":"GA",
    "sg:tags":[
        "floor",
        "laying",
        "contractor"
    ],
    "wof:name":"Dalton Direct Flooring Inc",
    "wof:placetype":"venue"
},
  "geometry": {"coordinates":[-85.08557999999999,34.86034],"type":"Point"}
}