{
  "type": "Feature",
  "properties": {
    "iso:country":"US",
    "sg:address":"976 Thigpen Trl",
    "sg:city":"Doerun",
    "sg:phone":"+1 229 881 9653",
    "sg:postcode":"31744",
    "sg:province":"GA",
    "sg:tags":[
        "farm",
        "cotton"
    ],
    "wof:name":"J & D Hembree Farms",
    "wof:placetype":"venue"
},
  "geometry": {"coordinates":[-83.967197,31.370018],"type":"Point"}
}