{
  "type": "Feature",
  "properties": {
    "addr:full":"3620 Lake Dr SE Smyrna GA 30082",
    "addr:housenumber":"3620",
    "addr:postcode":"30082",
    "addr:street":"Lake Dr Se",
    "iso:country":"US",
    "sg:address":"3620 Lake Dr SE",
    "sg:city":"Smyrna",
    "sg:classifiers":[
        {
            "category":"Education",
            "subcategory":"Special Training",
            "type":"Public Place"
        }
    ],
    "sg:phone":"+1 770 434 2062",
    "sg:postcode":"30082",
    "sg:province":"GA",
    "sg:tags":[
        "educational"
    ],
    "wof:name":"Lego Education",
    "wof:placetype":"venue"
},
  "geometry": {"coordinates":[-84.528445,33.865808],"type":"Point"}
}