{
  "type": "Feature",
  "properties": {
    "addr:full":"531 Scott Blvd Tucker GA 30084",
    "addr:housenumber":"531",
    "addr:postcode":"30084",
    "addr:street":"Scott Blvd",
    "iso:country":"US",
    "sg:address":"531 Scott Blvd",
    "sg:city":"Tucker",
    "sg:classifiers":[
        {
            "category":"Building & Trades",
            "subcategory":"Locksmith",
            "type":"Services"
        }
    ],
    "sg:phone":"+1 404 968 8166",
    "sg:postcode":"30084",
    "sg:province":"GA",
    "sg:tags":[
        "key"
    ],
    "wof:name":"Allways Locksmith",
    "wof:placetype":"venue"
},
  "geometry": {"coordinates":[-84.308373,33.779873],"type":"Point"}
}