{
  "type": "Feature",
  "properties": {
    "addr:full":"93 Richardson St SE Atlanta GA 30312",
    "addr:housenumber":"93",
    "addr:postcode":"30312",
    "addr:street":"Richardson St Se",
    "iso:country":"US",
    "sg:address":"93 Richardson St SE",
    "sg:city":"Atlanta",
    "sg:classifiers":[
        {
            "category":"Building & Trades",
            "subcategory":"Construction",
            "type":"Services"
        }
    ],
    "sg:phone":"+1 404 524 1728",
    "sg:postcode":"30312",
    "sg:province":"GA",
    "sg:tags":[
        "house"
    ],
    "wof:name":"Atlantic Development & Cnstr",
    "wof:placetype":"venue"
},
  "geometry": {"coordinates":[-84.38406500000001,33.740648],"type":"Point"}
}