{
  "type": "Feature",
  "properties": {
    "addr:full":"298 N Lexington St Lyons GA 30436",
    "addr:housenumber":"298",
    "addr:postcode":"30436",
    "addr:street":"N Lexington St",
    "iso:country":"US",
    "sg:address":"298 N Lexington St",
    "sg:city":"Lyons",
    "sg:classifiers":[
        {
            "category":"Education",
            "subcategory":"School",
            "type":"Public Place"
        }
    ],
    "sg:phone":"+1 912 526 3666",
    "sg:postcode":"30436",
    "sg:province":"GA",
    "sg:tags":[
        "elementary"
    ],
    "wof:name":"Lyons Elementary",
    "wof:placetype":"venue"
},
  "geometry": {"coordinates":[-82.319203,32.206175],"type":"Point"}
}