{
  "type": "Feature",
  "properties": {
    "addr:full":"975 Hightower Trl Atlanta GA 30350",
    "addr:housenumber":"975",
    "addr:postcode":"30350",
    "addr:street":"Hightower Trl",
    "iso:country":"US",
    "sg:address":"975 Hightower Trl",
    "sg:city":"Atlanta",
    "sg:classifiers":[
        {
            "category":"Professional",
            "type":"Services"
        }
    ],
    "sg:phone":"+1 770 518 8521",
    "sg:postcode":"30350",
    "sg:province":"GA",
    "wof:name":"Be Healthy Wealthy & Wise Inc",
    "wof:placetype":"venue"
},
  "geometry": {"coordinates":[-84.355923,33.990196],"type":"Point"}
}