{
  "type": "Feature",
  "properties": {
    "addr:full":"148 Church Rd Beech Island SC 29842",
    "addr:housenumber":"148",
    "addr:postcode":"29842",
    "addr:street":"Church Rd",
    "iso:country":"US",
    "sg:address":"148 Church Rd",
    "sg:city":"Beech Island",
    "sg:classifiers":[
        {
            "category":"Building & Trades",
            "subcategory":"Construction",
            "type":"Services"
        }
    ],
    "sg:phone":"+1 803 279 3437",
    "sg:postcode":"29842",
    "sg:province":"SC",
    "sg:tags":[
        "contractor"
    ],
    "wof:name":"Glanton Masonery",
    "wof:placetype":"venue"
},
  "geometry": {"coordinates":[-81.86797,33.430261],"type":"Point"}
}