{
  "type": "Feature",
  "properties": {
    "addr:full":"1480 Glenwood Ave SE Atlanta GA 30316",
    "addr:housenumber":"1480",
    "addr:postcode":"30316",
    "addr:street":"Glenwood Ave Se",
    "iso:country":"US",
    "sg:address":"1480 Glenwood Ave SE",
    "sg:city":"Atlanta",
    "sg:classifiers":[
        {
            "category":"Professional",
            "type":"Services"
        }
    ],
    "sg:phone":"+1 404 667 2097",
    "sg:postcode":"30316",
    "sg:province":"GA",
    "wof:name":"Nurse/Edward",
    "wof:placetype":"venue"
},
  "geometry": {"coordinates":[-84.3385,33.740151],"type":"Point"}
}