{
  "type": "Feature",
  "properties": {
    "addr:full":"600 W Broad St Athens GA 30601",
    "addr:housenumber":"600",
    "addr:postcode":"30601",
    "addr:street":"W Broad St",
    "iso:country":"US",
    "sg:address":"600 W Broad St",
    "sg:city":"Athens",
    "sg:classifiers":[
        {
            "category":"Shopping",
            "subcategory":"Tobacco",
            "type":"Retail Goods"
        }
    ],
    "sg:phone":"+1 706 354 0096",
    "sg:postcode":"30601",
    "sg:province":"GA",
    "sg:tags":[
        "cigarette",
        "cigar",
        "lighter"
    ],
    "wof:name":"Prime Tobacco",
    "wof:placetype":"venue"
},
  "geometry": {"coordinates":[-83.384199,33.955912],"type":"Point"}
}