{
  "type": "Feature",
  "properties": {
    "addr:full":"5952 Peachtree Industrial Blvd Ste 13 Norcross GA 30071",
    "addr:housenumber":"5952",
    "addr:postcode":"30071",
    "addr:street":"Peachtree Industrial Blvd Ste 13",
    "iso:country":"US",
    "sg:address":"5952 Peachtree Industrial Blvd Ste 13",
    "sg:city":"Norcross",
    "sg:classifiers":[
        {
            "category":"Wholesale",
            "subcategory":"Medical Equipment & Supplies",
            "type":"Manufacturing & Wholesale Goods"
        },
        {
            "category":"Shopping",
            "subcategory":"Pharmacy",
            "type":"Retail Goods"
        },
        {
            "category":"Health Services",
            "subcategory":"Dentist",
            "type":"Services"
        }
    ],
    "sg:phone":"+1 770 300 9058",
    "sg:postcode":"30071",
    "sg:province":"GA",
    "sg:tags":[
        "home",
        "clinic",
        "dental",
        "care"
    ],
    "sg:website":"http://www.lynchdental.com",
    "wof:name":"Lynch Dental Company",
    "wof:placetype":"venue"
},
  "geometry": {"coordinates":[-84.22789400000001,33.951225],"type":"Point"}
}