{
  "type": "Feature",
  "properties": {
    "iso:country":"US",
    "sg:address":"101 Murphy Industrial Blvd",
    "sg:city":"Bremen",
    "sg:classifiers":[
        {
            "category":"Autos & Motor Vehicles",
            "subcategory":"Auto Supplies",
            "type":"Retail Goods"
        }
    ],
    "sg:phone":"+1 678 309 2000",
    "sg:postcode":"30110",
    "sg:province":"GA",
    "sg:tags":[
        "body",
        "part"
    ],
    "wof:name":"Hl-A Co., Inc. (Delaware)",
    "wof:placetype":"venue"
},
  "geometry": {"coordinates":[-85.171413,33.697685],"type":"Point"}
}