{
  "type": "Feature",
  "properties": {
    "iso:country":"US",
    "sg:address":"6145 Northbelt Pkwy NW",
    "sg:city":"Norcross",
    "sg:classifiers":[
        {
            "category":"Professional",
            "subcategory":"Computer Services",
            "type":"Services"
        }
    ],
    "sg:phone":"+1 770 246 8600",
    "sg:postcode":"30071",
    "sg:province":"GA",
    "sg:tags":[
        "development",
        "consulting",
        "software"
    ],
    "wof:name":"Geofiny Technologies Inc",
    "wof:placetype":"venue"
},
  "geometry": {"coordinates":[-84.216618,33.926891],"type":"Point"}
}