{
  "type": "Feature",
  "properties": {
    "addr:full":"790 Hawthorne Ave Athens GA 30606",
    "addr:housenumber":"790",
    "addr:postcode":"30606",
    "addr:street":"Hawthorne Ave",
    "iso:country":"US",
    "sg:address":"790 Hawthorne Ave",
    "sg:city":"Athens",
    "sg:classifiers":[
        {
            "category":"Food & Beverages",
            "subcategory":"Groceries & Convenience Stores",
            "type":"Retail Goods"
        }
    ],
    "sg:phone":"+1 706 353 4788",
    "sg:postcode":"30606",
    "sg:province":"GA",
    "wof:name":"B P Food Mart",
    "wof:placetype":"venue"
},
  "geometry": {"coordinates":[-83.41324,33.961173],"type":"Point"}
}