{
  "type": "Feature",
  "properties": {
    "addr:full":"1525 Bethel Church Rd Omega GA 31775",
    "addr:housenumber":"1525",
    "addr:postcode":"31775",
    "addr:street":"Bethel Church Rd",
    "iso:country":"US",
    "sg:address":"1525 Bethel Church Rd",
    "sg:city":"Omega",
    "sg:classifiers":[
        {
            "category":"Building & Trades",
            "subcategory":"Plumbing",
            "type":"Services"
        }
    ],
    "sg:phone":"+1 229 776 7276",
    "sg:postcode":"31775",
    "sg:province":"GA",
    "sg:tags":[
        "heavy",
        "contractor"
    ],
    "wof:name":"Hurst Milford Septic Tanks",
    "wof:placetype":"venue"
},
  "geometry": {"coordinates":[-83.658674,31.344338],"type":"Point"}
}