{
  "type": "Feature",
  "properties": {
    "addr:full":"1850 Beaver Ridge Cir Norcross GA 30071",
    "addr:housenumber":"1850",
    "addr:postcode":"30071",
    "addr:street":"Beaver Ridge Cir",
    "iso:country":"US",
    "sg:address":"1850 Beaver Ridge Cir",
    "sg:city":"Norcross",
    "sg:classifiers":[
        {
            "category":"Professional",
            "subcategory":"Computer Services",
            "type":"Services"
        }
    ],
    "sg:phone":"+1 770 407 3333",
    "sg:postcode":"30071",
    "sg:province":"GA",
    "sg:tags":[
        "related",
        "business",
        "association"
    ],
    "wof:name":"Mindharbor Inc",
    "wof:placetype":"venue"
},
  "geometry": {"coordinates":[-84.16632300000001,33.934808],"type":"Point"}
}