{
  "type": "Feature",
  "properties": {
    "iso:country":"US",
    "sg:address":"749 Cedar Ave NW",
    "sg:city":"Atlanta",
    "sg:classifiers":[
        {
            "category":"Insurance",
            "subcategory":"Insurance Agent",
            "type":"Services"
        }
    ],
    "sg:phone":"+1 404 794 5553",
    "sg:postcode":"30318",
    "sg:province":"GA",
    "wof:name":"Community Devel Enferpris Inc",
    "wof:placetype":"venue"
},
  "geometry": {"coordinates":[-84.46483499999999,33.7745],"type":"Point"}
}