{
  "type": "Feature",
  "properties": {
    "iso:country":"US",
    "sg:address":"42 Broad St NW",
    "sg:city":"Atlanta",
    "sg:classifiers":[
        {
            "category":"Education",
            "subcategory":"School",
            "type":"Public Place"
        }
    ],
    "sg:phone":"+1 404 577 2366",
    "sg:postcode":"30303",
    "sg:province":"GA",
    "wof:name":"Esl Instruction",
    "wof:placetype":"venue"
},
  "geometry": {"coordinates":[-84.389974,33.755504],"type":"Point"}
}