{
  "type": "Feature",
  "properties": {
    "addr:full":"4325 Woodward Way Buford GA 30518",
    "addr:housenumber":"4325",
    "addr:postcode":"30518",
    "addr:street":"Woodward Way",
    "iso:country":"US",
    "sg:address":"4325 Woodward Way",
    "sg:city":"Buford",
    "sg:classifiers":[
        {
            "category":"Building & Trades",
            "subcategory":"Landscaping Services",
            "type":"Services"
        }
    ],
    "sg:phone":"+1 770 271 7058",
    "sg:postcode":"30518",
    "sg:province":"GA",
    "sg:tags":[
        "landscape",
        "contractor"
    ],
    "wof:name":"Absolute Landscape Inc",
    "wof:placetype":"venue"
},
  "geometry": {"coordinates":[-84.049425,34.07645],"type":"Point"}
}