{
  "type": "Feature",
  "properties": {
    "addr:full":"3009 Bransford Rd Augusta GA 30909",
    "addr:housenumber":"3009",
    "addr:postcode":"30909",
    "addr:street":"Bransford Rd",
    "iso:country":"US",
    "sg:address":"3009 Bransford Rd",
    "sg:city":"Augusta",
    "sg:classifiers":[
        {
            "category":"Professional",
            "subcategory":"Business Services",
            "type":"Services"
        }
    ],
    "sg:phone":"+1 706 738 6706",
    "sg:postcode":"30909",
    "sg:province":"GA",
    "wof:name":"Margaret Brown Flowers",
    "wof:placetype":"venue"
},
  "geometry": {"coordinates":[-82.044935,33.476605],"type":"Point"}
}