{
  "type": "Feature",
  "properties": {
    "addr:full":"1439 6th Ave Columbus GA 31901",
    "addr:housenumber":"1439",
    "addr:postcode":"31901",
    "addr:street":"6Th Ave",
    "iso:country":"US",
    "sg:address":"1439 6th Ave",
    "sg:city":"Columbus",
    "sg:classifiers":[
        {
            "category":"Home & Garden",
            "subcategory":"Building Materials",
            "type":"Retail Goods"
        }
    ],
    "sg:phone":"+1 706 327 3285",
    "sg:postcode":"31901",
    "sg:province":"GA",
    "sg:tags":[
        "plate",
        "glass-auto",
        "window",
        "glass"
    ],
    "wof:name":"Uneeda Glass Co",
    "wof:placetype":"venue"
},
  "geometry": {"coordinates":[-84.984796,32.47313],"type":"Point"}
}