{
  "type": "Feature",
  "properties": {
    "addr:full":"151 Skyview Dr Gainesville GA 30501",
    "addr:housenumber":"151",
    "addr:postcode":"30501",
    "addr:street":"Skyview Dr",
    "iso:country":"US",
    "sg:address":"151 Skyview Dr",
    "sg:city":"Gainesville",
    "sg:classifiers":[
        {
            "category":"Utilities",
            "subcategory":"Mobile Phone",
            "type":"Services"
        }
    ],
    "sg:phone":"+1 770 532 3157",
    "sg:postcode":"30501",
    "sg:province":"GA",
    "sg:tags":[
        "telephone",
        "cellular"
    ],
    "wof:name":"Cingular Wireless",
    "wof:placetype":"venue"
},
  "geometry": {"coordinates":[-83.86262600000001,34.309097],"type":"Point"}
}