{
  "type": "Feature",
  "properties": {
    "iso:country":"US",
    "sg:address":"3411 Austell Rd SW",
    "sg:city":"Marietta",
    "sg:classifiers":[
        {
            "category":"Professional",
            "subcategory":"Lawyer & Legal Services",
            "type":"Services"
        }
    ],
    "sg:phone":"+1 770 437 1150",
    "sg:postcode":"30008",
    "sg:province":"GA",
    "wof:name":"Onyirimba Law Offices",
    "wof:placetype":"venue"
},
  "geometry": {"coordinates":[-84.591103,33.869801],"type":"Point"}
}