{
  "type": "Feature",
  "properties": {
    "addr:full":"24 Amberstone Ct Jefferson GA 30549",
    "addr:housenumber":"24",
    "addr:postcode":"30549",
    "addr:street":"Amberstone Ct",
    "iso:country":"US",
    "sg:address":"24 Amberstone Ct",
    "sg:city":"Jefferson",
    "sg:classifiers":[
        {
            "category":"Real Estate",
            "subcategory":"Real Estate Services",
            "type":"Services"
        },
        {
            "category":"Real Estate",
            "subcategory":"Real Estate Agent",
            "type":"Services"
        }
    ],
    "sg:phone":"+1 706 367 4413",
    "sg:postcode":"30549",
    "sg:province":"GA",
    "sg:tags":[
        "buyer",
        "broker"
    ],
    "wof:name":"Solid Source Realty",
    "wof:placetype":"venue"
},
  "geometry": {"coordinates":[-83.63493699999999,34.098631],"type":"Point"}
}