{
  "type": "Feature",
  "properties": {
    "addr:full":"2200 Osborne Rd Saint Marys GA 31558",
    "addr:housenumber":"2200",
    "addr:postcode":"31558",
    "addr:street":"Osborne Rd",
    "iso:country":"US",
    "sg:address":"2200 Osborne Rd",
    "sg:city":"Saint Marys",
    "sg:classifiers":[
        {
            "category":"Restaurant",
            "type":"Food & Drink"
        }
    ],
    "sg:menulink":"http://www.allmenus.com/ga/st-marys/244291-sidelines/menu/",
    "sg:phone":"+1 912 576 9629",
    "sg:postcode":"31558",
    "sg:province":"GA",
    "sg:tags":[
        "american"
    ],
    "wof:name":"Sidelines",
    "wof:placetype":"venue"
},
  "geometry": {"coordinates":[-81.562138,30.746205],"type":"Point"}
}