{
  "type": "Feature",
  "properties": {
    "addr:full":"295 Sudderth St Buford GA 30518",
    "addr:housenumber":"295",
    "addr:postcode":"30518",
    "addr:street":"Sudderth St",
    "iso:country":"US",
    "sg:address":"295 Sudderth St",
    "sg:city":"Buford",
    "sg:classifiers":[
        {
            "category":"Utilities",
            "subcategory":"Telephone",
            "type":"Services"
        }
    ],
    "sg:phone":"+1 770 831 2532",
    "sg:postcode":"30518",
    "sg:province":"GA",
    "sg:tags":[
        "telecommunication"
    ],
    "wof:name":"Fogle Consulting",
    "wof:placetype":"venue"
},
  "geometry": {"coordinates":[-84.005229,34.113079],"type":"Point"}
}