{
  "type": "Feature",
  "properties": {
    "addr:full":"715 Rhodes Creek Trl Alpharetta GA 30004",
    "addr:housenumber":"715",
    "addr:postcode":"30004",
    "addr:street":"Rhodes Creek Trl",
    "iso:country":"US",
    "sg:address":"715 Rhodes Creek Trl",
    "sg:city":"Alpharetta",
    "sg:classifiers":[
        {
            "category":"Professional",
            "type":"Services"
        }
    ],
    "sg:phone":"+1 678 366 8838",
    "sg:postcode":"30004",
    "sg:province":"GA",
    "wof:name":"Tallent Inc II",
    "wof:placetype":"venue"
},
  "geometry": {"coordinates":[-84.287373,34.100103],"type":"Point"}
}