{
  "type": "Feature",
  "properties": {
    "addr:full":"600 N Greenwood St La Grange GA 30240",
    "addr:housenumber":"600",
    "addr:postcode":"30240",
    "addr:street":"N Greenwood St",
    "iso:country":"US",
    "sg:address":"600 N Greenwood St",
    "sg:city":"La Grange",
    "sg:classifiers":[
        {
            "category":"Wholesale",
            "subcategory":"Machinery & Supplies",
            "type":"Manufacturing & Wholesale Goods"
        }
    ],
    "sg:phone":"+1 706 884 7704",
    "sg:postcode":"30240",
    "sg:province":"GA",
    "sg:tags":[
        "equipment",
        "establishment"
    ],
    "wof:name":"Hair Connection & Supplies",
    "wof:placetype":"venue"
},
  "geometry": {"coordinates":[-85.03445000000001,33.049133],"type":"Point"}
}