{
  "type": "Feature",
  "properties": {
    "addr:full":"4400 Ashford Dunwoody Rd NE Atlanta GA 30346",
    "addr:housenumber":"4400",
    "addr:postcode":"30346",
    "addr:street":"Ashford Dunwoody Rd Ne",
    "iso:country":"US",
    "sg:address":"4400 Ashford Dunwoody Rd NE",
    "sg:city":"Atlanta",
    "sg:classifiers":[
        {
            "category":"Shopping",
            "subcategory":"Mobile Phones",
            "type":"Retail Goods"
        }
    ],
    "sg:phone":"+1 770 399 9723",
    "sg:postcode":"30346",
    "sg:province":"GA",
    "wof:name":"T-Mobile",
    "wof:placetype":"venue"
},
  "geometry": {"coordinates":[-84.340515,33.921742],"type":"Point"}
}