{
  "type": "Feature",
  "properties": {
    "iso:country":"US",
    "sg:address":"109 Pearl St",
    "sg:city":"Cuthbert",
    "sg:classifiers":[
        {
            "category":"Communications",
            "type":"Services"
        }
    ],
    "sg:phone":"+1 229 732 6767",
    "sg:postcode":"31791",
    "sg:province":"GA",
    "wof:name":"All Day Communications Inc",
    "wof:placetype":"venue"
},
  "geometry": {"coordinates":[-83.853151,31.529859],"type":"Point"}
}