{
  "type": "Feature",
  "properties": {
    "addr:full":"1100 Circle 75 Pkwy SE Ste 1100 Atlanta GA 30339",
    "addr:housenumber":"1100",
    "addr:postcode":"30339",
    "addr:street":"Circle 75 Pkwy Se Ste 1100",
    "iso:country":"US",
    "sg:address":"1100 Circle 75 Pkwy SE Ste 1100",
    "sg:city":"Atlanta",
    "sg:classifiers":[
        {
            "category":"Banks & Credit Unions",
            "subcategory":"Financial Services",
            "type":"Services"
        }
    ],
    "sg:phone":"+1 770 999 8640",
    "sg:postcode":"30339",
    "sg:province":"GA",
    "sg:tags":[
        "broker",
        "mortgage"
    ],
    "wof:name":"Processing Solutions",
    "wof:placetype":"venue"
},
  "geometry": {"coordinates":[-84.46980600000001,33.886815],"type":"Point"}
}