{
  "type": "Feature",
  "properties": {
    "iso:country":"US",
    "sg:address":"275 Carpenter Dr NE",
    "sg:city":"Atlanta",
    "sg:classifiers":[
        {
            "category":"Professional",
            "subcategory":"Business Services",
            "type":"Services"
        }
    ],
    "sg:phone":"+1 404 250 1297",
    "sg:postcode":"30328",
    "sg:province":"GA",
    "wof:name":"Southscribe",
    "wof:placetype":"venue"
},
  "geometry": {"coordinates":[-84.375794,33.914377],"type":"Point"}
}