{
  "type": "Feature",
  "properties": {
    "addr:full":"4281 Hugh Howell Rd Tucker GA 30084",
    "addr:housenumber":"4281",
    "addr:postcode":"30084",
    "addr:street":"Hugh Howell Rd",
    "iso:country":"US",
    "sg:address":"4281 Hugh Howell Rd",
    "sg:city":"Tucker",
    "sg:classifiers":[
        {
            "category":"Building & Trades",
            "subcategory":"Plumbing",
            "type":"Services"
        }
    ],
    "sg:phone":"+1 678 937 0574",
    "sg:postcode":"30084",
    "sg:province":"GA",
    "sg:tags":[
        "contractor"
    ],
    "wof:name":"Faith Mechanical E & I",
    "wof:placetype":"venue"
},
  "geometry": {"coordinates":[-84.20836,33.851684],"type":"Point"}
}