{
  "type": "Feature",
  "properties": {
    "addr:full":"1867 Watson Blvd Warner Robins GA 31093",
    "addr:housenumber":"1867",
    "addr:postcode":"31093",
    "addr:street":"Watson Blvd",
    "iso:country":"US",
    "sg:address":"1867 Watson Blvd",
    "sg:city":"Warner Robins",
    "sg:classifiers":[
        {
            "category":"Restaurant",
            "type":"Food & Drink"
        }
    ],
    "sg:menulink":"http://www.allmenus.com/ga/warner-robins/179965-chick-fil-a/menu/",
    "sg:phone":"+1 912 328 0445",
    "sg:postcode":"31093",
    "sg:province":"GA",
    "sg:tags":[
        "wrap",
        "soup",
        "american",
        "sandwich",
        "salad"
    ],
    "wof:name":"Chick-fil-A",
    "wof:placetype":"venue"
},
  "geometry": {"coordinates":[-83.639858,32.618206],"type":"Point"}
}