{
  "type": "Feature",
  "properties": {
    "addr:full":"305 Buckhead Avenue NE Suite 122 Atlanta GA 30305",
    "addr:housenumber":"305",
    "addr:postcode":"30305",
    "addr:street":"Buckhead Avenue Ne Suite 122",
    "iso:country":"US",
    "sg:address":"305 Buckhead Avenue NE Suite 122",
    "sg:city":"Atlanta",
    "sg:classifiers":[
        {
            "category":"Professional",
            "subcategory":"Lawyer & Legal Services",
            "type":"Services"
        }
    ],
    "sg:phone":"+1 404 816 1222",
    "sg:postcode":"30305",
    "sg:province":"GA",
    "wof:name":"Kintz Peter K Atty Jr",
    "wof:placetype":"venue"
},
  "geometry": {"coordinates":[-84.377669,33.838215],"type":"Point"}
}