{
  "type": "Feature",
  "properties": {
    "iso:country":"US",
    "sg:address":"4216 Aerie Cir",
    "sg:city":"Evans",
    "sg:classifiers":[
        {
            "category":"Education",
            "subcategory":"Special Training",
            "type":"Public Place"
        }
    ],
    "sg:phone":"+1 706 854 0090",
    "sg:postcode":"30809",
    "sg:province":"GA",
    "sg:tags":[
        "educational"
    ],
    "wof:name":"William F Trammell",
    "wof:placetype":"venue"
},
  "geometry": {"coordinates":[-82.102108,33.572565],"type":"Point"}
}