{
  "type": "Feature",
  "properties": {
    "addr:full":"1480 Old Salem Rd SE Conyers GA 30013",
    "addr:housenumber":"1480",
    "addr:postcode":"30013",
    "addr:street":"Old Salem Rd Se",
    "iso:country":"US",
    "sg:address":"1480 Old Salem Rd SE",
    "sg:city":"Conyers",
    "sg:classifiers":[
        {
            "category":"Personal",
            "subcategory":"Barber",
            "type":"Services"
        }
    ],
    "sg:phone":"+1 770 760 1185",
    "sg:postcode":"30013",
    "sg:province":"GA",
    "sg:tags":[
        "shop"
    ],
    "wof:name":"Bill's Salem Gate Barber Shop",
    "wof:placetype":"venue"
},
  "geometry": {"coordinates":[-84.00309900000001,33.647098],"type":"Point"}
}