{
  "type": "Feature",
  "properties": {
    "addr:full":"113 Jones Rd Cochran GA 31082",
    "addr:housenumber":"113",
    "addr:postcode":"31082",
    "addr:street":"Jones Rd",
    "iso:country":"US",
    "sg:address":"113 Jones Rd",
    "sg:city":"Cochran",
    "sg:classifiers":[
        {
            "category":"Freight",
            "type":"Transportation"
        }
    ],
    "sg:phone":"+1 478 934 4094",
    "sg:postcode":"31082",
    "sg:province":"GA",
    "sg:tags":[
        "trucking"
    ],
    "wof:name":"Flying Tiger Transport",
    "wof:placetype":"venue"
},
  "geometry": {"coordinates":[-82.769498,32.946008],"type":"Point"}
}