{
  "type": "Feature",
  "properties": {
    "iso:country":"US",
    "sg:address":"254 Bishkoko Ave",
    "sg:city":"Rossville",
    "sg:classifiers":[
        {
            "category":"Organizations",
            "subcategory":"Religious Organization",
            "type":"Services"
        }
    ],
    "sg:phone":"+1 706 858 1023",
    "sg:postcode":"30741",
    "sg:province":"GA",
    "sg:tags":[
        "church"
    ],
    "wof:name":"East Ridge United Pentecostal",
    "wof:placetype":"venue"
},
  "geometry": {"coordinates":[-85.24406500000001,34.983145],"type":"Point"}
}