{
  "type": "Feature",
  "properties": {
    "iso:country":"US",
    "sg:address":"903 Briarcliff Rd",
    "sg:city":"Nashville",
    "sg:classifiers":[
        {
            "category":"Place Of Worship",
            "subcategory":"Church",
            "type":"Public Place"
        },
        {
            "category":"Place Of Worship",
            "type":"Public Place"
        }
    ],
    "sg:phone":"+1 229 686 5291",
    "sg:postcode":"31639",
    "sg:province":"GA",
    "sg:tags":[
        "churches-methodist"
    ],
    "wof:name":"Nashville United Methodist Church",
    "wof:placetype":"venue"
},
  "geometry": {"coordinates":[-83.260576,31.203445],"type":"Point"}
}