{
  "type": "Feature",
  "properties": {
    "addr:full":"631 Irvin St Cornelia GA 30531",
    "addr:housenumber":"631",
    "addr:postcode":"30531",
    "addr:street":"Irvin St",
    "iso:country":"US",
    "sg:address":"631 Irvin St",
    "sg:city":"Cornelia",
    "sg:phone":"+1 706 776 2181",
    "sg:postcode":"30531",
    "sg:province":"GA",
    "wof:name":"Fenders Diner",
    "wof:placetype":"venue"
},
  "geometry": {"coordinates":[-83.527862,34.510997],"type":"Point"}
}