{
  "type": "Feature",
  "properties": {
    "addr:full":"3377 Ponder Rd Thomasville GA 31757",
    "addr:housenumber":"3377",
    "addr:postcode":"31757",
    "addr:street":"Ponder Rd",
    "iso:country":"US",
    "sg:address":"3377 Ponder Rd",
    "sg:city":"Thomasville",
    "sg:classifiers":[
        {
            "category":"Social Services",
            "subcategory":"Child Care",
            "type":"Services"
        }
    ],
    "sg:phone":"+1 229 228 5074",
    "sg:postcode":"31757",
    "sg:province":"GA",
    "sg:tags":[
        "center",
        "daycare"
    ],
    "wof:name":"Angela Clark",
    "wof:placetype":"venue"
},
  "geometry": {"coordinates":[-83.840615,30.924459],"type":"Point"}
}