{
  "type": "Feature",
  "properties": {
    "iso:country":"US",
    "sg:address":"2067 Pinnacle Point Dr",
    "sg:city":"Norcross",
    "sg:classifiers":[
        {
            "category":"Professional",
            "subcategory":"Computer Services",
            "type":"Services"
        }
    ],
    "sg:phone":"+1 770 446 1461",
    "sg:postcode":"30071",
    "sg:province":"GA",
    "sg:tags":[
        "programing",
        "custom"
    ],
    "wof:name":"Kinetic Wireless Inc",
    "wof:placetype":"venue"
},
  "geometry": {"coordinates":[-84.18328099999999,33.93333],"type":"Point"}
}