{
  "type": "Feature",
  "properties": {
    "iso:country":"US",
    "sg:address":"6286 Pine View Ter",
    "sg:city":"Riverdale",
    "sg:classifiers":[
        {
            "category":"Professional",
            "subcategory":"Management & Consulting",
            "type":"Services"
        }
    ],
    "sg:phone":"+1 770 991 0234",
    "sg:postcode":"30296",
    "sg:province":"GA",
    "sg:tags":[
        "business"
    ],
    "wof:name":"Granison Consulting",
    "wof:placetype":"venue"
},
  "geometry": {"coordinates":[-84.427009,33.582611],"type":"Point"}
}