{
  "type": "Feature",
  "properties": {
    "iso:country":"US",
    "sg:address":"407 Covington St",
    "sg:city":"Jackson",
    "sg:classifiers":[
        {
            "category":"Real Estate",
            "subcategory":"Real Estate Agent",
            "type":"Services"
        }
    ],
    "sg:phone":"+1 770 775 3341",
    "sg:postcode":"30233",
    "sg:province":"GA",
    "wof:name":"Morningside Realty",
    "wof:placetype":"venue"
},
  "geometry": {"coordinates":[-83.96169999999999,33.297311],"type":"Point"}
}