{
  "type": "Feature",
  "properties": {
    "iso:country":"US",
    "sg:address":"6680 Ashbrook Dr",
    "sg:city":"Douglasville",
    "sg:classifiers":[
        {
            "category":"Professional",
            "type":"Services"
        }
    ],
    "sg:phone":"+1 770 489 2248",
    "sg:postcode":"30135",
    "sg:province":"GA",
    "sg:tags":[
        "establishment"
    ],
    "wof:name":"Brown Chicago & Addison",
    "wof:placetype":"venue"
},
  "geometry": {"coordinates":[-84.79148600000001,33.655455],"type":"Point"}
}