{
  "type": "Feature",
  "properties": {
    "addr:full":"1743 Detroit Ave NW Atlanta GA 30314",
    "addr:housenumber":"1743",
    "addr:postcode":"30314",
    "addr:street":"Detroit Ave Nw",
    "iso:country":"US",
    "sg:address":"1743 Detroit Ave NW",
    "sg:city":"Atlanta",
    "sg:classifiers":[
        {
            "category":"Professional",
            "subcategory":"Accounting & Tax Preparation",
            "type":"Services"
        }
    ],
    "sg:phone":"+1 404 794 6273",
    "sg:postcode":"30314",
    "sg:province":"GA",
    "sg:tags":[
        "return"
    ],
    "wof:name":"Norwood Accoutning and Tax Svc",
    "wof:placetype":"venue"
},
  "geometry": {"coordinates":[-84.44412199999999,33.766666],"type":"Point"}
}