{
  "type": "Feature",
  "properties": {
    "iso:country":"US",
    "sg:address":"1023 Spring Place Rd NE",
    "sg:city":"White",
    "sg:classifiers":[
        {
            "category":"Shopping",
            "subcategory":"Clothing, Apparel, & Fashions",
            "type":"Retail Goods"
        }
    ],
    "sg:phone":"+1 770 382 2458",
    "sg:postcode":"30184",
    "sg:province":"GA",
    "sg:tags":[
        "t"
    ],
    "wof:name":"Spring Place Tees",
    "wof:placetype":"venue"
},
  "geometry": {"coordinates":[-84.78903699999999,34.350414],"type":"Point"}
}