{
  "type": "Feature",
  "properties": {
    "addr:full":"6301 Macon Rd Columbus GA 31907",
    "addr:housenumber":"6301",
    "addr:postcode":"31907",
    "addr:street":"Macon Rd",
    "iso:country":"US",
    "sg:address":"6301 Macon Rd",
    "sg:city":"Columbus",
    "sg:classifiers":[
        {
            "category":"Home & Garden",
            "subcategory":"Garden Supply",
            "type":"Retail Goods"
        }
    ],
    "sg:phone":"+1 706 561 2555",
    "sg:postcode":"31907",
    "sg:province":"GA",
    "sg:tags":[
        "landscaping",
        "nursery",
        "center",
        "contractor"
    ],
    "wof:name":"To-Mar Garden Center & Ldscpg",
    "wof:placetype":"venue"
},
  "geometry": {"coordinates":[-84.880392,32.518226],"type":"Point"}
}