{
  "type": "Feature",
  "properties": {
    "iso:country":"US",
    "sg:address":"2419 Giddens Dr",
    "sg:city":"Valdosta",
    "sg:classifiers":[
        {
            "category":"Social Services",
            "type":"Services"
        }
    ],
    "sg:phone":"+1 229 241 1777",
    "sg:postcode":"31602",
    "sg:province":"GA",
    "wof:name":"Rowes Daycare",
    "wof:placetype":"venue"
},
  "geometry": {"coordinates":[-83.28081,30.868406],"type":"Point"}
}