{
  "type": "Feature",
  "properties": {
    "addr:full":"202 Indian Trl Dahlonega GA 30533",
    "addr:housenumber":"202",
    "addr:postcode":"30533",
    "addr:street":"Indian Trl",
    "iso:country":"US",
    "sg:address":"202 Indian Trl",
    "sg:city":"Dahlonega",
    "sg:classifiers":[
        {
            "category":"Personal",
            "type":"Services"
        },
        {
            "category":"Professional",
            "subcategory":"Art Services",
            "type":"Services"
        }
    ],
    "sg:phone":"+1 706 864 5712",
    "sg:postcode":"30533",
    "sg:province":"GA",
    "sg:tags":[
        "photography",
        "videography",
        "wedding"
    ],
    "wof:name":"Kennison Photography",
    "wof:placetype":"venue"
},
  "geometry": {"coordinates":[-83.909485,34.53727],"type":"Point"}
}