{
  "type": "Feature",
  "properties": {
    "iso:country":"US",
    "sg:address":"1650 Anderson Mill Rd",
    "sg:city":"Austell",
    "sg:classifiers":[
        {
            "category":"Building & Trades",
            "subcategory":"Locksmith",
            "type":"Services"
        }
    ],
    "sg:phone":"+1 877 226 3763",
    "sg:postcode":"30106",
    "sg:province":"GA",
    "sg:tags":[
        "key"
    ],
    "wof:name":"1 & A Emergency Locksmith",
    "wof:placetype":"venue"
},
  "geometry": {"coordinates":[-84.60300100000001,33.848335],"type":"Point"}
}