{
  "type": "Feature",
  "properties": {
    "addr:full":"2480 Old Cornelia Hwy Gainesville GA 30507",
    "addr:housenumber":"2480",
    "addr:postcode":"30507",
    "addr:street":"Old Cornelia Hwy",
    "iso:country":"US",
    "sg:address":"2480 Old Cornelia Hwy",
    "sg:city":"Gainesville",
    "sg:classifiers":[
        {
            "category":"Education",
            "subcategory":"School",
            "type":"Public Place"
        }
    ],
    "sg:phone":"+1 770 532 0945",
    "sg:postcode":"30507",
    "sg:province":"GA",
    "sg:tags":[
        "elementary"
    ],
    "wof:name":"White Sulpher Elementary Schl",
    "wof:placetype":"venue"
},
  "geometry": {"coordinates":[-83.77431799999999,34.312775],"type":"Point"}
}