{
  "type": "Feature",
  "properties": {
    "addr:full":"2494 Hidden Cove Ct Apt C Gainesville GA 30501",
    "addr:housenumber":"2494",
    "addr:postcode":"30501",
    "addr:street":"Hidden Cove Ct Apt C Gainesville",
    "iso:country":"US",
    "sg:address":"2494 Hidden Cove Ct Apt C",
    "sg:city":"Gainesville",
    "sg:classifiers":[
        {
            "category":"Shopping",
            "subcategory":"Department Store",
            "type":"Retail Goods"
        }
    ],
    "sg:phone":"+1 404 408 2404",
    "sg:postcode":"30501",
    "sg:province":"GA",
    "wof:name":"London Tony Clothing Company",
    "wof:placetype":"venue"
},
  "geometry": {"coordinates":[-83.849262,34.335112],"type":"Point"}
}