{
  "type": "Feature",
  "properties": {
    "iso:country":"US",
    "sg:address":"3488 State Rte 332",
    "sg:city":"Hoschton",
    "sg:classifiers":[
        {
            "category":"Building & Trades",
            "subcategory":"Pest Control",
            "type":"Services"
        }
    ],
    "sg:phone":"+1 706 654 3361",
    "sg:postcode":"30548",
    "sg:province":"GA",
    "wof:name":"Cash Termite & Pest Control",
    "wof:placetype":"venue"
},
  "geometry": {"coordinates":[-83.690333,34.121556],"type":"Point"}
}