{
  "type": "Feature",
  "properties": {
    "iso:country":"US",
    "sg:address":"3223 S Cherokee Ln",
    "sg:city":"Woodstock",
    "sg:classifiers":[
        {
            "category":"Professional",
            "type":"Services"
        }
    ],
    "sg:phone":"+1 770 517 0161",
    "sg:postcode":"30188",
    "sg:province":"GA",
    "wof:name":"Advanced Simulations LLC",
    "wof:placetype":"venue"
},
  "geometry": {"coordinates":[-84.471531,34.085284],"type":"Point"}
}