{
  "type": "Feature",
  "properties": {
    "addr:full":"7015 Redwood Dr Columbus GA 31904",
    "addr:housenumber":"7015",
    "addr:postcode":"31904",
    "addr:street":"Redwood Dr",
    "iso:country":"US",
    "sg:address":"7015 Redwood Dr",
    "sg:city":"Columbus",
    "sg:classifiers":[
        {
            "category":"Professional",
            "type":"Services"
        }
    ],
    "sg:phone":"+1 706 320 9420",
    "sg:postcode":"31904",
    "sg:province":"GA",
    "wof:name":"Hancock Title",
    "wof:placetype":"venue"
},
  "geometry": {"coordinates":[-84.98490200000001,32.548924],"type":"Point"}
}