{
  "type": "Feature",
  "properties": {
    "iso:country":"US",
    "sg:address":"1919 Metropolitan Pkwy SW",
    "sg:city":"Atlanta",
    "sg:classifiers":[
        {
            "category":"Shopping",
            "subcategory":"Computers & Home Electronics",
            "type":"Retail Goods"
        }
    ],
    "sg:phone":"+1 404 761 6001",
    "sg:postcode":"30315",
    "sg:province":"GA",
    "wof:name":"A Computer Solutions Inc",
    "wof:placetype":"venue"
},
  "geometry": {"coordinates":[-84.40807,33.702009],"type":"Point"}
}