{
  "type": "Feature",
  "properties": {
    "addr:full":"2025 E Pinetree Blvd Thomasville GA 31792",
    "addr:housenumber":"2025",
    "addr:postcode":"31792",
    "addr:street":"E Pinetree Blvd",
    "iso:country":"US",
    "sg:address":"2025 E Pinetree Blvd",
    "sg:city":"Thomasville",
    "sg:classifiers":[
        {
            "category":"Real Estate",
            "subcategory":"Real Estate Operator",
            "type":"Services"
        }
    ],
    "sg:phone":"+1 229 226 6828",
    "sg:postcode":"31792",
    "sg:province":"GA",
    "sg:tags":[
        "building",
        "apartment"
    ],
    "wof:name":"Georgian Woods",
    "wof:placetype":"venue"
},
  "geometry": {"coordinates":[-83.948201,30.848575],"type":"Point"}
}