{
  "type": "Feature",
  "properties": {
    "addr:full":"436 Cobb Pkwy S Marietta GA 30060",
    "addr:housenumber":"436",
    "addr:postcode":"30060",
    "addr:street":"Cobb Pkwy S",
    "iso:country":"US",
    "sg:address":"436 Cobb Pkwy S",
    "sg:city":"Marietta",
    "sg:classifiers":[
        {
            "category":"Retail",
            "subcategory":"Auto Repair",
            "type":"Services"
        }
    ],
    "sg:phone":"+1 770 514 9440",
    "sg:postcode":"30060",
    "sg:province":"GA",
    "sg:tags":[
        "repairing",
        "automobile"
    ],
    "wof:name":"Marietta Auto Ctr",
    "wof:placetype":"venue"
},
  "geometry": {"coordinates":[-84.516176,33.942011],"type":"Point"}
}