{
  "type": "Feature",
  "properties": {
    "addr:full":"2160 Oakland Industrial Ct Lawrenceville GA 30044",
    "addr:housenumber":"2160",
    "addr:postcode":"30044",
    "addr:street":"Oakland Industrial Ct",
    "iso:country":"US",
    "sg:address":"2160 Oakland Industrial Ct",
    "sg:city":"Lawrenceville",
    "sg:classifiers":[
        {
            "category":"Wholesale",
            "subcategory":"Machinery & Supplies",
            "type":"Manufacturing & Wholesale Goods"
        }
    ],
    "sg:phone":"+1 678 518 4447",
    "sg:postcode":"30044",
    "sg:province":"GA",
    "sg:tags":[
        "equipment",
        "printing"
    ],
    "wof:name":"Design Inks LLC",
    "wof:placetype":"venue"
},
  "geometry": {"coordinates":[-84.074094,33.956956],"type":"Point"}
}