{
  "type": "Feature",
  "properties": {
    "iso:country":"US",
    "sg:address":"427 Rays Church Rd",
    "sg:city":"Bishop",
    "sg:classifiers":[
        {
            "category":"Real Estate",
            "subcategory":"Real Estate Agent",
            "type":"Services"
        }
    ],
    "sg:phone":"+1 706 769 4556",
    "sg:postcode":"30621",
    "sg:province":"GA",
    "sg:tags":[
        "appraiser"
    ],
    "wof:name":"Appraisal Services Of Ga",
    "wof:placetype":"venue"
},
  "geometry": {"coordinates":[-83.502695,33.839542],"type":"Point"}
}