{
  "type": "Feature",
  "properties": {
    "iso:country":"US",
    "sg:address":"515 Percy Miller Rd",
    "sg:city":"Hazlehurst",
    "sg:classifiers":[
        {
            "category":"Building & Trades",
            "subcategory":"Landscaping Services",
            "type":"Services"
        }
    ],
    "sg:phone":"+1 912 375 0103",
    "sg:postcode":"31539",
    "sg:province":"GA",
    "wof:name":"Johnson Tree Planting Service",
    "wof:placetype":"venue"
},
  "geometry": {"coordinates":[-82.43478,31.894525],"type":"Point"}
}