{
  "type": "Feature",
  "properties": {
    "addr:full":"802 Dacula Rd Dacula GA 30019",
    "addr:housenumber":"802",
    "addr:postcode":"ga 30019",
    "addr:street":"Dacula Rd",
    "iso:country":"US",
    "sg:address":"802 Dacula Rd",
    "sg:city":"Dacula",
    "sg:classifiers":[
        {
            "category":"Building & Trades",
            "subcategory":"Construction",
            "type":"Services"
        }
    ],
    "sg:phone":"+1 770 962 1891",
    "sg:postcode":"30019",
    "sg:province":"GA",
    "sg:tags":[
        "contractor"
    ],
    "wof:name":"Artistic Stucco European",
    "wof:placetype":"venue"
},
  "geometry": {"coordinates":[-83.910956,34.001146],"type":"Point"}
}