{
  "type": "Feature",
  "properties": {
    "addr:full":"2214 Silver Hill Rd Stone Mountain GA 30087",
    "addr:housenumber":"2214",
    "addr:postcode":"30087",
    "addr:street":"Silver Hill Rd",
    "iso:country":"US",
    "sg:address":"2214 Silver Hill Rd",
    "sg:city":"Stone Mountain",
    "sg:classifiers":[
        {
            "category":"Professional",
            "subcategory":"Business Services",
            "type":"Services"
        }
    ],
    "sg:phone":"+1 770 279 8889",
    "sg:postcode":"30087",
    "sg:province":"GA",
    "sg:tags":[
        "interior",
        "consultant",
        "design",
        "decorator"
    ],
    "wof:name":"Ellen Terry",
    "wof:placetype":"venue"
},
  "geometry": {"coordinates":[-84.150353,33.836001],"type":"Point"}
}