{
  "type": "Feature",
  "properties": {
    "iso:country":"US",
    "sg:address":"395 Charlotte Blvd",
    "sg:city":"Stockbridge",
    "sg:classifiers":[
        {
            "category":"Building & Trades",
            "subcategory":"Construction",
            "type":"Services"
        }
    ],
    "sg:phone":"+1 770 506 2321",
    "sg:postcode":"30281",
    "sg:province":"GA",
    "sg:tags":[
        "painter"
    ],
    "wof:name":"Bills GC",
    "wof:placetype":"venue"
},
  "geometry": {"coordinates":[-84.209795,33.546718],"type":"Point"}
}