{
  "type": "Feature",
  "properties": {
    "iso:country":"US",
    "sg:address":"546 S Candler St",
    "sg:city":"Decatur",
    "sg:classifiers":[
        {
            "category":"Autos & Motor Vehicles",
            "subcategory":"Automobile Sales",
            "type":"Retail Goods"
        },
        {
            "category":"Retail",
            "subcategory":"Auto Repair",
            "type":"Services"
        }
    ],
    "sg:phone":"+1 404 373 1916",
    "sg:postcode":"30030",
    "sg:province":"GA",
    "sg:tags":[
        "car",
        "new"
    ],
    "wof:name":"Decatur Automotive Center Lexus",
    "wof:placetype":"venue"
},
  "geometry": {"coordinates":[-84.292602,33.761963],"type":"Point"}
}