{
  "type": "Feature",
  "properties": {
    "iso:country":"US",
    "sg:address":"2254 Idlewood Rd",
    "sg:city":"Tucker",
    "sg:classifiers":[
        {
            "category":"Retail",
            "subcategory":"Auto Repair",
            "type":"Services"
        }
    ],
    "sg:phone":"+1 770 939 1938",
    "sg:postcode":"30084",
    "sg:province":"GA",
    "sg:tags":[
        "repairing",
        "automobile"
    ],
    "wof:name":"A & R Fleet Svc",
    "wof:placetype":"venue"
},
  "geometry": {"coordinates":[-84.21341700000001,33.850265],"type":"Point"}
}