{
  "type": "Feature",
  "properties": {
    "iso:country":"US",
    "sg:address":"4842 Fulton Industrial Bl",
    "sg:city":"Atlanta",
    "sg:classifiers":[
        {
            "category":"Restaurant",
            "type":"Food & Drink"
        }
    ],
    "sg:phone":"+1 404 696 3030",
    "sg:postcode":"30336",
    "sg:province":"GA",
    "wof:name":"Cafe Oasis",
    "wof:placetype":"venue"
},
  "geometry": {"coordinates":[-84.544708,33.755997],"type":"Point"}
}