{
  "type": "Feature",
  "properties": {
    "addr:full":"464 Kermitt Mann Rd Lyons GA 30436",
    "addr:housenumber":"464",
    "addr:postcode":"30436",
    "addr:street":"Kermitt Mann Rd",
    "iso:country":"US",
    "sg:address":"464 Kermitt Mann Rd",
    "sg:city":"Lyons",
    "sg:classifiers":[
        {
            "category":"Organizations",
            "subcategory":"Religious Organization",
            "type":"Services"
        }
    ],
    "sg:phone":"+1 912 565 0044",
    "sg:postcode":"30436",
    "sg:province":"GA",
    "wof:name":"Griner Settlement Church",
    "wof:placetype":"venue"
},
  "geometry": {"coordinates":[-82.34275,32.00142],"type":"Point"}
}