{
  "type": "Feature",
  "properties": {
    "addr:full":"5075 Peachtree Pkwy Norcross GA 30092",
    "addr:housenumber":"5075",
    "addr:postcode":"30092",
    "addr:street":"Peachtree Pkwy",
    "iso:country":"US",
    "sg:address":"5075 Peachtree Pkwy",
    "sg:city":"Norcross",
    "sg:classifiers":[
        {
            "category":"Bakery",
            "type":"Food & Drink"
        },
        {
            "category":"Coffee & Tea",
            "type":"Food & Drink"
        },
        {
            "category":"Bagels",
            "type":"Food & Drink"
        },
        {
            "category":"Donuts",
            "type":"Food & Drink"
        }
    ],
    "sg:menulink":"http://www.allmenus.com/ga/norcross/130409-dunkin-donuts/menu/",
    "sg:phone":"+1 678 966 0909",
    "sg:postcode":"30092",
    "sg:province":"GA",
    "sg:tags":[
        "american",
        "diner",
        "pastry"
    ],
    "wof:name":"Dunkin' Donuts",
    "wof:placetype":"venue"
},
  "geometry": {"coordinates":[-84.214153,33.985666],"type":"Point"}
}