{
  "type": "Feature",
  "properties": {
    "addr:full":"201 Dental Dr Warner Robins GA 31088",
    "addr:postcode":"31088",
    "iso:country":"US",
    "sg:address":"201 Dental Dr",
    "sg:city":"Warner Robins",
    "sg:classifiers":[
        {
            "category":"Health Services",
            "subcategory":"Doctor",
            "type":"Services"
        }
    ],
    "sg:phone":"+1 478 328 9555",
    "sg:postcode":"31088",
    "sg:province":"GA",
    "sg:tags":[
        "dentist"
    ],
    "wof:name":"Nicholas Golubow DMD Ms",
    "wof:placetype":"venue"
},
  "geometry": {"coordinates":[-83.638879,32.596545],"type":"Point"}
}