{
  "type": "Feature",
  "properties": {
    "addr:full":"7417 Madison Dr Atlanta GA 30346",
    "addr:housenumber":"7417",
    "addr:postcode":"30346",
    "addr:street":"Madison Dr",
    "iso:country":"US",
    "sg:address":"7417 Madison Dr",
    "sg:city":"Atlanta",
    "sg:classifiers":[
        {
            "category":"Manufacturing",
            "subcategory":"Tools & Machinery",
            "type":"Manufacturing & Wholesale Goods"
        }
    ],
    "sg:phone":"+1 404 816 0777",
    "sg:postcode":"30346",
    "sg:province":"GA",
    "sg:tags":[
        "environmental",
        "product",
        "mfg"
    ],
    "wof:name":"Enviromedix LLC",
    "wof:placetype":"venue"
},
  "geometry": {"coordinates":[-84.333657,33.929907],"type":"Point"}
}