{
  "type": "Feature",
  "properties": {
    "addr:full":"565 Trailside Ct Roswell GA 30075",
    "addr:housenumber":"565",
    "addr:postcode":"30075",
    "addr:street":"Trailside Ct",
    "iso:country":"US",
    "sg:address":"565 Trailside Ct",
    "sg:city":"Roswell",
    "sg:classifiers":[
        {
            "category":"Professional",
            "subcategory":"Business Services",
            "type":"Services"
        }
    ],
    "sg:phone":"+1 770 518 6275",
    "sg:postcode":"30075",
    "sg:province":"GA",
    "wof:name":"Kepler & Associates",
    "wof:placetype":"venue"
},
  "geometry": {"coordinates":[-84.40709699999999,34.072631],"type":"Point"}
}