{
  "type": "Feature",
  "properties": {
    "iso:country":"US",
    "sg:address":"4418 Branchwood Dr",
    "sg:city":"Augusta",
    "sg:classifiers":[
        {
            "category":"Home & Garden",
            "subcategory":"Carpets & Floor Coverings",
            "type":"Retail Goods"
        }
    ],
    "sg:phone":"+1 706 860 4595",
    "sg:postcode":"30907",
    "sg:province":"GA",
    "sg:tags":[
        "distributor",
        "rug",
        "manufacturer"
    ],
    "wof:name":"Greg Jones Carpet Cleanin",
    "wof:placetype":"venue"
},
  "geometry": {"coordinates":[-82.136606,33.511534],"type":"Point"}
}