{
  "type": "Feature",
  "properties": {
    "addr:full":"1895 Boulderview Dr SE Atlanta GA 30316",
    "addr:housenumber":"1895",
    "addr:postcode":"30316",
    "addr:street":"Boulderview Dr Se",
    "iso:country":"US",
    "sg:address":"1895 Boulderview Dr SE",
    "sg:city":"Atlanta",
    "sg:classifiers":[
        {
            "category":"Food & Beverages",
            "subcategory":"Groceries & Convenience Stores",
            "type":"Retail Goods"
        }
    ],
    "sg:phone":"+1 404 243 9687",
    "sg:postcode":"30316",
    "sg:province":"GA",
    "wof:name":"Phashuns 4 Less",
    "wof:placetype":"venue"
},
  "geometry": {"coordinates":[-84.311971,33.704192],"type":"Point"}
}