{
  "type": "Feature",
  "properties": {
    "iso:country":"US",
    "sg:address":"100 Lakeshore Dr NE",
    "sg:city":"Atlanta",
    "sg:classifiers":[
        {
            "category":"Real Estate",
            "subcategory":"Real Estate Agent",
            "type":"Services"
        }
    ],
    "sg:phone":"+1 770 457 1800",
    "sg:postcode":"30324",
    "sg:province":"GA",
    "sg:tags":[
        "apartment",
        "complex"
    ],
    "wof:name":"Metzger & Company Inc",
    "wof:placetype":"venue"
},
  "geometry": {"coordinates":[-84.365188,33.816013],"type":"Point"}
}