{
  "type": "Feature",
  "properties": {
    "addr:full":"1550 Wire Bridge Rd Watkinsville GA 30677",
    "addr:housenumber":"1550",
    "addr:postcode":"30677",
    "addr:street":"Wire Bridge Rd",
    "iso:country":"US",
    "sg:address":"1550 Wire Bridge Rd",
    "sg:city":"Watkinsville",
    "sg:classifiers":[
        {
            "category":"Farming",
            "subcategory":"Livestock Farm",
            "type":"Manufacturing & Wholesale Goods"
        }
    ],
    "sg:phone":"+1 706 769 7278",
    "sg:postcode":"30677",
    "sg:province":"GA",
    "sg:tags":[
        "ranch"
    ],
    "wof:name":"B Hansford",
    "wof:placetype":"venue"
},
  "geometry": {"coordinates":[-83.293556,33.796848],"type":"Point"}
}