{
  "type": "Feature",
  "properties": {
    "iso:country":"US",
    "sg:address":"155 Cherokee Pl",
    "sg:city":"Cartersville",
    "sg:classifiers":[
        {
            "category":"Shopping",
            "subcategory":"Stationery & Office Supplies",
            "type":"Retail Goods"
        }
    ],
    "sg:phone":"+1 770 386 9100",
    "sg:postcode":"30121",
    "sg:province":"GA",
    "wof:name":"Staples The Office Superstore",
    "wof:placetype":"venue"
},
  "geometry": {"coordinates":[-84.782702,34.17258],"type":"Point"}
}