{
  "type": "Feature",
  "properties": {
    "iso:country":"US",
    "sg:address":"80 Stratford Pl NE",
    "sg:city":"Atlanta",
    "sg:classifiers":[
        {
            "category":"Retail",
            "subcategory":"Portrait Studio",
            "type":"Services"
        }
    ],
    "sg:phone":"+1 404 365 9622",
    "sg:postcode":"30342",
    "sg:province":"GA",
    "sg:tags":[
        "photographer",
        "lawyer"
    ],
    "wof:name":"Jackie Lee Lawing",
    "wof:placetype":"venue"
},
  "geometry": {"coordinates":[-84.35830799999999,33.867509],"type":"Point"}
}