{
  "type": "Feature",
  "properties": {
    "iso:country":"US",
    "sg:address":"3420 Oakcliff Road",
    "sg:city":"Atlanta",
    "sg:classifiers":[
        {
            "category":"Shopping",
            "subcategory":"Shoes",
            "type":"Retail Goods"
        }
    ],
    "sg:phone":"+1 770 220 1811",
    "sg:postcode":"30340",
    "sg:province":"GA",
    "sg:tags":[
        "store"
    ],
    "wof:name":"Max Trading",
    "wof:placetype":"venue"
},
  "geometry": {"coordinates":[-84.254452,33.905369],"type":"Point"}
}