{
  "type": "Feature",
  "properties": {
    "addr:full":"6262 Skidaway Rd Savannah GA 31406",
    "addr:housenumber":"6262",
    "addr:postcode":"31406",
    "addr:street":"Skidaway Rd",
    "iso:country":"US",
    "sg:address":"6262 Skidaway Rd",
    "sg:city":"Savannah",
    "sg:classifiers":[
        {
            "category":"Recreation",
            "type":"Entertainment"
        }
    ],
    "sg:phone":"+1 912 351 3850",
    "sg:postcode":"31406",
    "sg:province":"GA",
    "sg:tags":[
        "tennis",
        "court"
    ],
    "wof:name":"Bacon Park Tennis Courts",
    "wof:placetype":"venue"
},
  "geometry": {"coordinates":[-81.078424,32.012336],"type":"Point"}
}