{
  "type": "Feature",
  "properties": {
    "addr:full":"718 Hwy 3 N Hampton GA 30228",
    "addr:housenumber":"718",
    "addr:postcode":"30228",
    "addr:street":"Hwy 3 N",
    "iso:country":"US",
    "sg:address":"718 Hwy 3 N",
    "sg:city":"Hampton",
    "sg:classifiers":[
        {
            "category":"Food & Beverages",
            "subcategory":"Fruits & Vegetables",
            "type":"Retail Goods"
        }
    ],
    "sg:phone":"+1 770 707 0044",
    "sg:postcode":"30228",
    "sg:province":"GA",
    "sg:tags":[
        "produce"
    ],
    "wof:name":"Granny's Produce",
    "wof:placetype":"venue"
},
  "geometry": {"coordinates":[-84.284942,33.424302],"type":"Point"}
}