{
  "type": "Feature",
  "properties": {
    "addr:full":"1311 S Harris St Sandersville GA 31082",
    "addr:housenumber":"1311",
    "addr:postcode":"31082",
    "addr:street":"S Harris St",
    "iso:country":"US",
    "sg:address":"1311 S Harris St",
    "sg:city":"Sandersville",
    "sg:classifiers":[
        {
            "category":"Autos & Motor Vehicles",
            "subcategory":"Automobile Sales",
            "type":"Retail Goods"
        }
    ],
    "sg:phone":"+1 478 552 5143",
    "sg:postcode":"31082",
    "sg:province":"GA",
    "sg:tags":[
        "car",
        "dealer"
    ],
    "wof:name":"Childre Chevrolet-Olds-Pontiac",
    "wof:placetype":"venue"
},
  "geometry": {"coordinates":[-82.809262,32.956273],"type":"Point"}
}