{
  "type": "Feature",
  "properties": {
    "iso:country":"US",
    "sg:address":"4013 Chastain Rd",
    "sg:city":"Blairsville",
    "sg:classifiers":[
        {
            "category":"Home & Garden",
            "subcategory":"Building Materials",
            "type":"Retail Goods"
        }
    ],
    "sg:phone":"+1 706 745 4355",
    "sg:postcode":"30514",
    "sg:province":"GA",
    "sg:tags":[
        "glass",
        "window",
        "plate"
    ],
    "wof:name":"Blairsville Glass & Aluminum",
    "wof:placetype":"venue"
},
  "geometry": {"coordinates":[-84.032951,34.889242],"type":"Point"}
}