{
  "type": "Feature",
  "properties": {
    "iso:country":"US",
    "sg:address":"1531 Industrial Dr",
    "sg:city":"Griffin",
    "sg:classifiers":[
        {
            "category":"Wholesale",
            "subcategory":"Scrap",
            "type":"Manufacturing & Wholesale Goods"
        }
    ],
    "sg:phone":"+1 770 412 2325",
    "sg:postcode":"30224",
    "sg:province":"GA",
    "sg:tags":[
        "synthetic",
        "wool",
        "waste"
    ],
    "wof:name":"Textile Fibers & By-Products",
    "wof:placetype":"venue"
},
  "geometry": {"coordinates":[-84.289277,33.220075],"type":"Point"}
}