{
  "type": "Feature",
  "properties": {
    "addr:full":"5221 4th Ave Eastman GA 31023",
    "addr:housenumber":"5221",
    "addr:postcode":"31023",
    "addr:street":"4Th Ave",
    "iso:country":"US",
    "sg:address":"5221 4th Ave",
    "sg:city":"Eastman",
    "sg:classifiers":[
        {
            "category":"Insurance",
            "subcategory":"Insurance Agent",
            "type":"Services"
        }
    ],
    "sg:phone":"+1 478 374 4855",
    "sg:postcode":"31023",
    "sg:province":"GA",
    "wof:name":"Charles Robinson Insurance",
    "wof:placetype":"venue"
},
  "geometry": {"coordinates":[-83.175104,32.198485],"type":"Point"}
}