{
  "type": "Feature",
  "properties": {
    "iso:country":"US",
    "sg:address":"1051 Hayes Industrial Dr",
    "sg:city":"Marietta",
    "sg:classifiers":[
        {
            "category":"Building & Trades",
            "subcategory":"Landscaping Services",
            "type":"Services"
        }
    ],
    "sg:phone":"+1 770 421 8000",
    "sg:postcode":"30062",
    "sg:province":"GA",
    "sg:website":"www.trugreen.com",
    "wof:name":"Trugreen",
    "wof:placetype":"venue"
},
  "geometry": {"coordinates":[-84.54294,33.977132],"type":"Point"}
}