{
  "type": "Feature",
  "properties": {
    "iso:country":"US",
    "sg:address":"7085 Maddox Rd",
    "sg:city":"Lithonia",
    "sg:classifiers":[
        {
            "category":"Building & Trades",
            "subcategory":"Landscaping Services",
            "type":"Services"
        }
    ],
    "sg:phone":"+1 770 482 7031",
    "sg:postcode":"30058",
    "sg:province":"GA",
    "sg:tags":[
        "landscape"
    ],
    "wof:name":"Key Total Landscaping",
    "wof:placetype":"venue"
},
  "geometry": {"coordinates":[-84.099041,33.737676],"type":"Point"}
}