{
  "type": "Feature",
  "properties": {
    "addr:full":"153 Charles Craven Rd Carrollton GA 30117",
    "addr:housenumber":"153",
    "addr:postcode":"30117",
    "addr:street":"Charles Craven Rd",
    "iso:country":"US",
    "sg:address":"153 Charles Craven Rd",
    "sg:city":"Carrollton",
    "sg:classifiers":[
        {
            "category":"Building & Trades",
            "subcategory":"Plumbing",
            "type":"Services"
        }
    ],
    "sg:phone":"+1 770 834 0176",
    "sg:postcode":"30117",
    "sg:province":"GA",
    "sg:tags":[
        "contractor"
    ],
    "wof:name":"Jiles-Turner Septic Tank Svc",
    "wof:placetype":"venue"
},
  "geometry": {"coordinates":[-85.180635,33.605193],"type":"Point"}
}