{
  "type": "Feature",
  "properties": {
    "iso:country":"US",
    "sg:address":"2301 Godby Rd",
    "sg:city":"Atlanta",
    "sg:classifiers":[
        {
            "category":"Health Services",
            "subcategory":"Clinic",
            "type":"Services"
        }
    ],
    "sg:phone":"+1 404 684 9518",
    "sg:postcode":"30349",
    "sg:province":"GA",
    "sg:tags":[
        "substance",
        "abuse"
    ],
    "wof:name":"Another Chance of Atlanta Inc",
    "wof:placetype":"venue"
},
  "geometry": {"coordinates":[-84.463334,33.616316],"type":"Point"}
}