{
  "type": "Feature",
  "properties": {
    "addr:full":"5635 Lenox Park Pl Buford GA 30518",
    "addr:housenumber":"5635",
    "addr:postcode":"30518",
    "addr:street":"Lenox Park Pl",
    "iso:country":"US",
    "sg:address":"5635 Lenox Park Pl",
    "sg:city":"Buford",
    "sg:classifiers":[
        {
            "category":"Personal",
            "subcategory":"Beauty Salon",
            "type":"Services"
        }
    ],
    "sg:phone":"+1 770 271 3002",
    "sg:postcode":"30518",
    "sg:province":"GA",
    "sg:tags":[
        "shop"
    ],
    "wof:name":"Hair Conductors Inc",
    "wof:placetype":"venue"
},
  "geometry": {"coordinates":[-84.075658,34.106568],"type":"Point"}
}