{
  "type": "Feature",
  "properties": {
    "iso:country":"US",
    "sg:address":"5910 Shannon Dr",
    "sg:city":"Cumming",
    "sg:classifiers":[
        {
            "category":"Shopping",
            "subcategory":"Catalog Store",
            "type":"Retail Goods"
        }
    ],
    "sg:phone":"+1 770 205 8430",
    "sg:postcode":"30040",
    "sg:province":"GA",
    "sg:tags":[
        "e"
    ],
    "wof:name":"Jadahost",
    "wof:placetype":"venue"
},
  "geometry": {"coordinates":[-84.157021,34.283543],"type":"Point"}
}