{
  "type": "Feature",
  "properties": {
    "addr:full":"10516 Alpharetta Hwy Roswell GA 30076",
    "addr:housenumber":"10516",
    "addr:postcode":"30076",
    "addr:street":"Alpharetta Hwy",
    "iso:country":"US",
    "sg:address":"10516 Alpharetta Hwy",
    "sg:city":"Roswell",
    "sg:classifiers":[
        {
            "category":"Restaurant",
            "type":"Food & Drink"
        }
    ],
    "sg:menulink":"http://www.allmenus.com/ga/roswell-alpharetta/171492-ci-cis-pizza/menu/",
    "sg:phone":"+1 770 645 1550",
    "sg:postcode":"30076",
    "sg:province":"GA",
    "sg:tags":[
        "american",
        "pizza"
    ],
    "wof:name":"Ci Ci's Pizza",
    "wof:placetype":"venue"
},
  "geometry": {"coordinates":[-84.343165,34.038333],"type":"Point"}
}