{
  "type": "Feature",
  "properties": {
    "addr:full":"3378 White Oak Rd Thomson GA 30824",
    "addr:housenumber":"3378",
    "addr:postcode":"30824",
    "addr:street":"White Oak Rd",
    "iso:country":"US",
    "sg:address":"3378 White Oak Rd",
    "sg:city":"Thomson",
    "sg:classifiers":[
        {
            "category":"Autos & Motor Vehicles",
            "subcategory":"Automobile Sales",
            "type":"Retail Goods"
        }
    ],
    "sg:phone":"+1 706 595 5937",
    "sg:postcode":"30824",
    "sg:province":"GA",
    "sg:tags":[
        "car",
        "dealer"
    ],
    "wof:name":"Swint Enterprises Auto Sales",
    "wof:placetype":"venue"
},
  "geometry": {"coordinates":[-82.40625300000001,33.490621],"type":"Point"}
}