{
  "type": "Feature",
  "properties": {
    "addr:full":"5356 N Henry Blvd Stockbridge GA 30281",
    "addr:housenumber":"5356",
    "addr:postcode":"30281",
    "addr:street":"N Henry Blvd",
    "iso:country":"US",
    "sg:address":"5356 N Henry Blvd",
    "sg:city":"Stockbridge",
    "sg:classifiers":[
        {
            "category":"Social Services",
            "subcategory":"Child Care",
            "type":"Services"
        }
    ],
    "sg:phone":"+1 770 474 6188",
    "sg:postcode":"30281",
    "sg:province":"GA",
    "sg:tags":[
        "day"
    ],
    "wof:name":"Childrens College Day CA",
    "wof:placetype":"venue"
},
  "geometry": {"coordinates":[-84.25098199999999,33.547461],"type":"Point"}
}