{
  "type": "Feature",
  "properties": {
    "addr:full":"4328 Dogwood Trce Decatur GA 30034",
    "addr:housenumber":"4328",
    "addr:postcode":"30034",
    "addr:street":"Dogwood Trce",
    "iso:country":"US",
    "sg:address":"4328 Dogwood Trce",
    "sg:city":"Decatur",
    "sg:classifiers":[
        {
            "category":"Wholesale",
            "subcategory":"Painting Supplies",
            "type":"Manufacturing & Wholesale Goods"
        }
    ],
    "sg:phone":"+1 770 593 3212",
    "sg:postcode":"30034",
    "sg:province":"GA",
    "sg:tags":[
        "goods-wholesale",
        "art",
        "manufacturer"
    ],
    "wof:name":"Jerry Johnson Portraits",
    "wof:placetype":"venue"
},
  "geometry": {"coordinates":[-84.212171,33.682762],"type":"Point"}
}