{
  "type": "Feature",
  "properties": {
    "iso:country":"US",
    "sg:address":"4255 Smoke Creek Pkwy",
    "sg:city":"Snellville",
    "sg:classifiers":[
        {
            "category":"Building & Trades",
            "subcategory":"Landscaping Services",
            "type":"Services"
        }
    ],
    "sg:phone":"+1 770 972 8102",
    "sg:postcode":"30039",
    "sg:province":"GA",
    "sg:tags":[
        "towing",
        "vehicle"
    ],
    "wof:name":"Jeff and Sons Towing",
    "wof:placetype":"venue"
},
  "geometry": {"coordinates":[-84.053822,33.774926],"type":"Point"}
}