{
  "type": "Feature",
  "properties": {
    "addr:full":"130 N Sage St Toccoa GA 30577",
    "addr:housenumber":"130",
    "addr:postcode":"30577",
    "addr:street":"N Sage St",
    "iso:country":"US",
    "sg:address":"130 N Sage St",
    "sg:city":"Toccoa",
    "sg:classifiers":[
        {
            "category":"Education",
            "subcategory":"Special Training",
            "type":"Public Place"
        }
    ],
    "sg:phone":"+1 706 886 9499",
    "sg:postcode":"30577",
    "sg:province":"GA",
    "sg:tags":[
        "instruction",
        "driving"
    ],
    "wof:name":"Browning's Driver Improvement",
    "wof:placetype":"venue"
},
  "geometry": {"coordinates":[-83.329911,34.579199],"type":"Point"}
}