{
  "type": "Feature",
  "properties": {
    "addr:full":"2515 Touchton Rd Valdosta GA 31601",
    "addr:housenumber":"2515",
    "addr:postcode":"31601",
    "addr:street":"Touchton Rd",
    "iso:country":"US",
    "sg:address":"2515 Touchton Rd",
    "sg:city":"Valdosta",
    "sg:classifiers":[
        {
            "category":"Retail",
            "subcategory":"Portrait Studio",
            "type":"Services"
        }
    ],
    "sg:phone":"+1 229 259 9696",
    "sg:postcode":"31601",
    "sg:province":"GA",
    "sg:tags":[
        "photo"
    ],
    "wof:name":"Lance Whitmore Photography",
    "wof:placetype":"venue"
},
  "geometry": {"coordinates":[-83.26846999999999,30.761481],"type":"Point"}
}