{
  "type": "Feature",
  "properties": {
    "iso:country":"US",
    "sg:address":"916 Birchwood Ct",
    "sg:city":"Mc Donough",
    "sg:classifiers":[
        {
            "category":"Building & Trades",
            "subcategory":"Landscaping Services",
            "type":"Services"
        }
    ],
    "sg:phone":"+1 678 432 8626",
    "sg:postcode":"30253",
    "sg:province":"GA",
    "sg:tags":[
        "landscape"
    ],
    "wof:name":"Front To Back Ldscp & Design",
    "wof:placetype":"venue"
},
  "geometry": {"coordinates":[-84.18859,33.469986],"type":"Point"}
}