{
  "type": "Feature",
  "properties": {
    "iso:country":"US",
    "sg:address":"2109 Moreland Ave SE",
    "sg:city":"Atlanta",
    "sg:classifiers":[
        {
            "category":"Building & Trades",
            "subcategory":"Locksmith",
            "type":"Services"
        }
    ],
    "sg:phone":"+1 678 845 9488",
    "sg:postcode":"30315",
    "sg:province":"GA",
    "sg:tags":[
        "key"
    ],
    "wof:name":"All Day All Night Emergency A Locksmith",
    "wof:placetype":"venue"
},
  "geometry": {"coordinates":[-84.349805,33.696679],"type":"Point"}
}