{
  "type": "Feature",
  "properties": {
    "addr:full":"2175 W County Line Rd Douglasville GA 30135",
    "addr:housenumber":"2175",
    "addr:postcode":"30135",
    "addr:street":"W County Line Rd",
    "iso:country":"US",
    "sg:address":"2175 W County Line Rd",
    "sg:city":"Douglasville",
    "sg:classifiers":[
        {
            "category":"Travel",
            "subcategory":"Travel Agent",
            "type":"Entertainment"
        }
    ],
    "sg:phone":"+1 678 838 1359",
    "sg:postcode":"30135",
    "sg:province":"GA",
    "sg:tags":[
        "agency",
        "bureau"
    ],
    "wof:name":"Global Shipping & Travel Inc",
    "wof:placetype":"venue"
},
  "geometry": {"coordinates":[-84.69342899999999,33.748393],"type":"Point"}
}