{
  "type": "Feature",
  "properties": {
    "iso:country":"US",
    "sg:address":"106 N Green St",
    "sg:city":"Thomaston",
    "sg:classifiers":[
        {
            "category":"Shopping",
            "subcategory":"Luggage & Leather Goods",
            "type":"Retail Goods"
        }
    ],
    "sg:phone":"+1 706 647 6436",
    "sg:postcode":"30286",
    "sg:province":"GA",
    "sg:tags":[
        "industrial",
        "shoe",
        "supply"
    ],
    "wof:name":"Edens Best Herbs",
    "wof:placetype":"venue"
},
  "geometry": {"coordinates":[-84.328197,32.888013],"type":"Point"}
}