{
  "type": "Feature",
  "properties": {
    "addr:full":"902 E 70th St Savannah GA 31405",
    "addr:housenumber":"902",
    "addr:postcode":"31405",
    "addr:street":"E 70Th St",
    "iso:country":"US",
    "sg:address":"902 E 70th St",
    "sg:city":"Savannah",
    "sg:classifiers":[
        {
            "category":"Home & Garden",
            "subcategory":"Home Furnishings",
            "type":"Retail Goods"
        }
    ],
    "sg:phone":"+1 912 355 4896",
    "sg:postcode":"31405",
    "sg:province":"GA",
    "wof:name":"Rackleaves",
    "wof:placetype":"venue"
},
  "geometry": {"coordinates":[-81.093847,32.026559],"type":"Point"}
}