{
  "type": "Feature",
  "properties": {
    "iso:country":"US",
    "sg:address":"85 Johnson Rd",
    "sg:city":"Suwanee",
    "sg:classifiers":[
        {
            "category":"Professional",
            "type":"Services"
        }
    ],
    "sg:phone":"+1 678 546 6840",
    "sg:postcode":"30024",
    "sg:province":"GA",
    "wof:name":"Ashleigh Walk",
    "wof:placetype":"venue"
},
  "geometry": {"coordinates":[-84.08823099999999,34.099673],"type":"Point"}
}