{
  "type": "Feature",
  "properties": {
    "iso:country":"US",
    "sg:address":"3939 McElroy Rd",
    "sg:city":"Atlanta",
    "sg:classifiers":[
        {
            "category":"Building & Trades",
            "subcategory":"Locksmith",
            "type":"Services"
        }
    ],
    "sg:phone":"+1 866 822 2501",
    "sg:postcode":"30340",
    "sg:province":"GA",
    "sg:tags":[
        "key"
    ],
    "wof:name":"1 24 Hour Emergency Locksmith",
    "wof:placetype":"venue"
},
  "geometry": {"coordinates":[-84.266718,33.909183],"type":"Point"}
}