{
  "type": "Feature",
  "properties": {
    "addr:full":"100 S Hampton Rd Hampton GA 30228",
    "addr:housenumber":"100",
    "addr:postcode":"30228",
    "addr:street":"S Hampton Rd",
    "iso:country":"US",
    "sg:address":"100 S Hampton Rd",
    "sg:city":"Hampton",
    "sg:classifiers":[
        {
            "category":"Building & Trades",
            "subcategory":"Construction",
            "type":"Services"
        }
    ],
    "sg:phone":"+1 770 946 4445",
    "sg:postcode":"30228",
    "sg:province":"GA",
    "sg:tags":[
        "painter"
    ],
    "wof:name":"Billy Duffey",
    "wof:placetype":"venue"
},
  "geometry": {"coordinates":[-84.268213,33.380896],"type":"Point"}
}