{
  "type": "Feature",
  "properties": {
    "iso:country":"US",
    "sg:address":"900 W Oglethorpe Blvd",
    "sg:city":"Albany",
    "sg:classifiers":[
        {
            "category":"Autos & Motor Vehicles",
            "subcategory":"Automobile Sales",
            "type":"Retail Goods"
        }
    ],
    "sg:phone":"+1 229 432 2604",
    "sg:postcode":"31701",
    "sg:province":"GA",
    "sg:tags":[
        "dealers-used",
        "used",
        "cars-wholesale",
        "car"
    ],
    "wof:name":"County Motors Used Cars",
    "wof:placetype":"venue"
},
  "geometry": {"coordinates":[-84.17066199999999,31.575319],"type":"Point"}
}