{
  "type": "Feature",
  "properties": {
    "iso:country":"US",
    "sg:address":"117 Picket Row",
    "sg:city":"Savannah",
    "sg:classifiers":[
        {
            "category":"Wholesale",
            "subcategory":"Durable Goods & Equipment",
            "type":"Manufacturing & Wholesale Goods"
        }
    ],
    "sg:phone":"+1 912 898 1120",
    "sg:postcode":"31410",
    "sg:province":"GA",
    "sg:tags":[
        "surveillance"
    ],
    "sg:website":"www.childview.com",
    "wof:name":"CHILDVIEW.COM",
    "wof:placetype":"venue"
},
  "geometry": {"coordinates":[-80.960838,32.018695],"type":"Point"}
}