{
  "type": "Feature",
  "properties": {
    "iso:country":"US",
    "sg:address":"3373 Cleveland Hwy",
    "sg:city":"Gainesville",
    "sg:classifiers":[
        {
            "category":"Building & Trades",
            "subcategory":"Construction",
            "type":"Services"
        }
    ],
    "sg:phone":"+1 770 536 4500",
    "sg:postcode":"30506",
    "sg:province":"GA",
    "sg:tags":[
        "contractor"
    ],
    "wof:name":"J L Construction Inc",
    "wof:placetype":"venue"
},
  "geometry": {"coordinates":[-83.81005500000001,34.377267],"type":"Point"}
}