{
  "type": "Feature",
  "properties": {
    "addr:full":"733 Simpson St NW Atlanta GA 30314",
    "addr:housenumber":"733",
    "addr:postcode":"30314",
    "addr:street":"Simpson St Nw",
    "iso:country":"US",
    "sg:address":"733 Simpson St NW",
    "sg:city":"Atlanta",
    "sg:classifiers":[
        {
            "category":"Restaurant",
            "type":"Food & Drink"
        }
    ],
    "sg:menulink":"http://www.allmenus.com/ga/atlanta/17879-china-express/menu/",
    "sg:phone":"+1 404 827 0008",
    "sg:postcode":"30314",
    "sg:province":"GA",
    "sg:tags":[
        "asian",
        "chinese"
    ],
    "wof:name":"China Express",
    "wof:placetype":"venue"
},
  "geometry": {"coordinates":[-84.411249,33.763442],"type":"Point"}
}