{
  "type": "Feature",
  "properties": {
    "addr:full":"103 Simmons Ave Saint Simons Island GA 31522",
    "addr:housenumber":"103",
    "addr:postcode":"31522",
    "addr:street":"Simmons Ave",
    "iso:country":"US",
    "sg:address":"103 Simmons Ave",
    "sg:city":"Saint Simons Island",
    "sg:classifiers":[
        {
            "category":"Real Estate",
            "subcategory":"Real Estate Agent",
            "type":"Services"
        }
    ],
    "sg:phone":"+1 912 638 2742",
    "sg:postcode":"31522",
    "sg:province":"GA",
    "sg:tags":[
        "manager",
        "broker"
    ],
    "wof:name":"Hardwick Realty",
    "wof:placetype":"venue"
},
  "geometry": {"coordinates":[-81.383647,31.156014],"type":"Point"}
}