{
  "type": "Feature",
  "properties": {
    "iso:country":"US",
    "sg:address":"106 E 16th St",
    "sg:city":"Alma",
    "sg:classifiers":[
        {
            "category":"Autos & Motor Vehicles",
            "subcategory":"Auto Supplies",
            "type":"Retail Goods"
        }
    ],
    "sg:phone":"+1 912 632 7243",
    "sg:postcode":"31510",
    "sg:province":"GA",
    "sg:tags":[
        "automobile",
        "parts"
    ],
    "wof:name":"Alma Auto Sure",
    "wof:placetype":"venue"
},
  "geometry": {"coordinates":[-82.46263399999999,31.539294],"type":"Point"}
}