{
  "type": "Feature",
  "properties": {
    "addr:full":"2071 Kinsmon Dr Marietta GA 30062",
    "addr:housenumber":"2071",
    "addr:postcode":"30062",
    "addr:street":"Kinsmon Dr",
    "iso:country":"US",
    "sg:address":"2071 Kinsmon Dr",
    "sg:city":"Marietta",
    "sg:classifiers":[
        {
            "category":"Wholesale",
            "subcategory":"Office Equipment",
            "type":"Manufacturing & Wholesale Goods"
        }
    ],
    "sg:phone":"+1 770 640 8484",
    "sg:postcode":"30062",
    "sg:province":"GA",
    "sg:tags":[
        "packaging",
        "machinery"
    ],
    "sg:website":"http://www.atlascopco.com",
    "wof:name":"Atlas Copco Compressors",
    "wof:placetype":"venue"
},
  "geometry": {"coordinates":[-84.416647,33.993789],"type":"Point"}
}