{
  "type": "Feature",
  "properties": {
    "addr:full":"5886 Wendy Bagwell Pkwy Ste 303 Hiram GA 30141",
    "addr:housenumber":"5886",
    "addr:postcode":"30141",
    "addr:street":"Wendy Bagwell Pkwy Ste 303",
    "iso:country":"US",
    "sg:address":"5886 Wendy Bagwell Pkwy Ste 303",
    "sg:city":"Hiram",
    "sg:classifiers":[
        {
            "category":"Banks & Credit Unions",
            "subcategory":"Financial Services",
            "type":"Services"
        }
    ],
    "sg:phone":"+1 770 222 3415",
    "sg:postcode":"30141",
    "sg:province":"GA",
    "sg:tags":[
        "broker",
        "mortgage"
    ],
    "sg:website":"www.loansfast.com",
    "wof:name":"American General Financial Services",
    "wof:placetype":"venue"
},
  "geometry": {"coordinates":[-84.730722,33.883473],"type":"Point"}
}