{
  "type": "Feature",
  "properties": {
    "iso:country":"US",
    "sg:address":"689 Medical Park Ln",
    "sg:city":"Gainesville",
    "sg:classifiers":[
        {
            "category":"Health Services",
            "subcategory":"Doctor",
            "type":"Services"
        }
    ],
    "sg:phone":"+1 770 534 4565",
    "sg:postcode":"30501",
    "sg:province":"GA",
    "wof:name":"Thornton Michael DMD PC",
    "wof:placetype":"venue"
},
  "geometry": {"coordinates":[-83.79921,34.320677],"type":"Point"}
}