{
  "type": "Feature",
  "properties": {
    "iso:country":"US",
    "sg:address":"3729 Martha Berry Hwy",
    "sg:city":"Rome",
    "sg:classifiers":[
        {
            "category":"Building & Trades",
            "subcategory":"Construction",
            "type":"Services"
        }
    ],
    "sg:phone":"+1 706 624 1590",
    "sg:postcode":"30165",
    "sg:province":"GA",
    "sg:tags":[
        "fire",
        "restoration",
        "damage"
    ],
    "wof:name":"Servpro Of Dalton/Calhoun",
    "wof:placetype":"venue"
},
  "geometry": {"coordinates":[-85.17232799999999,34.329324],"type":"Point"}
}