{
  "type": "Feature",
  "properties": {
    "addr:full":"243 Clements Rd Americus GA 31709",
    "addr:housenumber":"243",
    "addr:postcode":"31709",
    "addr:street":"Clements Rd",
    "iso:country":"US",
    "sg:address":"243 Clements Rd",
    "sg:city":"Americus",
    "sg:classifiers":[
        {
            "category":"Building & Trades",
            "subcategory":"Plumbing",
            "type":"Services"
        }
    ],
    "sg:phone":"+1 229 928 7481",
    "sg:postcode":"31709",
    "sg:province":"GA",
    "sg:tags":[
        "conditioning",
        "air",
        "system",
        "contractor"
    ],
    "wof:name":"Maximum Heating & Air Inc",
    "wof:placetype":"venue"
},
  "geometry": {"coordinates":[-84.065163,32.093872],"type":"Point"}
}