{
  "type": "Feature",
  "properties": {
    "iso:country":"US",
    "sg:address":"416 1st St SW",
    "sg:city":"Cairo",
    "sg:classifiers":[
        {
            "category":"Professional",
            "subcategory":"Accounting & Tax Preparation",
            "type":"Services"
        }
    ],
    "sg:phone":"+1 229 377 8334",
    "sg:postcode":"39828",
    "sg:province":"GA",
    "sg:tags":[
        "return",
        "billing"
    ],
    "wof:name":"Tax Express",
    "wof:placetype":"venue"
},
  "geometry": {"coordinates":[-84.21028,30.872409],"type":"Point"}
}