{
  "type": "Feature",
  "properties": {
    "addr:full":"7483 State Rte 85 Riverdale GA 30274",
    "addr:housenumber":"7483",
    "addr:postcode":"30274",
    "addr:street":"State Rte 85",
    "iso:country":"US",
    "sg:address":"7483 State Rte 85",
    "sg:city":"Riverdale",
    "sg:classifiers":[
        {
            "category":"Home & Garden",
            "subcategory":"Building Materials",
            "type":"Retail Goods"
        }
    ],
    "sg:phone":"+1 770 907 9657",
    "sg:postcode":"30274",
    "sg:province":"GA",
    "sg:tags":[
        "glass",
        "window",
        "plate"
    ],
    "wof:name":"Binswanger Glass Co",
    "wof:placetype":"venue"
},
  "geometry": {"coordinates":[-84.414475,33.550745],"type":"Point"}
}