{
  "type": "Feature",
  "properties": {
    "addr:full":"2910 Kipling Dr Augusta GA 30909",
    "addr:housenumber":"2910",
    "addr:postcode":"30909",
    "addr:street":"Kipling Dr",
    "iso:country":"US",
    "sg:address":"2910 Kipling Dr",
    "sg:city":"Augusta",
    "sg:classifiers":[
        {
            "category":"Professional",
            "subcategory":"Management & Consulting",
            "type":"Services"
        }
    ],
    "sg:phone":"+1 706 733 1228",
    "sg:postcode":"30909",
    "sg:province":"GA",
    "sg:tags":[
        "consultant",
        "business"
    ],
    "wof:name":"E Z Net Commerce",
    "wof:placetype":"venue"
},
  "geometry": {"coordinates":[-82.04403600000001,33.498647],"type":"Point"}
}