{
  "type": "Feature",
  "properties": {
    "iso:country":"US",
    "sg:address":"3553 Dunwoody Club Dr",
    "sg:city":"Atlanta",
    "sg:classifiers":[
        {
            "category":"Professional",
            "subcategory":"Printing & Photocopies",
            "type":"Services"
        }
    ],
    "sg:phone":"+1 770 671 9371",
    "sg:postcode":"30350",
    "sg:province":"GA",
    "sg:tags":[
        "lithographer"
    ],
    "wof:name":"Flowers Printing Services",
    "wof:placetype":"venue"
},
  "geometry": {"coordinates":[-84.328436,33.968154],"type":"Point"}
}