{
  "type": "Feature",
  "properties": {
    "addr:full":"1421 Beaverdale Rd NE Dalton GA 30721",
    "addr:housenumber":"1421",
    "addr:postcode":"30721",
    "addr:street":"Beaverdale Rd Ne",
    "iso:country":"US",
    "sg:address":"1421 Beaverdale Rd NE",
    "sg:city":"Dalton",
    "sg:classifiers":[
        {
            "category":"Building & Trades",
            "subcategory":"Construction",
            "type":"Services"
        }
    ],
    "sg:phone":"+1 706 277 0645",
    "sg:postcode":"30721",
    "sg:province":"GA",
    "sg:tags":[
        "general",
        "contractor"
    ],
    "wof:name":"Holcomb Construction",
    "wof:placetype":"venue"
},
  "geometry": {"coordinates":[-84.888553,34.869003],"type":"Point"}
}