{
  "type": "Feature",
  "properties": {
    "addr:full":"835 Hodges St Metter GA 30439",
    "addr:housenumber":"835",
    "addr:postcode":"30439",
    "addr:street":"Hodges St",
    "iso:country":"US",
    "sg:address":"835 Hodges St",
    "sg:city":"Metter",
    "sg:classifiers":[
        {
            "category":"Place Of Worship",
            "type":"Public Place"
        }
    ],
    "sg:phone":"+1 912 685 4063",
    "sg:postcode":"30439",
    "sg:province":"GA",
    "sg:tags":[
        "church"
    ],
    "wof:name":"Steep Hill M.B. Church",
    "wof:placetype":"venue"
},
  "geometry": {"coordinates":[-82.04374,32.403071],"type":"Point"}
}