{
  "type": "Feature",
  "properties": {
    "iso:country":"US",
    "sg:address":"9979 Twingate Dr",
    "sg:city":"Alpharetta",
    "sg:classifiers":[
        {
            "category":"Building & Trades",
            "subcategory":"Locksmith",
            "type":"Services"
        }
    ],
    "sg:phone":"+1 678 259 0051",
    "sg:postcode":"30022",
    "sg:province":"GA",
    "sg:tags":[
        "key"
    ],
    "wof:name":"A Locksmith 1-24-7",
    "wof:placetype":"venue"
},
  "geometry": {"coordinates":[-84.203008,34.019546],"type":"Point"}
}