{
  "type": "Feature",
  "properties": {
    "iso:country":"US",
    "sg:address":"123 Lee St",
    "sg:city":"Carrollton",
    "sg:classifiers":[
        {
            "category":"Personal",
            "subcategory":"Beauty Salon",
            "type":"Services"
        }
    ],
    "sg:phone":"+1 770 214 9411",
    "sg:postcode":"30117",
    "sg:province":"GA",
    "sg:tags":[
        "hair",
        "shop",
        "stylist"
    ],
    "wof:name":"Cuttin-Up",
    "wof:placetype":"venue"
},
  "geometry": {"coordinates":[-85.07528000000001,33.575664],"type":"Point"}
}