{
  "type": "Feature",
  "properties": {
    "addr:full":"624 W Gwinnett St Savannah GA 31401",
    "addr:housenumber":"624",
    "addr:postcode":"31401",
    "addr:street":"W Gwinnett St",
    "iso:country":"US",
    "sg:address":"624 W Gwinnett St",
    "sg:city":"Savannah",
    "sg:classifiers":[
        {
            "category":"Education",
            "subcategory":"Library",
            "type":"Public Place"
        }
    ],
    "sg:phone":"+1 912 238 3661",
    "sg:postcode":"31401",
    "sg:province":"GA",
    "wof:name":"Kayton Branch Library",
    "wof:placetype":"venue"
},
  "geometry": {"coordinates":[-81.106656,32.069929],"type":"Point"}
}