{
  "type": "Feature",
  "properties": {
    "addr:full":"229 W General Screven Way Hinesville GA 31313",
    "addr:housenumber":"229",
    "addr:postcode":"31313",
    "addr:street":"W General Screven Way",
    "iso:country":"US",
    "sg:address":"229 W General Screven Way",
    "sg:city":"Hinesville",
    "sg:classifiers":[
        {
            "category":"Real Estate",
            "subcategory":"Real Estate Services",
            "type":"Services"
        },
        {
            "category":"Real Estate",
            "subcategory":"Real Estate Agent",
            "type":"Services"
        }
    ],
    "sg:phone":"+1 912 876 2626",
    "sg:postcode":"31313",
    "sg:province":"GA",
    "sg:tags":[
        "buyer",
        "broker"
    ],
    "sg:website":"http://www.lighthouseprophecy.com",
    "wof:name":"Sikes Group",
    "wof:placetype":"venue"
},
  "geometry": {"coordinates":[-81.60710899999999,31.85813],"type":"Point"}
}