{
  "type": "Feature",
  "properties": {
    "iso:country":"US",
    "sg:address":"2113 Central Ave S",
    "sg:city":"Tifton",
    "sg:classifiers":[
        {
            "category":"Autos & Motor Vehicles",
            "subcategory":"Auto Supplies",
            "type":"Retail Goods"
        }
    ],
    "sg:phone":"+1 229 386 8268",
    "sg:postcode":"31794",
    "sg:province":"GA",
    "sg:tags":[
        "battery"
    ],
    "wof:name":"Dorite Battery Co",
    "wof:placetype":"venue"
},
  "geometry": {"coordinates":[-83.515528,31.442091],"type":"Point"}
}