{
  "type": "Feature",
  "properties": {
    "addr:full":"501 S Main St Swainsboro GA 30401",
    "addr:housenumber":"501",
    "addr:postcode":"30401",
    "addr:street":"S Main St",
    "iso:country":"US",
    "sg:address":"501 S Main St",
    "sg:city":"Swainsboro",
    "sg:classifiers":[
        {
            "category":"Shopping",
            "subcategory":"Clothing, Apparel, & Fashions",
            "type":"Retail Goods"
        }
    ],
    "sg:phone":"+1 478 237 2220",
    "sg:postcode":"30401",
    "sg:province":"GA",
    "wof:name":"Cato",
    "wof:placetype":"venue"
},
  "geometry": {"coordinates":[-82.325114,32.58728],"type":"Point"}
}