{
  "type": "Feature",
  "properties": {
    "addr:full":"1418 Dresden Dr. Atlanta GA 30319",
    "addr:housenumber":"1418",
    "addr:postcode":"30319",
    "addr:street":"Dresden Dr.",
    "iso:country":"US",
    "sg:address":"1418 Dresden Dr.",
    "sg:city":"Atlanta",
    "sg:classifiers":[
        {
            "category":"Arts & Performance",
            "subcategory":"Art Gallery",
            "type":"Entertainment"
        }
    ],
    "sg:phone":"+1 770 280 7087",
    "sg:postcode":"30319",
    "sg:province":"GA",
    "sg:website":"www.cocktailscanvas.com/",
    "wof:name":"Cocktails & Canvas",
    "wof:placetype":"venue"
},
  "geometry": {"coordinates":[-84.33093700000001,33.860855],"type":"Point"}
}