{
  "type": "Feature",
  "properties": {
    "addr:full":"4000 Northfield Way Roswell GA 30076",
    "addr:housenumber":"4000",
    "addr:postcode":"30076",
    "addr:street":"Northfield Way",
    "iso:country":"US",
    "sg:address":"4000 Northfield Way",
    "sg:city":"Roswell",
    "sg:classifiers":[
        {
            "category":"Wholesale",
            "subcategory":"Electrical",
            "type":"Manufacturing & Wholesale Goods"
        }
    ],
    "sg:phone":"+1 770 518 1153",
    "sg:postcode":"30076",
    "sg:province":"GA",
    "sg:tags":[
        "electronic"
    ],
    "wof:name":"Hobbs Distributing",
    "wof:placetype":"venue"
},
  "geometry": {"coordinates":[-84.32216,34.046565],"type":"Point"}
}