{
  "type": "Feature",
  "properties": {
    "iso:country":"US",
    "sg:address":"1711 Franklin Cir",
    "sg:city":"Dacula",
    "sg:classifiers":[
        {
            "category":"Building & Trades",
            "subcategory":"Construction",
            "type":"Services"
        }
    ],
    "sg:phone":"+1 770 945 8432",
    "sg:postcode":"30019",
    "sg:province":"GA",
    "sg:tags":[
        "nonresidential"
    ],
    "wof:name":"Elvin A Thigpen",
    "wof:placetype":"venue"
},
  "geometry": {"coordinates":[-83.851151,33.95829],"type":"Point"}
}