{
  "type": "Feature",
  "properties": {
    "iso:country":"US",
    "sg:address":"1921 Flat Rock Rd",
    "sg:city":"Watkinsville",
    "sg:classifiers":[
        {
            "category":"Building & Trades",
            "subcategory":"Electrical",
            "type":"Services"
        }
    ],
    "sg:phone":"+1 706 769 6954",
    "sg:postcode":"30677",
    "sg:province":"GA",
    "sg:tags":[
        "electrician",
        "contractor"
    ],
    "wof:name":"Michael Phillips Electrical Inc",
    "wof:placetype":"venue"
},
  "geometry": {"coordinates":[-83.355529,33.835912],"type":"Point"}
}