{
  "type": "Feature",
  "properties": {
    "addr:full":"1119 Lookout Ct Villa Rica GA 30180",
    "addr:housenumber":"1119",
    "addr:postcode":"30180",
    "addr:street":"Lookout Ct",
    "iso:country":"US",
    "sg:address":"1119 Lookout Ct",
    "sg:city":"Villa Rica",
    "sg:classifiers":[
        {
            "category":"Health Services",
            "subcategory":"Doctor",
            "type":"Services"
        }
    ],
    "sg:phone":"+1 770 832 9502",
    "sg:postcode":"30180",
    "sg:province":"GA",
    "sg:tags":[
        "physician",
        "surgeon"
    ],
    "wof:name":"Children's Healthcare-Atlnt",
    "wof:placetype":"venue"
},
  "geometry": {"coordinates":[-84.920074,33.641132],"type":"Point"}
}