{
  "type": "Feature",
  "properties": {
    "addr:full":"4870 Brandon Acres Ln Buford GA 30519",
    "addr:housenumber":"4870",
    "addr:postcode":"30519",
    "addr:street":"Brandon Acres Ln",
    "iso:country":"US",
    "sg:address":"4870 Brandon Acres Ln",
    "sg:city":"Buford",
    "sg:classifiers":[
        {
            "category":"Banks & Credit Unions",
            "subcategory":"Bank",
            "type":"Services"
        }
    ],
    "sg:phone":"+1 770 614 6606",
    "sg:postcode":"30519",
    "sg:province":"GA",
    "sg:tags":[
        "mortgage"
    ],
    "wof:name":"Streamline Mortgage Inc",
    "wof:placetype":"venue"
},
  "geometry": {"coordinates":[-83.883019,34.089293],"type":"Point"}
}