{
  "type": "Feature",
  "properties": {
    "addr:full":"12 Homer St Maysville GA 30558",
    "addr:housenumber":"12",
    "addr:postcode":"30558",
    "addr:street":"Homer St",
    "iso:country":"US",
    "sg:address":"12 Homer St",
    "sg:city":"Maysville",
    "sg:classifiers":[
        {
            "category":"Professional",
            "subcategory":"Business Services",
            "type":"Services"
        }
    ],
    "sg:phone":"+1 706 652 3122",
    "sg:postcode":"30558",
    "sg:province":"GA",
    "sg:tags":[
        "auctioneer"
    ],
    "wof:name":"Heritage Auction Co",
    "wof:placetype":"venue"
},
  "geometry": {"coordinates":[-83.559665,34.255877],"type":"Point"}
}