{
  "type": "Feature",
  "properties": {
    "iso:country":"US",
    "sg:address":"2222 Bull St",
    "sg:city":"Savannah",
    "sg:classifiers":[
        {
            "category":"Organizations",
            "subcategory":"Labor Organization",
            "type":"Services"
        }
    ],
    "sg:phone":"+1 912 234 5666",
    "sg:postcode":"31401",
    "sg:province":"GA",
    "sg:website":"http://www.apwu.org",
    "wof:name":"American Postal Workers Union",
    "wof:placetype":"venue"
},
  "geometry": {"coordinates":[-81.100703,32.056038],"type":"Point"}
}