{
  "type": "Feature",
  "properties": {
    "iso:country":"US",
    "sg:address":"Studioplex Lofts 659 Auburn Ave, Ste 144",
    "sg:city":"Atlanta",
    "sg:classifiers":[
        {
            "category":"Personal",
            "subcategory":"Beauty Salon",
            "type":"Services"
        },
        {
            "category":"Personal",
            "subcategory":"Barber",
            "type":"Services"
        }
    ],
    "sg:phone":"+1 404 558 3739",
    "sg:postcode":"30312",
    "sg:province":"GA",
    "sg:tags":[
        "hair"
    ],
    "sg:website":"www.mirarsalon.com",
    "wof:name":"MIRAR SALON",
    "wof:placetype":"venue"
},
  "geometry": {"coordinates":[-84.366061,33.756048],"type":"Point"}
}