{
  "type": "Feature",
  "properties": {
    "iso:country":"US",
    "sg:address":"5655 Austell Powder Springs Rd",
    "sg:city":"Austell",
    "sg:classifiers":[
        {
            "category":"Professional",
            "subcategory":"Business Services",
            "type":"Services"
        }
    ],
    "sg:phone":"+1 770 732 8566",
    "sg:postcode":"30106",
    "sg:province":"GA",
    "sg:tags":[
        "process",
        "server"
    ],
    "wof:name":"Quality Binder Solutions LLC",
    "wof:placetype":"venue"
},
  "geometry": {"coordinates":[-84.637393,33.816883],"type":"Point"}
}