{
  "type": "Feature",
  "properties": {
    "iso:country":"US",
    "sg:address":"118 Rosemont St",
    "sg:city":"St Simons Island",
    "sg:classifiers":[
        {
            "category":"Real Estate",
            "subcategory":"Real Estate Agent",
            "type":"Services"
        },
        {
            "category":"Banks & Credit Unions",
            "subcategory":"Financial Services",
            "type":"Services"
        }
    ],
    "sg:phone":"+1 912 638 3376",
    "sg:postcode":"31522",
    "sg:province":"GA",
    "sg:tags":[
        "management",
        "open",
        "investment"
    ],
    "wof:name":"Shanstorm Inc",
    "wof:placetype":"venue"
},
  "geometry": {"coordinates":[-81.37988199999999,31.183394],"type":"Point"}
}