{
  "type": "Feature",
  "properties": {
    "addr:full":"4480 S Cobb Dr SE Ste P Smyrna GA 30080",
    "addr:housenumber":"4480",
    "addr:postcode":"30080",
    "addr:street":"S Cobb Dr Se Ste P",
    "iso:country":"US",
    "sg:address":"4480 S Cobb Dr SE Ste P",
    "sg:city":"Smyrna",
    "sg:classifiers":[
        {
            "category":"Shopping",
            "subcategory":"Bicycles & Sporting Goods",
            "type":"Retail Goods"
        }
    ],
    "sg:phone":"+1 770 438 1150",
    "sg:postcode":"30080",
    "sg:province":"GA",
    "sg:tags":[
        "bike"
    ],
    "sg:website":"www.trailofwheels.com",
    "wof:name":"Trail of Wheels",
    "wof:placetype":"venue"
},
  "geometry": {"coordinates":[-84.50243500000001,33.844831],"type":"Point"}
}