{
  "type": "Feature",
  "properties": {
    "iso:country":"US",
    "sg:address":"3128 Holly Mill Run",
    "sg:city":"Marietta",
    "sg:classifiers":[
        {
            "category":"Building & Trades",
            "subcategory":"Landscaping Services",
            "type":"Services"
        }
    ],
    "sg:phone":"+1 770 321 9664",
    "sg:postcode":"30062",
    "sg:province":"GA",
    "sg:tags":[
        "lawn",
        "maintenance",
        "grounds"
    ],
    "wof:name":"Spears Landscaping Co",
    "wof:placetype":"venue"
},
  "geometry": {"coordinates":[-84.45650999999999,33.998939],"type":"Point"}
}