{
  "type": "Feature",
  "properties": {
    "iso:country":"US",
    "sg:address":"301 N Gross Rd",
    "sg:city":"Kingsland",
    "sg:classifiers":[
        {
            "category":"Professional",
            "subcategory":"Detective & Security Services",
            "type":"Services"
        }
    ],
    "sg:phone":"+1 912 882 6492",
    "sg:postcode":"31548",
    "sg:province":"GA",
    "sg:tags":[
        "information",
        "bureau"
    ],
    "wof:name":"Vashti's Baby Sitting Service",
    "wof:placetype":"venue"
},
  "geometry": {"coordinates":[-81.641806,30.792891],"type":"Point"}
}