{
  "type": "Feature",
  "properties": {
    "iso:country":"US",
    "sg:address":"2311 Thomas St",
    "sg:city":"Adel",
    "sg:classifiers":[
        {
            "category":"Restaurant",
            "type":"Food & Drink"
        }
    ],
    "sg:phone":"+1 229 896 1725",
    "sg:postcode":"31620",
    "sg:province":"GA",
    "wof:name":"Back Porch Restaurant & Gift",
    "wof:placetype":"venue"
},
  "geometry": {"coordinates":[-83.411249,31.160389],"type":"Point"}
}