{
  "type": "Feature",
  "properties": {
    "addr:full":"46 Owl Head Trl Hazlehurst GA 31539",
    "addr:housenumber":"46",
    "addr:postcode":"31539",
    "addr:street":"Owl Head Trl",
    "iso:country":"US",
    "sg:address":"46 Owl Head Trl",
    "sg:city":"Hazlehurst",
    "sg:classifiers":[
        {
            "category":"Real Estate",
            "subcategory":"Surveying",
            "type":"Services"
        }
    ],
    "sg:phone":"+1 912 375 9461",
    "sg:postcode":"31539",
    "sg:province":"GA",
    "sg:tags":[
        "surveyor",
        "land"
    ],
    "wof:name":"Greg Edward Land",
    "wof:placetype":"venue"
},
  "geometry": {"coordinates":[-82.537453,31.900106],"type":"Point"}
}