{
  "type": "Feature",
  "properties": {
    "iso:country":"US",
    "sg:address":"514 Pine Ave",
    "sg:city":"Albany",
    "sg:classifiers":[
        {
            "category":"Arts & Performance",
            "subcategory":"Theater",
            "type":"Entertainment"
        }
    ],
    "sg:phone":"+1 229 439 7141",
    "sg:postcode":"31701",
    "sg:province":"GA",
    "sg:website":"www.theatrealbany.com",
    "wof:name":"Theatre Albany",
    "wof:placetype":"venue"
},
  "geometry": {"coordinates":[-84.161547,31.578322],"type":"Point"}
}