{
  "type": "Feature",
  "properties": {
    "iso:country":"US",
    "sg:address":"3939 Lavista Rd",
    "sg:city":"Tucker",
    "sg:classifiers":[
        {
            "category":"Personal",
            "subcategory":"Nail Salon",
            "type":"Services"
        }
    ],
    "sg:phone":"+1 770 939 7210",
    "sg:postcode":"30084",
    "sg:province":"GA",
    "wof:name":"New Nails",
    "wof:placetype":"venue"
},
  "geometry": {"coordinates":[-84.258202,33.843601],"type":"Point"}
}