{
  "type": "Feature",
  "properties": {
    "addr:full":"221 Johnson St Statesboro GA 30458",
    "addr:housenumber":"221",
    "addr:postcode":"30458",
    "addr:street":"Johnson St",
    "iso:country":"US",
    "sg:address":"221 Johnson St",
    "sg:city":"Statesboro",
    "sg:classifiers":[
        {
            "category":"Building & Trades",
            "subcategory":"Construction",
            "type":"Services"
        }
    ],
    "sg:phone":"+1 912 764 3145",
    "sg:postcode":"30458",
    "sg:province":"GA",
    "sg:tags":[
        "concrete",
        "contractor"
    ],
    "wof:name":"Instant Concrete Finishing",
    "wof:placetype":"venue"
},
  "geometry": {"coordinates":[-81.79077599999999,32.448356],"type":"Point"}
}