{
  "type": "Feature",
  "properties": {
    "addr:full":"180 Teal Dr Ringgold GA 30736",
    "addr:housenumber":"180",
    "addr:postcode":"30736",
    "addr:street":"Teal Dr",
    "iso:country":"US",
    "sg:address":"180 Teal Dr",
    "sg:city":"Ringgold",
    "sg:classifiers":[
        {
            "category":"Professional",
            "subcategory":"Management & Consulting",
            "type":"Services"
        }
    ],
    "sg:phone":"+1 706 937 2633",
    "sg:postcode":"30736",
    "sg:province":"GA",
    "sg:tags":[
        "consultant",
        "business"
    ],
    "wof:name":"Epic Enterprises",
    "wof:placetype":"venue"
},
  "geometry": {"coordinates":[-85.161749,34.859232],"type":"Point"}
}