{
  "type": "Feature",
  "properties": {
    "addr:full":"825 Martin Luther King Jr Dr NW Atlanta GA 30314",
    "addr:housenumber":"825",
    "addr:postcode":"30314",
    "addr:street":"Martin Luther King Jr Dr Nw",
    "iso:country":"US",
    "sg:address":"825 Martin Luther King Jr Dr NW",
    "sg:city":"Atlanta",
    "sg:classifiers":[
        {
            "category":"Professional",
            "subcategory":"Accounting & Tax Preparation",
            "type":"Services"
        },
        {
            "category":"Banks & Credit Unions",
            "subcategory":"Financial Services",
            "type":"Services"
        }
    ],
    "sg:phone":"+1 404 584 5933",
    "sg:postcode":"30314",
    "sg:province":"GA",
    "sg:tags":[
        "return",
        "preparation-business",
        "taxes-consultants",
        "loan",
        "reporting",
        "representative",
        "alternative",
        "bookkeeping"
    ],
    "sg:website":"http://www.hrblock.com",
    "wof:name":"H&R Block",
    "wof:placetype":"venue"
},
  "geometry": {"coordinates":[-84.414571,33.754723],"type":"Point"}
}