{
  "type": "Feature",
  "properties": {
    "addr:full":"165 Glenclairn Ct Roswell GA 30076",
    "addr:housenumber":"165",
    "addr:postcode":"30076",
    "addr:street":"Glenclairn Ct",
    "iso:country":"US",
    "sg:address":"165 Glenclairn Ct",
    "sg:city":"Roswell",
    "sg:classifiers":[
        {
            "category":"Building & Trades",
            "subcategory":"Construction",
            "type":"Services"
        }
    ],
    "sg:phone":"+1 770 998 5461",
    "sg:postcode":"30076",
    "sg:province":"GA",
    "sg:tags":[
        "hanging",
        "contractor"
    ],
    "wof:name":"Taylored Decorating",
    "wof:placetype":"venue"
},
  "geometry": {"coordinates":[-84.352268,34.066894],"type":"Point"}
}