{
  "type": "Feature",
  "properties": {
    "addr:full":"4192 Norwich St Exd Brunswick GA 31520",
    "addr:housenumber":"4192",
    "addr:postcode":"31520",
    "addr:street":"Norwich St Exd",
    "iso:country":"US",
    "sg:address":"4192 Norwich St Exd",
    "sg:city":"Brunswick",
    "sg:classifiers":[
        {
            "category":"Food & Beverages",
            "subcategory":"Groceries & Convenience Stores",
            "type":"Retail Goods"
        }
    ],
    "sg:phone":"+1 912 264 5009",
    "sg:postcode":"31520",
    "sg:province":"GA",
    "wof:name":"Ozzie's",
    "wof:placetype":"venue"
},
  "geometry": {"coordinates":[-81.50635200000001,31.198027],"type":"Point"}
}