{
  "type": "Feature",
  "properties": {
    "addr:full":"109 Robin Dr Bonaire GA 31005",
    "addr:housenumber":"109",
    "addr:postcode":"31005",
    "addr:street":"Robin Dr",
    "iso:country":"US",
    "sg:address":"109 Robin Dr",
    "sg:city":"Bonaire",
    "sg:classifiers":[
        {
            "category":"Building & Trades",
            "subcategory":"Construction",
            "type":"Services"
        }
    ],
    "sg:phone":"+1 478 987 4047",
    "sg:postcode":"31005",
    "sg:province":"GA",
    "sg:tags":[
        "home",
        "improvement"
    ],
    "wof:name":"Martin Roofing Co",
    "wof:placetype":"venue"
},
  "geometry": {"coordinates":[-83.639679,32.542181],"type":"Point"}
}