{
  "type": "Feature",
  "properties": {
    "addr:full":"503 Forest Pkwy Forest Park GA 30297",
    "addr:housenumber":"503",
    "addr:postcode":"30297",
    "addr:street":"Forest Pkwy",
    "iso:country":"US",
    "sg:address":"503 Forest Pkwy",
    "sg:city":"Forest Park",
    "sg:classifiers":[
        {
            "category":"Food & Beverages",
            "subcategory":"Groceries & Convenience Stores",
            "type":"Retail Goods"
        }
    ],
    "sg:phone":"+1 404 366 4502",
    "sg:postcode":"30297",
    "sg:province":"GA",
    "wof:name":"Speedway Starvin Marvin Food Store",
    "wof:placetype":"venue"
},
  "geometry": {"coordinates":[-84.37460299999999,33.620899],"type":"Point"}
}