{
  "type": "Feature",
  "properties": {
    "iso:country":"US",
    "sg:address":"86 Bleeker St SW",
    "sg:city":"Lawrenceville",
    "sg:classifiers":[
        {
            "category":"Building & Trades",
            "subcategory":"Construction",
            "type":"Services"
        }
    ],
    "sg:phone":"+1 770 279 0684",
    "sg:postcode":"30044",
    "sg:province":"GA",
    "sg:tags":[
        "contractor"
    ],
    "wof:name":"Hayes Fence Company Inc",
    "wof:placetype":"venue"
},
  "geometry": {"coordinates":[-84.078778,33.905017],"type":"Point"}
}