{
  "type": "Feature",
  "properties": {
    "addr:full":"630 Price Quarters Rd Mcdonough GA 30253",
    "addr:housenumber":"630",
    "addr:postcode":"30253",
    "addr:street":"Price Quarters Rd",
    "iso:country":"US",
    "sg:address":"630 Price Quarters Rd",
    "sg:city":"Mcdonough",
    "sg:classifiers":[
        {
            "category":"Retail",
            "subcategory":"Laundry & Dry Cleaning",
            "type":"Services"
        }
    ],
    "sg:phone":"+1 770 914 1136",
    "sg:postcode":"30253",
    "sg:province":"GA",
    "sg:tags":[
        "cleaners",
        "plant",
        "drycleaning"
    ],
    "wof:name":"Nye Cleaners",
    "wof:placetype":"venue"
},
  "geometry": {"coordinates":[-84.151689,33.519182],"type":"Point"}
}