{
  "type": "Feature",
  "properties": {
    "addr:full":"2351 Hwy 113 Taylorsville GA 30178",
    "addr:housenumber":"2351",
    "addr:postcode":"30178",
    "addr:street":"Hwy 113",
    "iso:country":"US",
    "sg:address":"2351 Hwy 113",
    "sg:city":"Taylorsville",
    "sg:classifiers":[
        {
            "category":"Autos & Motor Vehicles",
            "subcategory":"Automobile Sales",
            "type":"Retail Goods"
        }
    ],
    "sg:phone":"+1 770 383 9191",
    "sg:postcode":"30178",
    "sg:province":"GA",
    "sg:tags":[
        "car",
        "dealer"
    ],
    "wof:name":"Midway Motors",
    "wof:placetype":"venue"
},
  "geometry": {"coordinates":[-84.93033699999999,34.100242],"type":"Point"}
}