{
  "type": "Feature",
  "properties": {
    "iso:country":"US",
    "sg:address":"5024 Bird Rd",
    "sg:city":"Gainesville",
    "sg:classifiers":[
        {
            "category":"Wholesale",
            "subcategory":"Computers",
            "type":"Manufacturing & Wholesale Goods"
        }
    ],
    "sg:phone":"+1 678 350 8153",
    "sg:postcode":"30506",
    "sg:province":"GA",
    "sg:tags":[
        "equipment"
    ],
    "wof:name":"Daveserv",
    "wof:placetype":"venue"
},
  "geometry": {"coordinates":[-83.903204,34.403161],"type":"Point"}
}