{
  "type": "Feature",
  "properties": {
    "addr:full":"4550 Jimmy Carter Blvd Norcross GA 30093",
    "addr:housenumber":"4550",
    "addr:postcode":"30093",
    "addr:street":"Jimmy Carter Blvd",
    "iso:country":"US",
    "sg:address":"4550 Jimmy Carter Blvd",
    "sg:city":"Norcross",
    "sg:classifiers":[
        {
            "category":"Real Estate",
            "subcategory":"Real Estate Services",
            "type":"Services"
        }
    ],
    "sg:phone":"+1 770 496 1889",
    "sg:postcode":"30093",
    "sg:province":"GA",
    "wof:name":"Jessee George William Jr Rl Est",
    "wof:placetype":"venue"
},
  "geometry": {"coordinates":[-84.190102,33.882801],"type":"Point"}
}