{
  "type": "Feature",
  "properties": {
    "addr:full":"10 Shorter Ave Rome GA 30165",
    "addr:housenumber":"10",
    "addr:postcode":"ga 30165",
    "addr:street":"Shorter Ave",
    "iso:country":"US",
    "sg:address":"10 Shorter Ave",
    "sg:city":"Rome",
    "sg:classifiers":[
        {
            "category":"Professional",
            "type":"Services"
        }
    ],
    "sg:phone":"+1 706 291 3986",
    "sg:postcode":"30165",
    "sg:province":"GA",
    "wof:name":"Snt",
    "wof:placetype":"venue"
},
  "geometry": {"coordinates":[-85.18548699999999,34.262114],"type":"Point"}
}