{
  "type": "Feature",
  "properties": {
    "addr:full":"303 S Scott St Bainbridge GA 39819",
    "addr:housenumber":"303",
    "addr:postcode":"39819",
    "addr:street":"S Scott St",
    "iso:country":"US",
    "sg:address":"303 S Scott St",
    "sg:city":"Bainbridge",
    "sg:classifiers":[
        {
            "category":"Shopping",
            "subcategory":"Discount & Variety Stores",
            "type":"Retail Goods"
        }
    ],
    "sg:phone":"+1 229 246 4366",
    "sg:postcode":"39819",
    "sg:province":"GA",
    "wof:name":"Family Dollar Stores",
    "wof:placetype":"venue"
},
  "geometry": {"coordinates":[-84.56782,30.903943],"type":"Point"}
}