{
  "type": "Feature",
  "properties": {
    "iso:country":"US",
    "sg:address":"810 Windy Hill Rd SE",
    "sg:city":"Smyrna",
    "sg:classifiers":[
        {
            "category":"Professional",
            "type":"Services"
        }
    ],
    "sg:phone":"+1 770 431 4875",
    "sg:postcode":"30080",
    "sg:province":"GA",
    "wof:name":"Luis Enrique Castillo",
    "wof:placetype":"venue"
},
  "geometry": {"coordinates":[-84.53192799999999,33.894371],"type":"Point"}
}