{
  "type": "Feature",
  "properties": {
    "addr:full":"210 Waterworks Rd Commerce GA 30529",
    "addr:housenumber":"210",
    "addr:postcode":"30529",
    "addr:street":"Waterworks Rd",
    "iso:country":"US",
    "sg:address":"210 Waterworks Rd",
    "sg:city":"Commerce",
    "sg:classifiers":[
        {
            "category":"Building & Trades",
            "subcategory":"Construction",
            "type":"Services"
        }
    ],
    "sg:phone":"+1 706 335 9262",
    "sg:postcode":"30529",
    "sg:province":"GA",
    "sg:tags":[
        "marking",
        "maintenance",
        "parking"
    ],
    "wof:name":"Public Works Dept",
    "wof:placetype":"venue"
},
  "geometry": {"coordinates":[-83.45933599999999,34.19715],"type":"Point"}
}