{
  "type": "Feature",
  "properties": {
    "iso:country":"US",
    "sg:address":"2020 E Victory Dr",
    "sg:city":"Savannah",
    "sg:classifiers":[
        {
            "category":"Restaurant",
            "type":"Food & Drink"
        }
    ],
    "sg:menulink":"http://www.allmenus.com/ga/savannah/180821-wendys/menu/",
    "sg:phone":"+1 912 234 2819",
    "sg:postcode":"31404",
    "sg:province":"GA",
    "sg:tags":[
        "burger",
        "american",
        "soup"
    ],
    "wof:name":"Wendy's",
    "wof:placetype":"venue"
},
  "geometry": {"coordinates":[-81.064618,32.042009],"type":"Point"}
}