{
  "type": "Feature",
  "properties": {
    "addr:full":"11675 Medlock Bridge Rd Duluth GA 30097",
    "addr:housenumber":"11675",
    "addr:postcode":"30097",
    "addr:street":"Medlock Bridge Rd",
    "iso:country":"US",
    "sg:address":"11675 Medlock Bridge Rd",
    "sg:city":"Duluth",
    "sg:classifiers":[
        {
            "category":"Banks & Credit Unions",
            "subcategory":"Bank",
            "type":"Services"
        }
    ],
    "sg:phone":"+1 770 495 5371",
    "sg:postcode":"30097",
    "sg:province":"GA",
    "wof:name":"National Bank Of Commerce",
    "wof:placetype":"venue"
},
  "geometry": {"coordinates":[-84.17421899999999,34.055641],"type":"Point"}
}