{
  "type": "Feature",
  "properties": {
    "iso:country":"US",
    "sg:address":"850 Great Southwest Pkwy SW",
    "sg:city":"Atlanta",
    "sg:classifiers":[
        {
            "category":"Wholesale",
            "subcategory":"Durable Goods & Equipment",
            "type":"Manufacturing & Wholesale Goods"
        }
    ],
    "sg:phone":"+1 404 629 6654",
    "sg:postcode":"30336",
    "sg:province":"GA",
    "sg:tags":[
        "importer"
    ],
    "wof:name":"MSM Imports Inc",
    "wof:placetype":"venue"
},
  "geometry": {"coordinates":[-84.57113099999999,33.737483],"type":"Point"}
}