{
  "type": "Feature",
  "properties": {
    "addr:full":"6836 State Rte 85 Riverdale GA 30274",
    "addr:housenumber":"6836",
    "addr:postcode":"30274",
    "addr:street":"State Rte 85",
    "iso:country":"US",
    "sg:address":"6836 State Rte 85",
    "sg:city":"Riverdale",
    "sg:classifiers":[
        {
            "category":"Retail",
            "subcategory":"Auto Repair",
            "type":"Services"
        }
    ],
    "sg:phone":"+1 770 997 7424",
    "sg:postcode":"30274",
    "sg:province":"GA",
    "sg:tags":[
        "body",
        "automobile",
        "painting",
        "general"
    ],
    "wof:name":"Riverdale Collision Inc",
    "wof:placetype":"venue"
},
  "geometry": {"coordinates":[-84.411663,33.579742],"type":"Point"}
}