{
  "type": "Feature",
  "properties": {
    "addr:full":"41 Peyton Rd SW Atlanta GA 30311",
    "addr:housenumber":"41",
    "addr:postcode":"30311",
    "addr:street":"Peyton Rd Sw",
    "iso:country":"US",
    "sg:address":"41 Peyton Rd SW",
    "sg:city":"Atlanta",
    "sg:classifiers":[
        {
            "category":"Professional",
            "type":"Services"
        },
        {
            "category":"Restaurant",
            "type":"Food & Drink"
        },
        {
            "category":"Fast Food",
            "type":"Food & Drink"
        }
    ],
    "sg:phone":"+1 678 940 7987",
    "sg:postcode":"30311",
    "sg:province":"GA",
    "sg:tags":[
        "seafood",
        "caterer",
        "soul",
        "take"
    ],
    "wof:name":"Rahims Seafood",
    "wof:placetype":"venue"
},
  "geometry": {"coordinates":[-84.4682,33.749965],"type":"Point"}
}