{
  "type": "Feature",
  "properties": {
    "iso:country":"US",
    "sg:address":"1539 Bethesda Church Rd",
    "sg:city":"Carrollton",
    "sg:classifiers":[
        {
            "category":"Organizations",
            "subcategory":"Religious Organization",
            "type":"Services"
        }
    ],
    "sg:phone":"+1 770 854 8532",
    "sg:postcode":"30117",
    "sg:province":"GA",
    "sg:tags":[
        "church"
    ],
    "wof:name":"Bethesda Baptist Church",
    "wof:placetype":"venue"
},
  "geometry": {"coordinates":[-85.151611,33.493105],"type":"Point"}
}