{
  "type": "Feature",
  "properties": {
    "addr:full":"4965 Flat Shoals Pkwy Decatur GA 30034",
    "addr:housenumber":"4965",
    "addr:postcode":"30034",
    "addr:street":"Flat Shoals Pkwy",
    "iso:country":"US",
    "sg:address":"4965 Flat Shoals Pkwy",
    "sg:city":"Decatur",
    "sg:classifiers":[
        {
            "category":"Restaurant",
            "type":"Food & Drink"
        }
    ],
    "sg:phone":"+1 770 987 0100",
    "sg:postcode":"30034",
    "sg:province":"GA",
    "sg:website":"www.wendys.com",
    "wof:name":"Wendy's Old Fashioned Hamburgers",
    "wof:placetype":"venue"
},
  "geometry": {"coordinates":[-84.229202,33.681198],"type":"Point"}
}