{
  "type": "Feature",
  "properties": {
    "iso:country":"US",
    "sg:address":"8896 Tara Blvd",
    "sg:city":"Jonesboro",
    "sg:classifiers":[
        {
            "category":"Health Services",
            "subcategory":"Clinic",
            "type":"Services"
        },
        {
            "category":"Health Services",
            "subcategory":"Nursing And Care Facility",
            "type":"Services"
        },
        {
            "category":"Health Services",
            "subcategory":"Health Practitioner",
            "type":"Services"
        }
    ],
    "sg:phone":"+1 770 210 0631",
    "sg:postcode":"30236",
    "sg:province":"GA",
    "sg:tags":[
        "home",
        "medical",
        "eldercare-home"
    ],
    "sg:website":"http://www.csshealthcare.com",
    "wof:name":"C SS Healthcare Services Inc",
    "wof:placetype":"venue"
},
  "geometry": {"coordinates":[-84.358034,33.510691],"type":"Point"}
}