{
  "type": "Feature",
  "properties": {
    "iso:country":"US",
    "sg:address":"1410 Pinyan Rd SE",
    "sg:city":"Ranger",
    "sg:classifiers":[
        {
            "category":"Professional",
            "type":"Services"
        }
    ],
    "sg:phone":"+1 706 337 7781",
    "sg:postcode":"30734",
    "sg:province":"GA",
    "wof:name":"Hicks Inc",
    "wof:placetype":"venue"
},
  "geometry": {"coordinates":[-84.655068,34.463818],"type":"Point"}
}