{
  "type": "Feature",
  "properties": {
    "iso:country":"US",
    "sg:address":"4175 King Richard Ct",
    "sg:city":"Snellville",
    "sg:classifiers":[
        {
            "category":"Professional",
            "subcategory":"Employment Agencies",
            "type":"Services"
        }
    ],
    "sg:phone":"+1 770 982 2456",
    "sg:postcode":"30039",
    "sg:province":"GA",
    "sg:tags":[
        "help",
        "supply"
    ],
    "wof:name":"Neat & Clean",
    "wof:placetype":"venue"
},
  "geometry": {"coordinates":[-84.071191,33.830755],"type":"Point"}
}