{
  "type": "Feature",
  "properties": {
    "addr:full":"5081 Mars Hill Rd Bogart GA 30622",
    "addr:housenumber":"5081",
    "addr:postcode":"30622",
    "addr:street":"Mars Hill Rd",
    "iso:country":"US",
    "sg:address":"5081 Mars Hill Rd",
    "sg:city":"Bogart",
    "sg:classifiers":[
        {
            "category":"Building & Trades",
            "subcategory":"Electrical",
            "type":"Services"
        }
    ],
    "sg:phone":"+1 770 725 5782",
    "sg:postcode":"30622",
    "sg:province":"GA",
    "sg:tags":[
        "electrical",
        "contractor"
    ],
    "wof:name":"Sosbee Electric Inc",
    "wof:placetype":"venue"
},
  "geometry": {"coordinates":[-83.529393,33.932111],"type":"Point"}
}