{
  "type": "Feature",
  "properties": {
    "iso:country":"US",
    "sg:address":"756 Dean Nichols Rd",
    "sg:city":"Statesboro",
    "sg:classifiers":[
        {
            "category":"Farming",
            "subcategory":"Farm",
            "type":"Manufacturing & Wholesale Goods"
        }
    ],
    "sg:phone":"+1 912 865 2871",
    "sg:postcode":"30458",
    "sg:province":"GA",
    "sg:tags":[
        "feedlot",
        "cattle",
        "crop",
        "beef",
        "general"
    ],
    "wof:name":"Nichols Farms",
    "wof:placetype":"venue"
},
  "geometry": {"coordinates":[-81.949625,32.500183],"type":"Point"}
}