{
  "type": "Feature",
  "properties": {
    "iso:country":"US",
    "sg:address":"222 Pine Level Church Rd",
    "sg:city":"Fitzgerald",
    "sg:classifiers":[
        {
            "category":"Professional",
            "type":"Services"
        }
    ],
    "sg:phone":"+1 229 424 9550",
    "sg:postcode":"31750",
    "sg:province":"GA",
    "wof:name":"Scott Griffin",
    "wof:placetype":"venue"
},
  "geometry": {"coordinates":[-83.189189,31.682626],"type":"Point"}
}