{
  "type": "Feature",
  "properties": {
    "addr:full":"702 Orange St Fort Valley GA 31030",
    "addr:housenumber":"702",
    "addr:postcode":"31030",
    "addr:street":"Orange St",
    "iso:country":"US",
    "sg:address":"702 Orange St",
    "sg:city":"Fort Valley",
    "sg:classifiers":[
        {
            "category":"Food & Beverages",
            "subcategory":"Groceries & Convenience Stores",
            "type":"Retail Goods"
        }
    ],
    "sg:phone":"+1 478 825 5249",
    "sg:postcode":"31030",
    "sg:province":"GA",
    "sg:tags":[
        "gasoline"
    ],
    "wof:name":"Bobby's Minit Mart",
    "wof:placetype":"venue"
},
  "geometry": {"coordinates":[-83.894414,32.558581],"type":"Point"}
}