{
  "type": "Feature",
  "properties": {
    "iso:country":"US",
    "sg:address":"5616 Redan Rd",
    "sg:city":"Stone Mountain",
    "sg:classifiers":[
        {
            "category":"Personal",
            "subcategory":"Beauty Salon",
            "type":"Services"
        }
    ],
    "sg:phone":"+1 770 498 1311",
    "sg:postcode":"30088",
    "sg:province":"GA",
    "wof:name":"Cache Hair",
    "wof:placetype":"venue"
},
  "geometry": {"coordinates":[-84.162561,33.755073],"type":"Point"}
}