{
  "type": "Feature",
  "properties": {
    "addr:full":"245 Country Club Dr Stockbridge GA 30281",
    "addr:housenumber":"245",
    "addr:postcode":"30281",
    "addr:street":"Country Club Dr",
    "iso:country":"US",
    "sg:address":"245 Country Club Dr",
    "sg:city":"Stockbridge",
    "sg:classifiers":[
        {
            "category":"Professional",
            "subcategory":"Lawyer & Legal Services",
            "type":"Services"
        }
    ],
    "sg:phone":"+1 678 289 8628",
    "sg:postcode":"30281",
    "sg:province":"GA",
    "sg:tags":[
        "attorney"
    ],
    "wof:name":"School Craft Watkins",
    "wof:placetype":"venue"
},
  "geometry": {"coordinates":[-84.227127,33.506094],"type":"Point"}
}