{
  "type": "Feature",
  "properties": {
    "addr:full":"364 Stringer Rd Rockmart GA 30153",
    "addr:housenumber":"364",
    "addr:postcode":"30153",
    "addr:street":"Stringer Rd",
    "iso:country":"US",
    "sg:address":"364 Stringer Rd",
    "sg:city":"Rockmart",
    "sg:classifiers":[
        {
            "category":"Professional",
            "type":"Services"
        }
    ],
    "sg:phone":"+1 770 684 7599",
    "sg:postcode":"30153",
    "sg:province":"GA",
    "wof:name":"Rodney J Brown",
    "wof:placetype":"venue"
},
  "geometry": {"coordinates":[-85.103599,33.990249],"type":"Point"}
}