{
  "type": "Feature",
  "properties": {
    "iso:country":"US",
    "sg:address":"141 Park Of Commerce Dr",
    "sg:city":"Savannah",
    "sg:classifiers":[
        {
            "category":"Communications",
            "subcategory":"Television Station",
            "type":"Services"
        },
        {
            "category":"Professional",
            "subcategory":"Computer Services",
            "type":"Services"
        }
    ],
    "sg:phone":"+1 912 644 7100",
    "sg:postcode":"31405",
    "sg:province":"GA",
    "sg:tags":[
        "satellite",
        "isp",
        "internet",
        "cable",
        "provider"
    ],
    "sg:website":"http://www.cablecomcast.com",
    "wof:name":"Comcast Cable Communications",
    "wof:placetype":"venue"
},
  "geometry": {"coordinates":[-81.164711,32.064289],"type":"Point"}
}