{
  "type": "Feature",
  "properties": {
    "iso:country":"US",
    "sg:address":"864 Keys Ferry Rd",
    "sg:city":"Jackson",
    "sg:classifiers":[
        {
            "category":"Manufacturing",
            "subcategory":"Food",
            "type":"Manufacturing & Wholesale Goods"
        }
    ],
    "sg:phone":"+1 770 504 9446",
    "sg:postcode":"30233",
    "sg:province":"GA",
    "sg:tags":[
        "mfg"
    ],
    "wof:name":"Glorias Pralines",
    "wof:placetype":"venue"
},
  "geometry": {"coordinates":[-83.969503,33.41261],"type":"Point"}
}