{
  "type": "Feature",
  "properties": {
    "addr:full":"3475 Piedmont Road NE Atlanta GA 30305",
    "addr:housenumber":"3475",
    "addr:postcode":"30305",
    "addr:street":"Piedmont Road Ne",
    "iso:country":"US",
    "sg:address":"3475 Piedmont Road NE",
    "sg:city":"Atlanta",
    "sg:classifiers":[
        {
            "category":"Real Estate",
            "subcategory":"Real Estate Services",
            "type":"Services"
        }
    ],
    "sg:phone":"+1 404 266 8889",
    "sg:postcode":"30305",
    "sg:province":"GA",
    "sg:tags":[
        "management",
        "property"
    ],
    "sg:website":"www.equityoffice.com",
    "wof:name":"Equity Office Properties",
    "wof:placetype":"venue"
},
  "geometry": {"coordinates":[-84.376636,33.849497],"type":"Point"}
}