{
  "type": "Feature",
  "properties": {
    "addr:full":"601 Broad St Rome GA 30161",
    "addr:housenumber":"601",
    "addr:postcode":"ga 30161",
    "addr:street":"Broad St",
    "iso:country":"US",
    "sg:address":"601 Broad St",
    "sg:city":"Rome",
    "sg:classifiers":[
        {
            "category":"Government",
            "subcategory":"Office",
            "type":"Public Place"
        }
    ],
    "sg:phone":"+1 706 236 4459",
    "sg:postcode":"30161",
    "sg:province":"GA",
    "sg:tags":[
        "village"
    ],
    "wof:name":"Rome Business License Inspctr",
    "wof:placetype":"venue"
},
  "geometry": {"coordinates":[-85.167599,34.256595],"type":"Point"}
}