{
  "type": "Feature",
  "properties": {
    "iso:country":"US",
    "sg:address":"118 N Jackson St",
    "sg:city":"Americus",
    "sg:classifiers":[
        {
            "category":"Professional",
            "type":"Services"
        }
    ],
    "sg:phone":"+1 229 928 9426",
    "sg:postcode":"31709",
    "sg:province":"GA",
    "wof:name":"JC Pineapple",
    "wof:placetype":"venue"
},
  "geometry": {"coordinates":[-84.233795,32.072226],"type":"Point"}
}