{
  "type": "Feature",
  "properties": {
    "addr:full":"364 Green St NE Gainesville GA 30501",
    "addr:housenumber":"364",
    "addr:postcode":"30501",
    "addr:street":"Green St Ne;Ga",
    "iso:country":"US",
    "sg:address":"364 Green St NE",
    "sg:city":"Gainesville",
    "sg:classifiers":[
        {
            "category":"Government",
            "subcategory":"Post Office",
            "type":"Public Place"
        }
    ],
    "sg:phone":"+1 770 536 7673",
    "sg:postcode":"30501",
    "sg:province":"GA",
    "sg:tags":[
        "postal",
        "us"
    ],
    "wof:name":"US Post Office",
    "wof:placetype":"venue"
},
  "geometry": {"coordinates":[-83.825811,34.3035],"type":"Point"}
}