{
  "type": "Feature",
  "properties": {
    "iso:country":"US",
    "sg:address":"1000 Tradeport Blvd",
    "sg:city":"Atlanta",
    "sg:classifiers":[
        {
            "category":"Manufacturing",
            "subcategory":"Printing",
            "type":"Manufacturing & Wholesale Goods"
        }
    ],
    "sg:phone":"+1 404 881 8323",
    "sg:postcode":"30354",
    "sg:province":"GA",
    "sg:tags":[
        "photography",
        "work",
        "agency",
        "digital"
    ],
    "wof:name":"Artcraft Graphic Productions",
    "wof:placetype":"venue"
},
  "geometry": {"coordinates":[-84.393737,33.650007],"type":"Point"}
}