{
  "type": "Feature",
  "properties": {
    "iso:country":"US",
    "sg:address":"6415 Atlanta Hwy",
    "sg:city":"Alpharetta",
    "sg:classifiers":[
        {
            "category":"Shopping",
            "subcategory":"Music",
            "type":"Retail Goods"
        }
    ],
    "sg:phone":"+1 770 664 7377",
    "sg:postcode":"30004",
    "sg:province":"GA",
    "wof:name":"Discolandia Music & Video",
    "wof:placetype":"venue"
},
  "geometry": {"coordinates":[-84.254273,34.129027],"type":"Point"}
}