{
  "type": "Feature",
  "properties": {
    "addr:full":"1195 Weldstone Ct Atlanta GA 30350",
    "addr:housenumber":"1195",
    "addr:postcode":"30350",
    "addr:street":"Weldstone Ct",
    "iso:country":"US",
    "sg:address":"1195 Weldstone Ct",
    "sg:city":"Atlanta",
    "sg:classifiers":[
        {
            "category":"Wholesale",
            "subcategory":"Office Equipment",
            "type":"Manufacturing & Wholesale Goods"
        }
    ],
    "sg:phone":"+1 770 393 0995",
    "sg:postcode":"30350",
    "sg:province":"GA",
    "sg:tags":[
        "credit",
        "plans-equipment",
        "card",
        "supply"
    ],
    "wof:name":"Sadapa Inc",
    "wof:placetype":"venue"
},
  "geometry": {"coordinates":[-84.347797,33.966498],"type":"Point"}
}