{
  "type": "Feature",
  "properties": {
    "iso:country":"US",
    "sg:address":"1984 Wedgewood Dr",
    "sg:city":"Stone Mountain",
    "sg:classifiers":[
        {
            "category":"Professional",
            "type":"Services"
        }
    ],
    "sg:phone":"+1 770 987 8771",
    "sg:postcode":"30088",
    "sg:province":"GA",
    "wof:name":"Organizational Support Svcs",
    "wof:placetype":"venue"
},
  "geometry": {"coordinates":[-84.189167,33.735348],"type":"Point"}
}