{
  "type": "Feature",
  "properties": {
    "iso:country":"US",
    "sg:address":"26 Bakers Xing",
    "sg:city":"Savannah",
    "sg:classifiers":[
        {
            "category":"Building & Trades",
            "subcategory":"Construction",
            "type":"Services"
        }
    ],
    "sg:phone":"+1 912 353 9721",
    "sg:postcode":"31406",
    "sg:province":"GA",
    "sg:tags":[
        "masonry",
        "contractor"
    ],
    "wof:name":"Scott Crowley Stucco Inc",
    "wof:placetype":"venue"
},
  "geometry": {"coordinates":[-81.069001,31.992568],"type":"Point"}
}