{
  "type": "Feature",
  "properties": {
    "iso:country":"US",
    "sg:address":"994 State Rte 24",
    "sg:city":"Waynesboro",
    "sg:classifiers":[
        {
            "category":"Wholesale",
            "subcategory":"Construction Materials",
            "type":"Manufacturing & Wholesale Goods"
        }
    ],
    "sg:phone":"+1 706 437 8733",
    "sg:postcode":"30830",
    "sg:province":"GA",
    "sg:tags":[
        "timberland",
        "company",
        "timber"
    ],
    "wof:name":"Savannah River Trading Co Inc",
    "wof:placetype":"venue"
},
  "geometry": {"coordinates":[-81.975967,33.066951],"type":"Point"}
}