{
  "type": "Feature",
  "properties": {
    "addr:full":"1318 May St Dalton GA 30721",
    "addr:housenumber":"1318",
    "addr:postcode":"30721",
    "addr:street":"May St",
    "iso:country":"US",
    "sg:address":"1318 May St",
    "sg:city":"Dalton",
    "sg:classifiers":[
        {
            "category":"Manufacturing",
            "subcategory":"Apparel",
            "type":"Manufacturing & Wholesale Goods"
        }
    ],
    "sg:phone":"+1 706 277 3178",
    "sg:postcode":"30721",
    "sg:province":"GA",
    "sg:tags":[
        "pillow"
    ],
    "wof:name":"Pillow Co Inc",
    "wof:placetype":"venue"
},
  "geometry": {"coordinates":[-84.948267,34.763968],"type":"Point"}
}