{
  "type": "Feature",
  "properties": {
    "iso:country":"US",
    "sg:address":"103 W Heritage Blvd S",
    "sg:city":"Byron",
    "sg:classifiers":[
        {
            "category":"Organizations",
            "subcategory":"Religious Organization",
            "type":"Services"
        }
    ],
    "sg:phone":"+1 478 956 5717",
    "sg:postcode":"31008",
    "sg:province":"GA",
    "sg:website":"www.umc.org",
    "wof:name":"Byron United Methodist Church",
    "wof:placetype":"venue"
},
  "geometry": {"coordinates":[-83.75941899999999,32.653645],"type":"Point"}
}