{
  "type": "Feature",
  "properties": {
    "iso:country":"US",
    "sg:address":"11213 State Rte 23",
    "sg:city":"Girard",
    "sg:classifiers":[
        {
            "category":"Retail",
            "subcategory":"Auto Repair",
            "type":"Services"
        }
    ],
    "sg:phone":"+1 478 569 9724",
    "sg:postcode":"30426",
    "sg:province":"GA",
    "sg:tags":[
        "general"
    ],
    "wof:name":"Jenkins Automotive",
    "wof:placetype":"venue"
},
  "geometry": {"coordinates":[-81.71203,33.040477],"type":"Point"}
}