{
  "type": "Feature",
  "properties": {
    "iso:country":"US",
    "sg:address":"3595 Canton Rd",
    "sg:city":"Marietta",
    "sg:classifiers":[
        {
            "category":"Utilities",
            "subcategory":"Mobile Phone",
            "type":"Services"
        }
    ],
    "sg:phone":"+1 770 924 3838",
    "sg:postcode":"30066",
    "sg:province":"GA",
    "sg:tags":[
        "communication",
        "radiotelephone"
    ],
    "wof:name":"All About Wireless",
    "wof:placetype":"venue"
},
  "geometry": {"coordinates":[-84.528408,34.038543],"type":"Point"}
}