{
  "type": "Feature",
  "properties": {
    "addr:full":"2696 Roff Ave Macon GA 31204",
    "addr:housenumber":"2696",
    "addr:postcode":"31204",
    "addr:street":"Roff Ave",
    "iso:country":"US",
    "sg:address":"2696 Roff Ave",
    "sg:city":"Macon",
    "sg:classifiers":[
        {
            "category":"Building & Trades",
            "subcategory":"Construction",
            "type":"Services"
        }
    ],
    "sg:phone":"+1 478 742 4505",
    "sg:postcode":"31204",
    "sg:province":"GA",
    "sg:tags":[
        "acoustical",
        "contractor"
    ],
    "wof:name":"Acousti Inc",
    "wof:placetype":"venue"
},
  "geometry": {"coordinates":[-83.66367200000001,32.841912],"type":"Point"}
}