{
  "type": "Feature",
  "properties": {
    "iso:country":"US",
    "sg:address":"1051 Industrial Blvd",
    "sg:city":"Watkinsville",
    "sg:classifiers":[
        {
            "category":"Wholesale",
            "subcategory":"Non-durable Goods",
            "type":"Manufacturing & Wholesale Goods"
        }
    ],
    "sg:phone":"+1 706 769 6282",
    "sg:postcode":"30642",
    "sg:province":"GA",
    "wof:name":"Trail Top Distribution LLC",
    "wof:placetype":"venue"
},
  "geometry": {"coordinates":[-83.190731,33.56752],"type":"Point"}
}