{
  "type": "Feature",
  "properties": {
    "iso:country":"US",
    "sg:address":"1724 Barrington Cir",
    "sg:city":"Marietta",
    "sg:classifiers":[
        {
            "category":"Local Transit",
            "type":"Transportation"
        }
    ],
    "sg:phone":"+1 770 579 1527",
    "sg:postcode":"30062",
    "sg:province":"GA",
    "sg:tags":[
        "cargo"
    ],
    "wof:name":"Ksp Logistics Inc",
    "wof:placetype":"venue"
},
  "geometry": {"coordinates":[-84.451418,33.99378],"type":"Point"}
}