{
  "type": "Feature",
  "properties": {
    "iso:country":"US",
    "sg:address":"190 Laurel Dr",
    "sg:city":"Clarkesville",
    "sg:classifiers":[
        {
            "category":"Shopping",
            "subcategory":"Florist",
            "type":"Retail Goods"
        }
    ],
    "sg:phone":"+1 706 754 4310",
    "sg:postcode":"30523",
    "sg:province":"GA",
    "wof:name":"Mauney's Florist & Greenhouse",
    "wof:placetype":"venue"
},
  "geometry": {"coordinates":[-83.519334,34.609943],"type":"Point"}
}