{
  "type": "Feature",
  "properties": {
    "addr:full":"319 Canton Rd Cumming GA 30040",
    "addr:housenumber":"319",
    "addr:postcode":"30040",
    "addr:street":"Canton Rd",
    "iso:country":"US",
    "sg:address":"319 Canton Rd",
    "sg:city":"Cumming",
    "sg:classifiers":[
        {
            "category":"Health Services",
            "subcategory":"Doctor",
            "type":"Services"
        }
    ],
    "sg:phone":"+1 770 888 2280",
    "sg:postcode":"30040",
    "sg:province":"GA",
    "sg:tags":[
        "physician",
        "surgeon",
        "neurology",
        "surgeons"
    ],
    "wof:name":"Shenkman, Carl Tyler, MD - Shenkman Carl Tyler MD",
    "wof:placetype":"venue"
},
  "geometry": {"coordinates":[-84.145118,34.2132],"type":"Point"}
}