{
  "type": "Feature",
  "properties": {
    "addr:full":"783 Ode Peppers Rd Winder GA 30680",
    "addr:housenumber":"783",
    "addr:postcode":"30680",
    "addr:street":"Ode Peppers Rd",
    "iso:country":"US",
    "sg:address":"783 Ode Peppers Rd",
    "sg:city":"Winder",
    "sg:classifiers":[
        {
            "category":"Building & Trades",
            "subcategory":"Construction",
            "type":"Services"
        }
    ],
    "sg:phone":"+1 770 586 0576",
    "sg:postcode":"30680",
    "sg:province":"GA",
    "sg:tags":[
        "restoration",
        "cleaning",
        "patio",
        "deck"
    ],
    "wof:name":"Precision Pressure Cleaning",
    "wof:placetype":"venue"
},
  "geometry": {"coordinates":[-83.679948,33.941266],"type":"Point"}
}