{
  "type": "Feature",
  "properties": {
    "addr:full":"1965 Lower Roswell Rd Marietta GA 30068",
    "addr:housenumber":"1965",
    "addr:postcode":"30068",
    "addr:street":"Lower Roswell Rd",
    "iso:country":"US",
    "sg:address":"1965 Lower Roswell Rd",
    "sg:city":"Marietta",
    "sg:classifiers":[
        {
            "category":"Building & Trades",
            "subcategory":"Locksmith",
            "type":"Services"
        }
    ],
    "sg:phone":"+1 888 317 2275",
    "sg:postcode":"30068",
    "sg:province":"GA",
    "sg:tags":[
        "key"
    ],
    "wof:name":"1 & A Emergency Locksmith",
    "wof:placetype":"venue"
},
  "geometry": {"coordinates":[-84.495154,33.950827],"type":"Point"}
}