{
  "type": "Feature",
  "properties": {
    "iso:country":"US",
    "sg:address":"855 Lovvorn Mill Rd",
    "sg:city":"Bowdon",
    "sg:classifiers":[
        {
            "category":"Freight",
            "type":"Transportation"
        }
    ],
    "sg:phone":"+1 770 258 9379",
    "sg:postcode":"30108",
    "sg:province":"GA",
    "sg:tags":[
        "over",
        "cattle",
        "hauling",
        "contract",
        "trucking"
    ],
    "wof:name":"Brent McCaghern Transport",
    "wof:placetype":"venue"
},
  "geometry": {"coordinates":[-85.27146999999999,33.568957],"type":"Point"}
}