{
  "type": "Feature",
  "properties": {
    "addr:full":"2477 Chestnut Log Loop Lithia Springs GA 30122",
    "addr:housenumber":"2477",
    "addr:postcode":"30122",
    "addr:street":"Chestnut Log Loop",
    "iso:country":"US",
    "sg:address":"2477 Chestnut Log Loop",
    "sg:city":"Lithia Springs",
    "sg:classifiers":[
        {
            "category":"Social Services",
            "subcategory":"Child Care",
            "type":"Services"
        }
    ],
    "sg:phone":"+1 770 948 7125",
    "sg:postcode":"30122",
    "sg:province":"GA",
    "wof:name":"Kid's Choice Learning Ctr",
    "wof:placetype":"venue"
},
  "geometry": {"coordinates":[-84.657444,33.749985],"type":"Point"}
}