{
  "type": "Feature",
  "properties": {
    "iso:country":"US",
    "sg:address":"7934 S Main St",
    "sg:city":"Helen",
    "sg:classifiers":[
        {
            "category":"Bars & Pubs",
            "type":"Food & Drink"
        }
    ],
    "sg:menulink":"http://www.allmenus.com/ga/helen/243940-southside-bar--grill/menu/",
    "sg:phone":"+1 706 878 2291",
    "sg:postcode":"30545",
    "sg:province":"GA",
    "sg:tags":[
        "american"
    ],
    "wof:name":"Southside Bar & Grill",
    "wof:placetype":"venue"
},
  "geometry": {"coordinates":[-83.72761199999999,34.700532],"type":"Point"}
}