{
  "type": "Feature",
  "properties": {
    "addr:full":"201 Bell Pl Woodstock GA 30188",
    "addr:housenumber":"201",
    "addr:postcode":"30188",
    "addr:street":"Bell Pl",
    "iso:country":"US",
    "sg:address":"201 Bell Pl",
    "sg:city":"Woodstock",
    "sg:classifiers":[
        {
            "category":"Manufacturing",
            "subcategory":"Tools & Machinery",
            "type":"Manufacturing & Wholesale Goods"
        }
    ],
    "sg:phone":"+1 770 926 3419",
    "sg:postcode":"30188",
    "sg:province":"GA",
    "sg:tags":[
        "adhesive",
        "gluing",
        "equipment"
    ],
    "wof:name":"Crist Co Sure Tack Systems",
    "wof:placetype":"venue"
},
  "geometry": {"coordinates":[-84.50932899999999,34.120708],"type":"Point"}
}