{
  "type": "Feature",
  "properties": {
    "addr:full":"1404 Red Oak Way Winder GA 30680",
    "addr:housenumber":"1404",
    "addr:postcode":"30680",
    "addr:street":"Red Oak Way",
    "iso:country":"US",
    "sg:address":"1404 Red Oak Way",
    "sg:city":"Winder",
    "sg:classifiers":[
        {
            "category":"Building & Trades",
            "subcategory":"Landscaping Services",
            "type":"Services"
        }
    ],
    "sg:phone":"+1 770 725 8771",
    "sg:postcode":"30680",
    "sg:province":"GA",
    "wof:name":"Lawrencvl Tree Experts",
    "wof:placetype":"venue"
},
  "geometry": {"coordinates":[-83.601403,34.013032],"type":"Point"}
}