{
  "type": "Feature",
  "properties": {
    "addr:full":"3243 Kingsdale Dr SW Atlanta GA 30311",
    "addr:housenumber":"3243",
    "addr:postcode":"30311",
    "addr:street":"Kingsdale Dr Sw",
    "iso:country":"US",
    "sg:address":"3243 Kingsdale Dr SW",
    "sg:city":"Atlanta",
    "sg:classifiers":[
        {
            "category":"Manufacturing",
            "subcategory":"Tools & Machinery",
            "type":"Manufacturing & Wholesale Goods"
        }
    ],
    "sg:phone":"+1 404 699 7149",
    "sg:postcode":"30311",
    "sg:province":"GA",
    "sg:tags":[
        "cutting",
        "gear"
    ],
    "wof:name":"Big Fan Gear Inc",
    "wof:placetype":"venue"
},
  "geometry": {"coordinates":[-84.495499,33.722153],"type":"Point"}
}