{
  "type": "Feature",
  "properties": {
    "iso:country":"US",
    "sg:address":"106 N Windward Dr",
    "sg:city":"Saint Simons Island",
    "sg:classifiers":[
        {
            "category":"Retail",
            "subcategory":"Repair Shop",
            "type":"Services"
        }
    ],
    "sg:phone":"+1 912 634 1880",
    "sg:postcode":"31522",
    "sg:province":"GA",
    "wof:name":"Isle Help",
    "wof:placetype":"venue"
},
  "geometry": {"coordinates":[-81.373653,31.202782],"type":"Point"}
}