{
  "type": "Feature",
  "properties": {
    "iso:country":"US",
    "sg:address":"2592 Collins Port Cove",
    "sg:city":"Suwanee",
    "sg:classifiers":[
        {
            "category":"Professional",
            "subcategory":"Business Services",
            "type":"Services"
        }
    ],
    "sg:phone":"+1 770 682 3396",
    "sg:postcode":"30024",
    "sg:province":"GA",
    "sg:tags":[
        "interior",
        "designer"
    ],
    "wof:name":"Aff Services Inc",
    "wof:placetype":"venue"
},
  "geometry": {"coordinates":[-84.02737500000001,34.014387],"type":"Point"}
}