{
  "type": "Feature",
  "properties": {
    "addr:full":"4149 Renfrew Ct SW Atlanta GA 30331",
    "addr:housenumber":"4149",
    "addr:postcode":"30331",
    "addr:street":"Renfrew Ct Sw",
    "iso:country":"US",
    "sg:address":"4149 Renfrew Ct SW",
    "sg:city":"Atlanta",
    "sg:classifiers":[
        {
            "category":"Banks & Credit Unions",
            "subcategory":"Financial Services",
            "type":"Services"
        }
    ],
    "sg:phone":"+1 404 691 8905",
    "sg:postcode":"30331",
    "sg:province":"GA",
    "sg:tags":[
        "investor"
    ],
    "wof:name":"1500 Investment Club LLC",
    "wof:placetype":"venue"
},
  "geometry": {"coordinates":[-84.520853,33.755524],"type":"Point"}
}