{
  "type": "Feature",
  "properties": {
    "addr:full":"700 Westlake Pkwy SW Atlanta GA 30336",
    "addr:housenumber":"700",
    "addr:postcode":"30336",
    "addr:street":"Westlake Pkwy Sw",
    "iso:country":"US",
    "sg:address":"700 Westlake Pkwy SW",
    "sg:city":"Atlanta",
    "sg:classifiers":[
        {
            "category":"Wholesale",
            "subcategory":"Machinery & Supplies",
            "type":"Manufacturing & Wholesale Goods"
        },
        {
            "category":"Wholesale",
            "subcategory":"Medical Equipment & Supplies",
            "type":"Manufacturing & Wholesale Goods"
        }
    ],
    "sg:phone":"+1 404 344 1002",
    "sg:postcode":"30336",
    "sg:province":"GA",
    "sg:tags":[
        "veterinary",
        "veterinarian"
    ],
    "sg:website":"www.mwivet.com",
    "wof:name":"Mwi Veterinary Supply Co",
    "wof:placetype":"venue"
},
  "geometry": {"coordinates":[-84.57924800000001,33.715017],"type":"Point"}
}