{
  "type": "Feature",
  "properties": {
    "iso:country":"US",
    "sg:address":"1040 Perkins Mill Rd",
    "sg:city":"Claxton",
    "sg:classifiers":[
        {
            "category":"Building & Trades",
            "subcategory":"Construction",
            "type":"Services"
        }
    ],
    "sg:phone":"+1 912 739 4093",
    "sg:postcode":"30417",
    "sg:province":"GA",
    "sg:tags":[
        "home",
        "general",
        "commercial",
        "contractor"
    ],
    "wof:name":"Sutton Construction Company",
    "wof:placetype":"venue"
},
  "geometry": {"coordinates":[-81.918791,32.146965],"type":"Point"}
}