{
  "type": "Feature",
  "properties": {
    "iso:country":"US",
    "sg:address":"1349 US Hwy 41",
    "sg:city":"Marietta",
    "sg:classifiers":[
        {
            "category":"Professional",
            "subcategory":"Management & Consulting",
            "type":"Services"
        }
    ],
    "sg:phone":"+1 770 425 3080",
    "sg:postcode":"30060",
    "sg:province":"GA",
    "sg:tags":[
        "business"
    ],
    "sg:website":"www.integratedscience.com",
    "wof:name":"Integrated Science & Tech",
    "wof:placetype":"venue"
},
  "geometry": {"coordinates":[-84.499921,33.91677],"type":"Point"}
}