{
  "type": "Feature",
  "properties": {
    "addr:full":"3087 Deans Bridge Rd Augusta GA 30906",
    "addr:housenumber":"3087",
    "addr:postcode":"30906",
    "addr:street":"Deans Bridge Rd",
    "iso:country":"US",
    "sg:address":"3087 Deans Bridge Rd",
    "sg:city":"Augusta",
    "sg:classifiers":[
        {
            "category":"Restaurant",
            "type":"Food & Drink"
        }
    ],
    "sg:menulink":"http://www.allmenus.com/ga/augusta/180678-wendys/menu/",
    "sg:phone":"+1 706 793 8611",
    "sg:postcode":"30906",
    "sg:province":"GA",
    "sg:tags":[
        "burger",
        "american",
        "soup"
    ],
    "wof:name":"Wendy's",
    "wof:placetype":"venue"
},
  "geometry": {"coordinates":[-82.051501,33.426803],"type":"Point"}
}