{
  "type": "Feature",
  "properties": {
    "iso:country":"US",
    "sg:address":"503 N Washington St",
    "sg:city":"Albany",
    "sg:classifiers":[
        {
            "category":"Building & Trades",
            "subcategory":"Plumbing",
            "type":"Services"
        }
    ],
    "sg:phone":"+1 229 436 9597",
    "sg:postcode":"31701",
    "sg:province":"GA",
    "sg:tags":[
        "heating",
        "contractor"
    ],
    "wof:name":"Pollock Heating & Cooling Co",
    "wof:placetype":"venue"
},
  "geometry": {"coordinates":[-84.151517,31.584583],"type":"Point"}
}