{
  "type": "Feature",
  "properties": {
    "iso:country":"US",
    "sg:address":"3003 Old Alabama Rd",
    "sg:city":"Alpharetta",
    "sg:classifiers":[
        {
            "category":"Shopping",
            "subcategory":"Pharmacy",
            "type":"Retail Goods"
        }
    ],
    "sg:phone":"+1 678 566 3284",
    "sg:postcode":"30022",
    "sg:province":"GA",
    "sg:tags":[
        "drugstore"
    ],
    "wof:name":"Walgreens",
    "wof:placetype":"venue"
},
  "geometry": {"coordinates":[-84.27191500000001,34.02163],"type":"Point"}
}