{
  "type": "Feature",
  "properties": {
    "iso:country":"US",
    "sg:address":"805 Old Ivy Path",
    "sg:city":"Mc Donough",
    "sg:classifiers":[
        {
            "category":"Professional",
            "type":"Services"
        }
    ],
    "sg:phone":"+1 678 432 5740",
    "sg:postcode":"30253",
    "sg:province":"GA",
    "wof:name":"Barry W West",
    "wof:placetype":"venue"
},
  "geometry": {"coordinates":[-84.178017,33.490902],"type":"Point"}
}