{
  "type": "Feature",
  "properties": {
    "iso:country":"US",
    "sg:address":"5137 Jones Cir",
    "sg:city":"Atlanta",
    "sg:classifiers":[
        {
            "category":"Social Services",
            "subcategory":"Child Care",
            "type":"Services"
        }
    ],
    "sg:phone":"+1 770 997 4538",
    "sg:postcode":"30349",
    "sg:province":"GA",
    "sg:tags":[
        "nursery",
        "day"
    ],
    "wof:name":"Taylor's Abcs Inc",
    "wof:placetype":"venue"
},
  "geometry": {"coordinates":[-84.45130399999999,33.615008],"type":"Point"}
}