{
  "type": "Feature",
  "properties": {
    "addr:full":"165 Hidden Hills Ln Athens GA 30605",
    "addr:housenumber":"165",
    "addr:postcode":"30605",
    "addr:street":"Hidden Hills Ln",
    "iso:country":"US",
    "sg:address":"165 Hidden Hills Ln",
    "sg:city":"Athens",
    "sg:classifiers":[
        {
            "category":"Home & Garden",
            "subcategory":"Home Furnishings",
            "type":"Retail Goods"
        }
    ],
    "sg:phone":"+1 706 546 5776",
    "sg:postcode":"30605",
    "sg:province":"GA",
    "wof:name":"Wired & Fired A Pot Playhouse",
    "wof:placetype":"venue"
},
  "geometry": {"coordinates":[-83.357867,33.902955],"type":"Point"}
}