{
  "type": "Feature",
  "properties": {
    "iso:country":"US",
    "sg:address":"35 Lamp Post Ct",
    "sg:city":"Stockbridge",
    "sg:classifiers":[
        {
            "category":"Professional",
            "type":"Services"
        }
    ],
    "sg:phone":"+1 770 474 9888",
    "sg:postcode":"30281",
    "sg:province":"GA",
    "wof:name":"All American Athletic Sports",
    "wof:placetype":"venue"
},
  "geometry": {"coordinates":[-84.229601,33.582504],"type":"Point"}
}