{
  "type": "Feature",
  "properties": {
    "iso:country":"US",
    "sg:address":"11 Horton St",
    "sg:city":"Winder",
    "sg:classifiers":[
        {
            "category":"Real Estate",
            "subcategory":"Real Estate Agent",
            "type":"Services"
        }
    ],
    "sg:phone":"+1 770 867 7495",
    "sg:postcode":"30680",
    "sg:province":"GA",
    "sg:tags":[
        "authorities",
        "housing"
    ],
    "sg:website":"www.winderhousing.org",
    "wof:name":"Winder Housing Authority",
    "wof:placetype":"venue"
},
  "geometry": {"coordinates":[-83.733678,33.993923],"type":"Point"}
}