{
  "type": "Feature",
  "properties": {
    "iso:country":"US",
    "sg:address":"5195 Jimmy Carter Blvd",
    "sg:city":"Norcross",
    "sg:classifiers":[
        {
            "category":"Health Services",
            "subcategory":"Doctor",
            "type":"Services"
        },
        {
            "category":"Health Services",
            "subcategory":"Hospital",
            "type":"Services"
        }
    ],
    "sg:phone":"+1 770 416 0700",
    "sg:postcode":"30093",
    "sg:province":"GA",
    "sg:tags":[
        "nursing",
        "family",
        "consultant",
        "medical",
        "practice",
        "home"
    ],
    "wof:name":"Clinica Medica Hispana II",
    "wof:placetype":"venue"
},
  "geometry": {"coordinates":[-84.203598,33.899601],"type":"Point"}
}