{
  "type": "Feature",
  "properties": {
    "iso:country":"US",
    "sg:address":"925 Elma G Miles Pkwy",
    "sg:city":"Hinesville",
    "sg:classifiers":[
        {
            "category":"Personal",
            "subcategory":"Beauty Salon",
            "type":"Services"
        }
    ],
    "sg:phone":"+1 912 369 6266",
    "sg:postcode":"31313",
    "sg:province":"GA",
    "sg:tags":[
        "shop"
    ],
    "wof:name":"Nina's Upscale Hair Salon",
    "wof:placetype":"venue"
},
  "geometry": {"coordinates":[-81.62609399999999,31.824678],"type":"Point"}
}