{
  "type": "Feature",
  "properties": {
    "addr:full":"3423 Piedmont Rd NE Atlanta GA 30305",
    "addr:housenumber":"3423",
    "addr:postcode":"30305",
    "addr:street":"Piedmont Rd Ne",
    "iso:country":"US",
    "sg:address":"3423 Piedmont Rd NE",
    "sg:city":"Atlanta",
    "sg:classifiers":[
        {
            "category":"Shopping",
            "subcategory":"Hobbies, Toys, & Games",
            "type":"Retail Goods"
        }
    ],
    "sg:phone":"+1 404 816 7767",
    "sg:postcode":"30305",
    "sg:province":"GA",
    "sg:tags":[
        "supply"
    ],
    "wof:name":"Blue Heat Games Inc",
    "wof:placetype":"venue"
},
  "geometry": {"coordinates":[-84.37258199999999,33.84603],"type":"Point"}
}