{
  "type": "Feature",
  "properties": {
    "iso:country":"US",
    "sg:address":"683 N Belair Rd",
    "sg:city":"Evans",
    "sg:classifiers":[
        {
            "category":"Wholesale",
            "subcategory":"Stationery",
            "type":"Manufacturing & Wholesale Goods"
        }
    ],
    "sg:phone":"+1 706 228 7208",
    "sg:postcode":"30809",
    "sg:province":"GA",
    "sg:tags":[
        "mapping"
    ],
    "wof:name":"Geographic Technologies Group",
    "wof:placetype":"venue"
},
  "geometry": {"coordinates":[-82.13037,33.545049],"type":"Point"}
}