{
  "type": "Feature",
  "properties": {
    "iso:country":"US",
    "sg:address":"435 Turkey Creek Rd",
    "sg:city":"Newnan",
    "sg:classifiers":[
        {
            "category":"Food & Beverages",
            "subcategory":"Groceries & Convenience Stores",
            "type":"Retail Goods"
        }
    ],
    "sg:phone":"+1 770 253 5242",
    "sg:postcode":"30263",
    "sg:province":"GA",
    "sg:tags":[
        "station",
        "gasoline"
    ],
    "wof:name":"Wood Woodie Grocery",
    "wof:placetype":"venue"
},
  "geometry": {"coordinates":[-84.77081,33.354231],"type":"Point"}
}