{
  "type": "Feature",
  "properties": {
    "iso:country":"US",
    "sg:address":"3105 Lakepoint Cir",
    "sg:city":"Acworth",
    "sg:classifiers":[
        {
            "category":"Wholesale",
            "subcategory":"Machinery & Supplies",
            "type":"Manufacturing & Wholesale Goods"
        }
    ],
    "sg:phone":"+1 770 595 6647",
    "sg:postcode":"30102",
    "sg:province":"GA",
    "sg:tags":[
        "equipment",
        "irrigation",
        "system"
    ],
    "wof:name":"All Irrigation",
    "wof:placetype":"venue"
},
  "geometry": {"coordinates":[-84.613207,34.113369],"type":"Point"}
}