{
  "type": "Feature",
  "properties": {
    "iso:country":"US",
    "sg:address":"4975 Stone Mountain Hwy Ste 600",
    "sg:city":"Lilburn",
    "sg:classifiers":[
        {
            "category":"Insurance",
            "subcategory":"Insurance Agent",
            "type":"Services"
        },
        {
            "category":"Insurance",
            "subcategory":"Hazard Insurance",
            "type":"Services"
        }
    ],
    "sg:phone":"+1 770 982 3278",
    "sg:postcode":"30047",
    "sg:province":"GA",
    "sg:tags":[
        "consultant",
        "analyst"
    ],
    "sg:website":"http://www.veloxinsurance.com",
    "wof:name":"VELOX INSURANCE",
    "wof:placetype":"venue"
},
  "geometry": {"coordinates":[-84.10080000000001,33.82538],"type":"Point"}
}