{
  "type": "Feature",
  "properties": {
    "iso:country":"US",
    "sg:address":"815 Jett Ferry Manor",
    "sg:city":"Atlanta",
    "sg:classifiers":[
        {
            "category":"Real Estate",
            "subcategory":"Real Estate Agent",
            "type":"Services"
        }
    ],
    "sg:phone":"+1 770 394 5081",
    "sg:postcode":"30350",
    "sg:province":"GA",
    "wof:name":"Arthur J Properties LLC",
    "wof:placetype":"venue"
},
  "geometry": {"coordinates":[-84.290097,33.970461],"type":"Point"}
}