{
  "type": "Feature",
  "properties": {
    "iso:country":"US",
    "sg:address":"742 GA-53",
    "sg:city":"Calhoun",
    "sg:classifiers":[
        {
            "category":"Restaurant",
            "type":"Food & Drink"
        }
    ],
    "sg:menulink":"http://www.allmenus.com/ga/calhoun/95559-ihop/menu/",
    "sg:phone":"+1 706 624 9800",
    "sg:postcode":"30701",
    "sg:province":"GA",
    "sg:tags":[
        "sandwich",
        "salad",
        "burger",
        "soup",
        "american",
        "steakhouse",
        "wrap"
    ],
    "wof:name":"IHOP",
    "wof:placetype":"venue"
},
  "geometry": {"coordinates":[-84.962712,34.497941],"type":"Point"}
}