{
  "type": "Feature",
  "properties": {
    "iso:country":"US",
    "sg:address":"202 7th St N",
    "sg:city":"Cordele",
    "sg:classifiers":[
        {
            "category":"Utilities",
            "subcategory":"Electric",
            "type":"Services"
        }
    ],
    "sg:phone":"+1 229 273 3811",
    "sg:postcode":"31015",
    "sg:province":"GA",
    "sg:tags":[
        "company"
    ],
    "sg:website":"www.crispcountypower.com",
    "wof:name":"Crisp County Power Commission",
    "wof:placetype":"venue"
},
  "geometry": {"coordinates":[-83.782607,31.970053],"type":"Point"}
}