{
  "type": "Feature",
  "properties": {
    "iso:country":"US",
    "sg:address":"2086 J Frank Culpepper Rd",
    "sg:city":"Lake Park",
    "sg:classifiers":[
        {
            "category":"Food & Beverages",
            "subcategory":"Fruits & Vegetables",
            "type":"Retail Goods"
        }
    ],
    "sg:phone":"+1 229 559 3714",
    "sg:postcode":"31636",
    "sg:province":"GA",
    "sg:tags":[
        "produce"
    ],
    "wof:name":"Nature's Quality Fine Ripe",
    "wof:placetype":"venue"
},
  "geometry": {"coordinates":[-83.129222,30.685488],"type":"Point"}
}