{
  "type": "Feature",
  "properties": {
    "addr:full":"3263 River Mist Cove Decatur GA 30034",
    "addr:housenumber":"3263",
    "addr:postcode":"30034",
    "addr:street":"River Mist Cove",
    "iso:country":"US",
    "sg:address":"3263 River Mist Cove",
    "sg:city":"Decatur",
    "sg:classifiers":[
        {
            "category":"Restaurant",
            "type":"Food & Drink"
        }
    ],
    "sg:phone":"+1 404 244 7001",
    "sg:postcode":"30034",
    "sg:province":"GA",
    "wof:name":"Natural Blend Smoothies",
    "wof:placetype":"venue"
},
  "geometry": {"coordinates":[-84.255736,33.672864],"type":"Point"}
}