{
  "type": "Feature",
  "properties": {
    "iso:country":"US",
    "sg:address":"310 W Patten St",
    "sg:city":"La Fayette",
    "sg:classifiers":[
        {
            "category":"Shopping",
            "subcategory":"Books",
            "type":"Retail Goods"
        }
    ],
    "sg:phone":"+1 706 638 3018",
    "sg:postcode":"30728",
    "sg:province":"GA",
    "wof:name":"Book Exchange",
    "wof:placetype":"venue"
},
  "geometry": {"coordinates":[-85.284963,34.704771],"type":"Point"}
}