{
  "type": "Feature",
  "properties": {
    "iso:country":"US",
    "sg:address":"8195 Industrial Pl",
    "sg:city":"Alpharetta",
    "sg:classifiers":[
        {
            "category":"Shopping",
            "subcategory":"Shoes",
            "type":"Retail Goods"
        }
    ],
    "sg:phone":"+1 770 772 7076",
    "sg:postcode":"30004",
    "sg:province":"GA",
    "wof:name":"Brake Shoe Crew LLC",
    "wof:placetype":"venue"
},
  "geometry": {"coordinates":[-84.25297,34.13707],"type":"Point"}
}