{
  "type": "Feature",
  "properties": {
    "addr:full":"469 Reed Creek Pt Hartwell GA 30643",
    "addr:housenumber":"469",
    "addr:postcode":"30643",
    "addr:street":"Reed Creek Pt",
    "iso:country":"US",
    "sg:address":"469 Reed Creek Pt",
    "sg:city":"Hartwell",
    "sg:classifiers":[
        {
            "category":"Real Estate",
            "subcategory":"Real Estate Services",
            "type":"Services"
        },
        {
            "category":"Real Estate",
            "subcategory":"Real Estate Agent",
            "type":"Services"
        }
    ],
    "sg:phone":"+1 706 377 4885",
    "sg:postcode":"30643",
    "sg:province":"GA",
    "sg:tags":[
        "buyer",
        "broker"
    ],
    "wof:name":"Landmark Realty Company",
    "wof:placetype":"venue"
},
  "geometry": {"coordinates":[-82.927492,34.474552],"type":"Point"}
}