{
  "type": "Feature",
  "properties": {
    "iso:country":"US",
    "sg:address":"3845 Conley St",
    "sg:city":"College Park",
    "sg:classifiers":[
        {
            "category":"Retail",
            "subcategory":"Auto Repair",
            "type":"Services"
        }
    ],
    "sg:phone":"+1 404 762 1632",
    "sg:postcode":"30337",
    "sg:province":"GA",
    "sg:tags":[
        "wrecker"
    ],
    "wof:name":"Moody's Wrecker Svc",
    "wof:placetype":"venue"
},
  "geometry": {"coordinates":[-84.45428800000001,33.650909],"type":"Point"}
}