{
  "type": "Feature",
  "properties": {
    "iso:country":"US",
    "sg:address":"620 Stiles Ave",
    "sg:city":"Savannah",
    "sg:classifiers":[
        {
            "category":"Home & Garden",
            "subcategory":"Building Materials",
            "type":"Retail Goods"
        }
    ],
    "sg:phone":"+1 912 232 6155",
    "sg:postcode":"31415",
    "sg:province":"GA",
    "sg:tags":[
        "mixed",
        "concrete"
    ],
    "wof:name":"Lafarge Building Materials Inc",
    "wof:placetype":"venue"
},
  "geometry": {"coordinates":[-81.112551,32.074131],"type":"Point"}
}