{
  "type": "Feature",
  "properties": {
    "addr:full":"38 Spring St Newnan GA 30263",
    "addr:housenumber":"38",
    "addr:postcode":"30263",
    "addr:street":"Spring St",
    "iso:country":"US",
    "sg:address":"38 Spring St",
    "sg:city":"Newnan",
    "sg:classifiers":[
        {
            "category":"Professional",
            "subcategory":"Business Services",
            "type":"Services"
        }
    ],
    "sg:phone":"+1 770 251 6118",
    "sg:postcode":"30263",
    "sg:province":"GA",
    "wof:name":"Partners In Faith Inc",
    "wof:placetype":"venue"
},
  "geometry": {"coordinates":[-84.80155999999999,33.373809],"type":"Point"}
}