{
  "type": "Feature",
  "properties": {
    "addr:full":"4688 Gilhams Rd Roswell GA 30075",
    "addr:housenumber":"4688",
    "addr:postcode":"30075",
    "addr:street":"Gilhams Rd",
    "iso:country":"US",
    "sg:address":"4688 Gilhams Rd",
    "sg:city":"Roswell",
    "sg:classifiers":[
        {
            "category":"Banks & Credit Unions",
            "subcategory":"Financial Services",
            "type":"Services"
        }
    ],
    "sg:phone":"+1 770 993 4787",
    "sg:postcode":"30075",
    "sg:province":"GA",
    "sg:tags":[
        "investor"
    ],
    "wof:name":"Pcd Investment Company Inc",
    "wof:placetype":"venue"
},
  "geometry": {"coordinates":[-84.414056,34.044702],"type":"Point"}
}