{
  "type": "Feature",
  "properties": {
    "addr:full":"123 W Putnam Ferry Rd Woodstock GA 30189",
    "addr:housenumber":"123",
    "addr:postcode":"30189",
    "addr:street":"W Putnam Ferry Rd",
    "iso:country":"US",
    "sg:address":"123 W Putnam Ferry Rd",
    "sg:city":"Woodstock",
    "sg:classifiers":[
        {
            "category":"Building & Trades",
            "subcategory":"Construction",
            "type":"Services"
        }
    ],
    "sg:phone":"+1 770 560 7046",
    "sg:postcode":"30189",
    "sg:province":"GA",
    "sg:tags":[
        "residential"
    ],
    "wof:name":"Affordble Rnvtons Cnstructions",
    "wof:placetype":"venue"
},
  "geometry": {"coordinates":[-84.56362900000001,34.123851],"type":"Point"}
}