{
  "type": "Feature",
  "properties": {
    "iso:country":"US",
    "sg:address":"5925 Bretton Woods Dr",
    "sg:city":"Lithonia",
    "sg:classifiers":[
        {
            "category":"Building & Trades",
            "subcategory":"Construction",
            "type":"Services"
        }
    ],
    "sg:phone":"+1 770 482 8252",
    "sg:postcode":"30058",
    "sg:province":"GA",
    "sg:tags":[
        "residential"
    ],
    "wof:name":"T C C",
    "wof:placetype":"venue"
},
  "geometry": {"coordinates":[-84.146472,33.738781],"type":"Point"}
}