{
  "type": "Feature",
  "properties": {
    "addr:full":"1165 Allgood Rd Marietta GA 30062",
    "addr:housenumber":"1165",
    "addr:postcode":"30062",
    "addr:street":"Allgood Rd",
    "iso:country":"US",
    "sg:address":"1165 Allgood Rd",
    "sg:city":"Marietta",
    "sg:classifiers":[
        {
            "category":"Recreation",
            "type":"Entertainment"
        }
    ],
    "sg:phone":"+1 770 977 9797",
    "sg:postcode":"30062",
    "sg:province":"GA",
    "wof:name":"Southern Athletics Inc",
    "wof:placetype":"venue"
},
  "geometry": {"coordinates":[-84.52242,33.977504],"type":"Point"}
}