{
  "type": "Feature",
  "properties": {
    "iso:country":"US",
    "sg:address":"1400 Long Bewick St",
    "sg:city":"Waycross",
    "sg:classifiers":[
        {
            "category":"Retail",
            "subcategory":"Repair Shop",
            "type":"Services"
        }
    ],
    "sg:phone":"+1 912 283 5869",
    "sg:postcode":"31501",
    "sg:province":"GA",
    "wof:name":"Dixie Diesel Repair",
    "wof:placetype":"venue"
},
  "geometry": {"coordinates":[-82.36913699999999,31.220965],"type":"Point"}
}