{
  "type": "Feature",
  "properties": {
    "addr:full":"1594 Emory Rd NE Atlanta GA 30306",
    "addr:housenumber":"1594",
    "addr:postcode":"30306",
    "addr:street":"Emory Rd Ne",
    "iso:country":"US",
    "sg:address":"1594 Emory Rd NE",
    "sg:city":"Atlanta",
    "sg:classifiers":[
        {
            "category":"Professional",
            "subcategory":"Business Services",
            "type":"Services"
        }
    ],
    "sg:phone":"+1 404 378 3522",
    "sg:postcode":"30306",
    "sg:province":"GA",
    "wof:name":"ME Design Studio",
    "wof:placetype":"venue"
},
  "geometry": {"coordinates":[-84.32889900000001,33.789979],"type":"Point"}
}