{
  "type": "Feature",
  "properties": {
    "addr:full":"144 8th St Augusta GA 30901",
    "addr:housenumber":"144",
    "addr:postcode":"30901",
    "addr:street":"8Th St",
    "iso:country":"US",
    "sg:address":"144 8th St",
    "sg:city":"Augusta",
    "sg:classifiers":[
        {
            "category":"Restaurant",
            "type":"Food & Drink"
        }
    ],
    "sg:phone":"+1 706 724 9457",
    "sg:postcode":"30901",
    "sg:province":"GA",
    "wof:name":"Joe's Underground Cafe",
    "wof:placetype":"venue"
},
  "geometry": {"coordinates":[-81.964956,33.475893],"type":"Point"}
}