{
  "type": "Feature",
  "properties": {
    "iso:country":"US",
    "sg:address":"6655 Malvin Dr",
    "sg:city":"Austell",
    "sg:classifiers":[
        {
            "category":"Building & Trades",
            "subcategory":"Construction",
            "type":"Services"
        }
    ],
    "sg:phone":"+1 770 941 9457",
    "sg:postcode":"30168",
    "sg:province":"GA",
    "sg:tags":[
        "restoration",
        "cleaning",
        "patio",
        "deck"
    ],
    "wof:name":"Noojin Pressure Washing",
    "wof:placetype":"venue"
},
  "geometry": {"coordinates":[-84.601455,33.791024],"type":"Point"}
}