{
  "type": "Feature",
  "properties": {
    "addr:full":"506 S Pentz St Dalton GA 30720",
    "addr:housenumber":"506",
    "addr:postcode":"30720",
    "addr:street":"S Pentz St",
    "iso:country":"US",
    "sg:address":"506 S Pentz St",
    "sg:city":"Dalton",
    "sg:classifiers":[
        {
            "category":"Organizations",
            "subcategory":"Religious Organization",
            "type":"Services"
        }
    ],
    "sg:phone":"+1 706 226 5535",
    "sg:postcode":"30720",
    "sg:province":"GA",
    "wof:name":"Liberty Baptist Church",
    "wof:placetype":"venue"
},
  "geometry": {"coordinates":[-84.969189,34.767269],"type":"Point"}
}