{
  "type": "Feature",
  "properties": {
    "addr:full":"1204 Greenvale Rd Albany GA 31707",
    "addr:housenumber":"1204",
    "addr:postcode":"31707",
    "addr:street":"Greenvale Rd",
    "iso:country":"US",
    "sg:address":"1204 Greenvale Rd",
    "sg:city":"Albany",
    "sg:classifiers":[
        {
            "category":"Building & Trades",
            "subcategory":"Construction",
            "type":"Services"
        }
    ],
    "sg:phone":"+1 229 903 8136",
    "sg:postcode":"31707",
    "sg:province":"GA",
    "wof:name":"Fiber Optic Services",
    "wof:placetype":"venue"
},
  "geometry": {"coordinates":[-84.19048600000001,31.578922],"type":"Point"}
}