{
  "type": "Feature",
  "properties": {
    "addr:full":"66 Mount Orum Ln Waverly GA 31565",
    "addr:housenumber":"66",
    "addr:postcode":"31565",
    "addr:street":"Mount Orum Ln",
    "iso:country":"US",
    "sg:address":"66 Mount Orum Ln",
    "sg:city":"Waverly",
    "sg:classifiers":[
        {
            "category":"Place Of Worship",
            "subcategory":"Church",
            "type":"Public Place"
        },
        {
            "category":"Place Of Worship",
            "type":"Public Place"
        }
    ],
    "sg:phone":"+1 912 265 9416",
    "sg:postcode":"31565",
    "sg:province":"GA",
    "sg:tags":[
        "churches-baptist-general",
        "churches-baptist"
    ],
    "wof:name":"Mt Orum Baptist Church",
    "wof:placetype":"venue"
},
  "geometry": {"coordinates":[-81.648568,31.105673],"type":"Point"}
}