{
  "type": "Feature",
  "properties": {
    "iso:country":"US",
    "sg:address":"105 S Newton St",
    "sg:city":"Claxton",
    "sg:classifiers":[
        {
            "category":"Insurance",
            "subcategory":"Insurance Agent",
            "type":"Services"
        }
    ],
    "sg:phone":"+1 912 739 1268",
    "sg:postcode":"30417",
    "sg:province":"GA",
    "wof:name":"Barnes Bootsy Insurance Agency",
    "wof:placetype":"venue"
},
  "geometry": {"coordinates":[-81.90494700000001,32.158897],"type":"Point"}
}