{
  "type": "Feature",
  "properties": {
    "addr:full":"4266 Roswell Rd Apt K4 Atlanta GA 30342",
    "addr:housenumber":"4266",
    "addr:postcode":"30342",
    "addr:street":"Roswell Rd Apt K4",
    "iso:country":"US",
    "sg:address":"4266 Roswell Rd Apt K4",
    "sg:city":"Atlanta",
    "sg:classifiers":[
        {
            "category":"Professional",
            "type":"Services"
        }
    ],
    "sg:phone":"+1 404 847 9296",
    "sg:postcode":"30342",
    "sg:province":"GA",
    "sg:tags":[
        "motion",
        "technician",
        "picture"
    ],
    "wof:name":"Fitch Film Flashes",
    "wof:placetype":"venue"
},
  "geometry": {"coordinates":[-84.381039,33.871141],"type":"Point"}
}