{
  "type": "Feature",
  "properties": {
    "iso:country":"US",
    "sg:address":"1397 Fairview Rd NE",
    "sg:city":"Atlanta",
    "sg:classifiers":[
        {
            "category":"Professional",
            "subcategory":"Management & Consulting",
            "type":"Services"
        }
    ],
    "sg:phone":"+1 404 731 7974",
    "sg:postcode":"30306",
    "sg:province":"GA",
    "sg:tags":[
        "consultant"
    ],
    "wof:name":"The Red Cedar Group",
    "wof:placetype":"venue"
},
  "geometry": {"coordinates":[-84.34163700000001,33.772839],"type":"Point"}
}