{
  "type": "Feature",
  "properties": {
    "addr:full":"2931 Bent Creek Run NW Kennesaw GA 30152",
    "addr:housenumber":"2931",
    "addr:postcode":"30152",
    "addr:street":"Bent Creek Run Nw",
    "iso:country":"US",
    "sg:address":"2931 Bent Creek Run NW",
    "sg:city":"Kennesaw",
    "sg:classifiers":[
        {
            "category":"Building & Trades",
            "subcategory":"Construction",
            "type":"Services"
        }
    ],
    "sg:phone":"+1 678 402 5029",
    "sg:postcode":"30152",
    "sg:province":"GA",
    "sg:tags":[
        "roofing",
        "contractor"
    ],
    "wof:name":"BRS Roofing and Construction",
    "wof:placetype":"venue"
},
  "geometry": {"coordinates":[-84.635468,34.022613],"type":"Point"}
}