{
  "type": "Feature",
  "properties": {
    "iso:country":"US",
    "sg:address":"1079 Brotherton Ln",
    "sg:city":"Chickamauga",
    "sg:classifiers":[
        {
            "category":"Manufacturing",
            "subcategory":"Buildings",
            "type":"Manufacturing & Wholesale Goods"
        },
        {
            "category":"Building & Trades",
            "subcategory":"Construction",
            "type":"Services"
        }
    ],
    "sg:phone":"+1 706 375 2252",
    "sg:postcode":"30707",
    "sg:province":"GA",
    "sg:tags":[
        "home",
        "builder",
        "contractor"
    ],
    "wof:name":"Hentz Construction",
    "wof:placetype":"venue"
},
  "geometry": {"coordinates":[-85.342336,34.824217],"type":"Point"}
}