{
  "type": "Feature",
  "properties": {
    "iso:country":"US",
    "sg:address":"3807 River North Dr",
    "sg:city":"Gainesville",
    "sg:classifiers":[
        {
            "category":"Building & Trades",
            "subcategory":"Construction",
            "type":"Services"
        }
    ],
    "sg:phone":"+1 770 532 0436",
    "sg:postcode":"30506",
    "sg:province":"GA",
    "sg:tags":[
        "residential",
        "nonresidential"
    ],
    "wof:name":"Belladonna Contracting Service",
    "wof:placetype":"venue"
},
  "geometry": {"coordinates":[-83.796233,34.390246],"type":"Point"}
}