{
  "type": "Feature",
  "properties": {
    "iso:country":"US",
    "sg:address":"3115 Buford Hwy NE",
    "sg:city":"Atlanta",
    "sg:classifiers":[
        {
            "category":"Restaurant",
            "type":"Food & Drink"
        }
    ],
    "sg:phone":"+1 404 728 0807",
    "sg:postcode":"30329",
    "sg:province":"GA",
    "sg:tags":[
        "mexican"
    ],
    "wof:name":"El Tropicana",
    "wof:placetype":"venue"
},
  "geometry": {"coordinates":[-84.333592,33.838655],"type":"Point"}
}