{
  "type": "Feature",
  "properties": {
    "iso:country":"US",
    "sg:address":"1604 12th St",
    "sg:city":"Columbus",
    "sg:classifiers":[
        {
            "category":"Health Services",
            "subcategory":"Doctor",
            "type":"Services"
        }
    ],
    "sg:phone":"+1 706 327 0337",
    "sg:postcode":"31906",
    "sg:province":"GA",
    "sg:tags":[
        "dentist"
    ],
    "wof:name":"Joe Arnold DDS",
    "wof:placetype":"venue"
},
  "geometry": {"coordinates":[-84.967455,32.468802],"type":"Point"}
}