{
  "type": "Feature",
  "properties": {
    "addr:full":"204 Adamson Sq Carrollton GA 30117",
    "addr:housenumber":"204",
    "addr:postcode":"30117",
    "addr:street":"Adamson Sq",
    "iso:country":"US",
    "sg:address":"204 Adamson Sq",
    "sg:city":"Carrollton",
    "sg:classifiers":[
        {
            "category":"Professional",
            "subcategory":"Detective & Security Services",
            "type":"Services"
        }
    ],
    "sg:phone":"+1 770 214 2131",
    "sg:postcode":"30117",
    "sg:province":"GA",
    "sg:tags":[
        "information",
        "bureau"
    ],
    "wof:name":"First Step Therapeutic Service",
    "wof:placetype":"venue"
},
  "geometry": {"coordinates":[-85.065579,33.575992],"type":"Point"}
}