{
  "type": "Feature",
  "properties": {
    "iso:country":"US",
    "sg:address":"7203 Hodgson Memorial Dr",
    "sg:city":"Savannah",
    "sg:classifiers":[
        {
            "category":"Health Services",
            "subcategory":"Optometrist",
            "type":"Services"
        }
    ],
    "sg:phone":"+1 912 352 9356",
    "sg:postcode":"31406",
    "sg:province":"GA",
    "sg:tags":[
        "optical",
        "good"
    ],
    "wof:name":"Nease Dr Corley H",
    "wof:placetype":"venue"
},
  "geometry": {"coordinates":[-81.109489,32.008484],"type":"Point"}
}