{
  "type": "Feature",
  "properties": {
    "iso:country":"US",
    "sg:address":"130 College St",
    "sg:city":"Cuthbert",
    "sg:classifiers":[
        {
            "category":"Retail",
            "subcategory":"Repair Shop",
            "type":"Services"
        }
    ],
    "sg:phone":"+1 229 732 2294",
    "sg:postcode":"31790",
    "sg:province":"GA",
    "sg:tags":[
        "satellite",
        "system"
    ],
    "wof:name":"Charlie's Satellite Systems",
    "wof:placetype":"venue"
},
  "geometry": {"coordinates":[-83.634007,31.665854],"type":"Point"}
}