{
  "type": "Feature",
  "properties": {
    "iso:country":"US",
    "sg:address":"228 Main St",
    "sg:city":"Hiawassee",
    "sg:classifiers":[
        {
            "category":"Shopping",
            "subcategory":"Used Merchandise",
            "type":"Retail Goods"
        }
    ],
    "sg:phone":"+1 706 896 0010",
    "sg:postcode":"30547",
    "sg:province":"GA",
    "sg:tags":[
        "pawnbroker"
    ],
    "wof:name":"Southland Pawn & Jewelry",
    "wof:placetype":"venue"
},
  "geometry": {"coordinates":[-83.49503300000001,34.335054],"type":"Point"}
}