{
  "type": "Feature",
  "properties": {
    "iso:country":"US",
    "sg:address":"2110 Powers Ferry Rd SE Ste 270",
    "sg:city":"Atlanta",
    "sg:classifiers":[
        {
            "category":"Professional",
            "subcategory":"Lawyer & Legal Services",
            "type":"Services"
        }
    ],
    "sg:phone":"+1 770 951 5444",
    "sg:postcode":"30339",
    "sg:province":"GA",
    "sg:tags":[
        "litigation"
    ],
    "wof:name":"Whiteman Hamilton & Hasner PC",
    "wof:placetype":"venue"
},
  "geometry": {"coordinates":[-84.4552,33.9025],"type":"Point"}
}