{
  "type": "Feature",
  "properties": {
    "addr:full":"10305 Rillridge Ct Alpharetta GA 30022",
    "addr:postcode":"10305;30022",
    "addr:street":"Rillridge Ct",
    "iso:country":"US",
    "sg:address":"10305 Rillridge Ct",
    "sg:city":"Alpharetta",
    "sg:classifiers":[
        {
            "category":"Real Estate",
            "subcategory":"Real Estate Agent",
            "type":"Services"
        }
    ],
    "sg:phone":"+1 770 777 9047",
    "sg:postcode":"30022",
    "sg:province":"GA",
    "wof:name":"Cardelino Real Estate Inc",
    "wof:placetype":"venue"
},
  "geometry": {"coordinates":[-84.266239,34.032407],"type":"Point"}
}