{
  "type": "Feature",
  "properties": {
    "addr:full":"9140 Turner Rd Jonesboro GA 30236",
    "addr:housenumber":"9140",
    "addr:postcode":"30236",
    "addr:street":"Turner Rd",
    "iso:country":"US",
    "sg:address":"9140 Turner Rd",
    "sg:city":"Jonesboro",
    "sg:classifiers":[
        {
            "category":"Wholesale",
            "subcategory":"Motor Vehicles",
            "type":"Manufacturing & Wholesale Goods"
        }
    ],
    "sg:phone":"+1 770 472 5610",
    "sg:postcode":"30236",
    "sg:province":"GA",
    "wof:name":"Tara Auto Auction Inc",
    "wof:placetype":"venue"
},
  "geometry": {"coordinates":[-84.345842,33.505654],"type":"Point"}
}