{
  "type": "Feature",
  "properties": {
    "addr:full":"200 Technology Ct SE Smyrna GA 30082",
    "addr:housenumber":"200",
    "addr:postcode":"30082",
    "addr:street":"Technology Ct Se",
    "iso:country":"US",
    "sg:address":"200 Technology Ct SE",
    "sg:city":"Smyrna",
    "sg:classifiers":[
        {
            "category":"Home & Garden",
            "subcategory":"Carpets & Floor Coverings",
            "type":"Retail Goods"
        }
    ],
    "sg:phone":"+1 770 874 7600",
    "sg:postcode":"30082",
    "sg:province":"GA",
    "sg:tags":[
        "flooring"
    ],
    "sg:website":"www.floorcoveringsinternational.com",
    "wof:name":"Floor Coverings International",
    "wof:placetype":"venue"
},
  "geometry": {"coordinates":[-84.499073,33.827162],"type":"Point"}
}