{
  "type": "Feature",
  "properties": {
    "iso:country":"US",
    "sg:address":"6180 Clyattville Lake Park Rd",
    "sg:city":"Valdosta",
    "sg:classifiers":[
        {
            "category":"Shopping",
            "subcategory":"Shoes",
            "type":"Retail Goods"
        }
    ],
    "sg:phone":"+1 229 559 1422",
    "sg:postcode":"31601",
    "sg:province":"GA",
    "wof:name":"Powder Buster",
    "wof:placetype":"venue"
},
  "geometry": {"coordinates":[-83.264036,30.684951],"type":"Point"}
}