{
  "type": "Feature",
  "properties": {
    "iso:country":"US",
    "sg:address":"4460 Annistown Rd SW",
    "sg:city":"Lithonia",
    "sg:classifiers":[
        {
            "category":"Organizations",
            "subcategory":"Religious Organization",
            "type":"Services"
        }
    ],
    "sg:phone":"+1 678 344 7212",
    "sg:postcode":"30058",
    "sg:province":"GA",
    "wof:name":"First Slavic Christian Church",
    "wof:placetype":"venue"
},
  "geometry": {"coordinates":[-84.123199,33.729698],"type":"Point"}
}