{
  "type": "Feature",
  "properties": {
    "iso:country":"US",
    "sg:address":"3150 Verona Ave",
    "sg:city":"Buford",
    "sg:classifiers":[
        {
            "category":"Building & Trades",
            "subcategory":"Construction",
            "type":"Services"
        }
    ],
    "sg:phone":"+1 770 536 4490",
    "sg:postcode":"30518",
    "sg:province":"GA",
    "sg:tags":[
        "fabricator",
        "metal"
    ],
    "wof:name":"Allison Dump Bodies & Trailers",
    "wof:placetype":"venue"
},
  "geometry": {"coordinates":[-83.971806,34.129806],"type":"Point"}
}