{
  "type": "Feature",
  "properties": {
    "addr:full":"2605 Hamilton Rd NE Buford GA 30518",
    "addr:housenumber":"2605",
    "addr:postcode":"30518",
    "addr:street":"Hamilton Rd Ne",
    "iso:country":"US",
    "sg:address":"2605 Hamilton Rd NE",
    "sg:city":"Buford",
    "sg:classifiers":[
        {
            "category":"Shopping",
            "subcategory":"Pharmacy",
            "type":"Retail Goods"
        }
    ],
    "sg:phone":"+1 678 546 5352",
    "sg:postcode":"30518",
    "sg:province":"GA",
    "sg:tags":[
        "drugstore"
    ],
    "sg:website":"www.cvs.com",
    "wof:name":"Cvs Pharmacy",
    "wof:placetype":"venue"
},
  "geometry": {"coordinates":[-83.955584,34.09335],"type":"Point"}
}