{
  "type": "Feature",
  "properties": {
    "addr:full":"65 State St Commerce GA 30530",
    "addr:housenumber":"65",
    "addr:postcode":"30530",
    "addr:street":"State St",
    "iso:country":"US",
    "sg:address":"65 State St",
    "sg:city":"Commerce",
    "sg:classifiers":[
        {
            "category":"Personal",
            "subcategory":"Beauty Salon",
            "type":"Services"
        }
    ],
    "sg:phone":"+1 706 335 4722",
    "sg:postcode":"30530",
    "sg:province":"GA",
    "sg:tags":[
        "shop"
    ],
    "wof:name":"New Image Family Styling Ctr",
    "wof:placetype":"venue"
},
  "geometry": {"coordinates":[-83.456323,34.203941],"type":"Point"}
}