{
  "type": "Feature",
  "properties": {
    "addr:full":"3309 Clairmont Rd Columbus GA 31906",
    "addr:housenumber":"3309",
    "addr:postcode":"31906",
    "addr:street":"Clairmont Rd",
    "iso:country":"US",
    "sg:address":"3309 Clairmont Rd",
    "sg:city":"Columbus",
    "sg:classifiers":[
        {
            "category":"Cinema",
            "subcategory":"Movie Rental",
            "type":"Entertainment"
        }
    ],
    "sg:phone":"+1 706 566 8033",
    "sg:postcode":"31906",
    "sg:province":"GA",
    "sg:tags":[
        "motion",
        "picture",
        "distributor",
        "film",
        "exchange"
    ],
    "wof:name":"Wolverine Productions",
    "wof:placetype":"venue"
},
  "geometry": {"coordinates":[-84.94384100000001,32.471899],"type":"Point"}
}