{
  "type": "Feature",
  "properties": {
    "addr:full":"336 E 3rd St Jackson GA 30233",
    "addr:housenumber":"336",
    "addr:postcode":"30233",
    "addr:street":"E 3Rd St",
    "iso:country":"US",
    "sg:address":"336 E 3rd St",
    "sg:city":"Jackson",
    "sg:classifiers":[
        {
            "category":"Health Services",
            "subcategory":"Optometrist",
            "type":"Services"
        }
    ],
    "sg:phone":"+1 770 775 3719",
    "sg:postcode":"30233",
    "sg:province":"GA",
    "wof:name":"Robert H Pinckney OD",
    "wof:placetype":"venue"
},
  "geometry": {"coordinates":[-83.964217,33.29437],"type":"Point"}
}