{
  "type": "Feature",
  "properties": {
    "addr:full":"5885 Cumming Hwy Buford GA 30518",
    "addr:housenumber":"5885",
    "addr:postcode":"30518",
    "addr:street":"Cumming Hwy",
    "iso:country":"US",
    "sg:address":"5885 Cumming Hwy",
    "sg:city":"Buford",
    "sg:classifiers":[
        {
            "category":"Building & Trades",
            "subcategory":"Cleaning & Sanitation",
            "type":"Services"
        }
    ],
    "sg:phone":"+1 770 569 5299",
    "sg:postcode":"30518",
    "sg:province":"GA",
    "sg:tags":[
        "janitor",
        "maintenance"
    ],
    "wof:name":"Professional Cleaning Services",
    "wof:placetype":"venue"
},
  "geometry": {"coordinates":[-84.075931,34.117179],"type":"Point"}
}