{
  "type": "Feature",
  "properties": {
    "iso:country":"US",
    "sg:address":"401 W Franklin St",
    "sg:city":"Sylvester",
    "sg:classifiers":[
        {
            "category":"Government",
            "subcategory":"Post Office",
            "type":"Public Place"
        }
    ],
    "sg:phone":"+1 229 776 2072",
    "sg:postcode":"31791",
    "sg:province":"GA",
    "sg:tags":[
        "postal",
        "us"
    ],
    "wof:name":"Sylvester Main Office",
    "wof:placetype":"venue"
},
  "geometry": {"coordinates":[-83.84286,31.530849],"type":"Point"}
}