{
  "type": "Feature",
  "properties": {
    "iso:country":"US",
    "sg:address":"3242 Summerchase Cir",
    "sg:city":"Augusta",
    "sg:classifiers":[
        {
            "category":"Banks & Credit Unions",
            "subcategory":"Bank",
            "type":"Services"
        }
    ],
    "sg:phone":"+1 706 733 0343",
    "sg:postcode":"30909",
    "sg:province":"GA",
    "wof:name":"Capital Overseas Bank LTD",
    "wof:placetype":"venue"
},
  "geometry": {"coordinates":[-82.055511,33.468362],"type":"Point"}
}