{
  "type": "Feature",
  "properties": {
    "addr:full":"720 Hambrick Dr SW Lilburn GA 30047",
    "addr:housenumber":"720",
    "addr:postcode":"30047",
    "addr:street":"Hambrick Dr Sw",
    "iso:country":"US",
    "sg:address":"720 Hambrick Dr SW",
    "sg:city":"Lilburn",
    "sg:classifiers":[
        {
            "category":"Manufacturing",
            "subcategory":"Tools & Machinery",
            "type":"Manufacturing & Wholesale Goods"
        }
    ],
    "sg:phone":"+1 770 925 1004",
    "sg:postcode":"30047",
    "sg:province":"GA",
    "sg:tags":[
        "industrial",
        "electrical",
        "apparatus",
        "mfg"
    ],
    "wof:name":"Global Consultants Inc",
    "wof:placetype":"venue"
},
  "geometry": {"coordinates":[-84.12966400000001,33.862086],"type":"Point"}
}