{
  "type": "Feature",
  "properties": {
    "iso:country":"US",
    "sg:address":"218 Glade Rd",
    "sg:city":"Jackson",
    "sg:classifiers":[
        {
            "category":"Professional",
            "subcategory":"Secretarial Services",
            "type":"Services"
        }
    ],
    "sg:phone":"+1 770 228 3654",
    "sg:postcode":"30233",
    "sg:province":"GA",
    "sg:tags":[
        "reporting"
    ],
    "wof:name":"Benson & Assoc Court Reporter",
    "wof:placetype":"venue"
},
  "geometry": {"coordinates":[-84.091853,33.25368],"type":"Point"}
}