{
  "type": "Feature",
  "properties": {
    "addr:full":"2151 Clay Rd Austell GA 30106",
    "addr:housenumber":"2151",
    "addr:postcode":"30106",
    "addr:street":"Clay Rd",
    "iso:country":"US",
    "sg:address":"2151 Clay Rd",
    "sg:city":"Austell",
    "sg:classifiers":[
        {
            "category":"Building & Trades",
            "subcategory":"Construction",
            "type":"Services"
        }
    ],
    "sg:phone":"+1 770 948 8576",
    "sg:postcode":"30106",
    "sg:province":"GA",
    "sg:tags":[
        "painter"
    ],
    "wof:name":"JLT Svc",
    "wof:placetype":"venue"
},
  "geometry": {"coordinates":[-84.616249,33.833207],"type":"Point"}
}