{
  "type": "Feature",
  "properties": {
    "iso:country":"US",
    "sg:address":"101 N Cherokee St",
    "sg:city":"La Fayette",
    "sg:classifiers":[
        {
            "category":"Insurance",
            "subcategory":"Insurance Agent",
            "type":"Services"
        }
    ],
    "sg:phone":"+1 706 638 3237",
    "sg:postcode":"30728",
    "sg:province":"GA",
    "wof:name":"Walker County Farm Bureau",
    "wof:placetype":"venue"
},
  "geometry": {"coordinates":[-85.283164,34.705939],"type":"Point"}
}