{
  "type": "Feature",
  "properties": {
    "addr:full":"71 Sherwood Ln Marietta GA 30067",
    "addr:housenumber":"71",
    "addr:postcode":"30067",
    "addr:street":"Sherwood Ln",
    "iso:country":"US",
    "sg:address":"71 Sherwood Ln",
    "sg:city":"Marietta",
    "sg:classifiers":[
        {
            "category":"Professional",
            "subcategory":"Business Services",
            "type":"Services"
        }
    ],
    "sg:phone":"+1 770 951 2111",
    "sg:postcode":"30067",
    "sg:province":"GA",
    "wof:name":"Ross Mattison Inc",
    "wof:placetype":"venue"
},
  "geometry": {"coordinates":[-84.411799,33.947671],"type":"Point"}
}