{
  "type": "Feature",
  "properties": {
    "iso:country":"US",
    "sg:address":"1504 Dawson Rd",
    "sg:city":"Albany",
    "sg:classifiers":[
        {
            "category":"Restaurant",
            "type":"Food & Drink"
        }
    ],
    "sg:phone":"+1 229 436 8444",
    "sg:postcode":"31707",
    "sg:province":"GA",
    "wof:name":"Morgan's",
    "wof:placetype":"venue"
},
  "geometry": {"coordinates":[-84.188355,31.589206],"type":"Point"}
}