{
  "type": "Feature",
  "properties": {
    "addr:full":"211 Main St S Tifton GA 31794",
    "addr:housenumber":"211",
    "addr:postcode":"31794",
    "addr:street":"Main St S",
    "iso:country":"US",
    "sg:address":"211 Main St S",
    "sg:city":"Tifton",
    "sg:classifiers":[
        {
            "category":"Restaurant",
            "type":"Food & Drink"
        }
    ],
    "sg:phone":"+1 229 382 1011",
    "sg:postcode":"31794",
    "sg:province":"GA",
    "sg:tags":[
        "eating"
    ],
    "wof:name":"LA Cabana Mexican Restaurant",
    "wof:placetype":"venue"
},
  "geometry": {"coordinates":[-83.50977899999999,31.452983],"type":"Point"}
}