{
  "type": "Feature",
  "properties": {
    "iso:country":"US",
    "sg:address":"2830 Clearview Pl",
    "sg:city":"Doraville",
    "sg:classifiers":[
        {
            "category":"Taxi",
            "type":"Transportation"
        }
    ],
    "sg:phone":"+1 770 448 1060",
    "sg:postcode":"30340",
    "sg:province":"GA",
    "sg:tags":[
        "taxicab"
    ],
    "wof:name":"Express Taxicab Co",
    "wof:placetype":"venue"
},
  "geometry": {"coordinates":[-84.26828399999999,33.898541],"type":"Point"}
}