{
  "type": "Feature",
  "properties": {
    "addr:full":"2904 N Patterson St Valdosta GA 31602",
    "addr:housenumber":"2904",
    "addr:postcode":"31602",
    "addr:street":"N Patterson St",
    "iso:country":"US",
    "sg:address":"2904 N Patterson St",
    "sg:city":"Valdosta",
    "sg:classifiers":[
        {
            "category":"Food & Beverages",
            "subcategory":"Specialty",
            "type":"Retail Goods"
        }
    ],
    "sg:phone":"+1 229 245 9246",
    "sg:postcode":"31602",
    "sg:province":"GA",
    "sg:tags":[
        "health",
        "diet"
    ],
    "wof:name":"Herb Shop Unlimited Inc",
    "wof:placetype":"venue"
},
  "geometry": {"coordinates":[-83.291487,30.873918],"type":"Point"}
}