{
  "type": "Feature",
  "properties": {
    "addr:full":"400 Ernest W Barrett Pkwy Kennesaw GA 30144",
    "addr:housenumber":"400",
    "addr:postcode":"30144",
    "addr:street":"Ernest W Barrett Pkwy",
    "iso:country":"US",
    "sg:address":"400 Ernest W Barrett Pkwy",
    "sg:city":"Kennesaw",
    "sg:classifiers":[
        {
            "category":"Shopping",
            "subcategory":"Shoes",
            "type":"Retail Goods"
        }
    ],
    "sg:phone":"+1 770 428 6102",
    "sg:postcode":"30144",
    "sg:province":"GA",
    "sg:tags":[
        "shoe",
        "store"
    ],
    "wof:name":"Stride Rite",
    "wof:placetype":"venue"
},
  "geometry": {"coordinates":[-84.56442199999999,34.011907],"type":"Point"}
}