{
  "type": "Feature",
  "properties": {
    "addr:full":"131 N Tusten St Elberton GA 30635",
    "addr:housenumber":"131",
    "addr:postcode":"30635",
    "addr:street":"N Tusten St",
    "iso:country":"US",
    "sg:address":"131 N Tusten St",
    "sg:city":"Elberton",
    "sg:classifiers":[
        {
            "category":"Wholesale",
            "subcategory":"Construction Materials",
            "type":"Manufacturing & Wholesale Goods"
        }
    ],
    "sg:phone":"+1 706 283 4448",
    "sg:postcode":"30635",
    "sg:province":"GA",
    "sg:tags":[
        "granite"
    ],
    "wof:name":"Granite World LLC",
    "wof:placetype":"venue"
},
  "geometry": {"coordinates":[-82.85858,34.11361],"type":"Point"}
}