{
  "type": "Feature",
  "properties": {
    "iso:country":"US",
    "sg:address":"132 Old Social Cir",
    "sg:city":"Social Circle",
    "sg:classifiers":[
        {
            "category":"Shopping",
            "subcategory":"Gifts & Souvenirs",
            "type":"Retail Goods"
        }
    ],
    "sg:phone":"+1 770 464 0670",
    "sg:postcode":"30025",
    "sg:province":"GA",
    "sg:tags":[
        "shop"
    ],
    "wof:name":"Gabriel's",
    "wof:placetype":"venue"
},
  "geometry": {"coordinates":[-83.717687,33.607811],"type":"Point"}
}