{
  "type": "Feature",
  "properties": {
    "addr:full":"4426 Hugh Howell Rd Tucker GA 30084",
    "addr:housenumber":"4426",
    "addr:postcode":"30084",
    "addr:street":"Hugh Howell Rd",
    "iso:country":"US",
    "sg:address":"4426 Hugh Howell Rd",
    "sg:city":"Tucker",
    "sg:classifiers":[
        {
            "category":"Freight",
            "type":"Transportation"
        }
    ],
    "sg:phone":"+1 404 396 0216",
    "sg:postcode":"30084",
    "sg:province":"GA",
    "sg:tags":[
        "trucking"
    ],
    "wof:name":"Naton Inc",
    "wof:placetype":"venue"
},
  "geometry": {"coordinates":[-84.206723,33.850585],"type":"Point"}
}