{
  "type": "Feature",
  "properties": {
    "iso:country":"US",
    "sg:address":"499 E Tennessee Ave",
    "sg:city":"Mc Caysville",
    "sg:classifiers":[
        {
            "category":"Home & Garden",
            "subcategory":"Home Furnishings",
            "type":"Retail Goods"
        }
    ],
    "sg:phone":"+1 706 492 2288",
    "sg:postcode":"30555",
    "sg:province":"GA",
    "wof:name":"Miracles Upholstery",
    "wof:placetype":"venue"
},
  "geometry": {"coordinates":[-84.362526,34.985399],"type":"Point"}
}