{
  "type": "Feature",
  "properties": {
    "addr:full":"1705 Cleveland Hwy Gainesville GA 30501",
    "addr:housenumber":"1705",
    "addr:postcode":"30501",
    "addr:street":"Cleveland Hwy",
    "iso:country":"US",
    "sg:address":"1705 Cleveland Hwy",
    "sg:city":"Gainesville",
    "sg:classifiers":[
        {
            "category":"Shopping",
            "subcategory":"Department Store",
            "type":"Retail Goods"
        }
    ],
    "sg:phone":"+1 770 532 7933",
    "sg:postcode":"30501",
    "sg:province":"GA",
    "sg:tags":[
        "shop"
    ],
    "wof:name":"K V Party & More",
    "wof:placetype":"venue"
},
  "geometry": {"coordinates":[-83.81361,34.328413],"type":"Point"}
}