{
  "type": "Feature",
  "properties": {
    "iso:country":"US",
    "sg:address":"2704 Bellingrath Dr",
    "sg:city":"Augusta",
    "sg:classifiers":[
        {
            "category":"Real Estate",
            "subcategory":"Real Estate Agent",
            "type":"Services"
        }
    ],
    "sg:phone":"+1 706 495 3850",
    "sg:postcode":"30906",
    "sg:province":"GA",
    "wof:name":"Metes & Bounds",
    "wof:placetype":"venue"
},
  "geometry": {"coordinates":[-82.06216000000001,33.404988],"type":"Point"}
}