{
  "type": "Feature",
  "properties": {
    "iso:country":"US",
    "sg:address":"1564 Herrington Rd # 1324",
    "sg:city":"Lawrenceville",
    "sg:classifiers":[
        {
            "category":"Building & Trades",
            "subcategory":"Construction",
            "type":"Services"
        }
    ],
    "sg:phone":"+1 678 523 5300",
    "sg:postcode":"30043",
    "sg:province":"GA",
    "sg:tags":[
        "wallcoverings-installation",
        "wallpaper"
    ],
    "wof:name":"Wc Pro Wallcovering",
    "wof:placetype":"venue"
},
  "geometry": {"coordinates":[-84.078957,33.964226],"type":"Point"}
}