{
  "type": "Feature",
  "properties": {
    "addr:full":"4143 Red Laurel Way SW Snellville GA 30039",
    "addr:housenumber":"4143",
    "addr:postcode":"30039",
    "addr:street":"Red Laurel Way Sw",
    "iso:country":"US",
    "sg:address":"4143 Red Laurel Way SW",
    "sg:city":"Snellville",
    "sg:classifiers":[
        {
            "category":"Professional",
            "subcategory":"Computer Services",
            "type":"Services"
        }
    ],
    "sg:phone":"+1 770 309 7870",
    "sg:postcode":"30039",
    "sg:province":"GA",
    "sg:tags":[
        "prepackaged",
        "software"
    ],
    "wof:name":"Hixoxih Software",
    "wof:placetype":"venue"
},
  "geometry": {"coordinates":[-84.04608500000001,33.79456],"type":"Point"}
}