{
  "type": "Feature",
  "properties": {
    "iso:country":"US",
    "sg:address":"895 Garden Walk Blvd",
    "sg:city":"Atlanta",
    "sg:classifiers":[
        {
            "category":"Structure",
            "subcategory":"Warehouse",
            "type":"Public Place"
        },
        {
            "category":"Retail",
            "subcategory":"Storage",
            "type":"Services"
        }
    ],
    "sg:phone":"+1 770 997 0880",
    "sg:postcode":"30349",
    "sg:province":"GA",
    "sg:tags":[
        "self",
        "warehouses-public-commercial"
    ],
    "wof:name":"Uac Logistics",
    "wof:placetype":"venue"
},
  "geometry": {"coordinates":[-84.419172,33.596011],"type":"Point"}
}