{
  "type": "Feature",
  "properties": {
    "iso:country":"US",
    "sg:address":"101 N Main St",
    "sg:city":"Swainsboro",
    "sg:classifiers":[
        {
            "category":"Government",
            "subcategory":"Office",
            "type":"Public Place"
        }
    ],
    "sg:phone":"+1 478 289 2617",
    "sg:postcode":"30401",
    "sg:province":"GA",
    "sg:tags":[
        "admin",
        "affairs",
        "state",
        "administration"
    ],
    "wof:name":"Veterans Service Georgia Dept",
    "wof:placetype":"venue"
},
  "geometry": {"coordinates":[-82.334711,32.59814],"type":"Point"}
}