{
  "type": "Feature",
  "properties": {
    "addr:full":"4325 1st Ave Tucker GA 30084",
    "addr:housenumber":"4325",
    "addr:postcode":"30084",
    "addr:street":"1St Ave",
    "iso:country":"US",
    "sg:address":"4325 1st Ave",
    "sg:city":"Tucker",
    "sg:phone":"+1 770 934 2768",
    "sg:postcode":"30084",
    "sg:province":"GA",
    "sg:website":"http://www.usps.com",
    "wof:name":"USPS - United States Post Office - Tucker Post Office",
    "wof:placetype":"venue"
},
  "geometry": {"coordinates":[-84.21174999999999,33.854423],"type":"Point"}
}