{
  "type": "Feature",
  "properties": {
    "iso:country":"US",
    "sg:address":"82 Peachtree St SW",
    "sg:city":"Atlanta",
    "sg:classifiers":[
        {
            "category":"Shopping",
            "subcategory":"Jewelry",
            "type":"Retail Goods"
        }
    ],
    "sg:phone":"+1 404 524 7612",
    "sg:postcode":"30303",
    "sg:province":"GA",
    "sg:tags":[
        "jeweler"
    ],
    "wof:name":"Solid Gold",
    "wof:placetype":"venue"
},
  "geometry": {"coordinates":[-84.391578,33.752794],"type":"Point"}
}