{
  "type": "Feature",
  "properties": {
    "addr:full":"3891 Manor House Dr Marietta GA 30062",
    "addr:housenumber":"3891",
    "addr:postcode":"30062",
    "addr:street":"Manor House Dr",
    "iso:country":"US",
    "sg:address":"3891 Manor House Dr",
    "sg:city":"Marietta",
    "sg:classifiers":[
        {
            "category":"Health Services",
            "subcategory":"Nursing And Care Facility",
            "type":"Services"
        }
    ],
    "sg:phone":"+1 770 552 1646",
    "sg:postcode":"30062",
    "sg:province":"GA",
    "sg:tags":[
        "organization",
        "membership"
    ],
    "wof:name":"Christmas Manor",
    "wof:placetype":"venue"
},
  "geometry": {"coordinates":[-84.43981599999999,34.02927],"type":"Point"}
}