{
  "type": "Feature",
  "properties": {
    "iso:country":"US",
    "sg:address":"4881 Timber Ridge Rd",
    "sg:city":"Marietta",
    "sg:classifiers":[
        {
            "category":"Building & Trades",
            "subcategory":"Plumbing",
            "type":"Services"
        }
    ],
    "sg:phone":"+1 770 998 6685",
    "sg:postcode":"30068",
    "sg:province":"GA",
    "sg:tags":[
        "contractor"
    ],
    "wof:name":"Bennett Plumbing Company",
    "wof:placetype":"venue"
},
  "geometry": {"coordinates":[-84.403841,33.993851],"type":"Point"}
}