{
  "type": "Feature",
  "properties": {
    "addr:full":"201 Bay St Thomasville GA 31792",
    "addr:housenumber":"201",
    "addr:postcode":"31792",
    "addr:street":"Bay St",
    "iso:country":"US",
    "sg:address":"201 Bay St",
    "sg:city":"Thomasville",
    "sg:classifiers":[
        {
            "category":"Personal",
            "subcategory":"Beauty Salon",
            "type":"Services"
        }
    ],
    "sg:phone":"+1 229 226 1795",
    "sg:postcode":"31792",
    "sg:province":"GA",
    "wof:name":"Taylor's Beauty Shop",
    "wof:placetype":"venue"
},
  "geometry": {"coordinates":[-83.995091,30.840503],"type":"Point"}
}