{
  "type": "Feature",
  "properties": {
    "iso:country":"US",
    "sg:address":"405 Greystone Ter",
    "sg:city":"Athens",
    "sg:classifiers":[
        {
            "category":"Professional",
            "subcategory":"Management & Consulting",
            "type":"Services"
        }
    ],
    "sg:phone":"+1 706 549 2568",
    "sg:postcode":"30606",
    "sg:province":"GA",
    "sg:tags":[
        "business"
    ],
    "wof:name":"Basics Consulting Group",
    "wof:placetype":"venue"
},
  "geometry": {"coordinates":[-83.410792,33.920581],"type":"Point"}
}