{
  "type": "Feature",
  "properties": {
    "iso:country":"US",
    "sg:address":"1136 Cleveland Ave Ste 212",
    "sg:city":"Atlanta",
    "sg:classifiers":[
        {
            "category":"Health Services",
            "subcategory":"Doctor",
            "type":"Services"
        }
    ],
    "sg:phone":"+1 404 761 3525",
    "sg:postcode":"30344",
    "sg:province":"GA",
    "wof:name":"Akbik Fawaz MD",
    "wof:placetype":"venue"
},
  "geometry": {"coordinates":[-84.457703,33.679199],"type":"Point"}
}