{
  "type": "Feature",
  "properties": {
    "iso:country":"US",
    "sg:address":"545 Veterans Memorial Pkwy SW",
    "sg:city":"Mableton",
    "sg:classifiers":[
        {
            "category":"Retail",
            "subcategory":"Auto Repair",
            "type":"Services"
        }
    ],
    "sg:phone":"+1 770 739 7225",
    "sg:postcode":"30126",
    "sg:province":"GA",
    "sg:tags":[
        "repairing",
        "automobile",
        "automotive"
    ],
    "wof:name":"Chavez Automotive Inc",
    "wof:placetype":"venue"
},
  "geometry": {"coordinates":[-84.56823300000001,33.81665],"type":"Point"}
}