{
  "type": "Feature",
  "properties": {
    "iso:country":"US",
    "sg:address":"1261 Parkwood Chase NW",
    "sg:city":"Acworth",
    "sg:classifiers":[
        {
            "category":"Insurance",
            "subcategory":"Insurance Agent",
            "type":"Services"
        }
    ],
    "sg:phone":"+1 770 977 1699",
    "sg:postcode":"30102",
    "sg:province":"GA",
    "wof:name":"Mitchell Benefits Inc",
    "wof:placetype":"venue"
},
  "geometry": {"coordinates":[-84.583254,34.064596],"type":"Point"}
}