{
  "type": "Feature",
  "properties": {
    "addr:full":"2093 Lake Park Dr SE Smyrna GA 30080",
    "addr:housenumber":"2093",
    "addr:postcode":"30080",
    "addr:street":"Lake Park Dr Se",
    "iso:country":"US",
    "sg:address":"2093 Lake Park Dr SE",
    "sg:city":"Smyrna",
    "sg:classifiers":[
        {
            "category":"Shopping",
            "subcategory":"Computers & Home Electronics",
            "type":"Retail Goods"
        }
    ],
    "sg:phone":"+1 770 435 3599",
    "sg:postcode":"30080",
    "sg:province":"GA",
    "sg:tags":[
        "renting",
        "equipment",
        "leasing"
    ],
    "sg:website":"http://www.rentalsystems.com",
    "wof:name":"Rental Systems, Inc.",
    "wof:placetype":"venue"
},
  "geometry": {"coordinates":[-84.490036,33.895777],"type":"Point"}
}