{
  "type": "Feature",
  "properties": {
    "addr:full":"2940 Chipmunk Trl SE Marietta GA 30067",
    "addr:housenumber":"2940",
    "addr:postcode":"30067",
    "addr:street":"Chipmunk Trl Se",
    "iso:country":"US",
    "sg:address":"2940 Chipmunk Trl SE",
    "sg:city":"Marietta",
    "sg:classifiers":[
        {
            "category":"Arts & Performance",
            "subcategory":"Music",
            "type":"Entertainment"
        }
    ],
    "sg:phone":"+1 770 984 0476",
    "sg:postcode":"30067",
    "sg:province":"GA",
    "sg:tags":[
        "jockey",
        "disc"
    ],
    "wof:name":"K C Cass",
    "wof:placetype":"venue"
},
  "geometry": {"coordinates":[-84.473522,33.929912],"type":"Point"}
}