{
  "type": "Feature",
  "properties": {
    "iso:country":"US",
    "sg:address":"6113 Buford Hwy NE",
    "sg:city":"Atlanta",
    "sg:classifiers":[
        {
            "category":"Shopping",
            "subcategory":"Clothing, Apparel, & Fashions",
            "type":"Retail Goods"
        }
    ],
    "sg:phone":"+1 770 457 3006",
    "sg:postcode":"30340",
    "sg:province":"GA",
    "sg:tags":[
        "accessory",
        "clothing",
        "women's"
    ],
    "wof:name":"Jenny's Place",
    "wof:placetype":"venue"
},
  "geometry": {"coordinates":[-84.258303,33.917096],"type":"Point"}
}