{
  "type": "Feature",
  "properties": {
    "addr:full":"3006 Miriam Ct Decatur GA 30032",
    "addr:housenumber":"3006",
    "addr:postcode":"30032",
    "addr:street":"Miriam Ct",
    "iso:country":"US",
    "sg:address":"3006 Miriam Ct",
    "sg:city":"Decatur",
    "sg:classifiers":[
        {
            "category":"Organizations",
            "subcategory":"Membership Organization",
            "type":"Services"
        }
    ],
    "sg:phone":"+1 404 284 5690",
    "sg:postcode":"30032",
    "sg:province":"GA",
    "wof:name":"Toney Neighborhood Association",
    "wof:placetype":"venue"
},
  "geometry": {"coordinates":[-84.267267,33.726923],"type":"Point"}
}