{
  "type": "Feature",
  "properties": {
    "addr:full":"1161 Mclendon Dr Decatur GA 30033",
    "addr:housenumber":"1161",
    "addr:postcode":"30033",
    "addr:street":"Mclendon Dr",
    "iso:country":"US",
    "sg:address":"1161 Mclendon Dr",
    "sg:city":"Decatur",
    "sg:classifiers":[
        {
            "category":"Personal",
            "subcategory":"Beauty Salon",
            "type":"Services"
        }
    ],
    "sg:phone":"+1 770 493 1315",
    "sg:postcode":"30033",
    "sg:province":"GA",
    "sg:tags":[
        "cosmetics-wholesale",
        "manufacturer"
    ],
    "wof:name":"Loreal Maybelline Jr",
    "wof:placetype":"venue"
},
  "geometry": {"coordinates":[-84.26064100000001,33.813684],"type":"Point"}
}