{
  "type": "Feature",
  "properties": {
    "iso:country":"US",
    "sg:address":"680 14th St NW",
    "sg:city":"Atlanta",
    "sg:classifiers":[
        {
            "category":"Professional",
            "subcategory":"Computer Services",
            "type":"Services"
        }
    ],
    "sg:phone":"+1 404 892 1688",
    "sg:postcode":"30318",
    "sg:province":"GA",
    "sg:tags":[
        "graphics"
    ],
    "wof:name":"Meteor",
    "wof:placetype":"venue"
},
  "geometry": {"coordinates":[-84.409668,33.785875],"type":"Point"}
}