{
  "type": "Feature",
  "properties": {
    "addr:full":"1270 Kelly Nelson Rd Lawrenceville GA 30043",
    "addr:housenumber":"1270",
    "addr:postcode":"30043",
    "addr:street":"Kelly Nelson Rd",
    "iso:country":"US",
    "sg:address":"1270 Kelly Nelson Rd",
    "sg:city":"Lawrenceville",
    "sg:classifiers":[
        {
            "category":"Retail",
            "subcategory":"Repair Shop",
            "type":"Services"
        }
    ],
    "sg:phone":"+1 678 985 0553",
    "sg:postcode":"30043",
    "sg:province":"GA",
    "wof:name":"Campos Cleaning",
    "wof:placetype":"venue"
},
  "geometry": {"coordinates":[-83.95907800000001,33.999615],"type":"Point"}
}