{
  "type": "Feature",
  "properties": {
    "iso:country":"US",
    "sg:address":"1107 Memorial Dr",
    "sg:city":"Dalton",
    "sg:classifiers":[
        {
            "category":"Health Services",
            "subcategory":"Doctor",
            "type":"Services"
        }
    ],
    "sg:phone":"+1 706 277 9393",
    "sg:postcode":"30720",
    "sg:province":"GA",
    "wof:name":"Bill Chung",
    "wof:placetype":"venue"
},
  "geometry": {"coordinates":[-84.981281,34.789041],"type":"Point"}
}