{
  "type": "Feature",
  "properties": {
    "iso:country":"US",
    "sg:address":"3155 Presidential Drive",
    "sg:city":"Atlanta",
    "sg:classifiers":[
        {
            "category":"Building & Trades",
            "subcategory":"Construction",
            "type":"Services"
        }
    ],
    "sg:phone":"+1 770 454 6308",
    "sg:postcode":"30340",
    "sg:province":"GA",
    "sg:tags":[
        "contractor"
    ],
    "wof:name":"Price E C General Contractors",
    "wof:placetype":"venue"
},
  "geometry": {"coordinates":[-84.259468,33.886771],"type":"Point"}
}