{
  "type": "Feature",
  "properties": {
    "iso:country":"US",
    "sg:address":"5593 New Peachtree Road",
    "sg:city":"Atlanta",
    "sg:classifiers":[
        {
            "category":"Restaurant",
            "type":"Food & Drink"
        }
    ],
    "sg:phone":"+1 770 986 8884",
    "sg:postcode":"30341",
    "sg:province":"GA",
    "wof:name":"Taste Good Noodles Products",
    "wof:placetype":"venue"
},
  "geometry": {"coordinates":[-84.293425,33.894627],"type":"Point"}
}