{
  "type": "Feature",
  "properties": {
    "addr:full":"14 Statesboro Mall Statesboro GA 30458",
    "addr:housenumber":"14",
    "addr:postcode":"30458",
    "addr:street":"Mall",
    "iso:country":"US",
    "sg:address":"14 Statesboro Mall",
    "sg:city":"Statesboro",
    "sg:classifiers":[
        {
            "category":"Food & Beverages",
            "subcategory":"Specialty",
            "type":"Retail Goods"
        },
        {
            "category":"Food & Beverages",
            "subcategory":"Fruits & Vegetables",
            "type":"Retail Goods"
        },
        {
            "category":"Shopping",
            "subcategory":"Pharmacy",
            "type":"Retail Goods"
        }
    ],
    "sg:phone":"+1 912 764 2456",
    "sg:postcode":"30458",
    "sg:province":"GA",
    "sg:tags":[
        "product",
        "wellness",
        "vitamin",
        "diet",
        "supplement",
        "health",
        "herb"
    ],
    "sg:website":"http://www.gnc.com",
    "wof:name":"GNC",
    "wof:placetype":"venue"
},
  "geometry": {"coordinates":[-81.76380899999999,32.409035],"type":"Point"}
}