{
  "type": "Feature",
  "properties": {
    "addr:full":"276 Main St Hiram GA 30141",
    "addr:housenumber":"276",
    "addr:postcode":"30141",
    "addr:street":"Main St",
    "iso:country":"US",
    "sg:address":"276 Main St",
    "sg:city":"Hiram",
    "sg:classifiers":[
        {
            "category":"Building & Trades",
            "subcategory":"Locksmith",
            "type":"Services"
        }
    ],
    "sg:phone":"+1 877 784 2710",
    "sg:postcode":"30141",
    "sg:province":"GA",
    "sg:tags":[
        "key"
    ],
    "wof:name":"1 & A Emergency Locksmith",
    "wof:placetype":"venue"
},
  "geometry": {"coordinates":[-84.755461,33.875344],"type":"Point"}
}