{
  "type": "Feature",
  "properties": {
    "iso:country":"US",
    "sg:address":"118 Brentwood Ln",
    "sg:city":"Woodstock",
    "sg:classifiers":[
        {
            "category":"Building & Trades",
            "subcategory":"Landscaping Services",
            "type":"Services"
        }
    ],
    "sg:phone":"+1 770 924 2137",
    "sg:postcode":"30188",
    "sg:province":"GA",
    "wof:name":"Bella Botanica Designs Inc",
    "wof:placetype":"venue"
},
  "geometry": {"coordinates":[-84.49323099999999,34.091608],"type":"Point"}
}