{
  "type": "Feature",
  "properties": {
    "iso:country":"US",
    "sg:address":"5968 Roswell Rd",
    "sg:city":"Atlanta",
    "sg:classifiers":[
        {
            "category":"Shopping",
            "type":"Retail Goods"
        }
    ],
    "sg:phone":"+1 404 851 0064",
    "sg:postcode":"30328",
    "sg:province":"GA",
    "sg:tags":[
        "picture",
        "frame"
    ],
    "wof:name":"Art Trends",
    "wof:placetype":"venue"
},
  "geometry": {"coordinates":[-84.379113,33.916601],"type":"Point"}
}