{
  "type": "Feature",
  "properties": {
    "addr:full":"6084 Riverdale Road Atlanta GA 30349",
    "addr:housenumber":"6084",
    "addr:postcode":"30349",
    "addr:street":"Riverdale Road",
    "iso:country":"US",
    "sg:address":"6084 Riverdale Road",
    "sg:city":"Atlanta",
    "sg:classifiers":[
        {
            "category":"Organizations",
            "subcategory":"Religious Organization",
            "type":"Services"
        }
    ],
    "sg:phone":"+1 770 994 0033",
    "sg:postcode":"30349",
    "sg:province":"GA",
    "wof:name":"Faith Walk Ministries",
    "wof:placetype":"venue"
},
  "geometry": {"coordinates":[-84.42385299999999,33.588386],"type":"Point"}
}