{
  "type": "Feature",
  "properties": {
    "iso:country":"US",
    "sg:address":"180 Hickman Dr",
    "sg:city":"Athens",
    "sg:classifiers":[
        {
            "category":"Manufacturing",
            "subcategory":"Buildings",
            "type":"Manufacturing & Wholesale Goods"
        },
        {
            "category":"Building & Trades",
            "subcategory":"Construction",
            "type":"Services"
        }
    ],
    "sg:phone":"+1 706 613 0906",
    "sg:postcode":"30601",
    "sg:province":"GA",
    "sg:tags":[
        "home",
        "builder",
        "contractor"
    ],
    "wof:name":"Bethel Church Homes",
    "wof:placetype":"venue"
},
  "geometry": {"coordinates":[-83.378263,33.962998],"type":"Point"}
}