{
  "type": "Feature",
  "properties": {
    "addr:full":"3022 Veterans Memorial Pkwy SW Lithia Springs GA 30168",
    "addr:housenumber":"3022",
    "addr:postcode":"30168",
    "addr:street":"Veterans Memorial Pkwy Sw",
    "iso:country":"US",
    "sg:address":"3022 Veterans Memorial Pkwy SW",
    "sg:city":"Lithia Springs",
    "sg:classifiers":[
        {
            "category":"Personal",
            "subcategory":"Beauty Salon",
            "type":"Services"
        }
    ],
    "sg:phone":"+1 770 819 3333",
    "sg:postcode":"30168",
    "sg:province":"GA",
    "wof:name":"Zoe's Hair",
    "wof:placetype":"venue"
},
  "geometry": {"coordinates":[-84.636383,33.808547],"type":"Point"}
}