{
  "type": "Feature",
  "properties": {
    "addr:full":"950 W Peachtree St NW Ste 275A Atlanta GA 30309",
    "addr:housenumber":"950",
    "addr:postcode":"30309",
    "addr:street":"W Peachtree St Nw Ste 275A",
    "iso:country":"US",
    "sg:address":"950 W Peachtree St NW Ste 275A",
    "sg:city":"Atlanta",
    "sg:phone":"+1 404 249 7377",
    "sg:postcode":"30309",
    "sg:province":"GA",
    "sg:website":"http://atlanta.citysearch.com/profile/external/47189482/atlanta_ga/hollywood_tans_midtown.html?publisher=yellowpages&reference_id=1&placement=ypwebsitemip",
    "wof:name":"Hollywood Tans - Midtown",
    "wof:placetype":"venue"
},
  "geometry": {"coordinates":[-84.387372,33.780543],"type":"Point"}
}