{
  "type": "Feature",
  "properties": {
    "iso:country":"US",
    "sg:address":"726 4th St NW",
    "sg:city":"Moultrie",
    "sg:classifiers":[
        {
            "category":"Personal",
            "subcategory":"Beauty Salon",
            "type":"Services"
        }
    ],
    "sg:phone":"+1 229 890 3709",
    "sg:postcode":"31768",
    "sg:province":"GA",
    "sg:tags":[
        "shop"
    ],
    "wof:name":"Unique Styles",
    "wof:placetype":"venue"
},
  "geometry": {"coordinates":[-83.793521,31.188701],"type":"Point"}
}