{
  "type": "Feature",
  "properties": {
    "iso:country":"US",
    "sg:address":"1301 Melody Ln",
    "sg:city":"Valdosta",
    "sg:classifiers":[
        {
            "category":"Insurance",
            "subcategory":"Insurance Agent",
            "type":"Services"
        },
        {
            "category":"Insurance",
            "subcategory":"Hazard Insurance",
            "type":"Services"
        }
    ],
    "sg:phone":"+1 229 245 9911",
    "sg:postcode":"31601",
    "sg:province":"GA",
    "sg:tags":[
        "auto",
        "recreational",
        "motorcycle",
        "vehicle",
        "marine",
        "boat"
    ],
    "wof:name":"Bauman Insurance Agency",
    "wof:placetype":"venue"
},
  "geometry": {"coordinates":[-83.304001,30.844139],"type":"Point"}
}