{
  "type": "Feature",
  "properties": {
    "iso:country":"US",
    "sg:address":"240 Brook Valley Dr",
    "sg:city":"Roswell",
    "sg:classifiers":[
        {
            "category":"Insurance",
            "subcategory":"Insurance Agent",
            "type":"Services"
        }
    ],
    "sg:phone":"+1 770 645 2500",
    "sg:postcode":"30075",
    "sg:province":"GA",
    "wof:name":"Kansas City Life Insurance Co",
    "wof:placetype":"venue"
},
  "geometry": {"coordinates":[-84.373288,34.058517],"type":"Point"}
}