{
  "type": "Feature",
  "properties": {
    "addr:full":"5442 Middle Ground Rd Louisville GA 30434",
    "addr:housenumber":"5442",
    "addr:postcode":"30434",
    "addr:street":"Middle Ground Rd",
    "iso:country":"US",
    "sg:address":"5442 Middle Ground Rd",
    "sg:city":"Louisville",
    "sg:classifiers":[
        {
            "category":"Communications",
            "subcategory":"Radio Station",
            "type":"Services"
        }
    ],
    "sg:phone":"+1 478 625 7248",
    "sg:postcode":"30434",
    "sg:province":"GA",
    "sg:tags":[
        "company",
        "broadcasting"
    ],
    "wof:name":"WPEH",
    "wof:placetype":"venue"
},
  "geometry": {"coordinates":[-82.38960299999999,33.016954],"type":"Point"}
}