{
  "type": "Feature",
  "properties": {
    "addr:full":"4261 Woodland Brook Dr Atlanta GA 30339",
    "addr:housenumber":"4261",
    "addr:postcode":"30339",
    "addr:street":"Woodland Brook Dr",
    "iso:country":"US",
    "sg:address":"4261 Woodland Brook Dr",
    "sg:city":"Atlanta",
    "sg:classifiers":[
        {
            "category":"Professional",
            "type":"Services"
        }
    ],
    "sg:phone":"+1 404 355 6738",
    "sg:postcode":"30339",
    "sg:province":"GA",
    "wof:name":"Towery Corp Inc",
    "wof:placetype":"venue"
},
  "geometry": {"coordinates":[-84.469863,33.849647],"type":"Point"}
}