{
  "type": "Feature",
  "properties": {
    "addr:full":"2683 Houston Ave Macon GA 31206",
    "addr:housenumber":"2683",
    "addr:postcode":"31206",
    "addr:street":"Houston Ave",
    "iso:country":"US",
    "sg:address":"2683 Houston Ave",
    "sg:city":"Macon",
    "sg:classifiers":[
        {
            "category":"Food & Beverages",
            "subcategory":"Groceries & Convenience Stores",
            "type":"Retail Goods"
        },
        {
            "category":"Restaurant",
            "type":"Food & Drink"
        }
    ],
    "sg:phone":"+1 478 781 1177",
    "sg:postcode":"31206",
    "sg:province":"GA",
    "sg:tags":[
        "out"
    ],
    "wof:name":"Chang's Cafe & Grocery",
    "wof:placetype":"venue"
},
  "geometry": {"coordinates":[-83.646131,32.811286],"type":"Point"}
}