{
  "type": "Feature",
  "properties": {
    "addr:full":"430 Smith Ave Thomasville GA 31792",
    "addr:housenumber":"430",
    "addr:postcode":"31792",
    "addr:street":"Smith Ave",
    "iso:country":"US",
    "sg:address":"430 Smith Ave",
    "sg:city":"Thomasville",
    "sg:classifiers":[
        {
            "category":"Deli",
            "type":"Food & Drink"
        },
        {
            "category":"Restaurant",
            "type":"Food & Drink"
        }
    ],
    "sg:phone":"+1 229 227 1440",
    "sg:postcode":"31792",
    "sg:province":"GA",
    "sg:tags":[
        "delicatessen"
    ],
    "wof:name":"Hawaii Snow & Deli",
    "wof:placetype":"venue"
},
  "geometry": {"coordinates":[-83.985519,30.83252],"type":"Point"}
}