{
  "type": "Feature",
  "properties": {
    "iso:country":"US",
    "sg:address":"1000 Fanfare Way Apt 1105",
    "sg:city":"Alpharetta",
    "sg:classifiers":[
        {
            "category":"Home & Garden",
            "subcategory":"Home Furnishings",
            "type":"Retail Goods"
        }
    ],
    "sg:phone":"+1 770 806 9964",
    "sg:postcode":"30009",
    "sg:province":"GA",
    "sg:tags":[
        "linen"
    ],
    "wof:name":"Leontine Sutton",
    "wof:placetype":"venue"
},
  "geometry": {"coordinates":[-84.30413799999999,34.047878],"type":"Point"}
}