{
  "type": "Feature",
  "properties": {
    "addr:full":"1013 University St Albany GA 31707",
    "addr:housenumber":"1013",
    "addr:postcode":"31707",
    "addr:street":"University St",
    "iso:country":"US",
    "sg:address":"1013 University St",
    "sg:city":"Albany",
    "sg:classifiers":[
        {
            "category":"Building & Trades",
            "subcategory":"Construction",
            "type":"Services"
        }
    ],
    "sg:phone":"+1 229 436 3775",
    "sg:postcode":"31707",
    "sg:province":"GA",
    "sg:tags":[
        "house"
    ],
    "wof:name":"Johnson Home Improvement",
    "wof:placetype":"venue"
},
  "geometry": {"coordinates":[-84.20245300000001,31.566881],"type":"Point"}
}