{
  "type": "Feature",
  "properties": {
    "addr:full":"113 Linkside Ct Woodstock GA 30189",
    "addr:housenumber":"113",
    "addr:postcode":"30189",
    "addr:street":"Linkside Ct",
    "iso:country":"US",
    "sg:address":"113 Linkside Ct",
    "sg:city":"Woodstock",
    "sg:classifiers":[
        {
            "category":"Shopping",
            "subcategory":"Pets & Pet Supplies",
            "type":"Retail Goods"
        }
    ],
    "sg:phone":"+1 770 617 0221",
    "sg:postcode":"30189",
    "sg:province":"GA",
    "sg:tags":[
        "furnishing",
        "dog",
        "store",
        "cat"
    ],
    "wof:name":"Joann's Pet Sitting",
    "wof:placetype":"venue"
},
  "geometry": {"coordinates":[-84.55285600000001,34.11655],"type":"Point"}
}