{
  "type": "Feature",
  "properties": {
    "iso:country":"US",
    "sg:address":"3200 Pointe Pkwy NW",
    "sg:city":"Norcross",
    "sg:classifiers":[
        {
            "category":"Autos & Motor Vehicles",
            "subcategory":"Fuel & Gas Station",
            "type":"Retail Goods"
        }
    ],
    "sg:phone":"+1 770 797 9269",
    "sg:postcode":"30092",
    "sg:province":"GA",
    "sg:tags":[
        "grocery",
        "station",
        "gasoline"
    ],
    "wof:name":"Sunoco",
    "wof:placetype":"venue"
},
  "geometry": {"coordinates":[-84.231948,33.954645],"type":"Point"}
}