{
  "type": "Feature",
  "properties": {
    "iso:country":"US",
    "sg:address":"223 Clydesdale Ln SE",
    "sg:city":"Mableton",
    "sg:classifiers":[
        {
            "category":"Parking",
            "type":"Transportation"
        }
    ],
    "sg:phone":"+1 770 745 7600",
    "sg:postcode":"30126",
    "sg:province":"GA",
    "sg:tags":[
        "garage"
    ],
    "wof:name":"Richardson's Parking",
    "wof:placetype":"venue"
},
  "geometry": {"coordinates":[-84.546763,33.802153],"type":"Point"}
}