{
  "type": "Feature",
  "properties": {
    "addr:full":"540 Bridgewater Dr NW Atlanta GA 30328",
    "addr:housenumber":"540",
    "addr:postcode":"30328",
    "addr:street":"Bridgewater Dr Nw",
    "iso:country":"US",
    "sg:address":"540 Bridgewater Dr NW",
    "sg:city":"Atlanta",
    "sg:classifiers":[
        {
            "category":"Professional",
            "subcategory":"Accounting & Tax Preparation",
            "type":"Services"
        }
    ],
    "sg:phone":"+1 404 697 6351",
    "sg:postcode":"30328",
    "sg:province":"GA",
    "wof:name":"Deborah Minor",
    "wof:placetype":"venue"
},
  "geometry": {"coordinates":[-84.40510399999999,33.928922],"type":"Point"}
}