{
  "type": "Feature",
  "properties": {
    "iso:country":"US",
    "sg:address":"6030 State Rte 85",
    "sg:city":"Riverdale",
    "sg:classifiers":[
        {
            "category":"Personal",
            "subcategory":"Barber",
            "type":"Services"
        }
    ],
    "sg:phone":"+1 770 994 6870",
    "sg:postcode":"30274",
    "sg:province":"GA",
    "wof:name":"Complete Cuts Barber Shop",
    "wof:placetype":"venue"
},
  "geometry": {"coordinates":[-84.408913,33.590804],"type":"Point"}
}