{
  "type": "Feature",
  "properties": {
    "iso:country":"US",
    "sg:address":"3500 Lenox Rd NE Ste 1500",
    "sg:city":"Atlanta",
    "sg:classifiers":[
        {
            "category":"Education",
            "subcategory":"Special Training",
            "type":"Public Place"
        },
        {
            "category":"Professional",
            "subcategory":"Employment Agencies",
            "type":"Services"
        }
    ],
    "sg:phone":"+1 404 631 6912",
    "sg:postcode":"30326",
    "sg:province":"GA",
    "sg:tags":[
        "career",
        "counseling",
        "vocational",
        "resume"
    ],
    "sg:website":"http://atlanta.citysearch.com/profile/external/604167972/atlanta_ga/blueprint_resumes_consulting.html?publisher=yellowpages&reference_id=1&placement=ypwebsitemip",
    "wof:name":"BluePrint Resumes & Consulting",
    "wof:placetype":"venue"
},
  "geometry": {"coordinates":[-84.36534899999999,33.852551],"type":"Point"}
}