{
  "type": "Feature",
  "properties": {
    "addr:full":"5855 Medlock Bridge Pkwy Alpharetta GA 30022",
    "addr:housenumber":"5855",
    "addr:postcode":"30022",
    "addr:street":"Medlock Bridge Pkwy",
    "iso:country":"US",
    "sg:address":"5855 Medlock Bridge Pkwy",
    "sg:city":"Alpharetta",
    "sg:classifiers":[
        {
            "category":"Banks & Credit Unions",
            "subcategory":"Bank",
            "type":"Services"
        }
    ],
    "sg:phone":"+1 770 622 6511",
    "sg:postcode":"30022",
    "sg:province":"GA",
    "sg:tags":[
        "loan",
        "real estate"
    ],
    "sg:website":"www.avalonmortgage.com",
    "wof:name":"Avalon Mortgage Inc",
    "wof:placetype":"venue"
},
  "geometry": {"coordinates":[-84.18941700000001,34.028164],"type":"Point"}
}