{
  "type": "Feature",
  "properties": {
    "addr:full":"934 Hunters Run Rd Hinesville GA 31313",
    "addr:housenumber":"934",
    "addr:postcode":"31313",
    "addr:street":"Hunters Run Rd",
    "iso:country":"US",
    "sg:address":"934 Hunters Run Rd",
    "sg:city":"Hinesville",
    "sg:classifiers":[
        {
            "category":"Insurance",
            "subcategory":"Insurance Agent",
            "type":"Services"
        }
    ],
    "sg:phone":"+1 912 369 4119",
    "sg:postcode":"31313",
    "sg:province":"GA",
    "wof:name":"AIG",
    "wof:placetype":"venue"
},
  "geometry": {"coordinates":[-81.606807,31.817345],"type":"Point"}
}