{
  "type": "Feature",
  "properties": {
    "addr:full":"5405 Webb Pkwy NW Lilburn GA 30047",
    "addr:housenumber":"5405",
    "addr:postcode":"30047",
    "addr:street":"Webb Pkwy Nw",
    "iso:country":"US",
    "sg:address":"5405 Webb Pkwy NW",
    "sg:city":"Lilburn",
    "sg:classifiers":[
        {
            "category":"Shopping",
            "subcategory":"Crafts & Fabrics",
            "type":"Retail Goods"
        }
    ],
    "sg:phone":"+1 770 638 1100",
    "sg:postcode":"30047",
    "sg:province":"GA",
    "sg:tags":[
        "embroidery"
    ],
    "sg:website":"http://www.apparelmanufacturing.com",
    "wof:name":"Apparel Concepts Inc",
    "wof:placetype":"venue"
},
  "geometry": {"coordinates":[-84.15433,33.877942],"type":"Point"}
}