{
  "type": "Feature",
  "properties": {
    "iso:country":"US",
    "sg:address":"7406 Madison Dr",
    "sg:city":"Atlanta",
    "sg:classifiers":[
        {
            "category":"Building & Trades",
            "subcategory":"Landscaping Services",
            "type":"Services"
        }
    ],
    "sg:phone":"+1 404 210 9686",
    "sg:postcode":"30346",
    "sg:province":"GA",
    "sg:tags":[
        "landscape",
        "contractor"
    ],
    "wof:name":"Renovations",
    "wof:placetype":"venue"
},
  "geometry": {"coordinates":[-84.33344,33.930956],"type":"Point"}
}