{
  "type": "Feature",
  "properties": {
    "addr:full":"526 Berry St Augusta GA 30907",
    "addr:housenumber":"526",
    "addr:postcode":"30907",
    "addr:street":"Berry St",
    "iso:country":"US",
    "sg:address":"526 Berry St",
    "sg:city":"Augusta",
    "sg:classifiers":[
        {
            "category":"Building & Trades",
            "subcategory":"Landscaping Services",
            "type":"Services"
        }
    ],
    "sg:phone":"+1 706 863 0478",
    "sg:postcode":"30907",
    "sg:province":"GA",
    "sg:tags":[
        "lawn",
        "maintenance",
        "grounds"
    ],
    "wof:name":"A & D Lawn Svc",
    "wof:placetype":"venue"
},
  "geometry": {"coordinates":[-82.106002,33.493079],"type":"Point"}
}