{
  "type": "Feature",
  "properties": {
    "iso:country":"US",
    "sg:address":"625 W Crossville Rd",
    "sg:city":"Roswell",
    "sg:classifiers":[
        {
            "category":"Shopping",
            "subcategory":"Gifts & Souvenirs",
            "type":"Retail Goods"
        }
    ],
    "sg:phone":"+1 770 649 6653",
    "sg:postcode":"30075",
    "sg:province":"GA",
    "sg:tags":[
        "shop"
    ],
    "wof:name":"On A Whim",
    "wof:placetype":"venue"
},
  "geometry": {"coordinates":[-84.382834,34.05912],"type":"Point"}
}