{
  "type": "Feature",
  "properties": {
    "iso:country":"US",
    "sg:address":"1035 Juniper St NE",
    "sg:city":"Atlanta",
    "sg:classifiers":[
        {
            "category":"Real Estate",
            "subcategory":"Real Estate Agent",
            "type":"Services"
        }
    ],
    "sg:phone":"+1 404 876 8700",
    "sg:postcode":"30309",
    "sg:province":"GA",
    "wof:name":"Partners Management",
    "wof:placetype":"venue"
},
  "geometry": {"coordinates":[-84.382499,33.781748],"type":"Point"}
}