{
  "type": "Feature",
  "properties": {
    "iso:country":"US",
    "sg:address":"1245 Bellemeade Dr SW",
    "sg:city":"Marietta",
    "sg:classifiers":[
        {
            "category":"Autos & Motor Vehicles",
            "subcategory":"Automobile Sales",
            "type":"Retail Goods"
        }
    ],
    "sg:phone":"+1 770 428 0206",
    "sg:postcode":"30008",
    "sg:province":"GA",
    "sg:tags":[
        "car",
        "used",
        "dealer"
    ],
    "wof:name":"Autofin Express",
    "wof:placetype":"venue"
},
  "geometry": {"coordinates":[-84.574258,33.921246],"type":"Point"}
}