{
  "type": "Feature",
  "properties": {
    "addr:full":"5105 Burruss Mill Rd Cumming GA 30041",
    "addr:postcode":"5105;30041",
    "addr:street":"Burruss Mill Rd",
    "iso:country":"US",
    "sg:address":"5105 Burruss Mill Rd",
    "sg:city":"Cumming",
    "sg:classifiers":[
        {
            "category":"Building & Trades",
            "subcategory":"Landscaping Services",
            "type":"Services"
        }
    ],
    "sg:phone":"+1 770 886 0510",
    "sg:postcode":"30041",
    "sg:province":"GA",
    "sg:tags":[
        "tree"
    ],
    "wof:name":"Husky Tree Svc Inc",
    "wof:placetype":"venue"
},
  "geometry": {"coordinates":[-84.060864,34.254929],"type":"Point"}
}