{
  "type": "Feature",
  "properties": {
    "iso:country":"US",
    "sg:address":"1561 Greyson Ridge",
    "sg:city":"Marietta",
    "sg:classifiers":[
        {
            "category":"Professional",
            "subcategory":"Business Services",
            "type":"Services"
        }
    ],
    "sg:phone":"+1 770 973 1663",
    "sg:postcode":"30062",
    "sg:province":"GA",
    "wof:name":"Oliveinteriors",
    "wof:placetype":"venue"
},
  "geometry": {"coordinates":[-84.484487,33.985179],"type":"Point"}
}