{
  "type": "Feature",
  "properties": {
    "addr:full":"1456 Turner McCall Blvd Rome GA 30161",
    "addr:housenumber":"1456",
    "addr:postcode":"ga 30161",
    "addr:street":"Turner Mccall Blvd",
    "iso:country":"US",
    "sg:address":"1456 Turner McCall Blvd",
    "sg:city":"Rome",
    "sg:classifiers":[
        {
            "category":"Shopping",
            "subcategory":"Bicycles & Sporting Goods",
            "type":"Retail Goods"
        }
    ],
    "sg:phone":"+1 706 235 3132",
    "sg:postcode":"30161",
    "sg:province":"GA",
    "wof:name":"Hibbett Sporting Goods Inc",
    "wof:placetype":"venue"
},
  "geometry": {"coordinates":[-85.16185299999999,34.247756],"type":"Point"}
}