{
  "type": "Feature",
  "properties": {
    "iso:country":"US",
    "sg:address":"2112 S Hamilton St",
    "sg:city":"Dalton",
    "sg:classifiers":[
        {
            "category":"Freight",
            "type":"Transportation"
        }
    ],
    "sg:phone":"+1 706 275 8847",
    "sg:postcode":"30720",
    "sg:province":"GA",
    "sg:tags":[
        "operator",
        "hauling",
        "trucking"
    ],
    "wof:name":"B & L Express Inc",
    "wof:placetype":"venue"
},
  "geometry": {"coordinates":[-84.96619099999999,34.731438],"type":"Point"}
}