{
  "type": "Feature",
  "properties": {
    "addr:full":"6622 S Sweetwater Rd Lithia Springs GA 30122",
    "addr:housenumber":"6622",
    "addr:postcode":"30122",
    "addr:street":"S Sweetwater Rd",
    "iso:country":"US",
    "sg:address":"6622 S Sweetwater Rd",
    "sg:city":"Lithia Springs",
    "sg:classifiers":[
        {
            "category":"Retail",
            "subcategory":"Laundry & Dry Cleaning",
            "type":"Services"
        },
        {
            "category":"Shopping",
            "subcategory":"Clothing, Apparel, & Fashions",
            "type":"Retail Goods"
        }
    ],
    "sg:phone":"+1 770 941 5881",
    "sg:postcode":"30122",
    "sg:province":"GA",
    "sg:tags":[
        "alteration"
    ],
    "wof:name":"Betty's Fashions & Designers",
    "wof:placetype":"venue"
},
  "geometry": {"coordinates":[-84.66050199999999,33.793718],"type":"Point"}
}