{
  "type": "Feature",
  "properties": {
    "addr:full":"200 Ashford Center N Atlanta GA 30338",
    "addr:housenumber":"200",
    "addr:postcode":"30338",
    "addr:street":"Ashford Center N",
    "iso:country":"US",
    "sg:address":"200 Ashford Center N",
    "sg:city":"Atlanta",
    "sg:classifiers":[
        {
            "category":"Home & Garden",
            "subcategory":"Furniture",
            "type":"Retail Goods"
        }
    ],
    "sg:phone":"+1 678 259 4600",
    "sg:postcode":"30338",
    "sg:province":"GA",
    "wof:name":"Herman Miller Inc",
    "wof:placetype":"venue"
},
  "geometry": {"coordinates":[-84.336747,33.941523],"type":"Point"}
}