{
  "type": "Feature",
  "properties": {
    "addr:full":"181 Sentinel Pl Marietta GA 30067",
    "addr:housenumber":"181",
    "addr:postcode":"30067",
    "addr:street":"Sentinel Pl",
    "iso:country":"US",
    "sg:address":"181 Sentinel Pl",
    "sg:city":"Marietta",
    "sg:classifiers":[
        {
            "category":"Communications",
            "subcategory":"Film & Video Production",
            "type":"Services"
        }
    ],
    "sg:phone":"+1 770 579 9966",
    "sg:postcode":"30067",
    "sg:province":"GA",
    "sg:tags":[
        "motion",
        "picture"
    ],
    "wof:name":"Media Consultants Inc",
    "wof:placetype":"venue"
},
  "geometry": {"coordinates":[-84.437825,33.951174],"type":"Point"}
}