{
  "type": "Feature",
  "properties": {
    "iso:country":"US",
    "sg:address":"301 S Baker St",
    "sg:city":"Alma",
    "sg:classifiers":[
        {
            "category":"Health Services",
            "subcategory":"Nursing And Care Facility",
            "type":"Services"
        }
    ],
    "sg:phone":"+1 912 632 7293",
    "sg:postcode":"31510",
    "sg:province":"GA",
    "sg:tags":[
        "home",
        "convalescent"
    ],
    "wof:name":"Twin Oaks Convalescent Ctr",
    "wof:placetype":"venue"
},
  "geometry": {"coordinates":[-82.45638,31.539797],"type":"Point"}
}