{
  "type": "Feature",
  "properties": {
    "addr:full":"3705 Cascade Rd SW Atlanta GA 30331",
    "addr:housenumber":"3705",
    "addr:postcode":"30331",
    "addr:street":"Cascade Rd Sw",
    "iso:country":"US",
    "sg:address":"3705 Cascade Rd SW",
    "sg:city":"Atlanta",
    "sg:classifiers":[
        {
            "category":"Banks & Credit Unions",
            "subcategory":"Bank",
            "type":"Services"
        }
    ],
    "sg:phone":"+1 404 691 9009",
    "sg:postcode":"30331",
    "sg:province":"GA",
    "sg:website":"www.ctbconnect.com",
    "wof:name":"Citizens Trust Bank",
    "wof:placetype":"venue"
},
  "geometry": {"coordinates":[-84.509691,33.724125],"type":"Point"}
}