{
  "type": "Feature",
  "properties": {
    "addr:full":"1071 Delaware Avenue SE Atlanta GA 30316",
    "addr:housenumber":"1071",
    "addr:postcode":"30316",
    "addr:street":"Delaware Avenue Se",
    "iso:country":"US",
    "sg:address":"1071 Delaware Avenue SE",
    "sg:city":"Atlanta",
    "sg:classifiers":[
        {
            "category":"Organizations",
            "subcategory":"Religious Organization",
            "type":"Services"
        }
    ],
    "sg:phone":"+1 404 627 2216",
    "sg:postcode":"30316",
    "sg:province":"GA",
    "wof:name":"Ormewood Park Presbyterian Church",
    "wof:placetype":"venue"
},
  "geometry": {"coordinates":[-84.351676,33.731962],"type":"Point"}
}