{
  "type": "Feature",
  "properties": {
    "iso:country":"US",
    "sg:address":"1114 Alabama St",
    "sg:city":"Carrollton",
    "sg:classifiers":[
        {
            "category":"Wholesale",
            "subcategory":"Home Furnishings",
            "type":"Manufacturing & Wholesale Goods"
        }
    ],
    "sg:phone":"+1 770 834 7775",
    "sg:postcode":"30117",
    "sg:province":"GA",
    "sg:tags":[
        "linen"
    ],
    "wof:name":"Peach State Textiles",
    "wof:placetype":"venue"
},
  "geometry": {"coordinates":[-85.099979,33.588166],"type":"Point"}
}