{
  "type": "Feature",
  "properties": {
    "addr:full":"13775 Highway 9 N Alpharetta GA 30004",
    "addr:housenumber":"13775",
    "addr:postcode":"30004",
    "addr:street":"Highway 9 N",
    "iso:country":"US",
    "sg:address":"13775 Highway 9 N",
    "sg:city":"Alpharetta",
    "sg:classifiers":[
        {
            "category":"Retail",
            "subcategory":"Veterinary Services",
            "type":"Services"
        }
    ],
    "sg:phone":"+1 770 667 9022",
    "sg:postcode":"30004",
    "sg:province":"GA",
    "sg:tags":[
        "veterinarian",
        "specialty"
    ],
    "wof:name":"Parker Tammy DVM",
    "wof:placetype":"venue"
},
  "geometry": {"coordinates":[-84.26969200000001,34.116858],"type":"Point"}
}