{
  "type": "Feature",
  "properties": {
    "iso:country":"US",
    "sg:address":"2030 Riverview Industrial Dr SE",
    "sg:city":"Mableton",
    "sg:classifiers":[
        {
            "category":"Manufacturing",
            "subcategory":"Metals",
            "type":"Manufacturing & Wholesale Goods"
        },
        {
            "category":"Building & Trades",
            "subcategory":"Construction",
            "type":"Services"
        }
    ],
    "sg:phone":"+1 404 355 5000",
    "sg:postcode":"30126",
    "sg:province":"GA",
    "sg:tags":[
        "finisher",
        "metals-pre-coated"
    ],
    "wof:name":"Coil Coaters Of America",
    "wof:placetype":"venue"
},
  "geometry": {"coordinates":[-84.494606,33.813799],"type":"Point"}
}