{
  "type": "Feature",
  "properties": {
    "iso:country":"US",
    "sg:address":"279 Southern Walk Cir",
    "sg:city":"Gray",
    "sg:classifiers":[
        {
            "category":"Building & Trades",
            "subcategory":"Construction",
            "type":"Services"
        }
    ],
    "sg:phone":"+1 478 986 0517",
    "sg:postcode":"31032",
    "sg:province":"GA",
    "wof:name":"First Place Builders",
    "wof:placetype":"venue"
},
  "geometry": {"coordinates":[-83.5085,33.018893],"type":"Point"}
}