{
  "type": "Feature",
  "properties": {
    "addr:full":"2100 Riverside Pkwy Lawrenceville GA 30043",
    "addr:housenumber":"2100",
    "addr:postcode":"30043",
    "addr:street":"Riverside Pkwy",
    "iso:country":"US",
    "sg:address":"2100 Riverside Pkwy",
    "sg:city":"Lawrenceville",
    "sg:classifiers":[
        {
            "category":"Shopping",
            "subcategory":"Shoes",
            "type":"Retail Goods"
        }
    ],
    "sg:phone":"+1 770 682 9815",
    "sg:postcode":"30043",
    "sg:province":"GA",
    "wof:name":"Famous Footwear",
    "wof:placetype":"venue"
},
  "geometry": {"coordinates":[-84.02454299999999,33.983403],"type":"Point"}
}