{
  "type": "Feature",
  "properties": {
    "iso:country":"US",
    "sg:address":"1705 Cleveland Hwy",
    "sg:city":"Gainesville",
    "sg:classifiers":[
        {
            "category":"Shopping",
            "subcategory":"Used Merchandise",
            "type":"Retail Goods"
        }
    ],
    "sg:phone":"+1 770 534 9070",
    "sg:postcode":"30501",
    "sg:province":"GA",
    "sg:tags":[
        "shop",
        "consignment"
    ],
    "wof:name":"Next To New Resale Boutique",
    "wof:placetype":"venue"
},
  "geometry": {"coordinates":[-83.81361,34.328413],"type":"Point"}
}