{
  "type": "Feature",
  "properties": {
    "addr:full":"902 Blue Sky Rdg Snellville GA 30078",
    "addr:housenumber":"902",
    "addr:postcode":"30078",
    "addr:street":"Blue Sky Rdg",
    "iso:country":"US",
    "sg:address":"902 Blue Sky Rdg",
    "sg:city":"Snellville",
    "sg:classifiers":[
        {
            "category":"Arena",
            "subcategory":"Sports Club",
            "type":"Entertainment"
        }
    ],
    "sg:phone":"+1 770 736 7580",
    "sg:postcode":"30078",
    "sg:province":"GA",
    "sg:tags":[
        "soccer"
    ],
    "wof:name":"All Soccer Africa",
    "wof:placetype":"venue"
},
  "geometry": {"coordinates":[-84.046896,33.892399],"type":"Point"}
}