{
  "type": "Feature",
  "properties": {
    "addr:full":"3633 Salem Rd Covington GA 30016",
    "addr:housenumber":"3633",
    "addr:postcode":"30016",
    "addr:street":"Salem Rd",
    "iso:country":"US",
    "sg:address":"3633 Salem Rd",
    "sg:city":"Covington",
    "sg:classifiers":[
        {
            "category":"Restaurant",
            "type":"Food & Drink"
        }
    ],
    "sg:phone":"+1 770 385 1650",
    "sg:postcode":"30016",
    "sg:province":"GA",
    "sg:tags":[
        "eating"
    ],
    "wof:name":"Pizza Inn",
    "wof:placetype":"venue"
},
  "geometry": {"coordinates":[-83.969953,33.593091],"type":"Point"}
}