{
  "type": "Feature",
  "properties": {
    "iso:country":"US",
    "sg:address":"215 Kingsley Way",
    "sg:city":"Woodstock",
    "sg:classifiers":[
        {
            "category":"Retail",
            "subcategory":"Repair Shop",
            "type":"Services"
        }
    ],
    "sg:phone":"+1 770 330 7946",
    "sg:postcode":"30188",
    "sg:province":"GA",
    "wof:name":"Cleanique Cleaning Inc",
    "wof:placetype":"venue"
},
  "geometry": {"coordinates":[-84.39254,34.134588],"type":"Point"}
}