{
  "type": "Feature",
  "properties": {
    "iso:country":"US",
    "sg:address":"250 Spring St NW Ste 8N301",
    "sg:city":"Atlanta",
    "sg:classifiers":[
        {
            "category":"Shopping",
            "subcategory":"Jewelry",
            "type":"Retail Goods"
        },
        {
            "category":"Retail",
            "subcategory":"Repair Shop",
            "type":"Services"
        }
    ],
    "sg:phone":"+1 404 524 4844",
    "sg:postcode":"30303",
    "sg:province":"GA",
    "sg:tags":[
        "jeweler",
        "watch",
        "clock"
    ],
    "wof:name":"La Scala Michael",
    "wof:placetype":"venue"
},
  "geometry": {"coordinates":[-84.38902299999999,33.761421],"type":"Point"}
}