{
  "type": "Feature",
  "properties": {
    "addr:full":"220 Johnson Ferry Rd NE Atlanta GA 30328",
    "addr:housenumber":"220",
    "addr:postcode":"30328",
    "addr:street":"Johnson Ferry Rd Ne",
    "iso:country":"US",
    "sg:address":"220 Johnson Ferry Rd NE",
    "sg:city":"Atlanta",
    "sg:classifiers":[
        {
            "category":"Shopping",
            "subcategory":"Shoes",
            "type":"Retail Goods"
        }
    ],
    "sg:phone":"+1 404 252 0710",
    "sg:postcode":"30328",
    "sg:province":"GA",
    "wof:name":"Foot Prints Of Nj Inc",
    "wof:placetype":"venue"
},
  "geometry": {"coordinates":[-84.38163,33.925811],"type":"Point"}
}