{
  "type": "Feature",
  "properties": {
    "iso:country":"US",
    "sg:address":"835 N Washington St",
    "sg:city":"Dublin",
    "sg:classifiers":[
        {
            "category":"Building & Trades",
            "subcategory":"Cleaning & Sanitation",
            "type":"Services"
        }
    ],
    "sg:phone":"+1 478 272 0647",
    "sg:postcode":"31021",
    "sg:province":"GA",
    "sg:tags":[
        "maintenance"
    ],
    "wof:name":"Wrights Cleaning Service",
    "wof:placetype":"venue"
},
  "geometry": {"coordinates":[-82.907977,32.54984],"type":"Point"}
}