{
  "type": "Feature",
  "properties": {
    "iso:country":"US",
    "sg:address":"553 Waterboy Rd",
    "sg:city":"Fairburn",
    "sg:classifiers":[
        {
            "category":"Building & Trades",
            "subcategory":"Cleaning & Sanitation",
            "type":"Services"
        }
    ],
    "sg:phone":"+1 770 969 9230",
    "sg:postcode":"30213",
    "sg:province":"GA",
    "sg:tags":[
        "maintenance"
    ],
    "wof:name":"Cassandra Executive Cleaning",
    "wof:placetype":"venue"
},
  "geometry": {"coordinates":[-84.602036,33.581449],"type":"Point"}
}