{
  "type": "Feature",
  "properties": {
    "addr:full":"35 Atlanta St Mcdonough GA 30253",
    "addr:housenumber":"35",
    "addr:postcode":"30253",
    "addr:street":"Atlanta St",
    "iso:country":"US",
    "sg:address":"35 Atlanta St",
    "sg:city":"Mcdonough",
    "sg:classifiers":[
        {
            "category":"Professional",
            "type":"Services"
        }
    ],
    "sg:phone":"+1 770 914 6961",
    "sg:postcode":"30253",
    "sg:province":"GA",
    "sg:website":"www.sentrack.com",
    "wof:name":"Sentinel",
    "wof:placetype":"venue"
},
  "geometry": {"coordinates":[-84.14713,33.448606],"type":"Point"}
}