{
  "type": "Feature",
  "properties": {
    "iso:country":"US",
    "sg:address":"826 W 3rd Ave",
    "sg:city":"Albany",
    "sg:classifiers":[
        {
            "category":"Manufacturing",
            "subcategory":"Metals",
            "type":"Manufacturing & Wholesale Goods"
        }
    ],
    "sg:phone":"+1 229 888 5268",
    "sg:postcode":"31701",
    "sg:province":"GA",
    "sg:tags":[
        "hardware",
        "mfg"
    ],
    "wof:name":"Saint-Gobain Abrasives Inc",
    "wof:placetype":"venue"
},
  "geometry": {"coordinates":[-84.170222,31.590105],"type":"Point"}
}