{
  "type": "Feature",
  "properties": {
    "iso:country":"US",
    "sg:address":"13525 Providence Lake Dr",
    "sg:city":"Alpharetta",
    "sg:classifiers":[
        {
            "category":"Real Estate",
            "subcategory":"Developer",
            "type":"Services"
        }
    ],
    "sg:phone":"+1 770 475 8529",
    "sg:postcode":"30004",
    "sg:province":"GA",
    "wof:name":"Ark Development Inc",
    "wof:placetype":"venue"
},
  "geometry": {"coordinates":[-84.369938,34.110723],"type":"Point"}
}