{
  "type": "Feature",
  "properties": {
    "iso:country":"US",
    "sg:address":"2347 Lenora Church Rd",
    "sg:city":"Snellville",
    "sg:classifiers":[
        {
            "category":"Health Services",
            "subcategory":"Optometrist",
            "type":"Services"
        },
        {
            "category":"Health Services",
            "subcategory":"Clinic",
            "type":"Services"
        }
    ],
    "sg:phone":"+1 770 979 2020",
    "sg:postcode":"30078",
    "sg:province":"GA",
    "sg:tags":[
        "ophthalmologist",
        "mental",
        "counseling"
    ],
    "wof:name":"Thornhill Blake",
    "wof:placetype":"venue"
},
  "geometry": {"coordinates":[-84.020302,33.856201],"type":"Point"}
}