{
  "type": "Feature",
  "properties": {
    "iso:country":"US",
    "sg:address":"3785 Presidential Pkwy",
    "sg:city":"Doraville",
    "sg:classifiers":[
        {
            "category":"Social Services",
            "type":"Services"
        }
    ],
    "sg:phone":"+1 770 455 0835",
    "sg:postcode":"30340",
    "sg:province":"GA",
    "sg:tags":[
        "counseling"
    ],
    "wof:name":"Highland Institute-Behavioral",
    "wof:placetype":"venue"
},
  "geometry": {"coordinates":[-84.26564399999999,33.886802],"type":"Point"}
}