{
  "type": "Feature",
  "properties": {
    "iso:country":"US",
    "sg:address":"12371 Molly Sue Ln",
    "sg:city":"Fayetteville",
    "sg:classifiers":[
        {
            "category":"Freight",
            "type":"Transportation"
        }
    ],
    "sg:phone":"+1 770 460 2424",
    "sg:postcode":"30215",
    "sg:province":"GA",
    "sg:tags":[
        "trucking"
    ],
    "wof:name":"Serious Trucking Co",
    "wof:placetype":"venue"
},
  "geometry": {"coordinates":[-84.400673,33.421878],"type":"Point"}
}