{
  "type": "Feature",
  "properties": {
    "addr:full":"5599 Craig Gap Rd Blairsville GA 30512",
    "addr:housenumber":"5599",
    "addr:postcode":"30512",
    "addr:street":"Craig Gap Rd",
    "iso:country":"US",
    "sg:address":"5599 Craig Gap Rd",
    "sg:city":"Blairsville",
    "sg:classifiers":[
        {
            "category":"Professional",
            "type":"Services"
        }
    ],
    "sg:phone":"+1 706 745 3122",
    "sg:postcode":"30512",
    "sg:province":"GA",
    "wof:name":"Johnny R Holbrooks",
    "wof:placetype":"venue"
},
  "geometry": {"coordinates":[-83.877968,34.775676],"type":"Point"}
}