{
  "type": "Feature",
  "properties": {
    "addr:full":"4368 W Atlanta Rd SE Smyrna GA 30080",
    "addr:housenumber":"4368",
    "addr:postcode":"30080",
    "addr:street":"W Atlanta Rd Se",
    "iso:country":"US",
    "sg:address":"4368 W Atlanta Rd SE",
    "sg:city":"Smyrna",
    "sg:classifiers":[
        {
            "category":"Shopping",
            "subcategory":"Computers & Home Electronics",
            "type":"Retail Goods"
        }
    ],
    "sg:phone":"+1 770 432 4770",
    "sg:postcode":"30080",
    "sg:province":"GA",
    "sg:tags":[
        "equipment",
        "dealer"
    ],
    "wof:name":"Brytech",
    "wof:placetype":"venue"
},
  "geometry": {"coordinates":[-84.494435,33.848071],"type":"Point"}
}