{
  "type": "Feature",
  "properties": {
    "iso:country":"US",
    "sg:address":"150 Hopewell Chase Ct",
    "sg:city":"Alpharetta",
    "sg:classifiers":[
        {
            "category":"Professional",
            "subcategory":"Computer Services",
            "type":"Services"
        }
    ],
    "sg:phone":"+1 770 781 8208",
    "sg:postcode":"30004",
    "sg:province":"GA",
    "sg:tags":[
        "datum"
    ],
    "wof:name":"Professional Digesting Service",
    "wof:placetype":"venue"
},
  "geometry": {"coordinates":[-84.276475,34.195163],"type":"Point"}
}