{
  "type": "Feature",
  "properties": {
    "iso:country":"US",
    "sg:address":"1020 Franklin Ct",
    "sg:city":"Buckhead",
    "sg:classifiers":[
        {
            "category":"Building & Trades",
            "subcategory":"Construction",
            "type":"Services"
        }
    ],
    "sg:phone":"+1 706 342 3884",
    "sg:postcode":"30625",
    "sg:province":"GA",
    "sg:tags":[
        "residential"
    ],
    "wof:name":"Dsgm Inc",
    "wof:placetype":"venue"
},
  "geometry": {"coordinates":[-83.283631,33.519365],"type":"Point"}
}