{
  "type": "Feature",
  "properties": {
    "addr:full":"5090 Buford Hwy Ste 103 Doraville GA 30340",
    "addr:housenumber":"5090",
    "addr:postcode":"30340",
    "addr:street":"Buford Hwy Ste 103",
    "iso:country":"US",
    "sg:address":"5090 Buford Hwy Ste 103",
    "sg:city":"Doraville",
    "sg:classifiers":[
        {
            "category":"Restaurant",
            "type":"Food & Drink"
        }
    ],
    "sg:phone":"+1 770 455 8388",
    "sg:postcode":"30340",
    "sg:province":"GA",
    "sg:tags":[
        "chinese"
    ],
    "wof:name":"Te Wei Chinese Kobobs",
    "wof:placetype":"venue"
},
  "geometry": {"coordinates":[-84.285899,33.891486],"type":"Point"}
}