{
  "type": "Feature",
  "properties": {
    "iso:country":"US",
    "sg:address":"3000 Northwoods Pkwy # 200",
    "sg:city":"Norcross",
    "sg:classifiers":[
        {
            "category":"Professional",
            "subcategory":"Detective & Security Services",
            "type":"Services"
        },
        {
            "category":"Manufacturing",
            "subcategory":"Electronics",
            "type":"Manufacturing & Wholesale Goods"
        }
    ],
    "sg:phone":"+1 770 447 9995",
    "sg:postcode":"30071",
    "sg:province":"GA",
    "sg:tags":[
        "control",
        "equipment-wholesale",
        "monitoring",
        "system",
        "manufacturer"
    ],
    "sg:website":"http://INTEGRATEDEXCELLENCE.COM",
    "wof:name":"Technical Maintenance Inc",
    "wof:placetype":"venue"
},
  "geometry": {"coordinates":[-84.19559,33.95779],"type":"Point"}
}