{
  "type": "Feature",
  "properties": {
    "addr:full":"2270 Byron Ct Marietta GA 30064",
    "addr:housenumber":"2270",
    "addr:postcode":"30064",
    "addr:street":"Byron Ct",
    "iso:country":"US",
    "sg:address":"2270 Byron Ct",
    "sg:city":"Marietta",
    "sg:classifiers":[
        {
            "category":"Education",
            "subcategory":"Special Training",
            "type":"Public Place"
        }
    ],
    "sg:phone":"+1 770 428 1415",
    "sg:postcode":"30064",
    "sg:province":"GA",
    "sg:tags":[
        "tutoring"
    ],
    "wof:name":"Private Tutoring Resource",
    "wof:placetype":"venue"
},
  "geometry": {"coordinates":[-84.620042,33.907958],"type":"Point"}
}