{
  "type": "Feature",
  "properties": {
    "iso:country":"US",
    "sg:address":"41 State Hwy 20 Spur SE",
    "sg:city":"Cartersville",
    "sg:classifiers":[
        {
            "category":"Travel",
            "subcategory":"Hotels & Motels",
            "type":"Entertainment"
        }
    ],
    "sg:phone":"+1 770 382 8881",
    "sg:postcode":"30121",
    "sg:province":"GA",
    "sg:tags":[
        "operation"
    ],
    "wof:name":"Super 8 Motel",
    "wof:placetype":"venue"
},
  "geometry": {"coordinates":[-84.758619,34.207728],"type":"Point"}
}