{
  "type": "Feature",
  "properties": {
    "iso:country":"US",
    "sg:address":"130 E Lower Factors Walk",
    "sg:city":"Savannah",
    "sg:classifiers":[
        {
            "category":"Restaurant",
            "type":"Food & Drink"
        }
    ],
    "sg:phone":"+1 912 231 0701",
    "sg:postcode":"31401",
    "sg:province":"GA",
    "sg:tags":[
        "eating"
    ],
    "sg:website":"www.cobblestonecafe.com",
    "wof:name":"Cobblestone Cafe",
    "wof:placetype":"venue"
},
  "geometry": {"coordinates":[-81.08380699999999,32.079469],"type":"Point"}
}