{
  "type": "Feature",
  "properties": {
    "iso:country":"US",
    "sg:address":"123 Fairview Rd",
    "sg:city":"Ellenwood",
    "sg:classifiers":[
        {
            "category":"Shopping",
            "type":"Retail Goods"
        },
        {
            "category":"Personal",
            "subcategory":"Beauty Salon",
            "type":"Services"
        }
    ],
    "sg:phone":"+1 770 507 6552",
    "sg:postcode":"30294",
    "sg:province":"GA",
    "sg:tags":[
        "shop",
        "cosmetic",
        "perfume"
    ],
    "wof:name":"J S Beauty Supply Corp",
    "wof:placetype":"venue"
},
  "geometry": {"coordinates":[-84.245254,33.618548],"type":"Point"}
}