{
  "type": "Feature",
  "properties": {
    "addr:full":"2100 Pleasant Hill Rd Duluth GA 30096",
    "addr:housenumber":"2100",
    "addr:postcode":"30096",
    "addr:street":"Pleasant Hill Rd",
    "iso:country":"US",
    "sg:address":"2100 Pleasant Hill Rd",
    "sg:city":"Duluth",
    "sg:classifiers":[
        {
            "category":"Shopping",
            "subcategory":"Clothing, Apparel, & Fashions",
            "type":"Retail Goods"
        }
    ],
    "sg:phone":"+1 770 497 0608",
    "sg:postcode":"30096",
    "sg:province":"GA",
    "sg:tags":[
        "accessory",
        "clothing",
        "women's"
    ],
    "wof:name":"Body Shop",
    "wof:placetype":"venue"
},
  "geometry": {"coordinates":[-84.133301,33.9571],"type":"Point"}
}