{
  "type": "Feature",
  "properties": {
    "addr:full":"1015 Optima Pl SW Marietta GA 30060",
    "addr:housenumber":"1015",
    "addr:postcode":"30060",
    "addr:street":"Optima Pl Sw",
    "iso:country":"US",
    "sg:address":"1015 Optima Pl SW",
    "sg:city":"Marietta",
    "sg:classifiers":[
        {
            "category":"Manufacturing",
            "subcategory":"Tools & Machinery",
            "type":"Manufacturing & Wholesale Goods"
        }
    ],
    "sg:phone":"+1 678 305 9204",
    "sg:postcode":"30060",
    "sg:province":"GA",
    "sg:tags":[
        "equipment",
        "mining",
        "export"
    ],
    "wof:name":"Tradelinks International Trade",
    "wof:placetype":"venue"
},
  "geometry": {"coordinates":[-84.58515300000001,33.866501],"type":"Point"}
}