{
  "type": "Feature",
  "properties": {
    "addr:full":"90 N Harney St Camilla GA 31730",
    "addr:housenumber":"90",
    "addr:postcode":"31730",
    "addr:street":"N Harney St",
    "iso:country":"US",
    "sg:address":"90 N Harney St",
    "sg:city":"Camilla",
    "sg:classifiers":[
        {
            "category":"Autos & Motor Vehicles",
            "subcategory":"Automobile Sales",
            "type":"Retail Goods"
        }
    ],
    "sg:phone":"+1 229 336 1110",
    "sg:postcode":"31730",
    "sg:province":"GA",
    "sg:tags":[
        "used"
    ],
    "wof:name":"E-Z Ride Auto Sales",
    "wof:placetype":"venue"
},
  "geometry": {"coordinates":[-84.208899,31.235022],"type":"Point"}
}