{
  "type": "Feature",
  "properties": {
    "iso:country":"US",
    "sg:address":"1401 Powder Springs Rd SW",
    "sg:city":"Marietta",
    "sg:classifiers":[
        {
            "category":"Retail",
            "subcategory":"Storage",
            "type":"Services"
        }
    ],
    "sg:phone":"+1 678 561 7943",
    "sg:postcode":"30064",
    "sg:province":"GA",
    "sg:tags":[
        "automobile",
        "self",
        "commercial",
        "household"
    ],
    "sg:website":"http://atlanta.citysearch.com/profile/external/604187442/marietta_ga/stormaster_self_storage.html?publisher=yellowpages&reference_id=1&placement=ypwebsitemip",
    "wof:name":"StorMaster Self Storage",
    "wof:placetype":"venue"
},
  "geometry": {"coordinates":[-84.596079,33.911486],"type":"Point"}
}