{
  "type": "Feature",
  "properties": {
    "addr:full":"3815 Evans Rd Cumming GA 30040",
    "addr:housenumber":"3815",
    "addr:postcode":"30040",
    "addr:street":"Evans Rd",
    "iso:country":"US",
    "sg:address":"3815 Evans Rd",
    "sg:city":"Cumming",
    "sg:classifiers":[
        {
            "category":"Home & Garden",
            "subcategory":"Furniture",
            "type":"Retail Goods"
        },
        {
            "category":"Home & Garden",
            "subcategory":"Home Furnishings",
            "type":"Retail Goods"
        },
        {
            "category":"Building & Trades",
            "subcategory":"Construction",
            "type":"Services"
        },
        {
            "category":"Wholesale",
            "subcategory":"Home Furnishings",
            "type":"Manufacturing & Wholesale Goods"
        }
    ],
    "sg:phone":"+1 770 887 4766",
    "sg:postcode":"30040",
    "sg:province":"GA",
    "sg:tags":[
        "equipment-wholesale",
        "kitchen",
        "cabinet",
        "refacing",
        "resurfacing",
        "equipment-household",
        "maker",
        "cabinets-refinishing",
        "manufacturer"
    ],
    "sg:website":"http://www.atlcasework.com",
    "wof:name":"Atlanta Casework Systems",
    "wof:placetype":"venue"
},
  "geometry": {"coordinates":[-84.22933500000001,34.236515],"type":"Point"}
}