{
  "type": "Feature",
  "properties": {
    "iso:country":"US",
    "sg:address":"1833 Bishops Green Dr",
    "sg:city":"Marietta",
    "sg:classifiers":[
        {
            "category":"Retail",
            "subcategory":"Self-service Laundry",
            "type":"Services"
        }
    ],
    "sg:phone":"+1 770 578 1967",
    "sg:postcode":"30062",
    "sg:province":"GA",
    "sg:tags":[
        "coin"
    ],
    "wof:name":"Gold Coin Inc",
    "wof:placetype":"venue"
},
  "geometry": {"coordinates":[-84.427132,33.994263],"type":"Point"}
}