{
  "type": "Feature",
  "properties": {
    "addr:full":"2700 Braselton Hwy Suite 10319 Dacula GA 30019",
    "addr:housenumber":"2700",
    "addr:postcode":"10319;ga 30019",
    "addr:street":"Braselton Hwy Suite",
    "iso:country":"US",
    "sg:address":"2700 Braselton Hwy Suite 10319",
    "sg:city":"Dacula",
    "sg:classifiers":[
        {
            "category":"Real Estate",
            "subcategory":"Real Estate Services",
            "type":"Services"
        },
        {
            "category":"Personal",
            "type":"Services"
        },
        {
            "category":"Banks & Credit Unions",
            "subcategory":"Financial Services",
            "type":"Services"
        },
        {
            "category":"Building & Trades",
            "subcategory":"Cleaning & Sanitation",
            "type":"Services"
        }
    ],
    "sg:phone":"+1 678 886 1357",
    "sg:postcode":"30019",
    "sg:province":"GA",
    "sg:tags":[
        "boarding",
        "house",
        "contractor",
        "eviction",
        "maintenance",
        "property"
    ],
    "sg:website":"http://www.homelogicproperties.com",
    "wof:name":"HomeLogic Properties",
    "wof:placetype":"venue"
},
  "geometry": {"coordinates":[-83.929543,34.04961],"type":"Point"}
}