{
  "type": "Feature",
  "properties": {
    "addr:full":"939 Peachtree St NE Atlanta GA 30309",
    "addr:housenumber":"939",
    "addr:postcode":"30309",
    "addr:street":"Peachtree St Ne",
    "iso:country":"US",
    "sg:address":"939 Peachtree St NE",
    "sg:city":"Atlanta",
    "sg:classifiers":[
        {
            "category":"Personal",
            "subcategory":"Hair Removal",
            "type":"Services"
        }
    ],
    "sg:phone":"+1 800 506 7985",
    "sg:postcode":"30309",
    "sg:province":"GA",
    "wof:name":"Laser Perfect",
    "wof:placetype":"venue"
},
  "geometry": {"coordinates":[-84.384103,33.780451],"type":"Point"}
}