{
  "type": "Feature",
  "properties": {
    "iso:country":"US",
    "sg:address":"184 Jefferson Pkwy",
    "sg:city":"Newnan",
    "sg:classifiers":[
        {
            "category":"Professional",
            "subcategory":"Management & Consulting",
            "type":"Services"
        }
    ],
    "sg:phone":"+1 770 304 9637",
    "sg:postcode":"30263",
    "sg:province":"GA",
    "wof:name":"Salomon Smith Barney",
    "wof:placetype":"venue"
},
  "geometry": {"coordinates":[-84.76863899999999,33.39675],"type":"Point"}
}