{
  "type": "Feature",
  "properties": {
    "addr:full":"2800 Spring Road Suite J Atlanta GA 30339",
    "addr:housenumber":"2800",
    "addr:postcode":"30339",
    "addr:street":"Spring Road Suite J",
    "iso:country":"US",
    "sg:address":"2800 Spring Road Suite J",
    "sg:city":"Atlanta",
    "sg:classifiers":[
        {
            "category":"Personal",
            "subcategory":"Beauty Salon",
            "type":"Services"
        }
    ],
    "sg:phone":"+1 770 334 7970",
    "sg:postcode":"30339",
    "sg:province":"GA",
    "sg:tags":[
        "makeup",
        "artist"
    ],
    "sg:website":"wetpaintmakeup.com",
    "wof:name":"Wet Paint Makeup Shop",
    "wof:placetype":"venue"
},
  "geometry": {"coordinates":[-84.472915,33.884819],"type":"Point"}
}