{
  "type": "Feature",
  "properties": {
    "addr:full":"8511 Waters Ave Savannah GA 31406",
    "addr:housenumber":"8511",
    "addr:postcode":"31406",
    "addr:street":"Waters Ave",
    "iso:country":"US",
    "sg:address":"8511 Waters Ave",
    "sg:city":"Savannah",
    "sg:classifiers":[
        {
            "category":"Organizations",
            "subcategory":"Religious Organization",
            "type":"Services"
        }
    ],
    "sg:phone":"+1 912 925 9060",
    "sg:postcode":"31406",
    "sg:province":"GA",
    "sg:tags":[
        "church"
    ],
    "wof:name":"Living Waters Assembly Of God",
    "wof:placetype":"venue"
},
  "geometry": {"coordinates":[-81.104929,31.988683],"type":"Point"}
}