{
  "type": "Feature",
  "properties": {
    "iso:country":"US",
    "sg:address":"12195 State Hwy 92",
    "sg:city":"Woodstock",
    "sg:classifiers":[
        {
            "category":"Restaurant",
            "type":"Food & Drink"
        },
        {
            "category":"Bars & Pubs",
            "type":"Food & Drink"
        }
    ],
    "sg:phone":"+1 770 924 5594",
    "sg:postcode":"30188",
    "sg:province":"GA",
    "wof:name":"Firehouse Food & Spirits",
    "wof:placetype":"venue"
},
  "geometry": {"coordinates":[-84.48148500000001,34.087612],"type":"Point"}
}