{
  "type": "Feature",
  "properties": {
    "iso:country":"US",
    "sg:address":"101 Woodard St",
    "sg:city":"Dublin",
    "sg:classifiers":[
        {
            "category":"Organizations",
            "subcategory":"Religious Organization",
            "type":"Services"
        }
    ],
    "sg:phone":"+1 478 272 7220",
    "sg:postcode":"31021",
    "sg:province":"GA",
    "sg:tags":[
        "church"
    ],
    "wof:name":"Greengrove Baptist Church",
    "wof:placetype":"venue"
},
  "geometry": {"coordinates":[-82.916968,32.523882],"type":"Point"}
}