{
  "type": "Feature",
  "properties": {
    "addr:full":"11130 Weeping Willow Pl Hampton GA 30228",
    "addr:housenumber":"11130",
    "addr:postcode":"30228",
    "addr:street":"Weeping Willow Pl",
    "iso:country":"US",
    "sg:address":"11130 Weeping Willow Pl",
    "sg:city":"Hampton",
    "sg:classifiers":[
        {
            "category":"Building & Trades",
            "subcategory":"Cleaning & Sanitation",
            "type":"Services"
        }
    ],
    "sg:phone":"+1 770 478 5010",
    "sg:postcode":"30228",
    "sg:province":"GA",
    "sg:tags":[
        "maintenance"
    ],
    "wof:name":"D&S Cleaning Service",
    "wof:placetype":"venue"
},
  "geometry": {"coordinates":[-84.334631,33.45102],"type":"Point"}
}