{
  "type": "Feature",
  "properties": {
    "iso:country":"US",
    "sg:address":"8401 Ferguson Ave",
    "sg:city":"Savannah",
    "sg:classifiers":[
        {
            "category":"Retail",
            "subcategory":"Laundry & Dry Cleaning",
            "type":"Services"
        }
    ],
    "sg:phone":"+1 912 354 2611",
    "sg:postcode":"31406",
    "sg:province":"GA",
    "sg:tags":[
        "garment",
        "agent",
        "cleaners"
    ],
    "wof:name":"Clifton's Dry Cleaners",
    "wof:placetype":"venue"
},
  "geometry": {"coordinates":[-81.07513299999999,31.984605],"type":"Point"}
}