{
  "type": "Feature",
  "properties": {
    "addr:full":"296 Roy Huie Rd Riverdale GA 30274",
    "addr:housenumber":"296",
    "addr:postcode":"30274",
    "addr:street":"Roy Huie Rd",
    "iso:country":"US",
    "sg:address":"296 Roy Huie Rd",
    "sg:city":"Riverdale",
    "sg:classifiers":[
        {
            "category":"Education",
            "subcategory":"College",
            "type":"Public Place"
        },
        {
            "category":"Real Estate",
            "subcategory":"Real Estate Operator",
            "type":"Services"
        }
    ],
    "sg:phone":"+1 770 997 7800",
    "sg:postcode":"30274",
    "sg:province":"GA",
    "sg:tags":[
        "housing",
        "apartment",
        "student"
    ],
    "wof:name":"Stone Gate Townhome Rentals",
    "wof:placetype":"venue"
},
  "geometry": {"coordinates":[-84.39931799999999,33.583022],"type":"Point"}
}