{
  "type": "Feature",
  "properties": {
    "addr:full":"4119 Rocky Ford Rd Valdosta GA 31601",
    "addr:housenumber":"4119",
    "addr:postcode":"31601",
    "addr:street":"Rocky Ford Rd",
    "iso:country":"US",
    "sg:address":"4119 Rocky Ford Rd",
    "sg:city":"Valdosta",
    "sg:classifiers":[
        {
            "category":"Building & Trades",
            "subcategory":"Construction",
            "type":"Services"
        }
    ],
    "sg:phone":"+1 229 245 7240",
    "sg:postcode":"31601",
    "sg:province":"GA",
    "sg:tags":[
        "steel",
        "fabrication",
        "welding"
    ],
    "wof:name":"Western Carolina Steel Forms",
    "wof:placetype":"venue"
},
  "geometry": {"coordinates":[-83.38188599999999,30.746805],"type":"Point"}
}