{
  "type": "Feature",
  "properties": {
    "addr:full":"115 Margie Dr Warner Robins GA 31093",
    "addr:housenumber":"115",
    "addr:postcode":"31093",
    "addr:street":"Margie Dr",
    "iso:country":"US",
    "sg:address":"115 Margie Dr",
    "sg:city":"Warner Robins",
    "sg:classifiers":[
        {
            "category":"Shopping",
            "subcategory":"Books",
            "type":"Retail Goods"
        }
    ],
    "sg:phone":"+1 478 971 2677",
    "sg:postcode":"31093",
    "sg:province":"GA",
    "sg:tags":[
        "bookstore"
    ],
    "wof:name":"Lamb's Well the",
    "wof:placetype":"venue"
},
  "geometry": {"coordinates":[-83.64969600000001,32.6409],"type":"Point"}
}