{
  "type": "Feature",
  "properties": {
    "addr:full":"6525 Professional Pl Riverdale GA 30274",
    "addr:housenumber":"6525",
    "addr:postcode":"30274",
    "addr:street":"Professional Pl",
    "iso:country":"US",
    "sg:address":"6525 Professional Pl",
    "sg:city":"Riverdale",
    "sg:classifiers":[
        {
            "category":"Health Services",
            "subcategory":"Doctor",
            "type":"Services"
        }
    ],
    "sg:phone":"+1 770 991 2800",
    "sg:postcode":"30274",
    "sg:province":"GA",
    "sg:tags":[
        "throat",
        "medical",
        "ear",
        "nose"
    ],
    "wof:name":"Herman Howard K MD",
    "wof:placetype":"venue"
},
  "geometry": {"coordinates":[-84.396004,33.576199],"type":"Point"}
}