{
  "type": "Feature",
  "properties": {
    "iso:country":"US",
    "sg:address":"4321 Abbotts Bridge Rd",
    "sg:city":"Duluth",
    "sg:classifiers":[
        {
            "category":"Retail",
            "subcategory":"Laundry & Dry Cleaning",
            "type":"Services"
        }
    ],
    "sg:phone":"+1 770 476 5504",
    "sg:postcode":"30097",
    "sg:province":"GA",
    "sg:tags":[
        "cleaners"
    ],
    "wof:name":"D J Cleaners",
    "wof:placetype":"venue"
},
  "geometry": {"coordinates":[-84.161355,34.020686],"type":"Point"}
}