{
  "type": "Feature",
  "properties": {
    "iso:country":"US",
    "sg:address":"664 W Bankhead Hwy",
    "sg:city":"Villa Rica",
    "sg:classifiers":[
        {
            "category":"Restaurant",
            "type":"Food & Drink"
        }
    ],
    "sg:phone":"+1 770 459 8400",
    "sg:postcode":"30180",
    "sg:province":"GA",
    "sg:tags":[
        "eating"
    ],
    "wof:name":"Romeros Itln & Greek Cuisine",
    "wof:placetype":"venue"
},
  "geometry": {"coordinates":[-84.936256,33.730565],"type":"Point"}
}