{
  "type": "Feature",
  "properties": {
    "addr:full":"313 Cattlemans Cir Mcdonough GA 30248",
    "addr:housenumber":"313",
    "addr:postcode":"30248",
    "addr:street":"Cattlemans Cir",
    "iso:country":"US",
    "sg:address":"313 Cattlemans Cir",
    "sg:city":"Mcdonough",
    "sg:classifiers":[
        {
            "category":"Shopping",
            "subcategory":"Catalog Store",
            "type":"Retail Goods"
        }
    ],
    "sg:phone":"+1 770 898 0611",
    "sg:postcode":"30248",
    "sg:province":"GA",
    "sg:tags":[
        "mail",
        "order"
    ],
    "wof:name":"Beabos",
    "wof:placetype":"venue"
},
  "geometry": {"coordinates":[-84.06050999999999,33.420757],"type":"Point"}
}