{
  "type": "Feature",
  "properties": {
    "addr:full":"643 Campbell Hill St NW Marietta GA 30060",
    "addr:housenumber":"643",
    "addr:postcode":"30060",
    "addr:street":"Campbell Hill St Nw",
    "iso:country":"US",
    "sg:address":"643 Campbell Hill St NW",
    "sg:city":"Marietta",
    "sg:classifiers":[
        {
            "category":"Health Services",
            "subcategory":"Doctor",
            "type":"Services"
        }
    ],
    "sg:phone":"+1 770 427 0285",
    "sg:postcode":"30060",
    "sg:province":"GA",
    "sg:tags":[
        "medical"
    ],
    "wof:name":"Laurie Leigh Robbins MD",
    "wof:placetype":"venue"
},
  "geometry": {"coordinates":[-84.55206800000001,33.968722],"type":"Point"}
}