{
  "type": "Feature",
  "properties": {
    "iso:country":"US",
    "sg:address":"2138 Martin Luther King Jr Blvd",
    "sg:city":"Augusta",
    "sg:classifiers":[
        {
            "category":"Personal",
            "subcategory":"Beauty Salon",
            "type":"Services"
        }
    ],
    "sg:phone":"+1 706 724 9682",
    "sg:postcode":"30901",
    "sg:province":"GA",
    "sg:tags":[
        "shop"
    ],
    "wof:name":"William Beauty Shop",
    "wof:placetype":"venue"
},
  "geometry": {"coordinates":[-81.997867,33.451263],"type":"Point"}
}