{
  "type": "Feature",
  "properties": {
    "iso:country":"US",
    "sg:address":"243 Haas Ave SE",
    "sg:city":"Atlanta",
    "sg:classifiers":[
        {
            "category":"Professional",
            "subcategory":"Art Services",
            "type":"Services"
        }
    ],
    "sg:phone":"+1 404 728 1993",
    "sg:postcode":"30316",
    "sg:province":"GA",
    "sg:tags":[
        "artist"
    ],
    "wof:name":"Art Illustration Design",
    "wof:placetype":"venue"
},
  "geometry": {"coordinates":[-84.344453,33.746584],"type":"Point"}
}