{
  "type": "Feature",
  "properties": {
    "addr:full":"408 Melanie St Woodstock GA 30188",
    "addr:housenumber":"408",
    "addr:postcode":"30188",
    "addr:street":"Melanie St",
    "iso:country":"US",
    "sg:address":"408 Melanie St",
    "sg:city":"Woodstock",
    "sg:classifiers":[
        {
            "category":"Professional",
            "type":"Services"
        }
    ],
    "sg:phone":"+1 770 592 6251",
    "sg:postcode":"30188",
    "sg:province":"GA",
    "wof:name":"H & M Meyer Inc",
    "wof:placetype":"venue"
},
  "geometry": {"coordinates":[-84.47601899999999,34.123599],"type":"Point"}
}