{
  "type": "Feature",
  "properties": {
    "iso:country":"US",
    "sg:address":"1939 Ed Bennett Rd",
    "sg:city":"Nicholson",
    "sg:classifiers":[
        {
            "category":"Building & Trades",
            "subcategory":"Construction",
            "type":"Services"
        }
    ],
    "sg:phone":"+1 706 208 0804",
    "sg:postcode":"30565",
    "sg:province":"GA",
    "sg:tags":[
        "general",
        "contractor"
    ],
    "wof:name":"Farmco Athens Inc",
    "wof:placetype":"venue"
},
  "geometry": {"coordinates":[-83.408457,34.056387],"type":"Point"}
}