{
  "type": "Feature",
  "properties": {
    "iso:country":"US",
    "sg:address":"3030 Headland Dr SW",
    "sg:city":"Atlanta",
    "sg:classifiers":[
        {
            "category":"Personal",
            "subcategory":"Barber",
            "type":"Services"
        }
    ],
    "sg:phone":"+1 404 494 3535",
    "sg:postcode":"30311",
    "sg:province":"GA",
    "sg:website":"www.firstclassbarbershop.com",
    "wof:name":"First Class Barber Shop",
    "wof:placetype":"venue"
},
  "geometry": {"coordinates":[-84.486603,33.689602],"type":"Point"}
}