{
  "type": "Feature",
  "properties": {
    "addr:full":"2231 Weatherstone Cir SE Conyers GA 30094",
    "addr:housenumber":"2231",
    "addr:postcode":"30094",
    "addr:street":"Weatherstone Cir Se",
    "iso:country":"US",
    "sg:address":"2231 Weatherstone Cir SE",
    "sg:city":"Conyers",
    "sg:classifiers":[
        {
            "category":"Farming",
            "subcategory":"Farm & Veterinary Services",
            "type":"Manufacturing & Wholesale Goods"
        }
    ],
    "sg:phone":"+1 770 929 0884",
    "sg:postcode":"30094",
    "sg:province":"GA",
    "sg:tags":[
        "consultant",
        "irrigation"
    ],
    "sg:website":"www.irrcons.com",
    "wof:name":"Irrigation Consultant Svc",
    "wof:placetype":"venue"
},
  "geometry": {"coordinates":[-84.023335,33.631037],"type":"Point"}
}