{
  "type": "Feature",
  "properties": {
    "iso:country":"US",
    "sg:address":"4060 Bay Creek Church Rd",
    "sg:city":"Loganville",
    "sg:classifiers":[
        {
            "category":"Home & Garden",
            "subcategory":"Home Furnishings",
            "type":"Retail Goods"
        }
    ],
    "sg:phone":"+1 770 466 4811",
    "sg:postcode":"30052",
    "sg:province":"GA",
    "sg:tags":[
        "curtain",
        "fixture",
        "drapery"
    ],
    "sg:website":"www.euro-elegance.com",
    "wof:name":"Silent Gliss USA Inc",
    "wof:placetype":"venue"
},
  "geometry": {"coordinates":[-83.854573,33.841279],"type":"Point"}
}