{
  "type": "Feature",
  "properties": {
    "addr:full":"300 E Main St Ste C Statesboro GA 30458",
    "addr:housenumber":"300",
    "addr:postcode":"30458",
    "addr:street":"E Main St Ste C",
    "iso:country":"US",
    "sg:address":"300 E Main St Ste C",
    "sg:city":"Statesboro",
    "sg:classifiers":[
        {
            "category":"Personal",
            "subcategory":"Beauty Salon",
            "type":"Services"
        },
        {
            "category":"Personal",
            "subcategory":"Barber",
            "type":"Services"
        }
    ],
    "sg:phone":"+1 912 489 6972",
    "sg:postcode":"30458",
    "sg:province":"GA",
    "wof:name":"Shantoria's Salon & Tan",
    "wof:placetype":"venue"
},
  "geometry": {"coordinates":[-81.793479,32.451147],"type":"Point"}
}