{
  "type": "Feature",
  "properties": {
    "iso:country":"US",
    "sg:address":"41 W Main St",
    "sg:city":"Statesboro",
    "sg:classifiers":[
        {
            "category":"Personal",
            "subcategory":"Shoe Repair & Shine",
            "type":"Services"
        }
    ],
    "sg:phone":"+1 912 764 5268",
    "sg:postcode":"30458",
    "sg:province":"GA",
    "sg:tags":[
        "repairing",
        "boot"
    ],
    "wof:name":"W & J Discount Shoe Repair",
    "wof:placetype":"venue"
},
  "geometry": {"coordinates":[-81.78555299999999,32.449129],"type":"Point"}
}