{
  "type": "Feature",
  "properties": {
    "iso:country":"US",
    "sg:address":"609 Short E St",
    "sg:city":"Thomaston",
    "sg:classifiers":[
        {
            "category":"Home & Garden",
            "subcategory":"Garden Supply",
            "type":"Retail Goods"
        }
    ],
    "sg:phone":"+1 706 647 7858",
    "sg:postcode":"30286",
    "sg:province":"GA",
    "sg:tags":[
        "nurseryman"
    ],
    "wof:name":"Little Garden Ctr & Greenhouse",
    "wof:placetype":"venue"
},
  "geometry": {"coordinates":[-84.328265,32.902146],"type":"Point"}
}