{
  "type": "Feature",
  "properties": {
    "addr:full":"Highway 49 & I 75 Byron GA 31008",
    "addr:housenumber":"75",
    "addr:postcode":"31008",
    "addr:street":"Highway 49 & I",
    "iso:country":"US",
    "sg:address":"Highway 49 & I 75",
    "sg:city":"Byron",
    "sg:classifiers":[
        {
            "category":"Shopping",
            "subcategory":"Clothing, Apparel, & Fashions",
            "type":"Retail Goods"
        }
    ],
    "sg:phone":"+1 478 956 2435",
    "sg:postcode":"31008",
    "sg:province":"GA",
    "sg:tags":[
        "accessory"
    ],
    "wof:name":"Dress Barn Inc",
    "wof:placetype":"venue"
},
  "geometry": {"coordinates":[-83.758003,32.656101],"type":"Point"}
}