{
  "type": "Feature",
  "properties": {
    "iso:country":"US",
    "sg:address":"109 Harbor Loop",
    "sg:city":"Dallas",
    "sg:classifiers":[
        {
            "category":"Personal",
            "type":"Services"
        }
    ],
    "sg:phone":"+1 770 443 8671",
    "sg:postcode":"30157",
    "sg:province":"GA",
    "wof:name":"Rays Residential Handyman",
    "wof:placetype":"venue"
},
  "geometry": {"coordinates":[-84.726545,33.928604],"type":"Point"}
}