{
  "type": "Feature",
  "properties": {
    "addr:full":"2122 N Point Cir Alpharetta GA 30022",
    "addr:housenumber":"2122",
    "addr:postcode":"30022",
    "addr:street":"N Point Cir",
    "iso:country":"US",
    "sg:address":"2122 N Point Cir",
    "sg:city":"Alpharetta",
    "sg:classifiers":[
        {
            "category":"Shopping",
            "subcategory":"Shoes",
            "type":"Retail Goods"
        }
    ],
    "sg:phone":"+1 770 751 9919",
    "sg:postcode":"30022",
    "sg:province":"GA",
    "sg:tags":[
        "store"
    ],
    "sg:website":"www.striderite.com",
    "wof:name":"Stride Rite",
    "wof:placetype":"venue"
},
  "geometry": {"coordinates":[-84.29450199999999,34.051102],"type":"Point"}
}