{
  "type": "Feature",
  "properties": {
    "iso:country":"US",
    "sg:address":"237 Upper Riverdale Rd",
    "sg:city":"Riverdale",
    "sg:classifiers":[
        {
            "category":"Health Services",
            "subcategory":"Doctor",
            "type":"Services"
        }
    ],
    "sg:phone":"+1 770 909 6345",
    "sg:postcode":"30236",
    "sg:province":"GA",
    "sg:tags":[
        "clinic"
    ],
    "wof:name":"Women's Health Research",
    "wof:placetype":"venue"
},
  "geometry": {"coordinates":[-84.38002299999999,33.580457],"type":"Point"}
}