{
  "type": "Feature",
  "properties": {
    "addr:full":"674 Morrow Industrial Blvd Jonesboro GA 30236",
    "addr:housenumber":"674",
    "addr:postcode":"30236",
    "addr:street":"Morrow Industrial Blvd",
    "iso:country":"US",
    "sg:address":"674 Morrow Industrial Blvd",
    "sg:city":"Jonesboro",
    "sg:classifiers":[
        {
            "category":"Professional",
            "subcategory":"Employment Agencies",
            "type":"Services"
        }
    ],
    "sg:phone":"+1 770 960 8701",
    "sg:postcode":"30236",
    "sg:province":"GA",
    "sg:tags":[
        "temporary",
        "help"
    ],
    "wof:name":"Deo Personnel Services",
    "wof:placetype":"venue"
},
  "geometry": {"coordinates":[-84.365695,33.572933],"type":"Point"}
}