{
  "type": "Feature",
  "properties": {
    "addr:full":"4351 Orchard Park Ct Stone Mountain GA 30083",
    "addr:housenumber":"4351",
    "addr:postcode":"30083",
    "addr:street":"Orchard Park Ct",
    "iso:country":"US",
    "sg:address":"4351 Orchard Park Ct",
    "sg:city":"Stone Mountain",
    "sg:classifiers":[
        {
            "category":"Professional",
            "subcategory":"Management & Consulting",
            "type":"Services"
        }
    ],
    "sg:phone":"+1 678 768 1838",
    "sg:postcode":"30083",
    "sg:province":"GA",
    "wof:name":"Anderson Business Solutions",
    "wof:placetype":"venue"
},
  "geometry": {"coordinates":[-84.21293799999999,33.819217],"type":"Point"}
}