{
  "type": "Feature",
  "properties": {
    "iso:country":"US",
    "sg:address":"3391 Executive Ln",
    "sg:city":"Winston",
    "sg:classifiers":[
        {
            "category":"Wholesale",
            "subcategory":"Construction Materials",
            "type":"Manufacturing & Wholesale Goods"
        },
        {
            "category":"Home & Garden",
            "subcategory":"Building Materials",
            "type":"Retail Goods"
        }
    ],
    "sg:phone":"+1 770 920 0429",
    "sg:postcode":"30187",
    "sg:province":"GA",
    "sg:tags":[
        "lumber"
    ],
    "wof:name":"Georgia Industrial Lumber Sup",
    "wof:placetype":"venue"
},
  "geometry": {"coordinates":[-84.786357,33.713253],"type":"Point"}
}