{
  "type": "Feature",
  "properties": {
    "addr:full":"12136 S Main St Trenton GA 30752",
    "addr:housenumber":"12136",
    "addr:postcode":"30752",
    "addr:street":"S Main St",
    "iso:country":"US",
    "sg:address":"12136 S Main St",
    "sg:city":"Trenton",
    "sg:classifiers":[
        {
            "category":"Banks & Credit Unions",
            "subcategory":"Bank",
            "type":"Services"
        }
    ],
    "sg:phone":"+1 706 657 4060",
    "sg:postcode":"30752",
    "sg:province":"GA",
    "sg:tags":[
        "cashing",
        "check"
    ],
    "wof:name":"Cash Place",
    "wof:placetype":"venue"
},
  "geometry": {"coordinates":[-85.511088,34.869526],"type":"Point"}
}