{
  "type": "Feature",
  "properties": {
    "iso:country":"US",
    "sg:address":"1668 Talmadge Dr",
    "sg:city":"Toccoa",
    "sg:classifiers":[
        {
            "category":"Organizations",
            "subcategory":"Religious Organization",
            "type":"Services"
        }
    ],
    "sg:phone":"+1 706 297 7978",
    "sg:postcode":"30563",
    "sg:province":"GA",
    "sg:tags":[
        "church"
    ],
    "wof:name":"CACOG",
    "wof:placetype":"venue"
},
  "geometry": {"coordinates":[-83.41172400000001,34.613441],"type":"Point"}
}