{
  "type": "Feature",
  "properties": {
    "addr:full":"1575 Northside Pkwy NW Atlanta GA 30318",
    "addr:housenumber":"1575",
    "addr:postcode":"30318",
    "addr:street":"Northside Pkwy Nw",
    "iso:country":"US",
    "sg:address":"1575 Northside Pkwy NW",
    "sg:city":"Atlanta",
    "sg:classifiers":[
        {
            "category":"Real Estate",
            "subcategory":"Developer",
            "type":"Services"
        }
    ],
    "sg:phone":"+1 404 352 2800",
    "sg:postcode":"30318",
    "sg:province":"GA",
    "sg:website":"www.lecraw.com",
    "wof:name":"Julian Le Craw & Co",
    "wof:placetype":"venue"
},
  "geometry": {"coordinates":[-84.40776700000001,33.798965],"type":"Point"}
}