{
  "type": "Feature",
  "properties": {
    "addr:full":"100 Leo St Eatonton GA 31024",
    "addr:housenumber":"100",
    "addr:postcode":"31024",
    "addr:street":"Leo St",
    "iso:country":"US",
    "sg:address":"100 Leo St",
    "sg:city":"Eatonton",
    "sg:classifiers":[
        {
            "category":"Professional",
            "type":"Services"
        }
    ],
    "sg:phone":"+1 706 484 9886",
    "sg:postcode":"31024",
    "sg:province":"GA",
    "wof:name":"Eagle One LLC",
    "wof:placetype":"venue"
},
  "geometry": {"coordinates":[-83.377031,33.315971],"type":"Point"}
}