{
  "type": "Feature",
  "properties": {
    "iso:country":"US",
    "sg:address":"163 Ponce de Leon Ave NE",
    "sg:city":"Atlanta",
    "sg:classifiers":[
        {
            "category":"Restaurant",
            "type":"Food & Drink"
        }
    ],
    "sg:phone":"+1 404 876 8532",
    "sg:postcode":"30308",
    "sg:province":"GA",
    "sg:tags":[
        "eating"
    ],
    "wof:name":"Philippes Beastreu",
    "wof:placetype":"venue"
},
  "geometry": {"coordinates":[-84.38287099999999,33.77236],"type":"Point"}
}