{
  "type": "Feature",
  "properties": {
    "addr:full":"2200 Roswell Rd Marietta GA 30062",
    "addr:housenumber":"2200",
    "addr:postcode":"30062",
    "addr:street":"Roswell Rd",
    "iso:country":"US",
    "sg:address":"2200 Roswell Rd",
    "sg:city":"Marietta",
    "sg:classifiers":[
        {
            "category":"Shopping",
            "subcategory":"Mobile Phones",
            "type":"Retail Goods"
        }
    ],
    "sg:phone":"+1 770 321 0006",
    "sg:postcode":"30062",
    "sg:province":"GA",
    "wof:name":"J C Wireless",
    "wof:placetype":"venue"
},
  "geometry": {"coordinates":[-84.48809799999999,33.970402],"type":"Point"}
}