{
  "type": "Feature",
  "properties": {
    "addr:full":"912 Killian Hill Rd SW Lilburn GA 30047",
    "addr:housenumber":"912",
    "addr:postcode":"30047",
    "addr:street":"Killian Hill Rd Sw",
    "iso:country":"US",
    "sg:address":"912 Killian Hill Rd SW",
    "sg:city":"Lilburn",
    "sg:classifiers":[
        {
            "category":"Banks & Credit Unions",
            "subcategory":"Investment Brokerage",
            "type":"Services"
        }
    ],
    "sg:phone":"+1 770 935 9575",
    "sg:postcode":"30047",
    "sg:province":"GA",
    "sg:tags":[
        "advisory",
        "financial"
    ],
    "wof:name":"Izett & Assoc",
    "wof:placetype":"venue"
},
  "geometry": {"coordinates":[-84.095922,33.869033],"type":"Point"}
}