{
  "type": "Feature",
  "properties": {
    "addr:full":"1568 Townsend Rd Villa Rica GA 30180",
    "addr:housenumber":"1568",
    "addr:postcode":"30180",
    "addr:street":"Townsend Rd",
    "iso:country":"US",
    "sg:address":"1568 Townsend Rd",
    "sg:city":"Villa Rica",
    "sg:classifiers":[
        {
            "category":"Wholesale",
            "subcategory":"Construction Materials",
            "type":"Manufacturing & Wholesale Goods"
        }
    ],
    "sg:phone":"+1 770 459 0064",
    "sg:postcode":"30180",
    "sg:province":"GA",
    "sg:tags":[
        "fence"
    ],
    "wof:name":"New Georgia Fence Co",
    "wof:placetype":"venue"
},
  "geometry": {"coordinates":[-84.89434199999999,33.791334],"type":"Point"}
}