{
  "type": "Feature",
  "properties": {
    "addr:full":"2637 Cobb Pkwy SE Smyrna GA 30080",
    "addr:housenumber":"2637",
    "addr:postcode":"30080",
    "addr:street":"Cobb Pkwy Se",
    "iso:country":"US",
    "sg:address":"2637 Cobb Pkwy SE",
    "sg:city":"Smyrna",
    "sg:classifiers":[
        {
            "category":"Restaurant",
            "type":"Food & Drink"
        }
    ],
    "sg:menulink":"http://www.allmenus.com/ga/northeast-cobb/189983-kfc---kentucky-fried-chicken/menu/",
    "sg:phone":"+1 770 850 0940",
    "sg:postcode":"30080",
    "sg:province":"GA",
    "sg:tags":[
        "american",
        "chicken"
    ],
    "wof:name":"KFC - Kentucky Fried Chicken",
    "wof:placetype":"venue"
},
  "geometry": {"coordinates":[-84.47378,33.889215],"type":"Point"}
}