{
  "type": "Feature",
  "properties": {
    "iso:country":"US",
    "sg:address":"205 Monck St",
    "sg:city":"Brunswick",
    "sg:classifiers":[
        {
            "category":"Home & Garden",
            "subcategory":"Hardware",
            "type":"Retail Goods"
        }
    ],
    "sg:phone":"+1 912 265 1321",
    "sg:postcode":"31520",
    "sg:province":"GA",
    "wof:name":"Georgia Ace Hardware",
    "wof:placetype":"venue"
},
  "geometry": {"coordinates":[-81.495362,31.1477],"type":"Point"}
}