{
  "type": "Feature",
  "properties": {
    "addr:full":"450 S Hill St Buford GA 30518",
    "addr:housenumber":"450",
    "addr:postcode":"30518",
    "addr:street":"S Hill St",
    "iso:country":"US",
    "sg:address":"450 S Hill St",
    "sg:city":"Buford",
    "sg:classifiers":[
        {
            "category":"Personal",
            "subcategory":"Beauty Salon",
            "type":"Services"
        }
    ],
    "sg:phone":"+1 678 765 2880",
    "sg:postcode":"30518",
    "sg:province":"GA",
    "wof:name":"Tiger Lily Salon & Boutique",
    "wof:placetype":"venue"
},
  "geometry": {"coordinates":[-83.998625,34.118773],"type":"Point"}
}