{
  "type": "Feature",
  "properties": {
    "iso:country":"US",
    "sg:address":"121 W Jones St",
    "sg:city":"Savannah",
    "sg:classifiers":[
        {
            "category":"Travel",
            "subcategory":"Hotels & Motels",
            "type":"Entertainment"
        }
    ],
    "sg:phone":"+1 912 233 5307",
    "sg:postcode":"31401",
    "sg:province":"GA",
    "sg:tags":[
        "breakfast",
        "accommodation",
        "bed"
    ],
    "wof:name":"Zeigler House",
    "wof:placetype":"venue"
},
  "geometry": {"coordinates":[-81.09649,32.072914],"type":"Point"}
}