{
  "type": "Feature",
  "properties": {
    "iso:country":"US",
    "sg:address":"4952 Brookside Way",
    "sg:city":"Duluth",
    "sg:classifiers":[
        {
            "category":"Building & Trades",
            "subcategory":"Construction",
            "type":"Services"
        }
    ],
    "sg:phone":"+1 404 295 9072",
    "sg:postcode":"30096",
    "sg:province":"GA",
    "sg:tags":[
        "hanging",
        "contractor"
    ],
    "wof:name":"Hermenegildo Gamez",
    "wof:placetype":"venue"
},
  "geometry": {"coordinates":[-84.18484100000001,33.950054],"type":"Point"}
}