{
  "type": "Feature",
  "properties": {
    "iso:country":"US",
    "sg:address":"5595 Attucks Blvd",
    "sg:city":"Morrow",
    "sg:classifiers":[
        {
            "category":"Shopping",
            "subcategory":"Books",
            "type":"Retail Goods"
        }
    ],
    "sg:phone":"+1 404 362 9159",
    "sg:postcode":"30260",
    "sg:province":"GA",
    "sg:tags":[
        "dealer"
    ],
    "wof:name":"Dannie's First Year Books",
    "wof:placetype":"venue"
},
  "geometry": {"coordinates":[-84.32033300000001,33.605082],"type":"Point"}
}