{
  "type": "Feature",
  "properties": {
    "iso:country":"US",
    "sg:address":"5741 Pineview Ave",
    "sg:city":"Columbus",
    "sg:classifiers":[
        {
            "category":"Professional",
            "type":"Services"
        }
    ],
    "sg:phone":"+1 706 221 7459",
    "sg:postcode":"31909",
    "sg:province":"GA",
    "wof:name":"Darlene Black",
    "wof:placetype":"venue"
},
  "geometry": {"coordinates":[-84.957187,32.529144],"type":"Point"}
}