{
  "type": "Feature",
  "properties": {
    "addr:full":"403 E Pine St Fitzgerald GA 31750",
    "addr:housenumber":"403",
    "addr:postcode":"31750",
    "addr:street":"E Pine St",
    "iso:country":"US",
    "sg:address":"403 E Pine St",
    "sg:city":"Fitzgerald",
    "sg:classifiers":[
        {
            "category":"Food & Beverages",
            "subcategory":"Liquor & Beverages",
            "type":"Retail Goods"
        }
    ],
    "sg:phone":"+1 229 423 4584",
    "sg:postcode":"31750",
    "sg:province":"GA",
    "sg:tags":[
        "beer"
    ],
    "wof:name":"The Beverage Center",
    "wof:placetype":"venue"
},
  "geometry": {"coordinates":[-83.250197,31.713573],"type":"Point"}
}