{
  "type": "Feature",
  "properties": {
    "iso:country":"US",
    "sg:address":"601 N Main St",
    "sg:city":"Wrens",
    "sg:classifiers":[
        {
            "category":"Utilities",
            "subcategory":"Mobile Phone",
            "type":"Services"
        },
        {
            "category":"Communications",
            "type":"Services"
        }
    ],
    "sg:phone":"+1 706 547 0052",
    "sg:postcode":"30833",
    "sg:province":"GA",
    "sg:tags":[
        "communication",
        "radiotelephone"
    ],
    "wof:name":"Crossroads Communications",
    "wof:placetype":"venue"
},
  "geometry": {"coordinates":[-82.383589,33.215324],"type":"Point"}
}