{
  "type": "Feature",
  "properties": {
    "iso:country":"US",
    "sg:address":"3686 N Hwy 16",
    "sg:city":"Carrollton",
    "sg:classifiers":[
        {
            "category":"Food & Beverages",
            "subcategory":"Groceries & Convenience Stores",
            "type":"Retail Goods"
        }
    ],
    "sg:phone":"+1 770 836 8688",
    "sg:postcode":"30116",
    "sg:province":"GA",
    "wof:name":"Corner Amoco",
    "wof:placetype":"venue"
},
  "geometry": {"coordinates":[-84.980418,33.526848],"type":"Point"}
}