{
  "type": "Feature",
  "properties": {
    "addr:full":"3795 Buford Hwy NE Atlanta GA 30329",
    "addr:housenumber":"3795",
    "addr:postcode":"30329",
    "addr:street":"Buford Hwy Ne",
    "iso:country":"US",
    "sg:address":"3795 Buford Hwy NE",
    "sg:city":"Atlanta",
    "sg:classifiers":[
        {
            "category":"Building & Trades",
            "subcategory":"Locksmith",
            "type":"Services"
        }
    ],
    "sg:phone":"+1 866 802 5814",
    "sg:postcode":"30329",
    "sg:province":"GA",
    "sg:tags":[
        "key"
    ],
    "wof:name":"A 1 Lock & Locksmith",
    "wof:placetype":"venue"
},
  "geometry": {"coordinates":[-84.314789,33.855229],"type":"Point"}
}