{
  "type": "Feature",
  "properties": {
    "iso:country":"US",
    "sg:address":"306 Lowery Rd",
    "sg:city":"Fayetteville",
    "sg:classifiers":[
        {
            "category":"Retail",
            "subcategory":"Auto Repair",
            "type":"Services"
        }
    ],
    "sg:phone":"+1 770 719 8452",
    "sg:postcode":"30215",
    "sg:province":"GA",
    "sg:tags":[
        "general"
    ],
    "wof:name":"Cabinet Garage",
    "wof:placetype":"venue"
},
  "geometry": {"coordinates":[-84.415356,33.315876],"type":"Point"}
}