{
  "type": "Feature",
  "properties": {
    "iso:country":"US",
    "sg:address":"601 N Lee St",
    "sg:city":"Valdosta",
    "sg:classifiers":[
        {
            "category":"Government",
            "subcategory":"Office",
            "type":"Public Place"
        }
    ],
    "sg:phone":"+1 229 245 8711",
    "sg:postcode":"31601",
    "sg:province":"GA",
    "wof:name":"Lowndes County Infectious",
    "wof:placetype":"venue"
},
  "geometry": {"coordinates":[-83.278015,30.841011],"type":"Point"}
}