{
  "type": "Feature",
  "properties": {
    "iso:country":"US",
    "sg:address":"6325 Hospital Pkwy",
    "sg:city":"Johns Creek",
    "sg:classifiers":[
        {
            "category":"Health Services",
            "subcategory":"Doctor",
            "type":"Services"
        }
    ],
    "sg:phone":"+1 770 495 0016",
    "sg:postcode":"30097",
    "sg:province":"GA",
    "sg:tags":[
        "orthopedist"
    ],
    "wof:name":"Resurgens Orthopaedics St Josephs",
    "wof:placetype":"venue"
},
  "geometry": {"coordinates":[-84.17569,34.067041],"type":"Point"}
}