{
  "type": "Feature",
  "properties": {
    "iso:country":"US",
    "sg:address":"317 Acaro Ct",
    "sg:city":"Ellenwood",
    "sg:classifiers":[
        {
            "category":"Arts & Performance",
            "subcategory":"Dance",
            "type":"Entertainment"
        }
    ],
    "sg:phone":"+1 770 987 2777",
    "sg:postcode":"30294",
    "sg:province":"GA",
    "sg:tags":[
        "instruction",
        "dancing"
    ],
    "wof:name":"Lansprom Creative Dance Servic",
    "wof:placetype":"venue"
},
  "geometry": {"coordinates":[-84.219273,33.626184],"type":"Point"}
}