{
  "type": "Feature",
  "properties": {
    "addr:full":"6638 Mount Zion Blvd Morrow GA 30260",
    "addr:housenumber":"6638",
    "addr:postcode":"30260",
    "addr:street":"Mount Zion Blvd",
    "iso:country":"US",
    "sg:address":"6638 Mount Zion Blvd",
    "sg:city":"Morrow",
    "sg:classifiers":[
        {
            "category":"Building & Trades",
            "subcategory":"Construction",
            "type":"Services"
        }
    ],
    "sg:phone":"+1 770 401 8861",
    "sg:postcode":"30260",
    "sg:province":"GA",
    "sg:tags":[
        "house"
    ],
    "wof:name":"On Time Construction",
    "wof:placetype":"venue"
},
  "geometry": {"coordinates":[-84.304413,33.574104],"type":"Point"}
}