{
  "type": "Feature",
  "properties": {
    "addr:full":"307 Brickyard Rd Dalton GA 30721",
    "addr:housenumber":"307",
    "addr:postcode":"30721",
    "addr:street":"Brickyard Rd",
    "iso:country":"US",
    "sg:address":"307 Brickyard Rd",
    "sg:city":"Dalton",
    "sg:classifiers":[
        {
            "category":"Organizations",
            "subcategory":"Religious Organization",
            "type":"Services"
        }
    ],
    "sg:phone":"+1 706 277 5521",
    "sg:postcode":"30721",
    "sg:province":"GA",
    "sg:tags":[
        "church"
    ],
    "wof:name":"Mc Farland Hill Baptist Church",
    "wof:placetype":"venue"
},
  "geometry": {"coordinates":[-84.967449,34.725372],"type":"Point"}
}