{
  "type": "Feature",
  "properties": {
    "addr:full":"3301 Poplar Ridge Dr Rex GA 30273",
    "addr:housenumber":"3301",
    "addr:postcode":"30273",
    "addr:street":"Poplar Ridge Dr",
    "iso:country":"US",
    "sg:address":"3301 Poplar Ridge Dr",
    "sg:city":"Rex",
    "sg:classifiers":[
        {
            "category":"Manufacturing",
            "subcategory":"Metals",
            "type":"Manufacturing & Wholesale Goods"
        }
    ],
    "sg:phone":"+1 678 296 1145",
    "sg:postcode":"30273",
    "sg:province":"GA",
    "sg:tags":[
        "fabrication",
        "structural"
    ],
    "wof:name":"Lsj Designs",
    "wof:placetype":"venue"
},
  "geometry": {"coordinates":[-84.28364500000001,33.56656],"type":"Point"}
}