{
  "type": "Feature",
  "properties": {
    "addr:full":"221 E Taylor St Savannah GA 31401",
    "addr:housenumber":"221",
    "addr:postcode":"31401",
    "addr:street":"E Taylor St",
    "iso:country":"US",
    "sg:address":"221 E Taylor St",
    "sg:city":"Savannah",
    "sg:classifiers":[
        {
            "category":"Health Services",
            "subcategory":"Health Practitioner",
            "type":"Services"
        }
    ],
    "sg:phone":"+1 912 238 5500",
    "sg:postcode":"31401",
    "sg:province":"GA",
    "wof:name":"Charlalee Sedgwick PHD",
    "wof:placetype":"venue"
},
  "geometry": {"coordinates":[-81.091354,32.070716],"type":"Point"}
}