{
  "type": "Feature",
  "properties": {
    "addr:full":"1610 Hood St Waycross GA 31503",
    "addr:housenumber":"1610",
    "addr:postcode":"31503",
    "addr:street":"Hood St",
    "iso:country":"US",
    "sg:address":"1610 Hood St",
    "sg:city":"Waycross",
    "sg:classifiers":[
        {
            "category":"Building & Trades",
            "subcategory":"Construction",
            "type":"Services"
        }
    ],
    "sg:phone":"+1 912 285 2459",
    "sg:postcode":"31503",
    "sg:province":"GA",
    "sg:tags":[
        "contractor"
    ],
    "wof:name":"V & H Builders Inc",
    "wof:placetype":"venue"
},
  "geometry": {"coordinates":[-82.369603,31.194465],"type":"Point"}
}