{
  "type": "Feature",
  "properties": {
    "iso:country":"US",
    "sg:address":"430 W Pike St",
    "sg:city":"Lawrenceville",
    "sg:classifiers":[
        {
            "category":"Shopping",
            "subcategory":"Jewelry",
            "type":"Retail Goods"
        }
    ],
    "sg:phone":"+1 770 995 2505",
    "sg:postcode":"30046",
    "sg:province":"GA",
    "sg:tags":[
        "watch"
    ],
    "wof:name":"Wilson Watch Co",
    "wof:placetype":"venue"
},
  "geometry": {"coordinates":[-84.001293,33.957884],"type":"Point"}
}