{
  "type": "Feature",
  "properties": {
    "addr:full":"1289 Bridges Ave SW Atlanta GA 30310",
    "addr:housenumber":"1289",
    "addr:postcode":"30310",
    "addr:street":"Bridges Ave Sw",
    "iso:country":"US",
    "sg:address":"1289 Bridges Ave SW",
    "sg:city":"Atlanta",
    "sg:classifiers":[
        {
            "category":"Building & Trades",
            "subcategory":"Landscaping Services",
            "type":"Services"
        }
    ],
    "sg:phone":"+1 404 753 1076",
    "sg:postcode":"30310",
    "sg:province":"GA",
    "sg:tags":[
        "lawn"
    ],
    "wof:name":"H & S Landscaping",
    "wof:placetype":"venue"
},
  "geometry": {"coordinates":[-84.430207,33.726485],"type":"Point"}
}