{
  "type": "Feature",
  "properties": {
    "iso:country":"US",
    "sg:address":"141 Cape Harbour Dr NW",
    "sg:city":"Milledgeville",
    "sg:classifiers":[
        {
            "category":"Shopping",
            "subcategory":"Bicycles & Sporting Goods",
            "type":"Retail Goods"
        }
    ],
    "sg:phone":"+1 478 968 7700",
    "sg:postcode":"31061",
    "sg:province":"GA",
    "sg:tags":[
        "equipment",
        "hunting",
        "supply"
    ],
    "sg:website":"www.thecrowroost.com",
    "wof:name":"Crow Roost",
    "wof:placetype":"venue"
},
  "geometry": {"coordinates":[-83.358008,33.168083],"type":"Point"}
}