{
  "type": "Feature",
  "properties": {
    "addr:full":"5277 Ash St Forest Park GA 30297",
    "addr:housenumber":"5277",
    "addr:postcode":"30297",
    "addr:street":"Ash St",
    "iso:country":"US",
    "sg:address":"5277 Ash St",
    "sg:city":"Forest Park",
    "sg:classifiers":[
        {
            "category":"Education",
            "subcategory":"School",
            "type":"Public Place"
        }
    ],
    "sg:phone":"+1 404 362 2000",
    "sg:postcode":"30297",
    "sg:province":"GA",
    "sg:tags":[
        "high",
        "middle",
        "elementary"
    ],
    "wof:name":"South Metro Psychoeducational Center",
    "wof:placetype":"venue"
},
  "geometry": {"coordinates":[-84.36350299999999,33.6106],"type":"Point"}
}