{
  "type": "Feature",
  "properties": {
    "addr:full":"127 Wc Bryant Pkwy Calhoun GA 30701",
    "addr:housenumber":"127",
    "addr:postcode":"30701",
    "addr:street":"Wc Bryant Pkwy",
    "iso:country":"US",
    "sg:address":"127 Wc Bryant Pkwy",
    "sg:city":"Calhoun",
    "sg:classifiers":[
        {
            "category":"Banks & Credit Unions",
            "subcategory":"Bank",
            "type":"Services"
        }
    ],
    "sg:phone":"+1 706 629 9551",
    "sg:postcode":"30701",
    "sg:province":"GA",
    "sg:tags":[
        "loan"
    ],
    "wof:name":"First Franklin Financial Corp",
    "wof:placetype":"venue"
},
  "geometry": {"coordinates":[-84.94618,34.483994],"type":"Point"}
}