{
  "type": "Feature",
  "properties": {
    "iso:country":"US",
    "sg:address":"22 Wolfpen Pass NE",
    "sg:city":"White",
    "sg:classifiers":[
        {
            "category":"Professional",
            "subcategory":"Computer Services",
            "type":"Services"
        }
    ],
    "sg:phone":"+1 706 386 6025",
    "sg:postcode":"30184",
    "sg:province":"GA",
    "wof:name":"Complete Computer Service Inc",
    "wof:placetype":"venue"
},
  "geometry": {"coordinates":[-84.74074299999999,34.233976],"type":"Point"}
}