{
  "type": "Feature",
  "properties": {
    "iso:country":"US",
    "sg:address":"123 Black Oak Trl",
    "sg:city":"Woodstock",
    "sg:classifiers":[
        {
            "category":"Utilities",
            "subcategory":"Cable",
            "type":"Services"
        }
    ],
    "sg:phone":"+1 678 614 2991",
    "sg:postcode":"30189",
    "sg:province":"GA",
    "sg:tags":[
        "television"
    ],
    "wof:name":"C&C Cable Service",
    "wof:placetype":"venue"
},
  "geometry": {"coordinates":[-84.594446,34.139966],"type":"Point"}
}