{
  "type": "Feature",
  "properties": {
    "iso:country":"US",
    "sg:address":"3843 Hillsborough Ct",
    "sg:city":"Snellville",
    "sg:classifiers":[
        {
            "category":"Banks & Credit Unions",
            "subcategory":"Financial Services",
            "type":"Services"
        }
    ],
    "sg:phone":"+1 770 761 0069",
    "sg:postcode":"30039",
    "sg:province":"GA",
    "sg:tags":[
        "mortgage"
    ],
    "wof:name":"Prinstar Real Estate & Mortgage Services",
    "wof:placetype":"venue"
},
  "geometry": {"coordinates":[-84.02259599999999,33.783822],"type":"Point"}
}