{
  "type": "Feature",
  "properties": {
    "iso:country":"US",
    "sg:address":"68 Hampton St",
    "sg:city":"Mcdonough",
    "sg:classifiers":[
        {
            "category":"Health Services",
            "subcategory":"Doctor",
            "type":"Services"
        },
        {
            "category":"Health Services",
            "subcategory":"Clinic",
            "type":"Services"
        }
    ],
    "sg:phone":"+1 770 914 0342",
    "sg:postcode":"30253",
    "sg:province":"GA",
    "sg:tags":[
        "physician",
        "family",
        "practice",
        "surgeons",
        "medicine",
        "surgeon"
    ],
    "wof:name":"McDonough Primary Care",
    "wof:placetype":"venue"
},
  "geometry": {"coordinates":[-84.15002800000001,33.445945],"type":"Point"}
}