{
  "type": "Feature",
  "properties": {
    "iso:country":"US",
    "sg:address":"123 Fitchburg Dr",
    "sg:city":"Woodstock",
    "sg:classifiers":[
        {
            "category":"Organizations",
            "subcategory":"Religious Organization",
            "type":"Services"
        }
    ],
    "sg:phone":"+1 770 591 5735",
    "sg:postcode":"30189",
    "sg:province":"GA",
    "wof:name":"Norman Hunt Evangelistic Inc",
    "wof:placetype":"venue"
},
  "geometry": {"coordinates":[-84.551108,34.084817],"type":"Point"}
}