{
  "type": "Feature",
  "properties": {
    "addr:full":"805 Hill St La Grange GA 30241",
    "addr:housenumber":"805",
    "addr:postcode":"30241",
    "addr:street":"Hill St",
    "iso:country":"US",
    "sg:address":"805 Hill St",
    "sg:city":"La Grange",
    "sg:classifiers":[
        {
            "category":"Recreation",
            "type":"Entertainment"
        }
    ],
    "sg:phone":"+1 706 845 9992",
    "sg:postcode":"30241",
    "sg:province":"GA",
    "wof:name":"Raceworld Speedway",
    "wof:placetype":"venue"
},
  "geometry": {"coordinates":[-85.01487899999999,33.045321],"type":"Point"}
}