{
  "type": "Feature",
  "properties": {
    "addr:full":"284 Bullsboro Dr Newnan GA 30263",
    "addr:housenumber":"284",
    "addr:postcode":"30263",
    "addr:street":"Bullsboro Dr",
    "iso:country":"US",
    "sg:address":"284 Bullsboro Dr",
    "sg:city":"Newnan",
    "sg:classifiers":[
        {
            "category":"Shopping",
            "subcategory":"Stationery & Office Supplies",
            "type":"Retail Goods"
        }
    ],
    "sg:phone":"+1 678 423 4400",
    "sg:postcode":"30263",
    "sg:province":"GA",
    "sg:tags":[
        "album",
        "scrapbook"
    ],
    "wof:name":"Matt Magic Scrap Books",
    "wof:placetype":"venue"
},
  "geometry": {"coordinates":[-84.765581,33.393326],"type":"Point"}
}