{
  "type": "Feature",
  "properties": {
    "iso:country":"US",
    "sg:address":"31 N Avondale Rd",
    "sg:city":"Avondale Estates",
    "sg:classifiers":[
        {
            "category":"Shopping",
            "subcategory":"Used Merchandise",
            "type":"Retail Goods"
        }
    ],
    "sg:phone":"+1 404 508 0611",
    "sg:postcode":"30002",
    "sg:province":"GA",
    "sg:tags":[
        "clothing"
    ],
    "wof:name":"Jack & Jill//A Consignment Btq",
    "wof:placetype":"venue"
},
  "geometry": {"coordinates":[-84.27232600000001,33.775262],"type":"Point"}
}