{
  "type": "Feature",
  "properties": {
    "iso:country":"US",
    "sg:address":"4555 Mansell Rd",
    "sg:city":"Alpharetta",
    "sg:classifiers":[
        {
            "category":"Banks & Credit Unions",
            "subcategory":"Financial Services",
            "type":"Services"
        }
    ],
    "sg:phone":"+1 678 319 4121",
    "sg:postcode":"30022",
    "sg:province":"GA",
    "sg:tags":[
        "broker",
        "mortgage"
    ],
    "sg:website":"www.suntrustmortgage.com",
    "wof:name":"Suntrust Mortgage Inc",
    "wof:placetype":"venue"
},
  "geometry": {"coordinates":[-84.285455,34.040828],"type":"Point"}
}