{
  "type": "Feature",
  "properties": {
    "iso:country":"US",
    "sg:address":"6808 Browns Mill Walk",
    "sg:city":"Lithonia",
    "sg:classifiers":[
        {
            "category":"Professional",
            "subcategory":"Business Services",
            "type":"Services"
        }
    ],
    "sg:phone":"+1 770 609 5872",
    "sg:postcode":"30038",
    "sg:province":"GA",
    "sg:tags":[
        "wrap",
        "designer",
        "gift"
    ],
    "wof:name":"Kimberly Nichole Inc",
    "wof:placetype":"venue"
},
  "geometry": {"coordinates":[-84.116457,33.638508],"type":"Point"}
}