{
  "type": "Feature",
  "properties": {
    "iso:country":"US",
    "sg:address":"880 Indian Trail Lilburn Rd NW",
    "sg:city":"Lilburn",
    "sg:classifiers":[
        {
            "category":"Personal",
            "subcategory":"Beauty Salon",
            "type":"Services"
        }
    ],
    "sg:phone":"+1 770 923 0507",
    "sg:postcode":"30047",
    "sg:province":"GA",
    "wof:name":"Hair Is Easy",
    "wof:placetype":"venue"
},
  "geometry": {"coordinates":[-84.154573,33.904966],"type":"Point"}
}