{
  "type": "Feature",
  "properties": {
    "addr:full":"5316 Buford Hwy Norcross GA 30071",
    "addr:housenumber":"5316",
    "addr:postcode":"30071",
    "addr:street":"Buford Hwy",
    "iso:country":"US",
    "sg:address":"5316 Buford Hwy",
    "sg:city":"Norcross",
    "sg:classifiers":[
        {
            "category":"Home & Garden",
            "subcategory":"Garden Supply",
            "type":"Retail Goods"
        }
    ],
    "sg:phone":"+1 770 448 3607",
    "sg:postcode":"30071",
    "sg:province":"GA",
    "wof:name":"Southern Shade Inc",
    "wof:placetype":"venue"
},
  "geometry": {"coordinates":[-84.19949099999999,33.948328],"type":"Point"}
}