{
  "type": "Feature",
  "properties": {
    "iso:country":"US",
    "sg:address":"428 Bentley Pl",
    "sg:city":"Tucker",
    "sg:classifiers":[
        {
            "category":"Real Estate",
            "subcategory":"Developer",
            "type":"Services"
        }
    ],
    "sg:phone":"+1 770 492 0288",
    "sg:postcode":"30084",
    "sg:province":"GA",
    "wof:name":"Allied Community Development",
    "wof:placetype":"venue"
},
  "geometry": {"coordinates":[-84.22161800000001,33.884997],"type":"Point"}
}