{
  "type": "Feature",
  "properties": {
    "addr:full":"7453 Woodruff Way Stone Mountain GA 30087",
    "addr:housenumber":"7453",
    "addr:postcode":"30087",
    "addr:street":"Woodruff Way",
    "iso:country":"US",
    "sg:address":"7453 Woodruff Way",
    "sg:city":"Stone Mountain",
    "sg:classifiers":[
        {
            "category":"Autos & Motor Vehicles",
            "subcategory":"Automobile Sales",
            "type":"Retail Goods"
        }
    ],
    "sg:phone":"+1 770 465 1100",
    "sg:postcode":"30087",
    "sg:province":"GA",
    "sg:tags":[
        "aircraft",
        "appraisal",
        "finance",
        "acquisition"
    ],
    "wof:name":"Air Transport Group LLC",
    "wof:placetype":"venue"
},
  "geometry": {"coordinates":[-84.085663,33.787245],"type":"Point"}
}