{
  "type": "Feature",
  "properties": {
    "iso:country":"US",
    "sg:address":"1784 New Franklin Rd",
    "sg:city":"La Grange",
    "sg:classifiers":[
        {
            "category":"Organizations",
            "subcategory":"Religious Organization",
            "type":"Services"
        }
    ],
    "sg:phone":"+1 706 884 4275",
    "sg:postcode":"30240",
    "sg:province":"GA",
    "wof:name":"Gerald Westbrook Rev",
    "wof:placetype":"venue"
},
  "geometry": {"coordinates":[-85.029533,33.092808],"type":"Point"}
}