{
  "type": "Feature",
  "properties": {
    "iso:country":"US",
    "sg:address":"1100 US Hwy 80",
    "sg:city":"Pooler",
    "sg:classifiers":[
        {
            "category":"Government",
            "subcategory":"Office",
            "type":"Public Place"
        }
    ],
    "sg:phone":"+1 912 748 1747",
    "sg:postcode":"31322",
    "sg:province":"GA",
    "sg:tags":[
        "construction",
        "highway",
        "maintenance"
    ],
    "wof:name":"Georgia Dot 1953",
    "wof:placetype":"venue"
},
  "geometry": {"coordinates":[-81.22901,32.106952],"type":"Point"}
}