{
  "type": "Feature",
  "properties": {
    "iso:country":"US",
    "sg:address":"2255 Shady Oaks Dr",
    "sg:city":"Loganville",
    "sg:phone":"+1 678 758 7285",
    "sg:postcode":"30052",
    "sg:province":"GA",
    "sg:tags":[
        "equipment",
        "commercial"
    ],
    "wof:name":"Quick N Easy Services",
    "wof:placetype":"venue"
},
  "geometry": {"coordinates":[-83.987661,33.829041],"type":"Point"}
}