{
  "type": "Feature",
  "properties": {
    "addr:full":"16 Due West Cove Dallas GA 30157",
    "addr:housenumber":"16",
    "addr:postcode":"30157",
    "addr:street":"Due West Cove",
    "iso:country":"US",
    "sg:address":"16 Due West Cove",
    "sg:city":"Dallas",
    "sg:classifiers":[
        {
            "category":"Real Estate",
            "subcategory":"Real Estate Agent",
            "type":"Services"
        }
    ],
    "sg:phone":"+1 770 655 6833",
    "sg:postcode":"30157",
    "sg:province":"GA",
    "sg:tags":[
        "inspection"
    ],
    "wof:name":"Lahey Home Inspection Team Inc",
    "wof:placetype":"venue"
},
  "geometry": {"coordinates":[-84.770169,33.967932],"type":"Point"}
}