{
  "type": "Feature",
  "properties": {
    "iso:country":"US",
    "sg:address":"4240 Little Falls Dr",
    "sg:city":"Cumming",
    "sg:classifiers":[
        {
            "category":"Manufacturing",
            "subcategory":"Food",
            "type":"Manufacturing & Wholesale Goods"
        }
    ],
    "sg:phone":"+1 678 455 4023",
    "sg:postcode":"30041",
    "sg:province":"GA",
    "sg:tags":[
        "mfg"
    ],
    "wof:name":"Alphabet Delite",
    "wof:placetype":"venue"
},
  "geometry": {"coordinates":[-84.086879,34.142995],"type":"Point"}
}