{
  "type": "Feature",
  "properties": {
    "addr:full":"4375 Burgess Hill Ln Alpharetta GA 30022",
    "addr:housenumber":"4375",
    "addr:postcode":"30022",
    "addr:street":"Burgess Hill Ln",
    "iso:country":"US",
    "sg:address":"4375 Burgess Hill Ln",
    "sg:city":"Alpharetta",
    "sg:classifiers":[
        {
            "category":"Shopping",
            "subcategory":"Jewelry",
            "type":"Retail Goods"
        }
    ],
    "sg:phone":"+1 770 410 4066",
    "sg:postcode":"30022",
    "sg:province":"GA",
    "sg:tags":[
        "precious",
        "semi-precious",
        "stone"
    ],
    "wof:name":"Dazzl Ltd Jewelry",
    "wof:placetype":"venue"
},
  "geometry": {"coordinates":[-84.234066,34.030854],"type":"Point"}
}