{
  "type": "Feature",
  "properties": {
    "iso:country":"US",
    "sg:address":"308 D Bob Ind Dr",
    "sg:city":"Peachtree City",
    "sg:classifiers":[
        {
            "category":"Shopping",
            "subcategory":"Books",
            "type":"Retail Goods"
        }
    ],
    "sg:phone":"+1 770 486 0608",
    "sg:postcode":"30269",
    "sg:province":"GA",
    "sg:tags":[
        "dealer"
    ],
    "wof:name":"Dodge Learning Resources",
    "wof:placetype":"venue"
},
  "geometry": {"coordinates":[-84.591048,33.391223],"type":"Point"}
}