{
  "type": "Feature",
  "properties": {
    "addr:full":"4735 Bass Dr Evans GA 30809",
    "addr:housenumber":"4735",
    "addr:postcode":"30809",
    "addr:street":"Bass Dr",
    "iso:country":"US",
    "sg:address":"4735 Bass Dr",
    "sg:city":"Evans",
    "sg:classifiers":[
        {
            "category":"Retail",
            "subcategory":"Auto Repair",
            "type":"Services"
        }
    ],
    "sg:phone":"+1 706 863 6189",
    "sg:postcode":"30809",
    "sg:province":"GA",
    "sg:tags":[
        "general"
    ],
    "wof:name":"Burekkhelters Garage Inc",
    "wof:placetype":"venue"
},
  "geometry": {"coordinates":[-82.162632,33.566113],"type":"Point"}
}