{
  "type": "Feature",
  "properties": {
    "addr:full":"2012 Floyd Rd Columbus GA 31907",
    "addr:housenumber":"2012",
    "addr:postcode":"31907",
    "addr:street":"Floyd Rd",
    "iso:country":"US",
    "sg:address":"2012 Floyd Rd",
    "sg:city":"Columbus",
    "sg:classifiers":[
        {
            "category":"Restaurant",
            "type":"Food & Drink"
        }
    ],
    "sg:menulink":"http://www.allmenus.com/ga/columbus/207137-sonic/menu/",
    "sg:phone":"+1 706 563 1135",
    "sg:postcode":"31907",
    "sg:province":"GA",
    "sg:tags":[
        "burger",
        "american"
    ],
    "wof:name":"Sonic",
    "wof:placetype":"venue"
},
  "geometry": {"coordinates":[-84.89873,32.479639],"type":"Point"}
}