{
  "type": "Feature",
  "properties": {
    "iso:country":"US",
    "sg:address":"750 Franklin Rd SE",
    "sg:city":"Marietta",
    "sg:classifiers":[
        {
            "category":"Real Estate",
            "subcategory":"Real Estate Operator",
            "type":"Services"
        }
    ],
    "sg:phone":"+1 678 594 0017",
    "sg:postcode":"30067",
    "sg:province":"GA",
    "sg:tags":[
        "apartment"
    ],
    "wof:name":"Georgia Partners Llc",
    "wof:placetype":"venue"
},
  "geometry": {"coordinates":[-84.501666,33.933174],"type":"Point"}
}