{
  "type": "Feature",
  "properties": {
    "addr:full":"236 Forsyth St SW Atlanta GA 30303",
    "addr:housenumber":"236",
    "addr:postcode":"30303",
    "addr:street":"Forsyth St Sw",
    "iso:country":"US",
    "sg:address":"236 Forsyth St SW",
    "sg:city":"Atlanta",
    "sg:classifiers":[
        {
            "category":"Communications",
            "type":"Services"
        }
    ],
    "sg:phone":"+1 404 827 9688",
    "sg:postcode":"30303",
    "sg:province":"GA",
    "sg:tags":[
        "communication"
    ],
    "wof:name":"B2b Communications",
    "wof:placetype":"venue"
},
  "geometry": {"coordinates":[-84.397209,33.747844],"type":"Point"}
}