{
  "type": "Feature",
  "properties": {
    "addr:full":"227 Sandy Springs Pl NE Atlanta GA 30328",
    "addr:housenumber":"227",
    "addr:postcode":"30328",
    "addr:street":"Sandy;Pl Ne",
    "iso:country":"US",
    "sg:address":"227 Sandy Springs Pl NE",
    "sg:city":"Atlanta",
    "sg:classifiers":[
        {
            "category":"Health Services",
            "subcategory":"Chiropractor",
            "type":"Services"
        }
    ],
    "sg:phone":"+1 404 705 9339",
    "sg:postcode":"30328",
    "sg:province":"GA",
    "wof:name":"Springs Chiropractic Health Centre the",
    "wof:placetype":"venue"
},
  "geometry": {"coordinates":[-84.380501,33.9202],"type":"Point"}
}