{
  "type": "Feature",
  "properties": {
    "iso:country":"US",
    "sg:address":"6 Plantation Dr NE",
    "sg:city":"Atlanta",
    "sg:classifiers":[
        {
            "category":"Retail",
            "subcategory":"Portrait Studio",
            "type":"Services"
        }
    ],
    "sg:phone":"+1 404 841 9554",
    "sg:postcode":"30324",
    "sg:province":"GA",
    "sg:tags":[
        "photographer"
    ],
    "wof:name":"Canvas On Demand",
    "wof:placetype":"venue"
},
  "geometry": {"coordinates":[-84.35549,33.8366],"type":"Point"}
}