{
  "type": "Feature",
  "properties": {
    "addr:full":"109 Patrol Rd Forsyth GA 31029",
    "addr:housenumber":"109",
    "addr:postcode":"31029",
    "addr:street":"Patrol Rd",
    "iso:country":"US",
    "sg:address":"109 Patrol Rd",
    "sg:city":"Forsyth",
    "sg:classifiers":[
        {
            "category":"Personal",
            "subcategory":"Beauty Salon",
            "type":"Services"
        },
        {
            "category":"Personal",
            "subcategory":"Barber",
            "type":"Services"
        }
    ],
    "sg:phone":"+1 478 994 1543",
    "sg:postcode":"31029",
    "sg:province":"GA",
    "wof:name":"Klassique Kuts",
    "wof:placetype":"venue"
},
  "geometry": {"coordinates":[-83.937973,33.03984],"type":"Point"}
}