{
  "type": "Feature",
  "properties": {
    "addr:full":"3395 Wildwood Rd Suwanee GA 30024",
    "addr:housenumber":"3395",
    "addr:postcode":"30024",
    "addr:street":"Wildwood Rd",
    "iso:country":"US",
    "sg:address":"3395 Wildwood Rd",
    "sg:city":"Suwanee",
    "sg:classifiers":[
        {
            "category":"Mining & Drilling",
            "type":"Manufacturing & Wholesale Goods"
        }
    ],
    "sg:phone":"+1 678 414 2956",
    "sg:postcode":"30024",
    "sg:province":"GA",
    "sg:tags":[
        "field"
    ],
    "wof:name":"Best Home Inspection Service",
    "wof:placetype":"venue"
},
  "geometry": {"coordinates":[-84.068372,34.032106],"type":"Point"}
}