{
  "type": "Feature",
  "properties": {
    "iso:country":"US",
    "sg:address":"1220 Austin Glen Dr",
    "sg:city":"Atlanta",
    "sg:classifiers":[
        {
            "category":"Manufacturing",
            "subcategory":"Printing",
            "type":"Manufacturing & Wholesale Goods"
        }
    ],
    "sg:phone":"+1 770 392 9946",
    "sg:postcode":"30338",
    "sg:province":"GA",
    "sg:tags":[
        "publishing"
    ],
    "wof:name":"Mainstream Press Inc",
    "wof:placetype":"venue"
},
  "geometry": {"coordinates":[-84.337126,33.960029],"type":"Point"}
}