{
  "type": "Feature",
  "properties": {
    "iso:country":"US",
    "sg:address":"1445 Field Park Cir",
    "sg:city":"Marietta",
    "sg:classifiers":[
        {
            "category":"Retail",
            "subcategory":"Auto Repair",
            "type":"Services"
        }
    ],
    "sg:phone":"+1 770 427 4590",
    "sg:postcode":"30066",
    "sg:province":"GA",
    "sg:tags":[
        "body",
        "shop",
        "automobile",
        "painting",
        "repairing"
    ],
    "sg:website":"www.magnumcollision.com",
    "wof:name":"Magnum Collision Repair Center",
    "wof:placetype":"venue"
},
  "geometry": {"coordinates":[-84.56289700000001,33.987],"type":"Point"}
}