{
  "type": "Feature",
  "properties": {
    "addr:full":"1523 Fair Rd Statesboro GA 30458",
    "addr:housenumber":"1523",
    "addr:postcode":"30458",
    "addr:street":"Fair Rd",
    "iso:country":"US",
    "sg:address":"1523 Fair Rd",
    "sg:city":"Statesboro",
    "sg:classifiers":[
        {
            "category":"Health Services",
            "subcategory":"Doctor",
            "type":"Services"
        }
    ],
    "sg:phone":"+1 912 871 2000",
    "sg:postcode":"30458",
    "sg:province":"GA",
    "sg:tags":[
        "physician",
        "surgeon"
    ],
    "wof:name":"Statesboro Ob/Gyn Specialists",
    "wof:placetype":"venue"
},
  "geometry": {"coordinates":[-81.76591000000001,32.410818],"type":"Point"}
}