{
  "type": "Feature",
  "properties": {
    "addr:full":"251 Lakeshore Dr Cordele GA 31015",
    "addr:housenumber":"251",
    "addr:postcode":"31015",
    "addr:street":"Lakeshore Dr",
    "iso:country":"US",
    "sg:address":"251 Lakeshore Dr",
    "sg:city":"Cordele",
    "sg:classifiers":[
        {
            "category":"Shopping",
            "type":"Retail Goods"
        }
    ],
    "sg:phone":"+1 229 535 4640",
    "sg:postcode":"31015",
    "sg:province":"GA",
    "sg:tags":[
        "cosmetic",
        "perfume"
    ],
    "wof:name":"Mary Kay & Herbalife",
    "wof:placetype":"venue"
},
  "geometry": {"coordinates":[-83.918436,31.858865],"type":"Point"}
}