{
  "type": "Feature",
  "properties": {
    "iso:country":"US",
    "sg:address":"3310 Antioch Church Rd",
    "sg:city":"Blairsville",
    "sg:classifiers":[
        {
            "category":"Recreation",
            "subcategory":"Marina",
            "type":"Entertainment"
        }
    ],
    "sg:phone":"+1 706 781 3526",
    "sg:postcode":"30512",
    "sg:province":"GA",
    "sg:tags":[
        "operation",
        "storage",
        "boat"
    ],
    "wof:name":"Mountain Lakes Boat & R V Stor",
    "wof:placetype":"venue"
},
  "geometry": {"coordinates":[-84.01036000000001,34.923323],"type":"Point"}
}