{
  "type": "Feature",
  "properties": {
    "iso:country":"US",
    "sg:address":"250 Spring St NW",
    "sg:city":"Atlanta",
    "sg:classifiers":[
        {
            "category":"Shopping",
            "subcategory":"Hobbies, Toys, & Games",
            "type":"Retail Goods"
        }
    ],
    "sg:phone":"+1 404 589 0042",
    "sg:postcode":"30303",
    "sg:province":"GA",
    "sg:tags":[
        "supply"
    ],
    "wof:name":"Aurora Plush Toys",
    "wof:placetype":"venue"
},
  "geometry": {"coordinates":[-84.38902299999999,33.761421],"type":"Point"}
}