{
  "type": "Feature",
  "properties": {
    "iso:country":"US",
    "sg:address":"5775 Peachtree-Dunwoody Rd NE Bldg D Ste 400",
    "sg:city":"Atlanta",
    "sg:classifiers":[
        {
            "category":"Health Services",
            "subcategory":"Dentist",
            "type":"Services"
        }
    ],
    "sg:phone":"+1 770 393 9201",
    "sg:postcode":"30342",
    "sg:province":"GA",
    "sg:website":"www.caugheydds.com",
    "wof:name":"Elizabeth Caughey, DDS",
    "wof:placetype":"venue"
},
  "geometry": {"coordinates":[-84.35258899999999,33.942126],"type":"Point"}
}