{
  "type": "Feature",
  "properties": {
    "iso:country":"US",
    "sg:address":"404 Kings Spring Village Pkwy",
    "sg:city":"Smyrna",
    "sg:classifiers":[
        {
            "category":"Professional",
            "subcategory":"Management & Consulting",
            "type":"Services"
        }
    ],
    "sg:phone":"+1 770 432 4444",
    "sg:postcode":"30082",
    "sg:province":"GA",
    "wof:name":"Delmar Gardens",
    "wof:placetype":"venue"
},
  "geometry": {"coordinates":[-84.517242,33.857482],"type":"Point"}
}