{
  "type": "Feature",
  "properties": {
    "addr:full":"110 Eagle Spring Dr Stockbridge GA 30281",
    "addr:housenumber":"110",
    "addr:postcode":"30281",
    "addr:street":"Eagle Spring Dr",
    "iso:country":"US",
    "sg:address":"110 Eagle Spring Dr",
    "sg:city":"Stockbridge",
    "sg:classifiers":[
        {
            "category":"Banks & Credit Unions",
            "subcategory":"Bank",
            "type":"Services"
        }
    ],
    "sg:phone":"+1 770 389 1528",
    "sg:postcode":"30281",
    "sg:province":"GA",
    "sg:tags":[
        "broker",
        "mortgage"
    ],
    "wof:name":"Chase Manhattan",
    "wof:placetype":"venue"
},
  "geometry": {"coordinates":[-84.226753,33.508124],"type":"Point"}
}