{
  "type": "Feature",
  "properties": {
    "addr:full":"1 S Main St Jasper GA 30143",
    "addr:housenumber":"1",
    "addr:postcode":"30143",
    "addr:street":"S Main St",
    "iso:country":"US",
    "sg:address":"1 S Main St",
    "sg:city":"Jasper",
    "sg:classifiers":[
        {
            "category":"Real Estate",
            "subcategory":"Developer",
            "type":"Services"
        }
    ],
    "sg:phone":"+1 706 253 2022",
    "sg:postcode":"30143",
    "sg:province":"GA",
    "wof:name":"Woodbourne Estates Of Georgia Inc",
    "wof:placetype":"venue"
},
  "geometry": {"coordinates":[-84.42984800000001,34.468102],"type":"Point"}
}