{
  "type": "Feature",
  "properties": {
    "addr:full":"3870 Granger Dr Atlanta GA 30341",
    "addr:housenumber":"3870",
    "addr:postcode":"30341",
    "addr:street":"Granger Dr",
    "iso:country":"US",
    "sg:address":"3870 Granger Dr",
    "sg:city":"Atlanta",
    "sg:classifiers":[
        {
            "category":"Building & Trades",
            "subcategory":"Plumbing",
            "type":"Services"
        }
    ],
    "sg:phone":"+1 770 458 4880",
    "sg:postcode":"30341",
    "sg:province":"GA",
    "sg:tags":[
        "contractor"
    ],
    "wof:name":"Acme Heating Air",
    "wof:placetype":"venue"
},
  "geometry": {"coordinates":[-84.315406,33.904756],"type":"Point"}
}