{
  "type": "Feature",
  "properties": {
    "addr:full":"1100 State Rte 54 Fayetteville GA 30214",
    "addr:housenumber":"1100",
    "addr:postcode":"30214",
    "addr:street":"State Rte 54",
    "iso:country":"US",
    "sg:address":"1100 State Rte 54",
    "sg:city":"Fayetteville",
    "sg:classifiers":[
        {
            "category":"Professional",
            "type":"Services"
        }
    ],
    "sg:phone":"+1 770 461 7168",
    "sg:postcode":"30214",
    "sg:province":"GA",
    "wof:name":"Donald D Lassen",
    "wof:placetype":"venue"
},
  "geometry": {"coordinates":[-84.4285,33.453207],"type":"Point"}
}