{
  "type": "Feature",
  "properties": {
    "iso:country":"US",
    "sg:address":"308 Hunt Rd",
    "sg:city":"Kathleen",
    "sg:classifiers":[
        {
            "category":"Building & Trades",
            "subcategory":"Construction",
            "type":"Services"
        }
    ],
    "sg:phone":"+1 478 218 2846",
    "sg:postcode":"31047",
    "sg:province":"GA",
    "sg:tags":[
        "hanging",
        "contractor"
    ],
    "wof:name":"International City Painting",
    "wof:placetype":"venue"
},
  "geometry": {"coordinates":[-83.68469,32.537962],"type":"Point"}
}