{
  "type": "Feature",
  "properties": {
    "iso:country":"US",
    "sg:address":"8290 Roswell Rd",
    "sg:city":"Atlanta",
    "sg:classifiers":[
        {
            "category":"Restaurant",
            "type":"Food & Drink"
        }
    ],
    "sg:menulink":"http://www.allmenus.com/ga/atlanta/89539-moes-southwest-grill/menu/",
    "sg:phone":"+1 678 585 7573",
    "sg:postcode":"30350",
    "sg:province":"GA",
    "sg:tags":[
        "mexican"
    ],
    "wof:name":"Moe's Southwest Grill",
    "wof:placetype":"venue"
},
  "geometry": {"coordinates":[-84.351122,33.981236],"type":"Point"}
}