{
  "type": "Feature",
  "properties": {
    "addr:full":"2340 N Druid Hills Rd NE Atlanta GA 30329",
    "addr:housenumber":"2340",
    "addr:postcode":"30329",
    "addr:street":"N Druid Hills Rd Ne",
    "iso:country":"US",
    "sg:address":"2340 N Druid Hills Rd NE",
    "sg:city":"Atlanta",
    "sg:classifiers":[
        {
            "category":"Building & Trades",
            "subcategory":"Locksmith",
            "type":"Services"
        }
    ],
    "sg:phone":"+1 866 637 0326",
    "sg:postcode":"30329",
    "sg:province":"GA",
    "sg:tags":[
        "key"
    ],
    "wof:name":"1 24 Hour Emergency Locksmith",
    "wof:placetype":"venue"
},
  "geometry": {"coordinates":[-84.329538,33.827646],"type":"Point"}
}