{
  "type": "Feature",
  "properties": {
    "iso:country":"US",
    "sg:address":"211 E Bolton St",
    "sg:city":"Savannah",
    "sg:classifiers":[
        {
            "category":"Real Estate",
            "subcategory":"Real Estate Agent",
            "type":"Services"
        }
    ],
    "sg:phone":"+1 912 234 9165",
    "sg:postcode":"31401",
    "sg:province":"GA",
    "wof:name":"Lukin Enterprises",
    "wof:placetype":"venue"
},
  "geometry": {"coordinates":[-81.09337499999999,32.065506],"type":"Point"}
}