{
  "type": "Feature",
  "properties": {
    "addr:full":"217 Columbia Ave Americus GA 31709",
    "addr:housenumber":"217",
    "addr:postcode":"31709",
    "addr:street":"Columbia Ave",
    "iso:country":"US",
    "sg:address":"217 Columbia Ave",
    "sg:city":"Americus",
    "sg:classifiers":[
        {
            "category":"Freight",
            "type":"Transportation"
        }
    ],
    "sg:phone":"+1 229 924 0488",
    "sg:postcode":"31709",
    "sg:province":"GA",
    "sg:tags":[
        "trucking"
    ],
    "wof:name":"B-Bar Dairy Inc",
    "wof:placetype":"venue"
},
  "geometry": {"coordinates":[-84.23159099999999,32.051451],"type":"Point"}
}