{
  "type": "Feature",
  "properties": {
    "iso:country":"US",
    "sg:address":"2583 US Hwy 441",
    "sg:city":"Dublin",
    "sg:classifiers":[
        {
            "category":"Home & Garden",
            "subcategory":"Building Materials",
            "type":"Retail Goods"
        }
    ],
    "sg:phone":"+1 478 272 6848",
    "sg:postcode":"31021",
    "sg:province":"GA",
    "wof:name":"Middle Georgia Garage Doors",
    "wof:placetype":"venue"
},
  "geometry": {"coordinates":[-82.941005,32.458496],"type":"Point"}
}