{
  "type": "Feature",
  "properties": {
    "iso:country":"US",
    "sg:address":"6 Liberty St",
    "sg:city":"Ludowici",
    "sg:classifiers":[
        {
            "category":"Insurance",
            "subcategory":"Insurance Agent",
            "type":"Services"
        }
    ],
    "sg:phone":"+1 912 545 2101",
    "sg:postcode":"31316",
    "sg:province":"GA",
    "wof:name":"Long County Farm Bureau",
    "wof:placetype":"venue"
},
  "geometry": {"coordinates":[-81.741355,31.709846],"type":"Point"}
}