{
  "type": "Feature",
  "properties": {
    "iso:country":"US",
    "sg:address":"5160 Cleveland Hwy",
    "sg:city":"Gainesville",
    "sg:classifiers":[
        {
            "category":"Food & Beverages",
            "subcategory":"Groceries & Convenience Stores",
            "type":"Retail Goods"
        }
    ],
    "sg:phone":"+1 770 983 7733",
    "sg:postcode":"30506",
    "sg:province":"GA",
    "wof:name":"Circle M Food Shop No 7",
    "wof:placetype":"venue"
},
  "geometry": {"coordinates":[-83.805864,34.444764],"type":"Point"}
}