{
  "type": "Feature",
  "properties": {
    "iso:country":"US",
    "sg:address":"6224 Forest Rd",
    "sg:city":"Columbus",
    "sg:classifiers":[
        {
            "category":"Organizations",
            "subcategory":"Religious Organization",
            "type":"Services"
        }
    ],
    "sg:phone":"+1 706 563 7518",
    "sg:postcode":"31907",
    "sg:province":"GA",
    "wof:name":"Forrest Road Church Of Christ",
    "wof:placetype":"venue"
},
  "geometry": {"coordinates":[-84.88399699999999,32.488481],"type":"Point"}
}