{
  "type": "Feature",
  "properties": {
    "addr:full":"207 Founders Dr Barnesville GA 30204",
    "addr:housenumber":"207",
    "addr:postcode":"30204",
    "addr:street":"Founders Dr",
    "iso:country":"US",
    "sg:address":"207 Founders Dr",
    "sg:city":"Barnesville",
    "sg:classifiers":[
        {
            "category":"Freight",
            "type":"Transportation"
        }
    ],
    "sg:phone":"+1 770 358 7299",
    "sg:postcode":"30204",
    "sg:province":"GA",
    "sg:tags":[
        "operator",
        "local",
        "trucking"
    ],
    "wof:name":"Capri Deliveries Inc",
    "wof:placetype":"venue"
},
  "geometry": {"coordinates":[-84.139297,33.048123],"type":"Point"}
}