{
  "type": "Feature",
  "properties": {
    "iso:country":"US",
    "sg:address":"2944 Rosebud Rd",
    "sg:city":"Loganville",
    "sg:classifiers":[
        {
            "category":"Restaurant",
            "type":"Food & Drink"
        }
    ],
    "sg:phone":"+1 770 972 8899",
    "sg:postcode":"30052",
    "sg:province":"GA",
    "sg:tags":[
        "japanese"
    ],
    "wof:name":"Nagoya Japanese Steak House",
    "wof:placetype":"venue"
},
  "geometry": {"coordinates":[-83.960572,33.788749],"type":"Point"}
}