{
  "type": "Feature",
  "properties": {
    "iso:country":"US",
    "sg:address":"811 Veterans Pkwy",
    "sg:city":"Columbus",
    "sg:classifiers":[
        {
            "category":"Retail",
            "subcategory":"Auto Repair",
            "type":"Services"
        }
    ],
    "sg:phone":"+1 706 494 8333",
    "sg:postcode":"31901",
    "sg:province":"GA",
    "sg:tags":[
        "transmission"
    ],
    "wof:name":"AAA Master Transmissions",
    "wof:placetype":"venue"
},
  "geometry": {"coordinates":[-84.987662,32.462633],"type":"Point"}
}