{
  "type": "Feature",
  "properties": {
    "addr:full":"110 W Jackson St Dublin GA 31021",
    "addr:housenumber":"110",
    "addr:postcode":"31021",
    "addr:street":"W Jackson St",
    "iso:country":"US",
    "sg:address":"110 W Jackson St",
    "sg:city":"Dublin",
    "sg:phone":"+1 478 275 1117",
    "sg:postcode":"31021",
    "sg:province":"GA",
    "wof:name":"Deano's",
    "wof:placetype":"venue"
},
  "geometry": {"coordinates":[-82.90424400000001,32.539633],"type":"Point"}
}