{
  "type": "Feature",
  "properties": {
    "iso:country":"US",
    "sg:address":"82 Moore Rd",
    "sg:city":"Macon",
    "sg:classifiers":[
        {
            "category":"Organizations",
            "subcategory":"Religious Organization",
            "type":"Services"
        }
    ],
    "sg:phone":"+1 478 994 0646",
    "sg:postcode":"31220",
    "sg:province":"GA",
    "wof:name":"Pleasant Grove Baptist Church",
    "wof:placetype":"venue"
},
  "geometry": {"coordinates":[-83.86564199999999,32.918633],"type":"Point"}
}