{
  "type": "Feature",
  "properties": {
    "iso:country":"US",
    "sg:address":"508 S Wall St",
    "sg:city":"Calhoun",
    "sg:classifiers":[
        {
            "category":"Professional",
            "subcategory":"Management & Consulting",
            "type":"Services"
        }
    ],
    "sg:phone":"+1 706 629 2747",
    "sg:postcode":"30701",
    "sg:province":"GA",
    "sg:tags":[
        "real estate"
    ],
    "wof:name":"Brown Rebecca & Associates RE",
    "wof:placetype":"venue"
},
  "geometry": {"coordinates":[-84.94884999999999,34.49192],"type":"Point"}
}