{
  "type": "Feature",
  "properties": {
    "iso:country":"US",
    "sg:address":"1018 Canterbury Rd",
    "sg:city":"Gainesville",
    "sg:classifiers":[
        {
            "category":"Travel",
            "subcategory":"Hotels & Motels",
            "type":"Entertainment"
        }
    ],
    "sg:phone":"+1 770 297 6701",
    "sg:postcode":"30501",
    "sg:province":"GA",
    "wof:name":"T P Corporate Lodging",
    "wof:placetype":"venue"
},
  "geometry": {"coordinates":[-83.86560299999999,34.311391],"type":"Point"}
}