{
  "type": "Feature",
  "properties": {
    "iso:country":"US",
    "sg:address":"4730 Nelson Brogdon Blvd",
    "sg:city":"Buford",
    "sg:classifiers":[
        {
            "category":"Autos & Motor Vehicles",
            "subcategory":"Auto Supplies",
            "type":"Retail Goods"
        }
    ],
    "sg:phone":"+1 770 945 7203",
    "sg:postcode":"30518",
    "sg:province":"GA",
    "sg:tags":[
        "automobile",
        "parts"
    ],
    "wof:name":"O Riely",
    "wof:placetype":"venue"
},
  "geometry": {"coordinates":[-84.02483599999999,34.103945],"type":"Point"}
}