{
  "type": "Feature",
  "properties": {
    "addr:full":"66 Forest Ct Dallas GA 30132",
    "addr:housenumber":"66",
    "addr:postcode":"30132",
    "addr:street":"Forest Ct",
    "iso:country":"US",
    "sg:address":"66 Forest Ct",
    "sg:city":"Dallas",
    "sg:classifiers":[
        {
            "category":"Building & Trades",
            "subcategory":"Pest Control",
            "type":"Services"
        }
    ],
    "sg:phone":"+1 770 445 0774",
    "sg:postcode":"30132",
    "sg:province":"GA",
    "wof:name":"B & K Pest Control & Lawn Care",
    "wof:placetype":"venue"
},
  "geometry": {"coordinates":[-84.792151,33.934958],"type":"Point"}
}