{
  "type": "Feature",
  "properties": {
    "addr:full":"1530 Carroll Dr NW Atlanta GA 30318",
    "addr:housenumber":"1530",
    "addr:postcode":"30318",
    "addr:street":"Carroll Dr Nw",
    "iso:country":"US",
    "sg:address":"1530 Carroll Dr NW",
    "sg:city":"Atlanta",
    "sg:classifiers":[
        {
            "category":"Professional",
            "type":"Services"
        }
    ],
    "sg:phone":"+1 404 352 9490",
    "sg:postcode":"30318",
    "sg:province":"GA",
    "sg:tags":[
        "establishment"
    ],
    "wof:name":"St Jude's Recovery Ctr",
    "wof:placetype":"venue"
},
  "geometry": {"coordinates":[-84.43936600000001,33.802391],"type":"Point"}
}