{
  "type": "Feature",
  "properties": {
    "iso:country":"US",
    "sg:address":"570 Clarke Rd",
    "sg:city":"Winterville",
    "sg:classifiers":[
        {
            "category":"Building & Trades",
            "subcategory":"Construction",
            "type":"Services"
        }
    ],
    "sg:phone":"+1 706 207 6743",
    "sg:postcode":"30683",
    "sg:province":"GA",
    "sg:tags":[
        "house"
    ],
    "wof:name":"XCEL Remodeling & Landscape",
    "wof:placetype":"venue"
},
  "geometry": {"coordinates":[-83.262912,33.917332],"type":"Point"}
}