{
  "type": "Feature",
  "properties": {
    "addr:full":"302 Pioneer Cir Woodstock GA 30188",
    "addr:housenumber":"302",
    "addr:postcode":"30188",
    "addr:street":"Pioneer Cir",
    "iso:country":"US",
    "sg:address":"302 Pioneer Cir",
    "sg:city":"Woodstock",
    "sg:classifiers":[
        {
            "category":"Retail",
            "subcategory":"Auto Repair",
            "type":"Services"
        }
    ],
    "sg:phone":"+1 770 592 8094",
    "sg:postcode":"30188",
    "sg:province":"GA",
    "sg:tags":[
        "automotive"
    ],
    "wof:name":"Precision Maintenance",
    "wof:placetype":"venue"
},
  "geometry": {"coordinates":[-84.44790500000001,34.087711],"type":"Point"}
}