{
  "type": "Feature",
  "properties": {
    "addr:full":"4923 Armour Rd Columbus GA 31904",
    "addr:housenumber":"4923",
    "addr:postcode":"31904",
    "addr:street":"Armour Rd",
    "iso:country":"US",
    "sg:address":"4923 Armour Rd",
    "sg:city":"Columbus",
    "sg:classifiers":[
        {
            "category":"Building & Trades",
            "subcategory":"Construction",
            "type":"Services"
        }
    ],
    "sg:phone":"+1 706 321 0336",
    "sg:postcode":"31904",
    "sg:province":"GA",
    "sg:tags":[
        "contractor"
    ],
    "wof:name":"DJI Builders",
    "wof:placetype":"venue"
},
  "geometry": {"coordinates":[-84.953847,32.512061],"type":"Point"}
}