{
  "type": "Feature",
  "properties": {
    "addr:full":"5002 Arcado Rd SW Lilburn GA 30047",
    "addr:housenumber":"5002",
    "addr:postcode":"30047",
    "addr:street":"Arcado Rd Sw",
    "iso:country":"US",
    "sg:address":"5002 Arcado Rd SW",
    "sg:city":"Lilburn",
    "sg:classifiers":[
        {
            "category":"Health Services",
            "subcategory":"Doctor",
            "type":"Services"
        }
    ],
    "sg:phone":"+1 678 380 1105",
    "sg:postcode":"30047",
    "sg:province":"GA",
    "sg:tags":[
        "medical"
    ],
    "wof:name":"Koong Fang Hwa Linnie Lee",
    "wof:placetype":"venue"
},
  "geometry": {"coordinates":[-84.13617499999999,33.874178],"type":"Point"}
}