{
  "type": "Feature",
  "properties": {
    "addr:full":"2004 Ga Highway 122 Ste 3 Thomasville GA 31757",
    "addr:postcode":"2004;31757",
    "addr:street":"Ga Highway 122 Ste 3",
    "iso:country":"US",
    "sg:address":"2004 Ga Highway 122 Ste 3",
    "sg:city":"Thomasville",
    "sg:classifiers":[
        {
            "category":"Personal",
            "subcategory":"Beauty Salon",
            "type":"Services"
        }
    ],
    "sg:phone":"+1 229 227 1742",
    "sg:postcode":"31757",
    "sg:province":"GA",
    "wof:name":"Styles Salon",
    "wof:placetype":"venue"
},
  "geometry": {"coordinates":[-83.94329999999999,30.854014],"type":"Point"}
}