{
  "type": "Feature",
  "properties": {
    "iso:country":"US",
    "sg:address":"1784 Ambur Cove Ct",
    "sg:city":"Lawrenceville",
    "sg:classifiers":[
        {
            "category":"Health Services",
            "subcategory":"Clinic",
            "type":"Services"
        }
    ],
    "sg:phone":"+1 770 995 6406",
    "sg:postcode":"30043",
    "sg:province":"GA",
    "wof:name":"Healthcare Decision Support",
    "wof:placetype":"venue"
},
  "geometry": {"coordinates":[-84.036231,33.993763],"type":"Point"}
}