{
  "type": "Feature",
  "properties": {
    "addr:full":"6337 Spring Lake Dr Flowery Branch GA 30542",
    "addr:housenumber":"6337",
    "addr:postcode":"30542",
    "addr:street":"Spring Lake Dr",
    "iso:country":"US",
    "sg:address":"6337 Spring Lake Dr",
    "sg:city":"Flowery Branch",
    "sg:classifiers":[
        {
            "category":"Professional",
            "subcategory":"Business Services",
            "type":"Services"
        }
    ],
    "sg:phone":"+1 770 967 0428",
    "sg:postcode":"30542",
    "sg:province":"GA",
    "wof:name":"Firescreek Technology Group",
    "wof:placetype":"venue"
},
  "geometry": {"coordinates":[-83.952118,34.177661],"type":"Point"}
}