{
  "type": "Feature",
  "properties": {
    "iso:country":"US",
    "sg:address":"2806 Old Thomson Rd",
    "sg:city":"Appling",
    "sg:classifiers":[
        {
            "category":"Building & Trades",
            "subcategory":"Construction",
            "type":"Services"
        }
    ],
    "sg:phone":"+1 706 541 0416",
    "sg:postcode":"30802",
    "sg:province":"GA",
    "sg:tags":[
        "contractor",
        "mechanical"
    ],
    "wof:name":"Anderson Mechanical Inc",
    "wof:placetype":"venue"
},
  "geometry": {"coordinates":[-82.351781,33.573711],"type":"Point"}
}