{
  "type": "Feature",
  "properties": {
    "addr:full":"4466 Walt Stephens Rd Stockbridge GA 30281",
    "addr:housenumber":"4466",
    "addr:postcode":"30281",
    "addr:street":"Walt Stephens Rd",
    "iso:country":"US",
    "sg:address":"4466 Walt Stephens Rd",
    "sg:city":"Stockbridge",
    "sg:classifiers":[
        {
            "category":"Personal",
            "subcategory":"Barber",
            "type":"Services"
        }
    ],
    "sg:phone":"+1 770 474 3603",
    "sg:postcode":"30281",
    "sg:province":"GA",
    "sg:tags":[
        "shop"
    ],
    "wof:name":"Mens Concept",
    "wof:placetype":"venue"
},
  "geometry": {"coordinates":[-84.247167,33.528897],"type":"Point"}
}