{
  "type": "Feature",
  "properties": {
    "iso:country":"US",
    "sg:address":"1317 Vine Cir",
    "sg:city":"Mcdonough",
    "sg:classifiers":[
        {
            "category":"Real Estate",
            "subcategory":"Real Estate Agent",
            "type":"Services"
        }
    ],
    "sg:phone":"+1 770 898 1043",
    "sg:postcode":"30253",
    "sg:province":"GA",
    "sg:tags":[
        "inspection"
    ],
    "wof:name":"Georgia Residential Home Insp",
    "wof:placetype":"venue"
},
  "geometry": {"coordinates":[-84.183504,33.487887],"type":"Point"}
}