{
  "type": "Feature",
  "properties": {
    "iso:country":"US",
    "sg:address":"807 Carroll St",
    "sg:city":"Perry",
    "sg:phone":"+1 478 988 3337",
    "sg:postcode":"31069",
    "sg:province":"GA",
    "sg:website":"http://www.letasonthesquare.com",
    "wof:name":"Leta's On the Square",
    "wof:placetype":"venue"
},
  "geometry": {"coordinates":[-83.734408,32.458016],"type":"Point"}
}