{
  "type": "Feature",
  "properties": {
    "iso:country":"US",
    "sg:address":"315 N Central Ave",
    "sg:city":"Atlanta",
    "sg:classifiers":[
        {
            "category":"Building & Trades",
            "subcategory":"Locksmith",
            "type":"Services"
        }
    ],
    "sg:phone":"+1 866 718 8992",
    "sg:postcode":"30354",
    "sg:province":"GA",
    "sg:tags":[
        "key"
    ],
    "wof:name":"A 1 Emergency Locksmith",
    "wof:placetype":"venue"
},
  "geometry": {"coordinates":[-84.39925599999999,33.653805],"type":"Point"}
}