{
  "type": "Feature",
  "properties": {
    "iso:country":"US",
    "sg:address":"51 Wildwood Spgs",
    "sg:city":"Blairsville",
    "sg:classifiers":[
        {
            "category":"Insurance",
            "subcategory":"Hazard Insurance",
            "type":"Services"
        }
    ],
    "sg:phone":"+1 678 314 7656",
    "sg:postcode":"30512",
    "sg:province":"GA",
    "wof:name":"Jimmy Camp Agency, Inc.",
    "wof:placetype":"venue"
},
  "geometry": {"coordinates":[-83.892258,34.835491],"type":"Point"}
}