{
  "type": "Feature",
  "properties": {
    "iso:country":"US",
    "sg:address":"312 N Hill St",
    "sg:city":"Griffin",
    "sg:classifiers":[
        {
            "category":"Retail",
            "subcategory":"Self-service Laundry",
            "type":"Services"
        }
    ],
    "sg:phone":"+1 770 229 2833",
    "sg:postcode":"30223",
    "sg:province":"GA",
    "sg:tags":[
        "coin",
        "power"
    ],
    "wof:name":"Howell Sunshine Laundromat",
    "wof:placetype":"venue"
},
  "geometry": {"coordinates":[-84.26363000000001,33.252378],"type":"Point"}
}