{
  "type": "Feature",
  "properties": {
    "iso:country":"US",
    "sg:address":"100 Hudson Rd",
    "sg:city":"Griffin",
    "sg:classifiers":[
        {
            "category":"Organizations",
            "subcategory":"Religious Organization",
            "type":"Services"
        }
    ],
    "sg:phone":"+1 770 228 4699",
    "sg:postcode":"30224",
    "sg:province":"GA",
    "sg:website":"www.eagleswaychurch.org",
    "wof:name":"Eagles Way Church",
    "wof:placetype":"venue"
},
  "geometry": {"coordinates":[-84.24241499999999,33.229599],"type":"Point"}
}