{
  "type": "Feature",
  "properties": {
    "addr:full":"2624 Sheffield Ct Marietta GA 30064",
    "addr:housenumber":"2624",
    "addr:postcode":"30064",
    "addr:street":"Sheffield Ct",
    "iso:country":"US",
    "sg:address":"2624 Sheffield Ct",
    "sg:city":"Marietta",
    "sg:classifiers":[
        {
            "category":"Building & Trades",
            "subcategory":"Construction",
            "type":"Services"
        }
    ],
    "sg:phone":"+1 770 943 7927",
    "sg:postcode":"30064",
    "sg:province":"GA",
    "sg:tags":[
        "hanging",
        "contractor"
    ],
    "wof:name":"Trinam Painting",
    "wof:placetype":"venue"
},
  "geometry": {"coordinates":[-84.630227,33.87211],"type":"Point"}
}