{
  "type": "Feature",
  "properties": {
    "iso:country":"US",
    "sg:address":"1684 Candler Rd",
    "sg:city":"Decatur",
    "sg:classifiers":[
        {
            "category":"Professional",
            "subcategory":"Lawyer & Legal Services",
            "type":"Services"
        }
    ],
    "sg:phone":"+1 404 289 5555",
    "sg:postcode":"30032",
    "sg:province":"GA",
    "sg:tags":[
        "information",
        "attorney",
        "practice",
        "referral"
    ],
    "wof:name":"Ellis, Donald Attorney At Law",
    "wof:placetype":"venue"
},
  "geometry": {"coordinates":[-84.289209,33.741072],"type":"Point"}
}