{
  "type": "Feature",
  "properties": {
    "iso:country":"US",
    "sg:address":"4860 Habersham Way SE",
    "sg:city":"Conyers",
    "sg:classifiers":[
        {
            "category":"Social Services",
            "subcategory":"Job Training",
            "type":"Services"
        }
    ],
    "sg:phone":"+1 770 761 7049",
    "sg:postcode":"30094",
    "sg:province":"GA",
    "wof:name":"Shamrock Services",
    "wof:placetype":"venue"
},
  "geometry": {"coordinates":[-84.034257,33.558273],"type":"Point"}
}