{
  "type": "Feature",
  "properties": {
    "iso:country":"US",
    "sg:address":"3128 Process Dr NW",
    "sg:city":"Norcross",
    "sg:classifiers":[
        {
            "category":"Manufacturing",
            "subcategory":"Tools & Machinery",
            "type":"Manufacturing & Wholesale Goods"
        },
        {
            "category":"Manufacturing",
            "subcategory":"Printing",
            "type":"Manufacturing & Wholesale Goods"
        }
    ],
    "sg:phone":"+1 770 448 9408",
    "sg:postcode":"30071",
    "sg:province":"GA",
    "sg:tags":[
        "plate",
        "printer",
        "for",
        "mfg",
        "color",
        "related",
        "separation"
    ],
    "wof:name":"Accurate Graphics Inc",
    "wof:placetype":"venue"
},
  "geometry": {"coordinates":[-84.178083,33.971065],"type":"Point"}
}