{
  "type": "Feature",
  "properties": {
    "iso:country":"US",
    "sg:address":"2452 US Hwy 280",
    "sg:city":"Cordele",
    "sg:classifiers":[
        {
            "category":"Food & Beverages",
            "subcategory":"Groceries & Convenience Stores",
            "type":"Retail Goods"
        }
    ],
    "sg:phone":"+1 229 273 7955",
    "sg:postcode":"31015",
    "sg:province":"GA",
    "sg:tags":[
        "grocer"
    ],
    "wof:name":"Arrowhead Grocery",
    "wof:placetype":"venue"
},
  "geometry": {"coordinates":[-83.899186,31.97001],"type":"Point"}
}