{
  "type": "Feature",
  "properties": {
    "addr:full":"2463 Hamilton Mill Pkwy Dacula GA 30019",
    "addr:housenumber":"2463",
    "addr:postcode":"ga 30019",
    "addr:street":"Hamilton Mill Pkwy",
    "iso:country":"US",
    "sg:address":"2463 Hamilton Mill Pkwy",
    "sg:city":"Dacula",
    "sg:classifiers":[
        {
            "category":"Insurance",
            "subcategory":"Insurance Agent",
            "type":"Services"
        },
        {
            "category":"Insurance",
            "subcategory":"Hazard Insurance",
            "type":"Services"
        },
        {
            "category":"Insurance",
            "subcategory":"Title Insurance",
            "type":"Services"
        }
    ],
    "sg:phone":"+1 678 745 9525",
    "sg:postcode":"30019",
    "sg:province":"GA",
    "sg:tags":[
        "auto",
        "homeowner"
    ],
    "sg:website":"http://apps.amfam.com/agentlocator/?sourceid=yp3",
    "wof:name":"American Family Insurance- John J Johnson",
    "wof:placetype":"venue"
},
  "geometry": {"coordinates":[-83.91774100000001,34.073846],"type":"Point"}
}