{
  "type": "Feature",
  "properties": {
    "addr:full":"9201 Ayersville Rd Toccoa GA 30577",
    "addr:housenumber":"9201",
    "addr:postcode":"30577",
    "addr:street":"Ayersville Rd",
    "iso:country":"US",
    "sg:address":"9201 Ayersville Rd",
    "sg:city":"Toccoa",
    "sg:classifiers":[
        {
            "category":"Manufacturing",
            "subcategory":"Tools & Machinery",
            "type":"Manufacturing & Wholesale Goods"
        }
    ],
    "sg:phone":"+1 706 886 2101",
    "sg:postcode":"30577",
    "sg:province":"GA",
    "sg:tags":[
        "pump"
    ],
    "sg:website":"www.pattersonpumps.com",
    "wof:name":"Patterson Pump Co",
    "wof:placetype":"venue"
},
  "geometry": {"coordinates":[-83.40948400000001,34.551834],"type":"Point"}
}