{
  "type": "Feature",
  "properties": {
    "iso:country":"US",
    "sg:address":"5835 Live Oak Pkwy Ste B",
    "sg:city":"Norcross",
    "sg:classifiers":[
        {
            "category":"Professional",
            "subcategory":"Accounting & Tax Preparation",
            "type":"Services"
        }
    ],
    "sg:phone":"+1 770 449 6715",
    "sg:postcode":"30093",
    "sg:province":"GA",
    "sg:tags":[
        "accountant"
    ],
    "wof:name":"Hill Les CPA PC",
    "wof:placetype":"venue"
},
  "geometry": {"coordinates":[-84.200699,33.912701],"type":"Point"}
}