{
  "type": "Feature",
  "properties": {
    "addr:full":"452 Benson Rd Dallas GA 30132",
    "addr:housenumber":"452",
    "addr:postcode":"30132",
    "addr:street":"Benson Rd",
    "iso:country":"US",
    "sg:address":"452 Benson Rd",
    "sg:city":"Dallas",
    "sg:classifiers":[
        {
            "category":"Building & Trades",
            "subcategory":"Construction",
            "type":"Services"
        }
    ],
    "sg:phone":"+1 770 445 3595",
    "sg:postcode":"30132",
    "sg:province":"GA",
    "sg:tags":[
        "house"
    ],
    "wof:name":"Jww Construction LLC",
    "wof:placetype":"venue"
},
  "geometry": {"coordinates":[-84.845022,34.015397],"type":"Point"}
}