{
  "type": "Feature",
  "properties": {
    "addr:full":"6555 Peachtree Industrial Atlanta GA 30360",
    "addr:housenumber":"6555",
    "addr:postcode":"30360",
    "addr:street":"Peachtree Industrial",
    "iso:country":"US",
    "sg:address":"6555 Peachtree Industrial",
    "sg:city":"Atlanta",
    "sg:classifiers":[
        {
            "category":"Manufacturing",
            "subcategory":"Rubber & Plastics",
            "type":"Manufacturing & Wholesale Goods"
        },
        {
            "category":"Autos & Motor Vehicles",
            "subcategory":"Auto Supplies",
            "type":"Retail Goods"
        },
        {
            "category":"Retail",
            "subcategory":"Auto Repair",
            "type":"Services"
        }
    ],
    "sg:phone":"+1 770 455 1080",
    "sg:postcode":"30360",
    "sg:province":"GA",
    "sg:tags":[
        "wheel",
        "tires-wholesale",
        "tire",
        "retread",
        "balancing",
        "wheels-aligning",
        "recap",
        "brake",
        "manufacturer"
    ],
    "sg:website":"http://www.ntb.com",
    "wof:name":"Ntb-National Tire & Battery",
    "wof:placetype":"venue"
},
  "geometry": {"coordinates":[-84.27672699999999,33.92548],"type":"Point"}
}