{
  "type": "Feature",
  "properties": {
    "iso:country":"US",
    "sg:address":"2759 Delk Rd SE",
    "sg:city":"Marietta",
    "sg:classifiers":[
        {
            "category":"Personal",
            "subcategory":"Beauty Salon",
            "type":"Services"
        },
        {
            "category":"Personal",
            "subcategory":"Day Spa",
            "type":"Services"
        }
    ],
    "sg:phone":"+1 770 980 2005",
    "sg:postcode":"30067",
    "sg:province":"GA",
    "wof:name":"Elysium Spirit at Marietta Healthcare",
    "wof:placetype":"venue"
},
  "geometry": {"coordinates":[-84.473046,33.923086],"type":"Point"}
}