{
  "type": "Feature",
  "properties": {
    "iso:country":"US",
    "sg:address":"1949 Linwood Ave",
    "sg:city":"Atlanta",
    "sg:classifiers":[
        {
            "category":"Real Estate",
            "subcategory":"Real Estate Services",
            "type":"Services"
        },
        {
            "category":"Banks & Credit Unions",
            "subcategory":"Financial Services",
            "type":"Services"
        }
    ],
    "sg:phone":"+1 404 763 9933",
    "sg:postcode":"30344",
    "sg:province":"GA",
    "sg:tags":[
        "loan",
        "broker",
        "mortgage"
    ],
    "wof:name":"Northern Solutions",
    "wof:placetype":"venue"
},
  "geometry": {"coordinates":[-84.452116,33.680838],"type":"Point"}
}