{
  "type": "Feature",
  "properties": {
    "iso:country":"US",
    "sg:address":"120 Cobb St",
    "sg:city":"Davisboro",
    "sg:classifiers":[
        {
            "category":"Farming",
            "subcategory":"Farm & Veterinary Services",
            "type":"Manufacturing & Wholesale Goods"
        }
    ],
    "sg:phone":"+1 478 348 4931",
    "sg:postcode":"31018",
    "sg:province":"GA",
    "sg:tags":[
        "seed",
        "grain",
        "cleaning"
    ],
    "wof:name":"Cobb & Cobb Seed Co",
    "wof:placetype":"venue"
},
  "geometry": {"coordinates":[-82.609061,32.987104],"type":"Point"}
}