{
  "type": "Feature",
  "properties": {
    "iso:country":"US",
    "sg:address":"2869 Woodland Park Dr NE",
    "sg:city":"Atlanta",
    "sg:classifiers":[
        {
            "category":"Building & Trades",
            "subcategory":"Electrical",
            "type":"Services"
        }
    ],
    "sg:phone":"+1 404 325 4836",
    "sg:postcode":"30345",
    "sg:province":"GA",
    "sg:tags":[
        "electric",
        "contractor"
    ],
    "wof:name":"Correct Tech",
    "wof:placetype":"venue"
},
  "geometry": {"coordinates":[-84.272232,33.839713],"type":"Point"}
}