{
  "type": "Feature",
  "properties": {
    "addr:full":"3097 Satellite Boulevard Duluth GA 30096-5810",
    "addr:housenumber":"3097",
    "addr:postcode":"30096-5810",
    "addr:street":"Satellite Boulevard",
    "iso:country":"US",
    "sg:address":"3097 Satellite Boulevard",
    "sg:city":"Duluth",
    "sg:classifiers":[
        {
            "category":"Professional",
            "subcategory":"Computer Services",
            "type":"Services"
        }
    ],
    "sg:phone":"+1 937 445 1936",
    "sg:postcode":"30096-5810",
    "sg:province":"GA",
    "sg:website":"http://www.ncr.com/",
    "wof:name":"NCR",
    "wof:placetype":"venue"
},
  "geometry": {"coordinates":[-84.115692,33.961657],"type":"Point"}
}