{
  "type": "Feature",
  "properties": {
    "iso:country":"US",
    "sg:address":"2565 Millerfield Rd",
    "sg:city":"Macon",
    "sg:classifiers":[
        {
            "category":"Real Estate",
            "subcategory":"Real Estate Operator",
            "type":"Services"
        }
    ],
    "sg:phone":"+1 478 743 3244",
    "sg:postcode":"31217",
    "sg:province":"GA",
    "sg:tags":[
        "apartment"
    ],
    "wof:name":"LA Tanya Village",
    "wof:placetype":"venue"
},
  "geometry": {"coordinates":[-83.580592,32.859638],"type":"Point"}
}