{
  "type": "Feature",
  "properties": {
    "iso:country":"US",
    "sg:address":"1300 Desota Dr",
    "sg:city":"Dalton",
    "sg:classifiers":[
        {
            "category":"Building & Trades",
            "subcategory":"Landscaping Services",
            "type":"Services"
        }
    ],
    "sg:phone":"+1 706 277 0006",
    "sg:postcode":"30720",
    "sg:province":"GA",
    "wof:name":"All - Seasons",
    "wof:placetype":"venue"
},
  "geometry": {"coordinates":[-84.985223,34.754138],"type":"Point"}
}