{
  "type": "Feature",
  "properties": {
    "addr:full":"1895 Highway 20 SE Ste 160 Conyers GA 30013",
    "addr:housenumber":"1895",
    "addr:postcode":"30013",
    "addr:street":"Highway 20 Se Ste 160",
    "iso:country":"US",
    "sg:address":"1895 Highway 20 SE Ste 160",
    "sg:city":"Conyers",
    "sg:classifiers":[
        {
            "category":"Health Services",
            "subcategory":"Chiropractor",
            "type":"Services"
        }
    ],
    "sg:phone":"+1 770 922 8150",
    "sg:postcode":"30013",
    "sg:province":"GA",
    "sg:tags":[
        "chiropractic"
    ],
    "wof:name":"Conyer's Chiropractic Center",
    "wof:placetype":"venue"
},
  "geometry": {"coordinates":[-84.014503,33.639767],"type":"Point"}
}