{
  "type": "Feature",
  "properties": {
    "iso:country":"US",
    "sg:address":"4670 Lost Mountain Dr",
    "sg:city":"Powder Springs",
    "sg:classifiers":[
        {
            "category":"Building & Trades",
            "subcategory":"Plumbing",
            "type":"Services"
        }
    ],
    "sg:phone":"+1 770 428 2895",
    "sg:postcode":"30127",
    "sg:province":"GA",
    "sg:tags":[
        "contractor"
    ],
    "wof:name":"Van Ledford",
    "wof:placetype":"venue"
},
  "geometry": {"coordinates":[-84.687242,33.921378],"type":"Point"}
}