{
  "type": "Feature",
  "properties": {
    "addr:full":"2240 Fountain Dr Snellville GA 30078",
    "addr:housenumber":"2240",
    "addr:postcode":"30078",
    "addr:street":"Fountain Dr",
    "iso:country":"US",
    "sg:address":"2240 Fountain Dr",
    "sg:city":"Snellville",
    "sg:classifiers":[
        {
            "category":"Insurance",
            "subcategory":"Hazard Insurance",
            "type":"Services"
        }
    ],
    "sg:phone":"+1 770 978 6076",
    "sg:postcode":"30078",
    "sg:province":"GA",
    "wof:name":"Kaiser Permanente",
    "wof:placetype":"venue"
},
  "geometry": {"coordinates":[-84.02907399999999,33.856232],"type":"Point"}
}