{
  "type": "Feature",
  "properties": {
    "iso:country":"US",
    "sg:address":"51 Bryant St",
    "sg:city":"Jasper",
    "sg:classifiers":[
        {
            "category":"Food & Beverages",
            "subcategory":"Groceries & Convenience Stores",
            "type":"Retail Goods"
        }
    ],
    "sg:phone":"+1 706 253 3662",
    "sg:postcode":"30143",
    "sg:province":"GA",
    "wof:name":"La Loma Mexican Store",
    "wof:placetype":"venue"
},
  "geometry": {"coordinates":[-84.44207,34.467211],"type":"Point"}
}