{
  "type": "Feature",
  "properties": {
    "addr:full":"190 Stewart Dr NW Milledgeville GA 31061",
    "addr:housenumber":"190",
    "addr:postcode":"31061",
    "addr:street":"Stewart Dr Nw",
    "iso:country":"US",
    "sg:address":"190 Stewart Dr NW",
    "sg:city":"Milledgeville",
    "sg:classifiers":[
        {
            "category":"Shopping",
            "subcategory":"Party Supplies",
            "type":"Retail Goods"
        }
    ],
    "sg:phone":"+1 478 457 3997",
    "sg:postcode":"31061",
    "sg:province":"GA",
    "sg:tags":[
        "decoration",
        "rental"
    ],
    "wof:name":"Happy Times Jumpers & Party Re",
    "wof:placetype":"venue"
},
  "geometry": {"coordinates":[-83.307288,33.166456],"type":"Point"}
}