{
  "type": "Feature",
  "properties": {
    "iso:country":"US",
    "sg:address":"1071 Yemassee Trl",
    "sg:city":"Stone Mountain",
    "sg:classifiers":[
        {
            "category":"Professional",
            "subcategory":"Management & Consulting",
            "type":"Services"
        }
    ],
    "sg:phone":"+1 404 297 4824",
    "sg:postcode":"30083",
    "sg:province":"GA",
    "wof:name":"Lawmark International Corp",
    "wof:placetype":"venue"
},
  "geometry": {"coordinates":[-84.22624999999999,33.765609],"type":"Point"}
}