{
  "type": "Feature",
  "properties": {
    "addr:full":"118 W Fork Dr Newnan GA 30263",
    "addr:housenumber":"118",
    "addr:postcode":"30263",
    "addr:street":"W Fork Dr",
    "iso:country":"US",
    "sg:address":"118 W Fork Dr",
    "sg:city":"Newnan",
    "sg:classifiers":[
        {
            "category":"Freight",
            "type":"Transportation"
        }
    ],
    "sg:phone":"+1 770 253 9832",
    "sg:postcode":"30263",
    "sg:province":"GA",
    "sg:tags":[
        "operator",
        "local",
        "trucking"
    ],
    "wof:name":"Westbrook Water",
    "wof:placetype":"venue"
},
  "geometry": {"coordinates":[-84.87270100000001,33.414079],"type":"Point"}
}