{
  "type": "Feature",
  "properties": {
    "addr:full":"4226 Beaver Ruin Ct NW Lilburn GA 30047",
    "addr:housenumber":"4226",
    "addr:postcode":"30047",
    "addr:street":"Beaver Ruin Ct Nw",
    "iso:country":"US",
    "sg:address":"4226 Beaver Ruin Ct NW",
    "sg:city":"Lilburn",
    "sg:classifiers":[
        {
            "category":"Health Services",
            "subcategory":"Doctor",
            "type":"Services"
        }
    ],
    "sg:phone":"+1 770 921 4443",
    "sg:postcode":"30047",
    "sg:province":"GA",
    "wof:name":"J J Shah",
    "wof:placetype":"venue"
},
  "geometry": {"coordinates":[-84.123965,33.905864],"type":"Point"}
}