{
  "type": "Feature",
  "properties": {
    "iso:country":"US",
    "sg:address":"3479 Casteel Rd",
    "sg:city":"Marietta",
    "sg:classifiers":[
        {
            "category":"Building & Trades",
            "subcategory":"Construction",
            "type":"Services"
        }
    ],
    "sg:phone":"+1 770 578 1193",
    "sg:postcode":"30062",
    "sg:province":"GA",
    "sg:tags":[
        "hanging",
        "contractor"
    ],
    "wof:name":"Trachtenberg Painting Group",
    "wof:placetype":"venue"
},
  "geometry": {"coordinates":[-84.44859599999999,34.002804],"type":"Point"}
}