{
  "type": "Feature",
  "properties": {
    "iso:country":"US",
    "sg:address":"6822 Cherry Cir",
    "sg:city":"Lithia Springs",
    "sg:classifiers":[
        {
            "category":"Shopping",
            "subcategory":"Clothing, Apparel, & Fashions",
            "type":"Retail Goods"
        }
    ],
    "sg:phone":"+1 770 941 4337",
    "sg:postcode":"30122",
    "sg:province":"GA",
    "wof:name":"Georgia Girl Crafts & More",
    "wof:placetype":"venue"
},
  "geometry": {"coordinates":[-84.67447300000001,33.7881],"type":"Point"}
}