{
  "type": "Feature",
  "properties": {
    "addr:full":"2703 Barnaby Dr Albany GA 31701",
    "addr:housenumber":"2703",
    "addr:postcode":"31701",
    "addr:street":"Barnaby Dr",
    "iso:country":"US",
    "sg:address":"2703 Barnaby Dr",
    "sg:city":"Albany",
    "sg:classifiers":[
        {
            "category":"Manufacturing",
            "subcategory":"Paper Products",
            "type":"Manufacturing & Wholesale Goods"
        }
    ],
    "sg:phone":"+1 229 888 7144",
    "sg:postcode":"31701",
    "sg:province":"GA",
    "sg:tags":[
        "die",
        "mfg"
    ],
    "wof:name":"Brown Doc Inc",
    "wof:placetype":"venue"
},
  "geometry": {"coordinates":[-84.165176,31.520014],"type":"Point"}
}