{
  "type": "Feature",
  "properties": {
    "addr:full":"1972 Lake Lucerne Dr SW Lilburn GA 30047",
    "addr:housenumber":"1972",
    "addr:postcode":"30047",
    "addr:street":"Lake Lucerne Dr Sw",
    "iso:country":"US",
    "sg:address":"1972 Lake Lucerne Dr SW",
    "sg:city":"Lilburn",
    "sg:classifiers":[
        {
            "category":"Structure",
            "subcategory":"Office Building",
            "type":"Public Place"
        }
    ],
    "sg:phone":"+1 678 227 0531",
    "sg:postcode":"30047",
    "sg:province":"GA",
    "sg:tags":[
        "park"
    ],
    "wof:name":"Janus Properties Lc",
    "wof:placetype":"venue"
},
  "geometry": {"coordinates":[-84.096101,33.831933],"type":"Point"}
}