{
  "type": "Feature",
  "properties": {
    "iso:country":"US",
    "sg:address":"2063 Beachwood Dr SE",
    "sg:city":"Conyers",
    "sg:classifiers":[
        {
            "category":"Professional",
            "subcategory":"Secretarial Services",
            "type":"Services"
        }
    ],
    "sg:phone":"+1 770 388 0815",
    "sg:postcode":"30013",
    "sg:province":"GA",
    "sg:tags":[
        "reporting"
    ],
    "wof:name":"Stokes Reporting Service",
    "wof:placetype":"venue"
},
  "geometry": {"coordinates":[-83.978694,33.599467],"type":"Point"}
}