{
  "type": "Feature",
  "properties": {
    "iso:country":"US",
    "sg:address":"1010 Olde Town Ln",
    "sg:city":"Woodstock",
    "sg:classifiers":[
        {
            "category":"Manufacturing",
            "subcategory":"Toys & Sporting Goods",
            "type":"Manufacturing & Wholesale Goods"
        }
    ],
    "sg:phone":"+1 770 924 2883",
    "sg:postcode":"30189",
    "sg:province":"GA",
    "sg:tags":[
        "mfg"
    ],
    "wof:name":"Hot Glove Inc",
    "wof:placetype":"venue"
},
  "geometry": {"coordinates":[-84.57243200000001,34.131011],"type":"Point"}
}