{
  "type": "Feature",
  "properties": {
    "iso:country":"US",
    "sg:address":"1236 Wildwood Ave",
    "sg:city":"Columbus",
    "sg:classifiers":[
        {
            "category":"Shopping",
            "subcategory":"Used Merchandise",
            "type":"Retail Goods"
        }
    ],
    "sg:phone":"+1 706 221 6321",
    "sg:postcode":"31906",
    "sg:province":"GA",
    "sg:tags":[
        "antique"
    ],
    "wof:name":"Wildwood Antiques",
    "wof:placetype":"venue"
},
  "geometry": {"coordinates":[-84.957824,32.472034],"type":"Point"}
}