{
  "type": "Feature",
  "properties": {
    "iso:country":"US",
    "sg:address":"59 Winnstead Dr",
    "sg:city":"Mableton",
    "sg:classifiers":[
        {
            "category":"Wholesale",
            "subcategory":"Vending Machines",
            "type":"Manufacturing & Wholesale Goods"
        }
    ],
    "sg:phone":"+1 770 948 4122",
    "sg:postcode":"30126",
    "sg:province":"GA",
    "sg:tags":[
        "operator"
    ],
    "wof:name":"Hayatdavoudi Vending Co",
    "wof:placetype":"venue"
},
  "geometry": {"coordinates":[-84.53096600000001,33.788954],"type":"Point"}
}