{
  "type": "Feature",
  "properties": {
    "iso:country":"US",
    "sg:address":"580 Briarmeade Dr",
    "sg:city":"Marietta",
    "sg:classifiers":[
        {
            "category":"Professional",
            "subcategory":"Business Services",
            "type":"Services"
        }
    ],
    "sg:phone":"+1 770 429 9649",
    "sg:postcode":"30064",
    "sg:province":"GA",
    "wof:name":"Interior Makeovers LLC",
    "wof:placetype":"venue"
},
  "geometry": {"coordinates":[-84.591894,33.934103],"type":"Point"}
}