{
  "type": "Feature",
  "properties": {
    "addr:full":"105 Pine St Mc Rae GA 31055",
    "addr:housenumber":"105",
    "addr:postcode":"31055",
    "addr:street":"Pine St Mc Rae",
    "iso:country":"US",
    "sg:address":"105 Pine St",
    "sg:city":"Mc Rae",
    "sg:classifiers":[
        {
            "category":"Government",
            "subcategory":"Police Station",
            "type":"Public Place"
        }
    ],
    "sg:phone":"+1 229 868 6333",
    "sg:postcode":"31055",
    "sg:province":"GA",
    "sg:tags":[
        "department"
    ],
    "wof:name":"Mc Rae Police Dept",
    "wof:placetype":"venue"
},
  "geometry": {"coordinates":[-82.89973500000001,32.067113],"type":"Point"}
}