{
  "type": "Feature",
  "properties": {
    "addr:full":"5701 Roswell Rd Atlanta GA 30342",
    "addr:housenumber":"5701",
    "addr:postcode":"30342",
    "addr:street":"Roswell Rd",
    "iso:country":"US",
    "sg:address":"5701 Roswell Rd",
    "sg:city":"Atlanta",
    "sg:classifiers":[
        {
            "category":"Food & Beverages",
            "subcategory":"Groceries & Convenience Stores",
            "type":"Retail Goods"
        }
    ],
    "sg:phone":"+1 404 943 0237",
    "sg:postcode":"30342",
    "sg:province":"GA",
    "wof:name":"Stars Oil Inc",
    "wof:placetype":"venue"
},
  "geometry": {"coordinates":[-84.378666,33.910185],"type":"Point"}
}