{
  "type": "Feature",
  "properties": {
    "iso:country":"US",
    "sg:address":"2910 Cole Ct Ste C",
    "sg:city":"Norcross",
    "sg:classifiers":[
        {
            "category":"Food & Beverages",
            "subcategory":"Specialty",
            "type":"Retail Goods"
        }
    ],
    "sg:phone":"+1 770 416 7349",
    "sg:postcode":"30071",
    "sg:province":"GA",
    "wof:name":"Perimeter Solutions & Maintenance",
    "wof:placetype":"venue"
},
  "geometry": {"coordinates":[-84.2033,33.9515],"type":"Point"}
}