{
  "type": "Feature",
  "properties": {
    "iso:country":"US",
    "sg:address":"4227 Steve Reynolds Blvd",
    "sg:city":"Norcross",
    "sg:classifiers":[
        {
            "category":"Shopping",
            "subcategory":"Comic Books",
            "type":"Retail Goods"
        }
    ],
    "sg:phone":"+1 770 923 2498",
    "sg:postcode":"30093",
    "sg:province":"GA",
    "wof:name":"House of Anime",
    "wof:placetype":"venue"
},
  "geometry": {"coordinates":[-84.146698,33.93],"type":"Point"}
}