{
  "type": "Feature",
  "properties": {
    "iso:country":"US",
    "sg:address":"1087 Alpharetta Hwy",
    "sg:city":"Roswell",
    "sg:classifiers":[
        {
            "category":"Health Services",
            "subcategory":"Doctor",
            "type":"Services"
        }
    ],
    "sg:phone":"+1 770 650 0061",
    "sg:postcode":"30075",
    "sg:province":"GA",
    "sg:tags":[
        "dentist"
    ],
    "wof:name":"Cosmetic & Family Dentistry",
    "wof:placetype":"venue"
},
  "geometry": {"coordinates":[-84.357426,34.028383],"type":"Point"}
}