{
  "type": "Feature",
  "properties": {
    "iso:country":"US",
    "sg:address":"1290 Sweetwoods Dr",
    "sg:city":"Lawrenceville",
    "sg:classifiers":[
        {
            "category":"Building & Trades",
            "subcategory":"Construction",
            "type":"Services"
        }
    ],
    "sg:phone":"+1 770 931 5787",
    "sg:postcode":"30044",
    "sg:province":"GA",
    "sg:tags":[
        "general",
        "contractor"
    ],
    "wof:name":"Lion Construction",
    "wof:placetype":"venue"
},
  "geometry": {"coordinates":[-84.09491800000001,33.948114],"type":"Point"}
}