{
  "type": "Feature",
  "properties": {
    "addr:full":"6383 Wedgewood Trce Tucker GA 30084",
    "addr:housenumber":"6383",
    "addr:postcode":"30084",
    "addr:street":"Wedgewood Trce",
    "iso:country":"US",
    "sg:address":"6383 Wedgewood Trce",
    "sg:city":"Tucker",
    "sg:classifiers":[
        {
            "category":"Real Estate",
            "subcategory":"Real Estate Agent",
            "type":"Services"
        }
    ],
    "sg:phone":"+1 770 938 2901",
    "sg:postcode":"30084",
    "sg:province":"GA",
    "wof:name":"Great Properties",
    "wof:placetype":"venue"
},
  "geometry": {"coordinates":[-84.20307200000001,33.889355],"type":"Point"}
}