{
  "type": "Feature",
  "properties": {
    "iso:country":"US",
    "sg:address":"4472 N Peachtree Rd",
    "sg:city":"Atlanta",
    "sg:classifiers":[
        {
            "category":"Real Estate",
            "subcategory":"Real Estate Agent",
            "type":"Services"
        }
    ],
    "sg:phone":"+1 770 986 8524",
    "sg:postcode":"30338",
    "sg:province":"GA",
    "wof:name":"Cook Appraisal Inc",
    "wof:placetype":"venue"
},
  "geometry": {"coordinates":[-84.29677700000001,33.920595],"type":"Point"}
}