{
  "type": "Feature",
  "properties": {
    "addr:full":"100 Ashley St Apt 98A Perry GA 31069",
    "addr:housenumber":"100",
    "addr:postcode":"31069",
    "addr:street":"Ashley St Apt",
    "iso:country":"US",
    "sg:address":"100 Ashley St Apt 98A",
    "sg:city":"Perry",
    "sg:classifiers":[
        {
            "category":"Real Estate",
            "subcategory":"Real Estate Operator",
            "type":"Services"
        }
    ],
    "sg:phone":"+1 478 987 7749",
    "sg:postcode":"31069",
    "sg:province":"GA",
    "sg:tags":[
        "apartment"
    ],
    "wof:name":"Heritage Apts",
    "wof:placetype":"venue"
},
  "geometry": {"coordinates":[-83.731407,32.463001],"type":"Point"}
}