{
  "type": "Feature",
  "properties": {
    "addr:full":"1038 E Forsyth St Americus GA 31709",
    "addr:housenumber":"1038",
    "addr:postcode":"31709",
    "addr:street":"E Forsyth St",
    "iso:country":"US",
    "sg:address":"1038 E Forsyth St",
    "sg:city":"Americus",
    "sg:classifiers":[
        {
            "category":"Wholesale",
            "subcategory":"Medical Equipment & Supplies",
            "type":"Manufacturing & Wholesale Goods"
        }
    ],
    "sg:phone":"+1 229 928 2701",
    "sg:postcode":"31709",
    "sg:province":"GA",
    "sg:tags":[
        "hospital"
    ],
    "wof:name":"MRS Homecare",
    "wof:placetype":"venue"
},
  "geometry": {"coordinates":[-84.217708,32.073363],"type":"Point"}
}