{
  "type": "Feature",
  "properties": {
    "addr:full":"2309 Abner Pl NW Atlanta GA 30318",
    "addr:housenumber":"2309",
    "addr:postcode":"30318",
    "addr:street":"Abner Pl Nw",
    "iso:country":"US",
    "sg:address":"2309 Abner Pl NW",
    "sg:city":"Atlanta",
    "sg:classifiers":[
        {
            "category":"Real Estate",
            "subcategory":"Real Estate Operator",
            "type":"Services"
        }
    ],
    "sg:phone":"+1 404 799 8621",
    "sg:postcode":"30318",
    "sg:province":"GA",
    "sg:tags":[
        "building",
        "nonresidential"
    ],
    "wof:name":"A&A Property",
    "wof:placetype":"venue"
},
  "geometry": {"coordinates":[-84.46510000000001,33.802008],"type":"Point"}
}