{
  "type": "Feature",
  "properties": {
    "addr:full":"106 Boone Rd Hoschton GA 30548",
    "addr:housenumber":"106",
    "addr:postcode":"30548",
    "addr:street":"Boone Rd",
    "iso:country":"US",
    "sg:address":"106 Boone Rd",
    "sg:city":"Hoschton",
    "sg:classifiers":[
        {
            "category":"Farming",
            "subcategory":"Poultry Farm",
            "type":"Manufacturing & Wholesale Goods"
        }
    ],
    "sg:phone":"+1 706 654 3942",
    "sg:postcode":"30548",
    "sg:province":"GA",
    "sg:tags":[
        "chicken"
    ],
    "wof:name":"Second Chance F",
    "wof:placetype":"venue"
},
  "geometry": {"coordinates":[-83.711736,34.109351],"type":"Point"}
}