{
  "type": "Feature",
  "properties": {
    "iso:country":"US",
    "sg:address":"1550 Pebblebrook Cir SE",
    "sg:city":"Mableton",
    "sg:classifiers":[
        {
            "category":"Education",
            "subcategory":"Special Training",
            "type":"Public Place"
        }
    ],
    "sg:phone":"+1 770 941 0533",
    "sg:postcode":"30126",
    "sg:province":"GA",
    "sg:tags":[
        "school",
        "language"
    ],
    "wof:name":"Georgia Japanese Language School",
    "wof:placetype":"venue"
},
  "geometry": {"coordinates":[-84.510749,33.819471],"type":"Point"}
}