{
  "type": "Feature",
  "properties": {
    "addr:full":"703 Indian Hills Pkwy NE Marietta GA 30068",
    "addr:housenumber":"703",
    "addr:postcode":"30068",
    "addr:street":"Indian Hills Pkwy Ne",
    "iso:country":"US",
    "sg:address":"703 Indian Hills Pkwy NE",
    "sg:city":"Marietta",
    "sg:classifiers":[
        {
            "category":"Manufacturing",
            "subcategory":"Printing",
            "type":"Manufacturing & Wholesale Goods"
        }
    ],
    "sg:phone":"+1 770 977 2173",
    "sg:postcode":"30068",
    "sg:province":"GA",
    "sg:tags":[
        "lithographic",
        "commercial"
    ],
    "wof:name":"Hughes Printing Services Inc",
    "wof:placetype":"venue"
},
  "geometry": {"coordinates":[-84.43833100000001,33.967821],"type":"Point"}
}