{
  "type": "Feature",
  "properties": {
    "addr:full":"4977 Fairhaven Way Roswell GA 30075",
    "addr:housenumber":"4977",
    "addr:postcode":"30075",
    "addr:street":"Fairhaven Way",
    "iso:country":"US",
    "sg:address":"4977 Fairhaven Way",
    "sg:city":"Roswell",
    "sg:classifiers":[
        {
            "category":"Professional",
            "subcategory":"Management & Consulting",
            "type":"Services"
        }
    ],
    "sg:phone":"+1 770 641 0151",
    "sg:postcode":"30075",
    "sg:province":"GA",
    "wof:name":"B Fishman Assoc",
    "wof:placetype":"venue"
},
  "geometry": {"coordinates":[-84.40529600000001,34.035877],"type":"Point"}
}