{
  "type": "Feature",
  "properties": {
    "addr:full":"4695 Arden Dr Buford GA 30518",
    "addr:housenumber":"4695",
    "addr:postcode":"30518",
    "addr:street":"Arden Dr",
    "iso:country":"US",
    "sg:address":"4695 Arden Dr",
    "sg:city":"Buford",
    "sg:classifiers":[
        {
            "category":"Professional",
            "subcategory":"Business Services",
            "type":"Services"
        }
    ],
    "sg:phone":"+1 770 932 8255",
    "sg:postcode":"30518",
    "sg:province":"GA",
    "wof:name":"Fem Services Inc",
    "wof:placetype":"venue"
},
  "geometry": {"coordinates":[-83.976859,34.123744],"type":"Point"}
}