{
  "type": "Feature",
  "properties": {
    "addr:full":"1976 Airport Ind Park Dr Marietta GA 30060",
    "addr:housenumber":"1976",
    "addr:postcode":"30060",
    "addr:street":"Airport Ind Park Dr",
    "iso:country":"US",
    "sg:address":"1976 Airport Ind Park Dr",
    "sg:city":"Marietta",
    "sg:classifiers":[
        {
            "category":"Building & Trades",
            "subcategory":"Plumbing",
            "type":"Services"
        }
    ],
    "sg:phone":"+1 770 952 3864",
    "sg:postcode":"30060",
    "sg:province":"GA",
    "sg:tags":[
        "contractor"
    ],
    "wof:name":"Miller Mechanical Contractor",
    "wof:placetype":"venue"
},
  "geometry": {"coordinates":[-84.49677800000001,33.90481],"type":"Point"}
}