{
  "type": "Feature",
  "properties": {
    "iso:country":"US",
    "sg:address":"2152 Paces Vale Pl",
    "sg:city":"Lawrenceville",
    "sg:classifiers":[
        {
            "category":"Wholesale",
            "subcategory":"Machinery & Supplies",
            "type":"Manufacturing & Wholesale Goods"
        }
    ],
    "sg:phone":"+1 770 277 4041",
    "sg:postcode":"30043",
    "sg:province":"GA",
    "sg:tags":[
        "equipment",
        "industrial"
    ],
    "wof:name":"R & M Handling",
    "wof:placetype":"venue"
},
  "geometry": {"coordinates":[-83.94157199999999,34.035085],"type":"Point"}
}