{
  "type": "Feature",
  "properties": {
    "addr:full":"216 Mims Rd Sylvania GA 30467",
    "addr:housenumber":"216",
    "addr:postcode":"30467",
    "addr:street":"Mims Rd",
    "iso:country":"US",
    "sg:address":"216 Mims Rd",
    "sg:city":"Sylvania",
    "sg:classifiers":[
        {
            "category":"Education",
            "subcategory":"School",
            "type":"Public Place"
        }
    ],
    "sg:phone":"+1 912 564 7114",
    "sg:postcode":"30467",
    "sg:province":"GA",
    "wof:name":"Screven County School District",
    "wof:placetype":"venue"
},
  "geometry": {"coordinates":[-81.64676,32.750828],"type":"Point"}
}