{
  "type": "Feature",
  "properties": {
    "iso:country":"US",
    "sg:address":"5249 Martins Crossing Rd",
    "sg:city":"Stone Mountain",
    "sg:classifiers":[
        {
            "category":"Local Transit",
            "type":"Transportation"
        }
    ],
    "sg:phone":"+1 770 469 0480",
    "sg:postcode":"30088",
    "sg:province":"GA",
    "sg:tags":[
        "shuttle",
        "to",
        "airport",
        "from"
    ],
    "wof:name":"H H Transportation",
    "wof:placetype":"venue"
},
  "geometry": {"coordinates":[-84.177122,33.774911],"type":"Point"}
}