{
  "type": "Feature",
  "properties": {
    "addr:full":"1017 Walthour Rd Savannah GA 31410",
    "addr:housenumber":"1017",
    "addr:postcode":"31410",
    "addr:street":"Walthour Rd",
    "iso:country":"US",
    "sg:address":"1017 Walthour Rd",
    "sg:city":"Savannah",
    "sg:classifiers":[
        {
            "category":"Building & Trades",
            "subcategory":"Construction",
            "type":"Services"
        }
    ],
    "sg:phone":"+1 912 898 9968",
    "sg:postcode":"31410",
    "sg:province":"GA",
    "sg:tags":[
        "system",
        "contractor",
        "air conditioning"
    ],
    "wof:name":"Carlson Heating And Air Condit",
    "wof:placetype":"venue"
},
  "geometry": {"coordinates":[-80.965512,32.004621],"type":"Point"}
}