{
  "type": "Feature",
  "properties": {
    "iso:country":"US",
    "sg:address":"80 Zander Dr",
    "sg:city":"Gainesville",
    "sg:classifiers":[
        {
            "category":"Building & Trades",
            "subcategory":"Construction",
            "type":"Services"
        }
    ],
    "sg:phone":"+1 770 535 2706",
    "sg:postcode":"30504",
    "sg:province":"GA",
    "sg:tags":[
        "fabricator",
        "metal"
    ],
    "wof:name":"C 2 Fabrication Inc",
    "wof:placetype":"venue"
},
  "geometry": {"coordinates":[-83.855732,34.273342],"type":"Point"}
}