{
  "type": "Feature",
  "properties": {
    "addr:full":"586 Highview Cir Grovetown GA 30813",
    "addr:housenumber":"586",
    "addr:postcode":"30813",
    "addr:street":"Highview Cir",
    "iso:country":"US",
    "sg:address":"586 Highview Cir",
    "sg:city":"Grovetown",
    "sg:classifiers":[
        {
            "category":"Building & Trades",
            "subcategory":"Electrical",
            "type":"Services"
        }
    ],
    "sg:phone":"+1 706 863 4494",
    "sg:postcode":"30813",
    "sg:province":"GA",
    "sg:tags":[
        "electrician"
    ],
    "wof:name":"Dlf Electrical",
    "wof:placetype":"venue"
},
  "geometry": {"coordinates":[-82.175887,33.470272],"type":"Point"}
}