{
  "type": "Feature",
  "properties": {
    "iso:country":"US",
    "sg:address":"1022 Swathmore Dr NW",
    "sg:city":"Atlanta",
    "sg:classifiers":[
        {
            "category":"Building & Trades",
            "subcategory":"Construction",
            "type":"Services"
        }
    ],
    "sg:phone":"+1 404 869 7709",
    "sg:postcode":"30327",
    "sg:province":"GA",
    "sg:tags":[
        "home",
        "improvement",
        "general",
        "contractor"
    ],
    "wof:name":"Quality Minded Remodeling Inc",
    "wof:placetype":"venue"
},
  "geometry": {"coordinates":[-84.419416,33.875581],"type":"Point"}
}