{
  "type": "Feature",
  "properties": {
    "addr:full":"1644 Temple Ave Suite A Atlanta GA 30337",
    "addr:housenumber":"1644",
    "addr:postcode":"30337",
    "addr:street":"Temple Ave Suite A",
    "iso:country":"US",
    "sg:address":"1644 Temple Ave Suite A",
    "sg:city":"Atlanta",
    "sg:classifiers":[
        {
            "category":"Professional",
            "subcategory":"Computer Services",
            "type":"Services"
        }
    ],
    "sg:phone":"+1 404 349 7870",
    "sg:postcode":"30337",
    "sg:province":"GA",
    "sg:tags":[
        "wire",
        "installation",
        "network",
        "cable",
        "rooms-installation",
        "technical",
        "assistance",
        "system",
        "equipment",
        "design",
        "support"
    ],
    "wof:name":"Tri-Core Technologies",
    "wof:placetype":"venue"
},
  "geometry": {"coordinates":[-84.442774,33.655714],"type":"Point"}
}