{
  "type": "Feature",
  "properties": {
    "addr:full":"3695 W C Hodges Rd Statesboro GA 30461",
    "addr:housenumber":"3695",
    "addr:postcode":"30461",
    "addr:street":"W C Hodges Rd",
    "iso:country":"US",
    "sg:address":"3695 W C Hodges Rd",
    "sg:city":"Statesboro",
    "sg:classifiers":[
        {
            "category":"Building & Trades",
            "subcategory":"Plumbing",
            "type":"Services"
        }
    ],
    "sg:phone":"+1 912 587 5381",
    "sg:postcode":"30461",
    "sg:province":"GA",
    "sg:tags":[
        "plumbing",
        "contractor"
    ],
    "wof:name":"A & A Plumbing & Electrical",
    "wof:placetype":"venue"
},
  "geometry": {"coordinates":[-81.768574,32.555623],"type":"Point"}
}