{
  "type": "Feature",
  "properties": {
    "addr:full":"110 Sycamore St Jefferson GA 30549",
    "addr:housenumber":"110",
    "addr:postcode":"30549",
    "addr:street":"Sycamore St",
    "iso:country":"US",
    "sg:address":"110 Sycamore St",
    "sg:city":"Jefferson",
    "sg:classifiers":[
        {
            "category":"Autos & Motor Vehicles",
            "subcategory":"Fuel & Gas Station",
            "type":"Retail Goods"
        }
    ],
    "sg:phone":"+1 706 367 1950",
    "sg:postcode":"30549",
    "sg:province":"GA",
    "sg:tags":[
        "station",
        "store"
    ],
    "wof:name":"Amoco Food Mart",
    "wof:placetype":"venue"
},
  "geometry": {"coordinates":[-83.571231,34.118409],"type":"Point"}
}