{
  "type": "Feature",
  "properties": {
    "addr:full":"1467 Stephenson Rd Lithonia GA 30058",
    "addr:housenumber":"1467",
    "addr:postcode":"30058",
    "addr:street":"Stephenson Rd",
    "iso:country":"US",
    "sg:address":"1467 Stephenson Rd",
    "sg:city":"Lithonia",
    "sg:classifiers":[
        {
            "category":"Organizations",
            "subcategory":"Religious Organization",
            "type":"Services"
        }
    ],
    "sg:phone":"+1 770 482 6858",
    "sg:postcode":"30058",
    "sg:province":"GA",
    "wof:name":"Rock Chapel Baptist Church",
    "wof:placetype":"venue"
},
  "geometry": {"coordinates":[-84.09710800000001,33.767009],"type":"Point"}
}