{
  "type": "Feature",
  "properties": {
    "iso:country":"US",
    "sg:address":"1292 Arbor Hill Rd",
    "sg:city":"Canton",
    "sg:classifiers":[
        {
            "category":"Professional",
            "subcategory":"Art Services",
            "type":"Services"
        }
    ],
    "sg:phone":"+1 770 663 3433",
    "sg:postcode":"30115",
    "sg:province":"GA",
    "sg:tags":[
        "commercial",
        "graphic",
        "design",
        "designer"
    ],
    "wof:name":"Apryl's Antics",
    "wof:placetype":"venue"
},
  "geometry": {"coordinates":[-84.35762,34.210861],"type":"Point"}
}