{
  "type": "Feature",
  "properties": {
    "addr:full":"215 North Ave NE Apt 3208 Atlanta GA 30308",
    "addr:housenumber":"215",
    "addr:postcode":"30308",
    "addr:street":"North Ave Ne Apt 3208",
    "iso:country":"US",
    "sg:address":"215 North Ave NE Apt 3208",
    "sg:city":"Atlanta",
    "sg:classifiers":[
        {
            "category":"Building & Trades",
            "subcategory":"Landscaping Services",
            "type":"Services"
        }
    ],
    "sg:phone":"+1 404 963 2092",
    "sg:postcode":"30308",
    "sg:province":"GA",
    "sg:tags":[
        "lawn"
    ],
    "wof:name":"The B/C Network",
    "wof:placetype":"venue"
},
  "geometry": {"coordinates":[-84.380386,33.771271],"type":"Point"}
}