{
  "type": "Feature",
  "properties": {
    "addr:full":"412 S Broad St Monroe GA 30655",
    "addr:housenumber":"412",
    "addr:postcode":"30655",
    "addr:street":"S Broad St",
    "iso:country":"US",
    "sg:address":"412 S Broad St",
    "sg:city":"Monroe",
    "sg:classifiers":[
        {
            "category":"Food & Beverages",
            "subcategory":"Groceries & Convenience Stores",
            "type":"Retail Goods"
        }
    ],
    "sg:phone":"+1 770 267 5632",
    "sg:postcode":"30655",
    "sg:province":"GA",
    "sg:tags":[
        "grocer"
    ],
    "wof:name":"John's Super Market Ind",
    "wof:placetype":"venue"
},
  "geometry": {"coordinates":[-83.711877,33.789889],"type":"Point"}
}