{
  "type": "Feature",
  "properties": {
    "iso:country":"US",
    "sg:address":"4504 Terret Trce NW",
    "sg:city":"Acworth",
    "sg:classifiers":[
        {
            "category":"Professional",
            "subcategory":"Computer Services",
            "type":"Services"
        }
    ],
    "sg:phone":"+1 770 529 2114",
    "sg:postcode":"30101",
    "sg:province":"GA",
    "sg:tags":[
        "related"
    ],
    "wof:name":"It Consortium Corp",
    "wof:placetype":"venue"
},
  "geometry": {"coordinates":[-84.67934700000001,34.046443],"type":"Point"}
}