{
  "type": "Feature",
  "properties": {
    "iso:country":"US",
    "sg:address":"327 Dahlonega Rd",
    "sg:city":"Cumming",
    "sg:classifiers":[
        {
            "category":"Insurance",
            "subcategory":"Health Insurance",
            "type":"Services"
        }
    ],
    "sg:phone":"+1 770 844 9303",
    "sg:postcode":"30040",
    "sg:province":"GA",
    "sg:tags":[
        "carrier",
        "plan"
    ],
    "wof:name":"Shawhankins",
    "wof:placetype":"venue"
},
  "geometry": {"coordinates":[-84.135243,34.216043],"type":"Point"}
}