{
  "type": "Feature",
  "properties": {
    "iso:country":"US",
    "sg:address":"110 Ann St",
    "sg:city":"Savannah",
    "sg:classifiers":[
        {
            "category":"Wholesale",
            "subcategory":"Hardware",
            "type":"Manufacturing & Wholesale Goods"
        }
    ],
    "sg:phone":"+1 912 238 4822",
    "sg:postcode":"31401",
    "sg:province":"GA",
    "sg:tags":[
        "air",
        "parts",
        "conditioning",
        "supply"
    ],
    "wof:name":"Johnstone Supply",
    "wof:placetype":"venue"
},
  "geometry": {"coordinates":[-81.098752,32.079691],"type":"Point"}
}