{
  "type": "Feature",
  "properties": {
    "iso:country":"US",
    "sg:address":"1906 Skylane Dr",
    "sg:city":"Albany",
    "sg:classifiers":[
        {
            "category":"Social Services",
            "subcategory":"Child Care",
            "type":"Services"
        }
    ],
    "sg:phone":"+1 229 903 1641",
    "sg:postcode":"31705",
    "sg:province":"GA",
    "sg:tags":[
        "day"
    ],
    "wof:name":"Better Learning Institution",
    "wof:placetype":"venue"
},
  "geometry": {"coordinates":[-84.10921399999999,31.602919],"type":"Point"}
}