{
  "type": "Feature",
  "properties": {
    "addr:full":"1267 Wommack Brantley Rd Tennille GA 31089",
    "addr:housenumber":"1267",
    "addr:postcode":"31089",
    "addr:street":"Wommack Brantley Rd",
    "iso:country":"US",
    "sg:address":"1267 Wommack Brantley Rd",
    "sg:city":"Tennille",
    "sg:classifiers":[
        {
            "category":"Farming",
            "subcategory":"Livestock Farm",
            "type":"Manufacturing & Wholesale Goods"
        }
    ],
    "sg:phone":"+1 478 552 1715",
    "sg:postcode":"31089",
    "sg:province":"GA",
    "sg:tags":[
        "beef",
        "feedlot",
        "cattle"
    ],
    "wof:name":"Davis Farms",
    "wof:placetype":"venue"
},
  "geometry": {"coordinates":[-82.798117,32.864874],"type":"Point"}
}