{
  "type": "Feature",
  "properties": {
    "addr:full":"158 Lamar Rd Macon GA 31220",
    "addr:housenumber":"158",
    "addr:postcode":"31220",
    "addr:street":"Lamar Rd",
    "iso:country":"US",
    "sg:address":"158 Lamar Rd",
    "sg:city":"Macon",
    "sg:classifiers":[
        {
            "category":"Organizations",
            "subcategory":"Religious Organization",
            "type":"Services"
        }
    ],
    "sg:phone":"+1 478 757 2240",
    "sg:postcode":"31220",
    "sg:province":"GA",
    "sg:tags":[
        "church"
    ],
    "wof:name":"New Heights Baptist Church",
    "wof:placetype":"venue"
},
  "geometry": {"coordinates":[-83.784316,32.861785],"type":"Point"}
}