{
  "type": "Feature",
  "properties": {
    "iso:country":"US",
    "sg:address":"201 S Railroad St",
    "sg:city":"Lenox",
    "sg:classifiers":[
        {
            "category":"Food & Beverages",
            "subcategory":"Groceries & Convenience Stores",
            "type":"Retail Goods"
        }
    ],
    "sg:phone":"+1 229 546 4905",
    "sg:postcode":"31637",
    "sg:province":"GA",
    "sg:tags":[
        "grocer"
    ],
    "wof:name":"Lenox Grocery",
    "wof:placetype":"venue"
},
  "geometry": {"coordinates":[-83.463742,31.27101],"type":"Point"}
}