{
  "type": "Feature",
  "properties": {
    "iso:country":"US",
    "sg:address":"1970 6th St",
    "sg:city":"Atlanta",
    "sg:classifiers":[
        {
            "category":"Food & Beverages",
            "subcategory":"Bakery",
            "type":"Retail Goods"
        }
    ],
    "sg:phone":"+1 770 455 9119",
    "sg:postcode":"30341",
    "sg:province":"GA",
    "sg:tags":[
        "baker"
    ],
    "wof:name":"Los Andes Bakery",
    "wof:placetype":"venue"
},
  "geometry": {"coordinates":[-84.308167,33.879114],"type":"Point"}
}