{
  "type": "Feature",
  "properties": {
    "iso:country":"US",
    "sg:address":"540 N Belair Rd",
    "sg:city":"Evans",
    "sg:classifiers":[
        {
            "category":"Restaurant",
            "type":"Food & Drink"
        }
    ],
    "sg:phone":"+1 706 650 2460",
    "sg:postcode":"30809",
    "sg:province":"GA",
    "sg:tags":[
        "style",
        "family"
    ],
    "wof:name":"Southern Restaurant Hospitalit",
    "wof:placetype":"venue"
},
  "geometry": {"coordinates":[-82.129141,33.535842],"type":"Point"}
}