{
  "type": "Feature",
  "properties": {
    "addr:full":"1110 39th St Columbus GA 31904",
    "addr:housenumber":"1110",
    "addr:postcode":"31904",
    "addr:street":"39Th St",
    "iso:country":"US",
    "sg:address":"1110 39th St",
    "sg:city":"Columbus",
    "sg:classifiers":[
        {
            "category":"Autos & Motor Vehicles",
            "subcategory":"Auto Supplies",
            "type":"Retail Goods"
        }
    ],
    "sg:phone":"+1 706 653 1525",
    "sg:postcode":"31904",
    "sg:province":"GA",
    "wof:name":"National Tire & Auto",
    "wof:placetype":"venue"
},
  "geometry": {"coordinates":[-84.97765800000001,32.500077],"type":"Point"}
}