{
  "type": "Feature",
  "properties": {
    "iso:country":"US",
    "sg:address":"5153 Whitehouse Pkwy",
    "sg:city":"Warm Springs",
    "sg:classifiers":[
        {
            "category":"Travel",
            "subcategory":"Campground",
            "type":"Entertainment"
        }
    ],
    "sg:phone":"+1 706 655 2480",
    "sg:postcode":"31830",
    "sg:province":"GA",
    "wof:name":"Ramsey Mobile Home & Rv Park",
    "wof:placetype":"venue"
},
  "geometry": {"coordinates":[-84.657839,32.92129],"type":"Point"}
}