{
  "type": "Feature",
  "properties": {
    "addr:full":"5245 Mike Padgett Hwy Hephzibah GA 30815",
    "addr:housenumber":"5245",
    "addr:postcode":"30815",
    "addr:street":"Mike Padgett Hwy",
    "iso:country":"US",
    "sg:address":"5245 Mike Padgett Hwy",
    "sg:city":"Hephzibah",
    "sg:classifiers":[
        {
            "category":"Health Services",
            "subcategory":"Nursing And Care Facility",
            "type":"Services"
        }
    ],
    "sg:phone":"+1 706 796 7390",
    "sg:postcode":"30815",
    "sg:province":"GA",
    "sg:tags":[
        "intermediate"
    ],
    "wof:name":"Lakeview Personal Care Home",
    "wof:placetype":"venue"
},
  "geometry": {"coordinates":[-81.95110200000001,33.243338],"type":"Point"}
}