{
  "type": "Feature",
  "properties": {
    "addr:full":"2560 Tommy Dillard Rd Monroe GA 30656",
    "addr:housenumber":"2560",
    "addr:postcode":"30656",
    "addr:street":"Tommy Dillard Rd",
    "iso:country":"US",
    "sg:address":"2560 Tommy Dillard Rd",
    "sg:city":"Monroe",
    "sg:classifiers":[
        {
            "category":"Wholesale",
            "subcategory":"Groceries",
            "type":"Manufacturing & Wholesale Goods"
        }
    ],
    "sg:phone":"+1 770 267 5253",
    "sg:postcode":"30656",
    "sg:province":"GA",
    "wof:name":"Log Cabin Consession",
    "wof:placetype":"venue"
},
  "geometry": {"coordinates":[-83.648505,33.841603],"type":"Point"}
}