{
  "type": "Feature",
  "properties": {
    "addr:full":"204 E 4th St Springfield Rincon GA 31326",
    "addr:housenumber":"204",
    "addr:postcode":"31326",
    "addr:street":"E 4Th St",
    "iso:country":"US",
    "sg:address":"204 E 4th St Springfield",
    "sg:city":"Rincon",
    "sg:classifiers":[
        {
            "category":"Building & Trades",
            "subcategory":"Construction",
            "type":"Services"
        }
    ],
    "sg:phone":"+1 912 826 6380",
    "sg:postcode":"31326",
    "sg:province":"GA",
    "sg:tags":[
        "system",
        "specialty",
        "heating",
        "contractor",
        "air conditioning"
    ],
    "sg:website":"http://www.gordonsheatingandair.com",
    "wof:name":"Gordons Heating & Air",
    "wof:placetype":"venue"
},
  "geometry": {"coordinates":[-81.235298,32.296261],"type":"Point"}
}