{
  "type": "Feature",
  "properties": {
    "iso:country":"US",
    "sg:address":"650 Great Southwest Pkwy SW",
    "sg:city":"Atlanta",
    "sg:classifiers":[
        {
            "category":"Wholesale",
            "subcategory":"Chemicals & Plastics",
            "type":"Manufacturing & Wholesale Goods"
        }
    ],
    "sg:phone":"+1 404 768 9999",
    "sg:postcode":"30336",
    "sg:province":"GA",
    "sg:tags":[
        "product",
        "allied"
    ],
    "wof:name":"Azalea Color Company",
    "wof:placetype":"venue"
},
  "geometry": {"coordinates":[-84.56967899999999,33.74096],"type":"Point"}
}