{
  "type": "Feature",
  "properties": {
    "addr:full":"315 S Lumpkin St Monroe GA 30655",
    "addr:housenumber":"315",
    "addr:postcode":"30655",
    "addr:street":"S Lumpkin St",
    "iso:country":"US",
    "sg:address":"315 S Lumpkin St",
    "sg:city":"Monroe",
    "sg:classifiers":[
        {
            "category":"Freight",
            "type":"Transportation"
        }
    ],
    "sg:phone":"+1 770 267 2964",
    "sg:postcode":"30655",
    "sg:province":"GA",
    "sg:tags":[
        "warehouse",
        "merchandise"
    ],
    "wof:name":"Walton Bonded Warehouse",
    "wof:placetype":"venue"
},
  "geometry": {"coordinates":[-83.711724,33.791056],"type":"Point"}
}