{
  "type": "Feature",
  "properties": {
    "iso:country":"US",
    "sg:address":"4 Mullberry Ct",
    "sg:city":"Savannah",
    "sg:classifiers":[
        {
            "category":"Banks & Credit Unions",
            "subcategory":"Bank",
            "type":"Services"
        }
    ],
    "sg:phone":"+1 912 234 8007",
    "sg:postcode":"31406",
    "sg:province":"GA",
    "sg:tags":[
        "personal",
        "institution"
    ],
    "wof:name":"Harbour Mortgage Corp",
    "wof:placetype":"venue"
},
  "geometry": {"coordinates":[-81.063897,31.996793],"type":"Point"}
}