{
  "type": "Feature",
  "properties": {
    "iso:country":"US",
    "sg:address":"2101 Womack Road",
    "sg:city":"Atlanta",
    "sg:classifiers":[
        {
            "category":"Education",
            "subcategory":"University",
            "type":"Public Place"
        }
    ],
    "sg:phone":"+1 770 274 5000",
    "sg:postcode":"30338",
    "sg:province":"GA",
    "sg:tags":[
        "college"
    ],
    "wof:name":"Georgia Perimeter College",
    "wof:placetype":"venue"
},
  "geometry": {"coordinates":[-84.301436,33.943622],"type":"Point"}
}