{
  "type": "Feature",
  "properties": {
    "iso:country":"US",
    "sg:address":"239 Mossy Oaks Dr",
    "sg:city":"Sylvester",
    "sg:classifiers":[
        {
            "category":"Retail",
            "subcategory":"Repair Shop",
            "type":"Services"
        }
    ],
    "sg:phone":"+1 229 776 0517",
    "sg:postcode":"31791",
    "sg:province":"GA",
    "sg:tags":[
        "welding"
    ],
    "wof:name":"United Welding & Millwrite Svc",
    "wof:placetype":"venue"
},
  "geometry": {"coordinates":[-83.96992,31.56975],"type":"Point"}
}