{
  "type": "Feature",
  "properties": {
    "addr:full":"89 Clinic Rd Tate GA 30177",
    "addr:housenumber":"89",
    "addr:postcode":"30177",
    "addr:street":"Clinic Rd",
    "iso:country":"US",
    "sg:address":"89 Clinic Rd",
    "sg:city":"Tate",
    "sg:classifiers":[
        {
            "category":"Health Services",
            "subcategory":"Doctor",
            "type":"Services"
        }
    ],
    "sg:phone":"+1 706 735 3333",
    "sg:postcode":"30177",
    "sg:province":"GA",
    "sg:tags":[
        "medical"
    ],
    "wof:name":"Joanne O Eustace MD",
    "wof:placetype":"venue"
},
  "geometry": {"coordinates":[-84.388164,34.416669],"type":"Point"}
}