{
  "type": "Feature",
  "properties": {
    "addr:full":"1055 Peachtree St NE Atlanta GA 30309",
    "addr:housenumber":"1055",
    "addr:postcode":"30309",
    "addr:street":"Peachtree St Ne",
    "iso:country":"US",
    "sg:address":"1055 Peachtree St NE",
    "sg:city":"Atlanta",
    "sg:classifiers":[
        {
            "category":"Professional",
            "subcategory":"Management & Consulting",
            "type":"Services"
        }
    ],
    "sg:phone":"+1 404 607 8050",
    "sg:postcode":"30309",
    "sg:province":"GA",
    "sg:tags":[
        "food",
        "beverage",
        "facility",
        "consultant"
    ],
    "wof:name":"Galardi South Enterprises Consulting, Inc.",
    "wof:placetype":"venue"
},
  "geometry": {"coordinates":[-84.383742,33.783414],"type":"Point"}
}