{
  "type": "Feature",
  "properties": {
    "addr:full":"4642 Peeler Mill Ct Atlanta GA 30338",
    "addr:housenumber":"4642",
    "addr:postcode":"30338",
    "addr:street":"Peeler Mill Ct",
    "iso:country":"US",
    "sg:address":"4642 Peeler Mill Ct",
    "sg:city":"Atlanta",
    "sg:classifiers":[
        {
            "category":"Organizations",
            "subcategory":"Religious Organization",
            "type":"Services"
        }
    ],
    "sg:phone":"+1 770 394 8697",
    "sg:postcode":"30338",
    "sg:province":"GA",
    "wof:name":"Trinity Resource Group",
    "wof:placetype":"venue"
},
  "geometry": {"coordinates":[-84.311522,33.932774],"type":"Point"}
}