{
  "type": "Feature",
  "properties": {
    "iso:country":"US",
    "sg:address":"4806 Piney Grove Rd",
    "sg:city":"Cumming",
    "sg:classifiers":[
        {
            "category":"Professional",
            "subcategory":"Management & Consulting",
            "type":"Services"
        }
    ],
    "sg:phone":"+1 770 888 1417",
    "sg:postcode":"30040",
    "sg:province":"GA",
    "sg:tags":[
        "party",
        "planning"
    ],
    "wof:name":"Sensational Celebrations",
    "wof:placetype":"venue"
},
  "geometry": {"coordinates":[-84.168835,34.178058],"type":"Point"}
}