{
  "type": "Feature",
  "properties": {
    "addr:full":"527 N Glenwood Ave Dalton GA 30721",
    "addr:housenumber":"527",
    "addr:postcode":"30721",
    "addr:street":"N Glenwood Ave",
    "iso:country":"US",
    "sg:address":"527 N Glenwood Ave",
    "sg:city":"Dalton",
    "sg:classifiers":[
        {
            "category":"Autos & Motor Vehicles",
            "subcategory":"Automobile Sales",
            "type":"Retail Goods"
        }
    ],
    "sg:phone":"+1 706 278 8854",
    "sg:postcode":"30721",
    "sg:province":"GA",
    "sg:tags":[
        "used"
    ],
    "wof:name":"City Motors",
    "wof:placetype":"venue"
},
  "geometry": {"coordinates":[-84.963843,34.781708],"type":"Point"}
}