{
  "type": "Feature",
  "properties": {
    "iso:country":"US",
    "sg:address":"206 Cambridge Trce",
    "sg:city":"Canton",
    "sg:classifiers":[
        {
            "category":"Wholesale",
            "subcategory":"Painting Supplies",
            "type":"Manufacturing & Wholesale Goods"
        }
    ],
    "sg:phone":"+1 770 408 8954",
    "sg:postcode":"30115",
    "sg:province":"GA",
    "sg:tags":[
        "goods-wholesale",
        "art",
        "manufacturer"
    ],
    "wof:name":"Reflective Portraits",
    "wof:placetype":"venue"
},
  "geometry": {"coordinates":[-84.334626,34.252647],"type":"Point"}
}