{
  "type": "Feature",
  "properties": {
    "addr:full":"2610 Cherokee Ave Columbus GA 31906",
    "addr:housenumber":"2610",
    "addr:postcode":"31906",
    "addr:street":"Cherokee Ave",
    "iso:country":"US",
    "sg:address":"2610 Cherokee Ave",
    "sg:city":"Columbus",
    "sg:classifiers":[
        {
            "category":"Organizations",
            "subcategory":"Community Association",
            "type":"Services"
        }
    ],
    "sg:phone":"+1 706 322 4441",
    "sg:postcode":"31906",
    "sg:province":"GA",
    "sg:tags":[
        "club"
    ],
    "sg:website":"www.ccofcolumbus.com",
    "wof:name":"Club House",
    "wof:placetype":"venue"
},
  "geometry": {"coordinates":[-84.96391,32.48857],"type":"Point"}
}