{
  "type": "Feature",
  "properties": {
    "addr:full":"88 Benham Cir Cartersville GA 30120",
    "addr:housenumber":"88",
    "addr:postcode":"30120",
    "addr:street":"Benham Cir",
    "iso:country":"US",
    "sg:address":"88 Benham Cir",
    "sg:city":"Cartersville",
    "sg:classifiers":[
        {
            "category":"Professional",
            "subcategory":"Lawyer & Legal Services",
            "type":"Services"
        }
    ],
    "sg:phone":"+1 770 387 0033",
    "sg:postcode":"30120",
    "sg:province":"GA",
    "wof:name":"Brads and Bond",
    "wof:placetype":"venue"
},
  "geometry": {"coordinates":[-84.81960100000001,34.197451],"type":"Point"}
}