{
  "type": "Feature",
  "properties": {
    "addr:full":"979 Iris Dr SE Conyers GA 30094",
    "addr:housenumber":"979",
    "addr:postcode":"30094",
    "addr:street":"Iris Dr Se",
    "iso:country":"US",
    "sg:address":"979 Iris Dr SE",
    "sg:city":"Conyers",
    "sg:classifiers":[
        {
            "category":"Autos & Motor Vehicles",
            "subcategory":"Automobile Sales",
            "type":"Retail Goods"
        },
        {
            "category":"Retail",
            "subcategory":"Auto Repair",
            "type":"Services"
        }
    ],
    "sg:phone":"+1 678 750 1333",
    "sg:postcode":"30094",
    "sg:province":"GA",
    "sg:tags":[
        "repairing",
        "used",
        "supply",
        "automotive",
        "car",
        "new",
        "tune",
        "service-equipment"
    ],
    "sg:website":"http://www.kiaofconyers.com",
    "wof:name":"Kia of Conyers",
    "wof:placetype":"venue"
},
  "geometry": {"coordinates":[-84.01123800000001,33.655002],"type":"Point"}
}