{
  "type": "Feature",
  "properties": {
    "iso:country":"US",
    "sg:address":"911 N Tennessee St",
    "sg:city":"Cartersville",
    "sg:classifiers":[
        {
            "category":"Insurance",
            "subcategory":"Insurance Agent",
            "type":"Services"
        }
    ],
    "sg:phone":"+1 770 386 6366",
    "sg:postcode":"30120",
    "sg:province":"GA",
    "wof:name":"Cotton States Insurance",
    "wof:placetype":"venue"
},
  "geometry": {"coordinates":[-84.79479600000001,34.184316],"type":"Point"}
}