{
  "type": "Feature",
  "properties": {
    "iso:country":"US",
    "sg:address":"910 Jamerson Rd",
    "sg:city":"Marietta",
    "sg:classifiers":[
        {
            "category":"Building & Trades",
            "subcategory":"Construction",
            "type":"Services"
        }
    ],
    "sg:phone":"+1 678 494 6872",
    "sg:postcode":"30066",
    "sg:province":"GA",
    "sg:tags":[
        "contractor"
    ],
    "wof:name":"Advanced Solid Surfaces",
    "wof:placetype":"venue"
},
  "geometry": {"coordinates":[-84.523383,34.069038],"type":"Point"}
}