{
  "type": "Feature",
  "properties": {
    "iso:country":"US",
    "sg:address":"241 Mulberry Dr",
    "sg:city":"Richmond Hill",
    "sg:classifiers":[
        {
            "category":"Retail",
            "subcategory":"Auto Repair",
            "type":"Services"
        }
    ],
    "sg:phone":"+1 912 459 3499",
    "sg:postcode":"31324",
    "sg:province":"GA",
    "sg:tags":[
        "repairing",
        "automobile"
    ],
    "wof:name":"Richmond Hill Auto Care Inc",
    "wof:placetype":"venue"
},
  "geometry": {"coordinates":[-81.308539,31.947811],"type":"Point"}
}