{
  "type": "Feature",
  "properties": {
    "addr:full":"3775 Sixes Rd Canton GA 30114",
    "addr:housenumber":"3775",
    "addr:postcode":"30114",
    "addr:street":"Sixes Rd",
    "iso:country":"US",
    "sg:address":"3775 Sixes Rd",
    "sg:city":"Canton",
    "sg:classifiers":[
        {
            "category":"Restaurant",
            "type":"Food & Drink"
        }
    ],
    "sg:menulink":"http://www.allmenus.com/ga/holly-springs/132308-subway/menu/",
    "sg:phone":"+1 678 493 3881",
    "sg:postcode":"30114",
    "sg:province":"GA",
    "sg:tags":[
        "american",
        "sandwich"
    ],
    "wof:name":"Subway",
    "wof:placetype":"venue"
},
  "geometry": {"coordinates":[-84.51799,34.147443],"type":"Point"}
}