{
  "type": "Feature",
  "properties": {
    "iso:country":"US",
    "sg:address":"12 W State St",
    "sg:city":"Savannah",
    "sg:classifiers":[
        {
            "category":"Freight",
            "type":"Transportation"
        }
    ],
    "sg:phone":"+1 912 233 8288",
    "sg:postcode":"31401",
    "sg:province":"GA",
    "sg:tags":[
        "domestic",
        "deep",
        "sea",
        "foreign"
    ],
    "wof:name":"Troika International Ltd Inc",
    "wof:placetype":"venue"
},
  "geometry": {"coordinates":[-81.092499,32.078405],"type":"Point"}
}