{
  "type": "Feature",
  "properties": {
    "addr:full":"103 Cooley Industrial Way Lagrange GA 30241",
    "addr:housenumber":"103",
    "addr:postcode":"30241",
    "addr:street":"Cooley Industrial Way",
    "iso:country":"US",
    "sg:address":"103 Cooley Industrial Way",
    "sg:city":"Lagrange",
    "sg:classifiers":[
        {
            "category":"Manufacturing",
            "subcategory":"Metals",
            "type":"Manufacturing & Wholesale Goods"
        }
    ],
    "sg:phone":"+1 706 882 4277",
    "sg:postcode":"30241",
    "sg:province":"GA",
    "sg:tags":[
        "fabricator",
        "sheet"
    ],
    "sg:website":"www.piedmontmechanical.com",
    "wof:name":"Piedmont Mechanical Inc",
    "wof:placetype":"venue"
},
  "geometry": {"coordinates":[-85.00315999999999,33.015946],"type":"Point"}
}