{
  "type": "Feature",
  "properties": {
    "addr:full":"2061 Lullwater Pl Lawrenceville GA 30043",
    "addr:housenumber":"2061",
    "addr:postcode":"30043",
    "addr:street":"Lullwater Pl",
    "iso:country":"US",
    "sg:address":"2061 Lullwater Pl",
    "sg:city":"Lawrenceville",
    "sg:classifiers":[
        {
            "category":"Real Estate",
            "subcategory":"Real Estate Operator",
            "type":"Services"
        }
    ],
    "sg:phone":"+1 404 728 9700",
    "sg:postcode":"30043",
    "sg:province":"GA",
    "sg:tags":[
        "apartment"
    ],
    "wof:name":"T P Corporate Lodging",
    "wof:placetype":"venue"
},
  "geometry": {"coordinates":[-84.068309,33.987857],"type":"Point"}
}