{
  "type": "Feature",
  "properties": {
    "iso:country":"US",
    "sg:address":"2665 Oak Log Way NE",
    "sg:city":"Buford",
    "sg:classifiers":[
        {
            "category":"Wholesale",
            "subcategory":"Machinery & Supplies",
            "type":"Manufacturing & Wholesale Goods"
        }
    ],
    "sg:phone":"+1 770 822 9098",
    "sg:postcode":"30519",
    "sg:province":"GA",
    "sg:tags":[
        "industrial"
    ],
    "wof:name":"Big Rock Refractories Inc",
    "wof:placetype":"venue"
},
  "geometry": {"coordinates":[-83.980724,34.052734],"type":"Point"}
}