{
  "type": "Feature",
  "properties": {
    "iso:country":"US",
    "sg:address":"3045 Commerce Way SE",
    "sg:city":"Atlanta",
    "sg:classifiers":[
        {
            "category":"Manufacturing",
            "subcategory":"Chemicals & Compounds",
            "type":"Manufacturing & Wholesale Goods"
        }
    ],
    "sg:phone":"+1 404 766 3992",
    "sg:postcode":"30354",
    "sg:province":"GA",
    "sg:tags":[
        "mfg"
    ],
    "wof:name":"Johnson Diversey Inc",
    "wof:placetype":"venue"
},
  "geometry": {"coordinates":[-84.399322,33.671088],"type":"Point"}
}