{
  "type": "Feature",
  "properties": {
    "addr:full":"350 Debord Dr Waleska GA 30183",
    "addr:housenumber":"350",
    "addr:postcode":"30183",
    "addr:street":"Debord Dr",
    "iso:country":"US",
    "sg:address":"350 Debord Dr",
    "sg:city":"Waleska",
    "sg:classifiers":[
        {
            "category":"Building & Trades",
            "subcategory":"Construction",
            "type":"Services"
        }
    ],
    "sg:phone":"+1 770 345 5901",
    "sg:postcode":"30183",
    "sg:province":"GA",
    "sg:tags":[
        "general",
        "contractor"
    ],
    "wof:name":"Rhodes Construction",
    "wof:placetype":"venue"
},
  "geometry": {"coordinates":[-84.58010299999999,34.352927],"type":"Point"}
}