{
  "type": "Feature",
  "properties": {
    "iso:country":"US",
    "sg:address":"2020 Ridge Gate Dr",
    "sg:city":"Cumming",
    "sg:classifiers":[
        {
            "category":"Professional",
            "subcategory":"Business Services",
            "type":"Services"
        }
    ],
    "sg:phone":"+1 678 947 8220",
    "sg:postcode":"30041",
    "sg:province":"GA",
    "sg:tags":[
        "insurance"
    ],
    "wof:name":"Sargent Financial Services",
    "wof:placetype":"venue"
},
  "geometry": {"coordinates":[-84.11442099999999,34.172078],"type":"Point"}
}