{
  "type": "Feature",
  "properties": {
    "iso:country":"US",
    "sg:address":"357 2nd Ave SE",
    "sg:city":"Cairo",
    "sg:classifiers":[
        {
            "category":"Retail",
            "subcategory":"Auto Repair",
            "type":"Services"
        }
    ],
    "sg:phone":"+1 229 377 9203",
    "sg:postcode":"39828",
    "sg:province":"GA",
    "sg:tags":[
        "general"
    ],
    "wof:name":"Southside Auto",
    "wof:placetype":"venue"
},
  "geometry": {"coordinates":[-84.204643,30.875389],"type":"Point"}
}