{
  "type": "Feature",
  "properties": {
    "iso:country":"US",
    "sg:address":"1210 Highway 138 SW",
    "sg:city":"Riverdale",
    "sg:classifiers":[
        {
            "category":"Retail",
            "subcategory":"Laundry & Dry Cleaning",
            "type":"Services"
        }
    ],
    "sg:phone":"+1 770 997 1500",
    "sg:postcode":"30296",
    "sg:province":"GA",
    "wof:name":"Esquire Cleaners",
    "wof:placetype":"venue"
},
  "geometry": {"coordinates":[-84.42898599999999,33.550357],"type":"Point"}
}