{
  "type": "Feature",
  "properties": {
    "addr:full":"4290 Linda Dr Douglasville GA 30134",
    "addr:housenumber":"4290",
    "addr:postcode":"30134",
    "addr:street":"Linda Dr",
    "iso:country":"US",
    "sg:address":"4290 Linda Dr",
    "sg:city":"Douglasville",
    "sg:classifiers":[
        {
            "category":"Building & Trades",
            "subcategory":"Cleaning & Sanitation",
            "type":"Services"
        }
    ],
    "sg:phone":"+1 770 949 6625",
    "sg:postcode":"30134",
    "sg:province":"GA",
    "sg:tags":[
        "maintenance"
    ],
    "wof:name":"Ruths Cleaning Svc",
    "wof:placetype":"venue"
},
  "geometry": {"coordinates":[-84.71419899999999,33.760289],"type":"Point"}
}