{
  "type": "Feature",
  "properties": {
    "iso:country":"US",
    "sg:address":"6857 Glen Cove Ln",
    "sg:city":"Stone Mountain",
    "sg:classifiers":[
        {
            "category":"Real Estate",
            "subcategory":"Real Estate Agent",
            "type":"Services"
        }
    ],
    "sg:phone":"+1 770 465 1112",
    "sg:postcode":"30087",
    "sg:province":"GA",
    "sg:website":"www.exchangeinc.net",
    "wof:name":"Real Estate Exchange",
    "wof:placetype":"venue"
},
  "geometry": {"coordinates":[-84.09778,33.787945],"type":"Point"}
}