{
  "type": "Feature",
  "properties": {
    "iso:country":"US",
    "sg:address":"3320 Lawrencevlle Swne Rd",
    "sg:city":"Suwanee",
    "sg:classifiers":[
        {
            "category":"Restaurant",
            "type":"Food & Drink"
        }
    ],
    "sg:phone":"+1 678 541 0350",
    "sg:postcode":"30024",
    "sg:province":"GA",
    "wof:name":"Moe's Southeast Grill",
    "wof:placetype":"venue"
},
  "geometry": {"coordinates":[-84.053802,34.041599],"type":"Point"}
}