{
  "type": "Feature",
  "properties": {
    "iso:country":"US",
    "sg:address":"200 W Oglethorpe Blvd",
    "sg:city":"Albany",
    "sg:classifiers":[
        {
            "category":"Government",
            "subcategory":"Office",
            "type":"Public Place"
        }
    ],
    "sg:phone":"+1 229 430 2721",
    "sg:postcode":"31701",
    "sg:province":"GA",
    "wof:name":"Albany Assertive Community",
    "wof:placetype":"venue"
},
  "geometry": {"coordinates":[-84.15366400000001,31.575291],"type":"Point"}
}