{
  "type": "Feature",
  "properties": {
    "iso:country":"US",
    "sg:address":"705 Sunset Dr",
    "sg:city":"Athens",
    "sg:classifiers":[
        {
            "category":"Professional",
            "type":"Services"
        }
    ],
    "sg:phone":"+1 706 613 8334",
    "sg:postcode":"30606",
    "sg:province":"GA",
    "sg:tags":[
        "establishment"
    ],
    "wof:name":"Tennis For Life",
    "wof:placetype":"venue"
},
  "geometry": {"coordinates":[-83.410539,33.962412],"type":"Point"}
}