{
  "type": "Feature",
  "properties": {
    "iso:country":"US",
    "sg:address":"13846 Panhandle Ln",
    "sg:city":"Hampton",
    "sg:classifiers":[
        {
            "category":"Retail",
            "subcategory":"Auto Repair",
            "type":"Services"
        }
    ],
    "sg:phone":"+1 678 545 1334",
    "sg:postcode":"30228",
    "sg:province":"GA",
    "sg:tags":[
        "body",
        "automobile",
        "painting",
        "repairing"
    ],
    "wof:name":"After Effects Inc",
    "wof:placetype":"venue"
},
  "geometry": {"coordinates":[-84.3776,33.376162],"type":"Point"}
}