{
  "type": "Feature",
  "properties": {
    "addr:full":"3201 W Roxboro Rd NE Atlanta GA 30324",
    "addr:housenumber":"3201",
    "addr:postcode":"30324",
    "addr:street":"W Roxboro Rd Ne",
    "iso:country":"US",
    "sg:address":"3201 W Roxboro Rd NE",
    "sg:city":"Atlanta",
    "sg:classifiers":[
        {
            "category":"Professional",
            "subcategory":"Management & Consulting",
            "type":"Services"
        }
    ],
    "sg:phone":"+1 404 233 6045",
    "sg:postcode":"30324",
    "sg:province":"GA",
    "sg:tags":[
        "farm"
    ],
    "wof:name":"William Laney",
    "wof:placetype":"venue"
},
  "geometry": {"coordinates":[-84.350441,33.841742],"type":"Point"}
}