{
  "type": "Feature",
  "properties": {
    "addr:full":"4266 Holland Dr Gainesville GA 30504",
    "addr:housenumber":"4266",
    "addr:postcode":"30504",
    "addr:street":"Holland Dr",
    "iso:country":"US",
    "sg:address":"4266 Holland Dr",
    "sg:city":"Gainesville",
    "sg:classifiers":[
        {
            "category":"Building & Trades",
            "subcategory":"Construction",
            "type":"Services"
        }
    ],
    "sg:phone":"+1 770 536 2890",
    "sg:postcode":"30504",
    "sg:province":"GA",
    "sg:tags":[
        "carpentry",
        "contractor"
    ],
    "wof:name":"S Mueller Custom Cabinets",
    "wof:placetype":"venue"
},
  "geometry": {"coordinates":[-83.914033,34.27131],"type":"Point"}
}