{
  "type": "Feature",
  "properties": {
    "iso:country":"US",
    "sg:address":"3604 Macon Rd",
    "sg:city":"Columbus",
    "sg:classifiers":[
        {
            "category":"Organizations",
            "subcategory":"Religious Organization",
            "type":"Services"
        }
    ],
    "sg:phone":"+1 706 507 4914",
    "sg:postcode":"31907",
    "sg:province":"GA",
    "sg:tags":[
        "church"
    ],
    "wof:name":"New Life Assembly",
    "wof:placetype":"venue"
},
  "geometry": {"coordinates":[-84.932219,32.488409],"type":"Point"}
}