{
  "type": "Feature",
  "properties": {
    "addr:full":"1563 Calvary Church Rd Gainesville GA 30507",
    "addr:housenumber":"1563",
    "addr:postcode":"30507",
    "addr:street":"Calvary Church Rd",
    "iso:country":"US",
    "sg:address":"1563 Calvary Church Rd",
    "sg:city":"Gainesville",
    "sg:classifiers":[
        {
            "category":"Manufacturing",
            "subcategory":"Printing",
            "type":"Manufacturing & Wholesale Goods"
        }
    ],
    "sg:phone":"+1 770 531 9911",
    "sg:postcode":"30507",
    "sg:province":"GA",
    "sg:tags":[
        "commercial"
    ],
    "wof:name":"Incentive Associates Inc",
    "wof:placetype":"venue"
},
  "geometry": {"coordinates":[-83.81579000000001,34.252134],"type":"Point"}
}