{
  "type": "Feature",
  "properties": {
    "addr:full":"75 Lester Rd SW Lawrenceville GA 30044",
    "addr:housenumber":"75",
    "addr:postcode":"30044",
    "addr:street":"Lester Rd Sw",
    "iso:country":"US",
    "sg:address":"75 Lester Rd SW",
    "sg:city":"Lawrenceville",
    "sg:classifiers":[
        {
            "category":"Professional",
            "type":"Services"
        }
    ],
    "sg:phone":"+1 770 638 8273",
    "sg:postcode":"30044",
    "sg:province":"GA",
    "sg:tags":[
        "establishment"
    ],
    "wof:name":"S & A Partners Ship",
    "wof:placetype":"venue"
},
  "geometry": {"coordinates":[-84.101187,33.898006],"type":"Point"}
}