{
  "type": "Feature",
  "properties": {
    "iso:country":"US",
    "sg:address":"1573 Virgil Pond Ln",
    "sg:city":"Loganville",
    "sg:classifiers":[
        {
            "category":"Health Services",
            "subcategory":"Chiropractor",
            "type":"Services"
        }
    ],
    "sg:phone":"+1 770 978 0897",
    "sg:postcode":"30052",
    "sg:province":"GA",
    "sg:tags":[
        "chiropractic"
    ],
    "wof:name":"Dc Trans",
    "wof:placetype":"venue"
},
  "geometry": {"coordinates":[-83.95127599999999,33.821937],"type":"Point"}
}