{
  "type": "Feature",
  "properties": {
    "addr:full":"5302 Heather Ln Atlanta GA 30349",
    "addr:housenumber":"5302",
    "addr:postcode":"30349",
    "addr:street":"Heather Ln",
    "iso:country":"US",
    "sg:address":"5302 Heather Ln",
    "sg:city":"Atlanta",
    "sg:classifiers":[
        {
            "category":"Professional",
            "type":"Services"
        }
    ],
    "sg:phone":"+1 770 909 3421",
    "sg:postcode":"30349",
    "sg:province":"GA",
    "wof:name":"Lionel Gomes",
    "wof:placetype":"venue"
},
  "geometry": {"coordinates":[-84.434923,33.60922],"type":"Point"}
}