{
  "type": "Feature",
  "properties": {
    "iso:country":"US",
    "sg:address":"311 New Airport Rd",
    "sg:city":"Lagrange",
    "sg:classifiers":[
        {
            "category":"Professional",
            "subcategory":"Advertising",
            "type":"Services"
        }
    ],
    "sg:phone":"+1 706 884 3400",
    "sg:postcode":"30240",
    "sg:province":"GA",
    "sg:website":"www.tharpeandjones.com",
    "wof:name":"Tharpe & Jones Inc",
    "wof:placetype":"venue"
},
  "geometry": {"coordinates":[-85.072371,33.021764],"type":"Point"}
}