{
  "type": "Feature",
  "properties": {
    "iso:country":"US",
    "sg:address":"1054 Double Bridges Rd",
    "sg:city":"Elberton",
    "sg:classifiers":[
        {
            "category":"Professional",
            "subcategory":"Business Services",
            "type":"Services"
        }
    ],
    "sg:phone":"+1 706 283 6212",
    "sg:postcode":"30635",
    "sg:province":"GA",
    "wof:name":"Tri Star USA Inc",
    "wof:placetype":"venue"
},
  "geometry": {"coordinates":[-82.88919300000001,34.190978],"type":"Point"}
}