{
  "type": "Feature",
  "properties": {
    "iso:country":"US",
    "sg:address":"601 Professional Dr",
    "sg:city":"Lawrenceville",
    "sg:classifiers":[
        {
            "category":"Health Services",
            "subcategory":"Doctor",
            "type":"Services"
        }
    ],
    "sg:phone":"+1 770 995 9528",
    "sg:postcode":"30046",
    "sg:province":"GA",
    "wof:name":"Simon Timothy MD",
    "wof:placetype":"venue"
},
  "geometry": {"coordinates":[-84.01187899999999,33.963669],"type":"Point"}
}