{
  "type": "Feature",
  "properties": {
    "addr:full":"741 Forest Park Ln Suwanee GA 30024",
    "addr:housenumber":"741",
    "addr:postcode":"30024",
    "addr:street":"Forest Park Ln",
    "iso:country":"US",
    "sg:address":"741 Forest Park Ln",
    "sg:city":"Suwanee",
    "sg:classifiers":[
        {
            "category":"Professional",
            "subcategory":"Management & Consulting",
            "type":"Services"
        }
    ],
    "sg:phone":"+1 770 963 1048",
    "sg:postcode":"30024",
    "sg:province":"GA",
    "sg:tags":[
        "business"
    ],
    "wof:name":"TW Consulting Inc",
    "wof:placetype":"venue"
},
  "geometry": {"coordinates":[-84.045829,34.007773],"type":"Point"}
}