{
  "type": "Feature",
  "properties": {
    "addr:full":"505 Osborne St St Marys GA 31558",
    "addr:housenumber":"505",
    "addr:postcode":"31558",
    "addr:street":"Osborne St",
    "iso:country":"US",
    "sg:address":"505 Osborne St",
    "sg:city":"St Marys",
    "sg:classifiers":[
        {
            "category":"Insurance",
            "subcategory":"Insurance Agent",
            "type":"Services"
        }
    ],
    "sg:phone":"+1 912 882 5656",
    "sg:postcode":"31558",
    "sg:province":"GA",
    "wof:name":"Flem Hall Insurance",
    "wof:placetype":"venue"
},
  "geometry": {"coordinates":[-81.546981,30.727509],"type":"Point"}
}