{
  "type": "Feature",
  "properties": {
    "iso:country":"US",
    "sg:address":"627 Uvalda Hwy",
    "sg:city":"Hazlehurst",
    "sg:classifiers":[
        {
            "category":"Freight",
            "type":"Transportation"
        }
    ],
    "sg:phone":"+1 912 375 4222",
    "sg:postcode":"31539",
    "sg:province":"GA",
    "sg:tags":[
        "trucking"
    ],
    "wof:name":"ABF Freight System Inc",
    "wof:placetype":"venue"
},
  "geometry": {"coordinates":[-82.568529,31.904147],"type":"Point"}
}