{
  "type": "Feature",
  "properties": {
    "addr:full":"2320 Gordon Hwy Augusta GA 30909",
    "addr:housenumber":"2320",
    "addr:postcode":"30909",
    "addr:street":"Gordon Hwy",
    "iso:country":"US",
    "sg:address":"2320 Gordon Hwy",
    "sg:city":"Augusta",
    "sg:classifiers":[
        {
            "category":"Bars & Pubs",
            "type":"Food & Drink"
        }
    ],
    "sg:phone":"+1 706 737 0905",
    "sg:postcode":"30909",
    "sg:province":"GA",
    "wof:name":"Charlie's Tavern",
    "wof:placetype":"venue"
},
  "geometry": {"coordinates":[-82.09344,33.445129],"type":"Point"}
}