{
  "type": "Feature",
  "properties": {
    "iso:country":"US",
    "sg:address":"2304 Allen Ave",
    "sg:city":"Augusta",
    "sg:classifiers":[
        {
            "category":"Building & Trades",
            "subcategory":"Landscaping Services",
            "type":"Services"
        }
    ],
    "sg:phone":"+1 706 627 9566",
    "sg:postcode":"30906",
    "sg:province":"GA",
    "sg:tags":[
        "tree"
    ],
    "wof:name":"Dowd's Tree Experts",
    "wof:placetype":"venue"
},
  "geometry": {"coordinates":[-82.035712,33.422584],"type":"Point"}
}