{
  "type": "Feature",
  "properties": {
    "iso:country":"US",
    "sg:address":"135 Woodridge Cir",
    "sg:city":"La Grange",
    "sg:classifiers":[
        {
            "category":"Utilities",
            "subcategory":"Telephone",
            "type":"Services"
        }
    ],
    "sg:phone":"+1 706 957 4573",
    "sg:postcode":"30241",
    "sg:province":"GA",
    "sg:tags":[
        "communications"
    ],
    "wof:name":"Wwwbadassserverscom",
    "wof:placetype":"venue"
},
  "geometry": {"coordinates":[-85.002501,33.061856],"type":"Point"}
}