{
  "type": "Feature",
  "properties": {
    "addr:full":"452 Winder Hwy Lawrenceville GA 30045",
    "addr:housenumber":"452",
    "addr:postcode":"30045",
    "addr:street":"Winder Hwy",
    "iso:country":"US",
    "sg:address":"452 Winder Hwy",
    "sg:city":"Lawrenceville",
    "sg:classifiers":[
        {
            "category":"Building & Trades",
            "subcategory":"Cleaning & Sanitation",
            "type":"Services"
        },
        {
            "category":"Retail",
            "subcategory":"Laundry & Dry Cleaning",
            "type":"Services"
        }
    ],
    "sg:phone":"+1 770 277 1041",
    "sg:postcode":"30045",
    "sg:province":"GA",
    "sg:tags":[
        "cleaners",
        "maintenance"
    ],
    "wof:name":"AAA Laundrymat & Cleaners",
    "wof:placetype":"venue"
},
  "geometry": {"coordinates":[-83.966643,33.964908],"type":"Point"}
}