{
  "type": "Feature",
  "properties": {
    "iso:country":"US",
    "sg:address":"1180 Cooper Rd",
    "sg:city":"Snellville",
    "sg:classifiers":[
        {
            "category":"Professional",
            "subcategory":"Management & Consulting",
            "type":"Services"
        }
    ],
    "sg:phone":"+1 770 972 1818",
    "sg:postcode":"30078",
    "sg:province":"GA",
    "sg:tags":[
        "consultant"
    ],
    "sg:website":"http://www.bridgeinternational.com",
    "wof:name":"Bridge International Inc",
    "wof:placetype":"venue"
},
  "geometry": {"coordinates":[-83.967444,33.861853],"type":"Point"}
}