{
  "type": "Feature",
  "properties": {
    "addr:full":"115 E Hill St Decatur GA 30030",
    "addr:housenumber":"115",
    "addr:postcode":"30030",
    "addr:street":"E Hill St",
    "iso:country":"US",
    "sg:address":"115 E Hill St",
    "sg:city":"Decatur",
    "sg:classifiers":[
        {
            "category":"Organizations",
            "subcategory":"Religious Organization",
            "type":"Services"
        }
    ],
    "sg:phone":"+1 404 373 3247",
    "sg:postcode":"30030",
    "sg:province":"GA",
    "wof:name":"Henry Thomas Tabernacle Church",
    "wof:placetype":"venue"
},
  "geometry": {"coordinates":[-84.29476,33.75963],"type":"Point"}
}