{
  "type": "Feature",
  "properties": {
    "addr:full":"1335 Access Rd Covington GA 30014",
    "addr:housenumber":"1335",
    "addr:postcode":"30014",
    "addr:street":"Access Rd",
    "iso:country":"US",
    "sg:address":"1335 Access Rd",
    "sg:city":"Covington",
    "sg:classifiers":[
        {
            "category":"Building & Trades",
            "subcategory":"Equipment Rental",
            "type":"Services"
        }
    ],
    "sg:phone":"+1 770 786 3254",
    "sg:postcode":"30014",
    "sg:province":"GA",
    "wof:name":"U-Haul",
    "wof:placetype":"venue"
},
  "geometry": {"coordinates":[-83.89497299999999,33.612375],"type":"Point"}
}