{
  "type": "Feature",
  "properties": {
    "addr:full":"6100 US Hwy 41 Hahira GA 31632",
    "addr:housenumber":"6100",
    "addr:postcode":"31632",
    "addr:street":"Us Hwy 41",
    "iso:country":"US",
    "sg:address":"6100 US Hwy 41",
    "sg:city":"Hahira",
    "sg:classifiers":[
        {
            "category":"Building & Trades",
            "subcategory":"Construction",
            "type":"Services"
        }
    ],
    "sg:phone":"+1 229 794 3537",
    "sg:postcode":"31632",
    "sg:province":"GA",
    "wof:name":"South Georgia Metal Works",
    "wof:placetype":"venue"
},
  "geometry": {"coordinates":[-83.376648,31.010958],"type":"Point"}
}