{
  "type": "Feature",
  "properties": {
    "iso:country":"US",
    "sg:address":"288 S Hill St",
    "sg:city":"Buford",
    "sg:classifiers":[
        {
            "category":"Wholesale",
            "subcategory":"Machinery & Supplies",
            "type":"Manufacturing & Wholesale Goods"
        },
        {
            "category":"Personal",
            "subcategory":"Beauty Salon",
            "type":"Services"
        }
    ],
    "sg:phone":"+1 770 945 8388",
    "sg:postcode":"30518",
    "sg:province":"GA",
    "sg:tags":[
        "equipment",
        "establishment"
    ],
    "wof:name":"Brandi Crowe Salon Services",
    "wof:placetype":"venue"
},
  "geometry": {"coordinates":[-83.999757,34.120268],"type":"Point"}
}