{
  "type": "Feature",
  "properties": {
    "addr:full":"5370 State Rte 20 Loganville GA 30052",
    "addr:housenumber":"5370",
    "addr:postcode":"30052",
    "addr:street":"State Rte 20",
    "iso:country":"US",
    "sg:address":"5370 State Rte 20",
    "sg:city":"Loganville",
    "sg:classifiers":[
        {
            "category":"Retail",
            "subcategory":"Repair Shop",
            "type":"Services"
        }
    ],
    "sg:phone":"+1 770 298 1263",
    "sg:postcode":"30052",
    "sg:province":"GA",
    "sg:tags":[
        "lock",
        "locksmith"
    ],
    "wof:name":"Cash Lock & Key",
    "wof:placetype":"venue"
},
  "geometry": {"coordinates":[-83.91435799999999,33.829768],"type":"Point"}
}