{
  "type": "Feature",
  "properties": {
    "iso:country":"US",
    "sg:address":"114 Buckhalter Rd",
    "sg:city":"Savannah",
    "sg:classifiers":[
        {
            "category":"Building & Trades",
            "subcategory":"Electrical",
            "type":"Services"
        }
    ],
    "sg:phone":"+1 912 236 0892",
    "sg:postcode":"31405",
    "sg:province":"GA",
    "sg:tags":[
        "electrician"
    ],
    "wof:name":"Underwood, Hoss Electric Co",
    "wof:placetype":"venue"
},
  "geometry": {"coordinates":[-81.184369,32.03218],"type":"Point"}
}