{
  "type": "Feature",
  "properties": {
    "addr:full":"3295 Northside Pkwy NW Atlanta GA 30327",
    "addr:housenumber":"3295",
    "addr:postcode":"30327",
    "addr:street":"Northside Pkwy Nw",
    "iso:country":"US",
    "sg:address":"3295 Northside Pkwy NW",
    "sg:city":"Atlanta",
    "sg:classifiers":[
        {
            "category":"Education",
            "subcategory":"Library",
            "type":"Public Place"
        }
    ],
    "sg:phone":"+1 404 262 1124",
    "sg:postcode":"30327",
    "sg:province":"GA",
    "wof:name":"Public Works Dept",
    "wof:placetype":"venue"
},
  "geometry": {"coordinates":[-84.42497,33.844245],"type":"Point"}
}