{
  "type": "Feature",
  "properties": {
    "iso:country":"US",
    "sg:address":"434 Northside Dr",
    "sg:city":"Valdosta",
    "sg:classifiers":[
        {
            "category":"Building & Trades",
            "subcategory":"Construction",
            "type":"Services"
        }
    ],
    "sg:phone":"+1 229 671 1987",
    "sg:postcode":"31602",
    "sg:province":"GA",
    "sg:tags":[
        "contractor"
    ],
    "wof:name":"Plantation Pools & Spas",
    "wof:placetype":"venue"
},
  "geometry": {"coordinates":[-83.28580100000001,30.870278],"type":"Point"}
}