{
  "type": "Feature",
  "properties": {
    "iso:country":"US",
    "sg:address":"5534 Janeru Cir",
    "sg:city":"Macon",
    "sg:classifiers":[
        {
            "category":"Organizations",
            "subcategory":"Religious Organization",
            "type":"Services"
        }
    ],
    "sg:phone":"+1 478 781 7324",
    "sg:postcode":"31216",
    "sg:province":"GA",
    "sg:tags":[
        "equipment"
    ],
    "wof:name":"Abundant Life Games LLC",
    "wof:placetype":"venue"
},
  "geometry": {"coordinates":[-83.746055,32.710214],"type":"Point"}
}