{
  "type": "Feature",
  "properties": {
    "iso:country":"US",
    "sg:address":"2458 Gough-Red Hill Rd",
    "sg:city":"Keysville",
    "sg:classifiers":[
        {
            "category":"Organizations",
            "subcategory":"Religious Organization",
            "type":"Services"
        }
    ],
    "sg:phone":"+1 706 554 5399",
    "sg:postcode":"30816",
    "sg:province":"GA",
    "sg:tags":[
        "church"
    ],
    "wof:name":"Forest Hill Baptist Church",
    "wof:placetype":"venue"
},
  "geometry": {"coordinates":[-82.155327,33.118012],"type":"Point"}
}