{
  "type": "Feature",
  "properties": {
    "iso:country":"US",
    "sg:address":"216 Thorncrest",
    "sg:city":"Stockbridge",
    "sg:classifiers":[
        {
            "category":"Professional",
            "subcategory":"Business Services",
            "type":"Services"
        }
    ],
    "sg:phone":"+1 770 507 5099",
    "sg:postcode":"30281",
    "sg:province":"GA",
    "wof:name":"Jhenda Group Inc",
    "wof:placetype":"venue"
},
  "geometry": {"coordinates":[-84.233603,33.586992],"type":"Point"}
}