{
  "type": "Feature",
  "properties": {
    "addr:full":"114 S Main St Moultrie GA 31768",
    "addr:housenumber":"114",
    "addr:postcode":"31768",
    "addr:street":"S Main St",
    "iso:country":"US",
    "sg:address":"114 S Main St",
    "sg:city":"Moultrie",
    "sg:classifiers":[
        {
            "category":"Shopping",
            "subcategory":"Gifts & Souvenirs",
            "type":"Retail Goods"
        }
    ],
    "sg:phone":"+1 229 985 3383",
    "sg:postcode":"31768",
    "sg:province":"GA",
    "sg:tags":[
        "shop"
    ],
    "wof:name":"Every Thing Special",
    "wof:placetype":"venue"
},
  "geometry": {"coordinates":[-83.788944,31.178837],"type":"Point"}
}