{
  "type": "Feature",
  "properties": {
    "iso:country":"US",
    "sg:address":"2849 Aunt Pittypat Ln",
    "sg:city":"Douglasville",
    "sg:classifiers":[
        {
            "category":"Retail",
            "subcategory":"Car Wash",
            "type":"Services"
        }
    ],
    "sg:phone":"+1 678 768 1560",
    "sg:postcode":"30135",
    "sg:province":"GA",
    "sg:tags":[
        "carwash"
    ],
    "wof:name":"Mos Detailing",
    "wof:placetype":"venue"
},
  "geometry": {"coordinates":[-84.67628000000001,33.729036],"type":"Point"}
}