{
  "type": "Feature",
  "properties": {
    "iso:country":"US",
    "sg:address":"909 E 3rd St",
    "sg:city":"Jackson",
    "sg:classifiers":[
        {
            "category":"Home & Garden",
            "subcategory":"Carpets & Floor Coverings",
            "type":"Retail Goods"
        }
    ],
    "sg:phone":"+1 770 504 1333",
    "sg:postcode":"30233",
    "sg:province":"GA",
    "wof:name":"Jackson Carpet",
    "wof:placetype":"venue"
},
  "geometry": {"coordinates":[-83.951122,33.294595],"type":"Point"}
}