{
  "type": "Feature",
  "properties": {
    "addr:full":"2810 Frank Camp Rd Monroe GA 30655",
    "addr:housenumber":"2810",
    "addr:postcode":"30655",
    "addr:street":"Frank Camp Rd",
    "iso:country":"US",
    "sg:address":"2810 Frank Camp Rd",
    "sg:city":"Monroe",
    "sg:classifiers":[
        {
            "category":"Social Services",
            "subcategory":"Child Care",
            "type":"Services"
        }
    ],
    "sg:phone":"+1 770 267 9702",
    "sg:postcode":"30655",
    "sg:province":"GA",
    "sg:tags":[
        "day"
    ],
    "wof:name":"Mundys Enterprises Inc",
    "wof:placetype":"venue"
},
  "geometry": {"coordinates":[-83.62027500000001,33.806149],"type":"Point"}
}