{
  "type": "Feature",
  "properties": {
    "addr:full":"6250 Marbut Rd Lithonia GA 30058",
    "addr:postcode":"6250;30058",
    "addr:street":"Marbut Rd",
    "iso:country":"US",
    "sg:address":"6250 Marbut Rd",
    "sg:city":"Lithonia",
    "sg:classifiers":[
        {
            "category":"Building & Trades",
            "subcategory":"Construction",
            "type":"Services"
        }
    ],
    "sg:phone":"+1 404 931 5784",
    "sg:postcode":"30058",
    "sg:province":"GA",
    "sg:tags":[
        "residential"
    ],
    "wof:name":"Taylormade Construction Inc",
    "wof:placetype":"venue"
},
  "geometry": {"coordinates":[-84.133877,33.727087],"type":"Point"}
}