{
  "type": "Feature",
  "properties": {
    "iso:country":"US",
    "sg:address":"922 Highway 81 E Ste 117",
    "sg:city":"McDonough",
    "sg:classifiers":[
        {
            "category":"Professional",
            "subcategory":"Advertising",
            "type":"Services"
        },
        {
            "category":"Communications",
            "subcategory":"Newspaper",
            "type":"Services"
        }
    ],
    "sg:phone":"+1 678 701 7265",
    "sg:postcode":"30253",
    "sg:province":"GA",
    "sg:tags":[
        "marketing"
    ],
    "sg:website":"localmarketexperts.com",
    "wof:name":"Local Market Experts",
    "wof:placetype":"venue"
},
  "geometry": {"coordinates":[-84.211398,33.429598],"type":"Point"}
}