{
  "type": "Feature",
  "properties": {
    "addr:full":"190 Terramont Ct Roswell GA 30076",
    "addr:housenumber":"190",
    "addr:postcode":"30076",
    "addr:street":"Terramont Ct",
    "iso:country":"US",
    "sg:address":"190 Terramont Ct",
    "sg:city":"Roswell",
    "sg:classifiers":[
        {
            "category":"Wholesale",
            "subcategory":"Non-durable Goods",
            "type":"Manufacturing & Wholesale Goods"
        }
    ],
    "sg:phone":"+1 770 645 0117",
    "sg:postcode":"30076",
    "sg:province":"GA",
    "sg:tags":[
        "advertising",
        "specialty"
    ],
    "wof:name":"Promotions Plus",
    "wof:placetype":"venue"
},
  "geometry": {"coordinates":[-84.307816,34.014989],"type":"Point"}
}