{
  "type": "Feature",
  "properties": {
    "iso:country":"US",
    "sg:address":"2765 Camp Branch Rd",
    "sg:city":"Buford",
    "sg:classifiers":[
        {
            "category":"Professional",
            "type":"Services"
        }
    ],
    "sg:phone":"+1 678 482 8698",
    "sg:postcode":"30519",
    "sg:province":"GA",
    "wof:name":"Szetos Inc",
    "wof:placetype":"venue"
},
  "geometry": {"coordinates":[-83.943701,34.071434],"type":"Point"}
}