{
  "type": "Feature",
  "properties": {
    "iso:country":"US",
    "sg:address":"975 Waverly Ct",
    "sg:city":"Marietta",
    "sg:classifiers":[
        {
            "category":"Manufacturing",
            "subcategory":"Metals",
            "type":"Manufacturing & Wholesale Goods"
        }
    ],
    "sg:phone":"+1 770 429 4919",
    "sg:postcode":"30064",
    "sg:province":"GA",
    "sg:tags":[
        "nonferrous"
    ],
    "wof:name":"Alcoa",
    "wof:placetype":"venue"
},
  "geometry": {"coordinates":[-84.584886,33.928085],"type":"Point"}
}