{
  "type": "Feature",
  "properties": {
    "addr:full":"24 Kitchen Way E Dahlonega GA 30533",
    "addr:housenumber":"24",
    "addr:postcode":"30533",
    "addr:street":"Kitchen Way E",
    "iso:country":"US",
    "sg:address":"24 Kitchen Way E",
    "sg:city":"Dahlonega",
    "sg:classifiers":[
        {
            "category":"Banks & Credit Unions",
            "subcategory":"Financial Services",
            "type":"Services"
        }
    ],
    "sg:phone":"+1 706 867 7822",
    "sg:postcode":"30533",
    "sg:province":"GA",
    "sg:tags":[
        "investor"
    ],
    "wof:name":"Sharp Investmests",
    "wof:placetype":"venue"
},
  "geometry": {"coordinates":[-83.981554,34.425011],"type":"Point"}
}