{
  "type": "Feature",
  "properties": {
    "addr:full":"1944 Walton Way Augusta GA 30904",
    "addr:housenumber":"1944",
    "addr:postcode":"30904",
    "addr:street":"Walton Way",
    "iso:country":"US",
    "sg:address":"1944 Walton Way",
    "sg:city":"Augusta",
    "sg:classifiers":[
        {
            "category":"Shopping",
            "type":"Retail Goods"
        }
    ],
    "sg:phone":"+1 706 733 2854",
    "sg:postcode":"30904",
    "sg:province":"GA",
    "sg:tags":[
        "wheel",
        "chair",
        "scooter"
    ],
    "wof:name":"Reliant Care",
    "wof:placetype":"venue"
},
  "geometry": {"coordinates":[-82.004251,33.475708],"type":"Point"}
}