{
  "type": "Feature",
  "properties": {
    "iso:country":"US",
    "sg:address":"110 Chester Ave SE",
    "sg:city":"Atlanta",
    "sg:classifiers":[
        {
            "category":"Shopping",
            "subcategory":"Clothing, Apparel, & Fashions",
            "type":"Retail Goods"
        }
    ],
    "sg:phone":"+1 404 222 0882",
    "sg:postcode":"30316",
    "sg:province":"GA",
    "sg:tags":[
        "boutique",
        "woman",
        "specialty"
    ],
    "wof:name":"Couture LLC",
    "wof:placetype":"venue"
},
  "geometry": {"coordinates":[-84.35911,33.749589],"type":"Point"}
}