{
  "type": "Feature",
  "properties": {
    "iso:country":"US",
    "sg:address":"147 Tye St",
    "sg:city":"Stockbridge",
    "sg:classifiers":[
        {
            "category":"Education",
            "subcategory":"School",
            "type":"Public Place"
        }
    ],
    "sg:phone":"+1 770 474 4066",
    "sg:postcode":"30281",
    "sg:province":"GA",
    "sg:tags":[
        "high",
        "middle",
        "elementary"
    ],
    "wof:name":"Henry County Schools",
    "wof:placetype":"venue"
},
  "geometry": {"coordinates":[-84.235586,33.537013],"type":"Point"}
}