{
  "type": "Feature",
  "properties": {
    "iso:country":"US",
    "sg:address":"2124 Skyview Dr",
    "sg:city":"Lithia Springs",
    "sg:classifiers":[
        {
            "category":"Building & Trades",
            "subcategory":"Construction",
            "type":"Services"
        }
    ],
    "sg:phone":"+1 678 945 6550",
    "sg:postcode":"30122",
    "sg:province":"GA",
    "sg:tags":[
        "contractor"
    ],
    "wof:name":"Champion Nationwide Contr",
    "wof:placetype":"venue"
},
  "geometry": {"coordinates":[-84.64742,33.786077],"type":"Point"}
}