{
  "type": "Feature",
  "properties": {
    "iso:country":"US",
    "sg:address":"10490 Alpharetta Hwy",
    "sg:city":"Roswell",
    "sg:classifiers":[
        {
            "category":"Personal",
            "subcategory":"Beauty Salon",
            "type":"Services"
        },
        {
            "category":"Personal",
            "subcategory":"Skin Care",
            "type":"Services"
        }
    ],
    "sg:phone":"+1 770 998 5648",
    "sg:postcode":"30076",
    "sg:province":"GA",
    "sg:tags":[
        "hair"
    ],
    "sg:website":"www.arthairsalon.com",
    "wof:name":"Art Hair Salon & Spa",
    "wof:placetype":"venue"
},
  "geometry": {"coordinates":[-84.343215,34.038129],"type":"Point"}
}