{
  "type": "Feature",
  "properties": {
    "addr:full":"813 Muirfield Trl Marietta GA 30068",
    "addr:housenumber":"813",
    "addr:postcode":"30068",
    "addr:street":"Muirfield Trl",
    "iso:country":"US",
    "sg:address":"813 Muirfield Trl",
    "sg:city":"Marietta",
    "sg:classifiers":[
        {
            "category":"Wholesale",
            "subcategory":"Non-durable Goods",
            "type":"Manufacturing & Wholesale Goods"
        }
    ],
    "sg:phone":"+1 770 977 7882",
    "sg:postcode":"30068",
    "sg:province":"GA",
    "wof:name":"Anita & Associates Inc",
    "wof:placetype":"venue"
},
  "geometry": {"coordinates":[-84.43153,33.97013],"type":"Point"}
}