{
  "type": "Feature",
  "properties": {
    "addr:full":"401 31st St SE Moultrie GA 31788",
    "addr:housenumber":"401",
    "addr:postcode":"31788",
    "addr:street":"31St St Se",
    "iso:country":"US",
    "sg:address":"401 31st St SE",
    "sg:city":"Moultrie",
    "sg:classifiers":[
        {
            "category":"Real Estate",
            "subcategory":"Real Estate Operator",
            "type":"Services"
        }
    ],
    "sg:phone":"+1 229 985 2384",
    "sg:postcode":"31788",
    "sg:province":"GA",
    "sg:tags":[
        "building",
        "apartment"
    ],
    "wof:name":"Fairmeadow Apartment LLC",
    "wof:placetype":"venue"
},
  "geometry": {"coordinates":[-83.74311899999999,31.17138],"type":"Point"}
}