{
  "type": "Feature",
  "properties": {
    "iso:country":"US",
    "sg:address":"724 5th St",
    "sg:city":"Macon",
    "sg:classifiers":[
        {
            "category":"Wholesale",
            "subcategory":"Auto Parts",
            "type":"Manufacturing & Wholesale Goods"
        }
    ],
    "sg:phone":"+1 478 745 5555",
    "sg:postcode":"31201",
    "sg:province":"GA",
    "wof:name":"Mighty Distributing",
    "wof:placetype":"venue"
},
  "geometry": {"coordinates":[-83.626687,32.831039],"type":"Point"}
}