{
  "type": "Feature",
  "properties": {
    "addr:full":"7404 Davidson Cir E Stockbridge GA 30281",
    "addr:housenumber":"7404",
    "addr:postcode":"30281",
    "addr:street":"Davidson Cir E",
    "iso:country":"US",
    "sg:address":"7404 Davidson Cir E",
    "sg:city":"Stockbridge",
    "sg:classifiers":[
        {
            "category":"Restaurant",
            "type":"Food & Drink"
        },
        {
            "category":"Ice Cream",
            "type":"Food & Drink"
        }
    ],
    "sg:menulink":"http://www.allmenus.com/ga/jonesboro/172627-dairy-queen/menu/",
    "sg:phone":"+1 770 389 5281",
    "sg:postcode":"30281",
    "sg:province":"GA",
    "sg:tags":[
        "burger",
        "american",
        "ice",
        "cream"
    ],
    "wof:name":"Dairy Queen",
    "wof:placetype":"venue"
},
  "geometry": {"coordinates":[-84.26468800000001,33.552543],"type":"Point"}
}