{
  "type": "Feature",
  "properties": {
    "addr:full":"1432 Stratfield Cir NE Atlanta GA 30319",
    "addr:housenumber":"1432",
    "addr:postcode":"30319",
    "addr:street":"Stratfield Cir Ne",
    "iso:country":"US",
    "sg:address":"1432 Stratfield Cir NE",
    "sg:city":"Atlanta",
    "sg:classifiers":[
        {
            "category":"Professional",
            "subcategory":"Computer Services",
            "type":"Services"
        }
    ],
    "sg:phone":"+1 404 841 9122",
    "sg:postcode":"30319",
    "sg:province":"GA",
    "sg:tags":[
        "cd-rom"
    ],
    "wof:name":"Medicat",
    "wof:placetype":"venue"
},
  "geometry": {"coordinates":[-84.329048,33.888862],"type":"Point"}
}