{
  "type": "Feature",
  "properties": {
    "iso:country":"US",
    "sg:address":"484 3rd St",
    "sg:city":"Macon",
    "sg:classifiers":[
        {
            "category":"Real Estate",
            "subcategory":"Developer",
            "type":"Services"
        }
    ],
    "sg:phone":"+1 478 742 3814",
    "sg:postcode":"31201",
    "sg:province":"GA",
    "wof:name":"Broadway Development Co",
    "wof:placetype":"venue"
},
  "geometry": {"coordinates":[-83.628811,32.834322],"type":"Point"}
}