{
  "type": "Feature",
  "properties": {
    "addr:full":"20 Glenlake Pkwy NE Atlanta GA 30328",
    "addr:housenumber":"20",
    "addr:postcode":"30328",
    "addr:street":"Glenlake Pkwy Ne",
    "iso:country":"US",
    "sg:address":"20 Glenlake Pkwy NE",
    "sg:city":"Atlanta",
    "sg:classifiers":[
        {
            "category":"Health Services",
            "subcategory":"Doctor",
            "type":"Services"
        }
    ],
    "sg:phone":"+1 404 365 0966",
    "sg:postcode":"30328",
    "sg:province":"GA",
    "sg:website":"www.kp.org",
    "wof:name":"Kaiser Permanente Health Plan",
    "wof:placetype":"venue"
},
  "geometry": {"coordinates":[-84.36156699999999,33.937247],"type":"Point"}
}