{
  "type": "Feature",
  "properties": {
    "iso:country":"US",
    "sg:address":"2301 Parklake Dr NE",
    "sg:city":"Atlanta",
    "sg:classifiers":[
        {
            "category":"Banks & Credit Unions",
            "subcategory":"Bank",
            "type":"Services"
        }
    ],
    "sg:phone":"+1 404 325 3270",
    "sg:postcode":"30345",
    "sg:province":"GA",
    "wof:name":"Briarwood Financial Services Inc",
    "wof:placetype":"venue"
},
  "geometry": {"coordinates":[-84.249318,33.853372],"type":"Point"}
}