{
  "type": "Feature",
  "properties": {
    "addr:full":"3675 Martin Luther King Jr Dr SW Atlanta GA 30331",
    "addr:housenumber":"3675",
    "addr:postcode":"30331",
    "addr:street":"Martin Luther King Jr Dr Sw",
    "iso:country":"US",
    "sg:address":"3675 Martin Luther King Jr Dr SW",
    "sg:city":"Atlanta",
    "sg:classifiers":[
        {
            "category":"Organizations",
            "subcategory":"Religious Organization",
            "type":"Services"
        }
    ],
    "sg:phone":"+1 404 691 4411",
    "sg:postcode":"30331",
    "sg:province":"GA",
    "sg:tags":[
        "church"
    ],
    "wof:name":"New Unity Missionary Bapt Chr",
    "wof:placetype":"venue"
},
  "geometry": {"coordinates":[-84.51015599999999,33.764619],"type":"Point"}
}