{
  "type": "Feature",
  "properties": {
    "iso:country":"US",
    "sg:address":"3717 Cross Creek Cir",
    "sg:city":"Valdosta",
    "sg:classifiers":[
        {
            "category":"Professional",
            "subcategory":"Detective & Security Services",
            "type":"Services"
        }
    ],
    "sg:phone":"+1 229 259 0763",
    "sg:postcode":"31605",
    "sg:province":"GA",
    "sg:tags":[
        "information",
        "bureau"
    ],
    "wof:name":"J And F Enterprises",
    "wof:placetype":"venue"
},
  "geometry": {"coordinates":[-83.243696,30.934693],"type":"Point"}
}