{
  "type": "Feature",
  "properties": {
    "iso:country":"US",
    "sg:address":"3350 Marietta Hwy",
    "sg:city":"Canton",
    "sg:classifiers":[
        {
            "category":"Restaurant",
            "type":"Food & Drink"
        }
    ],
    "sg:phone":"+1 770 345 5212",
    "sg:postcode":"30114",
    "sg:province":"GA",
    "wof:name":"Biscuit Barn",
    "wof:placetype":"venue"
},
  "geometry": {"coordinates":[-84.507301,34.221001],"type":"Point"}
}