{
  "type": "Feature",
  "properties": {
    "iso:country":"US",
    "sg:address":"699 Broad St",
    "sg:city":"Augusta",
    "sg:classifiers":[
        {
            "category":"Professional",
            "subcategory":"Lawyer & Legal Services",
            "type":"Services"
        }
    ],
    "sg:phone":"+1 706 724 2943",
    "sg:postcode":"30901",
    "sg:province":"GA",
    "sg:tags":[
        "attorney"
    ],
    "wof:name":"Thomas W Tinley III",
    "wof:placetype":"venue"
},
  "geometry": {"coordinates":[-81.961591,33.47404],"type":"Point"}
}