{
  "type": "Feature",
  "properties": {
    "addr:full":"2290 Moody Rd Warner Robins GA 31088",
    "addr:housenumber":"2290",
    "addr:postcode":"31088",
    "addr:street":"Moody Rd",
    "iso:country":"US",
    "sg:address":"2290 Moody Rd",
    "sg:city":"Warner Robins",
    "sg:classifiers":[
        {
            "category":"Banks & Credit Unions",
            "subcategory":"Investment Brokerage",
            "type":"Services"
        }
    ],
    "sg:phone":"+1 478 922 0588",
    "sg:postcode":"31088",
    "sg:province":"GA",
    "sg:tags":[
        "security"
    ],
    "wof:name":"Edward Jones Co",
    "wof:placetype":"venue"
},
  "geometry": {"coordinates":[-83.622676,32.589012],"type":"Point"}
}