{
  "type": "Feature",
  "properties": {
    "iso:country":"US",
    "sg:address":"1020 Nine North Dr",
    "sg:city":"Alpharetta",
    "sg:classifiers":[
        {
            "category":"Building & Trades",
            "subcategory":"Plumbing",
            "type":"Services"
        }
    ],
    "sg:phone":"+1 770 475 4722",
    "sg:postcode":"30004",
    "sg:province":"GA",
    "sg:tags":[
        "plumbing",
        "contractor"
    ],
    "wof:name":"Bill-John Plumbing Co Inc",
    "wof:placetype":"venue"
},
  "geometry": {"coordinates":[-84.257068,34.15215],"type":"Point"}
}