{
  "type": "Feature",
  "properties": {
    "iso:country":"US",
    "sg:address":"1520 W Cherry St",
    "sg:city":"Jesup",
    "sg:classifiers":[
        {
            "category":"Autos & Motor Vehicles",
            "subcategory":"Automobile Sales",
            "type":"Retail Goods"
        }
    ],
    "sg:phone":"+1 912 427 6932",
    "sg:postcode":"31545",
    "sg:province":"GA",
    "sg:tags":[
        "car",
        "dealer"
    ],
    "wof:name":"Billy Poppell Car Sales Inc",
    "wof:placetype":"venue"
},
  "geometry": {"coordinates":[-81.901713,31.620536],"type":"Point"}
}