{
  "type": "Feature",
  "properties": {
    "iso:country":"US",
    "sg:address":"225 Springtree Ct",
    "sg:city":"Atlanta",
    "sg:classifiers":[
        {
            "category":"Building & Trades",
            "subcategory":"Pest Control",
            "type":"Services"
        }
    ],
    "sg:phone":"+1 770 969 8668",
    "sg:postcode":"30349",
    "sg:province":"GA",
    "wof:name":"Ralph Grier",
    "wof:placetype":"venue"
},
  "geometry": {"coordinates":[-84.494738,33.570939],"type":"Point"}
}