{
  "type": "Feature",
  "properties": {
    "addr:full":"2376 Fairburn Rd Douglasville GA 30135",
    "addr:housenumber":"2376",
    "addr:postcode":"30135",
    "addr:street":"Fairburn Rd",
    "iso:country":"US",
    "sg:address":"2376 Fairburn Rd",
    "sg:city":"Douglasville",
    "sg:classifiers":[
        {
            "category":"Real Estate",
            "subcategory":"Real Estate Operator",
            "type":"Services"
        }
    ],
    "sg:phone":"+1 770 942 0504",
    "sg:postcode":"30135",
    "sg:province":"GA",
    "sg:tags":[
        "apartment"
    ],
    "wof:name":"Robinson & Sons Inc",
    "wof:placetype":"venue"
},
  "geometry": {"coordinates":[-84.678476,33.740553],"type":"Point"}
}