{
  "type": "Feature",
  "properties": {
    "iso:country":"US",
    "sg:address":"455 Red Hollow Rd",
    "sg:city":"Eastanollee",
    "sg:classifiers":[
        {
            "category":"Retail",
            "subcategory":"Repair Shop",
            "type":"Services"
        }
    ],
    "sg:phone":"+1 706 779 6818",
    "sg:postcode":"30538",
    "sg:province":"GA",
    "sg:tags":[
        "repairing",
        "piano",
        "refinishing"
    ],
    "wof:name":"Pianoforte' Shoppe",
    "wof:placetype":"venue"
},
  "geometry": {"coordinates":[-83.24036099999999,34.513362],"type":"Point"}
}