{
  "type": "Feature",
  "properties": {
    "addr:full":"1220 Caroline St NE Atlanta GA 30307",
    "addr:housenumber":"1220",
    "addr:postcode":"30307",
    "addr:street":"Caroline St Ne",
    "iso:country":"US",
    "sg:address":"1220 Caroline St NE",
    "sg:city":"Atlanta",
    "sg:classifiers":[
        {
            "category":"Coffee & Tea",
            "type":"Food & Drink"
        }
    ],
    "sg:menulink":"http://www.allmenus.com/ga/atlanta-decatur/221072-caribou-coffee/menu/",
    "sg:phone":"+1 404 589 3446",
    "sg:postcode":"30307",
    "sg:province":"GA",
    "sg:tags":[
        "american",
        "diner"
    ],
    "wof:name":"Caribou Coffee",
    "wof:placetype":"venue"
},
  "geometry": {"coordinates":[-84.347826,33.758427],"type":"Point"}
}