{
  "type": "Feature",
  "properties": {
    "addr:full":"900 Marietta Hwy Roswell GA 30075",
    "addr:housenumber":"900",
    "addr:postcode":"30075",
    "addr:street":"Marietta Hwy",
    "iso:country":"US",
    "sg:address":"900 Marietta Hwy",
    "sg:city":"Roswell",
    "sg:classifiers":[
        {
            "category":"Shopping",
            "subcategory":"Pharmacy",
            "type":"Retail Goods"
        }
    ],
    "sg:phone":"+1 678 352 7497",
    "sg:postcode":"30075",
    "sg:province":"GA",
    "sg:tags":[
        "drugstore"
    ],
    "wof:name":"Kroger Pharmacy",
    "wof:placetype":"venue"
},
  "geometry": {"coordinates":[-84.388901,34.006001],"type":"Point"}
}