{
  "type": "Feature",
  "properties": {
    "addr:full":"2218 Fellowship Rd Tucker GA 30084",
    "addr:housenumber":"2218",
    "addr:postcode":"30084",
    "addr:street":"Fellowship Rd",
    "iso:country":"US",
    "sg:address":"2218 Fellowship Rd",
    "sg:city":"Tucker",
    "sg:classifiers":[
        {
            "category":"Home & Garden",
            "subcategory":"Garden Supply",
            "type":"Retail Goods"
        }
    ],
    "sg:phone":"+1 770 491 0252",
    "sg:postcode":"30084",
    "sg:province":"GA",
    "sg:tags":[
        "repair"
    ],
    "wof:name":"Thomas Lawnmower & Equipment",
    "wof:placetype":"venue"
},
  "geometry": {"coordinates":[-84.217572,33.84784],"type":"Point"}
}