{
  "type": "Feature",
  "properties": {
    "iso:country":"US",
    "sg:address":"3725 Macon Rd",
    "sg:city":"Columbus",
    "sg:classifiers":[
        {
            "category":"Arts & Performance",
            "subcategory":"Theater",
            "type":"Entertainment"
        }
    ],
    "sg:phone":"+1 706 561 3342",
    "sg:postcode":"31907",
    "sg:province":"GA",
    "sg:tags":[
        "band",
        "orchestra"
    ],
    "wof:name":"Greater Columbus School-Music",
    "wof:placetype":"venue"
},
  "geometry": {"coordinates":[-84.929884,32.490705],"type":"Point"}
}