{
  "type": "Feature",
  "properties": {
    "iso:country":"US",
    "sg:address":"1867 Myrtle Dr SW 333",
    "sg:city":"Atlanta",
    "sg:classifiers":[
        {
            "category":"Social Services",
            "type":"Services"
        },
        {
            "category":"Professional",
            "subcategory":"Employment Agencies",
            "type":"Services"
        }
    ],
    "sg:phone":"+1 404 758 1363",
    "sg:postcode":"30311",
    "sg:province":"GA",
    "sg:tags":[
        "workers'",
        "placement",
        "volunteer"
    ],
    "wof:name":"Seldon Carl Foundation Inc",
    "wof:placetype":"venue"
},
  "geometry": {"coordinates":[-84.45497899999999,33.704685],"type":"Point"}
}