{
  "type": "Feature",
  "properties": {
    "iso:country":"US",
    "sg:address":"1680 Sacketts Dr",
    "sg:city":"Lawrenceville",
    "sg:classifiers":[
        {
            "category":"Shopping",
            "type":"Retail Goods"
        }
    ],
    "sg:phone":"+1 770 277 7291",
    "sg:postcode":"30043",
    "sg:province":"GA",
    "sg:tags":[
        "environmental",
        "recycling",
        "equipment"
    ],
    "wof:name":"Environmental Services & Pdts",
    "wof:placetype":"venue"
},
  "geometry": {"coordinates":[-83.988332,34.013646],"type":"Point"}
}