{
  "type": "Feature",
  "properties": {
    "addr:full":"3494 Lake Monroe Rd Douglasville GA 30135",
    "addr:housenumber":"3494",
    "addr:postcode":"30135",
    "addr:street":"Lake Monroe Rd",
    "iso:country":"US",
    "sg:address":"3494 Lake Monroe Rd",
    "sg:city":"Douglasville",
    "sg:classifiers":[
        {
            "category":"Wholesale",
            "subcategory":"Non-durable Goods",
            "type":"Manufacturing & Wholesale Goods"
        }
    ],
    "sg:phone":"+1 770 942 5064",
    "sg:postcode":"30135",
    "sg:province":"GA",
    "sg:tags":[
        "lithographic",
        "printing",
        "commercial"
    ],
    "wof:name":"Cooper Advertising",
    "wof:placetype":"venue"
},
  "geometry": {"coordinates":[-84.68298799999999,33.717963],"type":"Point"}
}