{
  "type": "Feature",
  "properties": {
    "iso:country":"US",
    "sg:address":"3162 Mercer University Dr",
    "sg:city":"Macon",
    "sg:classifiers":[
        {
            "category":"Wholesale",
            "subcategory":"Hardware",
            "type":"Manufacturing & Wholesale Goods"
        }
    ],
    "sg:phone":"+1 478 743 5429",
    "sg:postcode":"31204",
    "sg:province":"GA",
    "wof:name":"Trane",
    "wof:placetype":"venue"
},
  "geometry": {"coordinates":[-83.679245,32.825],"type":"Point"}
}