{
  "type": "Feature",
  "properties": {
    "iso:country":"US",
    "sg:address":"4170 Ben Carter Rd",
    "sg:city":"Baxley",
    "sg:classifiers":[
        {
            "category":"Building & Trades",
            "subcategory":"Landscaping Services",
            "type":"Services"
        }
    ],
    "sg:phone":"+1 912 367 1402",
    "sg:postcode":"31513",
    "sg:province":"GA",
    "sg:tags":[
        "tree",
        "stump",
        "grinding",
        "removal"
    ],
    "sg:website":"http://www.cowboycuts.com",
    "wof:name":"Cowboy Cuts Outside Maintenance",
    "wof:placetype":"venue"
},
  "geometry": {"coordinates":[-82.334442,31.797734],"type":"Point"}
}