{
  "type": "Feature",
  "properties": {
    "addr:full":"1801 Lake Cove Dr SW Atlanta GA 30331",
    "addr:housenumber":"1801",
    "addr:postcode":"30331",
    "addr:street":"Lake Cove Dr Sw",
    "iso:country":"US",
    "sg:address":"1801 Lake Cove Dr SW",
    "sg:city":"Atlanta",
    "sg:classifiers":[
        {
            "category":"Building & Trades",
            "subcategory":"Locksmith",
            "type":"Services"
        }
    ],
    "sg:phone":"+1 404 270 1768",
    "sg:postcode":"30331",
    "sg:province":"GA",
    "sg:tags":[
        "key"
    ],
    "wof:name":"24-Hours Emergency Locksmith",
    "wof:placetype":"venue"
},
  "geometry": {"coordinates":[-84.52701500000001,33.708746],"type":"Point"}
}