{
  "type": "Feature",
  "properties": {
    "iso:country":"US",
    "sg:address":"3130 Holtzclaw Dr",
    "sg:city":"Cumming",
    "sg:classifiers":[
        {
            "category":"Professional",
            "type":"Services"
        }
    ],
    "sg:phone":"+1 770 889 1477",
    "sg:postcode":"30041",
    "sg:province":"GA",
    "wof:name":"Bryan L Holtzclaw",
    "wof:placetype":"venue"
},
  "geometry": {"coordinates":[-84.08743,34.242925],"type":"Point"}
}