{
  "type": "Feature",
  "properties": {
    "addr:full":"1475 Buford Dr Ste 505 Lawrenceville GA 30043",
    "addr:housenumber":"1475",
    "addr:postcode":"30043",
    "addr:street":"Buford Dr Ste 505",
    "iso:country":"US",
    "sg:address":"1475 Buford Dr Ste 505",
    "sg:city":"Lawrenceville",
    "sg:classifiers":[
        {
            "category":"Personal",
            "subcategory":"Nail Salon",
            "type":"Services"
        }
    ],
    "sg:phone":"+1 770 338 9311",
    "sg:postcode":"30043",
    "sg:province":"GA",
    "sg:website":"www.firstpronails.com",
    "wof:name":"First Pro Nails",
    "wof:placetype":"venue"
},
  "geometry": {"coordinates":[-83.987999,34.0051],"type":"Point"}
}