{
  "type": "Feature",
  "properties": {
    "iso:country":"US",
    "sg:address":"553 S Hill St",
    "sg:city":"Buford",
    "sg:classifiers":[
        {
            "category":"Retail",
            "subcategory":"Auto Rental",
            "type":"Services"
        }
    ],
    "sg:phone":"+1 770 945 8416",
    "sg:postcode":"30518",
    "sg:province":"GA",
    "sg:tags":[
        "truck"
    ],
    "wof:name":"Ryder Joe E Etal",
    "wof:placetype":"venue"
},
  "geometry": {"coordinates":[-83.99771,34.117367],"type":"Point"}
}