{
  "type": "Feature",
  "properties": {
    "addr:full":"3293 Laventure Dr Atlanta GA 30341",
    "addr:housenumber":"3293",
    "addr:postcode":"30341",
    "addr:street":"Laventure Dr",
    "iso:country":"US",
    "sg:address":"3293 Laventure Dr",
    "sg:city":"Atlanta",
    "sg:classifiers":[
        {
            "category":"Retail",
            "subcategory":"Auto Repair",
            "type":"Services"
        }
    ],
    "sg:phone":"+1 770 457 0356",
    "sg:postcode":"30341",
    "sg:province":"GA",
    "wof:name":"Eu Auto Service",
    "wof:placetype":"venue"
},
  "geometry": {"coordinates":[-84.28589599999999,33.883801],"type":"Point"}
}