{
  "type": "Feature",
  "properties": {
    "iso:country":"US",
    "sg:address":"126 E 39th St",
    "sg:city":"Savannah",
    "sg:classifiers":[
        {
            "category":"Building & Trades",
            "subcategory":"Cleaning & Sanitation",
            "type":"Services"
        }
    ],
    "sg:phone":"+1 912 484 7627",
    "sg:postcode":"31401",
    "sg:province":"GA",
    "sg:tags":[
        "maintenance"
    ],
    "wof:name":"Soap On A Rope",
    "wof:placetype":"venue"
},
  "geometry": {"coordinates":[-81.09866100000001,32.055041],"type":"Point"}
}