{
  "type": "Feature",
  "properties": {
    "iso:country":"US",
    "sg:address":"194 Jonesboro Rd",
    "sg:city":"Jonesboro",
    "sg:classifiers":[
        {
            "category":"Health Services",
            "subcategory":"Chiropractor",
            "type":"Services"
        }
    ],
    "sg:phone":"+1 770 603 2555",
    "sg:postcode":"30236",
    "sg:province":"GA",
    "wof:name":"Phillips Bonnie Chiroprctr DC",
    "wof:placetype":"venue"
},
  "geometry": {"coordinates":[-84.35320299999999,33.533001],"type":"Point"}
}