{
  "type": "Feature",
  "properties": {
    "iso:country":"US",
    "sg:address":"5522 New Peachtree Rd #127",
    "sg:city":"Atlanta",
    "sg:classifiers":[
        {
            "category":"Food & Beverages",
            "subcategory":"Supermarket",
            "type":"Retail Goods"
        },
        {
            "category":"Food & Beverages",
            "subcategory":"Ethnic Foods",
            "type":"Retail Goods"
        }
    ],
    "sg:phone":"+1 770 216 8616",
    "sg:postcode":"30341",
    "sg:province":"GA",
    "sg:tags":[
        "super",
        "store"
    ],
    "wof:name":"Java Indonesian Foodmart",
    "wof:placetype":"venue"
},
  "geometry": {"coordinates":[-84.29634799999999,33.893721],"type":"Point"}
}