{
  "type": "Feature",
  "properties": {
    "addr:full":"5597 Durrett Dr Atlanta GA 30338",
    "addr:housenumber":"5597",
    "addr:postcode":"30338",
    "addr:street":"Durrett Dr",
    "iso:country":"US",
    "sg:address":"5597 Durrett Dr",
    "sg:city":"Atlanta",
    "sg:classifiers":[
        {
            "category":"Real Estate",
            "subcategory":"Real Estate Agent",
            "type":"Services"
        }
    ],
    "sg:phone":"+1 770 393 1633",
    "sg:postcode":"30338",
    "sg:province":"GA",
    "wof:name":"Joan P Coyle Inc",
    "wof:placetype":"venue"
},
  "geometry": {"coordinates":[-84.31531,33.964879],"type":"Point"}
}