{
  "type": "Feature",
  "properties": {
    "addr:full":"340 Shelli Ln Roswell GA 30075",
    "addr:housenumber":"340",
    "addr:postcode":"30075",
    "addr:street":"Shelli Ln",
    "iso:country":"US",
    "sg:address":"340 Shelli Ln",
    "sg:city":"Roswell",
    "sg:classifiers":[
        {
            "category":"Professional",
            "subcategory":"Computer Services",
            "type":"Services"
        }
    ],
    "sg:phone":"+1 770 552 1762",
    "sg:postcode":"30075",
    "sg:province":"GA",
    "sg:tags":[
        "related"
    ],
    "wof:name":"Progressive Computer System",
    "wof:placetype":"venue"
},
  "geometry": {"coordinates":[-84.36515,34.043662],"type":"Point"}
}