{
  "type": "Feature",
  "properties": {
    "addr:full":"4903 Forsyth Rd Macon GA 31210",
    "addr:housenumber":"4903",
    "addr:postcode":"31210",
    "addr:street":"Forsyth Rd",
    "iso:country":"US",
    "sg:address":"4903 Forsyth Rd",
    "sg:city":"Macon",
    "sg:classifiers":[
        {
            "category":"Banks & Credit Unions",
            "subcategory":"Bank",
            "type":"Services"
        }
    ],
    "sg:phone":"+1 478 477 4040",
    "sg:postcode":"31210",
    "sg:province":"GA",
    "sg:tags":[
        "loan",
        "real estate"
    ],
    "wof:name":"Magestic Mortgage",
    "wof:placetype":"venue"
},
  "geometry": {"coordinates":[-83.724645,32.880378],"type":"Point"}
}