{
  "type": "Feature",
  "properties": {
    "iso:country":"US",
    "sg:address":"985 Twin Springs Rd SE",
    "sg:city":"Dalton",
    "sg:classifiers":[
        {
            "category":"Professional",
            "subcategory":"Employment Agencies",
            "type":"Services"
        }
    ],
    "sg:phone":"+1 706 313 6491",
    "sg:postcode":"30721",
    "sg:province":"GA",
    "sg:tags":[
        "opportunity"
    ],
    "wof:name":"Corporate Solutions Grou",
    "wof:placetype":"venue"
},
  "geometry": {"coordinates":[-84.93947799999999,34.720218],"type":"Point"}
}