{
  "type": "Feature",
  "properties": {
    "addr:full":"1060 Big A Rd S Toccoa GA 30577",
    "addr:housenumber":"1060",
    "addr:postcode":"30577",
    "addr:street":"Big A Rd",
    "iso:country":"US",
    "sg:address":"1060 Big A Rd S",
    "sg:city":"Toccoa",
    "sg:classifiers":[
        {
            "category":"Banks & Credit Unions",
            "subcategory":"Bank",
            "type":"Services"
        }
    ],
    "sg:phone":"+1 706 886 3903",
    "sg:postcode":"30577",
    "sg:province":"GA",
    "wof:name":"Community Bank & Trust Co",
    "wof:placetype":"venue"
},
  "geometry": {"coordinates":[-83.300116,34.566012],"type":"Point"}
}