{
  "type": "Feature",
  "properties": {
    "iso:country":"US",
    "sg:address":"8265 Southport Ter",
    "sg:city":"Duluth",
    "sg:classifiers":[
        {
            "category":"Real Estate",
            "subcategory":"Real Estate Agent",
            "type":"Services"
        }
    ],
    "sg:phone":"+1 678 584 0992",
    "sg:postcode":"30097",
    "sg:province":"GA",
    "wof:name":"B B G H M LLC",
    "wof:placetype":"venue"
},
  "geometry": {"coordinates":[-84.141043,34.074319],"type":"Point"}
}