{
  "type": "Feature",
  "properties": {
    "iso:country":"US",
    "sg:address":"4333 Dunwoody Park",
    "sg:city":"Atlanta",
    "sg:classifiers":[
        {
            "category":"Professional",
            "type":"Services"
        }
    ],
    "sg:phone":"+1 770 392 1718",
    "sg:postcode":"30338",
    "sg:province":"GA",
    "wof:name":"Sharon Bennett Inc",
    "wof:placetype":"venue"
},
  "geometry": {"coordinates":[-84.313773,33.92397],"type":"Point"}
}