{
  "type": "Feature",
  "properties": {
    "addr:full":"1391 Highway 20 W McDonough GA 30253",
    "addr:housenumber":"1391",
    "addr:postcode":"30253",
    "addr:street":"Highway 20 W",
    "iso:country":"US",
    "sg:address":"1391 Highway 20 W",
    "sg:city":"McDonough",
    "sg:classifiers":[
        {
            "category":"Health Services",
            "subcategory":"Dentist",
            "type":"Services"
        }
    ],
    "sg:phone":"+1 770 898 1550",
    "sg:postcode":"30253",
    "sg:province":"GA",
    "sg:tags":[
        "orthodontist"
    ],
    "sg:website":"www.dentfirst.com",
    "wof:name":"Dent First",
    "wof:placetype":"venue"
},
  "geometry": {"coordinates":[-84.183806,33.424493],"type":"Point"}
}