{
  "type": "Feature",
  "properties": {
    "iso:country":"US",
    "sg:address":"401 N Selvidge St",
    "sg:city":"Dalton",
    "sg:classifiers":[
        {
            "category":"Wholesale",
            "subcategory":"Non-durable Goods",
            "type":"Manufacturing & Wholesale Goods"
        }
    ],
    "sg:phone":"+1 706 278 5463",
    "sg:postcode":"30720",
    "sg:province":"GA",
    "sg:tags":[
        "textile",
        "product",
        "fiber",
        "resin"
    ],
    "wof:name":"P S I Ltd",
    "wof:placetype":"venue"
},
  "geometry": {"coordinates":[-84.969807,34.777091],"type":"Point"}
}