{
  "type": "Feature",
  "properties": {
    "iso:country":"US",
    "sg:address":"253 Peters St",
    "sg:city":"Atlanta",
    "sg:classifiers":[
        {
            "category":"Professional",
            "type":"Services"
        },
        {
            "category":"Restaurant",
            "type":"Food & Drink"
        }
    ],
    "sg:phone":"+1 404 523 2121",
    "sg:postcode":"30313",
    "sg:province":"GA",
    "sg:tags":[
        "seafood",
        "caterer"
    ],
    "wof:name":"Baltimore Crab & Seafood",
    "wof:placetype":"venue"
},
  "geometry": {"coordinates":[-84.401608,33.747592],"type":"Point"}
}