{
  "type": "Feature",
  "properties": {
    "addr:full":"119 Ashley Cir Athens GA 30605",
    "addr:housenumber":"119",
    "addr:postcode":"30605",
    "addr:street":"Ashley Cir",
    "iso:country":"US",
    "sg:address":"119 Ashley Cir",
    "sg:city":"Athens",
    "sg:classifiers":[
        {
            "category":"Professional",
            "subcategory":"Management & Consulting",
            "type":"Services"
        }
    ],
    "sg:phone":"+1 706 425 0636",
    "sg:postcode":"30605",
    "sg:province":"GA",
    "sg:tags":[
        "education",
        "consult"
    ],
    "wof:name":"Judkin J Browning",
    "wof:placetype":"venue"
},
  "geometry": {"coordinates":[-83.333878,33.933715],"type":"Point"}
}