{
  "type": "Feature",
  "properties": {
    "addr:full":"190 Fowler Dr Athens GA 30601",
    "addr:housenumber":"190",
    "addr:postcode":"30601",
    "addr:street":"Fowler Dr",
    "iso:country":"US",
    "sg:address":"190 Fowler Dr",
    "sg:city":"Athens",
    "sg:classifiers":[
        {
            "category":"Building & Trades",
            "subcategory":"Construction",
            "type":"Services"
        }
    ],
    "sg:phone":"+1 706 546 0301",
    "sg:postcode":"30601",
    "sg:province":"GA",
    "sg:tags":[
        "heavy",
        "contractor"
    ],
    "wof:name":"Buggs Grading & Backhoe Svc",
    "wof:placetype":"venue"
},
  "geometry": {"coordinates":[-83.362796,33.989033],"type":"Point"}
}