{
  "type": "Feature",
  "properties": {
    "addr:full":"1887 Meadow Ln Decatur GA 30032",
    "addr:housenumber":"1887",
    "addr:postcode":"30032",
    "addr:street":"Meadow Ln",
    "iso:country":"US",
    "sg:address":"1887 Meadow Ln",
    "sg:city":"Decatur",
    "sg:classifiers":[
        {
            "category":"Organizations",
            "subcategory":"Religious Organization",
            "type":"Services"
        }
    ],
    "sg:phone":"+1 404 284 0730",
    "sg:postcode":"30032",
    "sg:province":"GA",
    "wof:name":"Elohim Ministries",
    "wof:placetype":"venue"
},
  "geometry": {"coordinates":[-84.270937,33.735551],"type":"Point"}
}