{
  "type": "Feature",
  "properties": {
    "addr:full":"188 Miller Rd Montezuma GA 31063",
    "addr:housenumber":"188",
    "addr:postcode":"31063",
    "addr:street":"Miller Rd",
    "iso:country":"US",
    "sg:address":"188 Miller Rd",
    "sg:city":"Montezuma",
    "sg:classifiers":[
        {
            "category":"Manufacturing",
            "subcategory":"Buildings",
            "type":"Manufacturing & Wholesale Goods"
        },
        {
            "category":"Building & Trades",
            "subcategory":"Construction",
            "type":"Services"
        }
    ],
    "sg:phone":"+1 478 472 8341",
    "sg:postcode":"31063",
    "sg:province":"GA",
    "sg:tags":[
        "home",
        "builder",
        "contractor"
    ],
    "wof:name":"Miller's Construction",
    "wof:placetype":"venue"
},
  "geometry": {"coordinates":[-83.95366300000001,32.30877],"type":"Point"}
}