{
  "type": "Feature",
  "properties": {
    "iso:country":"US",
    "sg:address":"851 Burns Walk Ct NW",
    "sg:city":"Lilburn",
    "sg:classifiers":[
        {
            "category":"Real Estate",
            "subcategory":"Real Estate Agent",
            "type":"Services"
        }
    ],
    "sg:phone":"+1 678 580 2212",
    "sg:postcode":"30047",
    "sg:province":"GA",
    "sg:tags":[
        "investment"
    ],
    "wof:name":"Punic Properties  LLC",
    "wof:placetype":"venue"
},
  "geometry": {"coordinates":[-84.15026,33.904666],"type":"Point"}
}