{
  "type": "Feature",
  "properties": {
    "iso:country":"US",
    "sg:address":"514 Flat Shoals Ave SE",
    "sg:city":"Atlanta",
    "sg:classifiers":[
        {
            "category":"Education",
            "subcategory":"School",
            "type":"Public Place"
        }
    ],
    "sg:phone":"+1 404 371 9992",
    "sg:postcode":"30316",
    "sg:province":"GA",
    "wof:name":"Georgia Charter Schools Assn",
    "wof:placetype":"venue"
},
  "geometry": {"coordinates":[-84.346987,33.741894],"type":"Point"}
}