{
  "type": "Feature",
  "properties": {
    "addr:full":"700 Feagin Mill Rd Warner Robins GA 31088",
    "addr:housenumber":"700",
    "addr:postcode":"31088",
    "addr:street":"Feagin Mill Rd",
    "iso:country":"US",
    "sg:address":"700 Feagin Mill Rd",
    "sg:city":"Warner Robins",
    "sg:classifiers":[
        {
            "category":"Shopping",
            "subcategory":"Beauty & Cosmetics",
            "type":"Retail Goods"
        }
    ],
    "sg:phone":"+1 478 225 9954",
    "sg:postcode":"31088",
    "sg:province":"GA",
    "sg:tags":[
        "supply"
    ],
    "wof:name":"478 Salon & Beauty Supply",
    "wof:placetype":"venue"
},
  "geometry": {"coordinates":[-83.654735,32.571753],"type":"Point"}
}