{
  "type": "Feature",
  "properties": {
    "addr:full":"1630 Satellite Blvd Ste 560 Duluth GA 30097",
    "addr:housenumber":"1630",
    "addr:postcode":"30097",
    "addr:street":"Satellite Blvd Ste 560",
    "iso:country":"US",
    "sg:address":"1630 Satellite Blvd Ste 560",
    "sg:city":"Duluth",
    "sg:classifiers":[
        {
            "category":"Home & Garden",
            "subcategory":"Household Appliances",
            "type":"Retail Goods"
        }
    ],
    "sg:phone":"+1 770 232 7137",
    "sg:postcode":"30097",
    "sg:province":"GA",
    "sg:tags":[
        "repair"
    ],
    "wof:name":"Climatic Corporation the",
    "wof:placetype":"venue"
},
  "geometry": {"coordinates":[-84.08380099999999,33.999802],"type":"Point"}
}