{
  "type": "Feature",
  "properties": {
    "iso:country":"US",
    "sg:address":"2411 State Rte 21",
    "sg:city":"Rincon",
    "sg:classifiers":[
        {
            "category":"Building & Trades",
            "subcategory":"Construction",
            "type":"Services"
        }
    ],
    "sg:phone":"+1 912 754 1733",
    "sg:postcode":"31326",
    "sg:province":"GA",
    "wof:name":"Wood Works Mfg",
    "wof:placetype":"venue"
},
  "geometry": {"coordinates":[-81.261304,32.340837],"type":"Point"}
}