{
  "type": "Feature",
  "properties": {
    "iso:country":"US",
    "sg:address":"20 Golf Cir NE",
    "sg:city":"Atlanta",
    "sg:classifiers":[
        {
            "category":"Building & Trades",
            "subcategory":"Construction",
            "type":"Services"
        }
    ],
    "sg:phone":"+1 404 892 2177",
    "sg:postcode":"30309",
    "sg:province":"GA",
    "sg:tags":[
        "fiber",
        "optic",
        "cable",
        "contractor"
    ],
    "wof:name":"Ace Inc",
    "wof:placetype":"venue"
},
  "geometry": {"coordinates":[-84.375468,33.80175],"type":"Point"}
}