{
  "type": "Feature",
  "properties": {
    "iso:country":"US",
    "sg:address":"592 John Dasher Rd",
    "sg:city":"Lyons",
    "sg:classifiers":[
        {
            "category":"Insurance",
            "subcategory":"Hazard Insurance",
            "type":"Services"
        }
    ],
    "sg:phone":"+1 912 565 8318",
    "sg:postcode":"30436",
    "sg:province":"GA",
    "wof:name":"Christopher Allen Hopkins",
    "wof:placetype":"venue"
},
  "geometry": {"coordinates":[-82.277407,32.031518],"type":"Point"}
}