{
  "type": "Feature",
  "properties": {
    "addr:full":"403 Old Mill Rd Cartersville GA 30120",
    "addr:housenumber":"403",
    "addr:postcode":"30120",
    "addr:street":"Old Mill Rd",
    "iso:country":"US",
    "sg:address":"403 Old Mill Rd",
    "sg:city":"Cartersville",
    "sg:classifiers":[
        {
            "category":"Manufacturing",
            "subcategory":"Printing",
            "type":"Manufacturing & Wholesale Goods"
        }
    ],
    "sg:phone":"+1 770 607 8388",
    "sg:postcode":"30120",
    "sg:province":"GA",
    "sg:tags":[
        "commercial"
    ],
    "wof:name":"Basic Printing & Rubber Stamps",
    "wof:placetype":"venue"
},
  "geometry": {"coordinates":[-84.81153500000001,34.151089],"type":"Point"}
}