{
  "type": "Feature",
  "properties": {
    "addr:full":"206 Hobbs Mill Rd Dearing GA 30808",
    "addr:housenumber":"206",
    "addr:postcode":"30808",
    "addr:street":"Hobbs Mill Rd",
    "iso:country":"US",
    "sg:address":"206 Hobbs Mill Rd",
    "sg:city":"Dearing",
    "sg:classifiers":[
        {
            "category":"Wholesale",
            "subcategory":"Meat",
            "type":"Manufacturing & Wholesale Goods"
        }
    ],
    "sg:phone":"+1 706 595 3777",
    "sg:postcode":"30808",
    "sg:province":"GA",
    "wof:name":"Happy Valley Processing Co",
    "wof:placetype":"venue"
},
  "geometry": {"coordinates":[-82.46402999999999,33.369273],"type":"Point"}
}