{
  "type": "Feature",
  "properties": {
    "addr:full":"4336 Moonlight Walk Lilburn GA 30047",
    "addr:housenumber":"4336",
    "addr:postcode":"30047",
    "addr:street":"Moonlight Walk",
    "iso:country":"US",
    "sg:address":"4336 Moonlight Walk",
    "sg:city":"Lilburn",
    "sg:classifiers":[
        {
            "category":"Structure",
            "subcategory":"Office Building",
            "type":"Public Place"
        }
    ],
    "sg:phone":"+1 770 551 1517",
    "sg:postcode":"30047",
    "sg:province":"GA",
    "sg:tags":[
        "park"
    ],
    "wof:name":"Akthar Properties",
    "wof:placetype":"venue"
},
  "geometry": {"coordinates":[-84.10654100000001,33.873276],"type":"Point"}
}