{
  "type": "Feature",
  "properties": {
    "iso:country":"US",
    "sg:address":"11 Tasso Cir",
    "sg:city":"Dallas",
    "sg:classifiers":[
        {
            "category":"Real Estate",
            "subcategory":"Real Estate Agent",
            "type":"Services"
        }
    ],
    "sg:phone":"+1 770 505 5900",
    "sg:postcode":"30161",
    "sg:province":"GA",
    "wof:name":"ERA Adventure Properties",
    "wof:placetype":"venue"
},
  "geometry": {"coordinates":[-85.141722,34.268064],"type":"Point"}
}