{
  "type": "Feature",
  "properties": {
    "iso:country":"US",
    "sg:address":"2720 US Hwy 341",
    "sg:city":"Clinchfield",
    "sg:classifiers":[
        {
            "category":"Wholesale",
            "subcategory":"Scrap",
            "type":"Manufacturing & Wholesale Goods"
        }
    ],
    "sg:phone":"+1 478 218 0293",
    "sg:postcode":"31030",
    "sg:province":"GA",
    "sg:tags":[
        "recycling",
        "center"
    ],
    "wof:name":"Tennessee Tire Recyclers Inc",
    "wof:placetype":"venue"
},
  "geometry": {"coordinates":[-83.88708200000001,32.567638],"type":"Point"}
}