{
  "type": "Feature",
  "properties": {
    "iso:country":"US",
    "sg:address":"310 Montgomery St",
    "sg:city":"Savannah",
    "sg:classifiers":[
        {
            "category":"Insurance",
            "subcategory":"Insurance Agent",
            "type":"Services"
        }
    ],
    "sg:phone":"+1 912 927 8002",
    "sg:postcode":"31401",
    "sg:province":"GA",
    "wof:name":"Collins and Company",
    "wof:placetype":"venue"
},
  "geometry": {"coordinates":[-81.097984,32.075519],"type":"Point"}
}