{
  "type": "Feature",
  "properties": {
    "addr:full":"2301 Morrison Rd SW Conyers GA 30094",
    "addr:housenumber":"2301",
    "addr:postcode":"30094",
    "addr:street":"Morrison Rd Sw",
    "iso:country":"US",
    "sg:address":"2301 Morrison Rd SW",
    "sg:city":"Conyers",
    "sg:classifiers":[
        {
            "category":"Health Services",
            "subcategory":"Hospital",
            "type":"Services"
        }
    ],
    "sg:phone":"+1 770 929 0459",
    "sg:postcode":"30094",
    "sg:province":"GA",
    "wof:name":"Ga Elks Aidmore Children's Center",
    "wof:placetype":"venue"
},
  "geometry": {"coordinates":[-84.05789900000001,33.6152],"type":"Point"}
}