{
  "type": "Feature",
  "properties": {
    "addr:full":"3070 Presidential Dr Atlanta GA 30340",
    "addr:housenumber":"3070",
    "addr:postcode":"30340",
    "addr:street":"Presidential Dr",
    "iso:country":"US",
    "sg:address":"3070 Presidential Dr",
    "sg:city":"Atlanta",
    "sg:classifiers":[
        {
            "category":"Personal",
            "type":"Services"
        }
    ],
    "sg:phone":"+1 404 492 6889",
    "sg:postcode":"30340",
    "sg:province":"GA",
    "sg:tags":[
        "mover"
    ],
    "sg:website":"www.milestonerelocation.com/atlanta",
    "wof:name":"Milestone Relocation Solutions",
    "wof:placetype":"venue"
},
  "geometry": {"coordinates":[-84.263228,33.886786],"type":"Point"}
}