{
  "type": "Feature",
  "properties": {
    "iso:country":"US",
    "sg:address":"918 Marietta Blvd NW",
    "sg:city":"Atlanta",
    "sg:classifiers":[
        {
            "category":"Communications",
            "type":"Services"
        }
    ],
    "sg:phone":"+1 404 794 0682",
    "sg:postcode":"30318",
    "sg:province":"GA",
    "wof:name":"Vitel Communications LLC",
    "wof:placetype":"venue"
},
  "geometry": {"coordinates":[-84.42789999999999,33.785802],"type":"Point"}
}