{
  "type": "Feature",
  "properties": {
    "addr:full":"3360 Venture Pkwy Duluth GA 30096",
    "addr:housenumber":"3360",
    "addr:postcode":"30096",
    "addr:street":"Venture Pkwy",
    "iso:country":"US",
    "sg:address":"3360 Venture Pkwy",
    "sg:city":"Duluth",
    "sg:classifiers":[
        {
            "category":"Shopping",
            "subcategory":"Department Store",
            "type":"Retail Goods"
        }
    ],
    "sg:phone":"+1 770 623 2200",
    "sg:postcode":"30096",
    "sg:province":"GA",
    "sg:website":"http://www.macys.com",
    "wof:name":"Macy's",
    "wof:placetype":"venue"
},
  "geometry": {"coordinates":[-84.125502,33.956229],"type":"Point"}
}