{
  "type": "Feature",
  "properties": {
    "iso:country":"US",
    "sg:address":"45 Melody Ridge",
    "sg:city":"Covington",
    "sg:classifiers":[
        {
            "category":"Real Estate",
            "subcategory":"Real Estate Agent",
            "type":"Services"
        }
    ],
    "sg:phone":"+1 770 787 0357",
    "sg:postcode":"30014",
    "sg:province":"GA",
    "wof:name":"Cowan Property Management Co L",
    "wof:placetype":"venue"
},
  "geometry": {"coordinates":[-83.77628799999999,33.596768],"type":"Point"}
}