{
  "type": "Feature",
  "properties": {
    "iso:country":"US",
    "sg:address":"3477 Winter Chase Dr",
    "sg:city":"Marietta",
    "sg:classifiers":[
        {
            "category":"Building & Trades",
            "subcategory":"Locksmith",
            "type":"Services"
        }
    ],
    "sg:phone":"+1 770 250 0491",
    "sg:postcode":"30062",
    "sg:province":"GA",
    "sg:tags":[
        "key"
    ],
    "wof:name":"1 & 24 Hour A A A Locksmith",
    "wof:placetype":"venue"
},
  "geometry": {"coordinates":[-84.447705,34.035794],"type":"Point"}
}