{
  "type": "Feature",
  "properties": {
    "iso:country":"US",
    "sg:address":"27 Collins Dr",
    "sg:city":"Cartersville",
    "sg:classifiers":[
        {
            "category":"Personal",
            "subcategory":"Tanning Parlor",
            "type":"Services"
        }
    ],
    "sg:phone":"+1 770 607 8973",
    "sg:postcode":"30120",
    "sg:province":"GA",
    "sg:tags":[
        "salon"
    ],
    "sg:website":"http://www.southernexposuretan.com",
    "wof:name":"Southern Exposure Tanning",
    "wof:placetype":"venue"
},
  "geometry": {"coordinates":[-84.796784,34.194903],"type":"Point"}
}