{
  "type": "Feature",
  "properties": {
    "iso:country":"US",
    "sg:address":"1040 Vijay Dr",
    "sg:city":"Atlanta",
    "sg:classifiers":[
        {
            "category":"Shopping",
            "subcategory":"Hobbies, Toys, & Games",
            "type":"Retail Goods"
        },
        {
            "category":"Retail",
            "subcategory":"Auto Repair",
            "type":"Services"
        }
    ],
    "sg:phone":"+1 770 458 1755",
    "sg:postcode":"30341",
    "sg:province":"GA",
    "sg:tags":[
        "repairing",
        "automotive",
        "automobile"
    ],
    "wof:name":"Toyonly",
    "wof:placetype":"venue"
},
  "geometry": {"coordinates":[-84.31358899999999,33.882423],"type":"Point"}
}