{
  "type": "Feature",
  "properties": {
    "iso:country":"US",
    "sg:address":"3573 Due West Rd NW",
    "sg:city":"Marietta",
    "sg:classifiers":[
        {
            "category":"Professional",
            "subcategory":"Management & Consulting",
            "type":"Services"
        }
    ],
    "sg:phone":"+1 770 422 5050",
    "sg:postcode":"30064",
    "sg:province":"GA",
    "wof:name":"Acquisition Services",
    "wof:placetype":"venue"
},
  "geometry": {"coordinates":[-84.65686599999999,33.957339],"type":"Point"}
}