{
  "type": "Feature",
  "properties": {
    "iso:country":"US",
    "sg:address":"1661 James Jackson Pkwy NW",
    "sg:city":"Atlanta",
    "sg:classifiers":[
        {
            "category":"Organizations",
            "subcategory":"Community Association",
            "type":"Services"
        }
    ],
    "sg:phone":"+1 404 794 2454",
    "sg:postcode":"30318",
    "sg:province":"GA",
    "sg:tags":[
        "youth",
        "org"
    ],
    "wof:name":"Butler Street Y",
    "wof:placetype":"venue"
},
  "geometry": {"coordinates":[-84.475176,33.798512],"type":"Point"}
}