{
  "type": "Feature",
  "properties": {
    "iso:country":"US",
    "sg:address":"705 Old Dalton Rd NE",
    "sg:city":"Rome",
    "sg:classifiers":[
        {
            "category":"Building & Trades",
            "subcategory":"Construction",
            "type":"Services"
        }
    ],
    "sg:phone":"+1 706 235 3400",
    "sg:postcode":"30165",
    "sg:province":"GA",
    "sg:tags":[
        "contractor"
    ],
    "wof:name":"Gutter Masters",
    "wof:placetype":"venue"
},
  "geometry": {"coordinates":[-85.163477,34.322933],"type":"Point"}
}