{
  "type": "Feature",
  "properties": {
    "iso:country":"US",
    "sg:address":"4520 Old Stilesboro Rd",
    "sg:city":"Acworth",
    "sg:classifiers":[
        {
            "category":"Shopping",
            "type":"Retail Goods"
        }
    ],
    "sg:phone":"+1 770 974 1315",
    "sg:postcode":"30101",
    "sg:province":"GA",
    "sg:tags":[
        "merchandise"
    ],
    "wof:name":"House of Bargains 2",
    "wof:placetype":"venue"
},
  "geometry": {"coordinates":[-84.68307900000001,34.010728],"type":"Point"}
}