{
  "type": "Feature",
  "properties": {
    "iso:country":"US",
    "sg:address":"3639 Peachtree Road NE",
    "sg:city":"Atlanta",
    "sg:classifiers":[
        {
            "category":"Retail",
            "subcategory":"Auto Repair",
            "type":"Services"
        }
    ],
    "sg:phone":"+1 404 266 1554",
    "sg:postcode":"30319",
    "sg:province":"GA",
    "wof:name":"Bp Oil Company",
    "wof:placetype":"venue"
},
  "geometry": {"coordinates":[-84.356931,33.854155],"type":"Point"}
}