{
  "type": "Feature",
  "properties": {
    "iso:country":"US",
    "sg:address":"500 Riley St",
    "sg:city":"Fort Valley",
    "sg:classifiers":[
        {
            "category":"Social Services",
            "type":"Services"
        }
    ],
    "sg:phone":"+1 478 825 1800",
    "sg:postcode":"31030",
    "sg:province":"GA",
    "sg:tags":[
        "youth",
        "organization",
        "center"
    ],
    "wof:name":"Boy & Girls Clubs-Peach County",
    "wof:placetype":"venue"
},
  "geometry": {"coordinates":[-83.89120699999999,32.557235],"type":"Point"}
}