{
  "type": "Feature",
  "properties": {
    "iso:country":"US",
    "sg:address":"317 W Blackshear Ave",
    "sg:city":"Waycross",
    "sg:classifiers":[
        {
            "category":"Social Services",
            "subcategory":"Child Care",
            "type":"Services"
        }
    ],
    "sg:phone":"+1 912 283 1191",
    "sg:postcode":"31501",
    "sg:province":"GA",
    "sg:tags":[
        "day"
    ],
    "wof:name":"Noah's Ark Daycare",
    "wof:placetype":"venue"
},
  "geometry": {"coordinates":[-82.37275099999999,31.235666],"type":"Point"}
}