{
  "type": "Feature",
  "properties": {
    "addr:full":"220 Gaskin Ave S Douglas GA 31533",
    "addr:housenumber":"220",
    "addr:postcode":"31533",
    "addr:street":"Gaskin Ave S",
    "iso:country":"US",
    "sg:address":"220 Gaskin Ave S",
    "sg:city":"Douglas",
    "sg:classifiers":[
        {
            "category":"Professional",
            "subcategory":"Engineering",
            "type":"Services"
        }
    ],
    "sg:phone":"+1 912 384 7723",
    "sg:postcode":"31533",
    "sg:province":"GA",
    "sg:tags":[
        "engineer"
    ],
    "wof:name":"Statewide Surveying Co",
    "wof:placetype":"venue"
},
  "geometry": {"coordinates":[-82.845083,31.507862],"type":"Point"}
}