{
  "type": "Feature",
  "properties": {
    "addr:full":"905 K St Brunswick GA 31520",
    "addr:housenumber":"905",
    "addr:postcode":"31520",
    "addr:street":"K St",
    "iso:country":"US",
    "sg:address":"905 K St",
    "sg:city":"Brunswick",
    "sg:classifiers":[
        {
            "category":"Organizations",
            "subcategory":"Religious Organization",
            "type":"Services"
        }
    ],
    "sg:phone":"+1 912 265 2990",
    "sg:postcode":"31520",
    "sg:province":"GA",
    "wof:name":"Fishers of Men World Harvest",
    "wof:placetype":"venue"
},
  "geometry": {"coordinates":[-81.493239,31.158505],"type":"Point"}
}