{
  "type": "Feature",
  "properties": {
    "addr:full":"16 Panther Ln Savannah GA 31419",
    "addr:housenumber":"16",
    "addr:postcode":"31419",
    "addr:street":"Panther Ln",
    "iso:country":"US",
    "sg:address":"16 Panther Ln",
    "sg:city":"Savannah",
    "sg:classifiers":[
        {
            "category":"Home & Garden",
            "subcategory":"Building Materials",
            "type":"Retail Goods"
        }
    ],
    "sg:phone":"+1 912 748 0767",
    "sg:postcode":"31419",
    "sg:province":"GA",
    "wof:name":"J & B Millwork",
    "wof:placetype":"venue"
},
  "geometry": {"coordinates":[-81.32291499999999,32.027849],"type":"Point"}
}