{
  "type": "Feature",
  "properties": {
    "iso:country":"US",
    "sg:address":"415 Soperton Ave",
    "sg:city":"Dublin",
    "sg:classifiers":[
        {
            "category":"Food & Beverages",
            "subcategory":"Groceries & Convenience Stores",
            "type":"Retail Goods"
        }
    ],
    "sg:phone":"+1 478 275 4863",
    "sg:postcode":"31027",
    "sg:province":"GA",
    "wof:name":"Friendly Gus Number 19",
    "wof:placetype":"venue"
},
  "geometry": {"coordinates":[-82.865365,32.543482],"type":"Point"}
}