{
  "type": "Feature",
  "properties": {
    "iso:country":"US",
    "sg:address":"226 S Broad St",
    "sg:city":"Bainbridge",
    "sg:classifiers":[
        {
            "category":"Banks & Credit Unions",
            "subcategory":"Bank",
            "type":"Services"
        }
    ],
    "sg:phone":"+1 229 248 3800",
    "sg:postcode":"39817",
    "sg:province":"GA",
    "sg:website":"www.parkavebank.com",
    "wof:name":"Park Avenue Bank",
    "wof:placetype":"venue"
},
  "geometry": {"coordinates":[-84.57571,30.904876],"type":"Point"}
}