{
  "type": "Feature",
  "properties": {
    "iso:country":"US",
    "sg:address":"3124 N Decatur Rd",
    "sg:city":"Scottdale",
    "sg:classifiers":[
        {
            "category":"Autos & Motor Vehicles",
            "subcategory":"Automobile Sales",
            "type":"Retail Goods"
        }
    ],
    "sg:phone":"+1 678 733 9774",
    "sg:postcode":"30079",
    "sg:province":"GA",
    "sg:tags":[
        "used",
        "car",
        "dealers-used",
        "new",
        "cars-wholesale"
    ],
    "sg:website":"http://atlanta.citysearch.com/profile/external/43844485/scottdale_ga/autostar_finance.html?publisher=yellowpages&reference_id=15&placement=ypwebsitemip",
    "wof:name":"AutoStar Finance",
    "wof:placetype":"venue"
},
  "geometry": {"coordinates":[-84.26496899999999,33.793591],"type":"Point"}
}