{
  "type": "Feature",
  "properties": {
    "addr:full":"10921 Hwy 36 Covington GA 30014",
    "addr:housenumber":"10921",
    "addr:postcode":"30014",
    "addr:street":"Hwy 36",
    "iso:country":"US",
    "sg:address":"10921 Hwy 36",
    "sg:city":"Covington",
    "sg:classifiers":[
        {
            "category":"Real Estate",
            "subcategory":"Real Estate Operator",
            "type":"Services"
        }
    ],
    "sg:phone":"+1 770 784 1821",
    "sg:postcode":"30014",
    "sg:province":"GA",
    "sg:tags":[
        "mobile",
        "home",
        "community"
    ],
    "wof:name":"Alcovy Mobile Home Park",
    "wof:placetype":"venue"
},
  "geometry": {"coordinates":[-83.847544,33.552846],"type":"Point"}
}