{
  "type": "Feature",
  "properties": {
    "iso:country":"US",
    "sg:address":"375 Hammock Rd NW",
    "sg:city":"Milledgeville",
    "sg:classifiers":[
        {
            "category":"Banks & Credit Unions",
            "subcategory":"Bank",
            "type":"Services"
        }
    ],
    "sg:phone":"+1 478 452 0430",
    "sg:postcode":"31061",
    "sg:province":"GA",
    "wof:name":"Mid South Federal CREDIT Union",
    "wof:placetype":"venue"
},
  "geometry": {"coordinates":[-83.253203,33.098035],"type":"Point"}
}