{
  "type": "Feature",
  "properties": {
    "addr:full":"12926 Highway 92 Woodstock GA 30188",
    "addr:housenumber":"12926",
    "addr:postcode":"30188",
    "addr:street":"Highway 92",
    "iso:country":"US",
    "sg:address":"12926 Highway 92",
    "sg:city":"Woodstock",
    "sg:classifiers":[
        {
            "category":"Health Services",
            "subcategory":"Chiropractor",
            "type":"Services"
        }
    ],
    "sg:phone":"+1 678 388 7671",
    "sg:postcode":"30188",
    "sg:province":"GA",
    "wof:name":"Georgia Chiropractic Group Llc",
    "wof:placetype":"venue"
},
  "geometry": {"coordinates":[-84.46768899999999,34.087017],"type":"Point"}
}