{
  "type": "Feature",
  "properties": {
    "addr:full":"5 George C Wilson Ct Augusta GA 30909",
    "addr:housenumber":"5",
    "addr:postcode":"30909",
    "addr:street":"George C Wilson Ct",
    "iso:country":"US",
    "sg:address":"5 George C Wilson Ct",
    "sg:city":"Augusta",
    "sg:classifiers":[
        {
            "category":"Professional",
            "subcategory":"Lawyer & Legal Services",
            "type":"Services"
        }
    ],
    "sg:phone":"+1 706 650 1257",
    "sg:postcode":"30909",
    "sg:province":"GA",
    "sg:tags":[
        "attorney"
    ],
    "wof:name":"John I Harper PC",
    "wof:placetype":"venue"
},
  "geometry": {"coordinates":[-82.08769100000001,33.482223],"type":"Point"}
}