{
  "type": "Feature",
  "properties": {
    "addr:full":"25 N Beulah St Winder GA 30680",
    "addr:housenumber":"25",
    "addr:postcode":"30680",
    "addr:street":"N Beulah St",
    "iso:country":"US",
    "sg:address":"25 N Beulah St",
    "sg:city":"Winder",
    "sg:classifiers":[
        {
            "category":"Building & Trades",
            "subcategory":"Pest Control",
            "type":"Services"
        }
    ],
    "sg:phone":"+1 770 922 7924",
    "sg:postcode":"30680",
    "sg:province":"GA",
    "wof:name":"Winder Pest Control",
    "wof:placetype":"venue"
},
  "geometry": {"coordinates":[-83.72522499999999,33.993286],"type":"Point"}
}