{
  "type": "Feature",
  "properties": {
    "addr:full":"511 Etowah St Acworth GA 30102",
    "addr:housenumber":"511",
    "addr:postcode":"30102",
    "addr:street":"Etowah St",
    "iso:country":"US",
    "sg:address":"511 Etowah St",
    "sg:city":"Acworth",
    "sg:classifiers":[
        {
            "category":"Manufacturing",
            "subcategory":"Printing",
            "type":"Manufacturing & Wholesale Goods"
        }
    ],
    "sg:phone":"+1 770 917 1898",
    "sg:postcode":"30102",
    "sg:province":"GA",
    "sg:tags":[
        "publishing"
    ],
    "wof:name":"Ocean Wave Publishing Inc",
    "wof:placetype":"venue"
},
  "geometry": {"coordinates":[-84.641338,34.12483],"type":"Point"}
}