{
  "type": "Feature",
  "properties": {
    "iso:country":"US",
    "sg:address":"2248 Cloverdale Dr SE",
    "sg:city":"Atlanta",
    "sg:classifiers":[
        {
            "category":"Professional",
            "subcategory":"Business Services",
            "type":"Services"
        }
    ],
    "sg:phone":"+1 404 627 2625",
    "sg:postcode":"30316",
    "sg:province":"GA",
    "sg:tags":[
        "fashion",
        "designer"
    ],
    "wof:name":"Mayes Custom Tailing",
    "wof:placetype":"venue"
},
  "geometry": {"coordinates":[-84.339569,33.727942],"type":"Point"}
}