{
  "type": "Feature",
  "properties": {
    "iso:country":"US",
    "sg:address":"3000 Centre Pkwy Ste 100",
    "sg:city":"Atlanta",
    "sg:classifiers":[
        {
            "category":"Professional",
            "subcategory":"Business Services",
            "type":"Services"
        }
    ],
    "sg:phone":"+1 404 836 4000",
    "sg:postcode":"30344",
    "sg:province":"GA",
    "sg:tags":[
        "mail",
        "shipping"
    ],
    "sg:website":"http://www.mailexpressinc.com",
    "wof:name":"Streamlite, Inc.",
    "wof:placetype":"venue"
},
  "geometry": {"coordinates":[-84.505454,33.652331],"type":"Point"}
}