{
  "type": "Feature",
  "properties": {
    "addr:full":"70 Piper Rd Covington GA 30014",
    "addr:housenumber":"70",
    "addr:postcode":"30014",
    "addr:street":"Piper Rd",
    "iso:country":"US",
    "sg:address":"70 Piper Rd",
    "sg:city":"Covington",
    "sg:classifiers":[
        {
            "category":"Education",
            "subcategory":"School",
            "type":"Public Place"
        }
    ],
    "sg:phone":"+1 770 788 1990",
    "sg:postcode":"30014",
    "sg:province":"GA",
    "wof:name":"Anointed Word Christian School",
    "wof:placetype":"venue"
},
  "geometry": {"coordinates":[-83.84733300000001,33.560378],"type":"Point"}
}