{
  "type": "Feature",
  "properties": {
    "iso:country":"US",
    "sg:address":"204 E Walker St",
    "sg:city":"Thomaston",
    "sg:classifiers":[
        {
            "category":"Building & Trades",
            "subcategory":"Electrical",
            "type":"Services"
        }
    ],
    "sg:phone":"+1 706 648 6493",
    "sg:postcode":"30286",
    "sg:province":"GA",
    "sg:tags":[
        "booth",
        "equipment",
        "telephone",
        "pay"
    ],
    "wof:name":"Equity Pay Telephone Co Inc",
    "wof:placetype":"venue"
},
  "geometry": {"coordinates":[-84.325166,32.892723],"type":"Point"}
}