{
  "type": "Feature",
  "properties": {
    "iso:country":"US",
    "sg:address":"1447 Jackson Rd",
    "sg:city":"Augusta",
    "sg:classifiers":[
        {
            "category":"Education",
            "subcategory":"Library",
            "type":"Public Place"
        }
    ],
    "sg:phone":"+1 706 736 6758",
    "sg:postcode":"30909",
    "sg:province":"GA",
    "wof:name":"Friedman Branch",
    "wof:placetype":"venue"
},
  "geometry": {"coordinates":[-82.069368,33.472663],"type":"Point"}
}