{
  "type": "Feature",
  "properties": {
    "addr:full":"323 Brentwood Cir Brunswick GA 31523",
    "addr:housenumber":"323",
    "addr:postcode":"31523",
    "addr:street":"Brentwood Cir",
    "iso:country":"US",
    "sg:address":"323 Brentwood Cir",
    "sg:city":"Brunswick",
    "sg:classifiers":[
        {
            "category":"Retail",
            "subcategory":"Laundry & Dry Cleaning",
            "type":"Services"
        }
    ],
    "sg:phone":"+1 912 262 0660",
    "sg:postcode":"31523",
    "sg:province":"GA",
    "sg:tags":[
        "cleaners",
        "rug",
        "carpet"
    ],
    "wof:name":"Massey's Chem-Dry Carpet Clng",
    "wof:placetype":"venue"
},
  "geometry": {"coordinates":[-81.551081,31.188548],"type":"Point"}
}