{
  "type": "Feature",
  "properties": {
    "addr:full":"2082 Kinsmon Dr Marietta GA 30062",
    "addr:housenumber":"2082",
    "addr:postcode":"30062",
    "addr:street":"Kinsmon Dr",
    "iso:country":"US",
    "sg:address":"2082 Kinsmon Dr",
    "sg:city":"Marietta",
    "sg:classifiers":[
        {
            "category":"Building & Trades",
            "subcategory":"Construction",
            "type":"Services"
        }
    ],
    "sg:phone":"+1 770 641 0063",
    "sg:postcode":"30062",
    "sg:province":"GA",
    "sg:tags":[
        "house"
    ],
    "wof:name":"Automatic Construction Tech",
    "wof:placetype":"venue"
},
  "geometry": {"coordinates":[-84.41799,33.994785],"type":"Point"}
}