{
  "type": "Feature",
  "properties": {
    "addr:full":"3778 Lavista Rd Tucker GA 30084",
    "addr:housenumber":"3778",
    "addr:postcode":"30084",
    "addr:street":"Lavista Rd",
    "iso:country":"US",
    "sg:address":"3778 Lavista Rd",
    "sg:city":"Tucker",
    "sg:classifiers":[
        {
            "category":"Building & Trades",
            "subcategory":"Construction",
            "type":"Services"
        }
    ],
    "sg:phone":"+1 404 320 8395",
    "sg:postcode":"30084",
    "sg:province":"GA",
    "sg:tags":[
        "general",
        "contractor"
    ],
    "wof:name":"Lighthouse Communities",
    "wof:placetype":"venue"
},
  "geometry": {"coordinates":[-84.26126499999999,33.840961],"type":"Point"}
}