{
  "type": "Feature",
  "properties": {
    "addr:full":"2001 Lawrenceville Suwanee Rd Suwanee GA 30024",
    "addr:housenumber":"2001",
    "addr:postcode":"30024",
    "addr:street":"Lawrenceville Suwanee Rd",
    "iso:country":"US",
    "sg:address":"2001 Lawrenceville Suwanee Rd",
    "sg:city":"Suwanee",
    "sg:classifiers":[
        {
            "category":"Personal",
            "subcategory":"Nail Salon",
            "type":"Services"
        }
    ],
    "sg:phone":"+1 770 236 9544",
    "sg:postcode":"30024",
    "sg:province":"GA",
    "wof:name":"Q Nails",
    "wof:placetype":"venue"
},
  "geometry": {"coordinates":[-84.053742,34.043705],"type":"Point"}
}