{
  "type": "Feature",
  "properties": {
    "iso:country":"US",
    "sg:address":"3402 Vineville Ave",
    "sg:city":"Macon",
    "sg:classifiers":[
        {
            "category":"Professional",
            "subcategory":"Lawyer & Legal Services",
            "type":"Services"
        }
    ],
    "sg:phone":"+1 478 475 5336",
    "sg:postcode":"31204",
    "sg:province":"GA",
    "sg:tags":[
        "living",
        "attorney",
        "law",
        "estate",
        "wills",
        "elder",
        "planning",
        "trust",
        "probate"
    ],
    "wof:name":"Freeney-Hindsman Peggy Attorney At Law",
    "wof:placetype":"venue"
},
  "geometry": {"coordinates":[-83.681121,32.856447],"type":"Point"}
}