{
  "type": "Feature",
  "properties": {
    "addr:full":"291 Martin Way Marietta GA 30064",
    "addr:housenumber":"291",
    "addr:postcode":"30064",
    "addr:street":"Martin Way",
    "iso:country":"US",
    "sg:address":"291 Martin Way",
    "sg:city":"Marietta",
    "sg:classifiers":[
        {
            "category":"Wholesale",
            "subcategory":"Stationery",
            "type":"Manufacturing & Wholesale Goods"
        }
    ],
    "sg:phone":"+1 770 422 0365",
    "sg:postcode":"30064",
    "sg:province":"GA",
    "sg:tags":[
        "supply"
    ],
    "wof:name":"Precision Forms Promotion",
    "wof:placetype":"venue"
},
  "geometry": {"coordinates":[-84.616286,33.946943],"type":"Point"}
}