{
  "type": "Feature",
  "properties": {
    "iso:country":"US",
    "sg:address":"4590 Deep Creek Dr NE",
    "sg:city":"Buford",
    "sg:classifiers":[
        {
            "category":"Professional",
            "subcategory":"Engineering",
            "type":"Services"
        }
    ],
    "sg:phone":"+1 770 271 8871",
    "sg:postcode":"30518",
    "sg:province":"GA",
    "wof:name":"Black Process Engineering Co",
    "wof:placetype":"venue"
},
  "geometry": {"coordinates":[-84.065198,34.079439],"type":"Point"}
}