{
  "type": "Feature",
  "properties": {
    "addr:full":"2115 Hamilton Creek Pkwy Dacula GA 30019",
    "addr:housenumber":"2115",
    "addr:postcode":"ga 30019",
    "addr:street":"Hamilton Creek Pkwy",
    "iso:country":"US",
    "sg:address":"2115 Hamilton Creek Pkwy",
    "sg:city":"Dacula",
    "sg:classifiers":[
        {
            "category":"Restaurant",
            "type":"Food & Drink"
        }
    ],
    "sg:phone":"+1 678 714 2778",
    "sg:postcode":"30019",
    "sg:province":"GA",
    "wof:name":"Golden Palace Express",
    "wof:placetype":"venue"
},
  "geometry": {"coordinates":[-83.91330000000001,34.0709],"type":"Point"}
}