{
  "type": "Feature",
  "properties": {
    "addr:full":"223 N Broad St Winder GA 30680",
    "addr:housenumber":"223",
    "addr:postcode":"30680",
    "addr:street":"N Broad St",
    "iso:country":"US",
    "sg:address":"223 N Broad St",
    "sg:city":"Winder",
    "sg:classifiers":[
        {
            "category":"Autos & Motor Vehicles",
            "subcategory":"Automobile Sales",
            "type":"Retail Goods"
        }
    ],
    "sg:phone":"+1 770 867 6551",
    "sg:postcode":"30680",
    "sg:province":"GA",
    "sg:tags":[
        "car",
        "dealer"
    ],
    "wof:name":"Yearwood's Used Cars",
    "wof:placetype":"venue"
},
  "geometry": {"coordinates":[-83.71392400000001,33.996588],"type":"Point"}
}