{
  "type": "Feature",
  "properties": {
    "iso:country":"US",
    "sg:address":"501 Jones Ave NW",
    "sg:city":"Atlanta",
    "sg:classifiers":[
        {
            "category":"Building & Trades",
            "subcategory":"Locksmith",
            "type":"Services"
        }
    ],
    "sg:phone":"+1 404 965 0347",
    "sg:postcode":"30314",
    "sg:province":"GA",
    "sg:tags":[
        "key"
    ],
    "wof:name":"A Locksmith 1-24-7",
    "wof:placetype":"venue"
},
  "geometry": {"coordinates":[-84.40366,33.764397],"type":"Point"}
}