{
  "type": "Feature",
  "properties": {
    "iso:country":"US",
    "sg:address":"590 E Main St",
    "sg:city":"Canton",
    "sg:classifiers":[
        {
            "category":"Health Services",
            "subcategory":"Doctor",
            "type":"Services"
        }
    ],
    "sg:phone":"+1 770 345 5641",
    "sg:postcode":"30114",
    "sg:province":"GA",
    "sg:tags":[
        "practice",
        "family"
    ],
    "wof:name":"Community Family Practice Inc",
    "wof:placetype":"venue"
},
  "geometry": {"coordinates":[-84.481126,34.236871],"type":"Point"}
}