{
  "type": "Feature",
  "properties": {
    "iso:country":"US",
    "sg:address":"56 Norcross St",
    "sg:city":"Roswell",
    "sg:classifiers":[
        {
            "category":"Retail",
            "subcategory":"Auto Repair",
            "type":"Services"
        }
    ],
    "sg:phone":"+1 770 992 6471",
    "sg:postcode":"30075",
    "sg:province":"GA",
    "sg:tags":[
        "body",
        "shop"
    ],
    "wof:name":"Auto Body Plus Inc",
    "wof:placetype":"venue"
},
  "geometry": {"coordinates":[-84.359425,34.025735],"type":"Point"}
}