{
  "type": "Feature",
  "properties": {
    "addr:full":"153 Rolling Hills Dr SW Cartersville GA 30120",
    "addr:housenumber":"153",
    "addr:postcode":"30120",
    "addr:street":"Rolling Hills Dr Sw",
    "iso:country":"US",
    "sg:address":"153 Rolling Hills Dr SW",
    "sg:city":"Cartersville",
    "sg:classifiers":[
        {
            "category":"Building & Trades",
            "subcategory":"Construction",
            "type":"Services"
        }
    ],
    "sg:phone":"+1 770 386 3937",
    "sg:postcode":"30120",
    "sg:province":"GA",
    "sg:tags":[
        "house"
    ],
    "wof:name":"Inmans Construction",
    "wof:placetype":"venue"
},
  "geometry": {"coordinates":[-84.84828,34.095331],"type":"Point"}
}