{
  "type": "Feature",
  "properties": {
    "addr:full":"2326 Patsy Ln Columbus GA 31903",
    "addr:housenumber":"2326",
    "addr:postcode":"31903",
    "addr:street":"Patsy Ln",
    "iso:country":"US",
    "sg:address":"2326 Patsy Ln",
    "sg:city":"Columbus",
    "sg:classifiers":[
        {
            "category":"Building & Trades",
            "subcategory":"Cleaning & Sanitation",
            "type":"Services"
        }
    ],
    "sg:phone":"+1 706 689 6100",
    "sg:postcode":"31903",
    "sg:province":"GA",
    "sg:tags":[
        "maintenance"
    ],
    "wof:name":"Lee ML Cleaning Service",
    "wof:placetype":"venue"
},
  "geometry": {"coordinates":[-84.969885,32.411189],"type":"Point"}
}