{
  "type": "Feature",
  "properties": {
    "addr:full":"5042 Nelson Brogdon Blvd Sugar Hill GA 30518",
    "addr:housenumber":"5042",
    "addr:postcode":"30518",
    "addr:street":"Nelson Brogdon Blvd;Hill",
    "iso:country":"US",
    "sg:address":"5042 Nelson Brogdon Blvd",
    "sg:city":"Sugar Hill",
    "sg:classifiers":[
        {
            "category":"Retail",
            "subcategory":"Auto Repair",
            "type":"Services"
        }
    ],
    "sg:phone":"+1 770 271 9595",
    "sg:postcode":"30518",
    "sg:province":"GA",
    "sg:tags":[
        "transmission"
    ],
    "wof:name":"Mr Transmission",
    "wof:placetype":"venue"
},
  "geometry": {"coordinates":[-84.033807,34.107998],"type":"Point"}
}