{
  "type": "Feature",
  "properties": {
    "iso:country":"US",
    "sg:address":"43 Pecks Mill Creek Rd",
    "sg:city":"Dahlonega",
    "sg:classifiers":[
        {
            "category":"Organizations",
            "subcategory":"Religious Organization",
            "type":"Services"
        }
    ],
    "sg:phone":"+1 706 867 6745",
    "sg:postcode":"30533",
    "sg:province":"GA",
    "sg:tags":[
        "church"
    ],
    "wof:name":"Berea Baptist Church",
    "wof:placetype":"venue"
},
  "geometry": {"coordinates":[-83.92047599999999,34.525678],"type":"Point"}
}