{
  "type": "Feature",
  "properties": {
    "addr:full":"112 Hicks Dr Perry GA 31069",
    "addr:housenumber":"112",
    "addr:postcode":"31069",
    "addr:street":"Hicks Dr",
    "iso:country":"US",
    "sg:address":"112 Hicks Dr",
    "sg:city":"Perry",
    "sg:classifiers":[
        {
            "category":"Freight",
            "type":"Transportation"
        }
    ],
    "sg:phone":"+1 478 987 4088",
    "sg:postcode":"31069",
    "sg:province":"GA",
    "sg:tags":[
        "trucking"
    ],
    "sg:website":"www.condortransport.com",
    "wof:name":"Condor Transport Inc",
    "wof:placetype":"venue"
},
  "geometry": {"coordinates":[-83.76137,32.43649],"type":"Point"}
}