{
  "type": "Feature",
  "properties": {
    "addr:full":"1781 Dresden Dr Atlanta GA 30319",
    "addr:housenumber":"1781",
    "addr:postcode":"30319",
    "addr:street":"Dresden Dr",
    "iso:country":"US",
    "sg:address":"1781 Dresden Dr",
    "sg:city":"Atlanta",
    "sg:classifiers":[
        {
            "category":"Place Of Worship",
            "subcategory":"Temple",
            "type":"Public Place"
        }
    ],
    "sg:phone":"+1 404 982 0051",
    "sg:postcode":"30319",
    "sg:province":"GA",
    "sg:tags":[
        "buddhist"
    ],
    "sg:website":"www.drepung.org",
    "wof:name":"Drepung Loseling Institute",
    "wof:placetype":"venue"
},
  "geometry": {"coordinates":[-84.31740499999999,33.86391],"type":"Point"}
}