{
  "type": "Feature",
  "properties": {
    "addr:full":"2800 Peachtree Industrial Blvd Duluth GA 30096",
    "addr:housenumber":"2800",
    "addr:postcode":"30096",
    "addr:street":"Peachtree Industrial Blvd",
    "iso:country":"US",
    "sg:address":"2800 Peachtree Industrial Blvd",
    "sg:city":"Duluth",
    "sg:classifiers":[
        {
            "category":"Building & Trades",
            "subcategory":"Construction",
            "type":"Services"
        }
    ],
    "sg:phone":"+1 678 584 5435",
    "sg:postcode":"30096",
    "sg:province":"GA",
    "sg:tags":[
        "home",
        "builder"
    ],
    "sg:website":"www.storeyresidential.com",
    "wof:name":"Storey Residential Properties",
    "wof:placetype":"venue"
},
  "geometry": {"coordinates":[-84.129206,34.021608],"type":"Point"}
}