{
  "type": "Feature",
  "properties": {
    "addr:full":"747 US Hwy 1 Swainsboro GA 30401",
    "addr:housenumber":"747",
    "addr:postcode":"30401",
    "addr:street":"Us Hwy 1",
    "iso:country":"US",
    "sg:address":"747 US Hwy 1",
    "sg:city":"Swainsboro",
    "sg:classifiers":[
        {
            "category":"Building & Trades",
            "subcategory":"Construction",
            "type":"Services"
        }
    ],
    "sg:phone":"+1 478 237 6708",
    "sg:postcode":"30401",
    "sg:province":"GA",
    "wof:name":"Handi House Mfg Co",
    "wof:placetype":"venue"
},
  "geometry": {"coordinates":[-82.316732,32.575878],"type":"Point"}
}