{
  "type": "Feature",
  "properties": {
    "addr:full":"2430 Melinda Dr NE Atlanta GA 30345",
    "addr:housenumber":"2430",
    "addr:postcode":"30345",
    "addr:street":"Melinda Dr Ne",
    "iso:country":"US",
    "sg:address":"2430 Melinda Dr NE",
    "sg:city":"Atlanta",
    "sg:classifiers":[
        {
            "category":"Professional",
            "subcategory":"Business Services",
            "type":"Services"
        }
    ],
    "sg:phone":"+1 404 636 5181",
    "sg:postcode":"30345",
    "sg:province":"GA",
    "sg:tags":[
        "interior",
        "designer",
        "furniture"
    ],
    "wof:name":"Hda",
    "wof:placetype":"venue"
},
  "geometry": {"coordinates":[-84.286056,33.855492],"type":"Point"}
}