{
  "type": "Feature",
  "properties": {
    "iso:country":"US",
    "sg:address":"3368 Wedgewood Dr",
    "sg:city":"Augusta",
    "sg:classifiers":[
        {
            "category":"Building & Trades",
            "subcategory":"Plumbing",
            "type":"Services"
        }
    ],
    "sg:phone":"+1 706 399 0444",
    "sg:postcode":"30909",
    "sg:province":"GA",
    "sg:tags":[
        "control",
        "air",
        "pollution"
    ],
    "wof:name":"Fresh Air Enterprises",
    "wof:placetype":"venue"
},
  "geometry": {"coordinates":[-82.08123999999999,33.472467],"type":"Point"}
}