{
  "type": "Feature",
  "properties": {
    "addr:full":"2546 Bethelview Rd Cumming GA 30040",
    "addr:housenumber":"2546",
    "addr:postcode":"30040",
    "addr:street":"Bethelview Rd",
    "iso:country":"US",
    "sg:address":"2546 Bethelview Rd",
    "sg:city":"Cumming",
    "sg:classifiers":[
        {
            "category":"Professional",
            "type":"Services"
        }
    ],
    "sg:phone":"+1 770 205 4728",
    "sg:postcode":"30040",
    "sg:province":"GA",
    "wof:name":"Dannie Bailey",
    "wof:placetype":"venue"
},
  "geometry": {"coordinates":[-84.194639,34.233715],"type":"Point"}
}