{
  "type": "Feature",
  "properties": {
    "addr:full":"2245 Button Gwinnett Dr Doraville GA 30340",
    "addr:housenumber":"2245",
    "addr:postcode":"30340",
    "addr:street":"Button Gwinnett Dr",
    "iso:country":"US",
    "sg:address":"2245 Button Gwinnett Dr",
    "sg:city":"Doraville",
    "sg:classifiers":[
        {
            "category":"Home & Garden",
            "subcategory":"Building Materials",
            "type":"Retail Goods"
        }
    ],
    "sg:phone":"+1 770 448 9250",
    "sg:postcode":"30340",
    "sg:province":"GA",
    "sg:tags":[
        "equipment",
        "fixture",
        "lighting"
    ],
    "wof:name":"Lighting Associates Inc",
    "wof:placetype":"venue"
},
  "geometry": {"coordinates":[-84.237999,33.914398],"type":"Point"}
}