{
  "type": "Feature",
  "properties": {
    "iso:country":"US",
    "sg:address":"1600 Turner McCall Blvd",
    "sg:city":"Rome",
    "sg:classifiers":[
        {
            "category":"Building & Trades",
            "subcategory":"Construction",
            "type":"Services"
        }
    ],
    "sg:phone":"+1 706 295 0444",
    "sg:postcode":"30161",
    "sg:province":"GA",
    "sg:tags":[
        "tile",
        "dealer"
    ],
    "sg:website":"www.tilesofcalhoun.com",
    "wof:name":"Toc",
    "wof:placetype":"venue"
},
  "geometry": {"coordinates":[-85.16124499999999,34.243099],"type":"Point"}
}