{
  "type": "Feature",
  "properties": {
    "iso:country":"US",
    "sg:address":"4624 Walnut Bend Dr",
    "sg:city":"Gainesville",
    "sg:classifiers":[
        {
            "category":"Recreation",
            "type":"Entertainment"
        }
    ],
    "sg:phone":"+1 770 532 2854",
    "sg:postcode":"30507",
    "sg:province":"GA",
    "wof:name":"Skate Country of Georgia Inc",
    "wof:placetype":"venue"
},
  "geometry": {"coordinates":[-83.80286700000001,34.19093],"type":"Point"}
}