{
  "type": "Feature",
  "properties": {
    "addr:full":"1210 Spring St NW Atlanta GA 30309",
    "addr:housenumber":"1210",
    "addr:postcode":"30309",
    "addr:street":"Spring St Nw",
    "iso:country":"US",
    "sg:address":"1210 Spring St NW",
    "sg:city":"Atlanta",
    "sg:classifiers":[
        {
            "category":"Communications",
            "subcategory":"Film & Video Production",
            "type":"Services"
        }
    ],
    "sg:phone":"+1 404 685 9606",
    "sg:postcode":"30309",
    "sg:province":"GA",
    "sg:tags":[
        "studio",
        "facility"
    ],
    "wof:name":"Chopping Block",
    "wof:placetype":"venue"
},
  "geometry": {"coordinates":[-84.38937,33.788918],"type":"Point"}
}