{
  "type": "Feature",
  "properties": {
    "addr:full":"235 S Main St Madison GA 30650",
    "addr:housenumber":"235",
    "addr:postcode":"30650",
    "addr:street":"S Main St",
    "iso:country":"US",
    "sg:address":"235 S Main St",
    "sg:city":"Madison",
    "sg:classifiers":[
        {
            "category":"Real Estate",
            "subcategory":"Real Estate Agent",
            "type":"Services"
        }
    ],
    "sg:phone":"+1 706 752 1111",
    "sg:postcode":"30650",
    "sg:province":"GA",
    "wof:name":"Margaret E Waldrep",
    "wof:placetype":"venue"
},
  "geometry": {"coordinates":[-83.468791,33.594965],"type":"Point"}
}