{
  "type": "Feature",
  "properties": {
    "addr:full":"127 Airport Rd St Simons Island GA 31522",
    "addr:housenumber":"127",
    "addr:postcode":"31522",
    "addr:street":"Airport Rd St Simons Island",
    "iso:country":"US",
    "sg:address":"127 Airport Rd",
    "sg:city":"St Simons Island",
    "sg:classifiers":[
        {
            "category":"Food & Beverages",
            "subcategory":"Meat & Fish",
            "type":"Retail Goods"
        },
        {
            "category":"Wholesale",
            "subcategory":"Seafood",
            "type":"Manufacturing & Wholesale Goods"
        }
    ],
    "sg:phone":"+1 912 638 5000",
    "sg:postcode":"31522",
    "sg:province":"GA",
    "sg:website":"www.farm-richfun.com",
    "wof:name":"Rich-Sea Pak Corp",
    "wof:placetype":"venue"
},
  "geometry": {"coordinates":[-81.38579799999999,31.157601],"type":"Point"}
}