{
  "type": "Feature",
  "properties": {
    "iso:country":"US",
    "sg:address":"532 W Church St",
    "sg:city":"Swainsboro",
    "sg:classifiers":[
        {
            "category":"Recreation",
            "type":"Entertainment"
        }
    ],
    "sg:phone":"+1 478 289 9011",
    "sg:postcode":"30401",
    "sg:province":"GA",
    "sg:tags":[
        "hall",
        "auditorium"
    ],
    "wof:name":"City Of Swainsboro",
    "wof:placetype":"venue"
},
  "geometry": {"coordinates":[-82.347165,32.593664],"type":"Point"}
}