{
  "type": "Feature",
  "properties": {
    "addr:full":"1811 Francis Rd SW Conyers GA 30094",
    "addr:housenumber":"1811",
    "addr:postcode":"30094",
    "addr:street":"Francis Rd Sw",
    "iso:country":"US",
    "sg:address":"1811 Francis Rd SW",
    "sg:city":"Conyers",
    "sg:classifiers":[
        {
            "category":"Manufacturing",
            "subcategory":"Buildings",
            "type":"Manufacturing & Wholesale Goods"
        }
    ],
    "sg:phone":"+1 770 483 0097",
    "sg:postcode":"30094",
    "sg:province":"GA",
    "sg:tags":[
        "wooden",
        "prefabricated",
        "mfg"
    ],
    "wof:name":"Southern Classic Inc",
    "wof:placetype":"venue"
},
  "geometry": {"coordinates":[-84.046829,33.657747],"type":"Point"}
}