{
  "type": "Feature",
  "properties": {
    "iso:country":"US",
    "sg:address":"411 N Cobb St",
    "sg:city":"Milledgeville",
    "sg:classifiers":[
        {
            "category":"Health Services",
            "subcategory":"Doctor",
            "type":"Services"
        }
    ],
    "sg:phone":"+1 478 453 0003",
    "sg:postcode":"31061",
    "sg:province":"GA",
    "sg:tags":[
        "physician",
        "surgeon",
        "medical"
    ],
    "wof:name":"Middle GA Gastroenterologist",
    "wof:placetype":"venue"
},
  "geometry": {"coordinates":[-83.242403,33.085494],"type":"Point"}
}