{
  "type": "Feature",
  "properties": {
    "addr:full":"1455 Riverstone Pkwy Canton GA 30114",
    "addr:housenumber":"1455",
    "addr:postcode":"30114",
    "addr:street":"Riverstone Pkwy",
    "iso:country":"US",
    "sg:address":"1455 Riverstone Pkwy",
    "sg:city":"Canton",
    "sg:classifiers":[
        {
            "category":"Shopping",
            "subcategory":"Optical Goods",
            "type":"Retail Goods"
        }
    ],
    "sg:phone":"+1 770 479 0078",
    "sg:postcode":"30114",
    "sg:province":"GA",
    "wof:name":"Pearl Vision",
    "wof:placetype":"venue"
},
  "geometry": {"coordinates":[-84.476106,34.24953],"type":"Point"}
}