{
  "type": "Feature",
  "properties": {
    "iso:country":"US",
    "sg:address":"4648 Woodstock Rd",
    "sg:city":"Roswell",
    "sg:classifiers":[
        {
            "category":"Freight",
            "type":"Transportation"
        },
        {
            "category":"Professional",
            "subcategory":"Printing & Photocopies",
            "type":"Services"
        }
    ],
    "sg:phone":"+1 678 352 1042",
    "sg:postcode":"30075",
    "sg:province":"GA",
    "sg:tags":[
        "shipping"
    ],
    "sg:website":"www.fedex.com/us/office/",
    "wof:name":"FedEx Office Print & Ship Center",
    "wof:placetype":"venue"
},
  "geometry": {"coordinates":[-84.42083599999999,34.062392],"type":"Point"}
}