{
  "type": "Feature",
  "properties": {
    "addr:full":"801 Old Newnan Rd Carrollton GA 30116",
    "addr:housenumber":"801",
    "addr:postcode":"30116",
    "addr:street":"Old Newnan Rd",
    "iso:country":"US",
    "sg:address":"801 Old Newnan Rd",
    "sg:city":"Carrollton",
    "sg:classifiers":[
        {
            "category":"Insurance",
            "subcategory":"Insurance Agent",
            "type":"Services"
        }
    ],
    "sg:phone":"+1 770 834 2041",
    "sg:postcode":"30116",
    "sg:province":"GA",
    "wof:name":"State Farm Insurance",
    "wof:placetype":"venue"
},
  "geometry": {"coordinates":[-85.04173900000001,33.57049],"type":"Point"}
}