{
  "type": "Feature",
  "properties": {
    "iso:country":"US",
    "sg:address":"406 W King St",
    "sg:city":"Sylvester",
    "sg:classifiers":[
        {
            "category":"Education",
            "subcategory":"School",
            "type":"Public Place"
        }
    ],
    "sg:phone":"+1 229 776 8625",
    "sg:postcode":"31791",
    "sg:province":"GA",
    "wof:name":"Worth County High School",
    "wof:placetype":"venue"
},
  "geometry": {"coordinates":[-83.841972,31.544665],"type":"Point"}
}