{
  "type": "Feature",
  "properties": {
    "addr:full":"1080 N Wayne St Milledgeville GA 31061",
    "addr:housenumber":"1080",
    "addr:postcode":"31061",
    "addr:street":"N Wayne St",
    "iso:country":"US",
    "sg:address":"1080 N Wayne St",
    "sg:city":"Milledgeville",
    "sg:classifiers":[
        {
            "category":"Taxi",
            "type":"Transportation"
        }
    ],
    "sg:phone":"+1 478 453 4878",
    "sg:postcode":"31061",
    "sg:province":"GA",
    "sg:tags":[
        "taxicab"
    ],
    "wof:name":"Roderick Dorns",
    "wof:placetype":"venue"
},
  "geometry": {"coordinates":[-83.23066300000001,33.093837],"type":"Point"}
}