{
  "type": "Feature",
  "properties": {
    "addr:full":"4343 Cypress Pl Oakwood GA 30566",
    "addr:housenumber":"4343",
    "addr:postcode":"30566",
    "addr:street":"Cypress Pl",
    "iso:country":"US",
    "sg:address":"4343 Cypress Pl",
    "sg:city":"Oakwood",
    "sg:classifiers":[
        {
            "category":"Professional",
            "subcategory":"Employment Agencies",
            "type":"Services"
        }
    ],
    "sg:phone":"+1 770 527 0871",
    "sg:postcode":"30566",
    "sg:province":"GA",
    "sg:tags":[
        "underground",
        "trenching"
    ],
    "sg:website":"http://www.farmradio.org",
    "wof:name":"Farmer Trenching Company",
    "wof:placetype":"venue"
},
  "geometry": {"coordinates":[-83.901275,34.259616],"type":"Point"}
}