{
  "type": "Feature",
  "properties": {
    "addr:full":"3857 Randall Mill Road NW Atlanta GA 30327",
    "addr:housenumber":"3857",
    "addr:postcode":"30327",
    "addr:street":"Randall Mill Road Nw",
    "iso:country":"US",
    "sg:address":"3857 Randall Mill Road NW",
    "sg:city":"Atlanta",
    "sg:classifiers":[
        {
            "category":"Professional",
            "subcategory":"Lawyer & Legal Services",
            "type":"Services"
        }
    ],
    "sg:phone":"+1 404 846 0100",
    "sg:postcode":"30327",
    "sg:province":"GA",
    "wof:name":"Brodhead Ben C ESQ Law Offices of",
    "wof:placetype":"venue"
},
  "geometry": {"coordinates":[-84.424868,33.860665],"type":"Point"}
}