{
  "type": "Feature",
  "properties": {
    "addr:full":"285 Boulevard NE Suite 610 Atlanta GA 30312",
    "addr:housenumber":"285",
    "addr:postcode":"30312",
    "addr:street":"Boulevard Ne Suite 610",
    "iso:country":"US",
    "sg:address":"285 Boulevard NE Suite 610",
    "sg:city":"Atlanta",
    "sg:classifiers":[
        {
            "category":"Health Services",
            "subcategory":"Doctor",
            "type":"Services"
        }
    ],
    "sg:phone":"+1 404 222 9914",
    "sg:postcode":"30312",
    "sg:province":"GA",
    "sg:tags":[
        "physician",
        "family",
        "practice",
        "surgeons",
        "internal",
        "medicine",
        "surgeon"
    ],
    "wof:name":"Primary Care Specialists",
    "wof:placetype":"venue"
},
  "geometry": {"coordinates":[-84.371972,33.762238],"type":"Point"}
}