{
  "type": "Feature",
  "properties": {
    "iso:country":"US",
    "sg:address":"3645 Lawrenceville Hwy",
    "sg:city":"Lawrenceville",
    "sg:classifiers":[
        {
            "category":"Manufacturing",
            "subcategory":"Jewelry",
            "type":"Manufacturing & Wholesale Goods"
        }
    ],
    "sg:phone":"+1 770 925 2006",
    "sg:postcode":"30044",
    "sg:province":"GA",
    "sg:tags":[
        "precious",
        "metal",
        "mfg"
    ],
    "wof:name":"P & A Jewelry Co",
    "wof:placetype":"venue"
},
  "geometry": {"coordinates":[-84.098415,33.914013],"type":"Point"}
}