{
  "type": "Feature",
  "properties": {
    "addr:full":"515 E Main St Cartersville GA 30121",
    "addr:housenumber":"515",
    "addr:postcode":"30121",
    "addr:street":"E Main St",
    "iso:country":"US",
    "sg:address":"515 E Main St",
    "sg:city":"Cartersville",
    "sg:classifiers":[
        {
            "category":"Banks & Credit Unions",
            "subcategory":"Bank",
            "type":"Services"
        }
    ],
    "sg:phone":"+1 770 383 7445",
    "sg:postcode":"30121",
    "sg:province":"GA",
    "sg:tags":[
        "national",
        "commercial"
    ],
    "wof:name":"SunTrust",
    "wof:placetype":"venue"
},
  "geometry": {"coordinates":[-84.78904300000001,34.166951],"type":"Point"}
}