{
  "type": "Feature",
  "properties": {
    "iso:country":"US",
    "sg:address":"1709 Ridgeway Avenue",
    "sg:city":"Atlanta",
    "sg:classifiers":[
        {
            "category":"Personal",
            "subcategory":"Massage",
            "type":"Services"
        },
        {
            "category":"Health Services",
            "subcategory":"Health Practitioner",
            "type":"Services"
        }
    ],
    "sg:phone":"+1 404 355 1662",
    "sg:postcode":"30318",
    "sg:province":"GA",
    "sg:tags":[
        "acupuncture"
    ],
    "sg:website":"www.artofhealinginc.com",
    "wof:name":"Art of Healing",
    "wof:placetype":"venue"
},
  "geometry": {"coordinates":[-84.415938,33.80212],"type":"Point"}
}