{
  "type": "Feature",
  "properties": {
    "addr:full":"770 Stonebridge Cres Lithonia GA 30058",
    "addr:housenumber":"770",
    "addr:postcode":"30058",
    "addr:street":"Stonebridge Cres",
    "iso:country":"US",
    "sg:address":"770 Stonebridge Cres",
    "sg:city":"Lithonia",
    "sg:classifiers":[
        {
            "category":"Organizations",
            "subcategory":"Religious Organization",
            "type":"Services"
        }
    ],
    "sg:phone":"+1 770 879 7085",
    "sg:postcode":"30058",
    "sg:province":"GA",
    "sg:tags":[
        "church"
    ],
    "wof:name":"Vision Of Hope Worship",
    "wof:placetype":"venue"
},
  "geometry": {"coordinates":[-84.08847299999999,33.775382],"type":"Point"}
}