{
  "type": "Feature",
  "properties": {
    "iso:country":"US",
    "sg:address":"1750 Powder Springs St S",
    "sg:city":"Marietta",
    "sg:classifiers":[
        {
            "category":"Personal",
            "subcategory":"Tanning Parlor",
            "type":"Services"
        },
        {
            "category":"Personal",
            "type":"Services"
        }
    ],
    "sg:phone":"+1 770 514 0053",
    "sg:postcode":"30064",
    "sg:province":"GA",
    "sg:tags":[
        "salon"
    ],
    "wof:name":"Catchin' Rays",
    "wof:placetype":"venue"
},
  "geometry": {"coordinates":[-84.605559,33.902048],"type":"Point"}
}