{
  "type": "Feature",
  "properties": {
    "addr:full":"5099 Southridge Pkwy Atlanta GA 30349",
    "addr:housenumber":"5099",
    "addr:postcode":"30349",
    "addr:street":"Southridge Pkwy",
    "iso:country":"US",
    "sg:address":"5099 Southridge Pkwy",
    "sg:city":"Atlanta",
    "sg:classifiers":[
        {
            "category":"Freight",
            "type":"Transportation"
        }
    ],
    "sg:phone":"+1 404 761 1148",
    "sg:postcode":"30349",
    "sg:province":"GA",
    "sg:tags":[
        "arrangement"
    ],
    "wof:name":"Hankyu Intl Trnspt USA",
    "wof:placetype":"venue"
},
  "geometry": {"coordinates":[-84.42497400000001,33.614989],"type":"Point"}
}