{
  "type": "Feature",
  "properties": {
    "iso:country":"US",
    "sg:address":"106 E Force St",
    "sg:city":"Valdosta",
    "sg:classifiers":[
        {
            "category":"Professional",
            "subcategory":"Lawyer & Legal Services",
            "type":"Services"
        }
    ],
    "sg:phone":"+1 229 247 1387",
    "sg:postcode":"31601",
    "sg:province":"GA",
    "sg:tags":[
        "attorney",
        "trust",
        "corporation",
        "wills",
        "partnership",
        "tax",
        "planning",
        "real estate",
        "law"
    ],
    "sg:website":"http://www.trust-law-online.com",
    "wof:name":"Smith Andrew PC",
    "wof:placetype":"venue"
},
  "geometry": {"coordinates":[-83.283858,30.840589],"type":"Point"}
}