{
  "type": "Feature",
  "properties": {
    "addr:full":"1635 Virginia Ave Atlanta GA 30337",
    "addr:housenumber":"1635",
    "addr:postcode":"30337",
    "addr:street":"Virginia Ave",
    "iso:country":"US",
    "sg:address":"1635 Virginia Ave",
    "sg:city":"Atlanta",
    "sg:classifiers":[
        {
            "category":"Building & Trades",
            "subcategory":"Locksmith",
            "type":"Services"
        }
    ],
    "sg:phone":"+1 866 545 7501",
    "sg:postcode":"30337",
    "sg:province":"GA",
    "sg:tags":[
        "key"
    ],
    "wof:name":"24 Hour 1 Emergency Locksmith",
    "wof:placetype":"venue"
},
  "geometry": {"coordinates":[-84.442858,33.659392],"type":"Point"}
}