{
  "type": "Feature",
  "properties": {
    "addr:full":"7830 Landowne Dr Atlanta GA 30350",
    "addr:housenumber":"7830",
    "addr:postcode":"30350",
    "addr:street":"Landowne Dr",
    "iso:country":"US",
    "sg:address":"7830 Landowne Dr",
    "sg:city":"Atlanta",
    "sg:classifiers":[
        {
            "category":"Wholesale",
            "subcategory":"Toys & Hobbies",
            "type":"Manufacturing & Wholesale Goods"
        }
    ],
    "sg:phone":"+1 770 396 1983",
    "sg:postcode":"30350",
    "sg:province":"GA",
    "wof:name":"Ja Ru Inc",
    "wof:placetype":"venue"
},
  "geometry": {"coordinates":[-84.278553,33.967549],"type":"Point"}
}