{
  "type": "Feature",
  "properties": {
    "addr:full":"5175 Performance Dr Cumming GA 30040",
    "addr:housenumber":"5175",
    "addr:postcode":"30040",
    "addr:street":"Performance Dr",
    "iso:country":"US",
    "sg:address":"5175 Performance Dr",
    "sg:city":"Cumming",
    "sg:classifiers":[
        {
            "category":"Airline",
            "type":"Transportation"
        },
        {
            "category":"Landmark",
            "subcategory":"Tourist Information",
            "type":"Public Place"
        },
        {
            "category":"Landmark",
            "subcategory":"Tourist Attraction",
            "type":"Public Place"
        }
    ],
    "sg:phone":"+1 678 576 1210",
    "sg:postcode":"30040",
    "sg:province":"GA",
    "sg:tags":[
        "tour",
        "tours-operators",
        "promoter",
        "sightseeing"
    ],
    "wof:name":"North Atlanta Executive Air",
    "wof:placetype":"venue"
},
  "geometry": {"coordinates":[-84.169709,34.170651],"type":"Point"}
}