{
  "type": "Feature",
  "properties": {
    "addr:full":"310 W Waugh St Dalton GA 30720",
    "addr:housenumber":"310",
    "addr:postcode":"30720",
    "addr:street":"W Waugh St",
    "iso:country":"US",
    "sg:address":"310 W Waugh St",
    "sg:city":"Dalton",
    "sg:classifiers":[
        {
            "category":"Insurance",
            "subcategory":"Insurance Agent",
            "type":"Services"
        }
    ],
    "sg:phone":"+1 706 226 1572",
    "sg:postcode":"30720",
    "sg:province":"GA",
    "wof:name":"North Georgia Insurance",
    "wof:placetype":"venue"
},
  "geometry": {"coordinates":[-84.972843,34.77429],"type":"Point"}
}