{
  "type": "Feature",
  "properties": {
    "iso:country":"US",
    "sg:address":"2501 Martin Luther King Jr Dr",
    "sg:city":"Albany",
    "sg:classifiers":[
        {
            "category":"Restaurant",
            "type":"Food & Drink"
        }
    ],
    "sg:phone":"+1 229 432 1961",
    "sg:postcode":"31701",
    "sg:province":"GA",
    "wof:name":"Skippy's Diner & Restaurant",
    "wof:placetype":"venue"
},
  "geometry": {"coordinates":[-84.155259,31.539088],"type":"Point"}
}