{
  "type": "Feature",
  "properties": {
    "iso:country":"US",
    "sg:address":"4505 Wedewer Way",
    "sg:city":"Woodstock",
    "sg:classifiers":[
        {
            "category":"Professional",
            "subcategory":"Accounting & Tax Preparation",
            "type":"Services"
        }
    ],
    "sg:phone":"+1 770 604 5662",
    "sg:postcode":"30188",
    "sg:province":"GA",
    "wof:name":"Cindy Milliner",
    "wof:placetype":"venue"
},
  "geometry": {"coordinates":[-84.437647,34.095291],"type":"Point"}
}