{
  "type": "Feature",
  "properties": {
    "addr:full":"2247 Venetian Dr SW Atlanta GA 30311",
    "addr:housenumber":"2247",
    "addr:postcode":"30311",
    "addr:street":"Venetian Dr Sw",
    "iso:country":"US",
    "sg:address":"2247 Venetian Dr SW",
    "sg:city":"Atlanta",
    "sg:classifiers":[
        {
            "category":"Professional",
            "subcategory":"Business Services",
            "type":"Services"
        }
    ],
    "sg:phone":"+1 404 892 0060",
    "sg:postcode":"30311",
    "sg:province":"GA",
    "sg:tags":[
        "translator",
        "interpreter"
    ],
    "wof:name":"Japanese Translators/Interprtr",
    "wof:placetype":"venue"
},
  "geometry": {"coordinates":[-84.459219,33.715401],"type":"Point"}
}