{
  "type": "Feature",
  "properties": {
    "addr:full":"6630 Oak Ridge Commerce Way Austell GA 30168",
    "addr:housenumber":"6630",
    "addr:postcode":"30168",
    "addr:street":"Oak Ridge Commerce Way",
    "iso:country":"US",
    "sg:address":"6630 Oak Ridge Commerce Way",
    "sg:city":"Austell",
    "sg:classifiers":[
        {
            "category":"Building & Trades",
            "subcategory":"Locksmith",
            "type":"Services"
        }
    ],
    "sg:phone":"+1 877 226 3006",
    "sg:postcode":"30168",
    "sg:province":"GA",
    "sg:tags":[
        "key"
    ],
    "wof:name":"24 Hour 1 Emergency Locksmith",
    "wof:placetype":"venue"
},
  "geometry": {"coordinates":[-84.604221,33.78583],"type":"Point"}
}