{
  "type": "Feature",
  "properties": {
    "addr:full":"812 Woodberry Dr Evans GA 30809",
    "addr:housenumber":"812",
    "addr:postcode":"30809",
    "addr:street":"Woodberry Dr",
    "iso:country":"US",
    "sg:address":"812 Woodberry Dr",
    "sg:city":"Evans",
    "sg:classifiers":[
        {
            "category":"Professional",
            "subcategory":"Management & Consulting",
            "type":"Services"
        }
    ],
    "sg:phone":"+1 706 364 4272",
    "sg:postcode":"30809",
    "sg:province":"GA",
    "sg:tags":[
        "marketing",
        "program"
    ],
    "wof:name":"Consumer First Randy Fadley",
    "wof:placetype":"venue"
},
  "geometry": {"coordinates":[-82.135513,33.550563],"type":"Point"}
}