{
  "type": "Feature",
  "properties": {
    "iso:country":"US",
    "sg:address":"108 Forrest Ave",
    "sg:city":"Cartersville",
    "sg:classifiers":[
        {
            "category":"Health Services",
            "subcategory":"Health Practitioner",
            "type":"Services"
        }
    ],
    "sg:phone":"+1 770 386 6222",
    "sg:postcode":"30120",
    "sg:province":"GA",
    "sg:tags":[
        "psychologist"
    ],
    "wof:name":"Newbridge Northwest Psychology",
    "wof:placetype":"venue"
},
  "geometry": {"coordinates":[-84.791211,34.165267],"type":"Point"}
}