{
  "type": "Feature",
  "properties": {
    "iso:country":"US",
    "sg:address":"161 Newport Rd SW",
    "sg:city":"Lilburn",
    "sg:classifiers":[
        {
            "category":"Building & Trades",
            "subcategory":"Construction",
            "type":"Services"
        }
    ],
    "sg:phone":"+1 770 381 9405",
    "sg:postcode":"30047",
    "sg:province":"GA",
    "sg:tags":[
        "hanging",
        "contractor"
    ],
    "wof:name":"Abe Painting Inc",
    "wof:placetype":"venue"
},
  "geometry": {"coordinates":[-84.12443,33.88536],"type":"Point"}
}