{
  "type": "Feature",
  "properties": {
    "addr:full":"11473 Tara Blvd Hampton GA 30228",
    "addr:housenumber":"11473",
    "addr:postcode":"30228",
    "addr:street":"Tara Blvd",
    "iso:country":"US",
    "sg:address":"11473 Tara Blvd",
    "sg:city":"Hampton",
    "sg:classifiers":[
        {
            "category":"Restaurant",
            "type":"Food & Drink"
        }
    ],
    "sg:menulink":"http://www.allmenus.com/ga/jonesboro/103563-ruby-tuesdays/menu/",
    "sg:phone":"+1 678 479 2072",
    "sg:postcode":"30228",
    "sg:province":"GA",
    "sg:tags":[
        "burger",
        "american"
    ],
    "wof:name":"Ruby Tuesdays",
    "wof:placetype":"venue"
},
  "geometry": {"coordinates":[-84.322152,33.44198],"type":"Point"}
}