{
  "type": "Feature",
  "properties": {
    "addr:full":"509 US Hwy 19 Zebulon GA 30295",
    "addr:housenumber":"509",
    "addr:postcode":"30295",
    "addr:street":"Us Hwy 19",
    "iso:country":"US",
    "sg:address":"509 US Hwy 19",
    "sg:city":"Zebulon",
    "sg:classifiers":[
        {
            "category":"Restaurant",
            "type":"Food & Drink"
        }
    ],
    "sg:phone":"+1 770 567 1485",
    "sg:postcode":"30295",
    "sg:province":"GA",
    "wof:name":"Antonio's Pizza & Subs",
    "wof:placetype":"venue"
},
  "geometry": {"coordinates":[-84.345214,33.093809],"type":"Point"}
}