{
  "type": "Feature",
  "properties": {
    "iso:country":"US",
    "sg:address":"581 Elam Ct NW",
    "sg:city":"Norcross",
    "sg:classifiers":[
        {
            "category":"Professional",
            "subcategory":"Accounting & Tax Preparation",
            "type":"Services"
        }
    ],
    "sg:phone":"+1 770 939 8700",
    "sg:postcode":"30093",
    "sg:province":"GA",
    "sg:tags":[
        "medical",
        "billing"
    ],
    "wof:name":"Sykes Associate Services",
    "wof:placetype":"venue"
},
  "geometry": {"coordinates":[-84.187921,33.878477],"type":"Point"}
}