{
  "type": "Feature",
  "properties": {
    "iso:country":"US",
    "sg:address":"4380 Broadway",
    "sg:city":"Macon",
    "sg:classifiers":[
        {
            "category":"Autos & Motor Vehicles",
            "subcategory":"Automobile Sales",
            "type":"Retail Goods"
        },
        {
            "category":"Professional",
            "subcategory":"Management & Consulting",
            "type":"Services"
        }
    ],
    "sg:phone":"+1 478 781 8010",
    "sg:postcode":"31206",
    "sg:province":"GA",
    "sg:tags":[
        "car",
        "dealer",
        "sales"
    ],
    "wof:name":"Fosters Auto Sales",
    "wof:placetype":"venue"
},
  "geometry": {"coordinates":[-83.65303,32.784761],"type":"Point"}
}