{
  "type": "Feature",
  "properties": {
    "addr:full":"864 Plainsville Dr Atlanta GA 30331",
    "addr:housenumber":"864",
    "addr:postcode":"30331",
    "addr:street":"Plainsville Dr",
    "iso:country":"US",
    "sg:address":"864 Plainsville Dr",
    "sg:city":"Atlanta",
    "sg:classifiers":[
        {
            "category":"Personal",
            "type":"Services"
        },
        {
            "category":"Retail",
            "subcategory":"Auto Repair",
            "type":"Services"
        }
    ],
    "sg:phone":"+1 404 978 3850",
    "sg:postcode":"30331",
    "sg:province":"GA",
    "sg:tags":[
        "towing",
        "road",
        "service-automotive"
    ],
    "wof:name":"Tru Blu Towing & Recovery Service Inc",
    "wof:placetype":"venue"
},
  "geometry": {"coordinates":[-84.518423,33.739512],"type":"Point"}
}