{
  "type": "Feature",
  "properties": {
    "addr:full":"298 W Broad St Camilla GA 31730",
    "addr:housenumber":"298",
    "addr:postcode":"31730",
    "addr:street":"W Broad St",
    "iso:country":"US",
    "sg:address":"298 W Broad St",
    "sg:city":"Camilla",
    "sg:classifiers":[
        {
            "category":"Building & Trades",
            "subcategory":"Plumbing",
            "type":"Services"
        }
    ],
    "sg:phone":"+1 229 336 0285",
    "sg:postcode":"31730",
    "sg:province":"GA",
    "sg:tags":[
        "plumbing",
        "contractor"
    ],
    "wof:name":"Agricultural Fabricators",
    "wof:placetype":"venue"
},
  "geometry": {"coordinates":[-84.21435099999999,31.231159],"type":"Point"}
}