{
  "type": "Feature",
  "properties": {
    "iso:country":"US",
    "sg:address":"3565 Martin Luther King Jr Dr SW",
    "sg:city":"Atlanta",
    "sg:classifiers":[
        {
            "category":"Wholesale",
            "subcategory":"Jewelry",
            "type":"Manufacturing & Wholesale Goods"
        }
    ],
    "sg:phone":"+1 404 699 1154",
    "sg:postcode":"30331",
    "sg:province":"GA",
    "sg:tags":[
        "stone"
    ],
    "wof:name":"Kim Soyon",
    "wof:placetype":"venue"
},
  "geometry": {"coordinates":[-84.504096,33.758618],"type":"Point"}
}