{
  "type": "Feature",
  "properties": {
    "addr:full":"1590 Adamson Pkwy Ste 360 Morrow GA 30260",
    "addr:housenumber":"1590",
    "addr:postcode":"30260",
    "addr:street":"Adamson Pkwy Ste 360",
    "iso:country":"US",
    "sg:address":"1590 Adamson Pkwy Ste 360",
    "sg:city":"Morrow",
    "sg:classifiers":[
        {
            "category":"Health Services",
            "subcategory":"Dentist",
            "type":"Services"
        }
    ],
    "sg:phone":"+1 770 242 3260",
    "sg:postcode":"30260",
    "sg:province":"GA",
    "sg:website":"www.nanstondental.com/",
    "wof:name":"Nanston Dental Group",
    "wof:placetype":"venue"
},
  "geometry": {"coordinates":[-84.33605,33.577144],"type":"Point"}
}