{
  "type": "Feature",
  "properties": {
    "addr:full":"6204 Old Liberty Hill Rd Toccoa GA 30577",
    "addr:housenumber":"6204",
    "addr:postcode":"30577",
    "addr:street":"Old Liberty Hill Rd",
    "iso:country":"US",
    "sg:address":"6204 Old Liberty Hill Rd",
    "sg:city":"Toccoa",
    "sg:classifiers":[
        {
            "category":"Wholesale",
            "subcategory":"Machinery & Supplies",
            "type":"Manufacturing & Wholesale Goods"
        }
    ],
    "sg:phone":"+1 706 886 9413",
    "sg:postcode":"30577",
    "sg:province":"GA",
    "sg:tags":[
        "equipment",
        "welding"
    ],
    "wof:name":"National Welders Supply Co",
    "wof:placetype":"venue"
},
  "geometry": {"coordinates":[-83.316734,34.548252],"type":"Point"}
}