{
  "type": "Feature",
  "properties": {
    "addr:full":"119 McCrary Dr Macon GA 31211",
    "addr:housenumber":"119",
    "addr:postcode":"31211",
    "addr:street":"Mccrary Dr",
    "iso:country":"US",
    "sg:address":"119 McCrary Dr",
    "sg:city":"Macon",
    "sg:classifiers":[
        {
            "category":"Building & Trades",
            "subcategory":"Construction",
            "type":"Services"
        }
    ],
    "sg:phone":"+1 478 742 3975",
    "sg:postcode":"31211",
    "sg:province":"GA",
    "sg:tags":[
        "contractor"
    ],
    "wof:name":"Napoleon Grant Masonry",
    "wof:placetype":"venue"
},
  "geometry": {"coordinates":[-83.578829,32.8742],"type":"Point"}
}