{
  "type": "Feature",
  "properties": {
    "addr:full":"2303 W Alberson Dr Albany GA 31721",
    "addr:housenumber":"2303",
    "addr:postcode":"31721",
    "addr:street":"W Alberson Dr",
    "iso:country":"US",
    "sg:address":"2303 W Alberson Dr",
    "sg:city":"Albany",
    "sg:classifiers":[
        {
            "category":"Organizations",
            "subcategory":"Non-profit Organization",
            "type":"Services"
        }
    ],
    "sg:phone":"+1 229 883 1687",
    "sg:postcode":"31721",
    "sg:province":"GA",
    "sg:tags":[
        "social"
    ],
    "wof:name":"Cultural Association of India",
    "wof:placetype":"venue"
},
  "geometry": {"coordinates":[-84.248372,31.60358],"type":"Point"}
}