{
  "type": "Feature",
  "properties": {
    "addr:full":"9115 Waits Ferry Xing Duluth GA 30097",
    "addr:housenumber":"9115",
    "addr:postcode":"30097",
    "addr:street":"Waits Ferry Xing",
    "iso:country":"US",
    "sg:address":"9115 Waits Ferry Xing",
    "sg:city":"Duluth",
    "sg:classifiers":[
        {
            "category":"Professional",
            "type":"Services"
        }
    ],
    "sg:phone":"+1 770 447 9750",
    "sg:postcode":"30097",
    "sg:province":"GA",
    "wof:name":"Pamela Clark",
    "wof:placetype":"venue"
},
  "geometry": {"coordinates":[-84.205924,34.003616],"type":"Point"}
}