{
  "type": "Feature",
  "properties": {
    "addr:full":"1992 Watson Blvd Warner Robins GA 31093",
    "addr:housenumber":"1992",
    "addr:postcode":"31093",
    "addr:street":"Watson Blvd",
    "iso:country":"US",
    "sg:address":"1992 Watson Blvd",
    "sg:city":"Warner Robins",
    "sg:classifiers":[
        {
            "category":"Restaurant",
            "type":"Food & Drink"
        }
    ],
    "sg:menulink":"http://www.allmenus.com/ga/warner-robins/105191-ryans/menu/",
    "sg:phone":"+1 478 922 9716",
    "sg:postcode":"31093",
    "sg:province":"GA",
    "sg:tags":[
        "american"
    ],
    "wof:name":"Ryan's",
    "wof:placetype":"venue"
},
  "geometry": {"coordinates":[-83.64607100000001,32.618317],"type":"Point"}
}