{
  "type": "Feature",
  "properties": {
    "iso:country":"US",
    "sg:address":"302 Providence Dr",
    "sg:city":"Dallas",
    "sg:classifiers":[
        {
            "category":"Professional",
            "type":"Services"
        }
    ],
    "sg:phone":"+1 770 443 6370",
    "sg:postcode":"30115",
    "sg:province":"GA",
    "sg:tags":[
        "establishment"
    ],
    "wof:name":"Ray King Inc",
    "wof:placetype":"venue"
},
  "geometry": {"coordinates":[-84.458535,34.19395],"type":"Point"}
}