{
  "type": "Feature",
  "properties": {
    "iso:country":"US",
    "sg:address":"510 Plaza Dr",
    "sg:city":"Atlanta",
    "sg:phone":"+1 404 608 8840",
    "sg:postcode":"30349",
    "sg:province":"GA",
    "wof:name":"World Ports International Inc",
    "wof:placetype":"venue"
},
  "geometry": {"coordinates":[-84.403659,33.62012],"type":"Point"}
}