{
  "type": "Feature",
  "properties": {
    "iso:country":"US",
    "sg:address":"548 Victoria Rd",
    "sg:city":"Woodstock",
    "sg:classifiers":[
        {
            "category":"Building & Trades",
            "subcategory":"Construction",
            "type":"Services"
        }
    ],
    "sg:phone":"+1 770 591 9717",
    "sg:postcode":"30189",
    "sg:province":"GA",
    "sg:tags":[
        "house"
    ],
    "wof:name":"Deckers Remodeling",
    "wof:placetype":"venue"
},
  "geometry": {"coordinates":[-84.605615,34.142771],"type":"Point"}
}