{
  "type": "Feature",
  "properties": {
    "addr:full":"845 Athens Hwy Loganville GA 30052",
    "addr:housenumber":"845",
    "addr:postcode":"30052",
    "addr:street":"Athens Hwy",
    "iso:country":"US",
    "sg:address":"845 Athens Hwy",
    "sg:city":"Loganville",
    "sg:classifiers":[
        {
            "category":"Building & Trades",
            "subcategory":"Plumbing",
            "type":"Services"
        }
    ],
    "sg:phone":"+1 770 466 2924",
    "sg:postcode":"30052",
    "sg:province":"GA",
    "sg:tags":[
        "conditioning",
        "air",
        "system",
        "contractor"
    ],
    "wof:name":"Tony Beck Heating & Air Cond",
    "wof:placetype":"venue"
},
  "geometry": {"coordinates":[-83.955787,33.861187],"type":"Point"}
}