{
  "type": "Feature",
  "properties": {
    "iso:country":"US",
    "sg:address":"931 Monroe Dr NE 210",
    "sg:city":"Atlanta",
    "sg:classifiers":[
        {
            "category":"Professional",
            "subcategory":"Testing Lab",
            "type":"Services"
        }
    ],
    "sg:phone":"+1 770 474 8130",
    "sg:postcode":"30308",
    "sg:province":"GA",
    "sg:tags":[
        "chemist"
    ],
    "wof:name":"Wavecrest Chemical",
    "wof:placetype":"venue"
},
  "geometry": {"coordinates":[-84.369392,33.779518],"type":"Point"}
}