{
  "type": "Feature",
  "properties": {
    "addr:full":"879 Primrose Place Dr Lawrenceville GA 30044",
    "addr:housenumber":"879",
    "addr:postcode":"30044",
    "addr:street":"Primrose Place Dr",
    "iso:country":"US",
    "sg:address":"879 Primrose Place Dr",
    "sg:city":"Lawrenceville",
    "sg:classifiers":[
        {
            "category":"Freight",
            "type":"Transportation"
        }
    ],
    "sg:phone":"+1 770 331 4682",
    "sg:postcode":"30044",
    "sg:province":"GA",
    "sg:tags":[
        "operator",
        "trucking"
    ],
    "wof:name":"Saming Trans Inc",
    "wof:placetype":"venue"
},
  "geometry": {"coordinates":[-84.033591,33.900871],"type":"Point"}
}