{
  "type": "Feature",
  "properties": {
    "addr:full":"1783 Panola Rd Ellenwood GA 30294",
    "addr:housenumber":"1783",
    "addr:postcode":"30294",
    "addr:street":"Panola Rd",
    "iso:country":"US",
    "sg:address":"1783 Panola Rd",
    "sg:city":"Ellenwood",
    "sg:classifiers":[
        {
            "category":"Manufacturing",
            "subcategory":"Printing",
            "type":"Manufacturing & Wholesale Goods"
        }
    ],
    "sg:phone":"+1 770 808 0457",
    "sg:postcode":"30294",
    "sg:province":"GA",
    "sg:tags":[
        "screen",
        "printer",
        "commercial"
    ],
    "wof:name":"Ellenwood Printing Company",
    "wof:placetype":"venue"
},
  "geometry": {"coordinates":[-84.23347800000001,33.622461],"type":"Point"}
}