{
  "type": "Feature",
  "properties": {
    "addr:full":"3008 Gillsville Hwy Gainesville GA 30507",
    "addr:housenumber":"3008",
    "addr:postcode":"30507",
    "addr:street":"Gillsville Hwy",
    "iso:country":"US",
    "sg:address":"3008 Gillsville Hwy",
    "sg:city":"Gainesville",
    "sg:classifiers":[
        {
            "category":"Restaurant",
            "type":"Food & Drink"
        }
    ],
    "sg:menulink":"http://www.allmenus.com/ga/gainesville/88939-papas-pizza-to-go/menu/",
    "sg:phone":"+1 770 287 7778",
    "sg:postcode":"30507",
    "sg:province":"GA",
    "sg:tags":[
        "american",
        "pizza"
    ],
    "wof:name":"Papas Pizza To Go",
    "wof:placetype":"venue"
},
  "geometry": {"coordinates":[-83.742333,34.266849],"type":"Point"}
}