{
  "type": "Feature",
  "properties": {
    "iso:country":"US",
    "sg:address":"224 Brown Industrial Pkwy",
    "sg:city":"Canton",
    "sg:classifiers":[
        {
            "category":"Building & Trades",
            "subcategory":"Construction",
            "type":"Services"
        }
    ],
    "sg:phone":"+1 770 345 1122",
    "sg:postcode":"30114",
    "sg:province":"GA",
    "sg:tags":[
        "roofing",
        "contractor"
    ],
    "wof:name":"Georgia Roof Masters",
    "wof:placetype":"venue"
},
  "geometry": {"coordinates":[-84.47185,34.240692],"type":"Point"}
}