{
  "type": "Feature",
  "properties": {
    "addr:full":"2150 Boggs Rd Duluth GA 30096",
    "addr:housenumber":"2150",
    "addr:postcode":"30096",
    "addr:street":"Boggs Rd",
    "iso:country":"US",
    "sg:address":"2150 Boggs Rd",
    "sg:city":"Duluth",
    "sg:classifiers":[
        {
            "category":"Professional",
            "subcategory":"Business Services",
            "type":"Services"
        },
        {
            "category":"Professional",
            "subcategory":"Accounting & Tax Preparation",
            "type":"Services"
        }
    ],
    "sg:phone":"+1 678 473 1885",
    "sg:postcode":"30096",
    "sg:province":"GA",
    "sg:tags":[
        "laser",
        "printing",
        "mailing",
        "referral",
        "information"
    ],
    "wof:name":"Arista Information Systems",
    "wof:placetype":"venue"
},
  "geometry": {"coordinates":[-84.099523,33.972858],"type":"Point"}
}