{
  "type": "Feature",
  "properties": {
    "iso:country":"US",
    "sg:address":"350 Country Club Dr Ste B",
    "sg:city":"Stockbridge",
    "sg:classifiers":[
        {
            "category":"Community Center",
            "type":"Public Place"
        }
    ],
    "sg:phone":"+1 770 507 0633",
    "sg:postcode":"30281",
    "sg:province":"GA",
    "sg:tags":[
        "medical"
    ],
    "wof:name":"Henry Medical Center",
    "wof:placetype":"venue"
},
  "geometry": {"coordinates":[-84.218777,33.509102],"type":"Point"}
}