{
  "type": "Feature",
  "properties": {
    "addr:full":"216 Johnson Fry Atlanta GA 30328",
    "addr:housenumber":"216",
    "addr:postcode":"30328",
    "addr:street":"Johnson Fry",
    "iso:country":"US",
    "sg:address":"216 Johnson Fry",
    "sg:city":"Atlanta",
    "sg:classifiers":[
        {
            "category":"Retail",
            "subcategory":"Animal Services",
            "type":"Services"
        }
    ],
    "sg:phone":"+1 404 705 8282",
    "sg:postcode":"30328",
    "sg:province":"GA",
    "sg:tags":[
        "pet"
    ],
    "wof:name":"Red Bandanna",
    "wof:placetype":"venue"
},
  "geometry": {"coordinates":[-84.37857200000001,33.936604],"type":"Point"}
}