{
  "type": "Feature",
  "properties": {
    "iso:country":"US",
    "sg:address":"733 Frank Kirk Rd",
    "sg:city":"Kennesaw",
    "sg:classifiers":[
        {
            "category":"Professional",
            "subcategory":"Management & Consulting",
            "type":"Services"
        }
    ],
    "sg:phone":"+1 770 424 6655",
    "sg:postcode":"30152",
    "sg:province":"GA",
    "sg:tags":[
        "business"
    ],
    "wof:name":"Greenhuse Cnslting Investments",
    "wof:placetype":"venue"
},
  "geometry": {"coordinates":[-84.64113,33.974199],"type":"Point"}
}