{
  "type": "Feature",
  "properties": {
    "addr:full":"2150 Northwest Pkwy SE Marietta GA 30067",
    "addr:housenumber":"2150",
    "addr:postcode":"30067",
    "addr:street":"Northwest Pkwy Se",
    "iso:country":"US",
    "sg:address":"2150 Northwest Pkwy SE",
    "sg:city":"Marietta",
    "sg:classifiers":[
        {
            "category":"Professional",
            "subcategory":"Accounting & Tax Preparation",
            "type":"Services"
        }
    ],
    "sg:phone":"+1 770 952 7380",
    "sg:postcode":"30067",
    "sg:province":"GA",
    "sg:tags":[
        "accountant"
    ],
    "wof:name":"Taylor & Harmon Llc Cpa's",
    "wof:placetype":"venue"
},
  "geometry": {"coordinates":[-84.492302,33.918499],"type":"Point"}
}