{
  "type": "Feature",
  "properties": {
    "iso:country":"US",
    "sg:address":"122 Lakeview Ct",
    "sg:city":"Augusta",
    "sg:classifiers":[
        {
            "category":"Building & Trades",
            "subcategory":"Construction",
            "type":"Services"
        }
    ],
    "sg:phone":"+1 706 860 2917",
    "sg:postcode":"30907",
    "sg:province":"GA",
    "sg:tags":[
        "house",
        "builder",
        "operative"
    ],
    "wof:name":"McGahee Builders Inc",
    "wof:placetype":"venue"
},
  "geometry": {"coordinates":[-82.113698,33.50343],"type":"Point"}
}