{
  "type": "Feature",
  "properties": {
    "addr:full":"3091 Governors Lake Dr Norcross GA 30071",
    "addr:housenumber":"3091",
    "addr:postcode":"30071",
    "addr:street":"Governors Lake Dr",
    "iso:country":"US",
    "sg:address":"3091 Governors Lake Dr",
    "sg:city":"Norcross",
    "sg:classifiers":[
        {
            "category":"Professional",
            "subcategory":"Lawyer & Legal Services",
            "type":"Services"
        }
    ],
    "sg:phone":"+1 770 209 1650",
    "sg:postcode":"30071",
    "sg:province":"GA",
    "wof:name":"Sheffield Cynthia Atty At Law",
    "wof:placetype":"venue"
},
  "geometry": {"coordinates":[-84.2547,33.934101],"type":"Point"}
}