{
  "type": "Feature",
  "properties": {
    "iso:country":"US",
    "sg:address":"127 Lovell Rd",
    "sg:city":"Toccoa",
    "sg:classifiers":[
        {
            "category":"Building & Trades",
            "subcategory":"Construction",
            "type":"Services"
        }
    ],
    "sg:phone":"+1 706 886 5891",
    "sg:postcode":"30577",
    "sg:province":"GA",
    "sg:tags":[
        "contractor"
    ],
    "wof:name":"Cobbs Roofing Shtmtl Works",
    "wof:placetype":"venue"
},
  "geometry": {"coordinates":[-83.33063900000001,34.558256],"type":"Point"}
}