{
  "type": "Feature",
  "properties": {
    "addr:full":"290 Arrowood Rd Tyrone GA 30290",
    "addr:housenumber":"290",
    "addr:postcode":"30290",
    "addr:street":"Arrowood Rd",
    "iso:country":"US",
    "sg:address":"290 Arrowood Rd",
    "sg:city":"Tyrone",
    "sg:classifiers":[
        {
            "category":"Freight",
            "type":"Transportation"
        }
    ],
    "sg:phone":"+1 678 364 8757",
    "sg:postcode":"30290",
    "sg:province":"GA",
    "sg:tags":[
        "operator",
        "trucking"
    ],
    "wof:name":"R and S Hauling Incorporated",
    "wof:placetype":"venue"
},
  "geometry": {"coordinates":[-84.59623000000001,33.480265],"type":"Point"}
}