{
  "type": "Feature",
  "properties": {
    "addr:full":"741 Pittman Ln Canton GA 30114",
    "addr:housenumber":"741",
    "addr:postcode":"30114",
    "addr:street":"Pittman Ln",
    "iso:country":"US",
    "sg:address":"741 Pittman Ln",
    "sg:city":"Canton",
    "sg:classifiers":[
        {
            "category":"Professional",
            "type":"Services"
        }
    ],
    "sg:phone":"+1 770 479 8898",
    "sg:postcode":"30114",
    "sg:province":"GA",
    "wof:name":"Jerry Dillon",
    "wof:placetype":"venue"
},
  "geometry": {"coordinates":[-84.50116300000001,34.343243],"type":"Point"}
}