{
  "type": "Feature",
  "properties": {
    "iso:country":"US",
    "sg:address":"2029 Thomas Rd",
    "sg:city":"Canton",
    "sg:classifiers":[
        {
            "category":"Personal",
            "subcategory":"Beauty Salon",
            "type":"Services"
        }
    ],
    "sg:phone":"+1 770 720 4247",
    "sg:postcode":"30115",
    "sg:province":"GA",
    "sg:tags":[
        "shop"
    ],
    "wof:name":"Hair Reflections By Wanda",
    "wof:placetype":"venue"
},
  "geometry": {"coordinates":[-84.404866,34.194911],"type":"Point"}
}