{
  "type": "Feature",
  "properties": {
    "iso:country":"US",
    "sg:address":"1028 Gray Hwy",
    "sg:city":"Macon",
    "sg:classifiers":[
        {
            "category":"Shopping",
            "type":"Retail Goods"
        },
        {
            "category":"Shopping",
            "subcategory":"Clothing, Apparel, & Fashions",
            "type":"Retail Goods"
        }
    ],
    "sg:phone":"+1 478 745 9600",
    "sg:postcode":"31211",
    "sg:province":"GA",
    "sg:tags":[
        "trophy",
        "medal",
        "award",
        "merchandise"
    ],
    "wof:name":"Daniely Trophies & Awards Inc",
    "wof:placetype":"venue"
},
  "geometry": {"coordinates":[-83.61836,32.854388],"type":"Point"}
}