{
  "type": "Feature",
  "properties": {
    "iso:country":"US",
    "sg:address":"4150 Mercer University Dr",
    "sg:city":"Macon",
    "sg:classifiers":[
        {
            "category":"Social Services",
            "subcategory":"Child Care",
            "type":"Services"
        }
    ],
    "sg:phone":"+1 478 477 1236",
    "sg:postcode":"31204",
    "sg:province":"GA",
    "sg:website":"www.childrensfriend.com",
    "wof:name":"Children's Friend Learning Ctr",
    "wof:placetype":"venue"
},
  "geometry": {"coordinates":[-83.70698,32.825006],"type":"Point"}
}