{
  "type": "Feature",
  "properties": {
    "addr:full":"1868 Washington Ave Atlanta GA 30344",
    "addr:housenumber":"1868",
    "addr:postcode":"30344",
    "addr:street":"Washington Ave",
    "iso:country":"US",
    "sg:address":"1868 Washington Ave",
    "sg:city":"Atlanta",
    "sg:classifiers":[
        {
            "category":"Real Estate",
            "subcategory":"Real Estate Agent",
            "type":"Services"
        }
    ],
    "sg:phone":"+1 404 209 8898",
    "sg:postcode":"30344",
    "sg:province":"GA",
    "sg:tags":[
        "management"
    ],
    "wof:name":"Northeast Property Mgmt Inc",
    "wof:placetype":"venue"
},
  "geometry": {"coordinates":[-84.44955899999999,33.675667],"type":"Point"}
}