{
  "type": "Feature",
  "properties": {
    "addr:full":"1225 Old Alpharetta Rd Alpharetta GA 30005",
    "addr:housenumber":"1225",
    "addr:postcode":"30005",
    "addr:street":"Old Alpharetta Rd",
    "iso:country":"US",
    "sg:address":"1225 Old Alpharetta Rd",
    "sg:city":"Alpharetta",
    "sg:classifiers":[
        {
            "category":"Professional",
            "subcategory":"Management & Consulting",
            "type":"Services"
        }
    ],
    "sg:phone":"+1 678 455 5365",
    "sg:postcode":"30005",
    "sg:province":"GA",
    "sg:tags":[
        "consultant",
        "business"
    ],
    "wof:name":"Mc Calla Co",
    "wof:placetype":"venue"
},
  "geometry": {"coordinates":[-84.193648,34.108593],"type":"Point"}
}