{
  "type": "Feature",
  "properties": {
    "addr:full":"2011 McFarland Ave Rossville GA 30741",
    "addr:housenumber":"2011",
    "addr:postcode":"30741",
    "addr:street":"Mcfarland Ave",
    "iso:country":"US",
    "sg:address":"2011 McFarland Ave",
    "sg:city":"Rossville",
    "sg:classifiers":[
        {
            "category":"Organizations",
            "subcategory":"Religious Organization",
            "type":"Services"
        }
    ],
    "sg:phone":"+1 706 866 4111",
    "sg:postcode":"30741",
    "sg:province":"GA",
    "sg:tags":[
        "church"
    ],
    "wof:name":"Fairview Church-Nazarene Shoe",
    "wof:placetype":"venue"
},
  "geometry": {"coordinates":[-85.288307,34.947146],"type":"Point"}
}