{
  "type": "Feature",
  "properties": {
    "iso:country":"US",
    "sg:address":"1001 S Martin Luther King Blvd",
    "sg:city":"Americus",
    "sg:classifiers":[
        {
            "category":"Bars & Pubs",
            "type":"Food & Drink"
        }
    ],
    "sg:phone":"+1 229 928 2137",
    "sg:postcode":"31719",
    "sg:province":"GA",
    "sg:tags":[
        "drinking",
        "beverage",
        "alcoholic"
    ],
    "wof:name":"Jumpin Johnny",
    "wof:placetype":"venue"
},
  "geometry": {"coordinates":[-84.252999,32.059233],"type":"Point"}
}