{
  "type": "Feature",
  "properties": {
    "addr:full":"6668 Mount Zion Blvd Morrow GA 30260",
    "addr:housenumber":"6668",
    "addr:postcode":"30260",
    "addr:street":"Mount Zion Blvd",
    "iso:country":"US",
    "sg:address":"6668 Mount Zion Blvd",
    "sg:city":"Morrow",
    "sg:classifiers":[
        {
            "category":"Real Estate",
            "subcategory":"Real Estate Operator",
            "type":"Services"
        }
    ],
    "sg:phone":"+1 770 961 5008",
    "sg:postcode":"30260",
    "sg:province":"GA",
    "sg:tags":[
        "apartment"
    ],
    "wof:name":"Regal Pointe Apartments",
    "wof:placetype":"venue"
},
  "geometry": {"coordinates":[-84.308502,33.571899],"type":"Point"}
}