{
  "type": "Feature",
  "properties": {
    "iso:country":"US",
    "sg:address":"250 Harris Ln",
    "sg:city":"Brunswick",
    "sg:classifiers":[
        {
            "category":"Wholesale",
            "subcategory":"Motor Vehicles",
            "type":"Manufacturing & Wholesale Goods"
        }
    ],
    "sg:phone":"+1 912 280 0505",
    "sg:postcode":"31561",
    "sg:province":"GA",
    "wof:name":"Andrew Vazquez Inc",
    "wof:placetype":"venue"
},
  "geometry": {"coordinates":[-81.325244,31.213931],"type":"Point"}
}