{
  "type": "Feature",
  "properties": {
    "iso:country":"US",
    "sg:address":"940 Haymon Morris Rd",
    "sg:city":"Winder",
    "sg:classifiers":[
        {
            "category":"Education",
            "subcategory":"School",
            "type":"Public Place"
        },
        {
            "category":"Government",
            "subcategory":"Office",
            "type":"Public Place"
        }
    ],
    "sg:phone":"+1 770 586 5111",
    "sg:postcode":"30680",
    "sg:province":"GA",
    "sg:tags":[
        "parish",
        "high",
        "government-county"
    ],
    "sg:website":"http://www.barrow.k12.ga.us",
    "wof:name":"Apalachee High School",
    "wof:placetype":"venue"
},
  "geometry": {"coordinates":[-83.78460699999999,33.950531],"type":"Point"}
}