{
  "type": "Feature",
  "properties": {
    "addr:full":"800 Sudbury Rd NE Atlanta GA 30328",
    "addr:housenumber":"800",
    "addr:postcode":"30328",
    "addr:street":"Sudbury Rd Ne",
    "iso:country":"US",
    "sg:address":"800 Sudbury Rd NE",
    "sg:city":"Atlanta",
    "sg:classifiers":[
        {
            "category":"Professional",
            "subcategory":"Business Services",
            "type":"Services"
        }
    ],
    "sg:phone":"+1 770 394 2195",
    "sg:postcode":"30328",
    "sg:province":"GA",
    "wof:name":"Thurmond Family Group Inc",
    "wof:placetype":"venue"
},
  "geometry": {"coordinates":[-84.35991199999999,33.952496],"type":"Point"}
}