{
  "type": "Feature",
  "properties": {
    "addr:full":"1895 D Youville Ln Atlanta GA 30341",
    "addr:housenumber":"1895 d",
    "addr:postcode":"30341",
    "addr:street":"Youville Ln",
    "iso:country":"US",
    "sg:address":"1895 D Youville Ln",
    "sg:city":"Atlanta",
    "sg:classifiers":[
        {
            "category":"Professional",
            "subcategory":"Management & Consulting",
            "type":"Services"
        }
    ],
    "sg:phone":"+1 404 372 7313",
    "sg:postcode":"30341",
    "sg:province":"GA",
    "sg:tags":[
        "sound",
        "system",
        "consultant"
    ],
    "wof:name":"On-Set Sound",
    "wof:placetype":"venue"
},
  "geometry": {"coordinates":[-84.312298,33.910632],"type":"Point"}
}