{
  "type": "Feature",
  "properties": {
    "addr:full":"1905 Scenic Hwy N Ste 640 Snellville GA 30078",
    "addr:housenumber":"1905",
    "addr:postcode":"30078",
    "addr:street":"Scenic Hwy N Ste 640",
    "iso:country":"US",
    "sg:address":"1905 Scenic Hwy N Ste 640",
    "sg:city":"Snellville",
    "sg:classifiers":[
        {
            "category":"Shopping",
            "subcategory":"Department Store",
            "type":"Retail Goods"
        }
    ],
    "sg:phone":"+1 770 736 1113",
    "sg:postcode":"30078",
    "sg:province":"GA",
    "wof:name":"Target Stores",
    "wof:placetype":"venue"
},
  "geometry": {"coordinates":[-84.013199,33.876202],"type":"Point"}
}