{
  "type": "Feature",
  "properties": {
    "iso:country":"US",
    "sg:address":"2837 Swamp Rd",
    "sg:city":"Waycross",
    "sg:classifiers":[
        {
            "category":"Building & Trades",
            "subcategory":"Plumbing",
            "type":"Services"
        }
    ],
    "sg:phone":"+1 912 287 1618",
    "sg:postcode":"31503",
    "sg:province":"GA",
    "sg:tags":[
        "plumbing",
        "contractor"
    ],
    "wof:name":"Lairsey Plumbing Co",
    "wof:placetype":"venue"
},
  "geometry": {"coordinates":[-82.34948199999999,31.17076],"type":"Point"}
}