{
  "type": "Feature",
  "properties": {
    "iso:country":"US",
    "sg:address":"425 Allens Landing Ct",
    "sg:city":"Lawrenceville",
    "sg:classifiers":[
        {
            "category":"Shopping",
            "subcategory":"Computers & Home Electronics",
            "type":"Retail Goods"
        }
    ],
    "sg:phone":"+1 678 523 3272",
    "sg:postcode":"30045",
    "sg:province":"GA",
    "wof:name":"Coleman Computer & Network Svc",
    "wof:placetype":"venue"
},
  "geometry": {"coordinates":[-83.951972,33.948503],"type":"Point"}
}