{
  "type": "Feature",
  "properties": {
    "iso:country":"US",
    "sg:address":"1588 Atkinson Rd",
    "sg:city":"Lawrenceville",
    "sg:classifiers":[
        {
            "category":"Professional",
            "subcategory":"Computer Services",
            "type":"Services"
        }
    ],
    "sg:phone":"+1 678 376 5959",
    "sg:postcode":"30043",
    "sg:province":"GA",
    "sg:tags":[
        "software"
    ],
    "wof:name":"A R T",
    "wof:placetype":"venue"
},
  "geometry": {"coordinates":[-84.07414300000001,33.970132],"type":"Point"}
}