{
  "type": "Feature",
  "properties": {
    "addr:full":"51 Cleveland Rd Locust Grove GA 30248",
    "addr:housenumber":"51",
    "addr:postcode":"30248",
    "addr:street":"Cleveland Rd",
    "iso:country":"US",
    "sg:address":"51 Cleveland Rd",
    "sg:city":"Locust Grove",
    "sg:classifiers":[
        {
            "category":"Professional",
            "subcategory":"Detective & Security Services",
            "type":"Services"
        }
    ],
    "sg:phone":"+1 770 957 4780",
    "sg:postcode":"30248",
    "sg:province":"GA",
    "sg:tags":[
        "system"
    ],
    "wof:name":"White Security System",
    "wof:placetype":"venue"
},
  "geometry": {"coordinates":[-84.049834,33.370292],"type":"Point"}
}