{
  "type": "Feature",
  "properties": {
    "addr:full":"421 Bowman Dr Resaca GA 30735",
    "addr:housenumber":"421",
    "addr:postcode":"30735",
    "addr:street":"Bowman Dr",
    "iso:country":"US",
    "sg:address":"421 Bowman Dr",
    "sg:city":"Resaca",
    "sg:classifiers":[
        {
            "category":"Restaurant",
            "type":"Food & Drink"
        }
    ],
    "sg:phone":"+1 706 625 5827",
    "sg:postcode":"30735",
    "sg:province":"GA",
    "sg:tags":[
        "eating"
    ],
    "wof:name":"Bowman Catering LLC",
    "wof:placetype":"venue"
},
  "geometry": {"coordinates":[-84.89043700000001,34.613873],"type":"Point"}
}