{
  "type": "Feature",
  "properties": {
    "iso:country":"US",
    "sg:address":"303 Falls Mountain Ct",
    "sg:city":"Dahlonega",
    "sg:classifiers":[
        {
            "category":"Professional",
            "type":"Services"
        }
    ],
    "sg:phone":"+1 706 867 9498",
    "sg:postcode":"30533",
    "sg:province":"GA",
    "wof:name":"Jet Exchange Inc",
    "wof:placetype":"venue"
},
  "geometry": {"coordinates":[-84.02161599999999,34.552905],"type":"Point"}
}