{
  "type": "Feature",
  "properties": {
    "iso:country":"US",
    "sg:address":"14191 River Rd",
    "sg:city":"Girard",
    "sg:classifiers":[
        {
            "category":"Personal",
            "type":"Services"
        },
        {
            "category":"Professional",
            "subcategory":"Art Services",
            "type":"Services"
        },
        {
            "category":"Professional",
            "subcategory":"Printing & Photocopies",
            "type":"Services"
        }
    ],
    "sg:phone":"+1 706 726 1404",
    "sg:postcode":"30426",
    "sg:province":"GA",
    "sg:tags":[
        "photographers-portrait",
        "videography",
        "photography",
        "planning",
        "wedding",
        "party",
        "photographers-commercial",
        "event"
    ],
    "sg:website":"http://www.chuckrevillephotography.com",
    "wof:name":"Chuck Reville Photography",
    "wof:placetype":"venue"
},
  "geometry": {"coordinates":[-81.59676,33.041555],"type":"Point"}
}