{
  "type": "Feature",
  "properties": {
    "addr:full":"108 Crooked Wood Ln Savannah GA 31406",
    "addr:housenumber":"108",
    "addr:postcode":"31406",
    "addr:street":"Crooked Wood Ln",
    "iso:country":"US",
    "sg:address":"108 Crooked Wood Ln",
    "sg:city":"Savannah",
    "sg:classifiers":[
        {
            "category":"Professional",
            "subcategory":"Management & Consulting",
            "type":"Services"
        }
    ],
    "sg:phone":"+1 912 354 1455",
    "sg:postcode":"31406",
    "sg:province":"GA",
    "wof:name":"Dana S Oliver & Assoc Inc",
    "wof:placetype":"venue"
},
  "geometry": {"coordinates":[-81.027671,31.998485],"type":"Point"}
}