{
  "type": "Feature",
  "properties": {
    "addr:full":"2153 Pond Rd Duluth GA 30096",
    "addr:housenumber":"2153",
    "addr:postcode":"30096",
    "addr:street":"Pond Rd",
    "iso:country":"US",
    "sg:address":"2153 Pond Rd",
    "sg:city":"Duluth",
    "sg:classifiers":[
        {
            "category":"Banks & Credit Unions",
            "subcategory":"Bank",
            "type":"Services"
        }
    ],
    "sg:phone":"+1 770 849 0788",
    "sg:postcode":"30096",
    "sg:province":"GA",
    "sg:tags":[
        "broker",
        "mortgage"
    ],
    "wof:name":"Home Loan Mortgage Corporation",
    "wof:placetype":"venue"
},
  "geometry": {"coordinates":[-84.16896199999999,33.941866],"type":"Point"}
}