{
  "type": "Feature",
  "properties": {
    "iso:country":"US",
    "sg:address":"1300 Commerce Dr Fl 6",
    "sg:city":"Decatur",
    "sg:classifiers":[
        {
            "category":"Banks & Credit Unions",
            "subcategory":"Investment Brokerage",
            "type":"Services"
        },
        {
            "category":"Government",
            "subcategory":"Office",
            "type":"Public Place"
        }
    ],
    "sg:phone":"+1 404 371 2886",
    "sg:postcode":"30030",
    "sg:province":"GA",
    "sg:tags":[
        "development",
        "councils",
        "parish",
        "economic",
        "government-county",
        "commissions",
        "authorities"
    ],
    "sg:website":"http://www.sugarcreekgolf.net",
    "wof:name":"Commissioners, Board Of",
    "wof:placetype":"venue"
},
  "geometry": {"coordinates":[-84.298866,33.774578],"type":"Point"}
}