{
  "type": "Feature",
  "properties": {
    "iso:country":"US",
    "sg:address":"7027 Swift St",
    "sg:city":"Lithonia",
    "sg:classifiers":[
        {
            "category":"Home & Garden",
            "subcategory":"Furniture",
            "type":"Retail Goods"
        }
    ],
    "sg:phone":"+1 770 482 6175",
    "sg:postcode":"30058",
    "sg:province":"GA",
    "wof:name":"Lithonia Furniture Store Inc",
    "wof:placetype":"venue"
},
  "geometry": {"coordinates":[-84.106408,33.713059],"type":"Point"}
}