{
  "type": "Feature",
  "properties": {
    "iso:country":"US",
    "sg:address":"366 W Memorial Dr",
    "sg:city":"Dallas",
    "sg:classifiers":[
        {
            "category":"Building & Trades",
            "subcategory":"Construction",
            "type":"Services"
        }
    ],
    "sg:phone":"+1 770 445 2443",
    "sg:postcode":"30132",
    "sg:province":"GA",
    "sg:tags":[
        "house"
    ],
    "wof:name":"Spartan Construction",
    "wof:placetype":"venue"
},
  "geometry": {"coordinates":[-84.84647200000001,33.923697],"type":"Point"}
}