{
  "type": "Feature",
  "properties": {
    "iso:country":"US",
    "sg:address":"150 Aspen Way",
    "sg:city":"Fayetteville",
    "sg:classifiers":[
        {
            "category":"Building & Trades",
            "subcategory":"Construction",
            "type":"Services"
        }
    ],
    "sg:phone":"+1 770 632 5583",
    "sg:postcode":"30214",
    "sg:province":"GA",
    "sg:tags":[
        "concrete",
        "contractor"
    ],
    "wof:name":"ALR Construction",
    "wof:placetype":"venue"
},
  "geometry": {"coordinates":[-84.552008,33.440451],"type":"Point"}
}