{
  "type": "Feature",
  "properties": {
    "iso:country":"US",
    "sg:address":"6350 Oakley Rd",
    "sg:city":"Union City",
    "sg:classifiers":[
        {
            "category":"Personal",
            "subcategory":"Beauty Salon",
            "type":"Services"
        }
    ],
    "sg:phone":"+1 770 964 3251",
    "sg:postcode":"30291",
    "sg:province":"GA",
    "wof:name":"Mystique Hair Studio",
    "wof:placetype":"venue"
},
  "geometry": {"coordinates":[-84.531854,33.584892],"type":"Point"}
}