{
  "type": "Feature",
  "properties": {
    "addr:full":"1620 Ocean Rd St Simons Island GA 31522",
    "addr:housenumber":"1620",
    "addr:postcode":"31522",
    "addr:street":"Ocean Rd St Simons Island",
    "iso:country":"US",
    "sg:address":"1620 Ocean Rd",
    "sg:city":"St Simons Island",
    "sg:classifiers":[
        {
            "category":"Professional",
            "subcategory":"Business Services",
            "type":"Services"
        }
    ],
    "sg:phone":"+1 912 638 1260",
    "sg:postcode":"31522",
    "sg:province":"GA",
    "sg:tags":[
        "interior",
        "consultant",
        "design",
        "decorator"
    ],
    "wof:name":"Karen & Co",
    "wof:placetype":"venue"
},
  "geometry": {"coordinates":[-81.373839,31.148087],"type":"Point"}
}