{
  "type": "Feature",
  "properties": {
    "iso:country":"US",
    "sg:address":"6980 Brown Dr S",
    "sg:city":"Fairburn",
    "sg:classifiers":[
        {
            "category":"Professional",
            "subcategory":"Business Services",
            "type":"Services"
        }
    ],
    "sg:phone":"+1 770 969 7777",
    "sg:postcode":"30213",
    "sg:province":"GA",
    "sg:tags":[
        "interior",
        "design"
    ],
    "wof:name":"Jtj Enterprises Inc",
    "wof:placetype":"venue"
},
  "geometry": {"coordinates":[-84.492656,33.565733],"type":"Point"}
}