{
  "type": "Feature",
  "properties": {
    "iso:country":"US",
    "sg:address":"4604 Augusta Rd",
    "sg:city":"Garden City",
    "sg:classifiers":[
        {
            "category":"Restaurant",
            "type":"Food & Drink"
        }
    ],
    "sg:phone":"+1 912 966 5325",
    "sg:postcode":"31408",
    "sg:province":"GA",
    "wof:name":"Central Park USA",
    "wof:placetype":"venue"
},
  "geometry": {"coordinates":[-81.156852,32.108555],"type":"Point"}
}