{
  "type": "Feature",
  "properties": {
    "addr:full":"307 W 4th St Waynesboro GA 30830",
    "addr:housenumber":"307",
    "addr:postcode":"30830",
    "addr:street":"W 4Th St",
    "iso:country":"US",
    "sg:address":"307 W 4th St",
    "sg:city":"Waynesboro",
    "sg:classifiers":[
        {
            "category":"Health Services",
            "subcategory":"Doctor",
            "type":"Services"
        }
    ],
    "sg:phone":"+1 706 554 2916",
    "sg:postcode":"30830",
    "sg:province":"GA",
    "sg:tags":[
        "physician",
        "surgeon"
    ],
    "wof:name":"Burke County Medical Specialists",
    "wof:placetype":"venue"
},
  "geometry": {"coordinates":[-82.013666,33.083689],"type":"Point"}
}