{
  "type": "Feature",
  "properties": {
    "addr:full":"2769 Donald Lee Hollowell Pkwy NW Atlanta GA 30318",
    "addr:housenumber":"2769",
    "addr:postcode":"30318",
    "addr:street":"Donald Lee Hollowell Pkwy Nw",
    "iso:country":"US",
    "sg:address":"2769 Donald Lee Hollowell Pkwy NW",
    "sg:city":"Atlanta",
    "sg:classifiers":[
        {
            "category":"Social Services",
            "subcategory":"Child Care",
            "type":"Services"
        },
        {
            "category":"Education",
            "subcategory":"Preschool",
            "type":"Public Place"
        },
        {
            "category":"Education",
            "subcategory":"School",
            "type":"Public Place"
        }
    ],
    "sg:phone":"+1 404 794 0404",
    "sg:postcode":"30318",
    "sg:province":"GA",
    "sg:tags":[
        "kindergarten",
        "k-",
        "private",
        "day"
    ],
    "wof:name":"Sesame Seed Preschool",
    "wof:placetype":"venue"
},
  "geometry": {"coordinates":[-84.478179,33.778771],"type":"Point"}
}