{
  "type": "Feature",
  "properties": {
    "iso:country":"US",
    "sg:address":"17840 Morganton Hwy",
    "sg:city":"Morganton",
    "sg:classifiers":[
        {
            "category":"Real Estate",
            "subcategory":"Developer",
            "type":"Services"
        }
    ],
    "sg:phone":"+1 706 838 5319",
    "sg:postcode":"30560",
    "sg:province":"GA",
    "sg:tags":[
        "cemetery"
    ],
    "wof:name":"Upper Wilscott Bapt Cemtry Fou",
    "wof:placetype":"venue"
},
  "geometry": {"coordinates":[-84.189948,34.841272],"type":"Point"}
}