{
  "type": "Feature",
  "properties": {
    "iso:country":"US",
    "sg:address":"412 Parliament Rd",
    "sg:city":"Augusta",
    "sg:classifiers":[
        {
            "category":"Professional",
            "type":"Services"
        }
    ],
    "sg:phone":"+1 706 855 1918",
    "sg:postcode":"30907",
    "sg:province":"GA",
    "wof:name":"H Stan Claxton",
    "wof:placetype":"venue"
},
  "geometry": {"coordinates":[-82.06782200000001,33.527965],"type":"Point"}
}