{
  "type": "Feature",
  "properties": {
    "iso:country":"US",
    "sg:address":"478 Northdale Rd",
    "sg:city":"Lawrenceville",
    "sg:classifiers":[
        {
            "category":"Home & Garden",
            "subcategory":"Carpets & Floor Coverings",
            "type":"Retail Goods"
        }
    ],
    "sg:phone":"+1 678 376 7992",
    "sg:postcode":"30045",
    "sg:province":"GA",
    "sg:tags":[
        "material"
    ],
    "wof:name":"Floor Store",
    "wof:placetype":"venue"
},
  "geometry": {"coordinates":[-83.991033,33.968359],"type":"Point"}
}