{
  "type": "Feature",
  "properties": {
    "addr:full":"804 Swanson Dr Lawrenceville GA 30043",
    "addr:housenumber":"804",
    "addr:postcode":"30043",
    "addr:street":"Swanson Dr",
    "iso:country":"US",
    "sg:address":"804 Swanson Dr",
    "sg:city":"Lawrenceville",
    "sg:classifiers":[
        {
            "category":"Restaurant",
            "type":"Food & Drink"
        }
    ],
    "sg:menulink":"http://www.allmenus.com/ga/lawrenceville/203336-mcdonalds/menu/",
    "sg:postcode":"30043",
    "sg:province":"GA",
    "sg:tags":[
        "burger",
        "american"
    ],
    "wof:name":"McDonald's",
    "wof:placetype":"venue"
},
  "geometry": {"coordinates":[-83.975433,33.985971],"type":"Point"}
}