{
  "type": "Feature",
  "properties": {
    "addr:full":"4820 Clark Howell Hwy Atlanta GA 30349",
    "addr:housenumber":"4820",
    "addr:postcode":"30349",
    "addr:street":"Clark Howell Hwy",
    "iso:country":"US",
    "sg:address":"4820 Clark Howell Hwy",
    "sg:city":"Atlanta",
    "sg:classifiers":[
        {
            "category":"Health Services",
            "subcategory":"Clinic",
            "type":"Services"
        }
    ],
    "sg:phone":"+1 404 761 6458",
    "sg:postcode":"30349",
    "sg:province":"GA",
    "sg:tags":[
        "home"
    ],
    "wof:name":"American Home Care",
    "wof:placetype":"venue"
},
  "geometry": {"coordinates":[-84.408866,33.624853],"type":"Point"}
}