{
  "type": "Feature",
  "properties": {
    "addr:full":"411 Martin Dr Jonesboro GA 30238",
    "addr:housenumber":"411",
    "addr:postcode":"30238",
    "addr:street":"Martin Dr",
    "iso:country":"US",
    "sg:address":"411 Martin Dr",
    "sg:city":"Jonesboro",
    "sg:classifiers":[
        {
            "category":"Health Services",
            "subcategory":"Nursing And Care Facility",
            "type":"Services"
        }
    ],
    "sg:phone":"+1 770 471 1933",
    "sg:postcode":"30238",
    "sg:province":"GA",
    "sg:tags":[
        "home",
        "retirement",
        "community"
    ],
    "wof:name":"Martin Drive Group Home",
    "wof:placetype":"venue"
},
  "geometry": {"coordinates":[-84.40410300000001,33.504485],"type":"Point"}
}