{
  "type": "Feature",
  "properties": {
    "iso:country":"US",
    "sg:address":"379 Woodward Ave SE",
    "sg:city":"Atlanta",
    "sg:classifiers":[
        {
            "category":"Arts & Performance",
            "subcategory":"Theater",
            "type":"Entertainment"
        }
    ],
    "sg:phone":"+1 404 222 9590",
    "sg:postcode":"30312",
    "sg:province":"GA",
    "sg:tags":[
        "theatrical",
        "manager",
        "producer"
    ],
    "wof:name":"Mud Puppy Productions Inc",
    "wof:placetype":"venue"
},
  "geometry": {"coordinates":[-84.375024,33.745484],"type":"Point"}
}