{
  "type": "Feature",
  "properties": {
    "iso:country":"US",
    "sg:address":"648 Hearthstone Ln SE",
    "sg:city":"Marietta",
    "sg:classifiers":[
        {
            "category":"Communications",
            "subcategory":"Television Station",
            "type":"Services"
        }
    ],
    "sg:phone":"+1 770 977 9933",
    "sg:postcode":"30067",
    "sg:province":"GA",
    "wof:name":"Vision Latina Television & Broadcasting Servics Uk",
    "wof:placetype":"venue"
},
  "geometry": {"coordinates":[-84.471397,33.9361],"type":"Point"}
}