{
  "type": "Feature",
  "properties": {
    "addr:full":"555 Victory Dr Lyons GA 30436",
    "addr:housenumber":"555",
    "addr:postcode":"30436",
    "addr:street":"Victory Dr",
    "iso:country":"US",
    "sg:address":"555 Victory Dr",
    "sg:city":"Lyons",
    "sg:classifiers":[
        {
            "category":"Manufacturing",
            "subcategory":"Apparel",
            "type":"Manufacturing & Wholesale Goods"
        }
    ],
    "sg:phone":"+1 912 526 1100",
    "sg:postcode":"30436",
    "sg:province":"GA",
    "sg:tags":[
        "boy",
        "furnishing"
    ],
    "wof:name":"Oxford Golf-Private Lable",
    "wof:placetype":"venue"
},
  "geometry": {"coordinates":[-82.324676,32.189664],"type":"Point"}
}