{
  "type": "Feature",
  "properties": {
    "addr:full":"8167 Colquitt Rd Atlanta GA 30350",
    "addr:housenumber":"8167",
    "addr:postcode":"30350",
    "addr:street":"Colquitt Rd",
    "iso:country":"US",
    "sg:address":"8167 Colquitt Rd",
    "sg:city":"Atlanta",
    "sg:classifiers":[
        {
            "category":"Wholesale",
            "subcategory":"Vending Machines",
            "type":"Manufacturing & Wholesale Goods"
        }
    ],
    "sg:phone":"+1 404 435 5795",
    "sg:postcode":"30350",
    "sg:province":"GA",
    "wof:name":"Atlantic Vending Inc",
    "wof:placetype":"venue"
},
  "geometry": {"coordinates":[-84.34723200000001,33.978376],"type":"Point"}
}