{
  "type": "Feature",
  "properties": {
    "iso:country":"US",
    "sg:address":"39 Sugar Ln",
    "sg:city":"Blue Ridge",
    "sg:classifiers":[
        {
            "category":"Building & Trades",
            "subcategory":"Plumbing",
            "type":"Services"
        }
    ],
    "sg:phone":"+1 706 632 8356",
    "sg:postcode":"30513",
    "sg:province":"GA",
    "sg:tags":[
        "repair",
        "heating"
    ],
    "wof:name":"Bobs Kerosene Heater Service",
    "wof:placetype":"venue"
},
  "geometry": {"coordinates":[-84.34276300000001,34.92329],"type":"Point"}
}