{
  "type": "Feature",
  "properties": {
    "iso:country":"US",
    "sg:address":"19 S Harney St",
    "sg:city":"Camilla",
    "sg:classifiers":[
        {
            "category":"Personal",
            "subcategory":"Beauty Salon",
            "type":"Services"
        }
    ],
    "sg:phone":"+1 229 336 8422",
    "sg:postcode":"31730",
    "sg:province":"GA",
    "sg:tags":[
        "shop"
    ],
    "wof:name":"Beauty Connection",
    "wof:placetype":"venue"
},
  "geometry": {"coordinates":[-84.208788,31.230473],"type":"Point"}
}