{
  "type": "Feature",
  "properties": {
    "addr:full":"4919 Old Waynesboro Rd Hephzibah GA 30815",
    "addr:housenumber":"4919",
    "addr:postcode":"30815",
    "addr:street":"Old Waynesboro Rd",
    "iso:country":"US",
    "sg:address":"4919 Old Waynesboro Rd",
    "sg:city":"Hephzibah",
    "sg:classifiers":[
        {
            "category":"Manufacturing",
            "subcategory":"Printing",
            "type":"Manufacturing & Wholesale Goods"
        }
    ],
    "sg:phone":"+1 706 592 0770",
    "sg:postcode":"30815",
    "sg:province":"GA",
    "sg:tags":[
        "lithographic",
        "commercial"
    ],
    "wof:name":"Majestic Sportswear & Screen P",
    "wof:placetype":"venue"
},
  "geometry": {"coordinates":[-82.007773,33.259422],"type":"Point"}
}