{
  "type": "Feature",
  "properties": {
    "addr:full":"401 Oak Grove Rd Mc Donough GA 30253",
    "addr:housenumber":"401",
    "addr:postcode":"30253",
    "addr:street":"Oak Grove Rd",
    "iso:country":"US",
    "sg:address":"401 Oak Grove Rd",
    "sg:city":"Mc Donough",
    "sg:classifiers":[
        {
            "category":"Professional",
            "type":"Services"
        }
    ],
    "sg:phone":"+1 770 957 5331",
    "sg:postcode":"30253",
    "sg:province":"GA",
    "wof:name":"BGB Services Inc",
    "wof:placetype":"venue"
},
  "geometry": {"coordinates":[-84.19446499999999,33.472189],"type":"Point"}
}