{
  "type": "Feature",
  "properties": {
    "iso:country":"US",
    "sg:address":"3461 Wrightsboro Rd",
    "sg:city":"Augusta",
    "sg:classifiers":[
        {
            "category":"Banks & Credit Unions",
            "subcategory":"Bank",
            "type":"Services"
        }
    ],
    "sg:phone":"+1 706 733 1022",
    "sg:postcode":"30909",
    "sg:province":"GA",
    "sg:tags":[
        "personal",
        "institution"
    ],
    "wof:name":"Beneficial",
    "wof:placetype":"venue"
},
  "geometry": {"coordinates":[-82.08293999999999,33.466814],"type":"Point"}
}