{
  "type": "Feature",
  "properties": {
    "iso:country":"US",
    "sg:address":"1460 Moreland Ave SE",
    "sg:city":"Atlanta",
    "sg:classifiers":[
        {
            "category":"Retail",
            "subcategory":"Car Wash",
            "type":"Services"
        }
    ],
    "sg:phone":"+1 404 627 5155",
    "sg:postcode":"30316",
    "sg:province":"GA",
    "sg:tags":[
        "carwash"
    ],
    "wof:name":"Dynamicbig Truck Detail",
    "wof:placetype":"venue"
},
  "geometry": {"coordinates":[-84.349585,33.711061],"type":"Point"}
}