{
  "type": "Feature",
  "properties": {
    "addr:full":"115 Robertson Rd Lagrange GA 30241",
    "addr:housenumber":"115",
    "addr:postcode":"30241",
    "addr:street":"Robertson Rd",
    "iso:country":"US",
    "sg:address":"115 Robertson Rd",
    "sg:city":"Lagrange",
    "sg:classifiers":[
        {
            "category":"Manufacturing",
            "subcategory":"Buildings",
            "type":"Manufacturing & Wholesale Goods"
        },
        {
            "category":"Building & Trades",
            "subcategory":"Construction",
            "type":"Services"
        }
    ],
    "sg:phone":"+1 706 882 0442",
    "sg:postcode":"30241",
    "sg:province":"GA",
    "sg:tags":[
        "home",
        "builder",
        "contractor"
    ],
    "sg:website":"http://www.philthepower.com",
    "wof:name":"Taylor Construction",
    "wof:placetype":"venue"
},
  "geometry": {"coordinates":[-84.969106,32.974587],"type":"Point"}
}