{
  "type": "Feature",
  "properties": {
    "addr:full":"3301 Bostwick Rd Madison GA 30650",
    "addr:housenumber":"3301",
    "addr:postcode":"30650",
    "addr:street":"Bostwick Rd",
    "iso:country":"US",
    "sg:address":"3301 Bostwick Rd",
    "sg:city":"Madison",
    "sg:classifiers":[
        {
            "category":"Freight",
            "type":"Transportation"
        }
    ],
    "sg:phone":"+1 706 342 8671",
    "sg:postcode":"30650",
    "sg:province":"GA",
    "sg:tags":[
        "operator",
        "trucking"
    ],
    "wof:name":"H E Transport",
    "wof:placetype":"venue"
},
  "geometry": {"coordinates":[-83.497085,33.658271],"type":"Point"}
}