{
  "type": "Feature",
  "properties": {
    "iso:country":"US",
    "sg:address":"418 E Park Ave",
    "sg:city":"Valdosta",
    "sg:classifiers":[
        {
            "category":"Shopping",
            "subcategory":"Clothing, Apparel, & Fashions",
            "type":"Retail Goods"
        }
    ],
    "sg:phone":"+1 229 293 9492",
    "sg:postcode":"31602",
    "sg:province":"GA",
    "wof:name":"Tillman & Sons Fashion",
    "wof:placetype":"venue"
},
  "geometry": {"coordinates":[-83.281156,30.856844],"type":"Point"}
}