{
  "type": "Feature",
  "properties": {
    "iso:country":"US",
    "sg:address":"1440 Olympic Dr",
    "sg:city":"Athens",
    "sg:classifiers":[
        {
            "category":"Building & Trades",
            "subcategory":"Construction",
            "type":"Services"
        }
    ],
    "sg:phone":"+1 706 227 3350",
    "sg:postcode":"30601",
    "sg:province":"GA",
    "sg:tags":[
        "general",
        "contractor"
    ],
    "wof:name":"Century Contractors",
    "wof:placetype":"venue"
},
  "geometry": {"coordinates":[-83.328191,33.976479],"type":"Point"}
}