{
  "type": "Feature",
  "properties": {
    "addr:full":"1700 Briarcliff Road NE Atlanta GA 30306",
    "addr:housenumber":"1700",
    "addr:postcode":"30306",
    "addr:street":"Briarcliff Road Ne",
    "iso:country":"US",
    "sg:address":"1700 Briarcliff Road NE",
    "sg:city":"Atlanta",
    "sg:classifiers":[
        {
            "category":"Health Services",
            "subcategory":"Doctor",
            "type":"Services"
        }
    ],
    "sg:phone":"+1 404 733 6550",
    "sg:postcode":"30306",
    "sg:province":"GA",
    "sg:tags":[
        "medicine",
        "internal"
    ],
    "wof:name":"Rolins Jeffrey V MD",
    "wof:placetype":"venue"
},
  "geometry": {"coordinates":[-84.337954,33.803487],"type":"Point"}
}