{
  "type": "Feature",
  "properties": {
    "iso:country":"US",
    "sg:address":"210 Chelsea Dr",
    "sg:city":"Decatur",
    "sg:classifiers":[
        {
            "category":"Shopping",
            "type":"Retail Goods"
        }
    ],
    "sg:phone":"+1 404 378 4434",
    "sg:postcode":"30030",
    "sg:province":"GA",
    "sg:tags":[
        "merchandise"
    ],
    "wof:name":"Kids Used Clothes & Stuff Inc",
    "wof:placetype":"venue"
},
  "geometry": {"coordinates":[-84.31041999999999,33.782042],"type":"Point"}
}