{
  "type": "Feature",
  "properties": {
    "iso:country":"US",
    "sg:address":"1226 Lula Lake Rd",
    "sg:city":"Lookout Mountain",
    "sg:classifiers":[
        {
            "category":"Food & Beverages",
            "subcategory":"Groceries & Convenience Stores",
            "type":"Retail Goods"
        }
    ],
    "sg:phone":"+1 706 820 1142",
    "sg:postcode":"30750",
    "sg:province":"GA",
    "sg:tags":[
        "grocer"
    ],
    "wof:name":"Favorite Market",
    "wof:placetype":"venue"
},
  "geometry": {"coordinates":[-85.356758,34.978491],"type":"Point"}
}