{
  "type": "Feature",
  "properties": {
    "iso:country":"US",
    "sg:address":"817 West Peachtree Street, Suite 220",
    "sg:city":"Atlanta",
    "sg:classifiers":[
        {
            "category":"Real Estate",
            "subcategory":"Real Estate Services",
            "type":"Services"
        }
    ],
    "sg:phone":"+1 404 575 1975",
    "sg:postcode":"30308",
    "sg:province":"GA",
    "sg:tags":[
        "management",
        "property"
    ],
    "sg:website":"www.atlantaloftsandcondos.com",
    "wof:name":"Cooper Brown Real Estate",
    "wof:placetype":"venue"
},
  "geometry": {"coordinates":[-84.387294,33.777116],"type":"Point"}
}