{
  "type": "Feature",
  "properties": {
    "iso:country":"US",
    "sg:address":"4838 State Rte 81 E",
    "sg:city":"Mcdonough",
    "sg:classifiers":[
        {
            "category":"Building & Trades",
            "subcategory":"Construction",
            "type":"Services"
        }
    ],
    "sg:phone":"+1 770 898 0836",
    "sg:postcode":"30252",
    "sg:province":"GA",
    "sg:tags":[
        "dry wall",
        "contractor"
    ],
    "wof:name":"Ray Pippin Drywall Inc",
    "wof:placetype":"venue"
},
  "geometry": {"coordinates":[-83.992384,33.444508],"type":"Point"}
}