{
  "type": "Feature",
  "properties": {
    "addr:full":"6105 Peachtree Pkwy Norcross GA 30092",
    "addr:housenumber":"6105",
    "addr:postcode":"30092",
    "addr:street":"Peachtree Pkwy",
    "iso:country":"US",
    "sg:address":"6105 Peachtree Pkwy",
    "sg:city":"Norcross",
    "sg:classifiers":[
        {
            "category":"Restaurant",
            "type":"Food & Drink"
        }
    ],
    "sg:phone":"+1 770 368 0833",
    "sg:postcode":"30092",
    "sg:province":"GA",
    "sg:website":"www.chick-fil-a.com",
    "wof:name":"Chick-Fil-A Inc",
    "wof:placetype":"venue"
},
  "geometry": {"coordinates":[-84.233902,33.953201],"type":"Point"}
}