{
  "type": "Feature",
  "properties": {
    "addr:full":"4444 N Henry Blvd Stockbridge GA 30281",
    "addr:housenumber":"4444",
    "addr:postcode":"30281",
    "addr:street":"N Henry Blvd",
    "iso:country":"US",
    "sg:address":"4444 N Henry Blvd",
    "sg:city":"Stockbridge",
    "sg:classifiers":[
        {
            "category":"Shopping",
            "subcategory":"Mobile Phones",
            "type":"Retail Goods"
        }
    ],
    "sg:phone":"+1 770 474 5955",
    "sg:postcode":"30281",
    "sg:province":"GA",
    "wof:name":"Sam Luke Corp",
    "wof:placetype":"venue"
},
  "geometry": {"coordinates":[-84.224901,33.543797],"type":"Point"}
}