{
  "type": "Feature",
  "properties": {
    "addr:full":"26 Ila Rd Commerce GA 30529",
    "addr:housenumber":"26",
    "addr:postcode":"30529",
    "addr:street":"Ila Rd",
    "iso:country":"US",
    "sg:address":"26 Ila Rd",
    "sg:city":"Commerce",
    "sg:classifiers":[
        {
            "category":"Retail",
            "subcategory":"Auto Repair",
            "type":"Services"
        }
    ],
    "sg:phone":"+1 706 335 5386",
    "sg:postcode":"30529",
    "sg:province":"GA",
    "sg:tags":[
        "engine",
        "automotive",
        "parts",
        "rebuilds"
    ],
    "wof:name":"Masters Auto Mch Sp & Parts",
    "wof:placetype":"venue"
},
  "geometry": {"coordinates":[-83.441917,34.192154],"type":"Point"}
}