{
  "type": "Feature",
  "properties": {
    "addr:full":"702 Vickers Ave Pearson GA 31642",
    "addr:housenumber":"702",
    "addr:postcode":"31642",
    "addr:street":"Vickers Ave",
    "iso:country":"US",
    "sg:address":"702 Vickers Ave",
    "sg:city":"Pearson",
    "sg:classifiers":[
        {
            "category":"Real Estate",
            "subcategory":"Real Estate Operator",
            "type":"Services"
        }
    ],
    "sg:phone":"+1 912 422 7500",
    "sg:postcode":"31642",
    "sg:province":"GA",
    "sg:tags":[
        "apartment"
    ],
    "wof:name":"Evergreen Apartments",
    "wof:placetype":"venue"
},
  "geometry": {"coordinates":[-82.844978,31.293251],"type":"Point"}
}