{
  "type": "Feature",
  "properties": {
    "addr:full":"3240 Glen Glade Way Cumming GA 30041",
    "addr:housenumber":"3240",
    "addr:postcode":"30041",
    "addr:street":"Glen Glade Way",
    "iso:country":"US",
    "sg:address":"3240 Glen Glade Way",
    "sg:city":"Cumming",
    "sg:classifiers":[
        {
            "category":"Farming",
            "subcategory":"Farm",
            "type":"Manufacturing & Wholesale Goods"
        }
    ],
    "sg:phone":"+1 770 888 0737",
    "sg:postcode":"30041",
    "sg:province":"GA",
    "sg:tags":[
        "crop",
        "general"
    ],
    "wof:name":"Willow Heights Farm Inc",
    "wof:placetype":"venue"
},
  "geometry": {"coordinates":[-84.187455,34.097668],"type":"Point"}
}