{
  "type": "Feature",
  "properties": {
    "iso:country":"US",
    "sg:address":"1190 Buckhead Xing",
    "sg:city":"Woodstock",
    "sg:classifiers":[
        {
            "category":"Retail",
            "subcategory":"Laundry & Dry Cleaning",
            "type":"Services"
        }
    ],
    "sg:phone":"+1 770 591 8882",
    "sg:postcode":"30189",
    "sg:province":"GA",
    "sg:tags":[
        "cleaners"
    ],
    "wof:name":"Dry Cleaning To Your Door",
    "wof:placetype":"venue"
},
  "geometry": {"coordinates":[-84.540188,34.108921],"type":"Point"}
}