{
  "type": "Feature",
  "properties": {
    "iso:country":"US",
    "sg:address":"3101 Cobb Pkwy",
    "sg:city":"Atlanta",
    "sg:classifiers":[
        {
            "category":"Shopping",
            "subcategory":"Clothing, Apparel, & Fashions",
            "type":"Retail Goods"
        }
    ],
    "sg:phone":"+1 770 952 9899",
    "sg:postcode":"30339",
    "sg:province":"GA",
    "sg:tags":[
        "children's",
        "men's",
        "clothing",
        "women's"
    ],
    "sg:website":"www.oldnavy.com",
    "wof:name":"Old Navy",
    "wof:placetype":"venue"
},
  "geometry": {"coordinates":[-84.45711900000001,33.878212],"type":"Point"}
}