{
  "type": "Feature",
  "properties": {
    "addr:full":"121 Coleman Rd Eatonton GA 31027",
    "addr:housenumber":"121",
    "addr:postcode":"31027",
    "addr:street":"Coleman Rd",
    "iso:country":"US",
    "sg:address":"121 Coleman Rd",
    "sg:city":"Eatonton",
    "sg:classifiers":[
        {
            "category":"Retail",
            "subcategory":"Auto Repair",
            "type":"Services"
        }
    ],
    "sg:phone":"+1 706 484 1337",
    "sg:postcode":"31027",
    "sg:province":"GA",
    "sg:tags":[
        "automotive"
    ],
    "wof:name":"Yesterdays Memories",
    "wof:placetype":"venue"
},
  "geometry": {"coordinates":[-82.850258,32.565519],"type":"Point"}
}