{
  "type": "Feature",
  "properties": {
    "iso:country":"US",
    "sg:address":"1212 Railroad St E",
    "sg:city":"Douglas",
    "sg:classifiers":[
        {
            "category":"Manufacturing",
            "subcategory":"Tools & Machinery",
            "type":"Manufacturing & Wholesale Goods"
        }
    ],
    "sg:phone":"+1 912 384 7812",
    "sg:postcode":"31533",
    "sg:province":"GA",
    "sg:tags":[
        "machine",
        "shop"
    ],
    "wof:name":"Thompson's Machine Co",
    "wof:placetype":"venue"
},
  "geometry": {"coordinates":[-82.83443200000001,31.504117],"type":"Point"}
}