{
  "type": "Feature",
  "properties": {
    "iso:country":"US",
    "sg:address":"230 McDonough Pkwy",
    "sg:city":"Mc Donough",
    "sg:classifiers":[
        {
            "category":"Freight",
            "type":"Transportation"
        }
    ],
    "sg:phone":"+1 770 914 7822",
    "sg:postcode":"30253",
    "sg:province":"GA",
    "sg:tags":[
        "general"
    ],
    "wof:name":"C & C Ventures",
    "wof:placetype":"venue"
},
  "geometry": {"coordinates":[-84.166282,33.437855],"type":"Point"}
}