{
  "type": "Feature",
  "properties": {
    "addr:full":"2803 Tyndall Dr Valdosta GA 31602",
    "addr:housenumber":"2803",
    "addr:postcode":"31602",
    "addr:street":"Tyndall Dr",
    "iso:country":"US",
    "sg:address":"2803 Tyndall Dr",
    "sg:city":"Valdosta",
    "sg:classifiers":[
        {
            "category":"Health Services",
            "subcategory":"Nursing And Care Facility",
            "type":"Services"
        }
    ],
    "sg:phone":"+1 229 249 9914",
    "sg:postcode":"31602",
    "sg:province":"GA",
    "sg:tags":[
        "personal",
        "home",
        "intermediate"
    ],
    "wof:name":"Tyndall Personal Care ( Inc )",
    "wof:placetype":"venue"
},
  "geometry": {"coordinates":[-83.25989300000001,30.873656],"type":"Point"}
}