{
  "type": "Feature",
  "properties": {
    "addr:full":"257 Lawrence St NE P.O. Box 3306 Marietta GA 30060",
    "addr:housenumber":"257;box 3306",
    "addr:postcode":"30060",
    "addr:street":"Lawrence St Ne",
    "iso:country":"US",
    "sg:address":"257 Lawrence St NE P.O. Box 3306",
    "sg:city":"Marietta",
    "sg:classifiers":[
        {
            "category":"Professional",
            "type":"Services"
        },
        {
            "category":"Personal",
            "type":"Services"
        }
    ],
    "sg:phone":"+1 404 475 8306",
    "sg:postcode":"30060",
    "sg:province":"GA",
    "sg:tags":[
        "full",
        "material",
        "storage",
        "moving",
        "services-labor",
        "mover"
    ],
    "sg:website":"http://www.chillyhawk.abaenterprises.net",
    "wof:name":"Chilly Hawk Transports",
    "wof:placetype":"venue"
},
  "geometry": {"coordinates":[-84.54504300000001,33.95317],"type":"Point"}
}