{
  "type": "Feature",
  "properties": {
    "addr:full":"3068 Old Norcross Rd Duluth GA 30096",
    "addr:housenumber":"3068",
    "addr:postcode":"30096",
    "addr:street":"Old Norcross Rd",
    "iso:country":"US",
    "sg:address":"3068 Old Norcross Rd",
    "sg:city":"Duluth",
    "sg:classifiers":[
        {
            "category":"Health Services",
            "subcategory":"Doctor",
            "type":"Services"
        },
        {
            "category":"Community Center",
            "type":"Public Place"
        }
    ],
    "sg:phone":"+1 770 925 7232",
    "sg:postcode":"30096",
    "sg:province":"GA",
    "sg:tags":[
        "medical"
    ],
    "sg:website":"www.gwinnettclinic.com",
    "wof:name":"Gwinnett Clinic",
    "wof:placetype":"venue"
},
  "geometry": {"coordinates":[-84.110517,33.957164],"type":"Point"}
}