{
  "type": "Feature",
  "properties": {
    "addr:full":"103 Westridge Ct Kingsland GA 31548",
    "addr:housenumber":"103",
    "addr:postcode":"31548",
    "addr:street":"Westridge Ct",
    "iso:country":"US",
    "sg:address":"103 Westridge Ct",
    "sg:city":"Kingsland",
    "sg:classifiers":[
        {
            "category":"Social Services",
            "type":"Services"
        }
    ],
    "sg:phone":"+1 912 576 1975",
    "sg:postcode":"31548",
    "sg:province":"GA",
    "sg:tags":[
        "organization",
        "welfare"
    ],
    "wof:name":"Young People On The Move Inc",
    "wof:placetype":"venue"
},
  "geometry": {"coordinates":[-81.624455,30.774358],"type":"Point"}
}