{
  "type": "Feature",
  "properties": {
    "iso:country":"US",
    "sg:address":"1624 Hamilton Rd",
    "sg:city":"Lagrange",
    "sg:classifiers":[
        {
            "category":"Manufacturing",
            "subcategory":"Printing",
            "type":"Manufacturing & Wholesale Goods"
        }
    ],
    "sg:phone":"+1 706 882 3855",
    "sg:postcode":"30241",
    "sg:province":"GA",
    "sg:tags":[
        "commercial",
        "lithographic"
    ],
    "wof:name":"Carter's Print Shop",
    "wof:placetype":"venue"
},
  "geometry": {"coordinates":[-85.019773,33.012144],"type":"Point"}
}