{
  "type": "Feature",
  "properties": {
    "iso:country":"US",
    "sg:address":"2326 Landings Ct",
    "sg:city":"Norcross",
    "sg:classifiers":[
        {
            "category":"Professional",
            "subcategory":"Secretarial Services",
            "type":"Services"
        }
    ],
    "sg:phone":"+1 770 246 9396",
    "sg:postcode":"30071",
    "sg:province":"GA",
    "sg:tags":[
        "resume"
    ],
    "wof:name":"Resumes Etc",
    "wof:placetype":"venue"
},
  "geometry": {"coordinates":[-84.19995400000001,33.93268],"type":"Point"}
}