{
  "type": "Feature",
  "properties": {
    "addr:full":"490 Lee Industrial Blvd Austell GA 30168",
    "addr:housenumber":"490",
    "addr:postcode":"30168",
    "addr:street":"Lee Industrial Blvd",
    "iso:country":"US",
    "sg:address":"490 Lee Industrial Blvd",
    "sg:city":"Austell",
    "sg:classifiers":[
        {
            "category":"Professional",
            "type":"Services"
        }
    ],
    "sg:phone":"+1 770 819 3206",
    "sg:postcode":"30168",
    "sg:province":"GA",
    "wof:name":"South Cobb Wrf",
    "wof:placetype":"venue"
},
  "geometry": {"coordinates":[-84.542303,33.775152],"type":"Point"}
}