{
  "type": "Feature",
  "properties": {
    "addr:full":"76 N Broad St Winder GA 30680",
    "addr:housenumber":"76",
    "addr:postcode":"30680",
    "addr:street":"N Broad St",
    "iso:country":"US",
    "sg:address":"76 N Broad St",
    "sg:city":"Winder",
    "sg:classifiers":[
        {
            "category":"Banks & Credit Unions",
            "subcategory":"Bank",
            "type":"Services"
        }
    ],
    "sg:phone":"+1 678 425 0000",
    "sg:postcode":"30680",
    "sg:province":"GA",
    "sg:tags":[
        "loan",
        "real estate"
    ],
    "wof:name":"Peoples Financial Svc",
    "wof:placetype":"venue"
},
  "geometry": {"coordinates":[-83.719739,33.993145],"type":"Point"}
}