{
  "type": "Feature",
  "properties": {
    "addr:full":"200 N Court St Quitman GA 31643",
    "addr:housenumber":"200",
    "addr:postcode":"31643",
    "addr:street":"N Court St",
    "iso:country":"US",
    "sg:address":"200 N Court St",
    "sg:city":"Quitman",
    "sg:classifiers":[
        {
            "category":"Place Of Worship",
            "subcategory":"Church",
            "type":"Public Place"
        },
        {
            "category":"Place Of Worship",
            "type":"Public Place"
        }
    ],
    "sg:phone":"+1 229 263 4559",
    "sg:postcode":"31643",
    "sg:province":"GA",
    "sg:tags":[
        "churches-presbyterian"
    ],
    "sg:website":"http://www.firstpresbyterianchurchquitman.com",
    "wof:name":"First Presbyterian Church of Quitman",
    "wof:placetype":"venue"
},
  "geometry": {"coordinates":[-83.560089,30.785789],"type":"Point"}
}