{
  "type": "Feature",
  "properties": {
    "iso:country":"US",
    "sg:address":"850 US Hwy 19",
    "sg:city":"Leesburg",
    "sg:classifiers":[
        {
            "category":"Organizations",
            "subcategory":"Religious Organization",
            "type":"Services"
        }
    ],
    "sg:phone":"+1 229 439 0885",
    "sg:postcode":"31763",
    "sg:province":"GA",
    "wof:name":"Jehovahs Witnesses Quick",
    "wof:placetype":"venue"
},
  "geometry": {"coordinates":[-84.19852899999999,31.788257],"type":"Point"}
}