{
  "type": "Feature",
  "properties": {
    "addr:full":"309 Bell Park Dr Woodstock GA 30188",
    "addr:housenumber":"309",
    "addr:postcode":"30188",
    "addr:street":"Bell Park Dr",
    "iso:country":"US",
    "sg:address":"309 Bell Park Dr",
    "sg:city":"Woodstock",
    "sg:classifiers":[
        {
            "category":"Professional",
            "subcategory":"Business Services",
            "type":"Services"
        },
        {
            "category":"Wholesale",
            "subcategory":"Electrical",
            "type":"Manufacturing & Wholesale Goods"
        }
    ],
    "sg:phone":"+1 770 592 8127",
    "sg:postcode":"30188",
    "sg:province":"GA",
    "sg:tags":[
        "recording",
        "audio",
        "tape"
    ],
    "wof:name":"It's A New Day",
    "wof:placetype":"venue"
},
  "geometry": {"coordinates":[-84.510458,34.121688],"type":"Point"}
}