{
  "type": "Feature",
  "properties": {
    "addr:full":"1080 Ralph David Abernathy Blvd Atlanta GA 31132",
    "addr:housenumber":"1080",
    "addr:postcode":"31132",
    "addr:street":"Ralph David Abernathy Blvd",
    "iso:country":"US",
    "sg:address":"1080 Ralph David Abernathy Blvd",
    "sg:city":"Atlanta",
    "sg:classifiers":[
        {
            "category":"Fast Food",
            "type":"Food & Drink"
        }
    ],
    "sg:phone":"+1 404 753 4363",
    "sg:postcode":"31132",
    "sg:province":"GA",
    "sg:website":"www.yasins.com",
    "wof:name":"Yasin's Homestyle Seafood",
    "wof:placetype":"venue"
},
  "geometry": {"coordinates":[-84.423042,33.738209],"type":"Point"}
}