{
  "type": "Feature",
  "properties": {
    "iso:country":"US",
    "sg:address":"3311 Chamblee Dunwoody Rd",
    "sg:city":"Atlanta",
    "sg:classifiers":[
        {
            "category":"Cinema",
            "subcategory":"Movie Rental",
            "type":"Entertainment"
        }
    ],
    "sg:phone":"+1 770 455 4125",
    "sg:postcode":"30341",
    "sg:province":"GA",
    "sg:tags":[
        "video",
        "tape",
        "music"
    ],
    "wof:name":"Discolandia Inc",
    "wof:placetype":"venue"
},
  "geometry": {"coordinates":[-84.29468799999999,33.891889],"type":"Point"}
}