{
  "type": "Feature",
  "properties": {
    "addr:full":"1085 Lovvorn Rd Carrollton GA 30117",
    "addr:housenumber":"1085",
    "addr:postcode":"30117",
    "addr:street":"Lovvorn Rd",
    "iso:country":"US",
    "sg:address":"1085 Lovvorn Rd",
    "sg:city":"Carrollton",
    "sg:classifiers":[
        {
            "category":"Food & Beverages",
            "subcategory":"Groceries & Convenience Stores",
            "type":"Retail Goods"
        }
    ],
    "sg:phone":"+1 770 830 9060",
    "sg:postcode":"30117",
    "sg:province":"GA",
    "sg:tags":[
        "grocer"
    ],
    "wof:name":"Tienda Hernandez",
    "wof:placetype":"venue"
},
  "geometry": {"coordinates":[-85.106191,33.580921],"type":"Point"}
}