{
  "type": "Feature",
  "properties": {
    "addr:full":"545 Rock Springs Rd Lawrenceville GA 30043",
    "addr:housenumber":"545",
    "addr:postcode":"30043",
    "addr:street":"Rock Springs Rd",
    "iso:country":"US",
    "sg:address":"545 Rock Springs Rd",
    "sg:city":"Lawrenceville",
    "sg:classifiers":[
        {
            "category":"Organizations",
            "subcategory":"Religious Organization",
            "type":"Services"
        }
    ],
    "sg:phone":"+1 770 271 1106",
    "sg:postcode":"30043",
    "sg:province":"GA",
    "wof:name":"Rock Springs Full Gospl Church",
    "wof:placetype":"venue"
},
  "geometry": {"coordinates":[-84.01656,34.039124],"type":"Point"}
}