{
  "type": "Feature",
  "properties": {
    "iso:country":"US",
    "sg:address":"6973 Clyo-Kildare Rd",
    "sg:city":"Newington",
    "sg:classifiers":[
        {
            "category":"Shopping",
            "subcategory":"Used Merchandise",
            "type":"Retail Goods"
        }
    ],
    "sg:phone":"+1 912 754 2440",
    "sg:postcode":"30446",
    "sg:province":"GA",
    "sg:tags":[
        "antique"
    ],
    "wof:name":"Mrs Mildred's Antiques",
    "wof:placetype":"venue"
},
  "geometry": {"coordinates":[-81.456636,32.533693],"type":"Point"}
}