{
  "type": "Feature",
  "properties": {
    "iso:country":"US",
    "sg:address":"1929 Albany St",
    "sg:city":"Brunswick",
    "sg:classifiers":[
        {
            "category":"Organizations",
            "subcategory":"Religious Organization",
            "type":"Services"
        }
    ],
    "sg:phone":"+1 912 265 7669",
    "sg:postcode":"31520",
    "sg:province":"GA",
    "sg:tags":[
        "church"
    ],
    "wof:name":"Saint Paul Baptist Church",
    "wof:placetype":"venue"
},
  "geometry": {"coordinates":[-81.491888,31.156918],"type":"Point"}
}