{
  "type": "Feature",
  "properties": {
    "iso:country":"US",
    "sg:address":"3350 Atlanta Rd SE",
    "sg:city":"Smyrna",
    "sg:classifiers":[
        {
            "category":"Real Estate",
            "subcategory":"Real Estate Services",
            "type":"Services"
        },
        {
            "category":"Real Estate",
            "subcategory":"Real Estate Agent",
            "type":"Services"
        }
    ],
    "sg:phone":"+1 404 219 4007",
    "sg:postcode":"30080",
    "sg:province":"GA",
    "sg:tags":[
        "buyer",
        "broker"
    ],
    "wof:name":"Realty Cityside",
    "wof:placetype":"venue"
},
  "geometry": {"coordinates":[-84.49745900000001,33.871948],"type":"Point"}
}