{
  "type": "Feature",
  "properties": {
    "iso:country":"US",
    "sg:address":"719 Fernstone Trl",
    "sg:city":"Lawrenceville",
    "sg:classifiers":[
        {
            "category":"Professional",
            "subcategory":"Business Services",
            "type":"Services"
        }
    ],
    "sg:phone":"+1 770 237 5728",
    "sg:postcode":"30045",
    "sg:province":"GA",
    "wof:name":"Valdez Enterprises",
    "wof:placetype":"venue"
},
  "geometry": {"coordinates":[-83.98991100000001,33.926037],"type":"Point"}
}