{
  "type": "Feature",
  "properties": {
    "addr:full":"874 Hyde Rd Marietta GA 30068",
    "addr:housenumber":"874",
    "addr:postcode":"30068",
    "addr:street":"Hyde Rd",
    "iso:country":"US",
    "sg:address":"874 Hyde Rd",
    "sg:city":"Marietta",
    "sg:classifiers":[
        {
            "category":"Professional",
            "subcategory":"Accounting & Tax Preparation",
            "type":"Services"
        }
    ],
    "sg:phone":"+1 770 640 6906",
    "sg:postcode":"30068",
    "sg:province":"GA",
    "sg:tags":[
        "investing"
    ],
    "wof:name":"Klausman Group",
    "wof:placetype":"venue"
},
  "geometry": {"coordinates":[-84.391998,33.969398],"type":"Point"}
}