{
  "type": "Feature",
  "properties": {
    "addr:full":"1111 Church St Covington GA 30014",
    "addr:housenumber":"1111",
    "addr:postcode":"30014",
    "addr:street":"Church St",
    "iso:country":"US",
    "sg:address":"1111 Church St",
    "sg:city":"Covington",
    "sg:classifiers":[
        {
            "category":"Real Estate",
            "subcategory":"Real Estate Agent",
            "type":"Services"
        }
    ],
    "sg:phone":"+1 770 787 7777",
    "sg:postcode":"30014",
    "sg:province":"GA",
    "wof:name":"Re/Max Agents Realty",
    "wof:placetype":"venue"
},
  "geometry": {"coordinates":[-83.859334,33.596586],"type":"Point"}
}