{
  "type": "Feature",
  "properties": {
    "addr:full":"975 McCurry Rd Hartwell GA 30643",
    "addr:housenumber":"975",
    "addr:postcode":"30643",
    "addr:street":"Mccurry Rd",
    "iso:country":"US",
    "sg:address":"975 McCurry Rd",
    "sg:city":"Hartwell",
    "sg:classifiers":[
        {
            "category":"Professional",
            "subcategory":"Management & Consulting",
            "type":"Services"
        }
    ],
    "sg:phone":"+1 706 376 0136",
    "sg:postcode":"30643",
    "sg:province":"GA",
    "wof:name":"Metal Marketing Inc",
    "wof:placetype":"venue"
},
  "geometry": {"coordinates":[-82.944796,34.264994],"type":"Point"}
}