{
  "type": "Feature",
  "properties": {
    "addr:full":"2520 Summeroak Dr Tucker GA 30084",
    "addr:housenumber":"2520",
    "addr:postcode":"30084",
    "addr:street":"Summeroak Dr",
    "iso:country":"US",
    "sg:address":"2520 Summeroak Dr",
    "sg:city":"Tucker",
    "sg:classifiers":[
        {
            "category":"Wholesale",
            "subcategory":"Groceries",
            "type":"Manufacturing & Wholesale Goods"
        }
    ],
    "sg:phone":"+1 770 908 0440",
    "sg:postcode":"30084",
    "sg:province":"GA",
    "sg:tags":[
        "general"
    ],
    "wof:name":"Summerwood Farms LLC",
    "wof:placetype":"venue"
},
  "geometry": {"coordinates":[-84.219819,33.857682],"type":"Point"}
}