{
  "type": "Feature",
  "properties": {
    "addr:full":"1088 Atlanta Rd SW Marietta GA 30060",
    "addr:housenumber":"1088",
    "addr:postcode":"30060",
    "addr:street":"Atlanta Rd Sw",
    "iso:country":"US",
    "sg:address":"1088 Atlanta Rd SW",
    "sg:city":"Marietta",
    "sg:classifiers":[
        {
            "category":"Wholesale",
            "subcategory":"Machinery & Supplies",
            "type":"Manufacturing & Wholesale Goods"
        }
    ],
    "sg:phone":"+1 770 422 1544",
    "sg:postcode":"30060",
    "sg:province":"GA",
    "sg:tags":[
        "equipment",
        "industrial"
    ],
    "wof:name":"Airgas",
    "wof:placetype":"venue"
},
  "geometry": {"coordinates":[-84.541848,33.926447],"type":"Point"}
}