{
  "type": "Feature",
  "properties": {
    "iso:country":"US",
    "sg:address":"4449 Coventry Ct",
    "sg:city":"Roswell",
    "sg:classifiers":[
        {
            "category":"Professional",
            "subcategory":"Business Services",
            "type":"Services"
        }
    ],
    "sg:phone":"+1 770 552 8271",
    "sg:postcode":"30075",
    "sg:province":"GA",
    "wof:name":"Rice Technologies Inc",
    "wof:placetype":"venue"
},
  "geometry": {"coordinates":[-84.421629,34.049291],"type":"Point"}
}