{
  "type": "Feature",
  "properties": {
    "addr:full":"150 Cottage Ln Carrollton GA 30117",
    "addr:housenumber":"150",
    "addr:postcode":"30117",
    "addr:street":"Cottage Ln",
    "iso:country":"US",
    "sg:address":"150 Cottage Ln",
    "sg:city":"Carrollton",
    "sg:classifiers":[
        {
            "category":"Social Services",
            "subcategory":"Adult Care",
            "type":"Services"
        }
    ],
    "sg:phone":"+1 770 830 8857",
    "sg:postcode":"30117",
    "sg:province":"GA",
    "sg:tags":[
        "home",
        "residential"
    ],
    "wof:name":"Cottage Landing",
    "wof:placetype":"venue"
},
  "geometry": {"coordinates":[-85.07687799999999,33.553471],"type":"Point"}
}