{
  "type": "Feature",
  "properties": {
    "iso:country":"US",
    "sg:address":"6597 Roswell Rd NE",
    "sg:city":"Atlanta",
    "sg:classifiers":[
        {
            "category":"Shopping",
            "subcategory":"Mobile Phones",
            "type":"Retail Goods"
        }
    ],
    "sg:phone":"+1 404 255 9588",
    "sg:postcode":"30328",
    "sg:province":"GA",
    "wof:name":"Skytalk Communications",
    "wof:placetype":"venue"
},
  "geometry": {"coordinates":[-84.37930299999999,33.935398],"type":"Point"}
}