{
  "type": "Feature",
  "properties": {
    "addr:full":"940 Lewis Ridge Cir Lawrenceville GA 30045",
    "addr:housenumber":"940",
    "addr:postcode":"30045",
    "addr:street":"Lewis Ridge Cir",
    "iso:country":"US",
    "sg:address":"940 Lewis Ridge Cir",
    "sg:city":"Lawrenceville",
    "sg:classifiers":[
        {
            "category":"Real Estate",
            "subcategory":"Real Estate Agent",
            "type":"Services"
        }
    ],
    "sg:phone":"+1 770 338 1181",
    "sg:postcode":"30045",
    "sg:province":"GA",
    "wof:name":"Daniel Y",
    "wof:placetype":"venue"
},
  "geometry": {"coordinates":[-83.951683,33.936829],"type":"Point"}
}