{
  "type": "Feature",
  "properties": {
    "iso:country":"US",
    "sg:address":"580 W End Pl SW",
    "sg:city":"Atlanta",
    "sg:classifiers":[
        {
            "category":"Social Services",
            "subcategory":"Child Care",
            "type":"Services"
        }
    ],
    "sg:phone":"+1 404 755 1458",
    "sg:postcode":"30310",
    "sg:province":"GA",
    "sg:tags":[
        "day"
    ],
    "wof:name":"Kids On Line Inc",
    "wof:placetype":"venue"
},
  "geometry": {"coordinates":[-84.424747,33.738983],"type":"Point"}
}