{
  "type": "Feature",
  "properties": {
    "addr:full":"854 Washington St W Gainesville GA 30501",
    "addr:housenumber":"854",
    "addr:postcode":"30501",
    "addr:street":"Washington St W",
    "iso:country":"US",
    "sg:address":"854 Washington St W",
    "sg:city":"Gainesville",
    "sg:classifiers":[
        {
            "category":"Banks & Credit Unions",
            "subcategory":"Bank",
            "type":"Services"
        }
    ],
    "sg:phone":"+1 770 536 2265",
    "sg:postcode":"30501",
    "sg:province":"GA",
    "wof:name":"B B & T",
    "wof:placetype":"venue"
},
  "geometry": {"coordinates":[-83.83609800000001,34.296984],"type":"Point"}
}