{
  "type": "Feature",
  "properties": {
    "iso:country":"US",
    "sg:address":"2950 Lovvorn Mill Rd",
    "sg:city":"Waco",
    "sg:classifiers":[
        {
            "category":"Building & Trades",
            "subcategory":"Electrical",
            "type":"Services"
        }
    ],
    "sg:phone":"+1 770 258 3254",
    "sg:postcode":"30108",
    "sg:province":"GA",
    "sg:tags":[
        "electrical",
        "contractor"
    ],
    "wof:name":"Warren Electrical",
    "wof:placetype":"venue"
},
  "geometry": {"coordinates":[-85.268638,33.606805],"type":"Point"}
}