{
  "type": "Feature",
  "properties": {
    "addr:full":"101 S Piedmont St Calhoun GA 30701",
    "addr:housenumber":"101",
    "addr:postcode":"30701",
    "addr:street":"S Piedmont St",
    "iso:country":"US",
    "sg:address":"101 S Piedmont St",
    "sg:city":"Calhoun",
    "sg:classifiers":[
        {
            "category":"Government",
            "subcategory":"Fire Station",
            "type":"Public Place"
        }
    ],
    "sg:phone":"+1 706 629 8851",
    "sg:postcode":"30701",
    "sg:province":"GA",
    "sg:tags":[
        "county",
        "protection"
    ],
    "wof:name":"Gordon County Fire Dept",
    "wof:placetype":"venue"
},
  "geometry": {"coordinates":[-84.950436,34.50287],"type":"Point"}
}