{
  "type": "Feature",
  "properties": {
    "iso:country":"US",
    "sg:address":"2482 Bright Star Rd",
    "sg:city":"Douglasville",
    "sg:classifiers":[
        {
            "category":"Manufacturing",
            "subcategory":"Tools & Machinery",
            "type":"Manufacturing & Wholesale Goods"
        }
    ],
    "sg:phone":"+1 770 942 1406",
    "sg:postcode":"30134",
    "sg:province":"GA",
    "sg:tags":[
        "conveyor",
        "parts",
        "supply"
    ],
    "wof:name":"Versa Mount",
    "wof:placetype":"venue"
},
  "geometry": {"coordinates":[-84.77777399999999,33.742493],"type":"Point"}
}