{
  "type": "Feature",
  "properties": {
    "iso:country":"US",
    "sg:address":"1278 Killian Knoll Cir SW",
    "sg:city":"Lilburn",
    "sg:classifiers":[
        {
            "category":"Wholesale",
            "subcategory":"Durable Goods & Equipment",
            "type":"Manufacturing & Wholesale Goods"
        }
    ],
    "sg:phone":"+1 770 638 1744",
    "sg:postcode":"30047",
    "sg:province":"GA",
    "sg:tags":[
        "professional"
    ],
    "wof:name":"Visionsoft Incl Inc",
    "wof:placetype":"venue"
},
  "geometry": {"coordinates":[-84.082981,33.864905],"type":"Point"}
}