{
  "type": "Feature",
  "properties": {
    "addr:full":"2103 Treeridge Pkwy Alpharetta GA 30022",
    "addr:housenumber":"2103",
    "addr:postcode":"30022",
    "addr:street":"Treeridge Pkwy",
    "iso:country":"US",
    "sg:address":"2103 Treeridge Pkwy",
    "sg:city":"Alpharetta",
    "sg:classifiers":[
        {
            "category":"Building & Trades",
            "subcategory":"Landscaping Services",
            "type":"Services"
        }
    ],
    "sg:phone":"+1 770 380 0169",
    "sg:postcode":"30022",
    "sg:province":"GA",
    "sg:tags":[
        "landscape",
        "contractor"
    ],
    "wof:name":"Pine Landscaping",
    "wof:placetype":"venue"
},
  "geometry": {"coordinates":[-84.278318,33.992059],"type":"Point"}
}