{
  "type": "Feature",
  "properties": {
    "iso:country":"US",
    "sg:address":"1042 Abrams Rd SE",
    "sg:city":"Silver Creek",
    "sg:classifiers":[
        {
            "category":"Farming",
            "subcategory":"Livestock Farm",
            "type":"Manufacturing & Wholesale Goods"
        }
    ],
    "sg:phone":"+1 706 234 7997",
    "sg:postcode":"30173",
    "sg:province":"GA",
    "sg:tags":[
        "equine"
    ],
    "wof:name":"Silver Cedar Farms LLC",
    "wof:placetype":"venue"
},
  "geometry": {"coordinates":[-85.08652600000001,34.14659],"type":"Point"}
}