{
  "type": "Feature",
  "properties": {
    "iso:country":"US",
    "sg:address":"1684 Little Joe Ct",
    "sg:city":"Decatur",
    "sg:classifiers":[
        {
            "category":"Personal",
            "subcategory":"Beauty Salon",
            "type":"Services"
        }
    ],
    "sg:phone":"+1 404 633 2779",
    "sg:postcode":"30033",
    "sg:province":"GA",
    "sg:tags":[
        "shop"
    ],
    "wof:name":"Iht Clips Inc",
    "wof:placetype":"venue"
},
  "geometry": {"coordinates":[-84.272019,33.831671],"type":"Point"}
}