{
  "type": "Feature",
  "properties": {
    "addr:full":"1950 W Exchange Pl Tucker GA 30084",
    "addr:housenumber":"1950",
    "addr:postcode":"30084",
    "addr:street":"W Exchange Pl",
    "iso:country":"US",
    "sg:address":"1950 W Exchange Pl",
    "sg:city":"Tucker",
    "sg:classifiers":[
        {
            "category":"Utilities",
            "subcategory":"Telephone",
            "type":"Services"
        }
    ],
    "sg:phone":"+1 770 908 6200",
    "sg:postcode":"30084",
    "sg:province":"GA",
    "sg:tags":[
        "communications",
        "radiotelephone",
        "communication"
    ],
    "wof:name":"BellSouth",
    "wof:placetype":"venue"
},
  "geometry": {"coordinates":[-84.24527999999999,33.843216],"type":"Point"}
}