{
  "type": "Feature",
  "properties": {
    "iso:country":"US",
    "sg:address":"186 Rolling Hills Ave",
    "sg:city":"Canton",
    "sg:classifiers":[
        {
            "category":"Education",
            "subcategory":"School",
            "type":"Public Place"
        }
    ],
    "sg:phone":"+1 770 479 9535",
    "sg:postcode":"30114",
    "sg:province":"GA",
    "sg:tags":[
        "high",
        "middle",
        "elementary"
    ],
    "wof:name":"Community Christian School",
    "wof:placetype":"venue"
},
  "geometry": {"coordinates":[-84.5056,34.204201],"type":"Point"}
}