{
  "type": "Feature",
  "properties": {
    "iso:country":"US",
    "sg:address":"2412 Antwerp Dr SE",
    "sg:city":"Atlanta",
    "sg:classifiers":[
        {
            "category":"Freight",
            "type":"Transportation"
        }
    ],
    "sg:phone":"+1 404 559 8601",
    "sg:postcode":"30315",
    "sg:province":"GA",
    "sg:tags":[
        "container",
        "arrangement"
    ],
    "sg:website":"http://www.logiserve.net",
    "wof:name":"Logiserve Inc.",
    "wof:placetype":"venue"
},
  "geometry": {"coordinates":[-84.385141,33.688609],"type":"Point"}
}