{
  "type": "Feature",
  "properties": {
    "addr:full":"490 Belgrave Ln Tucker GA 30084",
    "addr:housenumber":"490",
    "addr:postcode":"30084",
    "addr:street":"Belgrave Ln",
    "iso:country":"US",
    "sg:address":"490 Belgrave Ln",
    "sg:city":"Tucker",
    "sg:classifiers":[
        {
            "category":"Real Estate",
            "subcategory":"Real Estate Agent",
            "type":"Services"
        }
    ],
    "sg:phone":"+1 770 826 5257",
    "sg:postcode":"30084",
    "sg:province":"GA",
    "wof:name":"WAU Development",
    "wof:placetype":"venue"
},
  "geometry": {"coordinates":[-84.175786,33.882849],"type":"Point"}
}