{
  "type": "Feature",
  "properties": {
    "iso:country":"US",
    "sg:address":"371 W Parker St",
    "sg:city":"Baxley",
    "sg:classifiers":[
        {
            "category":"Communications",
            "subcategory":"Television Station",
            "type":"Services"
        },
        {
            "category":"Utilities",
            "subcategory":"Telephone",
            "type":"Services"
        },
        {
            "category":"Professional",
            "subcategory":"Computer Services",
            "type":"Services"
        }
    ],
    "sg:phone":"+1 912 705 5000",
    "sg:postcode":"31513",
    "sg:province":"GA",
    "sg:tags":[
        "distance",
        "satellite",
        "cable",
        "isp",
        "provider",
        "internet",
        "companies-long"
    ],
    "wof:name":"Atc",
    "wof:placetype":"venue"
},
  "geometry": {"coordinates":[-82.351393,31.779213],"type":"Point"}
}