{
  "type": "Feature",
  "properties": {
    "addr:full":"146 Meeks Rd NW Milledgeville GA 31061",
    "addr:housenumber":"146",
    "addr:postcode":"31061",
    "addr:street":"Meeks Rd Nw",
    "iso:country":"US",
    "sg:address":"146 Meeks Rd NW",
    "sg:city":"Milledgeville",
    "sg:classifiers":[
        {
            "category":"Freight",
            "type":"Transportation"
        }
    ],
    "sg:phone":"+1 478 453 0306",
    "sg:postcode":"31061",
    "sg:province":"GA",
    "sg:tags":[
        "operator",
        "local",
        "trucking"
    ],
    "wof:name":"Richard T Meeks",
    "wof:placetype":"venue"
},
  "geometry": {"coordinates":[-83.282561,33.103163],"type":"Point"}
}