{
  "type": "Feature",
  "properties": {
    "iso:country":"US",
    "sg:address":"6025 Oakbrook Pkwy",
    "sg:city":"Norcross",
    "sg:classifiers":[
        {
            "category":"Fast Food",
            "type":"Food & Drink"
        },
        {
            "category":"Restaurant",
            "type":"Food & Drink"
        }
    ],
    "sg:phone":"+1 770 446 6218",
    "sg:postcode":"30093",
    "sg:province":"GA",
    "sg:tags":[
        "hamburger",
        "house",
        "american",
        "dog",
        "hot",
        "steak"
    ],
    "sg:website":"http://www.steakale.com",
    "wof:name":"Steak and Ale",
    "wof:placetype":"venue"
},
  "geometry": {"coordinates":[-84.20285,33.912386],"type":"Point"}
}