{
  "type": "Feature",
  "properties": {
    "addr:full":"3450 Cobb Pkwy NW Acworth GA 30101",
    "addr:housenumber":"3450",
    "addr:postcode":"30101",
    "addr:street":"Cobb Pkwy Nw",
    "iso:country":"US",
    "sg:address":"3450 Cobb Pkwy NW",
    "sg:city":"Acworth",
    "sg:classifiers":[
        {
            "category":"Arena",
            "subcategory":"Sports Club",
            "type":"Entertainment"
        }
    ],
    "sg:phone":"+1 678 214 0400",
    "sg:postcode":"30101",
    "sg:province":"GA",
    "sg:tags":[
        "martial art"
    ],
    "wof:name":"Ata Karate Family Center of Acworth",
    "wof:placetype":"venue"
},
  "geometry": {"coordinates":[-84.688619,34.037756],"type":"Point"}
}