{
  "type": "Feature",
  "properties": {
    "iso:country":"US",
    "sg:address":"106 Grandcrest Dr",
    "sg:city":"Suwanee",
    "sg:classifiers":[
        {
            "category":"Organizations",
            "subcategory":"Religious Organization",
            "type":"Services"
        }
    ],
    "sg:phone":"+1 770 262 3323",
    "sg:postcode":"30024",
    "sg:province":"GA",
    "sg:tags":[
        "clergy"
    ],
    "wof:name":"Princess Tea & Gifts",
    "wof:placetype":"venue"
},
  "geometry": {"coordinates":[-84.107546,34.110005],"type":"Point"}
}