{
  "type": "Feature",
  "properties": {
    "iso:country":"US",
    "sg:address":"3743 Bouldercrest Rd",
    "sg:city":"Ellenwood",
    "sg:classifiers":[
        {
            "category":"Train Station",
            "subcategory":"Light Rail",
            "type":"Transportation"
        }
    ],
    "sg:phone":"+1 404 241 2073",
    "sg:postcode":"30294",
    "sg:province":"GA",
    "sg:tags":[
        "lighting",
        "maintenance"
    ],
    "wof:name":"Sign Repairs",
    "wof:placetype":"venue"
},
  "geometry": {"coordinates":[-84.288438,33.658579],"type":"Point"}
}