{
  "type": "Feature",
  "properties": {
    "addr:full":"2141 Highway 82 Statham GA 30666",
    "addr:housenumber":"2141",
    "addr:postcode":"30666",
    "addr:street":"Highway 82",
    "iso:country":"US",
    "sg:address":"2141 Highway 82",
    "sg:city":"Statham",
    "sg:classifiers":[
        {
            "category":"Place Of Worship",
            "subcategory":"Church",
            "type":"Public Place"
        },
        {
            "category":"Place Of Worship",
            "type":"Public Place"
        }
    ],
    "sg:phone":"+1 770 725 5511",
    "sg:postcode":"30666",
    "sg:province":"GA",
    "sg:tags":[
        "churches-baptist-general",
        "churches-baptist"
    ],
    "wof:name":"Fairfield Baptist Church",
    "wof:placetype":"venue"
},
  "geometry": {"coordinates":[-83.57659700000001,34.015062],"type":"Point"}
}