{
  "type": "Feature",
  "properties": {
    "iso:country":"US",
    "sg:address":"516 Sauls Rd",
    "sg:city":"Moultrie",
    "sg:classifiers":[
        {
            "category":"Building & Trades",
            "subcategory":"Pest Control",
            "type":"Services"
        }
    ],
    "sg:phone":"+1 229 985 9636",
    "sg:postcode":"31768",
    "sg:province":"GA",
    "wof:name":"Best One Pest Control Inc",
    "wof:placetype":"venue"
},
  "geometry": {"coordinates":[-83.819185,31.153247],"type":"Point"}
}