{
  "type": "Feature",
  "properties": {
    "addr:full":"2505 Danielsville Rd Athens GA 30601",
    "addr:housenumber":"2505",
    "addr:postcode":"30601",
    "addr:street":"Danielsville Rd",
    "iso:country":"US",
    "sg:address":"2505 Danielsville Rd",
    "sg:city":"Athens",
    "sg:classifiers":[
        {
            "category":"Retail",
            "subcategory":"Car Wash",
            "type":"Services"
        }
    ],
    "sg:phone":"+1 706 369 0095",
    "sg:postcode":"30601",
    "sg:province":"GA",
    "sg:tags":[
        "carwash"
    ],
    "wof:name":"RWS Auto Detail",
    "wof:placetype":"venue"
},
  "geometry": {"coordinates":[-83.33792,34.01979],"type":"Point"}
}