{
  "type": "Feature",
  "properties": {
    "addr:full":"429 Canton Rd Cumming GA 30040",
    "addr:housenumber":"429",
    "addr:postcode":"30040",
    "addr:street":"Canton Rd",
    "iso:country":"US",
    "sg:address":"429 Canton Rd",
    "sg:city":"Cumming",
    "sg:classifiers":[
        {
            "category":"Shopping",
            "subcategory":"Pharmacy",
            "type":"Retail Goods"
        }
    ],
    "sg:phone":"+1 770 887 7771",
    "sg:postcode":"30040",
    "sg:province":"GA",
    "sg:tags":[
        "drug",
        "store"
    ],
    "wof:name":"CVS",
    "wof:placetype":"venue"
},
  "geometry": {"coordinates":[-84.14567700000001,34.214209],"type":"Point"}
}