{
  "type": "Feature",
  "properties": {
    "addr:full":"219 Rope Mill Rd Woodstock GA 30188",
    "addr:housenumber":"219",
    "addr:postcode":"30188",
    "addr:street":"Rope Mill Rd",
    "iso:country":"US",
    "sg:address":"219 Rope Mill Rd",
    "sg:city":"Woodstock",
    "sg:classifiers":[
        {
            "category":"Organizations",
            "subcategory":"Religious Organization",
            "type":"Services"
        }
    ],
    "sg:phone":"+1 770 926 8838",
    "sg:postcode":"30188",
    "sg:province":"GA",
    "sg:website":"www.woodstockchurchofchrist.org",
    "wof:name":"Woodstock Day School",
    "wof:placetype":"venue"
},
  "geometry": {"coordinates":[-84.52493200000001,34.110388],"type":"Point"}
}