{
  "type": "Feature",
  "properties": {
    "addr:full":"138 Commerce Ave Lagrange GA 30241",
    "addr:housenumber":"138",
    "addr:postcode":"30241",
    "addr:street":"Commerce Ave",
    "iso:country":"US",
    "sg:address":"138 Commerce Ave",
    "sg:city":"Lagrange",
    "sg:classifiers":[
        {
            "category":"Autos & Motor Vehicles",
            "subcategory":"Fuel & Gas Station",
            "type":"Retail Goods"
        }
    ],
    "sg:phone":"+1 706 882 0202",
    "sg:postcode":"30241",
    "sg:province":"GA",
    "sg:tags":[
        "oil"
    ],
    "wof:name":"Woody's Exxon",
    "wof:placetype":"venue"
},
  "geometry": {"coordinates":[-85.026681,33.049322],"type":"Point"}
}