{
  "type": "Feature",
  "properties": {
    "addr:full":"3107 Sylvan Rd Atlanta GA 30354",
    "addr:housenumber":"3107",
    "addr:postcode":"30354",
    "addr:street":"Sylvan Rd",
    "iso:country":"US",
    "sg:address":"3107 Sylvan Rd",
    "sg:city":"Atlanta",
    "sg:classifiers":[
        {
            "category":"Manufacturing",
            "subcategory":"Glass & Minerals",
            "type":"Manufacturing & Wholesale Goods"
        }
    ],
    "sg:phone":"+1 404 765 8600",
    "sg:postcode":"30354",
    "sg:province":"GA",
    "sg:tags":[
        "glass-wholesale",
        "manufacturer",
        "container",
        "mfg"
    ],
    "wof:name":"Owens-Brockway Glass Container Inc.",
    "wof:placetype":"venue"
},
  "geometry": {"coordinates":[-84.41889999999999,33.66949],"type":"Point"}
}