{
  "type": "Feature",
  "properties": {
    "iso:country":"US",
    "sg:address":"4 Sea Breeze Ln",
    "sg:city":"Tybee Island",
    "sg:classifiers":[
        {
            "category":"Real Estate",
            "subcategory":"Real Estate Agent",
            "type":"Services"
        }
    ],
    "sg:phone":"+1 912 786 7638",
    "sg:postcode":"31328",
    "sg:province":"GA",
    "wof:name":"Vicki Shirer",
    "wof:placetype":"venue"
},
  "geometry": {"coordinates":[-80.85158199999999,32.024603],"type":"Point"}
}