{
  "type": "Feature",
  "properties": {
    "iso:country":"US",
    "sg:address":"1734 Moss Dr SW",
    "sg:city":"Snellville",
    "sg:classifiers":[
        {
            "category":"Professional",
            "subcategory":"Management & Consulting",
            "type":"Services"
        }
    ],
    "sg:phone":"+1 770 466 3437",
    "sg:postcode":"30078",
    "sg:province":"GA",
    "sg:tags":[
        "party",
        "planning"
    ],
    "wof:name":"Action Packed Parties & Rental",
    "wof:placetype":"venue"
},
  "geometry": {"coordinates":[-84.04121499999999,33.866391],"type":"Point"}
}