{
  "type": "Feature",
  "properties": {
    "addr:full":"8601 Dunwoody Place Atlanta GA 30350",
    "addr:housenumber":"8601",
    "addr:postcode":"30350",
    "addr:street":"Dunwoody Place",
    "iso:country":"US",
    "sg:address":"8601 Dunwoody Place",
    "sg:city":"Atlanta",
    "sg:classifiers":[
        {
            "category":"Shopping",
            "subcategory":"Clothing, Apparel, & Fashions",
            "type":"Retail Goods"
        }
    ],
    "sg:phone":"+1 770 993 1646",
    "sg:postcode":"30350",
    "sg:province":"GA",
    "sg:tags":[
        "clothing",
        "women's"
    ],
    "wof:name":"Southeast Apparel Limited",
    "wof:placetype":"venue"
},
  "geometry": {"coordinates":[-84.342144,33.989685],"type":"Point"}
}