{
  "type": "Feature",
  "properties": {
    "addr:full":"5260 Memorial Dr Stone Mountain GA 30083",
    "addr:housenumber":"5260",
    "addr:postcode":"30083",
    "addr:street":"Memorial Dr",
    "iso:country":"US",
    "sg:address":"5260 Memorial Dr",
    "sg:city":"Stone Mountain",
    "sg:classifiers":[
        {
            "category":"Government",
            "subcategory":"Office",
            "type":"Public Place"
        }
    ],
    "sg:phone":"+1 404 294 9065",
    "sg:postcode":"30083",
    "sg:province":"GA",
    "sg:tags":[
        "armed",
        "force",
        "recruiting"
    ],
    "wof:name":"US Army Recruiting",
    "wof:placetype":"venue"
},
  "geometry": {"coordinates":[-84.224031,33.797202],"type":"Point"}
}