{
  "type": "Feature",
  "properties": {
    "addr:full":"117 Sharon Ct Pooler GA 31322",
    "addr:housenumber":"117",
    "addr:postcode":"31322",
    "addr:street":"Sharon Ct",
    "iso:country":"US",
    "sg:address":"117 Sharon Ct",
    "sg:city":"Pooler",
    "sg:classifiers":[
        {
            "category":"Building & Trades",
            "subcategory":"Equipment Rental",
            "type":"Services"
        }
    ],
    "sg:phone":"+1 912 748 1318",
    "sg:postcode":"31322",
    "sg:province":"GA",
    "sg:tags":[
        "crane"
    ],
    "wof:name":"Tim's Crane & Rigging",
    "wof:placetype":"venue"
},
  "geometry": {"coordinates":[-81.226849,32.104221],"type":"Point"}
}