{
  "type": "Feature",
  "properties": {
    "addr:full":"4400 Ashford Dunwoody Rd NE Ste 1480 Atlanta GA 30346",
    "addr:housenumber":"4400",
    "addr:postcode":"30346",
    "addr:street":"Ashford Dunwoody Rd Ne Ste 1480",
    "iso:country":"US",
    "sg:address":"4400 Ashford Dunwoody Rd NE Ste 1480",
    "sg:city":"Atlanta",
    "sg:classifiers":[
        {
            "category":"Manufacturing",
            "subcategory":"Leather Goods",
            "type":"Manufacturing & Wholesale Goods"
        }
    ],
    "sg:phone":"+1 770 394 3235",
    "sg:postcode":"30346",
    "sg:province":"GA",
    "sg:website":"www.moriluggage.com",
    "wof:name":"Mori Luggage & Gifts",
    "wof:placetype":"venue"
},
  "geometry": {"coordinates":[-84.341719,33.923981],"type":"Point"}
}