{
  "type": "Feature",
  "properties": {
    "addr:full":"2772 Lake Vista Dr NE Buford GA 30519",
    "addr:housenumber":"2772",
    "addr:postcode":"30519",
    "addr:street":"Lake Vista Dr Ne",
    "iso:country":"US",
    "sg:address":"2772 Lake Vista Dr NE",
    "sg:city":"Buford",
    "sg:classifiers":[
        {
            "category":"Professional",
            "type":"Services"
        }
    ],
    "sg:phone":"+1 770 271 3551",
    "sg:postcode":"30519",
    "sg:province":"GA",
    "sg:tags":[
        "establishment"
    ],
    "wof:name":"Roth & Roth",
    "wof:placetype":"venue"
},
  "geometry": {"coordinates":[-83.931529,34.07673],"type":"Point"}
}