{
  "type": "Feature",
  "properties": {
    "addr:full":"960 Oconee St Athens GA 30605",
    "addr:housenumber":"960",
    "addr:postcode":"30605",
    "addr:street":"Oconee St",
    "iso:country":"US",
    "sg:address":"960 Oconee St",
    "sg:city":"Athens",
    "sg:classifiers":[
        {
            "category":"Real Estate",
            "subcategory":"Real Estate Operator",
            "type":"Services"
        }
    ],
    "sg:phone":"+1 706 549 2500",
    "sg:postcode":"30605",
    "sg:province":"GA",
    "sg:tags":[
        "apartment"
    ],
    "sg:website":"www.athensapartments.com",
    "wof:name":"Hill Apartment Complex",
    "wof:placetype":"venue"
},
  "geometry": {"coordinates":[-83.363801,33.950527],"type":"Point"}
}