{
  "type": "Feature",
  "properties": {
    "addr:full":"6234 Old Highway 5 Woodstock GA 30188",
    "addr:housenumber":"6234",
    "addr:postcode":"30188",
    "addr:street":"Old Highway 5",
    "iso:country":"US",
    "sg:address":"6234 Old Highway 5",
    "sg:city":"Woodstock",
    "sg:classifiers":[
        {
            "category":"Restaurant",
            "type":"Food & Drink"
        }
    ],
    "sg:menulink":"http://www.allmenus.com/ga/holly-springs/229561-taste-of-italy/menu/",
    "sg:phone":"+1 678 388 7270",
    "sg:postcode":"30188",
    "sg:province":"GA",
    "sg:tags":[
        "italian"
    ],
    "wof:name":"Taste Of Italy",
    "wof:placetype":"venue"
},
  "geometry": {"coordinates":[-84.497854,34.130459],"type":"Point"}
}