{
  "type": "Feature",
  "properties": {
    "addr:full":"1700 Murray Ave Dalton GA 30721",
    "addr:housenumber":"1700",
    "addr:postcode":"30721",
    "addr:street":"Murray Ave",
    "iso:country":"US",
    "sg:address":"1700 Murray Ave",
    "sg:city":"Dalton",
    "sg:classifiers":[
        {
            "category":"Personal",
            "subcategory":"Beauty Salon",
            "type":"Services"
        }
    ],
    "sg:phone":"+1 706 281 2073",
    "sg:postcode":"30721",
    "sg:province":"GA",
    "wof:name":"Genesis Salon De Belleza",
    "wof:placetype":"venue"
},
  "geometry": {"coordinates":[-84.940331,34.766411],"type":"Point"}
}