{
  "type": "Feature",
  "properties": {
    "addr:full":"2065 Red Rock Rd Toccoa GA 30577",
    "addr:housenumber":"2065",
    "addr:postcode":"30577",
    "addr:street":"Red Rock Rd",
    "iso:country":"US",
    "sg:address":"2065 Red Rock Rd",
    "sg:city":"Toccoa",
    "sg:classifiers":[
        {
            "category":"Food & Beverages",
            "subcategory":"Groceries & Convenience Stores",
            "type":"Retail Goods"
        }
    ],
    "sg:phone":"+1 706 297 0065",
    "sg:postcode":"30577",
    "sg:province":"GA",
    "sg:tags":[
        "grocer"
    ],
    "wof:name":"Ike's Food Mart",
    "wof:placetype":"venue"
},
  "geometry": {"coordinates":[-83.243059,34.585318],"type":"Point"}
}