{
  "type": "Feature",
  "properties": {
    "iso:country":"US",
    "sg:address":"101 Pine Dr",
    "sg:city":"Woodbine",
    "sg:classifiers":[
        {
            "category":"Building & Trades",
            "subcategory":"Plumbing",
            "type":"Services"
        }
    ],
    "sg:phone":"+1 912 729 1799",
    "sg:postcode":"31569",
    "sg:province":"GA",
    "sg:tags":[
        "plumbing",
        "contractor"
    ],
    "wof:name":"Camden Plumbing Svc",
    "wof:placetype":"venue"
},
  "geometry": {"coordinates":[-81.635492,30.862986],"type":"Point"}
}