{
  "type": "Feature",
  "properties": {
    "addr:full":"10820 Abbotts Bridge Rd Duluth GA 30097",
    "addr:housenumber":"10820",
    "addr:postcode":"30097",
    "addr:street":"Abbotts Bridge Rd",
    "iso:country":"US",
    "sg:address":"10820 Abbotts Bridge Rd",
    "sg:city":"Duluth",
    "sg:classifiers":[
        {
            "category":"Deli",
            "type":"Food & Drink"
        }
    ],
    "sg:menulink":"http://www.allmenus.com/ga/roswell-alpharetta/156708-my-friends-place/menu/",
    "sg:phone":"+1 770 814 0600",
    "sg:postcode":"30097",
    "sg:province":"GA",
    "sg:tags":[
        "american"
    ],
    "wof:name":"My Friend's Place",
    "wof:placetype":"venue"
},
  "geometry": {"coordinates":[-84.175589,34.042179],"type":"Point"}
}