{
  "type": "Feature",
  "properties": {
    "iso:country":"US",
    "sg:address":"530 Forest Hill Rd",
    "sg:city":"Macon",
    "sg:classifiers":[
        {
            "category":"Freight",
            "type":"Transportation"
        }
    ],
    "sg:phone":"+1 478 750 7279",
    "sg:postcode":"31210",
    "sg:province":"GA",
    "sg:tags":[
        "trucking"
    ],
    "wof:name":"Napier Diversified Services Inc",
    "wof:placetype":"venue"
},
  "geometry": {"coordinates":[-83.69081199999999,32.872258],"type":"Point"}
}