{
  "type": "Feature",
  "properties": {
    "iso:country":"US",
    "sg:address":"205 Joe Louis Dr NW",
    "sg:city":"Atlanta",
    "sg:classifiers":[
        {
            "category":"Retail",
            "subcategory":"Auto Repair",
            "type":"Services"
        }
    ],
    "sg:phone":"+1 404 794 4037",
    "sg:postcode":"30314",
    "sg:province":"GA",
    "sg:tags":[
        "general"
    ],
    "wof:name":"Gibbs Automotive & Electronics",
    "wof:placetype":"venue"
},
  "geometry": {"coordinates":[-84.460173,33.760921],"type":"Point"}
}