{
  "type": "Feature",
  "properties": {
    "iso:country":"US",
    "sg:address":"1295 Georgia Ave",
    "sg:city":"Macon",
    "sg:classifiers":[
        {
            "category":"Organizations",
            "subcategory":"Religious Organization",
            "type":"Services"
        }
    ],
    "sg:phone":"+1 478 742 4474",
    "sg:postcode":"31201",
    "sg:province":"GA",
    "sg:tags":[
        "church"
    ],
    "wof:name":"First Church-Christ Scientist",
    "wof:placetype":"venue"
},
  "geometry": {"coordinates":[-83.64018299999999,32.840805],"type":"Point"}
}