{
  "type": "Feature",
  "properties": {
    "iso:country":"US",
    "sg:address":"2275 Bethany Rd",
    "sg:city":"Jasper",
    "sg:classifiers":[
        {
            "category":"Building & Trades",
            "subcategory":"Construction",
            "type":"Services"
        }
    ],
    "sg:phone":"+1 770 735 2262",
    "sg:postcode":"30143",
    "sg:province":"GA",
    "sg:tags":[
        "general",
        "contractor"
    ],
    "wof:name":"Trillium Enterprises Inc",
    "wof:placetype":"venue"
},
  "geometry": {"coordinates":[-84.459439,34.40095],"type":"Point"}
}