{
  "type": "Feature",
  "properties": {
    "addr:full":"318 Robert Zorn Rd Lyons GA 30436",
    "addr:housenumber":"318",
    "addr:postcode":"30436",
    "addr:street":"Robert Zorn Rd",
    "iso:country":"US",
    "sg:address":"318 Robert Zorn Rd",
    "sg:city":"Lyons",
    "sg:classifiers":[
        {
            "category":"Freight",
            "type":"Transportation"
        }
    ],
    "sg:phone":"+1 912 537 1819",
    "sg:postcode":"30436",
    "sg:province":"GA",
    "sg:tags":[
        "operator",
        "trucking"
    ],
    "wof:name":"A & C Mobile Home Service",
    "wof:placetype":"venue"
},
  "geometry": {"coordinates":[-82.35334,32.248801],"type":"Point"}
}