{
  "type": "Feature",
  "properties": {
    "iso:country":"US",
    "sg:address":"316 Lexington Dr",
    "sg:city":"Albany",
    "sg:classifiers":[
        {
            "category":"Social Services",
            "subcategory":"Child Care",
            "type":"Services"
        }
    ],
    "sg:phone":"+1 229 435 6409",
    "sg:postcode":"31705",
    "sg:province":"GA",
    "sg:tags":[
        "day"
    ],
    "wof:name":"Lulas Day Care",
    "wof:placetype":"venue"
},
  "geometry": {"coordinates":[-84.080933,31.578912],"type":"Point"}
}