{
  "type": "Feature",
  "properties": {
    "iso:country":"US",
    "sg:address":"782 Ponce De Leon Ave NE",
    "sg:city":"Atlanta",
    "sg:classifiers":[
        {
            "category":"Restaurant",
            "type":"Food & Drink"
        }
    ],
    "sg:menulink":"http://www.allmenus.com/ga/atlanta/259548-doc-greens-gourmet-salads/menu/",
    "sg:phone":"+1 404 446 1750",
    "sg:postcode":"30306",
    "sg:province":"GA",
    "sg:tags":[
        "american",
        "sandwich",
        "salad"
    ],
    "wof:name":"Doc Green's Gourmet Salads",
    "wof:placetype":"venue"
},
  "geometry": {"coordinates":[-84.361521,33.77394],"type":"Point"}
}