{
  "type": "Feature",
  "properties": {
    "addr:full":"207 Courson Rd Baxley GA 31513",
    "addr:housenumber":"207",
    "addr:postcode":"31513",
    "addr:street":"Courson Rd",
    "iso:country":"US",
    "sg:address":"207 Courson Rd",
    "sg:city":"Baxley",
    "sg:classifiers":[
        {
            "category":"Retail",
            "subcategory":"Repair Shop",
            "type":"Services"
        },
        {
            "category":"Building & Trades",
            "subcategory":"Construction",
            "type":"Services"
        }
    ],
    "sg:phone":"+1 912 367 2611",
    "sg:postcode":"31513",
    "sg:province":"GA",
    "sg:tags":[
        "system",
        "major",
        "refinishing",
        "appliance",
        "heating",
        "specialty",
        "small",
        "contractor",
        "air conditioning"
    ],
    "wof:name":"Britts Refrigeration-Heating & Air Conditioning",
    "wof:placetype":"venue"
},
  "geometry": {"coordinates":[-82.368247,31.688651],"type":"Point"}
}