{
  "type": "Feature",
  "properties": {
    "addr:full":"959 E Confederate Ave SE Atlanta GA 30316",
    "addr:housenumber":"959",
    "addr:postcode":"30316",
    "addr:street":"E Confederate Ave Se",
    "iso:country":"US",
    "sg:address":"959 E Confederate Ave SE",
    "sg:city":"Atlanta",
    "sg:classifiers":[
        {
            "category":"Government",
            "subcategory":"Office",
            "type":"Public Place"
        }
    ],
    "sg:phone":"+1 404 624 7876",
    "sg:postcode":"30316",
    "sg:province":"GA",
    "sg:tags":[
        "state",
        "taxation"
    ],
    "wof:name":"Budget Office",
    "wof:placetype":"venue"
},
  "geometry": {"coordinates":[-84.357226,33.726618],"type":"Point"}
}