{
  "type": "Feature",
  "properties": {
    "addr:full":"4060 Peachtree Rd NE Atlanta GA 30319",
    "addr:housenumber":"4060",
    "addr:postcode":"30319",
    "addr:street":"Peachtree Rd Ne",
    "iso:country":"US",
    "sg:address":"4060 Peachtree Rd NE",
    "sg:city":"Atlanta",
    "sg:classifiers":[
        {
            "category":"Real Estate",
            "subcategory":"Architect",
            "type":"Services"
        }
    ],
    "sg:phone":"+1 404 315 1032",
    "sg:postcode":"30319",
    "sg:province":"GA",
    "wof:name":"Chamberlain Blanton Associates Architects",
    "wof:placetype":"venue"
},
  "geometry": {"coordinates":[-84.339598,33.861167],"type":"Point"}
}