{
  "type": "Feature",
  "properties": {
    "iso:country":"US",
    "sg:address":"25597 US Hwy 19",
    "sg:city":"Ochlocknee",
    "sg:classifiers":[
        {
            "category":"Manufacturing",
            "subcategory":"Lumber",
            "type":"Manufacturing & Wholesale Goods"
        }
    ],
    "sg:phone":"+1 229 224 8249",
    "sg:postcode":"31773",
    "sg:province":"GA",
    "sg:tags":[
        "logging",
        "contractor"
    ],
    "wof:name":"K Gunz Logging Inc",
    "wof:placetype":"venue"
},
  "geometry": {"coordinates":[-84.037088,30.976967],"type":"Point"}
}