{
  "type": "Feature",
  "properties": {
    "addr:full":"354 E Washington Ave Ashburn GA 31714",
    "addr:housenumber":"354",
    "addr:postcode":"31714",
    "addr:street":"E Washington Ave",
    "iso:country":"US",
    "sg:address":"354 E Washington Ave",
    "sg:city":"Ashburn",
    "sg:classifiers":[
        {
            "category":"Health Services",
            "subcategory":"Doctor",
            "type":"Services"
        }
    ],
    "sg:phone":"+1 229 567 3361",
    "sg:postcode":"31714",
    "sg:province":"GA",
    "sg:tags":[
        "physician",
        "medical",
        "surgeon"
    ],
    "wof:name":"Phoebe Family Medical Center",
    "wof:placetype":"venue"
},
  "geometry": {"coordinates":[-83.64877799999999,31.707667],"type":"Point"}
}