{
  "type": "Feature",
  "properties": {
    "iso:country":"US",
    "sg:address":"2784 N Decatur Rd Ste 145",
    "sg:city":"Decatur",
    "sg:classifiers":[
        {
            "category":"Health Services",
            "subcategory":"Clinic",
            "type":"Services"
        }
    ],
    "sg:phone":"+1 404 292 2664",
    "sg:postcode":"30033",
    "sg:province":"GA",
    "sg:tags":[
        "counseling",
        "mental"
    ],
    "wof:name":"Decatur Psychological Associates",
    "wof:placetype":"venue"
},
  "geometry": {"coordinates":[-84.279297,33.793201],"type":"Point"}
}