{
  "type": "Feature",
  "properties": {
    "addr:full":"156 Roberson Ln Milledgeville GA 31027",
    "addr:housenumber":"156",
    "addr:postcode":"31027",
    "addr:street":"Roberson Ln",
    "iso:country":"US",
    "sg:address":"156 Roberson Ln",
    "sg:city":"Milledgeville",
    "sg:classifiers":[
        {
            "category":"Government",
            "subcategory":"Office",
            "type":"Public Place"
        }
    ],
    "sg:phone":"+1 478 445 5465",
    "sg:postcode":"31027",
    "sg:province":"GA",
    "sg:tags":[
        "state",
        "inspection"
    ],
    "sg:website":"www.dol.state.ga.us",
    "wof:name":"Labor Dept",
    "wof:placetype":"venue"
},
  "geometry": {"coordinates":[-82.87340399999999,32.55395],"type":"Point"}
}