{
  "type": "Feature",
  "properties": {
    "iso:country":"US",
    "sg:address":"34 Broad St NW",
    "sg:city":"Atlanta",
    "sg:classifiers":[
        {
            "category":"Restaurant",
            "type":"Food & Drink"
        }
    ],
    "sg:phone":"+1 404 681 2909",
    "sg:postcode":"30303",
    "sg:province":"GA",
    "sg:tags":[
        "caterer"
    ],
    "wof:name":"Artists In The Kitchen",
    "wof:placetype":"venue"
},
  "geometry": {"coordinates":[-84.390126,33.755254],"type":"Point"}
}