{
  "type": "Feature",
  "properties": {
    "addr:full":"303 Falls Ct Woodstock GA 30188",
    "addr:housenumber":"303",
    "addr:postcode":"30188",
    "addr:street":"Falls Ct",
    "iso:country":"US",
    "sg:address":"303 Falls Ct",
    "sg:city":"Woodstock",
    "sg:classifiers":[
        {
            "category":"Real Estate",
            "subcategory":"Real Estate Agent",
            "type":"Services"
        }
    ],
    "sg:phone":"+1 770 569 9892",
    "sg:postcode":"30188",
    "sg:province":"GA",
    "wof:name":"Junxure Creative Inc",
    "wof:placetype":"venue"
},
  "geometry": {"coordinates":[-84.386668,34.128877],"type":"Point"}
}