{
  "type": "Feature",
  "properties": {
    "addr:full":"206 E Hillside Dr Lagrange GA 30241",
    "addr:housenumber":"206",
    "addr:postcode":"30241",
    "addr:street":"E Hillside Dr",
    "iso:country":"US",
    "sg:address":"206 E Hillside Dr",
    "sg:city":"Lagrange",
    "sg:classifiers":[
        {
            "category":"Organizations",
            "subcategory":"Religious Organization",
            "type":"Services"
        }
    ],
    "sg:phone":"+1 706 837 9190",
    "sg:postcode":"30241",
    "sg:province":"GA",
    "sg:tags":[
        "church"
    ],
    "wof:name":"Word Of Faith Ministry",
    "wof:placetype":"venue"
},
  "geometry": {"coordinates":[-85.024821,33.018361],"type":"Point"}
}