{
  "type": "Feature",
  "properties": {
    "iso:country":"US",
    "sg:address":"402 N West St",
    "sg:city":"Bainbridge",
    "sg:classifiers":[
        {
            "category":"Restaurant",
            "type":"Food & Drink"
        }
    ],
    "sg:phone":"+1 229 243 2233",
    "sg:postcode":"39817",
    "sg:province":"GA",
    "wof:name":"Court Yard Cafe",
    "wof:placetype":"venue"
},
  "geometry": {"coordinates":[-84.576521,30.909284],"type":"Point"}
}