{
  "type": "Feature",
  "properties": {
    "iso:country":"US",
    "sg:address":"3140 Dearing Acres Rd",
    "sg:city":"Thomson",
    "sg:classifiers":[
        {
            "category":"Retail",
            "subcategory":"Auto Repair",
            "type":"Services"
        }
    ],
    "sg:phone":"+1 706 595 0942",
    "sg:postcode":"30808",
    "sg:province":"GA",
    "sg:tags":[
        "general"
    ],
    "wof:name":"Jigs Wrecker Service & Auto R",
    "wof:placetype":"venue"
},
  "geometry": {"coordinates":[-82.406823,33.410929],"type":"Point"}
}