{
  "type": "Feature",
  "properties": {
    "iso:country":"US",
    "sg:address":"1111 Augusta Rd",
    "sg:city":"North Augusta",
    "sg:classifiers":[
        {
            "category":"Professional",
            "subcategory":"Business Services",
            "type":"Services"
        }
    ],
    "sg:phone":"+1 803 279 8017",
    "sg:postcode":"29822",
    "sg:province":"SC",
    "sg:tags":[
        "fund",
        "promotion",
        "raising"
    ],
    "wof:name":"Turn Key Promotions",
    "wof:placetype":"venue"
},
  "geometry": {"coordinates":[-81.891961,33.496761],"type":"Point"}
}