{
  "type": "Feature",
  "properties": {
    "iso:country":"US",
    "sg:address":"4036 Spalding Dr",
    "sg:city":"Atlanta",
    "sg:classifiers":[
        {
            "category":"Health Services",
            "subcategory":"Optometrist",
            "type":"Services"
        }
    ],
    "sg:phone":"+1 770 394 9273",
    "sg:postcode":"30350",
    "sg:province":"GA",
    "wof:name":"Dudovitz David W OD",
    "wof:placetype":"venue"
},
  "geometry": {"coordinates":[-84.346497,33.9659],"type":"Point"}
}