{
  "type": "Feature",
  "properties": {
    "iso:country":"US",
    "sg:address":"134 Rockbridge Rd SW",
    "sg:city":"Lilburn",
    "sg:classifiers":[
        {
            "category":"Building & Trades",
            "subcategory":"Plumbing",
            "type":"Services"
        }
    ],
    "sg:phone":"+1 770 921 5764",
    "sg:postcode":"30047",
    "sg:province":"GA",
    "sg:tags":[
        "contractor"
    ],
    "wof:name":"Elm Solar Solutions",
    "wof:placetype":"venue"
},
  "geometry": {"coordinates":[-84.152823,33.877137],"type":"Point"}
}