{
  "type": "Feature",
  "properties": {
    "addr:full":"59 Executive Park South NE Atlanta GA 30329",
    "addr:housenumber":"59",
    "addr:postcode":"30329",
    "addr:street":"Executive Park South Ne",
    "iso:country":"US",
    "sg:address":"59 Executive Park South NE",
    "sg:city":"Atlanta",
    "sg:classifiers":[
        {
            "category":"Professional",
            "subcategory":"Advertising",
            "type":"Services"
        }
    ],
    "sg:phone":"+1 404 235 2115",
    "sg:postcode":"30329",
    "sg:province":"GA",
    "sg:tags":[
        "agency",
        "specialty"
    ],
    "wof:name":"Bell South Advertising & Pub.",
    "wof:placetype":"venue"
},
  "geometry": {"coordinates":[-84.341071,33.828072],"type":"Point"}
}