{
  "type": "Feature",
  "properties": {
    "iso:country":"US",
    "sg:address":"2250 Chrysler Ter NE",
    "sg:city":"Atlanta",
    "sg:classifiers":[
        {
            "category":"Real Estate",
            "subcategory":"Real Estate Agent",
            "type":"Services"
        }
    ],
    "sg:phone":"+1 404 636 3704",
    "sg:postcode":"30345",
    "sg:province":"GA",
    "wof:name":"Liane R Levetan",
    "wof:placetype":"venue"
},
  "geometry": {"coordinates":[-84.29664099999999,33.837605],"type":"Point"}
}