{
  "type": "Feature",
  "properties": {
    "iso:country":"US",
    "sg:address":"9539 Highway 92 Ste 130",
    "sg:city":"Woodstock",
    "sg:classifiers":[
        {
            "category":"Real Estate",
            "subcategory":"Real Estate Services",
            "type":"Services"
        },
        {
            "category":"Banks & Credit Unions",
            "subcategory":"Financial Services",
            "type":"Services"
        }
    ],
    "sg:phone":"+1 770 924 4115",
    "sg:postcode":"30188",
    "sg:province":"GA",
    "sg:tags":[
        "financing",
        "processing",
        "loan",
        "mortgage",
        "broker"
    ],
    "sg:website":"www.aigag.com",
    "wof:name":"American General Financial Services",
    "wof:placetype":"venue"
},
  "geometry": {"coordinates":[-84.526398,34.0863],"type":"Point"}
}