{
  "type": "Feature",
  "properties": {
    "iso:country":"US",
    "sg:address":"3920 Club Dr",
    "sg:city":"Duluth",
    "sg:classifiers":[
        {
            "category":"Building & Trades",
            "subcategory":"Cleaning & Sanitation",
            "type":"Services"
        }
    ],
    "sg:phone":"+1 678 357 7139",
    "sg:postcode":"30096",
    "sg:province":"GA",
    "sg:tags":[
        "maintenance"
    ],
    "wof:name":"Wooree Cleaning Services",
    "wof:placetype":"venue"
},
  "geometry": {"coordinates":[-84.139427,33.942298],"type":"Point"}
}