{
  "type": "Feature",
  "properties": {
    "addr:full":"1847 Homestead Ave NE Atlanta GA 30306",
    "addr:housenumber":"1847",
    "addr:postcode":"30306",
    "addr:street":"Homestead Ave Ne",
    "iso:country":"US",
    "sg:address":"1847 Homestead Ave NE",
    "sg:city":"Atlanta",
    "sg:classifiers":[
        {
            "category":"Wholesale",
            "subcategory":"Jewelry",
            "type":"Manufacturing & Wholesale Goods"
        }
    ],
    "sg:phone":"+1 404 728 1994",
    "sg:postcode":"30306",
    "sg:province":"GA",
    "sg:tags":[
        "jeweler"
    ],
    "wof:name":"Karibou",
    "wof:placetype":"venue"
},
  "geometry": {"coordinates":[-84.34797500000001,33.803349],"type":"Point"}
}