{
  "type": "Feature",
  "properties": {
    "addr:full":"609 Northside Dr W Statesboro GA 30458",
    "addr:housenumber":"609",
    "addr:postcode":"30458",
    "addr:street":"Northside Dr W",
    "iso:country":"US",
    "sg:address":"609 Northside Dr W",
    "sg:city":"Statesboro",
    "sg:classifiers":[
        {
            "category":"Restaurant",
            "type":"Food & Drink"
        }
    ],
    "sg:menulink":"http://www.allmenus.com/ga/statesboro/140667-waffle-house/menu/",
    "sg:phone":"+1 706 965 2440",
    "sg:postcode":"30458",
    "sg:province":"GA",
    "sg:tags":[
        "american"
    ],
    "wof:name":"Waffle House",
    "wof:placetype":"venue"
},
  "geometry": {"coordinates":[-81.79137799999999,32.461637],"type":"Point"}
}