{
  "type": "Feature",
  "properties": {
    "iso:country":"US",
    "sg:address":"3969 Brockett Walk",
    "sg:city":"Tucker",
    "sg:classifiers":[
        {
            "category":"Travel",
            "subcategory":"Travel Agent",
            "type":"Entertainment"
        }
    ],
    "sg:phone":"+1 770 908 1893",
    "sg:postcode":"30084",
    "sg:province":"GA",
    "sg:tags":[
        "agency",
        "bureau"
    ],
    "wof:name":"Odyssey Travel",
    "wof:placetype":"venue"
},
  "geometry": {"coordinates":[-84.225553,33.844833],"type":"Point"}
}