{
  "type": "Feature",
  "properties": {
    "addr:full":"388 Richardson Rd SE Calhoun GA 30701",
    "addr:housenumber":"388",
    "addr:postcode":"30701",
    "addr:street":"Richardson Rd Se",
    "iso:country":"US",
    "sg:address":"388 Richardson Rd SE",
    "sg:city":"Calhoun",
    "sg:classifiers":[
        {
            "category":"Home & Garden",
            "subcategory":"Building Materials",
            "type":"Retail Goods"
        }
    ],
    "sg:phone":"+1 706 624 1584",
    "sg:postcode":"30701",
    "sg:province":"GA",
    "sg:website":"www.84lumber.com",
    "wof:name":"84 Lumber Co",
    "wof:placetype":"venue"
},
  "geometry": {"coordinates":[-84.925515,34.470183],"type":"Point"}
}