{
  "type": "Feature",
  "properties": {
    "addr:full":"752 White Blossom Ct Powder Springs GA 30127",
    "addr:housenumber":"752",
    "addr:postcode":"30127",
    "addr:street":"White Blossom Ct",
    "iso:country":"US",
    "sg:address":"752 White Blossom Ct",
    "sg:city":"Powder Springs",
    "sg:classifiers":[
        {
            "category":"Professional",
            "subcategory":"Business Services",
            "type":"Services"
        }
    ],
    "sg:phone":"+1 770 795 9981",
    "sg:postcode":"30127",
    "sg:province":"GA",
    "wof:name":"Franklin Management Group LLC",
    "wof:placetype":"venue"
},
  "geometry": {"coordinates":[-84.689922,33.934652],"type":"Point"}
}