{
  "type": "Feature",
  "properties": {
    "addr:full":"2324 Donald Lee Hollowell Pkwy NW Atlanta GA 30318",
    "addr:housenumber":"2324",
    "addr:postcode":"30318",
    "addr:street":"Donald Lee Hollowell Pkwy Nw",
    "iso:country":"US",
    "sg:address":"2324 Donald Lee Hollowell Pkwy NW",
    "sg:city":"Atlanta",
    "sg:classifiers":[
        {
            "category":"Building & Trades",
            "subcategory":"Locksmith",
            "type":"Services"
        }
    ],
    "sg:phone":"+1 678 369 5691",
    "sg:postcode":"30318",
    "sg:province":"GA",
    "sg:tags":[
        "key"
    ],
    "wof:name":"7 Days Emergency Locksmith",
    "wof:placetype":"venue"
},
  "geometry": {"coordinates":[-84.461755,33.777004],"type":"Point"}
}