{
  "type": "Feature",
  "properties": {
    "iso:country":"US",
    "sg:address":"1167 Henry Ave",
    "sg:city":"Columbus",
    "sg:classifiers":[
        {
            "category":"Recreation",
            "type":"Entertainment"
        }
    ],
    "sg:phone":"+1 706 321 1284",
    "sg:postcode":"31906",
    "sg:province":"GA",
    "wof:name":"Columbus Karate Academy",
    "wof:placetype":"venue"
},
  "geometry": {"coordinates":[-84.957747,32.468765],"type":"Point"}
}