{
  "type": "Feature",
  "properties": {
    "addr:full":"4020 Jim Moore Rd Dacula GA 30019",
    "addr:housenumber":"4020",
    "addr:postcode":"ga 30019",
    "addr:street":"Jim Moore Rd",
    "iso:country":"US",
    "sg:address":"4020 Jim Moore Rd",
    "sg:city":"Dacula",
    "sg:classifiers":[
        {
            "category":"Personal",
            "subcategory":"Beauty Salon",
            "type":"Services"
        }
    ],
    "sg:phone":"+1 770 271 1271",
    "sg:postcode":"30019",
    "sg:province":"GA",
    "sg:tags":[
        "shop"
    ],
    "wof:name":"Supercuts",
    "wof:placetype":"venue"
},
  "geometry": {"coordinates":[-83.90348899999999,34.05738],"type":"Point"}
}