{
  "type": "Feature",
  "properties": {
    "addr:full":"3050 Peachtree Rd NW Ste 135 Atlanta GA 30305",
    "addr:housenumber":"3050",
    "addr:postcode":"30305",
    "addr:street":"Peachtree Rd Nw Ste 135",
    "iso:country":"US",
    "sg:address":"3050 Peachtree Rd NW Ste 135",
    "sg:city":"Atlanta",
    "sg:classifiers":[
        {
            "category":"Personal",
            "subcategory":"Beauty Salon",
            "type":"Services"
        }
    ],
    "sg:phone":"+1 404 237 2539",
    "sg:postcode":"30305",
    "sg:province":"GA",
    "sg:tags":[
        "hair"
    ],
    "sg:website":"www.alexandarsalon.com",
    "wof:name":"Alexandar Salon",
    "wof:placetype":"venue"
},
  "geometry": {"coordinates":[-84.380696,33.838419],"type":"Point"}
}