{
  "type": "Feature",
  "properties": {
    "addr:full":"1991 S Cobb Dr Marietta GA 30060",
    "addr:housenumber":"1991",
    "addr:postcode":"30060",
    "addr:street":"S Cobb Dr",
    "iso:country":"US",
    "sg:address":"1991 S Cobb Dr",
    "sg:city":"Marietta",
    "sg:classifiers":[
        {
            "category":"Restaurant",
            "type":"Food & Drink"
        }
    ],
    "sg:phone":"+1 770 801 9450",
    "sg:postcode":"30060",
    "sg:province":"GA",
    "sg:tags":[
        "eating"
    ],
    "wof:name":"Vueleve A La Vida Mexican",
    "wof:placetype":"venue"
},
  "geometry": {"coordinates":[-84.543217,33.907313],"type":"Point"}
}