{
  "type": "Feature",
  "properties": {
    "iso:country":"US",
    "sg:address":"3344 River Birch Way",
    "sg:city":"Roswell",
    "sg:classifiers":[
        {
            "category":"Professional",
            "subcategory":"Management & Consulting",
            "type":"Services"
        }
    ],
    "sg:phone":"+1 770 998 2826",
    "sg:postcode":"30075",
    "sg:province":"GA",
    "sg:tags":[
        "business"
    ],
    "wof:name":"Regal Renditions",
    "wof:placetype":"venue"
},
  "geometry": {"coordinates":[-84.43030899999999,34.031876],"type":"Point"}
}