{
  "type": "Feature",
  "properties": {
    "addr:full":"8201 White Bluff Rd Savannah GA 31406",
    "addr:housenumber":"8201",
    "addr:postcode":"31406",
    "addr:street":"White Bluff Rd",
    "iso:country":"US",
    "sg:address":"8201 White Bluff Rd",
    "sg:city":"Savannah",
    "sg:classifiers":[
        {
            "category":"Government",
            "subcategory":"Office",
            "type":"Public Place"
        }
    ],
    "sg:phone":"+1 912 651 2001",
    "sg:postcode":"31406",
    "sg:province":"GA",
    "wof:name":"Pardons & Paroles State Board",
    "wof:placetype":"venue"
},
  "geometry": {"coordinates":[-81.12182199999999,31.999626],"type":"Point"}
}