{
  "type": "Feature",
  "properties": {
    "addr:full":"2891 N Decatur Rd Ste B Decatur GA 30033",
    "addr:housenumber":"2891",
    "addr:postcode":"30033",
    "addr:street":"N Decatur Rd Ste B",
    "iso:country":"US",
    "sg:address":"2891 N Decatur Rd Ste B",
    "sg:city":"Decatur",
    "sg:classifiers":[
        {
            "category":"Health Services",
            "subcategory":"Clinic",
            "type":"Services"
        },
        {
            "category":"Personal",
            "subcategory":"Hair Removal",
            "type":"Services"
        },
        {
            "category":"Personal",
            "subcategory":"Day Spa",
            "type":"Services"
        },
        {
            "category":"Personal",
            "subcategory":"Skin Care",
            "type":"Services"
        },
        {
            "category":"Health Services",
            "subcategory":"Doctor",
            "type":"Services"
        },
        {
            "category":"Health Services",
            "subcategory":"Health Practitioner",
            "type":"Services"
        }
    ],
    "sg:phone":"+1 404 298 7877",
    "sg:postcode":"30033",
    "sg:province":"GA",
    "sg:tags":[
        "control",
        "management",
        "weight",
        "physician",
        "medical",
        "surgeons",
        "loss"
    ],
    "sg:website":"http://www.myjawani.com",
    "wof:name":"Jawani Medical Spa",
    "wof:placetype":"venue"
},
  "geometry": {"coordinates":[-84.274134,33.793777],"type":"Point"}
}