{
  "type": "Feature",
  "properties": {
    "addr:full":"2040 Lower Roswell Rd Marietta GA 30068",
    "addr:housenumber":"2040",
    "addr:postcode":"30068",
    "addr:street":"Lower Roswell Rd",
    "iso:country":"US",
    "sg:address":"2040 Lower Roswell Rd",
    "sg:city":"Marietta",
    "sg:classifiers":[
        {
            "category":"Banks & Credit Unions",
            "subcategory":"Financial Services",
            "type":"Services"
        }
    ],
    "sg:phone":"+1 770 279 0222",
    "sg:postcode":"30068",
    "sg:province":"GA",
    "sg:tags":[
        "broker",
        "mortgage"
    ],
    "sg:website":"www.southeastmortgage.us",
    "wof:name":"Southeast Mortgage",
    "wof:placetype":"venue"
},
  "geometry": {"coordinates":[-84.492942,33.949566],"type":"Point"}
}