{
  "type": "Feature",
  "properties": {
    "addr:full":"884 Monroe Dr NE Atlanta GA 30308",
    "addr:housenumber":"884",
    "addr:postcode":"30308",
    "addr:street":"Monroe Dr Ne",
    "iso:country":"US",
    "sg:address":"884 Monroe Dr NE",
    "sg:city":"Atlanta",
    "sg:classifiers":[
        {
            "category":"Communications",
            "type":"Services"
        }
    ],
    "sg:phone":"+1 404 685 9600",
    "sg:postcode":"30308",
    "sg:province":"GA",
    "sg:tags":[
        "translator",
        "interpreter"
    ],
    "wof:name":"Key Lingo Translations",
    "wof:placetype":"venue"
},
  "geometry": {"coordinates":[-84.36967799999999,33.778629],"type":"Point"}
}