{
  "type": "Feature",
  "properties": {
    "iso:country":"US",
    "sg:address":"434 Green St NW",
    "sg:city":"Gainesville",
    "sg:classifiers":[
        {
            "category":"Building & Trades",
            "subcategory":"Construction",
            "type":"Services"
        }
    ],
    "sg:phone":"+1 770 718 5270",
    "sg:postcode":"30501",
    "sg:province":"GA",
    "sg:tags":[
        "residential"
    ],
    "wof:name":"Lan Homes Inc",
    "wof:placetype":"venue"
},
  "geometry": {"coordinates":[-83.826635,34.301284],"type":"Point"}
}