{
  "type": "Feature",
  "properties": {
    "addr:full":"5020 Snapfinger Woods Dr Decatur GA 30035",
    "addr:postcode":"5020;30035",
    "addr:street":"Snapfinger Woods Dr",
    "iso:country":"US",
    "sg:address":"5020 Snapfinger Woods Dr",
    "sg:city":"Decatur",
    "sg:classifiers":[
        {
            "category":"Organizations",
            "subcategory":"Religious Organization",
            "type":"Services"
        }
    ],
    "sg:phone":"+1 770 323 8550",
    "sg:postcode":"30035",
    "sg:province":"GA",
    "wof:name":"Cathedral of Divine Love",
    "wof:placetype":"venue"
},
  "geometry": {"coordinates":[-84.182877,33.711315],"type":"Point"}
}