{
  "type": "Feature",
  "properties": {
    "iso:country":"US",
    "sg:address":"390 Ernest W Barrett Pkwy",
    "sg:city":"Kennesaw",
    "sg:classifiers":[
        {
            "category":"Personal",
            "subcategory":"Beauty Salon",
            "type":"Services"
        }
    ],
    "sg:phone":"+1 678 797 9138",
    "sg:postcode":"30144",
    "sg:province":"GA",
    "wof:name":"Hair Connection",
    "wof:placetype":"venue"
},
  "geometry": {"coordinates":[-84.561075,34.013832],"type":"Point"}
}