{
  "type": "Feature",
  "properties": {
    "iso:country":"US",
    "sg:address":"413 Old Americus Rd",
    "sg:city":"Vienna",
    "sg:classifiers":[
        {
            "category":"Building & Trades",
            "subcategory":"Electrical",
            "type":"Services"
        }
    ],
    "sg:phone":"+1 229 268 4009",
    "sg:postcode":"31092",
    "sg:province":"GA",
    "sg:tags":[
        "electrical",
        "contractor"
    ],
    "wof:name":"Heard Electric",
    "wof:placetype":"venue"
},
  "geometry": {"coordinates":[-83.80294600000001,32.087225],"type":"Point"}
}