{
  "type": "Feature",
  "properties": {
    "iso:country":"US",
    "sg:address":"658 Kiowa Dr NE",
    "sg:city":"Marietta",
    "sg:classifiers":[
        {
            "category":"Real Estate",
            "subcategory":"Real Estate Operator",
            "type":"Services"
        }
    ],
    "sg:phone":"+1 770 427 1685",
    "sg:postcode":"30060",
    "sg:province":"GA",
    "sg:tags":[
        "apartment"
    ],
    "wof:name":"Harmony Apartment Homes",
    "wof:placetype":"venue"
},
  "geometry": {"coordinates":[-84.538803,33.9678],"type":"Point"}
}