{
  "type": "Feature",
  "properties": {
    "iso:country":"US",
    "sg:address":"6 Poseyville Rd",
    "sg:city":"Bremen",
    "sg:classifiers":[
        {
            "category":"Place Of Worship",
            "subcategory":"Church",
            "type":"Public Place"
        },
        {
            "category":"Place Of Worship",
            "type":"Public Place"
        }
    ],
    "sg:phone":"+1 770 537 1311",
    "sg:postcode":"30110",
    "sg:province":"GA",
    "sg:tags":[
        "churches-interdenominational",
        "denomination",
        "churches-various",
        "churches-methodist"
    ],
    "wof:name":"Poseyville United Methodist Church",
    "wof:placetype":"venue"
},
  "geometry": {"coordinates":[-85.146327,33.764772],"type":"Point"}
}