{
  "type": "Feature",
  "properties": {
    "addr:full":"570 Gaines School Rd Athens GA 30605",
    "addr:housenumber":"570",
    "addr:postcode":"30605",
    "addr:street":"Gaines School Rd",
    "iso:country":"US",
    "sg:address":"570 Gaines School Rd",
    "sg:city":"Athens",
    "sg:classifiers":[
        {
            "category":"Shopping",
            "subcategory":"Gifts & Souvenirs",
            "type":"Retail Goods"
        }
    ],
    "sg:phone":"+1 706 316 1588",
    "sg:postcode":"30605",
    "sg:province":"GA",
    "sg:tags":[
        "shop"
    ],
    "wof:name":"Rabbit In The Moon Inc",
    "wof:placetype":"venue"
},
  "geometry": {"coordinates":[-83.32917399999999,33.934033],"type":"Point"}
}