{
  "type": "Feature",
  "properties": {
    "iso:country":"US",
    "sg:address":"832 Forest Path Ln",
    "sg:city":"Alpharetta",
    "sg:classifiers":[
        {
            "category":"Professional",
            "type":"Services"
        }
    ],
    "sg:phone":"+1 770 569 7247",
    "sg:postcode":"30022",
    "sg:province":"GA",
    "wof:name":"Tucci",
    "wof:placetype":"venue"
},
  "geometry": {"coordinates":[-84.236502,34.056525],"type":"Point"}
}