{
  "type": "Feature",
  "properties": {
    "addr:full":"3112 Batesville Rd Woodstock GA 30188",
    "addr:housenumber":"3112",
    "addr:postcode":"30188",
    "addr:street":"Batesville Rd",
    "iso:country":"US",
    "sg:address":"3112 Batesville Rd",
    "sg:city":"Woodstock",
    "sg:classifiers":[
        {
            "category":"Building & Trades",
            "subcategory":"Plumbing",
            "type":"Services"
        }
    ],
    "sg:phone":"+1 770 442 1503",
    "sg:postcode":"30188",
    "sg:province":"GA",
    "sg:tags":[
        "plumbing",
        "contractor"
    ],
    "wof:name":"All Phase Plumbing Inc",
    "wof:placetype":"venue"
},
  "geometry": {"coordinates":[-84.372545,34.145635],"type":"Point"}
}