{
  "type": "Feature",
  "properties": {
    "iso:country":"US",
    "sg:address":"2783 Main St",
    "sg:city":"East Point",
    "sg:classifiers":[
        {
            "category":"Bars & Pubs",
            "type":"Food & Drink"
        },
        {
            "category":"Restaurant",
            "type":"Food & Drink"
        }
    ],
    "sg:phone":"+1 404 768 0007",
    "sg:postcode":"30344",
    "sg:province":"GA",
    "sg:tags":[
        "tavern",
        "traditional",
        "american"
    ],
    "sg:website":"www.thecornertavern.com/eastpoint",
    "wof:name":"East Point Corner Tavern",
    "wof:placetype":"venue"
},
  "geometry": {"coordinates":[-84.440592,33.679316],"type":"Point"}
}