{
  "type": "Feature",
  "properties": {
    "iso:country":"US",
    "sg:address":"27 State St",
    "sg:city":"Commerce",
    "sg:classifiers":[
        {
            "category":"Shopping",
            "type":"Retail Goods"
        }
    ],
    "sg:phone":"+1 706 335 7450",
    "sg:postcode":"30530",
    "sg:province":"GA",
    "sg:tags":[
        "durable",
        "merchandise"
    ],
    "wof:name":"Custom Awards & Signs",
    "wof:placetype":"venue"
},
  "geometry": {"coordinates":[-83.456648,34.203963],"type":"Point"}
}