{
  "type": "Feature",
  "properties": {
    "addr:full":"927 W Circle Dr Rossville GA 30741",
    "addr:housenumber":"927",
    "addr:postcode":"30741",
    "addr:street":"W Circle Dr",
    "iso:country":"US",
    "sg:address":"927 W Circle Dr",
    "sg:city":"Rossville",
    "sg:classifiers":[
        {
            "category":"Professional",
            "subcategory":"Business Services",
            "type":"Services"
        }
    ],
    "sg:phone":"+1 706 861 0756",
    "sg:postcode":"30741",
    "sg:province":"GA",
    "wof:name":"Stacy L Parson",
    "wof:placetype":"venue"
},
  "geometry": {"coordinates":[-85.322914,34.914054],"type":"Point"}
}