{
  "type": "Feature",
  "properties": {
    "addr:full":"1536 Dunwoody Village Pkw Atlanta GA 30338",
    "addr:housenumber":"1536",
    "addr:postcode":"30338",
    "addr:street":"Dunwoody Village",
    "iso:country":"US",
    "sg:address":"1536 Dunwoody Village Pkw",
    "sg:city":"Atlanta",
    "sg:classifiers":[
        {
            "category":"Professional",
            "subcategory":"Lawyer & Legal Services",
            "type":"Services"
        }
    ],
    "sg:phone":"+1 404 255 4442",
    "sg:postcode":"30338",
    "sg:province":"GA",
    "wof:name":"Farmer Hiers & De Veaux",
    "wof:placetype":"venue"
},
  "geometry": {"coordinates":[-84.33163500000001,33.947681],"type":"Point"}
}