{
  "type": "Feature",
  "properties": {
    "iso:country":"US",
    "sg:address":"933 N Ridge Dr",
    "sg:city":"Columbus",
    "sg:classifiers":[
        {
            "category":"Home & Garden",
            "subcategory":"Carpets & Floor Coverings",
            "type":"Retail Goods"
        }
    ],
    "sg:phone":"+1 706 321 0296",
    "sg:postcode":"31904",
    "sg:province":"GA",
    "wof:name":"Eagles Tile & Floor Covering",
    "wof:placetype":"venue"
},
  "geometry": {"coordinates":[-84.981511,32.555286],"type":"Point"}
}