{
  "type": "Feature",
  "properties": {
    "iso:country":"US",
    "sg:address":"7846 Chasewoods Dr",
    "sg:city":"Jonesboro",
    "sg:classifiers":[
        {
            "category":"Professional",
            "type":"Services"
        }
    ],
    "sg:phone":"+1 770 478 7472",
    "sg:postcode":"30236",
    "sg:province":"GA",
    "wof:name":"R Glass/Lynnett",
    "wof:placetype":"venue"
},
  "geometry": {"coordinates":[-84.381384,33.540894],"type":"Point"}
}