{
  "type": "Feature",
  "properties": {
    "iso:country":"US",
    "sg:address":"56 Hilliard St NE",
    "sg:city":"Atlanta",
    "sg:classifiers":[
        {
            "category":"Personal",
            "subcategory":"Barber",
            "type":"Services"
        }
    ],
    "sg:phone":"+1 404 523 9510",
    "sg:postcode":"30312",
    "sg:province":"GA",
    "sg:tags":[
        "shop"
    ],
    "wof:name":"Burden's Barber Shop",
    "wof:placetype":"venue"
},
  "geometry": {"coordinates":[-84.376503,33.755798],"type":"Point"}
}