{
  "type": "Feature",
  "properties": {
    "addr:full":"491 Supper Club Rd Dallas GA 30132",
    "addr:housenumber":"491",
    "addr:postcode":"30132",
    "addr:street":"Supper Club Rd",
    "iso:country":"US",
    "sg:address":"491 Supper Club Rd",
    "sg:city":"Dallas",
    "sg:classifiers":[
        {
            "category":"Building & Trades",
            "subcategory":"Construction",
            "type":"Services"
        }
    ],
    "sg:phone":"+1 770 445 4182",
    "sg:postcode":"30132",
    "sg:province":"GA",
    "sg:tags":[
        "roofing",
        "contractor"
    ],
    "wof:name":"A Bennett Roofing & Guttering",
    "wof:placetype":"venue"
},
  "geometry": {"coordinates":[-84.933212,33.942009],"type":"Point"}
}