{
  "type": "Feature",
  "properties": {
    "addr:full":"3620 Victory St Albany GA 31721",
    "addr:housenumber":"3620",
    "addr:postcode":"31721",
    "addr:street":"Victory St",
    "iso:country":"US",
    "sg:address":"3620 Victory St",
    "sg:city":"Albany",
    "sg:classifiers":[
        {
            "category":"Professional",
            "subcategory":"Computer Services",
            "type":"Services"
        }
    ],
    "sg:phone":"+1 229 888 2982",
    "sg:postcode":"31721",
    "sg:province":"GA",
    "sg:tags":[
        "information",
        "technology"
    ],
    "wof:name":"Robert Lee Perry",
    "wof:placetype":"venue"
},
  "geometry": {"coordinates":[-84.156182,31.50271],"type":"Point"}
}