{
  "type": "Feature",
  "properties": {
    "addr:full":"2665 Roswell Rd Marietta GA 30062",
    "addr:housenumber":"2665",
    "addr:postcode":"30062",
    "addr:street":"Roswell Rd",
    "iso:country":"US",
    "sg:address":"2665 Roswell Rd",
    "sg:city":"Marietta",
    "sg:classifiers":[
        {
            "category":"Professional",
            "subcategory":"Management & Consulting",
            "type":"Services"
        }
    ],
    "sg:phone":"+1 770 579 8759",
    "sg:postcode":"30062",
    "sg:province":"GA",
    "wof:name":"Sources Unlimited LLC",
    "wof:placetype":"venue"
},
  "geometry": {"coordinates":[-84.473208,33.975086],"type":"Point"}
}