{
  "type": "Feature",
  "properties": {
    "iso:country":"US",
    "sg:address":"208 Main St N",
    "sg:city":"Cornelia",
    "sg:classifiers":[
        {
            "category":"Personal",
            "subcategory":"Barber",
            "type":"Services"
        }
    ],
    "sg:phone":"+1 706 778 6975",
    "sg:postcode":"30531",
    "sg:province":"GA",
    "wof:name":"Daniel's Barber & Beauty Shop",
    "wof:placetype":"venue"
},
  "geometry": {"coordinates":[-83.52807,34.513632],"type":"Point"}
}