{
  "type": "Feature",
  "properties": {
    "addr:full":"1014 Sampler Way East Point GA 30344",
    "addr:housenumber":"1014",
    "addr:postcode":"30344",
    "addr:street":"Sampler Way",
    "iso:country":"US",
    "sg:address":"1014 Sampler Way",
    "sg:city":"East Point",
    "sg:classifiers":[
        {
            "category":"Wholesale",
            "subcategory":"Hardware",
            "type":"Manufacturing & Wholesale Goods"
        }
    ],
    "sg:phone":"+1 404 755 5775",
    "sg:postcode":"30344",
    "sg:province":"GA",
    "sg:tags":[
        "nut",
        "bolt"
    ],
    "wof:name":"Astro Bolt & Nut Co",
    "wof:placetype":"venue"
},
  "geometry": {"coordinates":[-84.42246799999999,33.695555],"type":"Point"}
}