{
  "type": "Feature",
  "properties": {
    "addr:full":"320 Northpoint Pkwy SE Acworth GA 30102",
    "addr:housenumber":"320",
    "addr:postcode":"30102",
    "addr:street":"Northpoint Pkwy Se",
    "iso:country":"US",
    "sg:address":"320 Northpoint Pkwy SE",
    "sg:city":"Acworth",
    "sg:classifiers":[
        {
            "category":"Manufacturing",
            "subcategory":"Tools & Machinery",
            "type":"Manufacturing & Wholesale Goods"
        }
    ],
    "sg:phone":"+1 770 529 1888",
    "sg:postcode":"30102",
    "sg:province":"GA",
    "sg:tags":[
        "assemble",
        "foam",
        "dispensing"
    ],
    "wof:name":"CCT Manufacturing Inc",
    "wof:placetype":"venue"
},
  "geometry": {"coordinates":[-84.666338,34.085578],"type":"Point"}
}