{
  "type": "Feature",
  "properties": {
    "iso:country":"US",
    "sg:address":"903 Huff Rd NW",
    "sg:city":"Atlanta",
    "sg:classifiers":[
        {
            "category":"Retail",
            "subcategory":"Auto Rental",
            "type":"Services"
        }
    ],
    "sg:phone":"+1 404 355 3093",
    "sg:postcode":"30318",
    "sg:province":"GA",
    "sg:tags":[
        "truck"
    ],
    "wof:name":"Lesco Truck Leasing",
    "wof:placetype":"venue"
},
  "geometry": {"coordinates":[-84.41743200000001,33.788669],"type":"Point"}
}