{
  "type": "Feature",
  "properties": {
    "addr:full":"1357 Michael Way Marietta GA 30062",
    "addr:housenumber":"1357",
    "addr:postcode":"30062",
    "addr:street":"Michael Way",
    "iso:country":"US",
    "sg:address":"1357 Michael Way",
    "sg:city":"Marietta",
    "sg:classifiers":[
        {
            "category":"Real Estate",
            "subcategory":"Developer",
            "type":"Services"
        }
    ],
    "sg:phone":"+1 404 392 3181",
    "sg:postcode":"30062",
    "sg:province":"GA",
    "wof:name":"Dirt Worx Land Developers Inc",
    "wof:placetype":"venue"
},
  "geometry": {"coordinates":[-84.43700200000001,33.983779],"type":"Point"}
}