{
  "type": "Feature",
  "properties": {
    "iso:country":"US",
    "sg:address":"796 Cannafax Rd",
    "sg:city":"Barnesville",
    "sg:classifiers":[
        {
            "category":"Personal",
            "subcategory":"Beauty Salon",
            "type":"Services"
        }
    ],
    "sg:phone":"+1 770 358 6210",
    "sg:postcode":"30204",
    "sg:province":"GA",
    "wof:name":"Sew Diva Inc",
    "wof:placetype":"venue"
},
  "geometry": {"coordinates":[-84.19617100000001,33.028564],"type":"Point"}
}