{
  "type": "Feature",
  "properties": {
    "addr:full":"2400 Lake Park Dr SE Smyrna GA 30080",
    "addr:housenumber":"2400",
    "addr:postcode":"30080",
    "addr:street":"Lake Park Dr Se",
    "iso:country":"US",
    "sg:address":"2400 Lake Park Dr SE",
    "sg:city":"Smyrna",
    "sg:classifiers":[
        {
            "category":"Professional",
            "subcategory":"Employment Agencies",
            "type":"Services"
        }
    ],
    "sg:phone":"+1 770 438 1177",
    "sg:postcode":"30080",
    "sg:province":"GA",
    "sg:tags":[
        "executive",
        "placement",
        "for"
    ],
    "wof:name":"Management Consultants Group",
    "wof:placetype":"venue"
},
  "geometry": {"coordinates":[-84.48177099999999,33.896809],"type":"Point"}
}