{
  "type": "Feature",
  "properties": {
    "addr:full":"125 Greenbriar Ct Savannah GA 31419",
    "addr:housenumber":"125",
    "addr:postcode":"31419",
    "addr:street":"Greenbriar Ct",
    "iso:country":"US",
    "sg:address":"125 Greenbriar Ct",
    "sg:city":"Savannah",
    "sg:classifiers":[
        {
            "category":"Professional",
            "type":"Services"
        }
    ],
    "sg:phone":"+1 912 961 5029",
    "sg:postcode":"31419",
    "sg:province":"GA",
    "wof:name":"Ronald Brantley",
    "wof:placetype":"venue"
},
  "geometry": {"coordinates":[-81.137579,31.963913],"type":"Point"}
}