{
  "type": "Feature",
  "properties": {
    "addr:full":"116 State Rte 61 Villa Rica GA 30180",
    "addr:housenumber":"116",
    "addr:postcode":"30180",
    "addr:street":"State Rte 61",
    "iso:country":"US",
    "sg:address":"116 State Rte 61",
    "sg:city":"Villa Rica",
    "sg:classifiers":[
        {
            "category":"Restaurant",
            "type":"Food & Drink"
        }
    ],
    "sg:phone":"+1 770 459 2128",
    "sg:postcode":"30180",
    "sg:province":"GA",
    "sg:website":"www.mcdonalds.com",
    "wof:name":"Mc Donald's",
    "wof:placetype":"venue"
},
  "geometry": {"coordinates":[-84.92259300000001,33.737025],"type":"Point"}
}