{
  "type": "Feature",
  "properties": {
    "addr:full":"835 S Chestatee St Dahlonega GA 30533",
    "addr:housenumber":"835",
    "addr:postcode":"30533",
    "addr:street":"S Chestatee St",
    "iso:country":"US",
    "sg:address":"835 S Chestatee St",
    "sg:city":"Dahlonega",
    "sg:classifiers":[
        {
            "category":"Real Estate",
            "subcategory":"Real Estate Agent",
            "type":"Services"
        }
    ],
    "sg:phone":"+1 706 864 7686",
    "sg:postcode":"30533",
    "sg:province":"GA",
    "wof:name":"S&R Properties",
    "wof:placetype":"venue"
},
  "geometry": {"coordinates":[-83.979326,34.526948],"type":"Point"}
}