{
  "type": "Feature",
  "properties": {
    "iso:country":"US",
    "sg:address":"129 Lucille Ave",
    "sg:city":"Ellijay",
    "sg:classifiers":[
        {
            "category":"Building & Trades",
            "subcategory":"Construction",
            "type":"Services"
        }
    ],
    "sg:phone":"+1 706 276 3396",
    "sg:postcode":"30540",
    "sg:province":"GA",
    "sg:tags":[
        "roofing",
        "contractor"
    ],
    "wof:name":"Award Roofing Enterprises",
    "wof:placetype":"venue"
},
  "geometry": {"coordinates":[-84.490109,34.696908],"type":"Point"}
}