{
  "type": "Feature",
  "properties": {
    "addr:full":"630 Turner Rd NE Rome GA 30165",
    "addr:housenumber":"630",
    "addr:postcode":"ga 30165",
    "addr:street":"Turner Rd Ne",
    "iso:country":"US",
    "sg:address":"630 Turner Rd NE",
    "sg:city":"Rome",
    "sg:classifiers":[
        {
            "category":"Professional",
            "type":"Services"
        }
    ],
    "sg:phone":"+1 706 291 0121",
    "sg:postcode":"30165",
    "sg:province":"GA",
    "wof:name":"Walter Butler",
    "wof:placetype":"venue"
},
  "geometry": {"coordinates":[-85.139455,34.401123],"type":"Point"}
}