{
  "type": "Feature",
  "properties": {
    "iso:country":"US",
    "sg:address":"104 Whitney Ct",
    "sg:city":"Mableton",
    "sg:classifiers":[
        {
            "category":"Building & Trades",
            "subcategory":"Landscaping Services",
            "type":"Services"
        }
    ],
    "sg:phone":"+1 678 478 9923",
    "sg:postcode":"30126",
    "sg:province":"GA",
    "sg:tags":[
        "landscape"
    ],
    "wof:name":"Casper Landscaping",
    "wof:placetype":"venue"
},
  "geometry": {"coordinates":[-84.53375699999999,33.788365],"type":"Point"}
}