{
  "type": "Feature",
  "properties": {
    "iso:country":"US",
    "sg:address":"1606 Kings Down Cir",
    "sg:city":"Atlanta",
    "sg:classifiers":[
        {
            "category":"Professional",
            "subcategory":"Employment Agencies",
            "type":"Services"
        }
    ],
    "sg:phone":"+1 770 396 5144",
    "sg:postcode":"30338",
    "sg:province":"GA",
    "wof:name":"Boger Carl F & Associate Inc",
    "wof:placetype":"venue"
},
  "geometry": {"coordinates":[-84.323212,33.930942],"type":"Point"}
}