{
  "type": "Feature",
  "properties": {
    "iso:country":"US",
    "sg:address":"251 Medical Way",
    "sg:city":"Atlanta",
    "sg:classifiers":[
        {
            "category":"Health Services",
            "subcategory":"Doctor",
            "type":"Services"
        }
    ],
    "sg:phone":"+1 770 991 2176",
    "sg:postcode":"30303",
    "sg:province":"GA",
    "sg:website":"www.southatlantapediatrics.com",
    "wof:name":"Thedford Victoria MD",
    "wof:placetype":"venue"
},
  "geometry": {"coordinates":[-84.38897,33.755418],"type":"Point"}
}