{
  "type": "Feature",
  "properties": {
    "iso:country":"US",
    "sg:address":"8005 US Hwy 80",
    "sg:city":"Savannah",
    "sg:classifiers":[
        {
            "category":"Marine",
            "type":"Transportation"
        }
    ],
    "sg:phone":"+1 912 898 8117",
    "sg:postcode":"31410",
    "sg:province":"GA",
    "sg:tags":[
        "surveyor"
    ],
    "wof:name":"M J Carter",
    "wof:placetype":"venue"
},
  "geometry": {"coordinates":[-80.964322,32.031837],"type":"Point"}
}