{
  "type": "Feature",
  "properties": {
    "iso:country":"US",
    "sg:address":"58 Park St SE",
    "sg:city":"Marietta",
    "sg:classifiers":[
        {
            "category":"Shopping",
            "subcategory":"Clothing, Apparel, & Fashions",
            "type":"Retail Goods"
        }
    ],
    "sg:phone":"+1 770 428 5313",
    "sg:postcode":"30060",
    "sg:province":"GA",
    "sg:tags":[
        "infant",
        "jean"
    ],
    "wof:name":"Goldsteins Inc",
    "wof:placetype":"venue"
},
  "geometry": {"coordinates":[-84.533255,33.949279],"type":"Point"}
}