{
  "type": "Feature",
  "properties": {
    "iso:country":"US",
    "sg:address":"305 S West St",
    "sg:city":"Bainbridge",
    "sg:classifiers":[
        {
            "category":"Health Services",
            "subcategory":"Chiropractor",
            "type":"Services"
        }
    ],
    "sg:phone":"+1 229 248 8499",
    "sg:postcode":"39819",
    "sg:province":"GA",
    "sg:tags":[
        "chiropractic"
    ],
    "wof:name":"Castoro, Peter DC",
    "wof:placetype":"venue"
},
  "geometry": {"coordinates":[-84.57648399999999,30.903976],"type":"Point"}
}