{
  "type": "Feature",
  "properties": {
    "addr:full":"102 Westchester Ln Athens GA 30606",
    "addr:housenumber":"102",
    "addr:postcode":"30606",
    "addr:street":"Westchester Ln",
    "iso:country":"US",
    "sg:address":"102 Westchester Ln",
    "sg:city":"Athens",
    "sg:classifiers":[
        {
            "category":"Freight",
            "type":"Transportation"
        },
        {
            "category":"Education",
            "subcategory":"Special Training",
            "type":"Public Place"
        }
    ],
    "sg:phone":"+1 706 548 5508",
    "sg:postcode":"30606",
    "sg:province":"GA",
    "sg:tags":[
        "operator",
        "local",
        "tutoring",
        "trucking"
    ],
    "wof:name":"Learning By Delivery",
    "wof:placetype":"venue"
},
  "geometry": {"coordinates":[-83.434603,33.961267],"type":"Point"}
}