{
  "type": "Feature",
  "properties": {
    "iso:country":"US",
    "sg:address":"5839 Memorial Dr",
    "sg:city":"Stone Mountain",
    "sg:classifiers":[
        {
            "category":"Education",
            "subcategory":"School",
            "type":"Public Place"
        }
    ],
    "sg:phone":"+1 678 676 1800",
    "sg:postcode":"30083",
    "sg:province":"GA",
    "sg:tags":[
        "high",
        "middle",
        "elementary"
    ],
    "wof:name":"East Campus",
    "wof:placetype":"venue"
},
  "geometry": {"coordinates":[-84.19956500000001,33.800034],"type":"Point"}
}