{
  "type": "Feature",
  "properties": {
    "addr:full":"385 George McClure Ln Cumming GA 30028",
    "addr:housenumber":"385",
    "addr:postcode":"30028",
    "addr:street":"George Mcclure Ln",
    "iso:country":"US",
    "sg:address":"385 George McClure Ln",
    "sg:city":"Cumming",
    "sg:classifiers":[
        {
            "category":"Freight",
            "type":"Transportation"
        }
    ],
    "sg:phone":"+1 770 888 9550",
    "sg:postcode":"30028",
    "sg:province":"GA",
    "sg:tags":[
        "operator",
        "local",
        "trucking"
    ],
    "wof:name":"Jtt Inc",
    "wof:placetype":"venue"
},
  "geometry": {"coordinates":[-84.280046,34.256885],"type":"Point"}
}