{
  "type": "Feature",
  "properties": {
    "iso:country":"US",
    "sg:address":"710 2nd St W",
    "sg:city":"Tifton",
    "sg:classifiers":[
        {
            "category":"Government",
            "subcategory":"Office",
            "type":"Public Place"
        }
    ],
    "sg:phone":"+1 229 386 3292",
    "sg:postcode":"31794",
    "sg:province":"GA",
    "sg:tags":[
        "state",
        "program"
    ],
    "sg:website":"www.dot.state.ga.us",
    "wof:name":"Transportation Dept-ROW",
    "wof:placetype":"venue"
},
  "geometry": {"coordinates":[-83.52246,31.457766],"type":"Point"}
}