{
  "type": "Feature",
  "properties": {
    "iso:country":"US",
    "sg:address":"1336 Mercantile Dr",
    "sg:city":"Albany",
    "sg:classifiers":[
        {
            "category":"Bars & Pubs",
            "type":"Food & Drink"
        }
    ],
    "sg:phone":"+1 229 446 4823",
    "sg:postcode":"31705",
    "sg:province":"GA",
    "sg:tags":[
        "drinking"
    ],
    "wof:name":"Topps Korner",
    "wof:placetype":"venue"
},
  "geometry": {"coordinates":[-84.12442799999999,31.554532],"type":"Point"}
}