{
  "type": "Feature",
  "properties": {
    "addr:full":"1806 Over Lake Dr SE Conyers GA 30013",
    "addr:housenumber":"1806",
    "addr:postcode":"30013",
    "addr:street":"Over Lake Dr Se",
    "iso:country":"US",
    "sg:address":"1806 Over Lake Dr SE",
    "sg:city":"Conyers",
    "sg:classifiers":[
        {
            "category":"Real Estate",
            "subcategory":"Real Estate Agent",
            "type":"Services"
        }
    ],
    "sg:phone":"+1 770 388 0077",
    "sg:postcode":"30013",
    "sg:province":"GA",
    "sg:tags":[
        "specializing",
        "residential",
        "property",
        "broker"
    ],
    "wof:name":"Better Homes and Gardens",
    "wof:placetype":"venue"
},
  "geometry": {"coordinates":[-84.009479,33.642313],"type":"Point"}
}