{
  "type": "Feature",
  "properties": {
    "addr:full":"760 Mt. Vernon Hwy Atlanta GA 30328",
    "addr:housenumber":"760",
    "addr:postcode":"30328",
    "addr:street":"Mt. Vernon Hwy",
    "iso:country":"US",
    "sg:address":"760 Mt. Vernon Hwy",
    "sg:city":"Atlanta",
    "sg:classifiers":[
        {
            "category":"Travel",
            "subcategory":"Hotels & Motels",
            "type":"Entertainment"
        },
        {
            "category":"Retail",
            "subcategory":"Event Space",
            "type":"Services"
        }
    ],
    "sg:phone":"+1 404 250 0110",
    "sg:postcode":"30328",
    "sg:province":"GA",
    "sg:tags":[
        "venue"
    ],
    "sg:website":"www.staybridge.com",
    "wof:name":"Staybridge Suites Atlanta Perimeter Center West",
    "wof:placetype":"venue"
},
  "geometry": {"coordinates":[-84.361918,33.929423],"type":"Point"}
}