{
  "type": "Feature",
  "properties": {
    "iso:country":"US",
    "sg:address":"441 Carole Dr",
    "sg:city":"Grovetown",
    "sg:classifiers":[
        {
            "category":"Building & Trades",
            "subcategory":"Construction",
            "type":"Services"
        }
    ],
    "sg:phone":"+1 706 231 3294",
    "sg:postcode":"30813",
    "sg:province":"GA",
    "sg:tags":[
        "metal",
        "installation",
        "fabrication",
        "sheet"
    ],
    "wof:name":"Jones Sheet Metal",
    "wof:placetype":"venue"
},
  "geometry": {"coordinates":[-82.288431,33.514435],"type":"Point"}
}