{
  "type": "Feature",
  "properties": {
    "addr:full":"1550 Chase Ct Riverdale GA 30296",
    "addr:housenumber":"1550",
    "addr:postcode":"30296",
    "addr:street":"Chase Ct",
    "iso:country":"US",
    "sg:address":"1550 Chase Ct",
    "sg:city":"Riverdale",
    "sg:classifiers":[
        {
            "category":"Wholesale",
            "subcategory":"Vending Machines",
            "type":"Manufacturing & Wholesale Goods"
        }
    ],
    "sg:phone":"+1 770 907 0256",
    "sg:postcode":"30296",
    "sg:province":"GA",
    "wof:name":"Two D's Muncheez",
    "wof:placetype":"venue"
},
  "geometry": {"coordinates":[-84.44044100000001,33.568167],"type":"Point"}
}