{
  "type": "Feature",
  "properties": {
    "addr:full":"155 Belmont Trce NW Atlanta GA 30328",
    "addr:housenumber":"155",
    "addr:postcode":"30328",
    "addr:street":"Belmont Trce Nw",
    "iso:country":"US",
    "sg:address":"155 Belmont Trce NW",
    "sg:city":"Atlanta",
    "sg:classifiers":[
        {
            "category":"Food & Beverages",
            "subcategory":"Liquor & Beverages",
            "type":"Retail Goods"
        }
    ],
    "sg:phone":"+1 404 250 9899",
    "sg:postcode":"30328",
    "sg:province":"GA",
    "sg:tags":[
        "product",
        "wine",
        "alcoholic",
        "mfg"
    ],
    "wof:name":"Olde World Wines Limited Inc",
    "wof:placetype":"venue"
},
  "geometry": {"coordinates":[-84.38767900000001,33.932469],"type":"Point"}
}