{
  "type": "Feature",
  "properties": {
    "iso:country":"US",
    "sg:address":"368 Wallace Gray Rd",
    "sg:city":"Newnan",
    "sg:classifiers":[
        {
            "category":"Retail",
            "subcategory":"Auto Repair",
            "type":"Services"
        }
    ],
    "sg:phone":"+1 770 253 7663",
    "sg:postcode":"30263",
    "sg:province":"GA",
    "sg:tags":[
        "repairing",
        "automobile",
        "general"
    ],
    "wof:name":"Stephens' Garage",
    "wof:placetype":"venue"
},
  "geometry": {"coordinates":[-84.844751,33.375784],"type":"Point"}
}