{
  "type": "Feature",
  "properties": {
    "iso:country":"US",
    "sg:address":"222 Forest Ln",
    "sg:city":"Washington",
    "sg:classifiers":[
        {
            "category":"Building & Trades",
            "subcategory":"Cleaning & Sanitation",
            "type":"Services"
        }
    ],
    "sg:phone":"+1 706 678 6966",
    "sg:postcode":"30673",
    "sg:province":"GA",
    "sg:tags":[
        "maintenance"
    ],
    "wof:name":"Double D Maintenance Inc",
    "wof:placetype":"venue"
},
  "geometry": {"coordinates":[-82.780135,33.750235],"type":"Point"}
}