{
  "type": "Feature",
  "properties": {
    "addr:full":"1605 Millen Hwy Sylvania GA 30467",
    "addr:housenumber":"1605",
    "addr:postcode":"30467",
    "addr:street":"Millen Hwy",
    "iso:country":"US",
    "sg:address":"1605 Millen Hwy",
    "sg:city":"Sylvania",
    "sg:classifiers":[
        {
            "category":"Recreation",
            "type":"Entertainment"
        }
    ],
    "sg:phone":"+1 912 863 2392",
    "sg:postcode":"30467",
    "sg:province":"GA",
    "sg:tags":[
        "parks"
    ],
    "wof:name":"Screven Co Bd Comm Rec Dept",
    "wof:placetype":"venue"
},
  "geometry": {"coordinates":[-81.65888099999999,32.76261],"type":"Point"}
}