{
  "type": "Feature",
  "properties": {
    "iso:country":"US",
    "sg:address":"274 Senoia Rd",
    "sg:city":"Fairburn",
    "sg:classifiers":[
        {
            "category":"Professional",
            "type":"Services"
        }
    ],
    "sg:phone":"+1 770 774 0292",
    "sg:postcode":"30213",
    "sg:province":"GA",
    "wof:name":"Tayo Reeds International Acade",
    "wof:placetype":"venue"
},
  "geometry": {"coordinates":[-84.582471,33.554377],"type":"Point"}
}