{
  "type": "Feature",
  "properties": {
    "iso:country":"US",
    "sg:address":"526 Village Ln",
    "sg:city":"Jonesboro",
    "sg:classifiers":[
        {
            "category":"Banks & Credit Unions",
            "subcategory":"Financial Services",
            "type":"Services"
        }
    ],
    "sg:phone":"+1 770 477 8491",
    "sg:postcode":"30236",
    "sg:province":"GA",
    "sg:tags":[
        "investor"
    ],
    "wof:name":"E C I N Inc",
    "wof:placetype":"venue"
},
  "geometry": {"coordinates":[-84.371404,33.56143],"type":"Point"}
}