{
  "type": "Feature",
  "properties": {
    "addr:full":"101 Fairview Rd Ellenwood GA 30294",
    "addr:housenumber":"101",
    "addr:postcode":"30294",
    "addr:street":"Fairview Rd",
    "iso:country":"US",
    "sg:address":"101 Fairview Rd",
    "sg:city":"Ellenwood",
    "sg:classifiers":[
        {
            "category":"Restaurant",
            "type":"Food & Drink"
        }
    ],
    "sg:phone":"+1 770 389 8989",
    "sg:postcode":"30294",
    "sg:province":"GA",
    "sg:tags":[
        "chinese"
    ],
    "wof:name":"Hunan Village 5 Inc",
    "wof:placetype":"venue"
},
  "geometry": {"coordinates":[-84.24570799999999,33.618578],"type":"Point"}
}