{
  "type": "Feature",
  "properties": {
    "addr:full":"1100 Gillionville Rd Albany GA 31707",
    "addr:housenumber":"1100",
    "addr:postcode":"31707",
    "addr:street":"Gillionville Rd",
    "iso:country":"US",
    "sg:address":"1100 Gillionville Rd",
    "sg:city":"Albany",
    "sg:classifiers":[
        {
            "category":"Banks & Credit Unions",
            "subcategory":"Bank",
            "type":"Services"
        }
    ],
    "sg:phone":"+1 229 430 5444",
    "sg:postcode":"31707",
    "sg:province":"GA",
    "sg:tags":[
        "national"
    ],
    "wof:name":"Sun Trust Bank",
    "wof:placetype":"venue"
},
  "geometry": {"coordinates":[-84.18711399999999,31.581086],"type":"Point"}
}