{
  "type": "Feature",
  "properties": {
    "addr:full":"4223 Tails Creek Rd Ellijay GA 30540",
    "addr:postcode":"4223;30540",
    "addr:street":"Tails Creek Rd",
    "iso:country":"US",
    "sg:address":"4223 Tails Creek Rd",
    "sg:city":"Ellijay",
    "sg:classifiers":[
        {
            "category":"Organizations",
            "subcategory":"Labor Organization",
            "type":"Services"
        }
    ],
    "sg:phone":"+1 706 276 1781",
    "sg:postcode":"30540",
    "sg:province":"GA",
    "wof:name":"Gilmer County Builders & Devel",
    "wof:placetype":"venue"
},
  "geometry": {"coordinates":[-84.53953799999999,34.7033],"type":"Point"}
}