{
  "type": "Feature",
  "properties": {
    "addr:full":"754 Woodson St SE Atlanta GA 30315",
    "addr:housenumber":"754",
    "addr:postcode":"30315",
    "addr:street":"Woodson St Se",
    "iso:country":"US",
    "sg:address":"754 Woodson St SE",
    "sg:city":"Atlanta",
    "sg:classifiers":[
        {
            "category":"Professional",
            "subcategory":"Management & Consulting",
            "type":"Services"
        }
    ],
    "sg:phone":"+1 404 622 4308",
    "sg:postcode":"30315",
    "sg:province":"GA",
    "sg:tags":[
        "consultant"
    ],
    "wof:name":"Henry Aaron",
    "wof:placetype":"venue"
},
  "geometry": {"coordinates":[-84.37921900000001,33.734064],"type":"Point"}
}