{
  "type": "Feature",
  "properties": {
    "addr:full":"101 Live Oak Ln NE Milledgeville GA 31061",
    "addr:housenumber":"101",
    "addr:postcode":"31061",
    "addr:street":"Live Oak Ln Ne",
    "iso:country":"US",
    "sg:address":"101 Live Oak Ln NE",
    "sg:city":"Milledgeville",
    "sg:classifiers":[
        {
            "category":"Building & Trades",
            "subcategory":"Construction",
            "type":"Services"
        }
    ],
    "sg:phone":"+1 478 452 1689",
    "sg:postcode":"31061",
    "sg:province":"GA",
    "sg:tags":[
        "house",
        "contractor"
    ],
    "wof:name":"TS Construction Co",
    "wof:placetype":"venue"
},
  "geometry": {"coordinates":[-83.251457,33.169738],"type":"Point"}
}