{
  "type": "Feature",
  "properties": {
    "iso:country":"US",
    "sg:address":"2487 Honey Creek Rd SW",
    "sg:city":"Conyers",
    "sg:classifiers":[
        {
            "category":"Professional",
            "subcategory":"Management & Consulting",
            "type":"Services"
        }
    ],
    "sg:phone":"+1 770 860 9060",
    "sg:postcode":"30094",
    "sg:province":"GA",
    "wof:name":"Mathis International",
    "wof:placetype":"venue"
},
  "geometry": {"coordinates":[-84.061554,33.595732],"type":"Point"}
}