{
  "type": "Feature",
  "properties": {
    "addr:full":"6035 Atlantic Blvd NW Norcross GA 30071",
    "addr:housenumber":"6035",
    "addr:postcode":"30071",
    "addr:street":"Atlantic Blvd Nw",
    "iso:country":"US",
    "sg:address":"6035 Atlantic Blvd NW",
    "sg:city":"Norcross",
    "sg:classifiers":[
        {
            "category":"Communications",
            "type":"Services"
        }
    ],
    "sg:phone":"+1 770 840 8440",
    "sg:postcode":"30071",
    "sg:province":"GA",
    "sg:tags":[
        "communication"
    ],
    "wof:name":"Trevick Communications Inc",
    "wof:placetype":"venue"
},
  "geometry": {"coordinates":[-84.228056,33.947262],"type":"Point"}
}