{
  "type": "Feature",
  "properties": {
    "addr:full":"1504 Fort View Ct Augusta GA 30909",
    "addr:housenumber":"1504",
    "addr:postcode":"30909",
    "addr:street":"Fort View Ct",
    "iso:country":"US",
    "sg:address":"1504 Fort View Ct",
    "sg:city":"Augusta",
    "sg:classifiers":[
        {
            "category":"Building & Trades",
            "subcategory":"Landscaping Services",
            "type":"Services"
        }
    ],
    "sg:phone":"+1 706 855 5088",
    "sg:postcode":"30909",
    "sg:province":"GA",
    "wof:name":"Lawn Manicurist",
    "wof:placetype":"venue"
},
  "geometry": {"coordinates":[-82.12332000000001,33.461549],"type":"Point"}
}