{
  "type": "Feature",
  "properties": {
    "iso:country":"US",
    "sg:address":"2900 Noble Ct",
    "sg:city":"Lawrenceville",
    "sg:classifiers":[
        {
            "category":"Real Estate",
            "subcategory":"Real Estate Agent",
            "type":"Services"
        }
    ],
    "sg:phone":"+1 770 717 2607",
    "sg:postcode":"30044",
    "sg:province":"GA",
    "sg:tags":[
        "investment"
    ],
    "wof:name":"Penvest Co",
    "wof:placetype":"venue"
},
  "geometry": {"coordinates":[-84.09429,33.940421],"type":"Point"}
}