{
  "type": "Feature",
  "properties": {
    "iso:country":"US",
    "sg:address":"135 Memorial Dr SW",
    "sg:city":"Atlanta",
    "sg:classifiers":[
        {
            "category":"Transit Center",
            "subcategory":"Freight",
            "type":"Transportation"
        },
        {
            "category":"Professional",
            "subcategory":"Advertising",
            "type":"Services"
        }
    ],
    "sg:phone":"+1 404 659 2472",
    "sg:postcode":"30303",
    "sg:province":"GA",
    "sg:tags":[
        "outdoor"
    ],
    "wof:name":"Whiteway Neon-Ad",
    "wof:placetype":"venue"
},
  "geometry": {"coordinates":[-84.391372,33.746912],"type":"Point"}
}