{
  "type": "Feature",
  "properties": {
    "iso:country":"US",
    "sg:address":"1734 Wingard Dr",
    "sg:city":"Marietta",
    "sg:classifiers":[
        {
            "category":"Social Services",
            "subcategory":"Adult Care",
            "type":"Services"
        }
    ],
    "sg:phone":"+1 678 560 8126",
    "sg:postcode":"30062",
    "sg:province":"GA",
    "sg:tags":[
        "foster"
    ],
    "wof:name":"Kids Of The King",
    "wof:placetype":"venue"
},
  "geometry": {"coordinates":[-84.504499,33.994103],"type":"Point"}
}