{
  "type": "Feature",
  "properties": {
    "addr:full":"3992 N Oak St Exd Valdosta GA 31605",
    "addr:housenumber":"3992",
    "addr:postcode":"31605",
    "addr:street":"N Oak St Exd",
    "iso:country":"US",
    "sg:address":"3992 N Oak St Exd",
    "sg:city":"Valdosta",
    "sg:classifiers":[
        {
            "category":"Education",
            "subcategory":"School",
            "type":"Public Place"
        }
    ],
    "sg:phone":"+1 229 244 6694",
    "sg:postcode":"31605",
    "sg:province":"GA",
    "wof:name":"Open Bible Christian School",
    "wof:placetype":"venue"
},
  "geometry": {"coordinates":[-83.284667,30.889964],"type":"Point"}
}