{
  "type": "Feature",
  "properties": {
    "iso:country":"US",
    "sg:address":"3435 Wrightsboro Rd",
    "sg:city":"Augusta",
    "sg:classifiers":[
        {
            "category":"Shopping",
            "type":"Retail Goods"
        }
    ],
    "sg:phone":"+1 706 736 2711",
    "sg:postcode":"30909",
    "sg:province":"GA",
    "sg:tags":[
        "item",
        "boutique"
    ],
    "wof:name":"De Luxe",
    "wof:placetype":"venue"
},
  "geometry": {"coordinates":[-82.07988,33.467499],"type":"Point"}
}