{
  "type": "Feature",
  "properties": {
    "iso:country":"US",
    "sg:address":"2803 S Main St",
    "sg:city":"Kennesaw",
    "sg:classifiers":[
        {
            "category":"Shopping",
            "subcategory":"Crafts & Fabrics",
            "type":"Retail Goods"
        }
    ],
    "sg:phone":"+1 770 421 1919",
    "sg:postcode":"30144",
    "sg:province":"GA",
    "sg:tags":[
        "art"
    ],
    "sg:website":"www.knittingemporium.com",
    "wof:name":"Kntting Emporium",
    "wof:placetype":"venue"
},
  "geometry": {"coordinates":[-84.615227,34.022689],"type":"Point"}
}