{
  "type": "Feature",
  "properties": {
    "iso:country":"US",
    "sg:address":"120 N Medical Pkwy",
    "sg:city":"Woodstock",
    "sg:classifiers":[
        {
            "category":"Health Services",
            "subcategory":"Doctor",
            "type":"Services"
        }
    ],
    "sg:phone":"+1 770 591 7929",
    "sg:postcode":"30189",
    "sg:province":"GA",
    "sg:tags":[
        "dentist"
    ],
    "sg:website":"www.beautifulsmiles-ga.com",
    "wof:name":"Towne Lake Family Dentistry",
    "wof:placetype":"venue"
},
  "geometry": {"coordinates":[-84.55124499999999,34.110536],"type":"Point"}
}