{
  "type": "Feature",
  "properties": {
    "iso:country":"US",
    "sg:address":"148 Carnes Rd SW",
    "sg:city":"Cartersville",
    "sg:classifiers":[
        {
            "category":"Freight",
            "type":"Transportation"
        }
    ],
    "sg:phone":"+1 770 606 9203",
    "sg:postcode":"30120",
    "sg:province":"GA",
    "sg:tags":[
        "operator",
        "local",
        "trucking"
    ],
    "wof:name":"Hammonds Hauling",
    "wof:placetype":"venue"
},
  "geometry": {"coordinates":[-84.855599,34.113644],"type":"Point"}
}