{
  "type": "Feature",
  "properties": {
    "iso:country":"US",
    "sg:address":"1840 State Rte 16",
    "sg:city":"Jackson",
    "sg:classifiers":[
        {
            "category":"Real Estate",
            "subcategory":"Real Estate Operator",
            "type":"Services"
        }
    ],
    "sg:phone":"+1 770 775 3845",
    "sg:postcode":"30233",
    "sg:province":"GA",
    "sg:tags":[
        "mobile",
        "home",
        "site"
    ],
    "wof:name":"Iron Springs Mobile Home Park",
    "wof:placetype":"venue"
},
  "geometry": {"coordinates":[-83.90975,33.288273],"type":"Point"}
}