{
  "type": "Feature",
  "properties": {
    "addr:full":"2812 Swamp Rd Waycross GA 31503",
    "addr:housenumber":"2812",
    "addr:postcode":"31503",
    "addr:street":"Swamp Rd",
    "iso:country":"US",
    "sg:address":"2812 Swamp Rd",
    "sg:city":"Waycross",
    "sg:classifiers":[
        {
            "category":"Personal",
            "subcategory":"Beauty Salon",
            "type":"Services"
        }
    ],
    "sg:phone":"+1 912 285 3945",
    "sg:postcode":"31503",
    "sg:province":"GA",
    "wof:name":"Carolyn's Beauty Shop",
    "wof:placetype":"venue"
},
  "geometry": {"coordinates":[-82.350149,31.173085],"type":"Point"}
}