{
  "type": "Feature",
  "properties": {
    "addr:full":"365 Villa Rica Way SW Marietta GA 30064",
    "addr:housenumber":"365",
    "addr:postcode":"30064",
    "addr:street":"Villa Rica Way Sw",
    "iso:country":"US",
    "sg:address":"365 Villa Rica Way SW",
    "sg:city":"Marietta",
    "sg:classifiers":[
        {
            "category":"Retail",
            "subcategory":"Veterinary Services",
            "type":"Services"
        }
    ],
    "sg:phone":"+1 770 528 6363",
    "sg:postcode":"30064",
    "sg:province":"GA",
    "sg:tags":[
        "veterinarian"
    ],
    "wof:name":"Town and Country Vet Clinic West",
    "wof:placetype":"venue"
},
  "geometry": {"coordinates":[-84.62190200000001,33.945202],"type":"Point"}
}