{
  "type": "Feature",
  "properties": {
    "addr:full":"5601 Story Rd Hiram GA 30141",
    "addr:housenumber":"5601",
    "addr:postcode":"30141",
    "addr:street":"Story Rd",
    "iso:country":"US",
    "sg:address":"5601 Story Rd",
    "sg:city":"Hiram",
    "sg:classifiers":[
        {
            "category":"Organizations",
            "subcategory":"Religious Organization",
            "type":"Services"
        }
    ],
    "sg:phone":"+1 770 943 1752",
    "sg:postcode":"30141",
    "sg:province":"GA",
    "sg:tags":[
        "church"
    ],
    "wof:name":"Revival Baptist Church",
    "wof:placetype":"venue"
},
  "geometry": {"coordinates":[-84.713121,33.862992],"type":"Point"}
}