{
  "type": "Feature",
  "properties": {
    "addr:full":"699 Echo St NW Atlanta GA 30318",
    "addr:housenumber":"699",
    "addr:postcode":"30318",
    "addr:street":"Echo St Nw",
    "iso:country":"US",
    "sg:address":"699 Echo St NW",
    "sg:city":"Atlanta",
    "sg:classifiers":[
        {
            "category":"Wholesale",
            "subcategory":"Auto Parts",
            "type":"Manufacturing & Wholesale Goods"
        }
    ],
    "sg:phone":"+1 404 875 7922",
    "sg:postcode":"30318",
    "sg:province":"GA",
    "sg:tags":[
        "automobile",
        "rebuilt",
        "used"
    ],
    "wof:name":"G F C Used Auto Parts",
    "wof:placetype":"venue"
},
  "geometry": {"coordinates":[-84.41034000000001,33.773459],"type":"Point"}
}