{
  "type": "Feature",
  "properties": {
    "addr:full":"351 Whaleys Lake Dr Jonesboro GA 30238",
    "addr:housenumber":"351",
    "addr:postcode":"30238",
    "addr:street":"Whaleys Lake Dr",
    "iso:country":"US",
    "sg:address":"351 Whaleys Lake Dr",
    "sg:city":"Jonesboro",
    "sg:classifiers":[
        {
            "category":"Sports & Exercise",
            "subcategory":"Bowling",
            "type":"Entertainment"
        }
    ],
    "sg:phone":"+1 770 210 9629",
    "sg:postcode":"30238",
    "sg:province":"GA",
    "sg:tags":[
        "center"
    ],
    "wof:name":"Paul Bowling",
    "wof:placetype":"venue"
},
  "geometry": {"coordinates":[-84.38000099999999,33.505488],"type":"Point"}
}