{
  "type": "Feature",
  "properties": {
    "addr:full":"1400 Indian Trl NW Atlanta GA 30327",
    "addr:housenumber":"1400",
    "addr:postcode":"30327",
    "addr:street":"Indian Trl Nw",
    "iso:country":"US",
    "sg:address":"1400 Indian Trl NW",
    "sg:city":"Atlanta",
    "sg:classifiers":[
        {
            "category":"Wholesale",
            "subcategory":"Machinery & Supplies",
            "type":"Manufacturing & Wholesale Goods"
        }
    ],
    "sg:phone":"+1 404 255 4382",
    "sg:postcode":"30327",
    "sg:province":"GA",
    "sg:tags":[
        "industrial",
        "machinery-new",
        "equipment",
        "used",
        "supplies-wholesale"
    ],
    "wof:name":"Morgan Chestnut Inc",
    "wof:placetype":"venue"
},
  "geometry": {"coordinates":[-84.43176,33.889068],"type":"Point"}
}