{
  "type": "Feature",
  "properties": {
    "addr:full":"1095 State St NW Atlanta GA 30318",
    "addr:housenumber":"1095",
    "addr:postcode":"30318",
    "addr:street":"State St Nw",
    "iso:country":"US",
    "sg:address":"1095 State St NW",
    "sg:city":"Atlanta",
    "sg:classifiers":[
        {
            "category":"Organizations",
            "subcategory":"Religious Organization",
            "type":"Services"
        }
    ],
    "sg:phone":"+1 404 874 9008",
    "sg:postcode":"30318",
    "sg:province":"GA",
    "sg:website":"www.westmerritts.org",
    "wof:name":"West Merritts Baptist Church",
    "wof:placetype":"venue"
},
  "geometry": {"coordinates":[-84.39869,33.785685],"type":"Point"}
}