{
  "type": "Feature",
  "properties": {
    "iso:country":"US",
    "sg:address":"3870 Hwy 124",
    "sg:city":"Snellville",
    "sg:classifiers":[
        {
            "category":"Retail",
            "subcategory":"Auto Repair",
            "type":"Services"
        }
    ],
    "sg:phone":"+1 770 978 8880",
    "sg:postcode":"30039",
    "sg:province":"GA",
    "sg:tags":[
        "body"
    ],
    "wof:name":"Prestige Cllision Gwinnett Inc",
    "wof:placetype":"venue"
},
  "geometry": {"coordinates":[-84.044128,33.789746],"type":"Point"}
}