{
  "type": "Feature",
  "properties": {
    "iso:country":"US",
    "sg:address":"1740 Hudson Bridge Rd",
    "sg:city":"Stockbridge",
    "sg:classifiers":[
        {
            "category":"Professional",
            "subcategory":"Business Services",
            "type":"Services"
        }
    ],
    "sg:phone":"+1 770 954 1622",
    "sg:postcode":"30281",
    "sg:province":"GA",
    "wof:name":"Dirt Dobbers",
    "wof:placetype":"venue"
},
  "geometry": {"coordinates":[-84.242231,33.502287],"type":"Point"}
}