{
  "type": "Feature",
  "properties": {
    "addr:full":"8751 Bellwood Ct Riverdale GA 30274",
    "addr:housenumber":"8751",
    "addr:postcode":"30274",
    "addr:street":"Bellwood Ct",
    "iso:country":"US",
    "sg:address":"8751 Bellwood Ct",
    "sg:city":"Riverdale",
    "sg:classifiers":[
        {
            "category":"Real Estate",
            "subcategory":"Architect",
            "type":"Services"
        }
    ],
    "sg:phone":"+1 770 210 2400",
    "sg:postcode":"30274",
    "sg:province":"GA",
    "sg:tags":[
        "home",
        "planning",
        "design"
    ],
    "wof:name":"Protexx Home Solutions",
    "wof:placetype":"venue"
},
  "geometry": {"coordinates":[-84.399001,33.517241],"type":"Point"}
}