{
  "type": "Feature",
  "properties": {
    "iso:country":"US",
    "sg:address":"651 Garden Walk Dr",
    "sg:city":"Stone Mountain",
    "sg:classifiers":[
        {
            "category":"Building & Trades",
            "subcategory":"Locksmith",
            "type":"Services"
        }
    ],
    "sg:phone":"+1 888 343 1508",
    "sg:postcode":"30083",
    "sg:province":"GA",
    "sg:tags":[
        "key"
    ],
    "wof:name":"1 & A Emergency Locksmith",
    "wof:placetype":"venue"
},
  "geometry": {"coordinates":[-84.18302300000001,33.795658],"type":"Point"}
}