{
  "type": "Feature",
  "properties": {
    "iso:country":"US",
    "sg:address":"2288 Flora Dr",
    "sg:city":"Marietta",
    "sg:classifiers":[
        {
            "category":"Building & Trades",
            "subcategory":"Construction",
            "type":"Services"
        }
    ],
    "sg:phone":"+1 770 289 4554",
    "sg:postcode":"30066",
    "sg:province":"GA",
    "sg:tags":[
        "contractor"
    ],
    "wof:name":"AJW Contracting",
    "wof:placetype":"venue"
},
  "geometry": {"coordinates":[-84.485214,34.028372],"type":"Point"}
}