{
  "type": "Feature",
  "properties": {
    "addr:full":"1488 Lavista Rd NE Atlanta GA 30324",
    "addr:housenumber":"1488",
    "addr:postcode":"30324",
    "addr:street":"Lavista Rd Ne",
    "iso:country":"US",
    "sg:address":"1488 Lavista Rd NE",
    "sg:city":"Atlanta",
    "sg:classifiers":[
        {
            "category":"Food & Beverages",
            "subcategory":"Supermarket",
            "type":"Retail Goods"
        }
    ],
    "sg:phone":"+1 404 320 6640",
    "sg:postcode":"30324",
    "sg:province":"GA",
    "sg:tags":[
        "super",
        "store"
    ],
    "wof:name":"Delicia Specialty Foods",
    "wof:placetype":"venue"
},
  "geometry": {"coordinates":[-84.33976199999999,33.814395],"type":"Point"}
}