{
  "type": "Feature",
  "properties": {
    "iso:country":"US",
    "sg:address":"810 Tift Ave N",
    "sg:city":"Tifton",
    "sg:classifiers":[
        {
            "category":"Organizations",
            "subcategory":"Professional Association",
            "type":"Services"
        }
    ],
    "sg:phone":"+1 229 386 4473",
    "sg:postcode":"31794",
    "sg:province":"GA",
    "sg:tags":[
        "business"
    ],
    "wof:name":"Talent Tree",
    "wof:placetype":"venue"
},
  "geometry": {"coordinates":[-83.50359,31.463672],"type":"Point"}
}