{
  "type": "Feature",
  "properties": {
    "addr:full":"515 S Scott St Bainbridge GA 39819",
    "addr:housenumber":"515",
    "addr:postcode":"39819",
    "addr:street":"S Scott St",
    "iso:country":"US",
    "sg:address":"515 S Scott St",
    "sg:city":"Bainbridge",
    "sg:classifiers":[
        {
            "category":"Banks & Credit Unions",
            "subcategory":"Bank",
            "type":"Services"
        }
    ],
    "sg:phone":"+1 229 246 3133",
    "sg:postcode":"39819",
    "sg:province":"GA",
    "sg:tags":[
        "small",
        "loan",
        "company",
        "financing",
        "mortgage"
    ],
    "wof:name":"Citi Financial",
    "wof:placetype":"venue"
},
  "geometry": {"coordinates":[-84.56782699999999,30.901838],"type":"Point"}
}