{
  "type": "Feature",
  "properties": {
    "addr:full":"105 Pine Cone Break Peachtree City GA 30269",
    "addr:housenumber":"105;break",
    "addr:postcode":"30269",
    "addr:street":"Pine Cone",
    "iso:country":"US",
    "sg:address":"105 Pine Cone Break",
    "sg:city":"Peachtree City",
    "sg:classifiers":[
        {
            "category":"Professional",
            "subcategory":"Business Services",
            "type":"Services"
        }
    ],
    "sg:phone":"+1 770 486 8447",
    "sg:postcode":"30269",
    "sg:province":"GA",
    "wof:name":"Cbc Business Svcs",
    "wof:placetype":"venue"
},
  "geometry": {"coordinates":[-84.57132799999999,33.401556],"type":"Point"}
}