{
  "type": "Feature",
  "properties": {
    "iso:country":"US",
    "sg:address":"5230 Centennial Hill Dr NW",
    "sg:city":"Acworth",
    "sg:classifiers":[
        {
            "category":"Health Services",
            "subcategory":"Doctor",
            "type":"Services"
        }
    ],
    "sg:phone":"+1 770 966 1696",
    "sg:postcode":"30102",
    "sg:province":"GA",
    "sg:tags":[
        "physician",
        "surgeon"
    ],
    "wof:name":"D.R. Horton, Inc.",
    "wof:placetype":"venue"
},
  "geometry": {"coordinates":[-84.61601899999999,34.076868],"type":"Point"}
}