{
  "type": "Feature",
  "properties": {
    "iso:country":"US",
    "sg:address":"995 Ivy Falls Dr NW",
    "sg:city":"Atlanta",
    "sg:classifiers":[
        {
            "category":"Health Services",
            "subcategory":"Doctor",
            "type":"Services"
        }
    ],
    "sg:phone":"+1 404 250 0993",
    "sg:postcode":"30328",
    "sg:province":"GA",
    "sg:tags":[
        "md",
        "professor",
        "on"
    ],
    "wof:name":"Mahlon R Delong",
    "wof:placetype":"venue"
},
  "geometry": {"coordinates":[-84.420018,33.922648],"type":"Point"}
}