{
  "type": "Feature",
  "properties": {
    "iso:country":"US",
    "sg:address":"807 Eisenhower Dr",
    "sg:city":"Augusta",
    "sg:classifiers":[
        {
            "category":"Shopping",
            "subcategory":"Bicycles & Sporting Goods",
            "type":"Retail Goods"
        }
    ],
    "sg:phone":"+1 706 737 4067",
    "sg:postcode":"30904",
    "sg:province":"GA",
    "sg:tags":[
        "equipment",
        "golf",
        "supply"
    ],
    "wof:name":"Augusta National Golf",
    "wof:placetype":"venue"
},
  "geometry": {"coordinates":[-82.015393,33.506797],"type":"Point"}
}