{
  "type": "Feature",
  "properties": {
    "addr:full":"2279 Connally Court Atlanta GA 30344",
    "addr:housenumber":"2279",
    "addr:postcode":"30344",
    "addr:street":"Connally Court",
    "iso:country":"US",
    "sg:address":"2279 Connally Court",
    "sg:city":"Atlanta",
    "sg:classifiers":[
        {
            "category":"Professional",
            "subcategory":"Lawyer & Legal Services",
            "type":"Services"
        }
    ],
    "sg:phone":"+1 404 349 2908",
    "sg:postcode":"30344",
    "sg:province":"GA",
    "wof:name":"Law Office of S Ralph Martin Jr",
    "wof:placetype":"venue"
},
  "geometry": {"coordinates":[-84.476052,33.693446],"type":"Point"}
}