{
  "type": "Feature",
  "properties": {
    "iso:country":"US",
    "sg:address":"12675 Providence Rd",
    "sg:city":"Alpharetta",
    "sg:classifiers":[
        {
            "category":"Place Of Worship",
            "subcategory":"Church",
            "type":"Public Place"
        },
        {
            "category":"Place Of Worship",
            "type":"Public Place"
        }
    ],
    "sg:phone":"+1 770 521 1229",
    "sg:postcode":"30009",
    "sg:province":"GA",
    "sg:tags":[
        "churches-baptist-general",
        "churches-baptist"
    ],
    "wof:name":"Christianity Construction Corp",
    "wof:placetype":"venue"
},
  "geometry": {"coordinates":[-84.30775800000001,34.090753],"type":"Point"}
}