{
  "type": "Feature",
  "properties": {
    "addr:full":"562 College St Macon GA 31201",
    "addr:housenumber":"562",
    "addr:postcode":"31201",
    "addr:street":"College St",
    "iso:country":"US",
    "sg:address":"562 College St",
    "sg:city":"Macon",
    "sg:classifiers":[
        {
            "category":"Professional",
            "subcategory":"Management & Consulting",
            "type":"Services"
        }
    ],
    "sg:phone":"+1 478 743 9184",
    "sg:postcode":"31201",
    "sg:province":"GA",
    "wof:name":"Robinson Management Services",
    "wof:placetype":"venue"
},
  "geometry": {"coordinates":[-83.639196,32.838678],"type":"Point"}
}