{
  "type": "Feature",
  "properties": {
    "addr:full":"3600 Preakness Dr Decatur GA 30034",
    "addr:housenumber":"3600",
    "addr:postcode":"30034",
    "addr:street":"Preakness Dr",
    "iso:country":"US",
    "sg:address":"3600 Preakness Dr",
    "sg:city":"Decatur",
    "sg:classifiers":[
        {
            "category":"Professional",
            "subcategory":"Management & Consulting",
            "type":"Services"
        }
    ],
    "sg:phone":"+1 404 289 6130",
    "sg:postcode":"30034",
    "sg:province":"GA",
    "sg:tags":[
        "drafting"
    ],
    "wof:name":"Entech Services Inc",
    "wof:placetype":"venue"
},
  "geometry": {"coordinates":[-84.24337199999999,33.699388],"type":"Point"}
}