{
  "type": "Feature",
  "properties": {
    "iso:country":"US",
    "sg:address":"1068 State Rte 36",
    "sg:city":"Jackson",
    "sg:classifiers":[
        {
            "category":"Building & Trades",
            "subcategory":"Construction",
            "type":"Services"
        }
    ],
    "sg:phone":"+1 770 775 2019",
    "sg:postcode":"30233",
    "sg:province":"GA",
    "sg:tags":[
        "excavation",
        "contractor"
    ],
    "wof:name":"Peek Lester Grading & Hauling",
    "wof:placetype":"venue"
},
  "geometry": {"coordinates":[-83.972255,33.281828],"type":"Point"}
}