{
  "type": "Feature",
  "properties": {
    "addr:full":"2177 Carlysle Creek Dr Lawrenceville GA 30044",
    "addr:housenumber":"2177",
    "addr:postcode":"30044",
    "addr:street":"Carlysle Creek Dr",
    "iso:country":"US",
    "sg:address":"2177 Carlysle Creek Dr",
    "sg:city":"Lawrenceville",
    "sg:classifiers":[
        {
            "category":"Organizations",
            "subcategory":"Religious Organization",
            "type":"Services"
        }
    ],
    "sg:phone":"+1 770 277 2111",
    "sg:postcode":"30044",
    "sg:province":"GA",
    "sg:tags":[
        "church"
    ],
    "wof:name":"Assist International Ministry",
    "wof:placetype":"venue"
},
  "geometry": {"coordinates":[-84.076255,33.951874],"type":"Point"}
}