{
  "type": "Feature",
  "properties": {
    "addr:full":"417 N Wilkinson St Milledgeville GA 31061",
    "addr:housenumber":"417",
    "addr:postcode":"31061",
    "addr:street":"N Wilkinson St",
    "iso:country":"US",
    "sg:address":"417 N Wilkinson St",
    "sg:city":"Milledgeville",
    "sg:classifiers":[
        {
            "category":"Insurance",
            "subcategory":"Insurance Agent",
            "type":"Services"
        }
    ],
    "sg:phone":"+1 478 414 7667",
    "sg:postcode":"31061",
    "sg:province":"GA",
    "wof:name":"Bakers Insurance",
    "wof:placetype":"venue"
},
  "geometry": {"coordinates":[-83.230268,33.086315],"type":"Point"}
}