{
  "type": "Feature",
  "properties": {
    "addr:full":"2535 Ivy St E Cumming GA 30041",
    "addr:housenumber":"2535",
    "addr:postcode":"30041",
    "addr:street":"Ivy St E",
    "iso:country":"US",
    "sg:address":"2535 Ivy St E",
    "sg:city":"Cumming",
    "sg:classifiers":[
        {
            "category":"Utilities",
            "subcategory":"Refuse",
            "type":"Services"
        },
        {
            "category":"Wholesale",
            "subcategory":"Scrap",
            "type":"Manufacturing & Wholesale Goods"
        }
    ],
    "sg:phone":"+1 770 205 6912",
    "sg:postcode":"30041",
    "sg:province":"GA",
    "sg:tags":[
        "recycling",
        "center",
        "system"
    ],
    "wof:name":"Olde Atlanta Recycling LLC",
    "wof:placetype":"venue"
},
  "geometry": {"coordinates":[-84.157647,34.161435],"type":"Point"}
}