{
  "type": "Feature",
  "properties": {
    "iso:country":"US",
    "sg:address":"1263 Augusta Rd",
    "sg:city":"North Augusta",
    "sg:classifiers":[
        {
            "category":"Restaurant",
            "type":"Food & Drink"
        }
    ],
    "sg:phone":"+1 803 663 7704",
    "sg:postcode":"29822",
    "sg:province":"SC",
    "sg:tags":[
        "eating"
    ],
    "wof:name":"TT&w Inc",
    "wof:placetype":"venue"
},
  "geometry": {"coordinates":[-81.89194000000001,33.496774],"type":"Point"}
}