{
  "type": "Feature",
  "properties": {
    "iso:country":"US",
    "sg:address":"290 Constitution Blvd",
    "sg:city":"Lawrenceville",
    "sg:classifiers":[
        {
            "category":"Social Services",
            "type":"Services"
        }
    ],
    "sg:phone":"+1 678 985 3141",
    "sg:postcode":"30045",
    "sg:province":"GA",
    "wof:name":"Aplhacare Christn Therapy Svcs",
    "wof:placetype":"venue"
},
  "geometry": {"coordinates":[-83.989417,33.943799],"type":"Point"}
}