{
  "type": "Feature",
  "properties": {
    "iso:country":"US",
    "sg:address":"115 W Main St",
    "sg:city":"Buford",
    "sg:classifiers":[
        {
            "category":"Social Services",
            "type":"Services"
        }
    ],
    "sg:phone":"+1 770 945 3074",
    "sg:postcode":"30518",
    "sg:province":"GA",
    "wof:name":"Buford Community Thrift Shop",
    "wof:placetype":"venue"
},
  "geometry": {"coordinates":[-84.008837,34.118376],"type":"Point"}
}