{
  "type": "Feature",
  "properties": {
    "iso:country":"US",
    "sg:address":"2040 Sunsweet Ct",
    "sg:city":"Lawrenceville",
    "sg:classifiers":[
        {
            "category":"Home & Garden",
            "subcategory":"Home Furnishings",
            "type":"Retail Goods"
        }
    ],
    "sg:phone":"+1 770 945 5375",
    "sg:postcode":"30043",
    "sg:province":"GA",
    "sg:tags":[
        "mirror"
    ],
    "wof:name":"Hunt Glass & Mirror",
    "wof:placetype":"venue"
},
  "geometry": {"coordinates":[-83.97914299999999,34.028067],"type":"Point"}
}