{
  "type": "Feature",
  "properties": {
    "addr:full":"6641 Green Island Dr Columbus GA 31904",
    "addr:housenumber":"6641",
    "addr:postcode":"31904",
    "addr:street":"Green Island Dr",
    "iso:country":"US",
    "sg:address":"6641 Green Island Dr",
    "sg:city":"Columbus",
    "sg:classifiers":[
        {
            "category":"Organizations",
            "subcategory":"Religious Organization",
            "type":"Services"
        }
    ],
    "sg:phone":"+1 706 323 5892",
    "sg:postcode":"31904",
    "sg:province":"GA",
    "wof:name":"Tabernacle AME Church",
    "wof:placetype":"venue"
},
  "geometry": {"coordinates":[-84.998188,32.543291],"type":"Point"}
}