{
  "type": "Feature",
  "properties": {
    "addr:full":"428 N Lake Dr Perry GA 31069",
    "addr:housenumber":"428",
    "addr:postcode":"31069",
    "addr:street":"N Lake Dr",
    "iso:country":"US",
    "sg:address":"428 N Lake Dr",
    "sg:city":"Perry",
    "sg:classifiers":[
        {
            "category":"Retail",
            "subcategory":"Repair Shop",
            "type":"Services"
        }
    ],
    "sg:phone":"+1 478 218 0290",
    "sg:postcode":"31069",
    "sg:province":"GA",
    "wof:name":"BJ Gallery and Framing",
    "wof:placetype":"venue"
},
  "geometry": {"coordinates":[-83.699777,32.519478],"type":"Point"}
}