{
  "type": "Feature",
  "properties": {
    "iso:country":"US",
    "sg:address":"980 Forest Park Ln",
    "sg:city":"Suwanee",
    "sg:classifiers":[
        {
            "category":"Building & Trades",
            "subcategory":"Construction",
            "type":"Services"
        }
    ],
    "sg:phone":"+1 770 527 4976",
    "sg:postcode":"30024",
    "sg:province":"GA",
    "sg:tags":[
        "contractor"
    ],
    "wof:name":"Rickye Contractors Inc",
    "wof:placetype":"venue"
},
  "geometry": {"coordinates":[-84.05032199999999,34.007222],"type":"Point"}
}