{
  "type": "Feature",
  "properties": {
    "addr:full":"2119 Azalea Dr Lawrenceville GA 30043",
    "addr:housenumber":"2119",
    "addr:postcode":"30043",
    "addr:street":"Azalea Dr",
    "iso:country":"US",
    "sg:address":"2119 Azalea Dr",
    "sg:city":"Lawrenceville",
    "sg:classifiers":[
        {
            "category":"Recreation",
            "type":"Entertainment"
        }
    ],
    "sg:phone":"+1 770 378 4310",
    "sg:postcode":"30043",
    "sg:province":"GA",
    "sg:tags":[
        "instruction",
        "golf"
    ],
    "wof:name":"Bob Cunningham's Golf Instr",
    "wof:placetype":"venue"
},
  "geometry": {"coordinates":[-83.991921,34.029792],"type":"Point"}
}