{
  "type": "Feature",
  "properties": {
    "iso:country":"US",
    "sg:address":"1306 Woodlawn Ave",
    "sg:city":"Tifton",
    "sg:classifiers":[
        {
            "category":"Recreation",
            "type":"Entertainment"
        }
    ],
    "sg:phone":"+1 229 386 0562",
    "sg:postcode":"31794",
    "sg:province":"GA",
    "sg:tags":[
        "drinking"
    ],
    "wof:name":"C-Way Pub",
    "wof:placetype":"venue"
},
  "geometry": {"coordinates":[-83.50578299999999,31.447307],"type":"Point"}
}