{
  "type": "Feature",
  "properties": {
    "addr:full":"3915 Snapfinger Pkwy Decatur GA 30035",
    "addr:housenumber":"3915",
    "addr:postcode":"30035",
    "addr:street":"Snapfinger Pkwy",
    "iso:country":"US",
    "sg:address":"3915 Snapfinger Pkwy",
    "sg:city":"Decatur",
    "sg:classifiers":[
        {
            "category":"Real Estate",
            "subcategory":"Real Estate Agent",
            "type":"Services"
        }
    ],
    "sg:phone":"+1 404 286 7792",
    "sg:postcode":"30035",
    "sg:province":"GA",
    "wof:name":"Friendship Foundation Inc",
    "wof:placetype":"venue"
},
  "geometry": {"coordinates":[-84.225148,33.71407],"type":"Point"}
}