{
  "type": "Feature",
  "properties": {
    "iso:country":"US",
    "sg:address":"601 7th St",
    "sg:city":"Augusta",
    "sg:classifiers":[
        {
            "category":"Professional",
            "subcategory":"Business Services",
            "type":"Services"
        }
    ],
    "sg:phone":"+1 706 722 3521",
    "sg:postcode":"30901",
    "sg:province":"GA",
    "sg:tags":[
        "convention",
        "meeting",
        "facility"
    ],
    "sg:website":"www.arccc.com",
    "wof:name":"Augusta-Richmond County Ctr",
    "wof:placetype":"venue"
},
  "geometry": {"coordinates":[-81.96692299999999,33.467528],"type":"Point"}
}