{
  "type": "Feature",
  "properties": {
    "addr:full":"111 Sycamore St Decatur GA 30030",
    "addr:housenumber":"111",
    "addr:postcode":"30030",
    "addr:street":"Sycamore St",
    "iso:country":"US",
    "sg:address":"111 Sycamore St",
    "sg:city":"Decatur",
    "sg:classifiers":[
        {
            "category":"Restaurant",
            "type":"Food & Drink"
        }
    ],
    "sg:phone":"+1 404 377 8050",
    "sg:postcode":"30030",
    "sg:province":"GA",
    "sg:tags":[
        "irish"
    ],
    "sg:website":"macmcgeeirishpub.com",
    "wof:name":"Mac McGee's",
    "wof:placetype":"venue"
},
  "geometry": {"coordinates":[-84.295682,33.77459],"type":"Point"}
}