{
  "type": "Feature",
  "properties": {
    "addr:full":"3506 Cresthill Ave Macon GA 31204",
    "addr:housenumber":"3506",
    "addr:postcode":"31204",
    "addr:street":"Cresthill Ave",
    "iso:country":"US",
    "sg:address":"3506 Cresthill Ave",
    "sg:city":"Macon",
    "sg:classifiers":[
        {
            "category":"Personal",
            "subcategory":"Beauty Salon",
            "type":"Services"
        }
    ],
    "sg:phone":"+1 478 471 9600",
    "sg:postcode":"31204",
    "sg:province":"GA",
    "sg:tags":[
        "manicuring"
    ],
    "wof:name":"Ailene V Williams Nailcare",
    "wof:placetype":"venue"
},
  "geometry": {"coordinates":[-83.69004,32.845211],"type":"Point"}
}