{
  "type": "Feature",
  "properties": {
    "addr:full":"2972 Alabama Hwy Rome GA 30165",
    "addr:housenumber":"2972",
    "addr:postcode":"ga 30165",
    "addr:street":"Alabama Hwy",
    "iso:country":"US",
    "sg:address":"2972 Alabama Hwy",
    "sg:city":"Rome",
    "sg:classifiers":[
        {
            "category":"Organizations",
            "subcategory":"Religious Organization",
            "type":"Services"
        }
    ],
    "sg:phone":"+1 706 235 4973",
    "sg:postcode":"30165",
    "sg:province":"GA",
    "sg:tags":[
        "church"
    ],
    "wof:name":"Beech Creek United Methodist",
    "wof:placetype":"venue"
},
  "geometry": {"coordinates":[-85.252019,34.271018],"type":"Point"}
}