{
  "type": "Feature",
  "properties": {
    "iso:country":"US",
    "sg:address":"1950 Spectrum Cir",
    "sg:city":"Marietta",
    "sg:classifiers":[
        {
            "category":"Banks & Credit Unions",
            "subcategory":"Bank",
            "type":"Services"
        }
    ],
    "sg:phone":"+1 770 850 2555",
    "sg:postcode":"30067",
    "sg:province":"GA",
    "sg:tags":[
        "mortgage",
        "show",
        "loan",
        "host",
        "banker",
        "real estate",
        "talk"
    ],
    "sg:website":"www.banksecrets.com",
    "wof:name":"Bankers Secrets Inc",
    "wof:placetype":"venue"
},
  "geometry": {"coordinates":[-84.468422,33.905372],"type":"Point"}
}