{
  "type": "Feature",
  "properties": {
    "iso:country":"US",
    "sg:address":"816 S Thornton Ave",
    "sg:city":"Dalton",
    "sg:classifiers":[
        {
            "category":"Professional",
            "subcategory":"Accounting & Tax Preparation",
            "type":"Services"
        }
    ],
    "sg:phone":"+1 706 370 7317",
    "sg:postcode":"30720",
    "sg:province":"GA",
    "sg:tags":[
        "return",
        "filing"
    ],
    "wof:name":"Brock Tax Svc",
    "wof:placetype":"venue"
},
  "geometry": {"coordinates":[-84.971729,34.764738],"type":"Point"}
}