{
  "type": "Feature",
  "properties": {
    "iso:country":"US",
    "sg:address":"844 Terry White Rd",
    "sg:city":"Aragon",
    "sg:classifiers":[
        {
            "category":"Professional",
            "subcategory":"Advertising",
            "type":"Services"
        }
    ],
    "sg:phone":"+1 770 684 5090",
    "sg:postcode":"30104",
    "sg:province":"GA",
    "sg:tags":[
        "agency"
    ],
    "wof:name":"Ls Advertising and Graphics",
    "wof:placetype":"venue"
},
  "geometry": {"coordinates":[-85.109033,34.073284],"type":"Point"}
}