{
  "type": "Feature",
  "properties": {
    "addr:full":"8977 Woodsong Trl Cumming GA 30041",
    "addr:housenumber":"8977",
    "addr:postcode":"30041",
    "addr:street":"Woodsong Trl",
    "iso:country":"US",
    "sg:address":"8977 Woodsong Trl",
    "sg:city":"Cumming",
    "sg:classifiers":[
        {
            "category":"Building & Trades",
            "subcategory":"Construction",
            "type":"Services"
        }
    ],
    "sg:phone":"+1 770 887 6455",
    "sg:postcode":"30041",
    "sg:province":"GA",
    "sg:tags":[
        "house",
        "builder",
        "operative"
    ],
    "wof:name":"Ronald Thompson Inc",
    "wof:placetype":"venue"
},
  "geometry": {"coordinates":[-84.163827,34.142082],"type":"Point"}
}