{
  "type": "Feature",
  "properties": {
    "iso:country":"US",
    "sg:address":"1462 Senator Rd",
    "sg:city":"Douglasville",
    "sg:classifiers":[
        {
            "category":"Building & Trades",
            "subcategory":"Construction",
            "type":"Services"
        }
    ],
    "sg:phone":"+1 770 942 8637",
    "sg:postcode":"30134",
    "sg:province":"GA",
    "sg:tags":[
        "house"
    ],
    "wof:name":"Donny A Pace Construction",
    "wof:placetype":"venue"
},
  "geometry": {"coordinates":[-84.809155,33.796873],"type":"Point"}
}