{
  "type": "Feature",
  "properties": {
    "iso:country":"US",
    "sg:address":"1150 Main St",
    "sg:city":"Whitesburg",
    "sg:classifiers":[
        {
            "category":"Restaurant",
            "type":"Food & Drink"
        }
    ],
    "sg:phone":"+1 770 830 7900",
    "sg:postcode":"30185",
    "sg:province":"GA",
    "wof:name":"Kay's Cafe",
    "wof:placetype":"venue"
},
  "geometry": {"coordinates":[-84.922394,33.503761],"type":"Point"}
}