{
  "type": "Feature",
  "properties": {
    "addr:full":"5607 Glenridge Dr NE Atlanta GA 30342",
    "addr:housenumber":"5607",
    "addr:postcode":"30342",
    "addr:street":"Glenridge Dr Ne",
    "iso:country":"US",
    "sg:address":"5607 Glenridge Dr NE",
    "sg:city":"Atlanta",
    "sg:classifiers":[
        {
            "category":"Professional",
            "subcategory":"Employment Agencies",
            "type":"Services"
        }
    ],
    "sg:phone":"+1 404 303 4985",
    "sg:postcode":"30342",
    "sg:province":"GA",
    "sg:tags":[
        "opportunity"
    ],
    "sg:website":"www.firstproinc.com",
    "wof:name":"Firstpro INC",
    "wof:placetype":"venue"
},
  "geometry": {"coordinates":[-84.36367799999999,33.907293],"type":"Point"}
}