{
  "type": "Feature",
  "properties": {
    "addr:full":"9480 Cain Cir Gainesville GA 30506",
    "addr:housenumber":"9480",
    "addr:postcode":"30506",
    "addr:street":"Cain Cir",
    "iso:country":"US",
    "sg:address":"9480 Cain Cir",
    "sg:city":"Gainesville",
    "sg:classifiers":[
        {
            "category":"Autos & Motor Vehicles",
            "subcategory":"Motorcycle Sales",
            "type":"Retail Goods"
        }
    ],
    "sg:phone":"+1 770 889 3882",
    "sg:postcode":"30506",
    "sg:province":"GA",
    "wof:name":"Mountain Thunder Cycles Inc",
    "wof:placetype":"venue"
},
  "geometry": {"coordinates":[-83.983437,34.245363],"type":"Point"}
}