{
  "type": "Feature",
  "properties": {
    "iso:country":"US",
    "sg:address":"2707 Watson Blvd",
    "sg:city":"Warner Robins",
    "sg:classifiers":[
        {
            "category":"Restaurant",
            "type":"Food & Drink"
        }
    ],
    "sg:phone":"+1 478 929 1800",
    "sg:postcode":"31093",
    "sg:province":"GA",
    "sg:tags":[
        "italian"
    ],
    "sg:website":"www.carinos.com/default.aspx",
    "wof:name":"Carino's Italian",
    "wof:placetype":"venue"
},
  "geometry": {"coordinates":[-83.669381,32.618302],"type":"Point"}
}