{
  "type": "Feature",
  "properties": {
    "iso:country":"US",
    "sg:address":"301 Eagles Landing Pkwy",
    "sg:city":"Stockbridge",
    "sg:classifiers":[
        {
            "category":"Professional",
            "type":"Services"
        }
    ],
    "sg:phone":"+1 770 389 6300",
    "sg:postcode":"30281",
    "sg:province":"GA",
    "wof:name":"William Carter Co",
    "wof:placetype":"venue"
},
  "geometry": {"coordinates":[-84.195654,33.518309],"type":"Point"}
}