{
  "type": "Feature",
  "properties": {
    "addr:full":"119 Sycamore Dr Athens GA 30606",
    "addr:housenumber":"119",
    "addr:postcode":"30606",
    "addr:street":"Sycamore Dr",
    "iso:country":"US",
    "sg:address":"119 Sycamore Dr",
    "sg:city":"Athens",
    "sg:classifiers":[
        {
            "category":"Real Estate",
            "subcategory":"Real Estate Operator",
            "type":"Services"
        }
    ],
    "sg:phone":"+1 706 548 7571",
    "sg:postcode":"30606",
    "sg:province":"GA",
    "sg:tags":[
        "managing",
        "apartment"
    ],
    "wof:name":"Wimberly & Daniel Properties",
    "wof:placetype":"venue"
},
  "geometry": {"coordinates":[-83.418043,33.947206],"type":"Point"}
}