{
  "type": "Feature",
  "properties": {
    "addr:full":"1881 Kerry Creek Dr Marietta GA 30066",
    "addr:housenumber":"1881",
    "addr:postcode":"30066",
    "addr:street":"Kerry Creek Dr",
    "iso:country":"US",
    "sg:address":"1881 Kerry Creek Dr",
    "sg:city":"Marietta",
    "sg:classifiers":[
        {
            "category":"Building & Trades",
            "subcategory":"Cleaning & Sanitation",
            "type":"Services"
        }
    ],
    "sg:phone":"+1 770 565 2130",
    "sg:postcode":"30066",
    "sg:province":"GA",
    "sg:tags":[
        "maintenance"
    ],
    "wof:name":"Harrison Cleaning Svc Inc",
    "wof:placetype":"venue"
},
  "geometry": {"coordinates":[-84.49404699999999,34.021757],"type":"Point"}
}