{
  "type": "Feature",
  "properties": {
    "addr:full":"1618 N Lee St Valdosta GA 31602",
    "addr:housenumber":"1618",
    "addr:postcode":"31602",
    "addr:street":"N Lee St",
    "iso:country":"US",
    "sg:address":"1618 N Lee St",
    "sg:city":"Valdosta",
    "sg:classifiers":[
        {
            "category":"Shopping",
            "subcategory":"Clothing, Apparel, & Fashions",
            "type":"Retail Goods"
        }
    ],
    "sg:phone":"+1 229 242 6693",
    "sg:postcode":"31602",
    "sg:province":"GA",
    "sg:tags":[
        "dance"
    ],
    "wof:name":"Gerlock Dance Studio",
    "wof:placetype":"venue"
},
  "geometry": {"coordinates":[-83.278395,30.851511],"type":"Point"}
}