{
  "type": "Feature",
  "properties": {
    "iso:country":"US",
    "sg:address":"210 Townpark Dr NW",
    "sg:city":"Kennesaw",
    "sg:classifiers":[
        {
            "category":"Home & Garden",
            "subcategory":"Carpets & Floor Coverings",
            "type":"Retail Goods"
        }
    ],
    "sg:phone":"+1 727 397 5070",
    "sg:postcode":"30144",
    "sg:province":"GA",
    "sg:tags":[
        "carpeting"
    ],
    "wof:name":"Flooring America",
    "wof:placetype":"venue"
},
  "geometry": {"coordinates":[-84.566002,34.038898],"type":"Point"}
}