{
  "type": "Feature",
  "properties": {
    "addr:full":"14 W De Renne Ave Savannah GA 31405",
    "addr:housenumber":"14",
    "addr:postcode":"31405",
    "addr:street":"W De Renne Ave",
    "iso:country":"US",
    "sg:address":"14 W De Renne Ave",
    "sg:city":"Savannah",
    "sg:classifiers":[
        {
            "category":"Restaurant",
            "type":"Food & Drink"
        }
    ],
    "sg:menulink":"http://www.allmenus.com/ga/savannah/160533-burger-king/menu/",
    "sg:phone":"+1 912 352 2514",
    "sg:postcode":"31405",
    "sg:province":"GA",
    "sg:tags":[
        "burger",
        "american"
    ],
    "wof:name":"Burger King",
    "wof:placetype":"venue"
},
  "geometry": {"coordinates":[-81.111757,32.029199],"type":"Point"}
}