{
  "type": "Feature",
  "properties": {
    "iso:country":"US",
    "sg:address":"215 Monroe Dr",
    "sg:city":"Mc Donough",
    "sg:classifiers":[
        {
            "category":"Shopping",
            "subcategory":"Gifts & Souvenirs",
            "type":"Retail Goods"
        }
    ],
    "sg:phone":"+1 770 914 7731",
    "sg:postcode":"30252",
    "sg:province":"GA",
    "wof:name":"Hardegree Gift & Jewelry",
    "wof:placetype":"venue"
},
  "geometry": {"coordinates":[-84.06678700000001,33.453569],"type":"Point"}
}