{
  "type": "Feature",
  "properties": {
    "addr:full":"304 N Mcdonough St Decatur GA 30030",
    "addr:housenumber":"304",
    "addr:postcode":"30030",
    "addr:street":"N Mcdonough St",
    "iso:country":"US",
    "sg:address":"304 N Mcdonough St",
    "sg:city":"Decatur",
    "sg:classifiers":[
        {
            "category":"Building & Trades",
            "subcategory":"Locksmith",
            "type":"Services"
        }
    ],
    "sg:phone":"+1 404 492 9014",
    "sg:postcode":"30030",
    "sg:province":"GA",
    "sg:tags":[
        "key"
    ],
    "sg:website":"www.locksmithindecatur.com/",
    "wof:name":"24 Hour Locksmith Of Decatur",
    "wof:placetype":"venue"
},
  "geometry": {"coordinates":[-84.29656199999999,33.773458],"type":"Point"}
}