{
  "type": "Feature",
  "properties": {
    "iso:country":"US",
    "sg:address":"313 Lawrence St NE",
    "sg:city":"Marietta",
    "sg:classifiers":[
        {
            "category":"Professional",
            "subcategory":"Lawyer & Legal Services",
            "type":"Services"
        }
    ],
    "sg:phone":"+1 770 427 9481",
    "sg:postcode":"30060",
    "sg:province":"GA",
    "sg:tags":[
        "practice",
        "attorney",
        "criminal",
        "law"
    ],
    "wof:name":"Ivester J Fred",
    "wof:placetype":"venue"
},
  "geometry": {"coordinates":[-84.543284,33.953128],"type":"Point"}
}