{
  "type": "Feature",
  "properties": {
    "iso:country":"US",
    "sg:address":"4773 Cherie Glen Ct",
    "sg:city":"Stone Mountain",
    "sg:classifiers":[
        {
            "category":"Real Estate",
            "subcategory":"Real Estate Agent",
            "type":"Services"
        }
    ],
    "sg:phone":"+1 404 294 0947",
    "sg:postcode":"30083",
    "sg:province":"GA",
    "wof:name":"Eagle Dawg Properties Inc",
    "wof:placetype":"venue"
},
  "geometry": {"coordinates":[-84.200768,33.8142],"type":"Point"}
}