{
  "type": "Feature",
  "properties": {
    "iso:country":"US",
    "sg:address":"1329 Sugarwood Ln",
    "sg:city":"Norcross",
    "sg:classifiers":[
        {
            "category":"Restaurant",
            "type":"Food & Drink"
        }
    ],
    "sg:phone":"+1 770 921 3899",
    "sg:postcode":"30093",
    "sg:province":"GA",
    "sg:tags":[
        "eating"
    ],
    "wof:name":"Vickery Creek Restaurant",
    "wof:placetype":"venue"
},
  "geometry": {"coordinates":[-84.168402,33.916076],"type":"Point"}
}