{
  "type": "Feature",
  "properties": {
    "iso:country":"US",
    "sg:address":"107 Church St NE",
    "sg:city":"Marietta",
    "sg:classifiers":[
        {
            "category":"Food & Beverages",
            "subcategory":"Specialty",
            "type":"Retail Goods"
        }
    ],
    "sg:phone":"+1 678 355 1733",
    "sg:postcode":"30060",
    "sg:province":"GA",
    "sg:website":"www.murphyspopcorn.com",
    "wof:name":"Murphy's Gourment Popcorn Store",
    "wof:placetype":"venue"
},
  "geometry": {"coordinates":[-84.550196,33.954043],"type":"Point"}
}