{
  "type": "Feature",
  "properties": {
    "iso:country":"US",
    "sg:address":"310 Johnson Ter",
    "sg:city":"Covington",
    "sg:classifiers":[
        {
            "category":"Building & Trades",
            "subcategory":"Plumbing",
            "type":"Services"
        }
    ],
    "sg:phone":"+1 770 787 2672",
    "sg:postcode":"30014",
    "sg:province":"GA",
    "sg:tags":[
        "contractor"
    ],
    "wof:name":"Purcell Plumbing",
    "wof:placetype":"venue"
},
  "geometry": {"coordinates":[-83.843637,33.495319],"type":"Point"}
}