{
  "type": "Feature",
  "properties": {
    "iso:country":"US",
    "sg:address":"1303 Scruggs Rd",
    "sg:city":"Ringgold",
    "sg:classifiers":[
        {
            "category":"Autos & Motor Vehicles",
            "subcategory":"Automobile Sales",
            "type":"Retail Goods"
        }
    ],
    "sg:phone":"+1 706 956 8256",
    "sg:postcode":"30736",
    "sg:province":"GA",
    "sg:tags":[
        "used",
        "auction",
        "car",
        "dealers-used",
        "cars-wholesale"
    ],
    "wof:name":"The New Tn Ga Auto Auctio",
    "wof:placetype":"venue"
},
  "geometry": {"coordinates":[-85.193575,34.965852],"type":"Point"}
}