{
  "type": "Feature",
  "properties": {
    "addr:full":"1132 Canton St Roswell GA 30075",
    "addr:housenumber":"1132",
    "addr:postcode":"30075",
    "addr:street":"Canton St",
    "iso:country":"US",
    "sg:address":"1132 Canton St",
    "sg:city":"Roswell",
    "sg:classifiers":[
        {
            "category":"Restaurant",
            "type":"Food & Drink"
        }
    ],
    "sg:phone":"+1 770 817 0202",
    "sg:postcode":"30075",
    "sg:province":"GA",
    "sg:website":"www.tasteofroswell.com",
    "wof:name":"Taste Restaurant & Bar",
    "wof:placetype":"venue"
},
  "geometry": {"coordinates":[-84.361851,34.029547],"type":"Point"}
}