{
  "type": "Feature",
  "properties": {
    "iso:country":"US",
    "sg:address":"5667 Stagecoach Rd",
    "sg:city":"Rex",
    "sg:classifiers":[
        {
            "category":"Manufacturing",
            "subcategory":"Aerospace",
            "type":"Manufacturing & Wholesale Goods"
        }
    ],
    "sg:phone":"+1 770 506 9487",
    "sg:postcode":"30273",
    "sg:province":"GA",
    "sg:tags":[
        "semi",
        "for",
        "mfg",
        "landing",
        "aircraft",
        "robotic",
        "changer",
        "gear"
    ],
    "wof:name":"D-Check Developments Inc",
    "wof:placetype":"venue"
},
  "geometry": {"coordinates":[-84.26181099999999,33.600242],"type":"Point"}
}