{
  "type": "Feature",
  "properties": {
    "addr:full":"3020 Business Park Drive, Suite A Norcross GA 30071",
    "addr:housenumber":"3020",
    "addr:postcode":"30071",
    "addr:street":"Business Park Drive Suite A",
    "iso:country":"US",
    "sg:address":"3020 Business Park Drive, Suite A",
    "sg:city":"Norcross",
    "sg:classifiers":[
        {
            "category":"Professional",
            "subcategory":"Business Services",
            "type":"Services"
        },
        {
            "category":"Manufacturing",
            "subcategory":"Signs",
            "type":"Manufacturing & Wholesale Goods"
        },
        {
            "category":"Home & Garden",
            "subcategory":"Carpets & Floor Coverings",
            "type":"Retail Goods"
        }
    ],
    "sg:phone":"+1 770 447 9498",
    "sg:postcode":"30071",
    "sg:province":"GA",
    "sg:tags":[
        "hanger",
        "flooring",
        "labeling",
        "contractor",
        "signs-erectors"
    ],
    "sg:website":"http://www.asgservices.com",
    "wof:name":"ASG Services, LLC",
    "wof:placetype":"venue"
},
  "geometry": {"coordinates":[-84.208967,33.954917],"type":"Point"}
}