{
  "type": "Feature",
  "properties": {
    "iso:country":"US",
    "sg:address":"309 N 6th Ave",
    "sg:city":"Chatsworth",
    "sg:classifiers":[
        {
            "category":"Real Estate",
            "subcategory":"Real Estate Services",
            "type":"Services"
        },
        {
            "category":"Professional",
            "subcategory":"Business Services",
            "type":"Services"
        },
        {
            "category":"Real Estate",
            "subcategory":"Surveying",
            "type":"Services"
        }
    ],
    "sg:phone":"+1 706 695 0614",
    "sg:postcode":"30705",
    "sg:province":"GA",
    "sg:tags":[
        "commercial",
        "appraisers-business",
        "industrial",
        "appraisers-commercial",
        "appraiser"
    ],
    "wof:name":"Rock Creek Appraisal",
    "wof:placetype":"venue"
},
  "geometry": {"coordinates":[-84.774269,34.768928],"type":"Point"}
}