{
  "type": "Feature",
  "properties": {
    "iso:country":"US",
    "sg:address":"2 Concourse Pkwy NE",
    "sg:city":"Atlanta",
    "sg:classifiers":[
        {
            "category":"Restaurant",
            "type":"Food & Drink"
        }
    ],
    "sg:phone":"+1 770 522 8122",
    "sg:postcode":"30328",
    "sg:province":"GA",
    "sg:tags":[
        "traditional",
        "american"
    ],
    "wof:name":"Sandy's Cafe",
    "wof:placetype":"venue"
},
  "geometry": {"coordinates":[-84.351731,33.9162],"type":"Point"}
}