{
  "type": "Feature",
  "properties": {
    "addr:full":"280 Brampton Rd Savannah GA 31408",
    "addr:housenumber":"280",
    "addr:postcode":"31408",
    "addr:street":"Brampton Rd",
    "iso:country":"US",
    "sg:address":"280 Brampton Rd",
    "sg:city":"Savannah",
    "sg:classifiers":[
        {
            "category":"Marine",
            "type":"Transportation"
        }
    ],
    "sg:phone":"+1 912 964 1811",
    "sg:postcode":"31408",
    "sg:province":"GA",
    "sg:tags":[
        "terminals-river"
    ],
    "wof:name":"Vopak Terminal Savannah, Inc",
    "wof:placetype":"venue"
},
  "geometry": {"coordinates":[-81.13567399999999,32.114591],"type":"Point"}
}