{
  "type": "Feature",
  "properties": {
    "iso:country":"US",
    "sg:address":"415 Temple St NW",
    "sg:city":"Atlanta",
    "sg:classifiers":[
        {
            "category":"Freight",
            "type":"Transportation"
        }
    ],
    "sg:phone":"+1 404 681 4108",
    "sg:postcode":"30314",
    "sg:province":"GA",
    "sg:tags":[
        "operator",
        "local",
        "trucking"
    ],
    "wof:name":"Do Right Movers",
    "wof:placetype":"venue"
},
  "geometry": {"coordinates":[-84.42195599999999,33.766321],"type":"Point"}
}