{
  "type": "Feature",
  "properties": {
    "addr:full":"518 N Harris St Sandersville GA 31082",
    "addr:housenumber":"518",
    "addr:postcode":"31082",
    "addr:street":"N Harris St",
    "iso:country":"US",
    "sg:address":"518 N Harris St",
    "sg:city":"Sandersville",
    "sg:classifiers":[
        {
            "category":"Government",
            "subcategory":"Office",
            "type":"Public Place"
        }
    ],
    "sg:phone":"+1 478 552 5178",
    "sg:postcode":"31082",
    "sg:province":"GA",
    "sg:website":"www.ga-edtech.org/ocone",
    "wof:name":"Oconee RESA",
    "wof:placetype":"venue"
},
  "geometry": {"coordinates":[-82.809399,32.994136],"type":"Point"}
}