{
  "type": "Feature",
  "properties": {
    "addr:full":"864 US Hwy 280 Americus GA 31709",
    "addr:housenumber":"864",
    "addr:postcode":"31709",
    "addr:street":"Us Hwy 280",
    "iso:country":"US",
    "sg:address":"864 US Hwy 280",
    "sg:city":"Americus",
    "sg:classifiers":[
        {
            "category":"Wholesale",
            "subcategory":"Machinery & Supplies",
            "type":"Manufacturing & Wholesale Goods"
        }
    ],
    "sg:phone":"+1 229 924 2141",
    "sg:postcode":"31709",
    "sg:province":"GA",
    "sg:tags":[
        "farm",
        "equipment"
    ],
    "wof:name":"Mc Cranie Tractor Co",
    "wof:placetype":"venue"
},
  "geometry": {"coordinates":[-84.220547,32.071211],"type":"Point"}
}