{
  "type": "Feature",
  "properties": {
    "iso:country":"US",
    "sg:address":"2417 Lenora Church Rd",
    "sg:city":"Snellville",
    "sg:classifiers":[
        {
            "category":"Marine",
            "type":"Transportation"
        },
        {
            "category":"Landmark",
            "subcategory":"Tourist Information",
            "type":"Public Place"
        }
    ],
    "sg:phone":"+1 770 985 1322",
    "sg:postcode":"30078",
    "sg:province":"GA",
    "sg:tags":[
        "promoter",
        "tours-operators",
        "cruise"
    ],
    "sg:website":"http://www.fantasiatravelinc.com",
    "wof:name":"Fantasia Travel Inc",
    "wof:placetype":"venue"
},
  "geometry": {"coordinates":[-84.019019,33.852324],"type":"Point"}
}