{
  "type": "Feature",
  "properties": {
    "addr:full":"2852 Delk Rd SE Marietta GA 30067",
    "addr:housenumber":"2852",
    "addr:postcode":"30067",
    "addr:street":"Delk Rd Se",
    "iso:country":"US",
    "sg:address":"2852 Delk Rd SE",
    "sg:city":"Marietta",
    "sg:classifiers":[
        {
            "category":"Shopping",
            "subcategory":"Mobile Phones",
            "type":"Retail Goods"
        }
    ],
    "sg:phone":"+1 678 831 0632",
    "sg:postcode":"30067",
    "sg:province":"GA",
    "wof:name":"Boost Mobile",
    "wof:placetype":"venue"
},
  "geometry": {"coordinates":[-84.46954100000001,33.923903],"type":"Point"}
}