{
  "type": "Feature",
  "properties": {
    "iso:country":"US",
    "sg:address":"2745 Mount Zion Rd",
    "sg:city":"Jonesboro",
    "sg:classifiers":[
        {
            "category":"Organizations",
            "subcategory":"Religious Organization",
            "type":"Services"
        }
    ],
    "sg:phone":"+1 770 961 8310",
    "sg:postcode":"30236",
    "sg:province":"GA",
    "wof:name":"Hope Church",
    "wof:placetype":"venue"
},
  "geometry": {"coordinates":[-84.300752,33.556913],"type":"Point"}
}