{
  "type": "Feature",
  "properties": {
    "iso:country":"US",
    "sg:address":"2840 Atlanta Rd SE",
    "sg:city":"Smyrna",
    "sg:classifiers":[
        {
            "category":"Fast Food",
            "type":"Food & Drink"
        },
        {
            "category":"Restaurant",
            "type":"Food & Drink"
        },
        {
            "category":"Professional",
            "type":"Services"
        }
    ],
    "sg:phone":"+1 770 319 6880",
    "sg:postcode":"30080",
    "sg:province":"GA",
    "sg:tags":[
        "mexican",
        "take",
        "caterer"
    ],
    "sg:website":"http://www.moes.com",
    "wof:name":"Moe's Southwest Grill",
    "wof:placetype":"venue"
},
  "geometry": {"coordinates":[-84.51419799999999,33.8834],"type":"Point"}
}