{
  "type": "Feature",
  "properties": {
    "addr:full":"4727 Walnut Ln Gainesville GA 30507",
    "addr:housenumber":"4727",
    "addr:postcode":"30507",
    "addr:street":"Walnut Ln",
    "iso:country":"US",
    "sg:address":"4727 Walnut Ln",
    "sg:city":"Gainesville",
    "sg:classifiers":[
        {
            "category":"Professional",
            "subcategory":"Business Services",
            "type":"Services"
        }
    ],
    "sg:phone":"+1 770 536 4918",
    "sg:postcode":"30507",
    "sg:province":"GA",
    "wof:name":"Residential Technology Inc",
    "wof:placetype":"venue"
},
  "geometry": {"coordinates":[-83.800995,34.190163],"type":"Point"}
}