{
  "type": "Feature",
  "properties": {
    "iso:country":"US",
    "sg:address":"3812 Arrel Dr",
    "sg:city":"Columbus",
    "sg:classifiers":[
        {
            "category":"Building & Trades",
            "subcategory":"Construction",
            "type":"Services"
        }
    ],
    "sg:phone":"+1 706 569 7643",
    "sg:postcode":"31909",
    "sg:province":"GA",
    "sg:tags":[
        "contractor"
    ],
    "wof:name":"Heritage Metal Works",
    "wof:placetype":"venue"
},
  "geometry": {"coordinates":[-84.92837,32.538218],"type":"Point"}
}