{
  "type": "Feature",
  "properties": {
    "addr:full":"596 State Rte 61 Villa Rica GA 30180",
    "addr:housenumber":"596",
    "addr:postcode":"30180",
    "addr:street":"State Rte 61",
    "iso:country":"US",
    "sg:address":"596 State Rte 61",
    "sg:city":"Villa Rica",
    "sg:classifiers":[
        {
            "category":"Restaurant",
            "type":"Food & Drink"
        }
    ],
    "sg:phone":"+1 770 459 3180",
    "sg:postcode":"30180",
    "sg:province":"GA",
    "wof:name":"Domino's Pizza",
    "wof:placetype":"venue"
},
  "geometry": {"coordinates":[-84.919155,33.743512],"type":"Point"}
}