{
  "type": "Feature",
  "properties": {
    "addr:full":"1700 River St Valdosta GA 31601",
    "addr:housenumber":"1700",
    "addr:postcode":"31601",
    "addr:street":"River St",
    "iso:country":"US",
    "sg:address":"1700 River St",
    "sg:city":"Valdosta",
    "sg:classifiers":[
        {
            "category":"Home & Garden",
            "subcategory":"Furniture",
            "type":"Retail Goods"
        }
    ],
    "sg:phone":"+1 229 253 1722",
    "sg:postcode":"31601",
    "sg:province":"GA",
    "wof:name":"River Street Home Furnishing",
    "wof:placetype":"venue"
},
  "geometry": {"coordinates":[-83.318637,30.82837],"type":"Point"}
}