{
  "type": "Feature",
  "properties": {
    "iso:country":"US",
    "sg:address":"412 Main St",
    "sg:city":"Blackshear",
    "sg:classifiers":[
        {
            "category":"Real Estate",
            "subcategory":"Real Estate Agent",
            "type":"Services"
        }
    ],
    "sg:phone":"+1 912 449 8188",
    "sg:postcode":"31516",
    "sg:province":"GA",
    "wof:name":"Manders Company",
    "wof:placetype":"venue"
},
  "geometry": {"coordinates":[-82.23915599999999,31.303037],"type":"Point"}
}