{
  "type": "Feature",
  "properties": {
    "iso:country":"US",
    "sg:address":"5901A Peachtree Industrial Blvd",
    "sg:city":"Atlanta",
    "sg:classifiers":[
        {
            "category":"Manufacturing",
            "subcategory":"Buildings",
            "type":"Manufacturing & Wholesale Goods"
        },
        {
            "category":"Building & Trades",
            "subcategory":"Construction",
            "type":"Services"
        }
    ],
    "sg:phone":"+1 678 459 3000",
    "sg:postcode":"30341",
    "sg:province":"GA",
    "sg:tags":[
        "consultant",
        "builder",
        "contractor",
        "home"
    ],
    "wof:name":"DPR Construction Atlanta",
    "wof:placetype":"venue"
},
  "geometry": {"coordinates":[-84.292072,33.908008],"type":"Point"}
}