{
  "type": "Feature",
  "properties": {
    "addr:full":"3608 Sunderland Cir NE Atlanta GA 30319",
    "addr:housenumber":"3608",
    "addr:postcode":"30319",
    "addr:street":"Sunderland Cir Ne",
    "iso:country":"US",
    "sg:address":"3608 Sunderland Cir NE",
    "sg:city":"Atlanta",
    "sg:classifiers":[
        {
            "category":"Professional",
            "subcategory":"Management & Consulting",
            "type":"Services"
        }
    ],
    "sg:phone":"+1 770 451 9977",
    "sg:postcode":"30319",
    "sg:province":"GA",
    "sg:tags":[
        "consultant",
        "employment"
    ],
    "wof:name":"Beyond Borders, Inc",
    "wof:placetype":"venue"
},
  "geometry": {"coordinates":[-84.335922,33.895741],"type":"Point"}
}