{
  "type": "Feature",
  "properties": {
    "addr:full":"506 Primrose Ln Locust Grove GA 30248",
    "addr:housenumber":"506",
    "addr:postcode":"30248",
    "addr:street":"Primrose Ln",
    "iso:country":"US",
    "sg:address":"506 Primrose Ln",
    "sg:city":"Locust Grove",
    "sg:classifiers":[
        {
            "category":"Building & Trades",
            "subcategory":"Construction",
            "type":"Services"
        }
    ],
    "sg:phone":"+1 770 957 5034",
    "sg:postcode":"30248",
    "sg:province":"GA",
    "sg:tags":[
        "contractor"
    ],
    "wof:name":"Howells Pressure Was",
    "wof:placetype":"venue"
},
  "geometry": {"coordinates":[-84.02976099999999,33.397508],"type":"Point"}
}