{
  "type": "Feature",
  "properties": {
    "addr:full":"4814 Stone Mountain Hwy Ste 6 Lilburn GA 30047",
    "addr:housenumber":"4814",
    "addr:postcode":"30047",
    "addr:street":"Stone Mountain Hwy Ste 6",
    "iso:country":"US",
    "sg:address":"4814 Stone Mountain Hwy Ste 6",
    "sg:city":"Lilburn",
    "sg:classifiers":[
        {
            "category":"Wholesale",
            "subcategory":"Computers",
            "type":"Manufacturing & Wholesale Goods"
        }
    ],
    "sg:phone":"+1 770 978 9225",
    "sg:postcode":"30047",
    "sg:province":"GA",
    "wof:name":"AA Computer Inc",
    "wof:placetype":"venue"
},
  "geometry": {"coordinates":[-84.095901,33.827301],"type":"Point"}
}