{
  "type": "Feature",
  "properties": {
    "iso:country":"US",
    "sg:address":"714 Rock Chapel Rd",
    "sg:city":"Lithonia",
    "sg:classifiers":[
        {
            "category":"Building & Trades",
            "subcategory":"Landscaping Services",
            "type":"Services"
        }
    ],
    "sg:phone":"+1 770 985 6631",
    "sg:postcode":"30058",
    "sg:province":"GA",
    "sg:tags":[
        "lawn",
        "maintenance",
        "grounds"
    ],
    "wof:name":"Lawn Service",
    "wof:placetype":"venue"
},
  "geometry": {"coordinates":[-84.076314,33.773916],"type":"Point"}
}