{
  "type": "Feature",
  "properties": {
    "addr:full":"527 Candler St NE Atlanta GA 30307",
    "addr:housenumber":"527",
    "addr:postcode":"30307",
    "addr:street":"Candler St Ne",
    "iso:country":"US",
    "sg:address":"527 Candler St NE",
    "sg:city":"Atlanta",
    "sg:classifiers":[
        {
            "category":"Professional",
            "type":"Services"
        }
    ],
    "sg:phone":"+1 404 584 6522",
    "sg:postcode":"30307",
    "sg:province":"GA",
    "wof:name":"3633 East Old Abode LLC",
    "wof:placetype":"venue"
},
  "geometry": {"coordinates":[-84.344978,33.768574],"type":"Point"}
}