{
  "type": "Feature",
  "properties": {
    "iso:country":"US",
    "sg:address":"108 2nd St W",
    "sg:city":"Darien",
    "sg:classifiers":[
        {
            "category":"Professional",
            "subcategory":"Lawyer & Legal Services",
            "type":"Services"
        }
    ],
    "sg:phone":"+1 912 437 4402",
    "sg:postcode":"31305",
    "sg:province":"GA",
    "sg:tags":[
        "divorce",
        "attorney",
        "criminal",
        "family",
        "law"
    ],
    "wof:name":"Poppell Bolin & West Pc",
    "wof:placetype":"venue"
},
  "geometry": {"coordinates":[-81.437061,31.37117],"type":"Point"}
}