{
  "type": "Feature",
  "properties": {
    "addr:full":"4346 Plainview Rd Pendergrass GA 30558",
    "addr:housenumber":"4346",
    "addr:postcode":"30558",
    "addr:street":"Plainview Rd",
    "iso:country":"US",
    "sg:address":"4346 Plainview Rd",
    "sg:city":"Pendergrass",
    "sg:classifiers":[
        {
            "category":"Government",
            "subcategory":"Fire Station",
            "type":"Public Place"
        }
    ],
    "sg:phone":"+1 706 693 4260",
    "sg:postcode":"30558",
    "sg:province":"GA",
    "sg:tags":[
        "department",
        "protection"
    ],
    "wof:name":"Plainview Volunteer Fire Depar",
    "wof:placetype":"venue"
},
  "geometry": {"coordinates":[-83.629186,34.220307],"type":"Point"}
}