{
  "type": "Feature",
  "properties": {
    "addr:full":"300 S River St Calhoun GA 30701",
    "addr:housenumber":"300",
    "addr:postcode":"30701",
    "addr:street":"S River St",
    "iso:country":"US",
    "sg:address":"300 S River St",
    "sg:city":"Calhoun",
    "sg:classifiers":[
        {
            "category":"Education",
            "subcategory":"School",
            "type":"Public Place"
        }
    ],
    "sg:phone":"+1 706 625 0433",
    "sg:postcode":"30701",
    "sg:province":"GA",
    "sg:tags":[
        "high",
        "k-",
        "private"
    ],
    "wof:name":"Northwest Psycho-Educational Program Calhoun High School",
    "wof:placetype":"venue"
},
  "geometry": {"coordinates":[-84.954987,34.502739],"type":"Point"}
}