{
  "type": "Feature",
  "properties": {
    "iso:country":"US",
    "sg:address":"190 Marietta St NW # 275",
    "sg:city":"Atlanta",
    "sg:classifiers":[
        {
            "category":"Restaurant",
            "type":"Food & Drink"
        }
    ],
    "sg:phone":"+1 404 584 8955",
    "sg:postcode":"30303",
    "sg:province":"GA",
    "sg:tags":[
        "pizza"
    ],
    "wof:name":"Rimini Pizza Of C N N Center",
    "wof:placetype":"venue"
},
  "geometry": {"coordinates":[-84.39357,33.757971],"type":"Point"}
}