{
  "type": "Feature",
  "properties": {
    "iso:country":"US",
    "sg:address":"3100 Leeds Garden Ln",
    "sg:city":"Alpharetta",
    "sg:classifiers":[
        {
            "category":"Organizations",
            "subcategory":"Community Association",
            "type":"Services"
        }
    ],
    "sg:phone":"+1 770 569 8454",
    "sg:postcode":"30022",
    "sg:province":"GA",
    "wof:name":"Destin Florida Condominium",
    "wof:placetype":"venue"
},
  "geometry": {"coordinates":[-84.27325999999999,34.018748],"type":"Point"}
}