{
  "type": "Feature",
  "properties": {
    "addr:full":"3060 Peachtree Rd NW Atlanta GA 30305",
    "addr:housenumber":"3060",
    "addr:postcode":"30305",
    "addr:street":"Peachtree Rd Nw",
    "iso:country":"US",
    "sg:address":"3060 Peachtree Rd NW",
    "sg:city":"Atlanta",
    "sg:classifiers":[
        {
            "category":"Real Estate",
            "subcategory":"Architect",
            "type":"Services"
        }
    ],
    "sg:phone":"+1 404 364 9633",
    "sg:postcode":"30305",
    "sg:province":"GA",
    "wof:name":"Diedrich Richard J Archt",
    "wof:placetype":"venue"
},
  "geometry": {"coordinates":[-84.380501,33.838699],"type":"Point"}
}