{
  "type": "Feature",
  "properties": {
    "addr:full":"3735 Cascade Road SW Atlanta GA 30331",
    "addr:housenumber":"3735",
    "addr:postcode":"30331",
    "addr:street":"Cascade Road Sw",
    "iso:country":"US",
    "sg:address":"3735 Cascade Road SW",
    "sg:city":"Atlanta",
    "sg:classifiers":[
        {
            "category":"Autos & Motor Vehicles",
            "subcategory":"Auto Supplies",
            "type":"Retail Goods"
        },
        {
            "category":"Retail",
            "subcategory":"Auto Repair",
            "type":"Services"
        }
    ],
    "sg:phone":"+1 404 696 6614",
    "sg:postcode":"30331",
    "sg:province":"GA",
    "sg:tags":[
        "tire"
    ],
    "wof:name":"Tires Plus",
    "wof:placetype":"venue"
},
  "geometry": {"coordinates":[-84.511455,33.723884],"type":"Point"}
}