{
  "type": "Feature",
  "properties": {
    "addr:full":"2126 Sandtown Rd SW Marietta GA 30060",
    "addr:housenumber":"2126",
    "addr:postcode":"30060",
    "addr:street":"Sandtown Rd Sw",
    "iso:country":"US",
    "sg:address":"2126 Sandtown Rd SW",
    "sg:city":"Marietta",
    "sg:classifiers":[
        {
            "category":"Wholesale",
            "subcategory":"Office Equipment",
            "type":"Manufacturing & Wholesale Goods"
        }
    ],
    "sg:phone":"+1 678 410 1369",
    "sg:postcode":"30060",
    "sg:province":"GA",
    "sg:tags":[
        "equipment-installation",
        "furniture"
    ],
    "wof:name":"Door And Hardware Installation",
    "wof:placetype":"venue"
},
  "geometry": {"coordinates":[-84.557664,33.901916],"type":"Point"}
}