{
  "type": "Feature",
  "properties": {
    "addr:full":"2600 School Drive Atlanta GA 30360",
    "addr:housenumber":"2600",
    "addr:postcode":"30360",
    "addr:street":"School Drive",
    "iso:country":"US",
    "sg:address":"2600 School Drive",
    "sg:city":"Atlanta",
    "sg:classifiers":[
        {
            "category":"Retail",
            "subcategory":"Pet Boarding",
            "type":"Services"
        }
    ],
    "sg:phone":"+1 770 457 0121",
    "sg:postcode":"30360",
    "sg:province":"GA",
    "sg:tags":[
        "boarding/pet",
        "sitting"
    ],
    "sg:website":"www.critter-sitters.com",
    "wof:name":"Critter Sitters",
    "wof:placetype":"venue"
},
  "geometry": {"coordinates":[-84.277967,33.906467],"type":"Point"}
}