{
  "type": "Feature",
  "properties": {
    "addr:full":"189 Wallace Dr Bloomingdale GA 31302",
    "addr:housenumber":"189",
    "addr:postcode":"31302",
    "addr:street":"Wallace Dr",
    "iso:country":"US",
    "sg:address":"189 Wallace Dr",
    "sg:city":"Bloomingdale",
    "sg:classifiers":[
        {
            "category":"Building & Trades",
            "subcategory":"Cleaning & Sanitation",
            "type":"Services"
        }
    ],
    "sg:phone":"+1 912 748 2912",
    "sg:postcode":"31302",
    "sg:province":"GA",
    "sg:tags":[
        "house"
    ],
    "wof:name":"A Good Cleaning Lady",
    "wof:placetype":"venue"
},
  "geometry": {"coordinates":[-81.331609,32.095091],"type":"Point"}
}