{
  "type": "Feature",
  "properties": {
    "addr:full":"3226 Buford Dr Buford GA 30519",
    "addr:housenumber":"3226",
    "addr:postcode":"30519",
    "addr:street":"Buford Dr",
    "iso:country":"US",
    "sg:address":"3226 Buford Dr",
    "sg:city":"Buford",
    "sg:classifiers":[
        {
            "category":"Home & Garden",
            "subcategory":"Carpets & Floor Coverings",
            "type":"Retail Goods"
        }
    ],
    "sg:phone":"+1 678 546 5146",
    "sg:postcode":"30519",
    "sg:province":"GA",
    "sg:tags":[
        "mattress"
    ],
    "wof:name":"Mattress Giant",
    "wof:placetype":"venue"
},
  "geometry": {"coordinates":[-83.990227,34.063789],"type":"Point"}
}