{
  "type": "Feature",
  "properties": {
    "addr:full":"105 Grant St Clarkesville GA 30523",
    "addr:housenumber":"105",
    "addr:postcode":"30523",
    "addr:street":"Grant St",
    "iso:country":"US",
    "sg:address":"105 Grant St",
    "sg:city":"Clarkesville",
    "sg:classifiers":[
        {
            "category":"Retail",
            "subcategory":"Auto Repair",
            "type":"Services"
        }
    ],
    "sg:phone":"+1 706 754 5108",
    "sg:postcode":"30523",
    "sg:province":"GA",
    "sg:tags":[
        "repairing",
        "automobile"
    ],
    "wof:name":"Finley's Garage",
    "wof:placetype":"venue"
},
  "geometry": {"coordinates":[-83.524839,34.617556],"type":"Point"}
}