{
  "type": "Feature",
  "properties": {
    "iso:country":"US",
    "sg:address":"340 W Ponce de Leon Ave",
    "sg:city":"Decatur",
    "sg:classifiers":[
        {
            "category":"Restaurant",
            "type":"Food & Drink"
        }
    ],
    "sg:phone":"+1 404 270 9165",
    "sg:postcode":"30030",
    "sg:province":"GA",
    "sg:tags":[
        "thai"
    ],
    "sg:website":"www.garlicthaisushi.com",
    "wof:name":"Garlic Thai Cuisine and Sushi Bar",
    "wof:placetype":"venue"
},
  "geometry": {"coordinates":[-84.30102599999999,33.775322],"type":"Point"}
}