{
  "type": "Feature",
  "properties": {
    "iso:country":"US",
    "sg:address":"3600 Dallas Hwy",
    "sg:city":"Marietta",
    "sg:classifiers":[
        {
            "category":"Professional",
            "subcategory":"Management & Consulting",
            "type":"Services"
        }
    ],
    "sg:phone":"+1 770 428 2244",
    "sg:postcode":"30064",
    "sg:province":"GA",
    "sg:tags":[
        "specializing",
        "construction",
        "church"
    ],
    "wof:name":"Cumberland America Inc",
    "wof:placetype":"venue"
},
  "geometry": {"coordinates":[-84.657061,33.953798],"type":"Point"}
}