{
  "type": "Feature",
  "properties": {
    "addr:full":"129 N Main St Sylvester GA 31791",
    "addr:housenumber":"129",
    "addr:postcode":"31791",
    "addr:street":"N Main St",
    "iso:country":"US",
    "sg:address":"129 N Main St",
    "sg:city":"Sylvester",
    "sg:classifiers":[
        {
            "category":"Personal",
            "subcategory":"Beauty Salon",
            "type":"Services"
        }
    ],
    "sg:phone":"+1 229 776 1309",
    "sg:postcode":"31791",
    "sg:province":"GA",
    "sg:tags":[
        "shop"
    ],
    "wof:name":"Reba's Cuts & Perms",
    "wof:placetype":"venue"
},
  "geometry": {"coordinates":[-83.83569799999999,31.525759],"type":"Point"}
}