{
  "type": "Feature",
  "properties": {
    "iso:country":"US",
    "sg:address":"1560 Southlake Pkwy Ste 12B",
    "sg:city":"Morrow",
    "sg:classifiers":[
        {
            "category":"Home & Garden",
            "subcategory":"Furniture",
            "type":"Retail Goods"
        }
    ],
    "sg:phone":"+1 770 960 2311",
    "sg:postcode":"30260",
    "sg:province":"GA",
    "sg:tags":[
        "store"
    ],
    "wof:name":"Bed and Breakfast Furniture Outlet",
    "wof:placetype":"venue"
},
  "geometry": {"coordinates":[-84.33782100000001,33.573017],"type":"Point"}
}