{
  "type": "Feature",
  "properties": {
    "addr:full":"7695 State Rte 17 Bowersville GA 30516",
    "addr:housenumber":"7695",
    "addr:postcode":"30516",
    "addr:street":"State Rte 17 Bowersville",
    "iso:country":"US",
    "sg:address":"7695 State Rte 17",
    "sg:city":"Bowersville",
    "sg:classifiers":[
        {
            "category":"Restaurant",
            "type":"Food & Drink"
        }
    ],
    "sg:phone":"+1 706 245 1106",
    "sg:postcode":"30516",
    "sg:province":"GA",
    "wof:name":"Chuck Wagon Grill & Trading",
    "wof:placetype":"venue"
},
  "geometry": {"coordinates":[-83.08635,34.370904],"type":"Point"}
}