{
  "type": "Feature",
  "properties": {
    "addr:full":"327 Highland Lake Cir Decatur GA 30033",
    "addr:housenumber":"327",
    "addr:postcode":"30033",
    "addr:street":"Highland Lake Cir",
    "iso:country":"US",
    "sg:address":"327 Highland Lake Cir",
    "sg:city":"Decatur",
    "sg:classifiers":[
        {
            "category":"Personal",
            "type":"Services"
        }
    ],
    "sg:phone":"+1 404 248 1378",
    "sg:postcode":"30033",
    "sg:province":"GA",
    "wof:name":"Student Links",
    "wof:placetype":"venue"
},
  "geometry": {"coordinates":[-84.308127,33.8025],"type":"Point"}
}