{
  "type": "Feature",
  "properties": {
    "addr:full":"8608 Kent Dr Savannah GA 31406",
    "addr:housenumber":"8608",
    "addr:postcode":"31406",
    "addr:street":"Kent Dr",
    "iso:country":"US",
    "sg:address":"8608 Kent Dr",
    "sg:city":"Savannah",
    "sg:classifiers":[
        {
            "category":"Shopping",
            "subcategory":"Jewelry",
            "type":"Retail Goods"
        }
    ],
    "sg:phone":"+1 912 354 2718",
    "sg:postcode":"31406",
    "sg:province":"GA",
    "wof:name":"Carriage Jewelers Inc",
    "wof:placetype":"venue"
},
  "geometry": {"coordinates":[-81.096042,31.987743],"type":"Point"}
}