{
  "type": "Feature",
  "properties": {
    "addr:full":"131 Lake View Cir Brunswick GA 31525",
    "addr:housenumber":"131",
    "addr:postcode":"31525",
    "addr:street":"Lake View Cir",
    "iso:country":"US",
    "sg:address":"131 Lake View Cir",
    "sg:city":"Brunswick",
    "sg:classifiers":[
        {
            "category":"Building & Trades",
            "subcategory":"Plumbing",
            "type":"Services"
        }
    ],
    "sg:phone":"+1 912 265 3503",
    "sg:postcode":"31525",
    "sg:province":"GA",
    "sg:tags":[
        "refrigeration",
        "heating",
        "contractor"
    ],
    "wof:name":"Air Teams",
    "wof:placetype":"venue"
},
  "geometry": {"coordinates":[-81.47608,31.194886],"type":"Point"}
}