{
  "type": "Feature",
  "properties": {
    "iso:country":"US",
    "sg:address":"410 Cattail Ives Rd",
    "sg:city":"Lawrenceville",
    "sg:classifiers":[
        {
            "category":"Real Estate",
            "subcategory":"Real Estate Services",
            "type":"Services"
        },
        {
            "category":"Real Estate",
            "subcategory":"Real Estate Agent",
            "type":"Services"
        }
    ],
    "sg:phone":"+1 770 837 9873",
    "sg:postcode":"30045",
    "sg:province":"GA",
    "sg:tags":[
        "buyer",
        "broker"
    ],
    "wof:name":"Homecore Realty",
    "wof:placetype":"venue"
},
  "geometry": {"coordinates":[-83.927887,33.908716],"type":"Point"}
}