{
  "type": "Feature",
  "properties": {
    "addr:full":"160 Old Tennessee Hwy White GA 30184",
    "addr:housenumber":"160",
    "addr:postcode":"30184",
    "addr:street":"Old Tennessee Hwy",
    "iso:country":"US",
    "sg:address":"160 Old Tennessee Hwy",
    "sg:city":"White",
    "sg:classifiers":[
        {
            "category":"Manufacturing",
            "subcategory":"Tools & Machinery",
            "type":"Manufacturing & Wholesale Goods"
        }
    ],
    "sg:phone":"+1 770 382 8850",
    "sg:postcode":"30184",
    "sg:province":"GA",
    "sg:tags":[
        "construction",
        "mfg"
    ],
    "wof:name":"Jennings Backhoe",
    "wof:placetype":"venue"
},
  "geometry": {"coordinates":[-84.756212,34.272581],"type":"Point"}
}