{
  "type": "Feature",
  "properties": {
    "addr:full":"8047 Aloha Dr Jonesboro GA 30236",
    "addr:housenumber":"8047",
    "addr:postcode":"30236",
    "addr:street":"Aloha Dr",
    "iso:country":"US",
    "sg:address":"8047 Aloha Dr",
    "sg:city":"Jonesboro",
    "sg:classifiers":[
        {
            "category":"Professional",
            "type":"Services"
        }
    ],
    "sg:phone":"+1 770 471 7810",
    "sg:postcode":"30236",
    "sg:province":"GA",
    "wof:name":"Classic Tan Inc",
    "wof:placetype":"venue"
},
  "geometry": {"coordinates":[-84.33821399999999,33.534995],"type":"Point"}
}