{
  "type": "Feature",
  "properties": {
    "addr:full":"603 W Crossville Rd Roswell GA 30075",
    "addr:housenumber":"603",
    "addr:postcode":"30075",
    "addr:street":"W Crossville Rd",
    "iso:country":"US",
    "sg:address":"603 W Crossville Rd",
    "sg:city":"Roswell",
    "sg:classifiers":[
        {
            "category":"Health Services",
            "subcategory":"Doctor",
            "type":"Services"
        }
    ],
    "sg:phone":"+1 678 277 9007",
    "sg:postcode":"30075",
    "sg:province":"GA",
    "wof:name":"Bean James L MD",
    "wof:placetype":"venue"
},
  "geometry": {"coordinates":[-84.379183,34.057265],"type":"Point"}
}