{
  "type": "Feature",
  "properties": {
    "iso:country":"US",
    "sg:address":"1133 Eagles Landing Pkwy",
    "sg:city":"Stockbridge",
    "sg:classifiers":[
        {
            "category":"Health Services",
            "subcategory":"Hospital",
            "type":"Services"
        }
    ],
    "sg:phone":"+1 770 389 2200",
    "sg:postcode":"30281",
    "sg:province":"GA",
    "sg:tags":[
        "medical",
        "general"
    ],
    "wof:name":"HENRY OCCUPATIONAL MEDICINE CL",
    "wof:placetype":"venue"
},
  "geometry": {"coordinates":[-84.22202900000001,33.511767],"type":"Point"}
}