{
  "type": "Feature",
  "properties": {
    "iso:country":"US",
    "sg:address":"525 Willowbrook Run",
    "sg:city":"Alpharetta",
    "sg:classifiers":[
        {
            "category":"Professional",
            "subcategory":"Management & Consulting",
            "type":"Services"
        }
    ],
    "sg:phone":"+1 770 667 3885",
    "sg:postcode":"30022",
    "sg:province":"GA",
    "sg:tags":[
        "business"
    ],
    "wof:name":"Comtrol Corp",
    "wof:placetype":"venue"
},
  "geometry": {"coordinates":[-84.224935,34.055329],"type":"Point"}
}