{
  "type": "Feature",
  "properties": {
    "addr:full":"831 6th Ave Columbus GA 31901",
    "addr:housenumber":"831",
    "addr:postcode":"31901",
    "addr:street":"6Th Ave",
    "iso:country":"US",
    "sg:address":"831 6th Ave",
    "sg:city":"Columbus",
    "sg:classifiers":[
        {
            "category":"Social Services",
            "subcategory":"Child Care",
            "type":"Services"
        },
        {
            "category":"Organizations",
            "subcategory":"Religious Organization",
            "type":"Services"
        }
    ],
    "sg:phone":"+1 706 327 0704",
    "sg:postcode":"31901",
    "sg:province":"GA",
    "sg:tags":[
        "church"
    ],
    "wof:name":"Friendship Baptist Church Day",
    "wof:placetype":"venue"
},
  "geometry": {"coordinates":[-84.984876,32.462397],"type":"Point"}
}