{
  "type": "Feature",
  "properties": {
    "addr:full":"494 Ashwood Dr Lawrenceville GA 30043",
    "addr:housenumber":"494",
    "addr:postcode":"30043",
    "addr:street":"Ashwood Dr",
    "iso:country":"US",
    "sg:address":"494 Ashwood Dr",
    "sg:city":"Lawrenceville",
    "sg:classifiers":[
        {
            "category":"Building & Trades",
            "subcategory":"Construction",
            "type":"Services"
        }
    ],
    "sg:phone":"+1 770 822 4004",
    "sg:postcode":"30043",
    "sg:province":"GA",
    "sg:tags":[
        "carpentry",
        "contractor"
    ],
    "wof:name":"Scott Whaley Construction",
    "wof:placetype":"venue"
},
  "geometry": {"coordinates":[-84.02362599999999,33.986083],"type":"Point"}
}