{
  "type": "Feature",
  "properties": {
    "addr:full":"607 Duncroft Ct Augusta GA 30907",
    "addr:housenumber":"607",
    "addr:postcode":"30907",
    "addr:street":"Duncroft Ct",
    "iso:country":"US",
    "sg:address":"607 Duncroft Ct",
    "sg:city":"Augusta",
    "sg:classifiers":[
        {
            "category":"Professional",
            "subcategory":"Engineering",
            "type":"Services"
        }
    ],
    "sg:phone":"+1 706 650 2488",
    "sg:postcode":"30907",
    "sg:province":"GA",
    "sg:tags":[
        "engineer"
    ],
    "wof:name":"Dwayne E Thomas",
    "wof:placetype":"venue"
},
  "geometry": {"coordinates":[-82.134811,33.497782],"type":"Point"}
}