{
  "type": "Feature",
  "properties": {
    "iso:country":"US",
    "sg:address":"193 Grant Rd",
    "sg:city":"Fayetteville",
    "sg:classifiers":[
        {
            "category":"Professional",
            "subcategory":"Management & Consulting",
            "type":"Services"
        }
    ],
    "sg:phone":"+1 770 460 2132",
    "sg:postcode":"30205",
    "sg:province":"GA",
    "sg:tags":[
        "business"
    ],
    "wof:name":"Kedron Consulting Inc",
    "wof:placetype":"venue"
},
  "geometry": {"coordinates":[-84.44212,33.320909],"type":"Point"}
}