{
  "type": "Feature",
  "properties": {
    "iso:country":"US",
    "sg:address":"2155 Monroe Dr NE",
    "sg:city":"Atlanta",
    "sg:classifiers":[
        {
            "category":"Communications",
            "subcategory":"Television Station",
            "type":"Services"
        }
    ],
    "sg:phone":"+1 404 881 3600",
    "sg:postcode":"30324",
    "sg:province":"GA",
    "wof:name":"Quest Broadcasting LLC",
    "wof:placetype":"venue"
},
  "geometry": {"coordinates":[-84.37036999999999,33.81066],"type":"Point"}
}