{
  "type": "Feature",
  "properties": {
    "iso:country":"US",
    "sg:address":"2845 Greenbriar Pkwy SW",
    "sg:city":"Atlanta",
    "sg:classifiers":[
        {
            "category":"Building & Trades",
            "subcategory":"Locksmith",
            "type":"Services"
        }
    ],
    "sg:phone":"+1 678 303 5338",
    "sg:postcode":"30331",
    "sg:province":"GA",
    "sg:tags":[
        "key"
    ],
    "wof:name":"0 1 24 Emergency A Locksmith",
    "wof:placetype":"venue"
},
  "geometry": {"coordinates":[-84.492603,33.686478],"type":"Point"}
}