{
  "type": "Feature",
  "properties": {
    "iso:country":"US",
    "sg:address":"601 S River St",
    "sg:city":"Calhoun",
    "sg:classifiers":[
        {
            "category":"Recreation",
            "type":"Entertainment"
        }
    ],
    "sg:phone":"+1 706 629 0177",
    "sg:postcode":"30701",
    "sg:province":"GA",
    "sg:tags":[
        "parks"
    ],
    "wof:name":"Calhoun City-Recreation Dept",
    "wof:placetype":"venue"
},
  "geometry": {"coordinates":[-84.955832,34.49095],"type":"Point"}
}