{
  "type": "Feature",
  "properties": {
    "addr:full":"240 S Elm St Commerce GA 30529",
    "addr:housenumber":"240",
    "addr:postcode":"30529",
    "addr:street":"S Elm St",
    "iso:country":"US",
    "sg:address":"240 S Elm St",
    "sg:city":"Commerce",
    "sg:classifiers":[
        {
            "category":"Banks & Credit Unions",
            "subcategory":"Bank",
            "type":"Services"
        }
    ],
    "sg:phone":"+1 706 336 3208",
    "sg:postcode":"30529",
    "sg:province":"GA",
    "wof:name":"Community Bank & Trust Co",
    "wof:placetype":"venue"
},
  "geometry": {"coordinates":[-83.44209600000001,34.185873],"type":"Point"}
}