{
  "type": "Feature",
  "properties": {
    "addr:full":"209 Swanton Way Ste B Decatur GA 30030",
    "addr:housenumber":"209",
    "addr:postcode":"30030",
    "addr:street":"Swanton Way Ste B",
    "iso:country":"US",
    "sg:address":"209 Swanton Way Ste B",
    "sg:city":"Decatur",
    "sg:classifiers":[
        {
            "category":"Health Services",
            "subcategory":"Doctor",
            "type":"Services"
        },
        {
            "category":"Health Services",
            "subcategory":"Health Practitioner",
            "type":"Services"
        }
    ],
    "sg:phone":"+1 404 377 7669",
    "sg:postcode":"30030",
    "sg:province":"GA",
    "sg:tags":[
        "physician",
        "surgeons",
        "drug",
        "abuse",
        "medicine",
        "addiction"
    ],
    "sg:website":"http://www.alliancerecoverycenter.com",
    "wof:name":"Alliance Recovery Center",
    "wof:placetype":"venue"
},
  "geometry": {"coordinates":[-84.298958,33.774577],"type":"Point"}
}