{
  "type": "Feature",
  "properties": {
    "addr:full":"3333 Buford Dr Buford GA 30519",
    "addr:housenumber":"3333",
    "addr:postcode":"30519",
    "addr:street":"Buford Dr",
    "iso:country":"US",
    "sg:address":"3333 Buford Dr",
    "sg:city":"Buford",
    "sg:classifiers":[
        {
            "category":"Bakery",
            "type":"Food & Drink"
        }
    ],
    "sg:menulink":"http://www.allmenus.com/ga/dacula-rocky-creek/235707-pretzel-time/menu/",
    "sg:phone":"+1 770 831 2370",
    "sg:postcode":"30519",
    "sg:province":"GA",
    "sg:tags":[
        "new",
        "american",
        "pastry"
    ],
    "wof:name":"Pretzel Time",
    "wof:placetype":"venue"
},
  "geometry": {"coordinates":[-83.984258,34.071252],"type":"Point"}
}