{
  "type": "Feature",
  "properties": {
    "addr:full":"1590 Scenic Hwy N Snellville GA 30078",
    "addr:housenumber":"1590",
    "addr:postcode":"30078",
    "addr:street":"Scenic Hwy N",
    "iso:country":"US",
    "sg:address":"1590 Scenic Hwy N",
    "sg:city":"Snellville",
    "sg:classifiers":[
        {
            "category":"Banks & Credit Unions",
            "subcategory":"Bank",
            "type":"Services"
        }
    ],
    "sg:phone":"+1 770 978 5050",
    "sg:postcode":"30078",
    "sg:province":"GA",
    "sg:website":"www.wachovia.com",
    "wof:name":"Wachovia",
    "wof:placetype":"venue"
},
  "geometry": {"coordinates":[-84.009598,33.887402],"type":"Point"}
}