{
  "type": "Feature",
  "properties": {
    "addr:full":"10150 Groomsbridge Rd Alpharetta GA 30022",
    "addr:housenumber":"10150",
    "addr:postcode":"30022",
    "addr:street":"Groomsbridge Rd",
    "iso:country":"US",
    "sg:address":"10150 Groomsbridge Rd",
    "sg:city":"Alpharetta",
    "sg:classifiers":[
        {
            "category":"Professional",
            "type":"Services"
        }
    ],
    "sg:phone":"+1 770 232 4850",
    "sg:postcode":"30022",
    "sg:province":"GA",
    "sg:tags":[
        "establishment"
    ],
    "wof:name":"Medlock Bridge Homeowners",
    "wof:placetype":"venue"
},
  "geometry": {"coordinates":[-84.19907499999999,34.029353],"type":"Point"}
}