{
  "type": "Feature",
  "properties": {
    "addr:full":"505 Summer Dr Atlanta GA 30328",
    "addr:housenumber":"505",
    "addr:postcode":"30328",
    "addr:street":"Summer Dr",
    "iso:country":"US",
    "sg:address":"505 Summer Dr",
    "sg:city":"Atlanta",
    "sg:classifiers":[
        {
            "category":"Professional",
            "type":"Services"
        }
    ],
    "sg:phone":"+1 678 441 0305",
    "sg:postcode":"30328",
    "sg:province":"GA",
    "wof:name":"Amfpg Inc",
    "wof:placetype":"venue"
},
  "geometry": {"coordinates":[-84.35206700000001,33.925507],"type":"Point"}
}