{
  "type": "Feature",
  "properties": {
    "iso:country":"US",
    "sg:address":"1 Aviation Way Dekalb-Peachtree Airport",
    "sg:city":"Atlanta",
    "sg:classifiers":[
        {
            "category":"Airline",
            "type":"Transportation"
        }
    ],
    "sg:phone":"+1 770 458 9851",
    "sg:postcode":"30341",
    "sg:province":"GA",
    "sg:website":"www.eppsaviation.com",
    "wof:name":"Epps Aviation",
    "wof:placetype":"venue"
},
  "geometry": {"coordinates":[-84.30603000000001,33.876547],"type":"Point"}
}