{
  "type": "Feature",
  "properties": {
    "iso:country":"US",
    "sg:address":"1016 Potash Rd",
    "sg:city":"Cedartown",
    "sg:classifiers":[
        {
            "category":"Real Estate",
            "subcategory":"Real Estate Agent",
            "type":"Services"
        }
    ],
    "sg:phone":"+1 770 748 9774",
    "sg:postcode":"30125",
    "sg:province":"GA",
    "wof:name":"Achim Realty & Construction",
    "wof:placetype":"venue"
},
  "geometry": {"coordinates":[-85.316367,33.991242],"type":"Point"}
}