{
  "type": "Feature",
  "properties": {
    "addr:full":"1000 N Point Cir Alpharetta GA 30022",
    "addr:housenumber":"1000",
    "addr:postcode":"30022",
    "addr:street":"N Point Cir",
    "iso:country":"US",
    "sg:address":"1000 N Point Cir",
    "sg:city":"Alpharetta",
    "sg:classifiers":[
        {
            "category":"Personal",
            "subcategory":"Piercing",
            "type":"Services"
        }
    ],
    "sg:phone":"+1 770 789 6233",
    "sg:postcode":"30022",
    "sg:province":"GA",
    "sg:tags":[
        "body"
    ],
    "wof:name":"Belly Buttons Personalized",
    "wof:placetype":"venue"
},
  "geometry": {"coordinates":[-84.29812,34.049494],"type":"Point"}
}