{
  "type": "Feature",
  "properties": {
    "iso:country":"US",
    "sg:address":"2215 Memorial Dr",
    "sg:city":"Waycross",
    "sg:classifiers":[
        {
            "category":"Shopping",
            "subcategory":"Clothing, Apparel, & Fashions",
            "type":"Retail Goods"
        }
    ],
    "sg:phone":"+1 912 284 9767",
    "sg:postcode":"31501",
    "sg:province":"GA",
    "sg:tags":[
        "t"
    ],
    "wof:name":"Southtern Outfitters Inc",
    "wof:placetype":"venue"
},
  "geometry": {"coordinates":[-82.333808,31.203689],"type":"Point"}
}