{
  "type": "Feature",
  "properties": {
    "addr:full":"2581 Piedmont Rd NE Atlanta GA 30324",
    "addr:housenumber":"2581",
    "addr:postcode":"30324",
    "addr:street":"Piedmont Rd Ne",
    "iso:country":"US",
    "sg:address":"2581 Piedmont Rd NE",
    "sg:city":"Atlanta",
    "sg:phone":"+1 404 231 4431",
    "sg:postcode":"30324",
    "sg:province":"GA",
    "wof:name":"Ivan Kosky Inc",
    "wof:placetype":"venue"
},
  "geometry": {"coordinates":[-84.367182,33.825268],"type":"Point"}
}