{
  "type": "Feature",
  "properties": {
    "addr:full":"4171 Raphael St SW Covington GA 30014",
    "addr:housenumber":"4171",
    "addr:postcode":"30014",
    "addr:street":"Raphael St Sw",
    "iso:country":"US",
    "sg:address":"4171 Raphael St SW",
    "sg:city":"Covington",
    "sg:classifiers":[
        {
            "category":"Coffee & Tea",
            "type":"Food & Drink"
        },
        {
            "category":"Restaurant",
            "type":"Food & Drink"
        }
    ],
    "sg:phone":"+1 678 625 0000",
    "sg:postcode":"30014",
    "sg:province":"GA",
    "sg:tags":[
        "shop",
        "espresso"
    ],
    "wof:name":"Town Center Breads Coffee House",
    "wof:placetype":"venue"
},
  "geometry": {"coordinates":[-83.87158100000001,33.59564],"type":"Point"}
}