{
  "type": "Feature",
  "properties": {
    "iso:country":"US",
    "sg:address":"1000 Cumberland Mall",
    "sg:city":"Atlanta",
    "sg:classifiers":[
        {
            "category":"Personal",
            "subcategory":"Beauty Salon",
            "type":"Services"
        },
        {
            "category":"Shopping",
            "subcategory":"Beauty & Cosmetics",
            "type":"Retail Goods"
        }
    ],
    "sg:phone":"+1 770 333 9771",
    "sg:postcode":"30339",
    "sg:province":"GA",
    "sg:tags":[
        "hair",
        "supply"
    ],
    "wof:name":"Trade Secret Style Express",
    "wof:placetype":"venue"
},
  "geometry": {"coordinates":[-84.47135900000001,33.879185],"type":"Point"}
}