{
  "type": "Feature",
  "properties": {
    "iso:country":"US",
    "sg:address":"5515 Reston Ct",
    "sg:city":"Atlanta",
    "sg:classifiers":[
        {
            "category":"Professional",
            "subcategory":"Business Services",
            "type":"Services"
        }
    ],
    "sg:phone":"+1 770 394 5404",
    "sg:postcode":"30338",
    "sg:province":"GA",
    "wof:name":"Accountability Group Inc",
    "wof:placetype":"venue"
},
  "geometry": {"coordinates":[-84.327141,33.962079],"type":"Point"}
}