{
  "type": "Feature",
  "properties": {
    "addr:full":"2010 Cobb Pkwy Kennesaw GA 30152",
    "addr:housenumber":"2010",
    "addr:postcode":"30152",
    "addr:street":"Cobb Pkwy",
    "iso:country":"US",
    "sg:address":"2010 Cobb Pkwy",
    "sg:city":"Kennesaw",
    "sg:classifiers":[
        {
            "category":"Restaurant",
            "type":"Food & Drink"
        }
    ],
    "sg:phone":"+1 770 422 3068",
    "sg:postcode":"30152",
    "sg:province":"GA",
    "wof:name":"Captain D's Seafood",
    "wof:placetype":"venue"
},
  "geometry": {"coordinates":[-84.601563,34.003619],"type":"Point"}
}