{
  "type": "Feature",
  "properties": {
    "iso:country":"US",
    "sg:address":"522 Candlewick Ln NW",
    "sg:city":"Lilburn",
    "sg:classifiers":[
        {
            "category":"Professional",
            "subcategory":"Business Services",
            "type":"Services"
        }
    ],
    "sg:phone":"+1 770 564 0193",
    "sg:postcode":"30047",
    "sg:province":"GA",
    "wof:name":"M & P Systems Inc",
    "wof:placetype":"venue"
},
  "geometry": {"coordinates":[-84.16356500000001,33.888805],"type":"Point"}
}