{
  "type": "Feature",
  "properties": {
    "addr:full":"1603 Whitesville St Lagrange GA 30240",
    "addr:housenumber":"1603",
    "addr:postcode":"30240",
    "addr:street":"Whitesville St",
    "iso:country":"US",
    "sg:address":"1603 Whitesville St",
    "sg:city":"Lagrange",
    "sg:classifiers":[
        {
            "category":"Communications",
            "type":"Services"
        }
    ],
    "sg:phone":"+1 706 845 6970",
    "sg:postcode":"30240",
    "sg:province":"GA",
    "sg:tags":[
        "internet"
    ],
    "sg:website":"www.tcvs.com",
    "wof:name":"True Color Video Systems",
    "wof:placetype":"venue"
},
  "geometry": {"coordinates":[-85.028983,33.012951],"type":"Point"}
}