{
  "type": "Feature",
  "properties": {
    "addr:full":"9754 State Rte 74 Macon GA 31220",
    "addr:housenumber":"9754",
    "addr:postcode":"31220",
    "addr:street":"State Rte 74",
    "iso:country":"US",
    "sg:address":"9754 State Rte 74",
    "sg:city":"Macon",
    "sg:classifiers":[
        {
            "category":"Organizations",
            "subcategory":"Religious Organization",
            "type":"Services"
        }
    ],
    "sg:phone":"+1 478 935 9958",
    "sg:postcode":"31220",
    "sg:province":"GA",
    "sg:tags":[
        "church"
    ],
    "wof:name":"Little Rogers CME Church",
    "wof:placetype":"venue"
},
  "geometry": {"coordinates":[-83.87827,32.865013],"type":"Point"}
}