{
  "type": "Feature",
  "properties": {
    "addr:full":"3029 Huffaker Rd NW Rome GA 30165",
    "addr:housenumber":"3029",
    "addr:postcode":"ga 30165",
    "addr:street":"Huffaker Rd Nw",
    "iso:country":"US",
    "sg:address":"3029 Huffaker Rd NW",
    "sg:city":"Rome",
    "sg:classifiers":[
        {
            "category":"Food & Beverages",
            "subcategory":"Groceries & Convenience Stores",
            "type":"Retail Goods"
        }
    ],
    "sg:phone":"+1 706 232 6198",
    "sg:postcode":"30165",
    "sg:province":"GA",
    "wof:name":"Rhondas Shopette 6",
    "wof:placetype":"venue"
},
  "geometry": {"coordinates":[-85.324207,34.298928],"type":"Point"}
}