{
  "type": "Feature",
  "properties": {
    "iso:country":"US",
    "sg:address":"1439 Old Salem Rd SE",
    "sg:city":"Conyers",
    "sg:classifiers":[
        {
            "category":"Real Estate",
            "subcategory":"Real Estate Operator",
            "type":"Services"
        }
    ],
    "sg:phone":"+1 770 490 9656",
    "sg:postcode":"30013",
    "sg:province":"GA",
    "sg:tags":[
        "building",
        "nonresidential"
    ],
    "wof:name":"Astrin Properties",
    "wof:placetype":"venue"
},
  "geometry": {"coordinates":[-84.002487,33.646481],"type":"Point"}
}