{
  "type": "Feature",
  "properties": {
    "iso:country":"US",
    "sg:address":"1220 Dekalb Ave NE",
    "sg:city":"Atlanta",
    "sg:classifiers":[
        {
            "category":"Professional",
            "type":"Services"
        }
    ],
    "sg:phone":"+1 404 222 0032",
    "sg:postcode":"30307",
    "sg:province":"GA",
    "sg:tags":[
        "establishment"
    ],
    "wof:name":"Brenda's Simply Unique",
    "wof:placetype":"venue"
},
  "geometry": {"coordinates":[-84.34727100000001,33.760835],"type":"Point"}
}