{
  "type": "Feature",
  "properties": {
    "iso:country":"US",
    "sg:address":"333 Moose Club Rd",
    "sg:city":"Thomson",
    "sg:classifiers":[
        {
            "category":"Freight",
            "type":"Transportation"
        }
    ],
    "sg:phone":"+1 706 595 8423",
    "sg:postcode":"30824",
    "sg:province":"GA",
    "sg:tags":[
        "local",
        "road",
        "trucking"
    ],
    "wof:name":"L King Trucking Inc",
    "wof:placetype":"venue"
},
  "geometry": {"coordinates":[-82.430097,33.474974],"type":"Point"}
}