{
  "type": "Feature",
  "properties": {
    "iso:country":"US",
    "sg:address":"15 River Ln",
    "sg:city":"Covington",
    "sg:classifiers":[
        {
            "category":"Real Estate",
            "subcategory":"Real Estate Agent",
            "type":"Services"
        }
    ],
    "sg:phone":"+1 678 342 9358",
    "sg:postcode":"30016",
    "sg:province":"GA",
    "wof:name":"Metro Brokers",
    "wof:placetype":"venue"
},
  "geometry": {"coordinates":[-83.980109,33.500315],"type":"Point"}
}