{
  "type": "Feature",
  "properties": {
    "iso:country":"US",
    "sg:address":"282 State Rte 314",
    "sg:city":"Fayetteville",
    "sg:classifiers":[
        {
            "category":"Shopping",
            "subcategory":"Clothing, Apparel, & Fashions",
            "type":"Retail Goods"
        }
    ],
    "sg:phone":"+1 770 461 4818",
    "sg:postcode":"30214",
    "sg:province":"GA",
    "sg:tags":[
        "shop",
        "tuxedo",
        "bridal",
        "rental"
    ],
    "sg:website":"www.belles-beaus.com",
    "wof:name":"Belles & Beaus Bridal & Formal",
    "wof:placetype":"venue"
},
  "geometry": {"coordinates":[-84.449669,33.473438],"type":"Point"}
}