{
  "type": "Feature",
  "properties": {
    "addr:full":"1977 S Cobb Dr Marietta GA 30060",
    "addr:housenumber":"1977",
    "addr:postcode":"30060",
    "addr:street":"S Cobb Dr",
    "iso:country":"US",
    "sg:address":"1977 S Cobb Dr",
    "sg:city":"Marietta",
    "sg:classifiers":[
        {
            "category":"Shopping",
            "subcategory":"Used Merchandise",
            "type":"Retail Goods"
        }
    ],
    "sg:phone":"+1 770 433 3322",
    "sg:postcode":"30060",
    "sg:province":"GA",
    "sg:tags":[
        "shop",
        "clothing",
        "thrift"
    ],
    "sg:website":"www.lastchance.com",
    "wof:name":"Last Chance Thrift Store",
    "wof:placetype":"venue"
},
  "geometry": {"coordinates":[-84.543052,33.906885],"type":"Point"}
}