{
  "type": "Feature",
  "properties": {
    "addr:full":"121 Linden Ave NE Atlanta GA 30308",
    "addr:housenumber":"121",
    "addr:postcode":"30308",
    "addr:street":"Linden Ave Ne",
    "iso:country":"US",
    "sg:address":"121 Linden Ave NE",
    "sg:city":"Atlanta",
    "sg:classifiers":[
        {
            "category":"Building & Trades",
            "subcategory":"Construction",
            "type":"Services"
        }
    ],
    "sg:phone":"+1 404 875 7900",
    "sg:postcode":"30308",
    "sg:province":"GA",
    "sg:tags":[
        "general",
        "contractor"
    ],
    "wof:name":"Linden Construction Co Inc",
    "wof:placetype":"venue"
},
  "geometry": {"coordinates":[-84.383596,33.769764],"type":"Point"}
}