{
  "type": "Feature",
  "properties": {
    "iso:country":"US",
    "sg:address":"3641 Chattanooga Rd",
    "sg:city":"Tunnel Hill",
    "sg:classifiers":[
        {
            "category":"Retail",
            "subcategory":"Auto Repair",
            "type":"Services"
        }
    ],
    "sg:phone":"+1 706 673 5650",
    "sg:postcode":"30755",
    "sg:province":"GA",
    "sg:tags":[
        "repairing",
        "automobile"
    ],
    "wof:name":"Whitfield Tire & Svc Ctr",
    "wof:placetype":"venue"
},
  "geometry": {"coordinates":[-85.04803800000001,34.845923],"type":"Point"}
}