{
  "type": "Feature",
  "properties": {
    "addr:full":"7129 Hodgson Memorial Dr Savannah GA 31406",
    "addr:housenumber":"7129",
    "addr:postcode":"31406",
    "addr:street":"Hodgson Memorial Dr",
    "iso:country":"US",
    "sg:address":"7129 Hodgson Memorial Dr",
    "sg:city":"Savannah",
    "sg:classifiers":[
        {
            "category":"Restaurant",
            "type":"Food & Drink"
        }
    ],
    "sg:phone":"+1 912 356 3388",
    "sg:postcode":"31406",
    "sg:province":"GA",
    "wof:name":"Omelette House",
    "wof:placetype":"venue"
},
  "geometry": {"coordinates":[-81.110254,32.005768],"type":"Point"}
}