{
  "type": "Feature",
  "properties": {
    "addr:full":"707 Whitlock Ave SW Marietta GA 30064",
    "addr:housenumber":"707",
    "addr:postcode":"30064",
    "addr:street":"Whitlock Ave Sw",
    "iso:country":"US",
    "sg:address":"707 Whitlock Ave SW",
    "sg:city":"Marietta",
    "sg:classifiers":[
        {
            "category":"Professional",
            "subcategory":"Lawyer & Legal Services",
            "type":"Services"
        }
    ],
    "sg:phone":"+1 770 426 8770",
    "sg:postcode":"30064",
    "sg:province":"GA",
    "wof:name":"Bang Interactive Inc",
    "wof:placetype":"venue"
},
  "geometry": {"coordinates":[-84.577974,33.952231],"type":"Point"}
}