{
  "type": "Feature",
  "properties": {
    "addr:full":"4 Stephenson Ave Savannah GA 31405",
    "addr:housenumber":"4",
    "addr:postcode":"31405",
    "addr:street":"Stephenson Ave",
    "iso:country":"US",
    "sg:address":"4 Stephenson Ave",
    "sg:city":"Savannah",
    "sg:classifiers":[
        {
            "category":"Travel",
            "subcategory":"Hotels & Motels",
            "type":"Entertainment"
        }
    ],
    "sg:phone":"+1 912 964 1224",
    "sg:postcode":"31405",
    "sg:province":"GA",
    "wof:name":"Hawthorn Suites Hotel",
    "wof:placetype":"venue"
},
  "geometry": {"coordinates":[-81.113282,32.013822],"type":"Point"}
}