{
  "type": "Feature",
  "properties": {
    "iso:country":"US",
    "sg:address":"275 Barnes Rd",
    "sg:city":"Waco",
    "sg:classifiers":[
        {
            "category":"Building & Trades",
            "subcategory":"Construction",
            "type":"Services"
        }
    ],
    "sg:phone":"+1 770 836 8470",
    "sg:postcode":"30182",
    "sg:province":"GA",
    "sg:tags":[
        "contractor"
    ],
    "wof:name":"Thompson Pools",
    "wof:placetype":"venue"
},
  "geometry": {"coordinates":[-85.219633,33.643768],"type":"Point"}
}