{
  "type": "Feature",
  "properties": {
    "addr:full":"1798 Montreal Rd Tucker GA 30084",
    "addr:housenumber":"1798",
    "addr:postcode":"30084",
    "addr:street":"Montreal Rd",
    "iso:country":"US",
    "sg:address":"1798 Montreal Rd",
    "sg:city":"Tucker",
    "sg:classifiers":[
        {
            "category":"Professional",
            "subcategory":"Computer Services",
            "type":"Services"
        }
    ],
    "sg:phone":"+1 678 382 0500",
    "sg:postcode":"30084",
    "sg:province":"GA",
    "sg:tags":[
        "web",
        "design",
        "page"
    ],
    "wof:name":"Enginegrafix",
    "wof:placetype":"venue"
},
  "geometry": {"coordinates":[-84.2569,33.835333],"type":"Point"}
}