{
  "type": "Feature",
  "properties": {
    "addr:full":"1501 O'Kelley Ln Albany GA 31707",
    "addr:housenumber":"1501",
    "addr:postcode":"31707",
    "addr:street":"O'Kelley Ln",
    "iso:country":"US",
    "sg:address":"1501 O'Kelley Ln",
    "sg:city":"Albany",
    "sg:phone":"+1 229 432 7400",
    "sg:postcode":"31707",
    "sg:province":"GA",
    "sg:tags":[
        "agricultural",
        "product"
    ],
    "wof:name":"Triangle Chemical Co",
    "wof:placetype":"venue"
},
  "geometry": {"coordinates":[-84.182121,31.609766],"type":"Point"}
}