{
  "type": "Feature",
  "properties": {
    "iso:country":"US",
    "sg:address":"3290 Carriage Way",
    "sg:city":"Marietta",
    "sg:classifiers":[
        {
            "category":"Professional",
            "subcategory":"Management & Consulting",
            "type":"Services"
        }
    ],
    "sg:phone":"+1 770 587 4543",
    "sg:postcode":"30062",
    "sg:province":"GA",
    "sg:tags":[
        "business"
    ],
    "wof:name":"Avc Consulting LLC",
    "wof:placetype":"venue"
},
  "geometry": {"coordinates":[-84.435196,34.028864],"type":"Point"}
}