{
  "type": "Feature",
  "properties": {
    "addr:full":"7053 Grinder Ct Austell GA 30168",
    "addr:postcode":"7053;30168",
    "addr:street":"Ct",
    "iso:country":"US",
    "sg:address":"7053 Grinder Ct",
    "sg:city":"Austell",
    "sg:classifiers":[
        {
            "category":"Professional",
            "subcategory":"Art Services",
            "type":"Services"
        }
    ],
    "sg:phone":"+1 770 819 8032",
    "sg:postcode":"30168",
    "sg:province":"GA",
    "sg:tags":[
        "commercial",
        "design"
    ],
    "wof:name":"Ro Design",
    "wof:placetype":"venue"
},
  "geometry": {"coordinates":[-84.59480600000001,33.783926],"type":"Point"}
}