{
  "type": "Feature",
  "properties": {
    "addr:full":"5414 Five Forks Trickum Rd SW Lilburn GA 30047",
    "addr:housenumber":"5414",
    "addr:postcode":"30047",
    "addr:street":"Five Forks Trickum Rd Sw",
    "iso:country":"US",
    "sg:address":"5414 Five Forks Trickum Rd SW",
    "sg:city":"Lilburn",
    "sg:classifiers":[
        {
            "category":"Food & Beverages",
            "subcategory":"Groceries & Convenience Stores",
            "type":"Retail Goods"
        }
    ],
    "sg:phone":"+1 770 925 0649",
    "sg:postcode":"30047",
    "sg:province":"GA",
    "wof:name":"Shell",
    "wof:placetype":"venue"
},
  "geometry": {"coordinates":[-84.130619,33.841036],"type":"Point"}
}