{
  "type": "Feature",
  "properties": {
    "addr:full":"1720 Pinehurst View Dr Grayson GA 30017",
    "addr:housenumber":"1720",
    "addr:postcode":"30017",
    "addr:street":"Pinehurst View Dr",
    "iso:country":"US",
    "sg:address":"1720 Pinehurst View Dr",
    "sg:city":"Grayson",
    "sg:classifiers":[
        {
            "category":"Building & Trades",
            "subcategory":"Construction",
            "type":"Services"
        }
    ],
    "sg:phone":"+1 678 344 1530",
    "sg:postcode":"30017",
    "sg:province":"GA",
    "wof:name":"Advance Network Communications",
    "wof:placetype":"venue"
},
  "geometry": {"coordinates":[-83.985587,33.891156],"type":"Point"}
}