{
  "type": "Feature",
  "properties": {
    "addr:full":"2111 Atkinson Rd Lawrenceville GA 30043",
    "addr:housenumber":"2111",
    "addr:postcode":"30043",
    "addr:street":"Atkinson Rd",
    "iso:country":"US",
    "sg:address":"2111 Atkinson Rd",
    "sg:city":"Lawrenceville",
    "sg:classifiers":[
        {
            "category":"Shopping",
            "subcategory":"Clothing, Apparel, & Fashions",
            "type":"Retail Goods"
        }
    ],
    "sg:phone":"+1 678 855 5375",
    "sg:postcode":"30043",
    "sg:province":"GA",
    "wof:name":"Reginald Retail Stors",
    "wof:placetype":"venue"
},
  "geometry": {"coordinates":[-84.079165,33.977196],"type":"Point"}
}