{
  "type": "Feature",
  "properties": {
    "iso:country":"US",
    "sg:address":"203 Kentwood Dr",
    "sg:city":"Peachtree City",
    "sg:classifiers":[
        {
            "category":"Professional",
            "type":"Services"
        }
    ],
    "sg:phone":"+1 678 364 8588",
    "sg:postcode":"30269",
    "sg:province":"GA",
    "wof:name":"Expection Children Service",
    "wof:placetype":"venue"
},
  "geometry": {"coordinates":[-84.53532,33.349515],"type":"Point"}
}