{
  "type": "Feature",
  "properties": {
    "iso:country":"US",
    "sg:address":"3101 E Walnut Ave",
    "sg:city":"Dalton",
    "sg:classifiers":[
        {
            "category":"Autos & Motor Vehicles",
            "subcategory":"Automobile Sales",
            "type":"Retail Goods"
        }
    ],
    "sg:phone":"+1 706 226 6595",
    "sg:postcode":"30721",
    "sg:province":"GA",
    "sg:tags":[
        "car",
        "used",
        "dealer"
    ],
    "wof:name":"Carpet Capitol Auto Sales Inc",
    "wof:placetype":"venue"
},
  "geometry": {"coordinates":[-84.918192,34.776249],"type":"Point"}
}