{
  "type": "Feature",
  "properties": {
    "iso:country":"US",
    "sg:address":"5180 Roswell Rd South Bldg, Ste 45",
    "sg:city":"Atlanta",
    "sg:classifiers":[
        {
            "category":"Health Services",
            "subcategory":"Clinic",
            "type":"Services"
        }
    ],
    "sg:phone":"+1 404 303 7979",
    "sg:postcode":"30342",
    "sg:province":"GA",
    "sg:tags":[
        "spa",
        "medical"
    ],
    "sg:website":"www.mesoatlanta.com",
    "wof:name":"The Mesotherapy Center",
    "wof:placetype":"venue"
},
  "geometry": {"coordinates":[-84.38181299999999,33.896112],"type":"Point"}
}