{
  "type": "Feature",
  "properties": {
    "iso:country":"US",
    "sg:address":"1087 Double Bridges Rd",
    "sg:city":"Winder",
    "sg:classifiers":[
        {
            "category":"Building & Trades",
            "subcategory":"Construction",
            "type":"Services"
        }
    ],
    "sg:phone":"+1 770 294 1646",
    "sg:postcode":"30680",
    "sg:province":"GA",
    "wof:name":"Sb Grading Inc",
    "wof:placetype":"venue"
},
  "geometry": {"coordinates":[-83.61020499999999,34.025372],"type":"Point"}
}