{
  "type": "Feature",
  "properties": {
    "iso:country":"US",
    "sg:address":"2601 Dawson Rd",
    "sg:city":"Albany",
    "sg:classifiers":[
        {
            "category":"Shopping",
            "subcategory":"Clothing, Apparel, & Fashions",
            "type":"Retail Goods"
        }
    ],
    "sg:phone":"+1 229 446 9688",
    "sg:postcode":"31707",
    "sg:province":"GA",
    "sg:tags":[
        "girls'",
        "clothing",
        "family"
    ],
    "sg:website":"http://www.gap.com",
    "wof:name":"Gap",
    "wof:placetype":"venue"
},
  "geometry": {"coordinates":[-84.217106,31.614355],"type":"Point"}
}