{
  "type": "Feature",
  "properties": {
    "addr:full":"113 S Perry St Lawrenceville GA 30045",
    "addr:housenumber":"113",
    "addr:postcode":"30045",
    "addr:street":"S Perry St",
    "iso:country":"US",
    "sg:address":"113 S Perry St",
    "sg:city":"Lawrenceville",
    "sg:classifiers":[
        {
            "category":"Health Services",
            "subcategory":"Clinic",
            "type":"Services"
        }
    ],
    "sg:phone":"+1 678 377 1642",
    "sg:postcode":"30045",
    "sg:province":"GA",
    "sg:tags":[
        "home"
    ],
    "wof:name":"Comfort Keepers",
    "wof:placetype":"venue"
},
  "geometry": {"coordinates":[-83.98909399999999,33.951602],"type":"Point"}
}