{
  "type": "Feature",
  "properties": {
    "addr:full":"7530 Highway 85 Riverdale GA 30274",
    "addr:housenumber":"7530",
    "addr:postcode":"30274",
    "addr:street":"Highway 85",
    "iso:country":"US",
    "sg:address":"7530 Highway 85",
    "sg:city":"Riverdale",
    "sg:classifiers":[
        {
            "category":"Retail",
            "subcategory":"Emissions Testing",
            "type":"Services"
        }
    ],
    "sg:phone":"+1 770 472 6198",
    "sg:postcode":"30274",
    "sg:province":"GA",
    "sg:tags":[
        "inspection"
    ],
    "wof:name":"Emissions To Go",
    "wof:placetype":"venue"
},
  "geometry": {"coordinates":[-84.41470700000001,33.549237],"type":"Point"}
}