{
  "type": "Feature",
  "properties": {
    "addr:full":"5058 Halcyondale Rd Sylvania GA 30467",
    "addr:housenumber":"5058",
    "addr:postcode":"30467",
    "addr:street":"Halcyondale Rd",
    "iso:country":"US",
    "sg:address":"5058 Halcyondale Rd",
    "sg:city":"Sylvania",
    "sg:classifiers":[
        {
            "category":"Building & Trades",
            "subcategory":"Landscaping Services",
            "type":"Services"
        }
    ],
    "sg:phone":"+1 912 857 4787",
    "sg:postcode":"30467",
    "sg:province":"GA",
    "sg:tags":[
        "lawn",
        "maintenance",
        "grounds"
    ],
    "wof:name":"Keep Off The Grass Inc",
    "wof:placetype":"venue"
},
  "geometry": {"coordinates":[-81.598907,32.625883],"type":"Point"}
}