{
  "type": "Feature",
  "properties": {
    "iso:country":"US",
    "sg:address":"120 Andrew Dr",
    "sg:city":"Stockbridge",
    "sg:classifiers":[
        {
            "category":"Wholesale",
            "subcategory":"Electrical",
            "type":"Manufacturing & Wholesale Goods"
        }
    ],
    "sg:phone":"+1 770 389 6683",
    "sg:postcode":"30281",
    "sg:province":"GA",
    "sg:tags":[
        "equipment"
    ],
    "wof:name":"Wl Akin",
    "wof:placetype":"venue"
},
  "geometry": {"coordinates":[-84.232957,33.499587],"type":"Point"}
}