{
  "type": "Feature",
  "properties": {
    "addr:full":"2601 Limestone Pkwy Gainesville GA 30501",
    "addr:housenumber":"2601",
    "addr:postcode":"30501",
    "addr:street":"Limestone Pkwy",
    "iso:country":"US",
    "sg:address":"2601 Limestone Pkwy",
    "sg:city":"Gainesville",
    "sg:classifiers":[
        {
            "category":"Banks & Credit Unions",
            "subcategory":"Bank",
            "type":"Services"
        }
    ],
    "sg:phone":"+1 770 534 4255",
    "sg:postcode":"30501",
    "sg:province":"GA",
    "sg:website":"www.hallcocu.org",
    "wof:name":"Hallco Federal Credit Union",
    "wof:placetype":"venue"
},
  "geometry": {"coordinates":[-83.80883799999999,34.332321],"type":"Point"}
}