{
  "type": "Feature",
  "properties": {
    "addr:full":"5090 Dawsonville Hwy Gainesville GA 30506",
    "addr:housenumber":"5090",
    "addr:postcode":"30506",
    "addr:street":"Dawsonville Hwy",
    "iso:country":"US",
    "sg:address":"5090 Dawsonville Hwy",
    "sg:city":"Gainesville",
    "sg:classifiers":[
        {
            "category":"Retail",
            "subcategory":"Auto Repair",
            "type":"Services"
        }
    ],
    "sg:phone":"+1 770 886 8028",
    "sg:postcode":"30506",
    "sg:province":"GA",
    "sg:tags":[
        "body"
    ],
    "wof:name":"Gene S Custom Trim",
    "wof:placetype":"venue"
},
  "geometry": {"coordinates":[-83.99176900000001,34.310727],"type":"Point"}
}