{
  "type": "Feature",
  "properties": {
    "addr:full":"1200 Spring St NW Atlanta GA 30309",
    "addr:housenumber":"1200",
    "addr:postcode":"30309",
    "addr:street":"Spring St Nw",
    "iso:country":"US",
    "sg:address":"1200 Spring St NW",
    "sg:city":"Atlanta",
    "sg:classifiers":[
        {
            "category":"Professional",
            "subcategory":"Business Services",
            "type":"Services"
        }
    ],
    "sg:phone":"+1 404 249 9418",
    "sg:postcode":"30309",
    "sg:province":"GA",
    "sg:tags":[
        "recording",
        "studio"
    ],
    "wof:name":"Brannon Productions",
    "wof:placetype":"venue"
},
  "geometry": {"coordinates":[-84.389374,33.789199],"type":"Point"}
}