{
  "type": "Feature",
  "properties": {
    "iso:country":"US",
    "sg:address":"2361 Fowlstown Rd",
    "sg:city":"Bainbridge",
    "sg:classifiers":[
        {
            "category":"Retail",
            "subcategory":"Auto Repair",
            "type":"Services"
        }
    ],
    "sg:phone":"+1 229 246 1315",
    "sg:postcode":"39819",
    "sg:province":"FL",
    "sg:tags":[
        "repairing",
        "automobile",
        "general"
    ],
    "wof:name":"Larry Harrison Auto Service",
    "wof:placetype":"venue"
},
  "geometry": {"coordinates":[-84.572343,30.867431],"type":"Point"}
}