{
  "type": "Feature",
  "properties": {
    "iso:country":"US",
    "sg:address":"1450 Mount Zion Rd",
    "sg:city":"Morrow",
    "sg:classifiers":[
        {
            "category":"Personal",
            "subcategory":"Barber",
            "type":"Services"
        }
    ],
    "sg:phone":"+1 770 968 7212",
    "sg:postcode":"30260",
    "sg:province":"GA",
    "wof:name":"Envious Styles",
    "wof:placetype":"venue"
},
  "geometry": {"coordinates":[-84.34039199999999,33.571561],"type":"Point"}
}