{
  "type": "Feature",
  "properties": {
    "addr:full":"333 Commerce Dr Decatur GA 30030",
    "addr:housenumber":"333",
    "addr:postcode":"30030",
    "addr:street":"Commerce Dr",
    "iso:country":"US",
    "sg:address":"333 Commerce Dr",
    "sg:city":"Decatur",
    "sg:classifiers":[
        {
            "category":"Restaurant",
            "type":"Food & Drink"
        }
    ],
    "sg:phone":"+1 404 370 0551",
    "sg:postcode":"30030",
    "sg:province":"GA",
    "sg:tags":[
        "pizza"
    ],
    "wof:name":"Fellini's Pizza",
    "wof:placetype":"venue"
},
  "geometry": {"coordinates":[-84.291681,33.77516],"type":"Point"}
}