{
  "type": "Feature",
  "properties": {
    "addr:full":"4113 Chickasaw Trl Douglasville GA 30135",
    "addr:housenumber":"4113",
    "addr:postcode":"30135",
    "addr:street":"Chickasaw Trl",
    "iso:country":"US",
    "sg:address":"4113 Chickasaw Trl",
    "sg:city":"Douglasville",
    "sg:classifiers":[
        {
            "category":"Building & Trades",
            "subcategory":"Landscaping Services",
            "type":"Services"
        }
    ],
    "sg:phone":"+1 770 920 4798",
    "sg:postcode":"30135",
    "sg:province":"GA",
    "wof:name":"Edmundo Lawn Service",
    "wof:placetype":"venue"
},
  "geometry": {"coordinates":[-84.693242,33.691804],"type":"Point"}
}