{
  "type": "Feature",
  "properties": {
    "iso:country":"US",
    "sg:address":"4006 Oakstone Dr",
    "sg:city":"Douglasville",
    "sg:classifiers":[
        {
            "category":"Building & Trades",
            "subcategory":"Landscaping Services",
            "type":"Services"
        }
    ],
    "sg:phone":"+1 404 427 7431",
    "sg:postcode":"30135",
    "sg:province":"GA",
    "sg:tags":[
        "landscape"
    ],
    "wof:name":"A & M Landscaping",
    "wof:placetype":"venue"
},
  "geometry": {"coordinates":[-84.705403,33.700266],"type":"Point"}
}