{
  "type": "Feature",
  "properties": {
    "iso:country":"US",
    "sg:address":"1480 Beaver Ruin Rd",
    "sg:city":"Norcross",
    "sg:classifiers":[
        {
            "category":"Personal",
            "subcategory":"Beauty Salon",
            "type":"Services"
        }
    ],
    "sg:phone":"+1 678 924 0048",
    "sg:postcode":"30093",
    "sg:province":"GA",
    "sg:tags":[
        "hair"
    ],
    "wof:name":"Salon 128 At Gwinnett Pavillion",
    "wof:placetype":"venue"
},
  "geometry": {"coordinates":[-84.14516500000001,33.93144],"type":"Point"}
}