{
  "type": "Feature",
  "properties": {
    "addr:full":"5 Concourse Pkwy Ste 3000 Atlanta GA 30314",
    "addr:housenumber":"5",
    "addr:postcode":"30314",
    "addr:street":"Concourse Pkwy Ste 3000",
    "iso:country":"US",
    "sg:address":"5 Concourse Pkwy Ste 3000",
    "sg:city":"Atlanta",
    "sg:classifiers":[
        {
            "category":"Banks & Credit Unions",
            "subcategory":"Financial Services",
            "type":"Services"
        }
    ],
    "sg:phone":"+1 866 540 6882",
    "sg:postcode":"30314",
    "sg:province":"GA",
    "sg:website":"www.trs.us",
    "wof:name":"The Retirement Solution",
    "wof:placetype":"venue"
},
  "geometry": {"coordinates":[-84.351934,33.916407],"type":"Point"}
}