{
  "type": "Feature",
  "properties": {
    "iso:country":"US",
    "sg:address":"223 E US Hwy 80",
    "sg:city":"Pooler",
    "sg:classifiers":[
        {
            "category":"Personal",
            "subcategory":"Beauty Salon",
            "type":"Services"
        }
    ],
    "sg:phone":"+1 912 748 0269",
    "sg:postcode":"31322",
    "sg:province":"GA",
    "sg:tags":[
        "shop"
    ],
    "wof:name":"Cuts Unlimited",
    "wof:placetype":"venue"
},
  "geometry": {"coordinates":[-81.244522,32.114602],"type":"Point"}
}