{
  "type": "Feature",
  "properties": {
    "addr:full":"2005 Veterans Blvd Dublin GA 31021",
    "addr:housenumber":"2005",
    "addr:postcode":"31021",
    "addr:street":"Veterans Blvd",
    "iso:country":"US",
    "sg:address":"2005 Veterans Blvd",
    "sg:city":"Dublin",
    "sg:classifiers":[
        {
            "category":"Government",
            "subcategory":"Office",
            "type":"Public Place"
        }
    ],
    "sg:phone":"+1 478 272 0804",
    "sg:postcode":"31021",
    "sg:province":"GA",
    "sg:tags":[
        "armed",
        "force",
        "recruiting"
    ],
    "wof:name":"US Army Recruiting",
    "wof:placetype":"venue"
},
  "geometry": {"coordinates":[-82.959864,32.543414],"type":"Point"}
}