{
  "type": "Feature",
  "properties": {
    "iso:country":"US",
    "sg:address":"3692 Occidental Ct",
    "sg:city":"Decatur",
    "sg:classifiers":[
        {
            "category":"Professional",
            "subcategory":"Management & Consulting",
            "type":"Services"
        },
        {
            "category":"Education",
            "subcategory":"Special Training",
            "type":"Public Place"
        }
    ],
    "sg:phone":"+1 770 981 3200",
    "sg:postcode":"30034",
    "sg:province":"GA",
    "wof:name":"R Thomas & Associates",
    "wof:placetype":"venue"
},
  "geometry": {"coordinates":[-84.237443,33.672577],"type":"Point"}
}