{
  "type": "Feature",
  "properties": {
    "addr:full":"237 John W Morrow Pkwy Gainesville GA 30501",
    "addr:housenumber":"237",
    "addr:postcode":"30501",
    "addr:street":"John W Morrow Pkwy",
    "iso:country":"US",
    "sg:address":"237 John W Morrow Pkwy",
    "sg:city":"Gainesville",
    "sg:classifiers":[
        {
            "category":"Personal",
            "subcategory":"Beauty Salon",
            "type":"Services"
        }
    ],
    "sg:phone":"+1 770 532 6091",
    "sg:postcode":"30501",
    "sg:province":"GA",
    "sg:tags":[
        "shop"
    ],
    "wof:name":"Hair Unique",
    "wof:placetype":"venue"
},
  "geometry": {"coordinates":[-83.83510099999999,34.29376],"type":"Point"}
}