{
  "type": "Feature",
  "properties": {
    "iso:country":"US",
    "sg:address":"2236 Redmond Cir",
    "sg:city":"Rome",
    "sg:classifiers":[
        {
            "category":"Health Services",
            "subcategory":"Doctor",
            "type":"Services"
        }
    ],
    "sg:phone":"+1 706 295 7385",
    "sg:postcode":"30165",
    "sg:province":"GA",
    "sg:tags":[
        "dentist"
    ],
    "wof:name":"Richard L Muller Jr DDS",
    "wof:placetype":"venue"
},
  "geometry": {"coordinates":[-85.226134,34.281058],"type":"Point"}
}