{
  "type": "Feature",
  "properties": {
    "addr:full":"21 Cathedral Hts Cartersville GA 30120",
    "addr:housenumber":"21",
    "addr:postcode":"30120",
    "addr:street":"Cathedral Hts",
    "iso:country":"US",
    "sg:address":"21 Cathedral Hts",
    "sg:city":"Cartersville",
    "sg:classifiers":[
        {
            "category":"Building & Trades",
            "subcategory":"Construction",
            "type":"Services"
        }
    ],
    "sg:phone":"+1 770 607 0326",
    "sg:postcode":"30120",
    "sg:province":"GA",
    "sg:tags":[
        "house"
    ],
    "wof:name":"Garrett Home Builders",
    "wof:placetype":"venue"
},
  "geometry": {"coordinates":[-84.91095199999999,34.149897],"type":"Point"}
}