{
  "type": "Feature",
  "properties": {
    "iso:country":"US",
    "sg:address":"6023 Sandy Springs Cir NE",
    "sg:city":"Atlanta",
    "sg:classifiers":[
        {
            "category":"Retail",
            "subcategory":"Veterinary Services",
            "type":"Services"
        },
        {
            "category":"Retail",
            "subcategory":"Pet Boarding",
            "type":"Services"
        }
    ],
    "sg:phone":"+1 404 255 8522",
    "sg:postcode":"30328",
    "sg:province":"GA",
    "sg:tags":[
        "veterinarian",
        "specialty",
        "boarding/pet",
        "sitting"
    ],
    "wof:name":"Ahearn Ella L DVM",
    "wof:placetype":"venue"
},
  "geometry": {"coordinates":[-84.384756,33.920228],"type":"Point"}
}