{
  "type": "Feature",
  "properties": {
    "iso:country":"US",
    "sg:address":"692 Puckett Dr",
    "sg:city":"Mableton",
    "sg:classifiers":[
        {
            "category":"Shopping",
            "subcategory":"Books",
            "type":"Retail Goods"
        }
    ],
    "sg:phone":"+1 770 944 3275",
    "sg:postcode":"30126",
    "sg:province":"GA",
    "sg:tags":[
        "dealers-used",
        "rare",
        "store"
    ],
    "wof:name":"Book House",
    "wof:placetype":"venue"
},
  "geometry": {"coordinates":[-84.57443600000001,33.816748],"type":"Point"}
}