{
  "type": "Feature",
  "properties": {
    "iso:country":"US",
    "sg:address":"343 Candlewood Dr",
    "sg:city":"Augusta",
    "sg:classifiers":[
        {
            "category":"Shopping",
            "subcategory":"Gifts & Souvenirs",
            "type":"Retail Goods"
        }
    ],
    "sg:phone":"+1 706 210 5500",
    "sg:postcode":"30907",
    "sg:province":"GA",
    "sg:tags":[
        "shop"
    ],
    "wof:name":"Anytime Gifts",
    "wof:placetype":"venue"
},
  "geometry": {"coordinates":[-82.095767,33.524324],"type":"Point"}
}