{
  "type": "Feature",
  "properties": {
    "iso:country":"US",
    "sg:address":"918 Old Lafayette Rd",
    "sg:city":"Chickamauga",
    "sg:classifiers":[
        {
            "category":"Local Transit",
            "type":"Transportation"
        }
    ],
    "sg:phone":"+1 706 375 3986",
    "sg:postcode":"30707",
    "sg:province":"GA",
    "sg:tags":[
        "public"
    ],
    "wof:name":"Mann, Rj Limousine",
    "wof:placetype":"venue"
},
  "geometry": {"coordinates":[-85.251679,34.840645],"type":"Point"}
}