{
  "type": "Feature",
  "properties": {
    "iso:country":"US",
    "sg:address":"102 N Washington St",
    "sg:city":"Albany",
    "sg:classifiers":[
        {
            "category":"Professional",
            "subcategory":"Management & Consulting",
            "type":"Services"
        }
    ],
    "sg:phone":"+1 229 435 4774",
    "sg:postcode":"31701",
    "sg:province":"GA",
    "sg:tags":[
        "consultant"
    ],
    "wof:name":"Lashley Consulting Co",
    "wof:placetype":"venue"
},
  "geometry": {"coordinates":[-84.151398,31.578414],"type":"Point"}
}