{
  "type": "Feature",
  "properties": {
    "addr:full":"860 W US Hwy 80 Pooler GA 31322",
    "addr:housenumber":"860",
    "addr:postcode":"31322",
    "addr:street":"W Us Hwy 80",
    "iso:country":"US",
    "sg:address":"860 W US Hwy 80",
    "sg:city":"Pooler",
    "sg:classifiers":[
        {
            "category":"Personal",
            "subcategory":"Beauty Salon",
            "type":"Services"
        }
    ],
    "sg:phone":"+1 912 748 9393",
    "sg:postcode":"31322",
    "sg:province":"GA",
    "wof:name":"Hair Gallery",
    "wof:placetype":"venue"
},
  "geometry": {"coordinates":[-81.260695,32.120252],"type":"Point"}
}