{
  "type": "Feature",
  "properties": {
    "addr:full":"1579 Koppers Rd Conley GA 30288",
    "addr:housenumber":"1579",
    "addr:postcode":"30288",
    "addr:street":"Koppers Rd",
    "iso:country":"US",
    "sg:address":"1579 Koppers Rd",
    "sg:city":"Conley",
    "sg:classifiers":[
        {
            "category":"Manufacturing",
            "subcategory":"Chemicals & Compounds",
            "type":"Manufacturing & Wholesale Goods"
        }
    ],
    "sg:phone":"+1 404 363 6300",
    "sg:postcode":"30288",
    "sg:province":"GA",
    "sg:tags":[
        "preparation",
        "mfg"
    ],
    "wof:name":"Arch Wood Protection Inc",
    "wof:placetype":"venue"
},
  "geometry": {"coordinates":[-84.327218,33.663282],"type":"Point"}
}