{
  "type": "Feature",
  "properties": {
    "addr:full":"2101 Tropicana Dr Suwanee GA 30024",
    "addr:housenumber":"2101",
    "addr:postcode":"30024",
    "addr:street":"Tropicana Dr",
    "iso:country":"US",
    "sg:address":"2101 Tropicana Dr",
    "sg:city":"Suwanee",
    "sg:classifiers":[
        {
            "category":"Building & Trades",
            "subcategory":"Plumbing",
            "type":"Services"
        }
    ],
    "sg:phone":"+1 770 682 8161",
    "sg:postcode":"30024",
    "sg:province":"GA",
    "sg:tags":[
        "contractor"
    ],
    "wof:name":"Gwinnett Refrigeration Svcs",
    "wof:placetype":"venue"
},
  "geometry": {"coordinates":[-84.043778,34.002995],"type":"Point"}
}