{
  "type": "Feature",
  "properties": {
    "iso:country":"US",
    "sg:address":"3000 Andora Dr SW",
    "sg:city":"Marietta",
    "sg:classifiers":[
        {
            "category":"Professional",
            "type":"Services"
        }
    ],
    "sg:phone":"+1 770 427 3500",
    "sg:postcode":"30064",
    "sg:province":"GA",
    "sg:tags":[
        "establishment"
    ],
    "wof:name":"Sandy Glen Sub Div",
    "wof:placetype":"venue"
},
  "geometry": {"coordinates":[-84.642296,33.933569],"type":"Point"}
}