{
  "type": "Feature",
  "properties": {
    "addr:full":"200 3rd St Macon GA 31201",
    "addr:housenumber":"200",
    "addr:postcode":"31201",
    "addr:street":"3Rd St",
    "iso:country":"US",
    "sg:address":"200 3rd St",
    "sg:city":"Macon",
    "sg:classifiers":[
        {
            "category":"Government",
            "subcategory":"Jail",
            "type":"Public Place"
        }
    ],
    "sg:phone":"+1 478 751 6092",
    "sg:postcode":"31201",
    "sg:province":"GA",
    "sg:tags":[
        "probation"
    ],
    "wof:name":"Macon Probation Office",
    "wof:placetype":"venue"
},
  "geometry": {"coordinates":[-83.62591999999999,32.837747],"type":"Point"}
}