{
  "type": "Feature",
  "properties": {
    "iso:country":"US",
    "sg:address":"460 Satilla Church Rd",
    "sg:city":"Baxley",
    "sg:classifiers":[
        {
            "category":"Professional",
            "subcategory":"Computer Services",
            "type":"Services"
        }
    ],
    "sg:phone":"+1 912 367 6070",
    "sg:postcode":"31513",
    "sg:province":"GA",
    "sg:tags":[
        "related"
    ],
    "wof:name":"Dynamic Computer Systems",
    "wof:placetype":"venue"
},
  "geometry": {"coordinates":[-82.35010800000001,31.746133],"type":"Point"}
}