{
  "type": "Feature",
  "properties": {
    "iso:country":"US",
    "sg:address":"314 Church St",
    "sg:city":"Decatur",
    "sg:classifiers":[
        {
            "category":"Real Estate",
            "subcategory":"Real Estate Agent",
            "type":"Services"
        }
    ],
    "sg:phone":"+1 404 378 9300",
    "sg:postcode":"30030",
    "sg:province":"GA",
    "wof:name":"Re/Max Executives-Decatur",
    "wof:placetype":"venue"
},
  "geometry": {"coordinates":[-84.294928,33.774305],"type":"Point"}
}