{
  "type": "Feature",
  "properties": {
    "addr:full":"350 Keys Ferry St Mcdonough GA 30253",
    "addr:housenumber":"350",
    "addr:postcode":"30253",
    "addr:street":"Keys Ferry St",
    "iso:country":"US",
    "sg:address":"350 Keys Ferry St",
    "sg:city":"Mcdonough",
    "sg:classifiers":[
        {
            "category":"Restaurant",
            "type":"Food & Drink"
        }
    ],
    "sg:menulink":"http://www.allmenus.com/ga/mcdonough/101704-huddle-house/menu/",
    "sg:phone":"+1 770 898 0670",
    "sg:postcode":"30253",
    "sg:province":"GA",
    "sg:tags":[
        "american",
        "diner"
    ],
    "wof:name":"Huddle House",
    "wof:placetype":"venue"
},
  "geometry": {"coordinates":[-84.136121,33.44691],"type":"Point"}
}