{
  "type": "Feature",
  "properties": {
    "iso:country":"US",
    "sg:address":"515 Denmark St Ste 600",
    "sg:city":"Statesboro",
    "sg:classifiers":[
        {
            "category":"Health Services",
            "subcategory":"Nursing And Care Facility",
            "type":"Services"
        },
        {
            "category":"Health Services",
            "subcategory":"Health Practitioner",
            "type":"Services"
        }
    ],
    "sg:phone":"+1 912 764 9500",
    "sg:postcode":"30458",
    "sg:province":"GA",
    "sg:tags":[
        "home",
        "eldercare-home"
    ],
    "wof:name":"Homebound Services, Inc.",
    "wof:placetype":"venue"
},
  "geometry": {"coordinates":[-81.799408,32.449581],"type":"Point"}
}