{
  "type": "Feature",
  "properties": {
    "iso:country":"US",
    "sg:address":"12 E York St",
    "sg:city":"Savannah",
    "sg:classifiers":[
        {
            "category":"Real Estate",
            "subcategory":"Real Estate Agent",
            "type":"Services"
        }
    ],
    "sg:phone":"+1 912 233 1276",
    "sg:postcode":"31401",
    "sg:province":"GA",
    "wof:name":"David A Byck Realty Co",
    "wof:placetype":"venue"
},
  "geometry": {"coordinates":[-81.09140499999999,32.077309],"type":"Point"}
}