{
  "type": "Feature",
  "properties": {
    "iso:country":"US",
    "sg:address":"1827 Watson Blvd",
    "sg:city":"Warner Robins",
    "sg:classifiers":[
        {
            "category":"Personal",
            "subcategory":"Tanning Parlor",
            "type":"Services"
        },
        {
            "category":"Sports & Exercise",
            "subcategory":"Gym",
            "type":"Entertainment"
        }
    ],
    "sg:phone":"+1 478 329 0200",
    "sg:postcode":"31093",
    "sg:province":"GA",
    "sg:website":"www.goldsgym.com",
    "wof:name":"Edge Fitness",
    "wof:placetype":"venue"
},
  "geometry": {"coordinates":[-83.63780199999999,32.618099],"type":"Point"}
}