{
  "type": "Feature",
  "properties": {
    "iso:country":"US",
    "sg:address":"2065 Resting Creek Dr",
    "sg:city":"Decatur",
    "sg:classifiers":[
        {
            "category":"Restaurant",
            "type":"Food & Drink"
        }
    ],
    "sg:phone":"+1 678 518 7010",
    "sg:postcode":"30035",
    "sg:province":"GA",
    "sg:tags":[
        "caterer"
    ],
    "wof:name":"Agape Catering Inc",
    "wof:placetype":"venue"
},
  "geometry": {"coordinates":[-84.19736,33.729216],"type":"Point"}
}