{
  "type": "Feature",
  "properties": {
    "addr:full":"202 Milton Ave SE Atlanta GA 30315",
    "addr:housenumber":"202",
    "addr:postcode":"30315",
    "addr:street":"Milton Ave Se",
    "iso:country":"US",
    "sg:address":"202 Milton Ave SE",
    "sg:city":"Atlanta",
    "sg:classifiers":[
        {
            "category":"Health Services",
            "subcategory":"Doctor",
            "type":"Services"
        }
    ],
    "sg:phone":"+1 404 624 3564",
    "sg:postcode":"30315",
    "sg:province":"GA",
    "sg:tags":[
        "medical",
        "clinic"
    ],
    "wof:name":"Community Advanced Practice",
    "wof:placetype":"venue"
},
  "geometry": {"coordinates":[-84.38098100000001,33.719968],"type":"Point"}
}