{
  "type": "Feature",
  "properties": {
    "iso:country":"US",
    "sg:address":"663 N Expy",
    "sg:city":"Griffin",
    "sg:classifiers":[
        {
            "category":"Shopping",
            "subcategory":"Gifts & Souvenirs",
            "type":"Retail Goods"
        }
    ],
    "sg:phone":"+1 770 228 8862",
    "sg:postcode":"30223",
    "sg:province":"GA",
    "wof:name":"Stacys",
    "wof:placetype":"venue"
},
  "geometry": {"coordinates":[-84.287391,33.250951],"type":"Point"}
}