{
  "type": "Feature",
  "properties": {
    "addr:full":"175 Alcovy Ind Blvd Dacula GA 30019",
    "addr:housenumber":"175",
    "addr:postcode":"ga 30019",
    "addr:street":"Alcovy Ind Blvd",
    "iso:country":"US",
    "sg:address":"175 Alcovy Ind Blvd",
    "sg:city":"Dacula",
    "sg:classifiers":[
        {
            "category":"Manufacturing",
            "subcategory":"Building Materials",
            "type":"Manufacturing & Wholesale Goods"
        }
    ],
    "sg:phone":"+1 678 407 6900",
    "sg:postcode":"30019",
    "sg:province":"GA",
    "sg:website":"www.weyerhaeuser.com",
    "wof:name":"Weyerhaeuser Co",
    "wof:placetype":"venue"
},
  "geometry": {"coordinates":[-83.931928,33.98199],"type":"Point"}
}