{
  "type": "Feature",
  "properties": {
    "addr:full":"5360 Grassy Pond Rd Lake Park GA 31699",
    "addr:housenumber":"5360",
    "addr:postcode":"31699",
    "addr:street":"Grassy Pond Rd",
    "iso:country":"US",
    "sg:address":"5360 Grassy Pond Rd",
    "sg:city":"Lake Park",
    "sg:classifiers":[
        {
            "category":"Recreation",
            "type":"Entertainment"
        }
    ],
    "sg:phone":"+1 229 559 5840",
    "sg:postcode":"31699",
    "sg:province":"GA",
    "wof:name":"Grassy Pond",
    "wof:placetype":"venue"
},
  "geometry": {"coordinates":[-83.238634,30.65739],"type":"Point"}
}