{
  "type": "Feature",
  "properties": {
    "iso:country":"US",
    "sg:address":"3445 Stratford Rd NE",
    "sg:city":"Atlanta",
    "sg:classifiers":[
        {
            "category":"Real Estate",
            "subcategory":"Real Estate Operator",
            "type":"Services"
        }
    ],
    "sg:phone":"+1 404 846 7100",
    "sg:postcode":"30326",
    "sg:province":"GA",
    "sg:tags":[
        "apartment"
    ],
    "wof:name":"Paramount At Buckhead",
    "wof:placetype":"venue"
},
  "geometry": {"coordinates":[-84.36687499999999,33.849414],"type":"Point"}
}