{
  "type": "Feature",
  "properties": {
    "addr:full":"660 Oxford Crest Ct NW Lawrenceville GA 30043",
    "addr:housenumber":"660",
    "addr:postcode":"30043",
    "addr:street":"Oxford Crest Ct Nw",
    "iso:country":"US",
    "sg:address":"660 Oxford Crest Ct NW",
    "sg:city":"Lawrenceville",
    "sg:classifiers":[
        {
            "category":"Professional",
            "subcategory":"Computer Services",
            "type":"Services"
        }
    ],
    "sg:phone":"+1 770 822 9833",
    "sg:postcode":"30043",
    "sg:province":"GA",
    "wof:name":"Gca Consulting",
    "wof:placetype":"venue"
},
  "geometry": {"coordinates":[-84.02342400000001,33.979826],"type":"Point"}
}