{
  "type": "Feature",
  "properties": {
    "addr:full":"675 Main St Thomson GA 30824",
    "addr:housenumber":"675",
    "addr:postcode":"30824",
    "addr:street":"Main St",
    "iso:country":"US",
    "sg:address":"675 Main St",
    "sg:city":"Thomson",
    "sg:classifiers":[
        {
            "category":"Shopping",
            "subcategory":"Department Store",
            "type":"Retail Goods"
        }
    ],
    "sg:phone":"+1 706 595 6341",
    "sg:postcode":"30824",
    "sg:province":"GA",
    "sg:tags":[
        "shop"
    ],
    "wof:name":"Family Dollar Store",
    "wof:placetype":"venue"
},
  "geometry": {"coordinates":[-82.505433,33.482641],"type":"Point"}
}