{
  "type": "Feature",
  "properties": {
    "iso:country":"US",
    "sg:address":"1721 Lake Rockaway Rd NW",
    "sg:city":"Conyers",
    "sg:classifiers":[
        {
            "category":"Retail",
            "subcategory":"Auto Repair",
            "type":"Services"
        }
    ],
    "sg:phone":"+1 770 483 2096",
    "sg:postcode":"30012",
    "sg:province":"GA",
    "sg:tags":[
        "body"
    ],
    "wof:name":"Complete Mobile Home Service",
    "wof:placetype":"venue"
},
  "geometry": {"coordinates":[-84.068877,33.692032],"type":"Point"}
}