{
  "type": "Feature",
  "properties": {
    "iso:country":"US",
    "sg:address":"489 Mona Ave",
    "sg:city":"Jesup",
    "sg:classifiers":[
        {
            "category":"Professional",
            "type":"Services"
        }
    ],
    "sg:phone":"+1 912 427 8371",
    "sg:postcode":"31545",
    "sg:province":"GA",
    "wof:name":"Duncan Terrell",
    "wof:placetype":"venue"
},
  "geometry": {"coordinates":[-81.967018,31.570452],"type":"Point"}
}