{
  "type": "Feature",
  "properties": {
    "addr:full":"231 Hightower Dr Augusta GA 30907",
    "addr:housenumber":"231",
    "addr:postcode":"30907",
    "addr:street":"Hightower Dr",
    "iso:country":"US",
    "sg:address":"231 Hightower Dr",
    "sg:city":"Augusta",
    "sg:classifiers":[
        {
            "category":"Professional",
            "type":"Services"
        }
    ],
    "sg:phone":"+1 706 863 3319",
    "sg:postcode":"30907",
    "sg:province":"GA",
    "wof:name":"Kathleen P Suggs",
    "wof:placetype":"venue"
},
  "geometry": {"coordinates":[-82.10133500000001,33.51444],"type":"Point"}
}