{
  "type": "Feature",
  "properties": {
    "iso:country":"US",
    "sg:address":"94 Virginia Cir",
    "sg:city":"Cedartown",
    "sg:classifiers":[
        {
            "category":"Professional",
            "subcategory":"Business Services",
            "type":"Services"
        }
    ],
    "sg:phone":"+1 770 748 1830",
    "sg:postcode":"30125",
    "sg:province":"GA",
    "wof:name":"Becky Millican Agency Inc",
    "wof:placetype":"venue"
},
  "geometry": {"coordinates":[-85.242822,34.038876],"type":"Point"}
}