{
  "type": "Feature",
  "properties": {
    "iso:country":"US",
    "sg:address":"1036 Westfield Trce",
    "sg:city":"Smyrna",
    "sg:classifiers":[
        {
            "category":"Building & Trades",
            "subcategory":"Electrical",
            "type":"Services"
        }
    ],
    "sg:phone":"+1 678 488 0202",
    "sg:postcode":"30082",
    "sg:province":"GA",
    "sg:tags":[
        "electrical",
        "contractor"
    ],
    "wof:name":"D C Energy Inc",
    "wof:placetype":"venue"
},
  "geometry": {"coordinates":[-84.538765,33.878734],"type":"Point"}
}