{
  "type": "Feature",
  "properties": {
    "addr:full":"1201 S 1st St E46 Jesup GA 31545",
    "addr:housenumber":"1201;e46",
    "addr:postcode":"31545",
    "addr:street":"S 1St St",
    "iso:country":"US",
    "sg:address":"1201 S 1st St E46",
    "sg:city":"Jesup",
    "sg:classifiers":[
        {
            "category":"Professional",
            "subcategory":"Management & Consulting",
            "type":"Services"
        }
    ],
    "sg:phone":"+1 912 424 0551",
    "sg:postcode":"31545",
    "sg:province":"GA",
    "sg:tags":[
        "consultant"
    ],
    "wof:name":"Taleshia S Williams",
    "wof:placetype":"venue"
},
  "geometry": {"coordinates":[-81.87511499999999,31.616217],"type":"Point"}
}