{
  "type": "Feature",
  "properties": {
    "addr:full":"860 Duluth Hwy Lawrenceville GA 30043",
    "addr:housenumber":"860",
    "addr:postcode":"30043",
    "addr:street":"Duluth Hwy",
    "iso:country":"US",
    "sg:address":"860 Duluth Hwy",
    "sg:city":"Lawrenceville",
    "sg:classifiers":[
        {
            "category":"Cinema",
            "subcategory":"Movie Rental",
            "type":"Entertainment"
        },
        {
            "category":"Shopping",
            "subcategory":"Music",
            "type":"Retail Goods"
        }
    ],
    "sg:phone":"+1 770 963 5710",
    "sg:postcode":"30043",
    "sg:province":"GA",
    "sg:tags":[
        "game",
        "video",
        "dvd's"
    ],
    "wof:name":"Cd Warehouse",
    "wof:placetype":"venue"
},
  "geometry": {"coordinates":[-84.020126,33.967166],"type":"Point"}
}