{
  "type": "Feature",
  "properties": {
    "addr:full":"112 Dixie Dr Woodstock GA 30189",
    "addr:housenumber":"112",
    "addr:postcode":"30189",
    "addr:street":"Dixie Dr",
    "iso:country":"US",
    "sg:address":"112 Dixie Dr",
    "sg:city":"Woodstock",
    "sg:classifiers":[
        {
            "category":"Manufacturing",
            "subcategory":"Retail Goods",
            "type":"Manufacturing & Wholesale Goods"
        }
    ],
    "sg:phone":"+1 678 494 2340",
    "sg:postcode":"30189",
    "sg:province":"GA",
    "sg:tags":[
        "product",
        "mfg"
    ],
    "wof:name":"Auto Source Industries",
    "wof:placetype":"venue"
},
  "geometry": {"coordinates":[-84.563952,34.086673],"type":"Point"}
}