{
  "type": "Feature",
  "properties": {
    "iso:country":"US",
    "sg:address":"1160 Grimes Bridge Rd",
    "sg:city":"Roswell",
    "sg:classifiers":[
        {
            "category":"Professional",
            "subcategory":"Lawyer & Legal Services",
            "type":"Services"
        }
    ],
    "sg:phone":"+1 770 587 3047",
    "sg:postcode":"30075",
    "sg:province":"GA",
    "wof:name":"Marett William W CPA Atty",
    "wof:placetype":"venue"
},
  "geometry": {"coordinates":[-84.342499,34.029999],"type":"Point"}
}