{
  "type": "Feature",
  "properties": {
    "iso:country":"US",
    "sg:address":"5222 N Henry Blvd",
    "sg:city":"Stockbridge",
    "sg:classifiers":[
        {
            "category":"Retail",
            "subcategory":"Laundry & Dry Cleaning",
            "type":"Services"
        }
    ],
    "sg:phone":"+1 770 474 4217",
    "sg:postcode":"30281",
    "sg:province":"GA",
    "sg:tags":[
        "garment",
        "agent"
    ],
    "wof:name":"Henry Cleaners",
    "wof:placetype":"venue"
},
  "geometry": {"coordinates":[-84.24697399999999,33.545662],"type":"Point"}
}