{
  "type": "Feature",
  "properties": {
    "addr:full":"4503 Insdale Ct NW Acworth GA 30101",
    "addr:housenumber":"4503",
    "addr:postcode":"30101",
    "addr:street":"Insdale Ct Nw",
    "iso:country":"US",
    "sg:address":"4503 Insdale Ct NW",
    "sg:city":"Acworth",
    "sg:classifiers":[
        {
            "category":"Health Services",
            "subcategory":"Chiropractor",
            "type":"Services"
        }
    ],
    "sg:phone":"+1 770 966 1386",
    "sg:postcode":"30101",
    "sg:province":"GA",
    "wof:name":"Marietta Injury Center Inc",
    "wof:placetype":"venue"
},
  "geometry": {"coordinates":[-84.61877200000001,34.064254],"type":"Point"}
}