{
  "type": "Feature",
  "properties": {
    "addr:full":"354 Winding Stream Trl SW Conyers GA 30094",
    "addr:housenumber":"354",
    "addr:postcode":"30094",
    "addr:street":"Winding Stream Trl Sw",
    "iso:country":"US",
    "sg:address":"354 Winding Stream Trl SW",
    "sg:city":"Conyers",
    "sg:classifiers":[
        {
            "category":"Communications",
            "subcategory":"Radio Station",
            "type":"Services"
        }
    ],
    "sg:phone":"+1 678 222 8249",
    "sg:postcode":"30094",
    "sg:province":"GA",
    "sg:tags":[
        "education"
    ],
    "wof:name":"Dwight D Frazier",
    "wof:placetype":"venue"
},
  "geometry": {"coordinates":[-84.033958,33.539644],"type":"Point"}
}