{
  "type": "Feature",
  "properties": {
    "addr:full":"414 Victoria Ave Cedartown GA 30125",
    "addr:housenumber":"414",
    "addr:postcode":"30125",
    "addr:street":"Victoria Ave",
    "iso:country":"US",
    "sg:address":"414 Victoria Ave",
    "sg:city":"Cedartown",
    "sg:classifiers":[
        {
            "category":"Recreation",
            "type":"Entertainment"
        }
    ],
    "sg:phone":"+1 770 748 7305",
    "sg:postcode":"30125",
    "sg:province":"GA",
    "wof:name":"Wayne Fortune",
    "wof:placetype":"venue"
},
  "geometry": {"coordinates":[-85.260368,34.017935],"type":"Point"}
}