{
  "type": "Feature",
  "properties": {
    "iso:country":"US",
    "sg:address":"890 N Atlanta St",
    "sg:city":"Roswell",
    "sg:classifiers":[
        {
            "category":"Professional",
            "subcategory":"Computer Services",
            "type":"Services"
        }
    ],
    "sg:phone":"+1 678 521 9487",
    "sg:postcode":"30075",
    "sg:province":"GA",
    "wof:name":"Limedot Web Shop",
    "wof:placetype":"venue"
},
  "geometry": {"coordinates":[-84.361724,34.021931],"type":"Point"}
}