{
  "type": "Feature",
  "properties": {
    "iso:country":"US",
    "sg:address":"438 W Ontario Ave SW",
    "sg:city":"Atlanta",
    "sg:classifiers":[
        {
            "category":"Professional",
            "type":"Services"
        }
    ],
    "sg:phone":"+1 404 755 7127",
    "sg:postcode":"30310",
    "sg:province":"GA",
    "wof:name":"Queens of Mercy",
    "wof:placetype":"venue"
},
  "geometry": {"coordinates":[-84.43966899999999,33.742419],"type":"Point"}
}