{
  "type": "Feature",
  "properties": {
    "iso:country":"US",
    "sg:address":"5062 Pearl Davis Rd",
    "sg:city":"Valdosta",
    "sg:classifiers":[
        {
            "category":"Restaurant",
            "type":"Food & Drink"
        }
    ],
    "sg:phone":"+1 229 245 0227",
    "sg:postcode":"31605",
    "sg:province":"GA",
    "sg:tags":[
        "pizza"
    ],
    "wof:name":"New York Pizza And Sandwich",
    "wof:placetype":"venue"
},
  "geometry": {"coordinates":[-83.238197,30.94453],"type":"Point"}
}