{
  "type": "Feature",
  "properties": {
    "iso:country":"US",
    "sg:address":"745 W Washington Ave",
    "sg:city":"Ashburn",
    "sg:classifiers":[
        {
            "category":"Restaurant",
            "type":"Food & Drink"
        }
    ],
    "sg:menulink":"http://www.allmenus.com/ga/ashburn-sycamore/102393-waffle-house/menu/",
    "sg:phone":"+1 229 567 8732",
    "sg:postcode":"31714",
    "sg:province":"GA",
    "sg:tags":[
        "american"
    ],
    "wof:name":"Waffle House",
    "wof:placetype":"venue"
},
  "geometry": {"coordinates":[-83.66721200000001,31.700816],"type":"Point"}
}