{
  "type": "Feature",
  "properties": {
    "addr:full":"2700 Fleetwood Dr Cumming GA 30041",
    "addr:housenumber":"2700",
    "addr:postcode":"30041",
    "addr:street":"Fleetwood Dr",
    "iso:country":"US",
    "sg:address":"2700 Fleetwood Dr",
    "sg:city":"Cumming",
    "sg:classifiers":[
        {
            "category":"Building & Trades",
            "subcategory":"Plumbing",
            "type":"Services"
        }
    ],
    "sg:phone":"+1 770 886 8385",
    "sg:postcode":"30041",
    "sg:province":"GA",
    "sg:tags":[
        "plumber",
        "industrial",
        "contractors-commercial"
    ],
    "wof:name":"Aab Plumbing",
    "wof:placetype":"venue"
},
  "geometry": {"coordinates":[-84.090121,34.22712],"type":"Point"}
}