{
  "type": "Feature",
  "properties": {
    "addr:full":"281 Twin Oaks Rd Demorest GA 30535",
    "addr:housenumber":"281",
    "addr:postcode":"30535",
    "addr:street":"Twin Oaks Rd",
    "iso:country":"US",
    "sg:address":"281 Twin Oaks Rd",
    "sg:city":"Demorest",
    "sg:classifiers":[
        {
            "category":"Building & Trades",
            "subcategory":"Construction",
            "type":"Services"
        }
    ],
    "sg:phone":"+1 706 754 2250",
    "sg:postcode":"30535",
    "sg:province":"GA",
    "sg:tags":[
        "siding",
        "contractor"
    ],
    "wof:name":"Wheeler Vinyl Siding",
    "wof:placetype":"venue"
},
  "geometry": {"coordinates":[-83.61813600000001,34.602835],"type":"Point"}
}