{
  "type": "Feature",
  "properties": {
    "iso:country":"US",
    "sg:address":"6625 Maid Marion Close",
    "sg:city":"Alpharetta",
    "sg:classifiers":[
        {
            "category":"Professional",
            "subcategory":"Computer Services",
            "type":"Services"
        }
    ],
    "sg:phone":"+1 770 740 9232",
    "sg:postcode":"30005",
    "sg:province":"GA",
    "sg:tags":[
        "related"
    ],
    "wof:name":"Marczyk Consulting Services",
    "wof:placetype":"venue"
},
  "geometry": {"coordinates":[-84.223679,34.068275],"type":"Point"}
}