{
  "type": "Feature",
  "properties": {
    "iso:country":"US",
    "sg:address":"715 2nd Ave",
    "sg:city":"West Point",
    "sg:classifiers":[
        {
            "category":"Personal",
            "subcategory":"Barber",
            "type":"Services"
        }
    ],
    "sg:phone":"+1 706 643 8801",
    "sg:postcode":"31833",
    "sg:province":"GA",
    "sg:tags":[
        "shop"
    ],
    "wof:name":"Jackson's Barber Shop",
    "wof:placetype":"venue"
},
  "geometry": {"coordinates":[-85.183094,32.876867],"type":"Point"}
}