{
  "type": "Feature",
  "properties": {
    "addr:full":"127 Cecily Ct Fortson GA 31808",
    "addr:housenumber":"127",
    "addr:postcode":"31808",
    "addr:street":"Cecily Ct",
    "iso:country":"US",
    "sg:address":"127 Cecily Ct",
    "sg:city":"Fortson",
    "sg:classifiers":[
        {
            "category":"Professional",
            "type":"Services"
        }
    ],
    "sg:phone":"+1 706 321 9482",
    "sg:postcode":"31808",
    "sg:province":"GA",
    "wof:name":"Bradley Schorr",
    "wof:placetype":"venue"
},
  "geometry": {"coordinates":[-85.022206,32.647797],"type":"Point"}
}