{
  "type": "Feature",
  "properties": {
    "addr:full":"1402 Camden Ave Woodbine GA 31569",
    "addr:housenumber":"1402",
    "addr:postcode":"31569",
    "addr:street":"Camden Ave",
    "iso:country":"US",
    "sg:address":"1402 Camden Ave",
    "sg:city":"Woodbine",
    "sg:classifiers":[
        {
            "category":"Organizations",
            "subcategory":"Religious Organization",
            "type":"Services"
        }
    ],
    "sg:phone":"+1 912 576 3121",
    "sg:postcode":"31569",
    "sg:province":"GA",
    "sg:tags":[
        "church"
    ],
    "wof:name":"Camden Ave Church Of God",
    "wof:placetype":"venue"
},
  "geometry": {"coordinates":[-81.719939,30.956922],"type":"Point"}
}