{
  "type": "Feature",
  "properties": {
    "addr:full":"5118 Miller Rd Columbus GA 31909",
    "addr:housenumber":"5118",
    "addr:postcode":"31909",
    "addr:street":"Miller Rd",
    "iso:country":"US",
    "sg:address":"5118 Miller Rd",
    "sg:city":"Columbus",
    "sg:classifiers":[
        {
            "category":"Manufacturing",
            "subcategory":"Glass & Minerals",
            "type":"Manufacturing & Wholesale Goods"
        }
    ],
    "sg:phone":"+1 706 562 1445",
    "sg:postcode":"31909",
    "sg:province":"GA",
    "sg:tags":[
        "ready"
    ],
    "sg:website":"www.rmusa.com",
    "wof:name":"Couch USA",
    "wof:placetype":"venue"
},
  "geometry": {"coordinates":[-84.915891,32.523274],"type":"Point"}
}