{
  "type": "Feature",
  "properties": {
    "iso:country":"US",
    "sg:address":"4867 Oakwood Ct",
    "sg:city":"Loganville",
    "sg:classifiers":[
        {
            "category":"Retail",
            "subcategory":"Repair Shop",
            "type":"Services"
        }
    ],
    "sg:phone":"+1 770 466 6470",
    "sg:postcode":"30052",
    "sg:province":"GA",
    "sg:tags":[
        "merchandise"
    ],
    "wof:name":"Art & Frmng Gallery Loganville",
    "wof:placetype":"venue"
},
  "geometry": {"coordinates":[-83.89532800000001,33.790234],"type":"Point"}
}