{
  "type": "Feature",
  "properties": {
    "iso:country":"US",
    "sg:address":"2048 Old Berlin Rd",
    "sg:city":"Moultrie",
    "sg:classifiers":[
        {
            "category":"Freight",
            "type":"Transportation"
        }
    ],
    "sg:phone":"+1 229 324 2924",
    "sg:postcode":"31788",
    "sg:province":"GA",
    "sg:tags":[
        "operator",
        "local",
        "trucking"
    ],
    "wof:name":"B&T Trucking Inc",
    "wof:placetype":"venue"
},
  "geometry": {"coordinates":[-83.696271,31.081241],"type":"Point"}
}