{
  "type": "Feature",
  "properties": {
    "iso:country":"US",
    "sg:address":"1251 N Hill St",
    "sg:city":"Griffin",
    "sg:classifiers":[
        {
            "category":"Food & Beverages",
            "subcategory":"Groceries & Convenience Stores",
            "type":"Retail Goods"
        }
    ],
    "sg:phone":"+1 770 412 0600",
    "sg:postcode":"30223",
    "sg:province":"GA",
    "wof:name":"Fast Food Market",
    "wof:placetype":"venue"
},
  "geometry": {"coordinates":[-84.261415,33.268344],"type":"Point"}
}