{
  "type": "Feature",
  "properties": {
    "addr:full":"7883 Warm Springs Rd Midland GA 31820",
    "addr:housenumber":"7883",
    "addr:postcode":"31820",
    "addr:street":"Warm Springs Rd",
    "iso:country":"US",
    "sg:address":"7883 Warm Springs Rd",
    "sg:city":"Midland",
    "sg:classifiers":[
        {
            "category":"Building & Trades",
            "subcategory":"Construction",
            "type":"Services"
        }
    ],
    "sg:phone":"+1 706 561 3948",
    "sg:postcode":"31820",
    "sg:province":"GA",
    "sg:tags":[
        "masonry",
        "contractor"
    ],
    "wof:name":"Lampton Mason Hardaway",
    "wof:placetype":"venue"
},
  "geometry": {"coordinates":[-84.861098,32.561034],"type":"Point"}
}