{
  "type": "Feature",
  "properties": {
    "addr:full":"1348 Lakeview Cir Macon GA 31206",
    "addr:housenumber":"1348",
    "addr:postcode":"31206",
    "addr:street":"Lakeview Cir",
    "iso:country":"US",
    "sg:address":"1348 Lakeview Cir",
    "sg:city":"Macon",
    "sg:classifiers":[
        {
            "category":"Professional",
            "subcategory":"Art Services",
            "type":"Services"
        }
    ],
    "sg:phone":"+1 478 788 6715",
    "sg:postcode":"31206",
    "sg:province":"GA",
    "sg:tags":[
        "graphic",
        "design"
    ],
    "wof:name":"Albert Grayer & Associates",
    "wof:placetype":"venue"
},
  "geometry": {"coordinates":[-83.663341,32.794866],"type":"Point"}
}