{
  "type": "Feature",
  "properties": {
    "iso:country":"US",
    "sg:address":"2840 Eva Lee Ct",
    "sg:city":"Marietta",
    "sg:classifiers":[
        {
            "category":"Building & Trades",
            "subcategory":"Construction",
            "type":"Services"
        }
    ],
    "sg:phone":"+1 678 283 0089",
    "sg:postcode":"30062",
    "sg:province":"GA",
    "sg:tags":[
        "house"
    ],
    "wof:name":"Crd Construction Inc",
    "wof:placetype":"venue"
},
  "geometry": {"coordinates":[-84.469813,34.022796],"type":"Point"}
}