{
  "type": "Feature",
  "properties": {
    "addr:full":"1934 N Druid Hills Rd NE Atlanta GA 30319",
    "addr:housenumber":"1934",
    "addr:postcode":"30319",
    "addr:street":"N Druid Hills Rd Ne",
    "iso:country":"US",
    "sg:address":"1934 N Druid Hills Rd NE",
    "sg:city":"Atlanta",
    "sg:classifiers":[
        {
            "category":"Professional",
            "subcategory":"Lawyer & Legal Services",
            "type":"Services"
        }
    ],
    "sg:phone":"+1 404 486 1166",
    "sg:postcode":"30319",
    "sg:province":"GA",
    "wof:name":"Ditrapano Law Firm",
    "wof:placetype":"venue"
},
  "geometry": {"coordinates":[-84.341427,33.834836],"type":"Point"}
}