{
  "type": "Feature",
  "properties": {
    "iso:country":"US",
    "sg:address":"5641 US Hwy 129",
    "sg:city":"Pendergrass",
    "sg:classifiers":[
        {
            "category":"Banks & Credit Unions",
            "subcategory":"Bank",
            "type":"Services"
        }
    ],
    "sg:phone":"+1 706 693 2758",
    "sg:postcode":"30567",
    "sg:province":"GA",
    "sg:tags":[
        "loan",
        "real estate"
    ],
    "wof:name":"Family First Mortgage",
    "wof:placetype":"venue"
},
  "geometry": {"coordinates":[-83.67953799999999,34.163655],"type":"Point"}
}