{
  "type": "Feature",
  "properties": {
    "addr:full":"3208 Canton Rd Marietta GA 30066",
    "addr:housenumber":"3208",
    "addr:postcode":"30066",
    "addr:street":"Canton Rd",
    "iso:country":"US",
    "sg:address":"3208 Canton Rd",
    "sg:city":"Marietta",
    "sg:classifiers":[
        {
            "category":"Shopping",
            "subcategory":"Pawn Shop",
            "type":"Retail Goods"
        }
    ],
    "sg:phone":"+1 770 420 3310",
    "sg:postcode":"30066",
    "sg:province":"GA",
    "sg:website":"www.justcashonline.com",
    "wof:name":"Just Cash",
    "wof:placetype":"venue"
},
  "geometry": {"coordinates":[-84.52767,34.029833],"type":"Point"}
}