{
  "type": "Feature",
  "properties": {
    "addr:full":"350 Beverly St Hinesville GA 31313",
    "addr:housenumber":"350",
    "addr:postcode":"31313",
    "addr:street":"Beverly St",
    "iso:country":"US",
    "sg:address":"350 Beverly St",
    "sg:city":"Hinesville",
    "sg:classifiers":[
        {
            "category":"Real Estate",
            "subcategory":"Real Estate Agent",
            "type":"Services"
        }
    ],
    "sg:phone":"+1 912 876 2319",
    "sg:postcode":"31313",
    "sg:province":"GA",
    "wof:name":"Stewart Pines Condominiums",
    "wof:placetype":"venue"
},
  "geometry": {"coordinates":[-81.604336,31.854213],"type":"Point"}
}