{
  "type": "Feature",
  "properties": {
    "iso:country":"US",
    "sg:address":"120 E Byp NE",
    "sg:city":"Moultrie",
    "sg:classifiers":[
        {
            "category":"Government",
            "subcategory":"Office",
            "type":"Public Place"
        }
    ],
    "sg:phone":"+1 229 891 7130",
    "sg:postcode":"31788",
    "sg:province":"GA",
    "sg:tags":[
        "state",
        "program"
    ],
    "wof:name":"Transportation Dept",
    "wof:placetype":"venue"
},
  "geometry": {"coordinates":[-83.76155799999999,31.177129],"type":"Point"}
}