{
  "type": "Feature",
  "properties": {
    "addr:full":"35 Wake Dr Stockbridge GA 30281",
    "addr:housenumber":"35",
    "addr:postcode":"30281",
    "addr:street":"Wake Dr",
    "iso:country":"US",
    "sg:address":"35 Wake Dr",
    "sg:city":"Stockbridge",
    "sg:classifiers":[
        {
            "category":"Professional",
            "type":"Services"
        }
    ],
    "sg:phone":"+1 770 474 4137",
    "sg:postcode":"30281",
    "sg:province":"GA",
    "wof:name":"Techonicarbecca",
    "wof:placetype":"venue"
},
  "geometry": {"coordinates":[-84.19339600000001,33.527281],"type":"Point"}
}