{
  "type": "Feature",
  "properties": {
    "addr:full":"107 Waterbend Dr Milledgeville GA 31061",
    "addr:housenumber":"107",
    "addr:postcode":"31061",
    "addr:street":"Waterbend Dr",
    "iso:country":"US",
    "sg:address":"107 Waterbend Dr",
    "sg:city":"Milledgeville",
    "sg:classifiers":[
        {
            "category":"Professional",
            "subcategory":"Business Services",
            "type":"Services"
        }
    ],
    "sg:phone":"+1 478 452 6894",
    "sg:postcode":"31061",
    "sg:province":"GA",
    "wof:name":"Youngblood D Business",
    "wof:placetype":"venue"
},
  "geometry": {"coordinates":[-83.252815,33.146743],"type":"Point"}
}