{
  "type": "Feature",
  "properties": {
    "addr:full":"5350 Kennedy St Columbus GA 31907",
    "addr:housenumber":"5350",
    "addr:postcode":"31907",
    "addr:street":"Kennedy St",
    "iso:country":"US",
    "sg:address":"5350 Kennedy St",
    "sg:city":"Columbus",
    "sg:classifiers":[
        {
            "category":"Wholesale",
            "subcategory":"Machinery & Supplies",
            "type":"Manufacturing & Wholesale Goods"
        }
    ],
    "sg:phone":"+1 706 689 5200",
    "sg:postcode":"31907",
    "sg:province":"GA",
    "sg:tags":[
        "equipment",
        "establishment"
    ],
    "wof:name":"Smarts TEC Inc",
    "wof:placetype":"venue"
},
  "geometry": {"coordinates":[-84.900176,32.441359],"type":"Point"}
}