{
  "type": "Feature",
  "properties": {
    "addr:full":"4452 Holiday Heights Dr Oakwood GA 30566",
    "addr:housenumber":"4452",
    "addr:postcode":"30566",
    "addr:street":"Holiday Heights Dr",
    "iso:country":"US",
    "sg:address":"4452 Holiday Heights Dr",
    "sg:city":"Oakwood",
    "sg:classifiers":[
        {
            "category":"Real Estate",
            "subcategory":"Real Estate Operator",
            "type":"Services"
        }
    ],
    "sg:phone":"+1 770 536 0207",
    "sg:postcode":"30566",
    "sg:province":"GA",
    "sg:tags":[
        "building",
        "nonresidential"
    ],
    "wof:name":"Bryan Properties",
    "wof:placetype":"venue"
},
  "geometry": {"coordinates":[-83.8934,34.254481],"type":"Point"}
}