{
  "type": "Feature",
  "properties": {
    "iso:country":"US",
    "sg:address":"1413 Allene Ave SW",
    "sg:city":"Atlanta",
    "sg:classifiers":[
        {
            "category":"Building & Trades",
            "subcategory":"Locksmith",
            "type":"Services"
        }
    ],
    "sg:phone":"+1 404 965 0443",
    "sg:postcode":"30310",
    "sg:province":"GA",
    "sg:tags":[
        "key"
    ],
    "wof:name":"A Locksmith A 1-24 Hour",
    "wof:placetype":"venue"
},
  "geometry": {"coordinates":[-84.413014,33.716292],"type":"Point"}
}