{
  "type": "Feature",
  "properties": {
    "iso:country":"US",
    "sg:address":"338 Industrial Blvd",
    "sg:city":"Midway",
    "sg:classifiers":[
        {
            "category":"Shopping",
            "subcategory":"Gifts & Souvenirs",
            "type":"Retail Goods"
        }
    ],
    "sg:phone":"+1 912 884 9727",
    "sg:postcode":"31320",
    "sg:province":"GA",
    "sg:tags":[
        "shop"
    ],
    "sg:website":"http://www.giftwrapcompany.com",
    "wof:name":"Gift Wrap Company, The",
    "wof:placetype":"venue"
},
  "geometry": {"coordinates":[-81.410085,31.794582],"type":"Point"}
}