{
  "type": "Feature",
  "properties": {
    "iso:country":"US",
    "sg:address":"1929 Walthour Rd",
    "sg:city":"Savannah",
    "sg:classifiers":[
        {
            "category":"Restaurant",
            "type":"Food & Drink"
        }
    ],
    "sg:phone":"+1 912 898 2081",
    "sg:postcode":"31410",
    "sg:province":"GA",
    "sg:tags":[
        "eating"
    ],
    "wof:name":"Izzys Ice Cream Jcl Co",
    "wof:placetype":"venue"
},
  "geometry": {"coordinates":[-80.992328,31.981322],"type":"Point"}
}