{
  "type": "Feature",
  "properties": {
    "addr:full":"352 Enterprise Dr Valdosta GA 31601",
    "addr:housenumber":"352",
    "addr:postcode":"31601",
    "addr:street":"Enterprise Dr",
    "iso:country":"US",
    "sg:address":"352 Enterprise Dr",
    "sg:city":"Valdosta",
    "sg:classifiers":[
        {
            "category":"Retail",
            "subcategory":"Repair Shop",
            "type":"Services"
        }
    ],
    "sg:phone":"+1 229 244 4500",
    "sg:postcode":"31601",
    "sg:province":"GA",
    "sg:tags":[
        "air",
        "system",
        "conditioning"
    ],
    "wof:name":"Fresh Air Inc",
    "wof:placetype":"venue"
},
  "geometry": {"coordinates":[-83.313935,30.827558],"type":"Point"}
}