{
  "type": "Feature",
  "properties": {
    "iso:country":"US",
    "sg:address":"2361 Sandy Creek Rd",
    "sg:city":"Madison",
    "sg:classifiers":[
        {
            "category":"Organizations",
            "subcategory":"Religious Organization",
            "type":"Services"
        }
    ],
    "sg:phone":"+1 706 342 4770",
    "sg:postcode":"30650",
    "sg:province":"GA",
    "wof:name":"Holland Springs Baptist Church",
    "wof:placetype":"venue"
},
  "geometry": {"coordinates":[-83.458319,33.655106],"type":"Point"}
}