{
  "type": "Feature",
  "properties": {
    "iso:country":"US",
    "sg:address":"1729 Kinsmon Cove",
    "sg:city":"Marietta",
    "sg:classifiers":[
        {
            "category":"Professional",
            "subcategory":"Business Services",
            "type":"Services"
        }
    ],
    "sg:phone":"+1 678 461 5645",
    "sg:postcode":"30062",
    "sg:province":"GA",
    "wof:name":"Auto Finance Solutions",
    "wof:placetype":"venue"
},
  "geometry": {"coordinates":[-84.421086,33.989661],"type":"Point"}
}