{
  "type": "Feature",
  "properties": {
    "addr:full":"3015 Peach Orchard Rd Augusta GA 30906",
    "addr:housenumber":"3015",
    "addr:postcode":"30906",
    "addr:street":"Peach Orchard Rd",
    "iso:country":"US",
    "sg:address":"3015 Peach Orchard Rd",
    "sg:city":"Augusta",
    "sg:classifiers":[
        {
            "category":"Place Of Worship",
            "subcategory":"Church",
            "type":"Public Place"
        },
        {
            "category":"Place Of Worship",
            "type":"Public Place"
        }
    ],
    "sg:phone":"+1 706 790 6149",
    "sg:postcode":"30906",
    "sg:province":"GA",
    "sg:tags":[
        "churches-non-denominational"
    ],
    "wof:name":"New Beginning Flowship Dream Center Apostle Julia & Pastor Judge Mckinley",
    "wof:placetype":"venue"
},
  "geometry": {"coordinates":[-82.024683,33.414603],"type":"Point"}
}