{
  "type": "Feature",
  "properties": {
    "iso:country":"US",
    "sg:address":"3572 Community Rd",
    "sg:city":"Brunswick",
    "sg:classifiers":[
        {
            "category":"Retail",
            "subcategory":"Auto Repair",
            "type":"Services"
        }
    ],
    "sg:phone":"+1 912 262 0024",
    "sg:postcode":"31520",
    "sg:province":"GA",
    "sg:tags":[
        "shop",
        "automotive",
        "lube"
    ],
    "wof:name":"Master Lube 2",
    "wof:placetype":"venue"
},
  "geometry": {"coordinates":[-81.496416,31.202784],"type":"Point"}
}