{
  "type": "Feature",
  "properties": {
    "addr:full":"2480 Bankhead Hwy NW Atlanta GA 30318",
    "addr:housenumber":"2480",
    "addr:postcode":"30318",
    "addr:street":"Bankhead Hwy Nw",
    "iso:country":"US",
    "sg:address":"2480 Bankhead Hwy NW",
    "sg:city":"Atlanta",
    "sg:classifiers":[
        {
            "category":"Organizations",
            "subcategory":"Religious Organization",
            "type":"Services"
        }
    ],
    "sg:phone":"+1 404 799 9652",
    "sg:postcode":"30318",
    "sg:province":"GA",
    "sg:tags":[
        "church"
    ],
    "wof:name":"Church Of Goodwill & Faith",
    "wof:placetype":"venue"
},
  "geometry": {"coordinates":[-84.467004,33.775872],"type":"Point"}
}