{
  "type": "Feature",
  "properties": {
    "iso:country":"US",
    "sg:address":"5900 Maxham Rd",
    "sg:city":"Austell",
    "sg:classifiers":[
        {
            "category":"Retail",
            "subcategory":"Auto Repair",
            "type":"Services"
        }
    ],
    "sg:phone":"+1 770 941 9355",
    "sg:postcode":"30168",
    "sg:province":"GA",
    "sg:tags":[
        "automobile",
        "customizing"
    ],
    "wof:name":"Extreme Dreams",
    "wof:placetype":"venue"
},
  "geometry": {"coordinates":[-84.619832,33.809086],"type":"Point"}
}