{
  "type": "Feature",
  "properties": {
    "addr:full":"130 Raymond Ct Fayetteville GA 30214",
    "addr:housenumber":"130",
    "addr:postcode":"30214",
    "addr:street":"Raymond Ct",
    "iso:country":"US",
    "sg:address":"130 Raymond Ct",
    "sg:city":"Fayetteville",
    "sg:classifiers":[
        {
            "category":"Health Services",
            "subcategory":"Medical Lab",
            "type":"Services"
        }
    ],
    "sg:phone":"+1 770 460 9320",
    "sg:postcode":"30214",
    "sg:province":"GA",
    "sg:tags":[
        "laboratory"
    ],
    "wof:name":"Medical Imaging Resources",
    "wof:placetype":"venue"
},
  "geometry": {"coordinates":[-84.48556000000001,33.483447],"type":"Point"}
}