{
  "type": "Feature",
  "properties": {
    "iso:country":"US",
    "sg:address":"130 Oak Pointe Trl",
    "sg:city":"Savannah",
    "sg:classifiers":[
        {
            "category":"Professional",
            "subcategory":"Lawyer & Legal Services",
            "type":"Services"
        }
    ],
    "sg:phone":"+1 912 927 3460",
    "sg:postcode":"31419",
    "sg:province":"GA",
    "wof:name":"Beach & Associates LLC",
    "wof:placetype":"venue"
},
  "geometry": {"coordinates":[-81.157134,31.945496],"type":"Point"}
}