{
  "type": "Feature",
  "properties": {
    "iso:country":"US",
    "sg:address":"317 West Hill St",
    "sg:city":"Decatur",
    "sg:classifiers":[
        {
            "category":"Sports & Exercise",
            "subcategory":"Gym",
            "type":"Entertainment"
        }
    ],
    "sg:phone":"+1 678 705 1439",
    "sg:postcode":"30030",
    "sg:province":"GA",
    "sg:website":"www.SnapFitness.com/DecaturGA",
    "wof:name":"Snap Fitness 24/7",
    "wof:placetype":"venue"
},
  "geometry": {"coordinates":[-84.30131,33.760016],"type":"Point"}
}