{
  "type": "Feature",
  "properties": {
    "addr:full":"3200 Cobb Parkway Atlanta GA 30339",
    "addr:housenumber":"3200",
    "addr:postcode":"30339",
    "addr:street":"Cobb Parkway",
    "iso:country":"US",
    "sg:address":"3200 Cobb Parkway",
    "sg:city":"Atlanta",
    "sg:classifiers":[
        {
            "category":"Travel",
            "subcategory":"Hotels & Motels",
            "type":"Entertainment"
        }
    ],
    "sg:phone":"+1 770 988 9449",
    "sg:postcode":"30339",
    "sg:province":"GA",
    "wof:name":"Homewood Suites by Hilton Atlanta-Galleria Cumberland",
    "wof:placetype":"venue"
},
  "geometry": {"coordinates":[-84.45967,33.879661],"type":"Point"}
}