{
  "type": "Feature",
  "properties": {
    "addr:full":"601 Parkaire Xing Marietta GA 30068",
    "addr:housenumber":"601",
    "addr:postcode":"30068",
    "addr:street":"Parkaire Xing",
    "iso:country":"US",
    "sg:address":"601 Parkaire Xing",
    "sg:city":"Marietta",
    "sg:classifiers":[
        {
            "category":"Wholesale",
            "subcategory":"Seafood",
            "type":"Manufacturing & Wholesale Goods"
        }
    ],
    "sg:phone":"+1 770 428 6604",
    "sg:postcode":"30068",
    "sg:province":"GA",
    "wof:name":"Sherrods Barbeque & Seafood",
    "wof:placetype":"venue"
},
  "geometry": {"coordinates":[-84.404168,33.963817],"type":"Point"}
}