{
  "type": "Feature",
  "properties": {
    "addr:full":"2853 Watchtower Approach Marietta GA 30064",
    "addr:housenumber":"2853",
    "addr:postcode":"30064",
    "addr:street":"Watchtower Approach",
    "iso:country":"US",
    "sg:address":"2853 Watchtower Approach",
    "sg:city":"Marietta",
    "sg:classifiers":[
        {
            "category":"Professional",
            "type":"Services"
        }
    ],
    "sg:phone":"+1 770 429 9460",
    "sg:postcode":"30064",
    "sg:province":"GA",
    "sg:tags":[
        "establishment"
    ],
    "wof:name":"Signal Hill Hoa",
    "wof:placetype":"venue"
},
  "geometry": {"coordinates":[-84.635774,33.971832],"type":"Point"}
}