{
  "type": "Feature",
  "properties": {
    "addr:full":"188 Anchor Rd Acworth GA 30101",
    "addr:housenumber":"188",
    "addr:postcode":"30101",
    "addr:street":"Anchor Rd",
    "iso:country":"US",
    "sg:address":"188 Anchor Rd",
    "sg:city":"Acworth",
    "sg:classifiers":[
        {
            "category":"Building & Trades",
            "subcategory":"Plumbing",
            "type":"Services"
        }
    ],
    "sg:phone":"+1 770 975 0682",
    "sg:postcode":"30101",
    "sg:province":"GA",
    "sg:tags":[
        "contractor"
    ],
    "wof:name":"All American Mechanical Inc",
    "wof:placetype":"venue"
},
  "geometry": {"coordinates":[-84.715277,34.085043],"type":"Point"}
}