{
  "type": "Feature",
  "properties": {
    "iso:country":"US",
    "sg:address":"101 S Glenwood Ave",
    "sg:city":"Dalton",
    "sg:classifiers":[
        {
            "category":"Wholesale",
            "subcategory":"Machinery & Supplies",
            "type":"Manufacturing & Wholesale Goods"
        },
        {
            "category":"Building & Trades",
            "subcategory":"Construction",
            "type":"Services"
        }
    ],
    "sg:phone":"+1 706 226 1052",
    "sg:postcode":"30721",
    "sg:province":"GA",
    "sg:tags":[
        "equipment",
        "general",
        "contractor"
    ],
    "wof:name":"Allied Service Contractors LLC",
    "wof:placetype":"venue"
},
  "geometry": {"coordinates":[-84.96552699999999,34.770748],"type":"Point"}
}