{
  "type": "Feature",
  "properties": {
    "iso:country":"US",
    "sg:address":"111 Courtney Ct",
    "sg:city":"Albany",
    "sg:classifiers":[
        {
            "category":"Building & Trades",
            "subcategory":"Electrical",
            "type":"Services"
        }
    ],
    "sg:phone":"+1 229 434 1469",
    "sg:postcode":"31721",
    "sg:province":"GA",
    "sg:tags":[
        "electric",
        "contractor"
    ],
    "wof:name":"Carswell Brothers Electric",
    "wof:placetype":"venue"
},
  "geometry": {"coordinates":[-84.22922800000001,31.586634],"type":"Point"}
}