{
  "type": "Feature",
  "properties": {
    "addr:full":"102 Warnell St Pembroke GA 31321",
    "addr:housenumber":"102",
    "addr:postcode":"31321",
    "addr:street":"Warnell St",
    "iso:country":"US",
    "sg:address":"102 Warnell St",
    "sg:city":"Pembroke",
    "sg:classifiers":[
        {
            "category":"Organizations",
            "subcategory":"Religious Organization",
            "type":"Services"
        }
    ],
    "sg:phone":"+1 912 653 2497",
    "sg:postcode":"31321",
    "sg:province":"GA",
    "wof:name":"Missionary Baptist",
    "wof:placetype":"venue"
},
  "geometry": {"coordinates":[-81.617728,32.14053],"type":"Point"}
}