{
  "type": "Feature",
  "properties": {
    "iso:country":"US",
    "sg:address":"912 S Broad St",
    "sg:city":"Cairo",
    "sg:classifiers":[
        {
            "category":"Freight",
            "type":"Transportation"
        }
    ],
    "sg:phone":"+1 229 377 1438",
    "sg:postcode":"39828",
    "sg:province":"GA",
    "sg:tags":[
        "operator",
        "local",
        "trucking"
    ],
    "wof:name":"John E Wisehart",
    "wof:placetype":"venue"
},
  "geometry": {"coordinates":[-84.20822200000001,30.866042],"type":"Point"}
}