{
  "type": "Feature",
  "properties": {
    "addr:full":"5265 Highway 92 Acworth GA 30102",
    "addr:housenumber":"5265",
    "addr:postcode":"30102",
    "addr:street":"Highway 92",
    "iso:country":"US",
    "sg:address":"5265 Highway 92",
    "sg:city":"Acworth",
    "sg:classifiers":[
        {
            "category":"Social Services",
            "subcategory":"Child Care",
            "type":"Services"
        },
        {
            "category":"Education",
            "subcategory":"Preschool",
            "type":"Public Place"
        },
        {
            "category":"Education",
            "subcategory":"School",
            "type":"Public Place"
        }
    ],
    "sg:phone":"+1 770 974 5831",
    "sg:postcode":"30102",
    "sg:province":"GA",
    "sg:tags":[
        "elementary",
        "day"
    ],
    "sg:website":"www.decschildcare.com",
    "wof:name":"Decs Childcare Schools",
    "wof:placetype":"venue"
},
  "geometry": {"coordinates":[-84.60340100000001,34.0895],"type":"Point"}
}