{
  "type": "Feature",
  "properties": {
    "addr:full":"4371 Powers Ferry Rd NW Atlanta GA 30327",
    "addr:housenumber":"4371",
    "addr:postcode":"30327",
    "addr:street":"Powers Ferry Rd Nw",
    "iso:country":"US",
    "sg:address":"4371 Powers Ferry Rd NW",
    "sg:city":"Atlanta",
    "sg:classifiers":[
        {
            "category":"Sports & Exercise",
            "subcategory":"Stables",
            "type":"Entertainment"
        }
    ],
    "sg:phone":"+1 404 252 4244",
    "sg:postcode":"30327",
    "sg:province":"GA",
    "sg:website":"http://www.chastainhorsepark.org",
    "wof:name":"Chastain Horse Park",
    "wof:placetype":"venue"
},
  "geometry": {"coordinates":[-84.397919,33.874371],"type":"Point"}
}