{
  "type": "Feature",
  "properties": {
    "addr:full":"1101 Wesley Park Dr Marietta GA 30064",
    "addr:housenumber":"1101",
    "addr:postcode":"30064",
    "addr:street":"Wesley Park Dr",
    "iso:country":"US",
    "sg:address":"1101 Wesley Park Dr",
    "sg:city":"Marietta",
    "sg:classifiers":[
        {
            "category":"Building & Trades",
            "subcategory":"Landscaping Services",
            "type":"Services"
        }
    ],
    "sg:phone":"+1 770 424 4686",
    "sg:postcode":"30064",
    "sg:province":"GA",
    "wof:name":"Cobb Tree Service",
    "wof:placetype":"venue"
},
  "geometry": {"coordinates":[-84.58505599999999,33.923952],"type":"Point"}
}