{
  "type": "Feature",
  "properties": {
    "iso:country":"US",
    "sg:address":"1740 State Rte 20",
    "sg:city":"Lawrenceville",
    "sg:classifiers":[
        {
            "category":"Professional",
            "subcategory":"Computer Services",
            "type":"Services"
        }
    ],
    "sg:phone":"+1 770 963 9314",
    "sg:postcode":"30043",
    "sg:province":"GA",
    "sg:tags":[
        "related"
    ],
    "wof:name":"Larpen Corp",
    "wof:placetype":"venue"
},
  "geometry": {"coordinates":[-83.986902,34.01756],"type":"Point"}
}