{
  "type": "Feature",
  "properties": {
    "iso:country":"US",
    "sg:address":"3748 Jonesboro Rd",
    "sg:city":"Hampton",
    "sg:classifiers":[
        {
            "category":"Retail",
            "subcategory":"Laundry & Dry Cleaning",
            "type":"Services"
        }
    ],
    "sg:phone":"+1 770 473 0727",
    "sg:postcode":"30228",
    "sg:province":"GA",
    "sg:tags":[
        "cleaners",
        "rug",
        "carpet"
    ],
    "wof:name":"Magic Carpet DRI",
    "wof:placetype":"venue"
},
  "geometry": {"coordinates":[-84.277235,33.468751],"type":"Point"}
}