{
  "type": "Feature",
  "properties": {
    "iso:country":"US",
    "sg:address":"1552 Gordon Hwy",
    "sg:city":"Augusta",
    "sg:classifiers":[
        {
            "category":"Retail",
            "subcategory":"Laundry & Dry Cleaning",
            "type":"Services"
        }
    ],
    "sg:phone":"+1 706 790 3335",
    "sg:postcode":"30906",
    "sg:province":"GA",
    "sg:tags":[
        "cleaners",
        "plant",
        "drycleaning"
    ],
    "wof:name":"Y&K Dry Cleaners",
    "wof:placetype":"venue"
},
  "geometry": {"coordinates":[-82.008168,33.438044],"type":"Point"}
}