{
  "type": "Feature",
  "properties": {
    "addr:full":"2656 Marleigh Farm Rd NW Kennesaw GA 30152",
    "addr:housenumber":"2656",
    "addr:postcode":"30152",
    "addr:street":"Marleigh Farm Rd Nw",
    "iso:country":"US",
    "sg:address":"2656 Marleigh Farm Rd NW",
    "sg:city":"Kennesaw",
    "sg:classifiers":[
        {
            "category":"Professional",
            "type":"Services"
        }
    ],
    "sg:phone":"+1 770 917 0124",
    "sg:postcode":"30152",
    "sg:province":"GA",
    "wof:name":"Cmt Designs Inc",
    "wof:placetype":"venue"
},
  "geometry": {"coordinates":[-84.65357,34.018164],"type":"Point"}
}