{
  "type": "Feature",
  "properties": {
    "addr:full":"265 Davis Rd Jefferson GA 30549",
    "addr:housenumber":"265",
    "addr:postcode":"30549",
    "addr:street":"Davis Rd",
    "iso:country":"US",
    "sg:address":"265 Davis Rd",
    "sg:city":"Jefferson",
    "sg:classifiers":[
        {
            "category":"Social Services",
            "type":"Services"
        }
    ],
    "sg:phone":"+1 706 367 1732",
    "sg:postcode":"30549",
    "sg:province":"GA",
    "sg:tags":[
        "probation"
    ],
    "wof:name":"Probation Detention",
    "wof:placetype":"venue"
},
  "geometry": {"coordinates":[-83.554098,34.086958],"type":"Point"}
}