{
  "type": "Feature",
  "properties": {
    "addr:full":"940 Glenbrook Dr NW Atlanta GA 30318",
    "addr:housenumber":"940",
    "addr:postcode":"30318",
    "addr:street":"Glenbrook Dr Nw",
    "iso:country":"US",
    "sg:address":"940 Glenbrook Dr NW",
    "sg:city":"Atlanta",
    "sg:classifiers":[
        {
            "category":"Professional",
            "type":"Services"
        }
    ],
    "sg:phone":"+1 404 352 5551",
    "sg:postcode":"30318",
    "sg:province":"GA",
    "wof:name":"C S Godfrey Inc",
    "wof:placetype":"venue"
},
  "geometry": {"coordinates":[-84.416954,33.814957],"type":"Point"}
}