{
  "type": "Feature",
  "properties": {
    "iso:country":"US",
    "sg:address":"5701 Riverview Rd SE",
    "sg:city":"Mableton",
    "sg:classifiers":[
        {
            "category":"Retail",
            "subcategory":"Auto Repair",
            "type":"Services"
        }
    ],
    "sg:phone":"+1 404 792 0697",
    "sg:postcode":"30126",
    "sg:province":"GA",
    "sg:tags":[
        "manufacturer",
        "recreational",
        "campers-wholesale",
        "trailer",
        "vehicle"
    ],
    "wof:name":"B & W Trailer Services Inc",
    "wof:placetype":"venue"
},
  "geometry": {"coordinates":[-84.48994399999999,33.814465],"type":"Point"}
}