{
  "type": "Feature",
  "properties": {
    "addr:full":"120 12th St Columbus GA 31901",
    "addr:housenumber":"120",
    "addr:postcode":"31901",
    "addr:street":"12Th St",
    "iso:country":"US",
    "sg:address":"120 12th St",
    "sg:city":"Columbus",
    "sg:classifiers":[
        {
            "category":"Professional",
            "type":"Services"
        }
    ],
    "sg:phone":"+1 706 322 0210",
    "sg:postcode":"31901",
    "sg:province":"GA",
    "sg:tags":[
        "establishment"
    ],
    "wof:name":"Royal Group Inc",
    "wof:placetype":"venue"
},
  "geometry": {"coordinates":[-84.990561,32.468527],"type":"Point"}
}