{
  "type": "Feature",
  "properties": {
    "addr:full":"7670 Abercorn St Savannah GA 31406",
    "addr:housenumber":"7670",
    "addr:postcode":"31406",
    "addr:street":"Abercorn St",
    "iso:country":"US",
    "sg:address":"7670 Abercorn St",
    "sg:city":"Savannah",
    "sg:classifiers":[
        {
            "category":"Retail",
            "subcategory":"Auto Repair",
            "type":"Services"
        }
    ],
    "sg:phone":"+1 912 356 1616",
    "sg:postcode":"31406",
    "sg:province":"GA",
    "sg:tags":[
        "automotive",
        "s",
        "general"
    ],
    "wof:name":"Asian Automotive Repair Svc",
    "wof:placetype":"venue"
},
  "geometry": {"coordinates":[-81.11532699999999,32.007659],"type":"Point"}
}