{
  "type": "Feature",
  "properties": {
    "addr:full":"7930 Saddle Ridge Dr Atlanta GA 30350",
    "addr:housenumber":"7930",
    "addr:postcode":"30350",
    "addr:street":"Saddle Ridge Dr",
    "iso:country":"US",
    "sg:address":"7930 Saddle Ridge Dr",
    "sg:city":"Atlanta",
    "sg:classifiers":[
        {
            "category":"Wholesale",
            "subcategory":"Stationery",
            "type":"Manufacturing & Wholesale Goods"
        }
    ],
    "sg:phone":"+1 770 481 7826",
    "sg:postcode":"30350",
    "sg:province":"GA",
    "sg:tags":[
        "wood",
        "container",
        "furniture"
    ],
    "wof:name":"Interntnal Drect Cont Srce LLC",
    "wof:placetype":"venue"
},
  "geometry": {"coordinates":[-84.32067499999999,33.971667],"type":"Point"}
}