{
  "type": "Feature",
  "properties": {
    "addr:full":"3355 Breckinridge Blvd # 128 Duluth GA 30096",
    "addr:housenumber":"3355",
    "addr:postcode":"30096",
    "addr:street":"Breckinridge Blvd # 128",
    "iso:country":"US",
    "sg:address":"3355 Breckinridge Blvd # 128",
    "sg:city":"Duluth",
    "sg:classifiers":[
        {
            "category":"Education",
            "subcategory":"Special Training",
            "type":"Public Place"
        },
        {
            "category":"Professional",
            "subcategory":"Computer Services",
            "type":"Services"
        }
    ],
    "sg:phone":"+1 770 935 0300",
    "sg:postcode":"30096",
    "sg:province":"GA",
    "sg:tags":[
        "school",
        "technology",
        "software"
    ],
    "wof:name":"Act",
    "wof:placetype":"venue"
},
  "geometry": {"coordinates":[-84.116685,33.954571],"type":"Point"}
}