{
  "type": "Feature",
  "properties": {
    "iso:country":"US",
    "sg:address":"505 Creekridge Ct",
    "sg:city":"Woodstock",
    "sg:classifiers":[
        {
            "category":"Professional",
            "subcategory":"Art Services",
            "type":"Services"
        }
    ],
    "sg:phone":"+1 770 928 0987",
    "sg:postcode":"30188",
    "sg:province":"GA",
    "sg:tags":[
        "commercial",
        "graphic",
        "design"
    ],
    "wof:name":"Image Design Group",
    "wof:placetype":"venue"
},
  "geometry": {"coordinates":[-84.500052,34.091935],"type":"Point"}
}