{
  "type": "Feature",
  "properties": {
    "addr:full":"4231 Pleasant Hill Rd Ste B Duluth GA 30096",
    "addr:housenumber":"4231",
    "addr:postcode":"30096",
    "addr:street":"Pleasant Hill Rd Ste B",
    "iso:country":"US",
    "sg:address":"4231 Pleasant Hill Rd Ste B",
    "sg:city":"Duluth",
    "sg:classifiers":[
        {
            "category":"Health Services",
            "subcategory":"Doctor",
            "type":"Services"
        }
    ],
    "sg:phone":"+1 678 474 0735",
    "sg:postcode":"30096",
    "sg:province":"GA",
    "wof:name":"Maternal and Family",
    "wof:placetype":"venue"
},
  "geometry": {"coordinates":[-84.173723,34.004726],"type":"Point"}
}