{
  "type": "Feature",
  "properties": {
    "addr:full":"123 Smith St Jonesboro GA 30236",
    "addr:housenumber":"123",
    "addr:postcode":"30236",
    "addr:street":"Smith St",
    "iso:country":"US",
    "sg:address":"123 Smith St",
    "sg:city":"Jonesboro",
    "sg:classifiers":[
        {
            "category":"Professional",
            "subcategory":"Lawyer & Legal Services",
            "type":"Services"
        }
    ],
    "sg:phone":"+1 770 478 1921",
    "sg:postcode":"30236",
    "sg:province":"GA",
    "sg:tags":[
        "attorney"
    ],
    "wof:name":"Morris & Schneider",
    "wof:placetype":"venue"
},
  "geometry": {"coordinates":[-84.354449,33.522627],"type":"Point"}
}