{
  "type": "Feature",
  "properties": {
    "iso:country":"US",
    "sg:address":"1478 Willow Bend Dr",
    "sg:city":"Woodstock",
    "sg:classifiers":[
        {
            "category":"Professional",
            "subcategory":"Engineering",
            "type":"Services"
        },
        {
            "category":"Professional",
            "subcategory":"Management & Consulting",
            "type":"Services"
        }
    ],
    "sg:phone":"+1 678 494 5281",
    "sg:postcode":"30188",
    "sg:province":"GA",
    "sg:tags":[
        "business",
        "engineer"
    ],
    "wof:name":"Brock Consulting Group Inc",
    "wof:placetype":"venue"
},
  "geometry": {"coordinates":[-84.43195799999999,34.095994],"type":"Point"}
}