{
  "type": "Feature",
  "properties": {
    "iso:country":"US",
    "sg:address":"4672 Martha Berry Hwy",
    "sg:city":"Rome",
    "sg:classifiers":[
        {
            "category":"Food & Beverages",
            "subcategory":"Groceries & Convenience Stores",
            "type":"Retail Goods"
        }
    ],
    "sg:phone":"+1 706 232 8911",
    "sg:postcode":"30165",
    "sg:province":"GA",
    "wof:name":"Taylor Marktet LLC",
    "wof:placetype":"venue"
},
  "geometry": {"coordinates":[-85.172392,34.353827],"type":"Point"}
}