{
  "type": "Feature",
  "properties": {
    "addr:full":"4370 Landover Way NW Suwanee GA 30024",
    "addr:housenumber":"4370",
    "addr:postcode":"30024",
    "addr:street":"Landover Way Nw",
    "iso:country":"US",
    "sg:address":"4370 Landover Way NW",
    "sg:city":"Suwanee",
    "sg:classifiers":[
        {
            "category":"Professional",
            "subcategory":"Business Services",
            "type":"Services"
        }
    ],
    "sg:phone":"+1 770 945 4079",
    "sg:postcode":"30024",
    "sg:province":"GA",
    "sg:tags":[
        "interior",
        "design"
    ],
    "wof:name":"Decorating Den",
    "wof:placetype":"venue"
},
  "geometry": {"coordinates":[-84.087102,34.063964],"type":"Point"}
}