{
  "type": "Feature",
  "properties": {
    "addr:full":"1144 Graydon St Savannah GA 31404",
    "addr:housenumber":"1144",
    "addr:postcode":"31404",
    "addr:street":"Graydon St",
    "iso:country":"US",
    "sg:address":"1144 Graydon St",
    "sg:city":"Savannah",
    "sg:classifiers":[
        {
            "category":"Building & Trades",
            "subcategory":"Landscaping Services",
            "type":"Services"
        }
    ],
    "sg:phone":"+1 912 238 0884",
    "sg:postcode":"31404",
    "sg:province":"GA",
    "wof:name":"Lb & Williams Lawncare",
    "wof:placetype":"venue"
},
  "geometry": {"coordinates":[-81.078414,32.062308],"type":"Point"}
}