{
  "type": "Feature",
  "properties": {
    "iso:country":"US",
    "sg:address":"96 Parrish St",
    "sg:city":"Griffin",
    "sg:classifiers":[
        {
            "category":"Building & Trades",
            "subcategory":"Construction",
            "type":"Services"
        }
    ],
    "sg:phone":"+1 770 228 1657",
    "sg:postcode":"30223",
    "sg:province":"GA",
    "sg:tags":[
        "general",
        "contractor"
    ],
    "wof:name":"RWS Construction",
    "wof:placetype":"venue"
},
  "geometry": {"coordinates":[-84.239902,33.239483],"type":"Point"}
}