{
  "type": "Feature",
  "properties": {
    "iso:country":"US",
    "sg:address":"2560 Ivy Stone Trl",
    "sg:city":"Buford",
    "sg:classifiers":[
        {
            "category":"Real Estate",
            "subcategory":"Real Estate Agent",
            "type":"Services"
        }
    ],
    "sg:phone":"+1 770 682 9493",
    "sg:postcode":"30519",
    "sg:province":"GA",
    "sg:tags":[
        "inspection"
    ],
    "wof:name":"Home Inspection Of Georgia",
    "wof:placetype":"venue"
},
  "geometry": {"coordinates":[-83.972126,34.052368],"type":"Point"}
}