{
  "type": "Feature",
  "properties": {
    "iso:country":"US",
    "sg:address":"224 W Main St",
    "sg:city":"Swainsboro",
    "sg:classifiers":[
        {
            "category":"Shopping",
            "subcategory":"Pharmacy",
            "type":"Retail Goods"
        }
    ],
    "sg:phone":"+1 478 237 7032",
    "sg:postcode":"30401",
    "sg:province":"GA",
    "sg:website":"www.shoprite.com",
    "wof:name":"Shop Rite Pharmacy",
    "wof:placetype":"venue"
},
  "geometry": {"coordinates":[-82.336777,32.595971],"type":"Point"}
}