{
  "type": "Feature",
  "properties": {
    "addr:full":"1287 Cedar Shoals Dr Athens GA 30605",
    "addr:housenumber":"1287",
    "addr:postcode":"30605",
    "addr:street":"Cedar Shoals Dr",
    "iso:country":"US",
    "sg:address":"1287 Cedar Shoals Dr",
    "sg:city":"Athens",
    "sg:classifiers":[
        {
            "category":"Wholesale",
            "subcategory":"Sporting Goods",
            "type":"Manufacturing & Wholesale Goods"
        }
    ],
    "sg:phone":"+1 706 227 2248",
    "sg:postcode":"30605",
    "sg:province":"GA",
    "sg:tags":[
        "tackle",
        "fishing"
    ],
    "sg:website":"www.bassbait.com",
    "wof:name":"Mc Guinness Fishing Products",
    "wof:placetype":"venue"
},
  "geometry": {"coordinates":[-83.33390900000001,33.925644],"type":"Point"}
}