{
  "type": "Feature",
  "properties": {
    "iso:country":"US",
    "sg:address":"593 Medinah Dr",
    "sg:city":"Augusta",
    "sg:classifiers":[
        {
            "category":"Health Services",
            "subcategory":"Clinic",
            "type":"Services"
        }
    ],
    "sg:phone":"+1 706 863 1107",
    "sg:postcode":"30907",
    "sg:province":"GA",
    "wof:name":"Michael D Duplessie MD",
    "wof:placetype":"venue"
},
  "geometry": {"coordinates":[-82.072701,33.544429],"type":"Point"}
}