{
  "type": "Feature",
  "properties": {
    "addr:full":"4329 Atlanta Hwy Loganville GA 30052",
    "addr:housenumber":"4329",
    "addr:postcode":"30052",
    "addr:street":"Atlanta Hwy",
    "iso:country":"US",
    "sg:address":"4329 Atlanta Hwy",
    "sg:city":"Loganville",
    "sg:classifiers":[
        {
            "category":"Autos & Motor Vehicles",
            "subcategory":"Auto Supplies",
            "type":"Retail Goods"
        }
    ],
    "sg:phone":"+1 770 554 9112",
    "sg:postcode":"30052",
    "sg:province":"GA",
    "sg:tags":[
        "tire"
    ],
    "sg:website":"http://www.tiresplus.com",
    "wof:name":"Tires Plus Total Car Care",
    "wof:placetype":"venue"
},
  "geometry": {"coordinates":[-83.905829,33.83974],"type":"Point"}
}