{
  "type": "Feature",
  "properties": {
    "addr:full":"875 Mansell Rd Ste C Roswell GA 30076",
    "addr:housenumber":"875",
    "addr:postcode":"30076",
    "addr:street":"Mansell Rd Ste C",
    "iso:country":"US",
    "sg:address":"875 Mansell Rd Ste C",
    "sg:city":"Roswell",
    "sg:classifiers":[
        {
            "category":"Autos & Motor Vehicles",
            "subcategory":"Automobile Sales",
            "type":"Retail Goods"
        },
        {
            "category":"Retail",
            "subcategory":"Auto Rental",
            "type":"Services"
        }
    ],
    "sg:phone":"+1 770 645 6784",
    "sg:postcode":"30076",
    "sg:province":"GA",
    "sg:tags":[
        "car",
        "leasing",
        "van"
    ],
    "sg:website":"www.avis.com",
    "wof:name":"Avis Rent A Car",
    "wof:placetype":"venue"
},
  "geometry": {"coordinates":[-84.338747,34.042673],"type":"Point"}
}