{
  "type": "Feature",
  "properties": {
    "addr:full":"10945 State Bridge Rd Suite 401-140 Alpharetta GA 30022",
    "addr:housenumber":"10945",
    "addr:postcode":"30022",
    "addr:street":"State Bridge Rd Suite 401-140",
    "iso:country":"US",
    "sg:address":"10945 State Bridge Rd Suite 401-140",
    "sg:city":"Alpharetta",
    "sg:classifiers":[
        {
            "category":"Professional",
            "subcategory":"Advertising",
            "type":"Services"
        }
    ],
    "sg:phone":"+1 678 274 9110",
    "sg:postcode":"30022",
    "sg:province":"GA",
    "sg:tags":[
        "marketing"
    ],
    "sg:website":"zimrock.com",
    "wof:name":"Zimrock Marketing",
    "wof:placetype":"venue"
},
  "geometry": {"coordinates":[-84.22331200000001,34.049501],"type":"Point"}
}