{
  "type": "Feature",
  "properties": {
    "iso:country":"US",
    "sg:address":"119 Wildwood Cir",
    "sg:city":"Gainesville",
    "sg:classifiers":[
        {
            "category":"Shopping",
            "type":"Retail Goods"
        }
    ],
    "sg:phone":"+1 770 536 1736",
    "sg:postcode":"30501",
    "sg:province":"GA",
    "sg:tags":[
        "merchandise"
    ],
    "wof:name":"Fpb Enterprises",
    "wof:placetype":"venue"
},
  "geometry": {"coordinates":[-83.80748699999999,34.335831],"type":"Point"}
}