{
  "type": "Feature",
  "properties": {
    "iso:country":"US",
    "sg:address":"103 Atlantic Ave",
    "sg:city":"Waco",
    "sg:classifiers":[
        {
            "category":"Restaurant",
            "type":"Food & Drink"
        }
    ],
    "sg:phone":"+1 770 537 0746",
    "sg:postcode":"30182",
    "sg:province":"GA",
    "wof:name":"Black Skillet",
    "wof:placetype":"venue"
},
  "geometry": {"coordinates":[-85.18371500000001,33.702159],"type":"Point"}
}