{
  "type": "Feature",
  "properties": {
    "addr:full":"436 Concord Cir Mc Donough GA 30253",
    "addr:housenumber":"436",
    "addr:postcode":"30253",
    "addr:street":"Concord Cir",
    "iso:country":"US",
    "sg:address":"436 Concord Cir",
    "sg:city":"Mc Donough",
    "sg:classifiers":[
        {
            "category":"Professional",
            "subcategory":"Business Services",
            "type":"Services"
        }
    ],
    "sg:phone":"+1 770 898 7235",
    "sg:postcode":"30253",
    "sg:province":"GA",
    "wof:name":"Southeast Design Build",
    "wof:placetype":"venue"
},
  "geometry": {"coordinates":[-84.18848699999999,33.488351],"type":"Point"}
}