{
  "type": "Feature",
  "properties": {
    "addr:full":"3623 Sunderland Cir NE Atlanta GA 30319",
    "addr:housenumber":"3623",
    "addr:postcode":"30319",
    "addr:street":"Sunderland Cir Ne",
    "iso:country":"US",
    "sg:address":"3623 Sunderland Cir NE",
    "sg:city":"Atlanta",
    "sg:classifiers":[
        {
            "category":"Professional",
            "subcategory":"Management & Consulting",
            "type":"Services"
        }
    ],
    "sg:phone":"+1 770 452 8141",
    "sg:postcode":"30319",
    "sg:province":"GA",
    "sg:tags":[
        "business"
    ],
    "wof:name":"Sales Advantages Inc",
    "wof:placetype":"venue"
},
  "geometry": {"coordinates":[-84.335634,33.896085],"type":"Point"}
}