{
  "type": "Feature",
  "properties": {
    "iso:country":"US",
    "sg:address":"1225 New Savannah Rd",
    "sg:city":"Augusta",
    "sg:classifiers":[
        {
            "category":"Building & Trades",
            "subcategory":"Electrical",
            "type":"Services"
        }
    ],
    "sg:phone":"+1 706 724 9507",
    "sg:postcode":"30901",
    "sg:province":"GA",
    "sg:tags":[
        "electric",
        "contractor"
    ],
    "wof:name":"Performance Electric Co",
    "wof:placetype":"venue"
},
  "geometry": {"coordinates":[-81.972595,33.456526],"type":"Point"}
}