{
  "type": "Feature",
  "properties": {
    "iso:country":"US",
    "sg:address":"2000 Convention Center Concourse",
    "sg:city":"Atlanta",
    "sg:classifiers":[
        {
            "category":"Food & Beverages",
            "subcategory":"Groceries & Convenience Stores",
            "type":"Retail Goods"
        }
    ],
    "sg:phone":"+1 770 997 3566",
    "sg:postcode":"30337",
    "sg:province":"GA",
    "sg:website":"www.georgiainternationalconventi...",
    "wof:name":"Georgia International Convention Center",
    "wof:placetype":"venue"
},
  "geometry": {"coordinates":[-84.455108,33.643858],"type":"Point"}
}