{
  "type": "Feature",
  "properties": {
    "iso:country":"US",
    "sg:address":"6161 Mableton Pkwy SW",
    "sg:city":"Mableton",
    "sg:classifiers":[
        {
            "category":"Banks & Credit Unions",
            "subcategory":"Financial Services",
            "type":"Services"
        }
    ],
    "sg:phone":"+1 770 948 7433",
    "sg:postcode":"30126",
    "sg:province":"GA",
    "sg:tags":[
        "cashing",
        "check"
    ],
    "wof:name":"Check Point Emissions",
    "wof:placetype":"venue"
},
  "geometry": {"coordinates":[-84.568252,33.803547],"type":"Point"}
}