{
  "type": "Feature",
  "properties": {
    "iso:country":"US",
    "sg:address":"5670 Peachtree Dunwoody Rd NE # 920",
    "sg:city":"Atlanta",
    "sg:classifiers":[
        {
            "category":"Health Services",
            "subcategory":"Doctor",
            "type":"Services"
        }
    ],
    "sg:phone":"+1 404 847 0664",
    "sg:postcode":"30342",
    "sg:province":"GA",
    "sg:tags":[
        "medicine",
        "physician",
        "practice",
        "surgeons",
        "family"
    ],
    "wof:name":"North Atlanta Surgical Assoc",
    "wof:placetype":"venue"
},
  "geometry": {"coordinates":[-84.35195899999999,33.908791],"type":"Point"}
}