{
  "type": "Feature",
  "properties": {
    "addr:full":"65 S Shore Dr Newnan GA 30263",
    "addr:housenumber":"65",
    "addr:postcode":"30263",
    "addr:street":"S Shore Dr",
    "iso:country":"US",
    "sg:address":"65 S Shore Dr",
    "sg:city":"Newnan",
    "sg:classifiers":[
        {
            "category":"Building & Trades",
            "subcategory":"Construction",
            "type":"Services"
        }
    ],
    "sg:phone":"+1 770 683 8798",
    "sg:postcode":"30263",
    "sg:province":"GA",
    "sg:tags":[
        "tile",
        "dealer"
    ],
    "wof:name":"Briva Designs",
    "wof:placetype":"venue"
},
  "geometry": {"coordinates":[-84.768632,33.465073],"type":"Point"}
}