{
  "type": "Feature",
  "properties": {
    "iso:country":"US",
    "sg:address":"245 Heath Way",
    "sg:city":"Fayetteville",
    "sg:classifiers":[
        {
            "category":"Building & Trades",
            "subcategory":"Construction",
            "type":"Services"
        }
    ],
    "sg:phone":"+1 770 716 1271",
    "sg:postcode":"30214",
    "sg:province":"GA",
    "sg:tags":[
        "contractor"
    ],
    "wof:name":"C & S Contracting",
    "wof:placetype":"venue"
},
  "geometry": {"coordinates":[-84.454194,33.526705],"type":"Point"}
}