{
  "type": "Feature",
  "properties": {
    "iso:country":"US",
    "sg:address":"2139 Greenville Rd",
    "sg:city":"Lagrange",
    "sg:classifiers":[
        {
            "category":"Shopping",
            "subcategory":"Bicycles & Sporting Goods",
            "type":"Retail Goods"
        }
    ],
    "sg:phone":"+1 706 637 9889",
    "sg:postcode":"30241",
    "sg:province":"GA",
    "sg:tags":[
        "equipment",
        "archery",
        "supply"
    ],
    "wof:name":"Archery Unlimited",
    "wof:placetype":"venue"
},
  "geometry": {"coordinates":[-84.958718,33.04185],"type":"Point"}
}