{
  "type": "Feature",
  "properties": {
    "addr:full":"8809 Willow Creek Ct Douglasville GA 30135",
    "addr:housenumber":"8809",
    "addr:postcode":"30135",
    "addr:street":"Willow Creek Ct",
    "iso:country":"US",
    "sg:address":"8809 Willow Creek Ct",
    "sg:city":"Douglasville",
    "sg:classifiers":[
        {
            "category":"Manufacturing",
            "subcategory":"Retail Goods",
            "type":"Manufacturing & Wholesale Goods"
        }
    ],
    "sg:phone":"+1 770 489 9367",
    "sg:postcode":"30135",
    "sg:province":"GA",
    "sg:tags":[
        "candle",
        "manufacturer"
    ],
    "wof:name":"Windscents",
    "wof:placetype":"venue"
},
  "geometry": {"coordinates":[-84.74813399999999,33.723665],"type":"Point"}
}