{
  "type": "Feature",
  "properties": {
    "addr:full":"7 Riverbend Dr SW Rome GA 30161",
    "addr:housenumber":"7",
    "addr:postcode":"ga 30161",
    "addr:street":"Riverbend Dr Sw",
    "iso:country":"US",
    "sg:address":"7 Riverbend Dr SW",
    "sg:city":"Rome",
    "sg:classifiers":[
        {
            "category":"Personal",
            "type":"Services"
        },
        {
            "category":"Recreation",
            "subcategory":"Picnic Area",
            "type":"Entertainment"
        },
        {
            "category":"Sports & Exercise",
            "subcategory":"Bowling",
            "type":"Entertainment"
        }
    ],
    "sg:phone":"+1 706 234 7373",
    "sg:postcode":"30161",
    "sg:province":"GA",
    "sg:tags":[
        "arcade",
        "planning",
        "place",
        "party",
        "event",
        "amusement"
    ],
    "wof:name":"Floyd Bowling & Amusement Center",
    "wof:placetype":"venue"
},
  "geometry": {"coordinates":[-85.166327,34.245251],"type":"Point"}
}