{
  "type": "Feature",
  "properties": {
    "iso:country":"US",
    "sg:address":"699 S State St",
    "sg:city":"Lyons",
    "sg:classifiers":[
        {
            "category":"Freight",
            "type":"Transportation"
        }
    ],
    "sg:phone":"+1 912 526 8142",
    "sg:postcode":"30436",
    "sg:province":"GA",
    "sg:tags":[
        "commercial",
        "storage"
    ],
    "wof:name":"C & T Mini Storage",
    "wof:placetype":"venue"
},
  "geometry": {"coordinates":[-82.325962,32.192177],"type":"Point"}
}