{
  "type": "Feature",
  "properties": {
    "iso:country":"US",
    "sg:address":"1515 Westfork Dr",
    "sg:city":"Lithia Springs",
    "sg:classifiers":[
        {
            "category":"Health Services",
            "subcategory":"Doctor",
            "type":"Services"
        }
    ],
    "sg:phone":"+1 770 739 2278",
    "sg:postcode":"30122",
    "sg:province":"GA",
    "wof:name":"Saltzman David Ph D",
    "wof:placetype":"venue"
},
  "geometry": {"coordinates":[-84.62449599999999,33.7882],"type":"Point"}
}