{
  "type": "Feature",
  "properties": {
    "iso:country":"US",
    "sg:address":"110 E Andrews Dr NW",
    "sg:city":"Atlanta",
    "sg:classifiers":[
        {
            "category":"Professional",
            "subcategory":"Accounting & Tax Preparation",
            "type":"Services"
        }
    ],
    "sg:phone":"+1 404 239 9464",
    "sg:postcode":"30305",
    "sg:province":"GA",
    "sg:tags":[
        "accountant"
    ],
    "wof:name":"Joyce A Bucher CPA",
    "wof:placetype":"venue"
},
  "geometry": {"coordinates":[-84.381967,33.843602],"type":"Point"}
}