{
  "type": "Feature",
  "properties": {
    "addr:full":"211 Luckie St Baxley GA 31513",
    "addr:housenumber":"211",
    "addr:postcode":"31513",
    "addr:street":"Luckie St",
    "iso:country":"US",
    "sg:address":"211 Luckie St",
    "sg:city":"Baxley",
    "sg:classifiers":[
        {
            "category":"Food & Beverages",
            "subcategory":"Liquor & Beverages",
            "type":"Retail Goods"
        }
    ],
    "sg:phone":"+1 912 367 7959",
    "sg:postcode":"31513",
    "sg:province":"GA",
    "sg:tags":[
        "alcoholic"
    ],
    "wof:name":"Package City",
    "wof:placetype":"venue"
},
  "geometry": {"coordinates":[-82.351373,31.775891],"type":"Point"}
}