{
  "type": "Feature",
  "properties": {
    "iso:country":"US",
    "sg:address":"4970 Portsmouth Ct",
    "sg:city":"Lithonia",
    "sg:classifiers":[
        {
            "category":"Freight",
            "type":"Transportation"
        }
    ],
    "sg:phone":"+1 678 418 7596",
    "sg:postcode":"30038",
    "sg:province":"GA",
    "sg:tags":[
        "operator",
        "local",
        "trucking"
    ],
    "wof:name":"R & B Trucking Inc",
    "wof:placetype":"venue"
},
  "geometry": {"coordinates":[-84.186448,33.680225],"type":"Point"}
}