{
  "type": "Feature",
  "properties": {
    "iso:country":"US",
    "sg:address":"7695 Hawthorne Dr",
    "sg:city":"Jonesboro",
    "sg:classifiers":[
        {
            "category":"Building & Trades",
            "subcategory":"Construction",
            "type":"Services"
        }
    ],
    "sg:phone":"+1 404 379 8938",
    "sg:postcode":"30236",
    "sg:province":"GA",
    "sg:tags":[
        "house"
    ],
    "wof:name":"Moores Construction",
    "wof:placetype":"venue"
},
  "geometry": {"coordinates":[-84.385079,33.545347],"type":"Point"}
}