{
  "type": "Feature",
  "properties": {
    "addr:full":"15 Tallapoosa St Temple GA 30179",
    "addr:housenumber":"15",
    "addr:postcode":"30179",
    "addr:street":"Tallapoosa St",
    "iso:country":"US",
    "sg:address":"15 Tallapoosa St",
    "sg:city":"Temple",
    "sg:classifiers":[
        {
            "category":"Shopping",
            "subcategory":"Hobbies, Toys, & Games",
            "type":"Retail Goods"
        }
    ],
    "sg:phone":"+1 770 562 8300",
    "sg:postcode":"30179",
    "sg:province":"GA",
    "sg:tags":[
        "craft"
    ],
    "wof:name":"I Love This Place",
    "wof:placetype":"venue"
},
  "geometry": {"coordinates":[-85.032661,33.736388],"type":"Point"}
}