{
  "type": "Feature",
  "properties": {
    "addr:full":"407 S Zetterower Ave Statesboro GA 30458",
    "addr:housenumber":"407",
    "addr:postcode":"30458",
    "addr:street":"S Zetterower Ave",
    "iso:country":"US",
    "sg:address":"407 S Zetterower Ave",
    "sg:city":"Statesboro",
    "sg:classifiers":[
        {
            "category":"Health Services",
            "subcategory":"Podiatrist",
            "type":"Services"
        }
    ],
    "sg:phone":"+1 912 489 3668",
    "sg:postcode":"30458",
    "sg:province":"GA",
    "wof:name":"Family Foot Care",
    "wof:placetype":"venue"
},
  "geometry": {"coordinates":[-81.780467,32.43922],"type":"Point"}
}