{
  "type": "Feature",
  "properties": {
    "addr:full":"3620 Atlanta Hwy Athens GA 30606",
    "addr:housenumber":"3620",
    "addr:postcode":"30606",
    "addr:street":"Atlanta Hwy",
    "iso:country":"US",
    "sg:address":"3620 Atlanta Hwy",
    "sg:city":"Athens",
    "sg:classifiers":[
        {
            "category":"Retail",
            "subcategory":"Laundry & Dry Cleaning",
            "type":"Services"
        }
    ],
    "sg:phone":"+1 706 369 3692",
    "sg:postcode":"30606",
    "sg:province":"GA",
    "sg:tags":[
        "cleaner"
    ],
    "wof:name":"Oxford Cleaners",
    "wof:placetype":"venue"
},
  "geometry": {"coordinates":[-83.456917,33.939186],"type":"Point"}
}