{
  "type": "Feature",
  "properties": {
    "iso:country":"US",
    "sg:address":"3870 Lawrenceville Hwy Ste C118",
    "sg:city":"Lawrenceville",
    "sg:classifiers":[
        {
            "category":"Wholesale",
            "subcategory":"Computers",
            "type":"Manufacturing & Wholesale Goods"
        },
        {
            "category":"Professional",
            "subcategory":"Computer Services",
            "type":"Services"
        }
    ],
    "sg:phone":"+1 678 924 5582",
    "sg:postcode":"30044",
    "sg:province":"GA",
    "sg:tags":[
        "repair"
    ],
    "wof:name":"A 2 Z Computer Services Inc",
    "wof:placetype":"venue"
},
  "geometry": {"coordinates":[-84.109168,33.907482],"type":"Point"}
}