{
  "type": "Feature",
  "properties": {
    "iso:country":"US",
    "sg:address":"663 Tommy Irvin Rd",
    "sg:city":"Mount Airy",
    "sg:classifiers":[
        {
            "category":"Farming",
            "subcategory":"Poultry Farm",
            "type":"Manufacturing & Wholesale Goods"
        }
    ],
    "sg:phone":"+1 706 754 4620",
    "sg:postcode":"30563",
    "sg:province":"GA",
    "sg:tags":[
        "hatchery",
        "chicken",
        "feedlot",
        "beef",
        "cattle"
    ],
    "wof:name":"Irvin Farms",
    "wof:placetype":"venue"
},
  "geometry": {"coordinates":[-83.4335,34.591676],"type":"Point"}
}