{
  "type": "Feature",
  "properties": {
    "iso:country":"US",
    "sg:address":"430 Wiscasset Cir",
    "sg:city":"Dallas",
    "sg:classifiers":[
        {
            "category":"Communications",
            "type":"Services"
        },
        {
            "category":"Professional",
            "subcategory":"Business Services",
            "type":"Services"
        }
    ],
    "sg:phone":"+1 678 631 2000",
    "sg:postcode":"30157",
    "sg:province":"GA",
    "wof:name":"Digital Communications Group",
    "wof:placetype":"venue"
},
  "geometry": {"coordinates":[-84.734264,33.966858],"type":"Point"}
}