{
  "type": "Feature",
  "properties": {
    "iso:country":"US",
    "sg:address":"3417 Rushing Rd",
    "sg:city":"Augusta",
    "sg:classifiers":[
        {
            "category":"Organizations",
            "subcategory":"Religious Organization",
            "type":"Services"
        }
    ],
    "sg:phone":"+1 706 798 4512",
    "sg:postcode":"30906",
    "sg:province":"GA",
    "wof:name":"Lloyd C Green Rev",
    "wof:placetype":"venue"
},
  "geometry": {"coordinates":[-82.035515,33.401453],"type":"Point"}
}