{
  "type": "Feature",
  "properties": {
    "addr:full":"246 Etheridge Rd Auburn GA 30011",
    "addr:housenumber":"246",
    "addr:postcode":"30011",
    "addr:street":"Etheridge Rd",
    "iso:country":"US",
    "sg:address":"246 Etheridge Rd",
    "sg:city":"Auburn",
    "sg:classifiers":[
        {
            "category":"Building & Trades",
            "subcategory":"Landscaping Services",
            "type":"Services"
        }
    ],
    "sg:phone":"+1 770 682 8733",
    "sg:postcode":"30011",
    "sg:province":"GA",
    "wof:name":"Pixie Forest Tree Care & Nurs",
    "wof:placetype":"venue"
},
  "geometry": {"coordinates":[-83.840529,34.020599],"type":"Point"}
}