{
  "type": "Feature",
  "properties": {
    "addr:full":"127 Shawns Way Augusta GA 30907",
    "addr:housenumber":"127",
    "addr:postcode":"30907",
    "addr:street":"Shawns Way",
    "iso:country":"US",
    "sg:address":"127 Shawns Way",
    "sg:city":"Augusta",
    "sg:classifiers":[
        {
            "category":"Building & Trades",
            "subcategory":"Plumbing",
            "type":"Services"
        }
    ],
    "sg:phone":"+1 706 650 7941",
    "sg:postcode":"30907",
    "sg:province":"GA",
    "sg:tags":[
        "contractor"
    ],
    "wof:name":"BJ Plumbing Company Inc",
    "wof:placetype":"venue"
},
  "geometry": {"coordinates":[-82.124612,33.511977],"type":"Point"}
}