{
  "type": "Feature",
  "properties": {
    "iso:country":"US",
    "sg:address":"125 Glynn St N",
    "sg:city":"Fayetteville",
    "sg:classifiers":[
        {
            "category":"Insurance",
            "subcategory":"Insurance Agent",
            "type":"Services"
        }
    ],
    "sg:phone":"+1 770 460 0178",
    "sg:postcode":"30214",
    "sg:province":"GA",
    "wof:name":"State Farm Insurance",
    "wof:placetype":"venue"
},
  "geometry": {"coordinates":[-84.45505300000001,33.448627],"type":"Point"}
}