{
  "type": "Feature",
  "properties": {
    "addr:full":"3565 Austell Rd SW Ste 19 Marietta GA 30008",
    "addr:housenumber":"3565",
    "addr:postcode":"30008",
    "addr:street":"Austell Rd Sw Ste 19",
    "iso:country":"US",
    "sg:address":"3565 Austell Rd SW Ste 19",
    "sg:city":"Marietta",
    "sg:classifiers":[
        {
            "category":"Professional",
            "subcategory":"Accounting & Tax Preparation",
            "type":"Services"
        },
        {
            "category":"Banks & Credit Unions",
            "subcategory":"Financial Services",
            "type":"Services"
        }
    ],
    "sg:phone":"+1 770 384 0737",
    "sg:postcode":"30008",
    "sg:province":"GA",
    "sg:tags":[
        "return",
        "preparation-business",
        "taxes-consultants",
        "loan",
        "representative",
        "alternative",
        "bookkeeping"
    ],
    "sg:website":"http://www.hrblock.com",
    "wof:name":"H & R Block",
    "wof:placetype":"venue"
},
  "geometry": {"coordinates":[-84.593902,33.865697],"type":"Point"}
}