{
  "type": "Feature",
  "properties": {
    "addr:full":"5527 Thomaston Rd Macon GA 31220",
    "addr:housenumber":"5527",
    "addr:postcode":"31220",
    "addr:street":"Thomaston Rd",
    "iso:country":"US",
    "sg:address":"5527 Thomaston Rd",
    "sg:city":"Macon",
    "sg:classifiers":[
        {
            "category":"Wholesale",
            "subcategory":"Hardware",
            "type":"Manufacturing & Wholesale Goods"
        },
        {
            "category":"Building & Trades",
            "subcategory":"Plumbing",
            "type":"Services"
        }
    ],
    "sg:phone":"+1 478 474 8544",
    "sg:postcode":"31220",
    "sg:province":"GA",
    "sg:tags":[
        "plumbing",
        "conditioning",
        "air",
        "system",
        "contractor"
    ],
    "wof:name":"Mingledorff's Inc",
    "wof:placetype":"venue"
},
  "geometry": {"coordinates":[-83.741871,32.834059],"type":"Point"}
}