{
  "type": "Feature",
  "properties": {
    "iso:country":"US",
    "sg:address":"3330 Cumberland Blvd SE",
    "sg:city":"Atlanta",
    "sg:classifiers":[
        {
            "category":"Real Estate",
            "subcategory":"Real Estate Operator",
            "type":"Services"
        }
    ],
    "sg:phone":"+1 404 442 7225",
    "sg:postcode":"30339",
    "sg:province":"GA",
    "sg:tags":[
        "industrial",
        "corporate",
        "developer"
    ],
    "wof:name":"Jennings Tooker Corp",
    "wof:placetype":"venue"
},
  "geometry": {"coordinates":[-84.458865,33.878458],"type":"Point"}
}