{
  "type": "Feature",
  "properties": {
    "addr:full":"170 Glynn St S Fayetteville GA 30214",
    "addr:housenumber":"170",
    "addr:postcode":"30214",
    "addr:street":"Glynn St S",
    "iso:country":"US",
    "sg:address":"170 Glynn St S",
    "sg:city":"Fayetteville",
    "sg:classifiers":[
        {
            "category":"Banks & Credit Unions",
            "subcategory":"Bank",
            "type":"Services"
        }
    ],
    "sg:phone":"+1 770 461 2265",
    "sg:postcode":"30214",
    "sg:province":"GA",
    "wof:name":"South Crest Bank",
    "wof:placetype":"venue"
},
  "geometry": {"coordinates":[-84.45512600000001,33.446872],"type":"Point"}
}