{
  "type": "Feature",
  "properties": {
    "addr:full":"1150 Hammond Dr NE Atlanta GA 30328",
    "addr:housenumber":"1150",
    "addr:postcode":"30328",
    "addr:street":"Hammond Dr Ne",
    "iso:country":"US",
    "sg:address":"1150 Hammond Dr NE",
    "sg:city":"Atlanta",
    "sg:classifiers":[
        {
            "category":"Professional",
            "subcategory":"Business Services",
            "type":"Services"
        }
    ],
    "sg:phone":"+1 770 698 8900",
    "sg:postcode":"30328",
    "sg:province":"GA",
    "sg:tags":[
        "interior",
        "consultant",
        "design",
        "decorator"
    ],
    "wof:name":"Expressions",
    "wof:placetype":"venue"
},
  "geometry": {"coordinates":[-84.35034,33.919032],"type":"Point"}
}