{
  "type": "Feature",
  "properties": {
    "iso:country":"US",
    "sg:address":"1507 Martin Luther King Dr",
    "sg:city":"Waycross",
    "sg:classifiers":[
        {
            "category":"Organizations",
            "subcategory":"Religious Organization",
            "type":"Services"
        }
    ],
    "sg:phone":"+1 912 287 0507",
    "sg:postcode":"31501",
    "sg:province":"GA",
    "sg:tags":[
        "church"
    ],
    "wof:name":"Northside Church of Christ",
    "wof:placetype":"venue"
},
  "geometry": {"coordinates":[-82.36605,31.229331],"type":"Point"}
}