{
  "type": "Feature",
  "properties": {
    "iso:country":"US",
    "sg:address":"5750 Long Island Drive NW",
    "sg:city":"Atlanta",
    "sg:classifiers":[
        {
            "category":"Education",
            "subcategory":"School",
            "type":"Public Place"
        },
        {
            "category":"Education",
            "subcategory":"University",
            "type":"Public Place"
        }
    ],
    "sg:phone":"+1 404 252 3910",
    "sg:postcode":"30327",
    "sg:province":"GA",
    "sg:tags":[
        "high",
        "middle",
        "college",
        "elementary"
    ],
    "sg:website":"www.firstmontessori.org",
    "wof:name":"Association Montessori Internationale",
    "wof:placetype":"venue"
},
  "geometry": {"coordinates":[-84.392154,33.910944],"type":"Point"}
}