{
  "type": "Feature",
  "properties": {
    "addr:full":"3935 State Rte 34 Sharpsburg GA 30277",
    "addr:housenumber":"3935",
    "addr:postcode":"30277",
    "addr:street":"State Rte 34",
    "iso:country":"US",
    "sg:address":"3935 State Rte 34",
    "sg:city":"Sharpsburg",
    "sg:classifiers":[
        {
            "category":"Organizations",
            "subcategory":"Religious Organization",
            "type":"Services"
        }
    ],
    "sg:phone":"+1 770 251 3777",
    "sg:postcode":"30277",
    "sg:province":"GA",
    "wof:name":"Peachtree City Church Of God",
    "wof:placetype":"venue"
},
  "geometry": {"coordinates":[-84.647796,33.401274],"type":"Point"}
}