{
  "type": "Feature",
  "properties": {
    "iso:country":"US",
    "sg:address":"1418 Knollwood Ter",
    "sg:city":"Decatur",
    "sg:classifiers":[
        {
            "category":"Organizations",
            "subcategory":"Community Association",
            "type":"Services"
        }
    ],
    "sg:phone":"+1 706 353 7117",
    "sg:postcode":"30033",
    "sg:province":"GA",
    "wof:name":"Delta Tau Delta Fraternity",
    "wof:placetype":"venue"
},
  "geometry": {"coordinates":[-84.295709,33.820521],"type":"Point"}
}