{
  "type": "Feature",
  "properties": {
    "iso:country":"US",
    "sg:address":"1512 Piedmont Avenue NE",
    "sg:city":"Atlanta",
    "sg:classifiers":[
        {
            "category":"Health Services",
            "subcategory":"Dentist",
            "type":"Services"
        }
    ],
    "sg:phone":"+1 404 873 2957",
    "sg:postcode":"30324",
    "sg:province":"GA",
    "wof:name":"Hooker Richard M D D S",
    "wof:placetype":"venue"
},
  "geometry": {"coordinates":[-84.371813,33.8009],"type":"Point"}
}