{
  "type": "Feature",
  "properties": {
    "addr:full":"5409 Shanna Ct Columbus GA 31907",
    "addr:housenumber":"5409",
    "addr:postcode":"31907",
    "addr:street":"Shanna Ct",
    "iso:country":"US",
    "sg:address":"5409 Shanna Ct",
    "sg:city":"Columbus",
    "sg:classifiers":[
        {
            "category":"Professional",
            "type":"Services"
        }
    ],
    "sg:phone":"+1 706 565 4729",
    "sg:postcode":"31907",
    "sg:province":"GA",
    "wof:name":"Gray Given Inc",
    "wof:placetype":"venue"
},
  "geometry": {"coordinates":[-84.88325,32.519116],"type":"Point"}
}