{
  "type": "Feature",
  "properties": {
    "iso:country":"US",
    "sg:address":"2900 Chamblee Tucker Rd # 9",
    "sg:city":"Atlanta",
    "sg:classifiers":[
        {
            "category":"Wholesale",
            "subcategory":"Computers",
            "type":"Manufacturing & Wholesale Goods"
        },
        {
            "category":"Professional",
            "subcategory":"Computer Services",
            "type":"Services"
        }
    ],
    "sg:phone":"+1 770 986 8887",
    "sg:postcode":"30341",
    "sg:province":"GA",
    "sg:tags":[
        "publisher",
        "cd-rom",
        "equipment",
        "software",
        "developer"
    ],
    "sg:website":"http://www.marx.com",
    "wof:name":"Marx Software Security",
    "wof:placetype":"venue"
},
  "geometry": {"coordinates":[-84.271019,33.877861],"type":"Point"}
}