{
  "type": "Feature",
  "properties": {
    "addr:full":"5450 N Henry Blvd Stockbridge GA 30281",
    "addr:housenumber":"5450",
    "addr:postcode":"30281",
    "addr:street":"N Henry Blvd",
    "iso:country":"US",
    "sg:address":"5450 N Henry Blvd",
    "sg:city":"Stockbridge",
    "sg:classifiers":[
        {
            "category":"Retail",
            "subcategory":"Car Wash",
            "type":"Services"
        }
    ],
    "sg:phone":"+1 678 289 8126",
    "sg:postcode":"30281",
    "sg:province":"GA",
    "sg:tags":[
        "polishing",
        "washing"
    ],
    "wof:name":"Wash Me Fast",
    "wof:placetype":"venue"
},
  "geometry": {"coordinates":[-84.25857000000001,33.552889],"type":"Point"}
}