{
  "type": "Feature",
  "properties": {
    "iso:country":"US",
    "sg:address":"607 N Washington St",
    "sg:city":"Albany",
    "sg:classifiers":[
        {
            "category":"Building & Trades",
            "subcategory":"Plumbing",
            "type":"Services"
        }
    ],
    "sg:phone":"+1 229 435 3300",
    "sg:postcode":"31701",
    "sg:province":"GA",
    "sg:tags":[
        "repair",
        "contractor",
        "re"
    ],
    "wof:name":"Dougherty Heating & Cooling",
    "wof:placetype":"venue"
},
  "geometry": {"coordinates":[-84.151526,31.586009],"type":"Point"}
}