{
  "type": "Feature",
  "properties": {
    "addr:full":"10455 Woodruff Rd Fairburn GA 30213",
    "addr:housenumber":"10455",
    "addr:postcode":"30213",
    "addr:street":"Woodruff Rd",
    "iso:country":"US",
    "sg:address":"10455 Woodruff Rd",
    "sg:city":"Fairburn",
    "sg:classifiers":[
        {
            "category":"Building & Trades",
            "subcategory":"Plumbing",
            "type":"Services"
        }
    ],
    "sg:phone":"+1 770 306 9592",
    "sg:postcode":"30213",
    "sg:province":"GA",
    "sg:tags":[
        "contractor"
    ],
    "wof:name":"Professional Plumbing",
    "wof:placetype":"venue"
},
  "geometry": {"coordinates":[-84.729957,33.600561],"type":"Point"}
}