{
  "type": "Feature",
  "properties": {
    "addr:full":"7391 Hodgson Memorial Dr Savannah GA 31406",
    "addr:housenumber":"7391",
    "addr:postcode":"31406",
    "addr:street":"Hodgson Memorial Dr",
    "iso:country":"US",
    "sg:address":"7391 Hodgson Memorial Dr",
    "sg:city":"Savannah",
    "sg:classifiers":[
        {
            "category":"Insurance",
            "subcategory":"Insurance Agent",
            "type":"Services"
        }
    ],
    "sg:phone":"+1 912 920 2800",
    "sg:postcode":"31406",
    "sg:province":"GA",
    "wof:name":"Glass Compton & Stevens",
    "wof:placetype":"venue"
},
  "geometry": {"coordinates":[-81.113254,32.001372],"type":"Point"}
}