{
  "type": "Feature",
  "properties": {
    "addr:full":"1331 Wesley Pkwy NW Atlanta GA 30327",
    "addr:housenumber":"1331",
    "addr:postcode":"30327",
    "addr:street":"Wesley Pkwy Nw",
    "iso:country":"US",
    "sg:address":"1331 Wesley Pkwy NW",
    "sg:city":"Atlanta",
    "sg:classifiers":[
        {
            "category":"Organizations",
            "subcategory":"Religious Organization",
            "type":"Services"
        }
    ],
    "sg:phone":"+1 404 351 1928",
    "sg:postcode":"30327",
    "sg:province":"GA",
    "wof:name":"Ebenezer Assoc LLC",
    "wof:placetype":"venue"
},
  "geometry": {"coordinates":[-84.431465,33.834375],"type":"Point"}
}