{
  "type": "Feature",
  "properties": {
    "iso:country":"US",
    "sg:address":"315 Church St",
    "sg:city":"Dahlonega",
    "sg:classifiers":[
        {
            "category":"Shopping",
            "subcategory":"Crafts & Fabrics",
            "type":"Retail Goods"
        }
    ],
    "sg:phone":"+1 706 867 8918",
    "sg:postcode":"30533",
    "sg:province":"GA",
    "sg:tags":[
        "sewing"
    ],
    "wof:name":"Magical Threads Inc",
    "wof:placetype":"venue"
},
  "geometry": {"coordinates":[-83.987565,34.532457],"type":"Point"}
}