{
  "type": "Feature",
  "properties": {
    "addr:full":"3650 Satellite Blvd Duluth GA 30096",
    "addr:housenumber":"3650",
    "addr:postcode":"30096",
    "addr:street":"Satellite Blvd",
    "iso:country":"US",
    "sg:address":"3650 Satellite Blvd",
    "sg:city":"Duluth",
    "sg:classifiers":[
        {
            "category":"Personal",
            "type":"Services"
        }
    ],
    "sg:phone":"+1 770 814 8801",
    "sg:postcode":"30096",
    "sg:province":"GA",
    "sg:tags":[
        "party",
        "planning",
        "event"
    ],
    "wof:name":"Laser Quest",
    "wof:placetype":"venue"
},
  "geometry": {"coordinates":[-84.137027,33.957499],"type":"Point"}
}