{
  "type": "Feature",
  "properties": {
    "addr:full":"3730 Holcomb Bridge Rd Norcross GA 30092",
    "addr:housenumber":"3730",
    "addr:postcode":"30092",
    "addr:street":"Holcomb Bridge Rd",
    "iso:country":"US",
    "sg:address":"3730 Holcomb Bridge Rd",
    "sg:city":"Norcross",
    "sg:classifiers":[
        {
            "category":"Professional",
            "subcategory":"Business Services",
            "type":"Services"
        }
    ],
    "sg:phone":"+1 770 263 8455",
    "sg:postcode":"30092",
    "sg:province":"GA",
    "wof:name":"A P Presentation",
    "wof:placetype":"venue"
},
  "geometry": {"coordinates":[-84.248412,33.960417],"type":"Point"}
}