{
  "type": "Feature",
  "properties": {
    "addr:full":"519 W Memorial Dr Dallas GA 30132",
    "addr:housenumber":"519",
    "addr:postcode":"30132",
    "addr:street":"W Memorial Dr",
    "iso:country":"US",
    "sg:address":"519 W Memorial Dr",
    "sg:city":"Dallas",
    "sg:classifiers":[
        {
            "category":"Local Transit",
            "type":"Transportation"
        }
    ],
    "sg:phone":"+1 770 443 2882",
    "sg:postcode":"30132",
    "sg:province":"GA",
    "sg:tags":[
        "passenger"
    ],
    "wof:name":"Shashas Cab & Limo Service",
    "wof:placetype":"venue"
},
  "geometry": {"coordinates":[-84.85083299999999,33.921812],"type":"Point"}
}