{
  "type": "Feature",
  "properties": {
    "addr:full":"166 Britton Rd Jackson GA 30233",
    "addr:housenumber":"166",
    "addr:postcode":"30233",
    "addr:street":"Britton Rd",
    "iso:country":"US",
    "sg:address":"166 Britton Rd",
    "sg:city":"Jackson",
    "sg:classifiers":[
        {
            "category":"Farming",
            "subcategory":"Farm",
            "type":"Manufacturing & Wholesale Goods"
        }
    ],
    "sg:phone":"+1 770 775 3661",
    "sg:postcode":"30233",
    "sg:province":"GA",
    "sg:tags":[
        "crop",
        "general"
    ],
    "wof:name":"Marion Brittion",
    "wof:placetype":"venue"
},
  "geometry": {"coordinates":[-84.049286,33.267898],"type":"Point"}
}