{
  "type": "Feature",
  "properties": {
    "addr:full":"31 Ivy Chase Way Atlanta GA 30342",
    "addr:housenumber":"31",
    "addr:postcode":"30342",
    "addr:street":"Ivy Chase Way",
    "iso:country":"US",
    "sg:address":"31 Ivy Chase Way",
    "sg:city":"Atlanta",
    "sg:classifiers":[
        {
            "category":"Building & Trades",
            "subcategory":"Construction",
            "type":"Services"
        }
    ],
    "sg:phone":"+1 404 816 9040",
    "sg:postcode":"30342",
    "sg:province":"GA",
    "sg:tags":[
        "house"
    ],
    "wof:name":"G Evans Inc",
    "wof:placetype":"venue"
},
  "geometry": {"coordinates":[-84.380668,33.856959],"type":"Point"}
}