{
  "type": "Feature",
  "properties": {
    "addr:full":"163 Tiburon Dr Lithonia GA 30038",
    "addr:housenumber":"163",
    "addr:postcode":"30038",
    "addr:street":"Tiburon Dr",
    "iso:country":"US",
    "sg:address":"163 Tiburon Dr",
    "sg:city":"Lithonia",
    "sg:classifiers":[
        {
            "category":"Building & Trades",
            "subcategory":"Construction",
            "type":"Services"
        }
    ],
    "sg:phone":"+1 770 987 0393",
    "sg:postcode":"30038",
    "sg:province":"GA",
    "sg:tags":[
        "residential"
    ],
    "wof:name":"Colby At Work Home Improvement",
    "wof:placetype":"venue"
},
  "geometry": {"coordinates":[-84.15029,33.70225],"type":"Point"}
}