{
  "type": "Feature",
  "properties": {
    "iso:country":"US",
    "sg:address":"241 Singletary Rd",
    "sg:city":"Cairo",
    "sg:classifiers":[
        {
            "category":"Professional",
            "type":"Services"
        }
    ],
    "sg:phone":"+1 229 377 8814",
    "sg:postcode":"39828",
    "sg:province":"GA",
    "sg:tags":[
        "establishment"
    ],
    "wof:name":"Fulghum Fibres Inc",
    "wof:placetype":"venue"
},
  "geometry": {"coordinates":[-84.146416,30.866395],"type":"Point"}
}