{
  "type": "Feature",
  "properties": {
    "iso:country":"US",
    "sg:address":"1558 Riverstone Pkwy",
    "sg:city":"Canton",
    "sg:classifiers":[
        {
            "category":"Shopping",
            "subcategory":"Books",
            "type":"Retail Goods"
        }
    ],
    "sg:phone":"+1 770 479 5005",
    "sg:postcode":"30114",
    "sg:province":"GA",
    "sg:tags":[
        "bookstore"
    ],
    "sg:website":"www.familychristian.com",
    "wof:name":"Family Christian Stores",
    "wof:placetype":"venue"
},
  "geometry": {"coordinates":[-84.46219600000001,34.261299],"type":"Point"}
}