{
  "type": "Feature",
  "properties": {
    "iso:country":"US",
    "sg:address":"1008 Bay St",
    "sg:city":"Brunswick",
    "sg:classifiers":[
        {
            "category":"Food & Beverages",
            "subcategory":"Groceries & Convenience Stores",
            "type":"Retail Goods"
        }
    ],
    "sg:phone":"+1 912 466 9005",
    "sg:postcode":"31520",
    "sg:province":"GA",
    "wof:name":"Amerimart",
    "wof:placetype":"venue"
},
  "geometry": {"coordinates":[-81.49687900000001,31.152828],"type":"Point"}
}