{
  "type": "Feature",
  "properties": {
    "addr:full":"1044 Whispering Woods Dr Canton GA 30114",
    "addr:housenumber":"1044",
    "addr:postcode":"30114",
    "addr:street":"Whispering Woods Dr",
    "iso:country":"US",
    "sg:address":"1044 Whispering Woods Dr",
    "sg:city":"Canton",
    "sg:classifiers":[
        {
            "category":"Manufacturing",
            "subcategory":"Wood Products",
            "type":"Manufacturing & Wholesale Goods"
        }
    ],
    "sg:phone":"+1 678 907 7627",
    "sg:postcode":"30114",
    "sg:province":"GA",
    "sg:tags":[
        "millwork-wholesale",
        "millwork",
        "manufacturer"
    ],
    "wof:name":"Wyatt's Woodworking",
    "wof:placetype":"venue"
},
  "geometry": {"coordinates":[-84.496889,34.257117],"type":"Point"}
}