{
  "type": "Feature",
  "properties": {
    "iso:country":"US",
    "sg:address":"3030 Greenwood Trl",
    "sg:city":"Marietta",
    "sg:classifiers":[
        {
            "category":"Real Estate",
            "subcategory":"Real Estate Agent",
            "type":"Services"
        }
    ],
    "sg:phone":"+1 770 955 3950",
    "sg:postcode":"30067",
    "sg:province":"GA",
    "sg:tags":[
        "property",
        "lessor"
    ],
    "wof:name":"Bobbie Pardue Ltd",
    "wof:placetype":"venue"
},
  "geometry": {"coordinates":[-84.46603899999999,33.932551],"type":"Point"}
}