{
  "type": "Feature",
  "properties": {
    "iso:country":"US",
    "sg:address":"1953 Rosebud Rd SW",
    "sg:city":"Grayson",
    "sg:classifiers":[
        {
            "category":"Retail",
            "subcategory":"Auto Repair",
            "type":"Services"
        }
    ],
    "sg:phone":"+1 678 376 2777",
    "sg:postcode":"30017",
    "sg:province":"GA",
    "sg:tags":[
        "automotive",
        "center"
    ],
    "wof:name":"Grayson Stone Mtn Car Care Ctr",
    "wof:placetype":"venue"
},
  "geometry": {"coordinates":[-83.95977499999999,33.896121],"type":"Point"}
}