{
  "type": "Feature",
  "properties": {
    "addr:full":"3983 Lavista Rd Ste 104 Tucker GA 30084",
    "addr:housenumber":"3983",
    "addr:postcode":"30084",
    "addr:street":"Lavista Rd Ste 104",
    "iso:country":"US",
    "sg:address":"3983 Lavista Rd Ste 104",
    "sg:city":"Tucker",
    "sg:classifiers":[
        {
            "category":"Health Services",
            "subcategory":"Doctor",
            "type":"Services"
        }
    ],
    "sg:phone":"+1 770 723 1111",
    "sg:postcode":"30084",
    "sg:province":"GA",
    "sg:tags":[
        "surgeon",
        "oral"
    ],
    "sg:website":"www.drpinsky.com",
    "wof:name":"Pinsky Richard DDS",
    "wof:placetype":"venue"
},
  "geometry": {"coordinates":[-84.25430299999999,33.846199],"type":"Point"}
}