{
  "type": "Feature",
  "properties": {
    "addr:full":"3286 Inner Perimeter Rd Valdosta GA 31602",
    "addr:housenumber":"3286",
    "addr:postcode":"31602",
    "addr:street":"Inner Perimeter Rd",
    "iso:country":"US",
    "sg:address":"3286 Inner Perimeter Rd",
    "sg:city":"Valdosta",
    "sg:classifiers":[
        {
            "category":"Restaurant",
            "type":"Food & Drink"
        }
    ],
    "sg:phone":"+1 229 244 4785",
    "sg:postcode":"31602",
    "sg:province":"GA",
    "sg:tags":[
        "eating"
    ],
    "wof:name":"Ryans",
    "wof:placetype":"venue"
},
  "geometry": {"coordinates":[-83.291078,30.882403],"type":"Point"}
}