{
  "type": "Feature",
  "properties": {
    "addr:full":"1838 Old Norcross Rd Lawrenceville GA 30044",
    "addr:housenumber":"1838",
    "addr:postcode":"30044",
    "addr:street":"Old Norcross Rd",
    "iso:country":"US",
    "sg:address":"1838 Old Norcross Rd",
    "sg:city":"Lawrenceville",
    "sg:classifiers":[
        {
            "category":"Banks & Credit Unions",
            "subcategory":"Bank",
            "type":"Services"
        }
    ],
    "sg:phone":"+1 770 237 5898",
    "sg:postcode":"30044",
    "sg:province":"GA",
    "sg:tags":[
        "mortgage",
        "loan",
        "broker",
        "real estate"
    ],
    "wof:name":"Primehomes Finance Corp",
    "wof:placetype":"venue"
},
  "geometry": {"coordinates":[-84.05626700000001,33.952682],"type":"Point"}
}