{
  "type": "Feature",
  "properties": {
    "iso:country":"US",
    "sg:address":"260 Red Plum Knoll",
    "sg:city":"Demorest",
    "sg:classifiers":[
        {
            "category":"Manufacturing",
            "subcategory":"Tools & Machinery",
            "type":"Manufacturing & Wholesale Goods"
        }
    ],
    "sg:phone":"+1 706 754 8761",
    "sg:postcode":"30535",
    "sg:province":"GA",
    "sg:tags":[
        "textile",
        "mfg"
    ],
    "wof:name":"Saurer Textile Sys Charlotte",
    "wof:placetype":"venue"
},
  "geometry": {"coordinates":[-83.631118,34.577238],"type":"Point"}
}