{
  "type": "Feature",
  "properties": {
    "addr:full":"740 Prince Ave Athens GA 30606",
    "addr:housenumber":"740",
    "addr:postcode":"30606",
    "addr:street":"Prince Ave",
    "iso:country":"US",
    "sg:address":"740 Prince Ave",
    "sg:city":"Athens",
    "sg:classifiers":[
        {
            "category":"Shopping",
            "subcategory":"Optical Goods",
            "type":"Retail Goods"
        },
        {
            "category":"Health Services",
            "subcategory":"Optometrist",
            "type":"Services"
        }
    ],
    "sg:phone":"+1 706 543 8958",
    "sg:postcode":"30606",
    "sg:province":"GA",
    "sg:tags":[
        "optician"
    ],
    "wof:name":"Logan Opticians",
    "wof:placetype":"venue"
},
  "geometry": {"coordinates":[-83.39079099999999,33.961655],"type":"Point"}
}