{
  "type": "Feature",
  "properties": {
    "addr:full":"1815 Hembree Road Suite 208 Alpharetta GA 30009",
    "addr:housenumber":"1815",
    "addr:postcode":"30009",
    "addr:street":"Hembree Road Suite 208",
    "iso:country":"US",
    "sg:address":"1815 Hembree Road Suite 208",
    "sg:city":"Alpharetta",
    "sg:classifiers":[
        {
            "category":"Bakery",
            "type":"Food & Drink"
        }
    ],
    "sg:phone":"+1 770 777 2253",
    "sg:postcode":"30009",
    "sg:province":"GA",
    "sg:website":"www.danishdelightbakery.com",
    "wof:name":"Danish Delight Bakery",
    "wof:placetype":"venue"
},
  "geometry": {"coordinates":[-84.304018,34.060695],"type":"Point"}
}