{
  "type": "Feature",
  "properties": {
    "addr:full":"355 Creekside Ct Alpharetta GA 30022",
    "addr:housenumber":"355",
    "addr:postcode":"30022",
    "addr:street":"Creekside Ct",
    "iso:country":"US",
    "sg:address":"355 Creekside Ct",
    "sg:city":"Alpharetta",
    "sg:classifiers":[
        {
            "category":"Real Estate",
            "subcategory":"Real Estate Agent",
            "type":"Services"
        }
    ],
    "sg:phone":"+1 678 339 9855",
    "sg:postcode":"30022",
    "sg:province":"GA",
    "wof:name":"Market Masters Realty Inc",
    "wof:placetype":"venue"
},
  "geometry": {"coordinates":[-84.225657,34.058472],"type":"Point"}
}