{
  "type": "Feature",
  "properties": {
    "addr:full":"2575 Cbb Intrntnl Blvd NW Ste D Kennesaw GA 30152",
    "addr:housenumber":"2575",
    "addr:postcode":"30152",
    "addr:street":"Cbb Intrntnl Blvd Nw Ste D",
    "iso:country":"US",
    "sg:address":"2575 Cbb Intrntnl Blvd NW Ste D",
    "sg:city":"Kennesaw",
    "sg:classifiers":[
        {
            "category":"Professional",
            "subcategory":"Computer Services",
            "type":"Services"
        }
    ],
    "sg:phone":"+1 770 422 9490",
    "sg:postcode":"30152",
    "sg:province":"GA",
    "sg:tags":[
        "repair"
    ],
    "wof:name":"Dawn Electronics Inc",
    "wof:placetype":"venue"
},
  "geometry": {"coordinates":[-84.64859800000001,34.004002],"type":"Point"}
}