{
  "type": "Feature",
  "properties": {
    "iso:country":"US",
    "sg:address":"802 S Madison St",
    "sg:city":"Quitman",
    "sg:classifiers":[
        {
            "category":"Retail",
            "subcategory":"Repair Shop",
            "type":"Services"
        }
    ],
    "sg:phone":"+1 229 263 5040",
    "sg:postcode":"31643",
    "sg:province":"GA",
    "sg:tags":[
        "small",
        "engine",
        "lawn",
        "mower"
    ],
    "wof:name":"Carney Brother Small Engine",
    "wof:placetype":"venue"
},
  "geometry": {"coordinates":[-83.56139899999999,30.779548],"type":"Point"}
}