{
  "type": "Feature",
  "properties": {
    "addr:full":"6329 Jonesboro Rd Morrow GA 30260",
    "addr:housenumber":"6329",
    "addr:postcode":"30260",
    "addr:street":"Jonesboro Rd",
    "iso:country":"US",
    "sg:address":"6329 Jonesboro Rd",
    "sg:city":"Morrow",
    "sg:classifiers":[
        {
            "category":"Recreation",
            "type":"Entertainment"
        }
    ],
    "sg:phone":"+1 770 960 1234",
    "sg:postcode":"30260",
    "sg:province":"GA",
    "sg:tags":[
        "karate",
        "studio"
    ],
    "wof:name":"Brian Karate Smith",
    "wof:placetype":"venue"
},
  "geometry": {"coordinates":[-84.338708,33.586776],"type":"Point"}
}