{
  "type": "Feature",
  "properties": {
    "addr:full":"46 Plantation Drive NE Atlanta GA 30324",
    "addr:housenumber":"46",
    "addr:postcode":"30324",
    "addr:street":"Plantation Drive Ne",
    "iso:country":"US",
    "sg:address":"46 Plantation Drive NE",
    "sg:city":"Atlanta",
    "sg:classifiers":[
        {
            "category":"Real Estate",
            "subcategory":"Real Estate Operator",
            "type":"Services"
        }
    ],
    "sg:phone":"+1 404 237 0048",
    "sg:postcode":"30324",
    "sg:province":"GA",
    "sg:tags":[
        "apartment"
    ],
    "wof:name":"The Plantation At Lenox",
    "wof:placetype":"venue"
},
  "geometry": {"coordinates":[-84.35383299999999,33.836698],"type":"Point"}
}