{
  "type": "Feature",
  "properties": {
    "addr:full":"586 Buckeye Cir SE Conyers GA 30094",
    "addr:housenumber":"586",
    "addr:postcode":"30094",
    "addr:street":"Buckeye Cir Se",
    "iso:country":"US",
    "sg:address":"586 Buckeye Cir SE",
    "sg:city":"Conyers",
    "sg:classifiers":[
        {
            "category":"Building & Trades",
            "subcategory":"Construction",
            "type":"Services"
        }
    ],
    "sg:phone":"+1 770 918 9299",
    "sg:postcode":"30094",
    "sg:province":"GA",
    "sg:tags":[
        "residential"
    ],
    "wof:name":"Brothers 2 Prof Turnkey",
    "wof:placetype":"venue"
},
  "geometry": {"coordinates":[-84.026625,33.555752],"type":"Point"}
}