{
  "type": "Feature",
  "properties": {
    "iso:country":"US",
    "sg:address":"3895 Peachtree Rd NE",
    "sg:city":"Atlanta",
    "sg:classifiers":[
        {
            "category":"Restaurant",
            "type":"Food & Drink"
        }
    ],
    "sg:menulink":"http://www.allmenus.com/ga/chamblee-doraville/242083-pizza-k/menu/",
    "sg:phone":"+1 770 237 8845",
    "sg:postcode":"30319",
    "sg:province":"GA",
    "sg:tags":[
        "american",
        "pizza"
    ],
    "wof:name":"Pizza K",
    "wof:placetype":"venue"
},
  "geometry": {"coordinates":[-84.343783,33.857522],"type":"Point"}
}