{
  "type": "Feature",
  "properties": {
    "addr:full":"443 Cohran Store Rd Douglasville GA 30134",
    "addr:housenumber":"443",
    "addr:postcode":"30134",
    "addr:street":"Cohran Store Rd",
    "iso:country":"US",
    "sg:address":"443 Cohran Store Rd",
    "sg:city":"Douglasville",
    "sg:classifiers":[
        {
            "category":"Shopping",
            "type":"Retail Goods"
        }
    ],
    "sg:phone":"+1 770 489 1432",
    "sg:postcode":"30134",
    "sg:province":"GA",
    "sg:tags":[
        "merchandise"
    ],
    "wof:name":"Unique Handcrafts Inc",
    "wof:placetype":"venue"
},
  "geometry": {"coordinates":[-84.83022699999999,33.796386],"type":"Point"}
}