{
  "type": "Feature",
  "properties": {
    "iso:country":"US",
    "sg:address":"1 Coca Cola Plaza NW",
    "sg:city":"Atlanta",
    "sg:classifiers":[
        {
            "category":"Food & Beverages",
            "subcategory":"Specialty",
            "type":"Retail Goods"
        }
    ],
    "sg:postcode":"30313",
    "sg:province":"GA",
    "sg:website":"www.qoo.com.sg/home/default_flas...",
    "wof:name":"Qoo",
    "wof:placetype":"venue"
},
  "geometry": {"coordinates":[-84.397165,33.769509],"type":"Point"}
}