{
  "type": "Feature",
  "properties": {
    "addr:full":"611 Forest Cir Douglas GA 31533",
    "addr:housenumber":"611",
    "addr:postcode":"31533",
    "addr:street":"Forest Cir",
    "iso:country":"US",
    "sg:address":"611 Forest Cir",
    "sg:city":"Douglas",
    "sg:classifiers":[
        {
            "category":"Retail",
            "subcategory":"Veterinary Services",
            "type":"Services"
        }
    ],
    "sg:phone":"+1 912 384 2164",
    "sg:postcode":"31533",
    "sg:province":"GA",
    "sg:tags":[
        "veterinarian"
    ],
    "wof:name":"James P Gossett DVM",
    "wof:placetype":"venue"
},
  "geometry": {"coordinates":[-82.841846,31.520499],"type":"Point"}
}