{
  "type": "Feature",
  "properties": {
    "addr:full":"2112 Fairburn Rd Douglasville GA 30135",
    "addr:housenumber":"2112",
    "addr:postcode":"30135",
    "addr:street":"Fairburn Rd",
    "iso:country":"US",
    "sg:address":"2112 Fairburn Rd",
    "sg:city":"Douglasville",
    "sg:phone":"+1 770 577 0420",
    "sg:postcode":"30135",
    "sg:province":"GA",
    "sg:website":"http://www.sunshinehouse.com",
    "wof:name":"Sunshine House",
    "wof:placetype":"venue"
},
  "geometry": {"coordinates":[-84.702118,33.747904],"type":"Point"}
}