{
  "type": "Feature",
  "properties": {
    "iso:country":"US",
    "sg:address":"28 Early Ct",
    "sg:city":"Newnan",
    "sg:classifiers":[
        {
            "category":"Real Estate",
            "subcategory":"Real Estate Agent",
            "type":"Services"
        }
    ],
    "sg:phone":"+1 770 304 4593",
    "sg:postcode":"30265",
    "sg:province":"GA",
    "wof:name":"Diane S Woody Appraiser",
    "wof:placetype":"venue"
},
  "geometry": {"coordinates":[-84.689108,33.423303],"type":"Point"}
}