{
  "type": "Feature",
  "properties": {
    "addr:full":"4248 Smithsonia Dr Tucker GA 30084",
    "addr:housenumber":"4248",
    "addr:postcode":"30084",
    "addr:street":"Smithsonia Dr",
    "iso:country":"US",
    "sg:address":"4248 Smithsonia Dr",
    "sg:city":"Tucker",
    "sg:classifiers":[
        {
            "category":"Restaurant",
            "type":"Food & Drink"
        }
    ],
    "sg:phone":"+1 770 934 4389",
    "sg:postcode":"30084",
    "sg:province":"GA",
    "sg:tags":[
        "eating"
    ],
    "wof:name":"Alegory Inc",
    "wof:placetype":"venue"
},
  "geometry": {"coordinates":[-84.213685,33.8678],"type":"Point"}
}