{
  "type": "Feature",
  "properties": {
    "iso:country":"US",
    "sg:address":"108 N Peterson Ave",
    "sg:city":"Douglas",
    "sg:classifiers":[
        {
            "category":"Insurance",
            "subcategory":"Insurance Agent",
            "type":"Services"
        }
    ],
    "sg:phone":"+1 912 384 6200",
    "sg:postcode":"31533",
    "sg:province":"GA",
    "wof:name":"Graham Farms Insurance",
    "wof:placetype":"venue"
},
  "geometry": {"coordinates":[-82.850298,31.509416],"type":"Point"}
}