{
  "type": "Feature",
  "properties": {
    "iso:country":"US",
    "sg:address":"288 Lanier Ave E",
    "sg:city":"Fayetteville",
    "sg:classifiers":[
        {
            "category":"Place Of Worship",
            "subcategory":"Mosque",
            "type":"Public Place"
        }
    ],
    "sg:phone":"+1 770 719 4447",
    "sg:postcode":"30214",
    "sg:province":"GA",
    "wof:name":"The Islamic Community Center of Atlanta",
    "wof:placetype":"venue"
},
  "geometry": {"coordinates":[-84.450822,33.448666],"type":"Point"}
}