{
  "type": "Feature",
  "properties": {
    "iso:country":"US",
    "sg:address":"800 Airport Rd",
    "sg:city":"Lawrenceville",
    "sg:classifiers":[
        {
            "category":"Autos & Motor Vehicles",
            "subcategory":"Automobile Sales",
            "type":"Retail Goods"
        },
        {
            "category":"Airline",
            "type":"Transportation"
        }
    ],
    "sg:phone":"+1 770 513 0000",
    "sg:postcode":"30045",
    "sg:province":"GA",
    "sg:tags":[
        "flight",
        "aircraft",
        "rental",
        "school",
        "airplane"
    ],
    "sg:website":"www.theflightschool.com",
    "wof:name":"Flight School of Gwinnett",
    "wof:placetype":"venue"
},
  "geometry": {"coordinates":[-83.965366,33.982389],"type":"Point"}
}