{
  "type": "Feature",
  "properties": {
    "addr:full":"423 Payton Ct Stockbridge GA 30281",
    "addr:housenumber":"423",
    "addr:postcode":"30281",
    "addr:street":"Payton Ct",
    "iso:country":"US",
    "sg:address":"423 Payton Ct",
    "sg:city":"Stockbridge",
    "sg:classifiers":[
        {
            "category":"Arts & Performance",
            "subcategory":"Theater",
            "type":"Entertainment"
        }
    ],
    "sg:phone":"+1 770 506 4346",
    "sg:postcode":"30281",
    "sg:province":"GA",
    "sg:tags":[
        "group"
    ],
    "wof:name":"Southside Entertainment",
    "wof:placetype":"venue"
},
  "geometry": {"coordinates":[-84.264431,33.530301],"type":"Point"}
}