{
  "type": "Feature",
  "properties": {
    "iso:country":"US",
    "sg:address":"2291 Plunkett Rd NW",
    "sg:city":"Conyers",
    "sg:classifiers":[
        {
            "category":"Manufacturing",
            "subcategory":"Electronics",
            "type":"Manufacturing & Wholesale Goods"
        }
    ],
    "sg:phone":"+1 800 572 3119",
    "sg:postcode":"30012",
    "sg:province":"GA",
    "sg:tags":[
        "control",
        "equipment-wholesale",
        "security",
        "manufacturer"
    ],
    "wof:name":"Lockdown Lockdry Division",
    "wof:placetype":"venue"
},
  "geometry": {"coordinates":[-84.057666,33.690423],"type":"Point"}
}