{
  "type": "Feature",
  "properties": {
    "iso:country":"US",
    "sg:address":"3457 Peach Orchard Rd",
    "sg:city":"Augusta",
    "sg:classifiers":[
        {
            "category":"Food & Beverages",
            "subcategory":"Groceries & Convenience Stores",
            "type":"Retail Goods"
        }
    ],
    "sg:phone":"+1 706 560 1075",
    "sg:postcode":"30906",
    "sg:province":"GA",
    "wof:name":"Bi-Lo LLC",
    "wof:placetype":"venue"
},
  "geometry": {"coordinates":[-82.02722300000001,33.390655],"type":"Point"}
}