{
  "type": "Feature",
  "properties": {
    "addr:full":"464 Stonebridge Ct Stone Mountain GA 30083",
    "addr:housenumber":"464",
    "addr:postcode":"30083",
    "addr:street":"Stonebridge Ct",
    "iso:country":"US",
    "sg:address":"464 Stonebridge Ct",
    "sg:city":"Stone Mountain",
    "sg:classifiers":[
        {
            "category":"Building & Trades",
            "subcategory":"Construction",
            "type":"Services"
        }
    ],
    "sg:phone":"+1 770 469 2797",
    "sg:postcode":"30083",
    "sg:province":"GA",
    "sg:tags":[
        "home",
        "improvement"
    ],
    "wof:name":"AM-Jam Contractors Inc",
    "wof:placetype":"venue"
},
  "geometry": {"coordinates":[-84.19401499999999,33.787786],"type":"Point"}
}