{
  "type": "Feature",
  "properties": {
    "addr:full":"405 Ty Ty Whiddon Mill Rd Ty Ty GA 31795",
    "addr:housenumber":"405",
    "addr:postcode":"31795",
    "addr:street":"Ty Ty Whiddon Mill Rd",
    "iso:country":"US",
    "sg:address":"405 Ty Ty Whiddon Mill Rd",
    "sg:city":"Ty Ty",
    "sg:classifiers":[
        {
            "category":"Real Estate",
            "subcategory":"Real Estate Agent",
            "type":"Services"
        }
    ],
    "sg:phone":"+1 229 386 4661",
    "sg:postcode":"31795",
    "sg:province":"GA",
    "sg:tags":[
        "appraiser"
    ],
    "wof:name":"Crumley & Assoc",
    "wof:placetype":"venue"
},
  "geometry": {"coordinates":[-83.637181,31.501765],"type":"Point"}
}