{
  "type": "Feature",
  "properties": {
    "iso:country":"US",
    "sg:address":"329 Kelly Mill Rd",
    "sg:city":"Cumming",
    "sg:classifiers":[
        {
            "category":"Professional",
            "subcategory":"Accounting & Tax Preparation",
            "type":"Services"
        }
    ],
    "sg:phone":"+1 770 888 1467",
    "sg:postcode":"30040",
    "sg:province":"GA",
    "sg:tags":[
        "accountant"
    ],
    "wof:name":"KHK CPA",
    "wof:placetype":"venue"
},
  "geometry": {"coordinates":[-84.14980799999999,34.205996],"type":"Point"}
}