{
  "type": "Feature",
  "properties": {
    "iso:country":"US",
    "sg:address":"1836 Olde Village Run",
    "sg:city":"Atlanta",
    "sg:classifiers":[
        {
            "category":"Restaurant",
            "type":"Food & Drink"
        }
    ],
    "sg:phone":"+1 770 390 9380",
    "sg:postcode":"30338",
    "sg:province":"GA",
    "wof:name":"Park Bench Steakhouse",
    "wof:placetype":"venue"
},
  "geometry": {"coordinates":[-84.31245,33.938222],"type":"Point"}
}