{
  "type": "Feature",
  "properties": {
    "iso:country":"US",
    "sg:address":"3319 Hunters Lodge Rd",
    "sg:city":"Marietta",
    "sg:classifiers":[
        {
            "category":"Professional",
            "subcategory":"Management & Consulting",
            "type":"Services"
        }
    ],
    "sg:phone":"+1 770 579 5719",
    "sg:postcode":"30062",
    "sg:province":"GA",
    "wof:name":"Pet Guy Pet Sitting",
    "wof:placetype":"venue"
},
  "geometry": {"coordinates":[-84.462343,34.031368],"type":"Point"}
}