{
  "type": "Feature",
  "properties": {
    "iso:country":"US",
    "sg:address":"3404 Hopkins Rd",
    "sg:city":"Powder Springs",
    "sg:classifiers":[
        {
            "category":"Restaurant",
            "type":"Food & Drink"
        }
    ],
    "sg:phone":"+1 770 222 7670",
    "sg:postcode":"30127",
    "sg:province":"GA",
    "wof:name":"Whistling Pig",
    "wof:placetype":"venue"
},
  "geometry": {"coordinates":[-84.65590400000001,33.869622],"type":"Point"}
}