{
  "type": "Feature",
  "properties": {
    "addr:full":"1541 Indian Forest Trl Stone Mountain GA 30083",
    "addr:housenumber":"1541",
    "addr:postcode":"30083",
    "addr:street":"Indian Forest Trl",
    "iso:country":"US",
    "sg:address":"1541 Indian Forest Trl",
    "sg:city":"Stone Mountain",
    "sg:classifiers":[
        {
            "category":"Building & Trades",
            "subcategory":"Construction",
            "type":"Services"
        }
    ],
    "sg:phone":"+1 404 247 0903",
    "sg:postcode":"30083",
    "sg:province":"GA",
    "sg:tags":[
        "roofing",
        "contractor"
    ],
    "wof:name":"Crutcher Home Improvements",
    "wof:placetype":"venue"
},
  "geometry": {"coordinates":[-84.216345,33.749728],"type":"Point"}
}