{
  "type": "Feature",
  "properties": {
    "iso:country":"US",
    "sg:address":"3516 Starwood Trl SW",
    "sg:city":"Lilburn",
    "sg:classifiers":[
        {
            "category":"Freight",
            "type":"Transportation"
        }
    ],
    "sg:phone":"+1 770 972 4601",
    "sg:postcode":"30047",
    "sg:province":"GA",
    "wof:name":"Arena Logistics Services Inc",
    "wof:placetype":"venue"
},
  "geometry": {"coordinates":[-84.06777700000001,33.864751],"type":"Point"}
}