{
  "type": "Feature",
  "properties": {
    "iso:country":"US",
    "sg:address":"107 Honey Bee Ln",
    "sg:city":"Brunswick",
    "sg:classifiers":[
        {
            "category":"Utilities",
            "type":"Services"
        }
    ],
    "sg:phone":"+1 912 267 9433",
    "sg:postcode":"31525",
    "sg:province":"GA",
    "sg:tags":[
        "sanitary"
    ],
    "wof:name":"D & B Sweeper Service Inc",
    "wof:placetype":"venue"
},
  "geometry": {"coordinates":[-81.453138,31.235866],"type":"Point"}
}