{
  "type": "Feature",
  "properties": {
    "iso:country":"US",
    "sg:address":"3157 Peachtree Dr NE",
    "sg:city":"Atlanta",
    "sg:classifiers":[
        {
            "category":"Shopping",
            "subcategory":"Clothing, Apparel, & Fashions",
            "type":"Retail Goods"
        }
    ],
    "sg:phone":"+1 404 237 2071",
    "sg:postcode":"30305",
    "sg:province":"GA",
    "sg:tags":[
        "furnishing"
    ],
    "sg:website":"www.rochesterclothing.com",
    "wof:name":"Rochester Big & Tall Clothing",
    "wof:placetype":"venue"
},
  "geometry": {"coordinates":[-84.36286699999999,33.84258],"type":"Point"}
}