{
  "type": "Feature",
  "properties": {
    "addr:full":"6911 Vesta Brook Dr Morrow GA 30260",
    "addr:housenumber":"6911",
    "addr:postcode":"30260",
    "addr:street":"Vesta Brook Dr",
    "iso:country":"US",
    "sg:address":"6911 Vesta Brook Dr",
    "sg:city":"Morrow",
    "sg:classifiers":[
        {
            "category":"Personal",
            "subcategory":"Beauty Salon",
            "type":"Services"
        }
    ],
    "sg:phone":"+1 770 656 8252",
    "sg:postcode":"30260",
    "sg:province":"GA",
    "wof:name":"Deborah's Hair Salon",
    "wof:placetype":"venue"
},
  "geometry": {"coordinates":[-84.304214,33.566391],"type":"Point"}
}