{
  "type": "Feature",
  "properties": {
    "iso:country":"US",
    "sg:address":"4335 N Shallowford Rd",
    "sg:city":"Atlanta",
    "sg:classifiers":[
        {
            "category":"Shopping",
            "subcategory":"Jewelry",
            "type":"Retail Goods"
        }
    ],
    "sg:phone":"+1 770 457 9686",
    "sg:postcode":"30341",
    "sg:province":"GA",
    "sg:tags":[
        "antique",
        "repair"
    ],
    "sg:website":"http://www.antiquewatchco.com",
    "wof:name":"Antique Watch Company",
    "wof:placetype":"venue"
},
  "geometry": {"coordinates":[-84.304616,33.91892],"type":"Point"}
}