{
  "type": "Feature",
  "properties": {
    "iso:country":"US",
    "sg:address":"861 Holcomb Bridge Rd Ste 104",
    "sg:city":"Roswell",
    "sg:classifiers":[
        {
            "category":"Insurance",
            "subcategory":"Hazard Insurance",
            "type":"Services"
        }
    ],
    "sg:phone":"+1 770 998 2498",
    "sg:postcode":"30076",
    "sg:province":"GA",
    "sg:website":"www.autoinsuranceatlantageorgia.com",
    "wof:name":"Oasis Insurance Agency",
    "wof:placetype":"venue"
},
  "geometry": {"coordinates":[-84.338418,34.029193],"type":"Point"}
}