{
  "type": "Feature",
  "properties": {
    "iso:country":"US",
    "sg:address":"3625 Brookview Dr Ste A",
    "sg:city":"Loganville",
    "sg:classifiers":[
        {
            "category":"Place Of Worship",
            "subcategory":"Church",
            "type":"Public Place"
        },
        {
            "category":"Place Of Worship",
            "type":"Public Place"
        }
    ],
    "sg:phone":"+1 770 554 5595",
    "sg:postcode":"30052",
    "sg:province":"GA",
    "sg:tags":[
        "churches-baptist-general",
        "churches-baptist"
    ],
    "wof:name":"Woodlake Baptist Church",
    "wof:placetype":"venue"
},
  "geometry": {"coordinates":[-83.846929,33.783968],"type":"Point"}
}