{
  "type": "Feature",
  "properties": {
    "addr:full":"320 Crosswalk Dr Auburn GA 30011",
    "addr:housenumber":"320",
    "addr:postcode":"30011",
    "addr:street":"Crosswalk Dr",
    "iso:country":"US",
    "sg:address":"320 Crosswalk Dr",
    "sg:city":"Auburn",
    "sg:classifiers":[
        {
            "category":"Building & Trades",
            "subcategory":"Cleaning & Sanitation",
            "type":"Services"
        }
    ],
    "sg:phone":"+1 770 967 3931",
    "sg:postcode":"30011",
    "sg:province":"GA",
    "sg:tags":[
        "janitor"
    ],
    "wof:name":"Sparkel Cleaning Svc",
    "wof:placetype":"venue"
},
  "geometry": {"coordinates":[-83.7966,33.981605],"type":"Point"}
}