{
  "type": "Feature",
  "properties": {
    "addr:full":"686 Cedar Ave NW Atlanta GA 30318",
    "addr:housenumber":"686",
    "addr:postcode":"30318",
    "addr:street":"Cedar Ave Nw",
    "iso:country":"US",
    "sg:address":"686 Cedar Ave NW",
    "sg:city":"Atlanta",
    "sg:classifiers":[
        {
            "category":"Travel",
            "subcategory":"Travel Agent",
            "type":"Entertainment"
        }
    ],
    "sg:phone":"+1 404 794 7064",
    "sg:postcode":"30318",
    "sg:province":"GA",
    "sg:tags":[
        "operator",
        "tour"
    ],
    "wof:name":"Byrke Tours & Charter Inc",
    "wof:placetype":"venue"
},
  "geometry": {"coordinates":[-84.46504,33.776156],"type":"Point"}
}