{
  "type": "Feature",
  "properties": {
    "iso:country":"US",
    "sg:address":"140 Davis Rd",
    "sg:city":"Kathleen",
    "sg:classifiers":[
        {
            "category":"Home & Garden",
            "subcategory":"Building Materials",
            "type":"Retail Goods"
        }
    ],
    "sg:phone":"+1 478 987 0919",
    "sg:postcode":"31047",
    "sg:province":"GA",
    "wof:name":"Wallpaper",
    "wof:placetype":"venue"
},
  "geometry": {"coordinates":[-83.614046,32.453987],"type":"Point"}
}