{
  "type": "Feature",
  "properties": {
    "iso:country":"US",
    "sg:address":"370 Sudan Rd",
    "sg:city":"Byron",
    "sg:classifiers":[
        {
            "category":"Real Estate",
            "subcategory":"Real Estate Operator",
            "type":"Services"
        }
    ],
    "sg:phone":"+1 478 953 3683",
    "sg:postcode":"31008",
    "sg:province":"GA",
    "sg:tags":[
        "mobile",
        "home",
        "community"
    ],
    "wof:name":"Sunnyland Mobile Home Park",
    "wof:placetype":"venue"
},
  "geometry": {"coordinates":[-83.711472,32.663425],"type":"Point"}
}