{
  "type": "Feature",
  "properties": {
    "addr:full":"1835 Old Savannah Rd Augusta GA 30901",
    "addr:housenumber":"1835",
    "addr:postcode":"30901",
    "addr:street":"Old Savannah Rd",
    "iso:country":"US",
    "sg:address":"1835 Old Savannah Rd",
    "sg:city":"Augusta",
    "sg:classifiers":[
        {
            "category":"Place Of Worship",
            "type":"Public Place"
        }
    ],
    "sg:phone":"+1 706 261 0183",
    "sg:postcode":"30901",
    "sg:province":"GA",
    "sg:tags":[
        "church"
    ],
    "wof:name":"Byrd Harvest Center Office",
    "wof:placetype":"venue"
},
  "geometry": {"coordinates":[-81.986425,33.45109],"type":"Point"}
}