{
  "type": "Feature",
  "properties": {
    "iso:country":"US",
    "sg:address":"3046 Spring Hill Pkwy SE A",
    "sg:city":"Smyrna",
    "sg:classifiers":[
        {
            "category":"Insurance",
            "subcategory":"Hazard Insurance",
            "type":"Services"
        },
        {
            "category":"Insurance",
            "subcategory":"Life Insurance",
            "type":"Services"
        },
        {
            "category":"Banks & Credit Unions",
            "subcategory":"Financial Services",
            "type":"Services"
        }
    ],
    "sg:phone":"+1 770 434 9217",
    "sg:postcode":"30080",
    "sg:province":"GA",
    "sg:tags":[
        "annuity",
        "retirement",
        "plan"
    ],
    "wof:name":"Sam Ray & Associates Incorporated",
    "wof:placetype":"venue"
},
  "geometry": {"coordinates":[-84.472838,33.88162],"type":"Point"}
}