{
  "type": "Feature",
  "properties": {
    "addr:full":"446 Haig Mill Rd NW Dalton GA 30721",
    "addr:housenumber":"446",
    "addr:postcode":"30721",
    "addr:street":"Haig Mill Rd Nw",
    "iso:country":"US",
    "sg:address":"446 Haig Mill Rd NW",
    "sg:city":"Dalton",
    "sg:classifiers":[
        {
            "category":"Professional",
            "type":"Services"
        }
    ],
    "sg:phone":"+1 706 259 6919",
    "sg:postcode":"30721",
    "sg:province":"GA",
    "wof:name":"Robert L Shoemaker",
    "wof:placetype":"venue"
},
  "geometry": {"coordinates":[-84.961412,34.827085],"type":"Point"}
}