{
  "type": "Feature",
  "properties": {
    "iso:country":"US",
    "sg:address":"351 Valley Hill Rd SE",
    "sg:city":"Riverdale",
    "sg:classifiers":[
        {
            "category":"Place Of Worship",
            "subcategory":"Church",
            "type":"Public Place"
        }
    ],
    "sg:phone":"+1 770 478 2282",
    "sg:postcode":"30274",
    "sg:province":"GA",
    "sg:tags":[
        "churches-baptist-southern",
        "churches-baptist"
    ],
    "wof:name":"Valley Hill Baptist Church",
    "wof:placetype":"venue"
},
  "geometry": {"coordinates":[-84.379293,33.556694],"type":"Point"}
}