{
  "type": "Feature",
  "properties": {
    "addr:full":"602 Rolling Hills Dr Newnan GA 30263",
    "addr:housenumber":"602",
    "addr:postcode":"30263",
    "addr:street":"Rolling Hills Dr",
    "iso:country":"US",
    "sg:address":"602 Rolling Hills Dr",
    "sg:city":"Newnan",
    "sg:classifiers":[
        {
            "category":"Professional",
            "type":"Services"
        }
    ],
    "sg:phone":"+1 678 423 9692",
    "sg:postcode":"30263",
    "sg:province":"GA",
    "wof:name":"Deborah Magner",
    "wof:placetype":"venue"
},
  "geometry": {"coordinates":[-84.805179,33.398086],"type":"Point"}
}