{
  "type": "Feature",
  "properties": {
    "addr:full":"705 Park Dr NE Atlanta GA 30306",
    "addr:housenumber":"705",
    "addr:postcode":"30306",
    "addr:street":"Park Dr Ne",
    "iso:country":"US",
    "sg:address":"705 Park Dr NE",
    "sg:city":"Atlanta",
    "sg:classifiers":[
        {
            "category":"Professional",
            "subcategory":"Art Services",
            "type":"Services"
        }
    ],
    "sg:phone":"+1 404 874 4707",
    "sg:postcode":"30306",
    "sg:province":"GA",
    "sg:tags":[
        "designer",
        "display",
        "producer"
    ],
    "wof:name":"Fentress Design",
    "wof:placetype":"venue"
},
  "geometry": {"coordinates":[-84.363922,33.783981],"type":"Point"}
}