{
  "type": "Feature",
  "properties": {
    "iso:country":"US",
    "sg:address":"3861 Stone Mountain Hwy",
    "sg:city":"Snellville",
    "sg:classifiers":[
        {
            "category":"Retail",
            "subcategory":"Auto Repair",
            "type":"Services"
        }
    ],
    "sg:phone":"+1 770 972 3886",
    "sg:postcode":"30039",
    "sg:province":"GA",
    "wof:name":"Meineke Car Care Centers Inc",
    "wof:placetype":"venue"
},
  "geometry": {"coordinates":[-84.03469800000001,33.804699],"type":"Point"}
}