{
  "type": "Feature",
  "properties": {
    "addr:full":"185 Pepperdine Way Fayetteville GA 30214",
    "addr:housenumber":"185",
    "addr:postcode":"30214",
    "addr:street":"Pepperdine Way",
    "iso:country":"US",
    "sg:address":"185 Pepperdine Way",
    "sg:city":"Fayetteville",
    "sg:classifiers":[
        {
            "category":"Organizations",
            "subcategory":"Membership Organization",
            "type":"Services"
        }
    ],
    "sg:phone":"+1 770 461 2404",
    "sg:postcode":"30214",
    "sg:province":"GA",
    "wof:name":"Hope For Haiti Inc",
    "wof:placetype":"venue"
},
  "geometry": {"coordinates":[-84.520476,33.488909],"type":"Point"}
}