{
  "type": "Feature",
  "properties": {
    "addr:full":"3550 Pairpoint Pl Alpharetta GA 30022",
    "addr:housenumber":"3550",
    "addr:postcode":"30022",
    "addr:street":"Pairpoint Pl",
    "iso:country":"US",
    "sg:address":"3550 Pairpoint Pl",
    "sg:city":"Alpharetta",
    "sg:classifiers":[
        {
            "category":"Sports & Exercise",
            "subcategory":"Tennis Court",
            "type":"Entertainment"
        }
    ],
    "sg:phone":"+1 770 992 2155",
    "sg:postcode":"30022",
    "sg:province":"GA",
    "wof:name":"Glastonberry Swim & Tennis Club",
    "wof:placetype":"venue"
},
  "geometry": {"coordinates":[-84.2565,34.012001],"type":"Point"}
}