{
  "type": "Feature",
  "properties": {
    "addr:full":"50 Lawrenceville St Ste 201 McDonough GA 30253",
    "addr:housenumber":"50",
    "addr:postcode":"30253",
    "addr:street":"Lawrenceville St Ste 201",
    "iso:country":"US",
    "sg:address":"50 Lawrenceville St Ste 201",
    "sg:city":"McDonough",
    "sg:classifiers":[
        {
            "category":"Health Services",
            "subcategory":"Doctor",
            "type":"Services"
        }
    ],
    "sg:phone":"+1 770 954 1180",
    "sg:postcode":"30253",
    "sg:province":"GA",
    "sg:tags":[
        "surgeon",
        "oral"
    ],
    "wof:name":"Dellinger William H Jr DDS",
    "wof:placetype":"venue"
},
  "geometry": {"coordinates":[-84.14556899999999,33.450321],"type":"Point"}
}