{
  "type": "Feature",
  "properties": {
    "addr:full":"566 E Main St Dahlonega GA 30533",
    "addr:housenumber":"566",
    "addr:postcode":"30533",
    "addr:street":"E Main St",
    "iso:country":"US",
    "sg:address":"566 E Main St",
    "sg:city":"Dahlonega",
    "sg:classifiers":[
        {
            "category":"Shopping",
            "subcategory":"Pharmacy",
            "type":"Retail Goods"
        }
    ],
    "sg:phone":"+1 706 864 8700",
    "sg:postcode":"30533",
    "sg:province":"GA",
    "wof:name":"Webbs Pharmacy Inc",
    "wof:placetype":"venue"
},
  "geometry": {"coordinates":[-83.977586,34.536439],"type":"Point"}
}