{
  "type": "Feature",
  "properties": {
    "addr:full":"1 Frontier Dr NW Conyers GA 30012",
    "addr:housenumber":"1",
    "addr:postcode":"30012",
    "addr:street":"Frontier Dr Nw",
    "iso:country":"US",
    "sg:address":"1 Frontier Dr NW",
    "sg:city":"Conyers",
    "sg:classifiers":[
        {
            "category":"Freight",
            "type":"Transportation"
        }
    ],
    "sg:phone":"+1 770 483 6635",
    "sg:postcode":"30012",
    "sg:province":"GA",
    "sg:tags":[
        "warehouse"
    ],
    "wof:name":"Warehouse",
    "wof:placetype":"venue"
},
  "geometry": {"coordinates":[-84.03613,33.711315],"type":"Point"}
}