{
  "type": "Feature",
  "properties": {
    "addr:full":"4780 Ashford Dunwoody Road Suite A130 Atlanta GA 30338",
    "addr:housenumber":"4780",
    "addr:postcode":"30338",
    "addr:street":"Ashford Dunwoody Road Suite A130",
    "iso:country":"US",
    "sg:address":"4780 Ashford Dunwoody Road Suite A130",
    "sg:city":"Atlanta",
    "sg:classifiers":[
        {
            "category":"Professional",
            "subcategory":"Computer Services",
            "type":"Services"
        }
    ],
    "sg:phone":"+1 404 861 8160",
    "sg:postcode":"30338",
    "sg:province":"GA",
    "sg:tags":[
        "er-wait-times",
        "emergency-rooms",
        "wait-times"
    ],
    "sg:website":"http://www.thedocclock.com",
    "wof:name":"TheDocClock",
    "wof:placetype":"venue"
},
  "geometry": {"coordinates":[-84.337855,33.934646],"type":"Point"}
}