{
  "type": "Feature",
  "properties": {
    "iso:country":"US",
    "sg:address":"125 Paradise Dr",
    "sg:city":"Savannah",
    "sg:classifiers":[
        {
            "category":"Retail",
            "subcategory":"Auto Rental",
            "type":"Services"
        }
    ],
    "sg:phone":"+1 912 925 0541",
    "sg:postcode":"31406",
    "sg:province":"GA",
    "sg:tags":[
        "trailer",
        "utility"
    ],
    "wof:name":"Derenne Mobile Home Court",
    "wof:placetype":"venue"
},
  "geometry": {"coordinates":[-81.123925,31.992164],"type":"Point"}
}