{
  "type": "Feature",
  "properties": {
    "iso:country":"US",
    "sg:address":"210 Prospect Pl",
    "sg:city":"Alpharetta",
    "sg:phone":"+1 678 319 9777",
    "sg:postcode":"30005",
    "sg:province":"GA",
    "wof:name":"Chiropractic Usa",
    "wof:placetype":"venue"
},
  "geometry": {"coordinates":[-84.227272,34.06049],"type":"Point"}
}