{
  "type": "Feature",
  "properties": {
    "iso:country":"US",
    "sg:address":"111 Village Lake Dr",
    "sg:city":"Pooler",
    "sg:classifiers":[
        {
            "category":"Transit Center",
            "subcategory":"Freight",
            "type":"Transportation"
        },
        {
            "category":"Freight",
            "type":"Transportation"
        }
    ],
    "sg:phone":"+1 912 596 8406",
    "sg:postcode":"31322",
    "sg:province":"GA",
    "sg:tags":[
        "local",
        "trucking-motor",
        "trucking"
    ],
    "wof:name":"William Henry Trucking",
    "wof:placetype":"venue"
},
  "geometry": {"coordinates":[-81.256987,32.138306],"type":"Point"}
}