{
  "type": "Feature",
  "properties": {
    "iso:country":"US",
    "sg:address":"2822 Willow Wood Cir",
    "sg:city":"Valdosta",
    "sg:classifiers":[
        {
            "category":"Organizations",
            "subcategory":"Membership Organization",
            "type":"Services"
        }
    ],
    "sg:phone":"+1 229 247 9959",
    "sg:postcode":"31602",
    "sg:province":"GA",
    "wof:name":"Recommendations For Care",
    "wof:placetype":"venue"
},
  "geometry": {"coordinates":[-83.298214,30.868298],"type":"Point"}
}