{
  "type": "Feature",
  "properties": {
    "iso:country":"US",
    "sg:address":"101 Country Club Rd",
    "sg:city":"Dublin",
    "sg:classifiers":[
        {
            "category":"Shopping",
            "subcategory":"Clothing, Apparel, & Fashions",
            "type":"Retail Goods"
        }
    ],
    "sg:phone":"+1 478 275 0721",
    "sg:postcode":"31021",
    "sg:province":"GA",
    "sg:tags":[
        "ready",
        "item",
        "boutique",
        "beauty",
        "operates"
    ],
    "wof:name":"Beauty Boutique Inc",
    "wof:placetype":"venue"
},
  "geometry": {"coordinates":[-82.91265300000001,32.563088],"type":"Point"}
}