{
  "type": "Feature",
  "properties": {
    "iso:country":"US",
    "sg:address":"1064 Bethsaida Rd",
    "sg:city":"Riverdale",
    "sg:classifiers":[
        {
            "category":"Place Of Worship",
            "subcategory":"Church",
            "type":"Public Place"
        }
    ],
    "sg:phone":"+1 770 997 6440",
    "sg:postcode":"30296",
    "sg:province":"GA",
    "sg:tags":[
        "churches-christian"
    ],
    "wof:name":"Riverdale Christian Church",
    "wof:placetype":"venue"
},
  "geometry": {"coordinates":[-84.42378600000001,33.562286],"type":"Point"}
}