{
  "type": "Feature",
  "properties": {
    "addr:full":"3896 Cherokee St NW Kennesaw GA 30144",
    "addr:housenumber":"3896",
    "addr:postcode":"30144",
    "addr:street":"Cherokee St Nw",
    "iso:country":"US",
    "sg:address":"3896 Cherokee St NW",
    "sg:city":"Kennesaw",
    "sg:classifiers":[
        {
            "category":"Building & Trades",
            "subcategory":"Locksmith",
            "type":"Services"
        }
    ],
    "sg:phone":"+1 678 369 4894",
    "sg:postcode":"30144",
    "sg:province":"GA",
    "sg:tags":[
        "key"
    ],
    "wof:name":"7 Days Emergency Locksmith",
    "wof:placetype":"venue"
},
  "geometry": {"coordinates":[-84.598664,34.048339],"type":"Point"}
}