{
  "type": "Feature",
  "properties": {
    "iso:country":"US",
    "sg:address":"2867 Holly Springs Rd",
    "sg:city":"Pendergrass",
    "sg:classifiers":[
        {
            "category":"Restaurant",
            "type":"Food & Drink"
        }
    ],
    "sg:phone":"+1 706 367 9624",
    "sg:postcode":"30567",
    "sg:province":"GA",
    "sg:tags":[
        "house",
        "steak",
        "barbecue"
    ],
    "wof:name":"Grays Smoke House Bbq",
    "wof:placetype":"venue"
},
  "geometry": {"coordinates":[-83.609334,34.191512],"type":"Point"}
}