{
  "type": "Feature",
  "properties": {
    "addr:full":"2990 Argonne Dr NW Atlanta GA 30305",
    "addr:housenumber":"2990",
    "addr:postcode":"30305",
    "addr:street":"Argonne Dr Nw",
    "iso:country":"US",
    "sg:address":"2990 Argonne Dr NW",
    "sg:city":"Atlanta",
    "sg:classifiers":[
        {
            "category":"Professional",
            "type":"Services"
        }
    ],
    "sg:phone":"+1 404 233 7859",
    "sg:postcode":"30305",
    "sg:province":"GA",
    "wof:name":"Lawgroup Inc",
    "wof:placetype":"venue"
},
  "geometry": {"coordinates":[-84.406087,33.836246],"type":"Point"}
}