{
  "type": "Feature",
  "properties": {
    "iso:country":"US",
    "sg:address":"963 Highland Vw NE",
    "sg:city":"Atlanta",
    "sg:classifiers":[
        {
            "category":"Museum",
            "type":"Entertainment"
        }
    ],
    "sg:phone":"+1 404 892 8422",
    "sg:postcode":"30306",
    "sg:province":"GA",
    "sg:tags":[
        "a",
        "art",
        "gallery",
        "operates",
        "as",
        "an",
        "specialized",
        "or"
    ],
    "wof:name":"Rocwood Studios Inc",
    "wof:placetype":"venue"
},
  "geometry": {"coordinates":[-84.353554,33.779116],"type":"Point"}
}