{
  "type": "Feature",
  "properties": {
    "addr:full":"1205 Green St Warner Robins GA 31093",
    "addr:housenumber":"1205",
    "addr:postcode":"31093",
    "addr:street":"Green St",
    "iso:country":"US",
    "sg:address":"1205 Green St",
    "sg:city":"Warner Robins",
    "sg:classifiers":[
        {
            "category":"Personal",
            "subcategory":"Beauty Salon",
            "type":"Services"
        }
    ],
    "sg:phone":"+1 478 328 7008",
    "sg:postcode":"31093",
    "sg:province":"GA",
    "sg:tags":[
        "shop"
    ],
    "wof:name":"Hair Gallery",
    "wof:placetype":"venue"
},
  "geometry": {"coordinates":[-83.637441,32.626254],"type":"Point"}
}