{
  "type": "Feature",
  "properties": {
    "addr:full":"639 Thornton Rd Lithia Springs GA 30122",
    "addr:housenumber":"639",
    "addr:postcode":"30122",
    "addr:street":"Thornton Rd",
    "iso:country":"US",
    "sg:address":"639 Thornton Rd",
    "sg:city":"Lithia Springs",
    "sg:classifiers":[
        {
            "category":"Food & Beverages",
            "subcategory":"Liquor & Beverages",
            "type":"Retail Goods"
        },
        {
            "category":"Professional",
            "subcategory":"Advertising",
            "type":"Services"
        }
    ],
    "sg:phone":"+1 770 944 2210",
    "sg:postcode":"30122",
    "sg:province":"GA",
    "sg:tags":[
        "mailing",
        "shipping",
        "alcoholic"
    ],
    "wof:name":"Quick Pack & Ship",
    "wof:placetype":"venue"
},
  "geometry": {"coordinates":[-84.62239,33.788808],"type":"Point"}
}