{
  "type": "Feature",
  "properties": {
    "iso:country":"US",
    "sg:address":"630 Legend Ct SW",
    "sg:city":"Atlanta",
    "sg:classifiers":[
        {
            "category":"Building & Trades",
            "subcategory":"Construction",
            "type":"Services"
        }
    ],
    "sg:phone":"+1 404 691 0976",
    "sg:postcode":"30331",
    "sg:province":"GA",
    "sg:tags":[
        "concrete",
        "pumping"
    ],
    "wof:name":"Atlantas Cascade Concrete Pmpg",
    "wof:placetype":"venue"
},
  "geometry": {"coordinates":[-84.52531,33.724332],"type":"Point"}
}