{
  "type": "Feature",
  "properties": {
    "addr:full":"5367 Clarks Bridge Rd Gainesville GA 30506",
    "addr:housenumber":"5367",
    "addr:postcode":"30506",
    "addr:street":"Clarks Bridge Rd",
    "iso:country":"US",
    "sg:address":"5367 Clarks Bridge Rd",
    "sg:city":"Gainesville",
    "sg:classifiers":[
        {
            "category":"Manufacturing",
            "subcategory":"Building Materials",
            "type":"Manufacturing & Wholesale Goods"
        }
    ],
    "sg:phone":"+1 770 983 1824",
    "sg:postcode":"30506",
    "sg:province":"GA",
    "sg:tags":[
        "mfg"
    ],
    "wof:name":"Russell Caufman",
    "wof:placetype":"venue"
},
  "geometry": {"coordinates":[-83.776355,34.439747],"type":"Point"}
}