{
  "type": "Feature",
  "properties": {
    "addr:full":"6955 McGinnis Ferry Rd Johns Creek GA 30097",
    "addr:housenumber":"6955",
    "addr:postcode":"30097",
    "addr:street":"Mcginnis Ferry Rd",
    "iso:country":"US",
    "sg:address":"6955 McGinnis Ferry Rd",
    "sg:city":"Johns Creek",
    "sg:classifiers":[
        {
            "category":"Deli",
            "type":"Food & Drink"
        }
    ],
    "sg:phone":"+1 678 473 0026",
    "sg:postcode":"30097",
    "sg:province":"GA",
    "sg:website":"www.jacksnyd.com",
    "wof:name":"Jack's New Yorker Deli",
    "wof:placetype":"venue"
},
  "geometry": {"coordinates":[-84.162615,34.066223],"type":"Point"}
}