{
  "type": "Feature",
  "properties": {
    "addr:full":"8430 Highway 85 Riverdale GA 30274",
    "addr:housenumber":"8430",
    "addr:postcode":"30274",
    "addr:street":"Highway 85",
    "iso:country":"US",
    "sg:address":"8430 Highway 85",
    "sg:city":"Riverdale",
    "sg:classifiers":[
        {
            "category":"Autos & Motor Vehicles",
            "subcategory":"Auto Supplies",
            "type":"Retail Goods"
        }
    ],
    "sg:phone":"+1 770 472 1500",
    "sg:postcode":"30274",
    "sg:province":"GA",
    "sg:tags":[
        "tire"
    ],
    "wof:name":"Total Tire & Auto Inc",
    "wof:placetype":"venue"
},
  "geometry": {"coordinates":[-84.420799,33.528599],"type":"Point"}
}