{
  "type": "Feature",
  "properties": {
    "iso:country":"US",
    "sg:address":"8181 Elberton Hwy",
    "sg:city":"Tignall",
    "sg:classifiers":[
        {
            "category":"Travel",
            "subcategory":"Campground",
            "type":"Entertainment"
        }
    ],
    "sg:phone":"+1 706 359 2053",
    "sg:postcode":"30668",
    "sg:province":"GA",
    "wof:name":"Broad River Campground",
    "wof:placetype":"venue"
},
  "geometry": {"coordinates":[-82.764386,33.935258],"type":"Point"}
}