{
  "type": "Feature",
  "properties": {
    "iso:country":"US",
    "sg:address":"284 US Hwy 221",
    "sg:city":"Adrian",
    "sg:classifiers":[
        {
            "category":"Building & Trades",
            "subcategory":"Pest Control",
            "type":"Services"
        }
    ],
    "sg:phone":"+1 478 668 4799",
    "sg:postcode":"31002",
    "sg:province":"GA",
    "wof:name":"Arrow Exterminators Inc",
    "wof:placetype":"venue"
},
  "geometry": {"coordinates":[-82.493061,32.540032],"type":"Point"}
}