{
  "type": "Feature",
  "properties": {
    "addr:full":"335 Upper Riverdale Rd Jonesboro GA 30236",
    "addr:housenumber":"335",
    "addr:postcode":"30236",
    "addr:street":"Upper Riverdale Rd",
    "iso:country":"US",
    "sg:address":"335 Upper Riverdale Rd",
    "sg:city":"Jonesboro",
    "sg:classifiers":[
        {
            "category":"Personal",
            "subcategory":"Nail Salon",
            "type":"Services"
        }
    ],
    "sg:phone":"+1 770 996 5620",
    "sg:postcode":"30236",
    "sg:province":"GA",
    "wof:name":"Place For Nails",
    "wof:placetype":"venue"
},
  "geometry": {"coordinates":[-84.33699799999999,33.5317],"type":"Point"}
}