{
  "type": "Feature",
  "properties": {
    "iso:country":"US",
    "sg:address":"1439 Old Salem Rd SE",
    "sg:city":"Conyers",
    "sg:classifiers":[
        {
            "category":"Restaurant",
            "type":"Food & Drink"
        },
        {
            "category":"Recreation",
            "type":"Entertainment"
        }
    ],
    "sg:phone":"+1 770 922 4559",
    "sg:postcode":"30013",
    "sg:province":"GA",
    "sg:tags":[
        "skating",
        "ope",
        "eating",
        "amusement",
        "rink"
    ],
    "wof:name":"Billy Bobs Pizza & Skating Ctr",
    "wof:placetype":"venue"
},
  "geometry": {"coordinates":[-84.002487,33.646481],"type":"Point"}
}