{
  "type": "Feature",
  "properties": {
    "addr:full":"114 Forrest Ave Lagrange GA 30240",
    "addr:housenumber":"114",
    "addr:postcode":"30240",
    "addr:street":"Forrest Ave",
    "iso:country":"US",
    "sg:address":"114 Forrest Ave",
    "sg:city":"Lagrange",
    "sg:classifiers":[
        {
            "category":"Building & Trades",
            "subcategory":"Landscaping Services",
            "type":"Services"
        }
    ],
    "sg:phone":"+1 706 882 1739",
    "sg:postcode":"30240",
    "sg:province":"GA",
    "sg:tags":[
        "landscape",
        "contractor"
    ],
    "wof:name":"Charles Herring Landscaping",
    "wof:placetype":"venue"
},
  "geometry": {"coordinates":[-85.045278,33.039549],"type":"Point"}
}