{
  "type": "Feature",
  "properties": {
    "addr:full":"314 College Dr Barnesville GA 30204",
    "addr:housenumber":"314",
    "addr:postcode":"30204",
    "addr:street":"College Dr",
    "iso:country":"US",
    "sg:address":"314 College Dr",
    "sg:city":"Barnesville",
    "sg:classifiers":[
        {
            "category":"Health Services",
            "subcategory":"Hospital",
            "type":"Services"
        }
    ],
    "sg:phone":"+1 770 358 5252",
    "sg:postcode":"30204",
    "sg:province":"GA",
    "sg:tags":[
        "mental"
    ],
    "wof:name":"Mc Intosh Trail MH/Mr/Sa",
    "wof:placetype":"venue"
},
  "geometry": {"coordinates":[-84.15340399999999,33.050785],"type":"Point"}
}