{
  "type": "Feature",
  "properties": {
    "addr:full":"1459 Pat Haralson Memorial Dr Blairsville GA 30512",
    "addr:housenumber":"1459",
    "addr:postcode":"30512",
    "addr:street":"Pat Haralson Memorial Dr",
    "iso:country":"US",
    "sg:address":"1459 Pat Haralson Memorial Dr",
    "sg:city":"Blairsville",
    "sg:classifiers":[
        {
            "category":"Utilities",
            "subcategory":"Water",
            "type":"Services"
        }
    ],
    "sg:phone":"+1 706 745 4598",
    "sg:postcode":"30512",
    "sg:province":"GA",
    "sg:tags":[
        "company",
        "sewage"
    ],
    "wof:name":"Notla Water Authority",
    "wof:placetype":"venue"
},
  "geometry": {"coordinates":[-83.97947499999999,34.883367],"type":"Point"}
}