{
  "type": "Feature",
  "properties": {
    "iso:country":"US",
    "sg:address":"2331 Adams Dr NW",
    "sg:city":"Atlanta",
    "sg:classifiers":[
        {
            "category":"Retail",
            "subcategory":"Auto Repair",
            "type":"Services"
        }
    ],
    "sg:phone":"+1 404 664 2488",
    "sg:postcode":"30318",
    "sg:province":"GA",
    "sg:tags":[
        "automobile",
        "customizing"
    ],
    "wof:name":"Reality's Edge Custom",
    "wof:placetype":"venue"
},
  "geometry": {"coordinates":[-84.454807,33.820505],"type":"Point"}
}