{
  "type": "Feature",
  "properties": {
    "iso:country":"US",
    "sg:address":"2200 Century Pkwy NE Ste 10",
    "sg:city":"Atlanta",
    "sg:classifiers":[
        {
            "category":"Professional",
            "subcategory":"Lawyer & Legal Services",
            "type":"Services"
        }
    ],
    "sg:phone":"+1 404 325 4800",
    "sg:postcode":"30345",
    "sg:province":"GA",
    "sg:tags":[
        "attorney",
        "practice"
    ],
    "wof:name":"Mabry & McClelland Llp",
    "wof:placetype":"venue"
},
  "geometry": {"coordinates":[-84.3078,33.8452],"type":"Point"}
}