{
  "type": "Feature",
  "properties": {
    "addr:full":"2316 State Rte 155 N Mcdonough GA 30252",
    "addr:housenumber":"2316",
    "addr:postcode":"30252",
    "addr:street":"State Rte 155 N",
    "iso:country":"US",
    "sg:address":"2316 State Rte 155 N",
    "sg:city":"Mcdonough",
    "sg:classifiers":[
        {
            "category":"Banks & Credit Unions",
            "subcategory":"Bank",
            "type":"Services"
        }
    ],
    "sg:phone":"+1 770 474 7293",
    "sg:postcode":"30252",
    "sg:province":"GA",
    "sg:tags":[
        "state",
        "commercial"
    ],
    "wof:name":"First State Bank",
    "wof:placetype":"venue"
},
  "geometry": {"coordinates":[-84.13870799999999,33.513683],"type":"Point"}
}