{
  "type": "Feature",
  "properties": {
    "iso:country":"US",
    "sg:address":"1700 Clairmont Rd",
    "sg:city":"Decatur",
    "sg:classifiers":[
        {
            "category":"Food & Beverages",
            "subcategory":"Supermarket",
            "type":"Retail Goods"
        }
    ],
    "sg:phone":"+1 404 471 1807",
    "sg:postcode":"30033",
    "sg:province":"GA",
    "sg:tags":[
        "super",
        "store"
    ],
    "wof:name":"Vba Atl",
    "wof:placetype":"venue"
},
  "geometry": {"coordinates":[-84.310654,33.80331],"type":"Point"}
}