{
  "type": "Feature",
  "properties": {
    "addr:full":"405 Al Henderson Blvd Savannah GA 31419",
    "addr:housenumber":"405",
    "addr:postcode":"31419",
    "addr:street":"Al Henderson Blvd",
    "iso:country":"US",
    "sg:address":"405 Al Henderson Blvd",
    "sg:city":"Savannah",
    "sg:classifiers":[
        {
            "category":"Travel",
            "subcategory":"Hotels & Motels",
            "type":"Entertainment"
        }
    ],
    "sg:phone":"+1 912 920 3535",
    "sg:postcode":"31419",
    "sg:province":"GA",
    "sg:tags":[
        "operation"
    ],
    "wof:name":"Red Roof Inn",
    "wof:placetype":"venue"
},
  "geometry": {"coordinates":[-81.27472,32.006517],"type":"Point"}
}