{
  "type": "Feature",
  "properties": {
    "iso:country":"US",
    "sg:address":"375 Saddle Horn Cir",
    "sg:city":"Roswell",
    "sg:classifiers":[
        {
            "category":"Professional",
            "subcategory":"Business Services",
            "type":"Services"
        }
    ],
    "sg:phone":"+1 770 518 0178",
    "sg:postcode":"30076",
    "sg:province":"GA",
    "wof:name":"Garvin D Andrea CPA PC",
    "wof:placetype":"venue"
},
  "geometry": {"coordinates":[-84.359647,34.063024],"type":"Point"}
}