{
  "type": "Feature",
  "properties": {
    "iso:country":"US",
    "sg:address":"2120 Country Club Rd",
    "sg:city":"Columbus",
    "sg:classifiers":[
        {
            "category":"Professional",
            "type":"Services"
        }
    ],
    "sg:phone":"+1 706 322 0004",
    "sg:postcode":"31906",
    "sg:province":"GA",
    "wof:name":"Helen L & Harry C Jackson",
    "wof:placetype":"venue"
},
  "geometry": {"coordinates":[-84.964184,32.486022],"type":"Point"}
}