{
  "type": "Feature",
  "properties": {
    "iso:country":"US",
    "sg:address":"625 Church St NE",
    "sg:city":"Marietta",
    "sg:classifiers":[
        {
            "category":"Health Services",
            "subcategory":"Doctor",
            "type":"Services"
        }
    ],
    "sg:phone":"+1 770 422 8505",
    "sg:postcode":"30060",
    "sg:province":"GA",
    "sg:tags":[
        "physician",
        "surgeon",
        "obstetrician",
        "medical",
        "gynecologist"
    ],
    "sg:website":"www.mariettaobgyn.com",
    "wof:name":"Mull Michael MD",
    "wof:placetype":"venue"
},
  "geometry": {"coordinates":[-84.55009099999999,33.966836],"type":"Point"}
}