{
  "type": "Feature",
  "properties": {
    "addr:full":"2814 Spring Road SE Atlanta GA 30339",
    "addr:housenumber":"2814",
    "addr:postcode":"30339",
    "addr:street":"Spring Road Se",
    "iso:country":"US",
    "sg:address":"2814 Spring Road SE",
    "sg:city":"Atlanta",
    "sg:classifiers":[
        {
            "category":"Wholesale",
            "subcategory":"Computers",
            "type":"Manufacturing & Wholesale Goods"
        },
        {
            "category":"Professional",
            "subcategory":"Computer Services",
            "type":"Services"
        }
    ],
    "sg:phone":"+1 770 432 4441",
    "sg:postcode":"30339",
    "sg:province":"GA",
    "sg:tags":[
        "repair"
    ],
    "wof:name":"Omega Maintenance",
    "wof:placetype":"venue"
},
  "geometry": {"coordinates":[-84.472886,33.885406],"type":"Point"}
}