{
  "type": "Feature",
  "properties": {
    "iso:country":"US",
    "sg:address":"246 Arnold Mill Rd",
    "sg:city":"Woodstock",
    "sg:classifiers":[
        {
            "category":"Building & Trades",
            "subcategory":"Landscaping Services",
            "type":"Services"
        }
    ],
    "sg:phone":"+1 770 917 0060",
    "sg:postcode":"30188",
    "sg:province":"GA",
    "sg:tags":[
        "consultant",
        "lawn",
        "designer",
        "landscape",
        "contractor"
    ],
    "wof:name":"Twin Oaks Landscape Service",
    "wof:placetype":"venue"
},
  "geometry": {"coordinates":[-84.506439,34.102551],"type":"Point"}
}