{
  "type": "Feature",
  "properties": {
    "addr:full":"6185 Jimmy Carter Blvd Norcross GA 30071",
    "addr:housenumber":"6185",
    "addr:postcode":"30071",
    "addr:street":"Jimmy Carter Blvd",
    "iso:country":"US",
    "sg:address":"6185 Jimmy Carter Blvd",
    "sg:city":"Norcross",
    "sg:classifiers":[
        {
            "category":"Wholesale",
            "subcategory":"Machinery & Supplies",
            "type":"Manufacturing & Wholesale Goods"
        },
        {
            "category":"Building & Trades",
            "subcategory":"Construction",
            "type":"Services"
        }
    ],
    "sg:phone":"+1 770 326 5654",
    "sg:postcode":"30071",
    "sg:province":"GA",
    "sg:tags":[
        "valve",
        "contractor"
    ],
    "sg:website":"http://www.tycovalves-na.com",
    "wof:name":"Tyco Valves & Controls",
    "wof:placetype":"venue"
},
  "geometry": {"coordinates":[-84.21822400000001,33.926102],"type":"Point"}
}