{
  "type": "Feature",
  "properties": {
    "iso:country":"US",
    "sg:address":"11720 Amberpark Dr # 160",
    "sg:city":"Alpharetta",
    "sg:classifiers":[
        {
            "category":"Communications",
            "subcategory":"Television Station",
            "type":"Services"
        }
    ],
    "sg:phone":"+1 770 754 1206",
    "sg:postcode":"30009",
    "sg:province":"GA",
    "sg:tags":[
        "satellite",
        "cable"
    ],
    "sg:website":"http://www.charter.ordercableonline.com",
    "wof:name":"Charter Communications Operating",
    "wof:placetype":"venue"
},
  "geometry": {"coordinates":[-84.278983,34.068494],"type":"Point"}
}