{
  "type": "Feature",
  "properties": {
    "iso:country":"US",
    "sg:address":"2382 Bolton Rd NW",
    "sg:city":"Atlanta",
    "sg:classifiers":[
        {
            "category":"Manufacturing",
            "subcategory":"Tools & Machinery",
            "type":"Manufacturing & Wholesale Goods"
        },
        {
            "category":"Freight",
            "type":"Transportation"
        },
        {
            "category":"Building & Trades",
            "subcategory":"Construction",
            "type":"Services"
        }
    ],
    "sg:phone":"+1 404 815 9983",
    "sg:postcode":"30318",
    "sg:province":"GA",
    "sg:tags":[
        "conveying",
        "conveyor",
        "equipment-wholesale",
        "system",
        "equipment",
        "monorail",
        "manufacturer"
    ],
    "wof:name":"Intec Solutions, Inc.",
    "wof:placetype":"venue"
},
  "geometry": {"coordinates":[-84.459324,33.82073],"type":"Point"}
}