{
  "type": "Feature",
  "properties": {
    "addr:full":"1381 Stonehenge Ct NW Kennesaw GA 30144",
    "addr:housenumber":"1381",
    "addr:postcode":"30144",
    "addr:street":"Stonehenge Ct Nw",
    "iso:country":"US",
    "sg:address":"1381 Stonehenge Ct NW",
    "sg:city":"Kennesaw",
    "sg:classifiers":[
        {
            "category":"Sports & Exercise",
            "subcategory":"Sports Center",
            "type":"Entertainment"
        }
    ],
    "sg:phone":"+1 770 499 8388",
    "sg:postcode":"30144",
    "sg:province":"GA",
    "sg:tags":[
        "manager",
        "promoter"
    ],
    "wof:name":"Team Innovations Inc",
    "wof:placetype":"venue"
},
  "geometry": {"coordinates":[-84.58748199999999,34.045082],"type":"Point"}
}