{
  "type": "Feature",
  "properties": {
    "iso:country":"US",
    "sg:address":"2560 Moreland Ave SE",
    "sg:city":"Atlanta",
    "sg:phone":"+1 404 622 1921",
    "sg:postcode":"30315",
    "sg:province":"GA",
    "wof:name":"Nalley Equipment Leasing",
    "wof:placetype":"venue"
},
  "geometry": {"coordinates":[-84.347742,33.683946],"type":"Point"}
}