{
  "type": "Feature",
  "properties": {
    "addr:full":"217 S Hill St Griffin GA 30224",
    "addr:housenumber":"217",
    "addr:postcode":"30224",
    "addr:street":"S Hill St",
    "iso:country":"US",
    "sg:address":"217 S Hill St",
    "sg:city":"Griffin",
    "sg:classifiers":[
        {
            "category":"Professional",
            "subcategory":"Lawyer & Legal Services",
            "type":"Services"
        }
    ],
    "sg:phone":"+1 770 412 6045",
    "sg:postcode":"30224",
    "sg:province":"GA",
    "sg:tags":[
        "attorney"
    ],
    "wof:name":"John P Joiner Law Office",
    "wof:placetype":"venue"
},
  "geometry": {"coordinates":[-84.263875,33.246933],"type":"Point"}
}