{
  "type": "Feature",
  "properties": {
    "iso:country":"US",
    "sg:address":"2511 Riverwood Spring",
    "sg:city":"Ellenwood",
    "sg:classifiers":[
        {
            "category":"Building & Trades",
            "subcategory":"Landscaping Services",
            "type":"Services"
        }
    ],
    "sg:phone":"+1 404 243 4836",
    "sg:postcode":"30294",
    "sg:province":"GA",
    "sg:tags":[
        "landscape"
    ],
    "wof:name":"Mrs Landscaping",
    "wof:placetype":"venue"
},
  "geometry": {"coordinates":[-84.28505,33.671127],"type":"Point"}
}