{
  "type": "Feature",
  "properties": {
    "iso:country":"US",
    "sg:address":"997 Mansell Rd",
    "sg:city":"Roswell",
    "sg:classifiers":[
        {
            "category":"Wholesale",
            "subcategory":"Non-durable Goods",
            "type":"Manufacturing & Wholesale Goods"
        }
    ],
    "sg:phone":"+1 678 277 9722",
    "sg:postcode":"30076",
    "sg:province":"GA",
    "wof:name":"Bonn Imports",
    "wof:placetype":"venue"
},
  "geometry": {"coordinates":[-84.330572,34.042595],"type":"Point"}
}