{
  "type": "Feature",
  "properties": {
    "iso:country":"US",
    "sg:address":"441 Marietta St",
    "sg:city":"Atlanta",
    "sg:classifiers":[
        {
            "category":"Professional",
            "subcategory":"Advertising",
            "type":"Services"
        }
    ],
    "sg:phone":"+1 404 589 4440",
    "sg:postcode":"30313",
    "sg:province":"GA",
    "sg:tags":[
        "agency"
    ],
    "wof:name":"Lunch Advertising Inc",
    "wof:placetype":"venue"
},
  "geometry": {"coordinates":[-84.397273,33.764967],"type":"Point"}
}