{
  "type": "Feature",
  "properties": {
    "iso:country":"US",
    "sg:address":"4564 Dewey Dr",
    "sg:city":"Augusta",
    "sg:classifiers":[
        {
            "category":"Retail",
            "subcategory":"Auto Repair",
            "type":"Services"
        }
    ],
    "sg:phone":"+1 706 860 4713",
    "sg:postcode":"30907",
    "sg:province":"GA",
    "sg:tags":[
        "body"
    ],
    "wof:name":"Gardner Paint & Body Inc",
    "wof:placetype":"venue"
},
  "geometry": {"coordinates":[-82.14453899999999,33.500071],"type":"Point"}
}