{
  "type": "Feature",
  "properties": {
    "addr:full":"3656 Oakland Ln Gainesville GA 30504",
    "addr:housenumber":"3656",
    "addr:postcode":"30504",
    "addr:street":"Oakland Ln",
    "iso:country":"US",
    "sg:address":"3656 Oakland Ln",
    "sg:city":"Gainesville",
    "sg:classifiers":[
        {
            "category":"Personal",
            "subcategory":"Beauty Salon",
            "type":"Services"
        }
    ],
    "sg:phone":"+1 770 532 6527",
    "sg:postcode":"30504",
    "sg:province":"GA",
    "sg:tags":[
        "hair",
        "stylist"
    ],
    "wof:name":"Scissors Hair Studio",
    "wof:placetype":"venue"
},
  "geometry": {"coordinates":[-83.88259100000001,34.260818],"type":"Point"}
}