{
  "type": "Feature",
  "properties": {
    "iso:country":"US",
    "sg:address":"1315 Augusta Ave",
    "sg:city":"Savannah",
    "sg:classifiers":[
        {
            "category":"Food & Beverages",
            "subcategory":"Groceries & Convenience Stores",
            "type":"Retail Goods"
        }
    ],
    "sg:phone":"+1 912 232 6690",
    "sg:postcode":"31415",
    "sg:province":"GA",
    "sg:tags":[
        "product"
    ],
    "wof:name":"Us Food Store",
    "wof:placetype":"venue"
},
  "geometry": {"coordinates":[-81.115718,32.080841],"type":"Point"}
}