{
  "type": "Feature",
  "properties": {
    "iso:country":"US",
    "sg:address":"1220 Compass Pointe Xing",
    "sg:city":"Alpharetta",
    "sg:classifiers":[
        {
            "category":"Professional",
            "subcategory":"Advertising",
            "type":"Services"
        }
    ],
    "sg:phone":"+1 770 346 8600",
    "sg:postcode":"30005",
    "sg:province":"GA",
    "sg:tags":[
        "agency"
    ],
    "wof:name":"Joe Marino",
    "wof:placetype":"venue"
},
  "geometry": {"coordinates":[-84.23079300000001,34.090803],"type":"Point"}
}