{
  "type": "Feature",
  "properties": {
    "iso:country":"US",
    "sg:address":"13 S Scott St",
    "sg:city":"Camilla",
    "sg:classifiers":[
        {
            "category":"Professional",
            "subcategory":"Advertising",
            "type":"Services"
        },
        {
            "category":"Wholesale",
            "subcategory":"Books, Periodicals, & Newspapers",
            "type":"Manufacturing & Wholesale Goods"
        }
    ],
    "sg:phone":"+1 229 336 5265",
    "sg:postcode":"31730",
    "sg:province":"GA",
    "sg:tags":[
        "print",
        "news",
        "dealers-wholesale"
    ],
    "sg:website":"http://www.mitchellrepublic.com",
    "wof:name":"Camilla Enterprise",
    "wof:placetype":"venue"
},
  "geometry": {"coordinates":[-84.210697,31.223605],"type":"Point"}
}