{
  "type": "Feature",
  "properties": {
    "addr:full":"1600 Mc Arthur St Albany GA 31701",
    "addr:housenumber":"1600",
    "addr:postcode":"31701",
    "addr:street":"Mc Arthur St",
    "iso:country":"US",
    "sg:address":"1600 Mc Arthur St",
    "sg:city":"Albany",
    "sg:classifiers":[
        {
            "category":"Organizations",
            "subcategory":"Religious Organization",
            "type":"Services"
        }
    ],
    "sg:phone":"+1 229 420 5515",
    "sg:postcode":"31701",
    "sg:province":"GA",
    "sg:tags":[
        "church"
    ],
    "wof:name":"New Generation Ministries",
    "wof:placetype":"venue"
},
  "geometry": {"coordinates":[-84.163276,31.559081],"type":"Point"}
}