{
  "type": "Feature",
  "properties": {
    "iso:country":"US",
    "sg:address":"903 Jackson St",
    "sg:city":"Thomson",
    "sg:classifiers":[
        {
            "category":"Personal",
            "subcategory":"Beauty Salon",
            "type":"Services"
        }
    ],
    "sg:phone":"+1 706 595 5065",
    "sg:postcode":"30824",
    "sg:province":"GA",
    "sg:tags":[
        "shop"
    ],
    "wof:name":"Hairs Days Family Hair Salon",
    "wof:placetype":"venue"
},
  "geometry": {"coordinates":[-82.49597799999999,33.451272],"type":"Point"}
}