{
  "type": "Feature",
  "properties": {
    "iso:country":"US",
    "sg:address":"360 Gees Mill Business Pkwy NE",
    "sg:city":"Conyers",
    "sg:classifiers":[
        {
            "category":"Professional",
            "subcategory":"Research",
            "type":"Services"
        }
    ],
    "sg:phone":"+1 770 918 0932",
    "sg:postcode":"30013",
    "sg:province":"GA",
    "sg:tags":[
        "laboratory"
    ],
    "wof:name":"A T & T Labs",
    "wof:placetype":"venue"
},
  "geometry": {"coordinates":[-83.97638999999999,33.649763],"type":"Point"}
}