{
  "type": "Feature",
  "properties": {
    "addr:full":"3173 Cobb Pkwy NW Kennesaw GA 30152",
    "addr:housenumber":"3173",
    "addr:postcode":"30152",
    "addr:street":"Cobb Pkwy Nw",
    "iso:country":"US",
    "sg:address":"3173 Cobb Pkwy NW",
    "sg:city":"Kennesaw",
    "sg:classifiers":[
        {
            "category":"Retail",
            "subcategory":"Auto Repair",
            "type":"Services"
        }
    ],
    "sg:phone":"+1 770 966 0151",
    "sg:postcode":"30152",
    "sg:province":"GA",
    "sg:website":"www.MaacoKennesaw.com",
    "wof:name":"Maaco Collision Repair & Auto Painting",
    "wof:placetype":"venue"
},
  "geometry": {"coordinates":[-84.663967,34.031823],"type":"Point"}
}