{
  "type": "Feature",
  "properties": {
    "iso:country":"US",
    "sg:address":"1512 Eatonton Rd",
    "sg:city":"Madison",
    "sg:classifiers":[
        {
            "category":"Shopping",
            "subcategory":"Mobile Phones",
            "type":"Retail Goods"
        }
    ],
    "sg:phone":"+1 706 752 0361",
    "sg:postcode":"30650",
    "sg:province":"GA",
    "sg:tags":[
        "equipment",
        "telephone",
        "cellular",
        "supply"
    ],
    "wof:name":"East Metro Cellular Inc",
    "wof:placetype":"venue"
},
  "geometry": {"coordinates":[-83.47743199999999,33.57153],"type":"Point"}
}