{
  "type": "Feature",
  "properties": {
    "iso:country":"US",
    "sg:address":"550 Highway 81 W",
    "sg:city":"McDonough",
    "sg:classifiers":[
        {
            "category":"Health Services",
            "subcategory":"Chiropractor",
            "type":"Services"
        }
    ],
    "sg:phone":"+1 678 583 0249",
    "sg:postcode":"30253",
    "sg:province":"GA",
    "wof:name":"Meininger Mark J Dr PC",
    "wof:placetype":"venue"
},
  "geometry": {"coordinates":[-84.166104,33.435024],"type":"Point"}
}