{
  "type": "Feature",
  "properties": {
    "addr:full":"620 Peachtree Street NE Atlanta GA 30308",
    "addr:housenumber":"620",
    "addr:postcode":"30308",
    "addr:street":"Peachtree Street Ne",
    "iso:country":"US",
    "sg:address":"620 Peachtree Street NE",
    "sg:city":"Atlanta",
    "sg:classifiers":[
        {
            "category":"Shopping",
            "subcategory":"Clothing, Apparel, & Fashions",
            "type":"Retail Goods"
        }
    ],
    "sg:phone":"+1 404 881 9630",
    "sg:postcode":"30308",
    "sg:province":"GA",
    "sg:tags":[
        "accessory",
        "clothing",
        "women's"
    ],
    "sg:website":"www.malleryfur.com",
    "wof:name":"Mallery Furs",
    "wof:placetype":"venue"
},
  "geometry": {"coordinates":[-84.38494799999999,33.771738],"type":"Point"}
}