{
  "type": "Feature",
  "properties": {
    "iso:country":"US",
    "sg:address":"227 Mitchell St SW",
    "sg:city":"Atlanta",
    "sg:classifiers":[
        {
            "category":"Real Estate",
            "subcategory":"Real Estate Services",
            "type":"Services"
        },
        {
            "category":"Building & Trades",
            "subcategory":"Cleaning & Sanitation",
            "type":"Services"
        }
    ],
    "sg:phone":"+1 404 523 4147",
    "sg:postcode":"30303",
    "sg:province":"GA",
    "sg:tags":[
        "maintenance",
        "cleaners-interior"
    ],
    "wof:name":"Service One Cleaning Co",
    "wof:placetype":"venue"
},
  "geometry": {"coordinates":[-84.395055,33.75204],"type":"Point"}
}