{
  "type": "Feature",
  "properties": {
    "addr:full":"31 Market Square Rd Newnan GA 30265",
    "addr:housenumber":"31",
    "addr:postcode":"30265",
    "addr:street":"Market Square Rd",
    "iso:country":"US",
    "sg:address":"31 Market Square Rd",
    "sg:city":"Newnan",
    "sg:classifiers":[
        {
            "category":"Restaurant",
            "type":"Food & Drink"
        }
    ],
    "sg:menulink":"http://www.allmenus.com/ga/newnan/114085-h-j--wings--things/menu/",
    "sg:phone":"+1 770 253 1087",
    "sg:postcode":"30265",
    "sg:province":"GA",
    "sg:tags":[
        "american"
    ],
    "wof:name":"H J  Wings & Things",
    "wof:placetype":"venue"
},
  "geometry": {"coordinates":[-84.740551,33.380009],"type":"Point"}
}