{
  "type": "Feature",
  "properties": {
    "addr:full":"255 Deepstep Rd NE Milledgeville GA 31061",
    "addr:housenumber":"255",
    "addr:postcode":"31061",
    "addr:street":"Deepstep Rd Ne",
    "iso:country":"US",
    "sg:address":"255 Deepstep Rd NE",
    "sg:city":"Milledgeville",
    "sg:classifiers":[
        {
            "category":"Farming",
            "subcategory":"Dairy Farm",
            "type":"Manufacturing & Wholesale Goods"
        }
    ],
    "sg:phone":"+1 478 452 3419",
    "sg:postcode":"31061",
    "sg:province":"GA",
    "wof:name":"William Blizzard",
    "wof:placetype":"venue"
},
  "geometry": {"coordinates":[-83.10051300000001,33.049882],"type":"Point"}
}