{
  "type": "Feature",
  "properties": {
    "addr:full":"2022 Cumming Hwy Canton GA 30114",
    "addr:housenumber":"2022",
    "addr:postcode":"30114",
    "addr:street":"Cumming Hwy",
    "iso:country":"US",
    "sg:address":"2022 Cumming Hwy",
    "sg:city":"Canton",
    "sg:classifiers":[
        {
            "category":"Shopping",
            "type":"Retail Goods"
        }
    ],
    "sg:phone":"+1 678 493 8627",
    "sg:postcode":"30114",
    "sg:province":"GA",
    "wof:name":"Target",
    "wof:placetype":"venue"
},
  "geometry": {"coordinates":[-84.457257,34.237194],"type":"Point"}
}