{
  "type": "Feature",
  "properties": {
    "addr:full":"3180 Presidential Dr Atlanta GA 30340",
    "addr:housenumber":"3180",
    "addr:postcode":"30340",
    "addr:street":"Presidential Dr",
    "iso:country":"US",
    "sg:address":"3180 Presidential Dr",
    "sg:city":"Atlanta",
    "sg:classifiers":[
        {
            "category":"Insurance",
            "subcategory":"Title Insurance",
            "type":"Services"
        }
    ],
    "sg:phone":"+1 770 491 7788",
    "sg:postcode":"30340",
    "sg:province":"GA",
    "sg:tags":[
        "carrier"
    ],
    "wof:name":"Title Partners",
    "wof:placetype":"venue"
},
  "geometry": {"coordinates":[-84.260941,33.88687],"type":"Point"}
}