{
  "type": "Feature",
  "properties": {
    "addr:full":"365 14th St NW Atlanta GA 30318",
    "addr:housenumber":"365",
    "addr:postcode":"30318",
    "addr:street":"14Th St Nw",
    "iso:country":"US",
    "sg:address":"365 14th St NW",
    "sg:city":"Atlanta",
    "sg:classifiers":[
        {
            "category":"Utilities",
            "subcategory":"Mobile Phone",
            "type":"Services"
        }
    ],
    "sg:phone":"+1 404 733 1001",
    "sg:postcode":"30318",
    "sg:province":"GA",
    "sg:tags":[
        "wireless",
        "communication"
    ],
    "wof:name":"Verizon Wireless City",
    "wof:placetype":"venue"
},
  "geometry": {"coordinates":[-84.399061,33.786182],"type":"Point"}
}