{
  "type": "Feature",
  "properties": {
    "addr:full":"925 N Martin Luther King Blvd Americus GA 31719",
    "addr:housenumber":"925",
    "addr:postcode":"31719",
    "addr:street":"N Martin Luther King Blvd",
    "iso:country":"US",
    "sg:address":"925 N Martin Luther King Blvd",
    "sg:city":"Americus",
    "sg:classifiers":[
        {
            "category":"Insurance",
            "subcategory":"Insurance Agent",
            "type":"Services"
        }
    ],
    "sg:phone":"+1 229 928 3686",
    "sg:postcode":"31719",
    "sg:province":"GA",
    "wof:name":"State Farm Insurance",
    "wof:placetype":"venue"
},
  "geometry": {"coordinates":[-84.238794,32.081116],"type":"Point"}
}