{
  "type": "Feature",
  "properties": {
    "addr:full":"970 Bonner Rd Carrollton GA 30117",
    "addr:housenumber":"970",
    "addr:postcode":"30117",
    "addr:street":"Bonner Rd",
    "iso:country":"US",
    "sg:address":"970 Bonner Rd",
    "sg:city":"Carrollton",
    "sg:classifiers":[
        {
            "category":"Wholesale",
            "subcategory":"Non-durable Goods",
            "type":"Manufacturing & Wholesale Goods"
        }
    ],
    "sg:phone":"+1 770 832 2368",
    "sg:postcode":"30117",
    "sg:province":"GA",
    "sg:tags":[
        "dry",
        "goods-wholesale"
    ],
    "wof:name":"B & K Core Supply Inc",
    "wof:placetype":"venue"
},
  "geometry": {"coordinates":[-85.12176700000001,33.549356],"type":"Point"}
}