{
  "type": "Feature",
  "properties": {
    "addr:full":"4558 Blooming Way Flowery Branch GA 30542",
    "addr:housenumber":"4558",
    "addr:postcode":"30542",
    "addr:street":"Blooming Way",
    "iso:country":"US",
    "sg:address":"4558 Blooming Way",
    "sg:city":"Flowery Branch",
    "sg:classifiers":[
        {
            "category":"Insurance",
            "subcategory":"Insurance Agent",
            "type":"Services"
        }
    ],
    "sg:phone":"+1 770 965 6100",
    "sg:postcode":"30542",
    "sg:province":"GA",
    "wof:name":"American Health Plans Inc",
    "wof:placetype":"venue"
},
  "geometry": {"coordinates":[-83.84957199999999,34.181078],"type":"Point"}
}