{
  "type": "Feature",
  "properties": {
    "addr:full":"948 Highway 138 SW Riverdale GA 30296",
    "addr:housenumber":"948",
    "addr:postcode":"30296",
    "addr:street":"Highway 138 Sw",
    "iso:country":"US",
    "sg:address":"948 Highway 138 SW",
    "sg:city":"Riverdale",
    "sg:classifiers":[
        {
            "category":"Health Services",
            "subcategory":"Dentist",
            "type":"Services"
        }
    ],
    "sg:phone":"+1 770 997 7181",
    "sg:postcode":"30296",
    "sg:province":"GA",
    "wof:name":"Parrott Clarence A DDS PC",
    "wof:placetype":"venue"
},
  "geometry": {"coordinates":[-84.42130299999999,33.5504],"type":"Point"}
}