{
  "type": "Feature",
  "properties": {
    "iso:country":"US",
    "sg:address":"417 Holiday Ave",
    "sg:city":"Dalton",
    "sg:classifiers":[
        {
            "category":"Travel",
            "subcategory":"Hotels & Motels",
            "type":"Entertainment"
        }
    ],
    "sg:phone":"+1 706 217 6200",
    "sg:postcode":"30720",
    "sg:province":"GA",
    "sg:website":"www.wellesleyonline.com",
    "wof:name":"Wellesley Suites Of Dalton",
    "wof:placetype":"venue"
},
  "geometry": {"coordinates":[-85.003578,34.76578],"type":"Point"}
}