{
  "type": "Feature",
  "properties": {
    "iso:country":"US",
    "sg:address":"3181 Sandy Creek Rd",
    "sg:city":"Madison",
    "sg:classifiers":[
        {
            "category":"Wholesale",
            "subcategory":"Meat",
            "type":"Manufacturing & Wholesale Goods"
        }
    ],
    "sg:phone":"+1 706 342 8909",
    "sg:postcode":"30650",
    "sg:province":"GA",
    "sg:tags":[
        "poultry",
        "processing"
    ],
    "wof:name":"P Ross Patrica",
    "wof:placetype":"venue"
},
  "geometry": {"coordinates":[-83.48378,33.66315],"type":"Point"}
}