{
  "type": "Feature",
  "properties": {
    "iso:country":"US",
    "sg:address":"2410 Paces Ferry Rd SE",
    "sg:city":"Atlanta",
    "sg:classifiers":[
        {
            "category":"Structure",
            "subcategory":"Warehouse",
            "type":"Public Place"
        }
    ],
    "sg:phone":"+1 770 432 7898",
    "sg:postcode":"30339",
    "sg:province":"GA",
    "sg:tags":[
        "warehouses-merchandise"
    ],
    "wof:name":"M D Hodges Enterprises",
    "wof:placetype":"venue"
},
  "geometry": {"coordinates":[-84.483907,33.86173],"type":"Point"}
}