{
  "type": "Feature",
  "properties": {
    "addr:full":"4370 Chapel Hill Farms Dr Douglasville GA 30135",
    "addr:housenumber":"4370",
    "addr:postcode":"30135",
    "addr:street":"Chapel Hill Farms Dr",
    "iso:country":"US",
    "sg:address":"4370 Chapel Hill Farms Dr",
    "sg:city":"Douglasville",
    "sg:classifiers":[
        {
            "category":"Professional",
            "subcategory":"Detective & Security Services",
            "type":"Services"
        }
    ],
    "sg:phone":"+1 404 374 1101",
    "sg:postcode":"30135",
    "sg:province":"GA",
    "sg:tags":[
        "system"
    ],
    "wof:name":"Adams Enterprises",
    "wof:placetype":"venue"
},
  "geometry": {"coordinates":[-84.719212,33.67215],"type":"Point"}
}