{
  "type": "Feature",
  "properties": {
    "iso:country":"US",
    "sg:address":"4199 Autumn Woods Ct",
    "sg:city":"Stone Mountain",
    "sg:classifiers":[
        {
            "category":"Shopping",
            "subcategory":"Clothing, Apparel, & Fashions",
            "type":"Retail Goods"
        }
    ],
    "sg:phone":"+1 404 294 4580",
    "sg:postcode":"30083",
    "sg:province":"GA",
    "wof:name":"A Plus Enterprise",
    "wof:placetype":"venue"
},
  "geometry": {"coordinates":[-84.217849,33.760378],"type":"Point"}
}