{
  "type": "Feature",
  "properties": {
    "iso:country":"US",
    "sg:address":"83 Clarendon Ave",
    "sg:city":"Avondale Estates",
    "sg:classifiers":[
        {
            "category":"Building & Trades",
            "subcategory":"Locksmith",
            "type":"Services"
        }
    ],
    "sg:phone":"+1 770 308 1440",
    "sg:postcode":"30002",
    "sg:province":"GA",
    "sg:tags":[
        "key"
    ],
    "wof:name":"1 1 24 A Emerg A Locksmith",
    "wof:placetype":"venue"
},
  "geometry": {"coordinates":[-84.267549,33.768796],"type":"Point"}
}