{
  "type": "Feature",
  "properties": {
    "iso:country":"US",
    "sg:address":"317 Virginia Ave S",
    "sg:city":"Tifton",
    "sg:classifiers":[
        {
            "category":"Restaurant",
            "type":"Food & Drink"
        }
    ],
    "sg:menulink":"http://www.allmenus.com/ga/tifton/207204-sonic/menu/",
    "sg:phone":"+1 912 387 0072",
    "sg:postcode":"31794",
    "sg:province":"GA",
    "sg:tags":[
        "burger",
        "american"
    ],
    "wof:name":"Sonic",
    "wof:placetype":"venue"
},
  "geometry": {"coordinates":[-83.528086,31.451139],"type":"Point"}
}