{
  "type": "Feature",
  "properties": {
    "iso:country":"US",
    "sg:address":"1060 S Main St",
    "sg:city":"Hinesville",
    "sg:classifiers":[
        {
            "category":"Restaurant",
            "type":"Food & Drink"
        }
    ],
    "sg:phone":"+1 912 877 4408",
    "sg:postcode":"31313",
    "sg:province":"GA",
    "sg:tags":[
        "eating"
    ],
    "wof:name":"B BS Snack Shack",
    "wof:placetype":"venue"
},
  "geometry": {"coordinates":[-81.605925,31.809915],"type":"Point"}
}