{
  "type": "Feature",
  "properties": {
    "addr:full":"2663 Old Clyattville Rd Valdosta GA 31601",
    "addr:housenumber":"2663",
    "addr:postcode":"31601",
    "addr:street":"Old Clyattville Rd",
    "iso:country":"US",
    "sg:address":"2663 Old Clyattville Rd",
    "sg:city":"Valdosta",
    "sg:classifiers":[
        {
            "category":"Farming",
            "subcategory":"Farm",
            "type":"Manufacturing & Wholesale Goods"
        }
    ],
    "sg:phone":"+1 229 244 8210",
    "sg:postcode":"31601",
    "sg:province":"GA",
    "sg:tags":[
        "crop",
        "general"
    ],
    "wof:name":"Zipperer Farms",
    "wof:placetype":"venue"
},
  "geometry": {"coordinates":[-83.303788,30.763254],"type":"Point"}
}