{
  "type": "Feature",
  "properties": {
    "addr:full":"3795 Buford Dr Buford GA 30519",
    "addr:housenumber":"3795",
    "addr:postcode":"30519",
    "addr:street":"Buford Dr",
    "iso:country":"US",
    "sg:address":"3795 Buford Dr",
    "sg:city":"Buford",
    "sg:classifiers":[
        {
            "category":"Manufacturing",
            "subcategory":"Textiles",
            "type":"Manufacturing & Wholesale Goods"
        }
    ],
    "sg:phone":"+1 770 271 3653",
    "sg:postcode":"30519",
    "sg:province":"GA",
    "sg:tags":[
        "mill",
        "thread"
    ],
    "wof:name":"Hometown Threads of Buford",
    "wof:placetype":"venue"
},
  "geometry": {"coordinates":[-83.990174,34.085027],"type":"Point"}
}