{
  "type": "Feature",
  "properties": {
    "addr:full":"9 Tower Dr Savannah GA 31405",
    "addr:housenumber":"9",
    "addr:postcode":"31405",
    "addr:street":"Tower Dr",
    "iso:country":"US",
    "sg:address":"9 Tower Dr",
    "sg:city":"Savannah",
    "sg:classifiers":[
        {
            "category":"Organizations",
            "subcategory":"Religious Organization",
            "type":"Services"
        }
    ],
    "sg:phone":"+1 912 238 4955",
    "sg:postcode":"31405",
    "sg:province":"GA",
    "wof:name":"Baptist Church",
    "wof:placetype":"venue"
},
  "geometry": {"coordinates":[-81.191971,32.042372],"type":"Point"}
}