{
  "type": "Feature",
  "properties": {
    "addr:full":"726 Talmadge Ave Savannah GA 31408",
    "addr:housenumber":"726",
    "addr:postcode":"31408",
    "addr:street":"Talmadge Ave",
    "iso:country":"US",
    "sg:address":"726 Talmadge Ave",
    "sg:city":"Savannah",
    "sg:classifiers":[
        {
            "category":"Building & Trades",
            "subcategory":"Equipment Rental",
            "type":"Services"
        }
    ],
    "sg:phone":"+1 912 963 1146",
    "sg:postcode":"31408",
    "sg:province":"GA",
    "sg:tags":[
        "audio",
        "leasing"
    ],
    "wof:name":"Symposium Audio Visuals",
    "wof:placetype":"venue"
},
  "geometry": {"coordinates":[-81.177233,32.086836],"type":"Point"}
}