{
  "type": "Feature",
  "properties": {
    "iso:country":"US",
    "sg:address":"219 College St",
    "sg:city":"Monticello",
    "sg:classifiers":[
        {
            "category":"Professional",
            "subcategory":"Management & Consulting",
            "type":"Services"
        }
    ],
    "sg:phone":"+1 706 468 6615",
    "sg:postcode":"31064",
    "sg:province":"GA",
    "wof:name":"Jordan Management Services",
    "wof:placetype":"venue"
},
  "geometry": {"coordinates":[-83.68679299999999,33.307188],"type":"Point"}
}