{
  "type": "Feature",
  "properties": {
    "addr:full":"45 Cathedral Hts Cartersville GA 30120",
    "addr:housenumber":"45",
    "addr:postcode":"30120",
    "addr:street":"Cathedral Hts",
    "iso:country":"US",
    "sg:address":"45 Cathedral Hts",
    "sg:city":"Cartersville",
    "sg:classifiers":[
        {
            "category":"Professional",
            "type":"Services"
        }
    ],
    "sg:phone":"+1 770 382 5185",
    "sg:postcode":"30120",
    "sg:province":"GA",
    "wof:name":"Walter F McDaniel",
    "wof:placetype":"venue"
},
  "geometry": {"coordinates":[-84.911192,34.150439],"type":"Point"}
}