{
  "type": "Feature",
  "properties": {
    "addr:full":"2942 Whispering Hills Dr Atlanta GA 30341",
    "addr:housenumber":"2942",
    "addr:postcode":"30341",
    "addr:street":"Whispering Hills Dr",
    "iso:country":"US",
    "sg:address":"2942 Whispering Hills Dr",
    "sg:city":"Atlanta",
    "sg:classifiers":[
        {
            "category":"Building & Trades",
            "subcategory":"Construction",
            "type":"Services"
        }
    ],
    "sg:phone":"+1 770 936 8598",
    "sg:postcode":"30341",
    "sg:province":"GA",
    "sg:tags":[
        "contractor"
    ],
    "wof:name":"Conscruz Siding Corporation",
    "wof:placetype":"venue"
},
  "geometry": {"coordinates":[-84.286647,33.87353],"type":"Point"}
}