{
  "type": "Feature",
  "properties": {
    "addr:full":"1613 Fenwick St Augusta GA 30904",
    "addr:housenumber":"1613",
    "addr:postcode":"30904",
    "addr:street":"Fenwick St",
    "iso:country":"US",
    "sg:address":"1613 Fenwick St",
    "sg:city":"Augusta",
    "sg:classifiers":[
        {
            "category":"Organizations",
            "subcategory":"Religious Organization",
            "type":"Services"
        }
    ],
    "sg:phone":"+1 706 738 5532",
    "sg:postcode":"30904",
    "sg:province":"GA",
    "sg:website":"www.augustafirst.org",
    "wof:name":"First Assembly Of God",
    "wof:placetype":"venue"
},
  "geometry": {"coordinates":[-81.99143599999999,33.477075],"type":"Point"}
}