{
  "type": "Feature",
  "properties": {
    "addr:full":"42 Milton Ave Frnt Alpharetta GA 30004",
    "addr:housenumber":"42",
    "addr:postcode":"30004",
    "addr:street":"Milton Ave",
    "iso:country":"US",
    "sg:address":"42 Milton Ave Frnt",
    "sg:city":"Alpharetta",
    "sg:classifiers":[
        {
            "category":"Shopping",
            "subcategory":"Music",
            "type":"Retail Goods"
        }
    ],
    "sg:phone":"+1 770 740 9067",
    "sg:postcode":"30004",
    "sg:province":"GA",
    "sg:tags":[
        "dvd's"
    ],
    "wof:name":"Miller Dan Enterprises",
    "wof:placetype":"venue"
},
  "geometry": {"coordinates":[-84.29589799999999,34.0756],"type":"Point"}
}