{
  "type": "Feature",
  "properties": {
    "addr:full":"231 Highway 515 Ste 5 Blairsville GA 30512",
    "addr:housenumber":"231",
    "addr:postcode":"30512",
    "addr:street":"Highway 515 Ste 5",
    "iso:country":"US",
    "sg:address":"231 Highway 515 Ste 5",
    "sg:city":"Blairsville",
    "sg:classifiers":[
        {
            "category":"Health Services",
            "subcategory":"Doctor",
            "type":"Services"
        },
        {
            "category":"Health Services",
            "subcategory":"Clinic",
            "type":"Services"
        }
    ],
    "sg:phone":"+1 706 745 8790",
    "sg:postcode":"30512",
    "sg:province":"GA",
    "sg:tags":[
        "physician",
        "family",
        "practice",
        "surgeons",
        "medicine",
        "surgeon"
    ],
    "wof:name":"Hillcrest Family Care Inc",
    "wof:placetype":"venue"
},
  "geometry": {"coordinates":[-83.958113,34.879149],"type":"Point"}
}