{
  "type": "Feature",
  "properties": {
    "iso:country":"US",
    "sg:address":"1100 Peachtree St NE",
    "sg:city":"Atlanta",
    "sg:classifiers":[
        {
            "category":"Professional",
            "subcategory":"Lawyer & Legal Services",
            "type":"Services"
        }
    ],
    "sg:phone":"+1 404 815 6413",
    "sg:postcode":"30309",
    "sg:province":"GA",
    "wof:name":"Rice Charles M Atty",
    "wof:placetype":"venue"
},
  "geometry": {"coordinates":[-84.38310199999999,33.784302],"type":"Point"}
}