{
  "type": "Feature",
  "properties": {
    "iso:country":"US",
    "sg:address":"190 Mc Garrah Rd",
    "sg:city":"Ochlocknee",
    "sg:classifiers":[
        {
            "category":"Health Services",
            "subcategory":"Doctor",
            "type":"Services"
        }
    ],
    "sg:phone":"+1 229 574 5756",
    "sg:postcode":"31773",
    "sg:province":"GA",
    "sg:tags":[
        "medical"
    ],
    "wof:name":"South Georgia Emergency Assoc",
    "wof:placetype":"venue"
},
  "geometry": {"coordinates":[-84.00194399999999,31.003055],"type":"Point"}
}