{
  "type": "Feature",
  "properties": {
    "addr:full":"3797 Due West Rd NW Marietta GA 30064",
    "addr:housenumber":"3797",
    "addr:postcode":"30064",
    "addr:street":"Due West Rd Nw",
    "iso:country":"US",
    "sg:address":"3797 Due West Rd NW",
    "sg:city":"Marietta",
    "sg:classifiers":[
        {
            "category":"Social Services",
            "subcategory":"Child Care",
            "type":"Services"
        }
    ],
    "sg:phone":"+1 770 590 0364",
    "sg:postcode":"30064",
    "sg:province":"GA",
    "sg:tags":[
        "day"
    ],
    "wof:name":"Due West Academy",
    "wof:placetype":"venue"
},
  "geometry": {"coordinates":[-84.66269699999999,33.965],"type":"Point"}
}