{
  "type": "Feature",
  "properties": {
    "iso:country":"US",
    "sg:address":"9388 Meadow Gate Ln",
    "sg:city":"Jonesboro",
    "sg:classifiers":[
        {
            "category":"Professional",
            "type":"Services"
        }
    ],
    "sg:phone":"+1 770 603 7199",
    "sg:postcode":"30236",
    "sg:province":"GA",
    "wof:name":"Global Network Engrg Tech I",
    "wof:placetype":"venue"
},
  "geometry": {"coordinates":[-84.325147,33.498713],"type":"Point"}
}