{
  "type": "Feature",
  "properties": {
    "addr:full":"119 W Central Ave Fitzgerald GA 31750",
    "addr:housenumber":"119",
    "addr:postcode":"31750",
    "addr:street":"W Central Ave",
    "iso:country":"US",
    "sg:address":"119 W Central Ave",
    "sg:city":"Fitzgerald",
    "sg:classifiers":[
        {
            "category":"Personal",
            "subcategory":"Beauty Salon",
            "type":"Services"
        }
    ],
    "sg:phone":"+1 229 423 9920",
    "sg:postcode":"31750",
    "sg:province":"GA",
    "sg:tags":[
        "shop"
    ],
    "wof:name":"His & Hers Style Shop",
    "wof:placetype":"venue"
},
  "geometry": {"coordinates":[-83.255608,31.714905],"type":"Point"}
}