{
  "type": "Feature",
  "properties": {
    "iso:country":"US",
    "sg:address":"4665 Ponte Vedra Dr SE",
    "sg:city":"Marietta",
    "sg:classifiers":[
        {
            "category":"Professional",
            "subcategory":"Lawyer & Legal Services",
            "type":"Services"
        }
    ],
    "sg:phone":"+1 770 952 1080",
    "sg:postcode":"30067",
    "sg:province":"GA",
    "wof:name":"Nash Melvin S Atty",
    "wof:placetype":"venue"
},
  "geometry": {"coordinates":[-84.416901,33.9445],"type":"Point"}
}