{
  "type": "Feature",
  "properties": {
    "iso:country":"US",
    "sg:address":"601 S Patterson St",
    "sg:city":"Valdosta",
    "sg:classifiers":[
        {
            "category":"Retail",
            "subcategory":"Car Wash",
            "type":"Services"
        }
    ],
    "sg:phone":"+1 229 242 3656",
    "sg:postcode":"31601",
    "sg:province":"GA",
    "sg:tags":[
        "automobile",
        "detail",
        "clean"
    ],
    "wof:name":"Superwash",
    "wof:placetype":"venue"
},
  "geometry": {"coordinates":[-83.27548299999999,30.824406],"type":"Point"}
}