{
  "type": "Feature",
  "properties": {
    "iso:country":"US",
    "sg:address":"5760 Buford Hwy NE",
    "sg:city":"Atlanta",
    "sg:classifiers":[
        {
            "category":"Shopping",
            "type":"Retail Goods"
        }
    ],
    "sg:phone":"+1 770 986 0017",
    "sg:postcode":"30340",
    "sg:province":"GA",
    "sg:tags":[
        "supply",
        "cosmetic",
        "beauty",
        "perfume"
    ],
    "wof:name":"Wang Beauty Supply",
    "wof:placetype":"venue"
},
  "geometry": {"coordinates":[-84.267628,33.908093],"type":"Point"}
}