{
  "type": "Feature",
  "properties": {
    "iso:country":"US",
    "sg:address":"2228 Redmond Cir",
    "sg:city":"Rome",
    "sg:classifiers":[
        {
            "category":"Shopping",
            "subcategory":"Used Merchandise",
            "type":"Retail Goods"
        }
    ],
    "sg:phone":"+1 706 291 0234",
    "sg:postcode":"30165",
    "sg:province":"GA",
    "wof:name":"Appliance World",
    "wof:placetype":"venue"
},
  "geometry": {"coordinates":[-85.226129,34.280901],"type":"Point"}
}