{
  "type": "Feature",
  "properties": {
    "addr:full":"1501 Sunnybrook Farm Rd Atlanta GA 30350",
    "addr:housenumber":"1501",
    "addr:postcode":"30350",
    "addr:street":"Sunnybrook Farm Rd",
    "iso:country":"US",
    "sg:address":"1501 Sunnybrook Farm Rd",
    "sg:city":"Atlanta",
    "sg:classifiers":[
        {
            "category":"Wholesale",
            "subcategory":"Non-durable Goods",
            "type":"Manufacturing & Wholesale Goods"
        }
    ],
    "sg:phone":"+1 770 396 0967",
    "sg:postcode":"30350",
    "sg:province":"GA",
    "sg:tags":[
        "party"
    ],
    "wof:name":"Cork & Company Inc",
    "wof:placetype":"venue"
},
  "geometry": {"coordinates":[-84.33721,33.979229],"type":"Point"}
}