{
  "type": "Feature",
  "properties": {
    "iso:country":"US",
    "sg:address":"8305 Williams Dr",
    "sg:city":"Douglasville",
    "sg:classifiers":[
        {
            "category":"Wholesale",
            "subcategory":"Motor Vehicles",
            "type":"Manufacturing & Wholesale Goods"
        }
    ],
    "sg:phone":"+1 770 489 1151",
    "sg:postcode":"30135",
    "sg:province":"GA",
    "wof:name":"J&H Auto Brokers Inc",
    "wof:placetype":"venue"
},
  "geometry": {"coordinates":[-84.846056,33.615431],"type":"Point"}
}