{
  "type": "Feature",
  "properties": {
    "addr:full":"275 Spring Creek Rd Roswell GA 30075",
    "addr:housenumber":"275",
    "addr:postcode":"30075",
    "addr:street":"Spring Creek Rd",
    "iso:country":"US",
    "sg:address":"275 Spring Creek Rd",
    "sg:city":"Roswell",
    "sg:classifiers":[
        {
            "category":"Freight",
            "type":"Transportation"
        },
        {
            "category":"Professional",
            "subcategory":"Business Services",
            "type":"Services"
        }
    ],
    "sg:phone":"+1 770 594 7386",
    "sg:postcode":"30075",
    "sg:province":"GA",
    "sg:tags":[
        "consultant"
    ],
    "wof:name":"Arey & Associates Inc",
    "wof:placetype":"venue"
},
  "geometry": {"coordinates":[-84.38858999999999,34.048679],"type":"Point"}
}