{
  "type": "Feature",
  "properties": {
    "iso:country":"US",
    "sg:address":"8440 Haven Wood Trl",
    "sg:city":"Roswell",
    "sg:classifiers":[
        {
            "category":"Real Estate",
            "subcategory":"Real Estate Agent",
            "type":"Services"
        }
    ],
    "sg:phone":"+1 770 641 9130",
    "sg:postcode":"30076",
    "sg:province":"GA",
    "wof:name":"Jo Anne Phillips",
    "wof:placetype":"venue"
},
  "geometry": {"coordinates":[-84.282229,33.98629],"type":"Point"}
}