{
  "type": "Feature",
  "properties": {
    "iso:country":"US",
    "sg:address":"365 Gaines School Rd",
    "sg:city":"Athens",
    "sg:classifiers":[
        {
            "category":"Health Services",
            "subcategory":"Health Practitioner",
            "type":"Services"
        }
    ],
    "sg:phone":"+1 706 369 8115",
    "sg:postcode":"30605",
    "sg:province":"GA",
    "wof:name":"East Athens Physical Therapy",
    "wof:placetype":"venue"
},
  "geometry": {"coordinates":[-83.32638799999999,33.935683],"type":"Point"}
}