{
  "type": "Feature",
  "properties": {
    "iso:country":"US",
    "sg:address":"708 G St",
    "sg:city":"Brunswick",
    "sg:classifiers":[
        {
            "category":"Real Estate",
            "subcategory":"Real Estate Services",
            "type":"Services"
        }
    ],
    "sg:phone":"+1 912 261 0748",
    "sg:postcode":"31520",
    "sg:province":"GA",
    "sg:tags":[
        "company",
        "title"
    ],
    "wof:name":"Golden Isles Title Svc Inc",
    "wof:placetype":"venue"
},
  "geometry": {"coordinates":[-81.49403100000001,31.1523],"type":"Point"}
}