{
  "type": "Feature",
  "properties": {
    "iso:country":"US",
    "sg:address":"2003 Riverside Pkwy",
    "sg:city":"Lawrenceville",
    "sg:classifiers":[
        {
            "category":"Retail",
            "subcategory":"Laundry & Dry Cleaning",
            "type":"Services"
        }
    ],
    "sg:phone":"+1 770 995 1888",
    "sg:postcode":"30043",
    "sg:province":"GA",
    "sg:tags":[
        "drycleaning",
        "plant",
        "cleaners"
    ],
    "wof:name":"Fabric Touch Cleaners",
    "wof:placetype":"venue"
},
  "geometry": {"coordinates":[-84.023729,33.984305],"type":"Point"}
}