{
  "type": "Feature",
  "properties": {
    "iso:country":"US",
    "sg:address":"7370 Southlake Pkwy",
    "sg:city":"Morrow",
    "sg:classifiers":[
        {
            "category":"Autos & Motor Vehicles",
            "subcategory":"Auto Supplies",
            "type":"Retail Goods"
        },
        {
            "category":"Retail",
            "subcategory":"Car Wash",
            "type":"Services"
        }
    ],
    "sg:phone":"+1 770 960 1877",
    "sg:postcode":"30260",
    "sg:province":"GA",
    "sg:tags":[
        "glass"
    ],
    "wof:name":"Waterworks Car Wash",
    "wof:placetype":"venue"
},
  "geometry": {"coordinates":[-84.33989699999999,33.5532],"type":"Point"}
}