{
  "type": "Feature",
  "properties": {
    "addr:full":"1404 Dresden Dr NE Atlanta GA 30319",
    "addr:housenumber":"1404",
    "addr:postcode":"30319",
    "addr:street":"Dresden Dr Ne",
    "iso:country":"US",
    "sg:address":"1404 Dresden Dr NE",
    "sg:city":"Atlanta",
    "sg:classifiers":[
        {
            "category":"Manufacturing",
            "subcategory":"Metals",
            "type":"Manufacturing & Wholesale Goods"
        }
    ],
    "sg:phone":"+1 404 869 0037",
    "sg:postcode":"30319",
    "sg:province":"GA",
    "wof:name":"Peachtree Polisher",
    "wof:placetype":"venue"
},
  "geometry": {"coordinates":[-84.331008,33.860887],"type":"Point"}
}