{
  "type": "Feature",
  "properties": {
    "iso:country":"US",
    "sg:address":"902 Carroll St",
    "sg:city":"Perry",
    "sg:classifiers":[
        {
            "category":"Shopping",
            "subcategory":"Clothing, Apparel, & Fashions",
            "type":"Retail Goods"
        }
    ],
    "sg:phone":"+1 478 988 9944",
    "sg:postcode":"31069",
    "sg:province":"GA",
    "wof:name":"Go Fish Clothing & Jewlery",
    "wof:placetype":"venue"
},
  "geometry": {"coordinates":[-83.732152,32.458674],"type":"Point"}
}