{
  "type": "Feature",
  "properties": {
    "addr:full":"689 Sycamore St Jefferson GA 30549",
    "addr:housenumber":"689",
    "addr:postcode":"30549",
    "addr:street":"Sycamore St",
    "iso:country":"US",
    "sg:address":"689 Sycamore St",
    "sg:city":"Jefferson",
    "sg:classifiers":[
        {
            "category":"Restaurant",
            "type":"Food & Drink"
        }
    ],
    "sg:menulink":"http://www.allmenus.com/ga/jefferson/80807-papa-johns-pizza/menu/",
    "sg:phone":"+1 706 367 5181",
    "sg:postcode":"30549",
    "sg:province":"GA",
    "sg:tags":[
        "american",
        "pizza"
    ],
    "wof:name":"Papa John's Pizza",
    "wof:placetype":"venue"
},
  "geometry": {"coordinates":[-83.56630800000001,34.124736],"type":"Point"}
}