{
  "type": "Feature",
  "properties": {
    "iso:country":"US",
    "sg:address":"318 Apache Dr",
    "sg:city":"Canton",
    "sg:classifiers":[
        {
            "category":"Retail",
            "subcategory":"Repair Shop",
            "type":"Services"
        }
    ],
    "sg:phone":"+1 770 345 4544",
    "sg:postcode":"30115",
    "sg:province":"GA",
    "sg:tags":[
        "welding"
    ],
    "wof:name":"Aero Professional Welding",
    "wof:placetype":"venue"
},
  "geometry": {"coordinates":[-84.47175799999999,34.170126],"type":"Point"}
}