{
  "type": "Feature",
  "properties": {
    "addr:full":"1250 Upper Hembree Rd Roswell GA 30076",
    "addr:housenumber":"1250",
    "addr:postcode":"30076",
    "addr:street":"Upper Hembree Rd",
    "iso:country":"US",
    "sg:address":"1250 Upper Hembree Rd",
    "sg:city":"Roswell",
    "sg:classifiers":[
        {
            "category":"Building & Trades",
            "subcategory":"Locksmith",
            "type":"Services"
        }
    ],
    "sg:phone":"+1 678 269 7159",
    "sg:postcode":"30076",
    "sg:province":"GA",
    "sg:tags":[
        "key"
    ],
    "wof:name":"7 Days Emergency Locksmith",
    "wof:placetype":"venue"
},
  "geometry": {"coordinates":[-84.323415,34.067574],"type":"Point"}
}