{
  "type": "Feature",
  "properties": {
    "iso:country":"US",
    "sg:address":"1102 Lake Haynes Ct NE",
    "sg:city":"Conyers",
    "sg:classifiers":[
        {
            "category":"Shopping",
            "subcategory":"Used Merchandise",
            "type":"Retail Goods"
        }
    ],
    "sg:phone":"+1 770 602 4535",
    "sg:postcode":"30012",
    "sg:province":"GA",
    "sg:tags":[
        "antique",
        "home",
        "accessory"
    ],
    "wof:name":"Richmond House",
    "wof:placetype":"venue"
},
  "geometry": {"coordinates":[-83.98091700000001,33.757638],"type":"Point"}
}