{
  "type": "Feature",
  "properties": {
    "iso:country":"US",
    "sg:address":"707 E Lake Dr",
    "sg:city":"Decatur",
    "sg:classifiers":[
        {
            "category":"Restaurant",
            "type":"Food & Drink"
        }
    ],
    "sg:phone":"+1 404 371 1113",
    "sg:postcode":"30030",
    "sg:province":"GA",
    "sg:website":"www.instantkavarna.com",
    "wof:name":"Kavarna",
    "wof:placetype":"venue"
},
  "geometry": {"coordinates":[-84.303212,33.759083],"type":"Point"}
}