{
  "type": "Feature",
  "properties": {
    "iso:country":"US",
    "sg:address":"3929 Pinehurst Way",
    "sg:city":"Duluth",
    "sg:classifiers":[
        {
            "category":"Shopping",
            "subcategory":"Used Merchandise",
            "type":"Retail Goods"
        }
    ],
    "sg:phone":"+1 770 813 9889",
    "sg:postcode":"30096",
    "sg:province":"GA",
    "sg:tags":[
        "antique"
    ],
    "wof:name":"Great Stuff Antiques",
    "wof:placetype":"venue"
},
  "geometry": {"coordinates":[-84.177162,34.003891],"type":"Point"}
}