{
  "type": "Feature",
  "properties": {
    "iso:country":"US",
    "sg:address":"327 E Main St",
    "sg:city":"Cartersville",
    "sg:classifiers":[
        {
            "category":"Personal",
            "subcategory":"Beauty Salon",
            "type":"Services"
        }
    ],
    "sg:phone":"+1 770 607 5855",
    "sg:postcode":"30120",
    "sg:province":"GA",
    "sg:tags":[
        "shop"
    ],
    "wof:name":"Paris Beauty Salon",
    "wof:placetype":"venue"
},
  "geometry": {"coordinates":[-84.79183999999999,34.166285],"type":"Point"}
}