{
  "type": "Feature",
  "properties": {
    "addr:full":"265 Peachtree St NE Atlanta GA 30303",
    "addr:housenumber":"265",
    "addr:postcode":"30303",
    "addr:street":"Peachtree St Ne",
    "iso:country":"US",
    "sg:address":"265 Peachtree St NE",
    "sg:city":"Atlanta",
    "sg:classifiers":[
        {
            "category":"Travel",
            "subcategory":"Hotels & Motels",
            "type":"Entertainment"
        }
    ],
    "sg:postcode":"30303",
    "sg:province":"GA",
    "sg:tags":[
        "lodging"
    ],
    "sg:website":"http://atlantaregency.hyatt.com/hyatt/hotels/index.jsp?src=agn_tig_hhc_lk_ntntlyellowpages_atlra",
    "wof:name":"Hyatt Regency Atlanta",
    "wof:placetype":"venue"
},
  "geometry": {"coordinates":[-84.395765,33.747575],"type":"Point"}
}