{
  "type": "Feature",
  "properties": {
    "addr:full":"1320 N Jefferson St Dublin GA 31021",
    "addr:housenumber":"1320",
    "addr:postcode":"31021",
    "addr:street":"N Jefferson St",
    "iso:country":"US",
    "sg:address":"1320 N Jefferson St",
    "sg:city":"Dublin",
    "sg:classifiers":[
        {
            "category":"Retail",
            "subcategory":"Funeral Services",
            "type":"Services"
        }
    ],
    "sg:phone":"+1 478 272 5855",
    "sg:postcode":"31021",
    "sg:province":"GA",
    "sg:tags":[
        "director"
    ],
    "wof:name":"Stanley Funeral Home Inc",
    "wof:placetype":"venue"
},
  "geometry": {"coordinates":[-82.917447,32.563465],"type":"Point"}
}