{
  "type": "Feature",
  "properties": {
    "iso:country":"US",
    "sg:address":"407 Old Mill Rd",
    "sg:city":"Savannah",
    "sg:classifiers":[
        {
            "category":"Professional",
            "subcategory":"Business Services",
            "type":"Services"
        }
    ],
    "sg:phone":"+1 912 927 6457",
    "sg:postcode":"31419",
    "sg:province":"GA",
    "wof:name":"Ankerson Enterprises Inc",
    "wof:placetype":"venue"
},
  "geometry": {"coordinates":[-81.14692700000001,31.963029],"type":"Point"}
}