{
  "type": "Feature",
  "properties": {
    "addr:full":"110 Chapman Ct La Fayette GA 30728",
    "addr:housenumber":"110",
    "addr:postcode":"30728",
    "addr:street":"Chapman Ct;Fayette",
    "iso:country":"US",
    "sg:address":"110 Chapman Ct",
    "sg:city":"La Fayette",
    "sg:classifiers":[
        {
            "category":"Manufacturing",
            "subcategory":"Tools & Machinery",
            "type":"Manufacturing & Wholesale Goods"
        }
    ],
    "sg:phone":"+1 706 638 7156",
    "sg:postcode":"30728",
    "sg:province":"GA",
    "sg:tags":[
        "machine",
        "shop"
    ],
    "wof:name":"Purnell Technologies",
    "wof:placetype":"venue"
},
  "geometry": {"coordinates":[-85.164143,34.759815],"type":"Point"}
}