{
  "type": "Feature",
  "properties": {
    "iso:country":"US",
    "sg:address":"101 Meadow Dr",
    "sg:city":"Cumming",
    "sg:classifiers":[
        {
            "category":"Personal",
            "subcategory":"Beauty Salon",
            "type":"Services"
        }
    ],
    "sg:phone":"+1 678 947 1121",
    "sg:postcode":"30040",
    "sg:province":"GA",
    "sg:tags":[
        "shop"
    ],
    "wof:name":"Hot City Looks",
    "wof:placetype":"venue"
},
  "geometry": {"coordinates":[-84.135398,34.200663],"type":"Point"}
}