{
  "type": "Feature",
  "properties": {
    "addr:full":"4117 Cherokee Trl Gainesville GA 30504",
    "addr:housenumber":"4117",
    "addr:postcode":"30504",
    "addr:street":"Cherokee Trl",
    "iso:country":"US",
    "sg:address":"4117 Cherokee Trl",
    "sg:city":"Gainesville",
    "sg:classifiers":[
        {
            "category":"Freight",
            "type":"Transportation"
        }
    ],
    "sg:phone":"+1 770 536 9063",
    "sg:postcode":"30504",
    "sg:province":"GA",
    "sg:tags":[
        "operator",
        "local",
        "trucking"
    ],
    "wof:name":"Wilson Hauling Assoc",
    "wof:placetype":"venue"
},
  "geometry": {"coordinates":[-83.919262,34.278024],"type":"Point"}
}