{
  "type": "Feature",
  "properties": {
    "iso:country":"US",
    "sg:address":"108 Proctor St",
    "sg:city":"Statesboro",
    "sg:classifiers":[
        {
            "category":"Social Services",
            "type":"Services"
        }
    ],
    "sg:phone":"+1 912 489 3663",
    "sg:postcode":"30458",
    "sg:province":"GA",
    "wof:name":"Food Bank Inc",
    "wof:placetype":"venue"
},
  "geometry": {"coordinates":[-81.787648,32.450067],"type":"Point"}
}