{
  "type": "Feature",
  "properties": {
    "addr:full":"3010 US Hwy 280 Cordele GA 31015",
    "addr:housenumber":"3010",
    "addr:postcode":"31015",
    "addr:street":"Us Hwy 280",
    "iso:country":"US",
    "sg:address":"3010 US Hwy 280",
    "sg:city":"Cordele",
    "sg:classifiers":[
        {
            "category":"Organizations",
            "subcategory":"Religious Organization",
            "type":"Services"
        }
    ],
    "sg:phone":"+1 229 273 2940",
    "sg:postcode":"31015",
    "sg:province":"GA",
    "sg:tags":[
        "church"
    ],
    "wof:name":"Morningside Baptist Church",
    "wof:placetype":"venue"
},
  "geometry": {"coordinates":[-83.73264399999999,31.956493],"type":"Point"}
}