{
  "type": "Feature",
  "properties": {
    "iso:country":"US",
    "sg:address":"125 Windsor Rd",
    "sg:city":"Savannah",
    "sg:classifiers":[
        {
            "category":"Organizations",
            "subcategory":"Religious Organization",
            "type":"Services"
        }
    ],
    "sg:phone":"+1 912 925 2029",
    "sg:postcode":"31419",
    "sg:province":"GA",
    "wof:name":"Evangelist Gene Burnett",
    "wof:placetype":"venue"
},
  "geometry": {"coordinates":[-81.137078,31.974157],"type":"Point"}
}