{
  "type": "Feature",
  "properties": {
    "addr:full":"5935 Buford Hwy Norcross GA 30071",
    "addr:housenumber":"5935",
    "addr:postcode":"30071",
    "addr:street":"Buford Hwy",
    "iso:country":"US",
    "sg:address":"5935 Buford Hwy",
    "sg:city":"Norcross",
    "sg:classifiers":[
        {
            "category":"Banks & Credit Unions",
            "subcategory":"Bank",
            "type":"Services"
        },
        {
            "category":"Banks & Credit Unions",
            "subcategory":"Financial Services",
            "type":"Services"
        }
    ],
    "sg:phone":"+1 800 734 4667",
    "sg:postcode":"30071",
    "sg:province":"GA",
    "sg:tags":[
        "broker",
        "mortgage"
    ],
    "sg:website":"www.regions.com",
    "wof:name":"Regions Bank",
    "wof:placetype":"venue"
},
  "geometry": {"coordinates":[-84.214699,33.935799],"type":"Point"}
}