{
  "type": "Feature",
  "properties": {
    "addr:full":"1150 S Marietta Pkwy Marietta GA 30060",
    "addr:housenumber":"1150",
    "addr:postcode":"30060",
    "addr:street":"S Marietta Pkwy",
    "iso:country":"US",
    "sg:address":"1150 S Marietta Pkwy",
    "sg:city":"Marietta",
    "sg:classifiers":[
        {
            "category":"Professional",
            "type":"Services"
        }
    ],
    "sg:phone":"+1 770 581 0400",
    "sg:postcode":"30060",
    "sg:province":"GA",
    "wof:name":"Homology",
    "wof:placetype":"venue"
},
  "geometry": {"coordinates":[-84.521621,33.941908],"type":"Point"}
}