{
  "type": "Feature",
  "properties": {
    "addr:full":"108 W Coffee St Hazlehurst GA 31539",
    "addr:housenumber":"108",
    "addr:postcode":"31539",
    "addr:street":"W Coffee St",
    "iso:country":"US",
    "sg:address":"108 W Coffee St",
    "sg:city":"Hazlehurst",
    "sg:classifiers":[
        {
            "category":"Education",
            "subcategory":"School",
            "type":"Public Place"
        }
    ],
    "sg:phone":"+1 912 375 6740",
    "sg:postcode":"31539",
    "sg:province":"GA",
    "wof:name":"Jeff Davis Community Education",
    "wof:placetype":"venue"
},
  "geometry": {"coordinates":[-82.598361,31.880453],"type":"Point"}
}