{
  "type": "Feature",
  "properties": {
    "addr:full":"730 Kingsbridge Rd Carrollton GA 30117",
    "addr:housenumber":"730",
    "addr:postcode":"30117",
    "addr:street":"Kingsbridge Rd",
    "iso:country":"US",
    "sg:address":"730 Kingsbridge Rd",
    "sg:city":"Carrollton",
    "sg:classifiers":[
        {
            "category":"Retail",
            "subcategory":"Repair Shop",
            "type":"Services"
        }
    ],
    "sg:phone":"+1 770 830 9183",
    "sg:postcode":"30117",
    "sg:province":"GA",
    "sg:tags":[
        "related"
    ],
    "wof:name":"West Georgia Forklift Repair",
    "wof:placetype":"venue"
},
  "geometry": {"coordinates":[-85.091409,33.600547],"type":"Point"}
}