{
  "type": "Feature",
  "properties": {
    "iso:country":"US",
    "sg:address":"134 Overlook Ct",
    "sg:city":"Ellenwood",
    "sg:classifiers":[
        {
            "category":"Recreation",
            "type":"Entertainment"
        }
    ],
    "sg:phone":"+1 770 369 0177",
    "sg:postcode":"30294",
    "sg:province":"GA",
    "sg:tags":[
        "entertainers-family",
        "business"
    ],
    "wof:name":"Grand Scale Entertainment",
    "wof:placetype":"venue"
},
  "geometry": {"coordinates":[-84.223583,33.623508],"type":"Point"}
}