{
  "type": "Feature",
  "properties": {
    "iso:country":"US",
    "sg:address":"2421 Waters Ave",
    "sg:city":"Savannah",
    "sg:classifiers":[
        {
            "category":"Shopping",
            "subcategory":"Hobbies, Toys, & Games",
            "type":"Retail Goods"
        },
        {
            "category":"Shopping",
            "subcategory":"Gifts & Souvenirs",
            "type":"Retail Goods"
        }
    ],
    "sg:phone":"+1 912 651 9930",
    "sg:postcode":"31404",
    "sg:province":"GA",
    "sg:tags":[
        "equipment",
        "ceramic",
        "supply"
    ],
    "wof:name":"Ruth's Ceramics",
    "wof:placetype":"venue"
},
  "geometry": {"coordinates":[-81.084722,32.050161],"type":"Point"}
}