{
  "type": "Feature",
  "properties": {
    "addr:full":"791 Mobley Rd Doerun GA 31744",
    "addr:housenumber":"791",
    "addr:postcode":"31744",
    "addr:street":"Mobley Rd",
    "iso:country":"US",
    "sg:address":"791 Mobley Rd",
    "sg:city":"Doerun",
    "sg:classifiers":[
        {
            "category":"Building & Trades",
            "subcategory":"Construction",
            "type":"Services"
        }
    ],
    "sg:phone":"+1 229 776 2323",
    "sg:postcode":"31744",
    "sg:province":"GA",
    "sg:tags":[
        "contractor"
    ],
    "wof:name":"Asphalt Sealcoating",
    "wof:placetype":"venue"
},
  "geometry": {"coordinates":[-83.95502500000001,31.386205],"type":"Point"}
}