{
  "type": "Feature",
  "properties": {
    "addr:full":"1197 Peachtree St NE Ste 524 Atlanta GA 30361",
    "addr:housenumber":"1197",
    "addr:postcode":"30361",
    "addr:street":"Peachtree St Ne Ste 524",
    "iso:country":"US",
    "sg:address":"1197 Peachtree St NE Ste 524",
    "sg:city":"Atlanta",
    "sg:classifiers":[
        {
            "category":"Personal",
            "subcategory":"Nail Salon",
            "type":"Services"
        }
    ],
    "sg:phone":"+1 404 872 7443",
    "sg:postcode":"30361",
    "sg:province":"GA",
    "wof:name":"Nails 4 U",
    "wof:placetype":"venue"
},
  "geometry": {"coordinates":[-84.383335,33.78716],"type":"Point"}
}