{
  "type": "Feature",
  "properties": {
    "addr:full":"151 Osigian Blvd Warner Robins GA 31088",
    "addr:housenumber":"151",
    "addr:postcode":"31088",
    "addr:street":"Osigian Blvd",
    "iso:country":"US",
    "sg:address":"151 Osigian Blvd",
    "sg:city":"Warner Robins",
    "sg:classifiers":[
        {
            "category":"Professional",
            "type":"Services"
        }
    ],
    "sg:phone":"+1 478 953 6373",
    "sg:postcode":"31088",
    "sg:province":"GA",
    "wof:name":"Pesystems Inc",
    "wof:placetype":"venue"
},
  "geometry": {"coordinates":[-83.68313000000001,32.613719],"type":"Point"}
}