{
  "type": "Feature",
  "properties": {
    "addr:full":"1805 Country Crest Way Dacula GA 30019",
    "addr:housenumber":"1805",
    "addr:postcode":"ga 30019",
    "addr:street":"Country Crest Way",
    "iso:country":"US",
    "sg:address":"1805 Country Crest Way",
    "sg:city":"Dacula",
    "sg:classifiers":[
        {
            "category":"Wholesale",
            "subcategory":"Non-durable Goods",
            "type":"Manufacturing & Wholesale Goods"
        }
    ],
    "sg:phone":"+1 770 277 0989",
    "sg:postcode":"30019",
    "sg:province":"GA",
    "sg:tags":[
        "gift",
        "contractor"
    ],
    "wof:name":"Elegant Designs",
    "wof:placetype":"venue"
},
  "geometry": {"coordinates":[-83.856004,33.953641],"type":"Point"}
}