{
  "type": "Feature",
  "properties": {
    "iso:country":"US",
    "sg:address":"4809 Joy Ln SW",
    "sg:city":"Lilburn",
    "sg:classifiers":[
        {
            "category":"Building & Trades",
            "subcategory":"Construction",
            "type":"Services"
        }
    ],
    "sg:phone":"+1 770 314 1600",
    "sg:postcode":"30047",
    "sg:province":"GA",
    "sg:tags":[
        "company"
    ],
    "wof:name":"Funderburk Construction",
    "wof:placetype":"venue"
},
  "geometry": {"coordinates":[-84.132965,33.881747],"type":"Point"}
}