{
  "type": "Feature",
  "properties": {
    "addr:full":"408 Cornish Mountain Rd Oxford GA 30054",
    "addr:housenumber":"408",
    "addr:postcode":"30054",
    "addr:street":"Cornish Mountain Rd",
    "iso:country":"US",
    "sg:address":"408 Cornish Mountain Rd",
    "sg:city":"Oxford",
    "sg:classifiers":[
        {
            "category":"Real Estate",
            "subcategory":"Developer",
            "type":"Services"
        }
    ],
    "sg:phone":"+1 770 787 3512",
    "sg:postcode":"30054",
    "sg:province":"GA",
    "wof:name":"TDH Development LLC",
    "wof:placetype":"venue"
},
  "geometry": {"coordinates":[-83.840311,33.663849],"type":"Point"}
}