{
  "type": "Feature",
  "properties": {
    "iso:country":"US",
    "sg:address":"3209 Deans Bridge Rd",
    "sg:city":"Augusta",
    "sg:classifiers":[
        {
            "category":"Restaurant",
            "type":"Food & Drink"
        }
    ],
    "sg:menulink":"http://www.allmenus.com/ga/augusta/174820-popeyes-chicken--biscuits/menu/",
    "sg:phone":"+1 706 790 9426",
    "sg:postcode":"30906",
    "sg:province":"GA",
    "sg:tags":[
        "american",
        "wing"
    ],
    "wof:name":"Popeyes Chicken & Biscuits",
    "wof:placetype":"venue"
},
  "geometry": {"coordinates":[-82.06740499999999,33.420629],"type":"Point"}
}