{
  "type": "Feature",
  "properties": {
    "addr:full":"621 North Avenue NE Building D Atlanta GA 30308",
    "addr:housenumber":"621",
    "addr:postcode":"30308",
    "addr:street":"North Avenue Ne Building D",
    "iso:country":"US",
    "sg:address":"621 North Avenue NE Building D",
    "sg:city":"Atlanta",
    "sg:classifiers":[
        {
            "category":"Professional",
            "type":"Services"
        }
    ],
    "sg:phone":"+1 404 815 0566",
    "sg:postcode":"30308",
    "sg:province":"GA",
    "sg:website":"www.asisignage.com",
    "wof:name":"ASI, Signage Innovations",
    "wof:placetype":"venue"
},
  "geometry": {"coordinates":[-84.409729,33.665627],"type":"Point"}
}