{
  "type": "Feature",
  "properties": {
    "iso:country":"US",
    "sg:address":"1400 Galleria Ln",
    "sg:city":"Smyrna",
    "sg:classifiers":[
        {
            "category":"Real Estate",
            "subcategory":"Real Estate Operator",
            "type":"Services"
        }
    ],
    "sg:phone":"+1 770 436 8050",
    "sg:postcode":"30080",
    "sg:province":"GA",
    "sg:tags":[
        "building",
        "apartment"
    ],
    "wof:name":"Galleria Courtyards",
    "wof:placetype":"venue"
},
  "geometry": {"coordinates":[-84.481737,33.886626],"type":"Point"}
}