{
  "type": "Feature",
  "properties": {
    "iso:country":"US",
    "sg:address":"35 Collier Rd NW Lbby",
    "sg:city":"Atlanta",
    "sg:classifiers":[
        {
            "category":"Health Services",
            "subcategory":"Doctor",
            "type":"Services"
        }
    ],
    "sg:phone":"+1 404 367 3100",
    "sg:postcode":"30309",
    "sg:province":"GA",
    "sg:tags":[
        "medicine",
        "internal"
    ],
    "sg:website":"www.piedmont.org",
    "wof:name":"Herd Paul MD",
    "wof:placetype":"venue"
},
  "geometry": {"coordinates":[-84.3955,33.807499],"type":"Point"}
}