{
  "type": "Feature",
  "properties": {
    "addr:full":"5498 Woodlin Rd Lula GA 30554",
    "addr:housenumber":"5498",
    "addr:postcode":"30554",
    "addr:street":"Woodlin Rd",
    "iso:country":"US",
    "sg:address":"5498 Woodlin Rd",
    "sg:city":"Lula",
    "sg:classifiers":[
        {
            "category":"Real Estate",
            "subcategory":"Surveying",
            "type":"Services"
        }
    ],
    "sg:phone":"+1 770 869 7615",
    "sg:postcode":"30554",
    "sg:province":"GA",
    "wof:name":"Viewpoint Land Surveying Inc",
    "wof:placetype":"venue"
},
  "geometry": {"coordinates":[-83.67214300000001,34.361443],"type":"Point"}
}