{
  "type": "Feature",
  "properties": {
    "addr:full":"3960 Buena Vista Rd Columbus GA 31907",
    "addr:housenumber":"3960",
    "addr:postcode":"31907",
    "addr:street":"Buena Vista Rd",
    "iso:country":"US",
    "sg:address":"3960 Buena Vista Rd",
    "sg:city":"Columbus",
    "sg:classifiers":[
        {
            "category":"Restaurant",
            "type":"Food & Drink"
        }
    ],
    "sg:menulink":"http://www.allmenus.com/ga/columbus/195986-taco-bell/menu/",
    "sg:postcode":"31907",
    "sg:province":"GA",
    "sg:tags":[
        "mexican"
    ],
    "wof:name":"Taco Bell",
    "wof:placetype":"venue"
},
  "geometry": {"coordinates":[-84.926483,32.463103],"type":"Point"}
}