{
  "type": "Feature",
  "properties": {
    "addr:full":"180 Daisy Ln Garfield GA 30425",
    "addr:housenumber":"180",
    "addr:postcode":"30425",
    "addr:street":"Daisy Ln",
    "iso:country":"US",
    "sg:address":"180 Daisy Ln",
    "sg:city":"Garfield",
    "sg:classifiers":[
        {
            "category":"Freight",
            "type":"Transportation"
        }
    ],
    "sg:phone":"+1 478 763 3350",
    "sg:postcode":"30425",
    "sg:province":"GA",
    "sg:tags":[
        "operator",
        "local",
        "trucking"
    ],
    "wof:name":"Lighthouse Trucking Inc",
    "wof:placetype":"venue"
},
  "geometry": {"coordinates":[-82.021653,32.600488],"type":"Point"}
}