{
  "type": "Feature",
  "properties": {
    "addr:full":"240 Arnold St Atlanta GA 30354",
    "addr:housenumber":"240",
    "addr:postcode":"30354",
    "addr:street":"Arnold St",
    "iso:country":"US",
    "sg:address":"240 Arnold St",
    "sg:city":"Atlanta",
    "sg:classifiers":[
        {
            "category":"Education",
            "subcategory":"School",
            "type":"Public Place"
        }
    ],
    "sg:phone":"+1 404 767 4312",
    "sg:postcode":"30354",
    "sg:province":"GA",
    "sg:tags":[
        "high",
        "middle",
        "elementary"
    ],
    "wof:name":"St John the Evangelist Catholic School",
    "wof:placetype":"venue"
},
  "geometry": {"coordinates":[-84.39769699999999,33.6562],"type":"Point"}
}