{
  "type": "Feature",
  "properties": {
    "iso:country":"US",
    "sg:address":"1839 N Creek Cir",
    "sg:city":"Alpharetta",
    "sg:classifiers":[
        {
            "category":"Professional",
            "subcategory":"Business Services",
            "type":"Services"
        }
    ],
    "sg:phone":"+1 770 740 8490",
    "sg:postcode":"30004",
    "sg:province":"GA",
    "wof:name":"Network Cmmnications Group LLC",
    "wof:placetype":"venue"
},
  "geometry": {"coordinates":[-84.292288,34.082917],"type":"Point"}
}