{
  "type": "Feature",
  "properties": {
    "addr:full":"3415 Hutchinson Rd Cumming GA 30040",
    "addr:housenumber":"3415",
    "addr:postcode":"30040",
    "addr:street":"Hutchinson Rd",
    "iso:country":"US",
    "sg:address":"3415 Hutchinson Rd",
    "sg:city":"Cumming",
    "sg:classifiers":[
        {
            "category":"Autos & Motor Vehicles",
            "subcategory":"Auto Supplies",
            "type":"Retail Goods"
        }
    ],
    "sg:phone":"+1 770 888 6642",
    "sg:postcode":"30040",
    "sg:province":"GA",
    "sg:tags":[
        "equipment",
        "station",
        "automotive"
    ],
    "wof:name":"Needham Equipment Co Inc",
    "wof:placetype":"venue"
},
  "geometry": {"coordinates":[-84.151211,34.189806],"type":"Point"}
}