{
  "type": "Feature",
  "properties": {
    "addr:full":"104 Fannin St Lagrange GA 30241",
    "addr:housenumber":"104",
    "addr:postcode":"30241",
    "addr:street":"Fannin St",
    "iso:country":"US",
    "sg:address":"104 Fannin St",
    "sg:city":"Lagrange",
    "sg:classifiers":[
        {
            "category":"Social Services",
            "subcategory":"Child Care",
            "type":"Services"
        }
    ],
    "sg:phone":"+1 706 845 0705",
    "sg:postcode":"30241",
    "sg:province":"GA",
    "wof:name":"Yvette's Little World",
    "wof:placetype":"venue"
},
  "geometry": {"coordinates":[-85.02776799999999,33.031393],"type":"Point"}
}