{
  "type": "Feature",
  "properties": {
    "iso:country":"US",
    "sg:address":"2805 Macon Dr SW Apt 13H",
    "sg:city":"Atlanta",
    "sg:classifiers":[
        {
            "category":"Building & Trades",
            "subcategory":"Cleaning & Sanitation",
            "type":"Services"
        }
    ],
    "sg:phone":"+1 678 949 2785",
    "sg:postcode":"30354",
    "sg:province":"GA",
    "sg:tags":[
        "cleaners-interior"
    ],
    "wof:name":"Totalglory Cleaning Service",
    "wof:placetype":"venue"
},
  "geometry": {"coordinates":[-84.388789,33.676833],"type":"Point"}
}