{
  "type": "Feature",
  "properties": {
    "addr:full":"4804 Hillside Ct Powder Springs GA 30127",
    "addr:housenumber":"4804",
    "addr:postcode":"30127",
    "addr:street":"Hillside Ct",
    "iso:country":"US",
    "sg:address":"4804 Hillside Ct",
    "sg:city":"Powder Springs",
    "sg:classifiers":[
        {
            "category":"Building & Trades",
            "subcategory":"Plumbing",
            "type":"Services"
        }
    ],
    "sg:phone":"+1 678 567 5200",
    "sg:postcode":"30127",
    "sg:province":"GA",
    "sg:tags":[
        "conditioning",
        "air",
        "system",
        "contractor"
    ],
    "wof:name":"United Heating & Cooling",
    "wof:placetype":"venue"
},
  "geometry": {"coordinates":[-84.694402,33.871665],"type":"Point"}
}