{
  "type": "Feature",
  "properties": {
    "addr:full":"2720 Mall of Georgia Blvd Buford GA 30519",
    "addr:housenumber":"2720",
    "addr:postcode":"30519",
    "addr:street":"Mall Of Georgia Blvd",
    "iso:country":"US",
    "sg:address":"2720 Mall of Georgia Blvd",
    "sg:city":"Buford",
    "sg:classifiers":[
        {
            "category":"Restaurant",
            "type":"Food & Drink"
        }
    ],
    "sg:menulink":"http://www.allmenus.com/ga/dacula-rocky-creek/241911-old-mill-house-restaurant/menu/",
    "sg:phone":"+1 770 271 9454",
    "sg:postcode":"30519",
    "sg:province":"GA",
    "sg:tags":[
        "american"
    ],
    "wof:name":"Old Mill House Restaurant",
    "wof:placetype":"venue"
},
  "geometry": {"coordinates":[-83.973772,34.066418],"type":"Point"}
}