{
  "type": "Feature",
  "properties": {
    "iso:country":"US",
    "sg:address":"59 Hager Dr",
    "sg:city":"Riverdale",
    "sg:classifiers":[
        {
            "category":"Professional",
            "subcategory":"Business Services",
            "type":"Services"
        }
    ],
    "sg:phone":"+1 770 477 2649",
    "sg:postcode":"30274",
    "sg:province":"GA",
    "sg:tags":[
        "director",
        "music"
    ],
    "wof:name":"Will W Rogers",
    "wof:placetype":"venue"
},
  "geometry": {"coordinates":[-84.394025,33.546891],"type":"Point"}
}