{
  "type": "Feature",
  "properties": {
    "iso:country":"US",
    "sg:address":"2236 Beecher Rd SW",
    "sg:city":"Atlanta",
    "sg:classifiers":[
        {
            "category":"Building & Trades",
            "subcategory":"Construction",
            "type":"Services"
        }
    ],
    "sg:phone":"+1 404 756 3003",
    "sg:postcode":"30311",
    "sg:province":"GA",
    "sg:tags":[
        "contractor"
    ],
    "wof:name":"Ferguson Contractors",
    "wof:placetype":"venue"
},
  "geometry": {"coordinates":[-84.461657,33.72889],"type":"Point"}
}