{
  "type": "Feature",
  "properties": {
    "addr:full":"997 State Rte 338 Dudley GA 31022",
    "addr:housenumber":"997",
    "addr:postcode":"31022",
    "addr:street":"State Rte 338",
    "iso:country":"US",
    "sg:address":"997 State Rte 338",
    "sg:city":"Dudley",
    "sg:classifiers":[
        {
            "category":"Social Services",
            "type":"Services"
        }
    ],
    "sg:phone":"+1 478 676 2945",
    "sg:postcode":"31022",
    "sg:province":"GA",
    "sg:tags":[
        "youth",
        "organization",
        "center"
    ],
    "wof:name":"Boys & Girls Club-Grtr Laurens",
    "wof:placetype":"venue"
},
  "geometry": {"coordinates":[-83.062268,32.547958],"type":"Point"}
}