{
  "type": "Feature",
  "properties": {
    "iso:country":"US",
    "sg:address":"2085 Roswell Rd Apt. 524",
    "sg:city":"Marietta",
    "sg:phone":"+1 404 439 0395",
    "sg:postcode":"30062",
    "sg:province":"GA",
    "wof:name":"All in One Repair and Construction",
    "wof:placetype":"venue"
},
  "geometry": {"coordinates":[-84.492138,33.965324],"type":"Point"}
}