{
  "type": "Feature",
  "properties": {
    "addr:full":"310 Berry St Soperton GA 30457",
    "addr:housenumber":"310",
    "addr:postcode":"30457",
    "addr:street":"Berry St",
    "iso:country":"US",
    "sg:address":"310 Berry St",
    "sg:city":"Soperton",
    "sg:classifiers":[
        {
            "category":"Building & Trades",
            "subcategory":"Construction",
            "type":"Services"
        }
    ],
    "sg:phone":"+1 912 529 4117",
    "sg:postcode":"30457",
    "sg:province":"GA",
    "sg:tags":[
        "masonry",
        "contractor"
    ],
    "wof:name":"Little Masonry",
    "wof:placetype":"venue"
},
  "geometry": {"coordinates":[-82.604901,32.378928],"type":"Point"}
}