{
  "type": "Feature",
  "properties": {
    "iso:country":"US",
    "sg:address":"18 Barry Dr NE",
    "sg:city":"White",
    "sg:classifiers":[
        {
            "category":"Professional",
            "subcategory":"Employment Agencies",
            "type":"Services"
        }
    ],
    "sg:phone":"+1 770 606 9019",
    "sg:postcode":"30184",
    "sg:province":"GA",
    "sg:tags":[
        "supply",
        "help",
        "contractor"
    ],
    "wof:name":"T Ps Staffing",
    "wof:placetype":"venue"
},
  "geometry": {"coordinates":[-84.754565,34.268681],"type":"Point"}
}