{
  "type": "Feature",
  "properties": {
    "iso:country":"US",
    "sg:address":"703 E Montgomery Xrd",
    "sg:city":"Savannah",
    "sg:classifiers":[
        {
            "category":"Building & Trades",
            "subcategory":"Landscaping Services",
            "type":"Services"
        }
    ],
    "sg:phone":"+1 912 925 3992",
    "sg:postcode":"31406",
    "sg:province":"GA",
    "wof:name":"Fancy Plants Inc",
    "wof:placetype":"venue"
},
  "geometry": {"coordinates":[-81.111131,31.995448],"type":"Point"}
}