{
  "type": "Feature",
  "properties": {
    "addr:full":"348 Buford Dr Lawrenceville GA 30045",
    "addr:housenumber":"348",
    "addr:postcode":"30045",
    "addr:street":"Buford Dr",
    "iso:country":"US",
    "sg:address":"348 Buford Dr",
    "sg:city":"Lawrenceville",
    "sg:classifiers":[
        {
            "category":"Insurance",
            "subcategory":"Insurance Agent",
            "type":"Services"
        }
    ],
    "sg:phone":"+1 770 338 9222",
    "sg:postcode":"30045",
    "sg:province":"GA",
    "wof:name":"ABC Insurance",
    "wof:placetype":"venue"
},
  "geometry": {"coordinates":[-83.985933,33.964977],"type":"Point"}
}