{
  "type": "Feature",
  "properties": {
    "iso:country":"US",
    "sg:address":"300 Hardee St",
    "sg:city":"Dallas",
    "sg:classifiers":[
        {
            "category":"Retail",
            "subcategory":"Repair Shop",
            "type":"Services"
        }
    ],
    "sg:phone":"+1 770 443 0487",
    "sg:postcode":"30132",
    "sg:province":"GA",
    "sg:tags":[
        "blacksmith"
    ],
    "wof:name":"Farber Creations",
    "wof:placetype":"venue"
},
  "geometry": {"coordinates":[-84.837037,33.920559],"type":"Point"}
}