{
  "type": "Feature",
  "properties": {
    "addr:full":"151 S Bethel St Thomaston GA 30286",
    "addr:housenumber":"151",
    "addr:postcode":"30286",
    "addr:street":"S Bethel St",
    "iso:country":"US",
    "sg:address":"151 S Bethel St",
    "sg:city":"Thomaston",
    "sg:classifiers":[
        {
            "category":"Organizations",
            "subcategory":"Professional Association",
            "type":"Services"
        }
    ],
    "sg:phone":"+1 706 647 7473",
    "sg:postcode":"30286",
    "sg:province":"GA",
    "sg:website":"www.ghsa.net",
    "wof:name":"Georgia High School Assn",
    "wof:placetype":"venue"
},
  "geometry": {"coordinates":[-84.32356799999999,32.88801],"type":"Point"}
}