{
  "type": "Feature",
  "properties": {
    "addr:full":"6655 Fred Bohannon Rd Eastman GA 31023",
    "addr:housenumber":"6655",
    "addr:postcode":"31023",
    "addr:street":"Fred Bohannon Rd",
    "iso:country":"US",
    "sg:address":"6655 Fred Bohannon Rd",
    "sg:city":"Eastman",
    "sg:classifiers":[
        {
            "category":"Retail",
            "subcategory":"Auto Repair",
            "type":"Services"
        }
    ],
    "sg:phone":"+1 478 374 5778",
    "sg:postcode":"31023",
    "sg:province":"GA",
    "sg:tags":[
        "repairing",
        "automobile"
    ],
    "wof:name":"Bohannon Towing",
    "wof:placetype":"venue"
},
  "geometry": {"coordinates":[-83.13975000000001,32.197759],"type":"Point"}
}