{
  "type": "Feature",
  "properties": {
    "iso:country":"US",
    "sg:address":"2918 Martha Berry Hwy",
    "sg:city":"Rome",
    "sg:classifiers":[
        {
            "category":"Food & Beverages",
            "subcategory":"Groceries & Convenience Stores",
            "type":"Retail Goods"
        }
    ],
    "sg:phone":"+1 706 232 2749",
    "sg:postcode":"30165",
    "sg:province":"GA",
    "sg:tags":[
        "station"
    ],
    "wof:name":"Favorite Markets 202",
    "wof:placetype":"venue"
},
  "geometry": {"coordinates":[-85.17428700000001,34.305144],"type":"Point"}
}