{
  "type": "Feature",
  "properties": {
    "addr:full":"2500 Northeast Expressway Atlanta GA 30345",
    "addr:housenumber":"2500",
    "addr:postcode":"30345",
    "addr:street":"Northeast Expressway",
    "iso:country":"US",
    "sg:address":"2500 Northeast Expressway",
    "sg:city":"Atlanta",
    "sg:classifiers":[
        {
            "category":"Real Estate",
            "subcategory":"Real Estate Services",
            "type":"Services"
        },
        {
            "category":"Real Estate",
            "subcategory":"Real Estate Operator",
            "type":"Services"
        }
    ],
    "sg:phone":"+1 866 548 1606",
    "sg:postcode":"30345",
    "sg:province":"GA",
    "sg:tags":[
        "apartment",
        "property",
        "management"
    ],
    "sg:website":"www.WestchesterClairmont.com",
    "wof:name":"Westchester at Clairmont",
    "wof:placetype":"venue"
},
  "geometry": {"coordinates":[-84.301255,33.853339],"type":"Point"}
}