{
  "type": "Feature",
  "properties": {
    "iso:country":"US",
    "sg:address":"890 Boulevard St",
    "sg:city":"Athens",
    "sg:classifiers":[
        {
            "category":"Organizations",
            "subcategory":"Religious Organization",
            "type":"Services"
        }
    ],
    "sg:phone":"+1 706 543 6320",
    "sg:postcode":"30601",
    "sg:province":"GA",
    "sg:tags":[
        "church"
    ],
    "wof:name":"West End Baptist Church Inc",
    "wof:placetype":"venue"
},
  "geometry": {"coordinates":[-83.395669,33.96628],"type":"Point"}
}