{
  "type": "Feature",
  "properties": {
    "iso:country":"US",
    "sg:address":"123 Main St",
    "sg:city":"Claxton",
    "sg:classifiers":[
        {
            "category":"Government",
            "subcategory":"Court House",
            "type":"Public Place"
        }
    ],
    "sg:phone":"+1 912 739 4080",
    "sg:postcode":"30417",
    "sg:province":"GA",
    "sg:tags":[
        "county"
    ],
    "wof:name":"Evans County Probate Court Ofc",
    "wof:placetype":"venue"
},
  "geometry": {"coordinates":[-81.92366,32.160556],"type":"Point"}
}