{
  "type": "Feature",
  "properties": {
    "iso:country":"US",
    "sg:address":"3856 Grand Forest Dr",
    "sg:city":"Norcross",
    "sg:classifiers":[
        {
            "category":"Personal",
            "type":"Services"
        }
    ],
    "sg:phone":"+1 770 798 9886",
    "sg:postcode":"30092",
    "sg:province":"GA",
    "sg:tags":[
        "assistant"
    ],
    "wof:name":"Fulltime Magi",
    "wof:placetype":"venue"
},
  "geometry": {"coordinates":[-84.242363,33.968235],"type":"Point"}
}