{
  "type": "Feature",
  "properties": {
    "addr:full":"2180 Irvindale Dr Atlanta GA 30341",
    "addr:housenumber":"2180",
    "addr:postcode":"30341",
    "addr:street":"Irvindale Dr",
    "iso:country":"US",
    "sg:address":"2180 Irvindale Dr",
    "sg:city":"Atlanta",
    "sg:classifiers":[
        {
            "category":"Manufacturing",
            "subcategory":"Chemicals & Compounds",
            "type":"Manufacturing & Wholesale Goods"
        }
    ],
    "sg:phone":"+1 770 986 7600",
    "sg:postcode":"30341",
    "sg:province":"GA",
    "sg:tags":[
        "control",
        "pest",
        "equipment",
        "supply"
    ],
    "wof:name":"Univar USA Inc",
    "wof:placetype":"venue"
},
  "geometry": {"coordinates":[-84.296753,33.897932],"type":"Point"}
}