{
  "type": "Feature",
  "properties": {
    "addr:full":"104 Hunton St NW Poulan GA 31781",
    "addr:housenumber":"104",
    "addr:postcode":"poulan;31781",
    "addr:street":"Hunton St Nw",
    "iso:country":"US",
    "sg:address":"104 Hunton St NW",
    "sg:city":"Poulan",
    "sg:classifiers":[
        {
            "category":"Retail",
            "subcategory":"Laundry & Dry Cleaning",
            "type":"Services"
        }
    ],
    "sg:phone":"+1 229 776 9346",
    "sg:postcode":"31781",
    "sg:province":"GA",
    "sg:tags":[
        "cleaners",
        "rug",
        "carpet"
    ],
    "wof:name":"Roy's Carpet & Upholstery",
    "wof:placetype":"venue"
},
  "geometry": {"coordinates":[-83.78824400000001,31.514652],"type":"Point"}
}