{
  "type": "Feature",
  "properties": {
    "iso:country":"US",
    "sg:address":"118 Olive St",
    "sg:city":"Gordon",
    "sg:classifiers":[
        {
            "category":"Organizations",
            "subcategory":"Religious Organization",
            "type":"Services"
        }
    ],
    "sg:phone":"+1 478 628 5417",
    "sg:postcode":"31031",
    "sg:province":"GA",
    "sg:tags":[
        "church"
    ],
    "wof:name":"Gordon Church-God In Christ",
    "wof:placetype":"venue"
},
  "geometry": {"coordinates":[-83.320966,32.882959],"type":"Point"}
}