{
  "type": "Feature",
  "properties": {
    "iso:country":"US",
    "sg:address":"104 E Main St",
    "sg:city":"Thomaston",
    "sg:classifiers":[
        {
            "category":"Retail",
            "subcategory":"Laundry & Dry Cleaning",
            "type":"Services"
        },
        {
            "category":"Shopping",
            "subcategory":"Clothing, Apparel, & Fashions",
            "type":"Retail Goods"
        }
    ],
    "sg:phone":"+1 706 646 3330",
    "sg:postcode":"30286",
    "sg:province":"GA",
    "sg:tags":[
        "alteration"
    ],
    "wof:name":"Thomaston Tailoring & Alterati",
    "wof:placetype":"venue"
},
  "geometry": {"coordinates":[-84.326166,32.88793],"type":"Point"}
}