{
  "type": "Feature",
  "properties": {
    "addr:full":"3859 Austin Cir Decatur GA 30032",
    "addr:housenumber":"3859",
    "addr:postcode":"30032",
    "addr:street":"Austin Cir",
    "iso:country":"US",
    "sg:address":"3859 Austin Cir",
    "sg:city":"Decatur",
    "sg:classifiers":[
        {
            "category":"Real Estate",
            "subcategory":"Real Estate Operator",
            "type":"Services"
        }
    ],
    "sg:phone":"+1 404 284 2553",
    "sg:postcode":"30032",
    "sg:province":"GA",
    "sg:tags":[
        "apartment"
    ],
    "wof:name":"Wynhollow Apts",
    "wof:placetype":"venue"
},
  "geometry": {"coordinates":[-84.2332,33.734501],"type":"Point"}
}