{
  "type": "Feature",
  "properties": {
    "iso:country":"US",
    "sg:address":"1100 Big A Rd S",
    "sg:city":"Toccoa",
    "sg:classifiers":[
        {
            "category":"Organizations",
            "subcategory":"Community Association",
            "type":"Services"
        }
    ],
    "sg:phone":"+1 706 886 4944",
    "sg:postcode":"30577",
    "sg:province":"GA",
    "sg:tags":[
        "club"
    ],
    "wof:name":"Fellowship Of Christian Athlts",
    "wof:placetype":"venue"
},
  "geometry": {"coordinates":[-83.298508,34.56538],"type":"Point"}
}