{
  "type": "Feature",
  "properties": {
    "iso:country":"US",
    "sg:address":"2810 Howell Rd",
    "sg:city":"Lake Park",
    "sg:classifiers":[
        {
            "category":"Building & Trades",
            "subcategory":"Construction",
            "type":"Services"
        }
    ],
    "sg:phone":"+1 229 245 1841",
    "sg:postcode":"31636",
    "sg:province":"GA",
    "sg:tags":[
        "house"
    ],
    "wof:name":"Allen Home Improvement & Repr",
    "wof:placetype":"venue"
},
  "geometry": {"coordinates":[-83.17312200000001,30.831985],"type":"Point"}
}