{
  "type": "Feature",
  "properties": {
    "addr:full":"1380 English St NW Atlanta GA 30318",
    "addr:housenumber":"1380",
    "addr:postcode":"30318",
    "addr:street":"English St Nw",
    "iso:country":"US",
    "sg:address":"1380 English St NW",
    "sg:city":"Atlanta",
    "sg:classifiers":[
        {
            "category":"Building & Trades",
            "subcategory":"Plumbing",
            "type":"Services"
        }
    ],
    "sg:phone":"+1 404 355 7707",
    "sg:postcode":"30318",
    "sg:province":"GA",
    "sg:tags":[
        "sheet",
        "work",
        "metal",
        "contractor"
    ],
    "wof:name":"B & S Sheet Metals",
    "wof:placetype":"venue"
},
  "geometry": {"coordinates":[-84.420609,33.792099],"type":"Point"}
}