{
  "type": "Feature",
  "properties": {
    "iso:country":"US",
    "sg:address":"3477 Friendship Farm Dr",
    "sg:city":"Buford",
    "sg:classifiers":[
        {
            "category":"Professional",
            "subcategory":"Art Services",
            "type":"Services"
        }
    ],
    "sg:phone":"+1 770 843 8898",
    "sg:postcode":"30519",
    "sg:province":"GA",
    "sg:tags":[
        "photographer"
    ],
    "sg:website":"www.casablancaphotography.net",
    "wof:name":"Casablanca Photography",
    "wof:placetype":"venue"
},
  "geometry": {"coordinates":[-83.91034000000001,34.121786],"type":"Point"}
}