{
  "type": "Feature",
  "properties": {
    "iso:country":"US",
    "sg:address":"1150 Grimes Bridge Rd",
    "sg:city":"Roswell",
    "sg:classifiers":[
        {
            "category":"Health Services",
            "subcategory":"Dentist",
            "type":"Services"
        }
    ],
    "sg:phone":"+1 770 641 8010",
    "sg:postcode":"30075",
    "sg:province":"GA",
    "wof:name":"Demercy & Associates",
    "wof:placetype":"venue"
},
  "geometry": {"coordinates":[-84.34279600000001,34.029499],"type":"Point"}
}