{
  "type": "Feature",
  "properties": {
    "iso:country":"US",
    "sg:address":"2100 Riveredge Pkwy NW",
    "sg:city":"Atlanta",
    "sg:classifiers":[
        {
            "category":"Banks & Credit Unions",
            "subcategory":"Investment Brokerage",
            "type":"Services"
        }
    ],
    "sg:phone":"+1 770 951 2129",
    "sg:postcode":"30328",
    "sg:province":"GA",
    "sg:tags":[
        "investing"
    ],
    "sg:website":"www.banyancapital.com",
    "wof:name":"Banyan Capital Management Inc",
    "wof:placetype":"venue"
},
  "geometry": {"coordinates":[-84.37869999999999,33.936401],"type":"Point"}
}