{
  "type": "Feature",
  "properties": {
    "iso:country":"US",
    "sg:address":"1704 Jimmy St",
    "sg:city":"Adel",
    "sg:classifiers":[
        {
            "category":"Social Services",
            "subcategory":"Adult Care",
            "type":"Services"
        }
    ],
    "sg:phone":"+1 229 549 9240",
    "sg:postcode":"31620",
    "sg:province":"GA",
    "sg:tags":[
        "counselor",
        "relation",
        "human"
    ],
    "sg:website":"http://www.christiancounselingservices.org",
    "wof:name":"Christian Counseling Services",
    "wof:placetype":"venue"
},
  "geometry": {"coordinates":[-83.415983,31.161208],"type":"Point"}
}