{
  "type": "Feature",
  "properties": {
    "addr:full":"745 Chastain Rd NW Kennesaw GA 30144",
    "addr:housenumber":"745",
    "addr:postcode":"30144",
    "addr:street":"Chastain Rd Nw",
    "iso:country":"US",
    "sg:address":"745 Chastain Rd NW",
    "sg:city":"Kennesaw",
    "sg:classifiers":[
        {
            "category":"Building & Trades",
            "subcategory":"Locksmith",
            "type":"Services"
        }
    ],
    "sg:phone":"+1 877 800 8916",
    "sg:postcode":"30144",
    "sg:province":"GA",
    "sg:tags":[
        "key"
    ],
    "wof:name":"1 24 Hour Emergency Locksmith",
    "wof:placetype":"venue"
},
  "geometry": {"coordinates":[-84.571962,34.035133],"type":"Point"}
}