{
  "type": "Feature",
  "properties": {
    "addr:full":"1518 State Rte 74 Tyrone GA 30290",
    "addr:housenumber":"1518",
    "addr:postcode":"30290",
    "addr:street":"State Rte 74",
    "iso:country":"US",
    "sg:address":"1518 State Rte 74",
    "sg:city":"Tyrone",
    "sg:classifiers":[
        {
            "category":"Personal",
            "subcategory":"Beauty Salon",
            "type":"Services"
        }
    ],
    "sg:phone":"+1 770 774 7477",
    "sg:postcode":"30290",
    "sg:province":"GA",
    "sg:tags":[
        "manicuring"
    ],
    "wof:name":"Beach Club",
    "wof:placetype":"venue"
},
  "geometry": {"coordinates":[-84.577438,33.505828],"type":"Point"}
}