{
  "type": "Feature",
  "properties": {
    "iso:country":"US",
    "sg:address":"76 Vaughn Rd",
    "sg:city":"Griffin",
    "sg:classifiers":[
        {
            "category":"Retail",
            "subcategory":"Repair Shop",
            "type":"Services"
        }
    ],
    "sg:phone":"+1 770 229 6204",
    "sg:postcode":"30223",
    "sg:province":"GA",
    "wof:name":"Howard Keith",
    "wof:placetype":"venue"
},
  "geometry": {"coordinates":[-84.383371,33.243108],"type":"Point"}
}