{
  "type": "Feature",
  "properties": {
    "iso:country":"US",
    "sg:address":"6170 Windsor Trace Dr",
    "sg:city":"Norcross",
    "sg:classifiers":[
        {
            "category":"Professional",
            "subcategory":"Management & Consulting",
            "type":"Services"
        }
    ],
    "sg:phone":"+1 770 449 1918",
    "sg:postcode":"30092",
    "sg:province":"GA",
    "wof:name":"Training & Management Ser",
    "wof:placetype":"venue"
},
  "geometry": {"coordinates":[-84.23969,33.959434],"type":"Point"}
}