{
  "type": "Feature",
  "properties": {
    "iso:country":"US",
    "sg:address":"1808 State Rte 52",
    "sg:city":"Chatsworth",
    "sg:classifiers":[
        {
            "category":"Freight",
            "type":"Transportation"
        }
    ],
    "sg:phone":"+1 706 695 4475",
    "sg:postcode":"30705",
    "sg:province":"GA",
    "sg:tags":[
        "operator",
        "trucking"
    ],
    "wof:name":"Manley Trucking",
    "wof:placetype":"venue"
},
  "geometry": {"coordinates":[-84.74340599999999,34.75906],"type":"Point"}
}