{
  "type": "Feature",
  "properties": {
    "iso:country":"US",
    "sg:address":"513 Mobile Ln SW",
    "sg:city":"Marietta",
    "sg:classifiers":[
        {
            "category":"Building & Trades",
            "subcategory":"Construction",
            "type":"Services"
        }
    ],
    "sg:phone":"+1 770 485 3209",
    "sg:postcode":"30008",
    "sg:province":"GA",
    "sg:tags":[
        "contractor"
    ],
    "wof:name":"Personal Touch Mobile Cleaning",
    "wof:placetype":"venue"
},
  "geometry": {"coordinates":[-84.55319299999999,33.930871],"type":"Point"}
}