{
  "type": "Feature",
  "properties": {
    "iso:country":"US",
    "sg:address":"310 Cotton Field Way",
    "sg:city":"Alpharetta",
    "sg:classifiers":[
        {
            "category":"Professional",
            "type":"Services"
        }
    ],
    "sg:phone":"+1 770 740 1890",
    "sg:postcode":"30022",
    "sg:province":"GA",
    "wof:name":"Fortney Fortna Genealogy",
    "wof:placetype":"venue"
},
  "geometry": {"coordinates":[-84.27296,34.048716],"type":"Point"}
}