{
  "type": "Feature",
  "properties": {
    "addr:full":"5770 Bankhead Hwy Austell GA 30134",
    "addr:housenumber":"5770",
    "addr:postcode":"30134",
    "addr:street":"Bankhead Hwy",
    "iso:country":"US",
    "sg:address":"5770 Bankhead Hwy",
    "sg:city":"Austell",
    "sg:classifiers":[
        {
            "category":"Food & Beverages",
            "subcategory":"Liquor & Beverages",
            "type":"Retail Goods"
        }
    ],
    "sg:phone":"+1 770 944 8344",
    "sg:postcode":"30134",
    "sg:province":"GA",
    "wof:name":"Al's Package",
    "wof:placetype":"venue"
},
  "geometry": {"coordinates":[-84.721521,33.764087],"type":"Point"}
}