{
  "type": "Feature",
  "properties": {
    "addr:full":"259 Scenic Hwy Lawrenceville GA 30045",
    "addr:housenumber":"259",
    "addr:postcode":"30045",
    "addr:street":"Scenic Hwy",
    "iso:country":"US",
    "sg:address":"259 Scenic Hwy",
    "sg:city":"Lawrenceville",
    "sg:classifiers":[
        {
            "category":"Food & Beverages",
            "subcategory":"Groceries & Convenience Stores",
            "type":"Retail Goods"
        }
    ],
    "sg:phone":"+1 770 822 9335",
    "sg:postcode":"30045",
    "sg:province":"GA",
    "wof:name":"Fina Mart",
    "wof:placetype":"venue"
},
  "geometry": {"coordinates":[-83.991203,33.9422],"type":"Point"}
}