{
  "type": "Feature",
  "properties": {
    "iso:country":"US",
    "sg:address":"48 Economy St",
    "sg:city":"Summerville",
    "sg:classifiers":[
        {
            "category":"Organizations",
            "subcategory":"Religious Organization",
            "type":"Services"
        }
    ],
    "sg:phone":"+1 706 857 6943",
    "sg:postcode":"30747",
    "sg:province":"GA",
    "sg:tags":[
        "church"
    ],
    "wof:name":"Spirit & Truth Assembly-Jesus",
    "wof:placetype":"venue"
},
  "geometry": {"coordinates":[-85.346543,34.4809],"type":"Point"}
}