{
  "type": "Feature",
  "properties": {
    "iso:country":"US",
    "sg:address":"1890 Forge St",
    "sg:city":"Tucker",
    "sg:classifiers":[
        {
            "category":"Freight",
            "type":"Transportation"
        }
    ],
    "sg:phone":"+1 770 908 2962",
    "sg:postcode":"30084",
    "sg:province":"GA",
    "sg:tags":[
        "operator",
        "storage",
        "trucking",
        "commercial",
        "local"
    ],
    "wof:name":"Corporate Relocation Specialis",
    "wof:placetype":"venue"
},
  "geometry": {"coordinates":[-84.19873800000001,33.840376],"type":"Point"}
}