{
  "type": "Feature",
  "properties": {
    "iso:country":"US",
    "sg:address":"1204 Scandrett Overlook NW",
    "sg:city":"Kennesaw",
    "sg:classifiers":[
        {
            "category":"Home & Garden",
            "subcategory":"Furniture",
            "type":"Retail Goods"
        }
    ],
    "sg:phone":"+1 770 590 1215",
    "sg:postcode":"30152",
    "sg:province":"GA",
    "wof:name":"D S Fine Furnishings",
    "wof:placetype":"venue"
},
  "geometry": {"coordinates":[-84.689151,33.984399],"type":"Point"}
}