{
  "type": "Feature",
  "properties": {
    "iso:country":"US",
    "sg:address":"127 Echota Cir",
    "sg:city":"Rome",
    "sg:classifiers":[
        {
            "category":"Building & Trades",
            "subcategory":"Electrical",
            "type":"Services"
        }
    ],
    "sg:phone":"+1 706 234 8934",
    "sg:postcode":"30165",
    "sg:province":"GA",
    "sg:tags":[
        "electric",
        "contractor"
    ],
    "wof:name":"Gene Wallace Electric Co",
    "wof:placetype":"venue"
},
  "geometry": {"coordinates":[-85.227576,34.265294],"type":"Point"}
}