{
  "type": "Feature",
  "properties": {
    "iso:country":"US",
    "sg:address":"1420 Radium Springs Rd",
    "sg:city":"Albany",
    "sg:classifiers":[
        {
            "category":"Real Estate",
            "subcategory":"Real Estate Operator",
            "type":"Services"
        }
    ],
    "sg:phone":"+1 229 435 3281",
    "sg:postcode":"31705",
    "sg:province":"GA",
    "sg:tags":[
        "building",
        "nonresidential"
    ],
    "wof:name":"Millinnium Mall Inc",
    "wof:placetype":"venue"
},
  "geometry": {"coordinates":[-84.13709299999999,31.552481],"type":"Point"}
}