{
  "type": "Feature",
  "properties": {
    "addr:full":"4260 Chamblee Rd Oakwood GA 30566",
    "addr:housenumber":"4260",
    "addr:postcode":"30566",
    "addr:street":"Chamblee Rd",
    "iso:country":"US",
    "sg:address":"4260 Chamblee Rd",
    "sg:city":"Oakwood",
    "sg:classifiers":[
        {
            "category":"Building & Trades",
            "subcategory":"Landscaping Services",
            "type":"Services"
        }
    ],
    "sg:phone":"+1 770 535 1585",
    "sg:postcode":"30566",
    "sg:province":"GA",
    "wof:name":"Premier Scapes",
    "wof:placetype":"venue"
},
  "geometry": {"coordinates":[-83.904916,34.223852],"type":"Point"}
}