{
  "type": "Feature",
  "properties": {
    "iso:country":"US",
    "sg:address":"208 Griffin Ave",
    "sg:city":"Valdosta",
    "sg:classifiers":[
        {
            "category":"Restaurant",
            "type":"Food & Drink"
        }
    ],
    "sg:phone":"+1 229 241 0122",
    "sg:postcode":"31601",
    "sg:province":"GA",
    "sg:tags":[
        "barbecue"
    ],
    "wof:name":"Leroy's BBQ",
    "wof:placetype":"venue"
},
  "geometry": {"coordinates":[-83.271264,30.820166],"type":"Point"}
}