{
  "type": "Feature",
  "properties": {
    "addr:full":"505 Cherokee Mills Dr Woodstock GA 30189",
    "addr:housenumber":"505",
    "addr:postcode":"30189",
    "addr:street":"Cherokee Mills Dr",
    "iso:country":"US",
    "sg:address":"505 Cherokee Mills Dr",
    "sg:city":"Woodstock",
    "sg:classifiers":[
        {
            "category":"Professional",
            "subcategory":"Business Services",
            "type":"Services"
        }
    ],
    "sg:phone":"+1 770 928 1979",
    "sg:postcode":"30189",
    "sg:province":"GA",
    "wof:name":"Fairfax Assoc",
    "wof:placetype":"venue"
},
  "geometry": {"coordinates":[-84.589933,34.158184],"type":"Point"}
}