{
  "type": "Feature",
  "properties": {
    "iso:country":"US",
    "sg:address":"2337 Pinetree Rd",
    "sg:city":"Savannah",
    "sg:classifiers":[
        {
            "category":"Manufacturing",
            "subcategory":"Printing",
            "type":"Manufacturing & Wholesale Goods"
        }
    ],
    "sg:phone":"+1 912 356 9412",
    "sg:postcode":"31404",
    "sg:province":"GA",
    "sg:tags":[
        "book"
    ],
    "wof:name":"Dillard Ink",
    "wof:placetype":"venue"
},
  "geometry": {"coordinates":[-81.073305,32.027559],"type":"Point"}
}