{
  "type": "Feature",
  "properties": {
    "addr:full":"3699 Ives Ct NW Kennesaw GA 30152",
    "addr:housenumber":"3699",
    "addr:postcode":"30152",
    "addr:street":"Ives Ct Nw",
    "iso:country":"US",
    "sg:address":"3699 Ives Ct NW",
    "sg:city":"Kennesaw",
    "sg:classifiers":[
        {
            "category":"Building & Trades",
            "subcategory":"Construction",
            "type":"Services"
        }
    ],
    "sg:phone":"+1 770 917 0757",
    "sg:postcode":"30152",
    "sg:province":"GA",
    "sg:tags":[
        "hanging",
        "contractor"
    ],
    "wof:name":"Painting By Charles",
    "wof:placetype":"venue"
},
  "geometry": {"coordinates":[-84.658936,34.018805],"type":"Point"}
}