{
  "type": "Feature",
  "properties": {
    "addr:full":"562 Farmers Market Rd Cordele GA 31015",
    "addr:housenumber":"562",
    "addr:postcode":"31015",
    "addr:street":"Farmers Market Rd",
    "iso:country":"US",
    "sg:address":"562 Farmers Market Rd",
    "sg:city":"Cordele",
    "sg:classifiers":[
        {
            "category":"Transit Center",
            "subcategory":"Freight",
            "type":"Transportation"
        },
        {
            "category":"Freight",
            "type":"Transportation"
        }
    ],
    "sg:phone":"+1 229 386 9920",
    "sg:postcode":"31015",
    "sg:province":"GA",
    "sg:tags":[
        "trucking-motor",
        "trucking"
    ],
    "wof:name":"R&L Carriers",
    "wof:placetype":"venue"
},
  "geometry": {"coordinates":[-83.761765,32.004123],"type":"Point"}
}