{
  "type": "Feature",
  "properties": {
    "addr:full":"5758 Harbor Dr NE Buford GA 30518",
    "addr:housenumber":"5758",
    "addr:postcode":"30518",
    "addr:street":"Harbor Dr Ne",
    "iso:country":"US",
    "sg:address":"5758 Harbor Dr NE",
    "sg:city":"Buford",
    "sg:classifiers":[
        {
            "category":"Real Estate",
            "subcategory":"Architect",
            "type":"Services"
        }
    ],
    "sg:phone":"+1 770 232 8650",
    "sg:postcode":"30518",
    "sg:province":"GA",
    "sg:tags":[
        "architectural"
    ],
    "wof:name":"Magister Operis",
    "wof:placetype":"venue"
},
  "geometry": {"coordinates":[-84.025732,34.137986],"type":"Point"}
}