{
  "type": "Feature",
  "properties": {
    "iso:country":"US",
    "sg:address":"678 Simpson St NW",
    "sg:city":"Atlanta",
    "sg:classifiers":[
        {
            "category":"Retail",
            "subcategory":"Auto Repair",
            "type":"Services"
        }
    ],
    "sg:phone":"+1 404 892 8860",
    "sg:postcode":"30314",
    "sg:province":"GA",
    "sg:tags":[
        "body",
        "automobile",
        "painting"
    ],
    "wof:name":"Gordon's Body Shop Inc",
    "wof:placetype":"venue"
},
  "geometry": {"coordinates":[-84.40922500000001,33.763358],"type":"Point"}
}