{
  "type": "Feature",
  "properties": {
    "addr:full":"2 Hobson Ct Columbus GA 31907",
    "addr:housenumber":"2",
    "addr:postcode":"31907",
    "addr:street":"Hobson Ct",
    "iso:country":"US",
    "sg:address":"2 Hobson Ct",
    "sg:city":"Columbus",
    "sg:classifiers":[
        {
            "category":"Real Estate",
            "subcategory":"Architect",
            "type":"Services"
        }
    ],
    "sg:phone":"+1 706 561 4087",
    "sg:postcode":"31907",
    "sg:province":"GA",
    "sg:tags":[
        "management",
        "architectural"
    ],
    "wof:name":"Ron Stotser",
    "wof:placetype":"venue"
},
  "geometry": {"coordinates":[-84.904196,32.507492],"type":"Point"}
}