{
  "type": "Feature",
  "properties": {
    "iso:country":"US",
    "sg:address":"1300 Carriage Pl",
    "sg:city":"Statesboro",
    "sg:classifiers":[
        {
            "category":"Manufacturing",
            "subcategory":"Food",
            "type":"Manufacturing & Wholesale Goods"
        },
        {
            "category":"Farming",
            "subcategory":"Farm",
            "type":"Manufacturing & Wholesale Goods"
        }
    ],
    "sg:phone":"+1 912 852 3242",
    "sg:postcode":"30458",
    "sg:province":"GA",
    "sg:tags":[
        "corn",
        "product"
    ],
    "wof:name":"Emory D Newton",
    "wof:placetype":"venue"
},
  "geometry": {"coordinates":[-81.83662,32.359503],"type":"Point"}
}