{
  "type": "Feature",
  "properties": {
    "iso:country":"US",
    "sg:address":"202 Pomona Rd",
    "sg:city":"Griffin",
    "sg:classifiers":[
        {
            "category":"Professional",
            "type":"Services"
        }
    ],
    "sg:phone":"+1 770 227 9291",
    "sg:postcode":"30223",
    "sg:province":"GA",
    "wof:name":"Justin Tyner Corporation",
    "wof:placetype":"venue"
},
  "geometry": {"coordinates":[-84.275648,33.329339],"type":"Point"}
}