{
  "type": "Feature",
  "properties": {
    "iso:country":"US",
    "sg:address":"718 Ponce De Leon Ave",
    "sg:city":"Atlanta",
    "sg:classifiers":[
        {
            "category":"Fast Food",
            "type":"Food & Drink"
        },
        {
            "category":"Restaurant",
            "type":"Food & Drink"
        }
    ],
    "sg:phone":"+1 404 685 3531",
    "sg:postcode":"30306",
    "sg:province":"GA",
    "sg:tags":[
        "mexican"
    ],
    "sg:website":"www.chipotle.com",
    "wof:name":"Chipotle",
    "wof:placetype":"venue"
},
  "geometry": {"coordinates":[-84.36362,33.773868],"type":"Point"}
}