{
  "type": "Feature",
  "properties": {
    "addr:full":"3577 Chamblee Tucker Rd Atlanta GA 30341",
    "addr:housenumber":"3577",
    "addr:postcode":"30341",
    "addr:street":"Chamblee Tucker Rd",
    "iso:country":"US",
    "sg:address":"3577 Chamblee Tucker Rd",
    "sg:city":"Atlanta",
    "sg:classifiers":[
        {
            "category":"Restaurant",
            "type":"Food & Drink"
        }
    ],
    "sg:phone":"+1 770 216 9338",
    "sg:postcode":"30341",
    "sg:province":"GA",
    "sg:tags":[
        "chinese"
    ],
    "wof:name":"China Star",
    "wof:placetype":"venue"
},
  "geometry": {"coordinates":[-84.246399,33.884899],"type":"Point"}
}