{
  "type": "Feature",
  "properties": {
    "addr:full":"1937 Mc Jenkins Dr NE Atlanta GA 30345",
    "addr:housenumber":"1937",
    "addr:postcode":"30345",
    "addr:street":"Mc Jenkins Dr Ne",
    "iso:country":"US",
    "sg:address":"1937 Mc Jenkins Dr NE",
    "sg:city":"Atlanta",
    "sg:classifiers":[
        {
            "category":"Professional",
            "subcategory":"Business Services",
            "type":"Services"
        }
    ],
    "sg:phone":"+1 404 636 0567",
    "sg:postcode":"30345",
    "sg:province":"GA",
    "wof:name":"Richardson Design Inc",
    "wof:placetype":"venue"
},
  "geometry": {"coordinates":[-84.31335,33.850263],"type":"Point"}
}