{
  "type": "Feature",
  "properties": {
    "addr:full":"9 Dunwoody Park Suite 116 Atlanta GA 30338",
    "addr:housenumber":"9",
    "addr:postcode":"30338",
    "addr:street":"Dunwoody Park Suite 116",
    "iso:country":"US",
    "sg:address":"9 Dunwoody Park Suite 116",
    "sg:city":"Atlanta",
    "sg:classifiers":[
        {
            "category":"Autos & Motor Vehicles",
            "subcategory":"Fuel & Gas Station",
            "type":"Retail Goods"
        }
    ],
    "sg:phone":"+1 770 698 9908",
    "sg:postcode":"30338",
    "sg:province":"GA",
    "wof:name":"Cardsouth Solutions",
    "wof:placetype":"venue"
},
  "geometry": {"coordinates":[-84.31395500000001,33.924307],"type":"Point"}
}