{
  "type": "Feature",
  "properties": {
    "addr:full":"3539 Lenox Rd NE Atlanta GA 30326",
    "addr:housenumber":"3539",
    "addr:postcode":"30326",
    "addr:street":"Lenox Rd Ne",
    "iso:country":"US",
    "sg:address":"3539 Lenox Rd NE",
    "sg:city":"Atlanta",
    "sg:classifiers":[
        {
            "category":"Building & Trades",
            "subcategory":"Locksmith",
            "type":"Services"
        }
    ],
    "sg:phone":"+1 678 865 8103",
    "sg:postcode":"30326",
    "sg:province":"GA",
    "sg:tags":[
        "key"
    ],
    "wof:name":"A Always Available Speedy A Locksmith",
    "wof:placetype":"venue"
},
  "geometry": {"coordinates":[-84.36429800000001,33.852581],"type":"Point"}
}