{
  "type": "Feature",
  "properties": {
    "iso:country":"US",
    "sg:address":"4555 Moon Valley Ln",
    "sg:city":"Lithonia",
    "sg:classifiers":[
        {
            "category":"Professional",
            "subcategory":"Management & Consulting",
            "type":"Services"
        }
    ],
    "sg:phone":"+1 770 323 6910",
    "sg:postcode":"30038",
    "sg:province":"GA",
    "sg:tags":[
        "training"
    ],
    "wof:name":"Professionalism Matters Inc",
    "wof:placetype":"venue"
},
  "geometry": {"coordinates":[-84.202257,33.669931],"type":"Point"}
}