{
  "type": "Feature",
  "properties": {
    "addr:full":"138 Brighton Rd NE Atlanta GA 30309",
    "addr:housenumber":"138",
    "addr:postcode":"30309",
    "addr:street":"Brighton Rd Ne",
    "iso:country":"US",
    "sg:address":"138 Brighton Rd NE",
    "sg:city":"Atlanta",
    "sg:classifiers":[
        {
            "category":"Professional",
            "subcategory":"Business Services",
            "type":"Services"
        }
    ],
    "sg:phone":"+1 404 352 9582",
    "sg:postcode":"30309",
    "sg:province":"GA",
    "wof:name":"Esm Interiors Inc",
    "wof:placetype":"venue"
},
  "geometry": {"coordinates":[-84.38503799999999,33.810758],"type":"Point"}
}