{
  "type": "Feature",
  "properties": {
    "addr:full":"606 Gaskin Ave S Douglas GA 31533",
    "addr:housenumber":"606",
    "addr:postcode":"31533",
    "addr:street":"Gaskin Ave S",
    "iso:country":"US",
    "sg:address":"606 Gaskin Ave S",
    "sg:city":"Douglas",
    "sg:classifiers":[
        {
            "category":"Food & Beverages",
            "subcategory":"Fruits & Vegetables",
            "type":"Retail Goods"
        }
    ],
    "sg:phone":"+1 912 384 9046",
    "sg:postcode":"31533",
    "sg:province":"GA",
    "sg:tags":[
        "produce"
    ],
    "wof:name":"Farmer's Curb Market",
    "wof:placetype":"venue"
},
  "geometry": {"coordinates":[-82.84530700000001,31.503263],"type":"Point"}
}