{
  "type": "Feature",
  "properties": {
    "iso:country":"US",
    "sg:address":"233 Apple Branch Dr",
    "sg:city":"Woodstock",
    "sg:classifiers":[
        {
            "category":"Retail",
            "subcategory":"Repair Shop",
            "type":"Services"
        },
        {
            "category":"Manufacturing",
            "subcategory":"Signs",
            "type":"Manufacturing & Wholesale Goods"
        }
    ],
    "sg:phone":"+1 770 516 3693",
    "sg:postcode":"30188",
    "sg:province":"GA",
    "sg:tags":[
        "signs-erectors",
        "hanger",
        "signs-maintenance"
    ],
    "wof:name":"Peach State Signs",
    "wof:placetype":"venue"
},
  "geometry": {"coordinates":[-84.467957,34.095861],"type":"Point"}
}