{
  "type": "Feature",
  "properties": {
    "iso:country":"US",
    "sg:address":"136 Walker St SW",
    "sg:city":"Atlanta",
    "sg:classifiers":[
        {
            "category":"Shopping",
            "subcategory":"Bicycles & Sporting Goods",
            "type":"Retail Goods"
        }
    ],
    "sg:phone":"+1 404 521 9054",
    "sg:postcode":"30313",
    "sg:province":"GA",
    "sg:tags":[
        "equipment",
        "playground"
    ],
    "wof:name":"Quadrozone",
    "wof:placetype":"venue"
},
  "geometry": {"coordinates":[-84.400651,33.75045],"type":"Point"}
}