{
  "type": "Feature",
  "properties": {
    "iso:country":"US",
    "sg:address":"2244 Henderson Mill Rd NE",
    "sg:city":"Atlanta",
    "sg:classifiers":[
        {
            "category":"Banks & Credit Unions",
            "subcategory":"Bank",
            "type":"Services"
        }
    ],
    "sg:phone":"+1 770 939 1904",
    "sg:postcode":"30345",
    "sg:province":"GA",
    "sg:tags":[
        "broker",
        "mortgage"
    ],
    "wof:name":"Legendary Lending Inc",
    "wof:placetype":"venue"
},
  "geometry": {"coordinates":[-84.257419,33.849303],"type":"Point"}
}