{
  "type": "Feature",
  "properties": {
    "iso:country":"US",
    "sg:address":"2359 Windy Hill Rd SE",
    "sg:city":"Marietta",
    "sg:classifiers":[
        {
            "category":"Home & Garden",
            "subcategory":"Furniture",
            "type":"Retail Goods"
        }
    ],
    "sg:phone":"+1 770 729 9995",
    "sg:postcode":"30067",
    "sg:province":"GA",
    "wof:name":"La-Z-Boy Furniture Galleries",
    "wof:placetype":"venue"
},
  "geometry": {"coordinates":[-84.48448999999999,33.903535],"type":"Point"}
}