{
  "type": "Feature",
  "properties": {
    "addr:full":"221 N Broad St Winder GA 30680",
    "addr:housenumber":"221",
    "addr:postcode":"30680",
    "addr:street":"N Broad St",
    "iso:country":"US",
    "sg:address":"221 N Broad St",
    "sg:city":"Winder",
    "sg:classifiers":[
        {
            "category":"Restaurant",
            "type":"Food & Drink"
        }
    ],
    "sg:phone":"+1 770 307 4661",
    "sg:postcode":"30680",
    "sg:province":"GA",
    "wof:name":"Formosa Chinese Restaurant",
    "wof:placetype":"venue"
},
  "geometry": {"coordinates":[-83.71390599999999,33.99659],"type":"Point"}
}