{
  "type": "Feature",
  "properties": {
    "addr:full":"1790 Whitley Rd Dacula GA 30019",
    "addr:housenumber":"1790",
    "addr:postcode":"ga 30019",
    "addr:street":"Whitley Rd",
    "iso:country":"US",
    "sg:address":"1790 Whitley Rd",
    "sg:city":"Dacula",
    "sg:classifiers":[
        {
            "category":"Professional",
            "subcategory":"Engineering",
            "type":"Services"
        }
    ],
    "sg:phone":"+1 770 513 0352",
    "sg:postcode":"30019",
    "sg:province":"GA",
    "wof:name":"Regal Oak Corp",
    "wof:placetype":"venue"
},
  "geometry": {"coordinates":[-83.83382400000001,33.963088],"type":"Point"}
}