{
  "type": "Feature",
  "properties": {
    "iso:country":"US",
    "sg:address":"111 10th St",
    "sg:city":"Augusta",
    "sg:classifiers":[
        {
            "category":"Professional",
            "type":"Services"
        }
    ],
    "sg:phone":"+1 706 722 8000",
    "sg:postcode":"30901",
    "sg:province":"GA",
    "sg:tags":[
        "establishment"
    ],
    "wof:name":"Downtown Development Authority",
    "wof:placetype":"venue"
},
  "geometry": {"coordinates":[-81.969212,33.477804],"type":"Point"}
}