{
  "type": "Feature",
  "properties": {
    "addr:full":"4178 Abbotts Bridge Rd Duluth GA 30097",
    "addr:housenumber":"4178",
    "addr:postcode":"30097",
    "addr:street":"Abbotts Bridge Rd",
    "iso:country":"US",
    "sg:address":"4178 Abbotts Bridge Rd",
    "sg:city":"Duluth",
    "sg:phone":"+1 770 623 3976",
    "sg:postcode":"30097",
    "sg:province":"GA",
    "wof:name":"Wolfgang's Auto Repair & Sales",
    "wof:placetype":"venue"
},
  "geometry": {"coordinates":[-84.15763099999999,34.018791],"type":"Point"}
}