{
  "type": "Feature",
  "properties": {
    "iso:country":"US",
    "sg:address":"210 N Jefferson St",
    "sg:city":"Dublin",
    "sg:classifiers":[
        {
            "category":"Autos & Motor Vehicles",
            "subcategory":"Automobile Sales",
            "type":"Retail Goods"
        },
        {
            "category":"Autos & Motor Vehicles",
            "subcategory":"Auto Supplies",
            "type":"Retail Goods"
        },
        {
            "category":"Retail",
            "subcategory":"Auto Repair",
            "type":"Services"
        }
    ],
    "sg:phone":"+1 478 272 3244",
    "sg:postcode":"31021",
    "sg:province":"GA",
    "sg:tags":[
        "used",
        "tire",
        "car",
        "lube",
        "oil",
        "truck",
        "new"
    ],
    "sg:website":"http://www.pittstoyota.com",
    "wof:name":"Pitts Toyota Scion",
    "wof:placetype":"venue"
},
  "geometry": {"coordinates":[-82.92153500000001,32.566765],"type":"Point"}
}