{
  "type": "Feature",
  "properties": {
    "addr:full":"545 Watergate Ct Roswell GA 30076",
    "addr:housenumber":"545",
    "addr:postcode":"30076",
    "addr:street":"Watergate Ct",
    "iso:country":"US",
    "sg:address":"545 Watergate Ct",
    "sg:city":"Roswell",
    "sg:classifiers":[
        {
            "category":"Real Estate",
            "subcategory":"Real Estate Agent",
            "type":"Services"
        }
    ],
    "sg:phone":"+1 770 331 7708",
    "sg:postcode":"30076",
    "sg:province":"GA",
    "wof:name":"Property Concepts LLC",
    "wof:placetype":"venue"
},
  "geometry": {"coordinates":[-84.31926799999999,33.996221],"type":"Point"}
}