{
  "type": "Feature",
  "properties": {
    "addr:full":"218 S Troup St Adel GA 31601",
    "addr:housenumber":"218",
    "addr:postcode":"31601",
    "addr:street":"S Troup St",
    "iso:country":"US",
    "sg:address":"218 S Troup St",
    "sg:city":"Adel",
    "sg:classifiers":[
        {
            "category":"Freight",
            "type":"Transportation"
        }
    ],
    "sg:phone":"+1 229 896 7012",
    "sg:postcode":"31601",
    "sg:province":"GA",
    "sg:tags":[
        "trucking"
    ],
    "wof:name":"Dav Cor Transport",
    "wof:placetype":"venue"
},
  "geometry": {"coordinates":[-83.27404,30.830633],"type":"Point"}
}