{
  "type": "Feature",
  "properties": {
    "iso:country":"US",
    "sg:address":"264 Keys Ferry Rd",
    "sg:city":"Mcdonough",
    "sg:classifiers":[
        {
            "category":"Shopping",
            "subcategory":"Clothing, Apparel, & Fashions",
            "type":"Retail Goods"
        }
    ],
    "sg:phone":"+1 770 898 3612",
    "sg:postcode":"30252",
    "sg:province":"GA",
    "wof:name":"Hannah Banana's",
    "wof:placetype":"venue"
},
  "geometry": {"coordinates":[-84.030951,33.433945],"type":"Point"}
}