{
  "type": "Feature",
  "properties": {
    "iso:country":"US",
    "sg:address":"539 Olympic Dr",
    "sg:city":"Athens",
    "sg:classifiers":[
        {
            "category":"Real Estate",
            "subcategory":"Real Estate Agent",
            "type":"Services"
        }
    ],
    "sg:phone":"+1 706 546 6666",
    "sg:postcode":"30601",
    "sg:province":"GA",
    "wof:name":"Mitchell Company The",
    "wof:placetype":"venue"
},
  "geometry": {"coordinates":[-83.34647099999999,33.965708],"type":"Point"}
}