{
  "type": "Feature",
  "properties": {
    "iso:country":"US",
    "sg:address":"4920 Roswell Road NE Suite 14",
    "sg:city":"Atlanta",
    "sg:classifiers":[
        {
            "category":"Restaurant",
            "type":"Food & Drink"
        }
    ],
    "sg:phone":"+1 404 303 7303",
    "sg:postcode":"30342",
    "sg:province":"GA",
    "wof:name":"Cafe Posh",
    "wof:placetype":"venue"
},
  "geometry": {"coordinates":[-84.381514,33.888815],"type":"Point"}
}