{
  "type": "Feature",
  "properties": {
    "addr:full":"3340 Peachtree Rd Atlanta GA 30326",
    "addr:housenumber":"3340",
    "addr:postcode":"30326",
    "addr:street":"Peachtree Rd",
    "iso:country":"US",
    "sg:address":"3340 Peachtree Rd",
    "sg:city":"Atlanta",
    "sg:classifiers":[
        {
            "category":"Professional",
            "subcategory":"Management & Consulting",
            "type":"Services"
        },
        {
            "category":"Professional",
            "subcategory":"Employment Agencies",
            "type":"Services"
        }
    ],
    "sg:phone":"+1 404 814 5282",
    "sg:postcode":"30326",
    "sg:province":"GA",
    "sg:tags":[
        "temporary",
        "personnel",
        "permanent",
        "consultant",
        "spec",
        "staffing"
    ],
    "wof:name":"Career Connection Inc",
    "wof:placetype":"venue"
},
  "geometry": {"coordinates":[-84.367447,33.84774],"type":"Point"}
}