{
  "type": "Feature",
  "properties": {
    "addr:full":"1000 Lake Regency Dr Atlanta GA 30349",
    "addr:housenumber":"1000",
    "addr:postcode":"30349",
    "addr:street":"Lake Regency Dr",
    "iso:country":"US",
    "sg:address":"1000 Lake Regency Dr",
    "sg:city":"Atlanta",
    "sg:classifiers":[
        {
            "category":"Professional",
            "subcategory":"Printing & Photocopies",
            "type":"Services"
        }
    ],
    "sg:phone":"+1 770 997 1690",
    "sg:postcode":"30349",
    "sg:province":"GA",
    "sg:tags":[
        "lithographer"
    ],
    "wof:name":"Gbc Quick Quality Printing",
    "wof:placetype":"venue"
},
  "geometry": {"coordinates":[-84.425428,33.598621],"type":"Point"}
}