{
  "type": "Feature",
  "properties": {
    "iso:country":"US",
    "sg:address":"107 Augusta Rd",
    "sg:city":"North Augusta",
    "sg:classifiers":[
        {
            "category":"Autos & Motor Vehicles",
            "subcategory":"Fuel & Gas Station",
            "type":"Retail Goods"
        }
    ],
    "sg:phone":"+1 803 278 2764",
    "sg:postcode":"29822",
    "sg:province":"SC",
    "sg:tags":[
        "station",
        "gasoline"
    ],
    "wof:name":"Circle K Store",
    "wof:placetype":"venue"
},
  "geometry": {"coordinates":[-81.89210300000001,33.496677],"type":"Point"}
}