{
  "type": "Feature",
  "properties": {
    "addr:full":"536 Heard Rd Pavo GA 31778",
    "addr:housenumber":"536",
    "addr:postcode":"31778",
    "addr:street":"Heard Rd",
    "iso:country":"US",
    "sg:address":"536 Heard Rd",
    "sg:city":"Pavo",
    "sg:classifiers":[
        {
            "category":"Manufacturing",
            "subcategory":"Lumber",
            "type":"Manufacturing & Wholesale Goods"
        }
    ],
    "sg:phone":"+1 229 985 0978",
    "sg:postcode":"31778",
    "sg:province":"GA",
    "sg:tags":[
        "logging"
    ],
    "wof:name":"Drag On Logging Transport",
    "wof:placetype":"venue"
},
  "geometry": {"coordinates":[-83.746375,31.041123],"type":"Point"}
}