{
  "type": "Feature",
  "properties": {
    "addr:full":"2957 N Druid Hills Road NE Atlanta GA 30329",
    "addr:housenumber":"2957",
    "addr:postcode":"30329",
    "addr:street":"N Druid Hills Road Ne",
    "iso:country":"US",
    "sg:address":"2957 N Druid Hills Road NE",
    "sg:city":"Atlanta",
    "sg:classifiers":[
        {
            "category":"Fast Food",
            "type":"Food & Drink"
        }
    ],
    "sg:phone":"+1 404 329 9385",
    "sg:postcode":"30329",
    "sg:province":"GA",
    "sg:website":"www.wendys.com",
    "wof:name":"Wendy's",
    "wof:placetype":"venue"
},
  "geometry": {"coordinates":[-84.309622,33.814967],"type":"Point"}
}