{
  "type": "Feature",
  "properties": {
    "iso:country":"US",
    "sg:address":"3400 Town Point Pkwy NW",
    "sg:city":"Kennesaw",
    "sg:classifiers":[
        {
            "category":"Building & Trades",
            "subcategory":"Construction",
            "type":"Services"
        }
    ],
    "sg:phone":"+1 770 433 3323",
    "sg:postcode":"30144",
    "sg:province":"GA",
    "sg:tags":[
        "material",
        "contractor"
    ],
    "wof:name":"American Exclusives",
    "wof:placetype":"venue"
},
  "geometry": {"coordinates":[-84.57957399999999,34.02852],"type":"Point"}
}