{
  "type": "Feature",
  "properties": {
    "addr:full":"1900 Tap Dr Vidalia GA 30474",
    "addr:postcode":"1900;30474",
    "addr:street":"Tap Dr Vidalia",
    "iso:country":"US",
    "sg:address":"1900 Tap Dr",
    "sg:city":"Vidalia",
    "sg:classifiers":[
        {
            "category":"Professional",
            "subcategory":"Secretarial Services",
            "type":"Services"
        }
    ],
    "sg:phone":"+1 912 537 4907",
    "sg:postcode":"30474",
    "sg:province":"GA",
    "sg:tags":[
        "hearing",
        "reporter"
    ],
    "wof:name":"Joann S Perry",
    "wof:placetype":"venue"
},
  "geometry": {"coordinates":[-82.44077900000001,32.232689],"type":"Point"}
}