{
  "type": "Feature",
  "properties": {
    "addr:full":"217 Oxford Dr Savannah GA 31405",
    "addr:housenumber":"217",
    "addr:postcode":"31405",
    "addr:street":"Oxford Dr",
    "iso:country":"US",
    "sg:address":"217 Oxford Dr",
    "sg:city":"Savannah",
    "sg:classifiers":[
        {
            "category":"Professional",
            "subcategory":"Management & Consulting",
            "type":"Services"
        }
    ],
    "sg:phone":"+1 912 354 1395",
    "sg:postcode":"31405",
    "sg:province":"GA",
    "sg:tags":[
        "business"
    ],
    "wof:name":"Earthware Inc",
    "wof:placetype":"venue"
},
  "geometry": {"coordinates":[-81.103351,32.025141],"type":"Point"}
}