{
  "type": "Feature",
  "properties": {
    "addr:full":"1350 Paces Forest Dr NW Atlanta GA 30327",
    "addr:housenumber":"1350",
    "addr:postcode":"30327",
    "addr:street":"Paces Forest Dr Nw",
    "iso:country":"US",
    "sg:address":"1350 Paces Forest Dr NW",
    "sg:city":"Atlanta",
    "sg:classifiers":[
        {
            "category":"Communications",
            "subcategory":"Radio Station",
            "type":"Services"
        }
    ],
    "sg:phone":"+1 404 262 1756",
    "sg:postcode":"30327",
    "sg:province":"GA",
    "wof:name":"Big Wolf",
    "wof:placetype":"venue"
},
  "geometry": {"coordinates":[-84.424404,33.847068],"type":"Point"}
}