{
  "type": "Feature",
  "properties": {
    "iso:country":"US",
    "sg:address":"3822 Stephanie Dr SW",
    "sg:city":"Atlanta",
    "sg:classifiers":[
        {
            "category":"Professional",
            "subcategory":"Business Services",
            "type":"Services"
        }
    ],
    "sg:phone":"+1 404 344 1733",
    "sg:postcode":"30331",
    "sg:province":"GA",
    "wof:name":"Private Secretary MGT Svcs",
    "wof:placetype":"venue"
},
  "geometry": {"coordinates":[-84.51040399999999,33.6737],"type":"Point"}
}