{
  "type": "Feature",
  "properties": {
    "iso:country":"US",
    "sg:address":"226 E Jackson St",
    "sg:city":"Thomasville",
    "sg:classifiers":[
        {
            "category":"Insurance",
            "subcategory":"Insurance Agent",
            "type":"Services"
        }
    ],
    "sg:phone":"+1 229 228 4567",
    "sg:postcode":"31792",
    "sg:province":"GA",
    "wof:name":"Waddell & Reed Inc",
    "wof:placetype":"venue"
},
  "geometry": {"coordinates":[-83.977897,30.839034],"type":"Point"}
}