{
  "type": "Feature",
  "properties": {
    "iso:country":"US",
    "sg:address":"44 Darbys Crossing Dr Ste 116",
    "sg:city":"Hiram",
    "sg:classifiers":[
        {
            "category":"Real Estate",
            "subcategory":"Real Estate Services",
            "type":"Services"
        },
        {
            "category":"Building & Trades",
            "subcategory":"Cleaning & Sanitation",
            "type":"Services"
        }
    ],
    "sg:phone":"+1 888 385 9234",
    "sg:postcode":"30141",
    "sg:province":"GA",
    "sg:tags":[
        "janitorial",
        "maintenance"
    ],
    "sg:website":"http://atlanta.citysearch.com/profile/external/45560397/hiram_ga/cleanstar_national_incorporated.html?publisher=yellowpages&reference_id=7&placement=ypwebsitemip",
    "wof:name":"Cleanstar National Incorporated",
    "wof:placetype":"venue"
},
  "geometry": {"coordinates":[-84.748926,33.90433],"type":"Point"}
}