{
  "type": "Feature",
  "properties": {
    "iso:country":"US",
    "sg:address":"974 Atlanta Hwy SE",
    "sg:city":"Winder",
    "sg:classifiers":[
        {
            "category":"Manufacturing",
            "subcategory":"Retail Goods",
            "type":"Manufacturing & Wholesale Goods"
        }
    ],
    "sg:phone":"+1 770 307 1519",
    "sg:postcode":"30680",
    "sg:province":"GA",
    "sg:tags":[
        "manufacturer"
    ],
    "wof:name":"Metal Construction Components",
    "wof:placetype":"venue"
},
  "geometry": {"coordinates":[-83.656488,33.977315],"type":"Point"}
}