{
  "type": "Feature",
  "properties": {
    "addr:full":"12400 Broadwell Rd Alpharetta GA 30004",
    "addr:housenumber":"12400",
    "addr:postcode":"30004",
    "addr:street":"Broadwell Rd",
    "iso:country":"US",
    "sg:address":"12400 Broadwell Rd",
    "sg:city":"Alpharetta",
    "sg:classifiers":[
        {
            "category":"Professional",
            "type":"Services"
        }
    ],
    "sg:phone":"+1 770 667 7897",
    "sg:postcode":"30004",
    "sg:province":"GA",
    "wof:name":"Greenblade Inc",
    "wof:placetype":"venue"
},
  "geometry": {"coordinates":[-84.33958699999999,34.084763],"type":"Point"}
}