{
  "type": "Feature",
  "properties": {
    "addr:full":"960 Thornton Rd Lithia Springs GA 30122",
    "addr:housenumber":"960",
    "addr:postcode":"30122",
    "addr:street":"Thornton Rd",
    "iso:country":"US",
    "sg:address":"960 Thornton Rd",
    "sg:city":"Lithia Springs",
    "sg:classifiers":[
        {
            "category":"Autos & Motor Vehicles",
            "subcategory":"Fuel & Gas Station",
            "type":"Retail Goods"
        }
    ],
    "sg:phone":"+1 770 732 1410",
    "sg:postcode":"30122",
    "sg:province":"GA",
    "sg:tags":[
        "station",
        "gasoline"
    ],
    "wof:name":"Phillips 27801",
    "wof:placetype":"venue"
},
  "geometry": {"coordinates":[-84.60692400000001,33.779597],"type":"Point"}
}