{
  "type": "Feature",
  "properties": {
    "addr:full":"624 Oak Moss Dr Lawrenceville GA 30043",
    "addr:housenumber":"624",
    "addr:postcode":"30043",
    "addr:street":"Oak Moss Dr",
    "iso:country":"US",
    "sg:address":"624 Oak Moss Dr",
    "sg:city":"Lawrenceville",
    "sg:classifiers":[
        {
            "category":"Retail",
            "subcategory":"Repair Shop",
            "type":"Services"
        }
    ],
    "sg:phone":"+1 404 918 1778",
    "sg:postcode":"30043",
    "sg:province":"GA",
    "sg:tags":[
        "plumbing",
        "drain",
        "cleaning",
        "sewer"
    ],
    "wof:name":"Action Rooter",
    "wof:placetype":"venue"
},
  "geometry": {"coordinates":[-83.99079,34.019052],"type":"Point"}
}