{
  "type": "Feature",
  "properties": {
    "iso:country":"US",
    "sg:address":"2965 Buford Hwy NE",
    "sg:city":"Atlanta",
    "sg:classifiers":[
        {
            "category":"Retail",
            "subcategory":"Veterinary Services",
            "type":"Services"
        },
        {
            "category":"Retail",
            "subcategory":"Pet Boarding",
            "type":"Services"
        }
    ],
    "sg:phone":"+1 770 476 3317",
    "sg:postcode":"30329",
    "sg:province":"GA",
    "sg:tags":[
        "veterinarian",
        "boarding/pet",
        "sitting"
    ],
    "wof:name":"Niagro Beth DVM",
    "wof:placetype":"venue"
},
  "geometry": {"coordinates":[-84.33910400000001,33.834801],"type":"Point"}
}