{
  "type": "Feature",
  "properties": {
    "addr:full":"252 Main St Forest Park GA 30297",
    "addr:housenumber":"252",
    "addr:postcode":"30297",
    "addr:street":"Main St",
    "iso:country":"US",
    "sg:address":"252 Main St",
    "sg:city":"Forest Park",
    "sg:classifiers":[
        {
            "category":"Organizations",
            "subcategory":"Labor Organization",
            "type":"Services"
        }
    ],
    "sg:phone":"+1 404 361 7801",
    "sg:postcode":"30297",
    "sg:province":"GA",
    "wof:name":"Bricklayers & Allied Cft Wkrs",
    "wof:placetype":"venue"
},
  "geometry": {"coordinates":[-84.380669,33.625359],"type":"Point"}
}