{
  "type": "Feature",
  "properties": {
    "iso:country":"US",
    "sg:address":"180 Oak Haven Ave",
    "sg:city":"Macon",
    "sg:classifiers":[
        {
            "category":"Building & Trades",
            "subcategory":"Landscaping Services",
            "type":"Services"
        }
    ],
    "sg:phone":"+1 478 474 5030",
    "sg:postcode":"31204",
    "sg:province":"GA",
    "wof:name":"Gray Brothers Tree Service",
    "wof:placetype":"venue"
},
  "geometry": {"coordinates":[-83.65888,32.845951],"type":"Point"}
}