{
  "type": "Feature",
  "properties": {
    "iso:country":"US",
    "sg:address":"4026 Colonial Dr SW",
    "sg:city":"Lilburn",
    "sg:classifiers":[
        {
            "category":"Manufacturing",
            "subcategory":"Tools & Machinery",
            "type":"Manufacturing & Wholesale Goods"
        },
        {
            "category":"Professional",
            "subcategory":"Computer Services",
            "type":"Services"
        }
    ],
    "sg:phone":"+1 770 717 9779",
    "sg:postcode":"30047",
    "sg:province":"GA",
    "sg:tags":[
        "networking",
        "solution",
        "provider"
    ],
    "wof:name":"Tecpro Solutions Inc",
    "wof:placetype":"venue"
},
  "geometry": {"coordinates":[-84.08558499999999,33.860461],"type":"Point"}
}