{
  "type": "Feature",
  "properties": {
    "addr:full":"2505 Nottingham Dr Savannah GA 31406",
    "addr:housenumber":"2505",
    "addr:postcode":"31406",
    "addr:street":"Nottingham Dr",
    "iso:country":"US",
    "sg:address":"2505 Nottingham Dr",
    "sg:city":"Savannah",
    "sg:classifiers":[
        {
            "category":"Organizations",
            "subcategory":"Non-profit Organization",
            "type":"Services"
        }
    ],
    "sg:phone":"+1 912 660 1082",
    "sg:postcode":"31406",
    "sg:province":"GA",
    "sg:tags":[
        "educational",
        "housing",
        "business",
        "social"
    ],
    "wof:name":"Terry Tolbert",
    "wof:placetype":"venue"
},
  "geometry": {"coordinates":[-81.065527,32.000694],"type":"Point"}
}