{
  "type": "Feature",
  "properties": {
    "addr:full":"70 Piper Rd Covington GA 30014",
    "addr:housenumber":"70",
    "addr:postcode":"30014",
    "addr:street":"Piper Rd",
    "iso:country":"US",
    "sg:address":"70 Piper Rd",
    "sg:city":"Covington",
    "sg:classifiers":[
        {
            "category":"Manufacturing",
            "subcategory":"Tools & Machinery",
            "type":"Manufacturing & Wholesale Goods"
        }
    ],
    "sg:phone":"+1 770 787 1002",
    "sg:postcode":"30014",
    "sg:province":"GA",
    "sg:tags":[
        "die",
        "maker"
    ],
    "wof:name":"Tricon Tool",
    "wof:placetype":"venue"
},
  "geometry": {"coordinates":[-83.84733300000001,33.560378],"type":"Point"}
}