{
  "type": "Feature",
  "properties": {
    "addr:full":"980 Jefferson St NW Atlanta GA 30318",
    "addr:housenumber":"980",
    "addr:postcode":"30318",
    "addr:street":"Jefferson St Nw",
    "iso:country":"US",
    "sg:address":"980 Jefferson St NW",
    "sg:city":"Atlanta",
    "sg:classifiers":[
        {
            "category":"Home & Garden",
            "subcategory":"Building Materials",
            "type":"Retail Goods"
        }
    ],
    "sg:phone":"+1 404 881 9700",
    "sg:postcode":"30318",
    "sg:province":"GA",
    "wof:name":"Capital Materials Inc",
    "wof:placetype":"venue"
},
  "geometry": {"coordinates":[-84.41873,33.775524],"type":"Point"}
}