{
  "type": "Feature",
  "properties": {
    "iso:country":"US",
    "sg:address":"102 3rd Ave",
    "sg:city":"Eastman",
    "sg:classifiers":[
        {
            "category":"Retail",
            "subcategory":"Laundry & Dry Cleaning",
            "type":"Services"
        }
    ],
    "sg:phone":"+1 478 374 3731",
    "sg:postcode":"31023",
    "sg:province":"GA",
    "sg:tags":[
        "drycleaning",
        "plant"
    ],
    "wof:name":"Dixie Cleaners",
    "wof:placetype":"venue"
},
  "geometry": {"coordinates":[-83.17701700000001,32.19636],"type":"Point"}
}