{
  "type": "Feature",
  "properties": {
    "addr:full":"400 Glenn St SW Atlanta GA 30312",
    "addr:housenumber":"400",
    "addr:postcode":"30312",
    "addr:street":"Glenn St Sw",
    "iso:country":"US",
    "sg:address":"400 Glenn St SW",
    "sg:city":"Atlanta",
    "sg:classifiers":[
        {
            "category":"Professional",
            "subcategory":"Computer Services",
            "type":"Services"
        }
    ],
    "sg:phone":"+1 404 873 6740",
    "sg:postcode":"30312",
    "sg:province":"GA",
    "sg:tags":[
        "develops",
        "market",
        "software"
    ],
    "wof:name":"Carreker Corporation",
    "wof:placetype":"venue"
},
  "geometry": {"coordinates":[-84.400999,33.73806],"type":"Point"}
}