{
  "type": "Feature",
  "properties": {
    "iso:country":"US",
    "sg:address":"10 Market Cir",
    "sg:city":"Barnesville",
    "sg:classifiers":[
        {
            "category":"Professional",
            "subcategory":"Employment Agencies",
            "type":"Services"
        }
    ],
    "sg:phone":"+1 770 358 6337",
    "sg:postcode":"30277",
    "sg:province":"GA",
    "wof:name":"Nurses United",
    "wof:placetype":"venue"
},
  "geometry": {"coordinates":[-84.645847,33.399196],"type":"Point"}
}