{
  "type": "Feature",
  "properties": {
    "addr:full":"69 Davis Rd Nevils GA 31321",
    "addr:housenumber":"69",
    "addr:postcode":"31321",
    "addr:street":"Davis Rd",
    "iso:country":"US",
    "sg:address":"69 Davis Rd",
    "sg:city":"Nevils",
    "sg:classifiers":[
        {
            "category":"Building & Trades",
            "subcategory":"Construction",
            "type":"Services"
        }
    ],
    "sg:phone":"+1 912 839 3749",
    "sg:postcode":"31321",
    "sg:province":"GA",
    "sg:tags":[
        "hanging",
        "painter",
        "contractor"
    ],
    "wof:name":"Davis Paint & Repair",
    "wof:placetype":"venue"
},
  "geometry": {"coordinates":[-81.73032600000001,32.263891],"type":"Point"}
}