{
  "type": "Feature",
  "properties": {
    "addr:full":"3090 Goode Rd Conyers GA 30094",
    "addr:housenumber":"3090",
    "addr:postcode":"30094",
    "addr:street":"Goode Rd",
    "iso:country":"US",
    "sg:address":"3090 Goode Rd",
    "sg:city":"Conyers",
    "sg:classifiers":[
        {
            "category":"Retail",
            "subcategory":"Repair Shop",
            "type":"Services"
        }
    ],
    "sg:phone":"+1 770 929 3891",
    "sg:postcode":"30094",
    "sg:province":"GA",
    "sg:tags":[
        "equipment",
        "refrigeration"
    ],
    "wof:name":"A True Service Company Inc",
    "wof:placetype":"venue"
},
  "geometry": {"coordinates":[-84.022786,33.606803],"type":"Point"}
}