{
  "type": "Feature",
  "properties": {
    "addr:full":"3746 Chamblee Tucker Rd Atlanta GA 30341",
    "addr:housenumber":"3746",
    "addr:postcode":"30341",
    "addr:street":"Chamblee Tucker Rd",
    "iso:country":"US",
    "sg:address":"3746 Chamblee Tucker Rd",
    "sg:city":"Atlanta",
    "sg:classifiers":[
        {
            "category":"Real Estate",
            "subcategory":"Real Estate Services",
            "type":"Services"
        }
    ],
    "sg:phone":"+1 770 934 5649",
    "sg:postcode":"30341",
    "sg:province":"GA",
    "wof:name":"Atlanta Real Estate",
    "wof:placetype":"venue"
},
  "geometry": {"coordinates":[-84.239502,33.884602],"type":"Point"}
}