{
  "type": "Feature",
  "properties": {
    "addr:full":"6320 Amherst Ct Norcross GA 30092",
    "addr:housenumber":"6320",
    "addr:postcode":"30092",
    "addr:street":"Amherst Ct",
    "iso:country":"US",
    "sg:address":"6320 Amherst Ct",
    "sg:city":"Norcross",
    "sg:classifiers":[
        {
            "category":"Professional",
            "subcategory":"Testing Lab",
            "type":"Services"
        }
    ],
    "sg:phone":"+1 770 242 6687",
    "sg:postcode":"30092",
    "sg:province":"GA",
    "sg:tags":[
        "consultant",
        "forensic"
    ],
    "sg:website":"www.norcrossgroup.com",
    "wof:name":"Norcross Group",
    "wof:placetype":"venue"
},
  "geometry": {"coordinates":[-84.24473,33.95452],"type":"Point"}
}