{
  "type": "Feature",
  "properties": {
    "iso:country":"US",
    "sg:address":"104 Ellis Rd",
    "sg:city":"Fayetteville",
    "sg:classifiers":[
        {
            "category":"Building & Trades",
            "subcategory":"Construction",
            "type":"Services"
        }
    ],
    "sg:phone":"+1 770 719 0359",
    "sg:postcode":"30214",
    "sg:province":"GA",
    "sg:tags":[
        "contractor"
    ],
    "sg:website":"www.gkcontracting.com",
    "wof:name":"Gk Contracting Inc",
    "wof:placetype":"venue"
},
  "geometry": {"coordinates":[-84.43770499999999,33.469704],"type":"Point"}
}