{
  "type": "Feature",
  "properties": {
    "addr:full":"3562 Cape York Trce Alpharetta GA 30022",
    "addr:housenumber":"3562",
    "addr:postcode":"30022",
    "addr:street":"Cape York Trce",
    "iso:country":"US",
    "sg:address":"3562 Cape York Trce",
    "sg:city":"Alpharetta",
    "sg:classifiers":[
        {
            "category":"Building & Trades",
            "subcategory":"Landscaping Services",
            "type":"Services"
        }
    ],
    "sg:phone":"+1 678 393 9506",
    "sg:postcode":"30022",
    "sg:province":"GA",
    "sg:tags":[
        "landscape"
    ],
    "wof:name":"Reyes Landscaping Inc",
    "wof:placetype":"venue"
},
  "geometry": {"coordinates":[-84.254228,34.050808],"type":"Point"}
}