{
  "type": "Feature",
  "properties": {
    "iso:country":"US",
    "sg:address":"5250 Wyntercreek Way",
    "sg:city":"Atlanta",
    "sg:classifiers":[
        {
            "category":"Professional",
            "subcategory":"Business Services",
            "type":"Services"
        }
    ],
    "sg:phone":"+1 770 393 2204",
    "sg:postcode":"30338",
    "sg:province":"GA",
    "wof:name":"Hammond Sherron Interiors",
    "wof:placetype":"venue"
},
  "geometry": {"coordinates":[-84.331768,33.954552],"type":"Point"}
}