{
  "type": "Feature",
  "properties": {
    "iso:country":"US",
    "sg:address":"67 Long Branch Rd",
    "sg:city":"Dahlonega",
    "sg:classifiers":[
        {
            "category":"Restaurant",
            "type":"Food & Drink"
        }
    ],
    "sg:menulink":"http://www.allmenus.com/ga/three-sisters-mountains/140685-waffle-house/menu/",
    "sg:phone":"+1 706 884 9905",
    "sg:postcode":"30533",
    "sg:province":"GA",
    "sg:tags":[
        "american"
    ],
    "wof:name":"Waffle House",
    "wof:placetype":"venue"
},
  "geometry": {"coordinates":[-83.96660799999999,34.469938],"type":"Point"}
}