{
  "type": "Feature",
  "properties": {
    "iso:country":"US",
    "sg:address":"1885 Tobacco Rd",
    "sg:city":"Augusta",
    "sg:classifiers":[
        {
            "category":"Government",
            "subcategory":"Office",
            "type":"Public Place"
        }
    ],
    "sg:phone":"+1 706 792 7744",
    "sg:postcode":"30906",
    "sg:province":"GA",
    "sg:tags":[
        "state"
    ],
    "wof:name":"Natural Resources Dept",
    "wof:placetype":"venue"
},
  "geometry": {"coordinates":[-82.008284,33.369728],"type":"Point"}
}