{
  "type": "Feature",
  "properties": {
    "iso:country":"US",
    "sg:address":"4736 Best Rd",
    "sg:city":"Atlanta",
    "sg:classifiers":[
        {
            "category":"Shopping",
            "subcategory":"Gifts & Souvenirs",
            "type":"Retail Goods"
        }
    ],
    "sg:phone":"+1 404 766 3126",
    "sg:postcode":"30337",
    "sg:province":"GA",
    "wof:name":"W H Smith Inc",
    "wof:placetype":"venue"
},
  "geometry": {"coordinates":[-84.45847500000001,33.624775],"type":"Point"}
}