{
  "type": "Feature",
  "properties": {
    "iso:country":"US",
    "sg:address":"4040 Bass Ln",
    "sg:city":"Cumming",
    "sg:classifiers":[
        {
            "category":"Travel",
            "subcategory":"Travel Agent",
            "type":"Entertainment"
        }
    ],
    "sg:phone":"+1 678 947 4800",
    "sg:postcode":"30028",
    "sg:province":"GA",
    "sg:tags":[
        "agency",
        "cruise"
    ],
    "sg:website":"www.leisuretravelandcruises.com",
    "wof:name":"Leisure Travel and Cruises",
    "wof:placetype":"venue"
},
  "geometry": {"coordinates":[-84.196033,34.26442],"type":"Point"}
}