{
  "type": "Feature",
  "properties": {
    "iso:country":"US",
    "sg:address":"5516 Westbrook Ln",
    "sg:city":"Oakwood",
    "sg:classifiers":[
        {
            "category":"Building & Trades",
            "subcategory":"Cleaning & Sanitation",
            "type":"Services"
        }
    ],
    "sg:phone":"+1 770 967 8000",
    "sg:postcode":"30566",
    "sg:province":"GA",
    "sg:tags":[
        "maintenance"
    ],
    "wof:name":"R & G Pressure Washing Inc",
    "wof:placetype":"venue"
},
  "geometry": {"coordinates":[-83.90928599999999,34.217383],"type":"Point"}
}