{
  "type": "Feature",
  "properties": {
    "addr:full":"537 Crawford St SE Dawson GA 39842",
    "addr:housenumber":"537",
    "addr:postcode":"39842",
    "addr:street":"Crawford St Se",
    "iso:country":"US",
    "sg:address":"537 Crawford St SE",
    "sg:city":"Dawson",
    "sg:classifiers":[
        {
            "category":"Building & Trades",
            "subcategory":"Construction",
            "type":"Services"
        }
    ],
    "sg:phone":"+1 229 995 4287",
    "sg:postcode":"39842",
    "sg:province":"GA",
    "wof:name":"Joe Moreland Contracting",
    "wof:placetype":"venue"
},
  "geometry": {"coordinates":[-84.437211,31.767718],"type":"Point"}
}