{
  "type": "Feature",
  "properties": {
    "iso:country":"US",
    "sg:address":"4210 Moreland Ave",
    "sg:city":"Conley",
    "sg:classifiers":[
        {
            "category":"Wholesale",
            "subcategory":"Durable Goods & Equipment",
            "type":"Manufacturing & Wholesale Goods"
        }
    ],
    "sg:phone":"+1 404 366 9155",
    "sg:postcode":"30288",
    "sg:province":"GA",
    "sg:tags":[
        "exporter"
    ],
    "wof:name":"Davenport Hauling",
    "wof:placetype":"venue"
},
  "geometry": {"coordinates":[-84.31976400000001,33.636268],"type":"Point"}
}