{
  "type": "Feature",
  "properties": {
    "addr:full":"1406 Dothan Rd Bainbridge GA 39817",
    "addr:housenumber":"1406",
    "addr:postcode":"39817",
    "addr:street":"Dothan Rd",
    "iso:country":"US",
    "sg:address":"1406 Dothan Rd",
    "sg:city":"Bainbridge",
    "sg:classifiers":[
        {
            "category":"Professional",
            "type":"Services"
        },
        {
            "category":"Retail",
            "subcategory":"Auto Repair",
            "type":"Services"
        }
    ],
    "sg:phone":"+1 229 246 6282",
    "sg:postcode":"39817",
    "sg:province":"GA",
    "sg:tags":[
        "shop",
        "establishment",
        "alignment"
    ],
    "wof:name":"Sirmons Alignment Inc",
    "wof:placetype":"venue"
},
  "geometry": {"coordinates":[-84.59366199999999,30.916936],"type":"Point"}
}