{
  "type": "Feature",
  "properties": {
    "addr:full":"2793 Montpelier Ave Macon GA 31204",
    "addr:housenumber":"2793",
    "addr:postcode":"31204",
    "addr:street":"Montpelier Ave",
    "iso:country":"US",
    "sg:address":"2793 Montpelier Ave",
    "sg:city":"Macon",
    "sg:classifiers":[
        {
            "category":"Food & Beverages",
            "subcategory":"Groceries & Convenience Stores",
            "type":"Retail Goods"
        }
    ],
    "sg:phone":"+1 478 746 3406",
    "sg:postcode":"31204",
    "sg:province":"GA",
    "wof:name":"Family Foods Stores",
    "wof:placetype":"venue"
},
  "geometry": {"coordinates":[-83.66833,32.830661],"type":"Point"}
}