{
  "type": "Feature",
  "properties": {
    "addr:full":"111 Highland Park Trl Atlanta GA 30350",
    "addr:housenumber":"111",
    "addr:postcode":"30350",
    "addr:street":"Highland Park Trl",
    "iso:country":"US",
    "sg:address":"111 Highland Park Trl",
    "sg:city":"Atlanta",
    "sg:classifiers":[
        {
            "category":"Autos & Motor Vehicles",
            "subcategory":"Automobile Sales",
            "type":"Retail Goods"
        },
        {
            "category":"Airline",
            "type":"Transportation"
        }
    ],
    "sg:phone":"+1 770 993 6334",
    "sg:postcode":"30350",
    "sg:province":"GA",
    "sg:tags":[
        "shuttle",
        "airport",
        "limo"
    ],
    "wof:name":"A B C Executive Limousine",
    "wof:placetype":"venue"
},
  "geometry": {"coordinates":[-84.342631,33.984391],"type":"Point"}
}