{
  "type": "Feature",
  "properties": {
    "addr:full":"504 Gi Maddox Pkwy Chatsworth GA 30705",
    "addr:housenumber":"504",
    "addr:postcode":"30705",
    "addr:street":"Gi Maddox Pkwy",
    "iso:country":"US",
    "sg:address":"504 Gi Maddox Pkwy",
    "sg:city":"Chatsworth",
    "sg:classifiers":[
        {
            "category":"Cinema",
            "subcategory":"Movie Rental",
            "type":"Entertainment"
        }
    ],
    "sg:phone":"+1 706 517 2307",
    "sg:postcode":"30705",
    "sg:province":"GA",
    "sg:tags":[
        "video",
        "store"
    ],
    "sg:website":"www.moviegallery.com",
    "wof:name":"Movie Gallery",
    "wof:placetype":"venue"
},
  "geometry": {"coordinates":[-84.782551,34.782416],"type":"Point"}
}