{
  "type": "Feature",
  "properties": {
    "iso:country":"US",
    "sg:address":"2115 Shell Rd",
    "sg:city":"Savannah",
    "sg:classifiers":[
        {
            "category":"Home & Garden",
            "subcategory":"Building Materials",
            "type":"Retail Goods"
        }
    ],
    "sg:phone":"+1 912 354 8951",
    "sg:postcode":"31404",
    "sg:province":"GA",
    "sg:tags":[
        "glass",
        "window",
        "plate"
    ],
    "wof:name":"Jack Ricks Glass Co",
    "wof:placetype":"venue"
},
  "geometry": {"coordinates":[-81.065558,32.03762],"type":"Point"}
}