{
  "type": "Feature",
  "properties": {
    "iso:country":"US",
    "sg:address":"522 Elma G Miles Pkwy",
    "sg:city":"Hinesville",
    "sg:classifiers":[
        {
            "category":"Health Services",
            "subcategory":"Doctor",
            "type":"Services"
        }
    ],
    "sg:phone":"+1 912 368 4850",
    "sg:postcode":"31313",
    "sg:province":"GA",
    "sg:tags":[
        "clinic"
    ],
    "sg:website":"www.gambro.com",
    "wof:name":"Gambro Healthcare",
    "wof:placetype":"venue"
},
  "geometry": {"coordinates":[-81.606881,31.836715],"type":"Point"}
}