{
  "type": "Feature",
  "properties": {
    "iso:country":"US",
    "sg:address":"980 Johnson Ferry Rd NE",
    "sg:city":"Atlanta",
    "sg:classifiers":[
        {
            "category":"Health Services",
            "subcategory":"Doctor",
            "type":"Services"
        }
    ],
    "sg:phone":"+1 404 256 5428",
    "sg:postcode":"30342",
    "sg:province":"GA",
    "sg:tags":[
        "physician",
        "reconstructive",
        "surgeons",
        "plastic",
        "surgery-general"
    ],
    "sg:website":"http://www.facialaestheticsurgery.com",
    "wof:name":"Sinha, Pradeep K",
    "wof:placetype":"venue"
},
  "geometry": {"coordinates":[-84.355908,33.907779],"type":"Point"}
}