{
  "type": "Feature",
  "properties": {
    "addr:full":"1016 Claxton Dairy Rd Dublin GA 31021",
    "addr:housenumber":"1016",
    "addr:postcode":"31021",
    "addr:street":"Claxton Dairy Rd",
    "iso:country":"US",
    "sg:address":"1016 Claxton Dairy Rd",
    "sg:city":"Dublin",
    "sg:classifiers":[
        {
            "category":"Banks & Credit Unions",
            "subcategory":"Bank",
            "type":"Services"
        }
    ],
    "sg:phone":"+1 478 272 0320",
    "sg:postcode":"31021",
    "sg:province":"GA",
    "sg:tags":[
        "financing"
    ],
    "wof:name":"Dublin Finance & Tax",
    "wof:placetype":"venue"
},
  "geometry": {"coordinates":[-82.92002599999999,32.544083],"type":"Point"}
}