{
  "type": "Feature",
  "properties": {
    "iso:country":"US",
    "sg:address":"2502 Oakrill Rd",
    "sg:city":"Marietta",
    "sg:classifiers":[
        {
            "category":"Professional",
            "subcategory":"Management & Consulting",
            "type":"Services"
        }
    ],
    "sg:phone":"+1 770 977 6826",
    "sg:postcode":"30062",
    "sg:province":"GA",
    "wof:name":"Sapphire Stars Inc",
    "wof:placetype":"venue"
},
  "geometry": {"coordinates":[-84.480653,34.007097],"type":"Point"}
}