{
  "type": "Feature",
  "properties": {
    "iso:country":"US",
    "sg:address":"510 Black Snake Rd",
    "sg:city":"Canon",
    "sg:classifiers":[
        {
            "category":"Farming",
            "subcategory":"Farm",
            "type":"Manufacturing & Wholesale Goods"
        }
    ],
    "sg:phone":"+1 706 246 3050",
    "sg:postcode":"30520",
    "sg:province":"GA",
    "sg:tags":[
        "crop",
        "general"
    ],
    "wof:name":"Skylers Farms",
    "wof:placetype":"venue"
},
  "geometry": {"coordinates":[-83.131101,34.318494],"type":"Point"}
}