{
  "type": "Feature",
  "properties": {
    "addr:full":"430 E Main St Canton GA 30114",
    "addr:housenumber":"430",
    "addr:postcode":"30114",
    "addr:street":"E Main St",
    "iso:country":"US",
    "sg:address":"430 E Main St",
    "sg:city":"Canton",
    "sg:classifiers":[
        {
            "category":"Shopping",
            "subcategory":"Florist",
            "type":"Retail Goods"
        }
    ],
    "sg:phone":"+1 770 479 3392",
    "sg:postcode":"30114",
    "sg:province":"GA",
    "sg:website":"fowlersflorist.com",
    "wof:name":"Fowlers Florist & Gifts",
    "wof:placetype":"venue"
},
  "geometry": {"coordinates":[-84.486988,34.236368],"type":"Point"}
}