{
  "type": "Feature",
  "properties": {
    "addr:full":"5975 Ashbury Ln Cumming GA 30028",
    "addr:housenumber":"5975",
    "addr:postcode":"30028",
    "addr:street":"Ashbury Ln",
    "iso:country":"US",
    "sg:address":"5975 Ashbury Ln",
    "sg:city":"Cumming",
    "sg:classifiers":[
        {
            "category":"Building & Trades",
            "subcategory":"Plumbing",
            "type":"Services"
        }
    ],
    "sg:phone":"+1 770 844 9862",
    "sg:postcode":"30028",
    "sg:province":"GA",
    "sg:tags":[
        "contractor"
    ],
    "wof:name":"Marcus Heating & AC",
    "wof:placetype":"venue"
},
  "geometry": {"coordinates":[-84.076883,34.321843],"type":"Point"}
}