{
  "type": "Feature",
  "properties": {
    "iso:country":"US",
    "sg:address":"1542 Canberra Dr",
    "sg:city":"Stone Mountain",
    "sg:classifiers":[
        {
            "category":"Organizations",
            "subcategory":"Religious Organization",
            "type":"Services"
        }
    ],
    "sg:phone":"+1 678 518 9176",
    "sg:postcode":"30088",
    "sg:province":"GA",
    "wof:name":"Daily Bread Ministries Inc",
    "wof:placetype":"venue"
},
  "geometry": {"coordinates":[-84.191627,33.745293],"type":"Point"}
}