{
  "type": "Feature",
  "properties": {
    "iso:country":"US",
    "sg:address":"1305 Alice St",
    "sg:city":"Waycross",
    "sg:classifiers":[
        {
            "category":"Organizations",
            "subcategory":"Religious Organization",
            "type":"Services"
        }
    ],
    "sg:phone":"+1 912 285 1204",
    "sg:postcode":"31501",
    "sg:province":"GA",
    "wof:name":"Memorial Baptist Church",
    "wof:placetype":"venue"
},
  "geometry": {"coordinates":[-82.352036,31.220351],"type":"Point"}
}