{
  "type": "Feature",
  "properties": {
    "addr:full":"1410 Laurel Haven Ct Lawrenceville GA 30043",
    "addr:housenumber":"1410",
    "addr:postcode":"30043",
    "addr:street":"Laurel Haven Ct",
    "iso:country":"US",
    "sg:address":"1410 Laurel Haven Ct",
    "sg:city":"Lawrenceville",
    "sg:classifiers":[
        {
            "category":"Professional",
            "subcategory":"Management & Consulting",
            "type":"Services"
        }
    ],
    "sg:phone":"+1 770 822 9233",
    "sg:postcode":"30043",
    "sg:province":"GA",
    "sg:tags":[
        "business"
    ],
    "wof:name":"Hesters Consulting Services",
    "wof:placetype":"venue"
},
  "geometry": {"coordinates":[-84.004514,33.995415],"type":"Point"}
}