{
  "type": "Feature",
  "properties": {
    "iso:country":"US",
    "sg:address":"1189 Bob Smith Rd",
    "sg:city":"Sharpsburg",
    "sg:classifiers":[
        {
            "category":"Restaurant",
            "type":"Food & Drink"
        }
    ],
    "sg:phone":"+1 770 253 7829",
    "sg:postcode":"30277",
    "sg:province":"GA",
    "sg:tags":[
        "eating"
    ],
    "wof:name":"R T M Enterprises Inc",
    "wof:placetype":"venue"
},
  "geometry": {"coordinates":[-84.64358199999999,33.378326],"type":"Point"}
}