{
  "type": "Feature",
  "properties": {
    "iso:country":"US",
    "sg:address":"3064 Kent Ct",
    "sg:city":"Duluth",
    "sg:classifiers":[
        {
            "category":"Manufacturing",
            "subcategory":"Lumber",
            "type":"Manufacturing & Wholesale Goods"
        }
    ],
    "sg:phone":"+1 770 476 3779",
    "sg:postcode":"30096",
    "sg:province":"GA",
    "sg:tags":[
        "logging"
    ],
    "wof:name":"Logs To Lumber",
    "wof:placetype":"venue"
},
  "geometry": {"coordinates":[-84.13020899999999,33.985097],"type":"Point"}
}