{
  "type": "Feature",
  "properties": {
    "iso:country":"US",
    "sg:address":"299 S Main St",
    "sg:city":"Alpharetta",
    "sg:classifiers":[
        {
            "category":"Health Services",
            "subcategory":"Medical Lab",
            "type":"Services"
        }
    ],
    "sg:phone":"+1 770 346 8952",
    "sg:postcode":"30004",
    "sg:province":"GA",
    "sg:tags":[
        "laboratory"
    ],
    "wof:name":"Quality Diagnostic Svc",
    "wof:placetype":"venue"
},
  "geometry": {"coordinates":[-84.29968599999999,34.068641],"type":"Point"}
}