{
  "type": "Feature",
  "properties": {
    "addr:full":"701 Lupo Ln Douglas GA 31533",
    "addr:housenumber":"701",
    "addr:postcode":"31533",
    "addr:street":"Lupo Ln",
    "iso:country":"US",
    "sg:address":"701 Lupo Ln",
    "sg:city":"Douglas",
    "sg:classifiers":[
        {
            "category":"Real Estate",
            "subcategory":"Real Estate Operator",
            "type":"Services"
        }
    ],
    "sg:phone":"+1 912 384 0002",
    "sg:postcode":"31533",
    "sg:province":"GA",
    "sg:tags":[
        "apartment"
    ],
    "wof:name":"Hunters Run Apartments",
    "wof:placetype":"venue"
},
  "geometry": {"coordinates":[-82.832438,31.501278],"type":"Point"}
}