{
  "type": "Feature",
  "properties": {
    "addr:full":"2888 Knotty Pine Ct. Buford GA 30519",
    "addr:housenumber":"2888",
    "addr:postcode":"30519",
    "addr:street":"Knotty Pine Ct.",
    "iso:country":"US",
    "sg:address":"2888 Knotty Pine Ct.",
    "sg:city":"Buford",
    "sg:classifiers":[
        {
            "category":"Building & Trades",
            "subcategory":"Construction",
            "type":"Services"
        }
    ],
    "sg:phone":"+1 770 256 9776",
    "sg:postcode":"30519",
    "sg:province":"GA",
    "sg:tags":[
        "contractor"
    ],
    "sg:website":"gwinnettoverheaddoors.com",
    "wof:name":"Gwinnett Overhead Door",
    "wof:placetype":"venue"
},
  "geometry": {"coordinates":[-83.9675,34.111913],"type":"Point"}
}