{
  "type": "Feature",
  "properties": {
    "addr:full":"215 N Piedmont St Calhoun GA 30701",
    "addr:housenumber":"215",
    "addr:postcode":"30701",
    "addr:street":"N Piedmont St",
    "iso:country":"US",
    "sg:address":"215 N Piedmont St",
    "sg:city":"Calhoun",
    "sg:classifiers":[
        {
            "category":"Insurance",
            "subcategory":"Insurance Agent",
            "type":"Services"
        }
    ],
    "sg:phone":"+1 706 629 6717",
    "sg:postcode":"30701",
    "sg:province":"GA",
    "wof:name":"Grooms Insurance",
    "wof:placetype":"venue"
},
  "geometry": {"coordinates":[-84.950177,34.505599],"type":"Point"}
}