{
  "type": "Feature",
  "properties": {
    "iso:country":"US",
    "sg:address":"237 W Wynngate Dr",
    "sg:city":"Augusta",
    "sg:classifiers":[
        {
            "category":"Building & Trades",
            "subcategory":"Construction",
            "type":"Services"
        }
    ],
    "sg:phone":"+1 706 394 2551",
    "sg:postcode":"30907",
    "sg:province":"GA",
    "sg:tags":[
        "home",
        "improvement"
    ],
    "wof:name":"House Helper",
    "wof:placetype":"venue"
},
  "geometry": {"coordinates":[-82.09053900000001,33.517321],"type":"Point"}
}