{
  "type": "Feature",
  "properties": {
    "iso:country":"US",
    "sg:address":"5112 4th Ave",
    "sg:city":"Eastman",
    "sg:classifiers":[
        {
            "category":"Professional",
            "subcategory":"Business Services",
            "type":"Services"
        }
    ],
    "sg:phone":"+1 478 374 1062",
    "sg:postcode":"31023",
    "sg:province":"GA",
    "wof:name":"King Enterprises",
    "wof:placetype":"venue"
},
  "geometry": {"coordinates":[-83.176177,32.197846],"type":"Point"}
}