{
  "type": "Feature",
  "properties": {
    "iso:country":"US",
    "sg:address":"157 W Wesley Rd NW",
    "sg:city":"Atlanta",
    "sg:classifiers":[
        {
            "category":"Social Services",
            "type":"Services"
        },
        {
            "category":"Professional",
            "subcategory":"Employment Agencies",
            "type":"Services"
        }
    ],
    "sg:phone":"+1 404 233 1385",
    "sg:postcode":"30305",
    "sg:province":"GA",
    "sg:tags":[
        "workers'",
        "placement",
        "volunteer"
    ],
    "wof:name":"Murren Foundation, Inc.",
    "wof:placetype":"venue"
},
  "geometry": {"coordinates":[-84.392776,33.828654],"type":"Point"}
}