{
  "type": "Feature",
  "properties": {
    "iso:country":"US",
    "sg:address":"4840 Roswell Rd NE",
    "sg:city":"Atlanta",
    "sg:classifiers":[
        {
            "category":"Professional",
            "subcategory":"Lawyer & Legal Services",
            "type":"Services"
        }
    ],
    "sg:phone":"+1 404 978 1633",
    "sg:postcode":"30342",
    "sg:province":"GA",
    "wof:name":"Augusta Title Inc Atty",
    "wof:placetype":"venue"
},
  "geometry": {"coordinates":[-84.381699,33.886799],"type":"Point"}
}