{
  "type": "Feature",
  "properties": {
    "addr:full":"18098 State Rte 67 Statesboro GA 30458",
    "addr:housenumber":"18098",
    "addr:postcode":"30458",
    "addr:street":"State Rte 67",
    "iso:country":"US",
    "sg:address":"18098 State Rte 67",
    "sg:city":"Statesboro",
    "sg:classifiers":[
        {
            "category":"Organizations",
            "subcategory":"Religious Organization",
            "type":"Services"
        }
    ],
    "sg:phone":"+1 912 681 2481",
    "sg:postcode":"30458",
    "sg:province":"GA",
    "sg:tags":[
        "church"
    ],
    "wof:name":"St Paul's Lutheran Church",
    "wof:placetype":"venue"
},
  "geometry": {"coordinates":[-81.801608,32.476774],"type":"Point"}
}