{
  "type": "Feature",
  "properties": {
    "addr:full":"1500 Southlake Mall Morrow GA 30260",
    "addr:housenumber":"1500",
    "addr:postcode":"30260",
    "addr:street":"Southlake Mall",
    "iso:country":"US",
    "sg:address":"1500 Southlake Mall",
    "sg:city":"Morrow",
    "sg:classifiers":[
        {
            "category":"Personal",
            "subcategory":"Beauty Salon",
            "type":"Services"
        }
    ],
    "sg:phone":"+1 404 961 3161",
    "sg:postcode":"30260",
    "sg:province":"GA",
    "wof:name":"Premier Salon 17749",
    "wof:placetype":"venue"
},
  "geometry": {"coordinates":[-84.35478999999999,33.573584],"type":"Point"}
}