{
  "type": "Feature",
  "properties": {
    "iso:country":"US",
    "sg:address":"180 Cobb Parkway",
    "sg:city":"Atlanta",
    "sg:classifiers":[
        {
            "category":"Landmark",
            "subcategory":"Tourist Information",
            "type":"Public Place"
        }
    ],
    "sg:phone":"+1 770 499 8868",
    "sg:postcode":"30303",
    "sg:province":"GA",
    "sg:tags":[
        "tour"
    ],
    "wof:name":"Nationwide Travel",
    "wof:placetype":"venue"
},
  "geometry": {"coordinates":[-84.38897,33.755418],"type":"Point"}
}