{
  "type": "Feature",
  "properties": {
    "iso:country":"US",
    "sg:address":"891 Pine Ridge Dr",
    "sg:city":"Stone Mountain",
    "sg:classifiers":[
        {
            "category":"Professional",
            "subcategory":"Secretarial Services",
            "type":"Services"
        }
    ],
    "sg:phone":"+1 770 879 0063",
    "sg:postcode":"30087",
    "sg:province":"GA",
    "sg:tags":[
        "reporting"
    ],
    "wof:name":"After Hours Typing Service",
    "wof:placetype":"venue"
},
  "geometry": {"coordinates":[-84.124343,33.768361],"type":"Point"}
}