{
  "type": "Feature",
  "properties": {
    "addr:full":"4327 Edgemere Dr Marietta GA 30062",
    "addr:housenumber":"4327",
    "addr:postcode":"30062",
    "addr:street":"Edgemere Dr",
    "iso:country":"US",
    "sg:address":"4327 Edgemere Dr",
    "sg:city":"Marietta",
    "sg:classifiers":[
        {
            "category":"Recreation",
            "type":"Entertainment"
        }
    ],
    "sg:phone":"+1 770 518 8345",
    "sg:postcode":"30062",
    "sg:province":"GA",
    "sg:tags":[
        "pool",
        "swimming"
    ],
    "wof:name":"Edgemere Clubhouse",
    "wof:placetype":"venue"
},
  "geometry": {"coordinates":[-84.427769,34.006265],"type":"Point"}
}