{
  "type": "Feature",
  "properties": {
    "addr:full":"3340 Peachtree Rd NE #10 Atlanta GA 30326",
    "addr:housenumber":"3340",
    "addr:postcode":"30326",
    "addr:street":"Peachtree Rd Ne # 10",
    "iso:country":"US",
    "sg:address":"3340 Peachtree Rd NE #10",
    "sg:city":"Atlanta",
    "sg:classifiers":[
        {
            "category":"Shopping",
            "subcategory":"Clothing, Apparel, & Fashions",
            "type":"Retail Goods"
        }
    ],
    "sg:phone":"+1 404 231 0044",
    "sg:postcode":"30326",
    "sg:province":"GA",
    "sg:tags":[
        "men's",
        "clothing"
    ],
    "sg:website":"www.guffeys.com",
    "wof:name":"Guffey's of Atlanta",
    "wof:placetype":"venue"
},
  "geometry": {"coordinates":[-84.36868200000001,33.845449],"type":"Point"}
}