{
  "type": "Feature",
  "properties": {
    "iso:country":"US",
    "sg:address":"2723 Highway 129 S",
    "sg:city":"Cleveland",
    "sg:classifiers":[
        {
            "category":"Insurance",
            "subcategory":"Hazard Insurance",
            "type":"Services"
        }
    ],
    "sg:phone":"+1 706 865 1072",
    "sg:postcode":"30528",
    "sg:province":"GA",
    "sg:tags":[
        "commercial",
        "business"
    ],
    "wof:name":"Rogers Miller Agency",
    "wof:placetype":"venue"
},
  "geometry": {"coordinates":[-83.763306,34.562336],"type":"Point"}
}