{
  "type": "Feature",
  "properties": {
    "iso:country":"US",
    "sg:address":"170 Butler Ave",
    "sg:city":"Midway",
    "sg:classifiers":[
        {
            "category":"Shopping",
            "subcategory":"Department Store",
            "type":"Retail Goods"
        }
    ],
    "sg:phone":"+1 912 884 2025",
    "sg:postcode":"31328",
    "sg:province":"GA",
    "sg:tags":[
        "shop"
    ],
    "wof:name":"Dollar General",
    "wof:placetype":"venue"
},
  "geometry": {"coordinates":[-80.84154100000001,32.011371],"type":"Point"}
}