{
  "type": "Feature",
  "properties": {
    "iso:country":"US",
    "sg:address":"5285 Cartersville Hwy",
    "sg:city":"Dallas",
    "sg:classifiers":[
        {
            "category":"Wholesale",
            "subcategory":"Electrical",
            "type":"Manufacturing & Wholesale Goods"
        }
    ],
    "sg:phone":"+1 770 445 1183",
    "sg:postcode":"30132",
    "sg:province":"GA",
    "sg:tags":[
        "fire",
        "alarm",
        "system"
    ],
    "wof:name":"Southeastern Wiring & Security",
    "wof:placetype":"venue"
},
  "geometry": {"coordinates":[-84.862303,34.013814],"type":"Point"}
}