{
  "type": "Feature",
  "properties": {
    "iso:country":"US",
    "sg:address":"4732 N Royal Atlanta Dr",
    "sg:city":"Tucker",
    "sg:classifiers":[
        {
            "category":"Utilities",
            "subcategory":"Telephone",
            "type":"Services"
        }
    ],
    "sg:phone":"+1 770 492 0650",
    "sg:postcode":"30084",
    "sg:province":"GA",
    "sg:tags":[
        "telecommunication"
    ],
    "wof:name":"Teleneeds",
    "wof:placetype":"venue"
},
  "geometry": {"coordinates":[-84.198212,33.859664],"type":"Point"}
}