{
  "type": "Feature",
  "properties": {
    "addr:full":"1614 Ellis St Brunswick GA 31520",
    "addr:housenumber":"1614",
    "addr:postcode":"31520",
    "addr:street":"Ellis St",
    "iso:country":"US",
    "sg:address":"1614 Ellis St",
    "sg:city":"Brunswick",
    "sg:classifiers":[
        {
            "category":"Professional",
            "subcategory":"Lawyer & Legal Services",
            "type":"Services"
        }
    ],
    "sg:phone":"+1 912 264 2347",
    "sg:postcode":"31520",
    "sg:province":"GA",
    "wof:name":"Richard H Taylor",
    "wof:placetype":"venue"
},
  "geometry": {"coordinates":[-81.49328199999999,31.151579],"type":"Point"}
}