{
  "type": "Feature",
  "properties": {
    "iso:country":"US",
    "sg:address":"1655 Spring Rd SE",
    "sg:city":"Smyrna",
    "sg:classifiers":[
        {
            "category":"Health Services",
            "subcategory":"Medical Lab",
            "type":"Services"
        }
    ],
    "sg:phone":"+1 678 305 7447",
    "sg:postcode":"30080",
    "sg:province":"GA",
    "sg:tags":[
        "resonance",
        "magnetic",
        "imaging"
    ],
    "wof:name":"Comprehensive Medical Dgnstc",
    "wof:placetype":"venue"
},
  "geometry": {"coordinates":[-84.50346399999999,33.882933],"type":"Point"}
}