{
  "type": "Feature",
  "properties": {
    "iso:country":"US",
    "sg:address":"2603 Sadie Ct",
    "sg:city":"Hephzibah",
    "sg:classifiers":[
        {
            "category":"Building & Trades",
            "subcategory":"Construction",
            "type":"Services"
        }
    ],
    "sg:phone":"+1 706 790 9220",
    "sg:postcode":"30815",
    "sg:province":"GA",
    "sg:tags":[
        "floor",
        "laying",
        "contractor"
    ],
    "wof:name":"J & B Installations Service",
    "wof:placetype":"venue"
},
  "geometry": {"coordinates":[-82.097185,33.374715],"type":"Point"}
}