{
  "type": "Feature",
  "properties": {
    "addr:full":"4026 Columans Cir SE Marietta GA 30067",
    "addr:housenumber":"4026",
    "addr:postcode":"30067",
    "addr:street":"Columans Cir Se",
    "iso:country":"US",
    "sg:address":"4026 Columans Cir SE",
    "sg:city":"Marietta",
    "sg:classifiers":[
        {
            "category":"Professional",
            "type":"Services"
        },
        {
            "category":"Professional",
            "subcategory":"Management & Consulting",
            "type":"Services"
        }
    ],
    "sg:phone":"+1 770 956 7686",
    "sg:postcode":"30067",
    "sg:province":"GA",
    "sg:tags":[
        "establishment"
    ],
    "wof:name":"Warner Fox Associates",
    "wof:placetype":"venue"
},
  "geometry": {"coordinates":[-84.417613,33.933652],"type":"Point"}
}