{
  "type": "Feature",
  "properties": {
    "addr:full":"5319 Lawrenceville Hwy Lilburn GA 30047",
    "addr:housenumber":"5319",
    "addr:postcode":"30047",
    "addr:street":"Lawrenceville Hwy",
    "iso:country":"US",
    "sg:address":"5319 Lawrenceville Hwy",
    "sg:city":"Lilburn",
    "sg:classifiers":[
        {
            "category":"Shopping",
            "subcategory":"Clothing, Apparel, & Fashions",
            "type":"Retail Goods"
        }
    ],
    "sg:phone":"+1 678 924 3100",
    "sg:postcode":"30047",
    "sg:province":"GA",
    "wof:name":"Descrete Fashions",
    "wof:placetype":"venue"
},
  "geometry": {"coordinates":[-84.155147,33.889286],"type":"Point"}
}