{
  "type": "Feature",
  "properties": {
    "iso:country":"US",
    "sg:address":"210 Lovvorn Rd",
    "sg:city":"Cedartown",
    "sg:classifiers":[
        {
            "category":"Manufacturing",
            "subcategory":"Paper Products",
            "type":"Manufacturing & Wholesale Goods"
        }
    ],
    "sg:phone":"+1 770 748 8400",
    "sg:postcode":"30125",
    "sg:province":"GA",
    "sg:tags":[
        "corrugated",
        "solid",
        "fiber",
        "box"
    ],
    "wof:name":"Inland Paperboard & Pkg Inc",
    "wof:placetype":"venue"
},
  "geometry": {"coordinates":[-85.241058,33.984261],"type":"Point"}
}