{
  "type": "Feature",
  "properties": {
    "iso:country":"US",
    "sg:address":"3074 Baymount Way",
    "sg:city":"Lawrenceville",
    "sg:classifiers":[
        {
            "category":"Education",
            "subcategory":"Special Training",
            "type":"Public Place"
        }
    ],
    "sg:phone":"+1 678 546 8526",
    "sg:postcode":"30043",
    "sg:province":"GA",
    "sg:tags":[
        "tutoring"
    ],
    "wof:name":"Floyd Jacinta Figures",
    "wof:placetype":"venue"
},
  "geometry": {"coordinates":[-84.00510800000001,34.049965],"type":"Point"}
}