{
  "type": "Feature",
  "properties": {
    "addr:full":"198 Candace Ln Kennesaw GA 30144",
    "addr:housenumber":"198",
    "addr:postcode":"30144",
    "addr:street":"Candace Ln",
    "iso:country":"US",
    "sg:address":"198 Candace Ln",
    "sg:city":"Kennesaw",
    "sg:classifiers":[
        {
            "category":"Wholesale",
            "subcategory":"Machinery & Supplies",
            "type":"Manufacturing & Wholesale Goods"
        }
    ],
    "sg:phone":"+1 770 794 3201",
    "sg:postcode":"30144",
    "sg:province":"GA",
    "sg:tags":[
        "industrial"
    ],
    "wof:name":"Valvtechnologies Inc",
    "wof:placetype":"venue"
},
  "geometry": {"coordinates":[-84.55557,34.04262],"type":"Point"}
}