{
  "type": "Feature",
  "properties": {
    "iso:country":"US",
    "sg:address":"2335 Howell Mill Rd NW",
    "sg:city":"Atlanta",
    "sg:classifiers":[
        {
            "category":"Banks & Credit Unions",
            "subcategory":"Financial Services",
            "type":"Services"
        }
    ],
    "sg:phone":"+1 404 367 9437",
    "sg:postcode":"30318",
    "sg:province":"GA",
    "sg:tags":[
        "management",
        "investment"
    ],
    "wof:name":"Bella Investment Group",
    "wof:placetype":"venue"
},
  "geometry": {"coordinates":[-84.417,33.819185],"type":"Point"}
}