{
  "type": "Feature",
  "properties": {
    "addr:full":"150 Marr Ave Marietta GA 30060",
    "addr:housenumber":"150",
    "addr:postcode":"30060",
    "addr:street":"Marr Ave",
    "iso:country":"US",
    "sg:address":"150 Marr Ave",
    "sg:city":"Marietta",
    "sg:classifiers":[
        {
            "category":"Manufacturing",
            "subcategory":"Tools & Machinery",
            "type":"Manufacturing & Wholesale Goods"
        }
    ],
    "sg:phone":"+1 770 795 8556",
    "sg:postcode":"30060",
    "sg:province":"GA",
    "sg:tags":[
        "machine",
        "shop"
    ],
    "sg:website":"www.diamondroller.com",
    "wof:name":"Diamond Holding Corp",
    "wof:placetype":"venue"
},
  "geometry": {"coordinates":[-84.55641199999999,33.975608],"type":"Point"}
}