{
  "type": "Feature",
  "properties": {
    "iso:country":"US",
    "sg:address":"4024 Lindsey Ln",
    "sg:city":"Rex",
    "sg:classifiers":[
        {
            "category":"Wholesale",
            "subcategory":"Apparel",
            "type":"Manufacturing & Wholesale Goods"
        }
    ],
    "sg:phone":"+1 770 506 0194",
    "sg:postcode":"30273",
    "sg:province":"GA",
    "sg:tags":[
        "sportswear-wholesale",
        "manufacturer"
    ],
    "wof:name":"A Bryant Custom",
    "wof:placetype":"venue"
},
  "geometry": {"coordinates":[-84.258939,33.592763],"type":"Point"}
}