{
  "type": "Feature",
  "properties": {
    "iso:country":"US",
    "sg:address":"3947 N Highway 27",
    "sg:city":"Carrollton",
    "sg:classifiers":[
        {
            "category":"Retail",
            "subcategory":"Auto Rental",
            "type":"Services"
        },
        {
            "category":"Retail",
            "subcategory":"Storage",
            "type":"Services"
        }
    ],
    "sg:phone":"+1 770 832 0045",
    "sg:postcode":"30117",
    "sg:province":"GA",
    "sg:tags":[
        "moving-self",
        "truck"
    ],
    "wof:name":"U Drive It Rentals",
    "wof:placetype":"venue"
},
  "geometry": {"coordinates":[-85.140298,33.654303],"type":"Point"}
}