{
  "type": "Feature",
  "properties": {
    "addr:full":"704 W Waugh St Dalton GA 30720",
    "addr:housenumber":"704",
    "addr:postcode":"30720",
    "addr:street":"W Waugh St",
    "iso:country":"US",
    "sg:address":"704 W Waugh St",
    "sg:city":"Dalton",
    "sg:classifiers":[
        {
            "category":"Professional",
            "subcategory":"Art Services",
            "type":"Services"
        }
    ],
    "sg:phone":"+1 706 275 6700",
    "sg:postcode":"30720",
    "sg:province":"GA",
    "sg:tags":[
        "graphic",
        "design"
    ],
    "wof:name":"Km Graphics",
    "wof:placetype":"venue"
},
  "geometry": {"coordinates":[-84.97948700000001,34.776523],"type":"Point"}
}