{
  "type": "Feature",
  "properties": {
    "iso:country":"US",
    "sg:address":"4627 Peachtree Place Pkwy",
    "sg:city":"Atlanta",
    "sg:classifiers":[
        {
            "category":"Shopping",
            "subcategory":"Gifts & Souvenirs",
            "type":"Retail Goods"
        }
    ],
    "sg:phone":"+1 770 242 0788",
    "sg:postcode":"30360",
    "sg:province":"GA",
    "wof:name":"Brinkley House Gifts",
    "wof:placetype":"venue"
},
  "geometry": {"coordinates":[-84.26863899999999,33.933345],"type":"Point"}
}