{
  "type": "Feature",
  "properties": {
    "addr:full":"80 Hickory Springs Industrial Dr Canton GA 30115",
    "addr:housenumber":"80",
    "addr:postcode":"30115",
    "addr:street":"Hickory Springs Industrial Dr",
    "iso:country":"US",
    "sg:address":"80 Hickory Springs Industrial Dr",
    "sg:city":"Canton",
    "sg:classifiers":[
        {
            "category":"Manufacturing",
            "subcategory":"Tools & Machinery",
            "type":"Manufacturing & Wholesale Goods"
        },
        {
            "category":"Building & Trades",
            "subcategory":"Landscaping Services",
            "type":"Services"
        }
    ],
    "sg:phone":"+1 770 345 6625",
    "sg:postcode":"30115",
    "sg:province":"GA",
    "sg:tags":[
        "manufacture",
        "sell",
        "lawn",
        "concrete",
        "contractor",
        "equipment",
        "curb",
        "landscape"
    ],
    "wof:name":"Tygar Manufacturing Inc",
    "wof:placetype":"venue"
},
  "geometry": {"coordinates":[-84.49423400000001,34.170467],"type":"Point"}
}