{
  "type": "Feature",
  "properties": {
    "addr:full":"2050 Buford Hwy Buford GA 30518",
    "addr:housenumber":"2050",
    "addr:postcode":"30518",
    "addr:street":"Buford Hwy",
    "iso:country":"US",
    "sg:address":"2050 Buford Hwy",
    "sg:city":"Buford",
    "sg:classifiers":[
        {
            "category":"Health Services",
            "subcategory":"Doctor",
            "type":"Services"
        }
    ],
    "sg:phone":"+1 770 614 7369",
    "sg:postcode":"30518",
    "sg:province":"GA",
    "sg:tags":[
        "physician",
        "surgeon"
    ],
    "wof:name":"Renfus, Renee MD FAAP",
    "wof:placetype":"venue"
},
  "geometry": {"coordinates":[-83.999854,34.109586],"type":"Point"}
}