{
  "type": "Feature",
  "properties": {
    "addr:full":"990 Iris Dr SW Ste 202 Conyers GA 30094",
    "addr:housenumber":"990",
    "addr:postcode":"30094",
    "addr:street":"Iris Dr Sw Ste 202",
    "iso:country":"US",
    "sg:address":"990 Iris Dr SW Ste 202",
    "sg:city":"Conyers",
    "sg:classifiers":[
        {
            "category":"Health Services",
            "subcategory":"Dentist",
            "type":"Services"
        }
    ],
    "sg:phone":"+1 770 483 8816",
    "sg:postcode":"30094",
    "sg:province":"GA",
    "wof:name":"Golden Robert D DMD",
    "wof:placetype":"venue"
},
  "geometry": {"coordinates":[-84.022003,33.659401],"type":"Point"}
}