{
  "type": "Feature",
  "properties": {
    "iso:country":"US",
    "sg:address":"269 Hurricane Shoals Rd NW",
    "sg:city":"Lawrenceville",
    "sg:classifiers":[
        {
            "category":"Manufacturing",
            "subcategory":"Chemicals & Compounds",
            "type":"Manufacturing & Wholesale Goods"
        }
    ],
    "sg:phone":"+1 770 962 4200",
    "sg:postcode":"30045",
    "sg:province":"GA",
    "sg:tags":[
        "industrial",
        "organic",
        "mfg"
    ],
    "wof:name":"Finishmaster Inc",
    "wof:placetype":"venue"
},
  "geometry": {"coordinates":[-84.00005299999999,33.968492],"type":"Point"}
}