{
  "type": "Feature",
  "properties": {
    "addr:full":"1167 Haithcock Dr Ball Ground GA 30107",
    "addr:housenumber":"1167",
    "addr:postcode":"30107",
    "addr:street":"Haithcock Dr",
    "iso:country":"US",
    "sg:address":"1167 Haithcock Dr",
    "sg:city":"Ball Ground",
    "sg:classifiers":[
        {
            "category":"Building & Trades",
            "subcategory":"Construction",
            "type":"Services"
        }
    ],
    "sg:phone":"+1 770 735 1457",
    "sg:postcode":"30107",
    "sg:province":"GA",
    "sg:tags":[
        "house"
    ],
    "wof:name":"Garretts Construction",
    "wof:placetype":"venue"
},
  "geometry": {"coordinates":[-84.388991,34.370626],"type":"Point"}
}