{
  "type": "Feature",
  "properties": {
    "iso:country":"US",
    "sg:address":"4713 Rockmart Rd SE",
    "sg:city":"Silver Creek",
    "sg:classifiers":[
        {
            "category":"Retail",
            "subcategory":"Auto Repair",
            "type":"Services"
        },
        {
            "category":"Wholesale",
            "subcategory":"Auto Parts",
            "type":"Manufacturing & Wholesale Goods"
        }
    ],
    "sg:phone":"+1 706 232 9583",
    "sg:postcode":"30173",
    "sg:province":"GA",
    "sg:tags":[
        "used",
        "supply",
        "automobile",
        "general",
        "au",
        "rebuilt"
    ],
    "wof:name":"Terrys Used Auto Parts",
    "wof:placetype":"venue"
},
  "geometry": {"coordinates":[-85.142224,34.159752],"type":"Point"}
}