{
  "type": "Feature",
  "properties": {
    "addr:full":"3586 Evans To Locks Rd Augusta GA 30907",
    "addr:housenumber":"3586;to",
    "addr:postcode":"30907",
    "addr:street":"Evans;Locks Rd",
    "iso:country":"US",
    "sg:address":"3586 Evans To Locks Rd",
    "sg:city":"Augusta",
    "sg:classifiers":[
        {
            "category":"Social Services",
            "type":"Services"
        }
    ],
    "sg:phone":"+1 706 231 1537",
    "sg:postcode":"30907",
    "sg:province":"GA",
    "sg:tags":[
        "youth",
        "shelter"
    ],
    "wof:name":"Youth Kastle",
    "wof:placetype":"venue"
},
  "geometry": {"coordinates":[-82.063542,33.553824],"type":"Point"}
}