{
  "type": "Feature",
  "properties": {
    "iso:country":"US",
    "sg:address":"495 Jaywood Ct",
    "sg:city":"Stone Mountain",
    "sg:classifiers":[
        {
            "category":"Social Services",
            "subcategory":"Adult Care",
            "type":"Services"
        }
    ],
    "sg:phone":"+1 770 413 0331",
    "sg:postcode":"30083",
    "sg:province":"GA",
    "sg:tags":[
        "home",
        "residential"
    ],
    "wof:name":"Ridgecrest",
    "wof:placetype":"venue"
},
  "geometry": {"coordinates":[-84.166971,33.790107],"type":"Point"}
}