{
  "type": "Feature",
  "properties": {
    "iso:country":"US",
    "sg:address":"546 Auburn Ave NE",
    "sg:city":"Atlanta",
    "sg:classifiers":[
        {
            "category":"Professional",
            "subcategory":"Management & Consulting",
            "type":"Services"
        }
    ],
    "sg:phone":"+1 404 523 2400",
    "sg:postcode":"30312",
    "sg:province":"GA",
    "sg:tags":[
        "marketing",
        "consultant"
    ],
    "wof:name":"Global Marketing & Pr",
    "wof:placetype":"venue"
},
  "geometry": {"coordinates":[-84.369421,33.755713],"type":"Point"}
}