{
  "type": "Feature",
  "properties": {
    "iso:country":"US",
    "sg:address":"7755 Hall Rd",
    "sg:city":"Fairburn",
    "sg:classifiers":[
        {
            "category":"Professional",
            "subcategory":"Art Services",
            "type":"Services"
        }
    ],
    "sg:phone":"+1 678 200 6084",
    "sg:postcode":"30213",
    "sg:province":"GA",
    "sg:tags":[
        "graphic",
        "commercial",
        "designer",
        "artist"
    ],
    "wof:name":"Teel Cook Design, Inc.",
    "wof:placetype":"venue"
},
  "geometry": {"coordinates":[-84.644092,33.629346],"type":"Point"}
}