{
  "type": "Feature",
  "properties": {
    "iso:country":"US",
    "sg:address":"120 Walker Pkwy",
    "sg:city":"Fayetteville",
    "sg:classifiers":[
        {
            "category":"Retail",
            "subcategory":"Car Wash",
            "type":"Services"
        }
    ],
    "sg:phone":"+1 770 461 1787",
    "sg:postcode":"30214",
    "sg:province":"GA",
    "sg:tags":[
        "carwash"
    ],
    "wof:name":"ADS Services",
    "wof:placetype":"venue"
},
  "geometry": {"coordinates":[-84.438732,33.476461],"type":"Point"}
}