{
  "type": "Feature",
  "properties": {
    "iso:country":"US",
    "sg:address":"270 Shannon Way",
    "sg:city":"Lawrenceville",
    "sg:classifiers":[
        {
            "category":"Retail",
            "subcategory":"Auto Repair",
            "type":"Services"
        }
    ],
    "sg:phone":"+1 770 513 9035",
    "sg:postcode":"30044",
    "sg:province":"GA",
    "wof:name":"J & B Automotive",
    "wof:placetype":"venue"
},
  "geometry": {"coordinates":[-84.063301,33.9277],"type":"Point"}
}