{
  "type": "Feature",
  "properties": {
    "iso:country":"US",
    "sg:address":"2190 Winterville Rd",
    "sg:city":"Athens",
    "sg:classifiers":[
        {
            "category":"Government",
            "subcategory":"Office",
            "type":"Public Place"
        }
    ],
    "sg:phone":"+1 706 353 4525",
    "sg:postcode":"30683",
    "sg:province":"GA",
    "sg:tags":[
        "federal",
        "security"
    ],
    "wof:name":"US Army Dept",
    "wof:placetype":"venue"
},
  "geometry": {"coordinates":[-83.32188499999999,33.955581],"type":"Point"}
}