{
  "type": "Feature",
  "properties": {
    "addr:full":"675 Church St Royston GA 30662",
    "addr:housenumber":"675",
    "addr:postcode":"30662",
    "addr:street":"Church St",
    "iso:country":"US",
    "sg:address":"675 Church St",
    "sg:city":"Royston",
    "sg:classifiers":[
        {
            "category":"Banks & Credit Unions",
            "subcategory":"Bank",
            "type":"Services"
        }
    ],
    "sg:phone":"+1 706 245 6142",
    "sg:postcode":"30662",
    "sg:province":"GA",
    "sg:tags":[
        "loan"
    ],
    "sg:website":"www.aggeorgia.com",
    "wof:name":"Ag Georgia Farm Credit",
    "wof:placetype":"venue"
},
  "geometry": {"coordinates":[-83.110686,34.281841],"type":"Point"}
}