{
  "type": "Feature",
  "properties": {
    "iso:country":"US",
    "sg:address":"146 Homer Dr",
    "sg:city":"Baldwin",
    "sg:classifiers":[
        {
            "category":"Autos & Motor Vehicles",
            "subcategory":"Automobile Sales",
            "type":"Retail Goods"
        }
    ],
    "sg:phone":"+1 706 778 7160",
    "sg:postcode":"30511",
    "sg:province":"GA",
    "sg:tags":[
        "car",
        "dealer"
    ],
    "wof:name":"Robert Bellamy Used Cars",
    "wof:placetype":"venue"
},
  "geometry": {"coordinates":[-83.53241800000001,34.49582],"type":"Point"}
}