{
  "type": "Feature",
  "properties": {
    "iso:country":"US",
    "sg:address":"61 Old Canton Rd",
    "sg:city":"Marietta",
    "sg:classifiers":[
        {
            "category":"Sports & Exercise",
            "subcategory":"Golf",
            "type":"Entertainment"
        }
    ],
    "sg:phone":"+1 770 565 5642",
    "sg:postcode":"30068",
    "sg:province":"GA",
    "sg:tags":[
        "course",
        "public"
    ],
    "sg:website":"www.southgolf.com",
    "wof:name":"Great Georgia Golf Inc",
    "wof:placetype":"venue"
},
  "geometry": {"coordinates":[-84.46217900000001,33.94937],"type":"Point"}
}