{
  "type": "Feature",
  "properties": {
    "iso:country":"US",
    "sg:address":"2500 Dallas Hwy",
    "sg:city":"Marietta",
    "sg:classifiers":[
        {
            "category":"Banks & Credit Unions",
            "subcategory":"Bank",
            "type":"Services"
        }
    ],
    "sg:phone":"+1 770 919 0845",
    "sg:postcode":"30064",
    "sg:province":"GA",
    "wof:name":"Washington Mutual",
    "wof:placetype":"venue"
},
  "geometry": {"coordinates":[-84.627056,33.946463],"type":"Point"}
}