{
  "type": "Feature",
  "properties": {
    "addr:full":"3404 Deans Bridge Rd Augusta GA 30906",
    "addr:housenumber":"3404",
    "addr:postcode":"30906",
    "addr:street":"Deans Bridge Rd",
    "iso:country":"US",
    "sg:address":"3404 Deans Bridge Rd",
    "sg:city":"Augusta",
    "sg:classifiers":[
        {
            "category":"Personal",
            "subcategory":"Beauty Salon",
            "type":"Services"
        }
    ],
    "sg:phone":"+1 706 798 6038",
    "sg:postcode":"30906",
    "sg:province":"GA",
    "sg:tags":[
        "shop"
    ],
    "wof:name":"Ce Ce Beauty Salon",
    "wof:placetype":"venue"
},
  "geometry": {"coordinates":[-82.080635,33.418545],"type":"Point"}
}