{
  "type": "Feature",
  "properties": {
    "addr:full":"923 W Franklin St Sylvester GA 31791",
    "addr:housenumber":"923",
    "addr:postcode":"31791",
    "addr:street":"W Franklin St",
    "iso:country":"US",
    "sg:address":"923 W Franklin St",
    "sg:city":"Sylvester",
    "sg:classifiers":[
        {
            "category":"Food & Beverages",
            "subcategory":"Groceries & Convenience Stores",
            "type":"Retail Goods"
        }
    ],
    "sg:phone":"+1 229 776 5552",
    "sg:postcode":"31791",
    "sg:province":"GA",
    "wof:name":"EZ-Corner",
    "wof:placetype":"venue"
},
  "geometry": {"coordinates":[-83.85263999999999,31.53185],"type":"Point"}
}