{
  "type": "Feature",
  "properties": {
    "addr:full":"2728 Watson Blvd Warner Robins GA 31093",
    "addr:housenumber":"2728",
    "addr:postcode":"31093",
    "addr:street":"Watson Blvd",
    "iso:country":"US",
    "sg:address":"2728 Watson Blvd",
    "sg:city":"Warner Robins",
    "sg:classifiers":[
        {
            "category":"Food & Beverages",
            "subcategory":"Specialty",
            "type":"Retail Goods"
        }
    ],
    "sg:phone":"+1 478 953 7480",
    "sg:postcode":"31093",
    "sg:province":"GA",
    "sg:website":"chefaudrey.com",
    "wof:name":"Chef Audrey's Bistro and Bakery",
    "wof:placetype":"venue"
},
  "geometry": {"coordinates":[-83.67061200000001,32.618298],"type":"Point"}
}