{
  "type": "Feature",
  "properties": {
    "iso:country":"US",
    "sg:address":"152 Jones St",
    "sg:city":"Cartersville",
    "sg:classifiers":[
        {
            "category":"Freight",
            "type":"Transportation"
        }
    ],
    "sg:phone":"+1 770 382 7886",
    "sg:postcode":"30120",
    "sg:province":"GA",
    "sg:tags":[
        "delivery"
    ],
    "wof:name":"Wilco Deliveries",
    "wof:placetype":"venue"
},
  "geometry": {"coordinates":[-84.803498,34.17141],"type":"Point"}
}