{
  "type": "Feature",
  "properties": {
    "iso:country":"US",
    "sg:address":"40 N Main St",
    "sg:city":"Moultrie",
    "sg:classifiers":[
        {
            "category":"Professional",
            "subcategory":"Accounting & Tax Preparation",
            "type":"Services"
        }
    ],
    "sg:phone":"+1 229 985 1978",
    "sg:postcode":"31768",
    "sg:province":"GA",
    "sg:tags":[
        "accountant"
    ],
    "wof:name":"Vines Ladson Wear & Mangum",
    "wof:placetype":"venue"
},
  "geometry": {"coordinates":[-83.78877799999999,31.180567],"type":"Point"}
}