{
  "type": "Feature",
  "properties": {
    "addr:full":"3647 Clearview Pkwy Doraville GA 30340",
    "addr:housenumber":"3647",
    "addr:postcode":"30340",
    "addr:street":"Clearview Pkwy",
    "iso:country":"US",
    "sg:address":"3647 Clearview Pkwy",
    "sg:city":"Doraville",
    "sg:classifiers":[
        {
            "category":"Building & Trades",
            "subcategory":"Locksmith",
            "type":"Services"
        }
    ],
    "sg:phone":"+1 877 563 4976",
    "sg:postcode":"30340",
    "sg:province":"GA",
    "sg:tags":[
        "key"
    ],
    "wof:name":"A 1 Emergency Locksmith",
    "wof:placetype":"venue"
},
  "geometry": {"coordinates":[-84.27109,33.899273],"type":"Point"}
}