{
  "type": "Feature",
  "properties": {
    "iso:country":"US",
    "sg:address":"820 N Houston Lake Blvd",
    "sg:city":"Centerville",
    "sg:classifiers":[
        {
            "category":"Food & Beverages",
            "subcategory":"Groceries & Convenience Stores",
            "type":"Retail Goods"
        }
    ],
    "sg:phone":"+1 478 333 6633",
    "sg:postcode":"31028",
    "sg:province":"GA",
    "sg:website":"www.stopandshop.com",
    "wof:name":"Stop & Shop",
    "wof:placetype":"venue"
},
  "geometry": {"coordinates":[-83.689447,32.63979],"type":"Point"}
}