{
  "type": "Feature",
  "properties": {
    "addr:full":"3831 Angora Pl Duluth GA 30096",
    "addr:housenumber":"3831",
    "addr:postcode":"30096",
    "addr:street":"Angora Pl",
    "iso:country":"US",
    "sg:address":"3831 Angora Pl",
    "sg:city":"Duluth",
    "sg:classifiers":[
        {
            "category":"Shopping",
            "subcategory":"Computers & Home Electronics",
            "type":"Retail Goods"
        }
    ],
    "sg:phone":"+1 678 575 6255",
    "sg:postcode":"30096",
    "sg:province":"GA",
    "wof:name":"Jays Computer",
    "wof:placetype":"venue"
},
  "geometry": {"coordinates":[-84.153029,33.966218],"type":"Point"}
}