{
  "type": "Feature",
  "properties": {
    "iso:country":"US",
    "sg:address":"2717 Cusseta Rd",
    "sg:city":"Columbus",
    "sg:classifiers":[
        {
            "category":"Organizations",
            "subcategory":"Religious Organization",
            "type":"Services"
        }
    ],
    "sg:phone":"+1 706 689 3799",
    "sg:postcode":"31903",
    "sg:province":"GA",
    "sg:tags":[
        "church"
    ],
    "wof:name":"Macedonia Baptist Church",
    "wof:placetype":"venue"
},
  "geometry": {"coordinates":[-84.953318,32.444603],"type":"Point"}
}