{
  "type": "Feature",
  "properties": {
    "iso:country":"US",
    "sg:address":"152 Briar Creek Trl",
    "sg:city":"Lizella",
    "sg:classifiers":[
        {
            "category":"Building & Trades",
            "subcategory":"Construction",
            "type":"Services"
        }
    ],
    "sg:phone":"+1 478 742 3213",
    "sg:postcode":"31052",
    "sg:province":"GA",
    "sg:tags":[
        "contractor"
    ],
    "wof:name":"Bens Gutter Service",
    "wof:placetype":"venue"
},
  "geometry": {"coordinates":[-83.792586,32.796347],"type":"Point"}
}