{
  "type": "Feature",
  "properties": {
    "iso:country":"US",
    "sg:address":"1005 Tyson Ave",
    "sg:city":"Tifton",
    "sg:classifiers":[
        {
            "category":"Building & Trades",
            "subcategory":"Landscaping Services",
            "type":"Services"
        }
    ],
    "sg:phone":"+1 229 387 6164",
    "sg:postcode":"31794",
    "sg:province":"GA",
    "sg:tags":[
        "landscape"
    ],
    "wof:name":"Ipsi",
    "wof:placetype":"venue"
},
  "geometry": {"coordinates":[-83.49937199999999,31.454173],"type":"Point"}
}