{
  "type": "Feature",
  "properties": {
    "addr:full":"1 Westbrook Cir Valdosta GA 31602",
    "addr:housenumber":"1",
    "addr:postcode":"31602",
    "addr:street":"Westbrook Cir",
    "iso:country":"US",
    "sg:address":"1 Westbrook Cir",
    "sg:city":"Valdosta",
    "sg:classifiers":[
        {
            "category":"Real Estate",
            "subcategory":"Real Estate Services",
            "type":"Services"
        },
        {
            "category":"Real Estate",
            "subcategory":"Real Estate Agent",
            "type":"Services"
        }
    ],
    "sg:phone":"+1 229 242 6102",
    "sg:postcode":"31602",
    "sg:province":"GA",
    "sg:tags":[
        "buyer",
        "broker"
    ],
    "wof:name":"Golivesky Lamar H Rl Est",
    "wof:placetype":"venue"
},
  "geometry": {"coordinates":[-83.31604799999999,30.850281],"type":"Point"}
}