{
  "type": "Feature",
  "properties": {
    "addr:full":"2020 Howell Mill Rd Atlanta GA 30318",
    "addr:housenumber":"2020",
    "addr:postcode":"30318",
    "addr:street":"Howell Mill Rd",
    "iso:country":"US",
    "sg:address":"2020 Howell Mill Rd",
    "sg:city":"Atlanta",
    "sg:classifiers":[
        {
            "category":"Professional",
            "subcategory":"Management & Consulting",
            "type":"Services"
        }
    ],
    "sg:phone":"+1 404 352 3010",
    "sg:postcode":"30318",
    "sg:province":"GA",
    "sg:tags":[
        "marketing",
        "program"
    ],
    "wof:name":"Higher Vision Marketing & Prom",
    "wof:placetype":"venue"
},
  "geometry": {"coordinates":[-84.41270299999999,33.810577],"type":"Point"}
}