{
  "type": "Feature",
  "properties": {
    "iso:country":"US",
    "sg:address":"435 Franklin Rd NE",
    "sg:city":"Atlanta",
    "sg:classifiers":[
        {
            "category":"Manufacturing",
            "subcategory":"Printing",
            "type":"Manufacturing & Wholesale Goods"
        }
    ],
    "sg:phone":"+1 404 250 0404",
    "sg:postcode":"30342",
    "sg:province":"GA",
    "sg:tags":[
        "newsletter"
    ],
    "wof:name":"Lacour-Niesen Visuals Inc",
    "wof:placetype":"venue"
},
  "geometry": {"coordinates":[-84.37356,33.886171],"type":"Point"}
}