{
  "type": "Feature",
  "properties": {
    "iso:country":"US",
    "sg:address":"1246 Middleton Church Rd",
    "sg:city":"Elberton",
    "sg:classifiers":[
        {
            "category":"Professional",
            "type":"Services"
        }
    ],
    "sg:phone":"+1 706 283 9821",
    "sg:postcode":"30635",
    "sg:province":"GA",
    "wof:name":"Specialty Stone Services",
    "wof:placetype":"venue"
},
  "geometry": {"coordinates":[-82.758854,34.103209],"type":"Point"}
}