{
  "type": "Feature",
  "properties": {
    "iso:country":"US",
    "sg:address":"2940 Pacific Dr",
    "sg:city":"Norcross",
    "sg:classifiers":[
        {
            "category":"Manufacturing",
            "subcategory":"Retail Goods",
            "type":"Manufacturing & Wholesale Goods"
        }
    ],
    "sg:phone":"+1 678 282 1000",
    "sg:postcode":"30071",
    "sg:province":"GA",
    "sg:tags":[
        "manufacturer"
    ],
    "sg:website":"www.mysterlinghome.com",
    "wof:name":"Sterling Industries",
    "wof:placetype":"venue"
},
  "geometry": {"coordinates":[-84.23487799999999,33.937491],"type":"Point"}
}