{
  "type": "Feature",
  "properties": {
    "iso:country":"US",
    "sg:address":"8 Lenox Pointe NE",
    "sg:city":"Atlanta",
    "sg:classifiers":[
        {
            "category":"Professional",
            "subcategory":"Lawyer & Legal Services",
            "type":"Services"
        }
    ],
    "sg:phone":"+1 404 219 7961",
    "sg:postcode":"30324",
    "sg:province":"GA",
    "sg:tags":[
        "attorney"
    ],
    "wof:name":"John C Tyler",
    "wof:placetype":"venue"
},
  "geometry": {"coordinates":[-84.353604,33.826353],"type":"Point"}
}