{
  "type": "Feature",
  "properties": {
    "iso:country":"US",
    "sg:address":"601 Carroll Ln",
    "sg:city":"Sylvester",
    "sg:classifiers":[
        {
            "category":"Social Services",
            "subcategory":"Child Care",
            "type":"Services"
        }
    ],
    "sg:phone":"+1 229 776 4500",
    "sg:postcode":"31791",
    "sg:province":"GA",
    "sg:tags":[
        "day"
    ],
    "wof:name":"Learning Tree Day Care",
    "wof:placetype":"venue"
},
  "geometry": {"coordinates":[-83.84560399999999,31.535414],"type":"Point"}
}