{
  "type": "Feature",
  "properties": {
    "addr:full":"110 E Main St Woodstock GA 30188",
    "addr:housenumber":"110",
    "addr:postcode":"30188",
    "addr:street":"E Main St",
    "iso:country":"US",
    "sg:address":"110 E Main St",
    "sg:city":"Woodstock",
    "sg:classifiers":[
        {
            "category":"Professional",
            "subcategory":"Accounting & Tax Preparation",
            "type":"Services"
        }
    ],
    "sg:phone":"+1 770 926 3035",
    "sg:postcode":"30188",
    "sg:province":"GA",
    "sg:tags":[
        "return"
    ],
    "wof:name":"Elyse Wall-Greeson",
    "wof:placetype":"venue"
},
  "geometry": {"coordinates":[-84.519026,34.101559],"type":"Point"}
}