{
  "type": "Feature",
  "properties": {
    "addr:full":"3413 Tarragon Dr Decatur GA 30034",
    "addr:housenumber":"3413",
    "addr:postcode":"30034",
    "addr:street":"Tarragon Dr",
    "iso:country":"US",
    "sg:address":"3413 Tarragon Dr",
    "sg:city":"Decatur",
    "sg:classifiers":[
        {
            "category":"Professional",
            "subcategory":"Business Services",
            "type":"Services"
        }
    ],
    "sg:phone":"+1 770 323 9799",
    "sg:postcode":"30034",
    "sg:province":"GA",
    "wof:name":"Fine Touch",
    "wof:placetype":"venue"
},
  "geometry": {"coordinates":[-84.208291,33.683358],"type":"Point"}
}