{
  "type": "Feature",
  "properties": {
    "addr:full":"2080 Timothy Rd Athens GA 30606",
    "addr:housenumber":"2080",
    "addr:postcode":"30606",
    "addr:street":"Timothy Rd",
    "iso:country":"US",
    "sg:address":"2080 Timothy Rd",
    "sg:city":"Athens",
    "sg:classifiers":[
        {
            "category":"Retail",
            "subcategory":"Auto Rental",
            "type":"Services"
        }
    ],
    "sg:phone":"+1 706 543 0771",
    "sg:postcode":"30606",
    "sg:province":"GA",
    "sg:tags":[
        "passenger",
        "car"
    ],
    "wof:name":"Enterprise Rent A Car",
    "wof:placetype":"venue"
},
  "geometry": {"coordinates":[-83.44480900000001,33.936076],"type":"Point"}
}