{
  "type": "Feature",
  "properties": {
    "addr:full":"2569 Iris Dr SE Conyers GA 30013",
    "addr:housenumber":"2569",
    "addr:postcode":"30013",
    "addr:street":"Iris Dr Se",
    "iso:country":"US",
    "sg:address":"2569 Iris Dr SE",
    "sg:city":"Conyers",
    "sg:classifiers":[
        {
            "category":"Building & Trades",
            "subcategory":"Construction",
            "type":"Services"
        }
    ],
    "sg:phone":"+1 770 785 7007",
    "sg:postcode":"30013",
    "sg:province":"GA",
    "sg:tags":[
        "contractor"
    ],
    "wof:name":"Atlanta Ram Jack Inc",
    "wof:placetype":"venue"
},
  "geometry": {"coordinates":[-83.96576899999999,33.630801],"type":"Point"}
}