{
  "type": "Feature",
  "properties": {
    "addr:full":"274 Crossroads Estates Dr Newnan GA 30265",
    "addr:housenumber":"274",
    "addr:postcode":"30265",
    "addr:street":"Crossroads Estates Dr",
    "iso:country":"US",
    "sg:address":"274 Crossroads Estates Dr",
    "sg:city":"Newnan",
    "sg:classifiers":[
        {
            "category":"Communications",
            "subcategory":"Radio Station",
            "type":"Services"
        }
    ],
    "sg:phone":"+1 770 254 1824",
    "sg:postcode":"30265",
    "sg:province":"GA",
    "sg:tags":[
        "broadcast"
    ],
    "wof:name":"Mickey",
    "wof:placetype":"venue"
},
  "geometry": {"coordinates":[-84.68241500000001,33.402148],"type":"Point"}
}