{
  "type": "Feature",
  "properties": {
    "iso:country":"US",
    "sg:address":"1265 Old Alpharetta Rd",
    "sg:city":"Alpharetta",
    "sg:classifiers":[
        {
            "category":"Manufacturing",
            "subcategory":"Metals",
            "type":"Manufacturing & Wholesale Goods"
        }
    ],
    "sg:phone":"+1 770 751 1875",
    "sg:postcode":"30005",
    "sg:province":"GA",
    "sg:tags":[
        "hardware"
    ],
    "sg:website":"www.kingfastener.com",
    "wof:name":"J O King Inc",
    "wof:placetype":"venue"
},
  "geometry": {"coordinates":[-84.195161,34.107711],"type":"Point"}
}