{
  "type": "Feature",
  "properties": {
    "iso:country":"US",
    "sg:address":"102 Crestwood Dr",
    "sg:city":"Gordon",
    "sg:classifiers":[
        {
            "category":"Manufacturing",
            "subcategory":"Apparel",
            "type":"Manufacturing & Wholesale Goods"
        }
    ],
    "sg:phone":"+1 478 452 3492",
    "sg:postcode":"31031",
    "sg:province":"GA",
    "wof:name":"Creations By Charis",
    "wof:placetype":"venue"
},
  "geometry": {"coordinates":[-83.26694000000001,32.996476],"type":"Point"}
}