{
  "type": "Feature",
  "properties": {
    "addr:full":"1337 Old Alabama Rd SW Mableton GA 30126",
    "addr:housenumber":"1337",
    "addr:postcode":"30126",
    "addr:street":"Old Alabama Rd Sw",
    "iso:country":"US",
    "sg:address":"1337 Old Alabama Rd SW",
    "sg:city":"Mableton",
    "sg:classifiers":[
        {
            "category":"Organizations",
            "subcategory":"Religious Organization",
            "type":"Services"
        }
    ],
    "sg:phone":"+1 770 941 1885",
    "sg:postcode":"30126",
    "sg:province":"GA",
    "sg:website":"www.glenforestbaptist.org",
    "wof:name":"Glen Forest Baptist Church",
    "wof:placetype":"venue"
},
  "geometry": {"coordinates":[-84.594812,33.808268],"type":"Point"}
}