{
  "type": "Feature",
  "properties": {
    "iso:country":"US",
    "sg:address":"754 Old Social Cir",
    "sg:city":"Social Circle",
    "sg:classifiers":[
        {
            "category":"Manufacturing",
            "subcategory":"Rubber & Plastics",
            "type":"Manufacturing & Wholesale Goods"
        }
    ],
    "sg:phone":"+1 770 464 2603",
    "sg:postcode":"30025",
    "sg:province":"GA",
    "sg:tags":[
        "insulation",
        "material"
    ],
    "wof:name":"Precision Foam Fabricators Inc",
    "wof:placetype":"venue"
},
  "geometry": {"coordinates":[-83.72529400000001,33.63449],"type":"Point"}
}