{
  "type": "Feature",
  "properties": {
    "addr:full":"436 Newnan Rd Carrollton GA 30117",
    "addr:housenumber":"436",
    "addr:postcode":"30117",
    "addr:street":"Newnan Rd",
    "iso:country":"US",
    "sg:address":"436 Newnan Rd",
    "sg:city":"Carrollton",
    "sg:classifiers":[
        {
            "category":"Banks & Credit Unions",
            "subcategory":"Financial Services",
            "type":"Services"
        },
        {
            "category":"Shopping",
            "subcategory":"Pawn Shop",
            "type":"Retail Goods"
        }
    ],
    "sg:phone":"+1 770 830 7009",
    "sg:postcode":"30117",
    "sg:province":"GA",
    "sg:tags":[
        "loan",
        "pawnbroker"
    ],
    "wof:name":"Fast Cash Title Pawn",
    "wof:placetype":"venue"
},
  "geometry": {"coordinates":[-85.058398,33.576384],"type":"Point"}
}