{
  "type": "Feature",
  "properties": {
    "addr:full":"9015 Campground Rd Matthews GA 30818",
    "addr:postcode":"9015;30818",
    "addr:street":"Campground Rd",
    "iso:country":"US",
    "sg:address":"9015 Campground Rd",
    "sg:city":"Matthews",
    "sg:classifiers":[
        {
            "category":"Organizations",
            "subcategory":"Religious Organization",
            "type":"Services"
        }
    ],
    "sg:phone":"+1 404 547 0054",
    "sg:postcode":"30818",
    "sg:province":"GA",
    "wof:name":"Flat Rock Mssnary Bptst Church",
    "wof:placetype":"venue"
},
  "geometry": {"coordinates":[-82.297449,33.237737],"type":"Point"}
}