{
  "type": "Feature",
  "properties": {
    "addr:full":"920 Woodstock Rd Roswell GA 30075",
    "addr:housenumber":"920",
    "addr:postcode":"30075",
    "addr:street":"Woodstock Rd",
    "iso:country":"US",
    "sg:address":"920 Woodstock Rd",
    "sg:city":"Roswell",
    "sg:classifiers":[
        {
            "category":"Home & Garden",
            "subcategory":"Home Furnishings",
            "type":"Retail Goods"
        }
    ],
    "sg:phone":"+1 770 650 8477",
    "sg:postcode":"30075",
    "sg:province":"GA",
    "wof:name":"Touch of Class",
    "wof:placetype":"venue"
},
  "geometry": {"coordinates":[-84.393901,34.062434],"type":"Point"}
}