{
  "type": "Feature",
  "properties": {
    "addr:full":"4461 Lambert Dr Kennesaw GA 30144",
    "addr:housenumber":"4461",
    "addr:postcode":"30144",
    "addr:street":"Lambert Dr",
    "iso:country":"US",
    "sg:address":"4461 Lambert Dr",
    "sg:city":"Kennesaw",
    "sg:classifiers":[
        {
            "category":"Professional",
            "subcategory":"Business Services",
            "type":"Services"
        }
    ],
    "sg:phone":"+1 770 926 7502",
    "sg:postcode":"30144",
    "sg:province":"GA",
    "wof:name":"Rudy Enterprises Inc",
    "wof:placetype":"venue"
},
  "geometry": {"coordinates":[-84.56440499999999,34.060541],"type":"Point"}
}