{
  "type": "Feature",
  "properties": {
    "iso:country":"US",
    "sg:address":"2819 Old Dawson Rd",
    "sg:city":"Albany",
    "sg:classifiers":[
        {
            "category":"Banks & Credit Unions",
            "subcategory":"Bank",
            "type":"Services"
        }
    ],
    "sg:phone":"+1 229 430 7040",
    "sg:postcode":"31707",
    "sg:province":"GA",
    "sg:tags":[
        "state",
        "commercial"
    ],
    "wof:name":"Security Bank & Trust Co",
    "wof:placetype":"venue"
},
  "geometry": {"coordinates":[-84.221906,31.613584],"type":"Point"}
}