{
  "type": "Feature",
  "properties": {
    "addr:full":"2903 Bankshill Row Atlanta GA 30319",
    "addr:housenumber":"2903",
    "addr:postcode":"30319",
    "addr:street":"Bankshill Row",
    "iso:country":"US",
    "sg:address":"2903 Bankshill Row",
    "sg:city":"Atlanta",
    "sg:classifiers":[
        {
            "category":"Professional",
            "subcategory":"Business Services",
            "type":"Services"
        }
    ],
    "sg:phone":"+1 404 239 0108",
    "sg:postcode":"30319",
    "sg:province":"GA",
    "wof:name":"Duncan Interiors Ltd",
    "wof:placetype":"venue"
},
  "geometry": {"coordinates":[-84.340423,33.872666],"type":"Point"}
}