{
  "type": "Feature",
  "properties": {
    "addr:full":"12370 Arnold Mill Rd Alpharetta GA 30004",
    "addr:housenumber":"12370",
    "addr:postcode":"30004",
    "addr:street":"Arnold Mill Rd",
    "iso:country":"US",
    "sg:address":"12370 Arnold Mill Rd",
    "sg:city":"Alpharetta",
    "sg:classifiers":[
        {
            "category":"Retail",
            "subcategory":"Laundry & Dry Cleaning",
            "type":"Services"
        }
    ],
    "sg:phone":"+1 770 663 7919",
    "sg:postcode":"30004",
    "sg:province":"GA",
    "sg:tags":[
        "cleaners",
        "plant",
        "drycleaning"
    ],
    "wof:name":"Crabapple Cleaners",
    "wof:placetype":"venue"
},
  "geometry": {"coordinates":[-84.357401,34.082006],"type":"Point"}
}