{
  "type": "Feature",
  "properties": {
    "addr:full":"3867 Holcomb Bridge Rd Norcross GA 30092",
    "addr:housenumber":"3867",
    "addr:postcode":"30092",
    "addr:street":"Holcomb Bridge Rd",
    "iso:country":"US",
    "sg:address":"3867 Holcomb Bridge Rd",
    "sg:city":"Norcross",
    "sg:classifiers":[
        {
            "category":"Manufacturing",
            "subcategory":"Printing",
            "type":"Manufacturing & Wholesale Goods"
        }
    ],
    "sg:phone":"+1 770 446 0088",
    "sg:postcode":"30092",
    "sg:province":"GA",
    "sg:tags":[
        "multimedia"
    ],
    "wof:name":"Prime Media Intl Nc",
    "wof:placetype":"venue"
},
  "geometry": {"coordinates":[-84.253714,33.964984],"type":"Point"}
}