{
  "type": "Feature",
  "properties": {
    "iso:country":"US",
    "sg:address":"533 Newcastle St",
    "sg:city":"Brunswick",
    "sg:classifiers":[
        {
            "category":"Organizations",
            "subcategory":"Religious Organization",
            "type":"Services"
        }
    ],
    "sg:phone":"+1 912 265 6831",
    "sg:postcode":"31520",
    "sg:province":"GA",
    "wof:name":"Southside Baptist Church",
    "wof:placetype":"venue"
},
  "geometry": {"coordinates":[-81.490613,31.135896],"type":"Point"}
}