{
  "type": "Feature",
  "properties": {
    "addr:full":"3018 Shenandoah Valley Rd NE Atlanta GA 30345",
    "addr:housenumber":"3018",
    "addr:postcode":"30345",
    "addr:street":"Shenandoah Valley Rd Ne",
    "iso:country":"US",
    "sg:address":"3018 Shenandoah Valley Rd NE",
    "sg:city":"Atlanta",
    "sg:classifiers":[
        {
            "category":"Farming",
            "subcategory":"Fish & Marine Products",
            "type":"Manufacturing & Wholesale Goods"
        }
    ],
    "sg:phone":"+1 770 493 6970",
    "sg:postcode":"30345",
    "sg:province":"GA",
    "sg:tags":[
        "wildlife",
        "management",
        "refuge"
    ],
    "wof:name":"National Wild Turkey Federation",
    "wof:placetype":"venue"
},
  "geometry": {"coordinates":[-84.26582500000001,33.861259],"type":"Point"}
}