{
  "type": "Feature",
  "properties": {
    "iso:country":"US",
    "sg:address":"2705 Pechtre Indstrl Blvd",
    "sg:city":"Duluth",
    "sg:classifiers":[
        {
            "category":"Sports & Exercise",
            "subcategory":"Golf",
            "type":"Entertainment"
        }
    ],
    "sg:phone":"+1 770 205 7070",
    "sg:postcode":"30097",
    "sg:province":"GA",
    "wof:name":"Hampton Golf Village",
    "wof:placetype":"venue"
},
  "geometry": {"coordinates":[-84.142197,34.023201],"type":"Point"}
}