{
  "type": "Feature",
  "properties": {
    "iso:country":"US",
    "sg:address":"2500 Cumberland Pkwy SE",
    "sg:city":"Atlanta",
    "sg:classifiers":[
        {
            "category":"Real Estate",
            "subcategory":"Architect",
            "type":"Services"
        }
    ],
    "sg:phone":"+1 770 874 7382",
    "sg:postcode":"30339",
    "sg:province":"GA",
    "sg:tags":[
        "architects'",
        "specification",
        "construction",
        "builders'",
        "architectural"
    ],
    "wof:name":"Elbert N Griffin",
    "wof:placetype":"venue"
},
  "geometry": {"coordinates":[-84.476578,33.865681],"type":"Point"}
}