{
  "type": "Feature",
  "properties": {
    "iso:country":"US",
    "sg:address":"1200 Tradeport Blvd",
    "sg:city":"Atlanta",
    "sg:classifiers":[
        {
            "category":"Government",
            "subcategory":"Office",
            "type":"Public Place"
        }
    ],
    "sg:phone":"+1 404 730 6100",
    "sg:postcode":"30354",
    "sg:province":"GA",
    "sg:tags":[
        "transportation"
    ],
    "wof:name":"Motor Vehicles Div of",
    "wof:placetype":"venue"
},
  "geometry": {"coordinates":[-84.39394900000001,33.649972],"type":"Point"}
}