{
  "type": "Feature",
  "properties": {
    "iso:country":"US",
    "sg:address":"5800 Moon Rd",
    "sg:city":"Columbus",
    "sg:classifiers":[
        {
            "category":"Wholesale",
            "subcategory":"Construction Materials",
            "type":"Manufacturing & Wholesale Goods"
        }
    ],
    "sg:phone":"+1 706 565 7666",
    "sg:postcode":"31909",
    "sg:province":"GA",
    "sg:tags":[
        "trade",
        "fence",
        "contractor"
    ],
    "wof:name":"A Atlas Fence Co",
    "wof:placetype":"venue"
},
  "geometry": {"coordinates":[-84.925422,32.52805],"type":"Point"}
}