{
  "type": "Feature",
  "properties": {
    "addr:full":"724 Memorial Drive SE Atlanta GA 30316",
    "addr:housenumber":"724",
    "addr:postcode":"30316",
    "addr:street":"Memorial Drive Se",
    "iso:country":"US",
    "sg:address":"724 Memorial Drive SE",
    "sg:city":"Atlanta",
    "sg:classifiers":[
        {
            "category":"Building & Trades",
            "subcategory":"Construction",
            "type":"Services"
        }
    ],
    "sg:phone":"+1 404 207 1370",
    "sg:postcode":"30316",
    "sg:province":"GA",
    "sg:tags":[
        "contractor"
    ],
    "wof:name":"Collins Ruby Stockade Homes",
    "wof:placetype":"venue"
},
  "geometry": {"coordinates":[-84.36372799999999,33.74655],"type":"Point"}
}