{
  "type": "Feature",
  "properties": {
    "addr:full":"5700 Glenridge Dr NE Atlanta GA 30328",
    "addr:housenumber":"5700",
    "addr:postcode":"30328",
    "addr:street":"Glenridge Dr Ne",
    "iso:country":"US",
    "sg:address":"5700 Glenridge Dr NE",
    "sg:city":"Atlanta",
    "sg:classifiers":[
        {
            "category":"Building & Trades",
            "subcategory":"Cleaning & Sanitation",
            "type":"Services"
        }
    ],
    "sg:phone":"+1 404 625 2096",
    "sg:postcode":"30328",
    "sg:province":"GA",
    "sg:tags":[
        "ventilating",
        "system"
    ],
    "wof:name":"Hvac Cleaning Technologies",
    "wof:placetype":"venue"
},
  "geometry": {"coordinates":[-84.361817,33.910748],"type":"Point"}
}