{
  "type": "Feature",
  "properties": {
    "addr:full":"732 Wellington Dr Byron GA 31008",
    "addr:housenumber":"732",
    "addr:postcode":"31008",
    "addr:street":"Wellington Dr",
    "iso:country":"US",
    "sg:address":"732 Wellington Dr",
    "sg:city":"Byron",
    "sg:classifiers":[
        {
            "category":"Retail",
            "subcategory":"Auto Repair",
            "type":"Services"
        }
    ],
    "sg:phone":"+1 478 956 1190",
    "sg:postcode":"31008",
    "sg:province":"GA",
    "sg:tags":[
        "automotive",
        "wrecker"
    ],
    "wof:name":"Action 24 Hour Towing & Rcvry",
    "wof:placetype":"venue"
},
  "geometry": {"coordinates":[-83.766876,32.697075],"type":"Point"}
}