{
  "type": "Feature",
  "properties": {
    "iso:country":"US",
    "sg:address":"1055 Red Oak Dr",
    "sg:city":"Macon",
    "sg:classifiers":[
        {
            "category":"Insurance",
            "subcategory":"Insurance Agent",
            "type":"Services"
        }
    ],
    "sg:phone":"+1 478 477 4645",
    "sg:postcode":"31204",
    "sg:province":"GA",
    "sg:tags":[
        "adjuster"
    ],
    "wof:name":"Bridge Water Group",
    "wof:placetype":"venue"
},
  "geometry": {"coordinates":[-83.670221,32.894813],"type":"Point"}
}