{
  "type": "Feature",
  "properties": {
    "iso:country":"US",
    "sg:address":"3633 Wheeler Rd",
    "sg:city":"Augusta",
    "sg:classifiers":[
        {
            "category":"Recreation",
            "type":"Entertainment"
        }
    ],
    "sg:phone":"+1 706 364 4250",
    "sg:postcode":"30909",
    "sg:province":"GA",
    "sg:tags":[
        "ticket"
    ],
    "sg:website":"www.ticketdaddy.com",
    "wof:name":"TICKETDADDY.COM",
    "wof:placetype":"venue"
},
  "geometry": {"coordinates":[-82.09338,33.482814],"type":"Point"}
}