{
  "type": "Feature",
  "properties": {
    "addr:full":"1185 Country Club Rd Newnan GA 30263",
    "addr:housenumber":"1185",
    "addr:postcode":"30263",
    "addr:street":"Country Club Rd",
    "iso:country":"US",
    "sg:address":"1185 Country Club Rd",
    "sg:city":"Newnan",
    "sg:classifiers":[
        {
            "category":"Building & Trades",
            "subcategory":"Construction",
            "type":"Services"
        }
    ],
    "sg:phone":"+1 770 301 1519",
    "sg:postcode":"30263",
    "sg:province":"GA",
    "sg:tags":[
        "excavation",
        "contractor"
    ],
    "wof:name":"Jackson Bushhogging & Hau",
    "wof:placetype":"venue"
},
  "geometry": {"coordinates":[-84.81093799999999,33.429664],"type":"Point"}
}