{
  "type": "Feature",
  "properties": {
    "iso:country":"US",
    "sg:address":"3457 Duckett Mill Rd",
    "sg:city":"Gainesville",
    "sg:classifiers":[
        {
            "category":"Building & Trades",
            "subcategory":"Construction",
            "type":"Services"
        }
    ],
    "sg:phone":"+1 770 503 9185",
    "sg:postcode":"30506",
    "sg:province":"GA",
    "sg:tags":[
        "residential",
        "nonresidential"
    ],
    "wof:name":"J&L Contracting",
    "wof:placetype":"venue"
},
  "geometry": {"coordinates":[-83.929541,34.313368],"type":"Point"}
}