{
  "type": "Feature",
  "properties": {
    "iso:country":"US",
    "sg:address":"337 S Erwin St",
    "sg:city":"Cartersville",
    "sg:classifiers":[
        {
            "category":"Wholesale",
            "subcategory":"Machinery & Supplies",
            "type":"Manufacturing & Wholesale Goods"
        }
    ],
    "sg:phone":"+1 770 386 3026",
    "sg:postcode":"30120",
    "sg:province":"GA",
    "sg:tags":[
        "bearing"
    ],
    "wof:name":"Applied Industrial Tech Inc",
    "wof:placetype":"venue"
},
  "geometry": {"coordinates":[-84.79414800000001,34.158165],"type":"Point"}
}