{
  "type": "Feature",
  "properties": {
    "addr:full":"1402 Tree Mountain Pkwy Stone Mountain GA 30083",
    "addr:housenumber":"1402",
    "addr:postcode":"30083",
    "addr:street":"Tree Mountain Pkwy",
    "iso:country":"US",
    "sg:address":"1402 Tree Mountain Pkwy",
    "sg:city":"Stone Mountain",
    "sg:classifiers":[
        {
            "category":"Shopping",
            "subcategory":"Clothing, Apparel, & Fashions",
            "type":"Retail Goods"
        }
    ],
    "sg:phone":"+1 770 498 3854",
    "sg:postcode":"30083",
    "sg:province":"GA",
    "wof:name":"Butterbean Design",
    "wof:placetype":"venue"
},
  "geometry": {"coordinates":[-84.178989,33.821139],"type":"Point"}
}