{
  "type": "Feature",
  "properties": {
    "iso:country":"US",
    "sg:address":"2250 Lakeway Dr",
    "sg:city":"Dacula",
    "sg:classifiers":[
        {
            "category":"Professional",
            "subcategory":"Business Services",
            "type":"Services"
        }
    ],
    "sg:phone":"+1 770 827 3698",
    "sg:postcode":"30019",
    "sg:province":"GA",
    "wof:name":"Affordable Professional Home",
    "wof:placetype":"venue"
},
  "geometry": {"coordinates":[-83.922952,34.061995],"type":"Point"}
}