{
  "type": "Feature",
  "properties": {
    "iso:country":"US",
    "sg:address":"830 Professional Center Dr",
    "sg:city":"Eastman",
    "sg:classifiers":[
        {
            "category":"Health Services",
            "subcategory":"Clinic",
            "type":"Services"
        }
    ],
    "sg:phone":"+1 478 374 7654",
    "sg:postcode":"31023",
    "sg:province":"GA",
    "sg:tags":[
        "welfare"
    ],
    "wof:name":"Eastman Internal Medicine",
    "wof:placetype":"venue"
},
  "geometry": {"coordinates":[-83.177846,32.185909],"type":"Point"}
}