{
  "type": "Feature",
  "properties": {
    "iso:country":"US",
    "sg:address":"276 E Main St",
    "sg:city":"Gibson",
    "sg:classifiers":[
        {
            "category":"Sports & Exercise",
            "subcategory":"Gym",
            "type":"Entertainment"
        }
    ],
    "sg:phone":"+1 706 598 3683",
    "sg:postcode":"30810",
    "sg:province":"GA",
    "sg:tags":[
        "gymnasium"
    ],
    "wof:name":"Glascock County Gymnasium",
    "wof:placetype":"venue"
},
  "geometry": {"coordinates":[-82.58386299999999,33.234432],"type":"Point"}
}