{
  "type": "Feature",
  "properties": {
    "iso:country":"US",
    "sg:address":"550 Pharr Rd NE",
    "sg:city":"Atlanta",
    "sg:classifiers":[
        {
            "category":"Communications",
            "subcategory":"Newspaper",
            "type":"Services"
        }
    ],
    "sg:phone":"+1 404 233 0980",
    "sg:postcode":"30305",
    "sg:province":"GA",
    "sg:tags":[
        "print",
        "medium"
    ],
    "wof:name":"Princeton Review",
    "wof:placetype":"venue"
},
  "geometry": {"coordinates":[-84.370373,33.837084],"type":"Point"}
}