{
  "type": "Feature",
  "properties": {
    "iso:country":"US",
    "sg:address":"6 Brandle Cove",
    "sg:city":"Savannah",
    "sg:classifiers":[
        {
            "category":"Personal",
            "type":"Services"
        }
    ],
    "sg:phone":"+1 912 231 0552",
    "sg:postcode":"31405",
    "sg:province":"GA",
    "wof:name":"Sharisma of Weddings",
    "wof:placetype":"venue"
},
  "geometry": {"coordinates":[-81.15249,32.03862],"type":"Point"}
}