{
  "type": "Feature",
  "properties": {
    "iso:country":"US",
    "sg:address":"359 Hearth Pl NW",
    "sg:city":"Lawrenceville",
    "sg:classifiers":[
        {
            "category":"Building & Trades",
            "subcategory":"Construction",
            "type":"Services"
        }
    ],
    "sg:phone":"+1 678 442 1611",
    "sg:postcode":"30043",
    "sg:province":"GA",
    "sg:tags":[
        "contractor"
    ],
    "wof:name":"C&F Drywall",
    "wof:placetype":"venue"
},
  "geometry": {"coordinates":[-84.027145,33.997891],"type":"Point"}
}