{
  "type": "Feature",
  "properties": {
    "iso:country":"US",
    "sg:address":"51 Willow Glen NE",
    "sg:city":"Atlanta",
    "sg:classifiers":[
        {
            "category":"Professional",
            "subcategory":"Computer Services",
            "type":"Services"
        }
    ],
    "sg:phone":"+1 404 705 9203",
    "sg:postcode":"30342",
    "sg:province":"GA",
    "sg:tags":[
        "programing",
        "custom"
    ],
    "wof:name":"Centuri Software LLC",
    "wof:placetype":"venue"
},
  "geometry": {"coordinates":[-84.375596,33.901827],"type":"Point"}
}