{
  "type": "Feature",
  "properties": {
    "iso:country":"US",
    "sg:address":"352 Price St",
    "sg:city":"Statham",
    "sg:classifiers":[
        {
            "category":"Personal",
            "subcategory":"Beauty Salon",
            "type":"Services"
        }
    ],
    "sg:phone":"+1 770 725 5901",
    "sg:postcode":"30666",
    "sg:province":"GA",
    "sg:tags":[
        "shop"
    ],
    "wof:name":"Sheila's Hair Styling",
    "wof:placetype":"venue"
},
  "geometry": {"coordinates":[-83.607961,33.959968],"type":"Point"}
}