{
  "type": "Feature",
  "properties": {
    "iso:country":"US",
    "sg:address":"159 Temple Ave W",
    "sg:city":"Newnan",
    "sg:classifiers":[
        {
            "category":"Banks & Credit Unions",
            "subcategory":"Bank",
            "type":"Services"
        }
    ],
    "sg:phone":"+1 770 251 5010",
    "sg:postcode":"30263",
    "sg:province":"GA",
    "sg:tags":[
        "loan"
    ],
    "wof:name":"Security Finance Corp",
    "wof:placetype":"venue"
},
  "geometry": {"coordinates":[-84.812247,33.381797],"type":"Point"}
}