{
  "type": "Feature",
  "properties": {
    "addr:full":"55 Savannah St Newnan GA 30263",
    "addr:housenumber":"55",
    "addr:postcode":"30263",
    "addr:street":"Savannah St",
    "iso:country":"US",
    "sg:address":"55 Savannah St",
    "sg:city":"Newnan",
    "sg:classifiers":[
        {
            "category":"Education",
            "subcategory":"Vocational School",
            "type":"Public Place"
        }
    ],
    "sg:phone":"+1 770 304 5904",
    "sg:postcode":"30263",
    "sg:province":"GA",
    "sg:tags":[
        "training",
        "business"
    ],
    "wof:name":"Marriott",
    "wof:placetype":"venue"
},
  "geometry": {"coordinates":[-84.79485200000001,33.370592],"type":"Point"}
}