{
  "type": "Feature",
  "properties": {
    "addr:full":"3241 Melba Dr Hephzibah GA 30815",
    "addr:housenumber":"3241",
    "addr:postcode":"30815",
    "addr:street":"Melba Dr",
    "iso:country":"US",
    "sg:address":"3241 Melba Dr",
    "sg:city":"Hephzibah",
    "sg:classifiers":[
        {
            "category":"Building & Trades",
            "subcategory":"Construction",
            "type":"Services"
        }
    ],
    "sg:phone":"+1 706 830 5064",
    "sg:postcode":"30815",
    "sg:province":"GA",
    "sg:tags":[
        "house"
    ],
    "wof:name":"A & E Restoration Services",
    "wof:placetype":"venue"
},
  "geometry": {"coordinates":[-82.159412,33.315824],"type":"Point"}
}