{
  "type": "Feature",
  "properties": {
    "iso:country":"US",
    "sg:address":"1690 Highway 20 W",
    "sg:city":"McDonough",
    "sg:classifiers":[
        {
            "category":"Real Estate",
            "subcategory":"Real Estate Operator",
            "type":"Services"
        }
    ],
    "sg:phone":"+1 678 432 0292",
    "sg:postcode":"30253",
    "sg:province":"GA",
    "sg:tags":[
        "apartment"
    ],
    "wof:name":"Villas At South Point",
    "wof:placetype":"venue"
},
  "geometry": {"coordinates":[-84.192774,33.417899],"type":"Point"}
}