{
  "type": "Feature",
  "properties": {
    "addr:full":"1955 Panola Rd Ellenwood GA 30294",
    "addr:housenumber":"1955",
    "addr:postcode":"30294",
    "addr:street":"Panola Rd",
    "iso:country":"US",
    "sg:address":"1955 Panola Rd",
    "sg:city":"Ellenwood",
    "sg:classifiers":[
        {
            "category":"Wholesale",
            "subcategory":"Durable Goods & Equipment",
            "type":"Manufacturing & Wholesale Goods"
        }
    ],
    "sg:phone":"+1 770 389 3035",
    "sg:postcode":"30294",
    "sg:province":"GA",
    "wof:name":"Ellenwood Wholesale PC",
    "wof:placetype":"venue"
},
  "geometry": {"coordinates":[-84.24274200000001,33.616034],"type":"Point"}
}