{
  "type": "Feature",
  "properties": {
    "addr:full":"1605 Mansell Rd Alpharetta GA 30004",
    "addr:housenumber":"1605",
    "addr:postcode":"30004",
    "addr:street":"Mansell Rd",
    "iso:country":"US",
    "sg:address":"1605 Mansell Rd",
    "sg:city":"Alpharetta",
    "sg:classifiers":[
        {
            "category":"Insurance",
            "subcategory":"Insurance Agent",
            "type":"Services"
        }
    ],
    "sg:phone":"+1 770 664 6000",
    "sg:postcode":"30004",
    "sg:province":"GA",
    "wof:name":"Allstate Insurance",
    "wof:placetype":"venue"
},
  "geometry": {"coordinates":[-84.316895,34.040437],"type":"Point"}
}