{
  "type": "Feature",
  "properties": {
    "iso:country":"US",
    "sg:address":"5983 Nachoochee Trl",
    "sg:city":"Flowery Branch",
    "sg:classifiers":[
        {
            "category":"Professional",
            "type":"Services"
        }
    ],
    "sg:phone":"+1 770 967 6313",
    "sg:postcode":"30542",
    "sg:province":"GA",
    "wof:name":"Sun Nurseries",
    "wof:placetype":"venue"
},
  "geometry": {"coordinates":[-83.952516,34.192772],"type":"Point"}
}