{
  "type": "Feature",
  "properties": {
    "addr:full":"7505 Hall Rd Fairburn GA 30213",
    "addr:housenumber":"7505",
    "addr:postcode":"30213",
    "addr:street":"Hall Rd",
    "iso:country":"US",
    "sg:address":"7505 Hall Rd",
    "sg:city":"Fairburn",
    "sg:classifiers":[
        {
            "category":"Professional",
            "type":"Services"
        }
    ],
    "sg:phone":"+1 770 969 7828",
    "sg:postcode":"30213",
    "sg:province":"GA",
    "wof:name":"Cathy M Saye",
    "wof:placetype":"venue"
},
  "geometry": {"coordinates":[-84.630391,33.616898],"type":"Point"}
}