{
  "type": "Feature",
  "properties": {
    "addr:full":"507 Industrial Blvd Mcdonough GA 30253",
    "addr:housenumber":"507",
    "addr:postcode":"30253",
    "addr:street":"Industrial Blvd",
    "iso:country":"US",
    "sg:address":"507 Industrial Blvd",
    "sg:city":"Mcdonough",
    "sg:classifiers":[
        {
            "category":"Building & Trades",
            "subcategory":"Construction",
            "type":"Services"
        },
        {
            "category":"Manufacturing",
            "subcategory":"Tools & Machinery",
            "type":"Manufacturing & Wholesale Goods"
        }
    ],
    "sg:phone":"+1 770 957 9046",
    "sg:postcode":"30253",
    "sg:province":"GA",
    "sg:tags":[
        "pipe",
        "mfg",
        "metal",
        "access",
        "machine",
        "fabricator",
        "repair",
        "welding"
    ],
    "wof:name":"Metalflex Manufacturing Co",
    "wof:placetype":"venue"
},
  "geometry": {"coordinates":[-84.16653700000001,33.417488],"type":"Point"}
}