{
  "type": "Feature",
  "properties": {
    "addr:full":"6665 State Hwy 42 Rex GA 30273",
    "addr:housenumber":"6665",
    "addr:postcode":"30273",
    "addr:street":"State Hwy 42",
    "iso:country":"US",
    "sg:address":"6665 State Hwy 42",
    "sg:city":"Rex",
    "sg:classifiers":[
        {
            "category":"Banks & Credit Unions",
            "subcategory":"Investment Brokerage",
            "type":"Services"
        }
    ],
    "sg:phone":"+1 770 389 1300",
    "sg:postcode":"30273",
    "sg:province":"GA",
    "sg:tags":[
        "consultant",
        "planning",
        "financial"
    ],
    "sg:website":"www.bbsinsurance.com",
    "wof:name":"Better Business Solutions",
    "wof:placetype":"venue"
},
  "geometry": {"coordinates":[-84.26796,33.575842],"type":"Point"}
}