{
  "type": "Feature",
  "properties": {
    "addr:full":"3792 Athens Hwy Greensboro GA 30642",
    "addr:housenumber":"3792",
    "addr:postcode":"30642",
    "addr:street":"Athens Hwy",
    "iso:country":"US",
    "sg:address":"3792 Athens Hwy",
    "sg:city":"Greensboro",
    "sg:classifiers":[
        {
            "category":"Building & Trades",
            "subcategory":"Landscaping Services",
            "type":"Services"
        }
    ],
    "sg:phone":"+1 706 453 4819",
    "sg:postcode":"30642",
    "sg:province":"GA",
    "sg:tags":[
        "landscape"
    ],
    "wof:name":"Landscape LLC Town Creek",
    "wof:placetype":"venue"
},
  "geometry": {"coordinates":[-83.21307400000001,33.621326],"type":"Point"}
}