{
  "type": "Feature",
  "properties": {
    "addr:full":"10475 Alpharetta Hwy Roswell GA 30075",
    "addr:housenumber":"10475",
    "addr:postcode":"30075",
    "addr:street":"Alpharetta Hwy",
    "iso:country":"US",
    "sg:address":"10475 Alpharetta Hwy",
    "sg:city":"Roswell",
    "sg:classifiers":[
        {
            "category":"Restaurant",
            "type":"Food & Drink"
        }
    ],
    "sg:phone":"+1 770 993 5151",
    "sg:postcode":"30075",
    "sg:province":"GA",
    "sg:tags":[
        "franchise"
    ],
    "wof:name":"Wendys",
    "wof:placetype":"venue"
},
  "geometry": {"coordinates":[-84.347032,34.034351],"type":"Point"}
}