{
  "type": "Feature",
  "properties": {
    "addr:full":"2002 Redmond Cir NW Rome GA 30165",
    "addr:housenumber":"2002",
    "addr:postcode":"ga 30165",
    "addr:street":"Redmond Cir Nw",
    "iso:country":"US",
    "sg:address":"2002 Redmond Cir NW",
    "sg:city":"Rome",
    "sg:classifiers":[
        {
            "category":"Wholesale",
            "subcategory":"Computers",
            "type":"Manufacturing & Wholesale Goods"
        }
    ],
    "sg:phone":"+1 706 235 4206",
    "sg:postcode":"30165",
    "sg:province":"GA",
    "sg:tags":[
        "equipment"
    ],
    "wof:name":"Micro Plus",
    "wof:placetype":"venue"
},
  "geometry": {"coordinates":[-85.222356,34.285628],"type":"Point"}
}