{
  "type": "Feature",
  "properties": {
    "iso:country":"US",
    "sg:address":"4345 Apple Tree Dr",
    "sg:city":"Stone Mountain",
    "sg:classifiers":[
        {
            "category":"Real Estate",
            "subcategory":"Real Estate Agent",
            "type":"Services"
        }
    ],
    "sg:phone":"+1 404 292 2219",
    "sg:postcode":"30083",
    "sg:province":"GA",
    "sg:website":"www.trincityrealty.com",
    "wof:name":"Trincity Realty LLC",
    "wof:placetype":"venue"
},
  "geometry": {"coordinates":[-84.209875,33.812062],"type":"Point"}
}