{
  "type": "Feature",
  "properties": {
    "iso:country":"US",
    "sg:address":"5459 Janet Ln",
    "sg:city":"Austell",
    "sg:classifiers":[
        {
            "category":"Retail",
            "subcategory":"Auto Repair",
            "type":"Services"
        }
    ],
    "sg:phone":"+1 770 851 4592",
    "sg:postcode":"30106",
    "sg:province":"GA",
    "sg:tags":[
        "repairing",
        "automobile"
    ],
    "wof:name":"Helping Hands Mobile Auto Rep",
    "wof:placetype":"venue"
},
  "geometry": {"coordinates":[-84.602912,33.822535],"type":"Point"}
}