{
  "type": "Feature",
  "properties": {
    "addr:full":"500 Jonesboro Rd Mcdonough GA 30253",
    "addr:housenumber":"500",
    "addr:postcode":"30253",
    "addr:street":"Jonesboro Rd",
    "iso:country":"US",
    "sg:address":"500 Jonesboro Rd",
    "sg:city":"Mcdonough",
    "sg:classifiers":[
        {
            "category":"Food & Beverages",
            "subcategory":"Groceries & Convenience Stores",
            "type":"Retail Goods"
        },
        {
            "category":"Autos & Motor Vehicles",
            "subcategory":"Fuel & Gas Station",
            "type":"Retail Goods"
        }
    ],
    "sg:phone":"+1 770 954 1641",
    "sg:postcode":"30253",
    "sg:province":"GA",
    "sg:tags":[
        "oil"
    ],
    "wof:name":"Citgo Quik Food Mart",
    "wof:placetype":"venue"
},
  "geometry": {"coordinates":[-84.176496,33.458374],"type":"Point"}
}