{
  "type": "Feature",
  "properties": {
    "addr:full":"221 N Main St Sylvania GA 30467",
    "addr:housenumber":"221",
    "addr:postcode":"30467",
    "addr:street":"N Main St",
    "iso:country":"US",
    "sg:address":"221 N Main St",
    "sg:city":"Sylvania",
    "sg:classifiers":[
        {
            "category":"Restaurant",
            "type":"Food & Drink"
        }
    ],
    "sg:phone":"+1 912 564 5056",
    "sg:postcode":"30467",
    "sg:province":"GA",
    "wof:name":"Liron's Cheese Stakes & Hogges",
    "wof:placetype":"venue"
},
  "geometry": {"coordinates":[-81.637186,32.752374],"type":"Point"}
}