{
  "type": "Feature",
  "properties": {
    "addr:full":"612 Interchange Dr SW Atlanta GA 30336",
    "addr:housenumber":"612",
    "addr:postcode":"30336",
    "addr:street":"Interchange Dr Sw",
    "iso:country":"US",
    "sg:address":"612 Interchange Dr SW",
    "sg:city":"Atlanta",
    "sg:classifiers":[
        {
            "category":"Professional",
            "subcategory":"Management & Consulting",
            "type":"Services"
        }
    ],
    "sg:phone":"+1 404 691 1199",
    "sg:postcode":"30336",
    "sg:province":"GA",
    "sg:tags":[
        "public",
        "relations"
    ],
    "sg:website":"www.aj-productions.com",
    "wof:name":"A J Productions Inc",
    "wof:placetype":"venue"
},
  "geometry": {"coordinates":[-84.525008,33.770032],"type":"Point"}
}