{
  "type": "Feature",
  "properties": {
    "addr:full":"3693 Campbellton Rd Atlanta GA 30331",
    "addr:housenumber":"3693",
    "addr:postcode":"30331",
    "addr:street":"Campbellton Rd",
    "iso:country":"US",
    "sg:address":"3693 Campbellton Rd",
    "sg:city":"Atlanta",
    "sg:classifiers":[
        {
            "category":"Social Services",
            "subcategory":"Child Care",
            "type":"Services"
        }
    ],
    "sg:phone":"+1 404 344 6729",
    "sg:postcode":"30331",
    "sg:province":"GA",
    "sg:tags":[
        "day"
    ],
    "wof:name":"Belivers Bible Day Care Center",
    "wof:placetype":"venue"
},
  "geometry": {"coordinates":[-84.50994300000001,33.690379],"type":"Point"}
}