{
  "type": "Feature",
  "properties": {
    "addr:full":"508 S Center St Thomaston GA 30286",
    "addr:housenumber":"508",
    "addr:postcode":"30286",
    "addr:street":"S Center St",
    "iso:country":"US",
    "sg:address":"508 S Center St",
    "sg:city":"Thomaston",
    "sg:classifiers":[
        {
            "category":"Professional",
            "type":"Services"
        }
    ],
    "sg:phone":"+1 706 647 3906",
    "sg:postcode":"30286",
    "sg:province":"GA",
    "wof:name":"Wayne Murphy",
    "wof:placetype":"venue"
},
  "geometry": {"coordinates":[-84.326246,32.88384],"type":"Point"}
}