{
  "type": "Feature",
  "properties": {
    "addr:full":"8995 Westside Pkwy Alpharetta GA 30004",
    "addr:housenumber":"8995",
    "addr:postcode":"30004",
    "addr:street":"Westside Pkwy",
    "iso:country":"US",
    "sg:address":"8995 Westside Pkwy",
    "sg:city":"Alpharetta",
    "sg:classifiers":[
        {
            "category":"Banks & Credit Unions",
            "subcategory":"Investment Brokerage",
            "type":"Services"
        }
    ],
    "sg:phone":"+1 678 336 2000",
    "sg:postcode":"30004",
    "sg:province":"GA",
    "sg:tags":[
        "advisory"
    ],
    "wof:name":"Alliance Technology Ventures",
    "wof:placetype":"venue"
},
  "geometry": {"coordinates":[-84.284994,34.069491],"type":"Point"}
}