{
  "type": "Feature",
  "properties": {
    "iso:country":"US",
    "sg:address":"4 Happy Hollow Rd",
    "sg:city":"Dahlonega",
    "sg:classifiers":[
        {
            "category":"Organizations",
            "subcategory":"Religious Organization",
            "type":"Services"
        }
    ],
    "sg:phone":"+1 706 864 3782",
    "sg:postcode":"30533",
    "sg:province":"GA",
    "sg:tags":[
        "church"
    ],
    "wof:name":"Dahlonega Church Of God",
    "wof:placetype":"venue"
},
  "geometry": {"coordinates":[-83.98876199999999,34.534814],"type":"Point"}
}