{
  "type": "Feature",
  "properties": {
    "iso:country":"US",
    "sg:address":"3947 Houston Ave",
    "sg:city":"Macon",
    "sg:classifiers":[
        {
            "category":"Restaurant",
            "type":"Food & Drink"
        }
    ],
    "sg:phone":"+1 478 788 1900",
    "sg:postcode":"31206",
    "sg:province":"GA",
    "wof:name":"Finchers Barbeque",
    "wof:placetype":"venue"
},
  "geometry": {"coordinates":[-83.65428900000001,32.794976],"type":"Point"}
}