{
  "type": "Feature",
  "properties": {
    "iso:country":"US",
    "sg:address":"893 State Rte 292",
    "sg:city":"Lyons",
    "sg:classifiers":[
        {
            "category":"Autos & Motor Vehicles",
            "subcategory":"Fuel & Gas Station",
            "type":"Retail Goods"
        }
    ],
    "sg:phone":"+1 912 526 5665",
    "sg:postcode":"30436",
    "sg:province":"GA",
    "sg:tags":[
        "station",
        "gasoline"
    ],
    "wof:name":"292 Country Pantry",
    "wof:placetype":"venue"
},
  "geometry": {"coordinates":[-82.29612899999999,32.203691],"type":"Point"}
}