{
  "type": "Feature",
  "properties": {
    "iso:country":"US",
    "sg:address":"118 E Maple St",
    "sg:city":"Decatur",
    "sg:classifiers":[
        {
            "category":"Organizations",
            "subcategory":"Non-profit Organization",
            "type":"Services"
        }
    ],
    "sg:phone":"+1 678 904 2640",
    "sg:postcode":"30030",
    "sg:province":"GA",
    "wof:name":"National Center For Human",
    "wof:placetype":"venue"
},
  "geometry": {"coordinates":[-84.29516700000001,33.771891],"type":"Point"}
}