{
  "type": "Feature",
  "properties": {
    "iso:country":"US",
    "sg:address":"222 E Harris St",
    "sg:city":"Savannah",
    "sg:classifiers":[
        {
            "category":"Organizations",
            "subcategory":"Religious Organization",
            "type":"Services"
        }
    ],
    "sg:phone":"+1 912 233 4709",
    "sg:postcode":"31401",
    "sg:province":"GA",
    "wof:name":"Cathedral of St John The Bapt",
    "wof:placetype":"venue"
},
  "geometry": {"coordinates":[-81.091418,32.073308],"type":"Point"}
}