{
  "type": "Feature",
  "properties": {
    "addr:full":"3939 Elizabeth Ter Rex GA 30273",
    "addr:housenumber":"3939",
    "addr:postcode":"30273",
    "addr:street":"Elizabeth Ter Rex",
    "iso:country":"US",
    "sg:address":"3939 Elizabeth Ter",
    "sg:city":"Rex",
    "sg:classifiers":[
        {
            "category":"Real Estate",
            "subcategory":"Developer",
            "type":"Services"
        }
    ],
    "sg:phone":"+1 770 474 7481",
    "sg:postcode":"30273",
    "sg:province":"GA",
    "wof:name":"Mayo Estates Inc",
    "wof:placetype":"venue"
},
  "geometry": {"coordinates":[-84.26244199999999,33.601711],"type":"Point"}
}