{
  "type": "Feature",
  "properties": {
    "addr:full":"590 Eagles Landing Pkwy Stockbridge GA 30281",
    "addr:housenumber":"590",
    "addr:postcode":"30281",
    "addr:street":"Eagles Landing Pkwy",
    "iso:country":"US",
    "sg:address":"590 Eagles Landing Pkwy",
    "sg:city":"Stockbridge",
    "sg:classifiers":[
        {
            "category":"Restaurant",
            "type":"Food & Drink"
        }
    ],
    "sg:phone":"+1 770 506 4600",
    "sg:postcode":"30281",
    "sg:province":"GA",
    "sg:tags":[
        "eating"
    ],
    "wof:name":"Mexitaco",
    "wof:placetype":"venue"
},
  "geometry": {"coordinates":[-84.20450599999999,33.517519],"type":"Point"}
}