{
  "type": "Feature",
  "properties": {
    "addr:full":"2681 Mount Paron Church Rd Monroe GA 30655",
    "addr:housenumber":"2681",
    "addr:postcode":"30655",
    "addr:street":"Mount Paron Church Rd",
    "iso:country":"US",
    "sg:address":"2681 Mount Paron Church Rd",
    "sg:city":"Monroe",
    "sg:classifiers":[
        {
            "category":"Retail",
            "subcategory":"Veterinary Services",
            "type":"Services"
        }
    ],
    "sg:phone":"+1 706 342 1476",
    "sg:postcode":"30655",
    "sg:province":"GA",
    "sg:tags":[
        "veterinarian"
    ],
    "wof:name":"Lassiter Veterinary Svc",
    "wof:placetype":"venue"
},
  "geometry": {"coordinates":[-83.671024,33.715197],"type":"Point"}
}