{
  "type": "Feature",
  "properties": {
    "addr:full":"2041 College St Rentz GA 31075",
    "addr:housenumber":"2041",
    "addr:postcode":"31075",
    "addr:street":"College St",
    "iso:country":"US",
    "sg:address":"2041 College St",
    "sg:city":"Rentz",
    "sg:classifiers":[
        {
            "category":"Manufacturing",
            "subcategory":"Building Materials",
            "type":"Manufacturing & Wholesale Goods"
        }
    ],
    "sg:phone":"+1 478 984 4207",
    "sg:postcode":"31075",
    "sg:province":"GA",
    "sg:tags":[
        "manufacturer",
        "wood",
        "kitchen",
        "cabinet"
    ],
    "wof:name":"Rentz Cabinet Company",
    "wof:placetype":"venue"
},
  "geometry": {"coordinates":[-82.992498,32.386097],"type":"Point"}
}