{
  "type": "Feature",
  "properties": {
    "iso:country":"US",
    "sg:address":"2826 10th Ave",
    "sg:city":"Columbus",
    "sg:classifiers":[
        {
            "category":"Building & Trades",
            "subcategory":"Construction",
            "type":"Services"
        }
    ],
    "sg:phone":"+1 706 324 1731",
    "sg:postcode":"31904",
    "sg:province":"GA",
    "sg:tags":[
        "hanging",
        "contractor"
    ],
    "wof:name":"Blackwell Paint Co",
    "wof:placetype":"venue"
},
  "geometry": {"coordinates":[-84.98026299999999,32.490357],"type":"Point"}
}