{
  "type": "Feature",
  "properties": {
    "addr:full":"1300 Echo Trl Watkinsville GA 30677",
    "addr:housenumber":"1300",
    "addr:postcode":"30677",
    "addr:street":"Echo Trl",
    "iso:country":"US",
    "sg:address":"1300 Echo Trl",
    "sg:city":"Watkinsville",
    "sg:classifiers":[
        {
            "category":"Professional",
            "subcategory":"Business Services",
            "type":"Services"
        }
    ],
    "sg:phone":"+1 706 769 4042",
    "sg:postcode":"30677",
    "sg:province":"GA",
    "wof:name":"J Gibbs Associates",
    "wof:placetype":"venue"
},
  "geometry": {"coordinates":[-83.43645100000001,33.851219],"type":"Point"}
}