{
  "type": "Feature",
  "properties": {
    "iso:country":"US",
    "sg:address":"4619 Woodland Brook Dr SE",
    "sg:city":"Atlanta",
    "sg:classifiers":[
        {
            "category":"Professional",
            "subcategory":"Computer Services",
            "type":"Services"
        },
        {
            "category":"Wholesale",
            "subcategory":"Computers",
            "type":"Manufacturing & Wholesale Goods"
        }
    ],
    "sg:phone":"+1 404 355 7603",
    "sg:postcode":"30339",
    "sg:province":"GA",
    "sg:tags":[
        "equipment",
        "cd-rom",
        "software"
    ],
    "sg:website":"http://www.lethoff.com",
    "wof:name":"Lethoff Inc",
    "wof:placetype":"venue"
},
  "geometry": {"coordinates":[-84.47266999999999,33.841015],"type":"Point"}
}