{
  "type": "Feature",
  "properties": {
    "iso:country":"US",
    "sg:address":"3127 Lenox Rd NE",
    "sg:city":"Atlanta",
    "sg:classifiers":[
        {
            "category":"Communications",
            "type":"Services"
        }
    ],
    "sg:phone":"+1 404 841 7977",
    "sg:postcode":"30324",
    "sg:province":"GA",
    "sg:tags":[
        "recording",
        "rehearsal",
        "studio"
    ],
    "wof:name":"From the Ground Up Records",
    "wof:placetype":"venue"
},
  "geometry": {"coordinates":[-84.35794300000001,33.839754],"type":"Point"}
}