{
  "type": "Feature",
  "properties": {
    "iso:country":"US",
    "sg:address":"1080 County Line Rd",
    "sg:city":"Lithia Springs",
    "sg:classifiers":[
        {
            "category":"Freight",
            "type":"Transportation"
        }
    ],
    "sg:phone":"+1 770 948 2411",
    "sg:postcode":"30122",
    "sg:province":"GA",
    "sg:tags":[
        "auto",
        "transport"
    ],
    "wof:name":"Dutton Transport",
    "wof:placetype":"venue"
},
  "geometry": {"coordinates":[-84.668374,33.775033],"type":"Point"}
}