{
  "type": "Feature",
  "properties": {
    "iso:country":"US",
    "sg:address":"Houston Lk",
    "sg:city":"Centerville",
    "sg:classifiers":[
        {
            "category":"Banks & Credit Unions",
            "subcategory":"Financial Services",
            "type":"Services"
        }
    ],
    "sg:phone":"+1 478 953 7400",
    "sg:postcode":"31028",
    "sg:province":"GA",
    "sg:tags":[
        "broker",
        "mortgage"
    ],
    "wof:name":"Fairfield Financial",
    "wof:placetype":"venue"
},
  "geometry": {"coordinates":[-83.68000000000001,32.634102],"type":"Point"}
}