{
  "type": "Feature",
  "properties": {
    "addr:full":"3049 Peachtree Dr NE Atlanta GA 30305",
    "addr:housenumber":"3049",
    "addr:postcode":"30305",
    "addr:street":"Peachtree Dr Ne",
    "iso:country":"US",
    "sg:address":"3049 Peachtree Dr NE",
    "sg:city":"Atlanta",
    "sg:classifiers":[
        {
            "category":"Bars & Pubs",
            "type":"Food & Drink"
        }
    ],
    "sg:phone":"+1 404 816 9931",
    "sg:postcode":"30305",
    "sg:province":"GA",
    "sg:tags":[
        "drinking"
    ],
    "wof:name":"Uranus",
    "wof:placetype":"venue"
},
  "geometry": {"coordinates":[-84.368033,33.837483],"type":"Point"}
}