{
  "type": "Feature",
  "properties": {
    "addr:full":"3626 Midway Rd Decatur GA 30032",
    "addr:housenumber":"3626",
    "addr:postcode":"30032",
    "addr:street":"Midway Rd",
    "iso:country":"US",
    "sg:address":"3626 Midway Rd",
    "sg:city":"Decatur",
    "sg:classifiers":[
        {
            "category":"Building & Trades",
            "subcategory":"Cleaning & Sanitation",
            "type":"Services"
        }
    ],
    "sg:phone":"+1 404 288 6949",
    "sg:postcode":"30032",
    "sg:province":"GA",
    "sg:tags":[
        "janitor"
    ],
    "wof:name":"Edna's Cleaning Svc",
    "wof:placetype":"venue"
},
  "geometry": {"coordinates":[-84.251627,33.76234],"type":"Point"}
}