{
  "type": "Feature",
  "properties": {
    "addr:full":"2778 Summit Dr Jonesboro GA 30236",
    "addr:housenumber":"2778",
    "addr:postcode":"30236",
    "addr:street":"Summit Dr",
    "iso:country":"US",
    "sg:address":"2778 Summit Dr",
    "sg:city":"Jonesboro",
    "sg:classifiers":[
        {
            "category":"Professional",
            "subcategory":"Business Services",
            "type":"Services"
        }
    ],
    "sg:phone":"+1 770 477 2109",
    "sg:postcode":"30236",
    "sg:province":"GA",
    "wof:name":"CB Enterprises Ltd",
    "wof:placetype":"venue"
},
  "geometry": {"coordinates":[-84.30054699999999,33.503797],"type":"Point"}
}