{
  "type": "Feature",
  "properties": {
    "iso:country":"US",
    "sg:address":"4215 Jimmy Lee Smith Pkwy",
    "sg:city":"Hiram",
    "sg:classifiers":[
        {
            "category":"Personal",
            "subcategory":"Nail Salon",
            "type":"Services"
        }
    ],
    "sg:phone":"+1 770 439 7333",
    "sg:postcode":"30141",
    "sg:province":"GA",
    "wof:name":"N T Nail",
    "wof:placetype":"venue"
},
  "geometry": {"coordinates":[-84.753998,33.891102],"type":"Point"}
}