{
  "type": "Feature",
  "properties": {
    "iso:country":"US",
    "sg:address":"881 Ponce De Leon Ave NE, ste 7",
    "sg:city":"Atlanta",
    "sg:classifiers":[
        {
            "category":"Personal",
            "type":"Services"
        },
        {
            "category":"Home & Garden",
            "subcategory":"Building Materials",
            "type":"Retail Goods"
        },
        {
            "category":"Building & Trades",
            "subcategory":"Construction",
            "type":"Services"
        }
    ],
    "sg:phone":"+1 404 745 3085",
    "sg:postcode":"30306",
    "sg:province":"GA",
    "sg:tags":[
        "fence-sales",
        "local",
        "fence",
        "contractor"
    ],
    "sg:website":"www.longfence.com",
    "wof:name":"Long Fence",
    "wof:placetype":"venue"
},
  "geometry": {"coordinates":[-84.358555,33.773435],"type":"Point"}
}