{
  "type": "Feature",
  "properties": {
    "addr:full":"2005 Estate Ct Woodstock GA 30188",
    "addr:housenumber":"2005",
    "addr:postcode":"30188",
    "addr:street":"Estate Ct",
    "iso:country":"US",
    "sg:address":"2005 Estate Ct",
    "sg:city":"Woodstock",
    "sg:classifiers":[
        {
            "category":"Building & Trades",
            "subcategory":"Construction",
            "type":"Services"
        }
    ],
    "sg:phone":"+1 770 591 2853",
    "sg:postcode":"30188",
    "sg:province":"GA",
    "sg:tags":[
        "hanging",
        "contractor"
    ],
    "wof:name":"J&J Pro Painting",
    "wof:placetype":"venue"
},
  "geometry": {"coordinates":[-84.408365,34.11428],"type":"Point"}
}