{
  "type": "Feature",
  "properties": {
    "addr:full":"1660 Winder Hwy Jefferson GA 30549",
    "addr:housenumber":"1660",
    "addr:postcode":"30549",
    "addr:street":"Winder Hwy",
    "iso:country":"US",
    "sg:address":"1660 Winder Hwy",
    "sg:city":"Jefferson",
    "sg:classifiers":[
        {
            "category":"Education",
            "subcategory":"School",
            "type":"Public Place"
        }
    ],
    "sg:phone":"+1 706 367 5151",
    "sg:postcode":"30549",
    "sg:province":"GA",
    "sg:website":"www.jackson.k12.ga.us",
    "wof:name":"Jackson County School District",
    "wof:placetype":"venue"
},
  "geometry": {"coordinates":[-83.594537,34.102394],"type":"Point"}
}