{
  "type": "Feature",
  "properties": {
    "iso:country":"US",
    "sg:address":"691 Ernest W Barrett Pkwy NW",
    "sg:city":"Kennesaw",
    "sg:classifiers":[
        {
            "category":"Shopping",
            "subcategory":"Bicycles & Sporting Goods",
            "type":"Retail Goods"
        }
    ],
    "sg:phone":"+1 770 281 0200",
    "sg:postcode":"30144",
    "sg:province":"GA",
    "wof:name":"Galyan's Trading Company",
    "wof:placetype":"venue"
},
  "geometry": {"coordinates":[-84.569881,34.008489],"type":"Point"}
}