{
  "type": "Feature",
  "properties": {
    "iso:country":"US",
    "sg:address":"1561 N Decatur Rd",
    "sg:city":"Atlanta",
    "sg:classifiers":[
        {
            "category":"Travel",
            "subcategory":"Travel Agent",
            "type":"Entertainment"
        }
    ],
    "sg:phone":"+1 404 377 9997",
    "sg:postcode":"30307",
    "sg:province":"GA",
    "sg:tags":[
        "agency"
    ],
    "wof:name":"Council Travel",
    "wof:placetype":"venue"
},
  "geometry": {"coordinates":[-84.326066,33.78808],"type":"Point"}
}