{
  "type": "Feature",
  "properties": {
    "iso:country":"US",
    "sg:address":"10423 Commerce St",
    "sg:city":"Summerville",
    "sg:classifiers":[
        {
            "category":"Autos & Motor Vehicles",
            "subcategory":"Automobile Sales",
            "type":"Retail Goods"
        }
    ],
    "sg:phone":"+1 706 857 2487",
    "sg:postcode":"30747",
    "sg:province":"GA",
    "sg:tags":[
        "car",
        "used"
    ],
    "wof:name":"Marks Auto Sales",
    "wof:placetype":"venue"
},
  "geometry": {"coordinates":[-85.344943,34.484843],"type":"Point"}
}