{
  "type": "Feature",
  "properties": {
    "iso:country":"US",
    "sg:address":"3426 Holcomb Bridge Rd",
    "sg:city":"Norcross",
    "sg:classifiers":[
        {
            "category":"Autos & Motor Vehicles",
            "subcategory":"Fuel & Gas Station",
            "type":"Retail Goods"
        }
    ],
    "sg:phone":"+1 678 291 0551",
    "sg:postcode":"30092",
    "sg:province":"GA",
    "wof:name":"Swifty Serve",
    "wof:placetype":"venue"
},
  "geometry": {"coordinates":[-84.242599,33.952702],"type":"Point"}
}