{
  "type": "Feature",
  "properties": {
    "iso:country":"US",
    "sg:address":"2793 Clairmont Rd NE",
    "sg:city":"Atlanta",
    "sg:classifiers":[
        {
            "category":"Professional",
            "subcategory":"Detective & Security Services",
            "type":"Services"
        }
    ],
    "sg:phone":"+1 404 248 2995",
    "sg:postcode":"30329",
    "sg:province":"GA",
    "sg:tags":[
        "control",
        "monitoring",
        "guard",
        "patrol",
        "system"
    ],
    "sg:website":"http://paradigmsecurity.net",
    "wof:name":"Paradigm Security Services Incorporated",
    "wof:placetype":"venue"
},
  "geometry": {"coordinates":[-84.31207000000001,33.83798],"type":"Point"}
}