{
  "type": "Feature",
  "properties": {
    "iso:country":"US",
    "sg:address":"4031 Jonesboro Rd",
    "sg:city":"Forest Park",
    "sg:classifiers":[
        {
            "category":"Personal",
            "subcategory":"Beauty Salon",
            "type":"Services"
        }
    ],
    "sg:phone":"+1 404 968 3305",
    "sg:postcode":"30297",
    "sg:province":"GA",
    "wof:name":"Hispano Beauty Salon",
    "wof:placetype":"venue"
},
  "geometry": {"coordinates":[-84.361665,33.640379],"type":"Point"}
}