{
  "type": "Feature",
  "properties": {
    "iso:country":"US",
    "sg:address":"939 Bridge Mill Ave",
    "sg:city":"Canton",
    "sg:classifiers":[
        {
            "category":"Professional",
            "subcategory":"Business Services",
            "type":"Services"
        }
    ],
    "sg:phone":"+1 770 479 6965",
    "sg:postcode":"30114",
    "sg:province":"GA",
    "wof:name":"Caratto Group LLC",
    "wof:placetype":"venue"
},
  "geometry": {"coordinates":[-84.569022,34.175182],"type":"Point"}
}