{
  "type": "Feature",
  "properties": {
    "iso:country":"US",
    "sg:address":"25 Key Rd",
    "sg:city":"Ellenwood",
    "sg:classifiers":[
        {
            "category":"Building & Trades",
            "subcategory":"Construction",
            "type":"Services"
        }
    ],
    "sg:phone":"+1 770 981 0115",
    "sg:postcode":"30294",
    "sg:province":"GA",
    "sg:tags":[
        "heavy"
    ],
    "wof:name":"Thomas Key Grading",
    "wof:placetype":"venue"
},
  "geometry": {"coordinates":[-84.217418,33.64237],"type":"Point"}
}