{
  "type": "Feature",
  "properties": {
    "iso:country":"US",
    "sg:address":"422 Southerfield Rd",
    "sg:city":"Americus",
    "sg:classifiers":[
        {
            "category":"Home & Garden",
            "subcategory":"Garden Supply",
            "type":"Retail Goods"
        }
    ],
    "sg:phone":"+1 229 928 4377",
    "sg:postcode":"31719",
    "sg:province":"GA",
    "wof:name":"Sweet Water Gardens & Gifts",
    "wof:placetype":"venue"
},
  "geometry": {"coordinates":[-84.22706100000001,32.091468],"type":"Point"}
}