{
  "type": "Feature",
  "properties": {
    "addr:full":"805 Berkeley Ave NW Atlanta GA 30318",
    "addr:housenumber":"805",
    "addr:postcode":"30318",
    "addr:street":"Berkeley Ave Nw",
    "iso:country":"US",
    "sg:address":"805 Berkeley Ave NW",
    "sg:city":"Atlanta",
    "sg:classifiers":[
        {
            "category":"Shopping",
            "subcategory":"Stationery & Office Supplies",
            "type":"Retail Goods"
        }
    ],
    "sg:phone":"+1 404 355 4256",
    "sg:postcode":"30318",
    "sg:province":"GA",
    "sg:tags":[
        "equipment"
    ],
    "wof:name":"G J's Furniture & Supply Co",
    "wof:placetype":"venue"
},
  "geometry": {"coordinates":[-84.415604,33.797001],"type":"Point"}
}