{
  "type": "Feature",
  "properties": {
    "addr:full":"5080 Highlands Pkwy SE Smyrna GA 30082",
    "addr:housenumber":"5080",
    "addr:postcode":"30082",
    "addr:street":"Highlands Pkwy Se",
    "iso:country":"US",
    "sg:address":"5080 Highlands Pkwy SE",
    "sg:city":"Smyrna",
    "sg:classifiers":[
        {
            "category":"Professional",
            "type":"Services"
        }
    ],
    "sg:phone":"+1 770 319 6557",
    "sg:postcode":"30082",
    "sg:province":"GA",
    "sg:tags":[
        "establishment"
    ],
    "wof:name":"Screen Works",
    "wof:placetype":"venue"
},
  "geometry": {"coordinates":[-84.50991999999999,33.829513],"type":"Point"}
}