{
  "type": "Feature",
  "properties": {
    "iso:country":"US",
    "sg:address":"587 Webb Gin House Rd",
    "sg:city":"Lawrenceville",
    "sg:classifiers":[
        {
            "category":"Organizations",
            "subcategory":"Religious Organization",
            "type":"Services"
        }
    ],
    "sg:phone":"+1 770 962 7369",
    "sg:postcode":"30045",
    "sg:province":"GA",
    "wof:name":"New Life Praise Center",
    "wof:placetype":"venue"
},
  "geometry": {"coordinates":[-83.974377,33.910803],"type":"Point"}
}