{
  "type": "Feature",
  "properties": {
    "addr:full":"4104 Lavista Rd Tucker GA 30084",
    "addr:housenumber":"4104",
    "addr:postcode":"30084",
    "addr:street":"Lavista Rd",
    "iso:country":"US",
    "sg:address":"4104 Lavista Rd",
    "sg:city":"Tucker",
    "sg:classifiers":[
        {
            "category":"Health Services",
            "subcategory":"Doctor",
            "type":"Services"
        }
    ],
    "sg:phone":"+1 770 493 6490",
    "sg:postcode":"30084",
    "sg:province":"GA",
    "wof:name":"Yagoda Joel P MD",
    "wof:placetype":"venue"
},
  "geometry": {"coordinates":[-84.246399,33.846401],"type":"Point"}
}