{
  "type": "Feature",
  "properties": {
    "addr:full":"1440 Woodhill Dr Marietta GA 30066",
    "addr:housenumber":"1440",
    "addr:postcode":"30066",
    "addr:street":"Woodhill Dr",
    "iso:country":"US",
    "sg:address":"1440 Woodhill Dr",
    "sg:city":"Marietta",
    "sg:classifiers":[
        {
            "category":"Wholesale",
            "subcategory":"Machinery & Supplies",
            "type":"Manufacturing & Wholesale Goods"
        }
    ],
    "sg:phone":"+1 770 565 4158",
    "sg:postcode":"30066",
    "sg:province":"GA",
    "wof:name":"Envy Irrigation",
    "wof:placetype":"venue"
},
  "geometry": {"coordinates":[-84.510925,34.037238],"type":"Point"}
}