{
  "type": "Feature",
  "properties": {
    "iso:country":"US",
    "sg:address":"4135 Cripple Creek Way",
    "sg:city":"Kennesaw",
    "sg:classifiers":[
        {
            "category":"Professional",
            "subcategory":"Management & Consulting",
            "type":"Services"
        }
    ],
    "sg:phone":"+1 770 924 0960",
    "sg:postcode":"30144",
    "sg:province":"GA",
    "sg:tags":[
        "business"
    ],
    "wof:name":"Ramnish Properties Inc",
    "wof:placetype":"venue"
},
  "geometry": {"coordinates":[-84.569992,34.047298],"type":"Point"}
}