{
  "type": "Feature",
  "properties": {
    "addr:full":"12155 Clairmonte Ave Alpharetta GA 30004",
    "addr:housenumber":"12155",
    "addr:postcode":"30004",
    "addr:street":"Clairmonte Ave",
    "iso:country":"US",
    "sg:address":"12155 Clairmonte Ave",
    "sg:city":"Alpharetta",
    "sg:classifiers":[
        {
            "category":"Professional",
            "subcategory":"Business Services",
            "type":"Services"
        }
    ],
    "sg:phone":"+1 770 442 5172",
    "sg:postcode":"30004",
    "sg:province":"GA",
    "wof:name":"Morgan Restoration Group Inc",
    "wof:placetype":"venue"
},
  "geometry": {"coordinates":[-84.28313199999999,34.080085],"type":"Point"}
}