{
  "type": "Feature",
  "properties": {
    "iso:country":"US",
    "sg:address":"170 Sagamore Ct",
    "sg:city":"Fayetteville",
    "sg:classifiers":[
        {
            "category":"Real Estate",
            "subcategory":"Real Estate Operator",
            "type":"Services"
        }
    ],
    "sg:phone":"+1 770 306 8835",
    "sg:postcode":"30214",
    "sg:province":"GA",
    "sg:tags":[
        "building",
        "nonresidential"
    ],
    "wof:name":"Louis & Renaldo Properties LLC",
    "wof:placetype":"venue"
},
  "geometry": {"coordinates":[-84.498001,33.514197],"type":"Point"}
}