{
  "type": "Feature",
  "properties": {
    "iso:country":"US",
    "sg:address":"3615 Canton Hwy",
    "sg:city":"Cumming",
    "sg:classifiers":[
        {
            "category":"Wholesale",
            "subcategory":"Machinery & Supplies",
            "type":"Manufacturing & Wholesale Goods"
        }
    ],
    "sg:phone":"+1 770 781 9949",
    "sg:postcode":"30040",
    "sg:province":"GA",
    "wof:name":"A1 Landscape Construction Inc",
    "wof:placetype":"venue"
},
  "geometry": {"coordinates":[-84.226395,34.238572],"type":"Point"}
}