{
  "type": "Feature",
  "properties": {
    "iso:country":"US",
    "sg:address":"1417 S 1st St",
    "sg:city":"Jesup",
    "sg:classifiers":[
        {
            "category":"Restaurant",
            "type":"Food & Drink"
        }
    ],
    "sg:phone":"+1 912 427 9202",
    "sg:postcode":"31545",
    "sg:province":"GA",
    "wof:name":"Habaneros Mexican Restaurant",
    "wof:placetype":"venue"
},
  "geometry": {"coordinates":[-81.911846,31.604771],"type":"Point"}
}