{
  "type": "Feature",
  "properties": {
    "iso:country":"US",
    "sg:address":"4049 Penhurst Dr",
    "sg:city":"Marietta",
    "sg:classifiers":[
        {
            "category":"Home & Garden",
            "subcategory":"Home Furnishings",
            "type":"Retail Goods"
        }
    ],
    "sg:phone":"+1 770 509 0442",
    "sg:postcode":"30062",
    "sg:province":"GA",
    "sg:tags":[
        "venetian",
        "blind"
    ],
    "wof:name":"Tru View",
    "wof:placetype":"venue"
},
  "geometry": {"coordinates":[-84.43261800000001,33.986634],"type":"Point"}
}