{
  "type": "Feature",
  "properties": {
    "iso:country":"US",
    "sg:address":"245 Riverstone Pkwy",
    "sg:city":"Canton",
    "sg:classifiers":[
        {
            "category":"Food & Beverages",
            "subcategory":"Groceries & Convenience Stores",
            "type":"Retail Goods"
        }
    ],
    "sg:phone":"+1 770 704 5440",
    "sg:postcode":"30114",
    "sg:province":"GA",
    "wof:name":"Ali & Ali Inc",
    "wof:placetype":"venue"
},
  "geometry": {"coordinates":[-84.493224,34.243334],"type":"Point"}
}