{
  "type": "Feature",
  "properties": {
    "iso:country":"US",
    "sg:address":"154 Parish Rd",
    "sg:city":"Covington",
    "sg:classifiers":[
        {
            "category":"Organizations",
            "subcategory":"Labor Organization",
            "type":"Services"
        },
        {
            "category":"Building & Trades",
            "subcategory":"Cleaning & Sanitation",
            "type":"Services"
        }
    ],
    "sg:phone":"+1 770 786 8022",
    "sg:postcode":"30014",
    "sg:province":"GA",
    "sg:tags":[
        "sweeping",
        "street",
        "service-power"
    ],
    "wof:name":"J & W Power Sweep",
    "wof:placetype":"venue"
},
  "geometry": {"coordinates":[-83.930587,33.620229],"type":"Point"}
}