{
  "type": "Feature",
  "properties": {
    "iso:country":"US",
    "sg:address":"741 S 8th St",
    "sg:city":"Griffin",
    "sg:classifiers":[
        {
            "category":"Retail",
            "subcategory":"Auto Repair",
            "type":"Services"
        }
    ],
    "sg:phone":"+1 770 228 0488",
    "sg:postcode":"30224",
    "sg:province":"GA",
    "sg:tags":[
        "general"
    ],
    "wof:name":"Griffin Auto Clinic",
    "wof:placetype":"venue"
},
  "geometry": {"coordinates":[-84.26585,33.236499],"type":"Point"}
}