{
  "type": "Feature",
  "properties": {
    "addr:full":"2047 Old Forge Way Marietta GA 30068",
    "addr:housenumber":"2047",
    "addr:postcode":"30068",
    "addr:street":"Old Forge Way",
    "iso:country":"US",
    "sg:address":"2047 Old Forge Way",
    "sg:city":"Marietta",
    "sg:classifiers":[
        {
            "category":"Professional",
            "type":"Services"
        }
    ],
    "sg:phone":"+1 770 993 3992",
    "sg:postcode":"30068",
    "sg:province":"GA",
    "wof:name":"Southern Network Svcs",
    "wof:placetype":"venue"
},
  "geometry": {"coordinates":[-84.402439,34.000862],"type":"Point"}
}