{
  "type": "Feature",
  "properties": {
    "iso:country":"US",
    "sg:address":"2150 Post Oak Tritt Rd # 100",
    "sg:city":"Marietta",
    "sg:classifiers":[
        {
            "category":"Retail",
            "subcategory":"Laundry & Dry Cleaning",
            "type":"Services"
        }
    ],
    "sg:phone":"+1 770 973 5301",
    "sg:postcode":"30062",
    "sg:province":"GA",
    "wof:name":"Clothing Care Cleaners",
    "wof:placetype":"venue"
},
  "geometry": {"coordinates":[-84.48809799999999,34.016701],"type":"Point"}
}