{
  "type": "Feature",
  "properties": {
    "iso:country":"US",
    "sg:address":"3045 Chastain Meadows Pkwy",
    "sg:city":"Marietta",
    "sg:classifiers":[
        {
            "category":"Government",
            "subcategory":"Fire Station",
            "type":"Public Place"
        },
        {
            "category":"Retail",
            "subcategory":"Laundry & Dry Cleaning",
            "type":"Services"
        },
        {
            "category":"Retail",
            "subcategory":"Repair Shop",
            "type":"Services"
        }
    ],
    "sg:phone":"+1 678 290 3104",
    "sg:postcode":"30066",
    "sg:province":"GA",
    "sg:tags":[
        "cleaner",
        "disaster",
        "recovery",
        "rug",
        "relief",
        "carpet"
    ],
    "wof:name":"Epic Response",
    "wof:placetype":"venue"
},
  "geometry": {"coordinates":[-84.556285,34.02606],"type":"Point"}
}