{
  "type": "Feature",
  "properties": {
    "addr:full":"186 Busbin Rd Fayetteville GA 30215",
    "addr:housenumber":"186",
    "addr:postcode":"30215",
    "addr:street":"Busbin Rd",
    "iso:country":"US",
    "sg:address":"186 Busbin Rd",
    "sg:city":"Fayetteville",
    "sg:classifiers":[
        {
            "category":"Retail",
            "subcategory":"Repair Shop",
            "type":"Services"
        }
    ],
    "sg:phone":"+1 770 460 1926",
    "sg:postcode":"30215",
    "sg:province":"GA",
    "sg:tags":[
        "sewer",
        "septic"
    ],
    "wof:name":"Fayette Septic & Sewer Inc",
    "wof:placetype":"venue"
},
  "geometry": {"coordinates":[-84.487359,33.374702],"type":"Point"}
}