{
  "type": "Feature",
  "properties": {
    "iso:country":"US",
    "sg:address":"3395 Northeast Expy NE",
    "sg:city":"Atlanta",
    "sg:classifiers":[
        {
            "category":"Professional",
            "subcategory":"Computer Services",
            "type":"Services"
        }
    ],
    "sg:phone":"+1 770 454 4300",
    "sg:postcode":"30341",
    "sg:province":"GA",
    "sg:tags":[
        "info",
        "processing"
    ],
    "wof:name":"First Data",
    "wof:placetype":"venue"
},
  "geometry": {"coordinates":[-84.272364,33.878212],"type":"Point"}
}