{
  "type": "Feature",
  "properties": {
    "addr:full":"1640 New High Shoals Rd Watkinsville GA 30677",
    "addr:housenumber":"1640",
    "addr:postcode":"30677",
    "addr:street":"New High Shoals Rd",
    "iso:country":"US",
    "sg:address":"1640 New High Shoals Rd",
    "sg:city":"Watkinsville",
    "sg:classifiers":[
        {
            "category":"Education",
            "subcategory":"School",
            "type":"Public Place"
        }
    ],
    "sg:phone":"+1 706 769 9372",
    "sg:postcode":"30677",
    "sg:province":"GA",
    "wof:name":"Westminster Christian Academy",
    "wof:placetype":"venue"
},
  "geometry": {"coordinates":[-83.435678,33.846963],"type":"Point"}
}