{
  "type": "Feature",
  "properties": {
    "addr:full":"5550 Hunters Forest Ln Atlanta GA 30349",
    "addr:housenumber":"5550",
    "addr:postcode":"30349",
    "addr:street":"Hunters Forest Ln",
    "iso:country":"US",
    "sg:address":"5550 Hunters Forest Ln",
    "sg:city":"Atlanta",
    "sg:classifiers":[
        {
            "category":"Social Services",
            "subcategory":"Child Care",
            "type":"Services"
        }
    ],
    "sg:phone":"+1 404 766 1683",
    "sg:postcode":"30349",
    "sg:province":"GA",
    "sg:tags":[
        "day"
    ],
    "wof:name":"Gails World of Tots",
    "wof:placetype":"venue"
},
  "geometry": {"coordinates":[-84.462056,33.602377],"type":"Point"}
}