{
  "type": "Feature",
  "properties": {
    "addr:full":"317 6th St NE Atlanta GA 30308",
    "addr:housenumber":"317",
    "addr:postcode":"30308",
    "addr:street":"6Th St Ne",
    "iso:country":"US",
    "sg:address":"317 6th St NE",
    "sg:city":"Atlanta",
    "sg:classifiers":[
        {
            "category":"Health Services",
            "subcategory":"Doctor",
            "type":"Services"
        },
        {
            "category":"Health Services",
            "subcategory":"Hospital",
            "type":"Services"
        }
    ],
    "sg:phone":"+1 404 291 2564",
    "sg:postcode":"30308",
    "sg:province":"GA",
    "sg:tags":[
        "nursing",
        "consultant",
        "medical",
        "practice",
        "home"
    ],
    "wof:name":"Health Resource Management Associates",
    "wof:placetype":"venue"
},
  "geometry": {"coordinates":[-84.376897,33.776178],"type":"Point"}
}