{
  "type": "Feature",
  "properties": {
    "iso:country":"US",
    "sg:address":"1443 Angus Trl SW",
    "sg:city":"Marietta",
    "sg:classifiers":[
        {
            "category":"Food & Beverages",
            "subcategory":"Groceries & Convenience Stores",
            "type":"Retail Goods"
        }
    ],
    "sg:phone":"+1 770 438 6036",
    "sg:postcode":"30008",
    "sg:province":"GA",
    "wof:name":"Medina Classic Curb",
    "wof:placetype":"venue"
},
  "geometry": {"coordinates":[-84.59569999999999,33.88916],"type":"Point"}
}