{
  "type": "Feature",
  "properties": {
    "iso:country":"US",
    "sg:address":"2998 Olive Grove Church Rd",
    "sg:city":"Roberta",
    "sg:classifiers":[
        {
            "category":"Building & Trades",
            "subcategory":"Construction",
            "type":"Services"
        }
    ],
    "sg:phone":"+1 478 836 5634",
    "sg:postcode":"31078",
    "sg:province":"GA",
    "sg:tags":[
        "mason",
        "masonry",
        "industrial",
        "contractors-commercial",
        "contractor"
    ],
    "wof:name":"General Masonry Contractors Inc",
    "wof:placetype":"venue"
},
  "geometry": {"coordinates":[-84.188749,32.715157],"type":"Point"}
}