{
  "type": "Feature",
  "properties": {
    "iso:country":"US",
    "sg:address":"2445 Flat Shoals Rd",
    "sg:city":"Atlanta",
    "sg:classifiers":[
        {
            "category":"Personal",
            "subcategory":"Barber",
            "type":"Services"
        }
    ],
    "sg:phone":"+1 678 519 3964",
    "sg:postcode":"30349",
    "sg:province":"GA",
    "wof:name":"Changing Heads Barber Shop",
    "wof:placetype":"venue"
},
  "geometry": {"coordinates":[-84.469893,33.588857],"type":"Point"}
}