{
  "type": "Feature",
  "properties": {
    "addr:full":"4909 Pulaski Rd Statesboro GA 30458",
    "addr:housenumber":"4909",
    "addr:postcode":"30458",
    "addr:street":"Pulaski Rd",
    "iso:country":"US",
    "sg:address":"4909 Pulaski Rd",
    "sg:city":"Statesboro",
    "sg:classifiers":[
        {
            "category":"Retail",
            "subcategory":"Repair Shop",
            "type":"Services"
        }
    ],
    "sg:phone":"+1 912 852 5304",
    "sg:postcode":"30458",
    "sg:province":"GA",
    "sg:tags":[
        "welding"
    ],
    "wof:name":"Laniers Welding Shop LLC",
    "wof:placetype":"venue"
},
  "geometry": {"coordinates":[-81.874989,32.428371],"type":"Point"}
}