{
  "type": "Feature",
  "properties": {
    "addr:full":"3802 Satellite Blvd Ste 200 Duluth GA 30096",
    "addr:housenumber":"3802",
    "addr:postcode":"30096",
    "addr:street":"Satellite Blvd Ste 200",
    "iso:country":"US",
    "sg:address":"3802 Satellite Blvd Ste 200",
    "sg:city":"Duluth",
    "sg:classifiers":[
        {
            "category":"Professional",
            "subcategory":"Lawyer & Legal Services",
            "type":"Services"
        }
    ],
    "sg:phone":"+1 770 813 3214",
    "sg:postcode":"30096",
    "sg:province":"GA",
    "wof:name":"Welsh Mark D PC",
    "wof:placetype":"venue"
},
  "geometry": {"coordinates":[-84.140297,33.955502],"type":"Point"}
}