{
  "type": "Feature",
  "properties": {
    "addr:full":"5184 Baldwin Ter Marietta GA 30068",
    "addr:housenumber":"5184",
    "addr:postcode":"30068",
    "addr:street":"Baldwin Ter",
    "iso:country":"US",
    "sg:address":"5184 Baldwin Ter",
    "sg:city":"Marietta",
    "sg:classifiers":[
        {
            "category":"Professional",
            "subcategory":"Business Services",
            "type":"Services"
        }
    ],
    "sg:phone":"+1 678 461 5927",
    "sg:postcode":"30068",
    "sg:province":"GA",
    "wof:name":"Impulse Solutions LLC",
    "wof:placetype":"venue"
},
  "geometry": {"coordinates":[-84.40250399999999,33.99503],"type":"Point"}
}