{
  "type": "Feature",
  "properties": {
    "addr:full":"232 Big Curve Rd Cordele GA 31015",
    "addr:housenumber":"232",
    "addr:postcode":"31015",
    "addr:street":"Big Curve Rd",
    "iso:country":"US",
    "sg:address":"232 Big Curve Rd",
    "sg:city":"Cordele",
    "sg:classifiers":[
        {
            "category":"Professional",
            "type":"Services"
        }
    ],
    "sg:phone":"+1 229 273 6582",
    "sg:postcode":"31015",
    "sg:province":"GA",
    "wof:name":"Carol Morris",
    "wof:placetype":"venue"
},
  "geometry": {"coordinates":[-83.78861999999999,31.884581],"type":"Point"}
}