{
  "type": "Feature",
  "properties": {
    "iso:country":"US",
    "sg:address":"630 Martin Luther King Jr Ave",
    "sg:city":"Cairo",
    "sg:classifiers":[
        {
            "category":"Retail",
            "subcategory":"Funeral Services",
            "type":"Services"
        }
    ],
    "sg:phone":"+1 229 377 1733",
    "sg:postcode":"39828",
    "sg:province":"GA",
    "sg:tags":[
        "director"
    ],
    "wof:name":"Williford's Funeral Home",
    "wof:placetype":"venue"
},
  "geometry": {"coordinates":[-84.217535,30.877938],"type":"Point"}
}