{
  "type": "Feature",
  "properties": {
    "addr:full":"1700 Norman Dr Valdosta GA 31601",
    "addr:housenumber":"1700",
    "addr:postcode":"31601",
    "addr:street":"Norman Dr",
    "iso:country":"US",
    "sg:address":"1700 Norman Dr",
    "sg:city":"Valdosta",
    "sg:classifiers":[
        {
            "category":"Travel",
            "subcategory":"Hotels & Motels",
            "type":"Entertainment"
        }
    ],
    "sg:phone":"+1 229 244 8846",
    "sg:postcode":"31601",
    "sg:province":"GA",
    "wof:name":"Citgo Days Inn",
    "wof:placetype":"venue"
},
  "geometry": {"coordinates":[-83.318909,30.84164],"type":"Point"}
}