{
  "type": "Feature",
  "properties": {
    "addr:full":"1503 Timberlane Rd Lawrenceville GA 30045",
    "addr:housenumber":"1503",
    "addr:postcode":"30045",
    "addr:street":"Timberlane Rd",
    "iso:country":"US",
    "sg:address":"1503 Timberlane Rd",
    "sg:city":"Lawrenceville",
    "sg:classifiers":[
        {
            "category":"Building & Trades",
            "subcategory":"Construction",
            "type":"Services"
        }
    ],
    "sg:phone":"+1 770 647 2338",
    "sg:postcode":"30045",
    "sg:province":"GA",
    "sg:tags":[
        "house"
    ],
    "wof:name":"Renoavators Inc",
    "wof:placetype":"venue"
},
  "geometry": {"coordinates":[-84.00157900000001,33.894959],"type":"Point"}
}