{
  "type": "Feature",
  "properties": {
    "addr:full":"3799 Buford Hwy NE Atlanta GA 30329",
    "addr:housenumber":"3799",
    "addr:postcode":"30329",
    "addr:street":"Buford Hwy Ne",
    "iso:country":"US",
    "sg:address":"3799 Buford Hwy NE",
    "sg:city":"Atlanta",
    "sg:classifiers":[
        {
            "category":"Personal",
            "type":"Services"
        }
    ],
    "sg:phone":"+1 404 634 2501",
    "sg:postcode":"30329",
    "sg:province":"GA",
    "sg:tags":[
        "mover"
    ],
    "wof:name":"U-Haul Company",
    "wof:placetype":"venue"
},
  "geometry": {"coordinates":[-84.315079,33.855337],"type":"Point"}
}