{
  "type": "Feature",
  "properties": {
    "iso:country":"US",
    "sg:address":"210 Thornton Dr",
    "sg:city":"Albany",
    "sg:classifiers":[
        {
            "category":"Recreation",
            "type":"Entertainment"
        }
    ],
    "sg:phone":"+1 229 430 5242",
    "sg:postcode":"31705",
    "sg:province":"GA",
    "wof:name":"Recreation & Parks Department",
    "wof:placetype":"venue"
},
  "geometry": {"coordinates":[-84.10756499999999,31.57103],"type":"Point"}
}