{
  "type": "Feature",
  "properties": {
    "iso:country":"US",
    "sg:address":"1716 Peterson Ave N",
    "sg:city":"Douglas",
    "sg:classifiers":[
        {
            "category":"Restaurant",
            "type":"Food & Drink"
        }
    ],
    "sg:menulink":"http://www.allmenus.com/ga/douglas/70756-pizza-hut/menu/",
    "sg:phone":"+1 912 384 5914",
    "sg:postcode":"31533",
    "sg:province":"GA",
    "sg:tags":[
        "american",
        "pizza"
    ],
    "wof:name":"Pizza Hut",
    "wof:placetype":"venue"
},
  "geometry": {"coordinates":[-82.850418,31.526568],"type":"Point"}
}