{
  "type": "Feature",
  "properties": {
    "addr:full":"1516 Monte Sano Ave Augusta GA 30904",
    "addr:housenumber":"1516",
    "addr:postcode":"30904",
    "addr:street":"Monte Sano Ave",
    "iso:country":"US",
    "sg:address":"1516 Monte Sano Ave",
    "sg:city":"Augusta",
    "sg:classifiers":[
        {
            "category":"Real Estate",
            "subcategory":"Real Estate Agent",
            "type":"Services"
        }
    ],
    "sg:phone":"+1 706 733 3626",
    "sg:postcode":"30904",
    "sg:province":"GA",
    "sg:tags":[
        "broker"
    ],
    "wof:name":"Minette Matthews & Associates",
    "wof:placetype":"venue"
},
  "geometry": {"coordinates":[-82.02807900000001,33.470521],"type":"Point"}
}