{
  "type": "Feature",
  "properties": {
    "iso:country":"US",
    "sg:address":"405 E Dykes St",
    "sg:city":"Cochran",
    "sg:classifiers":[
        {
            "category":"Professional",
            "subcategory":"Management & Consulting",
            "type":"Services"
        },
        {
            "category":"Real Estate",
            "subcategory":"Real Estate Operator",
            "type":"Services"
        }
    ],
    "sg:phone":"+1 478 934 9500",
    "sg:postcode":"31014",
    "sg:province":"GA",
    "sg:tags":[
        "consultant",
        "business"
    ],
    "wof:name":"Sawyer Enterprises Inc",
    "wof:placetype":"venue"
},
  "geometry": {"coordinates":[-83.351955,32.389059],"type":"Point"}
}