{
  "type": "Feature",
  "properties": {
    "iso:country":"US",
    "sg:address":"215 Foxworth Chase",
    "sg:city":"Alpharetta",
    "sg:classifiers":[
        {
            "category":"Professional",
            "subcategory":"Management & Consulting",
            "type":"Services"
        }
    ],
    "sg:phone":"+1 770 569 1538",
    "sg:postcode":"30022",
    "sg:province":"GA",
    "wof:name":"Kiksapa Inc",
    "wof:placetype":"venue"
},
  "geometry": {"coordinates":[-84.248159,34.017912],"type":"Point"}
}