{
  "type": "Feature",
  "properties": {
    "addr:full":"2100 Henderson Mill Road NE Atlanta GA 30345",
    "addr:housenumber":"2100",
    "addr:postcode":"30345",
    "addr:street":"Henderson Mill Road Ne",
    "iso:country":"US",
    "sg:address":"2100 Henderson Mill Road NE",
    "sg:city":"Atlanta",
    "sg:classifiers":[
        {
            "category":"Shopping",
            "subcategory":"Clothing, Apparel, & Fashions",
            "type":"Retail Goods"
        },
        {
            "category":"Shopping",
            "subcategory":"Party Supplies",
            "type":"Retail Goods"
        }
    ],
    "sg:phone":"+1 770 414 9900",
    "sg:postcode":"30345",
    "sg:province":"GA",
    "sg:tags":[
        "favors",
        "costume"
    ],
    "wof:name":"Halloween Costume Warehouse",
    "wof:placetype":"venue"
},
  "geometry": {"coordinates":[-84.25552,33.846963],"type":"Point"}
}