{
  "type": "Feature",
  "properties": {
    "iso:country":"US",
    "sg:address":"5615 Sweet Water Trl",
    "sg:city":"Buford",
    "sg:classifiers":[
        {
            "category":"Professional",
            "type":"Services"
        }
    ],
    "sg:phone":"+1 678 482 8794",
    "sg:postcode":"30518",
    "sg:province":"GA",
    "wof:name":"Kevin Roberts",
    "wof:placetype":"venue"
},
  "geometry": {"coordinates":[-83.96046,34.136963],"type":"Point"}
}