{
  "type": "Feature",
  "properties": {
    "iso:country":"US",
    "sg:address":"145 N Campbell Ave",
    "sg:city":"Tybee Island",
    "sg:classifiers":[
        {
            "category":"Building & Trades",
            "subcategory":"Plumbing",
            "type":"Services"
        }
    ],
    "sg:phone":"+1 912 786 9506",
    "sg:postcode":"31328",
    "sg:province":"GA",
    "sg:tags":[
        "plumbing",
        "contractor"
    ],
    "wof:name":"F C Heirs Plumbing Svc",
    "wof:placetype":"venue"
},
  "geometry": {"coordinates":[-80.84991599999999,32.014166],"type":"Point"}
}