{
  "type": "Feature",
  "properties": {
    "iso:country":"US",
    "sg:address":"4390 Forest Dr",
    "sg:city":"Augusta",
    "sg:classifiers":[
        {
            "category":"Government",
            "subcategory":"Office",
            "type":"Public Place"
        }
    ],
    "sg:phone":"+1 706 373 4285",
    "sg:postcode":"30907",
    "sg:province":"GA",
    "sg:tags":[
        "management"
    ],
    "wof:name":"Columbia Waste",
    "wof:placetype":"venue"
},
  "geometry": {"coordinates":[-82.132943,33.505827],"type":"Point"}
}