{
  "type": "Feature",
  "properties": {
    "addr:full":"2619 Bolton Rd NW Atlanta GA 30318",
    "addr:housenumber":"2619",
    "addr:postcode":"30318",
    "addr:street":"Bolton Rd Nw",
    "iso:country":"US",
    "sg:address":"2619 Bolton Rd NW",
    "sg:city":"Atlanta",
    "sg:classifiers":[
        {
            "category":"Retail",
            "subcategory":"Laundry & Dry Cleaning",
            "type":"Services"
        }
    ],
    "sg:phone":"+1 404 352 2600",
    "sg:postcode":"30318",
    "sg:province":"GA",
    "sg:tags":[
        "laundries-self"
    ],
    "wof:name":"Y K Coin Laundry",
    "wof:placetype":"venue"
},
  "geometry": {"coordinates":[-84.450169,33.820393],"type":"Point"}
}