{
  "type": "Feature",
  "properties": {
    "addr:full":"656 S Main St Baxley GA 31513",
    "addr:housenumber":"656",
    "addr:postcode":"31513",
    "addr:street":"S Main St",
    "iso:country":"US",
    "sg:address":"656 S Main St",
    "sg:city":"Baxley",
    "sg:classifiers":[
        {
            "category":"Personal",
            "subcategory":"Beauty Salon",
            "type":"Services"
        }
    ],
    "sg:phone":"+1 912 367 4441",
    "sg:postcode":"31513",
    "sg:province":"GA",
    "wof:name":"Laurie's Place",
    "wof:placetype":"venue"
},
  "geometry": {"coordinates":[-82.352507,31.768839],"type":"Point"}
}