{
  "type": "Feature",
  "properties": {
    "iso:country":"US",
    "sg:address":"4650 Jonesboro Rd",
    "sg:city":"Union City",
    "sg:classifiers":[
        {
            "category":"Banks & Credit Unions",
            "subcategory":"Bank",
            "type":"Services"
        }
    ],
    "sg:phone":"+1 770 908 2265",
    "sg:postcode":"30291",
    "sg:province":"GA",
    "wof:name":"Tucker Federal Bank",
    "wof:placetype":"venue"
},
  "geometry": {"coordinates":[-84.539703,33.568802],"type":"Point"}
}