{
  "type": "Feature",
  "properties": {
    "addr:full":"213 S Monroe St Dublin GA 31021",
    "addr:housenumber":"213",
    "addr:postcode":"31021",
    "addr:street":"S Monroe St",
    "iso:country":"US",
    "sg:address":"213 S Monroe St",
    "sg:city":"Dublin",
    "sg:classifiers":[
        {
            "category":"Professional",
            "subcategory":"Business Services",
            "type":"Services"
        }
    ],
    "sg:phone":"+1 478 274 9988",
    "sg:postcode":"31021",
    "sg:province":"GA",
    "sg:tags":[
        "recording",
        "studio"
    ],
    "sg:website":"www.gillisvideo.com",
    "wof:name":"Gil Gillis Video",
    "wof:placetype":"venue"
},
  "geometry": {"coordinates":[-82.906491,32.537612],"type":"Point"}
}