{
  "type": "Feature",
  "properties": {
    "iso:country":"US",
    "sg:address":"3782 Lawrenceville Hwy",
    "sg:city":"Tucker",
    "sg:classifiers":[
        {
            "category":"Real Estate",
            "subcategory":"Real Estate Agent",
            "type":"Services"
        }
    ],
    "sg:phone":"+1 770 496 0810",
    "sg:postcode":"30084",
    "sg:province":"GA",
    "sg:tags":[
        "broker",
        "mortgage"
    ],
    "wof:name":"Kelkris Properties",
    "wof:placetype":"venue"
},
  "geometry": {"coordinates":[-84.224129,33.849201],"type":"Point"}
}