{
  "type": "Feature",
  "properties": {
    "iso:country":"US",
    "sg:address":"3224 Still Meadows Ln",
    "sg:city":"Buford",
    "sg:classifiers":[
        {
            "category":"Building & Trades",
            "subcategory":"Locksmith",
            "type":"Services"
        }
    ],
    "sg:phone":"+1 770 945 8156",
    "sg:postcode":"30519",
    "sg:province":"GA",
    "sg:tags":[
        "key"
    ],
    "wof:name":"McGiboney Claude A",
    "wof:placetype":"venue"
},
  "geometry": {"coordinates":[-83.94628400000001,34.086613],"type":"Point"}
}