{
  "type": "Feature",
  "properties": {
    "addr:full":"140 Oak St Hampton GA 30228",
    "addr:housenumber":"140",
    "addr:postcode":"30228",
    "addr:street":"Oak St",
    "iso:country":"US",
    "sg:address":"140 Oak St",
    "sg:city":"Hampton",
    "sg:classifiers":[
        {
            "category":"Professional",
            "subcategory":"Accounting & Tax Preparation",
            "type":"Services"
        },
        {
            "category":"Professional",
            "subcategory":"Lawyer & Legal Services",
            "type":"Services"
        }
    ],
    "sg:phone":"+1 770 897 9300",
    "sg:postcode":"30228",
    "sg:province":"GA",
    "sg:tags":[
        "living",
        "bookkeeping",
        "return",
        "estate",
        "preparation-business",
        "planning",
        "trust",
        "probate"
    ],
    "wof:name":"Speedway Tax Service Inc",
    "wof:placetype":"venue"
},
  "geometry": {"coordinates":[-84.29491899999999,33.389607],"type":"Point"}
}