{
  "type": "Feature",
  "properties": {
    "addr:full":"523 Eugemar Dr Albany GA 31707",
    "addr:housenumber":"523",
    "addr:postcode":"31707",
    "addr:street":"Eugemar Dr",
    "iso:country":"US",
    "sg:address":"523 Eugemar Dr",
    "sg:city":"Albany",
    "sg:classifiers":[
        {
            "category":"Building & Trades",
            "subcategory":"Landscaping Services",
            "type":"Services"
        }
    ],
    "sg:phone":"+1 229 432 9250",
    "sg:postcode":"31707",
    "sg:province":"GA",
    "wof:name":"Phils Lawn Service",
    "wof:placetype":"venue"
},
  "geometry": {"coordinates":[-84.17803000000001,31.586463],"type":"Point"}
}