{
  "type": "Feature",
  "properties": {
    "iso:country":"US",
    "sg:address":"91 Sherwood Forest Dr",
    "sg:city":"Douglasville",
    "sg:classifiers":[
        {
            "category":"Retail",
            "subcategory":"Repair Shop",
            "type":"Services"
        }
    ],
    "sg:phone":"+1 770 489 5039",
    "sg:postcode":"30134",
    "sg:province":"GA",
    "wof:name":"Cottons Farrier Service",
    "wof:placetype":"venue"
},
  "geometry": {"coordinates":[-84.84953,33.800585],"type":"Point"}
}