{
  "type": "Feature",
  "properties": {
    "addr:full":"1305 Hawthorne Ave SE Smyrna GA 30080",
    "addr:housenumber":"1305",
    "addr:postcode":"30080",
    "addr:street":"Hawthorne Ave Se",
    "iso:country":"US",
    "sg:address":"1305 Hawthorne Ave SE",
    "sg:city":"Smyrna",
    "sg:classifiers":[
        {
            "category":"Health Services",
            "subcategory":"Medical Lab",
            "type":"Services"
        }
    ],
    "sg:phone":"+1 770 805 8111",
    "sg:postcode":"30080",
    "sg:province":"GA",
    "sg:tags":[
        "laboratory",
        "dental"
    ],
    "wof:name":"Overton & Goodwin Dental Lab",
    "wof:placetype":"venue"
},
  "geometry": {"coordinates":[-84.515891,33.890718],"type":"Point"}
}