{
  "type": "Feature",
  "properties": {
    "iso:country":"US",
    "sg:address":"1625 Keron Way",
    "sg:city":"Hephzibah",
    "sg:classifiers":[
        {
            "category":"Building & Trades",
            "subcategory":"Landscaping Services",
            "type":"Services"
        }
    ],
    "sg:phone":"+1 706 592 0258",
    "sg:postcode":"30815",
    "sg:province":"GA",
    "wof:name":"E & T Lawn Care",
    "wof:placetype":"venue"
},
  "geometry": {"coordinates":[-82.00315399999999,33.263683],"type":"Point"}
}