{
  "type": "Feature",
  "properties": {
    "addr:full":"4711 Best Road Atlanta GA 30337",
    "addr:housenumber":"4711",
    "addr:postcode":"30337",
    "addr:street":"Best Road",
    "iso:country":"US",
    "sg:address":"4711 Best Road",
    "sg:city":"Atlanta",
    "sg:classifiers":[
        {
            "category":"Travel",
            "subcategory":"Hotels & Motels",
            "type":"Entertainment"
        },
        {
            "category":"Restaurant",
            "type":"Food & Drink"
        }
    ],
    "sg:phone":"+1 404 766 7900",
    "sg:postcode":"30337",
    "sg:province":"GA",
    "wof:name":"Marrittt Khotels & Resorts",
    "wof:placetype":"venue"
},
  "geometry": {"coordinates":[-84.457909,33.626329],"type":"Point"}
}