{
  "type": "Feature",
  "properties": {
    "iso:country":"US",
    "sg:address":"8133 State Rte 112",
    "sg:city":"Camilla",
    "sg:classifiers":[
        {
            "category":"Farming",
            "subcategory":"Dairy Farm",
            "type":"Manufacturing & Wholesale Goods"
        }
    ],
    "sg:phone":"+1 229 336 7823",
    "sg:postcode":"31730",
    "sg:province":"GA",
    "wof:name":"Butcher Farms Inc",
    "wof:placetype":"venue"
},
  "geometry": {"coordinates":[-84.115255,31.302076],"type":"Point"}
}