{
  "type": "Feature",
  "properties": {
    "iso:country":"US",
    "sg:address":"2020 Abington Ln",
    "sg:city":"Snellville",
    "sg:classifiers":[
        {
            "category":"Building & Trades",
            "subcategory":"Construction",
            "type":"Services"
        }
    ],
    "sg:phone":"+1 770 972 9150",
    "sg:postcode":"30078",
    "sg:province":"GA",
    "sg:tags":[
        "house"
    ],
    "wof:name":"Alexander Williams Cnstr",
    "wof:placetype":"venue"
},
  "geometry": {"coordinates":[-83.99651799999999,33.855236],"type":"Point"}
}