{
  "type": "Feature",
  "properties": {
    "addr:full":"377 S Main St Alpharetta GA 30004",
    "addr:housenumber":"377",
    "addr:postcode":"30004",
    "addr:street":"S Main St",
    "iso:country":"US",
    "sg:address":"377 S Main St",
    "sg:city":"Alpharetta",
    "sg:classifiers":[
        {
            "category":"Shopping",
            "subcategory":"Used Merchandise",
            "type":"Retail Goods"
        }
    ],
    "sg:phone":"+1 770 713 2331",
    "sg:postcode":"30004",
    "sg:province":"GA",
    "wof:name":"Buck & Grannys",
    "wof:placetype":"venue"
},
  "geometry": {"coordinates":[-84.30318,34.067118],"type":"Point"}
}