{
  "type": "Feature",
  "properties": {
    "iso:country":"US",
    "sg:address":"1790 Niskey Cove Rd SW",
    "sg:city":"Atlanta",
    "sg:classifiers":[
        {
            "category":"Organizations",
            "subcategory":"Religious Organization",
            "type":"Services"
        }
    ],
    "sg:phone":"+1 404 349 3131",
    "sg:postcode":"30331",
    "sg:province":"GA",
    "wof:name":"Faith Temple",
    "wof:placetype":"venue"
},
  "geometry": {"coordinates":[-84.529967,33.708287],"type":"Point"}
}