{
  "type": "Feature",
  "properties": {
    "addr:full":"3323 Gum Creek Airport Rd Roopville GA 30170",
    "addr:housenumber":"3323",
    "addr:postcode":"30170",
    "addr:street":"Gum Creek Airport Rd",
    "iso:country":"US",
    "sg:address":"3323 Gum Creek Airport Rd",
    "sg:city":"Roopville",
    "sg:classifiers":[
        {
            "category":"Organizations",
            "subcategory":"Religious Organization",
            "type":"Services"
        }
    ],
    "sg:phone":"+1 770 832 8822",
    "sg:postcode":"30170",
    "sg:province":"GA",
    "sg:tags":[
        "church"
    ],
    "wof:name":"Unity Baptist Church",
    "wof:placetype":"venue"
},
  "geometry": {"coordinates":[-85.180373,33.40378],"type":"Point"}
}