{
  "type": "Feature",
  "properties": {
    "addr:full":"3140 Westpoint Rd Lagrange GA 30240",
    "addr:housenumber":"3140",
    "addr:postcode":"30240",
    "addr:street":"Westpoint Rd",
    "iso:country":"US",
    "sg:address":"3140 Westpoint Rd",
    "sg:city":"Lagrange",
    "sg:classifiers":[
        {
            "category":"Building & Trades",
            "subcategory":"Construction",
            "type":"Services"
        }
    ],
    "sg:phone":"+1 706 882 5115",
    "sg:postcode":"30240",
    "sg:province":"GA",
    "wof:name":"Quality Portable Buildings",
    "wof:placetype":"venue"
},
  "geometry": {"coordinates":[-85.103916,33.013028],"type":"Point"}
}