{
  "type": "Feature",
  "properties": {
    "iso:country":"US",
    "sg:address":"1409 W Baker Hwy",
    "sg:city":"Douglas",
    "sg:classifiers":[
        {
            "category":"Banks & Credit Unions",
            "subcategory":"Bank",
            "type":"Services"
        }
    ],
    "sg:phone":"+1 912 384 3893",
    "sg:postcode":"31533",
    "sg:province":"GA",
    "sg:tags":[
        "financing"
    ],
    "sg:website":"www.loansfast.com",
    "wof:name":"American General Finance Inc",
    "wof:placetype":"venue"
},
  "geometry": {"coordinates":[-82.86982500000001,31.498681],"type":"Point"}
}