{
  "type": "Feature",
  "properties": {
    "iso:country":"US",
    "sg:address":"485 Milledgeville Rd",
    "sg:city":"Eatonton",
    "sg:classifiers":[
        {
            "category":"Government",
            "subcategory":"Office",
            "type":"Public Place"
        }
    ],
    "sg:phone":"+1 706 485 2725",
    "sg:postcode":"31024",
    "sg:province":"GA",
    "sg:tags":[
        "federal",
        "program"
    ],
    "wof:name":"Us Food & Drug Administration",
    "wof:placetype":"venue"
},
  "geometry": {"coordinates":[-83.362684,33.274639],"type":"Point"}
}