{
  "type": "Feature",
  "properties": {
    "addr:full":"986 Progress Rd Ellijay GA 30540",
    "addr:housenumber":"986",
    "addr:postcode":"30540",
    "addr:street":"Progress Rd",
    "iso:country":"US",
    "sg:address":"986 Progress Rd",
    "sg:city":"Ellijay",
    "sg:classifiers":[
        {
            "category":"Retail",
            "subcategory":"Auto Repair",
            "type":"Services"
        }
    ],
    "sg:phone":"+1 706 636 5400",
    "sg:postcode":"30540",
    "sg:province":"GA",
    "sg:tags":[
        "carwash",
        "automotive"
    ],
    "wof:name":"Clean Car Center",
    "wof:placetype":"venue"
},
  "geometry": {"coordinates":[-84.493369,34.667983],"type":"Point"}
}