{
  "type": "Feature",
  "properties": {
    "iso:country":"US",
    "sg:address":"658 W 3rd St",
    "sg:city":"Jackson",
    "sg:classifiers":[
        {
            "category":"Real Estate",
            "subcategory":"Real Estate Agent",
            "type":"Services"
        }
    ],
    "sg:phone":"+1 770 775 5714",
    "sg:postcode":"30233",
    "sg:province":"GA",
    "wof:name":"Coldwell Banker",
    "wof:placetype":"venue"
},
  "geometry": {"coordinates":[-83.97336199999999,33.294241],"type":"Point"}
}