{
  "type": "Feature",
  "properties": {
    "iso:country":"US",
    "sg:address":"609 Academy Ave",
    "sg:city":"Dublin",
    "sg:classifiers":[
        {
            "category":"Building & Trades",
            "subcategory":"Construction",
            "type":"Services"
        }
    ],
    "sg:phone":"+1 478 296 9347",
    "sg:postcode":"31021",
    "sg:province":"GA",
    "sg:tags":[
        "bathroom",
        "remodeling"
    ],
    "wof:name":"Re-Bath Of Central Georgia",
    "wof:placetype":"venue"
},
  "geometry": {"coordinates":[-82.964371,32.495875],"type":"Point"}
}