{
  "type": "Feature",
  "properties": {
    "addr:full":"301 Olive St Hinesville GA 31313",
    "addr:housenumber":"301",
    "addr:postcode":"31313",
    "addr:street":"Olive St",
    "iso:country":"US",
    "sg:address":"301 Olive St",
    "sg:city":"Hinesville",
    "sg:classifiers":[
        {
            "category":"Government",
            "subcategory":"Office",
            "type":"Public Place"
        }
    ],
    "sg:phone":"+1 912 876 6573",
    "sg:postcode":"31313",
    "sg:province":"GA",
    "sg:tags":[
        "village"
    ],
    "wof:name":"Hinesville City Government Ofc",
    "wof:placetype":"venue"
},
  "geometry": {"coordinates":[-81.60549,31.848774],"type":"Point"}
}