{
  "type": "Feature",
  "properties": {
    "iso:country":"US",
    "sg:address":"5319 Price Rd",
    "sg:city":"Gainesville",
    "sg:classifiers":[
        {
            "category":"Place Of Worship",
            "subcategory":"Church",
            "type":"Public Place"
        },
        {
            "category":"Place Of Worship",
            "type":"Public Place"
        }
    ],
    "sg:phone":"+1 770 503 9049",
    "sg:postcode":"30506",
    "sg:province":"GA",
    "sg:tags":[
        "christ",
        "churches-community"
    ],
    "wof:name":"Lighthouse Community Church Inc",
    "wof:placetype":"venue"
},
  "geometry": {"coordinates":[-83.948684,34.403277],"type":"Point"}
}