{
  "type": "Feature",
  "properties": {
    "addr:full":"1100 Kennesaw Due West Rd NW Kennesaw GA 30152",
    "addr:housenumber":"1100",
    "addr:postcode":"30152",
    "addr:street":"Kennesaw Due West Rd Nw",
    "iso:country":"US",
    "sg:address":"1100 Kennesaw Due West Rd NW",
    "sg:city":"Kennesaw",
    "sg:classifiers":[
        {
            "category":"Professional",
            "subcategory":"Employment Agencies",
            "type":"Services"
        }
    ],
    "sg:phone":"+1 770 590 0705",
    "sg:postcode":"30152",
    "sg:province":"GA",
    "sg:tags":[
        "opportunity"
    ],
    "wof:name":"Lucas Group",
    "wof:placetype":"venue"
},
  "geometry": {"coordinates":[-84.636971,33.9818],"type":"Point"}
}