{
  "type": "Feature",
  "properties": {
    "iso:country":"US",
    "sg:address":"3959 Bolton St",
    "sg:city":"Augusta",
    "sg:classifiers":[
        {
            "category":"Building & Trades",
            "subcategory":"Construction",
            "type":"Services"
        },
        {
            "category":"Home & Garden",
            "subcategory":"Furniture",
            "type":"Retail Goods"
        }
    ],
    "sg:phone":"+1 706 868 6006",
    "sg:postcode":"30909",
    "sg:province":"GA",
    "sg:tags":[
        "maker",
        "cabinet"
    ],
    "wof:name":"Cox Cabinets & Wood Works",
    "wof:placetype":"venue"
},
  "geometry": {"coordinates":[-82.131429,33.459672],"type":"Point"}
}