{
  "type": "Feature",
  "properties": {
    "iso:country":"US",
    "sg:address":"1030 W Mill Dr NW",
    "sg:city":"Kennesaw",
    "sg:classifiers":[
        {
            "category":"Building & Trades",
            "subcategory":"Electrical",
            "type":"Services"
        }
    ],
    "sg:phone":"+1 770 429 0601",
    "sg:postcode":"30152",
    "sg:province":"GA",
    "sg:tags":[
        "electric",
        "contractor"
    ],
    "wof:name":"C & R Electric",
    "wof:placetype":"venue"
},
  "geometry": {"coordinates":[-84.674605,33.981665],"type":"Point"}
}