{
  "type": "Feature",
  "properties": {
    "iso:country":"US",
    "sg:address":"1929 Shorter Ave",
    "sg:city":"Rome",
    "sg:classifiers":[
        {
            "category":"Shopping",
            "subcategory":"Florist",
            "type":"Retail Goods"
        }
    ],
    "sg:phone":"+1 706 232 9761",
    "sg:postcode":"30165",
    "sg:province":"GA",
    "wof:name":"Flowers By Jacki",
    "wof:placetype":"venue"
},
  "geometry": {"coordinates":[-85.22044,34.270454],"type":"Point"}
}