{
  "type": "Feature",
  "properties": {
    "iso:country":"US",
    "sg:address":"1509 Mill Grove Ct",
    "sg:city":"Dacula",
    "sg:classifiers":[
        {
            "category":"Restaurant",
            "type":"Food & Drink"
        }
    ],
    "sg:phone":"+1 770 546 3238",
    "sg:postcode":"30019",
    "sg:province":"GA",
    "sg:tags":[
        "eating"
    ],
    "wof:name":"Chef At Svc",
    "wof:placetype":"venue"
},
  "geometry": {"coordinates":[-83.909043,34.04494],"type":"Point"}
}