{
  "type": "Feature",
  "properties": {
    "addr:full":"1180 Sunrise Field Ct Lawrenceville GA 30043",
    "addr:housenumber":"1180",
    "addr:postcode":"30043",
    "addr:street":"Sunrise Field Ct",
    "iso:country":"US",
    "sg:address":"1180 Sunrise Field Ct",
    "sg:city":"Lawrenceville",
    "sg:classifiers":[
        {
            "category":"Building & Trades",
            "subcategory":"Construction",
            "type":"Services"
        }
    ],
    "sg:phone":"+1 770 513 3325",
    "sg:postcode":"30043",
    "sg:province":"GA",
    "sg:tags":[
        "nonresidential"
    ],
    "wof:name":"GK Construction Co Inc",
    "wof:placetype":"venue"
},
  "geometry": {"coordinates":[-83.97074600000001,33.999455],"type":"Point"}
}