{
  "type": "Feature",
  "properties": {
    "iso:country":"US",
    "sg:address":"705 N Caswell St",
    "sg:city":"Glennville",
    "sg:classifiers":[
        {
            "category":"Government",
            "subcategory":"Office",
            "type":"Public Place"
        }
    ],
    "sg:phone":"+1 912 654 2421",
    "sg:postcode":"30427",
    "sg:province":"GA",
    "sg:tags":[
        "admin",
        "affairs",
        "state"
    ],
    "wof:name":"Veterans Service",
    "wof:placetype":"venue"
},
  "geometry": {"coordinates":[-81.925011,31.946648],"type":"Point"}
}