{
  "type": "Feature",
  "properties": {
    "addr:full":"11585 Jones Bridge Rd Ste 500 Alpharetta GA 30022",
    "addr:housenumber":"11585",
    "addr:postcode":"30022",
    "addr:street":"Jones Bridge Rd Ste 500",
    "iso:country":"US",
    "sg:address":"11585 Jones Bridge Rd Ste 500",
    "sg:city":"Alpharetta",
    "sg:classifiers":[
        {
            "category":"Food & Beverages",
            "subcategory":"Groceries & Convenience Stores",
            "type":"Retail Goods"
        }
    ],
    "sg:phone":"+1 770 751 4580",
    "sg:postcode":"30022",
    "sg:province":"GA",
    "wof:name":"Publix Super Markets",
    "wof:placetype":"venue"
},
  "geometry": {"coordinates":[-84.215093,34.061594],"type":"Point"}
}