{
  "type": "Feature",
  "properties": {
    "iso:country":"US",
    "sg:address":"244 Shady Hills Rd",
    "sg:city":"Hartwell",
    "sg:classifiers":[
        {
            "category":"Building & Trades",
            "subcategory":"Construction",
            "type":"Services"
        }
    ],
    "sg:phone":"+1 706 376 0727",
    "sg:postcode":"30643",
    "sg:province":"GA",
    "sg:tags":[
        "altering",
        "house",
        "remodeling",
        "contractor"
    ],
    "wof:name":"Blazek Construction",
    "wof:placetype":"venue"
},
  "geometry": {"coordinates":[-82.932997,34.378462],"type":"Point"}
}