{
  "type": "Feature",
  "properties": {
    "iso:country":"US",
    "sg:address":"1990 Sturbridge Ln",
    "sg:city":"Buford",
    "sg:classifiers":[
        {
            "category":"Professional",
            "subcategory":"Management & Consulting",
            "type":"Services"
        }
    ],
    "sg:phone":"+1 770 271 0238",
    "sg:postcode":"30519",
    "sg:province":"GA",
    "wof:name":"Ivan Burba Consultant",
    "wof:placetype":"venue"
},
  "geometry": {"coordinates":[-83.979432,34.079593],"type":"Point"}
}