{
  "type": "Feature",
  "properties": {
    "iso:country":"US",
    "sg:address":"402 SW Broad St",
    "sg:city":"Fairburn",
    "sg:classifiers":[
        {
            "category":"Professional",
            "type":"Services"
        }
    ],
    "sg:phone":"+1 770 774 2800",
    "sg:postcode":"30213",
    "sg:province":"GA",
    "sg:tags":[
        "establishment"
    ],
    "wof:name":"Claw Foot Connection",
    "wof:placetype":"venue"
},
  "geometry": {"coordinates":[-84.591303,33.557798],"type":"Point"}
}