{
  "type": "Feature",
  "properties": {
    "addr:full":"555 Cassidy Rd Thomasville GA 31792",
    "addr:housenumber":"555",
    "addr:postcode":"31792",
    "addr:street":"Cassidy Rd",
    "iso:country":"US",
    "sg:address":"555 Cassidy Rd",
    "sg:city":"Thomasville",
    "sg:classifiers":[
        {
            "category":"Real Estate",
            "subcategory":"Real Estate Operator",
            "type":"Services"
        }
    ],
    "sg:phone":"+1 229 226 0016",
    "sg:postcode":"31792",
    "sg:province":"GA",
    "sg:tags":[
        "building",
        "apartment"
    ],
    "wof:name":"Villa North Apts",
    "wof:placetype":"venue"
},
  "geometry": {"coordinates":[-83.99208299999999,30.853024],"type":"Point"}
}