{
  "type": "Feature",
  "properties": {
    "addr:full":"57 Eagle Dr Tifton GA 31793",
    "addr:housenumber":"57",
    "addr:postcode":"31793",
    "addr:street":"Eagle Dr",
    "iso:country":"US",
    "sg:address":"57 Eagle Dr",
    "sg:city":"Tifton",
    "sg:classifiers":[
        {
            "category":"Professional",
            "subcategory":"Business Services",
            "type":"Services"
        }
    ],
    "sg:phone":"+1 229 382 2521",
    "sg:postcode":"31793",
    "sg:province":"GA",
    "wof:name":"Dorsett Interiors By Amelia",
    "wof:placetype":"venue"
},
  "geometry": {"coordinates":[-83.5814,31.44828],"type":"Point"}
}