{
  "type": "Feature",
  "properties": {
    "iso:country":"US",
    "sg:address":"1560 US Hwy 1",
    "sg:city":"Louisville",
    "sg:classifiers":[
        {
            "category":"Shopping",
            "subcategory":"Department Store",
            "type":"Retail Goods"
        }
    ],
    "sg:phone":"+1 478 625 8222",
    "sg:postcode":"30434",
    "sg:province":"GA",
    "sg:tags":[
        "shop"
    ],
    "wof:name":"Family Dollar Store",
    "wof:placetype":"venue"
},
  "geometry": {"coordinates":[-82.40079799999999,33.012858],"type":"Point"}
}