{
  "type": "Feature",
  "properties": {
    "addr:full":"4482 Rowland Ct Stone Mountain GA 30083",
    "addr:housenumber":"4482",
    "addr:postcode":"30083",
    "addr:street":"Rowland Ct",
    "iso:country":"US",
    "sg:address":"4482 Rowland Ct",
    "sg:city":"Stone Mountain",
    "sg:classifiers":[
        {
            "category":"Organizations",
            "subcategory":"Community Association",
            "type":"Services"
        }
    ],
    "sg:phone":"+1 404 294 1579",
    "sg:postcode":"30083",
    "sg:province":"GA",
    "wof:name":"International Assoc of LI",
    "wof:placetype":"venue"
},
  "geometry": {"coordinates":[-84.20642599999999,33.780532],"type":"Point"}
}