{
  "type": "Feature",
  "properties": {
    "iso:country":"US",
    "sg:address":"30 Chateau Dr SE",
    "sg:city":"Rome",
    "sg:classifiers":[
        {
            "category":"Government",
            "subcategory":"Office",
            "type":"Public Place"
        }
    ],
    "sg:phone":"+1 706 802 5460",
    "sg:postcode":"30161",
    "sg:province":"GA",
    "wof:name":"Womens Outreach Program",
    "wof:placetype":"venue"
},
  "geometry": {"coordinates":[-85.153571,34.221859],"type":"Point"}
}