{
  "type": "Feature",
  "properties": {
    "addr:full":"2297 Highway 20 E McDonough GA 30252",
    "addr:housenumber":"2297",
    "addr:postcode":"30252",
    "addr:street":"Highway 20 E",
    "iso:country":"US",
    "sg:address":"2297 Highway 20 E",
    "sg:city":"McDonough",
    "sg:classifiers":[
        {
            "category":"Food & Beverages",
            "subcategory":"Groceries & Convenience Stores",
            "type":"Retail Goods"
        }
    ],
    "sg:phone":"+1 678 583 6808",
    "sg:postcode":"30252",
    "sg:province":"GA",
    "sg:website":"www.bp.com",
    "wof:name":"Provisions Bp",
    "wof:placetype":"venue"
},
  "geometry": {"coordinates":[-84.08760100000001,33.489601],"type":"Point"}
}