{
  "type": "Feature",
  "properties": {
    "addr:full":"451 Denham St Riverdale GA 30274",
    "addr:housenumber":"451",
    "addr:postcode":"30274",
    "addr:street":"Denham St",
    "iso:country":"US",
    "sg:address":"451 Denham St",
    "sg:city":"Riverdale",
    "sg:classifiers":[
        {
            "category":"Restaurant",
            "type":"Food & Drink"
        }
    ],
    "sg:phone":"+1 770 997 7874",
    "sg:postcode":"30274",
    "sg:province":"GA",
    "sg:tags":[
        "eating"
    ],
    "wof:name":"Creative Catering By Mary",
    "wof:placetype":"venue"
},
  "geometry": {"coordinates":[-84.40592700000001,33.576742],"type":"Point"}
}