{
  "type": "Feature",
  "properties": {
    "addr:full":"1133 Lloyd Rd Sycamore GA 31790",
    "addr:housenumber":"1133",
    "addr:postcode":"31790",
    "addr:street":"Lloyd Rd",
    "iso:country":"US",
    "sg:address":"1133 Lloyd Rd",
    "sg:city":"Sycamore",
    "sg:classifiers":[
        {
            "category":"Farming",
            "subcategory":"Farm",
            "type":"Manufacturing & Wholesale Goods"
        }
    ],
    "sg:phone":"+1 229 567 4469",
    "sg:postcode":"31790",
    "sg:province":"GA",
    "sg:tags":[
        "crop",
        "general"
    ],
    "wof:name":"L & F Farms Inc",
    "wof:placetype":"venue"
},
  "geometry": {"coordinates":[-83.544248,31.613568],"type":"Point"}
}