{
  "type": "Feature",
  "properties": {
    "addr:full":"2000 Riverside Pkwy Ste 102 Lawrenceville GA 30043",
    "addr:housenumber":"2000",
    "addr:postcode":"30043",
    "addr:street":"Riverside Pkwy Ste 102",
    "iso:country":"US",
    "sg:address":"2000 Riverside Pkwy Ste 102",
    "sg:city":"Lawrenceville",
    "sg:classifiers":[
        {
            "category":"Education",
            "subcategory":"Special Training",
            "type":"Public Place"
        }
    ],
    "sg:phone":"+1 770 822 6566",
    "sg:postcode":"30043",
    "sg:province":"GA",
    "sg:tags":[
        "tutoring"
    ],
    "wof:name":"Basics Learning Center Inc",
    "wof:placetype":"venue"
},
  "geometry": {"coordinates":[-84.035301,33.9683],"type":"Point"}
}