{
  "type": "Feature",
  "properties": {
    "addr:full":"7469 Tara Blvd Jonesboro GA 30236",
    "addr:housenumber":"7469",
    "addr:postcode":"30236",
    "addr:street":"Tara Blvd",
    "iso:country":"US",
    "sg:address":"7469 Tara Blvd",
    "sg:city":"Jonesboro",
    "sg:classifiers":[
        {
            "category":"Freight",
            "type":"Transportation"
        }
    ],
    "sg:phone":"+1 770 478 5650",
    "sg:postcode":"30236",
    "sg:province":"GA",
    "sg:tags":[
        "warehouse",
        "self",
        "storage"
    ],
    "wof:name":"Colonial Storage Center 151",
    "wof:placetype":"venue"
},
  "geometry": {"coordinates":[-84.366784,33.541203],"type":"Point"}
}