{
  "type": "Feature",
  "properties": {
    "addr:full":"329 S Houston Lake Rd Warner Robins GA 31088",
    "addr:housenumber":"329",
    "addr:postcode":"31088",
    "addr:street":"S Houston Lake Rd",
    "iso:country":"US",
    "sg:address":"329 S Houston Lake Rd",
    "sg:city":"Warner Robins",
    "sg:classifiers":[
        {
            "category":"Shopping",
            "subcategory":"Florist",
            "type":"Retail Goods"
        }
    ],
    "sg:phone":"+1 478 971 4856",
    "sg:postcode":"31088",
    "sg:province":"GA",
    "sg:website":"www.warnerrobinsflowers.com",
    "wof:name":"Forget-Me-Not Flowers of Warner Robins",
    "wof:placetype":"venue"
},
  "geometry": {"coordinates":[-83.67894800000001,32.611427],"type":"Point"}
}