{
  "type": "Feature",
  "properties": {
    "iso:country":"US",
    "sg:address":"1020 Broadway Ave",
    "sg:city":"Columbus",
    "sg:classifiers":[
        {
            "category":"Restaurant",
            "type":"Food & Drink"
        }
    ],
    "sg:phone":"+1 706 576 6991",
    "sg:postcode":"31901",
    "sg:province":"GA",
    "wof:name":"Picasso Pizza",
    "wof:placetype":"venue"
},
  "geometry": {"coordinates":[-84.99311299999999,32.466318],"type":"Point"}
}