{
  "type": "Feature",
  "properties": {
    "iso:country":"US",
    "sg:address":"61 Forsyth Street Suite 8B-70",
    "sg:city":"Atlanta",
    "sg:classifiers":[
        {
            "category":"Banks & Credit Unions",
            "subcategory":"Financial Services",
            "type":"Services"
        }
    ],
    "sg:phone":"+1 770 441 9235",
    "sg:postcode":"30303",
    "sg:province":"GA",
    "sg:website":"www.excelfcu.org",
    "wof:name":"Excel Federal Credit Union",
    "wof:placetype":"venue"
},
  "geometry": {"coordinates":[-84.393647,33.753728],"type":"Point"}
}