{
  "type": "Feature",
  "properties": {
    "addr:full":"355 S Atlanta St Roswell GA 30075",
    "addr:housenumber":"355",
    "addr:postcode":"30075",
    "addr:street":"S Atlanta St",
    "iso:country":"US",
    "sg:address":"355 S Atlanta St",
    "sg:city":"Roswell",
    "sg:classifiers":[
        {
            "category":"Health Services",
            "subcategory":"Dentist",
            "type":"Services"
        }
    ],
    "sg:phone":"+1 770 998 1466",
    "sg:postcode":"30075",
    "sg:province":"GA",
    "wof:name":"Evans Robert A DMD",
    "wof:placetype":"venue"
},
  "geometry": {"coordinates":[-84.3601,34.008701],"type":"Point"}
}