{
  "type": "Feature",
  "properties": {
    "iso:country":"US",
    "sg:address":"107 E Barnard St",
    "sg:city":"Glennville",
    "sg:classifiers":[
        {
            "category":"Insurance",
            "subcategory":"Hazard Insurance",
            "type":"Services"
        }
    ],
    "sg:phone":"+1 912 654 1221",
    "sg:postcode":"30427",
    "sg:province":"GA",
    "sg:tags":[
        "commercial",
        "business"
    ],
    "wof:name":"Keith Beasley & Associates",
    "wof:placetype":"venue"
},
  "geometry": {"coordinates":[-81.928735,31.936609],"type":"Point"}
}