{
  "type": "Feature",
  "properties": {
    "addr:full":"6930 Buford Hwy NE Atlanta GA 30340",
    "addr:housenumber":"6930",
    "addr:postcode":"30340",
    "addr:street":"Buford Hwy Ne",
    "iso:country":"US",
    "sg:address":"6930 Buford Hwy NE",
    "sg:city":"Atlanta",
    "sg:classifiers":[
        {
            "category":"Insurance",
            "subcategory":"Insurance Agent",
            "type":"Services"
        },
        {
            "category":"Insurance",
            "subcategory":"Hazard Insurance",
            "type":"Services"
        },
        {
            "category":"Banks & Credit Unions",
            "subcategory":"Financial Services",
            "type":"Services"
        }
    ],
    "sg:phone":"+1 877 669 6877",
    "sg:postcode":"30340",
    "sg:province":"GA",
    "sg:tags":[
        "sharing",
        "profit",
        "auto",
        "plan",
        "property",
        "casualty",
        "pension"
    ],
    "wof:name":"Nationwide Insurance",
    "wof:placetype":"venue"
},
  "geometry": {"coordinates":[-84.250444,33.924151],"type":"Point"}
}