{
  "type": "Feature",
  "properties": {
    "iso:country":"US",
    "sg:address":"40 Conners Rd",
    "sg:city":"Villa Rica",
    "sg:classifiers":[
        {
            "category":"Manufacturing",
            "subcategory":"Retail Goods",
            "type":"Manufacturing & Wholesale Goods"
        }
    ],
    "sg:phone":"+1 770 459 3653",
    "sg:postcode":"30180",
    "sg:province":"GA",
    "sg:tags":[
        "manufacturer"
    ],
    "wof:name":"Mary Ann Industries Inc",
    "wof:placetype":"venue"
},
  "geometry": {"coordinates":[-84.904957,33.730638],"type":"Point"}
}