{
  "type": "Feature",
  "properties": {
    "addr:full":"118 Orchard Rd Perry GA 31069",
    "addr:housenumber":"118",
    "addr:postcode":"31069",
    "addr:street":"Orchard Rd",
    "iso:country":"US",
    "sg:address":"118 Orchard Rd",
    "sg:city":"Perry",
    "sg:classifiers":[
        {
            "category":"Building & Trades",
            "subcategory":"Landscaping Services",
            "type":"Services"
        }
    ],
    "sg:phone":"+1 478 987 7886",
    "sg:postcode":"31069",
    "sg:province":"GA",
    "sg:tags":[
        "landscape"
    ],
    "wof:name":"International Landscaping",
    "wof:placetype":"venue"
},
  "geometry": {"coordinates":[-83.826178,32.39401],"type":"Point"}
}