{
  "type": "Feature",
  "properties": {
    "iso:country":"US",
    "sg:address":"761 Courtenay Dr NE",
    "sg:city":"Atlanta",
    "sg:classifiers":[
        {
            "category":"Professional",
            "subcategory":"Management & Consulting",
            "type":"Services"
        }
    ],
    "sg:phone":"+1 404 892 9520",
    "sg:postcode":"30306",
    "sg:province":"GA",
    "wof:name":"Bene Julian & Associates",
    "wof:placetype":"venue"
},
  "geometry": {"coordinates":[-84.362736,33.789606],"type":"Point"}
}