{
  "type": "Feature",
  "properties": {
    "iso:country":"US",
    "sg:address":"1707 Iola Dr",
    "sg:city":"Valdosta",
    "sg:classifiers":[
        {
            "category":"Professional",
            "subcategory":"Advertising",
            "type":"Services"
        }
    ],
    "sg:phone":"+1 229 249 9525",
    "sg:postcode":"31602",
    "sg:province":"GA",
    "sg:tags":[
        "outdoor"
    ],
    "wof:name":"Herndon Ventures Inc",
    "wof:placetype":"venue"
},
  "geometry": {"coordinates":[-83.282484,30.854201],"type":"Point"}
}