{
  "type": "Feature",
  "properties": {
    "addr:full":"4780 Ashford Dunwoody Rd Atlanta GA 30338",
    "addr:housenumber":"4780",
    "addr:postcode":"30338",
    "addr:street":"Ashford Dunwoody Rd",
    "iso:country":"US",
    "sg:address":"4780 Ashford Dunwoody Rd",
    "sg:city":"Atlanta",
    "sg:classifiers":[
        {
            "category":"Professional",
            "subcategory":"Computer Services",
            "type":"Services"
        }
    ],
    "sg:phone":"+1 678 303 2750",
    "sg:postcode":"30338",
    "sg:province":"GA",
    "sg:tags":[
        "telecommunication"
    ],
    "wof:name":"Voiceconnect Inc",
    "wof:placetype":"venue"
},
  "geometry": {"coordinates":[-84.337855,33.934646],"type":"Point"}
}