{
  "type": "Feature",
  "properties": {
    "iso:country":"US",
    "sg:address":"2525 Bangor Ct",
    "sg:city":"Snellville",
    "sg:classifiers":[
        {
            "category":"Professional",
            "subcategory":"Business Services",
            "type":"Services"
        }
    ],
    "sg:phone":"+1 770 557 0025",
    "sg:postcode":"30078",
    "sg:province":"GA",
    "wof:name":"Professional Interiors",
    "wof:placetype":"venue"
},
  "geometry": {"coordinates":[-84.03321699999999,33.87905],"type":"Point"}
}