{
  "type": "Feature",
  "properties": {
    "iso:country":"US",
    "sg:address":"3305 Commerce Dr",
    "sg:city":"Augusta",
    "sg:classifiers":[
        {
            "category":"Autos & Motor Vehicles",
            "subcategory":"Automobile Sales",
            "type":"Retail Goods"
        }
    ],
    "sg:phone":"+1 706 312 2110",
    "sg:postcode":"30909",
    "sg:province":"GA",
    "sg:tags":[
        "car",
        "dealer"
    ],
    "wof:name":"Bob Richards Chevrolet",
    "wof:placetype":"venue"
},
  "geometry": {"coordinates":[-82.058932,33.45032],"type":"Point"}
}