{
  "type": "Feature",
  "properties": {
    "iso:country":"US",
    "sg:address":"3205 Canton Rd",
    "sg:city":"Marietta",
    "sg:classifiers":[
        {
            "category":"Restaurant",
            "type":"Food & Drink"
        }
    ],
    "sg:menulink":"http://www.allmenus.com/ga/northeast-cobb/242063-g-angelos/menu/",
    "sg:phone":"+1 770 424 1800",
    "sg:postcode":"30066",
    "sg:province":"GA",
    "sg:tags":[
        "italian"
    ],
    "wof:name":"G Angelos",
    "wof:placetype":"venue"
},
  "geometry": {"coordinates":[-84.52781400000001,34.029825],"type":"Point"}
}