{
  "type": "Feature",
  "properties": {
    "iso:country":"US",
    "sg:address":"1429 Fairmont St NW",
    "sg:city":"Atlanta",
    "sg:classifiers":[
        {
            "category":"Professional",
            "subcategory":"Business Services",
            "type":"Services"
        }
    ],
    "sg:phone":"+1 404 350 0427",
    "sg:postcode":"30318",
    "sg:province":"GA",
    "sg:tags":[
        "holding"
    ],
    "wof:name":"Fox Mountain Holdings",
    "wof:placetype":"venue"
},
  "geometry": {"coordinates":[-84.422057,33.794598],"type":"Point"}
}