{
  "type": "Feature",
  "properties": {
    "addr:full":"4 Amlajack Blvd Newnan GA 30265",
    "addr:housenumber":"4",
    "addr:postcode":"30265",
    "addr:street":"Amlajack Blvd",
    "iso:country":"US",
    "sg:address":"4 Amlajack Blvd",
    "sg:city":"Newnan",
    "sg:classifiers":[
        {
            "category":"Professional",
            "subcategory":"Accounting & Tax Preparation",
            "type":"Services"
        },
        {
            "category":"Banks & Credit Unions",
            "subcategory":"Financial Services",
            "type":"Services"
        }
    ],
    "sg:phone":"+1 770 253 7530",
    "sg:postcode":"30265",
    "sg:province":"GA",
    "sg:tags":[
        "return",
        "preparation-business",
        "taxes-consultants",
        "loan",
        "reporting",
        "representative",
        "alternative",
        "bookkeeping"
    ],
    "sg:website":"http://www.hrblock.com",
    "wof:name":"H&R Block",
    "wof:placetype":"venue"
},
  "geometry": {"coordinates":[-84.754306,33.397655],"type":"Point"}
}