{
  "type": "Feature",
  "properties": {
    "addr:full":"3059 Lawrenceville Hwy Lawrenceville GA 30044",
    "addr:housenumber":"3059",
    "addr:postcode":"30044",
    "addr:street":"Lawrenceville Hwy",
    "iso:country":"US",
    "sg:address":"3059 Lawrenceville Hwy",
    "sg:city":"Lawrenceville",
    "sg:classifiers":[
        {
            "category":"Personal",
            "subcategory":"Beauty Salon",
            "type":"Services"
        }
    ],
    "sg:phone":"+1 770 381 0999",
    "sg:postcode":"30044",
    "sg:province":"GA",
    "sg:tags":[
        "hair"
    ],
    "wof:name":"Elegant Styles",
    "wof:placetype":"venue"
},
  "geometry": {"coordinates":[-84.08504000000001,33.921273],"type":"Point"}
}