{
  "type": "Feature",
  "properties": {
    "iso:country":"US",
    "sg:address":"4070 Amanda Ln",
    "sg:city":"Cumming",
    "sg:classifiers":[
        {
            "category":"Shopping",
            "type":"Retail Goods"
        }
    ],
    "sg:phone":"+1 678 513 5497",
    "sg:postcode":"30040",
    "sg:province":"GA",
    "sg:tags":[
        "equipment",
        "telephone",
        "supply"
    ],
    "sg:website":"www.bmhcomm.com",
    "wof:name":"BMH Communications Inc",
    "wof:placetype":"venue"
},
  "geometry": {"coordinates":[-84.225455,34.229968],"type":"Point"}
}