{
  "type": "Feature",
  "properties": {
    "iso:country":"US",
    "sg:address":"720 Veterans Memorial Pkwy SW",
    "sg:city":"Mableton",
    "sg:classifiers":[
        {
            "category":"Freight",
            "type":"Transportation"
        }
    ],
    "sg:phone":"+1 770 941 3004",
    "sg:postcode":"30126",
    "sg:province":"GA",
    "sg:tags":[
        "commercial",
        "storage"
    ],
    "wof:name":"Uncle Bob's Self-Storage",
    "wof:placetype":"venue"
},
  "geometry": {"coordinates":[-84.575541,33.818535],"type":"Point"}
}