{
  "type": "Feature",
  "properties": {
    "addr:full":"100 N Peachtree City Pkwy Atlanta GA 30303",
    "addr:housenumber":"100",
    "addr:postcode":"30303",
    "addr:street":"N Peachtree City Pkwy",
    "iso:country":"US",
    "sg:address":"100 N Peachtree City Pkwy",
    "sg:city":"Atlanta",
    "sg:classifiers":[
        {
            "category":"Health Services",
            "subcategory":"Optometrist",
            "type":"Services"
        }
    ],
    "sg:phone":"+1 770 487 1195",
    "sg:postcode":"30303",
    "sg:province":"GA",
    "wof:name":"Peachtree City Eye Center",
    "wof:placetype":"venue"
},
  "geometry": {"coordinates":[-84.557849,33.744132],"type":"Point"}
}