{
  "type": "Feature",
  "properties": {
    "iso:country":"US",
    "sg:address":"160 N Alexander St",
    "sg:city":"Toccoa",
    "sg:classifiers":[
        {
            "category":"Landmark",
            "subcategory":"Historic",
            "type":"Public Place"
        }
    ],
    "sg:phone":"+1 706 886 1582",
    "sg:postcode":"30577",
    "sg:province":"GA",
    "sg:tags":[
        "historical"
    ],
    "wof:name":"Stephens County Historical Society, Inc.",
    "wof:placetype":"venue"
},
  "geometry": {"coordinates":[-83.33152800000001,34.578559],"type":"Point"}
}