{
  "type": "Feature",
  "properties": {
    "addr:full":"4850 Sugarloaf Pkwy Lawrenceville GA 30044",
    "addr:housenumber":"4850",
    "addr:postcode":"30044",
    "addr:street":"Sugarloaf Pkwy",
    "iso:country":"US",
    "sg:address":"4850 Sugarloaf Pkwy",
    "sg:city":"Lawrenceville",
    "sg:classifiers":[
        {
            "category":"Personal",
            "subcategory":"Tanning Parlor",
            "type":"Services"
        }
    ],
    "sg:phone":"+1 770 963 1003",
    "sg:postcode":"30044",
    "sg:province":"GA",
    "wof:name":"Outback Tanning Salons",
    "wof:placetype":"venue"
},
  "geometry": {"coordinates":[-84.05349699999999,33.9548],"type":"Point"}
}