{
  "type": "Feature",
  "properties": {
    "iso:country":"US",
    "sg:address":"216 Wynn Pl",
    "sg:city":"Warner Robins",
    "sg:classifiers":[
        {
            "category":"Organizations",
            "subcategory":"Professional Association",
            "type":"Services"
        }
    ],
    "sg:phone":"+1 478 447 3222",
    "sg:postcode":"31088",
    "sg:province":"GA",
    "sg:tags":[
        "general",
        "contractor"
    ],
    "wof:name":"ROC Construction Co",
    "wof:placetype":"venue"
},
  "geometry": {"coordinates":[-83.599812,32.59603],"type":"Point"}
}