{
  "type": "Feature",
  "properties": {
    "addr:full":"1266 Lake Colony Dr Marietta GA 30068",
    "addr:housenumber":"1266",
    "addr:postcode":"30068",
    "addr:street":"Lake Colony Dr",
    "iso:country":"US",
    "sg:address":"1266 Lake Colony Dr",
    "sg:city":"Marietta",
    "sg:classifiers":[
        {
            "category":"Education",
            "subcategory":"Dance Studio",
            "type":"Public Place"
        }
    ],
    "sg:phone":"+1 770 998 1508",
    "sg:postcode":"30068",
    "sg:province":"GA",
    "sg:tags":[
        "instruction",
        "dancing"
    ],
    "wof:name":"Georgia Cotillion",
    "wof:placetype":"venue"
},
  "geometry": {"coordinates":[-84.40611800000001,33.978548],"type":"Point"}
}