{
  "type": "Feature",
  "properties": {
    "iso:country":"US",
    "sg:address":"124 Edgewood Ave NE",
    "sg:city":"Atlanta",
    "sg:classifiers":[
        {
            "category":"Shopping",
            "subcategory":"Books",
            "type":"Retail Goods"
        }
    ],
    "sg:phone":"+1 404 659 0959",
    "sg:postcode":"30303",
    "sg:province":"GA",
    "sg:tags":[
        "dealers-used",
        "rare",
        "store"
    ],
    "sg:website":"http://www.thecampushub.com",
    "wof:name":"Georgia Book Store Inc",
    "wof:placetype":"venue"
},
  "geometry": {"coordinates":[-84.38427,33.754471],"type":"Point"}
}