{
  "type": "Feature",
  "properties": {
    "iso:country":"US",
    "sg:address":"3671 Cobb Pkwy NW",
    "sg:city":"Acworth",
    "sg:classifiers":[
        {
            "category":"Retail",
            "subcategory":"Pet Boarding",
            "type":"Services"
        },
        {
            "category":"Animal Shelter",
            "type":"Public Place"
        },
        {
            "category":"Retail",
            "subcategory":"Veterinary Services",
            "type":"Services"
        },
        {
            "category":"Retail",
            "subcategory":"Animal Services",
            "type":"Services"
        }
    ],
    "sg:phone":"+1 770 974 3536",
    "sg:postcode":"30101",
    "sg:province":"GA",
    "sg:tags":[
        "sitting",
        "hospital",
        "specialty",
        "clinic",
        "veterinarian",
        "boarding/pet",
        "grooming",
        "kennel"
    ],
    "sg:website":"www.lakecityanimal.com",
    "wof:name":"Lake City Animal Hospital",
    "wof:placetype":"venue"
},
  "geometry": {"coordinates":[-84.695127,34.041169],"type":"Point"}
}