{
  "type": "Feature",
  "properties": {
    "addr:full":"100 Queens Way Woodstock GA 30189",
    "addr:housenumber":"100",
    "addr:postcode":"30189",
    "addr:street":"Queens Way",
    "iso:country":"US",
    "sg:address":"100 Queens Way",
    "sg:city":"Woodstock",
    "sg:classifiers":[
        {
            "category":"Autos & Motor Vehicles",
            "subcategory":"Motorcycle Sales",
            "type":"Retail Goods"
        }
    ],
    "sg:phone":"+1 678 445 3272",
    "sg:postcode":"30189",
    "sg:province":"GA",
    "sg:tags":[
        "scooter"
    ],
    "wof:name":"Cherokee Choppers",
    "wof:placetype":"venue"
},
  "geometry": {"coordinates":[-84.5612,34.085001],"type":"Point"}
}