{
  "type": "Feature",
  "properties": {
    "iso:country":"US",
    "sg:address":"5701 Roswell Rd",
    "sg:city":"Atlanta",
    "sg:classifiers":[
        {
            "category":"Retail",
            "subcategory":"Auto Repair",
            "type":"Services"
        }
    ],
    "sg:phone":"+1 404 252 1667",
    "sg:postcode":"30342",
    "sg:province":"GA",
    "sg:tags":[
        "automotive",
        "wrecker"
    ],
    "wof:name":"Palm Top Properties",
    "wof:placetype":"venue"
},
  "geometry": {"coordinates":[-84.378818,33.910669],"type":"Point"}
}