{
  "type": "Feature",
  "properties": {
    "iso:country":"US",
    "sg:address":"119 N Lee St",
    "sg:city":"Americus",
    "sg:classifiers":[
        {
            "category":"Banks & Credit Unions",
            "subcategory":"Bank",
            "type":"Services"
        }
    ],
    "sg:phone":"+1 229 924 4011",
    "sg:postcode":"31709",
    "sg:province":"GA",
    "sg:tags":[
        "saving",
        "commercial"
    ],
    "sg:website":"http://www.cbkamericus.com",
    "wof:name":"Citizens Bank Of Americus",
    "wof:placetype":"venue"
},
  "geometry": {"coordinates":[-84.232564,32.072844],"type":"Point"}
}