{
  "type": "Feature",
  "properties": {
    "iso:country":"US",
    "sg:address":"2611 Shorter Ave",
    "sg:city":"Rome",
    "sg:classifiers":[
        {
            "category":"Recreation",
            "type":"Entertainment"
        }
    ],
    "sg:phone":"+1 706 235 0996",
    "sg:postcode":"30165",
    "sg:province":"GA",
    "sg:tags":[
        "psychic",
        "medium"
    ],
    "wof:name":"Enlightenment",
    "wof:placetype":"venue"
},
  "geometry": {"coordinates":[-85.250534,34.271139],"type":"Point"}
}