{
  "type": "Feature",
  "properties": {
    "iso:country":"US",
    "sg:address":"1620 Power Ln",
    "sg:city":"Albany",
    "sg:classifiers":[
        {
            "category":"Wholesale",
            "subcategory":"Machinery & Supplies",
            "type":"Manufacturing & Wholesale Goods"
        }
    ],
    "sg:phone":"+1 229 420 4331",
    "sg:postcode":"31705",
    "sg:province":"GA",
    "sg:tags":[
        "equipment",
        "industrial"
    ],
    "wof:name":"Capital Nissan Forklift Co",
    "wof:placetype":"venue"
},
  "geometry": {"coordinates":[-84.101761,31.540678],"type":"Point"}
}