{
  "type": "Feature",
  "properties": {
    "addr:full":"4375 River Green Pkwy NW Duluth GA 30096",
    "addr:housenumber":"4375",
    "addr:postcode":"30096",
    "addr:street":"River Green Pkwy Nw",
    "iso:country":"US",
    "sg:address":"4375 River Green Pkwy NW",
    "sg:city":"Duluth",
    "sg:classifiers":[
        {
            "category":"Professional",
            "subcategory":"Management & Consulting",
            "type":"Services"
        }
    ],
    "sg:phone":"+1 770 622 1193",
    "sg:postcode":"30096",
    "sg:province":"GA",
    "sg:tags":[
        "marketing",
        "program"
    ],
    "wof:name":"POSSIBLENOW.COM/Dnc Solution",
    "wof:placetype":"venue"
},
  "geometry": {"coordinates":[-84.168224,34.014105],"type":"Point"}
}