{
  "type": "Feature",
  "properties": {
    "iso:country":"US",
    "sg:address":"1610 Old Camilla Hwy",
    "sg:city":"Moultrie",
    "sg:classifiers":[
        {
            "category":"Professional",
            "type":"Services"
        }
    ],
    "sg:phone":"+1 229 985 4505",
    "sg:postcode":"31768",
    "sg:province":"GA",
    "sg:tags":[
        "establishment"
    ],
    "wof:name":"Bishop Well & Pump Svc",
    "wof:placetype":"venue"
},
  "geometry": {"coordinates":[-83.813422,31.187151],"type":"Point"}
}