{
  "type": "Feature",
  "properties": {
    "iso:country":"US",
    "sg:address":"5 Cleveland Ave SW",
    "sg:city":"Atlanta",
    "sg:classifiers":[
        {
            "category":"Retail",
            "subcategory":"Laundry & Dry Cleaning",
            "type":"Services"
        }
    ],
    "sg:phone":"+1 678 999 9824",
    "sg:postcode":"30315",
    "sg:province":"GA",
    "wof:name":"Cleveland Avenue Cleaners",
    "wof:placetype":"venue"
},
  "geometry": {"coordinates":[-84.388992,33.681222],"type":"Point"}
}