{
  "type": "Feature",
  "properties": {
    "iso:country":"US",
    "sg:address":"5535 Joe Frank Harris Pkwy NW",
    "sg:city":"Adairsville",
    "sg:classifiers":[
        {
            "category":"Real Estate",
            "subcategory":"Real Estate Operator",
            "type":"Services"
        }
    ],
    "sg:phone":"+1 770 773 3959",
    "sg:postcode":"30103",
    "sg:province":"GA",
    "sg:tags":[
        "apartment"
    ],
    "wof:name":"Adairsville Arms Apartments",
    "wof:placetype":"venue"
},
  "geometry": {"coordinates":[-84.926124,34.365121],"type":"Point"}
}