{
  "type": "Feature",
  "properties": {
    "iso:country":"US",
    "sg:address":"1070 Apt To Miss Rd",
    "sg:city":"Monticello",
    "sg:classifiers":[
        {
            "category":"Manufacturing",
            "subcategory":"Lumber",
            "type":"Manufacturing & Wholesale Goods"
        }
    ],
    "sg:phone":"+1 706 468 1059",
    "sg:postcode":"31064",
    "sg:province":"GA",
    "sg:tags":[
        "logger"
    ],
    "wof:name":"Wood Logging",
    "wof:placetype":"venue"
},
  "geometry": {"coordinates":[-83.558892,33.298718],"type":"Point"}
}