{
  "type": "Feature",
  "properties": {
    "addr:full":"6317 Old Hwy 5 Woodstock GA 30188",
    "addr:housenumber":"6317",
    "addr:postcode":"30188",
    "addr:street":"Old Hwy 5",
    "iso:country":"US",
    "sg:address":"6317 Old Hwy 5",
    "sg:city":"Woodstock",
    "sg:classifiers":[
        {
            "category":"Food & Beverages",
            "subcategory":"Groceries & Convenience Stores",
            "type":"Retail Goods"
        }
    ],
    "sg:phone":"+1 770 928 9920",
    "sg:postcode":"30188",
    "sg:province":"GA",
    "sg:tags":[
        "station",
        "gasoline"
    ],
    "wof:name":"Western Way Station",
    "wof:placetype":"venue"
},
  "geometry": {"coordinates":[-84.49836000000001,34.128178],"type":"Point"}
}