{
  "type": "Feature",
  "properties": {
    "addr:full":"133 Lindsey Rd Swainsboro GA 30401",
    "addr:housenumber":"133",
    "addr:postcode":"30401",
    "addr:street":"Lindsey Rd",
    "iso:country":"US",
    "sg:address":"133 Lindsey Rd",
    "sg:city":"Swainsboro",
    "sg:classifiers":[
        {
            "category":"Building & Trades",
            "subcategory":"Construction",
            "type":"Services"
        }
    ],
    "sg:phone":"+1 478 237 7530",
    "sg:postcode":"30401",
    "sg:province":"GA",
    "sg:tags":[
        "steel",
        "fabrication",
        "welding"
    ],
    "wof:name":"Ogeechee Steel",
    "wof:placetype":"venue"
},
  "geometry": {"coordinates":[-82.315305,32.577838],"type":"Point"}
}