{
  "type": "Feature",
  "properties": {
    "iso:country":"US",
    "sg:address":"122 Old Airport Rd",
    "sg:city":"Lagrange",
    "sg:classifiers":[
        {
            "category":"Building & Trades",
            "subcategory":"Construction",
            "type":"Services"
        }
    ],
    "sg:phone":"+1 706 882 7231",
    "sg:postcode":"30240",
    "sg:province":"GA",
    "sg:tags":[
        "general",
        "contractor"
    ],
    "wof:name":"Mae Kemp Construction",
    "wof:placetype":"venue"
},
  "geometry": {"coordinates":[-85.070047,33.025132],"type":"Point"}
}