{
  "type": "Feature",
  "properties": {
    "addr:full":"5660 New Northside Dr NW Atlanta GA 30328",
    "addr:housenumber":"5660",
    "addr:postcode":"30328",
    "addr:street":"New Northside Dr Nw",
    "iso:country":"US",
    "sg:address":"5660 New Northside Dr NW",
    "sg:city":"Atlanta",
    "sg:classifiers":[
        {
            "category":"Professional",
            "subcategory":"Management & Consulting",
            "type":"Services"
        }
    ],
    "sg:phone":"+1 770 937 0520",
    "sg:postcode":"30328",
    "sg:province":"GA",
    "sg:tags":[
        "wholesale",
        "travel",
        "premium"
    ],
    "wof:name":"Southampton Group LLC",
    "wof:placetype":"venue"
},
  "geometry": {"coordinates":[-84.43079400000001,33.910765],"type":"Point"}
}