{
  "type": "Feature",
  "properties": {
    "addr:full":"1810 Wylds Rd Augusta GA 30909",
    "addr:housenumber":"1810",
    "addr:postcode":"30909",
    "addr:street":"Wylds Rd",
    "iso:country":"US",
    "sg:address":"1810 Wylds Rd",
    "sg:city":"Augusta",
    "sg:classifiers":[
        {
            "category":"Insurance",
            "subcategory":"Insurance Agent",
            "type":"Services"
        }
    ],
    "sg:phone":"+1 706 737 9003",
    "sg:postcode":"30909",
    "sg:province":"GA",
    "wof:name":"Allstate Insurance",
    "wof:placetype":"venue"
},
  "geometry": {"coordinates":[-82.071911,33.456385],"type":"Point"}
}