{
  "type": "Feature",
  "properties": {
    "addr:full":"3605 Flat Shoals Rd Atlanta GA 30349",
    "addr:housenumber":"3605",
    "addr:postcode":"30349",
    "addr:street":"Flat Shoals Rd",
    "iso:country":"US",
    "sg:address":"3605 Flat Shoals Rd",
    "sg:city":"Atlanta",
    "sg:classifiers":[
        {
            "category":"Building & Trades",
            "subcategory":"Electrical",
            "type":"Services"
        }
    ],
    "sg:phone":"+1 770 969 4347",
    "sg:postcode":"30349",
    "sg:province":"GA",
    "sg:tags":[
        "el",
        "security",
        "electrical",
        "system",
        "contractor"
    ],
    "wof:name":"Alarm Associates",
    "wof:placetype":"venue"
},
  "geometry": {"coordinates":[-84.509697,33.583835],"type":"Point"}
}