{
  "type": "Feature",
  "properties": {
    "iso:country":"US",
    "sg:address":"1003 7th St N",
    "sg:city":"Cordele",
    "sg:classifiers":[
        {
            "category":"Retail",
            "subcategory":"Auto Repair",
            "type":"Services"
        }
    ],
    "sg:phone":"+1 229 273 1334",
    "sg:postcode":"31015",
    "sg:province":"GA",
    "sg:tags":[
        "automobile",
        "top",
        "upholstery"
    ],
    "wof:name":"Whittle's Auto Glass",
    "wof:placetype":"venue"
},
  "geometry": {"coordinates":[-83.782934,31.979269],"type":"Point"}
}