{
  "type": "Feature",
  "properties": {
    "addr:full":"350 Peters St SW Atlanta GA 30313",
    "addr:housenumber":"350",
    "addr:postcode":"30313",
    "addr:street":"Peters St Sw",
    "iso:country":"US",
    "sg:address":"350 Peters St SW",
    "sg:city":"Atlanta",
    "sg:classifiers":[
        {
            "category":"Professional",
            "subcategory":"Computer Services",
            "type":"Services"
        }
    ],
    "sg:phone":"+1 404 522 5352",
    "sg:postcode":"30313",
    "sg:province":"GA",
    "sg:tags":[
        "consultant",
        "designer"
    ],
    "wof:name":"Byrgius",
    "wof:placetype":"venue"
},
  "geometry": {"coordinates":[-84.40473299999999,33.744729],"type":"Point"}
}