{
  "type": "Feature",
  "properties": {
    "addr:full":"910 N Jefferson St Dublin GA 31021",
    "addr:housenumber":"910",
    "addr:postcode":"31021",
    "addr:street":"N Jefferson St",
    "iso:country":"US",
    "sg:address":"910 N Jefferson St",
    "sg:city":"Dublin",
    "sg:classifiers":[
        {
            "category":"Government",
            "subcategory":"Office",
            "type":"Public Place"
        }
    ],
    "sg:phone":"+1 478 275 6890",
    "sg:postcode":"31021",
    "sg:province":"GA",
    "sg:tags":[
        "state",
        "inspection"
    ],
    "wof:name":"Georgia Labor DEPT-Olivor",
    "wof:placetype":"venue"
},
  "geometry": {"coordinates":[-82.9113,32.549147],"type":"Point"}
}