{
  "type": "Feature",
  "properties": {
    "iso:country":"US",
    "sg:address":"2792 Peeler Rd",
    "sg:city":"Atlanta",
    "sg:classifiers":[
        {
            "category":"Building & Trades",
            "subcategory":"Cleaning & Sanitation",
            "type":"Services"
        }
    ],
    "sg:phone":"+1 770 455 6406",
    "sg:postcode":"30360",
    "sg:province":"GA",
    "sg:tags":[
        "repair",
        "computer",
        "janitor",
        "maintenance"
    ],
    "sg:website":"www.psgga.com/",
    "wof:name":"Premier Services Group",
    "wof:placetype":"venue"
},
  "geometry": {"coordinates":[-84.281555,33.939555],"type":"Point"}
}