{
  "type": "Feature",
  "properties": {
    "addr:full":"1150 Lakes Blvd Lake Park GA 31636",
    "addr:housenumber":"1150",
    "addr:postcode":"31636",
    "addr:street":"Lakes Blvd",
    "iso:country":"US",
    "sg:address":"1150 Lakes Blvd",
    "sg:city":"Lake Park",
    "sg:classifiers":[
        {
            "category":"Shopping",
            "subcategory":"Books",
            "type":"Retail Goods"
        }
    ],
    "sg:phone":"+1 229 559 0657",
    "sg:postcode":"31636",
    "sg:province":"GA",
    "sg:tags":[
        "dealer"
    ],
    "wof:name":"Three Dollar Book Sale",
    "wof:placetype":"venue"
},
  "geometry": {"coordinates":[-83.21879300000001,30.681785],"type":"Point"}
}