{
  "type": "Feature",
  "properties": {
    "addr:full":"2500 E President St Savannah GA 31401",
    "addr:housenumber":"2500",
    "addr:postcode":"31401",
    "addr:street":"E President St",
    "iso:country":"US",
    "sg:address":"2500 E President St",
    "sg:city":"Savannah",
    "sg:classifiers":[
        {
            "category":"Social Services",
            "type":"Services"
        }
    ],
    "sg:phone":"+1 912 232 9706",
    "sg:postcode":"31401",
    "sg:province":"GA",
    "sg:tags":[
        "organization"
    ],
    "wof:name":"Red Cross",
    "wof:placetype":"venue"
},
  "geometry": {"coordinates":[-81.042993,32.066207],"type":"Point"}
}