{
  "type": "Feature",
  "properties": {
    "addr:full":"801 Gaskin Ave S Douglas GA 31533",
    "addr:housenumber":"801",
    "addr:postcode":"31533",
    "addr:street":"Gaskin Ave S",
    "iso:country":"US",
    "sg:address":"801 Gaskin Ave S",
    "sg:city":"Douglas",
    "sg:classifiers":[
        {
            "category":"Recreation",
            "type":"Entertainment"
        }
    ],
    "sg:phone":"+1 912 384 4467",
    "sg:postcode":"31533",
    "sg:province":"GA",
    "sg:tags":[
        "parks"
    ],
    "wof:name":"Willie Mae Rountree Recreation",
    "wof:placetype":"venue"
},
  "geometry": {"coordinates":[-82.845479,31.499889],"type":"Point"}
}