{
  "type": "Feature",
  "properties": {
    "addr:full":"9950 Farmbrook Ln Alpharetta GA 30022",
    "addr:housenumber":"9950",
    "addr:postcode":"30022",
    "addr:street":"Farmbrook Ln",
    "iso:country":"US",
    "sg:address":"9950 Farmbrook Ln",
    "sg:city":"Alpharetta",
    "sg:classifiers":[
        {
            "category":"Professional",
            "subcategory":"Management & Consulting",
            "type":"Services"
        }
    ],
    "sg:phone":"+1 770 368 9764",
    "sg:postcode":"30022",
    "sg:province":"GA",
    "wof:name":"Furmanco Inc",
    "wof:placetype":"venue"
},
  "geometry": {"coordinates":[-84.21284,34.024007],"type":"Point"}
}