{
  "type": "Feature",
  "properties": {
    "addr:full":"1275 Shiloh Rd NW Ste 2940 Kennesaw GA 30144",
    "addr:housenumber":"1275",
    "addr:postcode":"30144",
    "addr:street":"Shiloh Rd Nw Ste 2940",
    "iso:country":"US",
    "sg:address":"1275 Shiloh Rd NW Ste 2940",
    "sg:city":"Kennesaw",
    "sg:classifiers":[
        {
            "category":"Real Estate",
            "subcategory":"Real Estate Services",
            "type":"Services"
        }
    ],
    "sg:phone":"+1 770 499 8193",
    "sg:postcode":"30144",
    "sg:province":"GA",
    "sg:tags":[
        "management",
        "property"
    ],
    "sg:website":"www.rentlist.net/Greathomes",
    "wof:name":"Great Homes Realty & Property Management Llc",
    "wof:placetype":"venue"
},
  "geometry": {"coordinates":[-84.58929000000001,34.048901],"type":"Point"}
}