{
  "type": "Feature",
  "properties": {
    "iso:country":"US",
    "sg:address":"315 Creekside Ct",
    "sg:city":"Alpharetta",
    "sg:classifiers":[
        {
            "category":"Professional",
            "subcategory":"Business Services",
            "type":"Services"
        }
    ],
    "sg:phone":"+1 678 319 0524",
    "sg:postcode":"30022",
    "sg:province":"GA",
    "wof:name":"Travel Technology Partners",
    "wof:placetype":"venue"
},
  "geometry": {"coordinates":[-84.22590700000001,34.057534],"type":"Point"}
}