{
  "type": "Feature",
  "properties": {
    "iso:country":"US",
    "sg:address":"2705 Cobb Pkwy NW",
    "sg:city":"Kennesaw",
    "sg:classifiers":[
        {
            "category":"Building & Trades",
            "subcategory":"Locksmith",
            "type":"Services"
        }
    ],
    "sg:phone":"+1 770 250 0826",
    "sg:postcode":"30152",
    "sg:province":"GA",
    "sg:tags":[
        "key"
    ],
    "wof:name":"1 Day Two Fix It Kennesaw Locksmith",
    "wof:placetype":"venue"
},
  "geometry": {"coordinates":[-84.620999,34.019719],"type":"Point"}
}