{
  "type": "Feature",
  "properties": {
    "addr:full":"7755 US Hwy 80 Savannah GA 31410",
    "addr:housenumber":"7755",
    "addr:postcode":"31410",
    "addr:street":"Us Hwy 80",
    "iso:country":"US",
    "sg:address":"7755 US Hwy 80",
    "sg:city":"Savannah",
    "sg:classifiers":[
        {
            "category":"Food & Beverages",
            "subcategory":"Fruits & Vegetables",
            "type":"Retail Goods"
        }
    ],
    "sg:phone":"+1 912 897 0802",
    "sg:postcode":"31410",
    "sg:province":"GA",
    "sg:tags":[
        "produce"
    ],
    "wof:name":"Davis Produce",
    "wof:placetype":"venue"
},
  "geometry": {"coordinates":[-80.963319,32.032191],"type":"Point"}
}