{
  "type": "Feature",
  "properties": {
    "addr:full":"1680 Lower Roswell Rd Marietta GA 30068",
    "addr:housenumber":"1680",
    "addr:postcode":"30068",
    "addr:street":"Lower Roswell Rd",
    "iso:country":"US",
    "sg:address":"1680 Lower Roswell Rd",
    "sg:city":"Marietta",
    "sg:classifiers":[
        {
            "category":"Shopping",
            "subcategory":"Bicycles & Sporting Goods",
            "type":"Retail Goods"
        },
        {
            "category":"Autos & Motor Vehicles",
            "subcategory":"Motorcycle Sales",
            "type":"Retail Goods"
        }
    ],
    "sg:phone":"+1 770 321 9300",
    "sg:postcode":"30068",
    "sg:province":"GA",
    "sg:tags":[
        "car",
        "golf",
        "cart"
    ],
    "sg:website":"http://www.golfcartsatlanta.com",
    "wof:name":"Golf Carts Atlanta",
    "wof:placetype":"venue"
},
  "geometry": {"coordinates":[-84.503332,33.952059],"type":"Point"}
}