{
  "type": "Feature",
  "properties": {
    "iso:country":"US",
    "sg:address":"5660 New Northside Dr NW D",
    "sg:city":"Atlanta",
    "sg:classifiers":[
        {
            "category":"Manufacturing",
            "subcategory":"Tools & Machinery",
            "type":"Manufacturing & Wholesale Goods"
        }
    ],
    "sg:phone":"+1 770 933 1400",
    "sg:postcode":"30328",
    "sg:province":"GA",
    "sg:tags":[
        "springs-wholesale",
        "manufacturer"
    ],
    "sg:website":"http://www.suntorywatergroup.com",
    "wof:name":"Crystal Springs",
    "wof:placetype":"venue"
},
  "geometry": {"coordinates":[-84.430556,33.91014],"type":"Point"}
}