{
  "type": "Feature",
  "properties": {
    "addr:full":"1020 S Hamilton St Dalton GA 30720",
    "addr:housenumber":"1020",
    "addr:postcode":"30720",
    "addr:street":"S Hamilton St",
    "iso:country":"US",
    "sg:address":"1020 S Hamilton St",
    "sg:city":"Dalton",
    "sg:classifiers":[
        {
            "category":"Wholesale",
            "subcategory":"Electrical",
            "type":"Manufacturing & Wholesale Goods"
        }
    ],
    "sg:phone":"+1 706 275 4400",
    "sg:postcode":"30720",
    "sg:province":"GA",
    "sg:website":"www.rodenelectric.com",
    "wof:name":"Roden Electrical Supply Co",
    "wof:placetype":"venue"
},
  "geometry": {"coordinates":[-84.966742,34.757404],"type":"Point"}
}