{
  "type": "Feature",
  "properties": {
    "addr:full":"5455 Glenridge Dr NE Atlanta GA 30342",
    "addr:housenumber":"5455",
    "addr:postcode":"30342",
    "addr:street":"Glenridge Dr Ne",
    "iso:country":"US",
    "sg:address":"5455 Glenridge Dr NE",
    "sg:city":"Atlanta",
    "sg:classifiers":[
        {
            "category":"Community Center",
            "subcategory":"Senior",
            "type":"Public Place"
        },
        {
            "category":"Health Services",
            "subcategory":"Clinic",
            "type":"Services"
        },
        {
            "category":"Building & Trades",
            "subcategory":"Landscaping Services",
            "type":"Services"
        },
        {
            "category":"Social Services",
            "subcategory":"Retirement Home",
            "type":"Services"
        },
        {
            "category":"Health Services",
            "subcategory":"Nursing And Care Facility",
            "type":"Services"
        },
        {
            "category":"Social Services",
            "subcategory":"Adult Care",
            "type":"Services"
        }
    ],
    "sg:phone":"+1 404 381 1769",
    "sg:postcode":"30342",
    "sg:province":"GA",
    "sg:tags":[
        "living",
        "nurses-home",
        "apartment",
        "people",
        "alzheimer's",
        "residential",
        "assisted",
        "hotel",
        "life",
        "outpatient",
        "disabled",
        "elder",
        "independent",
        "convalescent",
        "bureau",
        "homes-institutional",
        "citizen",
        "homes-elderly",
        "aged",
        "homes-information"
    ],
    "sg:website":"http://altfarm.mediaplex.com/ad/ck/11624-100013-2738-28",
    "wof:name":"Belmont Village Senior Living",
    "wof:placetype":"venue"
},
  "geometry": {"coordinates":[-84.374477,33.902731],"type":"Point"}
}