{
  "type": "Feature",
  "properties": {
    "addr:full":"188 Upper Riverdale Rd Jonesboro GA 30236",
    "addr:housenumber":"188",
    "addr:postcode":"30236",
    "addr:street":"Upper Riverdale Rd",
    "iso:country":"US",
    "sg:address":"188 Upper Riverdale Rd",
    "sg:city":"Jonesboro",
    "sg:classifiers":[
        {
            "category":"Fast Food",
            "type":"Food & Drink"
        }
    ],
    "sg:phone":"+1 770 603 2290",
    "sg:postcode":"30236",
    "sg:province":"GA",
    "sg:tags":[
        "chicken",
        "wing"
    ],
    "wof:name":"Wings & Seafood",
    "wof:placetype":"venue"
},
  "geometry": {"coordinates":[-84.386957,33.578358],"type":"Point"}
}