{
  "type": "Feature",
  "properties": {
    "iso:country":"US",
    "sg:address":"3465 Joycliff Rd",
    "sg:city":"Macon",
    "sg:classifiers":[
        {
            "category":"Real Estate",
            "subcategory":"Real Estate Operator",
            "type":"Services"
        }
    ],
    "sg:phone":"+1 478 745 8053",
    "sg:postcode":"31211",
    "sg:province":"GA",
    "sg:tags":[
        "mobile",
        "home",
        "site"
    ],
    "wof:name":"Emerald Mobile Home Park",
    "wof:placetype":"venue"
},
  "geometry": {"coordinates":[-83.575278,32.88654],"type":"Point"}
}