{
  "type": "Feature",
  "properties": {
    "iso:country":"US",
    "sg:address":"1060 Culpepper Dr SW",
    "sg:city":"Conyers",
    "sg:classifiers":[
        {
            "category":"Health Services",
            "subcategory":"Hospital",
            "type":"Services"
        }
    ],
    "sg:phone":"+1 770 922 9578",
    "sg:postcode":"30094",
    "sg:province":"GA",
    "wof:name":"National Emergency Medical Services",
    "wof:placetype":"venue"
},
  "geometry": {"coordinates":[-84.021698,33.650902],"type":"Point"}
}