{
  "type": "Feature",
  "properties": {
    "addr:full":"412 James Brown Blvd Augusta GA 30901",
    "addr:housenumber":"412",
    "addr:postcode":"30901",
    "addr:street":"James Brown Blvd",
    "iso:country":"US",
    "sg:address":"412 James Brown Blvd",
    "sg:city":"Augusta",
    "sg:classifiers":[
        {
            "category":"Professional",
            "type":"Services"
        }
    ],
    "sg:phone":"+1 706 823 9387",
    "sg:postcode":"30901",
    "sg:province":"GA",
    "wof:name":"Feelings",
    "wof:placetype":"venue"
},
  "geometry": {"coordinates":[-81.96839199999999,33.474092],"type":"Point"}
}