{
  "type": "Feature",
  "properties": {
    "addr:full":"1265 Highway 54 W Fayetteville GA 30214",
    "addr:housenumber":"1265",
    "addr:postcode":"30214",
    "addr:street":"Highway 54 W",
    "iso:country":"US",
    "sg:address":"1265 Highway 54 W",
    "sg:city":"Fayetteville",
    "sg:classifiers":[
        {
            "category":"Health Services",
            "subcategory":"Doctor",
            "type":"Services"
        }
    ],
    "sg:phone":"+1 770 719 2797",
    "sg:postcode":"30214",
    "sg:province":"GA",
    "wof:name":"Peachtree Surgical Group PC",
    "wof:placetype":"venue"
},
  "geometry": {"coordinates":[-84.480103,33.484299],"type":"Point"}
}