{
  "type": "Feature",
  "properties": {
    "iso:country":"US",
    "sg:address":"123 Hutchinson Ferry Rd",
    "sg:city":"Bainbridge",
    "sg:classifiers":[
        {
            "category":"Professional",
            "type":"Services"
        },
        {
            "category":"Professional",
            "subcategory":"Advertising",
            "type":"Services"
        }
    ],
    "sg:phone":"+1 229 726 1414",
    "sg:postcode":"39819",
    "sg:province":"GA",
    "sg:tags":[
        "product",
        "fair",
        "trade",
        "exposition",
        "advertising-promotional",
        "shows"
    ],
    "wof:name":"Aka Drafting",
    "wof:placetype":"venue"
},
  "geometry": {"coordinates":[-84.736041,30.771754],"type":"Point"}
}