{
  "type": "Feature",
  "properties": {
    "iso:country":"US",
    "sg:address":"1887 Willow Trail Pkwy",
    "sg:city":"Norcross",
    "sg:classifiers":[
        {
            "category":"Home & Garden",
            "subcategory":"Home Furnishings",
            "type":"Retail Goods"
        },
        {
            "category":"Shopping",
            "subcategory":"Crafts & Fabrics",
            "type":"Retail Goods"
        }
    ],
    "sg:phone":"+1 770 921 1833",
    "sg:postcode":"30093",
    "sg:province":"GA",
    "sg:tags":[
        "decor",
        "art",
        "supply"
    ],
    "sg:website":"www.gardenridge.com/",
    "wof:name":"Garden Ridge",
    "wof:placetype":"venue"
},
  "geometry": {"coordinates":[-84.17440000000001,33.9259],"type":"Point"}
}