{
  "type": "Feature",
  "properties": {
    "iso:country":"US",
    "sg:address":"225 Townpark Dr",
    "sg:city":"Kennesaw",
    "sg:classifiers":[
        {
            "category":"Restaurant",
            "type":"Food & Drink"
        }
    ],
    "sg:phone":"+1 678 290 9002",
    "sg:postcode":"30144",
    "sg:province":"GA",
    "sg:tags":[
        "eating"
    ],
    "wof:name":"Town Park Cafe Inc",
    "wof:placetype":"venue"
},
  "geometry": {"coordinates":[-84.572799,34.042319],"type":"Point"}
}