{
  "type": "Feature",
  "properties": {
    "iso:country":"US",
    "sg:address":"1304 McDonald Rd",
    "sg:city":"Douglas",
    "sg:classifiers":[
        {
            "category":"Food & Beverages",
            "subcategory":"Groceries & Convenience Stores",
            "type":"Retail Goods"
        }
    ],
    "sg:phone":"+1 912 384 0989",
    "sg:postcode":"31533",
    "sg:province":"GA",
    "sg:tags":[
        "deli",
        "filling",
        "station"
    ],
    "wof:name":"Macks Minit Mart",
    "wof:placetype":"venue"
},
  "geometry": {"coordinates":[-82.839551,31.495578],"type":"Point"}
}