{
  "type": "Feature",
  "properties": {
    "addr:full":"604 Water Works Rd Crawford GA 30630",
    "addr:housenumber":"604",
    "addr:postcode":"30630",
    "addr:street":"Water Works Rd",
    "iso:country":"US",
    "sg:address":"604 Water Works Rd",
    "sg:city":"Crawford",
    "sg:classifiers":[
        {
            "category":"Farming",
            "subcategory":"Livestock Farm",
            "type":"Manufacturing & Wholesale Goods"
        }
    ],
    "sg:phone":"+1 706 743 5952",
    "sg:postcode":"30630",
    "sg:province":"GA",
    "sg:tags":[
        "animal",
        "general"
    ],
    "wof:name":"Gilbert H Underwood",
    "wof:placetype":"venue"
},
  "geometry": {"coordinates":[-83.145409,33.88306],"type":"Point"}
}