{
  "type": "Feature",
  "properties": {
    "iso:country":"US",
    "sg:address":"471 Rockbridge Trl",
    "sg:city":"Stone Mountain",
    "sg:classifiers":[
        {
            "category":"Professional",
            "subcategory":"Business Services",
            "type":"Services"
        }
    ],
    "sg:phone":"+1 404 499 2264",
    "sg:postcode":"30083",
    "sg:province":"GA",
    "wof:name":"Angelette & Assoc",
    "wof:placetype":"venue"
},
  "geometry": {"coordinates":[-84.22982,33.787379],"type":"Point"}
}