{
  "type": "Feature",
  "properties": {
    "iso:country":"US",
    "sg:address":"15134 State Rte 193",
    "sg:city":"Chickamauga",
    "sg:classifiers":[
        {
            "category":"Building & Trades",
            "subcategory":"Construction",
            "type":"Services"
        }
    ],
    "sg:phone":"+1 706 539 2278",
    "sg:postcode":"30707",
    "sg:province":"GA",
    "sg:tags":[
        "house",
        "nonresidential"
    ],
    "wof:name":"James E Guthrie Contractor",
    "wof:placetype":"venue"
},
  "geometry": {"coordinates":[-85.399923,34.781388],"type":"Point"}
}