{
  "type": "Feature",
  "properties": {
    "addr:full":"657 Athens St Jefferson GA 30549",
    "addr:housenumber":"657",
    "addr:postcode":"30549",
    "addr:street":"Athens St",
    "iso:country":"US",
    "sg:address":"657 Athens St",
    "sg:city":"Jefferson",
    "sg:classifiers":[
        {
            "category":"Health Services",
            "subcategory":"Doctor",
            "type":"Services"
        }
    ],
    "sg:phone":"+1 706 367 7302",
    "sg:postcode":"30549",
    "sg:province":"GA",
    "sg:tags":[
        "medical"
    ],
    "wof:name":"Health Connection Inc",
    "wof:placetype":"venue"
},
  "geometry": {"coordinates":[-83.573227,34.107757],"type":"Point"}
}