{
  "type": "Feature",
  "properties": {
    "addr:full":"1702 Peachtree St NW Atlanta GA 30309",
    "addr:housenumber":"1702",
    "addr:postcode":"30309",
    "addr:street":"Peachtree St Nw",
    "iso:country":"US",
    "sg:address":"1702 Peachtree St NW",
    "sg:city":"Atlanta",
    "sg:phone":"+1 404 671 8415",
    "sg:postcode":"30309",
    "sg:province":"GA",
    "wof:name":"Paul & Son's Locksmiths",
    "wof:placetype":"venue"
},
  "geometry": {"coordinates":[-84.392635,33.800608],"type":"Point"}
}