{
  "type": "Feature",
  "properties": {
    "addr:full":"11801 Hwy 197 N Clarkesville GA 30523",
    "addr:housenumber":"11801",
    "addr:postcode":"30523",
    "addr:street":"Hwy 197 N",
    "iso:country":"US",
    "sg:address":"11801 Hwy 197 N",
    "sg:city":"Clarkesville",
    "sg:classifiers":[
        {
            "category":"Restaurant",
            "type":"Food & Drink"
        }
    ],
    "sg:menulink":"http://www.allmenus.com/ga/clarkesville/243939-old-batesville-general-store--restaurant/menu/",
    "sg:phone":"+1 706 947 3434",
    "sg:postcode":"30523",
    "sg:province":"GA",
    "sg:tags":[
        "american"
    ],
    "wof:name":"Old Batesville General Store & Restaurant",
    "wof:placetype":"venue"
},
  "geometry": {"coordinates":[-83.611626,34.748168],"type":"Point"}
}