{
  "type": "Feature",
  "properties": {
    "iso:country":"US",
    "sg:address":"125 Airport Rd",
    "sg:city":"St Simons Island",
    "sg:classifiers":[
        {
            "category":"Autos & Motor Vehicles",
            "subcategory":"Automobile Sales",
            "type":"Retail Goods"
        }
    ],
    "sg:phone":"+1 912 638 5510",
    "sg:postcode":"31522",
    "sg:province":"GA",
    "sg:tags":[
        "aircraft"
    ],
    "wof:name":"Bill Walker & Assoc LTD",
    "wof:placetype":"venue"
},
  "geometry": {"coordinates":[-81.38579799999999,31.157603],"type":"Point"}
}