{
  "type": "Feature",
  "properties": {
    "iso:country":"US",
    "sg:address":"5549 Old National Hwy",
    "sg:city":"Atlanta",
    "sg:classifiers":[
        {
            "category":"Government",
            "subcategory":"Police Station",
            "type":"Public Place"
        }
    ],
    "sg:phone":"+1 404 763 4780",
    "sg:postcode":"30349",
    "sg:province":"GA",
    "sg:tags":[
        "department"
    ],
    "wof:name":"Old National Police Precinct",
    "wof:placetype":"venue"
},
  "geometry": {"coordinates":[-84.471962,33.60421],"type":"Point"}
}