{
  "type": "Feature",
  "properties": {
    "iso:country":"US",
    "sg:address":"2825 Hartwell Hwy",
    "sg:city":"Elberton",
    "sg:classifiers":[
        {
            "category":"Utilities",
            "subcategory":"Refuse",
            "type":"Services"
        },
        {
            "category":"Building & Trades",
            "subcategory":"Plumbing",
            "type":"Services"
        },
        {
            "category":"Utilities",
            "subcategory":"Recycling",
            "type":"Services"
        }
    ],
    "sg:phone":"+1 706 283 4962",
    "sg:postcode":"30635",
    "sg:province":"GA",
    "sg:tags":[
        "tank",
        "garbage",
        "septic",
        "disposal",
        "system",
        "collection",
        "equipment",
        "waste"
    ],
    "wof:name":"Mullenix, Construction Co",
    "wof:placetype":"venue"
},
  "geometry": {"coordinates":[-82.900068,34.246877],"type":"Point"}
}