{
  "type": "Feature",
  "properties": {
    "addr:full":"202 Wedgefield Xing Savannah GA 31405",
    "addr:housenumber":"202",
    "addr:postcode":"31405",
    "addr:street":"Wedgefield Xing",
    "iso:country":"US",
    "sg:address":"202 Wedgefield Xing",
    "sg:city":"Savannah",
    "sg:classifiers":[
        {
            "category":"Professional",
            "subcategory":"Business Services",
            "type":"Services"
        }
    ],
    "sg:phone":"+1 912 232 8355",
    "sg:postcode":"31405",
    "sg:province":"GA",
    "wof:name":"J & R Computer Solutions Inc",
    "wof:placetype":"venue"
},
  "geometry": {"coordinates":[-81.214128,32.065312],"type":"Point"}
}