{
  "type": "Feature",
  "properties": {
    "addr:full":"515 Old Macon Rd Byron GA 31008",
    "addr:housenumber":"515",
    "addr:postcode":"31008",
    "addr:street":"Old Macon Rd",
    "iso:country":"US",
    "sg:address":"515 Old Macon Rd",
    "sg:city":"Byron",
    "sg:classifiers":[
        {
            "category":"Travel",
            "subcategory":"Hotels & Motels",
            "type":"Entertainment"
        }
    ],
    "sg:phone":"+1 478 956 5600",
    "sg:postcode":"31008",
    "sg:province":"GA",
    "sg:website":"www.choicehotels.com/ires/en-us/...",
    "wof:name":"Econo Lodge",
    "wof:placetype":"venue"
},
  "geometry": {"coordinates":[-83.749802,32.658401],"type":"Point"}
}