{
  "type": "Feature",
  "properties": {
    "iso:country":"US",
    "sg:address":"210 N Main St",
    "sg:city":"Hinesville",
    "sg:classifiers":[
        {
            "category":"Real Estate",
            "subcategory":"Real Estate Services",
            "type":"Services"
        },
        {
            "category":"Banks & Credit Unions",
            "subcategory":"Financial Services",
            "type":"Services"
        }
    ],
    "sg:phone":"+1 912 369 4000",
    "sg:postcode":"31313",
    "sg:province":"GA",
    "sg:tags":[
        "loan",
        "processing"
    ],
    "wof:name":"Supreme Lending",
    "wof:placetype":"venue"
},
  "geometry": {"coordinates":[-81.59604400000001,31.848461],"type":"Point"}
}