{
  "type": "Feature",
  "properties": {
    "iso:country":"US",
    "sg:address":"3256 Peachtree Rd NE",
    "sg:city":"Atlanta",
    "sg:phone":"+1 404 816 3556",
    "sg:postcode":"30305",
    "sg:province":"GA",
    "sg:website":"http://www.rooms2go.com",
    "wof:name":"Rooms To Go",
    "wof:placetype":"venue"
},
  "geometry": {"coordinates":[-84.371368,33.843719],"type":"Point"}
}