{
  "type": "Feature",
  "properties": {
    "iso:country":"US",
    "sg:address":"13 Harbor Ln",
    "sg:city":"White",
    "sg:classifiers":[
        {
            "category":"Health Services",
            "subcategory":"Optometrist",
            "type":"Services"
        }
    ],
    "sg:phone":"+1 770 382 3693",
    "sg:postcode":"30184",
    "sg:province":"GA",
    "wof:name":"Donald Eye",
    "wof:placetype":"venue"
},
  "geometry": {"coordinates":[-84.742248,34.272984],"type":"Point"}
}