{
  "type": "Feature",
  "properties": {
    "iso:country":"US",
    "sg:address":"2130 Fieldstone View Ct SE",
    "sg:city":"Conyers",
    "sg:classifiers":[
        {
            "category":"Professional",
            "subcategory":"Computer Services",
            "type":"Services"
        }
    ],
    "sg:phone":"+1 770 388 7999",
    "sg:postcode":"30013",
    "sg:province":"GA",
    "sg:tags":[
        "related"
    ],
    "wof:name":"Mullen Business Services",
    "wof:placetype":"venue"
},
  "geometry": {"coordinates":[-83.976719,33.617894],"type":"Point"}
}