{
  "type": "Feature",
  "properties": {
    "iso:country":"US",
    "sg:address":"4379 W Club Dr NE",
    "sg:city":"Atlanta",
    "sg:classifiers":[
        {
            "category":"Professional",
            "subcategory":"Management & Consulting",
            "type":"Services"
        }
    ],
    "sg:phone":"+1 404 784 0630",
    "sg:postcode":"30319",
    "sg:province":"GA",
    "wof:name":"South Acre Realty Advisors",
    "wof:placetype":"venue"
},
  "geometry": {"coordinates":[-84.35786,33.874601],"type":"Point"}
}