{
  "type": "Feature",
  "properties": {
    "iso:country":"US",
    "sg:address":"1 Spring St",
    "sg:city":"Newnan",
    "sg:classifiers":[
        {
            "category":"Insurance",
            "subcategory":"Insurance Agent",
            "type":"Services"
        }
    ],
    "sg:phone":"+1 770 253 5580",
    "sg:postcode":"30263",
    "sg:province":"GA",
    "wof:name":"Glover Premium Installment",
    "wof:placetype":"venue"
},
  "geometry": {"coordinates":[-84.79879800000001,33.37355],"type":"Point"}
}