{
  "type": "Feature",
  "properties": {
    "addr:full":"3414 Welcome All Rd SW Atlanta GA 30331",
    "addr:housenumber":"3414",
    "addr:postcode":"30331",
    "addr:street":"Welcome All Rd Sw",
    "iso:country":"US",
    "sg:address":"3414 Welcome All Rd SW",
    "sg:city":"Atlanta",
    "sg:classifiers":[
        {
            "category":"Retail",
            "subcategory":"Auto Repair",
            "type":"Services"
        }
    ],
    "sg:phone":"+1 404 349 3238",
    "sg:postcode":"30331",
    "sg:province":"GA",
    "wof:name":"Goggins Automotive",
    "wof:placetype":"venue"
},
  "geometry": {"coordinates":[-84.522154,33.660266],"type":"Point"}
}