{
  "type": "Feature",
  "properties": {
    "iso:country":"US",
    "sg:address":"2180 Buckley Trl",
    "sg:city":"Snellville",
    "sg:classifiers":[
        {
            "category":"Manufacturing",
            "subcategory":"Printing",
            "type":"Manufacturing & Wholesale Goods"
        }
    ],
    "sg:phone":"+1 770 935 0660",
    "sg:postcode":"30078",
    "sg:province":"GA",
    "sg:tags":[
        "printer"
    ],
    "wof:name":"M & M Printing Co",
    "wof:placetype":"venue"
},
  "geometry": {"coordinates":[-83.991207,33.845338],"type":"Point"}
}