{
  "type": "Feature",
  "properties": {
    "addr:full":"1175 Cordele Ave Macon GA 31217",
    "addr:housenumber":"1175",
    "addr:postcode":"31217",
    "addr:street":"Cordele Ave",
    "iso:country":"US",
    "sg:address":"1175 Cordele Ave",
    "sg:city":"Macon",
    "sg:classifiers":[
        {
            "category":"Organizations",
            "subcategory":"Religious Organization",
            "type":"Services"
        }
    ],
    "sg:phone":"+1 478 741 1397",
    "sg:postcode":"31217",
    "sg:province":"GA",
    "wof:name":"Shiloh Baptist Church",
    "wof:placetype":"venue"
},
  "geometry": {"coordinates":[-83.605401,32.856329],"type":"Point"}
}