{
  "type": "Feature",
  "properties": {
    "iso:country":"US",
    "sg:address":"602 Herndon Rd",
    "sg:city":"Waynesboro",
    "sg:phone":"+1 706 554 3232",
    "sg:postcode":"30830",
    "sg:province":"GA",
    "sg:tags":[
        "agricultural",
        "product"
    ],
    "wof:name":"Edenfield's Farms",
    "wof:placetype":"venue"
},
  "geometry": {"coordinates":[-82.02175699999999,33.066939],"type":"Point"}
}