{
  "type": "Feature",
  "properties": {
    "iso:country":"US",
    "sg:address":"5667 Peachtree Dunwoody Rd NE",
    "sg:city":"Atlanta",
    "sg:classifiers":[
        {
            "category":"Health Services",
            "subcategory":"Doctor",
            "type":"Services"
        }
    ],
    "sg:phone":"+1 404 252 5669",
    "sg:postcode":"30342",
    "sg:province":"GA",
    "sg:website":"www.atlantacolon.com",
    "wof:name":"Grablowsky Oscar M MD",
    "wof:placetype":"venue"
},
  "geometry": {"coordinates":[-84.350897,33.909499],"type":"Point"}
}