{
  "type": "Feature",
  "properties": {
    "addr:full":"660 Northside Dr NW Atlanta GA 30318",
    "addr:housenumber":"660",
    "addr:postcode":"30318",
    "addr:street":"Northside Dr Nw",
    "iso:country":"US",
    "sg:address":"660 Northside Dr NW",
    "sg:city":"Atlanta",
    "sg:classifiers":[
        {
            "category":"Manufacturing",
            "subcategory":"Wood Products",
            "type":"Manufacturing & Wholesale Goods"
        }
    ],
    "sg:phone":"+1 404 794 1667",
    "sg:postcode":"30318",
    "sg:province":"GA",
    "sg:tags":[
        "firewood"
    ],
    "wof:name":"American Firewood Company",
    "wof:placetype":"venue"
},
  "geometry": {"coordinates":[-84.408187,33.77253],"type":"Point"}
}