{
  "type": "Feature",
  "properties": {
    "iso:country":"US",
    "sg:address":"3961 Floyd Rd",
    "sg:city":"Austell",
    "sg:classifiers":[
        {
            "category":"Autos & Motor Vehicles",
            "subcategory":"Auto Supplies",
            "type":"Retail Goods"
        }
    ],
    "sg:phone":"+1 770 739 3321",
    "sg:postcode":"30106",
    "sg:province":"GA",
    "sg:tags":[
        "glass"
    ],
    "wof:name":"Austell Auto Glass",
    "wof:placetype":"venue"
},
  "geometry": {"coordinates":[-84.590943,33.857037],"type":"Point"}
}