{
  "type": "Feature",
  "properties": {
    "addr:full":"308 Belmont Dr Dublin GA 31021",
    "addr:housenumber":"308",
    "addr:postcode":"31021",
    "addr:street":"Belmont Dr",
    "iso:country":"US",
    "sg:address":"308 Belmont Dr",
    "sg:city":"Dublin",
    "sg:classifiers":[
        {
            "category":"Organizations",
            "subcategory":"Religious Organization",
            "type":"Services"
        }
    ],
    "sg:phone":"+1 478 272 5536",
    "sg:postcode":"31021",
    "sg:province":"GA",
    "wof:name":"Glorious Light Ministries",
    "wof:placetype":"venue"
},
  "geometry": {"coordinates":[-82.937693,32.530781],"type":"Point"}
}