{
  "type": "Feature",
  "properties": {
    "iso:country":"US",
    "sg:address":"400 Lucky Ct SE",
    "sg:city":"Marietta",
    "sg:classifiers":[
        {
            "category":"Arts & Performance",
            "subcategory":"Art Gallery",
            "type":"Entertainment"
        }
    ],
    "sg:phone":"+1 770 977 1853",
    "sg:postcode":"30067",
    "sg:province":"GA",
    "sg:tags":[
        "rendering"
    ],
    "wof:name":"Binary By Products Inc",
    "wof:placetype":"venue"
},
  "geometry": {"coordinates":[-84.481526,33.943449],"type":"Point"}
}