{
  "type": "Feature",
  "properties": {
    "iso:country":"US",
    "sg:address":"4945 Panola Mill Dr",
    "sg:city":"Lithonia",
    "sg:classifiers":[
        {
            "category":"Banks & Credit Unions",
            "subcategory":"Bank",
            "type":"Services"
        }
    ],
    "sg:phone":"+1 770 323 9550",
    "sg:postcode":"30038",
    "sg:province":"GA",
    "sg:tags":[
        "mortgage"
    ],
    "wof:name":"Progressive Mrtg & Fincl Group",
    "wof:placetype":"venue"
},
  "geometry": {"coordinates":[-84.178299,33.692775],"type":"Point"}
}