{
  "type": "Feature",
  "properties": {
    "iso:country":"US",
    "sg:address":"244 Carter Rd",
    "sg:city":"Dallas",
    "sg:classifiers":[
        {
            "category":"Social Services",
            "type":"Services"
        },
        {
            "category":"Health Services",
            "subcategory":"Clinic",
            "type":"Services"
        },
        {
            "category":"Organizations",
            "subcategory":"Membership Organization",
            "type":"Services"
        }
    ],
    "sg:phone":"+1 770 505 0065",
    "sg:postcode":"30157",
    "sg:province":"GA",
    "sg:tags":[
        "support",
        "group",
        "welfare"
    ],
    "wof:name":"Casa Paulding",
    "wof:placetype":"venue"
},
  "geometry": {"coordinates":[-84.85660900000001,33.914757],"type":"Point"}
}