{
  "type": "Feature",
  "properties": {
    "addr:full":"2445 Ousley Ct Decatur GA 30032",
    "addr:housenumber":"2445",
    "addr:postcode":"30032",
    "addr:street":"Ousley Ct",
    "iso:country":"US",
    "sg:address":"2445 Ousley Ct",
    "sg:city":"Decatur",
    "sg:classifiers":[
        {
            "category":"Building & Trades",
            "subcategory":"Cleaning & Sanitation",
            "type":"Services"
        }
    ],
    "sg:phone":"+1 404 241 0456",
    "sg:postcode":"30032",
    "sg:province":"GA",
    "sg:tags":[
        "maintenance"
    ],
    "wof:name":"Elis Cleaning Svc",
    "wof:placetype":"venue"
},
  "geometry": {"coordinates":[-84.27743700000001,33.72033],"type":"Point"}
}