{
  "type": "Feature",
  "properties": {
    "addr:full":"2347 Peachtree Road NE Atlanta GA 30305",
    "addr:housenumber":"2347",
    "addr:postcode":"30305",
    "addr:street":"Peachtree Road Ne",
    "iso:country":"US",
    "sg:address":"2347 Peachtree Road NE",
    "sg:city":"Atlanta",
    "sg:classifiers":[
        {
            "category":"Home & Garden",
            "subcategory":"Hardware",
            "type":"Retail Goods"
        }
    ],
    "sg:postcode":"30305",
    "sg:province":"GA",
    "sg:tags":[
        "store"
    ],
    "sg:website":"www.acehardware.com",
    "wof:name":"Ace Hardware of Peachtree Battle",
    "wof:placetype":"venue"
},
  "geometry": {"coordinates":[-84.38865,33.819063],"type":"Point"}
}