{
  "type": "Feature",
  "properties": {
    "iso:country":"US",
    "sg:address":"1402 Abbey Ct",
    "sg:city":"Alpharetta",
    "sg:classifiers":[
        {
            "category":"Banks & Credit Unions",
            "subcategory":"Investment Brokerage",
            "type":"Services"
        },
        {
            "category":"Professional",
            "subcategory":"Management & Consulting",
            "type":"Services"
        }
    ],
    "sg:phone":"+1 678 297 1217",
    "sg:postcode":"30004",
    "sg:province":"GA",
    "sg:tags":[
        "consultant",
        "planning",
        "financial"
    ],
    "wof:name":"Maton Financial Services Inc",
    "wof:placetype":"venue"
},
  "geometry": {"coordinates":[-84.356295,34.086787],"type":"Point"}
}