{
  "type": "Feature",
  "properties": {
    "iso:country":"US",
    "sg:address":"548 Cedar Creek Dr",
    "sg:city":"Athens",
    "sg:classifiers":[
        {
            "category":"Manufacturing",
            "subcategory":"Printing",
            "type":"Manufacturing & Wholesale Goods"
        }
    ],
    "sg:phone":"+1 706 546 6740",
    "sg:postcode":"30605",
    "sg:province":"GA",
    "sg:tags":[
        "publisher",
        "guide"
    ],
    "wof:name":"Iberian Publishing Co",
    "wof:placetype":"venue"
},
  "geometry": {"coordinates":[-83.322919,33.925096],"type":"Point"}
}