{
  "type": "Feature",
  "properties": {
    "addr:full":"600 Galleria Pkwy Atlanta GA 30339",
    "addr:housenumber":"600",
    "addr:postcode":"30339",
    "addr:street":"Galleria Pkwy",
    "iso:country":"US",
    "sg:address":"600 Galleria Pkwy",
    "sg:city":"Atlanta",
    "sg:classifiers":[
        {
            "category":"Shopping",
            "subcategory":"Computers & Home Electronics",
            "type":"Retail Goods"
        }
    ],
    "sg:phone":"+1 770 937 0300",
    "sg:postcode":"30339",
    "sg:province":"GA",
    "sg:tags":[
        "software"
    ],
    "wof:name":"Decisions First Tech",
    "wof:placetype":"venue"
},
  "geometry": {"coordinates":[-84.46489099999999,33.883191],"type":"Point"}
}