{
  "type": "Feature",
  "properties": {
    "iso:country":"US",
    "sg:address":"3193 US Hwy 80",
    "sg:city":"Bloomingdale",
    "sg:classifiers":[
        {
            "category":"Building & Trades",
            "subcategory":"Construction",
            "type":"Services"
        }
    ],
    "sg:phone":"+1 912 748 0068",
    "sg:postcode":"31302",
    "sg:province":"GA",
    "sg:tags":[
        "siding",
        "contractor"
    ],
    "wof:name":"C L D Enterprises Inc",
    "wof:placetype":"venue"
},
  "geometry": {"coordinates":[-81.33425699999999,32.143861],"type":"Point"}
}