{
  "type": "Feature",
  "properties": {
    "addr:full":"150 Parkview Trace Pass Lilburn GA 30047",
    "addr:housenumber":"150",
    "addr:postcode":"30047",
    "addr:street":"Parkview Trace Pass",
    "iso:country":"US",
    "sg:address":"150 Parkview Trace Pass",
    "sg:city":"Lilburn",
    "sg:classifiers":[
        {
            "category":"Professional",
            "subcategory":"Accounting & Tax Preparation",
            "type":"Services"
        }
    ],
    "sg:phone":"+1 770 925 8502",
    "sg:postcode":"30047",
    "sg:province":"GA",
    "wof:name":"Bkr Medcaff Davis",
    "wof:placetype":"venue"
},
  "geometry": {"coordinates":[-84.139714,33.874859],"type":"Point"}
}