{
  "type": "Feature",
  "properties": {
    "iso:country":"US",
    "sg:address":"5527 New Jesup Hwy",
    "sg:city":"Brunswick",
    "sg:classifiers":[
        {
            "category":"Organizations",
            "subcategory":"Religious Organization",
            "type":"Services"
        }
    ],
    "sg:phone":"+1 912 264 3412",
    "sg:postcode":"31523",
    "sg:province":"GA",
    "wof:name":"Brockington Masonry CHR",
    "wof:placetype":"venue"
},
  "geometry": {"coordinates":[-81.53008,31.228468],"type":"Point"}
}