{
  "type": "Feature",
  "properties": {
    "iso:country":"US",
    "sg:address":"413 Connell Rd",
    "sg:city":"Valdosta",
    "sg:classifiers":[
        {
            "category":"Manufacturing",
            "subcategory":"Tools & Machinery",
            "type":"Manufacturing & Wholesale Goods"
        }
    ],
    "sg:phone":"+1 229 259 0027",
    "sg:postcode":"31602",
    "sg:province":"GA",
    "sg:tags":[
        "electrical",
        "mfg"
    ],
    "wof:name":"Pittman Electric Services",
    "wof:placetype":"venue"
},
  "geometry": {"coordinates":[-83.28403299999999,30.872997],"type":"Point"}
}