{
  "type": "Feature",
  "properties": {
    "addr:full":"301 N Stone Mtn Lithonia Rd Stone Mountain GA 30088",
    "addr:housenumber":"301",
    "addr:postcode":"30088",
    "addr:street":"N Stone Mtn Lithonia Rd",
    "iso:country":"US",
    "sg:address":"301 N Stone Mtn Lithonia Rd",
    "sg:city":"Stone Mountain",
    "sg:classifiers":[
        {
            "category":"Food & Beverages",
            "subcategory":"Groceries & Convenience Stores",
            "type":"Retail Goods"
        }
    ],
    "sg:phone":"+1 770 469 0786",
    "sg:postcode":"30088",
    "sg:province":"GA",
    "sg:tags":[
        "grocer"
    ],
    "wof:name":"Stop N Go",
    "wof:placetype":"venue"
},
  "geometry": {"coordinates":[-84.164007,33.788928],"type":"Point"}
}