{
  "type": "Feature",
  "properties": {
    "iso:country":"US",
    "sg:address":"1039 Lee St SW",
    "sg:city":"Atlanta",
    "sg:classifiers":[
        {
            "category":"Retail",
            "subcategory":"Auto Repair",
            "type":"Services"
        }
    ],
    "sg:phone":"+1 404 758 7053",
    "sg:postcode":"30310",
    "sg:province":"GA",
    "sg:tags":[
        "automotive"
    ],
    "wof:name":"Ace Alignment Co",
    "wof:placetype":"venue"
},
  "geometry": {"coordinates":[-84.41860200000001,33.726101],"type":"Point"}
}