{
  "type": "Feature",
  "properties": {
    "iso:country":"US",
    "sg:address":"3390 Ridge Rd",
    "sg:city":"Douglasville",
    "sg:classifiers":[
        {
            "category":"Building & Trades",
            "subcategory":"Construction",
            "type":"Services"
        }
    ],
    "sg:phone":"+1 770 920 7688",
    "sg:postcode":"30134",
    "sg:province":"GA",
    "sg:tags":[
        "contractor"
    ],
    "wof:name":"Tom Troy",
    "wof:placetype":"venue"
},
  "geometry": {"coordinates":[-84.833348,33.806882],"type":"Point"}
}