{
  "type": "Feature",
  "properties": {
    "iso:country":"US",
    "sg:address":"135 Summerfield Dr",
    "sg:city":"Macon",
    "sg:classifiers":[
        {
            "category":"Real Estate",
            "subcategory":"Real Estate Agent",
            "type":"Services"
        }
    ],
    "sg:phone":"+1 478 471 6192",
    "sg:postcode":"31210",
    "sg:province":"GA",
    "sg:tags":[
        "investment"
    ],
    "wof:name":"Beers Investment Properties",
    "wof:placetype":"venue"
},
  "geometry": {"coordinates":[-83.725578,32.887281],"type":"Point"}
}