{
  "type": "Feature",
  "properties": {
    "addr:full":"228 W Central Ave Fitzgerald GA 31750",
    "addr:housenumber":"228",
    "addr:postcode":"31750",
    "addr:street":"W Central Ave",
    "iso:country":"US",
    "sg:address":"228 W Central Ave",
    "sg:city":"Fitzgerald",
    "sg:classifiers":[
        {
            "category":"Shopping",
            "subcategory":"Department Store",
            "type":"Retail Goods"
        }
    ],
    "sg:phone":"+1 229 426 7511",
    "sg:postcode":"31750",
    "sg:province":"GA",
    "sg:tags":[
        "shop"
    ],
    "sg:website":"www.dollargeneral.com",
    "wof:name":"Dollar General",
    "wof:placetype":"venue"
},
  "geometry": {"coordinates":[-83.25615999999999,31.714748],"type":"Point"}
}