{
  "type": "Feature",
  "properties": {
    "iso:country":"US",
    "sg:address":"2714 Lynda Ln",
    "sg:city":"Columbus",
    "sg:classifiers":[
        {
            "category":"Wholesale",
            "subcategory":"Stationery",
            "type":"Manufacturing & Wholesale Goods"
        }
    ],
    "sg:phone":"+1 706 563 2888",
    "sg:postcode":"31906",
    "sg:province":"GA",
    "sg:tags":[
        "supply"
    ],
    "wof:name":"Econo Bank Supplies",
    "wof:placetype":"venue"
},
  "geometry": {"coordinates":[-84.95043699999999,32.488975],"type":"Point"}
}