{
  "type": "Feature",
  "properties": {
    "addr:full":"2815 Browns Bridge Rd Gainesville GA 30504",
    "addr:housenumber":"2815",
    "addr:postcode":"30504",
    "addr:street":"Browns Bridge Rd",
    "iso:country":"US",
    "sg:address":"2815 Browns Bridge Rd",
    "sg:city":"Gainesville",
    "sg:classifiers":[
        {
            "category":"Autos & Motor Vehicles",
            "subcategory":"Automobile Sales",
            "type":"Retail Goods"
        },
        {
            "category":"Retail",
            "subcategory":"Auto Repair",
            "type":"Services"
        }
    ],
    "sg:phone":"+1 678 717 2150",
    "sg:postcode":"30504",
    "sg:province":"GA",
    "sg:tags":[
        "body",
        "repairing",
        "painting",
        "new",
        "car"
    ],
    "wof:name":"Carriage Kia",
    "wof:placetype":"venue"
},
  "geometry": {"coordinates":[-83.873239,34.278226],"type":"Point"}
}