{
  "type": "Feature",
  "properties": {
    "addr:full":"132 Pavilion Pkwy Fayetteville GA 30214",
    "addr:housenumber":"132",
    "addr:postcode":"30214",
    "addr:street":"Pavilion Pkwy",
    "iso:country":"US",
    "sg:address":"132 Pavilion Pkwy",
    "sg:city":"Fayetteville",
    "sg:classifiers":[
        {
            "category":"Shopping",
            "subcategory":"Hobbies, Toys, & Games",
            "type":"Retail Goods"
        }
    ],
    "sg:phone":"+1 678 817 0359",
    "sg:postcode":"30214",
    "sg:province":"GA",
    "sg:tags":[
        "toy",
        "store"
    ],
    "sg:website":"www.toysrus.com",
    "wof:name":"Toys R Us",
    "wof:placetype":"venue"
},
  "geometry": {"coordinates":[-84.445472,33.480214],"type":"Point"}
}