{
  "type": "Feature",
  "properties": {
    "iso:country":"US",
    "sg:address":"4400 Roswell Rd",
    "sg:city":"Marietta",
    "sg:classifiers":[
        {
            "category":"Professional",
            "subcategory":"Business Services",
            "type":"Services"
        }
    ],
    "sg:phone":"+1 770 509 1996",
    "sg:postcode":"30062",
    "sg:province":"GA",
    "sg:tags":[
        "sewing",
        "alteration",
        "embroidery"
    ],
    "wof:name":"Monograms Embroidery & Gifts",
    "wof:placetype":"venue"
},
  "geometry": {"coordinates":[-84.42313900000001,33.985555],"type":"Point"}
}