{
  "type": "Feature",
  "properties": {
    "iso:country":"US",
    "sg:address":"105 Broad St SW",
    "sg:city":"Atlanta",
    "sg:classifiers":[
        {
            "category":"Building & Trades",
            "subcategory":"Electrical",
            "type":"Services"
        }
    ],
    "sg:phone":"+1 631 671 4878",
    "sg:postcode":"30303",
    "sg:province":"GA",
    "sg:tags":[
        "industrial",
        "electrician",
        "contractors-commercial",
        "electric"
    ],
    "wof:name":"Rasool Electrical & Construction",
    "wof:placetype":"venue"
},
  "geometry": {"coordinates":[-84.39337399999999,33.751677],"type":"Point"}
}