{
  "type": "Feature",
  "properties": {
    "addr:full":"143 Ashford Cir Atlanta GA 30338",
    "addr:housenumber":"143",
    "addr:postcode":"30338",
    "addr:street":"Ashford Cir",
    "iso:country":"US",
    "sg:address":"143 Ashford Cir",
    "sg:city":"Atlanta",
    "sg:classifiers":[
        {
            "category":"Professional",
            "subcategory":"Management & Consulting",
            "type":"Services"
        }
    ],
    "sg:phone":"+1 404 606 1188",
    "sg:postcode":"30338",
    "sg:province":"GA",
    "sg:tags":[
        "business"
    ],
    "wof:name":"Kandev Consulting LLC",
    "wof:placetype":"venue"
},
  "geometry": {"coordinates":[-84.336607,33.941873],"type":"Point"}
}