{
  "type": "Feature",
  "properties": {
    "iso:country":"US",
    "sg:address":"2568 Kings Way NW",
    "sg:city":"Lawrenceville",
    "sg:classifiers":[
        {
            "category":"Building & Trades",
            "subcategory":"Construction",
            "type":"Services"
        }
    ],
    "sg:phone":"+1 770 381 7948",
    "sg:postcode":"30044",
    "sg:province":"GA",
    "sg:tags":[
        "nonresidential"
    ],
    "wof:name":"Moffitt Enterprises",
    "wof:placetype":"venue"
},
  "geometry": {"coordinates":[-84.065653,33.921834],"type":"Point"}
}