{
  "type": "Feature",
  "properties": {
    "addr:full":"2759 Delk Rd SE Marietta GA 30067",
    "addr:housenumber":"2759",
    "addr:postcode":"30067",
    "addr:street":"Delk Rd Se",
    "iso:country":"US",
    "sg:address":"2759 Delk Rd SE",
    "sg:city":"Marietta",
    "sg:classifiers":[
        {
            "category":"Professional",
            "type":"Services"
        }
    ],
    "sg:phone":"+1 770 953 1888",
    "sg:postcode":"30067",
    "sg:province":"GA",
    "wof:name":"EZ Carbuy",
    "wof:placetype":"venue"
},
  "geometry": {"coordinates":[-84.470647,33.924086],"type":"Point"}
}