{
  "type": "Feature",
  "properties": {
    "iso:country":"US",
    "sg:address":"28 Sloan St",
    "sg:city":"Roswell",
    "sg:classifiers":[
        {
            "category":"Professional",
            "subcategory":"Management & Consulting",
            "type":"Services"
        }
    ],
    "sg:phone":"+1 770 552 3083",
    "sg:postcode":"30075",
    "sg:province":"GA",
    "sg:tags":[
        "business"
    ],
    "wof:name":"Momentum Technology",
    "wof:placetype":"venue"
},
  "geometry": {"coordinates":[-84.361886,34.015499],"type":"Point"}
}