{
  "type": "Feature",
  "properties": {
    "addr:full":"3001 Cobb Pkwy Atlanta GA 30339",
    "addr:housenumber":"3001",
    "addr:postcode":"30339",
    "addr:street":"Cobb Pkwy",
    "iso:country":"US",
    "sg:address":"3001 Cobb Pkwy",
    "sg:city":"Atlanta",
    "sg:classifiers":[
        {
            "category":"Shopping",
            "subcategory":"Pharmacy",
            "type":"Retail Goods"
        }
    ],
    "sg:phone":"+1 770 435 4404",
    "sg:postcode":"30339",
    "sg:province":"GA",
    "sg:tags":[
        "drugstore"
    ],
    "wof:name":"Nolen Inc",
    "wof:placetype":"venue"
},
  "geometry": {"coordinates":[-84.46383299999999,33.880995],"type":"Point"}
}