{
  "type": "Feature",
  "properties": {
    "addr:full":"5508 Peachtree Industrial Blvd Atlanta GA 30341",
    "addr:housenumber":"5508",
    "addr:postcode":"30341",
    "addr:street":"Peachtree Industrial Blvd",
    "iso:country":"US",
    "sg:address":"5508 Peachtree Industrial Blvd",
    "sg:city":"Atlanta",
    "sg:classifiers":[
        {
            "category":"Professional",
            "subcategory":"Management & Consulting",
            "type":"Services"
        },
        {
            "category":"Personal",
            "type":"Services"
        },
        {
            "category":"Shopping",
            "subcategory":"Discount & Variety Stores",
            "type":"Retail Goods"
        }
    ],
    "sg:phone":"+1 770 451 4028",
    "sg:postcode":"30341",
    "sg:province":"GA",
    "sg:tags":[
        "liquidation",
        "liquidator",
        "consultant",
        "motel",
        "hotel",
        "estates-sales",
        "appraisal"
    ],
    "sg:website":"http://www.hclsales.com",
    "wof:name":"Hotel Content Liquidators",
    "wof:placetype":"venue"
},
  "geometry": {"coordinates":[-84.302013,33.898248],"type":"Point"}
}