{
  "type": "Feature",
  "properties": {
    "addr:full":"410 State Rte 81 E Mcdonough GA 30252",
    "addr:housenumber":"410",
    "addr:postcode":"30252",
    "addr:street":"State Rte 81 E",
    "iso:country":"US",
    "sg:address":"410 State Rte 81 E",
    "sg:city":"Mcdonough",
    "sg:classifiers":[
        {
            "category":"Shopping",
            "subcategory":"Books",
            "type":"Retail Goods"
        }
    ],
    "sg:phone":"+1 770 389 4410",
    "sg:postcode":"30252",
    "sg:province":"GA",
    "sg:tags":[
        "dealer"
    ],
    "wof:name":"Because He Lives Christian",
    "wof:placetype":"venue"
},
  "geometry": {"coordinates":[-84.12885300000001,33.442896],"type":"Point"}
}