{
  "type": "Feature",
  "properties": {
    "iso:country":"US",
    "sg:address":"1580 Forest Hill Rd",
    "sg:city":"Macon",
    "sg:classifiers":[
        {
            "category":"Bars & Pubs",
            "type":"Food & Drink"
        }
    ],
    "sg:phone":"+1 478 477 0717",
    "sg:postcode":"31210",
    "sg:province":"GA",
    "sg:tags":[
        "lounge",
        "drinking",
        "cocktail"
    ],
    "wof:name":"Billy's Clubhouse",
    "wof:placetype":"venue"
},
  "geometry": {"coordinates":[-83.702158,32.896379],"type":"Point"}
}