{
  "type": "Feature",
  "properties": {
    "addr:full":"117 S Perry St Lawrenceville GA 30045",
    "addr:housenumber":"117",
    "addr:postcode":"30045",
    "addr:street":"S Perry St",
    "iso:country":"US",
    "sg:address":"117 S Perry St",
    "sg:city":"Lawrenceville",
    "sg:classifiers":[
        {
            "category":"Restaurant",
            "type":"Food & Drink"
        },
        {
            "category":"Food & Beverages",
            "subcategory":"Bakery",
            "type":"Retail Goods"
        }
    ],
    "sg:phone":"+1 770 995 0805",
    "sg:postcode":"30045",
    "sg:province":"GA",
    "sg:tags":[
        "greek",
        "vegetarian",
        "sandwich",
        "mediterranean"
    ],
    "wof:name":"Uptown Cafe",
    "wof:placetype":"venue"
},
  "geometry": {"coordinates":[-83.989531,33.955823],"type":"Point"}
}