{
  "type": "Feature",
  "properties": {
    "addr:full":"6199 Hickory Flat Hwy Ste 130 Canton GA 30115",
    "addr:housenumber":"6199",
    "addr:postcode":"30115",
    "addr:street":"Hickory Flat Hwy Ste 130",
    "iso:country":"US",
    "sg:address":"6199 Hickory Flat Hwy Ste 130",
    "sg:city":"Canton",
    "sg:classifiers":[
        {
            "category":"Health Services",
            "subcategory":"Dentist",
            "type":"Services"
        }
    ],
    "sg:phone":"+1 770 345 8646",
    "sg:postcode":"30115",
    "sg:province":"GA",
    "sg:website":"www.dameronsmiles.com",
    "wof:name":"Dameron Family Dentistry",
    "wof:placetype":"venue"
},
  "geometry": {"coordinates":[-84.471901,34.221699],"type":"Point"}
}