{
  "type": "Feature",
  "properties": {
    "iso:country":"US",
    "sg:address":"104 Lake Dr",
    "sg:city":"Warner Robins",
    "sg:classifiers":[
        {
            "category":"Building & Trades",
            "subcategory":"Construction",
            "type":"Services"
        },
        {
            "category":"Building & Trades",
            "subcategory":"Plumbing",
            "type":"Services"
        }
    ],
    "sg:phone":"+1 478 923 8955",
    "sg:postcode":"31088",
    "sg:province":"GA",
    "sg:tags":[
        "repair",
        "mobile",
        "heating",
        "air",
        "conditioning",
        "home"
    ],
    "wof:name":"Layson's Mobile Home Repair",
    "wof:placetype":"venue"
},
  "geometry": {"coordinates":[-83.662369,32.605226],"type":"Point"}
}