{
  "type": "Feature",
  "properties": {
    "addr:full":"5555 Peachtree Dunwoody Rd Atlanta GA 30342",
    "addr:housenumber":"5555",
    "addr:postcode":"30342",
    "addr:street":"Peachtree Dunwoody Rd",
    "iso:country":"US",
    "sg:address":"5555 Peachtree Dunwoody Rd",
    "sg:city":"Atlanta",
    "sg:classifiers":[
        {
            "category":"Health Services",
            "subcategory":"Doctor",
            "type":"Services"
        }
    ],
    "sg:phone":"+1 404 843 3323",
    "sg:postcode":"30342",
    "sg:province":"GA",
    "sg:tags":[
        "physician",
        "surgeon"
    ],
    "wof:name":"Peachtree Spine & Pain Phys",
    "wof:placetype":"venue"
},
  "geometry": {"coordinates":[-84.352833,33.903523],"type":"Point"}
}