{
  "type": "Feature",
  "properties": {
    "iso:country":"US",
    "sg:address":"9582 Canvasback Ct",
    "sg:city":"Jonesboro",
    "sg:classifiers":[
        {
            "category":"Professional",
            "subcategory":"Business Services",
            "type":"Services"
        }
    ],
    "sg:phone":"+1 770 478 1090",
    "sg:postcode":"30238",
    "sg:province":"GA",
    "sg:tags":[
        "marketing",
        "translation",
        "consulting",
        "language",
        "res"
    ],
    "wof:name":"Parlez-Vous Francais",
    "wof:placetype":"venue"
},
  "geometry": {"coordinates":[-84.399738,33.494468],"type":"Point"}
}