{
  "type": "Feature",
  "properties": {
    "addr:full":"1700 N Brown Rd NW Lawrenceville GA 30043",
    "addr:housenumber":"1700",
    "addr:postcode":"30043",
    "addr:street":"N Brown Rd Nw",
    "iso:country":"US",
    "sg:address":"1700 N Brown Rd NW",
    "sg:city":"Lawrenceville",
    "sg:classifiers":[
        {
            "category":"Organizations",
            "subcategory":"Religious Organization",
            "type":"Services"
        }
    ],
    "sg:phone":"+1 678 825 1260",
    "sg:postcode":"30043",
    "sg:province":"GA",
    "sg:tags":[
        "department",
        "church"
    ],
    "wof:name":"Insuracne Annuities & Relief",
    "wof:placetype":"venue"
},
  "geometry": {"coordinates":[-84.077449,33.992409],"type":"Point"}
}