{
  "type": "Feature",
  "properties": {
    "iso:country":"US",
    "sg:address":"2269 Scenic Dr",
    "sg:city":"Snellville",
    "sg:classifiers":[
        {
            "category":"Shopping",
            "subcategory":"Catalog Store",
            "type":"Retail Goods"
        }
    ],
    "sg:phone":"+1 678 344 5041",
    "sg:postcode":"30078",
    "sg:province":"GA",
    "sg:tags":[
        "house",
        "mail"
    ],
    "wof:name":"Neal Racing Converters",
    "wof:placetype":"venue"
},
  "geometry": {"coordinates":[-84.036249,33.852294],"type":"Point"}
}