{
  "type": "Feature",
  "properties": {
    "iso:country":"US",
    "sg:address":"1230 Dawson Rd",
    "sg:city":"Winterville",
    "sg:classifiers":[
        {
            "category":"Autos & Motor Vehicles",
            "subcategory":"Recreational Vehicle Sales",
            "type":"Retail Goods"
        }
    ],
    "sg:phone":"+1 706 742 8914",
    "sg:postcode":"30683",
    "sg:province":"GA",
    "sg:tags":[
        "cap",
        "truck",
        "trailer",
        "accessory"
    ],
    "wof:name":"Town & Country Campers",
    "wof:placetype":"venue"
},
  "geometry": {"coordinates":[-83.25637,33.933066],"type":"Point"}
}