{
  "type": "Feature",
  "properties": {
    "iso:country":"US",
    "sg:address":"11460 Maxwell Rd",
    "sg:city":"Alpharetta",
    "sg:classifiers":[
        {
            "category":"Retail",
            "subcategory":"Car Wash",
            "type":"Services"
        },
        {
            "category":"Retail",
            "subcategory":"Auto Repair",
            "type":"Services"
        }
    ],
    "sg:phone":"+1 770 360 9100",
    "sg:postcode":"30009",
    "sg:province":"GA",
    "sg:tags":[
        "body",
        "repairing",
        "painting",
        "automobile"
    ],
    "wof:name":"Fast-Trak Body Werks",
    "wof:placetype":"venue"
},
  "geometry": {"coordinates":[-84.302041,34.055327],"type":"Point"}
}