{
  "type": "Feature",
  "properties": {
    "iso:country":"US",
    "sg:address":"1480 Iris Dr SW",
    "sg:city":"Conyers",
    "sg:classifiers":[
        {
            "category":"Autos & Motor Vehicles",
            "subcategory":"Automobile Sales",
            "type":"Retail Goods"
        }
    ],
    "sg:phone":"+1 770 602 4306",
    "sg:postcode":"30094",
    "sg:province":"GA",
    "sg:tags":[
        "car",
        "dealer"
    ],
    "wof:name":"Star Suzuki Conyers",
    "wof:placetype":"venue"
},
  "geometry": {"coordinates":[-84.036126,33.667208],"type":"Point"}
}