{
  "type": "Feature",
  "properties": {
    "iso:country":"US",
    "sg:address":"240 Peachtree St NW",
    "sg:city":"Atlanta",
    "sg:classifiers":[
        {
            "category":"Wholesale",
            "subcategory":"Furniture",
            "type":"Manufacturing & Wholesale Goods"
        }
    ],
    "sg:phone":"+1 404 222 0392",
    "sg:postcode":"30303",
    "sg:province":"GA",
    "sg:tags":[
        "furniture-wholesale",
        "manufacturer"
    ],
    "sg:website":"www.artmaxfurniture.com",
    "wof:name":"Artmax",
    "wof:placetype":"venue"
},
  "geometry": {"coordinates":[-84.387581,33.760858],"type":"Point"}
}