{
  "type": "Feature",
  "properties": {
    "addr:full":"4994 Lower Roswell Rd Marietta GA 30068",
    "addr:housenumber":"4994",
    "addr:postcode":"30068",
    "addr:street":"Lower Roswell Rd",
    "iso:country":"US",
    "sg:address":"4994 Lower Roswell Rd",
    "sg:city":"Marietta",
    "sg:classifiers":[
        {
            "category":"Personal",
            "subcategory":"Massage",
            "type":"Services"
        }
    ],
    "sg:phone":"+1 770 977 7778",
    "sg:postcode":"30068",
    "sg:province":"GA",
    "wof:name":"Balance Massage",
    "wof:placetype":"venue"
},
  "geometry": {"coordinates":[-84.404343,33.966922],"type":"Point"}
}