{
  "type": "Feature",
  "properties": {
    "iso:country":"US",
    "sg:address":"1151 Kristen Cv",
    "sg:city":"Atlanta",
    "sg:classifiers":[
        {
            "category":"Social Services",
            "subcategory":"Child Care",
            "type":"Services"
        }
    ],
    "sg:phone":"+1 770 907 2657",
    "sg:postcode":"30349",
    "sg:province":"GA",
    "sg:tags":[
        "nursery",
        "day"
    ],
    "wof:name":"Hills Family Community Day Care",
    "wof:placetype":"venue"
},
  "geometry": {"coordinates":[-84.427116,33.603774],"type":"Point"}
}