{
  "type": "Feature",
  "properties": {
    "addr:full":"112 Park Pl Dublin GA 31021",
    "addr:housenumber":"112",
    "addr:postcode":"31021",
    "addr:street":"Park Pl",
    "iso:country":"US",
    "sg:address":"112 Park Pl",
    "sg:city":"Dublin",
    "sg:classifiers":[
        {
            "category":"Insurance",
            "subcategory":"Insurance Agent",
            "type":"Services"
        }
    ],
    "sg:phone":"+1 478 272 2520",
    "sg:postcode":"31021",
    "sg:province":"GA",
    "wof:name":"State Farm Insurance",
    "wof:placetype":"venue"
},
  "geometry": {"coordinates":[-82.912325,32.538568],"type":"Point"}
}