{
  "type": "Feature",
  "properties": {
    "addr:full":"2338 Thomson Rd Washington GA 30673",
    "addr:housenumber":"2338",
    "addr:postcode":"30673",
    "addr:street":"Thomson Rd",
    "iso:country":"US",
    "sg:address":"2338 Thomson Rd",
    "sg:city":"Washington",
    "sg:classifiers":[
        {
            "category":"Farming",
            "subcategory":"Livestock Farm",
            "type":"Manufacturing & Wholesale Goods"
        }
    ],
    "sg:phone":"+1 706 678 7885",
    "sg:postcode":"30673",
    "sg:province":"GA",
    "sg:tags":[
        "animal",
        "producer",
        "general"
    ],
    "wof:name":"Old South Cattle Company",
    "wof:placetype":"venue"
},
  "geometry": {"coordinates":[-82.65725999999999,33.687448],"type":"Point"}
}