{
  "type": "Feature",
  "properties": {
    "iso:country":"US",
    "sg:address":"264 Countryside Dr SW",
    "sg:city":"Calhoun",
    "sg:classifiers":[
        {
            "category":"Food & Beverages",
            "subcategory":"Specialty",
            "type":"Retail Goods"
        }
    ],
    "sg:phone":"+1 706 625 1810",
    "sg:postcode":"30701",
    "sg:province":"GA",
    "sg:tags":[
        "health",
        "diet"
    ],
    "wof:name":"Herbalife Independent Dist",
    "wof:placetype":"venue"
},
  "geometry": {"coordinates":[-84.954437,34.439803],"type":"Point"}
}