{
  "type": "Feature",
  "properties": {
    "addr:full":"203 Woodpark Pl Ste A200 Woodstock GA 30188",
    "addr:housenumber":"203",
    "addr:postcode":"30188",
    "addr:street":"Woodpark Pl Ste A200",
    "iso:country":"US",
    "sg:address":"203 Woodpark Pl Ste A200",
    "sg:city":"Woodstock",
    "sg:classifiers":[
        {
            "category":"Health Services",
            "subcategory":"Doctor",
            "type":"Services"
        }
    ],
    "sg:phone":"+1 770 924 6255",
    "sg:postcode":"30188",
    "sg:province":"GA",
    "sg:tags":[
        "obstetrician",
        "gynecologist"
    ],
    "wof:name":"Arista OB Gyn",
    "wof:placetype":"venue"
},
  "geometry": {"coordinates":[-84.52419999999999,34.0868],"type":"Point"}
}