{
  "type": "Feature",
  "properties": {
    "addr:full":"1350 Northmeadow Pkwy Roswell GA 30076",
    "addr:housenumber":"1350",
    "addr:postcode":"30076",
    "addr:street":"Northmeadow Pkwy",
    "iso:country":"US",
    "sg:address":"1350 Northmeadow Pkwy",
    "sg:city":"Roswell",
    "sg:classifiers":[
        {
            "category":"Utilities",
            "subcategory":"Mobile Phone",
            "type":"Services"
        }
    ],
    "sg:phone":"+1 770 667 4700",
    "sg:postcode":"30076",
    "sg:province":"GA",
    "sg:tags":[
        "telephone",
        "cellular"
    ],
    "wof:name":"Verizon",
    "wof:placetype":"venue"
},
  "geometry": {"coordinates":[-84.32038,34.066445],"type":"Point"}
}