{
  "type": "Feature",
  "properties": {
    "iso:country":"US",
    "sg:address":"688 Cumberland Cir NE",
    "sg:city":"Atlanta",
    "sg:classifiers":[
        {
            "category":"Banks & Credit Unions",
            "subcategory":"Investment Brokerage",
            "type":"Services"
        }
    ],
    "sg:phone":"+1 404 607 8607",
    "sg:postcode":"30306",
    "sg:province":"GA",
    "sg:tags":[
        "advisory"
    ],
    "wof:name":"Mike Szalkowski",
    "wof:placetype":"venue"
},
  "geometry": {"coordinates":[-84.36362200000001,33.797221],"type":"Point"}
}