{
  "type": "Feature",
  "properties": {
    "addr:full":"6135 Jimmy Carter Blvd C134 Norcross GA 30071",
    "addr:housenumber":"6135",
    "addr:postcode":"30071",
    "addr:street":"Jimmy Carter Blvd C134",
    "iso:country":"US",
    "sg:address":"6135 Jimmy Carter Blvd C134",
    "sg:city":"Norcross",
    "sg:classifiers":[
        {
            "category":"Wholesale",
            "subcategory":"Office Equipment",
            "type":"Manufacturing & Wholesale Goods"
        },
        {
            "category":"Building & Trades",
            "subcategory":"Equipment Rental",
            "type":"Services"
        }
    ],
    "sg:phone":"+1 770 448 4705",
    "sg:postcode":"30071",
    "sg:province":"GA",
    "sg:tags":[
        "refinish",
        "furniture",
        "leasing",
        "equipment-repair",
        "equipment-renting"
    ],
    "wof:name":"Allied Business Systems",
    "wof:placetype":"venue"
},
  "geometry": {"coordinates":[-84.215947,33.92453],"type":"Point"}
}