{
  "type": "Feature",
  "properties": {
    "iso:country":"US",
    "sg:address":"210 E 2nd Ave",
    "sg:city":"Rome",
    "sg:classifiers":[
        {
            "category":"Wholesale",
            "subcategory":"Office Equipment",
            "type":"Manufacturing & Wholesale Goods"
        }
    ],
    "sg:phone":"+1 706 232 2928",
    "sg:postcode":"30161",
    "sg:province":"GA",
    "sg:tags":[
        "bank",
        "supply"
    ],
    "wof:name":"Bank & Business Systems Inc",
    "wof:placetype":"venue"
},
  "geometry": {"coordinates":[-85.172419,34.250598],"type":"Point"}
}