{
  "type": "Feature",
  "properties": {
    "addr:full":"260 14th St NW Atlanta GA 30318",
    "addr:housenumber":"260",
    "addr:postcode":"30318",
    "addr:street":"14Th St Nw",
    "iso:country":"US",
    "sg:address":"260 14th St NW",
    "sg:city":"Atlanta",
    "sg:classifiers":[
        {
            "category":"Organizations",
            "subcategory":"Membership Organization",
            "type":"Services"
        }
    ],
    "sg:phone":"+1 404 685 2787",
    "sg:postcode":"30318",
    "sg:province":"GA",
    "sg:tags":[
        "broadcast",
        "television"
    ],
    "sg:website":"http://www.osah.state.ga.us",
    "wof:name":"Georgia Council For The Arts",
    "wof:placetype":"venue"
},
  "geometry": {"coordinates":[-84.395573,33.786357],"type":"Point"}
}