{
  "type": "Feature",
  "properties": {
    "iso:country":"US",
    "sg:address":"2970 N Lake Pkwy",
    "sg:city":"Columbus",
    "sg:classifiers":[
        {
            "category":"Restaurant",
            "type":"Food & Drink"
        }
    ],
    "sg:menulink":"http://www.allmenus.com/ga/columbus/10335-texas-roadhouse/menu/",
    "sg:phone":"+1 706 323 6616",
    "sg:postcode":"31909",
    "sg:province":"GA",
    "sg:tags":[
        "american",
        "steakhouse"
    ],
    "wof:name":"Texas Roadhouse",
    "wof:placetype":"venue"
},
  "geometry": {"coordinates":[-84.94697600000001,32.552014],"type":"Point"}
}