{
  "type": "Feature",
  "properties": {
    "iso:country":"US",
    "sg:address":"1252 Lawrenceville Suwanee Rd",
    "sg:city":"Lawrenceville",
    "sg:classifiers":[
        {
            "category":"Retail",
            "subcategory":"Repair Shop",
            "type":"Services"
        }
    ],
    "sg:phone":"+1 888 492 5831",
    "sg:postcode":"30043",
    "sg:province":"GA",
    "sg:tags":[
        "television",
        "radio-service"
    ],
    "sg:website":"http://local.ingenio.com/Listings/Details.aspx?NUM=a%3a9246554%3a13%3a4859924%3a14%3a0%3a7",
    "wof:name":"Sam's Electronics",
    "wof:placetype":"venue"
},
  "geometry": {"coordinates":[-84.020866,33.981756],"type":"Point"}
}