{
  "type": "Feature",
  "properties": {
    "iso:country":"US",
    "sg:address":"100 Peachtree St SW",
    "sg:city":"Atlanta",
    "sg:classifiers":[
        {
            "category":"Professional",
            "subcategory":"Management & Consulting",
            "type":"Services"
        }
    ],
    "sg:phone":"+1 404 688 8495",
    "sg:postcode":"30303",
    "sg:province":"GA",
    "sg:tags":[
        "information",
        "business"
    ],
    "wof:name":"Efficient Markets Corporation",
    "wof:placetype":"venue"
},
  "geometry": {"coordinates":[-84.39289100000001,33.751018],"type":"Point"}
}