{
  "type": "Feature",
  "properties": {
    "addr:full":"1455 Hearst Dr NE Atlanta GA 30319",
    "addr:housenumber":"1455",
    "addr:postcode":"30319",
    "addr:street":"Hearst Dr Ne",
    "iso:country":"US",
    "sg:address":"1455 Hearst Dr NE",
    "sg:city":"Atlanta",
    "sg:classifiers":[
        {
            "category":"Home & Garden",
            "subcategory":"Garden Supply",
            "type":"Retail Goods"
        }
    ],
    "sg:phone":"+1 404 252 1933",
    "sg:postcode":"30319",
    "sg:province":"GA",
    "wof:name":"Silver Lake Garden Club",
    "wof:placetype":"venue"
},
  "geometry": {"coordinates":[-84.328553,33.884964],"type":"Point"}
}