{
  "type": "Feature",
  "properties": {
    "addr:full":"13025 Birmingham Hwy Alpharetta GA 30004",
    "addr:housenumber":"13025",
    "addr:postcode":"30004",
    "addr:street":"Birmingham Hwy",
    "iso:country":"US",
    "sg:address":"13025 Birmingham Hwy",
    "sg:city":"Alpharetta",
    "sg:classifiers":[
        {
            "category":"Building & Trades",
            "subcategory":"Plumbing",
            "type":"Services"
        }
    ],
    "sg:phone":"+1 678 624 9292",
    "sg:postcode":"30004",
    "sg:province":"GA",
    "sg:tags":[
        "plumbing",
        "contractor"
    ],
    "wof:name":"Mock Plumbing & Mechanical",
    "wof:placetype":"venue"
},
  "geometry": {"coordinates":[-84.33936799999999,34.091069],"type":"Point"}
}