{
  "type": "Feature",
  "properties": {
    "addr:full":"158 Rumson Road NE Atlanta GA 30305",
    "addr:housenumber":"158",
    "addr:postcode":"30305",
    "addr:street":"Rumson Road Ne",
    "iso:country":"US",
    "sg:address":"158 Rumson Road NE",
    "sg:city":"Atlanta",
    "sg:classifiers":[
        {
            "category":"Arts & Performance",
            "subcategory":"Art Gallery",
            "type":"Entertainment"
        }
    ],
    "sg:phone":"+1 404 261 1712",
    "sg:postcode":"30305",
    "sg:province":"GA",
    "wof:name":"Connell Gallery-Great American Gallery",
    "wof:placetype":"venue"
},
  "geometry": {"coordinates":[-84.382238,33.831067],"type":"Point"}
}