{
  "type": "Feature",
  "properties": {
    "iso:country":"US",
    "sg:address":"3145 Briarcliff Rd NE",
    "sg:city":"Atlanta",
    "sg:classifiers":[
        {
            "category":"Tea Room",
            "subcategory":"None",
            "type":"Food & Drink"
        },
        {
            "category":"Coffee & Tea",
            "type":"Food & Drink"
        },
        {
            "category":"Restaurant",
            "type":"Food & Drink"
        }
    ],
    "sg:phone":"+1 404 728 0999",
    "sg:postcode":"30329",
    "sg:province":"GA",
    "sg:tags":[
        "ethiopian",
        "espresso"
    ],
    "sg:website":"skycitycoffee.com/",
    "wof:name":"Sky City Coffee",
    "wof:placetype":"venue"
},
  "geometry": {"coordinates":[-84.30999799999999,33.83736],"type":"Point"}
}