{
  "type": "Feature",
  "properties": {
    "iso:country":"US",
    "sg:address":"2008 N Ashley St",
    "sg:city":"Valdosta",
    "sg:classifiers":[
        {
            "category":"Shopping",
            "subcategory":"Bicycles & Sporting Goods",
            "type":"Retail Goods"
        }
    ],
    "sg:phone":"+1 912 247 1444",
    "sg:postcode":"31602",
    "sg:province":"GA",
    "wof:name":"P Js Bait & Tackle",
    "wof:placetype":"venue"
},
  "geometry": {"coordinates":[-83.280801,30.85723],"type":"Point"}
}