{
  "type": "Feature",
  "properties": {
    "addr:full":"831 Oakhill Ave SW Atlanta GA 30310",
    "addr:housenumber":"831",
    "addr:postcode":"30310",
    "addr:street":"Oakhill Ave Sw",
    "iso:country":"US",
    "sg:address":"831 Oakhill Ave SW",
    "sg:city":"Atlanta",
    "sg:classifiers":[
        {
            "category":"Building & Trades",
            "subcategory":"Landscaping Services",
            "type":"Services"
        }
    ],
    "sg:phone":"+1 404 758 3311",
    "sg:postcode":"30310",
    "sg:province":"GA",
    "wof:name":"John W Jackson Lawn Servi",
    "wof:placetype":"venue"
},
  "geometry": {"coordinates":[-84.40938800000001,33.732009],"type":"Point"}
}