{
  "type": "Feature",
  "properties": {
    "iso:country":"US",
    "sg:address":"695 Mansell Rd",
    "sg:city":"Roswell",
    "sg:classifiers":[
        {
            "category":"Professional",
            "type":"Services"
        }
    ],
    "sg:phone":"+1 770 641 7721",
    "sg:postcode":"30076",
    "sg:province":"GA",
    "sg:tags":[
        "establishment"
    ],
    "wof:name":"Mark Mc Manus & Assoc LLC",
    "wof:placetype":"venue"
},
  "geometry": {"coordinates":[-84.34188,34.042835],"type":"Point"}
}