{
  "type": "Feature",
  "properties": {
    "addr:full":"1754 S Burnt Hickory Rd Douglasville GA 30134",
    "addr:housenumber":"1754",
    "addr:postcode":"30134",
    "addr:street":"S Burnt Hickory Rd",
    "iso:country":"US",
    "sg:address":"1754 S Burnt Hickory Rd",
    "sg:city":"Douglasville",
    "sg:classifiers":[
        {
            "category":"Government",
            "subcategory":"Fire Station",
            "type":"Public Place"
        }
    ],
    "sg:phone":"+1 770 920 0017",
    "sg:postcode":"30134",
    "sg:province":"GA",
    "sg:tags":[
        "extinguisher",
        "protection",
        "servicing",
        "equipment-repairing"
    ],
    "wof:name":"I D E C Inc",
    "wof:placetype":"venue"
},
  "geometry": {"coordinates":[-84.70365099999999,33.758395],"type":"Point"}
}