{
  "type": "Feature",
  "properties": {
    "iso:country":"US",
    "sg:address":"150 S Church St",
    "sg:city":"Canton",
    "sg:classifiers":[
        {
            "category":"Professional",
            "subcategory":"Accounting & Tax Preparation",
            "type":"Services"
        }
    ],
    "sg:phone":"+1 770 720 4829",
    "sg:postcode":"30114",
    "sg:province":"GA",
    "sg:tags":[
        "accountant"
    ],
    "wof:name":"Cannon James E CPA",
    "wof:placetype":"venue"
},
  "geometry": {"coordinates":[-84.49099699999999,34.236599],"type":"Point"}
}