{
  "type": "Feature",
  "properties": {
    "iso:country":"US",
    "sg:address":"481 Colton Rd",
    "sg:city":"Mc Caysville",
    "sg:classifiers":[
        {
            "category":"Manufacturing",
            "subcategory":"Apparel",
            "type":"Manufacturing & Wholesale Goods"
        }
    ],
    "sg:phone":"+1 706 492 5594",
    "sg:postcode":"30555",
    "sg:province":"GA",
    "wof:name":"Performance Screen Prtg & EMB",
    "wof:placetype":"venue"
},
  "geometry": {"coordinates":[-84.373189,34.973659],"type":"Point"}
}