{
  "type": "Feature",
  "properties": {
    "iso:country":"US",
    "sg:address":"5619 Hwy 20 NE",
    "sg:city":"Cartersville",
    "sg:classifiers":[
        {
            "category":"Recreation",
            "type":"Entertainment"
        }
    ],
    "sg:phone":"+1 770 386 8562",
    "sg:postcode":"30121",
    "sg:province":"GA",
    "sg:tags":[
        "club",
        "membership"
    ],
    "wof:name":"Cartersville Golf Range",
    "wof:placetype":"venue"
},
  "geometry": {"coordinates":[-84.767343,34.204992],"type":"Point"}
}