{
  "type": "Feature",
  "properties": {
    "addr:full":"1101 Hillcrest Pkwy Dublin GA 31021",
    "addr:housenumber":"1101",
    "addr:postcode":"31021",
    "addr:street":"Hillcrest Pkwy",
    "iso:country":"US",
    "sg:address":"1101 Hillcrest Pkwy",
    "sg:city":"Dublin",
    "sg:classifiers":[
        {
            "category":"Professional",
            "type":"Services"
        },
        {
            "category":"Professional",
            "subcategory":"Business Services",
            "type":"Services"
        },
        {
            "category":"Professional",
            "subcategory":"Printing & Photocopies",
            "type":"Services"
        }
    ],
    "sg:phone":"+1 478 272 7676",
    "sg:postcode":"31021",
    "sg:province":"GA",
    "sg:tags":[
        "duplicating",
        "labeling",
        "packaging",
        "messenger",
        "shipping",
        "copying",
        "mail"
    ],
    "wof:name":"Mail & More",
    "wof:placetype":"venue"
},
  "geometry": {"coordinates":[-82.928301,32.547947],"type":"Point"}
}