{
  "type": "Feature",
  "properties": {
    "iso:country":"US",
    "sg:address":"235 Seay Ave",
    "sg:city":"Marietta",
    "sg:classifiers":[
        {
            "category":"Building & Trades",
            "subcategory":"Construction",
            "type":"Services"
        }
    ],
    "sg:phone":"+1 770 426 7030",
    "sg:postcode":"30060",
    "sg:province":"GA",
    "sg:tags":[
        "concrete",
        "contractor"
    ],
    "wof:name":"Motes Concrete Construction",
    "wof:placetype":"venue"
},
  "geometry": {"coordinates":[-84.54764400000001,33.912163],"type":"Point"}
}