{
  "type": "Feature",
  "properties": {
    "addr:full":"3685 Pilgrim Mill Rd Cumming GA 30041",
    "addr:housenumber":"3685",
    "addr:postcode":"30041",
    "addr:street":"Pilgrim Mill Rd",
    "iso:country":"US",
    "sg:address":"3685 Pilgrim Mill Rd",
    "sg:city":"Cumming",
    "sg:classifiers":[
        {
            "category":"Marine",
            "type":"Transportation"
        }
    ],
    "sg:phone":"+1 770 889 7743",
    "sg:postcode":"30041",
    "sg:province":"GA",
    "sg:tags":[
        "transporting",
        "boat"
    ],
    "wof:name":"Lake Lanier Marine Consignment",
    "wof:placetype":"venue"
},
  "geometry": {"coordinates":[-84.07606,34.213155],"type":"Point"}
}