{
  "type": "Feature",
  "properties": {
    "iso:country":"US",
    "sg:address":"5445 Triangle Pkwy NW",
    "sg:city":"Norcross",
    "sg:classifiers":[
        {
            "category":"Professional",
            "subcategory":"Computer Services",
            "type":"Services"
        }
    ],
    "sg:phone":"+1 770 559 6386",
    "sg:postcode":"30092",
    "sg:province":"GA",
    "sg:tags":[
        "application",
        "software"
    ],
    "wof:name":"Invistics Corporation",
    "wof:placetype":"venue"
},
  "geometry": {"coordinates":[-84.22321599999999,33.974273],"type":"Point"}
}