{
  "type": "Feature",
  "properties": {
    "iso:country":"US",
    "sg:address":"1459 Field Park Cir",
    "sg:city":"Marietta",
    "sg:classifiers":[
        {
            "category":"Restaurant",
            "type":"Food & Drink"
        }
    ],
    "sg:menulink":"http://www.allmenus.com/ga/marietta/238652-royal-waffel-king/menu/",
    "sg:phone":"+1 770 537 8000",
    "sg:postcode":"30066",
    "sg:province":"GA",
    "sg:tags":[
        "american"
    ],
    "wof:name":"Royal Waffel King",
    "wof:placetype":"venue"
},
  "geometry": {"coordinates":[-84.563525,33.986811],"type":"Point"}
}