{
  "type": "Feature",
  "properties": {
    "iso:country":"US",
    "sg:address":"3635 Southside Industrial Pkwy",
    "sg:city":"Atlanta",
    "sg:classifiers":[
        {
            "category":"Freight",
            "type":"Transportation"
        }
    ],
    "sg:phone":"+1 404 608 2690",
    "sg:postcode":"30354",
    "sg:province":"GA",
    "sg:tags":[
        "arrangement"
    ],
    "wof:name":"Airborne",
    "wof:placetype":"venue"
},
  "geometry": {"coordinates":[-84.37410800000001,33.657155],"type":"Point"}
}