{
  "type": "Feature",
  "properties": {
    "iso:country":"US",
    "sg:address":"743 Jodie Hobby Rd",
    "sg:city":"Sylvester",
    "sg:classifiers":[
        {
            "category":"Shopping",
            "subcategory":"Hobbies, Toys, & Games",
            "type":"Retail Goods"
        }
    ],
    "sg:phone":"+1 229 776 4974",
    "sg:postcode":"31791",
    "sg:province":"GA",
    "sg:tags":[
        "shop",
        "model",
        "hobby",
        "supply"
    ],
    "sg:website":"http://www.olinepublishing.com",
    "wof:name":"Olin Hobby",
    "wof:placetype":"venue"
},
  "geometry": {"coordinates":[-83.832571,31.661401],"type":"Point"}
}