{
  "type": "Feature",
  "properties": {
    "iso:country":"US",
    "sg:address":"530 Sunnyside Dr",
    "sg:city":"Lawrenceville",
    "sg:classifiers":[
        {
            "category":"Professional",
            "type":"Services"
        }
    ],
    "sg:phone":"+1 770 931 2929",
    "sg:postcode":"30044",
    "sg:province":"GA",
    "wof:name":"Jyb Services Inc",
    "wof:placetype":"venue"
},
  "geometry": {"coordinates":[-84.096529,33.92054],"type":"Point"}
}