{
  "type": "Feature",
  "properties": {
    "iso:country":"US",
    "sg:address":"2 Saint Ives Dr",
    "sg:city":"Savannah",
    "sg:classifiers":[
        {
            "category":"Professional",
            "type":"Services"
        }
    ],
    "sg:phone":"+1 912 925 7051",
    "sg:postcode":"31419",
    "sg:province":"GA",
    "wof:name":"Laura A Oake",
    "wof:placetype":"venue"
},
  "geometry": {"coordinates":[-81.226041,31.976156],"type":"Point"}
}