{
  "type": "Feature",
  "properties": {
    "addr:full":"181 Athens St Carnesville GA 30521",
    "addr:housenumber":"181",
    "addr:postcode":"30521",
    "addr:street":"Athens St",
    "iso:country":"US",
    "sg:address":"181 Athens St",
    "sg:city":"Carnesville",
    "sg:classifiers":[
        {
            "category":"Shopping",
            "subcategory":"Clothing, Apparel, & Fashions",
            "type":"Retail Goods"
        },
        {
            "category":"Shopping",
            "subcategory":"Shoes",
            "type":"Retail Goods"
        }
    ],
    "sg:phone":"+1 706 384 4243",
    "sg:postcode":"30521",
    "sg:province":"GA",
    "sg:tags":[
        "clothing",
        "boots-retail",
        "store"
    ],
    "wof:name":"H N Little Company Boots Plus",
    "wof:placetype":"venue"
},
  "geometry": {"coordinates":[-83.234089,34.36981],"type":"Point"}
}