{
  "type": "Feature",
  "properties": {
    "addr:full":"55 Beaverdam Road Ext Athens GA 30605",
    "addr:housenumber":"55",
    "addr:postcode":"30605",
    "addr:street":"Beaverdam Road Ext",
    "iso:country":"US",
    "sg:address":"55 Beaverdam Road Ext",
    "sg:city":"Athens",
    "sg:classifiers":[
        {
            "category":"Government",
            "subcategory":"Office",
            "type":"Public Place"
        }
    ],
    "sg:phone":"+1 706 369 5605",
    "sg:postcode":"30605",
    "sg:province":"GA",
    "wof:name":"Athens Rgnal Yuth Dtention Ctr",
    "wof:placetype":"venue"
},
  "geometry": {"coordinates":[-83.32003400000001,33.954781],"type":"Point"}
}