{
  "type": "Feature",
  "properties": {
    "iso:country":"US",
    "sg:address":"7614 Neese Commerce Rd",
    "sg:city":"Hull",
    "sg:classifiers":[
        {
            "category":"Building & Trades",
            "subcategory":"Landscaping Services",
            "type":"Services"
        }
    ],
    "sg:phone":"+1 706 215 2187",
    "sg:postcode":"30646",
    "sg:province":"GA",
    "sg:tags":[
        "lawn",
        "maintenance"
    ],
    "wof:name":"Cut-Rite Lawn Maintenance & Landscaping",
    "wof:placetype":"venue"
},
  "geometry": {"coordinates":[-83.31635300000001,34.078816],"type":"Point"}
}