{
  "type": "Feature",
  "properties": {
    "iso:country":"US",
    "sg:address":"3835 Presidential Pkwy Ste 107",
    "sg:city":"Atlanta",
    "sg:classifiers":[
        {
            "category":"Banks & Credit Unions",
            "subcategory":"Financial Services",
            "type":"Services"
        }
    ],
    "sg:phone":"+1 770 451 1117",
    "sg:postcode":"30340",
    "sg:province":"GA",
    "sg:tags":[
        "broker",
        "mortgage"
    ],
    "wof:name":"First United Home Mortgage Corp",
    "wof:placetype":"venue"
},
  "geometry": {"coordinates":[-84.264503,33.887901],"type":"Point"}
}