{
  "type": "Feature",
  "properties": {
    "iso:country":"US",
    "sg:address":"941 Hampton Hill Ct",
    "sg:city":"Lawrenceville",
    "sg:classifiers":[
        {
            "category":"Retail",
            "subcategory":"Animal Services",
            "type":"Services"
        }
    ],
    "sg:phone":"+1 770 354 1231",
    "sg:postcode":"30044",
    "sg:province":"GA",
    "wof:name":"Dave Crocodile Inc",
    "wof:placetype":"venue"
},
  "geometry": {"coordinates":[-84.098394,33.938542],"type":"Point"}
}