{
  "type": "Feature",
  "properties": {
    "addr:full":"1040 Barber St Athens GA 30601",
    "addr:housenumber":"1040",
    "addr:postcode":"30601",
    "addr:street":"Barber St",
    "iso:country":"US",
    "sg:address":"1040 Barber St",
    "sg:city":"Athens",
    "sg:classifiers":[
        {
            "category":"Retail",
            "subcategory":"Auto Repair",
            "type":"Services"
        }
    ],
    "sg:phone":"+1 706 548 1414",
    "sg:postcode":"30601",
    "sg:province":"GA",
    "sg:tags":[
        "automotive"
    ],
    "wof:name":"City Wide of Athens Towing",
    "wof:placetype":"venue"
},
  "geometry": {"coordinates":[-83.389145,33.975104],"type":"Point"}
}