{
  "type": "Feature",
  "properties": {
    "addr:full":"415 S 8th St Griffin GA 30224",
    "addr:housenumber":"415",
    "addr:postcode":"30224",
    "addr:street":"S 8Th St",
    "iso:country":"US",
    "sg:address":"415 S 8th St",
    "sg:city":"Griffin",
    "sg:classifiers":[
        {
            "category":"Health Services",
            "subcategory":"Doctor",
            "type":"Services"
        }
    ],
    "sg:phone":"+1 770 228 3929",
    "sg:postcode":"30224",
    "sg:province":"GA",
    "sg:tags":[
        "physician",
        "surgeon",
        "kidneys",
        "surgeons",
        "nephrology"
    ],
    "wof:name":"Clemente, Rosa E Md",
    "wof:placetype":"venue"
},
  "geometry": {"coordinates":[-84.265556,33.24424],"type":"Point"}
}