{
  "type": "Feature",
  "properties": {
    "iso:country":"US",
    "sg:address":"4000 Rotterdam Pass",
    "sg:city":"Hampton",
    "sg:classifiers":[
        {
            "category":"Sports & Exercise",
            "subcategory":"Golf",
            "type":"Entertainment"
        }
    ],
    "sg:phone":"+1 770 897 0361",
    "sg:postcode":"30228",
    "sg:province":"GA",
    "wof:name":"Crystal Lake Golf and Country Club",
    "wof:placetype":"venue"
},
  "geometry": {"coordinates":[-84.265305,33.443977],"type":"Point"}
}