{
  "type": "Feature",
  "properties": {
    "addr:full":"508 Saddlecreek Dr Mcdonough GA 30253",
    "addr:housenumber":"508",
    "addr:postcode":"30253",
    "addr:street":"Saddlecreek Dr",
    "iso:country":"US",
    "sg:address":"508 Saddlecreek Dr",
    "sg:city":"Mcdonough",
    "sg:classifiers":[
        {
            "category":"Shopping",
            "type":"Retail Goods"
        }
    ],
    "sg:phone":"+1 678 610 5959",
    "sg:postcode":"30253",
    "sg:province":"GA",
    "sg:tags":[
        "pet",
        "shop"
    ],
    "wof:name":"Brandon's Pits",
    "wof:placetype":"venue"
},
  "geometry": {"coordinates":[-84.17159599999999,33.433844],"type":"Point"}
}