{
  "type": "Feature",
  "properties": {
    "iso:country":"US",
    "sg:address":"228 Morrow Rd",
    "sg:city":"Forest Park",
    "sg:classifiers":[
        {
            "category":"Professional",
            "type":"Services"
        }
    ],
    "sg:phone":"+1 404 675 9039",
    "sg:postcode":"30297",
    "sg:province":"GA",
    "wof:name":"Dorcas",
    "wof:placetype":"venue"
},
  "geometry": {"coordinates":[-84.38310199999999,33.59306],"type":"Point"}
}