{
  "type": "Feature",
  "properties": {
    "iso:country":"US",
    "sg:address":"61 Gravitt Dr",
    "sg:city":"Rising Fawn",
    "sg:classifiers":[
        {
            "category":"Building & Trades",
            "subcategory":"Construction",
            "type":"Services"
        }
    ],
    "sg:phone":"+1 706 820 8065",
    "sg:postcode":"30738",
    "sg:province":"GA",
    "sg:tags":[
        "excavation",
        "contractor"
    ],
    "wof:name":"Lookout Excavating & Cnstr",
    "wof:placetype":"venue"
},
  "geometry": {"coordinates":[-85.39330200000001,34.899547],"type":"Point"}
}