{
  "type": "Feature",
  "properties": {
    "addr:full":"9162 Old Atlanta Hwy Covington GA 30014",
    "addr:housenumber":"9162",
    "addr:postcode":"30014",
    "addr:street":"Old Atlanta Hwy",
    "iso:country":"US",
    "sg:address":"9162 Old Atlanta Hwy",
    "sg:city":"Covington",
    "sg:classifiers":[
        {
            "category":"Retail",
            "subcategory":"Repair Shop",
            "type":"Services"
        }
    ],
    "sg:phone":"+1 770 787 0077",
    "sg:postcode":"30014",
    "sg:province":"GA",
    "sg:tags":[
        "machine",
        "equipment",
        "recycling"
    ],
    "wof:name":"RSC Machine Corporation",
    "wof:placetype":"venue"
},
  "geometry": {"coordinates":[-83.87427,33.6076],"type":"Point"}
}