{
  "type": "Feature",
  "properties": {
    "addr:full":"7900 Dogwood Way Douglasville GA 30134",
    "addr:housenumber":"7900",
    "addr:postcode":"30134",
    "addr:street":"Dogwood Way",
    "iso:country":"US",
    "sg:address":"7900 Dogwood Way",
    "sg:city":"Douglasville",
    "sg:classifiers":[
        {
            "category":"Professional",
            "type":"Services"
        }
    ],
    "sg:phone":"+1 678 715 8060",
    "sg:postcode":"30134",
    "sg:province":"GA",
    "sg:tags":[
        "establishment"
    ],
    "wof:name":"Maryams Place",
    "wof:placetype":"venue"
},
  "geometry": {"coordinates":[-84.763479,33.764649],"type":"Point"}
}