{
  "type": "Feature",
  "properties": {
    "addr:full":"2166 Brownings Trce Tucker GA 30084",
    "addr:housenumber":"2166",
    "addr:postcode":"30084",
    "addr:street":"Brownings Trce",
    "iso:country":"US",
    "sg:address":"2166 Brownings Trce",
    "sg:city":"Tucker",
    "sg:classifiers":[
        {
            "category":"Shopping",
            "subcategory":"Gifts & Souvenirs",
            "type":"Retail Goods"
        }
    ],
    "sg:phone":"+1 770 621 0021",
    "sg:postcode":"30084",
    "sg:province":"GA",
    "wof:name":"Armsteads Porch Gifts",
    "wof:placetype":"venue"
},
  "geometry": {"coordinates":[-84.215863,33.847114],"type":"Point"}
}