{
  "type": "Feature",
  "properties": {
    "addr:full":"29 Hospital Rd Newnan GA 30263",
    "addr:housenumber":"29",
    "addr:postcode":"30263",
    "addr:street":"Hospital Rd",
    "iso:country":"US",
    "sg:address":"29 Hospital Rd",
    "sg:city":"Newnan",
    "sg:classifiers":[
        {
            "category":"Community Center",
            "subcategory":"Senior",
            "type":"Public Place"
        },
        {
            "category":"Social Services",
            "subcategory":"Adult Care",
            "type":"Services"
        }
    ],
    "sg:phone":"+1 770 683 8600",
    "sg:postcode":"30263",
    "sg:province":"GA",
    "sg:tags":[
        "counseling",
        "citizen"
    ],
    "wof:name":"Council On Aging",
    "wof:placetype":"venue"
},
  "geometry": {"coordinates":[-84.81752,33.38807],"type":"Point"}
}