{
  "type": "Feature",
  "properties": {
    "iso:country":"US",
    "sg:address":"121 N Corners Pkwy",
    "sg:city":"Cumming",
    "sg:classifiers":[
        {
            "category":"Shopping",
            "subcategory":"Discount & Variety Stores",
            "type":"Retail Goods"
        }
    ],
    "sg:phone":"+1 678 513 7599",
    "sg:postcode":"30040",
    "sg:province":"GA",
    "wof:name":"Dollar General",
    "wof:placetype":"venue"
},
  "geometry": {"coordinates":[-84.153904,34.216059],"type":"Point"}
}