{
  "type": "Feature",
  "properties": {
    "iso:country":"US",
    "sg:address":"1440 Dutch Valley Pl NE",
    "sg:city":"Atlanta",
    "sg:classifiers":[
        {
            "category":"Building & Trades",
            "subcategory":"Locksmith",
            "type":"Services"
        }
    ],
    "sg:phone":"+1 404 492 9037",
    "sg:postcode":"30324",
    "sg:province":"GA",
    "sg:tags":[
        "key"
    ],
    "wof:name":"24 7 Emergency Locksmith",
    "wof:placetype":"venue"
},
  "geometry": {"coordinates":[-84.368281,33.793173],"type":"Point"}
}