{
  "type": "Feature",
  "properties": {
    "addr:full":"2754 Camille Dr Columbus GA 31906",
    "addr:housenumber":"2754",
    "addr:postcode":"31906",
    "addr:street":"Camille Dr",
    "iso:country":"US",
    "sg:address":"2754 Camille Dr",
    "sg:city":"Columbus",
    "sg:classifiers":[
        {
            "category":"Professional",
            "type":"Services"
        }
    ],
    "sg:phone":"+1 706 576 5619",
    "sg:postcode":"31906",
    "sg:province":"GA",
    "wof:name":"McCormick Inman Co Inc",
    "wof:placetype":"venue"
},
  "geometry": {"coordinates":[-84.949766,32.496435],"type":"Point"}
}