{
  "type": "Feature",
  "properties": {
    "addr:full":"3630 Old Milton Pkwy Alpharetta GA 30005",
    "addr:housenumber":"3630",
    "addr:postcode":"30005",
    "addr:street":"Old Milton Pkwy",
    "iso:country":"US",
    "sg:address":"3630 Old Milton Pkwy",
    "sg:city":"Alpharetta",
    "sg:classifiers":[
        {
            "category":"Retail",
            "subcategory":"Pet Boarding",
            "type":"Services"
        }
    ],
    "sg:phone":"+1 770 619 3988",
    "sg:postcode":"30005",
    "sg:province":"GA",
    "sg:tags":[
        "boarding/pet",
        "sitting"
    ],
    "sg:website":"www.mansbestfriend.com",
    "wof:name":"Mans Best Friend",
    "wof:placetype":"venue"
},
  "geometry": {"coordinates":[-84.25439900000001,34.065307],"type":"Point"}
}