{
  "type": "Feature",
  "properties": {
    "iso:country":"US",
    "sg:address":"3149 Bob Cox Rd",
    "sg:city":"Marietta",
    "sg:classifiers":[
        {
            "category":"Building & Trades",
            "subcategory":"Plumbing",
            "type":"Services"
        }
    ],
    "sg:phone":"+1 770 422 9932",
    "sg:postcode":"30064",
    "sg:province":"GA",
    "sg:tags":[
        "contractor"
    ],
    "wof:name":"Haskins Plumbing Co",
    "wof:placetype":"venue"
},
  "geometry": {"coordinates":[-84.64227,33.956472],"type":"Point"}
}