{
  "type": "Feature",
  "properties": {
    "addr:full":"220 S Zetterower Ave Statesboro GA 30458",
    "addr:housenumber":"220",
    "addr:postcode":"30458",
    "addr:street":"S Zetterower Ave",
    "iso:country":"US",
    "sg:address":"220 S Zetterower Ave",
    "sg:city":"Statesboro",
    "sg:classifiers":[
        {
            "category":"Professional",
            "subcategory":"Lawyer & Legal Services",
            "type":"Services"
        }
    ],
    "sg:phone":"+1 912 764 7000",
    "sg:postcode":"30458",
    "sg:province":"GA",
    "sg:tags":[
        "attorney"
    ],
    "wof:name":"Claeys Mc Elroy-Magruder",
    "wof:placetype":"venue"
},
  "geometry": {"coordinates":[-81.779206,32.442497],"type":"Point"}
}