{
  "type": "Feature",
  "properties": {
    "addr:full":"5 Glenda Trce Newnan GA 30265",
    "addr:housenumber":"5",
    "addr:postcode":"30265",
    "addr:street":"Glenda Trce",
    "iso:country":"US",
    "sg:address":"5 Glenda Trce",
    "sg:city":"Newnan",
    "sg:classifiers":[
        {
            "category":"Restaurant",
            "type":"Food & Drink"
        }
    ],
    "sg:phone":"+1 770 254 9861",
    "sg:postcode":"30265",
    "sg:province":"GA",
    "wof:name":"Chick-Fil-A",
    "wof:placetype":"venue"
},
  "geometry": {"coordinates":[-84.689301,33.471001],"type":"Point"}
}