{
  "type": "Feature",
  "properties": {
    "addr:full":"6237 Woodlake Dr Buford GA 30518",
    "addr:housenumber":"6237",
    "addr:postcode":"30518",
    "addr:street":"Woodlake Dr",
    "iso:country":"US",
    "sg:address":"6237 Woodlake Dr",
    "sg:city":"Buford",
    "sg:classifiers":[
        {
            "category":"Wholesale",
            "subcategory":"Hardware",
            "type":"Manufacturing & Wholesale Goods"
        }
    ],
    "sg:phone":"+1 770 945 9375",
    "sg:postcode":"30518",
    "sg:province":"GA",
    "sg:tags":[
        "machine",
        "making",
        "ice",
        "equipment"
    ],
    "wof:name":"Ice Systems Intl",
    "wof:placetype":"venue"
},
  "geometry": {"coordinates":[-84.028415,34.152698],"type":"Point"}
}