{
  "type": "Feature",
  "properties": {
    "iso:country":"US",
    "sg:address":"4640 Hemlock Dr",
    "sg:city":"Austell",
    "sg:classifiers":[
        {
            "category":"Communications",
            "subcategory":"Television Station",
            "type":"Services"
        }
    ],
    "sg:phone":"+1 404 322 5850",
    "sg:postcode":"30106",
    "sg:province":"GA",
    "sg:tags":[
        "repair",
        "satellite",
        "cable",
        "tv",
        "system",
        "equipment"
    ],
    "wof:name":"Digital Solutions",
    "wof:placetype":"venue"
},
  "geometry": {"coordinates":[-84.616096,33.840462],"type":"Point"}
}