{
  "type": "Feature",
  "properties": {
    "iso:country":"US",
    "sg:address":"3226 Browns Mill Rd SE",
    "sg:city":"Atlanta",
    "sg:classifiers":[
        {
            "category":"Professional",
            "subcategory":"Business Services",
            "type":"Services"
        }
    ],
    "sg:phone":"+1 478 279 0296",
    "sg:postcode":"30354",
    "sg:province":"GA",
    "sg:tags":[
        "management"
    ],
    "wof:name":"All About Business",
    "wof:placetype":"venue"
},
  "geometry": {"coordinates":[-84.379822,33.668129],"type":"Point"}
}