{
  "type": "Feature",
  "properties": {
    "addr:full":"2 W Bay St Savannah GA 31401",
    "addr:housenumber":"2",
    "addr:postcode":"31401",
    "addr:street":"W Bay St",
    "iso:country":"US",
    "sg:address":"2 W Bay St",
    "sg:city":"Savannah",
    "sg:classifiers":[
        {
            "category":"Bars & Pubs",
            "subcategory":"Lounge",
            "type":"Food & Drink"
        }
    ],
    "sg:phone":"+1 912 238 1234",
    "sg:postcode":"31401",
    "sg:province":"GA",
    "sg:tags":[
        "cocktail"
    ],
    "wof:name":"Vu Lounge",
    "wof:placetype":"venue"
},
  "geometry": {"coordinates":[-81.09123200000001,32.080921],"type":"Point"}
}