{
  "type": "Feature",
  "properties": {
    "iso:country":"US",
    "sg:address":"6822 Cowan Mill Rd",
    "sg:city":"Winston",
    "sg:classifiers":[
        {
            "category":"Building & Trades",
            "subcategory":"Electrical",
            "type":"Services"
        }
    ],
    "sg:phone":"+1 770 949 5253",
    "sg:postcode":"30187",
    "sg:province":"GA",
    "sg:tags":[
        "electrical",
        "contractor"
    ],
    "wof:name":"Dennis Wynn Services",
    "wof:placetype":"venue"
},
  "geometry": {"coordinates":[-84.811688,33.706237],"type":"Point"}
}