{
  "type": "Feature",
  "properties": {
    "addr:full":"3939 Old Flowery Branch Rd Oakwood GA 30566",
    "addr:housenumber":"3939",
    "addr:postcode":"30566",
    "addr:street":"Old Flowery Branch Rd",
    "iso:country":"US",
    "sg:address":"3939 Old Flowery Branch Rd",
    "sg:city":"Oakwood",
    "sg:classifiers":[
        {
            "category":"Professional",
            "subcategory":"Engineering",
            "type":"Services"
        }
    ],
    "sg:phone":"+1 770 297 0075",
    "sg:postcode":"30566",
    "sg:province":"GA",
    "sg:tags":[
        "engineer"
    ],
    "wof:name":"Bowman Engineering Inc",
    "wof:placetype":"venue"
},
  "geometry": {"coordinates":[-83.88893299999999,34.251149],"type":"Point"}
}