{
  "type": "Feature",
  "properties": {
    "iso:country":"US",
    "sg:address":"1248 Reynolds St",
    "sg:city":"Augusta",
    "sg:classifiers":[
        {
            "category":"Organizations",
            "subcategory":"Labor Organization",
            "type":"Services"
        }
    ],
    "sg:phone":"+1 706 722 4100",
    "sg:postcode":"30901",
    "sg:province":"GA",
    "wof:name":"CSRA Elec Joint Aprntcshp",
    "wof:placetype":"venue"
},
  "geometry": {"coordinates":[-81.973591,33.479613],"type":"Point"}
}