{
  "type": "Feature",
  "properties": {
    "addr:full":"5610 Tyson Dr Acworth GA 30102",
    "addr:housenumber":"5610",
    "addr:postcode":"30102",
    "addr:street":"Tyson Dr",
    "iso:country":"US",
    "sg:address":"5610 Tyson Dr",
    "sg:city":"Acworth",
    "sg:classifiers":[
        {
            "category":"Bus Charters",
            "type":"Transportation"
        }
    ],
    "sg:phone":"+1 770 926 4292",
    "sg:postcode":"30102",
    "sg:province":"GA",
    "sg:tags":[
        "buses-charter",
        "rental"
    ],
    "wof:name":"Merwin's Coach Service",
    "wof:placetype":"venue"
},
  "geometry": {"coordinates":[-84.587596,34.089308],"type":"Point"}
}