{
  "type": "Feature",
  "properties": {
    "addr:full":"103 Old Mill Rd Summerville GA 30731",
    "addr:housenumber":"103",
    "addr:postcode":"30731",
    "addr:street":"Old Mill Rd",
    "iso:country":"US",
    "sg:address":"103 Old Mill Rd",
    "sg:city":"Summerville",
    "sg:classifiers":[
        {
            "category":"Autos & Motor Vehicles",
            "subcategory":"Auto Supplies",
            "type":"Retail Goods"
        }
    ],
    "sg:phone":"+1 706 857 3408",
    "sg:postcode":"30731",
    "sg:province":"GA",
    "wof:name":"B& W Garage",
    "wof:placetype":"venue"
},
  "geometry": {"coordinates":[-85.44839899999999,34.561462],"type":"Point"}
}