{
  "type": "Feature",
  "properties": {
    "addr:full":"4925 Settingdown Rd Cumming GA 30041",
    "addr:housenumber":"4925",
    "addr:postcode":"30041",
    "addr:street":"Settingdown Rd",
    "iso:country":"US",
    "sg:address":"4925 Settingdown Rd",
    "sg:city":"Cumming",
    "sg:classifiers":[
        {
            "category":"Retail",
            "subcategory":"Repair Shop",
            "type":"Services"
        }
    ],
    "sg:phone":"+1 770 781 3817",
    "sg:postcode":"30041",
    "sg:province":"GA",
    "wof:name":"Modern Tech Service Inc",
    "wof:placetype":"venue"
},
  "geometry": {"coordinates":[-84.067497,34.297526],"type":"Point"}
}