{
  "type": "Feature",
  "properties": {
    "addr:full":"5183 Maggie Dr SW Stone Mountain GA 30087",
    "addr:housenumber":"5183",
    "addr:postcode":"30087",
    "addr:street":"Maggie Dr Sw",
    "iso:country":"US",
    "sg:address":"5183 Maggie Dr SW",
    "sg:city":"Stone Mountain",
    "sg:classifiers":[
        {
            "category":"Professional",
            "subcategory":"Computer Services",
            "type":"Services"
        }
    ],
    "sg:phone":"+1 404 849 9979",
    "sg:postcode":"30087",
    "sg:province":"GA",
    "sg:tags":[
        "consultant"
    ],
    "wof:name":"Global Data Solutions LLC",
    "wof:placetype":"venue"
},
  "geometry": {"coordinates":[-84.102391,33.818829],"type":"Point"}
}