{
  "type": "Feature",
  "properties": {
    "iso:country":"US",
    "sg:address":"204 Memorial Dr",
    "sg:city":"Hinesville",
    "sg:classifiers":[
        {
            "category":"Wholesale",
            "subcategory":"Auto Parts",
            "type":"Manufacturing & Wholesale Goods"
        }
    ],
    "sg:phone":"+1 912 368 3311",
    "sg:postcode":"31313",
    "sg:province":"GA",
    "sg:tags":[
        "supply"
    ],
    "wof:name":"NAPA Auto Parts",
    "wof:placetype":"venue"
},
  "geometry": {"coordinates":[-81.60015300000001,31.851603],"type":"Point"}
}