{
  "type": "Feature",
  "properties": {
    "iso:country":"US",
    "sg:address":"4300 Chapel Ct",
    "sg:city":"Douglasville",
    "sg:classifiers":[
        {
            "category":"Social Services",
            "subcategory":"Child Care",
            "type":"Services"
        }
    ],
    "sg:phone":"+1 770 920 5600",
    "sg:postcode":"30135",
    "sg:province":"GA",
    "wof:name":"Kids R Kids #40",
    "wof:placetype":"venue"
},
  "geometry": {"coordinates":[-84.727521,33.723749],"type":"Point"}
}