{
  "type": "Feature",
  "properties": {
    "addr:full":"3663 Mahan Rd Summerville GA 30747",
    "addr:housenumber":"3663",
    "addr:postcode":"30747",
    "addr:street":"Mahan Rd",
    "iso:country":"US",
    "sg:address":"3663 Mahan Rd",
    "sg:city":"Summerville",
    "sg:classifiers":[
        {
            "category":"Personal",
            "subcategory":"Beauty Salon",
            "type":"Services"
        }
    ],
    "sg:phone":"+1 706 857 4946",
    "sg:postcode":"30747",
    "sg:province":"GA",
    "wof:name":"Nancys Beauty Shop",
    "wof:placetype":"venue"
},
  "geometry": {"coordinates":[-85.366444,34.51724],"type":"Point"}
}