{
  "type": "Feature",
  "properties": {
    "iso:country":"US",
    "sg:address":"845 Laurel Mill Dr",
    "sg:city":"Roswell",
    "sg:classifiers":[
        {
            "category":"Real Estate",
            "subcategory":"Real Estate Agent",
            "type":"Services"
        }
    ],
    "sg:phone":"+1 770 643 7803",
    "sg:postcode":"30076",
    "sg:province":"GA",
    "wof:name":"Scott & Sonia Jensen Condo",
    "wof:placetype":"venue"
},
  "geometry": {"coordinates":[-84.29338199999999,34.027914],"type":"Point"}
}