{
  "type": "Feature",
  "properties": {
    "addr:full":"719 Dozier Dr Marietta GA 30066",
    "addr:housenumber":"719",
    "addr:postcode":"30066",
    "addr:street":"Dozier Dr",
    "iso:country":"US",
    "sg:address":"719 Dozier Dr",
    "sg:city":"Marietta",
    "sg:classifiers":[
        {
            "category":"Building & Trades",
            "subcategory":"Construction",
            "type":"Services"
        }
    ],
    "sg:phone":"+1 404 510 8008",
    "sg:postcode":"30066",
    "sg:province":"GA",
    "sg:tags":[
        "painter"
    ],
    "wof:name":"Jp's Painting Group Inc",
    "wof:placetype":"venue"
},
  "geometry": {"coordinates":[-84.530682,34.017056],"type":"Point"}
}