{
  "type": "Feature",
  "properties": {
    "iso:country":"US",
    "sg:address":"305 S Baker St",
    "sg:city":"Alma",
    "sg:classifiers":[
        {
            "category":"Social Services",
            "subcategory":"Child Care",
            "type":"Services"
        }
    ],
    "sg:phone":"+1 912 632 0130",
    "sg:postcode":"31510",
    "sg:province":"GA",
    "wof:name":"ABC Child Development Ctr",
    "wof:placetype":"venue"
},
  "geometry": {"coordinates":[-82.456502,31.539542],"type":"Point"}
}