{
  "type": "Feature",
  "properties": {
    "addr:full":"6897 Atomic Rd Aiken SC 29803",
    "addr:housenumber":"6897",
    "addr:postcode":"29803",
    "addr:street":"Atomic Rd",
    "iso:country":"US",
    "sg:address":"6897 Atomic Rd",
    "sg:city":"Aiken",
    "sg:classifiers":[
        {
            "category":"Building & Trades",
            "subcategory":"Construction",
            "type":"Services"
        }
    ],
    "sg:phone":"+1 803 827 1699",
    "sg:postcode":"29803",
    "sg:province":"SC",
    "sg:tags":[
        "hanging",
        "contractor"
    ],
    "wof:name":"Hendrix Painting Contractor",
    "wof:placetype":"venue"
},
  "geometry": {"coordinates":[-81.819486,33.369121],"type":"Point"}
}