{
  "type": "Feature",
  "properties": {
    "iso:country":"US",
    "sg:address":"1674 Washington Ave",
    "sg:city":"Atlanta",
    "sg:classifiers":[
        {
            "category":"Retail",
            "subcategory":"Repair Shop",
            "type":"Services"
        }
    ],
    "sg:phone":"+1 404 601 0399",
    "sg:postcode":"30344",
    "sg:province":"GA",
    "wof:name":"24 Hour Emergency Locksmith",
    "wof:placetype":"venue"
},
  "geometry": {"coordinates":[-84.444282,33.675478],"type":"Point"}
}