{
  "type": "Feature",
  "properties": {
    "iso:country":"US",
    "sg:address":"6333 State Hwy 42",
    "sg:city":"Rex",
    "sg:classifiers":[
        {
            "category":"Restaurant",
            "type":"Food & Drink"
        }
    ],
    "sg:phone":"+1 770 968 9196",
    "sg:postcode":"30273",
    "sg:province":"GA",
    "sg:tags":[
        "barbecue"
    ],
    "wof:name":"B & W Bbq",
    "wof:placetype":"venue"
},
  "geometry": {"coordinates":[-84.29115899999999,33.58149],"type":"Point"}
}