{
  "type": "Feature",
  "properties": {
    "addr:full":"2835 Garretts Chapel Rd Chickamauga GA 30707",
    "addr:housenumber":"2835",
    "addr:postcode":"30707",
    "addr:street":"Garretts Chapel Rd",
    "iso:country":"US",
    "sg:address":"2835 Garretts Chapel Rd",
    "sg:city":"Chickamauga",
    "sg:classifiers":[
        {
            "category":"Building & Trades",
            "subcategory":"Construction",
            "type":"Services"
        }
    ],
    "sg:phone":"+1 706 375 9336",
    "sg:postcode":"30707",
    "sg:province":"GA",
    "sg:tags":[
        "house"
    ],
    "wof:name":"LL Home Builders",
    "wof:placetype":"venue"
},
  "geometry": {"coordinates":[-85.34334200000001,34.859381],"type":"Point"}
}