{
  "type": "Feature",
  "properties": {
    "iso:country":"US",
    "sg:address":"1253 Woolfolk Ter",
    "sg:city":"Macon",
    "sg:classifiers":[
        {
            "category":"Social Services",
            "type":"Services"
        }
    ],
    "sg:phone":"+1 478 755 0080",
    "sg:postcode":"31217",
    "sg:province":"GA",
    "sg:tags":[
        "counseling"
    ],
    "wof:name":"Back To Street Ministries",
    "wof:placetype":"venue"
},
  "geometry": {"coordinates":[-83.603505,32.849576],"type":"Point"}
}