{
  "type": "Feature",
  "properties": {
    "addr:full":"4337 Atlanta Hwy Loganville GA 30052",
    "addr:housenumber":"4337",
    "addr:postcode":"30052",
    "addr:street":"Atlanta Hwy",
    "iso:country":"US",
    "sg:address":"4337 Atlanta Hwy",
    "sg:city":"Loganville",
    "sg:classifiers":[
        {
            "category":"Deli",
            "type":"Food & Drink"
        }
    ],
    "sg:menulink":"http://www.allmenus.com/ga/loganville/127007-blimpie-subs--sandwiches/menu/",
    "sg:phone":"+1 770 554 2440",
    "sg:postcode":"30052",
    "sg:province":"GA",
    "sg:tags":[
        "wrap",
        "american",
        "sandwich"
    ],
    "wof:name":"Blimpie Subs & Sandwiches",
    "wof:placetype":"venue"
},
  "geometry": {"coordinates":[-83.90553800000001,33.83962],"type":"Point"}
}