{
  "type": "Feature",
  "properties": {
    "addr:full":"3348 Cleveland Hwy Gainesville GA 30506",
    "addr:housenumber":"3348",
    "addr:postcode":"30506",
    "addr:street":"Cleveland Hwy",
    "iso:country":"US",
    "sg:address":"3348 Cleveland Hwy",
    "sg:city":"Gainesville",
    "sg:classifiers":[
        {
            "category":"Wholesale",
            "subcategory":"Computers",
            "type":"Manufacturing & Wholesale Goods"
        }
    ],
    "sg:phone":"+1 770 535 7015",
    "sg:postcode":"30506",
    "sg:province":"GA",
    "wof:name":"Mustang Computers and Supplies",
    "wof:placetype":"venue"
},
  "geometry": {"coordinates":[-83.80993100000001,34.377083],"type":"Point"}
}