{
  "type": "Feature",
  "properties": {
    "iso:country":"US",
    "sg:address":"808 N Merrimac Dr",
    "sg:city":"Fitzgerald",
    "sg:classifiers":[
        {
            "category":"Real Estate",
            "subcategory":"Real Estate Operator",
            "type":"Services"
        }
    ],
    "sg:phone":"+1 229 423 2647",
    "sg:postcode":"31750",
    "sg:province":"GA",
    "sg:tags":[
        "building",
        "apartment"
    ],
    "wof:name":"Colony Square Apartments",
    "wof:placetype":"venue"
},
  "geometry": {"coordinates":[-83.265101,31.723639],"type":"Point"}
}