{
  "type": "Feature",
  "properties": {
    "iso:country":"US",
    "sg:address":"629 Airport Rd",
    "sg:city":"Lawrenceville",
    "sg:classifiers":[
        {
            "category":"Building & Trades",
            "subcategory":"Plumbing",
            "type":"Services"
        }
    ],
    "sg:phone":"+1 770 995 4221",
    "sg:postcode":"30045",
    "sg:province":"GA",
    "sg:tags":[
        "tank",
        "septic"
    ],
    "wof:name":"Chapman Septic",
    "wof:placetype":"venue"
},
  "geometry": {"coordinates":[-83.97054300000001,33.980783],"type":"Point"}
}