{
  "type": "Feature",
  "properties": {
    "iso:country":"US",
    "sg:address":"1824 Nebo Rd",
    "sg:city":"Dallas",
    "sg:classifiers":[
        {
            "category":"Building & Trades",
            "subcategory":"Construction",
            "type":"Services"
        }
    ],
    "sg:phone":"+1 770 445 0002",
    "sg:postcode":"30157",
    "sg:province":"GA",
    "sg:tags":[
        "contractor"
    ],
    "wof:name":"Ww Drywall",
    "wof:placetype":"venue"
},
  "geometry": {"coordinates":[-84.852391,33.822452],"type":"Point"}
}