{
  "type": "Feature",
  "properties": {
    "addr:full":"47 Madison St Danielsville GA 30633",
    "addr:housenumber":"47",
    "addr:postcode":"30633",
    "addr:street":"Madison St",
    "iso:country":"US",
    "sg:address":"47 Madison St",
    "sg:city":"Danielsville",
    "sg:classifiers":[
        {
            "category":"Wholesale",
            "subcategory":"Machinery & Supplies",
            "type":"Manufacturing & Wholesale Goods"
        }
    ],
    "sg:phone":"+1 706 795 3361",
    "sg:postcode":"30633",
    "sg:province":"GA",
    "sg:tags":[
        "equipment",
        "establishment",
        "repair"
    ],
    "wof:name":"Madison County Lock & Key",
    "wof:placetype":"venue"
},
  "geometry": {"coordinates":[-83.220877,34.124507],"type":"Point"}
}