{
  "type": "Feature",
  "properties": {
    "iso:country":"US",
    "sg:address":"3450 Breckinridge Blvd",
    "sg:city":"Duluth",
    "sg:classifiers":[
        {
            "category":"Professional",
            "subcategory":"Business Services",
            "type":"Services"
        }
    ],
    "sg:phone":"+1 770 921 5033",
    "sg:postcode":"30096",
    "sg:province":"GA",
    "wof:name":"Interiors By Telanee",
    "wof:placetype":"venue"
},
  "geometry": {"coordinates":[-84.124728,33.951236],"type":"Point"}
}