{
  "type": "Feature",
  "properties": {
    "iso:country":"US",
    "sg:address":"4650 Stonewall Tell Rd",
    "sg:city":"Atlanta",
    "sg:classifiers":[
        {
            "category":"Professional",
            "subcategory":"Lawyer & Legal Services",
            "type":"Services"
        }
    ],
    "sg:phone":"+1 770 969 6126",
    "sg:postcode":"30349",
    "sg:province":"GA",
    "wof:name":"Paralegal Connection LLC",
    "wof:placetype":"venue"
},
  "geometry": {"coordinates":[-84.562504,33.628545],"type":"Point"}
}