{
  "type": "Feature",
  "properties": {
    "addr:full":"1401 Greensboro Hwy Watkinsville GA 30677",
    "addr:housenumber":"1401",
    "addr:postcode":"30677",
    "addr:street":"Greensboro Hwy",
    "iso:country":"US",
    "sg:address":"1401 Greensboro Hwy",
    "sg:city":"Watkinsville",
    "sg:classifiers":[
        {
            "category":"Building & Trades",
            "subcategory":"Construction",
            "type":"Services"
        }
    ],
    "sg:phone":"+1 706 769 9050",
    "sg:postcode":"30677",
    "sg:province":"GA",
    "sg:tags":[
        "resurfacing",
        "floor",
        "laying",
        "refinishing",
        "contractor"
    ],
    "wof:name":"Traditional Hardwood Floors",
    "wof:placetype":"venue"
},
  "geometry": {"coordinates":[-83.397488,33.851761],"type":"Point"}
}