{
  "type": "Feature",
  "properties": {
    "addr:full":"10 W Huntington Rd Athens GA 30606",
    "addr:housenumber":"10",
    "addr:postcode":"30606",
    "addr:street":"W Huntington Rd",
    "iso:country":"US",
    "sg:address":"10 W Huntington Rd",
    "sg:city":"Athens",
    "sg:classifiers":[
        {
            "category":"Restaurant",
            "type":"Food & Drink"
        }
    ],
    "sg:phone":"+1 706 353 9880",
    "sg:postcode":"30606",
    "sg:province":"GA",
    "wof:name":"Wendy's",
    "wof:placetype":"venue"
},
  "geometry": {"coordinates":[-83.464578,33.942077],"type":"Point"}
}