{
  "type": "Feature",
  "properties": {
    "iso:country":"US",
    "sg:address":"188 Wc Bryant Pkwy",
    "sg:city":"Calhoun",
    "sg:classifiers":[
        {
            "category":"Food & Beverages",
            "subcategory":"Groceries & Convenience Stores",
            "type":"Retail Goods"
        }
    ],
    "sg:phone":"+1 706 625 5134",
    "sg:postcode":"30701",
    "sg:province":"GA",
    "wof:name":"Laperla No 2 Hispanic Grocery",
    "wof:placetype":"venue"
},
  "geometry": {"coordinates":[-84.946962,34.481648],"type":"Point"}
}