{
  "type": "Feature",
  "properties": {
    "iso:country":"US",
    "sg:address":"2570 Riverglenn Cir",
    "sg:city":"Atlanta",
    "sg:classifiers":[
        {
            "category":"Conference Center",
            "type":"Public Place"
        }
    ],
    "sg:phone":"+1 770 455 1600",
    "sg:postcode":"30338",
    "sg:province":"GA",
    "sg:tags":[
        "lecture",
        "speakers",
        "seminar"
    ],
    "wof:name":"Global Events Inc",
    "wof:placetype":"venue"
},
  "geometry": {"coordinates":[-84.292327,33.933542],"type":"Point"}
}