{
  "type": "Feature",
  "properties": {
    "addr:full":"1084 C M Chafin Rd Norman Park GA 31771",
    "addr:housenumber":"1084 c m",
    "addr:postcode":"31771",
    "addr:street":"Chafin Rd",
    "iso:country":"US",
    "sg:address":"1084 C M Chafin Rd",
    "sg:city":"Norman Park",
    "sg:classifiers":[
        {
            "category":"Farming",
            "subcategory":"Farm",
            "type":"Manufacturing & Wholesale Goods"
        }
    ],
    "sg:phone":"+1 229 769 3546",
    "sg:postcode":"31771",
    "sg:province":"GA",
    "sg:tags":[
        "crop",
        "general"
    ],
    "wof:name":"G H Holloway Farms Inc",
    "wof:placetype":"venue"
},
  "geometry": {"coordinates":[-83.61386,31.197301],"type":"Point"}
}