{
  "type": "Feature",
  "properties": {
    "iso:country":"US",
    "sg:address":"437 Staley Ave",
    "sg:city":"Savannah",
    "sg:classifiers":[
        {
            "category":"Autos & Motor Vehicles",
            "subcategory":"Auto Supplies",
            "type":"Retail Goods"
        },
        {
            "category":"Retail",
            "subcategory":"Auto Repair",
            "type":"Services"
        }
    ],
    "sg:phone":"+1 912 352 3337",
    "sg:postcode":"31405",
    "sg:province":"GA",
    "sg:tags":[
        "automotive",
        "equipment",
        "brake",
        "transmissions-other",
        "automobile",
        "performance",
        "sport",
        "racing",
        "tune",
        "car"
    ],
    "sg:website":"http://www.jessesautomotive.com",
    "wof:name":"Jesse's Automotive",
    "wof:placetype":"venue"
},
  "geometry": {"coordinates":[-81.114166,32.033682],"type":"Point"}
}