{
  "type": "Feature",
  "properties": {
    "addr:full":"1107 Liberty Expy Albany GA 31705",
    "addr:housenumber":"1107",
    "addr:postcode":"31705",
    "addr:street":"Liberty Expy",
    "iso:country":"US",
    "sg:address":"1107 Liberty Expy",
    "sg:city":"Albany",
    "sg:classifiers":[
        {
            "category":"Organizations",
            "subcategory":"Religious Organization",
            "type":"Services"
        }
    ],
    "sg:phone":"+1 229 436 0044",
    "sg:postcode":"31705",
    "sg:province":"GA",
    "sg:tags":[
        "church"
    ],
    "wof:name":"Southview Christian Academy",
    "wof:placetype":"venue"
},
  "geometry": {"coordinates":[-84.115719,31.528679],"type":"Point"}
}