{
  "type": "Feature",
  "properties": {
    "addr:full":"589 Auburn Ave NE Unit G Atlanta GA 30312",
    "addr:housenumber":"589",
    "addr:postcode":"30312",
    "addr:street":"Auburn Ave Ne Unit G",
    "iso:country":"US",
    "sg:address":"589 Auburn Ave NE Unit G",
    "sg:city":"Atlanta",
    "sg:classifiers":[
        {
            "category":"Professional",
            "subcategory":"Art Services",
            "type":"Services"
        }
    ],
    "sg:phone":"+1 404 589 4642",
    "sg:postcode":"30312",
    "sg:province":"GA",
    "sg:tags":[
        "designer",
        "display",
        "producer"
    ],
    "wof:name":"Republic Of Design",
    "wof:placetype":"venue"
},
  "geometry": {"coordinates":[-84.36814699999999,33.75581],"type":"Point"}
}