{
  "type": "Feature",
  "properties": {
    "addr:full":"216 Robert Willis Rd Cairo GA 39827",
    "addr:housenumber":"216",
    "addr:postcode":"39827",
    "addr:street":"Robert Willis Rd",
    "iso:country":"US",
    "sg:address":"216 Robert Willis Rd",
    "sg:city":"Cairo",
    "sg:classifiers":[
        {
            "category":"Retail",
            "subcategory":"Repair Shop",
            "type":"Services"
        }
    ],
    "sg:phone":"+1 229 377 6638",
    "sg:postcode":"39827",
    "sg:province":"GA",
    "sg:tags":[
        "appliance"
    ],
    "wof:name":"Johnson's Appliance Repair",
    "wof:placetype":"venue"
},
  "geometry": {"coordinates":[-84.174373,30.901873],"type":"Point"}
}