{
  "type": "Feature",
  "properties": {
    "addr:full":"1050 Mill Run Way Marietta GA 30068",
    "addr:housenumber":"1050",
    "addr:postcode":"30068",
    "addr:street":"Mill Run Way",
    "iso:country":"US",
    "sg:address":"1050 Mill Run Way",
    "sg:city":"Marietta",
    "sg:classifiers":[
        {
            "category":"Building & Trades",
            "subcategory":"Locksmith",
            "type":"Services"
        }
    ],
    "sg:phone":"+1 770 308 0032",
    "sg:postcode":"30068",
    "sg:province":"GA",
    "sg:tags":[
        "key"
    ],
    "wof:name":"0 1 24 Hour A Locksmith",
    "wof:placetype":"venue"
},
  "geometry": {"coordinates":[-84.397508,33.976371],"type":"Point"}
}