{
  "type": "Feature",
  "properties": {
    "iso:country":"US",
    "sg:address":"2429 Washington Hwy",
    "sg:city":"Lincolnton",
    "sg:classifiers":[
        {
            "category":"Arts & Performance",
            "subcategory":"Theater",
            "type":"Entertainment"
        }
    ],
    "sg:phone":"+1 706 359 1997",
    "sg:postcode":"30817",
    "sg:province":"GA",
    "sg:tags":[
        "group"
    ],
    "wof:name":"Jeff & Sheri Easter",
    "wof:placetype":"venue"
},
  "geometry": {"coordinates":[-82.50529899999999,33.756475],"type":"Point"}
}