{
  "type": "Feature",
  "properties": {
    "addr:full":"14045 Abercorn St Exn Savannah GA 31419",
    "addr:housenumber":"14045",
    "addr:postcode":"31419",
    "addr:street":"Abercorn St Exn",
    "iso:country":"US",
    "sg:address":"14045 Abercorn St Exn",
    "sg:city":"Savannah",
    "sg:classifiers":[
        {
            "category":"Shopping",
            "subcategory":"Shoes",
            "type":"Retail Goods"
        }
    ],
    "sg:phone":"+1 912 925 4183",
    "sg:postcode":"31419",
    "sg:province":"GA",
    "sg:tags":[
        "shoe",
        "store"
    ],
    "wof:name":"Payless Shoe Source",
    "wof:placetype":"venue"
},
  "geometry": {"coordinates":[-81.169061,31.980932],"type":"Point"}
}