{
  "type": "Feature",
  "properties": {
    "addr:full":"9150 Horseshoe Bend Gainesville GA 30506",
    "addr:housenumber":"9150",
    "addr:postcode":"30506",
    "addr:street":"Horseshoe Bend",
    "iso:country":"US",
    "sg:address":"9150 Horseshoe Bend",
    "sg:city":"Gainesville",
    "sg:classifiers":[
        {
            "category":"Insurance",
            "subcategory":"Insurance Agent",
            "type":"Services"
        }
    ],
    "sg:phone":"+1 770 889 0827",
    "sg:postcode":"30506",
    "sg:province":"GA",
    "wof:name":"Vedder Brokerage Corp",
    "wof:placetype":"venue"
},
  "geometry": {"coordinates":[-83.983813,34.241992],"type":"Point"}
}