{
  "type": "Feature",
  "properties": {
    "iso:country":"US",
    "sg:address":"1307 Tal Phillips Rd",
    "sg:city":"Nicholson",
    "sg:classifiers":[
        {
            "category":"Professional",
            "type":"Services"
        }
    ],
    "sg:phone":"+1 706 757 8078",
    "sg:postcode":"30565",
    "sg:province":"GA",
    "wof:name":"Doug Makemson Sculpture LLC",
    "wof:placetype":"venue"
},
  "geometry": {"coordinates":[-83.398166,34.121791],"type":"Point"}
}