{
  "type": "Feature",
  "properties": {
    "iso:country":"US",
    "sg:address":"2187 Kearnes Dr",
    "sg:city":"Macon",
    "sg:classifiers":[
        {
            "category":"Shopping",
            "type":"Retail Goods"
        }
    ],
    "sg:phone":"+1 478 788 8130",
    "sg:postcode":"31216",
    "sg:province":"GA",
    "sg:tags":[
        "wedding",
        "supply"
    ],
    "wof:name":"Dave's Carriage Svc",
    "wof:placetype":"venue"
},
  "geometry": {"coordinates":[-83.621065,32.678019],"type":"Point"}
}