{
  "type": "Feature",
  "properties": {
    "addr:full":"101 Berry Rd Sylvester GA 31768",
    "addr:housenumber":"101",
    "addr:postcode":"31768",
    "addr:street":"Berry Rd",
    "iso:country":"US",
    "sg:address":"101 Berry Rd",
    "sg:city":"Sylvester",
    "sg:classifiers":[
        {
            "category":"Government",
            "subcategory":"Fire Station",
            "type":"Public Place"
        }
    ],
    "sg:phone":"+1 229 776 8511",
    "sg:postcode":"31768",
    "sg:province":"GA",
    "sg:tags":[
        "department"
    ],
    "wof:name":"Sylvester Fire Dept",
    "wof:placetype":"venue"
},
  "geometry": {"coordinates":[-83.71289899999999,31.090086],"type":"Point"}
}