{
  "type": "Feature",
  "properties": {
    "addr:full":"2355 Godby Rd College Park GA 30349",
    "addr:housenumber":"2355",
    "addr:postcode":"30349",
    "addr:street":"Godby Rd",
    "iso:country":"US",
    "sg:address":"2355 Godby Rd",
    "sg:city":"College Park",
    "sg:classifiers":[
        {
            "category":"Building & Trades",
            "subcategory":"Locksmith",
            "type":"Services"
        }
    ],
    "sg:phone":"+1 678 271 6437",
    "sg:postcode":"30349",
    "sg:province":"GA",
    "sg:tags":[
        "key"
    ],
    "wof:name":"0000 24 Hour Locksmith",
    "wof:placetype":"venue"
},
  "geometry": {"coordinates":[-84.46515100000001,33.616397],"type":"Point"}
}