{
  "type": "Feature",
  "properties": {
    "addr:full":"1491 Soaring Pointe Marietta GA 30062",
    "addr:housenumber":"1491",
    "addr:postcode":"30062",
    "addr:street":"Soaring Pointe",
    "iso:country":"US",
    "sg:address":"1491 Soaring Pointe",
    "sg:city":"Marietta",
    "sg:classifiers":[
        {
            "category":"Wholesale",
            "subcategory":"Plants",
            "type":"Manufacturing & Wholesale Goods"
        }
    ],
    "sg:phone":"+1 770 792 7345",
    "sg:postcode":"30062",
    "sg:province":"GA",
    "sg:tags":[
        "supply"
    ],
    "wof:name":"Itc Wholesale Trees",
    "wof:placetype":"venue"
},
  "geometry": {"coordinates":[-84.512969,33.972216],"type":"Point"}
}