{
  "type": "Feature",
  "properties": {
    "iso:country":"US",
    "sg:address":"6241 River Shore Pkwy NW",
    "sg:city":"Atlanta",
    "sg:classifiers":[
        {
            "category":"Building & Trades",
            "subcategory":"Locksmith",
            "type":"Services"
        }
    ],
    "sg:phone":"+1 404 965 0101",
    "sg:postcode":"30328",
    "sg:province":"GA",
    "sg:tags":[
        "key"
    ],
    "wof:name":"A Locksmith A 24 7",
    "wof:placetype":"venue"
},
  "geometry": {"coordinates":[-84.39933499999999,33.925339],"type":"Point"}
}