{
  "type": "Feature",
  "properties": {
    "addr:full":"75 Marietta St NW Suite # 101 Atlanta GA 30303",
    "addr:housenumber":"75",
    "addr:postcode":"30303",
    "addr:street":"Marietta St Nw Suite # 101",
    "iso:country":"US",
    "sg:address":"75 Marietta St NW Suite # 101",
    "sg:city":"Atlanta",
    "sg:classifiers":[
        {
            "category":"Coffee & Tea",
            "type":"Food & Drink"
        },
        {
            "category":"Restaurant",
            "type":"Food & Drink"
        }
    ],
    "sg:phone":"+1 404 523 8388",
    "sg:postcode":"30303",
    "sg:province":"GA",
    "sg:tags":[
        "espresso",
        "lunch",
        "brunch",
        "cafeteria",
        "breakfast"
    ],
    "wof:name":"Michael's Cafe",
    "wof:placetype":"venue"
},
  "geometry": {"coordinates":[-84.39146100000001,33.756244],"type":"Point"}
}