{
  "type": "Feature",
  "properties": {
    "iso:country":"US",
    "sg:address":"135 W Hancock St",
    "sg:city":"Decatur",
    "sg:classifiers":[
        {
            "category":"Banks & Credit Unions",
            "subcategory":"Bank",
            "type":"Services"
        }
    ],
    "sg:phone":"+1 404 373 1227",
    "sg:postcode":"30030",
    "sg:province":"GA",
    "sg:tags":[
        "telegraph"
    ],
    "wof:name":"Atlanta Guide",
    "wof:placetype":"venue"
},
  "geometry": {"coordinates":[-84.296986,33.764526],"type":"Point"}
}