{
  "type": "Feature",
  "properties": {
    "iso:country":"US",
    "sg:address":"154 Colwell Church Rd",
    "sg:city":"Epworth",
    "sg:classifiers":[
        {
            "category":"Building & Trades",
            "subcategory":"Construction",
            "type":"Services"
        }
    ],
    "sg:phone":"+1 706 632 4350",
    "sg:postcode":"30513",
    "sg:province":"GA",
    "sg:tags":[
        "warehouse"
    ],
    "wof:name":"G & N Enterprises Inc",
    "wof:placetype":"venue"
},
  "geometry": {"coordinates":[-84.46615199999999,34.900554],"type":"Point"}
}