{
  "type": "Feature",
  "properties": {
    "addr:full":"512 Monck St Brunswick GA 31520",
    "addr:housenumber":"512",
    "addr:postcode":"31520",
    "addr:street":"Monck St",
    "iso:country":"US",
    "sg:address":"512 Monck St",
    "sg:city":"Brunswick",
    "sg:classifiers":[
        {
            "category":"Retail",
            "subcategory":"Laundry & Dry Cleaning",
            "type":"Services"
        }
    ],
    "sg:phone":"+1 912 265 1234",
    "sg:postcode":"31520",
    "sg:province":"GA",
    "wof:name":"Morgan Dry Cleaners",
    "wof:placetype":"venue"
},
  "geometry": {"coordinates":[-81.4937,31.147987],"type":"Point"}
}