{
  "type": "Feature",
  "properties": {
    "iso:country":"US",
    "sg:address":"317 Sunlight Rd",
    "sg:city":"Ellijay",
    "sg:classifiers":[
        {
            "category":"Home & Garden",
            "subcategory":"Garden Supply",
            "type":"Retail Goods"
        }
    ],
    "sg:phone":"+1 706 635 6713",
    "sg:postcode":"30540",
    "sg:province":"GA",
    "sg:tags":[
        "lawn",
        "mower"
    ],
    "wof:name":"Bill's Small Engine Repair",
    "wof:placetype":"venue"
},
  "geometry": {"coordinates":[-84.523977,34.634255],"type":"Point"}
}