{
  "type": "Feature",
  "properties": {
    "addr:full":"937 Morrow Industrial Blvd Morrow GA 30260",
    "addr:housenumber":"937",
    "addr:postcode":"30260",
    "addr:street":"Morrow Industrial Blvd",
    "iso:country":"US",
    "sg:address":"937 Morrow Industrial Blvd",
    "sg:city":"Morrow",
    "sg:classifiers":[
        {
            "category":"Education",
            "subcategory":"School",
            "type":"Public Place"
        }
    ],
    "sg:phone":"+1 770 968 2917",
    "sg:postcode":"30260",
    "sg:province":"GA",
    "sg:tags":[
        "elementary"
    ],
    "wof:name":"Tara Elementary School",
    "wof:placetype":"venue"
},
  "geometry": {"coordinates":[-84.360817,33.572559],"type":"Point"}
}