{
  "type": "Feature",
  "properties": {
    "iso:country":"US",
    "sg:address":"7086 Blairs View Dr",
    "sg:city":"Austell",
    "sg:classifiers":[
        {
            "category":"Shopping",
            "subcategory":"Clothing, Apparel, & Fashions",
            "type":"Retail Goods"
        }
    ],
    "sg:phone":"+1 404 259 1182",
    "sg:postcode":"30168",
    "sg:province":"GA",
    "sg:tags":[
        "shirts-custom",
        "made",
        "alterations-clothing"
    ],
    "wof:name":"Kickboard Kouture",
    "wof:placetype":"venue"
},
  "geometry": {"coordinates":[-84.59201,33.782073],"type":"Point"}
}