{
  "type": "Feature",
  "properties": {
    "iso:country":"US",
    "sg:address":"83 Rio Rd",
    "sg:city":"Savannah",
    "sg:classifiers":[
        {
            "category":"Professional",
            "type":"Services"
        }
    ],
    "sg:phone":"+1 912 925 4805",
    "sg:postcode":"31419",
    "sg:province":"GA",
    "wof:name":"Ann Ward Studio",
    "wof:placetype":"venue"
},
  "geometry": {"coordinates":[-81.186543,31.975275],"type":"Point"}
}