{
  "type": "Feature",
  "properties": {
    "addr:full":"131 Veterans Memoril Hwy Atlanta GA 30303",
    "addr:housenumber":"131",
    "addr:postcode":"30303",
    "addr:street":"Veterans Memoril Hwy",
    "iso:country":"US",
    "sg:address":"131 Veterans Memoril Hwy",
    "sg:city":"Atlanta",
    "sg:classifiers":[
        {
            "category":"Retail",
            "subcategory":"Car Wash",
            "type":"Services"
        }
    ],
    "sg:phone":"+1 770 819 5000",
    "sg:postcode":"30303",
    "sg:province":"GA",
    "wof:name":"A Veteran's Car Wash & Detail",
    "wof:placetype":"venue"
},
  "geometry": {"coordinates":[-84.38897,33.755418],"type":"Point"}
}