{
  "type": "Feature",
  "properties": {
    "addr:full":"4555 Regency Trce SW Atlanta GA 30331",
    "addr:housenumber":"4555",
    "addr:postcode":"30331",
    "addr:street":"Regency Trce Sw",
    "iso:country":"US",
    "sg:address":"4555 Regency Trce SW",
    "sg:city":"Atlanta",
    "sg:classifiers":[
        {
            "category":"Professional",
            "subcategory":"Management & Consulting",
            "type":"Services"
        },
        {
            "category":"Professional",
            "subcategory":"Employment Agencies",
            "type":"Services"
        },
        {
            "category":"Organizations",
            "subcategory":"Community Association",
            "type":"Services"
        }
    ],
    "sg:phone":"+1 404 549 8902",
    "sg:postcode":"30331",
    "sg:province":"GA",
    "sg:tags":[
        "employer"
    ],
    "wof:name":"Hoa Regency",
    "wof:placetype":"venue"
},
  "geometry": {"coordinates":[-84.536903,33.70797],"type":"Point"}
}