{
  "type": "Feature",
  "properties": {
    "addr:full":"154 Oak Cir Pine Mountain GA 31822",
    "addr:housenumber":"154",
    "addr:postcode":"31822",
    "addr:street":"Oak Cir",
    "iso:country":"US",
    "sg:address":"154 Oak Cir",
    "sg:city":"Pine Mountain",
    "sg:classifiers":[
        {
            "category":"Shopping",
            "subcategory":"Used Merchandise",
            "type":"Retail Goods"
        }
    ],
    "sg:phone":"+1 706 663 8795",
    "sg:postcode":"31822",
    "sg:province":"GA",
    "sg:tags":[
        "shop",
        "pawn"
    ],
    "wof:name":"Uptown Drum Shop",
    "wof:placetype":"venue"
},
  "geometry": {"coordinates":[-84.82102500000001,32.847724],"type":"Point"}
}