{
  "type": "Feature",
  "properties": {
    "addr:full":"1305 Dantignac St Augusta GA 30901",
    "addr:housenumber":"1305",
    "addr:postcode":"30901",
    "addr:street":"Dantignac St",
    "iso:country":"US",
    "sg:address":"1305 Dantignac St",
    "sg:city":"Augusta",
    "sg:classifiers":[
        {
            "category":"Health Services",
            "subcategory":"Doctor",
            "type":"Services"
        }
    ],
    "sg:phone":"+1 706 823 3807",
    "sg:postcode":"30901",
    "sg:province":"GA",
    "sg:tags":[
        "physician",
        "surgeon"
    ],
    "wof:name":"Orthopaedic Associates-Augusta",
    "wof:placetype":"venue"
},
  "geometry": {"coordinates":[-81.979513,33.470099],"type":"Point"}
}