{
  "type": "Feature",
  "properties": {
    "addr:full":"405 Alice Ave Albany GA 31701",
    "addr:housenumber":"405",
    "addr:postcode":"31701",
    "addr:street":"Alice Ave",
    "iso:country":"US",
    "sg:address":"405 Alice Ave",
    "sg:city":"Albany",
    "sg:classifiers":[
        {
            "category":"Personal",
            "subcategory":"Beauty Salon",
            "type":"Services"
        }
    ],
    "sg:phone":"+1 229 434 0616",
    "sg:postcode":"31701",
    "sg:province":"GA",
    "sg:tags":[
        "shop"
    ],
    "wof:name":"Styles",
    "wof:placetype":"venue"
},
  "geometry": {"coordinates":[-84.15769400000001,31.558569],"type":"Point"}
}