{
  "type": "Feature",
  "properties": {
    "addr:full":"681 River Ridge Rd Clarkesville GA 30523",
    "addr:housenumber":"681",
    "addr:postcode":"30523",
    "addr:street":"River Ridge Rd",
    "iso:country":"US",
    "sg:address":"681 River Ridge Rd",
    "sg:city":"Clarkesville",
    "sg:classifiers":[
        {
            "category":"Education",
            "subcategory":"Vocational School",
            "type":"Public Place"
        }
    ],
    "sg:phone":"+1 706 754 8900",
    "sg:postcode":"30523",
    "sg:province":"GA",
    "sg:tags":[
        "processing",
        "datum"
    ],
    "wof:name":"Project Management Training",
    "wof:placetype":"venue"
},
  "geometry": {"coordinates":[-83.651833,34.653502],"type":"Point"}
}