{
  "type": "Feature",
  "properties": {
    "iso:country":"US",
    "sg:address":"11 Hartwell St",
    "sg:city":"Royston",
    "sg:classifiers":[
        {
            "category":"Real Estate",
            "subcategory":"Real Estate Agent",
            "type":"Services"
        }
    ],
    "sg:phone":"+1 706 246 9669",
    "sg:postcode":"30662",
    "sg:province":"GA",
    "wof:name":"Assist 2 Sell",
    "wof:placetype":"venue"
},
  "geometry": {"coordinates":[-83.11018199999999,34.287022],"type":"Point"}
}