{
  "type": "Feature",
  "properties": {
    "iso:country":"US",
    "sg:address":"6329 Woodlake Dr",
    "sg:city":"Buford",
    "sg:classifiers":[
        {
            "category":"Manufacturing",
            "subcategory":"Electronics",
            "type":"Manufacturing & Wholesale Goods"
        }
    ],
    "sg:phone":"+1 770 993 6000",
    "sg:postcode":"30518",
    "sg:province":"GA",
    "sg:tags":[
        "fire",
        "protection",
        "system",
        "mfg"
    ],
    "wof:name":"Safehome Industries Inc",
    "wof:placetype":"venue"
},
  "geometry": {"coordinates":[-84.025571,34.156668],"type":"Point"}
}