{
  "type": "Feature",
  "properties": {
    "addr:full":"3951 Snapfinger Pkwy Decatur GA 30035",
    "addr:housenumber":"3951",
    "addr:postcode":"30035",
    "addr:street":"Snapfinger Pkwy",
    "iso:country":"US",
    "sg:address":"3951 Snapfinger Pkwy",
    "sg:city":"Decatur",
    "sg:classifiers":[
        {
            "category":"Banks & Credit Unions",
            "subcategory":"Bank",
            "type":"Services"
        }
    ],
    "sg:phone":"+1 404 289 1100",
    "sg:postcode":"30035",
    "sg:province":"GA",
    "wof:name":"Omega Psi Phi Fraternity Federal Credit Union",
    "wof:placetype":"venue"
},
  "geometry": {"coordinates":[-84.22820299999999,33.714401],"type":"Point"}
}