{
  "type": "Feature",
  "properties": {
    "addr:full":"3560 Browns Bridge Rd Cumming GA 30028",
    "addr:housenumber":"3560",
    "addr:postcode":"30028",
    "addr:street":"Browns Bridge Rd",
    "iso:country":"US",
    "sg:address":"3560 Browns Bridge Rd",
    "sg:city":"Cumming",
    "sg:classifiers":[
        {
            "category":"Personal",
            "subcategory":"Nail Salon",
            "type":"Services"
        }
    ],
    "sg:phone":"+1 678 341 8023",
    "sg:postcode":"30028",
    "sg:province":"GA",
    "wof:name":"Elegant Nails",
    "wof:placetype":"venue"
},
  "geometry": {"coordinates":[-84.094545,34.269273],"type":"Point"}
}