{
  "type": "Feature",
  "properties": {
    "iso:country":"US",
    "sg:address":"10252 US Hwy 341",
    "sg:city":"Fort Valley",
    "sg:classifiers":[
        {
            "category":"Wholesale",
            "subcategory":"Farm Supplies",
            "type":"Manufacturing & Wholesale Goods"
        }
    ],
    "sg:phone":"+1 478 825 2010",
    "sg:postcode":"31030",
    "sg:province":"GA",
    "sg:tags":[
        "fertilizer"
    ],
    "wof:name":"Houston Fertilizer & Grain Co",
    "wof:placetype":"venue"
},
  "geometry": {"coordinates":[-83.809219,32.485323],"type":"Point"}
}