{
  "type": "Feature",
  "properties": {
    "iso:country":"US",
    "sg:address":"3205 Underwood Rd SE",
    "sg:city":"Conyers",
    "sg:classifiers":[
        {
            "category":"Education",
            "subcategory":"School",
            "type":"Public Place"
        }
    ],
    "sg:phone":"+1 770 922 0139",
    "sg:postcode":"30013",
    "sg:province":"GA",
    "sg:tags":[
        "high",
        "middle",
        "elementary"
    ],
    "wof:name":"Rockdale County Public Schools",
    "wof:placetype":"venue"
},
  "geometry": {"coordinates":[-83.987656,33.603696],"type":"Point"}
}