{
  "type": "Feature",
  "properties": {
    "addr:full":"6630 Callanwalde Ct Suwanee GA 30024",
    "addr:housenumber":"6630",
    "addr:postcode":"30024",
    "addr:street":"Callanwalde Ct",
    "iso:country":"US",
    "sg:address":"6630 Callanwalde Ct",
    "sg:city":"Suwanee",
    "sg:classifiers":[
        {
            "category":"Professional",
            "type":"Services"
        }
    ],
    "sg:phone":"+1 770 889 6001",
    "sg:postcode":"30024",
    "sg:province":"GA",
    "wof:name":"Marketplace Parkway LLC",
    "wof:placetype":"venue"
},
  "geometry": {"coordinates":[-84.117717,34.090013],"type":"Point"}
}