{
  "type": "Feature",
  "properties": {
    "addr:full":"610 Pineland Pl Macon GA 31220",
    "addr:housenumber":"610",
    "addr:postcode":"31220",
    "addr:street":"Pineland Pl",
    "iso:country":"US",
    "sg:address":"610 Pineland Pl",
    "sg:city":"Macon",
    "sg:classifiers":[
        {
            "category":"Banks & Credit Unions",
            "subcategory":"Bank",
            "type":"Services"
        }
    ],
    "sg:phone":"+1 478 405 2663",
    "sg:postcode":"31220",
    "sg:province":"GA",
    "sg:tags":[
        "lending",
        "mortgage"
    ],
    "wof:name":"Approved Home Lending",
    "wof:placetype":"venue"
},
  "geometry": {"coordinates":[-83.802633,32.887476],"type":"Point"}
}