{
  "type": "Feature",
  "properties": {
    "addr:full":"620 Bankhead Hwy Carrollton GA 30117",
    "addr:housenumber":"620",
    "addr:postcode":"30117",
    "addr:street":"Bankhead Hwy",
    "iso:country":"US",
    "sg:address":"620 Bankhead Hwy",
    "sg:city":"Carrollton",
    "sg:classifiers":[
        {
            "category":"Shopping",
            "subcategory":"Pharmacy",
            "type":"Retail Goods"
        }
    ],
    "sg:phone":"+1 770 832 1186",
    "sg:postcode":"30117",
    "sg:province":"GA",
    "wof:name":"Kmart Pharmacies Inc",
    "wof:placetype":"venue"
},
  "geometry": {"coordinates":[-85.055435,33.587841],"type":"Point"}
}