{
  "type": "Feature",
  "properties": {
    "iso:country":"US",
    "sg:address":"7374 Wood Hollow Way",
    "sg:city":"Stone Mountain",
    "sg:classifiers":[
        {
            "category":"Building & Trades",
            "subcategory":"Cleaning & Sanitation",
            "type":"Services"
        }
    ],
    "sg:phone":"+1 770 469 1177",
    "sg:postcode":"30087",
    "sg:province":"GA",
    "sg:tags":[
        "maintenance"
    ],
    "wof:name":"Ross Professional Bldg Svcs",
    "wof:placetype":"venue"
},
  "geometry": {"coordinates":[-84.087446,33.786428],"type":"Point"}
}