{
  "type": "Feature",
  "properties": {
    "addr:full":"3097 Hudson Way Decatur GA 30033",
    "addr:housenumber":"3097",
    "addr:postcode":"30033",
    "addr:street":"Hudson Way",
    "iso:country":"US",
    "sg:address":"3097 Hudson Way",
    "sg:city":"Decatur",
    "sg:classifiers":[
        {
            "category":"Professional",
            "subcategory":"Business Services",
            "type":"Services"
        }
    ],
    "sg:phone":"+1 404 982 0344",
    "sg:postcode":"30033",
    "sg:province":"GA",
    "sg:tags":[
        "interior",
        "decorating"
    ],
    "wof:name":"Ecclectique",
    "wof:placetype":"venue"
},
  "geometry": {"coordinates":[-84.262472,33.842628],"type":"Point"}
}