{
  "type": "Feature",
  "properties": {
    "addr:full":"2810 Bee Rd Savannah GA 31404",
    "addr:housenumber":"2810",
    "addr:postcode":"31404",
    "addr:street":"Bee Rd",
    "iso:country":"US",
    "sg:address":"2810 Bee Rd",
    "sg:city":"Savannah",
    "sg:classifiers":[
        {
            "category":"Food & Beverages",
            "subcategory":"Liquor & Beverages",
            "type":"Retail Goods"
        }
    ],
    "sg:phone":"+1 912 355 9588",
    "sg:postcode":"31404",
    "sg:province":"GA",
    "sg:tags":[
        "alcoholic"
    ],
    "wof:name":"Fine Things Boutique",
    "wof:placetype":"venue"
},
  "geometry": {"coordinates":[-81.07669799999999,32.045434],"type":"Point"}
}