{
  "type": "Feature",
  "properties": {
    "addr:full":"105 Horizon Dr Suwanee GA 30024",
    "addr:housenumber":"105",
    "addr:postcode":"30024",
    "addr:street":"Horizon Dr",
    "iso:country":"US",
    "sg:address":"105 Horizon Dr",
    "sg:city":"Suwanee",
    "sg:classifiers":[
        {
            "category":"Restaurant",
            "type":"Food & Drink"
        }
    ],
    "sg:phone":"+1 770 614 8545",
    "sg:postcode":"30024",
    "sg:province":"GA",
    "sg:tags":[
        "drinking",
        "eating"
    ],
    "wof:name":"Jeffreys Sports Bar and Grill",
    "wof:placetype":"venue"
},
  "geometry": {"coordinates":[-84.034319,34.032565],"type":"Point"}
}