{
  "type": "Feature",
  "properties": {
    "addr:full":"4343 Shallowford Rd Marietta GA 30062",
    "addr:housenumber":"4343",
    "addr:postcode":"30062",
    "addr:street":"Shallowford Rd",
    "iso:country":"US",
    "sg:address":"4343 Shallowford Rd",
    "sg:city":"Marietta",
    "sg:classifiers":[
        {
            "category":"Professional",
            "subcategory":"Business Services",
            "type":"Services"
        }
    ],
    "sg:phone":"+1 770 587 6963",
    "sg:postcode":"30062",
    "sg:province":"GA",
    "wof:name":"Metamorphosis Medical Group",
    "wof:placetype":"venue"
},
  "geometry": {"coordinates":[-84.42451800000001,34.02742],"type":"Point"}
}