{
  "type": "Feature",
  "properties": {
    "addr:full":"3109 Glen Wallace Dr Cumming GA 30040",
    "addr:housenumber":"3109",
    "addr:postcode":"30040",
    "addr:street":"Glen Wallace Dr",
    "iso:country":"US",
    "sg:address":"3109 Glen Wallace Dr",
    "sg:city":"Cumming",
    "sg:classifiers":[
        {
            "category":"Shopping",
            "subcategory":"Bicycles & Sporting Goods",
            "type":"Retail Goods"
        },
        {
            "category":"Retail",
            "subcategory":"Auto Repair",
            "type":"Services"
        }
    ],
    "sg:phone":"+1 770 844 1229",
    "sg:postcode":"30040",
    "sg:province":"GA",
    "sg:tags":[
        "machine",
        "automobile",
        "shop"
    ],
    "wof:name":"Reed Speed & Sports",
    "wof:placetype":"venue"
},
  "geometry": {"coordinates":[-84.185743,34.16641],"type":"Point"}
}