{
  "type": "Feature",
  "properties": {
    "iso:country":"US",
    "sg:address":"2881 Amwiler Rd",
    "sg:city":"Atlanta",
    "sg:classifiers":[
        {
            "category":"Wholesale",
            "subcategory":"Electrical",
            "type":"Manufacturing & Wholesale Goods"
        },
        {
            "category":"Shopping",
            "subcategory":"Computers & Home Electronics",
            "type":"Retail Goods"
        }
    ],
    "sg:phone":"+1 770 246 8420",
    "sg:postcode":"30360",
    "sg:province":"GA",
    "sg:tags":[
        "equipment",
        "consumer",
        "electric",
        "supply"
    ],
    "wof:name":"All Things Electronic",
    "wof:placetype":"venue"
},
  "geometry": {"coordinates":[-84.257024,33.925833],"type":"Point"}
}