{
  "type": "Feature",
  "properties": {
    "addr:full":"480 Evans St Homer GA 30547",
    "addr:housenumber":"480",
    "addr:postcode":"30547",
    "addr:street":"Evans St",
    "iso:country":"US",
    "sg:address":"480 Evans St",
    "sg:city":"Homer",
    "sg:classifiers":[
        {
            "category":"Shopping",
            "subcategory":"Department Store",
            "type":"Retail Goods"
        },
        {
            "category":"Shopping",
            "subcategory":"Discount & Variety Stores",
            "type":"Retail Goods"
        },
        {
            "category":"Shopping",
            "type":"Retail Goods"
        },
        {
            "category":"Food & Beverages",
            "subcategory":"Groceries & Convenience Stores",
            "type":"Retail Goods"
        }
    ],
    "sg:phone":"+1 706 677 1546",
    "sg:postcode":"30547",
    "sg:province":"GA",
    "sg:tags":[
        "merchandise"
    ],
    "sg:website":"http://www.dollargeneral.com",
    "wof:name":"Dollar General",
    "wof:placetype":"venue"
},
  "geometry": {"coordinates":[-83.50077,34.322816],"type":"Point"}
}