{
  "type": "Feature",
  "properties": {
    "addr:full":"5440 Union Hill Rd Canton GA 30115",
    "addr:housenumber":"5440",
    "addr:postcode":"30115",
    "addr:street":"Union Hill Rd",
    "iso:country":"US",
    "sg:address":"5440 Union Hill Rd",
    "sg:city":"Canton",
    "sg:classifiers":[
        {
            "category":"Building & Trades",
            "subcategory":"Landscaping Services",
            "type":"Services"
        }
    ],
    "sg:phone":"+1 770 425 1408",
    "sg:postcode":"30115",
    "sg:province":"GA",
    "sg:tags":[
        "tree"
    ],
    "wof:name":"Krussell's Tree Service Inc",
    "wof:placetype":"venue"
},
  "geometry": {"coordinates":[-84.36909300000001,34.199203],"type":"Point"}
}