{
  "type": "Feature",
  "properties": {
    "iso:country":"US",
    "sg:address":"385 Clem Lowell Rd",
    "sg:city":"Carrollton",
    "sg:classifiers":[
        {
            "category":"Wholesale",
            "subcategory":"Durable Goods & Equipment",
            "type":"Manufacturing & Wholesale Goods"
        }
    ],
    "sg:phone":"+1 770 834 3311",
    "sg:postcode":"30116",
    "sg:province":"GA",
    "sg:tags":[
        "pulpwood"
    ],
    "wof:name":"Carroll Cnty Pulpwood Timber",
    "wof:placetype":"venue"
},
  "geometry": {"coordinates":[-85.013424,33.52679],"type":"Point"}
}