{
  "type": "Feature",
  "properties": {
    "addr:full":"2191 Northlake Pkwy Tucker GA 30084",
    "addr:housenumber":"2191",
    "addr:postcode":"30084",
    "addr:street":"Northlake Pkwy",
    "iso:country":"US",
    "sg:address":"2191 Northlake Pkwy",
    "sg:city":"Tucker",
    "sg:classifiers":[
        {
            "category":"Professional",
            "subcategory":"Management & Consulting",
            "type":"Services"
        }
    ],
    "sg:phone":"+1 770 723 0466",
    "sg:postcode":"30084",
    "sg:province":"GA",
    "sg:tags":[
        "real estate"
    ],
    "wof:name":"Olatunji & Associates",
    "wof:placetype":"venue"
},
  "geometry": {"coordinates":[-84.24453,33.84728],"type":"Point"}
}