{
  "type": "Feature",
  "properties": {
    "addr:full":"2957 Clairmont Rd NE Atlanta GA 30329",
    "addr:housenumber":"2957",
    "addr:postcode":"30329",
    "addr:street":"Clairmont Rd Ne",
    "iso:country":"US",
    "sg:address":"2957 Clairmont Rd NE",
    "sg:city":"Atlanta",
    "sg:classifiers":[
        {
            "category":"Professional",
            "subcategory":"Engineering",
            "type":"Services"
        }
    ],
    "sg:phone":"+1 404 329 5900",
    "sg:postcode":"30329",
    "sg:province":"GA",
    "sg:website":"www.qk4.com",
    "wof:name":"Presnell Group",
    "wof:placetype":"venue"
},
  "geometry": {"coordinates":[-84.31451199999999,33.843282],"type":"Point"}
}