{
  "type": "Feature",
  "properties": {
    "iso:country":"US",
    "sg:address":"200 Harrington Ln",
    "sg:city":"Lawrenceville",
    "sg:classifiers":[
        {
            "category":"Professional",
            "type":"Services"
        }
    ],
    "sg:phone":"+1 770 339 1864",
    "sg:postcode":"30045",
    "sg:province":"GA",
    "wof:name":"Interflex Laser Engravers",
    "wof:placetype":"venue"
},
  "geometry": {"coordinates":[-84.012028,33.938998],"type":"Point"}
}