{
  "type": "Feature",
  "properties": {
    "iso:country":"US",
    "sg:address":"145 4th Ave SE",
    "sg:city":"Atlanta",
    "sg:classifiers":[
        {
            "category":"Education",
            "subcategory":"School",
            "type":"Public Place"
        }
    ],
    "sg:phone":"+1 404 371 7145",
    "sg:postcode":"30317",
    "sg:province":"GA",
    "sg:tags":[
        "high",
        "middle",
        "elementary"
    ],
    "wof:name":"Atlanta City School District",
    "wof:placetype":"venue"
},
  "geometry": {"coordinates":[-84.306691,33.748787],"type":"Point"}
}