{
  "type": "Feature",
  "properties": {
    "iso:country":"US",
    "sg:address":"4800 Briarcliff Rd NE",
    "sg:city":"Atlanta",
    "sg:classifiers":[
        {
            "category":"Shopping Center",
            "type":"Public Place"
        }
    ],
    "sg:phone":"+1 770 493 6340",
    "sg:postcode":"30345",
    "sg:province":"GA",
    "sg:tags":[
        "mall"
    ],
    "wof:name":"Mall Concepts",
    "wof:placetype":"venue"
},
  "geometry": {"coordinates":[-84.256737,33.848751],"type":"Point"}
}