{
  "type": "Feature",
  "properties": {
    "addr:full":"8330 State Rte 85 Riverdale GA 30274",
    "addr:housenumber":"8330",
    "addr:postcode":"30274",
    "addr:street":"State Rte 85",
    "iso:country":"US",
    "sg:address":"8330 State Rte 85",
    "sg:city":"Riverdale",
    "sg:classifiers":[
        {
            "category":"Autos & Motor Vehicles",
            "subcategory":"Automobile Sales",
            "type":"Retail Goods"
        }
    ],
    "sg:phone":"+1 678 479 9559",
    "sg:postcode":"30274",
    "sg:province":"GA",
    "sg:tags":[
        "used"
    ],
    "wof:name":"Freedom Used Auto Sales",
    "wof:placetype":"venue"
},
  "geometry": {"coordinates":[-84.42009,33.529867],"type":"Point"}
}