{
  "type": "Feature",
  "properties": {
    "iso:country":"US",
    "sg:address":"472 Providence Church Rd",
    "sg:city":"Lyons",
    "sg:classifiers":[
        {
            "category":"Real Estate",
            "subcategory":"Real Estate Operator",
            "type":"Services"
        }
    ],
    "sg:phone":"+1 912 565 7138",
    "sg:postcode":"30436",
    "sg:province":"GA",
    "sg:tags":[
        "property",
        "lessor"
    ],
    "wof:name":"Jones Farm Ernest",
    "wof:placetype":"venue"
},
  "geometry": {"coordinates":[-82.277708,31.971838],"type":"Point"}
}