{
  "type": "Feature",
  "properties": {
    "addr:full":"104 W State St Rm 220 Savannah GA 31401",
    "addr:housenumber":"104;220",
    "addr:postcode":"31401",
    "addr:street":"W State St Rm",
    "iso:country":"US",
    "sg:address":"104 W State St Rm 220",
    "sg:city":"Savannah",
    "sg:classifiers":[
        {
            "category":"Real Estate",
            "subcategory":"Real Estate Services",
            "type":"Services"
        },
        {
            "category":"Real Estate",
            "subcategory":"Real Estate Agent",
            "type":"Services"
        }
    ],
    "sg:phone":"+1 912 236 8992",
    "sg:postcode":"31401",
    "sg:province":"GA",
    "sg:tags":[
        "buyer",
        "management",
        "broker"
    ],
    "wof:name":"Gilbert Realty Company",
    "wof:placetype":"venue"
},
  "geometry": {"coordinates":[-81.09339900000001,32.078544],"type":"Point"}
}