{
  "type": "Feature",
  "properties": {
    "iso:country":"US",
    "sg:address":"2054 Rex Rd",
    "sg:city":"Morrow",
    "sg:classifiers":[
        {
            "category":"Professional",
            "subcategory":"Computer Services",
            "type":"Services"
        },
        {
            "category":"Wholesale",
            "subcategory":"Computers",
            "type":"Manufacturing & Wholesale Goods"
        }
    ],
    "sg:phone":"+1 404 343 6915",
    "sg:postcode":"30260",
    "sg:province":"GA",
    "sg:tags":[
        "equipment",
        "software"
    ],
    "wof:name":"A Better Future Computer Training Company Inc",
    "wof:placetype":"venue"
},
  "geometry": {"coordinates":[-84.323201,33.599501],"type":"Point"}
}