{
  "type": "Feature",
  "properties": {
    "iso:country":"US",
    "sg:address":"6556 Rosecommon Dr NW",
    "sg:city":"Norcross",
    "sg:classifiers":[
        {
            "category":"Shopping",
            "subcategory":"Hobbies, Toys, & Games",
            "type":"Retail Goods"
        }
    ],
    "sg:phone":"+1 770 448 1844",
    "sg:postcode":"30092",
    "sg:province":"GA",
    "wof:name":"Fox Den",
    "wof:placetype":"venue"
},
  "geometry": {"coordinates":[-84.248521,33.968768],"type":"Point"}
}