{
  "type": "Feature",
  "properties": {
    "addr:full":"6194 Warner Rd Columbus GA 31909",
    "addr:housenumber":"6194",
    "addr:postcode":"31909",
    "addr:street":"Warner Rd",
    "iso:country":"US",
    "sg:address":"6194 Warner Rd",
    "sg:city":"Columbus",
    "sg:classifiers":[
        {
            "category":"Building & Trades",
            "subcategory":"Electrical",
            "type":"Services"
        }
    ],
    "sg:phone":"+1 706 561 2486",
    "sg:postcode":"31909",
    "sg:province":"GA",
    "sg:tags":[
        "electrical",
        "electric",
        "contractor"
    ],
    "wof:name":"Strickland Electric Co Inc",
    "wof:placetype":"venue"
},
  "geometry": {"coordinates":[-84.91593,32.535638],"type":"Point"}
}