{
  "type": "Feature",
  "properties": {
    "addr:full":"885 Flat Shoals Rd SE Conyers GA 30094",
    "addr:housenumber":"885",
    "addr:postcode":"30094",
    "addr:street":"Flat Shoals Rd Se",
    "iso:country":"US",
    "sg:address":"885 Flat Shoals Rd SE",
    "sg:city":"Conyers",
    "sg:classifiers":[
        {
            "category":"Shopping",
            "subcategory":"Party Supplies",
            "type":"Retail Goods"
        }
    ],
    "sg:phone":"+1 770 922 2695",
    "sg:postcode":"30094",
    "sg:province":"GA",
    "sg:tags":[
        "children's",
        "planning",
        "entertainment"
    ],
    "sg:website":"http://www.amf.com",
    "wof:name":"AMF American Lanes",
    "wof:placetype":"venue"
},
  "geometry": {"coordinates":[-84.015192,33.64275],"type":"Point"}
}