{
  "type": "Feature",
  "properties": {
    "addr:full":"1110 Bull St Savannah GA 31401",
    "addr:housenumber":"1110",
    "addr:postcode":"31401",
    "addr:street":"Bull St",
    "iso:country":"US",
    "sg:address":"1110 Bull St",
    "sg:city":"Savannah",
    "sg:phone":"+1 912 790 9000",
    "sg:postcode":"31401",
    "sg:province":"GA",
    "sg:website":"http://www.local11ten.com",
    "wof:name":"Local 11 Ten",
    "wof:placetype":"venue"
},
  "geometry": {"coordinates":[-81.097268,32.064778],"type":"Point"}
}