{
  "type": "Feature",
  "properties": {
    "iso:country":"US",
    "sg:address":"102 W Liberty St",
    "sg:city":"Savannah",
    "sg:classifiers":[
        {
            "category":"Real Estate",
            "subcategory":"Real Estate Operator",
            "type":"Services"
        }
    ],
    "sg:phone":"+1 912 233 7263",
    "sg:postcode":"31401",
    "sg:province":"GA",
    "sg:tags":[
        "apartment"
    ],
    "wof:name":"Drayton Tower Apartments",
    "wof:placetype":"venue"
},
  "geometry": {"coordinates":[-81.095705,32.075353],"type":"Point"}
}