{
  "type": "Feature",
  "properties": {
    "iso:country":"US",
    "sg:address":"257 Robbie Ln",
    "sg:city":"Marietta",
    "sg:classifiers":[
        {
            "category":"Shopping",
            "subcategory":"Gifts & Souvenirs",
            "type":"Retail Goods"
        }
    ],
    "sg:phone":"+1 770 436 6271",
    "sg:postcode":"30060",
    "sg:province":"GA",
    "sg:tags":[
        "shop"
    ],
    "wof:name":"Blue Moon Creations Inc",
    "wof:placetype":"venue"
},
  "geometry": {"coordinates":[-84.558673,33.880353],"type":"Point"}
}