{
  "type": "Feature",
  "properties": {
    "addr:full":"7029 Clyo-Kildare Rd Newington GA 30446",
    "addr:housenumber":"7029",
    "addr:postcode":"30446",
    "addr:street":"Clyo-Kildare Rd",
    "iso:country":"US",
    "sg:address":"7029 Clyo-Kildare Rd",
    "sg:city":"Newington",
    "sg:classifiers":[
        {
            "category":"Food & Beverages",
            "subcategory":"Groceries & Convenience Stores",
            "type":"Retail Goods"
        }
    ],
    "sg:phone":"+1 912 754 3798",
    "sg:postcode":"30446",
    "sg:province":"GA",
    "sg:tags":[
        "grocer"
    ],
    "wof:name":"Graham's Grocery",
    "wof:placetype":"venue"
},
  "geometry": {"coordinates":[-81.457195,32.533372],"type":"Point"}
}