{
  "type": "Feature",
  "properties": {
    "iso:country":"US",
    "sg:address":"1270 Rivershyre Pkwy NE",
    "sg:city":"Lawrenceville",
    "sg:classifiers":[
        {
            "category":"Professional",
            "subcategory":"Management & Consulting",
            "type":"Services"
        }
    ],
    "sg:phone":"+1 770 963 9261",
    "sg:postcode":"30043",
    "sg:province":"GA",
    "wof:name":"Sites In Sight Inc",
    "wof:placetype":"venue"
},
  "geometry": {"coordinates":[-83.99435200000001,33.993016],"type":"Point"}
}