{
  "type": "Feature",
  "properties": {
    "addr:full":"3025 University Ave Columbus GA 31907",
    "addr:housenumber":"3025",
    "addr:postcode":"31907",
    "addr:street":"University Ave",
    "iso:country":"US",
    "sg:address":"3025 University Ave",
    "sg:city":"Columbus",
    "sg:classifiers":[
        {
            "category":"Banks & Credit Unions",
            "subcategory":"Investment Brokerage",
            "type":"Services"
        }
    ],
    "sg:phone":"+1 706 507 2015",
    "sg:postcode":"31907",
    "sg:province":"GA",
    "sg:tags":[
        "advisory"
    ],
    "wof:name":"Champions Financial",
    "wof:placetype":"venue"
},
  "geometry": {"coordinates":[-84.932427,32.492941],"type":"Point"}
}