{
  "type": "Feature",
  "properties": {
    "addr:full":"1800 Warm Springs Rd Columbus GA 31904",
    "addr:housenumber":"1800",
    "addr:postcode":"31904",
    "addr:street":"Warm Springs Rd",
    "iso:country":"US",
    "sg:address":"1800 Warm Springs Rd",
    "sg:city":"Columbus",
    "sg:classifiers":[
        {
            "category":"Health Services",
            "subcategory":"Doctor",
            "type":"Services"
        }
    ],
    "sg:phone":"+1 706 324 5001",
    "sg:postcode":"31904",
    "sg:province":"GA",
    "sg:tags":[
        "physician",
        "surgeon"
    ],
    "wof:name":"John W Lee MD",
    "wof:placetype":"venue"
},
  "geometry": {"coordinates":[-84.96428299999999,32.495688],"type":"Point"}
}