{
  "type": "Feature",
  "properties": {
    "iso:country":"US",
    "sg:address":"309 Nelson St",
    "sg:city":"Atlanta",
    "sg:classifiers":[
        {
            "category":"Food & Beverages",
            "subcategory":"Bakery",
            "type":"Retail Goods"
        }
    ],
    "sg:phone":"+1 404 521 0537",
    "sg:postcode":"30313",
    "sg:province":"GA",
    "sg:tags":[
        "sandwich"
    ],
    "sg:website":"www.jrcrickets.com",
    "wof:name":"J.R. Crickets",
    "wof:placetype":"venue"
},
  "geometry": {"coordinates":[-84.39795100000001,33.752018],"type":"Point"}
}