{
  "type": "Feature",
  "properties": {
    "iso:country":"US",
    "sg:address":"1090 Brittany Way",
    "sg:city":"Fayetteville",
    "sg:classifiers":[
        {
            "category":"Insurance",
            "subcategory":"Insurance Agent",
            "type":"Services"
        }
    ],
    "sg:phone":"+1 770 486 8466",
    "sg:postcode":"30214",
    "sg:province":"GA",
    "wof:name":"Southside Medical Ins",
    "wof:placetype":"venue"
},
  "geometry": {"coordinates":[-84.54682,33.440324],"type":"Point"}
}