{
  "type": "Feature",
  "properties": {
    "addr:full":"2160 Fountain Dr Ste 200 Snellville GA 30078",
    "addr:housenumber":"2160",
    "addr:postcode":"30078",
    "addr:street":"Fountain Dr Ste 200",
    "iso:country":"US",
    "sg:address":"2160 Fountain Dr Ste 200",
    "sg:city":"Snellville",
    "sg:classifiers":[
        {
            "category":"Health Services",
            "subcategory":"Doctor",
            "type":"Services"
        }
    ],
    "sg:phone":"+1 770 982 1111",
    "sg:postcode":"30078",
    "sg:province":"GA",
    "sg:tags":[
        "psychiatrist"
    ],
    "wof:name":"Healthcare For Seniors",
    "wof:placetype":"venue"
},
  "geometry": {"coordinates":[-84.029588,33.85767],"type":"Point"}
}