{
  "type": "Feature",
  "properties": {
    "iso:country":"US",
    "sg:address":"659 Atlanta St.",
    "sg:city":"Roswell",
    "sg:classifiers":[
        {
            "category":"Restaurant",
            "type":"Food & Drink"
        }
    ],
    "sg:phone":"+1 770 993 1000",
    "sg:postcode":"30075",
    "sg:province":"GA",
    "sg:tags":[
        "cajun/creole"
    ],
    "sg:website":"www.facebook.com/pages/Roswell-G...",
    "wof:name":"North of NOLA",
    "wof:placetype":"venue"
},
  "geometry": {"coordinates":[-84.362319,34.016917],"type":"Point"}
}