{
  "type": "Feature",
  "properties": {
    "iso:country":"US",
    "sg:address":"3625 Cumberland Boulevard SE",
    "sg:city":"Atlanta",
    "sg:classifiers":[
        {
            "category":"Banks & Credit Unions",
            "subcategory":"Investment Brokerage",
            "type":"Services"
        }
    ],
    "sg:phone":"+1 678 529 3400",
    "sg:postcode":"30339",
    "sg:province":"GA",
    "sg:tags":[
        "investing"
    ],
    "wof:name":"Asset Preservation Advisory",
    "wof:placetype":"venue"
},
  "geometry": {"coordinates":[-84.46558899999999,33.878131],"type":"Point"}
}