{
  "type": "Feature",
  "properties": {
    "addr:full":"905 E King Ave Kingsland GA 31548",
    "addr:housenumber":"905",
    "addr:postcode":"31548",
    "addr:street":"E King Ave",
    "iso:country":"US",
    "sg:address":"905 E King Ave",
    "sg:city":"Kingsland",
    "sg:classifiers":[
        {
            "category":"Insurance",
            "subcategory":"Insurance Agent",
            "type":"Services"
        }
    ],
    "sg:phone":"+1 912 729 7600",
    "sg:postcode":"31548",
    "sg:province":"GA",
    "wof:name":"Clyde Aldridge Insurance",
    "wof:placetype":"venue"
},
  "geometry": {"coordinates":[-81.672141,30.796311],"type":"Point"}
}