{
  "type": "Feature",
  "properties": {
    "addr:full":"378 Roscoe Davis Rd Monroe GA 30656",
    "addr:housenumber":"378",
    "addr:postcode":"30656",
    "addr:street":"Roscoe Davis Rd",
    "iso:country":"US",
    "sg:address":"378 Roscoe Davis Rd",
    "sg:city":"Monroe",
    "sg:classifiers":[
        {
            "category":"Building & Trades",
            "subcategory":"Construction",
            "type":"Services"
        }
    ],
    "sg:phone":"+1 770 207 1658",
    "sg:postcode":"30656",
    "sg:province":"GA",
    "sg:tags":[
        "contractor"
    ],
    "wof:name":"B & D Siding Inc",
    "wof:placetype":"venue"
},
  "geometry": {"coordinates":[-83.75240599999999,33.829902],"type":"Point"}
}