{
  "type": "Feature",
  "properties": {
    "addr:full":"4580 Thicket Trl Snellville GA 30039",
    "addr:postcode":"4580;30039",
    "addr:street":"Thicket Trl",
    "iso:country":"US",
    "sg:address":"4580 Thicket Trl",
    "sg:city":"Snellville",
    "sg:classifiers":[
        {
            "category":"Building & Trades",
            "subcategory":"Electrical",
            "type":"Services"
        }
    ],
    "sg:phone":"+1 770 979 8226",
    "sg:postcode":"30039",
    "sg:province":"GA",
    "sg:tags":[
        "electrician",
        "electric",
        "contractor"
    ],
    "wof:name":"Azar Services Inc",
    "wof:placetype":"venue"
},
  "geometry": {"coordinates":[-84.055199,33.783501],"type":"Point"}
}