{
  "type": "Feature",
  "properties": {
    "iso:country":"US",
    "sg:address":"1730 Cumberland Point Dr",
    "sg:city":"Marietta",
    "sg:classifiers":[
        {
            "category":"Personal",
            "subcategory":"Shoe Repair & Shine",
            "type":"Services"
        },
        {
            "category":"Banks & Credit Unions",
            "subcategory":"Financial Services",
            "type":"Services"
        }
    ],
    "sg:phone":"+1 770 951 9440",
    "sg:postcode":"30067",
    "sg:province":"GA",
    "sg:tags":[
        "repairing",
        "franchise",
        "boot"
    ],
    "wof:name":"Heel Quik",
    "wof:placetype":"venue"
},
  "geometry": {"coordinates":[-84.48966299999999,33.911722],"type":"Point"}
}