{
  "type": "Feature",
  "properties": {
    "addr:full":"508 Gentilly Rd Statesboro GA 30458",
    "addr:housenumber":"508",
    "addr:postcode":"30458",
    "addr:street":"Gentilly Rd",
    "iso:country":"US",
    "sg:address":"508 Gentilly Rd",
    "sg:city":"Statesboro",
    "sg:classifiers":[
        {
            "category":"Professional",
            "subcategory":"Management & Consulting",
            "type":"Services"
        }
    ],
    "sg:phone":"+1 912 764 4256",
    "sg:postcode":"30458",
    "sg:province":"GA",
    "wof:name":"Pineland Mgmt Office",
    "wof:placetype":"venue"
},
  "geometry": {"coordinates":[-81.769773,32.43564],"type":"Point"}
}