{
  "type": "Feature",
  "properties": {
    "addr:full":"74 Wilson Overlook Dahlonega GA 30533",
    "addr:housenumber":"74",
    "addr:postcode":"30533",
    "addr:street":"Wilson Overlook",
    "iso:country":"US",
    "sg:address":"74 Wilson Overlook",
    "sg:city":"Dahlonega",
    "sg:classifiers":[
        {
            "category":"Building & Trades",
            "subcategory":"Landscaping Services",
            "type":"Services"
        }
    ],
    "sg:phone":"+1 706 864 1029",
    "sg:postcode":"30533",
    "sg:province":"GA",
    "sg:tags":[
        "landscape"
    ],
    "wof:name":"Archon Landscaping LLC",
    "wof:placetype":"venue"
},
  "geometry": {"coordinates":[-84.062687,34.508959],"type":"Point"}
}