{
  "type": "Feature",
  "properties": {
    "addr:full":"3585 North Pkwy Cumming GA 30040",
    "addr:housenumber":"3585",
    "addr:postcode":"30040",
    "addr:street":"North Pkwy",
    "iso:country":"US",
    "sg:address":"3585 North Pkwy",
    "sg:city":"Cumming",
    "sg:classifiers":[
        {
            "category":"Wholesale",
            "subcategory":"Chemicals & Plastics",
            "type":"Manufacturing & Wholesale Goods"
        }
    ],
    "sg:phone":"+1 678 513 2900",
    "sg:postcode":"30040",
    "sg:province":"GA",
    "sg:tags":[
        "cleaner",
        "supply",
        "cleaning",
        "compound"
    ],
    "wof:name":"Amazon Premium Products",
    "wof:placetype":"venue"
},
  "geometry": {"coordinates":[-84.147921,34.191403],"type":"Point"}
}