{
  "type": "Feature",
  "properties": {
    "iso:country":"US",
    "sg:address":"9456 S Main St",
    "sg:city":"Jonesboro",
    "sg:classifiers":[
        {
            "category":"Shopping",
            "subcategory":"Clothing, Apparel, & Fashions",
            "type":"Retail Goods"
        }
    ],
    "sg:phone":"+1 770 471 8006",
    "sg:postcode":"30236",
    "sg:province":"GA",
    "sg:tags":[
        "alteration"
    ],
    "wof:name":"Telmarc International",
    "wof:placetype":"venue"
},
  "geometry": {"coordinates":[-84.338815,33.49281],"type":"Point"}
}