{
  "type": "Feature",
  "properties": {
    "iso:country":"US",
    "sg:address":"832 Turner McCall Blvd",
    "sg:city":"Rome",
    "sg:classifiers":[
        {
            "category":"Shopping",
            "subcategory":"Pharmacy",
            "type":"Retail Goods"
        }
    ],
    "sg:phone":"+1 706 291 7850",
    "sg:postcode":"30161",
    "sg:province":"GA",
    "wof:name":"Wards Pharmacy",
    "wof:placetype":"venue"
},
  "geometry": {"coordinates":[-85.164753,34.256494],"type":"Point"}
}