{
  "type": "Feature",
  "properties": {
    "iso:country":"US",
    "sg:address":"303 Fawnwood Ct",
    "sg:city":"Statesboro",
    "sg:classifiers":[
        {
            "category":"Education",
            "subcategory":"School",
            "type":"Public Place"
        }
    ],
    "sg:phone":"+1 912 681 5328",
    "sg:postcode":"30461",
    "sg:province":"GA",
    "wof:name":"Florida High School Sports Mag",
    "wof:placetype":"venue"
},
  "geometry": {"coordinates":[-81.783626,32.487415],"type":"Point"}
}