{
  "type": "Feature",
  "properties": {
    "addr:full":"500 Broad St Augusta GA 30901",
    "addr:housenumber":"500",
    "addr:postcode":"30901",
    "addr:street":"Broad St",
    "iso:country":"US",
    "sg:address":"500 Broad St",
    "sg:city":"Augusta",
    "sg:classifiers":[
        {
            "category":"Government",
            "subcategory":"Court House",
            "type":"Public Place"
        }
    ],
    "sg:phone":"+1 706 722 2074",
    "sg:postcode":"30901",
    "sg:province":"GA",
    "sg:tags":[
        "federal",
        "system"
    ],
    "wof:name":"U S Federal District Court",
    "wof:placetype":"venue"
},
  "geometry": {"coordinates":[-81.96033199999999,33.473577],"type":"Point"}
}