{
  "type": "Feature",
  "properties": {
    "addr:full":"35 Northside Dr SW Atlanta GA 30313",
    "addr:housenumber":"35",
    "addr:postcode":"30313",
    "addr:street":"Northside Dr Sw",
    "iso:country":"US",
    "sg:address":"35 Northside Dr SW",
    "sg:city":"Atlanta",
    "sg:classifiers":[
        {
            "category":"Real Estate",
            "subcategory":"Real Estate Operator",
            "type":"Services"
        }
    ],
    "sg:phone":"+1 404 681 2873",
    "sg:postcode":"30313",
    "sg:province":"GA",
    "sg:tags":[
        "apartment"
    ],
    "wof:name":"Friendship Tower Apartments",
    "wof:placetype":"venue"
},
  "geometry": {"coordinates":[-84.408338,33.744528],"type":"Point"}
}