{
  "type": "Feature",
  "properties": {
    "addr:full":"7501 Auden Trl Atlanta GA 30350",
    "addr:housenumber":"7501",
    "addr:postcode":"30350",
    "addr:street":"Auden Trl",
    "iso:country":"US",
    "sg:address":"7501 Auden Trl",
    "sg:city":"Atlanta",
    "sg:classifiers":[
        {
            "category":"Health Services",
            "subcategory":"Health Practitioner",
            "type":"Services"
        }
    ],
    "sg:phone":"+1 770 394 9791",
    "sg:postcode":"30350",
    "sg:province":"GA",
    "sg:tags":[
        "occupational",
        "therapist"
    ],
    "sg:website":"http://www.childrens-services.com",
    "wof:name":"Childrens Special Services LLC",
    "wof:placetype":"venue"
},
  "geometry": {"coordinates":[-84.34854900000001,33.960461],"type":"Point"}
}