{
  "type": "Feature",
  "properties": {
    "addr:full":"1874 Sturgeon Rd Buford GA 30518",
    "addr:housenumber":"1874",
    "addr:postcode":"30518",
    "addr:street":"Sturgeon Rd",
    "iso:country":"US",
    "sg:address":"1874 Sturgeon Rd",
    "sg:city":"Buford",
    "sg:classifiers":[
        {
            "category":"Building & Trades",
            "subcategory":"Construction",
            "type":"Services"
        }
    ],
    "sg:phone":"+1 770 401 0573",
    "sg:postcode":"30518",
    "sg:province":"GA",
    "sg:tags":[
        "hanging",
        "contractor"
    ],
    "wof:name":"Fredys Painting",
    "wof:placetype":"venue"
},
  "geometry": {"coordinates":[-84.00157299999999,34.098027],"type":"Point"}
}