{
  "type": "Feature",
  "properties": {
    "iso:country":"US",
    "sg:address":"382 Yonah St",
    "sg:city":"Cornelia",
    "sg:classifiers":[
        {
            "category":"Organizations",
            "subcategory":"Religious Organization",
            "type":"Services"
        }
    ],
    "sg:phone":"+1 706 778 6404",
    "sg:postcode":"30531",
    "sg:province":"GA",
    "sg:tags":[
        "clergy"
    ],
    "wof:name":"Cornelia Christian Church",
    "wof:placetype":"venue"
},
  "geometry": {"coordinates":[-83.523954,34.50542],"type":"Point"}
}