{
  "type": "Feature",
  "properties": {
    "iso:country":"US",
    "sg:address":"4276 Georgia Highway 120",
    "sg:city":"Buchanan",
    "sg:classifiers":[
        {
            "category":"Government",
            "subcategory":"Office",
            "type":"Public Place"
        }
    ],
    "sg:phone":"+1 770 646 2020",
    "sg:postcode":"30113",
    "sg:province":"GA",
    "sg:tags":[
        "parish",
        "government-county"
    ],
    "wof:name":"Haralson County Tax Commissioner",
    "wof:placetype":"venue"
},
  "geometry": {"coordinates":[-85.18843200000001,33.802305],"type":"Point"}
}