{
  "type": "Feature",
  "properties": {
    "addr:full":"104 Greenville St Lagrange GA 30241",
    "addr:housenumber":"104",
    "addr:postcode":"30241",
    "addr:street":"Greenville St",
    "iso:country":"US",
    "sg:address":"104 Greenville St",
    "sg:city":"Lagrange",
    "sg:classifiers":[
        {
            "category":"Professional",
            "subcategory":"Lawyer & Legal Services",
            "type":"Services"
        }
    ],
    "sg:phone":"+1 706 882 5235",
    "sg:postcode":"30241",
    "sg:province":"GA",
    "sg:tags":[
        "attorney"
    ],
    "wof:name":"Vickie Sue Mc Waters",
    "wof:placetype":"venue"
},
  "geometry": {"coordinates":[-85.030562,33.039427],"type":"Point"}
}