{
  "type": "Feature",
  "properties": {
    "addr:full":"128 Oak Hill Rd Covington GA 30016",
    "addr:housenumber":"128",
    "addr:postcode":"30016",
    "addr:street":"Oak Hill Rd",
    "iso:country":"US",
    "sg:address":"128 Oak Hill Rd",
    "sg:city":"Covington",
    "sg:classifiers":[
        {
            "category":"Building & Trades",
            "subcategory":"Construction",
            "type":"Services"
        }
    ],
    "sg:phone":"+1 770 788 8848",
    "sg:postcode":"30016",
    "sg:province":"GA",
    "sg:tags":[
        "hanging",
        "contractor"
    ],
    "wof:name":"Grimes Painting",
    "wof:placetype":"venue"
},
  "geometry": {"coordinates":[-83.949388,33.546936],"type":"Point"}
}