{
  "type": "Feature",
  "properties": {
    "addr:full":"1425 Blair Bridge Rd Austell GA 30168",
    "addr:housenumber":"1425",
    "addr:postcode":"30168",
    "addr:street":"Blair Bridge Rd",
    "iso:country":"US",
    "sg:address":"1425 Blair Bridge Rd",
    "sg:city":"Austell",
    "sg:classifiers":[
        {
            "category":"Professional",
            "subcategory":"Computer Services",
            "type":"Services"
        }
    ],
    "sg:phone":"+1 770 739 4251",
    "sg:postcode":"30168",
    "sg:province":"GA",
    "sg:tags":[
        "programing",
        "custom"
    ],
    "wof:name":"Kevin Johnson",
    "wof:placetype":"venue"
},
  "geometry": {"coordinates":[-84.598224,33.780555],"type":"Point"}
}