{
  "type": "Feature",
  "properties": {
    "addr:full":"371 Commercial Dr Thomasville GA 31792",
    "addr:housenumber":"371",
    "addr:postcode":"31792",
    "addr:street":"Commercial Dr",
    "iso:country":"US",
    "sg:address":"371 Commercial Dr",
    "sg:city":"Thomasville",
    "sg:classifiers":[
        {
            "category":"Retail",
            "subcategory":"Auto Repair",
            "type":"Services"
        }
    ],
    "sg:phone":"+1 229 226 1123",
    "sg:postcode":"31792",
    "sg:province":"GA",
    "sg:tags":[
        "repairing",
        "automobile"
    ],
    "wof:name":"Jon Mc Gee Auto Svc",
    "wof:placetype":"venue"
},
  "geometry": {"coordinates":[-83.940198,30.853447],"type":"Point"}
}