{
  "type": "Feature",
  "properties": {
    "iso:country":"US",
    "sg:address":"292 S Atlanta St Ste E",
    "sg:city":"Roswell",
    "sg:classifiers":[
        {
            "category":"Personal",
            "subcategory":"Beauty Salon",
            "type":"Services"
        }
    ],
    "sg:phone":"+1 678 795 1700",
    "sg:postcode":"30075",
    "sg:province":"GA",
    "sg:tags":[
        "hair"
    ],
    "wof:name":"Esquisite Beauty Supply and Salon",
    "wof:placetype":"venue"
},
  "geometry": {"coordinates":[-84.35845999999999,34.00856],"type":"Point"}
}