{
  "type": "Feature",
  "properties": {
    "iso:country":"US",
    "sg:address":"5025 Fox Lair Ln",
    "sg:city":"Alpharetta",
    "sg:classifiers":[
        {
            "category":"Building & Trades",
            "subcategory":"Construction",
            "type":"Services"
        }
    ],
    "sg:phone":"+1 770 754 1390",
    "sg:postcode":"30004",
    "sg:province":"GA",
    "sg:tags":[
        "house"
    ],
    "wof:name":"Deckcrafters",
    "wof:placetype":"venue"
},
  "geometry": {"coordinates":[-84.314267,34.075792],"type":"Point"}
}