{
  "type": "Feature",
  "properties": {
    "addr:full":"3535 Old Lexington Rd Athens GA 30605",
    "addr:housenumber":"3535",
    "addr:postcode":"30605",
    "addr:street":"Old Lexington Rd",
    "iso:country":"US",
    "sg:address":"3535 Old Lexington Rd",
    "sg:city":"Athens",
    "sg:classifiers":[
        {
            "category":"Shopping",
            "subcategory":"Gifts & Souvenirs",
            "type":"Retail Goods"
        }
    ],
    "sg:phone":"+1 706 548 0872",
    "sg:postcode":"30605",
    "sg:province":"GA",
    "sg:tags":[
        "party",
        "supply"
    ],
    "wof:name":"Joe Girl Enterprises",
    "wof:placetype":"venue"
},
  "geometry": {"coordinates":[-83.327945,33.909924],"type":"Point"}
}