{
  "type": "Feature",
  "properties": {
    "iso:country":"US",
    "sg:address":"630 Grimes Bridge Lndg",
    "sg:city":"Roswell",
    "sg:classifiers":[
        {
            "category":"Organizations",
            "subcategory":"Membership Organization",
            "type":"Services"
        }
    ],
    "sg:phone":"+1 770 992 6083",
    "sg:postcode":"30075",
    "sg:province":"GA",
    "wof:name":"Grimes Bridge Landing Assn",
    "wof:placetype":"venue"
},
  "geometry": {"coordinates":[-84.340852,34.015675],"type":"Point"}
}