{
  "type": "Feature",
  "properties": {
    "addr:full":"104 Colonial Rd Byron GA 31088",
    "addr:housenumber":"104",
    "addr:postcode":"31088",
    "addr:street":"Colonial Rd",
    "iso:country":"US",
    "sg:address":"104 Colonial Rd",
    "sg:city":"Byron",
    "sg:classifiers":[
        {
            "category":"Professional",
            "type":"Services"
        }
    ],
    "sg:phone":"+1 478 956 5559",
    "sg:postcode":"31088",
    "sg:province":"GA",
    "sg:tags":[
        "establishment"
    ],
    "wof:name":"Bashes",
    "wof:placetype":"venue"
},
  "geometry": {"coordinates":[-83.650193,32.60046],"type":"Point"}
}