{
  "type": "Feature",
  "properties": {
    "iso:country":"US",
    "sg:address":"874 Sylvan Dr",
    "sg:city":"Marietta",
    "sg:classifiers":[
        {
            "category":"Building & Trades",
            "subcategory":"Construction",
            "type":"Services"
        }
    ],
    "sg:phone":"+1 770 422 3101",
    "sg:postcode":"30066",
    "sg:province":"GA",
    "sg:tags":[
        "dry wall",
        "contractor"
    ],
    "wof:name":"J & F Drywall Inc",
    "wof:placetype":"venue"
},
  "geometry": {"coordinates":[-84.526999,34.003204],"type":"Point"}
}