{
  "type": "Feature",
  "properties": {
    "iso:country":"US",
    "sg:address":"4385 International Blvd NW",
    "sg:city":"Norcross",
    "sg:classifiers":[
        {
            "category":"Health Services",
            "subcategory":"Optometrist",
            "type":"Services"
        }
    ],
    "sg:phone":"+1 770 717 9893",
    "sg:postcode":"30093",
    "sg:province":"GA",
    "wof:name":"Vision International",
    "wof:placetype":"venue"
},
  "geometry": {"coordinates":[-84.148404,33.932556],"type":"Point"}
}