{
  "type": "Feature",
  "properties": {
    "iso:country":"US",
    "sg:address":"95 Philadelphia Dr",
    "sg:city":"Jasper",
    "sg:classifiers":[
        {
            "category":"Building & Trades",
            "subcategory":"Construction",
            "type":"Services"
        }
    ],
    "sg:phone":"+1 706 253 6630",
    "sg:postcode":"30143",
    "sg:province":"GA",
    "sg:tags":[
        "contractor",
        "grading"
    ],
    "sg:website":"http://www.hfgpipe.com",
    "wof:name":"High Falls Grading, Inc",
    "wof:placetype":"venue"
},
  "geometry": {"coordinates":[-84.472994,34.463775],"type":"Point"}
}