{
  "type": "Feature",
  "properties": {
    "addr:full":"1384 Rainier Falls Dr NE Atlanta GA 30329",
    "addr:housenumber":"1384",
    "addr:postcode":"30329",
    "addr:street":"Rainier Falls Dr Ne",
    "iso:country":"US",
    "sg:address":"1384 Rainier Falls Dr NE",
    "sg:city":"Atlanta",
    "sg:classifiers":[
        {
            "category":"Real Estate",
            "subcategory":"Real Estate Agent",
            "type":"Services"
        }
    ],
    "sg:phone":"+1 404 634 5120",
    "sg:postcode":"30329",
    "sg:province":"GA",
    "wof:name":"Caraphota Realty",
    "wof:placetype":"venue"
},
  "geometry": {"coordinates":[-84.327962,33.806933],"type":"Point"}
}