{
  "type": "Feature",
  "properties": {
    "addr:full":"1862 John Wesley Ave College Park GA 30337",
    "addr:housenumber":"1862",
    "addr:postcode":"30337",
    "addr:street":"John Wesley Ave",
    "iso:country":"US",
    "sg:address":"1862 John Wesley Ave",
    "sg:city":"College Park",
    "sg:classifiers":[
        {
            "category":"Shopping",
            "subcategory":"Clothing, Apparel, & Fashions",
            "type":"Retail Goods"
        }
    ],
    "sg:phone":"+1 404 968 4540",
    "sg:postcode":"30337",
    "sg:province":"GA",
    "sg:tags":[
        "item",
        "boutique"
    ],
    "wof:name":"Just Grace",
    "wof:placetype":"venue"
},
  "geometry": {"coordinates":[-84.45103899999999,33.650988],"type":"Point"}
}