{
  "type": "Feature",
  "properties": {
    "addr:full":"1218 Martin Luther King Jr Blvd Savannah GA 31415",
    "addr:housenumber":"1218",
    "addr:postcode":"31415",
    "addr:street":"Martin Luther King Jr Blvd",
    "iso:country":"US",
    "sg:address":"1218 Martin Luther King Jr Blvd",
    "sg:city":"Savannah",
    "sg:classifiers":[
        {
            "category":"Shopping",
            "subcategory":"Clothing, Apparel, & Fashions",
            "type":"Retail Goods"
        }
    ],
    "sg:phone":"+1 912 236 1272",
    "sg:postcode":"31415",
    "sg:province":"GA",
    "sg:tags":[
        "sportswear"
    ],
    "wof:name":"Heritage Convenience & Apparel",
    "wof:placetype":"venue"
},
  "geometry": {"coordinates":[-81.10311,32.06465],"type":"Point"}
}