{
  "type": "Feature",
  "properties": {
    "iso:country":"US",
    "sg:address":"1126 Ponce de Leon Ave NE",
    "sg:city":"Atlanta",
    "sg:classifiers":[
        {
            "category":"Professional",
            "subcategory":"Lawyer & Legal Services",
            "type":"Services"
        }
    ],
    "sg:phone":"+1 404 872 3007",
    "sg:postcode":"30306",
    "sg:province":"GA",
    "wof:name":"Jodi Spiegel Atty",
    "wof:placetype":"venue"
},
  "geometry": {"coordinates":[-84.34907699999999,33.773919],"type":"Point"}
}