{
  "type": "Feature",
  "properties": {
    "iso:country":"US",
    "sg:address":"5 Fallow Dr",
    "sg:city":"Rome",
    "sg:classifiers":[
        {
            "category":"Organizations",
            "subcategory":"Religious Organization",
            "type":"Services"
        }
    ],
    "sg:phone":"+1 706 232 4322",
    "sg:postcode":"30165",
    "sg:province":"GA",
    "wof:name":"Kirk Ayers Ministries Inc",
    "wof:placetype":"venue"
},
  "geometry": {"coordinates":[-85.255821,34.275738],"type":"Point"}
}