{
  "type": "Feature",
  "properties": {
    "addr:full":"4015 Community Rd Ste 102 Brunswick GA 31520",
    "addr:housenumber":"4015",
    "addr:postcode":"31520",
    "addr:street":"Community Rd Ste 102",
    "iso:country":"US",
    "sg:address":"4015 Community Rd Ste 102",
    "sg:city":"Brunswick",
    "sg:classifiers":[
        {
            "category":"Professional",
            "subcategory":"Lawyer & Legal Services",
            "type":"Services"
        }
    ],
    "sg:phone":"+1 912 267 6093",
    "sg:postcode":"31520",
    "sg:province":"GA",
    "sg:tags":[
        "attorney",
        "practice"
    ],
    "wof:name":"R Dean Attonery Of Law Weiss",
    "wof:placetype":"venue"
},
  "geometry": {"coordinates":[-81.502639,31.203335],"type":"Point"}
}