{
  "type": "Feature",
  "properties": {
    "addr:full":"3522 Ashford Dunwoody Rd NE Atlanta GA 30319",
    "addr:housenumber":"3522",
    "addr:postcode":"30319",
    "addr:street":"Ashford Dunwoody Rd Ne",
    "iso:country":"US",
    "sg:address":"3522 Ashford Dunwoody Rd NE",
    "sg:city":"Atlanta",
    "sg:classifiers":[
        {
            "category":"Professional",
            "subcategory":"Business Services",
            "type":"Services"
        }
    ],
    "sg:phone":"+1 312 714 0344",
    "sg:postcode":"30319",
    "sg:province":"GA",
    "sg:tags":[
        "testing"
    ],
    "wof:name":"Lbr Technologies",
    "wof:placetype":"venue"
},
  "geometry": {"coordinates":[-84.32872,33.89468],"type":"Point"}
}