{
  "type": "Feature",
  "properties": {
    "iso:country":"US",
    "sg:address":"509 Talula Ct",
    "sg:city":"Woodstock",
    "sg:classifiers":[
        {
            "category":"Professional",
            "type":"Services"
        }
    ],
    "sg:phone":"+1 770 592 1945",
    "sg:postcode":"30189",
    "sg:province":"GA",
    "wof:name":"Donald M Bare",
    "wof:placetype":"venue"
},
  "geometry": {"coordinates":[-84.535025,34.116286],"type":"Point"}
}