{
  "type": "Feature",
  "properties": {
    "iso:country":"US",
    "sg:address":"306 Lake Dr",
    "sg:city":"Dawsonville",
    "sg:classifiers":[
        {
            "category":"Health Services",
            "subcategory":"Medical Lab",
            "type":"Services"
        }
    ],
    "sg:phone":"+1 706 216 1718",
    "sg:postcode":"30534",
    "sg:province":"GA",
    "sg:tags":[
        "dental"
    ],
    "wof:name":"Distinctive Dental Svc Inc",
    "wof:placetype":"venue"
},
  "geometry": {"coordinates":[-84.021585,34.363867],"type":"Point"}
}