{
  "type": "Feature",
  "properties": {
    "iso:country":"US",
    "sg:address":"700 Poplar St",
    "sg:city":"Macon",
    "sg:classifiers":[
        {
            "category":"Government",
            "subcategory":"Office",
            "type":"Public Place"
        }
    ],
    "sg:phone":"+1 478 751 7214",
    "sg:postcode":"31201",
    "sg:province":"GA",
    "sg:tags":[
        "civil",
        "defense",
        "agency"
    ],
    "wof:name":"Macon-Bibb Cnty Emergency Mgmt",
    "wof:placetype":"venue"
},
  "geometry": {"coordinates":[-83.63223499999999,32.836393],"type":"Point"}
}