{
  "type": "Feature",
  "properties": {
    "iso:country":"US",
    "sg:address":"3625 Bridle Ridge Dr",
    "sg:city":"Suwanee",
    "sg:classifiers":[
        {
            "category":"Insurance",
            "subcategory":"Insurance Agent",
            "type":"Services"
        }
    ],
    "sg:phone":"+1 678 947 6748",
    "sg:postcode":"30024",
    "sg:province":"GA",
    "wof:name":"Wascovich Group",
    "wof:placetype":"venue"
},
  "geometry": {"coordinates":[-84.1679,34.085964],"type":"Point"}
}