{
  "type": "Feature",
  "properties": {
    "addr:full":"520 Skyview Dr Augusta GA 30901",
    "addr:housenumber":"520",
    "addr:postcode":"30901",
    "addr:street":"Skyview Dr",
    "iso:country":"US",
    "sg:address":"520 Skyview Dr",
    "sg:city":"Augusta",
    "sg:classifiers":[
        {
            "category":"Retail",
            "subcategory":"Repair Shop",
            "type":"Services"
        }
    ],
    "sg:phone":"+1 706 774 0600",
    "sg:postcode":"30901",
    "sg:province":"GA",
    "sg:tags":[
        "new",
        "industrial",
        "boiler",
        "used"
    ],
    "wof:name":"Professional Boiler Services",
    "wof:placetype":"venue"
},
  "geometry": {"coordinates":[-81.972341,33.456953],"type":"Point"}
}