{
  "type": "Feature",
  "properties": {
    "iso:country":"US",
    "sg:address":"3891 Hadley Farm Dr",
    "sg:city":"Marietta",
    "sg:classifiers":[
        {
            "category":"Building & Trades",
            "subcategory":"Landscaping Services",
            "type":"Services"
        }
    ],
    "sg:phone":"+1 770 517 0927",
    "sg:postcode":"30066",
    "sg:province":"GA",
    "sg:tags":[
        "lawn",
        "maintenance",
        "grounds"
    ],
    "wof:name":"Green Castle Land",
    "wof:placetype":"venue"
},
  "geometry": {"coordinates":[-84.52312999999999,34.046285],"type":"Point"}
}