{
  "type": "Feature",
  "properties": {
    "iso:country":"US",
    "sg:address":"4581 Dallas St",
    "sg:city":"Acworth",
    "sg:classifiers":[
        {
            "category":"Banks & Credit Unions",
            "subcategory":"Bank",
            "type":"Services"
        }
    ],
    "sg:phone":"+1 770 974 4241",
    "sg:postcode":"30101",
    "sg:province":"GA",
    "sg:tags":[
        "national",
        "commercial"
    ],
    "wof:name":"Bank of America",
    "wof:placetype":"venue"
},
  "geometry": {"coordinates":[-84.678077,34.065454],"type":"Point"}
}