{
  "type": "Feature",
  "properties": {
    "iso:country":"US",
    "sg:address":"1607 N Patterson St",
    "sg:city":"Valdosta",
    "sg:classifiers":[
        {
            "category":"Professional",
            "subcategory":"Accounting & Tax Preparation",
            "type":"Services"
        }
    ],
    "sg:phone":"+1 229 247 6314",
    "sg:postcode":"31602",
    "sg:province":"GA",
    "sg:tags":[
        "accountant"
    ],
    "sg:website":"www.svacpa.com",
    "wof:name":"Stevens Valenti & Assocs",
    "wof:placetype":"venue"
},
  "geometry": {"coordinates":[-83.28774300000001,30.850303],"type":"Point"}
}