{
  "type": "Feature",
  "properties": {
    "addr:full":"1176 Clinton Rd Macon GA 31211",
    "addr:housenumber":"1176",
    "addr:postcode":"31211",
    "addr:street":"Clinton Rd",
    "iso:country":"US",
    "sg:address":"1176 Clinton Rd",
    "sg:city":"Macon",
    "sg:classifiers":[
        {
            "category":"Professional",
            "subcategory":"Lawyer & Legal Services",
            "type":"Services"
        }
    ],
    "sg:phone":"+1 478 745 2402",
    "sg:postcode":"31211",
    "sg:province":"GA",
    "sg:tags":[
        "plan"
    ],
    "sg:website":"www.attorneyroymiller.com",
    "wof:name":"Roy Miller Pc",
    "wof:placetype":"venue"
},
  "geometry": {"coordinates":[-83.61859,32.857466],"type":"Point"}
}