{
  "type": "Feature",
  "properties": {
    "iso:country":"US",
    "sg:address":"5747 N Henry Blvd",
    "sg:city":"Stockbridge",
    "sg:classifiers":[
        {
            "category":"Retail",
            "subcategory":"Auto Repair",
            "type":"Services"
        }
    ],
    "sg:phone":"+1 770 474 6447",
    "sg:postcode":"30281",
    "sg:province":"GA",
    "wof:name":"Benco Automotive",
    "wof:placetype":"venue"
},
  "geometry": {"coordinates":[-84.2603,33.5588],"type":"Point"}
}