{
  "type": "Feature",
  "properties": {
    "iso:country":"US",
    "sg:address":"27 8th St NE",
    "sg:city":"Atlanta",
    "sg:classifiers":[
        {
            "category":"Building & Trades",
            "subcategory":"Landscaping Services",
            "type":"Services"
        }
    ],
    "sg:phone":"+1 404 892 1788",
    "sg:postcode":"30309",
    "sg:province":"GA",
    "sg:tags":[
        "designer",
        "landscape"
    ],
    "wof:name":"Richard Anderson Landscape",
    "wof:placetype":"venue"
},
  "geometry": {"coordinates":[-84.387203,33.779465],"type":"Point"}
}