{
  "type": "Feature",
  "properties": {
    "addr:full":"314 Somerlane Pl Avondale Estates GA 30002",
    "addr:housenumber":"314",
    "addr:postcode":"30002",
    "addr:street":"Somerlane Pl",
    "iso:country":"US",
    "sg:address":"314 Somerlane Pl",
    "sg:city":"Avondale Estates",
    "sg:classifiers":[
        {
            "category":"Organizations",
            "subcategory":"Professional Association",
            "type":"Services"
        }
    ],
    "sg:phone":"+1 404 292 2976",
    "sg:postcode":"30002",
    "sg:province":"GA",
    "wof:name":"Legal Assistant Mgmt Assn",
    "wof:placetype":"venue"
},
  "geometry": {"coordinates":[-84.25291199999999,33.783696],"type":"Point"}
}