{
  "type": "Feature",
  "properties": {
    "addr:full":"96 W Coffee St Hazlehurst GA 31539",
    "addr:housenumber":"96",
    "addr:postcode":"31539",
    "addr:street":"W Coffee St",
    "iso:country":"US",
    "sg:address":"96 W Coffee St",
    "sg:city":"Hazlehurst",
    "sg:classifiers":[
        {
            "category":"Restaurant",
            "type":"Food & Drink"
        }
    ],
    "sg:phone":"+1 912 375 2006",
    "sg:postcode":"31539",
    "sg:province":"GA",
    "wof:name":"Courson's Barbeque",
    "wof:placetype":"venue"
},
  "geometry": {"coordinates":[-82.597858,31.879234],"type":"Point"}
}