{
  "type": "Feature",
  "properties": {
    "addr:full":"1661 Cannonball Ct NW Lawrenceville GA 30044",
    "addr:housenumber":"1661",
    "addr:postcode":"30044",
    "addr:street":"Cannonball Ct Nw",
    "iso:country":"US",
    "sg:address":"1661 Cannonball Ct NW",
    "sg:city":"Lawrenceville",
    "sg:classifiers":[
        {
            "category":"Social Services",
            "subcategory":"Child Care",
            "type":"Services"
        }
    ],
    "sg:phone":"+1 770 682 0636",
    "sg:postcode":"30044",
    "sg:province":"GA",
    "sg:tags":[
        "day"
    ],
    "wof:name":"Glorias Playhouse",
    "wof:placetype":"venue"
},
  "geometry": {"coordinates":[-84.035622,33.934471],"type":"Point"}
}