{
  "type": "Feature",
  "properties": {
    "addr:full":"2078 Beaver Ruin Rd Norcross GA 30071",
    "addr:housenumber":"2078",
    "addr:postcode":"30071",
    "addr:street":"Beaver Ruin Rd",
    "iso:country":"US",
    "sg:address":"2078 Beaver Ruin Rd",
    "sg:city":"Norcross",
    "sg:classifiers":[
        {
            "category":"Utilities",
            "subcategory":"Mobile Phone",
            "type":"Services"
        },
        {
            "category":"Professional",
            "type":"Services"
        }
    ],
    "sg:phone":"+1 770 449 9737",
    "sg:postcode":"30071",
    "sg:province":"GA",
    "sg:tags":[
        "telephone",
        "cellular"
    ],
    "wof:name":"Cellular Connections",
    "wof:placetype":"venue"
},
  "geometry": {"coordinates":[-84.18167099999999,33.934303],"type":"Point"}
}