{
  "type": "Feature",
  "properties": {
    "addr:full":"4077 Jimmie Dyess Pkwy Augusta GA 30909",
    "addr:postcode":"4077;30909",
    "addr:street":"Jimmie Dyess Pkwy",
    "iso:country":"US",
    "sg:address":"4077 Jimmie Dyess Pkwy",
    "sg:city":"Augusta",
    "sg:classifiers":[
        {
            "category":"Restaurant",
            "type":"Food & Drink"
        }
    ],
    "sg:menulink":"http://www.allmenus.com/ga/harlem/140586-waffle-house/menu/",
    "sg:phone":"+1 678 423 1818",
    "sg:postcode":"30909",
    "sg:province":"GA",
    "sg:tags":[
        "american"
    ],
    "wof:name":"Waffle House",
    "wof:placetype":"venue"
},
  "geometry": {"coordinates":[-82.12976500000001,33.479449],"type":"Point"}
}