{
  "type": "Feature",
  "properties": {
    "iso:country":"US",
    "sg:address":"2305 Rowland Ave",
    "sg:city":"Savannah",
    "sg:classifiers":[
        {
            "category":"Autos & Motor Vehicles",
            "subcategory":"Auto Supplies",
            "type":"Retail Goods"
        },
        {
            "category":"Wholesale",
            "subcategory":"Drugs",
            "type":"Manufacturing & Wholesale Goods"
        },
        {
            "category":"Professional",
            "subcategory":"Printing & Photocopies",
            "type":"Services"
        },
        {
            "category":"Professional",
            "subcategory":"Advertising",
            "type":"Services"
        },
        {
            "category":"Manufacturing",
            "subcategory":"Signs",
            "type":"Manufacturing & Wholesale Goods"
        }
    ],
    "sg:phone":"+1 912 691 1117",
    "sg:postcode":"31404",
    "sg:province":"GA",
    "sg:tags":[
        "lettering",
        "product",
        "flag",
        "specialty",
        "decal",
        "truck",
        "pennant",
        "banners",
        "painting",
        "advertising-promotional"
    ],
    "sg:website":"http://www.grafixinc.net",
    "wof:name":"Grafix Inc",
    "wof:placetype":"venue"
},
  "geometry": {"coordinates":[-81.05843400000001,32.036338],"type":"Point"}
}