{
  "type": "Feature",
  "properties": {
    "iso:country":"US",
    "sg:address":"5762 Sydney Ann Ct",
    "sg:city":"Mableton",
    "sg:classifiers":[
        {
            "category":"Retail",
            "subcategory":"Auto Repair",
            "type":"Services"
        }
    ],
    "sg:phone":"+1 770 819 5070",
    "sg:postcode":"30126",
    "sg:province":"GA",
    "sg:tags":[
        "brake"
    ],
    "wof:name":"Atlanta Safety Brake Svc",
    "wof:placetype":"venue"
},
  "geometry": {"coordinates":[-84.596593,33.813837],"type":"Point"}
}