{
  "type": "Feature",
  "properties": {
    "addr:full":"7066 Whitfield Dr Riverdale GA 30296",
    "addr:housenumber":"7066",
    "addr:postcode":"30296",
    "addr:street":"Whitfield Dr",
    "iso:country":"US",
    "sg:address":"7066 Whitfield Dr",
    "sg:city":"Riverdale",
    "sg:classifiers":[
        {
            "category":"Food & Beverages",
            "subcategory":"Liquor & Beverages",
            "type":"Retail Goods"
        },
        {
            "category":"Food & Beverages",
            "subcategory":"Groceries & Convenience Stores",
            "type":"Retail Goods"
        }
    ],
    "sg:phone":"+1 678 773 2942",
    "sg:postcode":"30296",
    "sg:province":"GA",
    "sg:tags":[
        "juice",
        "bottler",
        "beverages-distributors"
    ],
    "wof:name":"Juice Plus",
    "wof:placetype":"venue"
},
  "geometry": {"coordinates":[-84.43038,33.562183],"type":"Point"}
}