{
  "type": "Feature",
  "properties": {
    "iso:country":"US",
    "sg:address":"7000 Peachtree Dunwoody Rd NE",
    "sg:city":"Atlanta",
    "sg:classifiers":[
        {
            "category":"Professional",
            "subcategory":"Business Services",
            "type":"Services"
        }
    ],
    "sg:phone":"+1 770 730 1654",
    "sg:postcode":"30328",
    "sg:province":"GA",
    "sg:tags":[
        "design"
    ],
    "wof:name":"Portfolio Interiors LLC",
    "wof:placetype":"venue"
},
  "geometry": {"coordinates":[-84.35391199999999,33.949818],"type":"Point"}
}