{
  "type": "Feature",
  "properties": {
    "addr:full":"586 B St Pine Mtn Valley GA 31823",
    "addr:housenumber":"586",
    "addr:postcode":"31823",
    "addr:street":"B St Pine Mtn",
    "iso:country":"US",
    "sg:address":"586 B St",
    "sg:city":"Pine Mtn Valley",
    "sg:classifiers":[
        {
            "category":"Home & Garden",
            "subcategory":"Furniture",
            "type":"Retail Goods"
        },
        {
            "category":"Home & Garden",
            "subcategory":"Garden Supply",
            "type":"Retail Goods"
        }
    ],
    "sg:phone":"+1 706 628 5334",
    "sg:postcode":"31823",
    "sg:province":"GA",
    "sg:tags":[
        "feeder",
        "house",
        "custom",
        "bird",
        "cabinet"
    ],
    "wof:name":"K Derums Cabinetmaker",
    "wof:placetype":"venue"
},
  "geometry": {"coordinates":[-84.82284799999999,32.790243],"type":"Point"}
}