{
  "type": "Feature",
  "properties": {
    "iso:country":"US",
    "sg:address":"160 Victory Dr",
    "sg:city":"Lyons",
    "sg:classifiers":[
        {
            "category":"Shopping",
            "subcategory":"Florist",
            "type":"Retail Goods"
        }
    ],
    "sg:phone":"+1 912 526 8541",
    "sg:postcode":"30436",
    "sg:province":"GA",
    "wof:name":"Ideal Pharmacy",
    "wof:placetype":"venue"
},
  "geometry": {"coordinates":[-82.32714799999999,32.200073],"type":"Point"}
}