{
  "type": "Feature",
  "properties": {
    "addr:full":"6432 Hwy 41 Ringgold GA 30736",
    "addr:housenumber":"6432",
    "addr:postcode":"30736",
    "addr:street":"Hwy 41",
    "iso:country":"US",
    "sg:address":"6432 Hwy 41",
    "sg:city":"Ringgold",
    "sg:classifiers":[
        {
            "category":"Retail",
            "subcategory":"Car Wash",
            "type":"Services"
        }
    ],
    "sg:phone":"+1 706 965 3075",
    "sg:postcode":"30736",
    "sg:province":"GA",
    "sg:tags":[
        "automobile",
        "detail",
        "clean"
    ],
    "wof:name":"Chambers Clean Up Shop",
    "wof:placetype":"venue"
},
  "geometry": {"coordinates":[-85.12835,34.921045],"type":"Point"}
}