{
  "type": "Feature",
  "properties": {
    "addr:full":"2325 Cheshire Bridge Rd NE Atlanta GA 30324",
    "addr:housenumber":"2325",
    "addr:postcode":"30324",
    "addr:street":"Cheshire Bridge Rd Ne",
    "iso:country":"US",
    "sg:address":"2325 Cheshire Bridge Rd NE",
    "sg:city":"Atlanta",
    "sg:classifiers":[
        {
            "category":"Food & Beverages",
            "subcategory":"Groceries & Convenience Stores",
            "type":"Retail Goods"
        }
    ],
    "sg:phone":"+1 404 638 1900",
    "sg:postcode":"30324",
    "sg:province":"GA",
    "sg:website":"www.publix.com/Home.do",
    "wof:name":"Publix",
    "wof:placetype":"venue"
},
  "geometry": {"coordinates":[-84.351716,33.818199],"type":"Point"}
}