{
  "type": "Feature",
  "properties": {
    "iso:country":"US",
    "sg:address":"296 College St",
    "sg:city":"Culloden",
    "sg:classifiers":[
        {
            "category":"Freight",
            "type":"Transportation"
        }
    ],
    "sg:phone":"+1 478 885 2222",
    "sg:postcode":"31016",
    "sg:province":"GA",
    "sg:tags":[
        "trucking"
    ],
    "wof:name":"International Cargo",
    "wof:placetype":"venue"
},
  "geometry": {"coordinates":[-84.094241,32.862205],"type":"Point"}
}