{
  "type": "Feature",
  "properties": {
    "addr:full":"35 Salem Branch Ct Covington GA 30016",
    "addr:housenumber":"35",
    "addr:postcode":"30016",
    "addr:street":"Salem Branch Ct",
    "iso:country":"US",
    "sg:address":"35 Salem Branch Ct",
    "sg:city":"Covington",
    "sg:classifiers":[
        {
            "category":"Utilities",
            "subcategory":"Cable",
            "type":"Services"
        }
    ],
    "sg:phone":"+1 770 787 5726",
    "sg:postcode":"30016",
    "sg:province":"GA",
    "sg:tags":[
        "television"
    ],
    "wof:name":"Rio Grande Cable",
    "wof:placetype":"venue"
},
  "geometry": {"coordinates":[-83.986525,33.571361],"type":"Point"}
}