{
  "type": "Feature",
  "properties": {
    "addr:full":"150 Shadinger Rd Carrollton GA 30116",
    "addr:housenumber":"150",
    "addr:postcode":"30116",
    "addr:street":"Shadinger Rd",
    "iso:country":"US",
    "sg:address":"150 Shadinger Rd",
    "sg:city":"Carrollton",
    "sg:classifiers":[
        {
            "category":"Farming",
            "subcategory":"Livestock Farm",
            "type":"Manufacturing & Wholesale Goods"
        }
    ],
    "sg:phone":"+1 770 832 6976",
    "sg:postcode":"30116",
    "sg:province":"GA",
    "sg:tags":[
        "beef",
        "feedlot",
        "cattle"
    ],
    "wof:name":"Jhs Farms Inc",
    "wof:placetype":"venue"
},
  "geometry": {"coordinates":[-85.07333300000001,33.523167],"type":"Point"}
}