{
  "type": "Feature",
  "properties": {
    "iso:country":"US",
    "sg:address":"3655 Roswell Rd NE Ste 216",
    "sg:city":"Atlanta",
    "sg:classifiers":[
        {
            "category":"Restaurant",
            "type":"Food & Drink"
        },
        {
            "category":"Food & Beverages",
            "subcategory":"Bakery",
            "type":"Retail Goods"
        }
    ],
    "sg:phone":"+1 404 239 9733",
    "sg:postcode":"30342",
    "sg:province":"GA",
    "sg:tags":[
        "sandwich",
        "pizza"
    ],
    "wof:name":"Marcello's Pizza & Subs",
    "wof:placetype":"venue"
},
  "geometry": {"coordinates":[-84.382599,33.854698],"type":"Point"}
}