{
  "type": "Feature",
  "properties": {
    "addr:full":"1210 Canton St Roswell GA 30075",
    "addr:housenumber":"1210",
    "addr:postcode":"30075",
    "addr:street":"Canton St",
    "iso:country":"US",
    "sg:address":"1210 Canton St",
    "sg:city":"Roswell",
    "sg:classifiers":[
        {
            "category":"Restaurant",
            "type":"Food & Drink"
        }
    ],
    "sg:menulink":"http://www.allmenus.com/ga/roswell-alpharetta/229555-rheas/menu/",
    "sg:phone":"+1 770 992 8638",
    "sg:postcode":"30075",
    "sg:province":"GA",
    "sg:tags":[
        "american"
    ],
    "wof:name":"Rheas",
    "wof:placetype":"venue"
},
  "geometry": {"coordinates":[-84.361374,34.031544],"type":"Point"}
}