{
  "type": "Feature",
  "properties": {
    "addr:full":"1994 Hosea L Williams Dr Atlanta GA 30317",
    "addr:housenumber":"1994",
    "addr:postcode":"30317",
    "addr:street":"Hosea L Williams Dr",
    "iso:country":"US",
    "sg:address":"1994 Hosea L Williams Dr",
    "sg:city":"Atlanta",
    "sg:classifiers":[
        {
            "category":"Fast Food",
            "type":"Food & Drink"
        },
        {
            "category":"Coffee & Tea",
            "type":"Food & Drink"
        },
        {
            "category":"Restaurant",
            "type":"Food & Drink"
        },
        {
            "category":"Bakery",
            "type":"Food & Drink"
        },
        {
            "category":"Tea Room",
            "subcategory":"None",
            "type":"Food & Drink"
        }
    ],
    "sg:phone":"+1 404 228 7369",
    "sg:postcode":"30317",
    "sg:province":"GA",
    "sg:tags":[
        "shop",
        "style",
        "family",
        "espresso",
        "pastry",
        "wedding",
        "cake",
        "take"
    ],
    "sg:website":"www.gatheringgroundskirkwood.com",
    "wof:name":"Gathering Grounds",
    "wof:placetype":"venue"
},
  "geometry": {"coordinates":[-84.32249299999999,33.751285],"type":"Point"}
}