{
  "type": "Feature",
  "properties": {
    "addr:full":"509 Summit Dr Albany GA 31707",
    "addr:housenumber":"509",
    "addr:postcode":"31707",
    "addr:street":"Summit Dr",
    "iso:country":"US",
    "sg:address":"509 Summit Dr",
    "sg:city":"Albany",
    "sg:classifiers":[
        {
            "category":"Building & Trades",
            "subcategory":"Construction",
            "type":"Services"
        }
    ],
    "sg:phone":"+1 229 888 7338",
    "sg:postcode":"31707",
    "sg:province":"GA",
    "sg:tags":[
        "house"
    ],
    "wof:name":"Security Contracting & Svcs",
    "wof:placetype":"venue"
},
  "geometry": {"coordinates":[-84.204162,31.58624],"type":"Point"}
}