{
  "type": "Feature",
  "properties": {
    "iso:country":"US",
    "sg:address":"1435 Boggs Rd",
    "sg:city":"Duluth",
    "sg:classifiers":[
        {
            "category":"Shopping",
            "subcategory":"Bicycles & Sporting Goods",
            "type":"Retail Goods"
        }
    ],
    "sg:phone":"+1 404 557 7926",
    "sg:postcode":"30096",
    "sg:province":"GA",
    "wof:name":"Sports Plus LLC",
    "wof:placetype":"venue"
},
  "geometry": {"coordinates":[-84.093948,33.954133],"type":"Point"}
}