{
  "type": "Feature",
  "properties": {
    "iso:country":"US",
    "sg:address":"204 N Elm St",
    "sg:city":"Rome",
    "sg:classifiers":[
        {
            "category":"Food & Beverages",
            "subcategory":"Groceries & Convenience Stores",
            "type":"Retail Goods"
        }
    ],
    "sg:phone":"+1 706 291 3898",
    "sg:postcode":"30165",
    "sg:province":"GA",
    "wof:name":"Elm Street Food & Beverage",
    "wof:placetype":"venue"
},
  "geometry": {"coordinates":[-85.20769,34.270924],"type":"Point"}
}