{
  "type": "Feature",
  "properties": {
    "iso:country":"US",
    "sg:address":"1570 Marble Way",
    "sg:city":"Lawrenceville",
    "sg:classifiers":[
        {
            "category":"Mining & Drilling",
            "type":"Manufacturing & Wholesale Goods"
        }
    ],
    "sg:phone":"+1 770 962 8855",
    "sg:postcode":"30043",
    "sg:province":"GA",
    "sg:tags":[
        "mineral"
    ],
    "wof:name":"J & D Fossils & Minerals",
    "wof:placetype":"venue"
},
  "geometry": {"coordinates":[-83.97569300000001,34.046662],"type":"Point"}
}