{
  "type": "Feature",
  "properties": {
    "iso:country":"US",
    "sg:address":"3124 Snapfinger Ct",
    "sg:city":"Decatur",
    "sg:classifiers":[
        {
            "category":"Building & Trades",
            "subcategory":"Construction",
            "type":"Services"
        }
    ],
    "sg:phone":"+1 678 428 8391",
    "sg:postcode":"30034",
    "sg:province":"GA",
    "sg:tags":[
        "hanging",
        "contractor"
    ],
    "wof:name":"Faux Effects By J H",
    "wof:placetype":"venue"
},
  "geometry": {"coordinates":[-84.20544099999999,33.694524],"type":"Point"}
}