{
  "type": "Feature",
  "properties": {
    "addr:full":"1300 E Broughton St Bainbridge GA 39817",
    "addr:housenumber":"1300",
    "addr:postcode":"39817",
    "addr:street":"E Broughton St",
    "iso:country":"US",
    "sg:address":"1300 E Broughton St",
    "sg:city":"Bainbridge",
    "sg:classifiers":[
        {
            "category":"Autos & Motor Vehicles",
            "subcategory":"Automobile Sales",
            "type":"Retail Goods"
        }
    ],
    "sg:phone":"+1 229 246 8616",
    "sg:postcode":"39817",
    "sg:province":"GA",
    "sg:tags":[
        "car",
        "dealer"
    ],
    "wof:name":"Gerald's Paint Body & Auto Sls",
    "wof:placetype":"venue"
},
  "geometry": {"coordinates":[-84.557845,30.905669],"type":"Point"}
}