{
  "type": "Feature",
  "properties": {
    "iso:country":"US",
    "sg:address":"74 Anderson Rd",
    "sg:city":"Griffin",
    "sg:classifiers":[
        {
            "category":"Professional",
            "subcategory":"Printing & Photocopies",
            "type":"Services"
        }
    ],
    "sg:phone":"+1 770 228 3504",
    "sg:postcode":"30223",
    "sg:province":"GA",
    "sg:tags":[
        "consultant"
    ],
    "wof:name":"Yellow Pages Yellowpages Co",
    "wof:placetype":"venue"
},
  "geometry": {"coordinates":[-84.39041,33.242164],"type":"Point"}
}