{
  "type": "Feature",
  "properties": {
    "addr:full":"2926 N Slappey Blvd Albany GA 31701",
    "addr:housenumber":"2926",
    "addr:postcode":"31701",
    "addr:street":"N Slappey Blvd",
    "iso:country":"US",
    "sg:address":"2926 N Slappey Blvd",
    "sg:city":"Albany",
    "sg:classifiers":[
        {
            "category":"Autos & Motor Vehicles",
            "subcategory":"Automobile Sales",
            "type":"Retail Goods"
        }
    ],
    "sg:phone":"+1 229 883 3100",
    "sg:postcode":"31701",
    "sg:province":"GA",
    "sg:tags":[
        "car",
        "township",
        "government-city",
        "village"
    ],
    "wof:name":"Ford Town Of Albany Inc",
    "wof:placetype":"venue"
},
  "geometry": {"coordinates":[-84.17697099999999,31.622589],"type":"Point"}
}