{
  "type": "Feature",
  "properties": {
    "addr:full":"400 Saddle Bridge Dr Alpharetta GA 30022",
    "addr:housenumber":"400",
    "addr:postcode":"30022",
    "addr:street":"Saddle Bridge Dr",
    "iso:country":"US",
    "sg:address":"400 Saddle Bridge Dr",
    "sg:city":"Alpharetta",
    "sg:classifiers":[
        {
            "category":"Manufacturing",
            "subcategory":"Printing",
            "type":"Manufacturing & Wholesale Goods"
        }
    ],
    "sg:phone":"+1 678 762 0187",
    "sg:postcode":"30022",
    "sg:province":"GA",
    "sg:tags":[
        "publishing"
    ],
    "wof:name":"Eera Info Inc",
    "wof:placetype":"venue"
},
  "geometry": {"coordinates":[-84.218369,34.049149],"type":"Point"}
}