{
  "type": "Feature",
  "properties": {
    "addr:full":"6631 Roswell Rd Atlanta GA 30328",
    "addr:housenumber":"6631",
    "addr:postcode":"30328",
    "addr:street":"Roswell Rd",
    "iso:country":"US",
    "sg:address":"6631 Roswell Rd",
    "sg:city":"Atlanta",
    "sg:classifiers":[
        {
            "category":"Food & Beverages",
            "subcategory":"Specialty",
            "type":"Retail Goods"
        }
    ],
    "sg:phone":"+1 404 843 2290",
    "sg:postcode":"30328",
    "sg:province":"GA",
    "sg:tags":[
        "health",
        "diet"
    ],
    "wof:name":"GNC",
    "wof:placetype":"venue"
},
  "geometry": {"coordinates":[-84.378292,33.936906],"type":"Point"}
}