{
  "type": "Feature",
  "properties": {
    "addr:full":"103 Westport Pl Peachtree City GA 30265",
    "addr:housenumber":"103",
    "addr:postcode":"30265",
    "addr:street":"Westport Pl",
    "iso:country":"US",
    "sg:address":"103 Westport Pl",
    "sg:city":"Peachtree City",
    "sg:classifiers":[
        {
            "category":"Real Estate",
            "subcategory":"Surveying",
            "type":"Services"
        }
    ],
    "sg:phone":"+1 770 486 7552",
    "sg:postcode":"30265",
    "sg:province":"GA",
    "sg:tags":[
        "surveyor"
    ],
    "wof:name":"W D Gray & Assoc",
    "wof:placetype":"venue"
},
  "geometry": {"coordinates":[-84.710724,33.350119],"type":"Point"}
}