{
  "type": "Feature",
  "properties": {
    "addr:full":"810 Georgia Ave Americus GA 31719",
    "addr:housenumber":"810",
    "addr:postcode":"31719",
    "addr:street":"Georgia Ave",
    "iso:country":"US",
    "sg:address":"810 Georgia Ave",
    "sg:city":"Americus",
    "sg:classifiers":[
        {
            "category":"Wholesale",
            "subcategory":"Stationery",
            "type":"Manufacturing & Wholesale Goods"
        }
    ],
    "sg:phone":"+1 229 931 2407",
    "sg:postcode":"31719",
    "sg:province":"GA",
    "sg:tags":[
        "supply"
    ],
    "wof:name":"Surplus & Supply",
    "wof:placetype":"venue"
},
  "geometry": {"coordinates":[-84.244445,32.089767],"type":"Point"}
}