{
  "type": "Feature",
  "properties": {
    "addr:full":"3500 Annandale Ln Suwanee GA 30024",
    "addr:housenumber":"3500",
    "addr:postcode":"30024",
    "addr:street":"Annandale Ln",
    "iso:country":"US",
    "sg:address":"3500 Annandale Ln",
    "sg:city":"Suwanee",
    "sg:classifiers":[
        {
            "category":"Health Services",
            "subcategory":"Clinic",
            "type":"Services"
        }
    ],
    "sg:phone":"+1 770 904 5020",
    "sg:postcode":"30024",
    "sg:province":"GA",
    "sg:tags":[
        "rehabilitation"
    ],
    "sg:website":"http://www.sundancerehab.com",
    "wof:name":"SunDance Rehabilitation",
    "wof:placetype":"venue"
},
  "geometry": {"coordinates":[-84.06353799999999,34.038315],"type":"Point"}
}