{
  "type": "Feature",
  "properties": {
    "addr:full":"906 Amber Dr Columbus GA 31907",
    "addr:housenumber":"906",
    "addr:postcode":"31907",
    "addr:street":"Amber Dr",
    "iso:country":"US",
    "sg:address":"906 Amber Dr",
    "sg:city":"Columbus",
    "sg:classifiers":[
        {
            "category":"Retail",
            "subcategory":"Car Wash",
            "type":"Services"
        }
    ],
    "sg:phone":"+1 706 569 5697",
    "sg:postcode":"31907",
    "sg:province":"GA",
    "sg:tags":[
        "carwash"
    ],
    "wof:name":"Richards Express Wash",
    "wof:placetype":"venue"
},
  "geometry": {"coordinates":[-84.89226499999999,32.465257],"type":"Point"}
}