{
  "type": "Feature",
  "properties": {
    "addr:full":"81 Peachtree Park Dr NE Atlanta GA 30309",
    "addr:housenumber":"81",
    "addr:postcode":"30309",
    "addr:street":"Peachtree Park Dr Ne",
    "iso:country":"US",
    "sg:address":"81 Peachtree Park Dr NE",
    "sg:city":"Atlanta",
    "sg:classifiers":[
        {
            "category":"Organizations",
            "subcategory":"Religious Organization",
            "type":"Services"
        }
    ],
    "sg:phone":"+1 404 605 0202",
    "sg:postcode":"30309",
    "sg:province":"GA",
    "wof:name":"Christ Church",
    "wof:placetype":"venue"
},
  "geometry": {"coordinates":[-84.38913599999999,33.812377],"type":"Point"}
}