{
  "type": "Feature",
  "properties": {
    "addr:full":"642 Shurling Dr Macon GA 31211",
    "addr:housenumber":"642",
    "addr:postcode":"31211",
    "addr:street":"Shurling Dr",
    "iso:country":"US",
    "sg:address":"642 Shurling Dr",
    "sg:city":"Macon",
    "sg:classifiers":[
        {
            "category":"Shopping",
            "subcategory":"Clothing, Apparel, & Fashions",
            "type":"Retail Goods"
        }
    ],
    "sg:phone":"+1 478 741 9677",
    "sg:postcode":"31211",
    "sg:province":"GA",
    "sg:tags":[
        "sporting"
    ],
    "wof:name":"Team Sports Inc",
    "wof:placetype":"venue"
},
  "geometry": {"coordinates":[-83.613134,32.859672],"type":"Point"}
}