{
  "type": "Feature",
  "properties": {
    "addr:full":"1155 5th St SE Cairo GA 39828",
    "addr:housenumber":"1155",
    "addr:postcode":"39828",
    "addr:street":"5Th St Se",
    "iso:country":"US",
    "sg:address":"1155 5th St SE",
    "sg:city":"Cairo",
    "sg:classifiers":[
        {
            "category":"Health Services",
            "subcategory":"Hospital",
            "type":"Services"
        }
    ],
    "sg:phone":"+1 229 377 1150",
    "sg:postcode":"39828",
    "sg:province":"GA",
    "wof:name":"Grady General Hospital",
    "wof:placetype":"venue"
},
  "geometry": {"coordinates":[-84.200264,30.863636],"type":"Point"}
}