{
  "type": "Feature",
  "properties": {
    "addr:full":"2 Skidaway Village Sq Savannah GA 31411",
    "addr:housenumber":"2",
    "addr:postcode":"31411",
    "addr:street":"Skidaway Village Sq",
    "iso:country":"US",
    "sg:address":"2 Skidaway Village Sq",
    "sg:city":"Savannah",
    "sg:classifiers":[
        {
            "category":"Banks & Credit Unions",
            "subcategory":"Investment Brokerage",
            "type":"Services"
        }
    ],
    "sg:phone":"+1 912 598 3140",
    "sg:postcode":"31411",
    "sg:province":"GA",
    "sg:tags":[
        "invest",
        "security",
        "commodity",
        "contract"
    ],
    "wof:name":"Wachovia Securities LLC",
    "wof:placetype":"venue"
},
  "geometry": {"coordinates":[-81.052238,31.940838],"type":"Point"}
}