{
  "type": "Feature",
  "properties": {
    "addr:full":"265 Peachtree St NE Atlanta GA 30303",
    "addr:housenumber":"265",
    "addr:postcode":"30303",
    "addr:street":"Peachtree St Ne",
    "iso:country":"US",
    "sg:address":"265 Peachtree St NE",
    "sg:city":"Atlanta",
    "sg:classifiers":[
        {
            "category":"Shopping",
            "subcategory":"Gifts & Souvenirs",
            "type":"Retail Goods"
        }
    ],
    "sg:phone":"+1 404 577 2683",
    "sg:postcode":"30303",
    "sg:province":"GA",
    "sg:tags":[
        "shop"
    ],
    "wof:name":"W H Smith",
    "wof:placetype":"venue"
},
  "geometry": {"coordinates":[-84.38748099999999,33.761129],"type":"Point"}
}