{
  "type": "Feature",
  "properties": {
    "iso:country":"US",
    "sg:address":"504 Stuart Ct",
    "sg:city":"Savannah",
    "sg:classifiers":[
        {
            "category":"Real Estate",
            "subcategory":"Real Estate Services",
            "type":"Services"
        },
        {
            "category":"Real Estate",
            "subcategory":"Real Estate Agent",
            "type":"Services"
        }
    ],
    "sg:phone":"+1 912 355 5598",
    "sg:postcode":"31405",
    "sg:province":"GA",
    "sg:tags":[
        "buyer",
        "broker"
    ],
    "wof:name":"Allan L Cooper Rl Est",
    "wof:placetype":"venue"
},
  "geometry": {"coordinates":[-81.102588,32.016335],"type":"Point"}
}