{
  "type": "Feature",
  "properties": {
    "addr:full":"3565 Austell Rd SW Ste 5A Marietta GA 30008",
    "addr:housenumber":"3565",
    "addr:postcode":"30008",
    "addr:street":"Austell Rd Sw Ste 5A",
    "iso:country":"US",
    "sg:address":"3565 Austell Rd SW Ste 5A",
    "sg:city":"Marietta",
    "sg:classifiers":[
        {
            "category":"Personal",
            "subcategory":"Nail Salon",
            "type":"Services"
        }
    ],
    "sg:phone":"+1 770 432 5959",
    "sg:postcode":"30008",
    "sg:province":"GA",
    "wof:name":"Nail Time",
    "wof:placetype":"venue"
},
  "geometry": {"coordinates":[-84.592201,33.868],"type":"Point"}
}