{
  "type": "Feature",
  "properties": {
    "iso:country":"US",
    "sg:address":"203 Commerce Ave",
    "sg:city":"Lagrange",
    "sg:classifiers":[
        {
            "category":"Personal",
            "subcategory":"Beauty Salon",
            "type":"Services"
        }
    ],
    "sg:phone":"+1 706 837 9000",
    "sg:postcode":"30241",
    "sg:province":"GA",
    "sg:tags":[
        "shop",
        "manicuring"
    ],
    "wof:name":"Lagrange Nail Salon",
    "wof:placetype":"venue"
},
  "geometry": {"coordinates":[-85.022468,33.049427],"type":"Point"}
}