{
  "type": "Feature",
  "properties": {
    "addr:full":"4184 Treaddur Bay Ln NW Norcross GA 30092",
    "addr:housenumber":"4184",
    "addr:postcode":"30092",
    "addr:street":"Treaddur Bay Ln Nw",
    "iso:country":"US",
    "sg:address":"4184 Treaddur Bay Ln NW",
    "sg:city":"Norcross",
    "sg:classifiers":[
        {
            "category":"Building & Trades",
            "subcategory":"Construction",
            "type":"Services"
        }
    ],
    "sg:phone":"+1 770 446 5959",
    "sg:postcode":"30092",
    "sg:province":"GA",
    "sg:tags":[
        "house"
    ],
    "wof:name":"Pete Witalis Homes Inc",
    "wof:placetype":"venue"
},
  "geometry": {"coordinates":[-84.22338999999999,33.98784],"type":"Point"}
}