{
  "type": "Feature",
  "properties": {
    "addr:full":"937 Greene St Augusta GA 30901",
    "addr:housenumber":"937",
    "addr:postcode":"30901",
    "addr:street":"Greene St",
    "iso:country":"US",
    "sg:address":"937 Greene St",
    "sg:city":"Augusta",
    "sg:classifiers":[
        {
            "category":"Building & Trades",
            "subcategory":"Construction",
            "type":"Services"
        }
    ],
    "sg:phone":"+1 706 722 7664",
    "sg:postcode":"30901",
    "sg:province":"GA",
    "sg:tags":[
        "contractor"
    ],
    "wof:name":"Williams Construction Co",
    "wof:placetype":"venue"
},
  "geometry": {"coordinates":[-81.969838,33.474696],"type":"Point"}
}