{
  "type": "Feature",
  "properties": {
    "iso:country":"US",
    "sg:address":"3750 Turner Heights Dr",
    "sg:city":"Decatur",
    "sg:classifiers":[
        {
            "category":"Professional",
            "subcategory":"Management & Consulting",
            "type":"Services"
        }
    ],
    "sg:phone":"+1 404 286 5378",
    "sg:postcode":"30032",
    "sg:province":"GA",
    "sg:tags":[
        "fire",
        "consultant",
        "protection"
    ],
    "wof:name":"Sympo King Productions",
    "wof:placetype":"venue"
},
  "geometry": {"coordinates":[-84.23732,33.751956],"type":"Point"}
}