{
  "type": "Feature",
  "properties": {
    "iso:country":"US",
    "sg:address":"2860 Cobb Pkwy S",
    "sg:city":"Atlanta",
    "sg:classifiers":[
        {
            "category":"Professional",
            "subcategory":"Accounting & Tax Preparation",
            "type":"Services"
        }
    ],
    "sg:phone":"+1 770 437 0411",
    "sg:postcode":"30339",
    "sg:province":"GA",
    "sg:tags":[
        "return",
        "filing"
    ],
    "wof:name":"Jackson Hewitt Tax Svc",
    "wof:placetype":"venue"
},
  "geometry": {"coordinates":[-84.467195,33.882341],"type":"Point"}
}