{
  "type": "Feature",
  "properties": {
    "addr:city":"Atlanta",
    "addr:full":"156 Heaton Park Drive Ne Atlanta, Ga 30307-1398",
    "addr:house_number":"156",
    "addr:housenumber":"156",
    "addr:phone":"+1 404-378-4311",
    "addr:postcode":"30307-1398",
    "addr:road":"Heaton Park Drive Ne",
    "addr:state":"GA",
    "addr:street":"Heaton Park Dr Ne",
    "iso:country":"US",
    "sg:address":"156 Heaton Park Dr NE",
    "sg:city":"Atlanta",
    "sg:phone":"+1 678 874 7102",
    "sg:postcode":"30307",
    "sg:province":"GA",
    "sg:website":"http://www.dekalb.k12.ga.us",
    "wof:airports":[
        102525899,
        102526927
    ],
    "wof:name":"Fernbank Science Center",
    "wof:placetype":"venue"
},
  "geometry": {"coordinates":[-84.31723,33.77846],"type":"Point"}
}