{
  "type": "Feature",
  "properties": {
    "iso:country":"US",
    "sg:address":"156 Heaton Park Dr NE",
    "sg:city":"Atlanta",
    "sg:phone":"+1 678 874 7102",
    "sg:postcode":"30307",
    "sg:province":"GA",
    "sg:website":"http://www.dekalb.k12.ga.us",
    "wof:name":"Fernbank Science Center",
    "wof:placetype":"venue"
},
  "geometry": {"coordinates":[-84.317123,33.778761],"type":"Point"}
}