{
  "type": "Feature",
  "properties": {
    "addr:full":"4435 Acworth Industrial Dr NW Acworth GA 30101",
    "addr:housenumber":"4435",
    "addr:postcode":"30101",
    "addr:street":"Acworth Industrial Dr Nw",
    "iso:country":"US",
    "sg:address":"4435 Acworth Industrial Dr NW",
    "sg:city":"Acworth",
    "sg:classifiers":[
        {
            "category":"Home & Garden",
            "subcategory":"Household Appliances",
            "type":"Retail Goods"
        },
        {
            "category":"Retail",
            "subcategory":"Laundry & Dry Cleaning",
            "type":"Services"
        },
        {
            "category":"Home & Garden",
            "subcategory":"Carpets & Floor Coverings",
            "type":"Retail Goods"
        },
        {
            "category":"Manufacturing",
            "subcategory":"Tools & Machinery",
            "type":"Manufacturing & Wholesale Goods"
        },
        {
            "category":"Utilities",
            "subcategory":"Water",
            "type":"Services"
        },
        {
            "category":"Personal",
            "type":"Services"
        },
        {
            "category":"Building & Trades",
            "subcategory":"Cleaning & Sanitation",
            "type":"Services"
        }
    ],
    "sg:phone":"+1 770 514 1789",
    "sg:postcode":"30101",
    "sg:province":"GA",
    "sg:tags":[
        "control",
        "cleaner",
        "duct",
        "house",
        "mold",
        "equipment",
        "damage",
        "extraction",
        "cleaning-industrial",
        "curtain",
        "drapery",
        "counteracting",
        "emergency",
        "fire",
        "cleaners-water",
        "odor",
        "rug",
        "restoration",
        "vacuum",
        "remediation",
        "upholstery",
        "flood",
        "air",
        "waxing",
        "ventilation",
        "smoke",
        "polishing"
    ],
    "sg:website":"http://www.servicemasterclean.com/reslf/smclean_leadform.asp?url=http://www.servicemasterclean.com/reslf/smclean_leadform.asp&partnerName=YellowPages.com&adName=yptl&HGProp=SMClean",
    "wof:name":"ServiceMaster Clean",
    "wof:placetype":"venue"
},
  "geometry": {"coordinates":[-84.660421,34.062812],"type":"Point"}
}