{
  "type": "Feature",
  "properties": {
    "iso:country":"US",
    "sg:address":"2222 Country Farm Ln",
    "sg:city":"Blairsville",
    "sg:classifiers":[
        {
            "category":"Travel",
            "subcategory":"Hotels & Motels",
            "type":"Entertainment"
        }
    ],
    "sg:phone":"+1 706 745 1560",
    "sg:postcode":"30512",
    "sg:province":"GA",
    "sg:tags":[
        "operation",
        "chalet",
        "rental",
        "cabin"
    ],
    "sg:website":"www.godscountryfarm.com",
    "wof:name":"God's Country Farm",
    "wof:placetype":"venue"
},
  "geometry": {"coordinates":[-84.091167,34.908705],"type":"Point"}
}