{
  "type": "Feature",
  "properties": {
    "addr:full":"3524 Palisade Cove Dr Duluth GA 30096",
    "addr:housenumber":"3524",
    "addr:postcode":"30096",
    "addr:street":"Palisade Cove Dr",
    "iso:country":"US",
    "sg:address":"3524 Palisade Cove Dr",
    "sg:city":"Duluth",
    "sg:classifiers":[
        {
            "category":"Professional",
            "subcategory":"Management & Consulting",
            "type":"Services"
        }
    ],
    "sg:phone":"+1 678 480 8853",
    "sg:postcode":"30096",
    "sg:province":"GA",
    "sg:tags":[
        "consultant"
    ],
    "wof:name":"Radiant Technologies Inc",
    "wof:placetype":"venue"
},
  "geometry": {"coordinates":[-84.15797499999999,33.992214],"type":"Point"}
}