{
  "type": "Feature",
  "properties": {
    "addr:full":"2818 Lawrence Pl Augusta GA 30909",
    "addr:housenumber":"2818",
    "addr:postcode":"30909",
    "addr:street":"Lawrence Pl",
    "iso:country":"US",
    "sg:address":"2818 Lawrence Pl",
    "sg:city":"Augusta",
    "sg:classifiers":[
        {
            "category":"Retail",
            "subcategory":"Laundry & Dry Cleaning",
            "type":"Services"
        }
    ],
    "sg:phone":"+1 706 733 3084",
    "sg:postcode":"30909",
    "sg:province":"GA",
    "sg:tags":[
        "cleaners"
    ],
    "wof:name":"Dry Cleaning To Your Door",
    "wof:placetype":"venue"
},
  "geometry": {"coordinates":[-82.036385,33.498258],"type":"Point"}
}