{
  "type": "Feature",
  "properties": {
    "addr:full":"502 E River St Savannah GA 31401",
    "addr:housenumber":"502",
    "addr:postcode":"31401",
    "addr:street":"E River St",
    "iso:country":"US",
    "sg:address":"502 E River St",
    "sg:city":"Savannah",
    "sg:classifiers":[
        {
            "category":"Shopping",
            "subcategory":"Gifts & Souvenirs",
            "type":"Retail Goods"
        }
    ],
    "sg:phone":"+1 912 238 4004",
    "sg:postcode":"31401",
    "sg:province":"GA",
    "wof:name":"Southern Flair",
    "wof:placetype":"venue"
},
  "geometry": {"coordinates":[-81.08345,32.079617],"type":"Point"}
}