{
  "type": "Feature",
  "properties": {
    "addr:full":"2095 Clayburn Dr Cumming GA 30040",
    "addr:housenumber":"2095",
    "addr:postcode":"30040",
    "addr:street":"Clayburn Dr",
    "iso:country":"US",
    "sg:address":"2095 Clayburn Dr",
    "sg:city":"Cumming",
    "sg:classifiers":[
        {
            "category":"Professional",
            "subcategory":"Business Services",
            "type":"Services"
        }
    ],
    "sg:phone":"+1 770 205 0666",
    "sg:postcode":"30040",
    "sg:province":"GA",
    "wof:name":"Gold Coast Partners Inc",
    "wof:placetype":"venue"
},
  "geometry": {"coordinates":[-84.114906,34.243309],"type":"Point"}
}