{
  "type": "Feature",
  "properties": {
    "addr:full":"2109 Avalon Rd Columbus GA 31907",
    "addr:housenumber":"2109",
    "addr:postcode":"31907",
    "addr:street":"Avalon Rd",
    "iso:country":"US",
    "sg:address":"2109 Avalon Rd",
    "sg:city":"Columbus",
    "sg:classifiers":[
        {
            "category":"Home & Garden",
            "subcategory":"Building Materials",
            "type":"Retail Goods"
        },
        {
            "category":"Building & Trades",
            "subcategory":"Construction",
            "type":"Services"
        }
    ],
    "sg:phone":"+1 706 332 2804",
    "sg:postcode":"31907",
    "sg:province":"GA",
    "sg:tags":[
        "repair",
        "bathroom",
        "roofing",
        "altering",
        "improvement",
        "concrete",
        "maintenance",
        "contractor",
        "remodeling"
    ],
    "wof:name":"Early Morning Remodeler Inc",
    "wof:placetype":"venue"
},
  "geometry": {"coordinates":[-84.921176,32.482489],"type":"Point"}
}