{
  "type": "Feature",
  "properties": {
    "iso:country":"US",
    "sg:address":"607 Whisperwill Dr",
    "sg:city":"Marietta",
    "sg:classifiers":[
        {
            "category":"Building & Trades",
            "subcategory":"Construction",
            "type":"Services"
        }
    ],
    "sg:phone":"+1 770 516 8841",
    "sg:postcode":"30066",
    "sg:province":"GA",
    "sg:tags":[
        "contractor",
        "mason"
    ],
    "wof:name":"Lem Masonry Inc",
    "wof:placetype":"venue"
},
  "geometry": {"coordinates":[-84.53289599999999,34.043941],"type":"Point"}
}