{
  "type": "Feature",
  "properties": {
    "iso:country":"US",
    "sg:address":"6581 Garrett Rd",
    "sg:city":"Buford",
    "sg:classifiers":[
        {
            "category":"Government",
            "subcategory":"Office",
            "type":"Public Place"
        }
    ],
    "sg:phone":"+1 770 271 7549",
    "sg:postcode":"30518",
    "sg:province":"GA",
    "sg:tags":[
        "national",
        "security"
    ],
    "wof:name":"Robbies Marine Services Inc",
    "wof:placetype":"venue"
},
  "geometry": {"coordinates":[-84.04432199999999,34.153377],"type":"Point"}
}