{
  "type": "Feature",
  "properties": {
    "iso:country":"US",
    "sg:address":"145 Nassau St NW",
    "sg:city":"Atlanta",
    "sg:classifiers":[
        {
            "category":"Social Services",
            "type":"Services"
        }
    ],
    "sg:phone":"+1 404 614 0040",
    "sg:postcode":"30303",
    "sg:province":"GA",
    "wof:name":"Youth Comm Vox Teen Newsppr",
    "wof:placetype":"venue"
},
  "geometry": {"coordinates":[-84.391876,33.758401],"type":"Point"}
}