{
  "type": "Feature",
  "properties": {
    "iso:country":"US",
    "sg:address":"2073 Blackberry Ln",
    "sg:city":"Auburn",
    "sg:classifiers":[
        {
            "category":"Shopping",
            "subcategory":"Gifts & Souvenirs",
            "type":"Retail Goods"
        }
    ],
    "sg:phone":"+1 770 339 9763",
    "sg:postcode":"30011",
    "sg:province":"GA",
    "wof:name":"Gift Box Company",
    "wof:placetype":"venue"
},
  "geometry": {"coordinates":[-83.86100999999999,34.025453],"type":"Point"}
}