{
  "type": "Feature",
  "properties": {
    "iso:country":"US",
    "sg:address":"3591 Clearview Pkwy",
    "sg:city":"Atlanta",
    "sg:classifiers":[
        {
            "category":"Manufacturing",
            "subcategory":"Tools & Machinery",
            "type":"Manufacturing & Wholesale Goods"
        }
    ],
    "sg:phone":"+1 770 455 1313",
    "sg:postcode":"30340",
    "sg:province":"GA",
    "sg:tags":[
        "body",
        "automobile",
        "shop",
        "equipment"
    ],
    "wof:name":"Power Sales",
    "wof:placetype":"venue"
},
  "geometry": {"coordinates":[-84.26945499999999,33.897567],"type":"Point"}
}