{
  "type": "Feature",
  "properties": {
    "addr:full":"1880 Johnson Rd NE Atlanta GA 30306",
    "addr:housenumber":"1880",
    "addr:postcode":"30306",
    "addr:street":"Johnson Rd Ne",
    "iso:country":"US",
    "sg:address":"1880 Johnson Rd NE",
    "sg:city":"Atlanta",
    "sg:classifiers":[
        {
            "category":"Professional",
            "subcategory":"Detective & Security Services",
            "type":"Services"
        }
    ],
    "sg:phone":"+1 404 874 2423",
    "sg:postcode":"30306",
    "sg:province":"GA",
    "sg:tags":[
        "guard",
        "patrol"
    ],
    "wof:name":"Argenbright Transportation",
    "wof:placetype":"venue"
},
  "geometry": {"coordinates":[-84.33927300000001,33.80404],"type":"Point"}
}