{
  "type": "Feature",
  "properties": {
    "iso:country":"US",
    "sg:address":"2535 Ivey Rd",
    "sg:city":"Augusta",
    "sg:classifiers":[
        {
            "category":"Utilities",
            "subcategory":"Telephone",
            "type":"Services"
        }
    ],
    "sg:phone":"+1 706 798 8590",
    "sg:postcode":"30906",
    "sg:province":"GA",
    "sg:tags":[
        "communications"
    ],
    "wof:name":"Bunch Busines Bldrs",
    "wof:placetype":"venue"
},
  "geometry": {"coordinates":[-82.02481400000001,33.433029],"type":"Point"}
}