{
  "type": "Feature",
  "properties": {
    "addr:full":"4750 Janice Dr Atlanta GA 30337",
    "addr:housenumber":"4750",
    "addr:postcode":"30337",
    "addr:street":"Janice Dr",
    "iso:country":"US",
    "sg:address":"4750 Janice Dr",
    "sg:city":"Atlanta",
    "sg:classifiers":[
        {
            "category":"Organizations",
            "subcategory":"Membership Organization",
            "type":"Services"
        }
    ],
    "sg:phone":"+1 404 559 1858",
    "sg:postcode":"30337",
    "sg:province":"GA",
    "wof:name":"Hand & Hands Community Svc Ctr",
    "wof:placetype":"venue"
},
  "geometry": {"coordinates":[-84.479484,33.631324],"type":"Point"}
}