{
  "type": "Feature",
  "properties": {
    "iso:country":"US",
    "sg:address":"845 Soaring Dr",
    "sg:city":"Marietta",
    "sg:classifiers":[
        {
            "category":"Professional",
            "subcategory":"Computer Services",
            "type":"Services"
        }
    ],
    "sg:phone":"+1 770 429 1471",
    "sg:postcode":"30062",
    "sg:province":"GA",
    "sg:tags":[
        "programing",
        "custom"
    ],
    "wof:name":"Scientific Art Inc",
    "wof:placetype":"venue"
},
  "geometry": {"coordinates":[-84.510586,33.970232],"type":"Point"}
}