{
  "type": "Feature",
  "properties": {
    "addr:full":"3455 Peachtree Rd NE Ste 100 Atlanta GA 30326",
    "addr:housenumber":"3455",
    "addr:postcode":"30326",
    "addr:street":"Peachtree Rd Ne Ste 100",
    "iso:country":"US",
    "sg:address":"3455 Peachtree Rd NE Ste 100",
    "sg:city":"Atlanta",
    "sg:classifiers":[
        {
            "category":"Wholesale",
            "subcategory":"Furniture",
            "type":"Manufacturing & Wholesale Goods"
        },
        {
            "category":"Home & Garden",
            "subcategory":"Furniture",
            "type":"Retail Goods"
        }
    ],
    "sg:phone":"+1 404 266 1911",
    "sg:postcode":"30326",
    "sg:province":"GA",
    "sg:tags":[
        "store",
        "furniture-wholesale",
        "manufacturer"
    ],
    "sg:website":"http://www.tekus.com",
    "wof:name":"Teknion",
    "wof:placetype":"venue"
},
  "geometry": {"coordinates":[-84.361504,33.850899],"type":"Point"}
}