{
  "type": "Feature",
  "properties": {
    "addr:full":"1700 Jeurgens Ct Norcross GA 30093",
    "addr:housenumber":"1700",
    "addr:postcode":"30093",
    "addr:street":"Jeurgens Ct",
    "iso:country":"US",
    "sg:address":"1700 Jeurgens Ct",
    "sg:city":"Norcross",
    "sg:classifiers":[
        {
            "category":"Professional",
            "type":"Services"
        },
        {
            "category":"Retail",
            "subcategory":"Event Space",
            "type":"Services"
        },
        {
            "category":"Conference Center",
            "type":"Public Place"
        }
    ],
    "sg:phone":"+1 770 279 9899",
    "sg:postcode":"30093",
    "sg:province":"GA",
    "sg:tags":[
        "fair",
        "facility",
        "venue",
        "trade",
        "exposition",
        "convention",
        "shows"
    ],
    "sg:website":"www.northatlantatradecenter.com",
    "wof:name":"North Atlanta Trade Center",
    "wof:placetype":"venue"
},
  "geometry": {"coordinates":[-84.181099,33.920101],"type":"Point"}
}