{
  "type": "Feature",
  "properties": {
    "addr:full":"54 Mimosa St Midway GA 31320",
    "addr:housenumber":"54",
    "addr:postcode":"31320",
    "addr:street":"Mimosa St",
    "iso:country":"US",
    "sg:address":"54 Mimosa St",
    "sg:city":"Midway",
    "sg:classifiers":[
        {
            "category":"Professional",
            "subcategory":"Computer Services",
            "type":"Services"
        }
    ],
    "sg:phone":"+1 912 272 9995",
    "sg:postcode":"31320",
    "sg:province":"GA",
    "sg:tags":[
        "information",
        "designer",
        "technology",
        "system",
        "consultant"
    ],
    "wof:name":"Megabytes Inc",
    "wof:placetype":"venue"
},
  "geometry": {"coordinates":[-81.391245,31.81004],"type":"Point"}
}