{
  "type": "Feature",
  "properties": {
    "addr:full":"2474 Old Toney Rd Ellenwood GA 30294",
    "addr:housenumber":"2474",
    "addr:postcode":"30294",
    "addr:street":"Old Toney Rd",
    "iso:country":"US",
    "sg:address":"2474 Old Toney Rd",
    "sg:city":"Ellenwood",
    "sg:classifiers":[
        {
            "category":"Personal",
            "subcategory":"Beauty Salon",
            "type":"Services"
        }
    ],
    "sg:phone":"+1 770 361 6464",
    "sg:postcode":"30294",
    "sg:province":"GA",
    "wof:name":"SRD Anointed Hair Salon",
    "wof:placetype":"venue"
},
  "geometry": {"coordinates":[-84.310526,33.624795],"type":"Point"}
}