{
  "type": "Feature",
  "properties": {
    "addr:full":"223 Ponce de Leon Ave NE Atlanta GA 30308",
    "addr:housenumber":"223",
    "addr:postcode":"30308",
    "addr:street":"Ponce De Leon Ave Ne",
    "iso:country":"US",
    "sg:address":"223 Ponce de Leon Ave NE",
    "sg:city":"Atlanta",
    "sg:classifiers":[
        {
            "category":"Travel",
            "subcategory":"Bed & Breakfast",
            "type":"Entertainment"
        }
    ],
    "sg:phone":"+1 404 875 9449",
    "sg:postcode":"30308",
    "sg:province":"GA",
    "sg:tags":[
        "inn"
    ],
    "sg:website":"http://www.atlantahostel.com",
    "wof:name":"Atlanta Hostel",
    "wof:placetype":"venue"
},
  "geometry": {"coordinates":[-84.38039000000001,33.772565],"type":"Point"}
}