{
  "type": "Feature",
  "properties": {
    "addr:full":"241 Cummings Rd Ringgold GA 30736",
    "addr:housenumber":"241",
    "addr:postcode":"30736",
    "addr:street":"Cummings Rd",
    "iso:country":"US",
    "sg:address":"241 Cummings Rd",
    "sg:city":"Ringgold",
    "sg:classifiers":[
        {
            "category":"Professional",
            "subcategory":"Detective & Security Services",
            "type":"Services"
        }
    ],
    "sg:phone":"+1 706 935 3202",
    "sg:postcode":"30736",
    "sg:province":"GA",
    "sg:tags":[
        "information",
        "bureau"
    ],
    "wof:name":"Thomas Services",
    "wof:placetype":"venue"
},
  "geometry": {"coordinates":[-85.148251,34.904773],"type":"Point"}
}