{
  "type": "Feature",
  "properties": {
    "addr:full":"4085 Hillcrest View Ct Suwanee GA 30024",
    "addr:housenumber":"4085",
    "addr:postcode":"30024",
    "addr:street":"Hillcrest View Ct",
    "iso:country":"US",
    "sg:address":"4085 Hillcrest View Ct",
    "sg:city":"Suwanee",
    "sg:classifiers":[
        {
            "category":"Retail",
            "subcategory":"Auto Repair",
            "type":"Services"
        }
    ],
    "sg:phone":"+1 770 831 1252",
    "sg:postcode":"30024",
    "sg:province":"GA",
    "wof:name":"Win Auto",
    "wof:placetype":"venue"
},
  "geometry": {"coordinates":[-84.044183,34.072125],"type":"Point"}
}