{
  "type": "Feature",
  "properties": {
    "iso:country":"US",
    "sg:address":"72 Cordell Dr",
    "sg:city":"Rossville",
    "sg:classifiers":[
        {
            "category":"Professional",
            "subcategory":"Secretarial Services",
            "type":"Services"
        }
    ],
    "sg:phone":"+1 706 858 6387",
    "sg:postcode":"30741",
    "sg:province":"GA",
    "sg:tags":[
        "assistant",
        "court",
        "hearing"
    ],
    "wof:name":"Georgia S Carr",
    "wof:placetype":"venue"
},
  "geometry": {"coordinates":[-85.24003500000001,34.979679],"type":"Point"}
}