{
  "type": "Feature",
  "properties": {
    "iso:country":"US",
    "sg:address":"2725 Cleveland Hwy",
    "sg:city":"Dalton",
    "sg:classifiers":[
        {
            "category":"Education",
            "subcategory":"School",
            "type":"Public Place"
        }
    ],
    "sg:phone":"+1 706 259 3920",
    "sg:postcode":"30721",
    "sg:province":"GA",
    "sg:tags":[
        "elementary"
    ],
    "wof:name":"Pleasant Grove Elementary Schl",
    "wof:placetype":"venue"
},
  "geometry": {"coordinates":[-84.94364899999999,34.852807],"type":"Point"}
}