{
  "type": "Feature",
  "properties": {
    "addr:full":"4447 Florence St Tucker GA 30084",
    "addr:housenumber":"4447",
    "addr:postcode":"30084",
    "addr:street":"Florence St",
    "iso:country":"US",
    "sg:address":"4447 Florence St",
    "sg:city":"Tucker",
    "sg:classifiers":[
        {
            "category":"Building & Trades",
            "subcategory":"Construction",
            "type":"Services"
        }
    ],
    "sg:phone":"+1 770 939 4822",
    "sg:postcode":"30084",
    "sg:province":"GA",
    "sg:tags":[
        "dry wall",
        "contractor"
    ],
    "wof:name":"Drywall Place",
    "wof:placetype":"venue"
},
  "geometry": {"coordinates":[-84.203964,33.846567],"type":"Point"}
}