{
  "type": "Feature",
  "properties": {
    "addr:full":"2495 Kings Arms Pt NE Atlanta GA 30345",
    "addr:housenumber":"2495",
    "addr:postcode":"30345",
    "addr:street":"Kings Arms Pt Ne",
    "iso:country":"US",
    "sg:address":"2495 Kings Arms Pt NE",
    "sg:city":"Atlanta",
    "sg:classifiers":[
        {
            "category":"Professional",
            "type":"Services"
        }
    ],
    "sg:phone":"+1 770 938 5629",
    "sg:postcode":"30345",
    "sg:province":"GA",
    "wof:name":"Sebo St Ives LLC",
    "wof:placetype":"venue"
},
  "geometry": {"coordinates":[-84.25875499999999,33.857705],"type":"Point"}
}