{
  "type": "Feature",
  "properties": {
    "iso:country":"US",
    "sg:address":"10 The Meadows",
    "sg:city":"Newnan",
    "sg:classifiers":[
        {
            "category":"Autos & Motor Vehicles",
            "subcategory":"Fuel & Gas Station",
            "type":"Retail Goods"
        }
    ],
    "sg:phone":"+1 770 253 4810",
    "sg:postcode":"30265",
    "sg:province":"GA",
    "sg:tags":[
        "station",
        "gasoline"
    ],
    "wof:name":"Avery Park Chevron",
    "wof:placetype":"venue"
},
  "geometry": {"coordinates":[-84.72176899999999,33.396889],"type":"Point"}
}