{
  "type": "Feature",
  "properties": {
    "iso:country":"US",
    "sg:address":"131 Salem Church Ave SW",
    "sg:city":"Milledgeville",
    "sg:classifiers":[
        {
            "category":"Education",
            "subcategory":"Library",
            "type":"Public Place"
        }
    ],
    "sg:phone":"+1 478 452 4244",
    "sg:postcode":"31061",
    "sg:province":"GA",
    "sg:tags":[
        "research"
    ],
    "wof:name":"Nipper Microservice",
    "wof:placetype":"venue"
},
  "geometry": {"coordinates":[-83.344196,33.001269],"type":"Point"}
}