{
  "type": "Feature",
  "properties": {
    "addr:full":"4025 Watson Blvd Warner Robins GA 31093",
    "addr:housenumber":"4025",
    "addr:postcode":"31093",
    "addr:street":"Watson Blvd",
    "iso:country":"US",
    "sg:address":"4025 Watson Blvd",
    "sg:city":"Warner Robins",
    "sg:classifiers":[
        {
            "category":"Building & Trades",
            "subcategory":"Construction",
            "type":"Services"
        }
    ],
    "sg:phone":"+1 478 953 7300",
    "sg:postcode":"31093",
    "sg:province":"GA",
    "sg:tags":[
        "designer",
        "business",
        "contractor",
        "pool",
        "dealer",
        "special",
        "swimming"
    ],
    "wof:name":"Mid State Pools & Spas",
    "wof:placetype":"venue"
},
  "geometry": {"coordinates":[-83.703047,32.614635],"type":"Point"}
}