{
  "type": "Feature",
  "properties": {
    "addr:full":"2390 Atlanta Rd SE Smyrna GA 30080",
    "addr:housenumber":"2390",
    "addr:postcode":"30080",
    "addr:street":"Atlanta Rd Se",
    "iso:country":"US",
    "sg:address":"2390 Atlanta Rd SE",
    "sg:city":"Smyrna",
    "sg:classifiers":[
        {
            "category":"Place Of Worship",
            "subcategory":"Church",
            "type":"Public Place"
        },
        {
            "category":"Place Of Worship",
            "type":"Public Place"
        }
    ],
    "sg:phone":"+1 770 434 2444",
    "sg:postcode":"30080",
    "sg:province":"GA",
    "sg:tags":[
        "churches-pentecostal-apostolic",
        "denomination",
        "churches-apostolic",
        "churches-interdenominational",
        "churches-various"
    ],
    "wof:name":"Apostolic Assembly",
    "wof:placetype":"venue"
},
  "geometry": {"coordinates":[-84.52076099999999,33.895038],"type":"Point"}
}