{
  "type": "Feature",
  "properties": {
    "addr:full":"2542 Old River Rd Fortson GA 31808",
    "addr:housenumber":"2542",
    "addr:postcode":"31808",
    "addr:street":"Old River Rd",
    "iso:country":"US",
    "sg:address":"2542 Old River Rd",
    "sg:city":"Fortson",
    "sg:classifiers":[
        {
            "category":"Food & Beverages",
            "subcategory":"Specialty",
            "type":"Retail Goods"
        }
    ],
    "sg:phone":"+1 706 327 0349",
    "sg:postcode":"31808",
    "sg:province":"GA",
    "wof:name":"Bob Ressmeyer",
    "wof:placetype":"venue"
},
  "geometry": {"coordinates":[-85.052431,32.607666],"type":"Point"}
}