{
  "type": "Feature",
  "properties": {
    "iso:country":"US",
    "sg:address":"1800 Century Boulevard NE Bsmt",
    "sg:city":"Atlanta",
    "sg:classifiers":[
        {
            "category":"Banks & Credit Unions",
            "subcategory":"Bank",
            "type":"Services"
        }
    ],
    "sg:phone":"+1 404 230 5555",
    "sg:postcode":"30345",
    "sg:province":"GA",
    "wof:name":"Suntrust",
    "wof:placetype":"venue"
},
  "geometry": {"coordinates":[-84.313288,33.846141],"type":"Point"}
}