{
  "type": "Feature",
  "properties": {
    "iso:country":"US",
    "sg:address":"7490 Old National Hwy",
    "sg:city":"Riverdale",
    "sg:classifiers":[
        {
            "category":"Shopping",
            "subcategory":"Clothing, Apparel, & Fashions",
            "type":"Retail Goods"
        }
    ],
    "sg:phone":"+1 770 907 8660",
    "sg:postcode":"30296",
    "sg:province":"GA",
    "wof:name":"One Stop Wedding Shop",
    "wof:placetype":"venue"
},
  "geometry": {"coordinates":[-84.46622600000001,33.553515],"type":"Point"}
}