{
  "type": "Feature",
  "properties": {
    "addr:full":"575 W Pike St Lawrenceville GA 30045",
    "addr:housenumber":"575",
    "addr:postcode":"30045",
    "addr:street":"W Pike",
    "iso:country":"US",
    "sg:address":"575 W Pike St",
    "sg:city":"Lawrenceville",
    "sg:classifiers":[
        {
            "category":"Food & Beverages",
            "subcategory":"Groceries & Convenience Stores",
            "type":"Retail Goods"
        }
    ],
    "sg:phone":"+1 770 277 6160",
    "sg:postcode":"30045",
    "sg:province":"GA",
    "wof:name":"Asian Market",
    "wof:placetype":"venue"
},
  "geometry": {"coordinates":[-84.006175,33.962145],"type":"Point"}
}