{
  "type": "Feature",
  "properties": {
    "iso:country":"US",
    "sg:address":"7041 Blueberry Ridge SE",
    "sg:city":"Acworth",
    "sg:classifiers":[
        {
            "category":"Building & Trades",
            "subcategory":"Construction",
            "type":"Services"
        }
    ],
    "sg:phone":"+1 770 974 7596",
    "sg:postcode":"30102",
    "sg:province":"GA",
    "sg:tags":[
        "home",
        "improvement"
    ],
    "wof:name":"J & J Home Improvement",
    "wof:placetype":"venue"
},
  "geometry": {"coordinates":[-84.69249600000001,34.128992],"type":"Point"}
}