{
  "type": "Feature",
  "properties": {
    "addr:full":"5155 Carole Pl Stone Mountain GA 30087",
    "addr:housenumber":"5155",
    "addr:postcode":"30087",
    "addr:street":"Carole Pl",
    "iso:country":"US",
    "sg:address":"5155 Carole Pl",
    "sg:city":"Stone Mountain",
    "sg:classifiers":[
        {
            "category":"Building & Trades",
            "subcategory":"Cleaning & Sanitation",
            "type":"Services"
        }
    ],
    "sg:phone":"+1 678 687 2945",
    "sg:postcode":"30087",
    "sg:province":"GA",
    "sg:tags":[
        "maintenance"
    ],
    "wof:name":"Agapes Cleaning Service",
    "wof:placetype":"venue"
},
  "geometry": {"coordinates":[-84.086083,33.789903],"type":"Point"}
}