{
  "type": "Feature",
  "properties": {
    "addr:full":"5178 Lake Forrest Dr NE Atlanta GA 30342",
    "addr:housenumber":"5178",
    "addr:postcode":"30342",
    "addr:street":"Lake Forrest Dr Ne",
    "iso:country":"US",
    "sg:address":"5178 Lake Forrest Dr NE",
    "sg:city":"Atlanta",
    "sg:classifiers":[
        {
            "category":"Autos & Motor Vehicles",
            "subcategory":"Auto Supplies",
            "type":"Retail Goods"
        },
        {
            "category":"Manufacturing",
            "subcategory":"Electronics",
            "type":"Manufacturing & Wholesale Goods"
        }
    ],
    "sg:phone":"+1 404 943 9622",
    "sg:postcode":"30342",
    "sg:province":"GA",
    "sg:tags":[
        "consultant",
        "robotics",
        "automation"
    ],
    "wof:name":"Sepa",
    "wof:placetype":"venue"
},
  "geometry": {"coordinates":[-84.38715000000001,33.896803],"type":"Point"}
}