{
  "type": "Feature",
  "properties": {
    "iso:country":"US",
    "sg:address":"3757 Covington Hwy",
    "sg:city":"Decatur",
    "sg:classifiers":[
        {
            "category":"Transit Center",
            "subcategory":"Freight",
            "type":"Transportation"
        },
        {
            "category":"Travel",
            "subcategory":"Travel Agent",
            "type":"Entertainment"
        },
        {
            "category":"Freight",
            "type":"Transportation"
        },
        {
            "category":"Local Transit",
            "type":"Transportation"
        }
    ],
    "sg:phone":"+1 404 289 2939",
    "sg:postcode":"30032",
    "sg:province":"GA",
    "sg:tags":[
        "consultant",
        "provider",
        "trucking",
        "trucking-motor",
        "broker"
    ],
    "wof:name":"Legends Transport",
    "wof:placetype":"venue"
},
  "geometry": {"coordinates":[-84.245773,33.76109],"type":"Point"}
}