{
  "type": "Feature",
  "properties": {
    "iso:country":"US",
    "sg:address":"1130 River Overlook Ct NE",
    "sg:city":"Lawrenceville",
    "sg:classifiers":[
        {
            "category":"Building & Trades",
            "subcategory":"Construction",
            "type":"Services"
        }
    ],
    "sg:phone":"+1 770 682 5743",
    "sg:postcode":"30043",
    "sg:province":"GA",
    "sg:tags":[
        "carpentry",
        "contractor"
    ],
    "wof:name":"C M I Millwork Installation",
    "wof:placetype":"venue"
},
  "geometry": {"coordinates":[-84.018745,33.977762],"type":"Point"}
}