{
  "type": "Feature",
  "properties": {
    "addr:full":"2122 Powell Ln Decatur GA 30033",
    "addr:housenumber":"2122",
    "addr:postcode":"30033",
    "addr:street":"Powell Ln",
    "iso:country":"US",
    "sg:address":"2122 Powell Ln",
    "sg:city":"Decatur",
    "sg:classifiers":[
        {
            "category":"Building & Trades",
            "subcategory":"Construction",
            "type":"Services"
        }
    ],
    "sg:phone":"+1 404 325 9273",
    "sg:postcode":"30033",
    "sg:province":"GA",
    "sg:tags":[
        "house"
    ],
    "wof:name":"Advanced Remodeling Technology",
    "wof:placetype":"venue"
},
  "geometry": {"coordinates":[-84.303783,33.791544],"type":"Point"}
}