{
  "type": "Feature",
  "properties": {
    "iso:country":"US",
    "sg:address":"6368 Foggy Oak Dr",
    "sg:city":"Fairburn",
    "sg:classifiers":[
        {
            "category":"Personal",
            "type":"Services"
        }
    ],
    "sg:phone":"+1 770 964 3136",
    "sg:postcode":"30213",
    "sg:province":"GA",
    "sg:tags":[
        "party",
        "planning",
        "event"
    ],
    "sg:website":"www.bargainbouncin.com",
    "wof:name":"Bargain Bouncin Party Rentals Llc",
    "wof:placetype":"venue"
},
  "geometry": {"coordinates":[-84.647926,33.581584],"type":"Point"}
}