{
  "type": "Feature",
  "properties": {
    "addr:full":"5994 Memorial Dr Stone Mountain GA 30083",
    "addr:housenumber":"5994",
    "addr:postcode":"30083",
    "addr:street":"Memorial Dr",
    "iso:country":"US",
    "sg:address":"5994 Memorial Dr",
    "sg:city":"Stone Mountain",
    "sg:classifiers":[
        {
            "category":"Professional",
            "subcategory":"Business Services",
            "type":"Services"
        }
    ],
    "sg:phone":"+1 404 297 9733",
    "sg:postcode":"30083",
    "sg:province":"GA",
    "sg:tags":[
        "fund",
        "promotion",
        "raising"
    ],
    "wof:name":"Hi Style Promotions",
    "wof:placetype":"venue"
},
  "geometry": {"coordinates":[-84.19631,33.800711],"type":"Point"}
}