{
  "type": "Feature",
  "properties": {
    "iso:country":"US",
    "sg:address":"4372 Baker Dr NW",
    "sg:city":"Atlanta",
    "sg:classifiers":[
        {
            "category":"Freight",
            "type":"Transportation"
        }
    ],
    "sg:phone":"+1 678 662 5525",
    "sg:postcode":"30340",
    "sg:province":"GA",
    "sg:tags":[
        "operator",
        "local",
        "trucking"
    ],
    "wof:name":"Davis Delivery",
    "wof:placetype":"venue"
},
  "geometry": {"coordinates":[-84.244427,33.920908],"type":"Point"}
}