{
  "type": "Feature",
  "properties": {
    "iso:country":"US",
    "sg:address":"418 Riverlake Ct",
    "sg:city":"Woodstock",
    "sg:classifiers":[
        {
            "category":"Professional",
            "subcategory":"Engineering",
            "type":"Services"
        }
    ],
    "sg:phone":"+1 770 475 0418",
    "sg:postcode":"30188",
    "sg:province":"GA",
    "wof:name":"Fairwind Industries",
    "wof:placetype":"venue"
},
  "geometry": {"coordinates":[-84.38601,34.120572],"type":"Point"}
}