{
  "type": "Feature",
  "properties": {
    "addr:full":"1280 County Line Rd NW Acworth GA 30101",
    "addr:housenumber":"1280",
    "addr:postcode":"30101",
    "addr:street":"County Line Rd Nw",
    "iso:country":"US",
    "sg:address":"1280 County Line Rd NW",
    "sg:city":"Acworth",
    "sg:classifiers":[
        {
            "category":"Building & Trades",
            "subcategory":"Plumbing",
            "type":"Services"
        }
    ],
    "sg:phone":"+1 770 795 8234",
    "sg:postcode":"30101",
    "sg:province":"GA",
    "sg:tags":[
        "contractor"
    ],
    "wof:name":"Vaughn Plumbing Services",
    "wof:placetype":"venue"
},
  "geometry": {"coordinates":[-84.73283000000001,33.984735],"type":"Point"}
}