{
  "type": "Feature",
  "properties": {
    "addr:full":"129 Main St Bogart GA 30622",
    "addr:housenumber":"129",
    "addr:postcode":"30622",
    "addr:street":"Main St",
    "iso:country":"US",
    "sg:address":"129 Main St",
    "sg:city":"Bogart",
    "sg:classifiers":[
        {
            "category":"Health Services",
            "subcategory":"Doctor",
            "type":"Services"
        }
    ],
    "sg:phone":"+1 770 725 7420",
    "sg:postcode":"30622",
    "sg:province":"GA",
    "sg:tags":[
        "physician",
        "surgeon"
    ],
    "wof:name":"Greater Athens Physicians Inc",
    "wof:placetype":"venue"
},
  "geometry": {"coordinates":[-83.534379,33.948822],"type":"Point"}
}