{
  "type": "Feature",
  "properties": {
    "iso:country":"US",
    "sg:address":"270 Plaza St",
    "sg:city":"Athens",
    "sg:classifiers":[
        {
            "category":"Building & Trades",
            "subcategory":"Pest Control",
            "type":"Services"
        }
    ],
    "sg:phone":"+1 706 613 8245",
    "sg:postcode":"30606",
    "sg:province":"GA",
    "wof:name":"Curry's Termite & Pest Control",
    "wof:placetype":"venue"
},
  "geometry": {"coordinates":[-83.39792,33.952721],"type":"Point"}
}