{
  "type": "Feature",
  "properties": {
    "iso:country":"US",
    "sg:address":"3205 Birchfield Trce",
    "sg:city":"Marietta",
    "sg:classifiers":[
        {
            "category":"Professional",
            "subcategory":"Advertising",
            "type":"Services"
        },
        {
            "category":"Professional",
            "subcategory":"Business Services",
            "type":"Services"
        }
    ],
    "sg:phone":"+1 770 977 1000",
    "sg:postcode":"30068",
    "sg:province":"GA",
    "sg:tags":[
        "demonstration"
    ],
    "wof:name":"Dillon Assoc Inc",
    "wof:placetype":"venue"
},
  "geometry": {"coordinates":[-84.458614,33.955918],"type":"Point"}
}