{
  "type": "Feature",
  "properties": {
    "addr:full":"600 US Hwy 19 S Camilla GA 31730",
    "addr:housenumber":"600",
    "addr:postcode":"31730",
    "addr:street":"Us Hwy 19 S",
    "iso:country":"US",
    "sg:address":"600 US Hwy 19 S",
    "sg:city":"Camilla",
    "sg:classifiers":[
        {
            "category":"Travel",
            "subcategory":"Hotels & Motels",
            "type":"Entertainment"
        }
    ],
    "sg:phone":"+1 229 336 0956",
    "sg:postcode":"31730",
    "sg:province":"GA",
    "wof:name":"Coutland Club Hotel",
    "wof:placetype":"venue"
},
  "geometry": {"coordinates":[-84.191322,31.220868],"type":"Point"}
}