{
  "type": "Feature",
  "properties": {
    "iso:country":"US",
    "sg:address":"4800 Briarcliff Road NE",
    "sg:city":"Atlanta",
    "sg:classifiers":[
        {
            "category":"Shopping",
            "subcategory":"Music",
            "type":"Retail Goods"
        }
    ],
    "sg:phone":"+1 770 908 0271",
    "sg:postcode":"30345",
    "sg:province":"GA",
    "sg:tags":[
        "dvd's"
    ],
    "wof:name":"Peppermint Music",
    "wof:placetype":"venue"
},
  "geometry": {"coordinates":[-84.255819,33.848445],"type":"Point"}
}