{
  "type": "Feature",
  "properties": {
    "addr:full":"1509 Old Peachtree Rd NE Lawrenceville GA 30043",
    "addr:housenumber":"1509",
    "addr:postcode":"30043",
    "addr:street":"Old Peachtree Rd Ne",
    "iso:country":"US",
    "sg:address":"1509 Old Peachtree Rd NE",
    "sg:city":"Lawrenceville",
    "sg:classifiers":[
        {
            "category":"Wholesale",
            "subcategory":"Non-durable Goods",
            "type":"Manufacturing & Wholesale Goods"
        }
    ],
    "sg:phone":"+1 770 822 1867",
    "sg:postcode":"30043",
    "sg:province":"GA",
    "wof:name":"Creative Expressions",
    "wof:placetype":"venue"
},
  "geometry": {"coordinates":[-83.969651,34.037326],"type":"Point"}
}