{
  "type": "Feature",
  "properties": {
    "iso:country":"US",
    "sg:address":"1270 Womack Rd",
    "sg:city":"Dunwoody",
    "sg:classifiers":[
        {
            "category":"Building & Trades",
            "subcategory":"Locksmith",
            "type":"Services"
        }
    ],
    "sg:phone":"+1 404 982 1937",
    "sg:postcode":"30338",
    "sg:province":"GA",
    "sg:tags":[
        "key"
    ],
    "wof:name":"A A A Justin Locksmith",
    "wof:placetype":"venue"
},
  "geometry": {"coordinates":[-84.430684,33.699213],"type":"Point"}
}