{
  "type": "Feature",
  "properties": {
    "iso:country":"US",
    "sg:address":"1368 Velvet Creek Ct SW",
    "sg:city":"Marietta",
    "sg:classifiers":[
        {
            "category":"Professional",
            "subcategory":"Business Services",
            "type":"Services"
        }
    ],
    "sg:phone":"+1 770 432 0938",
    "sg:postcode":"30008",
    "sg:province":"GA",
    "sg:tags":[
        "consulting",
        "computer",
        "design",
        "network",
        "system"
    ],
    "wof:name":"Georgia Soho",
    "wof:placetype":"venue"
},
  "geometry": {"coordinates":[-84.595934,33.87177],"type":"Point"}
}