{
  "type": "Feature",
  "properties": {
    "iso:country":"US",
    "sg:address":"1200 Abernathy Rd NE",
    "sg:city":"Atlanta",
    "sg:classifiers":[
        {
            "category":"Banks & Credit Unions",
            "subcategory":"Investment Brokerage",
            "type":"Services"
        }
    ],
    "sg:phone":"+1 678 441 1000",
    "sg:postcode":"30338",
    "sg:province":"GA",
    "sg:tags":[
        "stock",
        "bond"
    ],
    "sg:website":"www.ubs.com",
    "wof:name":"UBS Financial Svc",
    "wof:placetype":"venue"
},
  "geometry": {"coordinates":[-84.347565,33.938277],"type":"Point"}
}