{
  "type": "Feature",
  "properties": {
    "iso:country":"US",
    "sg:address":"111 Perimeter Center W",
    "sg:city":"Atlanta",
    "sg:classifiers":[
        {
            "category":"Travel",
            "subcategory":"Hotels & Motels",
            "type":"Entertainment"
        }
    ],
    "sg:phone":"+1 770 396 6800",
    "sg:postcode":"30346",
    "sg:province":"GA",
    "wof:name":"W Hotel",
    "wof:placetype":"venue"
},
  "geometry": {"coordinates":[-84.341534,33.9269],"type":"Point"}
}