{
  "type": "Feature",
  "properties": {
    "addr:full":"5619 Pennybrook Ct Stone Mountain GA 30087",
    "addr:housenumber":"5619",
    "addr:postcode":"30087",
    "addr:street":"Pennybrook Ct",
    "iso:country":"US",
    "sg:address":"5619 Pennybrook Ct",
    "sg:city":"Stone Mountain",
    "sg:classifiers":[
        {
            "category":"Professional",
            "type":"Services"
        }
    ],
    "sg:phone":"+1 770 498 8268",
    "sg:postcode":"30087",
    "sg:province":"GA",
    "wof:name":"Expressions By Delores",
    "wof:placetype":"venue"
},
  "geometry": {"coordinates":[-84.158563,33.791824],"type":"Point"}
}