{
  "type": "Feature",
  "properties": {
    "addr:full":"9131 Clubhouse Dr Riverdale GA 30274",
    "addr:housenumber":"9131",
    "addr:postcode":"30274",
    "addr:street":"Clubhouse Dr",
    "iso:country":"US",
    "sg:address":"9131 Clubhouse Dr",
    "sg:city":"Riverdale",
    "sg:classifiers":[
        {
            "category":"Professional",
            "type":"Services"
        }
    ],
    "sg:phone":"+1 770 210 3424",
    "sg:postcode":"30274",
    "sg:province":"GA",
    "wof:name":"Kim L Sowels",
    "wof:placetype":"venue"
},
  "geometry": {"coordinates":[-84.394789,33.505457],"type":"Point"}
}