{
  "type": "Feature",
  "properties": {
    "addr:full":"5000 Austell Powder Springs Rd Austell GA 30106",
    "addr:housenumber":"5000",
    "addr:postcode":"30106",
    "addr:street":"Austell Powder Springs Rd",
    "iso:country":"US",
    "sg:address":"5000 Austell Powder Springs Rd",
    "sg:city":"Austell",
    "sg:classifiers":[
        {
            "category":"Banks & Credit Unions",
            "subcategory":"Bank",
            "type":"Services"
        }
    ],
    "sg:phone":"+1 770 819 8385",
    "sg:postcode":"30106",
    "sg:province":"GA",
    "sg:website":"www.rbccentura.com",
    "wof:name":"Rbc Centura Bank",
    "wof:placetype":"venue"
},
  "geometry": {"coordinates":[-84.654359,33.83218],"type":"Point"}
}