{
  "type": "Feature",
  "properties": {
    "iso:country":"US",
    "sg:address":"4445 Commerce Dr SW",
    "sg:city":"Atlanta",
    "sg:classifiers":[
        {
            "category":"Wholesale",
            "subcategory":"Drugs",
            "type":"Manufacturing & Wholesale Goods"
        },
        {
            "category":"Professional",
            "subcategory":"Art Services",
            "type":"Services"
        },
        {
            "category":"Autos & Motor Vehicles",
            "subcategory":"Auto Supplies",
            "type":"Retail Goods"
        },
        {
            "category":"Professional",
            "subcategory":"Printing & Photocopies",
            "type":"Services"
        },
        {
            "category":"Manufacturing",
            "subcategory":"Printing",
            "type":"Manufacturing & Wholesale Goods"
        },
        {
            "category":"Manufacturing",
            "subcategory":"Signs",
            "type":"Manufacturing & Wholesale Goods"
        }
    ],
    "sg:phone":"+1 404 699 1865",
    "sg:postcode":"30336",
    "sg:province":"GA",
    "sg:tags":[
        "lettering",
        "designer",
        "producer",
        "pennant",
        "flag",
        "decal",
        "truck",
        "imaging",
        "digital",
        "banners",
        "painting",
        "display"
    ],
    "sg:website":"http://www.andersongraphicsinc.com",
    "wof:name":"AGI Graphics",
    "wof:placetype":"venue"
},
  "geometry": {"coordinates":[-84.53390899999999,33.761479],"type":"Point"}
}