{
  "type": "Feature",
  "properties": {
    "addr:full":"3218 Holt Rd Augusta GA 30909",
    "addr:housenumber":"3218",
    "addr:postcode":"30909",
    "addr:street":"Holt Rd",
    "iso:country":"US",
    "sg:address":"3218 Holt Rd",
    "sg:city":"Augusta",
    "sg:classifiers":[
        {
            "category":"Building & Trades",
            "subcategory":"Electrical",
            "type":"Services"
        }
    ],
    "sg:phone":"+1 706 794 4599",
    "sg:postcode":"30909",
    "sg:province":"GA",
    "sg:tags":[
        "electrical",
        "contractor"
    ],
    "wof:name":"Rd Electrical Services Inc",
    "wof:placetype":"venue"
},
  "geometry": {"coordinates":[-82.060163,33.461196],"type":"Point"}
}