{
  "type": "Feature",
  "properties": {
    "iso:country":"US",
    "sg:address":"1803 Martha Berry Blvd NW Ste 1",
    "sg:city":"Rome",
    "sg:phone":"+1 706 291 2499",
    "sg:postcode":"30165",
    "sg:province":"GA",
    "wof:name":"China City Restaurant",
    "wof:placetype":"venue"
},
  "geometry": {"coordinates":[-85.181883,34.275088],"type":"Point"}
}