{
  "type": "Feature",
  "properties": {
    "addr:full":"622 E Crossville Rd Roswell GA 30075",
    "addr:housenumber":"622",
    "addr:postcode":"30075",
    "addr:street":"E Crossville Rd",
    "iso:country":"US",
    "sg:address":"622 E Crossville Rd",
    "sg:city":"Roswell",
    "sg:classifiers":[
        {
            "category":"Shopping",
            "subcategory":"Shoes",
            "type":"Retail Goods"
        }
    ],
    "sg:phone":"+1 770 642 6022",
    "sg:postcode":"30075",
    "sg:province":"GA",
    "wof:name":"Rack Room Shoes Inc",
    "wof:placetype":"venue"
},
  "geometry": {"coordinates":[-84.346834,34.038374],"type":"Point"}
}