{
  "type": "Feature",
  "properties": {
    "addr:full":"2100 Keeling Ct Marietta GA 30064",
    "addr:housenumber":"2100",
    "addr:postcode":"30064",
    "addr:street":"Keeling Ct",
    "iso:country":"US",
    "sg:address":"2100 Keeling Ct",
    "sg:city":"Marietta",
    "sg:classifiers":[
        {
            "category":"Professional",
            "subcategory":"Management & Consulting",
            "type":"Services"
        },
        {
            "category":"Real Estate",
            "subcategory":"Real Estate Services",
            "type":"Services"
        }
    ],
    "sg:phone":"+1 770 420 5214",
    "sg:postcode":"30064",
    "sg:province":"GA",
    "sg:tags":[
        "research"
    ],
    "sg:website":"www.smartnumbers.com",
    "wof:name":"Smart Numbers LLC",
    "wof:placetype":"venue"
},
  "geometry": {"coordinates":[-84.613176,33.922182],"type":"Point"}
}