{
  "type": "Feature",
  "properties": {
    "iso:country":"US",
    "sg:address":"4609 Lewis Rd",
    "sg:city":"Stone Mountain",
    "sg:classifiers":[
        {
            "category":"Wholesale",
            "subcategory":"Groceries",
            "type":"Manufacturing & Wholesale Goods"
        }
    ],
    "sg:phone":"+1 678 406 0101",
    "sg:postcode":"30083",
    "sg:province":"GA",
    "sg:tags":[
        "food",
        "specializing",
        "pastry",
        "item"
    ],
    "wof:name":"Hafner USA Inc",
    "wof:placetype":"venue"
},
  "geometry": {"coordinates":[-84.19852,33.828934],"type":"Point"}
}