{
  "type": "Feature",
  "properties": {
    "iso:country":"US",
    "sg:address":"3795 Smithtown Rd",
    "sg:city":"Suwanee",
    "sg:classifiers":[
        {
            "category":"Professional",
            "subcategory":"Management & Consulting",
            "type":"Services"
        }
    ],
    "sg:phone":"+1 770 945 7981",
    "sg:postcode":"30024",
    "sg:province":"GA",
    "sg:tags":[
        "public",
        "relations"
    ],
    "wof:name":"Preston Group Inc",
    "wof:placetype":"venue"
},
  "geometry": {"coordinates":[-84.0518,34.049475],"type":"Point"}
}