{
  "type": "Feature",
  "properties": {
    "addr:full":"9716 Holly Hill Way Jonesboro GA 30238",
    "addr:housenumber":"9716",
    "addr:postcode":"30238",
    "addr:street":"Holly Hill Way",
    "iso:country":"US",
    "sg:address":"9716 Holly Hill Way",
    "sg:city":"Jonesboro",
    "sg:classifiers":[
        {
            "category":"Professional",
            "subcategory":"Business Services",
            "type":"Services"
        }
    ],
    "sg:phone":"+1 770 473 6376",
    "sg:postcode":"30238",
    "sg:province":"GA",
    "sg:tags":[
        "interior",
        "consultant",
        "design",
        "decorator"
    ],
    "wof:name":"Cozy Corners",
    "wof:placetype":"venue"
},
  "geometry": {"coordinates":[-84.38384000000001,33.483812],"type":"Point"}
}