{
  "type": "Feature",
  "properties": {
    "iso:country":"US",
    "sg:address":"62 Mill Wee Hollow Rd",
    "sg:city":"Rossville",
    "sg:classifiers":[
        {
            "category":"Manufacturing",
            "subcategory":"Metals",
            "type":"Manufacturing & Wholesale Goods"
        },
        {
            "category":"Professional",
            "subcategory":"Advertising",
            "type":"Services"
        }
    ],
    "sg:phone":"+1 706 820 1781",
    "sg:postcode":"30741",
    "sg:province":"GA",
    "sg:tags":[
        "distribution"
    ],
    "wof:name":"Sunbelt Turret Steel Industrie",
    "wof:placetype":"venue"
},
  "geometry": {"coordinates":[-85.339191,34.905654],"type":"Point"}
}