{
  "type": "Feature",
  "properties": {
    "addr:full":"991 Hunters Rd Sylvania GA 30467",
    "addr:housenumber":"991",
    "addr:postcode":"30467",
    "addr:street":"Hunters Rd",
    "iso:country":"US",
    "sg:address":"991 Hunters Rd",
    "sg:city":"Sylvania",
    "sg:classifiers":[
        {
            "category":"Real Estate",
            "subcategory":"Surveying",
            "type":"Services"
        }
    ],
    "sg:phone":"+1 912 857 3288",
    "sg:postcode":"30467",
    "sg:province":"GA",
    "wof:name":"Warren Poythress",
    "wof:placetype":"venue"
},
  "geometry": {"coordinates":[-81.55062,32.655243],"type":"Point"}
}