{
  "type": "Feature",
  "properties": {
    "iso:country":"US",
    "sg:address":"1251 Smith Rd",
    "sg:city":"Fortson",
    "sg:classifiers":[
        {
            "category":"Health Services",
            "subcategory":"Doctor",
            "type":"Services"
        }
    ],
    "sg:phone":"+1 706 323 1751",
    "sg:postcode":"31808",
    "sg:province":"GA",
    "sg:tags":[
        "physician"
    ],
    "wof:name":"Emergncy Med Spclists Columbus",
    "wof:placetype":"venue"
},
  "geometry": {"coordinates":[-84.97259699999999,32.605488],"type":"Point"}
}