{
  "type": "Feature",
  "properties": {
    "iso:country":"US",
    "sg:address":"3999 Austell Rd Ste 303",
    "sg:city":"Austell",
    "sg:classifiers":[
        {
            "category":"Building & Trades",
            "subcategory":"Construction",
            "type":"Services"
        }
    ],
    "sg:phone":"+1 770 438 2940",
    "sg:postcode":"30106",
    "sg:province":"GA",
    "sg:tags":[
        "contractor"
    ],
    "wof:name":"Pcg Interiors",
    "wof:placetype":"venue"
},
  "geometry": {"coordinates":[-84.601691,33.855906],"type":"Point"}
}