{
  "type": "Feature",
  "properties": {
    "iso:country":"US",
    "sg:address":"9825 Main St",
    "sg:city":"Woodstock",
    "sg:classifiers":[
        {
            "category":"Retail",
            "subcategory":"Laundry & Dry Cleaning",
            "type":"Services"
        }
    ],
    "sg:phone":"+1 770 926 8809",
    "sg:postcode":"30188",
    "sg:province":"GA",
    "sg:tags":[
        "cleaners",
        "plant",
        "drycleaning"
    ],
    "wof:name":"Carol's Cleaners",
    "wof:placetype":"venue"
},
  "geometry": {"coordinates":[-84.51932600000001,34.083577],"type":"Point"}
}