{
  "type": "Feature",
  "properties": {
    "iso:country":"US",
    "sg:address":"727 Church St NW",
    "sg:city":"Atlanta",
    "sg:classifiers":[
        {
            "category":"Professional",
            "subcategory":"Business Services",
            "type":"Services"
        }
    ],
    "sg:phone":"+1 404 792 4091",
    "sg:postcode":"30318",
    "sg:province":"GA",
    "sg:tags":[
        "recording",
        "studio"
    ],
    "wof:name":"Elixir Record Inc",
    "wof:placetype":"venue"
},
  "geometry": {"coordinates":[-84.466791,33.771093],"type":"Point"}
}