{
  "type": "Feature",
  "properties": {
    "iso:country":"US",
    "sg:address":"304 Pine St",
    "sg:city":"Eastman",
    "sg:classifiers":[
        {
            "category":"Retail",
            "subcategory":"Laundry & Dry Cleaning",
            "type":"Services"
        }
    ],
    "sg:phone":"+1 478 374 2798",
    "sg:postcode":"31023",
    "sg:province":"GA",
    "wof:name":"Emilys Alterations",
    "wof:placetype":"venue"
},
  "geometry": {"coordinates":[-83.17774300000001,32.195855],"type":"Point"}
}