{
  "type": "Feature",
  "properties": {
    "iso:country":"US",
    "sg:address":"2398 Reeves Creek Rd",
    "sg:city":"Jonesboro",
    "sg:classifiers":[
        {
            "category":"Travel",
            "subcategory":"Hotels & Motels",
            "type":"Entertainment"
        }
    ],
    "sg:phone":"+1 770 210 0037",
    "sg:postcode":"30236",
    "sg:province":"GA",
    "sg:tags":[
        "operation"
    ],
    "wof:name":"Shive Shakti LLC",
    "wof:placetype":"venue"
},
  "geometry": {"coordinates":[-84.312916,33.553434],"type":"Point"}
}