{
  "type": "Feature",
  "properties": {
    "addr:full":"793 Pyne Rd La Grange GA 30240",
    "addr:housenumber":"793",
    "addr:postcode":"30240",
    "addr:street":"Pyne Rd",
    "iso:country":"US",
    "sg:address":"793 Pyne Rd",
    "sg:city":"La Grange",
    "sg:classifiers":[
        {
            "category":"Building & Trades",
            "subcategory":"Construction",
            "type":"Services"
        }
    ],
    "sg:phone":"+1 706 883 7776",
    "sg:postcode":"30240",
    "sg:province":"GA",
    "wof:name":"Larry Gaston",
    "wof:placetype":"venue"
},
  "geometry": {"coordinates":[-85.130773,33.01496],"type":"Point"}
}