{
  "type": "Feature",
  "properties": {
    "iso:country":"US",
    "sg:address":"303 Sedgewick Trl",
    "sg:city":"Lawrenceville",
    "sg:classifiers":[
        {
            "category":"Travel",
            "subcategory":"Travel Agent",
            "type":"Entertainment"
        }
    ],
    "sg:phone":"+1 770 338 1250",
    "sg:postcode":"30044",
    "sg:province":"GA",
    "sg:tags":[
        "agency"
    ],
    "wof:name":"American Express",
    "wof:placetype":"venue"
},
  "geometry": {"coordinates":[-84.03713399999999,33.919464],"type":"Point"}
}