{
  "type": "Feature",
  "properties": {
    "iso:country":"US",
    "sg:address":"1654 Wynndowne Trl SE",
    "sg:city":"Smyrna",
    "sg:classifiers":[
        {
            "category":"Shopping",
            "subcategory":"Gifts & Souvenirs",
            "type":"Retail Goods"
        }
    ],
    "sg:phone":"+1 678 973 3031",
    "sg:postcode":"30080",
    "sg:province":"GA",
    "sg:tags":[
        "shop"
    ],
    "wof:name":"Wflp",
    "wof:placetype":"venue"
},
  "geometry": {"coordinates":[-84.504327,33.88736],"type":"Point"}
}