{
  "type": "Feature",
  "properties": {
    "addr:full":"615 Wynbrooke Pkwy Stone Mountain GA 30087",
    "addr:housenumber":"615",
    "addr:postcode":"30087",
    "addr:street":"Wynbrooke Pkwy",
    "iso:country":"US",
    "sg:address":"615 Wynbrooke Pkwy",
    "sg:city":"Stone Mountain",
    "sg:classifiers":[
        {
            "category":"Education",
            "subcategory":"Dance Studio",
            "type":"Public Place"
        }
    ],
    "sg:phone":"+1 770 879 7641",
    "sg:postcode":"30087",
    "sg:province":"GA",
    "sg:tags":[
        "instruction",
        "dancing"
    ],
    "wof:name":"Rakaba Ballet",
    "wof:placetype":"venue"
},
  "geometry": {"coordinates":[-84.10630500000001,33.792059],"type":"Point"}
}