{
  "type": "Feature",
  "properties": {
    "iso:country":"US",
    "sg:address":"3016 Sherwood Dr",
    "sg:city":"Brunswick",
    "sg:classifiers":[
        {
            "category":"Professional",
            "subcategory":"Business Services",
            "type":"Services"
        }
    ],
    "sg:phone":"+1 912 262 6731",
    "sg:postcode":"31520",
    "sg:province":"GA",
    "wof:name":"Jk Group",
    "wof:placetype":"venue"
},
  "geometry": {"coordinates":[-81.47846800000001,31.17372],"type":"Point"}
}