{
  "type": "Feature",
  "properties": {
    "iso:country":"US",
    "sg:address":"2860 Woodruff Dr NW",
    "sg:city":"Duluth",
    "sg:classifiers":[
        {
            "category":"Professional",
            "subcategory":"Art Services",
            "type":"Services"
        }
    ],
    "sg:phone":"+1 770 476 3103",
    "sg:postcode":"30096",
    "sg:province":"GA",
    "sg:tags":[
        "commercial",
        "design"
    ],
    "wof:name":"Creative Designs LLC",
    "wof:placetype":"venue"
},
  "geometry": {"coordinates":[-84.15081499999999,33.975915],"type":"Point"}
}