{
  "type": "Feature",
  "properties": {
    "addr:full":"2001 Montreal Rd Ste 100 Tucker GA 30084",
    "addr:housenumber":"2001",
    "addr:postcode":"30084",
    "addr:street":"Montreal Rd Ste 100",
    "iso:country":"US",
    "sg:address":"2001 Montreal Rd Ste 100",
    "sg:city":"Tucker",
    "sg:classifiers":[
        {
            "category":"Professional",
            "subcategory":"Accounting & Tax Preparation",
            "type":"Services"
        }
    ],
    "sg:phone":"+1 770 938 0904",
    "sg:postcode":"30084",
    "sg:province":"GA",
    "sg:tags":[
        "accountant"
    ],
    "wof:name":"McKain Judy CPA",
    "wof:placetype":"venue"
},
  "geometry": {"coordinates":[-84.256699,33.8423],"type":"Point"}
}