{
  "type": "Feature",
  "properties": {
    "addr:full":"4363 Tilly Mill Rd Atlanta GA 30360",
    "addr:postcode":"4363;30360",
    "addr:street":"Tilly Mill Rd",
    "iso:country":"US",
    "sg:address":"4363 Tilly Mill Rd",
    "sg:city":"Atlanta",
    "sg:classifiers":[
        {
            "category":"Sports & Exercise",
            "subcategory":"Gym",
            "type":"Entertainment"
        }
    ],
    "sg:phone":"+1 770 936 2555",
    "sg:postcode":"30360",
    "sg:province":"GA",
    "sg:tags":[
        "fitness",
        "physical",
        "facility"
    ],
    "wof:name":"King Spa",
    "wof:placetype":"venue"
},
  "geometry": {"coordinates":[-84.281487,33.923153],"type":"Point"}
}