{
  "type": "Feature",
  "properties": {
    "addr:full":"1816 Rocky Branch Pass Marietta GA 30066",
    "addr:housenumber":"1816",
    "addr:postcode":"30066",
    "addr:street":"Rocky Branch Pass",
    "iso:country":"US",
    "sg:address":"1816 Rocky Branch Pass",
    "sg:city":"Marietta",
    "sg:classifiers":[
        {
            "category":"Food & Beverages",
            "subcategory":"Liquor & Beverages",
            "type":"Retail Goods"
        }
    ],
    "sg:phone":"+1 678 445 4705",
    "sg:postcode":"30066",
    "sg:province":"GA",
    "sg:tags":[
        "alcoholic"
    ],
    "wof:name":"Old World Wines",
    "wof:placetype":"venue"
},
  "geometry": {"coordinates":[-84.48954999999999,34.054057],"type":"Point"}
}