{
  "type": "Feature",
  "properties": {
    "addr:full":"273 Darsey Rd Cairo GA 39828",
    "addr:housenumber":"273",
    "addr:postcode":"39828",
    "addr:street":"Darsey Rd",
    "iso:country":"US",
    "sg:address":"273 Darsey Rd",
    "sg:city":"Cairo",
    "sg:classifiers":[
        {
            "category":"Manufacturing",
            "subcategory":"Textiles",
            "type":"Manufacturing & Wholesale Goods"
        }
    ],
    "sg:phone":"+1 229 872 3202",
    "sg:postcode":"39828",
    "sg:province":"GA",
    "sg:tags":[
        "finishing",
        "mfg",
        "cotton",
        "plant",
        "trimming"
    ],
    "sg:website":"www.homesteadtshirts.com",
    "wof:name":"Homestead Imprinted Sportswear",
    "wof:placetype":"venue"
},
  "geometry": {"coordinates":[-84.361767,30.697671],"type":"Point"}
}