{
  "type": "Feature",
  "properties": {
    "iso:country":"US",
    "sg:address":"341 Orbit St",
    "sg:city":"Fortson",
    "sg:classifiers":[
        {
            "category":"Professional",
            "subcategory":"Business Services",
            "type":"Services"
        }
    ],
    "sg:phone":"+1 706 660 1680",
    "sg:postcode":"31808",
    "sg:province":"GA",
    "wof:name":"Pearl Ant Group",
    "wof:placetype":"venue"
},
  "geometry": {"coordinates":[-85.02423400000001,32.64522],"type":"Point"}
}