{
  "type": "Feature",
  "properties": {
    "iso:country":"US",
    "sg:address":"170 Plum Orchard Rd",
    "sg:city":"Covington",
    "sg:classifiers":[
        {
            "category":"Professional",
            "type":"Services"
        }
    ],
    "sg:phone":"+1 770 385 1478",
    "sg:postcode":"30016",
    "sg:province":"GA",
    "wof:name":"Marsha Eddins",
    "wof:placetype":"venue"
},
  "geometry": {"coordinates":[-83.965673,33.597665],"type":"Point"}
}