{
  "type": "Feature",
  "properties": {
    "iso:country":"US",
    "sg:address":"506 9th St E",
    "sg:city":"Tifton",
    "sg:classifiers":[
        {
            "category":"Professional",
            "subcategory":"Engineering",
            "type":"Services"
        }
    ],
    "sg:phone":"+1 229 387 6695",
    "sg:postcode":"31794",
    "sg:province":"GA",
    "sg:tags":[
        "engineer"
    ],
    "wof:name":"RAS Engineering Svc",
    "wof:placetype":"venue"
},
  "geometry": {"coordinates":[-83.50488799999999,31.449952],"type":"Point"}
}