{
  "type": "Feature",
  "properties": {
    "iso:country":"US",
    "sg:address":"16 Latimer St",
    "sg:city":"Hazlehurst",
    "sg:classifiers":[
        {
            "category":"Personal",
            "subcategory":"Beauty Salon",
            "type":"Services"
        }
    ],
    "sg:phone":"+1 912 375 9209",
    "sg:postcode":"31539",
    "sg:province":"GA",
    "wof:name":"Attractions Beauty Salon",
    "wof:placetype":"venue"
},
  "geometry": {"coordinates":[-82.59902599999999,31.866515],"type":"Point"}
}