{
  "type": "Feature",
  "properties": {
    "addr:full":"807 N Main St La Fayette GA 30728",
    "addr:housenumber":"807",
    "addr:postcode":"30728",
    "addr:street":"N Main St;Fayette",
    "iso:country":"US",
    "sg:address":"807 N Main St",
    "sg:city":"La Fayette",
    "sg:classifiers":[
        {
            "category":"Shopping",
            "subcategory":"Used Merchandise",
            "type":"Retail Goods"
        }
    ],
    "sg:phone":"+1 706 639 3383",
    "sg:postcode":"30728",
    "sg:province":"GA",
    "sg:tags":[
        "pawnbroker"
    ],
    "wof:name":"Cash Store",
    "wof:placetype":"venue"
},
  "geometry": {"coordinates":[-85.280035,34.719194],"type":"Point"}
}