{
  "type": "Feature",
  "properties": {
    "addr:full":"289 Fulghum Rd Rising Fawn GA 30738",
    "addr:housenumber":"289",
    "addr:postcode":"30738",
    "addr:street":"Fulghum Rd",
    "iso:country":"US",
    "sg:address":"289 Fulghum Rd",
    "sg:city":"Rising Fawn",
    "sg:classifiers":[
        {
            "category":"Professional",
            "type":"Services"
        }
    ],
    "sg:phone":"+1 706 398 1091",
    "sg:postcode":"30738",
    "sg:province":"GA",
    "wof:name":"Rodney New",
    "wof:placetype":"venue"
},
  "geometry": {"coordinates":[-85.466185,34.805008],"type":"Point"}
}