{
  "type": "Feature",
  "properties": {
    "addr:full":"1936 N Druid Hills Rd NE Atlanta GA 30319",
    "addr:housenumber":"1936",
    "addr:postcode":"30319",
    "addr:street":"N Druid Hills Rd Ne",
    "iso:country":"US",
    "sg:address":"1936 N Druid Hills Rd NE",
    "sg:city":"Atlanta",
    "sg:classifiers":[
        {
            "category":"Real Estate",
            "subcategory":"Architect",
            "type":"Services"
        },
        {
            "category":"Professional",
            "subcategory":"Management & Consulting",
            "type":"Services"
        }
    ],
    "sg:phone":"+1 404 261 7008",
    "sg:postcode":"30319",
    "sg:province":"GA",
    "sg:tags":[
        "aviation",
        "engineering",
        "architectural",
        "consultant"
    ],
    "wof:name":"Dye Aviation Facilities Inc",
    "wof:placetype":"venue"
},
  "geometry": {"coordinates":[-84.342472,33.83621],"type":"Point"}
}