{
  "type": "Feature",
  "properties": {
    "addr:full":"52 Telfair Pl Savannah GA 31415",
    "addr:housenumber":"52",
    "addr:postcode":"31415",
    "addr:street":"Telfair Pl",
    "iso:country":"US",
    "sg:address":"52 Telfair Pl",
    "sg:city":"Savannah",
    "sg:classifiers":[
        {
            "category":"Airline",
            "type":"Transportation"
        }
    ],
    "sg:phone":"+1 912 236 6922",
    "sg:postcode":"31415",
    "sg:province":"GA",
    "sg:tags":[
        "delivery",
        "air",
        "general",
        "freight",
        "warehousing"
    ],
    "wof:name":"Roushs Delivery Service Inc",
    "wof:placetype":"venue"
},
  "geometry": {"coordinates":[-81.161452,32.080983],"type":"Point"}
}