{
  "type": "Feature",
  "properties": {
    "iso:country":"US",
    "sg:address":"2782 Magnolia Cara Dr SW",
    "sg:city":"Grayson",
    "sg:classifiers":[
        {
            "category":"Real Estate",
            "subcategory":"Real Estate Agent",
            "type":"Services"
        },
        {
            "category":"Professional",
            "subcategory":"Business Services",
            "type":"Services"
        }
    ],
    "sg:phone":"+1 770 972 4366",
    "sg:postcode":"30017",
    "sg:province":"GA",
    "sg:tags":[
        "appraiser"
    ],
    "wof:name":"Gwinnett Appraisals Inc",
    "wof:placetype":"venue"
},
  "geometry": {"coordinates":[-83.99439700000001,33.861593],"type":"Point"}
}