{
  "type": "Feature",
  "properties": {
    "iso:country":"US",
    "sg:address":"425 3rd Ave W",
    "sg:city":"Albany",
    "sg:classifiers":[
        {
            "category":"Health Services",
            "subcategory":"Doctor",
            "type":"Services"
        }
    ],
    "sg:phone":"+1 229 312 7025",
    "sg:postcode":"31701",
    "sg:province":"GA",
    "sg:tags":[
        "physician",
        "surgeon"
    ],
    "wof:name":"Phoebe Center-Infectious Dis",
    "wof:placetype":"venue"
},
  "geometry": {"coordinates":[-84.157766,31.589686],"type":"Point"}
}