{
  "type": "Feature",
  "properties": {
    "iso:country":"US",
    "sg:address":"49 S Marietta Pkwy SW",
    "sg:city":"Marietta",
    "sg:classifiers":[
        {
            "category":"Health Services",
            "subcategory":"Doctor",
            "type":"Services"
        }
    ],
    "sg:phone":"+1 770 424 0647",
    "sg:postcode":"30064",
    "sg:province":"GA",
    "wof:name":"White Horace MD",
    "wof:placetype":"venue"
},
  "geometry": {"coordinates":[-84.555397,33.948502],"type":"Point"}
}