{
  "type": "Feature",
  "properties": {
    "iso:country":"US",
    "sg:address":"1318 Underwood St",
    "sg:city":"Dalton",
    "sg:classifiers":[
        {
            "category":"Manufacturing",
            "subcategory":"Apparel",
            "type":"Manufacturing & Wholesale Goods"
        }
    ],
    "sg:phone":"+1 706 278 8028",
    "sg:postcode":"30721",
    "sg:province":"GA",
    "sg:tags":[
        "sewing",
        "rug",
        "contractor",
        "distributor",
        "manufacturer",
        "carpet"
    ],
    "sg:website":"http://www.madisonindustries.com",
    "wof:name":"Madison Industries",
    "wof:placetype":"venue"
},
  "geometry": {"coordinates":[-84.948016,34.782674],"type":"Point"}
}