{
  "type": "Feature",
  "properties": {
    "iso:country":"US",
    "sg:address":"2550 Lithonia West Dr",
    "sg:city":"Lithonia",
    "sg:classifiers":[
        {
            "category":"Utilities",
            "subcategory":"Refuse",
            "type":"Services"
        }
    ],
    "sg:phone":"+1 770 987 5678",
    "sg:postcode":"30058",
    "sg:province":"GA",
    "sg:tags":[
        "truck",
        "dump"
    ],
    "wof:name":"Halls Of Georgia Inc",
    "wof:placetype":"venue"
},
  "geometry": {"coordinates":[-84.127548,33.715296],"type":"Point"}
}