{
  "type": "Feature",
  "properties": {
    "iso:country":"US",
    "sg:address":"3388 State University Dr",
    "sg:city":"Fort Valley",
    "sg:classifiers":[
        {
            "category":"Building & Trades",
            "subcategory":"Construction",
            "type":"Services"
        }
    ],
    "sg:phone":"+1 478 825 5158",
    "sg:postcode":"31030",
    "sg:province":"GA",
    "sg:tags":[
        "hanging",
        "contractor"
    ],
    "wof:name":"Genesis Painting",
    "wof:placetype":"venue"
},
  "geometry": {"coordinates":[-83.91969,32.514847],"type":"Point"}
}