{
  "type": "Feature",
  "properties": {
    "addr:full":"2050 Eatonton Rd Madison GA 30650",
    "addr:housenumber":"2050",
    "addr:postcode":"30650",
    "addr:street":"Eatonton Rd",
    "iso:country":"US",
    "sg:address":"2050 Eatonton Rd",
    "sg:city":"Madison",
    "sg:classifiers":[
        {
            "category":"Restaurant",
            "type":"Food & Drink"
        }
    ],
    "sg:menulink":"http://www.allmenus.com/ga/madison/140478-waffle-house/menu/",
    "sg:phone":"+1 706 356 2112",
    "sg:postcode":"30650",
    "sg:province":"GA",
    "sg:tags":[
        "american"
    ],
    "wof:name":"Waffle House",
    "wof:placetype":"venue"
},
  "geometry": {"coordinates":[-83.471138,33.54691],"type":"Point"}
}