{
  "type": "Feature",
  "properties": {
    "addr:full":"5306 Lower Meigs Rd Moultrie GA 31768",
    "addr:housenumber":"5306",
    "addr:postcode":"31768",
    "addr:street":"Lower Meigs Rd",
    "iso:country":"US",
    "sg:address":"5306 Lower Meigs Rd",
    "sg:city":"Moultrie",
    "sg:classifiers":[
        {
            "category":"Shopping",
            "type":"Retail Goods"
        }
    ],
    "sg:phone":"+1 229 941 2892",
    "sg:postcode":"31768",
    "sg:province":"GA",
    "sg:tags":[
        "merchandise"
    ],
    "wof:name":"Scites Body Shop",
    "wof:placetype":"venue"
},
  "geometry": {"coordinates":[-83.98860000000001,31.080972],"type":"Point"}
}