{
  "type": "Feature",
  "properties": {
    "iso:country":"US",
    "sg:address":"3976 Bankhead Hwy",
    "sg:city":"Douglasville",
    "sg:classifiers":[
        {
            "category":"Building & Trades",
            "subcategory":"Construction",
            "type":"Services"
        }
    ],
    "sg:phone":"+1 770 577 5770",
    "sg:postcode":"30134",
    "sg:province":"GA",
    "sg:tags":[
        "air",
        "heating",
        "conditioning/hvac"
    ],
    "sg:website":"www.dependableservices.com",
    "wof:name":"Dependable Services",
    "wof:placetype":"venue"
},
  "geometry": {"coordinates":[-84.702551,33.782818],"type":"Point"}
}