{
  "type": "Feature",
  "properties": {
    "addr:full":"3684 Community Rd Brunswick GA 31520",
    "addr:housenumber":"3684",
    "addr:postcode":"31520",
    "addr:street":"Community Rd",
    "iso:country":"US",
    "sg:address":"3684 Community Rd",
    "sg:city":"Brunswick",
    "sg:classifiers":[
        {
            "category":"Wholesale",
            "subcategory":"Construction Materials",
            "type":"Manufacturing & Wholesale Goods"
        }
    ],
    "sg:phone":"+1 912 265 5885",
    "sg:postcode":"31520",
    "sg:province":"GA",
    "sg:tags":[
        "tile",
        "ceramic",
        "accessory"
    ],
    "wof:name":"Modern Tile & Stone Inc",
    "wof:placetype":"venue"
},
  "geometry": {"coordinates":[-81.49536000000001,31.20231],"type":"Point"}
}