{
  "type": "Feature",
  "properties": {
    "addr:full":"326 Chesterfield Rd Bogart GA 30622",
    "addr:housenumber":"326",
    "addr:postcode":"30622",
    "addr:street":"Chesterfield Rd",
    "iso:country":"US",
    "sg:address":"326 Chesterfield Rd",
    "sg:city":"Bogart",
    "sg:classifiers":[
        {
            "category":"Shopping",
            "subcategory":"Clothing, Apparel, & Fashions",
            "type":"Retail Goods"
        }
    ],
    "sg:phone":"+1 706 354 6711",
    "sg:postcode":"30622",
    "sg:province":"GA",
    "wof:name":"Muckles Boutique",
    "wof:placetype":"venue"
},
  "geometry": {"coordinates":[-83.46485199999999,33.956087],"type":"Point"}
}