{
  "type": "Feature",
  "properties": {
    "iso:country":"US",
    "sg:address":"170 Treadwick Dr",
    "sg:city":"Atlanta",
    "sg:classifiers":[
        {
            "category":"Professional",
            "subcategory":"Management & Consulting",
            "type":"Services"
        }
    ],
    "sg:phone":"+1 770 396 7573",
    "sg:postcode":"30350",
    "sg:province":"GA",
    "wof:name":"Demick & Associates LLC",
    "wof:placetype":"venue"
},
  "geometry": {"coordinates":[-84.291213,33.961314],"type":"Point"}
}