{
  "type": "Feature",
  "properties": {
    "addr:full":"1125 E Lamar St Americus GA 31709",
    "addr:housenumber":"1125",
    "addr:postcode":"31709",
    "addr:street":"E Lamar St",
    "iso:country":"US",
    "sg:address":"1125 E Lamar St",
    "sg:city":"Americus",
    "sg:classifiers":[
        {
            "category":"Professional",
            "subcategory":"Accounting & Tax Preparation",
            "type":"Services"
        }
    ],
    "sg:phone":"+1 229 924 8144",
    "sg:postcode":"31709",
    "sg:province":"GA",
    "sg:tags":[
        "accountant"
    ],
    "wof:name":"Strickland Accounting LLC",
    "wof:placetype":"venue"
},
  "geometry": {"coordinates":[-84.21785199999999,32.071347],"type":"Point"}
}