{
  "type": "Feature",
  "properties": {
    "iso:country":"US",
    "sg:address":"1204 Wellington Ct",
    "sg:city":"Decatur",
    "sg:classifiers":[
        {
            "category":"Professional",
            "subcategory":"Business Services",
            "type":"Services"
        }
    ],
    "sg:phone":"+1 404 241 4139",
    "sg:postcode":"30034",
    "sg:province":"GA",
    "wof:name":"Crawl & Livingston Enterprises",
    "wof:placetype":"venue"
},
  "geometry": {"coordinates":[-84.259906,33.698151],"type":"Point"}
}