{
  "type": "Feature",
  "properties": {
    "addr:full":"4470 Thornwood Trl Stone Mountain GA 30083",
    "addr:housenumber":"4470",
    "addr:postcode":"30083",
    "addr:street":"Thornwood Trl",
    "iso:country":"US",
    "sg:address":"4470 Thornwood Trl",
    "sg:city":"Stone Mountain",
    "sg:classifiers":[
        {
            "category":"Arts & Performance",
            "subcategory":"Theater",
            "type":"Entertainment"
        }
    ],
    "sg:phone":"+1 404 292 9400",
    "sg:postcode":"30083",
    "sg:province":"GA",
    "sg:tags":[
        "theatrical"
    ],
    "wof:name":"New Jack Entertainment",
    "wof:placetype":"venue"
},
  "geometry": {"coordinates":[-84.20761,33.760065],"type":"Point"}
}