{
  "type": "Feature",
  "properties": {
    "iso:country":"US",
    "sg:address":"1011 W Gordon Ave",
    "sg:city":"Albany",
    "sg:classifiers":[
        {
            "category":"Personal",
            "subcategory":"Beauty Salon",
            "type":"Services"
        }
    ],
    "sg:phone":"+1 229 435 9933",
    "sg:postcode":"31701",
    "sg:province":"GA",
    "sg:tags":[
        "hair",
        "stylist"
    ],
    "wof:name":"Angel Hands Hair Dezigns",
    "wof:placetype":"venue"
},
  "geometry": {"coordinates":[-84.17401700000001,31.568129],"type":"Point"}
}