{
  "type": "Feature",
  "properties": {
    "iso:country":"US",
    "sg:address":"401 W 56th St",
    "sg:city":"Savannah",
    "sg:classifiers":[
        {
            "category":"Organizations",
            "subcategory":"Religious Organization",
            "type":"Services"
        }
    ],
    "sg:phone":"+1 912 236 3816",
    "sg:postcode":"31405",
    "sg:province":"GA",
    "sg:tags":[
        "church"
    ],
    "wof:name":"Saint Peters Baptist Church",
    "wof:placetype":"venue"
},
  "geometry": {"coordinates":[-81.112645,32.044371],"type":"Point"}
}