{
  "type": "Feature",
  "properties": {
    "addr:full":"123 E Atlanta Rd Ste 100 Stockbridge GA 30281",
    "addr:housenumber":"123",
    "addr:postcode":"30281",
    "addr:street":"E Atlanta Rd Ste 100",
    "iso:country":"US",
    "sg:address":"123 E Atlanta Rd Ste 100",
    "sg:city":"Stockbridge",
    "sg:classifiers":[
        {
            "category":"Professional",
            "subcategory":"Lawyer & Legal Services",
            "type":"Services"
        }
    ],
    "sg:phone":"+1 770 506 9092",
    "sg:postcode":"30281",
    "sg:province":"GA",
    "sg:tags":[
        "information",
        "attorney",
        "referral"
    ],
    "wof:name":"Ted N Echols' Pc",
    "wof:placetype":"venue"
},
  "geometry": {"coordinates":[-84.232716,33.547038],"type":"Point"}
}