{
  "type": "Feature",
  "properties": {
    "addr:full":"433 E Ontario Ave SW Atlanta GA 30310",
    "addr:housenumber":"433",
    "addr:postcode":"30310",
    "addr:street":"E Ontario Ave Sw",
    "iso:country":"US",
    "sg:address":"433 E Ontario Ave SW",
    "sg:city":"Atlanta",
    "sg:classifiers":[
        {
            "category":"Shopping",
            "subcategory":"Florist",
            "type":"Retail Goods"
        }
    ],
    "sg:phone":"+1 404 755 4488",
    "sg:postcode":"30310",
    "sg:province":"GA",
    "wof:name":"Ann Flowers Fouch",
    "wof:placetype":"venue"
},
  "geometry": {"coordinates":[-84.43810999999999,33.743542],"type":"Point"}
}