{
  "type": "Feature",
  "properties": {
    "addr:full":"300 White Ingram Pkwy Dallas GA 30132",
    "addr:housenumber":"300",
    "addr:postcode":"30132",
    "addr:street":"White Ingram Pkwy",
    "iso:country":"US",
    "sg:address":"300 White Ingram Pkwy",
    "sg:city":"Dallas",
    "sg:classifiers":[
        {
            "category":"Government",
            "subcategory":"Office",
            "type":"Public Place"
        }
    ],
    "sg:phone":"+1 770 443 7841",
    "sg:postcode":"30132",
    "sg:province":"GA",
    "sg:tags":[
        "state",
        "resource"
    ],
    "wof:name":"Human Resources Dept",
    "wof:placetype":"venue"
},
  "geometry": {"coordinates":[-84.79725500000001,33.912292],"type":"Point"}
}