{
  "type": "Feature",
  "properties": {
    "addr:full":"5337 Hearthstone Dr Gainesville GA 30504",
    "addr:housenumber":"5337",
    "addr:postcode":"30504",
    "addr:street":"Hearthstone Dr",
    "iso:country":"US",
    "sg:address":"5337 Hearthstone Dr",
    "sg:city":"Gainesville",
    "sg:classifiers":[
        {
            "category":"Building & Trades",
            "subcategory":"Construction",
            "type":"Services"
        }
    ],
    "sg:phone":"+1 770 533 9777",
    "sg:postcode":"30504",
    "sg:province":"GA",
    "sg:tags":[
        "ceiling",
        "contractor"
    ],
    "wof:name":"Mc Kenney Acoustical",
    "wof:placetype":"venue"
},
  "geometry": {"coordinates":[-83.92328000000001,34.236633],"type":"Point"}
}