{
  "type": "Feature",
  "properties": {
    "iso:country":"US",
    "sg:address":"204 Hazel Ave",
    "sg:city":"Nashville",
    "sg:classifiers":[
        {
            "category":"Government",
            "subcategory":"Office",
            "type":"Public Place"
        }
    ],
    "sg:phone":"+1 229 686 5648",
    "sg:postcode":"31639",
    "sg:province":"GA",
    "wof:name":"Berrien Cnty Senior Citizens",
    "wof:placetype":"venue"
},
  "geometry": {"coordinates":[-83.250015,31.198869],"type":"Point"}
}