{
  "type": "Feature",
  "properties": {
    "addr:full":"113 Shoppers Way Brunswick GA 31525",
    "addr:housenumber":"113",
    "addr:postcode":"31525",
    "addr:street":"Shoppers Way",
    "iso:country":"US",
    "sg:address":"113 Shoppers Way",
    "sg:city":"Brunswick",
    "sg:classifiers":[
        {
            "category":"Insurance",
            "subcategory":"Insurance Agent",
            "type":"Services"
        },
        {
            "category":"Insurance",
            "subcategory":"Hazard Insurance",
            "type":"Services"
        },
        {
            "category":"Insurance",
            "subcategory":"Title Insurance",
            "type":"Services"
        },
        {
            "category":"Insurance",
            "subcategory":"Life Insurance",
            "type":"Services"
        }
    ],
    "sg:phone":"+1 912 265 4287",
    "sg:postcode":"31525",
    "sg:province":"GA",
    "sg:tags":[
        "business",
        "auto",
        "commercial",
        "homeowner",
        "motorcycle",
        "renter"
    ],
    "wof:name":"Allstate Insurance Company - Raquel Lee",
    "wof:placetype":"venue"
},
  "geometry": {"coordinates":[-81.488151,31.219329],"type":"Point"}
}