{
  "type": "Feature",
  "properties": {
    "iso:country":"US",
    "sg:address":"4216 Alabama Hwy",
    "sg:city":"Rome",
    "sg:classifiers":[
        {
            "category":"Organizations",
            "subcategory":"Religious Organization",
            "type":"Services"
        }
    ],
    "sg:phone":"+1 706 234 6941",
    "sg:postcode":"30165",
    "sg:province":"GA",
    "sg:tags":[
        "church"
    ],
    "wof:name":"Jehovah's Witnesses",
    "wof:placetype":"venue"
},
  "geometry": {"coordinates":[-85.296036,34.261939],"type":"Point"}
}