{
  "type": "Feature",
  "properties": {
    "addr:full":"107 Forest Pkwy Ste 800 Forest Park GA 30297",
    "addr:housenumber":"107",
    "addr:postcode":"30297",
    "addr:street":"Forest Pkwy Ste 800;Park",
    "iso:country":"US",
    "sg:address":"107 Forest Pkwy Ste 800",
    "sg:city":"Forest Park",
    "sg:classifiers":[
        {
            "category":"Autos & Motor Vehicles",
            "subcategory":"Auto Supplies",
            "type":"Retail Goods"
        }
    ],
    "sg:phone":"+1 404 361 7060",
    "sg:postcode":"30297",
    "sg:province":"GA",
    "sg:tags":[
        "tire"
    ],
    "wof:name":"Trelleborg Wheel Systems",
    "wof:placetype":"venue"
},
  "geometry": {"coordinates":[-84.388358,33.618554],"type":"Point"}
}