{
  "type": "Feature",
  "properties": {
    "addr:full":"6205 Barfield Rd NE Atlanta GA 30328",
    "addr:housenumber":"6205",
    "addr:postcode":"30328",
    "addr:street":"Barfield Rd Ne",
    "iso:country":"US",
    "sg:address":"6205 Barfield Rd NE",
    "sg:city":"Atlanta",
    "sg:classifiers":[
        {
            "category":"Banks & Credit Unions",
            "subcategory":"Bank",
            "type":"Services"
        }
    ],
    "sg:phone":"+1 404 255 1009",
    "sg:postcode":"30328",
    "sg:province":"GA",
    "sg:tags":[
        "broker",
        "mortgage"
    ],
    "wof:name":"Mortgage Center Inc",
    "wof:placetype":"venue"
},
  "geometry": {"coordinates":[-84.359809,33.923199],"type":"Point"}
}