{
  "type": "Feature",
  "properties": {
    "addr:full":"5110 Chattahoochee St Flowery Branch GA 30542",
    "addr:housenumber":"5110",
    "addr:postcode":"30542",
    "addr:street":"Chattahoochee St",
    "iso:country":"US",
    "sg:address":"5110 Chattahoochee St",
    "sg:city":"Flowery Branch",
    "sg:classifiers":[
        {
            "category":"Retail",
            "subcategory":"Auto Rental",
            "type":"Services"
        }
    ],
    "sg:phone":"+1 770 967 2346",
    "sg:postcode":"30542",
    "sg:province":"GA",
    "sg:tags":[
        "renting",
        "truck",
        "leasing"
    ],
    "wof:name":"U-Haul Co",
    "wof:placetype":"venue"
},
  "geometry": {"coordinates":[-83.92286300000001,34.188993],"type":"Point"}
}