{
  "type": "Feature",
  "properties": {
    "iso:country":"US",
    "sg:address":"80 Upland Trl",
    "sg:city":"Oxford",
    "sg:classifiers":[
        {
            "category":"Banks & Credit Unions",
            "subcategory":"Investment Brokerage",
            "type":"Services"
        }
    ],
    "sg:phone":"+1 770 385 8880",
    "sg:postcode":"30054",
    "sg:province":"GA",
    "sg:tags":[
        "security"
    ],
    "wof:name":"RMS Enterprises Inc",
    "wof:placetype":"venue"
},
  "geometry": {"coordinates":[-83.91565,33.681269],"type":"Point"}
}