{
  "type": "Feature",
  "properties": {
    "iso:country":"US",
    "sg:address":"710 Jones Creek",
    "sg:city":"Evans",
    "sg:classifiers":[
        {
            "category":"Professional",
            "type":"Services"
        }
    ],
    "sg:phone":"+1 706 228 2848",
    "sg:postcode":"30809",
    "sg:province":"GA",
    "sg:tags":[
        "establishment"
    ],
    "wof:name":"Hodge A",
    "wof:placetype":"venue"
},
  "geometry": {"coordinates":[-82.095608,33.549053],"type":"Point"}
}