{
  "type": "Feature",
  "properties": {
    "addr:full":"4010 Dunwoody Park Atlanta GA 30338",
    "addr:housenumber":"4010",
    "addr:postcode":"30338",
    "addr:street":"Dunwoody Park",
    "iso:country":"US",
    "sg:address":"4010 Dunwoody Park",
    "sg:city":"Atlanta",
    "sg:classifiers":[
        {
            "category":"Professional",
            "type":"Services"
        }
    ],
    "sg:phone":"+1 770 551 9558",
    "sg:postcode":"30338",
    "sg:province":"GA",
    "wof:name":"James Ward",
    "wof:placetype":"venue"
},
  "geometry": {"coordinates":[-84.31167499999999,33.923877],"type":"Point"}
}