{
  "type": "Feature",
  "properties": {
    "iso:country":"US",
    "sg:address":"1810 Bishop Lake Ct",
    "sg:city":"Marietta",
    "sg:classifiers":[
        {
            "category":"Organizations",
            "subcategory":"Religious Organization",
            "type":"Services"
        }
    ],
    "sg:phone":"+1 770 579 5448",
    "sg:postcode":"30062",
    "sg:province":"GA",
    "sg:tags":[
        "church"
    ],
    "wof:name":"Mt Zion United Methodist Chr",
    "wof:placetype":"venue"
},
  "geometry": {"coordinates":[-84.426225,33.991836],"type":"Point"}
}