{
  "type": "Feature",
  "properties": {
    "iso:country":"US",
    "sg:address":"4454 Bogan Gates Trl",
    "sg:city":"Buford",
    "sg:classifiers":[
        {
            "category":"Professional",
            "subcategory":"Business Services",
            "type":"Services"
        }
    ],
    "sg:phone":"+1 770 309 5152",
    "sg:postcode":"30519",
    "sg:province":"GA",
    "sg:tags":[
        "organizing",
        "services-household"
    ],
    "wof:name":"Risk Management Of Georgia",
    "wof:placetype":"venue"
},
  "geometry": {"coordinates":[-83.947639,34.124294],"type":"Point"}
}