{
  "type": "Feature",
  "properties": {
    "iso:country":"US",
    "sg:address":"115 Church St",
    "sg:city":"Bainbridge",
    "sg:classifiers":[
        {
            "category":"Organizations",
            "subcategory":"Religious Organization",
            "type":"Services"
        }
    ],
    "sg:phone":"+1 229 246 3012",
    "sg:postcode":"39817",
    "sg:province":"GA",
    "sg:tags":[
        "church"
    ],
    "wof:name":"First African Church Of Bnbrdg",
    "wof:placetype":"venue"
},
  "geometry": {"coordinates":[-84.59129,30.914746],"type":"Point"}
}