{
  "type": "Feature",
  "properties": {
    "addr:full":"1810 Auger Dr Tucker GA 30084",
    "addr:housenumber":"1810",
    "addr:postcode":"30084",
    "addr:street":"Auger Dr",
    "iso:country":"US",
    "sg:address":"1810 Auger Dr",
    "sg:city":"Tucker",
    "sg:classifiers":[
        {
            "category":"Food & Beverages",
            "subcategory":"Bakery",
            "type":"Retail Goods"
        },
        {
            "category":"Bakery",
            "type":"Food & Drink"
        }
    ],
    "sg:phone":"+1 770 724 1367",
    "sg:postcode":"30084",
    "sg:province":"GA",
    "sg:tags":[
        "bakers-wholesale"
    ],
    "wof:name":"La Baguette",
    "wof:placetype":"venue"
},
  "geometry": {"coordinates":[-84.196577,33.836122],"type":"Point"}
}