{
  "type": "Feature",
  "properties": {
    "addr:full":"706 Rock Springs Rd Lawrenceville GA 30043",
    "addr:housenumber":"706",
    "addr:postcode":"30043",
    "addr:street":"Rock Springs Rd",
    "iso:country":"US",
    "sg:address":"706 Rock Springs Rd",
    "sg:city":"Lawrenceville",
    "sg:classifiers":[
        {
            "category":"Building & Trades",
            "subcategory":"Construction",
            "type":"Services"
        }
    ],
    "sg:phone":"+1 770 945 1601",
    "sg:postcode":"30043",
    "sg:province":"GA",
    "sg:tags":[
        "contractor"
    ],
    "wof:name":"Advance Insulation Inc",
    "wof:placetype":"venue"
},
  "geometry": {"coordinates":[-84.009483,34.045188],"type":"Point"}
}