{
  "type": "Feature",
  "properties": {
    "addr:full":"37 N Court Ave Blakely GA 31730",
    "addr:housenumber":"37",
    "addr:postcode":"31730",
    "addr:street":"N Court Ave",
    "iso:country":"US",
    "sg:address":"37 N Court Ave",
    "sg:city":"Blakely",
    "sg:classifiers":[
        {
            "category":"Personal",
            "subcategory":"Beauty Salon",
            "type":"Services"
        }
    ],
    "sg:phone":"+1 229 723 5568",
    "sg:postcode":"31730",
    "sg:province":"GA",
    "sg:tags":[
        "shop"
    ],
    "wof:name":"Advance Hair & Body Salon",
    "wof:placetype":"venue"
},
  "geometry": {"coordinates":[-84.20962400000001,31.232031],"type":"Point"}
}