{
  "type": "Feature",
  "properties": {
    "iso:country":"US",
    "sg:address":"62 Technology Dr",
    "sg:city":"Alpharetta",
    "sg:classifiers":[
        {
            "category":"Wholesale",
            "subcategory":"Electrical",
            "type":"Manufacturing & Wholesale Goods"
        }
    ],
    "sg:phone":"+1 770 772 7000",
    "sg:postcode":"30005",
    "sg:province":"GA",
    "sg:tags":[
        "electric",
        "motor"
    ],
    "wof:name":"Sarka Sales Agency",
    "wof:placetype":"venue"
},
  "geometry": {"coordinates":[-84.22046,34.115238],"type":"Point"}
}