{
  "type": "Feature",
  "properties": {
    "addr:full":"2330 Old US Highway 41 Valdosta GA 31601",
    "addr:housenumber":"2330",
    "addr:postcode":"31601",
    "addr:street":"Old Us Highway 41",
    "iso:country":"US",
    "sg:address":"2330 Old US Highway 41",
    "sg:city":"Valdosta",
    "sg:classifiers":[
        {
            "category":"Autos & Motor Vehicles",
            "subcategory":"Boat Sales",
            "type":"Retail Goods"
        },
        {
            "category":"Government",
            "subcategory":"Department Of Motor Vehicles",
            "type":"Public Place"
        }
    ],
    "sg:phone":"+1 229 244 6500",
    "sg:postcode":"31601",
    "sg:province":"GA",
    "sg:tags":[
        "trailer"
    ],
    "wof:name":"Winsel's Boats",
    "wof:placetype":"venue"
},
  "geometry": {"coordinates":[-83.250401,30.801164],"type":"Point"}
}