{
  "type": "Feature",
  "properties": {
    "addr:full":"197 Oak Leaf Dr SW Cartersville GA 30120",
    "addr:housenumber":"197",
    "addr:postcode":"30120",
    "addr:street":"Oak Leaf Dr Sw",
    "iso:country":"US",
    "sg:address":"197 Oak Leaf Dr SW",
    "sg:city":"Cartersville",
    "sg:classifiers":[
        {
            "category":"Retail",
            "subcategory":"Portrait Studio",
            "type":"Services"
        }
    ],
    "sg:phone":"+1 770 336 9096",
    "sg:postcode":"30120",
    "sg:province":"GA",
    "sg:tags":[
        "photo"
    ],
    "wof:name":"In Motion Photography",
    "wof:placetype":"venue"
},
  "geometry": {"coordinates":[-84.894744,34.221421],"type":"Point"}
}