{
  "type": "Feature",
  "properties": {
    "iso:country":"US",
    "sg:address":"3316 Pretty Branch Dr SE",
    "sg:city":"Smyrna",
    "sg:classifiers":[
        {
            "category":"Building & Trades",
            "subcategory":"Construction",
            "type":"Services"
        }
    ],
    "sg:phone":"+1 770 434 4087",
    "sg:postcode":"30080",
    "sg:province":"GA",
    "sg:tags":[
        "contractor"
    ],
    "wof:name":"Shaw Contracting & Design",
    "wof:placetype":"venue"
},
  "geometry": {"coordinates":[-84.513182,33.871661],"type":"Point"}
}