{
  "type": "Feature",
  "properties": {
    "addr:full":"1380 Capital Cir Lawrenceville GA 30043",
    "addr:housenumber":"1380",
    "addr:postcode":"30043",
    "addr:street":"Capital Cir",
    "iso:country":"US",
    "sg:address":"1380 Capital Cir",
    "sg:city":"Lawrenceville",
    "sg:classifiers":[
        {
            "category":"Home & Garden",
            "subcategory":"Carpets & Floor Coverings",
            "type":"Retail Goods"
        }
    ],
    "sg:phone":"+1 770 513 9113",
    "sg:postcode":"30043",
    "sg:province":"GA",
    "sg:tags":[
        "dealer",
        "rug"
    ],
    "wof:name":"Floor Coverings Intl",
    "wof:placetype":"venue"
},
  "geometry": {"coordinates":[-84.05547300000001,33.968896],"type":"Point"}
}