{
  "type": "Feature",
  "properties": {
    "iso:country":"US",
    "sg:address":"207 Banks Station",
    "sg:city":"Fayetteville",
    "sg:classifiers":[
        {
            "category":"Shopping",
            "type":"Retail Goods"
        }
    ],
    "sg:phone":"+1 770 412 7788",
    "sg:postcode":"30214",
    "sg:province":"GA",
    "sg:tags":[
        "supply"
    ],
    "wof:name":"South Metro Copier Systems",
    "wof:placetype":"venue"
},
  "geometry": {"coordinates":[-84.438096,33.469675],"type":"Point"}
}