{
  "type": "Feature",
  "properties": {
    "iso:country":"US",
    "sg:address":"4151 Memorial Dr",
    "sg:city":"Decatur",
    "sg:classifiers":[
        {
            "category":"Social Services",
            "type":"Services"
        }
    ],
    "sg:phone":"+1 404 284 6880",
    "sg:postcode":"30032",
    "sg:province":"GA",
    "sg:tags":[
        "individual",
        "family",
        "therapist",
        "marriage",
        "child",
        "counselor"
    ],
    "wof:name":"Matters Of The Heart",
    "wof:placetype":"venue"
},
  "geometry": {"coordinates":[-84.250923,33.769641],"type":"Point"}
}