{
  "type": "Feature",
  "properties": {
    "addr:full":"4773 High Oak Dr Macon GA 31210",
    "addr:housenumber":"4773",
    "addr:postcode":"31210",
    "addr:street":"High Oak Dr",
    "iso:country":"US",
    "sg:address":"4773 High Oak Dr",
    "sg:city":"Macon",
    "sg:classifiers":[
        {
            "category":"Freight",
            "type":"Transportation"
        }
    ],
    "sg:phone":"+1 478 461 4351",
    "sg:postcode":"31210",
    "sg:province":"GA",
    "sg:tags":[
        "operator",
        "local",
        "trucking"
    ],
    "wof:name":"JC Trucking",
    "wof:placetype":"venue"
},
  "geometry": {"coordinates":[-83.71940600000001,32.833423],"type":"Point"}
}