{
  "type": "Feature",
  "properties": {
    "addr:full":"943 Buford Hwy Buford GA 30518",
    "addr:housenumber":"943",
    "addr:postcode":"30518",
    "addr:street":"Buford Hwy",
    "iso:country":"US",
    "sg:address":"943 Buford Hwy",
    "sg:city":"Buford",
    "sg:classifiers":[
        {
            "category":"Wholesale",
            "subcategory":"Hardware",
            "type":"Manufacturing & Wholesale Goods"
        },
        {
            "category":"Wholesale",
            "subcategory":"Electrical",
            "type":"Manufacturing & Wholesale Goods"
        }
    ],
    "sg:phone":"+1 770 614 1401",
    "sg:postcode":"30518",
    "sg:province":"GA",
    "sg:tags":[
        "supermarket",
        "equipment",
        "representative",
        "refrigerator",
        "freezer"
    ],
    "wof:name":"Redico Inc",
    "wof:placetype":"venue"
},
  "geometry": {"coordinates":[-84.037819,34.081807],"type":"Point"}
}