{
  "type": "Feature",
  "properties": {
    "addr:full":"1747 Tunbridge Ln Lawrenceville GA 30043",
    "addr:housenumber":"1747",
    "addr:postcode":"30043",
    "addr:street":"Tunbridge Ln",
    "iso:country":"US",
    "sg:address":"1747 Tunbridge Ln",
    "sg:city":"Lawrenceville",
    "sg:classifiers":[
        {
            "category":"Professional",
            "subcategory":"Computer Services",
            "type":"Services"
        }
    ],
    "sg:phone":"+1 404 417 0646",
    "sg:postcode":"30043",
    "sg:province":"GA",
    "sg:tags":[
        "consultant",
        "designer"
    ],
    "wof:name":"Lukansz Arendt Consulting",
    "wof:placetype":"venue"
},
  "geometry": {"coordinates":[-84.04189599999999,33.984655],"type":"Point"}
}