{
  "type": "Feature",
  "properties": {
    "addr:full":"1500 Greyfield Ln Atlanta GA 30350",
    "addr:housenumber":"1500",
    "addr:postcode":"30350",
    "addr:street":"Greyfield Ln",
    "iso:country":"US",
    "sg:address":"1500 Greyfield Ln",
    "sg:city":"Atlanta",
    "sg:classifiers":[
        {
            "category":"Real Estate",
            "subcategory":"Real Estate Operator",
            "type":"Services"
        }
    ],
    "sg:phone":"+1 770 998 3704",
    "sg:postcode":"30350",
    "sg:province":"GA",
    "sg:tags":[
        "apartment"
    ],
    "wof:name":"Greyfield Apts",
    "wof:placetype":"venue"
},
  "geometry": {"coordinates":[-84.34345399999999,33.999676],"type":"Point"}
}