{
  "type": "Feature",
  "properties": {
    "iso:country":"US",
    "sg:address":"107 Sinclair Marina Rd NE",
    "sg:city":"Milledgeville",
    "sg:classifiers":[
        {
            "category":"Organizations",
            "subcategory":"Religious Organization",
            "type":"Services"
        }
    ],
    "sg:phone":"+1 478 452 2285",
    "sg:postcode":"31061",
    "sg:province":"GA",
    "wof:name":"Victory Baptist Church",
    "wof:placetype":"venue"
},
  "geometry": {"coordinates":[-83.28189399999999,33.172932],"type":"Point"}
}