{
  "type": "Feature",
  "properties": {
    "iso:country":"US",
    "sg:address":"8 E 4th Ave",
    "sg:city":"Rome",
    "sg:classifiers":[
        {
            "category":"Personal",
            "type":"Services"
        }
    ],
    "sg:phone":"+1 706 232 1899",
    "sg:postcode":"30162",
    "sg:province":"GA",
    "sg:tags":[
        "therapist",
        "massage"
    ],
    "wof:name":"Soothing Source Massage Thrpy",
    "wof:placetype":"venue"
},
  "geometry": {"coordinates":[-85.170958,34.253848],"type":"Point"}
}