{
  "type": "Feature",
  "properties": {
    "addr:full":"2503 Peach Orchard Rd Augusta GA 30906",
    "addr:housenumber":"2503",
    "addr:postcode":"30906",
    "addr:street":"Peach Orchard Rd",
    "iso:country":"US",
    "sg:address":"2503 Peach Orchard Rd",
    "sg:city":"Augusta",
    "sg:classifiers":[
        {
            "category":"Home & Garden",
            "subcategory":"Furniture",
            "type":"Retail Goods"
        }
    ],
    "sg:phone":"+1 706 772 7860",
    "sg:postcode":"30906",
    "sg:province":"GA",
    "sg:tags":[
        "mattress"
    ],
    "wof:name":"Mattress & More Quality Furn",
    "wof:placetype":"venue"
},
  "geometry": {"coordinates":[-82.016379,33.428495],"type":"Point"}
}