{
  "type": "Feature",
  "properties": {
    "iso:country":"US",
    "sg:address":"2540 Conway Vickers Rd",
    "sg:city":"Ambrose",
    "sg:classifiers":[
        {
            "category":"Real Estate",
            "subcategory":"Real Estate Services",
            "type":"Services"
        },
        {
            "category":"Real Estate",
            "subcategory":"Real Estate Agent",
            "type":"Services"
        }
    ],
    "sg:phone":"+1 912 384 1053",
    "sg:postcode":"31512",
    "sg:province":"GA",
    "sg:tags":[
        "buyer",
        "broker",
        "auctioneer"
    ],
    "wof:name":"Kenneth Vickers Realty",
    "wof:placetype":"venue"
},
  "geometry": {"coordinates":[-83.000023,31.482146],"type":"Point"}
}