{
  "type": "Feature",
  "properties": {
    "addr:full":"1650 Anderson Mill Rd Austell GA 30106",
    "addr:housenumber":"1650",
    "addr:postcode":"30106",
    "addr:street":"Anderson Mill Rd",
    "iso:country":"US",
    "sg:address":"1650 Anderson Mill Rd",
    "sg:city":"Austell",
    "sg:classifiers":[
        {
            "category":"Health Services",
            "subcategory":"Nursing And Care Facility",
            "type":"Services"
        }
    ],
    "sg:phone":"+1 770 485 2237",
    "sg:postcode":"30106",
    "sg:province":"GA",
    "wof:name":"Keiko Personal Care System",
    "wof:placetype":"venue"
},
  "geometry": {"coordinates":[-84.60251700000001,33.848136],"type":"Point"}
}