{
  "type": "Feature",
  "properties": {
    "iso:country":"US",
    "sg:address":"721 S Milledge Ave",
    "sg:city":"Athens",
    "sg:classifiers":[
        {
            "category":"Manufacturing",
            "subcategory":"Lumber",
            "type":"Manufacturing & Wholesale Goods"
        }
    ],
    "sg:phone":"+1 706 543 1085",
    "sg:postcode":"30605",
    "sg:province":"GA",
    "sg:tags":[
        "operation",
        "timber",
        "tract"
    ],
    "wof:name":"Mill Corp",
    "wof:placetype":"venue"
},
  "geometry": {"coordinates":[-83.387742,33.945033],"type":"Point"}
}