{
  "type": "Feature",
  "properties": {
    "iso:country":"US",
    "sg:address":"250 Rolling Meadows Dr",
    "sg:city":"Ringgold",
    "sg:classifiers":[
        {
            "category":"Professional",
            "type":"Services"
        }
    ],
    "sg:phone":"+1 706 937 5165",
    "sg:postcode":"30736",
    "sg:province":"GA",
    "wof:name":"GMC Form Service",
    "wof:placetype":"venue"
},
  "geometry": {"coordinates":[-85.16965500000001,34.902605],"type":"Point"}
}