{
  "type": "Feature",
  "properties": {
    "iso:country":"US",
    "sg:address":"1900 W Bay St",
    "sg:city":"Savannah",
    "sg:classifiers":[
        {
            "category":"Restaurant",
            "type":"Food & Drink"
        }
    ],
    "sg:phone":"+1 912 232 3902",
    "sg:postcode":"31415",
    "sg:province":"GA",
    "sg:tags":[
        "chinese"
    ],
    "wof:name":"Happy China",
    "wof:placetype":"venue"
},
  "geometry": {"coordinates":[-81.121244,32.089111],"type":"Point"}
}