{
  "type": "Feature",
  "properties": {
    "iso:country":"US",
    "sg:address":"25 Southside Industrial Pkwy SE",
    "sg:city":"Atlanta",
    "sg:classifiers":[
        {
            "category":"Professional",
            "subcategory":"Business Services",
            "type":"Services"
        }
    ],
    "sg:phone":"+1 404 363 4100",
    "sg:postcode":"30354",
    "sg:province":"GA",
    "sg:tags":[
        "repossessing"
    ],
    "wof:name":"United Auto Recovery",
    "wof:placetype":"venue"
},
  "geometry": {"coordinates":[-84.38490299999999,33.65229],"type":"Point"}
}