{
  "type": "Feature",
  "properties": {
    "iso:country":"US",
    "sg:address":"1030 Matheson Way",
    "sg:city":"Alpharetta",
    "sg:classifiers":[
        {
            "category":"Professional",
            "subcategory":"Employment Agencies",
            "type":"Services"
        }
    ],
    "sg:phone":"+1 770 663 9988",
    "sg:postcode":"30022",
    "sg:province":"GA",
    "sg:tags":[
        "opportunity"
    ],
    "wof:name":"Locum Tenens Usa, Inc.",
    "wof:placetype":"venue"
},
  "geometry": {"coordinates":[-84.237556,34.011742],"type":"Point"}
}