{
  "type": "Feature",
  "properties": {
    "addr:full":"8833 Lexington Dr Jonesboro GA 30238",
    "addr:housenumber":"8833",
    "addr:postcode":"30238",
    "addr:street":"Lexington Dr",
    "iso:country":"US",
    "sg:address":"8833 Lexington Dr",
    "sg:city":"Jonesboro",
    "sg:classifiers":[
        {
            "category":"Education",
            "subcategory":"School",
            "type":"Public Place"
        }
    ],
    "sg:phone":"+1 770 210 8505",
    "sg:postcode":"30238",
    "sg:province":"GA",
    "wof:name":"Twin Cedars Youth Services",
    "wof:placetype":"venue"
},
  "geometry": {"coordinates":[-84.38237100000001,33.517712],"type":"Point"}
}