{
  "type": "Feature",
  "properties": {
    "addr:full":"4333 Post Rd Winston GA 30187",
    "addr:housenumber":"4333",
    "addr:postcode":"30187",
    "addr:street":"Post Rd",
    "iso:country":"US",
    "sg:address":"4333 Post Rd",
    "sg:city":"Winston",
    "sg:classifiers":[
        {
            "category":"Food & Beverages",
            "subcategory":"Groceries & Convenience Stores",
            "type":"Retail Goods"
        }
    ],
    "sg:phone":"+1 770 949 2768",
    "sg:postcode":"30187",
    "sg:province":"GA",
    "sg:tags":[
        "gasoline"
    ],
    "wof:name":"Midget Market",
    "wof:placetype":"venue"
},
  "geometry": {"coordinates":[-84.85474600000001,33.690434],"type":"Point"}
}