{
  "type": "Feature",
  "properties": {
    "iso:country":"US",
    "sg:address":"6333 N Sweetwater Rd",
    "sg:city":"Lithia Springs",
    "sg:classifiers":[
        {
            "category":"Professional",
            "subcategory":"Computer Services",
            "type":"Services"
        }
    ],
    "sg:phone":"+1 770 944 6993",
    "sg:postcode":"30122",
    "sg:province":"GA",
    "sg:tags":[
        "programing",
        "custom"
    ],
    "wof:name":"Bizesolutions Inc",
    "wof:placetype":"venue"
},
  "geometry": {"coordinates":[-84.66307399999999,33.798902],"type":"Point"}
}