{
  "type": "Feature",
  "properties": {
    "iso:country":"US",
    "sg:address":"200 4th St SW",
    "sg:city":"Cairo",
    "sg:classifiers":[
        {
            "category":"Shopping",
            "subcategory":"Gifts & Souvenirs",
            "type":"Retail Goods"
        }
    ],
    "sg:phone":"+1 229 378 8196",
    "sg:postcode":"39828",
    "sg:province":"GA",
    "wof:name":"Rees",
    "wof:placetype":"venue"
},
  "geometry": {"coordinates":[-84.21404699999999,30.877311],"type":"Point"}
}