{
  "type": "Feature",
  "properties": {
    "iso:country":"US",
    "sg:address":"295 Farm Track",
    "sg:city":"Roswell",
    "sg:classifiers":[
        {
            "category":"Communications",
            "subcategory":"Film & Video Production",
            "type":"Services"
        }
    ],
    "sg:phone":"+1 770 552 8336",
    "sg:postcode":"30075",
    "sg:province":"GA",
    "sg:tags":[
        "motion"
    ],
    "wof:name":"Cathy Roberts",
    "wof:placetype":"venue"
},
  "geometry": {"coordinates":[-84.38184800000001,34.021413],"type":"Point"}
}