{
  "type": "Feature",
  "properties": {
    "addr:full":"3451 Atlanta Industrial Pkwy NW Atlanta GA 30331",
    "addr:housenumber":"3451",
    "addr:postcode":"30331",
    "addr:street":"Atlanta Industrial Pkwy Nw",
    "iso:country":"US",
    "sg:address":"3451 Atlanta Industrial Pkwy NW",
    "sg:city":"Atlanta",
    "sg:classifiers":[
        {
            "category":"Manufacturing",
            "subcategory":"Metals",
            "type":"Manufacturing & Wholesale Goods"
        }
    ],
    "sg:phone":"+1 404 699 0726",
    "sg:postcode":"30331",
    "sg:province":"GA",
    "sg:tags":[
        "fabricator",
        "aluminum"
    ],
    "sg:website":"www.integrismetals.com",
    "wof:name":"Integris Metals",
    "wof:placetype":"venue"
},
  "geometry": {"coordinates":[-84.495497,33.795302],"type":"Point"}
}