{
  "type": "Feature",
  "properties": {
    "iso:country":"US",
    "sg:address":"7124 Pechtre Indstrl Blvd",
    "sg:city":"Norcross",
    "sg:classifiers":[
        {
            "category":"Food & Beverages",
            "subcategory":"Groceries & Convenience Stores",
            "type":"Retail Goods"
        }
    ],
    "sg:phone":"+1 770 263 7838",
    "sg:postcode":"30071",
    "sg:province":"GA",
    "wof:name":"Tomato Japanese Grocery",
    "wof:placetype":"venue"
},
  "geometry": {"coordinates":[-84.263409,33.930816],"type":"Point"}
}