{
  "type": "Feature",
  "properties": {
    "addr:full":"4050 US Hwy 84 Cairo GA 39828",
    "addr:housenumber":"4050",
    "addr:postcode":"39828",
    "addr:street":"Us Hwy 84",
    "iso:country":"US",
    "sg:address":"4050 US Hwy 84",
    "sg:city":"Cairo",
    "sg:classifiers":[
        {
            "category":"Food & Beverages",
            "subcategory":"Groceries & Convenience Stores",
            "type":"Retail Goods"
        }
    ],
    "sg:phone":"+1 229 551 9000",
    "sg:postcode":"39828",
    "sg:province":"GA",
    "wof:name":"Country Meat Market Inc",
    "wof:placetype":"venue"
},
  "geometry": {"coordinates":[-84.118689,30.868168],"type":"Point"}
}