{
  "type": "Feature",
  "properties": {
    "iso:country":"US",
    "sg:address":"6501 Standing Boy Rd",
    "sg:city":"Columbus",
    "sg:classifiers":[
        {
            "category":"Organizations",
            "subcategory":"Community Association",
            "type":"Services"
        }
    ],
    "sg:phone":"+1 706 324 7191",
    "sg:postcode":"31904",
    "sg:province":"GA",
    "sg:tags":[
        "club"
    ],
    "sg:website":"www.greenislandcc.org",
    "wof:name":"Green Island Country Club",
    "wof:placetype":"venue"
},
  "geometry": {"coordinates":[-85.011539,32.545494],"type":"Point"}
}