{
  "type": "Feature",
  "properties": {
    "iso:country":"US",
    "sg:address":"2614 Billings Rd",
    "sg:city":"Hephzibah",
    "sg:classifiers":[
        {
            "category":"Social Services",
            "subcategory":"Child Care",
            "type":"Services"
        }
    ],
    "sg:phone":"+1 706 798 5749",
    "sg:postcode":"30815",
    "sg:province":"GA",
    "sg:tags":[
        "day"
    ],
    "wof:name":"Squeezee Day Care",
    "wof:placetype":"venue"
},
  "geometry": {"coordinates":[-82.07826,33.395889],"type":"Point"}
}