{
  "type": "Feature",
  "properties": {
    "iso:country":"US",
    "sg:address":"2401 Mellon Ct",
    "sg:city":"Decatur",
    "sg:classifiers":[
        {
            "category":"Manufacturing",
            "subcategory":"Chemicals & Compounds",
            "type":"Manufacturing & Wholesale Goods"
        },
        {
            "category":"Wholesale",
            "subcategory":"Medical Equipment & Supplies",
            "type":"Manufacturing & Wholesale Goods"
        },
        {
            "category":"Shopping",
            "subcategory":"Pharmacy",
            "type":"Retail Goods"
        }
    ],
    "sg:phone":"+1 770 987 4745",
    "sg:postcode":"30035",
    "sg:province":"GA",
    "sg:tags":[
        "pharmaceutical",
        "product",
        "proprietary",
        "products-wholesale",
        "medicines-patent",
        "manufacturer"
    ],
    "wof:name":"US Pharmaceutical Corporation",
    "wof:placetype":"venue"
},
  "geometry": {"coordinates":[-84.16870900000001,33.71825],"type":"Point"}
}