{
  "type": "Feature",
  "properties": {
    "addr:full":"3214 Milledgeville Rd Augusta GA 30909",
    "addr:housenumber":"3214",
    "addr:postcode":"30909",
    "addr:street":"Milledgeville Rd",
    "iso:country":"US",
    "sg:address":"3214 Milledgeville Rd",
    "sg:city":"Augusta",
    "sg:classifiers":[
        {
            "category":"Retail",
            "subcategory":"Auto Repair",
            "type":"Services"
        }
    ],
    "sg:phone":"+1 706 726 1906",
    "sg:postcode":"30909",
    "sg:province":"GA",
    "sg:tags":[
        "repairing",
        "automobile"
    ],
    "wof:name":"Automotive Repair Spec Inc",
    "wof:placetype":"venue"
},
  "geometry": {"coordinates":[-82.04859,33.44822],"type":"Point"}
}