{
  "type": "Feature",
  "properties": {
    "iso:country":"US",
    "sg:address":"144 E Weed St",
    "sg:city":"Brunswick",
    "sg:classifiers":[
        {
            "category":"Building & Trades",
            "subcategory":"Construction",
            "type":"Services"
        }
    ],
    "sg:phone":"+1 912 264 6234",
    "sg:postcode":"31558",
    "sg:province":"GA",
    "sg:tags":[
        "house",
        "speculative",
        "builder",
        "family"
    ],
    "wof:name":"Hardway Construction",
    "wof:placetype":"venue"
},
  "geometry": {"coordinates":[-81.547302,30.723036],"type":"Point"}
}