{
  "type": "Feature",
  "properties": {
    "iso:country":"US",
    "sg:address":"6300 John West Rd",
    "sg:city":"Douglasville",
    "sg:classifiers":[
        {
            "category":"Education",
            "subcategory":"School",
            "type":"Public Place"
        }
    ],
    "sg:phone":"+1 770 920 4120",
    "sg:postcode":"30134",
    "sg:province":"GA",
    "wof:name":"Bright Star Elementary School",
    "wof:placetype":"venue"
},
  "geometry": {"coordinates":[-84.78145000000001,33.725553],"type":"Point"}
}