{
  "type": "Feature",
  "properties": {
    "addr:full":"37 Saint Francis Pl Cartersville GA 30120",
    "addr:housenumber":"37",
    "addr:postcode":"30120",
    "addr:street":"Saint Francis Pl",
    "iso:country":"US",
    "sg:address":"37 Saint Francis Pl",
    "sg:city":"Cartersville",
    "sg:classifiers":[
        {
            "category":"Building & Trades",
            "subcategory":"Construction",
            "type":"Services"
        }
    ],
    "sg:phone":"+1 678 986 0455",
    "sg:postcode":"30120",
    "sg:province":"GA",
    "sg:tags":[
        "house"
    ],
    "wof:name":"Healthy Homes",
    "wof:placetype":"venue"
},
  "geometry": {"coordinates":[-84.805415,34.169955],"type":"Point"}
}