{
  "type": "Feature",
  "properties": {
    "iso:country":"US",
    "sg:address":"2470 Highway 81 Ste Ste A",
    "sg:city":"Atlanta",
    "sg:classifiers":[
        {
            "category":"Shopping",
            "subcategory":"Mobile Phones",
            "type":"Retail Goods"
        }
    ],
    "sg:phone":"+1 678 615 7252",
    "sg:postcode":"30303",
    "sg:province":"GA",
    "wof:name":"Verizon Wireless",
    "wof:placetype":"venue"
},
  "geometry": {"coordinates":[-84.068021,33.428939],"type":"Point"}
}