{
  "type": "Feature",
  "properties": {
    "iso:country":"US",
    "sg:address":"1295 Hembree Rd Ste B202",
    "sg:city":"Roswell",
    "sg:classifiers":[
        {
            "category":"Health Services",
            "subcategory":"Dentist",
            "type":"Services"
        }
    ],
    "sg:phone":"+1 770 475 6767",
    "sg:postcode":"30076",
    "sg:province":"GA",
    "wof:name":"Morris Mitzi D DMD PC",
    "wof:placetype":"venue"
},
  "geometry": {"coordinates":[-84.323132,34.060787],"type":"Point"}
}