{
  "type": "Feature",
  "properties": {
    "addr:full":"100 Bacon St Irwinton GA 31042",
    "addr:housenumber":"100",
    "addr:postcode":"31042",
    "addr:street":"Bacon St",
    "iso:country":"US",
    "sg:address":"100 Bacon St",
    "sg:city":"Irwinton",
    "sg:classifiers":[
        {
            "category":"Government",
            "subcategory":"Office",
            "type":"Public Place"
        }
    ],
    "sg:phone":"+1 478 946 2232",
    "sg:postcode":"31042",
    "sg:province":"GA",
    "sg:tags":[
        "county",
        "taxation"
    ],
    "wof:name":"Tax Commisioner's Office",
    "wof:placetype":"venue"
},
  "geometry": {"coordinates":[-83.17373000000001,32.811105],"type":"Point"}
}