{
  "type": "Feature",
  "properties": {
    "addr:full":"910 N Jefferson St Sted Albany GA 31701",
    "addr:housenumber":"910",
    "addr:postcode":"31701",
    "addr:street":"N Jefferson St",
    "iso:country":"US",
    "sg:address":"910 N Jefferson St Sted",
    "sg:city":"Albany",
    "sg:classifiers":[
        {
            "category":"Health Services",
            "subcategory":"Hospital",
            "type":"Services"
        }
    ],
    "sg:phone":"+1 229 889 7000",
    "sg:postcode":"31701",
    "sg:province":"GA",
    "sg:website":"http://www.phoebeputney.com",
    "wof:name":"Recovery Centers The",
    "wof:placetype":"venue"
},
  "geometry": {"coordinates":[-84.156053,31.588956],"type":"Point"}
}