{
  "type": "Feature",
  "properties": {
    "iso:country":"US",
    "sg:address":"153 Brigham Landing Rd",
    "sg:city":"Girard",
    "sg:classifiers":[
        {
            "category":"Social Services",
            "type":"Services"
        }
    ],
    "sg:phone":"+1 478 569 4661",
    "sg:postcode":"30426",
    "sg:province":"GA",
    "sg:tags":[
        "organization",
        "welfare"
    ],
    "wof:name":"Girard Nutrition",
    "wof:placetype":"venue"
},
  "geometry": {"coordinates":[-81.705375,33.052697],"type":"Point"}
}