{
  "type": "Feature",
  "properties": {
    "iso:country":"US",
    "sg:address":"1561 Virginia Ave",
    "sg:city":"Atlanta",
    "sg:classifiers":[
        {
            "category":"Autos & Motor Vehicles",
            "subcategory":"Auto Supplies",
            "type":"Retail Goods"
        }
    ],
    "sg:phone":"+1 404 766 9907",
    "sg:postcode":"30337",
    "sg:province":"GA",
    "sg:tags":[
        "wheel",
        "cover"
    ],
    "wof:name":"Hot Wheels AMG",
    "wof:placetype":"venue"
},
  "geometry": {"coordinates":[-84.439886,33.659349],"type":"Point"}
}