{
  "type": "Feature",
  "properties": {
    "iso:country":"US",
    "sg:address":"146 Allison Rd",
    "sg:city":"Cordele",
    "sg:classifiers":[
        {
            "category":"Retail",
            "subcategory":"Auto Repair",
            "type":"Services"
        }
    ],
    "sg:phone":"+1 229 271 9129",
    "sg:postcode":"31015",
    "sg:province":"GA",
    "sg:tags":[
        "automotive"
    ],
    "wof:name":"Tisons Radiator Shop",
    "wof:placetype":"venue"
},
  "geometry": {"coordinates":[-83.768506,31.91335],"type":"Point"}
}