{
  "type": "Feature",
  "properties": {
    "addr:full":"620 Cochran Hwy Eastman GA 31023",
    "addr:housenumber":"620",
    "addr:postcode":"31023",
    "addr:street":"Cochran Hwy",
    "iso:country":"US",
    "sg:address":"620 Cochran Hwy",
    "sg:city":"Eastman",
    "sg:classifiers":[
        {
            "category":"Food & Beverages",
            "subcategory":"Groceries & Convenience Stores",
            "type":"Retail Goods"
        }
    ],
    "sg:phone":"+1 478 374 7404",
    "sg:postcode":"31023",
    "sg:province":"GA",
    "wof:name":"Stop N' Shop",
    "wof:placetype":"venue"
},
  "geometry": {"coordinates":[-83.285529,32.320885],"type":"Point"}
}