{
  "type": "Feature",
  "properties": {
    "addr:full":"1803 Hilltop Dr Albany GA 31707",
    "addr:housenumber":"1803",
    "addr:postcode":"31707",
    "addr:street":"Hilltop Dr",
    "iso:country":"US",
    "sg:address":"1803 Hilltop Dr",
    "sg:city":"Albany",
    "sg:classifiers":[
        {
            "category":"Organizations",
            "subcategory":"Community Association",
            "type":"Services"
        }
    ],
    "sg:phone":"+1 229 435 1293",
    "sg:postcode":"31707",
    "sg:province":"GA",
    "wof:name":"Kiwanis International",
    "wof:placetype":"venue"
},
  "geometry": {"coordinates":[-84.191727,31.601951],"type":"Point"}
}