{
  "type": "Feature",
  "properties": {
    "addr:full":"1813 Candler Rd Decatur GA 30032",
    "addr:housenumber":"1813",
    "addr:postcode":"30032",
    "addr:street":"Candler Rd",
    "iso:country":"US",
    "sg:address":"1813 Candler Rd",
    "sg:city":"Decatur",
    "sg:classifiers":[
        {
            "category":"Health Services",
            "subcategory":"Chiropractor",
            "type":"Services"
        }
    ],
    "sg:phone":"+1 404 288 1887",
    "sg:postcode":"30032",
    "sg:province":"GA",
    "sg:tags":[
        "chiropractic"
    ],
    "wof:name":"Wellhealth Chiropractic Center",
    "wof:placetype":"venue"
},
  "geometry": {"coordinates":[-84.287745,33.737894],"type":"Point"}
}