{
  "type": "Feature",
  "properties": {
    "iso:country":"US",
    "sg:address":"250 N Milledge Ave",
    "sg:city":"Athens",
    "sg:classifiers":[
        {
            "category":"Professional",
            "type":"Services"
        },
        {
            "category":"Professional",
            "subcategory":"Lawyer & Legal Services",
            "type":"Services"
        }
    ],
    "sg:phone":"+1 706 316 1150",
    "sg:postcode":"30601",
    "sg:province":"GA",
    "sg:tags":[
        "attorney"
    ],
    "wof:name":"Begnaud & Marshall LLP",
    "wof:placetype":"venue"
},
  "geometry": {"coordinates":[-83.388846,33.956586],"type":"Point"}
}