{
  "type": "Feature",
  "properties": {
    "iso:country":"US",
    "sg:address":"11050 Crabapple Rd",
    "sg:city":"Roswell",
    "sg:classifiers":[
        {
            "category":"Health Services",
            "subcategory":"Clinic",
            "type":"Services"
        }
    ],
    "sg:phone":"+1 678 352 1060",
    "sg:postcode":"30075",
    "sg:province":"GA",
    "wof:name":"Gottlieb, Harris LMFT",
    "wof:placetype":"venue"
},
  "geometry": {"coordinates":[-84.361126,34.049552],"type":"Point"}
}