{
  "type": "Feature",
  "properties": {
    "addr:full":"124 E Mc Donough St Savannah GA 31401",
    "addr:housenumber":"124",
    "addr:postcode":"31401",
    "addr:street":"E Mc Donough St",
    "iso:country":"US",
    "sg:address":"124 E Mc Donough St",
    "sg:city":"Savannah",
    "sg:classifiers":[
        {
            "category":"Real Estate",
            "subcategory":"Real Estate Agent",
            "type":"Services"
        }
    ],
    "sg:phone":"+1 912 233 9387",
    "sg:postcode":"31401",
    "sg:province":"GA",
    "wof:name":"Malleable Reality Corporation",
    "wof:placetype":"venue"
},
  "geometry": {"coordinates":[-81.090898,32.075267],"type":"Point"}
}