{
  "type": "Feature",
  "properties": {
    "addr:full":"2943 Tall Pines Way NE Atlanta GA 30345",
    "addr:housenumber":"2943",
    "addr:postcode":"30345",
    "addr:street":"Tall Pines Way Ne",
    "iso:country":"US",
    "sg:address":"2943 Tall Pines Way NE",
    "sg:city":"Atlanta",
    "sg:classifiers":[
        {
            "category":"Wholesale",
            "subcategory":"Machinery & Supplies",
            "type":"Manufacturing & Wholesale Goods"
        }
    ],
    "sg:phone":"+1 770 938 6058",
    "sg:postcode":"30345",
    "sg:province":"GA",
    "sg:tags":[
        "equipment",
        "industrial"
    ],
    "sg:website":"http://www.panamericanresourcegroup.com",
    "wof:name":"Pan American Resource Group Ltd",
    "wof:placetype":"venue"
},
  "geometry": {"coordinates":[-84.268224,33.860811],"type":"Point"}
}