{
  "type": "Feature",
  "properties": {
    "addr:full":"450 Fosters Mill Ln NW Suwanee GA 30024",
    "addr:housenumber":"450",
    "addr:postcode":"30024",
    "addr:street":"Fosters Mill Ln Nw",
    "iso:country":"US",
    "sg:address":"450 Fosters Mill Ln NW",
    "sg:city":"Suwanee",
    "sg:classifiers":[
        {
            "category":"Arts & Performance",
            "subcategory":"Theater",
            "type":"Entertainment"
        }
    ],
    "sg:phone":"+1 678 376 2276",
    "sg:postcode":"30024",
    "sg:province":"GA",
    "sg:tags":[
        "group"
    ],
    "wof:name":"Georgia North Symphony Inc",
    "wof:placetype":"venue"
},
  "geometry": {"coordinates":[-84.044684,34.012491],"type":"Point"}
}