{
  "type": "Feature",
  "properties": {
    "iso:country":"US",
    "sg:address":"17 SW Broad St",
    "sg:city":"Fairburn",
    "sg:classifiers":[
        {
            "category":"Professional",
            "type":"Services"
        },
        {
            "category":"Restaurant",
            "type":"Food & Drink"
        }
    ],
    "sg:phone":"+1 770 964 0099",
    "sg:postcode":"30213",
    "sg:province":"GA",
    "sg:tags":[
        "caterer",
        "asian",
        "chinese",
        "pan"
    ],
    "wof:name":"China House",
    "wof:placetype":"venue"
},
  "geometry": {"coordinates":[-84.581718,33.566663],"type":"Point"}
}