{
  "type": "Feature",
  "properties": {
    "addr:full":"4030 Pleasantdale Rd Atlanta GA 30340",
    "addr:housenumber":"4030",
    "addr:postcode":"30340",
    "addr:street":"Pleasantdale Rd",
    "iso:country":"US",
    "sg:address":"4030 Pleasantdale Rd",
    "sg:city":"Atlanta",
    "sg:classifiers":[
        {
            "category":"Shopping",
            "subcategory":"Crafts & Fabrics",
            "type":"Retail Goods"
        }
    ],
    "sg:phone":"+1 770 409 8789",
    "sg:postcode":"30340",
    "sg:province":"GA",
    "sg:tags":[
        "adhesive",
        "glue"
    ],
    "wof:name":"Innochem",
    "wof:placetype":"venue"
},
  "geometry": {"coordinates":[-84.243531,33.899513],"type":"Point"}
}