{
  "type": "Feature",
  "properties": {
    "iso:country":"US",
    "sg:address":"2105 Norcross Pkwy",
    "sg:city":"Norcross",
    "sg:classifiers":[
        {
            "category":"Professional",
            "subcategory":"Business Services",
            "type":"Services"
        }
    ],
    "sg:phone":"+1 770 729 8544",
    "sg:postcode":"30071",
    "sg:province":"GA",
    "sg:tags":[
        "delivery",
        "courier"
    ],
    "wof:name":"Greyhound Bus Lines",
    "wof:placetype":"venue"
},
  "geometry": {"coordinates":[-84.185318,33.936057],"type":"Point"}
}