{
  "type": "Feature",
  "properties": {
    "iso:country":"US",
    "sg:address":"1004 Newnan Rd",
    "sg:city":"Carrollton",
    "sg:classifiers":[
        {
            "category":"Government",
            "subcategory":"Office",
            "type":"Public Place"
        }
    ],
    "sg:phone":"+1 770 836 6667",
    "sg:postcode":"30116",
    "sg:province":"GA",
    "sg:tags":[
        "county",
        "program",
        "health"
    ],
    "wof:name":"Carroll County Health Dept",
    "wof:placetype":"venue"
},
  "geometry": {"coordinates":[-85.046735,33.567339],"type":"Point"}
}