{
  "type": "Feature",
  "properties": {
    "addr:full":"7037 Gables Ln Atlanta GA 30350",
    "addr:housenumber":"7037",
    "addr:postcode":"30350",
    "addr:street":"Gables Ln",
    "iso:country":"US",
    "sg:address":"7037 Gables Ln",
    "sg:city":"Atlanta",
    "sg:classifiers":[
        {
            "category":"Professional",
            "subcategory":"Management & Consulting",
            "type":"Services"
        }
    ],
    "sg:phone":"+1 770 668 9116",
    "sg:postcode":"30350",
    "sg:province":"GA",
    "sg:tags":[
        "business"
    ],
    "wof:name":"Gladney Kenyon",
    "wof:placetype":"venue"
},
  "geometry": {"coordinates":[-84.353599,33.958112],"type":"Point"}
}