{
  "type": "Feature",
  "properties": {
    "iso:country":"US",
    "sg:address":"11685 Alpharetta Hwy Ste 310",
    "sg:city":"Roswell",
    "sg:classifiers":[
        {
            "category":"Health Services",
            "subcategory":"Dentist",
            "type":"Services"
        }
    ],
    "sg:phone":"+1 770 360 8008",
    "sg:postcode":"30076",
    "sg:province":"GA",
    "wof:name":"All Kid's Dentistry",
    "wof:placetype":"venue"
},
  "geometry": {"coordinates":[-84.32162099999999,34.064145],"type":"Point"}
}