{
  "type": "Feature",
  "properties": {
    "addr:full":"1407 Welcome Rd Newnan GA 30263",
    "addr:housenumber":"1407",
    "addr:postcode":"30263",
    "addr:street":"Welcome Rd",
    "iso:country":"US",
    "sg:address":"1407 Welcome Rd",
    "sg:city":"Newnan",
    "sg:classifiers":[
        {
            "category":"Professional",
            "type":"Services"
        }
    ],
    "sg:phone":"+1 770 502 8344",
    "sg:postcode":"30263",
    "sg:province":"GA",
    "wof:name":"Gillian/Lawrence",
    "wof:placetype":"venue"
},
  "geometry": {"coordinates":[-84.87694,33.396875],"type":"Point"}
}