{
  "type": "Feature",
  "properties": {
    "iso:country":"US",
    "sg:address":"5608 Riverdale Rd",
    "sg:city":"Atlanta",
    "sg:classifiers":[
        {
            "category":"Restaurant",
            "type":"Food & Drink"
        }
    ],
    "sg:phone":"+1 770 909 0870",
    "sg:postcode":"30349",
    "sg:province":"GA",
    "wof:name":"Smokey Joe's Famous Rib Shack",
    "wof:placetype":"venue"
},
  "geometry": {"coordinates":[-84.42993800000001,33.601849],"type":"Point"}
}