{
  "type": "Feature",
  "properties": {
    "iso:country":"US",
    "sg:address":"59 Lemmon Ln",
    "sg:city":"Ellijay",
    "sg:classifiers":[
        {
            "category":"Building & Trades",
            "subcategory":"Landscaping Services",
            "type":"Services"
        }
    ],
    "sg:phone":"+1 706 635 1244",
    "sg:postcode":"30540",
    "sg:province":"GA",
    "wof:name":"Keys Lawn Service",
    "wof:placetype":"venue"
},
  "geometry": {"coordinates":[-84.568122,34.651134],"type":"Point"}
}