{
  "type": "Feature",
  "properties": {
    "iso:country":"US",
    "sg:address":"6145 Barfield Rd NE",
    "sg:city":"Atlanta",
    "sg:classifiers":[
        {
            "category":"Food & Beverages",
            "subcategory":"Meat & Fish",
            "type":"Retail Goods"
        }
    ],
    "sg:phone":"+1 404 252 1896",
    "sg:postcode":"30328",
    "sg:province":"GA",
    "sg:tags":[
        "seafood",
        "seafood-wholesale",
        "market"
    ],
    "wof:name":"Processors Co-Op",
    "wof:placetype":"venue"
},
  "geometry": {"coordinates":[-84.35990099999999,33.922029],"type":"Point"}
}