{
  "type": "Feature",
  "properties": {
    "iso:country":"US",
    "sg:address":"1025 E Talley Ave",
    "sg:city":"Lakeland",
    "sg:classifiers":[
        {
            "category":"Place Of Worship",
            "type":"Public Place"
        }
    ],
    "sg:phone":"+1 229 452 0446",
    "sg:postcode":"31635",
    "sg:province":"GA",
    "sg:tags":[
        "church"
    ],
    "wof:name":"Power Of Love First Born Church",
    "wof:placetype":"venue"
},
  "geometry": {"coordinates":[-83.061761,31.037889],"type":"Point"}
}