{
  "type": "Feature",
  "properties": {
    "addr:full":"1606 Watson Blvd Warner Robins GA 31093",
    "addr:housenumber":"1606",
    "addr:postcode":"31093",
    "addr:street":"Watson Blvd",
    "iso:country":"US",
    "sg:address":"1606 Watson Blvd",
    "sg:city":"Warner Robins",
    "sg:classifiers":[
        {
            "category":"Health Services",
            "subcategory":"Doctor",
            "type":"Services"
        }
    ],
    "sg:phone":"+1 478 929 2001",
    "sg:postcode":"31093",
    "sg:province":"GA",
    "sg:tags":[
        "physician",
        "surgeon"
    ],
    "wof:name":"Pathology Institute-Ga",
    "wof:placetype":"venue"
},
  "geometry": {"coordinates":[-83.63166699999999,32.618207],"type":"Point"}
}