{
  "type": "Feature",
  "properties": {
    "iso:country":"US",
    "sg:address":"4361 Jonesboro Rd",
    "sg:city":"Hampton",
    "sg:classifiers":[
        {
            "category":"Farming",
            "subcategory":"Livestock Farm",
            "type":"Manufacturing & Wholesale Goods"
        }
    ],
    "sg:phone":"+1 770 471 9345",
    "sg:postcode":"30228",
    "sg:province":"GA",
    "sg:tags":[
        "beef",
        "feedlot",
        "cattle"
    ],
    "wof:name":"Circle G Ranches",
    "wof:placetype":"venue"
},
  "geometry": {"coordinates":[-84.282831,33.468612],"type":"Point"}
}