{
  "type": "Feature",
  "properties": {
    "addr:full":"938 Hall St SW Atlanta GA 30310",
    "addr:housenumber":"938",
    "addr:postcode":"30310",
    "addr:street":"Hall St Sw",
    "iso:country":"US",
    "sg:address":"938 Hall St SW",
    "sg:city":"Atlanta",
    "sg:classifiers":[
        {
            "category":"Manufacturing",
            "subcategory":"Building Materials",
            "type":"Manufacturing & Wholesale Goods"
        }
    ],
    "sg:phone":"+1 404 375 2391",
    "sg:postcode":"30310",
    "sg:province":"GA",
    "sg:tags":[
        "mfg"
    ],
    "wof:name":"Kw Woodworks LLC",
    "wof:placetype":"venue"
},
  "geometry": {"coordinates":[-84.425619,33.728875],"type":"Point"}
}