{
  "type": "Feature",
  "properties": {
    "addr:full":"1 Cone St NW Atlanta GA 30303",
    "addr:housenumber":"1",
    "addr:postcode":"30303",
    "addr:street":"Cone St Nw",
    "iso:country":"US",
    "sg:address":"1 Cone St NW",
    "sg:city":"Atlanta",
    "sg:classifiers":[
        {
            "category":"Food & Beverages",
            "subcategory":"Bakery",
            "type":"Retail Goods"
        }
    ],
    "sg:phone":"+1 404 681 2349",
    "sg:postcode":"30303",
    "sg:province":"GA",
    "wof:name":"Dunkin Donuts",
    "wof:placetype":"venue"
},
  "geometry": {"coordinates":[-84.391356,33.756982],"type":"Point"}
}