{
  "type": "Feature",
  "properties": {
    "iso:country":"US",
    "sg:address":"517 Old Mission Rd",
    "sg:city":"Brunswick",
    "sg:classifiers":[
        {
            "category":"Travel",
            "subcategory":"Travel Agent",
            "type":"Entertainment"
        }
    ],
    "sg:phone":"+1 912 264 1635",
    "sg:postcode":"31525",
    "sg:province":"GA",
    "sg:tags":[
        "operator",
        "tour"
    ],
    "wof:name":"Travelog Tours Inc",
    "wof:placetype":"venue"
},
  "geometry": {"coordinates":[-81.460002,31.212624],"type":"Point"}
}