{
  "type": "Feature",
  "properties": {
    "iso:country":"US",
    "sg:address":"511 John Street NW",
    "sg:city":"Atlanta",
    "sg:classifiers":[
        {
            "category":"Real Estate",
            "subcategory":"Real Estate Operator",
            "type":"Services"
        }
    ],
    "sg:phone":"+1 404 332 1506",
    "sg:postcode":"30318",
    "sg:province":"GA",
    "sg:tags":[
        "apartment"
    ],
    "wof:name":"Atlanta Housing Authority",
    "wof:placetype":"venue"
},
  "geometry": {"coordinates":[-84.40782799999999,33.766049],"type":"Point"}
}