{
  "type": "Feature",
  "properties": {
    "addr:full":"307 Main St S Adairsville GA 30103",
    "addr:housenumber":"307",
    "addr:postcode":"30103",
    "addr:street":"Main St S Adairsville",
    "iso:country":"US",
    "sg:address":"307 Main St S",
    "sg:city":"Adairsville",
    "sg:classifiers":[
        {
            "category":"Wholesale",
            "subcategory":"Plants",
            "type":"Manufacturing & Wholesale Goods"
        }
    ],
    "sg:phone":"+1 770 773 3365",
    "sg:postcode":"30103",
    "sg:province":"GA",
    "sg:tags":[
        "supply"
    ],
    "wof:name":"Don Austin Wholesale Pottery",
    "wof:placetype":"venue"
},
  "geometry": {"coordinates":[-84.934049,34.36352],"type":"Point"}
}