{
  "type": "Feature",
  "properties": {
    "addr:full":"3190 N Henry Blvd Stockbridge GA 30281",
    "addr:housenumber":"3190",
    "addr:postcode":"30281",
    "addr:street":"N Henry Blvd",
    "iso:country":"US",
    "sg:address":"3190 N Henry Blvd",
    "sg:city":"Stockbridge",
    "sg:classifiers":[
        {
            "category":"Insurance",
            "subcategory":"Insurance Agent",
            "type":"Services"
        }
    ],
    "sg:phone":"+1 770 506 1129",
    "sg:postcode":"30281",
    "sg:province":"GA",
    "wof:name":"Primerica Financial Svc",
    "wof:placetype":"venue"
},
  "geometry": {"coordinates":[-84.19614199999999,33.525727],"type":"Point"}
}