{
  "type": "Feature",
  "properties": {
    "addr:full":"480 E Paces Ferry Road NE Atlanta GA 30305",
    "addr:housenumber":"480",
    "addr:postcode":"30305",
    "addr:street":"E Paces Ferry Road Ne",
    "iso:country":"US",
    "sg:address":"480 E Paces Ferry Road NE",
    "sg:city":"Atlanta",
    "sg:classifiers":[
        {
            "category":"Shopping",
            "subcategory":"Jewelry",
            "type":"Retail Goods"
        }
    ],
    "sg:phone":"+1 404 237 7885",
    "sg:postcode":"30305",
    "sg:province":"GA",
    "wof:name":"Pickens",
    "wof:placetype":"venue"
},
  "geometry": {"coordinates":[-84.371951,33.838387],"type":"Point"}
}