{
  "type": "Feature",
  "properties": {
    "addr:full":"4387 Ridge Trl Martinez GA 30907",
    "addr:housenumber":"4387",
    "addr:postcode":"30907",
    "addr:street":"Ridge Trl Martinez",
    "iso:country":"US",
    "sg:address":"4387 Ridge Trl",
    "sg:city":"Martinez",
    "sg:classifiers":[
        {
            "category":"Wholesale",
            "subcategory":"Machinery & Supplies",
            "type":"Manufacturing & Wholesale Goods"
        }
    ],
    "sg:phone":"+1 706 860 7800",
    "sg:postcode":"30907",
    "sg:province":"GA",
    "sg:tags":[
        "janitor"
    ],
    "wof:name":"Professional Supply Co",
    "wof:placetype":"venue"
},
  "geometry": {"coordinates":[-82.132304,33.484902],"type":"Point"}
}