{
  "type": "Feature",
  "properties": {
    "addr:full":"2442 Marietta Hwy Canton GA 30114",
    "addr:housenumber":"2442",
    "addr:postcode":"30114",
    "addr:street":"Marietta Hwy",
    "iso:country":"US",
    "sg:address":"2442 Marietta Hwy",
    "sg:city":"Canton",
    "sg:classifiers":[
        {
            "category":"Wholesale",
            "subcategory":"Jewelry",
            "type":"Manufacturing & Wholesale Goods"
        }
    ],
    "sg:phone":"+1 678 880 0568",
    "sg:postcode":"30114",
    "sg:province":"GA",
    "sg:tags":[
        "beads"
    ],
    "wof:name":"Studio Beads & Supply",
    "wof:placetype":"venue"
},
  "geometry": {"coordinates":[-84.504413,34.21291],"type":"Point"}
}