{
  "type": "Feature",
  "properties": {
    "iso:country":"US",
    "sg:address":"2251 Sylvan Rd",
    "sg:city":"Atlanta",
    "sg:classifiers":[
        {
            "category":"Education",
            "subcategory":"Special Training",
            "type":"Public Place"
        }
    ],
    "sg:phone":"+1 404 768 6565",
    "sg:postcode":"30344",
    "sg:province":"GA",
    "wof:name":"Mexico Truck Driving School",
    "wof:placetype":"venue"
},
  "geometry": {"coordinates":[-84.418508,33.693174],"type":"Point"}
}