{
  "type": "Feature",
  "properties": {
    "addr:full":"1000 Blairs Bridge Rd Lithia Springs GA 30122",
    "addr:housenumber":"1000",
    "addr:postcode":"30122",
    "addr:street":"Blairs Bridge Rd",
    "iso:country":"US",
    "sg:address":"1000 Blairs Bridge Rd",
    "sg:city":"Lithia Springs",
    "sg:classifiers":[
        {
            "category":"Autos & Motor Vehicles",
            "subcategory":"Automobile Sales",
            "type":"Retail Goods"
        }
    ],
    "sg:phone":"+1 770 941 1200",
    "sg:postcode":"30122",
    "sg:province":"GA",
    "sg:tags":[
        "car"
    ],
    "wof:name":"Team Toyota Scion",
    "wof:placetype":"venue"
},
  "geometry": {"coordinates":[-84.605729,33.773105],"type":"Point"}
}