{
  "type": "Feature",
  "properties": {
    "addr:full":"2 Concourse Pkwy NE Atlanta GA 30328",
    "addr:housenumber":"2",
    "addr:postcode":"30328",
    "addr:street":"Concourse Pkwy Ne",
    "iso:country":"US",
    "sg:address":"2 Concourse Pkwy NE",
    "sg:city":"Atlanta",
    "sg:classifiers":[
        {
            "category":"Utilities",
            "subcategory":"Telephone",
            "type":"Services"
        }
    ],
    "sg:phone":"+1 770 350 9448",
    "sg:postcode":"30328",
    "sg:province":"GA",
    "sg:tags":[
        "company"
    ],
    "wof:name":"Us Lec",
    "wof:placetype":"venue"
},
  "geometry": {"coordinates":[-84.35118199999999,33.916461],"type":"Point"}
}