{
  "type": "Feature",
  "properties": {
    "iso:country":"US",
    "sg:address":"621 Virginia Ave N",
    "sg:city":"Tifton",
    "sg:classifiers":[
        {
            "category":"Organizations",
            "subcategory":"Non-profit Organization",
            "type":"Services"
        }
    ],
    "sg:phone":"+1 229 382 4491",
    "sg:postcode":"31794",
    "sg:province":"GA",
    "sg:tags":[
        "alternative",
        "abortion"
    ],
    "wof:name":"Pregnancy Care Ctr Of Tifton",
    "wof:placetype":"venue"
},
  "geometry": {"coordinates":[-83.526893,31.458526],"type":"Point"}
}