{
  "type": "Feature",
  "properties": {
    "addr:full":"107 Montrose Ln Centerville GA 31028",
    "addr:housenumber":"107",
    "addr:postcode":"31028",
    "addr:street":"Montrose Ln",
    "iso:country":"US",
    "sg:address":"107 Montrose Ln",
    "sg:city":"Centerville",
    "sg:classifiers":[
        {
            "category":"Health Services",
            "subcategory":"Health Practitioner",
            "type":"Services"
        }
    ],
    "sg:phone":"+1 478 953 7371",
    "sg:postcode":"31028",
    "sg:province":"GA",
    "sg:tags":[
        "pathologist",
        "speech"
    ],
    "wof:name":"Speech Beginnings Inc",
    "wof:placetype":"venue"
},
  "geometry": {"coordinates":[-83.691202,32.627377],"type":"Point"}
}