{
  "type": "Feature",
  "properties": {
    "iso:country":"US",
    "sg:address":"529 Sand Hill Shady Grove Rd",
    "sg:city":"Carrollton",
    "sg:classifiers":[
        {
            "category":"Professional",
            "subcategory":"Management & Consulting",
            "type":"Services"
        }
    ],
    "sg:phone":"+1 770 836 0194",
    "sg:postcode":"30116",
    "sg:province":"GA",
    "sg:tags":[
        "business"
    ],
    "wof:name":"Rearden & Assoc",
    "wof:placetype":"venue"
},
  "geometry": {"coordinates":[-84.99333,33.638895],"type":"Point"}
}