{
  "type": "Feature",
  "properties": {
    "addr:full":"208 Barfield Dr Dublin GA 31021",
    "addr:housenumber":"208",
    "addr:postcode":"31021",
    "addr:street":"Barfield Dr",
    "iso:country":"US",
    "sg:address":"208 Barfield Dr",
    "sg:city":"Dublin",
    "sg:classifiers":[
        {
            "category":"Manufacturing",
            "subcategory":"Lumber",
            "type":"Manufacturing & Wholesale Goods"
        }
    ],
    "sg:phone":"+1 478 274 1061",
    "sg:postcode":"31021",
    "sg:province":"GA",
    "sg:tags":[
        "operation",
        "timber",
        "tract"
    ],
    "wof:name":"R M Polk Natural Resources",
    "wof:placetype":"venue"
},
  "geometry": {"coordinates":[-82.94256799999999,32.578465],"type":"Point"}
}