{
  "type": "Feature",
  "properties": {
    "iso:country":"US",
    "sg:address":"100 Bradford Sq",
    "sg:city":"Fayetteville",
    "sg:classifiers":[
        {
            "category":"Education",
            "subcategory":"School",
            "type":"Public Place"
        }
    ],
    "sg:phone":"+1 770 460 3432",
    "sg:postcode":"30215",
    "sg:province":"GA",
    "sg:website":"www.fcboe.org",
    "wof:name":"Spring Hill Elementary School",
    "wof:placetype":"venue"
},
  "geometry": {"coordinates":[-84.46957,33.443301],"type":"Point"}
}