{
  "type": "Feature",
  "properties": {
    "iso:country":"US",
    "sg:address":"4 Indian Cove Rd",
    "sg:city":"Augusta",
    "sg:classifiers":[
        {
            "category":"Professional",
            "subcategory":"Advertising",
            "type":"Services"
        }
    ],
    "sg:phone":"+1 706 651 0004",
    "sg:postcode":"30909",
    "sg:province":"GA",
    "wof:name":"Outdoor Advertising",
    "wof:placetype":"venue"
},
  "geometry": {"coordinates":[-82.036185,33.488457],"type":"Point"}
}