{
  "type": "Feature",
  "properties": {
    "iso:country":"US",
    "sg:address":"138 Honey Creek Rd",
    "sg:city":"Mc Donough",
    "sg:classifiers":[
        {
            "category":"Building & Trades",
            "subcategory":"Electrical",
            "type":"Services"
        }
    ],
    "sg:phone":"+1 770 957 1883",
    "sg:postcode":"30252",
    "sg:province":"GA",
    "sg:tags":[
        "electrical",
        "contractor"
    ],
    "wof:name":"Stb Electric Inc",
    "wof:placetype":"venue"
},
  "geometry": {"coordinates":[-84.02825199999999,33.475272],"type":"Point"}
}