{
  "type": "Feature",
  "properties": {
    "iso:country":"US",
    "sg:address":"125 Cedar Ln",
    "sg:city":"Martinez",
    "sg:classifiers":[
        {
            "category":"Wholesale",
            "subcategory":"Non-durable Goods",
            "type":"Manufacturing & Wholesale Goods"
        }
    ],
    "sg:phone":"+1 706 863 8758",
    "sg:postcode":"30907",
    "sg:province":"GA",
    "sg:tags":[
        "bait",
        "fishing"
    ],
    "sg:website":"www.ghann.com",
    "wof:name":"Ghann's Cricket Farm Inc",
    "wof:placetype":"venue"
},
  "geometry": {"coordinates":[-82.071281,33.51942],"type":"Point"}
}