{
  "type": "Feature",
  "properties": {
    "addr:full":"207 E 3rd St Vidalia GA 30474",
    "addr:housenumber":"207",
    "addr:postcode":"30474",
    "addr:street":"E 3Rd St",
    "iso:country":"US",
    "sg:address":"207 E 3rd St",
    "sg:city":"Vidalia",
    "sg:classifiers":[
        {
            "category":"Professional",
            "subcategory":"Lawyer & Legal Services",
            "type":"Services"
        }
    ],
    "sg:phone":"+1 912 537 1448",
    "sg:postcode":"30474",
    "sg:province":"GA",
    "sg:tags":[
        "attorney"
    ],
    "wof:name":"Shook Firm",
    "wof:placetype":"venue"
},
  "geometry": {"coordinates":[-82.41310300000001,32.214495],"type":"Point"}
}