{
  "type": "Feature",
  "properties": {
    "iso:country":"US",
    "sg:address":"267 Peters St SW Unit 104",
    "sg:city":"Atlanta",
    "sg:classifiers":[
        {
            "category":"Professional",
            "subcategory":"Art Services",
            "type":"Services"
        }
    ],
    "sg:phone":"+1 404 577 7877",
    "sg:postcode":"30313",
    "sg:province":"GA",
    "sg:tags":[
        "designer",
        "display",
        "producer"
    ],
    "wof:name":"Soulo Event Designs",
    "wof:placetype":"venue"
},
  "geometry": {"coordinates":[-84.40275,33.746467],"type":"Point"}
}