{
  "type": "Feature",
  "properties": {
    "iso:country":"US",
    "sg:address":"27 Jones Rd",
    "sg:city":"La Fayette",
    "sg:classifiers":[
        {
            "category":"Organizations",
            "subcategory":"Religious Organization",
            "type":"Services"
        }
    ],
    "sg:phone":"+1 706 764 2003",
    "sg:postcode":"30728",
    "sg:province":"GA",
    "sg:tags":[
        "church"
    ],
    "wof:name":"Grace Baptist Tabernacle",
    "wof:placetype":"venue"
},
  "geometry": {"coordinates":[-85.243377,34.802644],"type":"Point"}
}