{
  "type": "Feature",
  "properties": {
    "iso:country":"US",
    "sg:address":"1425 Prince Ave",
    "sg:city":"Athens",
    "sg:classifiers":[
        {
            "category":"Military Area",
            "type":"Public Place"
        },
        {
            "category":"Government",
            "subcategory":"Office",
            "type":"Public Place"
        }
    ],
    "sg:phone":"+1 706 354 1500",
    "sg:postcode":"30606",
    "sg:province":"GA",
    "sg:tags":[
        "recruiting",
        "government-united",
        "force",
        "state",
        "armed"
    ],
    "sg:website":"http://www.navy.com",
    "wof:name":"Us Govt Navy - Navy Supply Corp School",
    "wof:placetype":"venue"
},
  "geometry": {"coordinates":[-83.401791,33.963863],"type":"Point"}
}