{
  "type": "Feature",
  "properties": {
    "iso:country":"US",
    "sg:address":"225 Sycamore St",
    "sg:city":"Greensboro",
    "sg:classifiers":[
        {
            "category":"Social Services",
            "type":"Services"
        }
    ],
    "sg:phone":"+1 706 453 4082",
    "sg:postcode":"30642",
    "sg:province":"GA",
    "sg:tags":[
        "organization",
        "welfare"
    ],
    "wof:name":"Family Connection",
    "wof:placetype":"venue"
},
  "geometry": {"coordinates":[-83.19054300000001,33.581719],"type":"Point"}
}