{
  "type": "Feature",
  "properties": {
    "addr:full":"1950 Old Ocilla Rd Tifton GA 31794",
    "addr:housenumber":"1950",
    "addr:postcode":"31794",
    "addr:street":"Old Ocilla Rd",
    "iso:country":"US",
    "sg:address":"1950 Old Ocilla Rd",
    "sg:city":"Tifton",
    "sg:classifiers":[
        {
            "category":"Health Services",
            "subcategory":"Doctor",
            "type":"Services"
        }
    ],
    "sg:phone":"+1 229 391 3300",
    "sg:postcode":"31794",
    "sg:province":"GA",
    "sg:tags":[
        "physician",
        "medical",
        "surgeon"
    ],
    "wof:name":"Family Practice Associates LLC",
    "wof:placetype":"venue"
},
  "geometry": {"coordinates":[-83.489555,31.47027],"type":"Point"}
}