{
  "type": "Feature",
  "properties": {
    "iso:country":"US",
    "sg:address":"1209 Solomon Temple Rd",
    "sg:city":"Wadley",
    "sg:classifiers":[
        {
            "category":"Retail",
            "subcategory":"Auto Repair",
            "type":"Services"
        }
    ],
    "sg:phone":"+1 478 252 0522",
    "sg:postcode":"30477",
    "sg:province":"GA",
    "sg:tags":[
        "body",
        "automobile",
        "painting"
    ],
    "wof:name":"Donnie's Paint & Body",
    "wof:placetype":"venue"
},
  "geometry": {"coordinates":[-82.39442200000001,32.924853],"type":"Point"}
}