{
  "type": "Feature",
  "properties": {
    "addr:full":"7111 Highway 278 NE Covington GA 30014",
    "addr:housenumber":"7111",
    "addr:postcode":"30014",
    "addr:street":"Highway 278 Ne",
    "iso:country":"US",
    "sg:address":"7111 Highway 278 NE",
    "sg:city":"Covington",
    "sg:classifiers":[
        {
            "category":"Personal",
            "subcategory":"Beauty Salon",
            "type":"Services"
        }
    ],
    "sg:phone":"+1 770 784 7004",
    "sg:postcode":"30014",
    "sg:province":"GA",
    "wof:name":"Salon Complete",
    "wof:placetype":"venue"
},
  "geometry": {"coordinates":[-83.8399,33.601507],"type":"Point"}
}