{
  "type": "Feature",
  "properties": {
    "iso:country":"US",
    "sg:address":"1116 Acker Dr",
    "sg:city":"Albany",
    "sg:classifiers":[
        {
            "category":"Building & Trades",
            "subcategory":"Plumbing",
            "type":"Services"
        }
    ],
    "sg:phone":"+1 229 889 8818",
    "sg:postcode":"31707",
    "sg:province":"GA",
    "sg:tags":[
        "contractor"
    ],
    "wof:name":"Mc Donald Plumbing",
    "wof:placetype":"venue"
},
  "geometry": {"coordinates":[-84.17871599999999,31.607169],"type":"Point"}
}