{
  "type": "Feature",
  "properties": {
    "iso:country":"US",
    "sg:address":"4777 Stone Dr",
    "sg:city":"Tucker",
    "sg:classifiers":[
        {
            "category":"Wholesale",
            "subcategory":"Metals & Minerals",
            "type":"Manufacturing & Wholesale Goods"
        }
    ],
    "sg:phone":"+1 770 934 8450",
    "sg:postcode":"30084",
    "sg:province":"GA",
    "sg:tags":[
        "spouting",
        "rain"
    ],
    "wof:name":"Alumax Home Products",
    "wof:placetype":"venue"
},
  "geometry": {"coordinates":[-84.19529799999999,33.838709],"type":"Point"}
}