{
  "type": "Feature",
  "properties": {
    "addr:full":"1541 Dean Forest Rd Savannah GA 31408",
    "addr:housenumber":"1541",
    "addr:postcode":"31408",
    "addr:street":"Dean Forest Rd",
    "iso:country":"US",
    "sg:address":"1541 Dean Forest Rd",
    "sg:city":"Savannah",
    "sg:classifiers":[
        {
            "category":"Autos & Motor Vehicles",
            "subcategory":"Auto Supplies",
            "type":"Retail Goods"
        },
        {
            "category":"Manufacturing",
            "subcategory":"Petroleum Products",
            "type":"Manufacturing & Wholesale Goods"
        },
        {
            "category":"Utilities",
            "subcategory":"Fuel Oil & Lpg",
            "type":"Services"
        }
    ],
    "sg:phone":"+1 912 964 1846",
    "sg:postcode":"31408",
    "sg:province":"GA",
    "sg:tags":[
        "handling",
        "oils-lubricating-wholesale",
        "oils-fuel-wholesale",
        "equipment",
        "lubricant",
        "oils-fuel",
        "manufacturer"
    ],
    "sg:website":"http://www.emeraldpetroco.com",
    "wof:name":"Emerald Petroleum Co Inc",
    "wof:placetype":"venue"
},
  "geometry": {"coordinates":[-81.195607,32.080487],"type":"Point"}
}