{
  "type": "Feature",
  "properties": {
    "addr:full":"969 Pine St NE Conyers GA 30012",
    "addr:housenumber":"969",
    "addr:postcode":"30012",
    "addr:street":"Pine St Ne",
    "iso:country":"US",
    "sg:address":"969 Pine St NE",
    "sg:city":"Conyers",
    "sg:classifiers":[
        {
            "category":"Government",
            "subcategory":"Office",
            "type":"Public Place"
        }
    ],
    "sg:phone":"+1 770 929 4012",
    "sg:postcode":"30012",
    "sg:province":"GA",
    "sg:tags":[
        "county",
        "taxation"
    ],
    "wof:name":"Rockdale County Tax Cmsnr",
    "wof:placetype":"venue"
},
  "geometry": {"coordinates":[-84.015869,33.668382],"type":"Point"}
}