{
  "type": "Feature",
  "properties": {
    "iso:country":"US",
    "sg:address":"2980 Columbus Rd",
    "sg:city":"Macon",
    "sg:classifiers":[
        {
            "category":"Professional",
            "type":"Services"
        }
    ],
    "sg:phone":"+1 478 745 7195",
    "sg:postcode":"31204",
    "sg:province":"GA",
    "wof:name":"Tabinkies",
    "wof:placetype":"venue"
},
  "geometry": {"coordinates":[-83.67281199999999,32.829178],"type":"Point"}
}