{
  "type": "Feature",
  "properties": {
    "addr:full":"638 E 56th St Savannah GA 31405",
    "addr:housenumber":"638",
    "addr:postcode":"31405",
    "addr:street":"E 56Th St",
    "iso:country":"US",
    "sg:address":"638 E 56th St",
    "sg:city":"Savannah",
    "sg:classifiers":[
        {
            "category":"Autos & Motor Vehicles",
            "subcategory":"Automobile Sales",
            "type":"Retail Goods"
        }
    ],
    "sg:phone":"+1 912 355 5166",
    "sg:postcode":"31405",
    "sg:province":"GA",
    "sg:tags":[
        "used"
    ],
    "wof:name":"Ardsley Assoc Inc",
    "wof:placetype":"venue"
},
  "geometry": {"coordinates":[-81.092162,32.039119],"type":"Point"}
}