{
  "type": "Feature",
  "properties": {
    "iso:country":"US",
    "sg:address":"1020 Cherokee Trl",
    "sg:city":"Woodstock",
    "sg:classifiers":[
        {
            "category":"Professional",
            "subcategory":"Management & Consulting",
            "type":"Services"
        }
    ],
    "sg:phone":"+1 770 928 6253",
    "sg:postcode":"30189",
    "sg:province":"GA",
    "sg:tags":[
        "business"
    ],
    "wof:name":"Dr Deborah A Pogrelis Consulti",
    "wof:placetype":"venue"
},
  "geometry": {"coordinates":[-84.54410799999999,34.088494],"type":"Point"}
}