{
  "type": "Feature",
  "properties": {
    "iso:country":"US",
    "sg:address":"514 Diamond Lure Rd",
    "sg:city":"Ellijay",
    "sg:classifiers":[
        {
            "category":"Utilities",
            "subcategory":"Telephone",
            "type":"Services"
        }
    ],
    "sg:phone":"+1 706 276 7420",
    "sg:postcode":"30536",
    "sg:province":"GA",
    "sg:tags":[
        "telecommunication"
    ],
    "wof:name":"American Tower Corp",
    "wof:placetype":"venue"
},
  "geometry": {"coordinates":[-84.383561,34.615997],"type":"Point"}
}