{
  "type": "Feature",
  "properties": {
    "iso:country":"US",
    "sg:address":"1637 Athens Hwy",
    "sg:city":"Grayson",
    "sg:classifiers":[
        {
            "category":"Real Estate",
            "subcategory":"Real Estate Agent",
            "type":"Services"
        }
    ],
    "sg:phone":"+1 770 979 1700",
    "sg:postcode":"30017",
    "sg:province":"GA",
    "sg:website":"www.remax-greateratlantaga.com",
    "wof:name":"Re/Max Greater Atlanta",
    "wof:placetype":"venue"
},
  "geometry": {"coordinates":[-83.98269999999999,33.858602],"type":"Point"}
}