{
  "type": "Feature",
  "properties": {
    "addr:full":"104 Oak St La Fayette GA 30728",
    "addr:housenumber":"104",
    "addr:postcode":"30728",
    "addr:street":"Oak St;Fayette",
    "iso:country":"US",
    "sg:address":"104 Oak St",
    "sg:city":"La Fayette",
    "sg:classifiers":[
        {
            "category":"Shopping",
            "subcategory":"Used Merchandise",
            "type":"Retail Goods"
        }
    ],
    "sg:phone":"+1 706 638 1034",
    "sg:postcode":"30728",
    "sg:province":"GA",
    "wof:name":"Jazzy Junction",
    "wof:placetype":"venue"
},
  "geometry": {"coordinates":[-85.28439,34.706018],"type":"Point"}
}