{
  "type": "Feature",
  "properties": {
    "addr:full":"2398 Lewis Loop Jesup GA 31545",
    "addr:housenumber":"2398",
    "addr:postcode":"31545",
    "addr:street":"Lewis Loop",
    "iso:country":"US",
    "sg:address":"2398 Lewis Loop",
    "sg:city":"Jesup",
    "sg:classifiers":[
        {
            "category":"Building & Trades",
            "subcategory":"Construction",
            "type":"Services"
        }
    ],
    "sg:phone":"+1 912 427 4369",
    "sg:postcode":"31545",
    "sg:province":"GA",
    "sg:tags":[
        "house"
    ],
    "wof:name":"Larry Landon Construction",
    "wof:placetype":"venue"
},
  "geometry": {"coordinates":[-81.920266,31.720379],"type":"Point"}
}