{
  "type": "Feature",
  "properties": {
    "iso:country":"US",
    "sg:address":"118 Pheasant Ridge",
    "sg:city":"Newnan",
    "sg:classifiers":[
        {
            "category":"Organizations",
            "subcategory":"Religious Organization",
            "type":"Services"
        }
    ],
    "sg:phone":"+1 770 304 3639",
    "sg:postcode":"30265",
    "sg:province":"GA",
    "sg:tags":[
        "church"
    ],
    "wof:name":"New Life Restoration Mnstrs",
    "wof:placetype":"venue"
},
  "geometry": {"coordinates":[-84.709745,33.379492],"type":"Point"}
}