{
  "type": "Feature",
  "properties": {
    "addr:full":"3205 Woodward Crossing Blvd Ste A Buford GA 30519",
    "addr:housenumber":"3205",
    "addr:postcode":"30519",
    "addr:street":"Woodward Crossing Blvd Ste A",
    "iso:country":"US",
    "sg:address":"3205 Woodward Crossing Blvd Ste A",
    "sg:city":"Buford",
    "sg:classifiers":[
        {
            "category":"Wholesale",
            "subcategory":"Computers",
            "type":"Manufacturing & Wholesale Goods"
        },
        {
            "category":"Shopping",
            "subcategory":"Computers & Home Electronics",
            "type":"Retail Goods"
        },
        {
            "category":"Professional",
            "subcategory":"Computer Services",
            "type":"Services"
        }
    ],
    "sg:phone":"+1 770 614 0533",
    "sg:postcode":"30519",
    "sg:province":"GA",
    "sg:tags":[
        "repair",
        "stereo",
        "installation",
        "consumer"
    ],
    "sg:website":"www.bestbuy.com",
    "wof:name":"Best Buy",
    "wof:placetype":"venue"
},
  "geometry": {"coordinates":[-83.98114,34.069232],"type":"Point"}
}