{
  "type": "Feature",
  "properties": {
    "addr:full":"4301 Roscoe Rd Newnan GA 30263",
    "addr:housenumber":"4301",
    "addr:postcode":"30263",
    "addr:street":"Roscoe Rd",
    "iso:country":"US",
    "sg:address":"4301 Roscoe Rd",
    "sg:city":"Newnan",
    "sg:classifiers":[
        {
            "category":"Organizations",
            "subcategory":"Religious Organization",
            "type":"Services"
        }
    ],
    "sg:phone":"+1 770 304 8999",
    "sg:postcode":"30263",
    "sg:province":"GA",
    "sg:tags":[
        "church"
    ],
    "wof:name":"Andrews Chapel United Metho Di",
    "wof:placetype":"venue"
},
  "geometry": {"coordinates":[-84.811939,33.501213],"type":"Point"}
}