{
  "type": "Feature",
  "properties": {
    "addr:full":"8380 Roswell Rd Atlanta GA 30350",
    "addr:housenumber":"8380",
    "addr:postcode":"30350",
    "addr:street":"Roswell Rd",
    "iso:country":"US",
    "sg:address":"8380 Roswell Rd",
    "sg:city":"Atlanta",
    "sg:classifiers":[
        {
            "category":"Professional",
            "subcategory":"Art Services",
            "type":"Services"
        }
    ],
    "sg:phone":"+1 404 513 4787",
    "sg:postcode":"30350",
    "sg:province":"GA",
    "sg:tags":[
        "commercial",
        "design"
    ],
    "wof:name":"Reenieimaging",
    "wof:placetype":"venue"
},
  "geometry": {"coordinates":[-84.35048999999999,33.980092],"type":"Point"}
}