{
  "type": "Feature",
  "properties": {
    "iso:country":"US",
    "sg:address":"132 Martin St",
    "sg:city":"Lincolnton",
    "sg:classifiers":[
        {
            "category":"Cinema",
            "subcategory":"Movie Rental",
            "type":"Entertainment"
        }
    ],
    "sg:phone":"+1 706 359 7469",
    "sg:postcode":"30817",
    "sg:province":"GA",
    "sg:tags":[
        "leasing",
        "video",
        "disc",
        "tape"
    ],
    "wof:name":"Showtime",
    "wof:placetype":"venue"
},
  "geometry": {"coordinates":[-82.48232899999999,33.788084],"type":"Point"}
}