{
  "type": "Feature",
  "properties": {
    "addr:full":"22 Hinson St Hazlehurst GA 31539",
    "addr:housenumber":"22",
    "addr:postcode":"31539",
    "addr:street":"Hinson St",
    "iso:country":"US",
    "sg:address":"22 Hinson St",
    "sg:city":"Hazlehurst",
    "sg:classifiers":[
        {
            "category":"Professional",
            "subcategory":"Lawyer & Legal Services",
            "type":"Services"
        }
    ],
    "sg:phone":"+1 912 375 4266",
    "sg:postcode":"31539",
    "sg:province":"GA",
    "sg:tags":[
        "attorney",
        "law",
        "bankruptcy"
    ],
    "sg:website":"http://www.thebankruptcygroup.net",
    "wof:name":"Bankruptcy Group The",
    "wof:placetype":"venue"
},
  "geometry": {"coordinates":[-82.59849,31.865853],"type":"Point"}
}