{
  "type": "Feature",
  "properties": {
    "iso:country":"US",
    "sg:address":"1031 S Main St",
    "sg:city":"Cedartown",
    "sg:classifiers":[
        {
            "category":"Retail",
            "subcategory":"Auto Repair",
            "type":"Services"
        },
        {
            "category":"Wholesale",
            "subcategory":"Auto Parts",
            "type":"Manufacturing & Wholesale Goods"
        }
    ],
    "sg:phone":"+1 770 748 1690",
    "sg:postcode":"30125",
    "sg:province":"GA",
    "sg:tags":[
        "automotive",
        "rebuilt",
        "automobile"
    ],
    "wof:name":"Alternators and Starters",
    "wof:placetype":"venue"
},
  "geometry": {"coordinates":[-85.254468,34.002826],"type":"Point"}
}