{
  "type": "Feature",
  "properties": {
    "addr:full":"1957 Meadowbrook Cir NW Dalton GA 30720",
    "addr:housenumber":"1957",
    "addr:postcode":"30720",
    "addr:street":"Meadowbrook Cir Nw",
    "iso:country":"US",
    "sg:address":"1957 Meadowbrook Cir NW",
    "sg:city":"Dalton",
    "sg:classifiers":[
        {
            "category":"Manufacturing",
            "subcategory":"Textiles",
            "type":"Manufacturing & Wholesale Goods"
        }
    ],
    "sg:phone":"+1 706 278 5306",
    "sg:postcode":"30720",
    "sg:province":"GA",
    "sg:tags":[
        "mfg"
    ],
    "wof:name":"Hellenic Rug Import",
    "wof:placetype":"venue"
},
  "geometry": {"coordinates":[-85.00140500000001,34.807914],"type":"Point"}
}