{
  "type": "Feature",
  "properties": {
    "addr:full":"1350 Winder Hwy Jefferson GA 30549",
    "addr:housenumber":"1350",
    "addr:postcode":"30549",
    "addr:street":"Winder Hwy",
    "iso:country":"US",
    "sg:address":"1350 Winder Hwy",
    "sg:city":"Jefferson",
    "sg:classifiers":[
        {
            "category":"Real Estate",
            "subcategory":"Real Estate Agent",
            "type":"Services"
        }
    ],
    "sg:phone":"+1 706 654 1315",
    "sg:postcode":"30549",
    "sg:province":"GA",
    "wof:name":"American Dream Realty Inc",
    "wof:placetype":"venue"
},
  "geometry": {"coordinates":[-83.590974,34.107776],"type":"Point"}
}