{
  "type": "Feature",
  "properties": {
    "iso:country":"US",
    "sg:address":"80 West Wieuca Rd NE",
    "sg:city":"Atlanta",
    "sg:classifiers":[
        {
            "category":"Health Services",
            "subcategory":"Clinic",
            "type":"Services"
        }
    ],
    "sg:phone":"+1 404 474 0506",
    "sg:postcode":"30342",
    "sg:province":"GA",
    "sg:tags":[
        "outpatient"
    ],
    "sg:website":"http://www.playworkstherapy.com",
    "wof:name":"Playworks Pediatric Therapy",
    "wof:placetype":"venue"
},
  "geometry": {"coordinates":[-84.383596,33.877542],"type":"Point"}
}