{
  "type": "Feature",
  "properties": {
    "addr:full":"4096 Pine Valley Rd Tucker GA 30084",
    "addr:housenumber":"4096",
    "addr:postcode":"30084",
    "addr:street":"Pine Valley Rd",
    "iso:country":"US",
    "sg:address":"4096 Pine Valley Rd",
    "sg:city":"Tucker",
    "sg:classifiers":[
        {
            "category":"Building & Trades",
            "subcategory":"Construction",
            "type":"Services"
        }
    ],
    "sg:phone":"+1 770 414 9663",
    "sg:postcode":"30084",
    "sg:province":"GA",
    "sg:tags":[
        "equipment",
        "supply",
        "drywall",
        "contractor"
    ],
    "wof:name":"Mc Drywall",
    "wof:placetype":"venue"
},
  "geometry": {"coordinates":[-84.22035,33.84526],"type":"Point"}
}