{
  "type": "Feature",
  "properties": {
    "iso:country":"US",
    "sg:address":"431 Old Dixie Way",
    "sg:city":"Forest Park",
    "sg:classifiers":[
        {
            "category":"Professional",
            "subcategory":"Business Services",
            "type":"Services"
        }
    ],
    "sg:phone":"+1 404 363 8990",
    "sg:postcode":"30297",
    "sg:province":"GA",
    "wof:name":"GEM Machine Group",
    "wof:placetype":"venue"
},
  "geometry": {"coordinates":[-84.376316,33.587344],"type":"Point"}
}