{
  "type": "Feature",
  "properties": {
    "iso:country":"US",
    "sg:address":"2501 Moody Rd",
    "sg:city":"Warner Robins",
    "sg:classifiers":[
        {
            "category":"Shopping",
            "subcategory":"Florist",
            "type":"Retail Goods"
        }
    ],
    "sg:phone":"+1 478 922 5616",
    "sg:postcode":"31088",
    "sg:province":"GA",
    "wof:name":"Warner Robins Florist",
    "wof:placetype":"venue"
},
  "geometry": {"coordinates":[-83.623859,32.57911],"type":"Point"}
}