{
  "type": "Feature",
  "properties": {
    "iso:country":"US",
    "sg:address":"319 Bay Springs Rd",
    "sg:city":"Sandersville",
    "sg:classifiers":[
        {
            "category":"Organizations",
            "subcategory":"Religious Organization",
            "type":"Services"
        }
    ],
    "sg:phone":"+1 478 552 3545",
    "sg:postcode":"31082",
    "sg:province":"GA",
    "wof:name":"Bay Springs Baptist Church",
    "wof:placetype":"venue"
},
  "geometry": {"coordinates":[-82.829705,33.039355],"type":"Point"}
}