{
  "type": "Feature",
  "properties": {
    "addr:full":"6065 Roswell Rd NE Atlanta GA 30328",
    "addr:housenumber":"6065;rd",
    "addr:postcode":"30328",
    "addr:street":"Roswell;Ne",
    "iso:country":"US",
    "sg:address":"6065 Roswell Rd NE",
    "sg:city":"Atlanta",
    "sg:classifiers":[
        {
            "category":"Utilities",
            "subcategory":"Fuel Oil & Lpg",
            "type":"Services"
        },
        {
            "category":"Shopping",
            "subcategory":"Computers & Home Electronics",
            "type":"Retail Goods"
        }
    ],
    "sg:phone":"+1 404 303 0500",
    "sg:postcode":"30328",
    "sg:province":"GA",
    "sg:tags":[
        "development",
        "exploration",
        "gas",
        "inventor"
    ],
    "wof:name":"Strico Output Ltd",
    "wof:placetype":"venue"
},
  "geometry": {"coordinates":[-84.37898300000001,33.920071],"type":"Point"}
}