{
  "type": "Feature",
  "properties": {
    "addr:full":"1639 Eastland Rd SE Atlanta GA 30316",
    "addr:housenumber":"1639",
    "addr:postcode":"30316",
    "addr:street":"Eastland Rd Se",
    "iso:country":"US",
    "sg:address":"1639 Eastland Rd SE",
    "sg:city":"Atlanta",
    "sg:classifiers":[
        {
            "category":"Organizations",
            "subcategory":"Religious Organization",
            "type":"Services"
        }
    ],
    "sg:phone":"+1 404 627 7614",
    "sg:postcode":"30316",
    "sg:province":"GA",
    "wof:name":"Faith and Deliverence Ministries",
    "wof:placetype":"venue"
},
  "geometry": {"coordinates":[-84.3321,33.7188],"type":"Point"}
}