{
  "type": "Feature",
  "properties": {
    "addr:full":"3783 Evans To Locks Rd Augusta GA 30907",
    "addr:housenumber":"3783;to",
    "addr:postcode":"30907",
    "addr:street":"Evans;Locks Rd",
    "iso:country":"US",
    "sg:address":"3783 Evans To Locks Rd",
    "sg:city":"Augusta",
    "sg:classifiers":[
        {
            "category":"Building & Trades",
            "subcategory":"Construction",
            "type":"Services"
        }
    ],
    "sg:phone":"+1 706 364 8648",
    "sg:postcode":"30907",
    "sg:province":"GA",
    "sg:tags":[
        "house"
    ],
    "wof:name":"Get Around 2 It Inc",
    "wof:placetype":"venue"
},
  "geometry": {"coordinates":[-82.075203,33.553397],"type":"Point"}
}