{
  "type": "Feature",
  "properties": {
    "iso:country":"US",
    "sg:address":"2 Mall Ct",
    "sg:city":"Savannah",
    "sg:classifiers":[
        {
            "category":"Home & Garden",
            "subcategory":"Furniture",
            "type":"Retail Goods"
        }
    ],
    "sg:phone":"+1 912 355 6992",
    "sg:postcode":"31406",
    "sg:province":"GA",
    "wof:name":"Rosens Marine Inc",
    "wof:placetype":"venue"
},
  "geometry": {"coordinates":[-81.106551,32.002254],"type":"Point"}
}