{
  "type": "Feature",
  "properties": {
    "addr:full":"10 Mark St NE Rome GA 30165",
    "addr:housenumber":"10",
    "addr:postcode":"ga 30165",
    "addr:street":"Mark St Ne",
    "iso:country":"US",
    "sg:address":"10 Mark St NE",
    "sg:city":"Rome",
    "sg:classifiers":[
        {
            "category":"Organizations",
            "subcategory":"Religious Organization",
            "type":"Services"
        }
    ],
    "sg:phone":"+1 706 234 5661",
    "sg:postcode":"30165",
    "sg:province":"GA",
    "wof:name":"William C Mathis Rev",
    "wof:placetype":"venue"
},
  "geometry": {"coordinates":[-85.16776400000001,34.311093],"type":"Point"}
}