{
  "type": "Feature",
  "properties": {
    "iso:country":"US",
    "sg:address":"2791 Sagamore Hill Dr",
    "sg:city":"Marietta",
    "sg:classifiers":[
        {
            "category":"Building & Trades",
            "subcategory":"Construction",
            "type":"Services"
        }
    ],
    "sg:phone":"+1 770 953 3202",
    "sg:postcode":"30067",
    "sg:province":"GA",
    "sg:tags":[
        "house"
    ],
    "wof:name":"General Home Repair",
    "wof:placetype":"venue"
},
  "geometry": {"coordinates":[-84.47160700000001,33.933923],"type":"Point"}
}