{
  "type": "Feature",
  "properties": {
    "iso:country":"US",
    "sg:address":"9579 Highway 5",
    "sg:city":"Douglasville",
    "sg:classifiers":[
        {
            "category":"Home & Garden",
            "subcategory":"Furniture",
            "type":"Retail Goods"
        }
    ],
    "sg:phone":"+1 770 949 1887",
    "sg:postcode":"30135",
    "sg:province":"GA",
    "sg:tags":[
        "store"
    ],
    "wof:name":"Bens Brands For Less Mattress",
    "wof:placetype":"venue"
},
  "geometry": {"coordinates":[-84.76272,33.722618],"type":"Point"}
}