{
  "type": "Feature",
  "properties": {
    "addr:full":"1596 Chatham Parkway  1596 Chatham Parkway Savannah,  GA 31408",
    "addr:housenumber":"1596;1596",
    "addr:postcode":"31408",
    "addr:street":"Chatham Parkway;Chatham Parkway",
    "iso:country":"US",
    "sg:address":"1596 Chatham Parkway  1596 Chatham Parkway",
    "sg:city":"Savannah, ",
    "sg:classifiers":[
        {
            "category":"Professional",
            "subcategory":"Computer Services",
            "type":"Services"
        }
    ],
    "sg:postcode":"31408",
    "sg:province":"GA",
    "sg:website":"http://www.grainger.com",
    "wof:name":"W.W. Grainger",
    "wof:placetype":"venue"
},
  "geometry": {"coordinates":[-81.160501,32.073454],"type":"Point"}
}