{
  "type": "Feature",
  "properties": {
    "addr:full":"40 River Shoals Ct Covington GA 30016",
    "addr:housenumber":"40",
    "addr:postcode":"30016",
    "addr:street":"River Shoals Ct",
    "iso:country":"US",
    "sg:address":"40 River Shoals Ct",
    "sg:city":"Covington",
    "sg:classifiers":[
        {
            "category":"Professional",
            "subcategory":"Art Services",
            "type":"Services"
        }
    ],
    "sg:phone":"+1 678 342 7951",
    "sg:postcode":"30016",
    "sg:province":"GA",
    "sg:tags":[
        "designer",
        "display",
        "producer"
    ],
    "wof:name":"Mary Magic Designs",
    "wof:placetype":"venue"
},
  "geometry": {"coordinates":[-83.883245,33.534508],"type":"Point"}
}