{
  "type": "Feature",
  "properties": {
    "iso:country":"US",
    "sg:address":"680 Murphy Ave SW",
    "sg:city":"Atlanta",
    "sg:classifiers":[
        {
            "category":"Health Services",
            "subcategory":"Hospital",
            "type":"Services"
        }
    ],
    "sg:phone":"+1 404 758 4463",
    "sg:postcode":"30310",
    "sg:province":"GA",
    "sg:tags":[
        "mental"
    ],
    "wof:name":"American Psychiatric Partners",
    "wof:placetype":"venue"
},
  "geometry": {"coordinates":[-84.412312,33.736119],"type":"Point"}
}