{
  "type": "Feature",
  "properties": {
    "iso:country":"US",
    "sg:address":"2550 Sandy Plains Rd",
    "sg:city":"Marietta",
    "sg:classifiers":[
        {
            "category":"Retail",
            "subcategory":"Laundry & Dry Cleaning",
            "type":"Services"
        }
    ],
    "sg:phone":"+1 770 973 8406",
    "sg:postcode":"30066",
    "sg:province":"GA",
    "wof:name":"Beverly Alteration Inc",
    "wof:placetype":"venue"
},
  "geometry": {"coordinates":[-84.489621,34.020362],"type":"Point"}
}