{
  "type": "Feature",
  "properties": {
    "iso:country":"US",
    "sg:address":"117 River Trace Ct",
    "sg:city":"Mc Donough",
    "sg:classifiers":[
        {
            "category":"Retail",
            "subcategory":"Laundry & Dry Cleaning",
            "type":"Services"
        }
    ],
    "sg:phone":"+1 678 343 1015",
    "sg:postcode":"30253",
    "sg:province":"GA",
    "sg:tags":[
        "carpet"
    ],
    "wof:name":"Superior Carpet Care Inc",
    "wof:placetype":"venue"
},
  "geometry": {"coordinates":[-84.164102,33.454445],"type":"Point"}
}