{
  "type": "Feature",
  "properties": {
    "addr:full":"452 Wimberly Way Powder Springs GA 30127",
    "addr:housenumber":"452",
    "addr:postcode":"30127",
    "addr:street":"Wimberly Way",
    "iso:country":"US",
    "sg:address":"452 Wimberly Way",
    "sg:city":"Powder Springs",
    "sg:classifiers":[
        {
            "category":"Autos & Motor Vehicles",
            "subcategory":"Automobile Sales",
            "type":"Retail Goods"
        }
    ],
    "sg:phone":"+1 770 489 7507",
    "sg:postcode":"30127",
    "sg:province":"GA",
    "sg:tags":[
        "used"
    ],
    "wof:name":"Dallas Auto Mart",
    "wof:placetype":"venue"
},
  "geometry": {"coordinates":[-84.75888999999999,33.803855],"type":"Point"}
}