{
  "type": "Feature",
  "properties": {
    "addr:full":"110 S Fry St Valdosta GA 31601",
    "addr:housenumber":"110",
    "addr:postcode":"31601",
    "addr:street":"S Fry St",
    "iso:country":"US",
    "sg:address":"110 S Fry St",
    "sg:city":"Valdosta",
    "sg:classifiers":[
        {
            "category":"Social Services",
            "subcategory":"Child Care",
            "type":"Services"
        }
    ],
    "sg:phone":"+1 229 247 3501",
    "sg:postcode":"31601",
    "sg:province":"GA",
    "wof:name":"Cuddle Care Ctr",
    "wof:placetype":"venue"
},
  "geometry": {"coordinates":[-83.270797,30.8338],"type":"Point"}
}