{
  "type": "Feature",
  "properties": {
    "addr:full":"11365 Crabapple Rd Roswell GA 30075",
    "addr:housenumber":"11365",
    "addr:postcode":"30075",
    "addr:street":"Crabapple Rd",
    "iso:country":"US",
    "sg:address":"11365 Crabapple Rd",
    "sg:city":"Roswell",
    "sg:classifiers":[
        {
            "category":"Organizations",
            "subcategory":"Religious Organization",
            "type":"Services"
        }
    ],
    "sg:phone":"+1 770 993 4617",
    "sg:postcode":"30075",
    "sg:province":"GA",
    "wof:name":"First Christian Church of Roswell",
    "wof:placetype":"venue"
},
  "geometry": {"coordinates":[-84.361198,34.0574],"type":"Point"}
}