{
  "type": "Feature",
  "properties": {
    "iso:country":"US",
    "sg:address":"4579 Jonesboro Rd",
    "sg:city":"Forest Park",
    "sg:classifiers":[
        {
            "category":"Food & Beverages",
            "subcategory":"Specialty",
            "type":"Retail Goods"
        }
    ],
    "sg:phone":"+1 404 366 5100",
    "sg:postcode":"30297",
    "sg:province":"GA",
    "wof:name":"Year Round Sales",
    "wof:placetype":"venue"
},
  "geometry": {"coordinates":[-84.357253,33.632008],"type":"Point"}
}