{
  "type": "Feature",
  "properties": {
    "iso:country":"US",
    "sg:address":"5959 Highway 42",
    "sg:city":"Ellenwood",
    "sg:classifiers":[
        {
            "category":"Shopping",
            "subcategory":"Tobacco",
            "type":"Retail Goods"
        },
        {
            "category":"Food & Beverages",
            "subcategory":"Liquor & Beverages",
            "type":"Retail Goods"
        }
    ],
    "sg:phone":"+1 770 968 5300",
    "sg:postcode":"30294",
    "sg:province":"GA",
    "sg:tags":[
        "shop",
        "beer",
        "spirit",
        "wine"
    ],
    "wof:name":"Curly's Outlet Beer Wine & Tobacco",
    "wof:placetype":"venue"
},
  "geometry": {"coordinates":[-84.293999,33.5919],"type":"Point"}
}