{
  "type": "Feature",
  "properties": {
    "iso:country":"US",
    "sg:address":"204 US Hwy 341",
    "sg:city":"Lumber City",
    "sg:classifiers":[
        {
            "category":"Food & Beverages",
            "subcategory":"Groceries & Convenience Stores",
            "type":"Retail Goods"
        }
    ],
    "sg:phone":"+1 912 363 2828",
    "sg:postcode":"31545",
    "sg:province":"GA",
    "wof:name":"Mac's Milk",
    "wof:placetype":"venue"
},
  "geometry": {"coordinates":[-81.88524099999999,31.607242],"type":"Point"}
}