{
  "type": "Feature",
  "properties": {
    "iso:country":"US",
    "sg:address":"5771 Winchester Pl",
    "sg:city":"Lithonia",
    "sg:classifiers":[
        {
            "category":"Bakery",
            "type":"Food & Drink"
        }
    ],
    "sg:phone":"+1 678 518 8243",
    "sg:postcode":"30038",
    "sg:province":"GA",
    "sg:tags":[
        "cake",
        "pastry",
        "wedding"
    ],
    "wof:name":"Pound Cakes By Elaine",
    "wof:placetype":"venue"
},
  "geometry": {"coordinates":[-84.15454200000001,33.663274],"type":"Point"}
}