{
  "type": "Feature",
  "properties": {
    "iso:country":"US",
    "sg:address":"270 Peachtree St NW",
    "sg:city":"Atlanta",
    "sg:phone":"+1 404 659 0078",
    "sg:postcode":"30303",
    "sg:province":"GA",
    "wof:name":"AAA Parking",
    "wof:placetype":"venue"
},
  "geometry": {"coordinates":[-84.387558,33.761954],"type":"Point"}
}