{
  "type": "Feature",
  "properties": {
    "addr:full":"2150 E Walnut Ave Dalton GA 30721",
    "addr:housenumber":"2150",
    "addr:postcode":"30721",
    "addr:street":"E Walnut Ave",
    "iso:country":"US",
    "sg:address":"2150 E Walnut Ave",
    "sg:city":"Dalton",
    "sg:classifiers":[
        {
            "category":"Shopping",
            "subcategory":"Bicycles & Sporting Goods",
            "type":"Retail Goods"
        },
        {
            "category":"Shopping",
            "subcategory":"Clothing, Apparel, & Fashions",
            "type":"Retail Goods"
        }
    ],
    "sg:phone":"+1 706 226 8335",
    "sg:postcode":"30721",
    "sg:province":"GA",
    "wof:name":"Hibbett Sporting Goods Inc",
    "wof:placetype":"venue"
},
  "geometry": {"coordinates":[-84.931392,34.762548],"type":"Point"}
}