{
  "type": "Feature",
  "properties": {
    "iso:country":"US",
    "sg:address":"3418 Dogwood Dr",
    "sg:city":"Hapeville",
    "sg:classifiers":[
        {
            "category":"Retail",
            "subcategory":"Auto Repair",
            "type":"Services"
        }
    ],
    "sg:phone":"+1 404 209 7661",
    "sg:postcode":"30354",
    "sg:province":"GA",
    "sg:tags":[
        "body",
        "automobile",
        "painting"
    ],
    "wof:name":"Spartan Lincoln Mercury Body",
    "wof:placetype":"venue"
},
  "geometry": {"coordinates":[-84.409876,33.661168],"type":"Point"}
}