{
  "type": "Feature",
  "properties": {
    "iso:country":"US",
    "sg:address":"4815 Northway Dr NE",
    "sg:city":"Atlanta",
    "sg:classifiers":[
        {
            "category":"Manufacturing",
            "subcategory":"Signs",
            "type":"Manufacturing & Wholesale Goods"
        }
    ],
    "sg:phone":"+1 404 250 0720",
    "sg:postcode":"30342",
    "sg:province":"GA",
    "sg:tags":[
        "specialty",
        "mfg"
    ],
    "wof:name":"J Lang",
    "wof:placetype":"venue"
},
  "geometry": {"coordinates":[-84.36209700000001,33.888412],"type":"Point"}
}