{
  "type": "Feature",
  "properties": {
    "addr:full":"424 Cook St Royston GA 30662",
    "addr:housenumber":"424",
    "addr:postcode":"30662",
    "addr:street":"Cook St",
    "iso:country":"US",
    "sg:address":"424 Cook St",
    "sg:city":"Royston",
    "sg:classifiers":[
        {
            "category":"Home & Garden",
            "subcategory":"Garden Supply",
            "type":"Retail Goods"
        }
    ],
    "sg:phone":"+1 706 245 8001",
    "sg:postcode":"30662",
    "sg:province":"GA",
    "sg:tags":[
        "lawn"
    ],
    "wof:name":"Johnson's Mower Shop",
    "wof:placetype":"venue"
},
  "geometry": {"coordinates":[-83.117706,34.283731],"type":"Point"}
}