{
  "type": "Feature",
  "properties": {
    "iso:country":"US",
    "sg:address":"309 Owens Dr",
    "sg:city":"Juliette",
    "sg:classifiers":[
        {
            "category":"Building & Trades",
            "subcategory":"Landscaping Services",
            "type":"Services"
        }
    ],
    "sg:phone":"+1 478 474 6022",
    "sg:postcode":"31046",
    "sg:province":"GA",
    "wof:name":"Halls Tree Service",
    "wof:placetype":"venue"
},
  "geometry": {"coordinates":[-83.751306,32.983175],"type":"Point"}
}