{
  "type": "Feature",
  "properties": {
    "iso:country":"US",
    "sg:address":"710 E Lake Dr",
    "sg:city":"Decatur",
    "sg:classifiers":[
        {
            "category":"Food & Beverages",
            "subcategory":"Groceries & Convenience Stores",
            "type":"Retail Goods"
        }
    ],
    "sg:phone":"+1 404 378 6411",
    "sg:postcode":"30030",
    "sg:province":"GA",
    "sg:tags":[
        "product",
        "grocer"
    ],
    "wof:name":"Hop N Shop Food Store",
    "wof:placetype":"venue"
},
  "geometry": {"coordinates":[-84.30321000000001,33.759357],"type":"Point"}
}