{
  "type": "Feature",
  "properties": {
    "addr:full":"4551 Lindsey Dr Powder Springs GA 30127",
    "addr:housenumber":"4551",
    "addr:postcode":"30127",
    "addr:street":"Lindsey Dr",
    "iso:country":"US",
    "sg:address":"4551 Lindsey Dr",
    "sg:city":"Powder Springs",
    "sg:classifiers":[
        {
            "category":"Real Estate",
            "subcategory":"Real Estate Operator",
            "type":"Services"
        }
    ],
    "sg:phone":"+1 770 439 8366",
    "sg:postcode":"30127",
    "sg:province":"GA",
    "sg:tags":[
        "building",
        "nonresidential"
    ],
    "wof:name":"SL Properties",
    "wof:placetype":"venue"
},
  "geometry": {"coordinates":[-84.69258000000001,33.820762],"type":"Point"}
}