{
  "type": "Feature",
  "properties": {
    "iso:country":"US",
    "sg:address":"2175 Laurel Mill Way",
    "sg:city":"Roswell",
    "sg:classifiers":[
        {
            "category":"Professional",
            "subcategory":"Business Services",
            "type":"Services"
        }
    ],
    "sg:phone":"+1 678 352 8229",
    "sg:postcode":"30076",
    "sg:province":"GA",
    "wof:name":"K H Designs",
    "wof:placetype":"venue"
},
  "geometry": {"coordinates":[-84.298236,34.031858],"type":"Point"}
}