{
  "type": "Feature",
  "properties": {
    "addr:full":"3640 Campbellton Rd SW Atlanta GA 30331",
    "addr:housenumber":"3640",
    "addr:postcode":"30331",
    "addr:street":"Campbellton Rd Sw",
    "iso:country":"US",
    "sg:address":"3640 Campbellton Rd SW",
    "sg:city":"Atlanta",
    "sg:phone":"+1 404 346 7040",
    "sg:postcode":"30331",
    "sg:province":"GA",
    "wof:name":"Ricks Beauty & Barber Salon Inc",
    "wof:placetype":"venue"
},
  "geometry": {"coordinates":[-84.507324,33.690028],"type":"Point"}
}