{
  "type": "Feature",
  "properties": {
    "iso:country":"US",
    "sg:address":"205 Daisy Pl",
    "sg:city":"Newnan",
    "sg:classifiers":[
        {
            "category":"Professional",
            "subcategory":"Computer Services",
            "type":"Services"
        }
    ],
    "sg:phone":"+1 770 251 4556",
    "sg:postcode":"30265",
    "sg:province":"GA",
    "sg:tags":[
        "related"
    ],
    "wof:name":"C C F Enterprises",
    "wof:placetype":"venue"
},
  "geometry": {"coordinates":[-84.70082600000001,33.413445],"type":"Point"}
}