{
  "type": "Feature",
  "properties": {
    "addr:full":"7370 Hodgson Memorial Dr Savannah GA 31406",
    "addr:housenumber":"7370",
    "addr:postcode":"31406",
    "addr:street":"Hodgson Memorial Dr",
    "iso:country":"US",
    "sg:address":"7370 Hodgson Memorial Dr",
    "sg:city":"Savannah",
    "sg:classifiers":[
        {
            "category":"Professional",
            "subcategory":"Management & Consulting",
            "type":"Services"
        },
        {
            "category":"Social Services",
            "type":"Services"
        }
    ],
    "sg:phone":"+1 912 351 0307",
    "sg:postcode":"31406",
    "sg:province":"GA",
    "sg:tags":[
        "employee",
        "assistance",
        "program"
    ],
    "wof:name":"Life Style Management Resource",
    "wof:placetype":"venue"
},
  "geometry": {"coordinates":[-81.11315999999999,32.001728],"type":"Point"}
}