{
  "type": "Feature",
  "properties": {
    "iso:country":"US",
    "sg:address":"68 Eagle Landing Dr",
    "sg:city":"Flintstone",
    "sg:classifiers":[
        {
            "category":"Shopping",
            "subcategory":"Gifts & Souvenirs",
            "type":"Retail Goods"
        }
    ],
    "sg:phone":"+1 706 820 2221",
    "sg:postcode":"30725",
    "sg:province":"GA",
    "wof:name":"Shapiros Gift Baskets",
    "wof:placetype":"venue"
},
  "geometry": {"coordinates":[-85.349621,34.923078],"type":"Point"}
}