{
  "type": "Feature",
  "properties": {
    "iso:country":"US",
    "sg:address":"1506 Bankhead Hwy",
    "sg:city":"Carrollton",
    "sg:classifiers":[
        {
            "category":"Shopping",
            "subcategory":"Discount & Variety Stores",
            "type":"Retail Goods"
        }
    ],
    "sg:phone":"+1 770 456 2060",
    "sg:postcode":"30116",
    "sg:province":"GA",
    "wof:name":"A Little Of This & A Little Of",
    "wof:placetype":"venue"
},
  "geometry": {"coordinates":[-85.025672,33.603424],"type":"Point"}
}