{
  "type": "Feature",
  "properties": {
    "iso:country":"US",
    "sg:address":"2623 Dawson Rd",
    "sg:city":"Albany",
    "sg:classifiers":[
        {
            "category":"Autos & Motor Vehicles",
            "subcategory":"Automobile Sales",
            "type":"Retail Goods"
        }
    ],
    "sg:phone":"+1 229 888 0510",
    "sg:postcode":"31707",
    "sg:province":"GA",
    "sg:tags":[
        "car",
        "used",
        "dealership"
    ],
    "wof:name":"Albany Lincoln Mercury Inc",
    "wof:placetype":"venue"
},
  "geometry": {"coordinates":[-84.2174,31.614613],"type":"Point"}
}