{
  "type": "Feature",
  "properties": {
    "iso:country":"US",
    "sg:address":"6770 Veterans Pkwy",
    "sg:city":"Columbus",
    "sg:classifiers":[
        {
            "category":"Personal",
            "subcategory":"Beauty Salon",
            "type":"Services"
        },
        {
            "category":"Personal",
            "subcategory":"Nail Salon",
            "type":"Services"
        }
    ],
    "sg:phone":"+1 706 653 2212",
    "sg:postcode":"31909",
    "sg:province":"GA",
    "wof:name":"New Nails Salon",
    "wof:placetype":"venue"
},
  "geometry": {"coordinates":[-84.954021,32.542819],"type":"Point"}
}