{
  "type": "Feature",
  "properties": {
    "addr:full":"331 Pyles Marsh Rd Brunswick GA 31525",
    "addr:housenumber":"331",
    "addr:postcode":"31525",
    "addr:street":"Pyles Marsh Rd",
    "iso:country":"US",
    "sg:address":"331 Pyles Marsh Rd",
    "sg:city":"Brunswick",
    "sg:classifiers":[
        {
            "category":"Manufacturing",
            "subcategory":"Lumber",
            "type":"Manufacturing & Wholesale Goods"
        }
    ],
    "sg:phone":"+1 912 280 9598",
    "sg:postcode":"31525",
    "sg:province":"GA",
    "sg:tags":[
        "operator",
        "mill",
        "local",
        "trucking"
    ],
    "wof:name":"Dewitt Interprizes",
    "wof:placetype":"venue"
},
  "geometry": {"coordinates":[-81.539356,31.247585],"type":"Point"}
}