{
  "type": "Feature",
  "properties": {
    "iso:country":"US",
    "sg:address":"6340 Sugarloaf Pkwy",
    "sg:city":"Duluth",
    "sg:classifiers":[
        {
            "category":"Professional",
            "type":"Services"
        }
    ],
    "sg:phone":"+1 678 584 5072",
    "sg:postcode":"30097",
    "sg:province":"GA",
    "sg:tags":[
        "establishment"
    ],
    "wof:name":"CTR Partners LLP",
    "wof:placetype":"venue"
},
  "geometry": {"coordinates":[-84.088403,33.989938],"type":"Point"}
}