{
  "type": "Feature",
  "properties": {
    "iso:country":"US",
    "sg:address":"300 Josephine Park Rd",
    "sg:city":"Waycross",
    "sg:classifiers":[
        {
            "category":"Social Services",
            "subcategory":"Child Care",
            "type":"Services"
        }
    ],
    "sg:phone":"+1 912 287 1419",
    "sg:postcode":"31503",
    "sg:province":"GA",
    "sg:tags":[
        "day"
    ],
    "wof:name":"Vicki Kauffman",
    "wof:placetype":"venue"
},
  "geometry": {"coordinates":[-82.255888,31.182563],"type":"Point"}
}