{
  "type": "Feature",
  "properties": {
    "iso:country":"US",
    "sg:address":"3083 Breckinridge Blvd",
    "sg:city":"Duluth",
    "sg:classifiers":[
        {
            "category":"Personal",
            "subcategory":"Barber",
            "type":"Services"
        }
    ],
    "sg:phone":"+1 770 931 7997",
    "sg:postcode":"30096",
    "sg:province":"GA",
    "wof:name":"Northern X-Posure",
    "wof:placetype":"venue"
},
  "geometry": {"coordinates":[-84.10289299999999,33.960102],"type":"Point"}
}