{
  "type": "Feature",
  "properties": {
    "addr:full":"1175 Lyndhurst Way Roswell GA 30075",
    "addr:housenumber":"1175",
    "addr:postcode":"30075",
    "addr:street":"Lyndhurst Way",
    "iso:country":"US",
    "sg:address":"1175 Lyndhurst Way",
    "sg:city":"Roswell",
    "sg:classifiers":[
        {
            "category":"Professional",
            "subcategory":"Computer Services",
            "type":"Services"
        }
    ],
    "sg:phone":"+1 770 587 9489",
    "sg:postcode":"30075",
    "sg:province":"GA",
    "sg:tags":[
        "datum"
    ],
    "wof:name":"Broadcast Data Sys",
    "wof:placetype":"venue"
},
  "geometry": {"coordinates":[-84.377189,34.052312],"type":"Point"}
}