{
  "type": "Feature",
  "properties": {
    "addr:full":"1395 Iris Dr SE Conyers GA 30013",
    "addr:housenumber":"1395",
    "addr:postcode":"30013",
    "addr:street":"Iris Dr Se",
    "iso:country":"US",
    "sg:address":"1395 Iris Dr SE",
    "sg:city":"Conyers",
    "sg:classifiers":[
        {
            "category":"Real Estate",
            "subcategory":"Real Estate Services",
            "type":"Services"
        },
        {
            "category":"Real Estate",
            "subcategory":"Surveying",
            "type":"Services"
        },
        {
            "category":"Real Estate",
            "subcategory":"Real Estate Agent",
            "type":"Services"
        }
    ],
    "sg:phone":"+1 770 483 0279",
    "sg:postcode":"30013",
    "sg:province":"GA",
    "sg:tags":[
        "buyer",
        "industrial",
        "appraisers-commercial",
        "broker",
        "appraiser"
    ],
    "wof:name":"Peachtree Appraisal Inc",
    "wof:placetype":"venue"
},
  "geometry": {"coordinates":[-83.99918700000001,33.649839],"type":"Point"}
}