{
  "type": "Feature",
  "properties": {
    "iso:country":"US",
    "sg:address":"2351 Howell Rd",
    "sg:city":"Warrenton",
    "sg:classifiers":[
        {
            "category":"Farming",
            "subcategory":"Farm & Veterinary Services",
            "type":"Manufacturing & Wholesale Goods"
        }
    ],
    "sg:phone":"+1 706 465 2985",
    "sg:postcode":"30828",
    "sg:province":"GA",
    "sg:tags":[
        "preparation",
        "crop",
        "for",
        "market"
    ],
    "wof:name":"Robert Johnson",
    "wof:placetype":"venue"
},
  "geometry": {"coordinates":[-82.661171,33.352178],"type":"Point"}
}