{
  "type": "Feature",
  "properties": {
    "addr:full":"1240 Gordon Park Rd Augusta GA 30901",
    "addr:housenumber":"1240",
    "addr:postcode":"30901",
    "addr:street":"Gordon Park Rd",
    "iso:country":"US",
    "sg:address":"1240 Gordon Park Rd",
    "sg:city":"Augusta",
    "sg:classifiers":[
        {
            "category":"Professional",
            "type":"Services"
        },
        {
            "category":"Personal",
            "type":"Services"
        },
        {
            "category":"Retail",
            "subcategory":"Event Space",
            "type":"Services"
        },
        {
            "category":"Retail",
            "subcategory":"Pet Boarding",
            "type":"Services"
        }
    ],
    "sg:phone":"+1 706 722 7582",
    "sg:postcode":"30901",
    "sg:province":"GA",
    "sg:tags":[
        "box",
        "full",
        "material",
        "storage",
        "packaging",
        "packing",
        "crating",
        "moving",
        "services-labor",
        "mover"
    ],
    "sg:website":"http://www.mayflower.com",
    "wof:name":"Mayflower Transit",
    "wof:placetype":"venue"
},
  "geometry": {"coordinates":[-81.97242300000001,33.454837],"type":"Point"}
}