{
  "type": "Feature",
  "properties": {
    "addr:full":"1413 Highway 76 Chatsworth GA 30705",
    "addr:housenumber":"1413",
    "addr:postcode":"30705",
    "addr:street":"Highway 76",
    "iso:country":"US",
    "sg:address":"1413 Highway 76",
    "sg:city":"Chatsworth",
    "sg:classifiers":[
        {
            "category":"Manufacturing",
            "subcategory":"Buildings",
            "type":"Manufacturing & Wholesale Goods"
        },
        {
            "category":"Building & Trades",
            "subcategory":"Construction",
            "type":"Services"
        }
    ],
    "sg:phone":"+1 706 695 8351",
    "sg:postcode":"30705",
    "sg:province":"GA",
    "sg:tags":[
        "roofing",
        "industrial",
        "system",
        "builder",
        "specialty",
        "heating",
        "contractors-commercial",
        "home",
        "contractor",
        "air conditioning"
    ],
    "wof:name":"Leonard Brothers Construction Inc",
    "wof:placetype":"venue"
},
  "geometry": {"coordinates":[-84.79435700000001,34.782683],"type":"Point"}
}