{
  "type": "Feature",
  "properties": {
    "iso:country":"US",
    "sg:address":"1538 N Moore Rd",
    "sg:city":"Rising Fawn",
    "sg:classifiers":[
        {
            "category":"Building & Trades",
            "subcategory":"Construction",
            "type":"Services"
        }
    ],
    "sg:phone":"+1 706 398 1291",
    "sg:postcode":"30738",
    "sg:province":"GA",
    "sg:tags":[
        "house",
        "general",
        "contractor"
    ],
    "wof:name":"Mc Bryar & Son Construction",
    "wof:placetype":"venue"
},
  "geometry": {"coordinates":[-85.453912,34.80854],"type":"Point"}
}