{
  "type": "Feature",
  "properties": {
    "iso:country":"US",
    "sg:address":"1081 Apalachee Woods Dr",
    "sg:city":"Buckhead",
    "sg:classifiers":[
        {
            "category":"Transit Center",
            "subcategory":"Freight",
            "type":"Transportation"
        },
        {
            "category":"Freight",
            "type":"Transportation"
        }
    ],
    "sg:phone":"+1 706 342 3744",
    "sg:postcode":"30625",
    "sg:province":"GA",
    "sg:tags":[
        "trucking-motor",
        "trucking"
    ],
    "wof:name":"Matthew D Smith Enterprises",
    "wof:placetype":"venue"
},
  "geometry": {"coordinates":[-83.331073,33.579224],"type":"Point"}
}