{
  "type": "Feature",
  "properties": {
    "iso:country":"US",
    "sg:address":"6111 Peachtree Dunwoody Rd",
    "sg:city":"Atlanta",
    "sg:classifiers":[
        {
            "category":"Health Services",
            "subcategory":"Health Practitioner",
            "type":"Services"
        }
    ],
    "sg:phone":"+1 770 828 0055",
    "sg:postcode":"30328",
    "sg:province":"GA",
    "wof:name":"Herbert K Stone PHD",
    "wof:placetype":"venue"
},
  "geometry": {"coordinates":[-84.351276,33.922568],"type":"Point"}
}