{
  "type": "Feature",
  "properties": {
    "iso:country":"US",
    "sg:address":"1070 Iris Dr SW",
    "sg:city":"Conyers",
    "sg:classifiers":[
        {
            "category":"Real Estate",
            "subcategory":"Real Estate Agent",
            "type":"Services"
        }
    ],
    "sg:phone":"+1 770 483 3939",
    "sg:postcode":"30094",
    "sg:province":"GA",
    "wof:name":"Gerri Murphy Realty Inc",
    "wof:placetype":"venue"
},
  "geometry": {"coordinates":[-84.02641199999999,33.662292],"type":"Point"}
}