{
  "type": "Feature",
  "properties": {
    "addr:full":"2301 Saint James Ct Marietta GA 30066",
    "addr:housenumber":"2301",
    "addr:postcode":"30066",
    "addr:street":"Saint James Ct",
    "iso:country":"US",
    "sg:address":"2301 Saint James Ct",
    "sg:city":"Marietta",
    "sg:classifiers":[
        {
            "category":"Insurance",
            "subcategory":"Insurance Agent",
            "type":"Services"
        }
    ],
    "sg:phone":"+1 770 509 0083",
    "sg:postcode":"30066",
    "sg:province":"GA",
    "wof:name":"Emerald Coast Marketing",
    "wof:placetype":"venue"
},
  "geometry": {"coordinates":[-84.514563,34.009777],"type":"Point"}
}