{
  "type": "Feature",
  "properties": {
    "addr:full":"1611 Nixon Rd Augusta GA 30906",
    "addr:housenumber":"1611",
    "addr:postcode":"30906",
    "addr:street":"Nixon Rd",
    "iso:country":"US",
    "sg:address":"1611 Nixon Rd",
    "sg:city":"Augusta",
    "sg:classifiers":[
        {
            "category":"Freight",
            "type":"Transportation"
        }
    ],
    "sg:phone":"+1 706 790 4251",
    "sg:postcode":"30906",
    "sg:province":"GA",
    "sg:tags":[
        "storage"
    ],
    "wof:name":"Covenant Storage",
    "wof:placetype":"venue"
},
  "geometry": {"coordinates":[-81.992777,33.424076],"type":"Point"}
}