{
  "type": "Feature",
  "properties": {
    "iso:country":"US",
    "sg:address":"206 Turtle Point Dr",
    "sg:city":"Carrollton",
    "sg:classifiers":[
        {
            "category":"Personal",
            "subcategory":"Beauty Salon",
            "type":"Services"
        }
    ],
    "sg:phone":"+1 770 832 8171",
    "sg:postcode":"30116",
    "sg:province":"GA",
    "sg:tags":[
        "shop"
    ],
    "wof:name":"Wonder Nails",
    "wof:placetype":"venue"
},
  "geometry": {"coordinates":[-85.047027,33.605546],"type":"Point"}
}