{
  "type": "Feature",
  "properties": {
    "addr:full":"1921 George Rd Augusta GA 30904",
    "addr:housenumber":"1921",
    "addr:postcode":"30904",
    "addr:street":"George Rd",
    "iso:country":"US",
    "sg:address":"1921 George Rd",
    "sg:city":"Augusta",
    "sg:classifiers":[
        {
            "category":"Building & Trades",
            "subcategory":"Construction",
            "type":"Services"
        }
    ],
    "sg:phone":"+1 706 729 9604",
    "sg:postcode":"30904",
    "sg:province":"GA",
    "sg:tags":[
        "repairing",
        "remodeling",
        "contractor"
    ],
    "wof:name":"Master Crafters",
    "wof:placetype":"venue"
},
  "geometry": {"coordinates":[-82.026044,33.446902],"type":"Point"}
}