{
  "type": "Feature",
  "properties": {
    "iso:country":"US",
    "sg:address":"2865 Donald Lee Hollowell Pkwy NW",
    "sg:city":"Atlanta",
    "sg:classifiers":[
        {
            "category":"Education",
            "subcategory":"School",
            "type":"Public Place"
        }
    ],
    "sg:phone":"+1 404 792 5975",
    "sg:postcode":"30318",
    "sg:province":"GA",
    "sg:tags":[
        "high",
        "middle",
        "elementary"
    ],
    "wof:name":"Tiem Pivado",
    "wof:placetype":"venue"
},
  "geometry": {"coordinates":[-84.481647,33.780965],"type":"Point"}
}