{
  "type": "Feature",
  "properties": {
    "addr:full":"4745 Hopewell Rd Cumming GA 30028",
    "addr:housenumber":"4745",
    "addr:postcode":"30028",
    "addr:street":"Hopewell Rd",
    "iso:country":"US",
    "sg:address":"4745 Hopewell Rd",
    "sg:city":"Cumming",
    "sg:classifiers":[
        {
            "category":"Social Services",
            "subcategory":"Child Care",
            "type":"Services"
        }
    ],
    "sg:phone":"+1 770 889 0621",
    "sg:postcode":"30028",
    "sg:province":"GA",
    "sg:tags":[
        "day"
    ],
    "wof:name":"D S Tiny Leatherworks",
    "wof:placetype":"venue"
},
  "geometry": {"coordinates":[-84.080815,34.303285],"type":"Point"}
}