{
  "type": "Feature",
  "properties": {
    "iso:country":"US",
    "sg:address":"1706 Holloway Rd",
    "sg:city":"Brooklet",
    "sg:classifiers":[
        {
            "category":"Manufacturing",
            "subcategory":"Printing",
            "type":"Manufacturing & Wholesale Goods"
        }
    ],
    "sg:phone":"+1 912 842 4200",
    "sg:postcode":"30415",
    "sg:province":"GA",
    "sg:tags":[
        "printer"
    ],
    "wof:name":"Brooklet Printing & Ofc Supply",
    "wof:placetype":"venue"
},
  "geometry": {"coordinates":[-81.602557,32.39698],"type":"Point"}
}