{
  "type": "Feature",
  "properties": {
    "addr:full":"6751 Houston Rd Macon GA 31216",
    "addr:housenumber":"6751",
    "addr:postcode":"31216",
    "addr:street":"Houston Rd",
    "iso:country":"US",
    "sg:address":"6751 Houston Rd",
    "sg:city":"Macon",
    "sg:classifiers":[
        {
            "category":"Organizations",
            "subcategory":"Religious Organization",
            "type":"Services"
        }
    ],
    "sg:phone":"+1 478 781 2324",
    "sg:postcode":"31216",
    "sg:province":"GA",
    "sg:tags":[
        "baptist",
        "church"
    ],
    "sg:website":"www.mikadobc.com",
    "wof:name":"Mikado Baptist Church",
    "wof:placetype":"venue"
},
  "geometry": {"coordinates":[-83.689301,32.716801],"type":"Point"}
}