{
  "type": "Feature",
  "properties": {
    "iso:country":"US",
    "sg:address":"4789 Buford Hwy NE",
    "sg:city":"Atlanta",
    "sg:classifiers":[
        {
            "category":"Autos & Motor Vehicles",
            "subcategory":"Auto Supplies",
            "type":"Retail Goods"
        },
        {
            "category":"Wholesale",
            "subcategory":"Auto Parts",
            "type":"Manufacturing & Wholesale Goods"
        }
    ],
    "sg:phone":"+1 770 458 5581",
    "sg:postcode":"30341",
    "sg:province":"GA",
    "sg:tags":[
        "automobile"
    ],
    "wof:name":"NAPA Auto Parts",
    "wof:placetype":"venue"
},
  "geometry": {"coordinates":[-84.290279,33.881791],"type":"Point"}
}