{
  "type": "Feature",
  "properties": {
    "iso:country":"US",
    "sg:address":"1820 Highway 20 SE",
    "sg:city":"Conyers",
    "sg:classifiers":[
        {
            "category":"Shopping",
            "subcategory":"Books",
            "type":"Retail Goods"
        }
    ],
    "sg:phone":"+1 770 483 4800",
    "sg:postcode":"30013",
    "sg:province":"GA",
    "sg:tags":[
        "bookstore"
    ],
    "wof:name":"Conyers Discount Book Sales",
    "wof:placetype":"venue"
},
  "geometry": {"coordinates":[-84.014397,33.6339],"type":"Point"}
}