{
  "type": "Feature",
  "properties": {
    "iso:country":"US",
    "sg:address":"710 Moore St",
    "sg:city":"Oxford",
    "sg:classifiers":[
        {
            "category":"Utilities",
            "subcategory":"Recycling",
            "type":"Services"
        }
    ],
    "sg:phone":"+1 678 625 4944",
    "sg:postcode":"30054",
    "sg:province":"GA",
    "wof:name":"Aqua-Terra Recycling & Trtmnt",
    "wof:placetype":"venue"
},
  "geometry": {"coordinates":[-83.88392399999999,33.618229],"type":"Point"}
}