{
  "type": "Feature",
  "properties": {
    "iso:country":"US",
    "sg:address":"1816 Shade Murphy Rd",
    "sg:city":"Moultrie",
    "sg:classifiers":[
        {
            "category":"Building & Trades",
            "subcategory":"Landfill",
            "type":"Services"
        }
    ],
    "sg:phone":"+1 229 616 7470",
    "sg:postcode":"31768",
    "sg:province":"GA",
    "wof:name":"Colquitt County",
    "wof:placetype":"venue"
},
  "geometry": {"coordinates":[-83.843147,31.09471],"type":"Point"}
}