{
  "type": "Feature",
  "properties": {
    "iso:country":"US",
    "sg:address":"1903 Drew Dr NW",
    "sg:city":"Atlanta",
    "sg:classifiers":[
        {
            "category":"Real Estate",
            "subcategory":"Real Estate Services",
            "type":"Services"
        }
    ],
    "sg:phone":"+1 404 794 6624",
    "sg:postcode":"30318",
    "sg:province":"GA",
    "sg:tags":[
        "vacancy",
        "apartment",
        "rental",
        "finder",
        "listing"
    ],
    "wof:name":"Columbia Crest",
    "wof:placetype":"venue"
},
  "geometry": {"coordinates":[-84.45026,33.792808],"type":"Point"}
}