{
  "type": "Feature",
  "properties": {
    "iso:country":"US",
    "sg:address":"3886 Maggie Ct SE",
    "sg:city":"Conyers",
    "sg:classifiers":[
        {
            "category":"Building & Trades",
            "subcategory":"Construction",
            "type":"Services"
        }
    ],
    "sg:phone":"+1 770 761 1963",
    "sg:postcode":"30013",
    "sg:province":"GA",
    "sg:tags":[
        "contractor"
    ],
    "wof:name":"A/A Vinyl Siding Inc",
    "wof:placetype":"venue"
},
  "geometry": {"coordinates":[-84.00724099999999,33.58557],"type":"Point"}
}