{
  "type": "Feature",
  "properties": {
    "iso:country":"US",
    "sg:address":"1015 Bill Wright Rd",
    "sg:city":"Jefferson",
    "sg:classifiers":[
        {
            "category":"Professional",
            "subcategory":"Business Services",
            "type":"Services"
        }
    ],
    "sg:phone":"+1 706 693 2457",
    "sg:postcode":"30549",
    "sg:province":"GA",
    "wof:name":"Huffman Terena",
    "wof:placetype":"venue"
},
  "geometry": {"coordinates":[-83.63275899999999,34.172146],"type":"Point"}
}