{
  "type": "Feature",
  "properties": {
    "addr:full":"3400 Quinn Ridge Dr Snellville GA 30039",
    "addr:housenumber":"3400",
    "addr:postcode":"30039",
    "addr:street":"Quinn Ridge Dr",
    "iso:country":"US",
    "sg:address":"3400 Quinn Ridge Dr",
    "sg:city":"Snellville",
    "sg:classifiers":[
        {
            "category":"Building & Trades",
            "subcategory":"Pest Control",
            "type":"Services"
        }
    ],
    "sg:phone":"+1 404 419 0475",
    "sg:postcode":"30039",
    "sg:province":"GA",
    "wof:name":"Towne Trapper",
    "wof:placetype":"venue"
},
  "geometry": {"coordinates":[-84.036382,33.820489],"type":"Point"}
}