{
  "type": "Feature",
  "properties": {
    "iso:country":"US",
    "sg:address":"3298 Stone Mountain Hwy",
    "sg:city":"Snellville",
    "sg:classifiers":[
        {
            "category":"Banks & Credit Unions",
            "subcategory":"Bank",
            "type":"Services"
        }
    ],
    "sg:phone":"+1 770 978 7825",
    "sg:postcode":"30039",
    "sg:province":"GA",
    "sg:tags":[
        "cashing",
        "check"
    ],
    "wof:name":"Check Changers",
    "wof:placetype":"venue"
},
  "geometry": {"coordinates":[-84.048513,33.847638],"type":"Point"}
}