{
  "type": "Feature",
  "properties": {
    "iso:country":"US",
    "sg:address":"2323 Main St Ste 1",
    "sg:city":"Tucker",
    "sg:classifiers":[
        {
            "category":"Personal",
            "subcategory":"Beauty Salon",
            "type":"Services"
        }
    ],
    "sg:phone":"+1 770 934 4415",
    "sg:postcode":"30084",
    "sg:province":"GA",
    "sg:tags":[
        "hair"
    ],
    "wof:name":"Stephen Harvey Salon",
    "wof:placetype":"venue"
},
  "geometry": {"coordinates":[-84.214235,33.852854],"type":"Point"}
}