{
  "type": "Feature",
  "properties": {
    "iso:country":"US",
    "sg:address":"1321 Sweetwoods Dr",
    "sg:city":"Lawrenceville",
    "sg:classifiers":[
        {
            "category":"Professional",
            "type":"Services"
        }
    ],
    "sg:phone":"+1 770 381 6816",
    "sg:postcode":"30044",
    "sg:province":"GA",
    "wof:name":"Earn Ernest U Jr Et Al",
    "wof:placetype":"venue"
},
  "geometry": {"coordinates":[-84.09457,33.948428],"type":"Point"}
}