{
  "type": "Feature",
  "properties": {
    "iso:country":"US",
    "sg:address":"3 George Rd SW",
    "sg:city":"Cave Spring",
    "sg:classifiers":[
        {
            "category":"Local Transit",
            "type":"Transportation"
        }
    ],
    "sg:phone":"+1 706 777 1616",
    "sg:postcode":"30124",
    "sg:province":"GA",
    "sg:tags":[
        "passenger"
    ],
    "wof:name":"Redmond Regional Med Centre",
    "wof:placetype":"venue"
},
  "geometry": {"coordinates":[-85.417531,34.173307],"type":"Point"}
}