{
  "type": "Feature",
  "properties": {
    "addr:full":"1631 Westhaven Dr SW Atlanta GA 30311",
    "addr:housenumber":"1631",
    "addr:postcode":"30311",
    "addr:street":"Westhaven Dr Sw",
    "iso:country":"US",
    "sg:address":"1631 Westhaven Dr SW",
    "sg:city":"Atlanta",
    "sg:classifiers":[
        {
            "category":"Organizations",
            "subcategory":"Religious Organization",
            "type":"Services"
        }
    ],
    "sg:phone":"+1 404 752 7665",
    "sg:postcode":"30311",
    "sg:province":"GA",
    "wof:name":"Second Mt Olive Baptist Church",
    "wof:placetype":"venue"
},
  "geometry": {"coordinates":[-84.43835300000001,33.732327],"type":"Point"}
}