{
  "type": "Feature",
  "properties": {
    "addr:full":"100 Peachtree St NW Atlanta GA 30303",
    "addr:housenumber":"100",
    "addr:postcode":"30303",
    "addr:street":"Peachtree St Nw",
    "iso:country":"US",
    "sg:address":"100 Peachtree St NW",
    "sg:city":"Atlanta",
    "sg:classifiers":[
        {
            "category":"Communications",
            "subcategory":"News Services",
            "type":"Services"
        }
    ],
    "sg:phone":"+1 404 814 1407",
    "sg:postcode":"30303",
    "sg:province":"GA",
    "sg:tags":[
        "stand"
    ],
    "wof:name":"Y S Newsstand Corp",
    "wof:placetype":"venue"
},
  "geometry": {"coordinates":[-84.392275,33.751881],"type":"Point"}
}