{
  "type": "Feature",
  "properties": {
    "addr:full":"6363 Jonesboro Rd Morrow GA 30260",
    "addr:housenumber":"6363",
    "addr:postcode":"30260",
    "addr:street":"Jonesboro Rd",
    "iso:country":"US",
    "sg:address":"6363 Jonesboro Rd",
    "sg:city":"Morrow",
    "sg:classifiers":[
        {
            "category":"Recreation",
            "type":"Entertainment"
        }
    ],
    "sg:phone":"+1 770 968 5166",
    "sg:postcode":"30260",
    "sg:province":"GA",
    "wof:name":"Bida Que Huong",
    "wof:placetype":"venue"
},
  "geometry": {"coordinates":[-84.338545,33.587531],"type":"Point"}
}