{
  "type": "Feature",
  "properties": {
    "addr:full":"4241 Wayside Ct SW Lilburn GA 30047",
    "addr:housenumber":"4241",
    "addr:postcode":"30047",
    "addr:street":"Wayside Ct Sw",
    "iso:country":"US",
    "sg:address":"4241 Wayside Ct SW",
    "sg:city":"Lilburn",
    "sg:classifiers":[
        {
            "category":"Building & Trades",
            "subcategory":"Construction",
            "type":"Services"
        }
    ],
    "sg:phone":"+1 770 717 1963",
    "sg:postcode":"30047",
    "sg:province":"GA",
    "sg:tags":[
        "general",
        "painter",
        "contractor"
    ],
    "wof:name":"Classic Paint and Construction",
    "wof:placetype":"venue"
},
  "geometry": {"coordinates":[-84.11394300000001,33.88878],"type":"Point"}
}