{
  "type": "Feature",
  "properties": {
    "iso:country":"US",
    "sg:address":"170 Bankston Rd",
    "sg:city":"Marietta",
    "sg:classifiers":[
        {
            "category":"Building & Trades",
            "subcategory":"Construction",
            "type":"Services"
        }
    ],
    "sg:phone":"+1 770 499 5017",
    "sg:postcode":"30062",
    "sg:province":"GA",
    "sg:tags":[
        "hanging",
        "contractor"
    ],
    "wof:name":"All Around Atlanta Paint",
    "wof:placetype":"venue"
},
  "geometry": {"coordinates":[-84.522493,33.966266],"type":"Point"}
}