{
  "type": "Feature",
  "properties": {
    "iso:country":"US",
    "sg:address":"2493 Mcafee Rd",
    "sg:city":"Decatur",
    "sg:classifiers":[
        {
            "category":"Building & Trades",
            "subcategory":"Construction",
            "type":"Services"
        }
    ],
    "sg:phone":"+1 404 534 0997",
    "sg:postcode":"30032",
    "sg:province":"GA",
    "sg:tags":[
        "equipment",
        "supply",
        "drywall",
        "contractor"
    ],
    "wof:name":"Ap Drywall",
    "wof:placetype":"venue"
},
  "geometry": {"coordinates":[-84.288011,33.731902],"type":"Point"}
}