{
  "type": "Feature",
  "properties": {
    "iso:country":"US",
    "sg:address":"589 Mangham Rd",
    "sg:city":"Griffin",
    "sg:classifiers":[
        {
            "category":"Professional",
            "subcategory":"Accounting & Tax Preparation",
            "type":"Services"
        }
    ],
    "sg:phone":"+1 770 233 9014",
    "sg:postcode":"30224",
    "sg:province":"GA",
    "sg:tags":[
        "bookkeeping",
        "general"
    ],
    "wof:name":"Financial Integrity Group",
    "wof:placetype":"venue"
},
  "geometry": {"coordinates":[-84.16416,33.23285],"type":"Point"}
}