{
  "type": "Feature",
  "properties": {
    "addr:full":"3900 Savannah Hwy Jesup GA 31545",
    "addr:housenumber":"3900",
    "addr:postcode":"31545",
    "addr:street":"Savannah Hwy",
    "iso:country":"US",
    "sg:address":"3900 Savannah Hwy",
    "sg:city":"Jesup",
    "sg:classifiers":[
        {
            "category":"Wholesale",
            "subcategory":"Machinery & Supplies",
            "type":"Manufacturing & Wholesale Goods"
        }
    ],
    "sg:phone":"+1 912 427 7062",
    "sg:postcode":"31545",
    "sg:province":"GA",
    "sg:tags":[
        "equipment",
        "log",
        "splitting"
    ],
    "sg:website":"www.altamahaequipment.com",
    "wof:name":"Altamaha Equipment Co",
    "wof:placetype":"venue"
},
  "geometry": {"coordinates":[-81.855172,31.648414],"type":"Point"}
}