{
  "type": "Feature",
  "properties": {
    "addr:full":"1409 Church St Exd Marietta GA 30060",
    "addr:housenumber":"1409",
    "addr:postcode":"30060",
    "addr:street":"Church St Exd",
    "iso:country":"US",
    "sg:address":"1409 Church St Exd",
    "sg:city":"Marietta",
    "sg:classifiers":[
        {
            "category":"Food & Beverages",
            "subcategory":"Specialty",
            "type":"Retail Goods"
        }
    ],
    "sg:phone":"+1 770 419 3654",
    "sg:postcode":"30060",
    "sg:province":"GA",
    "sg:tags":[
        "herb"
    ],
    "wof:name":"Wellness Express Depot",
    "wof:placetype":"venue"
},
  "geometry": {"coordinates":[-84.553009,33.974792],"type":"Point"}
}