{
  "type": "Feature",
  "properties": {
    "iso:country":"US",
    "sg:address":"225 Pine Ave",
    "sg:city":"Albany",
    "sg:classifiers":[
        {
            "category":"Government",
            "subcategory":"Office",
            "type":"Public Place"
        }
    ],
    "sg:phone":"+1 229 000 1111",
    "sg:postcode":"31701",
    "sg:province":"GA",
    "sg:tags":[
        "village"
    ],
    "wof:name":"Central Communications Div",
    "wof:placetype":"venue"
},
  "geometry": {"coordinates":[-84.15210999999999,31.578495],"type":"Point"}
}