{
  "type": "Feature",
  "properties": {
    "iso:country":"US",
    "sg:address":"420 County Line Rd",
    "sg:city":"Griffin",
    "sg:classifiers":[
        {
            "category":"Real Estate",
            "subcategory":"Real Estate Operator",
            "type":"Services"
        }
    ],
    "sg:phone":"+1 770 227 1967",
    "sg:postcode":"30224",
    "sg:province":"GA",
    "sg:tags":[
        "building",
        "nonresidential"
    ],
    "wof:name":"Petro Properties & Development",
    "wof:placetype":"venue"
},
  "geometry": {"coordinates":[-84.265541,33.189269],"type":"Point"}
}