{
  "type": "Feature",
  "properties": {
    "iso:country":"US",
    "sg:address":"730 State Rte 247",
    "sg:city":"Bonaire",
    "sg:classifiers":[
        {
            "category":"Building & Trades",
            "subcategory":"Construction",
            "type":"Services"
        }
    ],
    "sg:phone":"+1 478 929 8338",
    "sg:postcode":"31005",
    "sg:province":"GA",
    "sg:tags":[
        "excavating",
        "contractor"
    ],
    "wof:name":"Ace Excavating & Hauling Inc",
    "wof:placetype":"venue"
},
  "geometry": {"coordinates":[-83.596125,32.542442],"type":"Point"}
}