{
  "type": "Feature",
  "properties": {
    "addr:full":"610 McGarrah St Americus GA 31719",
    "addr:housenumber":"610",
    "addr:postcode":"31719",
    "addr:street":"Mcgarrah St",
    "iso:country":"US",
    "sg:address":"610 McGarrah St",
    "sg:city":"Americus",
    "sg:classifiers":[
        {
            "category":"Taxi",
            "type":"Transportation"
        }
    ],
    "sg:phone":"+1 229 928 8791",
    "sg:postcode":"31719",
    "sg:province":"GA",
    "sg:tags":[
        "taxicab"
    ],
    "wof:name":"T & M Taxi Service",
    "wof:placetype":"venue"
},
  "geometry": {"coordinates":[-84.23676,32.078644],"type":"Point"}
}