{
  "type": "Feature",
  "properties": {
    "iso:country":"US",
    "sg:address":"1031 Park Hill Dr",
    "sg:city":"Gainesville",
    "sg:classifiers":[
        {
            "category":"Building & Trades",
            "subcategory":"Construction",
            "type":"Services"
        }
    ],
    "sg:phone":"+1 770 536 3779",
    "sg:postcode":"30501",
    "sg:province":"GA",
    "sg:tags":[
        "grading",
        "trucking"
    ],
    "wof:name":"Pooles Grading & Trucking",
    "wof:placetype":"venue"
},
  "geometry": {"coordinates":[-83.82730599999999,34.313964],"type":"Point"}
}