{
  "type": "Feature",
  "properties": {
    "addr:full":"1 Gamble Rd Savannah GA 31405",
    "addr:housenumber":"1",
    "addr:postcode":"31405",
    "addr:street":"Gamble Rd",
    "iso:country":"US",
    "sg:address":"1 Gamble Rd",
    "sg:city":"Savannah",
    "sg:classifiers":[
        {
            "category":"Organizations",
            "subcategory":"Religious Organization",
            "type":"Services"
        }
    ],
    "sg:phone":"+1 912 920 3051",
    "sg:postcode":"31405",
    "sg:province":"GA",
    "wof:name":"Hispanic Baptist Mission",
    "wof:placetype":"venue"
},
  "geometry": {"coordinates":[-81.148916,32.041537],"type":"Point"}
}