{
  "type": "Feature",
  "properties": {
    "iso:country":"US",
    "sg:address":"2254 Carver Dr NW",
    "sg:city":"Atlanta",
    "sg:classifiers":[
        {
            "category":"Place Of Worship",
            "subcategory":"Church",
            "type":"Public Place"
        },
        {
            "category":"Place Of Worship",
            "type":"Public Place"
        },
        {
            "category":"Organizations",
            "subcategory":"Religious Organization",
            "type":"Services"
        }
    ],
    "sg:phone":"+1 404 228 6104",
    "sg:postcode":"30314",
    "sg:province":"GA",
    "sg:tags":[
        "god",
        "churches-church",
        "churches-pentecostal"
    ],
    "wof:name":"Up and Go Overcoming Church of GOD",
    "wof:placetype":"venue"
},
  "geometry": {"coordinates":[-84.46136199999999,33.759939],"type":"Point"}
}