{
  "type": "Feature",
  "properties": {
    "iso:country":"US",
    "sg:address":"130 S Hutchinson Ave",
    "sg:city":"Adel",
    "sg:classifiers":[
        {
            "category":"Wholesale",
            "subcategory":"Farm Supplies",
            "type":"Manufacturing & Wholesale Goods"
        }
    ],
    "sg:phone":"+1 229 896 3902",
    "sg:postcode":"31620",
    "sg:province":"GA",
    "sg:tags":[
        "feed"
    ],
    "wof:name":"Farmers Feed & Supply Store",
    "wof:placetype":"venue"
},
  "geometry": {"coordinates":[-83.423312,31.13662],"type":"Point"}
}