{
  "type": "Feature",
  "properties": {
    "addr:full":"205 Colony Run Alpharetta GA 30022",
    "addr:housenumber":"205",
    "addr:postcode":"30022",
    "addr:street":"Colony Run",
    "iso:country":"US",
    "sg:address":"205 Colony Run",
    "sg:city":"Alpharetta",
    "sg:classifiers":[
        {
            "category":"Building & Trades",
            "subcategory":"Landscaping Services",
            "type":"Services"
        }
    ],
    "sg:phone":"+1 770 667 6484",
    "sg:postcode":"30022",
    "sg:province":"GA",
    "sg:tags":[
        "landscape",
        "contractor"
    ],
    "wof:name":"Create-A-Scapes",
    "wof:placetype":"venue"
},
  "geometry": {"coordinates":[-84.243442,34.036301],"type":"Point"}
}