{
  "type": "Feature",
  "properties": {
    "addr:full":"525 Chamblin Rd Grovetown GA 30813",
    "addr:housenumber":"525",
    "addr:postcode":"30813",
    "addr:street":"Chamblin Rd",
    "iso:country":"US",
    "sg:address":"525 Chamblin Rd",
    "sg:city":"Grovetown",
    "sg:classifiers":[
        {
            "category":"Professional",
            "subcategory":"Management & Consulting",
            "type":"Services"
        }
    ],
    "sg:phone":"+1 706 860 5821",
    "sg:postcode":"30813",
    "sg:province":"GA",
    "wof:name":"Yonder Management Services",
    "wof:placetype":"venue"
},
  "geometry": {"coordinates":[-82.21354599999999,33.481276],"type":"Point"}
}