{
  "type": "Feature",
  "properties": {
    "addr:full":"287 Pharr Rd NE Atlanta GA 30305",
    "addr:housenumber":"287",
    "addr:postcode":"30305",
    "addr:street":"Pharr Rd Ne",
    "iso:country":"US",
    "sg:address":"287 Pharr Rd NE",
    "sg:city":"Atlanta",
    "sg:classifiers":[
        {
            "category":"Building & Trades",
            "subcategory":"Locksmith",
            "type":"Services"
        }
    ],
    "sg:phone":"+1 404 486 2986",
    "sg:postcode":"30305",
    "sg:province":"GA",
    "sg:tags":[
        "key"
    ],
    "wof:name":"A Cameron Locksmith",
    "wof:placetype":"venue"
},
  "geometry": {"coordinates":[-84.378156,33.83689],"type":"Point"}
}