{
  "type": "Feature",
  "properties": {
    "addr:full":"2540 Cumberland Blvd SE Smyrna GA 30080",
    "addr:housenumber":"2540",
    "addr:postcode":"30080",
    "addr:street":"Cumberland Blvd Se",
    "iso:country":"US",
    "sg:address":"2540 Cumberland Blvd SE",
    "sg:city":"Smyrna",
    "sg:classifiers":[
        {
            "category":"Shopping",
            "subcategory":"Crafts & Fabrics",
            "type":"Retail Goods"
        }
    ],
    "sg:phone":"+1 770 433 1700",
    "sg:postcode":"30080",
    "sg:province":"GA",
    "sg:tags":[
        "art",
        "supply"
    ],
    "sg:website":"www.michaels.com/",
    "wof:name":"Michaels",
    "wof:placetype":"venue"
},
  "geometry": {"coordinates":[-84.49960299999999,33.875],"type":"Point"}
}