{
  "type": "Feature",
  "properties": {
    "addr:full":"6056 Ga Hwy111 Calvary GA 31768",
    "addr:postcode":"6056;31768",
    "addr:street":"Ga Hwy111",
    "iso:country":"US",
    "sg:address":"6056 Ga Hwy111",
    "sg:city":"Calvary",
    "sg:classifiers":[
        {
            "category":"Freight",
            "type":"Transportation"
        }
    ],
    "sg:phone":"+1 229 872 3439",
    "sg:postcode":"31768",
    "sg:province":"GA",
    "sg:tags":[
        "commercial",
        "storage"
    ],
    "wof:name":"Southern Storage Solutions Inc",
    "wof:placetype":"venue"
},
  "geometry": {"coordinates":[-84.228296,31.523802],"type":"Point"}
}