{
  "type": "Feature",
  "properties": {
    "iso:country":"US",
    "sg:address":"3305 Victory Dr",
    "sg:city":"Columbus",
    "sg:classifiers":[
        {
            "category":"Shopping",
            "subcategory":"Clothing, Apparel, & Fashions",
            "type":"Retail Goods"
        }
    ],
    "sg:phone":"+1 706 689 7143",
    "sg:postcode":"31903",
    "sg:province":"GA",
    "sg:tags":[
        "wear"
    ],
    "wof:name":"Miasale Accessories",
    "wof:placetype":"venue"
},
  "geometry": {"coordinates":[-84.95236199999999,32.430255],"type":"Point"}
}