{
  "type": "Feature",
  "properties": {
    "addr:full":"133 Park Ave Wadley GA 30458",
    "addr:housenumber":"133",
    "addr:postcode":"30458",
    "addr:street":"Park Ave",
    "iso:country":"US",
    "sg:address":"133 Park Ave",
    "sg:city":"Wadley",
    "sg:classifiers":[
        {
            "category":"Recreation",
            "type":"Entertainment"
        }
    ],
    "sg:phone":"+1 478 252 1512",
    "sg:postcode":"30458",
    "sg:province":"GA",
    "sg:tags":[
        "parks"
    ],
    "wof:name":"Wadley Recreation Dept",
    "wof:placetype":"venue"
},
  "geometry": {"coordinates":[-81.774827,32.443268],"type":"Point"}
}