{
  "type": "Feature",
  "properties": {
    "iso:country":"US",
    "sg:address":"3687 Buford Dr",
    "sg:city":"Buford",
    "sg:classifiers":[
        {
            "category":"Food & Beverages",
            "subcategory":"Groceries & Convenience Stores",
            "type":"Retail Goods"
        }
    ],
    "sg:phone":"+1 770 945 8074",
    "sg:postcode":"30519",
    "sg:province":"GA",
    "wof:name":"Golden Pantry Food Store",
    "wof:placetype":"venue"
},
  "geometry": {"coordinates":[-83.987099,34.0816],"type":"Point"}
}