{
  "type": "Feature",
  "properties": {
    "iso:country":"US",
    "sg:address":"4963 Day Lily Way",
    "sg:city":"Acworth",
    "sg:classifiers":[
        {
            "category":"Real Estate",
            "subcategory":"Developer",
            "type":"Services"
        }
    ],
    "sg:phone":"+1 678 485 8068",
    "sg:postcode":"30102",
    "sg:province":"GA",
    "wof:name":"Old South Realty Dev Inc",
    "wof:placetype":"venue"
},
  "geometry": {"coordinates":[-84.575644,34.070282],"type":"Point"}
}