{
  "type": "Feature",
  "properties": {
    "addr:full":"2692 Inverloch Cir Duluth GA 30096",
    "addr:housenumber":"2692",
    "addr:postcode":"30096",
    "addr:street":"Inverloch Cir",
    "iso:country":"US",
    "sg:address":"2692 Inverloch Cir",
    "sg:city":"Duluth",
    "sg:classifiers":[
        {
            "category":"Building & Trades",
            "subcategory":"Equipment Rental",
            "type":"Services"
        }
    ],
    "sg:phone":"+1 770 623 5997",
    "sg:postcode":"30096",
    "sg:province":"GA",
    "sg:tags":[
        "aircraft",
        "leasing",
        "charter"
    ],
    "wof:name":"Ace Air Charter",
    "wof:placetype":"venue"
},
  "geometry": {"coordinates":[-84.16195500000001,33.965753],"type":"Point"}
}