{
  "type": "Feature",
  "properties": {
    "addr:full":"1161 Price Mill Rd Madison GA 30650",
    "addr:housenumber":"1161",
    "addr:postcode":"30650",
    "addr:street":"Price Mill Rd",
    "iso:country":"US",
    "sg:address":"1161 Price Mill Rd",
    "sg:city":"Madison",
    "sg:classifiers":[
        {
            "category":"Building & Trades",
            "subcategory":"Construction",
            "type":"Services"
        }
    ],
    "sg:phone":"+1 706 342 0993",
    "sg:postcode":"30650",
    "sg:province":"GA",
    "sg:tags":[
        "contractor"
    ],
    "wof:name":"Arctic Seal Insulation",
    "wof:placetype":"venue"
},
  "geometry": {"coordinates":[-83.495817,33.717315],"type":"Point"}
}