{
  "type": "Feature",
  "properties": {
    "iso:country":"US",
    "sg:address":"5468 Dorsett Shoals Rd",
    "sg:city":"Douglasville",
    "sg:classifiers":[
        {
            "category":"Professional",
            "subcategory":"Accounting & Tax Preparation",
            "type":"Services"
        }
    ],
    "sg:phone":"+1 770 947 4055",
    "sg:postcode":"30135",
    "sg:province":"GA",
    "sg:tags":[
        "accountant"
    ],
    "wof:name":"John Frazier CPA",
    "wof:placetype":"venue"
},
  "geometry": {"coordinates":[-84.74930999999999,33.672009],"type":"Point"}
}