{
  "type": "Feature",
  "properties": {
    "addr:full":"128 Schooner Dr Savannah GA 31410",
    "addr:housenumber":"128",
    "addr:postcode":"31410",
    "addr:street":"Schooner Dr",
    "iso:country":"US",
    "sg:address":"128 Schooner Dr",
    "sg:city":"Savannah",
    "sg:classifiers":[
        {
            "category":"Real Estate",
            "subcategory":"Real Estate Agent",
            "type":"Services"
        }
    ],
    "sg:phone":"+1 912 897 1633",
    "sg:postcode":"31410",
    "sg:province":"GA",
    "wof:name":"Wonderland Development Inc",
    "wof:placetype":"venue"
},
  "geometry": {"coordinates":[-81.010233,32.028397],"type":"Point"}
}