{
  "type": "Feature",
  "properties": {
    "iso:country":"US",
    "sg:address":"606 Kennedy St",
    "sg:city":"Glennville",
    "sg:classifiers":[
        {
            "category":"Farming",
            "subcategory":"Poultry Farm",
            "type":"Manufacturing & Wholesale Goods"
        }
    ],
    "sg:phone":"+1 912 654 3701",
    "sg:postcode":"30427",
    "sg:province":"GA",
    "sg:tags":[
        "chicken"
    ],
    "wof:name":"Jessie Kennedy",
    "wof:placetype":"venue"
},
  "geometry": {"coordinates":[-81.933925,31.930186],"type":"Point"}
}