{
  "type": "Feature",
  "properties": {
    "addr:full":"1575 Northside Dr NW Atlanta GA 30318",
    "addr:housenumber":"1575",
    "addr:postcode":"30318",
    "addr:street":"Northside Dr Nw",
    "iso:country":"US",
    "sg:address":"1575 Northside Dr NW",
    "sg:city":"Atlanta",
    "sg:classifiers":[
        {
            "category":"Professional",
            "subcategory":"Computer Services",
            "type":"Services"
        },
        {
            "category":"Wholesale",
            "subcategory":"Computers",
            "type":"Manufacturing & Wholesale Goods"
        }
    ],
    "sg:phone":"+1 404 351 3992",
    "sg:postcode":"30318",
    "sg:province":"GA",
    "sg:tags":[
        "equipment",
        "cd-rom",
        "software"
    ],
    "wof:name":"Nuesoft Technology",
    "wof:placetype":"venue"
},
  "geometry": {"coordinates":[-84.407822,33.798599],"type":"Point"}
}