{
  "type": "Feature",
  "properties": {
    "addr:full":"1210 Clairemont Rd Decatur GA 30030",
    "addr:housenumber":"1210",
    "addr:postcode":"30030",
    "addr:street":"Clairemont Rd",
    "iso:country":"US",
    "sg:address":"1210 Clairemont Rd",
    "sg:city":"Decatur",
    "sg:classifiers":[
        {
            "category":"Retail",
            "subcategory":"Auto Rental",
            "type":"Services"
        }
    ],
    "sg:phone":"+1 404 636 9365",
    "sg:postcode":"30030",
    "sg:province":"GA",
    "sg:tags":[
        "renting",
        "truck",
        "leasing"
    ],
    "wof:name":"Budget Truck Rental",
    "wof:placetype":"venue"
},
  "geometry": {"coordinates":[-84.30653599999999,33.790086],"type":"Point"}
}