{
  "type": "Feature",
  "properties": {
    "addr:full":"4151 Ashford Dunwoody Rd NE Atlanta GA 30319",
    "addr:housenumber":"4151",
    "addr:postcode":"30319",
    "addr:street":"Ashford Dunwoody Rd Ne",
    "iso:country":"US",
    "sg:address":"4151 Ashford Dunwoody Rd NE",
    "sg:city":"Atlanta",
    "sg:classifiers":[
        {
            "category":"Utilities",
            "subcategory":"Mobile Phone",
            "type":"Services"
        }
    ],
    "sg:phone":"+1 404 255 9999",
    "sg:postcode":"30319",
    "sg:province":"GA",
    "sg:tags":[
        "card",
        "calling"
    ],
    "wof:name":"North American Telephone Network",
    "wof:placetype":"venue"
},
  "geometry": {"coordinates":[-84.336056,33.914146],"type":"Point"}
}