{
  "type": "Feature",
  "properties": {
    "iso:country":"US",
    "sg:address":"2993 Bankhead Hwy",
    "sg:city":"Austell",
    "sg:classifiers":[
        {
            "category":"Real Estate",
            "subcategory":"Real Estate Services",
            "type":"Services"
        }
    ],
    "sg:phone":"+1 770 941 4390",
    "sg:postcode":"30116",
    "sg:province":"GA",
    "sg:tags":[
        "company",
        "title"
    ],
    "wof:name":"Title Max Of Austell",
    "wof:placetype":"venue"
},
  "geometry": {"coordinates":[-84.98377000000001,33.614168],"type":"Point"}
}