{
  "type": "Feature",
  "properties": {
    "iso:country":"US",
    "sg:address":"2374 Cove Rd",
    "sg:city":"Lithonia",
    "sg:classifiers":[
        {
            "category":"Professional",
            "subcategory":"Management & Consulting",
            "type":"Services"
        }
    ],
    "sg:phone":"+1 770 498 0419",
    "sg:postcode":"30058",
    "sg:province":"GA",
    "sg:tags":[
        "consultant"
    ],
    "sg:website":"www.techbuilders.net",
    "wof:name":"Truth Consulting",
    "wof:placetype":"venue"
},
  "geometry": {"coordinates":[-84.13527499999999,33.717778],"type":"Point"}
}