{
  "type": "Feature",
  "properties": {
    "iso:country":"US",
    "sg:address":"120 Twin Branch Rd",
    "sg:city":"Demorest",
    "sg:classifiers":[
        {
            "category":"Building & Trades",
            "subcategory":"Cleaning & Sanitation",
            "type":"Services"
        }
    ],
    "sg:phone":"+1 706 776 9186",
    "sg:postcode":"30553",
    "sg:province":"GA",
    "sg:tags":[
        "janitor"
    ],
    "wof:name":"HJS Cleaning Svc",
    "wof:placetype":"venue"
},
  "geometry": {"coordinates":[-83.09902599999999,34.406916],"type":"Point"}
}