{
  "type": "Feature",
  "properties": {
    "addr:full":"1811 N Columbia St Milledgeville GA 31061",
    "addr:housenumber":"1811",
    "addr:postcode":"31061",
    "addr:street":"N Columbia St",
    "iso:country":"US",
    "sg:address":"1811 N Columbia St",
    "sg:city":"Milledgeville",
    "sg:classifiers":[
        {
            "category":"Restaurant",
            "type":"Food & Drink"
        }
    ],
    "sg:phone":"+1 478 451 2888",
    "sg:postcode":"31061",
    "sg:province":"GA",
    "sg:tags":[
        "eating"
    ],
    "wof:name":"China Buffet",
    "wof:placetype":"venue"
},
  "geometry": {"coordinates":[-83.252593,33.106681],"type":"Point"}
}