{
  "type": "Feature",
  "properties": {
    "iso:country":"US",
    "sg:address":"68 Bullsboro Dr",
    "sg:city":"Newnan",
    "sg:classifiers":[
        {
            "category":"Wholesale",
            "subcategory":"Medical Equipment & Supplies",
            "type":"Manufacturing & Wholesale Goods"
        }
    ],
    "sg:phone":"+1 770 251 6550",
    "sg:postcode":"30263",
    "sg:province":"GA",
    "sg:tags":[
        "hospital"
    ],
    "sg:website":"www.apriahealthcare.com",
    "wof:name":"Apria Healthcare",
    "wof:placetype":"venue"
},
  "geometry": {"coordinates":[-84.78589599999999,33.383769],"type":"Point"}
}