{
  "type": "Feature",
  "properties": {
    "iso:country":"US",
    "sg:address":"2930 Fitzgerald Trce",
    "sg:city":"Duluth",
    "sg:classifiers":[
        {
            "category":"Professional",
            "type":"Services"
        }
    ],
    "sg:phone":"+1 770 232 0086",
    "sg:postcode":"30097",
    "sg:province":"GA",
    "sg:tags":[
        "processing",
        "data"
    ],
    "wof:name":"Frugally Yours",
    "wof:placetype":"venue"
},
  "geometry": {"coordinates":[-84.113212,33.990045],"type":"Point"}
}