{
  "type": "Feature",
  "properties": {
    "iso:country":"US",
    "sg:address":"11 Clear Creek Rd",
    "sg:city":"Ellijay",
    "sg:classifiers":[
        {
            "category":"Insurance",
            "subcategory":"Insurance Agent",
            "type":"Services"
        }
    ],
    "sg:phone":"+1 706 276 3946",
    "sg:postcode":"30536",
    "sg:province":"GA",
    "wof:name":"Columbus Life Insurance",
    "wof:placetype":"venue"
},
  "geometry": {"coordinates":[-84.46459400000001,34.624175],"type":"Point"}
}