{
  "type": "Feature",
  "properties": {
    "addr:full":"1201 Appian Way Lawrenceville GA 30045",
    "addr:housenumber":"1201",
    "addr:postcode":"30045",
    "addr:street":"Appian Way",
    "iso:country":"US",
    "sg:address":"1201 Appian Way",
    "sg:city":"Lawrenceville",
    "sg:classifiers":[
        {
            "category":"Building & Trades",
            "subcategory":"Construction",
            "type":"Services"
        }
    ],
    "sg:phone":"+1 770 995 1733",
    "sg:postcode":"30045",
    "sg:province":"GA",
    "sg:tags":[
        "house"
    ],
    "wof:name":"Upper Roo Construction Co",
    "wof:placetype":"venue"
},
  "geometry": {"coordinates":[-84.025823,33.944939],"type":"Point"}
}