{
  "type": "Feature",
  "properties": {
    "iso:country":"US",
    "sg:address":"29 Austin Dr",
    "sg:city":"Savannah",
    "sg:classifiers":[
        {
            "category":"Professional",
            "subcategory":"Management & Consulting",
            "type":"Services"
        }
    ],
    "sg:phone":"+1 912 920 8668",
    "sg:postcode":"31419",
    "sg:province":"GA",
    "sg:tags":[
        "party",
        "planning"
    ],
    "wof:name":"Clowning 4 The Kids",
    "wof:placetype":"venue"
},
  "geometry": {"coordinates":[-81.13566899999999,31.975614],"type":"Point"}
}