{
  "type": "Feature",
  "properties": {
    "addr:full":"9384 Windward Ct Jonesboro GA 30238",
    "addr:housenumber":"9384",
    "addr:postcode":"30238",
    "addr:street":"Windward Ct",
    "iso:country":"US",
    "sg:address":"9384 Windward Ct",
    "sg:city":"Jonesboro",
    "sg:classifiers":[
        {
            "category":"Building & Trades",
            "subcategory":"Construction",
            "type":"Services"
        }
    ],
    "sg:phone":"+1 770 473 7689",
    "sg:postcode":"30238",
    "sg:province":"GA",
    "sg:tags":[
        "house"
    ],
    "wof:name":"Four Star Builders Inc",
    "wof:placetype":"venue"
},
  "geometry": {"coordinates":[-84.359486,33.50079],"type":"Point"}
}