{
  "type": "Feature",
  "properties": {
    "iso:country":"US",
    "sg:address":"455 Fulton St SW",
    "sg:city":"Atlanta",
    "sg:classifiers":[
        {
            "category":"Real Estate",
            "subcategory":"Real Estate Operator",
            "type":"Services"
        }
    ],
    "sg:phone":"+1 404 577 8923",
    "sg:postcode":"30312",
    "sg:province":"GA",
    "sg:tags":[
        "apartment"
    ],
    "wof:name":"Mechanicsville Apts",
    "wof:placetype":"venue"
},
  "geometry": {"coordinates":[-84.40240300000001,33.741823],"type":"Point"}
}