{
  "type": "Feature",
  "properties": {
    "addr:full":"388 Auburn Ave NE Atlanta GA 30312",
    "addr:housenumber":"388",
    "addr:postcode":"30312",
    "addr:street":"Auburn Ave Ne",
    "iso:country":"US",
    "sg:address":"388 Auburn Ave NE",
    "sg:city":"Atlanta",
    "sg:classifiers":[
        {
            "category":"Retail",
            "subcategory":"Laundry & Dry Cleaning",
            "type":"Services"
        }
    ],
    "sg:phone":"+1 404 581 9497",
    "sg:postcode":"30312",
    "sg:province":"GA",
    "sg:tags":[
        "cleaner",
        "plant",
        "drycleaning",
        "agent",
        "garment"
    ],
    "wof:name":"Auburn Cleaners & Laundry",
    "wof:placetype":"venue"
},
  "geometry": {"coordinates":[-84.37490099999999,33.755402],"type":"Point"}
}