{
  "type": "Feature",
  "properties": {
    "addr:full":"4151 Memorial Dr Decatur GA 30032",
    "addr:housenumber":"4151",
    "addr:postcode":"30032",
    "addr:street":"Memorial Dr",
    "iso:country":"US",
    "sg:address":"4151 Memorial Dr",
    "sg:city":"Decatur",
    "sg:classifiers":[
        {
            "category":"Professional",
            "subcategory":"Lawyer & Legal Services",
            "type":"Services"
        }
    ],
    "sg:phone":"+1 404 292 8674",
    "sg:postcode":"30032",
    "sg:province":"GA",
    "wof:name":"Cary Langston",
    "wof:placetype":"venue"
},
  "geometry": {"coordinates":[-84.24968200000001,33.771262],"type":"Point"}
}