{
  "type": "Feature",
  "properties": {
    "addr:full":"117 W 54th St Savannah GA 31405",
    "addr:housenumber":"117",
    "addr:postcode":"31405",
    "addr:street":"W 54Th St",
    "iso:country":"US",
    "sg:address":"117 W 54th St",
    "sg:city":"Savannah",
    "sg:classifiers":[
        {
            "category":"Building & Trades",
            "subcategory":"Electrical",
            "type":"Services"
        }
    ],
    "sg:phone":"+1 912 667 7489",
    "sg:postcode":"31405",
    "sg:province":"GA",
    "sg:tags":[
        "electrician"
    ],
    "wof:name":"Sharpe Electric",
    "wof:placetype":"venue"
},
  "geometry": {"coordinates":[-81.107423,32.04498],"type":"Point"}
}