{
  "type": "Feature",
  "properties": {
    "iso:country":"US",
    "sg:address":"3799 Sanders Rd SW",
    "sg:city":"Marietta",
    "sg:classifiers":[
        {
            "category":"Home & Garden",
            "subcategory":"Garden Supply",
            "type":"Retail Goods"
        }
    ],
    "sg:phone":"+1 770 943 2383",
    "sg:postcode":"30008",
    "sg:province":"GA",
    "sg:tags":[
        "horticulture",
        "product"
    ],
    "wof:name":"Gaddy Tree Service",
    "wof:placetype":"venue"
},
  "geometry": {"coordinates":[-84.64122999999999,33.860098],"type":"Point"}
}