{
  "type": "Feature",
  "properties": {
    "iso:country":"US",
    "sg:address":"2646 Abington Dr",
    "sg:city":"Snellville",
    "sg:classifiers":[
        {
            "category":"Real Estate",
            "subcategory":"Real Estate Services",
            "type":"Services"
        },
        {
            "category":"Professional",
            "subcategory":"Business Services",
            "type":"Services"
        }
    ],
    "sg:phone":"+1 770 979 6955",
    "sg:postcode":"30078",
    "sg:province":"GA",
    "sg:tags":[
        "home",
        "inspector",
        "inspection"
    ],
    "sg:website":"www.gaqualityhomeinsp.com",
    "wof:name":"Georgia Quality Home Inspections",
    "wof:placetype":"venue"
},
  "geometry": {"coordinates":[-83.99956400000001,33.854735],"type":"Point"}
}