{
  "type": "Feature",
  "properties": {
    "addr:full":"711 Banner Elk Ct Stone Mountain GA 30083",
    "addr:housenumber":"711",
    "addr:postcode":"30083",
    "addr:street":"Banner Elk Ct",
    "iso:country":"US",
    "sg:address":"711 Banner Elk Ct",
    "sg:city":"Stone Mountain",
    "sg:classifiers":[
        {
            "category":"Professional",
            "type":"Services"
        }
    ],
    "sg:phone":"+1 404 508 9801",
    "sg:postcode":"30083",
    "sg:province":"GA",
    "wof:name":"Sharon E Crowder",
    "wof:placetype":"venue"
},
  "geometry": {"coordinates":[-84.1987,33.774693],"type":"Point"}
}