{
  "type": "Feature",
  "properties": {
    "addr:full":"3345 Middle Ground Rd Statesboro GA 30461",
    "addr:housenumber":"3345",
    "addr:postcode":"30461",
    "addr:street":"Middle Ground Rd",
    "iso:country":"US",
    "sg:address":"3345 Middle Ground Rd",
    "sg:city":"Statesboro",
    "sg:classifiers":[
        {
            "category":"Building & Trades",
            "subcategory":"Construction",
            "type":"Services"
        },
        {
            "category":"Home & Garden",
            "subcategory":"Carpets & Floor Coverings",
            "type":"Retail Goods"
        }
    ],
    "sg:phone":"+1 912 587 5454",
    "sg:postcode":"30461",
    "sg:province":"GA",
    "sg:tags":[
        "vinyl",
        "contractor"
    ],
    "wof:name":"American Vinyl Siding Services",
    "wof:placetype":"venue"
},
  "geometry": {"coordinates":[-81.832494,32.535492],"type":"Point"}
}