{
  "type": "Feature",
  "properties": {
    "addr:full":"131 Newport Rd SW Lilburn GA 30047",
    "addr:housenumber":"131",
    "addr:postcode":"30047",
    "addr:street":"Newport Rd Sw",
    "iso:country":"US",
    "sg:address":"131 Newport Rd SW",
    "sg:city":"Lilburn",
    "sg:classifiers":[
        {
            "category":"Professional",
            "type":"Services"
        }
    ],
    "sg:phone":"+1 770 923 0822",
    "sg:postcode":"30047",
    "sg:province":"GA",
    "wof:name":"Leo J Thompson",
    "wof:placetype":"venue"
},
  "geometry": {"coordinates":[-84.123643,33.885121],"type":"Point"}
}