{
  "type": "Feature",
  "properties": {
    "addr:full":"4837 Newton Ter NE Buford GA 30518",
    "addr:housenumber":"4837",
    "addr:postcode":"30518",
    "addr:street":"Newton Ter Ne",
    "iso:country":"US",
    "sg:address":"4837 Newton Ter NE",
    "sg:city":"Buford",
    "sg:classifiers":[
        {
            "category":"Wholesale",
            "subcategory":"Construction Materials",
            "type":"Manufacturing & Wholesale Goods"
        }
    ],
    "sg:phone":"+1 770 205 2900",
    "sg:postcode":"30518",
    "sg:province":"GA",
    "sg:tags":[
        "specialty"
    ],
    "wof:name":"Lnl Enterprises Inc",
    "wof:placetype":"venue"
},
  "geometry": {"coordinates":[-83.96922499999999,34.133038],"type":"Point"}
}