{
  "type": "Feature",
  "properties": {
    "addr:full":"1101 N Main St La Fayette GA 30728",
    "addr:housenumber":"1101",
    "addr:postcode":"30728",
    "addr:street":"N Main St;Fayette",
    "iso:country":"US",
    "sg:address":"1101 N Main St",
    "sg:city":"La Fayette",
    "sg:classifiers":[
        {
            "category":"Restaurant",
            "type":"Food & Drink"
        }
    ],
    "sg:menulink":"http://www.allmenus.com/ga/lafayette/203327-mcdonalds/menu/",
    "sg:postcode":"30728",
    "sg:province":"GA",
    "sg:tags":[
        "burger",
        "american"
    ],
    "wof:name":"McDonald's",
    "wof:placetype":"venue"
},
  "geometry": {"coordinates":[-85.279872,34.723591],"type":"Point"}
}