{
  "type": "Feature",
  "properties": {
    "iso:country":"US",
    "sg:address":"1723 12th Ave",
    "sg:city":"Columbus",
    "sg:classifiers":[
        {
            "category":"Retail",
            "subcategory":"Repair Shop",
            "type":"Services"
        }
    ],
    "sg:phone":"+1 706 576 5997",
    "sg:postcode":"31901",
    "sg:province":"GA",
    "sg:tags":[
        "upholsterer"
    ],
    "wof:name":"Frank Martin Upholstery",
    "wof:placetype":"venue"
},
  "geometry": {"coordinates":[-84.975882,32.479262],"type":"Point"}
}