{
  "type": "Feature",
  "properties": {
    "iso:country":"US",
    "sg:address":"5506 Buford Hwy",
    "sg:city":"Norcross",
    "sg:classifiers":[
        {
            "category":"Autos & Motor Vehicles",
            "subcategory":"Automobile Sales",
            "type":"Retail Goods"
        }
    ],
    "sg:phone":"+1 770 416 8888",
    "sg:postcode":"30071",
    "sg:province":"GA",
    "sg:tags":[
        "car",
        "used"
    ],
    "wof:name":"Bruce Motors Inc",
    "wof:placetype":"venue"
},
  "geometry": {"coordinates":[-84.20366199999999,33.944949],"type":"Point"}
}