{
  "type": "Feature",
  "properties": {
    "addr:full":"201 Cherokee St Marietta GA 30060",
    "addr:housenumber":"201",
    "addr:postcode":"30060",
    "addr:street":"Cherokee St",
    "iso:country":"US",
    "sg:address":"201 Cherokee St",
    "sg:city":"Marietta",
    "sg:classifiers":[
        {
            "category":"Building & Trades",
            "subcategory":"Landscaping Services",
            "type":"Services"
        }
    ],
    "sg:phone":"+1 404 285 2818",
    "sg:postcode":"30060",
    "sg:province":"GA",
    "sg:tags":[
        "landscape"
    ],
    "wof:name":"AAAA Landscaping",
    "wof:placetype":"venue"
},
  "geometry": {"coordinates":[-84.549121,33.957333],"type":"Point"}
}