{
  "type": "Feature",
  "properties": {
    "iso:country":"US",
    "sg:address":"4738 Jonesboro Rd",
    "sg:city":"Forest Park",
    "sg:classifiers":[
        {
            "category":"Shopping",
            "type":"Retail Goods"
        }
    ],
    "sg:phone":"+1 404 363 0322",
    "sg:postcode":"30297",
    "sg:province":"GA",
    "sg:tags":[
        "merchandise"
    ],
    "wof:name":"Award Center Inc",
    "wof:placetype":"venue"
},
  "geometry": {"coordinates":[-84.35509999999999,33.626252],"type":"Point"}
}