{
  "type": "Feature",
  "properties": {
    "iso:country":"US",
    "sg:address":"5850 Gateway Drive",
    "sg:city":"Atlanta",
    "sg:classifiers":[
        {
            "category":"Ice Cream",
            "type":"Food & Drink"
        }
    ],
    "sg:phone":"+1 770 663 1477",
    "sg:postcode":"30303",
    "sg:province":"GA",
    "sg:tags":[
        "frozen",
        "yogurt"
    ],
    "wof:name":"Brusters Old Fashioned Ice Cream & Yogurt",
    "wof:placetype":"venue"
},
  "geometry": {"coordinates":[-84.38897,33.755418],"type":"Point"}
}