{
  "type": "Feature",
  "properties": {
    "addr:full":"2242 US Hwy 441 Dublin GA 31021",
    "addr:housenumber":"2242",
    "addr:postcode":"31021",
    "addr:street":"Us Hwy 441",
    "iso:country":"US",
    "sg:address":"2242 US Hwy 441",
    "sg:city":"Dublin",
    "sg:classifiers":[
        {
            "category":"Shopping",
            "subcategory":"Gifts & Souvenirs",
            "type":"Retail Goods"
        }
    ],
    "sg:phone":"+1 478 275 7688",
    "sg:postcode":"31021",
    "sg:province":"GA",
    "wof:name":"Dublin Antique Mall",
    "wof:placetype":"venue"
},
  "geometry": {"coordinates":[-82.90898199999999,32.533589],"type":"Point"}
}