{
  "type": "Feature",
  "properties": {
    "addr:full":"3321 W Shadowlawn Ave NE Atlanta GA 30305",
    "addr:housenumber":"3321",
    "addr:postcode":"30305",
    "addr:street":"W Shadowlawn Ave Ne",
    "iso:country":"US",
    "sg:address":"3321 W Shadowlawn Ave NE",
    "sg:city":"Atlanta",
    "sg:phone":"+1 404 846 1790",
    "sg:postcode":"30305",
    "sg:province":"GA",
    "wof:name":"Claire Halloway",
    "wof:placetype":"venue"
},
  "geometry": {"coordinates":[-84.375894,33.845173],"type":"Point"}
}