{
  "type": "Feature",
  "properties": {
    "addr:full":"2869 Manitoba Ct Marietta GA 30062",
    "addr:housenumber":"2869",
    "addr:postcode":"30062",
    "addr:street":"Manitoba Ct",
    "iso:country":"US",
    "sg:address":"2869 Manitoba Ct",
    "sg:city":"Marietta",
    "sg:classifiers":[
        {
            "category":"Insurance",
            "subcategory":"Insurance Agent",
            "type":"Services"
        }
    ],
    "sg:phone":"+1 678 236 1600",
    "sg:postcode":"30062",
    "sg:province":"GA",
    "wof:name":"Peachtree Insurance Advisors",
    "wof:placetype":"venue"
},
  "geometry": {"coordinates":[-84.47624500000001,34.017669],"type":"Point"}
}