{
  "type": "Feature",
  "properties": {
    "addr:full":"2501 N Patterson St Valdosta GA 31602",
    "addr:housenumber":"2501",
    "addr:postcode":"31602",
    "addr:street":"N Patterson St",
    "iso:country":"US",
    "sg:address":"2501 N Patterson St",
    "sg:city":"Valdosta",
    "sg:classifiers":[
        {
            "category":"Health Services",
            "subcategory":"Doctor",
            "type":"Services"
        }
    ],
    "sg:phone":"+1 229 259 4656",
    "sg:postcode":"31602",
    "sg:province":"GA",
    "sg:tags":[
        "physician",
        "surgeon"
    ],
    "wof:name":"Emergency Services Of SGMC",
    "wof:placetype":"venue"
},
  "geometry": {"coordinates":[-83.288883,30.861611],"type":"Point"}
}