{
  "type": "Feature",
  "properties": {
    "addr:full":"730 Sandy Creek Rd Fayetteville GA 30214",
    "addr:housenumber":"730",
    "addr:postcode":"30214",
    "addr:street":"Sandy Creek Rd",
    "iso:country":"US",
    "sg:address":"730 Sandy Creek Rd",
    "sg:city":"Fayetteville",
    "sg:classifiers":[
        {
            "category":"Building & Trades",
            "subcategory":"Construction",
            "type":"Services"
        }
    ],
    "sg:phone":"+1 678 817 9401",
    "sg:postcode":"30214",
    "sg:province":"GA",
    "sg:tags":[
        "masonry",
        "contractor"
    ],
    "wof:name":"Q C Masonry",
    "wof:placetype":"venue"
},
  "geometry": {"coordinates":[-84.529659,33.483434],"type":"Point"}
}