{
  "type": "Feature",
  "properties": {
    "addr:full":"3740 Cannonwolde Dr Snellville GA 30039",
    "addr:housenumber":"3740",
    "addr:postcode":"30039",
    "addr:street":"Cannonwolde Dr",
    "iso:country":"US",
    "sg:address":"3740 Cannonwolde Dr",
    "sg:city":"Snellville",
    "sg:classifiers":[
        {
            "category":"Building & Trades",
            "subcategory":"Construction",
            "type":"Services"
        }
    ],
    "sg:phone":"+1 770 982 2776",
    "sg:postcode":"30039",
    "sg:province":"GA",
    "sg:tags":[
        "residential"
    ],
    "wof:name":"Traditions Fine Homebuilding",
    "wof:placetype":"venue"
},
  "geometry": {"coordinates":[-84.015469,33.81042],"type":"Point"}
}