{
  "type": "Feature",
  "properties": {
    "addr:full":"705 Townpark Ln NW Kennesaw GA 30144",
    "addr:housenumber":"705",
    "addr:postcode":"30144",
    "addr:street":"Townpark Ln Nw",
    "iso:country":"US",
    "sg:address":"705 Townpark Ln NW",
    "sg:city":"Kennesaw",
    "sg:classifiers":[
        {
            "category":"Restaurant",
            "type":"Food & Drink"
        }
    ],
    "sg:menulink":"http://www.allmenus.com/ga/northeast-cobb/48958-ocharleys/menu/",
    "sg:phone":"+1 770 792 7866",
    "sg:postcode":"30144",
    "sg:province":"GA",
    "sg:tags":[
        "american"
    ],
    "wof:name":"O'Charley's",
    "wof:placetype":"venue"
},
  "geometry": {"coordinates":[-84.546533,34.060632],"type":"Point"}
}