{
  "type": "Feature",
  "properties": {
    "addr:full":"61 Covered Bridge Rd Euharlee GA 30145",
    "addr:housenumber":"61",
    "addr:postcode":"30145",
    "addr:street":"Covered Bridge Rd",
    "iso:country":"US",
    "sg:address":"61 Covered Bridge Rd",
    "sg:city":"Euharlee",
    "sg:classifiers":[
        {
            "category":"Place Of Worship",
            "subcategory":"Church",
            "type":"Public Place"
        },
        {
            "category":"Place Of Worship",
            "type":"Public Place"
        }
    ],
    "sg:phone":"+1 770 386 2860",
    "sg:postcode":"30145",
    "sg:province":"GA",
    "sg:tags":[
        "churches-presbyterian-arp",
        "churches-presbyterian"
    ],
    "wof:name":"Euharlee Presbyterian Church",
    "wof:placetype":"venue"
},
  "geometry": {"coordinates":[-84.93398000000001,34.147123],"type":"Point"}
}