{
  "type": "Feature",
  "properties": {
    "addr:full":"406 Northside Dr Valdosta GA 31602",
    "addr:housenumber":"406",
    "addr:postcode":"31602",
    "addr:street":"Northside Dr",
    "iso:country":"US",
    "sg:address":"406 Northside Dr",
    "sg:city":"Valdosta",
    "sg:classifiers":[
        {
            "category":"Retail",
            "subcategory":"Repair Shop",
            "type":"Services"
        }
    ],
    "sg:phone":"+1 229 244 6668",
    "sg:postcode":"31602",
    "sg:province":"GA",
    "wof:name":"Bishops Jewelrs",
    "wof:placetype":"venue"
},
  "geometry": {"coordinates":[-83.284811,30.870613],"type":"Point"}
}