{
  "type": "Feature",
  "properties": {
    "iso:country":"US",
    "sg:address":"216 Greentree Pkwy",
    "sg:city":"Macon",
    "sg:classifiers":[
        {
            "category":"Retail",
            "subcategory":"Repair Shop",
            "type":"Services"
        }
    ],
    "sg:phone":"+1 478 736 6161",
    "sg:postcode":"31220",
    "sg:province":"GA",
    "sg:tags":[
        "pager"
    ],
    "wof:name":"Pager Repair Service",
    "wof:placetype":"venue"
},
  "geometry": {"coordinates":[-83.767116,32.86182],"type":"Point"}
}