{
  "type": "Feature",
  "properties": {
    "addr:full":"2375 Pine Cove Dr Tucker GA 30084",
    "addr:housenumber":"2375",
    "addr:postcode":"30084",
    "addr:street":"Pine Cove Dr",
    "iso:country":"US",
    "sg:address":"2375 Pine Cove Dr",
    "sg:city":"Tucker",
    "sg:classifiers":[
        {
            "category":"Wholesale",
            "subcategory":"Machinery & Supplies",
            "type":"Manufacturing & Wholesale Goods"
        }
    ],
    "sg:phone":"+1 770 938 9444",
    "sg:postcode":"30084",
    "sg:province":"GA",
    "sg:tags":[
        "sales"
    ],
    "wof:name":"Rudox Engines",
    "wof:placetype":"venue"
},
  "geometry": {"coordinates":[-84.220686,33.86007],"type":"Point"}
}