{
  "type": "Feature",
  "properties": {
    "iso:country":"US",
    "sg:address":"905 Hightower Trl",
    "sg:city":"Atlanta",
    "sg:classifiers":[
        {
            "category":"Professional",
            "subcategory":"Business Services",
            "type":"Services"
        }
    ],
    "sg:phone":"+1 770 998 9066",
    "sg:postcode":"30350",
    "sg:province":"GA",
    "wof:name":"Beverly Midwood Interiors Inc",
    "wof:placetype":"venue"
},
  "geometry": {"coordinates":[-84.361586,33.991538],"type":"Point"}
}