{
  "type": "Feature",
  "properties": {
    "iso:country":"US",
    "sg:address":"5986 Buford Hwy",
    "sg:city":"Norcross",
    "sg:classifiers":[
        {
            "category":"Shopping",
            "subcategory":"Pawn Shop",
            "type":"Retail Goods"
        }
    ],
    "sg:phone":"+1 770 447 6618",
    "sg:postcode":"30071",
    "sg:province":"GA",
    "sg:website":"www.pawnmart.com",
    "wof:name":"Pawnmart",
    "wof:placetype":"venue"
},
  "geometry": {"coordinates":[-84.216144,33.934741],"type":"Point"}
}