{
  "type": "Feature",
  "properties": {
    "addr:full":"415 Creekview Dr Stone Mountain GA 30083",
    "addr:housenumber":"415",
    "addr:postcode":"30083",
    "addr:street":"Creekview Dr",
    "iso:country":"US",
    "sg:address":"415 Creekview Dr",
    "sg:city":"Stone Mountain",
    "sg:classifiers":[
        {
            "category":"Building & Trades",
            "subcategory":"Construction",
            "type":"Services"
        }
    ],
    "sg:phone":"+1 770 560 4684",
    "sg:postcode":"30083",
    "sg:province":"GA",
    "sg:tags":[
        "house"
    ],
    "wof:name":"Decks Dawson & Remodeling",
    "wof:placetype":"venue"
},
  "geometry": {"coordinates":[-84.242345,33.787517],"type":"Point"}
}