{
  "type": "Feature",
  "properties": {
    "iso:country":"US",
    "sg:address":"4065 Shelby Ln",
    "sg:city":"Cumming",
    "sg:classifiers":[
        {
            "category":"Banks & Credit Unions",
            "subcategory":"Investment Brokerage",
            "type":"Services"
        }
    ],
    "sg:phone":"+1 770 888 2073",
    "sg:postcode":"30041",
    "sg:province":"GA",
    "sg:tags":[
        "advisory",
        "financial"
    ],
    "wof:name":"Merchant Financial Svc",
    "wof:placetype":"venue"
},
  "geometry": {"coordinates":[-84.07765499999999,34.20787],"type":"Point"}
}