{
  "type": "Feature",
  "properties": {
    "iso:country":"US",
    "sg:address":"1100 Hammond Dr NE",
    "sg:city":"Atlanta",
    "sg:classifiers":[
        {
            "category":"Professional",
            "subcategory":"Art Services",
            "type":"Services"
        },
        {
            "category":"Professional",
            "subcategory":"Computer Services",
            "type":"Services"
        }
    ],
    "sg:phone":"+1 877 585 8174",
    "sg:postcode":"30328",
    "sg:province":"GA",
    "sg:tags":[
        "consultant",
        "graphic",
        "designer",
        "system",
        "software"
    ],
    "wof:name":"Panda Web Designs",
    "wof:placetype":"venue"
},
  "geometry": {"coordinates":[-84.35128,33.918941],"type":"Point"}
}