{
  "type": "Feature",
  "properties": {
    "addr:full":"2482 Atlanta Rd SE Smyrna GA 30080",
    "addr:housenumber":"2482",
    "addr:postcode":"30080",
    "addr:street":"Atlanta Rd Se",
    "iso:country":"US",
    "sg:address":"2482 Atlanta Rd SE",
    "sg:city":"Smyrna",
    "sg:classifiers":[
        {
            "category":"Professional",
            "subcategory":"Management & Consulting",
            "type":"Services"
        }
    ],
    "sg:phone":"+1 770 801 9617",
    "sg:postcode":"30080",
    "sg:province":"GA",
    "sg:tags":[
        "consultant",
        "educational"
    ],
    "wof:name":"C Tec",
    "wof:placetype":"venue"
},
  "geometry": {"coordinates":[-84.520083,33.893682],"type":"Point"}
}