{
  "type": "Feature",
  "properties": {
    "iso:country":"US",
    "sg:address":"9238 River Chase Way",
    "sg:city":"Jonesboro",
    "sg:classifiers":[
        {
            "category":"Shopping",
            "subcategory":"Department Store",
            "type":"Retail Goods"
        }
    ],
    "sg:phone":"+1 678 479 5955",
    "sg:postcode":"30238",
    "sg:province":"GA",
    "sg:tags":[
        "variety"
    ],
    "wof:name":"Cns Variety",
    "wof:placetype":"venue"
},
  "geometry": {"coordinates":[-84.402449,33.503186],"type":"Point"}
}