{
  "type": "Feature",
  "properties": {
    "iso:country":"US",
    "sg:address":"3430 Riviera Dr",
    "sg:city":"Cumming",
    "sg:classifiers":[
        {
            "category":"Professional",
            "subcategory":"Art Services",
            "type":"Services"
        }
    ],
    "sg:phone":"+1 770 886 5576",
    "sg:postcode":"30041",
    "sg:province":"GA",
    "sg:tags":[
        "photography",
        "commercial"
    ],
    "wof:name":"Adventures In Advertising",
    "wof:placetype":"venue"
},
  "geometry": {"coordinates":[-84.089433,34.223135],"type":"Point"}
}