{
  "type": "Feature",
  "properties": {
    "iso:country":"US",
    "sg:address":"8960 Nesbit Lakes Dr",
    "sg:city":"Alpharetta",
    "sg:classifiers":[
        {
            "category":"Personal",
            "type":"Services"
        }
    ],
    "sg:phone":"+1 770 649 1696",
    "sg:postcode":"30022",
    "sg:province":"GA",
    "sg:tags":[
        "consultant",
        "planning",
        "wedding"
    ],
    "wof:name":"Notable Weddings And Events",
    "wof:placetype":"venue"
},
  "geometry": {"coordinates":[-84.28923500000001,34.016674],"type":"Point"}
}