{
  "type": "Feature",
  "properties": {
    "addr:full":"5445 Riverchase Dr Flowery Branch GA 30542",
    "addr:housenumber":"5445",
    "addr:postcode":"30542",
    "addr:street":"Riverchase Dr",
    "iso:country":"US",
    "sg:address":"5445 Riverchase Dr",
    "sg:city":"Flowery Branch",
    "sg:classifiers":[
        {
            "category":"Communications",
            "subcategory":"Film & Video Production",
            "type":"Services"
        }
    ],
    "sg:phone":"+1 678 617 5150",
    "sg:postcode":"30542",
    "sg:province":"GA",
    "sg:tags":[
        "motion"
    ],
    "wof:name":"Astral Productions",
    "wof:placetype":"venue"
},
  "geometry": {"coordinates":[-83.882873,34.15785],"type":"Point"}
}