{
  "type": "Feature",
  "properties": {
    "iso:country":"US",
    "sg:address":"2914 Professional Pkwy",
    "sg:city":"Augusta",
    "sg:classifiers":[
        {
            "category":"Wholesale",
            "subcategory":"Medical Equipment & Supplies",
            "type":"Manufacturing & Wholesale Goods"
        }
    ],
    "sg:phone":"+1 706 868 1919",
    "sg:postcode":"30907",
    "sg:province":"GA",
    "sg:tags":[
        "physician",
        "surgeon"
    ],
    "wof:name":"Just In Time Meds Inc",
    "wof:placetype":"venue"
},
  "geometry": {"coordinates":[-82.081165,33.499025],"type":"Point"}
}