{
  "type": "Feature",
  "properties": {
    "addr:full":"710 S Thornton Ave Dalton GA 30720",
    "addr:housenumber":"710",
    "addr:postcode":"30720",
    "addr:street":"S Thornton Ave",
    "iso:country":"US",
    "sg:address":"710 S Thornton Ave",
    "sg:city":"Dalton",
    "sg:classifiers":[
        {
            "category":"Professional",
            "subcategory":"Lawyer & Legal Services",
            "type":"Services"
        }
    ],
    "sg:phone":"+1 706 217 6118",
    "sg:postcode":"30720",
    "sg:province":"GA",
    "wof:name":"Firm McMahon Law",
    "wof:placetype":"venue"
},
  "geometry": {"coordinates":[-84.97174699999999,34.765341],"type":"Point"}
}