{
  "type": "Feature",
  "properties": {
    "addr:full":"320 Colonial Dr Carrollton GA 30117",
    "addr:housenumber":"320",
    "addr:postcode":"30117",
    "addr:street":"Colonial Dr",
    "iso:country":"US",
    "sg:address":"320 Colonial Dr",
    "sg:city":"Carrollton",
    "sg:classifiers":[
        {
            "category":"Building & Trades",
            "subcategory":"Construction",
            "type":"Services"
        }
    ],
    "sg:phone":"+1 770 834 0637",
    "sg:postcode":"30117",
    "sg:province":"GA",
    "sg:tags":[
        "residential"
    ],
    "wof:name":"Roark Construction Inc",
    "wof:placetype":"venue"
},
  "geometry": {"coordinates":[-85.113946,33.550393],"type":"Point"}
}