{
  "type": "Feature",
  "properties": {
    "addr:full":"520 E Montgomery St Villa Rica GA 30180",
    "addr:housenumber":"520",
    "addr:postcode":"30180",
    "addr:street":"E Montgomery St",
    "iso:country":"US",
    "sg:address":"520 E Montgomery St",
    "sg:city":"Villa Rica",
    "sg:classifiers":[
        {
            "category":"Freight",
            "type":"Transportation"
        },
        {
            "category":"Wholesale",
            "subcategory":"Motor Vehicles",
            "type":"Manufacturing & Wholesale Goods"
        }
    ],
    "sg:phone":"+1 770 459 4496",
    "sg:postcode":"30180",
    "sg:province":"GA",
    "sg:tags":[
        "commercial",
        "storage"
    ],
    "wof:name":"Capital Storage",
    "wof:placetype":"venue"
},
  "geometry": {"coordinates":[-84.906854,33.729993],"type":"Point"}
}