{
  "type": "Feature",
  "properties": {
    "addr:full":"6501 Peake Rd Macon GA 31210",
    "addr:housenumber":"6501",
    "addr:postcode":"31210",
    "addr:street":"Peake Rd",
    "iso:country":"US",
    "sg:address":"6501 Peake Rd",
    "sg:city":"Macon",
    "sg:classifiers":[
        {
            "category":"Health Services",
            "subcategory":"Doctor",
            "type":"Services"
        }
    ],
    "sg:phone":"+1 478 757 8868",
    "sg:postcode":"31210",
    "sg:province":"GA",
    "sg:tags":[
        "physician",
        "surgeon"
    ],
    "wof:name":"Vascular & Interventional",
    "wof:placetype":"venue"
},
  "geometry": {"coordinates":[-83.76406299999999,32.878563],"type":"Point"}
}