{
  "type": "Feature",
  "properties": {
    "addr:full":"317 Freys Gin Rd SE Marietta GA 30067",
    "addr:housenumber":"317",
    "addr:postcode":"30067",
    "addr:street":"Freys Gin Rd Se",
    "iso:country":"US",
    "sg:address":"317 Freys Gin Rd SE",
    "sg:city":"Marietta",
    "sg:classifiers":[
        {
            "category":"Wholesale",
            "subcategory":"Auto Parts",
            "type":"Manufacturing & Wholesale Goods"
        }
    ],
    "sg:phone":"+1 770 423 0198",
    "sg:postcode":"30067",
    "sg:province":"GA",
    "sg:tags":[
        "automobile",
        "rebuilt"
    ],
    "wof:name":"Marietta Auto Salvage",
    "wof:placetype":"venue"
},
  "geometry": {"coordinates":[-84.51685000000001,33.944571],"type":"Point"}
}