{
  "type": "Feature",
  "properties": {
    "addr:full":"5581 Wrightsboro Rd Grovetown GA 30813",
    "addr:housenumber":"5581",
    "addr:postcode":"30813",
    "addr:street":"Wrightsboro Rd",
    "iso:country":"US",
    "sg:address":"5581 Wrightsboro Rd",
    "sg:city":"Grovetown",
    "sg:classifiers":[
        {
            "category":"Manufacturing",
            "subcategory":"Apparel",
            "type":"Manufacturing & Wholesale Goods"
        }
    ],
    "sg:phone":"+1 706 556 0363",
    "sg:postcode":"30813",
    "sg:province":"GA",
    "sg:tags":[
        "product",
        "center",
        "mfg",
        "entertainment",
        "fabricated",
        "textile",
        "sport",
        "se"
    ],
    "wof:name":"Canterbury Trails",
    "wof:placetype":"venue"
},
  "geometry": {"coordinates":[-82.242403,33.470764],"type":"Point"}
}