{
  "type": "Feature",
  "properties": {
    "addr:full":"321 W 5th St Rome GA 30165",
    "addr:housenumber":"321",
    "addr:postcode":"ga 30165",
    "addr:street":"W 5Th St",
    "iso:country":"US",
    "sg:address":"321 W 5th St",
    "sg:city":"Rome",
    "sg:classifiers":[
        {
            "category":"Health Services",
            "subcategory":"Doctor",
            "type":"Services"
        }
    ],
    "sg:phone":"+1 706 234 1400",
    "sg:postcode":"30165",
    "sg:province":"GA",
    "sg:tags":[
        "physician",
        "surgeon",
        "medical"
    ],
    "sg:website":"www.rrocrome.com",
    "wof:name":"Regional Radiology Oncology",
    "wof:placetype":"venue"
},
  "geometry": {"coordinates":[-85.176289,34.258684],"type":"Point"}
}