{
  "type": "Feature",
  "properties": {
    "iso:country":"US",
    "sg:address":"1140 Prince Ave",
    "sg:city":"Athens",
    "sg:classifiers":[
        {
            "category":"Food & Beverages",
            "subcategory":"Fruits & Vegetables",
            "type":"Retail Goods"
        }
    ],
    "sg:phone":"+1 706 208 9800",
    "sg:postcode":"30606",
    "sg:province":"GA",
    "sg:tags":[
        "juice"
    ],
    "wof:name":"Righteous Juice Co",
    "wof:placetype":"venue"
},
  "geometry": {"coordinates":[-83.39551299999999,33.962223],"type":"Point"}
}