{
  "type": "Feature",
  "properties": {
    "addr:full":"310 N River St NW Calhoun GA 30701",
    "addr:housenumber":"310",
    "addr:postcode":"30701",
    "addr:street":"N River St Nw",
    "iso:country":"US",
    "sg:address":"310 N River St NW",
    "sg:city":"Calhoun",
    "sg:classifiers":[
        {
            "category":"Government",
            "subcategory":"Office",
            "type":"Public Place"
        }
    ],
    "sg:phone":"+1 706 624 1440",
    "sg:postcode":"30701",
    "sg:province":"GA",
    "wof:name":"Gordon County Environmental",
    "wof:placetype":"venue"
},
  "geometry": {"coordinates":[-84.956332,34.506519],"type":"Point"}
}