{
  "type": "Feature",
  "properties": {
    "iso:country":"US",
    "sg:address":"2736 Tritt Springs Trce NE",
    "sg:city":"Marietta",
    "sg:classifiers":[
        {
            "category":"Shopping",
            "type":"Retail Goods"
        }
    ],
    "sg:phone":"+1 678 560 6400",
    "sg:postcode":"30062",
    "sg:province":"GA",
    "sg:tags":[
        "merchandising"
    ],
    "wof:name":"Delta Control Mar Ga Mar",
    "wof:placetype":"venue"
},
  "geometry": {"coordinates":[-84.449692,34.01836],"type":"Point"}
}