{
  "type": "Feature",
  "properties": {
    "iso:country":"US",
    "sg:address":"2545 Bethany Ln",
    "sg:city":"Powder Springs",
    "sg:classifiers":[
        {
            "category":"Communications",
            "subcategory":"Television Station",
            "type":"Services"
        }
    ],
    "sg:phone":"+1 770 439 5820",
    "sg:postcode":"30127",
    "sg:province":"GA",
    "sg:tags":[
        "telephone"
    ],
    "wof:name":"Nichols Communications Inc",
    "wof:placetype":"venue"
},
  "geometry": {"coordinates":[-84.67586799999999,33.892698],"type":"Point"}
}