{
  "type": "Feature",
  "properties": {
    "addr:full":"1460 W Bay St Savannah GA 31415",
    "addr:housenumber":"1460",
    "addr:postcode":"31415",
    "addr:street":"W Bay St",
    "iso:country":"US",
    "sg:address":"1460 W Bay St",
    "sg:city":"Savannah",
    "sg:classifiers":[
        {
            "category":"Manufacturing",
            "subcategory":"Wood Products",
            "type":"Manufacturing & Wholesale Goods"
        },
        {
            "category":"Home & Garden",
            "subcategory":"Carpets & Floor Coverings",
            "type":"Retail Goods"
        },
        {
            "category":"Home & Garden",
            "subcategory":"Building Materials",
            "type":"Retail Goods"
        },
        {
            "category":"Building & Trades",
            "subcategory":"Construction",
            "type":"Services"
        },
        {
            "category":"Home & Garden",
            "subcategory":"Furniture",
            "type":"Retail Goods"
        }
    ],
    "sg:phone":"+1 912 447 0482",
    "sg:postcode":"31415",
    "sg:province":"GA",
    "sg:tags":[
        "equipment-household",
        "lumber",
        "tile-contractors",
        "kitchen",
        "cabinet"
    ],
    "wof:name":"Mo's Discount Lumber & Salvage LLC",
    "wof:placetype":"venue"
},
  "geometry": {"coordinates":[-81.106667,32.066195],"type":"Point"}
}