{
  "type": "Feature",
  "properties": {
    "addr:full":"125 Wellington Dr Perry GA 31069",
    "addr:housenumber":"125",
    "addr:postcode":"31069",
    "addr:street":"Wellington Dr",
    "iso:country":"US",
    "sg:address":"125 Wellington Dr",
    "sg:city":"Perry",
    "sg:classifiers":[
        {
            "category":"Banks & Credit Unions",
            "subcategory":"Financial Services",
            "type":"Services"
        }
    ],
    "sg:phone":"+1 478 987 6726",
    "sg:postcode":"31069",
    "sg:province":"GA",
    "sg:tags":[
        "investment",
        "closed"
    ],
    "wof:name":"DDB Investments Inc",
    "wof:placetype":"venue"
},
  "geometry": {"coordinates":[-83.697423,32.441616],"type":"Point"}
}