{
  "type": "Feature",
  "properties": {
    "iso:country":"US",
    "sg:address":"4924 Mercer University Dr",
    "sg:city":"Macon",
    "sg:classifiers":[
        {
            "category":"Retail",
            "subcategory":"Storage",
            "type":"Services"
        }
    ],
    "sg:phone":"+1 478 471 0603",
    "sg:postcode":"31210",
    "sg:province":"GA",
    "sg:tags":[
        "household",
        "commercial"
    ],
    "sg:website":"http://www.tshgroup.com",
    "wof:name":"Store House The",
    "wof:placetype":"venue"
},
  "geometry": {"coordinates":[-83.723377,32.829587],"type":"Point"}
}