{
  "type": "Feature",
  "properties": {
    "addr:full":"857 Collier Rd NW Atlanta GA 30318",
    "addr:housenumber":"857",
    "addr:postcode":"30318",
    "addr:street":"Collier Rd Nw",
    "iso:country":"US",
    "sg:address":"857 Collier Rd NW",
    "sg:city":"Atlanta",
    "sg:classifiers":[
        {
            "category":"Restaurant",
            "type":"Food & Drink"
        }
    ],
    "sg:menulink":"http://www.allmenus.com/ga/atlanta/18838-malaya/menu/",
    "sg:phone":"+1 404 609 9991",
    "sg:postcode":"30318",
    "sg:province":"GA",
    "sg:tags":[
        "thai",
        "malaysian",
        "asian",
        "chinese"
    ],
    "wof:name":"Malaya",
    "wof:placetype":"venue"
},
  "geometry": {"coordinates":[-84.414359,33.8095],"type":"Point"}
}