{
  "type": "Feature",
  "properties": {
    "addr:full":"1022 Windy Hill Rd SE Smyrna GA 30080",
    "addr:housenumber":"1022",
    "addr:postcode":"30080",
    "addr:street":"Windy Hill Rd Se",
    "iso:country":"US",
    "sg:address":"1022 Windy Hill Rd SE",
    "sg:city":"Smyrna",
    "sg:classifiers":[
        {
            "category":"Professional",
            "subcategory":"Lawyer & Legal Services",
            "type":"Services"
        }
    ],
    "sg:phone":"+1 770 803 9303",
    "sg:postcode":"30080",
    "sg:province":"GA",
    "sg:tags":[
        "plan"
    ],
    "wof:name":"Hispanoamerica Services",
    "wof:placetype":"venue"
},
  "geometry": {"coordinates":[-84.521743,33.894251],"type":"Point"}
}