{
  "type": "Feature",
  "properties": {
    "addr:full":"4325 Ivy Lynn Pl SW Snellville GA 30039",
    "addr:housenumber":"4325",
    "addr:postcode":"30039",
    "addr:street":"Ivy Lynn Pl Sw",
    "iso:country":"US",
    "sg:address":"4325 Ivy Lynn Pl SW",
    "sg:city":"Snellville",
    "sg:classifiers":[
        {
            "category":"Professional",
            "subcategory":"Management & Consulting",
            "type":"Services"
        }
    ],
    "sg:phone":"+1 678 614 1740",
    "sg:postcode":"30039",
    "sg:province":"GA",
    "sg:tags":[
        "business"
    ],
    "wof:name":"Atlanta Total Resource",
    "wof:placetype":"venue"
},
  "geometry": {"coordinates":[-83.990404,33.795302],"type":"Point"}
}