{
  "type": "Feature",
  "properties": {
    "iso:country":"US",
    "sg:address":"193 Ben Roy Mclendon Rd",
    "sg:city":"Lyons",
    "sg:classifiers":[
        {
            "category":"Insurance",
            "subcategory":"Hazard Insurance",
            "type":"Services"
        }
    ],
    "sg:phone":"+1 912 526 8177",
    "sg:postcode":"30436",
    "sg:province":"GA",
    "wof:name":"Michael Palma/A",
    "wof:placetype":"venue"
},
  "geometry": {"coordinates":[-82.29859399999999,32.184925],"type":"Point"}
}