{
  "type": "Feature",
  "properties": {
    "addr:full":"2365 Danielsville Rd Athens GA 30601",
    "addr:housenumber":"2365",
    "addr:postcode":"30601",
    "addr:street":"Danielsville Rd",
    "iso:country":"US",
    "sg:address":"2365 Danielsville Rd",
    "sg:city":"Athens",
    "sg:classifiers":[
        {
            "category":"Wholesale",
            "subcategory":"Groceries",
            "type":"Manufacturing & Wholesale Goods"
        }
    ],
    "sg:phone":"+1 706 425 9670",
    "sg:postcode":"30601",
    "sg:province":"GA",
    "sg:tags":[
        "frozen",
        "food"
    ],
    "wof:name":"Costa Del Sol",
    "wof:placetype":"venue"
},
  "geometry": {"coordinates":[-83.34532299999999,34.01395],"type":"Point"}
}