{
  "type": "Feature",
  "properties": {
    "addr:full":"3945 Flat Shoals Pkwy Decatur GA 30034",
    "addr:housenumber":"3945",
    "addr:postcode":"30034",
    "addr:street":"Flat Shoals Pkwy",
    "iso:country":"US",
    "sg:address":"3945 Flat Shoals Pkwy",
    "sg:city":"Decatur",
    "sg:classifiers":[
        {
            "category":"Autos & Motor Vehicles",
            "subcategory":"Automobile Sales",
            "type":"Retail Goods"
        }
    ],
    "sg:phone":"+1 404 212 0242",
    "sg:postcode":"30034",
    "sg:province":"GA",
    "sg:tags":[
        "car",
        "dealer"
    ],
    "wof:name":"Flat Shoals Auto Sales",
    "wof:placetype":"venue"
},
  "geometry": {"coordinates":[-84.26284099999999,33.695312],"type":"Point"}
}