{
  "type": "Feature",
  "properties": {
    "iso:country":"US",
    "sg:address":"2920 Woodgate Ct",
    "sg:city":"Marietta",
    "sg:classifiers":[
        {
            "category":"Health Services",
            "subcategory":"Clinic",
            "type":"Services"
        }
    ],
    "sg:phone":"+1 770 499 7367",
    "sg:postcode":"30066",
    "sg:province":"GA",
    "sg:tags":[
        "specialty",
        "outpatient"
    ],
    "wof:name":"Pure Gold Rehab",
    "wof:placetype":"venue"
},
  "geometry": {"coordinates":[-84.53404,34.022515],"type":"Point"}
}