{
  "type": "Feature",
  "properties": {
    "addr:full":"2125 Harmony Lake Cir Lithonia GA 30058",
    "addr:housenumber":"2125",
    "addr:postcode":"30058",
    "addr:street":"Harmony Lake Cir",
    "iso:country":"US",
    "sg:address":"2125 Harmony Lake Cir",
    "sg:city":"Lithonia",
    "sg:classifiers":[
        {
            "category":"Professional",
            "type":"Services"
        }
    ],
    "sg:phone":"+1 770 484 7136",
    "sg:postcode":"30058",
    "sg:province":"GA",
    "wof:name":"Repertoire Inc",
    "wof:placetype":"venue"
},
  "geometry": {"coordinates":[-84.062623,33.724955],"type":"Point"}
}