{
  "type": "Feature",
  "properties": {
    "iso:country":"US",
    "sg:address":"13 Broadmoor Cir",
    "sg:city":"Savannah",
    "sg:classifiers":[
        {
            "category":"Arts & Performance",
            "subcategory":"Theater",
            "type":"Entertainment"
        },
        {
            "category":"Personal",
            "type":"Services"
        }
    ],
    "sg:phone":"+1 912 352 2420",
    "sg:postcode":"31406",
    "sg:province":"GA",
    "sg:tags":[
        "repair",
        "musician"
    ],
    "wof:name":"Instrumental Links Inc",
    "wof:placetype":"venue"
},
  "geometry": {"coordinates":[-81.082175,32.013972],"type":"Point"}
}