{
  "type": "Feature",
  "properties": {
    "iso:country":"US",
    "sg:address":"5065 Riverthur Pl",
    "sg:city":"Duluth",
    "sg:classifiers":[
        {
            "category":"Professional",
            "type":"Services"
        }
    ],
    "sg:phone":"+1 770 263 9478",
    "sg:postcode":"30096",
    "sg:province":"GA",
    "wof:name":"Turnbury Oaks Hoa Inc",
    "wof:placetype":"venue"
},
  "geometry": {"coordinates":[-84.210227,33.982045],"type":"Point"}
}