{
  "type": "Feature",
  "properties": {
    "iso:country":"US",
    "sg:address":"5634 Zanola Dr",
    "sg:city":"Mableton",
    "sg:classifiers":[
        {
            "category":"Retail",
            "subcategory":"Auto Repair",
            "type":"Services"
        }
    ],
    "sg:phone":"+1 770 948 5251",
    "sg:postcode":"30126",
    "sg:province":"GA",
    "sg:tags":[
        "automotive"
    ],
    "wof:name":"Franks Radiator Sp & Wrckr Svc",
    "wof:placetype":"venue"
},
  "geometry": {"coordinates":[-84.59696099999999,33.815317],"type":"Point"}
}