{
  "type": "Feature",
  "properties": {
    "addr:full":"1980 Shoal Creek Rd Colbert GA 30656",
    "addr:housenumber":"1980",
    "addr:postcode":"30656",
    "addr:street":"Shoal Creek Rd",
    "iso:country":"US",
    "sg:address":"1980 Shoal Creek Rd",
    "sg:city":"Colbert",
    "sg:classifiers":[
        {
            "category":"Organizations",
            "subcategory":"Religious Organization",
            "type":"Services"
        }
    ],
    "sg:phone":"+1 706 788 3530",
    "sg:postcode":"30656",
    "sg:province":"GA",
    "wof:name":"Hope Worship Center Inc",
    "wof:placetype":"venue"
},
  "geometry": {"coordinates":[-83.702901,33.882773],"type":"Point"}
}