{
  "type": "Feature",
  "properties": {
    "addr:full":"2284 Old Concord Rd SE Smyrna GA 30082",
    "addr:housenumber":"2284",
    "addr:postcode":"30082",
    "addr:street":"Old Concord Rd Se",
    "iso:country":"US",
    "sg:address":"2284 Old Concord Rd SE",
    "sg:city":"Smyrna",
    "sg:classifiers":[
        {
            "category":"Building & Trades",
            "subcategory":"Construction",
            "type":"Services"
        }
    ],
    "sg:phone":"+1 770 432 1108",
    "sg:postcode":"30082",
    "sg:province":"GA",
    "sg:tags":[
        "door",
        "window",
        "installation"
    ],
    "wof:name":"Atlanta Door Win Installation",
    "wof:placetype":"venue"
},
  "geometry": {"coordinates":[-84.540192,33.896112],"type":"Point"}
}