{
  "type": "Feature",
  "properties": {
    "iso:country":"US",
    "sg:address":"1520 Pine Log Rd NE",
    "sg:city":"Conyers",
    "sg:classifiers":[
        {
            "category":"Banks & Credit Unions",
            "subcategory":"Financial Services",
            "type":"Services"
        }
    ],
    "sg:phone":"+1 770 648 6749",
    "sg:postcode":"30012",
    "sg:province":"GA",
    "wof:name":"W A Financial Services",
    "wof:placetype":"venue"
},
  "geometry": {"coordinates":[-83.99736,33.664139],"type":"Point"}
}