{
  "type": "Feature",
  "properties": {
    "addr:full":"121 S Lee St Fitzgerald GA 31750",
    "addr:housenumber":"121",
    "addr:postcode":"31750",
    "addr:street":"S Lee St",
    "iso:country":"US",
    "sg:address":"121 S Lee St",
    "sg:city":"Fitzgerald",
    "sg:classifiers":[
        {
            "category":"Insurance",
            "subcategory":"Insurance Agent",
            "type":"Services"
        }
    ],
    "sg:phone":"+1 229 423 4391",
    "sg:postcode":"31750",
    "sg:province":"GA",
    "sg:website":"www.libnat.com",
    "wof:name":"Liberty National Insurance Co",
    "wof:placetype":"venue"
},
  "geometry": {"coordinates":[-83.2559,31.71457],"type":"Point"}
}