{
  "type": "Feature",
  "properties": {
    "iso:country":"US",
    "sg:address":"1912 Driftwood Dr",
    "sg:city":"Augusta",
    "sg:classifiers":[
        {
            "category":"Shopping",
            "subcategory":"Clothing, Apparel, & Fashions",
            "type":"Retail Goods"
        }
    ],
    "sg:phone":"+1 706 834 4024",
    "sg:postcode":"30909",
    "sg:province":"GA",
    "wof:name":"Conner's Suits & Accessories",
    "wof:placetype":"venue"
},
  "geometry": {"coordinates":[-82.05314300000001,33.464234],"type":"Point"}
}