{
  "type": "Feature",
  "properties": {
    "addr:full":"1010 8th St W Tifton GA 31794",
    "addr:housenumber":"1010",
    "addr:postcode":"31794",
    "addr:street":"8Th St W",
    "iso:country":"US",
    "sg:address":"1010 8th St W",
    "sg:city":"Tifton",
    "sg:classifiers":[
        {
            "category":"Food & Beverages",
            "subcategory":"Groceries & Convenience Stores",
            "type":"Retail Goods"
        }
    ],
    "sg:phone":"+1 229 388 9126",
    "sg:postcode":"31794",
    "sg:province":"GA",
    "wof:name":"Quick Stop",
    "wof:placetype":"venue"
},
  "geometry": {"coordinates":[-83.52650800000001,31.463372],"type":"Point"}
}