{
  "type": "Feature",
  "properties": {
    "addr:full":"1820 Water Pl SE Atlanta GA 30339",
    "addr:housenumber":"1820",
    "addr:postcode":"30339",
    "addr:street":"Water Pl Se",
    "iso:country":"US",
    "sg:address":"1820 Water Pl SE",
    "sg:city":"Atlanta",
    "sg:classifiers":[
        {
            "category":"Health Services",
            "subcategory":"Health Practitioner",
            "type":"Services"
        }
    ],
    "sg:phone":"+1 770 956 0554",
    "sg:postcode":"30339",
    "sg:province":"GA",
    "sg:tags":[
        "hypnotherapy",
        "hypnotist"
    ],
    "wof:name":"Marion Massie Clh",
    "wof:placetype":"venue"
},
  "geometry": {"coordinates":[-84.484077,33.908392],"type":"Point"}
}