{
  "type": "Feature",
  "properties": {
    "iso:country":"US",
    "sg:address":"406 Pleasant Hill Rd NW",
    "sg:city":"Lilburn",
    "sg:classifiers":[
        {
            "category":"Retail",
            "subcategory":"Auto Repair",
            "type":"Services"
        }
    ],
    "sg:phone":"+1 770 921 1547",
    "sg:postcode":"30047",
    "sg:province":"GA",
    "sg:website":"www.ntb.com",
    "wof:name":"Ntb-National Tire & Battery",
    "wof:placetype":"venue"
},
  "geometry": {"coordinates":[-84.112602,33.9091],"type":"Point"}
}