{
  "type": "Feature",
  "properties": {
    "iso:country":"US",
    "sg:address":"152 Mills Lindsey School Rd",
    "sg:city":"Warthen",
    "sg:classifiers":[
        {
            "category":"Farming",
            "subcategory":"Livestock Farm",
            "type":"Manufacturing & Wholesale Goods"
        }
    ],
    "sg:phone":"+1 478 552 3271",
    "sg:postcode":"31094",
    "sg:province":"GA",
    "sg:tags":[
        "animal",
        "general"
    ],
    "wof:name":"C & H Farm Barn Inc",
    "wof:placetype":"venue"
},
  "geometry": {"coordinates":[-82.837541,33.129239],"type":"Point"}
}