{
  "type": "Feature",
  "properties": {
    "addr:full":"3404 Lakeview Lndg Lithonia GA 30038",
    "addr:housenumber":"3404",
    "addr:postcode":"30038",
    "addr:street":"Lakeview Lndg",
    "iso:country":"US",
    "sg:address":"3404 Lakeview Lndg",
    "sg:city":"Lithonia",
    "sg:classifiers":[
        {
            "category":"Manufacturing",
            "subcategory":"Electronics",
            "type":"Manufacturing & Wholesale Goods"
        },
        {
            "category":"Shopping",
            "subcategory":"Computers & Home Electronics",
            "type":"Retail Goods"
        }
    ],
    "sg:phone":"+1 404 488 0484",
    "sg:postcode":"30038",
    "sg:province":"GA",
    "sg:tags":[
        "supplies-wholesale",
        "manufacturer",
        "electronic",
        "consumer",
        "equipment"
    ],
    "wof:name":"Church Media Consulting",
    "wof:placetype":"venue"
},
  "geometry": {"coordinates":[-84.139797,33.683023],"type":"Point"}
}