{
  "type": "Feature",
  "properties": {
    "addr:full":"208 Pine Crest Dr Cumming GA 30040",
    "addr:housenumber":"208",
    "addr:postcode":"30040",
    "addr:street":"Pine Crest Dr",
    "iso:country":"US",
    "sg:address":"208 Pine Crest Dr",
    "sg:city":"Cumming",
    "sg:classifiers":[
        {
            "category":"Manufacturing",
            "subcategory":"Printing",
            "type":"Manufacturing & Wholesale Goods"
        }
    ],
    "sg:phone":"+1 770 887 5253",
    "sg:postcode":"30040",
    "sg:province":"GA",
    "sg:tags":[
        "publisher"
    ],
    "wof:name":"Beasley Report",
    "wof:placetype":"venue"
},
  "geometry": {"coordinates":[-84.15801,34.2176],"type":"Point"}
}