{
  "type": "Feature",
  "properties": {
    "addr:full":"64 Perimeter Center Pl Atlanta GA 30346",
    "addr:housenumber":"64",
    "addr:postcode":"30346",
    "addr:street":"Perimeter Center Pl",
    "iso:country":"US",
    "sg:address":"64 Perimeter Center Pl",
    "sg:city":"Atlanta",
    "sg:classifiers":[
        {
            "category":"Restaurant",
            "type":"Food & Drink"
        }
    ],
    "sg:phone":"+1 770 390 0776",
    "sg:postcode":"30346",
    "sg:province":"GA",
    "wof:name":"Cafe 64",
    "wof:placetype":"venue"
},
  "geometry": {"coordinates":[-84.34067,33.929223],"type":"Point"}
}