{
  "type": "Feature",
  "properties": {
    "iso:country":"US",
    "sg:address":"325 Perkins Rd",
    "sg:city":"Milner",
    "sg:classifiers":[
        {
            "category":"Building & Trades",
            "subcategory":"Cleaning & Sanitation",
            "type":"Services"
        }
    ],
    "sg:phone":"+1 770 229 9907",
    "sg:postcode":"30257",
    "sg:province":"GA",
    "sg:tags":[
        "maintenance"
    ],
    "wof:name":"First Class Cleaning By Karen",
    "wof:placetype":"venue"
},
  "geometry": {"coordinates":[-84.25979,33.153333],"type":"Point"}
}