{
  "type": "Feature",
  "properties": {
    "addr:full":"200 Montgomery Ferry Dr NE Atlanta GA 30309",
    "addr:housenumber":"200",
    "addr:postcode":"30309",
    "addr:street":"Montgomery Ferry Dr Ne",
    "iso:country":"US",
    "sg:address":"200 Montgomery Ferry Dr NE",
    "sg:city":"Atlanta",
    "sg:classifiers":[
        {
            "category":"Professional",
            "subcategory":"Business Services",
            "type":"Services"
        }
    ],
    "sg:phone":"+1 404 575 0898",
    "sg:postcode":"30309",
    "sg:province":"GA",
    "sg:tags":[
        "management"
    ],
    "wof:name":"Wellspring Resource Management",
    "wof:placetype":"venue"
},
  "geometry": {"coordinates":[-84.37493499999999,33.800745],"type":"Point"}
}