{
  "type": "Feature",
  "properties": {
    "addr:full":"3265 Beechwood Dr SE Marietta GA 30067",
    "addr:housenumber":"3265",
    "addr:postcode":"30067",
    "addr:street":"Beechwood Dr Se",
    "iso:country":"US",
    "sg:address":"3265 Beechwood Dr SE",
    "sg:city":"Marietta",
    "sg:classifiers":[
        {
            "category":"Banks & Credit Unions",
            "subcategory":"Bank",
            "type":"Services"
        },
        {
            "category":"Shopping",
            "subcategory":"Used Merchandise",
            "type":"Retail Goods"
        }
    ],
    "sg:phone":"+1 770 955 7638",
    "sg:postcode":"30067",
    "sg:province":"GA",
    "sg:tags":[
        "shop",
        "second",
        "resale",
        "hand"
    ],
    "wof:name":"Pb & J Consignment",
    "wof:placetype":"venue"
},
  "geometry": {"coordinates":[-84.45792899999999,33.922442],"type":"Point"}
}