{
  "type": "Feature",
  "properties": {
    "addr:full":"7776 McGinnis Ferry Rd Suwanee GA 30024",
    "addr:housenumber":"7776",
    "addr:postcode":"30024",
    "addr:street":"Mcginnis Ferry Rd",
    "iso:country":"US",
    "sg:address":"7776 McGinnis Ferry Rd",
    "sg:city":"Suwanee",
    "sg:classifiers":[
        {
            "category":"Personal",
            "subcategory":"Nail Salon",
            "type":"Services"
        }
    ],
    "sg:phone":"+1 770 232 9518",
    "sg:postcode":"30024",
    "sg:province":"GA",
    "wof:name":"V Nails",
    "wof:placetype":"venue"
},
  "geometry": {"coordinates":[-84.129615,34.05545],"type":"Point"}
}