{
  "type": "Feature",
  "properties": {
    "iso:country":"US",
    "sg:address":"212 Arrowhead Blvd",
    "sg:city":"Jonesboro",
    "sg:classifiers":[
        {
            "category":"Social Services",
            "type":"Services"
        }
    ],
    "sg:phone":"+1 770 471 8110",
    "sg:postcode":"30236",
    "sg:province":"GA",
    "sg:tags":[
        "health"
    ],
    "wof:name":"Thomas C Burns PHD",
    "wof:placetype":"venue"
},
  "geometry": {"coordinates":[-84.37227900000001,33.575775],"type":"Point"}
}