{
  "type": "Feature",
  "properties": {
    "iso:country":"US",
    "sg:address":"2025 Satellite Pointe",
    "sg:city":"Duluth",
    "sg:classifiers":[
        {
            "category":"Food & Beverages",
            "subcategory":"Groceries & Convenience Stores",
            "type":"Retail Goods"
        }
    ],
    "sg:phone":"+1 770 263 9044",
    "sg:postcode":"30096",
    "sg:province":"GA",
    "sg:tags":[
        "product"
    ],
    "wof:name":"Wholefoods",
    "wof:placetype":"venue"
},
  "geometry": {"coordinates":[-84.148252,33.947566],"type":"Point"}
}