{
  "type": "Feature",
  "properties": {
    "addr:full":"1027 Hogansville Rd Lagrange GA 30241",
    "addr:housenumber":"1027",
    "addr:postcode":"30241",
    "addr:street":"Hogansville Rd",
    "iso:country":"US",
    "sg:address":"1027 Hogansville Rd",
    "sg:city":"Lagrange",
    "sg:classifiers":[
        {
            "category":"Autos & Motor Vehicles",
            "subcategory":"Auto Supplies",
            "type":"Retail Goods"
        }
    ],
    "sg:phone":"+1 706 884 3383",
    "sg:postcode":"30241",
    "sg:province":"GA",
    "sg:tags":[
        "automobile",
        "parts"
    ],
    "wof:name":"Carquest Auto Parts",
    "wof:placetype":"venue"
},
  "geometry": {"coordinates":[-85.009828,33.049546],"type":"Point"}
}