{
  "type": "Feature",
  "properties": {
    "addr:full":"195 Weeks St Decatur GA 30030",
    "addr:housenumber":"195",
    "addr:postcode":"30030",
    "addr:street":"Weeks St",
    "iso:country":"US",
    "sg:address":"195 Weeks St",
    "sg:city":"Decatur",
    "sg:classifiers":[
        {
            "category":"Retail",
            "subcategory":"Auto Repair",
            "type":"Services"
        }
    ],
    "sg:phone":"+1 404 378 3520",
    "sg:postcode":"30030",
    "sg:province":"GA",
    "sg:tags":[
        "repairing",
        "automobile"
    ],
    "wof:name":"Clarke's Auto Repair & Svc",
    "wof:placetype":"venue"
},
  "geometry": {"coordinates":[-84.28694,33.772979],"type":"Point"}
}