{
  "type": "Feature",
  "properties": {
    "addr:full":"1948 Wesley Chapel Rd Decatur GA 30035",
    "addr:housenumber":"1948",
    "addr:postcode":"30035",
    "addr:street":"Wesley Chapel Rd",
    "iso:country":"US",
    "sg:address":"1948 Wesley Chapel Rd",
    "sg:city":"Decatur",
    "sg:classifiers":[
        {
            "category":"Shopping",
            "type":"Retail Goods"
        }
    ],
    "sg:phone":"+1 404 286 3492",
    "sg:postcode":"30035",
    "sg:province":"GA",
    "sg:tags":[
        "merchandise"
    ],
    "wof:name":"Smart Choices",
    "wof:placetype":"venue"
},
  "geometry": {"coordinates":[-84.21372700000001,33.733996],"type":"Point"}
}