{
  "type": "Feature",
  "properties": {
    "iso:country":"US",
    "sg:address":"1657 Dorsey Ave",
    "sg:city":"Atlanta",
    "sg:classifiers":[
        {
            "category":"Personal",
            "subcategory":"Beauty Salon",
            "type":"Services"
        }
    ],
    "sg:phone":"+1 404 762 0095",
    "sg:postcode":"30344",
    "sg:province":"GA",
    "sg:tags":[
        "shop"
    ],
    "wof:name":"Waymaker Full Service Salon",
    "wof:placetype":"venue"
},
  "geometry": {"coordinates":[-84.44393599999999,33.677361],"type":"Point"}
}