{
  "type": "Feature",
  "properties": {
    "addr:full":"4205 N Point Pkwy Ste C Alpharetta GA 30022",
    "addr:housenumber":"4205",
    "addr:postcode":"30022",
    "addr:street":"N Point Pkwy Ste C",
    "iso:country":"US",
    "sg:address":"4205 N Point Pkwy Ste C",
    "sg:city":"Alpharetta",
    "sg:classifiers":[
        {
            "category":"Health Services",
            "subcategory":"Dentist",
            "type":"Services"
        }
    ],
    "sg:phone":"+1 770 664 4936",
    "sg:postcode":"30022",
    "sg:province":"GA",
    "sg:tags":[
        "pediatric"
    ],
    "wof:name":"Alpharetta Children's Dentistry",
    "wof:placetype":"venue"
},
  "geometry": {"coordinates":[-84.264,34.063999],"type":"Point"}
}