{
  "type": "Feature",
  "properties": {
    "addr:full":"115 Commerce Dr Fayetteville GA 30214",
    "addr:housenumber":"115",
    "addr:postcode":"30214",
    "addr:street":"Commerce Dr",
    "iso:country":"US",
    "sg:address":"115 Commerce Dr",
    "sg:city":"Fayetteville",
    "sg:classifiers":[
        {
            "category":"Real Estate",
            "subcategory":"Real Estate Services",
            "type":"Services"
        }
    ],
    "sg:phone":"+1 678 817 5776",
    "sg:postcode":"30214",
    "sg:province":"GA",
    "sg:tags":[
        "management",
        "property"
    ],
    "wof:name":"Lighthouse Property Management",
    "wof:placetype":"venue"
},
  "geometry": {"coordinates":[-84.451894,33.464213],"type":"Point"}
}