{
  "type": "Feature",
  "properties": {
    "addr:full":"765 Pickens Dr Exd Marietta GA 30062",
    "addr:housenumber":"765",
    "addr:postcode":"30062",
    "addr:street":"Pickens Dr Exd",
    "iso:country":"US",
    "sg:address":"765 Pickens Dr Exd",
    "sg:city":"Marietta",
    "sg:classifiers":[
        {
            "category":"Building & Trades",
            "subcategory":"Pest Control",
            "type":"Services"
        }
    ],
    "sg:phone":"+1 770 489 9493",
    "sg:postcode":"30062",
    "sg:province":"GA",
    "sg:tags":[
        "provides"
    ],
    "wof:name":"Terminix",
    "wof:placetype":"venue"
},
  "geometry": {"coordinates":[-84.522938,33.967985],"type":"Point"}
}