{
  "type": "Feature",
  "properties": {
    "iso:country":"US",
    "sg:address":"2513 Royal Pl",
    "sg:city":"Tucker",
    "sg:classifiers":[
        {
            "category":"Manufacturing",
            "subcategory":"Tools & Machinery",
            "type":"Manufacturing & Wholesale Goods"
        },
        {
            "category":"Retail",
            "subcategory":"Repair Shop",
            "type":"Services"
        },
        {
            "category":"Retail",
            "subcategory":"Auto Repair",
            "type":"Services"
        }
    ],
    "sg:phone":"+1 770 938 3365",
    "sg:postcode":"30084",
    "sg:province":"GA",
    "sg:tags":[
        "automobile",
        "machine",
        "machinery-rebuild"
    ],
    "wof:name":"Adventures In Machining Inc",
    "wof:placetype":"venue"
},
  "geometry": {"coordinates":[-84.18532399999999,33.858646],"type":"Point"}
}