{
  "type": "Feature",
  "properties": {
    "addr:full":"894 Stekoa Falls Rd Clayton GA 30525",
    "addr:housenumber":"894",
    "addr:postcode":"30525",
    "addr:street":"Stekoa Falls Rd",
    "iso:country":"US",
    "sg:address":"894 Stekoa Falls Rd",
    "sg:city":"Clayton",
    "sg:classifiers":[
        {
            "category":"Retail",
            "subcategory":"Auto Repair",
            "type":"Services"
        }
    ],
    "sg:phone":"+1 706 782 3988",
    "sg:postcode":"30525",
    "sg:province":"GA",
    "sg:tags":[
        "automotive"
    ],
    "wof:name":"Donald G Miller",
    "wof:placetype":"venue"
},
  "geometry": {"coordinates":[-83.400738,34.858189],"type":"Point"}
}