{
  "type": "Feature",
  "properties": {
    "addr:full":"115 Heather Ridge Fairburn GA 30213",
    "addr:housenumber":"115",
    "addr:postcode":"30213",
    "addr:street":"Heather Ridge",
    "iso:country":"US",
    "sg:address":"115 Heather Ridge",
    "sg:city":"Fairburn",
    "sg:classifiers":[
        {
            "category":"Retail",
            "subcategory":"Auto Repair",
            "type":"Services"
        }
    ],
    "sg:phone":"+1 678 817 5047",
    "sg:postcode":"30213",
    "sg:province":"GA",
    "sg:tags":[
        "car",
        "used",
        "towing",
        "sales"
    ],
    "wof:name":"RNS Towing Inc",
    "wof:placetype":"venue"
},
  "geometry": {"coordinates":[-84.466444,33.535745],"type":"Point"}
}