{
  "type": "Feature",
  "properties": {
    "iso:country":"US",
    "sg:address":"1700 James Ray Dr SE",
    "sg:city":"Marietta",
    "sg:classifiers":[
        {
            "category":"Building & Trades",
            "subcategory":"Locksmith",
            "type":"Services"
        }
    ],
    "sg:phone":"+1 770 308 0043",
    "sg:postcode":"30060",
    "sg:province":"GA",
    "sg:tags":[
        "key"
    ],
    "wof:name":"A Locksmith A 24 7",
    "wof:placetype":"venue"
},
  "geometry": {"coordinates":[-84.542965,33.910981],"type":"Point"}
}