{
  "type": "Feature",
  "properties": {
    "iso:country":"US",
    "sg:address":"265 Jonesboro Rd",
    "sg:city":"Mcdonough",
    "sg:classifiers":[
        {
            "category":"Restaurant",
            "type":"Food & Drink"
        }
    ],
    "sg:phone":"+1 770 914 2323",
    "sg:postcode":"30253",
    "sg:province":"GA",
    "sg:tags":[
        "style",
        "family",
        "lunch",
        "american",
        "brunch",
        "breakfast"
    ],
    "sg:website":"http://www.wafflehouse.com",
    "wof:name":"Waffle House",
    "wof:placetype":"venue"
},
  "geometry": {"coordinates":[-84.168848,33.454556],"type":"Point"}
}