{
  "type": "Feature",
  "properties": {
    "iso:country":"US",
    "sg:address":"1872 Independence Sq",
    "sg:city":"Atlanta",
    "sg:classifiers":[
        {
            "category":"Banks & Credit Unions",
            "subcategory":"Bank",
            "type":"Services"
        }
    ],
    "sg:phone":"+1 678 240 2001",
    "sg:postcode":"30338",
    "sg:province":"GA",
    "sg:tags":[
        "loan",
        "real estate"
    ],
    "wof:name":"S E Home Loans",
    "wof:placetype":"venue"
},
  "geometry": {"coordinates":[-84.313695,33.930423],"type":"Point"}
}