{
  "type": "Feature",
  "properties": {
    "iso:country":"US",
    "sg:address":"396 Thompson St",
    "sg:city":"Alpharetta",
    "sg:classifiers":[
        {
            "category":"Retail",
            "subcategory":"Auto Repair",
            "type":"Services"
        }
    ],
    "sg:phone":"+1 770 475 7817",
    "sg:postcode":"30004",
    "sg:province":"GA",
    "sg:tags":[
        "automotive",
        "sport"
    ],
    "wof:name":"Green Racing Inc",
    "wof:placetype":"venue"
},
  "geometry": {"coordinates":[-84.282477,34.071093],"type":"Point"}
}