{
  "type": "Feature",
  "properties": {
    "iso:country":"US",
    "sg:address":"6720 Lancaster Cir",
    "sg:city":"Cumming",
    "sg:classifiers":[
        {
            "category":"Real Estate",
            "subcategory":"Real Estate Agent",
            "type":"Services"
        }
    ],
    "sg:phone":"+1 678 938 0702",
    "sg:postcode":"30040",
    "sg:province":"GA",
    "wof:name":"Beaver Creek Real Estate",
    "wof:placetype":"venue"
},
  "geometry": {"coordinates":[-84.209453,34.172031],"type":"Point"}
}