{
  "type": "Feature",
  "properties": {
    "iso:country":"US",
    "sg:address":"4639 Briar Hill Cove",
    "sg:city":"Duluth",
    "sg:classifiers":[
        {
            "category":"Utilities",
            "subcategory":"Telephone",
            "type":"Services"
        }
    ],
    "sg:phone":"+1 678 361 0444",
    "sg:postcode":"30096",
    "sg:province":"GA",
    "sg:tags":[
        "communications"
    ],
    "wof:name":"Nubian Networks LLC",
    "wof:placetype":"venue"
},
  "geometry": {"coordinates":[-84.191721,33.974287],"type":"Point"}
}