{
  "type": "Feature",
  "properties": {
    "iso:country":"US",
    "sg:address":"1293 Sand Hill Shady Grove Rd",
    "sg:city":"Carrollton",
    "sg:classifiers":[
        {
            "category":"Organizations",
            "subcategory":"Religious Organization",
            "type":"Services"
        }
    ],
    "sg:phone":"+1 770 834 8408",
    "sg:postcode":"30116",
    "sg:province":"GA",
    "sg:tags":[
        "church"
    ],
    "wof:name":"Shady Grove Baptist Church",
    "wof:placetype":"venue"
},
  "geometry": {"coordinates":[-85.021524,33.640225],"type":"Point"}
}