{
  "type": "Feature",
  "properties": {
    "iso:country":"US",
    "sg:address":"1019 Perry Cv",
    "sg:city":"Savannah",
    "sg:classifiers":[
        {
            "category":"Building & Trades",
            "subcategory":"Landscaping Services",
            "type":"Services"
        }
    ],
    "sg:phone":"+1 912 897 6588",
    "sg:postcode":"31410",
    "sg:province":"GA",
    "sg:tags":[
        "tree"
    ],
    "wof:name":"Herrington Tree Svc",
    "wof:placetype":"venue"
},
  "geometry": {"coordinates":[-81.015247,32.046605],"type":"Point"}
}