{
  "type": "Feature",
  "properties": {
    "iso:country":"US",
    "sg:address":"4740 Hammermill Rd",
    "sg:city":"Tucker",
    "sg:classifiers":[
        {
            "category":"Sports & Exercise",
            "subcategory":"Golf",
            "type":"Entertainment"
        }
    ],
    "sg:phone":"+1 770 493 9253",
    "sg:postcode":"30084",
    "sg:province":"GA",
    "sg:tags":[
        "instruction"
    ],
    "wof:name":"Smoke Rise Golf & Country Club Inc.",
    "wof:placetype":"venue"
},
  "geometry": {"coordinates":[-84.19767400000001,33.836941],"type":"Point"}
}