{
  "type": "Feature",
  "properties": {
    "iso:country":"US",
    "sg:address":"363 N Main St",
    "sg:city":"Reidsville",
    "sg:classifiers":[
        {
            "category":"Organizations",
            "subcategory":"Religious Organization",
            "type":"Services"
        }
    ],
    "sg:phone":"+1 912 557 1918",
    "sg:postcode":"30453",
    "sg:province":"GA",
    "sg:tags":[
        "church"
    ],
    "wof:name":"Twin Oaks Baptist Church",
    "wof:placetype":"venue"
},
  "geometry": {"coordinates":[-82.121291,32.099677],"type":"Point"}
}