{
  "type": "Feature",
  "properties": {
    "iso:country":"US",
    "sg:address":"909 Boxwood Dr",
    "sg:city":"Savannah",
    "sg:classifiers":[
        {
            "category":"Shopping",
            "subcategory":"Bicycles & Sporting Goods",
            "type":"Retail Goods"
        }
    ],
    "sg:phone":"+1 912 657 9484",
    "sg:postcode":"31410",
    "sg:province":"GA",
    "wof:name":"Joeys Bait House",
    "wof:placetype":"venue"
},
  "geometry": {"coordinates":[-80.96843200000001,32.003373],"type":"Point"}
}