{
  "type": "Feature",
  "properties": {
    "addr:full":"1930 Statham Rd Statham GA 30666",
    "addr:housenumber":"1930",
    "addr:postcode":"30666",
    "addr:street":"Statham Rd",
    "iso:country":"US",
    "sg:address":"1930 Statham Rd",
    "sg:city":"Statham",
    "sg:classifiers":[
        {
            "category":"Manufacturing",
            "subcategory":"Retail Goods",
            "type":"Manufacturing & Wholesale Goods"
        }
    ],
    "sg:phone":"+1 770 725 7877",
    "sg:postcode":"30666",
    "sg:province":"GA",
    "sg:tags":[
        "product",
        "mfg"
    ],
    "wof:name":"Piedmont Industries",
    "wof:placetype":"venue"
},
  "geometry": {"coordinates":[-83.59058,33.989085],"type":"Point"}
}