{
  "type": "Feature",
  "properties": {
    "iso:country":"US",
    "sg:address":"1090 Northchase Pkwy SE",
    "sg:city":"Marietta",
    "sg:classifiers":[
        {
            "category":"Wholesale",
            "subcategory":"Hardware",
            "type":"Manufacturing & Wholesale Goods"
        },
        {
            "category":"Professional",
            "type":"Services"
        }
    ],
    "sg:phone":"+1 770 984 3254",
    "sg:postcode":"30067",
    "sg:province":"GA",
    "sg:tags":[
        "establishment",
        "refrigeration"
    ],
    "wof:name":"Northfield Freezing Systems",
    "wof:placetype":"venue"
},
  "geometry": {"coordinates":[-84.47974000000001,33.926506],"type":"Point"}
}