{
  "type": "Feature",
  "properties": {
    "iso:country":"US",
    "sg:address":"1610 Main St NE",
    "sg:city":"Conyers",
    "sg:classifiers":[
        {
            "category":"Organizations",
            "subcategory":"Religious Organization",
            "type":"Services"
        }
    ],
    "sg:phone":"+1 770 918 0916",
    "sg:postcode":"30012",
    "sg:province":"GA",
    "sg:tags":[
        "church"
    ],
    "wof:name":"Word Of God Fellowship Ctr",
    "wof:placetype":"venue"
},
  "geometry": {"coordinates":[-83.99263000000001,33.683589],"type":"Point"}
}