{
  "type": "Feature",
  "properties": {
    "iso:country":"US",
    "sg:address":"566 16th Ave",
    "sg:city":"Albany",
    "sg:classifiers":[
        {
            "category":"Professional",
            "type":"Services"
        }
    ],
    "sg:phone":"+1 229 438 7244",
    "sg:postcode":"31701",
    "sg:province":"GA",
    "wof:name":"P O Cone",
    "wof:placetype":"venue"
},
  "geometry": {"coordinates":[-84.164091,31.608766],"type":"Point"}
}