{
  "type": "Feature",
  "properties": {
    "addr:full":"297 Omega Dr Lawrenceville GA 30044",
    "addr:housenumber":"297",
    "addr:postcode":"30044",
    "addr:street":"Omega Dr",
    "iso:country":"US",
    "sg:address":"297 Omega Dr",
    "sg:city":"Lawrenceville",
    "sg:classifiers":[
        {
            "category":"Professional",
            "type":"Services"
        }
    ],
    "sg:phone":"+1 678 467 1466",
    "sg:postcode":"30044",
    "sg:province":"GA",
    "wof:name":"A Gadget Guru",
    "wof:placetype":"venue"
},
  "geometry": {"coordinates":[-84.09305500000001,33.911131],"type":"Point"}
}