{
  "type": "Feature",
  "properties": {
    "iso:country":"US",
    "sg:address":"11660 Alpharetta Hwy",
    "sg:city":"Roswell",
    "sg:classifiers":[
        {
            "category":"Shopping",
            "subcategory":"Computers & Home Electronics",
            "type":"Retail Goods"
        }
    ],
    "sg:phone":"+1 678 393 8748",
    "sg:postcode":"30076",
    "sg:province":"GA",
    "sg:tags":[
        "software"
    ],
    "wof:name":"Mdvision",
    "wof:placetype":"venue"
},
  "geometry": {"coordinates":[-84.32037699999999,34.065286],"type":"Point"}
}