{
  "type": "Feature",
  "properties": {
    "addr:full":"835 Flint Ave Albany GA 31701",
    "addr:housenumber":"835",
    "addr:postcode":"31701",
    "addr:street":"Flint Ave",
    "iso:country":"US",
    "sg:address":"835 Flint Ave",
    "sg:city":"Albany",
    "sg:classifiers":[
        {
            "category":"Retail",
            "subcategory":"Repair Shop",
            "type":"Services"
        }
    ],
    "sg:phone":"+1 229 420 4066",
    "sg:postcode":"31701",
    "sg:province":"GA",
    "wof:name":"Alltech Service Company",
    "wof:placetype":"venue"
},
  "geometry": {"coordinates":[-84.17050500000001,31.580025],"type":"Point"}
}