{
  "type": "Feature",
  "properties": {
    "iso:country":"US",
    "sg:address":"1912 1st Ave",
    "sg:city":"Augusta",
    "sg:classifiers":[
        {
            "category":"Organizations",
            "subcategory":"Religious Organization",
            "type":"Services"
        }
    ],
    "sg:phone":"+1 706 722 1053",
    "sg:postcode":"30901",
    "sg:province":"GA",
    "wof:name":"Church God In Love By Jesus",
    "wof:placetype":"venue"
},
  "geometry": {"coordinates":[-82.000756,33.444473],"type":"Point"}
}