{
  "type": "Feature",
  "properties": {
    "addr:full":"557 Parker Dairy Rd Dublin GA 31021",
    "addr:housenumber":"557",
    "addr:postcode":"31021",
    "addr:street":"Parker Dairy Rd",
    "iso:country":"US",
    "sg:address":"557 Parker Dairy Rd",
    "sg:city":"Dublin",
    "sg:classifiers":[
        {
            "category":"Building & Trades",
            "subcategory":"Construction",
            "type":"Services"
        }
    ],
    "sg:phone":"+1 478 275 0682",
    "sg:postcode":"31021",
    "sg:province":"GA",
    "sg:tags":[
        "system",
        "contractor",
        "air conditioning"
    ],
    "wof:name":"Gregory Heating Cooling",
    "wof:placetype":"venue"
},
  "geometry": {"coordinates":[-82.919888,32.579986],"type":"Point"}
}