{
  "type": "Feature",
  "properties": {
    "addr:full":"3733 James Ed Rd Gainesville GA 30506",
    "addr:housenumber":"3733",
    "addr:postcode":"30506",
    "addr:street":"James Ed Rd",
    "iso:country":"US",
    "sg:address":"3733 James Ed Rd",
    "sg:city":"Gainesville",
    "sg:classifiers":[
        {
            "category":"Building & Trades",
            "subcategory":"Construction",
            "type":"Services"
        }
    ],
    "sg:phone":"+1 770 535 1514",
    "sg:postcode":"30506",
    "sg:province":"GA",
    "sg:tags":[
        "siding",
        "contractor"
    ],
    "wof:name":"Abernathy Vinyl Siding",
    "wof:placetype":"venue"
},
  "geometry": {"coordinates":[-83.81356700000001,34.389189],"type":"Point"}
}