{
  "type": "Feature",
  "properties": {
    "addr:full":"341 Hill St SE Atlanta GA 30312",
    "addr:housenumber":"341",
    "addr:postcode":"30312",
    "addr:street":"Hill St Se",
    "iso:country":"US",
    "sg:address":"341 Hill St SE",
    "sg:city":"Atlanta",
    "sg:classifiers":[
        {
            "category":"Organizations",
            "subcategory":"Religious Organization",
            "type":"Services"
        }
    ],
    "sg:phone":"+1 404 222 0949",
    "sg:postcode":"30312",
    "sg:province":"GA",
    "sg:tags":[
        "church"
    ],
    "wof:name":"Faith Temple Missionary Baptist Church",
    "wof:placetype":"venue"
},
  "geometry": {"coordinates":[-84.379733,33.74539],"type":"Point"}
}