{
  "type": "Feature",
  "properties": {
    "iso:country":"US",
    "sg:address":"1812 Old Jackson Rd",
    "sg:city":"Locust Grove",
    "sg:classifiers":[
        {
            "category":"Building & Trades",
            "subcategory":"Landscaping Services",
            "type":"Services"
        }
    ],
    "sg:phone":"+1 770 898 5651",
    "sg:postcode":"30248",
    "sg:province":"GA",
    "sg:tags":[
        "plant",
        "sales"
    ],
    "wof:name":"Tree House Farm",
    "wof:placetype":"venue"
},
  "geometry": {"coordinates":[-84.064364,33.388305],"type":"Point"}
}