{
  "type": "Feature",
  "properties": {
    "iso:country":"US",
    "sg:address":"1263 Palmer St",
    "sg:city":"Louisville",
    "sg:classifiers":[
        {
            "category":"Shopping",
            "type":"Retail Goods"
        }
    ],
    "sg:phone":"+1 478 625 8407",
    "sg:postcode":"30434",
    "sg:province":"GA",
    "sg:tags":[
        "cosmetic",
        "perfume"
    ],
    "wof:name":"Willie's Cosmetics",
    "wof:placetype":"venue"
},
  "geometry": {"coordinates":[-82.391245,33.009344],"type":"Point"}
}