{
  "type": "Feature",
  "properties": {
    "iso:country":"US",
    "sg:address":"990 Iris Dr SW",
    "sg:city":"Conyers",
    "sg:classifiers":[
        {
            "category":"Insurance",
            "subcategory":"Insurance Agent",
            "type":"Services"
        }
    ],
    "sg:phone":"+1 770 922 5555",
    "sg:postcode":"30094",
    "sg:province":"GA",
    "wof:name":"Harwell & Associates",
    "wof:placetype":"venue"
},
  "geometry": {"coordinates":[-84.020458,33.658236],"type":"Point"}
}