{
  "type": "Feature",
  "properties": {
    "iso:country":"US",
    "sg:address":"1480 Belmont Ave SW",
    "sg:city":"Atlanta",
    "sg:classifiers":[
        {
            "category":"Shopping",
            "subcategory":"Used Merchandise",
            "type":"Retail Goods"
        }
    ],
    "sg:phone":"+1 404 755 4495",
    "sg:postcode":"30310",
    "sg:province":"GA",
    "wof:name":"Antic Arts & Crafts",
    "wof:placetype":"venue"
},
  "geometry": {"coordinates":[-84.40983300000001,33.715776],"type":"Point"}
}