{
  "type": "Feature",
  "properties": {
    "iso:country":"US",
    "sg:address":"7104 Stonington Dr NE",
    "sg:city":"Atlanta",
    "sg:classifiers":[
        {
            "category":"Professional",
            "type":"Services"
        }
    ],
    "sg:phone":"+1 770 350 1101",
    "sg:postcode":"30328",
    "sg:province":"GA",
    "sg:tags":[
        "establishment"
    ],
    "wof:name":"Lisa Grider Design LLC",
    "wof:placetype":"venue"
},
  "geometry": {"coordinates":[-84.373294,33.948841],"type":"Point"}
}