{
  "type": "Feature",
  "properties": {
    "addr:full":"5975 State Bridge Rd Duluth GA 30097",
    "addr:housenumber":"5975",
    "addr:postcode":"30097",
    "addr:street":"State Bridge Rd",
    "iso:country":"US",
    "sg:address":"5975 State Bridge Rd",
    "sg:city":"Duluth",
    "sg:classifiers":[
        {
            "category":"Place Of Worship",
            "subcategory":"Church",
            "type":"Public Place"
        }
    ],
    "sg:phone":"+1 770 476 4441",
    "sg:postcode":"30097",
    "sg:province":"GA",
    "sg:website":"www.parkway-baptist.org",
    "wof:name":"Parkway Baptist Church",
    "wof:placetype":"venue"
},
  "geometry": {"coordinates":[-84.183502,34.011398],"type":"Point"}
}