{
  "type": "Feature",
  "properties": {
    "iso:country":"US",
    "sg:address":"1175 Hillary Ln",
    "sg:city":"Lawrenceville",
    "sg:classifiers":[
        {
            "category":"Freight",
            "type":"Transportation"
        }
    ],
    "sg:phone":"+1 678 377 0008",
    "sg:postcode":"30043",
    "sg:province":"GA",
    "sg:tags":[
        "delivery",
        "home",
        "appliance"
    ],
    "wof:name":"Diamond Delivery",
    "wof:placetype":"venue"
},
  "geometry": {"coordinates":[-84.041917,33.986762],"type":"Point"}
}