{
  "type": "Feature",
  "properties": {
    "iso:country":"US",
    "sg:address":"843 Stonebrook Dr",
    "sg:city":"Lithonia",
    "sg:classifiers":[
        {
            "category":"Banks & Credit Unions",
            "subcategory":"Investment Brokerage",
            "type":"Services"
        }
    ],
    "sg:phone":"+1 770 484 6001",
    "sg:postcode":"30058",
    "sg:province":"GA",
    "sg:tags":[
        "advisory",
        "financial"
    ],
    "wof:name":"Regients Financial",
    "wof:placetype":"venue"
},
  "geometry": {"coordinates":[-84.098209,33.769796],"type":"Point"}
}