{
  "type": "Feature",
  "properties": {
    "iso:country":"US",
    "sg:address":"515 Ralph David Abernathy Blvd",
    "sg:city":"Atlanta",
    "sg:classifiers":[
        {
            "category":"Manufacturing",
            "subcategory":"Building Materials",
            "type":"Manufacturing & Wholesale Goods"
        },
        {
            "category":"Home & Garden",
            "subcategory":"Furniture",
            "type":"Retail Goods"
        }
    ],
    "sg:phone":"+1 404 577 5262",
    "sg:postcode":"30312",
    "sg:province":"GA",
    "sg:tags":[
        "equipment",
        "cabinet",
        "wood",
        "kitchen",
        "mfg"
    ],
    "wof:name":"Southern Cabinet Design",
    "wof:placetype":"venue"
},
  "geometry": {"coordinates":[-84.406949,33.737414],"type":"Point"}
}