{
  "type": "Feature",
  "properties": {
    "addr:full":"424 Heard Ave Albany GA 31701",
    "addr:housenumber":"424",
    "addr:postcode":"31701",
    "addr:street":"Heard Ave",
    "iso:country":"US",
    "sg:address":"424 Heard Ave",
    "sg:city":"Albany",
    "sg:classifiers":[
        {
            "category":"Professional",
            "type":"Services"
        }
    ],
    "sg:phone":"+1 229 439 9786",
    "sg:postcode":"31701",
    "sg:province":"GA",
    "wof:name":"Bennie Russell",
    "wof:placetype":"venue"
},
  "geometry": {"coordinates":[-84.156198,31.553671],"type":"Point"}
}