{
  "type": "Feature",
  "properties": {
    "iso:country":"US",
    "sg:address":"6548 State Hwy 92",
    "sg:city":"Acworth",
    "sg:classifiers":[
        {
            "category":"Building & Trades",
            "subcategory":"Cleaning & Sanitation",
            "type":"Services"
        }
    ],
    "sg:phone":"+1 770 592 4444",
    "sg:postcode":"30102",
    "sg:province":"GA",
    "sg:tags":[
        "house"
    ],
    "sg:website":"www.merrymaids.com",
    "wof:name":"Merry Maids Inc",
    "wof:placetype":"venue"
},
  "geometry": {"coordinates":[-84.583702,34.088843],"type":"Point"}
}