{
  "type": "Feature",
  "properties": {
    "addr:full":"2863 Johnson Ferry Rd Marietta GA 30062",
    "addr:housenumber":"2863",
    "addr:postcode":"30062",
    "addr:street":"Johnson Ferry Rd",
    "iso:country":"US",
    "sg:address":"2863 Johnson Ferry Rd",
    "sg:city":"Marietta",
    "sg:classifiers":[
        {
            "category":"Banks & Credit Unions",
            "subcategory":"Bank",
            "type":"Services"
        }
    ],
    "sg:phone":"+1 770 993 5551",
    "sg:postcode":"30062",
    "sg:province":"GA",
    "wof:name":"Flag Bank",
    "wof:placetype":"venue"
},
  "geometry": {"coordinates":[-84.42890199999999,34.018299],"type":"Point"}
}