{
  "type": "Feature",
  "properties": {
    "addr:full":"5029 Lavista Rd Tucker GA 30084",
    "addr:housenumber":"5029",
    "addr:postcode":"30084",
    "addr:street":"Lavista Rd",
    "iso:country":"US",
    "sg:address":"5029 Lavista Rd",
    "sg:city":"Tucker",
    "sg:classifiers":[
        {
            "category":"Autos & Motor Vehicles",
            "subcategory":"Auto Supplies",
            "type":"Retail Goods"
        }
    ],
    "sg:phone":"+1 770 491 8120",
    "sg:postcode":"30084",
    "sg:province":"GA",
    "sg:tags":[
        "tire"
    ],
    "sg:website":"www.wilkinsontire.com",
    "wof:name":"Wilkinson Tire Center Inc",
    "wof:placetype":"venue"
},
  "geometry": {"coordinates":[-84.21550000000001,33.855598],"type":"Point"}
}