{
  "type": "Feature",
  "properties": {
    "iso:country":"US",
    "sg:address":"225 Hutcheson Pass",
    "sg:city":"Temple",
    "sg:classifiers":[
        {
            "category":"Building & Trades",
            "subcategory":"Construction",
            "type":"Services"
        }
    ],
    "sg:phone":"+1 770 459 1213",
    "sg:postcode":"30179",
    "sg:province":"GA",
    "sg:tags":[
        "house"
    ],
    "wof:name":"Anglers Construction",
    "wof:placetype":"venue"
},
  "geometry": {"coordinates":[-84.990949,33.84542],"type":"Point"}
}