{
  "type": "Feature",
  "properties": {
    "iso:country":"US",
    "sg:address":"138 Fanning Cir",
    "sg:city":"Swainsboro",
    "sg:classifiers":[
        {
            "category":"Freight",
            "type":"Transportation"
        }
    ],
    "sg:phone":"+1 478 237 2304",
    "sg:postcode":"30401",
    "sg:province":"GA",
    "sg:tags":[
        "operator",
        "local",
        "trucking"
    ],
    "wof:name":"E Wadley Trucking Inc",
    "wof:placetype":"venue"
},
  "geometry": {"coordinates":[-82.310894,32.576392],"type":"Point"}
}