{
  "type": "Feature",
  "properties": {
    "iso:country":"US",
    "sg:address":"2223 Blanchard Blvd",
    "sg:city":"Columbus",
    "sg:classifiers":[
        {
            "category":"Building & Trades",
            "subcategory":"Construction",
            "type":"Services"
        }
    ],
    "sg:phone":"+1 706 327 0456",
    "sg:postcode":"31901",
    "sg:province":"GA",
    "sg:tags":[
        "water",
        "main",
        "contractor"
    ],
    "wof:name":"Jack's Backflow Testing",
    "wof:placetype":"venue"
},
  "geometry": {"coordinates":[-84.96183600000001,32.442876],"type":"Point"}
}