{
  "type": "Feature",
  "properties": {
    "iso:country":"US",
    "sg:address":"1250 Moreland Ave SE",
    "sg:city":"Atlanta",
    "sg:classifiers":[
        {
            "category":"Autos & Motor Vehicles",
            "subcategory":"Automobile Sales",
            "type":"Retail Goods"
        }
    ],
    "sg:phone":"+1 404 622 5331",
    "sg:postcode":"30316",
    "sg:province":"GA",
    "sg:tags":[
        "car",
        "dealer"
    ],
    "wof:name":"Lanier Motors",
    "wof:placetype":"venue"
},
  "geometry": {"coordinates":[-84.349403,33.718],"type":"Point"}
}