{
  "type": "Feature",
  "properties": {
    "addr:full":"102 W Laurel Ave Rome GA 30165",
    "addr:housenumber":"102",
    "addr:postcode":"ga 30165",
    "addr:street":"W Laurel Ave",
    "iso:country":"US",
    "sg:address":"102 W Laurel Ave",
    "sg:city":"Rome",
    "sg:classifiers":[
        {
            "category":"Arts & Performance",
            "subcategory":"Theater",
            "type":"Entertainment"
        }
    ],
    "sg:phone":"+1 706 409 2197",
    "sg:postcode":"30165",
    "sg:province":"GA",
    "sg:tags":[
        "promotion"
    ],
    "wof:name":"Fatboy Productions",
    "wof:placetype":"venue"
},
  "geometry": {"coordinates":[-85.207319,34.269892],"type":"Point"}
}