{
  "type": "Feature",
  "properties": {
    "iso:country":"US",
    "sg:address":"1005 N Tennessee St",
    "sg:city":"Cartersville",
    "sg:classifiers":[
        {
            "category":"Manufacturing",
            "subcategory":"Lumber",
            "type":"Manufacturing & Wholesale Goods"
        }
    ],
    "sg:phone":"+1 770 387 3750",
    "sg:postcode":"30120",
    "sg:province":"GA",
    "sg:tags":[
        "government"
    ],
    "sg:website":"www.gfc.state.ga.us",
    "wof:name":"Forestry Commission",
    "wof:placetype":"venue"
},
  "geometry": {"coordinates":[-84.79519999999999,34.186105],"type":"Point"}
}