{
  "type": "Feature",
  "properties": {
    "addr:full":"871 Cobb Pkwy N Marietta GA 30062",
    "addr:housenumber":"871",
    "addr:postcode":"30062",
    "addr:street":"Cobb Pkwy N",
    "iso:country":"US",
    "sg:address":"871 Cobb Pkwy N",
    "sg:city":"Marietta",
    "sg:classifiers":[
        {
            "category":"Travel",
            "subcategory":"Hotels & Motels",
            "type":"Entertainment"
        }
    ],
    "sg:phone":"+1 770 422 0169",
    "sg:postcode":"30062",
    "sg:province":"GA",
    "wof:name":"Sun Inn",
    "wof:placetype":"venue"
},
  "geometry": {"coordinates":[-84.540802,33.971699],"type":"Point"}
}