{
  "type": "Feature",
  "properties": {
    "addr:full":"505 Harbor Gate Cir Alpharetta GA 30022",
    "addr:housenumber":"505",
    "addr:postcode":"30022",
    "addr:street":"Harbor Gate Cir",
    "iso:country":"US",
    "sg:address":"505 Harbor Gate Cir",
    "sg:city":"Alpharetta",
    "sg:classifiers":[
        {
            "category":"Banks & Credit Unions",
            "subcategory":"Bank",
            "type":"Services"
        }
    ],
    "sg:phone":"+1 770 616 8575",
    "sg:postcode":"30022",
    "sg:province":"GA",
    "sg:tags":[
        "broker",
        "mortgage"
    ],
    "wof:name":"Best Rates Nationwide Mrtg Inc",
    "wof:placetype":"venue"
},
  "geometry": {"coordinates":[-84.24309,34.023297],"type":"Point"}
}