{
  "type": "Feature",
  "properties": {
    "iso:country":"US",
    "sg:address":"1156 Meriwether St",
    "sg:city":"Griffin",
    "sg:classifiers":[
        {
            "category":"Professional",
            "subcategory":"Accounting & Tax Preparation",
            "type":"Services"
        }
    ],
    "sg:phone":"+1 770 228 4377",
    "sg:postcode":"30224",
    "sg:province":"GA",
    "sg:tags":[
        "return"
    ],
    "wof:name":"Zip Zap Tax Service",
    "wof:placetype":"venue"
},
  "geometry": {"coordinates":[-84.280381,33.239651],"type":"Point"}
}