{
  "type": "Feature",
  "properties": {
    "addr:full":"1156 Meriwether St Griffin GA 30224",
    "addr:housenumber":"1156",
    "addr:postcode":"30224",
    "addr:street":"Meriwether St",
    "iso:country":"US",
    "sg:address":"1156 Meriwether St",
    "sg:city":"Griffin",
    "sg:classifiers":[
        {
            "category":"Professional",
            "subcategory":"Accounting & Tax Preparation",
            "type":"Services"
        }
    ],
    "sg:phone":"+1 770 228 4377",
    "sg:postcode":"30224",
    "sg:province":"GA",
    "sg:tags":[
        "return"
    ],
    "wof:name":"Zip Zap Tax Service",
    "wof:placetype":"venue"
},
  "geometry": {"coordinates":[-84.28038100000001,33.239651],"type":"Point"}
}