{
  "type": "Feature",
  "properties": {
    "addr:full":"844 Ralph David Abernath Atlanta GA 30310",
    "addr:housenumber":"844",
    "addr:postcode":"30310",
    "addr:street":"Ralph David Abernath",
    "iso:country":"US",
    "sg:address":"844 Ralph David Abernath",
    "sg:city":"Atlanta",
    "sg:classifiers":[
        {
            "category":"Shopping",
            "subcategory":"Clothing, Apparel, & Fashions",
            "type":"Retail Goods"
        }
    ],
    "sg:phone":"+1 404 755 6533",
    "sg:postcode":"30310",
    "sg:province":"GA",
    "sg:tags":[
        "accessory",
        "clothing",
        "women's"
    ],
    "wof:name":"Product M T",
    "wof:placetype":"venue"
},
  "geometry": {"coordinates":[-84.41553,33.738181],"type":"Point"}
}