{
  "type": "Feature",
  "properties": {
    "iso:country":"US",
    "sg:address":"2654 Timberbrooke Way NW",
    "sg:city":"Duluth",
    "sg:classifiers":[
        {
            "category":"Professional",
            "subcategory":"Business Services",
            "type":"Services"
        }
    ],
    "sg:phone":"+1 770 329 3335",
    "sg:postcode":"30097",
    "sg:province":"GA",
    "wof:name":"Fiddlesticks Design",
    "wof:placetype":"venue"
},
  "geometry": {"coordinates":[-84.13291,34.013181],"type":"Point"}
}