{
  "type": "Feature",
  "properties": {
    "iso:country":"US",
    "sg:address":"2822 Limerick St",
    "sg:city":"Savannah",
    "sg:classifiers":[
        {
            "category":"Building & Trades",
            "subcategory":"Plumbing",
            "type":"Services"
        }
    ],
    "sg:phone":"+1 912 354 4965",
    "sg:postcode":"31404",
    "sg:province":"GA",
    "sg:tags":[
        "plumbing",
        "contractor"
    ],
    "wof:name":"Eh Hutson Plumbing Co",
    "wof:placetype":"venue"
},
  "geometry": {"coordinates":[-81.071495,32.043524],"type":"Point"}
}