{
  "type": "Feature",
  "properties": {
    "addr:full":"780 Johnson Ferry Road NE Atlanta GA 30342",
    "addr:housenumber":"780",
    "addr:postcode":"30342",
    "addr:street":"Johnson Ferry Road Ne",
    "iso:country":"US",
    "sg:address":"780 Johnson Ferry Road NE",
    "sg:city":"Atlanta",
    "sg:classifiers":[
        {
            "category":"Home & Garden",
            "subcategory":"Furniture",
            "type":"Retail Goods"
        }
    ],
    "sg:phone":"+1 404 255 2707",
    "sg:postcode":"30342",
    "sg:province":"GA",
    "sg:tags":[
        "store"
    ],
    "wof:name":"Network Appliance",
    "wof:placetype":"venue"
},
  "geometry": {"coordinates":[-84.36183,33.9071],"type":"Point"}
}