{
  "type": "Feature",
  "properties": {
    "iso:country":"US",
    "sg:address":"266 Bordeaux Ln",
    "sg:city":"Savannah",
    "sg:classifiers":[
        {
            "category":"Professional",
            "subcategory":"Business Services",
            "type":"Services"
        }
    ],
    "sg:phone":"+1 912 920 3898",
    "sg:postcode":"31419",
    "sg:province":"GA",
    "wof:name":"Coastal Carrier Express Inc",
    "wof:placetype":"venue"
},
  "geometry": {"coordinates":[-81.139635,31.963388],"type":"Point"}
}