{
  "type": "Feature",
  "properties": {
    "iso:country":"US",
    "sg:address":"1650 E Victory Dr",
    "sg:city":"Savannah",
    "sg:classifiers":[
        {
            "category":"Building & Trades",
            "subcategory":"Plumbing",
            "type":"Services"
        }
    ],
    "sg:phone":"+1 912 232 1650",
    "sg:postcode":"31404",
    "sg:province":"GA",
    "sg:tags":[
        "repair",
        "conditioning",
        "contractor",
        "system",
        "air"
    ],
    "sg:website":"www.smithairconditioning.com",
    "wof:name":"Smith Air Conditioning Inc",
    "wof:placetype":"venue"
},
  "geometry": {"coordinates":[-81.07323700000001,32.044937],"type":"Point"}
}