{
  "type": "Feature",
  "properties": {
    "iso:country":"US",
    "sg:address":"2274 Salem Rd SE",
    "sg:city":"Conyers",
    "sg:classifiers":[
        {
            "category":"Wholesale",
            "subcategory":"Machinery & Supplies",
            "type":"Manufacturing & Wholesale Goods"
        }
    ],
    "sg:phone":"+1 770 639 4037",
    "sg:postcode":"30013",
    "sg:province":"GA",
    "sg:tags":[
        "equipment",
        "industrial"
    ],
    "wof:name":"Dma Equipment Sales & Rental, Inc",
    "wof:placetype":"venue"
},
  "geometry": {"coordinates":[-83.978509,33.629342],"type":"Point"}
}