{
  "type": "Feature",
  "properties": {
    "iso:country":"US",
    "sg:address":"4465 Alicia Ln Ste 100",
    "sg:city":"Cumming",
    "sg:classifiers":[
        {
            "category":"Utilities",
            "subcategory":"Water",
            "type":"Services"
        },
        {
            "category":"Food & Beverages",
            "subcategory":"Liquor & Beverages",
            "type":"Retail Goods"
        }
    ],
    "sg:phone":"+1 404 355 2212",
    "sg:postcode":"30028",
    "sg:province":"GA",
    "sg:tags":[
        "bulk",
        "companies-bottled"
    ],
    "wof:name":"Amicalola",
    "wof:placetype":"venue"
},
  "geometry": {"coordinates":[-84.079978,34.28542],"type":"Point"}
}