{
  "type": "Feature",
  "properties": {
    "iso:country":"US",
    "sg:address":"1714 Deer Chase Ln",
    "sg:city":"Hephzibah",
    "sg:classifiers":[
        {
            "category":"Social Services",
            "subcategory":"Child Care",
            "type":"Services"
        }
    ],
    "sg:phone":"+1 706 793 4222",
    "sg:postcode":"30815",
    "sg:province":"GA",
    "sg:tags":[
        "nursery",
        "day"
    ],
    "wof:name":"Dorothy's Family Daycare",
    "wof:placetype":"venue"
},
  "geometry": {"coordinates":[-82.09359600000001,33.36407],"type":"Point"}
}