{
  "type": "Feature",
  "properties": {
    "addr:full":"3000 Windy Hill Rd SE Marietta GA 30067",
    "addr:housenumber":"3000",
    "addr:postcode":"30067",
    "addr:street":"Windy Hill Rd Se",
    "iso:country":"US",
    "sg:address":"3000 Windy Hill Rd SE",
    "sg:city":"Marietta",
    "sg:classifiers":[
        {
            "category":"Restaurant",
            "type":"Food & Drink"
        }
    ],
    "sg:phone":"+1 770 272 0407",
    "sg:postcode":"30067",
    "sg:province":"GA",
    "sg:tags":[
        "american"
    ],
    "wof:name":"Barkers Hot Dogs/Catering",
    "wof:placetype":"venue"
},
  "geometry": {"coordinates":[-84.467758,33.90451],"type":"Point"}
}