{
  "type": "Feature",
  "properties": {
    "iso:country":"US",
    "sg:address":"2815 Old Bushmill Rd",
    "sg:city":"Bremen",
    "sg:classifiers":[
        {
            "category":"Place Of Worship",
            "subcategory":"Church",
            "type":"Public Place"
        },
        {
            "category":"Place Of Worship",
            "type":"Public Place"
        },
        {
            "category":"Organizations",
            "subcategory":"Religious Organization",
            "type":"Services"
        }
    ],
    "sg:phone":"+1 770 824 5850",
    "sg:postcode":"30110",
    "sg:province":"GA",
    "sg:tags":[
        "churches-pentecostal-independent",
        "churches-pentecostal"
    ],
    "wof:name":"West Georgia Worship Center",
    "wof:placetype":"venue"
},
  "geometry": {"coordinates":[-85.172166,33.771094],"type":"Point"}
}