{
  "type": "Feature",
  "properties": {
    "iso:country":"US",
    "sg:address":"1200 Pawnee Dr",
    "sg:city":"Lincolnton",
    "sg:classifiers":[
        {
            "category":"Professional",
            "subcategory":"Business Services",
            "type":"Services"
        }
    ],
    "sg:phone":"+1 706 359 5174",
    "sg:postcode":"30817",
    "sg:province":"GA",
    "wof:name":"Heard Family Ltd Partnership",
    "wof:placetype":"venue"
},
  "geometry": {"coordinates":[-82.382859,33.836023],"type":"Point"}
}