{
  "type": "Feature",
  "properties": {
    "addr:full":"1453 Greene St Augusta GA 30901",
    "addr:housenumber":"1453",
    "addr:postcode":"30901",
    "addr:street":"Greene St",
    "iso:country":"US",
    "sg:address":"1453 Greene St",
    "sg:city":"Augusta",
    "sg:classifiers":[
        {
            "category":"Local Transit",
            "type":"Transportation"
        }
    ],
    "sg:phone":"+1 706 821 0044",
    "sg:postcode":"30901",
    "sg:province":"GA",
    "sg:tags":[
        "bus",
        "line"
    ],
    "wof:name":"Ga Bus Net",
    "wof:placetype":"venue"
},
  "geometry": {"coordinates":[-81.98298699999999,33.478892],"type":"Point"}
}