{
  "type": "Feature",
  "properties": {
    "addr:full":"2050 Luke Edwards Rd Dacula GA 30019",
    "addr:housenumber":"2050",
    "addr:postcode":"ga 30019",
    "addr:street":"Luke Edwards Rd",
    "iso:country":"US",
    "sg:address":"2050 Luke Edwards Rd",
    "sg:city":"Dacula",
    "sg:classifiers":[
        {
            "category":"Retail",
            "subcategory":"Laundry & Dry Cleaning",
            "type":"Services"
        }
    ],
    "sg:phone":"+1 770 676 6165",
    "sg:postcode":"30019",
    "sg:province":"GA",
    "sg:tags":[
        "cleaner"
    ],
    "sg:website":"http://www.greenmagiccarpet.com",
    "wof:name":"Green Magic Carpet Cleaners",
    "wof:placetype":"venue"
},
  "geometry": {"coordinates":[-83.87571699999999,33.93539],"type":"Point"}
}