{
  "type": "Feature",
  "properties": {
    "iso:country":"US",
    "sg:address":"2308 Lake Harbin Rd",
    "sg:city":"Morrow",
    "sg:classifiers":[
        {
            "category":"Personal",
            "subcategory":"Beauty Salon",
            "type":"Services"
        }
    ],
    "sg:phone":"+1 404 363 9265",
    "sg:postcode":"30260",
    "sg:province":"GA",
    "sg:tags":[
        "shop"
    ],
    "wof:name":"Kay",
    "wof:placetype":"venue"
},
  "geometry": {"coordinates":[-84.313969,33.583095],"type":"Point"}
}