{
  "type": "Feature",
  "properties": {
    "iso:country":"US",
    "sg:address":"1708 Emerson Bridge Ct NE",
    "sg:city":"Marietta",
    "sg:classifiers":[
        {
            "category":"Building & Trades",
            "subcategory":"Construction",
            "type":"Services"
        }
    ],
    "sg:phone":"+1 770 971 7386",
    "sg:postcode":"30062",
    "sg:province":"GA",
    "sg:tags":[
        "house"
    ],
    "wof:name":"Southcraft Home Builders Inc",
    "wof:placetype":"venue"
},
  "geometry": {"coordinates":[-84.438125,33.992715],"type":"Point"}
}