{
  "type": "Feature",
  "properties": {
    "addr:full":"922 Blue Heron Dr Brunswick GA 31525",
    "addr:housenumber":"922",
    "addr:postcode":"31525",
    "addr:street":"Blue Heron Dr",
    "iso:country":"US",
    "sg:address":"922 Blue Heron Dr",
    "sg:city":"Brunswick",
    "sg:classifiers":[
        {
            "category":"Professional",
            "subcategory":"Computer Services",
            "type":"Services"
        }
    ],
    "sg:phone":"+1 912 264 1489",
    "sg:postcode":"31525",
    "sg:province":"GA",
    "sg:tags":[
        "repair"
    ],
    "wof:name":"Blair Computer Svc",
    "wof:placetype":"venue"
},
  "geometry": {"coordinates":[-81.45632999999999,31.223364],"type":"Point"}
}