{
  "type": "Feature",
  "properties": {
    "addr:full":"3247 Shadowridge Dr SW Marietta GA 30008",
    "addr:housenumber":"3247",
    "addr:postcode":"30008",
    "addr:street":"Shadowridge Dr Sw",
    "iso:country":"US",
    "sg:address":"3247 Shadowridge Dr SW",
    "sg:city":"Marietta",
    "sg:classifiers":[
        {
            "category":"Professional",
            "type":"Services"
        }
    ],
    "sg:phone":"+1 770 439 3161",
    "sg:postcode":"30008",
    "sg:province":"GA",
    "wof:name":"Randy Galloway",
    "wof:placetype":"venue"
},
  "geometry": {"coordinates":[-84.61951500000001,33.874178],"type":"Point"}
}