{
  "type": "Feature",
  "properties": {
    "addr:full":"4943 Weaver Rd Gainesville GA 30507",
    "addr:housenumber":"4943",
    "addr:postcode":"30507",
    "addr:street":"Weaver Rd",
    "iso:country":"US",
    "sg:address":"4943 Weaver Rd",
    "sg:city":"Gainesville",
    "sg:classifiers":[
        {
            "category":"Building & Trades",
            "subcategory":"Construction",
            "type":"Services"
        }
    ],
    "sg:phone":"+1 770 536 7459",
    "sg:postcode":"30507",
    "sg:province":"GA",
    "sg:tags":[
        "floor",
        "laying",
        "contractor"
    ],
    "wof:name":"Brians Tile Work",
    "wof:placetype":"venue"
},
  "geometry": {"coordinates":[-83.78893100000001,34.196015],"type":"Point"}
}