{
  "type": "Feature",
  "properties": {
    "addr:full":"709 N Westover Blvd Albany GA 31707",
    "addr:housenumber":"709",
    "addr:postcode":"31707",
    "addr:street":"N Westover Blvd",
    "iso:country":"US",
    "sg:address":"709 N Westover Blvd",
    "sg:city":"Albany",
    "sg:classifiers":[
        {
            "category":"Health Services",
            "subcategory":"Health Practitioner",
            "type":"Services"
        }
    ],
    "sg:phone":"+1 229 446 2333",
    "sg:postcode":"31707",
    "sg:province":"GA",
    "sg:tags":[
        "therapist",
        "physical"
    ],
    "wof:name":"Advanced Rehab Ctr Inc",
    "wof:placetype":"venue"
},
  "geometry": {"coordinates":[-84.22240600000001,31.617513],"type":"Point"}
}