{
  "type": "Feature",
  "properties": {
    "addr:full":"445 Flintside Dr Cobb GA 31735",
    "addr:housenumber":"445",
    "addr:postcode":"31735",
    "addr:street":"Flintside Dr",
    "iso:country":"US",
    "sg:address":"445 Flintside Dr",
    "sg:city":"Cobb",
    "sg:classifiers":[
        {
            "category":"Freight",
            "type":"Transportation"
        }
    ],
    "sg:phone":"+1 229 853 2663",
    "sg:postcode":"31735",
    "sg:province":"GA",
    "sg:tags":[
        "operator",
        "local",
        "trucking"
    ],
    "wof:name":"Kimbrells Trucking Inc",
    "wof:placetype":"venue"
},
  "geometry": {"coordinates":[-83.935553,31.94606],"type":"Point"}
}