{
  "type": "Feature",
  "properties": {
    "addr:full":"2572 McKinnon Dr Decatur GA 30030",
    "addr:housenumber":"2572",
    "addr:postcode":"30030",
    "addr:street":"Mckinnon Dr",
    "iso:country":"US",
    "sg:address":"2572 McKinnon Dr",
    "sg:city":"Decatur",
    "sg:classifiers":[
        {
            "category":"Professional",
            "subcategory":"Management & Consulting",
            "type":"Services"
        }
    ],
    "sg:phone":"+1 404 713 0488",
    "sg:postcode":"30030",
    "sg:province":"GA",
    "sg:tags":[
        "life",
        "coach"
    ],
    "sg:website":"www.yourattentioncoach.com",
    "wof:name":"Your Attention Coach",
    "wof:placetype":"venue"
},
  "geometry": {"coordinates":[-84.28446599999999,33.760369],"type":"Point"}
}