{
  "type": "Feature",
  "properties": {
    "addr:full":"3121 N Oak St Exd Valdosta GA 31602",
    "addr:housenumber":"3121",
    "addr:postcode":"31602",
    "addr:street":"N Oak St Exd",
    "iso:country":"US",
    "sg:address":"3121 N Oak St Exd",
    "sg:city":"Valdosta",
    "sg:classifiers":[
        {
            "category":"Food & Beverages",
            "subcategory":"Liquor & Beverages",
            "type":"Retail Goods"
        }
    ],
    "sg:phone":"+1 229 242 4882",
    "sg:postcode":"31602",
    "sg:province":"GA",
    "sg:tags":[
        "beer",
        "station",
        "packaged",
        "wine"
    ],
    "wof:name":"Sing Service Station",
    "wof:placetype":"venue"
},
  "geometry": {"coordinates":[-83.29166499999999,30.882267],"type":"Point"}
}