{
  "type": "Feature",
  "properties": {
    "addr:full":"11130 State Bridge Rd Alpharetta GA 30022",
    "addr:housenumber":"11130",
    "addr:postcode":"30022",
    "addr:street":"State Bridge Rd",
    "iso:country":"US",
    "sg:address":"11130 State Bridge Rd",
    "sg:city":"Alpharetta",
    "sg:classifiers":[
        {
            "category":"Arts & Performance",
            "subcategory":"Arts Center",
            "type":"Entertainment"
        }
    ],
    "sg:phone":"+1 770 442 5229",
    "sg:postcode":"30022",
    "sg:province":"GA",
    "sg:tags":[
        "performing"
    ],
    "wof:name":"Fleetwood Dance Studio",
    "wof:placetype":"venue"
},
  "geometry": {"coordinates":[-84.230301,34.054798],"type":"Point"}
}