{
  "type": "Feature",
  "properties": {
    "addr:full":"2812 Gravel Springs Rd Buford GA 30519",
    "addr:housenumber":"2812",
    "addr:postcode":"30519",
    "addr:street":"Gravel Springs Rd",
    "iso:country":"US",
    "sg:address":"2812 Gravel Springs Rd",
    "sg:city":"Buford",
    "sg:classifiers":[
        {
            "category":"Banks & Credit Unions",
            "subcategory":"Financial Services",
            "type":"Services"
        }
    ],
    "sg:phone":"+1 770 945 3955",
    "sg:postcode":"30519",
    "sg:province":"GA",
    "sg:tags":[
        "investor"
    ],
    "wof:name":"Hwy 13 LLC",
    "wof:placetype":"venue"
},
  "geometry": {"coordinates":[-83.95402199999999,34.067821],"type":"Point"}
}