{
  "type": "Feature",
  "properties": {
    "addr:full":"385 Sam Nelson Rd Canton GA 30114",
    "addr:housenumber":"385",
    "addr:postcode":"30114",
    "addr:street":"Sam Nelson Rd",
    "iso:country":"US",
    "sg:address":"385 Sam Nelson Rd",
    "sg:city":"Canton",
    "sg:classifiers":[
        {
            "category":"Professional",
            "type":"Services"
        }
    ],
    "sg:phone":"+1 770 704 9728",
    "sg:postcode":"30114",
    "sg:province":"GA",
    "wof:name":"Smart Moves Inc",
    "wof:placetype":"venue"
},
  "geometry": {"coordinates":[-84.554475,34.281139],"type":"Point"}
}