{
  "type": "Feature",
  "properties": {
    "iso:country":"US",
    "sg:address":"3280 Howell Mill Road NW",
    "sg:city":"Atlanta",
    "sg:classifiers":[
        {
            "category":"Health Services",
            "subcategory":"Doctor",
            "type":"Services"
        }
    ],
    "sg:phone":"+1 404 352 1730",
    "sg:postcode":"30327",
    "sg:province":"GA",
    "sg:tags":[
        "dermatologist"
    ],
    "sg:website":"www.georgiaskinspecialists.com",
    "wof:name":"Hurt Susan MD",
    "wof:placetype":"venue"
},
  "geometry": {"coordinates":[-84.42827,33.845634],"type":"Point"}
}