{
  "type": "Feature",
  "properties": {
    "addr:full":"2700 6th St SE Moultrie GA 31768",
    "addr:housenumber":"2700",
    "addr:postcode":"31768",
    "addr:street":"6Th St Se",
    "iso:country":"US",
    "sg:address":"2700 6th St SE",
    "sg:city":"Moultrie",
    "sg:classifiers":[
        {
            "category":"Shopping",
            "type":"Retail Goods"
        }
    ],
    "sg:phone":"+1 229 217 0592",
    "sg:postcode":"31768",
    "sg:province":"GA",
    "sg:tags":[
        "repair",
        "electrical",
        "merchandise"
    ],
    "wof:name":"Luke Electric",
    "wof:placetype":"venue"
},
  "geometry": {"coordinates":[-83.777277,31.136042],"type":"Point"}
}