{
  "type": "Feature",
  "properties": {
    "addr:full":"100 Southern Pines Dr Lagrange GA 30241",
    "addr:housenumber":"100",
    "addr:postcode":"30241",
    "addr:street":"Southern Pines Dr",
    "iso:country":"US",
    "sg:address":"100 Southern Pines Dr",
    "sg:city":"Lagrange",
    "sg:classifiers":[
        {
            "category":"Home & Garden",
            "subcategory":"Furniture",
            "type":"Retail Goods"
        }
    ],
    "sg:phone":"+1 706 812 8881",
    "sg:postcode":"30241",
    "sg:province":"GA",
    "sg:tags":[
        "cabinet"
    ],
    "wof:name":"Cabinet Manufacturing Instltn",
    "wof:placetype":"venue"
},
  "geometry": {"coordinates":[-85.00592399999999,32.968663],"type":"Point"}
}