{
  "type": "Feature",
  "properties": {
    "iso:country":"US",
    "sg:address":"4005 Wetherburn Way",
    "sg:city":"Norcross",
    "sg:classifiers":[
        {
            "category":"Social Services",
            "subcategory":"Child Care",
            "type":"Services"
        }
    ],
    "sg:phone":"+1 770 840 8858",
    "sg:postcode":"30092",
    "sg:province":"GA",
    "sg:tags":[
        "day"
    ],
    "wof:name":"Pals & Gals Daycare Inc",
    "wof:placetype":"venue"
},
  "geometry": {"coordinates":[-84.25552500000001,33.968734],"type":"Point"}
}