{
  "type": "Feature",
  "properties": {
    "iso:country":"US",
    "sg:address":"5975 Shannon Dr",
    "sg:city":"Cumming",
    "sg:classifiers":[
        {
            "category":"Professional",
            "subcategory":"Business Services",
            "type":"Services"
        }
    ],
    "sg:phone":"+1 770 888 6728",
    "sg:postcode":"30040",
    "sg:province":"GA",
    "wof:name":"Rivers Group",
    "wof:placetype":"venue"
},
  "geometry": {"coordinates":[-84.158047,34.283226],"type":"Point"}
}