{
  "type": "Feature",
  "properties": {
    "iso:country":"US",
    "sg:address":"4512 Seymour Ln",
    "sg:city":"Albany",
    "sg:classifiers":[
        {
            "category":"Professional",
            "type":"Services"
        }
    ],
    "sg:phone":"+1 229 438 7588",
    "sg:postcode":"31705",
    "sg:province":"GA",
    "wof:name":"Cecil E Tillman",
    "wof:placetype":"venue"
},
  "geometry": {"coordinates":[-84.115914,31.465454],"type":"Point"}
}