{
  "type": "Feature",
  "properties": {
    "addr:full":"1976 E Victory Dr Savannah GA 31404",
    "addr:housenumber":"1976",
    "addr:postcode":"31404",
    "addr:street":"E Victory Dr",
    "iso:country":"US",
    "sg:address":"1976 E Victory Dr",
    "sg:city":"Savannah",
    "sg:classifiers":[
        {
            "category":"Food & Beverages",
            "subcategory":"Groceries & Convenience Stores",
            "type":"Retail Goods"
        }
    ],
    "sg:phone":"+1 912 233 8898",
    "sg:postcode":"31404",
    "sg:province":"GA",
    "wof:name":"Parker's",
    "wof:placetype":"venue"
},
  "geometry": {"coordinates":[-81.065313,32.042004],"type":"Point"}
}