{
  "type": "Feature",
  "properties": {
    "addr:full":"3939 Royal Dr NW Kennesaw GA 30144",
    "addr:housenumber":"3939",
    "addr:postcode":"30144",
    "addr:street":"Royal Dr Nw",
    "iso:country":"US",
    "sg:address":"3939 Royal Dr NW",
    "sg:city":"Kennesaw",
    "sg:classifiers":[
        {
            "category":"Professional",
            "subcategory":"Advertising",
            "type":"Services"
        },
        {
            "category":"Retail",
            "subcategory":"Repair Shop",
            "type":"Services"
        },
        {
            "category":"Manufacturing",
            "subcategory":"Signs",
            "type":"Manufacturing & Wholesale Goods"
        }
    ],
    "sg:phone":"+1 678 354 0788",
    "sg:postcode":"30144",
    "sg:province":"GA",
    "sg:tags":[
        "signs-erectors",
        "hanger",
        "specialty",
        "signs-maintenance"
    ],
    "sg:website":"http://www.signsupplyusa.com",
    "wof:name":"Sign Supply U S A",
    "wof:placetype":"venue"
},
  "geometry": {"coordinates":[-84.604159,34.048939],"type":"Point"}
}