{
  "type": "Feature",
  "properties": {
    "iso:country":"US",
    "sg:address":"130 Ridgecrest Way",
    "sg:city":"Stockbridge",
    "sg:classifiers":[
        {
            "category":"Real Estate",
            "subcategory":"Real Estate Services",
            "type":"Services"
        },
        {
            "category":"Building & Trades",
            "subcategory":"Construction",
            "type":"Services"
        }
    ],
    "sg:phone":"+1 770 389 0414",
    "sg:postcode":"30281",
    "sg:province":"GA",
    "sg:tags":[
        "home",
        "inspector",
        "painter"
    ],
    "wof:name":"Home Reviewal",
    "wof:placetype":"venue"
},
  "geometry": {"coordinates":[-84.229119,33.577537],"type":"Point"}
}