{
  "type": "Feature",
  "properties": {
    "iso:country":"US",
    "sg:address":"1000 Cambridge Sq Ste A",
    "sg:city":"Alpharetta",
    "sg:classifiers":[
        {
            "category":"Real Estate",
            "subcategory":"Real Estate Services",
            "type":"Services"
        }
    ],
    "sg:phone":"+1 770 475 7724",
    "sg:postcode":"30004",
    "sg:province":"GA",
    "sg:tags":[
        "management",
        "property"
    ],
    "wof:name":"Williamsburg Management Services",
    "wof:placetype":"venue"
},
  "geometry": {"coordinates":[-84.31379699999999,34.066299],"type":"Point"}
}