{
  "type": "Feature",
  "properties": {
    "addr:full":"665 Hickory Flat Rd Alpharetta GA 30004",
    "addr:housenumber":"665",
    "addr:postcode":"30004",
    "addr:street":"Hickory Flat Rd",
    "iso:country":"US",
    "sg:address":"665 Hickory Flat Rd",
    "sg:city":"Alpharetta",
    "sg:classifiers":[
        {
            "category":"Building & Trades",
            "subcategory":"Construction",
            "type":"Services"
        }
    ],
    "sg:phone":"+1 770 475 7443",
    "sg:postcode":"30004",
    "sg:province":"GA",
    "sg:tags":[
        "carpentry",
        "contractor"
    ],
    "wof:name":"Custom Wood Cabinets",
    "wof:placetype":"venue"
},
  "geometry": {"coordinates":[-84.339726,34.167987],"type":"Point"}
}