{
  "type": "Feature",
  "properties": {
    "addr:full":"865 Indian Trail Lilburn Rd NW Lilburn GA 30047",
    "addr:housenumber":"865",
    "addr:postcode":"30047",
    "addr:street":"Indian Trail Lilburn Rd Nw",
    "iso:country":"US",
    "sg:address":"865 Indian Trail Lilburn Rd NW",
    "sg:city":"Lilburn",
    "sg:classifiers":[
        {
            "category":"Insurance",
            "subcategory":"Insurance Agent",
            "type":"Services"
        }
    ],
    "sg:phone":"+1 770 717 7380",
    "sg:postcode":"30047",
    "sg:province":"GA",
    "wof:name":"Foster & Witmer",
    "wof:placetype":"venue"
},
  "geometry": {"coordinates":[-84.15596499999999,33.905947],"type":"Point"}
}