{
  "type": "Feature",
  "properties": {
    "iso:country":"US",
    "sg:address":"1305 Taylorsville Macedonia Rd",
    "sg:city":"Taylorsville",
    "sg:classifiers":[
        {
            "category":"Wholesale",
            "subcategory":"Construction Materials",
            "type":"Manufacturing & Wholesale Goods"
        }
    ],
    "sg:phone":"+1 770 382 4876",
    "sg:postcode":"30178",
    "sg:province":"GA",
    "wof:name":"Bobby Maxwell Shop",
    "wof:placetype":"venue"
},
  "geometry": {"coordinates":[-84.979338,34.127152],"type":"Point"}
}