{
  "type": "Feature",
  "properties": {
    "iso:country":"US",
    "sg:address":"230 Peachtree St NW",
    "sg:city":"Atlanta",
    "sg:classifiers":[
        {
            "category":"Building & Trades",
            "subcategory":"Locksmith",
            "type":"Services"
        }
    ],
    "sg:phone":"+1 404 975 4296",
    "sg:postcode":"30303",
    "sg:province":"GA",
    "sg:tags":[
        "key"
    ],
    "wof:name":"24 7 Emergency Locksmith",
    "wof:placetype":"venue"
},
  "geometry": {"coordinates":[-84.38769499999999,33.760332],"type":"Point"}
}