{
  "type": "Feature",
  "properties": {
    "addr:full":"1793 Beaver Ruin Rd Norcross GA 30093",
    "addr:housenumber":"1793",
    "addr:postcode":"30093",
    "addr:street":"Beaver Ruin Rd",
    "iso:country":"US",
    "sg:address":"1793 Beaver Ruin Rd",
    "sg:city":"Norcross",
    "sg:classifiers":[
        {
            "category":"Shopping",
            "subcategory":"Pets & Pet Supplies",
            "type":"Retail Goods"
        },
        {
            "category":"Retail",
            "subcategory":"Pet Boarding",
            "type":"Services"
        }
    ],
    "sg:phone":"+1 770 931 2411",
    "sg:postcode":"30093",
    "sg:province":"GA",
    "sg:tags":[
        "training",
        "boarding/pet",
        "sitting"
    ],
    "sg:website":"www.mansbf.com",
    "wof:name":"Man's Best Friend",
    "wof:placetype":"venue"
},
  "geometry": {"coordinates":[-84.157946,33.934737],"type":"Point"}
}