{
  "type": "Feature",
  "properties": {
    "addr:full":"255 Bluff Oak Dr Roswell GA 30076",
    "addr:housenumber":"255",
    "addr:postcode":"30076",
    "addr:street":"Bluff Oak Dr",
    "iso:country":"US",
    "sg:address":"255 Bluff Oak Dr",
    "sg:city":"Roswell",
    "sg:classifiers":[
        {
            "category":"Building & Trades",
            "subcategory":"Plumbing",
            "type":"Services"
        }
    ],
    "sg:phone":"+1 770 777 1114",
    "sg:postcode":"30076",
    "sg:province":"GA",
    "sg:tags":[
        "contractor"
    ],
    "wof:name":"Halcomb Plumbing Inc",
    "wof:placetype":"venue"
},
  "geometry": {"coordinates":[-84.343014,34.060296],"type":"Point"}
}