{
  "type": "Feature",
  "properties": {
    "iso:country":"US",
    "sg:address":"315 Advance St",
    "sg:city":"Swainsboro",
    "sg:classifiers":[
        {
            "category":"Social Services",
            "subcategory":"Adult Care",
            "type":"Services"
        }
    ],
    "sg:phone":"+1 478 289 8586",
    "sg:postcode":"30401",
    "sg:province":"GA",
    "sg:tags":[
        "nurses-home"
    ],
    "wof:name":"Smith Personal Care Home",
    "wof:placetype":"venue"
},
  "geometry": {"coordinates":[-82.3237,32.595539],"type":"Point"}
}