{
  "type": "Feature",
  "properties": {
    "addr:full":"132 Summit St Cornelia GA 30531",
    "addr:housenumber":"132",
    "addr:postcode":"30531",
    "addr:street":"Summit St",
    "iso:country":"US",
    "sg:address":"132 Summit St",
    "sg:city":"Cornelia",
    "sg:classifiers":[
        {
            "category":"Building & Trades",
            "subcategory":"Pest Control",
            "type":"Services"
        }
    ],
    "sg:phone":"+1 706 499 4309",
    "sg:postcode":"30531",
    "sg:province":"GA",
    "sg:tags":[
        "industrial",
        "services-commercial",
        "termite"
    ],
    "wof:name":"Quality Pest Control Inc",
    "wof:placetype":"venue"
},
  "geometry": {"coordinates":[-83.516822,34.508945],"type":"Point"}
}