{
  "type": "Feature",
  "properties": {
    "addr:full":"742 Ponce De Leon Pl NE Atlanta GA 30306",
    "addr:housenumber":"742",
    "addr:postcode":"30306",
    "addr:street":"Ponce De Leon Pl Ne",
    "iso:country":"US",
    "sg:address":"742 Ponce De Leon Pl NE",
    "sg:city":"Atlanta",
    "sg:classifiers":[
        {
            "category":"Sports & Exercise",
            "subcategory":"Gym",
            "type":"Entertainment"
        }
    ],
    "sg:phone":"+1 404 819 9830",
    "sg:postcode":"30306",
    "sg:province":"GA",
    "sg:tags":[
        "trainer"
    ],
    "sg:website":"www.ddpt.com",
    "wof:name":"Drew Dinwiddie Personal Training",
    "wof:placetype":"venue"
},
  "geometry": {"coordinates":[-84.363725,33.774301],"type":"Point"}
}