{
  "type": "Feature",
  "properties": {
    "iso:country":"US",
    "sg:address":"106 Laprade Rd",
    "sg:city":"Griffin",
    "sg:classifiers":[
        {
            "category":"Place Of Worship",
            "subcategory":"Church",
            "type":"Public Place"
        },
        {
            "category":"Place Of Worship",
            "type":"Public Place"
        }
    ],
    "sg:phone":"+1 770 233 9876",
    "sg:postcode":"30223",
    "sg:province":"GA",
    "sg:tags":[
        "churches-interdenominational",
        "churches-various",
        "denomination"
    ],
    "wof:name":"Griffin North Congregational Holiness Church",
    "wof:placetype":"venue"
},
  "geometry": {"coordinates":[-84.28513700000001,33.286961],"type":"Point"}
}