{
  "type": "Feature",
  "properties": {
    "addr:full":"1414 Alvaton Rd Gay GA 30218",
    "addr:housenumber":"1414",
    "addr:postcode":"30218",
    "addr:street":"Alvaton Rd",
    "iso:country":"US",
    "sg:address":"1414 Alvaton Rd",
    "sg:city":"Gay",
    "sg:classifiers":[
        {
            "category":"Organizations",
            "subcategory":"Religious Organization",
            "type":"Services"
        }
    ],
    "sg:phone":"+1 706 538 6625",
    "sg:postcode":"30218",
    "sg:province":"GA",
    "wof:name":"Church of Christ At Mt Carmel",
    "wof:placetype":"venue"
},
  "geometry": {"coordinates":[-84.659583,33.163854],"type":"Point"}
}