{
  "type": "Feature",
  "properties": {
    "iso:country":"US",
    "sg:address":"250 E Main St",
    "sg:city":"Canton",
    "sg:classifiers":[
        {
            "category":"Real Estate",
            "subcategory":"Real Estate Agent",
            "type":"Services"
        }
    ],
    "sg:phone":"+1 770 704 7713",
    "sg:postcode":"30114",
    "sg:province":"GA",
    "wof:name":"Babcock Properties",
    "wof:placetype":"venue"
},
  "geometry": {"coordinates":[-84.487397,34.236231],"type":"Point"}
}