{
  "type": "Feature",
  "properties": {
    "addr:full":"601 Twilley Rd NW Atlanta GA 30318",
    "addr:housenumber":"601",
    "addr:postcode":"30318",
    "addr:street":"Twilley Rd Nw",
    "iso:country":"US",
    "sg:address":"601 Twilley Rd NW",
    "sg:city":"Atlanta",
    "sg:classifiers":[
        {
            "category":"Building & Trades",
            "subcategory":"Locksmith",
            "type":"Services"
        }
    ],
    "sg:phone":"+1 404 720 0822",
    "sg:postcode":"30318",
    "sg:province":"GA",
    "sg:tags":[
        "key"
    ],
    "wof:name":"Any 24 Hour Emerg Locksmith",
    "wof:placetype":"venue"
},
  "geometry": {"coordinates":[-84.458665,33.771239],"type":"Point"}
}