{
  "type": "Feature",
  "properties": {
    "iso:country":"US",
    "sg:address":"307 Whitesville St",
    "sg:city":"Lagrange",
    "sg:classifiers":[
        {
            "category":"Education",
            "subcategory":"School",
            "type":"Public Place"
        }
    ],
    "sg:phone":"+1 706 884 1288",
    "sg:postcode":"30240",
    "sg:province":"GA",
    "wof:name":"Bethlehem Temple Christian Sch",
    "wof:placetype":"venue"
},
  "geometry": {"coordinates":[-85.02892199999999,33.034117],"type":"Point"}
}