{
  "type": "Feature",
  "properties": {
    "iso:country":"US",
    "sg:address":"312 Whitehead Rd",
    "sg:city":"Sugar Hill",
    "sg:classifiers":[
        {
            "category":"Building & Trades",
            "subcategory":"Locksmith",
            "type":"Services"
        }
    ],
    "sg:phone":"+1 404 856 7053",
    "sg:postcode":"30518",
    "sg:province":"GA",
    "sg:tags":[
        "key"
    ],
    "wof:name":"20 Min Locksmith",
    "wof:placetype":"venue"
},
  "geometry": {"coordinates":[-84.069351,34.102794],"type":"Point"}
}