{
  "type": "Feature",
  "properties": {
    "addr:full":"263 N Brunswick St Jesup GA 31546",
    "addr:housenumber":"263",
    "addr:postcode":"31546",
    "addr:street":"N Brunswick St",
    "iso:country":"US",
    "sg:address":"263 N Brunswick St",
    "sg:city":"Jesup",
    "sg:classifiers":[
        {
            "category":"Government",
            "subcategory":"Office",
            "type":"Public Place"
        }
    ],
    "sg:phone":"+1 912 427 5866",
    "sg:postcode":"31546",
    "sg:province":"GA",
    "sg:tags":[
        "state",
        "resource"
    ],
    "wof:name":"Human Resources Dept",
    "wof:placetype":"venue"
},
  "geometry": {"coordinates":[-81.87690000000001,31.607896],"type":"Point"}
}