{
  "type": "Feature",
  "properties": {
    "iso:country":"US",
    "sg:address":"132 Bel Air Cir",
    "sg:city":"Brunswick",
    "sg:classifiers":[
        {
            "category":"Professional",
            "subcategory":"Business Services",
            "type":"Services"
        }
    ],
    "sg:phone":"+1 912 264 5019",
    "sg:postcode":"31520",
    "sg:province":"GA",
    "wof:name":"Rcg Assoc",
    "wof:placetype":"venue"
},
  "geometry": {"coordinates":[-81.49728399999999,31.221384],"type":"Point"}
}