{
  "type": "Feature",
  "properties": {
    "iso:country":"US",
    "sg:address":"18 Jackson St NE",
    "sg:city":"Atlanta",
    "sg:classifiers":[
        {
            "category":"Utilities",
            "subcategory":"Cable",
            "type":"Services"
        }
    ],
    "sg:phone":"+1 404 522 3969",
    "sg:postcode":"30312",
    "sg:province":"GA",
    "sg:tags":[
        "television"
    ],
    "wof:name":"Innovation USA Trading",
    "wof:placetype":"venue"
},
  "geometry": {"coordinates":[-84.37438299999999,33.754337],"type":"Point"}
}