{
  "type": "Feature",
  "properties": {
    "iso:country":"US",
    "sg:address":"1062 Winterbrook Way",
    "sg:city":"Austell",
    "sg:classifiers":[
        {
            "category":"Professional",
            "type":"Services"
        }
    ],
    "sg:phone":"+1 770 745 7871",
    "sg:postcode":"30168",
    "sg:province":"GA",
    "wof:name":"Storm T Thru",
    "wof:placetype":"venue"
},
  "geometry": {"coordinates":[-84.588228,33.778413],"type":"Point"}
}