{
  "type": "Feature",
  "properties": {
    "iso:country":"US",
    "sg:address":"225 Fieldstone Path",
    "sg:city":"Alpharetta",
    "sg:classifiers":[
        {
            "category":"Professional",
            "subcategory":"Engineering",
            "type":"Services"
        }
    ],
    "sg:phone":"+1 770 740 9624",
    "sg:postcode":"30005",
    "sg:province":"GA",
    "wof:name":"Quadrell Corp",
    "wof:placetype":"venue"
},
  "geometry": {"coordinates":[-84.208281,34.091827],"type":"Point"}
}