{
  "type": "Feature",
  "properties": {
    "addr:full":"9442 S Main St Jonesboro GA 30236",
    "addr:housenumber":"9442",
    "addr:postcode":"30236",
    "addr:street":"S Main St",
    "iso:country":"US",
    "sg:address":"9442 S Main St",
    "sg:city":"Jonesboro",
    "sg:classifiers":[
        {
            "category":"Shopping",
            "subcategory":"Gifts & Souvenirs",
            "type":"Retail Goods"
        }
    ],
    "sg:phone":"+1 770 603 6217",
    "sg:postcode":"30236",
    "sg:province":"GA",
    "wof:name":"Magnolia Sweet",
    "wof:placetype":"venue"
},
  "geometry": {"coordinates":[-84.338804,33.492786],"type":"Point"}
}