{
  "type": "Feature",
  "properties": {
    "iso:country":"US",
    "sg:address":"1350 Ga Highway 40 E",
    "sg:city":"Kingsland",
    "sg:classifiers":[
        {
            "category":"Restaurant",
            "type":"Food & Drink"
        }
    ],
    "sg:menulink":"http://www.allmenus.com/ga/kingsland/180750-wendys/menu/",
    "sg:phone":"+1 912 729 5620",
    "sg:postcode":"31548",
    "sg:province":"GA",
    "sg:tags":[
        "burger",
        "american",
        "soup"
    ],
    "wof:name":"Wendy's",
    "wof:placetype":"venue"
},
  "geometry": {"coordinates":[-81.66268100000001,30.791957],"type":"Point"}
}