{
  "type": "Feature",
  "properties": {
    "addr:full":"3 1st St NW Moultrie GA 31768",
    "addr:housenumber":"3",
    "addr:postcode":"31768",
    "addr:street":"1St St Nw",
    "iso:country":"US",
    "sg:address":"3 1st St NW",
    "sg:city":"Moultrie",
    "sg:classifiers":[
        {
            "category":"Building & Trades",
            "subcategory":"Equipment Rental",
            "type":"Services"
        },
        {
            "category":"Professional",
            "subcategory":"Computer Services",
            "type":"Services"
        }
    ],
    "sg:phone":"+1 229 985 5005",
    "sg:postcode":"31768",
    "sg:province":"GA",
    "sg:tags":[
        "leasing",
        "furniture"
    ],
    "wof:name":"Buddy's Home Furnishings",
    "wof:placetype":"venue"
},
  "geometry": {"coordinates":[-83.790136,31.180938],"type":"Point"}
}