{
  "type": "Feature",
  "properties": {
    "iso:country":"US",
    "sg:address":"2216 Gamble Rd",
    "sg:city":"Savannah",
    "sg:classifiers":[
        {
            "category":"Building & Trades",
            "subcategory":"Construction",
            "type":"Services"
        }
    ],
    "sg:phone":"+1 912 629 0460",
    "sg:postcode":"31405",
    "sg:province":"GA",
    "sg:tags":[
        "carpentry",
        "contractor"
    ],
    "wof:name":"Panasteel LLC",
    "wof:placetype":"venue"
},
  "geometry": {"coordinates":[-81.14823800000001,32.043244],"type":"Point"}
}