{
  "type": "Feature",
  "properties": {
    "addr:full":"950 Old Nondy Sch Hse Rd Marietta GA 30066",
    "addr:housenumber":"950",
    "addr:postcode":"30066",
    "addr:street":"Old Nondy Sch Hse Rd",
    "iso:country":"US",
    "sg:address":"950 Old Nondy Sch Hse Rd",
    "sg:city":"Marietta",
    "sg:classifiers":[
        {
            "category":"Personal",
            "type":"Services"
        }
    ],
    "sg:phone":"+1 770 592 1777",
    "sg:postcode":"30066",
    "sg:province":"GA",
    "sg:tags":[
        "towing"
    ],
    "wof:name":"Alpha Towing Inc",
    "wof:placetype":"venue"
},
  "geometry": {"coordinates":[-84.521698,34.066299],"type":"Point"}
}