{
  "type": "Feature",
  "properties": {
    "addr:full":"2388 Bluff Creek Overlook Douglasville GA 30135",
    "addr:housenumber":"2388",
    "addr:postcode":"30135",
    "addr:street":"Bluff Creek Overlook",
    "iso:country":"US",
    "sg:address":"2388 Bluff Creek Overlook",
    "sg:city":"Douglasville",
    "sg:classifiers":[
        {
            "category":"Restaurant",
            "type":"Food & Drink"
        }
    ],
    "sg:phone":"+1 678 838 0833",
    "sg:postcode":"30135",
    "sg:province":"GA",
    "sg:tags":[
        "eating"
    ],
    "wof:name":"Joes Hot Fish",
    "wof:placetype":"venue"
},
  "geometry": {"coordinates":[-84.65333200000001,33.712924],"type":"Point"}
}