{
  "type": "Feature",
  "properties": {
    "iso:country":"US",
    "sg:address":"703 Oak Valley Ln",
    "sg:city":"Woodstock",
    "sg:classifiers":[
        {
            "category":"Food & Beverages",
            "subcategory":"Groceries & Convenience Stores",
            "type":"Retail Goods"
        }
    ],
    "sg:phone":"+1 770 772 6065",
    "sg:postcode":"30188",
    "sg:province":"GA",
    "sg:tags":[
        "pretzel"
    ],
    "wof:name":"Pierces Perfect Pretzels Inc",
    "wof:placetype":"venue"
},
  "geometry": {"coordinates":[-84.384201,34.123847],"type":"Point"}
}