{
  "type": "Feature",
  "properties": {
    "addr:full":"1100 Northside Dr NW Cumming GA 30012",
    "addr:housenumber":"1100",
    "addr:postcode":"30012",
    "addr:street":"Northside Dr Nw",
    "iso:country":"US",
    "sg:address":"1100 Northside Dr NW",
    "sg:city":"Cumming",
    "sg:classifiers":[
        {
            "category":"Health Services",
            "subcategory":"Medical Lab",
            "type":"Services"
        }
    ],
    "sg:phone":"+1 678 947 6566",
    "sg:postcode":"30012",
    "sg:province":"GA",
    "sg:tags":[
        "laboratory"
    ],
    "wof:name":"Quest Diagnostics",
    "wof:placetype":"venue"
},
  "geometry": {"coordinates":[-84.01378,33.676807],"type":"Point"}
}