{
  "type": "Feature",
  "properties": {
    "addr:full":"12206 Navajo Rd Savannah GA 31419",
    "addr:housenumber":"12206",
    "addr:postcode":"31419",
    "addr:street":"Navajo Rd",
    "iso:country":"US",
    "sg:address":"12206 Navajo Rd",
    "sg:city":"Savannah",
    "sg:classifiers":[
        {
            "category":"Insurance",
            "subcategory":"Insurance Agent",
            "type":"Services"
        }
    ],
    "sg:phone":"+1 912 925 5324",
    "sg:postcode":"31419",
    "sg:province":"GA",
    "wof:name":"Allstate Insurance",
    "wof:placetype":"venue"
},
  "geometry": {"coordinates":[-81.175101,31.982277],"type":"Point"}
}