{
  "type": "Feature",
  "properties": {
    "addr:full":"2495 Churchill Downs Cumming GA 30041",
    "addr:housenumber":"2495",
    "addr:postcode":"30041",
    "addr:street":"Churchill Downs",
    "iso:country":"US",
    "sg:address":"2495 Churchill Downs",
    "sg:city":"Cumming",
    "sg:classifiers":[
        {
            "category":"Building & Trades",
            "subcategory":"Plumbing",
            "type":"Services"
        }
    ],
    "sg:phone":"+1 770 889 8814",
    "sg:postcode":"30041",
    "sg:province":"GA",
    "sg:tags":[
        "contractor"
    ],
    "wof:name":"Adept Plumbing",
    "wof:placetype":"venue"
},
  "geometry": {"coordinates":[-84.102891,34.161203],"type":"Point"}
}