{
  "type": "Feature",
  "properties": {
    "addr:full":"2439 Trace Pond Cir Grayson GA 30017",
    "addr:housenumber":"2439",
    "addr:postcode":"30017",
    "addr:street":"Trace Pond Cir",
    "iso:country":"US",
    "sg:address":"2439 Trace Pond Cir",
    "sg:city":"Grayson",
    "sg:classifiers":[
        {
            "category":"Manufacturing",
            "subcategory":"Building Materials",
            "type":"Manufacturing & Wholesale Goods"
        },
        {
            "category":"Home & Garden",
            "subcategory":"Carpets & Floor Coverings",
            "type":"Retail Goods"
        }
    ],
    "sg:phone":"+1 770 972 4501",
    "sg:postcode":"30017",
    "sg:province":"GA",
    "sg:tags":[
        "materials-wholesale",
        "manufacturer"
    ],
    "wof:name":"Rudi Floor Covering",
    "wof:placetype":"venue"
},
  "geometry": {"coordinates":[-83.98052300000001,33.871301],"type":"Point"}
}