{
  "type": "Feature",
  "properties": {
    "addr:full":"1020 Spring Ives Dr Lawrenceville GA 30043",
    "addr:housenumber":"1020",
    "addr:postcode":"30043",
    "addr:street":"Spring Ives Dr",
    "iso:country":"US",
    "sg:address":"1020 Spring Ives Dr",
    "sg:city":"Lawrenceville",
    "sg:classifiers":[
        {
            "category":"Food & Beverages",
            "subcategory":"Groceries & Convenience Stores",
            "type":"Retail Goods"
        }
    ],
    "sg:phone":"+1 770 963 8263",
    "sg:postcode":"30043",
    "sg:province":"GA",
    "wof:name":"Tae Jin Food Co USA Inc",
    "wof:placetype":"venue"
},
  "geometry": {"coordinates":[-84.050933,34.001898],"type":"Point"}
}