{
  "type": "Feature",
  "properties": {
    "addr:full":"253 Timber Creek Ln SW Marietta GA 30060",
    "addr:housenumber":"253",
    "addr:postcode":"30060",
    "addr:street":"Timber Creek Ln Sw",
    "iso:country":"US",
    "sg:address":"253 Timber Creek Ln SW",
    "sg:city":"Marietta",
    "sg:classifiers":[
        {
            "category":"Autos & Motor Vehicles",
            "subcategory":"Auto Supplies",
            "type":"Retail Goods"
        }
    ],
    "sg:phone":"+1 404 401 1220",
    "sg:postcode":"30060",
    "sg:province":"GA",
    "sg:tags":[
        "automobile",
        "part"
    ],
    "wof:name":"Jnj Dock Bumper Replacement",
    "wof:placetype":"venue"
},
  "geometry": {"coordinates":[-84.559967,33.886143],"type":"Point"}
}