{
  "type": "Feature",
  "properties": {
    "addr:full":"557 S Main St Dawson GA 39842",
    "addr:housenumber":"557",
    "addr:postcode":"39842",
    "addr:street":"S Main St",
    "iso:country":"US",
    "sg:address":"557 S Main St",
    "sg:city":"Dawson",
    "sg:classifiers":[
        {
            "category":"Food & Beverages",
            "subcategory":"Liquor & Beverages",
            "type":"Retail Goods"
        }
    ],
    "sg:phone":"+1 229 995 4500",
    "sg:postcode":"39842",
    "sg:province":"GA",
    "wof:name":"ABC Package Store",
    "wof:placetype":"venue"
},
  "geometry": {"coordinates":[-84.447102,31.766427],"type":"Point"}
}