{
  "type": "Feature",
  "properties": {
    "addr:full":"1665 Georgia Highway 120 Tallapoosa GA 30176",
    "addr:housenumber":"1665",
    "addr:postcode":"30176",
    "addr:street":"Georgia Highway 120 Tallapoosa",
    "iso:country":"US",
    "sg:address":"1665 Georgia Highway 120",
    "sg:city":"Tallapoosa",
    "sg:classifiers":[
        {
            "category":"Education",
            "subcategory":"School",
            "type":"Public Place"
        }
    ],
    "sg:phone":"+1 770 574 2007",
    "sg:postcode":"30176",
    "sg:province":"GA",
    "sg:tags":[
        "high",
        "k-",
        "private"
    ],
    "wof:name":"Haralson County High School",
    "wof:placetype":"venue"
},
  "geometry": {"coordinates":[-85.248735,33.767434],"type":"Point"}
}