{
  "type": "Feature",
  "properties": {
    "iso:country":"US",
    "sg:address":"4646 Forsyth Rd",
    "sg:city":"Macon",
    "sg:classifiers":[
        {
            "category":"Retail",
            "subcategory":"Self-service Laundry",
            "type":"Services"
        }
    ],
    "sg:phone":"+1 478 474 4547",
    "sg:postcode":"31210",
    "sg:province":"GA",
    "wof:name":"Fabra Care Cleaners",
    "wof:placetype":"venue"
},
  "geometry": {"coordinates":[-83.707781,32.873254],"type":"Point"}
}