{
  "type": "Feature",
  "properties": {
    "addr:full":"23 S Elm St Commerce GA 30529",
    "addr:housenumber":"23",
    "addr:postcode":"30529",
    "addr:street":"S Elm St",
    "iso:country":"US",
    "sg:address":"23 S Elm St",
    "sg:city":"Commerce",
    "sg:classifiers":[
        {
            "category":"Restaurant",
            "type":"Food & Drink"
        }
    ],
    "sg:phone":"+1 706 336 8187",
    "sg:postcode":"30529",
    "sg:province":"GA",
    "sg:website":"www.clubhuddle.com",
    "wof:name":"Huddle House",
    "wof:placetype":"venue"
},
  "geometry": {"coordinates":[-83.441422,34.184837],"type":"Point"}
}