{
  "type": "Feature",
  "properties": {
    "iso:country":"US",
    "sg:address":"903 Parrish Ln",
    "sg:city":"Albany",
    "sg:classifiers":[
        {
            "category":"Professional",
            "type":"Services"
        }
    ],
    "sg:phone":"+1 229 436 1679",
    "sg:postcode":"31705",
    "sg:province":"GA",
    "wof:name":"Walter E Davis",
    "wof:placetype":"venue"
},
  "geometry": {"coordinates":[-84.12795699999999,31.469531],"type":"Point"}
}