{
  "type": "Feature",
  "properties": {
    "addr:full":"397 Vfw Rd Thomson GA 30824",
    "addr:housenumber":"397",
    "addr:postcode":"30824",
    "addr:street":"Vfw Rd",
    "iso:country":"US",
    "sg:address":"397 Vfw Rd",
    "sg:city":"Thomson",
    "sg:classifiers":[
        {
            "category":"Manufacturing",
            "subcategory":"Paper Products",
            "type":"Manufacturing & Wholesale Goods"
        }
    ],
    "sg:phone":"+1 706 595 9801",
    "sg:postcode":"30824",
    "sg:province":"GA",
    "sg:website":"www.internationalpaper.com",
    "wof:name":"International Paper Co",
    "wof:placetype":"venue"
},
  "geometry": {"coordinates":[-82.53708899999999,33.437742],"type":"Point"}
}