{
  "type": "Feature",
  "properties": {
    "addr:full":"609 W Franklin St Sylvester GA 31791",
    "addr:housenumber":"609",
    "addr:postcode":"31791",
    "addr:street":"W Franklin St",
    "iso:country":"US",
    "sg:address":"609 W Franklin St",
    "sg:city":"Sylvester",
    "sg:classifiers":[
        {
            "category":"Manufacturing",
            "subcategory":"Furniture",
            "type":"Manufacturing & Wholesale Goods"
        }
    ],
    "sg:phone":"+1 229 776 1188",
    "sg:postcode":"31791",
    "sg:province":"GA",
    "sg:tags":[
        "mfg",
        "made",
        "custom"
    ],
    "wof:name":"Joe Dinkel & Co",
    "wof:placetype":"venue"
},
  "geometry": {"coordinates":[-83.845844,31.530908],"type":"Point"}
}