{
  "type": "Feature",
  "properties": {
    "addr:full":"424 Cambridge Way Augusta GA 30907",
    "addr:housenumber":"424",
    "addr:postcode":"30907",
    "addr:street":"Cambridge Way",
    "iso:country":"US",
    "sg:address":"424 Cambridge Way",
    "sg:city":"Augusta",
    "sg:classifiers":[
        {
            "category":"Professional",
            "subcategory":"Accounting & Tax Preparation",
            "type":"Services"
        }
    ],
    "sg:phone":"+1 706 737 9072",
    "sg:postcode":"30907",
    "sg:province":"GA",
    "sg:tags":[
        "return",
        "filing"
    ],
    "wof:name":"Burnett Income Tax Svc",
    "wof:placetype":"venue"
},
  "geometry": {"coordinates":[-82.06242,33.539035],"type":"Point"}
}