{
  "type": "Feature",
  "properties": {
    "addr:full":"280 Luckie St Atlanta GA 30313",
    "addr:housenumber":"280",
    "addr:postcode":"30313",
    "addr:street":"Luckie St",
    "iso:country":"US",
    "sg:address":"280 Luckie St",
    "sg:city":"Atlanta",
    "sg:classifiers":[
        {
            "category":"Fast Food",
            "type":"Food & Drink"
        },
        {
            "category":"Restaurant",
            "type":"Food & Drink"
        }
    ],
    "sg:phone":"+1 404 688 4114",
    "sg:postcode":"30313",
    "sg:province":"GA",
    "sg:tags":[
        "style",
        "hamburger",
        "family",
        "dog",
        "hot",
        "take",
        "american"
    ],
    "sg:website":"http://www.johnnyrockets.com",
    "wof:name":"Johnny Rockets",
    "wof:placetype":"venue"
},
  "geometry": {"coordinates":[-84.395495,33.762372],"type":"Point"}
}