{
  "type": "Feature",
  "properties": {
    "iso:country":"US",
    "sg:address":"65 Wisteria Blvd",
    "sg:city":"Covington",
    "sg:classifiers":[
        {
            "category":"Shopping",
            "subcategory":"Gifts & Souvenirs",
            "type":"Retail Goods"
        }
    ],
    "sg:phone":"+1 770 788 6337",
    "sg:postcode":"30016",
    "sg:province":"GA",
    "wof:name":"Confetti Gift Baskets",
    "wof:placetype":"venue"
},
  "geometry": {"coordinates":[-83.950439,33.580903],"type":"Point"}
}