{
  "type": "Feature",
  "properties": {
    "addr:full":"1685 Withmere Way Atlanta GA 30338",
    "addr:housenumber":"1685",
    "addr:postcode":"30338",
    "addr:street":"Withmere Way",
    "iso:country":"US",
    "sg:address":"1685 Withmere Way",
    "sg:city":"Atlanta",
    "sg:classifiers":[
        {
            "category":"Professional",
            "subcategory":"Engineering",
            "type":"Services"
        }
    ],
    "sg:phone":"+1 770 671 9997",
    "sg:postcode":"30338",
    "sg:province":"GA",
    "wof:name":"Horne Engineering Services",
    "wof:placetype":"venue"
},
  "geometry": {"coordinates":[-84.325836,33.963322],"type":"Point"}
}