{
  "type": "Feature",
  "properties": {
    "iso:country":"US",
    "sg:address":"461 Ponce De Leon Ave NE",
    "sg:city":"Atlanta",
    "sg:classifiers":[
        {
            "category":"Restaurant",
            "type":"Food & Drink"
        }
    ],
    "sg:menulink":"http://www.allmenus.com/ga/atlanta/76116-dominos-pizza/menu/",
    "sg:phone":"+1 404 874 0030",
    "sg:postcode":"30308",
    "sg:province":"GA",
    "sg:tags":[
        "american",
        "wing",
        "pizza"
    ],
    "wof:name":"Domino's Pizza",
    "wof:placetype":"venue"
},
  "geometry": {"coordinates":[-84.371875,33.773009],"type":"Point"}
}