{
  "type": "Feature",
  "properties": {
    "addr:full":"1861 Columbia Ave Atlanta GA 30337",
    "addr:housenumber":"1861",
    "addr:postcode":"30337",
    "addr:street":"Columbia Ave",
    "iso:country":"US",
    "sg:address":"1861 Columbia Ave",
    "sg:city":"Atlanta",
    "sg:classifiers":[
        {
            "category":"Insurance",
            "subcategory":"Hazard Insurance",
            "type":"Services"
        },
        {
            "category":"Professional",
            "subcategory":"Business Services",
            "type":"Services"
        }
    ],
    "sg:phone":"+1 404 766 4726",
    "sg:postcode":"30337",
    "sg:province":"GA",
    "sg:tags":[
        "bonding",
        "bail",
        "bond"
    ],
    "wof:name":"Pace Bonding Co",
    "wof:placetype":"venue"
},
  "geometry": {"coordinates":[-84.44980700000001,33.652303],"type":"Point"}
}