{
  "type": "Feature",
  "properties": {
    "iso:country":"US",
    "sg:address":"281 Homer Chiles Rd",
    "sg:city":"Haddock",
    "sg:classifiers":[
        {
            "category":"Building & Trades",
            "subcategory":"Construction",
            "type":"Services"
        }
    ],
    "sg:phone":"+1 478 986 7297",
    "sg:postcode":"31033",
    "sg:province":"GA",
    "sg:tags":[
        "house"
    ],
    "wof:name":"Oconee Deck Company",
    "wof:placetype":"venue"
},
  "geometry": {"coordinates":[-83.47409,33.13983],"type":"Point"}
}