{
  "type": "Feature",
  "properties": {
    "iso:country":"US",
    "sg:address":"1175 Thompson Bridge Rd",
    "sg:city":"Gainesville",
    "sg:classifiers":[
        {
            "category":"Personal",
            "subcategory":"Beauty Salon",
            "type":"Services"
        }
    ],
    "sg:phone":"+1 770 718 5772",
    "sg:postcode":"30501",
    "sg:province":"GA",
    "wof:name":"Vogue Salon",
    "wof:placetype":"venue"
},
  "geometry": {"coordinates":[-83.83067699999999,34.317085],"type":"Point"}
}