{
  "type": "Feature",
  "properties": {
    "addr:full":"85 Washington St Jefferson GA 30549",
    "addr:housenumber":"85",
    "addr:postcode":"30549",
    "addr:street":"Washington St",
    "iso:country":"US",
    "sg:address":"85 Washington St",
    "sg:city":"Jefferson",
    "sg:classifiers":[
        {
            "category":"Government",
            "subcategory":"Office",
            "type":"Public Place"
        }
    ],
    "sg:phone":"+1 706 387 6246",
    "sg:postcode":"30549",
    "sg:province":"GA",
    "sg:tags":[
        "county"
    ],
    "wof:name":"Jackson County Clerk-Superior",
    "wof:placetype":"venue"
},
  "geometry": {"coordinates":[-83.57425000000001,34.118391],"type":"Point"}
}