{
  "type": "Feature",
  "properties": {
    "addr:full":"1741 Mountain Industrial Blvd Stone Mountain GA 30083",
    "addr:housenumber":"1741",
    "addr:postcode":"30083",
    "addr:street":"Mountain Industrial Blvd",
    "iso:country":"US",
    "sg:address":"1741 Mountain Industrial Blvd",
    "sg:city":"Stone Mountain",
    "sg:classifiers":[
        {
            "category":"Recreation",
            "subcategory":"Amusement Park",
            "type":"Entertainment"
        },
        {
            "category":"Personal",
            "type":"Services"
        },
        {
            "category":"Sports & Exercise",
            "subcategory":"Bowling",
            "type":"Entertainment"
        }
    ],
    "sg:phone":"+1 770 414 9996",
    "sg:postcode":"30083",
    "sg:province":"GA",
    "sg:tags":[
        "party",
        "planning",
        "event"
    ],
    "sg:website":"www.atlfuncenter.com",
    "wof:name":"Atlanta Fun Center",
    "wof:placetype":"venue"
},
  "geometry": {"coordinates":[-84.19869300000001,33.832867],"type":"Point"}
}