{
  "type": "Feature",
  "properties": {
    "iso:country":"US",
    "sg:address":"3026 Lake Park Dr",
    "sg:city":"Jonesboro",
    "sg:classifiers":[
        {
            "category":"Banks & Credit Unions",
            "subcategory":"Financial Services",
            "type":"Services"
        }
    ],
    "sg:phone":"+1 770 477 7978",
    "sg:postcode":"30236",
    "sg:province":"GA",
    "sg:tags":[
        "investor"
    ],
    "wof:name":"Fonzie Phan Investment Co Inc",
    "wof:placetype":"venue"
},
  "geometry": {"coordinates":[-84.29327600000001,33.521033],"type":"Point"}
}