{
  "type": "Feature",
  "properties": {
    "iso:country":"US",
    "sg:address":"1133 E West Connector # 130",
    "sg:city":"Austell",
    "sg:classifiers":[
        {
            "category":"Personal",
            "subcategory":"Beauty Salon",
            "type":"Services"
        },
        {
            "category":"Personal",
            "subcategory":"Barber",
            "type":"Services"
        }
    ],
    "sg:phone":"+1 770 863 9493",
    "sg:postcode":"30106",
    "sg:province":"GA",
    "sg:tags":[
        "hair",
        "accessory",
        "stylist",
        "supply"
    ],
    "sg:website":"http://www.supercuts.com/",
    "wof:name":"Supercuts",
    "wof:placetype":"venue"
},
  "geometry": {"coordinates":[-84.587996,33.857176],"type":"Point"}
}