{
  "type": "Feature",
  "properties": {
    "addr:full":"6941 Highway 85 Ste B Riverdale GA 30274",
    "addr:housenumber":"6941",
    "addr:postcode":"30274",
    "addr:street":"Highway 85 Ste B",
    "iso:country":"US",
    "sg:address":"6941 Highway 85 Ste B",
    "sg:city":"Riverdale",
    "sg:classifiers":[
        {
            "category":"Autos & Motor Vehicles",
            "subcategory":"Fuel & Gas Station",
            "type":"Retail Goods"
        },
        {
            "category":"Autos & Motor Vehicles",
            "subcategory":"Auto Supplies",
            "type":"Retail Goods"
        },
        {
            "category":"Retail",
            "subcategory":"Auto Repair",
            "type":"Services"
        }
    ],
    "sg:phone":"+1 770 997 6263",
    "sg:postcode":"30274",
    "sg:province":"GA",
    "sg:tags":[
        "tire"
    ],
    "wof:name":"Tire One Auto Service",
    "wof:placetype":"venue"
},
  "geometry": {"coordinates":[-84.413336,33.565646],"type":"Point"}
}