{
  "type": "Feature",
  "properties": {
    "addr:full":"69 Happy Landing Rd Waynesville GA 31566",
    "addr:housenumber":"69",
    "addr:postcode":"31566",
    "addr:street":"Happy Landing Rd",
    "iso:country":"US",
    "sg:address":"69 Happy Landing Rd",
    "sg:city":"Waynesville",
    "sg:classifiers":[
        {
            "category":"Building & Trades",
            "subcategory":"Pest Control",
            "type":"Services"
        }
    ],
    "sg:phone":"+1 912 778 3964",
    "sg:postcode":"31566",
    "sg:province":"GA",
    "wof:name":"Bull's Eye Pest Control",
    "wof:placetype":"venue"
},
  "geometry": {"coordinates":[-81.856616,31.162813],"type":"Point"}
}