{
  "type": "Feature",
  "properties": {
    "iso:country":"US",
    "sg:address":"1017 1st Ave",
    "sg:city":"Columbus",
    "sg:classifiers":[
        {
            "category":"Government",
            "subcategory":"Court House",
            "type":"Public Place"
        }
    ],
    "sg:phone":"+1 706 653 0827",
    "sg:postcode":"31901",
    "sg:province":"GA",
    "sg:tags":[
        "federal"
    ],
    "wof:name":"US District Court",
    "wof:placetype":"venue"
},
  "geometry": {"coordinates":[-84.9918,32.466369],"type":"Point"}
}