{
  "type": "Feature",
  "properties": {
    "iso:country":"US",
    "sg:address":"3266 Laramie Dr SE",
    "sg:city":"Atlanta",
    "sg:classifiers":[
        {
            "category":"Professional",
            "type":"Services"
        }
    ],
    "sg:phone":"+1 770 434 3349",
    "sg:postcode":"30339",
    "sg:province":"GA",
    "wof:name":"Keith Kennesaw LLC",
    "wof:placetype":"venue"
},
  "geometry": {"coordinates":[-84.462311,33.863361],"type":"Point"}
}