{
  "type": "Feature",
  "properties": {
    "iso:country":"US",
    "sg:address":"1501 Plunkett Rd",
    "sg:city":"Buford",
    "sg:classifiers":[
        {
            "category":"Building & Trades",
            "subcategory":"Construction",
            "type":"Services"
        }
    ],
    "sg:phone":"+1 770 616 8565",
    "sg:postcode":"30519",
    "sg:province":"GA",
    "sg:tags":[
        "contractor"
    ],
    "wof:name":"Cns Siding Contractors",
    "wof:placetype":"venue"
},
  "geometry": {"coordinates":[-83.995892,34.073534],"type":"Point"}
}