{
  "type": "Feature",
  "properties": {
    "iso:country":"US",
    "sg:address":"302 Poor Robin Ext",
    "sg:city":"Baxley",
    "sg:classifiers":[
        {
            "category":"Real Estate",
            "subcategory":"Real Estate Services",
            "type":"Services"
        },
        {
            "category":"Real Estate",
            "subcategory":"Real Estate Agent",
            "type":"Services"
        }
    ],
    "sg:phone":"+1 912 367 7128",
    "sg:postcode":"31513",
    "sg:province":"GA",
    "sg:tags":[
        "buyer",
        "broker"
    ],
    "wof:name":"Park Realty",
    "wof:placetype":"venue"
},
  "geometry": {"coordinates":[-82.353163,31.761649],"type":"Point"}
}