{
  "type": "Feature",
  "properties": {
    "iso:country":"US",
    "sg:address":"1147 Old Perkins Rd",
    "sg:city":"Millen",
    "sg:classifiers":[
        {
            "category":"Farming",
            "subcategory":"Livestock Farm",
            "type":"Manufacturing & Wholesale Goods"
        }
    ],
    "sg:phone":"+1 478 982 4404",
    "sg:postcode":"30442",
    "sg:province":"GA",
    "sg:tags":[
        "beef",
        "feedlot",
        "cattle"
    ],
    "wof:name":"W Wasden",
    "wof:placetype":"venue"
},
  "geometry": {"coordinates":[-81.930324,32.862874],"type":"Point"}
}