{
  "type": "Feature",
  "properties": {
    "addr:full":"157 Hodges St Cornelia GA 30531",
    "addr:housenumber":"157",
    "addr:postcode":"30531",
    "addr:street":"Hodges St",
    "iso:country":"US",
    "sg:address":"157 Hodges St",
    "sg:city":"Cornelia",
    "sg:classifiers":[
        {
            "category":"Health Services",
            "subcategory":"Doctor",
            "type":"Services"
        }
    ],
    "sg:phone":"+1 770 534 2336",
    "sg:postcode":"30531",
    "sg:province":"GA",
    "sg:tags":[
        "dentist"
    ],
    "wof:name":"Donald Cantrell DDS",
    "wof:placetype":"venue"
},
  "geometry": {"coordinates":[-83.527625,34.511606],"type":"Point"}
}