{
  "type": "Feature",
  "properties": {
    "iso:country":"US",
    "sg:address":"4750 Houston Rd",
    "sg:city":"Macon",
    "sg:classifiers":[
        {
            "category":"Wholesale",
            "subcategory":"Motor Vehicles",
            "type":"Manufacturing & Wholesale Goods"
        }
    ],
    "sg:phone":"+1 478 785 0999",
    "sg:postcode":"31216",
    "sg:province":"GA",
    "sg:tags":[
        "automobile",
        "used"
    ],
    "wof:name":"Car Land",
    "wof:placetype":"venue"
},
  "geometry": {"coordinates":[-83.659441,32.770167],"type":"Point"}
}