{
  "type": "Feature",
  "properties": {
    "addr:full":"277 Roberts Path Woodbine GA 31569",
    "addr:housenumber":"277",
    "addr:postcode":"31569",
    "addr:street":"Roberts Path",
    "iso:country":"US",
    "sg:address":"277 Roberts Path",
    "sg:city":"Woodbine",
    "sg:classifiers":[
        {
            "category":"Education",
            "subcategory":"School",
            "type":"Public Place"
        }
    ],
    "sg:phone":"+1 912 576 4800",
    "sg:postcode":"31569",
    "sg:province":"GA",
    "sg:website":"www.mamielougross.org",
    "wof:name":"Mamie Lou Gross Elem School",
    "wof:placetype":"venue"
},
  "geometry": {"coordinates":[-81.67610999999999,30.846794],"type":"Point"}
}