{
  "type": "Feature",
  "properties": {
    "addr:full":"204 Hudson St Americus GA 31709",
    "addr:housenumber":"204",
    "addr:postcode":"31709",
    "addr:street":"Hudson St",
    "iso:country":"US",
    "sg:address":"204 Hudson St",
    "sg:city":"Americus",
    "sg:classifiers":[
        {
            "category":"Utilities",
            "subcategory":"Mobile Phone",
            "type":"Services"
        }
    ],
    "sg:phone":"+1 229 924 2969",
    "sg:postcode":"31709",
    "sg:province":"GA",
    "sg:tags":[
        "repair",
        "beeper"
    ],
    "wof:name":"Propage Inc",
    "wof:placetype":"venue"
},
  "geometry": {"coordinates":[-84.217986,32.074864],"type":"Point"}
}