{
  "type": "Feature",
  "properties": {
    "iso:country":"US",
    "sg:address":"2147 Green Way Cir SE",
    "sg:city":"Conyers",
    "sg:classifiers":[
        {
            "category":"Professional",
            "subcategory":"Management & Consulting",
            "type":"Services"
        }
    ],
    "sg:phone":"+1 770 761 4433",
    "sg:postcode":"30013",
    "sg:province":"GA",
    "sg:tags":[
        "business"
    ],
    "wof:name":"Paschal Safety Consulants",
    "wof:placetype":"venue"
},
  "geometry": {"coordinates":[-83.973213,33.628077],"type":"Point"}
}