{
  "type": "Feature",
  "properties": {
    "addr:full":"3295 Chamblee Dunwoody Rd Atlanta GA 30341",
    "addr:housenumber":"3295",
    "addr:postcode":"30341",
    "addr:street":"Chamblee Dunwoody Rd",
    "iso:country":"US",
    "sg:address":"3295 Chamblee Dunwoody Rd",
    "sg:city":"Atlanta",
    "sg:classifiers":[
        {
            "category":"Restaurant",
            "type":"Food & Drink"
        }
    ],
    "sg:phone":"+1 770 216 9933",
    "sg:postcode":"30341",
    "sg:province":"GA",
    "sg:tags":[
        "chinese"
    ],
    "wof:name":"Royal China Restaurant",
    "wof:placetype":"venue"
},
  "geometry": {"coordinates":[-84.2929,33.891701],"type":"Point"}
}