{
  "type": "Feature",
  "properties": {
    "addr:full":"469 Calloway Rd Exd Evans GA 30809",
    "addr:housenumber":"469",
    "addr:postcode":"30809",
    "addr:street":"Calloway Rd Exd",
    "iso:country":"US",
    "sg:address":"469 Calloway Rd Exd",
    "sg:city":"Evans",
    "sg:classifiers":[
        {
            "category":"Retail",
            "subcategory":"Auto Repair",
            "type":"Services"
        }
    ],
    "sg:phone":"+1 706 863 7668",
    "sg:postcode":"30809",
    "sg:province":"GA",
    "sg:tags":[
        "body"
    ],
    "wof:name":"Matco Tools",
    "wof:placetype":"venue"
},
  "geometry": {"coordinates":[-82.202679,33.53428],"type":"Point"}
}