{
  "type": "Feature",
  "properties": {
    "iso:country":"US",
    "sg:address":"129 W Washington St",
    "sg:city":"Monroe",
    "sg:classifiers":[
        {
            "category":"Retail",
            "subcategory":"Funeral Services",
            "type":"Services"
        }
    ],
    "sg:phone":"+1 770 267 2642",
    "sg:postcode":"30655",
    "sg:province":"GA",
    "sg:tags":[
        "director"
    ],
    "wof:name":"Young's Funeral Home",
    "wof:placetype":"venue"
},
  "geometry": {"coordinates":[-83.71389499999999,33.793301],"type":"Point"}
}