{
  "type": "Feature",
  "properties": {
    "addr:full":"1911 W Forrest Ave Atlanta GA 30344",
    "addr:housenumber":"1911",
    "addr:postcode":"30344",
    "addr:street":"W Forrest Ave",
    "iso:country":"US",
    "sg:address":"1911 W Forrest Ave",
    "sg:city":"Atlanta",
    "sg:classifiers":[
        {
            "category":"Retail",
            "subcategory":"Auto Repair",
            "type":"Services"
        }
    ],
    "sg:phone":"+1 404 361 9965",
    "sg:postcode":"30344",
    "sg:province":"GA",
    "sg:tags":[
        "transmission"
    ],
    "wof:name":"Reliable Transmission Svc Inc",
    "wof:placetype":"venue"
},
  "geometry": {"coordinates":[-84.451033,33.686338],"type":"Point"}
}