{
  "type": "Feature",
  "properties": {
    "iso:country":"US",
    "sg:address":"5085 Avalon Ridge Pkwy",
    "sg:city":"Norcross",
    "sg:classifiers":[
        {
            "category":"Utilities",
            "subcategory":"Telephone",
            "type":"Services"
        }
    ],
    "sg:phone":"+1 770 453 9190",
    "sg:postcode":"30071",
    "sg:province":"GA",
    "sg:tags":[
        "host",
        "internet"
    ],
    "wof:name":"Ispsoft Inc",
    "wof:placetype":"venue"
},
  "geometry": {"coordinates":[-84.194462,33.964927],"type":"Point"}
}