{
  "type": "Feature",
  "properties": {
    "iso:country":"US",
    "sg:address":"50 Lakeland Dr NE",
    "sg:city":"Atlanta",
    "sg:classifiers":[
        {
            "category":"Professional",
            "type":"Services"
        }
    ],
    "sg:phone":"+1 404 266 9704",
    "sg:postcode":"30305",
    "sg:province":"GA",
    "wof:name":"RBA Svc Inc",
    "wof:placetype":"venue"
},
  "geometry": {"coordinates":[-84.38157699999999,33.84965],"type":"Point"}
}