{
  "type": "Feature",
  "properties": {
    "addr:full":"1540 Dogwood Dr SE Conyers GA 30013",
    "addr:housenumber":"1540",
    "addr:postcode":"30013",
    "addr:street":"Dogwood Dr Se",
    "iso:country":"US",
    "sg:address":"1540 Dogwood Dr SE",
    "sg:city":"Conyers",
    "sg:classifiers":[
        {
            "category":"Shopping",
            "subcategory":"Computers & Home Electronics",
            "type":"Retail Goods"
        }
    ],
    "sg:phone":"+1 770 483 4712",
    "sg:postcode":"30013",
    "sg:province":"GA",
    "wof:name":"Circuit City",
    "wof:placetype":"venue"
},
  "geometry": {"coordinates":[-84.000863,33.651885],"type":"Point"}
}