{
  "type": "Feature",
  "properties": {
    "addr:full":"1239 Fowler St Atlanta GA 30318",
    "addr:housenumber":"1239",
    "addr:postcode":"30318",
    "addr:street":"Fowler St",
    "iso:country":"US",
    "sg:address":"1239 Fowler St",
    "sg:city":"Atlanta",
    "sg:classifiers":[
        {
            "category":"Home & Garden",
            "subcategory":"Garden Supply",
            "type":"Retail Goods"
        }
    ],
    "sg:phone":"+1 404 532 0001",
    "sg:postcode":"30318",
    "sg:province":"GA",
    "sg:tags":[
        "nursery",
        "gardening"
    ],
    "wof:name":"Flora Hydroponics",
    "wof:placetype":"venue"
},
  "geometry": {"coordinates":[-84.392892,33.788658],"type":"Point"}
}