{
  "type": "Feature",
  "properties": {
    "addr:full":"2700 White Pine Ln Mansfield GA 30055",
    "addr:housenumber":"2700",
    "addr:postcode":"30055",
    "addr:street":"White Pine Ln",
    "iso:country":"US",
    "sg:address":"2700 White Pine Ln",
    "sg:city":"Mansfield",
    "sg:classifiers":[
        {
            "category":"Autos & Motor Vehicles",
            "subcategory":"Motorcycle Sales",
            "type":"Retail Goods"
        }
    ],
    "sg:phone":"+1 770 784 3478",
    "sg:postcode":"30055",
    "sg:province":"GA",
    "sg:tags":[
        "scooters-parts",
        "supply"
    ],
    "wof:name":"Georgia Prowlers Inc",
    "wof:placetype":"venue"
},
  "geometry": {"coordinates":[-83.719239,33.565444],"type":"Point"}
}