{
  "type": "Feature",
  "properties": {
    "addr:full":"291 Johnnie Collins Way Dahlonega GA 30533",
    "addr:housenumber":"291",
    "addr:postcode":"30533",
    "addr:street":"Johnnie Collins Way",
    "iso:country":"US",
    "sg:address":"291 Johnnie Collins Way",
    "sg:city":"Dahlonega",
    "sg:classifiers":[
        {
            "category":"Real Estate",
            "subcategory":"Real Estate Agent",
            "type":"Services"
        }
    ],
    "sg:phone":"+1 706 864 8888",
    "sg:postcode":"30533",
    "sg:province":"GA",
    "wof:name":"Southampton Properties",
    "wof:placetype":"venue"
},
  "geometry": {"coordinates":[-84.01241,34.567545],"type":"Point"}
}