{
  "type": "Feature",
  "properties": {
    "iso:country":"US",
    "sg:address":"897 Newtown Church Rd NE",
    "sg:city":"Calhoun",
    "sg:classifiers":[
        {
            "category":"Organizations",
            "subcategory":"Religious Organization",
            "type":"Services"
        }
    ],
    "sg:phone":"+1 706 629 9818",
    "sg:postcode":"30701",
    "sg:province":"GA",
    "wof:name":"New Town Baptist Church",
    "wof:placetype":"venue"
},
  "geometry": {"coordinates":[-84.90854899999999,34.529138],"type":"Point"}
}