{
  "type": "Feature",
  "properties": {
    "iso:country":"US",
    "sg:address":"622 Greenbriar Rd",
    "sg:city":"Warner Robins",
    "sg:classifiers":[
        {
            "category":"Recreation",
            "type":"Entertainment"
        }
    ],
    "sg:phone":"+1 478 923 2202",
    "sg:postcode":"31093",
    "sg:province":"GA",
    "sg:tags":[
        "sporting",
        "park",
        "amusement"
    ],
    "wof:name":"Olympia Skate Center",
    "wof:placetype":"venue"
},
  "geometry": {"coordinates":[-83.638397,32.6408],"type":"Point"}
}