{
  "type": "Feature",
  "properties": {
    "addr:full":"2330 Fieldstone Dr SE Conyers GA 30013",
    "addr:housenumber":"2330",
    "addr:postcode":"30013",
    "addr:street":"Fieldstone Dr Se",
    "iso:country":"US",
    "sg:address":"2330 Fieldstone Dr SE",
    "sg:city":"Conyers",
    "sg:classifiers":[
        {
            "category":"Building & Trades",
            "subcategory":"Construction",
            "type":"Services"
        }
    ],
    "sg:phone":"+1 770 483 1940",
    "sg:postcode":"30013",
    "sg:province":"GA",
    "sg:tags":[
        "general",
        "contractor"
    ],
    "wof:name":"Cornerstone Services",
    "wof:placetype":"venue"
},
  "geometry": {"coordinates":[-83.96687300000001,33.626827],"type":"Point"}
}