{
  "type": "Feature",
  "properties": {
    "addr:full":"2540 Cumberland Blvd SE Smyrna GA 30080",
    "addr:housenumber":"2540",
    "addr:postcode":"30080",
    "addr:street":"Cumberland Blvd Se",
    "iso:country":"US",
    "sg:address":"2540 Cumberland Blvd SE",
    "sg:city":"Smyrna",
    "sg:classifiers":[
        {
            "category":"Home & Garden",
            "subcategory":"Home Furnishings",
            "type":"Retail Goods"
        }
    ],
    "sg:phone":"+1 770 319 1465",
    "sg:postcode":"30080",
    "sg:province":"GA",
    "sg:tags":[
        "including",
        "kitchenware",
        "drapery"
    ],
    "wof:name":"Homegoods",
    "wof:placetype":"venue"
},
  "geometry": {"coordinates":[-84.46453700000001,33.878048],"type":"Point"}
}