{
  "type": "Feature",
  "properties": {
    "iso:country":"US",
    "sg:address":"370 Darren Dr",
    "sg:city":"Fayetteville",
    "sg:classifiers":[
        {
            "category":"Professional",
            "subcategory":"Business Services",
            "type":"Services"
        }
    ],
    "sg:phone":"+1 770 461 4647",
    "sg:postcode":"30215",
    "sg:province":"GA",
    "wof:name":"Ce Enterprises Inc",
    "wof:placetype":"venue"
},
  "geometry": {"coordinates":[-84.50232,33.360527],"type":"Point"}
}