{
  "type": "Feature",
  "properties": {
    "iso:country":"US",
    "sg:address":"1400 Montreal Rd",
    "sg:city":"Tucker",
    "sg:classifiers":[
        {
            "category":"Real Estate",
            "subcategory":"Real Estate Agent",
            "type":"Services"
        }
    ],
    "sg:phone":"+1 770 908 0720",
    "sg:postcode":"30084",
    "sg:province":"GA",
    "wof:name":"Lucretia B Ramsey Inc",
    "wof:placetype":"venue"
},
  "geometry": {"coordinates":[-84.254907,33.826191],"type":"Point"}
}