{
  "type": "Feature",
  "properties": {
    "iso:country":"US",
    "sg:address":"158 Tall Timbers Cir",
    "sg:city":"Newnan",
    "sg:classifiers":[
        {
            "category":"Shopping",
            "type":"Retail Goods"
        }
    ],
    "sg:phone":"+1 678 423 9374",
    "sg:postcode":"30263",
    "sg:province":"GA",
    "sg:tags":[
        "packaging",
        "wholesale"
    ],
    "wof:name":"Precision Packaging",
    "wof:placetype":"venue"
},
  "geometry": {"coordinates":[-84.733311,33.373587],"type":"Point"}
}