{
  "type": "Feature",
  "properties": {
    "addr:full":"819 Park St Gainesville GA 30501",
    "addr:housenumber":"819",
    "addr:postcode":"30501",
    "addr:street":"Park St",
    "iso:country":"US",
    "sg:address":"819 Park St",
    "sg:city":"Gainesville",
    "sg:classifiers":[
        {
            "category":"Personal",
            "type":"Services"
        }
    ],
    "sg:phone":"+1 770 297 7170",
    "sg:postcode":"30501",
    "sg:province":"GA",
    "wof:name":"Meetings & Milestones",
    "wof:placetype":"venue"
},
  "geometry": {"coordinates":[-83.820932,34.306797],"type":"Point"}
}