{
  "type": "Feature",
  "properties": {
    "addr:full":"1870 Atlanta Hwy Gainesville GA 30504",
    "addr:housenumber":"1870",
    "addr:postcode":"30504",
    "addr:street":"Atlanta Hwy",
    "iso:country":"US",
    "sg:address":"1870 Atlanta Hwy",
    "sg:city":"Gainesville",
    "sg:classifiers":[
        {
            "category":"Food & Beverages",
            "subcategory":"Bakery",
            "type":"Retail Goods"
        }
    ],
    "sg:phone":"+1 678 450 0061",
    "sg:postcode":"30504",
    "sg:province":"GA",
    "wof:name":"La Mejor De Michoacan Pasteler",
    "wof:placetype":"venue"
},
  "geometry": {"coordinates":[-83.84578500000001,34.259681],"type":"Point"}
}