{
  "type": "Feature",
  "properties": {
    "iso:country":"US",
    "sg:address":"4250 Roswell Rd NE",
    "sg:city":"Marietta",
    "sg:classifiers":[
        {
            "category":"Food & Beverages",
            "subcategory":"Groceries & Convenience Stores",
            "type":"Retail Goods"
        }
    ],
    "sg:phone":"+1 678 560 3585",
    "sg:postcode":"30062",
    "sg:province":"GA",
    "sg:website":"www.traderjoes.com/index.html",
    "wof:name":"Trader Joe's",
    "wof:placetype":"venue"
},
  "geometry": {"coordinates":[-84.428213,33.982759],"type":"Point"}
}