{
  "type": "Feature",
  "properties": {
    "iso:country":"US",
    "sg:address":"5225 Windward Pkwy",
    "sg:city":"Alpharetta",
    "sg:classifiers":[
        {
            "category":"Banks & Credit Unions",
            "subcategory":"Bank",
            "type":"Services"
        }
    ],
    "sg:phone":"+1 770 667 7899",
    "sg:postcode":"30004",
    "sg:province":"GA",
    "wof:name":"Futurus Bank",
    "wof:placetype":"venue"
},
  "geometry": {"coordinates":[-84.27600099999999,34.091301],"type":"Point"}
}