{
  "type": "Feature",
  "properties": {
    "addr:full":"115 S Wilkinson St Milledgeville GA 31061",
    "addr:housenumber":"115",
    "addr:postcode":"31061",
    "addr:street":"S Wilkinson St",
    "iso:country":"US",
    "sg:address":"115 S Wilkinson St",
    "sg:city":"Milledgeville",
    "sg:classifiers":[
        {
            "category":"Shopping",
            "subcategory":"Books",
            "type":"Retail Goods"
        }
    ],
    "sg:phone":"+1 478 445 7303",
    "sg:postcode":"31061",
    "sg:province":"GA",
    "wof:name":"Paw Prints Bookstore",
    "wof:placetype":"venue"
},
  "geometry": {"coordinates":[-83.228832,33.080684],"type":"Point"}
}