{
  "type": "Feature",
  "properties": {
    "addr:full":"830 Moseley Dr Stockbridge GA 30281",
    "addr:housenumber":"830",
    "addr:postcode":"30281",
    "addr:street":"Moseley Dr",
    "iso:country":"US",
    "sg:address":"830 Moseley Dr",
    "sg:city":"Stockbridge",
    "sg:classifiers":[
        {
            "category":"Building & Trades",
            "subcategory":"Plumbing",
            "type":"Services"
        }
    ],
    "sg:phone":"+1 678 289 6366",
    "sg:postcode":"30281",
    "sg:province":"GA",
    "sg:tags":[
        "plumbing",
        "contractor"
    ],
    "wof:name":"Mock Plumbing & Mechanical",
    "wof:placetype":"venue"
},
  "geometry": {"coordinates":[-84.16211199999999,33.569143],"type":"Point"}
}