{
  "type": "Feature",
  "properties": {
    "addr:full":"720 Sandtown Rd SW Marietta GA 30008",
    "addr:housenumber":"720",
    "addr:postcode":"30008",
    "addr:street":"Sandtown Rd Sw",
    "iso:country":"US",
    "sg:address":"720 Sandtown Rd SW",
    "sg:city":"Marietta",
    "sg:classifiers":[
        {
            "category":"Food & Beverages",
            "subcategory":"Groceries & Convenience Stores",
            "type":"Retail Goods"
        }
    ],
    "sg:phone":"+1 770 218 1200",
    "sg:postcode":"30008",
    "sg:province":"GA",
    "sg:tags":[
        "grocer"
    ],
    "sg:website":"http://www.save-a-lot.com/",
    "wof:name":"Save-A-Lot",
    "wof:placetype":"venue"
},
  "geometry": {"coordinates":[-84.55565799999999,33.933933],"type":"Point"}
}