{
  "type": "Feature",
  "properties": {
    "iso:country":"US",
    "sg:address":"2727 Paces Ferry Rd SE",
    "sg:city":"Atlanta",
    "sg:classifiers":[
        {
            "category":"Professional",
            "subcategory":"Lawyer & Legal Services",
            "type":"Services"
        }
    ],
    "sg:phone":"+1 770 436 5353",
    "sg:postcode":"30339",
    "sg:province":"GA",
    "sg:tags":[
        "personal",
        "injury"
    ],
    "wof:name":"Kirschner & Venker",
    "wof:placetype":"venue"
},
  "geometry": {"coordinates":[-84.47399900000001,33.865398],"type":"Point"}
}