{
  "type": "Feature",
  "properties": {
    "addr:full":"825 Jamerson Rd Marietta GA 30066",
    "addr:housenumber":"825",
    "addr:postcode":"30066",
    "addr:street":"Jamerson Rd",
    "iso:country":"US",
    "sg:address":"825 Jamerson Rd",
    "sg:city":"Marietta",
    "sg:classifiers":[
        {
            "category":"Building & Trades",
            "subcategory":"Construction",
            "type":"Services"
        }
    ],
    "sg:phone":"+1 770 516 6574",
    "sg:postcode":"30066",
    "sg:province":"GA",
    "sg:tags":[
        "painter"
    ],
    "wof:name":"J & S Painting Inc",
    "wof:placetype":"venue"
},
  "geometry": {"coordinates":[-84.526994,34.068304],"type":"Point"}
}