{
  "type": "Feature",
  "properties": {
    "addr:full":"1828 Flat Rock Rd Stockbridge GA 30281",
    "addr:housenumber":"1828",
    "addr:postcode":"30281",
    "addr:street":"Flat Rock Rd",
    "iso:country":"US",
    "sg:address":"1828 Flat Rock Rd",
    "sg:city":"Stockbridge",
    "sg:classifiers":[
        {
            "category":"Recreation",
            "type":"Entertainment"
        }
    ],
    "sg:phone":"+1 770 507 4410",
    "sg:postcode":"30281",
    "sg:province":"GA",
    "wof:name":"Blackjack Billiards",
    "wof:placetype":"venue"
},
  "geometry": {"coordinates":[-84.219747,33.579069],"type":"Point"}
}