{
  "type": "Feature",
  "properties": {
    "addr:full":"2925 Emerson Lake Dr Snellville GA 30078",
    "addr:housenumber":"2925",
    "addr:postcode":"30078",
    "addr:street":"Emerson Lake Dr",
    "iso:country":"US",
    "sg:address":"2925 Emerson Lake Dr",
    "sg:city":"Snellville",
    "sg:classifiers":[
        {
            "category":"Professional",
            "type":"Services"
        }
    ],
    "sg:phone":"+1 770 736 1054",
    "sg:postcode":"30078",
    "sg:province":"GA",
    "sg:tags":[
        "establishment"
    ],
    "wof:name":"Ready Rock Records",
    "wof:placetype":"venue"
},
  "geometry": {"coordinates":[-83.98382100000001,33.85225],"type":"Point"}
}