{
  "type": "Feature",
  "properties": {
    "addr:full":"101 W Wieuca Rd Ste 101 Atlanta GA 30342",
    "addr:housenumber":"101",
    "addr:postcode":"30342",
    "addr:street":"W Wieuca Rd Ste 101",
    "iso:country":"US",
    "sg:address":"101 W Wieuca Rd Ste 101",
    "sg:city":"Atlanta",
    "sg:classifiers":[
        {
            "category":"Real Estate",
            "subcategory":"Real Estate Services",
            "type":"Services"
        },
        {
            "category":"Real Estate",
            "subcategory":"Real Estate Operator",
            "type":"Services"
        }
    ],
    "sg:phone":"+1 404 236 8817",
    "sg:postcode":"30342",
    "sg:province":"GA",
    "sg:tags":[
        "apartment",
        "property",
        "management"
    ],
    "sg:website":"www.mystudentrental.com",
    "wof:name":"EFF Enterprises",
    "wof:placetype":"venue"
},
  "geometry": {"coordinates":[-84.381928,33.877904],"type":"Point"}
}