{
  "type": "Feature",
  "properties": {
    "iso:country":"US",
    "sg:address":"393 2nd Ave SE",
    "sg:city":"Cairo",
    "sg:classifiers":[
        {
            "category":"Organizations",
            "subcategory":"Religious Organization",
            "type":"Services"
        }
    ],
    "sg:phone":"+1 229 377 9894",
    "sg:postcode":"39828",
    "sg:province":"GA",
    "wof:name":"New Life Deliverance Inc",
    "wof:placetype":"venue"
},
  "geometry": {"coordinates":[-84.205029,30.875398],"type":"Point"}
}