{
  "type": "Feature",
  "properties": {
    "addr:full":"2000 Sullivan Rd Ste G Atlanta GA 30337",
    "addr:housenumber":"2000",
    "addr:postcode":"30337",
    "addr:street":"Sullivan Rd Ste G",
    "iso:country":"US",
    "sg:address":"2000 Sullivan Rd Ste G",
    "sg:city":"Atlanta",
    "sg:classifiers":[
        {
            "category":"Professional",
            "subcategory":"Business Services",
            "type":"Services"
        }
    ],
    "sg:phone":"+1 770 997 8055",
    "sg:postcode":"30337",
    "sg:province":"GA",
    "sg:tags":[
        "delivery",
        "courier"
    ],
    "sg:website":"www.amexpediting.com",
    "wof:name":"American Expediting Co",
    "wof:placetype":"venue"
},
  "geometry": {"coordinates":[-84.453215,33.624709],"type":"Point"}
}