{
  "type": "Feature",
  "properties": {
    "addr:full":"6507 Professional Pl Riverdale GA 30274",
    "addr:housenumber":"6507",
    "addr:postcode":"30274",
    "addr:street":"Professional Pl",
    "iso:country":"US",
    "sg:address":"6507 Professional Pl",
    "sg:city":"Riverdale",
    "sg:classifiers":[
        {
            "category":"Health Services",
            "subcategory":"Doctor",
            "type":"Services"
        }
    ],
    "sg:phone":"+1 770 991 2530",
    "sg:postcode":"30274",
    "sg:province":"GA",
    "sg:tags":[
        "cardiologist"
    ],
    "wof:name":"Olatidoye Abiodun G MD",
    "wof:placetype":"venue"
},
  "geometry": {"coordinates":[-84.396103,33.5765],"type":"Point"}
}