{
  "type": "Feature",
  "properties": {
    "iso:country":"US",
    "sg:address":"115 N Hamilton St",
    "sg:city":"Dalton",
    "sg:classifiers":[
        {
            "category":"Personal",
            "subcategory":"Beauty Salon",
            "type":"Services"
        }
    ],
    "sg:phone":"+1 706 226 8788",
    "sg:postcode":"30720",
    "sg:province":"GA",
    "wof:name":"Sothies",
    "wof:placetype":"venue"
},
  "geometry": {"coordinates":[-84.967901,34.771701],"type":"Point"}
}