{
  "type": "Feature",
  "properties": {
    "iso:country":"US",
    "sg:address":"4330 Lawrenceville Hwy NW",
    "sg:city":"Lilburn",
    "sg:classifiers":[
        {
            "category":"Retail",
            "subcategory":"Auto Repair",
            "type":"Services"
        }
    ],
    "sg:phone":"+1 678 380 8444",
    "sg:postcode":"30047",
    "sg:province":"GA",
    "wof:name":"Quality Autocare Center Inc",
    "wof:placetype":"venue"
},
  "geometry": {"coordinates":[-84.125366,33.901103],"type":"Point"}
}