{
  "type": "Feature",
  "properties": {
    "iso:country":"US",
    "sg:address":"201 Quacco Rd",
    "sg:city":"Savannah",
    "sg:classifiers":[
        {
            "category":"Building & Trades",
            "subcategory":"Construction",
            "type":"Services"
        }
    ],
    "sg:phone":"+1 912 231 0903",
    "sg:postcode":"31419",
    "sg:province":"GA",
    "sg:tags":[
        "roofing",
        "contractor"
    ],
    "wof:name":"All City Metal & Roofing",
    "wof:placetype":"venue"
},
  "geometry": {"coordinates":[-81.24318599999999,32.023468],"type":"Point"}
}