{
  "type": "Feature",
  "properties": {
    "iso:country":"US",
    "sg:address":"101 Blackbeard Island Cir",
    "sg:city":"Brunswick",
    "sg:classifiers":[
        {
            "category":"Professional",
            "type":"Services"
        }
    ],
    "sg:phone":"+1 912 261 0567",
    "sg:postcode":"31520",
    "sg:province":"GA",
    "sg:tags":[
        "establishment"
    ],
    "wof:name":"Sound 'n Sights",
    "wof:placetype":"venue"
},
  "geometry": {"coordinates":[-81.455719,31.17099],"type":"Point"}
}