{
  "type": "Feature",
  "properties": {
    "addr:full":"12 W Peachtree Pl Atlanta GA 30308",
    "addr:housenumber":"12",
    "addr:postcode":"30308",
    "addr:street":"W Peachtree Pl",
    "iso:country":"US",
    "sg:address":"12 W Peachtree Pl",
    "sg:city":"Atlanta",
    "sg:classifiers":[
        {
            "category":"Restaurant",
            "type":"Food & Drink"
        }
    ],
    "sg:phone":"+1 404 525 2246",
    "sg:postcode":"30308",
    "sg:province":"GA",
    "sg:tags":[
        "mediterranean"
    ],
    "sg:website":"socialintown.com",
    "wof:name":"Social",
    "wof:placetype":"venue"
},
  "geometry": {"coordinates":[-84.387907,33.763999],"type":"Point"}
}