{
  "type": "Feature",
  "properties": {
    "iso:country":"US",
    "sg:address":"1072 Foreststone Way",
    "sg:city":"Marietta",
    "sg:classifiers":[
        {
            "category":"Communications",
            "type":"Services"
        }
    ],
    "sg:phone":"+1 770 833 2679",
    "sg:postcode":"30064",
    "sg:province":"GA",
    "sg:tags":[
        "communication"
    ],
    "wof:name":"Kids Communication",
    "wof:placetype":"venue"
},
  "geometry": {"coordinates":[-84.58457,33.938921],"type":"Point"}
}