{
  "type": "Feature",
  "properties": {
    "addr:full":"2437 Old Hapeville Rd SW Atlanta GA 30315",
    "addr:housenumber":"2437",
    "addr:postcode":"30315",
    "addr:street":"Old Hapeville Rd Sw",
    "iso:country":"US",
    "sg:address":"2437 Old Hapeville Rd SW",
    "sg:city":"Atlanta",
    "sg:classifiers":[
        {
            "category":"Professional",
            "subcategory":"Accounting & Tax Preparation",
            "type":"Services"
        }
    ],
    "sg:phone":"+1 404 766 6833",
    "sg:postcode":"30315",
    "sg:province":"GA",
    "wof:name":"Williams Accounting",
    "wof:placetype":"venue"
},
  "geometry": {"coordinates":[-84.391784,33.686603],"type":"Point"}
}