{
  "type": "Feature",
  "properties": {
    "addr:full":"2600 Martin Luther King Jr Dr SW Atlanta GA 30311",
    "addr:housenumber":"2600",
    "addr:postcode":"30311",
    "addr:street":"Martin Luther King Jr Dr Sw",
    "iso:country":"US",
    "sg:address":"2600 Martin Luther King Jr Dr SW",
    "sg:city":"Atlanta",
    "sg:classifiers":[
        {
            "category":"Health Services",
            "subcategory":"Doctor",
            "type":"Services"
        }
    ],
    "sg:phone":"+1 404 696 1944",
    "sg:postcode":"30311",
    "sg:province":"GA",
    "sg:tags":[
        "physician",
        "surgeon"
    ],
    "wof:name":"Multi Specialty Group",
    "wof:placetype":"venue"
},
  "geometry": {"coordinates":[-84.47226999999999,33.7535],"type":"Point"}
}