{
  "type": "Feature",
  "properties": {
    "addr:full":"6304 Old Hwy 5 Woodstock GA 30188",
    "addr:housenumber":"6304",
    "addr:postcode":"30188",
    "addr:street":"Old Hwy 5",
    "iso:country":"US",
    "sg:address":"6304 Old Hwy 5",
    "sg:city":"Woodstock",
    "sg:classifiers":[
        {
            "category":"Health Services",
            "subcategory":"Doctor",
            "type":"Services"
        }
    ],
    "sg:phone":"+1 770 924 0157",
    "sg:postcode":"30188",
    "sg:province":"GA",
    "sg:tags":[
        "dentist"
    ],
    "wof:name":"Dr Timothy A Benich DDS",
    "wof:placetype":"venue"
},
  "geometry": {"coordinates":[-84.498338,34.128261],"type":"Point"}
}