{
  "type": "Feature",
  "properties": {
    "iso:country":"US",
    "sg:address":"307 Atkinson Dr",
    "sg:city":"Griffin",
    "sg:classifiers":[
        {
            "category":"Education",
            "subcategory":"School",
            "type":"Public Place"
        }
    ],
    "sg:phone":"+1 770 229 3715",
    "sg:postcode":"30223",
    "sg:province":"GA",
    "wof:name":"Susie B Atkinson Elementary",
    "wof:placetype":"venue"
},
  "geometry": {"coordinates":[-84.257442,33.270628],"type":"Point"}
}