{
  "type": "Feature",
  "properties": {
    "iso:country":"US",
    "sg:address":"549 Old C C C Rd",
    "sg:city":"Brunswick",
    "sg:classifiers":[
        {
            "category":"Professional",
            "subcategory":"Art Services",
            "type":"Services"
        }
    ],
    "sg:phone":"+1 912 466 0668",
    "sg:postcode":"31523",
    "sg:province":"GA",
    "sg:tags":[
        "graphic",
        "designer"
    ],
    "wof:name":"Thomas Custom Creations",
    "wof:placetype":"venue"
},
  "geometry": {"coordinates":[-81.644441,31.165661],"type":"Point"}
}