{
  "type": "Feature",
  "properties": {
    "iso:country":"US",
    "sg:address":"5641 Fairburn Rd",
    "sg:city":"Douglasville",
    "sg:classifiers":[
        {
            "category":"Banks & Credit Unions",
            "subcategory":"Bank",
            "type":"Services"
        }
    ],
    "sg:phone":"+1 770 920 3300",
    "sg:postcode":"30134",
    "sg:province":"GA",
    "sg:tags":[
        "national",
        "commercial"
    ],
    "wof:name":"SunTrust",
    "wof:placetype":"venue"
},
  "geometry": {"coordinates":[-84.73824,33.750868],"type":"Point"}
}