{
  "type": "Feature",
  "properties": {
    "iso:country":"US",
    "sg:address":"8400 Sardis Rd",
    "sg:city":"Palmetto",
    "sg:classifiers":[
        {
            "category":"Organizations",
            "subcategory":"Religious Organization",
            "type":"Services"
        }
    ],
    "sg:phone":"+1 770 463 4393",
    "sg:postcode":"30268",
    "sg:province":"GA",
    "wof:name":"Sardis Baptist Church",
    "wof:placetype":"venue"
},
  "geometry": {"coordinates":[-84.769471,33.527749],"type":"Point"}
}