{
  "type": "Feature",
  "properties": {
    "iso:country":"US",
    "sg:address":"206 W Crawford St",
    "sg:city":"Dalton",
    "sg:classifiers":[
        {
            "category":"Professional",
            "subcategory":"Accounting & Tax Preparation",
            "type":"Services"
        }
    ],
    "sg:phone":"+1 706 278 2834",
    "sg:postcode":"30720",
    "sg:province":"GA",
    "sg:tags":[
        "accountant"
    ],
    "sg:website":"www.winterharriscpa.com",
    "wof:name":"Winter & Harris PC",
    "wof:placetype":"venue"
},
  "geometry": {"coordinates":[-84.970866,34.771638],"type":"Point"}
}