{
  "type": "Feature",
  "properties": {
    "iso:country":"US",
    "sg:address":"4941 Brownwood Rd",
    "sg:city":"Rutledge",
    "sg:classifiers":[
        {
            "category":"Home & Garden",
            "subcategory":"Home Furnishings",
            "type":"Retail Goods"
        },
        {
            "category":"Building & Trades",
            "subcategory":"Construction",
            "type":"Services"
        },
        {
            "category":"Manufacturing",
            "subcategory":"Building Materials",
            "type":"Manufacturing & Wholesale Goods"
        }
    ],
    "sg:phone":"+1 706 557 9010",
    "sg:postcode":"30663",
    "sg:province":"GA",
    "sg:tags":[
        "industrial",
        "cabinetmakers-commercial",
        "cabinet",
        "refacing",
        "resurfacing",
        "maker",
        "cabinets-refinishing",
        "kitchen"
    ],
    "wof:name":"Superior Cabinetry & Millwork",
    "wof:placetype":"venue"
},
  "geometry": {"coordinates":[-83.606193,33.57467],"type":"Point"}
}