{
  "type": "Feature",
  "properties": {
    "iso:country":"US",
    "sg:address":"23 Lastinger Rd",
    "sg:city":"Tifton",
    "sg:classifiers":[
        {
            "category":"Home & Garden",
            "subcategory":"Carpets & Floor Coverings",
            "type":"Retail Goods"
        }
    ],
    "sg:phone":"+1 229 382 6019",
    "sg:postcode":"31794",
    "sg:province":"GA",
    "sg:tags":[
        "material"
    ],
    "wof:name":"Tawzer Carpet Service",
    "wof:placetype":"venue"
},
  "geometry": {"coordinates":[-83.429946,31.415312],"type":"Point"}
}