{
  "type": "Feature",
  "properties": {
    "addr:full":"210 Old Acworth Rd Dallas GA 30132",
    "addr:housenumber":"210",
    "addr:postcode":"30132",
    "addr:street":"Old Acworth Rd",
    "iso:country":"US",
    "sg:address":"210 Old Acworth Rd",
    "sg:city":"Dallas",
    "sg:classifiers":[
        {
            "category":"Real Estate",
            "subcategory":"Real Estate Agent",
            "type":"Services"
        }
    ],
    "sg:phone":"+1 770 445 4501",
    "sg:postcode":"30132",
    "sg:province":"GA",
    "wof:name":"Park Square Realty Inc",
    "wof:placetype":"venue"
},
  "geometry": {"coordinates":[-84.83711,33.927538],"type":"Point"}
}