{
  "type": "Feature",
  "properties": {
    "addr:full":"1 Peachtree Dr Savannah GA 31419",
    "addr:housenumber":"1",
    "addr:postcode":"31419",
    "addr:street":"Peachtree Dr",
    "iso:country":"US",
    "sg:address":"1 Peachtree Dr",
    "sg:city":"Savannah",
    "sg:classifiers":[
        {
            "category":"Real Estate",
            "subcategory":"Real Estate Operator",
            "type":"Services"
        }
    ],
    "sg:phone":"+1 912 927 0500",
    "sg:postcode":"31419",
    "sg:province":"GA",
    "sg:tags":[
        "retirement",
        "apartment",
        "complex"
    ],
    "wof:name":"Savannah Cmmons Rtrement Cmnty",
    "wof:placetype":"venue"
},
  "geometry": {"coordinates":[-81.15767700000001,31.989123],"type":"Point"}
}