{
  "type": "Feature",
  "properties": {
    "iso:country":"US",
    "sg:address":"4550 River Green Pkwy NW",
    "sg:city":"Duluth",
    "sg:classifiers":[
        {
            "category":"Professional",
            "subcategory":"Employment Agencies",
            "type":"Services"
        }
    ],
    "sg:phone":"+1 770 813 3320",
    "sg:postcode":"30096",
    "sg:province":"GA",
    "sg:tags":[
        "executive",
        "placement"
    ],
    "wof:name":"Bradbury & Williamson Inc",
    "wof:placetype":"venue"
},
  "geometry": {"coordinates":[-84.166443,34.013332],"type":"Point"}
}