{
  "type": "Feature",
  "properties": {
    "iso:country":"US",
    "sg:address":"1730 Fairview Ave",
    "sg:city":"Augusta",
    "sg:classifiers":[
        {
            "category":"Retail",
            "subcategory":"Auto Repair",
            "type":"Services"
        }
    ],
    "sg:phone":"+1 706 736 4001",
    "sg:postcode":"30904",
    "sg:province":"GA",
    "sg:tags":[
        "body"
    ],
    "wof:name":"Moochie Automotive",
    "wof:placetype":"venue"
},
  "geometry": {"coordinates":[-82.044741,33.451521],"type":"Point"}
}