{
  "type": "Feature",
  "properties": {
    "iso:country":"US",
    "sg:address":"1002 Pointe S Pkwy",
    "sg:city":"Jonesboro",
    "sg:classifiers":[
        {
            "category":"Health Services",
            "subcategory":"Dentist",
            "type":"Services"
        }
    ],
    "sg:phone":"+1 770 472 9399",
    "sg:postcode":"30238",
    "sg:province":"GA",
    "sg:tags":[
        "cosmetic"
    ],
    "sg:website":"www.greatexpressions.com",
    "wof:name":"Great Expressions Dental Centers",
    "wof:placetype":"venue"
},
  "geometry": {"coordinates":[-84.420627,33.520718],"type":"Point"}
}