{
  "type": "Feature",
  "properties": {
    "addr:full":"5486 Alabama Hwy Ringgold GA 30736",
    "addr:housenumber":"5486",
    "addr:postcode":"30736",
    "addr:street":"Alabama Hwy",
    "iso:country":"US",
    "sg:address":"5486 Alabama Hwy",
    "sg:city":"Ringgold",
    "sg:classifiers":[
        {
            "category":"Restaurant",
            "type":"Food & Drink"
        }
    ],
    "sg:menulink":"http://www.allmenus.com/ga/ringgold/154451-hardees/menu/",
    "sg:phone":"+1 706 935 2188",
    "sg:postcode":"30736",
    "sg:province":"GA",
    "sg:tags":[
        "burger",
        "american"
    ],
    "wof:name":"Hardee's",
    "wof:placetype":"venue"
},
  "geometry": {"coordinates":[-85.126346,34.910939],"type":"Point"}
}