{
  "type": "Feature",
  "properties": {
    "iso:country":"US",
    "sg:address":"1004 Cobb Pkwy",
    "sg:city":"Marietta",
    "sg:classifiers":[
        {
            "category":"Building & Trades",
            "subcategory":"Construction",
            "type":"Services"
        }
    ],
    "sg:phone":"+1 770 499 0991",
    "sg:postcode":"30062",
    "sg:province":"GA",
    "sg:tags":[
        "laying"
    ],
    "wof:name":"P S Hardwood Flooring",
    "wof:placetype":"venue"
},
  "geometry": {"coordinates":[-84.54732199999999,33.97642],"type":"Point"}
}