{
  "type": "Feature",
  "properties": {
    "addr:full":"3 E Liberty St Claxton GA 30417",
    "addr:housenumber":"3",
    "addr:postcode":"30417",
    "addr:street":"E Liberty St",
    "iso:country":"US",
    "sg:address":"3 E Liberty St",
    "sg:city":"Claxton",
    "sg:classifiers":[
        {
            "category":"Professional",
            "subcategory":"Management & Consulting",
            "type":"Services"
        },
        {
            "category":"Government",
            "subcategory":"Jail",
            "type":"Public Place"
        }
    ],
    "sg:phone":"+1 912 739 4046",
    "sg:postcode":"30417",
    "sg:province":"GA",
    "sg:tags":[
        "correctional",
        "institution"
    ],
    "wof:name":"Detention Management Svc",
    "wof:placetype":"venue"
},
  "geometry": {"coordinates":[-81.90293800000001,32.158817],"type":"Point"}
}