{
  "type": "Feature",
  "properties": {
    "iso:country":"US",
    "sg:address":"5717 Pine Brook Road NE",
    "sg:city":"Atlanta",
    "sg:classifiers":[
        {
            "category":"Professional",
            "subcategory":"Lawyer & Legal Services",
            "type":"Services"
        }
    ],
    "sg:phone":"+1 404 257 1611",
    "sg:postcode":"30328",
    "sg:province":"GA",
    "wof:name":"Kiser Eugene R PC",
    "wof:placetype":"venue"
},
  "geometry": {"coordinates":[-84.365432,33.911466],"type":"Point"}
}