{
  "type": "Feature",
  "properties": {
    "addr:full":"216 Commerce Ave Lagrange GA 30241",
    "addr:housenumber":"216",
    "addr:postcode":"30241",
    "addr:street":"Commerce Ave",
    "iso:country":"US",
    "sg:address":"216 Commerce Ave",
    "sg:city":"Lagrange",
    "sg:classifiers":[
        {
            "category":"Shopping",
            "subcategory":"Used Merchandise",
            "type":"Retail Goods"
        }
    ],
    "sg:phone":"+1 706 845 8980",
    "sg:postcode":"30241",
    "sg:province":"GA",
    "sg:tags":[
        "shop",
        "thrift"
    ],
    "wof:name":"Valley Rescue Thrift Store",
    "wof:placetype":"venue"
},
  "geometry": {"coordinates":[-85.021846,33.0493],"type":"Point"}
}