{
  "type": "Feature",
  "properties": {
    "addr:full":"3027 Jim Moore Rd Dacula GA 30019",
    "addr:housenumber":"3027",
    "addr:postcode":"ga 30019",
    "addr:street":"Jim Moore Rd",
    "iso:country":"US",
    "sg:address":"3027 Jim Moore Rd",
    "sg:city":"Dacula",
    "sg:classifiers":[
        {
            "category":"Shopping",
            "subcategory":"Pharmacy",
            "type":"Retail Goods"
        }
    ],
    "sg:phone":"+1 770 339 0129",
    "sg:postcode":"30019",
    "sg:province":"GA",
    "sg:tags":[
        "drugstore"
    ],
    "sg:website":"www.cvs.com",
    "wof:name":"Cvs Pharmacy",
    "wof:placetype":"venue"
},
  "geometry": {"coordinates":[-83.90940000000001,34.036151],"type":"Point"}
}