{
  "type": "Feature",
  "properties": {
    "addr:full":"2480 Briarcliff Rd NE Atlanta GA 30329",
    "addr:housenumber":"2480",
    "addr:postcode":"30329",
    "addr:street":"Briarcliff Rd Ne",
    "iso:country":"US",
    "sg:address":"2480 Briarcliff Rd NE",
    "sg:city":"Atlanta",
    "sg:classifiers":[
        {
            "category":"Bars & Pubs",
            "type":"Food & Drink"
        }
    ],
    "sg:menulink":"http://www.allmenus.com/ga/atlanta-decatur/92167-locos-grill-and-pub/menu/",
    "sg:phone":"+1 404 329 1999",
    "sg:postcode":"30329",
    "sg:province":"GA",
    "sg:tags":[
        "american"
    ],
    "wof:name":"Locos Grill and Pub",
    "wof:placetype":"venue"
},
  "geometry": {"coordinates":[-84.33229900000001,33.826599],"type":"Point"}
}