{
  "type": "Feature",
  "properties": {
    "addr:full":"2381 State Rte 36 Jackson GA 30233",
    "addr:housenumber":"2381",
    "addr:postcode":"30233",
    "addr:street":"State Rte 36",
    "iso:country":"US",
    "sg:address":"2381 State Rte 36",
    "sg:city":"Jackson",
    "sg:classifiers":[
        {
            "category":"Food & Beverages",
            "subcategory":"Groceries & Convenience Stores",
            "type":"Retail Goods"
        }
    ],
    "sg:phone":"+1 770 775 7406",
    "sg:postcode":"30233",
    "sg:province":"GA",
    "wof:name":"Highway 36 Superette",
    "wof:placetype":"venue"
},
  "geometry": {"coordinates":[-84.017533,33.249913],"type":"Point"}
}