{
  "type": "Feature",
  "properties": {
    "iso:country":"US",
    "sg:address":"3744 Lavista Rd # A",
    "sg:city":"Decatur",
    "sg:classifiers":[
        {
            "category":"Health Services",
            "subcategory":"Doctor",
            "type":"Services"
        },
        {
            "category":"Health Services",
            "subcategory":"Dentist",
            "type":"Services"
        }
    ],
    "sg:phone":"+1 404 325 8116",
    "sg:postcode":"30033",
    "sg:province":"GA",
    "sg:tags":[
        "surgeon",
        "oral",
        "orthodontist"
    ],
    "wof:name":"Clinebell John A DDS",
    "wof:placetype":"venue"
},
  "geometry": {"coordinates":[-84.264,33.840698],"type":"Point"}
}