{
  "type": "Feature",
  "properties": {
    "iso:country":"US",
    "sg:address":"2240 New Clinton Rd",
    "sg:city":"Macon",
    "sg:classifiers":[
        {
            "category":"Recreation",
            "type":"Entertainment"
        }
    ],
    "sg:phone":"+1 478 750 0775",
    "sg:postcode":"31217",
    "sg:province":"GA",
    "sg:tags":[
        "club",
        "membership"
    ],
    "wof:name":"Auto Club & Prof Details",
    "wof:placetype":"venue"
},
  "geometry": {"coordinates":[-83.587164,32.856064],"type":"Point"}
}