{
  "type": "Feature",
  "properties": {
    "addr:full":"10 Windsor Way Newnan GA 30263",
    "addr:housenumber":"10",
    "addr:postcode":"30263",
    "addr:street":"Windsor Way",
    "iso:country":"US",
    "sg:address":"10 Windsor Way",
    "sg:city":"Newnan",
    "sg:classifiers":[
        {
            "category":"Organizations",
            "subcategory":"Community Association",
            "type":"Services"
        }
    ],
    "sg:phone":"+1 770 251 1957",
    "sg:postcode":"30263",
    "sg:province":"GA",
    "wof:name":"Lake Placid Homeowners Assn",
    "wof:placetype":"venue"
},
  "geometry": {"coordinates":[-84.815248,33.42381],"type":"Point"}
}