{
  "type": "Feature",
  "properties": {
    "addr:full":"3301 Montreal Industrial Way Tucker GA 30084",
    "addr:housenumber":"3301",
    "addr:postcode":"30084",
    "addr:street":"Montreal Industrial Way",
    "iso:country":"US",
    "sg:address":"3301 Montreal Industrial Way",
    "sg:city":"Tucker",
    "sg:classifiers":[
        {
            "category":"Professional",
            "subcategory":"Employment Agencies",
            "type":"Services"
        }
    ],
    "sg:phone":"+1 770 493 3990",
    "sg:postcode":"30084",
    "sg:province":"GA",
    "wof:name":"Randstad",
    "wof:placetype":"venue"
},
  "geometry": {"coordinates":[-84.24865,33.840599],"type":"Point"}
}