{
  "type": "Feature",
  "properties": {
    "addr:full":"5722 Peachtree Industrial Blvd Atlanta GA 30341",
    "addr:housenumber":"5722",
    "addr:postcode":"30341",
    "addr:street":"Peachtree Industrial Blvd",
    "iso:country":"US",
    "sg:address":"5722 Peachtree Industrial Blvd",
    "sg:city":"Atlanta",
    "sg:classifiers":[
        {
            "category":"Autos & Motor Vehicles",
            "subcategory":"Auto Supplies",
            "type":"Retail Goods"
        }
    ],
    "sg:phone":"+1 770 451 2414",
    "sg:postcode":"30341",
    "sg:province":"GA",
    "sg:tags":[
        "lube",
        "oil"
    ],
    "sg:website":"http://www.expressoil.com",
    "wof:name":"Express Oil Change & Service Center",
    "wof:placetype":"venue"
},
  "geometry": {"coordinates":[-84.295689,33.904529],"type":"Point"}
}