{
  "type": "Feature",
  "properties": {
    "iso:country":"US",
    "sg:address":"12505 Cranwood Ln",
    "sg:city":"Savannah",
    "sg:classifiers":[
        {
            "category":"Building & Trades",
            "subcategory":"Construction",
            "type":"Services"
        }
    ],
    "sg:phone":"+1 912 356 0287",
    "sg:postcode":"31419",
    "sg:province":"GA",
    "sg:tags":[
        "general",
        "contractor"
    ],
    "wof:name":"Edwards Construction",
    "wof:placetype":"venue"
},
  "geometry": {"coordinates":[-81.139476,31.973428],"type":"Point"}
}