{
  "type": "Feature",
  "properties": {
    "iso:country":"US",
    "sg:address":"1338 10th St",
    "sg:city":"Augusta",
    "sg:classifiers":[
        {
            "category":"Food & Beverages",
            "subcategory":"Groceries & Convenience Stores",
            "type":"Retail Goods"
        }
    ],
    "sg:phone":"+1 706 724 3092",
    "sg:postcode":"30901",
    "sg:province":"GA",
    "sg:tags":[
        "grocer"
    ],
    "wof:name":"Reid's Community Grocery Store",
    "wof:placetype":"venue"
},
  "geometry": {"coordinates":[-81.977508,33.461418],"type":"Point"}
}