{
  "type": "Feature",
  "properties": {
    "addr:full":"2553 Washington Rd Augusta GA 30904",
    "addr:housenumber":"2553",
    "addr:postcode":"30904",
    "addr:street":"Washington Rd",
    "iso:country":"US",
    "sg:address":"2553 Washington Rd",
    "sg:city":"Augusta",
    "sg:classifiers":[
        {
            "category":"Organizations",
            "subcategory":"Professional Association",
            "type":"Services"
        }
    ],
    "sg:phone":"+1 706 733 5387",
    "sg:postcode":"30904",
    "sg:province":"GA",
    "sg:tags":[
        "membership"
    ],
    "wof:name":"Scottish Rite Of Free Masonry",
    "wof:placetype":"venue"
},
  "geometry": {"coordinates":[-82.019137,33.506489],"type":"Point"}
}