{
  "type": "Feature",
  "properties": {
    "iso:country":"US",
    "sg:address":"215 Star Cir",
    "sg:city":"Norman Park",
    "sg:classifiers":[
        {
            "category":"Professional",
            "type":"Services"
        }
    ],
    "sg:phone":"+1 229 769 5759",
    "sg:postcode":"31771",
    "sg:province":"GA",
    "wof:name":"Sheila Brooks",
    "wof:placetype":"venue"
},
  "geometry": {"coordinates":[-83.677071,31.276061],"type":"Point"}
}