{
  "type": "Feature",
  "properties": {
    "addr:full":"4987 Boring Pond Rd Lake Park GA 31606",
    "addr:housenumber":"4987",
    "addr:postcode":"31606",
    "addr:street":"Boring Pond Rd",
    "iso:country":"US",
    "sg:address":"4987 Boring Pond Rd",
    "sg:city":"Lake Park",
    "sg:classifiers":[
        {
            "category":"Personal",
            "subcategory":"Beauty Salon",
            "type":"Services"
        }
    ],
    "sg:phone":"+1 229 559 7119",
    "sg:postcode":"31606",
    "sg:province":"GA",
    "sg:tags":[
        "shop"
    ],
    "wof:name":"Lindas Country Curl",
    "wof:placetype":"venue"
},
  "geometry": {"coordinates":[-83.143552,30.77509],"type":"Point"}
}