{
  "type": "Feature",
  "properties": {
    "addr:full":"182 Old College St Hamilton GA 31811",
    "addr:housenumber":"182",
    "addr:postcode":"31811",
    "addr:street":"Old College St",
    "iso:country":"US",
    "sg:address":"182 Old College St",
    "sg:city":"Hamilton",
    "sg:classifiers":[
        {
            "category":"Insurance",
            "subcategory":"Insurance Agent",
            "type":"Services"
        }
    ],
    "sg:phone":"+1 706 628 4274",
    "sg:postcode":"31811",
    "sg:province":"GA",
    "wof:name":"Farm Bureau Insurance",
    "wof:placetype":"venue"
},
  "geometry": {"coordinates":[-84.867552,32.74045],"type":"Point"}
}