{
  "type": "Feature",
  "properties": {
    "addr:full":"396 Willowwind Dr Loganville GA 30052",
    "addr:housenumber":"396",
    "addr:postcode":"30052",
    "addr:street":"Willowwind Dr",
    "iso:country":"US",
    "sg:address":"396 Willowwind Dr",
    "sg:city":"Loganville",
    "sg:classifiers":[
        {
            "category":"Shopping",
            "subcategory":"Books",
            "type":"Retail Goods"
        }
    ],
    "sg:phone":"+1 770 554 3737",
    "sg:postcode":"30052",
    "sg:province":"GA",
    "wof:name":"Tex Mex Communications Inc",
    "wof:placetype":"venue"
},
  "geometry": {"coordinates":[-83.894237,33.869885],"type":"Point"}
}