{
  "type": "Feature",
  "properties": {
    "addr:full":"816 Piedmont Ave NE # 10 Atlanta GA 30308",
    "addr:housenumber":"816",
    "addr:postcode":"30308",
    "addr:street":"Piedmont Ave Ne # 10",
    "iso:country":"US",
    "sg:address":"816 Piedmont Ave NE # 10",
    "sg:city":"Atlanta",
    "sg:classifiers":[
        {
            "category":"Professional",
            "subcategory":"Research",
            "type":"Services"
        }
    ],
    "sg:phone":"+1 404 870 9978",
    "sg:postcode":"30308",
    "sg:province":"GA",
    "sg:tags":[
        "analysis",
        "market"
    ],
    "wof:name":"Envision It",
    "wof:placetype":"venue"
},
  "geometry": {"coordinates":[-84.381339,33.776927],"type":"Point"}
}