{
  "type": "Feature",
  "properties": {
    "iso:country":"US",
    "sg:address":"235 Ponce de Leon Pl",
    "sg:city":"Decatur",
    "sg:classifiers":[
        {
            "category":"Manufacturing",
            "subcategory":"Printing",
            "type":"Manufacturing & Wholesale Goods"
        }
    ],
    "sg:phone":"+1 404 377 8899",
    "sg:postcode":"30030",
    "sg:province":"GA",
    "sg:tags":[
        "publishing",
        "desktop"
    ],
    "wof:name":"Lazer Age Inc",
    "wof:placetype":"venue"
},
  "geometry": {"coordinates":[-84.299966,33.776371],"type":"Point"}
}