{
  "type": "Feature",
  "properties": {
    "addr:full":"7972 State Rte 85 Riverdale GA 30274",
    "addr:housenumber":"7972",
    "addr:postcode":"30274",
    "addr:street":"State Rte 85",
    "iso:country":"US",
    "sg:address":"7972 State Rte 85",
    "sg:city":"Riverdale",
    "sg:classifiers":[
        {
            "category":"Personal",
            "subcategory":"Beauty Salon",
            "type":"Services"
        }
    ],
    "sg:phone":"+1 770 603 2993",
    "sg:postcode":"30274",
    "sg:province":"GA",
    "sg:tags":[
        "hair",
        "studio"
    ],
    "wof:name":"Ambience Hair Studios",
    "wof:placetype":"venue"
},
  "geometry": {"coordinates":[-84.417841,33.537245],"type":"Point"}
}