{
  "type": "Feature",
  "properties": {
    "iso:country":"US",
    "sg:address":"10314 Mount Olive Rd",
    "sg:city":"Metter",
    "sg:classifiers":[
        {
            "category":"Building & Trades",
            "subcategory":"Construction",
            "type":"Services"
        }
    ],
    "sg:phone":"+1 912 685 6916",
    "sg:postcode":"30439",
    "sg:province":"GA",
    "sg:tags":[
        "industrial",
        "contractors-commercial",
        "contractor"
    ],
    "wof:name":"Gibson Specialty Contracting",
    "wof:placetype":"venue"
},
  "geometry": {"coordinates":[-82.13584899999999,32.359838],"type":"Point"}
}