{
  "type": "Feature",
  "properties": {
    "addr:full":"5440 Frontage Rd Forest Park GA 30297",
    "addr:housenumber":"5440",
    "addr:postcode":"30297",
    "addr:street":"Frontage Rd",
    "iso:country":"US",
    "sg:address":"5440 Frontage Rd",
    "sg:city":"Forest Park",
    "sg:classifiers":[
        {
            "category":"Organizations",
            "subcategory":"Religious Organization",
            "type":"Services"
        }
    ],
    "sg:phone":"+1 404 366 7007",
    "sg:postcode":"30297",
    "sg:province":"GA",
    "wof:name":"Oasis Global Ministries",
    "wof:placetype":"venue"
},
  "geometry": {"coordinates":[-84.38445299999999,33.591431],"type":"Point"}
}