{
  "type": "Feature",
  "properties": {
    "addr:full":"2895 Chamonix Dr Cumming GA 30041",
    "addr:housenumber":"2895",
    "addr:postcode":"30041",
    "addr:street":"Chamonix Dr",
    "iso:country":"US",
    "sg:address":"2895 Chamonix Dr",
    "sg:city":"Cumming",
    "sg:classifiers":[
        {
            "category":"Professional",
            "subcategory":"Business Services",
            "type":"Services"
        }
    ],
    "sg:phone":"+1 770 886 7566",
    "sg:postcode":"30041",
    "sg:province":"GA",
    "wof:name":"Ken Mayger",
    "wof:placetype":"venue"
},
  "geometry": {"coordinates":[-84.10674400000001,34.144821],"type":"Point"}
}