{
  "type": "Feature",
  "properties": {
    "addr:full":"162 Windcliff Pl Dallas GA 30132",
    "addr:housenumber":"162",
    "addr:postcode":"30132",
    "addr:street":"Windcliff Pl",
    "iso:country":"US",
    "sg:address":"162 Windcliff Pl",
    "sg:city":"Dallas",
    "sg:classifiers":[
        {
            "category":"Manufacturing",
            "subcategory":"Glass & Minerals",
            "type":"Manufacturing & Wholesale Goods"
        },
        {
            "category":"Manufacturing",
            "subcategory":"Building Materials",
            "type":"Manufacturing & Wholesale Goods"
        }
    ],
    "sg:phone":"+1 678 363 6736",
    "sg:postcode":"30132",
    "sg:province":"GA",
    "sg:tags":[
        "plate",
        "window",
        "glazier",
        "replacement",
        "repair"
    ],
    "wof:name":"Kevin A Peaster",
    "wof:placetype":"venue"
},
  "geometry": {"coordinates":[-84.817285,34.045192],"type":"Point"}
}