{
  "type": "Feature",
  "properties": {
    "addr:full":"126 Acadian Dr Stockbridge GA 30281",
    "addr:housenumber":"126",
    "addr:postcode":"30281",
    "addr:street":"Acadian Dr",
    "iso:country":"US",
    "sg:address":"126 Acadian Dr",
    "sg:city":"Stockbridge",
    "sg:classifiers":[
        {
            "category":"Manufacturing",
            "subcategory":"Apparel",
            "type":"Manufacturing & Wholesale Goods"
        }
    ],
    "sg:phone":"+1 678 432 5720",
    "sg:postcode":"30281",
    "sg:province":"GA",
    "sg:tags":[
        "clothing-men's-wholesale",
        "manufacturer"
    ],
    "wof:name":"Hy Sportswear",
    "wof:placetype":"venue"
},
  "geometry": {"coordinates":[-84.23904400000001,33.49364],"type":"Point"}
}