{
  "type": "Feature",
  "properties": {
    "addr:full":"340 Dodge Rd Saint Simons Island GA 31522",
    "addr:housenumber":"340",
    "addr:postcode":"31522",
    "addr:street":"Dodge Rd",
    "iso:country":"US",
    "sg:address":"340 Dodge Rd",
    "sg:city":"Saint Simons Island",
    "sg:classifiers":[
        {
            "category":"Professional",
            "subcategory":"Business Services",
            "type":"Services"
        }
    ],
    "sg:phone":"+1 912 638 8214",
    "sg:postcode":"31522",
    "sg:province":"GA",
    "sg:tags":[
        "ceremony",
        "player",
        "piano",
        "for",
        "special"
    ],
    "wof:name":"Beatrice Dismer",
    "wof:placetype":"venue"
},
  "geometry": {"coordinates":[-81.37748999999999,31.20713],"type":"Point"}
}