{
  "type": "Feature",
  "properties": {
    "iso:country":"US",
    "sg:address":"3616 S Puckett Rd",
    "sg:city":"Buford",
    "sg:classifiers":[
        {
            "category":"Building & Trades",
            "subcategory":"Electrical",
            "type":"Services"
        }
    ],
    "sg:phone":"+1 770 945 8653",
    "sg:postcode":"30519",
    "sg:province":"GA",
    "sg:tags":[
        "electric",
        "contractor"
    ],
    "wof:name":"Glen Pirkle Electrical Contr",
    "wof:placetype":"venue"
},
  "geometry": {"coordinates":[-83.934067,34.103956],"type":"Point"}
}