{
  "type": "Feature",
  "properties": {
    "addr:full":"12393 Sunset Maple Ter Alpharetta GA 30005",
    "addr:housenumber":"12393",
    "addr:postcode":"30005",
    "addr:street":"Sunset Maple Ter",
    "iso:country":"US",
    "sg:address":"12393 Sunset Maple Ter",
    "sg:city":"Alpharetta",
    "sg:classifiers":[
        {
            "category":"Professional",
            "type":"Services"
        }
    ],
    "sg:phone":"+1 770 753 4230",
    "sg:postcode":"30005",
    "sg:province":"GA",
    "wof:name":"Entire Data Inc",
    "wof:placetype":"venue"
},
  "geometry": {"coordinates":[-84.19383999999999,34.081603],"type":"Point"}
}