{
  "type": "Feature",
  "properties": {
    "iso:country":"US",
    "sg:address":"1126 E Montgomery Xrd",
    "sg:city":"Savannah",
    "sg:classifiers":[
        {
            "category":"Shopping",
            "subcategory":"Bicycles & Sporting Goods",
            "type":"Retail Goods"
        }
    ],
    "sg:phone":"+1 912 692 1005",
    "sg:postcode":"31406",
    "sg:province":"GA",
    "sg:tags":[
        "repair"
    ],
    "sg:website":"www.qualitybikeshop.com",
    "wof:name":"Quality Bike",
    "wof:placetype":"venue"
},
  "geometry": {"coordinates":[-81.10393000000001,31.993649],"type":"Point"}
}