{
  "type": "Feature",
  "properties": {
    "iso:country":"US",
    "sg:address":"2167 Cedar Dr",
    "sg:city":"Lawrenceville",
    "sg:classifiers":[
        {
            "category":"Wholesale",
            "subcategory":"Groceries",
            "type":"Manufacturing & Wholesale Goods"
        }
    ],
    "sg:phone":"+1 770 962 9786",
    "sg:postcode":"30043",
    "sg:province":"GA",
    "sg:tags":[
        "food"
    ],
    "wof:name":"H&L Beverage Inc",
    "wof:placetype":"venue"
},
  "geometry": {"coordinates":[-83.99637300000001,34.025204],"type":"Point"}
}