{
  "type": "Feature",
  "properties": {
    "iso:country":"US",
    "sg:address":"1050 Burton Dr NE",
    "sg:city":"Atlanta",
    "sg:classifiers":[
        {
            "category":"Arts & Performance",
            "subcategory":"Theater",
            "type":"Entertainment"
        }
    ],
    "sg:phone":"+1 404 633 4000",
    "sg:postcode":"30329",
    "sg:province":"GA",
    "sg:tags":[
        "group"
    ],
    "wof:name":"Evan and Jaron Inc",
    "wof:placetype":"venue"
},
  "geometry": {"coordinates":[-84.331946,33.809339],"type":"Point"}
}