{
  "type": "Feature",
  "properties": {
    "addr:full":"214 Wilshire Blvd Vidalia GA 30474",
    "addr:housenumber":"214",
    "addr:postcode":"30474",
    "addr:street":"Wilshire Blvd",
    "iso:country":"US",
    "sg:address":"214 Wilshire Blvd",
    "sg:city":"Vidalia",
    "sg:classifiers":[
        {
            "category":"Organizations",
            "subcategory":"Religious Organization",
            "type":"Services"
        }
    ],
    "sg:phone":"+1 912 538 1705",
    "sg:postcode":"30474",
    "sg:province":"GA",
    "sg:tags":[
        "church"
    ],
    "wof:name":"Phillips Temple Ministries In",
    "wof:placetype":"venue"
},
  "geometry": {"coordinates":[-82.405652,32.229662],"type":"Point"}
}