{
  "type": "Feature",
  "properties": {
    "addr:full":"659 Strickland Rd Lake Park GA 31636",
    "addr:housenumber":"659",
    "addr:postcode":"31636",
    "addr:street":"Strickland Rd",
    "iso:country":"US",
    "sg:address":"659 Strickland Rd",
    "sg:city":"Lake Park",
    "sg:classifiers":[
        {
            "category":"Farming",
            "subcategory":"Livestock Farm",
            "type":"Manufacturing & Wholesale Goods"
        }
    ],
    "sg:phone":"+1 229 559 7413",
    "sg:postcode":"31636",
    "sg:province":"GA",
    "sg:tags":[
        "animal",
        "general"
    ],
    "wof:name":"Strickland Farms",
    "wof:placetype":"venue"
},
  "geometry": {"coordinates":[-83.037554,30.628298],"type":"Point"}
}