{
  "type": "Feature",
  "properties": {
    "addr:full":"6311 Mableton Pkwy SE Mableton GA 30126",
    "addr:housenumber":"6311",
    "addr:postcode":"30126",
    "addr:street":"Mableton Pkwy Se",
    "iso:country":"US",
    "sg:address":"6311 Mableton Pkwy SE",
    "sg:city":"Mableton",
    "sg:classifiers":[
        {
            "category":"Autos & Motor Vehicles",
            "subcategory":"Fuel & Gas Station",
            "type":"Retail Goods"
        }
    ],
    "sg:phone":"+1 678 945 1984",
    "sg:postcode":"30126",
    "sg:province":"GA",
    "sg:tags":[
        "oil"
    ],
    "wof:name":"Chevron Food Mart",
    "wof:placetype":"venue"
},
  "geometry": {"coordinates":[-84.565989,33.800146],"type":"Point"}
}