{
  "type": "Feature",
  "properties": {
    "addr:full":"8510 Kent Dr Savannah GA 31406",
    "addr:housenumber":"8510",
    "addr:postcode":"31406",
    "addr:street":"Kent Dr",
    "iso:country":"US",
    "sg:address":"8510 Kent Dr",
    "sg:city":"Savannah",
    "sg:classifiers":[
        {
            "category":"Building & Trades",
            "subcategory":"Construction",
            "type":"Services"
        }
    ],
    "sg:phone":"+1 912 354 4156",
    "sg:postcode":"31406",
    "sg:province":"GA",
    "sg:tags":[
        "nonresidential"
    ],
    "wof:name":"Ghuman Teach",
    "wof:placetype":"venue"
},
  "geometry": {"coordinates":[-81.093317,31.988924],"type":"Point"}
}