{
  "type": "Feature",
  "properties": {
    "iso:country":"US",
    "sg:address":"2650 Hwy 42",
    "sg:city":"Locust Grove",
    "sg:classifiers":[
        {
            "category":"Professional",
            "subcategory":"Engineering",
            "type":"Services"
        }
    ],
    "sg:phone":"+1 770 898 0101",
    "sg:postcode":"30248",
    "sg:province":"GA",
    "sg:tags":[
        "engineer"
    ],
    "wof:name":"Civil Tech Engineering Inc",
    "wof:placetype":"venue"
},
  "geometry": {"coordinates":[-84.126418,33.377199],"type":"Point"}
}