{
  "type": "Feature",
  "properties": {
    "addr:full":"408 E Bolton St Savannah GA 31401",
    "addr:housenumber":"408",
    "addr:postcode":"31401",
    "addr:street":"E Bolton St",
    "iso:country":"US",
    "sg:address":"408 E Bolton St",
    "sg:city":"Savannah",
    "sg:classifiers":[
        {
            "category":"Social Services",
            "type":"Services"
        }
    ],
    "sg:phone":"+1 912 234 2159",
    "sg:postcode":"31401",
    "sg:province":"GA",
    "wof:name":"L C S W",
    "wof:placetype":"venue"
},
  "geometry": {"coordinates":[-81.091407,32.065141],"type":"Point"}
}