{
  "type": "Feature",
  "properties": {
    "iso:country":"US",
    "sg:address":"141 E Felton Rd",
    "sg:city":"Cartersville",
    "sg:classifiers":[
        {
            "category":"Social Services",
            "subcategory":"Child Care",
            "type":"Services"
        }
    ],
    "sg:phone":"+1 770 383 9535",
    "sg:postcode":"30120",
    "sg:province":"GA",
    "sg:tags":[
        "day"
    ],
    "wof:name":"Sylvan Learning Centers",
    "wof:placetype":"venue"
},
  "geometry": {"coordinates":[-84.792816,34.196713],"type":"Point"}
}