{
  "type": "Feature",
  "properties": {
    "iso:country":"US",
    "sg:address":"4390 Mead Rd",
    "sg:city":"Macon",
    "sg:classifiers":[
        {
            "category":"Freight",
            "type":"Transportation"
        }
    ],
    "sg:phone":"+1 478 781 7170",
    "sg:postcode":"31206",
    "sg:province":"GA",
    "sg:tags":[
        "operator",
        "trucking"
    ],
    "wof:name":"Wilson Trucking Corp",
    "wof:placetype":"venue"
},
  "geometry": {"coordinates":[-83.63905,32.785021],"type":"Point"}
}