{
  "type": "Feature",
  "properties": {
    "addr:full":"601 26th Ave SE Moultrie GA 31768",
    "addr:housenumber":"601",
    "addr:postcode":"31768",
    "addr:street":"26Th Ave Se",
    "iso:country":"US",
    "sg:address":"601 26th Ave SE",
    "sg:city":"Moultrie",
    "sg:classifiers":[
        {
            "category":"Social Services",
            "type":"Services"
        }
    ],
    "sg:phone":"+1 229 985 1154",
    "sg:postcode":"31768",
    "sg:province":"GA",
    "sg:tags":[
        "organization",
        "welfare"
    ],
    "wof:name":"YMCA",
    "wof:placetype":"venue"
},
  "geometry": {"coordinates":[-83.779301,31.137368],"type":"Point"}
}