{
  "type": "Feature",
  "properties": {
    "addr:full":"833 Parsons St SW Atlanta GA 30314",
    "addr:housenumber":"833",
    "addr:postcode":"30314",
    "addr:street":"Parsons St Sw",
    "iso:country":"US",
    "sg:address":"833 Parsons St SW",
    "sg:city":"Atlanta",
    "sg:classifiers":[
        {
            "category":"Government",
            "subcategory":"Office",
            "type":"Public Place"
        }
    ],
    "sg:phone":"+1 404 756 0957",
    "sg:postcode":"30314",
    "sg:province":"GA",
    "sg:tags":[
        "federal",
        "security"
    ],
    "wof:name":"Us Naval Rotc",
    "wof:placetype":"venue"
},
  "geometry": {"coordinates":[-84.41527499999999,33.75084],"type":"Point"}
}