{
  "type": "Feature",
  "properties": {
    "iso:country":"US",
    "sg:address":"2350 Spring Rd SE",
    "sg:city":"Smyrna",
    "sg:classifiers":[
        {
            "category":"Personal",
            "subcategory":"Beauty Salon",
            "type":"Services"
        }
    ],
    "sg:phone":"+1 770 434 6724",
    "sg:postcode":"30080",
    "sg:province":"GA",
    "sg:tags":[
        "hair"
    ],
    "wof:name":"Khuan's Hair Design",
    "wof:placetype":"venue"
},
  "geometry": {"coordinates":[-84.486378,33.883297],"type":"Point"}
}