{
  "type": "Feature",
  "properties": {
    "addr:full":"82 Buell Jones Rd Carrollton GA 30117",
    "addr:housenumber":"82",
    "addr:postcode":"30117",
    "addr:street":"Buell Jones Rd",
    "iso:country":"US",
    "sg:address":"82 Buell Jones Rd",
    "sg:city":"Carrollton",
    "sg:classifiers":[
        {
            "category":"Retail",
            "subcategory":"Laundry & Dry Cleaning",
            "type":"Services"
        }
    ],
    "sg:phone":"+1 770 830 7529",
    "sg:postcode":"30117",
    "sg:province":"GA",
    "wof:name":"Supreme Carpet Care",
    "wof:placetype":"venue"
},
  "geometry": {"coordinates":[-85.094128,33.632689],"type":"Point"}
}