{
  "type": "Feature",
  "properties": {
    "addr:full":"4099 Lavista Rd Tucker GA 30084",
    "addr:housenumber":"4099",
    "addr:postcode":"30084",
    "addr:street":"Lavista Rd",
    "iso:country":"US",
    "sg:address":"4099 Lavista Rd",
    "sg:city":"Tucker",
    "sg:phone":"+1 770 621 3500",
    "sg:postcode":"30084",
    "sg:province":"GA",
    "sg:website":"https://www.wachovia.com/?DCMP=KNL-CPS-DS-Directory-0703&HBX_PK=Banks&HBX_OU=71",
    "wof:name":"Wachovia Bank",
    "wof:placetype":"venue"
},
  "geometry": {"coordinates":[-84.250832,33.846439],"type":"Point"}
}