{
  "type": "Feature",
  "properties": {
    "addr:full":"3045 Washington Rd Atlanta GA 30344",
    "addr:housenumber":"3045",
    "addr:postcode":"30344",
    "addr:street":"Washington Rd",
    "iso:country":"US",
    "sg:address":"3045 Washington Rd",
    "sg:city":"Atlanta",
    "sg:classifiers":[
        {
            "category":"Professional",
            "type":"Services"
        }
    ],
    "sg:phone":"+1 404 767 2800",
    "sg:postcode":"30344",
    "sg:province":"GA",
    "wof:name":"Act Rejuvenate Inc",
    "wof:placetype":"venue"
},
  "geometry": {"coordinates":[-84.456239,33.673117],"type":"Point"}
}