{
  "type": "Feature",
  "properties": {
    "iso:country":"US",
    "sg:address":"105B Sunshine Ave",
    "sg:city":"Savannah",
    "sg:classifiers":[
        {
            "category":"Building & Trades",
            "subcategory":"Construction",
            "type":"Services"
        },
        {
            "category":"Military Area",
            "subcategory":"Armory",
            "type":"Public Place"
        }
    ],
    "sg:phone":"+1 912 236 1482",
    "sg:postcode":"31405",
    "sg:province":"GA",
    "sg:tags":[
        "repair",
        "fence-sales",
        "fence",
        "contractor"
    ],
    "wof:name":"Sunshine Fence Co",
    "wof:placetype":"venue"
},
  "geometry": {"coordinates":[-81.207555,32.061147],"type":"Point"}
}