{
  "type": "Feature",
  "properties": {
    "addr:full":"608 Tucker Dr Newnan GA 30263",
    "addr:housenumber":"608",
    "addr:postcode":"30263",
    "addr:street":"Tucker Dr",
    "iso:country":"US",
    "sg:address":"608 Tucker Dr",
    "sg:city":"Newnan",
    "sg:classifiers":[
        {
            "category":"Professional",
            "type":"Services"
        }
    ],
    "sg:phone":"+1 770 304 0528",
    "sg:postcode":"30263",
    "sg:province":"GA",
    "sg:tags":[
        "establishment"
    ],
    "wof:name":"Godfrey Terrace",
    "wof:placetype":"venue"
},
  "geometry": {"coordinates":[-84.80670000000001,33.398913],"type":"Point"}
}