{
  "type": "Feature",
  "properties": {
    "addr:full":"3050 Royal Blvd S Alpharetta GA 30022",
    "addr:housenumber":"3050",
    "addr:postcode":"30022",
    "addr:street":"Royal Blvd S",
    "iso:country":"US",
    "sg:address":"3050 Royal Blvd S",
    "sg:city":"Alpharetta",
    "sg:classifiers":[
        {
            "category":"Wholesale",
            "subcategory":"Machinery & Supplies",
            "type":"Manufacturing & Wholesale Goods"
        }
    ],
    "sg:phone":"+1 678 393 0030",
    "sg:postcode":"30022",
    "sg:province":"GA",
    "sg:tags":[
        "equipment",
        "industrial"
    ],
    "wof:name":"Entech Instruments Inc",
    "wof:placetype":"venue"
},
  "geometry": {"coordinates":[-84.271997,34.053455],"type":"Point"}
}