{
  "type": "Feature",
  "properties": {
    "addr:full":"5745 W Lees Mill Rd College Park GA 30349",
    "addr:housenumber":"5745",
    "addr:postcode":"30349",
    "addr:street":"W Lees Mill Rd",
    "iso:country":"US",
    "sg:address":"5745 W Lees Mill Rd",
    "sg:city":"College Park",
    "sg:classifiers":[
        {
            "category":"Education",
            "subcategory":"School",
            "type":"Public Place"
        }
    ],
    "sg:phone":"+1 770 991 4651",
    "sg:postcode":"30349",
    "sg:province":"GA",
    "sg:tags":[
        "high",
        "middle",
        "elementary"
    ],
    "wof:name":"Martin L King Elementary School",
    "wof:placetype":"venue"
},
  "geometry": {"coordinates":[-84.412683,33.594157],"type":"Point"}
}