{
  "type": "Feature",
  "properties": {
    "addr:full":"1505 Mount Vernon Rd Atlanta GA 30338",
    "addr:housenumber":"1505",
    "addr:postcode":"30338",
    "addr:street":"Mount Vernon Rd",
    "iso:country":"US",
    "sg:address":"1505 Mount Vernon Rd",
    "sg:city":"Atlanta",
    "sg:classifiers":[
        {
            "category":"Building & Trades",
            "subcategory":"Construction",
            "type":"Services"
        }
    ],
    "sg:phone":"+1 770 352 0870",
    "sg:postcode":"30338",
    "sg:province":"GA",
    "sg:tags":[
        "general",
        "contractor"
    ],
    "wof:name":"Dudley Barrett Construction",
    "wof:placetype":"venue"
},
  "geometry": {"coordinates":[-84.334272,33.945985],"type":"Point"}
}