{
  "type": "Feature",
  "properties": {
    "addr:full":"3700 Woodland Dr Columbus GA 31907",
    "addr:housenumber":"3700",
    "addr:postcode":"31907",
    "addr:street":"Woodland Dr",
    "iso:country":"US",
    "sg:address":"3700 Woodland Dr",
    "sg:city":"Columbus",
    "sg:classifiers":[
        {
            "category":"Education",
            "subcategory":"School",
            "type":"Public Place"
        }
    ],
    "sg:phone":"+1 706 748 2814",
    "sg:postcode":"31907",
    "sg:province":"GA",
    "sg:tags":[
        "elementary"
    ],
    "wof:name":"Johnson Elementary School",
    "wof:placetype":"venue"
},
  "geometry": {"coordinates":[-84.931442,32.47879],"type":"Point"}
}