{
  "type": "Feature",
  "properties": {
    "iso:country":"US",
    "sg:address":"4861 Clubgreen Summit Rd",
    "sg:city":"Stone Mountain",
    "sg:classifiers":[
        {
            "category":"Professional",
            "subcategory":"Management & Consulting",
            "type":"Services"
        }
    ],
    "sg:phone":"+1 770 323 3731",
    "sg:postcode":"30088",
    "sg:province":"GA",
    "sg:tags":[
        "consultant",
        "training"
    ],
    "wof:name":"Pauses",
    "wof:placetype":"venue"
},
  "geometry": {"coordinates":[-84.18916299999999,33.741016],"type":"Point"}
}