{
  "type": "Feature",
  "properties": {
    "addr:full":"507 Poplar St West Point GA 31833",
    "addr:housenumber":"507",
    "addr:postcode":"31833",
    "addr:street":"Poplar St",
    "iso:country":"US",
    "sg:address":"507 Poplar St",
    "sg:city":"West Point",
    "sg:classifiers":[
        {
            "category":"Organizations",
            "subcategory":"Religious Organization",
            "type":"Services"
        }
    ],
    "sg:phone":"+1 706 643 1051",
    "sg:postcode":"31833",
    "sg:province":"GA",
    "sg:website":"www.roperheightsbaptchurch.org",
    "wof:name":"Roper Heights Baptist Church",
    "wof:placetype":"venue"
},
  "geometry": {"coordinates":[-85.164912,32.887975],"type":"Point"}
}