{
  "type": "Feature",
  "properties": {
    "addr:full":"201 5th St W Darien GA 31305",
    "addr:housenumber":"201",
    "addr:postcode":"31305",
    "addr:street":"5Th St W Darien",
    "iso:country":"US",
    "sg:address":"201 5th St W",
    "sg:city":"Darien",
    "sg:classifiers":[
        {
            "category":"Organizations",
            "subcategory":"Religious Organization",
            "type":"Services"
        }
    ],
    "sg:phone":"+1 912 437 4959",
    "sg:postcode":"31305",
    "sg:province":"GA",
    "sg:tags":[
        "church"
    ],
    "wof:name":"First Baptist Church",
    "wof:placetype":"venue"
},
  "geometry": {"coordinates":[-81.43536,31.372979],"type":"Point"}
}