{
  "type": "Feature",
  "properties": {
    "addr:full":"706 Ave K West Point GA 31833",
    "addr:housenumber":"706",
    "addr:postcode":"31833",
    "addr:street":"Ave K",
    "iso:country":"US",
    "sg:address":"706 Ave K",
    "sg:city":"West Point",
    "sg:classifiers":[
        {
            "category":"Wholesale",
            "subcategory":"Durable Goods & Equipment",
            "type":"Manufacturing & Wholesale Goods"
        }
    ],
    "sg:phone":"+1 706 643 8158",
    "sg:postcode":"31833",
    "sg:province":"GA",
    "sg:tags":[
        "exporter"
    ],
    "wof:name":"Zynko Technology & Marketing",
    "wof:placetype":"venue"
},
  "geometry": {"coordinates":[-85.17001,32.873764],"type":"Point"}
}