{
  "type": "Feature",
  "properties": {
    "addr:full":"126 W Greene St Ste 18 Monticello GA 31064",
    "addr:housenumber":"126;18",
    "addr:postcode":"31064",
    "addr:street":"W Greene St Ste",
    "iso:country":"US",
    "sg:address":"126 W Greene St Ste 18",
    "sg:city":"Monticello",
    "sg:classifiers":[
        {
            "category":"Structure",
            "subcategory":"Office Building",
            "type":"Public Place"
        }
    ],
    "sg:phone":"+1 706 468 4900",
    "sg:postcode":"31064",
    "sg:province":"GA",
    "sg:tags":[
        "park"
    ],
    "sg:website":"http://www.jaspercountyga.org",
    "wof:name":"Board Of Commissioner",
    "wof:placetype":"venue"
},
  "geometry": {"coordinates":[-83.68366,33.304615],"type":"Point"}
}