{
  "type": "Feature",
  "properties": {
    "iso:country":"US",
    "sg:address":"3416 Forest Ridge Dr",
    "sg:city":"Albany",
    "sg:classifiers":[
        {
            "category":"Real Estate",
            "subcategory":"Real Estate Agent",
            "type":"Services"
        }
    ],
    "sg:phone":"+1 229 888 9101",
    "sg:postcode":"31721",
    "sg:province":"GA",
    "wof:name":"Motons Plus Inv Corp",
    "wof:placetype":"venue"
},
  "geometry": {"coordinates":[-84.236277,31.617067],"type":"Point"}
}