{
  "type": "Feature",
  "properties": {
    "addr:full":"100 Hickory Springs Industrial Dr Canton GA 30115",
    "addr:housenumber":"100",
    "addr:postcode":"30115",
    "addr:street":"Hickory Springs Industrial Dr",
    "iso:country":"US",
    "sg:address":"100 Hickory Springs Industrial Dr",
    "sg:city":"Canton",
    "sg:classifiers":[
        {
            "category":"Building & Trades",
            "subcategory":"Pest Control",
            "type":"Services"
        }
    ],
    "sg:phone":"+1 770 345 1384",
    "sg:postcode":"30115",
    "sg:province":"GA",
    "wof:name":"Orkin Exterminating Co",
    "wof:placetype":"venue"
},
  "geometry": {"coordinates":[-84.494407,34.171076],"type":"Point"}
}