{
  "type": "Feature",
  "properties": {
    "addr:full":"1565 Hascall Dr Marietta GA 30064",
    "addr:housenumber":"1565",
    "addr:postcode":"30064",
    "addr:street":"Hascall Dr",
    "iso:country":"US",
    "sg:address":"1565 Hascall Dr",
    "sg:city":"Marietta",
    "sg:classifiers":[
        {
            "category":"Banks & Credit Unions",
            "subcategory":"Bank",
            "type":"Services"
        }
    ],
    "sg:phone":"+1 770 426 9738",
    "sg:postcode":"30064",
    "sg:province":"GA",
    "sg:tags":[
        "mortgage"
    ],
    "wof:name":"Home Success",
    "wof:placetype":"venue"
},
  "geometry": {"coordinates":[-84.612228,33.917091],"type":"Point"}
}