{
  "type": "Feature",
  "properties": {
    "iso:country":"US",
    "sg:address":"2947 Scotland Rd",
    "sg:city":"Dublin",
    "sg:classifiers":[
        {
            "category":"Professional",
            "type":"Services"
        }
    ],
    "sg:phone":"+1 478 463 3067",
    "sg:postcode":"31021",
    "sg:province":"GA",
    "wof:name":"David R Alligood",
    "wof:placetype":"venue"
},
  "geometry": {"coordinates":[-82.858985,32.282987],"type":"Point"}
}