{
  "type": "Feature",
  "properties": {
    "addr:full":"224 Bryan St E Douglas GA 31533",
    "addr:housenumber":"224",
    "addr:postcode":"31533",
    "addr:street":"Bryan St E",
    "iso:country":"US",
    "sg:address":"224 Bryan St E",
    "sg:city":"Douglas",
    "sg:classifiers":[
        {
            "category":"Government",
            "subcategory":"City Hall",
            "type":"Public Place"
        },
        {
            "category":"Government",
            "subcategory":"Office",
            "type":"Public Place"
        }
    ],
    "sg:phone":"+1 912 384 3302",
    "sg:postcode":"31533",
    "sg:province":"GA",
    "sg:tags":[
        "town",
        "township",
        "planner",
        "government-city",
        "village"
    ],
    "wof:name":"City of Douglas",
    "wof:placetype":"venue"
},
  "geometry": {"coordinates":[-82.84921199999999,31.506398],"type":"Point"}
}