{
  "type": "Feature",
  "properties": {
    "addr:full":"921 Bush Rd Dublin GA 31027",
    "addr:housenumber":"921",
    "addr:postcode":"31027",
    "addr:street":"Bush Rd",
    "iso:country":"US",
    "sg:address":"921 Bush Rd",
    "sg:city":"Dublin",
    "sg:classifiers":[
        {
            "category":"Building & Trades",
            "subcategory":"Construction",
            "type":"Services"
        }
    ],
    "sg:phone":"+1 478 272 3348",
    "sg:postcode":"31027",
    "sg:province":"GA",
    "sg:tags":[
        "house",
        "carpentry",
        "cabinet",
        "maker",
        "contractor"
    ],
    "wof:name":"Townsend's Cabinet Shop",
    "wof:placetype":"venue"
},
  "geometry": {"coordinates":[-82.782563,32.47265],"type":"Point"}
}