{
  "type": "Feature",
  "properties": {
    "iso:country":"US",
    "sg:address":"1501 Osborne Rd",
    "sg:city":"Statham",
    "sg:classifiers":[
        {
            "category":"Real Estate",
            "subcategory":"Real Estate Services",
            "type":"Services"
        },
        {
            "category":"Real Estate",
            "subcategory":"Real Estate Agent",
            "type":"Services"
        }
    ],
    "sg:phone":"+1 770 725 7866",
    "sg:postcode":"30666",
    "sg:province":"GA",
    "sg:tags":[
        "management"
    ],
    "wof:name":"Cheryl O Bond Enterprises Inc",
    "wof:placetype":"venue"
},
  "geometry": {"coordinates":[-83.61625100000001,33.904879],"type":"Point"}
}