{
  "type": "Feature",
  "properties": {
    "iso:country":"US",
    "sg:address":"2300 Windy Ridge Pkwy SE",
    "sg:city":"Atlanta",
    "sg:classifiers":[
        {
            "category":"Real Estate",
            "subcategory":"Real Estate Agent",
            "type":"Services"
        }
    ],
    "sg:phone":"+1 770 951 8700",
    "sg:postcode":"30339",
    "sg:province":"GA",
    "sg:tags":[
        "management"
    ],
    "sg:website":"www.cousinsproperties.com",
    "wof:name":"Cousins Real Estate Corp",
    "wof:placetype":"venue"
},
  "geometry": {"coordinates":[-84.460093,33.90503],"type":"Point"}
}