{
  "type": "Feature",
  "properties": {
    "addr:full":"913 E Shotwell St Bainbridge GA 39819",
    "addr:housenumber":"913",
    "addr:postcode":"39819",
    "addr:street":"E Shotwell St",
    "iso:country":"US",
    "sg:address":"913 E Shotwell St",
    "sg:city":"Bainbridge",
    "sg:classifiers":[
        {
            "category":"Building & Trades",
            "subcategory":"Equipment Rental",
            "type":"Services"
        }
    ],
    "sg:phone":"+1 229 246 5100",
    "sg:postcode":"39819",
    "sg:province":"GA",
    "wof:name":"Rent-A-Center",
    "wof:placetype":"venue"
},
  "geometry": {"coordinates":[-84.565527,30.904052],"type":"Point"}
}