{
  "type": "Feature",
  "properties": {
    "addr:full":"6268 Branchville Rd Camilla GA 31730",
    "addr:housenumber":"6268",
    "addr:postcode":"31730",
    "addr:street":"Branchville Rd",
    "iso:country":"US",
    "sg:address":"6268 Branchville Rd",
    "sg:city":"Camilla",
    "sg:classifiers":[
        {
            "category":"Farming",
            "subcategory":"Livestock Farm",
            "type":"Manufacturing & Wholesale Goods"
        }
    ],
    "sg:phone":"+1 229 336 0562",
    "sg:postcode":"31730",
    "sg:province":"GA",
    "sg:tags":[
        "animal",
        "general"
    ],
    "wof:name":"Hilliard Farm",
    "wof:placetype":"venue"
},
  "geometry": {"coordinates":[-84.252218,31.178204],"type":"Point"}
}