{
  "type": "Feature",
  "properties": {
    "addr:full":"205 Johnny Mercer Blvd Savannah GA 31410",
    "addr:housenumber":"205",
    "addr:postcode":"31410",
    "addr:street":"Johnny Mercer Blvd",
    "iso:country":"US",
    "sg:address":"205 Johnny Mercer Blvd",
    "sg:city":"Savannah",
    "sg:classifiers":[
        {
            "category":"Food & Beverages",
            "subcategory":"Liquor & Beverages",
            "type":"Retail Goods"
        }
    ],
    "sg:phone":"+1 912 897 2606",
    "sg:postcode":"31410",
    "sg:province":"GA",
    "wof:name":"Wilmington Island Beverage",
    "wof:placetype":"venue"
},
  "geometry": {"coordinates":[-80.983203,32.013825],"type":"Point"}
}