{
  "type": "Feature",
  "properties": {
    "addr:full":"1209 Chattanooga Rd Dalton GA 30720",
    "addr:housenumber":"1209",
    "addr:postcode":"30720",
    "addr:street":"Chattanooga Rd",
    "iso:country":"US",
    "sg:address":"1209 Chattanooga Rd",
    "sg:city":"Dalton",
    "sg:classifiers":[
        {
            "category":"Autos & Motor Vehicles",
            "subcategory":"Automobile Sales",
            "type":"Retail Goods"
        }
    ],
    "sg:phone":"+1 706 278 2082",
    "sg:postcode":"30720",
    "sg:province":"GA",
    "sg:tags":[
        "used"
    ],
    "wof:name":"Smith Motors",
    "wof:placetype":"venue"
},
  "geometry": {"coordinates":[-84.97377299999999,34.780863],"type":"Point"}
}