{
  "type": "Feature",
  "properties": {
    "addr:full":"2656 Old Grade Rd Dalton GA 30721",
    "addr:housenumber":"2656",
    "addr:postcode":"30721",
    "addr:street":"Old Grade Rd",
    "iso:country":"US",
    "sg:address":"2656 Old Grade Rd",
    "sg:city":"Dalton",
    "sg:classifiers":[
        {
            "category":"Wholesale",
            "subcategory":"Apparel",
            "type":"Manufacturing & Wholesale Goods"
        }
    ],
    "sg:phone":"+1 706 278 1715",
    "sg:postcode":"30721",
    "sg:province":"GA",
    "sg:tags":[
        "lady"
    ],
    "wof:name":"Avis Apparel",
    "wof:placetype":"venue"
},
  "geometry": {"coordinates":[-84.92533,34.764538],"type":"Point"}
}