{
  "type": "Feature",
  "properties": {
    "iso:country":"US",
    "sg:address":"105 Pilgrim Way",
    "sg:city":"Fayetteville",
    "sg:classifiers":[
        {
            "category":"Autos & Motor Vehicles",
            "subcategory":"Auto Supplies",
            "type":"Retail Goods"
        }
    ],
    "sg:phone":"+1 770 716 7778",
    "sg:postcode":"30214",
    "sg:province":"GA",
    "sg:tags":[
        "glass"
    ],
    "wof:name":"Pay Less Auto Glass",
    "wof:placetype":"venue"
},
  "geometry": {"coordinates":[-84.45131499999999,33.479902],"type":"Point"}
}