{
  "type": "Feature",
  "properties": {
    "addr:full":"3150 Howell Mill Rd NW Atlanta GA 30327",
    "addr:housenumber":"3150",
    "addr:postcode":"30327",
    "addr:street":"Howell Mill Rd Nw",
    "iso:country":"US",
    "sg:address":"3150 Howell Mill Rd NW",
    "sg:city":"Atlanta",
    "sg:classifiers":[
        {
            "category":"Health Services",
            "subcategory":"Hospice",
            "type":"Services"
        }
    ],
    "sg:phone":"+1 404 352 4308",
    "sg:postcode":"30327",
    "sg:province":"GA",
    "sg:website":"http://www.weinsteinhospice.org",
    "wof:name":"Weinstein Hospice",
    "wof:placetype":"venue"
},
  "geometry": {"coordinates":[-84.42710099999999,33.840481],"type":"Point"}
}