{
  "type": "Feature",
  "properties": {
    "iso:country":"US",
    "sg:address":"2008 State Rte 54",
    "sg:city":"Fayetteville",
    "sg:classifiers":[
        {
            "category":"Professional",
            "type":"Services"
        }
    ],
    "sg:phone":"+1 770 631 1114",
    "sg:postcode":"30214",
    "sg:province":"GA",
    "wof:name":"Georgia Bancshares Inc",
    "wof:placetype":"venue"
},
  "geometry": {"coordinates":[-84.55647,33.428007],"type":"Point"}
}