{
  "type": "Feature",
  "properties": {
    "addr:full":"4132 Atlanta Hwy Loganville GA 30052",
    "addr:housenumber":"4132",
    "addr:postcode":"30052",
    "addr:street":"Atlanta Hwy",
    "iso:country":"US",
    "sg:address":"4132 Atlanta Hwy",
    "sg:city":"Loganville",
    "sg:classifiers":[
        {
            "category":"Health Services",
            "subcategory":"Doctor",
            "type":"Services"
        }
    ],
    "sg:phone":"+1 678 475 7817",
    "sg:postcode":"30052",
    "sg:province":"GA",
    "sg:tags":[
        "dentist"
    ],
    "wof:name":"North Georgia Orthodontics",
    "wof:placetype":"venue"
},
  "geometry": {"coordinates":[-83.90765,33.843578],"type":"Point"}
}