{
  "type": "Feature",
  "properties": {
    "iso:country":"US",
    "sg:address":"5675 Jimmy Carter Blvd",
    "sg:city":"Norcross",
    "sg:classifiers":[
        {
            "category":"Professional",
            "type":"Services"
        }
    ],
    "sg:phone":"+1 770 729 9555",
    "sg:postcode":"30071",
    "sg:province":"GA",
    "wof:name":"Raxa",
    "wof:placetype":"venue"
},
  "geometry": {"coordinates":[-84.208217,33.913413],"type":"Point"}
}