{
  "type": "Feature",
  "properties": {
    "iso:country":"US",
    "sg:address":"7020 Glade Rd SE",
    "sg:city":"Acworth",
    "sg:classifiers":[
        {
            "category":"Building & Trades",
            "subcategory":"Construction",
            "type":"Services"
        }
    ],
    "sg:phone":"+1 678 574 9202",
    "sg:postcode":"30102",
    "sg:province":"GA",
    "sg:tags":[
        "house"
    ],
    "wof:name":"Mako Enterprises Inc",
    "wof:placetype":"venue"
},
  "geometry": {"coordinates":[-84.68258899999999,34.127742],"type":"Point"}
}