{
  "type": "Feature",
  "properties": {
    "addr:full":"11720 Medlock Bridge Rd Duluth GA 30097",
    "addr:housenumber":"11720",
    "addr:postcode":"30097",
    "addr:street":"Medlock Bridge Rd",
    "iso:country":"US",
    "sg:address":"11720 Medlock Bridge Rd",
    "sg:city":"Duluth",
    "sg:classifiers":[
        {
            "category":"Shopping",
            "subcategory":"Optical Goods",
            "type":"Retail Goods"
        }
    ],
    "sg:phone":"+1 770 495 7898",
    "sg:postcode":"30097",
    "sg:province":"GA",
    "wof:name":"Doctor's Visionworks",
    "wof:placetype":"venue"
},
  "geometry": {"coordinates":[-84.170349,34.064498],"type":"Point"}
}