{
  "type": "Feature",
  "properties": {
    "addr:full":"4730 Lake Mirror Pl Forest Park GA 30297",
    "addr:housenumber":"4730",
    "addr:postcode":"30297",
    "addr:street":"Lake Mirror Pl",
    "iso:country":"US",
    "sg:address":"4730 Lake Mirror Pl",
    "sg:city":"Forest Park",
    "sg:classifiers":[
        {
            "category":"Freight",
            "type":"Transportation"
        },
        {
            "category":"Professional",
            "subcategory":"Business Services",
            "type":"Services"
        }
    ],
    "sg:phone":"+1 404 608 7180",
    "sg:postcode":"30297",
    "sg:province":"GA",
    "sg:tags":[
        "courier"
    ],
    "wof:name":"Roll On Express Inc",
    "wof:placetype":"venue"
},
  "geometry": {"coordinates":[-84.394431,33.625448],"type":"Point"}
}