{
  "type": "Feature",
  "properties": {
    "iso:country":"US",
    "sg:address":"260 N Milledge Ave",
    "sg:city":"Athens",
    "sg:classifiers":[
        {
            "category":"Insurance",
            "subcategory":"Insurance Agent",
            "type":"Services"
        }
    ],
    "sg:phone":"+1 706 353 8444",
    "sg:postcode":"30601",
    "sg:province":"GA",
    "sg:website":"http://www.baumwald.com",
    "wof:name":"Larry Baumwald Insurance",
    "wof:placetype":"venue"
},
  "geometry": {"coordinates":[-83.388953,33.956776],"type":"Point"}
}