{
  "type": "Feature",
  "properties": {
    "addr:full":"1717 Wimbledon Dr Thomasville GA 31792",
    "addr:housenumber":"1717",
    "addr:postcode":"31792",
    "addr:street":"Wimbledon Dr",
    "iso:country":"US",
    "sg:address":"1717 Wimbledon Dr",
    "sg:city":"Thomasville",
    "sg:classifiers":[
        {
            "category":"Coffee & Tea",
            "type":"Food & Drink"
        },
        {
            "category":"Restaurant",
            "type":"Food & Drink"
        }
    ],
    "sg:phone":"+1 229 225 9303",
    "sg:postcode":"31792",
    "sg:province":"GA",
    "sg:tags":[
        "espresso"
    ],
    "wof:name":"Sydmor Patisserie & Cafe",
    "wof:placetype":"venue"
},
  "geometry": {"coordinates":[-83.953275,30.826756],"type":"Point"}
}