{
  "type": "Feature",
  "properties": {
    "addr:full":"668 Richardson Rd NE Dalton GA 30721",
    "addr:housenumber":"668",
    "addr:postcode":"30721",
    "addr:street":"Richardson Rd Ne",
    "iso:country":"US",
    "sg:address":"668 Richardson Rd NE",
    "sg:city":"Dalton",
    "sg:classifiers":[
        {
            "category":"Manufacturing",
            "subcategory":"Textiles",
            "type":"Manufacturing & Wholesale Goods"
        }
    ],
    "sg:phone":"+1 706 259 4316",
    "sg:postcode":"30721",
    "sg:province":"GA",
    "sg:tags":[
        "mfg"
    ],
    "wof:name":"Lynette",
    "wof:placetype":"venue"
},
  "geometry": {"coordinates":[-84.879688,34.813213],"type":"Point"}
}