{
  "type": "Feature",
  "properties": {
    "addr:full":"171 Notnomis Rd Franklin GA 30217",
    "addr:housenumber":"171",
    "addr:postcode":"30217",
    "addr:street":"Notnomis Rd",
    "iso:country":"US",
    "sg:address":"171 Notnomis Rd",
    "sg:city":"Franklin",
    "sg:classifiers":[
        {
            "category":"Government",
            "subcategory":"Office",
            "type":"Public Place"
        }
    ],
    "sg:phone":"+1 770 854 5801",
    "sg:postcode":"30217",
    "sg:province":"GA",
    "sg:tags":[
        "legislative",
        "body",
        "city"
    ],
    "wof:name":"Central Hatchee City Hall",
    "wof:placetype":"venue"
},
  "geometry": {"coordinates":[-85.108959,33.362852],"type":"Point"}
}