{
  "type": "Feature",
  "properties": {
    "iso:country":"US",
    "sg:address":"671 10th St NW",
    "sg:city":"Atlanta",
    "sg:classifiers":[
        {
            "category":"Home & Garden",
            "subcategory":"Building Materials",
            "type":"Retail Goods"
        }
    ],
    "sg:phone":"+1 404 876 8821",
    "sg:postcode":"30318",
    "sg:province":"GA",
    "sg:tags":[
        "wall",
        "wholesale",
        "paint",
        "covering"
    ],
    "wof:name":"Duron Pints Wallcoverings 043",
    "wof:placetype":"venue"
},
  "geometry": {"coordinates":[-84.41013700000001,33.781643],"type":"Point"}
}