{
  "type": "Feature",
  "properties": {
    "iso:country":"US",
    "sg:address":"6041 Mableton Pkwy SE",
    "sg:city":"Mableton",
    "sg:classifiers":[
        {
            "category":"Manufacturing",
            "subcategory":"Printing",
            "type":"Manufacturing & Wholesale Goods"
        }
    ],
    "sg:phone":"+1 770 948 7099",
    "sg:postcode":"30126",
    "sg:province":"GA",
    "sg:tags":[
        "printer",
        "commercial"
    ],
    "wof:name":"Ramsey Printing Services",
    "wof:placetype":"venue"
},
  "geometry": {"coordinates":[-84.569113,33.805139],"type":"Point"}
}