{
  "type": "Feature",
  "properties": {
    "iso:country":"US",
    "sg:address":"5491 Palmer Rd",
    "sg:city":"Ochlocknee",
    "sg:classifiers":[
        {
            "category":"Manufacturing",
            "subcategory":"Metals",
            "type":"Manufacturing & Wholesale Goods"
        }
    ],
    "sg:phone":"+1 229 683 3484",
    "sg:postcode":"31773",
    "sg:province":"GA",
    "sg:tags":[
        "metal-wholesale",
        "specialty",
        "manufacturer"
    ],
    "wof:name":"Watts Metal Fabrication",
    "wof:placetype":"venue"
},
  "geometry": {"coordinates":[-84.015214,31.034094],"type":"Point"}
}