{
  "type": "Feature",
  "properties": {
    "addr:full":"360 Cedar St Metter GA 30439",
    "addr:housenumber":"360",
    "addr:postcode":"30439",
    "addr:street":"Cedar St",
    "iso:country":"US",
    "sg:address":"360 Cedar St",
    "sg:city":"Metter",
    "sg:classifiers":[
        {
            "category":"Government",
            "subcategory":"Office",
            "type":"Public Place"
        }
    ],
    "sg:phone":"+1 912 685 6424",
    "sg:postcode":"30439",
    "sg:province":"GA",
    "sg:tags":[
        "state"
    ],
    "wof:name":"Natural Resources Dept-Fishery",
    "wof:placetype":"venue"
},
  "geometry": {"coordinates":[-82.066152,32.405798],"type":"Point"}
}