{
  "type": "Feature",
  "properties": {
    "iso:country":"US",
    "sg:address":"2971 Flowers Rd S",
    "sg:city":"Atlanta",
    "sg:classifiers":[
        {
            "category":"Professional",
            "subcategory":"Management & Consulting",
            "type":"Services"
        }
    ],
    "sg:phone":"+1 770 451 1922",
    "sg:postcode":"30341",
    "sg:province":"GA",
    "sg:tags":[
        "book",
        "business"
    ],
    "wof:name":"St Barthelemy Press Limited",
    "wof:placetype":"venue"
},
  "geometry": {"coordinates":[-84.264127,33.870263],"type":"Point"}
}