{
  "type": "Feature",
  "properties": {
    "addr:full":"120 7th St S Cordele GA 31015",
    "addr:housenumber":"120",
    "addr:postcode":"31015",
    "addr:street":"7Th St S",
    "iso:country":"US",
    "sg:address":"120 7th St S",
    "sg:city":"Cordele",
    "sg:classifiers":[
        {
            "category":"Banks & Credit Unions",
            "subcategory":"Bank",
            "type":"Services"
        }
    ],
    "sg:phone":"+1 229 271 0058",
    "sg:postcode":"31015",
    "sg:province":"GA",
    "sg:tags":[
        "loan"
    ],
    "wof:name":"Pay Day Cash",
    "wof:placetype":"venue"
},
  "geometry": {"coordinates":[-83.782719,31.968168],"type":"Point"}
}