{
  "type": "Feature",
  "properties": {
    "addr:full":"1821 Highland Ave Dublin GA 31021",
    "addr:housenumber":"1821",
    "addr:postcode":"31021",
    "addr:street":"Highland Ave",
    "iso:country":"US",
    "sg:address":"1821 Highland Ave",
    "sg:city":"Dublin",
    "sg:classifiers":[
        {
            "category":"Professional",
            "type":"Services"
        }
    ],
    "sg:phone":"+1 478 275 9500",
    "sg:postcode":"31021",
    "sg:province":"GA",
    "sg:tags":[
        "alternative",
        "abortion"
    ],
    "sg:website":"http://www.preginfoga.com",
    "wof:name":"ABC Women's Clinic",
    "wof:placetype":"venue"
},
  "geometry": {"coordinates":[-82.93714199999999,32.538653],"type":"Point"}
}