{
  "type": "Feature",
  "properties": {
    "iso:country":"US",
    "sg:address":"7900 State Rte 16",
    "sg:city":"Brooks",
    "sg:classifiers":[
        {
            "category":"Shopping",
            "subcategory":"Bicycles & Sporting Goods",
            "type":"Retail Goods"
        }
    ],
    "sg:phone":"+1 770 599 3000",
    "sg:postcode":"30205",
    "sg:province":"GA",
    "sg:tags":[
        "saddlery",
        "harness"
    ],
    "wof:name":"Line Creek Feed & Tack",
    "wof:placetype":"venue"
},
  "geometry": {"coordinates":[-84.495634,33.256037],"type":"Point"}
}