{
  "type": "Feature",
  "properties": {
    "iso:country":"US",
    "sg:address":"6425 Roosevelt Hwy",
    "sg:city":"Union City",
    "sg:classifiers":[
        {
            "category":"Home & Garden",
            "subcategory":"Furniture",
            "type":"Retail Goods"
        }
    ],
    "sg:phone":"+1 770 964 6245",
    "sg:postcode":"30291",
    "sg:province":"GA",
    "wof:name":"Robinson's Antiques",
    "wof:placetype":"venue"
},
  "geometry": {"coordinates":[-84.55432,33.580011],"type":"Point"}
}