{
  "type": "Feature",
  "properties": {
    "iso:country":"US",
    "sg:address":"409 Broad St",
    "sg:city":"Rome",
    "sg:classifiers":[
        {
            "category":"Personal",
            "subcategory":"Beauty Salon",
            "type":"Services"
        }
    ],
    "sg:phone":"+1 706 291 8533",
    "sg:postcode":"30161",
    "sg:province":"GA",
    "sg:tags":[
        "shop"
    ],
    "wof:name":"Styles By Marie",
    "wof:placetype":"venue"
},
  "geometry": {"coordinates":[-85.170433,34.255481],"type":"Point"}
}