{
  "type": "Feature",
  "properties": {
    "iso:country":"US",
    "sg:address":"10600 Roxburgh Ln",
    "sg:city":"Roswell",
    "sg:classifiers":[
        {
            "category":"Professional",
            "subcategory":"Business Services",
            "type":"Services"
        }
    ],
    "sg:phone":"+1 770 751 1079",
    "sg:postcode":"30076",
    "sg:province":"GA",
    "wof:name":"North Pointe Photography",
    "wof:placetype":"venue"
},
  "geometry": {"coordinates":[-84.28798399999999,34.037323],"type":"Point"}
}