{
  "type": "Feature",
  "properties": {
    "addr:full":"230 7th St Macon GA 31201",
    "addr:housenumber":"230",
    "addr:postcode":"31201",
    "addr:street":"7Th St",
    "iso:country":"US",
    "sg:address":"230 7th St",
    "sg:city":"Macon",
    "sg:classifiers":[
        {
            "category":"Shopping",
            "subcategory":"Used Merchandise",
            "type":"Retail Goods"
        }
    ],
    "sg:phone":"+1 478 742 7874",
    "sg:postcode":"31201",
    "sg:province":"GA",
    "wof:name":"Second Chance",
    "wof:placetype":"venue"
},
  "geometry": {"coordinates":[-83.620025,32.833698],"type":"Point"}
}