{
  "type": "Feature",
  "properties": {
    "addr:full":"4518 Stratford Dr Douglasville GA 30135",
    "addr:housenumber":"4518",
    "addr:postcode":"30135",
    "addr:street":"Stratford Dr",
    "iso:country":"US",
    "sg:address":"4518 Stratford Dr",
    "sg:city":"Douglasville",
    "sg:classifiers":[
        {
            "category":"Professional",
            "subcategory":"Business Services",
            "type":"Services"
        }
    ],
    "sg:phone":"+1 770 489 5799",
    "sg:postcode":"30135",
    "sg:province":"GA",
    "wof:name":"Interiors By Frances",
    "wof:placetype":"venue"
},
  "geometry": {"coordinates":[-84.722567,33.689233],"type":"Point"}
}