{
  "type": "Feature",
  "properties": {
    "addr:full":"701 Baytree Rd Valdosta GA 31602",
    "addr:housenumber":"701",
    "addr:postcode":"31602",
    "addr:street":"Baytree Rd",
    "iso:country":"US",
    "sg:address":"701 Baytree Rd",
    "sg:city":"Valdosta",
    "sg:classifiers":[
        {
            "category":"Government",
            "subcategory":"Office",
            "type":"Public Place"
        }
    ],
    "sg:phone":"+1 229 333 5266",
    "sg:postcode":"31602",
    "sg:province":"GA",
    "wof:name":"2 Judicial Administrative Dist",
    "wof:placetype":"venue"
},
  "geometry": {"coordinates":[-83.297821,30.846771],"type":"Point"}
}