{
  "type": "Feature",
  "properties": {
    "addr:full":"6160 Mountain Brook Ln NW Atlanta GA 30328",
    "addr:housenumber":"6160",
    "addr:postcode":"30328",
    "addr:street":"Mountain Brook Ln Nw",
    "iso:country":"US",
    "sg:address":"6160 Mountain Brook Ln NW",
    "sg:city":"Atlanta",
    "sg:classifiers":[
        {
            "category":"Wholesale",
            "subcategory":"Construction Materials",
            "type":"Manufacturing & Wholesale Goods"
        }
    ],
    "sg:phone":"+1 404 252 4781",
    "sg:postcode":"30328",
    "sg:province":"GA",
    "wof:name":"Volan Ted & Assiciates Inc",
    "wof:placetype":"venue"
},
  "geometry": {"coordinates":[-84.41637799999999,33.925233],"type":"Point"}
}