{
  "type": "Feature",
  "properties": {
    "iso:country":"US",
    "sg:address":"2500 Meadowbrook Pkwy",
    "sg:city":"Duluth",
    "sg:classifiers":[
        {
            "category":"Building & Trades",
            "subcategory":"Plumbing",
            "type":"Services"
        }
    ],
    "sg:phone":"+1 404 505 7272",
    "sg:postcode":"30096",
    "sg:province":"GA",
    "sg:tags":[
        "contractor"
    ],
    "wof:name":"All American AC & Htg",
    "wof:placetype":"venue"
},
  "geometry": {"coordinates":[-84.09884599999999,33.975482],"type":"Point"}
}