{
  "type": "Feature",
  "properties": {
    "iso:country":"US",
    "sg:address":"50 Turnbull Rd",
    "sg:city":"Canon",
    "sg:classifiers":[
        {
            "category":"Retail",
            "subcategory":"Auto Repair",
            "type":"Services"
        }
    ],
    "sg:phone":"+1 706 356 2232",
    "sg:postcode":"30520",
    "sg:province":"GA",
    "sg:tags":[
        "body",
        "repairing",
        "painting",
        "automobile"
    ],
    "wof:name":"Fowler Body Shop",
    "wof:placetype":"venue"
},
  "geometry": {"coordinates":[-83.11995899999999,34.375379],"type":"Point"}
}