{
  "type": "Feature",
  "properties": {
    "addr:full":"3100 Highway 16 E Sharpsburg GA 30277",
    "addr:housenumber":"3100",
    "addr:postcode":"30277",
    "addr:street":"Highway 16 E",
    "iso:country":"US",
    "sg:address":"3100 Highway 16 E",
    "sg:city":"Sharpsburg",
    "sg:classifiers":[
        {
            "category":"Building & Trades",
            "subcategory":"Construction",
            "type":"Services"
        },
        {
            "category":"Home & Garden",
            "subcategory":"Carpets & Floor Coverings",
            "type":"Retail Goods"
        }
    ],
    "sg:phone":"+1 770 253 1001",
    "sg:postcode":"30277",
    "sg:province":"GA",
    "sg:tags":[
        "hardwood",
        "linoleum",
        "rug",
        "tile-contractors"
    ],
    "sg:website":"http://www.cowetaflooring.com",
    "wof:name":"Coweta Flooring",
    "wof:placetype":"venue"
},
  "geometry": {"coordinates":[-84.68644500000001,33.337908],"type":"Point"}
}