{
  "type": "Feature",
  "properties": {
    "iso:country":"US",
    "sg:address":"3520 Chartwell Blvd",
    "sg:city":"Suwanee",
    "sg:classifiers":[
        {
            "category":"Manufacturing",
            "subcategory":"Toys & Sporting Goods",
            "type":"Manufacturing & Wholesale Goods"
        }
    ],
    "sg:phone":"+1 770 889 8500",
    "sg:postcode":"30024",
    "sg:province":"GA",
    "sg:tags":[
        "equipment",
        "exercise",
        "mfg"
    ],
    "wof:name":"Technogym USA",
    "wof:placetype":"venue"
},
  "geometry": {"coordinates":[-84.151672,34.106439],"type":"Point"}
}