{
  "type": "Feature",
  "properties": {
    "iso:country":"US",
    "sg:address":"1736 Barton Chapel Rd",
    "sg:city":"Augusta",
    "sg:classifiers":[
        {
            "category":"Utilities",
            "subcategory":"Refuse",
            "type":"Services"
        }
    ],
    "sg:phone":"+1 706 667 9904",
    "sg:postcode":"30909",
    "sg:province":"GA",
    "sg:tags":[
        "truck",
        "dump"
    ],
    "wof:name":"Harris Trucking & Construction Inc",
    "wof:placetype":"venue"
},
  "geometry": {"coordinates":[-82.086082,33.455959],"type":"Point"}
}