{
  "type": "Feature",
  "properties": {
    "addr:full":"3847 State Rte 54 Hogansville GA 30230",
    "addr:housenumber":"3847",
    "addr:postcode":"30230",
    "addr:street":"State Rte 54",
    "iso:country":"US",
    "sg:address":"3847 State Rte 54",
    "sg:city":"Hogansville",
    "sg:classifiers":[
        {
            "category":"Organizations",
            "subcategory":"Religious Organization",
            "type":"Services"
        }
    ],
    "sg:phone":"+1 706 882 9290",
    "sg:postcode":"30230",
    "sg:province":"GA",
    "sg:tags":[
        "church"
    ],
    "wof:name":"Shiloh Baptist Church",
    "wof:placetype":"venue"
},
  "geometry": {"coordinates":[-85.018541,33.186012],"type":"Point"}
}