{
  "type": "Feature",
  "properties": {
    "iso:country":"US",
    "sg:address":"2451 Cumberland Pkwy SE",
    "sg:city":"Atlanta",
    "sg:classifiers":[
        {
            "category":"Banks & Credit Unions",
            "subcategory":"Bank",
            "type":"Services"
        },
        {
            "category":"Banks & Credit Unions",
            "subcategory":"Financial Services",
            "type":"Services"
        }
    ],
    "sg:phone":"+1 770 333 1070",
    "sg:postcode":"30339",
    "sg:province":"GA",
    "sg:tags":[
        "financing",
        "loan"
    ],
    "sg:website":"http://www.SunTrust.com",
    "wof:name":"SunTrust Bank - Paces Ferry Publix",
    "wof:placetype":"venue"
},
  "geometry": {"coordinates":[-84.477493,33.862537],"type":"Point"}
}