{
  "type": "Feature",
  "properties": {
    "iso:country":"US",
    "sg:address":"1688 W Taylor Ave",
    "sg:city":"Atlanta",
    "sg:classifiers":[
        {
            "category":"Retail",
            "subcategory":"Car Wash",
            "type":"Services"
        }
    ],
    "sg:phone":"+1 404 766 2623",
    "sg:postcode":"30344",
    "sg:province":"GA",
    "sg:tags":[
        "automobile",
        "upholstery",
        "cleaning"
    ],
    "wof:name":"Carpet Maintenance",
    "wof:placetype":"venue"
},
  "geometry": {"coordinates":[-84.44517,33.67335],"type":"Point"}
}