{
  "type": "Feature",
  "properties": {
    "iso:country":"US",
    "sg:address":"39 Sutton Rd",
    "sg:city":"Tifton",
    "sg:classifiers":[
        {
            "category":"Farming",
            "subcategory":"Farm",
            "type":"Manufacturing & Wholesale Goods"
        }
    ],
    "sg:phone":"+1 229 382 3580",
    "sg:postcode":"31794",
    "sg:province":"GA",
    "wof:name":"Franks Farm",
    "wof:placetype":"venue"
},
  "geometry": {"coordinates":[-83.44876600000001,31.482086],"type":"Point"}
}