{
  "type": "Feature",
  "properties": {
    "addr:full":"3321 Wheeler Rd Augusta GA 30909",
    "addr:housenumber":"3321",
    "addr:postcode":"30909",
    "addr:street":"Wheeler Rd",
    "iso:country":"US",
    "sg:address":"3321 Wheeler Rd",
    "sg:city":"Augusta",
    "sg:classifiers":[
        {
            "category":"Shopping",
            "subcategory":"Antiques",
            "type":"Retail Goods"
        }
    ],
    "sg:phone":"+1 706 738 6676",
    "sg:postcode":"30909",
    "sg:province":"GA",
    "wof:name":"Augusta Antique Show",
    "wof:placetype":"venue"
},
  "geometry": {"coordinates":[-82.061058,33.490883],"type":"Point"}
}