{
  "type": "Feature",
  "properties": {
    "addr:full":"1211 Kelvington Way SW Lilburn GA 30047",
    "addr:housenumber":"1211",
    "addr:postcode":"30047",
    "addr:street":"Kelvington Way Sw",
    "iso:country":"US",
    "sg:address":"1211 Kelvington Way SW",
    "sg:city":"Lilburn",
    "sg:classifiers":[
        {
            "category":"Professional",
            "subcategory":"Business Services",
            "type":"Services"
        },
        {
            "category":"Professional",
            "subcategory":"Management & Consulting",
            "type":"Services"
        }
    ],
    "sg:phone":"+1 678 344 9278",
    "sg:postcode":"30047",
    "sg:province":"GA",
    "sg:tags":[
        "fuel"
    ],
    "sg:website":"www.infocision.com",
    "wof:name":"Info Cision Management Corp",
    "wof:placetype":"venue"
},
  "geometry": {"coordinates":[-84.065673,33.872356],"type":"Point"}
}