{
  "type": "Feature",
  "properties": {
    "iso:country":"US",
    "sg:address":"5452 Salem Springs Dr",
    "sg:city":"Lithonia",
    "sg:classifiers":[
        {
            "category":"Professional",
            "subcategory":"Business Services",
            "type":"Services"
        }
    ],
    "sg:phone":"+1 770 322 0353",
    "sg:postcode":"30038",
    "sg:province":"GA",
    "wof:name":"Jifao Enterprise",
    "wof:placetype":"venue"
},
  "geometry": {"coordinates":[-84.16856,33.676229],"type":"Point"}
}