{
  "type": "Feature",
  "properties": {
    "iso:country":"US",
    "sg:address":"3201 S Cherokee Ln",
    "sg:city":"Woodstock",
    "sg:classifiers":[
        {
            "category":"Professional",
            "subcategory":"Engineering",
            "type":"Services"
        },
        {
            "category":"Professional",
            "subcategory":"Business Services",
            "type":"Services"
        }
    ],
    "sg:phone":"+1 770 475 6328",
    "sg:postcode":"30188",
    "sg:province":"GA",
    "sg:tags":[
        "civil",
        "consultant",
        "consulting",
        "coach",
        "engineer"
    ],
    "wof:name":"Ross Consulting Engineers PC",
    "wof:placetype":"venue"
},
  "geometry": {"coordinates":[-84.47149,34.085212],"type":"Point"}
}