{
  "type": "Feature",
  "properties": {
    "addr:full":"1554 Cedar Grove Rd Conley GA 30288",
    "addr:housenumber":"1554",
    "addr:postcode":"30288",
    "addr:street":"Cedar Grove Rd",
    "iso:country":"US",
    "sg:address":"1554 Cedar Grove Rd",
    "sg:city":"Conley",
    "sg:classifiers":[
        {
            "category":"Local Transit",
            "type":"Transportation"
        },
        {
            "category":"Travel",
            "subcategory":"Travel Agent",
            "type":"Entertainment"
        }
    ],
    "sg:phone":"+1 404 675 9025",
    "sg:postcode":"30288",
    "sg:province":"GA",
    "sg:tags":[
        "operator",
        "bus",
        "line",
        "tour"
    ],
    "wof:name":"Knight Tours",
    "wof:placetype":"venue"
},
  "geometry": {"coordinates":[-84.325383,33.657877],"type":"Point"}
}