{
  "type": "Feature",
  "properties": {
    "addr:full":"2595 Candler Rd Decatur GA 30032",
    "addr:housenumber":"2595",
    "addr:postcode":"30032",
    "addr:street":"Candler Rd",
    "iso:country":"US",
    "sg:address":"2595 Candler Rd",
    "sg:city":"Decatur",
    "sg:classifiers":[
        {
            "category":"Retail",
            "subcategory":"Auto Rental",
            "type":"Services"
        }
    ],
    "sg:phone":"+1 404 212 0881",
    "sg:postcode":"30032",
    "sg:province":"GA",
    "sg:tags":[
        "renting",
        "truck",
        "leasing"
    ],
    "wof:name":"U-Haul Co",
    "wof:placetype":"venue"
},
  "geometry": {"coordinates":[-84.273572,33.71551],"type":"Point"}
}