{
  "type": "Feature",
  "properties": {
    "iso:country":"US",
    "sg:address":"580 Fender Rd",
    "sg:city":"Jesup",
    "sg:classifiers":[
        {
            "category":"Manufacturing",
            "subcategory":"Lumber",
            "type":"Manufacturing & Wholesale Goods"
        }
    ],
    "sg:phone":"+1 912 427 4572",
    "sg:postcode":"31546",
    "sg:province":"GA",
    "sg:tags":[
        "logging",
        "contractor"
    ],
    "wof:name":"J Fred Fender Inc",
    "wof:placetype":"venue"
},
  "geometry": {"coordinates":[-81.837811,31.592006],"type":"Point"}
}