{
  "type": "Feature",
  "properties": {
    "addr:full":"541 Old Alabama Rd SE Cartersville GA 30120",
    "addr:housenumber":"541",
    "addr:postcode":"30120",
    "addr:street":"Old Alabama Rd Se",
    "iso:country":"US",
    "sg:address":"541 Old Alabama Rd SE",
    "sg:city":"Cartersville",
    "sg:classifiers":[
        {
            "category":"Freight",
            "type":"Transportation"
        }
    ],
    "sg:phone":"+1 770 607 0323",
    "sg:postcode":"30120",
    "sg:province":"GA",
    "sg:tags":[
        "operator",
        "trucking"
    ],
    "wof:name":"Averys Bushog",
    "wof:placetype":"venue"
},
  "geometry": {"coordinates":[-84.806197,34.116765],"type":"Point"}
}