{
  "type": "Feature",
  "properties": {
    "iso:country":"US",
    "sg:address":"4704 Martha Berry Hwy",
    "sg:city":"Rome",
    "sg:classifiers":[
        {
            "category":"Freight",
            "type":"Transportation"
        }
    ],
    "sg:phone":"+1 706 232 4244",
    "sg:postcode":"30165",
    "sg:province":"GA",
    "sg:tags":[
        "commercial",
        "storage"
    ],
    "wof:name":"Armuchee Secure Storage",
    "wof:placetype":"venue"
},
  "geometry": {"coordinates":[-85.17245200000001,34.3529],"type":"Point"}
}