{
  "type": "Feature",
  "properties": {
    "addr:full":"Salem Market Ctr Conyers GA 30013",
    "addr:postcode":"30013",
    "iso:country":"US",
    "sg:address":"Salem Market Ctr",
    "sg:city":"Conyers",
    "sg:classifiers":[
        {
            "category":"Professional",
            "subcategory":"Employment Agencies",
            "type":"Services"
        }
    ],
    "sg:phone":"+1 770 483 3432",
    "sg:postcode":"30013",
    "sg:province":"GA",
    "sg:website":"www.adecco.com",
    "wof:name":"Adecco Employment Services",
    "wof:placetype":"venue"
},
  "geometry": {"coordinates":[-83.992699,33.624199],"type":"Point"}
}