{
  "type": "Feature",
  "properties": {
    "iso:country":"US",
    "sg:address":"555 Old Norcross Rd",
    "sg:city":"Lawrenceville",
    "sg:classifiers":[
        {
            "category":"Health Services",
            "subcategory":"Doctor",
            "type":"Services"
        }
    ],
    "sg:phone":"+1 770 822 6360",
    "sg:postcode":"30045",
    "sg:province":"GA",
    "wof:name":"Ellis Howard MD",
    "wof:placetype":"venue"
},
  "geometry": {"coordinates":[-84.00659899999999,33.959099],"type":"Point"}
}