{
  "type": "Feature",
  "properties": {
    "iso:country":"US",
    "sg:address":"318 S 10th St",
    "sg:city":"Lyons",
    "sg:classifiers":[
        {
            "category":"Organizations",
            "subcategory":"Religious Organization",
            "type":"Services"
        }
    ],
    "sg:phone":"+1 912 526 8221",
    "sg:postcode":"30436",
    "sg:province":"GA",
    "sg:tags":[
        "church"
    ],
    "wof:name":"Lyon's Freewill Baptist Church",
    "wof:placetype":"venue"
},
  "geometry": {"coordinates":[-82.311408,32.198498],"type":"Point"}
}