{
  "type": "Feature",
  "properties": {
    "iso:country":"US",
    "sg:address":"437 Sims St",
    "sg:city":"Maysville",
    "sg:classifiers":[
        {
            "category":"Wholesale",
            "subcategory":"Electrical",
            "type":"Manufacturing & Wholesale Goods"
        }
    ],
    "sg:phone":"+1 706 652 3326",
    "sg:postcode":"30558",
    "sg:province":"GA",
    "sg:tags":[
        "supply"
    ],
    "wof:name":"CD Plumbing and Electrical Sup",
    "wof:placetype":"venue"
},
  "geometry": {"coordinates":[-83.56247999999999,34.251467],"type":"Point"}
}