{
  "type": "Feature",
  "properties": {
    "iso:country":"US",
    "sg:address":"44 Darby Crossing Dr #106A",
    "sg:city":"Hiram",
    "sg:classifiers":[
        {
            "category":"Building & Trades",
            "subcategory":"Cleaning & Sanitation",
            "type":"Services"
        }
    ],
    "sg:phone":"+1 678 567 0406",
    "sg:postcode":"30141",
    "sg:province":"GA",
    "sg:tags":[
        "carpet"
    ],
    "wof:name":"Omega Carpet & Janitorial & Water Restoration",
    "wof:placetype":"venue"
},
  "geometry": {"coordinates":[-84.748284,33.903188],"type":"Point"}
}