{
  "type": "Feature",
  "properties": {
    "iso:country":"US",
    "sg:address":"5350 Cross Roads Manor NW",
    "sg:city":"Atlanta",
    "sg:classifiers":[
        {
            "category":"Health Services",
            "subcategory":"Clinic",
            "type":"Services"
        }
    ],
    "sg:phone":"+1 770 952 8275",
    "sg:postcode":"30327",
    "sg:province":"GA",
    "wof:name":"Georgia Medical Research Inc",
    "wof:placetype":"venue"
},
  "geometry": {"coordinates":[-84.41952999999999,33.899879],"type":"Point"}
}