{
  "type": "Feature",
  "properties": {
    "iso:country":"US",
    "sg:address":"1772 Defoor Ave NW",
    "sg:city":"Atlanta",
    "sg:classifiers":[
        {
            "category":"Personal",
            "subcategory":"Beauty Salon",
            "type":"Services"
        }
    ],
    "sg:phone":"+1 404 351 5626",
    "sg:postcode":"30318",
    "sg:province":"GA",
    "sg:tags":[
        "shop"
    ],
    "wof:name":"Hairsong's",
    "wof:placetype":"venue"
},
  "geometry": {"coordinates":[-84.42173099999999,33.804598],"type":"Point"}
}