{
  "type": "Feature",
  "properties": {
    "iso:country":"US",
    "sg:address":"Mavell Rd",
    "sg:city":"Smyrna",
    "sg:classifiers":[
        {
            "category":"Park",
            "type":"Public Place"
        }
    ],
    "sg:postcode":"30080",
    "sg:province":"GA",
    "sg:website":"www.silvercometga.com",
    "wof:name":"Silver Comet Trail",
    "wof:placetype":"venue"
},
  "geometry": {"coordinates":[-84.51674300000001,33.843815],"type":"Point"}
}