{
  "type": "Feature",
  "properties": {
    "addr:full":"106 Greenbay Dr SE Dalton GA 30721",
    "addr:housenumber":"106",
    "addr:postcode":"30721",
    "addr:street":"Greenbay Dr Se",
    "iso:country":"US",
    "sg:address":"106 Greenbay Dr SE",
    "sg:city":"Dalton",
    "sg:classifiers":[
        {
            "category":"Local Transit",
            "type":"Transportation"
        }
    ],
    "sg:phone":"+1 706 370 7746",
    "sg:postcode":"30721",
    "sg:province":"GA",
    "wof:name":"Smith Logostics",
    "wof:placetype":"venue"
},
  "geometry": {"coordinates":[-84.907754,34.76208],"type":"Point"}
}