{
  "type": "Feature",
  "properties": {
    "addr:full":"5857 Earl Wayne Dr Lithonia GA 30058",
    "addr:housenumber":"5857",
    "addr:postcode":"30058",
    "addr:street":"Earl Wayne Dr",
    "iso:country":"US",
    "sg:address":"5857 Earl Wayne Dr",
    "sg:city":"Lithonia",
    "sg:classifiers":[
        {
            "category":"Wholesale",
            "subcategory":"Non-durable Goods",
            "type":"Manufacturing & Wholesale Goods"
        }
    ],
    "sg:phone":"+1 770 484 6797",
    "sg:postcode":"30058",
    "sg:province":"GA",
    "wof:name":"Infinity Intl Imports",
    "wof:placetype":"venue"
},
  "geometry": {"coordinates":[-84.14862599999999,33.740534],"type":"Point"}
}