{
  "type": "Feature",
  "properties": {
    "addr:full":"715 W Highway 96 Warner Robins GA 31088",
    "addr:housenumber":"715",
    "addr:postcode":"31088",
    "addr:street":"W Highway 96",
    "iso:country":"US",
    "sg:address":"715 W Highway 96",
    "sg:city":"Warner Robins",
    "sg:classifiers":[
        {
            "category":"Food & Beverages",
            "subcategory":"Liquor & Beverages",
            "type":"Retail Goods"
        }
    ],
    "sg:phone":"+1 478 988 9464",
    "sg:postcode":"31088",
    "sg:province":"GA",
    "sg:tags":[
        "beer",
        "spirit",
        "wine"
    ],
    "wof:name":"Galaxy Spirits Liquors",
    "wof:placetype":"venue"
},
  "geometry": {"coordinates":[-83.64160200000001,32.594002],"type":"Point"}
}