{
  "type": "Feature",
  "properties": {
    "iso:country":"US",
    "sg:address":"1056 Azalea Cir NE",
    "sg:city":"Marietta",
    "sg:classifiers":[
        {
            "category":"Building & Trades",
            "subcategory":"Construction",
            "type":"Services"
        }
    ],
    "sg:phone":"+1 678 525 9240",
    "sg:postcode":"30062",
    "sg:province":"GA",
    "sg:tags":[
        "house"
    ],
    "wof:name":"Jgc Design & Remodeling",
    "wof:placetype":"venue"
},
  "geometry": {"coordinates":[-84.516561,33.977101],"type":"Point"}
}