{
  "type": "Feature",
  "properties": {
    "iso:country":"US",
    "sg:address":"1479 Brockett Rd",
    "sg:city":"Tucker",
    "sg:classifiers":[
        {
            "category":"Professional",
            "subcategory":"Management & Consulting",
            "type":"Services"
        }
    ],
    "sg:phone":"+1 770 492 1226",
    "sg:postcode":"30084",
    "sg:province":"GA",
    "sg:tags":[
        "consultant",
        "hospital",
        "health"
    ],
    "wof:name":"Thomas Thomas and Walsh Inc",
    "wof:placetype":"venue"
},
  "geometry": {"coordinates":[-84.234279,33.826091],"type":"Point"}
}