{
  "type": "Feature",
  "properties": {
    "addr:full":"405 Old Alabama Rd Ringgold GA 30736",
    "addr:housenumber":"405",
    "addr:postcode":"30736",
    "addr:street":"Old Alabama Rd",
    "iso:country":"US",
    "sg:address":"405 Old Alabama Rd",
    "sg:city":"Ringgold",
    "sg:classifiers":[
        {
            "category":"Restaurant",
            "type":"Food & Drink"
        }
    ],
    "sg:phone":"+1 706 965 6400",
    "sg:postcode":"30736",
    "sg:province":"GA",
    "sg:tags":[
        "eating"
    ],
    "wof:name":"Pizza Hut",
    "wof:placetype":"venue"
},
  "geometry": {"coordinates":[-85.14401599999999,34.858221],"type":"Point"}
}