{
  "type": "Feature",
  "properties": {
    "iso:country":"US",
    "sg:address":"309 Granville Ct",
    "sg:city":"Atlanta",
    "sg:classifiers":[
        {
            "category":"Banks & Credit Unions",
            "subcategory":"Financial Services",
            "type":"Services"
        }
    ],
    "sg:phone":"+1 770 351 0555",
    "sg:postcode":"30328",
    "sg:province":"GA",
    "sg:tags":[
        "investor"
    ],
    "wof:name":"Kaasbell Capital MGT LLC",
    "wof:placetype":"venue"
},
  "geometry": {"coordinates":[-84.361006,33.930144],"type":"Point"}
}