{
  "type": "Feature",
  "properties": {
    "iso:country":"US",
    "sg:address":"130 Brockinton Dr",
    "sg:city":"Saint Simons Island",
    "sg:classifiers":[
        {
            "category":"Shopping",
            "subcategory":"Books",
            "type":"Retail Goods"
        }
    ],
    "sg:phone":"+1 912 638 7897",
    "sg:postcode":"31522",
    "sg:province":"GA",
    "wof:name":"Forgotton Lore",
    "wof:placetype":"venue"
},
  "geometry": {"coordinates":[-81.397842,31.162883],"type":"Point"}
}