{
  "type": "Feature",
  "properties": {
    "iso:country":"US",
    "sg:address":"95 Collier Rd",
    "sg:city":"Atlanta",
    "sg:classifiers":[
        {
            "category":"Health Services",
            "subcategory":"Doctor",
            "type":"Services"
        }
    ],
    "sg:phone":"+1 404 574 5820",
    "sg:postcode":"30370",
    "sg:province":"GA",
    "wof:name":"Dr. Tonya Jordan",
    "wof:placetype":"venue"
},
  "geometry": {"coordinates":[-84.396246,33.807894],"type":"Point"}
}