{
  "type": "Feature",
  "properties": {
    "iso:country":"US",
    "sg:address":"232 Forsyth St SW",
    "sg:city":"Atlanta",
    "sg:classifiers":[
        {
            "category":"Professional",
            "type":"Services"
        }
    ],
    "sg:phone":"+1 404 659 6163",
    "sg:postcode":"30303",
    "sg:province":"GA",
    "wof:name":"Intl Merchant Services",
    "wof:placetype":"venue"
},
  "geometry": {"coordinates":[-84.397284,33.747722],"type":"Point"}
}