{
  "type": "Feature",
  "properties": {
    "addr:full":"5646 Queensborough Dr Dunwoody GA 30338",
    "addr:housenumber":"5646",
    "addr:postcode":"30338",
    "addr:street":"Queensborough Dr",
    "iso:country":"US",
    "sg:address":"5646 Queensborough Dr",
    "sg:city":"Dunwoody",
    "sg:classifiers":[
        {
            "category":"Real Estate",
            "subcategory":"Real Estate Agent",
            "type":"Services"
        }
    ],
    "sg:phone":"+1 770 399 0892",
    "sg:postcode":"30338",
    "sg:province":"GA",
    "sg:tags":[
        "relocation"
    ],
    "wof:name":"Relocation Connection",
    "wof:placetype":"venue"
},
  "geometry": {"coordinates":[-84.34512100000001,33.965813],"type":"Point"}
}