{
  "type": "Feature",
  "properties": {
    "addr:full":"1051 Calhoun Falls Hwy Elberton GA 30635",
    "addr:housenumber":"1051",
    "addr:postcode":"30635",
    "addr:street":"Calhoun Falls Hwy",
    "iso:country":"US",
    "sg:address":"1051 Calhoun Falls Hwy",
    "sg:city":"Elberton",
    "sg:classifiers":[
        {
            "category":"Retail",
            "subcategory":"Repair Shop",
            "type":"Services"
        }
    ],
    "sg:phone":"+1 706 213 9915",
    "sg:postcode":"30635",
    "sg:province":"GA",
    "sg:tags":[
        "textile"
    ],
    "wof:name":"Carlisle Coatings & Waterproof",
    "wof:placetype":"venue"
},
  "geometry": {"coordinates":[-82.67595799999999,34.064262],"type":"Point"}
}