{
  "type": "Feature",
  "properties": {
    "iso:country":"US",
    "sg:address":"112 E Kytle St",
    "sg:city":"Cleveland",
    "sg:classifiers":[
        {
            "category":"Place Of Worship",
            "subcategory":"Church",
            "type":"Public Place"
        },
        {
            "category":"Place Of Worship",
            "type":"Public Place"
        }
    ],
    "sg:phone":"+1 706 865 2228",
    "sg:postcode":"30528",
    "sg:province":"GA",
    "sg:tags":[
        "churches-methodist"
    ],
    "wof:name":"Cleveland United Methodist Church",
    "wof:placetype":"venue"
},
  "geometry": {"coordinates":[-83.76171100000001,34.596678],"type":"Point"}
}