{
  "type": "Feature",
  "properties": {
    "iso:country":"US",
    "sg:address":"4154 Arcadia Industrial Cir SW",
    "sg:city":"Lilburn",
    "sg:classifiers":[
        {
            "category":"Retail",
            "subcategory":"Auto Repair",
            "type":"Services"
        }
    ],
    "sg:phone":"+1 770 806 9950",
    "sg:postcode":"30047",
    "sg:province":"GA",
    "sg:tags":[
        "body",
        "automobile",
        "painting"
    ],
    "wof:name":"Sprayglo Auto Refinishing",
    "wof:placetype":"venue"
},
  "geometry": {"coordinates":[-84.11080699999999,33.894332],"type":"Point"}
}