{
  "type": "Feature",
  "properties": {
    "iso:country":"US",
    "sg:address":"1555 Golf Link Dr",
    "sg:city":"Stone Mountain",
    "sg:classifiers":[
        {
            "category":"Professional",
            "type":"Services"
        }
    ],
    "sg:phone":"+1 770 981 9324",
    "sg:postcode":"30088",
    "sg:province":"GA",
    "wof:name":"East West North South",
    "wof:placetype":"venue"
},
  "geometry": {"coordinates":[-84.179503,33.748056],"type":"Point"}
}