{
  "type": "Feature",
  "properties": {
    "iso:country":"US",
    "sg:address":"3161 Auburn Ave",
    "sg:city":"Dacula",
    "sg:classifiers":[
        {
            "category":"Freight",
            "type":"Transportation"
        }
    ],
    "sg:phone":"+1 770 962 5484",
    "sg:postcode":"30019",
    "sg:province":"GA",
    "sg:tags":[
        "operator",
        "local",
        "trucking"
    ],
    "wof:name":"Ricky Tandum Dump Service",
    "wof:placetype":"venue"
},
  "geometry": {"coordinates":[-83.883447,34.009723],"type":"Point"}
}