{
  "type": "Feature",
  "properties": {
    "iso:country":"US",
    "sg:address":"6200 Dillon Rd",
    "sg:city":"Thomasville",
    "sg:classifiers":[
        {
            "category":"Real Estate",
            "subcategory":"Real Estate Operator",
            "type":"Services"
        }
    ],
    "sg:phone":"+1 229 226 2851",
    "sg:postcode":"31757",
    "sg:province":"GA",
    "sg:tags":[
        "property"
    ],
    "wof:name":"Hufstetler Properties LLP",
    "wof:placetype":"venue"
},
  "geometry": {"coordinates":[-83.88683399999999,30.939593],"type":"Point"}
}