{
  "type": "Feature",
  "properties": {
    "iso:country":"US",
    "sg:address":"1780 Mount Royal Dr NE",
    "sg:city":"Atlanta",
    "sg:classifiers":[
        {
            "category":"Professional",
            "type":"Services"
        }
    ],
    "sg:phone":"+1 404 633 8236",
    "sg:postcode":"30329",
    "sg:province":"GA",
    "wof:name":"Terry Weaver",
    "wof:placetype":"venue"
},
  "geometry": {"coordinates":[-84.32028,33.834312],"type":"Point"}
}