{
  "type": "Feature",
  "properties": {
    "iso:country":"US",
    "sg:address":"5475 Hampstead Way",
    "sg:city":"Duluth",
    "sg:classifiers":[
        {
            "category":"Professional",
            "subcategory":"Management & Consulting",
            "type":"Services"
        }
    ],
    "sg:phone":"+1 678 740 9851",
    "sg:postcode":"30097",
    "sg:province":"GA",
    "sg:tags":[
        "business"
    ],
    "wof:name":"Philip J Dreger Consulting",
    "wof:placetype":"venue"
},
  "geometry": {"coordinates":[-84.20097199999999,34.045914],"type":"Point"}
}