{
  "type": "Feature",
  "properties": {
    "iso:country":"US",
    "sg:address":"445 Bens Branch Rd",
    "sg:city":"Newington",
    "sg:classifiers":[
        {
            "category":"Manufacturing",
            "subcategory":"Tools & Machinery",
            "type":"Manufacturing & Wholesale Goods"
        }
    ],
    "sg:phone":"+1 912 857 3169",
    "sg:postcode":"30467",
    "sg:province":"GA",
    "sg:tags":[
        "shop",
        "industrial",
        "mfg",
        "pattern",
        "machine",
        "parts"
    ],
    "wof:name":"Austin Machine & Pattern Inc",
    "wof:placetype":"venue"
},
  "geometry": {"coordinates":[-81.448666,32.573835],"type":"Point"}
}