{
  "type": "Feature",
  "properties": {
    "iso:country":"US",
    "sg:address":"215 N Main St",
    "sg:city":"Jonesboro",
    "sg:classifiers":[
        {
            "category":"Real Estate",
            "subcategory":"Real Estate Services",
            "type":"Services"
        },
        {
            "category":"Real Estate",
            "subcategory":"Real Estate Agent",
            "type":"Services"
        }
    ],
    "sg:phone":"+1 770 473 7500",
    "sg:postcode":"30236",
    "sg:province":"GA",
    "sg:tags":[
        "buyer",
        "broker"
    ],
    "wof:name":"Brokers Realty Group Ltd",
    "wof:placetype":"venue"
},
  "geometry": {"coordinates":[-84.354421,33.529024],"type":"Point"}
}