{
  "type": "Feature",
  "properties": {
    "addr:full":"120 Melanie Ln Fairburn GA 30213",
    "addr:housenumber":"120",
    "addr:postcode":"30213",
    "addr:street":"Melanie Ln",
    "iso:country":"US",
    "sg:address":"120 Melanie Ln",
    "sg:city":"Fairburn",
    "sg:classifiers":[
        {
            "category":"Professional",
            "subcategory":"Accounting & Tax Preparation",
            "type":"Services"
        }
    ],
    "sg:phone":"+1 770 461 5104",
    "sg:postcode":"30213",
    "sg:province":"GA",
    "sg:tags":[
        "return",
        "filing"
    ],
    "wof:name":"Gerald Ford Accounting & Tax",
    "wof:placetype":"venue"
},
  "geometry": {"coordinates":[-84.474385,33.531057],"type":"Point"}
}