{
  "type": "Feature",
  "properties": {
    "iso:country":"US",
    "sg:address":"250 Martin Luther King Jr Blvd",
    "sg:city":"Savannah",
    "sg:classifiers":[
        {
            "category":"Shopping",
            "subcategory":"Gifts & Souvenirs",
            "type":"Retail Goods"
        }
    ],
    "sg:phone":"+1 912 232 3317",
    "sg:postcode":"31401",
    "sg:province":"GA",
    "wof:name":"Paddys",
    "wof:placetype":"venue"
},
  "geometry": {"coordinates":[-81.098904,32.075807],"type":"Point"}
}