{
  "type": "Feature",
  "properties": {
    "iso:country":"US",
    "sg:address":"800 Main St",
    "sg:city":"Perry",
    "sg:classifiers":[
        {
            "category":"Travel",
            "subcategory":"Hotels & Motels",
            "type":"Entertainment"
        }
    ],
    "sg:phone":"+1 478 987 1000",
    "sg:postcode":"31069",
    "sg:province":"GA",
    "sg:website":"www.newperryhotel.netfirms.com",
    "wof:name":"New Perry Hotel",
    "wof:placetype":"venue"
},
  "geometry": {"coordinates":[-83.73327399999999,32.457493],"type":"Point"}
}