{
  "type": "Feature",
  "properties": {
    "iso:country":"US",
    "sg:address":"2930 Pacific Dr",
    "sg:city":"Norcross",
    "sg:classifiers":[
        {
            "category":"Retail",
            "subcategory":"Repair Shop",
            "type":"Services"
        }
    ],
    "sg:phone":"+1 770 447 6001",
    "sg:postcode":"30071",
    "sg:province":"GA",
    "sg:tags":[
        "machine",
        "copy",
        "sales"
    ],
    "wof:name":"Atlanta Business Solutions",
    "wof:placetype":"venue"
},
  "geometry": {"coordinates":[-84.234982,33.937428],"type":"Point"}
}