{
  "type": "Feature",
  "properties": {
    "iso:country":"US",
    "sg:address":"6328 Mableton Pkwy SE",
    "sg:city":"Mableton",
    "sg:classifiers":[
        {
            "category":"Building & Trades",
            "subcategory":"Construction",
            "type":"Services"
        }
    ],
    "sg:phone":"+1 770 948 2128",
    "sg:postcode":"30126",
    "sg:province":"GA",
    "sg:tags":[
        "contractor"
    ],
    "wof:name":"Mannings Concrete Sawing",
    "wof:placetype":"venue"
},
  "geometry": {"coordinates":[-84.56523799999999,33.798843],"type":"Point"}
}