{
  "type": "Feature",
  "properties": {
    "iso:country":"US",
    "sg:address":"3565 River Birch Trl",
    "sg:city":"Decatur",
    "sg:classifiers":[
        {
            "category":"Professional",
            "type":"Services"
        }
    ],
    "sg:phone":"+1 404 244 8395",
    "sg:postcode":"30034",
    "sg:province":"GA",
    "wof:name":"Friend of A Friend Inc",
    "wof:placetype":"venue"
},
  "geometry": {"coordinates":[-84.279792,33.679395],"type":"Point"}
}