{
  "type": "Feature",
  "properties": {
    "addr:full":"3384 Peachtree Road Suite 605 Atlanta GA 30326",
    "addr:housenumber":"3384",
    "addr:postcode":"30326",
    "addr:street":"Peachtree Road Suite 605",
    "iso:country":"US",
    "sg:address":"3384 Peachtree Road Suite 605",
    "sg:city":"Atlanta",
    "sg:classifiers":[
        {
            "category":"Professional",
            "subcategory":"Computer Services",
            "type":"Services"
        }
    ],
    "sg:phone":"+1 404 841 3913",
    "sg:postcode":"30326",
    "sg:province":"GA",
    "sg:website":"http://www.wildfireplatform.com",
    "wof:name":"WeTheCitizens",
    "wof:placetype":"venue"
},
  "geometry": {"coordinates":[-84.36723000000001,33.847944],"type":"Point"}
}