{
  "type": "Feature",
  "properties": {
    "iso:country":"US",
    "sg:address":"1341 Midlawn Dr",
    "sg:city":"Decatur",
    "sg:classifiers":[
        {
            "category":"Professional",
            "subcategory":"Management & Consulting",
            "type":"Services"
        }
    ],
    "sg:phone":"+1 404 289 5806",
    "sg:postcode":"30032",
    "sg:province":"GA",
    "sg:tags":[
        "business"
    ],
    "wof:name":"Baker Consultants Inc",
    "wof:placetype":"venue"
},
  "geometry": {"coordinates":[-84.26253800000001,33.754098],"type":"Point"}
}