{
  "type": "Feature",
  "properties": {
    "addr:full":"5 Concourse Pkwy Ste 400 Atlanta GA 30328",
    "addr:housenumber":"5",
    "addr:postcode":"30328",
    "addr:street":"Concourse Pkwy Ste 400",
    "iso:country":"US",
    "sg:address":"5 Concourse Pkwy Ste 400",
    "sg:city":"Atlanta",
    "sg:classifiers":[
        {
            "category":"Professional",
            "subcategory":"Lawyer & Legal Services",
            "type":"Services"
        },
        {
            "category":"Banks & Credit Unions",
            "subcategory":"Financial Services",
            "type":"Services"
        }
    ],
    "sg:phone":"+1 770 265 1049",
    "sg:postcode":"30328",
    "sg:province":"GA",
    "sg:website":"www.linkedin.com/in/jindia",
    "wof:name":"Jindia Ajay K Atty",
    "wof:placetype":"venue"
},
  "geometry": {"coordinates":[-84.35193099999999,33.916394],"type":"Point"}
}