{
  "type": "Feature",
  "properties": {
    "addr:full":"12020 US Hwy 221 Bartow GA 30413",
    "addr:housenumber":"12020",
    "addr:postcode":"30413",
    "addr:street":"Us Hwy 221",
    "iso:country":"US",
    "sg:address":"12020 US Hwy 221",
    "sg:city":"Bartow",
    "sg:classifiers":[
        {
            "category":"Organizations",
            "subcategory":"Religious Organization",
            "type":"Services"
        }
    ],
    "sg:phone":"+1 478 364 3263",
    "sg:postcode":"30413",
    "sg:province":"GA",
    "sg:tags":[
        "church"
    ],
    "wof:name":"James Temple C M E Church",
    "wof:placetype":"venue"
},
  "geometry": {"coordinates":[-82.495008,32.824018],"type":"Point"}
}