{
  "type": "Feature",
  "properties": {
    "addr:full":"7342 Highway 85 Riverdale GA 30274",
    "addr:housenumber":"7342",
    "addr:postcode":"30274",
    "addr:street":"Highway 85",
    "iso:country":"US",
    "sg:address":"7342 Highway 85",
    "sg:city":"Riverdale",
    "sg:classifiers":[
        {
            "category":"Education",
            "subcategory":"Vocational School",
            "type":"Public Place"
        }
    ],
    "sg:phone":"+1 770 991 1195",
    "sg:postcode":"30274",
    "sg:province":"GA",
    "sg:tags":[
        "cosmetology"
    ],
    "wof:name":"Beauty College of Georgia",
    "wof:placetype":"venue"
},
  "geometry": {"coordinates":[-84.41419999999999,33.5555],"type":"Point"}
}