{
  "type": "Feature",
  "properties": {
    "iso:country":"US",
    "sg:address":"1745 Angelique Dr",
    "sg:city":"Decatur",
    "sg:classifiers":[
        {
            "category":"Travel",
            "subcategory":"Travel Agent",
            "type":"Entertainment"
        }
    ],
    "sg:phone":"+1 404 633 8526",
    "sg:postcode":"30033",
    "sg:province":"GA",
    "sg:tags":[
        "consultant",
        "transportation"
    ],
    "wof:name":"Waidner Enterprises",
    "wof:placetype":"venue"
},
  "geometry": {"coordinates":[-84.293869,33.833519],"type":"Point"}
}