{
  "type": "Feature",
  "properties": {
    "addr:full":"12 Brown Pl Fort Stewart GA 31315",
    "addr:housenumber":"12",
    "addr:postcode":"31315",
    "addr:street":"Brown Pl",
    "iso:country":"US",
    "sg:address":"12 Brown Pl",
    "sg:city":"Fort Stewart",
    "sg:classifiers":[
        {
            "category":"Professional",
            "subcategory":"Management & Consulting",
            "type":"Services"
        }
    ],
    "sg:phone":"+1 912 877 5645",
    "sg:postcode":"31315",
    "sg:province":"GA",
    "sg:tags":[
        "affairs",
        "public"
    ],
    "wof:name":"Aht Newsmaker",
    "wof:placetype":"venue"
},
  "geometry": {"coordinates":[-81.61439,31.878462],"type":"Point"}
}