{
  "type": "Feature",
  "properties": {
    "addr:full":"5115 Old Ellis Pt Roswell GA 30076",
    "addr:housenumber":"5115",
    "addr:postcode":"30076",
    "addr:street":"Old Ellis Pt",
    "iso:country":"US",
    "sg:address":"5115 Old Ellis Pt",
    "sg:city":"Roswell",
    "sg:classifiers":[
        {
            "category":"Real Estate",
            "subcategory":"Developer",
            "type":"Services"
        }
    ],
    "sg:phone":"+1 770 772 4093",
    "sg:postcode":"30076",
    "sg:province":"GA",
    "wof:name":"Commercial Site Development",
    "wof:placetype":"venue"
},
  "geometry": {"coordinates":[-84.32462200000001,34.051674],"type":"Point"}
}