{
  "type": "Feature",
  "properties": {
    "iso:country":"US",
    "sg:address":"245 N 5th Ave",
    "sg:city":"Rome",
    "sg:classifiers":[
        {
            "category":"Personal",
            "type":"Services"
        }
    ],
    "sg:phone":"+1 706 295 4081",
    "sg:postcode":"30165",
    "sg:province":"GA",
    "wof:name":"Crypt Kicker Tatoo",
    "wof:placetype":"venue"
},
  "geometry": {"coordinates":[-85.17328500000001,34.258022],"type":"Point"}
}