{
  "type": "Feature",
  "properties": {
    "addr:full":"1600 Goshen Rd Augusta GA 30906",
    "addr:housenumber":"1600",
    "addr:postcode":"30906",
    "addr:street":"Goshen Rd",
    "iso:country":"US",
    "sg:address":"1600 Goshen Rd",
    "sg:city":"Augusta",
    "sg:classifiers":[
        {
            "category":"Professional",
            "type":"Services"
        }
    ],
    "sg:phone":"+1 706 560 9008",
    "sg:postcode":"30906",
    "sg:province":"GA",
    "sg:tags":[
        "establishment"
    ],
    "wof:name":"LMCC Corp",
    "wof:placetype":"venue"
},
  "geometry": {"coordinates":[-81.993229,33.338277],"type":"Point"}
}