{
  "type": "Feature",
  "properties": {
    "iso:country":"US",
    "sg:address":"1669 Defoor Ave NW",
    "sg:city":"Atlanta",
    "sg:classifiers":[
        {
            "category":"Building & Trades",
            "subcategory":"Landscaping Services",
            "type":"Services"
        }
    ],
    "sg:phone":"+1 404 352 0024",
    "sg:postcode":"30318",
    "sg:province":"GA",
    "sg:tags":[
        "landscape",
        "contractor"
    ],
    "wof:name":"Turner Tree Svc Inc",
    "wof:placetype":"venue"
},
  "geometry": {"coordinates":[-84.41817899999999,33.800807],"type":"Point"}
}