{
  "type": "Feature",
  "properties": {
    "iso:country":"US",
    "sg:address":"3544 Cedartown Hwy",
    "sg:city":"Lindale",
    "sg:classifiers":[
        {
            "category":"Home & Garden",
            "subcategory":"Garden Supply",
            "type":"Retail Goods"
        }
    ],
    "sg:phone":"+1 706 802 1244",
    "sg:postcode":"30147",
    "sg:province":"GA",
    "sg:tags":[
        "engine"
    ],
    "wof:name":"Pat's Lawnmower & Small Engine",
    "wof:placetype":"venue"
},
  "geometry": {"coordinates":[-85.21301800000001,34.163549],"type":"Point"}
}