{
  "type": "Feature",
  "properties": {
    "addr:full":"77 King Rd NW Adairsville GA 30103",
    "addr:housenumber":"77",
    "addr:postcode":"adairsville;30103",
    "addr:street":"King Rd Nw",
    "iso:country":"US",
    "sg:address":"77 King Rd NW",
    "sg:city":"Adairsville",
    "sg:classifiers":[
        {
            "category":"Shopping",
            "subcategory":"Bicycles & Sporting Goods",
            "type":"Retail Goods"
        }
    ],
    "sg:phone":"+1 770 773 3548",
    "sg:postcode":"30103",
    "sg:province":"GA",
    "wof:name":"Roys Gun Service",
    "wof:placetype":"venue"
},
  "geometry": {"coordinates":[-84.850583,34.355773],"type":"Point"}
}