{
  "type": "Feature",
  "properties": {
    "addr:full":"311 State Rte 49 Byron GA 31008",
    "addr:housenumber":"311",
    "addr:postcode":"31008",
    "addr:street":"State Rte 49",
    "iso:country":"US",
    "sg:address":"311 State Rte 49",
    "sg:city":"Byron",
    "sg:classifiers":[
        {
            "category":"Restaurant",
            "type":"Food & Drink"
        }
    ],
    "sg:phone":"+1 478 956 0331",
    "sg:postcode":"31008",
    "sg:province":"GA",
    "sg:tags":[
        "eating"
    ],
    "wof:name":"China Buffet",
    "wof:placetype":"venue"
},
  "geometry": {"coordinates":[-83.74974400000001,32.656254],"type":"Point"}
}