{
  "type": "Feature",
  "properties": {
    "iso:country":"US",
    "sg:address":"1706 Bowens Mill Hwy",
    "sg:city":"Fitzgerald",
    "sg:classifiers":[
        {
            "category":"Building & Trades",
            "subcategory":"Construction",
            "type":"Services"
        }
    ],
    "sg:phone":"+1 229 423 8254",
    "sg:postcode":"31750",
    "sg:province":"GA",
    "sg:tags":[
        "hanging",
        "contractor"
    ],
    "wof:name":"Gilliard Painting",
    "wof:placetype":"venue"
},
  "geometry": {"coordinates":[-83.21436300000001,31.831024],"type":"Point"}
}