{
  "type": "Feature",
  "properties": {
    "iso:country":"US",
    "sg:address":"1011 Lawton St SW",
    "sg:city":"Atlanta",
    "sg:classifiers":[
        {
            "category":"Organizations",
            "subcategory":"Religious Organization",
            "type":"Services"
        }
    ],
    "sg:phone":"+1 404 758 0189",
    "sg:postcode":"30310",
    "sg:province":"GA",
    "wof:name":"Full Gspl Fith Dlvrance Temple",
    "wof:placetype":"venue"
},
  "geometry": {"coordinates":[-84.42339699999999,33.726965],"type":"Point"}
}