{
  "type": "Feature",
  "properties": {
    "addr:full":"3916 Forego Ct Marietta GA 30062",
    "addr:housenumber":"3916",
    "addr:postcode":"30062",
    "addr:street":"Forego Ct",
    "iso:country":"US",
    "sg:address":"3916 Forego Ct",
    "sg:city":"Marietta",
    "sg:classifiers":[
        {
            "category":"Wholesale",
            "subcategory":"Hardware",
            "type":"Manufacturing & Wholesale Goods"
        },
        {
            "category":"Building & Trades",
            "subcategory":"Plumbing",
            "type":"Services"
        }
    ],
    "sg:phone":"+1 770 578 9796",
    "sg:postcode":"30062",
    "sg:province":"GA",
    "sg:tags":[
        "equipment",
        "purifying",
        "contractor",
        "cleaning",
        "air"
    ],
    "wof:name":"T & A Heating & Air",
    "wof:placetype":"venue"
},
  "geometry": {"coordinates":[-84.438689,34.045013],"type":"Point"}
}