{
  "type": "Feature",
  "properties": {
    "addr:full":"4719 Lower Roswell Rd Marietta GA 30068",
    "addr:housenumber":"4719",
    "addr:postcode":"30068",
    "addr:street":"Lower Roswell Rd",
    "iso:country":"US",
    "sg:address":"4719 Lower Roswell Rd",
    "sg:city":"Marietta",
    "sg:classifiers":[
        {
            "category":"Personal",
            "subcategory":"Beauty Salon",
            "type":"Services"
        },
        {
            "category":"Personal",
            "subcategory":"Day Spa",
            "type":"Services"
        }
    ],
    "sg:phone":"+1 770 971 4130",
    "sg:postcode":"30068",
    "sg:province":"GA",
    "wof:name":"Rain Medi Day Spa",
    "wof:placetype":"venue"
},
  "geometry": {"coordinates":[-84.41426,33.965771],"type":"Point"}
}