{
  "type": "Feature",
  "properties": {
    "iso:country":"US",
    "sg:address":"295 Oak Grove Rd",
    "sg:city":"Cedartown",
    "sg:classifiers":[
        {
            "category":"Building & Trades",
            "subcategory":"Construction",
            "type":"Services"
        }
    ],
    "sg:phone":"+1 770 749 5020",
    "sg:postcode":"30125",
    "sg:province":"GA",
    "wof:name":"R & R Metal Buildings",
    "wof:placetype":"venue"
},
  "geometry": {"coordinates":[-85.23523299999999,34.059193],"type":"Point"}
}