{
  "type": "Feature",
  "properties": {
    "addr:full":"9745 Highway 92 Woodstock GA 30188",
    "addr:housenumber":"9745",
    "addr:postcode":"30188",
    "addr:street":"Highway 92",
    "iso:country":"US",
    "sg:address":"9745 Highway 92",
    "sg:city":"Woodstock",
    "sg:classifiers":[
        {
            "category":"Restaurant",
            "type":"Food & Drink"
        }
    ],
    "sg:menulink":"http://www.allmenus.com/ga/woodstock/147076-artuzzis-italian-kitchen/menu/",
    "sg:phone":"+1 770 592 6522",
    "sg:postcode":"30188",
    "sg:province":"GA",
    "sg:tags":[
        "italian"
    ],
    "wof:name":"Artuzzi's Italian Kitchen",
    "wof:placetype":"venue"
},
  "geometry": {"coordinates":[-84.523916,34.086304],"type":"Point"}
}