{
  "type": "Feature",
  "properties": {
    "addr:full":"2910 Buford Hwy Atlanta GA 30329",
    "addr:housenumber":"2910",
    "addr:postcode":"30329",
    "addr:street":"Buford Hwy",
    "iso:country":"US",
    "sg:address":"2910 Buford Hwy",
    "sg:city":"Atlanta",
    "sg:classifiers":[
        {
            "category":"Shopping",
            "subcategory":"Pharmacy",
            "type":"Retail Goods"
        }
    ],
    "sg:phone":"+1 404 325 2735",
    "sg:postcode":"30329",
    "sg:province":"GA",
    "sg:tags":[
        "drugstore"
    ],
    "sg:website":"www.cvs.com/",
    "wof:name":"CVS",
    "wof:placetype":"venue"
},
  "geometry": {"coordinates":[-84.34037600000001,33.833491],"type":"Point"}
}