{
  "type": "Feature",
  "properties": {
    "addr:full":"210 Peachtree St NW Atlanta GA 30303",
    "addr:housenumber":"210",
    "addr:postcode":"30303",
    "addr:street":"Peachtree St Nw",
    "iso:country":"US",
    "sg:address":"210 Peachtree St NW",
    "sg:city":"Atlanta",
    "sg:classifiers":[
        {
            "category":"Restaurant",
            "type":"Food & Drink"
        }
    ],
    "sg:phone":"+1 404 589 7550",
    "sg:postcode":"30303",
    "sg:province":"GA",
    "wof:name":"Cafe",
    "wof:placetype":"venue"
},
  "geometry": {"coordinates":[-84.387676,33.758578],"type":"Point"}
}