{
  "type": "Feature",
  "properties": {
    "addr:full":"133 Asbury Ln Hiram GA 30141",
    "addr:housenumber":"133",
    "addr:postcode":"30141",
    "addr:street":"Asbury Ln",
    "iso:country":"US",
    "sg:address":"133 Asbury Ln",
    "sg:city":"Hiram",
    "sg:classifiers":[
        {
            "category":"Restaurant",
            "type":"Food & Drink"
        }
    ],
    "sg:phone":"+1 678 715 2592",
    "sg:postcode":"30141",
    "sg:province":"GA",
    "sg:tags":[
        "eating"
    ],
    "wof:name":"Charleston Connection LLC",
    "wof:placetype":"venue"
},
  "geometry": {"coordinates":[-84.79329199999999,33.812825],"type":"Point"}
}