{
  "type": "Feature",
  "properties": {
    "iso:country":"US",
    "sg:address":"48 Fairfield Rd",
    "sg:city":"Villa Rica",
    "sg:classifiers":[
        {
            "category":"Banks & Credit Unions",
            "subcategory":"Bank",
            "type":"Services"
        }
    ],
    "sg:phone":"+1 770 214 2324",
    "sg:postcode":"30180",
    "sg:province":"GA",
    "sg:tags":[
        "loan",
        "real estate"
    ],
    "wof:name":"MPS Mortgage",
    "wof:placetype":"venue"
},
  "geometry": {"coordinates":[-84.95107299999999,33.639759],"type":"Point"}
}