{
  "type": "Feature",
  "properties": {
    "addr:full":"7152 State Rte 83 Monticello GA 31064",
    "addr:housenumber":"7152",
    "addr:postcode":"31064",
    "addr:street":"State Rte 83",
    "iso:country":"US",
    "sg:address":"7152 State Rte 83",
    "sg:city":"Monticello",
    "sg:classifiers":[
        {
            "category":"Building & Trades",
            "subcategory":"Construction",
            "type":"Services"
        }
    ],
    "sg:phone":"+1 706 468 1460",
    "sg:postcode":"31064",
    "sg:province":"GA",
    "sg:tags":[
        "house"
    ],
    "wof:name":"McLaurin Construction",
    "wof:placetype":"venue"
},
  "geometry": {"coordinates":[-83.721846,33.244415],"type":"Point"}
}