{
  "type": "Feature",
  "properties": {
    "addr:full":"226 Timber Lake Cir Douglasville GA 30134",
    "addr:housenumber":"226",
    "addr:postcode":"30134",
    "addr:street":"Timber Lake Cir",
    "iso:country":"US",
    "sg:address":"226 Timber Lake Cir",
    "sg:city":"Douglasville",
    "sg:classifiers":[
        {
            "category":"Personal",
            "subcategory":"Beauty Salon",
            "type":"Services"
        }
    ],
    "sg:phone":"+1 770 942 9747",
    "sg:postcode":"30134",
    "sg:province":"GA",
    "sg:tags":[
        "shop",
        "fitness",
        "physical",
        "facility"
    ],
    "wof:name":"W Chastain & Co Inc",
    "wof:placetype":"venue"
},
  "geometry": {"coordinates":[-84.71740200000001,33.796229],"type":"Point"}
}