{
  "type": "Feature",
  "properties": {
    "addr:full":"4652 Peachtree Place Pkwy Apt E Atlanta GA 30360",
    "addr:housenumber":"4652",
    "addr:postcode":"30360",
    "addr:street":"Peachtree Place Pkwy Apt E",
    "iso:country":"US",
    "sg:address":"4652 Peachtree Place Pkwy Apt E",
    "sg:city":"Atlanta",
    "sg:classifiers":[
        {
            "category":"Real Estate",
            "subcategory":"Real Estate Operator",
            "type":"Services"
        }
    ],
    "sg:phone":"+1 770 582 2006",
    "sg:postcode":"30360",
    "sg:province":"GA",
    "sg:tags":[
        "apartment"
    ],
    "wof:name":"Peachtree Place North",
    "wof:placetype":"venue"
},
  "geometry": {"coordinates":[-84.26892700000001,33.933092],"type":"Point"}
}