{
  "type": "Feature",
  "properties": {
    "iso:country":"US",
    "sg:address":"205 Sweetwater Rd",
    "sg:city":"North Augusta",
    "sg:classifiers":[
        {
            "category":"Professional",
            "type":"Services"
        }
    ],
    "sg:phone":"+1 803 279 1661",
    "sg:postcode":"29860",
    "sg:province":"SC",
    "sg:tags":[
        "establishment"
    ],
    "wof:name":"Kindermorgan Southeast",
    "wof:placetype":"venue"
},
  "geometry": {"coordinates":[-81.952366,33.594234],"type":"Point"}
}