{
  "type": "Feature",
  "properties": {
    "addr:full":"356 5th St NE Atlanta GA 30308",
    "addr:housenumber":"356",
    "addr:postcode":"30308",
    "addr:street":"5Th St Ne",
    "iso:country":"US",
    "sg:address":"356 5th St NE",
    "sg:city":"Atlanta",
    "sg:classifiers":[
        {
            "category":"Social Services",
            "subcategory":"Child Care",
            "type":"Services"
        },
        {
            "category":"Professional",
            "subcategory":"Employment Agencies",
            "type":"Services"
        }
    ],
    "sg:phone":"+1 404 607 7709",
    "sg:postcode":"30308",
    "sg:province":"GA",
    "sg:tags":[
        "opportunity",
        "day"
    ],
    "wof:name":"Nanny Solutions",
    "wof:placetype":"venue"
},
  "geometry": {"coordinates":[-84.375686,33.775401],"type":"Point"}
}