{
  "type": "Feature",
  "properties": {
    "addr:full":"506 Gowen Dr Folkston GA 31537",
    "addr:housenumber":"506",
    "addr:postcode":"31537",
    "addr:street":"Gowen Dr",
    "iso:country":"US",
    "sg:address":"506 Gowen Dr",
    "sg:city":"Folkston",
    "sg:classifiers":[
        {
            "category":"Home & Garden",
            "subcategory":"Home Furnishings",
            "type":"Retail Goods"
        }
    ],
    "sg:phone":"+1 912 496 2202",
    "sg:postcode":"31537",
    "sg:province":"GA",
    "sg:tags":[
        "repair"
    ],
    "wof:name":"Furniture Facelift",
    "wof:placetype":"venue"
},
  "geometry": {"coordinates":[-82.01652799999999,30.824714],"type":"Point"}
}