{
  "type": "Feature",
  "properties": {
    "iso:country":"US",
    "sg:address":"540 Hemlock St",
    "sg:city":"Macon",
    "sg:classifiers":[
        {
            "category":"Health Services",
            "subcategory":"Doctor",
            "type":"Services"
        }
    ],
    "sg:phone":"+1 478 743 8953",
    "sg:postcode":"31201",
    "sg:province":"GA",
    "sg:tags":[
        "physician",
        "surgeon"
    ],
    "wof:name":"Allergy Clinic",
    "wof:placetype":"venue"
},
  "geometry": {"coordinates":[-83.632103,32.830393],"type":"Point"}
}