{
  "type": "Feature",
  "properties": {
    "iso:country":"US",
    "sg:address":"800 W Jackson St",
    "sg:city":"Thomasville",
    "sg:classifiers":[
        {
            "category":"Government",
            "subcategory":"Jail",
            "type":"Public Place"
        }
    ],
    "sg:phone":"+1 229 225 4025",
    "sg:postcode":"31792",
    "sg:province":"GA",
    "sg:tags":[
        "govt",
        "state",
        "institution"
    ],
    "wof:name":"Corrections Dept Diversion Ctr",
    "wof:placetype":"venue"
},
  "geometry": {"coordinates":[-83.98699499999999,30.828197],"type":"Point"}
}