{
  "type": "Feature",
  "properties": {
    "addr:full":"1701 Hudson Bridge Rd Stockbridge GA 30281",
    "addr:housenumber":"1701",
    "addr:postcode":"30281",
    "addr:street":"Hudson Bridge Rd",
    "iso:country":"US",
    "sg:address":"1701 Hudson Bridge Rd",
    "sg:city":"Stockbridge",
    "sg:classifiers":[
        {
            "category":"Professional",
            "subcategory":"Employment Agencies",
            "type":"Services"
        }
    ],
    "sg:phone":"+1 678 289 8282",
    "sg:postcode":"30281",
    "sg:province":"GA",
    "sg:tags":[
        "help",
        "contractor"
    ],
    "wof:name":"Futurestaff",
    "wof:placetype":"venue"
},
  "geometry": {"coordinates":[-84.243503,33.501491],"type":"Point"}
}