{
  "type": "Feature",
  "properties": {
    "iso:country":"US",
    "sg:address":"5065 Lawrenceville Hwy NW",
    "sg:city":"Lilburn",
    "sg:classifiers":[
        {
            "category":"Retail",
            "subcategory":"Pet Boarding",
            "type":"Services"
        }
    ],
    "sg:phone":"+1 770 921 5838",
    "sg:postcode":"30047",
    "sg:province":"GA",
    "sg:tags":[
        "boarding/pet",
        "sitting"
    ],
    "wof:name":"Dog Wash",
    "wof:placetype":"venue"
},
  "geometry": {"coordinates":[-84.14859800000001,33.889198],"type":"Point"}
}