{
  "type": "Feature",
  "properties": {
    "iso:country":"US",
    "sg:address":"2915 Pinehigh Ct NW",
    "sg:city":"Duluth",
    "sg:classifiers":[
        {
            "category":"Travel",
            "subcategory":"Travel Agent",
            "type":"Entertainment"
        }
    ],
    "sg:phone":"+1 770 447 4853",
    "sg:postcode":"30096",
    "sg:province":"GA",
    "sg:tags":[
        "operator",
        "tour"
    ],
    "wof:name":"International Tour N Travel",
    "wof:placetype":"venue"
},
  "geometry": {"coordinates":[-84.178731,33.959287],"type":"Point"}
}