{
  "type": "Feature",
  "properties": {
    "addr:full":"312 Magnolia Dr Thomson GA 30824",
    "addr:housenumber":"312",
    "addr:postcode":"30824",
    "addr:street":"Magnolia Dr",
    "iso:country":"US",
    "sg:address":"312 Magnolia Dr",
    "sg:city":"Thomson",
    "sg:classifiers":[
        {
            "category":"Personal",
            "subcategory":"Beauty Salon",
            "type":"Services"
        }
    ],
    "sg:phone":"+1 706 597 1100",
    "sg:postcode":"30824",
    "sg:province":"GA",
    "wof:name":"Its All Hair",
    "wof:placetype":"venue"
},
  "geometry": {"coordinates":[-82.508602,33.473621],"type":"Point"}
}