{
  "type": "Feature",
  "properties": {
    "iso:country":"US",
    "sg:address":"112 W 2nd Ave",
    "sg:city":"Rome",
    "sg:classifiers":[
        {
            "category":"Restaurant",
            "type":"Food & Drink"
        }
    ],
    "sg:phone":"+1 706 378 8700",
    "sg:postcode":"30161",
    "sg:province":"GA",
    "wof:name":"Waterfront Grill & Bar",
    "wof:placetype":"venue"
},
  "geometry": {"coordinates":[-85.17480399999999,34.25293],"type":"Point"}
}