{
  "type": "Feature",
  "properties": {
    "iso:country":"US",
    "sg:address":"3710 Woodyhill Dr",
    "sg:city":"Lithonia",
    "sg:classifiers":[
        {
            "category":"Retail",
            "subcategory":"Auto Repair",
            "type":"Services"
        }
    ],
    "sg:phone":"+1 770 593 9411",
    "sg:postcode":"30038",
    "sg:province":"GA",
    "sg:tags":[
        "automobile",
        "towing"
    ],
    "wof:name":"Grier Towing",
    "wof:placetype":"venue"
},
  "geometry": {"coordinates":[-84.20142199999999,33.66807],"type":"Point"}
}