{
  "type": "Feature",
  "properties": {
    "iso:country":"US",
    "sg:address":"1605 Camp Ln",
    "sg:city":"Albany",
    "sg:classifiers":[
        {
            "category":"Wholesale",
            "subcategory":"Machinery & Supplies",
            "type":"Manufacturing & Wholesale Goods"
        }
    ],
    "sg:phone":"+1 229 436 9415",
    "sg:postcode":"31707",
    "sg:province":"GA",
    "sg:tags":[
        "equipment",
        "industrial"
    ],
    "wof:name":"Valves & Controls",
    "wof:placetype":"venue"
},
  "geometry": {"coordinates":[-84.18868399999999,31.5769],"type":"Point"}
}