{
  "type": "Feature",
  "properties": {
    "addr:full":"8620 N Main St Helen GA 30545",
    "addr:housenumber":"8620",
    "addr:postcode":"30545",
    "addr:street":"N Main St",
    "iso:country":"US",
    "sg:address":"8620 N Main St",
    "sg:city":"Helen",
    "sg:classifiers":[
        {
            "category":"Shopping",
            "subcategory":"Clothing, Apparel, & Fashions",
            "type":"Retail Goods"
        },
        {
            "category":"Manufacturing",
            "subcategory":"Leather Goods",
            "type":"Manufacturing & Wholesale Goods"
        },
        {
            "category":"Shopping",
            "subcategory":"Luggage & Leather Goods",
            "type":"Retail Goods"
        }
    ],
    "sg:phone":"+1 706 878 3534",
    "sg:postcode":"30545",
    "sg:province":"GA",
    "sg:tags":[
        "apparel"
    ],
    "wof:name":"Das First Leather",
    "wof:placetype":"venue"
},
  "geometry": {"coordinates":[-83.73008799999999,34.701115],"type":"Point"}
}