{
  "type": "Feature",
  "properties": {
    "iso:country":"US",
    "sg:address":"305 Michael Cir",
    "sg:city":"Canton",
    "sg:classifiers":[
        {
            "category":"Wholesale",
            "subcategory":"Non-durable Goods",
            "type":"Manufacturing & Wholesale Goods"
        }
    ],
    "sg:phone":"+1 770 720 1567",
    "sg:postcode":"30114",
    "sg:province":"GA",
    "wof:name":"Fmj Export Corporation",
    "wof:placetype":"venue"
},
  "geometry": {"coordinates":[-84.560492,34.208555],"type":"Point"}
}