{
  "type": "Feature",
  "properties": {
    "iso:country":"US",
    "sg:address":"81 Waterford Rd",
    "sg:city":"Bremen",
    "sg:classifiers":[
        {
            "category":"Transit Center",
            "subcategory":"Freight",
            "type":"Transportation"
        },
        {
            "category":"Freight",
            "type":"Transportation"
        }
    ],
    "sg:phone":"+1 770 537 6847",
    "sg:postcode":"30110",
    "sg:province":"GA",
    "sg:tags":[
        "local",
        "trucking-motor",
        "trucking"
    ],
    "wof:name":"Properties Associates Inc",
    "wof:placetype":"venue"
},
  "geometry": {"coordinates":[-85.14863800000001,33.742013],"type":"Point"}
}