{
  "type": "Feature",
  "properties": {
    "iso:country":"US",
    "sg:address":"104 Honey Bear Dr",
    "sg:city":"Griffin",
    "sg:classifiers":[
        {
            "category":"Professional",
            "type":"Services"
        }
    ],
    "sg:phone":"+1 770 228 8438",
    "sg:postcode":"30223",
    "sg:province":"GA",
    "wof:name":"Kevin C Moore",
    "wof:placetype":"venue"
},
  "geometry": {"coordinates":[-84.34519,33.350565],"type":"Point"}
}