{
  "type": "Feature",
  "properties": {
    "addr:full":"3916 Forego Ct Marietta GA 30062",
    "addr:housenumber":"3916",
    "addr:postcode":"30062",
    "addr:street":"Forego Ct",
    "iso:country":"US",
    "sg:address":"3916 Forego Ct",
    "sg:city":"Marietta",
    "sg:classifiers":[
        {
            "category":"Building & Trades",
            "subcategory":"Locksmith",
            "type":"Services"
        }
    ],
    "sg:phone":"+1 888 328 9501",
    "sg:postcode":"30062",
    "sg:province":"GA",
    "sg:tags":[
        "key"
    ],
    "wof:name":"1 24 Hour Emergency Locksmith",
    "wof:placetype":"venue"
},
  "geometry": {"coordinates":[-84.438507,34.044969],"type":"Point"}
}