{
  "type": "Feature",
  "properties": {
    "addr:full":"3509 Canton Rd Marietta GA 30066",
    "addr:housenumber":"3509",
    "addr:postcode":"30066",
    "addr:street":"Canton Rd",
    "iso:country":"US",
    "sg:address":"3509 Canton Rd",
    "sg:city":"Marietta",
    "sg:classifiers":[
        {
            "category":"Insurance",
            "subcategory":"Insurance Agent",
            "type":"Services"
        }
    ],
    "sg:phone":"+1 770 926 4432",
    "sg:postcode":"30066",
    "sg:province":"GA",
    "sg:tags":[
        "agency"
    ],
    "sg:website":"www.filkinscolbert.com",
    "wof:name":"Filkins Colbert & Associates",
    "wof:placetype":"venue"
},
  "geometry": {"coordinates":[-84.52794900000001,34.036603],"type":"Point"}
}