{
  "type": "Feature",
  "properties": {
    "addr:full":"822 Fort Howard Rd Rincon GA 31326",
    "addr:housenumber":"822",
    "addr:postcode":"31326",
    "addr:street":"Fort Howard Rd",
    "iso:country":"US",
    "sg:address":"822 Fort Howard Rd",
    "sg:city":"Rincon",
    "sg:classifiers":[
        {
            "category":"Freight",
            "type":"Transportation"
        }
    ],
    "sg:phone":"+1 912 826 0069",
    "sg:postcode":"31326",
    "sg:province":"GA",
    "sg:tags":[
        "distance",
        "long",
        "trucking"
    ],
    "wof:name":"Randalls Transportation",
    "wof:placetype":"venue"
},
  "geometry": {"coordinates":[-81.20075199999999,32.313243],"type":"Point"}
}