{
  "type": "Feature",
  "properties": {
    "iso:country":"US",
    "sg:address":"13405 Rockingham Rd",
    "sg:city":"Savannah",
    "sg:classifiers":[
        {
            "category":"Real Estate",
            "subcategory":"Real Estate Operator",
            "type":"Services"
        }
    ],
    "sg:phone":"+1 912 920 2923",
    "sg:postcode":"31419",
    "sg:province":"GA",
    "sg:tags":[
        "building",
        "nonresidential"
    ],
    "wof:name":"Free Accpted Msons Lodge No 93",
    "wof:placetype":"venue"
},
  "geometry": {"coordinates":[-81.153913,31.963954],"type":"Point"}
}