{
  "type": "Feature",
  "properties": {
    "iso:country":"US",
    "sg:address":"973 Enota Ave NE",
    "sg:city":"Gainesville",
    "sg:classifiers":[
        {
            "category":"Insurance",
            "subcategory":"Insurance Agent",
            "type":"Services"
        }
    ],
    "sg:phone":"+1 770 297 5321",
    "sg:postcode":"30501",
    "sg:province":"GA",
    "sg:tags":[
        "adjuster"
    ],
    "wof:name":"Crawford & Co",
    "wof:placetype":"venue"
},
  "geometry": {"coordinates":[-83.83038999999999,34.320212],"type":"Point"}
}