{
  "type": "Feature",
  "properties": {
    "addr:full":"2033 Countydown Ln Stone Mountain GA 30088",
    "addr:housenumber":"2033",
    "addr:postcode":"30088",
    "addr:street":"Countydown Ln",
    "iso:country":"US",
    "sg:address":"2033 Countydown Ln",
    "sg:city":"Stone Mountain",
    "sg:classifiers":[
        {
            "category":"Bars & Pubs",
            "type":"Food & Drink"
        }
    ],
    "sg:phone":"+1 770 981 0566",
    "sg:postcode":"30088",
    "sg:province":"GA",
    "sg:tags":[
        "drinking"
    ],
    "wof:name":"Tap Source Investments LL",
    "wof:placetype":"venue"
},
  "geometry": {"coordinates":[-84.173249,33.728239],"type":"Point"}
}