{
  "type": "Feature",
  "properties": {
    "iso:country":"US",
    "sg:address":"1005 Reunion Pl SW",
    "sg:city":"Atlanta",
    "sg:classifiers":[
        {
            "category":"Professional",
            "subcategory":"Management & Consulting",
            "type":"Services"
        }
    ],
    "sg:phone":"+1 404 691 1184",
    "sg:postcode":"30331",
    "sg:province":"GA",
    "sg:tags":[
        "public",
        "relations"
    ],
    "wof:name":"S&R Sales & Promotions",
    "wof:placetype":"venue"
},
  "geometry": {"coordinates":[-84.527434,33.725571],"type":"Point"}
}