{
  "type": "Feature",
  "properties": {
    "iso:country":"US",
    "sg:address":"5002 N Royal Atlanta Dr",
    "sg:city":"Tucker",
    "sg:classifiers":[
        {
            "category":"Wholesale",
            "subcategory":"Medical Equipment & Supplies",
            "type":"Manufacturing & Wholesale Goods"
        }
    ],
    "sg:phone":"+1 770 270 5459",
    "sg:postcode":"30084",
    "sg:province":"GA",
    "sg:tags":[
        "physician",
        "surgeon",
        "care",
        "health",
        "home"
    ],
    "wof:name":"Surgicare Supplies Inc",
    "wof:placetype":"venue"
},
  "geometry": {"coordinates":[-84.184825,33.858437],"type":"Point"}
}