{
  "type": "Feature",
  "properties": {
    "iso:country":"US",
    "sg:address":"334 Rose Garden Ln",
    "sg:city":"Ellijay",
    "sg:classifiers":[
        {
            "category":"Building & Trades",
            "subcategory":"Electrical",
            "type":"Services"
        }
    ],
    "sg:phone":"+1 706 635 2520",
    "sg:postcode":"30540",
    "sg:province":"GA",
    "sg:tags":[
        "electrician"
    ],
    "wof:name":"Jj Electric",
    "wof:placetype":"venue"
},
  "geometry": {"coordinates":[-84.558464,34.653385],"type":"Point"}
}