{
  "type": "Feature",
  "properties": {
    "iso:country":"US",
    "sg:address":"2614 Atomic Rd",
    "sg:city":"Beech Island",
    "sg:classifiers":[
        {
            "category":"Home & Garden",
            "subcategory":"Mobile Homes",
            "type":"Retail Goods"
        }
    ],
    "sg:phone":"+1 803 827 1137",
    "sg:postcode":"29842",
    "sg:province":"SC",
    "sg:tags":[
        "operator",
        "site"
    ],
    "wof:name":"Longs Mobile Home Village",
    "wof:placetype":"venue"
},
  "geometry": {"coordinates":[-81.899794,33.466766],"type":"Point"}
}