{
  "type": "Feature",
  "properties": {
    "addr:full":"251 Indian Hills Ct Marietta GA 30068",
    "addr:housenumber":"251",
    "addr:postcode":"30068",
    "addr:street":"Indian Hills Ct",
    "iso:country":"US",
    "sg:address":"251 Indian Hills Ct",
    "sg:city":"Marietta",
    "sg:classifiers":[
        {
            "category":"Home & Garden",
            "subcategory":"Garden Supply",
            "type":"Retail Goods"
        }
    ],
    "sg:phone":"+1 770 971 7229",
    "sg:postcode":"30068",
    "sg:province":"GA",
    "sg:tags":[
        "center"
    ],
    "wof:name":"Source",
    "wof:placetype":"venue"
},
  "geometry": {"coordinates":[-84.444562,33.954545],"type":"Point"}
}