{
  "type": "Feature",
  "properties": {
    "iso:country":"US",
    "sg:address":"1205 Tift Ave N",
    "sg:city":"Tifton",
    "sg:classifiers":[
        {
            "category":"Government",
            "subcategory":"Office",
            "type":"Public Place"
        }
    ],
    "sg:phone":"+1 229 391 9281",
    "sg:postcode":"31794",
    "sg:province":"GA",
    "wof:name":"Tift County Adult Health Clnc",
    "wof:placetype":"venue"
},
  "geometry": {"coordinates":[-83.50280600000001,31.466173],"type":"Point"}
}