{
  "type": "Feature",
  "properties": {
    "iso:country":"US",
    "sg:address":"14110 Hwy 36",
    "sg:city":"Covington",
    "sg:classifiers":[
        {
            "category":"Education",
            "subcategory":"School",
            "type":"Public Place"
        }
    ],
    "sg:phone":"+1 770 784 2980",
    "sg:postcode":"30014",
    "sg:province":"GA",
    "sg:tags":[
        "elementary"
    ],
    "wof:name":"Heard-Mixon Elementary",
    "wof:placetype":"venue"
},
  "geometry": {"coordinates":[-83.847623,33.469741],"type":"Point"}
}