{
  "type": "Feature",
  "properties": {
    "iso:country":"US",
    "sg:address":"325 Ga Highway 49 W",
    "sg:city":"Milledgeville",
    "sg:classifiers":[
        {
            "category":"Place Of Worship",
            "subcategory":"Church",
            "type":"Public Place"
        },
        {
            "category":"Place Of Worship",
            "type":"Public Place"
        }
    ],
    "sg:phone":"+1 478 454 5489",
    "sg:postcode":"31061",
    "sg:province":"GA",
    "sg:tags":[
        "testament",
        "christ-new",
        "churches-church",
        "christ"
    ],
    "wof:name":"New Beginnings Church Of Christ",
    "wof:placetype":"venue"
},
  "geometry": {"coordinates":[-83.259135,33.070675],"type":"Point"}
}