{
  "type": "Feature",
  "properties": {
    "addr:full":"1138 Strath Clyde Way Mc Donough GA 30253",
    "addr:housenumber":"1138",
    "addr:postcode":"30253",
    "addr:street":"Strath Clyde Way",
    "iso:country":"US",
    "sg:address":"1138 Strath Clyde Way",
    "sg:city":"Mc Donough",
    "sg:classifiers":[
        {
            "category":"Organizations",
            "subcategory":"Community Association",
            "type":"Services"
        }
    ],
    "sg:phone":"+1 678 583 0054",
    "sg:postcode":"30253",
    "sg:province":"GA",
    "wof:name":"Carlyle Home Owners Asctn",
    "wof:placetype":"venue"
},
  "geometry": {"coordinates":[-84.174601,33.513898],"type":"Point"}
}