{
  "type": "Feature",
  "properties": {
    "iso:country":"US",
    "sg:address":"2090 N Druid Hills Rd NE",
    "sg:city":"Atlanta",
    "sg:classifiers":[
        {
            "category":"Social Services",
            "type":"Services"
        },
        {
            "category":"Place Of Worship",
            "subcategory":"Church",
            "type":"Public Place"
        },
        {
            "category":"Place Of Worship",
            "type":"Public Place"
        },
        {
            "category":"Shopping",
            "subcategory":"Thrift Store",
            "type":"Retail Goods"
        }
    ],
    "sg:phone":"+1 404 315 7499",
    "sg:postcode":"30329",
    "sg:province":"GA",
    "sg:tags":[
        "shop",
        "churches-salvation",
        "army"
    ],
    "sg:website":"http://www.salvationarmyusa.org/",
    "wof:name":"Salvation Army Family Store",
    "wof:placetype":"venue"
},
  "geometry": {"coordinates":[-84.337018,33.83271],"type":"Point"}
}