{
  "type": "Feature",
  "properties": {
    "iso:country":"US",
    "sg:address":"1004 E Gwinnett St",
    "sg:city":"Savannah",
    "sg:classifiers":[
        {
            "category":"Personal",
            "subcategory":"Beauty Salon",
            "type":"Services"
        }
    ],
    "sg:phone":"+1 912 232 2632",
    "sg:postcode":"31401",
    "sg:province":"GA",
    "wof:name":"M'Lady's Stylon",
    "wof:placetype":"venue"
},
  "geometry": {"coordinates":[-81.080085,32.063124],"type":"Point"}
}