{
  "type": "Feature",
  "properties": {
    "addr:full":"608 Moreland Ave Atlanta GA 30307",
    "addr:housenumber":"608",
    "addr:postcode":"30307",
    "addr:street":"Moreland Ave",
    "iso:country":"US",
    "sg:address":"608 Moreland Ave",
    "sg:city":"Atlanta",
    "sg:classifiers":[
        {
            "category":"Personal",
            "subcategory":"Massage",
            "type":"Services"
        }
    ],
    "sg:phone":"+1 404 577 8555",
    "sg:postcode":"30307",
    "sg:province":"GA",
    "sg:website":"www.TheSpaFlow.com",
    "wof:name":"Spa Flow Mobile Massage Therapy",
    "wof:placetype":"venue"
},
  "geometry": {"coordinates":[-84.349338,33.77094],"type":"Point"}
}