{
  "type": "Feature",
  "properties": {
    "addr:full":"6100 Coca Cola Blvd Columbus GA 31909",
    "addr:housenumber":"6100",
    "addr:postcode":"31909",
    "addr:street":"Coca Cola Blvd",
    "iso:country":"US",
    "sg:address":"6100 Coca Cola Blvd",
    "sg:city":"Columbus",
    "sg:classifiers":[
        {
            "category":"Manufacturing",
            "subcategory":"Signs",
            "type":"Manufacturing & Wholesale Goods"
        }
    ],
    "sg:phone":"+1 706 569 9952",
    "sg:postcode":"31909",
    "sg:province":"GA",
    "sg:website":"www.signsinc.net",
    "wof:name":"Signs Inc",
    "wof:placetype":"venue"
},
  "geometry": {"coordinates":[-84.887039,32.532129],"type":"Point"}
}