{
  "type": "Feature",
  "properties": {
    "iso:country":"US",
    "sg:address":"1011 N Ashley St",
    "sg:city":"Valdosta",
    "sg:classifiers":[
        {
            "category":"Autos & Motor Vehicles",
            "subcategory":"Motorcycle Sales",
            "type":"Retail Goods"
        }
    ],
    "sg:phone":"+1 229 244 9910",
    "sg:postcode":"31601",
    "sg:province":"GA",
    "sg:tags":[
        "scooter"
    ],
    "wof:name":"Southern Cycles Inc",
    "wof:placetype":"venue"
},
  "geometry": {"coordinates":[-83.280148,30.843414],"type":"Point"}
}