{
  "type": "Feature",
  "properties": {
    "addr:full":"2424 Roswell Rd Marietta GA 30062",
    "addr:housenumber":"2424",
    "addr:postcode":"30062",
    "addr:street":"Roswell Rd",
    "iso:country":"US",
    "sg:address":"2424 Roswell Rd",
    "sg:city":"Marietta",
    "sg:classifiers":[
        {
            "category":"Restaurant",
            "type":"Food & Drink"
        }
    ],
    "sg:menulink":"http://www.allmenus.com/ga/marietta/124292-quiznos-sub/menu/",
    "sg:phone":"+1 770 565 8788",
    "sg:postcode":"30062",
    "sg:province":"GA",
    "sg:tags":[
        "wrap",
        "american",
        "sandwich"
    ],
    "wof:name":"Quiznos Sub",
    "wof:placetype":"venue"
},
  "geometry": {"coordinates":[-84.4808,33.973748],"type":"Point"}
}