{
  "type": "Feature",
  "properties": {
    "addr:full":"113 Grandmar Chase Canton GA 30115",
    "addr:housenumber":"113",
    "addr:postcode":"30115",
    "addr:street":"Grandmar Chase",
    "iso:country":"US",
    "sg:address":"113 Grandmar Chase",
    "sg:city":"Canton",
    "sg:classifiers":[
        {
            "category":"Food & Beverages",
            "subcategory":"Specialty",
            "type":"Retail Goods"
        }
    ],
    "sg:phone":"+1 770 740 2939",
    "sg:postcode":"30115",
    "sg:province":"GA",
    "wof:name":"Brian J Lunsford",
    "wof:placetype":"venue"
},
  "geometry": {"coordinates":[-84.35413200000001,34.234334],"type":"Point"}
}