{
  "type": "Feature",
  "properties": {
    "iso:country":"US",
    "sg:address":"2720 Klondike Rd SW",
    "sg:city":"Conyers",
    "sg:classifiers":[
        {
            "category":"Building & Trades",
            "subcategory":"Construction",
            "type":"Services"
        }
    ],
    "sg:phone":"+1 770 483 5757",
    "sg:postcode":"30094",
    "sg:province":"GA",
    "sg:tags":[
        "heavy"
    ],
    "wof:name":"Greenleaf Contracting",
    "wof:placetype":"venue"
},
  "geometry": {"coordinates":[-84.078053,33.658272],"type":"Point"}
}