{
  "type": "Feature",
  "properties": {
    "iso:country":"US",
    "sg:address":"20 S College St Ste A",
    "sg:city":"Homerville",
    "sg:classifiers":[
        {
            "category":"Government",
            "subcategory":"City Hall",
            "type":"Public Place"
        },
        {
            "category":"Utilities",
            "subcategory":"Water",
            "type":"Services"
        },
        {
            "category":"Government",
            "subcategory":"Office",
            "type":"Public Place"
        }
    ],
    "sg:phone":"+1 912 487 2375",
    "sg:postcode":"31634",
    "sg:province":"GA",
    "sg:tags":[
        "town",
        "company-utility",
        "planner",
        "supply",
        "system",
        "village",
        "township",
        "government-city"
    ],
    "wof:name":"City Of Homerville",
    "wof:placetype":"venue"
},
  "geometry": {"coordinates":[-82.750359,31.034499],"type":"Point"}
}