{
  "type": "Feature",
  "properties": {
    "addr:full":"521 W Solomon St Griffin GA 30223",
    "addr:housenumber":"521",
    "addr:postcode":"30223",
    "addr:street":"W Solomon St",
    "iso:country":"US",
    "sg:address":"521 W Solomon St",
    "sg:city":"Griffin",
    "sg:classifiers":[
        {
            "category":"Personal",
            "subcategory":"Beauty Salon",
            "type":"Services"
        }
    ],
    "sg:phone":"+1 770 227 8033",
    "sg:postcode":"30223",
    "sg:province":"GA",
    "sg:tags":[
        "shop"
    ],
    "wof:name":"Conncepts",
    "wof:placetype":"venue"
},
  "geometry": {"coordinates":[-84.271595,33.248873],"type":"Point"}
}