{
  "type": "Feature",
  "properties": {
    "addr:full":"500 9th St Columbus GA 31901",
    "addr:housenumber":"500",
    "addr:postcode":"31901",
    "addr:street":"9Th St",
    "iso:country":"US",
    "sg:address":"500 9th St",
    "sg:city":"Columbus",
    "sg:classifiers":[
        {
            "category":"Shopping",
            "subcategory":"Florist",
            "type":"Retail Goods"
        }
    ],
    "sg:phone":"+1 706 322 0107",
    "sg:postcode":"31901",
    "sg:province":"GA",
    "wof:name":"Sconiers Florist",
    "wof:placetype":"venue"
},
  "geometry": {"coordinates":[-84.984792,32.462835],"type":"Point"}
}