{
  "type": "Feature",
  "properties": {
    "addr:full":"110 Campbell St Thomasville GA 31792",
    "addr:housenumber":"110",
    "addr:postcode":"31792",
    "addr:street":"Campbell St",
    "iso:country":"US",
    "sg:address":"110 Campbell St",
    "sg:city":"Thomasville",
    "sg:classifiers":[
        {
            "category":"Building & Trades",
            "subcategory":"Construction",
            "type":"Services"
        }
    ],
    "sg:phone":"+1 229 228 0171",
    "sg:postcode":"31792",
    "sg:province":"GA",
    "sg:tags":[
        "roof",
        "structure"
    ],
    "wof:name":"Roof Trusses & Lumber",
    "wof:placetype":"venue"
},
  "geometry": {"coordinates":[-83.98692,30.832414],"type":"Point"}
}