{
  "type": "Feature",
  "properties": {
    "addr:full":"5498 Mt. Vernon Way Atlanta GA 30338",
    "addr:housenumber":"5498",
    "addr:postcode":"30338",
    "addr:street":"Mt. Vernon Way",
    "iso:country":"US",
    "sg:address":"5498 Mt. Vernon Way",
    "sg:city":"Atlanta",
    "sg:classifiers":[
        {
            "category":"Real Estate",
            "subcategory":"Real Estate Services",
            "type":"Services"
        }
    ],
    "sg:phone":"+1 404 313 5000",
    "sg:postcode":"30338",
    "sg:province":"GA",
    "sg:tags":[
        "home",
        "inspector",
        "inspection"
    ],
    "sg:website":"gghomeinspections.com/",
    "wof:name":"Double G Home Inspections",
    "wof:placetype":"venue"
},
  "geometry": {"coordinates":[-84.324988,33.96192],"type":"Point"}
}