{
  "type": "Feature",
  "properties": {
    "addr:full":"711 S Columbia Dr Decatur GA 30030",
    "addr:housenumber":"711",
    "addr:postcode":"30030",
    "addr:street":"S Columbia Dr",
    "iso:country":"US",
    "sg:address":"711 S Columbia Dr",
    "sg:city":"Decatur",
    "sg:classifiers":[
        {
            "category":"Organizations",
            "subcategory":"Non-profit Organization",
            "type":"Services"
        }
    ],
    "sg:phone":"+1 404 378 0938",
    "sg:postcode":"30030",
    "sg:province":"GA",
    "sg:website":"www.ourhousega.com",
    "wof:name":"Our House Inc",
    "wof:placetype":"venue"
},
  "geometry": {"coordinates":[-84.27883199999999,33.763149],"type":"Point"}
}