{
  "type": "Feature",
  "properties": {
    "iso:country":"US",
    "sg:address":"504 Vienna St",
    "sg:city":"Fort Valley",
    "sg:classifiers":[
        {
            "category":"Utilities",
            "subcategory":"Water",
            "type":"Services"
        }
    ],
    "sg:phone":"+1 478 825 7001",
    "sg:postcode":"31030",
    "sg:province":"GA",
    "sg:tags":[
        "supply"
    ],
    "wof:name":"Fort Valley Utility Plant",
    "wof:placetype":"venue"
},
  "geometry": {"coordinates":[-83.875224,32.5581],"type":"Point"}
}