{
  "type": "Feature",
  "properties": {
    "iso:country":"US",
    "sg:address":"2176 Highpoint Rd",
    "sg:city":"Snellville",
    "sg:classifiers":[
        {
            "category":"Professional",
            "subcategory":"Accounting & Tax Preparation",
            "type":"Services"
        }
    ],
    "sg:phone":"+1 770 979 3031",
    "sg:postcode":"30078",
    "sg:province":"GA",
    "sg:tags":[
        "bookkeeping",
        "general"
    ],
    "wof:name":"Programmed Accounting Svc",
    "wof:placetype":"venue"
},
  "geometry": {"coordinates":[-84.041467,33.849205],"type":"Point"}
}