{
  "type": "Feature",
  "properties": {
    "addr:full":"1173 S Hairston Rd Stone Mountain GA 30088",
    "addr:housenumber":"1173",
    "addr:postcode":"30088",
    "addr:street":"S Hairston Rd",
    "iso:country":"US",
    "sg:address":"1173 S Hairston Rd",
    "sg:city":"Stone Mountain",
    "sg:classifiers":[
        {
            "category":"Personal",
            "subcategory":"Nail Salon",
            "type":"Services"
        }
    ],
    "sg:phone":"+1 404 292 1514",
    "sg:postcode":"30088",
    "sg:province":"GA",
    "wof:name":"Best Nails",
    "wof:placetype":"venue"
},
  "geometry": {"coordinates":[-84.19650300000001,33.761799],"type":"Point"}
}