{
  "type": "Feature",
  "properties": {
    "iso:country":"US",
    "sg:address":"2034 Metropolitan Pkwy SW",
    "sg:city":"Atlanta",
    "sg:classifiers":[
        {
            "category":"Social Services",
            "type":"Services"
        }
    ],
    "sg:phone":"+1 404 761 1266",
    "sg:postcode":"30310",
    "sg:province":"GA",
    "sg:tags":[
        "organization",
        "welfare"
    ],
    "wof:name":"NAACP",
    "wof:placetype":"venue"
},
  "geometry": {"coordinates":[-84.408018,33.698349],"type":"Point"}
}