{
  "type": "Feature",
  "properties": {
    "iso:country":"US",
    "sg:address":"1775 Woodstock Rd",
    "sg:city":"Roswell",
    "sg:classifiers":[
        {
            "category":"Building & Trades",
            "subcategory":"Construction",
            "type":"Services"
        }
    ],
    "sg:phone":"+1 770 650 3939",
    "sg:postcode":"30075",
    "sg:province":"GA",
    "sg:tags":[
        "general",
        "commercial",
        "contractor"
    ],
    "wof:name":"Bowen Construction Services",
    "wof:placetype":"venue"
},
  "geometry": {"coordinates":[-84.414699,34.060351],"type":"Point"}
}