{
  "type": "Feature",
  "properties": {
    "iso:country":"US",
    "sg:address":"2383 Glynn Dr SE",
    "sg:city":"Atlanta",
    "sg:classifiers":[
        {
            "category":"Shopping",
            "subcategory":"Florist",
            "type":"Retail Goods"
        }
    ],
    "sg:phone":"+1 404 688 8801",
    "sg:postcode":"30316",
    "sg:province":"GA",
    "sg:tags":[
        "flower"
    ],
    "wof:name":"Park East Flowers Inc",
    "wof:placetype":"venue"
},
  "geometry": {"coordinates":[-84.337596,33.719659],"type":"Point"}
}