{
  "type": "Feature",
  "properties": {
    "addr:full":"4376 Lilburn Industrial Way SW Lilburn GA 30047",
    "addr:postcode":"4376;30047",
    "addr:street":"Industrial Way Sw",
    "iso:country":"US",
    "sg:address":"4376 Lilburn Industrial Way SW",
    "sg:city":"Lilburn",
    "sg:classifiers":[
        {
            "category":"Professional",
            "subcategory":"Accounting & Tax Preparation",
            "type":"Services"
        }
    ],
    "sg:phone":"+1 770 931 4070",
    "sg:postcode":"30047",
    "sg:province":"GA",
    "sg:tags":[
        "return",
        "filing"
    ],
    "wof:name":"Hewitt Hyperformance",
    "wof:placetype":"venue"
},
  "geometry": {"coordinates":[-84.120108,33.89315],"type":"Point"}
}