{
  "type": "Feature",
  "properties": {
    "addr:full":"3380 Town Point Pkwy NW Kennesaw GA 30144",
    "addr:housenumber":"3380",
    "addr:postcode":"30144",
    "addr:street":"Town Point Pkwy Nw",
    "iso:country":"US",
    "sg:address":"3380 Town Point Pkwy NW",
    "sg:city":"Kennesaw",
    "sg:classifiers":[
        {
            "category":"Professional",
            "subcategory":"Management & Consulting",
            "type":"Services"
        }
    ],
    "sg:phone":"+1 770 919 0969",
    "sg:postcode":"30144",
    "sg:province":"GA",
    "sg:tags":[
        "soil",
        "engineering"
    ],
    "wof:name":"S & M E Inc",
    "wof:placetype":"venue"
},
  "geometry": {"coordinates":[-84.58037899999999,34.031351],"type":"Point"}
}