{
  "type": "Feature",
  "properties": {
    "addr:full":"2905 Lonesome Rd Albany GA 31721",
    "addr:housenumber":"2905",
    "addr:postcode":"31721",
    "addr:street":"Lonesome Rd",
    "iso:country":"US",
    "sg:address":"2905 Lonesome Rd",
    "sg:city":"Albany",
    "sg:classifiers":[
        {
            "category":"Professional",
            "subcategory":"Accounting & Tax Preparation",
            "type":"Services"
        }
    ],
    "sg:phone":"+1 229 436 5430",
    "sg:postcode":"31721",
    "sg:province":"GA",
    "wof:name":"T and W Accounting",
    "wof:placetype":"venue"
},
  "geometry": {"coordinates":[-84.231781,31.494586],"type":"Point"}
}