{
  "type": "Feature",
  "properties": {
    "addr:full":"4725 S Atlanta Rd SE Smyrna GA 30080",
    "addr:housenumber":"4725",
    "addr:postcode":"30080",
    "addr:street":"S Atlanta Rd Se",
    "iso:country":"US",
    "sg:address":"4725 S Atlanta Rd SE",
    "sg:city":"Smyrna",
    "sg:classifiers":[
        {
            "category":"Food & Beverages",
            "subcategory":"Groceries & Convenience Stores",
            "type":"Retail Goods"
        }
    ],
    "sg:phone":"+1 404 799 3366",
    "sg:postcode":"30080",
    "sg:province":"GA",
    "wof:name":"Texaco Food Mart",
    "wof:placetype":"venue"
},
  "geometry": {"coordinates":[-84.484398,33.839901],"type":"Point"}
}