{
  "type": "Feature",
  "properties": {
    "addr:full":"40 Grace Dr SE Rome GA 30161",
    "addr:housenumber":"40",
    "addr:postcode":"ga 30161",
    "addr:street":"Grace Dr Se",
    "iso:country":"US",
    "sg:address":"40 Grace Dr SE",
    "sg:city":"Rome",
    "sg:classifiers":[
        {
            "category":"Travel",
            "subcategory":"Hotels & Motels",
            "type":"Entertainment"
        },
        {
            "category":"Travel",
            "subcategory":"Bed & Breakfast",
            "type":"Entertainment"
        }
    ],
    "sg:phone":"+1 706 291 7797",
    "sg:postcode":"30161",
    "sg:province":"GA",
    "sg:tags":[
        "inn",
        "lodging"
    ],
    "sg:website":"http://www.pmghotels.com",
    "wof:name":"Jameson Inn Rome",
    "wof:placetype":"venue"
},
  "geometry": {"coordinates":[-85.149306,34.223313],"type":"Point"}
}