{
  "type": "Feature",
  "properties": {
    "addr:full":"999 Baxter St Athens GA 30606",
    "addr:housenumber":"999",
    "addr:postcode":"30606",
    "addr:street":"Baxter St",
    "iso:country":"US",
    "sg:address":"999 Baxter St",
    "sg:city":"Athens",
    "sg:classifiers":[
        {
            "category":"Real Estate",
            "subcategory":"Real Estate Agent",
            "type":"Services"
        }
    ],
    "sg:phone":"+1 706 353 0090",
    "sg:postcode":"30606",
    "sg:province":"GA",
    "sg:tags":[
        "appraiser"
    ],
    "wof:name":"Carter Appraisal Svc",
    "wof:placetype":"venue"
},
  "geometry": {"coordinates":[-83.389009,33.948882],"type":"Point"}
}