{
  "type": "Feature",
  "properties": {
    "addr:full":"4037 Lawrenceville Hwy Tucker GA 30084",
    "addr:housenumber":"4037",
    "addr:postcode":"30084",
    "addr:street":"Lawrenceville Hwy",
    "iso:country":"US",
    "sg:address":"4037 Lawrenceville Hwy",
    "sg:city":"Tucker",
    "sg:classifiers":[
        {
            "category":"Building & Trades",
            "subcategory":"Locksmith",
            "type":"Services"
        }
    ],
    "sg:phone":"+1 678 269 7143",
    "sg:postcode":"30084",
    "sg:province":"GA",
    "sg:tags":[
        "key"
    ],
    "wof:name":"7 Days Emergency Locksmith",
    "wof:placetype":"venue"
},
  "geometry": {"coordinates":[-84.216567,33.849974],"type":"Point"}
}