{
  "type": "Feature",
  "properties": {
    "addr:full":"1831 Travers Cir Lawrenceville GA 30044",
    "addr:housenumber":"1831",
    "addr:postcode":"30044",
    "addr:street":"Travers Cir",
    "iso:country":"US",
    "sg:address":"1831 Travers Cir",
    "sg:city":"Lawrenceville",
    "sg:classifiers":[
        {
            "category":"Local Transit",
            "type":"Transportation"
        }
    ],
    "sg:phone":"+1 770 616 5184",
    "sg:postcode":"30044",
    "sg:province":"GA",
    "sg:tags":[
        "limousine"
    ],
    "wof:name":"First Class Limousine",
    "wof:placetype":"venue"
},
  "geometry": {"coordinates":[-84.037683,33.921717],"type":"Point"}
}