{
  "type": "Feature",
  "properties": {
    "addr:full":"834 High Green Ct Grovetown GA 30813",
    "addr:housenumber":"834",
    "addr:postcode":"30813",
    "addr:street":"High Green Ct",
    "iso:country":"US",
    "sg:address":"834 High Green Ct",
    "sg:city":"Grovetown",
    "sg:classifiers":[
        {
            "category":"Shopping",
            "type":"Retail Goods"
        }
    ],
    "sg:phone":"+1 706 399 9627",
    "sg:postcode":"30813",
    "sg:province":"GA",
    "sg:tags":[
        "merchandise"
    ],
    "wof:name":"Jennifer Mancilla",
    "wof:placetype":"venue"
},
  "geometry": {"coordinates":[-82.22951999999999,33.461396],"type":"Point"}
}