{
  "type": "Feature",
  "properties": {
    "addr:full":"4270 Lavista Rd Tucker GA 30084",
    "addr:housenumber":"4270",
    "addr:postcode":"30084",
    "addr:street":"Lavista Rd",
    "iso:country":"US",
    "sg:address":"4270 Lavista Rd",
    "sg:city":"Tucker",
    "sg:classifiers":[
        {
            "category":"Restaurant",
            "type":"Food & Drink"
        }
    ],
    "sg:menulink":"http://www.allmenus.com/ga/tucker/163343-rallys/menu/",
    "sg:phone":"+1 770 491 1461",
    "sg:postcode":"30084",
    "sg:province":"GA",
    "sg:tags":[
        "sandwich",
        "dog",
        "burger",
        "hot",
        "wrap",
        "american"
    ],
    "wof:name":"Rally's",
    "wof:placetype":"venue"
},
  "geometry": {"coordinates":[-84.24428899999999,33.847417],"type":"Point"}
}