{
  "type": "Feature",
  "properties": {
    "iso:country":"US",
    "sg:address":"320 Fairview Rd",
    "sg:city":"Ellenwood",
    "sg:classifiers":[
        {
            "category":"Autos & Motor Vehicles",
            "subcategory":"Fuel & Gas Station",
            "type":"Retail Goods"
        }
    ],
    "sg:phone":"+1 678 565 0071",
    "sg:postcode":"30294",
    "sg:province":"GA",
    "sg:tags":[
        "oil"
    ],
    "wof:name":"Chevron Food Mart",
    "wof:placetype":"venue"
},
  "geometry": {"coordinates":[-84.246787,33.61872],"type":"Point"}
}