{
  "type": "Feature",
  "properties": {
    "iso:country":"US",
    "sg:address":"3036 Marietta Hwy",
    "sg:city":"Canton",
    "sg:classifiers":[
        {
            "category":"Autos & Motor Vehicles",
            "subcategory":"Fuel & Gas Station",
            "type":"Retail Goods"
        }
    ],
    "sg:phone":"+1 770 479 8373",
    "sg:postcode":"30114",
    "sg:province":"GA",
    "sg:tags":[
        "oil"
    ],
    "wof:name":"Chevron Gas & Food",
    "wof:placetype":"venue"
},
  "geometry": {"coordinates":[-84.50598599999999,34.206452],"type":"Point"}
}