{
  "type": "Feature",
  "properties": {
    "addr:full":"202 E 4th St Woodbine GA 31569",
    "addr:housenumber":"202",
    "addr:postcode":"31569",
    "addr:street":"E 4Th St",
    "iso:country":"US",
    "sg:address":"202 E 4th St",
    "sg:city":"Woodbine",
    "sg:classifiers":[
        {
            "category":"Government",
            "subcategory":"Office",
            "type":"Public Place"
        }
    ],
    "sg:phone":"+1 912 576 5624",
    "sg:postcode":"31569",
    "sg:province":"GA",
    "sg:tags":[
        "county"
    ],
    "wof:name":"Camden County Clerk Of Court",
    "wof:placetype":"venue"
},
  "geometry": {"coordinates":[-81.72134800000001,30.968024],"type":"Point"}
}