{
  "type": "Feature",
  "properties": {
    "addr:full":"1700 Tree Ln Snellville GA 30078",
    "addr:housenumber":"1700",
    "addr:postcode":"30078",
    "addr:street":"Tree Ln",
    "iso:country":"US",
    "sg:address":"1700 Tree Ln",
    "sg:city":"Snellville",
    "sg:classifiers":[
        {
            "category":"Health Services",
            "subcategory":"Doctor",
            "type":"Services"
        }
    ],
    "sg:phone":"+1 770 979 4700",
    "sg:postcode":"30078",
    "sg:province":"GA",
    "sg:tags":[
        "physician",
        "gynecology",
        "surgeons",
        "obstetrics",
        "surgeon"
    ],
    "wof:name":"Women's Group Of Gwinnett",
    "wof:placetype":"venue"
},
  "geometry": {"coordinates":[-84.029764,33.883121],"type":"Point"}
}