{
  "type": "Feature",
  "properties": {
    "addr:full":"2556 Springdale Rd SW Atlanta GA 30315",
    "addr:housenumber":"2556",
    "addr:postcode":"30315",
    "addr:street":"Springdale Rd Sw",
    "iso:country":"US",
    "sg:address":"2556 Springdale Rd SW",
    "sg:city":"Atlanta",
    "sg:classifiers":[
        {
            "category":"Building & Trades",
            "subcategory":"Plumbing",
            "type":"Services"
        }
    ],
    "sg:phone":"+1 404 767 6446",
    "sg:postcode":"30315",
    "sg:province":"GA",
    "sg:tags":[
        "tank",
        "system",
        "septic"
    ],
    "wof:name":"Anderson Ed & Son",
    "wof:placetype":"venue"
},
  "geometry": {"coordinates":[-84.41536600000001,33.685168],"type":"Point"}
}