{
  "type": "Feature",
  "properties": {
    "iso:country":"US",
    "sg:address":"2590 Hamilton Mill Rd",
    "sg:city":"Buford",
    "sg:classifiers":[
        {
            "category":"Restaurant",
            "type":"Food & Drink"
        }
    ],
    "sg:phone":"+1 678 394 5200",
    "sg:postcode":"30519",
    "sg:province":"GA",
    "sg:tags":[
        "mexican"
    ],
    "sg:website":"molcajetemexicanrestaurant.com",
    "wof:name":"El Molcajete Mexican Restaurant",
    "wof:placetype":"venue"
},
  "geometry": {"coordinates":[-83.91824800000001,34.078785],"type":"Point"}
}