{
  "type": "Feature",
  "properties": {
    "iso:country":"US",
    "sg:address":"1601 Lester Rd NW",
    "sg:city":"Conyers",
    "sg:classifiers":[
        {
            "category":"Building & Trades",
            "subcategory":"Construction",
            "type":"Services"
        }
    ],
    "sg:phone":"+1 678 413 1616",
    "sg:postcode":"30012",
    "sg:province":"GA",
    "sg:tags":[
        "general",
        "nonresidential",
        "contractor"
    ],
    "wof:name":"Global International Co",
    "wof:placetype":"venue"
},
  "geometry": {"coordinates":[-84.05301300000001,33.690598],"type":"Point"}
}