{
  "type": "Feature",
  "properties": {
    "addr:full":"1921 Bull St Savannah GA 31401",
    "addr:housenumber":"1921",
    "addr:postcode":"31401",
    "addr:street":"Bull St",
    "iso:country":"US",
    "sg:address":"1921 Bull St",
    "sg:city":"Savannah",
    "sg:classifiers":[
        {
            "category":"Real Estate",
            "subcategory":"Real Estate Operator",
            "type":"Services"
        }
    ],
    "sg:phone":"+1 912 234 7303",
    "sg:postcode":"31401",
    "sg:province":"GA",
    "sg:tags":[
        "dwelling",
        "eating"
    ],
    "wof:name":"Gingerbread House",
    "wof:placetype":"venue"
},
  "geometry": {"coordinates":[-81.09994399999999,32.058215],"type":"Point"}
}