{
  "type": "Feature",
  "properties": {
    "addr:full":"840 Ernest W Barrett Pkwy Kennesaw GA 30144",
    "addr:housenumber":"840",
    "addr:postcode":"30144",
    "addr:street":"Ernest W Barrett Pkwy",
    "iso:country":"US",
    "sg:address":"840 Ernest W Barrett Pkwy",
    "sg:city":"Kennesaw",
    "sg:classifiers":[
        {
            "category":"Communications",
            "type":"Services"
        }
    ],
    "sg:phone":"+1 770 420 9214",
    "sg:postcode":"30144",
    "sg:province":"GA",
    "wof:name":"Prime Communications",
    "wof:placetype":"venue"
},
  "geometry": {"coordinates":[-84.576549,34.004973],"type":"Point"}
}