{
  "type": "Feature",
  "properties": {
    "addr:full":"63 Owens Dr Midway GA 31320",
    "addr:housenumber":"63",
    "addr:postcode":"31320",
    "addr:street":"Owens Dr",
    "iso:country":"US",
    "sg:address":"63 Owens Dr",
    "sg:city":"Midway",
    "sg:classifiers":[
        {
            "category":"Building & Trades",
            "subcategory":"Construction",
            "type":"Services"
        }
    ],
    "sg:phone":"+1 912 884 7585",
    "sg:postcode":"31320",
    "sg:province":"GA",
    "sg:tags":[
        "carpenter"
    ],
    "wof:name":"Midway Carpentry",
    "wof:placetype":"venue"
},
  "geometry": {"coordinates":[-81.39757299999999,31.835432],"type":"Point"}
}