{
  "type": "Feature",
  "properties": {
    "iso:country":"US",
    "sg:address":"201 E Broad Ave",
    "sg:city":"Albany",
    "sg:classifiers":[
        {
            "category":"Manufacturing",
            "subcategory":"Metals",
            "type":"Manufacturing & Wholesale Goods"
        },
        {
            "category":"Building & Trades",
            "subcategory":"Construction",
            "type":"Services"
        }
    ],
    "sg:phone":"+1 229 432 7147",
    "sg:postcode":"31705",
    "sg:province":"GA",
    "sg:tags":[
        "shop",
        "repair",
        "who",
        "fabricated",
        "fabricator",
        "welding",
        "structural"
    ],
    "wof:name":"Hambric Welding Inc",
    "wof:placetype":"venue"
},
  "geometry": {"coordinates":[-84.144198,31.576846],"type":"Point"}
}