{
  "type": "Feature",
  "properties": {
    "addr:full":"2755 Bankers Industrial Dr Atlanta GA 30360",
    "addr:housenumber":"2755",
    "addr:postcode":"30360",
    "addr:street":"Bankers Industrial Dr",
    "iso:country":"US",
    "sg:address":"2755 Bankers Industrial Dr",
    "sg:city":"Atlanta",
    "sg:classifiers":[
        {
            "category":"Professional",
            "subcategory":"Engineering",
            "type":"Services"
        }
    ],
    "sg:phone":"+1 770 209 9680",
    "sg:postcode":"30360",
    "sg:province":"GA",
    "sg:tags":[
        "electrical",
        "electronic",
        "engineer"
    ],
    "sg:website":"www.venture-eng.com",
    "wof:name":"Venture Engineering Corp Inc",
    "wof:placetype":"venue"
},
  "geometry": {"coordinates":[-84.26312,33.924556],"type":"Point"}
}