{
  "type": "Feature",
  "properties": {
    "addr:full":"511 N Jefferson St Dublin GA 31021",
    "addr:housenumber":"511",
    "addr:postcode":"31021",
    "addr:street":"N Jefferson St",
    "iso:country":"US",
    "sg:address":"511 N Jefferson St",
    "sg:city":"Dublin",
    "sg:classifiers":[
        {
            "category":"Autos & Motor Vehicles",
            "subcategory":"Automobile Sales",
            "type":"Retail Goods"
        }
    ],
    "sg:phone":"+1 478 275 2010",
    "sg:postcode":"31021",
    "sg:province":"GA",
    "sg:tags":[
        "new",
        "used",
        "car"
    ],
    "wof:name":"Dublin Auto Sales",
    "wof:placetype":"venue"
},
  "geometry": {"coordinates":[-82.901392,32.534736],"type":"Point"}
}