{
  "type": "Feature",
  "properties": {
    "iso:country":"US",
    "sg:address":"345 N Belair Rd",
    "sg:city":"Evans",
    "sg:classifiers":[
        {
            "category":"Health Services",
            "subcategory":"Doctor",
            "type":"Services"
        }
    ],
    "sg:phone":"+1 706 650 2285",
    "sg:postcode":"30809",
    "sg:province":"GA",
    "wof:name":"Belair Dental Assoc",
    "wof:placetype":"venue"
},
  "geometry": {"coordinates":[-82.13880899999999,33.525355],"type":"Point"}
}