{
  "type": "Feature",
  "properties": {
    "addr:full":"6470 Elsie St Douglasville GA 30134",
    "addr:housenumber":"6470",
    "addr:postcode":"30134",
    "addr:street":"Elsie St",
    "iso:country":"US",
    "sg:address":"6470 Elsie St",
    "sg:city":"Douglasville",
    "sg:classifiers":[
        {
            "category":"Building & Trades",
            "subcategory":"Construction",
            "type":"Services"
        }
    ],
    "sg:phone":"+1 770 942 0222",
    "sg:postcode":"30134",
    "sg:province":"GA",
    "sg:tags":[
        "contractor"
    ],
    "wof:name":"Willie Almond Construction",
    "wof:placetype":"venue"
},
  "geometry": {"coordinates":[-84.742949,33.759664],"type":"Point"}
}