{
  "type": "Feature",
  "properties": {
    "iso:country":"US",
    "sg:address":"1259 Russell Pkwy",
    "sg:city":"Warner Robins",
    "sg:classifiers":[
        {
            "category":"Professional",
            "type":"Services"
        }
    ],
    "sg:phone":"+1 478 975 9288",
    "sg:postcode":"31088",
    "sg:province":"GA",
    "wof:name":"Rivers & Co LLC",
    "wof:placetype":"venue"
},
  "geometry": {"coordinates":[-83.65092,32.594066],"type":"Point"}
}