{
  "type": "Feature",
  "properties": {
    "addr:full":"717 Connell Rd Moultrie GA 31788",
    "addr:housenumber":"717",
    "addr:postcode":"31788",
    "addr:street":"Connell Rd",
    "iso:country":"US",
    "sg:address":"717 Connell Rd",
    "sg:city":"Moultrie",
    "sg:classifiers":[
        {
            "category":"Building & Trades",
            "subcategory":"Cleaning & Sanitation",
            "type":"Services"
        }
    ],
    "sg:phone":"+1 229 324 3333",
    "sg:postcode":"31788",
    "sg:province":"GA",
    "sg:tags":[
        "maintenance"
    ],
    "wof:name":"West & Sons",
    "wof:placetype":"venue"
},
  "geometry": {"coordinates":[-83.702915,31.088252],"type":"Point"}
}