{
  "type": "Feature",
  "properties": {
    "iso:country":"US",
    "sg:address":"4603 Ruby Rd",
    "sg:city":"Stone Mountain",
    "sg:classifiers":[
        {
            "category":"Building & Trades",
            "subcategory":"Plumbing",
            "type":"Services"
        }
    ],
    "sg:phone":"+1 404 296 3729",
    "sg:postcode":"30083",
    "sg:province":"GA",
    "wof:name":"Stone Mountain Plumbing",
    "wof:placetype":"venue"
},
  "geometry": {"coordinates":[-84.201694,33.773675],"type":"Point"}
}