{
  "type": "Feature",
  "properties": {
    "iso:country":"US",
    "sg:address":"6053 Oakbrook Pkwy",
    "sg:city":"Norcross",
    "sg:classifiers":[
        {
            "category":"Shopping",
            "subcategory":"Clothing, Apparel, & Fashions",
            "type":"Retail Goods"
        }
    ],
    "sg:phone":"+1 770 441 0156",
    "sg:postcode":"30093",
    "sg:province":"GA",
    "sg:tags":[
        "work",
        "embroidery",
        "uniform"
    ],
    "wof:name":"Mindys Embroidery & Uniforms",
    "wof:placetype":"venue"
},
  "geometry": {"coordinates":[-84.204522,33.911386],"type":"Point"}
}