{
  "type": "Feature",
  "properties": {
    "iso:country":"US",
    "sg:address":"135 E Montgomery St",
    "sg:city":"Villa Rica",
    "sg:classifiers":[
        {
            "category":"Real Estate",
            "subcategory":"Real Estate Agent",
            "type":"Services"
        }
    ],
    "sg:phone":"+1 770 456 9444",
    "sg:postcode":"30180",
    "sg:province":"GA",
    "sg:website":"www.321fast.com",
    "wof:name":"Fastrack",
    "wof:placetype":"venue"
},
  "geometry": {"coordinates":[-84.91698100000001,33.729615],"type":"Point"}
}