{
  "type": "Feature",
  "properties": {
    "iso:country":"US",
    "sg:address":"6141 Johnson Rd",
    "sg:city":"Riverdale",
    "sg:classifiers":[
        {
            "category":"Building & Trades",
            "subcategory":"Landscaping Services",
            "type":"Services"
        }
    ],
    "sg:phone":"+1 770 256 6482",
    "sg:postcode":"30274",
    "sg:province":"GA",
    "sg:tags":[
        "lawn",
        "maintenance",
        "grounds"
    ],
    "wof:name":"Brooks Lawn Care",
    "wof:placetype":"venue"
},
  "geometry": {"coordinates":[-84.401369,33.584568],"type":"Point"}
}