{
  "type": "Feature",
  "properties": {
    "addr:full":"1906 N Woods Dr Marietta GA 30066",
    "addr:housenumber":"1906",
    "addr:postcode":"30066",
    "addr:street":"N Woods Dr",
    "iso:country":"US",
    "sg:address":"1906 N Woods Dr",
    "sg:city":"Marietta",
    "sg:classifiers":[
        {
            "category":"Professional",
            "subcategory":"Computer Services",
            "type":"Services"
        }
    ],
    "sg:phone":"+1 678 445 9297",
    "sg:postcode":"30066",
    "sg:province":"GA",
    "sg:tags":[
        "development",
        "software"
    ],
    "wof:name":"Endres Consulting Inc",
    "wof:placetype":"venue"
},
  "geometry": {"coordinates":[-84.49115,34.045605],"type":"Point"}
}