{
  "type": "Feature",
  "properties": {
    "iso:country":"US",
    "sg:address":"100 N 4th St",
    "sg:city":"Midway",
    "sg:classifiers":[
        {
            "category":"Education",
            "subcategory":"Special Training",
            "type":"Public Place"
        }
    ],
    "sg:phone":"+1 912 441 9043",
    "sg:postcode":"31320",
    "sg:province":"GA",
    "sg:tags":[
        "educational"
    ],
    "wof:name":"Systems Resources Inc",
    "wof:placetype":"venue"
},
  "geometry": {"coordinates":[-81.354889,31.81089],"type":"Point"}
}