{
  "type": "Feature",
  "properties": {
    "addr:full":"135 Toledo St Brunswick GA 31525",
    "addr:housenumber":"135",
    "addr:postcode":"31525",
    "addr:street":"Toledo St",
    "iso:country":"US",
    "sg:address":"135 Toledo St",
    "sg:city":"Brunswick",
    "sg:classifiers":[
        {
            "category":"Professional",
            "type":"Services"
        }
    ],
    "sg:phone":"+1 912 267 1381",
    "sg:postcode":"31525",
    "sg:province":"GA",
    "wof:name":"Stevedon Inc",
    "wof:placetype":"venue"
},
  "geometry": {"coordinates":[-81.491525,31.224518],"type":"Point"}
}