{
  "type": "Feature",
  "properties": {
    "iso:country":"US",
    "sg:address":"609 38th St",
    "sg:city":"Columbus",
    "sg:classifiers":[
        {
            "category":"Building & Trades",
            "subcategory":"Electrical",
            "type":"Services"
        }
    ],
    "sg:phone":"+1 706 324 0394",
    "sg:postcode":"31904",
    "sg:province":"GA",
    "sg:tags":[
        "electric",
        "contractor"
    ],
    "wof:name":"Davis Electric Co",
    "wof:placetype":"venue"
},
  "geometry": {"coordinates":[-84.984208,32.498927],"type":"Point"}
}