{
  "type": "Feature",
  "properties": {
    "iso:country":"US",
    "sg:address":"5925 Coca Cola Blvd",
    "sg:city":"Columbus",
    "sg:classifiers":[
        {
            "category":"Shopping",
            "subcategory":"Discount & Variety Stores",
            "type":"Retail Goods"
        },
        {
            "category":"Professional",
            "subcategory":"Management & Consulting",
            "type":"Services"
        }
    ],
    "sg:phone":"+1 706 651 9632",
    "sg:postcode":"31909",
    "sg:province":"GA",
    "sg:tags":[
        "merchandise",
        "general"
    ],
    "wof:name":"Merchandising Solutions LLC",
    "wof:placetype":"venue"
},
  "geometry": {"coordinates":[-84.887202,32.52902],"type":"Point"}
}