{
  "type": "Feature",
  "properties": {
    "iso:country":"US",
    "sg:address":"1569 Montreal Cir",
    "sg:city":"Tucker",
    "sg:classifiers":[
        {
            "category":"Restaurant",
            "type":"Food & Drink"
        }
    ],
    "sg:menulink":"http://www.allmenus.com/ga/tucker/106338-waffle-house/menu/",
    "sg:phone":"+1 770 938 6093",
    "sg:postcode":"30084",
    "sg:province":"GA",
    "sg:tags":[
        "american"
    ],
    "wof:name":"Waffle House",
    "wof:placetype":"venue"
},
  "geometry": {"coordinates":[-84.254389,33.827041],"type":"Point"}
}