{
  "type": "Feature",
  "properties": {
    "iso:country":"US",
    "sg:address":"714 US Hwy 84",
    "sg:city":"Cairo",
    "sg:classifiers":[
        {
            "category":"Food & Beverages",
            "subcategory":"Bakery",
            "type":"Retail Goods"
        }
    ],
    "sg:phone":"+1 229 377 9566",
    "sg:postcode":"39828",
    "sg:province":"GA",
    "sg:tags":[
        "baker"
    ],
    "wof:name":"Deb's Donuts",
    "wof:placetype":"venue"
},
  "geometry": {"coordinates":[-84.198294,30.880825],"type":"Point"}
}