{
  "type": "Feature",
  "properties": {
    "addr:full":"3557 W Hampton Dr Marietta GA 30064",
    "addr:housenumber":"3557",
    "addr:postcode":"30064",
    "addr:street":"W Hampton Dr",
    "iso:country":"US",
    "sg:address":"3557 W Hampton Dr",
    "sg:city":"Marietta",
    "sg:classifiers":[
        {
            "category":"Building & Trades",
            "subcategory":"Construction",
            "type":"Services"
        }
    ],
    "sg:phone":"+1 678 313 0382",
    "sg:postcode":"30064",
    "sg:province":"GA",
    "sg:tags":[
        "contractor"
    ],
    "wof:name":"P & D Properties",
    "wof:placetype":"venue"
},
  "geometry": {"coordinates":[-84.65618600000001,33.959949],"type":"Point"}
}