{
  "type": "Feature",
  "properties": {
    "addr:full":"116 Palmetto Rd Tyrone GA 30290",
    "addr:housenumber":"116",
    "addr:postcode":"30290",
    "addr:street":"Palmetto Rd",
    "iso:country":"US",
    "sg:address":"116 Palmetto Rd",
    "sg:city":"Tyrone",
    "sg:classifiers":[
        {
            "category":"Arena",
            "subcategory":"Sports Club",
            "type":"Entertainment"
        }
    ],
    "sg:phone":"+1 770 486 5363",
    "sg:postcode":"30290",
    "sg:province":"GA",
    "sg:tags":[
        "martial art"
    ],
    "wof:name":"Ippon Judo & Jujitsu",
    "wof:placetype":"venue"
},
  "geometry": {"coordinates":[-84.611997,33.492001],"type":"Point"}
}