{
  "type": "Feature",
  "properties": {
    "iso:country":"US",
    "sg:address":"1359 Rupert Rd Apt B",
    "sg:city":"Decatur",
    "sg:classifiers":[
        {
            "category":"Building & Trades",
            "subcategory":"Construction",
            "type":"Services"
        }
    ],
    "sg:phone":"+1 678 508 8141",
    "sg:postcode":"30030",
    "sg:province":"GA",
    "sg:tags":[
        "excavation",
        "contractor"
    ],
    "wof:name":"Earth Works Contracting",
    "wof:placetype":"venue"
},
  "geometry": {"coordinates":[-84.274598,33.753298],"type":"Point"}
}