{
  "type": "Feature",
  "properties": {
    "addr:full":"412 Ga Highway 247 S Bonaire GA 31005",
    "addr:housenumber":"412",
    "addr:postcode":"31005",
    "addr:street":"Ga Highway 247 S",
    "iso:country":"US",
    "sg:address":"412 Ga Highway 247 S",
    "sg:city":"Bonaire",
    "sg:classifiers":[
        {
            "category":"Building & Trades",
            "subcategory":"Electrical",
            "type":"Services"
        }
    ],
    "sg:phone":"+1 478 329 1211",
    "sg:postcode":"31005",
    "sg:province":"GA",
    "sg:tags":[
        "electrician"
    ],
    "wof:name":"Aes",
    "wof:placetype":"venue"
},
  "geometry": {"coordinates":[-83.59512100000001,32.566817],"type":"Point"}
}