{
  "type": "Feature",
  "properties": {
    "addr:full":"1604 Rocky Springs Rd Eastman GA 31023",
    "addr:housenumber":"1604",
    "addr:postcode":"31023",
    "addr:street":"Rocky Springs Rd",
    "iso:country":"US",
    "sg:address":"1604 Rocky Springs Rd",
    "sg:city":"Eastman",
    "sg:classifiers":[
        {
            "category":"Professional",
            "type":"Services"
        }
    ],
    "sg:phone":"+1 478 374 5265",
    "sg:postcode":"31023",
    "sg:province":"GA",
    "wof:name":"Spires/Kevin",
    "wof:placetype":"venue"
},
  "geometry": {"coordinates":[-83.24024900000001,32.155167],"type":"Point"}
}