{
  "type": "Feature",
  "properties": {
    "iso:country":"US",
    "sg:address":"1176 S Enota Dr NE",
    "sg:city":"Gainesville",
    "sg:classifiers":[
        {
            "category":"Home & Garden",
            "subcategory":"Household Appliances",
            "type":"Retail Goods"
        },
        {
            "category":"Wholesale",
            "subcategory":"Electrical",
            "type":"Manufacturing & Wholesale Goods"
        },
        {
            "category":"Professional",
            "subcategory":"Engineering",
            "type":"Services"
        }
    ],
    "sg:phone":"+1 770 534 5088",
    "sg:postcode":"30501",
    "sg:province":"GA",
    "sg:tags":[
        "purifying",
        "system",
        "systems-wholesale",
        "equipment",
        "manufacturer",
        "air conditioning",
        "cleaning"
    ],
    "wof:name":"Airsource 3000",
    "wof:placetype":"venue"
},
  "geometry": {"coordinates":[-83.821163,34.322697],"type":"Point"}
}