{
  "type": "Feature",
  "properties": {
    "iso:country":"US",
    "sg:address":"8018 Rockbridge Rd",
    "sg:city":"Lithonia",
    "sg:classifiers":[
        {
            "category":"Professional",
            "subcategory":"Business Services",
            "type":"Services"
        },
        {
            "category":"Wholesale",
            "subcategory":"Home Furnishings",
            "type":"Manufacturing & Wholesale Goods"
        }
    ],
    "sg:phone":"+1 770 484 7855",
    "sg:postcode":"30058",
    "sg:province":"GA",
    "sg:tags":[
        "interior",
        "consultant",
        "design",
        "decorator"
    ],
    "wof:name":"Domestic Designs",
    "wof:placetype":"venue"
},
  "geometry": {"coordinates":[-84.073601,33.774899],"type":"Point"}
}