{
  "type": "Feature",
  "properties": {
    "addr:full":"515 Brook Cir Roswell GA 30075",
    "addr:housenumber":"515",
    "addr:postcode":"30075",
    "addr:street":"Brook Cir",
    "iso:country":"US",
    "sg:address":"515 Brook Cir",
    "sg:city":"Roswell",
    "sg:classifiers":[
        {
            "category":"Professional",
            "subcategory":"Management & Consulting",
            "type":"Services"
        }
    ],
    "sg:phone":"+1 770 752 8111",
    "sg:postcode":"30075",
    "sg:province":"GA",
    "sg:tags":[
        "business"
    ],
    "wof:name":"Tzl Consulting Inc",
    "wof:placetype":"venue"
},
  "geometry": {"coordinates":[-84.364436,34.087032],"type":"Point"}
}