{
  "type": "Feature",
  "properties": {
    "addr:full":"4401 Montgomery St Savannah GA 31405",
    "addr:housenumber":"4401",
    "addr:postcode":"31405",
    "addr:street":"Montgomery St",
    "iso:country":"US",
    "sg:address":"4401 Montgomery St",
    "sg:city":"Savannah",
    "sg:classifiers":[
        {
            "category":"Travel",
            "subcategory":"Travel Agent",
            "type":"Entertainment"
        }
    ],
    "sg:phone":"+1 912 233 3896",
    "sg:postcode":"31405",
    "sg:province":"GA",
    "sg:tags":[
        "tours",
        "promoter"
    ],
    "wof:name":"Ghost Talk Ghost Walk Tours",
    "wof:placetype":"venue"
},
  "geometry": {"coordinates":[-81.111329,32.039966],"type":"Point"}
}