{
  "type": "Feature",
  "properties": {
    "iso:country":"US",
    "sg:address":"508 N Lakeshore Dr",
    "sg:city":"Carrollton",
    "sg:classifiers":[
        {
            "category":"Building & Trades",
            "subcategory":"Landscaping Services",
            "type":"Services"
        }
    ],
    "sg:phone":"+1 770 834 1137",
    "sg:postcode":"30117",
    "sg:province":"GA",
    "sg:tags":[
        "designer",
        "landscape"
    ],
    "wof:name":"Threadgill & Assoc LLC",
    "wof:placetype":"venue"
},
  "geometry": {"coordinates":[-85.057698,33.598072],"type":"Point"}
}