{
  "type": "Feature",
  "properties": {
    "iso:country":"US",
    "sg:address":"1224 1st St SE",
    "sg:city":"Moultrie",
    "sg:classifiers":[
        {
            "category":"Professional",
            "subcategory":"Advertising",
            "type":"Services"
        }
    ],
    "sg:phone":"+1 229 891 3894",
    "sg:postcode":"31768",
    "sg:province":"GA",
    "sg:tags":[
        "company"
    ],
    "wof:name":"Alpha Advertising Co",
    "wof:placetype":"venue"
},
  "geometry": {"coordinates":[-83.787689,31.16445],"type":"Point"}
}