{
  "type": "Feature",
  "properties": {
    "addr:full":"1501 Highway 19 N Thomaston GA 30286",
    "addr:housenumber":"1501",
    "addr:postcode":"30286",
    "addr:street":"Highway 19 N",
    "iso:country":"US",
    "sg:address":"1501 Highway 19 N",
    "sg:city":"Thomaston",
    "sg:classifiers":[
        {
            "category":"Food & Beverages",
            "subcategory":"Supermarket",
            "type":"Retail Goods"
        },
        {
            "category":"Food & Beverages",
            "subcategory":"Groceries & Convenience Stores",
            "type":"Retail Goods"
        }
    ],
    "sg:phone":"+1 706 648 4267",
    "sg:postcode":"30286",
    "sg:province":"GA",
    "sg:tags":[
        "super"
    ],
    "wof:name":"Flash Foods, Inc.",
    "wof:placetype":"venue"
},
  "geometry": {"coordinates":[-84.333984,32.934772],"type":"Point"}
}