{
  "type": "Feature",
  "properties": {
    "iso:country":"US",
    "sg:address":"10930 Crabapple Rd",
    "sg:city":"Roswell",
    "sg:classifiers":[
        {
            "category":"Restaurant",
            "type":"Food & Drink"
        }
    ],
    "sg:menulink":"http://www.allmenus.com/ga/roswell-alpharetta/55139-tijuana-flats/menu/",
    "sg:phone":"+1 770 594 7701",
    "sg:postcode":"30075",
    "sg:province":"GA",
    "sg:tags":[
        "mexican"
    ],
    "wof:name":"Tijuana Flats",
    "wof:placetype":"venue"
},
  "geometry": {"coordinates":[-84.361221,34.04584],"type":"Point"}
}