{
  "type": "Feature",
  "properties": {
    "iso:country":"US",
    "sg:address":"4809 Neville Way",
    "sg:city":"Marietta",
    "sg:classifiers":[
        {
            "category":"Recreation",
            "type":"Entertainment"
        }
    ],
    "sg:phone":"+1 770 592 9707",
    "sg:postcode":"30066",
    "sg:province":"GA",
    "sg:tags":[
        "bingo",
        "caller"
    ],
    "wof:name":"Mary Arowood",
    "wof:placetype":"venue"
},
  "geometry": {"coordinates":[-84.516733,34.070382],"type":"Point"}
}