{
  "type": "Feature",
  "properties": {
    "addr:full":"85 Darcee Ct Lawrenceville GA 30045",
    "addr:housenumber":"85",
    "addr:postcode":"30045",
    "addr:street":"Darcee Ct",
    "iso:country":"US",
    "sg:address":"85 Darcee Ct",
    "sg:city":"Lawrenceville",
    "sg:classifiers":[
        {
            "category":"Professional",
            "subcategory":"Management & Consulting",
            "type":"Services"
        }
    ],
    "sg:phone":"+1 770 513 7008",
    "sg:postcode":"30045",
    "sg:province":"GA",
    "sg:tags":[
        "business"
    ],
    "wof:name":"Harvard Inc",
    "wof:placetype":"venue"
},
  "geometry": {"coordinates":[-84.008838,33.942451],"type":"Point"}
}