{
  "type": "Feature",
  "properties": {
    "addr:full":"4324 Roswell Dr Augusta GA 30907",
    "addr:housenumber":"4324",
    "addr:postcode":"30907",
    "addr:street":"Roswell Dr",
    "iso:country":"US",
    "sg:address":"4324 Roswell Dr",
    "sg:city":"Augusta",
    "sg:classifiers":[
        {
            "category":"Building & Trades",
            "subcategory":"Landscaping Services",
            "type":"Services"
        }
    ],
    "sg:phone":"+1 706 284 2670",
    "sg:postcode":"30907",
    "sg:province":"GA",
    "wof:name":"A Perfect Landscape",
    "wof:placetype":"venue"
},
  "geometry": {"coordinates":[-82.12684,33.517074],"type":"Point"}
}