{
  "type": "Feature",
  "properties": {
    "iso:country":"US",
    "sg:address":"4770 Misty Lake Ct",
    "sg:city":"Kennesaw",
    "sg:classifiers":[
        {
            "category":"Professional",
            "subcategory":"Engineering",
            "type":"Services"
        }
    ],
    "sg:phone":"+1 770 924 0196",
    "sg:postcode":"30144",
    "sg:province":"GA",
    "sg:tags":[
        "equipment",
        "mfg",
        "re"
    ],
    "wof:name":"Flexible Engineering Resources",
    "wof:placetype":"venue"
},
  "geometry": {"coordinates":[-84.54847100000001,34.067857],"type":"Point"}
}