{
  "type": "Feature",
  "properties": {
    "iso:country":"US",
    "sg:address":"565 Camp Perrin Rd",
    "sg:city":"Lawrenceville",
    "sg:classifiers":[
        {
            "category":"Building & Trades",
            "subcategory":"Construction",
            "type":"Services"
        },
        {
            "category":"Retail",
            "subcategory":"Auto Repair",
            "type":"Services"
        }
    ],
    "sg:phone":"+1 678 377 2851",
    "sg:postcode":"30043",
    "sg:province":"GA",
    "sg:tags":[
        "body",
        "maker",
        "cabinet"
    ],
    "wof:name":"Carpenter's Custom Trim Inc",
    "wof:placetype":"venue"
},
  "geometry": {"coordinates":[-84.00473599999999,34.013847],"type":"Point"}
}