{
  "type": "Feature",
  "properties": {
    "iso:country":"US",
    "sg:address":"2016 Metropolitan Pkwy SW",
    "sg:city":"Atlanta",
    "sg:classifiers":[
        {
            "category":"Retail",
            "subcategory":"Auto Repair",
            "type":"Services"
        }
    ],
    "sg:phone":"+1 404 766 3242",
    "sg:postcode":"30310",
    "sg:province":"GA",
    "sg:tags":[
        "general"
    ],
    "wof:name":"Tucker Auto Electric Inc",
    "wof:placetype":"venue"
},
  "geometry": {"coordinates":[-84.408006,33.700161],"type":"Point"}
}