{
  "type": "Feature",
  "properties": {
    "addr:full":"861 Holcomb Bridge Rd Roswell GA 30076",
    "addr:housenumber":"861",
    "addr:postcode":"30076",
    "addr:street":"Holcomb Bridge Rd",
    "iso:country":"US",
    "sg:address":"861 Holcomb Bridge Rd",
    "sg:city":"Roswell",
    "sg:classifiers":[
        {
            "category":"Wholesale",
            "subcategory":"Durable Goods & Equipment",
            "type":"Manufacturing & Wholesale Goods"
        }
    ],
    "sg:phone":"+1 770 587 3789",
    "sg:postcode":"30076",
    "sg:province":"GA",
    "sg:tags":[
        "importer"
    ],
    "wof:name":"A B Imports Inc",
    "wof:placetype":"venue"
},
  "geometry": {"coordinates":[-84.33789299999999,34.030716],"type":"Point"}
}