{
  "type": "Feature",
  "properties": {
    "iso:country":"US",
    "sg:address":"5445 Fairington Rd",
    "sg:city":"Lithonia",
    "sg:classifiers":[
        {
            "category":"Shopping",
            "subcategory":"Shoes",
            "type":"Retail Goods"
        }
    ],
    "sg:phone":"+1 770 987 9853",
    "sg:postcode":"30038",
    "sg:province":"GA",
    "sg:tags":[
        "store"
    ],
    "sg:website":"www.payless.com",
    "wof:name":"Payless Shoe Store",
    "wof:placetype":"venue"
},
  "geometry": {"coordinates":[-84.16429599999999,33.70278],"type":"Point"}
}