{
  "type": "Feature",
  "properties": {
    "iso:country":"US",
    "sg:address":"750 Quarterpath Ln",
    "sg:city":"Alpharetta",
    "sg:classifiers":[
        {
            "category":"Professional",
            "type":"Services"
        }
    ],
    "sg:phone":"+1 770 569 2433",
    "sg:postcode":"30004",
    "sg:province":"GA",
    "wof:name":"Ashton Court of Rochester Inc",
    "wof:placetype":"venue"
},
  "geometry": {"coordinates":[-84.318378,34.141872],"type":"Point"}
}