{
  "type": "Feature",
  "properties": {
    "iso:country":"US",
    "sg:address":"445 Floyd Rd",
    "sg:city":"Hampton",
    "sg:classifiers":[
        {
            "category":"Building & Trades",
            "subcategory":"Construction",
            "type":"Services"
        }
    ],
    "sg:phone":"+1 770 707 0140",
    "sg:postcode":"30228",
    "sg:province":"GA",
    "sg:tags":[
        "waterproofing",
        "contractor"
    ],
    "wof:name":"Wms Waterproofing Inc",
    "wof:placetype":"venue"
},
  "geometry": {"coordinates":[-84.2804,33.363254],"type":"Point"}
}