{
  "type": "Feature",
  "properties": {
    "iso:country":"US",
    "sg:address":"921 E Currahee St",
    "sg:city":"Toccoa",
    "sg:classifiers":[
        {
            "category":"Shopping",
            "subcategory":"Pharmacy",
            "type":"Retail Goods"
        }
    ],
    "sg:phone":"+1 706 886 1118",
    "sg:postcode":"30577",
    "sg:province":"GA",
    "wof:name":"Medi Home Care",
    "wof:placetype":"venue"
},
  "geometry": {"coordinates":[-83.31247399999999,34.576901],"type":"Point"}
}