{
  "type": "Feature",
  "properties": {
    "addr:full":"214 Cherokee Rd Thomaston GA 30286",
    "addr:housenumber":"214",
    "addr:postcode":"30286",
    "addr:street":"Cherokee Rd",
    "iso:country":"US",
    "sg:address":"214 Cherokee Rd",
    "sg:city":"Thomaston",
    "sg:classifiers":[
        {
            "category":"Health Services",
            "subcategory":"Doctor",
            "type":"Services"
        }
    ],
    "sg:phone":"+1 706 647 9627",
    "sg:postcode":"30286",
    "sg:province":"GA",
    "sg:tags":[
        "medical"
    ],
    "wof:name":"Smith Venture Partners Lllp",
    "wof:placetype":"venue"
},
  "geometry": {"coordinates":[-84.33762,32.886064],"type":"Point"}
}