{
  "type": "Feature",
  "properties": {
    "addr:full":"45 Rainey Lake Rd Felton GA 30113",
    "addr:housenumber":"45",
    "addr:postcode":"30113",
    "addr:street":"Rainey Lake Rd",
    "iso:country":"US",
    "sg:address":"45 Rainey Lake Rd",
    "sg:city":"Felton",
    "sg:classifiers":[
        {
            "category":"Building & Trades",
            "subcategory":"Electrical",
            "type":"Services"
        }
    ],
    "sg:phone":"+1 770 646 8738",
    "sg:postcode":"30113",
    "sg:province":"GA",
    "sg:tags":[
        "electrical",
        "contractor"
    ],
    "wof:name":"Holtzclaw Maintenance",
    "wof:placetype":"venue"
},
  "geometry": {"coordinates":[-85.207904,33.888396],"type":"Point"}
}