{
  "type": "Feature",
  "properties": {
    "addr:full":"4175 Atlanta Hwy Bogart GA 30622",
    "addr:housenumber":"4175",
    "addr:postcode":"30622",
    "addr:street":"Atlanta Hwy Bogart",
    "iso:country":"US",
    "sg:address":"4175 Atlanta Hwy",
    "sg:city":"Bogart",
    "sg:classifiers":[
        {
            "category":"Home & Garden",
            "subcategory":"Building Materials",
            "type":"Retail Goods"
        }
    ],
    "sg:phone":"+1 706 369 0800",
    "sg:postcode":"30622",
    "sg:province":"GA",
    "sg:tags":[
        "lumber"
    ],
    "wof:name":"Southern Surplus Inc",
    "wof:placetype":"venue"
},
  "geometry": {"coordinates":[-83.48045500000001,33.940399],"type":"Point"}
}