{
  "type": "Feature",
  "properties": {
    "addr:full":"71 Arbor Hills Ter Talking Rock GA 30175",
    "addr:housenumber":"71",
    "addr:postcode":"30175",
    "addr:street":"Arbor Hills Ter",
    "iso:country":"US",
    "sg:address":"71 Arbor Hills Ter",
    "sg:city":"Talking Rock",
    "sg:classifiers":[
        {
            "category":"Autos & Motor Vehicles",
            "subcategory":"Motorcycle Sales",
            "type":"Retail Goods"
        }
    ],
    "sg:phone":"+1 706 253 7259",
    "sg:postcode":"30175",
    "sg:province":"GA",
    "sg:tags":[
        "scooter"
    ],
    "wof:name":"Mountain City Trikes",
    "wof:placetype":"venue"
},
  "geometry": {"coordinates":[-84.452732,34.490416],"type":"Point"}
}