{
  "type": "Feature",
  "properties": {
    "iso:country":"US",
    "sg:address":"11 Gable Ct Brunswick",
    "sg:city":"Brunswick",
    "sg:classifiers":[
        {
            "category":"Social Services",
            "subcategory":"Adult Care",
            "type":"Services"
        }
    ],
    "sg:phone":"+1 912 466 5870",
    "sg:postcode":"31525",
    "sg:province":"GA",
    "sg:tags":[
        "nurses-home"
    ],
    "wof:name":"Community Care Center",
    "wof:placetype":"venue"
},
  "geometry": {"coordinates":[-81.49942799999999,31.238154],"type":"Point"}
}