{
  "type": "Feature",
  "properties": {
    "iso:country":"US",
    "sg:address":"211 Ave C",
    "sg:city":"Carrollton",
    "sg:classifiers":[
        {
            "category":"Wholesale",
            "subcategory":"Chemicals & Plastics",
            "type":"Manufacturing & Wholesale Goods"
        }
    ],
    "sg:phone":"+1 770 834 6218",
    "sg:postcode":"30117",
    "sg:province":"GA",
    "wof:name":"E & C Chemicals Inc",
    "wof:placetype":"venue"
},
  "geometry": {"coordinates":[-85.098035,33.581728],"type":"Point"}
}