{
  "type": "Feature",
  "properties": {
    "iso:country":"US",
    "sg:address":"7096 Shenandoah Trl",
    "sg:city":"Austell",
    "sg:classifiers":[
        {
            "category":"Cinema",
            "subcategory":"Movie Theater",
            "type":"Entertainment"
        }
    ],
    "sg:phone":"+1 404 771 0226",
    "sg:postcode":"30168",
    "sg:province":"GA",
    "sg:tags":[
        "theatrical",
        "consultant"
    ],
    "wof:name":"Fantasy Productions",
    "wof:placetype":"venue"
},
  "geometry": {"coordinates":[-84.56482800000001,33.784139],"type":"Point"}
}