{
  "type": "Feature",
  "properties": {
    "addr:full":"179 Green St E Pelham GA 31779",
    "addr:housenumber":"179",
    "addr:postcode":"31779",
    "addr:street":"Green St E",
    "iso:country":"US",
    "sg:address":"179 Green St E",
    "sg:city":"Pelham",
    "sg:phone":"+1 229 294 6112",
    "sg:postcode":"31779",
    "sg:province":"GA",
    "sg:tags":[
        "farm"
    ],
    "wof:name":"Duze Enterprises",
    "wof:placetype":"venue"
},
  "geometry": {"coordinates":[-84.14956100000001,31.127536],"type":"Point"}
}