{
  "type": "Feature",
  "properties": {
    "iso:country":"US",
    "sg:address":"3489 Oak Leaf Ct",
    "sg:city":"Rex",
    "sg:classifiers":[
        {
            "category":"Education",
            "subcategory":"Special Training",
            "type":"Public Place"
        }
    ],
    "sg:phone":"+1 770 507 9073",
    "sg:postcode":"30273",
    "sg:province":"GA",
    "wof:name":"Sandras Continuing Education",
    "wof:placetype":"venue"
},
  "geometry": {"coordinates":[-84.277072,33.560605],"type":"Point"}
}