{
  "type": "Feature",
  "properties": {
    "iso:country":"US",
    "sg:address":"1621 Jones Chapel Shiloh Rd",
    "sg:city":"Danielsville",
    "sg:classifiers":[
        {
            "category":"Building & Trades",
            "subcategory":"Construction",
            "type":"Services"
        }
    ],
    "sg:phone":"+1 706 540 5818",
    "sg:postcode":"30633",
    "sg:province":"GA",
    "sg:tags":[
        "translation",
        "financial",
        "real estate"
    ],
    "wof:name":"CMR Inc",
    "wof:placetype":"venue"
},
  "geometry": {"coordinates":[-83.21018100000001,34.206993],"type":"Point"}
}