{
  "type": "Feature",
  "properties": {
    "addr:full":"319 Cantyre St Port Wentworth GA 31407",
    "addr:housenumber":"319",
    "addr:postcode":"31407",
    "addr:street":"Cantyre St",
    "iso:country":"US",
    "sg:address":"319 Cantyre St",
    "sg:city":"Port Wentworth",
    "sg:classifiers":[
        {
            "category":"Government",
            "subcategory":"Fire Station",
            "type":"Public Place"
        }
    ],
    "sg:phone":"+1 912 966 7426",
    "sg:postcode":"31407",
    "sg:province":"GA",
    "sg:tags":[
        "department"
    ],
    "wof:name":"Port Wentworth Fire Dept Adm",
    "wof:placetype":"venue"
},
  "geometry": {"coordinates":[-81.16350199999999,32.146346],"type":"Point"}
}