{
  "type": "Feature",
  "properties": {
    "addr:full":"204 Harrison Rd Juliette GA 31046",
    "addr:housenumber":"204",
    "addr:postcode":"31046",
    "addr:street":"Harrison Rd",
    "iso:country":"US",
    "sg:address":"204 Harrison Rd",
    "sg:city":"Juliette",
    "sg:classifiers":[
        {
            "category":"Shopping",
            "type":"Retail Goods"
        }
    ],
    "sg:phone":"+1 478 992 8380",
    "sg:postcode":"31046",
    "sg:province":"GA",
    "sg:tags":[
        "merchandise"
    ],
    "wof:name":"Wwwprintsandthepaupercom",
    "wof:placetype":"venue"
},
  "geometry": {"coordinates":[-83.803054,32.954946],"type":"Point"}
}