{
  "type": "Feature",
  "properties": {
    "iso:country":"US",
    "sg:address":"118 Cown Rd",
    "sg:city":"Villa Rica",
    "sg:classifiers":[
        {
            "category":"Restaurant",
            "type":"Food & Drink"
        }
    ],
    "sg:phone":"+1 770 456 6444",
    "sg:postcode":"30180",
    "sg:province":"GA",
    "wof:name":"Totsy's Seafood Heaven",
    "wof:placetype":"venue"
},
  "geometry": {"coordinates":[-84.979938,33.754616],"type":"Point"}
}