{
  "type": "Feature",
  "properties": {
    "addr:full":"37 Lagrange St Newnan GA 30263",
    "addr:housenumber":"37",
    "addr:postcode":"30263",
    "addr:street":"Lagrange St",
    "iso:country":"US",
    "sg:address":"37 Lagrange St",
    "sg:city":"Newnan",
    "sg:classifiers":[
        {
            "category":"Manufacturing",
            "subcategory":"Tools & Machinery",
            "type":"Manufacturing & Wholesale Goods"
        },
        {
            "category":"Retail",
            "subcategory":"Auto Repair",
            "type":"Services"
        }
    ],
    "sg:phone":"+1 770 252 4007",
    "sg:postcode":"30263",
    "sg:province":"GA",
    "sg:tags":[
        "shop",
        "automobile",
        "machine",
        "industrial",
        "mfg"
    ],
    "wof:name":"Zappa's Percision Automotive",
    "wof:placetype":"venue"
},
  "geometry": {"coordinates":[-84.80079499999999,33.371774],"type":"Point"}
}