{
  "type": "Feature",
  "properties": {
    "iso:country":"US",
    "sg:address":"5420 Houston Rd",
    "sg:city":"Macon",
    "sg:classifiers":[
        {
            "category":"Real Estate",
            "subcategory":"Real Estate Operator",
            "type":"Services"
        }
    ],
    "sg:phone":"+1 478 788 8027",
    "sg:postcode":"31216",
    "sg:province":"GA",
    "sg:tags":[
        "building",
        "apartment"
    ],
    "wof:name":"Harold Phillips",
    "wof:placetype":"venue"
},
  "geometry": {"coordinates":[-83.668503,32.752159],"type":"Point"}
}