{
  "type": "Feature",
  "properties": {
    "iso:country":"US",
    "sg:address":"2135 Montilly Pl SW",
    "sg:city":"Atlanta",
    "sg:classifiers":[
        {
            "category":"Professional",
            "subcategory":"Management & Consulting",
            "type":"Services"
        }
    ],
    "sg:phone":"+1 404 766 8112",
    "sg:postcode":"30349",
    "sg:province":"GA",
    "wof:name":"Baron and Farrell Management",
    "wof:placetype":"venue"
},
  "geometry": {"coordinates":[-84.461584,33.603547],"type":"Point"}
}