{
  "type": "Feature",
  "properties": {
    "addr:full":"1447 Oak Bend Way Lawrenceville GA 30045",
    "addr:housenumber":"1447",
    "addr:postcode":"30045",
    "addr:street":"Oak Bend Way",
    "iso:country":"US",
    "sg:address":"1447 Oak Bend Way",
    "sg:city":"Lawrenceville",
    "sg:classifiers":[
        {
            "category":"Shopping",
            "subcategory":"Catalog Store",
            "type":"Retail Goods"
        }
    ],
    "sg:phone":"+1 770 736 9802",
    "sg:postcode":"30045",
    "sg:province":"GA",
    "sg:tags":[
        "mail",
        "order",
        "online"
    ],
    "wof:name":"Strobel/Amway",
    "wof:placetype":"venue"
},
  "geometry": {"coordinates":[-83.980661,33.904328],"type":"Point"}
}