{
  "type": "Feature",
  "properties": {
    "addr:full":"1330 Veterans Memorial Hwy SW Mableton GA 30126",
    "addr:housenumber":"1330",
    "addr:postcode":"30126",
    "addr:street":"Veterans Memorial Hwy Sw",
    "iso:country":"US",
    "sg:address":"1330 Veterans Memorial Hwy SW",
    "sg:city":"Mableton",
    "sg:classifiers":[
        {
            "category":"Shopping",
            "subcategory":"Thrift Store",
            "type":"Retail Goods"
        },
        {
            "category":"Banks & Credit Unions",
            "subcategory":"Bank",
            "type":"Services"
        },
        {
            "category":"Shopping",
            "subcategory":"Used Merchandise",
            "type":"Retail Goods"
        }
    ],
    "sg:phone":"+1 770 948 8190",
    "sg:postcode":"30126",
    "sg:province":"GA",
    "sg:tags":[
        "shop",
        "second",
        "resale",
        "hand"
    ],
    "wof:name":"Az Thrift Store",
    "wof:placetype":"venue"
},
  "geometry": {"coordinates":[-84.59390500000001,33.815544],"type":"Point"}
}