{
  "type": "Feature",
  "properties": {
    "iso:country":"US",
    "sg:address":"43 N Broad St",
    "sg:city":"Winder",
    "sg:classifiers":[
        {
            "category":"Professional",
            "subcategory":"Lawyer & Legal Services",
            "type":"Services"
        }
    ],
    "sg:phone":"+1 770 867 2181",
    "sg:postcode":"30680",
    "sg:province":"GA",
    "sg:tags":[
        "attorney",
        "practice",
        "plan"
    ],
    "wof:name":"Wages, Nathaniel D, Law Office",
    "wof:placetype":"venue"
},
  "geometry": {"coordinates":[-83.721343,33.992023],"type":"Point"}
}