{
  "type": "Feature",
  "properties": {
    "iso:country":"US",
    "sg:address":"1451 Pleasant Valley Rd",
    "sg:city":"Vienna",
    "sg:classifiers":[
        {
            "category":"Building & Trades",
            "subcategory":"Landscaping Services",
            "type":"Services"
        }
    ],
    "sg:phone":"+1 229 268 1078",
    "sg:postcode":"31092",
    "sg:province":"GA",
    "sg:tags":[
        "landscape",
        "contractor"
    ],
    "wof:name":"Mcgraw Landscaping",
    "wof:placetype":"venue"
},
  "geometry": {"coordinates":[-83.838562,32.132324],"type":"Point"}
}