{
  "type": "Feature",
  "properties": {
    "addr:full":"259 Holland Dr NE Calhoun GA 30701",
    "addr:housenumber":"259",
    "addr:postcode":"30701",
    "addr:street":"Holland Dr Ne",
    "iso:country":"US",
    "sg:address":"259 Holland Dr NE",
    "sg:city":"Calhoun",
    "sg:classifiers":[
        {
            "category":"Building & Trades",
            "subcategory":"Plumbing",
            "type":"Services"
        }
    ],
    "sg:phone":"+1 706 602 0233",
    "sg:postcode":"30701",
    "sg:province":"GA",
    "sg:tags":[
        "contractor"
    ],
    "wof:name":"Advanced Services Inc",
    "wof:placetype":"venue"
},
  "geometry": {"coordinates":[-84.921615,34.559118],"type":"Point"}
}