{
  "type": "Feature",
  "properties": {
    "addr:full":"52 Broad St NW Atlanta GA 30303",
    "addr:housenumber":"52",
    "addr:postcode":"30303",
    "addr:street":"Broad St Nw",
    "iso:country":"US",
    "sg:address":"52 Broad St NW",
    "sg:city":"Atlanta",
    "sg:classifiers":[
        {
            "category":"Building & Trades",
            "subcategory":"Locksmith",
            "type":"Services"
        }
    ],
    "sg:phone":"+1 866 284 1085",
    "sg:postcode":"30303",
    "sg:province":"GA",
    "sg:tags":[
        "key"
    ],
    "wof:name":"1 24 Hour Emergency Locksmith",
    "wof:placetype":"venue"
},
  "geometry": {"coordinates":[-84.389809,33.755621],"type":"Point"}
}