{
  "type": "Feature",
  "properties": {
    "addr:full":"2871 Woodruff Dr NW Duluth GA 30096",
    "addr:housenumber":"2871",
    "addr:postcode":"30096",
    "addr:street":"Woodruff Dr Nw",
    "iso:country":"US",
    "sg:address":"2871 Woodruff Dr NW",
    "sg:city":"Duluth",
    "sg:classifiers":[
        {
            "category":"Building & Trades",
            "subcategory":"Construction",
            "type":"Services"
        }
    ],
    "sg:phone":"+1 770 476 5034",
    "sg:postcode":"30096",
    "sg:province":"GA",
    "sg:tags":[
        "house"
    ],
    "wof:name":"Stringer Builders Inc",
    "wof:placetype":"venue"
},
  "geometry": {"coordinates":[-84.150862,33.975712],"type":"Point"}
}