{
  "type": "Feature",
  "properties": {
    "addr:full":"114 Cherry St Marietta GA 30060",
    "addr:housenumber":"114",
    "addr:postcode":"30060",
    "addr:street":"Cherry St",
    "iso:country":"US",
    "sg:address":"114 Cherry St",
    "sg:city":"Marietta",
    "sg:classifiers":[
        {
            "category":"Communications",
            "subcategory":"Film & Video Production",
            "type":"Services"
        }
    ],
    "sg:phone":"+1 770 514 1224",
    "sg:postcode":"30060",
    "sg:province":"GA",
    "sg:tags":[
        "sound",
        "music",
        "effects"
    ],
    "wof:name":"Musicsworks",
    "wof:placetype":"venue"
},
  "geometry": {"coordinates":[-84.549071,33.967714],"type":"Point"}
}