{
  "type": "Feature",
  "properties": {
    "addr:full":"303 Braselman Ave Columbus GA 31907",
    "addr:housenumber":"303",
    "addr:postcode":"31907",
    "addr:street":"Braselman Ave",
    "iso:country":"US",
    "sg:address":"303 Braselman Ave",
    "sg:city":"Columbus",
    "sg:classifiers":[
        {
            "category":"Building & Trades",
            "subcategory":"Cleaning & Sanitation",
            "type":"Services"
        }
    ],
    "sg:phone":"+1 706 689 9979",
    "sg:postcode":"31907",
    "sg:province":"GA",
    "sg:tags":[
        "maintenance"
    ],
    "wof:name":"E & J Cleaning",
    "wof:placetype":"venue"
},
  "geometry": {"coordinates":[-84.918194,32.449187],"type":"Point"}
}