{
  "type": "Feature",
  "properties": {
    "iso:country":"US",
    "sg:address":"5354 McGinnis Ferry Rd",
    "sg:city":"Alpharetta",
    "sg:classifiers":[
        {
            "category":"Retail",
            "subcategory":"Laundry & Dry Cleaning",
            "type":"Services"
        }
    ],
    "sg:phone":"+1 770 521 5336",
    "sg:postcode":"30005",
    "sg:province":"GA",
    "wof:name":"Classy Cleaners",
    "wof:placetype":"venue"
},
  "geometry": {"coordinates":[-84.203085,34.090219],"type":"Point"}
}