{
  "type": "Feature",
  "properties": {
    "iso:country":"US",
    "sg:address":"6290 Abbotts Bridge Rd",
    "sg:city":"Duluth",
    "sg:classifiers":[
        {
            "category":"Health Services",
            "subcategory":"Doctor",
            "type":"Services"
        }
    ],
    "sg:phone":"+1 678 475 0009",
    "sg:postcode":"30097",
    "sg:province":"GA",
    "sg:tags":[
        "physician",
        "surgeon"
    ],
    "wof:name":"Riverside Plastic Surgery Ctr",
    "wof:placetype":"venue"
},
  "geometry": {"coordinates":[-84.175816,34.043566],"type":"Point"}
}