{
  "type": "Feature",
  "properties": {
    "addr:full":"675 Red Oak Rd Stockbridge GA 30281",
    "addr:housenumber":"675",
    "addr:postcode":"30281",
    "addr:street":"Red Oak Rd",
    "iso:country":"US",
    "sg:address":"675 Red Oak Rd",
    "sg:city":"Stockbridge",
    "sg:classifiers":[
        {
            "category":"Real Estate",
            "subcategory":"Developer",
            "type":"Services"
        }
    ],
    "sg:phone":"+1 770 507 2219",
    "sg:postcode":"30281",
    "sg:province":"GA",
    "wof:name":"Danlake Development Inc",
    "wof:placetype":"venue"
},
  "geometry": {"coordinates":[-84.230278,33.527243],"type":"Point"}
}