{
  "type": "Feature",
  "properties": {
    "addr:full":"1020 Edgewood Avenue NE Atlanta GA 30307",
    "addr:housenumber":"1020",
    "addr:postcode":"30307",
    "addr:street":"Edgewood Avenue Ne",
    "iso:country":"US",
    "sg:address":"1020 Edgewood Avenue NE",
    "sg:city":"Atlanta",
    "sg:classifiers":[
        {
            "category":"Professional",
            "subcategory":"Lawyer & Legal Services",
            "type":"Services"
        }
    ],
    "sg:phone":"+1 404 614 0001",
    "sg:postcode":"30307",
    "sg:province":"GA",
    "sg:tags":[
        "litigation"
    ],
    "wof:name":"Almond Calandra A",
    "wof:placetype":"venue"
},
  "geometry": {"coordinates":[-84.355024,33.756636],"type":"Point"}
}