{
  "type": "Feature",
  "properties": {
    "addr:full":"4324 N Shallowford Rd Atlanta GA 30341",
    "addr:housenumber":"4324",
    "addr:postcode":"30341",
    "addr:street":"N Shallowford Rd",
    "iso:country":"US",
    "sg:address":"4324 N Shallowford Rd",
    "sg:city":"Atlanta",
    "sg:classifiers":[
        {
            "category":"Building & Trades",
            "subcategory":"Locksmith",
            "type":"Services"
        }
    ],
    "sg:phone":"+1 678 269 7242",
    "sg:postcode":"30341",
    "sg:province":"GA",
    "sg:tags":[
        "key"
    ],
    "wof:name":"24 7 Emergency Locksmith",
    "wof:placetype":"venue"
},
  "geometry": {"coordinates":[-84.304447,33.91832],"type":"Point"}
}