{
  "type": "Feature",
  "properties": {
    "addr:full":"3115 Mercury Dr Columbus GA 31906",
    "addr:housenumber":"3115",
    "addr:postcode":"31906",
    "addr:street":"Mercury Dr",
    "iso:country":"US",
    "sg:address":"3115 Mercury Dr",
    "sg:city":"Columbus",
    "sg:classifiers":[
        {
            "category":"Professional",
            "subcategory":"Accounting & Tax Preparation",
            "type":"Services"
        }
    ],
    "sg:phone":"+1 706 221 9828",
    "sg:postcode":"31906",
    "sg:province":"GA",
    "sg:tags":[
        "return",
        "filing"
    ],
    "wof:name":"Premier Fast Tax",
    "wof:placetype":"venue"
},
  "geometry": {"coordinates":[-84.945808,32.480049],"type":"Point"}
}