{
  "type": "Feature",
  "properties": {
    "addr:full":"2484 Briarcliff Rd NE Ste 34 Atlanta GA 30329",
    "addr:housenumber":"2484",
    "addr:postcode":"30329",
    "addr:street":"Briarcliff Rd Ne Ste 34",
    "iso:country":"US",
    "sg:address":"2484 Briarcliff Rd NE Ste 34",
    "sg:city":"Atlanta",
    "sg:classifiers":[
        {
            "category":"Real Estate",
            "subcategory":"Real Estate Services",
            "type":"Services"
        },
        {
            "category":"Banks & Credit Unions",
            "subcategory":"Financial Services",
            "type":"Services"
        }
    ],
    "sg:phone":"+1 404 636 2225",
    "sg:postcode":"30329",
    "sg:province":"GA",
    "sg:tags":[
        "financing",
        "loan",
        "mortgage"
    ],
    "sg:website":"http://www.wellsfargofinancial.com",
    "wof:name":"Wells Fargo Financial",
    "wof:placetype":"venue"
},
  "geometry": {"coordinates":[-84.33238,33.826551],"type":"Point"}
}