{
  "type": "Feature",
  "properties": {
    "addr:full":"3445 Peachtree Rd Atlanta GA 30305",
    "addr:housenumber":"3445",
    "addr:postcode":"30305",
    "addr:street":"Peachtree Rd",
    "iso:country":"US",
    "sg:address":"3445 Peachtree Rd",
    "sg:city":"Atlanta",
    "sg:classifiers":[
        {
            "category":"Professional",
            "subcategory":"Computer Services",
            "type":"Services"
        }
    ],
    "sg:phone":"+1 404 495 7816",
    "sg:postcode":"30305",
    "sg:province":"GA",
    "sg:tags":[
        "programing",
        "custom"
    ],
    "wof:name":"Webroomz",
    "wof:placetype":"venue"
},
  "geometry": {"coordinates":[-84.365098,33.848806],"type":"Point"}
}