{
  "type": "Feature",
  "properties": {
    "addr:full":"2280 Melinda Dr NE Atlanta GA 30345",
    "addr:housenumber":"2280",
    "addr:postcode":"30345",
    "addr:street":"Melinda Dr Ne",
    "iso:country":"US",
    "sg:address":"2280 Melinda Dr NE",
    "sg:city":"Atlanta",
    "sg:classifiers":[
        {
            "category":"Wholesale",
            "subcategory":"Auto Parts",
            "type":"Manufacturing & Wholesale Goods"
        }
    ],
    "sg:phone":"+1 404 633 6553",
    "sg:postcode":"30345",
    "sg:province":"GA",
    "wof:name":"Isoya International",
    "wof:placetype":"venue"
},
  "geometry": {"coordinates":[-84.29414800000001,33.852074],"type":"Point"}
}