{
  "type": "Feature",
  "properties": {
    "addr:full":"1645 Hammond Woods Cir SW Marietta GA 30008",
    "addr:housenumber":"1645",
    "addr:postcode":"30008",
    "addr:street":"Hammond Woods Cir Sw",
    "iso:country":"US",
    "sg:address":"1645 Hammond Woods Cir SW",
    "sg:city":"Marietta",
    "sg:classifiers":[
        {
            "category":"Shopping",
            "subcategory":"Computers & Home Electronics",
            "type":"Retail Goods"
        }
    ],
    "sg:phone":"+1 770 424 0275",
    "sg:postcode":"30008",
    "sg:province":"GA",
    "wof:name":"Mitchell Communications",
    "wof:placetype":"venue"
},
  "geometry": {"coordinates":[-84.589634,33.909796],"type":"Point"}
}