{
  "type": "Feature",
  "properties": {
    "addr:full":"3836 Foxwood Rd Duluth GA 30096",
    "addr:housenumber":"3836",
    "addr:postcode":"30096",
    "addr:street":"Foxwood Rd",
    "iso:country":"US",
    "sg:address":"3836 Foxwood Rd",
    "sg:city":"Duluth",
    "sg:classifiers":[
        {
            "category":"Organizations",
            "subcategory":"Membership Organization",
            "type":"Services"
        }
    ],
    "sg:phone":"+1 770 447 9772",
    "sg:postcode":"30096",
    "sg:province":"GA",
    "wof:name":"Trout Unlimited",
    "wof:placetype":"venue"
},
  "geometry": {"coordinates":[-84.19636300000001,33.985913],"type":"Point"}
}