{
  "type": "Feature",
  "properties": {
    "iso:country":"US",
    "sg:address":"922 Pinhurst Dr NW",
    "sg:city":"Atlanta",
    "sg:classifiers":[
        {
            "category":"Local Transit",
            "type":"Transportation"
        }
    ],
    "sg:phone":"+1 770 444 9033",
    "sg:postcode":"30339",
    "sg:province":"GA",
    "sg:tags":[
        "limousine"
    ],
    "wof:name":"MSJ Limo",
    "wof:placetype":"venue"
},
  "geometry": {"coordinates":[-84.46652899999999,33.871782],"type":"Point"}
}