{
  "type": "Feature",
  "properties": {
    "addr:full":"2278A Powder Springs Rd SW Marietta GA 30064",
    "addr:housenumber":"2278a",
    "addr:postcode":"30064",
    "addr:street":"Powder Springs Rd Sw",
    "iso:country":"US",
    "sg:address":"2278A Powder Springs Rd SW",
    "sg:city":"Marietta",
    "sg:classifiers":[
        {
            "category":"Personal",
            "subcategory":"Nail Salon",
            "type":"Services"
        }
    ],
    "sg:phone":"+1 770 422 4621",
    "sg:postcode":"30064",
    "sg:province":"GA",
    "wof:name":"Pretty Nails",
    "wof:placetype":"venue"
},
  "geometry": {"coordinates":[-84.619321,33.882875],"type":"Point"}
}