{
  "type": "Feature",
  "properties": {
    "addr:full":"154 S Broad St Crawford GA 30630",
    "addr:housenumber":"154",
    "addr:postcode":"30630",
    "addr:street":"S Broad St",
    "iso:country":"US",
    "sg:address":"154 S Broad St",
    "sg:city":"Crawford",
    "sg:classifiers":[
        {
            "category":"Manufacturing",
            "subcategory":"Toys & Sporting Goods",
            "type":"Manufacturing & Wholesale Goods"
        }
    ],
    "sg:phone":"+1 706 743 7050",
    "sg:postcode":"30630",
    "sg:province":"GA",
    "sg:tags":[
        "wooden",
        "mfr",
        "craft",
        "kit"
    ],
    "wof:name":"B & B Family Enterprises Inc",
    "wof:placetype":"venue"
},
  "geometry": {"coordinates":[-83.15697900000001,33.881774],"type":"Point"}
}