{
  "type": "Feature",
  "properties": {
    "addr:full":"3429 Lawrenceville Suwanee Rd Ste E Suwanee GA 30024",
    "addr:housenumber":"3429",
    "addr:postcode":"30024",
    "addr:street":"Lawrenceville Suwanee Rd Ste E",
    "iso:country":"US",
    "sg:address":"3429 Lawrenceville Suwanee Rd Ste E",
    "sg:city":"Suwanee",
    "sg:classifiers":[
        {
            "category":"Restaurant",
            "type":"Food & Drink"
        }
    ],
    "sg:phone":"+1 770 904 6919",
    "sg:postcode":"30024",
    "sg:province":"GA",
    "sg:tags":[
        "japanese"
    ],
    "wof:name":"Joy of Tokyo",
    "wof:placetype":"venue"
},
  "geometry": {"coordinates":[-84.053848,34.042491],"type":"Point"}
}