{
  "type": "Feature",
  "properties": {
    "iso:country":"US",
    "sg:address":"676 Henderson Dr",
    "sg:city":"Cartersville",
    "sg:classifiers":[
        {
            "category":"Social Services",
            "subcategory":"Child Care",
            "type":"Services"
        }
    ],
    "sg:phone":"+1 770 386 1666",
    "sg:postcode":"30120",
    "sg:province":"GA",
    "wof:name":"Step By Step Child Dev Ctr",
    "wof:placetype":"venue"
},
  "geometry": {"coordinates":[-84.818088,34.155251],"type":"Point"}
}