{
  "type": "Feature",
  "properties": {
    "addr:full":"2665 Acorn Ave NE Atlanta GA 30305",
    "addr:housenumber":"2665",
    "addr:postcode":"30305",
    "addr:street":"Acorn Ave Ne",
    "iso:country":"US",
    "sg:address":"2665 Acorn Ave NE",
    "sg:city":"Atlanta",
    "sg:classifiers":[
        {
            "category":"Professional",
            "subcategory":"Management & Consulting",
            "type":"Services"
        }
    ],
    "sg:phone":"+1 404 262 1926",
    "sg:postcode":"30305",
    "sg:province":"GA",
    "sg:tags":[
        "business"
    ],
    "wof:name":"Kettering Consulting Group",
    "wof:placetype":"venue"
},
  "geometry": {"coordinates":[-84.37845,33.828652],"type":"Point"}
}