{
  "type": "Feature",
  "properties": {
    "iso:country":"US",
    "sg:address":"1720 Spectrum Dr",
    "sg:city":"Lawrenceville",
    "sg:classifiers":[
        {
            "category":"Home & Garden",
            "subcategory":"Furniture",
            "type":"Retail Goods"
        }
    ],
    "sg:phone":"+1 770 237 2170",
    "sg:postcode":"30043",
    "sg:province":"GA",
    "sg:tags":[
        "store"
    ],
    "wof:name":"Aresco",
    "wof:placetype":"venue"
},
  "geometry": {"coordinates":[-84.066101,33.973701],"type":"Point"}
}