{
  "type": "Feature",
  "properties": {
    "addr:full":"3550 North Pkwy Cumming GA 30040",
    "addr:housenumber":"3550",
    "addr:postcode":"30040",
    "addr:street":"North Pkwy",
    "iso:country":"US",
    "sg:address":"3550 North Pkwy",
    "sg:city":"Cumming",
    "sg:classifiers":[
        {
            "category":"Manufacturing",
            "subcategory":"Tools & Machinery",
            "type":"Manufacturing & Wholesale Goods"
        }
    ],
    "sg:phone":"+1 770 886 3121",
    "sg:postcode":"30040",
    "sg:province":"GA",
    "sg:tags":[
        "control",
        "panel"
    ],
    "wof:name":"Ergo Contract Mfg Inc",
    "wof:placetype":"venue"
},
  "geometry": {"coordinates":[-84.148894,34.191631],"type":"Point"}
}