{
  "type": "Feature",
  "properties": {
    "addr:full":"3758 Hwy 42 Locust Grove GA 30248",
    "addr:housenumber":"3758",
    "addr:postcode":"30248",
    "addr:street":"Hwy 42",
    "iso:country":"US",
    "sg:address":"3758 Hwy 42",
    "sg:city":"Locust Grove",
    "sg:classifiers":[
        {
            "category":"Health Services",
            "subcategory":"Doctor",
            "type":"Services"
        }
    ],
    "sg:phone":"+1 678 432 8246",
    "sg:postcode":"30248",
    "sg:province":"GA",
    "sg:tags":[
        "physician",
        "surgeon"
    ],
    "wof:name":"Atlanta Gastroenterology Assoc",
    "wof:placetype":"venue"
},
  "geometry": {"coordinates":[-84.11117299999999,33.350291],"type":"Point"}
}