{
  "type": "Feature",
  "properties": {
    "addr:full":"100 Technology Dr Alpharetta GA 30005",
    "addr:housenumber":"100",
    "addr:postcode":"30005",
    "addr:street":"Technology Dr",
    "iso:country":"US",
    "sg:address":"100 Technology Dr",
    "sg:city":"Alpharetta",
    "sg:classifiers":[
        {
            "category":"Manufacturing",
            "subcategory":"Tools & Machinery",
            "type":"Manufacturing & Wholesale Goods"
        }
    ],
    "sg:phone":"+1 770 740 3000",
    "sg:postcode":"30005",
    "sg:province":"GA",
    "sg:tags":[
        "mfg"
    ],
    "sg:website":"www.siemens.com",
    "wof:name":"Siemens Energy & Automation",
    "wof:placetype":"venue"
},
  "geometry": {"coordinates":[-84.22018199999999,34.115835],"type":"Point"}
}