{
  "type": "Feature",
  "properties": {
    "addr:full":"2880 Old Jackson Rd Locust Grove GA 30248",
    "addr:housenumber":"2880",
    "addr:postcode":"30248",
    "addr:street":"Old Jackson Rd",
    "iso:country":"US",
    "sg:address":"2880 Old Jackson Rd",
    "sg:city":"Locust Grove",
    "sg:classifiers":[
        {
            "category":"Building & Trades",
            "subcategory":"Construction",
            "type":"Services"
        }
    ],
    "sg:phone":"+1 678 583 9530",
    "sg:postcode":"30248",
    "sg:province":"GA",
    "sg:tags":[
        "new"
    ],
    "wof:name":"Southern Handyman",
    "wof:placetype":"venue"
},
  "geometry": {"coordinates":[-84.04218899999999,33.36669],"type":"Point"}
}