{
  "type": "Feature",
  "properties": {
    "iso:country":"US",
    "sg:address":"4746 Iron Hill Rd",
    "sg:city":"Dearing",
    "sg:classifiers":[
        {
            "category":"Professional",
            "type":"Services"
        }
    ],
    "sg:phone":"+1 706 595 2487",
    "sg:postcode":"30808",
    "sg:province":"GA",
    "wof:name":"David Workman",
    "wof:placetype":"venue"
},
  "geometry": {"coordinates":[-82.41168399999999,33.376982],"type":"Point"}
}