{
  "type": "Feature",
  "properties": {
    "iso:country":"US",
    "sg:address":"60 Forsyth St SW",
    "sg:city":"Atlanta",
    "sg:classifiers":[
        {
            "category":"Government",
            "subcategory":"Office",
            "type":"Public Place"
        }
    ],
    "sg:phone":"+1 404 562 5007",
    "sg:postcode":"30303",
    "sg:province":"GA",
    "sg:tags":[
        "national",
        "security"
    ],
    "wof:name":"Army Corp Engineers S ATL Div",
    "wof:placetype":"venue"
},
  "geometry": {"coordinates":[-84.39333999999999,33.752818],"type":"Point"}
}