{
  "type": "Feature",
  "properties": {
    "iso:country":"US",
    "sg:address":"130 Lockwood St",
    "sg:city":"Milledgeville",
    "sg:classifiers":[
        {
            "category":"Freight",
            "type":"Transportation"
        }
    ],
    "sg:phone":"+1 478 452 3165",
    "sg:postcode":"31061",
    "sg:province":"GA",
    "wof:name":"Travel Vantures Inc",
    "wof:placetype":"venue"
},
  "geometry": {"coordinates":[-83.232962,33.061645],"type":"Point"}
}