{
  "type": "Feature",
  "properties": {
    "addr:full":"200 Valley Dr Perry GA 31069",
    "addr:housenumber":"200",
    "addr:postcode":"31069",
    "addr:street":"Valley Dr",
    "iso:country":"US",
    "sg:address":"200 Valley Dr",
    "sg:city":"Perry",
    "sg:classifiers":[
        {
            "category":"Professional",
            "type":"Services"
        }
    ],
    "sg:phone":"+1 478 987 8877",
    "sg:postcode":"31069",
    "sg:province":"GA",
    "sg:tags":[
        "caterer"
    ],
    "wof:name":"Green Derby",
    "wof:placetype":"venue"
},
  "geometry": {"coordinates":[-83.745064,32.47084],"type":"Point"}
}