{
  "type": "Feature",
  "properties": {
    "iso:country":"US",
    "sg:address":"134 Cormorant Way",
    "sg:city":"Savannah",
    "sg:classifiers":[
        {
            "category":"Professional",
            "type":"Services"
        }
    ],
    "sg:phone":"+1 912 961 6125",
    "sg:postcode":"31419",
    "sg:province":"GA",
    "wof:name":"Marshmallows In Closet",
    "wof:placetype":"venue"
},
  "geometry": {"coordinates":[-81.244319,31.973868],"type":"Point"}
}