{
  "type": "Feature",
  "properties": {
    "addr:full":"270 Weatherly Wood Dr Winterville GA 30683",
    "addr:housenumber":"270",
    "addr:postcode":"30683",
    "addr:street":"Weatherly Wood Dr",
    "iso:country":"US",
    "sg:address":"270 Weatherly Wood Dr",
    "sg:city":"Winterville",
    "sg:classifiers":[
        {
            "category":"Wholesale",
            "subcategory":"Motor Vehicles",
            "type":"Manufacturing & Wholesale Goods"
        }
    ],
    "sg:phone":"+1 706 353 1460",
    "sg:postcode":"30683",
    "sg:province":"GA",
    "wof:name":"Barton Automobiles",
    "wof:placetype":"venue"
},
  "geometry": {"coordinates":[-83.302173,33.939706],"type":"Point"}
}