{
  "type": "Feature",
  "properties": {
    "addr:full":"4 Westfair Ct NE Atlanta GA 30328",
    "addr:housenumber":"4",
    "addr:postcode":"30328",
    "addr:street":"Westfair Ct Ne",
    "iso:country":"US",
    "sg:address":"4 Westfair Ct NE",
    "sg:city":"Atlanta",
    "sg:classifiers":[
        {
            "category":"Building & Trades",
            "subcategory":"Locksmith",
            "type":"Services"
        }
    ],
    "sg:phone":"+1 678 369 5751",
    "sg:postcode":"30328",
    "sg:province":"GA",
    "sg:tags":[
        "key"
    ],
    "wof:name":"24 7 Emergency Locksmith",
    "wof:placetype":"venue"
},
  "geometry": {"coordinates":[-84.354028,33.952913],"type":"Point"}
}