{
  "type": "Feature",
  "properties": {
    "iso:country":"US",
    "sg:address":"140 W Porter St",
    "sg:city":"Cartersville",
    "sg:classifiers":[
        {
            "category":"Recreation",
            "type":"Entertainment"
        }
    ],
    "sg:phone":"+1 770 387 3174",
    "sg:postcode":"30120",
    "sg:province":"GA",
    "sg:tags":[
        "instruction",
        "gymnastic"
    ],
    "wof:name":"Gymnastics Annex",
    "wof:placetype":"venue"
},
  "geometry": {"coordinates":[-84.797557,34.178978],"type":"Point"}
}