{
  "type": "Feature",
  "properties": {
    "iso:country":"US",
    "sg:address":"75 Spring St NW",
    "sg:city":"Atlanta",
    "sg:classifiers":[
        {
            "category":"Building & Trades",
            "subcategory":"Cleaning & Sanitation",
            "type":"Services"
        }
    ],
    "sg:phone":"+1 404 588 5551",
    "sg:postcode":"30303",
    "sg:province":"GA",
    "sg:tags":[
        "janitor"
    ],
    "wof:name":"Rosemark",
    "wof:placetype":"venue"
},
  "geometry": {"coordinates":[-84.39191,33.757416],"type":"Point"}
}