{
  "type": "Feature",
  "properties": {
    "iso:country":"US",
    "sg:address":"104 Main St",
    "sg:city":"Milner",
    "sg:classifiers":[
        {
            "category":"Manufacturing",
            "subcategory":"Food",
            "type":"Manufacturing & Wholesale Goods"
        }
    ],
    "sg:phone":"+1 770 358 0966",
    "sg:postcode":"30257",
    "sg:province":"GA",
    "sg:tags":[
        "corn",
        "chips",
        "potato"
    ],
    "wof:name":"Atlanta South Coffee & Vending",
    "wof:placetype":"venue"
},
  "geometry": {"coordinates":[-84.19583799999999,33.112292],"type":"Point"}
}