{
  "type": "Feature",
  "properties": {
    "addr:full":"1409 N Highland Ave NE K Atlanta GA 30306",
    "addr:housenumber":"1409",
    "addr:postcode":"30306",
    "addr:street":"N Highland Ave Ne K",
    "iso:country":"US",
    "sg:address":"1409 N Highland Ave NE K",
    "sg:city":"Atlanta",
    "sg:classifiers":[
        {
            "category":"Professional",
            "subcategory":"Business Services",
            "type":"Services"
        }
    ],
    "sg:phone":"+1 404 249 9582",
    "sg:postcode":"30306",
    "sg:province":"GA",
    "sg:tags":[
        "broker"
    ],
    "sg:website":"http://www.newbridgegroup.com",
    "wof:name":"Newbridge Group Inc",
    "wof:placetype":"venue"
},
  "geometry": {"coordinates":[-84.351679,33.793025],"type":"Point"}
}