{
  "type": "Feature",
  "properties": {
    "iso:country":"US",
    "sg:address":"3620 Dekalb Technology Pkwy",
    "sg:city":"Atlanta",
    "sg:classifiers":[
        {
            "category":"Professional",
            "subcategory":"Detective & Security Services",
            "type":"Services"
        }
    ],
    "sg:phone":"+1 770 220 1912",
    "sg:postcode":"30340",
    "sg:province":"GA",
    "sg:tags":[
        "car"
    ],
    "wof:name":"Investigative Solutions Inc",
    "wof:placetype":"venue"
},
  "geometry": {"coordinates":[-84.266947,33.887104],"type":"Point"}
}