{
  "type": "Feature",
  "properties": {
    "iso:country":"US",
    "sg:address":"6000 Medlock Bridge Pkwy",
    "sg:city":"Alpharetta",
    "sg:classifiers":[
        {
            "category":"Personal",
            "subcategory":"Beauty Salon",
            "type":"Services"
        },
        {
            "category":"Personal",
            "subcategory":"Barber",
            "type":"Services"
        }
    ],
    "sg:phone":"+1 770 476 0030",
    "sg:postcode":"30022",
    "sg:province":"GA",
    "sg:tags":[
        "hair"
    ],
    "sg:website":"www.marioshairdesigners.com",
    "wof:name":"Mario's Hair Designers",
    "wof:placetype":"venue"
},
  "geometry": {"coordinates":[-84.188103,34.029701],"type":"Point"}
}