{
  "type": "Feature",
  "properties": {
    "addr:full":"1 Western Hills Ct NW Norcross GA 30071",
    "addr:housenumber":"1",
    "addr:postcode":"30071",
    "addr:street":"Western Hills Ct Nw",
    "iso:country":"US",
    "sg:address":"1 Western Hills Ct NW",
    "sg:city":"Norcross",
    "sg:classifiers":[
        {
            "category":"Retail",
            "subcategory":"Storage",
            "type":"Services"
        }
    ],
    "sg:phone":"+1 678 373 0722",
    "sg:postcode":"30071",
    "sg:province":"GA",
    "sg:tags":[
        "self"
    ],
    "sg:website":"www.securcareselfstorage.com",
    "wof:name":"SecurCare Self Storage",
    "wof:placetype":"venue"
},
  "geometry": {"coordinates":[-84.209379,33.923625],"type":"Point"}
}