{
  "type": "Feature",
  "properties": {
    "addr:full":"452 Sawtell Ave SE Atlanta GA 30315",
    "addr:housenumber":"452",
    "addr:postcode":"30315",
    "addr:street":"Sawtell Ave Se",
    "iso:country":"US",
    "sg:address":"452 Sawtell Ave SE",
    "sg:city":"Atlanta",
    "sg:classifiers":[
        {
            "category":"Retail",
            "subcategory":"Repair Shop",
            "type":"Services"
        }
    ],
    "sg:phone":"+1 404 622 8825",
    "sg:postcode":"30315",
    "sg:province":"GA",
    "sg:tags":[
        "upholsterer"
    ],
    "wof:name":"Charles Bailey Furniture",
    "wof:placetype":"venue"
},
  "geometry": {"coordinates":[-84.373788,33.71286],"type":"Point"}
}