{
  "type": "Feature",
  "properties": {
    "iso:country":"US",
    "sg:address":"6300 Hwy 9 N",
    "sg:city":"Alpharetta",
    "sg:classifiers":[
        {
            "category":"Personal",
            "subcategory":"Beauty Salon",
            "type":"Services"
        }
    ],
    "sg:phone":"+1 770 752 0744",
    "sg:postcode":"30004",
    "sg:province":"GA",
    "sg:tags":[
        "manicuring"
    ],
    "wof:name":"Lilly Nails",
    "wof:placetype":"venue"
},
  "geometry": {"coordinates":[-84.253176,34.130329],"type":"Point"}
}