{
  "type": "Feature",
  "properties": {
    "iso:country":"US",
    "sg:address":"1525 Mills Lindsey School Rd",
    "sg:city":"Sandersville",
    "sg:classifiers":[
        {
            "category":"Farming",
            "subcategory":"Farm",
            "type":"Manufacturing & Wholesale Goods"
        }
    ],
    "sg:phone":"+1 478 552 3271",
    "sg:postcode":"31094",
    "sg:province":"GA",
    "sg:website":"www.howardsheppard.com",
    "wof:name":"C & H Farm Barn",
    "wof:placetype":"venue"
},
  "geometry": {"coordinates":[-82.853408,33.118269],"type":"Point"}
}