{
  "type": "Feature",
  "properties": {
    "iso:country":"US",
    "sg:address":"3880 Pittman Rd",
    "sg:city":"Atlanta",
    "sg:classifiers":[
        {
            "category":"Building & Trades",
            "subcategory":"Pest Control",
            "type":"Services"
        }
    ],
    "sg:phone":"+1 404 344 1620",
    "sg:postcode":"30349",
    "sg:province":"GA",
    "wof:name":"Contact Pest Control",
    "wof:placetype":"venue"
},
  "geometry": {"coordinates":[-84.578982,33.64995],"type":"Point"}
}