{
  "type": "Feature",
  "properties": {
    "addr:full":"688 Pulaski St Athens GA 30601",
    "addr:housenumber":"688",
    "addr:postcode":"30601",
    "addr:street":"Pulaski St",
    "iso:country":"US",
    "sg:address":"688 Pulaski St",
    "sg:city":"Athens",
    "sg:classifiers":[
        {
            "category":"Home & Garden",
            "subcategory":"Home Furnishings",
            "type":"Retail Goods"
        }
    ],
    "sg:phone":"+1 706 549 3072",
    "sg:postcode":"30601",
    "sg:province":"GA",
    "sg:tags":[
        "repair"
    ],
    "wof:name":"Gilree Upholstery & Trim Shop",
    "wof:placetype":"venue"
},
  "geometry": {"coordinates":[-83.38131199999999,33.967089],"type":"Point"}
}