{
  "type": "Feature",
  "properties": {
    "iso:country":"US",
    "sg:address":"3551 Spring Creek Cir",
    "sg:city":"Snellville",
    "sg:classifiers":[
        {
            "category":"Manufacturing",
            "subcategory":"Furniture",
            "type":"Manufacturing & Wholesale Goods"
        }
    ],
    "sg:phone":"+1 770 354 8259",
    "sg:postcode":"30039",
    "sg:province":"GA",
    "sg:tags":[
        "building",
        "public",
        "mfg"
    ],
    "wof:name":"Antebellum Woodworking",
    "wof:placetype":"venue"
},
  "geometry": {"coordinates":[-84.03521000000001,33.807189],"type":"Point"}
}