{
  "type": "Feature",
  "properties": {
    "iso:country":"US",
    "sg:address":"3536 Mcdaniel St",
    "sg:city":"Duluth",
    "sg:classifiers":[
        {
            "category":"Building & Trades",
            "subcategory":"Landscaping Services",
            "type":"Services"
        }
    ],
    "sg:phone":"+1 770 476 4595",
    "sg:postcode":"30096",
    "sg:province":"GA",
    "sg:tags":[
        "consultant",
        "lawn",
        "designer",
        "landscape"
    ],
    "sg:website":"http://www.imagescapesinc.com",
    "wof:name":"Imagescapes Inc",
    "wof:placetype":"venue"
},
  "geometry": {"coordinates":[-84.15091700000001,33.989944],"type":"Point"}
}