{
  "type": "Feature",
  "properties": {
    "addr:full":"110 Avonlea Dr Covington GA 30016",
    "addr:housenumber":"110",
    "addr:postcode":"30016",
    "addr:street":"Avonlea Dr",
    "iso:country":"US",
    "sg:address":"110 Avonlea Dr",
    "sg:city":"Covington",
    "sg:classifiers":[
        {
            "category":"Building & Trades",
            "subcategory":"Cleaning & Sanitation",
            "type":"Services"
        }
    ],
    "sg:phone":"+1 770 315 7737",
    "sg:postcode":"30016",
    "sg:province":"GA",
    "sg:tags":[
        "maintenance"
    ],
    "wof:name":"Gordon Cleaning Service",
    "wof:placetype":"venue"
},
  "geometry": {"coordinates":[-83.94427899999999,33.59589],"type":"Point"}
}