{
  "type": "Feature",
  "properties": {
    "iso:country":"US",
    "sg:address":"76 N Main St",
    "sg:city":"Blakely",
    "sg:classifiers":[
        {
            "category":"Personal",
            "subcategory":"Beauty Salon",
            "type":"Services"
        }
    ],
    "sg:phone":"+1 229 723 2370",
    "sg:postcode":"31768",
    "sg:province":"GA",
    "sg:tags":[
        "shop"
    ],
    "wof:name":"Abby Hattaway",
    "wof:placetype":"venue"
},
  "geometry": {"coordinates":[-83.788769,31.180203],"type":"Point"}
}