{
  "type": "Feature",
  "properties": {
    "iso:country":"US",
    "sg:address":"1420 Peachtree St NE Ste 100",
    "sg:city":"Atlanta",
    "sg:classifiers":[
        {
            "category":"Real Estate",
            "subcategory":"Real Estate Agent",
            "type":"Services"
        }
    ],
    "sg:phone":"+1 404 444 8446",
    "sg:postcode":"30309",
    "sg:province":"GA",
    "sg:website":"christopherfling.com/",
    "wof:name":"Christopher Fling, Keller Williams Realty Atlanta Midtown",
    "wof:placetype":"venue"
},
  "geometry": {"coordinates":[-84.38764399999999,33.792862],"type":"Point"}
}