{
  "type": "Feature",
  "properties": {
    "addr:full":"20 E Church St Cartersville GA 30120",
    "addr:housenumber":"20",
    "addr:postcode":"30120",
    "addr:street":"E Church St",
    "iso:country":"US",
    "sg:address":"20 E Church St",
    "sg:city":"Cartersville",
    "sg:classifiers":[
        {
            "category":"Personal",
            "subcategory":"Beauty Salon",
            "type":"Services"
        }
    ],
    "sg:phone":"+1 770 387 1200",
    "sg:postcode":"30120",
    "sg:province":"GA",
    "sg:tags":[
        "shop",
        "treatment",
        "skin"
    ],
    "wof:name":"Shaving Gallery",
    "wof:placetype":"venue"
},
  "geometry": {"coordinates":[-84.796097,34.167075],"type":"Point"}
}