{
  "type": "Feature",
  "properties": {
    "iso:country":"US",
    "sg:address":"1975 Old Hwy 19 S",
    "sg:city":"Thomaston",
    "sg:classifiers":[
        {
            "category":"Building & Trades",
            "subcategory":"Construction",
            "type":"Services"
        }
    ],
    "sg:phone":"+1 706 647 7946",
    "sg:postcode":"30286",
    "sg:province":"GA",
    "sg:tags":[
        "contractor"
    ],
    "wof:name":"Pooldepot Inc",
    "wof:placetype":"venue"
},
  "geometry": {"coordinates":[-84.320778,32.85166],"type":"Point"}
}