{
  "type": "Feature",
  "properties": {
    "iso:country":"US",
    "sg:address":"286 Fiddlers Trl",
    "sg:city":"Auburn",
    "sg:classifiers":[
        {
            "category":"Autos & Motor Vehicles",
            "subcategory":"Auto Supplies",
            "type":"Retail Goods"
        }
    ],
    "sg:phone":"+1 770 586 0558",
    "sg:postcode":"30011",
    "sg:province":"GA",
    "sg:tags":[
        "automobile",
        "part"
    ],
    "wof:name":"Oreilly",
    "wof:placetype":"venue"
},
  "geometry": {"coordinates":[-83.82470499999999,33.995672],"type":"Point"}
}