{
  "type": "Feature",
  "properties": {
    "addr:full":"2505 Woodbrook Ct Lawrenceville GA 30043",
    "addr:housenumber":"2505",
    "addr:postcode":"30043",
    "addr:street":"Woodbrook Ct",
    "iso:country":"US",
    "sg:address":"2505 Woodbrook Ct",
    "sg:city":"Lawrenceville",
    "sg:classifiers":[
        {
            "category":"Communications",
            "subcategory":"Film & Video Production",
            "type":"Services"
        }
    ],
    "sg:phone":"+1 770 682 6798",
    "sg:postcode":"30043",
    "sg:province":"GA",
    "sg:tags":[
        "motion"
    ],
    "wof:name":"Visual Edge Production Svcs",
    "wof:placetype":"venue"
},
  "geometry": {"coordinates":[-84.014945,34.029165],"type":"Point"}
}