{
  "type": "Feature",
  "properties": {
    "iso:country":"US",
    "sg:address":"478 Bennett Rd",
    "sg:city":"Homer",
    "sg:classifiers":[
        {
            "category":"Utilities",
            "subcategory":"Refuse",
            "type":"Services"
        }
    ],
    "sg:phone":"+1 706 677 4868",
    "sg:postcode":"30547",
    "sg:province":"GA",
    "sg:tags":[
        "garbage",
        "collection",
        "system"
    ],
    "wof:name":"Waste Management Inc",
    "wof:placetype":"venue"
},
  "geometry": {"coordinates":[-83.426036,34.355604],"type":"Point"}
}