{
  "type": "Feature",
  "properties": {
    "iso:country":"US",
    "sg:address":"8924 Bright Star Rd",
    "sg:city":"Douglasville",
    "sg:classifiers":[
        {
            "category":"Retail",
            "subcategory":"Auto Repair",
            "type":"Services"
        }
    ],
    "sg:phone":"+1 770 942 5343",
    "sg:postcode":"30134",
    "sg:province":"GA",
    "sg:tags":[
        "injection",
        "part",
        "diesel",
        "engines-diesel-fuel"
    ],
    "wof:name":"Georgia Diesel Repair Inc",
    "wof:placetype":"venue"
},
  "geometry": {"coordinates":[-84.778604,33.739058],"type":"Point"}
}