{
  "type": "Feature",
  "properties": {
    "addr:full":"721 Univeter Rd Canton GA 30115",
    "addr:housenumber":"721",
    "addr:postcode":"30115",
    "addr:street":"Univeter Rd",
    "iso:country":"US",
    "sg:address":"721 Univeter Rd",
    "sg:city":"Canton",
    "sg:classifiers":[
        {
            "category":"Building & Trades",
            "subcategory":"Construction",
            "type":"Services"
        }
    ],
    "sg:phone":"+1 770 720 4492",
    "sg:postcode":"30115",
    "sg:province":"GA",
    "sg:tags":[
        "masonry",
        "contractor"
    ],
    "wof:name":"Stoner Masonry",
    "wof:placetype":"venue"
},
  "geometry": {"coordinates":[-84.500294,34.195997],"type":"Point"}
}