{
  "type": "Feature",
  "properties": {
    "iso:country":"US",
    "sg:address":"129 Bethea Dr",
    "sg:city":"Fayetteville",
    "sg:classifiers":[
        {
            "category":"Professional",
            "type":"Services"
        },
        {
            "category":"Home & Garden",
            "subcategory":"Furniture",
            "type":"Retail Goods"
        }
    ],
    "sg:phone":"+1 678 817 1140",
    "sg:postcode":"30214",
    "sg:province":"GA",
    "sg:tags":[
        "top",
        "counter"
    ],
    "wof:name":"Unique Countertops Inc",
    "wof:placetype":"venue"
},
  "geometry": {"coordinates":[-84.44929999999999,33.499761],"type":"Point"}
}