{
  "type": "Feature",
  "properties": {
    "addr:full":"1336 Arlene Ct Lilburn GA 30047",
    "addr:housenumber":"1336",
    "addr:postcode":"30047",
    "addr:street":"Arlene Ct",
    "iso:country":"US",
    "sg:address":"1336 Arlene Ct",
    "sg:city":"Lilburn",
    "sg:classifiers":[
        {
            "category":"Manufacturing",
            "subcategory":"Signs",
            "type":"Manufacturing & Wholesale Goods"
        }
    ],
    "sg:phone":"+1 770 923 8510",
    "sg:postcode":"30047",
    "sg:province":"GA",
    "sg:tags":[
        "specialty",
        "mfg"
    ],
    "wof:name":"Stephens Signs & Specialties",
    "wof:placetype":"venue"
},
  "geometry": {"coordinates":[-84.106691,33.849285],"type":"Point"}
}