{
  "type": "Feature",
  "properties": {
    "addr:full":"1505 Johnson Ferry Rd Marietta GA 30062",
    "addr:housenumber":"1505",
    "addr:postcode":"30062",
    "addr:street":"Johnson Ferry Rd",
    "iso:country":"US",
    "sg:address":"1505 Johnson Ferry Rd",
    "sg:city":"Marietta",
    "sg:classifiers":[
        {
            "category":"Health Services",
            "subcategory":"Doctor",
            "type":"Services"
        },
        {
            "category":"Health Services",
            "subcategory":"Clinic",
            "type":"Services"
        }
    ],
    "sg:phone":"+1 770 977 1322",
    "sg:postcode":"30062",
    "sg:province":"GA",
    "sg:tags":[
        "counseling",
        "mental"
    ],
    "wof:name":"Rogers Steven D PHD",
    "wof:placetype":"venue"
},
  "geometry": {"coordinates":[-84.427002,33.987499],"type":"Point"}
}