{
  "type": "Feature",
  "properties": {
    "iso:country":"US",
    "sg:address":"899 Martin Luther King Jr Dr SW",
    "sg:city":"Atlanta",
    "sg:classifiers":[
        {
            "category":"Personal",
            "subcategory":"Beauty Salon",
            "type":"Services"
        }
    ],
    "sg:phone":"+1 404 659 8026",
    "sg:postcode":"30314",
    "sg:province":"GA",
    "sg:tags":[
        "shop"
    ],
    "wof:name":"Sammy Feathrstnes Hair Designs",
    "wof:placetype":"venue"
},
  "geometry": {"coordinates":[-84.41595,33.754785],"type":"Point"}
}