{
  "type": "Feature",
  "properties": {
    "addr:full":"4705 Canton Rd Marietta GA 30066",
    "addr:housenumber":"4705",
    "addr:postcode":"30066",
    "addr:street":"Canton Rd",
    "iso:country":"US",
    "sg:address":"4705 Canton Rd",
    "sg:city":"Marietta",
    "sg:classifiers":[
        {
            "category":"Retail",
            "subcategory":"Auto Rental",
            "type":"Services"
        }
    ],
    "sg:phone":"+1 770 592 2010",
    "sg:postcode":"30066",
    "sg:province":"GA",
    "sg:tags":[
        "car"
    ],
    "wof:name":"Nations Car Rental",
    "wof:placetype":"venue"
},
  "geometry": {"coordinates":[-84.52130099999999,34.0658],"type":"Point"}
}