{
  "type": "Feature",
  "properties": {
    "addr:full":"6400 Hillandale Dr Lithonia GA 30058",
    "addr:housenumber":"6400",
    "addr:postcode":"30058",
    "addr:street":"Hillandale Dr",
    "iso:country":"US",
    "sg:address":"6400 Hillandale Dr",
    "sg:city":"Lithonia",
    "sg:classifiers":[
        {
            "category":"Home & Garden",
            "subcategory":"Carpets & Floor Coverings",
            "type":"Retail Goods"
        },
        {
            "category":"Building & Trades",
            "subcategory":"Construction",
            "type":"Services"
        }
    ],
    "sg:phone":"+1 770 484 0014",
    "sg:postcode":"30058",
    "sg:province":"GA",
    "sg:tags":[
        "flooring",
        "ceramic",
        "rug",
        "vinyl",
        "tile",
        "dealer"
    ],
    "sg:website":"www.flooringandceramic.com",
    "wof:name":"Flooring & Ceramic Warehouse",
    "wof:placetype":"venue"
},
  "geometry": {"coordinates":[-84.11820299999999,33.70246],"type":"Point"}
}