{
  "type": "Feature",
  "properties": {
    "iso:country":"US",
    "sg:address":"818 1st Ave NE",
    "sg:city":"Cairo",
    "sg:classifiers":[
        {
            "category":"Banks & Credit Unions",
            "subcategory":"Bank",
            "type":"Services"
        }
    ],
    "sg:phone":"+1 229 377 8965",
    "sg:postcode":"39828",
    "sg:province":"GA",
    "sg:tags":[
        "federally",
        "chartered"
    ],
    "wof:name":"Five Star Credit Union",
    "wof:placetype":"venue"
},
  "geometry": {"coordinates":[-84.196926,30.877539],"type":"Point"}
}