{
  "type": "Feature",
  "properties": {
    "addr:full":"518 Chitwood Rd Baldwin GA 30511",
    "addr:housenumber":"518",
    "addr:postcode":"30511",
    "addr:street":"Chitwood Rd",
    "iso:country":"US",
    "sg:address":"518 Chitwood Rd",
    "sg:city":"Baldwin",
    "sg:classifiers":[
        {
            "category":"Professional",
            "subcategory":"Computer Services",
            "type":"Services"
        }
    ],
    "sg:phone":"+1 706 886 3935",
    "sg:postcode":"30511",
    "sg:province":"GA",
    "sg:tags":[
        "custom",
        "contractor",
        "programing",
        "trade"
    ],
    "wof:name":"Jl Enterprises",
    "wof:placetype":"venue"
},
  "geometry": {"coordinates":[-83.425321,34.448407],"type":"Point"}
}