{
  "type": "Feature",
  "properties": {
    "iso:country":"US",
    "sg:address":"949 Hwy 85 Con",
    "sg:city":"Brooks",
    "sg:classifiers":[
        {
            "category":"Building & Trades",
            "subcategory":"Plumbing",
            "type":"Services"
        }
    ],
    "sg:phone":"+1 770 716 6816",
    "sg:postcode":"30205",
    "sg:province":"GA",
    "sg:tags":[
        "conditioning",
        "air",
        "system",
        "contractor"
    ],
    "wof:name":"LTI Heating & Air Inc",
    "wof:placetype":"venue"
},
  "geometry": {"coordinates":[-84.45989299999999,33.293673],"type":"Point"}
}