{
  "type": "Feature",
  "properties": {
    "iso:country":"US",
    "sg:address":"2544 McClave Dr",
    "sg:city":"Doraville",
    "sg:classifiers":[
        {
            "category":"Real Estate",
            "subcategory":"Real Estate Operator",
            "type":"Services"
        }
    ],
    "sg:phone":"+1 770 451 8778",
    "sg:postcode":"30340",
    "sg:province":"GA",
    "sg:tags":[
        "building",
        "parks"
    ],
    "wof:name":"Pinetree Offices",
    "wof:placetype":"venue"
},
  "geometry": {"coordinates":[-84.284267,33.891688],"type":"Point"}
}