{
  "type": "Feature",
  "properties": {
    "addr:full":"110 Ball Ground Hwy Canton GA 30114",
    "addr:housenumber":"110",
    "addr:postcode":"30114",
    "addr:street":"Ball Ground Hwy",
    "iso:country":"US",
    "sg:address":"110 Ball Ground Hwy",
    "sg:city":"Canton",
    "sg:classifiers":[
        {
            "category":"Personal",
            "subcategory":"Beauty Salon",
            "type":"Services"
        }
    ],
    "sg:phone":"+1 770 720 7914",
    "sg:postcode":"30114",
    "sg:province":"GA",
    "sg:tags":[
        "shop"
    ],
    "wof:name":"Planet Nails",
    "wof:placetype":"venue"
},
  "geometry": {"coordinates":[-84.490784,34.243846],"type":"Point"}
}