{
  "type": "Feature",
  "properties": {
    "addr:full":"769 Lawton St SW Atlanta GA 30310",
    "addr:housenumber":"769",
    "addr:postcode":"30310",
    "addr:street":"Lawton St Sw",
    "iso:country":"US",
    "sg:address":"769 Lawton St SW",
    "sg:city":"Atlanta",
    "sg:classifiers":[
        {
            "category":"Communications",
            "subcategory":"Film & Video Production",
            "type":"Services"
        }
    ],
    "sg:phone":"+1 678 913 3853",
    "sg:postcode":"30310",
    "sg:province":"GA",
    "sg:tags":[
        "tv",
        "services-commercial",
        "companies-film",
        "radio"
    ],
    "wof:name":"Red Zone Productions",
    "wof:placetype":"venue"
},
  "geometry": {"coordinates":[-84.423348,33.73351],"type":"Point"}
}