{
  "type": "Feature",
  "properties": {
    "addr:full":"5775 Bethelview Rd Cumming GA 30040",
    "addr:housenumber":"5775",
    "addr:postcode":"30040",
    "addr:street":"Bethelview Rd",
    "iso:country":"US",
    "sg:address":"5775 Bethelview Rd",
    "sg:city":"Cumming",
    "sg:classifiers":[
        {
            "category":"Home & Garden",
            "subcategory":"Building Materials",
            "type":"Retail Goods"
        },
        {
            "category":"Mining & Drilling",
            "type":"Manufacturing & Wholesale Goods"
        }
    ],
    "sg:phone":"+1 678 513 7242",
    "sg:postcode":"30040",
    "sg:province":"GA",
    "sg:tags":[
        "injection",
        "metal",
        "fabrication",
        "molding"
    ],
    "sg:website":"www.headrick.net",
    "wof:name":"Headrick Building Products Inc",
    "wof:placetype":"venue"
},
  "geometry": {"coordinates":[-84.178679,34.168009],"type":"Point"}
}