{
  "type": "Feature",
  "properties": {
    "addr:full":"5236 Old Norcross Rd Norcross GA 30071",
    "addr:housenumber":"5236",
    "addr:postcode":"30071",
    "addr:street":"Old Norcross Rd",
    "iso:country":"US",
    "sg:address":"5236 Old Norcross Rd",
    "sg:city":"Norcross",
    "sg:classifiers":[
        {
            "category":"Building & Trades",
            "subcategory":"Plumbing",
            "type":"Services"
        }
    ],
    "sg:phone":"+1 770 457 1208",
    "sg:postcode":"30071",
    "sg:province":"GA",
    "sg:tags":[
        "contractor"
    ],
    "wof:name":"M & W Mechanical Contractors",
    "wof:placetype":"venue"
},
  "geometry": {"coordinates":[-84.19595,33.949276],"type":"Point"}
}