{
  "type": "Feature",
  "properties": {
    "addr:full":"303 N Main St La Fayette GA 30728",
    "addr:housenumber":"303",
    "addr:postcode":"30728",
    "addr:street":"N Main St;Fayette",
    "iso:country":"US",
    "sg:address":"303 N Main St",
    "sg:city":"La Fayette",
    "sg:classifiers":[
        {
            "category":"Retail",
            "subcategory":"Auto Repair",
            "type":"Services"
        }
    ],
    "sg:phone":"+1 706 638 5936",
    "sg:postcode":"30728",
    "sg:province":"GA",
    "sg:tags":[
        "exhaust"
    ],
    "wof:name":"Maxi Muffler Shop",
    "wof:placetype":"venue"
},
  "geometry": {"coordinates":[-85.281533,34.708593],"type":"Point"}
}