{
  "type": "Feature",
  "properties": {
    "addr:full":"311 W 4th St Waynesboro GA 30830",
    "addr:housenumber":"311",
    "addr:postcode":"30830",
    "addr:street":"W 4Th St",
    "iso:country":"US",
    "sg:address":"311 W 4th St",
    "sg:city":"Waynesboro",
    "sg:classifiers":[
        {
            "category":"Health Services",
            "subcategory":"Doctor",
            "type":"Services"
        }
    ],
    "sg:phone":"+1 706 554 2176",
    "sg:postcode":"30830",
    "sg:province":"GA",
    "sg:tags":[
        "physician",
        "family",
        "practice",
        "surgeons",
        "medicine",
        "surgeon"
    ],
    "wof:name":"Murray, B Lamar Dr",
    "wof:placetype":"venue"
},
  "geometry": {"coordinates":[-82.01370300000001,33.083654],"type":"Point"}
}