{
  "type": "Feature",
  "properties": {
    "iso:country":"US",
    "sg:address":"2133 Lawrencevlle Swne Rd",
    "sg:city":"Suwanee",
    "sg:classifiers":[
        {
            "category":"Restaurant",
            "type":"Food & Drink"
        }
    ],
    "sg:phone":"+1 678 985 1968",
    "sg:postcode":"30024",
    "sg:province":"GA",
    "sg:tags":[
        "chinese"
    ],
    "wof:name":"Royal Bamboo China Bistro",
    "wof:placetype":"venue"
},
  "geometry": {"coordinates":[-84.040398,34.0033],"type":"Point"}
}