{
  "type": "Feature",
  "properties": {
    "addr:full":"75 Sweetwater Way Powder Springs GA 30127",
    "addr:housenumber":"75",
    "addr:postcode":"30127",
    "addr:street":"Sweetwater Way",
    "iso:country":"US",
    "sg:address":"75 Sweetwater Way",
    "sg:city":"Powder Springs",
    "sg:classifiers":[
        {
            "category":"Retail",
            "subcategory":"Repair Shop",
            "type":"Services"
        }
    ],
    "sg:phone":"+1 770 947 7059",
    "sg:postcode":"30127",
    "sg:province":"GA",
    "wof:name":"Murphhys Cleaning Inc",
    "wof:placetype":"venue"
},
  "geometry": {"coordinates":[-84.75422399999999,33.796227],"type":"Point"}
}