{
  "type": "Feature",
  "properties": {
    "iso:country":"US",
    "sg:address":"6360 Crossroads Rd",
    "sg:city":"Cumming",
    "sg:classifiers":[
        {
            "category":"Building & Trades",
            "subcategory":"Landscaping Services",
            "type":"Services"
        }
    ],
    "sg:phone":"+1 770 886 7694",
    "sg:postcode":"30041",
    "sg:province":"GA",
    "sg:tags":[
        "landscape",
        "contractor"
    ],
    "wof:name":"Mullinax Landscape Svcs",
    "wof:placetype":"venue"
},
  "geometry": {"coordinates":[-84.058361,34.316849],"type":"Point"}
}