{
  "type": "Feature",
  "properties": {
    "iso:country":"US",
    "sg:address":"816 New Franklin Rd",
    "sg:city":"Lagrange",
    "sg:classifiers":[
        {
            "category":"Shopping",
            "subcategory":"Used Merchandise",
            "type":"Retail Goods"
        }
    ],
    "sg:phone":"+1 706 884 2855",
    "sg:postcode":"30240",
    "sg:province":"GA",
    "sg:tags":[
        "shop",
        "consignment"
    ],
    "wof:name":"Carousel Consignments",
    "wof:placetype":"venue"
},
  "geometry": {"coordinates":[-85.028274,33.066507],"type":"Point"}
}