{
  "type": "Feature",
  "properties": {
    "iso:country":"US",
    "sg:address":"2644 Woodwin Road",
    "sg:city":"Atlanta",
    "sg:classifiers":[
        {
            "category":"Building & Trades",
            "subcategory":"Construction",
            "type":"Services"
        }
    ],
    "sg:phone":"+1 770 234 0911",
    "sg:postcode":"30360",
    "sg:province":"GA",
    "sg:tags":[
        "contractor"
    ],
    "sg:website":"www.constructionahead.net/",
    "wof:name":"Construction Ahead",
    "wof:placetype":"venue"
},
  "geometry": {"coordinates":[-84.279511,33.918717],"type":"Point"}
}