{
  "type": "Feature",
  "properties": {
    "iso:country":"US",
    "sg:address":"4394 Hugh Howell Road",
    "sg:city":"Tucker",
    "sg:classifiers":[
        {
            "category":"Restaurant",
            "type":"Food & Drink"
        }
    ],
    "sg:phone":"+1 770 493 8002",
    "sg:postcode":"30084",
    "sg:province":"GA",
    "sg:tags":[
        "fusion",
        "sushi",
        "bar",
        "thai",
        "asian"
    ],
    "sg:website":"www.maithaiatlanta.com",
    "wof:name":"Mai Thai Restuarant",
    "wof:placetype":"venue"
},
  "geometry": {"coordinates":[-84.208975,33.85356],"type":"Point"}
}