{
  "type": "Feature",
  "properties": {
    "iso:country":"US",
    "sg:address":"9775 Medlock Bridge",
    "sg:city":"Johns Creek",
    "sg:classifiers":[
        {
            "category":"Health Services",
            "subcategory":"Dentist",
            "type":"Services"
        }
    ],
    "sg:phone":"+1 770 476 9595",
    "sg:postcode":"30097",
    "sg:province":"GA",
    "sg:website":"www.dentfirst.com",
    "wof:name":"Dent 1st",
    "wof:placetype":"venue"
},
  "geometry": {"coordinates":[-84.190152,34.015514],"type":"Point"}
}