{
  "type": "Feature",
  "properties": {
    "iso:country":"US",
    "sg:address":"147 S Mc Donough St",
    "sg:city":"Jonesboro",
    "sg:classifiers":[
        {
            "category":"Social Services",
            "type":"Services"
        }
    ],
    "sg:phone":"+1 770 477 8848",
    "sg:postcode":"30236",
    "sg:province":"GA",
    "wof:name":"Jonesboro Lighthouse Community",
    "wof:placetype":"venue"
},
  "geometry": {"coordinates":[-84.35402499999999,33.521305],"type":"Point"}
}