{
  "type": "Feature",
  "properties": {
    "addr:full":"105 Justice Blvd Griffin GA 30223",
    "addr:housenumber":"105",
    "addr:postcode":"30223",
    "addr:street":"Justice Blvd",
    "iso:country":"US",
    "sg:address":"105 Justice Blvd",
    "sg:city":"Griffin",
    "sg:classifiers":[
        {
            "category":"Government",
            "subcategory":"Office",
            "type":"Public Place"
        }
    ],
    "sg:phone":"+1 770 228 7350",
    "sg:postcode":"30223",
    "sg:province":"GA",
    "wof:name":"Griffin Regional Youth Dev Ctr",
    "wof:placetype":"venue"
},
  "geometry": {"coordinates":[-84.29216,33.238719],"type":"Point"}
}