{
  "type": "Feature",
  "properties": {
    "addr:full":"6301 Woodrow Rd Lithonia GA 30038",
    "addr:housenumber":"6301",
    "addr:postcode":"30038",
    "addr:street":"Woodrow Rd",
    "iso:country":"US",
    "sg:address":"6301 Woodrow Rd",
    "sg:city":"Lithonia",
    "sg:classifiers":[
        {
            "category":"Education",
            "subcategory":"School",
            "type":"Public Place"
        }
    ],
    "sg:phone":"+1 770 484 6779",
    "sg:postcode":"30038",
    "sg:province":"GA",
    "sg:tags":[
        "k-",
        "private"
    ],
    "wof:name":"Academy Of America",
    "wof:placetype":"venue"
},
  "geometry": {"coordinates":[-84.134826,33.694022],"type":"Point"}
}