{
  "type": "Feature",
  "properties": {
    "addr:full":"811 Pickens Industrial Dr Marietta GA 30062",
    "addr:housenumber":"811",
    "addr:postcode":"30062",
    "addr:street":"Pickens Industrial Dr",
    "iso:country":"US",
    "sg:address":"811 Pickens Industrial Dr",
    "sg:city":"Marietta",
    "sg:classifiers":[
        {
            "category":"Professional",
            "subcategory":"Business Services",
            "type":"Services"
        }
    ],
    "sg:phone":"+1 770 423 9575",
    "sg:postcode":"30062",
    "sg:province":"GA",
    "sg:tags":[
        "part",
        "mfg"
    ],
    "wof:name":"Casablanca Design",
    "wof:placetype":"venue"
},
  "geometry": {"coordinates":[-84.526839,33.972264],"type":"Point"}
}