{
  "type": "Feature",
  "properties": {
    "iso:country":"US",
    "sg:address":"2031 Blankenbaker Rd",
    "sg:city":"Statesboro",
    "sg:classifiers":[
        {
            "category":"Real Estate",
            "subcategory":"Developer",
            "type":"Services"
        }
    ],
    "sg:phone":"+1 912 852 9709",
    "sg:postcode":"30458",
    "sg:province":"GA",
    "wof:name":"B & C Developers LLC",
    "wof:placetype":"venue"
},
  "geometry": {"coordinates":[-81.87657900000001,32.432976],"type":"Point"}
}