{
  "type": "Feature",
  "properties": {
    "iso:country":"US",
    "sg:address":"141 W Wieuca Rd NE",
    "sg:city":"Atlanta",
    "sg:classifiers":[
        {
            "category":"Health Services",
            "subcategory":"Chiropractor",
            "type":"Services"
        }
    ],
    "sg:phone":"+1 404 257 0310",
    "sg:postcode":"30342",
    "sg:province":"GA",
    "wof:name":"Dicker Diane Dr",
    "wof:placetype":"venue"
},
  "geometry": {"coordinates":[-84.382103,33.877998],"type":"Point"}
}