{
  "type": "Feature",
  "properties": {
    "addr:full":"137 N Lumpkin St Athens GA 30601",
    "addr:housenumber":"137",
    "addr:postcode":"30601",
    "addr:street":"N Lumpkin St",
    "iso:country":"US",
    "sg:address":"137 N Lumpkin St",
    "sg:city":"Athens",
    "sg:classifiers":[
        {
            "category":"Bars & Pubs",
            "type":"Food & Drink"
        }
    ],
    "sg:phone":"+1 706 613 2324",
    "sg:postcode":"30601",
    "sg:province":"GA",
    "sg:tags":[
        "drinking"
    ],
    "wof:name":"Roadhouse",
    "wof:placetype":"venue"
},
  "geometry": {"coordinates":[-83.37703500000001,33.957878],"type":"Point"}
}