{
  "type": "Feature",
  "properties": {
    "iso:country":"US",
    "sg:address":"7842 Persimmon Tree Rd",
    "sg:city":"Lula",
    "sg:classifiers":[
        {
            "category":"Professional",
            "subcategory":"Art Services",
            "type":"Services"
        }
    ],
    "sg:phone":"+1 770 983 2154",
    "sg:postcode":"30554",
    "sg:province":"GA",
    "sg:tags":[
        "photographer"
    ],
    "wof:name":"Brandy Oliver Photography",
    "wof:placetype":"venue"
},
  "geometry": {"coordinates":[-83.712243,34.456013],"type":"Point"}
}