{
  "type": "Feature",
  "properties": {
    "addr:full":"416 Baytree Rd Valdosta GA 31602",
    "addr:housenumber":"416",
    "addr:postcode":"31602",
    "addr:street":"Baytree Rd",
    "iso:country":"US",
    "sg:address":"416 Baytree Rd",
    "sg:city":"Valdosta",
    "sg:classifiers":[
        {
            "category":"Professional",
            "subcategory":"Lawyer & Legal Services",
            "type":"Services"
        }
    ],
    "sg:phone":"+1 229 241 1767",
    "sg:postcode":"31602",
    "sg:province":"GA",
    "sg:tags":[
        "firm",
        "law"
    ],
    "wof:name":"Kenneth S Nugent PC",
    "wof:placetype":"venue"
},
  "geometry": {"coordinates":[-83.29228000000001,30.846924],"type":"Point"}
}