{
  "type": "Feature",
  "properties": {
    "addr:full":"3241 Glynn Ave Brunswick GA 31520",
    "addr:housenumber":"3241",
    "addr:postcode":"31520",
    "addr:street":"Glynn Ave",
    "iso:country":"US",
    "sg:address":"3241 Glynn Ave",
    "sg:city":"Brunswick",
    "sg:classifiers":[
        {
            "category":"Restaurant",
            "type":"Food & Drink"
        }
    ],
    "sg:phone":"+1 912 554 1999",
    "sg:postcode":"31520",
    "sg:province":"GA",
    "wof:name":"Eddie's Country Buffet",
    "wof:placetype":"venue"
},
  "geometry": {"coordinates":[-81.473641,31.177428],"type":"Point"}
}