{
  "type": "Feature",
  "properties": {
    "addr:full":"1479 Fieldgreen Overlook Stone Mountain GA 30088",
    "addr:housenumber":"1479",
    "addr:postcode":"30088",
    "addr:street":"Fieldgreen Overlook",
    "iso:country":"US",
    "sg:address":"1479 Fieldgreen Overlook",
    "sg:city":"Stone Mountain",
    "sg:classifiers":[
        {
            "category":"Professional",
            "subcategory":"Lawyer & Legal Services",
            "type":"Services"
        }
    ],
    "sg:phone":"+1 770 593 8728",
    "sg:postcode":"30088",
    "sg:province":"GA",
    "wof:name":"Lancy B Shakir",
    "wof:placetype":"venue"
},
  "geometry": {"coordinates":[-84.18566,33.750075],"type":"Point"}
}