{
  "type": "Feature",
  "properties": {
    "addr:full":"1498 Benson Rd Dallas GA 30132",
    "addr:housenumber":"1498",
    "addr:postcode":"30132",
    "addr:street":"Benson Rd",
    "iso:country":"US",
    "sg:address":"1498 Benson Rd",
    "sg:city":"Dallas",
    "sg:classifiers":[
        {
            "category":"Retail",
            "subcategory":"Auto Repair",
            "type":"Services"
        }
    ],
    "sg:phone":"+1 770 505 3949",
    "sg:postcode":"30132",
    "sg:province":"GA",
    "sg:tags":[
        "automotive"
    ],
    "wof:name":"Tow Technol On Wheels",
    "wof:placetype":"venue"
},
  "geometry": {"coordinates":[-84.84840699999999,34.022514],"type":"Point"}
}