{
  "type": "Feature",
  "properties": {
    "iso:country":"US",
    "sg:address":"306 S Manilla Ave",
    "sg:city":"Douglas",
    "sg:classifiers":[
        {
            "category":"Education",
            "subcategory":"Dance Studio",
            "type":"Public Place"
        },
        {
            "category":"Recreation",
            "type":"Entertainment"
        }
    ],
    "sg:phone":"+1 912 384 2878",
    "sg:postcode":"31533",
    "sg:province":"GA",
    "sg:tags":[
        "instruction",
        "dancing"
    ],
    "wof:name":"Regina's School Of Dance",
    "wof:placetype":"venue"
},
  "geometry": {"coordinates":[-82.853807,31.506502],"type":"Point"}
}