{
  "type": "Feature",
  "properties": {
    "iso:country":"US",
    "sg:address":"450 Brisco Blvd NE",
    "sg:city":"Lawrenceville",
    "sg:classifiers":[
        {
            "category":"Airport",
            "type":"Transportation"
        }
    ],
    "sg:phone":"+1 770 554 0508",
    "sg:postcode":"30045",
    "sg:province":"GA",
    "sg:tags":[
        "aircraft",
        "upholsterer"
    ],
    "wof:name":"Airtech Interiors",
    "wof:placetype":"venue"
},
  "geometry": {"coordinates":[-83.96219000000001,33.975227],"type":"Point"}
}