{
  "type": "Feature",
  "properties": {
    "iso:country":"US",
    "sg:address":"365 Lucas Rd SW",
    "sg:city":"Cartersville",
    "sg:classifiers":[
        {
            "category":"Building & Trades",
            "subcategory":"Plumbing",
            "type":"Services"
        },
        {
            "category":"Building & Trades",
            "subcategory":"Cleaning & Sanitation",
            "type":"Services"
        }
    ],
    "sg:phone":"+1 770 480 5037",
    "sg:postcode":"30120",
    "sg:province":"GA",
    "sg:tags":[
        "tanks-treatment",
        "tank",
        "system",
        "septic",
        "supply"
    ],
    "wof:name":"Cox, Billy",
    "wof:placetype":"venue"
},
  "geometry": {"coordinates":[-84.876167,34.096519],"type":"Point"}
}