{
  "type": "Feature",
  "properties": {
    "iso:country":"US",
    "sg:address":"2066 Chestnut Hill Cir",
    "sg:city":"Decatur",
    "sg:classifiers":[
        {
            "category":"Organizations",
            "subcategory":"Religious Organization",
            "type":"Services"
        }
    ],
    "sg:phone":"+1 404 289 3700",
    "sg:postcode":"30032",
    "sg:province":"GA",
    "sg:tags":[
        "church"
    ],
    "wof:name":"Living Waters Music",
    "wof:placetype":"venue"
},
  "geometry": {"coordinates":[-84.241722,33.73052],"type":"Point"}
}