{
  "type": "Feature",
  "properties": {
    "addr:full":"2003 Royal Ct Atlanta GA 30341",
    "addr:housenumber":"2003",
    "addr:postcode":"30341",
    "addr:street":"Royal Ct",
    "iso:country":"US",
    "sg:address":"2003 Royal Ct",
    "sg:city":"Atlanta",
    "sg:classifiers":[
        {
            "category":"Professional",
            "subcategory":"Management & Consulting",
            "type":"Services"
        }
    ],
    "sg:phone":"+1 770 455 7371",
    "sg:postcode":"30341",
    "sg:province":"GA",
    "sg:tags":[
        "business"
    ],
    "wof:name":"Container Science Inc",
    "wof:placetype":"venue"
},
  "geometry": {"coordinates":[-84.307298,33.91819],"type":"Point"}
}