{
  "type": "Feature",
  "properties": {
    "addr:full":"1078 Polo Club Dr Marietta GA 30064",
    "addr:housenumber":"1078",
    "addr:postcode":"30064",
    "addr:street":"Polo Club Dr",
    "iso:country":"US",
    "sg:address":"1078 Polo Club Dr",
    "sg:city":"Marietta",
    "sg:classifiers":[
        {
            "category":"Food & Beverages",
            "subcategory":"Specialty",
            "type":"Retail Goods"
        }
    ],
    "sg:phone":"+1 770 422 6373",
    "sg:postcode":"30064",
    "sg:province":"GA",
    "sg:tags":[
        "water",
        "bulk",
        "company"
    ],
    "wof:name":"ACS Water Co Inc",
    "wof:placetype":"venue"
},
  "geometry": {"coordinates":[-84.62727599999999,33.98055],"type":"Point"}
}