{
  "type": "Feature",
  "properties": {
    "addr:full":"102 N Fair St Calhoun GA 30701",
    "addr:housenumber":"102",
    "addr:postcode":"30701",
    "addr:street":"N Fair St",
    "iso:country":"US",
    "sg:address":"102 N Fair St",
    "sg:city":"Calhoun",
    "sg:classifiers":[
        {
            "category":"Retail",
            "subcategory":"Car Wash",
            "type":"Services"
        }
    ],
    "sg:phone":"+1 706 629 3777",
    "sg:postcode":"30701",
    "sg:province":"GA",
    "sg:tags":[
        "carwash"
    ],
    "wof:name":"Billy Gs Car Wash",
    "wof:placetype":"venue"
},
  "geometry": {"coordinates":[-84.957928,34.503761],"type":"Point"}
}