{
  "type": "Feature",
  "properties": {
    "addr:full":"4004 Dover Ave Alpharetta GA 30004",
    "addr:housenumber":"4004",
    "addr:postcode":"30004",
    "addr:street":"Dover Ave",
    "iso:country":"US",
    "sg:address":"4004 Dover Ave",
    "sg:city":"Alpharetta",
    "sg:classifiers":[
        {
            "category":"Professional",
            "type":"Services"
        }
    ],
    "sg:phone":"+1 770 667 9918",
    "sg:postcode":"30004",
    "sg:province":"GA",
    "wof:name":"Jim Harrington Garden Designs",
    "wof:placetype":"venue"
},
  "geometry": {"coordinates":[-84.30053700000001,34.092783],"type":"Point"}
}