{
  "type": "Feature",
  "properties": {
    "iso:country":"US",
    "sg:address":"38 Henry Nix Rd",
    "sg:city":"Cleveland",
    "sg:classifiers":[
        {
            "category":"Retail",
            "subcategory":"Auto Repair",
            "type":"Services"
        }
    ],
    "sg:phone":"+1 706 865 9275",
    "sg:postcode":"30528",
    "sg:province":"GA",
    "sg:tags":[
        "body",
        "painting",
        "repairing",
        "automobile"
    ],
    "wof:name":"Chri's Paint & Body Shop",
    "wof:placetype":"venue"
},
  "geometry": {"coordinates":[-83.73276,34.590168],"type":"Point"}
}