{
  "type": "Feature",
  "properties": {
    "iso:country":"US",
    "sg:address":"545 Devonshire Walk Dr",
    "sg:city":"Suwanee",
    "sg:classifiers":[
        {
            "category":"Manufacturing",
            "subcategory":"Electronics",
            "type":"Manufacturing & Wholesale Goods"
        }
    ],
    "sg:phone":"+1 770 277 2939",
    "sg:postcode":"30024",
    "sg:province":"GA",
    "sg:tags":[
        "communications",
        "equipment"
    ],
    "wof:name":"Carrier Access Corp",
    "wof:placetype":"venue"
},
  "geometry": {"coordinates":[-84.042299,34.014713],"type":"Point"}
}