{
  "type": "Feature",
  "properties": {
    "iso:country":"US",
    "sg:address":"5000 Davis Love Dr",
    "sg:city":"Cumming",
    "sg:classifiers":[
        {
            "category":"Arena",
            "subcategory":"Sports Club",
            "type":"Entertainment"
        },
        {
            "category":"Sports & Exercise",
            "subcategory":"Sports Center",
            "type":"Entertainment"
        },
        {
            "category":"Sports & Exercise",
            "subcategory":"Golf",
            "type":"Entertainment"
        }
    ],
    "sg:phone":"+1 678 513 1000",
    "sg:postcode":"30041",
    "sg:province":"GA",
    "sg:tags":[
        "courses-private",
        "course",
        "instruction"
    ],
    "wof:name":"Windermere Golf Club",
    "wof:placetype":"venue"
},
  "geometry": {"coordinates":[-84.12494700000001,34.13768],"type":"Point"}
}