{
  "type": "Feature",
  "properties": {
    "addr:full":"545 Lorene Dr SW Marietta GA 30060",
    "addr:housenumber":"545",
    "addr:postcode":"30060",
    "addr:street":"Lorene Dr Sw",
    "iso:country":"US",
    "sg:address":"545 Lorene Dr SW",
    "sg:city":"Marietta",
    "sg:classifiers":[
        {
            "category":"Education",
            "subcategory":"School",
            "type":"Public Place"
        }
    ],
    "sg:phone":"+1 770 434 1320",
    "sg:postcode":"30060",
    "sg:province":"GA",
    "sg:tags":[
        "high",
        "middle",
        "elementary"
    ],
    "wof:name":"Open Bible Ministries",
    "wof:placetype":"venue"
},
  "geometry": {"coordinates":[-84.569801,33.900799],"type":"Point"}
}