{
  "type": "Feature",
  "properties": {
    "addr:full":"40 Macon St Mcdonough GA 30253",
    "addr:housenumber":"40",
    "addr:postcode":"30253",
    "addr:street":"Macon St",
    "iso:country":"US",
    "sg:address":"40 Macon St",
    "sg:city":"Mcdonough",
    "sg:classifiers":[
        {
            "category":"Real Estate",
            "subcategory":"Real Estate Agent",
            "type":"Services"
        }
    ],
    "sg:phone":"+1 770 898 3949",
    "sg:postcode":"30253",
    "sg:province":"GA",
    "sg:tags":[
        "appraiser"
    ],
    "wof:name":"Eagles Landing Appraisal Group",
    "wof:placetype":"venue"
},
  "geometry": {"coordinates":[-84.146306,33.446483],"type":"Point"}
}