{
  "type": "Feature",
  "properties": {
    "addr:full":"305 W Belmont Dr Calhoun GA 30701",
    "addr:housenumber":"305",
    "addr:postcode":"30701",
    "addr:street":"W Belmont Dr",
    "iso:country":"US",
    "sg:address":"305 W Belmont Dr",
    "sg:city":"Calhoun",
    "sg:classifiers":[
        {
            "category":"Cinema",
            "subcategory":"Movie Rental",
            "type":"Entertainment"
        }
    ],
    "sg:phone":"+1 706 629 9126",
    "sg:postcode":"30701",
    "sg:province":"GA",
    "sg:tags":[
        "video"
    ],
    "wof:name":"Movie Gallery",
    "wof:placetype":"venue"
},
  "geometry": {"coordinates":[-84.93919699999999,34.479823],"type":"Point"}
}