{
  "type": "Feature",
  "properties": {
    "addr:full":"1781 15th St Augusta GA 30901",
    "addr:housenumber":"1781",
    "addr:postcode":"30901",
    "addr:street":"15Th St",
    "iso:country":"US",
    "sg:address":"1781 15th St",
    "sg:city":"Augusta",
    "sg:classifiers":[
        {
            "category":"Building & Trades",
            "subcategory":"Cleaning & Sanitation",
            "type":"Services"
        }
    ],
    "sg:phone":"+1 706 737 7189",
    "sg:postcode":"30901",
    "sg:province":"GA",
    "sg:tags":[
        "cleaning-industrial",
        "contractor"
    ],
    "sg:website":"http://www.richmond.k12.ga.us",
    "wof:name":"Maintenance Department",
    "wof:placetype":"venue"
},
  "geometry": {"coordinates":[-81.99964900000001,33.45377],"type":"Point"}
}