{
  "type": "Feature",
  "properties": {
    "iso:country":"US",
    "sg:address":"5517 Dahlonega Hwy",
    "sg:city":"Clermont",
    "sg:classifiers":[
        {
            "category":"Building & Trades",
            "subcategory":"Construction",
            "type":"Services"
        }
    ],
    "sg:phone":"+1 770 983 9119",
    "sg:postcode":"30527",
    "sg:province":"GA",
    "sg:tags":[
        "general",
        "contractor"
    ],
    "wof:name":"Rite Way Construction",
    "wof:placetype":"venue"
},
  "geometry": {"coordinates":[-83.81594200000001,34.461607],"type":"Point"}
}