{
  "type": "Feature",
  "properties": {
    "iso:country":"US",
    "sg:address":"125 Plantation Centre Dr S",
    "sg:city":"Macon",
    "sg:classifiers":[
        {
            "category":"Professional",
            "subcategory":"Accounting & Tax Preparation",
            "type":"Services"
        },
        {
            "category":"Professional",
            "subcategory":"Lawyer & Legal Services",
            "type":"Services"
        }
    ],
    "sg:phone":"+1 478 474 4277",
    "sg:postcode":"31210",
    "sg:province":"GA",
    "sg:tags":[
        "attorney",
        "taxes-consultants",
        "corporation",
        "partnership",
        "representative",
        "law",
        "bankruptcy"
    ],
    "wof:name":"Weinberg Neal",
    "wof:placetype":"venue"
},
  "geometry": {"coordinates":[-83.761472,32.876525],"type":"Point"}
}