{
  "type": "Feature",
  "properties": {
    "iso:country":"US",
    "sg:address":"4186 Nahunta Ct",
    "sg:city":"Norcross",
    "sg:classifiers":[
        {
            "category":"Building & Trades",
            "subcategory":"Landscaping Services",
            "type":"Services"
        }
    ],
    "sg:phone":"+1 770 448 4892",
    "sg:postcode":"30092",
    "sg:province":"GA",
    "sg:tags":[
        "landscape",
        "contractor"
    ],
    "wof:name":"Garden Splendor",
    "wof:placetype":"venue"
},
  "geometry": {"coordinates":[-84.24130599999999,33.979723],"type":"Point"}
}