{
  "type": "Feature",
  "properties": {
    "iso:country":"US",
    "sg:address":"611 Cook St",
    "sg:city":"Royston",
    "sg:classifiers":[
        {
            "category":"Health Services",
            "subcategory":"Doctor",
            "type":"Services"
        }
    ],
    "sg:phone":"+1 706 245 1460",
    "sg:postcode":"30662",
    "sg:province":"GA",
    "sg:tags":[
        "physician",
        "surgeon"
    ],
    "wof:name":"Kaleen Ahmed MD",
    "wof:placetype":"venue"
},
  "geometry": {"coordinates":[-83.122367,34.284505],"type":"Point"}
}