{
  "type": "Feature",
  "properties": {
    "addr:full":"86 Jackson Concourse Pendergrass GA 30567",
    "addr:housenumber":"86",
    "addr:postcode":"30567",
    "addr:street":"Jackson Concourse",
    "iso:country":"US",
    "sg:address":"86 Jackson Concourse",
    "sg:city":"Pendergrass",
    "sg:classifiers":[
        {
            "category":"Food & Beverages",
            "subcategory":"Specialty",
            "type":"Retail Goods"
        },
        {
            "category":"Wholesale",
            "subcategory":"Groceries",
            "type":"Manufacturing & Wholesale Goods"
        },
        {
            "category":"Food & Beverages",
            "subcategory":"Groceries & Convenience Stores",
            "type":"Retail Goods"
        }
    ],
    "sg:phone":"+1 706 693 2425",
    "sg:postcode":"30567",
    "sg:province":"GA",
    "sg:tags":[
        "grocers-wholesale",
        "grocers-specialty"
    ],
    "wof:name":"Signature Custom Packing",
    "wof:placetype":"venue"
},
  "geometry": {"coordinates":[-83.671189,34.157771],"type":"Point"}
}