{
  "type": "Feature",
  "properties": {
    "addr:full":"307 Market Place Blvd Cartersville GA 30121",
    "addr:housenumber":"307",
    "addr:postcode":"30121",
    "addr:street":"Market Place Blvd",
    "iso:country":"US",
    "sg:address":"307 Market Place Blvd",
    "sg:city":"Cartersville",
    "sg:classifiers":[
        {
            "category":"Autos & Motor Vehicles",
            "subcategory":"Auto Supplies",
            "type":"Retail Goods"
        },
        {
            "category":"Retail",
            "subcategory":"Auto Repair",
            "type":"Services"
        }
    ],
    "sg:phone":"+1 770 607 0103",
    "sg:postcode":"30121",
    "sg:province":"GA",
    "sg:tags":[
        "lube",
        "oil",
        "tire"
    ],
    "sg:website":"http://www.firestonecompleteautocare.com/?s_kwcid=IYP_NTL",
    "wof:name":"Firestone Complete Auto Care Store",
    "wof:placetype":"venue"
},
  "geometry": {"coordinates":[-84.79176699999999,34.200987],"type":"Point"}
}