{
  "type": "Feature",
  "properties": {
    "iso:country":"US",
    "sg:address":"344 Staten St",
    "sg:city":"Jonesboro",
    "sg:classifiers":[
        {
            "category":"Building & Trades",
            "subcategory":"Construction",
            "type":"Services"
        }
    ],
    "sg:phone":"+1 770 477 0831",
    "sg:postcode":"30238",
    "sg:province":"GA",
    "sg:tags":[
        "paper",
        "painting",
        "hanging"
    ],
    "wof:name":"H & H Painting",
    "wof:placetype":"venue"
},
  "geometry": {"coordinates":[-84.405322,33.505217],"type":"Point"}
}