{
  "type": "Feature",
  "properties": {
    "addr:full":"1588 Atkinson Rd Lawrenceville GA 30043",
    "addr:housenumber":"1588",
    "addr:postcode":"30043",
    "addr:street":"Atkinson Rd",
    "iso:country":"US",
    "sg:address":"1588 Atkinson Rd",
    "sg:city":"Lawrenceville",
    "sg:classifiers":[
        {
            "category":"Shopping",
            "subcategory":"Computers & Home Electronics",
            "type":"Retail Goods"
        }
    ],
    "sg:phone":"+1 678 985 1314",
    "sg:postcode":"30043",
    "sg:province":"GA",
    "wof:name":"Perimeter Sound Science",
    "wof:placetype":"venue"
},
  "geometry": {"coordinates":[-84.071602,33.9674],"type":"Point"}
}