{
  "type": "Feature",
  "properties": {
    "addr:full":"363 Forest Pkwy Forest Park GA 30297",
    "addr:housenumber":"363",
    "addr:postcode":"30297",
    "addr:street":"Forest Pkwy",
    "iso:country":"US",
    "sg:address":"363 Forest Pkwy",
    "sg:city":"Forest Park",
    "sg:classifiers":[
        {
            "category":"Professional",
            "subcategory":"Engineering",
            "type":"Services"
        }
    ],
    "sg:phone":"+1 770 329 0330",
    "sg:postcode":"30297",
    "sg:province":"GA",
    "wof:name":"E/E Engineers",
    "wof:placetype":"venue"
},
  "geometry": {"coordinates":[-84.394644,33.618179],"type":"Point"}
}