{
  "type": "Feature",
  "properties": {
    "addr:full":"225 Meadows Rd Covington GA 30014",
    "addr:housenumber":"225",
    "addr:postcode":"30014",
    "addr:street":"Meadows Rd",
    "iso:country":"US",
    "sg:address":"225 Meadows Rd",
    "sg:city":"Covington",
    "sg:classifiers":[
        {
            "category":"Building & Trades",
            "subcategory":"Construction",
            "type":"Services"
        }
    ],
    "sg:phone":"+1 770 788 2995",
    "sg:postcode":"30014",
    "sg:province":"GA",
    "sg:tags":[
        "supplier",
        "contracting",
        "general"
    ],
    "wof:name":"G C Supply Co Inc Ranger &",
    "wof:placetype":"venue"
},
  "geometry": {"coordinates":[-83.78577799999999,33.635007],"type":"Point"}
}