{
  "type": "Feature",
  "properties": {
    "addr:full":"607 Butts Mill Rd Pine Mountain GA 31822",
    "addr:housenumber":"607",
    "addr:postcode":"31822",
    "addr:street":"Butts Mill Rd",
    "iso:country":"US",
    "sg:address":"607 Butts Mill Rd",
    "sg:city":"Pine Mountain",
    "sg:classifiers":[
        {
            "category":"Restaurant",
            "type":"Food & Drink"
        }
    ],
    "sg:phone":"+1 706 663 4777",
    "sg:postcode":"31822",
    "sg:province":"GA",
    "sg:tags":[
        "eating"
    ],
    "wof:name":"Carriage & Horses",
    "wof:placetype":"venue"
},
  "geometry": {"coordinates":[-84.873239,32.868714],"type":"Point"}
}