{
  "type": "Feature",
  "properties": {
    "addr:full":"930 Eagles Landing Pkwy Stockbridge GA 30281",
    "addr:housenumber":"930",
    "addr:postcode":"30281",
    "addr:street":"Eagles Landing Pkwy",
    "iso:country":"US",
    "sg:address":"930 Eagles Landing Pkwy",
    "sg:city":"Stockbridge",
    "sg:classifiers":[
        {
            "category":"Real Estate",
            "subcategory":"Real Estate Operator",
            "type":"Services"
        }
    ],
    "sg:phone":"+1 770 474 4849",
    "sg:postcode":"30281",
    "sg:province":"GA",
    "sg:tags":[
        "property",
        "lessor"
    ],
    "wof:name":"River Chase Realty",
    "wof:placetype":"venue"
},
  "geometry": {"coordinates":[-84.21233700000001,33.513616],"type":"Point"}
}