{
  "type": "Feature",
  "properties": {
    "addr:full":"5552 Robin Rd Ste B Acworth GA 30102",
    "addr:housenumber":"5552",
    "addr:postcode":"30102",
    "addr:street":"Robin Rd Ste B",
    "iso:country":"US",
    "sg:address":"5552 Robin Rd Ste B",
    "sg:city":"Acworth",
    "sg:classifiers":[
        {
            "category":"Professional",
            "subcategory":"Lawyer & Legal Services",
            "type":"Services"
        }
    ],
    "sg:phone":"+1 770 928 4444",
    "sg:postcode":"30102",
    "sg:province":"GA",
    "wof:name":"Flint & Connolly Llp",
    "wof:placetype":"venue"
},
  "geometry": {"coordinates":[-84.584,34.089802],"type":"Point"}
}