{
  "type": "Feature",
  "properties": {
    "addr:full":"200 Highland Way Chatsworth GA 30705",
    "addr:housenumber":"200",
    "addr:postcode":"30705",
    "addr:street":"Highland Way",
    "iso:country":"US",
    "sg:address":"200 Highland Way",
    "sg:city":"Chatsworth",
    "sg:classifiers":[
        {
            "category":"Wholesale",
            "subcategory":"Home Furnishings",
            "type":"Manufacturing & Wholesale Goods"
        }
    ],
    "sg:phone":"+1 706 695 1964",
    "sg:postcode":"30705",
    "sg:province":"GA",
    "sg:tags":[
        "rug",
        "carpet"
    ],
    "wof:name":"Victory Carpet Corp",
    "wof:placetype":"venue"
},
  "geometry": {"coordinates":[-84.797344,34.755003],"type":"Point"}
}