{
  "type": "Feature",
  "properties": {
    "addr:full":"61 Windmill Dr Chatsworth GA 30705",
    "addr:housenumber":"61",
    "addr:postcode":"30705",
    "addr:street":"Windmill Dr",
    "iso:country":"US",
    "sg:address":"61 Windmill Dr",
    "sg:city":"Chatsworth",
    "sg:classifiers":[
        {
            "category":"Shopping",
            "subcategory":"Florist",
            "type":"Retail Goods"
        }
    ],
    "sg:phone":"+1 706 517 3168",
    "sg:postcode":"30705",
    "sg:province":"GA",
    "wof:name":"Secret Garden Floral Design",
    "wof:placetype":"venue"
},
  "geometry": {"coordinates":[-84.822546,34.852145],"type":"Point"}
}