{
  "type": "Feature",
  "properties": {
    "addr:full":"609 Garnet Ct Canton GA 30114",
    "addr:housenumber":"609",
    "addr:postcode":"30114",
    "addr:street":"Garnet Ct",
    "iso:country":"US",
    "sg:address":"609 Garnet Ct",
    "sg:city":"Canton",
    "sg:classifiers":[
        {
            "category":"Autos & Motor Vehicles",
            "subcategory":"Automobile Sales",
            "type":"Retail Goods"
        }
    ],
    "sg:phone":"+1 678 493 2845",
    "sg:postcode":"30114",
    "sg:province":"GA",
    "sg:tags":[
        "new",
        "car"
    ],
    "wof:name":"James W Conner Fleet Services",
    "wof:placetype":"venue"
},
  "geometry": {"coordinates":[-84.53232800000001,34.169038],"type":"Point"}
}