{
  "type": "Feature",
  "properties": {
    "iso:country":"US",
    "sg:address":"166 Cedar Creek Dr",
    "sg:city":"Dallas",
    "sg:classifiers":[
        {
            "category":"Shopping",
            "type":"Retail Goods"
        }
    ],
    "sg:phone":"+1 770 445 0233",
    "sg:postcode":"30157",
    "sg:province":"GA",
    "sg:tags":[
        "merchandise"
    ],
    "wof:name":"Dream Shoppes Inc",
    "wof:placetype":"venue"
},
  "geometry": {"coordinates":[-84.88334500000001,33.813976],"type":"Point"}
}