{
  "type": "Feature",
  "properties": {
    "addr:full":"850 Cobb Place Blvd NW Kennesaw GA 30144",
    "addr:housenumber":"850",
    "addr:postcode":"30144",
    "addr:street":"Cobb Place Blvd Nw",
    "iso:country":"US",
    "sg:address":"850 Cobb Place Blvd NW",
    "sg:city":"Kennesaw",
    "sg:classifiers":[
        {
            "category":"Wholesale",
            "subcategory":"Computers",
            "type":"Manufacturing & Wholesale Goods"
        },
        {
            "category":"Professional",
            "subcategory":"Computer Services",
            "type":"Services"
        }
    ],
    "sg:phone":"+1 770 424 7868",
    "sg:postcode":"30144",
    "sg:province":"GA",
    "sg:tags":[
        "repair",
        "stereo",
        "installation"
    ],
    "wof:name":"Best Buy",
    "wof:placetype":"venue"
},
  "geometry": {"coordinates":[-84.572701,34.010799],"type":"Point"}
}