{
  "type": "Feature",
  "properties": {
    "addr:full":"3281 Hidden Cove Cir Norcross GA 30092",
    "addr:housenumber":"3281",
    "addr:postcode":"30092",
    "addr:street":"Hidden Cove Cir",
    "iso:country":"US",
    "sg:address":"3281 Hidden Cove Cir",
    "sg:city":"Norcross",
    "sg:classifiers":[
        {
            "category":"Real Estate",
            "subcategory":"Real Estate Operator",
            "type":"Services"
        }
    ],
    "sg:phone":"+1 770 729 0904",
    "sg:postcode":"30092",
    "sg:province":"GA",
    "sg:tags":[
        "apartment"
    ],
    "wof:name":"Hidden Cove",
    "wof:placetype":"venue"
},
  "geometry": {"coordinates":[-84.237099,33.950901],"type":"Point"}
}