{
  "type": "Feature",
  "properties": {
    "addr:full":"5975 Roswell Road NE Atlanta GA 30328",
    "addr:housenumber":"5975",
    "addr:postcode":"30328",
    "addr:street":"Roswell Road Ne",
    "iso:country":"US",
    "sg:address":"5975 Roswell Road NE",
    "sg:city":"Atlanta",
    "sg:classifiers":[
        {
            "category":"Retail",
            "subcategory":"Laundry & Dry Cleaning",
            "type":"Services"
        }
    ],
    "sg:phone":"+1 404 250 9354",
    "sg:postcode":"30328",
    "sg:province":"GA",
    "wof:name":"Peachy Cleaners",
    "wof:placetype":"venue"
},
  "geometry": {"coordinates":[-84.37902099999999,33.918323],"type":"Point"}
}