{
  "type": "Feature",
  "properties": {
    "iso:country":"US",
    "sg:address":"2526 Mount Vernon Rd",
    "sg:city":"Dunwoody",
    "sg:classifiers":[
        {
            "category":"Organizations",
            "subcategory":"Non-profit Organization",
            "type":"Services"
        }
    ],
    "sg:phone":"+1 770 458 0425",
    "sg:postcode":"30338",
    "sg:province":"GA",
    "sg:tags":[
        "fund",
        "counselor",
        "raising"
    ],
    "wof:name":"Kidscents",
    "wof:placetype":"venue"
},
  "geometry": {"coordinates":[-84.301401,33.958183],"type":"Point"}
}