{
  "type": "Feature",
  "properties": {
    "addr:full":"2010 Darien Park Dr Roswell GA 30076",
    "addr:housenumber":"2010",
    "addr:postcode":"30076",
    "addr:street":"Darien Park Dr",
    "iso:country":"US",
    "sg:address":"2010 Darien Park Dr",
    "sg:city":"Roswell",
    "sg:classifiers":[
        {
            "category":"Building & Trades",
            "subcategory":"Construction",
            "type":"Services"
        }
    ],
    "sg:phone":"+1 770 998 3694",
    "sg:postcode":"30076",
    "sg:province":"GA",
    "sg:tags":[
        "painting",
        "contractor"
    ],
    "wof:name":"JS Painting",
    "wof:placetype":"venue"
},
  "geometry": {"coordinates":[-84.346129,34.049756],"type":"Point"}
}