{
  "type": "Feature",
  "properties": {
    "iso:country":"US",
    "sg:address":"2507 Moody Rd Ste C",
    "sg:city":"Warner Robins",
    "sg:classifiers":[
        {
            "category":"Retail",
            "subcategory":"Portrait Studio",
            "type":"Services"
        }
    ],
    "sg:phone":"+1 478 225 6821",
    "sg:postcode":"31088",
    "sg:province":"GA",
    "sg:tags":[
        "photography",
        "store"
    ],
    "sg:website":"www.majesticframes.com",
    "wof:name":"Majestic Frames",
    "wof:placetype":"venue"
},
  "geometry": {"coordinates":[-83.623912,32.57818],"type":"Point"}
}