{
  "type": "Feature",
  "properties": {
    "iso:country":"US",
    "sg:address":"1050 Bedford Gardens Dr",
    "sg:city":"Alpharetta",
    "sg:classifiers":[
        {
            "category":"Real Estate",
            "subcategory":"Architect",
            "type":"Services"
        }
    ],
    "sg:phone":"+1 770 772 9896",
    "sg:postcode":"30022",
    "sg:province":"GA",
    "wof:name":"Pam Jordan Co",
    "wof:placetype":"venue"
},
  "geometry": {"coordinates":[-84.252843,34.005058],"type":"Point"}
}