{
  "type": "Feature",
  "properties": {
    "iso:country":"US",
    "sg:address":"8 N Stillwood Ct",
    "sg:city":"Savannah",
    "sg:classifiers":[
        {
            "category":"Real Estate",
            "subcategory":"Developer",
            "type":"Services"
        }
    ],
    "sg:phone":"+1 912 925 2530",
    "sg:postcode":"31419",
    "sg:province":"GA",
    "sg:tags":[
        "construction",
        "nonresidential"
    ],
    "wof:name":"H K Enterprise Inc",
    "wof:placetype":"venue"
},
  "geometry": {"coordinates":[-81.15304399999999,31.961649],"type":"Point"}
}