{
  "type": "Feature",
  "properties": {
    "addr:full":"985 Airline Rd Mc Donough GA 30252",
    "addr:housenumber":"985",
    "addr:postcode":"30252",
    "addr:street":"Airline Rd",
    "iso:country":"US",
    "sg:address":"985 Airline Rd",
    "sg:city":"Mc Donough",
    "sg:classifiers":[
        {
            "category":"Real Estate",
            "subcategory":"Real Estate Operator",
            "type":"Services"
        }
    ],
    "sg:phone":"+1 770 954 1984",
    "sg:postcode":"30252",
    "sg:province":"GA",
    "sg:tags":[
        "building",
        "nonresidential"
    ],
    "wof:name":"Register Land & Properties LLC",
    "wof:placetype":"venue"
},
  "geometry": {"coordinates":[-84.099565,33.468052],"type":"Point"}
}