{
  "type": "Feature",
  "properties": {
    "addr:full":"2426 Hephzibah Church Rd Lincolnton GA 30817",
    "addr:housenumber":"2426",
    "addr:postcode":"30817",
    "addr:street":"Hephzibah Church Rd",
    "iso:country":"US",
    "sg:address":"2426 Hephzibah Church Rd",
    "sg:city":"Lincolnton",
    "sg:classifiers":[
        {
            "category":"Building & Trades",
            "subcategory":"Construction",
            "type":"Services"
        }
    ],
    "sg:phone":"+1 706 359 6428",
    "sg:postcode":"30817",
    "sg:province":"GA",
    "sg:tags":[
        "bulldozing"
    ],
    "wof:name":"Johnson's Equipment",
    "wof:placetype":"venue"
},
  "geometry": {"coordinates":[-82.52654699999999,33.722372],"type":"Point"}
}