{
  "type": "Feature",
  "properties": {
    "iso:country":"US",
    "sg:address":"5180 Jimmy Carter Blvd",
    "sg:city":"Norcross",
    "sg:classifiers":[
        {
            "category":"Health Services",
            "subcategory":"Doctor",
            "type":"Services"
        }
    ],
    "sg:phone":"+1 770 613 0013",
    "sg:postcode":"30093",
    "sg:province":"GA",
    "sg:tags":[
        "practice",
        "family"
    ],
    "wof:name":"Pleasant Hill Medical Center",
    "wof:placetype":"venue"
},
  "geometry": {"coordinates":[-84.203102,33.8992],"type":"Point"}
}