{
  "type": "Feature",
  "properties": {
    "addr:full":"3365 Steve Reynolds Blvd Ste 107 Duluth GA 30096",
    "addr:housenumber":"3365",
    "addr:postcode":"30096",
    "addr:street":"Steve Reynolds Blvd Ste 107",
    "iso:country":"US",
    "sg:address":"3365 Steve Reynolds Blvd Ste 107",
    "sg:city":"Duluth",
    "sg:classifiers":[
        {
            "category":"Shopping",
            "subcategory":"Used Merchandise",
            "type":"Retail Goods"
        }
    ],
    "sg:phone":"+1 678 417 5544",
    "sg:postcode":"30096",
    "sg:province":"GA",
    "sg:tags":[
        "vintage",
        "consignment"
    ],
    "wof:name":"Olive Company",
    "wof:placetype":"venue"
},
  "geometry": {"coordinates":[-84.140636,33.952896],"type":"Point"}
}