{
  "type": "Feature",
  "properties": {
    "addr:full":"6310 Mableton Pkwy SW Ste 1000 Mableton GA 30126",
    "addr:housenumber":"6310",
    "addr:postcode":"30126",
    "addr:street":"Mableton Pkwy Sw Ste 1000",
    "iso:country":"US",
    "sg:address":"6310 Mableton Pkwy SW Ste 1000",
    "sg:city":"Mableton",
    "sg:classifiers":[
        {
            "category":"Building & Trades",
            "subcategory":"Plumbing",
            "type":"Services"
        }
    ],
    "sg:phone":"+1 770 941 5421",
    "sg:postcode":"30126",
    "sg:province":"GA",
    "wof:name":"Northwest Plumbing",
    "wof:placetype":"venue"
},
  "geometry": {"coordinates":[-84.566783,33.800749],"type":"Point"}
}