{
  "type": "Feature",
  "properties": {
    "addr:full":"3539 Palisade Cove Dr Duluth GA 30096",
    "addr:housenumber":"3539",
    "addr:postcode":"30096",
    "addr:street":"Palisade Cove Dr",
    "iso:country":"US",
    "sg:address":"3539 Palisade Cove Dr",
    "sg:city":"Duluth",
    "sg:classifiers":[
        {
            "category":"Airline",
            "type":"Transportation"
        }
    ],
    "sg:phone":"+1 678 665 6901",
    "sg:postcode":"30096",
    "sg:province":"GA",
    "sg:tags":[
        "cargo",
        "air"
    ],
    "wof:name":"World Cargo Express",
    "wof:placetype":"venue"
},
  "geometry": {"coordinates":[-84.15812,33.992117],"type":"Point"}
}