{
  "type": "Feature",
  "properties": {
    "iso:country":"US",
    "sg:address":"299 Robertson Ave",
    "sg:city":"Tallapoosa",
    "sg:classifiers":[
        {
            "category":"Social Services",
            "subcategory":"Child Care",
            "type":"Services"
        }
    ],
    "sg:phone":"+1 770 574 9888",
    "sg:postcode":"30176",
    "sg:province":"GA",
    "sg:tags":[
        "kindergarten",
        "academic",
        "school"
    ],
    "wof:name":"Wee Care",
    "wof:placetype":"venue"
},
  "geometry": {"coordinates":[-85.29019,33.74809],"type":"Point"}
}