{
  "type": "Feature",
  "properties": {
    "addr:full":"400 Bradford St S Gainesville GA 30501",
    "addr:housenumber":"400",
    "addr:postcode":"30501",
    "addr:street":"Bradford St S;Ga",
    "iso:country":"US",
    "sg:address":"400 Bradford St S",
    "sg:city":"Gainesville",
    "sg:classifiers":[
        {
            "category":"Restaurant",
            "type":"Food & Drink"
        }
    ],
    "sg:phone":"+1 770 535 3725",
    "sg:postcode":"30501",
    "sg:province":"GA",
    "sg:tags":[
        "eating"
    ],
    "wof:name":"Ice Box",
    "wof:placetype":"venue"
},
  "geometry": {"coordinates":[-83.824476,34.296321],"type":"Point"}
}