{
  "type": "Feature",
  "properties": {
    "iso:country":"US",
    "sg:address":"210 Willow Bush Trce",
    "sg:city":"Roswell",
    "sg:classifiers":[
        {
            "category":"Professional",
            "subcategory":"Management & Consulting",
            "type":"Services"
        }
    ],
    "sg:phone":"+1 770 642 4592",
    "sg:postcode":"30075",
    "sg:province":"GA",
    "wof:name":"Gold Sail Inc",
    "wof:placetype":"venue"
},
  "geometry": {"coordinates":[-84.39831,34.038699],"type":"Point"}
}