{
  "type": "Feature",
  "properties": {
    "addr:full":"574 Fairburn Road NW Atlanta GA 30331",
    "addr:housenumber":"574",
    "addr:postcode":"30331",
    "addr:street":"Fairburn Road Nw",
    "iso:country":"US",
    "sg:address":"574 Fairburn Road NW",
    "sg:city":"Atlanta",
    "sg:classifiers":[
        {
            "category":"Organizations",
            "subcategory":"Religious Organization",
            "type":"Services"
        }
    ],
    "sg:phone":"+1 404 696 7308",
    "sg:postcode":"30331",
    "sg:province":"GA",
    "wof:name":"New Canaan Baptist",
    "wof:placetype":"venue"
},
  "geometry": {"coordinates":[-84.499938,33.770213],"type":"Point"}
}