{
  "type": "Feature",
  "properties": {
    "addr:full":"784 Cole Rd SW Lilburn GA 30047",
    "addr:housenumber":"784",
    "addr:postcode":"30047",
    "addr:street":"Cole Rd Sw",
    "iso:country":"US",
    "sg:address":"784 Cole Rd SW",
    "sg:city":"Lilburn",
    "sg:classifiers":[
        {
            "category":"Manufacturing",
            "subcategory":"Buildings",
            "type":"Manufacturing & Wholesale Goods"
        },
        {
            "category":"Manufacturing",
            "subcategory":"Metals",
            "type":"Manufacturing & Wholesale Goods"
        }
    ],
    "sg:phone":"+1 770 806 9088",
    "sg:postcode":"30047",
    "sg:province":"GA",
    "sg:tags":[
        "steel",
        "erectors"
    ],
    "sg:website":"http://www.techbuildingsystems.com",
    "wof:name":"Tech Building Systems",
    "wof:placetype":"venue"
},
  "geometry": {"coordinates":[-84.118505,33.863071],"type":"Point"}
}