{
  "type": "Feature",
  "properties": {
    "iso:country":"US",
    "sg:address":"2761 London Berry Ct",
    "sg:city":"Snellville",
    "sg:classifiers":[
        {
            "category":"Real Estate",
            "subcategory":"Real Estate Agent",
            "type":"Services"
        }
    ],
    "sg:phone":"+1 770 237 9986",
    "sg:postcode":"30039",
    "sg:province":"GA",
    "sg:tags":[
        "inspection"
    ],
    "wof:name":"Ashley's Home Inspection Svc",
    "wof:placetype":"venue"
},
  "geometry": {"coordinates":[-84.010296,33.826484],"type":"Point"}
}