{
  "type": "Feature",
  "properties": {
    "addr:full":"6855 Peachtree Industrial Blvd Norcross GA 30092",
    "addr:housenumber":"6855",
    "addr:postcode":"30092",
    "addr:street":"Peachtree Industrial Blvd",
    "iso:country":"US",
    "sg:address":"6855 Peachtree Industrial Blvd",
    "sg:city":"Norcross",
    "sg:classifiers":[
        {
            "category":"Retail",
            "subcategory":"Auto Repair",
            "type":"Services"
        }
    ],
    "sg:phone":"+1 770 441 1662",
    "sg:postcode":"30092",
    "sg:province":"GA",
    "sg:tags":[
        "repairing",
        "automobile"
    ],
    "wof:name":"Auto Service Ctr",
    "wof:placetype":"venue"
},
  "geometry": {"coordinates":[-84.254565,33.935842],"type":"Point"}
}