{
  "type": "Feature",
  "properties": {
    "addr:full":"3255 Rebecca S Waldron Rd Douglas GA 31535",
    "addr:housenumber":"3255",
    "addr:postcode":"31535",
    "addr:street":"Rebecca S Waldron Rd",
    "iso:country":"US",
    "sg:address":"3255 Rebecca S Waldron Rd",
    "sg:city":"Douglas",
    "sg:classifiers":[
        {
            "category":"Building & Trades",
            "subcategory":"Plumbing",
            "type":"Services"
        },
        {
            "category":"Home & Garden",
            "subcategory":"Building Materials",
            "type":"Retail Goods"
        },
        {
            "category":"Utilities",
            "subcategory":"Sewage",
            "type":"Services"
        }
    ],
    "sg:phone":"+1 912 384 3526",
    "sg:postcode":"31535",
    "sg:province":"GA",
    "sg:tags":[
        "heater",
        "systems-cleaning",
        "drain",
        "tank",
        "septic",
        "consultant",
        "plumber",
        "contractor",
        "water",
        "industrial",
        "cleaning",
        "plumbing-drain",
        "sewer",
        "contractors-commercial"
    ],
    "sg:website":"http://www.MrRooter.com",
    "wof:name":"Mr. Rooter Plumbing Of Valdosta",
    "wof:placetype":"venue"
},
  "geometry": {"coordinates":[-82.80108199999999,31.41145],"type":"Point"}
}