{
  "type": "Feature",
  "properties": {
    "iso:country":"US",
    "sg:address":"436 Lavender Rd NW",
    "sg:city":"Rome",
    "sg:classifiers":[
        {
            "category":"Manufacturing",
            "subcategory":"Textiles",
            "type":"Manufacturing & Wholesale Goods"
        }
    ],
    "sg:phone":"+1 706 234 8648",
    "sg:postcode":"30165",
    "sg:province":"GA",
    "sg:tags":[
        "mfg"
    ],
    "wof:name":"Mohawk Dyehouse",
    "wof:placetype":"venue"
},
  "geometry": {"coordinates":[-85.223769,34.367308],"type":"Point"}
}