{
  "type": "Feature",
  "properties": {
    "iso:country":"US",
    "sg:address":"336 Caswyck Trce",
    "sg:city":"Alpharetta",
    "sg:classifiers":[
        {
            "category":"Restaurant",
            "type":"Food & Drink"
        }
    ],
    "sg:phone":"+1 678 624 9522",
    "sg:postcode":"30022",
    "sg:province":"GA",
    "sg:tags":[
        "eating"
    ],
    "wof:name":"Pampas Grill",
    "wof:placetype":"venue"
},
  "geometry": {"coordinates":[-84.228614,34.054212],"type":"Point"}
}