{
  "type": "Feature",
  "properties": {
    "addr:full":"1788 Philema Rd Albany GA 31701",
    "addr:housenumber":"1788",
    "addr:postcode":"31701",
    "addr:street":"Philema Rd",
    "iso:country":"US",
    "sg:address":"1788 Philema Rd",
    "sg:city":"Albany",
    "sg:classifiers":[
        {
            "category":"Building & Trades",
            "subcategory":"Cleaning & Sanitation",
            "type":"Services"
        }
    ],
    "sg:phone":"+1 229 436 5822",
    "sg:postcode":"31701",
    "sg:province":"GA",
    "sg:tags":[
        "maintenance"
    ],
    "wof:name":"Total Cleaning Service",
    "wof:placetype":"venue"
},
  "geometry": {"coordinates":[-84.117318,31.631445],"type":"Point"}
}