{
  "type": "Feature",
  "properties": {
    "addr:full":"905 Moreland Ave SE Atlanta GA 30316",
    "addr:housenumber":"905",
    "addr:postcode":"30316",
    "addr:street":"Moreland Ave Se",
    "iso:country":"US",
    "sg:address":"905 Moreland Ave SE",
    "sg:city":"Atlanta",
    "sg:classifiers":[
        {
            "category":"Building & Trades",
            "subcategory":"Construction",
            "type":"Services"
        }
    ],
    "sg:phone":"+1 404 454 6825",
    "sg:postcode":"30316",
    "sg:province":"GA",
    "sg:tags":[
        "wallcoverings-installation",
        "wallpaper",
        "painting",
        "contractor"
    ],
    "wof:name":"Painter Ready",
    "wof:placetype":"venue"
},
  "geometry": {"coordinates":[-84.34937600000001,33.7297],"type":"Point"}
}