{
  "type": "Feature",
  "properties": {
    "addr:full":"2778 State Rte 81 E Mcdonough GA 30252",
    "addr:housenumber":"2778",
    "addr:postcode":"30252",
    "addr:street":"State Rte 81 E",
    "iso:country":"US",
    "sg:address":"2778 State Rte 81 E",
    "sg:city":"Mcdonough",
    "sg:classifiers":[
        {
            "category":"Food & Beverages",
            "subcategory":"Groceries & Convenience Stores",
            "type":"Retail Goods"
        }
    ],
    "sg:phone":"+1 678 432 6760",
    "sg:postcode":"30252",
    "sg:province":"GA",
    "wof:name":"Howell Grocery",
    "wof:placetype":"venue"
},
  "geometry": {"coordinates":[-84.063907,33.429749],"type":"Point"}
}