{
  "type": "Feature",
  "properties": {
    "addr:full":"260 18th Street NW Atlanta GA 30363",
    "addr:housenumber":"260",
    "addr:postcode":"30363",
    "addr:street":"18Th Street Nw",
    "iso:country":"US",
    "sg:address":"260 18th Street NW",
    "sg:city":"Atlanta",
    "sg:classifiers":[
        {
            "category":"Shopping",
            "subcategory":"Clothing, Apparel, & Fashions",
            "type":"Retail Goods"
        }
    ],
    "sg:phone":"+1 404 249 9180",
    "sg:postcode":"30363",
    "sg:province":"GA",
    "sg:tags":[
        "accessory",
        "clothing",
        "women's"
    ],
    "sg:website":"www.anntaylor.com",
    "wof:name":"Ann Taylor",
    "wof:placetype":"venue"
},
  "geometry": {"coordinates":[-84.396529,33.792433],"type":"Point"}
}