{
  "type": "Feature",
  "properties": {
    "iso:country":"US",
    "sg:address":"21 Sundew Rd",
    "sg:city":"Savannah",
    "sg:classifiers":[
        {
            "category":"Restaurant",
            "type":"Food & Drink"
        }
    ],
    "sg:phone":"+1 912 484 5617",
    "sg:postcode":"31411",
    "sg:province":"GA",
    "sg:tags":[
        "eating"
    ],
    "wof:name":"Savoir Fare Personal Chef Svc",
    "wof:placetype":"venue"
},
  "geometry": {"coordinates":[-81.049747,31.944985],"type":"Point"}
}