{
  "type": "Feature",
  "properties": {
    "iso:country":"US",
    "sg:address":"186 Derby St",
    "sg:city":"Athens",
    "sg:classifiers":[
        {
            "category":"Organizations",
            "subcategory":"Religious Organization",
            "type":"Services"
        }
    ],
    "sg:phone":"+1 706 543 5039",
    "sg:postcode":"30601",
    "sg:province":"GA",
    "sg:tags":[
        "church"
    ],
    "wof:name":"Ebenezer Baptist Church East",
    "wof:placetype":"venue"
},
  "geometry": {"coordinates":[-83.35812300000001,33.954817],"type":"Point"}
}