{
  "type": "Feature",
  "properties": {
    "iso:country":"US",
    "sg:address":"725 Apsley Way",
    "sg:city":"Alpharetta",
    "sg:classifiers":[
        {
            "category":"Insurance",
            "subcategory":"Insurance Agent",
            "type":"Services"
        }
    ],
    "sg:phone":"+1 678 366 2002",
    "sg:postcode":"30022",
    "sg:province":"GA",
    "wof:name":"Allegiance Benefits Co",
    "wof:placetype":"venue"
},
  "geometry": {"coordinates":[-84.21130100000001,34.028618],"type":"Point"}
}