{
  "type": "Feature",
  "properties": {
    "iso:country":"US",
    "sg:address":"3992 Columbia Rd",
    "sg:city":"Augusta",
    "sg:classifiers":[
        {
            "category":"Professional",
            "subcategory":"Accounting & Tax Preparation",
            "type":"Services"
        }
    ],
    "sg:phone":"+1 706 922 9997",
    "sg:postcode":"30907",
    "sg:province":"GA",
    "wof:name":"Kim Young M EA",
    "wof:placetype":"venue"
},
  "geometry": {"coordinates":[-82.102234,33.508807],"type":"Point"}
}