{
  "type": "Feature",
  "properties": {
    "addr:full":"522 Viridian Vw Peachtree City GA 30269",
    "addr:housenumber":"522",
    "addr:postcode":"30269",
    "addr:street":"Viridian Vw",
    "iso:country":"US",
    "sg:address":"522 Viridian Vw",
    "sg:city":"Peachtree City",
    "sg:classifiers":[
        {
            "category":"Farming",
            "subcategory":"Livestock Farm",
            "type":"Manufacturing & Wholesale Goods"
        }
    ],
    "sg:phone":"+1 770 631 8580",
    "sg:postcode":"30269",
    "sg:province":"GA",
    "sg:tags":[
        "beef",
        "feedlot",
        "cattle"
    ],
    "wof:name":"Mark Strahler",
    "wof:placetype":"venue"
},
  "geometry": {"coordinates":[-84.59043,33.381476],"type":"Point"}
}