{
  "type": "Feature",
  "properties": {
    "iso:country":"US",
    "sg:address":"2180 Oakpointe Ct",
    "sg:city":"Buford",
    "sg:classifiers":[
        {
            "category":"Autos & Motor Vehicles",
            "subcategory":"Auto Supplies",
            "type":"Retail Goods"
        }
    ],
    "sg:phone":"+1 770 932 5902",
    "sg:postcode":"30519",
    "sg:province":"GA",
    "wof:name":"Grand Touring Specialties",
    "wof:placetype":"venue"
},
  "geometry": {"coordinates":[-83.879603,34.084513],"type":"Point"}
}