{
  "type": "Feature",
  "properties": {
    "addr:full":"218 Peachtree St NW Atlanta GA 30303",
    "addr:housenumber":"218",
    "addr:postcode":"30303",
    "addr:street":"Peachtree St Nw",
    "iso:country":"US",
    "sg:address":"218 Peachtree St NW",
    "sg:city":"Atlanta",
    "sg:classifiers":[
        {
            "category":"Restaurant",
            "type":"Food & Drink"
        }
    ],
    "sg:phone":"+1 404 223 6462",
    "sg:postcode":"30303",
    "sg:province":"GA",
    "sg:tags":[
        "eating"
    ],
    "wof:name":"Level 3 Cafe & Lounge",
    "wof:placetype":"venue"
},
  "geometry": {"coordinates":[-84.387637,33.760955],"type":"Point"}
}