{
  "type": "Feature",
  "properties": {
    "addr:full":"176 Key Circle Dr Brunswick GA 31520",
    "addr:housenumber":"176",
    "addr:postcode":"31520",
    "addr:street":"Key Circle Dr",
    "iso:country":"US",
    "sg:address":"176 Key Circle Dr",
    "sg:city":"Brunswick",
    "sg:classifiers":[
        {
            "category":"Building & Trades",
            "subcategory":"Construction",
            "type":"Services"
        }
    ],
    "sg:phone":"+1 912 265 5498",
    "sg:postcode":"31520",
    "sg:province":"GA",
    "sg:tags":[
        "house",
        "contractor",
        "commercial",
        "family",
        "general"
    ],
    "sg:website":"www.southerncontractors.net",
    "wof:name":"Southern Contractors of Glynn",
    "wof:placetype":"venue"
},
  "geometry": {"coordinates":[-81.49187499999999,31.201217],"type":"Point"}
}