{
  "type": "Feature",
  "properties": {
    "iso:country":"US",
    "sg:address":"6632 Springlake Dr",
    "sg:city":"Columbus",
    "sg:classifiers":[
        {
            "category":"Organizations",
            "subcategory":"Religious Organization",
            "type":"Services"
        }
    ],
    "sg:phone":"+1 706 569 1583",
    "sg:postcode":"31909",
    "sg:province":"GA",
    "wof:name":"Jimmy Blanton",
    "wof:placetype":"venue"
},
  "geometry": {"coordinates":[-84.93041599999999,32.541939],"type":"Point"}
}