{
  "type": "Feature",
  "properties": {
    "addr:full":"3372 Cobb Pkwy NW Ste 420 Acworth GA 30101",
    "addr:housenumber":"3372",
    "addr:postcode":"30101",
    "addr:street":"Cobb Pkwy Nw Ste 420",
    "iso:country":"US",
    "sg:address":"3372 Cobb Pkwy NW Ste 420",
    "sg:city":"Acworth",
    "sg:classifiers":[
        {
            "category":"Shopping",
            "subcategory":"Mobile Phones",
            "type":"Retail Goods"
        }
    ],
    "sg:phone":"+1 770 966 8181",
    "sg:postcode":"30101",
    "sg:province":"GA",
    "sg:website":"www.bellsouth.com",
    "wof:name":"AT&T",
    "wof:placetype":"venue"
},
  "geometry": {"coordinates":[-84.681899,34.035766],"type":"Point"}
}