{
  "type": "Feature",
  "properties": {
    "iso:country":"US",
    "sg:address":"6728 Mason Creek Rd",
    "sg:city":"Douglasville",
    "sg:classifiers":[
        {
            "category":"Arts & Performance",
            "subcategory":"Theater",
            "type":"Entertainment"
        }
    ],
    "sg:phone":"+1 770 947 9335",
    "sg:postcode":"30135",
    "sg:province":"GA",
    "sg:tags":[
        "group"
    ],
    "wof:name":"Compact Disc Jockey",
    "wof:placetype":"venue"
},
  "geometry": {"coordinates":[-84.80382299999999,33.679798],"type":"Point"}
}