{
  "type": "Feature",
  "properties": {
    "iso:country":"US",
    "sg:address":"2440 Sandy Plains Rd",
    "sg:city":"Marietta",
    "sg:classifiers":[
        {
            "category":"Health Services",
            "subcategory":"Doctor",
            "type":"Services"
        },
        {
            "category":"Health Services",
            "subcategory":"Clinic",
            "type":"Services"
        }
    ],
    "sg:phone":"+1 770 977 9201",
    "sg:postcode":"30066",
    "sg:province":"GA",
    "sg:tags":[
        "counseling",
        "mental"
    ],
    "wof:name":"Powell James PHD",
    "wof:placetype":"venue"
},
  "geometry": {"coordinates":[-84.49140199999999,34.018101],"type":"Point"}
}