{
  "type": "Feature",
  "properties": {
    "addr:full":"1946 Spring Bluff Rd Waverly GA 31565",
    "addr:housenumber":"1946",
    "addr:postcode":"31565",
    "addr:street":"Spring Bluff Rd",
    "iso:country":"US",
    "sg:address":"1946 Spring Bluff Rd",
    "sg:city":"Waverly",
    "sg:classifiers":[
        {
            "category":"Building & Trades",
            "subcategory":"Construction",
            "type":"Services"
        }
    ],
    "sg:phone":"+1 912 280 9437",
    "sg:postcode":"31565",
    "sg:province":"GA",
    "wof:name":"Spring Bluff Modular",
    "wof:placetype":"venue"
},
  "geometry": {"coordinates":[-81.63507300000001,31.066342],"type":"Point"}
}