{
  "type": "Feature",
  "properties": {
    "addr:full":"426 Woodridge Dr Atlanta GA 30339",
    "addr:housenumber":"426",
    "addr:postcode":"30339",
    "addr:street":"Woodridge Dr",
    "iso:country":"US",
    "sg:address":"426 Woodridge Dr",
    "sg:city":"Atlanta",
    "sg:classifiers":[
        {
            "category":"Utilities",
            "subcategory":"Telephone",
            "type":"Services"
        }
    ],
    "sg:phone":"+1 678 612 4759",
    "sg:postcode":"30339",
    "sg:province":"GA",
    "sg:tags":[
        "it"
    ],
    "wof:name":"Reliant Tech Solutions LLC",
    "wof:placetype":"venue"
},
  "geometry": {"coordinates":[-84.467628,33.870389],"type":"Point"}
}