{
  "type": "Feature",
  "properties": {
    "addr:full":"1523 Pleasant Hill Rd Duluth GA 30044",
    "addr:housenumber":"1523",
    "addr:postcode":"30044",
    "addr:street":"Pleasant Hill Rd",
    "iso:country":"US",
    "sg:address":"1523 Pleasant Hill Rd",
    "sg:city":"Duluth",
    "sg:classifiers":[
        {
            "category":"Banks & Credit Unions",
            "subcategory":"Bank",
            "type":"Services"
        }
    ],
    "sg:phone":"+1 770 717 1846",
    "sg:postcode":"30044",
    "sg:province":"GA",
    "sg:tags":[
        "personal",
        "institution"
    ],
    "wof:name":"Instant Cash",
    "wof:placetype":"venue"
},
  "geometry": {"coordinates":[-84.12421999999999,33.943888],"type":"Point"}
}