{
  "type": "Feature",
  "properties": {
    "iso:country":"US",
    "sg:address":"2050 Lawrenceville Hwy",
    "sg:city":"Decatur",
    "sg:classifiers":[
        {
            "category":"Shopping",
            "subcategory":"Clothing, Apparel, & Fashions",
            "type":"Retail Goods"
        }
    ],
    "sg:phone":"+1 404 728 0888",
    "sg:postcode":"30033",
    "sg:province":"GA",
    "sg:tags":[
        "handbag"
    ],
    "wof:name":"Marilyn's Handbags & Acces",
    "wof:placetype":"venue"
},
  "geometry": {"coordinates":[-84.27352,33.809413],"type":"Point"}
}