{
  "type": "Feature",
  "properties": {
    "iso:country":"US",
    "sg:address":"3977 Saint Clair Ct NE",
    "sg:city":"Atlanta",
    "sg:phone":"+1 404 434 8526",
    "sg:postcode":"30319",
    "sg:province":"GA",
    "wof:name":"Alexander E. Kahn & Associates, P.C.",
    "wof:placetype":"venue"
},
  "geometry": {"coordinates":[-84.32898900000001,33.909082],"type":"Point"}
}