{
  "type": "Feature",
  "properties": {
    "addr:full":"769 State Rte 53 Spr Calhoun GA 30701",
    "addr:housenumber":"769",
    "addr:postcode":"30701",
    "addr:street":"State Rte 53 Spr",
    "iso:country":"US",
    "sg:address":"769 State Rte 53 Spr",
    "sg:city":"Calhoun",
    "sg:classifiers":[
        {
            "category":"Food & Beverages",
            "subcategory":"Liquor & Beverages",
            "type":"Retail Goods"
        }
    ],
    "sg:phone":"+1 706 602 0038",
    "sg:postcode":"30701",
    "sg:province":"GA",
    "wof:name":"ABC Liquor Store",
    "wof:placetype":"venue"
},
  "geometry": {"coordinates":[-84.957009,34.502046],"type":"Point"}
}