{
  "type": "Feature",
  "properties": {
    "addr:full":"1535 Duluth Hwy Lawrenceville GA 30043",
    "addr:housenumber":"1535",
    "addr:postcode":"30043",
    "addr:street":"Duluth Hwy",
    "iso:country":"US",
    "sg:address":"1535 Duluth Hwy",
    "sg:city":"Lawrenceville",
    "sg:classifiers":[
        {
            "category":"Autos & Motor Vehicles",
            "subcategory":"Fuel & Gas Station",
            "type":"Retail Goods"
        },
        {
            "category":"Food & Beverages",
            "subcategory":"Groceries & Convenience Stores",
            "type":"Retail Goods"
        }
    ],
    "sg:phone":"+1 678 682 8928",
    "sg:postcode":"30043",
    "sg:province":"GA",
    "sg:website":"http://www.exxon.com",
    "wof:name":"Exxon Food Mart",
    "wof:placetype":"venue"
},
  "geometry": {"coordinates":[-84.056905,33.973395],"type":"Point"}
}