{
  "type": "Feature",
  "properties": {
    "addr:full":"3056 New Franklin Rd Lagrange GA 30240",
    "addr:housenumber":"3056",
    "addr:postcode":"30240",
    "addr:street":"New Franklin Rd",
    "iso:country":"US",
    "sg:address":"3056 New Franklin Rd",
    "sg:city":"Lagrange",
    "sg:classifiers":[
        {
            "category":"Retail",
            "subcategory":"Repair Shop",
            "type":"Services"
        },
        {
            "category":"Home & Garden",
            "subcategory":"Garden Supply",
            "type":"Retail Goods"
        }
    ],
    "sg:phone":"+1 706 884 0156",
    "sg:postcode":"30240",
    "sg:province":"GA",
    "sg:tags":[
        "hardware",
        "lawn",
        "mower"
    ],
    "wof:name":"Small Engine City & Marine",
    "wof:placetype":"venue"
},
  "geometry": {"coordinates":[-85.04099600000001,33.116298],"type":"Point"}
}