{
  "type": "Feature",
  "properties": {
    "addr:full":"2711 Metropolitan Pkwy SW Atlanta GA 30315",
    "addr:housenumber":"2711",
    "addr:postcode":"30315",
    "addr:street":"Metropolitan Pkwy Sw",
    "iso:country":"US",
    "sg:address":"2711 Metropolitan Pkwy SW",
    "sg:city":"Atlanta",
    "sg:classifiers":[
        {
            "category":"Retail",
            "subcategory":"Portrait Studio",
            "type":"Services"
        },
        {
            "category":"Shopping",
            "subcategory":"Pharmacy",
            "type":"Retail Goods"
        }
    ],
    "sg:phone":"+1 404 768 9719",
    "sg:postcode":"30315",
    "sg:province":"GA",
    "sg:tags":[
        "photography",
        "drugstore",
        "store"
    ],
    "sg:website":"www.walgreens.com",
    "wof:name":"Walgreens",
    "wof:placetype":"venue"
},
  "geometry": {"coordinates":[-84.40772200000001,33.680967],"type":"Point"}
}