{
  "type": "Feature",
  "properties": {
    "addr:full":"1914 Tynemoore Ct SE Smyrna GA 30080",
    "addr:housenumber":"1914",
    "addr:postcode":"30080",
    "addr:street":"Tynemoore Ct Se",
    "iso:country":"US",
    "sg:address":"1914 Tynemoore Ct SE",
    "sg:city":"Smyrna",
    "sg:classifiers":[
        {
            "category":"Professional",
            "type":"Services"
        }
    ],
    "sg:phone":"+1 770 801 0322",
    "sg:postcode":"30080",
    "sg:province":"GA",
    "sg:tags":[
        "establishment"
    ],
    "wof:name":"Exim House Inc",
    "wof:placetype":"venue"
},
  "geometry": {"coordinates":[-84.490255,33.855624],"type":"Point"}
}