{
  "type": "Feature",
  "properties": {
    "iso:country":"US",
    "sg:address":"107 Clay St SE",
    "sg:city":"Atlanta",
    "sg:classifiers":[
        {
            "category":"Manufacturing",
            "subcategory":"Lumber",
            "type":"Manufacturing & Wholesale Goods"
        }
    ],
    "sg:phone":"+1 404 377 1115",
    "sg:postcode":"30317",
    "sg:province":"GA",
    "sg:tags":[
        "logging"
    ],
    "wof:name":"Phillips Transportation",
    "wof:placetype":"venue"
},
  "geometry": {"coordinates":[-84.330495,33.750347],"type":"Point"}
}