{
  "type": "Feature",
  "properties": {
    "addr:full":"5142 Washington Rd Evans GA 30809",
    "addr:housenumber":"5142",
    "addr:postcode":"30809",
    "addr:street":"Washington Rd",
    "iso:country":"US",
    "sg:address":"5142 Washington Rd",
    "sg:city":"Evans",
    "sg:phone":"+1 706 228 1644",
    "sg:postcode":"30809",
    "sg:province":"GA",
    "sg:website":"http://www.blimpie.com",
    "wof:name":"BLIMPIE Subs & Salads",
    "wof:placetype":"venue"
},
  "geometry": {"coordinates":[-82.156498,33.553871],"type":"Point"}
}