{
  "type": "Feature",
  "properties": {
    "iso:country":"US",
    "sg:address":"163 Meadowview Ln",
    "sg:city":"Powder Springs",
    "sg:classifiers":[
        {
            "category":"Professional",
            "subcategory":"Management & Consulting",
            "type":"Services"
        }
    ],
    "sg:phone":"+1 770 439 3751",
    "sg:postcode":"30127",
    "sg:province":"GA",
    "sg:tags":[
        "business"
    ],
    "wof:name":"Gvgm",
    "wof:placetype":"venue"
},
  "geometry": {"coordinates":[-84.739473,33.834829],"type":"Point"}
}