{
  "type": "Feature",
  "properties": {
    "addr:full":"5750 Old Atlanta Rd Suwanee GA 30024",
    "addr:housenumber":"5750",
    "addr:postcode":"30024",
    "addr:street":"Old Atlanta Rd",
    "iso:country":"US",
    "sg:address":"5750 Old Atlanta Rd",
    "sg:city":"Suwanee",
    "sg:classifiers":[
        {
            "category":"Sports & Exercise",
            "subcategory":"Golf",
            "type":"Entertainment"
        }
    ],
    "sg:phone":"+1 770 497 0097",
    "sg:postcode":"30024",
    "sg:province":"GA",
    "sg:tags":[
        "course"
    ],
    "sg:website":"www.golfoldeatlanta.com",
    "wof:name":"Olde Atlanta Golf Club",
    "wof:placetype":"venue"
},
  "geometry": {"coordinates":[-84.129299,34.072815],"type":"Point"}
}