{
  "type": "Feature",
  "properties": {
    "addr:full":"1905 Scenic Hwy N Ste 210 Snellville GA 30078",
    "addr:housenumber":"1905",
    "addr:postcode":"30078",
    "addr:street":"Scenic Hwy N Ste 210",
    "iso:country":"US",
    "sg:address":"1905 Scenic Hwy N Ste 210",
    "sg:city":"Snellville",
    "sg:classifiers":[
        {
            "category":"Shopping",
            "subcategory":"Clothing, Apparel, & Fashions",
            "type":"Retail Goods"
        }
    ],
    "sg:phone":"+1 770 978 7334",
    "sg:postcode":"30078",
    "sg:province":"GA",
    "sg:tags":[
        "accessory",
        "clothing",
        "women's"
    ],
    "sg:website":"lanebryant.charmingshoppes.com",
    "wof:name":"Lane Bryant",
    "wof:placetype":"venue"
},
  "geometry": {"coordinates":[-84.014937,33.876778],"type":"Point"}
}