{
  "type": "Feature",
  "properties": {
    "iso:country":"US",
    "sg:address":"111 Kenton Pl",
    "sg:city":"Peachtree City",
    "sg:classifiers":[
        {
            "category":"Health Services",
            "subcategory":"Health Practitioner",
            "type":"Services"
        }
    ],
    "sg:phone":"+1 770 486 1810",
    "sg:postcode":"30269",
    "sg:province":"GA",
    "sg:tags":[
        "homeopath"
    ],
    "wof:name":"Center For Mind Body Therapy",
    "wof:placetype":"venue"
},
  "geometry": {"coordinates":[-84.535726,33.354228],"type":"Point"}
}