{
  "type": "Feature",
  "properties": {
    "addr:full":"3241 Deans Bridge Rd Augusta GA 30906",
    "addr:housenumber":"3241",
    "addr:postcode":"30906",
    "addr:street":"Deans Bridge Rd",
    "iso:country":"US",
    "sg:address":"3241 Deans Bridge Rd",
    "sg:city":"Augusta",
    "sg:classifiers":[
        {
            "category":"Insurance",
            "subcategory":"Insurance Agent",
            "type":"Services"
        }
    ],
    "sg:phone":"+1 706 796 3500",
    "sg:postcode":"30906",
    "sg:province":"GA",
    "wof:name":"Direct General Ins Agency",
    "wof:placetype":"venue"
},
  "geometry": {"coordinates":[-82.063447,33.421815],"type":"Point"}
}