{
  "type": "Feature",
  "properties": {
    "addr:full":"845 Spring St NW Unit 321 Atlanta GA 30308",
    "addr:housenumber":"845;321",
    "addr:postcode":"30308",
    "addr:street":"Spring St Nw Unit",
    "iso:country":"US",
    "sg:address":"845 Spring St NW Unit 321",
    "sg:city":"Atlanta",
    "sg:classifiers":[
        {
            "category":"Real Estate",
            "subcategory":"Real Estate Services",
            "type":"Services"
        }
    ],
    "sg:phone":"+1 404 881 0049",
    "sg:postcode":"30308",
    "sg:province":"GA",
    "sg:tags":[
        "management",
        "condominium"
    ],
    "wof:name":"Midcity Lofts Condominium Association Inc",
    "wof:placetype":"venue"
},
  "geometry": {"coordinates":[-84.388802,33.777802],"type":"Point"}
}