{
  "type": "Feature",
  "properties": {
    "iso:country":"US",
    "sg:address":"5715 Buford Hwy NE",
    "sg:city":"Atlanta",
    "sg:classifiers":[
        {
            "category":"Health Services",
            "subcategory":"Chiropractor",
            "type":"Services"
        }
    ],
    "sg:phone":"+1 770 451 4011",
    "sg:postcode":"30340",
    "sg:province":"GA",
    "sg:tags":[
        "chiropractic"
    ],
    "wof:name":"Kim Family Chiropractic",
    "wof:placetype":"venue"
},
  "geometry": {"coordinates":[-84.26939400000001,33.906771],"type":"Point"}
}