{
  "type": "Feature",
  "properties": {
    "iso:country":"US",
    "sg:address":"2426 Abercorn St",
    "sg:city":"Savannah",
    "sg:classifiers":[
        {
            "category":"Shopping",
            "subcategory":"Gifts & Souvenirs",
            "type":"Retail Goods"
        }
    ],
    "sg:phone":"+1 912 495 9700",
    "sg:postcode":"31401",
    "sg:province":"GA",
    "wof:name":"Annie Caroline",
    "wof:placetype":"venue"
},
  "geometry": {"coordinates":[-81.09868400000001,32.054089],"type":"Point"}
}