{
  "type": "Feature",
  "properties": {
    "addr:full":"2694 Summerbrooke Dr Kennesaw GA 30152",
    "addr:housenumber":"2694",
    "addr:postcode":"30152",
    "addr:street":"Summerbrooke Dr",
    "iso:country":"US",
    "sg:address":"2694 Summerbrooke Dr",
    "sg:city":"Kennesaw",
    "sg:classifiers":[
        {
            "category":"Utilities",
            "subcategory":"Cable",
            "type":"Services"
        }
    ],
    "sg:phone":"+1 770 714 3435",
    "sg:postcode":"30152",
    "sg:province":"GA",
    "sg:tags":[
        "television"
    ],
    "wof:name":"Optical Cable Corporation",
    "wof:placetype":"venue"
},
  "geometry": {"coordinates":[-84.639482,34.020816],"type":"Point"}
}