{
  "type": "Feature",
  "properties": {
    "iso:country":"US",
    "sg:address":"405 Kings Way",
    "sg:city":"Saint Simons Island",
    "sg:classifiers":[
        {
            "category":"Professional",
            "type":"Services"
        }
    ],
    "sg:phone":"+1 912 638 6482",
    "sg:postcode":"31522",
    "sg:province":"GA",
    "wof:name":"Robert E Olson",
    "wof:placetype":"venue"
},
  "geometry": {"coordinates":[-81.397144,31.138947],"type":"Point"}
}