{
  "type": "Feature",
  "properties": {
    "iso:country":"US",
    "sg:address":"5673 Peachtree Dunwoody Rd",
    "sg:city":"Atlanta",
    "sg:classifiers":[
        {
            "category":"Health Services",
            "subcategory":"Doctor",
            "type":"Services"
        }
    ],
    "sg:phone":"+1 404 252 0113",
    "sg:postcode":"30342",
    "sg:province":"GA",
    "sg:tags":[
        "physician",
        "surgeon"
    ],
    "wof:name":"Southern Ear Nose & Throat",
    "wof:placetype":"venue"
},
  "geometry": {"coordinates":[-84.35254,33.907219],"type":"Point"}
}