{
  "type": "Feature",
  "properties": {
    "addr:full":"1177 Groover Old Mill Rd Statesboro GA 30458",
    "addr:housenumber":"1177",
    "addr:postcode":"30458",
    "addr:street":"Groover Old Mill Rd",
    "iso:country":"US",
    "sg:address":"1177 Groover Old Mill Rd",
    "sg:city":"Statesboro",
    "sg:phone":"+1 912 839 3551",
    "sg:postcode":"30458",
    "sg:province":"GA",
    "sg:tags":[
        "farm",
        "soybean"
    ],
    "wof:name":"Tommy Harville",
    "wof:placetype":"venue"
},
  "geometry": {"coordinates":[-81.79176099999999,32.333855],"type":"Point"}
}