{
  "type": "Feature",
  "properties": {
    "addr:full":"1542 Mozley Pl SW Atlanta GA 30314",
    "addr:housenumber":"1542",
    "addr:postcode":"30314",
    "addr:street":"Mozley Pl Sw",
    "iso:country":"US",
    "sg:address":"1542 Mozley Pl SW",
    "sg:city":"Atlanta",
    "sg:classifiers":[
        {
            "category":"Wholesale",
            "subcategory":"Music Publishers",
            "type":"Manufacturing & Wholesale Goods"
        },
        {
            "category":"Wholesale",
            "subcategory":"Books, Periodicals, & Newspapers",
            "type":"Manufacturing & Wholesale Goods"
        }
    ],
    "sg:phone":"+1 404 753 8815",
    "sg:postcode":"30314",
    "sg:province":"GA",
    "sg:tags":[
        "distribution"
    ],
    "wof:name":"Teglen Harp Publishing Co",
    "wof:placetype":"venue"
},
  "geometry": {"coordinates":[-84.438051,33.751216],"type":"Point"}
}