{
  "type": "Feature",
  "properties": {
    "iso:country":"US",
    "sg:address":"5951 Bostwick Rd",
    "sg:city":"Bostwick",
    "sg:classifiers":[
        {
            "category":"Government",
            "subcategory":"Office",
            "type":"Public Place"
        }
    ],
    "sg:phone":"+1 706 343 0065",
    "sg:postcode":"30623",
    "sg:province":"GA",
    "sg:tags":[
        "city"
    ],
    "wof:name":"Bostwick City Hall",
    "wof:placetype":"venue"
},
  "geometry": {"coordinates":[-83.514583,33.737376],"type":"Point"}
}