{
  "type": "Feature",
  "properties": {
    "addr:full":"107 E College St Wrightsville GA 31096",
    "addr:housenumber":"107",
    "addr:postcode":"31096",
    "addr:street":"E College St",
    "iso:country":"US",
    "sg:address":"107 E College St",
    "sg:city":"Wrightsville",
    "sg:classifiers":[
        {
            "category":"Professional",
            "subcategory":"Accounting & Tax Preparation",
            "type":"Services"
        }
    ],
    "sg:phone":"+1 478 864 7700",
    "sg:postcode":"31096",
    "sg:province":"GA",
    "sg:tags":[
        "return",
        "preparation-business"
    ],
    "wof:name":"Complete Income Tax Service 5",
    "wof:placetype":"venue"
},
  "geometry": {"coordinates":[-82.719679,32.72857],"type":"Point"}
}