{
  "type": "Feature",
  "properties": {
    "addr:full":"3736 Sandhill Dr SE Conyers GA 30094",
    "addr:housenumber":"3736",
    "addr:postcode":"30094",
    "addr:street":"Sandhill Dr Se",
    "iso:country":"US",
    "sg:address":"3736 Sandhill Dr SE",
    "sg:city":"Conyers",
    "sg:classifiers":[
        {
            "category":"Real Estate",
            "subcategory":"Developer",
            "type":"Services"
        }
    ],
    "sg:phone":"+1 770 922 9400",
    "sg:postcode":"30094",
    "sg:province":"GA",
    "wof:name":"R J G Inc",
    "wof:placetype":"venue"
},
  "geometry": {"coordinates":[-84.02524099999999,33.590201],"type":"Point"}
}