{
  "type": "Feature",
  "properties": {
    "iso:country":"US",
    "sg:address":"1946 Rosewood Rd",
    "sg:city":"Decatur",
    "sg:classifiers":[
        {
            "category":"Building & Trades",
            "subcategory":"Cleaning & Sanitation",
            "type":"Services"
        }
    ],
    "sg:phone":"+1 404 288 5181",
    "sg:postcode":"30032",
    "sg:province":"GA",
    "wof:name":"Linwood Cleaning Service",
    "wof:placetype":"venue"
},
  "geometry": {"coordinates":[-84.261968,33.733124],"type":"Point"}
}