{
  "type": "Feature",
  "properties": {
    "addr:full":"45 Miner Dr Richmond Hill GA 31324",
    "addr:housenumber":"45",
    "addr:postcode":"31324",
    "addr:street":"Miner Dr",
    "iso:country":"US",
    "sg:address":"45 Miner Dr",
    "sg:city":"Richmond Hill",
    "sg:classifiers":[
        {
            "category":"Professional",
            "subcategory":"Computer Services",
            "type":"Services"
        }
    ],
    "sg:phone":"+1 912 756 6767",
    "sg:postcode":"31324",
    "sg:province":"GA",
    "sg:tags":[
        "internet"
    ],
    "wof:name":"HIQ Networking Inc",
    "wof:placetype":"venue"
},
  "geometry": {"coordinates":[-81.305746,31.92943],"type":"Point"}
}