{
  "type": "Feature",
  "properties": {
    "addr:full":"1366 Southern Woods Dr Tucker GA 30084",
    "addr:housenumber":"1366",
    "addr:postcode":"30084",
    "addr:street":"Southern Woods Dr",
    "iso:country":"US",
    "sg:address":"1366 Southern Woods Dr",
    "sg:city":"Tucker",
    "sg:classifiers":[
        {
            "category":"Professional",
            "type":"Services"
        }
    ],
    "sg:phone":"+1 770 938 0532",
    "sg:postcode":"30084",
    "sg:province":"GA",
    "wof:name":"Sergio Cruz",
    "wof:placetype":"venue"
},
  "geometry": {"coordinates":[-84.21361899999999,33.89123],"type":"Point"}
}