{
  "type": "Feature",
  "properties": {
    "iso:country":"US",
    "sg:address":"1398 Metropolitan Pkwy SW",
    "sg:city":"Atlanta",
    "sg:classifiers":[
        {
            "category":"Personal",
            "subcategory":"Beauty Salon",
            "type":"Services"
        }
    ],
    "sg:phone":"+1 404 752 8340",
    "sg:postcode":"30310",
    "sg:province":"GA",
    "sg:tags":[
        "hair"
    ],
    "wof:name":"Jones Ar",
    "wof:placetype":"venue"
},
  "geometry": {"coordinates":[-84.40769899999999,33.716824],"type":"Point"}
}