{
  "type": "Feature",
  "properties": {
    "iso:country":"US",
    "sg:address":"136 Cornerstone Dr",
    "sg:city":"Brunswick",
    "sg:classifiers":[
        {
            "category":"Coffee & Tea",
            "type":"Food & Drink"
        },
        {
            "category":"Restaurant",
            "type":"Food & Drink"
        }
    ],
    "sg:phone":"+1 912 264 4447",
    "sg:postcode":"31523",
    "sg:province":"GA",
    "sg:tags":[
        "espresso"
    ],
    "wof:name":"Magnolia Cafe",
    "wof:placetype":"venue"
},
  "geometry": {"coordinates":[-81.539248,31.237249],"type":"Point"}
}