{
  "type": "Feature",
  "properties": {
    "addr:full":"633 Overhill Dr Woodstock GA 30189",
    "addr:housenumber":"633",
    "addr:postcode":"30189",
    "addr:street":"Overhill Dr",
    "iso:country":"US",
    "sg:address":"633 Overhill Dr",
    "sg:city":"Woodstock",
    "sg:classifiers":[
        {
            "category":"Manufacturing",
            "subcategory":"Paper Products",
            "type":"Manufacturing & Wholesale Goods"
        }
    ],
    "sg:phone":"+1 770 592 0891",
    "sg:postcode":"30189",
    "sg:province":"GA",
    "sg:tags":[
        "food",
        "sanitary",
        "container",
        "mfg"
    ],
    "wof:name":"Wincup",
    "wof:placetype":"venue"
},
  "geometry": {"coordinates":[-84.535686,34.11912],"type":"Point"}
}