{
  "type": "Feature",
  "properties": {
    "iso:country":"US",
    "sg:address":"270 Jade Cove Cir",
    "sg:city":"Roswell",
    "sg:classifiers":[
        {
            "category":"Professional",
            "subcategory":"Accounting & Tax Preparation",
            "type":"Services"
        }
    ],
    "sg:phone":"+1 770 552 9410",
    "sg:postcode":"30075",
    "sg:province":"GA",
    "sg:tags":[
        "accountant"
    ],
    "wof:name":"Robin R Mc Intire CPA",
    "wof:placetype":"venue"
},
  "geometry": {"coordinates":[-84.337609,34.02227],"type":"Point"}
}