{
  "type": "Feature",
  "properties": {
    "iso:country":"US",
    "sg:address":"4658 S Old Peachtree Rd",
    "sg:city":"Norcross",
    "sg:classifiers":[
        {
            "category":"Autos & Motor Vehicles",
            "subcategory":"Auto Supplies",
            "type":"Retail Goods"
        },
        {
            "category":"Wholesale",
            "subcategory":"Auto Parts",
            "type":"Manufacturing & Wholesale Goods"
        }
    ],
    "sg:phone":"+1 770 455 0457",
    "sg:postcode":"30071",
    "sg:province":"GA",
    "sg:tags":[
        "automobile",
        "rebuilt",
        "rebuilt-wholesale",
        "supplies-used",
        "manufacturer"
    ],
    "wof:name":"Gene Hamilton",
    "wof:placetype":"venue"
},
  "geometry": {"coordinates":[-84.184591,33.96736],"type":"Point"}
}