{
  "type": "Feature",
  "properties": {
    "iso:country":"US",
    "sg:address":"1300 Parkwood Cir SE",
    "sg:city":"Atlanta",
    "sg:classifiers":[
        {
            "category":"Building & Trades",
            "subcategory":"Construction",
            "type":"Services"
        }
    ],
    "sg:phone":"+1 770 952 7171",
    "sg:postcode":"30339",
    "sg:province":"GA",
    "sg:tags":[
        "interior",
        "design"
    ],
    "wof:name":"Imaging Design",
    "wof:placetype":"venue"
},
  "geometry": {"coordinates":[-84.461119,33.901413],"type":"Point"}
}