{
  "type": "Feature",
  "properties": {
    "addr:full":"25 W Main St Cartersville GA 30120",
    "addr:housenumber":"25",
    "addr:postcode":"30120",
    "addr:street":"W Main St",
    "iso:country":"US",
    "sg:address":"25 W Main St",
    "sg:city":"Cartersville",
    "sg:classifiers":[
        {
            "category":"Retail",
            "subcategory":"Portrait Studio",
            "type":"Services"
        }
    ],
    "sg:phone":"+1 770 382 2835",
    "sg:postcode":"30120",
    "sg:province":"GA",
    "sg:tags":[
        "photographer"
    ],
    "wof:name":"Ron Greene Photography Studio",
    "wof:placetype":"venue"
},
  "geometry": {"coordinates":[-84.800141,34.163988],"type":"Point"}
}