{
  "type": "Feature",
  "properties": {
    "addr:full":"145 Julia Ct Fayetteville GA 30214",
    "addr:housenumber":"145",
    "addr:postcode":"30214",
    "addr:street":"Julia Ct",
    "iso:country":"US",
    "sg:address":"145 Julia Ct",
    "sg:city":"Fayetteville",
    "sg:classifiers":[
        {
            "category":"Real Estate",
            "subcategory":"Real Estate Operator",
            "type":"Services"
        }
    ],
    "sg:phone":"+1 770 486 6032",
    "sg:postcode":"30214",
    "sg:province":"GA",
    "sg:tags":[
        "building",
        "nonresidential"
    ],
    "wof:name":"Ve Properties LLC",
    "wof:placetype":"venue"
},
  "geometry": {"coordinates":[-84.45242,33.473141],"type":"Point"}
}