{
  "type": "Feature",
  "properties": {
    "iso:country":"US",
    "sg:address":"711 Industrial Blvd",
    "sg:city":"Gainesville",
    "sg:classifiers":[
        {
            "category":"Shopping",
            "subcategory":"Computers & Home Electronics",
            "type":"Retail Goods"
        }
    ],
    "sg:phone":"+1 770 718 1226",
    "sg:postcode":"30501",
    "sg:province":"GA",
    "wof:name":"Discotca Chipicuaro",
    "wof:placetype":"venue"
},
  "geometry": {"coordinates":[-83.82512199999999,34.285575],"type":"Point"}
}