{
  "type": "Feature",
  "properties": {
    "iso:country":"US",
    "sg:address":"302 W 10th St",
    "sg:city":"West Point",
    "sg:classifiers":[
        {
            "category":"Autos & Motor Vehicles",
            "subcategory":"Fuel & Gas Station",
            "type":"Retail Goods"
        }
    ],
    "sg:phone":"+1 706 645 3402",
    "sg:postcode":"31833",
    "sg:province":"GA",
    "sg:tags":[
        "grocery",
        "station",
        "gasoline"
    ],
    "wof:name":"Spectrum 2",
    "wof:placetype":"venue"
},
  "geometry": {"coordinates":[-85.183098,32.879267],"type":"Point"}
}