{
  "type": "Feature",
  "properties": {
    "addr:full":"9165 Woodhill Ln Jonesboro GA 30238",
    "addr:housenumber":"9165",
    "addr:postcode":"30238",
    "addr:street":"Woodhill Ln",
    "iso:country":"US",
    "sg:address":"9165 Woodhill Ln",
    "sg:city":"Jonesboro",
    "sg:classifiers":[
        {
            "category":"Building & Trades",
            "subcategory":"Construction",
            "type":"Services"
        }
    ],
    "sg:phone":"+1 770 471 4155",
    "sg:postcode":"30238",
    "sg:province":"GA",
    "sg:tags":[
        "painter"
    ],
    "wof:name":"Lynvetts Inc",
    "wof:placetype":"venue"
},
  "geometry": {"coordinates":[-84.41043000000001,33.503437],"type":"Point"}
}