{
  "type": "Feature",
  "properties": {
    "addr:full":"255 Edgeman Rd Ringgold GA 30736",
    "addr:housenumber":"255",
    "addr:postcode":"30736",
    "addr:street":"Edgeman Rd",
    "iso:country":"US",
    "sg:address":"255 Edgeman Rd",
    "sg:city":"Ringgold",
    "sg:classifiers":[
        {
            "category":"Home & Garden",
            "subcategory":"Building Materials",
            "type":"Retail Goods"
        }
    ],
    "sg:phone":"+1 706 965 6877",
    "sg:postcode":"30736",
    "sg:province":"GA",
    "sg:tags":[
        "shutter"
    ],
    "sg:website":"www.theshuttershoppe.com",
    "wof:name":"Shutter Shoppe",
    "wof:placetype":"venue"
},
  "geometry": {"coordinates":[-85.016728,34.959548],"type":"Point"}
}