{
  "type": "Feature",
  "properties": {
    "addr:full":"1237 Broadway Ave Columbus GA 31901",
    "addr:housenumber":"1237",
    "addr:postcode":"31901",
    "addr:street":"Broadway Ave",
    "iso:country":"US",
    "sg:address":"1237 Broadway Ave",
    "sg:city":"Columbus",
    "sg:classifiers":[
        {
            "category":"Banks & Credit Unions",
            "subcategory":"Bank",
            "type":"Services"
        }
    ],
    "sg:phone":"+1 706 324 6411",
    "sg:postcode":"31901",
    "sg:province":"GA",
    "sg:tags":[
        "personal",
        "financing",
        "institution"
    ],
    "wof:name":"Mann Finance Corp",
    "wof:placetype":"venue"
},
  "geometry": {"coordinates":[-84.993188,32.469837],"type":"Point"}
}