{
  "type": "Feature",
  "properties": {
    "iso:country":"US",
    "sg:address":"4007 Sunset Dr",
    "sg:city":"Rising Fawn",
    "sg:classifiers":[
        {
            "category":"Real Estate",
            "subcategory":"Real Estate Operator",
            "type":"Services"
        }
    ],
    "sg:phone":"+1 706 398 9119",
    "sg:postcode":"30738",
    "sg:province":"GA",
    "sg:tags":[
        "building"
    ],
    "wof:name":"Hlm Properties Inc",
    "wof:placetype":"venue"
},
  "geometry": {"coordinates":[-85.517207,34.797992],"type":"Point"}
}