{
  "type": "Feature",
  "properties": {
    "iso:country":"US",
    "sg:address":"3521 Flat Shoals Rd",
    "sg:city":"Decatur",
    "sg:classifiers":[
        {
            "category":"Autos & Motor Vehicles",
            "subcategory":"Fuel & Gas Station",
            "type":"Retail Goods"
        }
    ],
    "sg:phone":"+1 404 381 3017",
    "sg:postcode":"30034",
    "sg:province":"GA",
    "wof:name":"Flat Shoals Food Mart",
    "wof:placetype":"venue"
},
  "geometry": {"coordinates":[-84.272383,33.7049],"type":"Point"}
}