{
  "type": "Feature",
  "properties": {
    "iso:country":"US",
    "sg:address":"1397 Independence Way",
    "sg:city":"Marietta",
    "sg:classifiers":[
        {
            "category":"Shopping",
            "type":"Retail Goods"
        }
    ],
    "sg:phone":"+1 678 560 4819",
    "sg:postcode":"30062",
    "sg:province":"GA",
    "sg:tags":[
        "merchandise"
    ],
    "wof:name":"Perfectly Pampered Pets",
    "wof:placetype":"venue"
},
  "geometry": {"coordinates":[-84.44365999999999,33.984926],"type":"Point"}
}