{
  "type": "Feature",
  "properties": {
    "addr:full":"145 Hampton Point Dr Saint Simons Island GA 31522",
    "addr:housenumber":"145",
    "addr:postcode":"31522",
    "addr:street":"Hampton Point Dr",
    "iso:country":"US",
    "sg:address":"145 Hampton Point Dr",
    "sg:city":"Saint Simons Island",
    "sg:classifiers":[
        {
            "category":"Professional",
            "subcategory":"Business Services",
            "type":"Services"
        }
    ],
    "sg:phone":"+1 912 634 5887",
    "sg:postcode":"31522",
    "sg:province":"GA",
    "wof:name":"Go Fish Clothing & Jewelry",
    "wof:placetype":"venue"
},
  "geometry": {"coordinates":[-81.344572,31.280235],"type":"Point"}
}