{
  "type": "Feature",
  "properties": {
    "addr:full":"382 S Davis Rd Lagrange GA 30241",
    "addr:housenumber":"382",
    "addr:postcode":"30241",
    "addr:street":"S Davis Rd",
    "iso:country":"US",
    "sg:address":"382 S Davis Rd",
    "sg:city":"Lagrange",
    "sg:classifiers":[
        {
            "category":"Professional",
            "type":"Services"
        },
        {
            "category":"Restaurant",
            "type":"Food & Drink"
        }
    ],
    "sg:phone":"+1 706 883 8547",
    "sg:postcode":"30241",
    "sg:province":"GA",
    "sg:tags":[
        "caterer"
    ],
    "wof:name":"Los Nopales Mexican Restaurant",
    "wof:placetype":"venue"
},
  "geometry": {"coordinates":[-85.028988,33.006907],"type":"Point"}
}