{
  "type": "Feature",
  "properties": {
    "iso:country":"US",
    "sg:address":"4228 Aerie Cir",
    "sg:city":"Evans",
    "sg:classifiers":[
        {
            "category":"Professional",
            "type":"Services"
        }
    ],
    "sg:phone":"+1 706 868 5228",
    "sg:postcode":"30809",
    "sg:province":"GA",
    "sg:tags":[
        "establishment"
    ],
    "wof:name":"M & M Unlimited",
    "wof:placetype":"venue"
},
  "geometry": {"coordinates":[-82.10164,33.574188],"type":"Point"}
}