{
  "type": "Feature",
  "properties": {
    "addr:full":"119 School St Kingston GA 30145",
    "addr:housenumber":"119",
    "addr:postcode":"30145",
    "addr:street":"School St",
    "iso:country":"US",
    "sg:address":"119 School St",
    "sg:city":"Kingston",
    "sg:classifiers":[
        {
            "category":"Professional",
            "subcategory":"Accounting & Tax Preparation",
            "type":"Services"
        }
    ],
    "sg:phone":"+1 770 336 5680",
    "sg:postcode":"30145",
    "sg:province":"GA",
    "sg:tags":[
        "bookkeeping",
        "general"
    ],
    "wof:name":"B & L Bookkeeping",
    "wof:placetype":"venue"
},
  "geometry": {"coordinates":[-84.95841,34.236319],"type":"Point"}
}