{
  "type": "Feature",
  "properties": {
    "iso:country":"US",
    "sg:address":"2735 Melanie Ct",
    "sg:city":"Jonesboro",
    "sg:classifiers":[
        {
            "category":"Building & Trades",
            "subcategory":"Construction",
            "type":"Services"
        },
        {
            "category":"Building & Trades",
            "subcategory":"Electrical",
            "type":"Services"
        }
    ],
    "sg:phone":"+1 770 473 1535",
    "sg:postcode":"30236",
    "sg:province":"GA",
    "sg:tags":[
        "contractors-commercial",
        "industrial",
        "electrician",
        "electric",
        "contractor"
    ],
    "wof:name":"Southern Mobility Inc",
    "wof:placetype":"venue"
},
  "geometry": {"coordinates":[-84.302438,33.524873],"type":"Point"}
}