{
  "type": "Feature",
  "properties": {
    "iso:country":"US",
    "sg:address":"600 E Pine St",
    "sg:city":"Vienna",
    "sg:classifiers":[
        {
            "category":"Organizations",
            "subcategory":"Religious Organization",
            "type":"Services"
        }
    ],
    "sg:phone":"+1 229 268 5846",
    "sg:postcode":"31092",
    "sg:province":"GA",
    "sg:tags":[
        "church"
    ],
    "wof:name":"Healing & Deliverance Church",
    "wof:placetype":"venue"
},
  "geometry": {"coordinates":[-83.786461,32.095076],"type":"Point"}
}