{
  "type": "Feature",
  "properties": {
    "addr:full":"9982 Tara Blvd Hwy 19 41 Jonesboro GA 30236",
    "addr:housenumber":"9982;41",
    "addr:postcode":"30236",
    "addr:street":"Tara Blvd Hwy 19",
    "iso:country":"US",
    "sg:address":"9982 Tara Blvd Hwy 19 41",
    "sg:city":"Jonesboro",
    "sg:classifiers":[
        {
            "category":"Retail",
            "subcategory":"Auto Repair",
            "type":"Services"
        }
    ],
    "sg:phone":"+1 678 545 1295",
    "sg:postcode":"30236",
    "sg:province":"GA",
    "wof:name":"Extreme Kustoms",
    "wof:placetype":"venue"
},
  "geometry": {"coordinates":[-84.338938,33.482059],"type":"Point"}
}