{
  "type": "Feature",
  "properties": {
    "iso:country":"US",
    "sg:address":"8109 Paces Park Dr",
    "sg:city":"Decatur",
    "sg:classifiers":[
        {
            "category":"Professional",
            "subcategory":"Printing & Photocopies",
            "type":"Services"
        }
    ],
    "sg:phone":"+1 404 298 7449",
    "sg:postcode":"30033",
    "sg:province":"GA",
    "sg:tags":[
        "photographers-commercial"
    ],
    "wof:name":"Creative Images",
    "wof:placetype":"venue"
},
  "geometry": {"coordinates":[-84.274162,33.795582],"type":"Point"}
}