{
  "type": "Feature",
  "properties": {
    "iso:country":"US",
    "sg:address":"407 W 9th St",
    "sg:city":"Waynesboro",
    "sg:classifiers":[
        {
            "category":"Social Services",
            "subcategory":"Child Care",
            "type":"Services"
        }
    ],
    "sg:phone":"+1 706 554 0945",
    "sg:postcode":"30830",
    "sg:province":"GA",
    "sg:tags":[
        "day"
    ],
    "wof:name":"A Childs World Daycare",
    "wof:placetype":"venue"
},
  "geometry": {"coordinates":[-82.023551,33.094338],"type":"Point"}
}