{
  "type": "Feature",
  "properties": {
    "addr:full":"2221 Peachtree Rd NE D Atlanta GA 30309",
    "addr:housenumber":"2221",
    "addr:postcode":"30309",
    "addr:street":"Peachtree Rd Ne D",
    "iso:country":"US",
    "sg:address":"2221 Peachtree Rd NE D",
    "sg:city":"Atlanta",
    "sg:classifiers":[
        {
            "category":"Real Estate",
            "subcategory":"Real Estate Services",
            "type":"Services"
        },
        {
            "category":"Real Estate",
            "subcategory":"Real Estate Agent",
            "type":"Services"
        }
    ],
    "sg:phone":"+1 404 556 1913",
    "sg:postcode":"30309",
    "sg:province":"GA",
    "sg:tags":[
        "management"
    ],
    "wof:name":"Rei Atlanta",
    "wof:placetype":"venue"
},
  "geometry": {"coordinates":[-84.39174800000001,33.814873],"type":"Point"}
}