{
  "type": "Feature",
  "properties": {
    "addr:full":"127 E Haynes St Sandersville GA 31082",
    "addr:housenumber":"127",
    "addr:postcode":"31082",
    "addr:street":"E Haynes St",
    "iso:country":"US",
    "sg:address":"127 E Haynes St",
    "sg:city":"Sandersville",
    "sg:classifiers":[
        {
            "category":"Food & Beverages",
            "subcategory":"Meat & Fish",
            "type":"Retail Goods"
        }
    ],
    "sg:phone":"+1 478 552 3381",
    "sg:postcode":"31082",
    "sg:province":"GA",
    "wof:name":"Palace Market Processing Inc",
    "wof:placetype":"venue"
},
  "geometry": {"coordinates":[-82.810349,32.982882],"type":"Point"}
}