{
  "type": "Feature",
  "properties": {
    "iso:country":"US",
    "sg:address":"701 Winding River Way",
    "sg:city":"Woodstock",
    "sg:classifiers":[
        {
            "category":"Retail",
            "subcategory":"Repair Shop",
            "type":"Services"
        },
        {
            "category":"Manufacturing",
            "subcategory":"Signs",
            "type":"Manufacturing & Wholesale Goods"
        }
    ],
    "sg:phone":"+1 678 445 0045",
    "sg:postcode":"30188",
    "sg:province":"GA",
    "sg:tags":[
        "signs-maintenance"
    ],
    "sg:website":"http://www.highlandsigns.com",
    "wof:name":"Highland Signs",
    "wof:placetype":"venue"
},
  "geometry": {"coordinates":[-84.460358,34.11018],"type":"Point"}
}