{
  "type": "Feature",
  "properties": {
    "iso:country":"US",
    "sg:address":"900 11th St",
    "sg:city":"Macon",
    "sg:classifiers":[
        {
            "category":"Government",
            "subcategory":"Police Station",
            "type":"Public Place"
        }
    ],
    "sg:phone":"+1 478 742 0221",
    "sg:postcode":"31201",
    "sg:province":"GA",
    "sg:tags":[
        "department"
    ],
    "wof:name":"Macon Police Dept-Auto Pound",
    "wof:placetype":"venue"
},
  "geometry": {"coordinates":[-83.620853,32.819051],"type":"Point"}
}