{
  "type": "Feature",
  "properties": {
    "addr:full":"4094 Brewer Dr SW Atlanta GA 30331",
    "addr:housenumber":"4094",
    "addr:postcode":"30331",
    "addr:street":"Brewer Dr Sw",
    "iso:country":"US",
    "sg:address":"4094 Brewer Dr SW",
    "sg:city":"Atlanta",
    "sg:classifiers":[
        {
            "category":"Retail",
            "subcategory":"Auto Repair",
            "type":"Services"
        }
    ],
    "sg:phone":"+1 404 699 5578",
    "sg:postcode":"30331",
    "sg:province":"GA",
    "sg:tags":[
        "automotive"
    ],
    "wof:name":"Malone Towing Service Inc",
    "wof:placetype":"venue"
},
  "geometry": {"coordinates":[-84.520365,33.751853],"type":"Point"}
}