{
  "type": "Feature",
  "properties": {
    "addr:full":"201 Idlewood Dr Bonaire GA 31005",
    "addr:housenumber":"201",
    "addr:postcode":"31005",
    "addr:street":"Idlewood Dr",
    "iso:country":"US",
    "sg:address":"201 Idlewood Dr",
    "sg:city":"Bonaire",
    "sg:classifiers":[
        {
            "category":"Insurance",
            "subcategory":"Insurance Agent",
            "type":"Services"
        }
    ],
    "sg:phone":"+1 478 929 2478",
    "sg:postcode":"31005",
    "sg:province":"GA",
    "wof:name":"Jasons Ltd",
    "wof:placetype":"venue"
},
  "geometry": {"coordinates":[-83.63951299999999,32.573921],"type":"Point"}
}