{
  "type": "Feature",
  "properties": {
    "addr:full":"32 Frank St SW Marietta GA 30008",
    "addr:housenumber":"32",
    "addr:postcode":"30008",
    "addr:street":"Frank St Sw",
    "iso:country":"US",
    "sg:address":"32 Frank St SW",
    "sg:city":"Marietta",
    "sg:classifiers":[
        {
            "category":"Building & Trades",
            "subcategory":"Landscaping Services",
            "type":"Services"
        }
    ],
    "sg:phone":"+1 678 354 1833",
    "sg:postcode":"30008",
    "sg:province":"GA",
    "sg:tags":[
        "landscape"
    ],
    "wof:name":"Morales Landscaping",
    "wof:placetype":"venue"
},
  "geometry": {"coordinates":[-84.55732,33.931929],"type":"Point"}
}