{
  "type": "Feature",
  "properties": {
    "addr:full":"1 Skc Dr Covington GA 30014",
    "addr:housenumber":"1",
    "addr:postcode":"30014",
    "addr:street":"Skc Dr",
    "iso:country":"US",
    "sg:address":"1 Skc Dr",
    "sg:city":"Covington",
    "sg:classifiers":[
        {
            "category":"Manufacturing",
            "subcategory":"Rubber & Plastics",
            "type":"Manufacturing & Wholesale Goods"
        }
    ],
    "sg:phone":"+1 678 342 1000",
    "sg:postcode":"30014",
    "sg:province":"GA",
    "sg:tags":[
        "polyester",
        "film",
        "mfg"
    ],
    "sg:website":"www.skcfilms.com",
    "wof:name":"SKC Inc",
    "wof:placetype":"venue"
},
  "geometry": {"coordinates":[-83.816425,33.618089],"type":"Point"}
}