{
  "type": "Feature",
  "properties": {
    "iso:country":"US",
    "sg:address":"2070 Black Fox Dr NE",
    "sg:city":"Atlanta",
    "sg:classifiers":[
        {
            "category":"Home & Garden",
            "subcategory":"Building Materials",
            "type":"Retail Goods"
        }
    ],
    "sg:phone":"+1 404 634 4531",
    "sg:postcode":"30345",
    "sg:province":"GA",
    "wof:name":"Glass House Fabricators Inc",
    "wof:placetype":"venue"
},
  "geometry": {"coordinates":[-84.303104,33.826624],"type":"Point"}
}