{
  "type": "Feature",
  "properties": {
    "addr:full":"679 Johnson Ferry Rd Marietta GA 30068",
    "addr:housenumber":"679",
    "addr:postcode":"30068",
    "addr:street":"Johnson Ferry Rd",
    "iso:country":"US",
    "sg:address":"679 Johnson Ferry Rd",
    "sg:city":"Marietta",
    "sg:classifiers":[
        {
            "category":"Retail",
            "subcategory":"Auto Repair",
            "type":"Services"
        }
    ],
    "sg:phone":"+1 770 971 1331",
    "sg:postcode":"30068",
    "sg:province":"GA",
    "sg:tags":[
        "body",
        "automobile",
        "painting",
        "general"
    ],
    "wof:name":"Ellison's Body Shop",
    "wof:placetype":"venue"
},
  "geometry": {"coordinates":[-84.411726,33.965537],"type":"Point"}
}