{
  "type": "Feature",
  "properties": {
    "addr:full":"5413 Amity Dr Powder Springs GA 30127",
    "addr:housenumber":"5413",
    "addr:postcode":"30127",
    "addr:street":"Amity Dr",
    "iso:country":"US",
    "sg:address":"5413 Amity Dr",
    "sg:city":"Powder Springs",
    "sg:classifiers":[
        {
            "category":"Real Estate",
            "subcategory":"Architect",
            "type":"Services"
        }
    ],
    "sg:phone":"+1 770 439 7836",
    "sg:postcode":"30127",
    "sg:province":"GA",
    "sg:tags":[
        "architectural"
    ],
    "wof:name":"Jim Godino",
    "wof:placetype":"venue"
},
  "geometry": {"coordinates":[-84.713286,33.918985],"type":"Point"}
}