{
  "type": "Feature",
  "properties": {
    "addr:full":"800 Daniel St Waycross GA 31501",
    "addr:housenumber":"800",
    "addr:postcode":"31501",
    "addr:street":"Daniel St",
    "iso:country":"US",
    "sg:address":"800 Daniel St",
    "sg:city":"Waycross",
    "sg:classifiers":[
        {
            "category":"Organizations",
            "subcategory":"Religious Organization",
            "type":"Services"
        }
    ],
    "sg:phone":"+1 912 283 1071",
    "sg:postcode":"31501",
    "sg:province":"GA",
    "wof:name":"Church Of God In Christ",
    "wof:placetype":"venue"
},
  "geometry": {"coordinates":[-82.359549,31.222554],"type":"Point"}
}