{
  "type": "Feature",
  "properties": {
    "addr:full":"6746 Baynes Hill Dr Clarkston GA 30021",
    "addr:housenumber":"6746",
    "addr:postcode":"30021",
    "addr:street":"Baynes Hill Dr",
    "iso:country":"US",
    "sg:address":"6746 Baynes Hill Dr",
    "sg:city":"Clarkston",
    "sg:classifiers":[
        {
            "category":"Retail",
            "subcategory":"Auto Repair",
            "type":"Services"
        }
    ],
    "sg:phone":"+1 404 299 8477",
    "sg:postcode":"30021",
    "sg:province":"GA",
    "sg:tags":[
        "repairing",
        "automobile"
    ],
    "wof:name":"Prime Auto Svc",
    "wof:placetype":"venue"
},
  "geometry": {"coordinates":[-84.227439,33.799296],"type":"Point"}
}