{
  "type": "Feature",
  "properties": {
    "iso:country":"US",
    "sg:address":"6555 Mcdonough Dr",
    "sg:city":"Norcross",
    "sg:classifiers":[
        {
            "category":"Insurance",
            "subcategory":"Insurance Agent",
            "type":"Services"
        },
        {
            "category":"Insurance",
            "subcategory":"Hazard Insurance",
            "type":"Services"
        }
    ],
    "sg:phone":"+1 770 326 5410",
    "sg:postcode":"30093",
    "sg:province":"GA",
    "sg:tags":[
        "fire",
        "property",
        "casualty"
    ],
    "wof:name":"Waco Fire & Casualty",
    "wof:placetype":"venue"
},
  "geometry": {"coordinates":[-84.222745,33.903198],"type":"Point"}
}