{
  "type": "Feature",
  "properties": {
    "iso:country":"US",
    "sg:address":"895 S 1st St",
    "sg:city":"Jesup",
    "sg:classifiers":[
        {
            "category":"Insurance",
            "subcategory":"Insurance Agent",
            "type":"Services"
        },
        {
            "category":"Insurance",
            "subcategory":"Hazard Insurance",
            "type":"Services"
        },
        {
            "category":"Insurance",
            "subcategory":"Title Insurance",
            "type":"Services"
        },
        {
            "category":"Insurance",
            "subcategory":"Life Insurance",
            "type":"Services"
        }
    ],
    "sg:phone":"+1 912 385 2301",
    "sg:postcode":"31545",
    "sg:province":"GA",
    "sg:tags":[
        "business",
        "auto",
        "commercial",
        "homeowner",
        "motorcycle",
        "renter"
    ],
    "wof:name":"Allstate Insurance Company - Lynn Bennett",
    "wof:placetype":"venue"
},
  "geometry": {"coordinates":[-81.87685399999999,31.614682],"type":"Point"}
}