{
  "type": "Feature",
  "properties": {
    "iso:country":"US",
    "sg:address":"3141 Piedmont Road NE",
    "sg:city":"Atlanta",
    "sg:classifiers":[
        {
            "category":"Retail",
            "subcategory":"Portrait Studio",
            "type":"Services"
        }
    ],
    "sg:phone":"+1 404 869 1116",
    "sg:postcode":"30305",
    "sg:province":"GA",
    "sg:tags":[
        "photography",
        "store"
    ],
    "sg:website":"www.wolfcamera.com",
    "wof:name":"Wolf Camera Ultra",
    "wof:placetype":"venue"
},
  "geometry": {"coordinates":[-84.370712,33.842383],"type":"Point"}
}