{
  "type": "Feature",
  "properties": {
    "addr:full":"1800 James Jackson Pkwy NW Atlanta GA 30318",
    "addr:housenumber":"1800",
    "addr:postcode":"30318",
    "addr:street":"James Jackson Pkwy Nw",
    "iso:country":"US",
    "sg:address":"1800 James Jackson Pkwy NW",
    "sg:city":"Atlanta",
    "sg:classifiers":[
        {
            "category":"Banks & Credit Unions",
            "subcategory":"Bank",
            "type":"Services"
        }
    ],
    "sg:phone":"+1 404 792 8560",
    "sg:postcode":"30318",
    "sg:province":"GA",
    "sg:website":"www.apcu.com",
    "wof:name":"Atlanta Postal Credit Union",
    "wof:placetype":"venue"
},
  "geometry": {"coordinates":[-84.475782,33.804608],"type":"Point"}
}