{
  "type": "Feature",
  "properties": {
    "iso:country":"US",
    "sg:address":"2745 Sandy Plains Rd NE",
    "sg:city":"Marietta",
    "sg:classifiers":[
        {
            "category":"Manufacturing",
            "subcategory":"Toys & Sporting Goods",
            "type":"Manufacturing & Wholesale Goods"
        }
    ],
    "sg:phone":"+1 770 578 1112",
    "sg:postcode":"30066",
    "sg:province":"GA",
    "sg:tags":[
        "mfg"
    ],
    "wof:name":"Colossal Games & Cards",
    "wof:placetype":"venue"
},
  "geometry": {"coordinates":[-84.49254999999999,34.016603],"type":"Point"}
}