{
  "type": "Feature",
  "properties": {
    "iso:country":"US",
    "sg:address":"173 Floyd Rd",
    "sg:city":"Danielsville",
    "sg:classifiers":[
        {
            "category":"Building & Trades",
            "subcategory":"Plumbing",
            "type":"Services"
        }
    ],
    "sg:phone":"+1 706 789 2659",
    "sg:postcode":"30633",
    "sg:province":"GA",
    "sg:tags":[
        "plumbing",
        "contractor"
    ],
    "wof:name":"Chandler Plumbing & Well Svc",
    "wof:placetype":"venue"
},
  "geometry": {"coordinates":[-83.265514,34.148896],"type":"Point"}
}