{
  "type": "Feature",
  "properties": {
    "iso:country":"US",
    "sg:address":"3155 Presidential Dr",
    "sg:city":"Atlanta",
    "sg:classifiers":[
        {
            "category":"Food & Beverages",
            "subcategory":"Groceries & Convenience Stores",
            "type":"Retail Goods"
        }
    ],
    "sg:phone":"+1 770 457 7404",
    "sg:postcode":"30340",
    "sg:province":"GA",
    "wof:name":"ATL Destinations & Concierge",
    "wof:placetype":"venue"
},
  "geometry": {"coordinates":[-84.259765,33.886731],"type":"Point"}
}