{
  "type": "Feature",
  "properties": {
    "addr:full":"241 W Wieuca Rd NE Atlanta GA 30342",
    "addr:housenumber":"241",
    "addr:postcode":"30342",
    "addr:street":"W Wieuca Rd Ne",
    "iso:country":"US",
    "sg:address":"241 W Wieuca Rd NE",
    "sg:city":"Atlanta",
    "sg:classifiers":[
        {
            "category":"Insurance",
            "subcategory":"Life Insurance",
            "type":"Services"
        }
    ],
    "sg:phone":"+1 404 252 0044",
    "sg:postcode":"30342",
    "sg:province":"GA",
    "sg:website":"http://www.ashfinancialgroup.com",
    "wof:name":"Jefferson-Pilot Life Insurance Co",
    "wof:placetype":"venue"
},
  "geometry": {"coordinates":[-84.378879,33.876406],"type":"Point"}
}