{
  "type": "Feature",
  "properties": {
    "iso:country":"US",
    "sg:address":"313 W Pine St",
    "sg:city":"Fitzgerald",
    "sg:classifiers":[
        {
            "category":"Building & Trades",
            "subcategory":"Electrical",
            "type":"Services"
        }
    ],
    "sg:phone":"+1 229 423 5851",
    "sg:postcode":"31750",
    "sg:province":"GA",
    "sg:tags":[
        "electrician"
    ],
    "wof:name":"Wes Electric",
    "wof:placetype":"venue"
},
  "geometry": {"coordinates":[-83.257338,31.713559],"type":"Point"}
}