{
  "type": "Feature",
  "properties": {
    "iso:country":"US",
    "sg:address":"41 Old Mill Ct",
    "sg:city":"Atlanta",
    "sg:classifiers":[
        {
            "category":"Building & Trades",
            "subcategory":"Construction",
            "type":"Services"
        }
    ],
    "sg:phone":"+1 404 842 0538",
    "sg:postcode":"30349",
    "sg:province":"GA",
    "sg:tags":[
        "house"
    ],
    "wof:name":"Quad Incorporated",
    "wof:placetype":"venue"
},
  "geometry": {"coordinates":[-84.432273,33.601607],"type":"Point"}
}