{
  "type": "Feature",
  "properties": {
    "iso:country":"US",
    "sg:address":"518 Atlanta St SE",
    "sg:city":"Marietta",
    "sg:classifiers":[
        {
            "category":"Retail",
            "subcategory":"Auto Repair",
            "type":"Services"
        }
    ],
    "sg:phone":"+1 770 427 0017",
    "sg:postcode":"30060",
    "sg:province":"GA",
    "wof:name":"Butler Automotive",
    "wof:placetype":"venue"
},
  "geometry": {"coordinates":[-84.54471100000001,33.939765],"type":"Point"}
}