{
  "type": "Feature",
  "properties": {
    "iso:country":"US",
    "sg:address":"2091 Cherry Ln",
    "sg:city":"Decatur",
    "sg:classifiers":[
        {
            "category":"Home & Garden",
            "subcategory":"Garden Supply",
            "type":"Retail Goods"
        }
    ],
    "sg:phone":"+1 404 241 9427",
    "sg:postcode":"30032",
    "sg:province":"GA",
    "sg:tags":[
        "horticulture",
        "product"
    ],
    "wof:name":"Sky Edge Landscaping",
    "wof:placetype":"venue"
},
  "geometry": {"coordinates":[-84.30497,33.722112],"type":"Point"}
}