{
  "type": "Feature",
  "properties": {
    "iso:country":"US",
    "sg:address":"1107 Virginia St",
    "sg:city":"Columbus",
    "sg:classifiers":[
        {
            "category":"Retail",
            "subcategory":"Portrait Studio",
            "type":"Services"
        }
    ],
    "sg:phone":"+1 706 653 2580",
    "sg:postcode":"31901",
    "sg:province":"GA",
    "sg:tags":[
        "photo",
        "merchandise"
    ],
    "wof:name":"Thats Our Baby",
    "wof:placetype":"venue"
},
  "geometry": {"coordinates":[-84.976179,32.473619],"type":"Point"}
}