{
  "type": "Feature",
  "properties": {
    "iso:country":"US",
    "sg:address":"1629 Bridge Mill Dr",
    "sg:city":"Marietta",
    "sg:classifiers":[
        {
            "category":"Building & Trades",
            "subcategory":"Construction",
            "type":"Services"
        }
    ],
    "sg:phone":"+1 770 607 3832",
    "sg:postcode":"30067",
    "sg:province":"GA",
    "sg:tags":[
        "general",
        "contractor"
    ],
    "wof:name":"Kevin Yetman Construction",
    "wof:placetype":"venue"
},
  "geometry": {"coordinates":[-84.476826,33.914211],"type":"Point"}
}