{
  "type": "Feature",
  "properties": {
    "addr:full":"455 Casteel Rd Marietta GA 30064",
    "addr:housenumber":"455",
    "addr:postcode":"30064",
    "addr:street":"Casteel Rd",
    "iso:country":"US",
    "sg:address":"455 Casteel Rd",
    "sg:city":"Marietta",
    "sg:classifiers":[
        {
            "category":"Organizations",
            "subcategory":"Religious Organization",
            "type":"Services"
        }
    ],
    "sg:phone":"+1 770 427 3624",
    "sg:postcode":"30064",
    "sg:province":"GA",
    "wof:name":"Marantha Assembly",
    "wof:placetype":"venue"
},
  "geometry": {"coordinates":[-84.663645,33.941421],"type":"Point"}
}