{
  "type": "Feature",
  "properties": {
    "iso:country":"US",
    "sg:address":"3620 Kennesaw Dr NW",
    "sg:city":"Kennesaw",
    "sg:classifiers":[
        {
            "category":"Professional",
            "subcategory":"Computer Services",
            "type":"Services"
        }
    ],
    "sg:phone":"+1 770 436 2324",
    "sg:postcode":"30144",
    "sg:province":"GA",
    "sg:tags":[
        "repair"
    ],
    "wof:name":"Computer Concepts Services",
    "wof:placetype":"venue"
},
  "geometry": {"coordinates":[-84.622173,34.018411],"type":"Point"}
}