{
  "type": "Feature",
  "properties": {
    "addr:full":"202 Brumbelow Rd Carrollton GA 30117",
    "addr:housenumber":"202",
    "addr:postcode":"30117",
    "addr:street":"Brumbelow Rd",
    "iso:country":"US",
    "sg:address":"202 Brumbelow Rd",
    "sg:city":"Carrollton",
    "sg:classifiers":[
        {
            "category":"Restaurant",
            "type":"Food & Drink"
        }
    ],
    "sg:phone":"+1 770 832 3664",
    "sg:postcode":"30117",
    "sg:province":"GA",
    "wof:name":"T C Rose",
    "wof:placetype":"venue"
},
  "geometry": {"coordinates":[-85.098404,33.581676],"type":"Point"}
}