{
  "type": "Feature",
  "properties": {
    "iso:country":"US",
    "sg:address":"570 Piedmont Ave NE",
    "sg:city":"Atlanta",
    "sg:classifiers":[
        {
            "category":"Wholesale",
            "subcategory":"Computers",
            "type":"Manufacturing & Wholesale Goods"
        }
    ],
    "sg:phone":"+1 770 941 4171",
    "sg:postcode":"30308",
    "sg:province":"GA",
    "wof:name":"Vause Computer Systems Inc",
    "wof:placetype":"venue"
},
  "geometry": {"coordinates":[-84.381967,33.771197],"type":"Point"}
}