{
  "type": "Feature",
  "properties": {
    "addr:full":"3177 Helen Hwy Cleveland GA 30528",
    "addr:housenumber":"3177",
    "addr:postcode":"30528",
    "addr:street":"Helen Hwy",
    "iso:country":"US",
    "sg:address":"3177 Helen Hwy",
    "sg:city":"Cleveland",
    "sg:classifiers":[
        {
            "category":"Manufacturing",
            "subcategory":"Furniture",
            "type":"Manufacturing & Wholesale Goods"
        }
    ],
    "sg:phone":"+1 770 888 9945",
    "sg:postcode":"30528",
    "sg:province":"GA",
    "sg:tags":[
        "building",
        "public",
        "mfg"
    ],
    "wof:name":"Camp Installations",
    "wof:placetype":"venue"
},
  "geometry": {"coordinates":[-83.74105900000001,34.640912],"type":"Point"}
}