{
  "type": "Feature",
  "properties": {
    "iso:country":"US",
    "sg:address":"205 E Greene St",
    "sg:city":"Greensboro",
    "sg:classifiers":[
        {
            "category":"Government",
            "subcategory":"Police Station",
            "type":"Public Place"
        }
    ],
    "sg:phone":"+1 706 453 3350",
    "sg:postcode":"30642",
    "sg:province":"GA",
    "sg:tags":[
        "sheriff"
    ],
    "wof:name":"Greene County Police",
    "wof:placetype":"venue"
},
  "geometry": {"coordinates":[-83.18092300000001,33.576855],"type":"Point"}
}