{
  "type": "Feature",
  "properties": {
    "iso:country":"US",
    "sg:address":"212 E Church St",
    "sg:city":"Cartersville",
    "sg:classifiers":[
        {
            "category":"Health Services",
            "subcategory":"Doctor",
            "type":"Services"
        }
    ],
    "sg:phone":"+1 770 382 1215",
    "sg:postcode":"30120",
    "sg:province":"GA",
    "sg:tags":[
        "dentist"
    ],
    "wof:name":"Family Dental Assoc",
    "wof:placetype":"venue"
},
  "geometry": {"coordinates":[-84.790111,34.168623],"type":"Point"}
}