{
  "type": "Feature",
  "properties": {
    "iso:country":"US",
    "sg:address":"1598 Bankhead Hwy NW",
    "sg:city":"Atlanta",
    "sg:classifiers":[
        {
            "category":"Autos & Motor Vehicles",
            "subcategory":"Auto Supplies",
            "type":"Retail Goods"
        }
    ],
    "sg:phone":"+1 404 792 0721",
    "sg:postcode":"30318",
    "sg:province":"GA",
    "sg:tags":[
        "automobile",
        "parts"
    ],
    "wof:name":"Autozone",
    "wof:placetype":"venue"
},
  "geometry": {"coordinates":[-84.44119999999999,33.77243],"type":"Point"}
}