{
  "type": "Feature",
  "properties": {
    "addr:full":"5450 McGinnis Ferry Rd Alpharetta GA 30005",
    "addr:postcode":"5450;30005",
    "addr:street":"Mcginnis Ferry Rd",
    "iso:country":"US",
    "sg:address":"5450 McGinnis Ferry Rd",
    "sg:city":"Alpharetta",
    "sg:classifiers":[
        {
            "category":"Real Estate",
            "subcategory":"Real Estate Agent",
            "type":"Services"
        }
    ],
    "sg:phone":"+1 770 346 0080",
    "sg:postcode":"30005",
    "sg:province":"GA",
    "wof:name":"Lyles Rl Est & Invstmnt Grp",
    "wof:placetype":"venue"
},
  "geometry": {"coordinates":[-84.19650300000001,34.088503],"type":"Point"}
}