{
  "type": "Feature",
  "properties": {
    "iso:country":"US",
    "sg:address":"4800 Briarcliff Rd NE",
    "sg:city":"Atlanta",
    "sg:classifiers":[
        {
            "category":"Personal",
            "subcategory":"Shoe Repair & Shine",
            "type":"Services"
        }
    ],
    "sg:phone":"+1 770 496 0021",
    "sg:postcode":"30345",
    "sg:province":"GA",
    "sg:tags":[
        "repairing",
        "boot"
    ],
    "wof:name":"Hakky Instant Shoe Repair",
    "wof:placetype":"venue"
},
  "geometry": {"coordinates":[-84.255785,33.848165],"type":"Point"}
}