{
  "type": "Feature",
  "properties": {
    "addr:full":"10305 Abercorn St Savannah GA 31406",
    "addr:housenumber":"10305",
    "addr:postcode":"31406",
    "addr:street":"Abercorn St",
    "iso:country":"US",
    "sg:address":"10305 Abercorn St",
    "sg:city":"Savannah",
    "sg:classifiers":[
        {
            "category":"Home & Garden",
            "subcategory":"Furniture",
            "type":"Retail Goods"
        }
    ],
    "sg:phone":"+1 912 920 1266",
    "sg:postcode":"31406",
    "sg:province":"GA",
    "wof:name":"Farmers Furniture",
    "wof:placetype":"venue"
},
  "geometry": {"coordinates":[-81.13044600000001,31.990736],"type":"Point"}
}