{
  "type": "Feature",
  "properties": {
    "iso:country":"US",
    "sg:address":"4737 Young Harris Hwy",
    "sg:city":"Blairsville",
    "sg:classifiers":[
        {
            "category":"Building & Trades",
            "subcategory":"Construction",
            "type":"Services"
        }
    ],
    "sg:phone":"+1 706 379 1269",
    "sg:postcode":"30512",
    "sg:province":"GA",
    "sg:tags":[
        "builder",
        "operative"
    ],
    "wof:name":"Magestic Matineelike Prpts",
    "wof:placetype":"venue"
},
  "geometry": {"coordinates":[-83.884852,34.907031],"type":"Point"}
}