{
  "type": "Feature",
  "properties": {
    "iso:country":"US",
    "sg:address":"4259 Shipyard Trce",
    "sg:city":"Roswell",
    "sg:classifiers":[
        {
            "category":"Personal",
            "subcategory":"Beauty Salon",
            "type":"Services"
        }
    ],
    "sg:phone":"+1 770 998 7765",
    "sg:postcode":"30075",
    "sg:province":"GA",
    "sg:tags":[
        "shop"
    ],
    "wof:name":"Patricia Kallen",
    "wof:placetype":"venue"
},
  "geometry": {"coordinates":[-84.425416,34.037617],"type":"Point"}
}