{
  "type": "Feature",
  "properties": {
    "addr:full":"4721 Fellswood Dr Stone Mountain GA 30083",
    "addr:housenumber":"4721",
    "addr:postcode":"30083",
    "addr:street":"Fellswood Dr",
    "iso:country":"US",
    "sg:address":"4721 Fellswood Dr",
    "sg:city":"Stone Mountain",
    "sg:classifiers":[
        {
            "category":"Freight",
            "type":"Transportation"
        }
    ],
    "sg:phone":"+1 404 296 0737",
    "sg:postcode":"30083",
    "sg:province":"GA",
    "sg:tags":[
        "operator",
        "local",
        "trucking"
    ],
    "wof:name":"C&G Trucking Inc",
    "wof:placetype":"venue"
},
  "geometry": {"coordinates":[-84.194835,33.804546],"type":"Point"}
}