{
  "type": "Feature",
  "properties": {
    "addr:full":"4355 River Green Pkwy # 100 Duluth GA 30096",
    "addr:housenumber":"4355",
    "addr:postcode":"30096",
    "addr:street":"River Green Pkwy # 100",
    "iso:country":"US",
    "sg:address":"4355 River Green Pkwy # 100",
    "sg:city":"Duluth",
    "sg:classifiers":[
        {
            "category":"Travel",
            "subcategory":"Travel Agent",
            "type":"Entertainment"
        }
    ],
    "sg:phone":"+1 770 291 4200",
    "sg:postcode":"30096",
    "sg:province":"GA",
    "sg:tags":[
        "agency",
        "services-commercial"
    ],
    "wof:name":"Will Brown",
    "wof:placetype":"venue"
},
  "geometry": {"coordinates":[-84.16797,34.020483],"type":"Point"}
}