{
  "type": "Feature",
  "properties": {
    "iso:country":"US",
    "sg:address":"1490 Cameron Glen Dr",
    "sg:city":"Marietta",
    "sg:classifiers":[
        {
            "category":"Personal",
            "subcategory":"Beauty Salon",
            "type":"Services"
        }
    ],
    "sg:phone":"+1 770 434 7722",
    "sg:postcode":"30062",
    "sg:province":"GA",
    "sg:tags":[
        "hair"
    ],
    "wof:name":"Vanity Salon",
    "wof:placetype":"venue"
},
  "geometry": {"coordinates":[-84.508414,33.982955],"type":"Point"}
}