{
  "type": "Feature",
  "properties": {
    "addr:full":"3645 Oakcliff Rd Atlanta GA 30340",
    "addr:housenumber":"3645",
    "addr:postcode":"30340",
    "addr:street":"Oakcliff Rd",
    "iso:country":"US",
    "sg:address":"3645 Oakcliff Rd",
    "sg:city":"Atlanta",
    "sg:classifiers":[
        {
            "category":"Wholesale",
            "subcategory":"Non-durable Goods",
            "type":"Manufacturing & Wholesale Goods"
        }
    ],
    "sg:phone":"+1 770 448 5600",
    "sg:postcode":"30340",
    "sg:province":"GA",
    "sg:tags":[
        "store",
        "merchandise",
        "variety"
    ],
    "wof:name":"Coastline Int Dist Ltd",
    "wof:placetype":"venue"
},
  "geometry": {"coordinates":[-84.250507,33.901117],"type":"Point"}
}