{
  "type": "Feature",
  "properties": {
    "addr:full":"1551 Jennings Mill Rd Bogart GA 30622",
    "addr:housenumber":"1551",
    "addr:postcode":"30622",
    "addr:street":"Jennings Mill Rd",
    "iso:country":"US",
    "sg:address":"1551 Jennings Mill Rd",
    "sg:city":"Bogart",
    "sg:classifiers":[
        {
            "category":"Professional",
            "type":"Services"
        }
    ],
    "sg:phone":"+1 706 549 5600",
    "sg:postcode":"30622",
    "sg:province":"GA",
    "sg:tags":[
        "establishment"
    ],
    "wof:name":"Riverstar Group LLC",
    "wof:placetype":"venue"
},
  "geometry": {"coordinates":[-83.46213899999999,33.924411],"type":"Point"}
}