{
  "type": "Feature",
  "properties": {
    "iso:country":"US",
    "sg:address":"3877 Manson Ave",
    "sg:city":"Smyrna",
    "sg:classifiers":[
        {
            "category":"Professional",
            "subcategory":"Engineering",
            "type":"Services"
        }
    ],
    "sg:phone":"+1 770 436 6052",
    "sg:postcode":"30082",
    "sg:province":"GA",
    "wof:name":"Martin Engineering Inc",
    "wof:placetype":"venue"
},
  "geometry": {"coordinates":[-84.54447399999999,33.860013],"type":"Point"}
}