{
  "type": "Feature",
  "properties": {
    "iso:country":"US",
    "sg:address":"1124 Lockwood Ave",
    "sg:city":"Columbus",
    "sg:classifiers":[
        {
            "category":"Wholesale",
            "subcategory":"Electrical",
            "type":"Manufacturing & Wholesale Goods"
        }
    ],
    "sg:phone":"+1 706 571 9291",
    "sg:postcode":"31906",
    "sg:province":"GA",
    "sg:tags":[
        "equipment"
    ],
    "wof:name":"Alarm Communications Inc",
    "wof:placetype":"venue"
},
  "geometry": {"coordinates":[-84.962103,32.468497],"type":"Point"}
}