{
  "type": "Feature",
  "properties": {
    "addr:full":"3323 Bemiss Rd Valdosta GA 31605",
    "addr:housenumber":"3323",
    "addr:postcode":"31605",
    "addr:street":"Bemiss Rd",
    "iso:country":"US",
    "sg:address":"3323 Bemiss Rd",
    "sg:city":"Valdosta",
    "sg:classifiers":[
        {
            "category":"Building & Trades",
            "subcategory":"Construction",
            "type":"Services"
        }
    ],
    "sg:phone":"+1 229 247 0754",
    "sg:postcode":"31605",
    "sg:province":"GA",
    "sg:tags":[
        "general",
        "contractor"
    ],
    "wof:name":"Tom Coody Construction Co",
    "wof:placetype":"venue"
},
  "geometry": {"coordinates":[-83.272851,30.884369],"type":"Point"}
}