{
  "type": "Feature",
  "properties": {
    "addr:full":"1718 Brown Rd Hephzibah GA 30815",
    "addr:housenumber":"1718",
    "addr:postcode":"30815",
    "addr:street":"Brown Rd",
    "iso:country":"US",
    "sg:address":"1718 Brown Rd",
    "sg:city":"Hephzibah",
    "sg:classifiers":[
        {
            "category":"Shopping",
            "subcategory":"Department Store",
            "type":"Retail Goods"
        }
    ],
    "sg:phone":"+1 706 592 3637",
    "sg:postcode":"30815",
    "sg:province":"GA",
    "sg:tags":[
        "shop"
    ],
    "wof:name":"Dollar General",
    "wof:placetype":"venue"
},
  "geometry": {"coordinates":[-81.96003399999999,33.319279],"type":"Point"}
}