{
  "type": "Feature",
  "properties": {
    "iso:country":"US",
    "sg:address":"102 E Calhoun St",
    "sg:city":"Bainbridge",
    "sg:classifiers":[
        {
            "category":"Autos & Motor Vehicles",
            "subcategory":"Automobile Sales",
            "type":"Retail Goods"
        }
    ],
    "sg:phone":"+1 229 246 6268",
    "sg:postcode":"39817",
    "sg:province":"GA",
    "sg:tags":[
        "car",
        "dealer"
    ],
    "wof:name":"C & J Enterprises",
    "wof:placetype":"venue"
},
  "geometry": {"coordinates":[-84.57659099999999,30.909329],"type":"Point"}
}