{
  "type": "Feature",
  "properties": {
    "addr:full":"1970 Riverside Pkwy Lawrenceville GA 30043",
    "addr:housenumber":"1970",
    "addr:postcode":"30043",
    "addr:street":"Riverside Pkwy",
    "iso:country":"US",
    "sg:address":"1970 Riverside Pkwy",
    "sg:city":"Lawrenceville",
    "sg:classifiers":[
        {
            "category":"Professional",
            "subcategory":"Lawyer & Legal Services",
            "type":"Services"
        }
    ],
    "sg:phone":"+1 770 995 2581",
    "sg:postcode":"30043",
    "sg:province":"GA",
    "sg:tags":[
        "attorney"
    ],
    "wof:name":"Primerica Mc Dade Assoc",
    "wof:placetype":"venue"
},
  "geometry": {"coordinates":[-84.023377,33.984451],"type":"Point"}
}