{
  "type": "Feature",
  "properties": {
    "addr:full":"570 Mulberry St Macon GA 31201",
    "addr:housenumber":"570",
    "addr:postcode":"31201",
    "addr:street":"Mulberry St",
    "iso:country":"US",
    "sg:address":"570 Mulberry St",
    "sg:city":"Macon",
    "sg:classifiers":[
        {
            "category":"Wholesale",
            "subcategory":"Furniture",
            "type":"Manufacturing & Wholesale Goods"
        }
    ],
    "sg:phone":"+1 478 765 1515",
    "sg:postcode":"31201",
    "sg:province":"GA",
    "sg:tags":[
        "commercial"
    ],
    "wof:name":"Commercial Furnishings Inc",
    "wof:placetype":"venue"
},
  "geometry": {"coordinates":[-83.627562,32.83741],"type":"Point"}
}