{
  "type": "Feature",
  "properties": {
    "addr:full":"212 Ridley Howard Ct Decatur GA 30030",
    "addr:housenumber":"212",
    "addr:postcode":"30030",
    "addr:street":"Ridley Howard Ct",
    "iso:country":"US",
    "sg:address":"212 Ridley Howard Ct",
    "sg:city":"Decatur",
    "sg:classifiers":[
        {
            "category":"Professional",
            "subcategory":"Engineering",
            "type":"Services"
        }
    ],
    "sg:phone":"+1 404 378 6660",
    "sg:postcode":"30030",
    "sg:province":"GA",
    "wof:name":"Georgia Carolina Engineering",
    "wof:placetype":"venue"
},
  "geometry": {"coordinates":[-84.3044,33.7843],"type":"Point"}
}