{
  "type": "Feature",
  "properties": {
    "addr:full":"9898 State Hwy 92 Woodstock GA 30188",
    "addr:housenumber":"9898",
    "addr:postcode":"30188",
    "addr:street":"State Hwy 92",
    "iso:country":"US",
    "sg:address":"9898 State Hwy 92",
    "sg:city":"Woodstock",
    "sg:classifiers":[
        {
            "category":"Professional",
            "subcategory":"Lawyer & Legal Services",
            "type":"Services"
        }
    ],
    "sg:phone":"+1 770 926 2956",
    "sg:postcode":"30188",
    "sg:province":"GA",
    "sg:tags":[
        "attorney"
    ],
    "wof:name":"Clark & Washington",
    "wof:placetype":"venue"
},
  "geometry": {"coordinates":[-84.524073,34.086253],"type":"Point"}
}