{
  "type": "Feature",
  "properties": {
    "iso:country":"US",
    "sg:address":"25034 Gardner Dr",
    "sg:city":"Alpharetta",
    "sg:classifiers":[
        {
            "category":"Professional",
            "type":"Services"
        }
    ],
    "sg:phone":"+1 678 366 9255",
    "sg:postcode":"30004",
    "sg:province":"GA",
    "wof:name":"Harvest Consulting",
    "wof:placetype":"venue"
},
  "geometry": {"coordinates":[-84.288329,34.067784],"type":"Point"}
}