{
  "type": "Feature",
  "properties": {
    "iso:country":"US",
    "sg:address":"10880 Medlock Bridge Rd",
    "sg:city":"Duluth",
    "sg:classifiers":[
        {
            "category":"Building & Trades",
            "subcategory":"Construction",
            "type":"Services"
        }
    ],
    "sg:phone":"+1 678 417 1692",
    "sg:postcode":"30097",
    "sg:province":"GA",
    "sg:tags":[
        "home",
        "builder"
    ],
    "wof:name":"Beazer Homes",
    "wof:placetype":"venue"
},
  "geometry": {"coordinates":[-84.18066399999999,34.044237],"type":"Point"}
}