{
  "type": "Feature",
  "properties": {
    "addr:full":"3101 Barnard St Savannah GA 31405",
    "addr:housenumber":"3101",
    "addr:postcode":"31405",
    "addr:street":"Barnard St",
    "iso:country":"US",
    "sg:address":"3101 Barnard St",
    "sg:city":"Savannah",
    "sg:classifiers":[
        {
            "category":"Building & Trades",
            "subcategory":"Construction",
            "type":"Services"
        }
    ],
    "sg:phone":"+1 912 236 6018",
    "sg:postcode":"31405",
    "sg:province":"GA",
    "sg:tags":[
        "fabricator",
        "metal"
    ],
    "wof:name":"Drainage Specialties",
    "wof:placetype":"venue"
},
  "geometry": {"coordinates":[-81.10523499999999,32.049617],"type":"Point"}
}