{
  "type": "Feature",
  "properties": {
    "iso:country":"US",
    "sg:address":"4235 Fairway Villas Dr",
    "sg:city":"Alpharetta",
    "sg:classifiers":[
        {
            "category":"Professional",
            "subcategory":"Business Services",
            "type":"Services"
        }
    ],
    "sg:phone":"+1 770 569 9499",
    "sg:postcode":"30022",
    "sg:province":"GA",
    "wof:name":"Miller Black",
    "wof:placetype":"venue"
},
  "geometry": {"coordinates":[-84.237431,34.010871],"type":"Point"}
}