{
  "type": "Feature",
  "properties": {
    "iso:country":"US",
    "sg:address":"4794 Clark St SW",
    "sg:city":"Norcross",
    "sg:classifiers":[
        {
            "category":"Wholesale",
            "subcategory":"Machinery & Supplies",
            "type":"Manufacturing & Wholesale Goods"
        }
    ],
    "sg:phone":"+1 800 879 8000",
    "sg:postcode":"30014",
    "sg:province":"GA",
    "sg:tags":[
        "power",
        "tool",
        "hand",
        "equipment",
        "fastener",
        "fastening"
    ],
    "wof:name":"Atlanta Distribution Center",
    "wof:placetype":"venue"
},
  "geometry": {"coordinates":[-83.875006,33.599004],"type":"Point"}
}