{
  "type": "Feature",
  "properties": {
    "addr:full":"1681 Lukken Industrial Dr W Lagrange GA 30240",
    "addr:housenumber":"1681",
    "addr:postcode":"30240",
    "addr:street":"Lukken Industrial Dr W",
    "iso:country":"US",
    "sg:address":"1681 Lukken Industrial Dr W",
    "sg:city":"Lagrange",
    "sg:classifiers":[
        {
            "category":"Building & Trades",
            "subcategory":"Construction",
            "type":"Services"
        }
    ],
    "sg:phone":"+1 706 884 7874",
    "sg:postcode":"30240",
    "sg:province":"GA",
    "sg:tags":[
        "fabricator",
        "metal"
    ],
    "wof:name":"Polk Sheet Metal Works Inc",
    "wof:placetype":"venue"
},
  "geometry": {"coordinates":[-85.09998299999999,33.006016],"type":"Point"}
}