{
  "type": "Feature",
  "properties": {
    "addr:full":"233 Davis Rd Augusta GA 30907",
    "addr:housenumber":"233",
    "addr:postcode":"30907",
    "addr:street":"Davis Rd",
    "iso:country":"US",
    "sg:address":"233 Davis Rd",
    "sg:city":"Augusta",
    "sg:classifiers":[
        {
            "category":"Professional",
            "subcategory":"Lawyer & Legal Services",
            "type":"Services"
        }
    ],
    "sg:phone":"+1 706 863 4515",
    "sg:postcode":"30907",
    "sg:province":"GA",
    "sg:tags":[
        "attorney"
    ],
    "wof:name":"Leonard M Tuggle Jr",
    "wof:placetype":"venue"
},
  "geometry": {"coordinates":[-82.083153,33.502999],"type":"Point"}
}