{
  "type": "Feature",
  "properties": {
    "addr:full":"265 Park Bridge Ln Roswell GA 30075",
    "addr:housenumber":"265",
    "addr:postcode":"30075",
    "addr:street":"Park Bridge Ln",
    "iso:country":"US",
    "sg:address":"265 Park Bridge Ln",
    "sg:city":"Roswell",
    "sg:classifiers":[
        {
            "category":"Building & Trades",
            "subcategory":"Construction",
            "type":"Services"
        }
    ],
    "sg:phone":"+1 770 552 0088",
    "sg:postcode":"30075",
    "sg:province":"GA",
    "sg:tags":[
        "house"
    ],
    "wof:name":"Chuck Mayuski Design & Rmdlg",
    "wof:placetype":"venue"
},
  "geometry": {"coordinates":[-84.364335,34.03475],"type":"Point"}
}