{
  "type": "Feature",
  "properties": {
    "iso:country":"US",
    "sg:address":"5829 Brookstone Walk NW",
    "sg:city":"Acworth",
    "sg:classifiers":[
        {
            "category":"Professional",
            "subcategory":"Business Services",
            "type":"Services"
        }
    ],
    "sg:phone":"+1 770 425 0268",
    "sg:postcode":"30101",
    "sg:province":"GA",
    "wof:name":"Global Technology Transfe",
    "wof:placetype":"venue"
},
  "geometry": {"coordinates":[-84.72369999999999,33.988019],"type":"Point"}
}