{
  "type": "Feature",
  "properties": {
    "addr:full":"2 Peachtree St NW Atlanta GA 30303",
    "addr:housenumber":"2",
    "addr:postcode":"30303",
    "addr:street":"Peachtree St Nw",
    "iso:country":"US",
    "sg:address":"2 Peachtree St NW",
    "sg:city":"Atlanta",
    "sg:classifiers":[
        {
            "category":"Education",
            "subcategory":"Library",
            "type":"Public Place"
        },
        {
            "category":"Government",
            "subcategory":"Office",
            "type":"Public Place"
        }
    ],
    "sg:phone":"+1 404 657 2700",
    "sg:postcode":"30303",
    "sg:province":"GA",
    "sg:tags":[
        "agency",
        "health"
    ],
    "wof:name":"Public Health Georgia Dept",
    "wof:placetype":"venue"
},
  "geometry": {"coordinates":[-84.389781,33.754318],"type":"Point"}
}