{
  "type": "Feature",
  "properties": {
    "addr:full":"3926 Hickory Grove Rd N Valdosta GA 31606",
    "addr:housenumber":"3926",
    "addr:postcode":"31606",
    "addr:street":"Hickory Grove Rd N",
    "iso:country":"US",
    "sg:address":"3926 Hickory Grove Rd N",
    "sg:city":"Valdosta",
    "sg:classifiers":[
        {
            "category":"Manufacturing",
            "subcategory":"Furniture",
            "type":"Manufacturing & Wholesale Goods"
        }
    ],
    "sg:phone":"+1 229 244 5931",
    "sg:postcode":"31606",
    "sg:province":"GA",
    "sg:tags":[
        "wood",
        "mfg"
    ],
    "wof:name":"Fletcher Cabinet Shop",
    "wof:placetype":"venue"
},
  "geometry": {"coordinates":[-83.20345,30.782767],"type":"Point"}
}