{
  "type": "Feature",
  "properties": {
    "iso:country":"US",
    "sg:address":"1980 Fordham Rd",
    "sg:city":"Rentz",
    "sg:classifiers":[
        {
            "category":"Building & Trades",
            "subcategory":"Construction",
            "type":"Services"
        }
    ],
    "sg:phone":"+1 478 984 4937",
    "sg:postcode":"31075",
    "sg:province":"GA",
    "sg:tags":[
        "wallpaper"
    ],
    "wof:name":"Mary's Wallcovering Srv Inc",
    "wof:placetype":"venue"
},
  "geometry": {"coordinates":[-82.959619,32.365265],"type":"Point"}
}