{
  "type": "Feature",
  "properties": {
    "addr:full":"123 Banks Station Fayetteville GA 30214",
    "addr:housenumber":"123",
    "addr:postcode":"30214",
    "addr:street":"Banks Station",
    "iso:country":"US",
    "sg:address":"123 Banks Station",
    "sg:city":"Fayetteville",
    "sg:classifiers":[
        {
            "category":"Personal",
            "subcategory":"Beauty Salon",
            "type":"Services"
        }
    ],
    "sg:phone":"+1 770 719 1018",
    "sg:postcode":"30214",
    "sg:province":"GA",
    "wof:name":"Great Clips",
    "wof:placetype":"venue"
},
  "geometry": {"coordinates":[-84.448443,33.468239],"type":"Point"}
}