{
  "type": "Feature",
  "properties": {
    "addr:full":"17221 State Rte 242 Bartow GA 30413",
    "addr:housenumber":"17221",
    "addr:postcode":"30413",
    "addr:street":"State Rte 242",
    "iso:country":"US",
    "sg:address":"17221 State Rte 242",
    "sg:city":"Bartow",
    "sg:classifiers":[
        {
            "category":"Building & Trades",
            "subcategory":"Landscaping Services",
            "type":"Services"
        }
    ],
    "sg:phone":"+1 478 364 3232",
    "sg:postcode":"30413",
    "sg:province":"GA",
    "sg:tags":[
        "lawn",
        "maintenance",
        "grounds"
    ],
    "wof:name":"Turff Farm Jenning",
    "wof:placetype":"venue"
},
  "geometry": {"coordinates":[-82.515659,32.882427],"type":"Point"}
}