{
  "type": "Feature",
  "properties": {
    "iso:country":"US",
    "sg:address":"316 Alexander St SE Ste 3",
    "sg:city":"Marietta",
    "sg:classifiers":[
        {
            "category":"Health Services",
            "subcategory":"Health Practitioner",
            "type":"Services"
        }
    ],
    "sg:phone":"+1 678 581 0146",
    "sg:postcode":"30060",
    "sg:province":"GA",
    "sg:tags":[
        "therapy",
        "physical"
    ],
    "wof:name":"Glick David Triad Edupsych PC",
    "wof:placetype":"venue"
},
  "geometry": {"coordinates":[-84.545067,33.947712],"type":"Point"}
}