{
  "type": "Feature",
  "properties": {
    "iso:country":"US",
    "sg:address":"2418 Atlanta Rd SE",
    "sg:city":"Smyrna",
    "sg:classifiers":[
        {
            "category":"Sports & Exercise",
            "subcategory":"Gym",
            "type":"Entertainment"
        }
    ],
    "sg:phone":"+1 770 434 8585",
    "sg:postcode":"30080",
    "sg:province":"GA",
    "sg:tags":[
        "club",
        "health",
        "studio",
        "gymnasium"
    ],
    "wof:name":"12th Round Boxing Gym",
    "wof:placetype":"venue"
},
  "geometry": {"coordinates":[-84.518089,33.891136],"type":"Point"}
}