{
  "type": "Feature",
  "properties": {
    "iso:country":"US",
    "sg:address":"3460 Victory Dr",
    "sg:city":"Columbus",
    "sg:classifiers":[
        {
            "category":"Banks & Credit Unions",
            "subcategory":"Bank",
            "type":"Services"
        }
    ],
    "sg:phone":"+1 706 689 8859",
    "sg:postcode":"31903",
    "sg:province":"GA",
    "sg:tags":[
        "loan"
    ],
    "wof:name":"Titlewave",
    "wof:placetype":"venue"
},
  "geometry": {"coordinates":[-84.94832100000001,32.425203],"type":"Point"}
}