{
  "type": "Feature",
  "properties": {
    "addr:full":"4771 Britt Rd Norcross GA 30093",
    "addr:housenumber":"4771",
    "addr:postcode":"30093",
    "addr:street":"Britt Rd",
    "iso:country":"US",
    "sg:address":"4771 Britt Rd",
    "sg:city":"Norcross",
    "sg:classifiers":[
        {
            "category":"Wholesale",
            "subcategory":"Apparel",
            "type":"Manufacturing & Wholesale Goods"
        },
        {
            "category":"Shopping",
            "subcategory":"Shoes",
            "type":"Retail Goods"
        }
    ],
    "sg:phone":"+1 770 939 9191",
    "sg:postcode":"30093",
    "sg:province":"GA",
    "wof:name":"Calzados De Leon Guanajuato",
    "wof:placetype":"venue"
},
  "geometry": {"coordinates":[-84.19827600000001,33.882078],"type":"Point"}
}