{
  "type": "Feature",
  "properties": {
    "iso:country":"US",
    "sg:address":"2674 Winder Hwy",
    "sg:city":"Dacula",
    "sg:classifiers":[
        {
            "category":"Fast Food",
            "type":"Food & Drink"
        },
        {
            "category":"Restaurant",
            "type":"Food & Drink"
        },
        {
            "category":"Ice Cream",
            "type":"Food & Drink"
        }
    ],
    "sg:phone":"+1 770 995 9296",
    "sg:postcode":"30019",
    "sg:province":"GA",
    "sg:tags":[
        "frozen",
        "dessert",
        "take"
    ],
    "sg:website":"http://www.dairyqueen.com",
    "wof:name":"Dairy Queen",
    "wof:placetype":"venue"
},
  "geometry": {"coordinates":[-83.891119,33.988469],"type":"Point"}
}