{
  "type": "Feature",
  "properties": {
    "addr:full":"2721 State Rte 85 S Senoia GA 30276",
    "addr:housenumber":"2721",
    "addr:postcode":"30276",
    "addr:street":"State Rte 85 S Senoia",
    "iso:country":"US",
    "sg:address":"2721 State Rte 85 S",
    "sg:city":"Senoia",
    "sg:classifiers":[
        {
            "category":"Building & Trades",
            "subcategory":"Construction",
            "type":"Services"
        }
    ],
    "sg:phone":"+1 770 716 6694",
    "sg:postcode":"30276",
    "sg:province":"GA",
    "sg:tags":[
        "house",
        "builder",
        "home"
    ],
    "wof:name":"J P Dennis Custom Homes Inc",
    "wof:placetype":"venue"
},
  "geometry": {"coordinates":[-84.51461399999999,33.325947],"type":"Point"}
}