{
  "type": "Feature",
  "properties": {
    "iso:country":"US",
    "sg:address":"3373 Cleveland Hwy",
    "sg:city":"Gainesville",
    "sg:classifiers":[
        {
            "category":"Retail",
            "subcategory":"Auto Repair",
            "type":"Services"
        }
    ],
    "sg:phone":"+1 770 297 7881",
    "sg:postcode":"30506",
    "sg:province":"GA",
    "sg:tags":[
        "transmission"
    ],
    "wof:name":"B & D Transmissions",
    "wof:placetype":"venue"
},
  "geometry": {"coordinates":[-83.81005500000001,34.377267],"type":"Point"}
}