{
  "type": "Feature",
  "properties": {
    "iso:country":"US",
    "sg:address":"2900 Chamblee Tucker Rd",
    "sg:city":"Atlanta",
    "sg:classifiers":[
        {
            "category":"Professional",
            "subcategory":"Management & Consulting",
            "type":"Services"
        }
    ],
    "sg:phone":"+1 770 220 0608",
    "sg:postcode":"30341",
    "sg:province":"GA",
    "sg:tags":[
        "a",
        "company",
        "as",
        "business",
        "operates"
    ],
    "wof:name":"McKing Consulting Corporation",
    "wof:placetype":"venue"
},
  "geometry": {"coordinates":[-84.26906700000001,33.877884],"type":"Point"}
}