{
  "type": "Feature",
  "properties": {
    "iso:country":"US",
    "sg:address":"429 Crosshaven Way",
    "sg:city":"Mcdonough",
    "sg:classifiers":[
        {
            "category":"Real Estate",
            "subcategory":"Real Estate Agent",
            "type":"Services"
        }
    ],
    "sg:phone":"+1 770 954 0011",
    "sg:postcode":"30253",
    "sg:province":"GA",
    "sg:tags":[
        "appraiser"
    ],
    "wof:name":"M H Biggers Appraisals",
    "wof:placetype":"venue"
},
  "geometry": {"coordinates":[-84.17792900000001,33.513385],"type":"Point"}
}