{
  "type": "Feature",
  "properties": {
    "iso:country":"US",
    "sg:address":"670 Memorial Dr SE",
    "sg:city":"Atlanta",
    "sg:classifiers":[
        {
            "category":"Retail",
            "subcategory":"Auto Repair",
            "type":"Services"
        }
    ],
    "sg:phone":"+1 404 614 0016",
    "sg:postcode":"30312",
    "sg:province":"GA",
    "sg:tags":[
        "body",
        "shop",
        "painting",
        "automobile"
    ],
    "sg:website":"www.abccollisioninc.com",
    "wof:name":"ABC Collision",
    "wof:placetype":"venue"
},
  "geometry": {"coordinates":[-84.36550099999999,33.746601],"type":"Point"}
}