{
  "type": "Feature",
  "properties": {
    "addr:full":"1525 Madison Hwy Valdosta GA 31601",
    "addr:housenumber":"1525",
    "addr:postcode":"31601",
    "addr:street":"Madison Hwy",
    "iso:country":"US",
    "sg:address":"1525 Madison Hwy",
    "sg:city":"Valdosta",
    "sg:classifiers":[
        {
            "category":"Wholesale",
            "subcategory":"Groceries",
            "type":"Manufacturing & Wholesale Goods"
        }
    ],
    "sg:phone":"+1 229 244 2833",
    "sg:postcode":"31601",
    "sg:province":"GA",
    "sg:tags":[
        "bottling",
        "facility"
    ],
    "wof:name":"Pepsi-Cola",
    "wof:placetype":"venue"
},
  "geometry": {"coordinates":[-83.274447,30.806264],"type":"Point"}
}