{
  "type": "Feature",
  "properties": {
    "iso:country":"US",
    "sg:address":"805 Mount Vernon Hwy NW",
    "sg:city":"Atlanta",
    "sg:classifiers":[
        {
            "category":"Organizations",
            "subcategory":"Religious Organization",
            "type":"Services"
        }
    ],
    "sg:phone":"+1 404 255 4023",
    "sg:postcode":"30327",
    "sg:province":"GA",
    "sg:website":"www.holyinnocents.org",
    "wof:name":"Holy Innocents' Episcopal Church",
    "wof:placetype":"venue"
},
  "geometry": {"coordinates":[-84.412187,33.908726],"type":"Point"}
}