{
  "type": "Feature",
  "properties": {
    "iso:country":"US",
    "sg:address":"209 Boulevard",
    "sg:city":"Gainesville",
    "sg:classifiers":[
        {
            "category":"Restaurant",
            "type":"Food & Drink"
        }
    ],
    "sg:phone":"+1 770 536 8781",
    "sg:postcode":"30501",
    "sg:province":"GA",
    "sg:tags":[
        "eating"
    ],
    "wof:name":"McDonalds",
    "wof:placetype":"venue"
},
  "geometry": {"coordinates":[-83.823286,34.303643],"type":"Point"}
}