{
  "type": "Feature",
  "properties": {
    "addr:full":"218 Sharon Cir Rossville GA 30741",
    "addr:housenumber":"218",
    "addr:postcode":"30741",
    "addr:street":"Sharon Cir",
    "iso:country":"US",
    "sg:address":"218 Sharon Cir",
    "sg:city":"Rossville",
    "sg:classifiers":[
        {
            "category":"Building & Trades",
            "subcategory":"Construction",
            "type":"Services"
        }
    ],
    "sg:phone":"+1 706 858 8863",
    "sg:postcode":"30741",
    "sg:province":"GA",
    "sg:tags":[
        "house"
    ],
    "wof:name":"Houston Construction Co",
    "wof:placetype":"venue"
},
  "geometry": {"coordinates":[-85.249061,34.970407],"type":"Point"}
}