{
  "type": "Feature",
  "properties": {
    "addr:full":"158 7th Ave NW Dawson GA 39842",
    "addr:housenumber":"158",
    "addr:postcode":"39842",
    "addr:street":"7Th Ave Nw",
    "iso:country":"US",
    "sg:address":"158 7th Ave NW",
    "sg:city":"Dawson",
    "sg:classifiers":[
        {
            "category":"Retail",
            "subcategory":"Auto Repair",
            "type":"Services"
        }
    ],
    "sg:phone":"+1 229 995 2294",
    "sg:postcode":"39842",
    "sg:province":"GA",
    "sg:tags":[
        "general"
    ],
    "wof:name":"Chambless Garage",
    "wof:placetype":"venue"
},
  "geometry": {"coordinates":[-84.44734099999999,31.775738],"type":"Point"}
}