{
  "type": "Feature",
  "properties": {
    "addr:full":"4285 Aaronmoor Ln Cumming GA 30040",
    "addr:housenumber":"4285",
    "addr:postcode":"30040",
    "addr:street":"Aaronmoor Ln",
    "iso:country":"US",
    "sg:address":"4285 Aaronmoor Ln",
    "sg:city":"Cumming",
    "sg:classifiers":[
        {
            "category":"Manufacturing",
            "subcategory":"Metals",
            "type":"Manufacturing & Wholesale Goods"
        }
    ],
    "sg:phone":"+1 770 888 1108",
    "sg:postcode":"30040",
    "sg:province":"GA",
    "sg:tags":[
        "fiber",
        "optics",
        "system"
    ],
    "wof:name":"Advanced Lightwave Systems Inc",
    "wof:placetype":"venue"
},
  "geometry": {"coordinates":[-84.213038,34.236324],"type":"Point"}
}