{
  "type": "Feature",
  "properties": {
    "addr:full":"2952 Martin Luther King Jr Blvd Columbus GA 31906",
    "addr:housenumber":"2952",
    "addr:postcode":"31906",
    "addr:street":"Martin Luther King Jr Blvd",
    "iso:country":"US",
    "sg:address":"2952 Martin Luther King Jr Blvd",
    "sg:city":"Columbus",
    "sg:classifiers":[
        {
            "category":"Retail",
            "subcategory":"Auto Repair",
            "type":"Services"
        }
    ],
    "sg:phone":"+1 706 653 7200",
    "sg:postcode":"31906",
    "sg:province":"GA",
    "sg:tags":[
        "body",
        "automobile",
        "painting"
    ],
    "wof:name":"Chuck's Auto Paint & Body",
    "wof:placetype":"venue"
},
  "geometry": {"coordinates":[-84.946331,32.455229],"type":"Point"}
}