{
  "type": "Feature",
  "properties": {
    "addr:full":"5100 Post Rd Cumming GA 30040",
    "addr:housenumber":"5100",
    "addr:postcode":"30040",
    "addr:street":"Post Rd",
    "iso:country":"US",
    "sg:address":"5100 Post Rd",
    "sg:city":"Cumming",
    "sg:classifiers":[
        {
            "category":"Recreation",
            "type":"Entertainment"
        }
    ],
    "sg:phone":"+1 770 886 4089",
    "sg:postcode":"30040",
    "sg:province":"GA",
    "sg:tags":[
        "parks"
    ],
    "wof:name":"Midway Park",
    "wof:placetype":"venue"
},
  "geometry": {"coordinates":[-84.220067,34.202809],"type":"Point"}
}