{
  "type": "Feature",
  "properties": {
    "iso:country":"US",
    "sg:address":"2331 4th St",
    "sg:city":"Tucker",
    "sg:classifiers":[
        {
            "category":"Professional",
            "subcategory":"Art Services",
            "type":"Services"
        }
    ],
    "sg:phone":"+1 770 939 0902",
    "sg:postcode":"30084",
    "sg:province":"GA",
    "sg:tags":[
        "design",
        "sign"
    ],
    "wof:name":"Indigo Arts",
    "wof:placetype":"venue"
},
  "geometry": {"coordinates":[-84.21263500000001,33.853567],"type":"Point"}
}