{
  "type": "Feature",
  "properties": {
    "addr:full":"4863 Milgen Rd Columbus GA 31907",
    "addr:housenumber":"4863",
    "addr:postcode":"31907",
    "addr:street":"Milgen Rd",
    "iso:country":"US",
    "sg:address":"4863 Milgen Rd",
    "sg:city":"Columbus",
    "sg:classifiers":[
        {
            "category":"Building & Trades",
            "subcategory":"Equipment Rental",
            "type":"Services"
        }
    ],
    "sg:phone":"+1 706 561 3131",
    "sg:postcode":"31907",
    "sg:province":"GA",
    "sg:tags":[
        "crane"
    ],
    "wof:name":"All Crane Rental Of Georgia",
    "wof:placetype":"venue"
},
  "geometry": {"coordinates":[-84.910253,32.517406],"type":"Point"}
}