{
  "type": "Feature",
  "properties": {
    "iso:country":"US",
    "sg:address":"2255 Cumberland Pkwy SE Bldg 1400",
    "sg:city":"Atlanta",
    "sg:classifiers":[
        {
            "category":"Health Services",
            "subcategory":"Doctor",
            "type":"Services"
        }
    ],
    "sg:phone":"+1 770 955 9477",
    "sg:postcode":"30339",
    "sg:province":"GA",
    "sg:tags":[
        "practice",
        "family"
    ],
    "sg:website":"viningsmed.com/",
    "wof:name":"Vinings Medical Center, Anita Smith MD",
    "wof:placetype":"venue"
},
  "geometry": {"coordinates":[-84.480621,33.857665],"type":"Point"}
}