{
  "type": "Feature",
  "properties": {
    "iso:country":"US",
    "sg:address":"501 Dorsey Rd",
    "sg:city":"Hampton",
    "sg:classifiers":[
        {
            "category":"Building & Trades",
            "subcategory":"Plumbing",
            "type":"Services"
        }
    ],
    "sg:phone":"+1 678 410 1406",
    "sg:postcode":"30228",
    "sg:province":"GA",
    "sg:tags":[
        "contractor"
    ],
    "wof:name":"Scott Roberts Heating & Air",
    "wof:placetype":"venue"
},
  "geometry": {"coordinates":[-84.246194,33.402701],"type":"Point"}
}