{
  "type": "Feature",
  "properties": {
    "iso:country":"US",
    "sg:address":"127 Friendship Church Rd",
    "sg:city":"Brooks",
    "sg:classifiers":[
        {
            "category":"Freight",
            "type":"Transportation"
        }
    ],
    "sg:phone":"+1 770 306 9752",
    "sg:postcode":"30205",
    "sg:province":"GA",
    "wof:name":"Global Trade Solutions Inc",
    "wof:placetype":"venue"
},
  "geometry": {"coordinates":[-84.460216,33.312738],"type":"Point"}
}