{
  "type": "Feature",
  "properties": {
    "iso:country":"US",
    "sg:address":"767 Peachtree Pkwy",
    "sg:city":"Cumming",
    "sg:classifiers":[
        {
            "category":"Health Services",
            "subcategory":"Doctor",
            "type":"Services"
        },
        {
            "category":"Health Services",
            "subcategory":"Clinic",
            "type":"Services"
        },
        {
            "category":"Community Center",
            "type":"Public Place"
        },
        {
            "category":"Health Services",
            "subcategory":"Chiropractor",
            "type":"Services"
        }
    ],
    "sg:phone":"+1 770 781 4200",
    "sg:postcode":"30041",
    "sg:province":"GA",
    "sg:tags":[
        "physician",
        "medical",
        "surgeon",
        "chiropractic"
    ],
    "wof:name":"Mc Namara Chiropractic",
    "wof:placetype":"venue"
},
  "geometry": {"coordinates":[-84.17218,34.143162],"type":"Point"}
}