{
  "type": "Feature",
  "properties": {
    "iso:country":"US",
    "sg:address":"1967 State Rte 54",
    "sg:city":"Fayetteville",
    "sg:classifiers":[
        {
            "category":"Shopping",
            "subcategory":"Computers & Home Electronics",
            "type":"Retail Goods"
        }
    ],
    "sg:phone":"+1 770 692 2205",
    "sg:postcode":"30214",
    "sg:province":"GA",
    "sg:tags":[
        "software"
    ],
    "wof:name":"Softlanta",
    "wof:placetype":"venue"
},
  "geometry": {"coordinates":[-84.555392,33.430365],"type":"Point"}
}