{
  "type": "Feature",
  "properties": {
    "addr:full":"6648 Yellow Creek Rd Murrayville GA 30564",
    "addr:housenumber":"6648",
    "addr:postcode":"30564",
    "addr:street":"Yellow Creek Rd",
    "iso:country":"US",
    "sg:address":"6648 Yellow Creek Rd",
    "sg:city":"Murrayville",
    "sg:classifiers":[
        {
            "category":"Professional",
            "subcategory":"Lawyer & Legal Services",
            "type":"Services"
        }
    ],
    "sg:phone":"+1 770 534 2655",
    "sg:postcode":"30564",
    "sg:province":"GA",
    "sg:tags":[
        "convention",
        "reporters-court"
    ],
    "wof:name":"Jean Rider",
    "wof:placetype":"venue"
},
  "geometry": {"coordinates":[-83.957666,34.4239],"type":"Point"}
}