{
  "type": "Feature",
  "properties": {
    "iso:country":"US",
    "sg:address":"2410 Wood Creek Ct NE",
    "sg:city":"Dacula",
    "sg:classifiers":[
        {
            "category":"Building & Trades",
            "subcategory":"Construction",
            "type":"Services"
        }
    ],
    "sg:phone":"+1 678 985 9581",
    "sg:postcode":"30019",
    "sg:province":"GA",
    "sg:tags":[
        "house"
    ],
    "wof:name":"Spencer Homes Inc",
    "wof:placetype":"venue"
},
  "geometry": {"coordinates":[-83.912848,34.018618],"type":"Point"}
}