{
  "type": "Feature",
  "properties": {
    "addr:full":"7505 Waters Ave Savannah GA 31406",
    "addr:housenumber":"7505",
    "addr:postcode":"31406",
    "addr:street":"Waters Ave",
    "iso:country":"US",
    "sg:address":"7505 Waters Ave",
    "sg:city":"Savannah",
    "sg:classifiers":[
        {
            "category":"Recreation",
            "type":"Entertainment"
        }
    ],
    "sg:phone":"+1 912 351 4148",
    "sg:postcode":"31406",
    "sg:province":"GA",
    "wof:name":"Tybee Light Power Squadron",
    "wof:placetype":"venue"
},
  "geometry": {"coordinates":[-81.10241000000001,32.002502],"type":"Point"}
}