{
  "type": "Feature",
  "properties": {
    "addr:full":"2759 Delk Rd Ste 1180 Marietta GA 30067",
    "addr:housenumber":"2759",
    "addr:postcode":"30067",
    "addr:street":"Delk Rd Ste 1180",
    "iso:country":"US",
    "sg:address":"2759 Delk Rd Ste 1180",
    "sg:city":"Marietta",
    "sg:classifiers":[
        {
            "category":"Insurance",
            "subcategory":"Hazard Insurance",
            "type":"Services"
        }
    ],
    "sg:phone":"+1 770 841 1245",
    "sg:postcode":"30067",
    "sg:province":"GA",
    "wof:name":"Marina Insurance",
    "wof:placetype":"venue"
},
  "geometry": {"coordinates":[-84.472768,33.923803],"type":"Point"}
}