{
  "type": "Feature",
  "properties": {
    "iso:country":"US",
    "sg:address":"6030 State Rte 85",
    "sg:city":"Riverdale",
    "sg:classifiers":[
        {
            "category":"Freight",
            "type":"Transportation"
        }
    ],
    "sg:phone":"+1 770 996 6869",
    "sg:postcode":"30274",
    "sg:province":"GA",
    "sg:tags":[
        "mover"
    ],
    "wof:name":"All Pro Haul For Less",
    "wof:placetype":"venue"
},
  "geometry": {"coordinates":[-84.408913,33.590804],"type":"Point"}
}