{
  "type": "Feature",
  "properties": {
    "iso:country":"US",
    "sg:address":"135 E Felton Rd",
    "sg:city":"Cartersville",
    "sg:classifiers":[
        {
            "category":"Banks & Credit Unions",
            "subcategory":"Investment Brokerage",
            "type":"Services"
        }
    ],
    "sg:phone":"+1 770 386 4901",
    "sg:postcode":"30120",
    "sg:province":"GA",
    "sg:tags":[
        "security"
    ],
    "wof:name":"Edward Jones Co",
    "wof:placetype":"venue"
},
  "geometry": {"coordinates":[-84.792779,34.196713],"type":"Point"}
}