{
  "type": "Feature",
  "properties": {
    "iso:country":"US",
    "sg:address":"85 Poplar St NW",
    "sg:city":"Atlanta",
    "sg:classifiers":[
        {
            "category":"Bars & Pubs",
            "subcategory":"Lounge",
            "type":"Food & Drink"
        },
        {
            "category":"Restaurant",
            "type":"Food & Drink"
        }
    ],
    "sg:phone":"+1 404 917 1820",
    "sg:postcode":"30303",
    "sg:province":"GA",
    "sg:tags":[
        "pizza"
    ],
    "sg:website":"www.sliceatlanta.com",
    "wof:name":"Slice",
    "wof:placetype":"venue"
},
  "geometry": {"coordinates":[-84.389915,33.756931],"type":"Point"}
}