{
  "type": "Feature",
  "properties": {
    "iso:country":"US",
    "sg:address":"2612 Monterey Pkwy",
    "sg:city":"Atlanta",
    "sg:classifiers":[
        {
            "category":"Personal",
            "subcategory":"Adult",
            "type":"Services"
        }
    ],
    "sg:phone":"+1 770 512 8932",
    "sg:postcode":"30350",
    "sg:province":"GA",
    "sg:tags":[
        "escort"
    ],
    "wof:name":"Ashleys",
    "wof:placetype":"venue"
},
  "geometry": {"coordinates":[-84.375,33.962257],"type":"Point"}
}