{
  "type": "Feature",
  "properties": {
    "addr:full":"1175 Fleming St SE Smyrna GA 30080",
    "addr:housenumber":"1175",
    "addr:postcode":"30080",
    "addr:street":"Fleming St Se",
    "iso:country":"US",
    "sg:address":"1175 Fleming St SE",
    "sg:city":"Smyrna",
    "sg:classifiers":[
        {
            "category":"Wholesale",
            "subcategory":"Metals & Minerals",
            "type":"Manufacturing & Wholesale Goods"
        }
    ],
    "sg:phone":"+1 770 437 9760",
    "sg:postcode":"30080",
    "sg:province":"GA",
    "sg:tags":[
        "castings-non-ferrous"
    ],
    "wof:name":"Blue Marble Trading",
    "wof:placetype":"venue"
},
  "geometry": {"coordinates":[-84.520308,33.88965],"type":"Point"}
}