{
  "type": "Feature",
  "properties": {
    "iso:country":"US",
    "sg:address":"1502 Stone Mill Trce",
    "sg:city":"Stone Mountain",
    "sg:classifiers":[
        {
            "category":"Professional",
            "type":"Services"
        }
    ],
    "sg:phone":"+1 770 413 0611",
    "sg:postcode":"30083",
    "sg:province":"GA",
    "wof:name":"Stone Mill Village Number One",
    "wof:placetype":"venue"
},
  "geometry": {"coordinates":[-84.178808,33.823423],"type":"Point"}
}