{
  "type": "Feature",
  "properties": {
    "addr:full":"727 Juniper St NE Atlanta GA 30308",
    "addr:housenumber":"727",
    "addr:postcode":"30308",
    "addr:street":"Juniper St Ne",
    "iso:country":"US",
    "sg:address":"727 Juniper St NE",
    "sg:city":"Atlanta",
    "sg:classifiers":[
        {
            "category":"Professional",
            "subcategory":"Management & Consulting",
            "type":"Services"
        }
    ],
    "sg:phone":"+1 404 881 9948",
    "sg:postcode":"30308",
    "sg:province":"GA",
    "sg:tags":[
        "consultant",
        "business"
    ],
    "wof:name":"Pyramid Plus Inc",
    "wof:placetype":"venue"
},
  "geometry": {"coordinates":[-84.383235,33.77375],"type":"Point"}
}