{
  "type": "Feature",
  "properties": {
    "iso:country":"US",
    "sg:address":"901 Joy Rd Lot 284",
    "sg:city":"Columbus",
    "sg:classifiers":[
        {
            "category":"Taxi",
            "type":"Transportation"
        }
    ],
    "sg:phone":"+1 706 393 0689",
    "sg:postcode":"31906",
    "sg:province":"GA",
    "wof:name":"Goldstar Taxi",
    "wof:placetype":"venue"
},
  "geometry": {"coordinates":[-84.93331499999999,32.438169],"type":"Point"}
}