{
  "type": "Feature",
  "properties": {
    "addr:full":"1383 Redmond Cir Rome GA 30165",
    "addr:housenumber":"1383",
    "addr:postcode":"ga 30165",
    "addr:street":"Redmond Cir",
    "iso:country":"US",
    "sg:address":"1383 Redmond Cir",
    "sg:city":"Rome",
    "sg:classifiers":[
        {
            "category":"Restaurant",
            "type":"Food & Drink"
        }
    ],
    "sg:phone":"+1 706 236 9545",
    "sg:postcode":"30165",
    "sg:province":"GA",
    "wof:name":"Bojangles' Famous Chicken",
    "wof:placetype":"venue"
},
  "geometry": {"coordinates":[-85.206484,34.284857],"type":"Point"}
}