{
  "type": "Feature",
  "properties": {
    "iso:country":"US",
    "sg:address":"3175 Satellite Blvd NW",
    "sg:city":"Duluth",
    "sg:classifiers":[
        {
            "category":"Health Services",
            "subcategory":"Doctor",
            "type":"Services"
        }
    ],
    "sg:phone":"+1 770 622 9610",
    "sg:postcode":"30096",
    "sg:province":"GA",
    "sg:tags":[
        "physician",
        "surgeon"
    ],
    "wof:name":"Lasik Plus Vision Ctr",
    "wof:placetype":"venue"
},
  "geometry": {"coordinates":[-84.132299,33.962136],"type":"Point"}
}