{
  "type": "Feature",
  "properties": {
    "addr:full":"3829 Clairmont Rd Atlanta GA 30341",
    "addr:housenumber":"3829",
    "addr:postcode":"30341",
    "addr:street":"Clairmont Rd",
    "iso:country":"US",
    "sg:address":"3829 Clairmont Rd",
    "sg:city":"Atlanta",
    "sg:classifiers":[
        {
            "category":"Restaurant",
            "type":"Food & Drink"
        }
    ],
    "sg:phone":"+1 770 234 0057",
    "sg:postcode":"30341",
    "sg:province":"GA",
    "sg:tags":[
        "new",
        "american"
    ],
    "sg:website":"www.the57threstaurant.com",
    "wof:name":"57th Fighter Group Restaurant",
    "wof:placetype":"venue"
},
  "geometry": {"coordinates":[-84.30567000000001,33.872553],"type":"Point"}
}