{
  "type": "Feature",
  "properties": {
    "iso:country":"US",
    "sg:address":"3015 Windward Plz",
    "sg:city":"Alpharetta",
    "sg:classifiers":[
        {
            "category":"Banks & Credit Unions",
            "subcategory":"Bank",
            "type":"Services"
        }
    ],
    "sg:phone":"+1 770 751 8290",
    "sg:postcode":"30005",
    "sg:province":"GA",
    "sg:tags":[
        "banking",
        "loan",
        "real estate"
    ],
    "wof:name":"Wilmington Finance Inc",
    "wof:placetype":"venue"
},
  "geometry": {"coordinates":[-84.239949,34.093221],"type":"Point"}
}