{
  "type": "Feature",
  "properties": {
    "addr:full":"5344 Buford Hwy NE Doraville GA 30340",
    "addr:housenumber":"5344",
    "addr:postcode":"30340",
    "addr:street":"Buford Hwy Ne",
    "iso:country":"US",
    "sg:address":"5344 Buford Hwy NE",
    "sg:city":"Doraville",
    "sg:classifiers":[
        {
            "category":"Personal",
            "subcategory":"Beauty Salon",
            "type":"Services"
        }
    ],
    "sg:phone":"+1 770 220 3055",
    "sg:postcode":"30340",
    "sg:province":"GA",
    "wof:name":"Kaco Poco",
    "wof:placetype":"venue"
},
  "geometry": {"coordinates":[-84.278395,33.899395],"type":"Point"}
}