{
  "type": "Feature",
  "properties": {
    "iso:country":"US",
    "sg:address":"1402 Austin Dr",
    "sg:city":"Decatur",
    "sg:classifiers":[
        {
            "category":"Education",
            "subcategory":"School",
            "type":"Public Place"
        }
    ],
    "sg:phone":"+1 678 874 1200",
    "sg:postcode":"30032",
    "sg:province":"GA",
    "sg:tags":[
        "high",
        "middle",
        "elementary"
    ],
    "wof:name":"Glen Haven Elementary School",
    "wof:placetype":"venue"
},
  "geometry": {"coordinates":[-84.233791,33.750859],"type":"Point"}
}