{
  "type": "Feature",
  "properties": {
    "addr:full":"227 Sandy Springs Pl NW Sandy Springs GA 30342",
    "addr:housenumber":"227",
    "addr:postcode":"30342",
    "addr:street":"Sandy;Pl Nw",
    "iso:country":"US",
    "sg:address":"227 Sandy Springs Pl NW",
    "sg:city":"Sandy Springs",
    "sg:classifiers":[
        {
            "category":"Retail",
            "subcategory":"Laundry & Dry Cleaning",
            "type":"Services"
        }
    ],
    "sg:phone":"+1 404 255 5103",
    "sg:postcode":"30342",
    "sg:province":"GA",
    "wof:name":"Urich's Cleaners",
    "wof:placetype":"venue"
},
  "geometry": {"coordinates":[-84.383433,33.920474],"type":"Point"}
}