{
  "type": "Feature",
  "properties": {
    "iso:country":"US",
    "sg:address":"1030 Delta Blvd",
    "sg:city":"Atlanta",
    "sg:classifiers":[
        {
            "category":"Airline",
            "type":"Transportation"
        }
    ],
    "sg:phone":"+1 404 715 2600",
    "sg:postcode":"30320",
    "sg:province":"GA",
    "sg:website":"www.delta.com",
    "wof:name":"Delta Air Lines",
    "wof:placetype":"venue"
},
  "geometry": {"coordinates":[-84.423097,33.657612],"type":"Point"}
}