{
  "type": "Feature",
  "properties": {
    "iso:country":"US",
    "sg:address":"421 Twin Lakes Dr",
    "sg:city":"Villa Rica",
    "sg:classifiers":[
        {
            "category":"Real Estate",
            "subcategory":"Real Estate Agent",
            "type":"Services"
        }
    ],
    "sg:phone":"+1 770 459 8682",
    "sg:postcode":"30180",
    "sg:province":"GA",
    "wof:name":"Metro Broker",
    "wof:placetype":"venue"
},
  "geometry": {"coordinates":[-84.902111,33.763047],"type":"Point"}
}