{
  "type": "Feature",
  "properties": {
    "iso:country":"US",
    "sg:address":"8 Aviation Ct",
    "sg:city":"Savannah",
    "sg:classifiers":[
        {
            "category":"Freight",
            "type":"Transportation"
        }
    ],
    "sg:phone":"+1 912 964 0707",
    "sg:postcode":"31408",
    "sg:province":"GA",
    "sg:tags":[
        "warehouse",
        "forwarder",
        "warehousing"
    ],
    "wof:name":"Coastal Logistics Group Inc",
    "wof:placetype":"venue"
},
  "geometry": {"coordinates":[-81.17560400000001,32.12938],"type":"Point"}
}