{
  "type": "Feature",
  "properties": {
    "iso:country":"US",
    "sg:address":"2500 W Hillview Dr",
    "sg:city":"Dalton",
    "sg:classifiers":[
        {
            "category":"Home & Garden",
            "subcategory":"Carpets & Floor Coverings",
            "type":"Retail Goods"
        }
    ],
    "sg:phone":"+1 706 259 5948",
    "sg:postcode":"30721",
    "sg:province":"GA",
    "wof:name":"Leos Carpets Inc",
    "wof:placetype":"venue"
},
  "geometry": {"coordinates":[-84.948824,34.821069],"type":"Point"}
}