{
  "type": "Feature",
  "properties": {
    "iso:country":"US",
    "sg:address":"326 W Hill St",
    "sg:city":"Decatur",
    "sg:classifiers":[
        {
            "category":"Shopping",
            "subcategory":"Beauty & Cosmetics",
            "type":"Retail Goods"
        }
    ],
    "sg:phone":"+1 404 231 2389",
    "sg:postcode":"30030",
    "sg:province":"GA",
    "sg:tags":[
        "merchandise"
    ],
    "wof:name":"Permanent Csmtc Prfssnals Atla",
    "wof:placetype":"venue"
},
  "geometry": {"coordinates":[-84.302564,33.759631],"type":"Point"}
}