{
  "type": "Feature",
  "properties": {
    "addr:full":"331 Birchwood Dr Clarkesville GA 30523",
    "addr:housenumber":"331",
    "addr:postcode":"30523",
    "addr:street":"Birchwood Dr",
    "iso:country":"US",
    "sg:address":"331 Birchwood Dr",
    "sg:city":"Clarkesville",
    "sg:classifiers":[
        {
            "category":"Building & Trades",
            "subcategory":"Construction",
            "type":"Services"
        }
    ],
    "sg:phone":"+1 706 754 7141",
    "sg:postcode":"30523",
    "sg:province":"GA",
    "sg:tags":[
        "roofing",
        "contractor"
    ],
    "wof:name":"J & DS Roofing",
    "wof:placetype":"venue"
},
  "geometry": {"coordinates":[-83.466486,34.628645],"type":"Point"}
}