{
  "type": "Feature",
  "properties": {
    "iso:country":"US",
    "sg:address":"2135 Hills Ave NW",
    "sg:city":"Atlanta",
    "sg:classifiers":[
        {
            "category":"Home & Garden",
            "subcategory":"Carpets & Floor Coverings",
            "type":"Retail Goods"
        }
    ],
    "sg:phone":"+1 404 355 9670",
    "sg:postcode":"30318",
    "sg:province":"GA",
    "wof:name":"Lee Home Products Corporation",
    "wof:placetype":"venue"
},
  "geometry": {"coordinates":[-84.43056,33.814287],"type":"Point"}
}