{
  "type": "Feature",
  "properties": {
    "addr:full":"3290 Coachmans Way NE Roswell GA 30075",
    "addr:postcode":"3290;30075",
    "addr:street":"Coachmans Way Ne",
    "iso:country":"US",
    "sg:address":"3290 Coachmans Way NE",
    "sg:city":"Roswell",
    "sg:classifiers":[
        {
            "category":"Sports & Exercise",
            "subcategory":"Gym",
            "type":"Entertainment"
        }
    ],
    "sg:phone":"+1 770 998 4610",
    "sg:postcode":"30075",
    "sg:province":"GA",
    "wof:name":"Joe Corley American Karate",
    "wof:placetype":"venue"
},
  "geometry": {"coordinates":[-84.410866,34.031348],"type":"Point"}
}