{
  "type": "Feature",
  "properties": {
    "addr:full":"2996 Grandview Ave NE 3 Atlanta GA 30305",
    "addr:housenumber":"2996;3",
    "addr:postcode":"30305",
    "addr:street":"Grandview Ave Ne",
    "iso:country":"US",
    "sg:address":"2996 Grandview Ave NE 3",
    "sg:city":"Atlanta",
    "sg:classifiers":[
        {
            "category":"Health Services",
            "subcategory":"Health Practitioner",
            "type":"Services"
        }
    ],
    "sg:phone":"+1 404 364 9668",
    "sg:postcode":"30305",
    "sg:province":"GA",
    "sg:tags":[
        "holistic"
    ],
    "wof:name":"Cahill, Kimberly",
    "wof:placetype":"venue"
},
  "geometry": {"coordinates":[-84.376328,33.836995],"type":"Point"}
}