{
  "type": "Feature",
  "properties": {
    "iso:country":"US",
    "sg:address":"212 Anchor Dr",
    "sg:city":"Brunswick",
    "sg:classifiers":[
        {
            "category":"Wholesale",
            "subcategory":"Medical Equipment & Supplies",
            "type":"Manufacturing & Wholesale Goods"
        },
        {
            "category":"Building & Trades",
            "subcategory":"Plumbing",
            "type":"Services"
        }
    ],
    "sg:phone":"+1 912 265 0558",
    "sg:postcode":"31523",
    "sg:province":"GA",
    "sg:tags":[
        "hospital",
        "contractor"
    ],
    "wof:name":"Mechanical Piping Sales Inc",
    "wof:placetype":"venue"
},
  "geometry": {"coordinates":[-81.57324199999999,31.147959],"type":"Point"}
}