{
  "type": "Feature",
  "properties": {
    "iso:country":"US",
    "sg:address":"415 Rockmart Rd",
    "sg:city":"Villa Rica",
    "sg:classifiers":[
        {
            "category":"Organizations",
            "subcategory":"Religious Organization",
            "type":"Services"
        }
    ],
    "sg:phone":"+1 770 459 2007",
    "sg:postcode":"30180",
    "sg:province":"GA",
    "wof:name":"Victory Tabernacle",
    "wof:placetype":"venue"
},
  "geometry": {"coordinates":[-84.924105,33.742466],"type":"Point"}
}