{
  "type": "Feature",
  "properties": {
    "iso:country":"US",
    "sg:address":"34 Powder Springs St",
    "sg:city":"Marietta",
    "sg:classifiers":[
        {
            "category":"Bakery",
            "type":"Food & Drink"
        }
    ],
    "sg:phone":"+1 678 891 8148",
    "sg:postcode":"30068",
    "sg:province":"GA",
    "sg:website":"www.saboresbakery.webs.com",
    "wof:name":"Sabores Bakery",
    "wof:placetype":"venue"
},
  "geometry": {"coordinates":[-84.550363,33.947671],"type":"Point"}
}