{
  "type": "Feature",
  "properties": {
    "iso:country":"US",
    "sg:address":"410 Ralph G Hendrix Rd",
    "sg:city":"Statesboro",
    "sg:classifiers":[
        {
            "category":"Banks & Credit Unions",
            "subcategory":"Investment Brokerage",
            "type":"Services"
        }
    ],
    "sg:phone":"+1 912 681 4661",
    "sg:postcode":"30458",
    "sg:province":"GA",
    "sg:tags":[
        "advisory"
    ],
    "wof:name":"Jdt Investment Group, Inc.",
    "wof:placetype":"venue"
},
  "geometry": {"coordinates":[-81.819057,32.408035],"type":"Point"}
}