{
  "type": "Feature",
  "properties": {
    "iso:country":"US",
    "sg:address":"2929 Watson Blvd",
    "sg:city":"Warner Robins",
    "sg:classifiers":[
        {
            "category":"Restaurant",
            "type":"Food & Drink"
        }
    ],
    "sg:phone":"+1 478 971 4500",
    "sg:postcode":"31093",
    "sg:province":"GA",
    "sg:tags":[
        "eating"
    ],
    "wof:name":"Roly Poly Sandwiches",
    "wof:placetype":"venue"
},
  "geometry": {"coordinates":[-83.684814,32.618315],"type":"Point"}
}