{
  "type": "Feature",
  "properties": {
    "iso:country":"US",
    "sg:address":"405 Birch Rill Dr",
    "sg:city":"Alpharetta",
    "sg:classifiers":[
        {
            "category":"Health Services",
            "subcategory":"Health Practitioner",
            "type":"Services"
        }
    ],
    "sg:phone":"+1 770 442 5260",
    "sg:postcode":"30022",
    "sg:province":"GA",
    "wof:name":"Alpharetta Ethical Therapeutic",
    "wof:placetype":"venue"
},
  "geometry": {"coordinates":[-84.268782,34.030056],"type":"Point"}
}