{
  "type": "Feature",
  "properties": {
    "iso:country":"US",
    "sg:address":"1786 Northeast Expy NE",
    "sg:city":"Atlanta",
    "sg:classifiers":[
        {
            "category":"Professional",
            "subcategory":"Computer Services",
            "type":"Services"
        }
    ],
    "sg:phone":"+1 404 325 2730",
    "sg:postcode":"30329",
    "sg:province":"GA",
    "sg:tags":[
        "prepackaged",
        "software",
        "custom"
    ],
    "wof:name":"Qhs",
    "wof:placetype":"venue"
},
  "geometry": {"coordinates":[-84.320345,33.839669],"type":"Point"}
}