{
  "type": "Feature",
  "properties": {
    "iso:country":"US",
    "sg:address":"411 Carter Ave",
    "sg:city":"Blackshear",
    "sg:classifiers":[
        {
            "category":"Organizations",
            "subcategory":"Religious Organization",
            "type":"Services"
        }
    ],
    "sg:phone":"+1 912 449 5066",
    "sg:postcode":"31516",
    "sg:province":"GA",
    "sg:tags":[
        "church"
    ],
    "wof:name":"Blackshear Church of God",
    "wof:placetype":"venue"
},
  "geometry": {"coordinates":[-82.248756,31.31161],"type":"Point"}
}