{
  "type": "Feature",
  "properties": {
    "addr:full":"5450 Peachtree Pkwy Norcross GA 30092",
    "addr:housenumber":"5450",
    "addr:postcode":"30092",
    "addr:street":"Peachtree Pkwy",
    "iso:country":"US",
    "sg:address":"5450 Peachtree Pkwy",
    "sg:city":"Norcross",
    "sg:classifiers":[
        {
            "category":"Deli",
            "type":"Food & Drink"
        }
    ],
    "sg:menulink":"http://www.allmenus.com/ga/norcross/156719-my-friends-place/menu/",
    "sg:phone":"+1 770 446 8629",
    "sg:postcode":"30092",
    "sg:province":"GA",
    "sg:tags":[
        "american"
    ],
    "wof:name":"My Friend's Place",
    "wof:placetype":"venue"
},
  "geometry": {"coordinates":[-84.219159,33.970448],"type":"Point"}
}