{
  "type": "Feature",
  "properties": {
    "addr:full":"111 Habersham Pl Carrollton GA 30117",
    "addr:housenumber":"111",
    "addr:postcode":"30117",
    "addr:street":"Habersham Pl",
    "iso:country":"US",
    "sg:address":"111 Habersham Pl",
    "sg:city":"Carrollton",
    "sg:classifiers":[
        {
            "category":"Wholesale",
            "subcategory":"Auto Parts",
            "type":"Manufacturing & Wholesale Goods"
        }
    ],
    "sg:phone":"+1 770 834 2714",
    "sg:postcode":"30117",
    "sg:province":"GA",
    "wof:name":"Bill Perry & Associates Inc",
    "wof:placetype":"venue"
},
  "geometry": {"coordinates":[-85.10587,33.563642],"type":"Point"}
}