{
  "type": "Feature",
  "properties": {
    "iso:country":"US",
    "sg:address":"993 Johnson Ferry Rd NE Ste D240",
    "sg:city":"Atlanta",
    "sg:classifiers":[
        {
            "category":"Shopping",
            "subcategory":"Optician",
            "type":"Retail Goods"
        },
        {
            "category":"Health Services",
            "subcategory":"Optometrist",
            "type":"Services"
        }
    ],
    "sg:phone":"+1 404 252 0624",
    "sg:postcode":"30342",
    "sg:province":"GA",
    "sg:tags":[
        "optical",
        "eyewear"
    ],
    "wof:name":"Northside Optical Ltd",
    "wof:placetype":"venue"
},
  "geometry": {"coordinates":[-84.355903,33.90735],"type":"Point"}
}