{
  "type": "Feature",
  "properties": {
    "iso:country":"US",
    "sg:address":"710 S Cave Spring St",
    "sg:city":"Cedartown",
    "sg:classifiers":[
        {
            "category":"Organizations",
            "subcategory":"Religious Organization",
            "type":"Services"
        }
    ],
    "sg:phone":"+1 770 748 7466",
    "sg:postcode":"30125",
    "sg:province":"GA",
    "wof:name":"Calvery Assembly of God",
    "wof:placetype":"venue"
},
  "geometry": {"coordinates":[-85.25871600000001,34.005784],"type":"Point"}
}