{
  "type": "Feature",
  "properties": {
    "addr:full":"1019 Memorial Dr Griffin GA 30223",
    "addr:housenumber":"1019",
    "addr:postcode":"30223",
    "addr:street":"Memorial Dr",
    "iso:country":"US",
    "sg:address":"1019 Memorial Dr",
    "sg:city":"Griffin",
    "sg:classifiers":[
        {
            "category":"Shopping",
            "subcategory":"Discount & Variety Stores",
            "type":"Retail Goods"
        }
    ],
    "sg:phone":"+1 770 233 9434",
    "sg:postcode":"30223",
    "sg:province":"GA",
    "wof:name":"Dollar General",
    "wof:placetype":"venue"
},
  "geometry": {"coordinates":[-84.253742,33.246063],"type":"Point"}
}