{
  "type": "Feature",
  "properties": {
    "addr:full":"133 Heritage Dr Thomasville GA 31792",
    "addr:housenumber":"133",
    "addr:postcode":"31792",
    "addr:street":"Heritage Dr",
    "iso:country":"US",
    "sg:address":"133 Heritage Dr",
    "sg:city":"Thomasville",
    "sg:classifiers":[
        {
            "category":"Farming",
            "subcategory":"Crops",
            "type":"Manufacturing & Wholesale Goods"
        }
    ],
    "sg:phone":"+1 229 226 3690",
    "sg:postcode":"31792",
    "sg:province":"GA",
    "sg:tags":[
        "farm",
        "grove",
        "nut",
        "tree",
        "field",
        "corn"
    ],
    "wof:name":"Rhett Stilwell",
    "wof:placetype":"venue"
},
  "geometry": {"coordinates":[-83.941937,30.816471],"type":"Point"}
}