{
  "type": "Feature",
  "properties": {
    "addr:full":"2510 Shallowford Rd Marietta GA 30066",
    "addr:housenumber":"2510",
    "addr:postcode":"30066",
    "addr:street":"Shallowford Rd",
    "iso:country":"US",
    "sg:address":"2510 Shallowford Rd",
    "sg:city":"Marietta",
    "sg:classifiers":[
        {
            "category":"Home & Garden",
            "subcategory":"Hardware",
            "type":"Retail Goods"
        }
    ],
    "sg:phone":"+1 770 926 0700",
    "sg:postcode":"30066",
    "sg:province":"GA",
    "sg:tags":[
        "store"
    ],
    "wof:name":"Hardware Shallowford True Value",
    "wof:placetype":"venue"
},
  "geometry": {"coordinates":[-84.476799,34.041302],"type":"Point"}
}