{
  "type": "Feature",
  "properties": {
    "iso:country":"US",
    "sg:address":"250 Spring Street NW",
    "sg:city":"Atlanta",
    "sg:classifiers":[
        {
            "category":"Shopping",
            "subcategory":"Clothing, Apparel, & Fashions",
            "type":"Retail Goods"
        }
    ],
    "sg:phone":"+1 404 658 9264",
    "sg:postcode":"30303",
    "sg:province":"GA",
    "sg:tags":[
        "children's",
        "clothing"
    ],
    "wof:name":"Atlanta Hosiery Company",
    "wof:placetype":"venue"
},
  "geometry": {"coordinates":[-84.38900099999999,33.761587],"type":"Point"}
}