{
  "type": "Feature",
  "properties": {
    "iso:country":"US",
    "sg:address":"195 Crescent Dr",
    "sg:city":"Newnan",
    "sg:classifiers":[
        {
            "category":"Professional",
            "subcategory":"Management & Consulting",
            "type":"Services"
        }
    ],
    "sg:phone":"+1 770 304 2695",
    "sg:postcode":"30265",
    "sg:province":"GA",
    "wof:name":"Concept Construction Mgt",
    "wof:placetype":"venue"
},
  "geometry": {"coordinates":[-84.68302199999999,33.428189],"type":"Point"}
}