{
  "type": "Feature",
  "properties": {
    "iso:country":"US",
    "sg:address":"12 Hemingway Dr",
    "sg:city":"Savannah",
    "sg:classifiers":[
        {
            "category":"Travel",
            "subcategory":"Travel Agent",
            "type":"Entertainment"
        }
    ],
    "sg:phone":"+1 912 598 9789",
    "sg:postcode":"31411",
    "sg:province":"GA",
    "sg:tags":[
        "agency",
        "tourist"
    ],
    "wof:name":"Grand Destination Management",
    "wof:placetype":"venue"
},
  "geometry": {"coordinates":[-81.04106,31.930389],"type":"Point"}
}