{
  "type": "Feature",
  "properties": {
    "iso:country":"US",
    "sg:address":"2453 Powder Springs Rd SW",
    "sg:city":"Marietta",
    "sg:classifiers":[
        {
            "category":"Health Services",
            "subcategory":"Chiropractor",
            "type":"Services"
        }
    ],
    "sg:phone":"+1 770 439 9355",
    "sg:postcode":"30064",
    "sg:province":"GA",
    "sg:tags":[
        "chiropractic"
    ],
    "wof:name":"Pro Health & Rehab",
    "wof:placetype":"venue"
},
  "geometry": {"coordinates":[-84.624624,33.872565],"type":"Point"}
}