{
  "type": "Feature",
  "properties": {
    "iso:country":"US",
    "sg:address":"1055 Lancashire Cir",
    "sg:city":"Stone Mountain",
    "sg:classifiers":[
        {
            "category":"Real Estate",
            "subcategory":"Real Estate Operator",
            "type":"Services"
        }
    ],
    "sg:phone":"+1 404 292 0985",
    "sg:postcode":"30083",
    "sg:province":"GA",
    "sg:tags":[
        "apartment"
    ],
    "wof:name":"Lancashire Court",
    "wof:placetype":"venue"
},
  "geometry": {"coordinates":[-84.19090300000001,33.809898],"type":"Point"}
}