{
  "type": "Feature",
  "properties": {
    "iso:country":"US",
    "sg:address":"3604 Bakers Ferry Rd SW",
    "sg:city":"Atlanta",
    "sg:classifiers":[
        {
            "category":"Restaurant",
            "type":"Food & Drink"
        }
    ],
    "sg:menulink":"http://www.allmenus.com/ga/atlanta/195960-taco-bell/menu/",
    "sg:postcode":"30331",
    "sg:province":"GA",
    "sg:tags":[
        "mexican"
    ],
    "wof:name":"Taco Bell",
    "wof:placetype":"venue"
},
  "geometry": {"coordinates":[-84.506038,33.758928],"type":"Point"}
}