{
  "type": "Feature",
  "properties": {
    "addr:full":"1400 Roberta Dr SW Marietta GA 30008",
    "addr:housenumber":"1400",
    "addr:postcode":"30008",
    "addr:street":"Roberta Dr Sw",
    "iso:country":"US",
    "sg:address":"1400 Roberta Dr SW",
    "sg:city":"Marietta",
    "sg:classifiers":[
        {
            "category":"Local Transit",
            "type":"Transportation"
        }
    ],
    "sg:phone":"+1 678 642 5250",
    "sg:postcode":"30008",
    "sg:province":"GA",
    "sg:tags":[
        "shuttle"
    ],
    "wof:name":"G&C Limousines",
    "wof:placetype":"venue"
},
  "geometry": {"coordinates":[-84.557541,33.916409],"type":"Point"}
}