{
  "type": "Feature",
  "properties": {
    "iso:country":"US",
    "sg:address":"224 Hammond Drive NE",
    "sg:city":"Atlanta",
    "sg:classifiers":[
        {
            "category":"Autos & Motor Vehicles",
            "subcategory":"Auto Supplies",
            "type":"Retail Goods"
        }
    ],
    "sg:phone":"+1 404 256 4195",
    "sg:postcode":"30328",
    "sg:province":"GA",
    "sg:tags":[
        "tire"
    ],
    "sg:website":"www.big10tires.com",
    "wof:name":"Big 10 Tires and Automotive Service Centers",
    "wof:placetype":"venue"
},
  "geometry": {"coordinates":[-84.382143,33.918907],"type":"Point"}
}