{
  "type": "Feature",
  "properties": {
    "addr:full":"104 Commerce Ave Lagrange GA 30241",
    "addr:housenumber":"104",
    "addr:postcode":"30241",
    "addr:street":"Commerce Ave",
    "iso:country":"US",
    "sg:address":"104 Commerce Ave",
    "sg:city":"Lagrange",
    "sg:classifiers":[
        {
            "category":"Restaurant",
            "type":"Food & Drink"
        }
    ],
    "sg:menulink":"http://www.allmenus.com/ga/lagrange/100682-captain-ds-seafood/menu/",
    "sg:phone":"+1 706 884 4005",
    "sg:postcode":"30241",
    "sg:province":"GA",
    "sg:tags":[
        "seafood",
        "american"
    ],
    "wof:name":"Captain D's Seafood",
    "wof:placetype":"venue"
},
  "geometry": {"coordinates":[-85.02851099999999,33.049347],"type":"Point"}
}