{
  "type": "Feature",
  "properties": {
    "addr:full":"111 S Main St Lake Park GA 31636",
    "addr:housenumber":"111",
    "addr:postcode":"31636",
    "addr:street":"S Main St",
    "iso:country":"US",
    "sg:address":"111 S Main St",
    "sg:city":"Lake Park",
    "sg:classifiers":[
        {
            "category":"Manufacturing",
            "subcategory":"Tools & Machinery",
            "type":"Manufacturing & Wholesale Goods"
        }
    ],
    "sg:phone":"+1 229 559 6327",
    "sg:postcode":"31636",
    "sg:province":"GA",
    "sg:tags":[
        "fire",
        "equipment",
        "protection"
    ],
    "wof:name":"Bennett's Fire Protection Syst",
    "wof:placetype":"venue"
},
  "geometry": {"coordinates":[-83.18002799999999,30.683196],"type":"Point"}
}