{
  "type": "Feature",
  "properties": {
    "addr:full":"309 Cutty Sark Way Alpharetta GA 30005",
    "addr:housenumber":"309",
    "addr:postcode":"30005",
    "addr:street":"Cutty Sark Way",
    "iso:country":"US",
    "sg:address":"309 Cutty Sark Way",
    "sg:city":"Alpharetta",
    "sg:classifiers":[
        {
            "category":"Professional",
            "subcategory":"Engineering",
            "type":"Services"
        }
    ],
    "sg:phone":"+1 678 977 1508",
    "sg:postcode":"30005",
    "sg:province":"GA",
    "sg:tags":[
        "consultant",
        "energy",
        "conservation"
    ],
    "wof:name":"Jogar Energy & Utility Services, Inc.",
    "wof:placetype":"venue"
},
  "geometry": {"coordinates":[-84.225314,34.073682],"type":"Point"}
}