{
  "type": "Feature",
  "properties": {
    "addr:full":"5300 Memorial Dr Stone Mountain GA 30083",
    "addr:housenumber":"5300",
    "addr:postcode":"30083",
    "addr:street":"Memorial Dr",
    "iso:country":"US",
    "sg:address":"5300 Memorial Dr",
    "sg:city":"Stone Mountain",
    "sg:classifiers":[
        {
            "category":"Personal",
            "subcategory":"Beauty Salon",
            "type":"Services"
        }
    ],
    "sg:phone":"+1 770 298 0619",
    "sg:postcode":"30083",
    "sg:province":"GA",
    "sg:tags":[
        "treatment",
        "skin"
    ],
    "wof:name":"Total U By Melvnia",
    "wof:placetype":"venue"
},
  "geometry": {"coordinates":[-84.21485,33.800523],"type":"Point"}
}