{
  "type": "Feature",
  "properties": {
    "iso:country":"US",
    "sg:address":"586 Highview Cir",
    "sg:city":"Grovetown",
    "sg:classifiers":[
        {
            "category":"Professional",
            "type":"Services"
        }
    ],
    "sg:phone":"+1 706 855 8438",
    "sg:postcode":"30813",
    "sg:province":"GA",
    "wof:name":"David Fearneyhough",
    "wof:placetype":"venue"
},
  "geometry": {"coordinates":[-82.175719,33.468878],"type":"Point"}
}