{
  "type": "Feature",
  "properties": {
    "iso:country":"US",
    "sg:address":"610 E Ann St",
    "sg:city":"Valdosta",
    "sg:classifiers":[
        {
            "category":"Real Estate",
            "subcategory":"Real Estate Operator",
            "type":"Services"
        }
    ],
    "sg:phone":"+1 229 242 4130",
    "sg:postcode":"31601",
    "sg:province":"GA",
    "sg:tags":[
        "apartment"
    ],
    "sg:website":"http://www.valdostahousingauthority.org",
    "wof:name":"Valdosta Housing Authority",
    "wof:placetype":"venue"
},
  "geometry": {"coordinates":[-83.277689,30.84506],"type":"Point"}
}