{
  "type": "Feature",
  "properties": {
    "iso:country":"US",
    "sg:address":"690 Freeman Dr",
    "sg:city":"Covington",
    "sg:classifiers":[
        {
            "category":"Professional",
            "subcategory":"Employment Agencies",
            "type":"Services"
        }
    ],
    "sg:phone":"+1 678 253 4147",
    "sg:postcode":"30016",
    "sg:province":"GA",
    "sg:website":"ama-unified-communications.com",
    "wof:name":"AMA Unified Communications Corporation",
    "wof:placetype":"venue"
},
  "geometry": {"coordinates":[-84.01563,33.523743],"type":"Point"}
}