{
  "type": "Feature",
  "properties": {
    "iso:country":"US",
    "sg:address":"4403 E Durham Cir",
    "sg:city":"Stone Mountain",
    "sg:classifiers":[
        {
            "category":"Freight",
            "type":"Transportation"
        }
    ],
    "sg:phone":"+1 404 299 6817",
    "sg:postcode":"30083",
    "sg:province":"GA",
    "sg:tags":[
        "hauling",
        "trucking"
    ],
    "wof:name":"MVG Trucking Co",
    "wof:placetype":"venue"
},
  "geometry": {"coordinates":[-84.211315,33.767988],"type":"Point"}
}