{
  "type": "Feature",
  "properties": {
    "iso:country":"US",
    "sg:address":"152 N Crest Blvd",
    "sg:city":"Macon",
    "sg:classifiers":[
        {
            "category":"Professional",
            "subcategory":"Accounting & Tax Preparation",
            "type":"Services"
        }
    ],
    "sg:phone":"+1 478 477 4666",
    "sg:postcode":"31210",
    "sg:province":"GA",
    "sg:tags":[
        "return"
    ],
    "wof:name":"Randall L Brittain CPA",
    "wof:placetype":"venue"
},
  "geometry": {"coordinates":[-83.693213,32.903367],"type":"Point"}
}