{
  "type": "Feature",
  "properties": {
    "addr:full":"118 Suncrest Blvd Savannah GA 31410",
    "addr:housenumber":"118",
    "addr:postcode":"31410",
    "addr:street":"Suncrest Blvd",
    "iso:country":"US",
    "sg:address":"118 Suncrest Blvd",
    "sg:city":"Savannah",
    "sg:classifiers":[
        {
            "category":"Shopping",
            "type":"Retail Goods"
        }
    ],
    "sg:phone":"+1 912 897 9179",
    "sg:postcode":"31410",
    "sg:province":"GA",
    "sg:tags":[
        "merchandise"
    ],
    "wof:name":"Be Healthy & More",
    "wof:placetype":"venue"
},
  "geometry": {"coordinates":[-80.975632,32.029805],"type":"Point"}
}