{
  "type": "Feature",
  "properties": {
    "addr:full":"123 W Cherry St Jesup GA 31545",
    "addr:housenumber":"123",
    "addr:postcode":"31545",
    "addr:street":"W Cherry St",
    "iso:country":"US",
    "sg:address":"123 W Cherry St",
    "sg:city":"Jesup",
    "sg:classifiers":[
        {
            "category":"Shopping",
            "subcategory":"Crafts & Fabrics",
            "type":"Retail Goods"
        }
    ],
    "sg:phone":"+1 912 427 2415",
    "sg:postcode":"31545",
    "sg:province":"GA",
    "sg:tags":[
        "textile"
    ],
    "wof:name":"Wildwood Textile Sales",
    "wof:placetype":"venue"
},
  "geometry": {"coordinates":[-81.884035,31.60604],"type":"Point"}
}