{
  "type": "Feature",
  "properties": {
    "iso:country":"US",
    "sg:address":"111 Mountainview Cir",
    "sg:city":"Canton",
    "sg:classifiers":[
        {
            "category":"Restaurant",
            "type":"Food & Drink"
        }
    ],
    "sg:phone":"+1 678 880 0717",
    "sg:postcode":"30115",
    "sg:province":"GA",
    "wof:name":"Dos Maragritas",
    "wof:placetype":"venue"
},
  "geometry": {"coordinates":[-84.498689,34.188393],"type":"Point"}
}