{
  "type": "Feature",
  "properties": {
    "iso:country":"US",
    "sg:address":"371 Farr Rd",
    "sg:city":"Tyrone",
    "sg:classifiers":[
        {
            "category":"Social Services",
            "subcategory":"Job Training",
            "type":"Services"
        }
    ],
    "sg:phone":"+1 770 632 9219",
    "sg:postcode":"30290",
    "sg:province":"GA",
    "sg:tags":[
        "leadership"
    ],
    "wof:name":"Jo Rusin Leadership",
    "wof:placetype":"venue"
},
  "geometry": {"coordinates":[-84.577257,33.464194],"type":"Point"}
}