{
  "type": "Feature",
  "properties": {
    "iso:country":"US",
    "sg:address":"132 Gloster Rd NW",
    "sg:city":"Lawrenceville",
    "sg:classifiers":[
        {
            "category":"Real Estate",
            "subcategory":"Real Estate Agent",
            "type":"Services"
        }
    ],
    "sg:phone":"+1 770 923 3703",
    "sg:postcode":"30044",
    "sg:province":"GA",
    "wof:name":"Rl Panyik & Assoc Inc",
    "wof:placetype":"venue"
},
  "geometry": {"coordinates":[-84.06968999999999,33.919412],"type":"Point"}
}