{
  "type": "Feature",
  "properties": {
    "addr:full":"4766 Olde Village Ln Atlanta GA 30338",
    "addr:housenumber":"4766",
    "addr:postcode":"30338",
    "addr:street":"Olde Village Ln",
    "iso:country":"US",
    "sg:address":"4766 Olde Village Ln",
    "sg:city":"Atlanta",
    "sg:classifiers":[
        {
            "category":"Manufacturing",
            "subcategory":"Tools & Machinery",
            "type":"Manufacturing & Wholesale Goods"
        }
    ],
    "sg:phone":"+1 770 551 0971",
    "sg:postcode":"30338",
    "sg:province":"GA",
    "sg:tags":[
        "springs-wholesale",
        "manufacturer"
    ],
    "wof:name":"Dunwoody Funhouse",
    "wof:placetype":"venue"
},
  "geometry": {"coordinates":[-84.310303,33.93729],"type":"Point"}
}