{
  "type": "Feature",
  "properties": {
    "iso:country":"US",
    "sg:address":"255 Corporate Center Dr",
    "sg:city":"Stockbridge",
    "sg:classifiers":[
        {
            "category":"Health Services",
            "subcategory":"Optometrist",
            "type":"Services"
        }
    ],
    "sg:phone":"+1 770 474 7761",
    "sg:postcode":"30281",
    "sg:province":"GA",
    "sg:tags":[
        "ophthalmologist"
    ],
    "wof:name":"Freeman Kevin S MD",
    "wof:placetype":"venue"
},
  "geometry": {"coordinates":[-84.21959699999999,33.507],"type":"Point"}
}