{
  "type": "Feature",
  "properties": {
    "iso:country":"US",
    "sg:address":"1453 Oakridge Cir",
    "sg:city":"Decatur",
    "sg:classifiers":[
        {
            "category":"Professional",
            "type":"Services"
        }
    ],
    "sg:phone":"+1 404 636 4499",
    "sg:postcode":"30033",
    "sg:province":"GA",
    "wof:name":"Patricia Dunkel",
    "wof:placetype":"venue"
},
  "geometry": {"coordinates":[-84.283502,33.823731],"type":"Point"}
}