{
  "type": "Feature",
  "properties": {
    "addr:full":"728 Pine Ave Albany GA 31701",
    "addr:housenumber":"728",
    "addr:postcode":"31701",
    "addr:street":"Pine Ave",
    "iso:country":"US",
    "sg:address":"728 Pine Ave",
    "sg:city":"Albany",
    "sg:classifiers":[
        {
            "category":"Personal",
            "subcategory":"Beauty Salon",
            "type":"Services"
        }
    ],
    "sg:phone":"+1 229 883 8444",
    "sg:postcode":"31701",
    "sg:province":"GA",
    "sg:tags":[
        "shop"
    ],
    "wof:name":"Ashanti S Hair Care",
    "wof:placetype":"venue"
},
  "geometry": {"coordinates":[-84.165593,31.578351],"type":"Point"}
}