{
  "type": "Feature",
  "properties": {
    "addr:full":"2214 Palmyra Rd Albany GA 31701",
    "addr:housenumber":"2214",
    "addr:postcode":"31701",
    "addr:street":"Palmyra Rd",
    "iso:country":"US",
    "sg:address":"2214 Palmyra Rd",
    "sg:city":"Albany",
    "sg:classifiers":[
        {
            "category":"Personal",
            "subcategory":"Beauty Salon",
            "type":"Services"
        }
    ],
    "sg:phone":"+1 229 446 1088",
    "sg:postcode":"31701",
    "sg:province":"GA",
    "sg:tags":[
        "shop"
    ],
    "wof:name":"Nails Unlimited",
    "wof:placetype":"venue"
},
  "geometry": {"coordinates":[-84.17411800000001,31.608832],"type":"Point"}
}