{
  "type": "Feature",
  "properties": {
    "addr:full":"137 Larkin St Ste 6045 Cornelia GA 30531",
    "addr:housenumber":"137",
    "addr:postcode":"30531",
    "addr:street":"Larkin St Ste 6045 Cornelia",
    "iso:country":"US",
    "sg:address":"137 Larkin St Ste 6045",
    "sg:city":"Cornelia",
    "sg:classifiers":[
        {
            "category":"Social Services",
            "subcategory":"Adult Care",
            "type":"Services"
        },
        {
            "category":"Community Center",
            "subcategory":"Youth",
            "type":"Public Place"
        }
    ],
    "sg:phone":"+1 706 776 8298",
    "sg:postcode":"30531",
    "sg:province":"GA",
    "sg:tags":[
        "camp"
    ],
    "wof:name":"Wow Youth Camp Inc Of North Georgia",
    "wof:placetype":"venue"
},
  "geometry": {"coordinates":[-83.52449900000001,34.509517],"type":"Point"}
}