{
  "type": "Feature",
  "properties": {
    "iso:country":"US",
    "sg:address":"3906 Savannah Dr",
    "sg:city":"Columbus",
    "sg:classifiers":[
        {
            "category":"Building & Trades",
            "subcategory":"Plumbing",
            "type":"Services"
        }
    ],
    "sg:phone":"+1 706 561 0689",
    "sg:postcode":"31907",
    "sg:province":"GA",
    "sg:tags":[
        "conditioning",
        "air",
        "system",
        "contractor"
    ],
    "wof:name":"Stokes Heating & Air Cond",
    "wof:placetype":"venue"
},
  "geometry": {"coordinates":[-84.926456,32.501286],"type":"Point"}
}