{
  "type": "Feature",
  "properties": {
    "addr:full":"2955 Shady Creek Ct Marietta GA 30062",
    "addr:housenumber":"2955",
    "addr:postcode":"30062",
    "addr:street":"Shady Creek Ct",
    "iso:country":"US",
    "sg:address":"2955 Shady Creek Ct",
    "sg:city":"Marietta",
    "sg:classifiers":[
        {
            "category":"Home & Garden",
            "subcategory":"Garden Supply",
            "type":"Retail Goods"
        }
    ],
    "sg:phone":"+1 770 973 2615",
    "sg:postcode":"30062",
    "sg:province":"GA",
    "wof:name":"Dixie Bonsai From",
    "wof:placetype":"venue"
},
  "geometry": {"coordinates":[-84.449406,34.022069],"type":"Point"}
}