{
  "type": "Feature",
  "properties": {
    "addr:full":"13751 Highway 411 N Crandall GA 30711",
    "addr:housenumber":"13751",
    "addr:postcode":"30711",
    "addr:street":"Highway 411 N",
    "iso:country":"US",
    "sg:address":"13751 Highway 411 N",
    "sg:city":"Crandall",
    "sg:classifiers":[
        {
            "category":"Travel",
            "subcategory":"Hotels & Motels",
            "type":"Entertainment"
        },
        {
            "category":"Personal",
            "type":"Services"
        }
    ],
    "sg:phone":"+1 706 328 3083",
    "sg:postcode":"30711",
    "sg:province":"GA",
    "sg:tags":[
        "concierge",
        "assistant"
    ],
    "wof:name":"Paul Douthitt",
    "wof:placetype":"venue"
},
  "geometry": {"coordinates":[-84.732681,34.968349],"type":"Point"}
}