{
  "type": "Feature",
  "properties": {
    "addr:full":"2649 Bridgehampton Rd SW Marietta GA 30064",
    "addr:housenumber":"2649",
    "addr:postcode":"30064",
    "addr:street":"Bridgehampton Rd Sw",
    "iso:country":"US",
    "sg:address":"2649 Bridgehampton Rd SW",
    "sg:city":"Marietta",
    "sg:classifiers":[
        {
            "category":"Building & Trades",
            "subcategory":"Construction",
            "type":"Services"
        }
    ],
    "sg:phone":"+1 678 232 5758",
    "sg:postcode":"30064",
    "sg:province":"GA",
    "sg:tags":[
        "house"
    ],
    "wof:name":"J & K Creations",
    "wof:placetype":"venue"
},
  "geometry": {"coordinates":[-84.620279,33.891138],"type":"Point"}
}