{
  "type": "Feature",
  "properties": {
    "iso:country":"US",
    "sg:address":"4155 US Hwy 27",
    "sg:city":"Cataula",
    "sg:classifiers":[
        {
            "category":"Education",
            "subcategory":"Dance Studio",
            "type":"Public Place"
        }
    ],
    "sg:phone":"+1 706 320 9250",
    "sg:postcode":"31804",
    "sg:province":"GA",
    "wof:name":"Center Stage Dance Studio",
    "wof:placetype":"venue"
},
  "geometry": {"coordinates":[-84.872804,32.650441],"type":"Point"}
}