{
  "type": "Feature",
  "properties": {
    "addr:full":"3008 Tealing Walk Roswell GA 30075",
    "addr:housenumber":"3008",
    "addr:postcode":"30075",
    "addr:street":"Tealing Walk",
    "iso:country":"US",
    "sg:address":"3008 Tealing Walk",
    "sg:city":"Roswell",
    "sg:classifiers":[
        {
            "category":"Professional",
            "subcategory":"Lawyer & Legal Services",
            "type":"Services"
        }
    ],
    "sg:phone":"+1 770 650 2720",
    "sg:postcode":"30075",
    "sg:province":"GA",
    "wof:name":"Richard W Monat",
    "wof:placetype":"venue"
},
  "geometry": {"coordinates":[-84.40435600000001,34.018972],"type":"Point"}
}