{
  "type": "Feature",
  "properties": {
    "iso:country":"US",
    "sg:address":"20 Barksdale Dr",
    "sg:city":"Savannah",
    "sg:classifiers":[
        {
            "category":"Building & Trades",
            "subcategory":"Construction",
            "type":"Services"
        }
    ],
    "sg:phone":"+1 912 925 5700",
    "sg:postcode":"31419",
    "sg:province":"GA",
    "sg:tags":[
        "contractor"
    ],
    "wof:name":"Acoustical Solutions",
    "wof:placetype":"venue"
},
  "geometry": {"coordinates":[-81.226185,31.984209],"type":"Point"}
}