{
  "type": "Feature",
  "properties": {
    "iso:country":"US",
    "sg:address":"3278 Beech Dr",
    "sg:city":"Decatur",
    "sg:classifiers":[
        {
            "category":"Transit Center",
            "subcategory":"Freight",
            "type":"Transportation"
        },
        {
            "category":"Freight",
            "type":"Transportation"
        }
    ],
    "sg:phone":"+1 404 284 0169",
    "sg:postcode":"30032",
    "sg:province":"GA",
    "sg:tags":[
        "trucking-motor",
        "trucking"
    ],
    "wof:name":"American Way Hauling",
    "wof:placetype":"venue"
},
  "geometry": {"coordinates":[-84.255107,33.75708],"type":"Point"}
}