{
  "type": "Feature",
  "properties": {
    "addr:full":"127 S Belair Rd Augusta GA 30907",
    "addr:housenumber":"127",
    "addr:postcode":"30907",
    "addr:street":"S Belair Rd",
    "iso:country":"US",
    "sg:address":"127 S Belair Rd",
    "sg:city":"Augusta",
    "sg:classifiers":[
        {
            "category":"Health Services",
            "subcategory":"Optometrist",
            "type":"Services"
        }
    ],
    "sg:phone":"+1 706 869 1800",
    "sg:postcode":"30907",
    "sg:province":"GA",
    "wof:name":"E Jack Moomey OD",
    "wof:placetype":"venue"
},
  "geometry": {"coordinates":[-82.140351,33.502581],"type":"Point"}
}