{
  "type": "Feature",
  "properties": {
    "addr:full":"1855 Hodges Cir Mansfield GA 30055",
    "addr:housenumber":"1855",
    "addr:postcode":"30055",
    "addr:street":"Hodges Cir",
    "iso:country":"US",
    "sg:address":"1855 Hodges Cir",
    "sg:city":"Mansfield",
    "sg:classifiers":[
        {
            "category":"Building & Trades",
            "subcategory":"Construction",
            "type":"Services"
        }
    ],
    "sg:phone":"+1 770 385 6338",
    "sg:postcode":"30055",
    "sg:province":"GA",
    "sg:tags":[
        "house"
    ],
    "wof:name":"Trim Line Construction Inc",
    "wof:placetype":"venue"
},
  "geometry": {"coordinates":[-83.68218899999999,33.573508],"type":"Point"}
}