{
  "type": "Feature",
  "properties": {
    "addr:full":"2132 Brookview Dr NW Atlanta GA 30318",
    "addr:housenumber":"2132",
    "addr:postcode":"30318",
    "addr:street":"Brookview Dr Nw",
    "iso:country":"US",
    "sg:address":"2132 Brookview Dr NW",
    "sg:city":"Atlanta",
    "sg:classifiers":[
        {
            "category":"Professional",
            "subcategory":"Engineering",
            "type":"Services"
        }
    ],
    "sg:phone":"+1 404 605 0520",
    "sg:postcode":"30318",
    "sg:province":"GA",
    "sg:tags":[
        "conglomerate"
    ],
    "wof:name":"Rmp",
    "wof:placetype":"venue"
},
  "geometry": {"coordinates":[-84.41982400000001,33.814618],"type":"Point"}
}