{
  "type": "Feature",
  "properties": {
    "addr:full":"4228 Cheltingham Lane Smyrna GA 30082",
    "addr:housenumber":"4228",
    "addr:postcode":"30082",
    "addr:street":"Cheltingham Lane",
    "iso:country":"US",
    "sg:address":"4228 Cheltingham Lane",
    "sg:city":"Smyrna",
    "sg:classifiers":[
        {
            "category":"Arts & Performance",
            "subcategory":"Music",
            "type":"Entertainment"
        }
    ],
    "sg:phone":"+1 770 433 3208",
    "sg:postcode":"30082",
    "sg:province":"GA",
    "sg:tags":[
        "arranger",
        "composer"
    ],
    "sg:website":"http://www.fatsoproductions.com",
    "wof:name":"Fat-So Productions, Inc.",
    "wof:placetype":"venue"
},
  "geometry": {"coordinates":[-84.529562,33.85037],"type":"Point"}
}