{
  "type": "Feature",
  "properties": {
    "addr:full":"45 N Main St Clayton GA 30525",
    "addr:housenumber":"45",
    "addr:postcode":"30525",
    "addr:street":"N Main St",
    "iso:country":"US",
    "sg:address":"45 N Main St",
    "sg:city":"Clayton",
    "sg:classifiers":[
        {
            "category":"Banks & Credit Unions",
            "subcategory":"Bank",
            "type":"Services"
        }
    ],
    "sg:phone":"+1 706 782 4256",
    "sg:postcode":"30525",
    "sg:province":"GA",
    "sg:tags":[
        "financing"
    ],
    "wof:name":"First Franklin Financial Corp",
    "wof:placetype":"venue"
},
  "geometry": {"coordinates":[-83.40080399999999,34.879623],"type":"Point"}
}