{
  "type": "Feature",
  "properties": {
    "addr:full":"5053 Glaze Dr Atlanta GA 30360",
    "addr:postcode":"5053;30360",
    "addr:street":"Glaze Dr",
    "iso:country":"US",
    "sg:address":"5053 Glaze Dr",
    "sg:city":"Atlanta",
    "sg:classifiers":[
        {
            "category":"Building & Trades",
            "subcategory":"Landscaping Services",
            "type":"Services"
        }
    ],
    "sg:phone":"+1 770 396 3500",
    "sg:postcode":"30360",
    "sg:province":"GA",
    "sg:tags":[
        "tree"
    ],
    "wof:name":"A Arm Strong Tree",
    "wof:placetype":"venue"
},
  "geometry": {"coordinates":[-84.271502,33.946572],"type":"Point"}
}