{
  "type": "Feature",
  "properties": {
    "addr:full":"1350 Larson Ct Marietta GA 30064",
    "addr:housenumber":"1350",
    "addr:postcode":"30064",
    "addr:street":"Larson Ct",
    "iso:country":"US",
    "sg:address":"1350 Larson Ct",
    "sg:city":"Marietta",
    "sg:classifiers":[
        {
            "category":"Manufacturing",
            "subcategory":"Apparel",
            "type":"Manufacturing & Wholesale Goods"
        }
    ],
    "sg:phone":"+1 770 428 7423",
    "sg:postcode":"30064",
    "sg:province":"GA",
    "sg:tags":[
        "mfg"
    ],
    "wof:name":"Childrens Market",
    "wof:placetype":"venue"
},
  "geometry": {"coordinates":[-84.597782,33.919818],"type":"Point"}
}