{
  "type": "Feature",
  "properties": {
    "iso:country":"US",
    "sg:address":"4571 Piney Grove Rd",
    "sg:city":"Cumming",
    "sg:classifiers":[
        {
            "category":"Building & Trades",
            "subcategory":"Landscaping Services",
            "type":"Services"
        }
    ],
    "sg:phone":"+1 770 886 5070",
    "sg:postcode":"30040",
    "sg:province":"GA",
    "sg:tags":[
        "landscape",
        "contractor"
    ],
    "wof:name":"Creech Landscape & Cnstr",
    "wof:placetype":"venue"
},
  "geometry": {"coordinates":[-84.170913,34.183193],"type":"Point"}
}