{
  "type": "Feature",
  "properties": {
    "iso:country":"US",
    "sg:address":"110 Gould St",
    "sg:city":"Saint Simons Island",
    "sg:classifiers":[
        {
            "category":"Professional",
            "type":"Services"
        }
    ],
    "sg:phone":"+1 912 638 9542",
    "sg:postcode":"31522",
    "sg:province":"GA",
    "wof:name":"Neil Glasscock",
    "wof:placetype":"venue"
},
  "geometry": {"coordinates":[-81.40290400000001,31.136848],"type":"Point"}
}