{
  "type": "Feature",
  "properties": {
    "iso:country":"US",
    "sg:address":"115 Temple St",
    "sg:city":"Villa Rica",
    "sg:classifiers":[
        {
            "category":"Organizations",
            "subcategory":"Religious Organization",
            "type":"Services"
        }
    ],
    "sg:phone":"+1 770 214 2303",
    "sg:postcode":"30180",
    "sg:province":"GA",
    "sg:tags":[
        "church"
    ],
    "wof:name":"License Christian Therapy",
    "wof:placetype":"venue"
},
  "geometry": {"coordinates":[-84.918359,33.731578],"type":"Point"}
}