{
  "type": "Feature",
  "properties": {
    "addr:full":"20 Grandview Rd Jasper GA 30143",
    "addr:housenumber":"20",
    "addr:postcode":"30143",
    "addr:street":"Grandview Rd",
    "iso:country":"US",
    "sg:address":"20 Grandview Rd",
    "sg:city":"Jasper",
    "sg:classifiers":[
        {
            "category":"Personal",
            "subcategory":"Beauty Salon",
            "type":"Services"
        }
    ],
    "sg:phone":"+1 770 893 6075",
    "sg:postcode":"30143",
    "sg:province":"GA",
    "wof:name":"Styles Are Us",
    "wof:placetype":"venue"
},
  "geometry": {"coordinates":[-84.388302,34.467541],"type":"Point"}
}