{
  "type": "Feature",
  "properties": {
    "addr:full":"805 Dawsonville Hwy Gainesville GA 30501",
    "addr:housenumber":"805",
    "addr:postcode":"30501",
    "addr:street":"Dawsonville Hwy",
    "iso:country":"US",
    "sg:address":"805 Dawsonville Hwy",
    "sg:city":"Gainesville",
    "sg:classifiers":[
        {
            "category":"Restaurant",
            "type":"Food & Drink"
        }
    ],
    "sg:menulink":"http://www.allmenus.com/ga/gainesville/207157-sonic/menu/",
    "sg:phone":"+1 770 532 7900",
    "sg:postcode":"30501",
    "sg:province":"GA",
    "sg:tags":[
        "burger",
        "american"
    ],
    "wof:name":"Sonic",
    "wof:placetype":"venue"
},
  "geometry": {"coordinates":[-83.835346,34.297032],"type":"Point"}
}