{
  "type": "Feature",
  "properties": {
    "addr:full":"5 Beech St Newnan GA 30263",
    "addr:housenumber":"5",
    "addr:postcode":"30263",
    "addr:street":"Beech St",
    "iso:country":"US",
    "sg:address":"5 Beech St",
    "sg:city":"Newnan",
    "sg:classifiers":[
        {
            "category":"Professional",
            "type":"Services"
        }
    ],
    "sg:phone":"+1 770 253 3231",
    "sg:postcode":"30263",
    "sg:province":"GA",
    "wof:name":"Rita Chapman",
    "wof:placetype":"venue"
},
  "geometry": {"coordinates":[-84.825399,33.388443],"type":"Point"}
}