{
  "type": "Feature",
  "properties": {
    "addr:full":"1444 Sam Nunn Blvd Perry GA 31069",
    "addr:housenumber":"1444",
    "addr:postcode":"31069",
    "addr:street":"Sam Nunn Blvd",
    "iso:country":"US",
    "sg:address":"1444 Sam Nunn Blvd",
    "sg:city":"Perry",
    "sg:classifiers":[
        {
            "category":"Professional",
            "subcategory":"Management & Consulting",
            "type":"Services"
        }
    ],
    "sg:phone":"+1 478 987 3717",
    "sg:postcode":"31069",
    "sg:province":"GA",
    "sg:tags":[
        "consultant",
        "timber",
        "tract"
    ],
    "wof:name":"Southern Timber Cons LLC",
    "wof:placetype":"venue"
},
  "geometry": {"coordinates":[-83.741586,32.469637],"type":"Point"}
}