{
  "type": "Feature",
  "properties": {
    "addr:full":"43 Jefferson Pkwy Newnan GA 30263",
    "addr:housenumber":"43",
    "addr:postcode":"30263",
    "addr:street":"Jefferson Pkwy",
    "iso:country":"US",
    "sg:address":"43 Jefferson Pkwy",
    "sg:city":"Newnan",
    "sg:classifiers":[
        {
            "category":"Professional",
            "subcategory":"Management & Consulting",
            "type":"Services"
        }
    ],
    "sg:phone":"+1 678 423 6660",
    "sg:postcode":"30263",
    "sg:province":"GA",
    "sg:tags":[
        "handling",
        "call",
        "business"
    ],
    "wof:name":"Excel Management Services Inc",
    "wof:placetype":"venue"
},
  "geometry": {"coordinates":[-84.768738,33.394553],"type":"Point"}
}