{
  "type": "Feature",
  "properties": {
    "iso:country":"US",
    "sg:address":"205 Pendleton Dr",
    "sg:city":"Athens",
    "sg:classifiers":[
        {
            "category":"Retail",
            "subcategory":"Portrait Studio",
            "type":"Services"
        }
    ],
    "sg:phone":"+1 706 353 3722",
    "sg:postcode":"30606",
    "sg:province":"GA",
    "sg:tags":[
        "photo"
    ],
    "wof:name":"Barbara Dickson Photography",
    "wof:placetype":"venue"
},
  "geometry": {"coordinates":[-83.42998799999999,33.974147],"type":"Point"}
}