{
  "type": "Feature",
  "properties": {
    "addr:full":"1406 Sweet Gum Rd Mc Rae GA 31055",
    "addr:housenumber":"1406",
    "addr:postcode":"31055",
    "addr:street":"Sweet Gum Rd;Rae",
    "iso:country":"US",
    "sg:address":"1406 Sweet Gum Rd",
    "sg:city":"Mc Rae",
    "sg:classifiers":[
        {
            "category":"Building & Trades",
            "subcategory":"Plumbing",
            "type":"Services"
        }
    ],
    "sg:phone":"+1 229 868 5005",
    "sg:postcode":"31055",
    "sg:province":"GA",
    "sg:tags":[
        "contractor"
    ],
    "wof:name":"Vinston Plumbing",
    "wof:placetype":"venue"
},
  "geometry": {"coordinates":[-82.912255,32.059421],"type":"Point"}
}