{
  "type": "Feature",
  "properties": {
    "iso:country":"US",
    "sg:address":"5351 Snapfinger Woods Dr",
    "sg:city":"Decatur",
    "sg:classifiers":[
        {
            "category":"Utilities",
            "subcategory":"Refuse",
            "type":"Services"
        }
    ],
    "sg:phone":"+1 770 593 9434",
    "sg:postcode":"30035",
    "sg:province":"GA",
    "sg:tags":[
        "dry",
        "recycles",
        "filter",
        "collect",
        "cleaning",
        "disposes"
    ],
    "sg:website":"www.mcfsystems.com",
    "wof:name":"MCF Systems Atlanta Inc",
    "wof:placetype":"venue"
},
  "geometry": {"coordinates":[-84.169712,33.709234],"type":"Point"}
}