{
  "type": "Feature",
  "properties": {
    "addr:full":"2385 Rayonier Rd Jesup GA 31545",
    "addr:housenumber":"2385",
    "addr:postcode":"31545",
    "addr:street":"Rayonier Rd",
    "iso:country":"US",
    "sg:address":"2385 Rayonier Rd",
    "sg:city":"Jesup",
    "sg:classifiers":[
        {
            "category":"Building & Trades",
            "subcategory":"Construction",
            "type":"Services"
        }
    ],
    "sg:phone":"+1 912 588 9795",
    "sg:postcode":"31545",
    "sg:province":"GA",
    "sg:tags":[
        "residential"
    ],
    "wof:name":"Woodcock Decorators",
    "wof:placetype":"venue"
},
  "geometry": {"coordinates":[-81.877724,31.66554],"type":"Point"}
}