{
  "type": "Feature",
  "properties": {
    "addr:full":"4125 Buford Hwy Duluth GA 30096",
    "addr:housenumber":"4125",
    "addr:postcode":"30096",
    "addr:street":"Buford Hwy",
    "iso:country":"US",
    "sg:address":"4125 Buford Hwy",
    "sg:city":"Duluth",
    "sg:classifiers":[
        {
            "category":"Wholesale",
            "subcategory":"Office Equipment",
            "type":"Manufacturing & Wholesale Goods"
        },
        {
            "category":"Shopping",
            "type":"Retail Goods"
        }
    ],
    "sg:phone":"+1 678 206 0381",
    "sg:postcode":"30096",
    "sg:province":"GA",
    "sg:tags":[
        "put",
        "vault",
        "safe",
        "to",
        "money"
    ],
    "wof:name":"Sungil America Inc",
    "wof:placetype":"venue"
},
  "geometry": {"coordinates":[-84.16703699999999,33.973998],"type":"Point"}
}