{
  "type": "Feature",
  "properties": {
    "addr:full":"1086 Clinton Rd Macon GA 31211",
    "addr:housenumber":"1086",
    "addr:postcode":"31211",
    "addr:street":"Clinton Rd",
    "iso:country":"US",
    "sg:address":"1086 Clinton Rd",
    "sg:city":"Macon",
    "sg:classifiers":[
        {
            "category":"Building & Trades",
            "subcategory":"Cleaning & Sanitation",
            "type":"Services"
        }
    ],
    "sg:phone":"+1 478 743 5844",
    "sg:postcode":"31211",
    "sg:province":"GA",
    "sg:tags":[
        "maintenance"
    ],
    "wof:name":"S & S Cleaning Service",
    "wof:placetype":"venue"
},
  "geometry": {"coordinates":[-83.62038099999999,32.852797],"type":"Point"}
}