{
  "type": "Feature",
  "properties": {
    "addr:full":"97 McKeown Rd Villa Rica GA 30180",
    "addr:housenumber":"97",
    "addr:postcode":"30180",
    "addr:street":"Mckeown Rd",
    "iso:country":"US",
    "sg:address":"97 McKeown Rd",
    "sg:city":"Villa Rica",
    "sg:classifiers":[
        {
            "category":"Restaurant",
            "type":"Food & Drink"
        }
    ],
    "sg:phone":"+1 770 459 3528",
    "sg:postcode":"30180",
    "sg:province":"GA",
    "wof:name":"Kibble Cafe",
    "wof:placetype":"venue"
},
  "geometry": {"coordinates":[-84.937454,33.795554],"type":"Point"}
}