{
  "type": "Feature",
  "properties": {
    "iso:country":"US",
    "sg:address":"885 Woodstock Rd",
    "sg:city":"Roswell",
    "sg:classifiers":[
        {
            "category":"Recreation",
            "type":"Entertainment"
        }
    ],
    "sg:phone":"+1 770 331 3881",
    "sg:postcode":"30075",
    "sg:province":"GA",
    "sg:tags":[
        "instruction",
        "golf"
    ],
    "wof:name":"Atlanta Golf Academy",
    "wof:placetype":"venue"
},
  "geometry": {"coordinates":[-84.391503,34.062613],"type":"Point"}
}