{
  "type": "Feature",
  "properties": {
    "addr:full":"114 Bryan St Mcdonough GA 30253",
    "addr:housenumber":"114",
    "addr:postcode":"30253",
    "addr:street":"Bryan St",
    "iso:country":"US",
    "sg:address":"114 Bryan St",
    "sg:city":"Mcdonough",
    "sg:classifiers":[
        {
            "category":"Real Estate",
            "subcategory":"Real Estate Agent",
            "type":"Services"
        }
    ],
    "sg:phone":"+1 678 432 7753",
    "sg:postcode":"30253",
    "sg:province":"GA",
    "wof:name":"Harry Norman Realtors",
    "wof:placetype":"venue"
},
  "geometry": {"coordinates":[-84.142815,33.444908],"type":"Point"}
}