{
  "type": "Feature",
  "properties": {
    "addr:full":"2325 Sebring Ct Marietta GA 30064",
    "addr:housenumber":"2325",
    "addr:postcode":"30064",
    "addr:street":"Sebring Ct",
    "iso:country":"US",
    "sg:address":"2325 Sebring Ct",
    "sg:city":"Marietta",
    "sg:classifiers":[
        {
            "category":"Building & Trades",
            "subcategory":"Electrical",
            "type":"Services"
        }
    ],
    "sg:phone":"+1 770 439 8556",
    "sg:postcode":"30064",
    "sg:province":"GA",
    "sg:tags":[
        "electrical",
        "contractor"
    ],
    "wof:name":"Seemore Elctronic Surveillance",
    "wof:placetype":"venue"
},
  "geometry": {"coordinates":[-84.616546,33.890676],"type":"Point"}
}