{
  "type": "Feature",
  "properties": {
    "addr:full":"2697 Sandy Plains Rd Marietta GA 30066",
    "addr:housenumber":"2697",
    "addr:postcode":"30066",
    "addr:street":"Sandy Plains Rd",
    "iso:country":"US",
    "sg:address":"2697 Sandy Plains Rd",
    "sg:city":"Marietta",
    "sg:phone":"+1 770 971 1355",
    "sg:postcode":"30066",
    "sg:province":"GA",
    "sg:website":"http://www.sandyplainschiro.com",
    "wof:name":"Sandy Plains Chiropractic",
    "wof:placetype":"venue"
},
  "geometry": {"coordinates":[-84.492555,34.016678],"type":"Point"}
}