{
  "type": "Feature",
  "properties": {
    "addr:full":"1836 S Boyd Dr Rocky Face GA 30740",
    "addr:housenumber":"1836",
    "addr:postcode":"30740",
    "addr:street":"S Boyd Dr",
    "iso:country":"US",
    "sg:address":"1836 S Boyd Dr",
    "sg:city":"Rocky Face",
    "sg:classifiers":[
        {
            "category":"Manufacturing",
            "subcategory":"Lumber",
            "type":"Manufacturing & Wholesale Goods"
        }
    ],
    "sg:phone":"+1 706 673 4632",
    "sg:postcode":"30740",
    "sg:province":"GA",
    "sg:tags":[
        "logging"
    ],
    "wof:name":"C L H Logging",
    "wof:placetype":"venue"
},
  "geometry": {"coordinates":[-85.044012,34.789287],"type":"Point"}
}