{
  "type": "Feature",
  "properties": {
    "iso:country":"US",
    "sg:address":"3829 Redan Rd",
    "sg:city":"Decatur",
    "sg:classifiers":[
        {
            "category":"Real Estate",
            "subcategory":"Real Estate Operator",
            "type":"Services"
        }
    ],
    "sg:phone":"+1 404 289 5638",
    "sg:postcode":"30032",
    "sg:province":"GA",
    "sg:tags":[
        "apartment"
    ],
    "wof:name":"Redan Village",
    "wof:placetype":"venue"
},
  "geometry": {"coordinates":[-84.235298,33.7617],"type":"Point"}
}