{
  "type": "Feature",
  "properties": {
    "iso:country":"US",
    "sg:address":"1512 Dupree Rd",
    "sg:city":"Woodstock",
    "sg:classifiers":[
        {
            "category":"Retail",
            "subcategory":"Repair Shop",
            "type":"Services"
        }
    ],
    "sg:phone":"+1 770 591 5838",
    "sg:postcode":"30189",
    "sg:province":"GA",
    "sg:tags":[
        "automotive",
        "equipment"
    ],
    "wof:name":"American Equipment Service",
    "wof:placetype":"venue"
},
  "geometry": {"coordinates":[-84.545182,34.092345],"type":"Point"}
}