{
  "type": "Feature",
  "properties": {
    "addr:full":"1199 Crestbrook Ln Mableton GA 30126",
    "addr:housenumber":"1199",
    "addr:postcode":"30126",
    "addr:street":"Crestbrook Ln",
    "iso:country":"US",
    "sg:address":"1199 Crestbrook Ln",
    "sg:city":"Mableton",
    "sg:classifiers":[
        {
            "category":"Professional",
            "type":"Services"
        }
    ],
    "sg:phone":"+1 770 420 0835",
    "sg:postcode":"30126",
    "sg:province":"GA",
    "sg:tags":[
        "establishment"
    ],
    "wof:name":"Att Cits",
    "wof:placetype":"venue"
},
  "geometry": {"coordinates":[-84.588369,33.835972],"type":"Point"}
}