{
  "type": "Feature",
  "properties": {
    "iso:country":"US",
    "sg:address":"1950 Spectrum Cir",
    "sg:city":"Marietta",
    "sg:classifiers":[
        {
            "category":"Professional",
            "subcategory":"Management & Consulting",
            "type":"Services"
        }
    ],
    "sg:phone":"+1 770 857 2298",
    "sg:postcode":"30067",
    "sg:province":"GA",
    "sg:tags":[
        "consultant",
        "business"
    ],
    "wof:name":"First Preston Management",
    "wof:placetype":"venue"
},
  "geometry": {"coordinates":[-84.468422,33.905372],"type":"Point"}
}