{
  "type": "Feature",
  "properties": {
    "addr:full":"5570 Lawrenceville Hwy NW Ste F Lilburn GA 30047",
    "addr:housenumber":"5570",
    "addr:postcode":"30047",
    "addr:street":"Lawrenceville Hwy Nw Ste F",
    "iso:country":"US",
    "sg:address":"5570 Lawrenceville Hwy NW Ste F",
    "sg:city":"Lilburn",
    "sg:classifiers":[
        {
            "category":"Shopping",
            "subcategory":"Books",
            "type":"Retail Goods"
        }
    ],
    "sg:phone":"+1 770 925 0580",
    "sg:postcode":"30047",
    "sg:province":"GA",
    "sg:tags":[
        "bookstore"
    ],
    "wof:name":"Priscilla's Christian Book Store",
    "wof:placetype":"venue"
},
  "geometry": {"coordinates":[-84.16269699999999,33.882301],"type":"Point"}
}