{
  "type": "Feature",
  "properties": {
    "iso:country":"US",
    "sg:address":"601 Woodwalk Ln",
    "sg:city":"Augusta",
    "sg:classifiers":[
        {
            "category":"Organizations",
            "subcategory":"Membership Organization",
            "type":"Services"
        }
    ],
    "sg:phone":"+1 706 855 1485",
    "sg:postcode":"30907",
    "sg:province":"GA",
    "wof:name":"Cedars Assn Inc",
    "wof:placetype":"venue"
},
  "geometry": {"coordinates":[-82.049588,33.538643],"type":"Point"}
}