{
  "type": "Feature",
  "properties": {
    "addr:full":"101 Wexford Cir Bonaire GA 31005",
    "addr:housenumber":"101",
    "addr:postcode":"31005",
    "addr:street":"Wexford Cir",
    "iso:country":"US",
    "sg:address":"101 Wexford Cir",
    "sg:city":"Bonaire",
    "sg:classifiers":[
        {
            "category":"Building & Trades",
            "subcategory":"Construction",
            "type":"Services"
        }
    ],
    "sg:phone":"+1 478 929 9674",
    "sg:postcode":"31005",
    "sg:province":"GA",
    "sg:tags":[
        "house"
    ],
    "wof:name":"S&K Homebuilders Inc",
    "wof:placetype":"venue"
},
  "geometry": {"coordinates":[-83.60621500000001,32.563524],"type":"Point"}
}