{
  "type": "Feature",
  "properties": {
    "addr:full":"3938 Willowood Rd Augusta GA 30907",
    "addr:housenumber":"3938",
    "addr:postcode":"30907",
    "addr:street":"Willowood Rd",
    "iso:country":"US",
    "sg:address":"3938 Willowood Rd",
    "sg:city":"Augusta",
    "sg:classifiers":[
        {
            "category":"Professional",
            "type":"Services"
        }
    ],
    "sg:phone":"+1 706 868 8967",
    "sg:postcode":"30907",
    "sg:province":"GA",
    "wof:name":"Rykken Aceves 6roup",
    "wof:placetype":"venue"
},
  "geometry": {"coordinates":[-82.09649400000001,33.497256],"type":"Point"}
}