{
  "type": "Feature",
  "properties": {
    "addr:full":"605 Inman Rd Ste B Fayetteville GA 30215",
    "addr:housenumber":"605",
    "addr:postcode":"30215",
    "addr:street":"Inman Rd Ste B",
    "iso:country":"US",
    "sg:address":"605 Inman Rd Ste B",
    "sg:city":"Fayetteville",
    "sg:classifiers":[
        {
            "category":"Professional",
            "subcategory":"Engineering",
            "type":"Services"
        }
    ],
    "sg:phone":"+1 770 460 5032",
    "sg:postcode":"30215",
    "sg:province":"GA",
    "sg:tags":[
        "consulting",
        "engineer"
    ],
    "wof:name":"Aaa Consulting, Incorporated",
    "wof:placetype":"venue"
},
  "geometry": {"coordinates":[-84.41597299999999,33.395147],"type":"Point"}
}