{
  "type": "Feature",
  "properties": {
    "iso:country":"US",
    "sg:address":"5600 Milgen Rd",
    "sg:city":"Columbus",
    "sg:classifiers":[
        {
            "category":"Personal",
            "subcategory":"Beauty Salon",
            "type":"Services"
        }
    ],
    "sg:phone":"+1 706 561 1485",
    "sg:postcode":"31907",
    "sg:province":"GA",
    "sg:tags":[
        "shop",
        "barber"
    ],
    "wof:name":"Casual Cuts Inc",
    "wof:placetype":"venue"
},
  "geometry": {"coordinates":[-84.88757099999999,32.52552],"type":"Point"}
}