{
  "type": "Feature",
  "properties": {
    "iso:country":"US",
    "sg:address":"211 Perimeter Center Pkwy Ste 200",
    "sg:city":"Atlanta",
    "sg:classifiers":[
        {
            "category":"Education",
            "subcategory":"Special Training",
            "type":"Public Place"
        },
        {
            "category":"Wholesale",
            "subcategory":"Computers",
            "type":"Manufacturing & Wholesale Goods"
        }
    ],
    "sg:phone":"+1 770 270 2000",
    "sg:postcode":"30346",
    "sg:province":"GA",
    "sg:tags":[
        "school",
        "specialty",
        "adult"
    ],
    "sg:website":"www.nhgeorgia.com",
    "wof:name":"New Horizons Computer Learning Centers",
    "wof:placetype":"venue"
},
  "geometry": {"coordinates":[-84.344672,33.925945],"type":"Point"}
}