{
  "type": "Feature",
  "properties": {
    "addr:full":"485 W Huntington Rd Athens GA 30606",
    "addr:housenumber":"485",
    "addr:postcode":"30606",
    "addr:street":"W Huntington Rd",
    "iso:country":"US",
    "sg:address":"485 W Huntington Rd",
    "sg:city":"Athens",
    "sg:classifiers":[
        {
            "category":"Personal",
            "type":"Services"
        }
    ],
    "sg:phone":"+1 706 338 3833",
    "sg:postcode":"30606",
    "sg:province":"GA",
    "sg:tags":[
        "therapist",
        "massage"
    ],
    "wof:name":"Professional Massage Therapy",
    "wof:placetype":"venue"
},
  "geometry": {"coordinates":[-83.46369799999999,33.948126],"type":"Point"}
}