{
  "type": "Feature",
  "properties": {
    "iso:country":"US",
    "sg:address":"3360 Osborne Road NE",
    "sg:city":"Atlanta",
    "sg:classifiers":[
        {
            "category":"Park",
            "type":"Public Place"
        },
        {
            "category":"Sports & Exercise",
            "subcategory":"Sports Center",
            "type":"Entertainment"
        }
    ],
    "sg:phone":"+1 404 303 2100",
    "sg:postcode":"30319",
    "sg:province":"GA",
    "sg:tags":[
        "amateur",
        "team"
    ],
    "wof:name":"Dekalb County Government",
    "wof:placetype":"venue"
},
  "geometry": {"coordinates":[-84.34436700000001,33.887758],"type":"Point"}
}