{
  "type": "Feature",
  "properties": {
    "addr:full":"463 State Rte 314 Fayetteville GA 30214",
    "addr:housenumber":"463",
    "addr:postcode":"30214",
    "addr:street":"State Rte 314",
    "iso:country":"US",
    "sg:address":"463 State Rte 314",
    "sg:city":"Fayetteville",
    "sg:classifiers":[
        {
            "category":"Retail",
            "subcategory":"Repair Shop",
            "type":"Services"
        }
    ],
    "sg:phone":"+1 678 817 9856",
    "sg:postcode":"30214",
    "sg:province":"GA",
    "wof:name":"P & L Cleaning",
    "wof:placetype":"venue"
},
  "geometry": {"coordinates":[-84.449679,33.488934],"type":"Point"}
}