{
  "type": "Feature",
  "properties": {
    "addr:full":"206 E Lamar St Americus GA 31709",
    "addr:housenumber":"206",
    "addr:postcode":"31709",
    "addr:street":"E Lamar St",
    "iso:country":"US",
    "sg:address":"206 E Lamar St",
    "sg:city":"Americus",
    "sg:classifiers":[
        {
            "category":"Health Services",
            "subcategory":"Doctor",
            "type":"Services"
        }
    ],
    "sg:phone":"+1 229 924 6648",
    "sg:postcode":"31709",
    "sg:province":"GA",
    "sg:tags":[
        "physician",
        "surgeon",
        "surgeons",
        "psychiatry"
    ],
    "wof:name":"Mila S Keh Md",
    "wof:placetype":"venue"
},
  "geometry": {"coordinates":[-84.229523,32.071999],"type":"Point"}
}