{
  "type": "Feature",
  "properties": {
    "iso:country":"US",
    "sg:address":"1750 Marietta Hwy",
    "sg:city":"Canton",
    "sg:classifiers":[
        {
            "category":"Retail",
            "subcategory":"Laundry & Dry Cleaning",
            "type":"Services"
        }
    ],
    "sg:phone":"+1 678 493 0767",
    "sg:postcode":"30114",
    "sg:province":"GA",
    "sg:tags":[
        "cleaners"
    ],
    "wof:name":"Mr Cleaners",
    "wof:placetype":"venue"
},
  "geometry": {"coordinates":[-84.506435,34.221287],"type":"Point"}
}