{
  "type": "Feature",
  "properties": {
    "addr:full":"113 Broad St Manchester GA 31830",
    "addr:housenumber":"113",
    "addr:postcode":"31830",
    "addr:street":"Broad St",
    "iso:country":"US",
    "sg:address":"113 Broad St",
    "sg:city":"Manchester",
    "sg:classifiers":[
        {
            "category":"Autos & Motor Vehicles",
            "subcategory":"Automobile Sales",
            "type":"Retail Goods"
        }
    ],
    "sg:phone":"+1 706 846 2157",
    "sg:postcode":"31830",
    "sg:province":"GA",
    "sg:tags":[
        "used"
    ],
    "wof:name":"Economy Used Cars",
    "wof:placetype":"venue"
},
  "geometry": {"coordinates":[-84.678884,32.890969],"type":"Point"}
}