{
  "type": "Feature",
  "properties": {
    "iso:country":"US",
    "sg:address":"1113 Creekdale Dr",
    "sg:city":"Clarkston",
    "sg:classifiers":[
        {
            "category":"Professional",
            "subcategory":"Management & Consulting",
            "type":"Services"
        }
    ],
    "sg:phone":"+1 404 423 3349",
    "sg:postcode":"30021",
    "sg:province":"GA",
    "wof:name":"Hatchet Man Presents",
    "wof:placetype":"venue"
},
  "geometry": {"coordinates":[-84.254294,33.811366],"type":"Point"}
}