{
  "type": "Feature",
  "properties": {
    "iso:country":"US",
    "sg:address":"2971 Flowers Rd S",
    "sg:city":"Atlanta",
    "sg:classifiers":[
        {
            "category":"Professional",
            "subcategory":"Management & Consulting",
            "type":"Services"
        },
        {
            "category":"Banks & Credit Unions",
            "subcategory":"Financial Services",
            "type":"Services"
        }
    ],
    "sg:phone":"+1 770 458 8947",
    "sg:postcode":"30341",
    "sg:province":"GA",
    "sg:tags":[
        "consultant",
        "financing",
        "planning"
    ],
    "wof:name":"Carney Tom",
    "wof:placetype":"venue"
},
  "geometry": {"coordinates":[-84.26697,33.870912],"type":"Point"}
}