{
  "type": "Feature",
  "properties": {
    "iso:country":"US",
    "sg:address":"4488 N Shallowford Rd",
    "sg:city":"Atlanta",
    "sg:classifiers":[
        {
            "category":"Social Services",
            "subcategory":"Job Training",
            "type":"Services"
        }
    ],
    "sg:phone":"+1 770 396 1510",
    "sg:postcode":"30338",
    "sg:province":"GA",
    "sg:tags":[
        "rehabilitation"
    ],
    "wof:name":"Nova Care",
    "wof:placetype":"venue"
},
  "geometry": {"coordinates":[-84.30808399999999,33.924892],"type":"Point"}
}