{
  "type": "Feature",
  "properties": {
    "addr:full":"240 Ponce De Leon Ave NE Atlanta GA 30309",
    "addr:housenumber":"240",
    "addr:postcode":"30309",
    "addr:street":"Ponce De Leon Ave Ne",
    "iso:country":"US",
    "sg:address":"240 Ponce De Leon Ave NE",
    "sg:city":"Atlanta",
    "sg:classifiers":[
        {
            "category":"Sports & Exercise",
            "subcategory":"Gym",
            "type":"Entertainment"
        },
        {
            "category":"Arena",
            "subcategory":"Sports Club",
            "type":"Entertainment"
        }
    ],
    "sg:phone":"+1 404 745 3019",
    "sg:postcode":"30309",
    "sg:province":"GA",
    "sg:tags":[
        "trainer",
        "martial art"
    ],
    "sg:website":"www.unit2fitness.com",
    "wof:name":"Unit 2 Fitness",
    "wof:placetype":"venue"
},
  "geometry": {"coordinates":[-84.379356,33.772976],"type":"Point"}
}