{
  "type": "Feature",
  "properties": {
    "addr:full":"5378 Goose Creek Way Norcross GA 30092",
    "addr:housenumber":"5378",
    "addr:postcode":"30092",
    "addr:street":"Goose Creek Way",
    "iso:country":"US",
    "sg:address":"5378 Goose Creek Way",
    "sg:city":"Norcross",
    "sg:classifiers":[
        {
            "category":"Professional",
            "type":"Services"
        },
        {
            "category":"Professional",
            "subcategory":"Management & Consulting",
            "type":"Services"
        }
    ],
    "sg:phone":"+1 770 449 9079",
    "sg:postcode":"30092",
    "sg:province":"GA",
    "sg:tags":[
        "establishment"
    ],
    "wof:name":"Kinney Group",
    "wof:placetype":"venue"
},
  "geometry": {"coordinates":[-84.235691,33.99563],"type":"Point"}
}