{
  "type": "Feature",
  "properties": {
    "iso:country":"US",
    "sg:address":"6154 Atlantic Blvd",
    "sg:city":"Norcross",
    "sg:classifiers":[
        {
            "category":"Professional",
            "subcategory":"Employment Agencies",
            "type":"Services"
        }
    ],
    "sg:phone":"+1 770 447 1972",
    "sg:postcode":"30071",
    "sg:province":"GA",
    "sg:website":"www.staffmark.com",
    "wof:name":"Staffmark",
    "wof:placetype":"venue"
},
  "geometry": {"coordinates":[-84.230407,33.942548],"type":"Point"}
}