{
  "type": "Feature",
  "properties": {
    "addr:full":"311 Jesse Jewell Pkwy SW Gainesville GA 30501",
    "addr:housenumber":"311",
    "addr:postcode":"30501",
    "addr:street":"Jesse Jewell Pkwy Sw",
    "iso:country":"US",
    "sg:address":"311 Jesse Jewell Pkwy SW",
    "sg:city":"Gainesville",
    "sg:classifiers":[
        {
            "category":"Restaurant",
            "type":"Food & Drink"
        }
    ],
    "sg:phone":"+1 770 536 9177",
    "sg:postcode":"30501",
    "sg:province":"GA",
    "sg:tags":[
        "american"
    ],
    "sg:website":"http://www.wildwingcafe.com",
    "wof:name":"Wild Wing Cafe",
    "wof:placetype":"venue"
},
  "geometry": {"coordinates":[-83.82818399999999,34.296031],"type":"Point"}
}