{
  "type": "Feature",
  "properties": {
    "addr:full":"4768 Melborne Trl Flowery Branch GA 30542",
    "addr:housenumber":"4768",
    "addr:postcode":"30542",
    "addr:street":"Melborne Trl",
    "iso:country":"US",
    "sg:address":"4768 Melborne Trl",
    "sg:city":"Flowery Branch",
    "sg:classifiers":[
        {
            "category":"Building & Trades",
            "subcategory":"Construction",
            "type":"Services"
        }
    ],
    "sg:phone":"+1 770 965 3135",
    "sg:postcode":"30542",
    "sg:province":"GA",
    "sg:tags":[
        "hanging",
        "contractor"
    ],
    "wof:name":"Bailey Improvements",
    "wof:placetype":"venue"
},
  "geometry": {"coordinates":[-83.894965,34.175832],"type":"Point"}
}