{
  "type": "Feature",
  "properties": {
    "addr:full":"1700 Cumberland Point Dr SE Marietta GA 30067",
    "addr:housenumber":"1700",
    "addr:postcode":"30067",
    "addr:street":"Cumberland Point Dr Se",
    "iso:country":"US",
    "sg:address":"1700 Cumberland Point Dr SE",
    "sg:city":"Marietta",
    "sg:classifiers":[
        {
            "category":"Health Services",
            "subcategory":"Clinic",
            "type":"Services"
        }
    ],
    "sg:phone":"+1 770 612 8264",
    "sg:postcode":"30067",
    "sg:province":"GA",
    "sg:tags":[
        "information",
        "alcoholism",
        "treatment"
    ],
    "wof:name":"Addiction Solutions Methadone Treatment",
    "wof:placetype":"venue"
},
  "geometry": {"coordinates":[-84.492779,33.911392],"type":"Point"}
}