{
  "type": "Feature",
  "properties": {
    "addr:full":"8891 Bright Star Rd Douglasville GA 30134",
    "addr:housenumber":"8891",
    "addr:postcode":"30134",
    "addr:street":"Bright Star Rd",
    "iso:country":"US",
    "sg:address":"8891 Bright Star Rd",
    "sg:city":"Douglasville",
    "sg:classifiers":[
        {
            "category":"Wholesale",
            "subcategory":"Vending Machines",
            "type":"Manufacturing & Wholesale Goods"
        }
    ],
    "sg:phone":"+1 770 942 0238",
    "sg:postcode":"30134",
    "sg:province":"GA",
    "wof:name":"Willis Quick Snax",
    "wof:placetype":"venue"
},
  "geometry": {"coordinates":[-84.777916,33.742551],"type":"Point"}
}