{
  "type": "Feature",
  "properties": {
    "iso:country":"US",
    "sg:address":"11 Red Fox Trl",
    "sg:city":"Euharlee",
    "sg:classifiers":[
        {
            "category":"Building & Trades",
            "subcategory":"Construction",
            "type":"Services"
        }
    ],
    "sg:phone":"+1 404 557 8964",
    "sg:postcode":"30145",
    "sg:province":"GA",
    "sg:tags":[
        "contractor"
    ],
    "wof:name":"Elite General Contracting",
    "wof:placetype":"venue"
},
  "geometry": {"coordinates":[-84.93450900000001,34.151181],"type":"Point"}
}