{
  "type": "Feature",
  "properties": {
    "addr:full":"1568 Willingham Dr Atlanta GA 30344",
    "addr:housenumber":"1568",
    "addr:postcode":"30344",
    "addr:street":"Willingham Dr",
    "iso:country":"US",
    "sg:address":"1568 Willingham Dr",
    "sg:city":"Atlanta",
    "sg:classifiers":[
        {
            "category":"Social Services",
            "type":"Services"
        }
    ],
    "sg:phone":"+1 404 559 4909",
    "sg:postcode":"30344",
    "sg:province":"GA",
    "sg:tags":[
        "probation"
    ],
    "wof:name":"South Fulton Parole Office",
    "wof:placetype":"venue"
},
  "geometry": {"coordinates":[-84.439999,33.669082],"type":"Point"}
}