{
  "type": "Feature",
  "properties": {
    "iso:country":"US",
    "sg:address":"408 N White St Rm 601",
    "sg:city":"Carrollton",
    "sg:classifiers":[
        {
            "category":"Organizations",
            "subcategory":"Membership Organization",
            "type":"Services"
        }
    ],
    "sg:phone":"+1 770 832 8942",
    "sg:postcode":"30117",
    "sg:province":"GA",
    "sg:tags":[
        "military",
        "veteran"
    ],
    "wof:name":"Georgia Department Of Veterans Service",
    "wof:placetype":"venue"
},
  "geometry": {"coordinates":[-85.07096,33.58345],"type":"Point"}
}