{
  "type": "Feature",
  "properties": {
    "iso:country":"US",
    "sg:address":"4921 Rockwood Dr",
    "sg:city":"Marietta",
    "sg:classifiers":[
        {
            "category":"Real Estate",
            "subcategory":"Real Estate Operator",
            "type":"Services"
        }
    ],
    "sg:phone":"+1 770 926 5154",
    "sg:postcode":"30066",
    "sg:province":"GA",
    "sg:tags":[
        "building",
        "nonresidential"
    ],
    "wof:name":"Chm Properties LLC",
    "wof:placetype":"venue"
},
  "geometry": {"coordinates":[-84.513583,34.071338],"type":"Point"}
}