{
  "type": "Feature",
  "properties": {
    "addr:full":"221 S Broad St Monroe GA 30655",
    "addr:housenumber":"221",
    "addr:postcode":"30655",
    "addr:street":"S Broad St",
    "iso:country":"US",
    "sg:address":"221 S Broad St",
    "sg:city":"Monroe",
    "sg:classifiers":[
        {
            "category":"Banks & Credit Unions",
            "subcategory":"Bank",
            "type":"Services"
        },
        {
            "category":"Banks & Credit Unions",
            "subcategory":"Financial Services",
            "type":"Services"
        }
    ],
    "sg:phone":"+1 770 207 1000",
    "sg:postcode":"30655",
    "sg:province":"GA",
    "sg:tags":[
        "commercial",
        "loan",
        "saving",
        "mortgage"
    ],
    "sg:website":"https://www.wachovia.com/?DCMP=KNL-CPS-DS-Directory-0703&HBX_PK=Banks&HBX_OU=71",
    "wof:name":"Wachovia Bank",
    "wof:placetype":"venue"
},
  "geometry": {"coordinates":[-83.712931,33.793245],"type":"Point"}
}