{
  "type": "Feature",
  "properties": {
    "iso:country":"US",
    "sg:address":"587 Main St",
    "sg:city":"Palmetto",
    "sg:classifiers":[
        {
            "category":"Professional",
            "subcategory":"Lawyer & Legal Services",
            "type":"Services"
        }
    ],
    "sg:phone":"+1 770 463 8700",
    "sg:postcode":"30268",
    "sg:province":"GA",
    "wof:name":"Kalish & Associates PC",
    "wof:placetype":"venue"
},
  "geometry": {"coordinates":[-84.670906,33.509791],"type":"Point"}
}