{
  "type": "Feature",
  "properties": {
    "addr:full":"3211 Oakcliff Industrial St Atlanta GA 30340",
    "addr:housenumber":"3211",
    "addr:postcode":"30340",
    "addr:street":"Oakcliff Industrial St",
    "iso:country":"US",
    "sg:address":"3211 Oakcliff Industrial St",
    "sg:city":"Atlanta",
    "sg:classifiers":[
        {
            "category":"Professional",
            "type":"Services"
        },
        {
            "category":"Wholesale",
            "subcategory":"Non-durable Goods",
            "type":"Manufacturing & Wholesale Goods"
        }
    ],
    "sg:phone":"+1 770 454 7622",
    "sg:postcode":"30340",
    "sg:province":"GA",
    "sg:tags":[
        "hair",
        "merchandise",
        "general"
    ],
    "wof:name":"Aura Enterprises Inc",
    "wof:placetype":"venue"
},
  "geometry": {"coordinates":[-84.254638,33.901176],"type":"Point"}
}