{
  "type": "Feature",
  "properties": {
    "iso:country":"US",
    "sg:address":"7001 Concourse Pkwy",
    "sg:city":"Douglasville",
    "sg:classifiers":[
        {
            "category":"Professional",
            "subcategory":"Art Services",
            "type":"Services"
        }
    ],
    "sg:phone":"+1 770 947 6010",
    "sg:postcode":"30134",
    "sg:province":"GA",
    "sg:tags":[
        "photographers-portrait"
    ],
    "wof:name":"Picture Me Portrait Studios",
    "wof:placetype":"venue"
},
  "geometry": {"coordinates":[-84.758742,33.730146],"type":"Point"}
}