{
  "type": "Feature",
  "properties": {
    "iso:country":"US",
    "sg:address":"4994 Lower Roswell Rd",
    "sg:city":"Marietta",
    "sg:classifiers":[
        {
            "category":"Insurance",
            "subcategory":"Insurance Agent",
            "type":"Services"
        }
    ],
    "sg:phone":"+1 770 971 9814",
    "sg:postcode":"30068",
    "sg:province":"GA",
    "wof:name":"Allstate Insurance",
    "wof:placetype":"venue"
},
  "geometry": {"coordinates":[-84.404932,33.966504],"type":"Point"}
}