{
  "type": "Feature",
  "properties": {
    "iso:country":"US",
    "sg:address":"125 Braided Blanket Bluff",
    "sg:city":"Alpharetta",
    "sg:classifiers":[
        {
            "category":"Building & Trades",
            "subcategory":"Construction",
            "type":"Services"
        }
    ],
    "sg:phone":"+1 770 318 1651",
    "sg:postcode":"30022",
    "sg:province":"GA",
    "sg:tags":[
        "hanging",
        "contractor"
    ],
    "wof:name":"Mr Painter Construction",
    "wof:placetype":"venue"
},
  "geometry": {"coordinates":[-84.230389,34.050131],"type":"Point"}
}