{
  "type": "Feature",
  "properties": {
    "addr:full":"2019 Linnhurst Dr Savannah GA 31404",
    "addr:housenumber":"2019",
    "addr:postcode":"31404",
    "addr:street":"Linnhurst Dr",
    "iso:country":"US",
    "sg:address":"2019 Linnhurst Dr",
    "sg:city":"Savannah",
    "sg:classifiers":[
        {
            "category":"Insurance",
            "subcategory":"Insurance Agent",
            "type":"Services"
        }
    ],
    "sg:phone":"+1 912 355 5454",
    "sg:postcode":"31404",
    "sg:province":"GA",
    "sg:website":"www.greggmillerinsurance.com",
    "wof:name":"Freddie M Miller Insurance Inc",
    "wof:placetype":"venue"
},
  "geometry": {"coordinates":[-81.06779400000001,32.034942],"type":"Point"}
}