{
  "type": "Feature",
  "properties": {
    "addr:full":"5570 Windward Pkwy Alpharetta GA 30004",
    "addr:housenumber":"5570",
    "addr:postcode":"30004",
    "addr:street":"Windward Pkwy",
    "iso:country":"US",
    "sg:address":"5570 Windward Pkwy",
    "sg:city":"Alpharetta",
    "sg:classifiers":[
        {
            "category":"Banks & Credit Unions",
            "subcategory":"Bank",
            "type":"Services"
        }
    ],
    "sg:phone":"+1 678 624 1940",
    "sg:postcode":"30004",
    "sg:province":"GA",
    "wof:name":"Wachovia Bank",
    "wof:placetype":"venue"
},
  "geometry": {"coordinates":[-84.270706,34.088153],"type":"Point"}
}