{
  "type": "Feature",
  "properties": {
    "iso:country":"US",
    "sg:address":"1572 Cumming Hwy",
    "sg:city":"Sugar Hill",
    "sg:classifiers":[
        {
            "category":"Building & Trades",
            "subcategory":"Locksmith",
            "type":"Services"
        }
    ],
    "sg:phone":"+1 404 789 2683",
    "sg:postcode":"30518",
    "sg:province":"GA",
    "sg:tags":[
        "key"
    ],
    "wof:name":"Albert Locksmith",
    "wof:placetype":"venue"
},
  "geometry": {"coordinates":[-84.04073099999999,34.111301],"type":"Point"}
}