{
  "type": "Feature",
  "properties": {
    "addr:full":"100 Pine Lake Dr Cumming GA 30040",
    "addr:housenumber":"100",
    "addr:postcode":"30040",
    "addr:street":"Pine Lake Dr",
    "iso:country":"US",
    "sg:address":"100 Pine Lake Dr",
    "sg:city":"Cumming",
    "sg:classifiers":[
        {
            "category":"Professional",
            "subcategory":"Accounting & Tax Preparation",
            "type":"Services"
        }
    ],
    "sg:phone":"+1 770 205 1479",
    "sg:postcode":"30040",
    "sg:province":"GA",
    "sg:tags":[
        "accountant"
    ],
    "wof:name":"William Shell CPA",
    "wof:placetype":"venue"
},
  "geometry": {"coordinates":[-84.169906,34.22161],"type":"Point"}
}