{
  "type": "Feature",
  "properties": {
    "iso:country":"US",
    "sg:address":"200 Northspring Ct",
    "sg:city":"Warner Robins",
    "sg:classifiers":[
        {
            "category":"Health Services",
            "subcategory":"Nursing And Care Facility",
            "type":"Services"
        }
    ],
    "sg:phone":"+1 478 923 1065",
    "sg:postcode":"31093",
    "sg:province":"GA",
    "sg:tags":[
        "skilled"
    ],
    "wof:name":"Houston Cty of Mntl",
    "wof:placetype":"venue"
},
  "geometry": {"coordinates":[-83.634713,32.649389],"type":"Point"}
}