{
  "type": "Feature",
  "properties": {
    "addr:full":"2918 Veterans Pkwy Columbus GA 31904",
    "addr:housenumber":"2918",
    "addr:postcode":"31904",
    "addr:street":"Veterans Pkwy",
    "iso:country":"US",
    "sg:address":"2918 Veterans Pkwy",
    "sg:city":"Columbus",
    "sg:classifiers":[
        {
            "category":"Building & Trades",
            "subcategory":"Construction",
            "type":"Services"
        }
    ],
    "sg:phone":"+1 706 322 9600",
    "sg:postcode":"31904",
    "sg:province":"GA",
    "sg:tags":[
        "home",
        "builder"
    ],
    "wof:name":"Hinton Construction",
    "wof:placetype":"venue"
},
  "geometry": {"coordinates":[-84.98299400000001,32.491387],"type":"Point"}
}