{
  "type": "Feature",
  "properties": {
    "addr:full":"2152 Northwest Pkwy SE Ste G Marietta GA 30067",
    "addr:housenumber":"2152",
    "addr:postcode":"30067",
    "addr:street":"Northwest Pkwy Se Ste G",
    "iso:country":"US",
    "sg:address":"2152 Northwest Pkwy SE Ste G",
    "sg:city":"Marietta",
    "sg:classifiers":[
        {
            "category":"Building & Trades",
            "subcategory":"Construction",
            "type":"Services"
        }
    ],
    "sg:phone":"+1 770 792 8628",
    "sg:postcode":"30067",
    "sg:province":"GA",
    "sg:tags":[
        "contractor"
    ],
    "sg:website":"www.constructorgeneral.com",
    "wof:name":"Constructor General Inc",
    "wof:placetype":"venue"
},
  "geometry": {"coordinates":[-84.492203,33.918499],"type":"Point"}
}