{
  "type": "Feature",
  "properties": {
    "addr:full":"602 N Poplar St Butler GA 31006",
    "addr:housenumber":"602",
    "addr:postcode":"31006",
    "addr:street":"N Poplar St",
    "iso:country":"US",
    "sg:address":"602 N Poplar St",
    "sg:city":"Butler",
    "sg:classifiers":[
        {
            "category":"Autos & Motor Vehicles",
            "subcategory":"Automobile Sales",
            "type":"Retail Goods"
        }
    ],
    "sg:phone":"+1 478 862 2588",
    "sg:postcode":"31006",
    "sg:province":"GA",
    "sg:tags":[
        "truck"
    ],
    "wof:name":"Barrow Trucks & More",
    "wof:placetype":"venue"
},
  "geometry": {"coordinates":[-84.23970799999999,32.569085],"type":"Point"}
}