{
  "type": "Feature",
  "properties": {
    "iso:country":"US",
    "sg:address":"3701 Pio Nono Ave",
    "sg:city":"Macon",
    "sg:classifiers":[
        {
            "category":"Food & Beverages",
            "subcategory":"Groceries & Convenience Stores",
            "type":"Retail Goods"
        }
    ],
    "sg:phone":"+1 478 788 0856",
    "sg:postcode":"31206",
    "sg:province":"GA",
    "wof:name":"Express Foods",
    "wof:placetype":"venue"
},
  "geometry": {"coordinates":[-83.667227,32.795784],"type":"Point"}
}