{
  "type": "Feature",
  "properties": {
    "iso:country":"US",
    "sg:address":"319 Mcdonough Blvd SE",
    "sg:city":"Atlanta",
    "sg:classifiers":[
        {
            "category":"Building & Trades",
            "subcategory":"Cleaning & Sanitation",
            "type":"Services"
        },
        {
            "category":"Building & Trades",
            "subcategory":"Construction",
            "type":"Services"
        }
    ],
    "sg:phone":"+1 404 622 1397",
    "sg:postcode":"30315",
    "sg:province":"GA",
    "sg:tags":[
        "home",
        "repair",
        "maintenance",
        "house"
    ],
    "wof:name":"National Container Of Atlanta",
    "wof:placetype":"venue"
},
  "geometry": {"coordinates":[-84.377419,33.716325],"type":"Point"}
}