{
  "type": "Feature",
  "properties": {
    "iso:country":"US",
    "sg:address":"800 E Dykes St",
    "sg:city":"Cochran",
    "sg:classifiers":[
        {
            "category":"Recreation",
            "type":"Entertainment"
        }
    ],
    "sg:phone":"+1 478 934 3225",
    "sg:postcode":"31014",
    "sg:province":"GA",
    "sg:tags":[
        "parks"
    ],
    "wof:name":"Cochran Recreation Dept",
    "wof:placetype":"venue"
},
  "geometry": {"coordinates":[-83.34656099999999,32.393516],"type":"Point"}
}