{
  "type": "Feature",
  "properties": {
    "iso:country":"US",
    "sg:address":"5117 Memorial Dr",
    "sg:city":"Decatur",
    "sg:classifiers":[
        {
            "category":"Building & Trades",
            "subcategory":"Locksmith",
            "type":"Services"
        }
    ],
    "sg:phone":"+1 404 486 2992",
    "sg:postcode":"30030",
    "sg:province":"GA",
    "sg:tags":[
        "key"
    ],
    "wof:name":"A A Wright Locksmith",
    "wof:placetype":"venue"
},
  "geometry": {"coordinates":[-84.226176,33.794821],"type":"Point"}
}