{
  "type": "Feature",
  "properties": {
    "iso:country":"US",
    "sg:address":"118 Barry St",
    "sg:city":"Decatur",
    "sg:classifiers":[
        {
            "category":"Building & Trades",
            "subcategory":"Construction",
            "type":"Services"
        }
    ],
    "sg:phone":"+1 404 378 3885",
    "sg:postcode":"30030",
    "sg:province":"GA",
    "sg:tags":[
        "contractor"
    ],
    "sg:website":"www.jwhammer.com",
    "wof:name":"John Wesley Hammer Construction Co Inc",
    "wof:placetype":"venue"
},
  "geometry": {"coordinates":[-84.29201999999999,33.772356],"type":"Point"}
}