{
  "type": "Feature",
  "properties": {
    "iso:country":"US",
    "sg:address":"2166 Burley Ct SE",
    "sg:city":"Conyers",
    "sg:classifiers":[
        {
            "category":"Professional",
            "subcategory":"Secretarial Services",
            "type":"Services"
        }
    ],
    "sg:phone":"+1 770 918 1635",
    "sg:postcode":"30094",
    "sg:province":"GA",
    "sg:tags":[
        "processing",
        "word"
    ],
    "wof:name":"Professional Word Processing",
    "wof:placetype":"venue"
},
  "geometry": {"coordinates":[-84.056645,33.56164],"type":"Point"}
}