{
  "type": "Feature",
  "properties": {
    "addr:full":"1202 Winona Ave Waycross GA 31503",
    "addr:housenumber":"1202",
    "addr:postcode":"31503",
    "addr:street":"Winona Ave",
    "iso:country":"US",
    "sg:address":"1202 Winona Ave",
    "sg:city":"Waycross",
    "sg:classifiers":[
        {
            "category":"Professional",
            "type":"Services"
        }
    ],
    "sg:phone":"+1 912 284 1836",
    "sg:postcode":"31503",
    "sg:province":"GA",
    "wof:name":"Bertram B Burnett PHD",
    "wof:placetype":"venue"
},
  "geometry": {"coordinates":[-82.383662,31.229859],"type":"Point"}
}