{
  "type": "Feature",
  "properties": {
    "addr:full":"1850 Jonesboro Rd Mcdonough GA 30253",
    "addr:housenumber":"1850",
    "addr:postcode":"30253",
    "addr:street":"Jonesboro Rd",
    "iso:country":"US",
    "sg:address":"1850 Jonesboro Rd",
    "sg:city":"Mcdonough",
    "sg:phone":"+1 770 914 9057",
    "sg:postcode":"30253",
    "sg:province":"GA",
    "sg:website":"http://target.com",
    "wof:name":"Target Optical",
    "wof:placetype":"venue"
},
  "geometry": {"coordinates":[-84.21656400000001,33.464363],"type":"Point"}
}