{
  "type": "Feature",
  "properties": {
    "addr:full":"5072 Alabama Hwy Ringgold GA 30736",
    "addr:housenumber":"5072",
    "addr:postcode":"30736",
    "addr:street":"Alabama Hwy",
    "iso:country":"US",
    "sg:address":"5072 Alabama Hwy",
    "sg:city":"Ringgold",
    "sg:classifiers":[
        {
            "category":"Autos & Motor Vehicles",
            "subcategory":"Auto Supplies",
            "type":"Retail Goods"
        }
    ],
    "sg:phone":"+1 706 965 8520",
    "sg:postcode":"30736",
    "sg:province":"GA",
    "sg:tags":[
        "equipment",
        "parts",
        "electrical",
        "automobile"
    ],
    "sg:website":"www.advancedautoparts.com",
    "wof:name":"Advance Auto Parts Inc",
    "wof:placetype":"venue"
},
  "geometry": {"coordinates":[-85.12340500000001,34.917167],"type":"Point"}
}