{
  "type": "Feature",
  "properties": {
    "iso:country":"US",
    "sg:address":"1856 Bishops Green Dr",
    "sg:city":"Marietta",
    "sg:classifiers":[
        {
            "category":"Building & Trades",
            "subcategory":"Construction",
            "type":"Services"
        }
    ],
    "sg:phone":"+1 770 578 4404",
    "sg:postcode":"30062",
    "sg:province":"GA",
    "sg:tags":[
        "interior",
        "design"
    ],
    "wof:name":"Beverly Brown Design Associate",
    "wof:placetype":"venue"
},
  "geometry": {"coordinates":[-84.425003,33.997601],"type":"Point"}
}