{
  "type": "Feature",
  "properties": {
    "iso:country":"US",
    "sg:address":"3978 Hammonds Ferry Ct",
    "sg:city":"Evans",
    "sg:classifiers":[
        {
            "category":"Building & Trades",
            "subcategory":"Construction",
            "type":"Services"
        }
    ],
    "sg:phone":"+1 706 855 1626",
    "sg:postcode":"30809",
    "sg:province":"GA",
    "sg:tags":[
        "home",
        "general",
        "contractor"
    ],
    "wof:name":"Homestead Builders Inc",
    "wof:placetype":"venue"
},
  "geometry": {"coordinates":[-82.109272,33.553482],"type":"Point"}
}