{
  "type": "Feature",
  "properties": {
    "addr:full":"5321 Salem Springs Pl Lithonia GA 30038",
    "addr:housenumber":"5321",
    "addr:postcode":"30038",
    "addr:street":"Salem Springs Pl",
    "iso:country":"US",
    "sg:address":"5321 Salem Springs Pl",
    "sg:city":"Lithonia",
    "sg:classifiers":[
        {
            "category":"Professional",
            "subcategory":"Management & Consulting",
            "type":"Services"
        }
    ],
    "sg:phone":"+1 678 580 3041",
    "sg:postcode":"30038",
    "sg:province":"GA",
    "sg:tags":[
        "business"
    ],
    "wof:name":"Henderson Info Consulting",
    "wof:placetype":"venue"
},
  "geometry": {"coordinates":[-84.17371799999999,33.675447],"type":"Point"}
}