{
  "type": "Feature",
  "properties": {
    "addr:full":"965 Hickman Rd Augusta GA 30904",
    "addr:housenumber":"965",
    "addr:postcode":"30904",
    "addr:street":"Hickman Rd",
    "iso:country":"US",
    "sg:address":"965 Hickman Rd",
    "sg:city":"Augusta",
    "sg:classifiers":[
        {
            "category":"Recreation",
            "type":"Entertainment"
        }
    ],
    "sg:phone":"+1 706 738 2031",
    "sg:postcode":"30904",
    "sg:province":"GA",
    "sg:tags":[
        "environmental",
        "ecological",
        "conservation"
    ],
    "sg:website":"http://www.goboatgeorgia.com",
    "wof:name":"Hickman Park",
    "wof:placetype":"venue"
},
  "geometry": {"coordinates":[-82.010214,33.473874],"type":"Point"}
}