{
  "type": "Feature",
  "properties": {
    "addr:full":"626 Yellow Creek Rd Ball Ground GA 30107",
    "addr:housenumber":"626",
    "addr:postcode":"30107",
    "addr:street":"Yellow Creek Rd",
    "iso:country":"US",
    "sg:address":"626 Yellow Creek Rd",
    "sg:city":"Ball Ground",
    "sg:classifiers":[
        {
            "category":"Manufacturing",
            "subcategory":"Tools & Machinery",
            "type":"Manufacturing & Wholesale Goods"
        }
    ],
    "sg:phone":"+1 770 893 3807",
    "sg:postcode":"30107",
    "sg:province":"GA",
    "sg:tags":[
        "computer",
        "electronic",
        "mfg"
    ],
    "wof:name":"Rk Mapping Services LLC",
    "wof:placetype":"venue"
},
  "geometry": {"coordinates":[-84.274494,34.29397],"type":"Point"}
}