{
  "type": "Feature",
  "properties": {
    "iso:country":"US",
    "sg:address":"805 Broad St",
    "sg:city":"Rome",
    "sg:classifiers":[
        {
            "category":"Shopping",
            "subcategory":"Jewelry",
            "type":"Retail Goods"
        }
    ],
    "sg:phone":"+1 706 291 8596",
    "sg:postcode":"30161",
    "sg:province":"GA",
    "wof:name":"Masseys Fine Jewelry Company",
    "wof:placetype":"venue"
},
  "geometry": {"coordinates":[-85.16491499999999,34.257243],"type":"Point"}
}