{
  "type": "Feature",
  "properties": {
    "addr:full":"1890 Shurling Dr Macon GA 31211",
    "addr:housenumber":"1890",
    "addr:postcode":"31211",
    "addr:street":"Shurling Dr",
    "iso:country":"US",
    "sg:address":"1890 Shurling Dr",
    "sg:city":"Macon",
    "sg:classifiers":[
        {
            "category":"Food & Beverages",
            "subcategory":"Groceries & Convenience Stores",
            "type":"Retail Goods"
        }
    ],
    "sg:phone":"+1 478 743 2368",
    "sg:postcode":"31211",
    "sg:province":"GA",
    "wof:name":"Shurlington Food Mart",
    "wof:placetype":"venue"
},
  "geometry": {"coordinates":[-83.594967,32.860878],"type":"Point"}
}