{
  "type": "Feature",
  "properties": {
    "iso:country":"US",
    "sg:address":"6755 Shiloh Rd E",
    "sg:city":"Alpharetta",
    "sg:classifiers":[
        {
            "category":"Professional",
            "subcategory":"Computer Services",
            "type":"Services"
        }
    ],
    "sg:phone":"+1 770 205 8236",
    "sg:postcode":"30005",
    "sg:province":"GA",
    "sg:tags":[
        "software"
    ],
    "wof:name":"Image Corporation of America",
    "wof:placetype":"venue"
},
  "geometry": {"coordinates":[-84.201083,34.110206],"type":"Point"}
}