{
  "type": "Feature",
  "properties": {
    "addr:full":"4465 Peachtree Dunwoody R Atlanta GA 30342",
    "addr:housenumber":"4465",
    "addr:postcode":"30342",
    "addr:street":"Peachtree Dunwoody R",
    "iso:country":"US",
    "sg:address":"4465 Peachtree Dunwoody R",
    "sg:city":"Atlanta",
    "sg:classifiers":[
        {
            "category":"Building & Trades",
            "subcategory":"Cleaning & Sanitation",
            "type":"Services"
        }
    ],
    "sg:phone":"+1 404 261 5940",
    "sg:postcode":"30342",
    "sg:province":"GA",
    "sg:tags":[
        "carpet"
    ],
    "sg:website":"www.buckheadfloorservice.com",
    "wof:name":"Buckhead Floor Service",
    "wof:placetype":"venue"
},
  "geometry": {"coordinates":[-84.357907,33.87633],"type":"Point"}
}