{
  "type": "Feature",
  "properties": {
    "addr:full":"3379 Peachtree Rd Ste 260 Atlanta GA 30326",
    "addr:housenumber":"3379",
    "addr:postcode":"30326",
    "addr:street":"Peachtree Rd Ste 260",
    "iso:country":"US",
    "sg:address":"3379 Peachtree Rd Ste 260",
    "sg:city":"Atlanta",
    "sg:classifiers":[
        {
            "category":"Health Services",
            "subcategory":"Clinic",
            "type":"Services"
        },
        {
            "category":"Personal",
            "subcategory":"Skin Care",
            "type":"Services"
        }
    ],
    "sg:phone":"+1 404 437 7800",
    "sg:postcode":"30326",
    "sg:province":"GA",
    "sg:tags":[
        "spa",
        "medical"
    ],
    "sg:website":"www.a4mmd.com",
    "wof:name":"Advanced Anti-Aging and Aesthetic Medicine",
    "wof:placetype":"venue"
},
  "geometry": {"coordinates":[-84.36581700000001,33.848118],"type":"Point"}
}