{
  "type": "Feature",
  "properties": {
    "iso:country":"US",
    "sg:address":"55 Acorn Way",
    "sg:city":"Covington",
    "sg:classifiers":[
        {
            "category":"Shopping",
            "type":"Retail Goods"
        }
    ],
    "sg:phone":"+1 678 342 9133",
    "sg:postcode":"30016",
    "sg:province":"GA",
    "sg:tags":[
        "cosmetic",
        "perfume"
    ],
    "wof:name":"ATM Beauty",
    "wof:placetype":"venue"
},
  "geometry": {"coordinates":[-83.916872,33.481205],"type":"Point"}
}