{
  "type": "Feature",
  "properties": {
    "iso:country":"US",
    "sg:address":"6358 Old Dixie Hwy",
    "sg:city":"Jonesboro",
    "sg:classifiers":[
        {
            "category":"Travel",
            "subcategory":"Hotels & Motels",
            "type":"Entertainment"
        }
    ],
    "sg:phone":"+1 770 968 5018",
    "sg:postcode":"30236",
    "sg:province":"GA",
    "wof:name":"Americas Best Value Inn & Suites",
    "wof:placetype":"venue"
},
  "geometry": {"coordinates":[-84.37500199999999,33.581218],"type":"Point"}
}