{
  "type": "Feature",
  "properties": {
    "iso:country":"US",
    "sg:address":"271 Sarah Ln",
    "sg:city":"Lawrenceville",
    "sg:classifiers":[
        {
            "category":"Professional",
            "subcategory":"Management & Consulting",
            "type":"Services"
        }
    ],
    "sg:phone":"+1 770 995 0482",
    "sg:postcode":"30045",
    "sg:province":"GA",
    "wof:name":"Jpc Marketing Inc",
    "wof:placetype":"venue"
},
  "geometry": {"coordinates":[-84.00367,33.937434],"type":"Point"}
}