{
  "type": "Feature",
  "properties": {
    "addr:full":"1109 Highway 441 S Clayton GA 30525",
    "addr:housenumber":"1109",
    "addr:postcode":"30525",
    "addr:street":"Highway 441 S",
    "iso:country":"US",
    "sg:address":"1109 Highway 441 S",
    "sg:city":"Clayton",
    "sg:classifiers":[
        {
            "category":"Building & Trades",
            "subcategory":"Landscaping Services",
            "type":"Services"
        }
    ],
    "sg:phone":"+1 706 782 7290",
    "sg:postcode":"30525",
    "sg:province":"GA",
    "sg:tags":[
        "tree"
    ],
    "wof:name":"Ramey Tree Service & Construction",
    "wof:placetype":"venue"
},
  "geometry": {"coordinates":[-83.40063600000001,34.87025],"type":"Point"}
}