{
  "type": "Feature",
  "properties": {
    "addr:full":"5185 Smithfield Rd Bowdon GA 30108",
    "addr:housenumber":"5185",
    "addr:postcode":"30108",
    "addr:street":"Smithfield Rd",
    "iso:country":"US",
    "sg:address":"5185 Smithfield Rd",
    "sg:city":"Bowdon",
    "sg:classifiers":[
        {
            "category":"Building & Trades",
            "subcategory":"Construction",
            "type":"Services"
        }
    ],
    "sg:phone":"+1 770 258 2402",
    "sg:postcode":"30108",
    "sg:province":"GA",
    "sg:tags":[
        "house"
    ],
    "wof:name":"Mc Leroy Construction",
    "wof:placetype":"venue"
},
  "geometry": {"coordinates":[-85.239566,33.585311],"type":"Point"}
}