{
  "type": "Feature",
  "properties": {
    "addr:full":"1141 Oxford Dr SE Conyers GA 30013",
    "addr:housenumber":"1141",
    "addr:postcode":"30013",
    "addr:street":"Oxford Dr Se",
    "iso:country":"US",
    "sg:address":"1141 Oxford Dr SE",
    "sg:city":"Conyers",
    "sg:classifiers":[
        {
            "category":"Banks & Credit Unions",
            "subcategory":"Financial Services",
            "type":"Services"
        }
    ],
    "sg:phone":"+1 770 388 9209",
    "sg:postcode":"30013",
    "sg:province":"GA",
    "sg:tags":[
        "investor"
    ],
    "wof:name":"T & T Unlimited Investments",
    "wof:placetype":"venue"
},
  "geometry": {"coordinates":[-84.00636299999999,33.618383],"type":"Point"}
}