{
  "type": "Feature",
  "properties": {
    "iso:country":"US",
    "sg:address":"66 Laketop Dr SE",
    "sg:city":"Cartersville",
    "sg:classifiers":[
        {
            "category":"Building & Trades",
            "subcategory":"Construction",
            "type":"Services"
        }
    ],
    "sg:phone":"+1 770 974 5850",
    "sg:postcode":"30121",
    "sg:province":"GA",
    "sg:tags":[
        "contractor"
    ],
    "wof:name":"Sun & Wind Inc",
    "wof:placetype":"venue"
},
  "geometry": {"coordinates":[-84.719228,34.099447],"type":"Point"}
}