{
  "type": "Feature",
  "properties": {
    "addr:full":"111 S Hutchinson Ave Adel GA 31620",
    "addr:housenumber":"111",
    "addr:postcode":"31620",
    "addr:street":"S Hutchinson Ave",
    "iso:country":"US",
    "sg:address":"111 S Hutchinson Ave",
    "sg:city":"Adel",
    "sg:classifiers":[
        {
            "category":"Shopping",
            "subcategory":"Jewelry",
            "type":"Retail Goods"
        }
    ],
    "sg:phone":"+1 229 896 1295",
    "sg:postcode":"31620",
    "sg:province":"GA",
    "sg:tags":[
        "jeweler"
    ],
    "wof:name":"Joseph's Jewelers",
    "wof:placetype":"venue"
},
  "geometry": {"coordinates":[-83.42338700000001,31.136867],"type":"Point"}
}