{
  "type": "Feature",
  "properties": {
    "addr:full":"439 Azalea Dr Stockbridge GA 30281",
    "addr:housenumber":"439",
    "addr:postcode":"30281",
    "addr:street":"Azalea Dr",
    "iso:country":"US",
    "sg:address":"439 Azalea Dr",
    "sg:city":"Stockbridge",
    "sg:classifiers":[
        {
            "category":"Building & Trades",
            "subcategory":"Construction",
            "type":"Services"
        }
    ],
    "sg:phone":"+1 770 474 2305",
    "sg:postcode":"30281",
    "sg:province":"GA",
    "wof:name":"Southern Construction",
    "wof:placetype":"venue"
},
  "geometry": {"coordinates":[-84.214636,33.585612],"type":"Point"}
}