{
  "type": "Feature",
  "properties": {
    "iso:country":"US",
    "sg:address":"1305 E 2nd Ave",
    "sg:city":"Albany",
    "sg:classifiers":[
        {
            "category":"Education",
            "subcategory":"School",
            "type":"Public Place"
        }
    ],
    "sg:phone":"+1 229 431 3367",
    "sg:postcode":"31705",
    "sg:province":"GA",
    "wof:name":"Jackson Heights Elementary",
    "wof:placetype":"venue"
},
  "geometry": {"coordinates":[-84.120096,31.5864],"type":"Point"}
}