{
  "type": "Feature",
  "properties": {
    "addr:full":"164 Commercial Dr Thomasville GA 31792",
    "addr:housenumber":"164",
    "addr:postcode":"31792",
    "addr:street":"Commercial Dr",
    "iso:country":"US",
    "sg:address":"164 Commercial Dr",
    "sg:city":"Thomasville",
    "sg:classifiers":[
        {
            "category":"Professional",
            "subcategory":"Credit Reporting & Collection",
            "type":"Services"
        }
    ],
    "sg:phone":"+1 229 227 9770",
    "sg:postcode":"31792",
    "sg:province":"GA",
    "sg:tags":[
        "agency"
    ],
    "wof:name":"South Georgia Management Svc",
    "wof:placetype":"venue"
},
  "geometry": {"coordinates":[-83.942903,30.850136],"type":"Point"}
}