{
  "type": "Feature",
  "properties": {
    "iso:country":"US",
    "sg:address":"124 Championship Ct",
    "sg:city":"Fayetteville",
    "sg:classifiers":[
        {
            "category":"Professional",
            "subcategory":"Business Services",
            "type":"Services"
        }
    ],
    "sg:phone":"+1 770 460 0800",
    "sg:postcode":"30215",
    "sg:province":"GA",
    "wof:name":"Lido Marketing Group Inc",
    "wof:placetype":"venue"
},
  "geometry": {"coordinates":[-84.399879,33.426165],"type":"Point"}
}