{
  "type": "Feature",
  "properties": {
    "addr:full":"165 W Wieuca Rd NE # 303 Atlanta GA 30342",
    "addr:housenumber":"165",
    "addr:postcode":"30342",
    "addr:street":"W Wieuca Rd Ne # 303",
    "iso:country":"US",
    "sg:address":"165 W Wieuca Rd NE # 303",
    "sg:city":"Atlanta",
    "sg:classifiers":[
        {
            "category":"Real Estate",
            "subcategory":"Real Estate Services",
            "type":"Services"
        },
        {
            "category":"Real Estate",
            "subcategory":"Real Estate Agent",
            "type":"Services"
        }
    ],
    "sg:phone":"+1 404 847 1267",
    "sg:postcode":"30342",
    "sg:province":"GA",
    "sg:tags":[
        "buyer",
        "management",
        "broker"
    ],
    "wof:name":"Atlantic Realty",
    "wof:placetype":"venue"
},
  "geometry": {"coordinates":[-84.38115999999999,33.877481],"type":"Point"}
}