{
  "type": "Feature",
  "properties": {
    "addr:full":"507 Valenti Ct Riverdale GA 30274",
    "addr:housenumber":"507",
    "addr:postcode":"30274",
    "addr:street":"Valenti Ct",
    "iso:country":"US",
    "sg:address":"507 Valenti Ct",
    "sg:city":"Riverdale",
    "sg:classifiers":[
        {
            "category":"Building & Trades",
            "subcategory":"Construction",
            "type":"Services"
        }
    ],
    "sg:phone":"+1 770 603 9220",
    "sg:postcode":"30274",
    "sg:province":"GA",
    "sg:tags":[
        "residential"
    ],
    "wof:name":"James Nettles",
    "wof:placetype":"venue"
},
  "geometry": {"coordinates":[-84.406733,33.528607],"type":"Point"}
}