{
  "type": "Feature",
  "properties": {
    "iso:country":"US",
    "sg:address":"1120 Greenbriar Cir",
    "sg:city":"Decatur",
    "sg:classifiers":[
        {
            "category":"Real Estate",
            "subcategory":"Real Estate Services",
            "type":"Services"
        },
        {
            "category":"Building & Trades",
            "subcategory":"Cleaning & Sanitation",
            "type":"Services"
        },
        {
            "category":"Building & Trades",
            "subcategory":"Construction",
            "type":"Services"
        }
    ],
    "sg:phone":"+1 404 428 0718",
    "sg:postcode":"30033",
    "sg:province":"GA",
    "sg:tags":[
        "home",
        "staging",
        "painter"
    ],
    "wof:name":"A Clean Slate",
    "wof:placetype":"venue"
},
  "geometry": {"coordinates":[-84.26091599999999,33.808197],"type":"Point"}
}