{
  "type": "Feature",
  "properties": {
    "addr:full":"8165 Gullatt Rd Palmetto GA 30268",
    "addr:housenumber":"8165",
    "addr:postcode":"30268",
    "addr:street":"Gullatt Rd",
    "iso:country":"US",
    "sg:address":"8165 Gullatt Rd",
    "sg:city":"Palmetto",
    "sg:classifiers":[
        {
            "category":"Wholesale",
            "subcategory":"Machinery & Supplies",
            "type":"Manufacturing & Wholesale Goods"
        }
    ],
    "sg:phone":"+1 770 774 9276",
    "sg:postcode":"30268",
    "sg:province":"GA",
    "sg:tags":[
        "equipment"
    ],
    "wof:name":"Georgia Rigging Inc",
    "wof:placetype":"venue"
},
  "geometry": {"coordinates":[-84.621515,33.534763],"type":"Point"}
}