{
  "type": "Feature",
  "properties": {
    "addr:full":"5000 Highlands Pkwy SE Smyrna GA 30082",
    "addr:housenumber":"5000",
    "addr:postcode":"30082",
    "addr:street":"Highlands Pkwy Se",
    "iso:country":"US",
    "sg:address":"5000 Highlands Pkwy SE",
    "sg:city":"Smyrna",
    "sg:classifiers":[
        {
            "category":"Professional",
            "subcategory":"Detective & Security Services",
            "type":"Services"
        },
        {
            "category":"Organizations",
            "subcategory":"Professional Association",
            "type":"Services"
        }
    ],
    "sg:phone":"+1 865 540 4376",
    "sg:postcode":"30082",
    "sg:province":"GA",
    "sg:tags":[
        "information",
        "bureau",
        "representative",
        "agent",
        "manufacturers'"
    ],
    "wof:name":"High Tech Network",
    "wof:placetype":"venue"
},
  "geometry": {"coordinates":[-84.510998,33.830146],"type":"Point"}
}