{
  "type": "Feature",
  "properties": {
    "iso:country":"US",
    "sg:address":"746 Grovania Rd",
    "sg:city":"Hawkinsville",
    "sg:classifiers":[
        {
            "category":"Professional",
            "subcategory":"Management & Consulting",
            "type":"Services"
        }
    ],
    "sg:phone":"+1 478 988 8355",
    "sg:postcode":"31036",
    "sg:province":"GA",
    "wof:name":"Kmm Management LLC",
    "wof:placetype":"venue"
},
  "geometry": {"coordinates":[-83.63840999999999,32.380891],"type":"Point"}
}