{
  "type": "Feature",
  "properties": {
    "iso:country":"US",
    "sg:address":"5608 New Jesup Hwy",
    "sg:city":"Brunswick",
    "sg:classifiers":[
        {
            "category":"Place Of Worship",
            "subcategory":"Church",
            "type":"Public Place"
        },
        {
            "category":"Place Of Worship",
            "type":"Public Place"
        }
    ],
    "sg:phone":"+1 912 265 7070",
    "sg:postcode":"31523",
    "sg:province":"GA",
    "sg:tags":[
        "churches-pentecostal-independent",
        "churches-pentecostal"
    ],
    "sg:website":"http://www.firstupchurst.com",
    "wof:name":"United Pentecostal Church",
    "wof:placetype":"venue"
},
  "geometry": {"coordinates":[-81.531812,31.230446],"type":"Point"}
}