{
  "type": "Feature",
  "properties": {
    "iso:country":"US",
    "sg:address":"1111 S Hamilton St",
    "sg:city":"Dalton",
    "sg:classifiers":[
        {
            "category":"Wholesale",
            "subcategory":"Construction Materials",
            "type":"Manufacturing & Wholesale Goods"
        },
        {
            "category":"Home & Garden",
            "subcategory":"Building Materials",
            "type":"Retail Goods"
        }
    ],
    "sg:phone":"+1 706 259 0601",
    "sg:postcode":"30720",
    "sg:province":"GA",
    "sg:tags":[
        "brick",
        "common",
        "face"
    ],
    "wof:name":"Key-James Brick & Supply Inc",
    "wof:placetype":"venue"
},
  "geometry": {"coordinates":[-84.966269,34.755846],"type":"Point"}
}