{
  "type": "Feature",
  "properties": {
    "addr:full":"1945 Rockbridge Rd Stone Mountain GA 30087",
    "addr:housenumber":"1945",
    "addr:postcode":"30087",
    "addr:street":"Rockbridge Rd",
    "iso:country":"US",
    "sg:address":"1945 Rockbridge Rd",
    "sg:city":"Stone Mountain",
    "sg:classifiers":[
        {
            "category":"Restaurant",
            "type":"Food & Drink"
        }
    ],
    "sg:menulink":"http://www.allmenus.com/ga/lilburn/140470-waffle-house/menu/",
    "sg:phone":"+1 770 338 4243",
    "sg:postcode":"30087",
    "sg:province":"GA",
    "sg:tags":[
        "american"
    ],
    "wof:name":"Waffle House",
    "wof:placetype":"venue"
},
  "geometry": {"coordinates":[-84.11798400000001,33.823078],"type":"Point"}
}