{
  "type": "Feature",
  "properties": {
    "addr:full":"196 Cassville White Rd NW Cartersville GA 30121",
    "addr:housenumber":"196",
    "addr:postcode":"30121",
    "addr:street":"Cassville White Rd Nw",
    "iso:country":"US",
    "sg:address":"196 Cassville White Rd NW",
    "sg:city":"Cartersville",
    "sg:classifiers":[
        {
            "category":"Retail",
            "subcategory":"Repair Shop",
            "type":"Services"
        }
    ],
    "sg:phone":"+1 770 382 5179",
    "sg:postcode":"30121",
    "sg:province":"GA",
    "sg:tags":[
        "taxidermist"
    ],
    "wof:name":"Medicine Wolf Taxidermy",
    "wof:placetype":"venue"
},
  "geometry": {"coordinates":[-84.847272,34.2514],"type":"Point"}
}