{
  "type": "Feature",
  "properties": {
    "iso:country":"US",
    "sg:address":"8 Peachtree Battle Ave NW",
    "sg:city":"Atlanta",
    "sg:classifiers":[
        {
            "category":"Education",
            "subcategory":"School",
            "type":"Public Place"
        }
    ],
    "sg:phone":"+1 404 802 7050",
    "sg:postcode":"30305",
    "sg:province":"GA",
    "sg:tags":[
        "elementary"
    ],
    "sg:website":"http://www.atlanta.k12.ga.us",
    "wof:name":"East Rivers Elem School",
    "wof:placetype":"venue"
},
  "geometry": {"coordinates":[-84.389191,33.819801],"type":"Point"}
}