{
  "type": "Feature",
  "properties": {
    "addr:full":"2877 Sapelo Dr Valdosta GA 31605",
    "addr:housenumber":"2877",
    "addr:postcode":"31605",
    "addr:street":"Sapelo Dr",
    "iso:country":"US",
    "sg:address":"2877 Sapelo Dr",
    "sg:city":"Valdosta",
    "sg:classifiers":[
        {
            "category":"Professional",
            "subcategory":"Management & Consulting",
            "type":"Services"
        }
    ],
    "sg:phone":"+1 229 247 9986",
    "sg:postcode":"31605",
    "sg:province":"GA",
    "wof:name":"Sprete Office Solutions",
    "wof:placetype":"venue"
},
  "geometry": {"coordinates":[-83.251835,30.895043],"type":"Point"}
}