{
  "type": "Feature",
  "properties": {
    "iso:country":"US",
    "sg:address":"139 Wilson Rd",
    "sg:city":"Vidalia",
    "sg:classifiers":[
        {
            "category":"Retail",
            "subcategory":"Auto Repair",
            "type":"Services"
        }
    ],
    "sg:phone":"+1 912 538 8299",
    "sg:postcode":"30413",
    "sg:province":"GA",
    "sg:tags":[
        "body",
        "automobile",
        "painting"
    ],
    "wof:name":"West Side Collision Ctr",
    "wof:placetype":"venue"
},
  "geometry": {"coordinates":[-82.589823,32.84407],"type":"Point"}
}