{
  "type": "Feature",
  "properties": {
    "iso:country":"US",
    "sg:address":"3365 Mountain View Rd",
    "sg:city":"Gainesville",
    "sg:classifiers":[
        {
            "category":"Autos & Motor Vehicles",
            "subcategory":"Auto Supplies",
            "type":"Retail Goods"
        },
        {
            "category":"Retail",
            "subcategory":"Auto Repair",
            "type":"Services"
        }
    ],
    "sg:phone":"+1 770 535 7278",
    "sg:postcode":"30504",
    "sg:province":"GA",
    "sg:tags":[
        "automobile"
    ],
    "wof:name":"Mountain View Auto Repair Inc",
    "wof:placetype":"venue"
},
  "geometry": {"coordinates":[-83.863178,34.256118],"type":"Point"}
}