{
  "type": "Feature",
  "properties": {
    "addr:full":"545 N Mcdonough St Decatur GA 30030",
    "addr:housenumber":"545",
    "addr:postcode":"30030",
    "addr:street":"N Mcdonough St",
    "iso:country":"US",
    "sg:address":"545 N Mcdonough St",
    "sg:city":"Decatur",
    "sg:classifiers":[
        {
            "category":"Professional",
            "subcategory":"Lawyer & Legal Services",
            "type":"Services"
        }
    ],
    "sg:phone":"+1 404 377 7760",
    "sg:postcode":"30030",
    "sg:province":"GA",
    "sg:tags":[
        "information",
        "attorney",
        "practice",
        "referral"
    ],
    "wof:name":"Curtis R Richardson",
    "wof:placetype":"venue"
},
  "geometry": {"coordinates":[-84.296491,33.773657],"type":"Point"}
}