{
  "type": "Feature",
  "properties": {
    "addr:full":"140 Rainbow Way Fayetteville GA 30214",
    "addr:housenumber":"140",
    "addr:postcode":"30214",
    "addr:street":"Rainbow Way",
    "iso:country":"US",
    "sg:address":"140 Rainbow Way",
    "sg:city":"Fayetteville",
    "sg:classifiers":[
        {
            "category":"Freight",
            "type":"Transportation"
        }
    ],
    "sg:phone":"+1 770 719 8322",
    "sg:postcode":"30214",
    "sg:province":"GA",
    "sg:tags":[
        "broker"
    ],
    "wof:name":"K C Logistics Inc",
    "wof:placetype":"venue"
},
  "geometry": {"coordinates":[-84.428853,33.506198],"type":"Point"}
}