{
  "type": "Feature",
  "properties": {
    "addr:full":"777 King George Blvd Savannah GA 31419",
    "addr:housenumber":"777",
    "addr:postcode":"31419",
    "addr:street":"King George Blvd",
    "iso:country":"US",
    "sg:address":"777 King George Blvd",
    "sg:city":"Savannah",
    "sg:classifiers":[
        {
            "category":"Real Estate",
            "subcategory":"Real Estate Agent",
            "type":"Services"
        }
    ],
    "sg:phone":"+1 912 927 7172",
    "sg:postcode":"31419",
    "sg:province":"GA",
    "wof:name":"Coldwell Banker Greater",
    "wof:placetype":"venue"
},
  "geometry": {"coordinates":[-81.210144,31.989959],"type":"Point"}
}