{
  "type": "Feature",
  "properties": {
    "addr:full":"3280 Timberloch Dr NE Marietta GA 30068",
    "addr:housenumber":"3280",
    "addr:postcode":"30068",
    "addr:street":"Timberloch Dr Ne",
    "iso:country":"US",
    "sg:address":"3280 Timberloch Dr NE",
    "sg:city":"Marietta",
    "sg:classifiers":[
        {
            "category":"Professional",
            "type":"Services"
        }
    ],
    "sg:phone":"+1 770 971 1776",
    "sg:postcode":"30068",
    "sg:province":"GA",
    "wof:name":"Endless Reach Inc",
    "wof:placetype":"venue"
},
  "geometry": {"coordinates":[-84.461924,33.952317],"type":"Point"}
}