{
  "type": "Feature",
  "properties": {
    "addr:full":"511 Spruce St Fort Valley GA 31030",
    "addr:housenumber":"511",
    "addr:postcode":"31030",
    "addr:street":"Spruce St",
    "iso:country":"US",
    "sg:address":"511 Spruce St",
    "sg:city":"Fort Valley",
    "sg:classifiers":[
        {
            "category":"Personal",
            "subcategory":"Beauty Salon",
            "type":"Services"
        }
    ],
    "sg:phone":"+1 478 825 5977",
    "sg:postcode":"31030",
    "sg:province":"GA",
    "sg:tags":[
        "shop"
    ],
    "wof:name":"Dollar Beauty & Barber Shop",
    "wof:placetype":"venue"
},
  "geometry": {"coordinates":[-83.88640100000001,32.545933],"type":"Point"}
}