{
  "type": "Feature",
  "properties": {
    "iso:country":"US",
    "sg:address":"2810 E Atlanta Rd",
    "sg:city":"Ellenwood",
    "sg:classifiers":[
        {
            "category":"Shopping",
            "type":"Retail Goods"
        }
    ],
    "sg:phone":"+1 770 507 0048",
    "sg:postcode":"30294",
    "sg:province":"GA",
    "sg:tags":[
        "supply",
        "cosmetic",
        "beauty",
        "perfume"
    ],
    "wof:name":"Beauty and More III",
    "wof:placetype":"venue"
},
  "geometry": {"coordinates":[-84.244457,33.616696],"type":"Point"}
}