{
  "type": "Feature",
  "properties": {
    "addr:full":"4246 Dykes Dr NW Atlanta GA 30342",
    "addr:housenumber":"4246",
    "addr:postcode":"30342",
    "addr:street":"Dykes Dr Nw",
    "iso:country":"US",
    "sg:address":"4246 Dykes Dr NW",
    "sg:city":"Atlanta",
    "sg:classifiers":[
        {
            "category":"Professional",
            "type":"Services"
        }
    ],
    "sg:phone":"+1 404 228 5703",
    "sg:postcode":"30342",
    "sg:province":"GA",
    "sg:tags":[
        "publication",
        "editorial"
    ],
    "wof:name":"Allison Battista Editorial Services",
    "wof:placetype":"venue"
},
  "geometry": {"coordinates":[-84.402388,33.871303],"type":"Point"}
}