{
  "type": "Feature",
  "properties": {
    "iso:country":"US",
    "sg:address":"4345 Hugh Howell Rd",
    "sg:city":"Tucker",
    "sg:classifiers":[
        {
            "category":"Retail",
            "subcategory":"Auto Repair",
            "type":"Services"
        }
    ],
    "sg:phone":"+1 770 938 4047",
    "sg:postcode":"30084",
    "sg:province":"GA",
    "sg:tags":[
        "automotive"
    ],
    "wof:name":"Fast Pass Emission Testing",
    "wof:placetype":"venue"
},
  "geometry": {"coordinates":[-84.2093,33.851912],"type":"Point"}
}