{
  "type": "Feature",
  "properties": {
    "iso:country":"US",
    "sg:address":"5102 Audley Ln NW",
    "sg:city":"Norcross",
    "sg:classifiers":[
        {
            "category":"Professional",
            "type":"Services"
        }
    ],
    "sg:phone":"+1 770 662 0207",
    "sg:postcode":"30092",
    "sg:province":"GA",
    "wof:name":"Solbourne Inc",
    "wof:placetype":"venue"
},
  "geometry": {"coordinates":[-84.220372,33.995885],"type":"Point"}
}