{
  "type": "Feature",
  "properties": {
    "addr:full":"1519 Johnson Ferry Rd Marietta GA 30062",
    "addr:housenumber":"1519",
    "addr:postcode":"30062",
    "addr:street":"Johnson Ferry Rd",
    "iso:country":"US",
    "sg:address":"1519 Johnson Ferry Rd",
    "sg:city":"Marietta",
    "sg:classifiers":[
        {
            "category":"Health Services",
            "subcategory":"Doctor",
            "type":"Services"
        }
    ],
    "sg:phone":"+1 770 971 3376",
    "sg:postcode":"30062",
    "sg:province":"GA",
    "sg:tags":[
        "physician",
        "dermatology",
        "surgeons",
        "surgeon"
    ],
    "sg:website":"http://www.dermatologyconsultants.org",
    "wof:name":"Kelly Benjamin J MD",
    "wof:placetype":"venue"
},
  "geometry": {"coordinates":[-84.427257,33.986891],"type":"Point"}
}