{
  "type": "Feature",
  "properties": {
    "addr:full":"3370 Colonial Pkwy Decatur GA 30034",
    "addr:housenumber":"3370",
    "addr:postcode":"30034",
    "addr:street":"Colonial Pkwy",
    "iso:country":"US",
    "sg:address":"3370 Colonial Pkwy",
    "sg:city":"Decatur",
    "sg:classifiers":[
        {
            "category":"Retail",
            "subcategory":"Auto Rental",
            "type":"Services"
        }
    ],
    "sg:phone":"+1 770 212 5590",
    "sg:postcode":"30034",
    "sg:province":"GA",
    "sg:tags":[
        "renting",
        "truck",
        "leasing"
    ],
    "wof:name":"Ryder Integrated Logistics Inc",
    "wof:placetype":"venue"
},
  "geometry": {"coordinates":[-84.270326,33.690241],"type":"Point"}
}