{
  "type": "Feature",
  "properties": {
    "iso:country":"US",
    "sg:address":"3053 Cobb Pkwy NW",
    "sg:city":"Kennesaw",
    "sg:classifiers":[
        {
            "category":"Food & Beverages",
            "subcategory":"Groceries & Convenience Stores",
            "type":"Retail Goods"
        }
    ],
    "sg:phone":"+1 770 529 2127",
    "sg:postcode":"30152",
    "sg:province":"GA",
    "sg:website":"www.chevron.com",
    "wof:name":"Chevron Food Mart",
    "wof:placetype":"venue"
},
  "geometry": {"coordinates":[-84.647598,34.028599],"type":"Point"}
}