{
  "type": "Feature",
  "properties": {
    "iso:country":"US",
    "sg:address":"2177 Bonnevit Court NE",
    "sg:city":"Atlanta",
    "sg:classifiers":[
        {
            "category":"Building & Trades",
            "subcategory":"Cleaning & Sanitation",
            "type":"Services"
        }
    ],
    "sg:phone":"+1 404 320 9518",
    "sg:postcode":"30345",
    "sg:province":"GA",
    "sg:tags":[
        "carpet"
    ],
    "wof:name":"Hunt's Specialty Services",
    "wof:placetype":"venue"
},
  "geometry": {"coordinates":[-84.299981,33.834158],"type":"Point"}
}