{
  "type": "Feature",
  "properties": {
    "addr:full":"800 Russell Pkwy Warner Robins GA 31088",
    "addr:housenumber":"800",
    "addr:postcode":"31088",
    "addr:street":"Russell Pkwy",
    "iso:country":"US",
    "sg:address":"800 Russell Pkwy",
    "sg:city":"Warner Robins",
    "sg:classifiers":[
        {
            "category":"Food & Beverages",
            "subcategory":"Liquor & Beverages",
            "type":"Retail Goods"
        }
    ],
    "sg:phone":"+1 478 923 8109",
    "sg:postcode":"31088",
    "sg:province":"GA",
    "sg:tags":[
        "beer",
        "spirit",
        "wine"
    ],
    "wof:name":"Bennett's Liquors",
    "wof:placetype":"venue"
},
  "geometry": {"coordinates":[-83.637001,32.594101],"type":"Point"}
}