{
  "type": "Feature",
  "properties": {
    "iso:country":"US",
    "sg:address":"1208 Russell Pkwy",
    "sg:city":"Warner Robins",
    "sg:classifiers":[
        {
            "category":"Restaurant",
            "type":"Food & Drink"
        }
    ],
    "sg:phone":"+1 478 329 1604",
    "sg:postcode":"31088",
    "sg:province":"GA",
    "sg:tags":[
        "buffet"
    ],
    "wof:name":"Ole Time Buffet",
    "wof:placetype":"venue"
},
  "geometry": {"coordinates":[-83.646942,32.594105],"type":"Point"}
}