{
  "type": "Feature",
  "properties": {
    "iso:country":"US",
    "sg:address":"254 Martin Luther King Jr Blvd",
    "sg:city":"Savannah",
    "sg:classifiers":[
        {
            "category":"Building & Trades",
            "subcategory":"Construction",
            "type":"Services"
        }
    ],
    "sg:phone":"+1 912 233 4209",
    "sg:postcode":"31401",
    "sg:province":"GA",
    "sg:tags":[
        "house",
        "general",
        "contractor"
    ],
    "wof:name":"Archer Western Construction",
    "wof:placetype":"venue"
},
  "geometry": {"coordinates":[-81.098885,32.075866],"type":"Point"}
}