{
  "type": "Feature",
  "properties": {
    "addr:full":"1425 Lanier Blvd Brunswick GA 31520",
    "addr:housenumber":"1425",
    "addr:postcode":"31520",
    "addr:street":"Lanier Blvd",
    "iso:country":"US",
    "sg:address":"1425 Lanier Blvd",
    "sg:city":"Brunswick",
    "sg:classifiers":[
        {
            "category":"Education",
            "subcategory":"Special Training",
            "type":"Public Place"
        },
        {
            "category":"Social Services",
            "type":"Services"
        }
    ],
    "sg:phone":"+1 912 280 0996",
    "sg:postcode":"31520",
    "sg:province":"GA",
    "sg:tags":[
        "youth",
        "organization",
        "center"
    ],
    "wof:name":"Coastal Mentors Inc",
    "wof:placetype":"venue"
},
  "geometry": {"coordinates":[-81.481267,31.152183],"type":"Point"}
}