{
  "type": "Feature",
  "properties": {
    "addr:full":"3100 Coody Dairy Rd Vienna GA 31092",
    "addr:postcode":"3100;31092",
    "addr:street":"Coody Dairy Rd",
    "iso:country":"US",
    "sg:address":"3100 Coody Dairy Rd",
    "sg:city":"Vienna",
    "sg:classifiers":[
        {
            "category":"Farming",
            "subcategory":"Farm",
            "type":"Manufacturing & Wholesale Goods"
        }
    ],
    "sg:phone":"+1 229 268 8593",
    "sg:postcode":"31092",
    "sg:province":"GA",
    "wof:name":"Bledsoe Farms-Mobile",
    "wof:placetype":"venue"
},
  "geometry": {"coordinates":[-83.65893699999999,32.122163],"type":"Point"}
}