{
  "type": "Feature",
  "properties": {
    "iso:country":"US",
    "sg:address":"3350 Buford Dr",
    "sg:city":"Buford",
    "sg:classifiers":[
        {
            "category":"Professional",
            "subcategory":"Business Services",
            "type":"Services"
        }
    ],
    "sg:phone":"+1 770 831 2833",
    "sg:postcode":"30519",
    "sg:province":"GA",
    "sg:tags":[
        "management",
        "document",
        "records-storage"
    ],
    "wof:name":"Windward Star",
    "wof:placetype":"venue"
},
  "geometry": {"coordinates":[-83.98432200000001,34.07238],"type":"Point"}
}