{
  "type": "Feature",
  "properties": {
    "iso:country":"US",
    "sg:address":"1527 Rockdale Dr",
    "sg:city":"Dublin",
    "sg:classifiers":[
        {
            "category":"Communications",
            "subcategory":"Film & Video Production",
            "type":"Services"
        }
    ],
    "sg:phone":"+1 478 272 3251",
    "sg:postcode":"31021",
    "sg:province":"GA",
    "sg:tags":[
        "motion",
        "picture"
    ],
    "wof:name":"Bell Video Production",
    "wof:placetype":"venue"
},
  "geometry": {"coordinates":[-82.971138,32.547785],"type":"Point"}
}