{
  "type": "Feature",
  "properties": {
    "addr:full":"12280 Houze Rd Alpharetta GA 30004",
    "addr:housenumber":"12280",
    "addr:postcode":"30004",
    "addr:street":"Houze Rd",
    "iso:country":"US",
    "sg:address":"12280 Houze Rd",
    "sg:city":"Alpharetta",
    "sg:classifiers":[
        {
            "category":"Retail",
            "subcategory":"Laundry & Dry Cleaning",
            "type":"Services"
        }
    ],
    "sg:phone":"+1 770 475 4344",
    "sg:postcode":"30004",
    "sg:province":"GA",
    "wof:name":"Old Salem Cleaning Center",
    "wof:placetype":"venue"
},
  "geometry": {"coordinates":[-84.343597,34.0816],"type":"Point"}
}