{
  "type": "Feature",
  "properties": {
    "iso:country":"US",
    "sg:address":"1077 Juniper St 12th & Juniper St",
    "sg:city":"Atlanta",
    "sg:classifiers":[
        {
            "category":"Restaurant",
            "type":"Food & Drink"
        }
    ],
    "sg:phone":"+1 404 876 7925",
    "sg:postcode":"30309",
    "sg:province":"GA",
    "sg:tags":[
        "new",
        "american",
        "brunch",
        "breakfast"
    ],
    "sg:website":"www.einsteinsatlanta.com",
    "wof:name":"Einstein's",
    "wof:placetype":"venue"
},
  "geometry": {"coordinates":[-84.382267,33.783779],"type":"Point"}
}