{
  "type": "Feature",
  "properties": {
    "addr:full":"900 Harvey Branch Rd Danville GA 31017",
    "addr:housenumber":"900",
    "addr:postcode":"31017",
    "addr:street":"Harvey Branch Rd",
    "iso:country":"US",
    "sg:address":"900 Harvey Branch Rd",
    "sg:city":"Danville",
    "sg:classifiers":[
        {
            "category":"Retail",
            "subcategory":"Laundry & Dry Cleaning",
            "type":"Services"
        },
        {
            "category":"Building & Trades",
            "subcategory":"Cleaning & Sanitation",
            "type":"Services"
        }
    ],
    "sg:phone":"+1 478 461 3939",
    "sg:postcode":"31017",
    "sg:province":"GA",
    "sg:tags":[
        "cleaner",
        "house"
    ],
    "wof:name":"Crcs Cleaning Svc",
    "wof:placetype":"venue"
},
  "geometry": {"coordinates":[-83.299099,32.5549],"type":"Point"}
}