{
  "type": "Feature",
  "properties": {
    "addr:full":"210 Medical Blvd Stockbridge GA 30281",
    "addr:housenumber":"210",
    "addr:postcode":"30281",
    "addr:street":"Medical Blvd",
    "iso:country":"US",
    "sg:address":"210 Medical Blvd",
    "sg:city":"Stockbridge",
    "sg:classifiers":[
        {
            "category":"Health Services",
            "subcategory":"Doctor",
            "type":"Services"
        }
    ],
    "sg:phone":"+1 770 506 1800",
    "sg:postcode":"30281",
    "sg:province":"GA",
    "sg:website":"www.painmanagementspecialistsofa...",
    "wof:name":"Berinhout Randall MD",
    "wof:placetype":"venue"
},
  "geometry": {"coordinates":[-84.22489899999999,33.512501],"type":"Point"}
}