{
  "type": "Feature",
  "properties": {
    "addr:full":"1336 Columbia Dr Decatur GA 30032",
    "addr:housenumber":"1336",
    "addr:postcode":"30032",
    "addr:street":"Columbia Dr",
    "iso:country":"US",
    "sg:address":"1336 Columbia Dr",
    "sg:city":"Decatur",
    "sg:classifiers":[
        {
            "category":"Health Services",
            "subcategory":"Doctor",
            "type":"Services"
        }
    ],
    "sg:phone":"+1 404 284 3031",
    "sg:postcode":"30032",
    "sg:province":"GA",
    "sg:tags":[
        "medical"
    ],
    "wof:name":"Nagpal Satwant K MD",
    "wof:placetype":"venue"
},
  "geometry": {"coordinates":[-84.264017,33.750102],"type":"Point"}
}