{
  "type": "Feature",
  "properties": {
    "addr:full":"127 Big Oak Dr Canton GA 30115",
    "addr:housenumber":"127",
    "addr:postcode":"30115",
    "addr:street":"Big Oak Dr",
    "iso:country":"US",
    "sg:address":"127 Big Oak Dr",
    "sg:city":"Canton",
    "sg:classifiers":[
        {
            "category":"Insurance",
            "subcategory":"Insurance Agent",
            "type":"Services"
        },
        {
            "category":"Insurance",
            "subcategory":"Hazard Insurance",
            "type":"Services"
        },
        {
            "category":"Insurance",
            "subcategory":"Title Insurance",
            "type":"Services"
        },
        {
            "category":"Insurance",
            "subcategory":"Life Insurance",
            "type":"Services"
        }
    ],
    "sg:phone":"+1 770 479 3637",
    "sg:postcode":"30115",
    "sg:province":"GA",
    "sg:tags":[
        "business",
        "auto",
        "commercial",
        "homeowner",
        "motorcycle",
        "renter"
    ],
    "wof:name":"Allstate Insurance Company - Winfred Collins",
    "wof:placetype":"venue"
},
  "geometry": {"coordinates":[-84.446067,34.234047],"type":"Point"}
}