{
  "type": "Feature",
  "properties": {
    "addr:full":"2311 E Broad Ave Albany GA 31705",
    "addr:housenumber":"2311",
    "addr:postcode":"31705",
    "addr:street":"E Broad Ave",
    "iso:country":"US",
    "sg:address":"2311 E Broad Ave",
    "sg:city":"Albany",
    "sg:classifiers":[
        {
            "category":"Restaurant",
            "type":"Food & Drink"
        }
    ],
    "sg:phone":"+1 229 594 1497",
    "sg:postcode":"31705",
    "sg:province":"GA",
    "wof:name":"Pico de Gallo",
    "wof:placetype":"venue"
},
  "geometry": {"coordinates":[-84.095786,31.574692],"type":"Point"}
}