{
  "type": "Feature",
  "properties": {
    "addr:full":"7355 Oakley Industrial Blvd Union City GA 30291",
    "addr:housenumber":"7355",
    "addr:postcode":"30291",
    "addr:street":"Oakley Industrial Blvd",
    "iso:country":"US",
    "sg:address":"7355 Oakley Industrial Blvd",
    "sg:city":"Union City",
    "sg:classifiers":[
        {
            "category":"Building & Trades",
            "subcategory":"Plumbing",
            "type":"Services"
        }
    ],
    "sg:phone":"+1 770 306 2466",
    "sg:postcode":"30291",
    "sg:province":"GA",
    "sg:tags":[
        "contractor"
    ],
    "wof:name":"Stuart Southside Mechanical",
    "wof:placetype":"venue"
},
  "geometry": {"coordinates":[-84.54281,33.55185],"type":"Point"}
}