{
  "type": "Feature",
  "properties": {
    "iso:country":"US",
    "sg:address":"4664 Lawrenceville Hwy NW",
    "sg:city":"Lilburn",
    "sg:classifiers":[
        {
            "category":"Manufacturing",
            "subcategory":"Glass & Minerals",
            "type":"Manufacturing & Wholesale Goods"
        }
    ],
    "sg:phone":"+1 770 564 3730",
    "sg:postcode":"30047",
    "sg:province":"GA",
    "sg:tags":[
        "glass-block"
    ],
    "sg:website":"http://www.vitroamerica.com",
    "wof:name":"Vitro America",
    "wof:placetype":"venue"
},
  "geometry": {"coordinates":[-84.137514,33.898317],"type":"Point"}
}