{
  "type": "Feature",
  "properties": {
    "iso:country":"US",
    "sg:address":"1990 Ronald Reagan Blvd",
    "sg:city":"Cumming",
    "sg:classifiers":[
        {
            "category":"Wholesale",
            "subcategory":"Non-durable Goods",
            "type":"Manufacturing & Wholesale Goods"
        },
        {
            "category":"Shopping",
            "subcategory":"Department Store",
            "type":"Retail Goods"
        },
        {
            "category":"Building & Trades",
            "subcategory":"Cleaning & Sanitation",
            "type":"Services"
        },
        {
            "category":"Home & Garden",
            "subcategory":"Hardware",
            "type":"Retail Goods"
        }
    ],
    "sg:phone":"+1 770 889 0731",
    "sg:postcode":"30041",
    "sg:province":"GA",
    "sg:tags":[
        "cleaner",
        "supply",
        "supplies-wholesale",
        "equipment",
        "house",
        "janitor",
        "manufacturer"
    ],
    "wof:name":"Chem-Pro Supply Inc",
    "wof:placetype":"venue"
},
  "geometry": {"coordinates":[-84.141441,34.173828],"type":"Point"}
}