{
  "type": "Feature",
  "properties": {
    "iso:country":"US",
    "sg:address":"1590 Adamson Pkwy",
    "sg:city":"Morrow",
    "sg:classifiers":[
        {
            "category":"Professional",
            "subcategory":"Lawyer & Legal Services",
            "type":"Services"
        }
    ],
    "sg:phone":"+1 678 422 6639",
    "sg:postcode":"30260",
    "sg:province":"GA",
    "sg:tags":[
        "practice",
        "attorney",
        "criminal",
        "law"
    ],
    "wof:name":"Law Offices Of Charles M Evans And Associates Pc",
    "wof:placetype":"venue"
},
  "geometry": {"coordinates":[-84.338097,33.577339],"type":"Point"}
}