{
  "type": "Feature",
  "properties": {
    "addr:full":"2537 Lafayette Plaza Dr Albany GA 31707",
    "addr:housenumber":"2537",
    "addr:postcode":"31707",
    "addr:street":"Lafayette Plaza Dr",
    "iso:country":"US",
    "sg:address":"2537 Lafayette Plaza Dr",
    "sg:city":"Albany",
    "sg:classifiers":[
        {
            "category":"Professional",
            "subcategory":"Management & Consulting",
            "type":"Services"
        },
        {
            "category":"Professional",
            "subcategory":"Employment Agencies",
            "type":"Services"
        }
    ],
    "sg:phone":"+1 229 436 1580",
    "sg:postcode":"31707",
    "sg:province":"GA",
    "sg:tags":[
        "personnel",
        "supply",
        "help",
        "consultant"
    ],
    "wof:name":"Market Place Staffing Services",
    "wof:placetype":"venue"
},
  "geometry": {"coordinates":[-84.221414,31.611764],"type":"Point"}
}