{
  "type": "Feature",
  "properties": {
    "iso:country":"US",
    "sg:address":"1810 Mills B Lane Blvd",
    "sg:city":"Savannah",
    "sg:classifiers":[
        {
            "category":"Building & Trades",
            "subcategory":"Construction",
            "type":"Services"
        }
    ],
    "sg:phone":"+1 912 236 0099",
    "sg:postcode":"31405",
    "sg:province":"GA",
    "sg:tags":[
        "general",
        "contractor"
    ],
    "wof:name":"Pat Mathis Construction Co Inc",
    "wof:placetype":"venue"
},
  "geometry": {"coordinates":[-81.131074,32.051663],"type":"Point"}
}