{
  "type": "Feature",
  "properties": {
    "addr:full":"1638 Lovelace Rd Lincolnton GA 30817",
    "addr:housenumber":"1638",
    "addr:postcode":"30817",
    "addr:street":"Lovelace Rd",
    "iso:country":"US",
    "sg:address":"1638 Lovelace Rd",
    "sg:city":"Lincolnton",
    "sg:classifiers":[
        {
            "category":"Organizations",
            "subcategory":"Religious Organization",
            "type":"Services"
        }
    ],
    "sg:phone":"+1 706 359 5086",
    "sg:postcode":"30817",
    "sg:province":"GA",
    "wof:name":"Harmony Baptist Church",
    "wof:placetype":"venue"
},
  "geometry": {"coordinates":[-82.522035,33.785003],"type":"Point"}
}