{
  "type": "Feature",
  "properties": {
    "iso:country":"US",
    "sg:address":"142 Griswood Dr",
    "sg:city":"Augusta",
    "sg:classifiers":[
        {
            "category":"Home & Garden",
            "subcategory":"Building Materials",
            "type":"Retail Goods"
        }
    ],
    "sg:phone":"+1 706 860 2967",
    "sg:postcode":"30907",
    "sg:province":"GA",
    "wof:name":"Paper Dolls Wallpaper & Pntg",
    "wof:placetype":"venue"
},
  "geometry": {"coordinates":[-82.135035,33.511713],"type":"Point"}
}