{
  "type": "Feature",
  "properties": {
    "iso:country":"US",
    "sg:address":"7009 Williams Dr",
    "sg:city":"Douglasville",
    "sg:classifiers":[
        {
            "category":"Retail",
            "subcategory":"Repair Shop",
            "type":"Services"
        }
    ],
    "sg:phone":"+1 770 942 4289",
    "sg:postcode":"30135",
    "sg:province":"GA",
    "sg:tags":[
        "welding"
    ],
    "wof:name":"J C Welding Service",
    "wof:placetype":"venue"
},
  "geometry": {"coordinates":[-84.846934,33.615443],"type":"Point"}
}