{
  "type": "Feature",
  "properties": {
    "iso:country":"US",
    "sg:address":"209 Chambers Cove Dr",
    "sg:city":"Macon",
    "sg:classifiers":[
        {
            "category":"Professional",
            "type":"Services"
        }
    ],
    "sg:phone":"+1 478 781 4119",
    "sg:postcode":"31206",
    "sg:province":"GA",
    "wof:name":"Enchanting Affairs Inc",
    "wof:placetype":"venue"
},
  "geometry": {"coordinates":[-83.718583,32.804707],"type":"Point"}
}