{
  "type": "Feature",
  "properties": {
    "addr:full":"2614 Bridgewood Ln Snellville GA 30078",
    "addr:housenumber":"2614",
    "addr:postcode":"30078",
    "addr:street":"Bridgewood Ln",
    "iso:country":"US",
    "sg:address":"2614 Bridgewood Ln",
    "sg:city":"Snellville",
    "sg:classifiers":[
        {
            "category":"Retail",
            "subcategory":"Self-service Laundry",
            "type":"Services"
        }
    ],
    "sg:phone":"+1 770 979 6437",
    "sg:postcode":"30078",
    "sg:province":"GA",
    "sg:tags":[
        "coin"
    ],
    "wof:name":"Country Coin Laudry",
    "wof:placetype":"venue"
},
  "geometry": {"coordinates":[-84.03038100000001,33.872053],"type":"Point"}
}