{
  "type": "Feature",
  "properties": {
    "addr:full":"3635 Charlton Ives Dr Lilburn GA 30047",
    "addr:housenumber":"3635",
    "addr:postcode":"30047",
    "addr:street":"Charlton Ives Dr",
    "iso:country":"US",
    "sg:address":"3635 Charlton Ives Dr",
    "sg:city":"Lilburn",
    "sg:classifiers":[
        {
            "category":"Professional",
            "type":"Services"
        }
    ],
    "sg:phone":"+1 770 925 2879",
    "sg:postcode":"30047",
    "sg:province":"GA",
    "wof:name":"Bobbie Brech",
    "wof:placetype":"venue"
},
  "geometry": {"coordinates":[-84.11080800000001,33.915201],"type":"Point"}
}