{
  "type": "Feature",
  "properties": {
    "addr:full":"728 Bellemeade Ave NW Atlanta GA 30318",
    "addr:housenumber":"728",
    "addr:postcode":"30318",
    "addr:street":"Bellemeade Ave Nw",
    "iso:country":"US",
    "sg:address":"728 Bellemeade Ave NW",
    "sg:city":"Atlanta",
    "sg:classifiers":[
        {
            "category":"Professional",
            "subcategory":"Management & Consulting",
            "type":"Services"
        }
    ],
    "sg:phone":"+1 404 477 3156",
    "sg:postcode":"30318",
    "sg:province":"GA",
    "sg:tags":[
        "consultant",
        "energy",
        "conservation"
    ],
    "wof:name":"Lee's Resources",
    "wof:placetype":"venue"
},
  "geometry": {"coordinates":[-84.41243299999999,33.800288],"type":"Point"}
}