{
  "type": "Feature",
  "properties": {
    "addr:full":"3501 Johns Rd Tucker GA 30084",
    "addr:housenumber":"3501",
    "addr:postcode":"30084",
    "addr:street":"Johns Rd",
    "iso:country":"US",
    "sg:address":"3501 Johns Rd",
    "sg:city":"Tucker",
    "sg:classifiers":[
        {
            "category":"Professional",
            "subcategory":"Art Services",
            "type":"Services"
        }
    ],
    "sg:phone":"+1 770 939 7462",
    "sg:postcode":"30084",
    "sg:province":"GA",
    "sg:tags":[
        "commercial",
        "design"
    ],
    "wof:name":"Skyline Digital Graphic Art",
    "wof:placetype":"venue"
},
  "geometry": {"coordinates":[-84.247456,33.828156],"type":"Point"}
}