{
  "type": "Feature",
  "properties": {
    "addr:full":"134 Market Sq Cartersville GA 30120",
    "addr:housenumber":"134",
    "addr:postcode":"30120",
    "addr:street":"Market Sq",
    "iso:country":"US",
    "sg:address":"134 Market Sq",
    "sg:city":"Cartersville",
    "sg:classifiers":[
        {
            "category":"Professional",
            "subcategory":"Accounting & Tax Preparation",
            "type":"Services"
        }
    ],
    "sg:phone":"+1 770 383 3034",
    "sg:postcode":"30120",
    "sg:province":"GA",
    "sg:tags":[
        "return",
        "preparation-business"
    ],
    "wof:name":"Latino Income Tax Service",
    "wof:placetype":"venue"
},
  "geometry": {"coordinates":[-84.788726,34.175025],"type":"Point"}
}