{
  "type": "Feature",
  "properties": {
    "iso:country":"US",
    "sg:address":"11115 Rotherick Dr",
    "sg:city":"Alpharetta",
    "sg:classifiers":[
        {
            "category":"Building & Trades",
            "subcategory":"Equipment Rental",
            "type":"Services"
        }
    ],
    "sg:phone":"+1 770 521 9873",
    "sg:postcode":"30022",
    "sg:province":"GA",
    "sg:tags":[
        "leasing"
    ],
    "wof:name":"Phoenix Group USA",
    "wof:placetype":"venue"
},
  "geometry": {"coordinates":[-84.221537,34.05121],"type":"Point"}
}