{
  "type": "Feature",
  "properties": {
    "addr:full":"1811 Davie Cir SE Smyrna GA 30080",
    "addr:housenumber":"1811",
    "addr:postcode":"30080",
    "addr:street":"Davie Cir Se",
    "iso:country":"US",
    "sg:address":"1811 Davie Cir SE",
    "sg:city":"Smyrna",
    "sg:classifiers":[
        {
            "category":"Autos & Motor Vehicles",
            "subcategory":"Automobile Sales",
            "type":"Retail Goods"
        }
    ],
    "sg:phone":"+1 678 309 9564",
    "sg:postcode":"30080",
    "sg:province":"GA",
    "sg:tags":[
        "used"
    ],
    "wof:name":"Okehson International Inc",
    "wof:placetype":"venue"
},
  "geometry": {"coordinates":[-84.500208,33.892534],"type":"Point"}
}