{
  "type": "Feature",
  "properties": {
    "addr:full":"101 Murdock Ln Byron GA 31008",
    "addr:housenumber":"101",
    "addr:postcode":"31008",
    "addr:street":"Murdock Ln",
    "iso:country":"US",
    "sg:address":"101 Murdock Ln",
    "sg:city":"Byron",
    "sg:classifiers":[
        {
            "category":"Government",
            "subcategory":"Office",
            "type":"Public Place"
        }
    ],
    "sg:phone":"+1 478 956 2411",
    "sg:postcode":"31008",
    "sg:province":"GA",
    "sg:tags":[
        "village"
    ],
    "wof:name":"Byron Building Inspector",
    "wof:placetype":"venue"
},
  "geometry": {"coordinates":[-83.75646999999999,32.656538],"type":"Point"}
}