{
  "type": "Feature",
  "properties": {
    "addr:full":"8460 Hospital Dr Douglasville GA 30134",
    "addr:housenumber":"8460",
    "addr:postcode":"30134",
    "addr:street":"Hospital Dr",
    "iso:country":"US",
    "sg:address":"8460 Hospital Dr",
    "sg:city":"Douglasville",
    "sg:classifiers":[
        {
            "category":"Real Estate",
            "subcategory":"Real Estate Operator",
            "type":"Services"
        }
    ],
    "sg:phone":"+1 770 949 8988",
    "sg:postcode":"30134",
    "sg:province":"GA",
    "sg:tags":[
        "building",
        "apartment"
    ],
    "wof:name":"Oak Creek Apartments",
    "wof:placetype":"venue"
},
  "geometry": {"coordinates":[-84.730797,33.7495],"type":"Point"}
}