{
  "type": "Feature",
  "properties": {
    "iso:country":"US",
    "sg:address":"116 Old River Bridge Rd SE",
    "sg:city":"Milledgeville",
    "sg:classifiers":[
        {
            "category":"Building & Trades",
            "subcategory":"Construction",
            "type":"Services"
        }
    ],
    "sg:phone":"+1 478 452 2580",
    "sg:postcode":"31061",
    "sg:province":"GA",
    "sg:tags":[
        "excavating",
        "contractor"
    ],
    "wof:name":"Agee Construction Co",
    "wof:placetype":"venue"
},
  "geometry": {"coordinates":[-83.208303,33.08404],"type":"Point"}
}