{
  "type": "Feature",
  "properties": {
    "addr:full":"1138 W Taylor St Griffin GA 30223",
    "addr:housenumber":"1138",
    "addr:postcode":"30223",
    "addr:street":"W Taylor St",
    "iso:country":"US",
    "sg:address":"1138 W Taylor St",
    "sg:city":"Griffin",
    "sg:classifiers":[
        {
            "category":"Shopping",
            "subcategory":"Used Merchandise",
            "type":"Retail Goods"
        }
    ],
    "sg:phone":"+1 770 229 8060",
    "sg:postcode":"30223",
    "sg:province":"GA",
    "wof:name":"Pawn City",
    "wof:placetype":"venue"
},
  "geometry": {"coordinates":[-84.280158,33.247314],"type":"Point"}
}