{
  "type": "Feature",
  "properties": {
    "iso:country":"US",
    "sg:address":"5295 Stone Mountain Hwy",
    "sg:city":"Stone Mountain",
    "sg:classifiers":[
        {
            "category":"Shopping",
            "subcategory":"Crafts & Fabrics",
            "type":"Retail Goods"
        }
    ],
    "sg:phone":"+1 770 413 1800",
    "sg:postcode":"30087",
    "sg:province":"GA",
    "sg:tags":[
        "art",
        "supply"
    ],
    "wof:name":"Quilting Essentials",
    "wof:placetype":"venue"
},
  "geometry": {"coordinates":[-84.110703,33.823399],"type":"Point"}
}