{
  "type": "Feature",
  "properties": {
    "addr:full":"288 Valley Hart Rd Hartwell GA 30643",
    "addr:housenumber":"288",
    "addr:postcode":"30643",
    "addr:street":"Valley Hart Rd",
    "iso:country":"US",
    "sg:address":"288 Valley Hart Rd",
    "sg:city":"Hartwell",
    "sg:classifiers":[
        {
            "category":"Government",
            "subcategory":"Office",
            "type":"Public Place"
        }
    ],
    "sg:phone":"+1 706 376 7503",
    "sg:postcode":"30643",
    "sg:province":"GA",
    "sg:tags":[
        "parish",
        "government-county"
    ],
    "wof:name":"County Maintenance Shop",
    "wof:placetype":"venue"
},
  "geometry": {"coordinates":[-82.937377,34.31217],"type":"Point"}
}