{
  "type": "Feature",
  "properties": {
    "addr:full":"20 Hinson St Hazlehurst GA 31539",
    "addr:housenumber":"20",
    "addr:postcode":"31539",
    "addr:street":"Hinson St",
    "iso:country":"US",
    "sg:address":"20 Hinson St",
    "sg:city":"Hazlehurst",
    "sg:classifiers":[
        {
            "category":"Shopping",
            "subcategory":"Used Merchandise",
            "type":"Retail Goods"
        }
    ],
    "sg:phone":"+1 912 375 2590",
    "sg:postcode":"31539",
    "sg:province":"GA",
    "wof:name":"Tl Cs Collectibles",
    "wof:placetype":"venue"
},
  "geometry": {"coordinates":[-82.597837,31.865479],"type":"Point"}
}