{
  "type": "Feature",
  "properties": {
    "addr:full":"299 Grayson Hwy Lawrenceville GA 30045",
    "addr:housenumber":"299",
    "addr:postcode":"30045",
    "addr:street":"Grayson Hwy",
    "iso:country":"US",
    "sg:address":"299 Grayson Hwy",
    "sg:city":"Lawrenceville",
    "sg:classifiers":[
        {
            "category":"Restaurant",
            "type":"Food & Drink"
        }
    ],
    "sg:menulink":"http://www.allmenus.com/ga/lawrenceville/207168-sonic/menu/",
    "sg:phone":"+1 770 338 1416",
    "sg:postcode":"30045",
    "sg:province":"GA",
    "sg:tags":[
        "burger",
        "american"
    ],
    "wof:name":"Sonic",
    "wof:placetype":"venue"
},
  "geometry": {"coordinates":[-83.984815,33.944089],"type":"Point"}
}