{
  "type": "Feature",
  "properties": {
    "iso:country":"US",
    "sg:address":"309 1st St",
    "sg:city":"Carrollton",
    "sg:classifiers":[
        {
            "category":"Autos & Motor Vehicles",
            "subcategory":"Boat Sales",
            "type":"Retail Goods"
        }
    ],
    "sg:phone":"+1 770 832 3330",
    "sg:postcode":"30117",
    "sg:province":"GA",
    "sg:tags":[
        "equipment",
        "supply"
    ],
    "wof:name":"Georgia West Marine",
    "wof:placetype":"venue"
},
  "geometry": {"coordinates":[-85.09263300000001,33.581266],"type":"Point"}
}