{
  "type": "Feature",
  "properties": {
    "addr:full":"133 Davis Rd Augusta GA 30907",
    "addr:housenumber":"133",
    "addr:postcode":"30907",
    "addr:street":"Davis Rd",
    "iso:country":"US",
    "sg:address":"133 Davis Rd",
    "sg:city":"Augusta",
    "sg:classifiers":[
        {
            "category":"Building & Trades",
            "subcategory":"Electrical",
            "type":"Services"
        }
    ],
    "sg:phone":"+1 706 868 8103",
    "sg:postcode":"30907",
    "sg:province":"GA",
    "sg:tags":[
        "industrial",
        "electrician",
        "electric",
        "contractors-commercial"
    ],
    "sg:website":"http://www.robzapataselectric.com",
    "wof:name":"Rob Zapata's Electric",
    "wof:placetype":"venue"
},
  "geometry": {"coordinates":[-82.083353,33.507248],"type":"Point"}
}