{
  "type": "Feature",
  "properties": {
    "addr:full":"611 4th St Augusta GA 30901",
    "addr:housenumber":"611",
    "addr:postcode":"30901",
    "addr:street":"4Th St",
    "iso:country":"US",
    "sg:address":"611 4th St",
    "sg:city":"Augusta",
    "sg:classifiers":[
        {
            "category":"Insurance",
            "subcategory":"Hazard Insurance",
            "type":"Services"
        }
    ],
    "sg:phone":"+1 706 722 3789",
    "sg:postcode":"30901",
    "sg:province":"GA",
    "sg:tags":[
        "bond"
    ],
    "wof:name":"Anytime Bell Bonding",
    "wof:placetype":"venue"
},
  "geometry": {"coordinates":[-81.958444,33.467784],"type":"Point"}
}