{
  "type": "Feature",
  "properties": {
    "addr:full":"420 Peach Dr Mcdonough GA 30253",
    "addr:housenumber":"420",
    "addr:postcode":"30253",
    "addr:street":"Peach Dr",
    "iso:country":"US",
    "sg:address":"420 Peach Dr",
    "sg:city":"Mcdonough",
    "sg:classifiers":[
        {
            "category":"Home & Garden",
            "subcategory":"Building Materials",
            "type":"Retail Goods"
        },
        {
            "category":"Building & Trades",
            "subcategory":"Construction",
            "type":"Services"
        }
    ],
    "sg:phone":"+1 770 315 6681",
    "sg:postcode":"30253",
    "sg:province":"GA",
    "sg:tags":[
        "concrete",
        "staining",
        "contractor"
    ],
    "wof:name":"M & S Concrete, Inc.",
    "wof:placetype":"venue"
},
  "geometry": {"coordinates":[-84.19750999999999,33.494714],"type":"Point"}
}