{
  "type": "Feature",
  "properties": {
    "addr:full":"3830 New Macland Rd Powder Springs GA 30127",
    "addr:housenumber":"3830",
    "addr:postcode":"30127",
    "addr:street":"New Macland Rd",
    "iso:country":"US",
    "sg:address":"3830 New Macland Rd",
    "sg:city":"Powder Springs",
    "sg:classifiers":[
        {
            "category":"Shopping",
            "subcategory":"Computers & Home Electronics",
            "type":"Retail Goods"
        }
    ],
    "sg:phone":"+1 770 439 3030",
    "sg:postcode":"30127",
    "sg:province":"GA",
    "sg:tags":[
        "equipment",
        "dealer"
    ],
    "wof:name":"Paulding Computers",
    "wof:placetype":"venue"
},
  "geometry": {"coordinates":[-84.675831,33.859581],"type":"Point"}
}