{
  "type": "Feature",
  "properties": {
    "addr:full":"208 Sabrina Ct Woodstock GA 30188",
    "addr:housenumber":"208",
    "addr:postcode":"30188",
    "addr:street":"Sabrina Ct",
    "iso:country":"US",
    "sg:address":"208 Sabrina Ct",
    "sg:city":"Woodstock",
    "sg:classifiers":[
        {
            "category":"Shopping",
            "subcategory":"Computers & Home Electronics",
            "type":"Retail Goods"
        }
    ],
    "sg:phone":"+1 770 591 0590",
    "sg:postcode":"30188",
    "sg:province":"GA",
    "sg:tags":[
        "electronic"
    ],
    "wof:name":"Mainstream Systems Inc",
    "wof:placetype":"venue"
},
  "geometry": {"coordinates":[-84.484318,34.107404],"type":"Point"}
}