{
  "type": "Feature",
  "properties": {
    "iso:country":"US",
    "sg:address":"6925 Polo Dr",
    "sg:city":"Cumming",
    "sg:classifiers":[
        {
            "category":"Real Estate",
            "subcategory":"Real Estate Agent",
            "type":"Services"
        }
    ],
    "sg:phone":"+1 770 886 3736",
    "sg:postcode":"30040",
    "sg:province":"GA",
    "wof:name":"Pilgrim Property",
    "wof:placetype":"venue"
},
  "geometry": {"coordinates":[-84.20439,34.186742],"type":"Point"}
}