{
  "type": "Feature",
  "properties": {
    "iso:country":"US",
    "sg:address":"107 Schmitt Rd",
    "sg:city":"Rossville",
    "sg:classifiers":[
        {
            "category":"Personal",
            "type":"Services"
        }
    ],
    "sg:phone":"+1 706 866 9356",
    "sg:postcode":"30741",
    "sg:province":"GA",
    "wof:name":"VIP Spa",
    "wof:placetype":"venue"
},
  "geometry": {"coordinates":[-85.341475,34.924563],"type":"Point"}
}