{
  "type": "Feature",
  "properties": {
    "iso:country":"US",
    "sg:address":"1958 Walton Woods Cir",
    "sg:city":"Tucker",
    "sg:classifiers":[
        {
            "category":"Professional",
            "subcategory":"Employment Agencies",
            "type":"Services"
        }
    ],
    "sg:phone":"+1 770 414 1234",
    "sg:postcode":"30084",
    "sg:province":"GA",
    "sg:website":"www.cartwrightmorris.com",
    "wof:name":"Cartwright Morris & Associates",
    "wof:placetype":"venue"
},
  "geometry": {"coordinates":[-84.22989699999999,33.8395],"type":"Point"}
}