{
  "type": "Feature",
  "properties": {
    "addr:full":"1012 Calhoun Ave Rome GA 30161",
    "addr:housenumber":"1012",
    "addr:postcode":"ga 30161",
    "addr:street":"Calhoun Ave",
    "iso:country":"US",
    "sg:address":"1012 Calhoun Ave",
    "sg:city":"Rome",
    "sg:classifiers":[
        {
            "category":"Retail",
            "subcategory":"Auto Repair",
            "type":"Services"
        }
    ],
    "sg:phone":"+1 706 295 2888",
    "sg:postcode":"30161",
    "sg:province":"GA",
    "sg:tags":[
        "automotive"
    ],
    "wof:name":"Rabbits Towing Service",
    "wof:placetype":"venue"
},
  "geometry": {"coordinates":[-85.143044,34.270091],"type":"Point"}
}