{
  "type": "Feature",
  "properties": {
    "addr:full":"112 N Gross Rd Kingsland GA 31548",
    "addr:housenumber":"112",
    "addr:postcode":"31548",
    "addr:street":"N Gross Rd",
    "iso:country":"US",
    "sg:address":"112 N Gross Rd",
    "sg:city":"Kingsland",
    "sg:classifiers":[
        {
            "category":"Coffee & Tea",
            "type":"Food & Drink"
        },
        {
            "category":"Restaurant",
            "type":"Food & Drink"
        }
    ],
    "sg:phone":"+1 912 882 6300",
    "sg:postcode":"31548",
    "sg:province":"GA",
    "sg:tags":[
        "espresso"
    ],
    "wof:name":"Mango's Cafe",
    "wof:placetype":"venue"
},
  "geometry": {"coordinates":[-81.64536200000001,30.788258],"type":"Point"}
}