{
  "type": "Feature",
  "properties": {
    "addr:full":"5502 Peachtree Rd Chamblee GA 30341",
    "addr:housenumber":"5502",
    "addr:postcode":"30341",
    "addr:street":"Peachtree Rd",
    "iso:country":"US",
    "sg:address":"5502 Peachtree Rd",
    "sg:city":"Chamblee",
    "sg:classifiers":[
        {
            "category":"Professional",
            "subcategory":"Advertising",
            "type":"Services"
        }
    ],
    "sg:phone":"+1 770 451 0452",
    "sg:postcode":"30341",
    "sg:province":"GA",
    "sg:tags":[
        "counselor"
    ],
    "wof:name":"Show Me Atlanta",
    "wof:placetype":"venue"
},
  "geometry": {"coordinates":[-84.29607300000001,33.895194],"type":"Point"}
}