{
  "type": "Feature",
  "properties": {
    "iso:country":"US",
    "sg:address":"4830 Pinto Dr",
    "sg:city":"Albany",
    "sg:classifiers":[
        {
            "category":"Building & Trades",
            "subcategory":"Construction",
            "type":"Services"
        }
    ],
    "sg:phone":"+1 229 888 1874",
    "sg:postcode":"31705",
    "sg:province":"GA",
    "sg:tags":[
        "contractor"
    ],
    "wof:name":"Robert Edwards Contractor",
    "wof:placetype":"venue"
},
  "geometry": {"coordinates":[-84.10029299999999,31.461603],"type":"Point"}
}