{
  "type": "Feature",
  "properties": {
    "addr:full":"1200 Memorial Dr Dalton GA 30720",
    "addr:housenumber":"1200",
    "addr:postcode":"30720",
    "addr:street":"Memorial Dr",
    "iso:country":"US",
    "sg:address":"1200 Memorial Dr",
    "sg:city":"Dalton",
    "sg:classifiers":[
        {
            "category":"Banks & Credit Unions",
            "subcategory":"Bank",
            "type":"Services"
        }
    ],
    "sg:phone":"+1 706 272 6196",
    "sg:postcode":"30720",
    "sg:province":"GA",
    "sg:tags":[
        "federal"
    ],
    "wof:name":"Hmc Employees Federal Cu",
    "wof:placetype":"venue"
},
  "geometry": {"coordinates":[-84.985928,34.788852],"type":"Point"}
}