{
  "type": "Feature",
  "properties": {
    "iso:country":"US",
    "sg:address":"1144 Avondale Ave SE",
    "sg:city":"Atlanta",
    "sg:classifiers":[
        {
            "category":"Organizations",
            "subcategory":"Non-profit Organization",
            "type":"Services"
        }
    ],
    "sg:phone":"+1 404 622 9107",
    "sg:postcode":"30312",
    "sg:province":"GA",
    "wof:name":"Fulton County Voiture",
    "wof:placetype":"venue"
},
  "geometry": {"coordinates":[-84.363316,33.72262],"type":"Point"}
}