{
  "type": "Feature",
  "properties": {
    "addr:full":"689 Robinhood Trl Gainesville GA 30501",
    "addr:housenumber":"689",
    "addr:postcode":"30501",
    "addr:street":"Robinhood Trl",
    "iso:country":"US",
    "sg:address":"689 Robinhood Trl",
    "sg:city":"Gainesville",
    "sg:classifiers":[
        {
            "category":"Banks & Credit Unions",
            "subcategory":"Financial Services",
            "type":"Services"
        }
    ],
    "sg:phone":"+1 770 536 1058",
    "sg:postcode":"30501",
    "sg:province":"GA",
    "sg:tags":[
        "trust",
        "management"
    ],
    "wof:name":"Cox Properties Ltd LP",
    "wof:placetype":"venue"
},
  "geometry": {"coordinates":[-83.810744,34.31678],"type":"Point"}
}