{
  "type": "Feature",
  "properties": {
    "addr:full":"7992 State Rte 85 Riverdale GA 30274",
    "addr:housenumber":"7992",
    "addr:postcode":"30274",
    "addr:street":"State Rte 85",
    "iso:country":"US",
    "sg:address":"7992 State Rte 85",
    "sg:city":"Riverdale",
    "sg:classifiers":[
        {
            "category":"Professional",
            "type":"Services"
        }
    ],
    "sg:phone":"+1 770 471 6473",
    "sg:postcode":"30274",
    "sg:province":"GA",
    "sg:tags":[
        "establishment"
    ],
    "wof:name":"Texmex",
    "wof:placetype":"venue"
},
  "geometry": {"coordinates":[-84.418019,33.536675],"type":"Point"}
}