{
  "type": "Feature",
  "properties": {
    "iso:country":"US",
    "sg:address":"1100 N Blair Bridge Rd",
    "sg:city":"Austell",
    "sg:classifiers":[
        {
            "category":"Travel",
            "subcategory":"Hotels & Motels",
            "type":"Entertainment"
        }
    ],
    "sg:phone":"+1 800 424 6423",
    "sg:postcode":"30168",
    "sg:province":"GA",
    "sg:website":"http://www.qualityinn.com/hotel-austell-georgia-GA628?promo=yplocal",
    "wof:name":"Quality Inn & Suites at Six Flags Austell",
    "wof:placetype":"venue"
},
  "geometry": {"coordinates":[-84.60685700000001,33.779316],"type":"Point"}
}