{
  "type": "Feature",
  "properties": {
    "addr:full":"4075 Marietta Hwy Dallas GA 30157",
    "addr:housenumber":"4075",
    "addr:postcode":"30157",
    "addr:street":"Marietta Hwy",
    "iso:country":"US",
    "sg:address":"4075 Marietta Hwy",
    "sg:city":"Dallas",
    "sg:classifiers":[
        {
            "category":"Health Services",
            "subcategory":"Optometrist",
            "type":"Services"
        }
    ],
    "sg:phone":"+1 770 445 9866",
    "sg:postcode":"30157",
    "sg:province":"GA",
    "sg:tags":[
        "ophthalmologist"
    ],
    "wof:name":"Scott Eye Clinic",
    "wof:placetype":"venue"
},
  "geometry": {"coordinates":[-84.72519699999999,33.934399],"type":"Point"}
}