{
  "type": "Feature",
  "properties": {
    "iso:country":"US",
    "sg:address":"609 Court St",
    "sg:city":"Homerville",
    "sg:classifiers":[
        {
            "category":"Manufacturing",
            "subcategory":"Tools & Machinery",
            "type":"Manufacturing & Wholesale Goods"
        }
    ],
    "sg:phone":"+1 912 487 2951",
    "sg:postcode":"31634",
    "sg:province":"GA",
    "sg:tags":[
        "industrial",
        "mfg"
    ],
    "wof:name":"Smith Tool & Die",
    "wof:placetype":"venue"
},
  "geometry": {"coordinates":[-82.75259699999999,31.043623],"type":"Point"}
}