{
  "type": "Feature",
  "properties": {
    "iso:country":"US",
    "sg:address":"2933 Pleasant Valley Dr",
    "sg:city":"Atlanta",
    "sg:classifiers":[
        {
            "category":"Home & Garden",
            "subcategory":"Hardware",
            "type":"Retail Goods"
        }
    ],
    "sg:phone":"+1 678 205 2899",
    "sg:postcode":"30340",
    "sg:province":"GA",
    "sg:tags":[
        "store"
    ],
    "wof:name":"Blackjack Glass & Hardware",
    "wof:placetype":"venue"
},
  "geometry": {"coordinates":[-84.265761,33.906628],"type":"Point"}
}