{
  "type": "Feature",
  "properties": {
    "iso:country":"US",
    "sg:address":"132 N Hill St",
    "sg:city":"Griffin",
    "sg:classifiers":[
        {
            "category":"Government",
            "subcategory":"Office",
            "type":"Public Place"
        }
    ],
    "sg:phone":"+1 770 229 6400",
    "sg:postcode":"30223",
    "sg:province":"GA",
    "sg:tags":[
        "city"
    ],
    "wof:name":"Griffin City Hall",
    "wof:placetype":"venue"
},
  "geometry": {"coordinates":[-84.26361199999999,33.25282],"type":"Point"}
}