{
  "type": "Feature",
  "properties": {
    "addr:full":"5380 Jonesboro Rd Morrow GA 30260",
    "addr:housenumber":"5380",
    "addr:postcode":"30260",
    "addr:street":"Jonesboro Rd",
    "iso:country":"US",
    "sg:address":"5380 Jonesboro Rd",
    "sg:city":"Morrow",
    "sg:classifiers":[
        {
            "category":"Food & Beverages",
            "subcategory":"Ethnic Foods",
            "type":"Retail Goods"
        }
    ],
    "sg:phone":"+1 404 362 0013",
    "sg:postcode":"30260",
    "sg:province":"GA",
    "sg:tags":[
        "grocers-ethnic"
    ],
    "wof:name":"International Farmers Market",
    "wof:placetype":"venue"
},
  "geometry": {"coordinates":[-84.344696,33.608397],"type":"Point"}
}