{
  "type": "Feature",
  "properties": {
    "addr:full":"3480 Mill Bridge Dr Marietta GA 30062",
    "addr:housenumber":"3480",
    "addr:postcode":"30062",
    "addr:street":"Mill Bridge Dr",
    "iso:country":"US",
    "sg:address":"3480 Mill Bridge Dr",
    "sg:city":"Marietta",
    "sg:classifiers":[
        {
            "category":"Professional",
            "subcategory":"Computer Services",
            "type":"Services"
        }
    ],
    "sg:phone":"+1 770 578 7629",
    "sg:postcode":"30062",
    "sg:province":"GA",
    "sg:tags":[
        "consulting"
    ],
    "wof:name":"Deb Consulting",
    "wof:placetype":"venue"
},
  "geometry": {"coordinates":[-84.450177,33.994077],"type":"Point"}
}