{
  "type": "Feature",
  "properties": {
    "addr:full":"101 Industrial Park Blvd Warner Robins GA 31088",
    "addr:housenumber":"101",
    "addr:postcode":"31088",
    "addr:street":"Industrial Park Blvd",
    "iso:country":"US",
    "sg:address":"101 Industrial Park Blvd",
    "sg:city":"Warner Robins",
    "sg:classifiers":[
        {
            "category":"Manufacturing",
            "subcategory":"Electronics",
            "type":"Manufacturing & Wholesale Goods"
        }
    ],
    "sg:phone":"+1 478 929 2651",
    "sg:postcode":"31088",
    "sg:province":"GA",
    "sg:tags":[
        "equipment",
        "mfg",
        "printed",
        "communication"
    ],
    "wof:name":"Warner Rbins Rgnal Support Ctr",
    "wof:placetype":"venue"
},
  "geometry": {"coordinates":[-83.58781500000001,32.582465],"type":"Point"}
}