{
  "type": "Feature",
  "properties": {
    "addr:full":"6258 Silver Spur Dr Lithonia GA 30058",
    "addr:housenumber":"6258",
    "addr:postcode":"30058",
    "addr:street":"Silver Spur Dr",
    "iso:country":"US",
    "sg:address":"6258 Silver Spur Dr",
    "sg:city":"Lithonia",
    "sg:classifiers":[
        {
            "category":"Shopping",
            "subcategory":"Florist",
            "type":"Retail Goods"
        }
    ],
    "sg:phone":"+1 404 451 4550",
    "sg:postcode":"30058",
    "sg:province":"GA",
    "wof:name":"Thank Yous & I Dos Flowers",
    "wof:placetype":"venue"
},
  "geometry": {"coordinates":[-84.134221,33.756718],"type":"Point"}
}