{
  "type": "Feature",
  "properties": {
    "addr:full":"108 Catoosa St Ringgold GA 30741",
    "addr:housenumber":"108",
    "addr:postcode":"30741",
    "addr:street":"Catoosa St",
    "iso:country":"US",
    "sg:address":"108 Catoosa St",
    "sg:city":"Ringgold",
    "sg:classifiers":[
        {
            "category":"Education",
            "subcategory":"Library",
            "type":"Public Place"
        }
    ],
    "sg:phone":"+1 706 965 3600",
    "sg:postcode":"30741",
    "sg:province":"GA",
    "sg:website":"www.ngrl.org",
    "wof:name":"Catoosa County Public Library",
    "wof:placetype":"venue"
},
  "geometry": {"coordinates":[-85.270285,34.974039],"type":"Point"}
}