{
  "type": "Feature",
  "properties": {
    "addr:full":"5223 Riverside Dr Macon GA 31210",
    "addr:housenumber":"5223",
    "addr:postcode":"31210",
    "addr:street":"Riverside Dr",
    "iso:country":"US",
    "sg:address":"5223 Riverside Dr",
    "sg:city":"Macon",
    "sg:classifiers":[
        {
            "category":"Professional",
            "subcategory":"Engineering",
            "type":"Services"
        }
    ],
    "sg:phone":"+1 478 745 7378",
    "sg:postcode":"31210",
    "sg:province":"GA",
    "sg:tags":[
        "engineer"
    ],
    "wof:name":"Hulsey Mc Cormick & Wallace",
    "wof:placetype":"venue"
},
  "geometry": {"coordinates":[-83.713554,32.929464],"type":"Point"}
}