{
  "type": "Feature",
  "properties": {
    "addr:full":"377 River Run Trl Cornelia GA 30531",
    "addr:housenumber":"377",
    "addr:postcode":"30531",
    "addr:street":"River Run Trl",
    "iso:country":"US",
    "sg:address":"377 River Run Trl",
    "sg:city":"Cornelia",
    "sg:classifiers":[
        {
            "category":"Building & Trades",
            "subcategory":"Construction",
            "type":"Services"
        }
    ],
    "sg:phone":"+1 706 776 8431",
    "sg:postcode":"30531",
    "sg:province":"GA",
    "sg:tags":[
        "floor",
        "laying",
        "contractor"
    ],
    "wof:name":"Duane Gleason",
    "wof:placetype":"venue"
},
  "geometry": {"coordinates":[-83.65612400000001,34.514732],"type":"Point"}
}