{
  "type": "Feature",
  "properties": {
    "iso:country":"US",
    "sg:address":"245 Durand Rd",
    "sg:city":"Lagrange",
    "sg:classifiers":[
        {
            "category":"Education",
            "subcategory":"Dance Studio",
            "type":"Public Place"
        }
    ],
    "sg:phone":"+1 706 812 1039",
    "sg:postcode":"30241",
    "sg:province":"GA",
    "sg:tags":[
        "instruction",
        "dancing"
    ],
    "wof:name":"Stars & Stripes",
    "wof:placetype":"venue"
},
  "geometry": {"coordinates":[-84.99174600000001,33.033076],"type":"Point"}
}