{
  "type": "Feature",
  "properties": {
    "addr:full":"5821 Nancy Ave Columbus GA 31909",
    "addr:housenumber":"5821",
    "addr:postcode":"31909",
    "addr:street":"Nancy Ave",
    "iso:country":"US",
    "sg:address":"5821 Nancy Ave",
    "sg:city":"Columbus",
    "sg:classifiers":[
        {
            "category":"Building & Trades",
            "subcategory":"Construction",
            "type":"Services"
        }
    ],
    "sg:phone":"+1 706 682 2314",
    "sg:postcode":"31909",
    "sg:province":"GA",
    "sg:tags":[
        "home",
        "improvement"
    ],
    "wof:name":"Professional Pest Control Inc",
    "wof:placetype":"venue"
},
  "geometry": {"coordinates":[-84.92506400000001,32.527397],"type":"Point"}
}