{
  "type": "Feature",
  "properties": {
    "addr:full":"1001 US Hwy 19 Bus Griffin GA 30223",
    "addr:housenumber":"1001",
    "addr:postcode":"30223",
    "addr:street":"Us Hwy 19 Bus",
    "iso:country":"US",
    "sg:address":"1001 US Hwy 19 Bus",
    "sg:city":"Griffin",
    "sg:classifiers":[
        {
            "category":"Government",
            "subcategory":"Office",
            "type":"Public Place"
        }
    ],
    "sg:phone":"+1 770 228 7337",
    "sg:postcode":"30223",
    "sg:province":"GA",
    "wof:name":"Georgia Dept Of Transportation",
    "wof:placetype":"venue"
},
  "geometry": {"coordinates":[-84.27935600000001,33.247473],"type":"Point"}
}