{
  "type": "Feature",
  "properties": {
    "addr:full":"100 S Hutchinson Ave Adel GA 31620",
    "addr:housenumber":"100",
    "addr:postcode":"31620",
    "addr:street":"S Hutchinson Ave",
    "iso:country":"US",
    "sg:address":"100 S Hutchinson Ave",
    "sg:city":"Adel",
    "sg:classifiers":[
        {
            "category":"Organizations",
            "subcategory":"Professional Association",
            "type":"Services"
        }
    ],
    "sg:phone":"+1 229 896 2281",
    "sg:postcode":"31620",
    "sg:province":"GA",
    "sg:tags":[
        "business"
    ],
    "wof:name":"Adel-Cook Cnty Chmber Commerce",
    "wof:placetype":"venue"
},
  "geometry": {"coordinates":[-83.42335799999999,31.137031],"type":"Point"}
}