{
  "type": "Feature",
  "properties": {
    "addr:full":"22 Lenox Pointe NE Ste B Atlanta GA 30324",
    "addr:housenumber":"22",
    "addr:postcode":"30324",
    "addr:street":"Lenox Pointe Ne Ste B",
    "iso:country":"US",
    "sg:address":"22 Lenox Pointe NE Ste B",
    "sg:city":"Atlanta",
    "sg:classifiers":[
        {
            "category":"Health Services",
            "subcategory":"Doctor",
            "type":"Services"
        }
    ],
    "sg:phone":"+1 404 325 0100",
    "sg:postcode":"30324",
    "sg:province":"GA",
    "sg:tags":[
        "psychiatrist"
    ],
    "wof:name":"Eubanks A Benjamin MD",
    "wof:placetype":"venue"
},
  "geometry": {"coordinates":[-84.355248,33.825926],"type":"Point"}
}