{
  "type": "Feature",
  "properties": {
    "iso:country":"US",
    "sg:address":"3005 Chamblee Tucker Rd",
    "sg:city":"Atlanta",
    "sg:classifiers":[
        {
            "category":"Professional",
            "subcategory":"Business Services",
            "type":"Services"
        }
    ],
    "sg:phone":"+1 770 488 5815",
    "sg:postcode":"30341",
    "sg:province":"GA",
    "sg:tags":[
        "medical",
        "administration"
    ],
    "wof:name":"Office On Smoking & Health",
    "wof:placetype":"venue"
},
  "geometry": {"coordinates":[-84.268674,33.878244],"type":"Point"}
}