{
  "type": "Feature",
  "properties": {
    "iso:country":"US",
    "sg:address":"9148 Hwy 278 NE",
    "sg:city":"Covington",
    "sg:classifiers":[
        {
            "category":"Cinema",
            "subcategory":"Movie Rental",
            "type":"Entertainment"
        }
    ],
    "sg:phone":"+1 770 787 4885",
    "sg:postcode":"30014",
    "sg:province":"GA",
    "sg:tags":[
        "video",
        "tape"
    ],
    "wof:name":"Video Update Inc",
    "wof:placetype":"venue"
},
  "geometry": {"coordinates":[-83.833488,33.599299],"type":"Point"}
}