{
  "type": "Feature",
  "properties": {
    "iso:country":"US",
    "sg:address":"1524 Willingham Dr",
    "sg:city":"Atlanta",
    "sg:classifiers":[
        {
            "category":"Manufacturing",
            "subcategory":"Chemicals & Compounds",
            "type":"Manufacturing & Wholesale Goods"
        }
    ],
    "sg:phone":"+1 404 761 7524",
    "sg:postcode":"30344",
    "sg:province":"GA",
    "sg:tags":[
        "paint",
        "mfg"
    ],
    "wof:name":"Pride Paint Inc",
    "wof:placetype":"venue"
},
  "geometry": {"coordinates":[-84.437748,33.668297],"type":"Point"}
}