{
  "type": "Feature",
  "properties": {
    "addr:full":"571 Kilgo Cir Atlanta GA 30322",
    "addr:housenumber":"571",
    "addr:postcode":"30322",
    "addr:street":"Kilgo Cir",
    "iso:country":"US",
    "sg:address":"571 Kilgo Cir",
    "sg:city":"Atlanta",
    "sg:classifiers":[
        {
            "category":"Shopping",
            "subcategory":"Books",
            "type":"Retail Goods"
        }
    ],
    "sg:phone":"+1 404 727 0509",
    "sg:postcode":"30322",
    "sg:province":"GA",
    "wof:name":"Micheal C Crlos Mseum Bookshop",
    "wof:placetype":"venue"
},
  "geometry": {"coordinates":[-84.325087,33.789919],"type":"Point"}
}