{
  "type": "Feature",
  "properties": {
    "addr:full":"4469 WPA Rd Blackshear GA 31516",
    "addr:housenumber":"4469",
    "addr:postcode":"31516",
    "addr:street":"Wpa Rd",
    "iso:country":"US",
    "sg:address":"4469 WPA Rd",
    "sg:city":"Blackshear",
    "sg:classifiers":[
        {
            "category":"Building & Trades",
            "subcategory":"Cleaning & Sanitation",
            "type":"Services"
        }
    ],
    "sg:phone":"+1 912 647 2955",
    "sg:postcode":"31516",
    "sg:province":"GA",
    "sg:tags":[
        "chemical"
    ],
    "wof:name":"Nu-Chem Industries Inc",
    "wof:placetype":"venue"
},
  "geometry": {"coordinates":[-82.18056799999999,31.389485],"type":"Point"}
}