{
  "type": "Feature",
  "properties": {
    "addr:full":"120 W Taylor St Griffin GA 30223",
    "addr:housenumber":"120",
    "addr:postcode":"30223",
    "addr:street":"W Taylor St",
    "iso:country":"US",
    "sg:address":"120 W Taylor St",
    "sg:city":"Griffin",
    "sg:classifiers":[
        {
            "category":"Personal",
            "type":"Services"
        },
        {
            "category":"Sports & Exercise",
            "subcategory":"Gym",
            "type":"Entertainment"
        },
        {
            "category":"Health Services",
            "subcategory":"Health Practitioner",
            "type":"Services"
        },
        {
            "category":"Arena",
            "subcategory":"Sports Club",
            "type":"Entertainment"
        }
    ],
    "sg:phone":"+1 800 615 7352",
    "sg:postcode":"30223",
    "sg:province":"GA",
    "sg:tags":[
        "trainer",
        "control",
        "weight",
        "consultant",
        "program",
        "fitness",
        "physical"
    ],
    "sg:website":"http://atlanta.citysearch.com/profile/external/37650111/griffin_ga/curves.html?publisher=yellowpages&reference_id=1&placement=ypwebsitemip",
    "wof:name":"Curves",
    "wof:placetype":"venue"
},
  "geometry": {"coordinates":[-84.264717,33.24713],"type":"Point"}
}