{
  "type": "Feature",
  "properties": {
    "addr:full":"2799 Holly Springs Rd NE Marietta GA 30062",
    "addr:housenumber":"2799",
    "addr:postcode":"30062",
    "addr:street":"Holly Springs Rd Ne",
    "iso:country":"US",
    "sg:address":"2799 Holly Springs Rd NE",
    "sg:city":"Marietta",
    "sg:classifiers":[
        {
            "category":"Place Of Worship",
            "subcategory":"Church",
            "type":"Public Place"
        },
        {
            "category":"Place Of Worship",
            "type":"Public Place"
        },
        {
            "category":"Organizations",
            "subcategory":"Religious Organization",
            "type":"Services"
        }
    ],
    "sg:phone":"+1 770 578 1533",
    "sg:postcode":"30062",
    "sg:province":"GA",
    "sg:tags":[
        "universalist",
        "churches-unitarian"
    ],
    "sg:website":"http://www.emersonuu.org",
    "wof:name":"Emerson Unitarian Universalist",
    "wof:placetype":"venue"
},
  "geometry": {"coordinates":[-84.471001,34.0172],"type":"Point"}
}