{
  "type": "Feature",
  "properties": {
    "iso:country":"US",
    "sg:address":"3261 Manor Ridge",
    "sg:city":"Gainesville",
    "sg:classifiers":[
        {
            "category":"Utilities",
            "subcategory":"Telephone",
            "type":"Services"
        }
    ],
    "sg:phone":"+1 678 450 6879",
    "sg:postcode":"30506",
    "sg:province":"GA",
    "sg:tags":[
        "telecommunication"
    ],
    "wof:name":"A T & T",
    "wof:placetype":"venue"
},
  "geometry": {"coordinates":[-83.92649299999999,34.333653],"type":"Point"}
}