{
  "type": "Feature",
  "properties": {
    "addr:full":"204 S Smith St Sandersville GA 31082",
    "addr:housenumber":"204",
    "addr:postcode":"31082",
    "addr:street":"S Smith St",
    "iso:country":"US",
    "sg:address":"204 S Smith St",
    "sg:city":"Sandersville",
    "sg:classifiers":[
        {
            "category":"Organizations",
            "subcategory":"Non-profit Organization",
            "type":"Services"
        }
    ],
    "sg:phone":"+1 478 552 1387",
    "sg:postcode":"31082",
    "sg:province":"GA",
    "sg:tags":[
        "social"
    ],
    "wof:name":"First Chrstn Chrch Mission Str",
    "wof:placetype":"venue"
},
  "geometry": {"coordinates":[-82.808476,32.980823],"type":"Point"}
}