{
  "type": "Feature",
  "properties": {
    "iso:country":"US",
    "sg:address":"703 Rowland Springs Rd",
    "sg:city":"Cartersville",
    "sg:classifiers":[
        {
            "category":"Building & Trades",
            "subcategory":"Electrical",
            "type":"Services"
        }
    ],
    "sg:phone":"+1 770 382 0217",
    "sg:postcode":"30121",
    "sg:province":"GA",
    "sg:tags":[
        "electrical",
        "contractor"
    ],
    "wof:name":"Daniel L Smith Electric",
    "wof:placetype":"venue"
},
  "geometry": {"coordinates":[-84.78446,34.182843],"type":"Point"}
}