{
  "type": "Feature",
  "properties": {
    "iso:country":"US",
    "sg:address":"1083 Oakdale Rd NE",
    "sg:city":"Atlanta",
    "sg:classifiers":[
        {
            "category":"Professional",
            "type":"Services"
        },
        {
            "category":"Professional",
            "subcategory":"Research",
            "type":"Services"
        }
    ],
    "sg:phone":"+1 404 373 0995",
    "sg:postcode":"30307",
    "sg:province":"GA",
    "sg:tags":[
        "archaeologist",
        "arranged",
        "outfitted",
        "expedition"
    ],
    "wof:name":"Conservation Anthropologica",
    "wof:placetype":"venue"
},
  "geometry": {"coordinates":[-84.33427,33.784914],"type":"Point"}
}