{
  "type": "Feature",
  "properties": {
    "addr:full":"826 Church Street Unit 2 Decatur GA 30030",
    "addr:housenumber":"826",
    "addr:postcode":"30030",
    "addr:street":"Church Street;2",
    "iso:country":"US",
    "sg:address":"826 Church Street Unit 2",
    "sg:city":"Decatur",
    "sg:classifiers":[
        {
            "category":"Education",
            "subcategory":"School",
            "type":"Public Place"
        }
    ],
    "sg:phone":"+1 678 395 9727",
    "sg:postcode":"30030",
    "sg:province":"GA",
    "wof:name":"Hannah's Inc",
    "wof:placetype":"venue"
},
  "geometry": {"coordinates":[-84.295198,33.779903],"type":"Point"}
}