{
  "type": "Feature",
  "properties": {
    "iso:country":"US",
    "sg:address":"334 Tifton Eldorado Rd",
    "sg:city":"Tifton",
    "sg:classifiers":[
        {
            "category":"Government",
            "subcategory":"Office",
            "type":"Public Place"
        }
    ],
    "sg:phone":"+1 229 386 7468",
    "sg:postcode":"31794",
    "sg:province":"GA",
    "sg:tags":[
        "state",
        "resource"
    ],
    "wof:name":"New Focus Ctr For Women",
    "wof:placetype":"venue"
},
  "geometry": {"coordinates":[-83.483842,31.438258],"type":"Point"}
}