{
  "type": "Feature",
  "properties": {
    "iso:country":"US",
    "sg:address":"101 Wynfield Dr",
    "sg:city":"Tyrone",
    "sg:classifiers":[
        {
            "category":"Transit Center",
            "subcategory":"Freight",
            "type":"Transportation"
        },
        {
            "category":"Freight",
            "type":"Transportation"
        }
    ],
    "sg:phone":"+1 770 969 6280",
    "sg:postcode":"30290",
    "sg:province":"GA",
    "sg:tags":[
        "local",
        "trucking-motor",
        "trucking"
    ],
    "wof:name":"K. Brown, Inc.",
    "wof:placetype":"venue"
},
  "geometry": {"coordinates":[-84.593048,33.49239],"type":"Point"}
}