{
  "type": "Feature",
  "properties": {
    "addr:full":"3540 Mulberry Way Duluth GA 30096",
    "addr:housenumber":"3540",
    "addr:postcode":"30096",
    "addr:street":"Mulberry Way",
    "iso:country":"US",
    "sg:address":"3540 Mulberry Way",
    "sg:city":"Duluth",
    "sg:classifiers":[
        {
            "category":"Professional",
            "subcategory":"Computer Services",
            "type":"Services"
        }
    ],
    "sg:phone":"+1 404 918 6851",
    "sg:postcode":"30096",
    "sg:province":"GA",
    "sg:tags":[
        "consulting",
        "technology"
    ],
    "wof:name":"Fdss",
    "wof:placetype":"venue"
},
  "geometry": {"coordinates":[-84.171616,34.011172],"type":"Point"}
}