{
  "type": "Feature",
  "properties": {
    "iso:country":"US",
    "sg:address":"1730 Cumberland Point Dr SE",
    "sg:city":"Marietta",
    "sg:classifiers":[
        {
            "category":"Personal",
            "subcategory":"Shoe Repair & Shine",
            "type":"Services"
        },
        {
            "category":"Shopping",
            "subcategory":"Shoes",
            "type":"Retail Goods"
        }
    ],
    "sg:phone":"+1 770 955 3375",
    "sg:postcode":"30067",
    "sg:province":"GA",
    "sg:tags":[
        "dyer",
        "store"
    ],
    "wof:name":"Shu -Re-Nu/Auto Soler",
    "wof:placetype":"venue"
},
  "geometry": {"coordinates":[-84.492637,33.911497],"type":"Point"}
}