{
  "type": "Feature",
  "properties": {
    "addr:full":"2026 Emerald Dr Jonesboro GA 30236",
    "addr:housenumber":"2026",
    "addr:postcode":"30236",
    "addr:street":"Emerald Dr",
    "iso:country":"US",
    "sg:address":"2026 Emerald Dr",
    "sg:city":"Jonesboro",
    "sg:classifiers":[
        {
            "category":"Professional",
            "type":"Services"
        }
    ],
    "sg:phone":"+1 770 472 5932",
    "sg:postcode":"30236",
    "sg:province":"GA",
    "wof:name":"Merj Aire Inc",
    "wof:placetype":"venue"
},
  "geometry": {"coordinates":[-84.32900100000001,33.515637],"type":"Point"}
}