{
  "type": "Feature",
  "properties": {
    "iso:country":"US",
    "sg:address":"3410 W Paces Ferry Ct NW",
    "sg:city":"Atlanta",
    "sg:classifiers":[
        {
            "category":"Government",
            "subcategory":"Office",
            "type":"Public Place"
        }
    ],
    "sg:phone":"+1 404 275 1917",
    "sg:postcode":"30327",
    "sg:province":"GA",
    "sg:tags":[
        "development"
    ],
    "wof:name":"Wingmark St John Dev LLC",
    "wof:placetype":"venue"
},
  "geometry": {"coordinates":[-84.424322,33.849351],"type":"Point"}
}