{
  "type": "Feature",
  "properties": {
    "iso:country":"US",
    "sg:address":"259 S Main St",
    "sg:city":"Jonesboro",
    "sg:classifiers":[
        {
            "category":"Professional",
            "subcategory":"Accounting & Tax Preparation",
            "type":"Services"
        }
    ],
    "sg:phone":"+1 770 478 2377",
    "sg:postcode":"30236",
    "sg:province":"GA",
    "sg:tags":[
        "return"
    ],
    "wof:name":"Express Tax II",
    "wof:placetype":"venue"
},
  "geometry": {"coordinates":[-84.352572,33.51185],"type":"Point"}
}