{
  "type": "Feature",
  "properties": {
    "addr:full":"4153 Flat Shoals Pkwy Decatur GA 30034",
    "addr:housenumber":"4153",
    "addr:postcode":"30034",
    "addr:street":"Flat Shoals Pkwy",
    "iso:country":"US",
    "sg:address":"4153 Flat Shoals Pkwy",
    "sg:city":"Decatur",
    "sg:classifiers":[
        {
            "category":"Professional",
            "subcategory":"Management & Consulting",
            "type":"Services"
        }
    ],
    "sg:phone":"+1 404 212 0070",
    "sg:postcode":"30034",
    "sg:province":"GA",
    "sg:tags":[
        "consultant",
        "business"
    ],
    "wof:name":"R Thomas & Assoc Inc",
    "wof:placetype":"venue"
},
  "geometry": {"coordinates":[-84.259844,33.692012],"type":"Point"}
}