{
  "type": "Feature",
  "properties": {
    "addr:full":"5119 Riverdale Rd Atlanta GA 30349",
    "addr:housenumber":"5119",
    "addr:postcode":"30349",
    "addr:street":"Riverdale Rd",
    "iso:country":"US",
    "sg:address":"5119 Riverdale Rd",
    "sg:city":"Atlanta",
    "sg:classifiers":[
        {
            "category":"Restaurant",
            "type":"Food & Drink"
        }
    ],
    "sg:phone":"+1 770 997 9989",
    "sg:postcode":"30349",
    "sg:province":"GA",
    "sg:tags":[
        "eating"
    ],
    "wof:name":"Wendys",
    "wof:placetype":"venue"
},
  "geometry": {"coordinates":[-84.438456,33.615671],"type":"Point"}
}