{
  "type": "Feature",
  "properties": {
    "addr:full":"1010 Beck St Griffin GA 30224",
    "addr:housenumber":"1010",
    "addr:postcode":"30224",
    "addr:street":"Beck St",
    "iso:country":"US",
    "sg:address":"1010 Beck St",
    "sg:city":"Griffin",
    "sg:classifiers":[
        {
            "category":"Restaurant",
            "type":"Food & Drink"
        }
    ],
    "sg:phone":"+1 770 412 8062",
    "sg:postcode":"30224",
    "sg:province":"GA",
    "sg:tags":[
        "eating"
    ],
    "wof:name":"Kistons Catering",
    "wof:placetype":"venue"
},
  "geometry": {"coordinates":[-84.278167,33.238675],"type":"Point"}
}