{
  "type": "Feature",
  "properties": {
    "iso:country":"US",
    "sg:address":"2505 Eastgate Pl",
    "sg:city":"Snellville",
    "sg:classifiers":[
        {
            "category":"Organizations",
            "subcategory":"Religious Organization",
            "type":"Services"
        }
    ],
    "sg:phone":"+1 678 344 0490",
    "sg:postcode":"30078",
    "sg:province":"GA",
    "sg:tags":[
        "church"
    ],
    "wof:name":"Jesus Is The Way Restoration",
    "wof:placetype":"venue"
},
  "geometry": {"coordinates":[-84.00644200000001,33.856819],"type":"Point"}
}