{
  "type": "Feature",
  "properties": {
    "addr:full":"5041 Union St Union City GA 30291",
    "addr:housenumber":"5041",
    "addr:postcode":"30291",
    "addr:street":"Union St",
    "iso:country":"US",
    "sg:address":"5041 Union St",
    "sg:city":"Union City",
    "sg:classifiers":[
        {
            "category":"Professional",
            "subcategory":"Business Services",
            "type":"Services"
        }
    ],
    "sg:phone":"+1 770 969 0550",
    "sg:postcode":"30291",
    "sg:province":"GA",
    "wof:name":"Southside Business Svc",
    "wof:placetype":"venue"
},
  "geometry": {"coordinates":[-84.55165,33.578862],"type":"Point"}
}