{
  "type": "Feature",
  "properties": {
    "addr:full":"304 Buford Dr # B Lawrenceville GA 30045",
    "addr:housenumber":"304",
    "addr:postcode":"30045",
    "addr:street":"Buford Dr # B",
    "iso:country":"US",
    "sg:address":"304 Buford Dr # B",
    "sg:city":"Lawrenceville",
    "sg:classifiers":[
        {
            "category":"Retail",
            "subcategory":"Auto Repair",
            "type":"Services"
        }
    ],
    "sg:phone":"+1 770 963 1889",
    "sg:postcode":"30045",
    "sg:province":"GA",
    "wof:name":"Five Star Automotive",
    "wof:placetype":"venue"
},
  "geometry": {"coordinates":[-83.98580200000001,33.965302],"type":"Point"}
}