{
  "type": "Feature",
  "properties": {
    "addr:full":"207 Greensway Peachtree City GA 30269",
    "addr:housenumber":"207",
    "addr:postcode":"30269",
    "addr:street":"Greensway",
    "iso:country":"US",
    "sg:address":"207 Greensway",
    "sg:city":"Peachtree City",
    "sg:classifiers":[
        {
            "category":"Professional",
            "subcategory":"Computer Services",
            "type":"Services"
        }
    ],
    "sg:phone":"+1 770 632 6057",
    "sg:postcode":"30269",
    "sg:province":"GA",
    "sg:tags":[
        "design",
        "system"
    ],
    "wof:name":"Elevenfingerscom",
    "wof:placetype":"venue"
},
  "geometry": {"coordinates":[-84.57147399999999,33.411745],"type":"Point"}
}