{
  "type": "Feature",
  "properties": {
    "addr:full":"4488 N Shallowford Rd Atlanta GA 30338",
    "addr:housenumber":"4488",
    "addr:postcode":"30338",
    "addr:street":"N Shallowford Rd",
    "iso:country":"US",
    "sg:address":"4488 N Shallowford Rd",
    "sg:city":"Atlanta",
    "sg:classifiers":[
        {
            "category":"Professional",
            "subcategory":"Lawyer & Legal Services",
            "type":"Services"
        }
    ],
    "sg:phone":"+1 770 481 0609",
    "sg:postcode":"30338",
    "sg:province":"GA",
    "wof:name":"Wen & Wen Associates Llc Atty",
    "wof:placetype":"venue"
},
  "geometry": {"coordinates":[-84.305801,33.922199],"type":"Point"}
}