{
  "type": "Feature",
  "properties": {
    "addr:full":"170 Stonehaven Dr Fayetteville GA 30215",
    "addr:housenumber":"170",
    "addr:postcode":"30215",
    "addr:street":"Stonehaven Dr",
    "iso:country":"US",
    "sg:address":"170 Stonehaven Dr",
    "sg:city":"Fayetteville",
    "sg:classifiers":[
        {
            "category":"Professional",
            "subcategory":"Management & Consulting",
            "type":"Services"
        }
    ],
    "sg:phone":"+1 678 817 7188",
    "sg:postcode":"30215",
    "sg:province":"GA",
    "wof:name":"Mach One Marketing",
    "wof:placetype":"venue"
},
  "geometry": {"coordinates":[-84.519961,33.363202],"type":"Point"}
}