{
  "type": "Feature",
  "properties": {
    "addr:full":"1784 Century Blvd NE Ste C Atlanta GA 30345",
    "addr:housenumber":"1784",
    "addr:postcode":"30345",
    "addr:street":"Century Blvd Ne Ste C",
    "iso:country":"US",
    "sg:address":"1784 Century Blvd NE Ste C",
    "sg:city":"Atlanta",
    "sg:classifiers":[
        {
            "category":"Real Estate",
            "subcategory":"Real Estate Services",
            "type":"Services"
        }
    ],
    "sg:phone":"+1 404 321 1221",
    "sg:postcode":"30345",
    "sg:province":"GA",
    "sg:tags":[
        "management",
        "property"
    ],
    "wof:name":"Lantrac Properties Inc",
    "wof:placetype":"venue"
},
  "geometry": {"coordinates":[-84.313969,33.84572],"type":"Point"}
}