{
  "type": "Feature",
  "properties": {
    "iso:country":"US",
    "sg:address":"1100 Wadsworth Rd",
    "sg:city":"Albany",
    "sg:classifiers":[
        {
            "category":"Building & Trades",
            "subcategory":"Equipment Rental",
            "type":"Services"
        }
    ],
    "sg:phone":"+1 229 436 8474",
    "sg:postcode":"31721",
    "sg:province":"GA",
    "sg:tags":[
        "toilet",
        "portable"
    ],
    "wof:name":"Mobile Johnny of Albany Inc",
    "wof:placetype":"venue"
},
  "geometry": {"coordinates":[-84.304084,31.623056],"type":"Point"}
}