{
  "type": "Feature",
  "properties": {
    "addr:full":"520 Stonebrook Farms Dr Alpharetta GA 30004",
    "addr:housenumber":"520",
    "addr:postcode":"30004",
    "addr:street":"Stonebrook Farms Dr",
    "iso:country":"US",
    "sg:address":"520 Stonebrook Farms Dr",
    "sg:city":"Alpharetta",
    "sg:classifiers":[
        {
            "category":"Shopping",
            "type":"Retail Goods"
        }
    ],
    "sg:phone":"+1 770 754 9111",
    "sg:postcode":"30004",
    "sg:province":"GA",
    "sg:tags":[
        "merchandise"
    ],
    "wof:name":"Greatful Pets of Alpharetta",
    "wof:placetype":"venue"
},
  "geometry": {"coordinates":[-84.276009,34.155858],"type":"Point"}
}