{
  "type": "Feature",
  "properties": {
    "addr:full":"4847 Industrial Access Rd Douglasville GA 30134",
    "addr:housenumber":"4847",
    "addr:postcode":"30134",
    "addr:street":"Industrial Access Rd",
    "iso:country":"US",
    "sg:address":"4847 Industrial Access Rd",
    "sg:city":"Douglasville",
    "sg:classifiers":[
        {
            "category":"Communications",
            "subcategory":"Film & Video Production",
            "type":"Services"
        }
    ],
    "sg:phone":"+1 770 947 8280",
    "sg:postcode":"30134",
    "sg:province":"GA",
    "sg:tags":[
        "motion",
        "picture"
    ],
    "wof:name":"C Marc Dgtal Video Productions",
    "wof:placetype":"venue"
},
  "geometry": {"coordinates":[-84.725386,33.769649],"type":"Point"}
}