{
  "type": "Feature",
  "properties": {
    "addr:full":"1800 Century Blvd NE Atlanta GA 30345",
    "addr:housenumber":"1800",
    "addr:postcode":"30345",
    "addr:street":"Century Blvd Ne",
    "iso:country":"US",
    "sg:address":"1800 Century Blvd NE",
    "sg:city":"Atlanta",
    "sg:classifiers":[
        {
            "category":"Insurance",
            "subcategory":"Insurance Agent",
            "type":"Services"
        }
    ],
    "sg:phone":"+1 404 321 1660",
    "sg:postcode":"30345",
    "sg:province":"GA",
    "wof:name":"Southern Mar AVI Underwriters",
    "wof:placetype":"venue"
},
  "geometry": {"coordinates":[-84.312175,33.846256],"type":"Point"}
}