{
  "type": "Feature",
  "properties": {
    "iso:country":"US",
    "sg:address":"3245 Peachtree Pkwy",
    "sg:city":"Suwanee",
    "sg:classifiers":[
        {
            "category":"Sports & Exercise",
            "subcategory":"Gym",
            "type":"Entertainment"
        }
    ],
    "sg:phone":"+1 678 208 0958",
    "sg:postcode":"30024",
    "sg:province":"GA",
    "sg:tags":[
        "trainer"
    ],
    "wof:name":"Laurel Springs Chiropractic",
    "wof:placetype":"venue"
},
  "geometry": {"coordinates":[-84.161118,34.083694],"type":"Point"}
}