{
  "type": "Feature",
  "properties": {
    "addr:full":"3166 Maple Dr NE Ste 134 Atlanta GA 30305",
    "addr:housenumber":"3166",
    "addr:postcode":"30305",
    "addr:street":"Maple Dr Ne Ste 134",
    "iso:country":"US",
    "sg:address":"3166 Maple Dr NE Ste 134",
    "sg:city":"Atlanta",
    "sg:classifiers":[
        {
            "category":"Shopping",
            "subcategory":"Stationery & Office Supplies",
            "type":"Retail Goods"
        },
        {
            "category":"Wholesale",
            "subcategory":"Office Equipment",
            "type":"Manufacturing & Wholesale Goods"
        },
        {
            "category":"Professional",
            "subcategory":"Printing & Photocopies",
            "type":"Services"
        }
    ],
    "sg:phone":"+1 404 237 0720",
    "sg:postcode":"30305",
    "sg:province":"GA",
    "sg:tags":[
        "services-commercial",
        "register",
        "autographic",
        "furniture"
    ],
    "wof:name":"1st Office Products",
    "wof:placetype":"venue"
},
  "geometry": {"coordinates":[-84.372257,33.840409],"type":"Point"}
}