{
  "type": "Feature",
  "properties": {
    "addr:full":"614 S 8th St Griffin GA 30224",
    "addr:housenumber":"614",
    "addr:postcode":"30224",
    "addr:street":"S 8Th St",
    "iso:country":"US",
    "sg:address":"614 S 8th St",
    "sg:city":"Griffin",
    "sg:classifiers":[
        {
            "category":"Health Services",
            "subcategory":"Doctor",
            "type":"Services"
        }
    ],
    "sg:phone":"+1 770 228 1010",
    "sg:postcode":"30224",
    "sg:province":"GA",
    "sg:tags":[
        "dentist"
    ],
    "wof:name":"Gruskin & Lucas P C",
    "wof:placetype":"venue"
},
  "geometry": {"coordinates":[-84.26562199999999,33.239741],"type":"Point"}
}