{
  "type": "Feature",
  "properties": {
    "iso:country":"US",
    "sg:address":"918 Martin Luther King Jr Blvd",
    "sg:city":"Savannah",
    "sg:classifiers":[
        {
            "category":"Health Services",
            "subcategory":"Doctor",
            "type":"Services"
        }
    ],
    "sg:phone":"+1 912 238 0062",
    "sg:postcode":"31415",
    "sg:province":"GA",
    "sg:tags":[
        "physician",
        "surgeon"
    ],
    "wof:name":"Myra Pope Family Practice",
    "wof:placetype":"venue"
},
  "geometry": {"coordinates":[-81.102194,32.067018],"type":"Point"}
}