{
  "type": "Feature",
  "properties": {
    "addr:full":"1030 Campbell St Thomasville GA 31792",
    "addr:housenumber":"1030",
    "addr:postcode":"31792",
    "addr:street":"Campbell St",
    "iso:country":"US",
    "sg:address":"1030 Campbell St",
    "sg:city":"Thomasville",
    "sg:classifiers":[
        {
            "category":"Home & Garden",
            "subcategory":"Building Materials",
            "type":"Retail Goods"
        }
    ],
    "sg:phone":"+1 229 228 4584",
    "sg:postcode":"31792",
    "sg:province":"GA",
    "sg:tags":[
        "mixed",
        "concrete"
    ],
    "wof:name":"Scruggs Concrete",
    "wof:placetype":"venue"
},
  "geometry": {"coordinates":[-84.009528,30.829267],"type":"Point"}
}