{
  "type": "Feature",
  "properties": {
    "addr:full":"1502 Fairway Dr Vidalia GA 30474",
    "addr:housenumber":"1502",
    "addr:postcode":"30474",
    "addr:street":"Fairway Dr Vidalia",
    "iso:country":"US",
    "sg:address":"1502 Fairway Dr",
    "sg:city":"Vidalia",
    "sg:classifiers":[
        {
            "category":"Personal",
            "subcategory":"Beauty Salon",
            "type":"Services"
        }
    ],
    "sg:phone":"+1 912 537 3919",
    "sg:postcode":"30474",
    "sg:province":"GA",
    "wof:name":"Mane Attraction",
    "wof:placetype":"venue"
},
  "geometry": {"coordinates":[-82.443218,32.197719],"type":"Point"}
}