{
  "type": "Feature",
  "properties": {
    "addr:full":"4132 Stone Mountain Hwy Lilburn GA 30047",
    "addr:housenumber":"4132",
    "addr:postcode":"30047",
    "addr:street":"Stone Mountain Hwy",
    "iso:country":"US",
    "sg:address":"4132 Stone Mountain Hwy",
    "sg:city":"Lilburn",
    "sg:classifiers":[
        {
            "category":"Restaurant",
            "type":"Food & Drink"
        }
    ],
    "sg:phone":"+1 770 979 2296",
    "sg:postcode":"30047",
    "sg:province":"GA",
    "wof:name":"Fisherman's Catch Restaurant",
    "wof:placetype":"venue"
},
  "geometry": {"coordinates":[-84.072197,33.836399],"type":"Point"}
}