{
  "type": "Feature",
  "properties": {
    "addr:full":"97 Stoker Rd SW Cartersville GA 30120",
    "addr:housenumber":"97",
    "addr:postcode":"30120",
    "addr:street":"Stoker Rd Sw",
    "iso:country":"US",
    "sg:address":"97 Stoker Rd SW",
    "sg:city":"Cartersville",
    "sg:classifiers":[
        {
            "category":"Building & Trades",
            "subcategory":"Electrical",
            "type":"Services"
        }
    ],
    "sg:phone":"+1 770 546 4996",
    "sg:postcode":"30120",
    "sg:province":"GA",
    "sg:tags":[
        "electrician"
    ],
    "wof:name":"Clowers Electric",
    "wof:placetype":"venue"
},
  "geometry": {"coordinates":[-84.86173100000001,34.202346],"type":"Point"}
}