{
  "type": "Feature",
  "properties": {
    "addr:full":"211 River's Bend Brunswick GA 31525",
    "addr:housenumber":"211",
    "addr:postcode":"31525",
    "addr:street":"River'S Bend",
    "iso:country":"US",
    "sg:address":"211 River's Bend",
    "sg:city":"Brunswick",
    "sg:classifiers":[
        {
            "category":"Social Services",
            "subcategory":"Child Care",
            "type":"Services"
        }
    ],
    "sg:phone":"+1 912 264 2963",
    "sg:postcode":"31525",
    "sg:province":"GA",
    "sg:tags":[
        "day"
    ],
    "wof:name":"Montessori Christn Schoolhouse",
    "wof:placetype":"venue"
},
  "geometry": {"coordinates":[-81.4474,31.23183],"type":"Point"}
}