{
  "type": "Feature",
  "properties": {
    "iso:country":"US",
    "sg:address":"3181 US Hwy 80",
    "sg:city":"Bloomingdale",
    "sg:classifiers":[
        {
            "category":"Retail",
            "subcategory":"Repair Shop",
            "type":"Services"
        }
    ],
    "sg:phone":"+1 912 748 5440",
    "sg:postcode":"31302",
    "sg:province":"GA",
    "sg:tags":[
        "repairing",
        "piano",
        "refinishing"
    ],
    "wof:name":"Matt Deffley",
    "wof:placetype":"venue"
},
  "geometry": {"coordinates":[-81.334559,32.143956],"type":"Point"}
}