{
  "type": "Feature",
  "properties": {
    "iso:country":"US",
    "sg:address":"2657 Kings Way",
    "sg:city":"Lawrenceville",
    "sg:classifiers":[
        {
            "category":"Sports & Exercise",
            "subcategory":"Swimming Pool",
            "type":"Entertainment"
        },
        {
            "category":"Building & Trades",
            "subcategory":"Construction",
            "type":"Services"
        },
        {
            "category":"Manufacturing",
            "subcategory":"Building Materials",
            "type":"Manufacturing & Wholesale Goods"
        },
        {
            "category":"Military Area",
            "subcategory":"Armory",
            "type":"Public Place"
        }
    ],
    "sg:phone":"+1 770 925 3245",
    "sg:postcode":"30044",
    "sg:province":"GA",
    "sg:tags":[
        "repair",
        "fence",
        "cover",
        "contractor",
        "accessory",
        "gate",
        "welder",
        "enclosure",
        "fence-sales"
    ],
    "sg:website":"http://www.lawrencevillefence.com",
    "wof:name":"Lawrenceville Fence Company",
    "wof:placetype":"venue"
},
  "geometry": {"coordinates":[-84.068494,33.920975],"type":"Point"}
}