{
  "type": "Feature",
  "properties": {
    "iso:country":"US",
    "sg:address":"2322 Quickwater Ct",
    "sg:city":"Decatur",
    "sg:classifiers":[
        {
            "category":"Wholesale",
            "subcategory":"Vending Machines",
            "type":"Manufacturing & Wholesale Goods"
        }
    ],
    "sg:phone":"+1 770 323 1539",
    "sg:postcode":"30035",
    "sg:province":"GA",
    "sg:tags":[
        "merchandise"
    ],
    "wof:name":"Norkesha Canteen",
    "wof:placetype":"venue"
},
  "geometry": {"coordinates":[-84.19528699999999,33.723649],"type":"Point"}
}