{
  "type": "Feature",
  "properties": {
    "addr:full":"244 Callaway Rd Fayetteville GA 30215",
    "addr:housenumber":"244",
    "addr:postcode":"30215",
    "addr:street":"Callaway Rd",
    "iso:country":"US",
    "sg:address":"244 Callaway Rd",
    "sg:city":"Fayetteville",
    "sg:classifiers":[
        {
            "category":"Retail",
            "subcategory":"Pet Boarding",
            "type":"Services"
        }
    ],
    "sg:phone":"+1 770 461 9893",
    "sg:postcode":"30215",
    "sg:province":"GA",
    "sg:tags":[
        "boarding/pet",
        "sitting"
    ],
    "wof:name":"Waterwood Kennel",
    "wof:placetype":"venue"
},
  "geometry": {"coordinates":[-84.421997,33.447399],"type":"Point"}
}