{
  "type": "Feature",
  "properties": {
    "iso:country":"US",
    "sg:address":"501 State Hwy 138",
    "sg:city":"Riverdale",
    "sg:classifiers":[
        {
            "category":"Professional",
            "subcategory":"Management & Consulting",
            "type":"Services"
        },
        {
            "category":"Professional",
            "subcategory":"Employment Agencies",
            "type":"Services"
        }
    ],
    "sg:phone":"+1 770 302 0488",
    "sg:postcode":"30274",
    "sg:province":"GA",
    "sg:tags":[
        "personnel",
        "supply",
        "help",
        "consultant"
    ],
    "wof:name":"Royal Staffing Inc Riverdale",
    "wof:placetype":"venue"
},
  "geometry": {"coordinates":[-84.406868,33.546574],"type":"Point"}
}