{
  "type": "Feature",
  "properties": {
    "iso:country":"US",
    "sg:address":"535 W Taylor St",
    "sg:city":"Griffin",
    "sg:classifiers":[
        {
            "category":"Shopping",
            "subcategory":"Used Merchandise",
            "type":"Retail Goods"
        }
    ],
    "sg:phone":"+1 770 412 9390",
    "sg:postcode":"30223",
    "sg:province":"GA",
    "sg:tags":[
        "pawnbroker"
    ],
    "wof:name":"Title Max Of Griffin II",
    "wof:placetype":"venue"
},
  "geometry": {"coordinates":[-84.271458,33.247331],"type":"Point"}
}