{
  "type": "Feature",
  "properties": {
    "iso:country":"US",
    "sg:address":"418 3rd St",
    "sg:city":"Macon",
    "sg:classifiers":[
        {
            "category":"Home & Garden",
            "subcategory":"Furniture",
            "type":"Retail Goods"
        }
    ],
    "sg:phone":"+1 478 743 5004",
    "sg:postcode":"31201",
    "sg:province":"GA",
    "wof:name":"Blair Furniture Co",
    "wof:placetype":"venue"
},
  "geometry": {"coordinates":[-83.62763099999999,32.835729],"type":"Point"}
}