{
  "type": "Feature",
  "properties": {
    "iso:country":"US",
    "sg:address":"5021 Young Harris Hwy",
    "sg:city":"Blairsville",
    "sg:classifiers":[
        {
            "category":"Building & Trades",
            "subcategory":"Construction",
            "type":"Services"
        }
    ],
    "sg:phone":"+1 706 781 6100",
    "sg:postcode":"30512",
    "sg:province":"GA",
    "sg:tags":[
        "contractor"
    ],
    "wof:name":"Blue Mountain Homes/Polysteel",
    "wof:placetype":"venue"
},
  "geometry": {"coordinates":[-83.86802,34.910792],"type":"Point"}
}