{
  "type": "Feature",
  "properties": {
    "addr:full":"33 Ponce de Leon Ave NE Atlanta GA 30308",
    "addr:housenumber":"33",
    "addr:postcode":"30308",
    "addr:street":"Ponce De Leon Ave Ne",
    "iso:country":"US",
    "sg:address":"33 Ponce de Leon Ave NE",
    "sg:city":"Atlanta",
    "sg:classifiers":[
        {
            "category":"Real Estate",
            "subcategory":"Real Estate Services",
            "type":"Services"
        }
    ],
    "sg:phone":"+1 404 874 1880",
    "sg:postcode":"30308",
    "sg:province":"GA",
    "sg:tags":[
        "management",
        "condominium"
    ],
    "wof:name":"Thirty Three Ponce Condominiums Association",
    "wof:placetype":"venue"
},
  "geometry": {"coordinates":[-84.386244,33.772283],"type":"Point"}
}