{
  "type": "Feature",
  "properties": {
    "addr:full":"918 E Jefferson St Americus GA 31709",
    "addr:housenumber":"918",
    "addr:postcode":"31709",
    "addr:street":"E Jefferson St",
    "iso:country":"US",
    "sg:address":"918 E Jefferson St",
    "sg:city":"Americus",
    "sg:classifiers":[
        {
            "category":"Organizations",
            "subcategory":"Religious Organization",
            "type":"Services"
        }
    ],
    "sg:phone":"+1 229 924 2839",
    "sg:postcode":"31709",
    "sg:province":"GA",
    "wof:name":"Friendship Baptist Assn",
    "wof:placetype":"venue"
},
  "geometry": {"coordinates":[-84.21551599999999,32.075236],"type":"Point"}
}