{
  "type": "Feature",
  "properties": {
    "iso:country":"US",
    "sg:address":"71 Maddox Dr NE",
    "sg:city":"Atlanta",
    "sg:classifiers":[
        {
            "category":"Education",
            "subcategory":"Library",
            "type":"Public Place"
        }
    ],
    "sg:phone":"+1 404 892 3060",
    "sg:postcode":"30309",
    "sg:province":"GA",
    "wof:name":"Dave Branch Media Inc",
    "wof:placetype":"venue"
},
  "geometry": {"coordinates":[-84.37766999999999,33.795261],"type":"Point"}
}