{
  "type": "Feature",
  "properties": {
    "addr:full":"107 Durham St Dallas GA 30132",
    "addr:housenumber":"107",
    "addr:postcode":"30132",
    "addr:street":"Durham St",
    "iso:country":"US",
    "sg:address":"107 Durham St",
    "sg:city":"Dallas",
    "sg:classifiers":[
        {
            "category":"Real Estate",
            "subcategory":"Real Estate Agent",
            "type":"Services"
        }
    ],
    "sg:phone":"+1 770 445 3076",
    "sg:postcode":"30132",
    "sg:province":"GA",
    "wof:name":"Northwest Realty",
    "wof:placetype":"venue"
},
  "geometry": {"coordinates":[-84.85906,33.918918],"type":"Point"}
}