{
  "type": "Feature",
  "properties": {
    "iso:country":"US",
    "sg:address":"1766 Hunters Trce SW",
    "sg:city":"Lilburn",
    "sg:classifiers":[
        {
            "category":"Building & Trades",
            "subcategory":"Construction",
            "type":"Services"
        }
    ],
    "sg:phone":"+1 770 979 8828",
    "sg:postcode":"30047",
    "sg:province":"GA",
    "sg:tags":[
        "roofing",
        "contractor"
    ],
    "wof:name":"J C Hinkle LTD",
    "wof:placetype":"venue"
},
  "geometry": {"coordinates":[-84.074341,33.850526],"type":"Point"}
}