{
  "type": "Feature",
  "properties": {
    "iso:country":"US",
    "sg:address":"1441 Dupree Rd",
    "sg:city":"Woodstock",
    "sg:classifiers":[
        {
            "category":"Building & Trades",
            "subcategory":"Construction",
            "type":"Services"
        }
    ],
    "sg:phone":"+1 678 445 9065",
    "sg:postcode":"30189",
    "sg:province":"GA",
    "sg:tags":[
        "control",
        "erosion"
    ],
    "wof:name":"Georgia Erosion Control Ctr",
    "wof:placetype":"venue"
},
  "geometry": {"coordinates":[-84.533902,34.095861],"type":"Point"}
}