{
  "type": "Feature",
  "properties": {
    "iso:country":"US",
    "sg:address":"6824 Cove Cir",
    "sg:city":"Columbus",
    "sg:classifiers":[
        {
            "category":"Retail",
            "subcategory":"Repair Shop",
            "type":"Services"
        }
    ],
    "sg:phone":"+1 706 569 8242",
    "sg:postcode":"31907",
    "sg:province":"GA",
    "sg:tags":[
        "air",
        "conditioning",
        "contractor"
    ],
    "wof:name":"Dorsey Heating & AC",
    "wof:placetype":"venue"
},
  "geometry": {"coordinates":[-84.872614,32.475034],"type":"Point"}
}