{
  "type": "Feature",
  "properties": {
    "iso:country":"US",
    "sg:address":"120 Myrtle Rd",
    "sg:city":"Woodstock",
    "sg:classifiers":[
        {
            "category":"Real Estate",
            "subcategory":"Real Estate Agent",
            "type":"Services"
        }
    ],
    "sg:phone":"+1 770 926 9070",
    "sg:postcode":"30189",
    "sg:province":"GA",
    "sg:tags":[
        "broker"
    ],
    "wof:name":"Che Properties Inc",
    "wof:placetype":"venue"
},
  "geometry": {"coordinates":[-84.614441,34.136104],"type":"Point"}
}