{
  "type": "Feature",
  "properties": {
    "addr:full":"501 Amsterdam Ave NE Atlanta GA 30306",
    "addr:housenumber":"501",
    "addr:postcode":"30306",
    "addr:street":"Amsterdam Ave Ne",
    "iso:country":"US",
    "sg:address":"501 Amsterdam Ave NE",
    "sg:city":"Atlanta",
    "sg:classifiers":[
        {
            "category":"Personal",
            "type":"Services"
        }
    ],
    "sg:phone":"+1 404 873 5400",
    "sg:postcode":"30306",
    "sg:province":"GA",
    "sg:tags":[
        "pet",
        "boarding/pet",
        "sitting"
    ],
    "sg:website":"www.piedmontbark.com",
    "wof:name":"Piedmont Bark",
    "wof:placetype":"venue"
},
  "geometry": {"coordinates":[-84.369424,33.788689],"type":"Point"}
}