{
  "type": "Feature",
  "properties": {
    "iso:country":"US",
    "sg:address":"1000 Cobb Pkwy S",
    "sg:city":"Marietta",
    "sg:classifiers":[
        {
            "category":"Shopping",
            "subcategory":"Stationery & Office Supplies",
            "type":"Retail Goods"
        }
    ],
    "sg:phone":"+1 678 290 9855",
    "sg:postcode":"30060",
    "sg:province":"GA",
    "sg:tags":[
        "equipment"
    ],
    "wof:name":"Office Furniture Outlet",
    "wof:placetype":"venue"
},
  "geometry": {"coordinates":[-84.50751200000001,33.926511],"type":"Point"}
}