{
  "type": "Feature",
  "properties": {
    "addr:full":"5350 Oak Valley Rd Toccoa GA 30577",
    "addr:housenumber":"5350",
    "addr:postcode":"30577",
    "addr:street":"Oak Valley Rd",
    "iso:country":"US",
    "sg:address":"5350 Oak Valley Rd",
    "sg:city":"Toccoa",
    "sg:classifiers":[
        {
            "category":"Home & Garden",
            "subcategory":"Furniture",
            "type":"Retail Goods"
        }
    ],
    "sg:phone":"+1 706 886 9632",
    "sg:postcode":"30577",
    "sg:province":"GA",
    "wof:name":"Caudell Wood Products",
    "wof:placetype":"venue"
},
  "geometry": {"coordinates":[-83.265863,34.577045],"type":"Point"}
}