{
  "type": "Feature",
  "properties": {
    "iso:country":"US",
    "sg:address":"1470 Waterford Ln",
    "sg:city":"Monroe",
    "sg:classifiers":[
        {
            "category":"Professional",
            "type":"Services"
        }
    ],
    "sg:phone":"+1 770 979 3918",
    "sg:postcode":"30656",
    "sg:province":"GA",
    "wof:name":"Blue Ridge Mapping Inc",
    "wof:placetype":"venue"
},
  "geometry": {"coordinates":[-83.784187,33.822732],"type":"Point"}
}