{
  "type": "Feature",
  "properties": {
    "iso:country":"US",
    "sg:address":"2863 Anvil Block Rd",
    "sg:city":"Ellenwood",
    "sg:classifiers":[
        {
            "category":"Food & Beverages",
            "subcategory":"Groceries & Convenience Stores",
            "type":"Retail Goods"
        }
    ],
    "sg:phone":"+1 404 608 9192",
    "sg:postcode":"30294",
    "sg:province":"GA",
    "wof:name":"Anvil Block Amoco",
    "wof:placetype":"venue"
},
  "geometry": {"coordinates":[-84.295303,33.6339],"type":"Point"}
}