{
  "type": "Feature",
  "properties": {
    "addr:full":"6276 Southland Forest Dr Stone Mountain GA 30087",
    "addr:housenumber":"6276",
    "addr:postcode":"30087",
    "addr:street":"Southland Forest Dr",
    "iso:country":"US",
    "sg:address":"6276 Southland Forest Dr",
    "sg:city":"Stone Mountain",
    "sg:classifiers":[
        {
            "category":"Local Transit",
            "type":"Transportation"
        }
    ],
    "sg:phone":"+1 770 879 5397",
    "sg:postcode":"30087",
    "sg:province":"GA",
    "sg:tags":[
        "passenger"
    ],
    "wof:name":"Harris Limosine Service",
    "wof:placetype":"venue"
},
  "geometry": {"coordinates":[-84.13203300000001,33.77775],"type":"Point"}
}