{
  "type": "Feature",
  "properties": {
    "iso:country":"US",
    "sg:address":"2708 Mechanics Ave",
    "sg:city":"Savannah",
    "sg:classifiers":[
        {
            "category":"Education",
            "subcategory":"Library",
            "type":"Public Place"
        }
    ],
    "sg:phone":"+1 912 354 5864",
    "sg:postcode":"31404",
    "sg:province":"GA",
    "wof:name":"Thunderbolt Branch Library",
    "wof:placetype":"venue"
},
  "geometry": {"coordinates":[-81.05312499999999,32.034548],"type":"Point"}
}