{
  "type": "Feature",
  "properties": {
    "addr:full":"105 Cochran Rd SE Marietta GA 30060",
    "addr:housenumber":"105",
    "addr:postcode":"30060",
    "addr:street":"Cochran Rd Se",
    "iso:country":"US",
    "sg:address":"105 Cochran Rd SE",
    "sg:city":"Marietta",
    "sg:classifiers":[
        {
            "category":"Professional",
            "type":"Services"
        }
    ],
    "sg:phone":"+1 770 794 1365",
    "sg:postcode":"30060",
    "sg:province":"GA",
    "wof:name":"Knox Technical Svcs",
    "wof:placetype":"venue"
},
  "geometry": {"coordinates":[-84.54874700000001,33.912916],"type":"Point"}
}