{
  "type": "Feature",
  "properties": {
    "iso:country":"US",
    "sg:address":"3261 N Henry Blvd",
    "sg:city":"Stockbridge",
    "sg:classifiers":[
        {
            "category":"Building & Trades",
            "subcategory":"Construction",
            "type":"Services"
        }
    ],
    "sg:phone":"+1 770 474 5020",
    "sg:postcode":"30281",
    "sg:province":"GA",
    "sg:tags":[
        "contractor"
    ],
    "wof:name":"Carreker Construction Inc",
    "wof:placetype":"venue"
},
  "geometry": {"coordinates":[-84.197475,33.528841],"type":"Point"}
}