{
  "type": "Feature",
  "properties": {
    "iso:country":"US",
    "sg:address":"2207 Loudon Ln",
    "sg:city":"Kennesaw",
    "sg:classifiers":[
        {
            "category":"Shopping",
            "type":"Retail Goods"
        }
    ],
    "sg:phone":"+1 770 857 4598",
    "sg:postcode":"30152",
    "sg:province":"GA",
    "sg:tags":[
        "merchandise"
    ],
    "wof:name":"Candle Patch",
    "wof:placetype":"venue"
},
  "geometry": {"coordinates":[-84.62791900000001,34.002767],"type":"Point"}
}