{
  "type": "Feature",
  "properties": {
    "iso:country":"US",
    "sg:address":"3473 Maritime Glen",
    "sg:city":"Gainesville",
    "sg:classifiers":[
        {
            "category":"Professional",
            "subcategory":"Management & Consulting",
            "type":"Services"
        }
    ],
    "sg:phone":"+1 770 532 1875",
    "sg:postcode":"30506",
    "sg:province":"GA",
    "wof:name":"Prism Group",
    "wof:placetype":"venue"
},
  "geometry": {"coordinates":[-83.943906,34.321634],"type":"Point"}
}