{
  "type": "Feature",
  "properties": {
    "iso:country":"US",
    "sg:address":"1220 Village Oaks Ln",
    "sg:city":"Lawrenceville",
    "sg:classifiers":[
        {
            "category":"Building & Trades",
            "subcategory":"Landscaping Services",
            "type":"Services"
        }
    ],
    "sg:phone":"+1 770 338 5619",
    "sg:postcode":"30043",
    "sg:province":"GA",
    "wof:name":"Natures Creations Custom Lands",
    "wof:placetype":"venue"
},
  "geometry": {"coordinates":[-83.973883,34.003177],"type":"Point"}
}