{
  "type": "Feature",
  "properties": {
    "iso:country":"US",
    "sg:address":"5735 Dawsonville Hwy",
    "sg:city":"Gainesville",
    "sg:classifiers":[
        {
            "category":"Organizations",
            "subcategory":"Religious Organization",
            "type":"Services"
        }
    ],
    "sg:phone":"+1 770 844 1371",
    "sg:postcode":"30506",
    "sg:province":"GA",
    "sg:tags":[
        "monastery",
        "convent"
    ],
    "wof:name":"Dominican Sister",
    "wof:placetype":"venue"
},
  "geometry": {"coordinates":[-84.003303,34.319889],"type":"Point"}
}