{
  "type": "Feature",
  "properties": {
    "addr:full":"430 Crabapple Farm Dr Alpharetta GA 30004",
    "addr:housenumber":"430",
    "addr:postcode":"30004",
    "addr:street":"Crabapple Farm Dr",
    "iso:country":"US",
    "sg:address":"430 Crabapple Farm Dr",
    "sg:city":"Alpharetta",
    "sg:classifiers":[
        {
            "category":"Banks & Credit Unions",
            "subcategory":"Financial Services",
            "type":"Services"
        }
    ],
    "sg:phone":"+1 770 664 0615",
    "sg:postcode":"30004",
    "sg:province":"GA",
    "sg:tags":[
        "investor"
    ],
    "wof:name":"L W Cleveland Investments LP",
    "wof:placetype":"venue"
},
  "geometry": {"coordinates":[-84.348817,34.086234],"type":"Point"}
}