{
  "type": "Feature",
  "properties": {
    "addr:full":"1735 Millhouse Run Marietta GA 30066",
    "addr:housenumber":"1735",
    "addr:postcode":"30066",
    "addr:street":"Millhouse Run",
    "iso:country":"US",
    "sg:address":"1735 Millhouse Run",
    "sg:city":"Marietta",
    "sg:classifiers":[
        {
            "category":"Retail",
            "subcategory":"Laundry & Dry Cleaning",
            "type":"Services"
        }
    ],
    "sg:phone":"+1 770 516 8068",
    "sg:postcode":"30066",
    "sg:province":"GA",
    "sg:tags":[
        "cleaners",
        "rug",
        "carpet"
    ],
    "wof:name":"Chem-Dry By Arnie",
    "wof:placetype":"venue"
},
  "geometry": {"coordinates":[-84.488111,34.054653],"type":"Point"}
}