{
  "type": "Feature",
  "properties": {
    "addr:full":"4034 Hartley Bridge Rd Macon GA 31216",
    "addr:housenumber":"4034",
    "addr:postcode":"31216",
    "addr:street":"Hartley Bridge Rd",
    "iso:country":"US",
    "sg:address":"4034 Hartley Bridge Rd",
    "sg:city":"Macon",
    "sg:classifiers":[
        {
            "category":"Home & Garden",
            "subcategory":"Garden Supply",
            "type":"Retail Goods"
        }
    ],
    "sg:phone":"+1 478 784 0138",
    "sg:postcode":"31216",
    "sg:province":"GA",
    "sg:tags":[
        "nurseryman"
    ],
    "wof:name":"Green Leaf Garden Center",
    "wof:placetype":"venue"
},
  "geometry": {"coordinates":[-83.703294,32.743939],"type":"Point"}
}