{
  "type": "Feature",
  "properties": {
    "iso:country":"US",
    "sg:address":"108 W Lamar St",
    "sg:city":"Americus",
    "sg:classifiers":[
        {
            "category":"Insurance",
            "subcategory":"Insurance Agent",
            "type":"Services"
        },
        {
            "category":"Insurance",
            "subcategory":"Hazard Insurance",
            "type":"Services"
        },
        {
            "category":"Insurance",
            "subcategory":"Title Insurance",
            "type":"Services"
        },
        {
            "category":"Insurance",
            "subcategory":"Health Insurance",
            "type":"Services"
        },
        {
            "category":"Insurance",
            "subcategory":"Life Insurance",
            "type":"Services"
        }
    ],
    "sg:phone":"+1 229 924 2924",
    "sg:postcode":"31709",
    "sg:province":"GA",
    "sg:tags":[
        "business",
        "auto",
        "commercial",
        "homeowner",
        "property",
        "casualty"
    ],
    "sg:website":"http://www.thehooksagency.com",
    "wof:name":"Hooks Agency Inc",
    "wof:placetype":"venue"
},
  "geometry": {"coordinates":[-84.232826,32.072204],"type":"Point"}
}