{
  "type": "Feature",
  "properties": {
    "iso:country":"US",
    "sg:address":"4989 Riverhill Rd",
    "sg:city":"Marietta",
    "sg:classifiers":[
        {
            "category":"Wholesale",
            "subcategory":"Durable Goods & Equipment",
            "type":"Manufacturing & Wholesale Goods"
        }
    ],
    "sg:phone":"+1 770 973 1124",
    "sg:postcode":"30068",
    "sg:province":"GA",
    "sg:tags":[
        "representative",
        "manufacturer"
    ],
    "wof:name":"G & G Sales Inc",
    "wof:placetype":"venue"
},
  "geometry": {"coordinates":[-84.40624200000001,33.959171],"type":"Point"}
}