{
  "type": "Feature",
  "properties": {
    "iso:country":"US",
    "sg:address":"1260 Compass Pointe Xing",
    "sg:city":"Alpharetta",
    "sg:classifiers":[
        {
            "category":"Professional",
            "subcategory":"Engineering",
            "type":"Services"
        }
    ],
    "sg:phone":"+1 770 751 7077",
    "sg:postcode":"30005",
    "sg:province":"GA",
    "wof:name":"Cardozo Engineering Inc",
    "wof:placetype":"venue"
},
  "geometry": {"coordinates":[-84.231656,34.090521],"type":"Point"}
}