{
  "type": "Feature",
  "properties": {
    "addr:full":"6188 Newberry Ln Riverdale GA 30296",
    "addr:housenumber":"6188",
    "addr:postcode":"30296",
    "addr:street":"Newberry Ln",
    "iso:country":"US",
    "sg:address":"6188 Newberry Ln",
    "sg:city":"Riverdale",
    "sg:classifiers":[
        {
            "category":"Food & Beverages",
            "subcategory":"Groceries & Convenience Stores",
            "type":"Retail Goods"
        }
    ],
    "sg:phone":"+1 770 996 8096",
    "sg:postcode":"30296",
    "sg:province":"GA",
    "wof:name":"91st Psalm Catering & Food",
    "wof:placetype":"venue"
},
  "geometry": {"coordinates":[-84.450166,33.586829],"type":"Point"}
}