{
  "type": "Feature",
  "properties": {
    "iso:country":"US",
    "sg:address":"6005 Collins Ter",
    "sg:city":"Statesboro",
    "sg:classifiers":[
        {
            "category":"Banks & Credit Unions",
            "subcategory":"Investment Brokerage",
            "type":"Services"
        }
    ],
    "sg:phone":"+1 912 682 9807",
    "sg:postcode":"30461",
    "sg:province":"GA",
    "sg:tags":[
        "advisory"
    ],
    "wof:name":"Strategic Capital Planning, Inc.",
    "wof:placetype":"venue"
},
  "geometry": {"coordinates":[-81.71221300000001,32.396034],"type":"Point"}
}