{
  "type": "Feature",
  "properties": {
    "iso:country":"US",
    "sg:address":"5978 Peachtree Road",
    "sg:city":"Atlanta",
    "sg:classifiers":[
        {
            "category":"Home & Garden",
            "subcategory":"Furniture",
            "type":"Retail Goods"
        }
    ],
    "sg:phone":"+1 770 458 1092",
    "sg:postcode":"30341",
    "sg:province":"GA",
    "sg:tags":[
        "store"
    ],
    "wof:name":"Sterling Industries",
    "wof:placetype":"venue"
},
  "geometry": {"coordinates":[-84.289591,33.907109],"type":"Point"}
}