{
  "type": "Feature",
  "properties": {
    "addr:full":"1 Coca Cola Plaza NW Atlanta GA 30313",
    "addr:housenumber":"1",
    "addr:postcode":"30313",
    "addr:street":"Coca;Plaza Nw",
    "iso:country":"US",
    "sg:address":"1 Coca Cola Plaza NW",
    "sg:city":"Atlanta",
    "sg:classifiers":[
        {
            "category":"Professional",
            "subcategory":"Employment Agencies",
            "type":"Services"
        }
    ],
    "sg:phone":"+1 404 815 0185",
    "sg:postcode":"30313",
    "sg:province":"GA",
    "wof:name":"Management Decisions",
    "wof:placetype":"venue"
},
  "geometry": {"coordinates":[-84.397042,33.769452],"type":"Point"}
}