{
  "type": "Feature",
  "properties": {
    "iso:country":"US",
    "sg:address":"324 Pine St",
    "sg:city":"Eastman",
    "sg:classifiers":[
        {
            "category":"Social Services",
            "subcategory":"Child Care",
            "type":"Services"
        }
    ],
    "sg:phone":"+1 478 374 4788",
    "sg:postcode":"31023",
    "sg:province":"GA",
    "sg:tags":[
        "kindergarten",
        "academic",
        "school"
    ],
    "wof:name":"Dodge County Head Start",
    "wof:placetype":"venue"
},
  "geometry": {"coordinates":[-83.17763600000001,32.195643],"type":"Point"}
}