{
  "type": "Feature",
  "properties": {
    "addr:full":"103 Margaret St La Fayette GA 30728",
    "addr:housenumber":"103",
    "addr:postcode":"30728",
    "addr:street":"Margaret St;Fayette",
    "iso:country":"US",
    "sg:address":"103 Margaret St",
    "sg:city":"La Fayette",
    "sg:classifiers":[
        {
            "category":"Personal",
            "subcategory":"Beauty Salon",
            "type":"Services"
        }
    ],
    "sg:phone":"+1 706 638 6400",
    "sg:postcode":"30728",
    "sg:province":"GA",
    "sg:tags":[
        "shop"
    ],
    "wof:name":"Head Quarters",
    "wof:placetype":"venue"
},
  "geometry": {"coordinates":[-85.28147800000001,34.708599],"type":"Point"}
}