{
  "type": "Feature",
  "properties": {
    "addr:full":"4095 Jonesboro Rd Forest Park GA 30297",
    "addr:housenumber":"4095",
    "addr:postcode":"30297",
    "addr:street":"Jonesboro Rd",
    "iso:country":"US",
    "sg:address":"4095 Jonesboro Rd",
    "sg:city":"Forest Park",
    "sg:classifiers":[
        {
            "category":"Building & Trades",
            "subcategory":"Locksmith",
            "type":"Services"
        }
    ],
    "sg:phone":"+1 678 269 7241",
    "sg:postcode":"30297",
    "sg:province":"GA",
    "sg:tags":[
        "key"
    ],
    "wof:name":"7 Days Emergency Locksmith",
    "wof:placetype":"venue"
},
  "geometry": {"coordinates":[-84.363128,33.642792],"type":"Point"}
}