{
  "type": "Feature",
  "properties": {
    "iso:country":"US",
    "sg:address":"5440 Thomaston Rd",
    "sg:city":"Macon",
    "sg:classifiers":[
        {
            "category":"Personal",
            "subcategory":"Beauty Salon",
            "type":"Services"
        }
    ],
    "sg:phone":"+1 478 405 9800",
    "sg:postcode":"31220",
    "sg:province":"GA",
    "sg:tags":[
        "nail",
        "manicuring"
    ],
    "wof:name":"Sun Nail 2",
    "wof:placetype":"venue"
},
  "geometry": {"coordinates":[-83.73968600000001,32.833919],"type":"Point"}
}