{
  "type": "Feature",
  "properties": {
    "iso:country":"US",
    "sg:address":"2145 Roswell Rd",
    "sg:city":"Marietta",
    "sg:classifiers":[
        {
            "category":"Shopping",
            "subcategory":"Hobbies, Toys, & Games",
            "type":"Retail Goods"
        }
    ],
    "sg:phone":"+1 678 560 8980",
    "sg:postcode":"30062",
    "sg:province":"GA",
    "sg:tags":[
        "model",
        "supply"
    ],
    "wof:name":"Marietta Hobbies",
    "wof:placetype":"venue"
},
  "geometry": {"coordinates":[-84.49086800000001,33.966713],"type":"Point"}
}