{
  "type": "Feature",
  "properties": {
    "iso:country":"US",
    "sg:address":"1813 Candler Rd",
    "sg:city":"Decatur",
    "sg:classifiers":[
        {
            "category":"Wholesale",
            "subcategory":"Stationery",
            "type":"Manufacturing & Wholesale Goods"
        },
        {
            "category":"Shopping",
            "subcategory":"Stationery & Office Supplies",
            "type":"Retail Goods"
        }
    ],
    "sg:phone":"+1 404 284 5446",
    "sg:postcode":"30032",
    "sg:province":"GA",
    "wof:name":"Curtis Office Products Inc",
    "wof:placetype":"venue"
},
  "geometry": {"coordinates":[-84.28739299999999,33.737576],"type":"Point"}
}