{
  "type": "Feature",
  "properties": {
    "addr:full":"336 Karen Dr Alpharetta GA 30004",
    "addr:housenumber":"336",
    "addr:postcode":"30004",
    "addr:street":"Karen Dr",
    "iso:country":"US",
    "sg:address":"336 Karen Dr",
    "sg:city":"Alpharetta",
    "sg:classifiers":[
        {
            "category":"Building & Trades",
            "subcategory":"Construction",
            "type":"Services"
        }
    ],
    "sg:phone":"+1 678 366 2226",
    "sg:postcode":"30004",
    "sg:province":"GA",
    "sg:tags":[
        "house"
    ],
    "wof:name":"Signature Remodeling LLC",
    "wof:placetype":"venue"
},
  "geometry": {"coordinates":[-84.297293,34.068052],"type":"Point"}
}