{
  "type": "Feature",
  "properties": {
    "addr:full":"310 45th St Columbus GA 31904",
    "addr:housenumber":"310",
    "addr:postcode":"31904",
    "addr:street":"45Th St",
    "iso:country":"US",
    "sg:address":"310 45th St",
    "sg:city":"Columbus",
    "sg:classifiers":[
        {
            "category":"Freight",
            "type":"Transportation"
        }
    ],
    "sg:phone":"+1 706 322 4428",
    "sg:postcode":"31904",
    "sg:province":"GA",
    "sg:tags":[
        "trucking"
    ],
    "sg:website":"www.yellowfreight.com",
    "wof:name":"Yellow Transportation Inc",
    "wof:placetype":"venue"
},
  "geometry": {"coordinates":[-84.984425,32.507053],"type":"Point"}
}