{
  "type": "Feature",
  "properties": {
    "addr:full":"7320 Central Ave Savannah GA 31406",
    "addr:housenumber":"7320",
    "addr:postcode":"31406",
    "addr:street":"Central Ave",
    "iso:country":"US",
    "sg:address":"7320 Central Ave",
    "sg:city":"Savannah",
    "sg:classifiers":[
        {
            "category":"Wholesale",
            "subcategory":"Medical Equipment & Supplies",
            "type":"Manufacturing & Wholesale Goods"
        }
    ],
    "sg:phone":"+1 912 355 9494",
    "sg:postcode":"31406",
    "sg:province":"GA",
    "sg:tags":[
        "disposable"
    ],
    "wof:name":"Life Systems Inc",
    "wof:placetype":"venue"
},
  "geometry": {"coordinates":[-81.075783,31.990071],"type":"Point"}
}