{
  "type": "Feature",
  "properties": {
    "iso:country":"US",
    "sg:address":"115 Bacon St",
    "sg:city":"Nahunta",
    "sg:classifiers":[
        {
            "category":"Government",
            "subcategory":"Office",
            "type":"Public Place"
        }
    ],
    "sg:phone":"+1 912 462 5380",
    "sg:postcode":"31553",
    "sg:province":"GA",
    "wof:name":"Brantley County Medical Svc",
    "wof:placetype":"venue"
},
  "geometry": {"coordinates":[-81.979944,31.205844],"type":"Point"}
}