{
  "type": "Feature",
  "properties": {
    "iso:country":"US",
    "sg:address":"947 Newport Rd",
    "sg:city":"Macon",
    "sg:classifiers":[
        {
            "category":"Professional",
            "subcategory":"Business Services",
            "type":"Services"
        }
    ],
    "sg:phone":"+1 478 474 1543",
    "sg:postcode":"31210",
    "sg:province":"GA",
    "wof:name":"Heart of GA Gun & Knife Show",
    "wof:placetype":"venue"
},
  "geometry": {"coordinates":[-83.696358,32.890437],"type":"Point"}
}