{
  "type": "Feature",
  "properties": {
    "iso:country":"US",
    "sg:address":"924 E Shotwell St",
    "sg:city":"Bainbridge",
    "sg:classifiers":[
        {
            "category":"Home & Garden",
            "subcategory":"Building Materials",
            "type":"Retail Goods"
        }
    ],
    "sg:phone":"+1 229 246 2917",
    "sg:postcode":"39819",
    "sg:province":"FL",
    "sg:tags":[
        "paint",
        "covering"
    ],
    "wof:name":"Sherwin-Williams Paints",
    "wof:placetype":"venue"
},
  "geometry": {"coordinates":[-84.565246,30.903899],"type":"Point"}
}