{
  "type": "Feature",
  "properties": {
    "addr:full":"302 Auburn Ave Atlanta GA 30303",
    "addr:housenumber":"302",
    "addr:postcode":"30303",
    "addr:street":"Auburn Ave",
    "iso:country":"US",
    "sg:address":"302 Auburn Ave",
    "sg:city":"Atlanta",
    "sg:classifiers":[
        {
            "category":"Food & Beverages",
            "subcategory":"Ethnic Foods",
            "type":"Retail Goods"
        }
    ],
    "sg:phone":"+1 404 688 5855",
    "sg:postcode":"30303",
    "sg:province":"GA",
    "sg:tags":[
        "soul"
    ],
    "wof:name":"Thelma's Kitchen",
    "wof:placetype":"venue"
},
  "geometry": {"coordinates":[-84.377792,33.755705],"type":"Point"}
}