{
  "type": "Feature",
  "properties": {
    "addr:full":"1670 Rolling Meadows Ct Young Harris GA 30546",
    "addr:housenumber":"1670",
    "addr:postcode":"30546",
    "addr:street":"Rolling Meadows Ct",
    "iso:country":"US",
    "sg:address":"1670 Rolling Meadows Ct",
    "sg:city":"Young Harris",
    "sg:classifiers":[
        {
            "category":"Wholesale",
            "subcategory":"Medical Equipment & Supplies",
            "type":"Manufacturing & Wholesale Goods"
        }
    ],
    "sg:phone":"+1 706 379 3055",
    "sg:postcode":"30546",
    "sg:province":"GA",
    "wof:name":"Shared Medical Technologies",
    "wof:placetype":"venue"
},
  "geometry": {"coordinates":[-83.851061,34.972888],"type":"Point"}
}