{
  "type": "Feature",
  "properties": {
    "addr:full":"2255 Pleasant Hill Rd Duluth GA 30096",
    "addr:housenumber":"2255",
    "addr:postcode":"30096",
    "addr:street":"Pleasant Hill Rd",
    "iso:country":"US",
    "sg:address":"2255 Pleasant Hill Rd",
    "sg:city":"Duluth",
    "sg:classifiers":[
        {
            "category":"Shopping",
            "subcategory":"Stationery & Office Supplies",
            "type":"Retail Goods"
        },
        {
            "category":"Professional",
            "subcategory":"Printing & Photocopies",
            "type":"Services"
        }
    ],
    "sg:phone":"+1 678 474 4761",
    "sg:postcode":"30096",
    "sg:province":"GA",
    "sg:tags":[
        "equipment"
    ],
    "wof:name":"Staples the Office Superstore",
    "wof:placetype":"venue"
},
  "geometry": {"coordinates":[-84.136803,33.961899],"type":"Point"}
}