{
  "type": "Feature",
  "properties": {
    "iso:country":"US",
    "sg:address":"2386 Clower St SW",
    "sg:city":"Snellville",
    "sg:classifiers":[
        {
            "category":"Wholesale",
            "subcategory":"Auto Parts",
            "type":"Manufacturing & Wholesale Goods"
        }
    ],
    "sg:phone":"+1 770 982 2100",
    "sg:postcode":"30078",
    "sg:province":"GA",
    "sg:tags":[
        "automobile",
        "supply"
    ],
    "wof:name":"DWC",
    "wof:placetype":"venue"
},
  "geometry": {"coordinates":[-84.015005,33.859077],"type":"Point"}
}