{
  "type": "Feature",
  "properties": {
    "iso:country":"US",
    "sg:address":"435 Park Creek Dr",
    "sg:city":"Alpharetta",
    "sg:classifiers":[
        {
            "category":"Shopping",
            "subcategory":"Catalog Store",
            "type":"Retail Goods"
        }
    ],
    "sg:phone":"+1 770 772 6066",
    "sg:postcode":"30005",
    "sg:province":"GA",
    "sg:tags":[
        "mail",
        "house"
    ],
    "wof:name":"Twin Thoughts",
    "wof:placetype":"venue"
},
  "geometry": {"coordinates":[-84.237397,34.063073],"type":"Point"}
}