{
  "type": "Feature",
  "properties": {
    "addr:full":"38 Camellia Cir Newnan GA 30263",
    "addr:housenumber":"38",
    "addr:postcode":"30263",
    "addr:street":"Camellia Cir",
    "iso:country":"US",
    "sg:address":"38 Camellia Cir",
    "sg:city":"Newnan",
    "sg:classifiers":[
        {
            "category":"Professional",
            "type":"Services"
        }
    ],
    "sg:phone":"+1 770 251 3336",
    "sg:postcode":"30263",
    "sg:province":"GA",
    "wof:name":"William Lam Inc",
    "wof:placetype":"venue"
},
  "geometry": {"coordinates":[-84.771776,33.408954],"type":"Point"}
}