{
  "type": "Feature",
  "properties": {
    "addr:full":"15 N Steele St La Fayette GA 30728",
    "addr:housenumber":"15",
    "addr:postcode":"30728",
    "addr:street":"N Steele St;Fayette",
    "iso:country":"US",
    "sg:address":"15 N Steele St",
    "sg:city":"La Fayette",
    "sg:classifiers":[
        {
            "category":"Professional",
            "type":"Services"
        }
    ],
    "sg:phone":"+1 706 638 5764",
    "sg:postcode":"30728",
    "sg:province":"GA",
    "wof:name":"Melvin Frazier",
    "wof:placetype":"venue"
},
  "geometry": {"coordinates":[-85.290065,34.710762],"type":"Point"}
}