{
  "type": "Feature",
  "properties": {
    "addr:full":"101 N Peterson Ave Douglas GA 31533",
    "addr:housenumber":"101",
    "addr:postcode":"31533",
    "addr:street":"N Peterson Ave",
    "iso:country":"US",
    "sg:address":"101 N Peterson Ave",
    "sg:city":"Douglas",
    "sg:classifiers":[
        {
            "category":"Manufacturing",
            "subcategory":"Petroleum Products",
            "type":"Manufacturing & Wholesale Goods"
        }
    ],
    "sg:phone":"+1 912 384 8114",
    "sg:postcode":"31533",
    "sg:province":"GA",
    "sg:tags":[
        "asphalt"
    ],
    "wof:name":"Douglas Asphalt Co",
    "wof:placetype":"venue"
},
  "geometry": {"coordinates":[-82.85037199999999,31.509466],"type":"Point"}
}