{
  "type": "Feature",
  "properties": {
    "iso:country":"US",
    "sg:address":"700 Country Lake Ct",
    "sg:city":"Mcdonough",
    "sg:classifiers":[
        {
            "category":"Professional",
            "subcategory":"Business Services",
            "type":"Services"
        },
        {
            "category":"Manufacturing",
            "subcategory":"Tools & Machinery",
            "type":"Manufacturing & Wholesale Goods"
        }
    ],
    "sg:phone":"+1 770 898 3989",
    "sg:postcode":"30252",
    "sg:province":"GA",
    "sg:tags":[
        "sprinkler",
        "contractor"
    ],
    "wof:name":"Vaughn & Co",
    "wof:placetype":"venue"
},
  "geometry": {"coordinates":[-84.093712,33.493235],"type":"Point"}
}