{
  "type": "Feature",
  "properties": {
    "addr:full":"311 W Broad St Sparta GA 31087",
    "addr:housenumber":"311",
    "addr:postcode":"31087",
    "addr:street":"W Broad St",
    "iso:country":"US",
    "sg:address":"311 W Broad St",
    "sg:city":"Sparta",
    "sg:classifiers":[
        {
            "category":"Food & Beverages",
            "subcategory":"Groceries & Convenience Stores",
            "type":"Retail Goods"
        }
    ],
    "sg:phone":"+1 706 444 6889",
    "sg:postcode":"31087",
    "sg:province":"GA",
    "wof:name":"Corner Pantry",
    "wof:placetype":"venue"
},
  "geometry": {"coordinates":[-82.98419,33.274162],"type":"Point"}
}