{
  "type": "Feature",
  "properties": {
    "addr:full":"1536 Stella Ave Vidalia GA 30474",
    "addr:housenumber":"1536",
    "addr:postcode":"30474",
    "addr:street":"Stella Ave",
    "iso:country":"US",
    "sg:address":"1536 Stella Ave",
    "sg:city":"Vidalia",
    "sg:classifiers":[
        {
            "category":"Real Estate",
            "subcategory":"Real Estate Operator",
            "type":"Services"
        }
    ],
    "sg:phone":"+1 912 537 2193",
    "sg:postcode":"30474",
    "sg:province":"GA",
    "sg:tags":[
        "building",
        "nonresidential"
    ],
    "wof:name":"J & S Properties of Vidalia",
    "wof:placetype":"venue"
},
  "geometry": {"coordinates":[-82.404274,32.189018],"type":"Point"}
}