{
  "type": "Feature",
  "properties": {
    "iso:country":"US",
    "sg:address":"490 Great Southwest Pkwy SW",
    "sg:city":"Atlanta",
    "sg:classifiers":[
        {
            "category":"Manufacturing",
            "subcategory":"Chemicals & Compounds",
            "type":"Manufacturing & Wholesale Goods"
        }
    ],
    "sg:phone":"+1 404 696 9861",
    "sg:postcode":"30336",
    "sg:province":"GA",
    "sg:tags":[
        "water",
        "ink",
        "printing",
        "based",
        "mfg"
    ],
    "wof:name":"Brewers Ink of Georgia",
    "wof:placetype":"venue"
},
  "geometry": {"coordinates":[-84.56702900000001,33.745415],"type":"Point"}
}