{
  "type": "Feature",
  "properties": {
    "iso:country":"US",
    "sg:address":"809 Amaranth Ave",
    "sg:city":"Savannah",
    "sg:classifiers":[
        {
            "category":"Organizations",
            "subcategory":"Community Association",
            "type":"Services"
        }
    ],
    "sg:phone":"+1 912 236 7966",
    "sg:postcode":"31405",
    "sg:province":"GA",
    "wof:name":"Jackson Pk Neighborhood Watch",
    "wof:placetype":"venue"
},
  "geometry": {"coordinates":[-81.113849,32.050253],"type":"Point"}
}