{
  "type": "Feature",
  "properties": {
    "addr:full":"2455 Windridge Dr NE Conyers GA 30013",
    "addr:housenumber":"2455",
    "addr:postcode":"30013",
    "addr:street":"Windridge Dr Ne",
    "iso:country":"US",
    "sg:address":"2455 Windridge Dr NE",
    "sg:city":"Conyers",
    "sg:classifiers":[
        {
            "category":"Professional",
            "subcategory":"Business Services",
            "type":"Services"
        }
    ],
    "sg:phone":"+1 770 860 1622",
    "sg:postcode":"30013",
    "sg:province":"GA",
    "wof:name":"Bella Donna Svcs",
    "wof:placetype":"venue"
},
  "geometry": {"coordinates":[-83.967202,33.675743],"type":"Point"}
}