{
  "type": "Feature",
  "properties": {
    "addr:full":"1925 Variations Dr NE Atlanta GA 30329",
    "addr:housenumber":"1925",
    "addr:postcode":"30329",
    "addr:street":"Variations Dr Ne",
    "iso:country":"US",
    "sg:address":"1925 Variations Dr NE",
    "sg:city":"Atlanta",
    "sg:classifiers":[
        {
            "category":"Freight",
            "type":"Transportation"
        }
    ],
    "sg:phone":"+1 404 762 8599",
    "sg:postcode":"30329",
    "sg:province":"GA",
    "wof:name":"Global Freight Solutions Inc",
    "wof:placetype":"venue"
},
  "geometry": {"coordinates":[-84.309635,33.857495],"type":"Point"}
}