{
  "type": "Feature",
  "properties": {
    "iso:country":"US",
    "sg:address":"147 Lake Dr",
    "sg:city":"Cordele",
    "sg:classifiers":[
        {
            "category":"Organizations",
            "subcategory":"Religious Organization",
            "type":"Services"
        }
    ],
    "sg:phone":"+1 229 273 8677",
    "sg:postcode":"31015",
    "sg:province":"GA",
    "wof:name":"Davis Chapel Methodist Church",
    "wof:placetype":"venue"
},
  "geometry": {"coordinates":[-83.90533600000001,31.874369],"type":"Point"}
}