{
  "type": "Feature",
  "properties": {
    "addr:full":"4811 Ridge Rd Douglasville GA 30134",
    "addr:housenumber":"4811",
    "addr:postcode":"30134",
    "addr:street":"Ridge Rd",
    "iso:country":"US",
    "sg:address":"4811 Ridge Rd",
    "sg:city":"Douglasville",
    "sg:classifiers":[
        {
            "category":"Restaurant",
            "type":"Food & Drink"
        }
    ],
    "sg:phone":"+1 678 715 2999",
    "sg:postcode":"30134",
    "sg:province":"GA",
    "wof:name":"Subway Sandwiches & Salads",
    "wof:placetype":"venue"
},
  "geometry": {"coordinates":[-84.804469,33.821276],"type":"Point"}
}