{
  "type": "Feature",
  "properties": {
    "iso:country":"US",
    "sg:address":"1140 University Dr NE",
    "sg:city":"Atlanta",
    "sg:classifiers":[
        {
            "category":"Social Services",
            "subcategory":"Child Care",
            "type":"Services"
        },
        {
            "category":"Education",
            "subcategory":"School",
            "type":"Public Place"
        }
    ],
    "sg:phone":"+1 404 873 1212",
    "sg:postcode":"30306",
    "sg:province":"GA",
    "sg:website":"www.atlantajcc.org",
    "wof:name":"Keshet Pre School",
    "wof:placetype":"venue"
},
  "geometry": {"coordinates":[-84.349146,33.791199],"type":"Point"}
}