{
  "type": "Feature",
  "properties": {
    "addr:full":"22 W Jefferson St Hazlehurst GA 31539",
    "addr:housenumber":"22",
    "addr:postcode":"31539",
    "addr:street":"W Jefferson St",
    "iso:country":"US",
    "sg:address":"22 W Jefferson St",
    "sg:city":"Hazlehurst",
    "sg:classifiers":[
        {
            "category":"Health Services",
            "subcategory":"Doctor",
            "type":"Services"
        }
    ],
    "sg:phone":"+1 912 375 7575",
    "sg:postcode":"31539",
    "sg:province":"GA",
    "sg:tags":[
        "dentist"
    ],
    "wof:name":"Dana E Fender DDS",
    "wof:placetype":"venue"
},
  "geometry": {"coordinates":[-82.605073,31.862578],"type":"Point"}
}