{
  "type": "Feature",
  "properties": {
    "iso:country":"US",
    "sg:address":"3401 Treecrest Pkwy",
    "sg:city":"Decatur",
    "sg:classifiers":[
        {
            "category":"Banks & Credit Unions",
            "subcategory":"Investment Brokerage",
            "type":"Services"
        }
    ],
    "sg:phone":"+1 770 808 0240",
    "sg:postcode":"30035",
    "sg:province":"GA",
    "wof:name":"A1 Entreprenuer Invstmnt LLC",
    "wof:placetype":"venue"
},
  "geometry": {"coordinates":[-84.185934,33.712884],"type":"Point"}
}