{
  "type": "Feature",
  "properties": {
    "addr:full":"143 Lytle Rd Rossville GA 30741",
    "addr:housenumber":"143",
    "addr:postcode":"30741",
    "addr:street":"Lytle Rd",
    "iso:country":"US",
    "sg:address":"143 Lytle Rd",
    "sg:city":"Rossville",
    "sg:classifiers":[
        {
            "category":"Real Estate",
            "subcategory":"Real Estate Operator",
            "type":"Services"
        }
    ],
    "sg:phone":"+1 706 861 0645",
    "sg:postcode":"30741",
    "sg:province":"GA",
    "sg:tags":[
        "mobile",
        "home",
        "site"
    ],
    "wof:name":"Tree & Sky Park For MBL Homes",
    "wof:placetype":"venue"
},
  "geometry": {"coordinates":[-85.297254,34.933719],"type":"Point"}
}