{
  "type": "Feature",
  "properties": {
    "iso:country":"US",
    "sg:address":"2971 Flowers Rd S Ste 118",
    "sg:city":"Atlanta",
    "sg:classifiers":[
        {
            "category":"Wholesale",
            "subcategory":"Hardware",
            "type":"Manufacturing & Wholesale Goods"
        },
        {
            "category":"Wholesale",
            "subcategory":"Machinery & Supplies",
            "type":"Manufacturing & Wholesale Goods"
        }
    ],
    "sg:phone":"+1 770 451 8436",
    "sg:postcode":"30341",
    "sg:province":"GA",
    "sg:tags":[
        "compressor",
        "compressors-wholesale"
    ],
    "wof:name":"A-C Compressor Corp",
    "wof:placetype":"venue"
},
  "geometry": {"coordinates":[-84.26697,33.870912],"type":"Point"}
}