{
  "type": "Feature",
  "properties": {
    "iso:country":"US",
    "sg:address":"2415 Fletcher Rd",
    "sg:city":"Hinesville",
    "sg:classifiers":[
        {
            "category":"Professional",
            "subcategory":"Business Services",
            "type":"Services"
        }
    ],
    "sg:phone":"+1 912 877 7402",
    "sg:postcode":"31313",
    "sg:province":"GA",
    "wof:name":"El Elyon Construction",
    "wof:placetype":"venue"
},
  "geometry": {"coordinates":[-81.62487,31.784041],"type":"Point"}
}