{
  "type": "Feature",
  "properties": {
    "addr:full":"3193 Howell Mill Rd NW Atlanta GA 30327",
    "addr:housenumber":"3193",
    "addr:postcode":"30327",
    "addr:street":"Howell Mill Rd Nw",
    "iso:country":"US",
    "sg:address":"3193 Howell Mill Rd NW",
    "sg:city":"Atlanta",
    "sg:classifiers":[
        {
            "category":"Health Services",
            "subcategory":"Doctor",
            "type":"Services"
        }
    ],
    "sg:phone":"+1 404 355 1312",
    "sg:postcode":"30327",
    "sg:province":"GA",
    "sg:tags":[
        "physician",
        "reconstructive",
        "surgeons",
        "plastic",
        "surgeon"
    ],
    "sg:website":"http://www.sinussurgery.com",
    "wof:name":"Atlanta Center For E.N.T. & Facial Plastic Surgery",
    "wof:placetype":"venue"
},
  "geometry": {"coordinates":[-84.427268,33.840715],"type":"Point"}
}