{
  "type": "Feature",
  "properties": {
    "iso:country":"US",
    "sg:address":"2346 Basswood Dr",
    "sg:city":"Augusta",
    "sg:classifiers":[
        {
            "category":"Professional",
            "subcategory":"Management & Consulting",
            "type":"Services"
        }
    ],
    "sg:phone":"+1 706 796 6501",
    "sg:postcode":"30906",
    "sg:province":"GA",
    "sg:tags":[
        "promotion",
        "sales"
    ],
    "wof:name":"Private Page",
    "wof:placetype":"venue"
},
  "geometry": {"coordinates":[-82.067352,33.358107],"type":"Point"}
}