{
  "type": "Feature",
  "properties": {
    "iso:country":"US",
    "sg:address":"203 College Ave",
    "sg:city":"Elberton",
    "sg:classifiers":[
        {
            "category":"Government",
            "subcategory":"Office",
            "type":"Public Place"
        }
    ],
    "sg:phone":"+1 706 213 2038",
    "sg:postcode":"30635",
    "sg:province":"GA",
    "wof:name":"Elbert County Group Home",
    "wof:placetype":"venue"
},
  "geometry": {"coordinates":[-82.87275099999999,34.115893],"type":"Point"}
}