{
  "type": "Feature",
  "properties": {
    "iso:country":"US",
    "sg:address":"45 Hill St",
    "sg:city":"Statesboro",
    "sg:classifiers":[
        {
            "category":"Home & Garden",
            "subcategory":"Furniture",
            "type":"Retail Goods"
        }
    ],
    "sg:phone":"+1 912 764 3561",
    "sg:postcode":"30458",
    "sg:province":"GA",
    "sg:tags":[
        "top",
        "counter"
    ],
    "wof:name":"Coastal Counter Top Distrs Inc",
    "wof:placetype":"venue"
},
  "geometry": {"coordinates":[-81.78025,32.450472],"type":"Point"}
}