{
  "type": "Feature",
  "properties": {
    "addr:full":"400 Okefenokee Dr Folkston GA 31537",
    "addr:housenumber":"400",
    "addr:postcode":"31537",
    "addr:street":"Okefenokee Dr",
    "iso:country":"US",
    "sg:address":"400 Okefenokee Dr",
    "sg:city":"Folkston",
    "sg:classifiers":[
        {
            "category":"Insurance",
            "subcategory":"Hazard Insurance",
            "type":"Services"
        }
    ],
    "sg:phone":"+1 912 496 2556",
    "sg:postcode":"31537",
    "sg:province":"GA",
    "sg:tags":[
        "bond"
    ],
    "wof:name":"Chancey Bail Bonding",
    "wof:placetype":"venue"
},
  "geometry": {"coordinates":[-82.012619,30.839063],"type":"Point"}
}