{
  "type": "Feature",
  "properties": {
    "iso:country":"US",
    "sg:address":"3115 Green Gate Way SE",
    "sg:city":"Conyers",
    "sg:classifiers":[
        {
            "category":"Banks & Credit Unions",
            "subcategory":"Bank",
            "type":"Services"
        }
    ],
    "sg:phone":"+1 770 760 9053",
    "sg:postcode":"30013",
    "sg:province":"GA",
    "sg:tags":[
        "depository",
        "banking"
    ],
    "wof:name":"Bakers Rack Cakes & Cater",
    "wof:placetype":"venue"
},
  "geometry": {"coordinates":[-83.995833,33.611043],"type":"Point"}
}