{
  "type": "Feature",
  "properties": {
    "iso:country":"US",
    "sg:address":"2165 W Park Ct",
    "sg:city":"Stone Mountain",
    "sg:classifiers":[
        {
            "category":"Professional",
            "subcategory":"Management & Consulting",
            "type":"Services"
        }
    ],
    "sg:phone":"+1 770 879 8424",
    "sg:postcode":"30087",
    "sg:province":"GA",
    "sg:tags":[
        "marketing",
        "program"
    ],
    "wof:name":"Taylormade Marketing LLC",
    "wof:placetype":"venue"
},
  "geometry": {"coordinates":[-84.11632899999999,33.817689],"type":"Point"}
}