{
  "type": "Feature",
  "properties": {
    "addr:full":"1628 State Rte 115 E Cleveland GA 30528",
    "addr:housenumber":"1628",
    "addr:postcode":"30528",
    "addr:street":"State Rte 115 E",
    "iso:country":"US",
    "sg:address":"1628 State Rte 115 E",
    "sg:city":"Cleveland",
    "sg:classifiers":[
        {
            "category":"Home & Garden",
            "subcategory":"Building Materials",
            "type":"Retail Goods"
        }
    ],
    "sg:phone":"+1 706 865 0104",
    "sg:postcode":"30528",
    "sg:province":"GA",
    "sg:tags":[
        "door"
    ],
    "wof:name":"Elite Garage Doors",
    "wof:placetype":"venue"
},
  "geometry": {"coordinates":[-83.733816,34.590388],"type":"Point"}
}