{
  "type": "Feature",
  "properties": {
    "addr:full":"802 Maple Dr Statesboro GA 30461",
    "addr:housenumber":"802",
    "addr:postcode":"30461",
    "addr:street":"Maple Dr",
    "iso:country":"US",
    "sg:address":"802 Maple Dr",
    "sg:city":"Statesboro",
    "sg:classifiers":[
        {
            "category":"Social Services",
            "subcategory":"Child Care",
            "type":"Services"
        }
    ],
    "sg:phone":"+1 912 764 2658",
    "sg:postcode":"30461",
    "sg:province":"GA",
    "sg:tags":[
        "day"
    ],
    "wof:name":"Playroom For Infants & Chldrn",
    "wof:placetype":"venue"
},
  "geometry": {"coordinates":[-81.750062,32.449945],"type":"Point"}
}