{
  "type": "Feature",
  "properties": {
    "addr:full":"244 Kurtz Rd Marietta GA 30066",
    "addr:housenumber":"244",
    "addr:postcode":"30066",
    "addr:street":"Kurtz Rd",
    "iso:country":"US",
    "sg:address":"244 Kurtz Rd",
    "sg:city":"Marietta",
    "sg:classifiers":[
        {
            "category":"Organizations",
            "subcategory":"Religious Organization",
            "type":"Services"
        }
    ],
    "sg:phone":"+1 770 422 1089",
    "sg:postcode":"30066",
    "sg:province":"GA",
    "sg:tags":[
        "church"
    ],
    "sg:website":"www.stpaulumc.com",
    "wof:name":"St Paul United Methodist Chr",
    "wof:placetype":"venue"
},
  "geometry": {"coordinates":[-84.544855,34.002913],"type":"Point"}
}