{
  "type": "Feature",
  "properties": {
    "iso:country":"US",
    "sg:address":"6141 Oakbrook Pkwy",
    "sg:city":"Norcross",
    "sg:classifiers":[
        {
            "category":"Professional",
            "type":"Services"
        }
    ],
    "sg:phone":"+1 770 449 6020",
    "sg:postcode":"30093",
    "sg:province":"GA",
    "wof:name":"Cool Engery",
    "wof:placetype":"venue"
},
  "geometry": {"coordinates":[-84.202929,33.912733],"type":"Point"}
}