{
  "type": "Feature",
  "properties": {
    "iso:country":"US",
    "sg:address":"11 Gaberonne Ct NE",
    "sg:city":"Atlanta",
    "sg:classifiers":[
        {
            "category":"Personal",
            "subcategory":"Beauty Salon",
            "type":"Services"
        }
    ],
    "sg:phone":"+1 404 233 5786",
    "sg:postcode":"30324",
    "sg:province":"GA",
    "sg:tags":[
        "cosmetics-wholesale",
        "manufacturer"
    ],
    "sg:website":"http://www.sesderma.com",
    "wof:name":"Sesvalia Usa",
    "wof:placetype":"venue"
},
  "geometry": {"coordinates":[-84.350647,33.827628],"type":"Point"}
}