{
  "type": "Feature",
  "properties": {
    "addr:full":"1140 Hammond Dr NE Atlanta GA 30328",
    "addr:housenumber":"1140",
    "addr:postcode":"30328",
    "addr:street":"Hammond Dr Ne",
    "iso:country":"US",
    "sg:address":"1140 Hammond Dr NE",
    "sg:city":"Atlanta",
    "sg:classifiers":[
        {
            "category":"Health Services",
            "subcategory":"Chiropractor",
            "type":"Services"
        }
    ],
    "sg:phone":"+1 770 901 9303",
    "sg:postcode":"30328",
    "sg:province":"GA",
    "wof:name":"Dagnew Bethlehem Dr DC",
    "wof:placetype":"venue"
},
  "geometry": {"coordinates":[-84.3494,33.918956],"type":"Point"}
}