{
  "type": "Feature",
  "properties": {
    "iso:country":"US",
    "sg:address":"153 H Powell Rd",
    "sg:city":"Lyons",
    "sg:classifiers":[
        {
            "category":"Farming",
            "subcategory":"Nursery",
            "type":"Manufacturing & Wholesale Goods"
        }
    ],
    "sg:phone":"+1 912 565 7238",
    "sg:postcode":"30436",
    "sg:province":"GA",
    "sg:tags":[
        "ornamental"
    ],
    "wof:name":"C & M Greenhouses",
    "wof:placetype":"venue"
},
  "geometry": {"coordinates":[-82.34902200000001,32.001625],"type":"Point"}
}