{
  "type": "Feature",
  "properties": {
    "addr:full":"7 Pine Ridge Dr Newnan GA 30263",
    "addr:housenumber":"7",
    "addr:postcode":"30263",
    "addr:street":"Pine Ridge Dr",
    "iso:country":"US",
    "sg:address":"7 Pine Ridge Dr",
    "sg:city":"Newnan",
    "sg:classifiers":[
        {
            "category":"Real Estate",
            "subcategory":"Real Estate Agent",
            "type":"Services"
        }
    ],
    "sg:phone":"+1 770 251 1515",
    "sg:postcode":"30263",
    "sg:province":"GA",
    "wof:name":"Kilgore Realty Inc",
    "wof:placetype":"venue"
},
  "geometry": {"coordinates":[-84.774766,33.423003],"type":"Point"}
}