{
  "type": "Feature",
  "properties": {
    "iso:country":"US",
    "sg:address":"310 E 3rd St",
    "sg:city":"Donalsonville",
    "sg:classifiers":[
        {
            "category":"Restaurant",
            "type":"Food & Drink"
        }
    ],
    "sg:phone":"+1 229 524 5059",
    "sg:postcode":"31794",
    "sg:province":"GA",
    "sg:website":"www.hardees.com",
    "wof:name":"Hardee's",
    "wof:placetype":"venue"
},
  "geometry": {"coordinates":[-83.509334,31.452413],"type":"Point"}
}