{
  "type": "Feature",
  "properties": {
    "addr:full":"3263 Davis Dr Valdosta GA 31606",
    "addr:housenumber":"3263",
    "addr:postcode":"31606",
    "addr:street":"Davis Dr",
    "iso:country":"US",
    "sg:address":"3263 Davis Dr",
    "sg:city":"Valdosta",
    "sg:classifiers":[
        {
            "category":"Building & Trades",
            "subcategory":"Landscaping Services",
            "type":"Services"
        }
    ],
    "sg:phone":"+1 229 242 6775",
    "sg:postcode":"31606",
    "sg:province":"GA",
    "sg:tags":[
        "tree"
    ],
    "wof:name":"Pro Tree Svc Inc",
    "wof:placetype":"venue"
},
  "geometry": {"coordinates":[-83.23078,30.78022],"type":"Point"}
}