{
  "type": "Feature",
  "properties": {
    "iso:country":"US",
    "sg:address":"530 Soperton Ave",
    "sg:city":"East Dublin",
    "sg:classifiers":[
        {
            "category":"Home & Garden",
            "subcategory":"Building Materials",
            "type":"Retail Goods"
        }
    ],
    "sg:phone":"+1 478 272 2725",
    "sg:postcode":"31027",
    "sg:province":"GA",
    "wof:name":"Charlie's Surplus Bldg Mtrls",
    "wof:placetype":"venue"
},
  "geometry": {"coordinates":[-82.863337,32.542512],"type":"Point"}
}