{
  "type": "Feature",
  "properties": {
    "addr:full":"805 Emerald Ct Norcross GA 30093",
    "addr:housenumber":"805",
    "addr:postcode":"30093",
    "addr:street":"Emerald Ct",
    "iso:country":"US",
    "sg:address":"805 Emerald Ct",
    "sg:city":"Norcross",
    "sg:classifiers":[
        {
            "category":"Personal",
            "type":"Services"
        },
        {
            "category":"Professional",
            "subcategory":"Art Services",
            "type":"Services"
        }
    ],
    "sg:phone":"+1 770 921 4799",
    "sg:postcode":"30093",
    "sg:province":"GA",
    "sg:tags":[
        "photography",
        "videography",
        "wedding"
    ],
    "wof:name":"Shermemories Photography",
    "wof:placetype":"venue"
},
  "geometry": {"coordinates":[-84.184038,33.888416],"type":"Point"}
}