{
  "type": "Feature",
  "properties": {
    "addr:full":"2382 Timberwolf Ct Buford GA 30519",
    "addr:housenumber":"2382",
    "addr:postcode":"30519",
    "addr:street":"Timberwolf Ct",
    "iso:country":"US",
    "sg:address":"2382 Timberwolf Ct",
    "sg:city":"Buford",
    "sg:phone":"+1 678 765 6505",
    "sg:postcode":"30519",
    "sg:province":"GA",
    "wof:name":"Georgia Property Inspectors",
    "wof:placetype":"venue"
},
  "geometry": {"coordinates":[-83.97268099999999,34.088062],"type":"Point"}
}