{
  "type": "Feature",
  "properties": {
    "iso:country":"US",
    "sg:address":"1068 Tumblewood Trl",
    "sg:city":"Lawrenceville",
    "sg:classifiers":[
        {
            "category":"Banks & Credit Unions",
            "subcategory":"Investment Brokerage",
            "type":"Services"
        }
    ],
    "sg:phone":"+1 770 717 9215",
    "sg:postcode":"30044",
    "sg:province":"GA",
    "sg:tags":[
        "trust"
    ],
    "wof:name":"Hashigami Living Trust Th",
    "wof:placetype":"venue"
},
  "geometry": {"coordinates":[-84.12252100000001,33.925913],"type":"Point"}
}