{
  "type": "Feature",
  "properties": {
    "addr:full":"697 Davis Rd Ste 500 Stockbridge GA 30281",
    "addr:housenumber":"697",
    "addr:postcode":"30281",
    "addr:street":"Davis Rd Ste 500",
    "iso:country":"US",
    "sg:address":"697 Davis Rd Ste 500",
    "sg:city":"Stockbridge",
    "sg:classifiers":[
        {
            "category":"Home & Garden",
            "subcategory":"Household Appliances",
            "type":"Retail Goods"
        },
        {
            "category":"Communications",
            "subcategory":"Radio Station",
            "type":"Services"
        },
        {
            "category":"Shopping",
            "subcategory":"Computers & Home Electronics",
            "type":"Retail Goods"
        },
        {
            "category":"Home & Garden",
            "subcategory":"Furniture",
            "type":"Retail Goods"
        }
    ],
    "sg:phone":"+1 678 565 7655",
    "sg:postcode":"30281",
    "sg:province":"GA",
    "sg:tags":[
        "renting",
        "television",
        "leasing",
        "radio-renting",
        "equipment",
        "rental"
    ],
    "sg:website":"http://www.rentacenter.com/",
    "wof:name":"Rent-A-Center",
    "wof:placetype":"venue"
},
  "geometry": {"coordinates":[-84.256068,33.555921],"type":"Point"}
}