{
  "type": "Feature",
  "properties": {
    "iso:country":"US",
    "sg:address":"607 Washington St",
    "sg:city":"Lincolnton",
    "sg:classifiers":[
        {
            "category":"Health Services",
            "subcategory":"Clinic",
            "type":"Services"
        }
    ],
    "sg:phone":"+1 706 359 2041",
    "sg:postcode":"30817",
    "sg:province":"GA",
    "wof:name":"CSRA Home Health Agency Inc",
    "wof:placetype":"venue"
},
  "geometry": {"coordinates":[-82.48572799999999,33.782503],"type":"Point"}
}