{
  "type": "Feature",
  "properties": {
    "addr:full":"200 Beulah Church Rd Carrollton GA 30117",
    "addr:housenumber":"200",
    "addr:postcode":"30117",
    "addr:street":"Beulah Church Rd",
    "iso:country":"US",
    "sg:address":"200 Beulah Church Rd",
    "sg:city":"Carrollton",
    "sg:classifiers":[
        {
            "category":"Manufacturing",
            "subcategory":"Wood Products",
            "type":"Manufacturing & Wholesale Goods"
        }
    ],
    "sg:phone":"+1 770 838 0002",
    "sg:postcode":"30117",
    "sg:province":"GA",
    "sg:tags":[
        "mfg"
    ],
    "wof:name":"Garrett Moulding Co Inc",
    "wof:placetype":"venue"
},
  "geometry": {"coordinates":[-85.096718,33.601028],"type":"Point"}
}