{
  "type": "Feature",
  "properties": {
    "iso:country":"US",
    "sg:address":"1810 Fairpointe Trce",
    "sg:city":"Stone Mountain",
    "sg:classifiers":[
        {
            "category":"Professional",
            "type":"Services"
        }
    ],
    "sg:phone":"+1 770 322 5039",
    "sg:postcode":"30088",
    "sg:province":"GA",
    "wof:name":"McGraw Haffa Inc",
    "wof:placetype":"venue"
},
  "geometry": {"coordinates":[-84.18341700000001,33.737166],"type":"Point"}
}