{
  "type": "Feature",
  "properties": {
    "addr:full":"4481 Rowland North Dr Stone Mountain GA 30083",
    "addr:housenumber":"4481",
    "addr:postcode":"30083",
    "addr:street":"Rowland North Dr",
    "iso:country":"US",
    "sg:address":"4481 Rowland North Dr",
    "sg:city":"Stone Mountain",
    "sg:classifiers":[
        {
            "category":"Building & Trades",
            "subcategory":"Cleaning & Sanitation",
            "type":"Services"
        }
    ],
    "sg:phone":"+1 404 298 6859",
    "sg:postcode":"30083",
    "sg:province":"GA",
    "sg:tags":[
        "maintenance"
    ],
    "wof:name":"Belma Enterprises",
    "wof:placetype":"venue"
},
  "geometry": {"coordinates":[-84.20996599999999,33.774077],"type":"Point"}
}