{
  "type": "Feature",
  "properties": {
    "iso:country":"US",
    "sg:address":"886 Flagler Cir",
    "sg:city":"Smyrna",
    "sg:classifiers":[
        {
            "category":"Building & Trades",
            "subcategory":"Construction",
            "type":"Services"
        }
    ],
    "sg:phone":"+1 770 401 1090",
    "sg:postcode":"30080",
    "sg:province":"GA",
    "sg:tags":[
        "drywall",
        "contractor"
    ],
    "wof:name":"Davis Contracting Co",
    "wof:placetype":"venue"
},
  "geometry": {"coordinates":[-84.528755,33.882088],"type":"Point"}
}