{
  "type": "Feature",
  "properties": {
    "addr:full":"328 S Main St Madison GA 30650",
    "addr:housenumber":"328",
    "addr:postcode":"30650",
    "addr:street":"S Main St",
    "iso:country":"US",
    "sg:address":"328 S Main St",
    "sg:city":"Madison",
    "sg:classifiers":[
        {
            "category":"Organizations",
            "subcategory":"Religious Organization",
            "type":"Services"
        }
    ],
    "sg:phone":"+1 706 342 2177",
    "sg:postcode":"30650",
    "sg:province":"GA",
    "sg:tags":[
        "church"
    ],
    "wof:name":"Madison Baptist Church Inc",
    "wof:placetype":"venue"
},
  "geometry": {"coordinates":[-83.47004,33.593584],"type":"Point"}
}