{
  "type": "Feature",
  "properties": {
    "iso:country":"US",
    "sg:address":"460 Abbeywood Dr",
    "sg:city":"Roswell",
    "sg:classifiers":[
        {
            "category":"Banks & Credit Unions",
            "subcategory":"Investment Brokerage",
            "type":"Services"
        }
    ],
    "sg:phone":"+1 770 640 8025",
    "sg:postcode":"30075",
    "sg:province":"GA",
    "sg:tags":[
        "security"
    ],
    "wof:name":"Vee M Bundy & Assoc",
    "wof:placetype":"venue"
},
  "geometry": {"coordinates":[-84.39421400000001,34.022718],"type":"Point"}
}