{
  "type": "Feature",
  "properties": {
    "addr:full":"758 Guide Post Ln Stone Mountain GA 30088",
    "addr:housenumber":"758",
    "addr:postcode":"30088",
    "addr:street":"Guide Post Ln",
    "iso:country":"US",
    "sg:address":"758 Guide Post Ln",
    "sg:city":"Stone Mountain",
    "sg:classifiers":[
        {
            "category":"Shopping",
            "subcategory":"Catalog Store",
            "type":"Retail Goods"
        }
    ],
    "sg:phone":"+1 404 299 6327",
    "sg:postcode":"30088",
    "sg:province":"GA",
    "sg:tags":[
        "house",
        "mail",
        "telephone",
        "gift",
        "communications"
    ],
    "wof:name":"Y D C",
    "wof:placetype":"venue"
},
  "geometry": {"coordinates":[-84.19060399999999,33.773675],"type":"Point"}
}