{
  "type": "Feature",
  "properties": {
    "iso:country":"US",
    "sg:address":"1030 Cambridge Sq Ste A",
    "sg:city":"Alpharetta",
    "sg:classifiers":[
        {
            "category":"Insurance",
            "subcategory":"Hazard Insurance",
            "type":"Services"
        }
    ],
    "sg:phone":"+1 770 442 2272",
    "sg:postcode":"30009",
    "sg:province":"GA",
    "sg:tags":[
        "commercial",
        "business"
    ],
    "wof:name":"Adcock Insurance Agency Inc",
    "wof:placetype":"venue"
},
  "geometry": {"coordinates":[-84.31541799999999,34.066739],"type":"Point"}
}