{
  "type": "Feature",
  "properties": {
    "addr:full":"2203 Veterans Blvd Dublin GA 31021",
    "addr:housenumber":"2203",
    "addr:postcode":"31021",
    "addr:street":"Veterans Blvd",
    "iso:country":"US",
    "sg:address":"2203 Veterans Blvd",
    "sg:city":"Dublin",
    "sg:classifiers":[
        {
            "category":"Restaurant",
            "type":"Food & Drink"
        }
    ],
    "sg:menulink":"http://www.allmenus.com/ga/dublin/153965-zaxbys/menu/",
    "sg:phone":"+1 478 275 1070",
    "sg:postcode":"31021",
    "sg:province":"GA",
    "sg:tags":[
        "american",
        "wing"
    ],
    "wof:name":"Zaxby's",
    "wof:placetype":"venue"
},
  "geometry": {"coordinates":[-82.94194400000001,32.539033],"type":"Point"}
}