{
  "type": "Feature",
  "properties": {
    "addr:full":"2575 Monroe Dr Gainesville GA 30507",
    "addr:housenumber":"2575",
    "addr:postcode":"30507",
    "addr:street":"Monroe Dr",
    "iso:country":"US",
    "sg:address":"2575 Monroe Dr",
    "sg:city":"Gainesville",
    "sg:classifiers":[
        {
            "category":"Utilities",
            "subcategory":"Refuse",
            "type":"Services"
        }
    ],
    "sg:phone":"+1 770 287 7991",
    "sg:postcode":"30507",
    "sg:province":"GA",
    "sg:tags":[
        "landfill"
    ],
    "wof:name":"Rts Landfill/Waste Management",
    "wof:placetype":"venue"
},
  "geometry": {"coordinates":[-83.79814,34.286224],"type":"Point"}
}