{
  "type": "Feature",
  "properties": {
    "iso:country":"US",
    "sg:address":"10118 Hidden Branches Way NE",
    "sg:city":"Covington",
    "sg:classifiers":[
        {
            "category":"Building & Trades",
            "subcategory":"Construction",
            "type":"Services"
        }
    ],
    "sg:phone":"+1 770 385 9088",
    "sg:postcode":"30014",
    "sg:province":"GA",
    "sg:tags":[
        "employed",
        "self",
        "drywall",
        "contractor"
    ],
    "wof:name":"Robert A Johnson",
    "wof:placetype":"venue"
},
  "geometry": {"coordinates":[-83.832435,33.610531],"type":"Point"}
}