{
  "type": "Feature",
  "properties": {
    "iso:country":"US",
    "sg:address":"708 Bowens Mill Rd SW",
    "sg:city":"Douglas",
    "sg:classifiers":[
        {
            "category":"Professional",
            "subcategory":"Business Services",
            "type":"Services"
        }
    ],
    "sg:phone":"+1 912 384 6333",
    "sg:postcode":"31533",
    "sg:province":"GA",
    "sg:tags":[
        "repairing",
        "sign"
    ],
    "wof:name":"Douglas Sign Co",
    "wof:placetype":"venue"
},
  "geometry": {"coordinates":[-82.87367500000001,31.499018],"type":"Point"}
}