{
  "type": "Feature",
  "properties": {
    "iso:country":"US",
    "sg:address":"416 Yorkhouse Rd",
    "sg:city":"Mountain City",
    "sg:classifiers":[
        {
            "category":"Travel",
            "subcategory":"Hotels & Motels",
            "type":"Entertainment"
        }
    ],
    "sg:phone":"+1 706 746 2068",
    "sg:postcode":"30568",
    "sg:province":"GA",
    "sg:tags":[
        "breakfast",
        "accommodation",
        "bed"
    ],
    "wof:name":"York House",
    "wof:placetype":"venue"
},
  "geometry": {"coordinates":[-83.37657,34.957241],"type":"Point"}
}