{
  "type": "Feature",
  "properties": {
    "iso:country":"US",
    "sg:address":"462 W Orange St",
    "sg:city":"Jesup",
    "sg:classifiers":[
        {
            "category":"Retail",
            "subcategory":"Repair Shop",
            "type":"Services"
        }
    ],
    "sg:phone":"+1 912 427 6762",
    "sg:postcode":"31545",
    "sg:province":"GA",
    "sg:tags":[
        "equipment",
        "telephone",
        "system"
    ],
    "wof:name":"Godwin Communications",
    "wof:placetype":"venue"
},
  "geometry": {"coordinates":[-81.889194,31.606435],"type":"Point"}
}