{
  "type": "Feature",
  "properties": {
    "addr:full":"8151 Hazelbrand Rd NE Covington GA 30014",
    "addr:housenumber":"8151",
    "addr:postcode":"30014",
    "addr:street":"Hazelbrand Rd Ne",
    "iso:country":"US",
    "sg:address":"8151 Hazelbrand Rd NE",
    "sg:city":"Covington",
    "sg:classifiers":[
        {
            "category":"Social Services",
            "subcategory":"Child Care",
            "type":"Services"
        }
    ],
    "sg:phone":"+1 770 787 6500",
    "sg:postcode":"30014",
    "sg:province":"GA",
    "wof:name":"Little Angels Child Care",
    "wof:placetype":"venue"
},
  "geometry": {"coordinates":[-83.835775,33.597952],"type":"Point"}
}