{
  "type": "Feature",
  "properties": {
    "iso:country":"US",
    "sg:address":"351 Newport St NW",
    "sg:city":"Atlanta",
    "sg:classifiers":[
        {
            "category":"Freight",
            "type":"Transportation"
        }
    ],
    "sg:phone":"+1 404 522 5855",
    "sg:postcode":"30314",
    "sg:province":"GA",
    "sg:tags":[
        "hauling"
    ],
    "wof:name":"Lb Trucking",
    "wof:placetype":"venue"
},
  "geometry": {"coordinates":[-84.413787,33.764075],"type":"Point"}
}