{
  "type": "Feature",
  "properties": {
    "iso:country":"US",
    "sg:address":"2217 Roswell Rd",
    "sg:city":"Marietta",
    "sg:classifiers":[
        {
            "category":"Arena",
            "subcategory":"Sports Club",
            "type":"Entertainment"
        }
    ],
    "sg:phone":"+1 770 973 4075",
    "sg:postcode":"30062",
    "sg:province":"GA",
    "sg:tags":[
        "martial art"
    ],
    "wof:name":"Tiger Tae Kwon DO Academy",
    "wof:placetype":"venue"
},
  "geometry": {"coordinates":[-84.48812599999999,33.970883],"type":"Point"}
}