{
  "type": "Feature",
  "properties": {
    "addr:full":"1338 Gordon Hwy Augusta GA 30901",
    "addr:housenumber":"1338",
    "addr:postcode":"30901",
    "addr:street":"Gordon Hwy",
    "iso:country":"US",
    "sg:address":"1338 Gordon Hwy",
    "sg:city":"Augusta",
    "sg:classifiers":[
        {
            "category":"Wholesale",
            "subcategory":"Machinery & Supplies",
            "type":"Manufacturing & Wholesale Goods"
        }
    ],
    "sg:phone":"+1 706 724 9567",
    "sg:postcode":"30901",
    "sg:province":"GA",
    "sg:tags":[
        "auto"
    ],
    "wof:name":"C & W Equipment & Supply Co",
    "wof:placetype":"venue"
},
  "geometry": {"coordinates":[-81.977498,33.445349],"type":"Point"}
}