{
  "type": "Feature",
  "properties": {
    "addr:full":"5050 Jimmy Carter Blvd Norcross GA 30093",
    "addr:housenumber":"5050",
    "addr:postcode":"30093",
    "addr:street":"Jimmy Carter Blvd",
    "iso:country":"US",
    "sg:address":"5050 Jimmy Carter Blvd",
    "sg:city":"Norcross",
    "sg:classifiers":[
        {
            "category":"Restaurant",
            "type":"Food & Drink"
        },
        {
            "category":"Food & Beverages",
            "subcategory":"Groceries & Convenience Stores",
            "type":"Retail Goods"
        }
    ],
    "sg:phone":"+1 770 416 6090",
    "sg:postcode":"30093",
    "sg:province":"GA",
    "sg:tags":[
        "american",
        "latin",
        "mexican"
    ],
    "wof:name":"Carmelitas Mexican Store",
    "wof:placetype":"venue"
},
  "geometry": {"coordinates":[-84.19940200000001,33.8974],"type":"Point"}
}