{
  "type": "Feature",
  "properties": {
    "iso:country":"US",
    "sg:address":"1350 S Zack Hinton Pkwy",
    "sg:city":"McDonough",
    "sg:classifiers":[
        {
            "category":"Personal",
            "subcategory":"Barber",
            "type":"Services"
        }
    ],
    "sg:phone":"+1 770 914 6300",
    "sg:postcode":"30253",
    "sg:province":"GA",
    "wof:name":"Wayne's Barber Shop",
    "wof:placetype":"venue"
},
  "geometry": {"coordinates":[-84.137996,33.432891],"type":"Point"}
}