{
  "type": "Feature",
  "properties": {
    "addr:full":"1501 Old Hwy 19 S Thomaston GA 30286",
    "addr:housenumber":"1501",
    "addr:postcode":"30286",
    "addr:street":"Old Hwy 19 S",
    "iso:country":"US",
    "sg:address":"1501 Old Hwy 19 S",
    "sg:city":"Thomaston",
    "sg:classifiers":[
        {
            "category":"Food & Beverages",
            "subcategory":"Groceries & Convenience Stores",
            "type":"Retail Goods"
        }
    ],
    "sg:phone":"+1 706 648 4267",
    "sg:postcode":"30286",
    "sg:province":"GA",
    "wof:name":"Flash Foods Inc",
    "wof:placetype":"venue"
},
  "geometry": {"coordinates":[-84.319942,32.857339],"type":"Point"}
}