{
  "type": "Feature",
  "properties": {
    "iso:country":"US",
    "sg:address":"500 Pinnacle Ct",
    "sg:city":"Norcross",
    "sg:classifiers":[
        {
            "category":"Education",
            "subcategory":"College",
            "type":"Public Place"
        }
    ],
    "sg:phone":"+1 770 368 8877",
    "sg:postcode":"30071",
    "sg:province":"GA",
    "sg:tags":[
        "academic",
        "school"
    ],
    "sg:website":"www.barrington.edu",
    "wof:name":"Barrington University",
    "wof:placetype":"venue"
},
  "geometry": {"coordinates":[-84.187675,33.930578],"type":"Point"}
}