{
  "type": "Feature",
  "properties": {
    "addr:full":"5390 McGinnis Ferry Rd Alpharetta GA 30005",
    "addr:postcode":"5390;30005",
    "addr:street":"Mcginnis Ferry Rd",
    "iso:country":"US",
    "sg:address":"5390 McGinnis Ferry Rd",
    "sg:city":"Alpharetta",
    "sg:classifiers":[
        {
            "category":"Organizations",
            "subcategory":"Religious Organization",
            "type":"Services"
        }
    ],
    "sg:phone":"+1 770 740 1279",
    "sg:postcode":"30005",
    "sg:province":"GA",
    "wof:name":"Lord of Life Lutheran Church Elca",
    "wof:placetype":"venue"
},
  "geometry": {"coordinates":[-84.200699,34.09],"type":"Point"}
}