{
  "type": "Feature",
  "properties": {
    "addr:full":"4425 Memorial Dr Decatur GA 30032",
    "addr:housenumber":"4425",
    "addr:postcode":"30032",
    "addr:street":"Memorial Dr",
    "iso:country":"US",
    "sg:address":"4425 Memorial Dr",
    "sg:city":"Decatur",
    "sg:classifiers":[
        {
            "category":"Health Services",
            "subcategory":"Hospital",
            "type":"Services"
        }
    ],
    "sg:phone":"+1 404 298 8330",
    "sg:postcode":"30032",
    "sg:province":"GA",
    "sg:tags":[
        "mental"
    ],
    "wof:name":"MHM Correctional Svc Inc",
    "wof:placetype":"venue"
},
  "geometry": {"coordinates":[-84.24464399999999,33.776422],"type":"Point"}
}