{
  "type": "Feature",
  "properties": {
    "addr:full":"4911 Old Briar Trl Douglasville GA 30135",
    "addr:housenumber":"4911",
    "addr:postcode":"30135",
    "addr:street":"Old Briar Trl",
    "iso:country":"US",
    "sg:address":"4911 Old Briar Trl",
    "sg:city":"Douglasville",
    "sg:classifiers":[
        {
            "category":"Real Estate",
            "subcategory":"Real Estate Agent",
            "type":"Services"
        }
    ],
    "sg:phone":"+1 770 949 9068",
    "sg:postcode":"30135",
    "sg:province":"GA",
    "wof:name":"Edwards Const Co",
    "wof:placetype":"venue"
},
  "geometry": {"coordinates":[-84.734883,33.69963],"type":"Point"}
}