{
  "type": "Feature",
  "properties": {
    "iso:country":"US",
    "sg:address":"79 State Rte 57",
    "sg:city":"Swainsboro",
    "sg:classifiers":[
        {
            "category":"Farming",
            "subcategory":"Livestock Farm",
            "type":"Manufacturing & Wholesale Goods"
        }
    ],
    "sg:phone":"+1 912 562 4226",
    "sg:postcode":"30401",
    "sg:province":"GA",
    "sg:tags":[
        "beef",
        "feedlot",
        "cattle"
    ],
    "wof:name":"Hooks  Evans Cattle Co Inc",
    "wof:placetype":"venue"
},
  "geometry": {"coordinates":[-82.34606599999999,32.592682],"type":"Point"}
}