{
  "type": "Feature",
  "properties": {
    "iso:country":"US",
    "sg:address":"6633 Pleasant Valley Dr",
    "sg:city":"Morrow",
    "sg:classifiers":[
        {
            "category":"Banks & Credit Unions",
            "subcategory":"Financial Services",
            "type":"Services"
        }
    ],
    "sg:phone":"+1 770 961 2881",
    "sg:postcode":"30260",
    "sg:province":"GA",
    "sg:tags":[
        "company",
        "holding"
    ],
    "wof:name":"Jebco Holdings Inc",
    "wof:placetype":"venue"
},
  "geometry": {"coordinates":[-84.327495,33.574198],"type":"Point"}
}