{
  "type": "Feature",
  "properties": {
    "iso:country":"US",
    "sg:address":"2586 Graywall St",
    "sg:city":"Atlanta",
    "sg:classifiers":[
        {
            "category":"Professional",
            "subcategory":"Accounting & Tax Preparation",
            "type":"Services"
        }
    ],
    "sg:phone":"+1 404 209 7609",
    "sg:postcode":"30344",
    "sg:province":"GA",
    "sg:tags":[
        "return"
    ],
    "wof:name":"Bourget Financial Service",
    "wof:placetype":"venue"
},
  "geometry": {"coordinates":[-84.464009,33.684626],"type":"Point"}
}