{
  "type": "Feature",
  "properties": {
    "addr:full":"7875 Roswell Rd Ste E Atlanta GA 30350",
    "addr:housenumber":"7875",
    "addr:postcode":"30350",
    "addr:street":"Roswell Rd Ste E",
    "iso:country":"US",
    "sg:address":"7875 Roswell Rd Ste E",
    "sg:city":"Atlanta",
    "sg:classifiers":[
        {
            "category":"Personal",
            "subcategory":"Nail Salon",
            "type":"Services"
        }
    ],
    "sg:phone":"+1 770 395 9112",
    "sg:postcode":"30350",
    "sg:province":"GA",
    "wof:name":"Elegant Nails",
    "wof:placetype":"venue"
},
  "geometry": {"coordinates":[-84.358346,33.971777],"type":"Point"}
}