{
  "type": "Feature",
  "properties": {
    "iso:country":"US",
    "sg:address":"1007 Mission Rd SW",
    "sg:city":"Cartersville",
    "sg:classifiers":[
        {
            "category":"Building & Trades",
            "subcategory":"Construction",
            "type":"Services"
        }
    ],
    "sg:phone":"+1 770 387 0099",
    "sg:postcode":"30120",
    "sg:province":"GA",
    "sg:tags":[
        "contractor"
    ],
    "wof:name":"Robinson & Robinson Properties",
    "wof:placetype":"venue"
},
  "geometry": {"coordinates":[-84.86868699999999,34.161108],"type":"Point"}
}