{
  "type": "Feature",
  "properties": {
    "iso:country":"US",
    "sg:address":"1033 Riverbend Ct",
    "sg:city":"Riverdale",
    "sg:classifiers":[
        {
            "category":"Building & Trades",
            "subcategory":"Construction",
            "type":"Services"
        }
    ],
    "sg:phone":"+1 770 997 7295",
    "sg:postcode":"30296",
    "sg:province":"GA",
    "sg:tags":[
        "house"
    ],
    "wof:name":"Platinum Construction & Contg",
    "wof:placetype":"venue"
},
  "geometry": {"coordinates":[-84.42331299999999,33.577105],"type":"Point"}
}