{
  "type": "Feature",
  "properties": {
    "addr:full":"545 Cool Springs Walk Woodstock GA 30188",
    "addr:housenumber":"545",
    "addr:postcode":"30188",
    "addr:street":"Cool Springs Walk",
    "iso:country":"US",
    "sg:address":"545 Cool Springs Walk",
    "sg:city":"Woodstock",
    "sg:classifiers":[
        {
            "category":"Home & Garden",
            "subcategory":"Garden Supply",
            "type":"Retail Goods"
        }
    ],
    "sg:phone":"+1 770 924 9006",
    "sg:postcode":"30188",
    "sg:province":"GA",
    "wof:name":"Horticultural Horizons",
    "wof:placetype":"venue"
},
  "geometry": {"coordinates":[-84.490837,34.142915],"type":"Point"}
}