{
  "type": "Feature",
  "properties": {
    "addr:full":"2462 W Point Ave Atlanta GA 30337",
    "addr:housenumber":"2462",
    "addr:postcode":"30337",
    "addr:street":"W Point Ave",
    "iso:country":"US",
    "sg:address":"2462 W Point Ave",
    "sg:city":"Atlanta",
    "sg:classifiers":[
        {
            "category":"Manufacturing",
            "subcategory":"Glass & Minerals",
            "type":"Manufacturing & Wholesale Goods"
        }
    ],
    "sg:phone":"+1 404 762 9554",
    "sg:postcode":"30337",
    "sg:province":"GA",
    "sg:tags":[
        "cast",
        "stone"
    ],
    "sg:website":"http://www.boralbricks.com",
    "wof:name":"Brick Studio",
    "wof:placetype":"venue"
},
  "geometry": {"coordinates":[-84.46556699999999,33.633161],"type":"Point"}
}