{
  "type": "Feature",
  "properties": {
    "addr:full":"1128 17th St Columbus GA 31901",
    "addr:housenumber":"1128",
    "addr:postcode":"31901",
    "addr:street":"17Th St",
    "iso:country":"US",
    "sg:address":"1128 17th St",
    "sg:city":"Columbus",
    "sg:classifiers":[
        {
            "category":"Health Services",
            "subcategory":"Health Practitioner",
            "type":"Services"
        }
    ],
    "sg:phone":"+1 706 324 6762",
    "sg:postcode":"31901",
    "sg:province":"GA",
    "wof:name":"Aquarin Enterprises",
    "wof:placetype":"venue"
},
  "geometry": {"coordinates":[-84.976195,32.478413],"type":"Point"}
}