{
  "type": "Feature",
  "properties": {
    "iso:country":"US",
    "sg:address":"1509 E Shotwell St",
    "sg:city":"Bainbridge",
    "sg:classifiers":[
        {
            "category":"Insurance",
            "subcategory":"Insurance Agent",
            "type":"Services"
        },
        {
            "category":"Insurance",
            "subcategory":"Hazard Insurance",
            "type":"Services"
        }
    ],
    "sg:phone":"+1 229 515 4007",
    "sg:postcode":"39819",
    "sg:province":"GA",
    "sg:tags":[
        "auto",
        "motorcycle"
    ],
    "sg:website":"http://www.firstacceptancecorp.com/Locations.aspx",
    "wof:name":"Acceptance Auto Insurance- Bainbridge",
    "wof:placetype":"venue"
},
  "geometry": {"coordinates":[-84.537407,30.902835],"type":"Point"}
}