{
  "type": "Feature",
  "properties": {
    "addr:full":"1354 Salem Dr Alpharetta GA 30004",
    "addr:housenumber":"1354",
    "addr:postcode":"30004",
    "addr:street":"Salem Dr",
    "iso:country":"US",
    "sg:address":"1354 Salem Dr",
    "sg:city":"Alpharetta",
    "sg:classifiers":[
        {
            "category":"Professional",
            "type":"Services"
        }
    ],
    "sg:phone":"+1 770 475 2320",
    "sg:postcode":"30004",
    "sg:province":"GA",
    "sg:tags":[
        "establishment"
    ],
    "wof:name":"Lana Robinson Born",
    "wof:placetype":"venue"
},
  "geometry": {"coordinates":[-84.31386500000001,34.089507],"type":"Point"}
}