{
  "type": "Feature",
  "properties": {
    "iso:country":"US",
    "sg:address":"3065 Shallowford Rd",
    "sg:city":"Marietta",
    "sg:classifiers":[
        {
            "category":"Professional",
            "type":"Services"
        }
    ],
    "sg:phone":"+1 770 509 9485",
    "sg:postcode":"30062",
    "sg:province":"GA",
    "wof:name":"Southrn Automated Services",
    "wof:placetype":"venue"
},
  "geometry": {"coordinates":[-84.46232999999999,34.0363],"type":"Point"}
}