{
  "type": "Feature",
  "properties": {
    "iso:country":"US",
    "sg:address":"1575 Mount Vernon Rd",
    "sg:city":"Atlanta",
    "sg:phone":"+1 770 352 0281",
    "sg:postcode":"30338",
    "sg:province":"GA",
    "sg:website":"http://www.blockbuster.com",
    "wof:name":"Blockbuster Video",
    "wof:placetype":"venue"
},
  "geometry": {"coordinates":[-84.335277,33.945689],"type":"Point"}
}