{
  "type": "Feature",
  "properties": {
    "addr:full":"1 Cnn Ctr NW Atlanta GA 30303",
    "addr:housenumber":"1",
    "addr:postcode":"30303",
    "addr:street":"Cnn Ctr Nw",
    "iso:country":"US",
    "sg:address":"1 Cnn Ctr NW",
    "sg:city":"Atlanta",
    "sg:classifiers":[
        {
            "category":"Restaurant",
            "type":"Food & Drink"
        }
    ],
    "sg:phone":"+1 404 688 8703",
    "sg:postcode":"30303",
    "sg:province":"GA",
    "sg:tags":[
        "new",
        "american"
    ],
    "wof:name":"Salad Sensations At Cnn",
    "wof:placetype":"venue"
},
  "geometry": {"coordinates":[-84.394645,33.757644],"type":"Point"}
}