{
  "type": "Feature",
  "properties": {
    "addr:full":"1209 E 35th St Savannah GA 31404",
    "addr:housenumber":"1209",
    "addr:postcode":"31404",
    "addr:street":"E 35Th St",
    "iso:country":"US",
    "sg:address":"1209 E 35th St",
    "sg:city":"Savannah",
    "sg:classifiers":[
        {
            "category":"Building & Trades",
            "subcategory":"Construction",
            "type":"Services"
        }
    ],
    "sg:phone":"+1 912 236 8453",
    "sg:postcode":"31404",
    "sg:province":"GA",
    "sg:tags":[
        "tile",
        "dealer"
    ],
    "wof:name":"Shekina Tile Works Et Al",
    "wof:placetype":"venue"
},
  "geometry": {"coordinates":[-81.079492,32.053662],"type":"Point"}
}