{
  "type": "Feature",
  "properties": {
    "addr:full":"3810 Ogeechee Rd Savannah GA 31405",
    "addr:housenumber":"3810",
    "addr:postcode":"31405",
    "addr:street":"Ogeechee Rd",
    "iso:country":"US",
    "sg:address":"3810 Ogeechee Rd",
    "sg:city":"Savannah",
    "sg:classifiers":[
        {
            "category":"Retail",
            "subcategory":"Auto Repair",
            "type":"Services"
        }
    ],
    "sg:phone":"+1 912 236 8520",
    "sg:postcode":"31405",
    "sg:province":"GA",
    "sg:tags":[
        "transmission"
    ],
    "wof:name":"Transmission Specialist",
    "wof:placetype":"venue"
},
  "geometry": {"coordinates":[-81.151546,32.0514],"type":"Point"}
}