{
  "type": "Feature",
  "properties": {
    "addr:full":"3239 Plum Ave Patterson GA 31557",
    "addr:housenumber":"3239",
    "addr:postcode":"ga 31557",
    "addr:street":"Plum Ave",
    "iso:country":"US",
    "sg:address":"3239 Plum Ave",
    "sg:city":"Patterson",
    "sg:phone":"+1 912 647 5359",
    "sg:postcode":"31557",
    "sg:province":"GA",
    "sg:tags":[
        "farm",
        "tobacco"
    ],
    "wof:name":"Bennett, Jereal",
    "wof:placetype":"venue"
},
  "geometry": {"coordinates":[-82.14529400000001,31.391809],"type":"Point"}
}