{
  "type": "Feature",
  "properties": {
    "iso:country":"US",
    "sg:address":"2302 Wilemere Dr",
    "sg:city":"Savannah",
    "sg:classifiers":[
        {
            "category":"Professional",
            "subcategory":"Business Services",
            "type":"Services"
        }
    ],
    "sg:phone":"+1 912 356 9265",
    "sg:postcode":"31404",
    "sg:province":"GA",
    "wof:name":"IB Ladefoged Yacht Design Inc",
    "wof:placetype":"venue"
},
  "geometry": {"coordinates":[-81.07446299999999,32.029718],"type":"Point"}
}