{
  "type": "Feature",
  "properties": {
    "addr:full":"200 N Grade Dr Dalton GA 30721",
    "addr:housenumber":"200",
    "addr:postcode":"30721",
    "addr:street":"N Grade Dr",
    "iso:country":"US",
    "sg:address":"200 N Grade Dr",
    "sg:city":"Dalton",
    "sg:classifiers":[
        {
            "category":"Building & Trades",
            "subcategory":"Construction",
            "type":"Services"
        }
    ],
    "sg:phone":"+1 706 278 5262",
    "sg:postcode":"30721",
    "sg:province":"GA",
    "sg:tags":[
        "contractor"
    ],
    "wof:name":"Lowes Cstm Tile Installation",
    "wof:placetype":"venue"
},
  "geometry": {"coordinates":[-84.945713,34.773467],"type":"Point"}
}