{
  "type": "Feature",
  "properties": {
    "iso:country":"US",
    "sg:address":"3848 Saint Marys Rd",
    "sg:city":"Columbus",
    "sg:classifiers":[
        {
            "category":"Restaurant",
            "type":"Food & Drink"
        }
    ],
    "sg:menulink":"http://www.allmenus.com/ga/columbus/154409-hardees/menu/",
    "sg:phone":"+1 706 687 1809",
    "sg:postcode":"31906",
    "sg:province":"GA",
    "sg:tags":[
        "burger",
        "american"
    ],
    "wof:name":"Hardee's",
    "wof:placetype":"venue"
},
  "geometry": {"coordinates":[-84.930988,32.446459],"type":"Point"}
}