{
  "type": "Feature",
  "properties": {
    "addr:full":"2488 Lakeland Rd SE Dalton GA 30721",
    "addr:housenumber":"2488",
    "addr:postcode":"30721",
    "addr:street":"Lakeland Rd Se Dalton",
    "iso:country":"US",
    "sg:address":"2488 Lakeland Rd SE",
    "sg:city":"Dalton",
    "sg:classifiers":[
        {
            "category":"Wholesale",
            "subcategory":"Machinery & Supplies",
            "type":"Manufacturing & Wholesale Goods"
        }
    ],
    "sg:phone":"+1 706 277 9010",
    "sg:postcode":"30721",
    "sg:province":"GA",
    "sg:tags":[
        "textile",
        "mill"
    ],
    "wof:name":"General Fibers & Fabrics Inc",
    "wof:placetype":"venue"
},
  "geometry": {"coordinates":[-84.96213,34.716993],"type":"Point"}
}