{
  "type": "Feature",
  "properties": {
    "addr:full":"810 Marietta St. Atlanta GA 30318",
    "addr:housenumber":"810",
    "addr:postcode":"30318",
    "addr:street":"Marietta St.",
    "iso:country":"US",
    "sg:address":"810 Marietta St.",
    "sg:city":"Atlanta",
    "sg:classifiers":[
        {
            "category":"Fast Food",
            "type":"Food & Drink"
        }
    ],
    "sg:phone":"+1 404 876 2005",
    "sg:postcode":"30318",
    "sg:province":"GA",
    "sg:tags":[
        "burger"
    ],
    "sg:website":"www.burgerjoesga.com",
    "wof:name":"Burger Joe's",
    "wof:placetype":"venue"
},
  "geometry": {"coordinates":[-84.40619,33.774463],"type":"Point"}
}