{
  "type": "Feature",
  "properties": {
    "iso:country":"US",
    "sg:address":"3343 E Fairview Rd SW",
    "sg:city":"Stockbridge",
    "sg:classifiers":[
        {
            "category":"Education",
            "subcategory":"School",
            "type":"Public Place"
        }
    ],
    "sg:phone":"+1 770 483 0657",
    "sg:postcode":"30281",
    "sg:province":"GA",
    "wof:name":"Rockdale County of",
    "wof:placetype":"venue"
},
  "geometry": {"coordinates":[-84.115799,33.574501],"type":"Point"}
}