{
  "type": "Feature",
  "properties": {
    "addr:full":"11905 Highway 11 Trenton GA 30752",
    "addr:housenumber":"11905",
    "addr:postcode":"30752",
    "addr:street":"Highway 11",
    "iso:country":"US",
    "sg:address":"11905 Highway 11",
    "sg:city":"Trenton",
    "sg:classifiers":[
        {
            "category":"Place Of Worship",
            "subcategory":"Church",
            "type":"Public Place"
        },
        {
            "category":"Place Of Worship",
            "type":"Public Place"
        }
    ],
    "sg:phone":"+1 706 657 4639",
    "sg:postcode":"30752",
    "sg:province":"GA",
    "sg:tags":[
        "churches-baptist-general",
        "churches-baptist"
    ],
    "wof:name":"First Baptist Church",
    "wof:placetype":"venue"
},
  "geometry": {"coordinates":[-85.51606,34.863049],"type":"Point"}
}