{
  "type": "Feature",
  "properties": {
    "iso:country":"US",
    "sg:address":"1880 W Oak Pkwy",
    "sg:city":"Marietta",
    "sg:classifiers":[
        {
            "category":"Education",
            "subcategory":"School",
            "type":"Public Place"
        }
    ],
    "sg:phone":"+1 770 977 9797",
    "sg:postcode":"30062",
    "sg:province":"GA",
    "wof:name":"Sca Camps",
    "wof:placetype":"venue"
},
  "geometry": {"coordinates":[-84.523315,33.992935],"type":"Point"}
}