{
  "type": "Feature",
  "properties": {
    "iso:country":"US",
    "sg:address":"240 Old Epps Bridge Rd",
    "sg:city":"Athens",
    "sg:classifiers":[
        {
            "category":"Home & Garden",
            "subcategory":"Carpets & Floor Coverings",
            "type":"Retail Goods"
        }
    ],
    "sg:phone":"+1 706 549 6313",
    "sg:postcode":"30606",
    "sg:province":"GA",
    "sg:tags":[
        "dealer",
        "rug"
    ],
    "wof:name":"LEWIS Co",
    "wof:placetype":"venue"
},
  "geometry": {"coordinates":[-83.409903,33.951178],"type":"Point"}
}