{
  "type": "Feature",
  "properties": {
    "addr:full":"296 Sunset Ave NW Atlanta GA 30314",
    "addr:housenumber":"296",
    "addr:postcode":"30314",
    "addr:street":"Sunset Ave Nw",
    "iso:country":"US",
    "sg:address":"296 Sunset Ave NW",
    "sg:city":"Atlanta",
    "sg:classifiers":[
        {
            "category":"Education",
            "subcategory":"Special Training",
            "type":"Public Place"
        }
    ],
    "sg:phone":"+1 404 577 8711",
    "sg:postcode":"30314",
    "sg:province":"GA",
    "wof:name":"Educational Enterprises",
    "wof:placetype":"venue"
},
  "geometry": {"coordinates":[-84.410059,33.762814],"type":"Point"}
}