{
  "type": "Feature",
  "properties": {
    "addr:full":"110 Plantation Dr Thomasville GA 31792",
    "addr:housenumber":"110",
    "addr:postcode":"31792",
    "addr:street":"Plantation Dr",
    "iso:country":"US",
    "sg:address":"110 Plantation Dr",
    "sg:city":"Thomasville",
    "sg:classifiers":[
        {
            "category":"Autos & Motor Vehicles",
            "subcategory":"Auto Supplies",
            "type":"Retail Goods"
        },
        {
            "category":"Retail",
            "subcategory":"Auto Repair",
            "type":"Services"
        }
    ],
    "sg:phone":"+1 229 225 1253",
    "sg:postcode":"31792",
    "sg:province":"GA",
    "sg:tags":[
        "recap",
        "retread",
        "tire"
    ],
    "sg:website":"http://www.snidertire.net",
    "wof:name":"Snider Tire Inc Commercial Division",
    "wof:placetype":"venue"
},
  "geometry": {"coordinates":[-83.962947,30.823353],"type":"Point"}
}