{
  "type": "Feature",
  "properties": {
    "addr:full":"750 Townpark Ln NW Kennesaw GA 30144",
    "addr:housenumber":"750",
    "addr:postcode":"30144",
    "addr:street":"Townpark Ln Nw",
    "iso:country":"US",
    "sg:address":"750 Townpark Ln NW",
    "sg:city":"Kennesaw",
    "sg:classifiers":[
        {
            "category":"Health Services",
            "subcategory":"Hospital",
            "type":"Services"
        }
    ],
    "sg:phone":"+1 770 514 5566",
    "sg:postcode":"30144",
    "sg:province":"GA",
    "sg:tags":[
        "medical",
        "surgical",
        "hospitalization",
        "plan"
    ],
    "wof:name":"Kaiser Foundation Health Plan",
    "wof:placetype":"venue"
},
  "geometry": {"coordinates":[-84.57246499999999,34.036327],"type":"Point"}
}