{
  "type": "Feature",
  "properties": {
    "addr:full":"1801 Wynnton Rd Columbus GA 31906",
    "addr:housenumber":"1801",
    "addr:postcode":"31906",
    "addr:street":"Wynnton Rd",
    "iso:country":"US",
    "sg:address":"1801 Wynnton Rd",
    "sg:city":"Columbus",
    "sg:classifiers":[
        {
            "category":"Wholesale",
            "subcategory":"Medical Equipment & Supplies",
            "type":"Manufacturing & Wholesale Goods"
        }
    ],
    "sg:phone":"+1 706 322 0003",
    "sg:postcode":"31906",
    "sg:province":"GA",
    "sg:tags":[
        "wheel",
        "chair",
        "lift",
        "ramp"
    ],
    "wof:name":"Enh & Assoc",
    "wof:placetype":"venue"
},
  "geometry": {"coordinates":[-84.965825,32.468202],"type":"Point"}
}