{
  "type": "Feature",
  "properties": {
    "addr:full":"1908 Lower Roswell Rd Marietta GA 30068",
    "addr:housenumber":"1908",
    "addr:postcode":"30068",
    "addr:street":"Lower Roswell Rd",
    "iso:country":"US",
    "sg:address":"1908 Lower Roswell Rd",
    "sg:city":"Marietta",
    "sg:classifiers":[
        {
            "category":"Retail",
            "subcategory":"Auto Repair",
            "type":"Services"
        }
    ],
    "sg:phone":"+1 770 579 2667",
    "sg:postcode":"30068",
    "sg:province":"GA",
    "wof:name":"Honda Repair by Acupro Automotive Service",
    "wof:placetype":"venue"
},
  "geometry": {"coordinates":[-84.49690200000001,33.951302],"type":"Point"}
}