{
  "type": "Feature",
  "properties": {
    "iso:country":"US",
    "sg:address":"1 S Main St",
    "sg:city":"Alpharetta",
    "sg:classifiers":[
        {
            "category":"Shopping",
            "subcategory":"Clothing, Apparel, & Fashions",
            "type":"Retail Goods"
        }
    ],
    "sg:phone":"+1 770 751 9857",
    "sg:postcode":"30009",
    "sg:province":"GA",
    "sg:tags":[
        "apparel",
        "women's"
    ],
    "wof:name":"Galerie",
    "wof:placetype":"venue"
},
  "geometry": {"coordinates":[-84.29454800000001,34.075588],"type":"Point"}
}