{
  "type": "Feature",
  "properties": {
    "addr:full":"4142 Brockett Creek Dr Tucker GA 30084",
    "addr:housenumber":"4142",
    "addr:postcode":"30084",
    "addr:street":"Brockett Creek Dr",
    "iso:country":"US",
    "sg:address":"4142 Brockett Creek Dr",
    "sg:city":"Tucker",
    "sg:classifiers":[
        {
            "category":"Professional",
            "type":"Services"
        }
    ],
    "sg:phone":"+1 770 414 1604",
    "sg:postcode":"30084",
    "sg:province":"GA",
    "wof:name":"Wade Fields Inc",
    "wof:placetype":"venue"
},
  "geometry": {"coordinates":[-84.218632,33.83954],"type":"Point"}
}