{
  "type": "Feature",
  "properties": {
    "iso:country":"US",
    "sg:address":"795 Woodhull Rd",
    "sg:city":"Bainbridge",
    "sg:classifiers":[
        {
            "category":"Professional",
            "type":"Services"
        }
    ],
    "sg:phone":"+1 229 246 3626",
    "sg:postcode":"39819",
    "sg:province":"FL",
    "wof:name":"Daniel L Provence",
    "wof:placetype":"venue"
},
  "geometry": {"coordinates":[-84.492753,30.849807],"type":"Point"}
}