{
  "type": "Feature",
  "properties": {
    "iso:country":"US",
    "sg:address":"401 Airport Rd",
    "sg:city":"Griffin",
    "sg:classifiers":[
        {
            "category":"Food & Beverages",
            "subcategory":"Groceries & Convenience Stores",
            "type":"Retail Goods"
        }
    ],
    "sg:phone":"+1 770 228 3950",
    "sg:postcode":"30224",
    "sg:province":"GA",
    "wof:name":"K & P's One Stop",
    "wof:placetype":"venue"
},
  "geometry": {"coordinates":[-84.278279,33.222538],"type":"Point"}
}