{
  "type": "Feature",
  "properties": {
    "addr:full":"205 Swanton Way Decatur GA 30030",
    "addr:housenumber":"205",
    "addr:postcode":"30030",
    "addr:street":"Swanton Way",
    "iso:country":"US",
    "sg:address":"205 Swanton Way",
    "sg:city":"Decatur",
    "sg:classifiers":[
        {
            "category":"Real Estate",
            "subcategory":"Real Estate Agent",
            "type":"Services"
        }
    ],
    "sg:phone":"+1 404 377 3003",
    "sg:postcode":"30030",
    "sg:province":"GA",
    "wof:name":"First Realty Advisors",
    "wof:placetype":"venue"
},
  "geometry": {"coordinates":[-84.298892,33.77462],"type":"Point"}
}