{
  "type": "Feature",
  "properties": {
    "addr:full":"2501 Burton Dam Rd Clarkesville GA 30523",
    "addr:housenumber":"2501",
    "addr:postcode":"30523",
    "addr:street":"Burton Dam Rd",
    "iso:country":"US",
    "sg:address":"2501 Burton Dam Rd",
    "sg:city":"Clarkesville",
    "sg:classifiers":[
        {
            "category":"Home & Garden",
            "subcategory":"Home Furnishings",
            "type":"Retail Goods"
        }
    ],
    "sg:phone":"+1 706 947 0601",
    "sg:postcode":"30523",
    "sg:province":"GA",
    "wof:name":"North G A Shutter & Blind Comp",
    "wof:placetype":"venue"
},
  "geometry": {"coordinates":[-83.55244399999999,34.787695],"type":"Point"}
}