{
  "type": "Feature",
  "properties": {
    "iso:country":"US",
    "sg:address":"1085 Bellaire Ct",
    "sg:city":"Lawrenceville",
    "sg:classifiers":[
        {
            "category":"Professional",
            "subcategory":"Art Services",
            "type":"Services"
        }
    ],
    "sg:phone":"+1 770 995 7374",
    "sg:postcode":"30043",
    "sg:province":"GA",
    "sg:tags":[
        "photography",
        "commercial"
    ],
    "wof:name":"Michael W Thomas Photography",
    "wof:placetype":"venue"
},
  "geometry": {"coordinates":[-84.039214,33.976388],"type":"Point"}
}