{
  "type": "Feature",
  "properties": {
    "iso:country":"US",
    "sg:address":"3121 Parkwood Dr",
    "sg:city":"Valdosta",
    "sg:classifiers":[
        {
            "category":"Professional",
            "type":"Services"
        }
    ],
    "sg:phone":"+1 229 244 6897",
    "sg:postcode":"31605",
    "sg:province":"GA",
    "wof:name":"Bernard J Boyles",
    "wof:placetype":"venue"
},
  "geometry": {"coordinates":[-83.249115,30.890456],"type":"Point"}
}