{
  "type": "Feature",
  "properties": {
    "iso:country":"US",
    "sg:address":"180 Orchard Ln",
    "sg:city":"Talking Rock",
    "sg:classifiers":[
        {
            "category":"Retail",
            "subcategory":"Repair Shop",
            "type":"Services"
        }
    ],
    "sg:phone":"+1 706 276 2459",
    "sg:postcode":"30175",
    "sg:province":"GA",
    "sg:tags":[
        "welding"
    ],
    "wof:name":"Knowles Mobile Welding",
    "wof:placetype":"venue"
},
  "geometry": {"coordinates":[-84.450649,34.596803],"type":"Point"}
}