{
  "type": "Feature",
  "properties": {
    "iso:country":"US",
    "sg:address":"800 N Broad St",
    "sg:city":"Cairo",
    "sg:classifiers":[
        {
            "category":"Real Estate",
            "subcategory":"Real Estate Agent",
            "type":"Services"
        }
    ],
    "sg:phone":"+1 229 377 4002",
    "sg:postcode":"39828",
    "sg:province":"GA",
    "sg:tags":[
        "appraiser"
    ],
    "wof:name":"Brown Appraisal Svc",
    "wof:placetype":"venue"
},
  "geometry": {"coordinates":[-84.20816499999999,30.887203],"type":"Point"}
}