{
  "type": "Feature",
  "properties": {
    "iso:country":"US",
    "sg:address":"5623 Blackjack Rd",
    "sg:city":"Flowery Branch",
    "sg:classifiers":[
        {
            "category":"Shopping",
            "subcategory":"Gifts & Souvenirs",
            "type":"Retail Goods"
        }
    ],
    "sg:phone":"+1 770 271 7842",
    "sg:postcode":"30542",
    "sg:province":"GA",
    "wof:name":"Debbies Gift Baskets",
    "wof:placetype":"venue"
},
  "geometry": {"coordinates":[-83.92764,34.143767],"type":"Point"}
}