{
  "type": "Feature",
  "properties": {
    "addr:full":"690 Mount Vernon Hwy Atlanta GA 30328",
    "addr:housenumber":"690",
    "addr:postcode":"30328",
    "addr:street":"Mount Vernon Hwy",
    "iso:country":"US",
    "sg:address":"690 Mount Vernon Hwy",
    "sg:city":"Atlanta",
    "sg:classifiers":[
        {
            "category":"Social Services",
            "subcategory":"Adult Care",
            "type":"Services"
        }
    ],
    "sg:phone":"+1 404 843 1964",
    "sg:postcode":"30328",
    "sg:province":"GA",
    "sg:tags":[
        "home",
        "residential"
    ],
    "wof:name":"Eden Brook Assisted Living",
    "wof:placetype":"venue"
},
  "geometry": {"coordinates":[-84.363839,33.928114],"type":"Point"}
}