{
  "type": "Feature",
  "properties": {
    "addr:full":"7001 Roswell Rd Atlanta GA 30328",
    "addr:housenumber":"7001",
    "addr:postcode":"30328",
    "addr:street":"Roswell Rd",
    "iso:country":"US",
    "sg:address":"7001 Roswell Rd",
    "sg:city":"Atlanta",
    "sg:classifiers":[
        {
            "category":"Professional",
            "subcategory":"Detective & Security Services",
            "type":"Services"
        }
    ],
    "sg:phone":"+1 770 730 9727",
    "sg:postcode":"30328",
    "sg:province":"GA",
    "sg:tags":[
        "contracting"
    ],
    "wof:name":"R George Security Consultants",
    "wof:placetype":"venue"
},
  "geometry": {"coordinates":[-84.37226800000001,33.943394],"type":"Point"}
}