{
  "type": "Feature",
  "properties": {
    "addr:full":"2731 Vanna Rd Royston GA 30662",
    "addr:housenumber":"2731",
    "addr:postcode":"30662",
    "addr:street":"Vanna Rd",
    "iso:country":"US",
    "sg:address":"2731 Vanna Rd",
    "sg:city":"Royston",
    "sg:classifiers":[
        {
            "category":"Professional",
            "type":"Services"
        }
    ],
    "sg:phone":"+1 706 245 6353",
    "sg:postcode":"30662",
    "sg:province":"GA",
    "wof:name":"Bryant Poultry Inc",
    "wof:placetype":"venue"
},
  "geometry": {"coordinates":[-83.067807,34.237814],"type":"Point"}
}