{
  "type": "Feature",
  "properties": {
    "addr:full":"1926 12th Ave Columbus GA 31901",
    "addr:housenumber":"1926",
    "addr:postcode":"31901",
    "addr:street":"12Th Ave",
    "iso:country":"US",
    "sg:address":"1926 12th Ave",
    "sg:city":"Columbus",
    "sg:classifiers":[
        {
            "category":"Taxi",
            "type":"Transportation"
        }
    ],
    "sg:phone":"+1 706 653 7467",
    "sg:postcode":"31901",
    "sg:province":"GA",
    "sg:tags":[
        "taxicab"
    ],
    "wof:name":"City Cab Shop",
    "wof:placetype":"venue"
},
  "geometry": {"coordinates":[-84.97574,32.481295],"type":"Point"}
}