{
  "type": "Feature",
  "properties": {
    "iso:country":"US",
    "sg:address":"127 Peachtree St NE Ste 1010",
    "sg:city":"Atlanta",
    "sg:classifiers":[
        {
            "category":"Professional",
            "subcategory":"Lawyer & Legal Services",
            "type":"Services"
        }
    ],
    "sg:phone":"+1 404 874 4213",
    "sg:postcode":"30303",
    "sg:province":"GA",
    "wof:name":"The Law Office of Daryl Von Yokely",
    "wof:placetype":"venue"
},
  "geometry": {"coordinates":[-84.387817,33.757062],"type":"Point"}
}