{
  "type": "Feature",
  "properties": {
    "iso:country":"US",
    "sg:address":"321 Wagon Wheel Way",
    "sg:city":"Peachtree City",
    "sg:classifiers":[
        {
            "category":"Building & Trades",
            "subcategory":"Cleaning & Sanitation",
            "type":"Services"
        }
    ],
    "sg:phone":"+1 770 632 8636",
    "sg:postcode":"30269",
    "sg:province":"GA",
    "sg:tags":[
        "janitor"
    ],
    "wof:name":"Susan Palmer's Cleaning Svc",
    "wof:placetype":"venue"
},
  "geometry": {"coordinates":[-84.55589999999999,33.422932],"type":"Point"}
}