{
  "type": "Feature",
  "properties": {
    "addr:full":"272 Oak Hill Rd Cairo GA 39828",
    "addr:housenumber":"272",
    "addr:postcode":"39828",
    "addr:street":"Oak Hill Rd",
    "iso:country":"US",
    "sg:address":"272 Oak Hill Rd",
    "sg:city":"Cairo",
    "sg:classifiers":[
        {
            "category":"Wholesale",
            "subcategory":"Fruits & Vegetables",
            "type":"Manufacturing & Wholesale Goods"
        }
    ],
    "sg:phone":"+1 229 872 3214",
    "sg:postcode":"39828",
    "sg:province":"GA",
    "sg:tags":[
        "fresh",
        "vegetables-wholesale"
    ],
    "wof:name":"Hopkins Food Services, Inc.",
    "wof:placetype":"venue"
},
  "geometry": {"coordinates":[-84.288392,30.776271],"type":"Point"}
}