{
  "type": "Feature",
  "properties": {
    "addr:full":"2750 Cleveland Hwy Murrayville GA 30564",
    "addr:housenumber":"2750",
    "addr:postcode":"30564",
    "addr:street":"Cleveland Hwy",
    "iso:country":"US",
    "sg:address":"2750 Cleveland Hwy",
    "sg:city":"Murrayville",
    "sg:classifiers":[
        {
            "category":"Freight",
            "type":"Transportation"
        }
    ],
    "sg:phone":"+1 706 867 8381",
    "sg:postcode":"30564",
    "sg:province":"GA",
    "sg:tags":[
        "hauling",
        "trucking"
    ],
    "wof:name":"Triple C Grading & Hauling Inc",
    "wof:placetype":"venue"
},
  "geometry": {"coordinates":[-83.844097,34.539685],"type":"Point"}
}