{
  "type": "Feature",
  "properties": {
    "iso:country":"US",
    "sg:address":"101 Powder Creek Ct",
    "sg:city":"Dallas",
    "sg:classifiers":[
        {
            "category":"Building & Trades",
            "subcategory":"Construction",
            "type":"Services"
        }
    ],
    "sg:phone":"+1 770 445 9937",
    "sg:postcode":"30157",
    "sg:province":"GA",
    "sg:tags":[
        "contractor"
    ],
    "wof:name":"Hennington Construction",
    "wof:placetype":"venue"
},
  "geometry": {"coordinates":[-84.74742500000001,33.914458],"type":"Point"}
}