{
  "type": "Feature",
  "properties": {
    "iso:country":"US",
    "sg:address":"3955 Lawrenceville Hwy",
    "sg:city":"Lilburn",
    "sg:classifiers":[
        {
            "category":"Professional",
            "subcategory":"Accounting & Tax Preparation",
            "type":"Services"
        }
    ],
    "sg:phone":"+1 770 925 1143",
    "sg:postcode":"30047",
    "sg:province":"GA",
    "sg:tags":[
        "billing"
    ],
    "wof:name":"Provider Resource Network Inc",
    "wof:placetype":"venue"
},
  "geometry": {"coordinates":[-84.114763,33.904057],"type":"Point"}
}