{
  "type": "Feature",
  "properties": {
    "addr:full":"1458 Tutt Ave Augusta GA 30901",
    "addr:housenumber":"1458",
    "addr:postcode":"30901",
    "addr:street":"Tutt Ave",
    "iso:country":"US",
    "sg:address":"1458 Tutt Ave",
    "sg:city":"Augusta",
    "sg:classifiers":[
        {
            "category":"Organizations",
            "subcategory":"Religious Organization",
            "type":"Services"
        }
    ],
    "sg:phone":"+1 706 481 0784",
    "sg:postcode":"30901",
    "sg:province":"GA",
    "sg:tags":[
        "church"
    ],
    "wof:name":"Mt Sinai Baptist Church",
    "wof:placetype":"venue"
},
  "geometry": {"coordinates":[-81.99564700000001,33.459844],"type":"Point"}
}