{
  "type": "Feature",
  "properties": {
    "addr:full":"1200 Mayview Rd Sandersville GA 31082",
    "addr:housenumber":"1200",
    "addr:postcode":"31082",
    "addr:street":"Mayview Rd",
    "iso:country":"US",
    "sg:address":"1200 Mayview Rd",
    "sg:city":"Sandersville",
    "sg:classifiers":[
        {
            "category":"Manufacturing",
            "subcategory":"Paper Products",
            "type":"Manufacturing & Wholesale Goods"
        }
    ],
    "sg:phone":"+1 478 552 1408",
    "sg:postcode":"31082",
    "sg:province":"GA",
    "sg:tags":[
        "supplier"
    ],
    "wof:name":"Stephens Enterprises",
    "wof:placetype":"venue"
},
  "geometry": {"coordinates":[-82.78722,33.012902],"type":"Point"}
}