{
  "type": "Feature",
  "properties": {
    "addr:full":"209 Sunset Dr Dahlonega GA 30533",
    "addr:housenumber":"209",
    "addr:postcode":"30533",
    "addr:street":"Sunset Dr",
    "iso:country":"US",
    "sg:address":"209 Sunset Dr",
    "sg:city":"Dahlonega",
    "sg:classifiers":[
        {
            "category":"Professional",
            "subcategory":"Computer Services",
            "type":"Services"
        }
    ],
    "sg:phone":"+1 706 867 7699",
    "sg:postcode":"30533",
    "sg:province":"GA",
    "sg:tags":[
        "prepackaged",
        "software"
    ],
    "wof:name":"Click Software",
    "wof:placetype":"venue"
},
  "geometry": {"coordinates":[-83.99308000000001,34.529369],"type":"Point"}
}