{
  "type": "Feature",
  "properties": {
    "iso:country":"US",
    "sg:address":"200 Jesup Rd",
    "sg:city":"Pooler",
    "sg:classifiers":[
        {
            "category":"Sports & Exercise",
            "subcategory":"Race Track",
            "type":"Entertainment"
        }
    ],
    "sg:phone":"+1 912 964 8200",
    "sg:postcode":"31322",
    "sg:province":"GA",
    "sg:tags":[
        "operation",
        "racing",
        "or"
    ],
    "sg:website":"www.ospracing.net",
    "wof:name":"Oglethorpe Speedway",
    "wof:placetype":"venue"
},
  "geometry": {"coordinates":[-81.208232,32.089793],"type":"Point"}
}