{
  "type": "Feature",
  "properties": {
    "iso:country":"US",
    "sg:address":"4882 Glade Farm Rd",
    "sg:city":"Gainesville",
    "sg:classifiers":[
        {
            "category":"Professional",
            "subcategory":"Management & Consulting",
            "type":"Services"
        }
    ],
    "sg:phone":"+1 770 983 7078",
    "sg:postcode":"30506",
    "sg:province":"GA",
    "sg:tags":[
        "communications",
        "consultant"
    ],
    "wof:name":"Whitmire Communication Conslnt",
    "wof:placetype":"venue"
},
  "geometry": {"coordinates":[-83.76042099999999,34.413547],"type":"Point"}
}