{
  "type": "Feature",
  "properties": {
    "iso:country":"US",
    "sg:address":"2127 Martin Luther King Jr Blvd",
    "sg:city":"Augusta",
    "sg:classifiers":[
        {
            "category":"Organizations",
            "subcategory":"Religious Organization",
            "type":"Services"
        }
    ],
    "sg:phone":"+1 706 724 0008",
    "sg:postcode":"30901",
    "sg:province":"GA",
    "sg:tags":[
        "church"
    ],
    "wof:name":"Servants Of God Baptist Church",
    "wof:placetype":"venue"
},
  "geometry": {"coordinates":[-81.99714299999999,33.451588],"type":"Point"}
}