{
  "type": "Feature",
  "properties": {
    "addr:full":"342 Marietta St Atlanta GA 30313",
    "addr:housenumber":"342",
    "addr:postcode":"30313",
    "addr:street":"Marietta St",
    "iso:country":"US",
    "sg:address":"342 Marietta St",
    "sg:city":"Atlanta",
    "sg:classifiers":[
        {
            "category":"Manufacturing",
            "subcategory":"Signs",
            "type":"Manufacturing & Wholesale Goods"
        }
    ],
    "sg:phone":"+1 404 577 4099",
    "sg:postcode":"30313",
    "sg:province":"GA",
    "sg:tags":[
        "specialty",
        "mfg"
    ],
    "wof:name":"Pioneer Neon Lofts",
    "wof:placetype":"venue"
},
  "geometry": {"coordinates":[-84.397228,33.763292],"type":"Point"}
}