{
  "type": "Feature",
  "properties": {
    "iso:country":"US",
    "sg:address":"801 Tebeau St",
    "sg:city":"Waycross",
    "sg:classifiers":[
        {
            "category":"Shopping",
            "subcategory":"Florist",
            "type":"Retail Goods"
        }
    ],
    "sg:phone":"+1 912 285 1377",
    "sg:postcode":"31501",
    "sg:province":"GA",
    "wof:name":"Tebeauville Store",
    "wof:placetype":"venue"
},
  "geometry": {"coordinates":[-82.360024,31.216714],"type":"Point"}
}