{
  "type": "Feature",
  "properties": {
    "addr:full":"132 Collis Restaurant Rd Eatonton GA 31024",
    "addr:housenumber":"132",
    "addr:postcode":"31024",
    "addr:street":"Rd",
    "iso:country":"US",
    "sg:address":"132 Collis Restaurant Rd",
    "sg:city":"Eatonton",
    "sg:classifiers":[
        {
            "category":"Travel",
            "subcategory":"Hotels & Motels",
            "type":"Entertainment"
        }
    ],
    "sg:phone":"+1 706 485 6999",
    "sg:postcode":"31024",
    "sg:province":"GA",
    "sg:tags":[
        "lodging"
    ],
    "wof:name":"Brantley's Marina and Lodging",
    "wof:placetype":"venue"
},
  "geometry": {"coordinates":[-83.249809,33.395569],"type":"Point"}
}