{
  "type": "Feature",
  "properties": {
    "addr:full":"304 Grady St S Portal GA 30450",
    "addr:housenumber":"304",
    "addr:postcode":"30450",
    "addr:street":"Grady St S",
    "iso:country":"US",
    "sg:address":"304 Grady St S",
    "sg:city":"Portal",
    "sg:classifiers":[
        {
            "category":"Organizations",
            "subcategory":"Professional Association",
            "type":"Services"
        }
    ],
    "sg:phone":"+1 912 865 9811",
    "sg:postcode":"30450",
    "sg:province":"GA",
    "sg:website":"www.openchurch.com",
    "wof:name":"Open Church Ministries",
    "wof:placetype":"venue"
},
  "geometry": {"coordinates":[-81.933042,32.537365],"type":"Point"}
}