{
  "type": "Feature",
  "properties": {
    "iso:country":"US",
    "sg:address":"1060 Tuxedo Ct",
    "sg:city":"Roswell",
    "sg:classifiers":[
        {
            "category":"Professional",
            "subcategory":"Management & Consulting",
            "type":"Services"
        }
    ],
    "sg:phone":"+1 770 992 1816",
    "sg:postcode":"30075",
    "sg:province":"GA",
    "sg:tags":[
        "business"
    ],
    "wof:name":"Chapman Consultants Inc",
    "wof:placetype":"venue"
},
  "geometry": {"coordinates":[-84.34232799999999,34.02776],"type":"Point"}
}