{
  "type": "Feature",
  "properties": {
    "iso:country":"US",
    "sg:address":"424 W Memorial Dr",
    "sg:city":"Dallas",
    "sg:classifiers":[
        {
            "category":"Home & Garden",
            "subcategory":"Furniture",
            "type":"Retail Goods"
        }
    ],
    "sg:phone":"+1 770 505 5559",
    "sg:postcode":"30132",
    "sg:province":"GA",
    "wof:name":"Furniture World Inc",
    "wof:placetype":"venue"
},
  "geometry": {"coordinates":[-84.849125,33.923382],"type":"Point"}
}