{
  "type": "Feature",
  "properties": {
    "addr:full":"3501 Earline Ave Columbus GA 31904",
    "addr:housenumber":"3501",
    "addr:postcode":"31904",
    "addr:street":"Earline Ave",
    "iso:country":"US",
    "sg:address":"3501 Earline Ave",
    "sg:city":"Columbus",
    "sg:classifiers":[
        {
            "category":"Wholesale",
            "subcategory":"Non-durable Goods",
            "type":"Manufacturing & Wholesale Goods"
        }
    ],
    "sg:phone":"+1 706 321 8883",
    "sg:postcode":"31904",
    "sg:province":"GA",
    "sg:tags":[
        "advertising"
    ],
    "wof:name":"Solutions Too",
    "wof:placetype":"venue"
},
  "geometry": {"coordinates":[-84.978179,32.498292],"type":"Point"}
}