{
  "type": "Feature",
  "properties": {
    "iso:country":"US",
    "sg:address":"100 N Oaks Dr",
    "sg:city":"Dalton",
    "sg:classifiers":[
        {
            "category":"Food & Beverages",
            "subcategory":"Groceries & Convenience Stores",
            "type":"Retail Goods"
        }
    ],
    "sg:phone":"+1 706 259 2828",
    "sg:postcode":"30721",
    "sg:province":"GA",
    "wof:name":"Smart Mart",
    "wof:placetype":"venue"
},
  "geometry": {"coordinates":[-84.95854199999999,34.804532],"type":"Point"}
}