{
  "type": "Feature",
  "properties": {
    "addr:full":"2200 Center Dr Vidalia GA 30474",
    "addr:housenumber":"2200",
    "addr:postcode":"30474",
    "addr:street":"Center Dr Vidalia",
    "iso:country":"US",
    "sg:address":"2200 Center Dr",
    "sg:city":"Vidalia",
    "sg:classifiers":[
        {
            "category":"Organizations",
            "subcategory":"Religious Organization",
            "type":"Services"
        }
    ],
    "sg:phone":"+1 912 537 4651",
    "sg:postcode":"30474",
    "sg:province":"GA",
    "sg:tags":[
        "church"
    ],
    "wof:name":"New Life Church",
    "wof:placetype":"venue"
},
  "geometry": {"coordinates":[-82.40864999999999,32.187514],"type":"Point"}
}