{
  "type": "Feature",
  "properties": {
    "addr:full":"500 Sun Valley Dr Roswell GA 30076",
    "addr:housenumber":"500",
    "addr:postcode":"30076",
    "addr:street":"Sun Valley Dr",
    "iso:country":"US",
    "sg:address":"500 Sun Valley Dr",
    "sg:city":"Roswell",
    "sg:classifiers":[
        {
            "category":"Insurance",
            "subcategory":"Insurance Agent",
            "type":"Services"
        }
    ],
    "sg:phone":"+1 770 643 0600",
    "sg:postcode":"30076",
    "sg:province":"GA",
    "wof:name":"White Bill Insurance Agency",
    "wof:placetype":"venue"
},
  "geometry": {"coordinates":[-84.339178,34.05134],"type":"Point"}
}