{
  "type": "Feature",
  "properties": {
    "iso:country":"US",
    "sg:address":"207 Northridge Dr",
    "sg:city":"La Grange",
    "sg:classifiers":[
        {
            "category":"Professional",
            "subcategory":"Business Services",
            "type":"Services"
        }
    ],
    "sg:phone":"+1 706 845 0981",
    "sg:postcode":"30240",
    "sg:province":"GA",
    "wof:name":"Lindner Solutions Inc",
    "wof:placetype":"venue"
},
  "geometry": {"coordinates":[-85.04720399999999,33.081745],"type":"Point"}
}