{
  "type": "Feature",
  "properties": {
    "addr:full":"452 Cherokee Ave SE Ste A Atlanta GA 30312",
    "addr:housenumber":"452",
    "addr:postcode":"30312",
    "addr:street":"Cherokee Ave Se Ste A",
    "iso:country":"US",
    "sg:address":"452 Cherokee Ave SE Ste A",
    "sg:city":"Atlanta",
    "sg:classifiers":[
        {
            "category":"Personal",
            "subcategory":"Beauty Salon",
            "type":"Services"
        }
    ],
    "sg:phone":"+1 404 222 0244",
    "sg:postcode":"30312",
    "sg:province":"GA",
    "sg:tags":[
        "hair",
        "stylist"
    ],
    "sg:website":"http://www.fresche.net",
    "wof:name":"Fresche.",
    "wof:placetype":"venue"
},
  "geometry": {"coordinates":[-84.37341000000001,33.742044],"type":"Point"}
}