{
  "type": "Feature",
  "properties": {
    "iso:country":"US",
    "sg:address":"519 W Adair St",
    "sg:city":"Valdosta",
    "sg:classifiers":[
        {
            "category":"Place Of Worship",
            "subcategory":"Church",
            "type":"Public Place"
        },
        {
            "category":"Place Of Worship",
            "type":"Public Place"
        }
    ],
    "sg:phone":"+1 229 244 4848",
    "sg:postcode":"31601",
    "sg:province":"GA",
    "sg:tags":[
        "churches-interdenominational",
        "churches-various",
        "denomination"
    ],
    "wof:name":"Universal Deliverance Church Inc",
    "wof:placetype":"venue"
},
  "geometry": {"coordinates":[-83.28882299999999,30.836068],"type":"Point"}
}