{
  "type": "Feature",
  "properties": {
    "addr:full":"140 Oak St Canton GA 30114",
    "addr:housenumber":"140",
    "addr:postcode":"30114",
    "addr:street":"Oak St",
    "iso:country":"US",
    "sg:address":"140 Oak St",
    "sg:city":"Canton",
    "sg:classifiers":[
        {
            "category":"Building & Trades",
            "subcategory":"Electrical",
            "type":"Services"
        }
    ],
    "sg:phone":"+1 770 479 1675",
    "sg:postcode":"30114",
    "sg:province":"GA",
    "sg:tags":[
        "electrical",
        "contractor"
    ],
    "wof:name":"B & T Electric Inc",
    "wof:placetype":"venue"
},
  "geometry": {"coordinates":[-84.487071,34.238551],"type":"Point"}
}