{
  "type": "Feature",
  "properties": {
    "iso:country":"US",
    "sg:address":"11030 Bell Rd",
    "sg:city":"Duluth",
    "sg:classifiers":[
        {
            "category":"Real Estate",
            "subcategory":"Real Estate Services",
            "type":"Services"
        },
        {
            "category":"Real Estate",
            "subcategory":"Real Estate Agent",
            "type":"Services"
        }
    ],
    "sg:phone":"+1 770 497 0797",
    "sg:postcode":"30097",
    "sg:province":"GA",
    "sg:tags":[
        "buyer",
        "broker"
    ],
    "sg:website":"http://www.prudentialproperties.com",
    "wof:name":"Prudential Georgia Realty",
    "wof:placetype":"venue"
},
  "geometry": {"coordinates":[-84.17601000000001,34.050152],"type":"Point"}
}