{
  "type": "Feature",
  "properties": {
    "addr:full":"3546 Stapp Dr Tucker GA 30084",
    "addr:housenumber":"3546",
    "addr:postcode":"30084",
    "addr:street":"Stapp Dr",
    "iso:country":"US",
    "sg:address":"3546 Stapp Dr",
    "sg:city":"Tucker",
    "sg:classifiers":[
        {
            "category":"Recreation",
            "type":"Entertainment"
        }
    ],
    "sg:phone":"+1 770 496 0002",
    "sg:postcode":"30084",
    "sg:province":"GA",
    "sg:tags":[
        "fishing",
        "lake"
    ],
    "wof:name":"Twin Brothers Lake",
    "wof:placetype":"venue"
},
  "geometry": {"coordinates":[-84.24351,33.826163],"type":"Point"}
}