{
  "type": "Feature",
  "properties": {
    "addr:full":"233 E Broad St Griffin GA 30223",
    "addr:housenumber":"233",
    "addr:postcode":"30223",
    "addr:street":"E Broad St",
    "iso:country":"US",
    "sg:address":"233 E Broad St",
    "sg:city":"Griffin",
    "sg:classifiers":[
        {
            "category":"Railroad",
            "type":"Transportation"
        }
    ],
    "sg:phone":"+1 770 227 3281",
    "sg:postcode":"30223",
    "sg:province":"GA",
    "wof:name":"Griffin Depot",
    "wof:placetype":"venue"
},
  "geometry": {"coordinates":[-84.26162600000001,33.250088],"type":"Point"}
}