{
  "type": "Feature",
  "properties": {
    "addr:full":"221 New Normantown Rd Vidalia GA 30474",
    "addr:housenumber":"221",
    "addr:postcode":"30474",
    "addr:street":"New Normantown Rd",
    "iso:country":"US",
    "sg:address":"221 New Normantown Rd",
    "sg:city":"Vidalia",
    "sg:classifiers":[
        {
            "category":"Wholesale",
            "subcategory":"Farm Supplies",
            "type":"Manufacturing & Wholesale Goods"
        }
    ],
    "sg:phone":"+1 912 537 2172",
    "sg:postcode":"30474",
    "sg:province":"GA",
    "sg:tags":[
        "livestock"
    ],
    "wof:name":"H&M Livestock Market Inc",
    "wof:placetype":"venue"
},
  "geometry": {"coordinates":[-82.39074100000001,32.294084],"type":"Point"}
}