{
  "type": "Feature",
  "properties": {
    "iso:country":"US",
    "sg:address":"851 Ooltewah Ringgold Rd",
    "sg:city":"Ringgold",
    "sg:classifiers":[
        {
            "category":"Place Of Worship",
            "type":"Public Place"
        }
    ],
    "sg:phone":"+1 706 935 2382",
    "sg:postcode":"30736",
    "sg:province":"GA",
    "sg:tags":[
        "church"
    ],
    "wof:name":"Friendship Primitive Baptist",
    "wof:placetype":"venue"
},
  "geometry": {"coordinates":[-85.09923999999999,34.974817],"type":"Point"}
}