{
  "type": "Feature",
  "properties": {
    "addr:full":"2601 Parkwood Dr Brunswick GA 31520",
    "addr:housenumber":"2601",
    "addr:postcode":"31520",
    "addr:street":"Parkwood Dr",
    "iso:country":"US",
    "sg:address":"2601 Parkwood Dr",
    "sg:city":"Brunswick",
    "sg:classifiers":[
        {
            "category":"Health Services",
            "subcategory":"Clinic",
            "type":"Services"
        },
        {
            "category":"Professional",
            "subcategory":"Management & Consulting",
            "type":"Services"
        }
    ],
    "sg:phone":"+1 912 554 8220",
    "sg:postcode":"31520",
    "sg:province":"GA",
    "sg:tags":[
        "home",
        "infusion"
    ],
    "wof:name":"Seaside Pharmaceutical Inc",
    "wof:placetype":"venue"
},
  "geometry": {"coordinates":[-81.482388,31.173474],"type":"Point"}
}