{
  "type": "Feature",
  "properties": {
    "iso:country":"US",
    "sg:address":"1739 US Hwy 1",
    "sg:city":"Lyons",
    "sg:classifiers":[
        {
            "category":"Food & Beverages",
            "subcategory":"Groceries & Convenience Stores",
            "type":"Retail Goods"
        }
    ],
    "sg:phone":"+1 912 526 4301",
    "sg:postcode":"30436",
    "sg:province":"GA",
    "wof:name":"Sweet Onion Junction",
    "wof:placetype":"venue"
},
  "geometry": {"coordinates":[-82.339833,32.157745],"type":"Point"}
}