{
  "type": "Feature",
  "properties": {
    "addr:full":"25 Tara Ct Savannah GA 31406",
    "addr:housenumber":"25",
    "addr:postcode":"31406",
    "addr:street":"Tara Ct",
    "iso:country":"US",
    "sg:address":"25 Tara Ct",
    "sg:city":"Savannah",
    "sg:classifiers":[
        {
            "category":"Professional",
            "subcategory":"Secretarial Services",
            "type":"Services"
        }
    ],
    "sg:phone":"+1 912 356 5489",
    "sg:postcode":"31406",
    "sg:province":"GA",
    "sg:tags":[
        "transcription",
        "medical"
    ],
    "wof:name":"Savannah Transcription Service",
    "wof:placetype":"venue"
},
  "geometry": {"coordinates":[-81.077297,31.982879],"type":"Point"}
}