{
  "type": "Feature",
  "properties": {
    "iso:country":"US",
    "sg:address":"1429 State Rte 23",
    "sg:city":"Waynesboro",
    "sg:classifiers":[
        {
            "category":"Health Services",
            "subcategory":"Nursing And Care Facility",
            "type":"Services"
        }
    ],
    "sg:phone":"+1 706 437 0951",
    "sg:postcode":"30830",
    "sg:province":"GA",
    "sg:tags":[
        "personal",
        "home"
    ],
    "wof:name":"Wesby Personal Care Home Inc",
    "wof:placetype":"venue"
},
  "geometry": {"coordinates":[-81.929681,33.196831],"type":"Point"}
}