{
  "type": "Feature",
  "properties": {
    "addr:full":"510 W Lake Dr Athens GA 30606",
    "addr:housenumber":"510",
    "addr:postcode":"30606",
    "addr:street":"W Lake Dr",
    "iso:country":"US",
    "sg:address":"510 W Lake Dr",
    "sg:city":"Athens",
    "sg:classifiers":[
        {
            "category":"Professional",
            "subcategory":"Engineering",
            "type":"Services"
        }
    ],
    "sg:phone":"+1 706 546 5617",
    "sg:postcode":"30606",
    "sg:province":"GA",
    "sg:tags":[
        "consulting",
        "engineer"
    ],
    "wof:name":"Sam Mc Williams & Associates",
    "wof:placetype":"venue"
},
  "geometry": {"coordinates":[-83.402174,33.936546],"type":"Point"}
}