{
  "type": "Feature",
  "properties": {
    "addr:full":"6558 Roswell Rd NE Atlanta GA 30328",
    "addr:housenumber":"6558;rd",
    "addr:postcode":"30328",
    "addr:street":"Roswell;Ne",
    "iso:country":"US",
    "sg:address":"6558 Roswell Rd NE",
    "sg:city":"Atlanta",
    "sg:classifiers":[
        {
            "category":"Place Of Worship",
            "type":"Public Place"
        }
    ],
    "sg:phone":"+1 404 252 8929",
    "sg:postcode":"30328",
    "sg:province":"GA",
    "sg:tags":[
        "church"
    ],
    "wof:name":"Lazarus House Ministries",
    "wof:placetype":"venue"
},
  "geometry": {"coordinates":[-84.37975,33.934607],"type":"Point"}
}