{
  "type": "Feature",
  "properties": {
    "addr:full":"1396 Government Cir Jonesboro GA 30236",
    "addr:housenumber":"1396",
    "addr:postcode":"30236",
    "addr:street":"Government Cir",
    "iso:country":"US",
    "sg:address":"1396 Government Cir",
    "sg:city":"Jonesboro",
    "sg:classifiers":[
        {
            "category":"Animal Shelter",
            "type":"Public Place"
        },
        {
            "category":"Government",
            "subcategory":"Office",
            "type":"Public Place"
        }
    ],
    "sg:phone":"+1 770 477 3509",
    "sg:postcode":"30236",
    "sg:province":"GA",
    "sg:tags":[
        "parish",
        "government-county"
    ],
    "wof:name":"Clayton County Rabies & Animal",
    "wof:placetype":"venue"
},
  "geometry": {"coordinates":[-84.35019200000001,33.536464],"type":"Point"}
}