{
  "type": "Feature",
  "properties": {
    "addr:full":"1710 Philema Rd S Albany GA 31701",
    "addr:housenumber":"1710",
    "addr:postcode":"31701",
    "addr:street":"Philema Rd",
    "iso:country":"US",
    "sg:address":"1710 Philema Rd S",
    "sg:city":"Albany",
    "sg:classifiers":[
        {
            "category":"Personal",
            "subcategory":"Beauty Salon",
            "type":"Services"
        }
    ],
    "sg:phone":"+1 229 436 3411",
    "sg:postcode":"31701",
    "sg:province":"GA",
    "sg:tags":[
        "hair",
        "stylist"
    ],
    "wof:name":"The Head Shed",
    "wof:placetype":"venue"
},
  "geometry": {"coordinates":[-84.11535600000001,31.63273],"type":"Point"}
}