{
  "type": "Feature",
  "properties": {
    "addr:full":"423 Eastwood Dr Dublin GA 31021",
    "addr:housenumber":"423",
    "addr:postcode":"31021",
    "addr:street":"Eastwood Dr",
    "iso:country":"US",
    "sg:address":"423 Eastwood Dr",
    "sg:city":"Dublin",
    "sg:classifiers":[
        {
            "category":"Government",
            "subcategory":"Office",
            "type":"Public Place"
        }
    ],
    "sg:phone":"+1 478 272 7876",
    "sg:postcode":"31021",
    "sg:province":"GA",
    "wof:name":"Lee Payne/Norman",
    "wof:placetype":"venue"
},
  "geometry": {"coordinates":[-82.94425200000001,32.558929],"type":"Point"}
}