{
  "type": "Feature",
  "properties": {
    "iso:country":"US",
    "sg:address":"120 Morallion Hill",
    "sg:city":"Peachtree City",
    "sg:classifiers":[
        {
            "category":"Autos & Motor Vehicles",
            "subcategory":"Auto Supplies",
            "type":"Retail Goods"
        }
    ],
    "sg:phone":"+1 770 228 3866",
    "sg:postcode":"30269",
    "sg:province":"GA",
    "sg:tags":[
        "tire"
    ],
    "wof:name":"Alignments Unlimited",
    "wof:placetype":"venue"
},
  "geometry": {"coordinates":[-84.54483399999999,33.36096],"type":"Point"}
}