{
  "type": "Feature",
  "properties": {
    "iso:country":"US",
    "sg:address":"72 Benson Rd",
    "sg:city":"Dallas",
    "sg:classifiers":[
        {
            "category":"Freight",
            "type":"Transportation"
        }
    ],
    "sg:phone":"+1 770 445 9283",
    "sg:postcode":"30132",
    "sg:province":"GA",
    "sg:tags":[
        "operator",
        "local",
        "trucking"
    ],
    "wof:name":"Tony Wilson Trucking Inc",
    "wof:placetype":"venue"
},
  "geometry": {"coordinates":[-84.84538000000001,34.015044],"type":"Point"}
}