{
  "type": "Feature",
  "properties": {
    "iso:country":"US",
    "sg:address":"126 Parks Mill Rd",
    "sg:city":"Buckhead",
    "sg:classifiers":[
        {
            "category":"Health Services",
            "subcategory":"Nursing And Care Facility",
            "type":"Services"
        }
    ],
    "sg:phone":"+1 706 485 1179",
    "sg:postcode":"30625",
    "sg:province":"GA",
    "sg:tags":[
        "residential",
        "intermediate"
    ],
    "wof:name":"Oconee Gardens Retirement Home",
    "wof:placetype":"venue"
},
  "geometry": {"coordinates":[-83.324539,33.451343],"type":"Point"}
}