{
  "type": "Feature",
  "properties": {
    "iso:country":"US",
    "sg:address":"1705 Washington St",
    "sg:city":"Bainbridge",
    "sg:classifiers":[
        {
            "category":"Professional",
            "type":"Services"
        }
    ],
    "sg:phone":"+1 229 248 0651",
    "sg:postcode":"39819",
    "sg:province":"FL",
    "wof:name":"Margaret Fagg",
    "wof:placetype":"venue"
},
  "geometry": {"coordinates":[-84.579015,30.888492],"type":"Point"}
}