{
  "type": "Feature",
  "properties": {
    "addr:full":"901 Veterans Memorial Pkwy SE Mableton GA 30126",
    "addr:housenumber":"901",
    "addr:postcode":"30126",
    "addr:street":"Veterans Memorial Pkwy Se",
    "iso:country":"US",
    "sg:address":"901 Veterans Memorial Pkwy SE",
    "sg:city":"Mableton",
    "sg:classifiers":[
        {
            "category":"Insurance",
            "subcategory":"Insurance Agent",
            "type":"Services"
        }
    ],
    "sg:phone":"+1 770 941 2352",
    "sg:postcode":"30126",
    "sg:province":"GA",
    "wof:name":"All Risk Insurance",
    "wof:placetype":"venue"
},
  "geometry": {"coordinates":[-84.52765599999999,33.805205],"type":"Point"}
}