{
  "type": "Feature",
  "properties": {
    "addr:full":"201 E Broad St Greensboro GA 30642",
    "addr:housenumber":"201",
    "addr:postcode":"30642",
    "addr:street":"E Broad St",
    "iso:country":"US",
    "sg:address":"201 E Broad St",
    "sg:city":"Greensboro",
    "sg:classifiers":[
        {
            "category":"Restaurant",
            "type":"Food & Drink"
        }
    ],
    "sg:phone":"+1 706 453 4062",
    "sg:postcode":"30642",
    "sg:province":"GA",
    "sg:tags":[
        "eating"
    ],
    "wof:name":"Hardees",
    "wof:placetype":"venue"
},
  "geometry": {"coordinates":[-83.18106299999999,33.575784],"type":"Point"}
}