{
  "type": "Feature",
  "properties": {
    "addr:full":"989 Slygo Rd Trenton GA 30752",
    "addr:housenumber":"989",
    "addr:postcode":"30752",
    "addr:street":"Slygo Rd",
    "iso:country":"US",
    "sg:address":"989 Slygo Rd",
    "sg:city":"Trenton",
    "sg:classifiers":[
        {
            "category":"Utilities",
            "subcategory":"Water",
            "type":"Services"
        }
    ],
    "sg:phone":"+1 706 657 2000",
    "sg:postcode":"30752",
    "sg:province":"GA",
    "sg:tags":[
        "bulk",
        "companies-bottled"
    ],
    "wof:name":"Water 2000 Marketing Inc",
    "wof:placetype":"venue"
},
  "geometry": {"coordinates":[-85.48317400000001,34.942676],"type":"Point"}
}