{
  "type": "Feature",
  "properties": {
    "addr:full":"230 Doctortown Rd Jesup GA 31545",
    "addr:housenumber":"230",
    "addr:postcode":"31545",
    "addr:street":"Doctortown Rd",
    "iso:country":"US",
    "sg:address":"230 Doctortown Rd",
    "sg:city":"Jesup",
    "sg:classifiers":[
        {
            "category":"Professional",
            "subcategory":"Management & Consulting",
            "type":"Services"
        }
    ],
    "sg:phone":"+1 912 427 9004",
    "sg:postcode":"31545",
    "sg:province":"GA",
    "sg:tags":[
        "consultant",
        "safety"
    ],
    "wof:name":"OCTS Inc",
    "wof:placetype":"venue"
},
  "geometry": {"coordinates":[-81.84360599999999,31.648626],"type":"Point"}
}