{
  "type": "Feature",
  "properties": {
    "addr:full":"4201 Hwy 142 Newborn GA 30056",
    "addr:housenumber":"4201",
    "addr:postcode":"30056",
    "addr:street":"Hwy 142 Newborn",
    "iso:country":"US",
    "sg:address":"4201 Hwy 142",
    "sg:city":"Newborn",
    "sg:classifiers":[
        {
            "category":"Personal",
            "subcategory":"Beauty Salon",
            "type":"Services"
        }
    ],
    "sg:phone":"+1 770 787 6115",
    "sg:postcode":"30056",
    "sg:province":"GA",
    "wof:name":"A Cut Above",
    "wof:placetype":"venue"
},
  "geometry": {"coordinates":[-83.695801,33.517001],"type":"Point"}
}