{
  "type": "Feature",
  "properties": {
    "addr:full":"111 Oakcrest Dr Statesboro GA 30461",
    "addr:housenumber":"111",
    "addr:postcode":"30461",
    "addr:street":"Oakcrest Dr",
    "iso:country":"US",
    "sg:address":"111 Oakcrest Dr",
    "sg:city":"Statesboro",
    "sg:classifiers":[
        {
            "category":"Professional",
            "type":"Services"
        }
    ],
    "sg:phone":"+1 912 489 6840",
    "sg:postcode":"30461",
    "sg:province":"GA",
    "sg:tags":[
        "establishment"
    ],
    "wof:name":"Josh Aubrey Productions",
    "wof:placetype":"venue"
},
  "geometry": {"coordinates":[-81.751198,32.454459],"type":"Point"}
}