{
  "type": "Feature",
  "properties": {
    "addr:full":"780 Baconsfield Dr Macon GA 31211",
    "addr:housenumber":"780",
    "addr:postcode":"31211",
    "addr:street":"Baconsfield Dr",
    "iso:country":"US",
    "sg:address":"780 Baconsfield Dr",
    "sg:city":"Macon",
    "sg:classifiers":[
        {
            "category":"Social Services",
            "type":"Services"
        }
    ],
    "sg:phone":"+1 478 743 9165",
    "sg:postcode":"31211",
    "sg:province":"GA",
    "sg:tags":[
        "organization",
        "welfare"
    ],
    "wof:name":"March Of Dimes",
    "wof:placetype":"venue"
},
  "geometry": {"coordinates":[-83.62691700000001,32.851896],"type":"Point"}
}