{
  "type": "Feature",
  "properties": {
    "iso:country":"US",
    "sg:address":"8400 Abercorn St",
    "sg:city":"Savannah",
    "sg:classifiers":[
        {
            "category":"Professional",
            "subcategory":"Detective & Security Services",
            "type":"Services"
        }
    ],
    "sg:phone":"+1 912 925 8988",
    "sg:postcode":"31406",
    "sg:province":"GA",
    "sg:tags":[
        "guard",
        "patrol"
    ],
    "wof:name":"A P Security Agency",
    "wof:placetype":"venue"
},
  "geometry": {"coordinates":[-81.12724300000001,31.99933],"type":"Point"}
}