{
  "type": "Feature",
  "properties": {
    "addr:full":"326 Taft St SW Atlanta GA 30315",
    "addr:housenumber":"326",
    "addr:postcode":"30315",
    "addr:street":"Taft St Sw",
    "iso:country":"US",
    "sg:address":"326 Taft St SW",
    "sg:city":"Atlanta",
    "sg:classifiers":[
        {
            "category":"Social Services",
            "subcategory":"Child Care",
            "type":"Services"
        }
    ],
    "sg:phone":"+1 404 624 8181",
    "sg:postcode":"30315",
    "sg:province":"GA",
    "sg:tags":[
        "nursery",
        "day"
    ],
    "wof:name":"Ram Personal Care Program",
    "wof:placetype":"venue"
},
  "geometry": {"coordinates":[-84.39924600000001,33.710499],"type":"Point"}
}