{
  "type": "Feature",
  "properties": {
    "iso:country":"US",
    "sg:address":"890 Rivermist Dr",
    "sg:city":"Ball Ground",
    "sg:classifiers":[
        {
            "category":"Manufacturing",
            "subcategory":"Apparel",
            "type":"Manufacturing & Wholesale Goods"
        }
    ],
    "sg:phone":"+1 770 479 1262",
    "sg:postcode":"30107",
    "sg:province":"GA",
    "sg:tags":[
        "textile",
        "product",
        "fabricated",
        "mfg"
    ],
    "wof:name":"Rivermist Farm",
    "wof:placetype":"venue"
},
  "geometry": {"coordinates":[-84.413539,34.291351],"type":"Point"}
}