{
  "type": "Feature",
  "properties": {
    "iso:country":"US",
    "sg:address":"323 Industrial Blvd",
    "sg:city":"Thomasville",
    "sg:classifiers":[
        {
            "category":"Manufacturing",
            "subcategory":"Rubber & Plastics",
            "type":"Manufacturing & Wholesale Goods"
        }
    ],
    "sg:phone":"+1 229 228 6366",
    "sg:postcode":"31792",
    "sg:province":"GA",
    "sg:website":"www.hpii.com",
    "wof:name":"Home Products Intl Corp",
    "wof:placetype":"venue"
},
  "geometry": {"coordinates":[-83.995816,30.8303],"type":"Point"}
}