{
  "type": "Feature",
  "properties": {
    "iso:country":"US",
    "sg:address":"405 Cumming St",
    "sg:city":"Alpharetta",
    "sg:classifiers":[
        {
            "category":"Education",
            "subcategory":"School",
            "type":"Public Place"
        }
    ],
    "sg:phone":"+1 770 667 2912",
    "sg:postcode":"30004",
    "sg:province":"GA",
    "sg:tags":[
        "high",
        "middle",
        "elementary"
    ],
    "wof:name":"Fulton County Board of Education",
    "wof:placetype":"venue"
},
  "geometry": {"coordinates":[-84.278066,34.08341],"type":"Point"}
}