{
  "type": "Feature",
  "properties": {
    "addr:full":"450 Wynbrooke Pkwy Stone Mountain GA 30087",
    "addr:housenumber":"450",
    "addr:postcode":"30087",
    "addr:street":"Wynbrooke Pkwy",
    "iso:country":"US",
    "sg:address":"450 Wynbrooke Pkwy",
    "sg:city":"Stone Mountain",
    "sg:classifiers":[
        {
            "category":"Home & Garden",
            "subcategory":"Furniture",
            "type":"Retail Goods"
        }
    ],
    "sg:phone":"+1 770 469 8363",
    "sg:postcode":"30087",
    "sg:province":"GA",
    "wof:name":"Keppeler Fine Furniture",
    "wof:placetype":"venue"
},
  "geometry": {"coordinates":[-84.10829099999999,33.789132],"type":"Point"}
}