{
  "type": "Feature",
  "properties": {
    "addr:full":"2464 Winder Hwy Dacula GA 30019",
    "addr:housenumber":"2464",
    "addr:postcode":"ga 30019",
    "addr:street":"Winder Hwy",
    "iso:country":"US",
    "sg:address":"2464 Winder Hwy",
    "sg:city":"Dacula",
    "sg:classifiers":[
        {
            "category":"Utilities",
            "subcategory":"Mobile Phone",
            "type":"Services"
        },
        {
            "category":"Communications",
            "type":"Services"
        }
    ],
    "sg:phone":"+1 770 682 6033",
    "sg:postcode":"30019",
    "sg:province":"GA",
    "sg:tags":[
        "communication",
        "telephone",
        "cellular"
    ],
    "wof:name":"Next Star Communication Inc",
    "wof:placetype":"venue"
},
  "geometry": {"coordinates":[-83.899179,33.989045],"type":"Point"}
}