{
  "type": "Feature",
  "properties": {
    "iso:country":"US",
    "sg:address":"4052 Indian Creek Rd",
    "sg:city":"Martinez",
    "sg:classifiers":[
        {
            "category":"Professional",
            "subcategory":"Accounting & Tax Preparation",
            "type":"Services"
        }
    ],
    "sg:phone":"+1 706 863 2537",
    "sg:postcode":"30907",
    "sg:province":"GA",
    "sg:tags":[
        "billing"
    ],
    "wof:name":"Medi-CLAIMS LLC",
    "wof:placetype":"venue"
},
  "geometry": {"coordinates":[-82.102085,33.496997],"type":"Point"}
}