{
  "type": "Feature",
  "properties": {
    "addr:full":"350 Hendrix Rd Villa Rica GA 30153",
    "addr:housenumber":"350",
    "addr:postcode":"30153",
    "addr:street":"Hendrix Rd",
    "iso:country":"US",
    "sg:address":"350 Hendrix Rd",
    "sg:city":"Villa Rica",
    "sg:classifiers":[
        {
            "category":"Professional",
            "subcategory":"Management & Consulting",
            "type":"Services"
        }
    ],
    "sg:phone":"+1 770 459 4160",
    "sg:postcode":"30153",
    "sg:province":"GA",
    "sg:tags":[
        "business"
    ],
    "wof:name":"Veit Consulting Inc",
    "wof:placetype":"venue"
},
  "geometry": {"coordinates":[-85.144795,33.994546],"type":"Point"}
}