{
  "type": "Feature",
  "properties": {
    "iso:country":"US",
    "sg:address":"3775 Sixes Rd",
    "sg:city":"Canton",
    "sg:classifiers":[
        {
            "category":"Personal",
            "subcategory":"Barber",
            "type":"Services"
        }
    ],
    "sg:phone":"+1 404 892 1233",
    "sg:postcode":"30114",
    "sg:province":"GA",
    "sg:tags":[
        "shop"
    ],
    "wof:name":"Bc and Co",
    "wof:placetype":"venue"
},
  "geometry": {"coordinates":[-84.548875,34.175956],"type":"Point"}
}