{
  "type": "Feature",
  "properties": {
    "addr:full":"1100 Circle 75 Pkwy SE Ste 1200 Atlanta GA 30339",
    "addr:housenumber":"1100",
    "addr:postcode":"30339",
    "addr:street":"Circle 75 Pkwy Se Ste 1200",
    "iso:country":"US",
    "sg:address":"1100 Circle 75 Pkwy SE Ste 1200",
    "sg:city":"Atlanta",
    "sg:classifiers":[
        {
            "category":"Professional",
            "subcategory":"Advertising",
            "type":"Services"
        }
    ],
    "sg:phone":"+1 770 303 0400",
    "sg:postcode":"30339",
    "sg:province":"GA",
    "sg:tags":[
        "product",
        "advertising-promotional",
        "specialty"
    ],
    "wof:name":"Summit-Atlanta",
    "wof:placetype":"venue"
},
  "geometry": {"coordinates":[-84.465024,33.890776],"type":"Point"}
}