{
  "type": "Feature",
  "properties": {
    "iso:country":"US",
    "sg:address":"5558 Neal Dr",
    "sg:city":"Macon",
    "sg:classifiers":[
        {
            "category":"Shopping",
            "subcategory":"Hobbies, Toys, & Games",
            "type":"Retail Goods"
        }
    ],
    "sg:phone":"+1 478 781 1429",
    "sg:postcode":"31216",
    "sg:province":"GA",
    "sg:tags":[
        "craft",
        "gift",
        "supply"
    ],
    "wof:name":"K & S Craft Supls & Gifts Inc",
    "wof:placetype":"venue"
},
  "geometry": {"coordinates":[-83.747731,32.710245],"type":"Point"}
}