{
  "type": "Feature",
  "properties": {
    "iso:country":"US",
    "sg:address":"2877 Hammett Rd",
    "sg:city":"Hogansville",
    "sg:classifiers":[
        {
            "category":"Building & Trades",
            "subcategory":"Construction",
            "type":"Services"
        }
    ],
    "sg:phone":"+1 706 883 8855",
    "sg:postcode":"30230",
    "sg:province":"GA",
    "sg:tags":[
        "wallcoverings-installation",
        "wallpaper",
        "painting",
        "contractor"
    ],
    "wof:name":"Total Painting Inc",
    "wof:placetype":"venue"
},
  "geometry": {"coordinates":[-84.978342,33.130958],"type":"Point"}
}