{
  "type": "Feature",
  "properties": {
    "iso:country":"US",
    "sg:address":"1064 Spruce Creek Ln",
    "sg:city":"Lawrenceville",
    "sg:classifiers":[
        {
            "category":"Real Estate",
            "subcategory":"Real Estate Agent",
            "type":"Services"
        }
    ],
    "sg:phone":"+1 770 339 6497",
    "sg:postcode":"30045",
    "sg:province":"GA",
    "wof:name":"Next Level Realty",
    "wof:placetype":"venue"
},
  "geometry": {"coordinates":[-83.935733,33.935511],"type":"Point"}
}