{
  "type": "Feature",
  "properties": {
    "addr:full":"121 E Jefferson St Madison GA 30650",
    "addr:housenumber":"121",
    "addr:postcode":"30650",
    "addr:street":"E Jefferson St",
    "iso:country":"US",
    "sg:address":"121 E Jefferson St",
    "sg:city":"Madison",
    "sg:classifiers":[
        {
            "category":"Real Estate",
            "subcategory":"Real Estate Agent",
            "type":"Services"
        }
    ],
    "sg:phone":"+1 706 342 0693",
    "sg:postcode":"30650",
    "sg:province":"GA",
    "wof:name":"Madison Realty Inc",
    "wof:placetype":"venue"
},
  "geometry": {"coordinates":[-83.464862,33.594383],"type":"Point"}
}