{
  "type": "Feature",
  "properties": {
    "iso:country":"US",
    "sg:address":"125 Townpark Dr",
    "sg:city":"Kennesaw",
    "sg:classifiers":[
        {
            "category":"Organizations",
            "subcategory":"Professional Association",
            "type":"Services"
        }
    ],
    "sg:phone":"+1 770 420 8285",
    "sg:postcode":"30144",
    "sg:province":"GA",
    "sg:tags":[
        "business",
        "trade"
    ],
    "wof:name":"Balt Trading Intl",
    "wof:placetype":"venue"
},
  "geometry": {"coordinates":[-84.566451,34.037749],"type":"Point"}
}