{
  "type": "Feature",
  "properties": {
    "addr:full":"749 E 3rd St Jackson GA 30233",
    "addr:housenumber":"749",
    "addr:postcode":"30233",
    "addr:street":"E 3Rd St",
    "iso:country":"US",
    "sg:address":"749 E 3rd St",
    "sg:city":"Jackson",
    "sg:classifiers":[
        {
            "category":"Autos & Motor Vehicles",
            "subcategory":"Auto Supplies",
            "type":"Retail Goods"
        }
    ],
    "sg:phone":"+1 770 775 7855",
    "sg:postcode":"30233",
    "sg:province":"GA",
    "sg:tags":[
        "automobile",
        "parts"
    ],
    "sg:website":"www.advanceautoparts.com",
    "wof:name":"Advance Auto Parts Inc",
    "wof:placetype":"venue"
},
  "geometry": {"coordinates":[-83.95497899999999,33.294552],"type":"Point"}
}