{
  "type": "Feature",
  "properties": {
    "iso:country":"US",
    "sg:address":"3211 Circle Oaks Dr SE",
    "sg:city":"Atlanta",
    "sg:classifiers":[
        {
            "category":"Professional",
            "type":"Services"
        }
    ],
    "sg:phone":"+1 770 433 8348",
    "sg:postcode":"30339",
    "sg:province":"GA",
    "sg:tags":[
        "establishment"
    ],
    "wof:name":"CCH",
    "wof:placetype":"venue"
},
  "geometry": {"coordinates":[-84.463309,33.86524],"type":"Point"}
}