{
  "type": "Feature",
  "properties": {
    "addr:full":"20 Bledsoe Rd Newnan GA 30265",
    "addr:housenumber":"20",
    "addr:postcode":"30265",
    "addr:street":"Bledsoe Rd",
    "iso:country":"US",
    "sg:address":"20 Bledsoe Rd",
    "sg:city":"Newnan",
    "sg:classifiers":[
        {
            "category":"Manufacturing",
            "subcategory":"Motor Vehicles & Parts",
            "type":"Manufacturing & Wholesale Goods"
        }
    ],
    "sg:phone":"+1 770 683 4674",
    "sg:postcode":"30265",
    "sg:province":"GA",
    "sg:tags":[
        "automobile",
        "supply"
    ],
    "wof:name":"Off Road Innovation",
    "wof:placetype":"venue"
},
  "geometry": {"coordinates":[-84.75296299999999,33.400237],"type":"Point"}
}