{
  "type": "Feature",
  "properties": {
    "addr:full":"1100 N Madison St Albany GA 31701",
    "addr:housenumber":"1100",
    "addr:postcode":"31701",
    "addr:street":"N Madison St",
    "iso:country":"US",
    "sg:address":"1100 N Madison St",
    "sg:city":"Albany",
    "sg:classifiers":[
        {
            "category":"Shopping",
            "type":"Retail Goods"
        }
    ],
    "sg:phone":"+1 229 446 7480",
    "sg:postcode":"31701",
    "sg:province":"GA",
    "sg:tags":[
        "merchandise"
    ],
    "wof:name":"Albany Orthotics & Prosthetics",
    "wof:placetype":"venue"
},
  "geometry": {"coordinates":[-84.162042,31.592965],"type":"Point"}
}