{
  "type": "Feature",
  "properties": {
    "iso:country":"US",
    "sg:address":"131 Fitchburg Dr",
    "sg:city":"Woodstock",
    "sg:classifiers":[
        {
            "category":"Professional",
            "subcategory":"Management & Consulting",
            "type":"Services"
        }
    ],
    "sg:phone":"+1 770 928 4300",
    "sg:postcode":"30189",
    "sg:province":"GA",
    "sg:tags":[
        "business"
    ],
    "wof:name":"Forsythe Technologies Inc",
    "wof:placetype":"venue"
},
  "geometry": {"coordinates":[-84.55128000000001,34.085161],"type":"Point"}
}