{
  "type": "Feature",
  "properties": {
    "addr:full":"3720 Longview Dr Atlanta GA 30341",
    "addr:housenumber":"3720",
    "addr:postcode":"30341",
    "addr:street":"Longview Dr",
    "iso:country":"US",
    "sg:address":"3720 Longview Dr",
    "sg:city":"Atlanta",
    "sg:classifiers":[
        {
            "category":"Real Estate",
            "subcategory":"Real Estate Services",
            "type":"Services"
        },
        {
            "category":"Communications",
            "subcategory":"Film & Video Production",
            "type":"Services"
        },
        {
            "category":"Professional",
            "subcategory":"Art Services",
            "type":"Services"
        },
        {
            "category":"Professional",
            "subcategory":"Printing & Photocopies",
            "type":"Services"
        },
        {
            "category":"Real Estate",
            "subcategory":"Real Estate Agent",
            "type":"Services"
        }
    ],
    "sg:phone":"+1 404 353 5078",
    "sg:postcode":"30341",
    "sg:province":"GA",
    "sg:tags":[
        "videography",
        "aerial",
        "exchange",
        "photographer",
        "photography",
        "photographers-commercial"
    ],
    "wof:name":"Virtual Advantages, LLC",
    "wof:placetype":"venue"
},
  "geometry": {"coordinates":[-84.302277,33.901791],"type":"Point"}
}