{
  "type": "Feature",
  "properties": {
    "iso:country":"US",
    "sg:address":"101 John St",
    "sg:city":"Sylvania",
    "sg:classifiers":[
        {
            "category":"Education",
            "subcategory":"Special Training",
            "type":"Public Place"
        }
    ],
    "sg:phone":"+1 912 564 0083",
    "sg:postcode":"30467",
    "sg:province":"GA",
    "wof:name":"Positive Action Committee",
    "wof:placetype":"venue"
},
  "geometry": {"coordinates":[-81.646593,32.760951],"type":"Point"}
}