{
  "type": "Feature",
  "properties": {
    "iso:country":"US",
    "sg:address":"10 River St",
    "sg:city":"Ellijay",
    "sg:classifiers":[
        {
            "category":"Shopping",
            "subcategory":"Jewelry",
            "type":"Retail Goods"
        }
    ],
    "sg:phone":"+1 706 635 2234",
    "sg:postcode":"30540",
    "sg:province":"GA",
    "sg:tags":[
        "jeweler"
    ],
    "wof:name":"Andy's Jewelers Inc",
    "wof:placetype":"venue"
},
  "geometry": {"coordinates":[-84.481917,34.694576],"type":"Point"}
}