{
  "type": "Feature",
  "properties": {
    "addr:full":"789 N Houston Rd Warner Robins GA 31093",
    "addr:housenumber":"789",
    "addr:postcode":"31093",
    "addr:street":"N Houston Rd",
    "iso:country":"US",
    "sg:address":"789 N Houston Rd",
    "sg:city":"Warner Robins",
    "sg:classifiers":[
        {
            "category":"Autos & Motor Vehicles",
            "subcategory":"Auto Supplies",
            "type":"Retail Goods"
        }
    ],
    "sg:phone":"+1 478 929 5445",
    "sg:postcode":"31093",
    "sg:province":"GA",
    "sg:tags":[
        "tire"
    ],
    "sg:website":"www.chevron.com",
    "wof:name":"Bob's Chevron Service",
    "wof:placetype":"venue"
},
  "geometry": {"coordinates":[-83.6418,32.630699],"type":"Point"}
}