{
  "type": "Feature",
  "properties": {
    "addr:full":"105 Madison Pl Fayetteville GA 30214",
    "addr:housenumber":"105",
    "addr:postcode":"30214",
    "addr:street":"Madison Pl",
    "iso:country":"US",
    "sg:address":"105 Madison Pl",
    "sg:city":"Fayetteville",
    "sg:classifiers":[
        {
            "category":"Retail",
            "subcategory":"Repair Shop",
            "type":"Services"
        }
    ],
    "sg:phone":"+1 770 716 9064",
    "sg:postcode":"30214",
    "sg:province":"GA",
    "sg:tags":[
        "appliance"
    ],
    "wof:name":"F D C's Appliance Repair",
    "wof:placetype":"venue"
},
  "geometry": {"coordinates":[-84.47552,33.484793],"type":"Point"}
}