{
  "type": "Feature",
  "properties": {
    "addr:full":"180 Winterberry Ridge Fairburn GA 30213",
    "addr:housenumber":"180",
    "addr:postcode":"30213",
    "addr:street":"Winterberry Ridge",
    "iso:country":"US",
    "sg:address":"180 Winterberry Ridge",
    "sg:city":"Fairburn",
    "sg:classifiers":[
        {
            "category":"Shopping",
            "subcategory":"Computers & Home Electronics",
            "type":"Retail Goods"
        }
    ],
    "sg:phone":"+1 770 293 4232",
    "sg:postcode":"30213",
    "sg:province":"GA",
    "wof:name":"Pinnacle Software Solutions",
    "wof:placetype":"venue"
},
  "geometry": {"coordinates":[-84.467742,33.530424],"type":"Point"}
}