{
  "type": "Feature",
  "properties": {
    "iso:country":"US",
    "sg:address":"2897 US Hwy 441 S",
    "sg:city":"Douglas",
    "sg:classifiers":[
        {
            "category":"Food & Beverages",
            "subcategory":"Groceries & Convenience Stores",
            "type":"Retail Goods"
        }
    ],
    "sg:phone":"+1 912 384 6325",
    "sg:postcode":"31535",
    "sg:province":"GA",
    "wof:name":"Quick Change",
    "wof:placetype":"venue"
},
  "geometry": {"coordinates":[-82.85069,31.466376],"type":"Point"}
}