{
  "type": "Feature",
  "properties": {
    "iso:country":"US",
    "sg:address":"8750 Nesbit Ferry Rd",
    "sg:city":"Alpharetta",
    "sg:classifiers":[
        {
            "category":"Retail",
            "subcategory":"Veterinary Services",
            "type":"Services"
        }
    ],
    "sg:phone":"+1 770 998 8450",
    "sg:postcode":"30022",
    "sg:province":"GA",
    "sg:tags":[
        "hospital",
        "veterinarian"
    ],
    "sg:website":"www.yourvmc.com",
    "wof:name":"Veterinary Medical Center",
    "wof:placetype":"venue"
},
  "geometry": {"coordinates":[-84.27334999999999,33.99254],"type":"Point"}
}