{
  "type": "Feature",
  "properties": {
    "iso:country":"US",
    "sg:address":"2100 Norcross Pkwy",
    "sg:city":"Norcross",
    "sg:classifiers":[
        {
            "category":"Professional",
            "subcategory":"Advertising",
            "type":"Services"
        }
    ],
    "sg:phone":"+1 770 368 1109",
    "sg:postcode":"30071",
    "sg:province":"GA",
    "sg:tags":[
        "distribution"
    ],
    "wof:name":"Microcast Technologies",
    "wof:placetype":"venue"
},
  "geometry": {"coordinates":[-84.185152,33.936298],"type":"Point"}
}