{
  "type": "Feature",
  "properties": {
    "iso:country":"US",
    "sg:address":"300 Dogwood Glen",
    "sg:city":"Centerville",
    "sg:classifiers":[
        {
            "category":"Professional",
            "subcategory":"Computer Services",
            "type":"Services"
        }
    ],
    "sg:phone":"+1 478 922 6564",
    "sg:postcode":"31028",
    "sg:province":"GA",
    "sg:tags":[
        "related"
    ],
    "wof:name":"Wicks Tucker LLC",
    "wof:placetype":"venue"
},
  "geometry": {"coordinates":[-83.66721,32.643345],"type":"Point"}
}