{
  "type": "Feature",
  "properties": {
    "iso:country":"US",
    "sg:address":"350 Town Center Ave",
    "sg:city":"Suwanee",
    "sg:classifiers":[
        {
            "category":"Restaurant",
            "type":"Food & Drink"
        }
    ],
    "sg:menulink":"http://www.allmenus.com/ga/suwanee-duluth/205766-ippolitos/menu/",
    "sg:phone":"+1 770 831 3633",
    "sg:postcode":"30024",
    "sg:province":"GA",
    "sg:tags":[
        "middle",
        "eastern"
    ],
    "wof:name":"Ippolito's",
    "wof:placetype":"venue"
},
  "geometry": {"coordinates":[-84.064363,34.05574],"type":"Point"}
}