{
  "type": "Feature",
  "properties": {
    "addr:full":"3095 Peachtree Industrial Blvd Ste 110 Duluth GA 30097",
    "addr:housenumber":"3095",
    "addr:postcode":"30097",
    "addr:street":"Peachtree Industrial Blvd Ste 110",
    "iso:country":"US",
    "sg:address":"3095 Peachtree Industrial Blvd Ste 110",
    "sg:city":"Duluth",
    "sg:classifiers":[
        {
            "category":"Personal",
            "subcategory":"Beauty Salon",
            "type":"Services"
        }
    ],
    "sg:phone":"+1 770 826 5275",
    "sg:postcode":"30097",
    "sg:province":"GA",
    "sg:tags":[
        "hair"
    ],
    "wof:name":"Kitty Lewis",
    "wof:placetype":"venue"
},
  "geometry": {"coordinates":[-84.156871,34.022691],"type":"Point"}
}