{
  "type": "Feature",
  "properties": {
    "addr:full":"3880 Martha Berry Hwy Rome GA 30165",
    "addr:housenumber":"3880",
    "addr:postcode":"ga 30165",
    "addr:street":"Martha Berry Hwy",
    "iso:country":"US",
    "sg:address":"3880 Martha Berry Hwy",
    "sg:city":"Rome",
    "sg:classifiers":[
        {
            "category":"Shopping",
            "subcategory":"Department Store",
            "type":"Retail Goods"
        }
    ],
    "sg:phone":"+1 706 235 8812",
    "sg:postcode":"30165",
    "sg:province":"GA",
    "sg:tags":[
        "shop"
    ],
    "wof:name":"Dollar General",
    "wof:placetype":"venue"
},
  "geometry": {"coordinates":[-85.172338,34.330513],"type":"Point"}
}