{
  "type": "Feature",
  "properties": {
    "iso:country":"US",
    "sg:address":"3 Dunwoody Park S",
    "sg:city":"Atlanta",
    "sg:classifiers":[
        {
            "category":"Arts & Performance",
            "subcategory":"Theater",
            "type":"Entertainment"
        }
    ],
    "sg:phone":"+1 770 394 5521",
    "sg:postcode":"30338",
    "sg:province":"GA",
    "sg:tags":[
        "on",
        "hold",
        "telephone",
        "advertising"
    ],
    "wof:name":"Accurate Communications Corp",
    "wof:placetype":"venue"
},
  "geometry": {"coordinates":[-84.311268,33.923978],"type":"Point"}
}