{
  "type": "Feature",
  "properties": {
    "addr:full":"3917 Hadley Farm Dr Marietta GA 30066",
    "addr:housenumber":"3917",
    "addr:postcode":"30066",
    "addr:street":"Hadley Farm Dr",
    "iso:country":"US",
    "sg:address":"3917 Hadley Farm Dr",
    "sg:city":"Marietta",
    "sg:classifiers":[
        {
            "category":"Professional",
            "subcategory":"Business Services",
            "type":"Services"
        }
    ],
    "sg:phone":"+1 770 591 2374",
    "sg:postcode":"30066",
    "sg:province":"GA",
    "sg:tags":[
        "event"
    ],
    "wof:name":"Bourbon Street Events",
    "wof:placetype":"venue"
},
  "geometry": {"coordinates":[-84.522887,34.046909],"type":"Point"}
}