{
  "type": "Feature",
  "properties": {
    "addr:full":"2555 Cumberland Pkwy SE Atlanta GA 30339",
    "addr:housenumber":"2555",
    "addr:postcode":"30339",
    "addr:street":"Cumberland Pkwy Se",
    "iso:country":"US",
    "sg:address":"2555 Cumberland Pkwy SE",
    "sg:city":"Atlanta",
    "sg:classifiers":[
        {
            "category":"Professional",
            "subcategory":"Business Services",
            "type":"Services"
        }
    ],
    "sg:phone":"+1 770 444 3055",
    "sg:postcode":"30339",
    "sg:province":"GA",
    "sg:tags":[
        "legal"
    ],
    "wof:name":"Intermark Language Services",
    "wof:placetype":"venue"
},
  "geometry": {"coordinates":[-84.472146,33.878217],"type":"Point"}
}