{
  "type": "Feature",
  "properties": {
    "iso:country":"US",
    "sg:address":"889 Moreland Ave SE",
    "sg:city":"Atlanta",
    "sg:classifiers":[
        {
            "category":"Professional",
            "subcategory":"Management & Consulting",
            "type":"Services"
        }
    ],
    "sg:phone":"+1 404 622 1205",
    "sg:postcode":"30316",
    "sg:province":"GA",
    "sg:tags":[
        "consultant",
        "business"
    ],
    "wof:name":"Speakman Management Consulting",
    "wof:placetype":"venue"
},
  "geometry": {"coordinates":[-84.3494,33.73177],"type":"Point"}
}