{
  "type": "Feature",
  "properties": {
    "addr:full":"6115 Wilson Rd Duluth GA 30097",
    "addr:housenumber":"6115",
    "addr:postcode":"30097",
    "addr:street":"Wilson Rd",
    "iso:country":"US",
    "sg:address":"6115 Wilson Rd",
    "sg:city":"Duluth",
    "sg:classifiers":[
        {
            "category":"Education",
            "subcategory":"School",
            "type":"Public Place"
        }
    ],
    "sg:phone":"+1 770 497 3811",
    "sg:postcode":"30097",
    "sg:province":"GA",
    "sg:tags":[
        "high",
        "middle",
        "elementary"
    ],
    "wof:name":"Wilson Creek Elementary School",
    "wof:placetype":"venue"
},
  "geometry": {"coordinates":[-84.183896,34.033204],"type":"Point"}
}