{
  "type": "Feature",
  "properties": {
    "iso:country":"US",
    "sg:address":"2 Main St",
    "sg:city":"Woodland",
    "sg:classifiers":[
        {
            "category":"Shopping",
            "subcategory":"Hobbies, Toys, & Games",
            "type":"Retail Goods"
        }
    ],
    "sg:phone":"+1 706 674 2229",
    "sg:postcode":"31815",
    "sg:province":"GA",
    "sg:tags":[
        "supply"
    ],
    "wof:name":"Games & Things",
    "wof:placetype":"venue"
},
  "geometry": {"coordinates":[-84.79883100000001,32.050129],"type":"Point"}
}