{
  "type": "Feature",
  "properties": {
    "addr:full":"4851 Trevino Cir Duluth GA 30096",
    "addr:housenumber":"4851",
    "addr:postcode":"30096",
    "addr:street":"Trevino Cir",
    "iso:country":"US",
    "sg:address":"4851 Trevino Cir",
    "sg:city":"Duluth",
    "sg:classifiers":[
        {
            "category":"Professional",
            "subcategory":"Lawyer & Legal Services",
            "type":"Services"
        }
    ],
    "sg:phone":"+1 770 300 9919",
    "sg:postcode":"30096",
    "sg:province":"GA",
    "wof:name":"Michael C Obertone Esquire PC",
    "wof:placetype":"venue"
},
  "geometry": {"coordinates":[-84.178805,33.953771],"type":"Point"}
}