{
  "type": "Feature",
  "properties": {
    "addr:full":"2491 Hilton Dr Gainesville GA 30501",
    "addr:housenumber":"2491",
    "addr:postcode":"30501",
    "addr:street":"Hilton Dr",
    "iso:country":"US",
    "sg:address":"2491 Hilton Dr",
    "sg:city":"Gainesville",
    "sg:classifiers":[
        {
            "category":"Building & Trades",
            "subcategory":"Construction",
            "type":"Services"
        }
    ],
    "sg:phone":"+1 678 450 5600",
    "sg:postcode":"30501",
    "sg:province":"GA",
    "sg:tags":[
        "roofing",
        "industrial",
        "contractors-commercial",
        "contractor"
    ],
    "wof:name":"Hayse Roofing",
    "wof:placetype":"venue"
},
  "geometry": {"coordinates":[-83.842857,34.27631],"type":"Point"}
}