{
  "type": "Feature",
  "properties": {
    "iso:country":"US",
    "sg:address":"298 Millbrook Farm Rd",
    "sg:city":"Marietta",
    "sg:classifiers":[
        {
            "category":"Building & Trades",
            "subcategory":"Construction",
            "type":"Services"
        }
    ],
    "sg:phone":"+1 678 560 9741",
    "sg:postcode":"30068",
    "sg:province":"GA",
    "sg:tags":[
        "nonresidential"
    ],
    "wof:name":"Noyes Co Inc",
    "wof:placetype":"venue"
},
  "geometry": {"coordinates":[-84.469308,33.945762],"type":"Point"}
}