{
  "type": "Feature",
  "properties": {
    "addr:full":"3490 Piedmont Road NE Atlanta GA 30305",
    "addr:housenumber":"3490",
    "addr:postcode":"30305",
    "addr:street":"Piedmont Road Ne",
    "iso:country":"US",
    "sg:address":"3490 Piedmont Road NE",
    "sg:city":"Atlanta",
    "sg:classifiers":[
        {
            "category":"Professional",
            "subcategory":"Lawyer & Legal Services",
            "type":"Services"
        },
        {
            "category":"Health Services",
            "subcategory":"Dentist",
            "type":"Services"
        }
    ],
    "sg:phone":"+1 404 237 5700",
    "sg:postcode":"30305",
    "sg:province":"GA",
    "wof:name":"Levine Jonathan R Attrny",
    "wof:placetype":"venue"
},
  "geometry": {"coordinates":[-84.37491,33.84875],"type":"Point"}
}