{
  "type": "Feature",
  "properties": {
    "addr:full":"125 Heritage Farm Ln Fayetteville GA 30215",
    "addr:housenumber":"125",
    "addr:postcode":"30215",
    "addr:street":"Heritage Farm Ln",
    "iso:country":"US",
    "sg:address":"125 Heritage Farm Ln",
    "sg:city":"Fayetteville",
    "sg:classifiers":[
        {
            "category":"Shopping",
            "subcategory":"Jewelry",
            "type":"Retail Goods"
        }
    ],
    "sg:phone":"+1 770 460 6876",
    "sg:postcode":"30215",
    "sg:province":"GA",
    "wof:name":"Patricia Gilmore Jewelry Desig",
    "wof:placetype":"venue"
},
  "geometry": {"coordinates":[-84.52037900000001,33.444132],"type":"Point"}
}