{
  "type": "Feature",
  "properties": {
    "addr:full":"1914 Knight Rd Ellijay GA 30540",
    "addr:housenumber":"1914",
    "addr:postcode":"30540",
    "addr:street":"Knight Rd",
    "iso:country":"US",
    "sg:address":"1914 Knight Rd",
    "sg:city":"Ellijay",
    "sg:classifiers":[
        {
            "category":"Building & Trades",
            "subcategory":"Electrical",
            "type":"Services"
        }
    ],
    "sg:phone":"+1 706 635 2405",
    "sg:postcode":"30540",
    "sg:province":"GA",
    "sg:tags":[
        "electrical",
        "contractor"
    ],
    "wof:name":"John Becker Co",
    "wof:placetype":"venue"
},
  "geometry": {"coordinates":[-84.559085,34.632309],"type":"Point"}
}