{
  "type": "Feature",
  "properties": {
    "iso:country":"US",
    "sg:address":"7788 Georgetown Chase",
    "sg:city":"Roswell",
    "sg:classifiers":[
        {
            "category":"Professional",
            "type":"Services"
        }
    ],
    "sg:phone":"+1 678 352 8867",
    "sg:postcode":"30075",
    "sg:province":"GA",
    "sg:tags":[
        "consulting",
        "business"
    ],
    "wof:name":"Heather J Paper Consultant",
    "wof:placetype":"venue"
},
  "geometry": {"coordinates":[-84.366933,34.022072],"type":"Point"}
}