{
  "type": "Feature",
  "properties": {
    "addr:full":"218 Ward St W Douglas GA 31533",
    "addr:housenumber":"218",
    "addr:postcode":"31533",
    "addr:street":"Ward St W",
    "iso:country":"US",
    "sg:address":"218 Ward St W",
    "sg:city":"Douglas",
    "sg:classifiers":[
        {
            "category":"Restaurant",
            "type":"Food & Drink"
        }
    ],
    "sg:phone":"+1 912 384 2270",
    "sg:postcode":"31533",
    "sg:province":"GA",
    "sg:tags":[
        "pizza"
    ],
    "wof:name":"Danny's Pizza",
    "wof:placetype":"venue"
},
  "geometry": {"coordinates":[-82.851533,31.508933],"type":"Point"}
}