{
  "type": "Feature",
  "properties": {
    "iso:country":"US",
    "sg:address":"981 N Burnt Hickory Rd",
    "sg:city":"Douglasville",
    "sg:classifiers":[
        {
            "category":"Professional",
            "subcategory":"Research",
            "type":"Services"
        }
    ],
    "sg:phone":"+1 770 942 9876",
    "sg:postcode":"30134",
    "sg:province":"GA",
    "sg:tags":[
        "analysis",
        "market"
    ],
    "wof:name":"Omega Research & Development",
    "wof:placetype":"venue"
},
  "geometry": {"coordinates":[-84.706045,33.777427],"type":"Point"}
}