{
  "type": "Feature",
  "properties": {
    "addr:full":"496 Reed Rd NW Dalton GA 30720",
    "addr:housenumber":"496",
    "addr:postcode":"30720",
    "addr:street":"Reed Rd Nw",
    "iso:country":"US",
    "sg:address":"496 Reed Rd NW",
    "sg:city":"Dalton",
    "sg:classifiers":[
        {
            "category":"Personal",
            "subcategory":"Barber",
            "type":"Services"
        }
    ],
    "sg:phone":"+1 706 275 8731",
    "sg:postcode":"30720",
    "sg:province":"GA",
    "sg:tags":[
        "shop"
    ],
    "wof:name":"Charlotte's Barber Shop",
    "wof:placetype":"venue"
},
  "geometry": {"coordinates":[-84.972852,34.798028],"type":"Point"}
}