{
  "type": "Feature",
  "properties": {
    "addr:full":"3874 Starling Rd Pembroke GA 31321",
    "addr:housenumber":"3874",
    "addr:postcode":"31321",
    "addr:street":"Starling Rd",
    "iso:country":"US",
    "sg:address":"3874 Starling Rd",
    "sg:city":"Pembroke",
    "sg:classifiers":[
        {
            "category":"Professional",
            "type":"Services"
        }
    ],
    "sg:phone":"+1 912 653 5430",
    "sg:postcode":"31321",
    "sg:province":"GA",
    "wof:name":"Ralph C Miller",
    "wof:placetype":"venue"
},
  "geometry": {"coordinates":[-81.652405,32.224669],"type":"Point"}
}