{
  "type": "Feature",
  "properties": {
    "addr:full":"5713 Hammond Dr NW Norcross GA 30071",
    "addr:housenumber":"5713",
    "addr:postcode":"30071",
    "addr:street":"Hammond Dr Nw",
    "iso:country":"US",
    "sg:address":"5713 Hammond Dr NW",
    "sg:city":"Norcross",
    "sg:classifiers":[
        {
            "category":"Retail",
            "subcategory":"Auto Repair",
            "type":"Services"
        }
    ],
    "sg:phone":"+1 770 662 5075",
    "sg:postcode":"30071",
    "sg:province":"GA",
    "sg:tags":[
        "sales",
        "minor"
    ],
    "wof:name":"Rockys Automotive",
    "wof:placetype":"venue"
},
  "geometry": {"coordinates":[-84.19986900000001,33.924612],"type":"Point"}
}