{
  "type": "Feature",
  "properties": {
    "iso:country":"US",
    "sg:address":"4297 Palm Springs Dr",
    "sg:city":"Atlanta",
    "sg:classifiers":[
        {
            "category":"Shopping",
            "subcategory":"Clothing, Apparel, & Fashions",
            "type":"Retail Goods"
        }
    ],
    "sg:phone":"+1 404 761 2371",
    "sg:postcode":"30344",
    "sg:province":"GA",
    "wof:name":"You Got Style By V",
    "wof:placetype":"venue"
},
  "geometry": {"coordinates":[-84.488046,33.640636],"type":"Point"}
}