{
  "type": "Feature",
  "properties": {
    "addr:full":"2654 White Sulphur Rd Gainesville GA 30501",
    "addr:housenumber":"2654",
    "addr:postcode":"30501",
    "addr:street":"White Sulphur Rd",
    "iso:country":"US",
    "sg:address":"2654 White Sulphur Rd",
    "sg:city":"Gainesville",
    "sg:classifiers":[
        {
            "category":"Professional",
            "subcategory":"Business Services",
            "type":"Services"
        }
    ],
    "sg:phone":"+1 770 538 4884",
    "sg:postcode":"30501",
    "sg:province":"GA",
    "sg:tags":[
        "packaging"
    ],
    "wof:name":"Concept Packaging Concept",
    "wof:placetype":"venue"
},
  "geometry": {"coordinates":[-83.778722,34.343577],"type":"Point"}
}