{
  "type": "Feature",
  "properties": {
    "addr:full":"3750 Satellite Blvd Duluth GA 30096",
    "addr:housenumber":"3750",
    "addr:postcode":"30096",
    "addr:street":"Satellite Blvd",
    "iso:country":"US",
    "sg:address":"3750 Satellite Blvd",
    "sg:city":"Duluth",
    "sg:classifiers":[
        {
            "category":"Travel",
            "subcategory":"Hotels & Motels",
            "type":"Entertainment"
        },
        {
            "category":"Real Estate",
            "subcategory":"Real Estate Operator",
            "type":"Services"
        }
    ],
    "sg:phone":"+1 770 622 9700",
    "sg:postcode":"30096",
    "sg:province":"GA",
    "sg:tags":[
        "building",
        "apartment"
    ],
    "wof:name":"Intown Suites Gwinnett Place",
    "wof:placetype":"venue"
},
  "geometry": {"coordinates":[-84.138603,33.957001],"type":"Point"}
}