{
  "type": "Feature",
  "properties": {
    "iso:country":"US",
    "sg:address":"1530 Old Alabama Rd",
    "sg:city":"Roswell",
    "sg:classifiers":[
        {
            "category":"Coffee & Tea",
            "type":"Food & Drink"
        }
    ],
    "sg:menulink":"http://www.allmenus.com/ga/roswell-alpharetta/108019-starbucks-coffee/menu/",
    "sg:phone":"+1 770 518 0118",
    "sg:postcode":"30076",
    "sg:province":"GA",
    "sg:tags":[
        "american"
    ],
    "wof:name":"Starbucks Coffee",
    "wof:placetype":"venue"
},
  "geometry": {"coordinates":[-84.31756300000001,34.020866],"type":"Point"}
}