{
  "type": "Feature",
  "properties": {
    "iso:country":"US",
    "sg:address":"1060 Hillcrest Dr",
    "sg:city":"Watkinsville",
    "sg:classifiers":[
        {
            "category":"Building & Trades",
            "subcategory":"Construction",
            "type":"Services"
        }
    ],
    "sg:phone":"+1 706 769 7916",
    "sg:postcode":"30677",
    "sg:province":"GA",
    "sg:tags":[
        "hanging",
        "contractor"
    ],
    "wof:name":"Loggins JD Painting",
    "wof:placetype":"venue"
},
  "geometry": {"coordinates":[-83.44146600000001,33.862141],"type":"Point"}
}