{
  "type": "Feature",
  "properties": {
    "addr:full":"4739 Kings Down Rd Atlanta GA 30338",
    "addr:housenumber":"4739",
    "addr:postcode":"30338",
    "addr:street":"Kings Down Rd",
    "iso:country":"US",
    "sg:address":"4739 Kings Down Rd",
    "sg:city":"Atlanta",
    "sg:classifiers":[
        {
            "category":"Banks & Credit Unions",
            "subcategory":"Financial Services",
            "type":"Services"
        }
    ],
    "sg:phone":"+1 770 392 0366",
    "sg:postcode":"30338",
    "sg:province":"GA",
    "sg:tags":[
        "investor"
    ],
    "wof:name":"Dax Investments LP",
    "wof:placetype":"venue"
},
  "geometry": {"coordinates":[-84.327877,33.935279],"type":"Point"}
}