{
  "type": "Feature",
  "properties": {
    "addr:full":"113 Corporate Park E Lagrange GA 30241",
    "addr:housenumber":"113",
    "addr:postcode":"30241",
    "addr:street":"Corporate Park E",
    "iso:country":"US",
    "sg:address":"113 Corporate Park E",
    "sg:city":"Lagrange",
    "sg:classifiers":[
        {
            "category":"Building & Trades",
            "subcategory":"Cleaning & Sanitation",
            "type":"Services"
        }
    ],
    "sg:phone":"+1 706 882 8581",
    "sg:postcode":"30241",
    "sg:province":"GA",
    "sg:tags":[
        "janitor"
    ],
    "sg:website":"www.teamnational.com",
    "wof:name":"LA Grange Building Svc",
    "wof:placetype":"venue"
},
  "geometry": {"coordinates":[-84.981155,33.033234],"type":"Point"}
}