{
  "type": "Feature",
  "properties": {
    "addr:full":"3965 Gloucester Dr Tucker GA 30084",
    "addr:housenumber":"3965",
    "addr:postcode":"30084",
    "addr:street":"Gloucester Dr",
    "iso:country":"US",
    "sg:address":"3965 Gloucester Dr",
    "sg:city":"Tucker",
    "sg:classifiers":[
        {
            "category":"Manufacturing",
            "subcategory":"Buildings",
            "type":"Manufacturing & Wholesale Goods"
        },
        {
            "category":"Social Services",
            "subcategory":"Retirement Home",
            "type":"Services"
        },
        {
            "category":"Building & Trades",
            "subcategory":"Construction",
            "type":"Services"
        }
    ],
    "sg:phone":"+1 404 294 0203",
    "sg:postcode":"30084",
    "sg:province":"GA",
    "sg:tags":[
        "living",
        "nursing",
        "facility",
        "assisted",
        "contractor",
        "convalescent",
        "builder"
    ],
    "wof:name":"Avondale Homes of Northlake",
    "wof:placetype":"venue"
},
  "geometry": {"coordinates":[-84.231847,33.836711],"type":"Point"}
}