{
  "type": "Feature",
  "properties": {
    "iso:country":"US",
    "sg:address":"440 Ernest W Barrett Pkwy NW",
    "sg:city":"Kennesaw",
    "sg:classifiers":[
        {
            "category":"Health Services",
            "subcategory":"Dentist",
            "type":"Services"
        }
    ],
    "sg:phone":"+1 770 427 6000",
    "sg:postcode":"30144",
    "sg:province":"GA",
    "sg:tags":[
        "dental",
        "clinic",
        "dentists-orthodontists"
    ],
    "sg:website":"http://www.dentfirst.com",
    "wof:name":"Dent1st Dental Care",
    "wof:placetype":"venue"
},
  "geometry": {"coordinates":[-84.56411,34.012138],"type":"Point"}
}