{
  "type": "Feature",
  "properties": {
    "addr:full":"221 Circle Valley Dr SE Calhoun GA 30701",
    "addr:housenumber":"221",
    "addr:postcode":"30701",
    "addr:street":"Circle Valley Dr Se",
    "iso:country":"US",
    "sg:address":"221 Circle Valley Dr SE",
    "sg:city":"Calhoun",
    "sg:classifiers":[
        {
            "category":"Professional",
            "type":"Services"
        }
    ],
    "sg:phone":"+1 706 625 1186",
    "sg:postcode":"30701",
    "sg:province":"GA",
    "wof:name":"Kevin D King",
    "wof:placetype":"venue"
},
  "geometry": {"coordinates":[-84.873271,34.490317],"type":"Point"}
}