{
  "type": "Feature",
  "properties": {
    "addr:full":"1270 McConnell Dr Ste B Decatur GA 30033",
    "addr:housenumber":"1270",
    "addr:postcode":"30033",
    "addr:street":"Mcconnell Dr Ste B",
    "iso:country":"US",
    "sg:address":"1270 McConnell Dr Ste B",
    "sg:city":"Decatur",
    "sg:classifiers":[
        {
            "category":"Health Services",
            "subcategory":"Dentist",
            "type":"Services"
        }
    ],
    "sg:phone":"+1 404 636 2501",
    "sg:postcode":"30033",
    "sg:province":"GA",
    "sg:tags":[
        "dentists-pediatric",
        "pediatric",
        "dentistry"
    ],
    "wof:name":"Davis Walter Ray Jr DDS MSD PC",
    "wof:placetype":"venue"
},
  "geometry": {"coordinates":[-84.308403,33.809601],"type":"Point"}
}