{
  "type": "Feature",
  "properties": {
    "addr:full":"6612 Tara Blvd Jonesboro GA 30236",
    "addr:housenumber":"6612",
    "addr:postcode":"30236",
    "addr:street":"Tara Blvd",
    "iso:country":"US",
    "sg:address":"6612 Tara Blvd",
    "sg:city":"Jonesboro",
    "sg:classifiers":[
        {
            "category":"Banks & Credit Unions",
            "subcategory":"Bank",
            "type":"Services"
        }
    ],
    "sg:phone":"+1 770 960 1029",
    "sg:postcode":"30236",
    "sg:province":"GA",
    "wof:name":"El Banco De Nuestra",
    "wof:placetype":"venue"
},
  "geometry": {"coordinates":[-84.371494,33.574406],"type":"Point"}
}