{
  "type": "Feature",
  "properties": {
    "iso:country":"US",
    "sg:address":"405 Old Albany Rd",
    "sg:city":"Moultrie",
    "sg:classifiers":[
        {
            "category":"Structure",
            "subcategory":"Office Building",
            "type":"Public Place"
        }
    ],
    "sg:phone":"+1 229 891 4212",
    "sg:postcode":"31768",
    "sg:province":"GA",
    "sg:tags":[
        "park"
    ],
    "sg:website":"http://www.winn-dixie.com",
    "wof:name":"Woodland Apartments",
    "wof:placetype":"venue"
},
  "geometry": {"coordinates":[-83.827011,31.234013],"type":"Point"}
}