{
  "type": "Feature",
  "properties": {
    "addr:full":"950 E Paces Ferry Rd NE Atlanta GA 30326",
    "addr:housenumber":"950",
    "addr:postcode":"30326",
    "addr:street":"E Paces Ferry Rd Ne",
    "iso:country":"US",
    "sg:address":"950 E Paces Ferry Rd NE",
    "sg:city":"Atlanta",
    "sg:classifiers":[
        {
            "category":"Banks & Credit Unions",
            "subcategory":"Investment Brokerage",
            "type":"Services"
        },
        {
            "category":"Banks & Credit Unions",
            "subcategory":"Bank",
            "type":"Services"
        }
    ],
    "sg:phone":"+1 404 237 2210",
    "sg:postcode":"30326",
    "sg:province":"GA",
    "sg:tags":[
        "transfer",
        "bond",
        "broker",
        "agent",
        "stock"
    ],
    "wof:name":"Katz Sidney I /Invstmts",
    "wof:placetype":"venue"
},
  "geometry": {"coordinates":[-84.35713199999999,33.846291],"type":"Point"}
}