{
  "type": "Feature",
  "properties": {
    "iso:country":"US",
    "sg:address":"3500 Peachtree Road NE",
    "sg:city":"Atlanta",
    "sg:classifiers":[
        {
            "category":"Shopping",
            "subcategory":"Jewelry",
            "type":"Retail Goods"
        }
    ],
    "sg:phone":"+1 404 869 7220",
    "sg:postcode":"30326",
    "sg:province":"GA",
    "wof:name":"Moffatts Fine Estate Jewelers",
    "wof:placetype":"venue"
},
  "geometry": {"coordinates":[-84.35895600000001,33.853867],"type":"Point"}
}