{
  "type": "Feature",
  "properties": {
    "addr:full":"340 Walmart Way Dahlonega GA 30533",
    "addr:housenumber":"340",
    "addr:postcode":"30533",
    "addr:street":"Walmart Way",
    "iso:country":"US",
    "sg:address":"340 Walmart Way",
    "sg:city":"Dahlonega",
    "sg:classifiers":[
        {
            "category":"Sports & Exercise",
            "subcategory":"Gym",
            "type":"Entertainment"
        }
    ],
    "sg:phone":"+1 706 864 2397",
    "sg:postcode":"30533",
    "sg:province":"GA",
    "sg:tags":[
        "facility",
        "club",
        "gymnasium",
        "health",
        "fitness",
        "studio",
        "physical"
    ],
    "wof:name":"Curves For Women",
    "wof:placetype":"venue"
},
  "geometry": {"coordinates":[-83.971862,34.539049],"type":"Point"}
}