{
  "type": "Feature",
  "properties": {
    "iso:country":"US",
    "sg:address":"489 Bishop St NW",
    "sg:city":"Atlanta",
    "sg:classifiers":[
        {
            "category":"Shopping",
            "type":"Retail Goods"
        }
    ],
    "sg:phone":"+1 404 881 1262",
    "sg:postcode":"30318",
    "sg:province":"GA",
    "sg:tags":[
        "material",
        "merchandise"
    ],
    "wof:name":"Christopher Condon Stoneworks",
    "wof:placetype":"venue"
},
  "geometry": {"coordinates":[-84.406637,33.791746],"type":"Point"}
}