{
  "type": "Feature",
  "properties": {
    "addr:full":"4703 Ecton Dr Marietta GA 30066",
    "addr:housenumber":"4703",
    "addr:postcode":"30066",
    "addr:street":"Ecton Dr",
    "iso:country":"US",
    "sg:address":"4703 Ecton Dr",
    "sg:city":"Marietta",
    "sg:classifiers":[
        {
            "category":"Manufacturing",
            "subcategory":"Tools & Machinery",
            "type":"Manufacturing & Wholesale Goods"
        }
    ],
    "sg:phone":"+1 770 928 7690",
    "sg:postcode":"30066",
    "sg:province":"GA",
    "sg:tags":[
        "control",
        "mfg",
        "panel",
        "system",
        "specialty"
    ],
    "sg:website":"www.controlautomation.com",
    "wof:name":"Control Automation Inc",
    "wof:placetype":"venue"
},
  "geometry": {"coordinates":[-84.523258,34.065424],"type":"Point"}
}