{
  "type": "Feature",
  "properties": {
    "iso:country":"US",
    "sg:address":"920 Burning Bush Dr",
    "sg:city":"Loganville",
    "sg:classifiers":[
        {
            "category":"Professional",
            "type":"Services"
        }
    ],
    "sg:phone":"+1 770 982 4783",
    "sg:postcode":"30052",
    "sg:province":"GA",
    "sg:tags":[
        "establishment"
    ],
    "wof:name":"At&T Cits",
    "wof:placetype":"venue"
},
  "geometry": {"coordinates":[-83.95660700000001,33.840313],"type":"Point"}
}