{
  "type": "Feature",
  "properties": {
    "iso:country":"US",
    "sg:address":"500 Memorial Dr",
    "sg:city":"Waycross",
    "sg:classifiers":[
        {
            "category":"Food & Beverages",
            "subcategory":"Groceries & Convenience Stores",
            "type":"Retail Goods"
        }
    ],
    "sg:phone":"+1 912 283 2898",
    "sg:postcode":"31501",
    "sg:province":"GA",
    "sg:tags":[
        "station",
        "gas"
    ],
    "wof:name":"Shell",
    "wof:placetype":"venue"
},
  "geometry": {"coordinates":[-82.353951,31.211339],"type":"Point"}
}