{
  "type": "Feature",
  "properties": {
    "iso:country":"US",
    "sg:address":"3910 Sunlight Trl",
    "sg:city":"Cumming",
    "sg:classifiers":[
        {
            "category":"Professional",
            "type":"Services"
        }
    ],
    "sg:phone":"+1 770 844 2043",
    "sg:postcode":"30041",
    "sg:province":"GA",
    "wof:name":"Corey D Chapman",
    "wof:placetype":"venue"
},
  "geometry": {"coordinates":[-84.06832799999999,34.251731],"type":"Point"}
}