{
  "type": "Feature",
  "properties": {
    "addr:full":"807 Bolton Pl NW Atlanta GA 30331",
    "addr:housenumber":"807",
    "addr:postcode":"30331",
    "addr:street":"Bolton Pl Nw",
    "iso:country":"US",
    "sg:address":"807 Bolton Pl NW",
    "sg:city":"Atlanta",
    "sg:classifiers":[
        {
            "category":"Restaurant",
            "type":"Food & Drink"
        }
    ],
    "sg:phone":"+1 404 696 0700",
    "sg:postcode":"30331",
    "sg:province":"GA",
    "wof:name":"Leola's Inc",
    "wof:placetype":"venue"
},
  "geometry": {"coordinates":[-84.500912,33.779342],"type":"Point"}
}