{
  "type": "Feature",
  "properties": {
    "addr:full":"4199 Paces Ferry Rd SE Ste B Atlanta GA 30339",
    "addr:housenumber":"4199",
    "addr:postcode":"30339",
    "addr:street":"Paces Ferry Rd Se Ste B",
    "iso:country":"US",
    "sg:address":"4199 Paces Ferry Rd SE Ste B",
    "sg:city":"Atlanta",
    "sg:classifiers":[
        {
            "category":"Building & Trades",
            "subcategory":"Locksmith",
            "type":"Services"
        }
    ],
    "sg:phone":"+1 866 270 1880",
    "sg:postcode":"30339",
    "sg:province":"GA",
    "sg:tags":[
        "key"
    ],
    "wof:name":"A 1 Lock & Locksmith",
    "wof:placetype":"venue"
},
  "geometry": {"coordinates":[-84.458409,33.860579],"type":"Point"}
}