{
  "type": "Feature",
  "properties": {
    "addr:full":"223 Carl Vinson Pkwy Warner Robins GA 31088",
    "addr:housenumber":"223",
    "addr:postcode":"31088",
    "addr:street":"Carl Vinson Pkwy",
    "iso:country":"US",
    "sg:address":"223 Carl Vinson Pkwy",
    "sg:city":"Warner Robins",
    "sg:classifiers":[
        {
            "category":"Health Services",
            "subcategory":"Doctor",
            "type":"Services"
        }
    ],
    "sg:phone":"+1 478 923 3999",
    "sg:postcode":"31088",
    "sg:province":"GA",
    "sg:tags":[
        "dentist"
    ],
    "wof:name":"Strawn & Hall",
    "wof:placetype":"venue"
},
  "geometry": {"coordinates":[-83.66521,32.597701],"type":"Point"}
}