{
  "type": "Feature",
  "properties": {
    "addr:full":"807 Fair St SW Atlanta GA 30314",
    "addr:housenumber":"807",
    "addr:postcode":"30314",
    "addr:street":"Fair St Sw",
    "iso:country":"US",
    "sg:address":"807 Fair St SW",
    "sg:city":"Atlanta",
    "sg:classifiers":[
        {
            "category":"Place Of Worship",
            "subcategory":"Church",
            "type":"Public Place"
        },
        {
            "category":"Place Of Worship",
            "type":"Public Place"
        }
    ],
    "sg:phone":"+1 404 523 0242",
    "sg:postcode":"30314",
    "sg:province":"GA",
    "sg:tags":[
        "lutheran",
        "america",
        "churches-lutheran",
        "churches-lutheran-evangelical"
    ],
    "wof:name":"Atlanta University Center Lutheran Campus Ministry",
    "wof:placetype":"venue"
},
  "geometry": {"coordinates":[-84.41455499999999,33.749276],"type":"Point"}
}