{
  "type": "Feature",
  "properties": {
    "addr:full":"2257 Heath Rd Macon GA 31206",
    "addr:housenumber":"2257",
    "addr:postcode":"31206",
    "addr:street":"Heath Rd",
    "iso:country":"US",
    "sg:address":"2257 Heath Rd",
    "sg:city":"Macon",
    "sg:classifiers":[
        {
            "category":"Insurance",
            "subcategory":"Hazard Insurance",
            "type":"Services"
        }
    ],
    "sg:phone":"+1 478 477 7899",
    "sg:postcode":"31206",
    "sg:province":"GA",
    "sg:tags":[
        "carrier"
    ],
    "wof:name":"MetLife",
    "wof:placetype":"venue"
},
  "geometry": {"coordinates":[-83.74530799999999,32.832783],"type":"Point"}
}