{
  "type": "Feature",
  "properties": {
    "iso:country":"US",
    "sg:address":"511 Baytree Rd",
    "sg:city":"Valdosta",
    "sg:classifiers":[
        {
            "category":"Organizations",
            "subcategory":"Religious Organization",
            "type":"Services"
        }
    ],
    "sg:phone":"+1 229 244 1813",
    "sg:postcode":"31602",
    "sg:province":"GA",
    "wof:name":"Temple Israel",
    "wof:placetype":"venue"
},
  "geometry": {"coordinates":[-83.295903,30.846731],"type":"Point"}
}