{
  "type": "Feature",
  "properties": {
    "addr:full":"4571 Cox Rd Evans GA 30809",
    "addr:housenumber":"4571",
    "addr:postcode":"30809",
    "addr:street":"Cox Rd",
    "iso:country":"US",
    "sg:address":"4571 Cox Rd",
    "sg:city":"Evans",
    "sg:classifiers":[
        {
            "category":"Organizations",
            "subcategory":"Religious Organization",
            "type":"Services"
        }
    ],
    "sg:phone":"+1 706 650 9187",
    "sg:postcode":"30809",
    "sg:province":"GA",
    "sg:tags":[
        "church"
    ],
    "wof:name":"Mosaic United Methodist Church",
    "wof:placetype":"venue"
},
  "geometry": {"coordinates":[-82.146311,33.525169],"type":"Point"}
}