{
  "type": "Feature",
  "properties": {
    "addr:full":"1450 Ponce De Leon Avenue NE Atlanta GA 30307",
    "addr:housenumber":"1450",
    "addr:postcode":"30307",
    "addr:street":"Ponce De Leon Avenue Ne",
    "iso:country":"US",
    "sg:address":"1450 Ponce De Leon Avenue NE",
    "sg:city":"Atlanta",
    "sg:classifiers":[
        {
            "category":"Organizations",
            "subcategory":"Religious Organization",
            "type":"Services"
        }
    ],
    "sg:phone":"+1 404 373 2663",
    "sg:postcode":"30307",
    "sg:province":"GA",
    "wof:name":"Church of Jesus Christ of Latter-Day Saints",
    "wof:placetype":"venue"
},
  "geometry": {"coordinates":[-84.33872599999999,33.773913],"type":"Point"}
}