{
  "type": "Feature",
  "properties": {
    "addr:full":"209 Turner McCall Blvd Rome GA 30165",
    "addr:housenumber":"209",
    "addr:postcode":"ga 30165",
    "addr:street":"Turner Mccall Blvd",
    "iso:country":"US",
    "sg:address":"209 Turner McCall Blvd",
    "sg:city":"Rome",
    "sg:classifiers":[
        {
            "category":"Utilities",
            "subcategory":"Mobile Phone",
            "type":"Services"
        }
    ],
    "sg:phone":"+1 706 234 6400",
    "sg:postcode":"30165",
    "sg:province":"GA",
    "sg:tags":[
        "telephone",
        "cellular"
    ],
    "wof:name":"Nexcom",
    "wof:placetype":"venue"
},
  "geometry": {"coordinates":[-85.18073,34.260486],"type":"Point"}
}