{
  "type": "Feature",
  "properties": {
    "addr:full":"1015 Curtis Pkwy SE Calhoun GA 30701",
    "addr:housenumber":"1015",
    "addr:postcode":"30701",
    "addr:street":"Curtis Pkwy Se",
    "iso:country":"US",
    "sg:address":"1015 Curtis Pkwy SE",
    "sg:city":"Calhoun",
    "sg:classifiers":[
        {
            "category":"Retail",
            "subcategory":"Portrait Studio",
            "type":"Services"
        }
    ],
    "sg:phone":"+1 706 629 6600",
    "sg:postcode":"30701",
    "sg:province":"GA",
    "sg:tags":[
        "photographer",
        "photo"
    ],
    "wof:name":"In Focus Studio",
    "wof:placetype":"venue"
},
  "geometry": {"coordinates":[-84.9217,34.489348],"type":"Point"}
}