{
  "type": "Feature",
  "properties": {
    "iso:country":"US",
    "sg:address":"165 Nash St",
    "sg:city":"Lawrenceville",
    "sg:classifiers":[
        {
            "category":"Banks & Credit Unions",
            "subcategory":"Bank",
            "type":"Services"
        }
    ],
    "sg:phone":"+1 770 995 5206",
    "sg:postcode":"30046",
    "sg:province":"GA",
    "wof:name":"Fifth Third Bank Bank",
    "wof:placetype":"venue"
},
  "geometry": {"coordinates":[-83.990576,33.95004],"type":"Point"}
}