{
  "type": "Feature",
  "properties": {
    "iso:country":"US",
    "sg:address":"5102 Paulsen St",
    "sg:city":"Savannah",
    "sg:classifiers":[
        {
            "category":"Health Services",
            "subcategory":"Doctor",
            "type":"Services"
        }
    ],
    "sg:phone":"+1 912 353 8699",
    "sg:postcode":"31405",
    "sg:province":"GA",
    "sg:tags":[
        "physician",
        "surgeon"
    ],
    "wof:name":"Pediatrics",
    "wof:placetype":"venue"
},
  "geometry": {"coordinates":[-81.09653,32.028846],"type":"Point"}
}