{
  "type": "Feature",
  "properties": {
    "iso:country":"US",
    "sg:address":"5700 Pechtre Indstrl Blvd",
    "sg:city":"Atlanta",
    "sg:classifiers":[
        {
            "category":"Retail",
            "subcategory":"Auto Repair",
            "type":"Services"
        }
    ],
    "sg:phone":"+1 770 452 6090",
    "sg:postcode":"30341",
    "sg:province":"GA",
    "sg:tags":[
        "body",
        "shop"
    ],
    "wof:name":"Ed Voyles Acura",
    "wof:placetype":"venue"
},
  "geometry": {"coordinates":[-84.296097,33.9039],"type":"Point"}
}