{
  "type": "Feature",
  "properties": {
    "addr:full":"6075 Roswell Rd NE Atlanta GA 30328",
    "addr:housenumber":"6075;rd",
    "addr:postcode":"30328",
    "addr:street":"Roswell;Ne",
    "iso:country":"US",
    "sg:address":"6075 Roswell Rd NE",
    "sg:city":"Atlanta",
    "sg:classifiers":[
        {
            "category":"Shopping",
            "subcategory":"Clothing, Apparel, & Fashions",
            "type":"Retail Goods"
        },
        {
            "category":"Shopping",
            "subcategory":"Bridal",
            "type":"Retail Goods"
        }
    ],
    "sg:phone":"+1 404 943 0037",
    "sg:postcode":"30328",
    "sg:province":"GA",
    "sg:tags":[
        "clothing",
        "women's"
    ],
    "sg:website":"tkdesignsatlanta.com",
    "wof:name":"TK Designs Inc",
    "wof:placetype":"venue"
},
  "geometry": {"coordinates":[-84.37902,33.920806],"type":"Point"}
}