{
  "type": "Feature",
  "properties": {
    "addr:full":"1874 Mary Lou Ln SE Atlanta GA 30316",
    "addr:housenumber":"1874",
    "addr:postcode":"30316",
    "addr:street":"Mary Lou Ln Se",
    "iso:country":"US",
    "sg:address":"1874 Mary Lou Ln SE",
    "sg:city":"Atlanta",
    "sg:classifiers":[
        {
            "category":"Shopping",
            "subcategory":"Clothing, Apparel, & Fashions",
            "type":"Retail Goods"
        }
    ],
    "sg:phone":"+1 404 830 4363",
    "sg:postcode":"30316",
    "sg:province":"GA",
    "sg:tags":[
        "garment"
    ],
    "wof:name":"J C's Unique Apparel",
    "wof:placetype":"venue"
},
  "geometry": {"coordinates":[-84.313954,33.703004],"type":"Point"}
}