{
  "type": "Feature",
  "properties": {
    "addr:full":"2006 N Point Cir Alpharetta GA 30022",
    "addr:housenumber":"2006",
    "addr:postcode":"30022",
    "addr:street":"N Point Cir",
    "iso:country":"US",
    "sg:address":"2006 N Point Cir",
    "sg:city":"Alpharetta",
    "sg:classifiers":[
        {
            "category":"Shopping",
            "subcategory":"Optical Goods",
            "type":"Retail Goods"
        }
    ],
    "sg:phone":"+1 770 777 0018",
    "sg:postcode":"30022",
    "sg:province":"GA",
    "wof:name":"Eye Gallery",
    "wof:placetype":"venue"
},
  "geometry": {"coordinates":[-84.2957,34.050438],"type":"Point"}
}