{
  "type": "Feature",
  "properties": {
    "iso:country":"US",
    "sg:address":"104 Parsons Pl",
    "sg:city":"Peachtree City",
    "sg:classifiers":[
        {
            "category":"Professional",
            "subcategory":"Computer Services",
            "type":"Services"
        }
    ],
    "sg:phone":"+1 770 632 9919",
    "sg:postcode":"30269",
    "sg:province":"GA",
    "sg:tags":[
        "related"
    ],
    "wof:name":"Humlie Ent",
    "wof:placetype":"venue"
},
  "geometry": {"coordinates":[-84.55977300000001,33.398141],"type":"Point"}
}