{
  "type": "Feature",
  "properties": {
    "addr:full":"574 Bramlett Shoals Rd Lawrenceville GA 30045",
    "addr:housenumber":"574",
    "addr:postcode":"30045",
    "addr:street":"Bramlett Shoals Rd",
    "iso:country":"US",
    "sg:address":"574 Bramlett Shoals Rd",
    "sg:city":"Lawrenceville",
    "sg:classifiers":[
        {
            "category":"Professional",
            "subcategory":"Business Services",
            "type":"Services"
        }
    ],
    "sg:phone":"+1 770 513 9846",
    "sg:postcode":"30045",
    "sg:province":"GA",
    "sg:tags":[
        "embroidery"
    ],
    "wof:name":"Top Drawer Embroidery",
    "wof:placetype":"venue"
},
  "geometry": {"coordinates":[-83.927487,33.95725],"type":"Point"}
}