{
  "type": "Feature",
  "properties": {
    "iso:country":"US",
    "sg:address":"503 Eisenhower Dr",
    "sg:city":"Savannah",
    "sg:classifiers":[
        {
            "category":"Health Services",
            "subcategory":"Medical Lab",
            "type":"Services"
        }
    ],
    "sg:phone":"+1 912 354 1444",
    "sg:postcode":"31406",
    "sg:province":"GA",
    "sg:tags":[
        "center",
        "diagnostic"
    ],
    "wof:name":"HealthSouth",
    "wof:placetype":"venue"
},
  "geometry": {"coordinates":[-81.10462699999999,32.007582],"type":"Point"}
}