{
  "type": "Feature",
  "properties": {
    "iso:country":"US",
    "sg:address":"135 Beaver Dam Rd",
    "sg:city":"Eatonton",
    "sg:classifiers":[
        {
            "category":"Building & Trades",
            "subcategory":"Equipment Rental",
            "type":"Services"
        }
    ],
    "sg:phone":"+1 706 484 2164",
    "sg:postcode":"31024",
    "sg:province":"GA",
    "sg:tags":[
        "medical"
    ],
    "wof:name":"M&M Mobility Service Inc",
    "wof:placetype":"venue"
},
  "geometry": {"coordinates":[-83.50019899999999,33.318027],"type":"Point"}
}