{
  "type": "Feature",
  "properties": {
    "addr:full":"1241 Eatonton Rd Madison GA 30650",
    "addr:housenumber":"1241",
    "addr:postcode":"30650",
    "addr:street":"Eatonton Rd",
    "iso:country":"US",
    "sg:address":"1241 Eatonton Rd",
    "sg:city":"Madison",
    "sg:classifiers":[
        {
            "category":"Food & Beverages",
            "subcategory":"Groceries & Convenience Stores",
            "type":"Retail Goods"
        }
    ],
    "sg:phone":"+1 706 752 0003",
    "sg:postcode":"30650",
    "sg:province":"GA",
    "wof:name":"Sunflower Foodmart",
    "wof:placetype":"venue"
},
  "geometry": {"coordinates":[-83.477701,33.580575],"type":"Point"}
}