{
  "type": "Feature",
  "properties": {
    "addr:full":"5 Skylake Ct Columbus GA 31907",
    "addr:housenumber":"5",
    "addr:postcode":"31907",
    "addr:street":"Skylake Ct",
    "iso:country":"US",
    "sg:address":"5 Skylake Ct",
    "sg:city":"Columbus",
    "sg:classifiers":[
        {
            "category":"Banks & Credit Unions",
            "subcategory":"Bank",
            "type":"Services"
        }
    ],
    "sg:phone":"+1 706 221 8363",
    "sg:postcode":"31907",
    "sg:province":"GA",
    "sg:tags":[
        "loan",
        "real estate"
    ],
    "wof:name":"Moneywise Financial Svc",
    "wof:placetype":"venue"
},
  "geometry": {"coordinates":[-84.901774,32.486513],"type":"Point"}
}