{
  "type": "Feature",
  "properties": {
    "addr:full":"9579 State Rte 5 Douglasville GA 30135",
    "addr:housenumber":"9579",
    "addr:postcode":"30135",
    "addr:street":"State Rte 5",
    "iso:country":"US",
    "sg:address":"9579 State Rte 5",
    "sg:city":"Douglasville",
    "sg:classifiers":[
        {
            "category":"Cinema",
            "subcategory":"Movie Rental",
            "type":"Entertainment"
        }
    ],
    "sg:phone":"+1 770 949 4340",
    "sg:postcode":"30135",
    "sg:province":"GA",
    "sg:tags":[
        "leasing",
        "video",
        "disc",
        "tape"
    ],
    "wof:name":"Blockbuster Video",
    "wof:placetype":"venue"
},
  "geometry": {"coordinates":[-84.76232899999999,33.724809],"type":"Point"}
}