{
  "type": "Feature",
  "properties": {
    "iso:country":"US",
    "sg:address":"5800 Manassas Dr",
    "sg:city":"Columbus",
    "sg:classifiers":[
        {
            "category":"Professional",
            "subcategory":"Detective & Security Services",
            "type":"Services"
        }
    ],
    "sg:phone":"+1 706 221 6712",
    "sg:postcode":"31909",
    "sg:province":"GA",
    "sg:tags":[
        "information",
        "bureau"
    ],
    "wof:name":"Stan S Pool Service",
    "wof:placetype":"venue"
},
  "geometry": {"coordinates":[-84.893356,32.537998],"type":"Point"}
}