{
  "type": "Feature",
  "properties": {
    "iso:country":"US",
    "sg:address":"6700 Tribble St",
    "sg:city":"Lithonia",
    "sg:classifiers":[
        {
            "category":"Building & Trades",
            "subcategory":"Construction",
            "type":"Services"
        }
    ],
    "sg:phone":"+1 770 482 2000",
    "sg:postcode":"30058",
    "sg:province":"GA",
    "sg:tags":[
        "system",
        "specialty",
        "heating",
        "mechanical",
        "contractor",
        "air conditioning"
    ],
    "wof:name":"Bachelor & Kimball Inc",
    "wof:placetype":"venue"
},
  "geometry": {"coordinates":[-84.11573799999999,33.718689],"type":"Point"}
}