{
  "type": "Feature",
  "properties": {
    "addr:full":"182 Moss Oaks Rd Perry GA 31069",
    "addr:housenumber":"182",
    "addr:postcode":"31069",
    "addr:street":"Moss Oaks Rd",
    "iso:country":"US",
    "sg:address":"182 Moss Oaks Rd",
    "sg:city":"Perry",
    "sg:classifiers":[
        {
            "category":"Organizations",
            "subcategory":"Religious Organization",
            "type":"Services"
        }
    ],
    "sg:phone":"+1 478 987 4059",
    "sg:postcode":"31069",
    "sg:province":"GA",
    "wof:name":"Mount Zion Cme Church",
    "wof:placetype":"venue"
},
  "geometry": {"coordinates":[-83.78291,32.431109],"type":"Point"}
}