{
  "type": "Feature",
  "properties": {
    "iso:country":"US",
    "sg:address":"400 Cummings St",
    "sg:city":"Valdosta",
    "sg:classifiers":[
        {
            "category":"Retail",
            "subcategory":"Repair Shop",
            "type":"Services"
        }
    ],
    "sg:phone":"+1 229 247 0500",
    "sg:postcode":"31601",
    "sg:province":"GA",
    "wof:name":"Mary Cleaning and Landscaping",
    "wof:placetype":"venue"
},
  "geometry": {"coordinates":[-83.26615099999999,30.82068],"type":"Point"}
}