{
  "type": "Feature",
  "properties": {
    "addr:full":"3925 N Oak St Exd Valdosta GA 31605",
    "addr:housenumber":"3925",
    "addr:postcode":"31605",
    "addr:street":"N Oak St Exd",
    "iso:country":"US",
    "sg:address":"3925 N Oak St Exd",
    "sg:city":"Valdosta",
    "sg:classifiers":[
        {
            "category":"Building & Trades",
            "subcategory":"Construction",
            "type":"Services"
        }
    ],
    "sg:phone":"+1 229 242 9577",
    "sg:postcode":"31605",
    "sg:province":"GA",
    "sg:tags":[
        "general",
        "contractor"
    ],
    "wof:name":"Bedgood Quality Construction",
    "wof:placetype":"venue"
},
  "geometry": {"coordinates":[-83.284852,30.890037],"type":"Point"}
}