{
  "type": "Feature",
  "properties": {
    "iso:country":"US",
    "sg:address":"4368 Conwhey Ct",
    "sg:city":"Smyrna",
    "sg:classifiers":[
        {
            "category":"Retail",
            "subcategory":"Portrait Studio",
            "type":"Services"
        }
    ],
    "sg:phone":"+1 404 542 5837",
    "sg:postcode":"30082",
    "sg:province":"GA",
    "sg:tags":[
        "photo"
    ],
    "wof:name":"Master Joes Photography",
    "wof:placetype":"venue"
},
  "geometry": {"coordinates":[-84.575232,33.847688],"type":"Point"}
}