{
  "type": "Feature",
  "properties": {
    "addr:full":"1105 E Main St Royston GA 30639",
    "addr:housenumber":"1105",
    "addr:postcode":"30639",
    "addr:street":"E Main St",
    "iso:country":"US",
    "sg:address":"1105 E Main St",
    "sg:city":"Royston",
    "sg:classifiers":[
        {
            "category":"Real Estate",
            "subcategory":"Real Estate Agent",
            "type":"Services"
        }
    ],
    "sg:phone":"+1 706 245 7221",
    "sg:postcode":"30639",
    "sg:province":"GA",
    "wof:name":"Coldwell Banker",
    "wof:placetype":"venue"
},
  "geometry": {"coordinates":[-83.13973799999999,34.285489],"type":"Point"}
}