{
  "type": "Feature",
  "properties": {
    "addr:full":"413 N Gray St Millen GA 30442",
    "addr:housenumber":"413",
    "addr:postcode":"30442",
    "addr:street":"N Gray St",
    "iso:country":"US",
    "sg:address":"413 N Gray St",
    "sg:city":"Millen",
    "sg:classifiers":[
        {
            "category":"Organizations",
            "subcategory":"Religious Organization",
            "type":"Services"
        }
    ],
    "sg:phone":"+1 478 982 2664",
    "sg:postcode":"30442",
    "sg:province":"GA",
    "sg:tags":[
        "church"
    ],
    "wof:name":"Millen United Methodist Church",
    "wof:placetype":"venue"
},
  "geometry": {"coordinates":[-81.941309,32.807359],"type":"Point"}
}