{
  "type": "Feature",
  "properties": {
    "iso:country":"US",
    "sg:address":"2370 Roxburgh Dr",
    "sg:city":"Roswell",
    "sg:classifiers":[
        {
            "category":"Professional",
            "subcategory":"Lawyer & Legal Services",
            "type":"Services"
        }
    ],
    "sg:phone":"+1 770 664 8555",
    "sg:postcode":"30076",
    "sg:province":"GA",
    "sg:tags":[
        "attorney"
    ],
    "wof:name":"Frederick L Cooper III Law Ofc",
    "wof:placetype":"venue"
},
  "geometry": {"coordinates":[-84.28780999999999,34.027019],"type":"Point"}
}