{
  "type": "Feature",
  "properties": {
    "iso:country":"US",
    "sg:address":"1404 Plant Ave",
    "sg:city":"Waycross",
    "sg:classifiers":[
        {
            "category":"Restaurant",
            "type":"Food & Drink"
        }
    ],
    "sg:phone":"+1 912 287 1303",
    "sg:postcode":"31501",
    "sg:province":"GA",
    "sg:tags":[
        "eating"
    ],
    "wof:name":"Jerry J's Inc",
    "wof:placetype":"venue"
},
  "geometry": {"coordinates":[-82.339403,31.225023],"type":"Point"}
}