{
  "type": "Feature",
  "properties": {
    "addr:full":"233 Lee Ann Rd Buchanan GA 30113",
    "addr:housenumber":"233",
    "addr:postcode":"30113",
    "addr:street":"Lee Ann Rd",
    "iso:country":"US",
    "sg:address":"233 Lee Ann Rd",
    "sg:city":"Buchanan",
    "sg:classifiers":[
        {
            "category":"Building & Trades",
            "subcategory":"Construction",
            "type":"Services"
        }
    ],
    "sg:phone":"+1 770 947 8280",
    "sg:postcode":"30113",
    "sg:province":"GA",
    "sg:tags":[
        "floor",
        "laying",
        "contractor"
    ],
    "wof:name":"Georgia Floortech Inc",
    "wof:placetype":"venue"
},
  "geometry": {"coordinates":[-85.146782,33.880583],"type":"Point"}
}