{
  "type": "Feature",
  "properties": {
    "addr:full":"100 N Jackson St Athens GA 30601",
    "addr:housenumber":"100",
    "addr:postcode":"30601",
    "addr:street":"N Jackson St",
    "iso:country":"US",
    "sg:address":"100 N Jackson St",
    "sg:city":"Athens",
    "sg:classifiers":[
        {
            "category":"Bars & Pubs",
            "type":"Food & Drink"
        }
    ],
    "sg:phone":"+1 706 613 0504",
    "sg:postcode":"30601",
    "sg:province":"GA",
    "sg:tags":[
        "club",
        "night"
    ],
    "wof:name":"Toppers International Showbar",
    "wof:placetype":"venue"
},
  "geometry": {"coordinates":[-83.374506,33.95876],"type":"Point"}
}