{
  "type": "Feature",
  "properties": {
    "iso:country":"US",
    "sg:address":"405 W 9th St",
    "sg:city":"Waynesboro",
    "sg:classifiers":[
        {
            "category":"Professional",
            "type":"Services"
        }
    ],
    "sg:phone":"+1 706 554 4393",
    "sg:postcode":"30830",
    "sg:province":"GA",
    "wof:name":"Donald Crawford",
    "wof:placetype":"venue"
},
  "geometry": {"coordinates":[-82.023534,33.094348],"type":"Point"}
}