{
  "type": "Feature",
  "properties": {
    "addr:full":"2305 Sterling Pl Valdosta GA 31602",
    "addr:housenumber":"2305",
    "addr:postcode":"31602",
    "addr:street":"Sterling Pl",
    "iso:country":"US",
    "sg:address":"2305 Sterling Pl",
    "sg:city":"Valdosta",
    "sg:classifiers":[
        {
            "category":"Social Services",
            "subcategory":"Child Care",
            "type":"Services"
        }
    ],
    "sg:phone":"+1 229 241 7842",
    "sg:postcode":"31602",
    "sg:province":"GA",
    "wof:name":"Garden Of Eden Preschool",
    "wof:placetype":"venue"
},
  "geometry": {"coordinates":[-83.268539,30.865388],"type":"Point"}
}