{
  "type": "Feature",
  "properties": {
    "iso:country":"US",
    "sg:address":"1164 Winder Hwy",
    "sg:city":"Lawrenceville",
    "sg:classifiers":[
        {
            "category":"Restaurant",
            "type":"Food & Drink"
        }
    ],
    "sg:menulink":"http://www.allmenus.com/ga/lawrenceville/70779-pizza-hut/menu/",
    "sg:phone":"+1 770 513 8400",
    "sg:postcode":"30045",
    "sg:province":"GA",
    "sg:tags":[
        "american",
        "pizza"
    ],
    "wof:name":"Pizza Hut",
    "wof:placetype":"venue"
},
  "geometry": {"coordinates":[-83.94622,33.974966],"type":"Point"}
}