{
  "type": "Feature",
  "properties": {
    "addr:full":"4960 Redan Rd Stone Mountain GA 30088",
    "addr:housenumber":"4960",
    "addr:postcode":"30088",
    "addr:street":"Redan Rd",
    "iso:country":"US",
    "sg:address":"4960 Redan Rd",
    "sg:city":"Stone Mountain",
    "sg:classifiers":[
        {
            "category":"Personal",
            "subcategory":"Nail Salon",
            "type":"Services"
        }
    ],
    "sg:phone":"+1 404 294 5020",
    "sg:postcode":"30088",
    "sg:province":"GA",
    "wof:name":"P3 Nails",
    "wof:placetype":"venue"
},
  "geometry": {"coordinates":[-84.19382400000001,33.760832],"type":"Point"}
}