{
  "type": "Feature",
  "properties": {
    "addr:full":"1352 Jimson Cir SE Conyers GA 30013",
    "addr:housenumber":"1352",
    "addr:postcode":"30013",
    "addr:street":"Jimson Cir Se",
    "iso:country":"US",
    "sg:address":"1352 Jimson Cir SE",
    "sg:city":"Conyers",
    "sg:classifiers":[
        {
            "category":"Banks & Credit Unions",
            "subcategory":"Investment Brokerage",
            "type":"Services"
        }
    ],
    "sg:phone":"+1 770 922 0681",
    "sg:postcode":"30013",
    "sg:province":"GA",
    "sg:tags":[
        "security"
    ],
    "wof:name":"Transactions International Inc",
    "wof:placetype":"venue"
},
  "geometry": {"coordinates":[-84.007909,33.627338],"type":"Point"}
}