{
  "type": "Feature",
  "properties": {
    "iso:country":"US",
    "sg:address":"1050 Hospital Dr",
    "sg:city":"Stockbridge",
    "sg:classifiers":[
        {
            "category":"Community Center",
            "type":"Public Place"
        }
    ],
    "sg:phone":"+1 770 506 1600",
    "sg:postcode":"30281",
    "sg:province":"GA",
    "sg:tags":[
        "medical"
    ],
    "sg:website":"www.henrymedical.com",
    "wof:name":"Laurel Park At Henry Medical Center",
    "wof:placetype":"venue"
},
  "geometry": {"coordinates":[-84.228302,33.512001],"type":"Point"}
}