{
  "type": "Feature",
  "properties": {
    "iso:country":"US",
    "sg:address":"4316 Lawrenceville Highway",
    "sg:city":"Tucker",
    "sg:classifiers":[
        {
            "category":"Restaurant",
            "type":"Food & Drink"
        }
    ],
    "sg:phone":"+1 770 807 8000",
    "sg:postcode":"30084",
    "sg:province":"GA",
    "sg:tags":[
        "pizza"
    ],
    "sg:website":"riversidepizza.net/",
    "wof:name":"Riverside Pizza",
    "wof:placetype":"venue"
},
  "geometry": {"coordinates":[-84.20907099999999,33.856144],"type":"Point"}
}