{
  "type": "Feature",
  "properties": {
    "iso:country":"US",
    "sg:address":"2955 Johnson Ferry Rd",
    "sg:city":"Marietta",
    "sg:classifiers":[
        {
            "category":"Retail",
            "subcategory":"Auto Repair",
            "type":"Services"
        }
    ],
    "sg:phone":"+1 770 641 9906",
    "sg:postcode":"30062",
    "sg:province":"GA",
    "wof:name":"East Cobb Auto Care Center",
    "wof:placetype":"venue"
},
  "geometry": {"coordinates":[-84.42759700000001,34.020901],"type":"Point"}
}