{
  "type": "Feature",
  "properties": {
    "addr:full":"1216 Mauge St Augusta GA 30901",
    "addr:housenumber":"1216",
    "addr:postcode":"30901",
    "addr:street":"Mauge St",
    "iso:country":"US",
    "sg:address":"1216 Mauge St",
    "sg:city":"Augusta",
    "sg:classifiers":[
        {
            "category":"Personal",
            "subcategory":"Beauty Salon",
            "type":"Services"
        }
    ],
    "sg:phone":"+1 706 826 1959",
    "sg:postcode":"30901",
    "sg:province":"GA",
    "wof:name":"Rebecca's Beauty Salon",
    "wof:placetype":"venue"
},
  "geometry": {"coordinates":[-81.98143399999999,33.464947],"type":"Point"}
}