{
  "type": "Feature",
  "properties": {
    "addr:full":"5952 Peachtree Industrial Blvd Norcross GA 30071",
    "addr:housenumber":"5952",
    "addr:postcode":"30071",
    "addr:street":"Peachtree Industrial Blvd",
    "iso:country":"US",
    "sg:address":"5952 Peachtree Industrial Blvd",
    "sg:city":"Norcross",
    "sg:classifiers":[
        {
            "category":"Utilities",
            "subcategory":"Mobile Phone",
            "type":"Services"
        }
    ],
    "sg:phone":"+1 770 326 7965",
    "sg:postcode":"30071",
    "sg:province":"GA",
    "sg:tags":[
        "communications",
        "radiotelephone"
    ],
    "wof:name":"Nextel",
    "wof:placetype":"venue"
},
  "geometry": {"coordinates":[-84.22775300000001,33.951228],"type":"Point"}
}