{
  "type": "Feature",
  "properties": {
    "addr:full":"2300 Colleen Cir Marietta GA 30060",
    "addr:housenumber":"2300",
    "addr:postcode":"30060",
    "addr:street":"Colleen Cir",
    "iso:country":"US",
    "sg:address":"2300 Colleen Cir",
    "sg:city":"Marietta",
    "sg:classifiers":[
        {
            "category":"Retail",
            "subcategory":"Repair Shop",
            "type":"Services"
        }
    ],
    "sg:phone":"+1 770 803 0321",
    "sg:postcode":"30060",
    "sg:province":"GA",
    "wof:name":"Golden Clean Service",
    "wof:placetype":"venue"
},
  "geometry": {"coordinates":[-84.567328,33.89693],"type":"Point"}
}