{
  "type": "Feature",
  "properties": {
    "iso:country":"US",
    "sg:address":"121 Lovingood Dr",
    "sg:city":"Woodstock",
    "sg:classifiers":[
        {
            "category":"Professional",
            "subcategory":"Business Services",
            "type":"Services"
        }
    ],
    "sg:phone":"+1 770 926 0782",
    "sg:postcode":"30189",
    "sg:province":"GA",
    "wof:name":"Piggyback Express Inc",
    "wof:placetype":"venue"
},
  "geometry": {"coordinates":[-84.59888599999999,34.160317],"type":"Point"}
}