{
  "type": "Feature",
  "properties": {
    "iso:country":"US",
    "sg:address":"1645 River Oak Dr",
    "sg:city":"Roswell",
    "sg:classifiers":[
        {
            "category":"Professional",
            "subcategory":"Management & Consulting",
            "type":"Services"
        }
    ],
    "sg:phone":"+1 678 461 0286",
    "sg:postcode":"30075",
    "sg:province":"GA",
    "sg:tags":[
        "business"
    ],
    "wof:name":"Ifi LLC",
    "wof:placetype":"venue"
},
  "geometry": {"coordinates":[-84.37080400000001,34.055954],"type":"Point"}
}