{
  "type": "Feature",
  "properties": {
    "iso:country":"US",
    "sg:address":"2250 Pendley Rd",
    "sg:city":"Cumming",
    "sg:classifiers":[
        {
            "category":"Autos & Motor Vehicles",
            "subcategory":"Automobile Sales",
            "type":"Retail Goods"
        },
        {
            "category":"Retail",
            "subcategory":"Auto Repair",
            "type":"Services"
        }
    ],
    "sg:phone":"+1 770 781 8989",
    "sg:postcode":"30041",
    "sg:province":"GA",
    "sg:tags":[
        "body",
        "repairing",
        "used",
        "car",
        "new",
        "painting"
    ],
    "wof:name":"Flashback Motorworks",
    "wof:placetype":"venue"
},
  "geometry": {"coordinates":[-84.159654,34.164225],"type":"Point"}
}