{
  "type": "Feature",
  "properties": {
    "addr:full":"2488 Blue Ridge Hwy Blairsville GA 30512",
    "addr:housenumber":"2488",
    "addr:postcode":"30512",
    "addr:street":"Blue Ridge Hwy",
    "iso:country":"US",
    "sg:address":"2488 Blue Ridge Hwy",
    "sg:city":"Blairsville",
    "sg:classifiers":[
        {
            "category":"Food & Beverages",
            "subcategory":"Groceries & Convenience Stores",
            "type":"Retail Goods"
        }
    ],
    "sg:phone":"+1 706 745 9843",
    "sg:postcode":"30512",
    "sg:province":"GA",
    "wof:name":"Daves Market Inc",
    "wof:placetype":"venue"
},
  "geometry": {"coordinates":[-84.00687499999999,34.843533],"type":"Point"}
}