{
  "type": "Feature",
  "properties": {
    "addr:full":"1109 Southlake Mall Morrow GA 30260",
    "addr:housenumber":"1109",
    "addr:postcode":"30260",
    "addr:street":"Southlake Mall",
    "iso:country":"US",
    "sg:address":"1109 Southlake Mall",
    "sg:city":"Morrow",
    "sg:classifiers":[
        {
            "category":"Sports & Exercise",
            "subcategory":"Bicycle Rental",
            "type":"Entertainment"
        }
    ],
    "sg:phone":"+1 678 422 5270",
    "sg:postcode":"30260",
    "sg:province":"GA",
    "sg:tags":[
        "wear"
    ],
    "sg:website":"www.pacsun.com",
    "wof:name":"Pacific Sunwear",
    "wof:placetype":"venue"
},
  "geometry": {"coordinates":[-84.351303,33.5732],"type":"Point"}
}