{
  "type": "Feature",
  "properties": {
    "addr:full":"2533 Sullivan Rd College Park GA 30337",
    "addr:housenumber":"2533",
    "addr:postcode":"30337",
    "addr:street":"Sullivan Rd",
    "iso:country":"US",
    "sg:address":"2533 Sullivan Rd",
    "sg:city":"College Park",
    "sg:classifiers":[
        {
            "category":"Retail",
            "subcategory":"Veterinary Services",
            "type":"Services"
        }
    ],
    "sg:phone":"+1 678 973 2881",
    "sg:postcode":"30337",
    "sg:province":"GA",
    "sg:tags":[
        "veterinarian"
    ],
    "sg:website":"atlantapets.org/lifeline.zz?this=71",
    "wof:name":"Lifeline Spay & Neuter Clinic",
    "wof:placetype":"venue"
},
  "geometry": {"coordinates":[-84.472144,33.625047],"type":"Point"}
}