{
  "type": "Feature",
  "properties": {
    "iso:country":"US",
    "sg:address":"10 18th St NW",
    "sg:city":"Atlanta",
    "sg:classifiers":[
        {
            "category":"Real Estate",
            "subcategory":"Architect",
            "type":"Services"
        }
    ],
    "sg:phone":"+1 404 872 2217",
    "sg:postcode":"30309",
    "sg:province":"GA",
    "wof:name":"Arkhora Associates Inc",
    "wof:placetype":"venue"
},
  "geometry": {"coordinates":[-84.38775699999999,33.793316],"type":"Point"}
}