{
  "type": "Feature",
  "properties": {
    "iso:country":"US",
    "sg:address":"65 Seabolt Rd",
    "sg:city":"Locust Grove",
    "sg:classifiers":[
        {
            "category":"Building & Trades",
            "subcategory":"Pest Control",
            "type":"Services"
        }
    ],
    "sg:phone":"+1 770 954 9300",
    "sg:postcode":"30248",
    "sg:province":"GA",
    "wof:name":"Evans Termite & Pest Control",
    "wof:placetype":"venue"
},
  "geometry": {"coordinates":[-84.100253,33.376489],"type":"Point"}
}