{
  "type": "Feature",
  "properties": {
    "addr:full":"5455 McGinnis Ferry Rd Alpharetta GA 30005",
    "addr:postcode":"5455;30005",
    "addr:street":"Mcginnis Ferry Rd",
    "iso:country":"US",
    "sg:address":"5455 McGinnis Ferry Rd",
    "sg:city":"Alpharetta",
    "sg:classifiers":[
        {
            "category":"Professional",
            "subcategory":"Management & Consulting",
            "type":"Services"
        }
    ],
    "sg:phone":"+1 770 753 8700",
    "sg:postcode":"30005",
    "sg:province":"GA",
    "sg:tags":[
        "information",
        "technology"
    ],
    "wof:name":"Guestnet and Total Choice",
    "wof:placetype":"venue"
},
  "geometry": {"coordinates":[-84.194884,34.087893],"type":"Point"}
}