{
  "type": "Feature",
  "properties": {
    "iso:country":"US",
    "sg:address":"5928 Dogwood Dr SE",
    "sg:city":"Acworth",
    "sg:classifiers":[
        {
            "category":"Building & Trades",
            "subcategory":"Landscaping Services",
            "type":"Services"
        }
    ],
    "sg:phone":"+1 770 231 8360",
    "sg:postcode":"30102",
    "sg:province":"GA",
    "sg:tags":[
        "landscape",
        "contractor"
    ],
    "wof:name":"G V Landscaping",
    "wof:placetype":"venue"
},
  "geometry": {"coordinates":[-84.687248,34.098554],"type":"Point"}
}