{
  "type": "Feature",
  "properties": {
    "iso:country":"US",
    "sg:address":"210 Washington Street NW  Suite 203",
    "sg:city":"Gainesville ",
    "sg:classifiers":[
        {
            "category":"Professional",
            "subcategory":"Advertising",
            "type":"Services"
        }
    ],
    "sg:phone":"+1 770 297 2431",
    "sg:postcode":"30501",
    "sg:province":"GA",
    "sg:tags":[
        "interactive-marketing",
        "search-engine-optimization",
        "ecommerce",
        "web-design",
        "marketing-strategy",
        "email-marketing",
        "pay-per-click",
        "landing-pages",
        "micro-sites",
        "online-brand-strategy"
    ],
    "sg:website":"http://www.redclayinteractive.com",
    "wof:name":"Red Clay Interactive",
    "wof:placetype":"venue"
},
  "geometry": {"coordinates":[-83.822396,34.301927],"type":"Point"}
}