{
  "type": "Feature",
  "properties": {
    "addr:full":"109 Morrow St Monroe GA 30655",
    "addr:housenumber":"109",
    "addr:postcode":"30655",
    "addr:street":"Morrow St",
    "iso:country":"US",
    "sg:address":"109 Morrow St",
    "sg:city":"Monroe",
    "sg:classifiers":[
        {
            "category":"Personal",
            "subcategory":"Beauty Salon",
            "type":"Services"
        }
    ],
    "sg:phone":"+1 770 207 9633",
    "sg:postcode":"30655",
    "sg:province":"GA",
    "wof:name":"Hair & Salon",
    "wof:placetype":"venue"
},
  "geometry": {"coordinates":[-83.719211,33.805608],"type":"Point"}
}