{
  "type": "Feature",
  "properties": {
    "iso:country":"US",
    "sg:address":"2672 Old Hapeville Rd SW",
    "sg:city":"Atlanta",
    "sg:classifiers":[
        {
            "category":"Education",
            "subcategory":"School",
            "type":"Public Place"
        }
    ],
    "sg:phone":"+1 404 669 2717",
    "sg:postcode":"30315",
    "sg:province":"GA",
    "sg:tags":[
        "high",
        "middle",
        "elementary"
    ],
    "wof:name":"Atlanta City School District",
    "wof:placetype":"venue"
},
  "geometry": {"coordinates":[-84.39411,33.682022],"type":"Point"}
}