{
  "type": "Feature",
  "properties": {
    "addr:full":"1435 State Rte 16 W Griffin GA 30223",
    "addr:housenumber":"1435",
    "addr:postcode":"30223",
    "addr:street":"State Rte 16 W",
    "iso:country":"US",
    "sg:address":"1435 State Rte 16 W",
    "sg:city":"Griffin",
    "sg:classifiers":[
        {
            "category":"Home & Garden",
            "subcategory":"Building Materials",
            "type":"Retail Goods"
        }
    ],
    "sg:phone":"+1 770 233 9411",
    "sg:postcode":"30223",
    "sg:province":"GA",
    "wof:name":"Home Depot",
    "wof:placetype":"venue"
},
  "geometry": {"coordinates":[-84.28490499999999,33.247453],"type":"Point"}
}