{
  "type": "Feature",
  "properties": {
    "iso:country":"US",
    "sg:address":"2484 Marietta Hwy",
    "sg:city":"Canton",
    "sg:classifiers":[
        {
            "category":"Professional",
            "type":"Services"
        }
    ],
    "sg:phone":"+1 770 479 1559",
    "sg:postcode":"30114",
    "sg:province":"GA",
    "sg:tags":[
        "establishment"
    ],
    "wof:name":"Vault",
    "wof:placetype":"venue"
},
  "geometry": {"coordinates":[-84.504383,34.212751],"type":"Point"}
}