{
  "type": "Feature",
  "properties": {
    "addr:full":"2320 Virginia Place NE Suite C Atlanta GA 30305",
    "addr:housenumber":"2320",
    "addr:postcode":"30305",
    "addr:street":"Virginia Place Ne Suite C",
    "iso:country":"US",
    "sg:address":"2320 Virginia Place NE Suite C",
    "sg:city":"Atlanta",
    "sg:classifiers":[
        {
            "category":"Personal",
            "subcategory":"Beauty Salon",
            "type":"Services"
        }
    ],
    "sg:phone":"+1 404 261 3105",
    "sg:postcode":"30305",
    "sg:province":"GA",
    "sg:tags":[
        "hair"
    ],
    "wof:name":"J Michelle Salon",
    "wof:placetype":"venue"
},
  "geometry": {"coordinates":[-84.380551,33.818426],"type":"Point"}
}