{
  "type": "Feature",
  "properties": {
    "addr:full":"440 Old Albany Rd Moultrie GA 31768",
    "addr:housenumber":"440",
    "addr:postcode":"31768",
    "addr:street":"Old Albany Rd",
    "iso:country":"US",
    "sg:address":"440 Old Albany Rd",
    "sg:city":"Moultrie",
    "sg:classifiers":[
        {
            "category":"Transit Center",
            "subcategory":"Freight",
            "type":"Transportation"
        },
        {
            "category":"Freight",
            "type":"Transportation"
        }
    ],
    "sg:phone":"+1 229 985 8854",
    "sg:postcode":"31768",
    "sg:province":"GA",
    "sg:tags":[
        "local",
        "trucking-motor",
        "trucking"
    ],
    "wof:name":"Campbell Trucking",
    "wof:placetype":"venue"
},
  "geometry": {"coordinates":[-83.827011,31.234586],"type":"Point"}
}