{
  "type": "Feature",
  "properties": {
    "addr:full":"104 Westview Dr Villa Rica GA 30180",
    "addr:housenumber":"104",
    "addr:postcode":"30180",
    "addr:street":"Westview Dr",
    "iso:country":"US",
    "sg:address":"104 Westview Dr",
    "sg:city":"Villa Rica",
    "sg:classifiers":[
        {
            "category":"Restaurant",
            "type":"Food & Drink"
        }
    ],
    "sg:phone":"+1 770 459 0110",
    "sg:postcode":"30180",
    "sg:province":"GA",
    "sg:tags":[
        "eating",
        "household",
        "appliance"
    ],
    "wof:name":"Do It Right Kitchen & Bath",
    "wof:placetype":"venue"
},
  "geometry": {"coordinates":[-84.920562,33.732478],"type":"Point"}
}