{
  "type": "Feature",
  "properties": {
    "iso:country":"US",
    "sg:address":"4000 Five Forks Trickum Rd SW Trickum",
    "sg:city":"Lilburn",
    "sg:classifiers":[
        {
            "category":"Social Services",
            "type":"Services"
        }
    ],
    "sg:phone":"+1 404 545 7595",
    "sg:postcode":"30047",
    "sg:province":"GA",
    "wof:name":"Star Struck Foundation Inc",
    "wof:placetype":"venue"
},
  "geometry": {"coordinates":[-84.09100100000001,33.869486],"type":"Point"}
}