{
  "type": "Feature",
  "properties": {
    "iso:country":"US",
    "sg:address":"6557 Rosecommon Dr NW",
    "sg:city":"Norcross",
    "sg:classifiers":[
        {
            "category":"Food & Beverages",
            "subcategory":"Bakery",
            "type":"Retail Goods"
        }
    ],
    "sg:phone":"+1 770 448 7304",
    "sg:postcode":"30092",
    "sg:province":"GA",
    "wof:name":"A Private Affair",
    "wof:placetype":"venue"
},
  "geometry": {"coordinates":[-84.248372,33.968809],"type":"Point"}
}