{
  "type": "Feature",
  "properties": {
    "iso:country":"US",
    "sg:address":"461 Powers Ferry Rd SE",
    "sg:city":"Marietta",
    "sg:classifiers":[
        {
            "category":"Organizations",
            "subcategory":"Religious Organization",
            "type":"Services"
        }
    ],
    "sg:phone":"+1 770 321 0025",
    "sg:postcode":"30067",
    "sg:province":"GA",
    "sg:tags":[
        "church"
    ],
    "wof:name":"Georgia Brazilian Assembly-God",
    "wof:placetype":"venue"
},
  "geometry": {"coordinates":[-84.49323800000001,33.940898],"type":"Point"}
}