{
  "type": "Feature",
  "properties": {
    "addr:full":"1 Martin Luther King Jr Dr SE Atlanta GA 30334",
    "addr:housenumber":"1",
    "addr:postcode":"30334",
    "addr:street":"Martin Luther King Jr Dr Se",
    "iso:country":"US",
    "sg:address":"1 Martin Luther King Jr Dr SE",
    "sg:city":"Atlanta",
    "sg:classifiers":[
        {
            "category":"Government",
            "subcategory":"Office",
            "type":"Public Place"
        }
    ],
    "sg:phone":"+1 404 656 4154",
    "sg:postcode":"30334",
    "sg:province":"GA",
    "sg:tags":[
        "state",
        "program"
    ],
    "wof:name":"Building Authority-Team North",
    "wof:placetype":"venue"
},
  "geometry": {"coordinates":[-84.388458,33.750039],"type":"Point"}
}