{
  "type": "Feature",
  "properties": {
    "iso:country":"US",
    "sg:address":"1734 Jenkins St",
    "sg:city":"Augusta",
    "sg:classifiers":[
        {
            "category":"Professional",
            "subcategory":"Accounting & Tax Preparation",
            "type":"Services"
        }
    ],
    "sg:phone":"+1 706 739 1984",
    "sg:postcode":"30904",
    "sg:province":"GA",
    "sg:tags":[
        "return"
    ],
    "wof:name":"Simmons Income Tax Service",
    "wof:placetype":"venue"
},
  "geometry": {"coordinates":[-81.997158,33.4767],"type":"Point"}
}