{
  "type": "Feature",
  "properties": {
    "iso:country":"US",
    "sg:address":"374 N Deshong Rd",
    "sg:city":"Stone Mountain",
    "sg:classifiers":[
        {
            "category":"Restaurant",
            "type":"Food & Drink"
        }
    ],
    "sg:menulink":"http://www.allmenus.com/ga/stone-mountain/132717-subway/menu/",
    "sg:phone":"+1 770 465 0087",
    "sg:postcode":"30087",
    "sg:province":"GA",
    "sg:tags":[
        "american",
        "sandwich"
    ],
    "wof:name":"Subway",
    "wof:placetype":"venue"
},
  "geometry": {"coordinates":[-84.10202700000001,33.785525],"type":"Point"}
}