{
  "type": "Feature",
  "properties": {
    "iso:country":"US",
    "sg:address":"3514 Palisade Cove Dr",
    "sg:city":"Duluth",
    "sg:classifiers":[
        {
            "category":"Autos & Motor Vehicles",
            "subcategory":"Auto Supplies",
            "type":"Retail Goods"
        }
    ],
    "sg:phone":"+1 770 622 2466",
    "sg:postcode":"30096",
    "sg:province":"GA",
    "sg:tags":[
        "glass"
    ],
    "wof:name":"Atlantic Auto Glass",
    "wof:placetype":"venue"
},
  "geometry": {"coordinates":[-84.15860000000001,33.992901],"type":"Point"}
}