{
  "type": "Feature",
  "properties": {
    "addr:full":"5670 Hwy 9 N Alpharetta GA 30004",
    "addr:housenumber":"5670",
    "addr:postcode":"30004",
    "addr:street":"Hwy 9 N",
    "iso:country":"US",
    "sg:address":"5670 Hwy 9 N",
    "sg:city":"Alpharetta",
    "sg:classifiers":[
        {
            "category":"Retail",
            "subcategory":"Laundry & Dry Cleaning",
            "type":"Services"
        }
    ],
    "sg:phone":"+1 770 740 0026",
    "sg:postcode":"30004",
    "sg:province":"GA",
    "sg:tags":[
        "drycleaning",
        "plant"
    ],
    "wof:name":"Champion Cleaners",
    "wof:placetype":"venue"
},
  "geometry": {"coordinates":[-84.251755,34.144101],"type":"Point"}
}