{
  "type": "Feature",
  "properties": {
    "addr:full":"4560 Atwater Ct Ste 108 Buford GA 30518",
    "addr:housenumber":"4560",
    "addr:postcode":"30518",
    "addr:street":"Atwater Ct Ste 108",
    "iso:country":"US",
    "sg:address":"4560 Atwater Ct Ste 108",
    "sg:city":"Buford",
    "sg:classifiers":[
        {
            "category":"Wholesale",
            "subcategory":"Computers",
            "type":"Manufacturing & Wholesale Goods"
        },
        {
            "category":"Professional",
            "subcategory":"Computer Services",
            "type":"Services"
        }
    ],
    "sg:phone":"+1 678 528 1654",
    "sg:postcode":"30518",
    "sg:province":"GA",
    "sg:tags":[
        "repair"
    ],
    "sg:website":"www.mobiledepotinc.com",
    "wof:name":"Mobile Depot",
    "wof:placetype":"venue"
},
  "geometry": {"coordinates":[-84.01546399999999,34.101398],"type":"Point"}
}