{
  "type": "Feature",
  "properties": {
    "iso:country":"US",
    "sg:address":"24 Latimer Ln",
    "sg:city":"Kennesaw",
    "sg:classifiers":[
        {
            "category":"Wholesale",
            "subcategory":"Groceries",
            "type":"Manufacturing & Wholesale Goods"
        }
    ],
    "sg:phone":"+1 770 429 8193",
    "sg:postcode":"30144",
    "sg:province":"GA",
    "sg:tags":[
        "food",
        "broker"
    ],
    "wof:name":"Silver Star Wholesale Inc",
    "wof:placetype":"venue"
},
  "geometry": {"coordinates":[-84.54672100000001,34.065091],"type":"Point"}
}