{
  "type": "Feature",
  "properties": {
    "iso:country":"US",
    "sg:address":"1910 State Rte 20",
    "sg:city":"Conyers",
    "sg:classifiers":[
        {
            "category":"Utilities",
            "subcategory":"Mobile Phone",
            "type":"Services"
        }
    ],
    "sg:phone":"+1 770 922 2355",
    "sg:postcode":"30013",
    "sg:province":"GA",
    "sg:tags":[
        "telephone",
        "cellular"
    ],
    "wof:name":"Cellular Wireless",
    "wof:placetype":"venue"
},
  "geometry": {"coordinates":[-84.014274,33.640433],"type":"Point"}
}