{
  "type": "Feature",
  "properties": {
    "addr:full":"355 Balboa Ct NE Atlanta GA 30342",
    "addr:housenumber":"355",
    "addr:postcode":"30342",
    "addr:street":"Balboa Ct Ne",
    "iso:country":"US",
    "sg:address":"355 Balboa Ct NE",
    "sg:city":"Atlanta",
    "sg:classifiers":[
        {
            "category":"Professional",
            "subcategory":"Management & Consulting",
            "type":"Services"
        }
    ],
    "sg:phone":"+1 404 256 0028",
    "sg:postcode":"30342",
    "sg:province":"GA",
    "sg:tags":[
        "consultant",
        "business"
    ],
    "wof:name":"Pamela Zendt Consulting Inc",
    "wof:placetype":"venue"
},
  "geometry": {"coordinates":[-84.365887,33.899733],"type":"Point"}
}