{
  "type": "Feature",
  "properties": {
    "addr:full":"1391 Normandy Dr NE Atlanta GA 30306",
    "addr:housenumber":"1391",
    "addr:postcode":"30306",
    "addr:street":"Normandy Dr Ne",
    "iso:country":"US",
    "sg:address":"1391 Normandy Dr NE",
    "sg:city":"Atlanta",
    "sg:classifiers":[
        {
            "category":"Communications",
            "subcategory":"Film & Video Production",
            "type":"Services"
        }
    ],
    "sg:phone":"+1 404 876 8894",
    "sg:postcode":"30306",
    "sg:province":"GA",
    "sg:tags":[
        "motion"
    ],
    "wof:name":"Selk Production Audio Inc",
    "wof:placetype":"venue"
},
  "geometry": {"coordinates":[-84.344154,33.786541],"type":"Point"}
}