{
  "type": "Feature",
  "properties": {
    "addr:full":"2448 Lumpkin Rd Augusta GA 30906",
    "addr:housenumber":"2448",
    "addr:postcode":"30906",
    "addr:street":"Lumpkin Rd",
    "iso:country":"US",
    "sg:address":"2448 Lumpkin Rd",
    "sg:city":"Augusta",
    "sg:classifiers":[
        {
            "category":"Real Estate",
            "subcategory":"Real Estate Agent",
            "type":"Services"
        }
    ],
    "sg:phone":"+1 706 796 0106",
    "sg:postcode":"30906",
    "sg:province":"GA",
    "sg:website":"www.century21jk.com",
    "wof:name":"Jeff Keller Realty Co",
    "wof:placetype":"venue"
},
  "geometry": {"coordinates":[-82.041056,33.420687],"type":"Point"}
}