{
  "type": "Feature",
  "properties": {
    "addr:full":"2600 Century Pkwy NE Ste 100 Atlanta GA 30345",
    "addr:housenumber":"2600",
    "addr:postcode":"30345",
    "addr:street":"Century Pkwy Ne Ste 100",
    "iso:country":"US",
    "sg:address":"2600 Century Pkwy NE Ste 100",
    "sg:city":"Atlanta",
    "sg:classifiers":[
        {
            "category":"Professional",
            "subcategory":"Lawyer & Legal Services",
            "type":"Services"
        }
    ],
    "sg:phone":"+1 404 325 9100",
    "sg:postcode":"30345",
    "sg:province":"GA",
    "sg:tags":[
        "divorce",
        "law",
        "family"
    ],
    "wof:name":"Hardaman Donna M",
    "wof:placetype":"venue"
},
  "geometry": {"coordinates":[-84.305408,33.848216],"type":"Point"}
}