{
  "type": "Feature",
  "properties": {
    "addr:full":"10270 Medlock Bridge Rd Duluth GA 30097",
    "addr:housenumber":"10270",
    "addr:postcode":"30097",
    "addr:street":"Medlock Bridge Rd",
    "iso:country":"US",
    "sg:address":"10270 Medlock Bridge Rd",
    "sg:city":"Duluth",
    "sg:classifiers":[
        {
            "category":"Restaurant",
            "type":"Food & Drink"
        }
    ],
    "sg:phone":"+1 770 476 1766",
    "sg:postcode":"30097",
    "sg:province":"GA",
    "sg:website":"www.jrsloghouse.com",
    "wof:name":"J R's Log House Restaurant",
    "wof:placetype":"venue"
},
  "geometry": {"coordinates":[-84.186181,34.032692],"type":"Point"}
}