{
  "type": "Feature",
  "properties": {
    "addr:full":"1290 S Houston Lake Rd Warner Robins GA 31088",
    "addr:housenumber":"1290",
    "addr:postcode":"31088",
    "addr:street":"S Houston Lake Rd",
    "iso:country":"US",
    "sg:address":"1290 S Houston Lake Rd",
    "sg:city":"Warner Robins",
    "sg:classifiers":[
        {
            "category":"Banks & Credit Unions",
            "subcategory":"Bank",
            "type":"Services"
        },
        {
            "category":"Banks & Credit Unions",
            "subcategory":"Financial Services",
            "type":"Services"
        }
    ],
    "sg:phone":"+1 478 987 1009",
    "sg:postcode":"31088",
    "sg:province":"GA",
    "sg:tags":[
        "broker",
        "mortgage"
    ],
    "wof:name":"Colony Bank of Houston County",
    "wof:placetype":"venue"
},
  "geometry": {"coordinates":[-83.6623,32.557999],"type":"Point"}
}