{
  "type": "Feature",
  "properties": {
    "iso:country":"US",
    "sg:address":"2445 Doubletree Dr",
    "sg:city":"Acworth",
    "sg:classifiers":[
        {
            "category":"Building & Trades",
            "subcategory":"Construction",
            "type":"Services"
        }
    ],
    "sg:phone":"+1 770 917 1684",
    "sg:postcode":"30102",
    "sg:province":"GA",
    "sg:tags":[
        "repairing",
        "remodeling",
        "contractor"
    ],
    "wof:name":"Mustard Seed Renovations Inc",
    "wof:placetype":"venue"
},
  "geometry": {"coordinates":[-84.615028,34.076567],"type":"Point"}
}