{
  "type": "Feature",
  "properties": {
    "addr:full":"1085 Norwalk Trce Lawrenceville GA 30043",
    "addr:housenumber":"1085",
    "addr:postcode":"30043",
    "addr:street":"Norwalk Trce",
    "iso:country":"US",
    "sg:address":"1085 Norwalk Trce",
    "sg:city":"Lawrenceville",
    "sg:classifiers":[
        {
            "category":"Food & Beverages",
            "subcategory":"Ethnic Foods",
            "type":"Retail Goods"
        }
    ],
    "sg:phone":"+1 770 338 0252",
    "sg:postcode":"30043",
    "sg:province":"GA",
    "sg:tags":[
        "grocers-ethnic"
    ],
    "wof:name":"Thorntons Cultural Creations",
    "wof:placetype":"venue"
},
  "geometry": {"coordinates":[-83.976653,33.997483],"type":"Point"}
}