{
  "type": "Feature",
  "properties": {
    "addr:full":"721 Knight Ave Waycross GA 31501",
    "addr:housenumber":"721",
    "addr:postcode":"31501",
    "addr:street":"Knight Ave",
    "iso:country":"US",
    "sg:address":"721 Knight Ave",
    "sg:city":"Waycross",
    "sg:classifiers":[
        {
            "category":"Wholesale",
            "subcategory":"Machinery & Supplies",
            "type":"Manufacturing & Wholesale Goods"
        }
    ],
    "sg:phone":"+1 912 283 5583",
    "sg:postcode":"31501",
    "sg:province":"GA",
    "sg:tags":[
        "equipment",
        "hydraulic"
    ],
    "wof:name":"Equipment South Inc",
    "wof:placetype":"venue"
},
  "geometry": {"coordinates":[-82.34269500000001,31.209841],"type":"Point"}
}