{
  "type": "Feature",
  "properties": {
    "addr:full":"2855 Emerald Ln Acworth GA 30102",
    "addr:housenumber":"2855",
    "addr:postcode":"30102",
    "addr:street":"Emerald Ln",
    "iso:country":"US",
    "sg:address":"2855 Emerald Ln",
    "sg:city":"Acworth",
    "sg:classifiers":[
        {
            "category":"Professional",
            "subcategory":"Employment Agencies",
            "type":"Services"
        }
    ],
    "sg:phone":"+1 770 974 8453",
    "sg:postcode":"30102",
    "sg:province":"GA",
    "sg:tags":[
        "help",
        "supply"
    ],
    "wof:name":"Rcr Trucking Inc",
    "wof:placetype":"venue"
},
  "geometry": {"coordinates":[-84.63611899999999,34.087925],"type":"Point"}
}