{
  "type": "Feature",
  "properties": {
    "iso:country":"US",
    "sg:address":"39 Boulevard NE",
    "sg:city":"Atlanta",
    "sg:classifiers":[
        {
            "category":"Park",
            "type":"Public Place"
        }
    ],
    "sg:phone":"+1 404 525 7557",
    "sg:postcode":"30312",
    "sg:province":"GA",
    "wof:name":"Eastern National Monument Association",
    "wof:placetype":"venue"
},
  "geometry": {"coordinates":[-84.37226,33.755216],"type":"Point"}
}