{
  "type": "Feature",
  "properties": {
    "addr:full":"2726 Watson Blvd Warner Robins GA 31093",
    "addr:housenumber":"2726",
    "addr:postcode":"31093",
    "addr:street":"Watson Blvd",
    "iso:country":"US",
    "sg:address":"2726 Watson Blvd",
    "sg:city":"Warner Robins",
    "sg:classifiers":[
        {
            "category":"Shopping",
            "subcategory":"Stationery & Office Supplies",
            "type":"Retail Goods"
        }
    ],
    "sg:phone":"+1 478 971 1574",
    "sg:postcode":"31093",
    "sg:province":"GA",
    "sg:tags":[
        "equipment"
    ],
    "sg:website":"www.staples.com",
    "wof:name":"Staples the Office Superstore",
    "wof:placetype":"venue"
},
  "geometry": {"coordinates":[-83.67089799999999,32.618401],"type":"Point"}
}