{
  "type": "Feature",
  "properties": {
    "addr:full":"1821 Plum St Valdosta GA 31601",
    "addr:housenumber":"1821",
    "addr:postcode":"31601",
    "addr:street":"Plum St",
    "iso:country":"US",
    "sg:address":"1821 Plum St",
    "sg:city":"Valdosta",
    "sg:classifiers":[
        {
            "category":"Personal",
            "subcategory":"Beauty Salon",
            "type":"Services"
        }
    ],
    "sg:phone":"+1 229 244 7040",
    "sg:postcode":"31601",
    "sg:province":"GA",
    "wof:name":"Bedazzled Salon",
    "wof:placetype":"venue"
},
  "geometry": {"coordinates":[-83.30785,30.845702],"type":"Point"}
}