{
  "type": "Feature",
  "properties": {
    "addr:full":"4021 Fambrough Dr Powder Springs GA 30127",
    "addr:housenumber":"4021",
    "addr:postcode":"30127",
    "addr:street":"Fambrough Dr",
    "iso:country":"US",
    "sg:address":"4021 Fambrough Dr",
    "sg:city":"Powder Springs",
    "sg:classifiers":[
        {
            "category":"Building & Trades",
            "subcategory":"Construction",
            "type":"Services"
        }
    ],
    "sg:phone":"+1 770 439 9451",
    "sg:postcode":"30127",
    "sg:province":"GA",
    "sg:tags":[
        "fabricator",
        "product",
        "finisher",
        "metal",
        "architectural"
    ],
    "wof:name":"Custom Architectural Design",
    "wof:placetype":"venue"
},
  "geometry": {"coordinates":[-84.704173,33.877428],"type":"Point"}
}