{
  "type": "Feature",
  "properties": {
    "addr:full":"115 W Peachtree Place NW Atlanta GA 30313",
    "addr:housenumber":"115",
    "addr:postcode":"30313",
    "addr:street":"W Peachtree Place Nw",
    "iso:country":"US",
    "sg:address":"115 W Peachtree Place NW",
    "sg:city":"Atlanta",
    "sg:classifiers":[
        {
            "category":"Banks & Credit Unions",
            "subcategory":"Financial Services",
            "type":"Services"
        }
    ],
    "sg:phone":"+1 404 524 1111",
    "sg:postcode":"30313",
    "sg:province":"GA",
    "sg:tags":[
        "broker",
        "mortgage"
    ],
    "sg:website":"www.sharpemtg.com",
    "wof:name":"Sharpe Mortgage Lending Services Of Georgia",
    "wof:placetype":"venue"
},
  "geometry": {"coordinates":[-84.39103799999999,33.764028],"type":"Point"}
}