{
  "type": "Feature",
  "properties": {
    "iso:country":"US",
    "sg:address":"502 Russell Pkwy",
    "sg:city":"Warner Robins",
    "sg:classifiers":[
        {
            "category":"Retail",
            "subcategory":"Repair Shop",
            "type":"Services"
        }
    ],
    "sg:phone":"+1 478 464 0119",
    "sg:postcode":"31088",
    "sg:province":"GA",
    "sg:tags":[
        "sporting"
    ],
    "wof:name":"Ardvarks Arms",
    "wof:placetype":"venue"
},
  "geometry": {"coordinates":[-83.631726,32.593993],"type":"Point"}
}