{
  "type": "Feature",
  "properties": {
    "addr:full":"1723 Braselton Hwy Lawrenceville GA 30043",
    "addr:housenumber":"1723",
    "addr:postcode":"30043",
    "addr:street":"Braselton Hwy",
    "iso:country":"US",
    "sg:address":"1723 Braselton Hwy",
    "sg:city":"Lawrenceville",
    "sg:classifiers":[
        {
            "category":"Professional",
            "subcategory":"Management & Consulting",
            "type":"Services"
        }
    ],
    "sg:phone":"+1 678 985 5844",
    "sg:postcode":"30043",
    "sg:province":"GA",
    "wof:name":"Fsa Special Market Consultants",
    "wof:placetype":"venue"
},
  "geometry": {"coordinates":[-83.960818,34.028846],"type":"Point"}
}