{
  "type": "Feature",
  "properties": {
    "addr:full":"4666 Kellogg Dr SW Lilburn GA 30047",
    "addr:housenumber":"4666",
    "addr:postcode":"30047",
    "addr:street":"Kellogg Dr Sw",
    "iso:country":"US",
    "sg:address":"4666 Kellogg Dr SW",
    "sg:city":"Lilburn",
    "sg:classifiers":[
        {
            "category":"Building & Trades",
            "subcategory":"Construction",
            "type":"Services"
        }
    ],
    "sg:phone":"+1 770 972 9359",
    "sg:postcode":"30047",
    "sg:province":"GA",
    "sg:tags":[
        "carpentry",
        "contractor"
    ],
    "wof:name":"Jack Andrew Burrow",
    "wof:placetype":"venue"
},
  "geometry": {"coordinates":[-84.10003500000001,33.84344],"type":"Point"}
}