{
  "type": "Feature",
  "properties": {
    "addr:full":"1720 Stoney Brook Way Alpharetta GA 30005",
    "addr:housenumber":"1720",
    "addr:postcode":"30005",
    "addr:street":"Stoney Brook Way",
    "iso:country":"US",
    "sg:address":"1720 Stoney Brook Way",
    "sg:city":"Alpharetta",
    "sg:classifiers":[
        {
            "category":"Manufacturing",
            "subcategory":"Apparel",
            "type":"Manufacturing & Wholesale Goods"
        }
    ],
    "sg:phone":"+1 770 888 6453",
    "sg:postcode":"30005",
    "sg:province":"GA",
    "sg:tags":[
        "mfg"
    ],
    "wof:name":"Something Special",
    "wof:placetype":"venue"
},
  "geometry": {"coordinates":[-84.192108,34.095544],"type":"Point"}
}