{
  "type": "Feature",
  "properties": {
    "iso:country":"US",
    "sg:address":"3665 Riley Rd",
    "sg:city":"Douglasville",
    "sg:classifiers":[
        {
            "category":"Professional",
            "subcategory":"Computer Services",
            "type":"Services"
        }
    ],
    "sg:phone":"+1 404 213 7619",
    "sg:postcode":"30134",
    "sg:province":"GA",
    "sg:tags":[
        "related"
    ],
    "wof:name":"Berryman Groupcom",
    "wof:placetype":"venue"
},
  "geometry": {"coordinates":[-84.693326,33.780145],"type":"Point"}
}