{
  "type": "Feature",
  "properties": {
    "addr:full":"2765 Bankers Industrial Dr Atlanta GA 30360",
    "addr:postcode":"2765;30360",
    "addr:street":"Industrial Dr",
    "iso:country":"US",
    "sg:address":"2765 Bankers Industrial Dr",
    "sg:city":"Atlanta",
    "sg:classifiers":[
        {
            "category":"Home & Garden",
            "subcategory":"Building Materials",
            "type":"Retail Goods"
        }
    ],
    "sg:phone":"+1 770 209 9190",
    "sg:postcode":"30360",
    "sg:province":"GA",
    "sg:tags":[
        "insulation",
        "heat"
    ],
    "sg:website":"www.bayinsulationmbi.com",
    "wof:name":"Bay Insulation Of Georgia",
    "wof:placetype":"venue"
},
  "geometry": {"coordinates":[-84.26305600000001,33.92445],"type":"Point"}
}