{
  "type": "Feature",
  "properties": {
    "addr:full":"550 Grosso Ave Macon GA 31204",
    "addr:housenumber":"550",
    "addr:postcode":"31204",
    "addr:street":"Grosso Ave",
    "iso:country":"US",
    "sg:address":"550 Grosso Ave",
    "sg:city":"Macon",
    "sg:classifiers":[
        {
            "category":"Restaurant",
            "type":"Food & Drink"
        }
    ],
    "sg:menulink":"http://www.allmenus.com/ga/macon/203358-mcdonalds/menu/",
    "sg:postcode":"31204",
    "sg:province":"GA",
    "sg:tags":[
        "burger",
        "american"
    ],
    "wof:name":"McDonald's",
    "wof:placetype":"venue"
},
  "geometry": {"coordinates":[-83.67049,32.82492],"type":"Point"}
}