{
  "type": "Feature",
  "properties": {
    "addr:full":"1104 S Madison St Albany GA 31701",
    "addr:housenumber":"1104",
    "addr:postcode":"31701",
    "addr:street":"S Madison St",
    "iso:country":"US",
    "sg:address":"1104 S Madison St",
    "sg:city":"Albany",
    "sg:classifiers":[
        {
            "category":"Retail",
            "subcategory":"Laundry & Dry Cleaning",
            "type":"Services"
        }
    ],
    "sg:phone":"+1 229 888 1378",
    "sg:postcode":"31701",
    "sg:province":"GA",
    "sg:tags":[
        "garment",
        "agent"
    ],
    "wof:name":"Six Point Dry Cleaners",
    "wof:placetype":"venue"
},
  "geometry": {"coordinates":[-84.161829,31.562707],"type":"Point"}
}