{
  "type": "Feature",
  "properties": {
    "addr:full":"1099 Colony Cir Marietta GA 30068",
    "addr:housenumber":"1099",
    "addr:postcode":"30068",
    "addr:street":"Colony Cir",
    "iso:country":"US",
    "sg:address":"1099 Colony Cir",
    "sg:city":"Marietta",
    "sg:classifiers":[
        {
            "category":"Professional",
            "subcategory":"Computer Services",
            "type":"Services"
        }
    ],
    "sg:phone":"+1 770 993 1292",
    "sg:postcode":"30068",
    "sg:province":"GA",
    "sg:tags":[
        "equipment",
        "electronics",
        "leasing"
    ],
    "wof:name":"Cashline",
    "wof:placetype":"venue"
},
  "geometry": {"coordinates":[-84.403336,33.976465],"type":"Point"}
}