{
  "type": "Feature",
  "properties": {
    "addr:full":"2597 Brookhaven Chase Ln NE Atlanta GA 30319",
    "addr:housenumber":"2597",
    "addr:postcode":"30319",
    "addr:street":"Brookhaven Chase Ln Ne",
    "iso:country":"US",
    "sg:address":"2597 Brookhaven Chase Ln NE",
    "sg:city":"Atlanta",
    "sg:classifiers":[
        {
            "category":"Professional",
            "subcategory":"Business Services",
            "type":"Services"
        }
    ],
    "sg:phone":"+1 404 240 0160",
    "sg:postcode":"30319",
    "sg:province":"GA",
    "sg:tags":[
        "holding"
    ],
    "wof:name":"Mra Signature Holdings",
    "wof:placetype":"venue"
},
  "geometry": {"coordinates":[-84.339091,33.856201],"type":"Point"}
}