{
  "type": "Feature",
  "properties": {
    "addr:full":"762 W Spring St Monroe GA 30655",
    "addr:housenumber":"762",
    "addr:postcode":"30655",
    "addr:street":"W Spring St",
    "iso:country":"US",
    "sg:address":"762 W Spring St",
    "sg:city":"Monroe",
    "sg:classifiers":[
        {
            "category":"Restaurant",
            "type":"Food & Drink"
        }
    ],
    "sg:phone":"+1 770 207 7717",
    "sg:postcode":"30655",
    "sg:province":"GA",
    "sg:tags":[
        "eating"
    ],
    "wof:name":"Hong Kong Kitchen",
    "wof:placetype":"venue"
},
  "geometry": {"coordinates":[-83.727289,33.793684],"type":"Point"}
}