{
  "type": "Feature",
  "properties": {
    "addr:full":"2880 Margaret Mitchell Dr NW Atlanta GA 30327",
    "addr:housenumber":"2880",
    "addr:postcode":"30327",
    "addr:street":"Margaret Mitchell Dr Nw",
    "iso:country":"US",
    "sg:address":"2880 Margaret Mitchell Dr NW",
    "sg:city":"Atlanta",
    "sg:classifiers":[
        {
            "category":"Professional",
            "subcategory":"Business Services",
            "type":"Services"
        }
    ],
    "sg:phone":"+1 404 352 0956",
    "sg:postcode":"30327",
    "sg:province":"GA",
    "wof:name":"Snob Inc",
    "wof:placetype":"venue"
},
  "geometry": {"coordinates":[-84.435627,33.834113],"type":"Point"}
}