{
  "type": "Feature",
  "properties": {
    "iso:country":"US",
    "sg:address":"6365 Rockbridge Rd",
    "sg:city":"Stone Mountain",
    "sg:classifiers":[
        {
            "category":"Building & Trades",
            "subcategory":"Construction",
            "type":"Services"
        }
    ],
    "sg:phone":"+1 770 469 4757",
    "sg:postcode":"30087",
    "sg:province":"GA",
    "sg:tags":[
        "steel",
        "erection",
        "structural"
    ],
    "wof:name":"Cowart Steel Erectors",
    "wof:placetype":"venue"
},
  "geometry": {"coordinates":[-84.13712200000001,33.785891],"type":"Point"}
}