{
  "type": "Feature",
  "properties": {
    "addr:full":"130 Steeple Ct Fayetteville GA 30214",
    "addr:housenumber":"130",
    "addr:postcode":"30214",
    "addr:street":"Steeple Ct",
    "iso:country":"US",
    "sg:address":"130 Steeple Ct",
    "sg:city":"Fayetteville",
    "sg:classifiers":[
        {
            "category":"Organizations",
            "subcategory":"Membership Organization",
            "type":"Services"
        }
    ],
    "sg:phone":"+1 770 460 6290",
    "sg:postcode":"30214",
    "sg:province":"GA",
    "wof:name":"Fayette County Art Association",
    "wof:placetype":"venue"
},
  "geometry": {"coordinates":[-84.432039,33.478238],"type":"Point"}
}