{
  "type": "Feature",
  "properties": {
    "addr:full":"11940 Alpharetta Hwy Alpharetta GA 30004",
    "addr:housenumber":"11940",
    "addr:postcode":"30004",
    "addr:street":"Alpharetta Hwy",
    "iso:country":"US",
    "sg:address":"11940 Alpharetta Hwy",
    "sg:city":"Alpharetta",
    "sg:classifiers":[
        {
            "category":"Professional",
            "type":"Services"
        }
    ],
    "sg:phone":"+1 770 664 1064",
    "sg:postcode":"30004",
    "sg:province":"GA",
    "sg:tags":[
        "caterer"
    ],
    "wof:name":"A Dish In A Dash Catering Company",
    "wof:placetype":"venue"
},
  "geometry": {"coordinates":[-84.31379699999999,34.066299],"type":"Point"}
}