{
  "type": "Feature",
  "properties": {
    "iso:country":"US",
    "sg:address":"2251 Old Cornelia Hwy",
    "sg:city":"Gainesville",
    "sg:classifiers":[
        {
            "category":"Freight",
            "type":"Transportation"
        }
    ],
    "sg:phone":"+1 770 287 8490",
    "sg:postcode":"30507",
    "sg:province":"GA",
    "sg:tags":[
        "trucking"
    ],
    "sg:website":"www.turbocorp.com",
    "wof:name":"Turbo Transport",
    "wof:placetype":"venue"
},
  "geometry": {"coordinates":[-83.783365,34.313755],"type":"Point"}
}