{
  "type": "Feature",
  "properties": {
    "addr:full":"5565 Mill Trace Court Atlanta GA 30338",
    "addr:housenumber":"5565",
    "addr:postcode":"30338",
    "addr:street":"Mill Trace Court",
    "iso:country":"US",
    "sg:address":"5565 Mill Trace Court",
    "sg:city":"Atlanta",
    "sg:classifiers":[
        {
            "category":"Sports & Exercise",
            "subcategory":"Sports Center",
            "type":"Entertainment"
        },
        {
            "category":"Arena",
            "subcategory":"Sports Club",
            "type":"Entertainment"
        }
    ],
    "sg:phone":"+1 770 393 9132",
    "sg:postcode":"30338",
    "sg:province":"GA",
    "sg:tags":[
        "professional",
        "amateur",
        "team"
    ],
    "wof:name":"Mill Glen Swim & Tennis Club",
    "wof:placetype":"venue"
},
  "geometry": {"coordinates":[-84.332505,33.965019],"type":"Point"}
}