{
  "type": "Feature",
  "properties": {
    "addr:full":"635 Main St SW Gainesville GA 30501",
    "addr:housenumber":"635",
    "addr:postcode":"30501",
    "addr:street":"Main St Sw",
    "iso:country":"US",
    "sg:address":"635 Main St SW",
    "sg:city":"Gainesville",
    "sg:classifiers":[
        {
            "category":"Health Services",
            "subcategory":"Clinic",
            "type":"Services"
        },
        {
            "category":"Community Center",
            "type":"Public Place"
        }
    ],
    "sg:phone":"+1 770 503 0049",
    "sg:postcode":"30501",
    "sg:province":"GA",
    "sg:tags":[
        "medical"
    ],
    "wof:name":"Urgent",
    "wof:placetype":"venue"
},
  "geometry": {"coordinates":[-83.824264,34.294865],"type":"Point"}
}