{
  "type": "Feature",
  "properties": {
    "iso:country":"US",
    "sg:address":"848 Mayson Turner Rd NW",
    "sg:city":"Atlanta",
    "sg:classifiers":[
        {
            "category":"Restaurant",
            "type":"Food & Drink"
        }
    ],
    "sg:phone":"+1 404 523 4001",
    "sg:postcode":"30314",
    "sg:province":"GA",
    "sg:tags":[
        "eating"
    ],
    "wof:name":"Sweet Pie N Buy",
    "wof:placetype":"venue"
},
  "geometry": {"coordinates":[-84.415425,33.754915],"type":"Point"}
}