{
  "type": "Feature",
  "properties": {
    "addr:full":"1833 Rock Chapel Rd Lithonia GA 30058",
    "addr:housenumber":"1833",
    "addr:postcode":"30058",
    "addr:street":"Rock Chapel Rd",
    "iso:country":"US",
    "sg:address":"1833 Rock Chapel Rd",
    "sg:city":"Lithonia",
    "sg:classifiers":[
        {
            "category":"Retail",
            "subcategory":"Auto Repair",
            "type":"Services"
        }
    ],
    "sg:phone":"+1 770 482 2173",
    "sg:postcode":"30058",
    "sg:province":"GA",
    "wof:name":"Diverse Movement",
    "wof:placetype":"venue"
},
  "geometry": {"coordinates":[-84.086327,33.737727],"type":"Point"}
}