{
  "type": "Feature",
  "properties": {
    "iso:country":"US",
    "sg:address":"1289 S Hairston Rd",
    "sg:city":"Stone Mountain",
    "sg:classifiers":[
        {
            "category":"Insurance",
            "subcategory":"Insurance Agent",
            "type":"Services"
        }
    ],
    "sg:phone":"+1 770 987 2288",
    "sg:postcode":"30088",
    "sg:province":"GA",
    "wof:name":"Copper Insurance Inc",
    "wof:placetype":"venue"
},
  "geometry": {"coordinates":[-84.196837,33.760941],"type":"Point"}
}