{
  "type": "Feature",
  "properties": {
    "addr:full":"100 Lyons Rd Athens GA 30605",
    "addr:housenumber":"100",
    "addr:postcode":"30605",
    "addr:street":"Lyons Rd",
    "iso:country":"US",
    "sg:address":"100 Lyons Rd",
    "sg:city":"Athens",
    "sg:classifiers":[
        {
            "category":"Building & Trades",
            "subcategory":"Plumbing",
            "type":"Services"
        }
    ],
    "sg:phone":"+1 706 546 1810",
    "sg:postcode":"30605",
    "sg:province":"GA",
    "sg:tags":[
        "system",
        "contractor",
        "air conditioning"
    ],
    "wof:name":"D & D Heating & Air Conditioning Inc",
    "wof:placetype":"venue"
},
  "geometry": {"coordinates":[-83.324791,33.955448],"type":"Point"}
}