{
  "type": "Feature",
  "properties": {
    "addr:full":"800 1st St Macon GA 31201",
    "addr:housenumber":"800",
    "addr:postcode":"31201",
    "addr:street":"1St St",
    "iso:country":"US",
    "sg:address":"800 1st St",
    "sg:city":"Macon",
    "sg:classifiers":[
        {
            "category":"Professional",
            "subcategory":"Business Services",
            "type":"Services"
        }
    ],
    "sg:phone":"+1 478 751 9213",
    "sg:postcode":"31201",
    "sg:province":"GA",
    "wof:name":"Macon Fire Dept",
    "wof:placetype":"venue"
},
  "geometry": {"coordinates":[-83.63550499999999,32.831643],"type":"Point"}
}