{
  "type": "Feature",
  "properties": {
    "iso:country":"US",
    "sg:address":"933 Kirkwood Ave SE",
    "sg:city":"Atlanta",
    "sg:classifiers":[
        {
            "category":"Retail",
            "subcategory":"Auto Rental",
            "type":"Services"
        }
    ],
    "sg:phone":"+1 404 688 1805",
    "sg:postcode":"30316",
    "sg:province":"GA",
    "sg:tags":[
        "truck"
    ],
    "wof:name":"Southern Leasing & Supply",
    "wof:placetype":"venue"
},
  "geometry": {"coordinates":[-84.35668200000001,33.750202],"type":"Point"}
}