{
  "type": "Feature",
  "properties": {
    "addr:full":"8540 Roswell Road Atlanta GA 30350",
    "addr:housenumber":"8540",
    "addr:postcode":"30350",
    "addr:street":"Roswell Road",
    "iso:country":"US",
    "sg:address":"8540 Roswell Road",
    "sg:city":"Atlanta",
    "sg:classifiers":[
        {
            "category":"Bars & Pubs",
            "subcategory":"Lounge",
            "type":"Food & Drink"
        },
        {
            "category":"Restaurant",
            "type":"Food & Drink"
        },
        {
            "category":"Bars & Pubs",
            "type":"Food & Drink"
        }
    ],
    "sg:phone":"+1 770 587 3837",
    "sg:postcode":"30350",
    "sg:province":"GA",
    "sg:tags":[
        "pan",
        "cocktail",
        "chinese",
        "asian"
    ],
    "wof:name":"North Peking Chinese Restaurant",
    "wof:placetype":"venue"
},
  "geometry": {"coordinates":[-84.351041,33.987698],"type":"Point"}
}