{
  "type": "Feature",
  "properties": {
    "addr:full":"919 Chattahoochee Ave NW Atlanta GA 30318",
    "addr:housenumber":"919",
    "addr:postcode":"30318",
    "addr:street":"Chattahoochee Ave Nw",
    "iso:country":"US",
    "sg:address":"919 Chattahoochee Ave NW",
    "sg:city":"Atlanta",
    "sg:classifiers":[
        {
            "category":"Personal",
            "type":"Services"
        }
    ],
    "sg:phone":"+1 404 351 0992",
    "sg:postcode":"30318",
    "sg:province":"GA",
    "sg:tags":[
        "wear",
        "formal"
    ],
    "wof:name":"Colsar Formal Wear",
    "wof:placetype":"venue"
},
  "geometry": {"coordinates":[-84.437838,33.809884],"type":"Point"}
}