{
  "type": "Feature",
  "properties": {
    "iso:country":"US",
    "sg:address":"345 N Main St",
    "sg:city":"Boston",
    "sg:classifiers":[
        {
            "category":"Shopping",
            "subcategory":"Clothing, Apparel, & Fashions",
            "type":"Retail Goods"
        }
    ],
    "sg:phone":"+1 229 498 7590",
    "sg:postcode":"31626",
    "sg:province":"GA",
    "wof:name":"Kings & Queens Fashion Ect",
    "wof:placetype":"venue"
},
  "geometry": {"coordinates":[-83.789626,30.794874],"type":"Point"}
}