{
  "type": "Feature",
  "properties": {
    "iso:country":"US",
    "sg:address":"4902 Glenwhite Dr",
    "sg:city":"Duluth",
    "sg:classifiers":[
        {
            "category":"Shopping",
            "subcategory":"Computers & Home Electronics",
            "type":"Retail Goods"
        }
    ],
    "sg:phone":"+1 770 343 8780",
    "sg:postcode":"30096",
    "sg:province":"GA",
    "wof:name":"Burgess Information Systems",
    "wof:placetype":"venue"
},
  "geometry": {"coordinates":[-84.18089000000001,33.949121],"type":"Point"}
}