{
  "type": "Feature",
  "properties": {
    "addr:full":"80 Oak Hill Cir Covington GA 30016",
    "addr:housenumber":"80",
    "addr:postcode":"30016",
    "addr:street":"Oak Hill Cir",
    "iso:country":"US",
    "sg:address":"80 Oak Hill Cir",
    "sg:city":"Covington",
    "sg:classifiers":[
        {
            "category":"Utilities",
            "subcategory":"Refuse",
            "type":"Services"
        }
    ],
    "sg:phone":"+1 678 342 0094",
    "sg:postcode":"30016",
    "sg:province":"GA",
    "sg:tags":[
        "system"
    ],
    "wof:name":"Landfill Technologies Inc",
    "wof:placetype":"venue"
},
  "geometry": {"coordinates":[-83.96973300000001,33.545148],"type":"Point"}
}