{
  "type": "Feature",
  "properties": {
    "addr:full":"2000 Grove Point Rd Savannah GA 31419",
    "addr:housenumber":"2000",
    "addr:postcode":"31419",
    "addr:street":"Grove Point Rd",
    "iso:country":"US",
    "sg:address":"2000 Grove Point Rd",
    "sg:city":"Savannah",
    "sg:classifiers":[
        {
            "category":"Personal",
            "subcategory":"Beauty Salon",
            "type":"Services"
        }
    ],
    "sg:phone":"+1 912 921 0442",
    "sg:postcode":"31419",
    "sg:province":"GA",
    "sg:tags":[
        "shop"
    ],
    "wof:name":"Wynden Hair Resort",
    "wof:placetype":"venue"
},
  "geometry": {"coordinates":[-81.22183200000001,31.983665],"type":"Point"}
}