{
  "type": "Feature",
  "properties": {
    "addr:full":"2131 Rowland Ave Savannah GA 31404",
    "addr:housenumber":"2131",
    "addr:postcode":"31404",
    "addr:street":"Rowland Ave",
    "iso:country":"US",
    "sg:address":"2131 Rowland Ave",
    "sg:city":"Savannah",
    "sg:classifiers":[
        {
            "category":"Retail",
            "subcategory":"Laundry & Dry Cleaning",
            "type":"Services"
        }
    ],
    "sg:phone":"+1 912 351 6537",
    "sg:postcode":"31404",
    "sg:province":"GA",
    "sg:tags":[
        "cleaner",
        "rug",
        "carpet"
    ],
    "wof:name":"Performance Initiatives",
    "wof:placetype":"venue"
},
  "geometry": {"coordinates":[-81.06412899999999,32.039721],"type":"Point"}
}