{
  "type": "Feature",
  "properties": {
    "addr:full":"1303 Veterans Memorial Hwy SE Mableton GA 30126",
    "addr:housenumber":"1303",
    "addr:postcode":"30126",
    "addr:street":"Veterans Memorial Hwy Se",
    "iso:country":"US",
    "sg:address":"1303 Veterans Memorial Hwy SE",
    "sg:city":"Mableton",
    "sg:classifiers":[
        {
            "category":"Shopping",
            "subcategory":"Gifts & Souvenirs",
            "type":"Retail Goods"
        },
        {
            "category":"Professional",
            "subcategory":"Business Services",
            "type":"Services"
        },
        {
            "category":"Manufacturing",
            "subcategory":"Retail Goods",
            "type":"Manufacturing & Wholesale Goods"
        }
    ],
    "sg:phone":"+1 404 699 9699",
    "sg:postcode":"30126",
    "sg:province":"GA",
    "sg:tags":[
        "shop",
        "importer",
        "giftware's-wholesale",
        "manufacturer"
    ],
    "wof:name":"Us Wholesale Inc",
    "wof:placetype":"venue"
},
  "geometry": {"coordinates":[-84.518671,33.80181],"type":"Point"}
}