{
  "type": "Feature",
  "properties": {
    "iso:country":"US",
    "sg:address":"490 Six Flags Dr",
    "sg:city":"Austell",
    "sg:classifiers":[
        {
            "category":"Professional",
            "subcategory":"Business Services",
            "type":"Services"
        }
    ],
    "sg:phone":"+1 770 739 6632",
    "sg:postcode":"30168",
    "sg:province":"GA",
    "wof:name":"Kustum Design",
    "wof:placetype":"venue"
},
  "geometry": {"coordinates":[-84.569526,33.778065],"type":"Point"}
}