{
  "type": "Feature",
  "properties": {
    "addr:full":"6577 Peachtree Industrial Blvd Atlanta GA 30360",
    "addr:housenumber":"6577",
    "addr:postcode":"30360",
    "addr:street":"Peachtree Industrial Blvd",
    "iso:country":"US",
    "sg:address":"6577 Peachtree Industrial Blvd",
    "sg:city":"Atlanta",
    "sg:classifiers":[
        {
            "category":"Wholesale",
            "subcategory":"Chemicals & Plastics",
            "type":"Manufacturing & Wholesale Goods"
        }
    ],
    "sg:phone":"+1 770 448 6440",
    "sg:postcode":"30360",
    "sg:province":"GA",
    "sg:website":"www.mayzo.com",
    "wof:name":"Mayzo",
    "wof:placetype":"venue"
},
  "geometry": {"coordinates":[-84.27435800000001,33.926619],"type":"Point"}
}