{
  "type": "Feature",
  "properties": {
    "iso:country":"US",
    "sg:address":"4323 Seago Rd",
    "sg:city":"Hephzibah",
    "sg:classifiers":[
        {
            "category":"Farming",
            "subcategory":"Farm",
            "type":"Manufacturing & Wholesale Goods"
        }
    ],
    "sg:phone":"+1 706 414 0436",
    "sg:postcode":"30815",
    "sg:province":"GA",
    "wof:name":"Wildfire Farm",
    "wof:placetype":"venue"
},
  "geometry": {"coordinates":[-82.003699,33.303001],"type":"Point"}
}