{
  "type": "Feature",
  "properties": {
    "addr:full":"2841 Greenbriar Pkwy SW # 470 Atlanta GA 30331",
    "addr:housenumber":"2841",
    "addr:postcode":"30331",
    "addr:street":"Greenbriar Pkwy Sw # 470",
    "iso:country":"US",
    "sg:address":"2841 Greenbriar Pkwy SW # 470",
    "sg:city":"Atlanta",
    "sg:classifiers":[
        {
            "category":"Shopping",
            "subcategory":"Shoes",
            "type":"Retail Goods"
        }
    ],
    "sg:phone":"+1 404 629 0038",
    "sg:postcode":"30331",
    "sg:province":"GA",
    "sg:tags":[
        "store"
    ],
    "wof:name":"Greenbriar Mall Footaction Inc",
    "wof:placetype":"venue"
},
  "geometry": {"coordinates":[-84.489051,33.689626],"type":"Point"}
}