{
  "type": "Feature",
  "properties": {
    "iso:country":"US",
    "sg:address":"1060 Moreland Industrial Blvd SE",
    "sg:city":"Atlanta",
    "sg:classifiers":[
        {
            "category":"Utilities",
            "subcategory":"Refuse",
            "type":"Services"
        }
    ],
    "sg:phone":"+1 404 622 3389",
    "sg:postcode":"30316",
    "sg:province":"GA",
    "sg:tags":[
        "landfill"
    ],
    "wof:name":"Donzi Lane Landfill",
    "wof:placetype":"venue"
},
  "geometry": {"coordinates":[-84.347707,33.7099],"type":"Point"}
}