{
  "type": "Feature",
  "properties": {
    "iso:country":"US",
    "sg:address":"375 Rockbridge Rd NW",
    "sg:city":"Lilburn",
    "sg:classifiers":[
        {
            "category":"Building & Trades",
            "subcategory":"Construction",
            "type":"Services"
        }
    ],
    "sg:phone":"+1 678 321 6943",
    "sg:postcode":"30047",
    "sg:province":"GA",
    "sg:tags":[
        "contractor"
    ],
    "sg:website":"tilecontractorinlilburn.info/",
    "wof:name":"AG Tile Solutions",
    "wof:placetype":"venue"
},
  "geometry": {"coordinates":[-84.163858,33.883218],"type":"Point"}
}