{
  "type": "Feature",
  "properties": {
    "iso:country":"US",
    "sg:address":"712 Lincoln St",
    "sg:city":"Lagrange",
    "sg:classifiers":[
        {
            "category":"Personal",
            "subcategory":"Beauty Salon",
            "type":"Services"
        }
    ],
    "sg:phone":"+1 706 884 2000",
    "sg:postcode":"30240",
    "sg:province":"GA",
    "wof:name":"M & D II Beauty Salon",
    "wof:placetype":"venue"
},
  "geometry": {"coordinates":[-85.047989,33.026661],"type":"Point"}
}