{
  "type": "Feature",
  "properties": {
    "addr:full":"50 Milner St Temple GA 30179",
    "addr:housenumber":"50",
    "addr:postcode":"30179",
    "addr:street":"Milner St",
    "iso:country":"US",
    "sg:address":"50 Milner St",
    "sg:city":"Temple",
    "sg:classifiers":[
        {
            "category":"Recreation",
            "type":"Entertainment"
        }
    ],
    "sg:phone":"+1 770 562 3848",
    "sg:postcode":"30179",
    "sg:province":"GA",
    "sg:tags":[
        "center"
    ],
    "wof:name":"Recreational Department-Temple",
    "wof:placetype":"venue"
},
  "geometry": {"coordinates":[-85.03282799999999,33.741386],"type":"Point"}
}