{
  "type": "Feature",
  "properties": {
    "iso:country":"US",
    "sg:address":"1853 Hardman Ln",
    "sg:city":"Woodstock",
    "sg:classifiers":[
        {
            "category":"Social Services",
            "subcategory":"Child Care",
            "type":"Services"
        }
    ],
    "sg:phone":"+1 770 926 8474",
    "sg:postcode":"30188",
    "sg:province":"GA",
    "sg:tags":[
        "day"
    ],
    "wof:name":"Homestyle Child Care",
    "wof:placetype":"venue"
},
  "geometry": {"coordinates":[-84.405939,34.119178],"type":"Point"}
}