{
  "type": "Feature",
  "properties": {
    "iso:country":"US",
    "sg:address":"481 Buck Blvd SE",
    "sg:city":"Calhoun",
    "sg:classifiers":[
        {
            "category":"Professional",
            "type":"Services"
        }
    ],
    "sg:phone":"+1 706 624 0625",
    "sg:postcode":"30701",
    "sg:province":"GA",
    "wof:name":"Nancy Runkle",
    "wof:placetype":"venue"
},
  "geometry": {"coordinates":[-84.830386,34.500484],"type":"Point"}
}