{
  "type": "Feature",
  "properties": {
    "addr:full":"2526 Mount Vernon Rd Ste B Atlanta GA 30338",
    "addr:housenumber":"2526",
    "addr:postcode":"30338",
    "addr:street":"Mount Vernon Rd Ste B",
    "iso:country":"US",
    "sg:address":"2526 Mount Vernon Rd Ste B",
    "sg:city":"Atlanta",
    "sg:classifiers":[
        {
            "category":"Professional",
            "subcategory":"Lawyer & Legal Services",
            "type":"Services"
        }
    ],
    "sg:phone":"+1 770 730 0730",
    "sg:postcode":"30338",
    "sg:province":"GA",
    "sg:tags":[
        "notary"
    ],
    "wof:name":"Ups Store the",
    "wof:placetype":"venue"
},
  "geometry": {"coordinates":[-84.300849,33.958754],"type":"Point"}
}