{
  "type": "Feature",
  "properties": {
    "iso:country":"US",
    "sg:address":"1010 Millstone Ter",
    "sg:city":"Bogart",
    "sg:classifiers":[
        {
            "category":"Professional",
            "subcategory":"Advertising",
            "type":"Services"
        }
    ],
    "sg:phone":"+1 706 369 8614",
    "sg:postcode":"30622",
    "sg:province":"GA",
    "sg:tags":[
        "counselor"
    ],
    "wof:name":"Jaber Agency",
    "wof:placetype":"venue"
},
  "geometry": {"coordinates":[-83.483079,33.920895],"type":"Point"}
}