{
  "type": "Feature",
  "properties": {
    "addr:full":"314 Newnan St Carrollton GA 30117",
    "addr:housenumber":"314",
    "addr:postcode":"30117",
    "addr:street":"Newnan St",
    "iso:country":"US",
    "sg:address":"314 Newnan St",
    "sg:city":"Carrollton",
    "sg:classifiers":[
        {
            "category":"Retail",
            "subcategory":"Laundry & Dry Cleaning",
            "type":"Services"
        }
    ],
    "sg:phone":"+1 770 832 6366",
    "sg:postcode":"30117",
    "sg:province":"GA",
    "sg:tags":[
        "cleaners",
        "plant",
        "drycleaning"
    ],
    "wof:name":"J Carl Cleaners Inc",
    "wof:placetype":"venue"
},
  "geometry": {"coordinates":[-85.073269,33.579988],"type":"Point"}
}