{
  "type": "Feature",
  "properties": {
    "iso:country":"US",
    "sg:address":"112 Jackson Dr",
    "sg:city":"Valdosta",
    "sg:classifiers":[
        {
            "category":"Building & Trades",
            "subcategory":"Cleaning & Sanitation",
            "type":"Services"
        }
    ],
    "sg:phone":"+1 229 219 0696",
    "sg:postcode":"31601",
    "sg:province":"GA",
    "sg:tags":[
        "butler",
        "maid"
    ],
    "wof:name":"Saxton Unlimited",
    "wof:placetype":"venue"
},
  "geometry": {"coordinates":[-83.272626,30.812069],"type":"Point"}
}