{
  "type": "Feature",
  "properties": {
    "addr:full":"411 Maxham Rd Austell GA 30168",
    "addr:housenumber":"411",
    "addr:postcode":"30168",
    "addr:street":"Maxham Rd",
    "iso:country":"US",
    "sg:address":"411 Maxham Rd",
    "sg:city":"Austell",
    "sg:classifiers":[
        {
            "category":"Personal",
            "subcategory":"Nail Salon",
            "type":"Services"
        }
    ],
    "sg:phone":"+1 770 941 0308",
    "sg:postcode":"30168",
    "sg:province":"GA",
    "wof:name":"Atlanta Nails",
    "wof:placetype":"venue"
},
  "geometry": {"coordinates":[-84.620102,33.795601],"type":"Point"}
}