{
  "type": "Feature",
  "properties": {
    "addr:full":"245 Springwater Chase Newnan GA 30265",
    "addr:housenumber":"245",
    "addr:postcode":"30265",
    "addr:street":"Springwater Chase",
    "iso:country":"US",
    "sg:address":"245 Springwater Chase",
    "sg:city":"Newnan",
    "sg:classifiers":[
        {
            "category":"Building & Trades",
            "subcategory":"Construction",
            "type":"Services"
        }
    ],
    "sg:phone":"+1 770 304 1401",
    "sg:postcode":"30265",
    "sg:province":"GA",
    "sg:tags":[
        "nonresidential"
    ],
    "wof:name":"M Cubed Building Services",
    "wof:placetype":"venue"
},
  "geometry": {"coordinates":[-84.69646299999999,33.435505],"type":"Point"}
}