{
  "type": "Feature",
  "properties": {
    "iso:country":"US",
    "sg:address":"604 S Keeler Woods Dr NW",
    "sg:city":"Marietta",
    "sg:classifiers":[
        {
            "category":"Home & Garden",
            "subcategory":"Home Furnishings",
            "type":"Retail Goods"
        },
        {
            "category":"Restaurant",
            "type":"Food & Drink"
        }
    ],
    "sg:phone":"+1 770 424 7371",
    "sg:postcode":"30064",
    "sg:province":"GA",
    "sg:tags":[
        "utensil",
        "cooking",
        "eating"
    ],
    "wof:name":"Dinner Is Served Inc",
    "wof:placetype":"venue"
},
  "geometry": {"coordinates":[-84.570139,33.960675],"type":"Point"}
}