{
  "type": "Feature",
  "properties": {
    "iso:country":"US",
    "sg:address":"107 P Rickman Industrial Dr",
    "sg:city":"Canton",
    "sg:classifiers":[
        {
            "category":"Building & Trades",
            "subcategory":"Construction",
            "type":"Services"
        }
    ],
    "sg:phone":"+1 770 345 3777",
    "sg:postcode":"30115",
    "sg:province":"GA",
    "sg:tags":[
        "contractor"
    ],
    "wof:name":"Raytex Construction",
    "wof:placetype":"venue"
},
  "geometry": {"coordinates":[-84.49802099999999,34.177797],"type":"Point"}
}