{
  "type": "Feature",
  "properties": {
    "addr:full":"4650 Jimmy Carter Blvd Ste 127 Norcross GA 30093",
    "addr:housenumber":"4650",
    "addr:postcode":"30093",
    "addr:street":"Jimmy Carter Blvd Ste 127",
    "iso:country":"US",
    "sg:address":"4650 Jimmy Carter Blvd Ste 127",
    "sg:city":"Norcross",
    "sg:classifiers":[
        {
            "category":"Shopping",
            "subcategory":"Pawn Shop",
            "type":"Retail Goods"
        }
    ],
    "sg:phone":"+1 678 937 0480",
    "sg:postcode":"30093",
    "sg:province":"GA",
    "wof:name":"Value Pawn & Jewelry",
    "wof:placetype":"venue"
},
  "geometry": {"coordinates":[-84.192745,33.886041],"type":"Point"}
}