{
  "type": "Feature",
  "properties": {
    "iso:country":"US",
    "sg:address":"3202 State Rte 5",
    "sg:city":"Douglasville",
    "sg:classifiers":[
        {
            "category":"Restaurant",
            "type":"Food & Drink"
        }
    ],
    "sg:phone":"+1 770 949 0492",
    "sg:postcode":"30135",
    "sg:province":"GA",
    "sg:tags":[
        "eating"
    ],
    "sg:website":"www.chick-fil-a.com",
    "wof:name":"Chick-Fil-A",
    "wof:placetype":"venue"
},
  "geometry": {"coordinates":[-84.76546500000001,33.716996],"type":"Point"}
}