{
  "type": "Feature",
  "properties": {
    "iso:country":"US",
    "sg:address":"1603 Temperance Hall Rd",
    "sg:city":"Rock Spring",
    "sg:classifiers":[
        {
            "category":"Building & Trades",
            "subcategory":"Construction",
            "type":"Services"
        }
    ],
    "sg:phone":"+1 706 965 8914",
    "sg:postcode":"30739",
    "sg:province":"GA",
    "sg:tags":[
        "contractor"
    ],
    "wof:name":"Imagination Pools LLC",
    "wof:placetype":"venue"
},
  "geometry": {"coordinates":[-85.16677199999999,34.797525],"type":"Point"}
}