{
  "type": "Feature",
  "properties": {
    "addr:full":"324 W Parkwood Rd Decatur GA 30030",
    "addr:housenumber":"324",
    "addr:postcode":"30030",
    "addr:street":"W Parkwood Rd",
    "iso:country":"US",
    "sg:address":"324 W Parkwood Rd",
    "sg:city":"Decatur",
    "sg:classifiers":[
        {
            "category":"Building & Trades",
            "subcategory":"Construction",
            "type":"Services"
        }
    ],
    "sg:phone":"+1 404 377 8771",
    "sg:postcode":"30030",
    "sg:province":"GA",
    "sg:tags":[
        "general",
        "contractor"
    ],
    "wof:name":"Sterling Works LLC",
    "wof:placetype":"venue"
},
  "geometry": {"coordinates":[-84.314469,33.769297],"type":"Point"}
}