{
  "type": "Feature",
  "properties": {
    "addr:full":"1465 Holcomb Bridge Rd Roswell GA 30076",
    "addr:housenumber":"1465",
    "addr:postcode":"30076",
    "addr:street":"Holcomb Bridge Rd",
    "iso:country":"US",
    "sg:address":"1465 Holcomb Bridge Rd",
    "sg:city":"Roswell",
    "sg:classifiers":[
        {
            "category":"Food & Beverages",
            "subcategory":"Groceries & Convenience Stores",
            "type":"Retail Goods"
        }
    ],
    "sg:phone":"+1 678 585 7901",
    "sg:postcode":"30076",
    "sg:province":"GA",
    "wof:name":"Right Stuff Food Stores the",
    "wof:placetype":"venue"
},
  "geometry": {"coordinates":[-84.317902,34.020302],"type":"Point"}
}