{
  "type": "Feature",
  "properties": {
    "addr:full":"6590 Bannister Rd Cumming GA 30028",
    "addr:housenumber":"6590",
    "addr:postcode":"30028",
    "addr:street":"Bannister Rd",
    "iso:country":"US",
    "sg:address":"6590 Bannister Rd",
    "sg:city":"Cumming",
    "sg:classifiers":[
        {
            "category":"Manufacturing",
            "subcategory":"Pet Food",
            "type":"Manufacturing & Wholesale Goods"
        }
    ],
    "sg:phone":"+1 678 513 0454",
    "sg:postcode":"30028",
    "sg:province":"GA",
    "sg:tags":[
        "feed"
    ],
    "wof:name":"Ampro Products Inc",
    "wof:placetype":"venue"
},
  "geometry": {"coordinates":[-84.14230999999999,34.316932],"type":"Point"}
}