{
  "type": "Feature",
  "properties": {
    "addr:full":"3694 Union Ave Atlanta GA 30354",
    "addr:housenumber":"3694",
    "addr:postcode":"30354",
    "addr:street":"Union Ave",
    "iso:country":"US",
    "sg:address":"3694 Union Ave",
    "sg:city":"Atlanta",
    "sg:classifiers":[
        {
            "category":"Home & Garden",
            "subcategory":"Carpets & Floor Coverings",
            "type":"Retail Goods"
        }
    ],
    "sg:phone":"+1 404 768 4700",
    "sg:postcode":"30354",
    "sg:province":"GA",
    "sg:tags":[
        "vinyl"
    ],
    "wof:name":"Mid Atlantic Vinyl Products",
    "wof:placetype":"venue"
},
  "geometry": {"coordinates":[-84.408682,33.652499],"type":"Point"}
}