{
  "type": "Feature",
  "properties": {
    "iso:country":"US",
    "sg:address":"1570 Holcomb Bridge Rd",
    "sg:city":"Roswell",
    "sg:classifiers":[
        {
            "category":"Restaurant",
            "type":"Food & Drink"
        }
    ],
    "sg:menulink":"http://www.allmenus.com/ga/roswell-alpharetta/114019-dick-and-harrys/menu/",
    "sg:phone":"+1 770 641 8757",
    "sg:postcode":"30076",
    "sg:province":"GA",
    "sg:tags":[
        "american"
    ],
    "wof:name":"Dick And Harry's",
    "wof:placetype":"venue"
},
  "geometry": {"coordinates":[-84.314196,34.018845],"type":"Point"}
}