{
  "type": "Feature",
  "properties": {
    "addr:full":"1069 Atlanta Industrial Dr Marietta GA 30066",
    "addr:housenumber":"1069",
    "addr:postcode":"30066",
    "addr:street":"Atlanta Industrial Dr",
    "iso:country":"US",
    "sg:address":"1069 Atlanta Industrial Dr",
    "sg:city":"Marietta",
    "sg:classifiers":[
        {
            "category":"Manufacturing",
            "subcategory":"Paper Products",
            "type":"Manufacturing & Wholesale Goods"
        }
    ],
    "sg:phone":"+1 770 427 0162",
    "sg:postcode":"30066",
    "sg:province":"GA",
    "sg:tags":[
        "box",
        "paperboard",
        "mill",
        "folding",
        "mfg"
    ],
    "wof:name":"Low Paper",
    "wof:placetype":"venue"
},
  "geometry": {"coordinates":[-84.537845,33.981325],"type":"Point"}
}