{
  "type": "Feature",
  "properties": {
    "iso:country":"US",
    "sg:address":"38 N Williams St",
    "sg:city":"Hazlehurst",
    "sg:classifiers":[
        {
            "category":"Personal",
            "subcategory":"Beauty Salon",
            "type":"Services"
        }
    ],
    "sg:phone":"+1 912 375 2159",
    "sg:postcode":"31539",
    "sg:province":"GA",
    "sg:tags":[
        "shop"
    ],
    "wof:name":"Kountry Glamour",
    "wof:placetype":"venue"
},
  "geometry": {"coordinates":[-82.597146,31.87029],"type":"Point"}
}