{
  "type": "Feature",
  "properties": {
    "addr:full":"4175 Clairmont Rd Chamblee GA 30341",
    "addr:housenumber":"4175",
    "addr:postcode":"30341",
    "addr:street":"Clairmont Rd",
    "iso:country":"US",
    "sg:address":"4175 Clairmont Rd",
    "sg:city":"Chamblee",
    "sg:classifiers":[
        {
            "category":"Real Estate",
            "subcategory":"Real Estate Agent",
            "type":"Services"
        }
    ],
    "sg:phone":"+1 770 454 1000",
    "sg:postcode":"30341",
    "sg:province":"GA",
    "sg:website":"www.caseyandassociates.net",
    "wof:name":"Casey & Assoc Real Estate",
    "wof:placetype":"venue"
},
  "geometry": {"coordinates":[-84.30997000000001,33.885154],"type":"Point"}
}