{
  "type": "Feature",
  "properties": {
    "iso:country":"US",
    "sg:address":"306 Stonewall St NE",
    "sg:city":"Dawson",
    "sg:classifiers":[
        {
            "category":"Organizations",
            "subcategory":"Religious Organization",
            "type":"Services"
        }
    ],
    "sg:phone":"+1 229 995 2316",
    "sg:postcode":"39842",
    "sg:province":"GA",
    "sg:tags":[
        "church"
    ],
    "wof:name":"Dawson United Methodist Church",
    "wof:placetype":"venue"
},
  "geometry": {"coordinates":[-84.445318,31.776577],"type":"Point"}
}