{
  "type": "Feature",
  "properties": {
    "iso:country":"US",
    "sg:address":"7621 Rock Mountain Rd",
    "sg:city":"Lithonia",
    "sg:classifiers":[
        {
            "category":"Mining & Drilling",
            "type":"Manufacturing & Wholesale Goods"
        }
    ],
    "sg:phone":"+1 770 482 2396",
    "sg:postcode":"30058",
    "sg:province":"GA",
    "sg:tags":[
        "stone"
    ],
    "wof:name":"Lafarge Aggregates",
    "wof:placetype":"venue"
},
  "geometry": {"coordinates":[-84.077089,33.748219],"type":"Point"}
}