{
  "type": "Feature",
  "properties": {
    "addr:full":"7060 Mableton Pkwy SE Mableton GA 30126",
    "addr:housenumber":"7060",
    "addr:postcode":"30126",
    "addr:street":"Mableton Pkwy Se",
    "iso:country":"US",
    "sg:address":"7060 Mableton Pkwy SE",
    "sg:city":"Mableton",
    "sg:classifiers":[
        {
            "category":"Autos & Motor Vehicles",
            "subcategory":"Recreational Vehicle Sales",
            "type":"Retail Goods"
        }
    ],
    "sg:phone":"+1 770 732 8098",
    "sg:postcode":"30126",
    "sg:province":"GA",
    "sg:tags":[
        "repairing",
        "facilities-renting",
        "automobile"
    ],
    "wof:name":"Red D Arc",
    "wof:placetype":"venue"
},
  "geometry": {"coordinates":[-84.536987,33.781223],"type":"Point"}
}