{
  "type": "Feature",
  "properties": {
    "iso:country":"US",
    "sg:address":"8956 State Rte 193",
    "sg:city":"Chickamauga",
    "sg:classifiers":[
        {
            "category":"Personal",
            "subcategory":"Beauty Salon",
            "type":"Services"
        }
    ],
    "sg:phone":"+1 706 931 2338",
    "sg:postcode":"30707",
    "sg:province":"GA",
    "wof:name":"High Point Professional Beauty",
    "wof:placetype":"venue"
},
  "geometry": {"coordinates":[-85.366924,34.863882],"type":"Point"}
}