{
  "type": "Feature",
  "properties": {
    "iso:country":"US",
    "sg:address":"1403 Iris Dr SE",
    "sg:city":"Conyers",
    "sg:classifiers":[
        {
            "category":"Organizations",
            "subcategory":"Religious Organization",
            "type":"Services"
        }
    ],
    "sg:phone":"+1 770 879 9386",
    "sg:postcode":"30013",
    "sg:province":"GA",
    "sg:tags":[
        "church"
    ],
    "sg:website":"www.biblebasedchurch.org",
    "wof:name":"Bible Based Community Church",
    "wof:placetype":"venue"
},
  "geometry": {"coordinates":[-83.996583,33.647986],"type":"Point"}
}