{
  "type": "Feature",
  "properties": {
    "addr:full":"204 Water Oaks Ct Hampton GA 30228",
    "addr:housenumber":"204",
    "addr:postcode":"30228",
    "addr:street":"Water Oaks Ct",
    "iso:country":"US",
    "sg:address":"204 Water Oaks Ct",
    "sg:city":"Hampton",
    "sg:classifiers":[
        {
            "category":"Banks & Credit Unions",
            "subcategory":"Investment Brokerage",
            "type":"Services"
        },
        {
            "category":"Insurance",
            "subcategory":"Insurance Agent",
            "type":"Services"
        }
    ],
    "sg:phone":"+1 770 603 2600",
    "sg:postcode":"30228",
    "sg:province":"GA",
    "sg:tags":[
        "advisory"
    ],
    "wof:name":"San Financial Planning Service",
    "wof:placetype":"venue"
},
  "geometry": {"coordinates":[-84.28476499999999,33.473102],"type":"Point"}
}