{
  "type": "Feature",
  "properties": {
    "addr:full":"898 US Hwy 441 Clayton GA 30525",
    "addr:housenumber":"898",
    "addr:postcode":"30525",
    "addr:street":"Us Hwy 441",
    "iso:country":"US",
    "sg:address":"898 US Hwy 441",
    "sg:city":"Clayton",
    "sg:classifiers":[
        {
            "category":"Retail",
            "subcategory":"Funeral Services",
            "type":"Services"
        }
    ],
    "sg:phone":"+1 706 782 9599",
    "sg:postcode":"30525",
    "sg:province":"GA",
    "sg:tags":[
        "director"
    ],
    "wof:name":"Beck Funeral Home",
    "wof:placetype":"venue"
},
  "geometry": {"coordinates":[-83.391379,34.904773],"type":"Point"}
}