{
  "type": "Feature",
  "properties": {
    "addr:full":"1105 Woodstock Rd Ste 120 Roswell GA 30075",
    "addr:housenumber":"1105",
    "addr:postcode":"30075",
    "addr:street":"Woodstock Rd Ste 120",
    "iso:country":"US",
    "sg:address":"1105 Woodstock Rd Ste 120",
    "sg:city":"Roswell",
    "sg:classifiers":[
        {
            "category":"Personal",
            "subcategory":"Barber",
            "type":"Services"
        }
    ],
    "sg:phone":"+1 770 640 5559",
    "sg:postcode":"30075",
    "sg:province":"GA",
    "wof:name":"Sport Clips",
    "wof:placetype":"venue"
},
  "geometry": {"coordinates":[-84.394317,34.062728],"type":"Point"}
}