{
  "type": "Feature",
  "properties": {
    "iso:country":"US",
    "sg:address":"143 Cedar Post Rd",
    "sg:city":"Chickamauga",
    "sg:classifiers":[
        {
            "category":"Education",
            "subcategory":"School",
            "type":"Public Place"
        }
    ],
    "sg:phone":"+1 706 375 5550",
    "sg:postcode":"30707",
    "sg:province":"GA",
    "wof:name":"Unified Development & Cnstr LL",
    "wof:placetype":"venue"
},
  "geometry": {"coordinates":[-85.280986,34.834041],"type":"Point"}
}