{
  "type": "Feature",
  "properties": {
    "iso:country":"US",
    "sg:address":"364 Fir Rd NE",
    "sg:city":"Ranger",
    "sg:classifiers":[
        {
            "category":"Home & Garden",
            "subcategory":"Hardware",
            "type":"Retail Goods"
        },
        {
            "category":"Building & Trades",
            "subcategory":"Locksmith",
            "type":"Services"
        }
    ],
    "sg:phone":"+1 706 624 3610",
    "sg:postcode":"30734",
    "sg:province":"GA",
    "sg:tags":[
        "lock",
        "store"
    ],
    "wof:name":"Affordable Locksmith",
    "wof:placetype":"venue"
},
  "geometry": {"coordinates":[-84.72017700000001,34.535549],"type":"Point"}
}