{
  "type": "Feature",
  "properties": {
    "iso:country":"US",
    "sg:address":"1595 Kensw Due West",
    "sg:city":"Kennesaw",
    "sg:classifiers":[
        {
            "category":"Social Services",
            "subcategory":"Child Care",
            "type":"Services"
        },
        {
            "category":"Education",
            "subcategory":"Preschool",
            "type":"Public Place"
        },
        {
            "category":"Education",
            "subcategory":"School",
            "type":"Public Place"
        }
    ],
    "sg:phone":"+1 770 419 0384",
    "sg:postcode":"30144",
    "sg:province":"GA",
    "sg:tags":[
        "elementary",
        "day"
    ],
    "sg:website":"www.primroseschools.com",
    "wof:name":"Primrose School",
    "wof:placetype":"venue"
},
  "geometry": {"coordinates":[-84.629069,33.99303],"type":"Point"}
}