{
  "type": "Feature",
  "properties": {
    "addr:full":"714 Euel Dr Mcdonough GA 30252",
    "addr:housenumber":"714",
    "addr:postcode":"30252",
    "addr:street":"Euel Dr",
    "iso:country":"US",
    "sg:address":"714 Euel Dr",
    "sg:city":"Mcdonough",
    "sg:classifiers":[
        {
            "category":"Professional",
            "subcategory":"Management & Consulting",
            "type":"Services"
        }
    ],
    "sg:phone":"+1 770 914 7651",
    "sg:postcode":"30252",
    "sg:province":"GA",
    "sg:tags":[
        "consultant",
        "business"
    ],
    "wof:name":"Soler Communications",
    "wof:placetype":"venue"
},
  "geometry": {"coordinates":[-84.079652,33.45882],"type":"Point"}
}