{
  "type": "Feature",
  "properties": {
    "iso:country":"US",
    "sg:address":"1899 Metropolitan Pkwy SW",
    "sg:city":"Atlanta",
    "sg:classifiers":[
        {
            "category":"Wholesale",
            "subcategory":"Apparel",
            "type":"Manufacturing & Wholesale Goods"
        },
        {
            "category":"Shopping",
            "subcategory":"Shoes",
            "type":"Retail Goods"
        }
    ],
    "sg:phone":"+1 404 753 7798",
    "sg:postcode":"30315",
    "sg:province":"GA",
    "sg:tags":[
        "shoes-wholesale",
        "store",
        "manufacturer"
    ],
    "wof:name":"Shoetime International Inc",
    "wof:placetype":"venue"
},
  "geometry": {"coordinates":[-84.408215,33.703391],"type":"Point"}
}