{
  "type": "Feature",
  "properties": {
    "addr:full":"104 Lakepoint Ct Stockbridge GA 30281",
    "addr:housenumber":"104",
    "addr:postcode":"30281",
    "addr:street":"Lakepoint Ct",
    "iso:country":"US",
    "sg:address":"104 Lakepoint Ct",
    "sg:city":"Stockbridge",
    "sg:classifiers":[
        {
            "category":"Wholesale",
            "subcategory":"Machinery & Supplies",
            "type":"Manufacturing & Wholesale Goods"
        }
    ],
    "sg:phone":"+1 770 389 4989",
    "sg:postcode":"30281",
    "sg:province":"GA",
    "wof:name":"Cody Property Development Ltd",
    "wof:placetype":"venue"
},
  "geometry": {"coordinates":[-84.179923,33.530396],"type":"Point"}
}