{
  "type": "Feature",
  "properties": {
    "iso:country":"US",
    "sg:address":"4205 Veterans Memoril Hwy",
    "sg:city":"Lithia Springs",
    "sg:classifiers":[
        {
            "category":"Shopping",
            "subcategory":"Antiques",
            "type":"Retail Goods"
        }
    ],
    "sg:phone":"+1 770 949 1188",
    "sg:postcode":"30122",
    "sg:province":"GA",
    "wof:name":"Bill's Flea Market",
    "wof:placetype":"venue"
},
  "geometry": {"coordinates":[-84.67739899999999,33.793201],"type":"Point"}
}