{
  "type": "Feature",
  "properties": {
    "addr:full":"5610 Oak Ridge Dr Gainesville GA 30506",
    "addr:housenumber":"5610",
    "addr:postcode":"30506",
    "addr:street":"Oak Ridge Dr",
    "iso:country":"US",
    "sg:address":"5610 Oak Ridge Dr",
    "sg:city":"Gainesville",
    "sg:classifiers":[
        {
            "category":"Professional",
            "type":"Services"
        }
    ],
    "sg:phone":"+1 770 533 9251",
    "sg:postcode":"30506",
    "sg:province":"GA",
    "wof:name":"Lanier Vacation Services Inc",
    "wof:placetype":"venue"
},
  "geometry": {"coordinates":[-83.962975,34.410004],"type":"Point"}
}