{
  "type": "Feature",
  "properties": {
    "addr:full":"2911 Chamberlain S Ferry Rd Lincolnton GA 30817",
    "addr:housenumber":"2911",
    "addr:postcode":"30817",
    "addr:street":"Chamberlain S Ferry Rd",
    "iso:country":"US",
    "sg:address":"2911 Chamberlain S Ferry Rd",
    "sg:city":"Lincolnton",
    "sg:classifiers":[
        {
            "category":"Freight",
            "type":"Transportation"
        }
    ],
    "sg:phone":"+1 706 359 1036",
    "sg:postcode":"30817",
    "sg:province":"GA",
    "sg:tags":[
        "operator",
        "trucking"
    ],
    "wof:name":"Hammer Time Trucking",
    "wof:placetype":"venue"
},
  "geometry": {"coordinates":[-82.40093899999999,33.802754],"type":"Point"}
}