{
  "type": "Feature",
  "properties": {
    "addr:full":"1040 Gaines School Rd Athens GA 30605",
    "addr:housenumber":"1040",
    "addr:postcode":"30605",
    "addr:street":"Gaines School Rd",
    "iso:country":"US",
    "sg:address":"1040 Gaines School Rd",
    "sg:city":"Athens",
    "sg:classifiers":[
        {
            "category":"Professional",
            "type":"Services"
        }
    ],
    "sg:phone":"+1 706 354 1142",
    "sg:postcode":"30605",
    "sg:province":"GA",
    "sg:tags":[
        "establishment"
    ],
    "wof:name":"Galis Kimbrough LLC",
    "wof:placetype":"venue"
},
  "geometry": {"coordinates":[-83.337254,33.927845],"type":"Point"}
}