{
  "type": "Feature",
  "properties": {
    "addr:full":"6586 Ga Highway 40 E Saint Marys GA 31558",
    "addr:housenumber":"6586",
    "addr:postcode":"31558",
    "addr:street":"Ga Highway 40 E",
    "iso:country":"US",
    "sg:address":"6586 Ga Highway 40 E",
    "sg:city":"Saint Marys",
    "sg:classifiers":[
        {
            "category":"Restaurant",
            "type":"Food & Drink"
        }
    ],
    "sg:menulink":"http://www.allmenus.com/ga/st-marys/244190-happy-wok-buffet/menu/",
    "sg:phone":"+1 912 882 7510",
    "sg:postcode":"31558",
    "sg:province":"GA",
    "sg:tags":[
        "asian",
        "chinese"
    ],
    "wof:name":"Happy Wok Buffet",
    "wof:placetype":"venue"
},
  "geometry": {"coordinates":[-81.57645599999999,30.752057],"type":"Point"}
}