{
  "type": "Feature",
  "properties": {
    "iso:country":"US",
    "sg:address":"15 Snow Rd",
    "sg:city":"Mt Zion",
    "sg:classifiers":[
        {
            "category":"Personal",
            "subcategory":"Beauty Salon",
            "type":"Services"
        }
    ],
    "sg:phone":"+1 770 836 1020",
    "sg:postcode":"30150",
    "sg:province":"GA",
    "wof:name":"Belle Rae Salon",
    "wof:placetype":"venue"
},
  "geometry": {"coordinates":[-85.165995,33.660204],"type":"Point"}
}