{
  "type": "Feature",
  "properties": {
    "iso:country":"US",
    "sg:address":"718 E Side Ave SE",
    "sg:city":"Atlanta",
    "sg:classifiers":[
        {
            "category":"Professional",
            "subcategory":"Business Services",
            "type":"Services"
        }
    ],
    "sg:phone":"+1 404 627 8882",
    "sg:postcode":"30316",
    "sg:province":"GA",
    "sg:tags":[
        "personal"
    ],
    "wof:name":"Caleco Creations",
    "wof:placetype":"venue"
},
  "geometry": {"coordinates":[-84.339947,33.734279],"type":"Point"}
}