{
  "type": "Feature",
  "properties": {
    "addr:full":"480 Holiday Cir Forsyth GA 31029",
    "addr:housenumber":"480",
    "addr:postcode":"31029",
    "addr:street":"Holiday Cir",
    "iso:country":"US",
    "sg:address":"480 Holiday Cir",
    "sg:city":"Forsyth",
    "sg:classifiers":[
        {
            "category":"Travel",
            "subcategory":"Hotels & Motels",
            "type":"Entertainment"
        },
        {
            "category":"Retail",
            "subcategory":"Event Space",
            "type":"Services"
        }
    ],
    "sg:phone":"+1 478 994 5691",
    "sg:postcode":"31029",
    "sg:province":"GA",
    "sg:tags":[
        "facility",
        "banquet",
        "reception",
        "lodging",
        "hall"
    ],
    "sg:website":"http://www.ramada.com/hotel/30926&cid=RANE",
    "wof:name":"Ramada Conference Center Forsyth",
    "wof:placetype":"venue"
},
  "geometry": {"coordinates":[-83.922915,33.033732],"type":"Point"}
}