{
  "type": "Feature",
  "properties": {
    "addr:full":"6301 Lively Rd Cumming GA 30040",
    "addr:housenumber":"6301",
    "addr:postcode":"30040",
    "addr:street":"Lively Rd",
    "iso:country":"US",
    "sg:address":"6301 Lively Rd",
    "sg:city":"Cumming",
    "sg:classifiers":[
        {
            "category":"Professional",
            "subcategory":"Lawyer & Legal Services",
            "type":"Services"
        }
    ],
    "sg:phone":"+1 770 475 0841",
    "sg:postcode":"30040",
    "sg:province":"GA",
    "wof:name":"Lynda Sewell Hulsey Atto",
    "wof:placetype":"venue"
},
  "geometry": {"coordinates":[-84.257261,34.169437],"type":"Point"}
}