{
  "type": "Feature",
  "properties": {
    "iso:country":"US",
    "sg:address":"2299 Godby Road",
    "sg:city":"Atlanta",
    "sg:classifiers":[
        {
            "category":"Social Services",
            "subcategory":"Child Care",
            "type":"Services"
        }
    ],
    "sg:phone":"+1 404 559 8099",
    "sg:postcode":"30349",
    "sg:province":"GA",
    "sg:tags":[
        "day"
    ],
    "wof:name":"Day Star Christian Academy",
    "wof:placetype":"venue"
},
  "geometry": {"coordinates":[-84.46405300000001,33.616242],"type":"Point"}
}