{
  "type": "Feature",
  "properties": {
    "iso:country":"US",
    "sg:address":"866 Forest Path",
    "sg:city":"Stone Mountain",
    "sg:classifiers":[
        {
            "category":"Professional",
            "type":"Services"
        }
    ],
    "sg:phone":"+1 770 879 9766",
    "sg:postcode":"30088",
    "sg:province":"GA",
    "wof:name":"Sea Traders Inc",
    "wof:placetype":"venue"
},
  "geometry": {"coordinates":[-84.16889500000001,33.768119],"type":"Point"}
}