{
  "type": "Feature",
  "properties": {
    "iso:country":"US",
    "sg:address":"273 Smith Ferguson Rd",
    "sg:city":"Dallas",
    "sg:classifiers":[
        {
            "category":"Professional",
            "type":"Services"
        }
    ],
    "sg:phone":"+1 770 317 3560",
    "sg:postcode":"30157",
    "sg:province":"GA",
    "wof:name":"Georgia West Guide Service",
    "wof:placetype":"venue"
},
  "geometry": {"coordinates":[-84.842674,33.850009],"type":"Point"}
}