{
  "type": "Feature",
  "properties": {
    "iso:country":"US",
    "sg:address":"1902 Windsor Spring Rd",
    "sg:city":"Augusta",
    "sg:classifiers":[
        {
            "category":"Food & Beverages",
            "subcategory":"Groceries & Convenience Stores",
            "type":"Retail Goods"
        }
    ],
    "sg:phone":"+1 706 560 2004",
    "sg:postcode":"30906",
    "sg:province":"GA",
    "wof:name":"Kay's Stop N Shop",
    "wof:placetype":"venue"
},
  "geometry": {"coordinates":[-82.016312,33.411888],"type":"Point"}
}