{
  "type": "Feature",
  "properties": {
    "iso:country":"US",
    "sg:address":"3850 Holcomb Bridge Rd",
    "sg:city":"Norcross",
    "sg:classifiers":[
        {
            "category":"Manufacturing",
            "subcategory":"Printing",
            "type":"Manufacturing & Wholesale Goods"
        }
    ],
    "sg:phone":"+1 770 441 2305",
    "sg:postcode":"30092",
    "sg:province":"GA",
    "sg:tags":[
        "book"
    ],
    "wof:name":"Scholastic Inc",
    "wof:placetype":"venue"
},
  "geometry": {"coordinates":[-84.253896,33.965333],"type":"Point"}
}