{
  "type": "Feature",
  "properties": {
    "iso:country":"US",
    "sg:address":"2870 Dogwood Hollow Ln",
    "sg:city":"Lawrenceville",
    "sg:classifiers":[
        {
            "category":"Building & Trades",
            "subcategory":"Construction",
            "type":"Services"
        }
    ],
    "sg:phone":"+1 770 945 7039",
    "sg:postcode":"30043",
    "sg:province":"GA",
    "sg:tags":[
        "home",
        "builder"
    ],
    "wof:name":"Hamlet At Rock Springs Home",
    "wof:placetype":"venue"
},
  "geometry": {"coordinates":[-84.01611200000001,34.04404],"type":"Point"}
}