{
  "type": "Feature",
  "properties": {
    "addr:full":"10820 Abbotts Bridge Rd Duluth GA 30097",
    "addr:housenumber":"10820",
    "addr:postcode":"30097",
    "addr:street":"Abbotts Bridge Rd",
    "iso:country":"US",
    "sg:address":"10820 Abbotts Bridge Rd",
    "sg:city":"Duluth",
    "sg:classifiers":[
        {
            "category":"Shopping",
            "subcategory":"Jewelry",
            "type":"Retail Goods"
        }
    ],
    "sg:phone":"+1 678 417 9105",
    "sg:postcode":"30097",
    "sg:province":"GA",
    "wof:name":"Sh Faith Jewelry",
    "wof:placetype":"venue"
},
  "geometry": {"coordinates":[-84.17618400000001,34.043627],"type":"Point"}
}