{
  "type": "Feature",
  "properties": {
    "addr:full":"2894 Piney Grove Rd Blackshear GA 31516",
    "addr:housenumber":"2894",
    "addr:postcode":"31516",
    "addr:street":"Piney Grove Rd",
    "iso:country":"US",
    "sg:address":"2894 Piney Grove Rd",
    "sg:city":"Blackshear",
    "sg:classifiers":[
        {
            "category":"Professional",
            "type":"Services"
        }
    ],
    "sg:phone":"+1 912 449 6818",
    "sg:postcode":"31516",
    "sg:province":"GA",
    "wof:name":"Maureen Brown",
    "wof:placetype":"venue"
},
  "geometry": {"coordinates":[-82.27222999999999,31.303127],"type":"Point"}
}