{
  "type": "Feature",
  "properties": {
    "addr:full":"241 Newnan Crossing Byp Newnan GA 30265",
    "addr:housenumber":"241",
    "addr:postcode":"30265",
    "addr:street":"Newnan Crossing Byp",
    "iso:country":"US",
    "sg:address":"241 Newnan Crossing Byp",
    "sg:city":"Newnan",
    "sg:classifiers":[
        {
            "category":"Shopping",
            "subcategory":"Department Store",
            "type":"Retail Goods"
        },
        {
            "category":"Shopping",
            "type":"Retail Goods"
        },
        {
            "category":"Shopping",
            "subcategory":"Discount & Variety Stores",
            "type":"Retail Goods"
        }
    ],
    "sg:phone":"+1 770 253 4526",
    "sg:postcode":"30265",
    "sg:province":"GA",
    "sg:tags":[
        "merchandise"
    ],
    "sg:website":"http://www.dollartree.com/",
    "wof:name":"Dollar Tree",
    "wof:placetype":"venue"
},
  "geometry": {"coordinates":[-84.762333,33.391188],"type":"Point"}
}