{
  "type": "Feature",
  "properties": {
    "iso:country":"US",
    "sg:address":"1205 S Milledge Ave",
    "sg:city":"Athens",
    "sg:classifiers":[
        {
            "category":"Food & Beverages",
            "subcategory":"Groceries & Convenience Stores",
            "type":"Retail Goods"
        }
    ],
    "sg:phone":"+1 706 543 1021",
    "sg:postcode":"30605",
    "sg:province":"GA",
    "wof:name":"Golden Pantry Food Store",
    "wof:placetype":"venue"
},
  "geometry": {"coordinates":[-83.386183,33.938688],"type":"Point"}
}