{
  "type": "Feature",
  "properties": {
    "iso:country":"US",
    "sg:address":"4093 Lawrenceville Hwy",
    "sg:city":"Lilburn",
    "sg:classifiers":[
        {
            "category":"Taxi",
            "type":"Transportation"
        }
    ],
    "sg:phone":"+1 770 921 5777",
    "sg:postcode":"30047",
    "sg:province":"GA",
    "sg:tags":[
        "taxicab"
    ],
    "wof:name":"Jalisco Taxi Service",
    "wof:placetype":"venue"
},
  "geometry": {"coordinates":[-84.11656000000001,33.903907],"type":"Point"}
}