{
  "type": "Feature",
  "properties": {
    "addr:full":"4228 Buena Vista Rd Columbus GA 31907",
    "addr:housenumber":"4228",
    "addr:postcode":"31907",
    "addr:street":"Buena Vista Rd",
    "iso:country":"US",
    "sg:address":"4228 Buena Vista Rd",
    "sg:city":"Columbus",
    "sg:classifiers":[
        {
            "category":"Utilities",
            "subcategory":"Mobile Phone",
            "type":"Services"
        },
        {
            "category":"Utilities",
            "subcategory":"Telephone",
            "type":"Services"
        },
        {
            "category":"Manufacturing",
            "subcategory":"Electronics",
            "type":"Manufacturing & Wholesale Goods"
        },
        {
            "category":"Communications",
            "type":"Services"
        }
    ],
    "sg:phone":"+1 706 561 6050",
    "sg:postcode":"31907",
    "sg:province":"GA",
    "sg:tags":[
        "telecommunications-equipment",
        "systems-repair",
        "supply",
        "system",
        "equipment",
        "paging",
        "signaling",
        "cellular"
    ],
    "wof:name":"Columbus Wireless Communications",
    "wof:placetype":"venue"
},
  "geometry": {"coordinates":[-84.921927,32.464457],"type":"Point"}
}