{
  "type": "Feature",
  "properties": {
    "addr:full":"4060 Peachtree Rd NE Atlanta GA 30319",
    "addr:housenumber":"4060",
    "addr:postcode":"30319",
    "addr:street":"Peachtree Rd Ne",
    "iso:country":"US",
    "sg:address":"4060 Peachtree Rd NE",
    "sg:city":"Atlanta",
    "sg:classifiers":[
        {
            "category":"Professional",
            "subcategory":"Management & Consulting",
            "type":"Services"
        }
    ],
    "sg:phone":"+1 404 869 0244",
    "sg:postcode":"30319",
    "sg:province":"GA",
    "sg:tags":[
        "development",
        "business"
    ],
    "wof:name":"Synergy 7 Consulting",
    "wof:placetype":"venue"
},
  "geometry": {"coordinates":[-84.34043699999999,33.859193],"type":"Point"}
}