{
  "type": "Feature",
  "properties": {
    "addr:full":"524 S Houston Lake Rd Warner Robins GA 31088",
    "addr:housenumber":"524",
    "addr:postcode":"31088",
    "addr:street":"S Houston Lake Rd",
    "iso:country":"US",
    "sg:address":"524 S Houston Lake Rd",
    "sg:city":"Warner Robins",
    "sg:classifiers":[
        {
            "category":"Professional",
            "type":"Services"
        }
    ],
    "sg:phone":"+1 478 971 4815",
    "sg:postcode":"31088",
    "sg:province":"GA",
    "sg:tags":[
        "establishment"
    ],
    "wof:name":"Clean Air Solutions",
    "wof:placetype":"venue"
},
  "geometry": {"coordinates":[-83.67506,32.605176],"type":"Point"}
}