{
  "type": "Feature",
  "properties": {
    "addr:full":"175 Wellborn Chase Fayetteville GA 30215",
    "addr:housenumber":"175",
    "addr:postcode":"30215",
    "addr:street":"Wellborn Chase",
    "iso:country":"US",
    "sg:address":"175 Wellborn Chase",
    "sg:city":"Fayetteville",
    "sg:classifiers":[
        {
            "category":"Education",
            "subcategory":"Special Training",
            "type":"Public Place"
        }
    ],
    "sg:phone":"+1 770 460 6160",
    "sg:postcode":"30215",
    "sg:province":"GA",
    "sg:tags":[
        "tutoring"
    ],
    "wof:name":"Arthur Nce Workshops",
    "wof:placetype":"venue"
},
  "geometry": {"coordinates":[-84.51703999999999,33.361241],"type":"Point"}
}