{
  "type": "Feature",
  "properties": {
    "iso:country":"US",
    "sg:address":"2590 Jenna Ln",
    "sg:city":"Lithia Springs",
    "sg:classifiers":[
        {
            "category":"Professional",
            "type":"Services"
        }
    ],
    "sg:phone":"+1 770 220 9436",
    "sg:postcode":"30122",
    "sg:province":"GA",
    "wof:name":"Bnb Visions Inc",
    "wof:placetype":"venue"
},
  "geometry": {"coordinates":[-84.660484,33.743777],"type":"Point"}
}