{
  "type": "Feature",
  "properties": {
    "iso:country":"US",
    "sg:address":"5283 Cedar Rock Dr",
    "sg:city":"Lithonia",
    "sg:classifiers":[
        {
            "category":"Professional",
            "type":"Services"
        }
    ],
    "sg:phone":"+1 678 984 3481",
    "sg:postcode":"30038",
    "sg:province":"GA",
    "wof:name":"Blanch Service Co",
    "wof:placetype":"venue"
},
  "geometry": {"coordinates":[-84.17090899999999,33.684743],"type":"Point"}
}