{
  "type": "Feature",
  "properties": {
    "addr:full":"962 Watkins Field Rd Clayton GA 30525",
    "addr:housenumber":"962",
    "addr:postcode":"30525",
    "addr:street":"Watkins Field Rd",
    "iso:country":"US",
    "sg:address":"962 Watkins Field Rd",
    "sg:city":"Clayton",
    "sg:classifiers":[
        {
            "category":"Real Estate",
            "subcategory":"Real Estate Agent",
            "type":"Services"
        }
    ],
    "sg:phone":"+1 706 782 1974",
    "sg:postcode":"30525",
    "sg:province":"GA",
    "sg:tags":[
        "appraiser"
    ],
    "wof:name":"Suttles & Associates Inc",
    "wof:placetype":"venue"
},
  "geometry": {"coordinates":[-83.34348,34.851166],"type":"Point"}
}