{
  "type": "Feature",
  "properties": {
    "addr:full":"715 Brighton Rd Tifton GA 31794",
    "addr:housenumber":"715",
    "addr:postcode":"31794",
    "addr:street":"Brighton Rd",
    "iso:country":"US",
    "sg:address":"715 Brighton Rd",
    "sg:city":"Tifton",
    "sg:classifiers":[
        {
            "category":"Organizations",
            "subcategory":"Religious Organization",
            "type":"Services"
        }
    ],
    "sg:phone":"+1 229 382 6120",
    "sg:postcode":"31794",
    "sg:province":"GA",
    "wof:name":"Trinity Worship Center",
    "wof:placetype":"venue"
},
  "geometry": {"coordinates":[-83.470467,31.503926],"type":"Point"}
}