{
  "type": "Feature",
  "properties": {
    "iso:country":"US",
    "sg:address":"784 Gray Hwy",
    "sg:city":"Macon",
    "sg:classifiers":[
        {
            "category":"Autos & Motor Vehicles",
            "subcategory":"Automobile Sales",
            "type":"Retail Goods"
        }
    ],
    "sg:phone":"+1 478 745 6668",
    "sg:postcode":"31211",
    "sg:province":"GA",
    "sg:tags":[
        "used"
    ],
    "wof:name":"HRM Auto Sales",
    "wof:placetype":"venue"
},
  "geometry": {"coordinates":[-83.62090600000001,32.851242],"type":"Point"}
}