{
  "type": "Feature",
  "properties": {
    "addr:full":"4918 Bill Gardner Pkwy Locust Grove GA 30248",
    "addr:housenumber":"4918",
    "addr:postcode":"30248",
    "addr:street":"Bill Gardner Pkwy",
    "iso:country":"US",
    "sg:address":"4918 Bill Gardner Pkwy",
    "sg:city":"Locust Grove",
    "sg:classifiers":[
        {
            "category":"Restaurant",
            "type":"Food & Drink"
        }
    ],
    "sg:phone":"+1 678 432 2502",
    "sg:postcode":"30248",
    "sg:province":"GA",
    "wof:name":"Kickin' Chicken-Locust Grove",
    "wof:placetype":"venue"
},
  "geometry": {"coordinates":[-84.114115,33.353384],"type":"Point"}
}