{
  "type": "Feature",
  "properties": {
    "addr:full":"1101 E 16th Ave Cordele GA 31015",
    "addr:housenumber":"1101",
    "addr:postcode":"31015",
    "addr:street":"E 16Th Ave",
    "iso:country":"US",
    "sg:address":"1101 E 16th Ave",
    "sg:city":"Cordele",
    "sg:classifiers":[
        {
            "category":"Restaurant",
            "type":"Food & Drink"
        }
    ],
    "sg:menulink":"http://www.allmenus.com/ga/cordele/160510-burger-king/menu/",
    "sg:phone":"+1 229 273 4507",
    "sg:postcode":"31015",
    "sg:province":"GA",
    "sg:tags":[
        "burger",
        "american"
    ],
    "wof:name":"Burger King",
    "wof:placetype":"venue"
},
  "geometry": {"coordinates":[-83.765315,31.963255],"type":"Point"}
}