{
  "type": "Feature",
  "properties": {
    "iso:country":"US",
    "sg:address":"106 Lucy Cir",
    "sg:city":"Warner Robins",
    "sg:classifiers":[
        {
            "category":"Bus Charters",
            "type":"Transportation"
        }
    ],
    "sg:phone":"+1 478 975 9287",
    "sg:postcode":"31093",
    "sg:province":"GA",
    "sg:tags":[
        "rental",
        "transport"
    ],
    "wof:name":"Transmouth Motorcoach",
    "wof:placetype":"venue"
},
  "geometry": {"coordinates":[-83.62088300000001,32.656309],"type":"Point"}
}