{
  "type": "Feature",
  "properties": {
    "iso:country":"US",
    "sg:address":"306 W Broad St",
    "sg:city":"Greensboro",
    "sg:classifiers":[
        {
            "category":"Travel",
            "subcategory":"Hotels & Motels",
            "type":"Entertainment"
        }
    ],
    "sg:phone":"+1 706 453 4074",
    "sg:postcode":"30642",
    "sg:province":"GA",
    "sg:tags":[
        "operation"
    ],
    "wof:name":"Ambikaniketan LLC",
    "wof:placetype":"venue"
},
  "geometry": {"coordinates":[-83.186733,33.576165],"type":"Point"}
}