{
  "type": "Feature",
  "properties": {
    "iso:country":"US",
    "sg:address":"124 John Smith Ave",
    "sg:city":"Shellman",
    "sg:classifiers":[
        {
            "category":"Social Services",
            "subcategory":"Child Care",
            "type":"Services"
        }
    ],
    "sg:phone":"+1 229 679 5785",
    "sg:postcode":"39886",
    "sg:province":"GA",
    "sg:tags":[
        "nursery",
        "day"
    ],
    "wof:name":"Bettys Child Care",
    "wof:placetype":"venue"
},
  "geometry": {"coordinates":[-84.61771400000001,31.751835],"type":"Point"}
}