{
  "type": "Feature",
  "properties": {
    "iso:country":"US",
    "sg:address":"3230 Peachtree Corners Cir Ste V",
    "sg:city":"Norcross",
    "sg:classifiers":[
        {
            "category":"Real Estate",
            "subcategory":"Real Estate Operator",
            "type":"Services"
        }
    ],
    "sg:phone":"+1 770 242 2730",
    "sg:postcode":"30092",
    "sg:province":"GA",
    "sg:tags":[
        "apartment"
    ],
    "sg:website":"www.cbre.com",
    "wof:name":"Cb Richard Ellis",
    "wof:placetype":"venue"
},
  "geometry": {"coordinates":[-84.250175,33.942203],"type":"Point"}
}