{
  "type": "Feature",
  "properties": {
    "iso:country":"US",
    "sg:address":"343 State Rte 326",
    "sg:city":"Commerce",
    "sg:classifiers":[
        {
            "category":"Building & Trades",
            "subcategory":"Landscaping Services",
            "type":"Services"
        }
    ],
    "sg:phone":"+1 706 335 7731",
    "sg:postcode":"30530",
    "sg:province":"GA",
    "sg:tags":[
        "wiring",
        "exterior",
        "contractor"
    ],
    "wof:name":"Exterior Dsigns Gen Contg Svcs",
    "wof:placetype":"venue"
},
  "geometry": {"coordinates":[-83.45241900000001,34.205274],"type":"Point"}
}