{
  "type": "Feature",
  "properties": {
    "iso:country":"US",
    "sg:address":"600 Main St",
    "sg:city":"Blackshear",
    "sg:classifiers":[
        {
            "category":"Education",
            "subcategory":"Library",
            "type":"Public Place"
        }
    ],
    "sg:phone":"+1 912 449 7040",
    "sg:postcode":"31516",
    "sg:province":"GA",
    "wof:name":"Bkackshear Merorial Lirary Sys",
    "wof:placetype":"venue"
},
  "geometry": {"coordinates":[-82.23735000000001,31.30151],"type":"Point"}
}