{
  "type": "Feature",
  "properties": {
    "addr:full":"171 Huskins Rd Canton GA 30115",
    "addr:housenumber":"171",
    "addr:postcode":"30115",
    "addr:street":"Huskins Rd",
    "iso:country":"US",
    "sg:address":"171 Huskins Rd",
    "sg:city":"Canton",
    "sg:classifiers":[
        {
            "category":"Professional",
            "type":"Services"
        }
    ],
    "sg:phone":"+1 770 720 0259",
    "sg:postcode":"30115",
    "sg:province":"GA",
    "wof:name":"Scott H Alton",
    "wof:placetype":"venue"
},
  "geometry": {"coordinates":[-84.492288,34.188113],"type":"Point"}
}