{
  "type": "Feature",
  "properties": {
    "iso:country":"US",
    "sg:address":"2665 Favor Rd SW",
    "sg:city":"Marietta",
    "sg:classifiers":[
        {
            "category":"Professional",
            "type":"Services"
        }
    ],
    "sg:phone":"+1 770 434 2290",
    "sg:postcode":"30060",
    "sg:province":"GA",
    "wof:name":"Sandra Winfield",
    "wof:placetype":"venue"
},
  "geometry": {"coordinates":[-84.56673499999999,33.8905],"type":"Point"}
}