{
  "type": "Feature",
  "properties": {
    "iso:country":"US",
    "sg:address":"2151 Zelda Dr NE",
    "sg:city":"Atlanta",
    "sg:classifiers":[
        {
            "category":"Professional",
            "subcategory":"Management & Consulting",
            "type":"Services"
        }
    ],
    "sg:phone":"+1 770 492 0610",
    "sg:postcode":"30345",
    "sg:province":"GA",
    "wof:name":"Windvane",
    "wof:placetype":"venue"
},
  "geometry": {"coordinates":[-84.258741,33.846831],"type":"Point"}
}