{
  "type": "Feature",
  "properties": {
    "addr:full":"3120 Breckinridge Blvd Duluth GA 30096",
    "addr:housenumber":"3120",
    "addr:postcode":"30096",
    "addr:street":"Breckinridge Blvd",
    "iso:country":"US",
    "sg:address":"3120 Breckinridge Blvd",
    "sg:city":"Duluth",
    "sg:classifiers":[
        {
            "category":"Professional",
            "subcategory":"Business Services",
            "type":"Services"
        }
    ],
    "sg:phone":"+1 770 564 5311",
    "sg:postcode":"30096",
    "sg:province":"GA",
    "wof:name":"William Nemetz",
    "wof:placetype":"venue"
},
  "geometry": {"coordinates":[-84.106742,33.960204],"type":"Point"}
}