{
  "type": "Feature",
  "properties": {
    "iso:country":"US",
    "sg:address":"5280 Buford Hwy NE",
    "sg:city":"Doraville",
    "sg:classifiers":[
        {
            "category":"Building & Trades",
            "subcategory":"Construction",
            "type":"Services"
        }
    ],
    "sg:phone":"+1 404 261 8177",
    "sg:postcode":"30340",
    "sg:province":"GA",
    "sg:tags":[
        "general",
        "contractor"
    ],
    "wof:name":"Builder's Tec",
    "wof:placetype":"venue"
},
  "geometry": {"coordinates":[-84.278395,33.899395],"type":"Point"}
}