{
  "type": "Feature",
  "properties": {
    "iso:country":"US",
    "sg:address":"380 Athens Hwy",
    "sg:city":"Loganville",
    "sg:classifiers":[
        {
            "category":"Retail",
            "subcategory":"Auto Repair",
            "type":"Services"
        }
    ],
    "sg:phone":"+1 770 554 0522",
    "sg:postcode":"30052",
    "sg:province":"GA",
    "sg:tags":[
        "repairing",
        "automobile",
        "general"
    ],
    "wof:name":"Longpro Automotive",
    "wof:placetype":"venue"
},
  "geometry": {"coordinates":[-83.92755,33.8527],"type":"Point"}
}