{
  "type": "Feature",
  "properties": {
    "iso:country":"US",
    "sg:address":"698 N Marietta Pkwy",
    "sg:city":"Marietta",
    "sg:classifiers":[
        {
            "category":"Social Services",
            "type":"Services"
        }
    ],
    "sg:phone":"+1 770 919 9088",
    "sg:postcode":"30060",
    "sg:province":"GA",
    "sg:tags":[
        "professional",
        "counselor"
    ],
    "sg:website":"www.medlintc.com",
    "wof:name":"Medlin Treatment Ctr",
    "wof:placetype":"venue"
},
  "geometry": {"coordinates":[-84.53473099999999,33.958708],"type":"Point"}
}