{
  "type": "Feature",
  "properties": {
    "addr:full":"56 Short St Dahlonega GA 30533",
    "addr:housenumber":"56",
    "addr:postcode":"30533",
    "addr:street":"Short St",
    "iso:country":"US",
    "sg:address":"56 Short St",
    "sg:city":"Dahlonega",
    "sg:classifiers":[
        {
            "category":"Government",
            "subcategory":"Office",
            "type":"Public Place"
        }
    ],
    "sg:phone":"+1 706 867 2727",
    "sg:postcode":"30533",
    "sg:province":"GA",
    "sg:tags":[
        "county",
        "program",
        "health"
    ],
    "wof:name":"Lumpkin County Health Ctr",
    "wof:placetype":"venue"
},
  "geometry": {"coordinates":[-83.98157999999999,34.535111],"type":"Point"}
}