{
  "type": "Feature",
  "properties": {
    "addr:full":"6792 W Fayetteville Rd Riverdale GA 30296",
    "addr:housenumber":"6792",
    "addr:postcode":"30296",
    "addr:street":"W Fayetteville Rd",
    "iso:country":"US",
    "sg:address":"6792 W Fayetteville Rd",
    "sg:city":"Riverdale",
    "sg:classifiers":[
        {
            "category":"Wholesale",
            "subcategory":"Home Furnishings",
            "type":"Manufacturing & Wholesale Goods"
        }
    ],
    "sg:phone":"+1 770 996 0217",
    "sg:postcode":"30296",
    "sg:province":"GA",
    "sg:tags":[
        "manufacturer",
        "baskets-wholesale"
    ],
    "wof:name":"Baskets & Stuff",
    "wof:placetype":"venue"
},
  "geometry": {"coordinates":[-84.447941,33.569565],"type":"Point"}
}