{
  "type": "Feature",
  "properties": {
    "iso:country":"US",
    "sg:address":"1005 Tebeau St",
    "sg:city":"Waycross",
    "sg:classifiers":[
        {
            "category":"Shopping",
            "subcategory":"Discount & Variety Stores",
            "type":"Retail Goods"
        }
    ],
    "sg:phone":"+1 912 283 2330",
    "sg:postcode":"31501",
    "sg:province":"GA",
    "wof:name":"Super 10",
    "wof:placetype":"venue"
},
  "geometry": {"coordinates":[-82.360024,31.216714],"type":"Point"}
}