{
  "type": "Feature",
  "properties": {
    "addr:full":"665 Holcomb Bridge Rd Roswell GA 30076",
    "addr:housenumber":"665",
    "addr:postcode":"30076",
    "addr:street":"Holcomb Bridge Rd",
    "iso:country":"US",
    "sg:address":"665 Holcomb Bridge Rd",
    "sg:city":"Roswell",
    "sg:classifiers":[
        {
            "category":"Restaurant",
            "type":"Food & Drink"
        }
    ],
    "sg:phone":"+1 770 992 6075",
    "sg:postcode":"30076",
    "sg:province":"GA",
    "sg:tags":[
        "eating"
    ],
    "wof:name":"Pizza Hut",
    "wof:placetype":"venue"
},
  "geometry": {"coordinates":[-84.34189000000001,34.034448],"type":"Point"}
}