{
  "type": "Feature",
  "properties": {
    "iso:country":"US",
    "sg:address":"2474 Shingle Oak Ct",
    "sg:city":"Lawrenceville",
    "sg:classifiers":[
        {
            "category":"Wholesale",
            "subcategory":"Apparel",
            "type":"Manufacturing & Wholesale Goods"
        }
    ],
    "sg:phone":"+1 770 682 9675",
    "sg:postcode":"30043",
    "sg:province":"GA",
    "sg:tags":[
        "clothing"
    ],
    "wof:name":"RG Welmering Sales",
    "wof:placetype":"venue"
},
  "geometry": {"coordinates":[-84.057914,34.003315],"type":"Point"}
}