{
  "type": "Feature",
  "properties": {
    "iso:country":"US",
    "sg:address":"439 S Main St",
    "sg:city":"Statesboro",
    "sg:classifiers":[
        {
            "category":"Freight",
            "type":"Transportation"
        }
    ],
    "sg:phone":"+1 912 764 6076",
    "sg:postcode":"30458",
    "sg:province":"GA",
    "sg:tags":[
        "commercial",
        "storage"
    ],
    "wof:name":"AAA Mini Warehouses",
    "wof:placetype":"venue"
},
  "geometry": {"coordinates":[-81.784988,32.43399],"type":"Point"}
}