{
  "type": "Feature",
  "properties": {
    "iso:country":"US",
    "sg:address":"2465 Misty Hollow Ln",
    "sg:city":"Cumming",
    "sg:classifiers":[
        {
            "category":"Professional",
            "subcategory":"Business Services",
            "type":"Services"
        }
    ],
    "sg:phone":"+1 770 781 3667",
    "sg:postcode":"30040",
    "sg:province":"GA",
    "wof:name":"Creative Interiors Inc",
    "wof:placetype":"venue"
},
  "geometry": {"coordinates":[-84.18874700000001,34.236773],"type":"Point"}
}