{
  "type": "Feature",
  "properties": {
    "iso:country":"US",
    "sg:address":"1616 N Ashley St",
    "sg:city":"Valdosta",
    "sg:classifiers":[
        {
            "category":"Restaurant",
            "type":"Food & Drink"
        }
    ],
    "sg:phone":"+1 229 242 8678",
    "sg:postcode":"31602",
    "sg:province":"GA",
    "sg:tags":[
        "eating"
    ],
    "wof:name":"Panda 2000",
    "wof:placetype":"venue"
},
  "geometry": {"coordinates":[-83.280593,30.850689],"type":"Point"}
}