{
  "type": "Feature",
  "properties": {
    "iso:country":"US",
    "sg:address":"3032 Stone Hogan Connector Rd SW",
    "sg:city":"Atlanta",
    "sg:classifiers":[
        {
            "category":"Food & Beverages",
            "subcategory":"Groceries & Convenience Stores",
            "type":"Retail Goods"
        }
    ],
    "sg:phone":"+1 404 494 8008",
    "sg:postcode":"30331",
    "sg:province":"GA",
    "wof:name":"C & S Foodmart",
    "wof:placetype":"venue"
},
  "geometry": {"coordinates":[-84.49615799999999,33.673068],"type":"Point"}
}