{
  "type": "Feature",
  "properties": {
    "iso:country":"US",
    "sg:address":"870 Pine Shadows Dr",
    "sg:city":"Dallas",
    "sg:classifiers":[
        {
            "category":"Retail",
            "subcategory":"Auto Repair",
            "type":"Services"
        }
    ],
    "sg:phone":"+1 770 445 4814",
    "sg:postcode":"30157",
    "sg:province":"GA",
    "sg:tags":[
        "general"
    ],
    "wof:name":"B JS Garage",
    "wof:placetype":"venue"
},
  "geometry": {"coordinates":[-84.853382,33.834446],"type":"Point"}
}