{
  "type": "Feature",
  "properties": {
    "iso:country":"US",
    "sg:address":"500 Norwich Rd",
    "sg:city":"Augusta",
    "sg:classifiers":[
        {
            "category":"Real Estate",
            "subcategory":"Real Estate Operator",
            "type":"Services"
        }
    ],
    "sg:phone":"+1 706 733 2817",
    "sg:postcode":"30909",
    "sg:province":"GA",
    "sg:tags":[
        "apartment"
    ],
    "wof:name":"Waverly Villa Apts Maintenance",
    "wof:placetype":"venue"
},
  "geometry": {"coordinates":[-82.056259,33.497829],"type":"Point"}
}