{
  "type": "Feature",
  "properties": {
    "iso:country":"US",
    "sg:address":"5909 Peachtree Dunwoody R",
    "sg:city":"Atlanta",
    "sg:classifiers":[
        {
            "category":"Professional",
            "subcategory":"Accounting & Tax Preparation",
            "type":"Services"
        }
    ],
    "sg:phone":"+1 770 261 1900",
    "sg:postcode":"30328",
    "sg:province":"GA",
    "sg:tags":[
        "accountant"
    ],
    "wof:name":"Clayton Christopher",
    "wof:placetype":"venue"
},
  "geometry": {"coordinates":[-84.351373,33.915069],"type":"Point"}
}