{
  "type": "Feature",
  "properties": {
    "addr:full":"4031 Bankhead Hwy Douglasville GA 30134",
    "addr:housenumber":"4031",
    "addr:postcode":"30134",
    "addr:street":"Bankhead Hwy",
    "iso:country":"US",
    "sg:address":"4031 Bankhead Hwy",
    "sg:city":"Douglasville",
    "sg:classifiers":[
        {
            "category":"Organizations",
            "subcategory":"Religious Organization",
            "type":"Services"
        }
    ],
    "sg:phone":"+1 770 942 4134",
    "sg:postcode":"30134",
    "sg:province":"GA",
    "sg:website":"www.insidebbc.com",
    "wof:name":"Beulah Baptist Church",
    "wof:placetype":"venue"
},
  "geometry": {"coordinates":[-84.702904,33.781601],"type":"Point"}
}