{
  "type": "Feature",
  "properties": {
    "addr:full":"3611 Salem Rd Covington GA 30016",
    "addr:housenumber":"3611",
    "addr:postcode":"30016",
    "addr:street":"Salem Rd",
    "iso:country":"US",
    "sg:address":"3611 Salem Rd",
    "sg:city":"Covington",
    "sg:classifiers":[
        {
            "category":"Personal",
            "subcategory":"Beauty Salon",
            "type":"Services"
        }
    ],
    "sg:phone":"+1 678 625 0307",
    "sg:postcode":"30016",
    "sg:province":"GA",
    "wof:name":"Cleopatra Treasures",
    "wof:placetype":"venue"
},
  "geometry": {"coordinates":[-83.97022,33.593632],"type":"Point"}
}