{
  "type": "Feature",
  "properties": {
    "addr:full":"201 W Montgomery Xrd Savannah GA 31406",
    "addr:housenumber":"201",
    "addr:postcode":"31406",
    "addr:street":"W Montgomery Xrd",
    "iso:country":"US",
    "sg:address":"201 W Montgomery Xrd",
    "sg:city":"Savannah",
    "sg:classifiers":[
        {
            "category":"Building & Trades",
            "subcategory":"Construction",
            "type":"Services"
        }
    ],
    "sg:phone":"+1 912 631 1693",
    "sg:postcode":"31406",
    "sg:province":"GA",
    "sg:tags":[
        "contractor"
    ],
    "wof:name":"Titan Foundations",
    "wof:placetype":"venue"
},
  "geometry": {"coordinates":[-81.12749100000001,31.99929],"type":"Point"}
}