{
  "type": "Feature",
  "properties": {
    "addr:full":"157 Delahanty Ct Beech Island SC 29842",
    "addr:housenumber":"157",
    "addr:postcode":"29842",
    "addr:street":"Delahanty Ct",
    "iso:country":"US",
    "sg:address":"157 Delahanty Ct",
    "sg:city":"Beech Island",
    "sg:classifiers":[
        {
            "category":"Retail",
            "subcategory":"Auto Repair",
            "type":"Services"
        }
    ],
    "sg:phone":"+1 803 593 5563",
    "sg:postcode":"29842",
    "sg:province":"SC",
    "sg:tags":[
        "repairing",
        "automobile"
    ],
    "wof:name":"Redd Auto Repair",
    "wof:placetype":"venue"
},
  "geometry": {"coordinates":[-81.90979299999999,33.498577],"type":"Point"}
}