{
  "type": "Feature",
  "properties": {
    "iso:country":"US",
    "sg:address":"1108 S Wall St",
    "sg:city":"Calhoun",
    "sg:classifiers":[
        {
            "category":"Shopping",
            "subcategory":"Computers & Home Electronics",
            "type":"Retail Goods"
        }
    ],
    "sg:phone":"+1 706 625 5359",
    "sg:postcode":"30701",
    "sg:province":"GA",
    "sg:tags":[
        "satellite",
        "television",
        "cable"
    ],
    "wof:name":"Dish Power Satellite",
    "wof:placetype":"venue"
},
  "geometry": {"coordinates":[-84.938925,34.481625],"type":"Point"}
}