{
  "type": "Feature",
  "properties": {
    "addr:full":"718 S Davis St Nashville GA 31639",
    "addr:housenumber":"718",
    "addr:postcode":"31639",
    "addr:street":"S Davis St",
    "iso:country":"US",
    "sg:address":"718 S Davis St",
    "sg:city":"Nashville",
    "sg:classifiers":[
        {
            "category":"Restaurant",
            "type":"Food & Drink"
        }
    ],
    "sg:menulink":"http://www.allmenus.com/ga/nashville/101713-huddle-house/menu/",
    "sg:phone":"+1 229 686 9880",
    "sg:postcode":"31639",
    "sg:province":"GA",
    "sg:tags":[
        "american",
        "diner"
    ],
    "wof:name":"Huddle House",
    "wof:placetype":"venue"
},
  "geometry": {"coordinates":[-83.251329,31.196938],"type":"Point"}
}