{
  "type": "Feature",
  "properties": {
    "addr:full":"1950 Century Blvd NE Atlanta GA 30345",
    "addr:housenumber":"1950",
    "addr:postcode":"30345",
    "addr:street":"Century Blvd Ne",
    "iso:country":"US",
    "sg:address":"1950 Century Blvd NE",
    "sg:city":"Atlanta",
    "sg:classifiers":[
        {
            "category":"Professional",
            "subcategory":"Business Services",
            "type":"Services"
        }
    ],
    "sg:phone":"+1 404 870 8871",
    "sg:postcode":"30345",
    "sg:province":"GA",
    "wof:name":"Fussel & Associates LLC",
    "wof:placetype":"venue"
},
  "geometry": {"coordinates":[-84.310158,33.845404],"type":"Point"}
}