{
  "type": "Feature",
  "properties": {
    "iso:country":"US",
    "sg:address":"1360 Union Hill Rd",
    "sg:city":"Alpharetta",
    "sg:classifiers":[
        {
            "category":"Building & Trades",
            "subcategory":"Construction",
            "type":"Services"
        }
    ],
    "sg:phone":"+1 770 475 7551",
    "sg:postcode":"30004",
    "sg:province":"GA",
    "sg:tags":[
        "painter"
    ],
    "wof:name":"Spray On Siding Of North Ga",
    "wof:placetype":"venue"
},
  "geometry": {"coordinates":[-84.236805,34.114236],"type":"Point"}
}