{
  "type": "Feature",
  "properties": {
    "addr:full":"1303 Vada Rd Bainbridge GA 39817",
    "addr:housenumber":"1303",
    "addr:postcode":"39817",
    "addr:street":"Vada Rd",
    "iso:country":"US",
    "sg:address":"1303 Vada Rd",
    "sg:city":"Bainbridge",
    "sg:classifiers":[
        {
            "category":"Organizations",
            "subcategory":"Religious Organization",
            "type":"Services"
        }
    ],
    "sg:phone":"+1 229 246 5615",
    "sg:postcode":"39817",
    "sg:province":"GA",
    "sg:tags":[
        "church"
    ],
    "wof:name":"Morningside Baptist Church",
    "wof:placetype":"venue"
},
  "geometry": {"coordinates":[-84.55726199999999,30.915708],"type":"Point"}
}