{
  "type": "Feature",
  "properties": {
    "addr:full":"1761 Gerrard Rd Lavonia GA 30553",
    "addr:housenumber":"1761",
    "addr:postcode":"30553",
    "addr:street":"Gerrard Rd",
    "iso:country":"US",
    "sg:address":"1761 Gerrard Rd",
    "sg:city":"Lavonia",
    "sg:classifiers":[
        {
            "category":"Retail",
            "subcategory":"Auto Repair",
            "type":"Services"
        }
    ],
    "sg:phone":"+1 706 356 4279",
    "sg:postcode":"30553",
    "sg:province":"GA",
    "sg:tags":[
        "repairing",
        "automobile"
    ],
    "wof:name":"Ai Import Svc Ctr",
    "wof:placetype":"venue"
},
  "geometry": {"coordinates":[-83.12062,34.450077],"type":"Point"}
}