{
  "type": "Feature",
  "properties": {
    "iso:country":"US",
    "sg:address":"12 Dixon St",
    "sg:city":"Newnan",
    "sg:classifiers":[
        {
            "category":"Professional",
            "subcategory":"Business Services",
            "type":"Services"
        }
    ],
    "sg:phone":"+1 770 304 2083",
    "sg:postcode":"30263",
    "sg:province":"GA",
    "wof:name":"Breezeway Ventures Inc",
    "wof:placetype":"venue"
},
  "geometry": {"coordinates":[-84.80889500000001,33.381058],"type":"Point"}
}