{
  "type": "Feature",
  "properties": {
    "addr:full":"2520 Park Central Blvd Suite C4 Decatur GA 30035",
    "addr:housenumber":"2520",
    "addr:postcode":"30035",
    "addr:street":"Park Central Blvd Suite C4",
    "iso:country":"US",
    "sg:address":"2520 Park Central Blvd Suite C4",
    "sg:city":"Decatur",
    "sg:classifiers":[
        {
            "category":"Personal",
            "type":"Services"
        }
    ],
    "sg:phone":"+1 770 323 0424",
    "sg:postcode":"30035",
    "sg:province":"GA",
    "sg:tags":[
        "planning",
        "wedding"
    ],
    "sg:website":"awesomerents.com",
    "wof:name":"Awesome Events Party Rentals",
    "wof:placetype":"venue"
},
  "geometry": {"coordinates":[-84.172107,33.712716],"type":"Point"}
}