{
  "type": "Feature",
  "properties": {
    "addr:full":"977 N Hairston Rd Stone Mountain GA 30083",
    "addr:housenumber":"977",
    "addr:postcode":"30083",
    "addr:street":"N Hairston Rd",
    "iso:country":"US",
    "sg:address":"977 N Hairston Rd",
    "sg:city":"Stone Mountain",
    "sg:classifiers":[
        {
            "category":"Real Estate",
            "subcategory":"Real Estate Operator",
            "type":"Services"
        }
    ],
    "sg:phone":"+1 404 299 3614",
    "sg:postcode":"30083",
    "sg:province":"GA",
    "sg:tags":[
        "apartment"
    ],
    "wof:name":"Shadow Trace Apartments",
    "wof:placetype":"venue"
},
  "geometry": {"coordinates":[-84.193703,33.8055],"type":"Point"}
}