{
  "type": "Feature",
  "properties": {
    "iso:country":"US",
    "sg:address":"2445 Suncrest Ct",
    "sg:city":"Buford",
    "sg:classifiers":[
        {
            "category":"Restaurant",
            "type":"Food & Drink"
        }
    ],
    "sg:phone":"+1 678 793 1570",
    "sg:postcode":"30519",
    "sg:province":"GA",
    "sg:tags":[
        "eating"
    ],
    "wof:name":"KB Cooks",
    "wof:placetype":"venue"
},
  "geometry": {"coordinates":[-83.981499,34.04785],"type":"Point"}
}