{
  "type": "Feature",
  "properties": {
    "addr:full":"290 Cherokee Ave Athens GA 30606",
    "addr:housenumber":"290",
    "addr:postcode":"30606",
    "addr:street":"Cherokee Ave",
    "iso:country":"US",
    "sg:address":"290 Cherokee Ave",
    "sg:city":"Athens",
    "sg:classifiers":[
        {
            "category":"Health Services",
            "subcategory":"Doctor",
            "type":"Services"
        }
    ],
    "sg:phone":"+1 706 353 3755",
    "sg:postcode":"30606",
    "sg:province":"GA",
    "sg:tags":[
        "medical"
    ],
    "wof:name":"Shu T Tsao MD",
    "wof:placetype":"venue"
},
  "geometry": {"coordinates":[-83.389791,33.938997],"type":"Point"}
}