{
  "type": "Feature",
  "properties": {
    "addr:full":"5445 Mountain Trl Douglasville GA 30135",
    "addr:housenumber":"5445",
    "addr:postcode":"30135",
    "addr:street":"Mountain Trl",
    "iso:country":"US",
    "sg:address":"5445 Mountain Trl",
    "sg:city":"Douglasville",
    "sg:classifiers":[
        {
            "category":"Professional",
            "subcategory":"Business Services",
            "type":"Services"
        }
    ],
    "sg:phone":"+1 770 489 8254",
    "sg:postcode":"30135",
    "sg:province":"GA",
    "wof:name":"Este Residential Design",
    "wof:placetype":"venue"
},
  "geometry": {"coordinates":[-84.713759,33.731334],"type":"Point"}
}