{
  "type": "Feature",
  "properties": {
    "addr:full":"404 Pine Ave Albany GA 31701",
    "addr:housenumber":"404",
    "addr:postcode":"31701",
    "addr:street":"Pine Ave",
    "iso:country":"US",
    "sg:address":"404 Pine Ave",
    "sg:city":"Albany",
    "sg:classifiers":[
        {
            "category":"Professional",
            "subcategory":"Lawyer & Legal Services",
            "type":"Services"
        }
    ],
    "sg:phone":"+1 229 438 1024",
    "sg:postcode":"31701",
    "sg:province":"GA",
    "sg:tags":[
        "attorney",
        "copyright",
        "patent",
        "practice",
        "trademark",
        "law"
    ],
    "wof:name":"Brian D Bellamy",
    "wof:placetype":"venue"
},
  "geometry": {"coordinates":[-84.156111,31.578449],"type":"Point"}
}