{
  "type": "Feature",
  "properties": {
    "addr:full":"18 Collins Dr Cartersville GA 30120",
    "addr:housenumber":"18",
    "addr:postcode":"30120",
    "addr:street":"Collins Dr",
    "iso:country":"US",
    "sg:address":"18 Collins Dr",
    "sg:city":"Cartersville",
    "sg:classifiers":[
        {
            "category":"Professional",
            "subcategory":"Accounting & Tax Preparation",
            "type":"Services"
        }
    ],
    "sg:phone":"+1 770 386 3313",
    "sg:postcode":"30120",
    "sg:province":"GA",
    "wof:name":"Noble Team Inc",
    "wof:placetype":"venue"
},
  "geometry": {"coordinates":[-84.789387,34.192982],"type":"Point"}
}