{
  "type": "Feature",
  "properties": {
    "iso:country":"US",
    "sg:address":"179 Orange St",
    "sg:city":"Macon",
    "sg:classifiers":[
        {
            "category":"Retail",
            "subcategory":"Portrait Studio",
            "type":"Services"
        }
    ],
    "sg:phone":"+1 478 746 8350",
    "sg:postcode":"31201",
    "sg:province":"GA",
    "sg:tags":[
        "photographer",
        "photographers-portrait",
        "photo"
    ],
    "wof:name":"Hill Ken Wedding Photography",
    "wof:placetype":"venue"
},
  "geometry": {"coordinates":[-83.635226,32.844678],"type":"Point"}
}