{
  "type": "Feature",
  "properties": {
    "addr:full":"200 Snelson St Waycross GA 31501",
    "addr:housenumber":"200",
    "addr:postcode":"31501",
    "addr:street":"Snelson St",
    "iso:country":"US",
    "sg:address":"200 Snelson St",
    "sg:city":"Waycross",
    "sg:classifiers":[
        {
            "category":"Place Of Worship",
            "subcategory":"Church",
            "type":"Public Place"
        },
        {
            "category":"Place Of Worship",
            "type":"Public Place"
        }
    ],
    "sg:phone":"+1 912 338 0404",
    "sg:postcode":"31501",
    "sg:province":"GA",
    "sg:tags":[
        "churches-holiness"
    ],
    "wof:name":"The Way Of Holiness Church Inc",
    "wof:placetype":"venue"
},
  "geometry": {"coordinates":[-82.36170199999999,31.20171],"type":"Point"}
}