{
  "type": "Feature",
  "properties": {
    "addr:full":"317 Bankhead Hwy Carrollton GA 30117",
    "addr:housenumber":"317",
    "addr:postcode":"30117",
    "addr:street":"Bankhead Hwy",
    "iso:country":"US",
    "sg:address":"317 Bankhead Hwy",
    "sg:city":"Carrollton",
    "sg:classifiers":[
        {
            "category":"Professional",
            "subcategory":"Employment Agencies",
            "type":"Services"
        }
    ],
    "sg:phone":"+1 770 830 1221",
    "sg:postcode":"30117",
    "sg:province":"GA",
    "sg:tags":[
        "supply",
        "help",
        "contractor"
    ],
    "wof:name":"Avail-Ability Personnel Inc",
    "wof:placetype":"venue"
},
  "geometry": {"coordinates":[-85.06052,33.584797],"type":"Point"}
}