{
  "type": "Feature",
  "properties": {
    "iso:country":"US",
    "sg:address":"45431 Pointe Dr",
    "sg:city":"Hammond",
    "sg:classifiers":[
        {
            "category":"Banks & Credit Unions",
            "subcategory":"Investment Brokerage",
            "type":"Services"
        }
    ],
    "sg:phone":"+1 985 542 1060",
    "sg:postcode":"70401",
    "sg:province":"LA",
    "sg:tags":[
        "investing"
    ],
    "wof:name":"Np Investors Llc",
    "wof:placetype":"venue"
},
  "geometry": {"coordinates":[-84.393245,33.686666],"type":"Point"}
}