{
  "type": "Feature",
  "properties": {
    "addr:full":"125 Springwater Trce Woodstock GA 30188",
    "addr:housenumber":"125",
    "addr:postcode":"30188",
    "addr:street":"Springwater Trce",
    "iso:country":"US",
    "sg:address":"125 Springwater Trce",
    "sg:city":"Woodstock",
    "sg:classifiers":[
        {
            "category":"Building & Trades",
            "subcategory":"Landscaping Services",
            "type":"Services"
        }
    ],
    "sg:phone":"+1 770 924 0120",
    "sg:postcode":"30188",
    "sg:province":"GA",
    "sg:tags":[
        "landscape"
    ],
    "wof:name":"Buds & Blooms Landscaping",
    "wof:placetype":"venue"
},
  "geometry": {"coordinates":[-84.493325,34.143271],"type":"Point"}
}