{
  "type": "Feature",
  "properties": {
    "addr:full":"333 Shadowood Pkwy SE Atlanta GA 30339",
    "addr:housenumber":"333",
    "addr:postcode":"30339",
    "addr:street":"Shadowood Pkwy Se",
    "iso:country":"US",
    "sg:address":"333 Shadowood Pkwy SE",
    "sg:city":"Atlanta",
    "sg:classifiers":[
        {
            "category":"Retail",
            "subcategory":"Portrait Studio",
            "type":"Services"
        }
    ],
    "sg:phone":"+1 770 435 8682",
    "sg:postcode":"30339",
    "sg:province":"GA",
    "sg:tags":[
        "photo"
    ],
    "wof:name":"Toles Photography",
    "wof:placetype":"venue"
},
  "geometry": {"coordinates":[-84.45432599999999,33.898328],"type":"Point"}
}