{
  "type": "Feature",
  "properties": {
    "addr:full":"1504 Chattanooga Rd Dalton GA 30720",
    "addr:housenumber":"1504",
    "addr:postcode":"30720",
    "addr:street":"Chattanooga Rd",
    "iso:country":"US",
    "sg:address":"1504 Chattanooga Rd",
    "sg:city":"Dalton",
    "sg:classifiers":[
        {
            "category":"Health Services",
            "subcategory":"Doctor",
            "type":"Services"
        }
    ],
    "sg:phone":"+1 706 226 2273",
    "sg:postcode":"30720",
    "sg:province":"GA",
    "sg:tags":[
        "physician",
        "surgeon"
    ],
    "wof:name":"Priority Care",
    "wof:placetype":"venue"
},
  "geometry": {"coordinates":[-84.977295,34.785832],"type":"Point"}
}