{
  "type": "Feature",
  "properties": {
    "iso:country":"US",
    "sg:address":"611 McGruder St NE",
    "sg:city":"Atlanta",
    "sg:classifiers":[
        {
            "category":"Organizations",
            "subcategory":"Religious Organization",
            "type":"Services"
        }
    ],
    "sg:phone":"+1 404 525 2160",
    "sg:postcode":"30312",
    "sg:province":"GA",
    "wof:name":"Mc Gruder Church God In Christ",
    "wof:placetype":"venue"
},
  "geometry": {"coordinates":[-84.366153,33.75846],"type":"Point"}
}