{
  "type": "Feature",
  "properties": {
    "addr:full":"260 College Ave Athens GA 30601",
    "addr:housenumber":"260",
    "addr:postcode":"30601",
    "addr:street":"College Ave",
    "iso:country":"US",
    "sg:address":"260 College Ave",
    "sg:city":"Athens",
    "sg:classifiers":[
        {
            "category":"Professional",
            "subcategory":"Lawyer & Legal Services",
            "type":"Services"
        }
    ],
    "sg:phone":"+1 706 353 3300",
    "sg:postcode":"30601",
    "sg:province":"GA",
    "sg:tags":[
        "attorney"
    ],
    "wof:name":"James W Smith Law Offices",
    "wof:placetype":"venue"
},
  "geometry": {"coordinates":[-83.375575,33.958878],"type":"Point"}
}