{
  "type": "Feature",
  "properties": {
    "addr:full":"2284 Old Rex Morrow Rd Morrow GA 30260",
    "addr:housenumber":"2284",
    "addr:postcode":"30260",
    "addr:street":"Old Rex Morrow Rd",
    "iso:country":"US",
    "sg:address":"2284 Old Rex Morrow Rd",
    "sg:city":"Morrow",
    "sg:classifiers":[
        {
            "category":"Education",
            "subcategory":"Special Training",
            "type":"Public Place"
        }
    ],
    "sg:phone":"+1 404 362 3800",
    "sg:postcode":"30260",
    "sg:province":"GA",
    "sg:tags":[
        "curriculum",
        "datum"
    ],
    "wof:name":"Central Office",
    "wof:placetype":"venue"
},
  "geometry": {"coordinates":[-84.315338,33.594357],"type":"Point"}
}