{
  "type": "Feature",
  "properties": {
    "iso:country":"US",
    "sg:address":"223 Fair Ground Rd",
    "sg:city":"Swainsboro",
    "sg:classifiers":[
        {
            "category":"Manufacturing",
            "subcategory":"Metals",
            "type":"Manufacturing & Wholesale Goods"
        }
    ],
    "sg:phone":"+1 478 289 9003",
    "sg:postcode":"30401",
    "sg:province":"GA",
    "sg:tags":[
        "sanitary",
        "ware",
        "mfg"
    ],
    "wof:name":"Double D Metals",
    "wof:placetype":"venue"
},
  "geometry": {"coordinates":[-82.338369,32.626671],"type":"Point"}
}