{
  "type": "Feature",
  "properties": {
    "addr:full":"3235 Town Manor Cir Dacula GA 30019",
    "addr:housenumber":"3235",
    "addr:postcode":"ga 30019",
    "addr:street":"Town Manor Cir",
    "iso:country":"US",
    "sg:address":"3235 Town Manor Cir",
    "sg:city":"Dacula",
    "sg:classifiers":[
        {
            "category":"Freight",
            "type":"Transportation"
        }
    ],
    "sg:phone":"+1 770 963 6711",
    "sg:postcode":"30019",
    "sg:province":"GA",
    "sg:tags":[
        "general"
    ],
    "wof:name":"Sunbelt Warehouse Inc",
    "wof:placetype":"venue"
},
  "geometry": {"coordinates":[-83.91657600000001,34.059018],"type":"Point"}
}