{
  "type": "Feature",
  "properties": {
    "iso:country":"US",
    "sg:address":"1320 Union Hill Rd",
    "sg:city":"Alpharetta",
    "sg:classifiers":[
        {
            "category":"Manufacturing",
            "subcategory":"Printing",
            "type":"Manufacturing & Wholesale Goods"
        }
    ],
    "sg:phone":"+1 678 393 0355",
    "sg:postcode":"30004",
    "sg:province":"GA",
    "sg:tags":[
        "commercial"
    ],
    "wof:name":"Screensmith Inc",
    "wof:placetype":"venue"
},
  "geometry": {"coordinates":[-84.236784,34.115324],"type":"Point"}
}