{
  "type": "Feature",
  "properties": {
    "addr:full":"145 Valleywood Dr Athens GA 30606",
    "addr:housenumber":"145",
    "addr:postcode":"30606",
    "addr:street":"Valleywood Dr",
    "iso:country":"US",
    "sg:address":"145 Valleywood Dr",
    "sg:city":"Athens",
    "sg:classifiers":[
        {
            "category":"Professional",
            "subcategory":"Detective & Security Services",
            "type":"Services"
        }
    ],
    "sg:phone":"+1 706 546 1718",
    "sg:postcode":"30606",
    "sg:province":"GA",
    "sg:tags":[
        "car"
    ],
    "wof:name":"Tillman Security Inc",
    "wof:placetype":"venue"
},
  "geometry": {"coordinates":[-83.42548499999999,33.977042],"type":"Point"}
}