{
  "type": "Feature",
  "properties": {
    "iso:country":"US",
    "sg:address":"6372 Looper Lake Dr",
    "sg:city":"Flowery Branch",
    "sg:classifiers":[
        {
            "category":"Building & Trades",
            "subcategory":"Plumbing",
            "type":"Services"
        }
    ],
    "sg:phone":"+1 770 965 2047",
    "sg:postcode":"30542",
    "sg:province":"GA",
    "sg:tags":[
        "contractor"
    ],
    "wof:name":"Bart Plumbing Heating & C",
    "wof:placetype":"venue"
},
  "geometry": {"coordinates":[-83.893193,34.149309],"type":"Point"}
}