{
  "type": "Feature",
  "properties": {
    "iso:country":"US",
    "sg:address":"3425 Rushing Rd",
    "sg:city":"Augusta",
    "sg:classifiers":[
        {
            "category":"Retail",
            "subcategory":"Portrait Studio",
            "type":"Services"
        }
    ],
    "sg:phone":"+1 706 793 1999",
    "sg:postcode":"30906",
    "sg:province":"GA",
    "sg:tags":[
        "photo"
    ],
    "wof:name":"Mervin Jenkins Photography",
    "wof:placetype":"venue"
},
  "geometry": {"coordinates":[-82.037874,33.399661],"type":"Point"}
}