{
  "type": "Feature",
  "properties": {
    "addr:full":"3560 Piedmont Rd NE Atlanta GA 30305",
    "addr:housenumber":"3560",
    "addr:postcode":"30305",
    "addr:street":"Piedmont Rd Ne",
    "iso:country":"US",
    "sg:address":"3560 Piedmont Rd NE",
    "sg:city":"Atlanta",
    "sg:classifiers":[
        {
            "category":"Shopping",
            "subcategory":"Jewelry",
            "type":"Retail Goods"
        }
    ],
    "sg:phone":"+1 404 233 0110",
    "sg:postcode":"30305",
    "sg:province":"GA",
    "sg:tags":[
        "watch"
    ],
    "wof:name":"Rick Prince Watches",
    "wof:placetype":"venue"
},
  "geometry": {"coordinates":[-84.379661,33.851322],"type":"Point"}
}