{
  "type": "Feature",
  "properties": {
    "iso:country":"US",
    "sg:address":"984 Prospect Rd",
    "sg:city":"Rockmart",
    "sg:classifiers":[
        {
            "category":"Sports & Exercise",
            "subcategory":"Gym",
            "type":"Entertainment"
        }
    ],
    "sg:phone":"+1 770 684 6446",
    "sg:postcode":"30163",
    "sg:province":"GA",
    "sg:tags":[
        "fitness",
        "physical",
        "facility"
    ],
    "wof:name":"Energy Max Aerobics & Fitness",
    "wof:placetype":"venue"
},
  "geometry": {"coordinates":[-85.07082200000001,34.028815],"type":"Point"}
}