{
  "type": "Feature",
  "properties": {
    "iso:country":"US",
    "sg:address":"102 Johnny Ln",
    "sg:city":"Sylvester",
    "sg:classifiers":[
        {
            "category":"Building & Trades",
            "subcategory":"Electrical",
            "type":"Services"
        }
    ],
    "sg:phone":"+1 229 776 2888",
    "sg:postcode":"31791",
    "sg:province":"GA",
    "sg:tags":[
        "electrical",
        "contractor"
    ],
    "wof:name":"Quality Security Inc",
    "wof:placetype":"venue"
},
  "geometry": {"coordinates":[-83.87366299999999,31.583681],"type":"Point"}
}