{
  "type": "Feature",
  "properties": {
    "iso:country":"US",
    "sg:address":"4420B Bankers Cir",
    "sg:city":"Atlanta",
    "sg:classifiers":[
        {
            "category":"Shopping",
            "subcategory":"Clothing, Apparel, & Fashions",
            "type":"Retail Goods"
        },
        {
            "category":"Wholesale",
            "subcategory":"Apparel",
            "type":"Manufacturing & Wholesale Goods"
        },
        {
            "category":"Manufacturing",
            "subcategory":"Apparel",
            "type":"Manufacturing & Wholesale Goods"
        }
    ],
    "sg:phone":"+1 770 441 9622",
    "sg:postcode":"30360",
    "sg:province":"GA",
    "sg:tags":[
        "clothing-men's-wholesale",
        "t-shirts-wholesale",
        "t-shirt",
        "sportswear",
        "manufacturer"
    ],
    "wof:name":"A & G Inc",
    "wof:placetype":"venue"
},
  "geometry": {"coordinates":[-84.26490099999999,33.923581],"type":"Point"}
}