{
  "type": "Feature",
  "properties": {
    "iso:country":"US",
    "sg:address":"281 Shortleaf Pl",
    "sg:city":"Thomasville",
    "sg:classifiers":[
        {
            "category":"Manufacturing",
            "subcategory":"Signs",
            "type":"Manufacturing & Wholesale Goods"
        }
    ],
    "sg:phone":"+1 229 226 6609",
    "sg:postcode":"31792",
    "sg:province":"GA",
    "sg:tags":[
        "specialty",
        "mfg"
    ],
    "wof:name":"Ragan Signs",
    "wof:placetype":"venue"
},
  "geometry": {"coordinates":[-83.993182,30.876484],"type":"Point"}
}