{
  "type": "Feature",
  "properties": {
    "addr:full":"6678 Covington Hwy Lithonia GA 30058",
    "addr:housenumber":"6678",
    "addr:postcode":"30058",
    "addr:street":"Covington Hwy",
    "iso:country":"US",
    "sg:address":"6678 Covington Hwy",
    "sg:city":"Lithonia",
    "sg:classifiers":[
        {
            "category":"Food & Beverages",
            "subcategory":"Groceries & Convenience Stores",
            "type":"Retail Goods"
        }
    ],
    "sg:phone":"+1 770 593 7110",
    "sg:postcode":"30058",
    "sg:province":"GA",
    "sg:tags":[
        "supermarket"
    ],
    "wof:name":"Kroger",
    "wof:placetype":"venue"
},
  "geometry": {"coordinates":[-84.142205,33.717292],"type":"Point"}
}