{
  "type": "Feature",
  "properties": {
    "iso:country":"US",
    "sg:address":"5971 Bostwick Rd",
    "sg:city":"Bostwick",
    "sg:classifiers":[
        {
            "category":"Shopping",
            "subcategory":"Discount & Variety Stores",
            "type":"Retail Goods"
        }
    ],
    "sg:phone":"+1 706 342 0553",
    "sg:postcode":"30623",
    "sg:province":"GA",
    "sg:tags":[
        "merchandise",
        "general"
    ],
    "wof:name":"Bostwick Supply & Gin Co",
    "wof:placetype":"venue"
},
  "geometry": {"coordinates":[-83.514377,33.73727],"type":"Point"}
}