{
  "type": "Feature",
  "properties": {
    "addr:full":"17 Parkgate Dr NE Atlanta GA 30328",
    "addr:housenumber":"17",
    "addr:postcode":"30328",
    "addr:street":"Parkgate Dr Ne",
    "iso:country":"US",
    "sg:address":"17 Parkgate Dr NE",
    "sg:city":"Atlanta",
    "sg:classifiers":[
        {
            "category":"Shopping",
            "subcategory":"Clothing, Apparel, & Fashions",
            "type":"Retail Goods"
        }
    ],
    "sg:phone":"+1 678 320 0149",
    "sg:postcode":"30328",
    "sg:province":"GA",
    "sg:tags":[
        "urban",
        "via",
        "sale"
    ],
    "wof:name":"Bc Sales",
    "wof:placetype":"venue"
},
  "geometry": {"coordinates":[-84.358502,33.961957],"type":"Point"}
}