{
  "type": "Feature",
  "properties": {
    "addr:full":"400 Highway 49 North Byron GA 31008",
    "addr:housenumber":"400",
    "addr:postcode":"31008",
    "addr:street":"Highway 49 North",
    "iso:country":"US",
    "sg:address":"400 Highway 49 North",
    "sg:city":"Byron",
    "sg:classifiers":[
        {
            "category":"Fast Food",
            "type":"Food & Drink"
        },
        {
            "category":"Restaurant",
            "type":"Food & Drink"
        }
    ],
    "sg:phone":"+1 478 956 3900",
    "sg:postcode":"31008",
    "sg:province":"GA",
    "sg:tags":[
        "style",
        "family",
        "traditional",
        "american",
        "take",
        "chicken"
    ],
    "sg:website":"www.zaxbys.com",
    "wof:name":"Zaxby's",
    "wof:placetype":"venue"
},
  "geometry": {"coordinates":[-83.743515,32.659977],"type":"Point"}
}