{
  "type": "Feature",
  "properties": {
    "iso:country":"US",
    "sg:address":"5525 Nagel Ln",
    "sg:city":"Valdosta",
    "sg:classifiers":[
        {
            "category":"Professional",
            "subcategory":"Business Services",
            "type":"Services"
        }
    ],
    "sg:phone":"+1 229 559 8285",
    "sg:postcode":"31606",
    "sg:province":"GA",
    "wof:name":"McKeen Enterprises Inc",
    "wof:placetype":"venue"
},
  "geometry": {"coordinates":[-83.174645,30.738806],"type":"Point"}
}