{
  "type": "Feature",
  "properties": {
    "addr:full":"659 Auburn Avenue NE Atlanta GA 30312",
    "addr:housenumber":"659",
    "addr:postcode":"30312",
    "addr:street":"Auburn Avenue Ne",
    "iso:country":"US",
    "sg:address":"659 Auburn Avenue NE",
    "sg:city":"Atlanta",
    "sg:classifiers":[
        {
            "category":"Building & Trades",
            "subcategory":"Construction",
            "type":"Services"
        }
    ],
    "sg:phone":"+1 404 523 1760",
    "sg:postcode":"30312",
    "sg:province":"GA",
    "sg:tags":[
        "interior",
        "design"
    ],
    "wof:name":"C D & Associates",
    "wof:placetype":"venue"
},
  "geometry": {"coordinates":[-84.366809,33.756488],"type":"Point"}
}