{
  "type": "Feature",
  "properties": {
    "addr:full":"1610 Market Place Blvd Cumming GA 30041",
    "addr:housenumber":"1610",
    "addr:postcode":"30041",
    "addr:street":"Market Place Blvd",
    "iso:country":"US",
    "sg:address":"1610 Market Place Blvd",
    "sg:city":"Cumming",
    "sg:classifiers":[
        {
            "category":"Restaurant",
            "type":"Food & Drink"
        }
    ],
    "sg:menulink":"http://www.allmenus.com/ga/cumming/94270-provinos-italian-restaurant/menu/",
    "sg:phone":"+1 770 205 5605",
    "sg:postcode":"30041",
    "sg:province":"GA",
    "sg:tags":[
        "italian"
    ],
    "wof:name":"Provino's Italian Restaurant",
    "wof:placetype":"venue"
},
  "geometry": {"coordinates":[-84.130307,34.187838],"type":"Point"}
}