{
  "type": "Feature",
  "properties": {
    "iso:country":"US",
    "sg:address":"3653 Memorial Dr",
    "sg:city":"Decatur",
    "sg:classifiers":[
        {
            "category":"Retail",
            "subcategory":"Auto Repair",
            "type":"Services"
        }
    ],
    "sg:phone":"+1 404 286 2034",
    "sg:postcode":"30032",
    "sg:province":"GA",
    "sg:tags":[
        "repairing",
        "automobile",
        "general"
    ],
    "wof:name":"Decatur Auto Care",
    "wof:placetype":"venue"
},
  "geometry": {"coordinates":[-84.26600000000001,33.755874],"type":"Point"}
}