{
  "type": "Feature",
  "properties": {
    "addr:full":"2310 Bemiss Rd Valdosta GA 31602",
    "addr:housenumber":"2310",
    "addr:postcode":"31602",
    "addr:street":"Bemiss Rd",
    "iso:country":"US",
    "sg:address":"2310 Bemiss Rd",
    "sg:city":"Valdosta",
    "sg:classifiers":[
        {
            "category":"Professional",
            "subcategory":"Accounting & Tax Preparation",
            "type":"Services"
        }
    ],
    "sg:phone":"+1 229 242 1547",
    "sg:postcode":"31602",
    "sg:province":"GA",
    "sg:tags":[
        "bookkeeping",
        "general"
    ],
    "wof:name":"Jo Studstill",
    "wof:placetype":"venue"
},
  "geometry": {"coordinates":[-83.27971100000001,30.866505],"type":"Point"}
}