{
  "type": "Feature",
  "properties": {
    "iso:country":"US",
    "sg:address":"6334 US Hwy 29",
    "sg:city":"Tucker",
    "sg:classifiers":[
        {
            "category":"Restaurant",
            "type":"Food & Drink"
        }
    ],
    "sg:phone":"+1 770 938 6682",
    "sg:postcode":"30084",
    "sg:province":"GA",
    "wof:name":"Arby's",
    "wof:placetype":"venue"
},
  "geometry": {"coordinates":[-84.182012,33.867595],"type":"Point"}
}