{
  "type": "Feature",
  "properties": {
    "iso:country":"US",
    "sg:address":"1328 Greenville St",
    "sg:city":"La Grange",
    "sg:classifiers":[
        {
            "category":"Freight",
            "type":"Transportation"
        }
    ],
    "sg:phone":"+1 706 882 8674",
    "sg:postcode":"30241",
    "sg:province":"GA",
    "sg:tags":[
        "operator",
        "local",
        "trucking"
    ],
    "wof:name":"La Grange Bus Station",
    "wof:placetype":"venue"
},
  "geometry": {"coordinates":[-85.00161199999999,33.043057],"type":"Point"}
}