{
  "type": "Feature",
  "properties": {
    "addr:full":"3330 Cumberland Blvd Suite 500 Atlanta GA 30339",
    "addr:housenumber":"3330",
    "addr:postcode":"30339",
    "addr:street":"Cumberland Blvd Suite 500",
    "iso:country":"US",
    "sg:address":"3330 Cumberland Blvd Suite 500",
    "sg:city":"Atlanta",
    "sg:classifiers":[
        {
            "category":"Health Services",
            "subcategory":"Doctor",
            "type":"Services"
        },
        {
            "category":"Shopping",
            "subcategory":"Gifts & Souvenirs",
            "type":"Retail Goods"
        }
    ],
    "sg:phone":"+1 770 223 9677",
    "sg:postcode":"30339",
    "sg:province":"GA",
    "sg:tags":[
        "physician",
        "management",
        "weight",
        "loss",
        "surgeons",
        "basket"
    ],
    "wof:name":"BioFitness",
    "wof:placetype":"venue"
},
  "geometry": {"coordinates":[-84.461659,33.877109],"type":"Point"}
}