{
  "type": "Feature",
  "properties": {
    "iso:country":"US",
    "sg:address":"923 Dill Ave SW",
    "sg:city":"Atlanta",
    "sg:classifiers":[
        {
            "category":"Health Services",
            "subcategory":"Chiropractor",
            "type":"Services"
        }
    ],
    "sg:phone":"+1 404 753 3141",
    "sg:postcode":"30310",
    "sg:province":"GA",
    "wof:name":"Sparlin Eugene E Dr",
    "wof:placetype":"venue"
},
  "geometry": {"coordinates":[-84.421817,33.718419],"type":"Point"}
}