{
  "type": "Feature",
  "properties": {
    "iso:country":"US",
    "sg:address":"1401 Robert B Miller Jr",
    "sg:city":"Savannah",
    "sg:classifiers":[
        {
            "category":"Airport",
            "type":"Transportation"
        }
    ],
    "sg:phone":"+1 912 966 8283",
    "sg:postcode":"31408",
    "sg:province":"GA",
    "sg:tags":[
        "military",
        "force",
        "armed"
    ],
    "wof:name":"165th Aw/Fm-Fs",
    "wof:placetype":"venue"
},
  "geometry": {"coordinates":[-81.185614,32.130046],"type":"Point"}
}