{
  "type": "Feature",
  "properties": {
    "iso:country":"US",
    "sg:address":"211 Bullsboro Dr",
    "sg:city":"Newnan",
    "sg:classifiers":[
        {
            "category":"Banks & Credit Unions",
            "subcategory":"Bank",
            "type":"Services"
        }
    ],
    "sg:phone":"+1 770 251 4110",
    "sg:postcode":"30263",
    "sg:province":"GA",
    "sg:tags":[
        "loan"
    ],
    "wof:name":"Cash Express-Discount Title",
    "wof:placetype":"venue"
},
  "geometry": {"coordinates":[-84.776011,33.388444],"type":"Point"}
}