{
  "type": "Feature",
  "properties": {
    "iso:country":"US",
    "sg:address":"3801 Austell Rd",
    "sg:city":"Lawrenceville",
    "sg:classifiers":[
        {
            "category":"Restaurant",
            "type":"Food & Drink"
        }
    ],
    "sg:phone":"+1 770 948 8500",
    "sg:postcode":"30043",
    "sg:province":"GA",
    "sg:tags":[
        "pizza"
    ],
    "sg:website":"www.dominos.com",
    "wof:name":"Domino's Pizza",
    "wof:placetype":"venue"
},
  "geometry": {"coordinates":[-84.013496,34.002499],"type":"Point"}
}