{
  "type": "Feature",
  "properties": {
    "addr:full":"1879 Audubon Dr NE Atlanta GA 30329",
    "addr:housenumber":"1879",
    "addr:postcode":"30329",
    "addr:street":"Audubon Dr Ne",
    "iso:country":"US",
    "sg:address":"1879 Audubon Dr NE",
    "sg:city":"Atlanta",
    "sg:classifiers":[
        {
            "category":"Professional",
            "subcategory":"Computer Services",
            "type":"Services"
        }
    ],
    "sg:phone":"+1 404 329 9680",
    "sg:postcode":"30329",
    "sg:province":"GA",
    "sg:tags":[
        "related"
    ],
    "wof:name":"Thomas R Saunders",
    "wof:placetype":"venue"
},
  "geometry": {"coordinates":[-84.312831,33.832751],"type":"Point"}
}