{
  "type": "Feature",
  "properties": {
    "addr:full":"110 W Green St Bainbridge GA 39819",
    "addr:housenumber":"110",
    "addr:postcode":"39819",
    "addr:street":"W Green St",
    "iso:country":"US",
    "sg:address":"110 W Green St",
    "sg:city":"Bainbridge",
    "sg:classifiers":[
        {
            "category":"Real Estate",
            "subcategory":"Real Estate Agent",
            "type":"Services"
        }
    ],
    "sg:phone":"+1 229 246 7313",
    "sg:postcode":"39819",
    "sg:province":"GA",
    "sg:tags":[
        "appraiser"
    ],
    "wof:name":"Tipton Appraisal Svc",
    "wof:placetype":"venue"
},
  "geometry": {"coordinates":[-84.577439,30.900244],"type":"Point"}
}