{
  "type": "Feature",
  "properties": {
    "iso:country":"US",
    "sg:address":"660 W Warren Dr",
    "sg:city":"Forest Park",
    "sg:classifiers":[
        {
            "category":"Building & Trades",
            "subcategory":"Construction",
            "type":"Services"
        }
    ],
    "sg:phone":"+1 404 626 4575",
    "sg:postcode":"30297",
    "sg:province":"GA",
    "sg:tags":[
        "residential"
    ],
    "wof:name":"Circle C Grading",
    "wof:placetype":"venue"
},
  "geometry": {"coordinates":[-84.36764700000001,33.625774],"type":"Point"}
}