{
  "type": "Feature",
  "properties": {
    "addr:full":"2727 Paces Ferry Rd SE Atlanta GA 30339",
    "addr:housenumber":"2727",
    "addr:postcode":"30339",
    "addr:street":"Paces Ferry Rd Se",
    "iso:country":"US",
    "sg:address":"2727 Paces Ferry Rd SE",
    "sg:city":"Atlanta",
    "sg:classifiers":[
        {
            "category":"Insurance",
            "subcategory":"Insurance Agent",
            "type":"Services"
        },
        {
            "category":"Insurance",
            "subcategory":"Hazard Insurance",
            "type":"Services"
        }
    ],
    "sg:phone":"+1 770 951 2782",
    "sg:postcode":"30339",
    "sg:province":"GA",
    "sg:tags":[
        "consultant",
        "commercial",
        "analyst",
        "business"
    ],
    "sg:website":"http://www.iicinc.com",
    "wof:name":"Insurance Industry Consultants",
    "wof:placetype":"venue"
},
  "geometry": {"coordinates":[-84.474216,33.865364],"type":"Point"}
}