{
  "type": "Feature",
  "properties": {
    "addr:full":"3223 Grove Trl Acworth GA 30101",
    "addr:housenumber":"3223",
    "addr:postcode":"30101",
    "addr:street":"Grove Trl",
    "iso:country":"US",
    "sg:address":"3223 Grove Trl",
    "sg:city":"Acworth",
    "sg:classifiers":[
        {
            "category":"Food & Beverages",
            "subcategory":"Fruits & Vegetables",
            "type":"Retail Goods"
        }
    ],
    "sg:phone":"+1 678 574 8824",
    "sg:postcode":"30101",
    "sg:province":"GA",
    "sg:tags":[
        "produce"
    ],
    "wof:name":"Carrillo's Produce",
    "wof:placetype":"venue"
},
  "geometry": {"coordinates":[-84.648668,34.065863],"type":"Point"}
}