{
  "type": "Feature",
  "properties": {
    "iso:country":"US",
    "sg:address":"2133 Sugar Maple Ln NW",
    "sg:city":"Acworth",
    "sg:classifiers":[
        {
            "category":"Professional",
            "subcategory":"Business Services",
            "type":"Services"
        }
    ],
    "sg:phone":"+1 770 529 2889",
    "sg:postcode":"30101",
    "sg:province":"GA",
    "wof:name":"Lumina Design Group Inc",
    "wof:placetype":"venue"
},
  "geometry": {"coordinates":[-84.61401499999999,34.058203],"type":"Point"}
}