{
  "type": "Feature",
  "properties": {
    "iso:country":"US",
    "sg:address":"2303 Spring Lake Ct",
    "sg:city":"Morrow",
    "sg:classifiers":[
        {
            "category":"Professional",
            "subcategory":"Management & Consulting",
            "type":"Services"
        }
    ],
    "sg:phone":"+1 770 968 6569",
    "sg:postcode":"30260",
    "sg:province":"GA",
    "sg:tags":[
        "business"
    ],
    "wof:name":"Lwd Consulting Inc",
    "wof:placetype":"venue"
},
  "geometry": {"coordinates":[-84.33515,33.565045],"type":"Point"}
}