{
  "type": "Feature",
  "properties": {
    "iso:country":"US",
    "sg:address":"104 E Broad St",
    "sg:city":"Camilla",
    "sg:classifiers":[
        {
            "category":"Food & Beverages",
            "subcategory":"Groceries & Convenience Stores",
            "type":"Retail Goods"
        }
    ],
    "sg:phone":"+1 229 336 7380",
    "sg:postcode":"31730",
    "sg:province":"GA",
    "wof:name":"Shop & Save Svc Ctr",
    "wof:placetype":"venue"
},
  "geometry": {"coordinates":[-84.205015,31.231154],"type":"Point"}
}