{
  "type": "Feature",
  "properties": {
    "addr:full":"1370 Beechwood Cir Lawrenceville GA 30045",
    "addr:housenumber":"1370",
    "addr:postcode":"30045",
    "addr:street":"Beechwood Cir",
    "iso:country":"US",
    "sg:address":"1370 Beechwood Cir",
    "sg:city":"Lawrenceville",
    "sg:classifiers":[
        {
            "category":"Banks & Credit Unions",
            "subcategory":"Financial Services",
            "type":"Services"
        }
    ],
    "sg:phone":"+1 770 962 6000",
    "sg:postcode":"30045",
    "sg:province":"GA",
    "sg:tags":[
        "trust",
        "management"
    ],
    "wof:name":"Massey Living Trust",
    "wof:placetype":"venue"
},
  "geometry": {"coordinates":[-83.96005100000001,33.926387],"type":"Point"}
}