{
  "type": "Feature",
  "properties": {
    "iso:country":"US",
    "sg:address":"5452 Blue Cedar Dr",
    "sg:city":"Buford",
    "sg:classifiers":[
        {
            "category":"Shopping",
            "subcategory":"Books",
            "type":"Retail Goods"
        }
    ],
    "sg:phone":"+1 770 945 8824",
    "sg:postcode":"30518",
    "sg:province":"GA",
    "wof:name":"Build Books of Georgia Inc",
    "wof:placetype":"venue"
},
  "geometry": {"coordinates":[-84.07977200000001,34.103877],"type":"Point"}
}