{
  "type": "Feature",
  "properties": {
    "addr:full":"85 E Park Ln NE Atlanta GA 30309",
    "addr:housenumber":"85",
    "addr:postcode":"30309",
    "addr:street":"E Park Ln Ne",
    "iso:country":"US",
    "sg:address":"85 E Park Ln NE",
    "sg:city":"Atlanta",
    "sg:classifiers":[
        {
            "category":"Travel",
            "subcategory":"Campground",
            "type":"Entertainment"
        }
    ],
    "sg:phone":"+1 404 875 0291",
    "sg:postcode":"30309",
    "sg:province":"GA",
    "sg:tags":[
        "camp"
    ],
    "wof:name":"Brigadoon",
    "wof:placetype":"venue"
},
  "geometry": {"coordinates":[-84.374332,33.793324],"type":"Point"}
}