{
  "type": "Feature",
  "properties": {
    "addr:full":"182 Peachtree Way NE Atlanta GA 30305",
    "addr:housenumber":"182",
    "addr:postcode":"30305",
    "addr:street":"Peachtree Way Ne",
    "iso:country":"US",
    "sg:address":"182 Peachtree Way NE",
    "sg:city":"Atlanta",
    "sg:classifiers":[
        {
            "category":"Banks & Credit Unions",
            "subcategory":"Investment Brokerage",
            "type":"Services"
        }
    ],
    "sg:phone":"+1 404 261 5293",
    "sg:postcode":"30305",
    "sg:province":"GA",
    "sg:tags":[
        "security"
    ],
    "wof:name":"Tri States Securities Corp",
    "wof:placetype":"venue"
},
  "geometry": {"coordinates":[-84.381709,33.827027],"type":"Point"}
}