{
  "type": "Feature",
  "properties": {
    "addr:full":"3568 Casteel Rd Marietta GA 30062",
    "addr:housenumber":"3568",
    "addr:postcode":"30062",
    "addr:street":"Casteel Rd",
    "iso:country":"US",
    "sg:address":"3568 Casteel Rd",
    "sg:city":"Marietta",
    "sg:classifiers":[
        {
            "category":"Wholesale",
            "subcategory":"Electrical",
            "type":"Manufacturing & Wholesale Goods"
        }
    ],
    "sg:phone":"+1 770 509 8895",
    "sg:postcode":"30062",
    "sg:province":"GA",
    "sg:tags":[
        "entry",
        "security",
        "based",
        "telephone",
        "system"
    ],
    "wof:name":"Ameritel Corporation",
    "wof:placetype":"venue"
},
  "geometry": {"coordinates":[-84.44954799999999,34.003924],"type":"Point"}
}