{
  "type": "Feature",
  "properties": {
    "iso:country":"US",
    "sg:address":"1084 Woodruff Plantation Pkwy",
    "sg:city":"Marietta",
    "sg:classifiers":[
        {
            "category":"Building & Trades",
            "subcategory":"Construction",
            "type":"Services"
        }
    ],
    "sg:phone":"+1 770 953 1084",
    "sg:postcode":"30067",
    "sg:province":"GA",
    "sg:tags":[
        "house"
    ],
    "wof:name":"John Todd Builders",
    "wof:placetype":"venue"
},
  "geometry": {"coordinates":[-84.450355,33.923363],"type":"Point"}
}