{
  "type": "Feature",
  "properties": {
    "iso:country":"US",
    "sg:address":"408 W Main St",
    "sg:city":"Bloomingdale",
    "sg:classifiers":[
        {
            "category":"Building & Trades",
            "subcategory":"Cleaning & Sanitation",
            "type":"Services"
        }
    ],
    "sg:phone":"+1 912 330 9300",
    "sg:postcode":"31302",
    "sg:province":"GA",
    "sg:tags":[
        "janitor"
    ],
    "wof:name":"Moores Cleaning Svc",
    "wof:placetype":"venue"
},
  "geometry": {"coordinates":[-81.307142,32.13042],"type":"Point"}
}