{
  "type": "Feature",
  "properties": {
    "addr:full":"14 Suffolk Pl SW Lilburn GA 30047",
    "addr:housenumber":"14",
    "addr:postcode":"30047",
    "addr:street":"Suffolk Pl Sw",
    "iso:country":"US",
    "sg:address":"14 Suffolk Pl SW",
    "sg:city":"Lilburn",
    "sg:classifiers":[
        {
            "category":"Professional",
            "subcategory":"Accounting & Tax Preparation",
            "type":"Services"
        }
    ],
    "sg:phone":"+1 770 931 7882",
    "sg:postcode":"30047",
    "sg:province":"GA",
    "sg:tags":[
        "return",
        "filing"
    ],
    "wof:name":"Real Taxes",
    "wof:placetype":"venue"
},
  "geometry": {"coordinates":[-84.152731,33.873873],"type":"Point"}
}