{
  "type": "Feature",
  "properties": {
    "iso:country":"US",
    "sg:address":"109 Lakeview Cir NE",
    "sg:city":"Milledgeville",
    "sg:classifiers":[
        {
            "category":"Retail",
            "subcategory":"Auto Repair",
            "type":"Services"
        }
    ],
    "sg:phone":"+1 478 452 2531",
    "sg:postcode":"31061",
    "sg:province":"GA",
    "sg:tags":[
        "general"
    ],
    "wof:name":"Gulf Garage Doors Inc",
    "wof:placetype":"venue"
},
  "geometry": {"coordinates":[-83.23962,33.158829],"type":"Point"}
}