{
  "type": "Feature",
  "properties": {
    "iso:country":"US",
    "sg:address":"1185 Beaver Ruin Rd",
    "sg:city":"Norcross",
    "sg:classifiers":[
        {
            "category":"Manufacturing",
            "subcategory":"Tools & Machinery",
            "type":"Manufacturing & Wholesale Goods"
        }
    ],
    "sg:phone":"+1 770 921 0397",
    "sg:postcode":"30093",
    "sg:province":"GA",
    "sg:tags":[
        "pump"
    ],
    "wof:name":"Georgia Chemical Equipment Co",
    "wof:placetype":"venue"
},
  "geometry": {"coordinates":[-84.138498,33.923936],"type":"Point"}
}