{
  "type": "Feature",
  "properties": {
    "addr:full":"791 Moores Mill Rd Atlanta GA 30327",
    "addr:housenumber":"791",
    "addr:postcode":"30327",
    "addr:street":"Moores Mill Rd",
    "iso:country":"US",
    "sg:address":"791 Moores Mill Rd",
    "sg:city":"Atlanta",
    "sg:classifiers":[
        {
            "category":"Professional",
            "type":"Services"
        }
    ],
    "sg:phone":"+1 404 261 4227",
    "sg:postcode":"30327",
    "sg:province":"GA",
    "wof:name":"Amanda Kibler",
    "wof:placetype":"venue"
},
  "geometry": {"coordinates":[-84.414604,33.841132],"type":"Point"}
}