{
  "type": "Feature",
  "properties": {
    "iso:country":"US",
    "sg:address":"1000 Whitlock Ave NW Ste 200",
    "sg:city":"Marietta",
    "sg:classifiers":[
        {
            "category":"Banks & Credit Unions",
            "subcategory":"Bank",
            "type":"Services"
        }
    ],
    "sg:phone":"+1 770 423 1223",
    "sg:postcode":"30064",
    "sg:province":"GA",
    "wof:name":"Best Bank",
    "wof:placetype":"venue"
},
  "geometry": {"coordinates":[-84.580973,33.951958],"type":"Point"}
}