{
  "type": "Feature",
  "properties": {
    "addr:full":"135 Mount Carmel Rd McDonough GA 30253",
    "addr:housenumber":"135",
    "addr:postcode":"30253",
    "addr:street":"Mount Carmel Rd",
    "iso:country":"US",
    "sg:address":"135 Mount Carmel Rd",
    "sg:city":"McDonough",
    "sg:classifiers":[
        {
            "category":"Home & Garden",
            "subcategory":"Garden Supply",
            "type":"Retail Goods"
        }
    ],
    "sg:phone":"+1 678 583 5000",
    "sg:postcode":"30253",
    "sg:province":"GA",
    "sg:tags":[
        "nursery",
        "gardening"
    ],
    "sg:website":"www.johndeerelandscapes.com",
    "wof:name":"John Deere Landscapes Inc",
    "wof:placetype":"venue"
},
  "geometry": {"coordinates":[-84.201599,33.453899],"type":"Point"}
}