{
  "type": "Feature",
  "properties": {
    "iso:country":"US",
    "sg:address":"2885 Lower Union Hill Rd",
    "sg:city":"Canton",
    "sg:classifiers":[
        {
            "category":"Restaurant",
            "type":"Food & Drink"
        }
    ],
    "sg:phone":"+1 770 475 2324",
    "sg:postcode":"30115",
    "sg:province":"GA",
    "sg:tags":[
        "eating"
    ],
    "wof:name":"Sugar Pike Junctions",
    "wof:placetype":"venue"
},
  "geometry": {"coordinates":[-84.383731,34.193959],"type":"Point"}
}