{
  "type": "Feature",
  "properties": {
    "iso:country":"US",
    "sg:address":"57 Railroad St NW",
    "sg:city":"Lilburn",
    "sg:classifiers":[
        {
            "category":"Building & Trades",
            "subcategory":"Construction",
            "type":"Services"
        }
    ],
    "sg:phone":"+1 770 921 2569",
    "sg:postcode":"30047",
    "sg:province":"GA",
    "sg:tags":[
        "cabinet",
        "build",
        "maker"
    ],
    "sg:website":"www.rfscabinets.com",
    "wof:name":"RFS Cabinets",
    "wof:placetype":"venue"
},
  "geometry": {"coordinates":[-84.135451,33.884919],"type":"Point"}
}