{
  "type": "Feature",
  "properties": {
    "iso:country":"US",
    "sg:address":"5933 Bobbin Ln",
    "sg:city":"Lithonia",
    "sg:classifiers":[
        {
            "category":"Building & Trades",
            "subcategory":"Cleaning & Sanitation",
            "type":"Services"
        }
    ],
    "sg:phone":"+1 770 981 8838",
    "sg:postcode":"30058",
    "sg:province":"GA",
    "sg:tags":[
        "janitorial"
    ],
    "wof:name":"Clear Vision Enterprises",
    "wof:placetype":"venue"
},
  "geometry": {"coordinates":[-84.145623,33.731339],"type":"Point"}
}