{
  "type": "Feature",
  "properties": {
    "addr:full":"203 Fair St Lagrange GA 30241",
    "addr:housenumber":"203",
    "addr:postcode":"30241",
    "addr:street":"Fair St",
    "iso:country":"US",
    "sg:address":"203 Fair St",
    "sg:city":"Lagrange",
    "sg:classifiers":[
        {
            "category":"Organizations",
            "subcategory":"Religious Organization",
            "type":"Services"
        }
    ],
    "sg:phone":"+1 706 884 8787",
    "sg:postcode":"30241",
    "sg:province":"GA",
    "sg:tags":[
        "church"
    ],
    "wof:name":"United Methodist Hispanic",
    "wof:placetype":"venue"
},
  "geometry": {"coordinates":[-85.015528,33.043774],"type":"Point"}
}