{
  "type": "Feature",
  "properties": {
    "addr:full":"33 Palm Ln Buena Vista GA 31830",
    "addr:housenumber":"33",
    "addr:postcode":"31830",
    "addr:street":"Palm Ln",
    "iso:country":"US",
    "sg:address":"33 Palm Ln",
    "sg:city":"Buena Vista",
    "sg:classifiers":[
        {
            "category":"Farming",
            "subcategory":"Farm & Veterinary Services",
            "type":"Manufacturing & Wholesale Goods"
        }
    ],
    "sg:phone":"+1 229 277 0093",
    "sg:postcode":"31830",
    "sg:province":"GA",
    "wof:name":"Southwestern Farm Svc Inc",
    "wof:placetype":"venue"
},
  "geometry": {"coordinates":[-84.769976,32.921504],"type":"Point"}
}