{
  "type": "Feature",
  "properties": {
    "addr:full":"2660 Holcomb Bridge Rd Alpharetta GA 30022",
    "addr:housenumber":"2660",
    "addr:postcode":"30022",
    "addr:street":"Holcomb Bridge Rd",
    "iso:country":"US",
    "sg:address":"2660 Holcomb Bridge Rd",
    "sg:city":"Alpharetta",
    "sg:phone":"+1 770 642 7440",
    "sg:postcode":"30022",
    "sg:province":"GA",
    "sg:tags":[
        "mail",
        "electronic"
    ],
    "wof:name":"E Media Trade Dotnet",
    "wof:placetype":"venue"
},
  "geometry": {"coordinates":[-84.28251400000001,33.996112],"type":"Point"}
}