{
  "type": "Feature",
  "properties": {
    "addr:full":"5107 Oak St Eastman GA 31023",
    "addr:housenumber":"5107",
    "addr:postcode":"31023",
    "addr:street":"Oak St",
    "iso:country":"US",
    "sg:address":"5107 Oak St",
    "sg:city":"Eastman",
    "sg:classifiers":[
        {
            "category":"Place Of Worship",
            "type":"Public Place"
        }
    ],
    "sg:phone":"+1 478 374 0442",
    "sg:postcode":"31023",
    "sg:province":"GA",
    "sg:tags":[
        "church"
    ],
    "sg:website":"http://www.abc-usa.org",
    "wof:name":"First Baptist Church",
    "wof:placetype":"venue"
},
  "geometry": {"coordinates":[-83.192745,32.21059],"type":"Point"}
}