{
  "type": "Feature",
  "properties": {
    "addr:full":"1395 Georgia Ave Macon GA 31201",
    "addr:housenumber":"1395",
    "addr:postcode":"31201",
    "addr:street":"Georgia Ave",
    "iso:country":"US",
    "sg:address":"1395 Georgia Ave",
    "sg:city":"Macon",
    "sg:classifiers":[
        {
            "category":"Shopping",
            "subcategory":"Bicycles & Sporting Goods",
            "type":"Retail Goods"
        }
    ],
    "sg:phone":"+1 478 750 7665",
    "sg:postcode":"31201",
    "sg:province":"GA",
    "wof:name":"Poolsharks & Mermaids",
    "wof:placetype":"venue"
},
  "geometry": {"coordinates":[-83.640669,32.840801],"type":"Point"}
}