{
  "type": "Feature",
  "properties": {
    "addr:full":"4808 Chelsea Way Acworth GA 30102",
    "addr:housenumber":"4808",
    "addr:postcode":"30102",
    "addr:street":"Chelsea Way",
    "iso:country":"US",
    "sg:address":"4808 Chelsea Way",
    "sg:city":"Acworth",
    "sg:classifiers":[
        {
            "category":"Building & Trades",
            "subcategory":"Construction",
            "type":"Services"
        }
    ],
    "sg:phone":"+1 770 928 2885",
    "sg:postcode":"30102",
    "sg:province":"GA",
    "sg:tags":[
        "house"
    ],
    "wof:name":"Crofts Craftsmen",
    "wof:placetype":"venue"
},
  "geometry": {"coordinates":[-84.568224,34.073879],"type":"Point"}
}