{
  "type": "Feature",
  "properties": {
    "addr:full":"5373 Wydella Rd SW Lilburn GA 30047",
    "addr:housenumber":"5373",
    "addr:postcode":"30047",
    "addr:street":"Wydella Rd Sw",
    "iso:country":"US",
    "sg:address":"5373 Wydella Rd SW",
    "sg:city":"Lilburn",
    "sg:classifiers":[
        {
            "category":"Organizations",
            "subcategory":"Religious Organization",
            "type":"Services"
        }
    ],
    "sg:phone":"+1 770 381 7488",
    "sg:postcode":"30047",
    "sg:province":"GA",
    "sg:tags":[
        "church"
    ],
    "wof:name":"St Stephen The Martyr",
    "wof:placetype":"venue"
},
  "geometry": {"coordinates":[-84.141679,33.864614],"type":"Point"}
}