{
  "type": "Feature",
  "properties": {
    "iso:country":"US",
    "sg:address":"105 Weatherstone Dr # 640",
    "sg:city":"Woodstock",
    "sg:classifiers":[
        {
            "category":"Health Services",
            "subcategory":"Chiropractor",
            "type":"Services"
        }
    ],
    "sg:phone":"+1 770 592 6696",
    "sg:postcode":"30188",
    "sg:province":"GA",
    "sg:tags":[
        "chiropractic"
    ],
    "wof:name":"Dr Robert Chifone",
    "wof:placetype":"venue"
},
  "geometry": {"coordinates":[-84.471413,34.089026],"type":"Point"}
}