{
  "type": "Feature",
  "properties": {
    "addr:full":"163 Northcutt Rd Ellijay GA 30540",
    "addr:housenumber":"163",
    "addr:postcode":"30540",
    "addr:street":"Northcutt Rd",
    "iso:country":"US",
    "sg:address":"163 Northcutt Rd",
    "sg:city":"Ellijay",
    "sg:classifiers":[
        {
            "category":"Professional",
            "subcategory":"Research",
            "type":"Services"
        }
    ],
    "sg:phone":"+1 706 635 2847",
    "sg:postcode":"30540",
    "sg:province":"GA",
    "sg:tags":[
        "environmental",
        "ecological"
    ],
    "sg:website":"www.bctweb.com",
    "wof:name":"Bio Conversion Technology Inc",
    "wof:placetype":"venue"
},
  "geometry": {"coordinates":[-84.458011,34.721141],"type":"Point"}
}