{
  "type": "Feature",
  "properties": {
    "addr:full":"1430 Towne Lake Pkwy Woodstock GA 30189",
    "addr:housenumber":"1430",
    "addr:postcode":"30189",
    "addr:street":"Towne Lake Pkwy",
    "iso:country":"US",
    "sg:address":"1430 Towne Lake Pkwy",
    "sg:city":"Woodstock",
    "sg:phone":"+1 770 419 4049",
    "sg:postcode":"30189",
    "sg:province":"GA",
    "sg:website":"http://storedetail.publix.com/USA/GA/1430-Towne-Lake-Pkwy.html",
    "wof:name":"Publix Super Market",
    "wof:placetype":"venue"
},
  "geometry": {"coordinates":[-84.540111,34.104311],"type":"Point"}
}