{
  "type": "Feature",
  "properties": {
    "addr:full":"111 Windy Oaks Rd Dahlonega GA 30533",
    "addr:housenumber":"111",
    "addr:postcode":"30533",
    "addr:street":"Windy Oaks Rd",
    "iso:country":"US",
    "sg:address":"111 Windy Oaks Rd",
    "sg:city":"Dahlonega",
    "sg:classifiers":[
        {
            "category":"Home & Garden",
            "subcategory":"Furniture",
            "type":"Retail Goods"
        }
    ],
    "sg:phone":"+1 706 864 6082",
    "sg:postcode":"30533",
    "sg:province":"GA",
    "wof:name":"Lalija Rustic Art",
    "wof:placetype":"venue"
},
  "geometry": {"coordinates":[-84.07600600000001,34.510061],"type":"Point"}
}