{
  "type": "Feature",
  "properties": {
    "addr:full":"250 Johnson Rd N Crandall GA 30711",
    "addr:housenumber":"250",
    "addr:postcode":"30711",
    "addr:street":"Johnson Rd N",
    "iso:country":"US",
    "sg:address":"250 Johnson Rd N",
    "sg:city":"Crandall",
    "sg:classifiers":[
        {
            "category":"Retail",
            "subcategory":"Repair Shop",
            "type":"Services"
        },
        {
            "category":"Manufacturing",
            "subcategory":"Signs",
            "type":"Manufacturing & Wholesale Goods"
        }
    ],
    "sg:phone":"+1 706 260 0965",
    "sg:postcode":"30711",
    "sg:province":"GA",
    "sg:tags":[
        "signs-erectors",
        "hanger",
        "signs-maintenance"
    ],
    "wof:name":"The Sign Doctor L L C",
    "wof:placetype":"venue"
},
  "geometry": {"coordinates":[-84.801259,34.970631],"type":"Point"}
}