{
  "type": "Feature",
  "properties": {
    "addr:full":"224 Baywood Cir La Grange GA 30240",
    "addr:housenumber":"224",
    "addr:postcode":"30240",
    "addr:street":"Baywood Cir",
    "iso:country":"US",
    "sg:address":"224 Baywood Cir",
    "sg:city":"La Grange",
    "sg:classifiers":[
        {
            "category":"Professional",
            "type":"Services"
        }
    ],
    "sg:phone":"+1 706 845 8180",
    "sg:postcode":"30240",
    "sg:province":"GA",
    "wof:name":"E F Moreman",
    "wof:placetype":"venue"
},
  "geometry": {"coordinates":[-85.09006599999999,33.058923],"type":"Point"}
}