{
  "type": "Feature",
  "properties": {
    "iso:country":"US",
    "sg:address":"3165 Caney Rd",
    "sg:city":"Cumming",
    "sg:classifiers":[
        {
            "category":"Freight",
            "type":"Transportation"
        }
    ],
    "sg:phone":"+1 770 663 6396",
    "sg:postcode":"30041",
    "sg:province":"GA",
    "wof:name":"Moving Water LLC",
    "wof:placetype":"venue"
},
  "geometry": {"coordinates":[-84.17872300000001,34.095497],"type":"Point"}
}