{
  "type": "Feature",
  "properties": {
    "addr:full":"1010 Norcross Industrial Ct Norcross GA 30071",
    "addr:housenumber":"1010",
    "addr:postcode":"30071",
    "addr:street":"Norcross Industrial Ct",
    "iso:country":"US",
    "sg:address":"1010 Norcross Industrial Ct",
    "sg:city":"Norcross",
    "sg:classifiers":[
        {
            "category":"Home & Garden",
            "subcategory":"Home Furnishings",
            "type":"Retail Goods"
        }
    ],
    "sg:phone":"+1 770 729 3985",
    "sg:postcode":"30071",
    "sg:province":"GA",
    "sg:tags":[
        "window",
        "covering"
    ],
    "wof:name":"Contract Windoware",
    "wof:placetype":"venue"
},
  "geometry": {"coordinates":[-84.201441,33.948481],"type":"Point"}
}