{
  "type": "Feature",
  "properties": {
    "addr:full":"2626 Princess Ln SE Marietta GA 30067",
    "addr:housenumber":"2626",
    "addr:postcode":"30067",
    "addr:street":"Princess Ln Se",
    "iso:country":"US",
    "sg:address":"2626 Princess Ln SE",
    "sg:city":"Marietta",
    "sg:classifiers":[
        {
            "category":"Landmark",
            "subcategory":"Tourist Information",
            "type":"Public Place"
        }
    ],
    "sg:phone":"+1 770 977 0679",
    "sg:postcode":"30067",
    "sg:province":"GA",
    "sg:tags":[
        "promoter",
        "tours-operators"
    ],
    "wof:name":"Lady Elegant Tours Inc",
    "wof:placetype":"venue"
},
  "geometry": {"coordinates":[-84.47713400000001,33.9394],"type":"Point"}
}