{
  "type": "Feature",
  "properties": {
    "iso:country":"US",
    "sg:address":"12544 Darvish Ln",
    "sg:city":"Alpharetta",
    "sg:classifiers":[
        {
            "category":"Restaurant",
            "type":"Food & Drink"
        }
    ],
    "sg:phone":"+1 770 475 4335",
    "sg:postcode":"30005",
    "sg:province":"GA",
    "sg:tags":[
        "japanese"
    ],
    "wof:name":"Little Tokyo",
    "wof:placetype":"venue"
},
  "geometry": {"coordinates":[-84.206079,34.084544],"type":"Point"}
}