{
  "type": "Feature",
  "properties": {
    "addr:full":"257 Oakridge Trl Fayetteville GA 30214",
    "addr:housenumber":"257",
    "addr:postcode":"30214",
    "addr:street":"Oakridge Trl",
    "iso:country":"US",
    "sg:address":"257 Oakridge Trl",
    "sg:city":"Fayetteville",
    "sg:classifiers":[
        {
            "category":"Personal",
            "subcategory":"Barber",
            "type":"Services"
        }
    ],
    "sg:phone":"+1 404 983 1952",
    "sg:postcode":"30214",
    "sg:province":"GA",
    "sg:tags":[
        "shop"
    ],
    "wof:name":"Tom Barber Inc",
    "wof:placetype":"venue"
},
  "geometry": {"coordinates":[-84.521286,33.515686],"type":"Point"}
}