{
  "type": "Feature",
  "properties": {
    "iso:country":"US",
    "sg:address":"5416 Trumpet Vine Trl SE",
    "sg:city":"Mableton",
    "sg:classifiers":[
        {
            "category":"Professional",
            "subcategory":"Accounting & Tax Preparation",
            "type":"Services"
        }
    ],
    "sg:phone":"+1 770 745 7577",
    "sg:postcode":"30126",
    "sg:province":"GA",
    "sg:tags":[
        "accountant"
    ],
    "wof:name":"Tom Ellis & Company PC",
    "wof:placetype":"venue"
},
  "geometry": {"coordinates":[-84.52600099999999,33.818298],"type":"Point"}
}