{
  "type": "Feature",
  "properties": {
    "iso:country":"US",
    "sg:address":"3692 Paddington Trail",
    "sg:city":"Rex",
    "sg:classifiers":[
        {
            "category":"Personal",
            "subcategory":"Beauty Salon",
            "type":"Services"
        }
    ],
    "sg:phone":"+1 770 310 7407",
    "sg:postcode":"30273",
    "sg:province":"GA",
    "wof:name":"KINKX SALON",
    "wof:placetype":"venue"
},
  "geometry": {"coordinates":[-84.269257,33.589008],"type":"Point"}
}