{
  "type": "Feature",
  "properties": {
    "iso:country":"US",
    "sg:address":"3866 Grand Forest Dr NW",
    "sg:city":"Norcross",
    "sg:classifiers":[
        {
            "category":"Shopping",
            "subcategory":"Computers & Home Electronics",
            "type":"Retail Goods"
        }
    ],
    "sg:phone":"+1 770 242 9499",
    "sg:postcode":"30092",
    "sg:province":"GA",
    "sg:tags":[
        "radio",
        "television",
        "electronic",
        "store"
    ],
    "wof:name":"Interactive Automation LLC",
    "wof:placetype":"venue"
},
  "geometry": {"coordinates":[-84.241528,33.966867],"type":"Point"}
}