{
  "type": "Feature",
  "properties": {
    "addr:full":"1540 Marble Way Lawrenceville GA 30043",
    "addr:housenumber":"1540",
    "addr:postcode":"30043",
    "addr:street":"Marble Way",
    "iso:country":"US",
    "sg:address":"1540 Marble Way",
    "sg:city":"Lawrenceville",
    "sg:classifiers":[
        {
            "category":"Home & Garden",
            "subcategory":"Building Materials",
            "type":"Retail Goods"
        }
    ],
    "sg:phone":"+1 770 513 2022",
    "sg:postcode":"30043",
    "sg:province":"GA",
    "sg:tags":[
        "glass",
        "window",
        "plate"
    ],
    "wof:name":"G & M Glass & Door Service",
    "wof:placetype":"venue"
},
  "geometry": {"coordinates":[-83.97582199999999,34.046594],"type":"Point"}
}