{
  "type": "Feature",
  "properties": {
    "iso:country":"US",
    "sg:address":"1943 Shiloh Valley Trl NW",
    "sg:city":"Kennesaw",
    "sg:classifiers":[
        {
            "category":"Building & Trades",
            "subcategory":"Cleaning & Sanitation",
            "type":"Services"
        }
    ],
    "sg:phone":"+1 678 581 9951",
    "sg:postcode":"30144",
    "sg:province":"GA",
    "sg:tags":[
        "home"
    ],
    "sg:website":"www.aquastarmaids.com",
    "wof:name":"AquaStar Cleaning Services",
    "wof:placetype":"venue"
},
  "geometry": {"coordinates":[-84.563318,33.998584],"type":"Point"}
}