{
  "type": "Feature",
  "properties": {
    "addr:full":"4169 Clairmont Rd Atlanta GA 30341",
    "addr:housenumber":"4169",
    "addr:postcode":"30341",
    "addr:street":"Clairmont Rd",
    "iso:country":"US",
    "sg:address":"4169 Clairmont Rd",
    "sg:city":"Atlanta",
    "sg:classifiers":[
        {
            "category":"Building & Trades",
            "subcategory":"Construction",
            "type":"Services"
        }
    ],
    "sg:phone":"+1 770 986 8600",
    "sg:postcode":"30341",
    "sg:province":"GA",
    "sg:tags":[
        "house",
        "siding",
        "contractor"
    ],
    "wof:name":"Insulated Wall Systems",
    "wof:placetype":"venue"
},
  "geometry": {"coordinates":[-84.31002100000001,33.885252],"type":"Point"}
}