{
  "type": "Feature",
  "properties": {
    "addr:full":"3079 Hathaway Ct Atlanta GA 30341",
    "addr:housenumber":"3079",
    "addr:postcode":"30341",
    "addr:street":"Hathaway Ct",
    "iso:country":"US",
    "sg:address":"3079 Hathaway Ct",
    "sg:city":"Atlanta",
    "sg:classifiers":[
        {
            "category":"Wholesale",
            "subcategory":"Groceries",
            "type":"Manufacturing & Wholesale Goods"
        }
    ],
    "sg:phone":"+1 770 496 1523",
    "sg:postcode":"30341",
    "sg:province":"GA",
    "sg:tags":[
        "confectionery",
        "candy"
    ],
    "wof:name":"Sweet B Enterprises",
    "wof:placetype":"venue"
},
  "geometry": {"coordinates":[-84.24097500000001,33.87936],"type":"Point"}
}