{
  "type": "Feature",
  "properties": {
    "addr:full":"3601 Abercorn St Savannah GA 31405",
    "addr:housenumber":"3601",
    "addr:postcode":"31405",
    "addr:street":"Abercorn St",
    "iso:country":"US",
    "sg:address":"3601 Abercorn St",
    "sg:city":"Savannah",
    "sg:classifiers":[
        {
            "category":"Building & Trades",
            "subcategory":"Landscaping Services",
            "type":"Services"
        }
    ],
    "sg:phone":"+1 912 236 0845",
    "sg:postcode":"31405",
    "sg:province":"GA",
    "sg:tags":[
        "landscape"
    ],
    "wof:name":"Jo Hickson ASLA",
    "wof:placetype":"venue"
},
  "geometry": {"coordinates":[-81.10231400000001,32.044396],"type":"Point"}
}