{
  "type": "Feature",
  "properties": {
    "iso:country":"US",
    "sg:address":"5245 2nd Dr",
    "sg:city":"Valdosta",
    "sg:classifiers":[
        {
            "category":"Real Estate",
            "subcategory":"Real Estate Operator",
            "type":"Services"
        }
    ],
    "sg:phone":"+1 229 559 5627",
    "sg:postcode":"31601",
    "sg:province":"GA",
    "sg:tags":[
        "mobile",
        "home",
        "community"
    ],
    "wof:name":"Oak Wood Mobile Home Park",
    "wof:placetype":"venue"
},
  "geometry": {"coordinates":[-83.272622,30.690508],"type":"Point"}
}