{
  "type": "Feature",
  "properties": {
    "addr:full":"120 Bradford Dr Macon GA 31210",
    "addr:housenumber":"120",
    "addr:postcode":"31210",
    "addr:street":"Bradford Dr",
    "iso:country":"US",
    "sg:address":"120 Bradford Dr",
    "sg:city":"Macon",
    "sg:classifiers":[
        {
            "category":"Professional",
            "subcategory":"Computer Services",
            "type":"Services"
        }
    ],
    "sg:phone":"+1 478 475 4071",
    "sg:postcode":"31210",
    "sg:province":"GA",
    "sg:tags":[
        "software"
    ],
    "wof:name":"Cadama Inc",
    "wof:placetype":"venue"
},
  "geometry": {"coordinates":[-83.74453200000001,32.911146],"type":"Point"}
}