{
  "type": "Feature",
  "properties": {
    "addr:full":"185 Kathi Ave Fayetteville GA 30214",
    "addr:housenumber":"185",
    "addr:postcode":"30214",
    "addr:street":"Kathi Ave",
    "iso:country":"US",
    "sg:address":"185 Kathi Ave",
    "sg:city":"Fayetteville",
    "sg:classifiers":[
        {
            "category":"Professional",
            "subcategory":"Accounting & Tax Preparation",
            "type":"Services"
        }
    ],
    "sg:phone":"+1 770 460 5518",
    "sg:postcode":"30214",
    "sg:province":"GA",
    "wof:name":"Bausch & Associates Inc",
    "wof:placetype":"venue"
},
  "geometry": {"coordinates":[-84.45171000000001,33.456304],"type":"Point"}
}