{
  "type": "Feature",
  "properties": {
    "iso:country":"US",
    "sg:address":"440 Railroad St",
    "sg:city":"Thomson",
    "sg:classifiers":[
        {
            "category":"Retail",
            "subcategory":"Auto Repair",
            "type":"Services"
        }
    ],
    "sg:phone":"+1 706 595 4111",
    "sg:postcode":"30824",
    "sg:province":"GA",
    "sg:tags":[
        "repairing",
        "automobile",
        "automotive",
        "general"
    ],
    "wof:name":"Anything Honda",
    "wof:placetype":"venue"
},
  "geometry": {"coordinates":[-82.49448,33.468473],"type":"Point"}
}