{
  "type": "Feature",
  "properties": {
    "addr:full":"1908 Highway 81 E McDonough GA 30252",
    "addr:housenumber":"1908",
    "addr:postcode":"30252",
    "addr:street":"Highway 81 E",
    "iso:country":"US",
    "sg:address":"1908 Highway 81 E",
    "sg:city":"McDonough",
    "sg:classifiers":[
        {
            "category":"Banks & Credit Unions",
            "subcategory":"Bank",
            "type":"Services"
        }
    ],
    "sg:phone":"+1 770 474 7829",
    "sg:postcode":"30252",
    "sg:province":"GA",
    "wof:name":"First State Bank the",
    "wof:placetype":"venue"
},
  "geometry": {"coordinates":[-84.090261,33.428487],"type":"Point"}
}