{
  "type": "Feature",
  "properties": {
    "iso:country":"US",
    "sg:address":"404 Mcrae St.",
    "sg:city":"Alamo",
    "sg:classifiers":[
        {
            "category":"Education",
            "subcategory":"Music School",
            "type":"Public Place"
        },
        {
            "category":"Education",
            "subcategory":"School",
            "type":"Public Place"
        }
    ],
    "sg:phone":"+1 912 568 7198",
    "sg:postcode":"30411",
    "sg:province":"GA",
    "sg:tags":[
        "information",
        "district",
        "high",
        "middle",
        "elementary"
    ],
    "wof:name":"Wheeler County Board Education",
    "wof:placetype":"venue"
},
  "geometry": {"coordinates":[-82.78209099999999,32.148609],"type":"Point"}
}