{
  "type": "Feature",
  "properties": {
    "iso:country":"US",
    "sg:address":"1924 Tucker Industrial Rd",
    "sg:city":"Atlanta",
    "sg:classifiers":[
        {
            "category":"Building & Trades",
            "subcategory":"Plumbing",
            "type":"Services"
        }
    ],
    "sg:phone":"+1 770 934 8511",
    "sg:postcode":"30084",
    "sg:province":"GA",
    "wof:name":"Tc Plumbing Inc",
    "wof:placetype":"venue"
},
  "geometry": {"coordinates":[-84.203681,33.83935],"type":"Point"}
}