{
  "type": "Feature",
  "properties": {
    "iso:country":"US",
    "sg:address":"866 Main St",
    "sg:city":"Stone Mountain",
    "sg:classifiers":[
        {
            "category":"Personal",
            "subcategory":"Barber",
            "type":"Services"
        }
    ],
    "sg:phone":"+1 770 469 5918",
    "sg:postcode":"30083",
    "sg:province":"GA",
    "sg:tags":[
        "shop",
        "beauty"
    ],
    "wof:name":"Hair Cutting Co",
    "wof:placetype":"venue"
},
  "geometry": {"coordinates":[-84.17001999999999,33.803345],"type":"Point"}
}