{
  "type": "Feature",
  "properties": {
    "addr:full":"4 Calhoun Ave Rome GA 30161",
    "addr:housenumber":"4",
    "addr:postcode":"ga 30161",
    "addr:street":"Calhoun Ave",
    "iso:country":"US",
    "sg:address":"4 Calhoun Ave",
    "sg:city":"Rome",
    "sg:classifiers":[
        {
            "category":"Restaurant",
            "type":"Food & Drink"
        }
    ],
    "sg:phone":"+1 706 291 7188",
    "sg:postcode":"30161",
    "sg:province":"GA",
    "sg:tags":[
        "eating"
    ],
    "wof:name":"Troys Bar-B-Que",
    "wof:placetype":"venue"
},
  "geometry": {"coordinates":[-85.15209,34.265478],"type":"Point"}
}