{
  "type": "Feature",
  "properties": {
    "iso:country":"US",
    "sg:address":"511 Augusta Rd",
    "sg:city":"North Augusta",
    "sg:classifiers":[
        {
            "category":"Restaurant",
            "type":"Food & Drink"
        }
    ],
    "sg:phone":"+1 803 279 3807",
    "sg:postcode":"29822",
    "sg:province":"SC",
    "sg:tags":[
        "eating"
    ],
    "wof:name":"Edmunds Barbecue",
    "wof:placetype":"venue"
},
  "geometry": {"coordinates":[-81.892046,33.496711],"type":"Point"}
}