{
  "type": "Feature",
  "properties": {
    "iso:country":"US",
    "sg:address":"576 Pirklefield Dr",
    "sg:city":"Covington",
    "sg:classifiers":[
        {
            "category":"Professional",
            "subcategory":"Credit Reporting & Collection",
            "type":"Services"
        }
    ],
    "sg:phone":"+1 770 788 8904",
    "sg:postcode":"30014",
    "sg:province":"GA",
    "wof:name":"Rental Property Services Co",
    "wof:placetype":"venue"
},
  "geometry": {"coordinates":[-83.823395,33.75152],"type":"Point"}
}