{
  "type": "Feature",
  "properties": {
    "iso:country":"US",
    "sg:address":"2245 Callaway Rd SW",
    "sg:city":"Marietta",
    "sg:classifiers":[
        {
            "category":"Recreation",
            "type":"Entertainment"
        }
    ],
    "sg:phone":"+1 770 528 8865",
    "sg:postcode":"30008",
    "sg:province":"GA",
    "wof:name":"County Park Ranger",
    "wof:placetype":"venue"
},
  "geometry": {"coordinates":[-84.590518,33.895183],"type":"Point"}
}