{
  "type": "Feature",
  "properties": {
    "iso:country":"US",
    "sg:address":"255 Highway 53 E",
    "sg:city":"Calhoun",
    "sg:classifiers":[
        {
            "category":"Restaurant",
            "type":"Food & Drink"
        }
    ],
    "sg:menulink":"http://www.allmenus.com/ga/calhoun/153434-bojangles/menu/",
    "sg:phone":"+1 706 625 3949",
    "sg:postcode":"30701",
    "sg:province":"GA",
    "sg:tags":[
        "chicken",
        "sandwich",
        "american"
    ],
    "wof:name":"Bojangle's",
    "wof:placetype":"venue"
},
  "geometry": {"coordinates":[-84.953529,34.480613],"type":"Point"}
}