{
  "type": "Feature",
  "properties": {
    "addr:full":"4608 Jimmy Carter Blvd Norcross GA 30093",
    "addr:housenumber":"4608",
    "addr:postcode":"30093",
    "addr:street":"Jimmy Carter Blvd",
    "iso:country":"US",
    "sg:address":"4608 Jimmy Carter Blvd",
    "sg:city":"Norcross",
    "sg:classifiers":[
        {
            "category":"Wholesale",
            "subcategory":"Auto Parts",
            "type":"Manufacturing & Wholesale Goods"
        }
    ],
    "sg:phone":"+1 678 937 9983",
    "sg:postcode":"30093",
    "sg:province":"GA",
    "sg:tags":[
        "automobile",
        "supply"
    ],
    "wof:name":"R P & M Motorsports",
    "wof:placetype":"venue"
},
  "geometry": {"coordinates":[-84.19391,33.88746],"type":"Point"}
}