{
  "type": "Feature",
  "properties": {
    "iso:country":"US",
    "sg:address":"727 Juniper St NE",
    "sg:city":"Atlanta",
    "sg:classifiers":[
        {
            "category":"Personal",
            "subcategory":"Beauty Salon",
            "type":"Services"
        }
    ],
    "sg:phone":"+1 404 876 4891",
    "sg:postcode":"30308",
    "sg:province":"GA",
    "sg:tags":[
        "shop"
    ],
    "wof:name":"Juan's Beauty Salon",
    "wof:placetype":"venue"
},
  "geometry": {"coordinates":[-84.383235,33.77375],"type":"Point"}
}