{
  "type": "Feature",
  "properties": {
    "addr:full":"321 Chandler Rd Mcdonough GA 30253",
    "addr:housenumber":"321",
    "addr:postcode":"30253",
    "addr:street":"Chandler Rd",
    "iso:country":"US",
    "sg:address":"321 Chandler Rd",
    "sg:city":"Mcdonough",
    "sg:classifiers":[
        {
            "category":"Freight",
            "type":"Transportation"
        }
    ],
    "sg:phone":"+1 770 318 4575",
    "sg:postcode":"30253",
    "sg:province":"GA",
    "sg:tags":[
        "trucking"
    ],
    "wof:name":"C & V Transport",
    "wof:placetype":"venue"
},
  "geometry": {"coordinates":[-84.176081,33.482845],"type":"Point"}
}