{
  "type": "Feature",
  "properties": {
    "addr:full":"100 Elmwood St Warner Robins GA 31093",
    "addr:housenumber":"100",
    "addr:postcode":"31093",
    "addr:street":"Elmwood St",
    "iso:country":"US",
    "sg:address":"100 Elmwood St",
    "sg:city":"Warner Robins",
    "sg:classifiers":[
        {
            "category":"Building & Trades",
            "subcategory":"Electrical",
            "type":"Services"
        }
    ],
    "sg:phone":"+1 478 922 3534",
    "sg:postcode":"31093",
    "sg:province":"GA",
    "sg:tags":[
        "electrical",
        "contractor"
    ],
    "wof:name":"3rd Electric Inc",
    "wof:placetype":"venue"
},
  "geometry": {"coordinates":[-83.61427399999999,32.64311],"type":"Point"}
}