{
  "type": "Feature",
  "properties": {
    "iso:country":"US",
    "sg:address":"3929 Canton Rd",
    "sg:city":"Marietta",
    "sg:classifiers":[
        {
            "category":"Food & Beverages",
            "subcategory":"Specialty",
            "type":"Retail Goods"
        }
    ],
    "sg:phone":"+1 770 422 5200",
    "sg:postcode":"30066",
    "sg:province":"GA",
    "sg:tags":[
        "water",
        "bulk",
        "company"
    ],
    "wof:name":"Georgia Mountain Water",
    "wof:placetype":"venue"
},
  "geometry": {"coordinates":[-84.528085,34.048071],"type":"Point"}
}