{
  "type": "Feature",
  "properties": {
    "iso:country":"US",
    "sg:address":"3193 Howell Mill Rd NW",
    "sg:city":"Atlanta",
    "sg:classifiers":[
        {
            "category":"Health Services",
            "subcategory":"Doctor",
            "type":"Services"
        }
    ],
    "sg:phone":"+1 404 355 4823",
    "sg:postcode":"30327",
    "sg:province":"GA",
    "sg:tags":[
        "medical"
    ],
    "wof:name":"Cline Peter J MD/Internal MD",
    "wof:placetype":"venue"
},
  "geometry": {"coordinates":[-84.427757,33.842254],"type":"Point"}
}