{
  "type": "Feature",
  "properties": {
    "addr:full":"115 Mallory St St Simons Island GA 31522",
    "addr:housenumber":"115",
    "addr:postcode":"31522",
    "addr:street":"Mallory St",
    "iso:country":"US",
    "sg:address":"115 Mallory St",
    "sg:city":"St Simons Island",
    "sg:classifiers":[
        {
            "category":"Restaurant",
            "type":"Food & Drink"
        }
    ],
    "sg:phone":"+1 912 638 7007",
    "sg:postcode":"31522",
    "sg:province":"GA",
    "wof:name":"Blue Water Bistro",
    "wof:placetype":"venue"
},
  "geometry": {"coordinates":[-81.39141600000001,31.145184],"type":"Point"}
}