{
  "type": "Feature",
  "properties": {
    "iso:country":"US",
    "sg:address":"106 E Jackson St",
    "sg:city":"Dublin",
    "sg:classifiers":[
        {
            "category":"Restaurant",
            "type":"Food & Drink"
        }
    ],
    "sg:phone":"+1 478 272 9956",
    "sg:postcode":"31021",
    "sg:province":"GA",
    "sg:tags":[
        "fast"
    ],
    "wof:name":"Minute Grill",
    "wof:placetype":"venue"
},
  "geometry": {"coordinates":[-82.902829,32.540648],"type":"Point"}
}