{
  "type": "Feature",
  "properties": {
    "addr:full":"1002 Apt To Miss Rd Monticello GA 31064",
    "addr:housenumber":"1002",
    "addr:postcode":"31064",
    "addr:street":"Miss Rd",
    "iso:country":"US",
    "sg:address":"1002 Apt To Miss Rd",
    "sg:city":"Monticello",
    "sg:classifiers":[
        {
            "category":"Manufacturing",
            "subcategory":"Lumber",
            "type":"Manufacturing & Wholesale Goods"
        }
    ],
    "sg:phone":"+1 706 468 0643",
    "sg:postcode":"31064",
    "sg:province":"GA",
    "sg:tags":[
        "cutting",
        "timber"
    ],
    "wof:name":"Pope Lumber",
    "wof:placetype":"venue"
},
  "geometry": {"coordinates":[-83.55934499999999,33.299261],"type":"Point"}
}