{
  "type": "Feature",
  "properties": {
    "iso:country":"US",
    "sg:address":"325 W Washington St",
    "sg:city":"Madison",
    "sg:classifiers":[
        {
            "category":"Restaurant",
            "type":"Food & Drink"
        }
    ],
    "sg:phone":"+1 706 342 1600",
    "sg:postcode":"30650",
    "sg:province":"GA",
    "wof:name":"Adrian's Place",
    "wof:placetype":"venue"
},
  "geometry": {"coordinates":[-83.47096999999999,33.597858],"type":"Point"}
}