{
  "type": "Feature",
  "properties": {
    "addr:full":"520 General Courtney Hodge Blvd Perry GA 31069",
    "addr:housenumber":"520",
    "addr:postcode":"31069",
    "addr:street":"General Courtney Hodge Blvd",
    "iso:country":"US",
    "sg:address":"520 General Courtney Hodge Blvd",
    "sg:city":"Perry",
    "sg:classifiers":[
        {
            "category":"Autos & Motor Vehicles",
            "subcategory":"Automobile Sales",
            "type":"Retail Goods"
        }
    ],
    "sg:phone":"+1 478 987 0865",
    "sg:postcode":"31069",
    "sg:province":"GA",
    "sg:tags":[
        "car",
        "dealer"
    ],
    "wof:name":"S & E Sales & Svc",
    "wof:placetype":"venue"
},
  "geometry": {"coordinates":[-83.74307899999999,32.452526],"type":"Point"}
}