{
  "type": "Feature",
  "properties": {
    "iso:country":"US",
    "sg:address":"5353 Denny Dr",
    "sg:city":"Atlanta",
    "sg:classifiers":[
        {
            "category":"Professional",
            "subcategory":"Computer Services",
            "type":"Services"
        }
    ],
    "sg:phone":"+1 770 969 9597",
    "sg:postcode":"30349",
    "sg:province":"GA",
    "sg:tags":[
        "consultant",
        "designer"
    ],
    "wof:name":"C & R Business Svc",
    "wof:placetype":"venue"
},
  "geometry": {"coordinates":[-84.45758499999999,33.606677],"type":"Point"}
}