{
  "type": "Feature",
  "properties": {
    "addr:full":"1216 Dawson Rd Albany GA 31707",
    "addr:housenumber":"1216",
    "addr:postcode":"31707",
    "addr:street":"Dawson Rd",
    "iso:country":"US",
    "sg:address":"1216 Dawson Rd",
    "sg:city":"Albany",
    "sg:classifiers":[
        {
            "category":"Professional",
            "subcategory":"Management & Consulting",
            "type":"Services"
        }
    ],
    "sg:phone":"+1 229 436 2458",
    "sg:postcode":"31707",
    "sg:province":"GA",
    "sg:tags":[
        "report",
        "construction"
    ],
    "wof:name":"F W Dodge Mc Graw-Hill",
    "wof:placetype":"venue"
},
  "geometry": {"coordinates":[-84.182655,31.585476],"type":"Point"}
}