{
  "type": "Feature",
  "properties": {
    "iso:country":"US",
    "sg:address":"8432 Adair St",
    "sg:city":"Douglasville",
    "sg:classifiers":[
        {
            "category":"Banks & Credit Unions",
            "subcategory":"Investment Brokerage",
            "type":"Services"
        }
    ],
    "sg:phone":"+1 770 920 8306",
    "sg:postcode":"30134",
    "sg:province":"GA",
    "sg:tags":[
        "security"
    ],
    "wof:name":"Edward Jones 06397",
    "wof:placetype":"venue"
},
  "geometry": {"coordinates":[-84.745362,33.751152],"type":"Point"}
}