{
  "type": "Feature",
  "properties": {
    "addr:full":"1001 Bay Pointe Xing Alpharetta GA 30005",
    "addr:housenumber":"1001",
    "addr:postcode":"30005",
    "addr:street":"Bay Pointe Xing",
    "iso:country":"US",
    "sg:address":"1001 Bay Pointe Xing",
    "sg:city":"Alpharetta",
    "sg:classifiers":[
        {
            "category":"Restaurant",
            "type":"Food & Drink"
        },
        {
            "category":"Organizations",
            "subcategory":"Professional Association",
            "type":"Services"
        }
    ],
    "sg:phone":"+1 770 772 5627",
    "sg:postcode":"30005",
    "sg:province":"GA",
    "sg:tags":[
        "eating"
    ],
    "wof:name":"Bay Pointe Sub Assoc",
    "wof:placetype":"venue"
},
  "geometry": {"coordinates":[-84.22415599999999,34.082921],"type":"Point"}
}