{
  "type": "Feature",
  "properties": {
    "addr:full":"2403 Candler Rd Decatur GA 30032",
    "addr:housenumber":"2403",
    "addr:postcode":"30032",
    "addr:street":"Candler Rd",
    "iso:country":"US",
    "sg:address":"2403 Candler Rd",
    "sg:city":"Decatur",
    "sg:classifiers":[
        {
            "category":"Professional",
            "subcategory":"Accounting & Tax Preparation",
            "type":"Services"
        }
    ],
    "sg:phone":"+1 404 284 6337",
    "sg:postcode":"30032",
    "sg:province":"GA",
    "sg:tags":[
        "return",
        "filing"
    ],
    "sg:website":"www.c-and-m-business-svcs.com",
    "wof:name":"C & M Business Svc",
    "wof:placetype":"venue"
},
  "geometry": {"coordinates":[-84.27557400000001,33.718413],"type":"Point"}
}