{
  "type": "Feature",
  "properties": {
    "iso:country":"US",
    "sg:address":"955 Springrock Dr",
    "sg:city":"Lawrenceville",
    "sg:classifiers":[
        {
            "category":"Real Estate",
            "subcategory":"Real Estate Services",
            "type":"Services"
        },
        {
            "category":"Real Estate",
            "subcategory":"Real Estate Agent",
            "type":"Services"
        }
    ],
    "sg:phone":"+1 770 271 0224",
    "sg:postcode":"30043",
    "sg:province":"GA",
    "sg:tags":[
        "buyer",
        "broker"
    ],
    "wof:name":"Rock Springs Realty Inc",
    "wof:placetype":"venue"
},
  "geometry": {"coordinates":[-84.005994,34.043199],"type":"Point"}
}