{
  "type": "Feature",
  "properties": {
    "iso:country":"US",
    "sg:address":"4749 Nelson Brogdon Blvd # 200",
    "sg:city":"Buford",
    "sg:classifiers":[
        {
            "category":"Health Services",
            "subcategory":"Dentist",
            "type":"Services"
        }
    ],
    "sg:phone":"+1 770 932 7726",
    "sg:postcode":"30518",
    "sg:province":"GA",
    "wof:name":"Atlanta Orthofacial Surgery",
    "wof:placetype":"venue"
},
  "geometry": {"coordinates":[-84.02392399999999,34.103602],"type":"Point"}
}