{
  "type": "Feature",
  "properties": {
    "iso:country":"US",
    "sg:address":"3005 Old Alabama Rd",
    "sg:city":"Alpharetta",
    "sg:classifiers":[
        {
            "category":"Shopping",
            "subcategory":"Used Merchandise",
            "type":"Retail Goods"
        }
    ],
    "sg:phone":"+1 770 619 0945",
    "sg:postcode":"30022",
    "sg:province":"GA",
    "wof:name":"Josephiness Antq & Fine Linens",
    "wof:placetype":"venue"
},
  "geometry": {"coordinates":[-84.275009,34.020624],"type":"Point"}
}