{
  "type": "Feature",
  "properties": {
    "addr:full":"2180 Northlake Pkwy Tucker GA 30084",
    "addr:housenumber":"2180",
    "addr:postcode":"30084",
    "addr:street":"Northlake Pkwy",
    "iso:country":"US",
    "sg:address":"2180 Northlake Pkwy",
    "sg:city":"Tucker",
    "sg:classifiers":[
        {
            "category":"Bars & Pubs",
            "type":"Food & Drink"
        }
    ],
    "sg:phone":"+1 770 934 6226",
    "sg:postcode":"30084",
    "sg:province":"GA",
    "sg:tags":[
        "drinking"
    ],
    "wof:name":"Kaiso Lounge",
    "wof:placetype":"venue"
},
  "geometry": {"coordinates":[-84.24467799999999,33.84766],"type":"Point"}
}