{
  "type": "Feature",
  "properties": {
    "iso:country":"US",
    "sg:address":"3568 Natalie Ct",
    "sg:city":"Loganville",
    "sg:classifiers":[
        {
            "category":"Professional",
            "type":"Services"
        }
    ],
    "sg:phone":"+1 770 466 0793",
    "sg:postcode":"30052",
    "sg:province":"GA",
    "wof:name":"Donna H Fulford",
    "wof:placetype":"venue"
},
  "geometry": {"coordinates":[-83.84947099999999,33.794763],"type":"Point"}
}