{
  "type": "Feature",
  "properties": {
    "iso:country":"US",
    "sg:address":"590 Big Sky Dr",
    "sg:city":"Hamilton",
    "sg:classifiers":[
        {
            "category":"Manufacturing",
            "subcategory":"Tools & Machinery",
            "type":"Manufacturing & Wholesale Goods"
        }
    ],
    "sg:phone":"+1 706 628 4556",
    "sg:postcode":"31811",
    "sg:province":"GA",
    "sg:tags":[
        "machine",
        "vending",
        "mfg"
    ],
    "wof:name":"Carter Co",
    "wof:placetype":"venue"
},
  "geometry": {"coordinates":[-84.930508,32.729129],"type":"Point"}
}