{
  "type": "Feature",
  "properties": {
    "iso:country":"US",
    "sg:address":"111 Shallowford Rd",
    "sg:city":"Dalton",
    "sg:classifiers":[
        {
            "category":"Professional",
            "type":"Services"
        }
    ],
    "sg:phone":"+1 706 259 7083",
    "sg:postcode":"30721",
    "sg:province":"GA",
    "wof:name":"Jones Courtney & Patrick",
    "wof:placetype":"venue"
},
  "geometry": {"coordinates":[-84.956098,34.823436],"type":"Point"}
}