{
  "type": "Feature",
  "properties": {
    "iso:country":"US",
    "sg:address":"2662 Holcomb Bridge Rd",
    "sg:city":"Alpharetta",
    "sg:classifiers":[
        {
            "category":"Building & Trades",
            "subcategory":"Cleaning & Sanitation",
            "type":"Services"
        }
    ],
    "sg:phone":"+1 770 594 1836",
    "sg:postcode":"30022",
    "sg:province":"GA",
    "sg:tags":[
        "janitor"
    ],
    "wof:name":"Q Care Carpet Cleaning",
    "wof:placetype":"venue"
},
  "geometry": {"coordinates":[-84.28255,33.996175],"type":"Point"}
}