{
  "type": "Feature",
  "properties": {
    "addr:full":"724 Emerald Ridge Woodstock GA 30189",
    "addr:housenumber":"724",
    "addr:postcode":"30189",
    "addr:street":"Emerald Ridge",
    "iso:country":"US",
    "sg:address":"724 Emerald Ridge",
    "sg:city":"Woodstock",
    "sg:classifiers":[
        {
            "category":"Building & Trades",
            "subcategory":"Electrical",
            "type":"Services"
        }
    ],
    "sg:phone":"+1 678 445 9147",
    "sg:postcode":"30189",
    "sg:province":"GA",
    "sg:tags":[
        "electrical",
        "contractor"
    ],
    "wof:name":"Rl Wiley Electric Co Inc",
    "wof:placetype":"venue"
},
  "geometry": {"coordinates":[-84.60435200000001,34.140446],"type":"Point"}
}