{
  "type": "Feature",
  "properties": {
    "iso:country":"US",
    "sg:address":"405 W Main St",
    "sg:city":"Thomaston",
    "sg:classifiers":[
        {
            "category":"Health Services",
            "subcategory":"Clinic",
            "type":"Services"
        }
    ],
    "sg:phone":"+1 706 647 4781",
    "sg:postcode":"30286",
    "sg:province":"GA",
    "sg:tags":[
        "home",
        "care"
    ],
    "wof:name":"First Choice Medical Services",
    "wof:placetype":"venue"
},
  "geometry": {"coordinates":[-84.331762,32.889083],"type":"Point"}
}