{
  "type": "Feature",
  "properties": {
    "addr:full":"1058 Rocky Branch Rd Clarkesville GA 30523",
    "addr:housenumber":"1058",
    "addr:postcode":"30523",
    "addr:street":"Rocky Branch Rd",
    "iso:country":"US",
    "sg:address":"1058 Rocky Branch Rd",
    "sg:city":"Clarkesville",
    "sg:classifiers":[
        {
            "category":"Manufacturing",
            "subcategory":"Electronics",
            "type":"Manufacturing & Wholesale Goods"
        }
    ],
    "sg:phone":"+1 706 754 4147",
    "sg:postcode":"30523",
    "sg:province":"GA",
    "sg:tags":[
        "equipment",
        "electronic",
        "supply"
    ],
    "sg:website":"www.indak.com",
    "wof:name":"Piedmont Automotive Products",
    "wof:placetype":"venue"
},
  "geometry": {"coordinates":[-83.50656600000001,34.607943],"type":"Point"}
}