{
  "type": "Feature",
  "properties": {
    "addr:full":"6175 Hickory Flat Hwy Canton GA 30115",
    "addr:housenumber":"6175",
    "addr:postcode":"30115",
    "addr:street":"Hickory Flat Hwy",
    "iso:country":"US",
    "sg:address":"6175 Hickory Flat Hwy",
    "sg:city":"Canton",
    "sg:classifiers":[
        {
            "category":"Personal",
            "subcategory":"Beauty Salon",
            "type":"Services"
        },
        {
            "category":"Personal",
            "subcategory":"Barber",
            "type":"Services"
        }
    ],
    "sg:phone":"+1 770 345 4668",
    "sg:postcode":"30115",
    "sg:province":"GA",
    "sg:tags":[
        "shop"
    ],
    "wof:name":"Hair Connection",
    "wof:placetype":"venue"
},
  "geometry": {"coordinates":[-84.41766699999999,34.175517],"type":"Point"}
}