{
  "type": "Feature",
  "properties": {
    "iso:country":"US",
    "sg:address":"3365 Piedmont Rd NE",
    "sg:city":"Atlanta",
    "sg:classifiers":[
        {
            "category":"Restaurant",
            "type":"Food & Drink"
        }
    ],
    "sg:phone":"+1 404 239 9557",
    "sg:postcode":"30305",
    "sg:province":"GA",
    "wof:name":"Ru San's Buckhead At Tower Pl",
    "wof:placetype":"venue"
},
  "geometry": {"coordinates":[-84.374196,33.848513],"type":"Point"}
}