{
  "type": "Feature",
  "properties": {
    "iso:country":"US",
    "sg:address":"5389 New Peachtree Road",
    "sg:city":"Atlanta",
    "sg:classifiers":[
        {
            "category":"Bakery",
            "type":"Food & Drink"
        }
    ],
    "sg:phone":"+1 770 451 4608",
    "sg:postcode":"30341",
    "sg:province":"GA",
    "wof:name":"Dinho Bakery and Company",
    "wof:placetype":"venue"
},
  "geometry": {"coordinates":[-84.300517,33.890602],"type":"Point"}
}