{
  "type": "Feature",
  "properties": {
    "addr:full":"206 E 16th Ave Cordele GA 31015",
    "addr:housenumber":"206",
    "addr:postcode":"31015",
    "addr:street":"E 16Th Ave",
    "iso:country":"US",
    "sg:address":"206 E 16th Ave",
    "sg:city":"Cordele",
    "sg:classifiers":[
        {
            "category":"Personal",
            "subcategory":"Beauty Salon",
            "type":"Services"
        }
    ],
    "sg:phone":"+1 229 273 2847",
    "sg:postcode":"31015",
    "sg:province":"GA",
    "wof:name":"Sassy Styles",
    "wof:placetype":"venue"
},
  "geometry": {"coordinates":[-83.780925,31.963602],"type":"Point"}
}