{
  "type": "Feature",
  "properties": {
    "iso:country":"US",
    "sg:address":"570 Buckingham Ter",
    "sg:city":"Fairburn",
    "sg:classifiers":[
        {
            "category":"Health Services",
            "subcategory":"Clinic",
            "type":"Services"
        },
        {
            "category":"Community Center",
            "type":"Public Place"
        }
    ],
    "sg:phone":"+1 770 629 5995",
    "sg:postcode":"30213",
    "sg:province":"GA",
    "sg:tags":[
        "medical"
    ],
    "wof:name":"Clerk Surgical Assisting Services",
    "wof:placetype":"venue"
},
  "geometry": {"coordinates":[-84.608113,33.566095],"type":"Point"}
}