{
  "type": "Feature",
  "properties": {
    "iso:country":"US",
    "sg:address":"1300 Boat Rock Rd SW",
    "sg:city":"Atlanta",
    "sg:classifiers":[
        {
            "category":"Shopping",
            "subcategory":"Party Supplies",
            "type":"Retail Goods"
        }
    ],
    "sg:phone":"+1 404 271 2552",
    "sg:postcode":"30331",
    "sg:province":"GA",
    "sg:tags":[
        "decorating",
        "convention"
    ],
    "wof:name":"Stacys Home Accessories",
    "wof:placetype":"venue"
},
  "geometry": {"coordinates":[-84.562962,33.720854],"type":"Point"}
}