{
  "type": "Feature",
  "properties": {
    "addr:full":"1955 Panola Rd Ellenwood GA 30294",
    "addr:housenumber":"1955",
    "addr:postcode":"30294",
    "addr:street":"Panola Rd",
    "iso:country":"US",
    "sg:address":"1955 Panola Rd",
    "sg:city":"Ellenwood",
    "sg:classifiers":[
        {
            "category":"Retail",
            "subcategory":"Auto Rental",
            "type":"Services"
        }
    ],
    "sg:phone":"+1 678 565 9862",
    "sg:postcode":"30294",
    "sg:province":"GA",
    "sg:tags":[
        "renting",
        "leasing",
        "trailer"
    ],
    "wof:name":"U-Haul Co",
    "wof:placetype":"venue"
},
  "geometry": {"coordinates":[-84.24274200000001,33.616034],"type":"Point"}
}