{
  "type": "Feature",
  "properties": {
    "iso:country":"US",
    "sg:address":"79 Griffin Rd NW",
    "sg:city":"Cartersville",
    "sg:classifiers":[
        {
            "category":"Building & Trades",
            "subcategory":"Electrical",
            "type":"Services"
        }
    ],
    "sg:phone":"+1 770 336 9660",
    "sg:postcode":"30120",
    "sg:province":"GA",
    "sg:tags":[
        "electrical",
        "contractor"
    ],
    "wof:name":"Miracle Electric Service",
    "wof:placetype":"venue"
},
  "geometry": {"coordinates":[-84.87788999999999,34.273936],"type":"Point"}
}