{
  "type": "Feature",
  "properties": {
    "iso:country":"US",
    "sg:address":"1400 Old Conyers Rd",
    "sg:city":"Stockbridge",
    "sg:classifiers":[
        {
            "category":"Food & Beverages",
            "subcategory":"Groceries & Convenience Stores",
            "type":"Retail Goods"
        }
    ],
    "sg:phone":"+1 770 389 8300",
    "sg:postcode":"30281",
    "sg:province":"GA",
    "wof:name":"Flat Rock Amoco",
    "wof:placetype":"venue"
},
  "geometry": {"coordinates":[-84.196701,33.564999],"type":"Point"}
}