{
  "type": "Feature",
  "properties": {
    "addr:full":"119 S Victory Dr Lyons GA 30436",
    "addr:housenumber":"119",
    "addr:postcode":"30436",
    "addr:street":"S Victory Dr",
    "iso:country":"US",
    "sg:address":"119 S Victory Dr",
    "sg:city":"Lyons",
    "sg:classifiers":[
        {
            "category":"Insurance",
            "subcategory":"Hazard Insurance",
            "type":"Services"
        }
    ],
    "sg:phone":"+1 912 526 5333",
    "sg:postcode":"30436",
    "sg:province":"GA",
    "wof:name":"LLS Insurance Agency",
    "wof:placetype":"venue"
},
  "geometry": {"coordinates":[-82.327479,32.201838],"type":"Point"}
}