{
  "type": "Feature",
  "properties": {
    "iso:country":"US",
    "sg:address":"1128 Pinecrest Ter",
    "sg:city":"Alpharetta",
    "sg:classifiers":[
        {
            "category":"Building & Trades",
            "subcategory":"Construction",
            "type":"Services"
        }
    ],
    "sg:phone":"+1 770 475 9467",
    "sg:postcode":"30004",
    "sg:province":"GA",
    "sg:tags":[
        "house"
    ],
    "wof:name":"Chastain Construction Services",
    "wof:placetype":"venue"
},
  "geometry": {"coordinates":[-84.256494,34.117601],"type":"Point"}
}