{
  "type": "Feature",
  "properties": {
    "iso:country":"US",
    "sg:address":"630 Willow Knoll Dr SE",
    "sg:city":"Marietta",
    "sg:classifiers":[
        {
            "category":"Professional",
            "subcategory":"Management & Consulting",
            "type":"Services"
        }
    ],
    "sg:phone":"+1 770 952 1194",
    "sg:postcode":"30067",
    "sg:province":"GA",
    "sg:tags":[
        "consultant",
        "planning",
        "space",
        "facility"
    ],
    "wof:name":"Relogistics, Inc",
    "wof:placetype":"venue"
},
  "geometry": {"coordinates":[-84.41516300000001,33.94058],"type":"Point"}
}