{
  "type": "Feature",
  "properties": {
    "addr:full":"6629 Spring St Douglasville GA 30134",
    "addr:housenumber":"6629",
    "addr:postcode":"30134",
    "addr:street":"Spring St",
    "iso:country":"US",
    "sg:address":"6629 Spring St",
    "sg:city":"Douglasville",
    "sg:classifiers":[
        {
            "category":"Professional",
            "subcategory":"Computer Services",
            "type":"Services"
        }
    ],
    "sg:phone":"+1 770 947 2246",
    "sg:postcode":"30134",
    "sg:province":"GA",
    "sg:tags":[
        "related"
    ],
    "wof:name":"Techcare Corp",
    "wof:placetype":"venue"
},
  "geometry": {"coordinates":[-84.747547,33.749534],"type":"Point"}
}