{
  "type": "Feature",
  "properties": {
    "addr:full":"5735 Garden Walk Flowery Branch GA 30542",
    "addr:housenumber":"5735",
    "addr:postcode":"30542",
    "addr:street":"Garden Walk",
    "iso:country":"US",
    "sg:address":"5735 Garden Walk",
    "sg:city":"Flowery Branch",
    "sg:classifiers":[
        {
            "category":"Retail",
            "subcategory":"Auto Repair",
            "type":"Services"
        }
    ],
    "sg:phone":"+1 770 540 8506",
    "sg:postcode":"30542",
    "sg:province":"GA",
    "sg:tags":[
        "automotive"
    ],
    "wof:name":"A1 Custom Automats",
    "wof:placetype":"venue"
},
  "geometry": {"coordinates":[-83.93465999999999,34.199193],"type":"Point"}
}