{
  "type": "Feature",
  "properties": {
    "addr:full":"1315 Delauney Ave Ste 101 Columbus GA 31901",
    "addr:housenumber":"1315",
    "addr:postcode":"31901",
    "addr:street":"Delauney Ave Ste 101",
    "iso:country":"US",
    "sg:address":"1315 Delauney Ave Ste 101",
    "sg:city":"Columbus",
    "sg:classifiers":[
        {
            "category":"Health Services",
            "subcategory":"Doctor",
            "type":"Services"
        }
    ],
    "sg:phone":"+1 706 320 0055",
    "sg:postcode":"31901",
    "sg:province":"GA",
    "sg:tags":[
        "physician",
        "family",
        "practice",
        "surgeons",
        "internal",
        "medicine",
        "surgeon"
    ],
    "wof:name":"Christian Medical Associates",
    "wof:placetype":"venue"
},
  "geometry": {"coordinates":[-84.973007,32.473976],"type":"Point"}
}