{
  "type": "Feature",
  "properties": {
    "addr:full":"1650 Brockett Rd Tucker GA 30084",
    "addr:housenumber":"1650",
    "addr:postcode":"30084",
    "addr:street":"Brockett Rd",
    "iso:country":"US",
    "sg:address":"1650 Brockett Rd",
    "sg:city":"Tucker",
    "sg:classifiers":[
        {
            "category":"Wholesale",
            "subcategory":"Machinery & Supplies",
            "type":"Manufacturing & Wholesale Goods"
        }
    ],
    "sg:phone":"+1 770 939 8640",
    "sg:postcode":"30084",
    "sg:province":"GA",
    "sg:tags":[
        "pressure",
        "commercial",
        "washing"
    ],
    "wof:name":"Imagefirst Pressure Wshg Svc",
    "wof:placetype":"venue"
},
  "geometry": {"coordinates":[-84.22719600000001,33.832383],"type":"Point"}
}