{
  "type": "Feature",
  "properties": {
    "addr:full":"4142 Lee Rd SW Snellville GA 30039",
    "addr:housenumber":"4142",
    "addr:postcode":"30039",
    "addr:street":"Lee Rd Sw",
    "iso:country":"US",
    "sg:address":"4142 Lee Rd SW",
    "sg:city":"Snellville",
    "sg:classifiers":[
        {
            "category":"Professional",
            "subcategory":"Business Services",
            "type":"Services"
        }
    ],
    "sg:phone":"+1 770 978 7728",
    "sg:postcode":"30039",
    "sg:province":"GA",
    "wof:name":"Be Goode HM Coml Installation",
    "wof:placetype":"venue"
},
  "geometry": {"coordinates":[-84.02915900000001,33.779787],"type":"Point"}
}