{
  "type": "Feature",
  "properties": {
    "addr:full":"369 S Belair Rd Augusta GA 30907",
    "addr:housenumber":"369",
    "addr:postcode":"30907",
    "addr:street":"S Belair Rd",
    "iso:country":"US",
    "sg:address":"369 S Belair Rd",
    "sg:city":"Augusta",
    "sg:classifiers":[
        {
            "category":"Retail",
            "subcategory":"Auto Repair",
            "type":"Services"
        }
    ],
    "sg:phone":"+1 706 651 9808",
    "sg:postcode":"30907",
    "sg:province":"GA",
    "sg:tags":[
        "automobile",
        "lubrication"
    ],
    "sg:website":"http://www.jiffylube.com",
    "wof:name":"Jiffy Lube",
    "wof:placetype":"venue"
},
  "geometry": {"coordinates":[-82.134727,33.488137],"type":"Point"}
}