{
  "type": "Feature",
  "properties": {
    "iso:country":"US",
    "sg:address":"1403 4th Ave",
    "sg:city":"Brunswick",
    "sg:classifiers":[
        {
            "category":"Retail",
            "subcategory":"Veterinary Services",
            "type":"Services"
        }
    ],
    "sg:phone":"+1 912 264 2258",
    "sg:postcode":"31520",
    "sg:province":"GA",
    "wof:name":"Animal Care Clinic",
    "wof:placetype":"venue"
},
  "geometry": {"coordinates":[-81.48272299999999,31.134475],"type":"Point"}
}