{
  "type": "Feature",
  "properties": {
    "iso:country":"US",
    "sg:address":"6577 State Hwy 42",
    "sg:city":"Rex",
    "sg:classifiers":[
        {
            "category":"Autos & Motor Vehicles",
            "subcategory":"Automobile Sales",
            "type":"Retail Goods"
        }
    ],
    "sg:phone":"+1 770 474 1761",
    "sg:postcode":"30273",
    "sg:province":"GA",
    "sg:tags":[
        "car",
        "used",
        "dealer",
        "new"
    ],
    "wof:name":"Rex Motors Sales & Service",
    "wof:placetype":"venue"
},
  "geometry": {"coordinates":[-84.27039000000001,33.57712],"type":"Point"}
}