{
  "type": "Feature",
  "properties": {
    "addr:full":"5975 Fairburn Rd Douglasville GA 30134",
    "addr:housenumber":"5975",
    "addr:postcode":"30134",
    "addr:street":"Fairburn Rd",
    "iso:country":"US",
    "sg:address":"5975 Fairburn Rd",
    "sg:city":"Douglasville",
    "sg:classifiers":[
        {
            "category":"Banks & Credit Unions",
            "subcategory":"Bank",
            "type":"Services"
        }
    ],
    "sg:phone":"+1 770 577 0498",
    "sg:postcode":"30134",
    "sg:province":"GA",
    "sg:tags":[
        "personal",
        "institution"
    ],
    "wof:name":"Advance America",
    "wof:placetype":"venue"
},
  "geometry": {"coordinates":[-84.739043,33.751045],"type":"Point"}
}