{
  "type": "Feature",
  "properties": {
    "addr:full":"369 Fairview Rd Ellenwood GA 30294",
    "addr:housenumber":"369",
    "addr:postcode":"30294",
    "addr:street":"Fairview Rd",
    "iso:country":"US",
    "sg:address":"369 Fairview Rd",
    "sg:city":"Ellenwood",
    "sg:classifiers":[
        {
            "category":"Real Estate",
            "subcategory":"Real Estate Agent",
            "type":"Services"
        }
    ],
    "sg:phone":"+1 770 507 7071",
    "sg:postcode":"30294",
    "sg:province":"GA",
    "wof:name":"Milestone Personnel Services",
    "wof:placetype":"venue"
},
  "geometry": {"coordinates":[-84.249662,33.619064],"type":"Point"}
}