{
  "type": "Feature",
  "properties": {
    "iso:country":"US",
    "sg:address":"297 Prince Ave",
    "sg:city":"Athens",
    "sg:classifiers":[
        {
            "category":"Professional",
            "subcategory":"Lawyer & Legal Services",
            "type":"Services"
        }
    ],
    "sg:phone":"+1 706 353 8099",
    "sg:postcode":"30601",
    "sg:province":"GA",
    "sg:tags":[
        "practice",
        "attorney",
        "criminal",
        "law"
    ],
    "sg:website":"http://www.elizabethmgrant.com",
    "wof:name":"Grant Elizabeth M",
    "wof:placetype":"venue"
},
  "geometry": {"coordinates":[-83.383314,33.960383],"type":"Point"}
}