{
  "type": "Feature",
  "properties": {
    "iso:country":"US",
    "sg:address":"996 W Ridge Rd",
    "sg:city":"Gainesville",
    "sg:classifiers":[
        {
            "category":"Social Services",
            "type":"Services"
        }
    ],
    "sg:phone":"+1 770 531 0046",
    "sg:postcode":"30501",
    "sg:province":"GA",
    "sg:tags":[
        "organization",
        "welfare"
    ],
    "wof:name":"Veterans & Community Outreach",
    "wof:placetype":"venue"
},
  "geometry": {"coordinates":[-83.814318,34.283831],"type":"Point"}
}