{
  "type": "Feature",
  "properties": {
    "addr:full":"1473 State Rte 75 Alt Cleveland GA 30528",
    "addr:housenumber":"1473",
    "addr:postcode":"30528",
    "addr:street":"State Rte 75 Alt",
    "iso:country":"US",
    "sg:address":"1473 State Rte 75 Alt",
    "sg:city":"Cleveland",
    "sg:classifiers":[
        {
            "category":"Building & Trades",
            "subcategory":"Construction",
            "type":"Services"
        }
    ],
    "sg:phone":"+1 706 865 6147",
    "sg:postcode":"30528",
    "sg:province":"GA",
    "sg:tags":[
        "general",
        "contractor"
    ],
    "sg:website":"www.rcc-i.com",
    "wof:name":"Ron Cantrell Construction Inc",
    "wof:placetype":"venue"
},
  "geometry": {"coordinates":[-83.795182,34.641747],"type":"Point"}
}