{
  "type": "Feature",
  "properties": {
    "iso:country":"US",
    "sg:address":"1718 W Oakridge Dr",
    "sg:city":"Albany",
    "sg:classifiers":[
        {
            "category":"Wholesale",
            "subcategory":"Machinery & Supplies",
            "type":"Manufacturing & Wholesale Goods"
        }
    ],
    "sg:phone":"+1 229 883 1827",
    "sg:postcode":"31707",
    "sg:province":"GA",
    "sg:tags":[
        "contractor"
    ],
    "wof:name":"Danny Swain Heavy Equipment",
    "wof:placetype":"venue"
},
  "geometry": {"coordinates":[-84.204133,31.548988],"type":"Point"}
}