{
  "type": "Feature",
  "properties": {
    "addr:full":"5945 Riggins Mill Rd Dry Branch GA 31020",
    "addr:housenumber":"5945",
    "addr:postcode":"31020",
    "addr:street":"Riggins Mill Rd Dry Branch",
    "iso:country":"US",
    "sg:address":"5945 Riggins Mill Rd",
    "sg:city":"Dry Branch",
    "sg:classifiers":[
        {
            "category":"Utilities",
            "subcategory":"Refuse",
            "type":"Services"
        }
    ],
    "sg:phone":"+1 478 746 6565",
    "sg:postcode":"31020",
    "sg:province":"GA",
    "sg:tags":[
        "system"
    ],
    "wof:name":"Riggins Mill Recycle Plastics",
    "wof:placetype":"venue"
},
  "geometry": {"coordinates":[-83.53574399999999,32.803805],"type":"Point"}
}