{
  "type": "Feature",
  "properties": {
    "addr:full":"1416 Baytree Rd Valdosta GA 31602",
    "addr:housenumber":"1416",
    "addr:postcode":"31602",
    "addr:street":"Baytree Rd",
    "iso:country":"US",
    "sg:address":"1416 Baytree Rd",
    "sg:city":"Valdosta",
    "sg:classifiers":[
        {
            "category":"Freight",
            "type":"Transportation"
        }
    ],
    "sg:phone":"+1 229 241 7668",
    "sg:postcode":"31602",
    "sg:province":"GA",
    "sg:tags":[
        "general"
    ],
    "wof:name":"Baytree Self Storage",
    "wof:placetype":"venue"
},
  "geometry": {"coordinates":[-83.311307,30.847017],"type":"Point"}
}