{
  "type": "Feature",
  "properties": {
    "addr:full":"430 Prince Ave Athens GA 30601",
    "addr:housenumber":"430",
    "addr:postcode":"30601",
    "addr:street":"Prince Ave",
    "iso:country":"US",
    "sg:address":"430 Prince Ave",
    "sg:city":"Athens",
    "sg:classifiers":[
        {
            "category":"Restaurant",
            "type":"Food & Drink"
        }
    ],
    "sg:menulink":"http://www.allmenus.com/ga/athens/244192-huddle-house/menu/",
    "sg:phone":"+1 706 354 6100",
    "sg:postcode":"30601",
    "sg:province":"GA",
    "sg:tags":[
        "american",
        "diner"
    ],
    "wof:name":"Huddle House",
    "wof:placetype":"venue"
},
  "geometry": {"coordinates":[-83.385237,33.960714],"type":"Point"}
}