{
  "type": "Feature",
  "properties": {
    "iso:country":"US",
    "sg:address":"607 Ashley Cir",
    "sg:city":"Marietta",
    "sg:classifiers":[
        {
            "category":"Building & Trades",
            "subcategory":"Landscaping Services",
            "type":"Services"
        }
    ],
    "sg:phone":"+1 770 633 8172",
    "sg:postcode":"30008",
    "sg:province":"GA",
    "sg:tags":[
        "landscape",
        "contractor"
    ],
    "wof:name":"Sola Landscaping",
    "wof:placetype":"venue"
},
  "geometry": {"coordinates":[-84.600408,33.899429],"type":"Point"}
}