{
  "type": "Feature",
  "properties": {
    "addr:full":"1198 Howell Mill Rd NW Atlanta GA 30318",
    "addr:housenumber":"1198",
    "addr:postcode":"30318",
    "addr:street":"Howell Mill Rd Nw",
    "iso:country":"US",
    "sg:address":"1198 Howell Mill Rd NW",
    "sg:city":"Atlanta",
    "sg:phone":"+1 404 355 0788",
    "sg:postcode":"30318",
    "sg:province":"GA",
    "wof:name":"The Garden Path",
    "wof:placetype":"venue"
},
  "geometry": {"coordinates":[-84.411732,33.786884],"type":"Point"}
}