{
  "type": "Feature",
  "properties": {
    "addr:full":"1175 Orchid Way Canton GA 30115",
    "addr:housenumber":"1175",
    "addr:postcode":"30115",
    "addr:street":"Orchid Way",
    "iso:country":"US",
    "sg:address":"1175 Orchid Way",
    "sg:city":"Canton",
    "sg:classifiers":[
        {
            "category":"Education",
            "subcategory":"Special Training",
            "type":"Public Place"
        }
    ],
    "sg:phone":"+1 770 475 4472",
    "sg:postcode":"30115",
    "sg:province":"GA",
    "wof:name":"A Joyful Noise",
    "wof:placetype":"venue"
},
  "geometry": {"coordinates":[-84.39989799999999,34.18561],"type":"Point"}
}