{
  "type": "Feature",
  "properties": {
    "iso:country":"US",
    "sg:address":"121 Harris Dr",
    "sg:city":"Locust Grove",
    "sg:classifiers":[
        {
            "category":"Autos & Motor Vehicles",
            "subcategory":"Automobile Sales",
            "type":"Retail Goods"
        }
    ],
    "sg:phone":"+1 770 914 6070",
    "sg:postcode":"30248",
    "sg:province":"GA",
    "sg:tags":[
        "new",
        "used"
    ],
    "wof:name":"McDonough Motors",
    "wof:placetype":"venue"
},
  "geometry": {"coordinates":[-84.092161,33.366083],"type":"Point"}
}