{
  "type": "Feature",
  "properties": {
    "iso:country":"US",
    "sg:address":"5085 Jett Forest Trl NW",
    "sg:city":"Atlanta",
    "sg:classifiers":[
        {
            "category":"Shopping",
            "subcategory":"Jewelry",
            "type":"Retail Goods"
        }
    ],
    "sg:phone":"+1 404 847 0545",
    "sg:postcode":"30327",
    "sg:province":"GA",
    "sg:tags":[
        "precious",
        "semi-precious",
        "stone"
    ],
    "wof:name":"Kate Slater Jewelry Design",
    "wof:placetype":"venue"
},
  "geometry": {"coordinates":[-84.421201,33.893926],"type":"Point"}
}