{
  "type": "Feature",
  "properties": {
    "addr:full":"210 Rose Dhu Rd Savannah GA 31419",
    "addr:housenumber":"210",
    "addr:postcode":"31419",
    "addr:street":"Rose Dhu Rd",
    "iso:country":"US",
    "sg:address":"210 Rose Dhu Rd",
    "sg:city":"Savannah",
    "sg:classifiers":[
        {
            "category":"Building & Trades",
            "subcategory":"Construction",
            "type":"Services"
        }
    ],
    "sg:phone":"+1 912 927 4242",
    "sg:postcode":"31419",
    "sg:province":"GA",
    "sg:tags":[
        "house"
    ],
    "wof:name":"Nelson Homes Inc",
    "wof:placetype":"venue"
},
  "geometry": {"coordinates":[-81.13924299999999,31.937875],"type":"Point"}
}