{
  "type": "Feature",
  "properties": {
    "addr:full":"8305 Dunwoody Pl Atlanta GA 30350",
    "addr:housenumber":"8305",
    "addr:postcode":"30350",
    "addr:street":"Dunwoody Pl",
    "iso:country":"US",
    "sg:address":"8305 Dunwoody Pl",
    "sg:city":"Atlanta",
    "sg:classifiers":[
        {
            "category":"Professional",
            "subcategory":"Engineering",
            "type":"Services"
        }
    ],
    "sg:phone":"+1 770 642 8200",
    "sg:postcode":"30350",
    "sg:province":"GA",
    "sg:tags":[
        "engineer"
    ],
    "wof:name":"G Ben Turnipseed Engineers Inc",
    "wof:placetype":"venue"
},
  "geometry": {"coordinates":[-84.34131499999999,33.985367],"type":"Point"}
}