{
  "type": "Feature",
  "properties": {
    "addr:full":"214 Ashley Dr Mc Donough GA 30252",
    "addr:housenumber":"214",
    "addr:postcode":"30252",
    "addr:street":"Ashley Dr",
    "iso:country":"US",
    "sg:address":"214 Ashley Dr",
    "sg:city":"Mc Donough",
    "sg:classifiers":[
        {
            "category":"Building & Trades",
            "subcategory":"Landscaping Services",
            "type":"Services"
        }
    ],
    "sg:phone":"+1 404 425 2282",
    "sg:postcode":"30252",
    "sg:province":"GA",
    "sg:tags":[
        "landscape"
    ],
    "wof:name":"Harvey Design Group Inc",
    "wof:placetype":"venue"
},
  "geometry": {"coordinates":[-84.121464,33.472753],"type":"Point"}
}