{
  "type": "Feature",
  "properties": {
    "iso:country":"US",
    "sg:address":"1111 Scott Blvd",
    "sg:city":"Decatur",
    "sg:classifiers":[
        {
            "category":"Organizations",
            "subcategory":"Membership Organization",
            "type":"Services"
        }
    ],
    "sg:phone":"+1 404 377 7037",
    "sg:postcode":"30030",
    "sg:province":"GA",
    "wof:name":"Chesterfield Association Inc",
    "wof:placetype":"venue"
},
  "geometry": {"coordinates":[-84.298176,33.788481],"type":"Point"}
}