{
  "type": "Feature",
  "properties": {
    "addr:full":"301 State Rte 188 Cairo GA 39828",
    "addr:housenumber":"301",
    "addr:postcode":"39828",
    "addr:street":"State Rte 188",
    "iso:country":"US",
    "sg:address":"301 State Rte 188",
    "sg:city":"Cairo",
    "sg:classifiers":[
        {
            "category":"Home & Garden",
            "subcategory":"Garden Supply",
            "type":"Retail Goods"
        }
    ],
    "sg:phone":"+1 229 377 9145",
    "sg:postcode":"39828",
    "sg:province":"GA",
    "sg:tags":[
        "center"
    ],
    "wof:name":"Tri Color Garden",
    "wof:placetype":"venue"
},
  "geometry": {"coordinates":[-84.20128,30.878779],"type":"Point"}
}