{
  "type": "Feature",
  "properties": {
    "iso:country":"US",
    "sg:address":"6040 Unity Dr",
    "sg:city":"Norcross",
    "sg:classifiers":[
        {
            "category":"Arts & Performance",
            "subcategory":"Theater",
            "type":"Entertainment"
        }
    ],
    "sg:phone":"+1 770 441 9806",
    "sg:postcode":"30071",
    "sg:province":"GA",
    "sg:tags":[
        "live",
        "music"
    ],
    "wof:name":"Spectrum Entertainment",
    "wof:placetype":"venue"
},
  "geometry": {"coordinates":[-84.204763,33.914911],"type":"Point"}
}