{
  "type": "Feature",
  "properties": {
    "iso:country":"US",
    "sg:address":"1720 Lake Dow Rd",
    "sg:city":"Mc Donough",
    "sg:classifiers":[
        {
            "category":"Recreation",
            "type":"Entertainment"
        }
    ],
    "sg:phone":"+1 770 898 5707",
    "sg:postcode":"30252",
    "sg:province":"GA",
    "sg:tags":[
        "club",
        "membership"
    ],
    "wof:name":"Community Playhouse Club",
    "wof:placetype":"venue"
},
  "geometry": {"coordinates":[-84.071836,33.447724],"type":"Point"}
}