{
  "type": "Feature",
  "properties": {
    "iso:country":"US",
    "sg:address":"3200 Downwood Cir NW",
    "sg:city":"Atlanta",
    "sg:classifiers":[
        {
            "category":"Professional",
            "subcategory":"Detective & Security Services",
            "type":"Services"
        }
    ],
    "sg:phone":"+1 404 355 2690",
    "sg:postcode":"30327",
    "sg:province":"GA",
    "sg:tags":[
        "information",
        "bureau"
    ],
    "wof:name":"Buckhead Surgical Servic",
    "wof:placetype":"venue"
},
  "geometry": {"coordinates":[-84.426422,33.840912],"type":"Point"}
}