{
  "type": "Feature",
  "properties": {
    "addr:full":"2540 Pleasant Hill Rd Duluth GA 30096",
    "addr:housenumber":"2540",
    "addr:postcode":"30096",
    "addr:street":"Pleasant Hill Rd",
    "iso:country":"US",
    "sg:address":"2540 Pleasant Hill Rd",
    "sg:city":"Duluth",
    "sg:classifiers":[
        {
            "category":"Banks & Credit Unions",
            "subcategory":"Bank",
            "type":"Services"
        }
    ],
    "sg:phone":"+1 678 417 7572",
    "sg:postcode":"30096",
    "sg:province":"GA",
    "wof:name":"United Commercial Bank",
    "wof:placetype":"venue"
},
  "geometry": {"coordinates":[-84.143158,33.967199],"type":"Point"}
}