{
  "type": "Feature",
  "properties": {
    "addr:full":"2900 Crepe Myrtle Dr Blackshear GA 31516",
    "addr:housenumber":"2900",
    "addr:postcode":"31516",
    "addr:street":"Crepe Myrtle Dr",
    "iso:country":"US",
    "sg:address":"2900 Crepe Myrtle Dr",
    "sg:city":"Blackshear",
    "sg:classifiers":[
        {
            "category":"Utilities",
            "subcategory":"Cable",
            "type":"Services"
        }
    ],
    "sg:phone":"+1 912 449 3040",
    "sg:postcode":"31516",
    "sg:province":"GA",
    "sg:tags":[
        "television"
    ],
    "wof:name":"Star Independant Investor",
    "wof:placetype":"venue"
},
  "geometry": {"coordinates":[-82.278114,31.248322],"type":"Point"}
}