{
  "type": "Feature",
  "properties": {
    "iso:country":"US",
    "sg:address":"116 River Bottom Cir",
    "sg:city":"Athens",
    "sg:classifiers":[
        {
            "category":"Arts & Performance",
            "subcategory":"Theater",
            "type":"Entertainment"
        }
    ],
    "sg:phone":"+1 706 549 5712",
    "sg:postcode":"30606",
    "sg:province":"GA",
    "sg:tags":[
        "live",
        "music"
    ],
    "sg:website":"www.crs2.com",
    "wof:name":"Computer Related Svc",
    "wof:placetype":"venue"
},
  "geometry": {"coordinates":[-83.457138,33.956596],"type":"Point"}
}