{
  "type": "Feature",
  "properties": {
    "iso:country":"US",
    "sg:address":"180 Riverstone Pkwy",
    "sg:city":"Canton",
    "sg:classifiers":[
        {
            "category":"Food & Beverages",
            "subcategory":"Groceries & Convenience Stores",
            "type":"Retail Goods"
        }
    ],
    "sg:phone":"+1 770 720 1270",
    "sg:postcode":"30114",
    "sg:province":"GA",
    "sg:tags":[
        "grocer"
    ],
    "wof:name":"Carniceria Ramirez",
    "wof:placetype":"venue"
},
  "geometry": {"coordinates":[-84.49214499999999,34.243505],"type":"Point"}
}