{
  "type": "Feature",
  "properties": {
    "addr:full":"7200 Bishop Rd Austell GA 30168",
    "addr:housenumber":"7200",
    "addr:postcode":"30168",
    "addr:street":"Bishop Rd",
    "iso:country":"US",
    "sg:address":"7200 Bishop Rd",
    "sg:city":"Austell",
    "sg:classifiers":[
        {
            "category":"Building & Trades",
            "subcategory":"Construction",
            "type":"Services"
        }
    ],
    "sg:phone":"+1 770 732 9288",
    "sg:postcode":"30168",
    "sg:province":"GA",
    "sg:tags":[
        "lift",
        "aerial",
        "scaffolding"
    ],
    "sg:website":"http://www.fraco.com",
    "wof:name":"Fraco Products Inc",
    "wof:placetype":"venue"
},
  "geometry": {"coordinates":[-84.54650100000001,33.778301],"type":"Point"}
}