{
  "type": "Feature",
  "properties": {
    "iso:country":"US",
    "sg:address":"2020 Hills Ave NW",
    "sg:city":"Atlanta",
    "sg:classifiers":[
        {
            "category":"Wholesale",
            "subcategory":"Office Equipment",
            "type":"Manufacturing & Wholesale Goods"
        }
    ],
    "sg:phone":"+1 404 605 0100",
    "sg:postcode":"30318",
    "sg:province":"GA",
    "sg:tags":[
        "banking",
        "parts",
        "bank",
        "supply"
    ],
    "wof:name":"Bankers Exchange Inc",
    "wof:placetype":"venue"
},
  "geometry": {"coordinates":[-84.433907,33.809717],"type":"Point"}
}