{
  "type": "Feature",
  "properties": {
    "addr:full":"3405 Mike Padgett Hwy Augusta GA 30906",
    "addr:housenumber":"3405",
    "addr:postcode":"30906",
    "addr:street":"Mike Padgett Hwy",
    "iso:country":"US",
    "sg:address":"3405 Mike Padgett Hwy",
    "sg:city":"Augusta",
    "sg:classifiers":[
        {
            "category":"Health Services",
            "subcategory":"Hospital",
            "type":"Services"
        },
        {
            "category":"Social Services",
            "subcategory":"Job Training",
            "type":"Services"
        },
        {
            "category":"Health Services",
            "subcategory":"Clinic",
            "type":"Services"
        }
    ],
    "sg:phone":"+1 706 792 7105",
    "sg:postcode":"30906",
    "sg:province":"GA",
    "sg:tags":[
        "medical",
        "nursing",
        "homes-skilled",
        "facility"
    ],
    "sg:website":"http://www.ecrh.dhr.state.ga.us",
    "wof:name":"East Central Regional Hospital",
    "wof:placetype":"venue"
},
  "geometry": {"coordinates":[-82.00559199999999,33.398548],"type":"Point"}
}