{
  "type": "Feature",
  "properties": {
    "iso:country":"US",
    "sg:address":"4144 Clairmont Rd",
    "sg:city":"Atlanta",
    "sg:classifiers":[
        {
            "category":"Health Services",
            "subcategory":"Chiropractor",
            "type":"Services"
        }
    ],
    "sg:phone":"+1 404 885 1799",
    "sg:postcode":"30341",
    "sg:province":"GA",
    "wof:name":"Dc Center",
    "wof:placetype":"venue"
},
  "geometry": {"coordinates":[-84.30954699999999,33.883794],"type":"Point"}
}