{
  "type": "Feature",
  "properties": {
    "iso:country":"US",
    "sg:address":"5730 Riverwood Dr NW",
    "sg:city":"Atlanta",
    "sg:classifiers":[
        {
            "category":"Retail",
            "subcategory":"Car Wash",
            "type":"Services"
        }
    ],
    "sg:phone":"+1 404 633 5973",
    "sg:postcode":"30328",
    "sg:province":"GA",
    "wof:name":"Atlantas Best Carwashes Inc",
    "wof:placetype":"venue"
},
  "geometry": {"coordinates":[-84.397976,33.92597],"type":"Point"}
}