{
  "type": "Feature",
  "properties": {
    "addr:full":"1974 Mason Mill Rd Decatur GA 30033",
    "addr:housenumber":"1974",
    "addr:postcode":"30033",
    "addr:street":"Mason Mill Rd",
    "iso:country":"US",
    "sg:address":"1974 Mason Mill Rd",
    "sg:city":"Decatur",
    "sg:classifiers":[
        {
            "category":"Professional",
            "subcategory":"Computer Services",
            "type":"Services"
        }
    ],
    "sg:phone":"+1 404 315 1972",
    "sg:postcode":"30033",
    "sg:province":"GA",
    "sg:tags":[
        "physical",
        "custom",
        "commercial",
        "programing",
        "research"
    ],
    "wof:name":"General Computer Services",
    "wof:placetype":"venue"
},
  "geometry": {"coordinates":[-84.30900099999999,33.806938],"type":"Point"}
}