{
  "type": "Feature",
  "properties": {
    "addr:full":"4191 Fitzgerald Hwy Ambrose GA 31512",
    "addr:housenumber":"4191",
    "addr:postcode":"31512",
    "addr:street":"Fitzgerald Hwy",
    "iso:country":"US",
    "sg:address":"4191 Fitzgerald Hwy",
    "sg:city":"Ambrose",
    "sg:classifiers":[
        {
            "category":"Farming",
            "subcategory":"Livestock Farm",
            "type":"Manufacturing & Wholesale Goods"
        }
    ],
    "sg:phone":"+1 912 359 3521",
    "sg:postcode":"31512",
    "sg:province":"GA",
    "sg:tags":[
        "beef",
        "feedlot",
        "cattle"
    ],
    "wof:name":"Jimmy Mc Callum",
    "wof:placetype":"venue"
},
  "geometry": {"coordinates":[-82.96429500000001,31.659203],"type":"Point"}
}