{
  "type": "Feature",
  "properties": {
    "addr:full":"5050 Jimmy Carter Blvd Norcross GA 30093",
    "addr:housenumber":"5050",
    "addr:postcode":"30093",
    "addr:street":"Jimmy Carter Blvd",
    "iso:country":"US",
    "sg:address":"5050 Jimmy Carter Blvd",
    "sg:city":"Norcross",
    "sg:classifiers":[
        {
            "category":"Taxi",
            "type":"Transportation"
        }
    ],
    "sg:phone":"+1 770 582 9757",
    "sg:postcode":"30093",
    "sg:province":"GA",
    "wof:name":"Economy Taxi",
    "wof:placetype":"venue"
},
  "geometry": {"coordinates":[-84.19933899999999,33.897114],"type":"Point"}
}