{
  "type": "Feature",
  "properties": {
    "addr:full":"176 Key Circle Dr Brunswick GA 31520",
    "addr:housenumber":"176",
    "addr:postcode":"31520",
    "addr:street":"Key Circle Dr",
    "iso:country":"US",
    "sg:address":"176 Key Circle Dr",
    "sg:city":"Brunswick",
    "sg:classifiers":[
        {
            "category":"Professional",
            "type":"Services"
        }
    ],
    "sg:phone":"+1 912 262 1930",
    "sg:postcode":"31520",
    "sg:province":"GA",
    "wof:name":"Total Life Care Services",
    "wof:placetype":"venue"
},
  "geometry": {"coordinates":[-81.49187499999999,31.201217],"type":"Point"}
}