{
  "type": "Feature",
  "properties": {
    "addr:full":"PO Box 769 Canton GA 30169",
    "addr:housenumber":"po",
    "addr:postcode":"30169",
    "addr:street":"Box 769",
    "iso:country":"US",
    "sg:address":"PO Box 769",
    "sg:city":"Canton",
    "sg:classifiers":[
        {
            "category":"Education",
            "subcategory":"School",
            "type":"Public Place"
        }
    ],
    "sg:phone":"+1 770 479 1871",
    "sg:postcode":"30169",
    "sg:province":"GA",
    "sg:tags":[
        "high",
        "middle",
        "elementary"
    ],
    "sg:website":"www.cherokee.k12.ga.us",
    "wof:name":"Cherokee County of",
    "wof:placetype":"venue"
},
  "geometry": {"coordinates":[-84.492178,34.235988],"type":"Point"}
}