{
  "type": "Feature",
  "properties": {
    "iso:country":"US",
    "sg:address":"765 River Overlook Dr NW",
    "sg:city":"Lawrenceville",
    "sg:classifiers":[
        {
            "category":"Professional",
            "subcategory":"Business Services",
            "type":"Services"
        }
    ],
    "sg:phone":"+1 404 667 2383",
    "sg:postcode":"30043",
    "sg:province":"GA",
    "wof:name":"C&S Enterprises",
    "wof:placetype":"venue"
},
  "geometry": {"coordinates":[-84.02293899999999,33.977858],"type":"Point"}
}