{
  "type": "Feature",
  "properties": {
    "addr:full":"600 Guy Paine Rd Macon GA 31206",
    "addr:housenumber":"600",
    "addr:postcode":"31206",
    "addr:street":"Guy Paine Rd",
    "iso:country":"US",
    "sg:address":"600 Guy Paine Rd",
    "sg:city":"Macon",
    "sg:classifiers":[
        {
            "category":"Building & Trades",
            "subcategory":"Electrical",
            "type":"Services"
        }
    ],
    "sg:phone":"+1 478 784 1105",
    "sg:postcode":"31206",
    "sg:province":"GA",
    "sg:tags":[
        "contracting",
        "electrical"
    ],
    "wof:name":"Mr Electric",
    "wof:placetype":"venue"
},
  "geometry": {"coordinates":[-83.650468,32.780159],"type":"Point"}
}