{
  "type": "Feature",
  "properties": {
    "iso:country":"US",
    "sg:address":"1167 Clearview Dr NE",
    "sg:city":"Atlanta",
    "sg:classifiers":[
        {
            "category":"Shopping",
            "subcategory":"Discount & Variety Stores",
            "type":"Retail Goods"
        }
    ],
    "sg:phone":"+1 404 636 1099",
    "sg:postcode":"30319",
    "sg:province":"GA",
    "sg:tags":[
        "antique",
        "novelty"
    ],
    "wof:name":"Southern Gallery",
    "wof:placetype":"venue"
},
  "geometry": {"coordinates":[-84.34069,33.838378],"type":"Point"}
}