{
  "type": "Feature",
  "properties": {
    "addr:full":"2960 Gravel Springs Rd Buford GA 30519",
    "addr:housenumber":"2960",
    "addr:postcode":"30519",
    "addr:street":"Gravel Springs Rd",
    "iso:country":"US",
    "sg:address":"2960 Gravel Springs Rd",
    "sg:city":"Buford",
    "sg:phone":"+1 770 945 7727",
    "sg:postcode":"30519",
    "sg:province":"GA",
    "wof:name":"Gravel Springs Dental",
    "wof:placetype":"venue"
},
  "geometry": {"coordinates":[-83.961878,34.070438],"type":"Point"}
}