{
  "type": "Feature",
  "properties": {
    "iso:country":"US",
    "sg:address":"27 Hardee Dr",
    "sg:city":"Savannah",
    "sg:classifiers":[
        {
            "category":"Building & Trades",
            "subcategory":"Construction",
            "type":"Services"
        }
    ],
    "sg:phone":"+1 912 355 7148",
    "sg:postcode":"31406",
    "sg:province":"GA",
    "sg:tags":[
        "contract",
        "nonresidential"
    ],
    "wof:name":"Colby Enterprises Inc",
    "wof:placetype":"venue"
},
  "geometry": {"coordinates":[-81.086805,31.927174],"type":"Point"}
}