{
  "type": "Feature",
  "properties": {
    "iso:country":"US",
    "sg:address":"6436 Douglas Blvd",
    "sg:city":"Douglasville",
    "sg:classifiers":[
        {
            "category":"Manufacturing",
            "subcategory":"Glass & Minerals",
            "type":"Manufacturing & Wholesale Goods"
        }
    ],
    "sg:phone":"+1 770 942 2784",
    "sg:postcode":"30135",
    "sg:province":"GA",
    "sg:tags":[
        "plate",
        "window",
        "glass-auto"
    ],
    "wof:name":"ABRA Auto Glass",
    "wof:placetype":"venue"
},
  "geometry": {"coordinates":[-84.741005,33.730674],"type":"Point"}
}