{
  "type": "Feature",
  "properties": {
    "iso:country":"US",
    "sg:address":"1712 Ellis St",
    "sg:city":"Brunswick",
    "sg:classifiers":[
        {
            "category":"Professional",
            "subcategory":"Employment Agencies",
            "type":"Services"
        }
    ],
    "sg:phone":"+1 912 267 1000",
    "sg:postcode":"31520",
    "sg:province":"GA",
    "wof:name":"Personnel Depot Inc",
    "wof:placetype":"venue"
},
  "geometry": {"coordinates":[-81.493977,31.153679],"type":"Point"}
}