{
  "type": "Feature",
  "properties": {
    "addr:full":"1309 Jodeco Rd Stockbridge GA 30281",
    "addr:housenumber":"1309",
    "addr:postcode":"30281",
    "addr:street":"Jodeco Rd",
    "iso:country":"US",
    "sg:address":"1309 Jodeco Rd",
    "sg:city":"Stockbridge",
    "sg:classifiers":[
        {
            "category":"Education",
            "subcategory":"School",
            "type":"Public Place"
        }
    ],
    "sg:phone":"+1 770 389 8819",
    "sg:postcode":"30281",
    "sg:province":"GA",
    "sg:tags":[
        "elementary"
    ],
    "sg:website":"www.henry.k12.ga.us",
    "wof:name":"Pates Creek Elementary School",
    "wof:placetype":"venue"
},
  "geometry": {"coordinates":[-84.244732,33.497966],"type":"Point"}
}