{
  "type": "Feature",
  "properties": {
    "iso:country":"US",
    "sg:address":"458 20th Ave",
    "sg:city":"Columbus",
    "sg:classifiers":[
        {
            "category":"Personal",
            "subcategory":"Beauty Salon",
            "type":"Services"
        }
    ],
    "sg:phone":"+1 706 682 0212",
    "sg:postcode":"31903",
    "sg:province":"GA",
    "sg:tags":[
        "shop"
    ],
    "wof:name":"Foster's Hair Braiding",
    "wof:placetype":"venue"
},
  "geometry": {"coordinates":[-84.96316899999999,32.45279],"type":"Point"}
}