{
  "type": "Feature",
  "properties": {
    "iso:country":"US",
    "sg:address":"1575 Watercove Ln",
    "sg:city":"Lawrenceville",
    "sg:classifiers":[
        {
            "category":"Building & Trades",
            "subcategory":"Cleaning & Sanitation",
            "type":"Services"
        }
    ],
    "sg:phone":"+1 770 527 5046",
    "sg:postcode":"30043",
    "sg:province":"GA",
    "sg:tags":[
        "maintenance"
    ],
    "wof:name":"City Building Inc",
    "wof:placetype":"venue"
},
  "geometry": {"coordinates":[-84.03869299999999,33.983214],"type":"Point"}
}