{
  "type": "Feature",
  "properties": {
    "addr:full":"297 Cotton Ave SE Pelham GA 31779",
    "addr:housenumber":"297",
    "addr:postcode":"31779",
    "addr:street":"Cotton Ave Se",
    "iso:country":"US",
    "sg:address":"297 Cotton Ave SE",
    "sg:city":"Pelham",
    "sg:classifiers":[
        {
            "category":"Government",
            "subcategory":"Office",
            "type":"Public Place"
        }
    ],
    "sg:phone":"+1 229 294 6015",
    "sg:postcode":"31779",
    "sg:province":"GA",
    "sg:tags":[
        "village"
    ],
    "wof:name":"Maintenance Shop",
    "wof:placetype":"venue"
},
  "geometry": {"coordinates":[-84.14595199999999,31.118167],"type":"Point"}
}