{
  "type": "Feature",
  "properties": {
    "iso:country":"US",
    "sg:address":"72 Public Sq N",
    "sg:city":"Dahlonega",
    "sg:classifiers":[
        {
            "category":"Real Estate",
            "subcategory":"Real Estate Agent",
            "type":"Services"
        }
    ],
    "sg:phone":"+1 706 864 1010",
    "sg:postcode":"30533",
    "sg:province":"GA",
    "sg:tags":[
        "appraiser"
    ],
    "wof:name":"Appraisal Network",
    "wof:placetype":"venue"
},
  "geometry": {"coordinates":[-83.98518900000001,34.532753],"type":"Point"}
}