{
  "type": "Feature",
  "properties": {
    "addr:full":"980 Johnson Ferry Rd NE Atlanta GA 30342",
    "addr:housenumber":"980",
    "addr:postcode":"30342",
    "addr:street":"Johnson Ferry Rd Ne",
    "iso:country":"US",
    "sg:address":"980 Johnson Ferry Rd NE",
    "sg:city":"Atlanta",
    "sg:classifiers":[
        {
            "category":"Health Services",
            "subcategory":"Doctor",
            "type":"Services"
        }
    ],
    "sg:phone":"+1 404 255 0621",
    "sg:postcode":"30342",
    "sg:province":"GA",
    "sg:tags":[
        "throat",
        "ear",
        "obstetrician",
        "nose",
        "gynecologist"
    ],
    "wof:name":"Rosenberg Stephen A MD",
    "wof:placetype":"venue"
},
  "geometry": {"coordinates":[-84.355301,33.907902],"type":"Point"}
}