{
  "type": "Feature",
  "properties": {
    "addr:full":"1261 Black Ankle Creek Rd Blue Ridge GA 30513",
    "addr:housenumber":"1261",
    "addr:postcode":"30513",
    "addr:street":"Black Ankle Creek Rd",
    "iso:country":"US",
    "sg:address":"1261 Black Ankle Creek Rd",
    "sg:city":"Blue Ridge",
    "sg:classifiers":[
        {
            "category":"Building & Trades",
            "subcategory":"Construction",
            "type":"Services"
        }
    ],
    "sg:phone":"+1 706 838 4561",
    "sg:postcode":"30513",
    "sg:province":"GA",
    "sg:tags":[
        "home"
    ],
    "wof:name":"Ronald D Coleman Enterprises",
    "wof:placetype":"venue"
},
  "geometry": {"coordinates":[-84.23500799999999,34.745098],"type":"Point"}
}