{
  "type": "Feature",
  "properties": {
    "addr:full":"12184 Highway 92 Woodstock GA 30188",
    "addr:housenumber":"12184",
    "addr:postcode":"30188",
    "addr:street":"Highway 92",
    "iso:country":"US",
    "sg:address":"12184 Highway 92",
    "sg:city":"Woodstock",
    "sg:classifiers":[
        {
            "category":"Shopping",
            "subcategory":"Beauty & Cosmetics",
            "type":"Retail Goods"
        }
    ],
    "sg:phone":"+1 678 388 7543",
    "sg:postcode":"30188",
    "sg:province":"GA",
    "sg:tags":[
        "supply"
    ],
    "sg:website":"www.sallybeauty.com",
    "wof:name":"Sally Beauty Supply",
    "wof:placetype":"venue"
},
  "geometry": {"coordinates":[-84.483037,34.087343],"type":"Point"}
}