{
  "type": "Feature",
  "properties": {
    "addr:full":"100 E McIntosh Rd Griffin GA 30223",
    "addr:housenumber":"100",
    "addr:postcode":"30223",
    "addr:street":"E Mcintosh Rd",
    "iso:country":"US",
    "sg:address":"100 E McIntosh Rd",
    "sg:city":"Griffin",
    "sg:classifiers":[
        {
            "category":"Organizations",
            "subcategory":"Religious Organization",
            "type":"Services"
        }
    ],
    "sg:phone":"+1 770 228 8148",
    "sg:postcode":"30223",
    "sg:province":"GA",
    "wof:name":"Highland Baptist Church",
    "wof:placetype":"venue"
},
  "geometry": {"coordinates":[-84.280475,33.278762],"type":"Point"}
}