{
  "type": "Feature",
  "properties": {
    "addr:full":"3600 Mansell Rd Alpharetta GA 30022",
    "addr:housenumber":"3600",
    "addr:postcode":"30022",
    "addr:street":"Mansell Rd",
    "iso:country":"US",
    "sg:address":"3600 Mansell Rd",
    "sg:city":"Alpharetta",
    "sg:classifiers":[
        {
            "category":"Professional",
            "subcategory":"Lawyer & Legal Services",
            "type":"Services"
        }
    ],
    "sg:phone":"+1 770 641 5400",
    "sg:postcode":"30022",
    "sg:province":"GA",
    "sg:website":"www.culpepper.com",
    "wof:name":"Culpepper and Associates Inc",
    "wof:placetype":"venue"
},
  "geometry": {"coordinates":[-84.29589799999999,34.037498],"type":"Point"}
}