{
  "type": "Feature",
  "properties": {
    "addr:full":"513 W 2nd Ave Albany GA 31701",
    "addr:housenumber":"513",
    "addr:postcode":"31701",
    "addr:street":"W 2Nd Ave",
    "iso:country":"US",
    "sg:address":"513 W 2nd Ave",
    "sg:city":"Albany",
    "sg:classifiers":[
        {
            "category":"Health Services",
            "subcategory":"Doctor",
            "type":"Services"
        }
    ],
    "sg:phone":"+1 229 432 7444",
    "sg:postcode":"31701",
    "sg:province":"GA",
    "sg:tags":[
        "medical"
    ],
    "wof:name":"Diosita Lariosa MD",
    "wof:placetype":"venue"
},
  "geometry": {"coordinates":[-84.161632,31.588925],"type":"Point"}
}