{
  "type": "Feature",
  "properties": {
    "iso:country":"US",
    "sg:address":"2827 Greenrock Trl",
    "sg:city":"Atlanta",
    "sg:classifiers":[
        {
            "category":"Professional",
            "type":"Services"
        }
    ],
    "sg:phone":"+1 770 939 1777",
    "sg:postcode":"30340",
    "sg:province":"GA",
    "sg:tags":[
        "motion",
        "picture",
        "film"
    ],
    "wof:name":"Isosceles Inc",
    "wof:placetype":"venue"
},
  "geometry": {"coordinates":[-84.231781,33.87149],"type":"Point"}
}