{
  "type": "Feature",
  "properties": {
    "iso:country":"US",
    "sg:address":"1722 Rondon Ct SE",
    "sg:city":"Atlanta",
    "sg:classifiers":[
        {
            "category":"Communications",
            "subcategory":"Film & Video Production",
            "type":"Services"
        }
    ],
    "sg:phone":"+1 404 241 9124",
    "sg:postcode":"30316",
    "sg:province":"GA",
    "sg:tags":[
        "tv",
        "services-commercial",
        "companies-film",
        "radio"
    ],
    "wof:name":"Hood Swagg Productionz",
    "wof:placetype":"venue"
},
  "geometry": {"coordinates":[-84.319605,33.69976],"type":"Point"}
}