{
  "type": "Feature",
  "properties": {
    "iso:country":"US",
    "sg:address":"104 Church St",
    "sg:city":"Decatur",
    "sg:phone":"+1 404 378 3694",
    "sg:postcode":"30030",
    "sg:province":"GA",
    "wof:name":"Reagin, Richard S, Od - Reagin Optometric Group",
    "wof:placetype":"venue"
},
  "geometry": {"coordinates":[-84.294967,33.770602],"type":"Point"}
}