{
  "type": "Feature",
  "properties": {
    "iso:country":"US",
    "sg:address":"8891 Bright Star Rd",
    "sg:city":"Douglasville",
    "sg:classifiers":[
        {
            "category":"Personal",
            "type":"Services"
        }
    ],
    "sg:phone":"+1 770 577 2142",
    "sg:postcode":"30134",
    "sg:province":"GA",
    "sg:tags":[
        "mover"
    ],
    "wof:name":"All Star Movers",
    "wof:placetype":"venue"
},
  "geometry": {"coordinates":[-84.779082,33.740018],"type":"Point"}
}