{
  "type": "Feature",
  "properties": {
    "addr:full":"1080 Dawsonville Hwy Gainesville GA 30501",
    "addr:housenumber":"1080",
    "addr:postcode":"30501",
    "addr:street":"Dawsonville Hwy",
    "iso:country":"US",
    "sg:address":"1080 Dawsonville Hwy",
    "sg:city":"Gainesville",
    "sg:classifiers":[
        {
            "category":"Shopping",
            "subcategory":"Bicycles & Sporting Goods",
            "type":"Retail Goods"
        }
    ],
    "sg:phone":"+1 770 503 0470",
    "sg:postcode":"30501",
    "sg:province":"GA",
    "wof:name":"Play It Again Sports",
    "wof:placetype":"venue"
},
  "geometry": {"coordinates":[-83.857429,34.299623],"type":"Point"}
}