{
  "type": "Feature",
  "properties": {
    "iso:country":"US",
    "sg:address":"2456 Walker St",
    "sg:city":"Columbus",
    "sg:classifiers":[
        {
            "category":"Building & Trades",
            "subcategory":"Cleaning & Sanitation",
            "type":"Services"
        }
    ],
    "sg:phone":"+1 706 687 8111",
    "sg:postcode":"31903",
    "sg:province":"GA",
    "sg:tags":[
        "janitor"
    ],
    "wof:name":"C C & A Cleaning Svc",
    "wof:placetype":"venue"
},
  "geometry": {"coordinates":[-84.971344,32.407426],"type":"Point"}
}