{
  "type": "Feature",
  "properties": {
    "iso:country":"US",
    "sg:address":"2160 Westside Ct",
    "sg:city":"Snellville",
    "sg:classifiers":[
        {
            "category":"Professional",
            "subcategory":"Advertising",
            "type":"Services"
        },
        {
            "category":"Retail",
            "subcategory":"Repair Shop",
            "type":"Services"
        },
        {
            "category":"Manufacturing",
            "subcategory":"Signs",
            "type":"Manufacturing & Wholesale Goods"
        }
    ],
    "sg:phone":"+1 770 982 3988",
    "sg:postcode":"30078",
    "sg:province":"GA",
    "sg:tags":[
        "signs-erectors",
        "hanger",
        "specialty",
        "signs-maintenance"
    ],
    "wof:name":"Angles Wood & Graphics",
    "wof:placetype":"venue"
},
  "geometry": {"coordinates":[-84.05162199999999,33.847691],"type":"Point"}
}