{
  "type": "Feature",
  "properties": {
    "iso:country":"US",
    "sg:address":"12075 King Rd",
    "sg:city":"Roswell",
    "sg:classifiers":[
        {
            "category":"Wholesale",
            "subcategory":"Vending Machines",
            "type":"Manufacturing & Wholesale Goods"
        }
    ],
    "sg:phone":"+1 770 645 7929",
    "sg:postcode":"30075",
    "sg:province":"GA",
    "sg:tags":[
        "operator"
    ],
    "wof:name":"Kudzu Vending",
    "wof:placetype":"venue"
},
  "geometry": {"coordinates":[-84.382064,34.074485],"type":"Point"}
}