{
  "type": "Feature",
  "properties": {
    "addr:full":"8450 Hatch Pkwy S Baxley GA 31513",
    "addr:postcode":"8450;31513",
    "addr:street":"Hatch Pkwy S Baxley",
    "iso:country":"US",
    "sg:address":"8450 Hatch Pkwy S",
    "sg:city":"Baxley",
    "sg:classifiers":[
        {
            "category":"Retail",
            "subcategory":"Auto Repair",
            "type":"Services"
        }
    ],
    "sg:phone":"+1 912 367 2900",
    "sg:postcode":"31513",
    "sg:province":"GA",
    "sg:tags":[
        "body",
        "automobile",
        "painting"
    ],
    "wof:name":"Joe's Body Shop",
    "wof:placetype":"venue"
},
  "geometry": {"coordinates":[-82.415986,31.672989],"type":"Point"}
}