{
  "type": "Feature",
  "properties": {
    "iso:country":"US",
    "sg:address":"779 S Marietta Pkwy",
    "sg:city":"Marietta",
    "sg:classifiers":[
        {
            "category":"Restaurant",
            "type":"Food & Drink"
        }
    ],
    "sg:phone":"+1 770 426 9522",
    "sg:postcode":"30060",
    "sg:province":"GA",
    "sg:tags":[
        "eating"
    ],
    "wof:name":"Larrys Country Kitchen",
    "wof:placetype":"venue"
},
  "geometry": {"coordinates":[-84.53103900000001,33.942429],"type":"Point"}
}