{
  "type": "Feature",
  "properties": {
    "iso:country":"US",
    "sg:address":"801 N Tennessee St",
    "sg:city":"Cartersville",
    "sg:classifiers":[
        {
            "category":"Professional",
            "subcategory":"Accounting & Tax Preparation",
            "type":"Services"
        }
    ],
    "sg:phone":"+1 770 607 1331",
    "sg:postcode":"30120",
    "sg:province":"GA",
    "sg:tags":[
        "return"
    ],
    "wof:name":"Web Tax",
    "wof:placetype":"venue"
},
  "geometry": {"coordinates":[-84.79422700000001,34.181895],"type":"Point"}
}