{
  "type": "Feature",
  "properties": {
    "addr:full":"4846 Trevor Ct NE Marietta GA 30068",
    "addr:housenumber":"4846",
    "addr:postcode":"30068",
    "addr:street":"Trevor Ct Ne",
    "iso:country":"US",
    "sg:address":"4846 Trevor Ct NE",
    "sg:city":"Marietta",
    "sg:classifiers":[
        {
            "category":"Professional",
            "subcategory":"Engineering",
            "type":"Services"
        }
    ],
    "sg:phone":"+1 770 594 1770",
    "sg:postcode":"30068",
    "sg:province":"GA",
    "sg:tags":[
        "engineer"
    ],
    "wof:name":"L D Coach",
    "wof:placetype":"venue"
},
  "geometry": {"coordinates":[-84.41017100000001,33.978461],"type":"Point"}
}