{
  "type": "Feature",
  "properties": {
    "addr:full":"212 Hospital Dr Warner Robins GA 31088",
    "addr:housenumber":"212",
    "addr:postcode":"31088",
    "addr:street":"Hospital Dr",
    "iso:country":"US",
    "sg:address":"212 Hospital Dr",
    "sg:city":"Warner Robins",
    "sg:classifiers":[
        {
            "category":"Health Services",
            "subcategory":"Medical Lab",
            "type":"Services"
        }
    ],
    "sg:phone":"+1 478 929 9663",
    "sg:postcode":"31088",
    "sg:province":"GA",
    "sg:tags":[
        "laboratory"
    ],
    "wof:name":"Southeastern Pathology Assoc",
    "wof:placetype":"venue"
},
  "geometry": {"coordinates":[-83.629372,32.615307],"type":"Point"}
}