{
  "type": "Feature",
  "properties": {
    "addr:full":"397 State Rte 126 Dexter GA 31019",
    "addr:housenumber":"397",
    "addr:postcode":"31019",
    "addr:street":"State Rte 126",
    "iso:country":"US",
    "sg:address":"397 State Rte 126",
    "sg:city":"Dexter",
    "sg:classifiers":[
        {
            "category":"Home & Garden",
            "subcategory":"Garden Supply",
            "type":"Retail Goods"
        }
    ],
    "sg:phone":"+1 478 358 4595",
    "sg:postcode":"31019",
    "sg:province":"GA",
    "wof:name":"Browns Nursery",
    "wof:placetype":"venue"
},
  "geometry": {"coordinates":[-83.08292299999999,32.356544],"type":"Point"}
}