{
  "type": "Feature",
  "properties": {
    "addr:full":"3330 Willow Ridge Cir SW Gainesville GA 30504",
    "addr:housenumber":"3330",
    "addr:postcode":"30504",
    "addr:street":"Willow Ridge Cir Sw",
    "iso:country":"US",
    "sg:address":"3330 Willow Ridge Cir SW",
    "sg:city":"Gainesville",
    "sg:classifiers":[
        {
            "category":"Professional",
            "subcategory":"Business Services",
            "type":"Services"
        }
    ],
    "sg:phone":"+1 678 571 7706",
    "sg:postcode":"30504",
    "sg:province":"GA",
    "wof:name":"Menhay Inc",
    "wof:placetype":"venue"
},
  "geometry": {"coordinates":[-83.871606,34.266233],"type":"Point"}
}