{
  "type": "Feature",
  "properties": {
    "addr:full":"119 Samanthas Way Mcdonough GA 30253",
    "addr:housenumber":"119",
    "addr:postcode":"30253",
    "addr:street":"Samanthas Way",
    "iso:country":"US",
    "sg:address":"119 Samanthas Way",
    "sg:city":"Mcdonough",
    "sg:classifiers":[
        {
            "category":"Shopping",
            "subcategory":"Clothing, Apparel, & Fashions",
            "type":"Retail Goods"
        }
    ],
    "sg:phone":"+1 770 898 1029",
    "sg:postcode":"30253",
    "sg:province":"GA",
    "sg:tags":[
        "family"
    ],
    "wof:name":"Trinuity Fashions",
    "wof:placetype":"venue"
},
  "geometry": {"coordinates":[-84.16866,33.441885],"type":"Point"}
}