{
  "type": "Feature",
  "properties": {
    "addr:full":"5150 Chattahoochee Ind Park Cumming GA 30041",
    "addr:housenumber":"5150",
    "addr:postcode":"30041",
    "addr:street":"Chattahoochee Ind Park",
    "iso:country":"US",
    "sg:address":"5150 Chattahoochee Ind Park",
    "sg:city":"Cumming",
    "sg:classifiers":[
        {
            "category":"Shopping",
            "subcategory":"Computers & Home Electronics",
            "type":"Retail Goods"
        }
    ],
    "sg:phone":"+1 770 844 6330",
    "sg:postcode":"30041",
    "sg:province":"GA",
    "wof:name":"Debbies Little Dishes",
    "wof:placetype":"venue"
},
  "geometry": {"coordinates":[-84.061837,34.251714],"type":"Point"}
}