{
  "type": "Feature",
  "properties": {
    "addr:full":"435 Peachtree St NE Atlanta GA 30308",
    "addr:housenumber":"435",
    "addr:postcode":"30308",
    "addr:street":"Peachtree St Ne",
    "iso:country":"US",
    "sg:address":"435 Peachtree St NE",
    "sg:city":"Atlanta",
    "sg:classifiers":[
        {
            "category":"Organizations",
            "subcategory":"Community Association",
            "type":"Services"
        }
    ],
    "sg:phone":"+1 404 963 2313",
    "sg:postcode":"30308",
    "sg:province":"GA",
    "wof:name":"Stl",
    "wof:placetype":"venue"
},
  "geometry": {"coordinates":[-84.385411,33.766563],"type":"Point"}
}