{
  "type": "Feature",
  "properties": {
    "iso:country":"US",
    "sg:address":"3495 Piedmont Road NE",
    "sg:city":"Atlanta",
    "sg:classifiers":[
        {
            "category":"Professional",
            "subcategory":"Accounting & Tax Preparation",
            "type":"Services"
        }
    ],
    "sg:phone":"+1 404 262 7920",
    "sg:postcode":"30305",
    "sg:province":"GA",
    "sg:tags":[
        "accountant"
    ],
    "wof:name":"Thornton Douglas D CPA",
    "wof:placetype":"venue"
},
  "geometry": {"coordinates":[-84.37752399999999,33.849907],"type":"Point"}
}