{
  "type": "Feature",
  "properties": {
    "iso:country":"US",
    "sg:address":"3837 Mercer University Dr",
    "sg:city":"Macon",
    "sg:classifiers":[
        {
            "category":"Restaurant",
            "type":"Food & Drink"
        }
    ],
    "sg:menulink":"http://www.allmenus.com/ga/macon/207174-sonic/menu/",
    "sg:phone":"+1 478 405 5510",
    "sg:postcode":"31204",
    "sg:province":"GA",
    "sg:tags":[
        "burger",
        "american"
    ],
    "wof:name":"Sonic",
    "wof:placetype":"venue"
},
  "geometry": {"coordinates":[-83.701554,32.823438],"type":"Point"}
}