{
  "type": "Feature",
  "properties": {
    "iso:country":"US",
    "sg:address":"1001 Garden View Dr NE # 129",
    "sg:city":"Atlanta",
    "sg:classifiers":[
        {
            "category":"Retail",
            "subcategory":"Laundry & Dry Cleaning",
            "type":"Services"
        }
    ],
    "sg:phone":"+1 202 329 7813",
    "sg:postcode":"30319",
    "sg:province":"GA",
    "sg:tags":[
        "cleaner",
        "commercial"
    ],
    "wof:name":"L Luv Heartbreaker",
    "wof:placetype":"venue"
},
  "geometry": {"coordinates":[-84.348821,33.850499],"type":"Point"}
}