{
  "type": "Feature",
  "properties": {
    "iso:country":"US",
    "sg:address":"50 Lower Alabama St SW",
    "sg:city":"Atlanta",
    "sg:classifiers":[
        {
            "category":"Shopping",
            "subcategory":"Crafts & Fabrics",
            "type":"Retail Goods"
        }
    ],
    "sg:phone":"+1 404 588 0889",
    "sg:postcode":"30303",
    "sg:province":"GA",
    "sg:tags":[
        "art",
        "supply"
    ],
    "wof:name":"Fashion Art",
    "wof:placetype":"venue"
},
  "geometry": {"coordinates":[-84.39099899999999,33.7533],"type":"Point"}
}