{
  "type": "Feature",
  "properties": {
    "addr:full":"230 Ladora Dr Dallas GA 30157",
    "addr:housenumber":"230",
    "addr:postcode":"30157",
    "addr:street":"Ladora Dr",
    "iso:country":"US",
    "sg:address":"230 Ladora Dr",
    "sg:city":"Dallas",
    "sg:classifiers":[
        {
            "category":"Building & Trades",
            "subcategory":"Electrical",
            "type":"Services"
        }
    ],
    "sg:phone":"+1 770 445 3625",
    "sg:postcode":"30157",
    "sg:province":"GA",
    "sg:tags":[
        "electrical",
        "contractor"
    ],
    "wof:name":"Ricks Comm Maintenance",
    "wof:placetype":"venue"
},
  "geometry": {"coordinates":[-84.85073800000001,33.850263],"type":"Point"}
}