{
  "type": "Feature",
  "properties": {
    "addr:full":"610 Potts Rd Newnan GA 30263",
    "addr:housenumber":"610",
    "addr:postcode":"30263",
    "addr:street":"Potts Rd",
    "iso:country":"US",
    "sg:address":"610 Potts Rd",
    "sg:city":"Newnan",
    "sg:classifiers":[
        {
            "category":"Building & Trades",
            "subcategory":"Construction",
            "type":"Services"
        }
    ],
    "sg:phone":"+1 770 251 6353",
    "sg:postcode":"30263",
    "sg:province":"GA",
    "sg:tags":[
        "pipe",
        "line",
        "contractor"
    ],
    "wof:name":"Paragon Pipeline",
    "wof:placetype":"venue"
},
  "geometry": {"coordinates":[-84.8002,33.32444],"type":"Point"}
}