{
  "type": "Feature",
  "properties": {
    "iso:country":"US",
    "sg:address":"5398 Atlanta Hwy",
    "sg:city":"Bogart",
    "sg:classifiers":[
        {
            "category":"Taxi",
            "type":"Transportation"
        }
    ],
    "sg:phone":"+1 770 725 2572",
    "sg:postcode":"30622",
    "sg:province":"GA",
    "sg:tags":[
        "taxicab"
    ],
    "wof:name":"Taxi Top ADS",
    "wof:placetype":"venue"
},
  "geometry": {"coordinates":[-83.516893,33.946382],"type":"Point"}
}