{
  "type": "Feature",
  "properties": {
    "iso:country":"US",
    "sg:address":"2300 Peachtree Rd NW Ste B201",
    "sg:city":"Atlanta",
    "sg:classifiers":[
        {
            "category":"Building & Trades",
            "subcategory":"Construction",
            "type":"Services"
        }
    ],
    "sg:phone":"+1 404 355 7600",
    "sg:postcode":"30309",
    "sg:province":"GA",
    "sg:tags":[
        "interior",
        "design"
    ],
    "sg:website":"www.huffdewberry.com",
    "wof:name":"Huff-Dewberry Llc",
    "wof:placetype":"venue"
},
  "geometry": {"coordinates":[-84.389301,33.817752],"type":"Point"}
}