{
  "type": "Feature",
  "properties": {
    "iso:country":"US",
    "sg:address":"6935 Commercial Dr",
    "sg:city":"Morrow",
    "sg:classifiers":[
        {
            "category":"Building & Trades",
            "subcategory":"Construction",
            "type":"Services"
        }
    ],
    "sg:phone":"+1 770 960 9025",
    "sg:postcode":"30260",
    "sg:province":"GA",
    "sg:tags":[
        "dry wall",
        "contractor"
    ],
    "wof:name":"BKP Inc",
    "wof:placetype":"venue"
},
  "geometry": {"coordinates":[-84.341515,33.564207],"type":"Point"}
}