{
  "type": "Feature",
  "properties": {
    "iso:country":"US",
    "sg:address":"1236 40th St",
    "sg:city":"Columbus",
    "sg:classifiers":[
        {
            "category":"Arts & Performance",
            "subcategory":"Theater",
            "type":"Entertainment"
        },
        {
            "category":"Professional",
            "subcategory":"Management & Consulting",
            "type":"Services"
        }
    ],
    "sg:phone":"+1 706 576 5768",
    "sg:postcode":"31904",
    "sg:province":"GA",
    "sg:tags":[
        "party",
        "planning",
        "group",
        "se"
    ],
    "sg:website":"www.clownin-around.com",
    "wof:name":"Clowning Around",
    "wof:placetype":"venue"
},
  "geometry": {"coordinates":[-84.973896,32.501865],"type":"Point"}
}