{
  "type": "Feature",
  "properties": {
    "addr:full":"819 E Jane St Valdosta GA 31601",
    "addr:housenumber":"819",
    "addr:postcode":"31601",
    "addr:street":"E Jane St",
    "iso:country":"US",
    "sg:address":"819 E Jane St",
    "sg:city":"Valdosta",
    "sg:classifiers":[
        {
            "category":"Health Services",
            "subcategory":"Clinic",
            "type":"Services"
        }
    ],
    "sg:phone":"+1 229 247 5747",
    "sg:postcode":"31601",
    "sg:province":"GA",
    "sg:tags":[
        "home",
        "care"
    ],
    "wof:name":"Rosa B Green",
    "wof:placetype":"venue"
},
  "geometry": {"coordinates":[-83.269296,30.845756],"type":"Point"}
}