{
  "type": "Feature",
  "properties": {
    "iso:country":"US",
    "sg:address":"3405 Creekwood Dr SE",
    "sg:city":"Conyers",
    "sg:classifiers":[
        {
            "category":"Freight",
            "type":"Transportation"
        }
    ],
    "sg:phone":"+1 770 918 5010",
    "sg:postcode":"30094",
    "sg:province":"GA",
    "wof:name":"Woodridge Transportation LLC",
    "wof:placetype":"venue"
},
  "geometry": {"coordinates":[-84.023754,33.598812],"type":"Point"}
}