{
  "type": "Feature",
  "properties": {
    "iso:country":"US",
    "sg:address":"246 Circle Dr",
    "sg:city":"Cornelia",
    "sg:classifiers":[
        {
            "category":"Place Of Worship",
            "subcategory":"Church",
            "type":"Public Place"
        },
        {
            "category":"Place Of Worship",
            "type":"Public Place"
        }
    ],
    "sg:phone":"+1 706 778 7642",
    "sg:postcode":"30531",
    "sg:province":"GA",
    "sg:tags":[
        "churches-baptist-general",
        "churches-baptist"
    ],
    "wof:name":"Northside Baptist Church",
    "wof:placetype":"venue"
},
  "geometry": {"coordinates":[-83.531066,34.520873],"type":"Point"}
}