{
  "type": "Feature",
  "properties": {
    "iso:country":"US",
    "sg:address":"109 Park of Commerce Dr",
    "sg:city":"Savannah",
    "sg:classifiers":[
        {
            "category":"Wholesale",
            "subcategory":"Office Equipment",
            "type":"Manufacturing & Wholesale Goods"
        }
    ],
    "sg:phone":"+1 912 234 5086",
    "sg:postcode":"31405",
    "sg:province":"GA",
    "sg:tags":[
        "machine",
        "industrial",
        "duplicating",
        "copying"
    ],
    "wof:name":"Lanier Worldwide Inc",
    "wof:placetype":"venue"
},
  "geometry": {"coordinates":[-81.16143599999999,32.063934],"type":"Point"}
}