{
  "type": "Feature",
  "properties": {
    "addr:full":"5507 Pond Mill Ct Flowery Branch GA 30542",
    "addr:housenumber":"5507",
    "addr:postcode":"30542",
    "addr:street":"Pond Mill Ct",
    "iso:country":"US",
    "sg:address":"5507 Pond Mill Ct",
    "sg:city":"Flowery Branch",
    "sg:classifiers":[
        {
            "category":"Building & Trades",
            "subcategory":"Cleaning & Sanitation",
            "type":"Services"
        }
    ],
    "sg:phone":"+1 770 965 6949",
    "sg:postcode":"30542",
    "sg:province":"GA",
    "sg:tags":[
        "maintenance"
    ],
    "wof:name":"Saras Cleaning Services",
    "wof:placetype":"venue"
},
  "geometry": {"coordinates":[-83.876367,34.149699],"type":"Point"}
}