{
  "type": "Feature",
  "properties": {
    "iso:country":"US",
    "sg:address":"801 N Madison Ave",
    "sg:city":"Douglas",
    "sg:classifiers":[
        {
            "category":"Shopping",
            "subcategory":"Used Merchandise",
            "type":"Retail Goods"
        },
        {
            "category":"Shopping",
            "subcategory":"Gifts & Souvenirs",
            "type":"Retail Goods"
        }
    ],
    "sg:phone":"+1 912 383 8803",
    "sg:postcode":"31533",
    "sg:province":"GA",
    "sg:tags":[
        "shop",
        "antique"
    ],
    "sg:website":"www.beckysgiftsonline.com",
    "wof:name":"Becky's Gifts & Antiques",
    "wof:placetype":"venue"
},
  "geometry": {"coordinates":[-82.849436,31.515661],"type":"Point"}
}