{
  "type": "Feature",
  "properties": {
    "addr:full":"208 3rd St Soperton GA 30457",
    "addr:housenumber":"208",
    "addr:postcode":"30457",
    "addr:street":"3Rd St",
    "iso:country":"US",
    "sg:address":"208 3rd St",
    "sg:city":"Soperton",
    "sg:classifiers":[
        {
            "category":"Utilities",
            "subcategory":"Telephone",
            "type":"Services"
        }
    ],
    "sg:phone":"+1 912 529 4436",
    "sg:postcode":"30457",
    "sg:province":"GA",
    "sg:tags":[
        "company"
    ],
    "sg:website":"www.planters.net",
    "wof:name":"Plant Telecommunications",
    "wof:placetype":"venue"
},
  "geometry": {"coordinates":[-82.595975,32.372161],"type":"Point"}
}