{
  "type": "Feature",
  "properties": {
    "iso:country":"US",
    "sg:address":"2802 Paces Ferry Rd SE",
    "sg:city":"Atlanta",
    "sg:classifiers":[
        {
            "category":"Real Estate",
            "subcategory":"Real Estate Services",
            "type":"Services"
        }
    ],
    "sg:phone":"+1 770 434 0100",
    "sg:postcode":"30339",
    "sg:province":"GA",
    "sg:tags":[
        "consultant",
        "commercial"
    ],
    "wof:name":"Kpk Commercial",
    "wof:placetype":"venue"
},
  "geometry": {"coordinates":[-84.47113,33.865669],"type":"Point"}
}