{
  "type": "Feature",
  "properties": {
    "addr:full":"1400 Lawrenceville Hwy NW Atlanta GA 30303",
    "addr:housenumber":"1400",
    "addr:postcode":"30303",
    "addr:street":"Lawrenceville Hwy Nw",
    "iso:country":"US",
    "sg:address":"1400 Lawrenceville Hwy NW",
    "sg:city":"Atlanta",
    "sg:classifiers":[
        {
            "category":"Shopping",
            "subcategory":"Department Store",
            "type":"Retail Goods"
        }
    ],
    "sg:phone":"+1 770 682 5804",
    "sg:postcode":"30303",
    "sg:province":"GA",
    "sg:website":"www.walmart.com",
    "wof:name":"Wal-Mart Supercenter",
    "wof:placetype":"venue"
},
  "geometry": {"coordinates":[-84.025212,33.936508],"type":"Point"}
}