{
  "type": "Feature",
  "properties": {
    "addr:full":"222 E Robert Toombs Ave Washington GA 30673",
    "addr:housenumber":"222",
    "addr:postcode":"30673",
    "addr:street":"E Robert Toombs Ave",
    "iso:country":"US",
    "sg:address":"222 E Robert Toombs Ave",
    "sg:city":"Washington",
    "sg:classifiers":[
        {
            "category":"Retail",
            "subcategory":"Laundry & Dry Cleaning",
            "type":"Services"
        }
    ],
    "sg:phone":"+1 706 678 2232",
    "sg:postcode":"30673",
    "sg:province":"GA",
    "sg:tags":[
        "drycleaning",
        "plant",
        "cleaners"
    ],
    "wof:name":"J & J Colonial Cleaners",
    "wof:placetype":"venue"
},
  "geometry": {"coordinates":[-82.73253200000001,33.736265],"type":"Point"}
}