{
  "type": "Feature",
  "properties": {
    "iso:country":"US",
    "sg:address":"2505 Chamblee Tucker Rd",
    "sg:city":"Chamblee",
    "sg:classifiers":[
        {
            "category":"Banks & Credit Unions",
            "subcategory":"Bank",
            "type":"Services"
        }
    ],
    "sg:phone":"+1 770 936 0884",
    "sg:postcode":"30341",
    "sg:province":"GA",
    "sg:tags":[
        "loan"
    ],
    "wof:name":"Global Funding Svc",
    "wof:placetype":"venue"
},
  "geometry": {"coordinates":[-84.287582,33.885607],"type":"Point"}
}