{
  "type": "Feature",
  "properties": {
    "addr:full":"6 Joshuas Retreat Savannah GA 31411",
    "addr:housenumber":"6",
    "addr:postcode":"31411",
    "addr:street":"Joshuas Retreat",
    "iso:country":"US",
    "sg:address":"6 Joshuas Retreat",
    "sg:city":"Savannah",
    "sg:classifiers":[
        {
            "category":"Professional",
            "subcategory":"Business Services",
            "type":"Services"
        }
    ],
    "sg:phone":"+1 912 598 1651",
    "sg:postcode":"31411",
    "sg:province":"GA",
    "wof:name":"J F Kempf and Associates Inc",
    "wof:placetype":"venue"
},
  "geometry": {"coordinates":[-81.034434,31.946409],"type":"Point"}
}