{
  "type": "Feature",
  "properties": {
    "addr:full":"4191 Pleasant Hill Rd Duluth GA 30096",
    "addr:housenumber":"4191",
    "addr:postcode":"30096",
    "addr:street":"Pleasant Hill Rd",
    "iso:country":"US",
    "sg:address":"4191 Pleasant Hill Rd",
    "sg:city":"Duluth",
    "sg:classifiers":[
        {
            "category":"Wholesale",
            "subcategory":"Electrical",
            "type":"Manufacturing & Wholesale Goods"
        }
    ],
    "sg:phone":"+1 770 813 7447",
    "sg:postcode":"30096",
    "sg:province":"GA",
    "sg:tags":[
        "electronic"
    ],
    "wof:name":"Heilind Electronics Inc",
    "wof:placetype":"venue"
},
  "geometry": {"coordinates":[-84.164793,34.002909],"type":"Point"}
}