{
  "type": "Feature",
  "properties": {
    "addr:full":"201 Acord Dr Sylvester GA 31791",
    "addr:housenumber":"201",
    "addr:postcode":"31791",
    "addr:street":"Acord Dr",
    "iso:country":"US",
    "sg:address":"201 Acord Dr",
    "sg:city":"Sylvester",
    "sg:classifiers":[
        {
            "category":"Animal Shelter",
            "type":"Public Place"
        },
        {
            "category":"Building & Trades",
            "subcategory":"Pest Control",
            "type":"Services"
        }
    ],
    "sg:phone":"+1 229 343 1503",
    "sg:postcode":"31791",
    "sg:province":"GA",
    "sg:tags":[
        "removal"
    ],
    "wof:name":"Beck's Wildlife Removal",
    "wof:placetype":"venue"
},
  "geometry": {"coordinates":[-83.960356,31.513572],"type":"Point"}
}