{
  "type": "Feature",
  "properties": {
    "addr:full":"859 D H Alderman Rd Moultrie GA 31788",
    "addr:housenumber":"859",
    "addr:postcode":"31788",
    "addr:street":"D H Alderman Rd",
    "iso:country":"US",
    "sg:address":"859 D H Alderman Rd",
    "sg:city":"Moultrie",
    "sg:phone":"+1 229 985 1563",
    "sg:postcode":"31788",
    "sg:province":"GA",
    "sg:tags":[
        "farm",
        "corn"
    ],
    "wof:name":"Guy Hart",
    "wof:placetype":"venue"
},
  "geometry": {"coordinates":[-83.64886199999999,31.193303],"type":"Point"}
}