{
  "type": "Feature",
  "properties": {
    "iso:country":"US",
    "sg:address":"55 Georgia Avenue SE",
    "sg:city":"Atlanta",
    "sg:classifiers":[
        {
            "category":"Restaurant",
            "type":"Food & Drink"
        }
    ],
    "sg:phone":"+1 404 221 0715",
    "sg:postcode":"30312",
    "sg:province":"GA",
    "sg:tags":[
        "asian",
        "chinese",
        "pan"
    ],
    "wof:name":"Fuwah Chinese Restaurant",
    "wof:placetype":"venue"
},
  "geometry": {"coordinates":[-84.38633799999999,33.736822],"type":"Point"}
}