{
  "type": "Feature",
  "properties": {
    "iso:country":"US",
    "sg:address":"2039 Tuxedo Ave NE",
    "sg:city":"Atlanta",
    "sg:classifiers":[
        {
            "category":"Professional",
            "subcategory":"Advertising",
            "type":"Services"
        }
    ],
    "sg:phone":"+1 404 371 4545",
    "sg:postcode":"30307",
    "sg:province":"GA",
    "sg:tags":[
        "agency"
    ],
    "wof:name":"Ad Express",
    "wof:placetype":"venue"
},
  "geometry": {"coordinates":[-84.319163,33.765947],"type":"Point"}
}