{
  "type": "Feature",
  "properties": {
    "addr:full":"412 23rd Ave W Cordele GA 31015",
    "addr:housenumber":"412",
    "addr:postcode":"31015",
    "addr:street":"23Rd Ave W",
    "iso:country":"US",
    "sg:address":"412 23rd Ave W",
    "sg:city":"Cordele",
    "sg:classifiers":[
        {
            "category":"Professional",
            "type":"Services"
        }
    ],
    "sg:phone":"+1 229 273 5681",
    "sg:postcode":"31015",
    "sg:province":"GA",
    "wof:name":"Carolyn Butts",
    "wof:placetype":"venue"
},
  "geometry": {"coordinates":[-83.786395,31.955909],"type":"Point"}
}