{
  "type": "Feature",
  "properties": {
    "addr:full":"5440 Oakbrook Pkwy Norcross GA 30093",
    "addr:housenumber":"5440",
    "addr:postcode":"30093",
    "addr:street":"Oakbrook Pkwy",
    "iso:country":"US",
    "sg:address":"5440 Oakbrook Pkwy",
    "sg:city":"Norcross",
    "sg:classifiers":[
        {
            "category":"Manufacturing",
            "subcategory":"Tools & Machinery",
            "type":"Manufacturing & Wholesale Goods"
        }
    ],
    "sg:phone":"+1 770 448 0250",
    "sg:postcode":"30093",
    "sg:province":"GA",
    "sg:tags":[
        "photo",
        "mfg",
        "d",
        "x"
    ],
    "wof:name":"Allied Dgnstc Imging Resources",
    "wof:placetype":"venue"
},
  "geometry": {"coordinates":[-84.175591,33.919976],"type":"Point"}
}