{
  "type": "Feature",
  "properties": {
    "iso:country":"US",
    "sg:address":"7840 Roswell Road Bldg 500",
    "sg:city":"Atlanta",
    "sg:classifiers":[
        {
            "category":"Banks & Credit Unions",
            "subcategory":"Bank",
            "type":"Services"
        },
        {
            "category":"Banks & Credit Unions",
            "subcategory":"Financial Services",
            "type":"Services"
        }
    ],
    "sg:phone":"+1 770 353 2400",
    "sg:postcode":"30350",
    "sg:province":"GA",
    "sg:tags":[
        "financing"
    ],
    "wof:name":"GE Capital",
    "wof:placetype":"venue"
},
  "geometry": {"coordinates":[-84.35957999999999,33.97041],"type":"Point"}
}