{
  "type": "Feature",
  "properties": {
    "iso:country":"US",
    "sg:address":"402 Hines Dr",
    "sg:city":"Hinesville",
    "sg:classifiers":[
        {
            "category":"Retail",
            "subcategory":"Laundry & Dry Cleaning",
            "type":"Services"
        }
    ],
    "sg:phone":"+1 912 876 6552",
    "sg:postcode":"31313",
    "sg:province":"GA",
    "sg:tags":[
        "cleaners",
        "rug",
        "carpet"
    ],
    "wof:name":"All Star Carpet Care",
    "wof:placetype":"venue"
},
  "geometry": {"coordinates":[-81.594196,31.820109],"type":"Point"}
}