{
  "type": "Feature",
  "properties": {
    "iso:country":"US",
    "sg:address":"7685 The Blfs",
    "sg:city":"Austell",
    "sg:classifiers":[
        {
            "category":"Freight",
            "type":"Transportation"
        }
    ],
    "sg:phone":"+1 770 739 1074",
    "sg:postcode":"30168",
    "sg:province":"GA",
    "sg:tags":[
        "operator",
        "trucking"
    ],
    "wof:name":"McArthur Express South Inc",
    "wof:placetype":"venue"
},
  "geometry": {"coordinates":[-84.561942,33.765817],"type":"Point"}
}