{
  "type": "Feature",
  "properties": {
    "iso:country":"US",
    "sg:address":"2301 Moody Rd",
    "sg:city":"Warner Robins",
    "sg:classifiers":[
        {
            "category":"Travel",
            "subcategory":"Campground",
            "type":"Entertainment"
        }
    ],
    "sg:phone":"+1 478 922 1145",
    "sg:postcode":"31088",
    "sg:province":"GA",
    "sg:tags":[
        "youth",
        "camp"
    ],
    "wof:name":"Camp Jubilee Inc",
    "wof:placetype":"venue"
},
  "geometry": {"coordinates":[-83.62278000000001,32.587178],"type":"Point"}
}