{
  "type": "Feature",
  "properties": {
    "addr:full":"1155 Cedar Shoals Dr Athens GA 30605",
    "addr:housenumber":"1155",
    "addr:postcode":"30605",
    "addr:street":"Cedar Shoals Dr",
    "iso:country":"US",
    "sg:address":"1155 Cedar Shoals Dr",
    "sg:city":"Athens",
    "sg:classifiers":[
        {
            "category":"Health Services",
            "subcategory":"Doctor",
            "type":"Services"
        }
    ],
    "sg:phone":"+1 706 546 8720",
    "sg:postcode":"30605",
    "sg:province":"GA",
    "wof:name":"Patrick J Benjamin DMD",
    "wof:placetype":"venue"
},
  "geometry": {"coordinates":[-83.334362,33.925942],"type":"Point"}
}