{
  "type": "Feature",
  "properties": {
    "addr:full":"1159 27th St Columbus GA 31904",
    "addr:housenumber":"1159",
    "addr:postcode":"31904",
    "addr:street":"27Th St",
    "iso:country":"US",
    "sg:address":"1159 27th St",
    "sg:city":"Columbus",
    "sg:classifiers":[
        {
            "category":"Personal",
            "subcategory":"Beauty Salon",
            "type":"Services"
        }
    ],
    "sg:phone":"+1 706 324 2209",
    "sg:postcode":"31904",
    "sg:province":"GA",
    "sg:tags":[
        "shop"
    ],
    "wof:name":"Jordan City Beauty Shop",
    "wof:placetype":"venue"
},
  "geometry": {"coordinates":[-84.97617200000001,32.486278],"type":"Point"}
}