{
  "type": "Feature",
  "properties": {
    "addr:full":"295 Woodland Ave Summerville GA 30747",
    "addr:housenumber":"295",
    "addr:postcode":"30747",
    "addr:street":"Woodland Ave",
    "iso:country":"US",
    "sg:address":"295 Woodland Ave",
    "sg:city":"Summerville",
    "sg:classifiers":[
        {
            "category":"Health Services",
            "subcategory":"Hospital",
            "type":"Services"
        }
    ],
    "sg:phone":"+1 706 857 1470",
    "sg:postcode":"30747",
    "sg:province":"GA",
    "sg:tags":[
        "mental"
    ],
    "wof:name":"Volunteers Of America",
    "wof:placetype":"venue"
},
  "geometry": {"coordinates":[-85.348169,34.489157],"type":"Point"}
}