{
  "type": "Feature",
  "properties": {
    "addr:full":"971 N Hairston Rd Stone Mountain GA 30083",
    "addr:housenumber":"971",
    "addr:postcode":"30083",
    "addr:street":"N Hairston Rd",
    "iso:country":"US",
    "sg:address":"971 N Hairston Rd",
    "sg:city":"Stone Mountain",
    "sg:classifiers":[
        {
            "category":"Restaurant",
            "type":"Food & Drink"
        }
    ],
    "sg:phone":"+1 770 498 3660",
    "sg:postcode":"30083",
    "sg:province":"GA",
    "wof:name":"Geraldine's Fish & Grits",
    "wof:placetype":"venue"
},
  "geometry": {"coordinates":[-84.19357599999999,33.801638],"type":"Point"}
}