{
  "type": "Feature",
  "properties": {
    "iso:country":"US",
    "sg:address":"3586 Old Milton Pkwy",
    "sg:city":"Alpharetta",
    "sg:classifiers":[
        {
            "category":"Professional",
            "subcategory":"Business Services",
            "type":"Services"
        }
    ],
    "sg:phone":"+1 770 619 4308",
    "sg:postcode":"30005",
    "sg:province":"GA",
    "sg:tags":[
        "inspection"
    ],
    "wof:name":"Stucco Inspections & Repairs",
    "wof:placetype":"venue"
},
  "geometry": {"coordinates":[-84.25737599999999,34.0665],"type":"Point"}
}