{
  "type": "Feature",
  "properties": {
    "iso:country":"US",
    "sg:address":"304 E Bay St",
    "sg:city":"Savannah",
    "sg:classifiers":[
        {
            "category":"Professional",
            "subcategory":"Lawyer & Legal Services",
            "type":"Services"
        }
    ],
    "sg:phone":"+1 912 231 1140",
    "sg:postcode":"31401",
    "sg:province":"GA",
    "sg:tags":[
        "attorney",
        "partnership",
        "negligence",
        "family",
        "divorce",
        "practice",
        "liability",
        "malpractice",
        "corporation",
        "law",
        "business"
    ],
    "sg:website":"http://www.savagelawfirm.net",
    "wof:name":"Karsman, Stanley M - Savage Turner Pinson & Karsman",
    "wof:placetype":"venue"
},
  "geometry": {"coordinates":[-81.087718,32.07997],"type":"Point"}
}