{
  "type": "Feature",
  "properties": {
    "iso:country":"US",
    "sg:address":"930 Mays Bridge Rd SW",
    "sg:city":"Rome",
    "sg:classifiers":[
        {
            "category":"Building & Trades",
            "subcategory":"Landscaping Services",
            "type":"Services"
        }
    ],
    "sg:phone":"+1 706 232 5092",
    "sg:postcode":"30165",
    "sg:province":"GA",
    "sg:tags":[
        "landscape"
    ],
    "wof:name":"R & C Tractor Service",
    "wof:placetype":"venue"
},
  "geometry": {"coordinates":[-85.310867,34.242776],"type":"Point"}
}