{
  "type": "Feature",
  "properties": {
    "iso:country":"US",
    "sg:address":"815 Milledgeville Hwy",
    "sg:city":"Sparta",
    "sg:classifiers":[
        {
            "category":"Home & Garden",
            "subcategory":"Building Materials",
            "type":"Retail Goods"
        }
    ],
    "sg:phone":"+1 706 444 5052",
    "sg:postcode":"31087",
    "sg:province":"GA",
    "wof:name":"Harris & Pound",
    "wof:placetype":"venue"
},
  "geometry": {"coordinates":[-83.057047,33.223952],"type":"Point"}
}