{
  "type": "Feature",
  "properties": {
    "iso:country":"US",
    "sg:address":"1498 Veterans Memorial Hwy SE",
    "sg:city":"Mableton",
    "sg:classifiers":[
        {
            "category":"Building & Trades",
            "subcategory":"Locksmith",
            "type":"Services"
        }
    ],
    "sg:phone":"+1 770 250 0448",
    "sg:postcode":"30126",
    "sg:province":"GA",
    "sg:tags":[
        "key"
    ],
    "wof:name":"A Locksmith A 1 24 Hour",
    "wof:placetype":"venue"
},
  "geometry": {"coordinates":[-84.510363,33.79664],"type":"Point"}
}