{
  "type": "Feature",
  "properties": {
    "addr:full":"5521 Whittondale Rd Lithonia GA 30058",
    "addr:housenumber":"5521",
    "addr:postcode":"30058",
    "addr:street":"Whittondale Rd",
    "iso:country":"US",
    "sg:address":"5521 Whittondale Rd",
    "sg:city":"Lithonia",
    "sg:classifiers":[
        {
            "category":"Building & Trades",
            "subcategory":"Cleaning & Sanitation",
            "type":"Services"
        }
    ],
    "sg:phone":"+1 770 808 1388",
    "sg:postcode":"30058",
    "sg:province":"GA",
    "sg:tags":[
        "janitorial"
    ],
    "wof:name":"T & T Company",
    "wof:placetype":"venue"
},
  "geometry": {"coordinates":[-84.16400400000001,33.743096],"type":"Point"}
}