{
  "type": "Feature",
  "properties": {
    "iso:country":"US",
    "sg:address":"1881 Chamblee Tucker Rd",
    "sg:city":"Chamblee",
    "sg:classifiers":[
        {
            "category":"Building & Trades",
            "subcategory":"Locksmith",
            "type":"Services"
        }
    ],
    "sg:phone":"+1 877 292 7871",
    "sg:postcode":"30341",
    "sg:province":"GA",
    "sg:tags":[
        "key"
    ],
    "wof:name":"1 & A Emergency Locksmith",
    "wof:placetype":"venue"
},
  "geometry": {"coordinates":[-84.309434,33.888173],"type":"Point"}
}