{
  "type": "Feature",
  "properties": {
    "iso:country":"US",
    "sg:address":"2572 Tyler Way",
    "sg:city":"Decatur",
    "sg:classifiers":[
        {
            "category":"Building & Trades",
            "subcategory":"Cleaning & Sanitation",
            "type":"Services"
        }
    ],
    "sg:phone":"+1 404 241 7399",
    "sg:postcode":"30032",
    "sg:province":"GA",
    "sg:tags":[
        "butlers'",
        "maids'",
        "maintenance"
    ],
    "wof:name":"Bettys Best Maid Svc",
    "wof:placetype":"venue"
},
  "geometry": {"coordinates":[-84.283691,33.723071],"type":"Point"}
}