{
  "type": "Feature",
  "properties": {
    "iso:country":"US",
    "sg:address":"1869 Sylvester Hwy",
    "sg:city":"Moultrie",
    "sg:classifiers":[
        {
            "category":"Autos & Motor Vehicles",
            "subcategory":"Fuel & Gas Station",
            "type":"Retail Goods"
        }
    ],
    "sg:phone":"+1 229 985 1799",
    "sg:postcode":"31768",
    "sg:province":"GA",
    "sg:tags":[
        "station",
        "gasoline"
    ],
    "wof:name":"Peacocks Auto Service",
    "wof:placetype":"venue"
},
  "geometry": {"coordinates":[-83.79040000000001,31.209238],"type":"Point"}
}