{
  "type": "Feature",
  "properties": {
    "addr:full":"3675 Crestwood Pkwy Duluth GA 30096",
    "addr:housenumber":"3675",
    "addr:postcode":"30096",
    "addr:street":"Crestwood Pkwy",
    "iso:country":"US",
    "sg:address":"3675 Crestwood Pkwy",
    "sg:city":"Duluth",
    "sg:classifiers":[
        {
            "category":"Shopping",
            "subcategory":"Computers & Home Electronics",
            "type":"Retail Goods"
        }
    ],
    "sg:phone":"+1 678 380 5080",
    "sg:postcode":"30096",
    "sg:province":"GA",
    "sg:tags":[
        "equipment",
        "electronic",
        "supply"
    ],
    "wof:name":"CSR Electronics",
    "wof:placetype":"venue"
},
  "geometry": {"coordinates":[-84.127937,33.946856],"type":"Point"}
}