{
  "type": "Feature",
  "properties": {
    "addr:full":"4920 Paulsen St Savannah GA 31405",
    "addr:housenumber":"4920",
    "addr:postcode":"31405",
    "addr:street":"Paulsen St",
    "iso:country":"US",
    "sg:address":"4920 Paulsen St",
    "sg:city":"Savannah",
    "sg:classifiers":[
        {
            "category":"Health Services",
            "subcategory":"Health Practitioner",
            "type":"Services"
        }
    ],
    "sg:phone":"+1 912 351 9944",
    "sg:postcode":"31405",
    "sg:province":"GA",
    "wof:name":"Center For Psychlgical Svcs PC",
    "wof:placetype":"venue"
},
  "geometry": {"coordinates":[-81.09599900000001,32.030139],"type":"Point"}
}