{
  "type": "Feature",
  "properties": {
    "addr:full":"253 Silvers Rd Chatsworth GA 30705",
    "addr:housenumber":"253",
    "addr:postcode":"30705",
    "addr:street":"Silvers Rd",
    "iso:country":"US",
    "sg:address":"253 Silvers Rd",
    "sg:city":"Chatsworth",
    "sg:classifiers":[
        {
            "category":"Home & Garden",
            "subcategory":"Carpets & Floor Coverings",
            "type":"Retail Goods"
        }
    ],
    "sg:phone":"+1 706 695 1750",
    "sg:postcode":"30705",
    "sg:province":"GA",
    "sg:tags":[
        "mat",
        "matting"
    ],
    "wof:name":"Cyrus Manufacturing Inc",
    "wof:placetype":"venue"
},
  "geometry": {"coordinates":[-84.73672500000001,34.709203],"type":"Point"}
}