{
  "type": "Feature",
  "properties": {
    "addr:full":"1910 Highway 20 SE Conyers GA 30013",
    "addr:housenumber":"1910",
    "addr:postcode":"30013",
    "addr:street":"Highway 20 Se",
    "iso:country":"US",
    "sg:address":"1910 Highway 20 SE",
    "sg:city":"Conyers",
    "sg:classifiers":[
        {
            "category":"Personal",
            "subcategory":"Nail Salon",
            "type":"Services"
        }
    ],
    "sg:phone":"+1 770 860 1843",
    "sg:postcode":"30013",
    "sg:province":"GA",
    "wof:name":"Cindy's Nails",
    "wof:placetype":"venue"
},
  "geometry": {"coordinates":[-84.014397,33.633202],"type":"Point"}
}