{
  "type": "Feature",
  "properties": {
    "iso:country":"US",
    "sg:address":"1784 Century Blvd NE",
    "sg:city":"Atlanta",
    "sg:classifiers":[
        {
            "category":"Health Services",
            "subcategory":"Health Practitioner",
            "type":"Services"
        }
    ],
    "sg:phone":"+1 404 320 3355",
    "sg:postcode":"30345",
    "sg:province":"GA",
    "sg:tags":[
        "psychotherapist"
    ],
    "wof:name":"Otherwise Management Cnsltng",
    "wof:placetype":"venue"
},
  "geometry": {"coordinates":[-84.314975,33.8455],"type":"Point"}
}