{
  "type": "Feature",
  "properties": {
    "addr:full":"971 N Hairston Rd Ste 2 Stone Mountain GA 30083",
    "addr:housenumber":"971",
    "addr:postcode":"30083",
    "addr:street":"N Hairston Rd Ste 2",
    "iso:country":"US",
    "sg:address":"971 N Hairston Rd Ste 2",
    "sg:city":"Stone Mountain",
    "sg:classifiers":[
        {
            "category":"Shopping",
            "subcategory":"Bicycles & Sporting Goods",
            "type":"Retail Goods"
        }
    ],
    "sg:phone":"+1 770 469 9940",
    "sg:postcode":"30083",
    "sg:province":"GA",
    "wof:name":"Startime Soccer & Sports",
    "wof:placetype":"venue"
},
  "geometry": {"coordinates":[-84.193425,33.8055],"type":"Point"}
}