{
  "type": "Feature",
  "properties": {
    "iso:country":"US",
    "sg:address":"1426 Monte Sano Ave",
    "sg:city":"Augusta",
    "sg:classifiers":[
        {
            "category":"Manufacturing",
            "subcategory":"Printing",
            "type":"Manufacturing & Wholesale Goods"
        }
    ],
    "sg:phone":"+1 706 738 9368",
    "sg:postcode":"30904",
    "sg:province":"GA",
    "sg:tags":[
        "periodical"
    ],
    "wof:name":"Cable Video Magazine",
    "wof:placetype":"venue"
},
  "geometry": {"coordinates":[-82.027984,33.471451],"type":"Point"}
}