{
  "type": "Feature",
  "properties": {
    "addr:full":"1990 Lakeside Pkwy Tucker GA 30084",
    "addr:housenumber":"1990",
    "addr:postcode":"30084",
    "addr:street":"Lakeside Pkwy",
    "iso:country":"US",
    "sg:address":"1990 Lakeside Pkwy",
    "sg:city":"Tucker",
    "sg:classifiers":[
        {
            "category":"Professional",
            "subcategory":"Management & Consulting",
            "type":"Services"
        }
    ],
    "sg:phone":"+1 770 621 7600",
    "sg:postcode":"30084",
    "sg:province":"GA",
    "sg:tags":[
        "nonphysical",
        "r",
        "commercial"
    ],
    "wof:name":"Nelson Taylor Sofres",
    "wof:placetype":"venue"
},
  "geometry": {"coordinates":[-84.23965,33.838878],"type":"Point"}
}