{
  "type": "Feature",
  "properties": {
    "iso:country":"US",
    "sg:address":"301 Denmark St",
    "sg:city":"Statesboro",
    "sg:classifiers":[
        {
            "category":"Building & Trades",
            "subcategory":"Construction",
            "type":"Services"
        }
    ],
    "sg:phone":"+1 912 489 5230",
    "sg:postcode":"30458",
    "sg:province":"GA",
    "sg:tags":[
        "contractor"
    ],
    "wof:name":"Under One Roof",
    "wof:placetype":"venue"
},
  "geometry": {"coordinates":[-81.79437799999999,32.44983],"type":"Point"}
}