{
  "type": "Feature",
  "properties": {
    "addr:full":"113 Acacia Ct Leesburg GA 31763",
    "addr:housenumber":"113",
    "addr:postcode":"31763",
    "addr:street":"Acacia Ct",
    "iso:country":"US",
    "sg:address":"113 Acacia Ct",
    "sg:city":"Leesburg",
    "sg:classifiers":[
        {
            "category":"Food & Beverages",
            "subcategory":"Specialty",
            "type":"Retail Goods"
        }
    ],
    "sg:phone":"+1 229 432 5818",
    "sg:postcode":"31763",
    "sg:province":"GA",
    "sg:tags":[
        "health",
        "diet"
    ],
    "wof:name":"Herbalife Distributor",
    "wof:placetype":"venue"
},
  "geometry": {"coordinates":[-84.173073,31.636926],"type":"Point"}
}