{
  "type": "Feature",
  "properties": {
    "iso:country":"US",
    "sg:address":"3245 US Hwy 82 W",
    "sg:city":"Sylvester",
    "sg:classifiers":[
        {
            "category":"Organizations",
            "subcategory":"Religious Organization",
            "type":"Services"
        }
    ],
    "sg:phone":"+1 229 777 0230",
    "sg:postcode":"31791",
    "sg:province":"GA",
    "sg:tags":[
        "church"
    ],
    "wof:name":"Sanctuary Of Praise Church",
    "wof:placetype":"venue"
},
  "geometry": {"coordinates":[-83.908298,31.550489],"type":"Point"}
}