{
  "type": "Feature",
  "properties": {
    "addr:full":"2404 Chateau Ct Lithia Springs GA 30122",
    "addr:housenumber":"2404",
    "addr:postcode":"30122",
    "addr:street":"Chateau Ct",
    "iso:country":"US",
    "sg:address":"2404 Chateau Ct",
    "sg:city":"Lithia Springs",
    "sg:classifiers":[
        {
            "category":"Shopping",
            "subcategory":"Used Merchandise",
            "type":"Retail Goods"
        }
    ],
    "sg:phone":"+1 770 941 9454",
    "sg:postcode":"30122",
    "sg:province":"GA",
    "wof:name":"Fancies & Wimsies",
    "wof:placetype":"venue"
},
  "geometry": {"coordinates":[-84.653966,33.751835],"type":"Point"}
}