{
  "type": "Feature",
  "properties": {
    "addr:full":"3080 E Shadowlawn Ave NE Atlanta GA 30305",
    "addr:housenumber":"3080",
    "addr:postcode":"30305",
    "addr:street":"E Shadowlawn Ave Ne",
    "iso:country":"US",
    "sg:address":"3080 E Shadowlawn Ave NE",
    "sg:city":"Atlanta",
    "sg:classifiers":[
        {
            "category":"Arts & Performance",
            "subcategory":"Arts Center",
            "type":"Entertainment"
        }
    ],
    "sg:phone":"+1 404 364 9555",
    "sg:postcode":"30305",
    "sg:province":"GA",
    "sg:tags":[
        "performing"
    ],
    "wof:name":"Lee Harper Studios",
    "wof:placetype":"venue"
},
  "geometry": {"coordinates":[-84.373901,33.8391],"type":"Point"}
}