{
  "type": "Feature",
  "properties": {
    "addr:full":"308 E Main St Claxton GA 30417",
    "addr:housenumber":"308",
    "addr:postcode":"30417",
    "addr:street":"E Main St",
    "iso:country":"US",
    "sg:address":"308 E Main St",
    "sg:city":"Claxton",
    "sg:classifiers":[
        {
            "category":"Professional",
            "subcategory":"Lawyer & Legal Services",
            "type":"Services"
        }
    ],
    "sg:phone":"+1 912 739 3595",
    "sg:postcode":"30417",
    "sg:province":"GA",
    "sg:tags":[
        "attorney"
    ],
    "wof:name":"Hal T Peel PC",
    "wof:placetype":"venue"
},
  "geometry": {"coordinates":[-81.89967,32.161402],"type":"Point"}
}