{
  "type": "Feature",
  "properties": {
    "addr:full":"2354 Holcomb Bridge Rd Roswell GA 30076",
    "addr:housenumber":"2354",
    "addr:postcode":"30076",
    "addr:street":"Holcomb Bridge Rd",
    "iso:country":"US",
    "sg:address":"2354 Holcomb Bridge Rd",
    "sg:city":"Roswell",
    "sg:classifiers":[
        {
            "category":"Personal",
            "subcategory":"Beauty Salon",
            "type":"Services"
        }
    ],
    "sg:phone":"+1 770 640 3868",
    "sg:postcode":"30076",
    "sg:province":"GA",
    "sg:tags":[
        "shop"
    ],
    "wof:name":"Sport Clips",
    "wof:placetype":"venue"
},
  "geometry": {"coordinates":[-84.291365,34.003083],"type":"Point"}
}