{
  "type": "Feature",
  "properties": {
    "iso:country":"US",
    "sg:address":"5520 Carriage Walk Way",
    "sg:city":"Stone Mountain",
    "sg:classifiers":[
        {
            "category":"Professional",
            "type":"Services"
        }
    ],
    "sg:phone":"+1 770 465 3000",
    "sg:postcode":"30087",
    "sg:province":"GA",
    "wof:name":"Global Project Evaluators",
    "wof:placetype":"venue"
},
  "geometry": {"coordinates":[-84.16318800000001,33.79068],"type":"Point"}
}