{
  "type": "Feature",
  "properties": {
    "addr:full":"124 S Houston Lake Rd Warner Robins GA 31088",
    "addr:housenumber":"124",
    "addr:postcode":"31088",
    "addr:street":"S Houston Lake Rd",
    "iso:country":"US",
    "sg:address":"124 S Houston Lake Rd",
    "sg:city":"Warner Robins",
    "sg:classifiers":[
        {
            "category":"Retail",
            "subcategory":"Auto Repair",
            "type":"Services"
        }
    ],
    "sg:phone":"+1 478 953 2884",
    "sg:postcode":"31088",
    "sg:province":"GA",
    "wof:name":"Express Oil Change",
    "wof:placetype":"venue"
},
  "geometry": {"coordinates":[-83.68173400000001,32.616638],"type":"Point"}
}