{
  "type": "Feature",
  "properties": {
    "iso:country":"US",
    "sg:address":"6199 Hwy 278 NE",
    "sg:city":"Covington",
    "sg:classifiers":[
        {
            "category":"Shopping",
            "subcategory":"Jewelry",
            "type":"Retail Goods"
        }
    ],
    "sg:phone":"+1 770 786 0878",
    "sg:postcode":"30014",
    "sg:province":"GA",
    "sg:tags":[
        "jeweler"
    ],
    "wof:name":"Direct Gold Outlet Inc",
    "wof:placetype":"venue"
},
  "geometry": {"coordinates":[-83.842581,33.602222],"type":"Point"}
}