{
  "type": "Feature",
  "properties": {
    "iso:country":"US",
    "sg:address":"2130 Silver Cir",
    "sg:city":"Gainesville",
    "sg:classifiers":[
        {
            "category":"Professional",
            "type":"Services"
        }
    ],
    "sg:phone":"+1 770 534 1293",
    "sg:postcode":"30501",
    "sg:province":"GA",
    "wof:name":"Thomas A Corbin",
    "wof:placetype":"venue"
},
  "geometry": {"coordinates":[-83.817556,34.347709],"type":"Point"}
}