{
  "type": "Feature",
  "properties": {
    "addr:full":"115 E 11th St Waynesboro GA 30830",
    "addr:housenumber":"115",
    "addr:postcode":"30830",
    "addr:street":"E 11Th St",
    "iso:country":"US",
    "sg:address":"115 E 11th St",
    "sg:city":"Waynesboro",
    "sg:classifiers":[
        {
            "category":"Health Services",
            "subcategory":"Nursing And Care Facility",
            "type":"Services"
        }
    ],
    "sg:phone":"+1 706 554 3652",
    "sg:postcode":"30830",
    "sg:province":"GA",
    "sg:tags":[
        "personal",
        "home",
        "intermediate"
    ],
    "wof:name":"Setzer's Personal Care Home",
    "wof:placetype":"venue"
},
  "geometry": {"coordinates":[-82.019097,33.099217],"type":"Point"}
}