{
  "type": "Feature",
  "properties": {
    "addr:full":"2766 Holly Springs Pkwy Canton GA 30115",
    "addr:housenumber":"2766",
    "addr:postcode":"30115",
    "addr:street":"Holly Springs Pkwy",
    "iso:country":"US",
    "sg:address":"2766 Holly Springs Pkwy",
    "sg:city":"Canton",
    "sg:classifiers":[
        {
            "category":"Banks & Credit Unions",
            "subcategory":"Bank",
            "type":"Services"
        }
    ],
    "sg:phone":"+1 770 345 8004",
    "sg:postcode":"30115",
    "sg:province":"GA",
    "wof:name":"State Farm Insurance",
    "wof:placetype":"venue"
},
  "geometry": {"coordinates":[-84.50140399999999,34.174],"type":"Point"}
}