{
  "type": "Feature",
  "properties": {
    "iso:country":"US",
    "sg:address":"2510 Bouldercrest Road SE",
    "sg:city":"Atlanta",
    "sg:classifiers":[
        {
            "category":"Food & Beverages",
            "subcategory":"Groceries & Convenience Stores",
            "type":"Retail Goods"
        }
    ],
    "sg:phone":"+1 404 244 1791",
    "sg:postcode":"30316",
    "sg:province":"GA",
    "wof:name":"Amoco Food Shop",
    "wof:placetype":"venue"
},
  "geometry": {"coordinates":[-84.31097,33.688035],"type":"Point"}
}