{
  "type": "Feature",
  "properties": {
    "addr:full":"3412 Pierce Dr Atlanta GA 30341",
    "addr:housenumber":"3412",
    "addr:postcode":"30341",
    "addr:street":"Pierce Dr",
    "iso:country":"US",
    "sg:address":"3412 Pierce Dr",
    "sg:city":"Atlanta",
    "sg:classifiers":[
        {
            "category":"Shopping",
            "subcategory":"Catalog Store",
            "type":"Retail Goods"
        }
    ],
    "sg:phone":"+1 770 455 1800",
    "sg:postcode":"30341",
    "sg:province":"GA",
    "sg:tags":[
        "mail",
        "order"
    ],
    "wof:name":"Peachtree Circle Bridal Gifts",
    "wof:placetype":"venue"
},
  "geometry": {"coordinates":[-84.305567,33.893504],"type":"Point"}
}