{
  "type": "Feature",
  "properties": {
    "iso:country":"US",
    "sg:address":"126 Mount Olive Church Rd",
    "sg:city":"Moultrie",
    "sg:classifiers":[
        {
            "category":"Organizations",
            "subcategory":"Religious Organization",
            "type":"Services"
        }
    ],
    "sg:phone":"+1 229 985 4994",
    "sg:postcode":"31788",
    "sg:province":"GA",
    "sg:tags":[
        "church"
    ],
    "wof:name":"Mount Olive Baptist Church",
    "wof:placetype":"venue"
},
  "geometry": {"coordinates":[-83.72867100000001,31.18893],"type":"Point"}
}