{
  "type": "Feature",
  "properties": {
    "addr:full":"9464 Main St Woodstock GA 30188",
    "addr:housenumber":"9464",
    "addr:postcode":"30188",
    "addr:street":"Main St",
    "iso:country":"US",
    "sg:address":"9464 Main St",
    "sg:city":"Woodstock",
    "sg:classifiers":[
        {
            "category":"Shopping",
            "subcategory":"Department Store",
            "type":"Retail Goods"
        }
    ],
    "sg:phone":"+1 770 516 4719",
    "sg:postcode":"30188",
    "sg:province":"GA",
    "wof:name":"Wal-Mart",
    "wof:placetype":"venue"
},
  "geometry": {"coordinates":[-84.519549,34.087995],"type":"Point"}
}