{
  "type": "Feature",
  "properties": {
    "iso:country":"US",
    "sg:address":"1400 Pope Dr",
    "sg:city":"Douglas",
    "sg:classifiers":[
        {
            "category":"Manufacturing",
            "subcategory":"Aerospace",
            "type":"Manufacturing & Wholesale Goods"
        }
    ],
    "sg:phone":"+1 912 384 6633",
    "sg:postcode":"31535",
    "sg:province":"GA",
    "sg:tags":[
        "aircraft",
        "component"
    ],
    "wof:name":"Precision Castparts Corp",
    "wof:placetype":"venue"
},
  "geometry": {"coordinates":[-82.864733,31.490608],"type":"Point"}
}