{
  "type": "Feature",
  "properties": {
    "iso:country":"US",
    "sg:address":"11350 Woodstock Rd",
    "sg:city":"Roswell",
    "sg:classifiers":[
        {
            "category":"Building & Trades",
            "subcategory":"Electrical",
            "type":"Services"
        }
    ],
    "sg:phone":"+1 770 998 0450",
    "sg:postcode":"30075",
    "sg:province":"GA",
    "sg:tags":[
        "electrical",
        "contractor"
    ],
    "wof:name":"Inglett & Stubbs",
    "wof:placetype":"venue"
},
  "geometry": {"coordinates":[-84.383555,34.058156],"type":"Point"}
}