{
  "type": "Feature",
  "properties": {
    "addr:full":"1929 Dawson Rd Albany GA 31707",
    "addr:housenumber":"1929",
    "addr:postcode":"31707",
    "addr:street":"Dawson Rd",
    "iso:country":"US",
    "sg:address":"1929 Dawson Rd",
    "sg:city":"Albany",
    "sg:classifiers":[
        {
            "category":"Retail",
            "subcategory":"Repair Shop",
            "type":"Services"
        }
    ],
    "sg:phone":"+1 229 435 7233",
    "sg:postcode":"31707",
    "sg:province":"GA",
    "sg:tags":[
        "equipment"
    ],
    "wof:name":"A-1 Lock & Key Inc",
    "wof:placetype":"venue"
},
  "geometry": {"coordinates":[-84.196298,31.596435],"type":"Point"}
}