{
  "type": "Feature",
  "properties": {
    "iso:country":"US",
    "sg:address":"1419 Veterans Memorial Pkwy SW",
    "sg:city":"Mableton",
    "sg:classifiers":[
        {
            "category":"Food & Beverages",
            "subcategory":"Bakery",
            "type":"Retail Goods"
        }
    ],
    "sg:phone":"+1 678 360 5022",
    "sg:postcode":"30126",
    "sg:province":"GA",
    "sg:tags":[
        "baker"
    ],
    "wof:name":"Christians Bakery Inc",
    "wof:placetype":"venue"
},
  "geometry": {"coordinates":[-84.59502500000001,33.815173],"type":"Point"}
}