{
  "type": "Feature",
  "properties": {
    "iso:country":"US",
    "sg:address":"114 Lyerly St",
    "sg:city":"Summerville",
    "sg:classifiers":[
        {
            "category":"Restaurant",
            "type":"Food & Drink"
        }
    ],
    "sg:menulink":"http://www.allmenus.com/ga/summerville/101735-huddle-house/menu/",
    "sg:phone":"+1 706 857 6858",
    "sg:postcode":"30747",
    "sg:province":"GA",
    "sg:tags":[
        "american",
        "diner"
    ],
    "wof:name":"Huddle House",
    "wof:placetype":"venue"
},
  "geometry": {"coordinates":[-85.357964,34.471541],"type":"Point"}
}