{
  "type": "Feature",
  "properties": {
    "iso:country":"US",
    "sg:address":"112 Park West Dr",
    "sg:city":"Mcdonough",
    "sg:classifiers":[
        {
            "category":"Social Services",
            "type":"Services"
        }
    ],
    "sg:phone":"+1 770 320 8200",
    "sg:postcode":"30253",
    "sg:province":"GA",
    "sg:tags":[
        "food",
        "banks"
    ],
    "wof:name":"Southern Crescent Resource",
    "wof:placetype":"venue"
},
  "geometry": {"coordinates":[-84.164681,33.423415],"type":"Point"}
}