{
  "type": "Feature",
  "properties": {
    "addr:full":"1816 Midtown Dr Columbus GA 31906",
    "addr:housenumber":"1816",
    "addr:postcode":"31906",
    "addr:street":"Midtown Dr",
    "iso:country":"US",
    "sg:address":"1816 Midtown Dr",
    "sg:city":"Columbus",
    "sg:classifiers":[
        {
            "category":"Personal",
            "subcategory":"Beauty Salon",
            "type":"Services"
        }
    ],
    "sg:phone":"+1 706 563 7885",
    "sg:postcode":"31906",
    "sg:province":"GA",
    "wof:name":"Life Styles Hair Studio",
    "wof:placetype":"venue"
},
  "geometry": {"coordinates":[-84.941193,32.477913],"type":"Point"}
}