{
  "type": "Feature",
  "properties": {
    "addr:full":"3335 Golfe Links Dr Snellville GA 30039",
    "addr:housenumber":"3335",
    "addr:postcode":"30039",
    "addr:street":"Golfe Links Dr",
    "iso:country":"US",
    "sg:address":"3335 Golfe Links Dr",
    "sg:city":"Snellville",
    "sg:classifiers":[
        {
            "category":"Building & Trades",
            "subcategory":"Construction",
            "type":"Services"
        }
    ],
    "sg:phone":"+1 770 978 1878",
    "sg:postcode":"30039",
    "sg:province":"GA",
    "sg:tags":[
        "interior",
        "design"
    ],
    "wof:name":"Walter's Design Associates",
    "wof:placetype":"venue"
},
  "geometry": {"coordinates":[-84.025803,33.819302],"type":"Point"}
}