{
  "type": "Feature",
  "properties": {
    "addr:full":"215 Dromedary St Woodbury GA 30293",
    "addr:housenumber":"215",
    "addr:postcode":"30293",
    "addr:street":"Dromedary St",
    "iso:country":"US",
    "sg:address":"215 Dromedary St",
    "sg:city":"Woodbury",
    "sg:classifiers":[
        {
            "category":"Professional",
            "subcategory":"Accounting & Tax Preparation",
            "type":"Services"
        }
    ],
    "sg:phone":"+1 706 553 9584",
    "sg:postcode":"30293",
    "sg:province":"GA",
    "sg:tags":[
        "return",
        "filing"
    ],
    "wof:name":"D & M Income Tax Svc",
    "wof:placetype":"venue"
},
  "geometry": {"coordinates":[-84.58265400000001,32.981749],"type":"Point"}
}