{
  "type": "Feature",
  "properties": {
    "addr:full":"510 Ashley St W Douglas GA 31533",
    "addr:housenumber":"510",
    "addr:postcode":"31533",
    "addr:street":"Ashley St W",
    "iso:country":"US",
    "sg:address":"510 Ashley St W",
    "sg:city":"Douglas",
    "sg:classifiers":[
        {
            "category":"Food & Beverages",
            "subcategory":"Specialty",
            "type":"Retail Goods"
        }
    ],
    "sg:phone":"+1 912 389 1662",
    "sg:postcode":"31533",
    "sg:province":"GA",
    "sg:tags":[
        "product",
        "health",
        "diet"
    ],
    "wof:name":"Diet Centers",
    "wof:placetype":"venue"
},
  "geometry": {"coordinates":[-82.856903,31.508354],"type":"Point"}
}