{
  "type": "Feature",
  "properties": {
    "addr:full":"116 Commerce Ave Lagrange GA 30241",
    "addr:housenumber":"116",
    "addr:postcode":"30241",
    "addr:street":"Commerce Ave",
    "iso:country":"US",
    "sg:address":"116 Commerce Ave",
    "sg:city":"Lagrange",
    "sg:classifiers":[
        {
            "category":"Restaurant",
            "type":"Food & Drink"
        }
    ],
    "sg:menulink":"http://www.allmenus.com/ga/lagrange/179899-chick-fil-a/menu/",
    "sg:phone":"+1 706 812 9210",
    "sg:postcode":"30241",
    "sg:province":"GA",
    "sg:tags":[
        "wrap",
        "soup",
        "american",
        "sandwich",
        "salad"
    ],
    "wof:name":"Chick-fil-A",
    "wof:placetype":"venue"
},
  "geometry": {"coordinates":[-85.028205,33.049345],"type":"Point"}
}