{
  "type": "Feature",
  "properties": {
    "iso:country":"US",
    "sg:address":"28107 Plantation Dr NE",
    "sg:city":"Atlanta",
    "sg:classifiers":[
        {
            "category":"Shopping",
            "subcategory":"Mobile Phones",
            "type":"Retail Goods"
        },
        {
            "category":"Shopping",
            "subcategory":"Computers & Home Electronics",
            "type":"Retail Goods"
        },
        {
            "category":"Wholesale",
            "subcategory":"Computers",
            "type":"Manufacturing & Wholesale Goods"
        }
    ],
    "sg:phone":"+1 404 467 4508",
    "sg:postcode":"30324",
    "sg:province":"GA",
    "sg:website":"www.rentcell.com",
    "wof:name":"Rentcell",
    "wof:placetype":"venue"
},
  "geometry": {"coordinates":[-84.356189,33.835269],"type":"Point"}
}