{
  "type": "Feature",
  "properties": {
    "iso:country":"US",
    "sg:address":"65 Rainbow Dr",
    "sg:city":"Woodbine",
    "sg:classifiers":[
        {
            "category":"Building & Trades",
            "subcategory":"Equipment Rental",
            "type":"Services"
        }
    ],
    "sg:phone":"+1 912 729 7953",
    "sg:postcode":"31545",
    "sg:province":"GA",
    "sg:tags":[
        "yard"
    ],
    "wof:name":"Romparoom Bounce House Rentals",
    "wof:placetype":"venue"
},
  "geometry": {"coordinates":[-81.900098,31.635336],"type":"Point"}
}