{
  "type": "Feature",
  "properties": {
    "addr:full":"1332 Oakwoods Dr Woodstock GA 30188",
    "addr:housenumber":"1332",
    "addr:postcode":"30188",
    "addr:street":"Oakwoods Dr",
    "iso:country":"US",
    "sg:address":"1332 Oakwoods Dr",
    "sg:city":"Woodstock",
    "sg:classifiers":[
        {
            "category":"Travel",
            "subcategory":"Travel Agent",
            "type":"Entertainment"
        }
    ],
    "sg:phone":"+1 770 928 2392",
    "sg:postcode":"30188",
    "sg:province":"GA",
    "sg:tags":[
        "agency"
    ],
    "wof:name":"Uniglobe All Points Travel",
    "wof:placetype":"venue"
},
  "geometry": {"coordinates":[-84.51200799999999,34.075897],"type":"Point"}
}