{
  "type": "Feature",
  "properties": {
    "addr:full":"211 W Gordon Ave Rossville GA 30741",
    "addr:housenumber":"211",
    "addr:postcode":"30741",
    "addr:street":"W Gordon Ave",
    "iso:country":"US",
    "sg:address":"211 W Gordon Ave",
    "sg:city":"Rossville",
    "sg:classifiers":[
        {
            "category":"Building & Trades",
            "subcategory":"Plumbing",
            "type":"Services"
        }
    ],
    "sg:phone":"+1 706 937 2120",
    "sg:postcode":"30741",
    "sg:province":"GA",
    "sg:tags":[
        "conditioning",
        "air",
        "system",
        "contractor"
    ],
    "wof:name":"TAC Mechanical Inc",
    "wof:placetype":"venue"
},
  "geometry": {"coordinates":[-85.289682,34.984143],"type":"Point"}
}