{
  "type": "Feature",
  "properties": {
    "addr:full":"360 W Main St Canton GA 30114",
    "addr:housenumber":"360",
    "addr:postcode":"30114",
    "addr:street":"W Main St",
    "iso:country":"US",
    "sg:address":"360 W Main St",
    "sg:city":"Canton",
    "sg:classifiers":[
        {
            "category":"Professional",
            "type":"Services"
        }
    ],
    "sg:phone":"+1 678 493 8432",
    "sg:postcode":"30114",
    "sg:province":"GA",
    "wof:name":"Robin Butler",
    "wof:placetype":"venue"
},
  "geometry": {"coordinates":[-84.494381,34.23718],"type":"Point"}
}