{
  "type": "Feature",
  "properties": {
    "iso:country":"US",
    "sg:address":"1387 Springdale Rd NE",
    "sg:city":"Atlanta",
    "sg:classifiers":[
        {
            "category":"Building & Trades",
            "subcategory":"Landscaping Services",
            "type":"Services"
        }
    ],
    "sg:phone":"+1 770 873 5522",
    "sg:postcode":"30306",
    "sg:province":"GA",
    "sg:tags":[
        "lawn",
        "maintenance",
        "grounds"
    ],
    "wof:name":"Atlanta Lawn & Small Tree Svc",
    "wof:placetype":"venue"
},
  "geometry": {"coordinates":[-84.33420700000001,33.791367],"type":"Point"}
}