{
  "type": "Feature",
  "properties": {
    "addr:full":"611 Village Lake Dr Waycross GA 31503",
    "addr:housenumber":"611",
    "addr:postcode":"31503",
    "addr:street":"Village Lake Dr",
    "iso:country":"US",
    "sg:address":"611 Village Lake Dr",
    "sg:city":"Waycross",
    "sg:classifiers":[
        {
            "category":"Organizations",
            "subcategory":"Religious Organization",
            "type":"Services"
        }
    ],
    "sg:phone":"+1 912 287 0088",
    "sg:postcode":"31503",
    "sg:province":"GA",
    "wof:name":"Executive Committee Baptist Co",
    "wof:placetype":"venue"
},
  "geometry": {"coordinates":[-82.406997,31.214597],"type":"Point"}
}