{
  "type": "Feature",
  "properties": {
    "addr:full":"117 Folsom Rd Tallapoosa GA 30113",
    "addr:housenumber":"117",
    "addr:postcode":"30113",
    "addr:street":"Folsom Rd",
    "iso:country":"US",
    "sg:address":"117 Folsom Rd",
    "sg:city":"Tallapoosa",
    "sg:classifiers":[
        {
            "category":"Building & Trades",
            "subcategory":"Landscaping Services",
            "type":"Services"
        }
    ],
    "sg:phone":"+1 770 646 1746",
    "sg:postcode":"30113",
    "sg:province":"GA",
    "sg:tags":[
        "landscape",
        "contractor"
    ],
    "wof:name":"Garden Granny's",
    "wof:placetype":"venue"
},
  "geometry": {"coordinates":[-85.37150099999999,33.861414],"type":"Point"}
}