{
  "type": "Feature",
  "properties": {
    "addr:full":"1112 Mary Lee Ln SW Lilburn GA 30047",
    "addr:housenumber":"1112",
    "addr:postcode":"30047",
    "addr:street":"Mary Lee Ln Sw",
    "iso:country":"US",
    "sg:address":"1112 Mary Lee Ln SW",
    "sg:city":"Lilburn",
    "sg:classifiers":[
        {
            "category":"Wholesale",
            "subcategory":"Machinery & Supplies",
            "type":"Manufacturing & Wholesale Goods"
        }
    ],
    "sg:phone":"+1 770 925 2725",
    "sg:postcode":"30047",
    "sg:province":"GA",
    "sg:tags":[
        "industrial"
    ],
    "wof:name":"Flowserve Corporation",
    "wof:placetype":"venue"
},
  "geometry": {"coordinates":[-84.084306,33.868204],"type":"Point"}
}