{
  "type": "Feature",
  "properties": {
    "addr:full":"4771 Britt Rd Norcross GA 30093",
    "addr:housenumber":"4771",
    "addr:postcode":"30093",
    "addr:street":"Britt Rd",
    "iso:country":"US",
    "sg:address":"4771 Britt Rd",
    "sg:city":"Norcross",
    "sg:classifiers":[
        {
            "category":"Restaurant",
            "type":"Food & Drink"
        }
    ],
    "sg:phone":"+1 770 492 0400",
    "sg:postcode":"30093",
    "sg:province":"GA",
    "sg:tags":[
        "eating"
    ],
    "wof:name":"Steaks To Go",
    "wof:placetype":"venue"
},
  "geometry": {"coordinates":[-84.19827600000001,33.882078],"type":"Point"}
}