{
  "type": "Feature",
  "properties": {
    "iso:country":"US",
    "sg:address":"330 Adams Rd",
    "sg:city":"Canton",
    "sg:classifiers":[
        {
            "category":"Communications",
            "type":"Services"
        },
        {
            "category":"Professional",
            "subcategory":"Art Services",
            "type":"Services"
        }
    ],
    "sg:phone":"+1 770 720 2811",
    "sg:postcode":"30115",
    "sg:province":"GA",
    "sg:tags":[
        "communication",
        "graphic",
        "designer"
    ],
    "wof:name":"Visual Communication Images",
    "wof:placetype":"venue"
},
  "geometry": {"coordinates":[-84.413612,34.227676],"type":"Point"}
}