{
  "type": "Feature",
  "properties": {
    "iso:country":"US",
    "sg:address":"1114 N Wall St",
    "sg:city":"Calhoun",
    "sg:classifiers":[
        {
            "category":"Autos & Motor Vehicles",
            "subcategory":"Automobile Sales",
            "type":"Retail Goods"
        }
    ],
    "sg:phone":"+1 706 629 9884",
    "sg:postcode":"30701",
    "sg:province":"GA",
    "sg:tags":[
        "car",
        "used",
        "dealer"
    ],
    "wof:name":"Crawford's Used Cars",
    "wof:placetype":"venue"
},
  "geometry": {"coordinates":[-84.942144,34.520489],"type":"Point"}
}