{
  "type": "Feature",
  "properties": {
    "addr:full":"380 Stonewall Ave W Fayetteville GA 30214",
    "addr:housenumber":"380",
    "addr:postcode":"30214",
    "addr:street":"Stonewall Ave W",
    "iso:country":"US",
    "sg:address":"380 Stonewall Ave W",
    "sg:city":"Fayetteville",
    "sg:classifiers":[
        {
            "category":"Professional",
            "subcategory":"Management & Consulting",
            "type":"Services"
        }
    ],
    "sg:phone":"+1 770 716 5151",
    "sg:postcode":"30214",
    "sg:province":"GA",
    "sg:tags":[
        "consultant",
        "business"
    ],
    "wof:name":"Cima Group Inc",
    "wof:placetype":"venue"
},
  "geometry": {"coordinates":[-84.45751300000001,33.447716],"type":"Point"}
}