{
  "type": "Feature",
  "properties": {
    "addr:full":"3460 Dearborn Plz Atlanta GA 30354",
    "addr:housenumber":"3460",
    "addr:postcode":"30354",
    "addr:street":"Dearborn Plz",
    "iso:country":"US",
    "sg:address":"3460 Dearborn Plz",
    "sg:city":"Atlanta",
    "sg:classifiers":[
        {
            "category":"Food & Beverages",
            "subcategory":"Groceries & Convenience Stores",
            "type":"Retail Goods"
        }
    ],
    "sg:phone":"+1 404 766 4623",
    "sg:postcode":"30354",
    "sg:province":"GA",
    "sg:tags":[
        "mexican",
        "market"
    ],
    "wof:name":"La Michoacana Mexican Food Mkt",
    "wof:placetype":"venue"
},
  "geometry": {"coordinates":[-84.407112,33.659004],"type":"Point"}
}