{
  "type": "Feature",
  "properties": {
    "addr:full":"103 George St Adairsville GA 30103",
    "addr:housenumber":"103",
    "addr:postcode":"30103",
    "addr:street":"George St",
    "iso:country":"US",
    "sg:address":"103 George St",
    "sg:city":"Adairsville",
    "sg:classifiers":[
        {
            "category":"Building & Trades",
            "subcategory":"Construction",
            "type":"Services"
        }
    ],
    "sg:phone":"+1 770 877 9478",
    "sg:postcode":"30103",
    "sg:province":"GA",
    "sg:tags":[
        "wallcoverings-installation",
        "wallpaper",
        "painting",
        "contractor"
    ],
    "wof:name":"Smith Cathy Painter",
    "wof:placetype":"venue"
},
  "geometry": {"coordinates":[-84.936683,34.370531],"type":"Point"}
}