{
  "type": "Feature",
  "properties": {
    "addr:full":"7795 Blue Ridge Hwy Blairsville GA 30512",
    "addr:housenumber":"7795",
    "addr:postcode":"30512",
    "addr:street":"Blue Ridge Hwy",
    "iso:country":"US",
    "sg:address":"7795 Blue Ridge Hwy",
    "sg:city":"Blairsville",
    "sg:classifiers":[
        {
            "category":"Recreation",
            "type":"Entertainment"
        }
    ],
    "sg:phone":"+1 706 745 4261",
    "sg:postcode":"30512",
    "sg:province":"GA",
    "sg:tags":[
        "skating",
        "rink"
    ],
    "wof:name":"Bill's Roller Rink",
    "wof:placetype":"venue"
},
  "geometry": {"coordinates":[-84.095823,34.853868],"type":"Point"}
}