{
  "type": "Feature",
  "properties": {
    "iso:country":"US",
    "sg:address":"3711 Benjamin E Mays Dr SW",
    "sg:city":"Atlanta",
    "sg:classifiers":[
        {
            "category":"Government",
            "subcategory":"Office",
            "type":"Public Place"
        }
    ],
    "sg:phone":"+1 404 696 7623",
    "sg:postcode":"30331",
    "sg:province":"GA",
    "wof:name":"Lee, Annette",
    "wof:placetype":"venue"
},
  "geometry": {"coordinates":[-84.508436,33.739661],"type":"Point"}
}