{
  "type": "Feature",
  "properties": {
    "addr:full":"368 Crescent Dr Newnan GA 30265",
    "addr:housenumber":"368",
    "addr:postcode":"30265",
    "addr:street":"Crescent Dr",
    "iso:country":"US",
    "sg:address":"368 Crescent Dr",
    "sg:city":"Newnan",
    "sg:classifiers":[
        {
            "category":"Professional",
            "subcategory":"Advertising",
            "type":"Services"
        }
    ],
    "sg:phone":"+1 770 502 7947",
    "sg:postcode":"30265",
    "sg:province":"GA",
    "sg:tags":[
        "mail",
        "direct"
    ],
    "sg:website":"http://www.moneymailer.com",
    "wof:name":"Money Mailer",
    "wof:placetype":"venue"
},
  "geometry": {"coordinates":[-84.67684,33.428044],"type":"Point"}
}