{
  "type": "Feature",
  "properties": {
    "addr:full":"1223 Wynterhall Ln Atlanta GA 30338",
    "addr:housenumber":"1223",
    "addr:postcode":"30338",
    "addr:street":"Wynterhall Ln",
    "iso:country":"US",
    "sg:address":"1223 Wynterhall Ln",
    "sg:city":"Atlanta",
    "sg:classifiers":[
        {
            "category":"Shopping",
            "subcategory":"Hobbies, Toys, & Games",
            "type":"Retail Goods"
        }
    ],
    "sg:phone":"+1 770 396 9357",
    "sg:postcode":"30338",
    "sg:province":"GA",
    "wof:name":"Georgia N Trains",
    "wof:placetype":"venue"
},
  "geometry": {"coordinates":[-84.338297,33.952259],"type":"Point"}
}