{
  "type": "Feature",
  "properties": {
    "iso:country":"US",
    "sg:address":"358 US Hwy 80",
    "sg:city":"Danville",
    "sg:classifiers":[
        {
            "category":"Food & Beverages",
            "subcategory":"Groceries & Convenience Stores",
            "type":"Retail Goods"
        }
    ],
    "sg:phone":"+1 478 962 3557",
    "sg:postcode":"31017",
    "sg:province":"GA",
    "wof:name":"Bowmans 1 Stop",
    "wof:placetype":"venue"
},
  "geometry": {"coordinates":[-83.253998,32.605028],"type":"Point"}
}