{
  "type": "Feature",
  "properties": {
    "addr:full":"2665 Skyland Dr NE Atlanta GA 30319",
    "addr:housenumber":"2665",
    "addr:postcode":"30319",
    "addr:street":"Skyland Dr Ne",
    "iso:country":"US",
    "sg:address":"2665 Skyland Dr NE",
    "sg:city":"Atlanta",
    "sg:classifiers":[
        {
            "category":"Building & Trades",
            "subcategory":"Locksmith",
            "type":"Services"
        }
    ],
    "sg:phone":"+1 404 682 9440",
    "sg:postcode":"30319",
    "sg:province":"GA",
    "sg:tags":[
        "key"
    ],
    "wof:name":"1 2 3 24 Hour A Locksmith",
    "wof:placetype":"venue"
},
  "geometry": {"coordinates":[-84.314615,33.86397],"type":"Point"}
}