{
  "type": "Feature",
  "properties": {
    "addr:full":"2453 Coronet Way NW K2 Atlanta GA 30318",
    "addr:housenumber":"2453",
    "addr:postcode":"30318",
    "addr:street":"Coronet Way Nw",
    "iso:country":"US",
    "sg:address":"2453 Coronet Way NW K2",
    "sg:city":"Atlanta",
    "sg:classifiers":[
        {
            "category":"Building & Trades",
            "subcategory":"Electrical",
            "type":"Services"
        }
    ],
    "sg:phone":"+1 678 427 3926",
    "sg:postcode":"30318",
    "sg:province":"GA",
    "sg:tags":[
        "industrial",
        "electrician",
        "contractors-commercial",
        "electric"
    ],
    "wof:name":"LG Electrical Services",
    "wof:placetype":"venue"
},
  "geometry": {"coordinates":[-84.44918800000001,33.820229],"type":"Point"}
}