{
  "type": "Feature",
  "properties": {
    "addr:full":"806 W Highland Ave Albany GA 31701",
    "addr:housenumber":"806",
    "addr:postcode":"31701",
    "addr:street":"W Highland Ave",
    "iso:country":"US",
    "sg:address":"806 W Highland Ave",
    "sg:city":"Albany",
    "sg:classifiers":[
        {
            "category":"Retail",
            "subcategory":"Funeral Services",
            "type":"Services"
        }
    ],
    "sg:phone":"+1 229 434 0520",
    "sg:postcode":"31701",
    "sg:province":"GA",
    "wof:name":"Ward & Ward Mortuary",
    "wof:placetype":"venue"
},
  "geometry": {"coordinates":[-84.17051600000001,31.57371],"type":"Point"}
}