{
  "type": "Feature",
  "properties": {
    "iso:country":"US",
    "sg:address":"1390 Veterans Memorial Hwy SW",
    "sg:city":"Mableton",
    "sg:classifiers":[
        {
            "category":"Home & Garden",
            "subcategory":"Household Appliances",
            "type":"Retail Goods"
        }
    ],
    "sg:phone":"+1 770 819 6915",
    "sg:postcode":"30126",
    "sg:province":"GA",
    "wof:name":"Jim's Appliance Center",
    "wof:placetype":"venue"
},
  "geometry": {"coordinates":[-84.59471499999999,33.815476],"type":"Point"}
}