{
  "type": "Feature",
  "properties": {
    "iso:country":"US",
    "sg:address":"2429 Victory Dr",
    "sg:city":"Columbus",
    "sg:classifiers":[
        {
            "category":"Personal",
            "type":"Services"
        }
    ],
    "sg:phone":"+1 706 687 0007",
    "sg:postcode":"31901",
    "sg:province":"GA",
    "sg:tags":[
        "mover",
        "full",
        "storage"
    ],
    "sg:website":"http://www.aimovers.com",
    "wof:name":"American International Movers",
    "wof:placetype":"venue"
},
  "geometry": {"coordinates":[-84.964275,32.440018],"type":"Point"}
}