{
  "type": "Feature",
  "properties": {
    "iso:country":"US",
    "sg:address":"660 Juniper St NE",
    "sg:city":"Atlanta",
    "sg:classifiers":[
        {
            "category":"Building & Trades",
            "subcategory":"Locksmith",
            "type":"Services"
        }
    ],
    "sg:phone":"+1 404 728 8124",
    "sg:postcode":"30308",
    "sg:province":"GA",
    "sg:tags":[
        "key"
    ],
    "wof:name":"A A Paul Locksmith",
    "wof:placetype":"venue"
},
  "geometry": {"coordinates":[-84.383382,33.773125],"type":"Point"}
}