{
  "type": "Feature",
  "properties": {
    "addr:full":"478 Northdale Rd Lawrenceville GA 30045",
    "addr:housenumber":"478",
    "addr:postcode":"30045",
    "addr:street":"Northdale Rd",
    "iso:country":"US",
    "sg:address":"478 Northdale Rd",
    "sg:city":"Lawrenceville",
    "sg:classifiers":[
        {
            "category":"Building & Trades",
            "subcategory":"Plumbing",
            "type":"Services"
        }
    ],
    "sg:phone":"+1 678 376 5929",
    "sg:postcode":"30045",
    "sg:province":"GA",
    "sg:tags":[
        "conditioning",
        "air",
        "system",
        "contractor"
    ],
    "wof:name":"Air Flow Mechanical",
    "wof:placetype":"venue"
},
  "geometry": {"coordinates":[-83.991033,33.968359],"type":"Point"}
}