{
  "type": "Feature",
  "properties": {
    "iso:country":"US",
    "sg:address":"5684 Orchard Place Xing",
    "sg:city":"Lilburn",
    "sg:classifiers":[
        {
            "category":"Professional",
            "subcategory":"Computer Services",
            "type":"Services"
        }
    ],
    "sg:phone":"+1 678 232 3614",
    "sg:postcode":"30047",
    "sg:province":"GA",
    "sg:tags":[
        "consulting",
        "it"
    ],
    "wof:name":"Entole",
    "wof:placetype":"venue"
},
  "geometry": {"coordinates":[-84.151066,33.859161],"type":"Point"}
}