{
  "type": "Feature",
  "properties": {
    "addr:full":"2600 Dallas Hwy Marietta GA 30064",
    "addr:housenumber":"2600",
    "addr:postcode":"30064",
    "addr:street":"Dallas Hwy",
    "iso:country":"US",
    "sg:address":"2600 Dallas Hwy",
    "sg:city":"Marietta",
    "sg:classifiers":[
        {
            "category":"Banks & Credit Unions",
            "subcategory":"Bank",
            "type":"Services"
        }
    ],
    "sg:phone":"+1 770 590 3950",
    "sg:postcode":"30064",
    "sg:province":"GA",
    "sg:tags":[
        "state",
        "commercial"
    ],
    "wof:name":"SunTrust",
    "wof:placetype":"venue"
},
  "geometry": {"coordinates":[-84.628754,33.946716],"type":"Point"}
}