{
  "type": "Feature",
  "properties": {
    "addr:full":"1046 Rock Creek Ln Norcross GA 30093",
    "addr:housenumber":"1046",
    "addr:postcode":"30093",
    "addr:street":"Rock Creek Ln",
    "iso:country":"US",
    "sg:address":"1046 Rock Creek Ln",
    "sg:city":"Norcross",
    "sg:classifiers":[
        {
            "category":"Organizations",
            "subcategory":"Religious Organization",
            "type":"Services"
        }
    ],
    "sg:phone":"+1 770 356 6216",
    "sg:postcode":"30093",
    "sg:province":"GA",
    "sg:tags":[
        "duty",
        "ministry"
    ],
    "wof:name":"A Place of Refuge Safe Passage",
    "wof:placetype":"venue"
},
  "geometry": {"coordinates":[-84.154292,33.912894],"type":"Point"}
}