{
  "type": "Feature",
  "properties": {
    "addr:full":"2480 Flat Shoals Rd Atlanta GA 30349",
    "addr:housenumber":"2480",
    "addr:postcode":"30349",
    "addr:street":"Flat Shoals Rd",
    "iso:country":"US",
    "sg:address":"2480 Flat Shoals Rd",
    "sg:city":"Atlanta",
    "sg:classifiers":[
        {
            "category":"Fast Food",
            "type":"Food & Drink"
        },
        {
            "category":"Restaurant",
            "type":"Food & Drink"
        }
    ],
    "sg:phone":"+1 770 997 4430",
    "sg:postcode":"30349",
    "sg:province":"GA",
    "sg:tags":[
        "take"
    ],
    "sg:website":"http://www.mrs-winners.com",
    "wof:name":"Mrs Winner's Chicken & Biscuits",
    "wof:placetype":"venue"
},
  "geometry": {"coordinates":[-84.469876,33.588855],"type":"Point"}
}