{
  "type": "Feature",
  "properties": {
    "iso:country":"US",
    "sg:address":"220 Johnson Rd",
    "sg:city":"Suwanee",
    "sg:classifiers":[
        {
            "category":"Professional",
            "subcategory":"Management & Consulting",
            "type":"Services"
        }
    ],
    "sg:phone":"+1 770 614 0060",
    "sg:postcode":"30024",
    "sg:province":"GA",
    "wof:name":"Daecon Inc",
    "wof:placetype":"venue"
},
  "geometry": {"coordinates":[-84.093491,34.09465],"type":"Point"}
}