{
  "type": "Feature",
  "properties": {
    "addr:full":"25 Ag Best Rd Eastman GA 31023",
    "addr:housenumber":"25",
    "addr:postcode":"31023",
    "addr:street":"Ag Best Rd",
    "iso:country":"US",
    "sg:address":"25 Ag Best Rd",
    "sg:city":"Eastman",
    "sg:classifiers":[
        {
            "category":"Wholesale",
            "subcategory":"Vending Machines",
            "type":"Manufacturing & Wholesale Goods"
        }
    ],
    "sg:phone":"+1 478 374 0502",
    "sg:postcode":"31023",
    "sg:province":"GA",
    "wof:name":"S & C Supply",
    "wof:placetype":"venue"
},
  "geometry": {"coordinates":[-83.15091700000001,32.171078],"type":"Point"}
}