{
  "type": "Feature",
  "properties": {
    "iso:country":"US",
    "sg:address":"1616 E Shotwell St",
    "sg:city":"Bainbridge",
    "sg:classifiers":[
        {
            "category":"Shopping",
            "subcategory":"Pharmacy",
            "type":"Retail Goods"
        }
    ],
    "sg:phone":"+1 229 246 8300",
    "sg:postcode":"39819",
    "sg:province":"GA",
    "wof:name":"Eckerd",
    "wof:placetype":"venue"
},
  "geometry": {"coordinates":[-84.55045699999999,30.903769],"type":"Point"}
}