{
  "type": "Feature",
  "properties": {
    "addr:full":"514 Old Statenville Rd Valdosta GA 31601",
    "addr:housenumber":"514",
    "addr:postcode":"31601",
    "addr:street":"Old Statenville Rd",
    "iso:country":"US",
    "sg:address":"514 Old Statenville Rd",
    "sg:city":"Valdosta",
    "sg:classifiers":[
        {
            "category":"Personal",
            "subcategory":"Beauty Salon",
            "type":"Services"
        }
    ],
    "sg:phone":"+1 229 247 5049",
    "sg:postcode":"31601",
    "sg:province":"GA",
    "sg:tags":[
        "shop"
    ],
    "wof:name":"Tinas Lacoiffeuse",
    "wof:placetype":"venue"
},
  "geometry": {"coordinates":[-83.264921,30.820826],"type":"Point"}
}