{
  "type": "Feature",
  "properties": {
    "iso:country":"US",
    "sg:address":"3264 Commerce Ave",
    "sg:city":"Duluth",
    "sg:classifiers":[
        {
            "category":"Autos & Motor Vehicles",
            "subcategory":"Automobile Sales",
            "type":"Retail Goods"
        }
    ],
    "sg:phone":"+1 888 617 3377",
    "sg:postcode":"30096",
    "sg:province":"GA",
    "sg:tags":[
        "car"
    ],
    "sg:website":"gwinnettbmw.com",
    "wof:name":"United BMW of Gwinnett",
    "wof:placetype":"venue"
},
  "geometry": {"coordinates":[-84.119421,33.959237],"type":"Point"}
}