{
  "type": "Feature",
  "properties": {
    "addr:full":"2172 Sugar Maple Cove NW Acworth GA 30101",
    "addr:housenumber":"2172",
    "addr:postcode":"30101",
    "addr:street":"Sugar Maple Cove Nw",
    "iso:country":"US",
    "sg:address":"2172 Sugar Maple Cove NW",
    "sg:city":"Acworth",
    "sg:classifiers":[
        {
            "category":"Building & Trades",
            "subcategory":"Construction",
            "type":"Services"
        }
    ],
    "sg:phone":"+1 770 851 4928",
    "sg:postcode":"30101",
    "sg:province":"GA",
    "sg:tags":[
        "contractor"
    ],
    "sg:website":"www.dps-inc.org",
    "wof:name":"Distinguished Products & Services, Inc",
    "wof:placetype":"venue"
},
  "geometry": {"coordinates":[-84.614755,34.058735],"type":"Point"}
}