{
  "type": "Feature",
  "properties": {
    "addr:full":"3077 N Druid Hills Rd Decatur GA 30033",
    "addr:housenumber":"3077",
    "addr:postcode":"30033",
    "addr:street":"N Druid Hills Rd",
    "iso:country":"US",
    "sg:address":"3077 N Druid Hills Rd",
    "sg:city":"Decatur",
    "sg:classifiers":[
        {
            "category":"Restaurant",
            "type":"Food & Drink"
        }
    ],
    "sg:menulink":"http://www.allmenus.com/ga/atlanta-decatur/18127-papa-johns-pizza/menu/",
    "sg:phone":"+1 404 315 8282",
    "sg:postcode":"30033",
    "sg:province":"GA",
    "sg:tags":[
        "american",
        "pizza"
    ],
    "wof:name":"Papa John's Pizza",
    "wof:placetype":"venue"
},
  "geometry": {"coordinates":[-84.30684100000001,33.812485],"type":"Point"}
}