{
  "type": "Feature",
  "properties": {
    "addr:full":"2086 Breconridge Dr Marietta GA 30064",
    "addr:housenumber":"2086",
    "addr:postcode":"30064",
    "addr:street":"Breconridge Dr",
    "iso:country":"US",
    "sg:address":"2086 Breconridge Dr",
    "sg:city":"Marietta",
    "sg:classifiers":[
        {
            "category":"Home & Garden",
            "subcategory":"Home Furnishings",
            "type":"Retail Goods"
        }
    ],
    "sg:phone":"+1 770 590 8989",
    "sg:postcode":"30064",
    "sg:province":"GA",
    "wof:name":"Happy Cooker",
    "wof:placetype":"venue"
},
  "geometry": {"coordinates":[-84.611611,33.914739],"type":"Point"}
}