{
  "type": "Feature",
  "properties": {
    "addr:full":"835 Jett Ferry Mnr Atlanta GA 30350",
    "addr:housenumber":"835",
    "addr:postcode":"30350",
    "addr:street":"Jett Ferry Mnr",
    "iso:country":"US",
    "sg:address":"835 Jett Ferry Mnr",
    "sg:city":"Atlanta",
    "sg:classifiers":[
        {
            "category":"Health Services",
            "subcategory":"Doctor",
            "type":"Services"
        },
        {
            "category":"Health Services",
            "subcategory":"Dentist",
            "type":"Services"
        }
    ],
    "sg:phone":"+1 770 393 9487",
    "sg:postcode":"30350",
    "sg:province":"GA",
    "sg:tags":[
        "dentists-oral",
        "physician",
        "maxillofacial",
        "surgeons",
        "surgery",
        "oral"
    ],
    "wof:name":"Prilkuck Jeffrey G Dmd Mags Pc",
    "wof:placetype":"venue"
},
  "geometry": {"coordinates":[-84.290752,33.97078],"type":"Point"}
}