{
  "type": "Feature",
  "properties": {
    "iso:country":"US",
    "sg:address":"70 Courtland St NE",
    "sg:city":"Atlanta",
    "sg:classifiers":[
        {
            "category":"Retail",
            "subcategory":"Repair Shop",
            "type":"Services"
        }
    ],
    "sg:phone":"+1 404 584 8001",
    "sg:postcode":"30308",
    "sg:province":"GA",
    "wof:name":"Xerox",
    "wof:placetype":"venue"
},
  "geometry": {"coordinates":[-84.38426699999999,33.75557],"type":"Point"}
}