{
  "type": "Feature",
  "properties": {
    "iso:country":"US",
    "sg:address":"4790 Peachtree Ind Blvd",
    "sg:city":"Norcross",
    "sg:classifiers":[
        {
            "category":"Restaurant",
            "type":"Food & Drink"
        }
    ],
    "sg:phone":"+1 678 527 8899",
    "sg:postcode":"30071",
    "sg:province":"GA",
    "sg:tags":[
        "new",
        "american"
    ],
    "sg:website":"www.facebook.com/pages/Norcross-...",
    "wof:name":"Berkeley's Sports Grill",
    "wof:placetype":"venue"
},
  "geometry": {"coordinates":[-84.245716,33.9406],"type":"Point"}
}