{
  "type": "Feature",
  "properties": {
    "iso:country":"US",
    "sg:address":"400 Cedar St",
    "sg:city":"Metter",
    "sg:classifiers":[
        {
            "category":"Health Services",
            "subcategory":"Hospital",
            "type":"Services"
        }
    ],
    "sg:phone":"+1 912 685 5911",
    "sg:postcode":"30439",
    "sg:province":"GA",
    "wof:name":"Chest Pain Ctr",
    "wof:placetype":"venue"
},
  "geometry": {"coordinates":[-82.066593,32.407069],"type":"Point"}
}