{
  "type": "Feature",
  "properties": {
    "iso:country":"US",
    "sg:address":"1210 Vintage Club Dr",
    "sg:city":"Duluth",
    "sg:classifiers":[
        {
            "category":"Professional",
            "subcategory":"Management & Consulting",
            "type":"Services"
        }
    ],
    "sg:phone":"+1 770 476 5704",
    "sg:postcode":"30097",
    "sg:province":"GA",
    "wof:name":"Stumpers LLC",
    "wof:placetype":"venue"
},
  "geometry": {"coordinates":[-84.180361,34.029086],"type":"Point"}
}