{
  "type": "Feature",
  "properties": {
    "iso:country":"US",
    "sg:address":"175 Carnes Dr",
    "sg:city":"Fayetteville",
    "sg:classifiers":[
        {
            "category":"Building & Trades",
            "subcategory":"Equipment Rental",
            "type":"Services"
        }
    ],
    "sg:phone":"+1 770 460 7163",
    "sg:postcode":"30214",
    "sg:province":"GA",
    "sg:tags":[
        "truck"
    ],
    "sg:website":"www.alllift.com",
    "wof:name":"All-Lift",
    "wof:placetype":"venue"
},
  "geometry": {"coordinates":[-84.434364,33.503089],"type":"Point"}
}