{
  "type": "Feature",
  "properties": {
    "iso:country":"US",
    "sg:address":"9845 Bankside Dr Ste 110",
    "sg:city":"Roswell",
    "sg:classifiers":[
        {
            "category":"Communications",
            "subcategory":"Film & Video Production",
            "type":"Services"
        },
        {
            "category":"Communications",
            "subcategory":"Television Station",
            "type":"Services"
        }
    ],
    "sg:phone":"+1 770 361 5203",
    "sg:postcode":"30076",
    "sg:province":"GA",
    "sg:tags":[
        "companies-film",
        "producer",
        "tv",
        "program",
        "radio",
        "distributor"
    ],
    "sg:website":"http://www.intermarkinc.com",
    "wof:name":"Meeting Concepts",
    "wof:placetype":"venue"
},
  "geometry": {"coordinates":[-84.278649,34.023378],"type":"Point"}
}