{
  "type": "Feature",
  "properties": {
    "addr:full":"2017 Boone Dairy Rd Valdosta GA 31601",
    "addr:housenumber":"2017",
    "addr:postcode":"31601",
    "addr:street":"Boone Dairy Rd",
    "iso:country":"US",
    "sg:address":"2017 Boone Dairy Rd",
    "sg:city":"Valdosta",
    "sg:classifiers":[
        {
            "category":"Building & Trades",
            "subcategory":"Construction",
            "type":"Services"
        }
    ],
    "sg:phone":"+1 229 244 7382",
    "sg:postcode":"31601",
    "sg:province":"GA",
    "sg:tags":[
        "roofing",
        "contractor"
    ],
    "wof:name":"Lowndes Roofing & Sheet Metal",
    "wof:placetype":"venue"
},
  "geometry": {"coordinates":[-83.31309899999999,30.817981],"type":"Point"}
}