{
  "type": "Feature",
  "properties": {
    "addr:full":"4227 Steve Reynolds Blvd Norcross GA 30093",
    "addr:housenumber":"4227",
    "addr:postcode":"30093",
    "addr:street":"Steve Reynolds Blvd",
    "iso:country":"US",
    "sg:address":"4227 Steve Reynolds Blvd",
    "sg:city":"Norcross",
    "sg:classifiers":[
        {
            "category":"Home & Garden",
            "subcategory":"Carpets & Floor Coverings",
            "type":"Retail Goods"
        }
    ],
    "sg:phone":"+1 770 638 8200",
    "sg:postcode":"30093",
    "sg:province":"GA",
    "wof:name":"Mikes Carpets",
    "wof:placetype":"venue"
},
  "geometry": {"coordinates":[-84.14767000000001,33.92726],"type":"Point"}
}