{
  "type": "Feature",
  "properties": {
    "iso:country":"US",
    "sg:address":"963 Summit Ave",
    "sg:city":"Macon",
    "sg:classifiers":[
        {
            "category":"Professional",
            "type":"Services"
        }
    ],
    "sg:phone":"+1 478 745 3926",
    "sg:postcode":"31211",
    "sg:province":"GA",
    "wof:name":"Blue Ridge Container Inc",
    "wof:placetype":"venue"
},
  "geometry": {"coordinates":[-83.62421999999999,32.855969],"type":"Point"}
}