{
  "type": "Feature",
  "properties": {
    "iso:country":"US",
    "sg:address":"11553 US Hwy 84",
    "sg:city":"Midway",
    "sg:classifiers":[
        {
            "category":"Professional",
            "subcategory":"Accounting & Tax Preparation",
            "type":"Services"
        }
    ],
    "sg:phone":"+1 912 884 9167",
    "sg:postcode":"31320",
    "sg:province":"GA",
    "sg:tags":[
        "return",
        "filing"
    ],
    "wof:name":"Brown's Tax & Accounting",
    "wof:placetype":"venue"
},
  "geometry": {"coordinates":[-81.42690899999999,31.799816],"type":"Point"}
}