{
  "type": "Feature",
  "properties": {
    "addr:full":"1208 Everwood Dr SW Marietta GA 30008",
    "addr:housenumber":"1208",
    "addr:postcode":"30008",
    "addr:street":"Everwood Dr Sw",
    "iso:country":"US",
    "sg:address":"1208 Everwood Dr SW",
    "sg:city":"Marietta",
    "sg:classifiers":[
        {
            "category":"Food & Beverages",
            "subcategory":"Liquor & Beverages",
            "type":"Retail Goods"
        },
        {
            "category":"Wholesale",
            "subcategory":"Wine & Distilled Alcoholic Beverages",
            "type":"Manufacturing & Wholesale Goods"
        }
    ],
    "sg:phone":"+1 770 436 1639",
    "sg:postcode":"30008",
    "sg:province":"GA",
    "sg:tags":[
        "broker"
    ],
    "wof:name":"Best Wine Pick",
    "wof:placetype":"venue"
},
  "geometry": {"coordinates":[-84.591628,33.887009],"type":"Point"}
}