{
  "type": "Feature",
  "properties": {
    "addr:full":"1700 Mansell Rd Alpharetta GA 30004",
    "addr:housenumber":"1700",
    "addr:postcode":"30004",
    "addr:street":"Mansell Rd",
    "iso:country":"US",
    "sg:address":"1700 Mansell Rd",
    "sg:city":"Alpharetta",
    "sg:classifiers":[
        {
            "category":"Restaurant",
            "type":"Food & Drink"
        }
    ],
    "sg:phone":"+1 770 649 0064",
    "sg:postcode":"30004",
    "sg:province":"GA",
    "sg:tags":[
        "seafood",
        "steakhouse"
    ],
    "sg:website":"www.raysrestaurants.com/index.ph...",
    "wof:name":"Ray's Killer Creek",
    "wof:placetype":"venue"
},
  "geometry": {"coordinates":[-84.31657800000001,34.040441],"type":"Point"}
}