{
  "type": "Feature",
  "properties": {
    "addr:full":"3460 Fawn Trl Marietta GA 30066",
    "addr:housenumber":"3460",
    "addr:postcode":"30066",
    "addr:street":"Fawn Trl",
    "iso:country":"US",
    "sg:address":"3460 Fawn Trl",
    "sg:city":"Marietta",
    "sg:classifiers":[
        {
            "category":"Building & Trades",
            "subcategory":"Construction",
            "type":"Services"
        }
    ],
    "sg:phone":"+1 770 973 8215",
    "sg:postcode":"30066",
    "sg:province":"GA",
    "sg:tags":[
        "house"
    ],
    "wof:name":"Rci Contracting",
    "wof:placetype":"venue"
},
  "geometry": {"coordinates":[-84.50229299999999,34.031455],"type":"Point"}
}