{
  "type": "Feature",
  "properties": {
    "iso:country":"US",
    "sg:address":"250 Little St",
    "sg:city":"Athens",
    "sg:classifiers":[
        {
            "category":"Arts & Performance",
            "subcategory":"Theater",
            "type":"Entertainment"
        }
    ],
    "sg:phone":"+1 706 369 7758",
    "sg:postcode":"30605",
    "sg:province":"GA",
    "sg:tags":[
        "group"
    ],
    "wof:name":"Scott Munn",
    "wof:placetype":"venue"
},
  "geometry": {"coordinates":[-83.366367,33.950587],"type":"Point"}
}