{
  "type": "Feature",
  "properties": {
    "addr:full":"4060 Twin Oaks Rd Valdosta GA 31601",
    "addr:housenumber":"4060",
    "addr:postcode":"31601",
    "addr:street":"Twin Oaks Rd",
    "iso:country":"US",
    "sg:address":"4060 Twin Oaks Rd",
    "sg:city":"Valdosta",
    "sg:classifiers":[
        {
            "category":"Building & Trades",
            "subcategory":"Landscaping Services",
            "type":"Services"
        }
    ],
    "sg:phone":"+1 229 559 5213",
    "sg:postcode":"31601",
    "sg:province":"GA",
    "wof:name":"Smiths Lawn Care",
    "wof:placetype":"venue"
},
  "geometry": {"coordinates":[-83.27840399999999,30.719203],"type":"Point"}
}