{
  "type": "Feature",
  "properties": {
    "iso:country":"US",
    "sg:address":"900 Peachtree St #302",
    "sg:city":"Atlanta",
    "sg:classifiers":[
        {
            "category":"Sports & Exercise",
            "subcategory":"Gym",
            "type":"Entertainment"
        }
    ],
    "sg:phone":"+1 404 892 9100",
    "sg:postcode":"30309",
    "sg:province":"GA",
    "sg:tags":[
        "yoga"
    ],
    "sg:website":"www.onlyoga.com",
    "wof:name":"onlYoga",
    "wof:placetype":"venue"
},
  "geometry": {"coordinates":[-84.38438600000001,33.77933],"type":"Point"}
}