{
  "type": "Feature",
  "properties": {
    "addr:full":"532 Plasters Ave NE Atlanta GA 30324",
    "addr:housenumber":"532",
    "addr:postcode":"30324",
    "addr:street":"Plasters Ave Ne",
    "iso:country":"US",
    "sg:address":"532 Plasters Ave NE",
    "sg:city":"Atlanta",
    "sg:classifiers":[
        {
            "category":"Retail",
            "subcategory":"Repair Shop",
            "type":"Services"
        }
    ],
    "sg:phone":"+1 404 876 1267",
    "sg:postcode":"30324",
    "sg:province":"GA",
    "sg:tags":[
        "lock",
        "safe",
        "locksmith",
        "vault"
    ],
    "sg:website":"http://www.realpagessites.com/bullardslockmaster",
    "wof:name":"Bullard's Lockmaster & Safe Co Inc",
    "wof:placetype":"venue"
},
  "geometry": {"coordinates":[-84.37029,33.812159],"type":"Point"}
}