{
  "type": "Feature",
  "properties": {
    "iso:country":"US",
    "sg:address":"743 Main St SW",
    "sg:city":"Gainesville",
    "sg:classifiers":[
        {
            "category":"Banks & Credit Unions",
            "subcategory":"Bank",
            "type":"Services"
        }
    ],
    "sg:phone":"+1 770 297 0082",
    "sg:postcode":"30501",
    "sg:province":"GA",
    "sg:tags":[
        "loan",
        "real estate"
    ],
    "wof:name":"Pine State Mortgage Corp",
    "wof:placetype":"venue"
},
  "geometry": {"coordinates":[-83.82278599999999,34.292812],"type":"Point"}
}