{
  "type": "Feature",
  "properties": {
    "iso:country":"US",
    "sg:address":"4472 Glenaire Cove NW",
    "sg:city":"Acworth",
    "sg:classifiers":[
        {
            "category":"Building & Trades",
            "subcategory":"Construction",
            "type":"Services"
        }
    ],
    "sg:phone":"+1 770 975 0878",
    "sg:postcode":"30101",
    "sg:province":"GA",
    "sg:tags":[
        "home",
        "builder",
        "operative",
        "family"
    ],
    "wof:name":"Pulte",
    "wof:placetype":"venue"
},
  "geometry": {"coordinates":[-84.613185,34.063228],"type":"Point"}
}