{
  "type": "Feature",
  "properties": {
    "iso:country":"US",
    "sg:address":"6728 State Rte 85",
    "sg:city":"Riverdale",
    "sg:classifiers":[
        {
            "category":"Autos & Motor Vehicles",
            "subcategory":"Automobile Sales",
            "type":"Retail Goods"
        }
    ],
    "sg:phone":"+1 678 709 2863",
    "sg:postcode":"30274",
    "sg:province":"GA",
    "sg:tags":[
        "used"
    ],
    "wof:name":"AAG Of Georgia",
    "wof:placetype":"venue"
},
  "geometry": {"coordinates":[-84.411571,33.580146],"type":"Point"}
}