{
  "type": "Feature",
  "properties": {
    "iso:country":"US",
    "sg:address":"1875 Gramercy Ct",
    "sg:city":"Atlanta",
    "sg:classifiers":[
        {
            "category":"Autos & Motor Vehicles",
            "subcategory":"Fuel & Gas Station",
            "type":"Retail Goods"
        }
    ],
    "sg:phone":"+1 770 394 8778",
    "sg:postcode":"30338",
    "sg:province":"GA",
    "sg:tags":[
        "station",
        "store"
    ],
    "wof:name":"Chevron Food Mart",
    "wof:placetype":"venue"
},
  "geometry": {"coordinates":[-84.31209699999999,33.953587],"type":"Point"}
}