{
  "type": "Feature",
  "properties": {
    "addr:full":"215 Lakewood Way SW 101 Atlanta GA 30315",
    "addr:housenumber":"215;101",
    "addr:postcode":"30315",
    "addr:street":"Lakewood Way Sw",
    "iso:country":"US",
    "sg:address":"215 Lakewood Way SW 101",
    "sg:city":"Atlanta",
    "sg:classifiers":[
        {
            "category":"Community Center",
            "type":"Public Place"
        }
    ],
    "sg:phone":"+1 404 658 7855",
    "sg:postcode":"30315",
    "sg:province":"GA",
    "sg:tags":[
        "recreation"
    ],
    "sg:website":"http://www.atlantaciviccenter.com",
    "wof:name":"Parks, Recreation & Cultural",
    "wof:placetype":"venue"
},
  "geometry": {"coordinates":[-84.39457899999999,33.700326],"type":"Point"}
}