{
  "type": "Feature",
  "properties": {
    "iso:country":"US",
    "sg:address":"1909 Tebeau St",
    "sg:city":"Waycross",
    "sg:classifiers":[
        {
            "category":"Health Services",
            "subcategory":"Medical Lab",
            "type":"Services"
        }
    ],
    "sg:phone":"+1 912 287 0965",
    "sg:postcode":"31501",
    "sg:province":"GA",
    "sg:tags":[
        "laboratory"
    ],
    "wof:name":"Laboratory Corp Of America",
    "wof:placetype":"venue"
},
  "geometry": {"coordinates":[-82.346255,31.228445],"type":"Point"}
}