{
  "type": "Feature",
  "properties": {
    "iso:country":"US",
    "sg:address":"583 Dripping Rock Rd",
    "sg:city":"Molena",
    "sg:classifiers":[
        {
            "category":"Organizations",
            "subcategory":"Religious Organization",
            "type":"Services"
        }
    ],
    "sg:phone":"+1 706 647 2751",
    "sg:postcode":"30258",
    "sg:province":"GA",
    "sg:tags":[
        "church"
    ],
    "wof:name":"Liberty Worship Ctr",
    "wof:placetype":"venue"
},
  "geometry": {"coordinates":[-84.507582,32.964818],"type":"Point"}
}