{
  "type": "Feature",
  "properties": {
    "iso:country":"US",
    "sg:address":"2581 Piedmont Road NE",
    "sg:city":"Atlanta",
    "sg:classifiers":[
        {
            "category":"Manufacturing",
            "subcategory":"Leather Goods",
            "type":"Manufacturing & Wholesale Goods"
        }
    ],
    "sg:phone":"+1 404 842 1616",
    "sg:postcode":"30324",
    "sg:province":"GA",
    "wof:name":"Vulcanos International Corporation",
    "wof:placetype":"venue"
},
  "geometry": {"coordinates":[-84.36738699999999,33.823968],"type":"Point"}
}