{
  "type": "Feature",
  "properties": {
    "addr:full":"125 Hambleton St Thomasville GA 31792",
    "addr:housenumber":"125",
    "addr:postcode":"31792",
    "addr:street":"Hambleton St",
    "iso:country":"US",
    "sg:address":"125 Hambleton St",
    "sg:city":"Thomasville",
    "sg:classifiers":[
        {
            "category":"Health Services",
            "subcategory":"Nursing And Care Facility",
            "type":"Services"
        }
    ],
    "sg:phone":"+1 229 551 0717",
    "sg:postcode":"31792",
    "sg:province":"GA",
    "sg:tags":[
        "home",
        "institution"
    ],
    "wof:name":"Pinnacle PLACE",
    "wof:placetype":"venue"
},
  "geometry": {"coordinates":[-83.987647,30.824746],"type":"Point"}
}