{
  "type": "Feature",
  "properties": {
    "addr:full":"2315 Ashton Ridge Dr Dacula GA 30019",
    "addr:housenumber":"2315",
    "addr:postcode":"ga 30019",
    "addr:street":"Ashton Ridge Dr",
    "iso:country":"US",
    "sg:address":"2315 Ashton Ridge Dr",
    "sg:city":"Dacula",
    "sg:classifiers":[
        {
            "category":"Organizations",
            "subcategory":"Community Association",
            "type":"Services"
        }
    ],
    "sg:phone":"+1 770 945 7768",
    "sg:postcode":"30019",
    "sg:province":"GA",
    "wof:name":"Laureate Delta Kappa",
    "wof:placetype":"venue"
},
  "geometry": {"coordinates":[-83.931573,34.060223],"type":"Point"}
}