{
  "type": "Feature",
  "properties": {
    "addr:full":"144 Riverchase Dr Woodstock GA 30188",
    "addr:housenumber":"144",
    "addr:postcode":"30188",
    "addr:street":"Riverchase Dr",
    "iso:country":"US",
    "sg:address":"144 Riverchase Dr",
    "sg:city":"Woodstock",
    "sg:classifiers":[
        {
            "category":"Local Transit",
            "type":"Transportation"
        }
    ],
    "sg:phone":"+1 770 924 5774",
    "sg:postcode":"30188",
    "sg:province":"GA",
    "sg:tags":[
        "passenger"
    ],
    "wof:name":"ATL Fancy Limousine",
    "wof:placetype":"venue"
},
  "geometry": {"coordinates":[-84.443466,34.097012],"type":"Point"}
}