{
  "type": "Feature",
  "properties": {
    "iso:country":"US",
    "sg:address":"2200 Rosemont Dr",
    "sg:city":"Columbus",
    "sg:classifiers":[
        {
            "category":"Health Services",
            "subcategory":"Doctor",
            "type":"Services"
        }
    ],
    "sg:phone":"+1 706 596 1895",
    "sg:postcode":"31904",
    "sg:province":"GA",
    "wof:name":"Narde Joseph A DDS",
    "wof:placetype":"venue"
},
  "geometry": {"coordinates":[-84.961529,32.500233],"type":"Point"}
}