{
  "type": "Feature",
  "properties": {
    "iso:country":"US",
    "sg:address":"357 Shire Way",
    "sg:city":"Lawrenceville",
    "sg:classifiers":[
        {
            "category":"Building & Trades",
            "subcategory":"Plumbing",
            "type":"Services"
        }
    ],
    "sg:phone":"+1 770 925 0744",
    "sg:postcode":"30044",
    "sg:province":"GA",
    "sg:tags":[
        "contractor"
    ],
    "wof:name":"Freds Plumbing",
    "wof:placetype":"venue"
},
  "geometry": {"coordinates":[-84.090825,33.892739],"type":"Point"}
}