{
  "type": "Feature",
  "properties": {
    "iso:country":"US",
    "sg:address":"4160 Wilbur Dr",
    "sg:city":"Columbus",
    "sg:classifiers":[
        {
            "category":"Building & Trades",
            "subcategory":"Construction",
            "type":"Services"
        }
    ],
    "sg:phone":"+1 706 681 8849",
    "sg:postcode":"31909",
    "sg:province":"GA",
    "sg:tags":[
        "resurfacing",
        "laying",
        "refinishing",
        "floor"
    ],
    "wof:name":"Precision Hardwood Flooring",
    "wof:placetype":"venue"
},
  "geometry": {"coordinates":[-84.921857,32.530521],"type":"Point"}
}