{
  "type": "Feature",
  "properties": {
    "addr:full":"2016 Village North Rd Atlanta GA 30338",
    "addr:housenumber":"2016",
    "addr:postcode":"30338",
    "addr:street":"Village North Rd",
    "iso:country":"US",
    "sg:address":"2016 Village North Rd",
    "sg:city":"Atlanta",
    "sg:classifiers":[
        {
            "category":"Shopping",
            "subcategory":"Computers & Home Electronics",
            "type":"Retail Goods"
        }
    ],
    "sg:phone":"+1 770 395 1705",
    "sg:postcode":"30338",
    "sg:province":"GA",
    "sg:tags":[
        "programing",
        "custom"
    ],
    "wof:name":"Paradigm Exchange",
    "wof:placetype":"venue"
},
  "geometry": {"coordinates":[-84.30662100000001,33.937378],"type":"Point"}
}