{
  "type": "Feature",
  "properties": {
    "addr:full":"41 Park Of Commerce Way Savannah GA 31405",
    "addr:housenumber":"41",
    "addr:postcode":"31405",
    "addr:street":"Park;Commerce Way",
    "iso:country":"US",
    "sg:address":"41 Park Of Commerce Way",
    "sg:city":"Savannah",
    "sg:classifiers":[
        {
            "category":"Building & Trades",
            "subcategory":"Cleaning & Sanitation",
            "type":"Services"
        },
        {
            "category":"Home & Garden",
            "subcategory":"Hardware",
            "type":"Retail Goods"
        }
    ],
    "sg:phone":"+1 912 239 9773",
    "sg:postcode":"31405",
    "sg:province":"GA",
    "sg:tags":[
        "supply",
        "room",
        "floor",
        "facility",
        "equipment",
        "waxing",
        "clean",
        "polishing",
        "janitor",
        "janitorial"
    ],
    "sg:website":"http://www.officecleanusa.com",
    "wof:name":"Office Clean Inc",
    "wof:placetype":"venue"
},
  "geometry": {"coordinates":[-81.16324,32.066565],"type":"Point"}
}