{
  "type": "Feature",
  "properties": {
    "addr:full":"124 N Mc Donough St Jonesboro GA 30236",
    "addr:housenumber":"124",
    "addr:postcode":"30236",
    "addr:street":"N Mc Donough St",
    "iso:country":"US",
    "sg:address":"124 N Mc Donough St",
    "sg:city":"Jonesboro",
    "sg:classifiers":[
        {
            "category":"Professional",
            "subcategory":"Secretarial Services",
            "type":"Services"
        }
    ],
    "sg:phone":"+1 770 473 7483",
    "sg:postcode":"30236",
    "sg:province":"GA",
    "sg:tags":[
        "reporting",
        "court"
    ],
    "wof:name":"Southern Crescent Court Rprtng",
    "wof:placetype":"venue"
},
  "geometry": {"coordinates":[-84.354106,33.521383],"type":"Point"}
}