{
  "type": "Feature",
  "properties": {
    "addr:full":"2000 Hamilton Rd Columbus GA 31904",
    "addr:housenumber":"2000",
    "addr:postcode":"31904",
    "addr:street":"Hamilton Rd",
    "iso:country":"US",
    "sg:address":"2000 Hamilton Rd",
    "sg:city":"Columbus",
    "sg:classifiers":[
        {
            "category":"Health Services",
            "subcategory":"Doctor",
            "type":"Services"
        }
    ],
    "sg:phone":"+1 706 324 4891",
    "sg:postcode":"31904",
    "sg:province":"GA",
    "sg:tags":[
        "ob"
    ],
    "wof:name":"Obstetrics/Gynclgc Ascts Colum",
    "wof:placetype":"venue"
},
  "geometry": {"coordinates":[-84.984627,32.483213],"type":"Point"}
}