{
  "type": "Feature",
  "properties": {
    "addr:full":"4644 Brittany Dr Evans GA 30809",
    "addr:housenumber":"4644",
    "addr:postcode":"30809",
    "addr:street":"Brittany Dr",
    "iso:country":"US",
    "sg:address":"4644 Brittany Dr",
    "sg:city":"Evans",
    "sg:classifiers":[
        {
            "category":"Building & Trades",
            "subcategory":"Construction",
            "type":"Services"
        }
    ],
    "sg:phone":"+1 706 830 5033",
    "sg:postcode":"30809",
    "sg:province":"GA",
    "sg:tags":[
        "restoration",
        "cleaning",
        "patio",
        "deck"
    ],
    "wof:name":"Envirowash",
    "wof:placetype":"venue"
},
  "geometry": {"coordinates":[-82.153706,33.535396],"type":"Point"}
}