{
  "type": "Feature",
  "properties": {
    "iso:country":"US",
    "sg:address":"262 Ocilla Hwy",
    "sg:city":"Fitzgerald",
    "sg:classifiers":[
        {
            "category":"Building & Trades",
            "subcategory":"Equipment Rental",
            "type":"Services"
        }
    ],
    "sg:phone":"+1 229 423 7368",
    "sg:postcode":"31750",
    "sg:province":"GA",
    "sg:tags":[
        "appliance",
        "furniture"
    ],
    "wof:name":"Quality Rentals",
    "wof:placetype":"venue"
},
  "geometry": {"coordinates":[-83.24645700000001,31.694492],"type":"Point"}
}