{
  "type": "Feature",
  "properties": {
    "iso:country":"US",
    "sg:address":"795 Holcomb Bridge Rd",
    "sg:city":"Roswell",
    "sg:classifiers":[
        {
            "category":"Banks & Credit Unions",
            "subcategory":"Bank",
            "type":"Services"
        }
    ],
    "sg:phone":"+1 770 642 6161",
    "sg:postcode":"30076",
    "sg:province":"GA",
    "sg:tags":[
        "cashing",
        "agency",
        "check"
    ],
    "wof:name":"Ace Cash Express",
    "wof:placetype":"venue"
},
  "geometry": {"coordinates":[-84.33669,34.02962],"type":"Point"}
}