{
  "type": "Feature",
  "properties": {
    "addr:full":"1320 1st St NE Moultrie GA 31768",
    "addr:housenumber":"1320",
    "addr:postcode":"31768",
    "addr:street":"1St St Ne",
    "iso:country":"US",
    "sg:address":"1320 1st St NE",
    "sg:city":"Moultrie",
    "sg:classifiers":[
        {
            "category":"Retail",
            "subcategory":"Auto Repair",
            "type":"Services"
        }
    ],
    "sg:phone":"+1 229 985 1709",
    "sg:postcode":"31768",
    "sg:province":"GA",
    "sg:tags":[
        "general"
    ],
    "wof:name":"Kents Darrell Garage",
    "wof:placetype":"venue"
},
  "geometry": {"coordinates":[-83.787543,31.193957],"type":"Point"}
}