{
  "type": "Feature",
  "properties": {
    "iso:country":"US",
    "sg:address":"3445 Peachtree Rd",
    "sg:city":"Atlanta",
    "sg:classifiers":[
        {
            "category":"Banks & Credit Unions",
            "subcategory":"Financial Services",
            "type":"Services"
        }
    ],
    "sg:phone":"+1 404 846 8291",
    "sg:postcode":"30305",
    "sg:province":"GA",
    "sg:tags":[
        "trust",
        "investment",
        "real estate"
    ],
    "wof:name":"Cousins Properties Inc",
    "wof:placetype":"venue"
},
  "geometry": {"coordinates":[-84.365098,33.848806],"type":"Point"}
}