{
  "type": "Feature",
  "properties": {
    "addr:full":"191 Carl Griffin Dr Savannah GA 31405",
    "addr:housenumber":"191",
    "addr:postcode":"31405",
    "addr:street":"Carl Griffin Dr",
    "iso:country":"US",
    "sg:address":"191 Carl Griffin Dr",
    "sg:city":"Savannah",
    "sg:classifiers":[
        {
            "category":"Government",
            "subcategory":"Jail",
            "type":"Public Place"
        }
    ],
    "sg:phone":"+1 912 652 3879",
    "sg:postcode":"31405",
    "sg:province":"GA",
    "sg:tags":[
        "support",
        "correctional",
        "institution",
        "facility"
    ],
    "wof:name":"Savannah Rydc",
    "wof:placetype":"venue"
},
  "geometry": {"coordinates":[-81.165555,32.067805],"type":"Point"}
}