{
  "type": "Feature",
  "properties": {
    "iso:country":"US",
    "sg:address":"1745 Pierce Arrow Pkwy",
    "sg:city":"Tucker",
    "sg:classifiers":[
        {
            "category":"Building & Trades",
            "subcategory":"Landscaping Services",
            "type":"Services"
        }
    ],
    "sg:phone":"+1 770 356 2135",
    "sg:postcode":"30084",
    "sg:province":"GA",
    "sg:tags":[
        "landscape",
        "contractor"
    ],
    "wof:name":"Beauty Scapes Of Georgia",
    "wof:placetype":"venue"
},
  "geometry": {"coordinates":[-84.215535,33.834803],"type":"Point"}
}