{
  "type": "Feature",
  "properties": {
    "iso:country":"US",
    "sg:address":"1715 Portrush Pl",
    "sg:city":"Alpharetta",
    "sg:classifiers":[
        {
            "category":"Professional",
            "subcategory":"Management & Consulting",
            "type":"Services"
        }
    ],
    "sg:phone":"+1 770 667 5293",
    "sg:postcode":"30005",
    "sg:province":"GA",
    "wof:name":"Protrust LLC",
    "wof:placetype":"venue"
},
  "geometry": {"coordinates":[-84.21828600000001,34.081917],"type":"Point"}
}