{
  "type": "Feature",
  "properties": {
    "iso:country":"US",
    "sg:address":"3925 Johns Creek Ct",
    "sg:city":"Suwanee",
    "sg:classifiers":[
        {
            "category":"Health Services",
            "subcategory":"Optometrist",
            "type":"Services"
        }
    ],
    "sg:phone":"+1 770 232 7844",
    "sg:postcode":"30024",
    "sg:province":"GA",
    "wof:name":"South Forsyth Eyecare",
    "wof:placetype":"venue"
},
  "geometry": {"coordinates":[-84.160599,34.069302],"type":"Point"}
}