{
  "type": "Feature",
  "properties": {
    "iso:country":"US",
    "sg:address":"1025 Main St",
    "sg:city":"Whitesburg",
    "sg:classifiers":[
        {
            "category":"Health Services",
            "subcategory":"Clinic",
            "type":"Services"
        }
    ],
    "sg:phone":"+1 770 834 3536",
    "sg:postcode":"30185",
    "sg:province":"GA",
    "wof:name":"Devine Health",
    "wof:placetype":"venue"
},
  "geometry": {"coordinates":[-84.91712099999999,33.498102],"type":"Point"}
}