{
  "type": "Feature",
  "properties": {
    "addr:full":"408 Johnston St Savannah GA 31405",
    "addr:housenumber":"408",
    "addr:postcode":"31405",
    "addr:street":"Johnston St",
    "iso:country":"US",
    "sg:address":"408 Johnston St",
    "sg:city":"Savannah",
    "sg:classifiers":[
        {
            "category":"Health Services",
            "subcategory":"Doctor",
            "type":"Services"
        }
    ],
    "sg:phone":"+1 912 354 2386",
    "sg:postcode":"31405",
    "sg:province":"GA",
    "sg:tags":[
        "medical"
    ],
    "wof:name":"Lange Stephen J Jr Dr",
    "wof:placetype":"venue"
},
  "geometry": {"coordinates":[-81.10468899999999,32.020723],"type":"Point"}
}