{
  "type": "Feature",
  "properties": {
    "addr:full":"3963 Saint George Terrace Hiram GA 30141",
    "addr:housenumber":"3963",
    "addr:postcode":"30141",
    "addr:street":"Saint George Terrace",
    "iso:country":"US",
    "sg:address":"3963 Saint George Terrace",
    "sg:city":"Hiram",
    "sg:classifiers":[
        {
            "category":"Retail",
            "subcategory":"Pet Boarding",
            "type":"Services"
        }
    ],
    "sg:phone":"+1 770 575 1423",
    "sg:postcode":"30141",
    "sg:province":"GA",
    "sg:tags":[
        "boarding/pet",
        "sitting"
    ],
    "sg:website":"www.SafeAtHomePetSitting.com",
    "wof:name":"Safe At Home Pet Sitting",
    "wof:placetype":"venue"
},
  "geometry": {"coordinates":[-84.711697,33.854478],"type":"Point"}
}