{
  "type": "Feature",
  "properties": {
    "addr:full":"801 W Paces Ferry Rd NW Atlanta GA 30327",
    "addr:housenumber":"801",
    "addr:postcode":"30327",
    "addr:street":"W Paces Ferry Rd Nw",
    "iso:country":"US",
    "sg:address":"801 W Paces Ferry Rd NW",
    "sg:city":"Atlanta",
    "sg:classifiers":[
        {
            "category":"Professional",
            "subcategory":"Lawyer & Legal Services",
            "type":"Services"
        }
    ],
    "sg:phone":"+1 404 233 9817",
    "sg:postcode":"30327",
    "sg:province":"GA",
    "wof:name":"Edward T M Garland Atty",
    "wof:placetype":"venue"
},
  "geometry": {"coordinates":[-84.41159399999999,33.848974],"type":"Point"}
}