{
  "type": "Feature",
  "properties": {
    "addr:full":"202 Garden Walk Way Loganville GA 30052",
    "addr:housenumber":"202",
    "addr:postcode":"30052",
    "addr:street":"Garden Walk Way",
    "iso:country":"US",
    "sg:address":"202 Garden Walk Way",
    "sg:city":"Loganville",
    "sg:classifiers":[
        {
            "category":"Manufacturing",
            "subcategory":"Building Materials",
            "type":"Manufacturing & Wholesale Goods"
        }
    ],
    "sg:phone":"+1 770 554 8474",
    "sg:postcode":"30052",
    "sg:province":"GA",
    "sg:tags":[
        "mfg",
        "wood",
        "kitchen",
        "cabinet"
    ],
    "wof:name":"Hane Custom Cabinetry",
    "wof:placetype":"venue"
},
  "geometry": {"coordinates":[-83.921161,33.854836],"type":"Point"}
}