{
  "type": "Feature",
  "properties": {
    "addr:full":"124 Powers Ferry Rd SE Ste B Marietta GA 30067",
    "addr:housenumber":"124",
    "addr:postcode":"30067",
    "addr:street":"Powers Ferry Rd Se Ste B",
    "iso:country":"US",
    "sg:address":"124 Powers Ferry Rd SE Ste B",
    "sg:city":"Marietta",
    "sg:classifiers":[
        {
            "category":"Personal",
            "subcategory":"Beauty Salon",
            "type":"Services"
        }
    ],
    "sg:phone":"+1 770 973 8336",
    "sg:postcode":"30067",
    "sg:province":"GA",
    "sg:tags":[
        "hair"
    ],
    "wof:name":"Today's Hair",
    "wof:placetype":"venue"
},
  "geometry": {"coordinates":[-84.508904,33.9491],"type":"Point"}
}