{
  "type": "Feature",
  "properties": {
    "addr:full":"445 Ansley Dr Roswell GA 30076",
    "addr:housenumber":"445",
    "addr:postcode":"30076",
    "addr:street":"Ansley Dr",
    "iso:country":"US",
    "sg:address":"445 Ansley Dr",
    "sg:city":"Roswell",
    "sg:classifiers":[
        {
            "category":"Professional",
            "subcategory":"Management & Consulting",
            "type":"Services"
        }
    ],
    "sg:phone":"+1 770 587 1848",
    "sg:postcode":"30076",
    "sg:province":"GA",
    "sg:tags":[
        "business"
    ],
    "wof:name":"Williamson Consultants Group",
    "wof:placetype":"venue"
},
  "geometry": {"coordinates":[-84.304146,34.022179],"type":"Point"}
}