{
  "type": "Feature",
  "properties": {
    "iso:country":"US",
    "sg:address":"2542 Bexley Ct",
    "sg:city":"Snellville",
    "sg:classifiers":[
        {
            "category":"Professional",
            "type":"Services"
        }
    ],
    "sg:phone":"+1 770 979 6281",
    "sg:postcode":"30078",
    "sg:province":"GA",
    "sg:tags":[
        "establishment"
    ],
    "wof:name":"Quest Technologies Inc",
    "wof:placetype":"venue"
},
  "geometry": {"coordinates":[-84.03810199999999,33.882537],"type":"Point"}
}