{
  "type": "Feature",
  "properties": {
    "addr:full":"3250 Peachtree Industrial Blvd Duluth GA 30096",
    "addr:housenumber":"3250",
    "addr:postcode":"30096",
    "addr:street":"Peachtree Industrial Blvd",
    "iso:country":"US",
    "sg:address":"3250 Peachtree Industrial Blvd",
    "sg:city":"Duluth",
    "sg:classifiers":[
        {
            "category":"Professional",
            "subcategory":"Art Services",
            "type":"Services"
        }
    ],
    "sg:phone":"+1 770 622 1900",
    "sg:postcode":"30096",
    "sg:province":"GA",
    "sg:tags":[
        "designer",
        "display",
        "producer"
    ],
    "wof:name":"Design Initiative Group Holdings",
    "wof:placetype":"venue"
},
  "geometry": {"coordinates":[-84.161706,34.018557],"type":"Point"}
}