{
  "type": "Feature",
  "properties": {
    "addr:full":"2135 Liddell Dr NE Atlanta GA 30324",
    "addr:housenumber":"2135",
    "addr:postcode":"30324",
    "addr:street":"Liddell Dr Ne",
    "iso:country":"US",
    "sg:address":"2135 Liddell Dr NE",
    "sg:city":"Atlanta",
    "sg:classifiers":[
        {
            "category":"Professional",
            "subcategory":"Management & Consulting",
            "type":"Services"
        },
        {
            "category":"Professional",
            "subcategory":"Advertising",
            "type":"Services"
        },
        {
            "category":"Shopping",
            "subcategory":"Pets & Pet Supplies",
            "type":"Retail Goods"
        }
    ],
    "sg:phone":"+1 404 897 3602",
    "sg:postcode":"30324",
    "sg:province":"GA",
    "sg:tags":[
        "marketing",
        "training",
        "program",
        "consultant"
    ],
    "wof:name":"Barking Hound Village Marketing Office",
    "wof:placetype":"venue"
},
  "geometry": {"coordinates":[-84.361949,33.811716],"type":"Point"}
}