{
  "type": "Feature",
  "properties": {
    "addr:full":"4825 Kenilworth Dr Stone Mountain GA 30083",
    "addr:housenumber":"4825",
    "addr:postcode":"30083",
    "addr:street":"Kenilworth Dr",
    "iso:country":"US",
    "sg:address":"4825 Kenilworth Dr",
    "sg:city":"Stone Mountain",
    "sg:classifiers":[
        {
            "category":"Education",
            "subcategory":"Special Training",
            "type":"Public Place"
        }
    ],
    "sg:phone":"+1 404 294 1449",
    "sg:postcode":"30083",
    "sg:province":"GA",
    "sg:tags":[
        "program",
        "enrichment"
    ],
    "wof:name":"Bettys Enrichment Program",
    "wof:placetype":"venue"
},
  "geometry": {"coordinates":[-84.192252,33.793857],"type":"Point"}
}