{
  "type": "Feature",
  "properties": {
    "addr:full":"1790 Atkinson Rd Lawrenceville GA 30043",
    "addr:housenumber":"1790",
    "addr:postcode":"30043",
    "addr:street":"Atkinson Rd",
    "iso:country":"US",
    "sg:address":"1790 Atkinson Rd",
    "sg:city":"Lawrenceville",
    "sg:classifiers":[
        {
            "category":"Professional",
            "subcategory":"Lawyer & Legal Services",
            "type":"Services"
        }
    ],
    "sg:phone":"+1 678 990 9676",
    "sg:postcode":"30043",
    "sg:province":"GA",
    "wof:name":"Day Charles T III Attorney At Law",
    "wof:placetype":"venue"
},
  "geometry": {"coordinates":[-84.07690599999999,33.973029],"type":"Point"}
}