{
  "type": "Feature",
  "properties": {
    "iso:country":"US",
    "sg:address":"5337 Orchard Pl",
    "sg:city":"Morrow",
    "sg:classifiers":[
        {
            "category":"Manufacturing",
            "subcategory":"Food",
            "type":"Manufacturing & Wholesale Goods"
        }
    ],
    "sg:phone":"+1 404 299 6662",
    "sg:postcode":"30260",
    "sg:province":"GA",
    "sg:tags":[
        "delivers",
        "cookie",
        "mfg"
    ],
    "wof:name":"Cookiegrams",
    "wof:placetype":"venue"
},
  "geometry": {"coordinates":[-84.346311,33.608968],"type":"Point"}
}