{
  "type": "Feature",
  "properties": {
    "addr:full":"45 Medical Center Dr Dawsonville GA 30529",
    "addr:housenumber":"45",
    "addr:postcode":"30529",
    "addr:street":"Medical Center Dr",
    "iso:country":"US",
    "sg:address":"45 Medical Center Dr",
    "sg:city":"Dawsonville",
    "sg:classifiers":[
        {
            "category":"Health Services",
            "subcategory":"Doctor",
            "type":"Services"
        }
    ],
    "sg:phone":"+1 706 216 3238",
    "sg:postcode":"30529",
    "sg:province":"GA",
    "sg:tags":[
        "physician",
        "surgeon"
    ],
    "sg:website":"www.nghs.com",
    "wof:name":"Neighborhood Healthcare Ctr",
    "wof:placetype":"venue"
},
  "geometry": {"coordinates":[-83.468583,34.218949],"type":"Point"}
}