{
  "type": "Feature",
  "properties": {
    "iso:country":"US",
    "sg:address":"466 Asbury Rd",
    "sg:city":"Temple",
    "sg:classifiers":[
        {
            "category":"Retail",
            "subcategory":"Car Wash",
            "type":"Services"
        }
    ],
    "sg:phone":"+1 770 562 0774",
    "sg:postcode":"30179",
    "sg:province":"GA",
    "sg:tags":[
        "carwash"
    ],
    "wof:name":"Michael Cowser",
    "wof:placetype":"venue"
},
  "geometry": {"coordinates":[-85.03414100000001,33.766397],"type":"Point"}
}