{
  "type": "Feature",
  "properties": {
    "addr:full":"65 Black Rock Ct Oxford GA 30054",
    "addr:housenumber":"65",
    "addr:postcode":"30054",
    "addr:street":"Black Rock Ct",
    "iso:country":"US",
    "sg:address":"65 Black Rock Ct",
    "sg:city":"Oxford",
    "sg:classifiers":[
        {
            "category":"Banks & Credit Unions",
            "subcategory":"Investment Brokerage",
            "type":"Services"
        }
    ],
    "sg:phone":"+1 770 554 1285",
    "sg:postcode":"30054",
    "sg:province":"GA",
    "wof:name":"Edward Jones Investments",
    "wof:placetype":"venue"
},
  "geometry": {"coordinates":[-83.92130400000001,33.699771],"type":"Point"}
}