{
  "type": "Feature",
  "properties": {
    "iso:country":"US",
    "sg:address":"115 Airport Rd",
    "sg:city":"Newnan",
    "sg:classifiers":[
        {
            "category":"Professional",
            "type":"Services"
        }
    ],
    "sg:phone":"+1 770 253 9090",
    "sg:postcode":"30263",
    "sg:province":"GA",
    "wof:name":"Ronig Air Service",
    "wof:placetype":"venue"
},
  "geometry": {"coordinates":[-84.77685099999999,33.311524],"type":"Point"}
}