{
  "type": "Feature",
  "properties": {
    "addr:full":"1405 Home Place Dr Lawrenceville GA 30043",
    "addr:housenumber":"1405",
    "addr:postcode":"30043",
    "addr:street":"Home Place Dr",
    "iso:country":"US",
    "sg:address":"1405 Home Place Dr",
    "sg:city":"Lawrenceville",
    "sg:classifiers":[
        {
            "category":"Food & Beverages",
            "subcategory":"Groceries & Convenience Stores",
            "type":"Retail Goods"
        }
    ],
    "sg:phone":"+1 770 962 2598",
    "sg:postcode":"30043",
    "sg:province":"GA",
    "wof:name":"DS Convenience Store",
    "wof:placetype":"venue"
},
  "geometry": {"coordinates":[-84.04703600000001,33.978738],"type":"Point"}
}