{
  "type": "Feature",
  "properties": {
    "iso:country":"US",
    "sg:address":"535 E May St",
    "sg:city":"Dalton",
    "sg:classifiers":[
        {
            "category":"Government",
            "subcategory":"Office",
            "type":"Public Place"
        }
    ],
    "sg:phone":"+1 706 278 6936",
    "sg:postcode":"30701",
    "sg:province":"GA",
    "sg:tags":[
        "village"
    ],
    "wof:name":"Dalton Building Inspector",
    "wof:placetype":"venue"
},
  "geometry": {"coordinates":[-84.93503200000001,34.488007],"type":"Point"}
}