{
  "type": "Feature",
  "properties": {
    "addr:full":"500 Technology Ct SE Smyrna GA 30082",
    "addr:housenumber":"500",
    "addr:postcode":"30082",
    "addr:street":"Technology Ct Se",
    "iso:country":"US",
    "sg:address":"500 Technology Ct SE",
    "sg:city":"Smyrna",
    "sg:classifiers":[
        {
            "category":"Manufacturing",
            "subcategory":"Tools & Machinery",
            "type":"Manufacturing & Wholesale Goods"
        }
    ],
    "sg:phone":"+1 770 319 2470",
    "sg:postcode":"30082",
    "sg:province":"GA",
    "sg:tags":[
        "analytical",
        "mfg",
        "instr"
    ],
    "wof:name":"Thermo Andersen Inc",
    "wof:placetype":"venue"
},
  "geometry": {"coordinates":[-84.499059,33.825773],"type":"Point"}
}