{
  "type": "Feature",
  "properties": {
    "iso:country":"US",
    "sg:address":"2278 Ingleside Ave",
    "sg:city":"Macon",
    "sg:classifiers":[
        {
            "category":"Insurance",
            "subcategory":"Insurance Agent",
            "type":"Services"
        }
    ],
    "sg:phone":"+1 478 841 2100",
    "sg:postcode":"31204",
    "sg:province":"GA",
    "wof:name":"Best Insurance Group",
    "wof:placetype":"venue"
},
  "geometry": {"coordinates":[-83.652303,32.853669],"type":"Point"}
}