{
  "type": "Feature",
  "properties": {
    "iso:country":"US",
    "sg:address":"One Securities Ctr 3490 Piedmont Rd NE Ste 110",
    "sg:city":"Atlanta",
    "sg:classifiers":[
        {
            "category":"Health Services",
            "subcategory":"Dentist",
            "type":"Services"
        }
    ],
    "sg:phone":"+1 404 266 1300",
    "sg:postcode":"30326",
    "sg:province":"GA",
    "sg:website":"www.buckheaddentalassociates.com",
    "wof:name":"Buckhead Dental Associates PC",
    "wof:placetype":"venue"
},
  "geometry": {"coordinates":[-84.37656800000001,33.848348],"type":"Point"}
}