{
  "type": "Feature",
  "properties": {
    "iso:country":"US",
    "sg:address":"114 S Hulin Ave",
    "sg:city":"Tignall",
    "sg:classifiers":[
        {
            "category":"Banks & Credit Unions",
            "subcategory":"Bank",
            "type":"Services"
        }
    ],
    "sg:phone":"+1 706 285 2195",
    "sg:postcode":"30668",
    "sg:province":"GA",
    "wof:name":"Farmers & Merchants Bank",
    "wof:placetype":"venue"
},
  "geometry": {"coordinates":[-82.742419,33.860048],"type":"Point"}
}