{
  "type": "Feature",
  "properties": {
    "iso:country":"US",
    "sg:address":"2000 Haymarket Pl SE",
    "sg:city":"Conyers",
    "sg:classifiers":[
        {
            "category":"Professional",
            "subcategory":"Business Services",
            "type":"Services"
        }
    ],
    "sg:phone":"+1 770 679 1169",
    "sg:postcode":"30013",
    "sg:province":"GA",
    "wof:name":"Mdg Enterprise Inc",
    "wof:placetype":"venue"
},
  "geometry": {"coordinates":[-84.00858599999999,33.636838],"type":"Point"}
}