{
  "type": "Feature",
  "properties": {
    "iso:country":"US",
    "sg:address":"17 Lyle Field Rd",
    "sg:city":"Jefferson",
    "sg:classifiers":[
        {
            "category":"Building & Trades",
            "subcategory":"Construction",
            "type":"Services"
        }
    ],
    "sg:phone":"+1 706 654 9135",
    "sg:postcode":"30549",
    "sg:province":"GA",
    "sg:tags":[
        "maker",
        "cabinet"
    ],
    "wof:name":"Stewart Custom Svc Inc",
    "wof:placetype":"venue"
},
  "geometry": {"coordinates":[-83.564956,34.168713],"type":"Point"}
}