{
  "type": "Feature",
  "properties": {
    "iso:country":"US",
    "sg:address":"156 Bethesda Church Rd",
    "sg:city":"Lawrenceville",
    "sg:classifiers":[
        {
            "category":"Professional",
            "type":"Services"
        }
    ],
    "sg:phone":"+1 770 923 1094",
    "sg:postcode":"30044",
    "sg:province":"GA",
    "sg:tags":[
        "establishment"
    ],
    "wof:name":"Davis Development Co",
    "wof:placetype":"venue"
},
  "geometry": {"coordinates":[-84.08356499999999,33.911934],"type":"Point"}
}