{
  "type": "Feature",
  "properties": {
    "iso:country":"US",
    "sg:address":"112 Mall Rd",
    "sg:city":"Dublin",
    "sg:classifiers":[
        {
            "category":"Utilities",
            "subcategory":"Mobile Phone",
            "type":"Services"
        },
        {
            "category":"Shopping",
            "subcategory":"Mobile Phones",
            "type":"Retail Goods"
        },
        {
            "category":"Utilities",
            "subcategory":"Telephone",
            "type":"Services"
        }
    ],
    "sg:phone":"+1 478 272 9619",
    "sg:postcode":"31021",
    "sg:province":"GA",
    "sg:tags":[
        "equipment",
        "communication",
        "cellular",
        "supply"
    ],
    "sg:website":"http://www.verizonwireless.com",
    "wof:name":"Verizon",
    "wof:placetype":"venue"
},
  "geometry": {"coordinates":[-82.953755,32.541806],"type":"Point"}
}