{
  "type": "Feature",
  "properties": {
    "iso:country":"US",
    "sg:address":"12 S Wall St",
    "sg:city":"Cartersville",
    "sg:classifiers":[
        {
            "category":"Wholesale",
            "subcategory":"Non-durable Goods",
            "type":"Manufacturing & Wholesale Goods"
        }
    ],
    "sg:phone":"+1 770 598 5296",
    "sg:postcode":"30120",
    "sg:province":"GA",
    "wof:name":"Sugarbakers",
    "wof:placetype":"venue"
},
  "geometry": {"coordinates":[-84.795239,34.165365],"type":"Point"}
}