{
  "type": "Feature",
  "properties": {
    "addr:full":"425 Gregory Ln Acworth GA 30102",
    "addr:housenumber":"425",
    "addr:postcode":"30102",
    "addr:street":"Gregory Ln",
    "iso:country":"US",
    "sg:address":"425 Gregory Ln",
    "sg:city":"Acworth",
    "sg:classifiers":[
        {
            "category":"Building & Trades",
            "subcategory":"Electrical",
            "type":"Services"
        }
    ],
    "sg:phone":"+1 770 926 6134",
    "sg:postcode":"30102",
    "sg:province":"GA",
    "sg:tags":[
        "electrician"
    ],
    "wof:name":"Motes Electrical Contractors Inc",
    "wof:placetype":"venue"
},
  "geometry": {"coordinates":[-84.575997,34.081231],"type":"Point"}
}