{
  "type": "Feature",
  "properties": {
    "addr:full":"430 Little New York Rd Carrollton GA 30116",
    "addr:housenumber":"430",
    "addr:postcode":"30116",
    "addr:street":"Little New York Rd",
    "iso:country":"US",
    "sg:address":"430 Little New York Rd",
    "sg:city":"Carrollton",
    "sg:classifiers":[
        {
            "category":"Building & Trades",
            "subcategory":"Electrical",
            "type":"Services"
        }
    ],
    "sg:phone":"+1 770 832 2509",
    "sg:postcode":"30116",
    "sg:province":"GA",
    "sg:tags":[
        "electrical",
        "contractor"
    ],
    "wof:name":"Advantage Electric",
    "wof:placetype":"venue"
},
  "geometry": {"coordinates":[-84.973296,33.518054],"type":"Point"}
}