{
  "type": "Feature",
  "properties": {
    "iso:country":"US",
    "sg:address":"1855 Central Ave",
    "sg:city":"Augusta",
    "sg:classifiers":[
        {
            "category":"Restaurant",
            "type":"Food & Drink"
        }
    ],
    "sg:phone":"+1 706 733 3505",
    "sg:postcode":"30904",
    "sg:province":"GA",
    "sg:tags":[
        "eating"
    ],
    "wof:name":"Cafe Du Teau",
    "wof:placetype":"venue"
},
  "geometry": {"coordinates":[-82.002573,33.468815],"type":"Point"}
}