{
  "type": "Feature",
  "properties": {
    "iso:country":"US",
    "sg:address":"909 Mitchell Bridge Rd",
    "sg:city":"Chatsworth",
    "sg:classifiers":[
        {
            "category":"Shopping",
            "type":"Retail Goods"
        }
    ],
    "sg:phone":"+1 706 695 2757",
    "sg:postcode":"30705",
    "sg:province":"GA",
    "sg:tags":[
        "cosmetic",
        "perfume"
    ],
    "wof:name":"Mary Kay Cosmetics",
    "wof:placetype":"venue"
},
  "geometry": {"coordinates":[-84.827935,34.811651],"type":"Point"}
}