{
  "type": "Feature",
  "properties": {
    "iso:country":"US",
    "sg:address":"3404 Clairmont Rd NE",
    "sg:city":"Atlanta",
    "sg:classifiers":[
        {
            "category":"Retail",
            "subcategory":"Laundry & Dry Cleaning",
            "type":"Services"
        }
    ],
    "sg:phone":"+1 404 634 3944",
    "sg:postcode":"30319",
    "sg:province":"GA",
    "sg:tags":[
        "cleaner",
        "commercial"
    ],
    "wof:name":"Young Cleaners",
    "wof:placetype":"venue"
},
  "geometry": {"coordinates":[-84.311699,33.8582],"type":"Point"}
}