{
  "type": "Feature",
  "properties": {
    "addr:full":"2412 Red Oak Dr Waycross GA 31501",
    "addr:housenumber":"2412",
    "addr:postcode":"31501",
    "addr:street":"Red Oak Dr",
    "iso:country":"US",
    "sg:address":"2412 Red Oak Dr",
    "sg:city":"Waycross",
    "sg:classifiers":[
        {
            "category":"Professional",
            "type":"Services"
        }
    ],
    "sg:phone":"+1 912 285 3313",
    "sg:postcode":"31501",
    "sg:province":"GA",
    "wof:name":"Project Fishing Inc",
    "wof:placetype":"venue"
},
  "geometry": {"coordinates":[-82.366322,31.250208],"type":"Point"}
}