{
  "type": "Feature",
  "properties": {
    "addr:full":"5555 Glenridge Dr NE Atlanta GA 30342",
    "addr:housenumber":"5555",
    "addr:postcode":"30342",
    "addr:street":"Glenridge Dr Ne",
    "iso:country":"US",
    "sg:address":"5555 Glenridge Dr NE",
    "sg:city":"Atlanta",
    "sg:classifiers":[
        {
            "category":"Professional",
            "subcategory":"Management & Consulting",
            "type":"Services"
        }
    ],
    "sg:phone":"+1 404 459 5955",
    "sg:postcode":"30342",
    "sg:province":"GA",
    "sg:tags":[
        "consultant"
    ],
    "wof:name":"Innova Consulting",
    "wof:placetype":"venue"
},
  "geometry": {"coordinates":[-84.36757900000001,33.906466],"type":"Point"}
}