{
  "type": "Feature",
  "properties": {
    "addr:full":"1600 Macon Rd Perry GA 31069",
    "addr:housenumber":"1600",
    "addr:postcode":"31069",
    "addr:street":"Macon Rd",
    "iso:country":"US",
    "sg:address":"1600 Macon Rd",
    "sg:city":"Perry",
    "sg:classifiers":[
        {
            "category":"Retail",
            "subcategory":"Auto Rental",
            "type":"Services"
        }
    ],
    "sg:phone":"+1 478 988 4008",
    "sg:postcode":"31069",
    "sg:province":"GA",
    "sg:tags":[
        "renting",
        "automobile",
        "passenger",
        "car"
    ],
    "wof:name":"Enterprise Rent-A-Car",
    "wof:placetype":"venue"
},
  "geometry": {"coordinates":[-83.72904699999999,32.472653],"type":"Point"}
}