{
  "type": "Feature",
  "properties": {
    "iso:country":"US",
    "sg:address":"2969 Kaley Dr NW",
    "sg:city":"Kennesaw",
    "sg:classifiers":[
        {
            "category":"Manufacturing",
            "subcategory":"Tools & Machinery",
            "type":"Manufacturing & Wholesale Goods"
        }
    ],
    "sg:phone":"+1 770 514 9676",
    "sg:postcode":"30152",
    "sg:province":"GA",
    "sg:tags":[
        "dental",
        "product",
        "mfg"
    ],
    "wof:name":"Dentsply International Inc",
    "wof:placetype":"venue"
},
  "geometry": {"coordinates":[-84.63830400000001,34.016014],"type":"Point"}
}