{
  "type": "Feature",
  "properties": {
    "iso:country":"US",
    "sg:address":"627 N Marietta Pkwy",
    "sg:city":"Marietta",
    "sg:classifiers":[
        {
            "category":"Utilities",
            "subcategory":"Electric",
            "type":"Services"
        }
    ],
    "sg:phone":"+1 770 794 5240",
    "sg:postcode":"30060",
    "sg:province":"GA",
    "wof:name":"Marietta City of",
    "wof:placetype":"venue"
},
  "geometry": {"coordinates":[-84.532758,33.959317],"type":"Point"}
}