{
  "type": "Feature",
  "properties": {
    "addr:full":"2391 Montevideo Rd Elberton GA 30635",
    "addr:housenumber":"2391",
    "addr:postcode":"30635",
    "addr:street":"Montevideo Rd",
    "iso:country":"US",
    "sg:address":"2391 Montevideo Rd",
    "sg:city":"Elberton",
    "sg:classifiers":[
        {
            "category":"Building & Trades",
            "subcategory":"Construction",
            "type":"Services"
        }
    ],
    "sg:phone":"+1 706 283 2286",
    "sg:postcode":"30635",
    "sg:province":"GA",
    "sg:tags":[
        "house"
    ],
    "wof:name":"Jimmy Carnes Construction",
    "wof:placetype":"venue"
},
  "geometry": {"coordinates":[-82.792844,34.275628],"type":"Point"}
}