{
  "type": "Feature",
  "properties": {
    "addr:full":"6043 New Jesup Hwy Brunswick GA 31523",
    "addr:housenumber":"6043",
    "addr:postcode":"31523",
    "addr:street":"New Jesup Hwy",
    "iso:country":"US",
    "sg:address":"6043 New Jesup Hwy",
    "sg:city":"Brunswick",
    "sg:classifiers":[
        {
            "category":"Utilities",
            "subcategory":"Natural Gas",
            "type":"Services"
        }
    ],
    "sg:phone":"+1 912 264 9777",
    "sg:postcode":"31523",
    "sg:province":"GA",
    "sg:tags":[
        "distribution"
    ],
    "wof:name":"Infinite Energy",
    "wof:placetype":"venue"
},
  "geometry": {"coordinates":[-81.540279,31.238958],"type":"Point"}
}