{
  "type": "Feature",
  "properties": {
    "addr:full":"113 W Sheraton Dr Washington GA 30673",
    "addr:housenumber":"113",
    "addr:postcode":"30673",
    "addr:street":"W Sheraton Dr",
    "iso:country":"US",
    "sg:address":"113 W Sheraton Dr",
    "sg:city":"Washington",
    "sg:classifiers":[
        {
            "category":"Organizations",
            "subcategory":"Religious Organization",
            "type":"Services"
        }
    ],
    "sg:phone":"+1 706 678 7331",
    "sg:postcode":"30673",
    "sg:province":"GA",
    "wof:name":"Little Rver Untd Mthdst Church",
    "wof:placetype":"venue"
},
  "geometry": {"coordinates":[-82.72327900000001,33.734966],"type":"Point"}
}