{
  "type": "Feature",
  "properties": {
    "iso:country":"US",
    "sg:address":"2571 Country Farm Trce",
    "sg:city":"Powder Springs",
    "sg:classifiers":[
        {
            "category":"Building & Trades",
            "subcategory":"Landscaping Services",
            "type":"Services"
        }
    ],
    "sg:phone":"+1 770 439 9898",
    "sg:postcode":"30127",
    "sg:province":"GA",
    "wof:name":"Armstrong Cleaning & Lawn Svc",
    "wof:placetype":"venue"
},
  "geometry": {"coordinates":[-84.64413500000001,33.891996],"type":"Point"}
}