{
  "type": "Feature",
  "properties": {
    "addr:full":"2782 Marietta Hwy Canton GA 30114",
    "addr:housenumber":"2782",
    "addr:postcode":"30114",
    "addr:street":"Marietta Hwy",
    "iso:country":"US",
    "sg:address":"2782 Marietta Hwy",
    "sg:city":"Canton",
    "sg:classifiers":[
        {
            "category":"Banks & Credit Unions",
            "subcategory":"Financial Services",
            "type":"Services"
        }
    ],
    "sg:phone":"+1 770 479 5831",
    "sg:postcode":"30114",
    "sg:province":"GA",
    "sg:tags":[
        "broker",
        "mortgage"
    ],
    "wof:name":"Wachovia Mortgage Corporation",
    "wof:placetype":"venue"
},
  "geometry": {"coordinates":[-84.50720200000001,34.218952],"type":"Point"}
}