{
  "type": "Feature",
  "properties": {
    "addr:full":"32 Tarleton Way Mableton GA 30126",
    "addr:housenumber":"32",
    "addr:postcode":"30126",
    "addr:street":"Tarleton Way",
    "iso:country":"US",
    "sg:address":"32 Tarleton Way",
    "sg:city":"Mableton",
    "sg:classifiers":[
        {
            "category":"Building & Trades",
            "subcategory":"Cleaning & Sanitation",
            "type":"Services"
        }
    ],
    "sg:phone":"+1 770 944 1103",
    "sg:postcode":"30126",
    "sg:province":"GA",
    "sg:tags":[
        "janitor"
    ],
    "wof:name":"Byrd Cleaning Svc",
    "wof:placetype":"venue"
},
  "geometry": {"coordinates":[-84.53282900000001,33.788677],"type":"Point"}
}