{
  "type": "Feature",
  "properties": {
    "iso:country":"US",
    "sg:address":"7565 Industrial Ct",
    "sg:city":"Alpharetta",
    "sg:classifiers":[
        {
            "category":"Wholesale",
            "subcategory":"Electrical",
            "type":"Manufacturing & Wholesale Goods"
        }
    ],
    "sg:phone":"+1 770 888 7703",
    "sg:postcode":"30004",
    "sg:province":"GA",
    "sg:tags":[
        "alarm",
        "burglar",
        "system"
    ],
    "wof:name":"Secured Perimeters",
    "wof:placetype":"venue"
},
  "geometry": {"coordinates":[-84.251008,34.136815],"type":"Point"}
}