{
  "type": "Feature",
  "properties": {
    "iso:country":"US",
    "sg:address":"1390 Indian Trail Lilburn Rd",
    "sg:city":"Norcross",
    "sg:classifiers":[
        {
            "category":"Manufacturing",
            "subcategory":"Tools & Machinery",
            "type":"Manufacturing & Wholesale Goods"
        },
        {
            "category":"Home & Garden",
            "subcategory":"Garden Supply",
            "type":"Retail Goods"
        },
        {
            "category":"Autos & Motor Vehicles",
            "subcategory":"Auto Supplies",
            "type":"Retail Goods"
        }
    ],
    "sg:phone":"+1 770 381 1997",
    "sg:postcode":"30093",
    "sg:province":"GA",
    "sg:tags":[
        "engine",
        "lawn",
        "landscaping",
        "mowers-sharpening",
        "gasoline",
        "mower",
        "equipment",
        "repairing"
    ],
    "sg:website":"http://www.turfmachinecompany.com",
    "wof:name":"Turf Machine Co Inc",
    "wof:placetype":"venue"
},
  "geometry": {"coordinates":[-84.164681,33.917939],"type":"Point"}
}