{
  "type": "Feature",
  "properties": {
    "iso:country":"US",
    "sg:address":"8134 Geiger St NW",
    "sg:city":"Covington",
    "sg:classifiers":[
        {
            "category":"Education",
            "subcategory":"Special Training",
            "type":"Public Place"
        }
    ],
    "sg:phone":"+1 770 787 2778",
    "sg:postcode":"30014",
    "sg:province":"GA",
    "sg:tags":[
        "reading",
        "instruction",
        "improvement"
    ],
    "wof:name":"Literacy Volunteer-Netwon Cnty",
    "wof:placetype":"venue"
},
  "geometry": {"coordinates":[-83.87573500000001,33.609974],"type":"Point"}
}