{
  "type": "Feature",
  "properties": {
    "iso:country":"US",
    "sg:address":"2126 Weybridge Dr",
    "sg:city":"Jonesboro",
    "sg:classifiers":[
        {
            "category":"Professional",
            "type":"Services"
        }
    ],
    "sg:phone":"+1 770 477 1832",
    "sg:postcode":"30236",
    "sg:province":"GA",
    "wof:name":"Jita Inc",
    "wof:placetype":"venue"
},
  "geometry": {"coordinates":[-84.320714,33.556503],"type":"Point"}
}