{
  "type": "Feature",
  "properties": {
    "iso:country":"US",
    "sg:address":"12350 Arnold Mill Rd",
    "sg:city":"Alpharetta",
    "sg:classifiers":[
        {
            "category":"Restaurant",
            "type":"Food & Drink"
        }
    ],
    "sg:menulink":"http://www.allmenus.com/ga/roswell-alpharetta/232781-mangia-pizza/menu/",
    "sg:phone":"+1 678 867 0200",
    "sg:postcode":"30004",
    "sg:province":"GA",
    "sg:tags":[
        "american",
        "pizza"
    ],
    "wof:name":"Mangia Pizza",
    "wof:placetype":"venue"
},
  "geometry": {"coordinates":[-84.35811699999999,34.082382],"type":"Point"}
}