{
  "type": "Feature",
  "properties": {
    "iso:country":"US",
    "sg:address":"461 State Rte 247",
    "sg:city":"Bonaire",
    "sg:classifiers":[
        {
            "category":"Manufacturing",
            "subcategory":"Wood Products",
            "type":"Manufacturing & Wholesale Goods"
        }
    ],
    "sg:phone":"+1 478 929 2238",
    "sg:postcode":"31005",
    "sg:province":"GA",
    "sg:tags":[
        "pallet",
        "skid"
    ],
    "wof:name":"M W Pallet Co",
    "wof:placetype":"venue"
},
  "geometry": {"coordinates":[-83.59754700000001,32.55959],"type":"Point"}
}