{
  "type": "Feature",
  "properties": {
    "iso:country":"US",
    "sg:address":"1339 Fairview Dr",
    "sg:city":"Moultrie",
    "sg:classifiers":[
        {
            "category":"Professional",
            "subcategory":"Management & Consulting",
            "type":"Services"
        }
    ],
    "sg:phone":"+1 229 985 2242",
    "sg:postcode":"31768",
    "sg:province":"GA",
    "wof:name":"Pro Tech Ventures L L C",
    "wof:placetype":"venue"
},
  "geometry": {"coordinates":[-83.79387,31.160899],"type":"Point"}
}