{
  "type": "Feature",
  "properties": {
    "addr:full":"3201 Cains Hill Pl NW Atlanta GA 30305",
    "addr:housenumber":"3201",
    "addr:postcode":"30305",
    "addr:street":"Cains Hill Pl Nw",
    "iso:country":"US",
    "sg:address":"3201 Cains Hill Pl NW",
    "sg:city":"Atlanta",
    "sg:classifiers":[
        {
            "category":"Social Services",
            "subcategory":"Child Care",
            "type":"Services"
        },
        {
            "category":"Education",
            "subcategory":"School",
            "type":"Public Place"
        }
    ],
    "sg:phone":"+1 404 233 2128",
    "sg:postcode":"30305",
    "sg:province":"GA",
    "sg:tags":[
        "elementary",
        "kindergarten"
    ],
    "sg:website":"www.suzukilearning.com",
    "wof:name":"Suzuki Learning Centers",
    "wof:placetype":"venue"
},
  "geometry": {"coordinates":[-84.38069900000001,33.842499],"type":"Point"}
}