{
  "type": "Feature",
  "properties": {
    "addr:full":"98 Patterson Rd Lawrenceville GA 30044",
    "addr:housenumber":"98",
    "addr:postcode":"30044",
    "addr:street":"Patterson Rd",
    "iso:country":"US",
    "sg:address":"98 Patterson Rd",
    "sg:city":"Lawrenceville",
    "sg:classifiers":[
        {
            "category":"Personal",
            "type":"Services"
        }
    ],
    "sg:phone":"+1 770 962 5867",
    "sg:postcode":"30044",
    "sg:province":"GA",
    "sg:tags":[
        "party",
        "planning",
        "event"
    ],
    "wof:name":"Georgia Gymnastics Academy Inc",
    "wof:placetype":"venue"
},
  "geometry": {"coordinates":[-84.037903,33.925701],"type":"Point"}
}