{
  "type": "Feature",
  "properties": {
    "addr:full":"520 Branch Dr Alpharetta GA 30004",
    "addr:housenumber":"520",
    "addr:postcode":"30004",
    "addr:street":"Branch Dr",
    "iso:country":"US",
    "sg:address":"520 Branch Dr",
    "sg:city":"Alpharetta",
    "sg:classifiers":[
        {
            "category":"Home & Garden",
            "subcategory":"Building Materials",
            "type":"Retail Goods"
        }
    ],
    "sg:phone":"+1 770 772 1555",
    "sg:postcode":"30004",
    "sg:province":"GA",
    "sg:tags":[
        "plumbing",
        "fixture",
        "supply"
    ],
    "wof:name":"Home Depot Supply",
    "wof:placetype":"venue"
},
  "geometry": {"coordinates":[-84.22351,34.129173],"type":"Point"}
}