{
  "type": "Feature",
  "properties": {
    "iso:country":"US",
    "sg:address":"5095 Dublin Dr SW",
    "sg:city":"Atlanta",
    "sg:classifiers":[
        {
            "category":"Recreation",
            "subcategory":"Picnic Area",
            "type":"Entertainment"
        }
    ],
    "sg:phone":"+1 404 349 3033",
    "sg:postcode":"30331",
    "sg:province":"GA",
    "sg:tags":[
        "place",
        "arcade",
        "amusement"
    ],
    "wof:name":"Family Fun Inc",
    "wof:placetype":"venue"
},
  "geometry": {"coordinates":[-84.55406600000001,33.693185],"type":"Point"}
}