{
  "type": "Feature",
  "properties": {
    "addr:full":"4455 Stone Mountain Hwy Lilburn GA 30047",
    "addr:housenumber":"4455",
    "addr:postcode":"30047",
    "addr:street":"Stone Mountain Hwy",
    "iso:country":"US",
    "sg:address":"4455 Stone Mountain Hwy",
    "sg:city":"Lilburn",
    "sg:classifiers":[
        {
            "category":"Retail",
            "subcategory":"Auto Repair",
            "type":"Services"
        }
    ],
    "sg:phone":"+1 404 408 0108",
    "sg:postcode":"30047",
    "sg:province":"GA",
    "sg:tags":[
        "transmission"
    ],
    "wof:name":"Jds Transmissions",
    "wof:placetype":"venue"
},
  "geometry": {"coordinates":[-84.089562,33.831791],"type":"Point"}
}