{
  "type": "Feature",
  "properties": {
    "addr:full":"2010 Mesa Dr SE Atlanta GA 30316",
    "addr:housenumber":"2010",
    "addr:postcode":"30316",
    "addr:street":"Mesa Dr Se",
    "iso:country":"US",
    "sg:address":"2010 Mesa Dr SE",
    "sg:city":"Atlanta",
    "sg:classifiers":[
        {
            "category":"Organizations",
            "subcategory":"Religious Organization",
            "type":"Services"
        }
    ],
    "sg:phone":"+1 404 243 7073",
    "sg:postcode":"30316",
    "sg:province":"GA",
    "wof:name":"The Greater Word Ministries Holiness Church Inc",
    "wof:placetype":"venue"
},
  "geometry": {"coordinates":[-84.305609,33.6961],"type":"Point"}
}