{
  "type": "Feature",
  "properties": {
    "addr:full":"1410 Wynnton Rd Columbus GA 31906",
    "addr:housenumber":"1410",
    "addr:postcode":"31906",
    "addr:street":"Wynnton Rd",
    "iso:country":"US",
    "sg:address":"1410 Wynnton Rd",
    "sg:city":"Columbus",
    "sg:classifiers":[
        {
            "category":"Professional",
            "subcategory":"Lawyer & Legal Services",
            "type":"Services"
        },
        {
            "category":"Organizations",
            "subcategory":"Professional Association",
            "type":"Services"
        }
    ],
    "sg:phone":"+1 706 317 1919",
    "sg:postcode":"31906",
    "sg:province":"GA",
    "sg:tags":[
        "litigation",
        "attorney",
        "nursing",
        "civil",
        "worker",
        "compensation",
        "trial",
        "benefit",
        "employee",
        "home",
        "law"
    ],
    "sg:website":"http://www.realpages.com/sites/agnewlaw",
    "wof:name":"Agnew & Agnew Law Firm",
    "wof:placetype":"venue"
},
  "geometry": {"coordinates":[-84.971963,32.466777],"type":"Point"}
}