{
  "type": "Feature",
  "properties": {
    "iso:country":"US",
    "sg:address":"4209 Jonesboro Rd",
    "sg:city":"Forest Park",
    "sg:classifiers":[
        {
            "category":"Autos & Motor Vehicles",
            "subcategory":"Fuel & Gas Station",
            "type":"Retail Goods"
        }
    ],
    "sg:phone":"+1 404 361 5752",
    "sg:postcode":"30297",
    "sg:province":"GA",
    "sg:tags":[
        "oil"
    ],
    "wof:name":"Shell Food Mart",
    "wof:placetype":"venue"
},
  "geometry": {"coordinates":[-84.360116,33.637396],"type":"Point"}
}