{
  "type": "Feature",
  "properties": {
    "addr:full":"4490 Chamblee Dunwoody Rd Dunwoody GA 30338",
    "addr:housenumber":"4490",
    "addr:postcode":"30338",
    "addr:street":"Chamblee Dunwoody Rd",
    "iso:country":"US",
    "sg:address":"4490 Chamblee Dunwoody Rd",
    "sg:city":"Dunwoody",
    "sg:classifiers":[
        {
            "category":"Home & Garden",
            "subcategory":"Furniture",
            "type":"Retail Goods"
        }
    ],
    "sg:phone":"+1 770 457 0298",
    "sg:postcode":"30338",
    "sg:province":"GA",
    "wof:name":"Grand Harbour Imports Co",
    "wof:placetype":"venue"
},
  "geometry": {"coordinates":[-84.31461400000001,33.923152],"type":"Point"}
}