{
  "type": "Feature",
  "properties": {
    "iso:country":"US",
    "sg:address":"2100 Huntington Dr",
    "sg:city":"Loganville",
    "sg:classifiers":[
        {
            "category":"Building & Trades",
            "subcategory":"Construction",
            "type":"Services"
        }
    ],
    "sg:phone":"+1 404 606 7078",
    "sg:postcode":"30052",
    "sg:province":"GA",
    "sg:tags":[
        "floor",
        "laying",
        "contractor"
    ],
    "wof:name":"Floors & More",
    "wof:placetype":"venue"
},
  "geometry": {"coordinates":[-83.90323600000001,33.82767],"type":"Point"}
}