{
  "type": "Feature",
  "properties": {
    "iso:country":"US",
    "sg:address":"662 11th St NW",
    "sg:city":"Atlanta",
    "sg:classifiers":[
        {
            "category":"Manufacturing",
            "subcategory":"Tools & Machinery",
            "type":"Manufacturing & Wholesale Goods"
        }
    ],
    "sg:phone":"+1 800 282 3173",
    "sg:postcode":"30318",
    "sg:province":"GA",
    "sg:tags":[
        "scale"
    ],
    "wof:name":"Toledo, Scales & Sales Div",
    "wof:placetype":"venue"
},
  "geometry": {"coordinates":[-84.40907900000001,33.78302],"type":"Point"}
}