{
  "type": "Feature",
  "properties": {
    "iso:country":"US",
    "sg:address":"4045 Fve Frks Trckm Rd SW",
    "sg:city":"Lilburn",
    "sg:classifiers":[
        {
            "category":"Shopping",
            "subcategory":"Pharmacy",
            "type":"Retail Goods"
        },
        {
            "category":"Food & Beverages",
            "subcategory":"Groceries & Convenience Stores",
            "type":"Retail Goods"
        }
    ],
    "sg:phone":"+1 770 381 4176",
    "sg:postcode":"30047",
    "sg:province":"GA",
    "sg:tags":[
        "drugstore"
    ],
    "wof:name":"Publix Pharmacy",
    "wof:placetype":"venue"
},
  "geometry": {"coordinates":[-84.09169799999999,33.869202],"type":"Point"}
}