{
  "type": "Feature",
  "properties": {
    "addr:full":"210 Autumn Ridge Trl Roswell GA 30076",
    "addr:housenumber":"210",
    "addr:postcode":"30076",
    "addr:street":"Autumn Ridge Trl",
    "iso:country":"US",
    "sg:address":"210 Autumn Ridge Trl",
    "sg:city":"Roswell",
    "sg:classifiers":[
        {
            "category":"Organizations",
            "subcategory":"Religious Organization",
            "type":"Services"
        }
    ],
    "sg:phone":"+1 770 643 9690",
    "sg:postcode":"30076",
    "sg:province":"GA",
    "wof:name":"Raise His Praise International",
    "wof:placetype":"venue"
},
  "geometry": {"coordinates":[-84.300746,33.999707],"type":"Point"}
}