{
  "type": "Feature",
  "properties": {
    "iso:country":"US",
    "sg:address":"1850 Lake Park Dr SE Ste 204",
    "sg:city":"Smyrna",
    "sg:classifiers":[
        {
            "category":"Professional",
            "subcategory":"Lawyer & Legal Services",
            "type":"Services"
        }
    ],
    "sg:phone":"+1 770 801 9950",
    "sg:postcode":"30080",
    "sg:province":"GA",
    "wof:name":"Kaiden & Kaiden Llc Attorneys At Law Atty",
    "wof:placetype":"venue"
},
  "geometry": {"coordinates":[-84.48580200000001,33.895302],"type":"Point"}
}