{
  "type": "Feature",
  "properties": {
    "iso:country":"US",
    "sg:address":"201 Durden Dr",
    "sg:city":"Pooler",
    "sg:classifiers":[
        {
            "category":"Building & Trades",
            "subcategory":"Construction",
            "type":"Services"
        }
    ],
    "sg:phone":"+1 912 748 7130",
    "sg:postcode":"31322",
    "sg:province":"GA",
    "sg:tags":[
        "house"
    ],
    "wof:name":"Wade Construction",
    "wof:placetype":"venue"
},
  "geometry": {"coordinates":[-81.257626,32.122189],"type":"Point"}
}