{
  "type": "Feature",
  "properties": {
    "iso:country":"US",
    "sg:address":"4969 Elizabeth Way NW",
    "sg:city":"Lilburn",
    "sg:classifiers":[
        {
            "category":"Banks & Credit Unions",
            "subcategory":"Financial Services",
            "type":"Services"
        }
    ],
    "sg:phone":"+1 770 923 1216",
    "sg:postcode":"30047",
    "sg:province":"GA",
    "sg:tags":[
        "information",
        "consumer"
    ],
    "wof:name":"N V Know Info",
    "wof:placetype":"venue"
},
  "geometry": {"coordinates":[-84.13987899999999,33.884208],"type":"Point"}
}