{
  "type": "Feature",
  "properties": {
    "iso:country":"US",
    "sg:address":"194 Stone Mill Ln NW",
    "sg:city":"Marietta",
    "sg:classifiers":[
        {
            "category":"Organizations",
            "subcategory":"Labor Organization",
            "type":"Services"
        }
    ],
    "sg:phone":"+1 770 499 2393",
    "sg:postcode":"30064",
    "sg:province":"GA",
    "wof:name":"Star Network Services",
    "wof:placetype":"venue"
},
  "geometry": {"coordinates":[-84.619759,33.957868],"type":"Point"}
}