{
  "type": "Feature",
  "properties": {
    "addr:full":"878 Peachtree St Atlanta GA 30309",
    "addr:housenumber":"878",
    "addr:postcode":"30309",
    "addr:street":"Peachtree St",
    "iso:country":"US",
    "sg:address":"878 Peachtree St",
    "sg:city":"Atlanta",
    "sg:classifiers":[
        {
            "category":"Arts & Performance",
            "subcategory":"Comedy Club",
            "type":"Entertainment"
        }
    ],
    "sg:phone":"+1 877 523 3288",
    "sg:postcode":"30309",
    "sg:province":"GA",
    "sg:website":"www.vortexcomedy.com",
    "wof:name":"Laughing Skull Lounge",
    "wof:placetype":"venue"
},
  "geometry": {"coordinates":[-84.384398,33.778915],"type":"Point"}
}