{
  "type": "Feature",
  "properties": {
    "addr:full":"1398 Joyner Ave Marietta GA 30060",
    "addr:housenumber":"1398",
    "addr:postcode":"30060",
    "addr:street":"Joyner Ave",
    "iso:country":"US",
    "sg:address":"1398 Joyner Ave",
    "sg:city":"Marietta",
    "sg:classifiers":[
        {
            "category":"Building & Trades",
            "subcategory":"Construction",
            "type":"Services"
        }
    ],
    "sg:phone":"+1 770 514 8261",
    "sg:postcode":"30060",
    "sg:province":"GA",
    "sg:tags":[
        "hanging",
        "contractor"
    ],
    "wof:name":"Perez Painting",
    "wof:placetype":"venue"
},
  "geometry": {"coordinates":[-84.54509899999999,33.921031],"type":"Point"}
}