{
  "type": "Feature",
  "properties": {
    "iso:country":"US",
    "sg:address":"1208 Gloucester St",
    "sg:city":"Brunswick",
    "sg:classifiers":[
        {
            "category":"Shopping",
            "subcategory":"Used Merchandise",
            "type":"Retail Goods"
        }
    ],
    "sg:phone":"+1 912 264 2322",
    "sg:postcode":"31520",
    "sg:province":"GA",
    "wof:name":"Downtown Antiques Mall",
    "wof:placetype":"venue"
},
  "geometry": {"coordinates":[-81.489589,31.15053],"type":"Point"}
}