{
  "type": "Feature",
  "properties": {
    "addr:full":"3236 Ramsgate Rd Augusta GA 30909",
    "addr:housenumber":"3236",
    "addr:postcode":"30909",
    "addr:street":"Ramsgate Rd",
    "iso:country":"US",
    "sg:address":"3236 Ramsgate Rd",
    "sg:city":"Augusta",
    "sg:classifiers":[
        {
            "category":"Utilities",
            "subcategory":"Mobile Phone",
            "type":"Services"
        }
    ],
    "sg:phone":"+1 706 831 7215",
    "sg:postcode":"30909",
    "sg:province":"GA",
    "sg:tags":[
        "cellular"
    ],
    "wof:name":"Cellsource Corporation",
    "wof:placetype":"venue"
},
  "geometry": {"coordinates":[-82.062467,33.49625],"type":"Point"}
}