{
  "type": "Feature",
  "properties": {
    "iso:country":"US",
    "sg:address":"3633 Walton Way Ext",
    "sg:city":"Augusta",
    "sg:classifiers":[
        {
            "category":"Personal",
            "subcategory":"Nail Salon",
            "type":"Services"
        }
    ],
    "sg:phone":"+1 706 736 0676",
    "sg:postcode":"30909",
    "sg:province":"GA",
    "wof:name":"Falcon Nails",
    "wof:placetype":"venue"
},
  "geometry": {"coordinates":[-82.075211,33.490443],"type":"Point"}
}