{
  "type": "Feature",
  "properties": {
    "addr:full":"210 Highway 515 Blairsville GA 30512",
    "addr:housenumber":"210",
    "addr:postcode":"30512",
    "addr:street":"Highway 515",
    "iso:country":"US",
    "sg:address":"210 Highway 515",
    "sg:city":"Blairsville",
    "sg:classifiers":[
        {
            "category":"Restaurant",
            "type":"Food & Drink"
        }
    ],
    "sg:menulink":"http://www.allmenus.com/ga/blairsville/153927-zaxbys/menu/",
    "sg:phone":"+1 706 745 0092",
    "sg:postcode":"30512",
    "sg:province":"GA",
    "sg:tags":[
        "american",
        "wing"
    ],
    "wof:name":"Zaxby's",
    "wof:placetype":"venue"
},
  "geometry": {"coordinates":[-83.958528,34.878801],"type":"Point"}
}