{
  "type": "Feature",
  "properties": {
    "addr:full":"2978 Rainbow Dr Decatur GA 30034",
    "addr:housenumber":"2978",
    "addr:postcode":"30034",
    "addr:street":"Rainbow Dr",
    "iso:country":"US",
    "sg:address":"2978 Rainbow Dr",
    "sg:city":"Decatur",
    "sg:classifiers":[
        {
            "category":"Building & Trades",
            "subcategory":"Construction",
            "type":"Services"
        }
    ],
    "sg:phone":"+1 404 286 4587",
    "sg:postcode":"30034",
    "sg:province":"GA",
    "sg:tags":[
        "residential",
        "contractor"
    ],
    "wof:name":"Synergy Home Builders Inc",
    "wof:placetype":"venue"
},
  "geometry": {"coordinates":[-84.269695,33.709845],"type":"Point"}
}