{
  "type": "Feature",
  "properties": {
    "addr:full":"210 7th St W Tifton GA 31794",
    "addr:housenumber":"210",
    "addr:postcode":"31794",
    "addr:street":"7Th St W",
    "iso:country":"US",
    "sg:address":"210 7th St W",
    "sg:city":"Tifton",
    "sg:classifiers":[
        {
            "category":"Restaurant",
            "type":"Food & Drink"
        },
        {
            "category":"Ice Cream",
            "type":"Food & Drink"
        }
    ],
    "sg:menulink":"http://www.allmenus.com/ga/tifton/172478-dairy-queen/menu/",
    "sg:phone":"+1 229 382 5532",
    "sg:postcode":"31794",
    "sg:province":"GA",
    "sg:tags":[
        "burger",
        "american",
        "ice",
        "cream"
    ],
    "wof:name":"Dairy Queen",
    "wof:placetype":"venue"
},
  "geometry": {"coordinates":[-83.51514,31.450234],"type":"Point"}
}