{
  "type": "Feature",
  "properties": {
    "addr:full":"3067 Peachtree Industrial Blvd Duluth GA 30097",
    "addr:housenumber":"3067",
    "addr:postcode":"30097",
    "addr:street":"Peachtree Industrial Blvd",
    "iso:country":"US",
    "sg:address":"3067 Peachtree Industrial Blvd",
    "sg:city":"Duluth",
    "sg:classifiers":[
        {
            "category":"Banks & Credit Unions",
            "subcategory":"Bank",
            "type":"Services"
        }
    ],
    "sg:phone":"+1 678 280 0200",
    "sg:postcode":"30097",
    "sg:province":"GA",
    "sg:tags":[
        "loan",
        "real estate"
    ],
    "wof:name":"Mortgage 4u Inc",
    "wof:placetype":"venue"
},
  "geometry": {"coordinates":[-84.134219,34.022216],"type":"Point"}
}