{
  "type": "Feature",
  "properties": {
    "iso:country":"US",
    "sg:address":"3660 Campbellton Rd",
    "sg:city":"Atlanta",
    "sg:classifiers":[
        {
            "category":"Autos & Motor Vehicles",
            "subcategory":"Auto Supplies",
            "type":"Retail Goods"
        }
    ],
    "sg:phone":"+1 404 344 8995",
    "sg:postcode":"30331",
    "sg:province":"GA",
    "sg:tags":[
        "parts"
    ],
    "wof:name":"Autozone",
    "wof:placetype":"venue"
},
  "geometry": {"coordinates":[-84.506471,33.690101],"type":"Point"}
}