{
  "type": "Feature",
  "properties": {
    "iso:country":"US",
    "sg:address":"110 Carnegie Pl Ste 100",
    "sg:city":"Fayetteville",
    "sg:classifiers":[
        {
            "category":"Organizations",
            "subcategory":"Religious Organization",
            "type":"Services"
        }
    ],
    "sg:phone":"+1 770 460 1337",
    "sg:postcode":"30214",
    "sg:province":"GA",
    "wof:name":"Worldwide Discipleship Assn Inc",
    "wof:placetype":"venue"
},
  "geometry": {"coordinates":[-84.428802,33.509399],"type":"Point"}
}