{
  "type": "Feature",
  "properties": {
    "iso:country":"US",
    "sg:address":"1755 The Exchange SE",
    "sg:city":"Atlanta",
    "sg:classifiers":[
        {
            "category":"Government",
            "subcategory":"Office",
            "type":"Public Place"
        }
    ],
    "sg:phone":"+1 678 247 0021",
    "sg:postcode":"30339",
    "sg:province":"GA",
    "sg:tags":[
        "government-state"
    ],
    "wof:name":"City Of Atlanta",
    "wof:placetype":"venue"
},
  "geometry": {"coordinates":[-84.480406,33.909421],"type":"Point"}
}