{
  "type": "Feature",
  "properties": {
    "iso:country":"US",
    "sg:address":"2732 Cliffview Dr SW",
    "sg:city":"Lilburn",
    "sg:classifiers":[
        {
            "category":"Banks & Credit Unions",
            "subcategory":"Financial Services",
            "type":"Services"
        }
    ],
    "sg:phone":"+1 770 736 8669",
    "sg:postcode":"30047",
    "sg:province":"GA",
    "sg:tags":[
        "investment",
        "real estate"
    ],
    "wof:name":"Nu Dimensions Investments LLC",
    "wof:placetype":"venue"
},
  "geometry": {"coordinates":[-84.084115,33.815351],"type":"Point"}
}