{
  "type": "Feature",
  "properties": {
    "iso:country":"US",
    "sg:address":"3906 Oakdale Ter NW",
    "sg:city":"Duluth",
    "sg:classifiers":[
        {
            "category":"Professional",
            "type":"Services"
        }
    ],
    "sg:phone":"+1 770 622 6515",
    "sg:postcode":"30096",
    "sg:province":"GA",
    "wof:name":"Thunder Tree Service",
    "wof:placetype":"venue"
},
  "geometry": {"coordinates":[-84.155484,34.012395],"type":"Point"}
}