{
  "type": "Feature",
  "properties": {
    "iso:country":"US",
    "sg:address":"3475 Lenox Rd NE Ste 920",
    "sg:city":"Atlanta",
    "sg:classifiers":[
        {
            "category":"Professional",
            "subcategory":"Lawyer & Legal Services",
            "type":"Services"
        }
    ],
    "sg:phone":"+1 404 240 0335",
    "sg:postcode":"30326",
    "sg:province":"GA",
    "wof:name":"Azar Richard J Atty",
    "wof:placetype":"venue"
},
  "geometry": {"coordinates":[-84.361198,33.849499],"type":"Point"}
}