{
  "type": "Feature",
  "properties": {
    "addr:full":"201 S Grant St Fitzgerald GA 31750",
    "addr:housenumber":"201",
    "addr:postcode":"31750",
    "addr:street":"S Grant St",
    "iso:country":"US",
    "sg:address":"201 S Grant St",
    "sg:city":"Fitzgerald",
    "sg:classifiers":[
        {
            "category":"Insurance",
            "subcategory":"Hazard Insurance",
            "type":"Services"
        }
    ],
    "sg:phone":"+1 229 423 2333",
    "sg:postcode":"31750",
    "sg:province":"GA",
    "sg:tags":[
        "commercial",
        "business"
    ],
    "wof:name":"General Insurance Agency",
    "wof:placetype":"venue"
},
  "geometry": {"coordinates":[-83.252983,31.71664],"type":"Point"}
}