{
  "type": "Feature",
  "properties": {
    "addr:full":"1110 Cumberland Mall SE Atlanta GA 30339",
    "addr:housenumber":"1110",
    "addr:postcode":"30339",
    "addr:street":"Cumberland Mall Se",
    "iso:country":"US",
    "sg:address":"1110 Cumberland Mall SE",
    "sg:city":"Atlanta",
    "sg:classifiers":[
        {
            "category":"Shopping",
            "subcategory":"Bicycles & Sporting Goods",
            "type":"Retail Goods"
        }
    ],
    "sg:phone":"+1 678 842 0939",
    "sg:postcode":"30339",
    "sg:province":"GA",
    "wof:name":"Fans the Wear Inc",
    "wof:placetype":"venue"
},
  "geometry": {"coordinates":[-84.470893,33.880008],"type":"Point"}
}