{
  "type": "Feature",
  "properties": {
    "iso:country":"US",
    "sg:address":"2000 Riveredge Pkwy NW",
    "sg:city":"Atlanta",
    "sg:classifiers":[
        {
            "category":"Professional",
            "subcategory":"Lawyer & Legal Services",
            "type":"Services"
        }
    ],
    "sg:phone":"+1 770 951 2525",
    "sg:postcode":"30328",
    "sg:province":"GA",
    "wof:name":"Brown James H Atty",
    "wof:placetype":"venue"
},
  "geometry": {"coordinates":[-84.43879699999999,33.906898],"type":"Point"}
}