{
  "type": "Feature",
  "properties": {
    "addr:full":"2032 Hwy 81 S Covington GA 30016",
    "addr:housenumber":"2032",
    "addr:postcode":"30016",
    "addr:street":"Hwy 81 S",
    "iso:country":"US",
    "sg:address":"2032 Hwy 81 S",
    "sg:city":"Covington",
    "sg:classifiers":[
        {
            "category":"Autos & Motor Vehicles",
            "subcategory":"Automobile Sales",
            "type":"Retail Goods"
        }
    ],
    "sg:phone":"+1 770 385 2999",
    "sg:postcode":"30016",
    "sg:province":"GA",
    "wof:name":"Wheels On Credit",
    "wof:placetype":"venue"
},
  "geometry": {"coordinates":[-83.90989500000001,33.563609],"type":"Point"}
}