{
  "type": "Feature",
  "properties": {
    "addr:full":"2545 Densmore Rd Cumming GA 30041",
    "addr:housenumber":"2545",
    "addr:postcode":"30041",
    "addr:street":"Densmore Rd",
    "iso:country":"US",
    "sg:address":"2545 Densmore Rd",
    "sg:city":"Cumming",
    "sg:classifiers":[
        {
            "category":"Building & Trades",
            "subcategory":"Construction",
            "type":"Services"
        }
    ],
    "sg:phone":"+1 770 887 3350",
    "sg:postcode":"30041",
    "sg:province":"GA",
    "sg:tags":[
        "house"
    ],
    "wof:name":"All About Construction Inc",
    "wof:placetype":"venue"
},
  "geometry": {"coordinates":[-84.176564,34.100471],"type":"Point"}
}