{
  "type": "Feature",
  "properties": {
    "addr:full":"1021 Rosser St NW Conyers GA 30012",
    "addr:housenumber":"1021",
    "addr:postcode":"30012",
    "addr:street":"Rosser St Nw",
    "iso:country":"US",
    "sg:address":"1021 Rosser St NW",
    "sg:city":"Conyers",
    "sg:classifiers":[
        {
            "category":"Social Services",
            "subcategory":"Child Care",
            "type":"Services"
        }
    ],
    "sg:phone":"+1 770 760 9710",
    "sg:postcode":"30012",
    "sg:province":"GA",
    "sg:tags":[
        "day"
    ],
    "wof:name":"Genesis Childcare & D",
    "wof:placetype":"venue"
},
  "geometry": {"coordinates":[-84.020967,33.670466],"type":"Point"}
}