{
  "type": "Feature",
  "properties": {
    "iso:country":"US",
    "sg:address":"111 Breckinridge Dr",
    "sg:city":"Valdosta",
    "sg:classifiers":[
        {
            "category":"Wholesale",
            "subcategory":"Chemicals & Plastics",
            "type":"Manufacturing & Wholesale Goods"
        }
    ],
    "sg:phone":"+1 229 244 8779",
    "sg:postcode":"31605",
    "sg:province":"GA",
    "wof:name":"Kelco Packaging & Sales",
    "wof:placetype":"venue"
},
  "geometry": {"coordinates":[-83.295232,30.88996],"type":"Point"}
}