{
  "type": "Feature",
  "properties": {
    "addr:full":"1556 Golden Ave Augusta GA 30906",
    "addr:housenumber":"1556",
    "addr:postcode":"30906",
    "addr:street":"Golden Ave",
    "iso:country":"US",
    "sg:address":"1556 Golden Ave",
    "sg:city":"Augusta",
    "sg:classifiers":[
        {
            "category":"Shopping",
            "subcategory":"Department Store",
            "type":"Retail Goods"
        }
    ],
    "sg:phone":"+1 706 793 0032",
    "sg:postcode":"30906",
    "sg:province":"GA",
    "sg:tags":[
        "shop"
    ],
    "wof:name":"Lawson's",
    "wof:placetype":"venue"
},
  "geometry": {"coordinates":[-82.05466699999999,33.43509],"type":"Point"}
}