{
  "type": "Feature",
  "properties": {
    "iso:country":"US",
    "sg:address":"2802 Paces Ferry Rd SE",
    "sg:city":"Atlanta",
    "sg:classifiers":[
        {
            "category":"Real Estate",
            "subcategory":"Developer",
            "type":"Services"
        }
    ],
    "sg:phone":"+1 404 237 8828",
    "sg:postcode":"30339",
    "sg:province":"GA",
    "sg:tags":[
        "building",
        "development"
    ],
    "wof:name":"Morgan Capital",
    "wof:placetype":"venue"
},
  "geometry": {"coordinates":[-84.47015,33.865754],"type":"Point"}
}