{
  "type": "Feature",
  "properties": {
    "iso:country":"US",
    "sg:address":"2650 Pleasantdale Road",
    "sg:city":"Atlanta",
    "sg:classifiers":[
        {
            "category":"Shopping",
            "subcategory":"Computers & Home Electronics",
            "type":"Retail Goods"
        },
        {
            "category":"Communications",
            "type":"Services"
        }
    ],
    "sg:phone":"+1 770 368 8070",
    "sg:postcode":"30340",
    "sg:province":"GA",
    "sg:tags":[
        "recording",
        "rehearsal",
        "studio"
    ],
    "wof:name":"Rm Audio",
    "wof:placetype":"venue"
},
  "geometry": {"coordinates":[-84.245228,33.918637],"type":"Point"}
}