{
  "type": "Feature",
  "properties": {
    "addr:full":"518 Prince Ave Swainsboro GA 30401",
    "addr:housenumber":"518",
    "addr:postcode":"30401",
    "addr:street":"Prince Ave",
    "iso:country":"US",
    "sg:address":"518 Prince Ave",
    "sg:city":"Swainsboro",
    "sg:classifiers":[
        {
            "category":"Building & Trades",
            "subcategory":"Equipment Rental",
            "type":"Services"
        }
    ],
    "sg:phone":"+1 478 237 8320",
    "sg:postcode":"30401",
    "sg:province":"GA",
    "sg:tags":[
        "yard",
        "leasing",
        "store"
    ],
    "wof:name":"Lawson Rental",
    "wof:placetype":"venue"
},
  "geometry": {"coordinates":[-82.354574,32.595624],"type":"Point"}
}