{
  "type": "Feature",
  "properties": {
    "addr:full":"1271 Tacoma Dr NW Atlanta GA 30318",
    "addr:housenumber":"1271",
    "addr:postcode":"30318",
    "addr:street":"Tacoma Dr Nw",
    "iso:country":"US",
    "sg:address":"1271 Tacoma Dr NW",
    "sg:city":"Atlanta",
    "sg:classifiers":[
        {
            "category":"Wholesale",
            "subcategory":"Wine & Distilled Alcoholic Beverages",
            "type":"Manufacturing & Wholesale Goods"
        }
    ],
    "sg:phone":"+1 404 352 1041",
    "sg:postcode":"30318",
    "sg:province":"GA",
    "sg:tags":[
        "beer",
        "ale",
        "liquor"
    ],
    "sg:website":"http://www.haydenbeverage.com",
    "wof:name":"General Wholesale Co",
    "wof:placetype":"venue"
},
  "geometry": {"coordinates":[-84.431652,33.794768],"type":"Point"}
}