{
  "type": "Feature",
  "properties": {
    "iso:country":"US",
    "sg:address":"2142 Green Forrest Dr",
    "sg:city":"Decatur",
    "sg:classifiers":[
        {
            "category":"Professional",
            "subcategory":"Detective & Security Services",
            "type":"Services"
        }
    ],
    "sg:phone":"+1 404 284 0464",
    "sg:postcode":"30032",
    "sg:province":"GA",
    "sg:tags":[
        "bodyguard",
        "patrol",
        "consultant",
        "system",
        "equipment",
        "guard"
    ],
    "wof:name":"Serenity Security Services",
    "wof:placetype":"venue"
},
  "geometry": {"coordinates":[-84.25953699999999,33.726653],"type":"Point"}
}