{
  "type": "Feature",
  "properties": {
    "addr:full":"1139 Deleon Ct Clarkston GA 30021",
    "addr:housenumber":"1139",
    "addr:postcode":"30021",
    "addr:street":"Deleon Ct",
    "iso:country":"US",
    "sg:address":"1139 Deleon Ct",
    "sg:city":"Clarkston",
    "sg:classifiers":[
        {
            "category":"Professional",
            "type":"Services"
        }
    ],
    "sg:phone":"+1 404 297 0991",
    "sg:postcode":"30021",
    "sg:province":"GA",
    "wof:name":"Ferrone Inc",
    "wof:placetype":"venue"
},
  "geometry": {"coordinates":[-84.252134,33.81003],"type":"Point"}
}