{
  "type": "Feature",
  "properties": {
    "iso:country":"US",
    "sg:address":"151 Arcado Rd SW",
    "sg:city":"Lilburn",
    "sg:classifiers":[
        {
            "category":"Education",
            "subcategory":"Preschool",
            "type":"Public Place"
        },
        {
            "category":"Education",
            "subcategory":"School",
            "type":"Public Place"
        }
    ],
    "sg:phone":"+1 770 921 3224",
    "sg:postcode":"30047",
    "sg:province":"GA",
    "sg:tags":[
        "high",
        "middle",
        "elementary"
    ],
    "sg:website":"www.khcs.org",
    "wof:name":"Killian Hill Baptist Church & Christian School",
    "wof:placetype":"venue"
},
  "geometry": {"coordinates":[-84.112801,33.886902],"type":"Point"}
}