{
  "type": "Feature",
  "properties": {
    "addr:full":"3911 Sedgefield Dr Valdosta GA 31605",
    "addr:housenumber":"3911",
    "addr:postcode":"31605",
    "addr:street":"Sedgefield Dr",
    "iso:country":"US",
    "sg:address":"3911 Sedgefield Dr",
    "sg:city":"Valdosta",
    "sg:classifiers":[
        {
            "category":"Health Services",
            "subcategory":"Health Practitioner",
            "type":"Services"
        }
    ],
    "sg:phone":"+1 229 249 8165",
    "sg:postcode":"31605",
    "sg:province":"GA",
    "sg:tags":[
        "shop",
        "beauty"
    ],
    "wof:name":"Golden Pyramid Hlth & Buty Spa",
    "wof:placetype":"venue"
},
  "geometry": {"coordinates":[-83.29685499999999,30.891282],"type":"Point"}
}