{
  "type": "Feature",
  "properties": {
    "addr:full":"7172 Ironwood Dr Gainesville GA 30507",
    "addr:housenumber":"7172",
    "addr:postcode":"30507",
    "addr:street":"Ironwood Dr",
    "iso:country":"US",
    "sg:address":"7172 Ironwood Dr",
    "sg:city":"Gainesville",
    "sg:classifiers":[
        {
            "category":"Building & Trades",
            "subcategory":"Construction",
            "type":"Services"
        }
    ],
    "sg:phone":"+1 770 718 1449",
    "sg:postcode":"30507",
    "sg:province":"GA",
    "sg:tags":[
        "contractor",
        "painting",
        "hanging"
    ],
    "wof:name":"Becky Nix Painting",
    "wof:placetype":"venue"
},
  "geometry": {"coordinates":[-83.79391099999999,34.212578],"type":"Point"}
}