{
  "type": "Feature",
  "properties": {
    "iso:country":"US",
    "sg:address":"235 Bayfield Ct",
    "sg:city":"Alpharetta",
    "sg:classifiers":[
        {
            "category":"Building & Trades",
            "subcategory":"Construction",
            "type":"Services"
        }
    ],
    "sg:phone":"+1 678 297 0033",
    "sg:postcode":"30004",
    "sg:province":"GA",
    "sg:tags":[
        "contractor"
    ],
    "wof:name":"Modular Building Systems",
    "wof:placetype":"venue"
},
  "geometry": {"coordinates":[-84.27463299999999,34.109099],"type":"Point"}
}