{
  "type": "Feature",
  "properties": {
    "addr:full":"230 Thurmon Loop Rd Jesup GA 31545",
    "addr:housenumber":"230",
    "addr:postcode":"31545",
    "addr:street":"Thurmon Loop Rd",
    "iso:country":"US",
    "sg:address":"230 Thurmon Loop Rd",
    "sg:city":"Jesup",
    "sg:classifiers":[
        {
            "category":"Retail",
            "subcategory":"Auto Repair",
            "type":"Services"
        }
    ],
    "sg:phone":"+1 912 427 7921",
    "sg:postcode":"31545",
    "sg:province":"GA",
    "sg:tags":[
        "automotive",
        "general"
    ],
    "wof:name":"Ronald Starter & Alternator",
    "wof:placetype":"venue"
},
  "geometry": {"coordinates":[-81.86478700000001,31.681642],"type":"Point"}
}