{
  "type": "Feature",
  "properties": {
    "iso:country":"US",
    "sg:address":"2200 Century Parkway Suite 750",
    "sg:city":"Atlanta",
    "sg:classifiers":[
        {
            "category":"Banks & Credit Unions",
            "subcategory":"Investment Brokerage",
            "type":"Services"
        }
    ],
    "sg:phone":"+1 404 634 1998",
    "sg:postcode":"30345",
    "sg:province":"GA",
    "sg:tags":[
        "security"
    ],
    "wof:name":"LPL Financial",
    "wof:placetype":"venue"
},
  "geometry": {"coordinates":[-84.307739,33.845341],"type":"Point"}
}