{
  "type": "Feature",
  "properties": {
    "iso:country":"US",
    "sg:address":"3577 Cantrell Rd NE",
    "sg:city":"Atlanta",
    "sg:classifiers":[
        {
            "category":"Manufacturing",
            "subcategory":"Aerospace",
            "type":"Manufacturing & Wholesale Goods"
        }
    ],
    "sg:phone":"+1 404 786 6600",
    "sg:postcode":"30319",
    "sg:province":"GA",
    "sg:tags":[
        "equipment",
        "aircraft",
        "part",
        "design",
        "supplies-wholesale",
        "manufacturer"
    ],
    "wof:name":"Jet Coup",
    "wof:placetype":"venue"
},
  "geometry": {"coordinates":[-84.352407,33.852501],"type":"Point"}
}