{
  "type": "Feature",
  "properties": {
    "addr:full":"3071 Francine Dr Decatur GA 30033",
    "addr:housenumber":"3071",
    "addr:postcode":"30033",
    "addr:street":"Francine Dr",
    "iso:country":"US",
    "sg:address":"3071 Francine Dr",
    "sg:city":"Decatur",
    "sg:classifiers":[
        {
            "category":"Professional",
            "subcategory":"Business Services",
            "type":"Services"
        }
    ],
    "sg:phone":"+1 404 779 7658",
    "sg:postcode":"30033",
    "sg:province":"GA",
    "wof:name":"Ar6tistic Ventures LP",
    "wof:placetype":"venue"
},
  "geometry": {"coordinates":[-84.264959,33.814042],"type":"Point"}
}