{
  "type": "Feature",
  "properties": {
    "addr:full":"3155 Presidential Dr Doraville GA 30340",
    "addr:housenumber":"3155",
    "addr:postcode":"30340",
    "addr:street":"Presidential Dr",
    "iso:country":"US",
    "sg:address":"3155 Presidential Dr",
    "sg:city":"Doraville",
    "sg:classifiers":[
        {
            "category":"Manufacturing",
            "subcategory":"Printing",
            "type":"Manufacturing & Wholesale Goods"
        }
    ],
    "sg:phone":"+1 770 454 0818",
    "sg:postcode":"30340",
    "sg:province":"GA",
    "sg:tags":[
        "screen"
    ],
    "wof:name":"Follo-Graphics",
    "wof:placetype":"venue"
},
  "geometry": {"coordinates":[-84.259765,33.886731],"type":"Point"}
}