{
  "type": "Feature",
  "properties": {
    "addr:full":"3355 Lenox Rd Atlanta GA 30326",
    "addr:housenumber":"3355",
    "addr:postcode":"30326",
    "addr:street":"Lenox Rd",
    "iso:country":"US",
    "sg:address":"3355 Lenox Rd",
    "sg:city":"Atlanta",
    "sg:classifiers":[
        {
            "category":"Professional",
            "subcategory":"Lawyer & Legal Services",
            "type":"Services"
        }
    ],
    "sg:phone":"+1 877 373 4878",
    "sg:postcode":"30326",
    "sg:province":"GA",
    "sg:tags":[
        "personal",
        "injury"
    ],
    "sg:website":"www.atlantahurt.com",
    "wof:name":"Neil Flit",
    "wof:placetype":"venue"
},
  "geometry": {"coordinates":[-84.358132,33.84682],"type":"Point"}
}