{
  "type": "Feature",
  "properties": {
    "addr:full":"7205 Hunters Dr Cumming GA 30040",
    "addr:housenumber":"7205",
    "addr:postcode":"30040",
    "addr:street":"Hunters Dr",
    "iso:country":"US",
    "sg:address":"7205 Hunters Dr",
    "sg:city":"Cumming",
    "sg:classifiers":[
        {
            "category":"Wholesale",
            "subcategory":"Electrical",
            "type":"Manufacturing & Wholesale Goods"
        },
        {
            "category":"Wholesale",
            "subcategory":"Durable Goods & Equipment",
            "type":"Manufacturing & Wholesale Goods"
        }
    ],
    "sg:phone":"+1 770 886 3036",
    "sg:postcode":"30040",
    "sg:province":"GA",
    "sg:tags":[
        "electronic",
        "representative",
        "manufacturer"
    ],
    "wof:name":"Pro Com Group Inc",
    "wof:placetype":"venue"
},
  "geometry": {"coordinates":[-84.19551800000001,34.292839],"type":"Point"}
}