{
  "type": "Feature",
  "properties": {
    "iso:country":"US",
    "sg:address":"119 Fairfield Ct",
    "sg:city":"Warner Robins",
    "sg:classifiers":[
        {
            "category":"Social Services",
            "type":"Services"
        }
    ],
    "sg:phone":"+1 478 923 3479",
    "sg:postcode":"31093",
    "sg:province":"GA",
    "sg:tags":[
        "family"
    ],
    "wof:name":"Sarah Richmond",
    "wof:placetype":"venue"
},
  "geometry": {"coordinates":[-83.666493,32.649953],"type":"Point"}
}