{
  "type": "Feature",
  "properties": {
    "addr:full":"8126 State Rte 85 Riverdale GA 30274",
    "addr:housenumber":"8126",
    "addr:postcode":"30274",
    "addr:street":"State Rte 85",
    "iso:country":"US",
    "sg:address":"8126 State Rte 85",
    "sg:city":"Riverdale",
    "sg:classifiers":[
        {
            "category":"Autos & Motor Vehicles",
            "subcategory":"Auto Supplies",
            "type":"Retail Goods"
        }
    ],
    "sg:phone":"+1 770 472 3777",
    "sg:postcode":"30274",
    "sg:province":"GA",
    "sg:tags":[
        "hitch",
        "trailer",
        "utility"
    ],
    "wof:name":"Mikes Trailer Hitches & Acc",
    "wof:placetype":"venue"
},
  "geometry": {"coordinates":[-84.41897,33.533494],"type":"Point"}
}