{
  "type": "Feature",
  "properties": {
    "addr:full":"1913 Gillespie Ave Albany GA 31707",
    "addr:housenumber":"1913",
    "addr:postcode":"31707",
    "addr:street":"Gillespie Ave",
    "iso:country":"US",
    "sg:address":"1913 Gillespie Ave",
    "sg:city":"Albany",
    "sg:classifiers":[
        {
            "category":"Wholesale",
            "subcategory":"Machinery & Supplies",
            "type":"Manufacturing & Wholesale Goods"
        }
    ],
    "sg:phone":"+1 229 888 5735",
    "sg:postcode":"31707",
    "sg:province":"GA",
    "sg:tags":[
        "chemical",
        "pressure",
        "washer",
        "cleaning"
    ],
    "wof:name":"Shoemakers Pressure Washers",
    "wof:placetype":"venue"
},
  "geometry": {"coordinates":[-84.19879899999999,31.571048],"type":"Point"}
}