{
  "type": "Feature",
  "properties": {
    "addr:full":"3444 Rose Arbor Ct Atlanta GA 30340",
    "addr:housenumber":"3444",
    "addr:postcode":"30340",
    "addr:street":"Rose Arbor Ct",
    "iso:country":"US",
    "sg:address":"3444 Rose Arbor Ct",
    "sg:city":"Atlanta",
    "sg:classifiers":[
        {
            "category":"Professional",
            "subcategory":"Management & Consulting",
            "type":"Services"
        }
    ],
    "sg:phone":"+1 770 855 7135",
    "sg:postcode":"30340",
    "sg:province":"GA",
    "sg:tags":[
        "distributor",
        "grocery"
    ],
    "wof:name":"Able Packaging  Inc",
    "wof:placetype":"venue"
},
  "geometry": {"coordinates":[-84.251175,33.891317],"type":"Point"}
}