{
  "type": "Feature",
  "properties": {
    "iso:country":"US",
    "sg:address":"2434 Old Cornelia Hwy",
    "sg:city":"Gainesville",
    "sg:classifiers":[
        {
            "category":"Education",
            "subcategory":"Library",
            "type":"Public Place"
        }
    ],
    "sg:phone":"+1 770 531 2500",
    "sg:postcode":"30507",
    "sg:province":"GA",
    "wof:name":"East Hall Library",
    "wof:placetype":"venue"
},
  "geometry": {"coordinates":[-83.77709,34.313778],"type":"Point"}
}