{
  "type": "Feature",
  "properties": {
    "iso:country":"US",
    "sg:address":"477 S Jones St",
    "sg:city":"Fort Valley",
    "sg:classifiers":[
        {
            "category":"Professional",
            "subcategory":"Research",
            "type":"Services"
        }
    ],
    "sg:phone":"+1 478 825 3646",
    "sg:postcode":"31030",
    "sg:province":"GA",
    "sg:tags":[
        "nonphysical",
        "commercial"
    ],
    "wof:name":"Academic Qualitative",
    "wof:placetype":"venue"
},
  "geometry": {"coordinates":[-83.907004,32.528529],"type":"Point"}
}