{
  "type": "Feature",
  "properties": {
    "iso:country":"US",
    "sg:address":"5402 Sandell Ct",
    "sg:city":"Atlanta",
    "sg:classifiers":[
        {
            "category":"Professional",
            "type":"Services"
        }
    ],
    "sg:phone":"+1 770 394 8662",
    "sg:postcode":"30338",
    "sg:province":"GA",
    "wof:name":"Onesky",
    "wof:placetype":"venue"
},
  "geometry": {"coordinates":[-84.300325,33.954584],"type":"Point"}
}