{
  "type": "Feature",
  "properties": {
    "iso:country":"US",
    "sg:address":"1506 W Ward St Exd",
    "sg:city":"Douglas",
    "sg:classifiers":[
        {
            "category":"Autos & Motor Vehicles",
            "subcategory":"Boat Sales",
            "type":"Retail Goods"
        }
    ],
    "sg:phone":"+1 912 384 7244",
    "sg:postcode":"31533",
    "sg:province":"GA",
    "sg:tags":[
        "supply"
    ],
    "wof:name":"Southeastern Marine",
    "wof:placetype":"venue"
},
  "geometry": {"coordinates":[-82.866574,31.509331],"type":"Point"}
}