{
  "type": "Feature",
  "properties": {
    "iso:country":"US",
    "sg:address":"2730 Brookhaven Ln",
    "sg:city":"Buford",
    "sg:classifiers":[
        {
            "category":"Autos & Motor Vehicles",
            "subcategory":"Boat Sales",
            "type":"Retail Goods"
        }
    ],
    "sg:phone":"+1 404 697 4103",
    "sg:postcode":"30518",
    "sg:province":"GA",
    "sg:tags":[
        "repair",
        "maintenance"
    ],
    "wof:name":"Mobile One Boat Service, Inc",
    "wof:placetype":"venue"
},
  "geometry": {"coordinates":[-84.004249,34.150628],"type":"Point"}
}