{
  "type": "Feature",
  "properties": {
    "addr:full":"1800 Peachtree St Atlanta GA 30309",
    "addr:housenumber":"1800",
    "addr:postcode":"30309",
    "addr:street":"Peachtree St",
    "iso:country":"US",
    "sg:address":"1800 Peachtree St",
    "sg:city":"Atlanta",
    "sg:classifiers":[
        {
            "category":"Deli",
            "type":"Food & Drink"
        },
        {
            "category":"Food & Beverages",
            "subcategory":"Bakery",
            "type":"Retail Goods"
        }
    ],
    "sg:phone":"+1 404 355 0600",
    "sg:postcode":"30309",
    "sg:province":"GA",
    "sg:tags":[
        "sandwich"
    ],
    "sg:website":"sayheydeli.com",
    "wof:name":"Say Hey Deli",
    "wof:placetype":"venue"
},
  "geometry": {"coordinates":[-84.393542,33.804164],"type":"Point"}
}