{
  "type": "Feature",
  "properties": {
    "iso:country":"US",
    "sg:address":"1366 Wesleyan Ct NE",
    "sg:city":"Marietta",
    "sg:classifiers":[
        {
            "category":"Professional",
            "subcategory":"Management & Consulting",
            "type":"Services"
        },
        {
            "category":"Wholesale",
            "subcategory":"Durable Goods & Equipment",
            "type":"Manufacturing & Wholesale Goods"
        }
    ],
    "sg:phone":"+1 770 578 4368",
    "sg:postcode":"30068",
    "sg:province":"GA",
    "sg:tags":[
        "exporter",
        "business"
    ],
    "sg:website":"www.bristolenterprises.com",
    "wof:name":"Bristol Enterprises LLC",
    "wof:placetype":"venue"
},
  "geometry": {"coordinates":[-84.411224,33.982484],"type":"Point"}
}