{
  "type": "Feature",
  "properties": {
    "addr:full":"85 5th St NW Atlanta GA 30308",
    "addr:housenumber":"85",
    "addr:postcode":"30308",
    "addr:street":"5Th St Nw",
    "iso:country":"US",
    "sg:address":"85 5th St NW",
    "sg:city":"Atlanta",
    "sg:classifiers":[
        {
            "category":"Professional",
            "subcategory":"Management & Consulting",
            "type":"Services"
        }
    ],
    "sg:phone":"+1 404 347 9117",
    "sg:postcode":"30308",
    "sg:province":"GA",
    "sg:tags":[
        "consultant",
        "business"
    ],
    "wof:name":"5th Street Management Co LLC",
    "wof:placetype":"venue"
},
  "geometry": {"coordinates":[-84.389443,33.776925],"type":"Point"}
}