{
  "type": "Feature",
  "properties": {
    "iso:country":"US",
    "sg:address":"861 Georgia Highway 279",
    "sg:city":"Fairburn",
    "sg:classifiers":[
        {
            "category":"Education",
            "subcategory":"School",
            "type":"Public Place"
        }
    ],
    "sg:phone":"+1 770 461 2202",
    "sg:postcode":"30213",
    "sg:province":"GA",
    "sg:tags":[
        "high",
        "middle",
        "elementary"
    ],
    "wof:name":"Our Lady of Mercy High School",
    "wof:placetype":"venue"
},
  "geometry": {"coordinates":[-84.467697,33.5312],"type":"Point"}
}