{
  "type": "Feature",
  "properties": {
    "addr:full":"1164 Parham Rd Griffin GA 30223",
    "addr:housenumber":"1164",
    "addr:postcode":"30223",
    "addr:street":"Parham Rd",
    "iso:country":"US",
    "sg:address":"1164 Parham Rd",
    "sg:city":"Griffin",
    "sg:classifiers":[
        {
            "category":"Professional",
            "type":"Services"
        }
    ],
    "sg:phone":"+1 770 228 6947",
    "sg:postcode":"30223",
    "sg:province":"GA",
    "wof:name":"Donald E Shivers",
    "wof:placetype":"venue"
},
  "geometry": {"coordinates":[-84.153868,33.264464],"type":"Point"}
}