{
  "type": "Feature",
  "properties": {
    "addr:full":"555 Spence Rd Fairburn GA 30213",
    "addr:housenumber":"555",
    "addr:postcode":"30213",
    "addr:street":"Spence Rd",
    "iso:country":"US",
    "sg:address":"555 Spence Rd",
    "sg:city":"Fairburn",
    "sg:classifiers":[
        {
            "category":"Professional",
            "type":"Services"
        }
    ],
    "sg:phone":"+1 770 903 9185",
    "sg:postcode":"30213",
    "sg:province":"GA",
    "wof:name":"MA Prowell Family Ltd Par",
    "wof:placetype":"venue"
},
  "geometry": {"coordinates":[-84.57333,33.555704],"type":"Point"}
}