{
  "type": "Feature",
  "properties": {
    "addr:full":"3622 Phillips Dr Augusta GA 30907",
    "addr:housenumber":"3622",
    "addr:postcode":"30907",
    "addr:street":"Phillips Dr",
    "iso:country":"US",
    "sg:address":"3622 Phillips Dr",
    "sg:city":"Augusta",
    "sg:classifiers":[
        {
            "category":"Insurance",
            "subcategory":"Insurance Agent",
            "type":"Services"
        }
    ],
    "sg:phone":"+1 706 860 8282",
    "sg:postcode":"30907",
    "sg:province":"GA",
    "wof:name":"Woodman of World Lf Insur Soc",
    "wof:placetype":"venue"
},
  "geometry": {"coordinates":[-82.077709,33.524127],"type":"Point"}
}