{
  "type": "Feature",
  "properties": {
    "addr:full":"405 Heritage Dr Warner Robins GA 31093",
    "addr:housenumber":"405",
    "addr:postcode":"31093",
    "addr:street":"Heritage Dr",
    "iso:country":"US",
    "sg:address":"405 Heritage Dr",
    "sg:city":"Warner Robins",
    "sg:classifiers":[
        {
            "category":"Building & Trades",
            "subcategory":"Landscaping Services",
            "type":"Services"
        }
    ],
    "sg:phone":"+1 478 922 6794",
    "sg:postcode":"31093",
    "sg:province":"GA",
    "sg:tags":[
        "landscape"
    ],
    "wof:name":"Evans Landscapes",
    "wof:placetype":"venue"
},
  "geometry": {"coordinates":[-83.66229800000001,32.660176],"type":"Point"}
}