{
  "type": "Feature",
  "properties": {
    "addr:full":"854 Sunset Blvd Mableton GA 30126",
    "addr:housenumber":"854",
    "addr:postcode":"30126",
    "addr:street":"Sunset Blvd",
    "iso:country":"US",
    "sg:address":"854 Sunset Blvd",
    "sg:city":"Mableton",
    "sg:classifiers":[
        {
            "category":"Wholesale",
            "subcategory":"Home Furnishings",
            "type":"Manufacturing & Wholesale Goods"
        }
    ],
    "sg:phone":"+1 770 944 2453",
    "sg:postcode":"30126",
    "sg:province":"GA",
    "sg:tags":[
        "window",
        "covering"
    ],
    "wof:name":"Custom Shutters Inc",
    "wof:placetype":"venue"
},
  "geometry": {"coordinates":[-84.580297,33.807942],"type":"Point"}
}