{
  "type": "Feature",
  "properties": {
    "iso:country":"US",
    "sg:address":"240 Oakwood Rd",
    "sg:city":"Mineral Bluff",
    "sg:classifiers":[
        {
            "category":"Professional",
            "type":"Services"
        }
    ],
    "sg:phone":"+1 706 374 3145",
    "sg:postcode":"30553",
    "sg:province":"GA",
    "wof:name":"Elaine D Crane",
    "wof:placetype":"venue"
},
  "geometry": {"coordinates":[-83.104181,34.499814],"type":"Point"}
}