{
  "type": "Feature",
  "properties": {
    "addr:full":"134 S Clayton St Lawrenceville GA 30045",
    "addr:housenumber":"134",
    "addr:postcode":"30045",
    "addr:street":"S Clayton St",
    "iso:country":"US",
    "sg:address":"134 S Clayton St",
    "sg:city":"Lawrenceville",
    "sg:classifiers":[
        {
            "category":"Travel",
            "subcategory":"Travel Agent",
            "type":"Entertainment"
        }
    ],
    "sg:phone":"+1 770 237 0002",
    "sg:postcode":"30045",
    "sg:province":"GA",
    "sg:tags":[
        "agency",
        "bureau"
    ],
    "wof:name":"Copacabana Travel Management",
    "wof:placetype":"venue"
},
  "geometry": {"coordinates":[-83.988326,33.95559],"type":"Point"}
}