{
  "type": "Feature",
  "properties": {
    "iso:country":"US",
    "sg:address":"1239 Russell Pkwy",
    "sg:city":"Warner Robins",
    "sg:classifiers":[
        {
            "category":"Personal",
            "subcategory":"Tattoo Parlor",
            "type":"Services"
        }
    ],
    "sg:phone":"+1 478 225 9325",
    "sg:postcode":"31088",
    "sg:province":"GA",
    "wof:name":"Sacred Heart Southside",
    "wof:placetype":"venue"
},
  "geometry": {"coordinates":[-83.648242,32.593843],"type":"Point"}
}