{
  "type": "Feature",
  "properties": {
    "iso:country":"US",
    "sg:address":"1705 Oakmont Dr",
    "sg:city":"Dalton",
    "sg:classifiers":[
        {
            "category":"Home & Garden",
            "subcategory":"Household Appliances",
            "type":"Retail Goods"
        },
        {
            "category":"Building & Trades",
            "subcategory":"Construction",
            "type":"Services"
        }
    ],
    "sg:phone":"+1 706 529 5523",
    "sg:postcode":"30720",
    "sg:province":"GA",
    "sg:tags":[
        "major",
        "system",
        "appliances-small",
        "specialty",
        "heating",
        "contractor",
        "air conditioning"
    ],
    "wof:name":"Godwin HVAC",
    "wof:placetype":"venue"
},
  "geometry": {"coordinates":[-84.994208,34.748486],"type":"Point"}
}