{
  "type": "Feature",
  "properties": {
    "addr:full":"2179 Northlake Pkwy Ste 114 Tucker GA 30084",
    "addr:housenumber":"2179",
    "addr:postcode":"30084",
    "addr:street":"Northlake Pkwy Ste 114",
    "iso:country":"US",
    "sg:address":"2179 Northlake Pkwy Ste 114",
    "sg:city":"Tucker",
    "sg:classifiers":[
        {
            "category":"Building & Trades",
            "subcategory":"Cleaning & Sanitation",
            "type":"Services"
        },
        {
            "category":"Building & Trades",
            "subcategory":"Construction",
            "type":"Services"
        }
    ],
    "sg:phone":"+1 770 723 7760",
    "sg:postcode":"30084",
    "sg:province":"GA",
    "sg:tags":[
        "contractor",
        "carpet"
    ],
    "sg:website":"www.advantagerestorationandcontr...",
    "wof:name":"Advantage Restoration and Contracting Inc",
    "wof:placetype":"venue"
},
  "geometry": {"coordinates":[-84.244445,33.849192],"type":"Point"}
}