{
  "type": "Feature",
  "properties": {
    "addr:full":"2211 Marshes Glenn Dr Norcross GA 30071",
    "addr:postcode":"2211;30071",
    "addr:street":"Marshes Glenn Dr",
    "iso:country":"US",
    "sg:address":"2211 Marshes Glenn Dr",
    "sg:city":"Norcross",
    "sg:classifiers":[
        {
            "category":"Freight",
            "type":"Transportation"
        }
    ],
    "sg:phone":"+1 770 447 5793",
    "sg:postcode":"30071",
    "sg:province":"GA",
    "sg:tags":[
        "operator",
        "local",
        "trucking"
    ],
    "wof:name":"Laid Back Trucking Inc",
    "wof:placetype":"venue"
},
  "geometry": {"coordinates":[-84.207165,33.932839],"type":"Point"}
}