{
  "type": "Feature",
  "properties": {
    "addr:full":"1036 Lakes Blvd Lake Park GA 31636",
    "addr:housenumber":"1036",
    "addr:postcode":"31636",
    "addr:street":"Lakes Blvd",
    "iso:country":"US",
    "sg:address":"1036 Lakes Blvd",
    "sg:city":"Lake Park",
    "sg:classifiers":[
        {
            "category":"Personal",
            "subcategory":"Beauty Salon",
            "type":"Services"
        }
    ],
    "sg:phone":"+1 229 559 1904",
    "sg:postcode":"31636",
    "sg:province":"GA",
    "sg:tags":[
        "shop"
    ],
    "wof:name":"Looks Inc",
    "wof:placetype":"venue"
},
  "geometry": {"coordinates":[-83.217527,30.68237],"type":"Point"}
}