{
  "type": "Feature",
  "properties": {
    "iso:country":"US",
    "sg:address":"502 Isabella St",
    "sg:city":"Waycross",
    "sg:classifiers":[
        {
            "category":"Health Services",
            "subcategory":"Doctor",
            "type":"Services"
        }
    ],
    "sg:phone":"+1 912 285 2020",
    "sg:postcode":"31503",
    "sg:province":"GA",
    "sg:tags":[
        "physician",
        "surgeon"
    ],
    "wof:name":"Clark Eye Clinic",
    "wof:placetype":"venue"
},
  "geometry": {"coordinates":[-82.360967,31.211546],"type":"Point"}
}