{
  "type": "Feature",
  "properties": {
    "addr:full":"3031 Vineville Ave Macon GA 31204",
    "addr:housenumber":"3031",
    "addr:postcode":"31204",
    "addr:street":"Vineville Ave",
    "iso:country":"US",
    "sg:address":"3031 Vineville Ave",
    "sg:city":"Macon",
    "sg:classifiers":[
        {
            "category":"Retail",
            "subcategory":"Auto Repair",
            "type":"Services"
        }
    ],
    "sg:phone":"+1 478 745 1090",
    "sg:postcode":"31204",
    "sg:province":"GA",
    "sg:tags":[
        "automobile",
        "lubrication"
    ],
    "wof:name":"Jiffy Lube",
    "wof:placetype":"venue"
},
  "geometry": {"coordinates":[-83.672228,32.84859],"type":"Point"}
}