{
  "type": "Feature",
  "properties": {
    "iso:country":"US",
    "sg:address":"4335 Melanie Ln",
    "sg:city":"Atlanta",
    "sg:classifiers":[
        {
            "category":"Insurance",
            "subcategory":"Insurance Agent",
            "type":"Services"
        }
    ],
    "sg:phone":"+1 770 306 2571",
    "sg:postcode":"30349",
    "sg:province":"GA",
    "sg:tags":[
        "adjuster"
    ],
    "wof:name":"Crawford And Crawford Enterpri",
    "wof:placetype":"venue"
},
  "geometry": {"coordinates":[-84.524486,33.597418],"type":"Point"}
}