{
  "type": "Feature",
  "properties": {
    "iso:country":"US",
    "sg:address":"2200 Century Parkway NE Suite 700",
    "sg:city":"Atlanta",
    "sg:classifiers":[
        {
            "category":"Professional",
            "subcategory":"Accounting & Tax Preparation",
            "type":"Services"
        }
    ],
    "sg:phone":"+1 404 982 0522",
    "sg:postcode":"30345",
    "sg:province":"GA",
    "sg:tags":[
        "accountant"
    ],
    "wof:name":"Williford Windham and Stone Cpas",
    "wof:placetype":"venue"
},
  "geometry": {"coordinates":[-84.307695,33.84532],"type":"Point"}
}