{
  "type": "Feature",
  "properties": {
    "addr:full":"3843 Betty Jean Ct Lilburn GA 30047",
    "addr:housenumber":"3843",
    "addr:postcode":"30047",
    "addr:street":"Betty Jean Ct",
    "iso:country":"US",
    "sg:address":"3843 Betty Jean Ct",
    "sg:city":"Lilburn",
    "sg:classifiers":[
        {
            "category":"Building & Trades",
            "subcategory":"Construction",
            "type":"Services"
        }
    ],
    "sg:phone":"+1 404 597 1610",
    "sg:postcode":"30047",
    "sg:province":"GA",
    "sg:tags":[
        "house"
    ],
    "wof:name":"John Nelson Craftsman",
    "wof:placetype":"venue"
},
  "geometry": {"coordinates":[-84.082949,33.870367],"type":"Point"}
}