{
  "type": "Feature",
  "properties": {
    "iso:country":"US",
    "sg:address":"9193 Lavonia Rd",
    "sg:city":"Carnesville",
    "sg:classifiers":[
        {
            "category":"Shopping",
            "subcategory":"Computers & Home Electronics",
            "type":"Retail Goods"
        }
    ],
    "sg:phone":"+1 706 384 7479",
    "sg:postcode":"30521",
    "sg:province":"GA",
    "sg:tags":[
        "equipment",
        "dealer"
    ],
    "wof:name":"Complete Computers",
    "wof:placetype":"venue"
},
  "geometry": {"coordinates":[-83.24189200000001,34.367164],"type":"Point"}
}