{
  "type": "Feature",
  "properties": {
    "addr:full":"2600 Century Pkwy NE Atlanta GA 30345",
    "addr:housenumber":"2600",
    "addr:postcode":"30345",
    "addr:street":"Century Pkwy Ne",
    "iso:country":"US",
    "sg:address":"2600 Century Pkwy NE",
    "sg:city":"Atlanta",
    "sg:classifiers":[
        {
            "category":"Professional",
            "subcategory":"Computer Services",
            "type":"Services"
        }
    ],
    "sg:phone":"+1 770 590 1002",
    "sg:postcode":"30345",
    "sg:province":"GA",
    "sg:tags":[
        "related"
    ],
    "wof:name":"Square Knot Inc",
    "wof:placetype":"venue"
},
  "geometry": {"coordinates":[-84.306663,33.847554],"type":"Point"}
}