{
  "type": "Feature",
  "properties": {
    "iso:country":"US",
    "sg:address":"510 Skyview Dr",
    "sg:city":"Augusta",
    "sg:classifiers":[
        {
            "category":"Building & Trades",
            "subcategory":"Construction",
            "type":"Services"
        }
    ],
    "sg:phone":"+1 706 724 8840",
    "sg:postcode":"30901",
    "sg:province":"GA",
    "sg:tags":[
        "fabricator",
        "sandblasting",
        "metal"
    ],
    "sg:website":"http://www.metalspecialistsofaugusta.com",
    "wof:name":"Metal Specialists of Augusta",
    "wof:placetype":"venue"
},
  "geometry": {"coordinates":[-81.970073,33.456326],"type":"Point"}
}