{
  "type": "Feature",
  "properties": {
    "addr:full":"2910 N Druid Hills Rd NE Atlanta GA 30329",
    "addr:housenumber":"2910",
    "addr:postcode":"30329",
    "addr:street":"N Druid Hills Rd Ne",
    "iso:country":"US",
    "sg:address":"2910 N Druid Hills Rd NE",
    "sg:city":"Atlanta",
    "sg:classifiers":[
        {
            "category":"Wholesale",
            "subcategory":"Non-durable Goods",
            "type":"Manufacturing & Wholesale Goods"
        }
    ],
    "sg:phone":"+1 678 702 8800",
    "sg:postcode":"30329",
    "sg:province":"GA",
    "sg:tags":[
        "biological",
        "product"
    ],
    "wof:name":"Nano Biotechnologies",
    "wof:placetype":"venue"
},
  "geometry": {"coordinates":[-84.31084199999999,33.816238],"type":"Point"}
}