{
  "type": "Feature",
  "properties": {
    "addr:full":"7525 Covington Hwy Ste F Lithonia GA 30058",
    "addr:housenumber":"7525",
    "addr:postcode":"30058",
    "addr:street":"Covington Hwy Ste F",
    "iso:country":"US",
    "sg:address":"7525 Covington Hwy Ste F",
    "sg:city":"Lithonia",
    "sg:classifiers":[
        {
            "category":"Cinema",
            "subcategory":"Movie Rental",
            "type":"Entertainment"
        }
    ],
    "sg:phone":"+1 770 482 8556",
    "sg:postcode":"30058",
    "sg:province":"GA",
    "sg:tags":[
        "game",
        "video"
    ],
    "wof:name":"Movie World II",
    "wof:placetype":"venue"
},
  "geometry": {"coordinates":[-84.11514699999999,33.707144],"type":"Point"}
}