{
  "type": "Feature",
  "properties": {
    "iso:country":"US",
    "sg:address":"983 S Cobb Dr SE",
    "sg:city":"Marietta",
    "sg:classifiers":[
        {
            "category":"Autos & Motor Vehicles",
            "subcategory":"Motorcycle Sales",
            "type":"Retail Goods"
        }
    ],
    "sg:phone":"+1 770 919 1703",
    "sg:postcode":"30060",
    "sg:province":"GA",
    "wof:name":"Harley Rentals",
    "wof:placetype":"venue"
},
  "geometry": {"coordinates":[-84.550201,33.9305],"type":"Point"}
}