{
  "type": "Feature",
  "properties": {
    "iso:country":"US",
    "sg:address":"4604 E Fairview Rd SW",
    "sg:city":"Stockbridge",
    "sg:classifiers":[
        {
            "category":"Retail",
            "subcategory":"Auto Repair",
            "type":"Services"
        }
    ],
    "sg:phone":"+1 770 761 4044",
    "sg:postcode":"30281",
    "sg:province":"GA",
    "wof:name":"Guffeys Automotive",
    "wof:placetype":"venue"
},
  "geometry": {"coordinates":[-84.139353,33.609081],"type":"Point"}
}