{
  "type": "Feature",
  "properties": {
    "iso:country":"US",
    "sg:address":"869 Virginia Ave",
    "sg:city":"Atlanta",
    "sg:classifiers":[
        {
            "category":"Park",
            "type":"Public Place"
        },
        {
            "category":"Recreation",
            "subcategory":"Playground",
            "type":"Entertainment"
        }
    ],
    "sg:phone":"+1 404 817 6744",
    "sg:postcode":"30306",
    "sg:province":"GA",
    "wof:name":"John Howell Memorial Park",
    "wof:placetype":"venue"
},
  "geometry": {"coordinates":[-84.35892,33.782029],"type":"Point"}
}