{
  "type": "Feature",
  "properties": {
    "addr:full":"3479 Lawrenceville Suwanee Rd Suwanee GA 30024",
    "addr:housenumber":"3479",
    "addr:postcode":"30024",
    "addr:street":"Lawrenceville Suwanee Rd",
    "iso:country":"US",
    "sg:address":"3479 Lawrenceville Suwanee Rd",
    "sg:city":"Suwanee",
    "sg:classifiers":[
        {
            "category":"Building & Trades",
            "subcategory":"Cleaning & Sanitation",
            "type":"Services"
        },
        {
            "category":"Structure",
            "subcategory":"Warehouse",
            "type":"Public Place"
        },
        {
            "category":"Building & Trades",
            "subcategory":"Construction",
            "type":"Services"
        }
    ],
    "sg:phone":"+1 770 662 8393",
    "sg:postcode":"30024",
    "sg:province":"GA",
    "sg:tags":[
        "roofing",
        "industrial",
        "warehouses-merchandise",
        "fire",
        "damage",
        "contractor",
        "water",
        "restoration",
        "contractors-commercial"
    ],
    "sg:website":"http://www.adgenterprises.net",
    "wof:name":"ADG Enterprises",
    "wof:placetype":"venue"
},
  "geometry": {"coordinates":[-84.056186,34.04463],"type":"Point"}
}