{
  "type": "Feature",
  "properties": {
    "iso:country":"US",
    "sg:address":"2283 Windland Dr",
    "sg:city":"Lawrenceville",
    "sg:classifiers":[
        {
            "category":"Freight",
            "type":"Transportation"
        }
    ],
    "sg:phone":"+1 770 978 8921",
    "sg:postcode":"30044",
    "sg:province":"GA",
    "wof:name":"T & M Transportation",
    "wof:placetype":"venue"
},
  "geometry": {"coordinates":[-84.03883399999999,33.902981],"type":"Point"}
}