{
  "type": "Feature",
  "properties": {
    "iso:country":"US",
    "sg:address":"5371 Old National Hwy",
    "sg:city":"Atlanta",
    "sg:classifiers":[
        {
            "category":"Restaurant",
            "type":"Food & Drink"
        }
    ],
    "sg:phone":"+1 404 767 6661",
    "sg:postcode":"30349",
    "sg:province":"GA",
    "sg:tags":[
        "drinking",
        "eating"
    ],
    "wof:name":"Ritz The",
    "wof:placetype":"venue"
},
  "geometry": {"coordinates":[-84.4717,33.611269],"type":"Point"}
}