{
  "type": "Feature",
  "properties": {
    "addr:full":"6015 Oakbrook Pkwy Norcross GA 30093",
    "addr:housenumber":"6015",
    "addr:postcode":"30093",
    "addr:street":"Oakbrook Pkwy",
    "iso:country":"US",
    "sg:address":"6015 Oakbrook Pkwy",
    "sg:city":"Norcross",
    "sg:classifiers":[
        {
            "category":"Travel",
            "subcategory":"Hotels & Motels",
            "type":"Entertainment"
        }
    ],
    "sg:phone":"+1 770 242 6917",
    "sg:postcode":"30093",
    "sg:province":"GA",
    "sg:tags":[
        "operation"
    ],
    "sg:website":"www.motel6.com",
    "wof:name":"Motel 6",
    "wof:placetype":"venue"
},
  "geometry": {"coordinates":[-84.205299,33.910599],"type":"Point"}
}