{
  "type": "Feature",
  "properties": {
    "iso:country":"US",
    "sg:address":"3914 River Place Dr",
    "sg:city":"Macon",
    "sg:classifiers":[
        {
            "category":"Bars & Pubs",
            "type":"Food & Drink"
        },
        {
            "category":"Restaurant",
            "type":"Food & Drink"
        },
        {
            "category":"Bars & Pubs",
            "subcategory":"Sports Bar",
            "type":"Food & Drink"
        }
    ],
    "sg:phone":"+1 478 475 4114",
    "sg:postcode":"31210",
    "sg:province":"GA",
    "sg:tags":[
        "grill",
        "brew"
    ],
    "wof:name":"Wagers Inc",
    "wof:placetype":"venue"
},
  "geometry": {"coordinates":[-83.685901,32.90521],"type":"Point"}
}