{
  "type": "Feature",
  "properties": {
    "addr:full":"431 2nd Ave SE Cairo GA 39828",
    "addr:housenumber":"431",
    "addr:postcode":"39828",
    "addr:street":"2Nd Ave Se",
    "iso:country":"US",
    "sg:address":"431 2nd Ave SE",
    "sg:city":"Cairo",
    "sg:classifiers":[
        {
            "category":"Insurance",
            "subcategory":"Hazard Insurance",
            "type":"Services"
        }
    ],
    "sg:phone":"+1 229 377 9667",
    "sg:postcode":"39828",
    "sg:province":"GA",
    "sg:website":"http://statefarm.mqgroup.com/url.asp?usr=111656",
    "wof:name":"State Farm Insurance Agent-Jim Scarbrough",
    "wof:placetype":"venue"
},
  "geometry": {"coordinates":[-84.203248,30.87528],"type":"Point"}
}