{
  "type": "Feature",
  "properties": {
    "addr:full":"5640 Hog Mountain Rd Flowery Branch GA 30542",
    "addr:housenumber":"5640",
    "addr:postcode":"30542",
    "addr:street":"Hog Mountain Rd",
    "iso:country":"US",
    "sg:address":"5640 Hog Mountain Rd",
    "sg:city":"Flowery Branch",
    "sg:classifiers":[
        {
            "category":"Building & Trades",
            "subcategory":"Construction",
            "type":"Services"
        }
    ],
    "sg:phone":"+1 770 945 1113",
    "sg:postcode":"30542",
    "sg:province":"GA",
    "sg:tags":[
        "general",
        "contractor"
    ],
    "wof:name":"Greenwood Builder Group Inc",
    "wof:placetype":"venue"
},
  "geometry": {"coordinates":[-83.929316,34.141899],"type":"Point"}
}