{
  "type": "Feature",
  "properties": {
    "iso:country":"US",
    "sg:address":"28 W Jefferson St",
    "sg:city":"Hazlehurst",
    "sg:classifiers":[
        {
            "category":"Personal",
            "subcategory":"Beauty Salon",
            "type":"Services"
        }
    ],
    "sg:phone":"+1 912 375 0055",
    "sg:postcode":"31539",
    "sg:province":"GA",
    "sg:tags":[
        "wig",
        "hair",
        "piece"
    ],
    "wof:name":"New Beginnings Unisex Hairstyling Salon",
    "wof:placetype":"venue"
},
  "geometry": {"coordinates":[-82.60545,31.862622],"type":"Point"}
}