{
  "type": "Feature",
  "properties": {
    "iso:country":"US",
    "sg:address":"120 Brumbelow Rd",
    "sg:city":"Carrollton",
    "sg:classifiers":[
        {
            "category":"Organizations",
            "subcategory":"Membership Organization",
            "type":"Services"
        },
        {
            "category":"Organizations",
            "subcategory":"Professional Association",
            "type":"Services"
        }
    ],
    "sg:phone":"+1 770 214 2698",
    "sg:postcode":"30117",
    "sg:province":"GA",
    "wof:name":"Latinos United Of Carroll Co",
    "wof:placetype":"venue"
},
  "geometry": {"coordinates":[-85.098387,33.576597],"type":"Point"}
}