{
  "type": "Feature",
  "properties": {
    "iso:country":"US",
    "sg:address":"1 W Washington St",
    "sg:city":"Newnan",
    "sg:classifiers":[
        {
            "category":"Real Estate",
            "subcategory":"Real Estate Agent",
            "type":"Services"
        }
    ],
    "sg:phone":"+1 770 251 2343",
    "sg:postcode":"30263",
    "sg:province":"GA",
    "sg:tags":[
        "appraiser"
    ],
    "wof:name":"Dunaway Appraisal Svc",
    "wof:placetype":"venue"
},
  "geometry": {"coordinates":[-84.801287,33.375295],"type":"Point"}
}