{
  "type": "Feature",
  "properties": {
    "addr:full":"2501 E Piedmont Rd Ste 116 Marietta GA 30062",
    "addr:housenumber":"2501",
    "addr:postcode":"30062",
    "addr:street":"E Piedmont Rd Ste 116",
    "iso:country":"US",
    "sg:address":"2501 E Piedmont Rd Ste 116",
    "sg:city":"Marietta",
    "sg:classifiers":[
        {
            "category":"Real Estate",
            "subcategory":"Architect",
            "type":"Services"
        }
    ],
    "sg:phone":"+1 770 575 5790",
    "sg:postcode":"30062",
    "sg:province":"GA",
    "wof:name":"Jones & Associates Architects",
    "wof:placetype":"venue"
},
  "geometry": {"coordinates":[-84.489799,34.010101],"type":"Point"}
}