{
  "type": "Feature",
  "properties": {
    "addr:full":"3669 Kaci Ct Douglasville GA 30135",
    "addr:housenumber":"3669",
    "addr:postcode":"30135",
    "addr:street":"Kaci Ct",
    "iso:country":"US",
    "sg:address":"3669 Kaci Ct",
    "sg:city":"Douglasville",
    "sg:classifiers":[
        {
            "category":"Professional",
            "type":"Services"
        }
    ],
    "sg:phone":"+1 770 942 1329",
    "sg:postcode":"30135",
    "sg:province":"GA",
    "wof:name":"Kmac Inc",
    "wof:placetype":"venue"
},
  "geometry": {"coordinates":[-84.73289200000001,33.705744],"type":"Point"}
}