{
  "type": "Feature",
  "properties": {
    "iso:country":"US",
    "sg:address":"154 Yancey Rd",
    "sg:city":"Arnoldsville",
    "sg:classifiers":[
        {
            "category":"Government",
            "subcategory":"Office",
            "type":"Public Place"
        }
    ],
    "sg:phone":"+1 706 742 5036",
    "sg:postcode":"30619",
    "sg:province":"GA",
    "sg:tags":[
        "city"
    ],
    "wof:name":"Arnoldsville City Hall",
    "wof:placetype":"venue"
},
  "geometry": {"coordinates":[-83.218101,33.903251],"type":"Point"}
}