{
  "type": "Feature",
  "properties": {
    "addr:full":"320 Sunset Ave NW Atlanta GA 30314",
    "addr:housenumber":"320",
    "addr:postcode":"30314",
    "addr:street":"Sunset Ave Nw",
    "iso:country":"US",
    "sg:address":"320 Sunset Ave NW",
    "sg:city":"Atlanta",
    "sg:classifiers":[
        {
            "category":"Food & Beverages",
            "subcategory":"Groceries & Convenience Stores",
            "type":"Retail Goods"
        }
    ],
    "sg:phone":"+1 678 732 9548",
    "sg:postcode":"30314",
    "sg:province":"GA",
    "wof:name":"Sweetooth",
    "wof:placetype":"venue"
},
  "geometry": {"coordinates":[-84.40996800000001,33.76324],"type":"Point"}
}