{
  "type": "Feature",
  "properties": {
    "iso:country":"US",
    "sg:address":"2296 Henderson Mill Rd NE",
    "sg:city":"Atlanta",
    "sg:classifiers":[
        {
            "category":"Insurance",
            "subcategory":"Title Insurance",
            "type":"Services"
        }
    ],
    "sg:phone":"+1 678 636 3725",
    "sg:postcode":"30345",
    "sg:province":"GA",
    "sg:tags":[
        "mortgage"
    ],
    "wof:name":"Closing Portal",
    "wof:placetype":"venue"
},
  "geometry": {"coordinates":[-84.258926,33.852066],"type":"Point"}
}