{
  "type": "Feature",
  "properties": {
    "addr:full":"709 Stephenson Ave Savannah GA 31405",
    "addr:housenumber":"709",
    "addr:postcode":"31405",
    "addr:street":"Stephenson Ave",
    "iso:country":"US",
    "sg:address":"709 Stephenson Ave",
    "sg:city":"Savannah",
    "sg:classifiers":[
        {
            "category":"Shopping",
            "subcategory":"Gifts & Souvenirs",
            "type":"Retail Goods"
        }
    ],
    "sg:phone":"+1 912 691 1940",
    "sg:postcode":"31405",
    "sg:province":"GA",
    "sg:tags":[
        "equipment"
    ],
    "wof:name":"In Any Event",
    "wof:placetype":"venue"
},
  "geometry": {"coordinates":[-81.09989299999999,32.009985],"type":"Point"}
}