{
  "type": "Feature",
  "properties": {
    "iso:country":"US",
    "sg:address":"2404 Candler Rd",
    "sg:city":"Decatur",
    "sg:classifiers":[
        {
            "category":"Health Services",
            "subcategory":"Doctor",
            "type":"Services"
        }
    ],
    "sg:phone":"+1 404 289 5660",
    "sg:postcode":"30032",
    "sg:province":"GA",
    "sg:tags":[
        "dentist"
    ],
    "wof:name":"C David KNOX & Assoc",
    "wof:placetype":"venue"
},
  "geometry": {"coordinates":[-84.275432,33.718463],"type":"Point"}
}