{
  "type": "Feature",
  "properties": {
    "addr:full":"4156 Napier Ave Macon GA 31210",
    "addr:housenumber":"4156",
    "addr:postcode":"31210",
    "addr:street":"Napier Ave",
    "iso:country":"US",
    "sg:address":"4156 Napier Ave",
    "sg:city":"Macon",
    "sg:classifiers":[
        {
            "category":"Wholesale",
            "subcategory":"Electrical",
            "type":"Manufacturing & Wholesale Goods"
        }
    ],
    "sg:phone":"+1 478 475 5579",
    "sg:postcode":"31210",
    "sg:province":"GA",
    "sg:tags":[
        "control",
        "security",
        "system"
    ],
    "wof:name":"Security Network",
    "wof:placetype":"venue"
},
  "geometry": {"coordinates":[-83.69476400000001,32.860611],"type":"Point"}
}