{
  "type": "Feature",
  "properties": {
    "iso:country":"US",
    "sg:address":"5451 Bowman Rd",
    "sg:city":"Macon",
    "sg:classifiers":[
        {
            "category":"Personal",
            "subcategory":"Nail Salon",
            "type":"Services"
        }
    ],
    "sg:phone":"+1 478 477 7455",
    "sg:postcode":"31210",
    "sg:province":"GA",
    "wof:name":"Sassy Nails",
    "wof:placetype":"venue"
},
  "geometry": {"coordinates":[-83.733644,32.925625],"type":"Point"}
}