{
  "type": "Feature",
  "properties": {
    "addr:full":"1608 Bull St Savannah GA 31401",
    "addr:housenumber":"1608",
    "addr:postcode":"31401",
    "addr:street":"Bull St",
    "iso:country":"US",
    "sg:address":"1608 Bull St",
    "sg:city":"Savannah",
    "sg:classifiers":[
        {
            "category":"Personal",
            "subcategory":"Beauty Salon",
            "type":"Services"
        }
    ],
    "sg:phone":"+1 912 233 6668",
    "sg:postcode":"31401",
    "sg:province":"GA",
    "sg:tags":[
        "shop"
    ],
    "wof:name":"Something To Talk About",
    "wof:placetype":"venue"
},
  "geometry": {"coordinates":[-81.098882,32.060442],"type":"Point"}
}