{
  "type": "Feature",
  "properties": {
    "addr:full":"172 Haynes St SW Atlanta GA 30313",
    "addr:housenumber":"172",
    "addr:postcode":"30313",
    "addr:street":"Haynes St Sw",
    "iso:country":"US",
    "sg:address":"172 Haynes St SW",
    "sg:city":"Atlanta",
    "sg:classifiers":[
        {
            "category":"Real Estate",
            "subcategory":"Real Estate Operator",
            "type":"Services"
        }
    ],
    "sg:phone":"+1 404 522 7667",
    "sg:postcode":"30313",
    "sg:province":"GA",
    "sg:tags":[
        "building",
        "park"
    ],
    "wof:name":"GE Lofts Condo Hoa",
    "wof:placetype":"venue"
},
  "geometry": {"coordinates":[-84.400396,33.749743],"type":"Point"}
}