{
  "type": "Feature",
  "properties": {
    "addr:full":"4482 Beacon Hill Dr Lilburn GA 30047",
    "addr:housenumber":"4482",
    "addr:postcode":"30047",
    "addr:street":"Beacon Hill Dr",
    "iso:country":"US",
    "sg:address":"4482 Beacon Hill Dr",
    "sg:city":"Lilburn",
    "sg:classifiers":[
        {
            "category":"Professional",
            "subcategory":"Business Services",
            "type":"Services"
        }
    ],
    "sg:phone":"+1 678 380 8928",
    "sg:postcode":"30047",
    "sg:province":"GA",
    "wof:name":"Afzal Enterprises Inc",
    "wof:placetype":"venue"
},
  "geometry": {"coordinates":[-84.103093,33.8566],"type":"Point"}
}