{
  "type": "Feature",
  "properties": {
    "iso:country":"US",
    "sg:address":"233 W Main St",
    "sg:city":"Manchester",
    "sg:classifiers":[
        {
            "category":"Shopping",
            "subcategory":"Clothing, Apparel, & Fashions",
            "type":"Retail Goods"
        }
    ],
    "sg:phone":"+1 706 846 2699",
    "sg:postcode":"31816",
    "sg:province":"GA",
    "sg:tags":[
        "printing",
        "commercial",
        "sportswear"
    ],
    "wof:name":"Sideline Sports",
    "wof:placetype":"venue"
},
  "geometry": {"coordinates":[-84.61629499999999,32.853073],"type":"Point"}
}