{
  "type": "Feature",
  "properties": {
    "iso:country":"US",
    "sg:address":"2680 Sandstone Dr",
    "sg:city":"Lawrenceville",
    "sg:classifiers":[
        {
            "category":"Professional",
            "type":"Services"
        }
    ],
    "sg:phone":"+1 770 963 9283",
    "sg:postcode":"30043",
    "sg:province":"GA",
    "wof:name":"A J Volpi",
    "wof:placetype":"venue"
},
  "geometry": {"coordinates":[-84.00608800000001,34.038707],"type":"Point"}
}