{
  "type": "Feature",
  "properties": {
    "iso:country":"US",
    "sg:address":"471 Mount Vernon Hwy",
    "sg:city":"Atlanta",
    "sg:classifiers":[
        {
            "category":"Professional",
            "subcategory":"Management & Consulting",
            "type":"Services"
        },
        {
            "category":"Restaurant",
            "type":"Food & Drink"
        }
    ],
    "sg:phone":"+1 404 303 9535",
    "sg:postcode":"30328",
    "sg:province":"GA",
    "sg:tags":[
        "eating"
    ],
    "wof:name":"Southern Foodservice Mgmt",
    "wof:placetype":"venue"
},
  "geometry": {"coordinates":[-84.37369,33.924342],"type":"Point"}
}