{
  "type": "Feature",
  "properties": {
    "addr:full":"1800 Dogwood Dr SE Conyers GA 30013",
    "addr:housenumber":"1800",
    "addr:postcode":"30013",
    "addr:street":"Dogwood Dr Se",
    "iso:country":"US",
    "sg:address":"1800 Dogwood Dr SE",
    "sg:city":"Conyers",
    "sg:classifiers":[
        {
            "category":"Shopping",
            "subcategory":"Optician",
            "type":"Retail Goods"
        }
    ],
    "sg:phone":"+1 770 761 3629",
    "sg:postcode":"30013",
    "sg:province":"GA",
    "sg:tags":[
        "eyewear"
    ],
    "wof:name":"Bj's Optical",
    "wof:placetype":"venue"
},
  "geometry": {"coordinates":[-83.99189800000001,33.6455],"type":"Point"}
}