{
  "type": "Feature",
  "properties": {
    "iso:country":"US",
    "sg:address":"470 Cason Rd",
    "sg:city":"Cedartown",
    "sg:classifiers":[
        {
            "category":"Retail",
            "subcategory":"Auto Repair",
            "type":"Services"
        }
    ],
    "sg:phone":"+1 770 749 0280",
    "sg:postcode":"30125",
    "sg:province":"GA",
    "sg:tags":[
        "general"
    ],
    "wof:name":"Brooks Automotive",
    "wof:placetype":"venue"
},
  "geometry": {"coordinates":[-85.25026699999999,33.988236],"type":"Point"}
}