{
  "type": "Feature",
  "properties": {
    "addr:full":"2517 Sylvester Hwy Albany GA 31705",
    "addr:housenumber":"2517",
    "addr:postcode":"31705",
    "addr:street":"Sylvester Hwy",
    "iso:country":"US",
    "sg:address":"2517 Sylvester Hwy",
    "sg:city":"Albany",
    "sg:classifiers":[
        {
            "category":"Home & Garden",
            "subcategory":"Mobile Homes",
            "type":"Retail Goods"
        }
    ],
    "sg:phone":"+1 229 435 1144",
    "sg:postcode":"31705",
    "sg:province":"GA",
    "wof:name":"Clayton Homes",
    "wof:placetype":"venue"
},
  "geometry": {"coordinates":[-84.084361,31.574817],"type":"Point"}
}