{
  "type": "Feature",
  "properties": {
    "iso:country":"US",
    "sg:address":"3515 Old Petersburg Rd",
    "sg:city":"Augusta",
    "sg:classifiers":[
        {
            "category":"Shopping",
            "subcategory":"Discount & Variety Stores",
            "type":"Retail Goods"
        }
    ],
    "sg:phone":"+1 706 854 9143",
    "sg:postcode":"30907",
    "sg:province":"GA",
    "wof:name":"Dollar Wash",
    "wof:placetype":"venue"
},
  "geometry": {"coordinates":[-82.07448100000001,33.516922],"type":"Point"}
}