{
  "type": "Feature",
  "properties": {
    "addr:full":"836 N Atlanta St Roswell GA 30075",
    "addr:housenumber":"836",
    "addr:postcode":"30075",
    "addr:street":"N Atlanta St",
    "iso:country":"US",
    "sg:address":"836 N Atlanta St",
    "sg:city":"Roswell",
    "sg:classifiers":[
        {
            "category":"Shopping",
            "subcategory":"Computers & Home Electronics",
            "type":"Retail Goods"
        }
    ],
    "sg:phone":"+1 770 992 1969",
    "sg:postcode":"30075",
    "sg:province":"GA",
    "sg:tags":[
        "television",
        "radio"
    ],
    "wof:name":"Radio City",
    "wof:placetype":"venue"
},
  "geometry": {"coordinates":[-84.36179799999999,34.020211],"type":"Point"}
}