{
  "type": "Feature",
  "properties": {
    "addr:full":"327 Monroe St Ste A Clarkesville GA 30523",
    "addr:housenumber":"327",
    "addr:postcode":"30523",
    "addr:street":"Monroe St Ste A",
    "iso:country":"US",
    "sg:address":"327 Monroe St Ste A",
    "sg:city":"Clarkesville",
    "sg:classifiers":[
        {
            "category":"Fast Food",
            "type":"Food & Drink"
        },
        {
            "category":"Restaurant",
            "type":"Food & Drink"
        }
    ],
    "sg:phone":"+1 706 754 1540",
    "sg:postcode":"30523",
    "sg:province":"GA",
    "sg:tags":[
        "take",
        "pizza"
    ],
    "sg:website":"http://www.papaspizzatogo.com",
    "wof:name":"Papas Pizza To Go",
    "wof:placetype":"venue"
},
  "geometry": {"coordinates":[-83.530226,34.613491],"type":"Point"}
}