{
  "type": "Feature",
  "properties": {
    "iso:country":"US",
    "sg:address":"7101 Peachford Cir",
    "sg:city":"Atlanta",
    "sg:classifiers":[
        {
            "category":"Building & Trades",
            "subcategory":"Electrical",
            "type":"Services"
        }
    ],
    "sg:phone":"+1 770 455 9319",
    "sg:postcode":"30338",
    "sg:province":"GA",
    "sg:tags":[
        "electrical",
        "contractor"
    ],
    "wof:name":"Garden State Electric",
    "wof:placetype":"venue"
},
  "geometry": {"coordinates":[-84.30466800000001,33.923191],"type":"Point"}
}