{
  "type": "Feature",
  "properties": {
    "addr:full":"4625 Canton Hwy Cumming GA 30040",
    "addr:housenumber":"4625",
    "addr:postcode":"30040",
    "addr:street":"Canton Hwy",
    "iso:country":"US",
    "sg:address":"4625 Canton Hwy",
    "sg:city":"Cumming",
    "sg:classifiers":[
        {
            "category":"Organizations",
            "subcategory":"Religious Organization",
            "type":"Services"
        }
    ],
    "sg:phone":"+1 770 205 7652",
    "sg:postcode":"30040",
    "sg:province":"GA",
    "sg:tags":[
        "church"
    ],
    "wof:name":"Gods House Of Prayer",
    "wof:placetype":"venue"
},
  "geometry": {"coordinates":[-84.255072,34.237481],"type":"Point"}
}