{
  "type": "Feature",
  "properties": {
    "addr:full":"1251 McIntosh Rd Douglasville GA 30134",
    "addr:housenumber":"1251",
    "addr:postcode":"30134",
    "addr:street":"Mcintosh Rd",
    "iso:country":"US",
    "sg:address":"1251 McIntosh Rd",
    "sg:city":"Douglasville",
    "sg:classifiers":[
        {
            "category":"Building & Trades",
            "subcategory":"Construction",
            "type":"Services"
        }
    ],
    "sg:phone":"+1 770 942 1228",
    "sg:postcode":"30134",
    "sg:province":"GA",
    "sg:tags":[
        "painter"
    ],
    "wof:name":"Progressive Painting & Wlpaper",
    "wof:placetype":"venue"
},
  "geometry": {"coordinates":[-84.725685,33.769688],"type":"Point"}
}