{
  "type": "Feature",
  "properties": {
    "addr:full":"2450 Galleria Pkwy Atlanta GA 30339",
    "addr:housenumber":"2450",
    "addr:postcode":"30339",
    "addr:street":"Galleria Pkwy",
    "iso:country":"US",
    "sg:address":"2450 Galleria Pkwy",
    "sg:city":"Atlanta",
    "sg:classifiers":[
        {
            "category":"Shopping",
            "subcategory":"Gifts & Souvenirs",
            "type":"Retail Goods"
        }
    ],
    "sg:phone":"+1 770 951 1728",
    "sg:postcode":"30339",
    "sg:province":"GA",
    "sg:tags":[
        "shop",
        "newsstand"
    ],
    "wof:name":"W H Smith 376",
    "wof:placetype":"venue"
},
  "geometry": {"coordinates":[-84.465463,33.882652],"type":"Point"}
}