{
  "type": "Feature",
  "properties": {
    "iso:country":"US",
    "sg:address":"4902 Hwy 9 N",
    "sg:city":"Alpharetta",
    "sg:classifiers":[
        {
            "category":"Restaurant",
            "type":"Food & Drink"
        }
    ],
    "sg:phone":"+1 678 879 9855",
    "sg:postcode":"30004",
    "sg:province":"GA",
    "wof:name":"Roasted Garlic The",
    "wof:placetype":"venue"
},
  "geometry": {"coordinates":[-84.238231,34.158355],"type":"Point"}
}