{
  "type": "Feature",
  "properties": {
    "iso:country":"US",
    "sg:address":"101 Industrial Park Dr",
    "sg:city":"Cumming",
    "sg:classifiers":[
        {
            "category":"Manufacturing",
            "subcategory":"Tools & Machinery",
            "type":"Manufacturing & Wholesale Goods"
        }
    ],
    "sg:phone":"+1 770 781 8855",
    "sg:postcode":"30040",
    "sg:province":"GA",
    "sg:tags":[
        "machine",
        "shop"
    ],
    "wof:name":"Mc Cullough Manufacturing Inc",
    "wof:placetype":"venue"
},
  "geometry": {"coordinates":[-84.14615499999999,34.19543],"type":"Point"}
}