{
  "type": "Feature",
  "properties": {
    "iso:country":"US",
    "sg:address":"1000 Northside Dr NW",
    "sg:city":"Atlanta",
    "sg:classifiers":[
        {
            "category":"Real Estate",
            "subcategory":"Real Estate Operator",
            "type":"Services"
        }
    ],
    "sg:phone":"+1 877 707 7691",
    "sg:postcode":"30318",
    "sg:province":"GA",
    "sg:tags":[
        "apartment"
    ],
    "sg:website":"http://local.ingenio.com/Listings/Details.aspx?NUM=a%3a10248516%3a13%3a4859924%3a14%3a0%3a7",
    "wof:name":"Tivoli Tenside",
    "wof:placetype":"venue"
},
  "geometry": {"coordinates":[-84.40749099999999,33.781794],"type":"Point"}
}