{
  "type": "Feature",
  "properties": {
    "iso:country":"US",
    "sg:address":"764 Attapulgas Climax Rd",
    "sg:city":"Climax",
    "sg:classifiers":[
        {
            "category":"Retail",
            "subcategory":"Auto Repair",
            "type":"Services"
        }
    ],
    "sg:phone":"+1 229 248 6500",
    "sg:postcode":"39834",
    "sg:province":"GA",
    "sg:tags":[
        "truck"
    ],
    "wof:name":"Climax Tractor Co",
    "wof:placetype":"venue"
},
  "geometry": {"coordinates":[-84.469397,30.840663],"type":"Point"}
}