{
  "type": "Feature",
  "properties": {
    "iso:country":"US",
    "sg:address":"700 Davis Ave",
    "sg:city":"Savannah",
    "sg:classifiers":[
        {
            "category":"Social Services",
            "subcategory":"Child Care",
            "type":"Services"
        }
    ],
    "sg:phone":"+1 912 964 6012",
    "sg:postcode":"31408",
    "sg:province":"GA",
    "wof:name":"Cooper Head Start Ctr",
    "wof:placetype":"venue"
},
  "geometry": {"coordinates":[-81.15004399999999,32.096492],"type":"Point"}
}