{
  "type": "Feature",
  "properties": {
    "addr:full":"1535 Irby Rd Fort Valley GA 31030",
    "addr:housenumber":"1535",
    "addr:postcode":"31030",
    "addr:street":"Irby Rd",
    "iso:country":"US",
    "sg:address":"1535 Irby Rd",
    "sg:city":"Fort Valley",
    "sg:classifiers":[
        {
            "category":"Farming",
            "subcategory":"Nursery",
            "type":"Manufacturing & Wholesale Goods"
        }
    ],
    "sg:phone":"+1 478 825 8430",
    "sg:postcode":"31030",
    "sg:province":"GA",
    "sg:tags":[
        "ornamental"
    ],
    "wof:name":"Spillers Farm",
    "wof:placetype":"venue"
},
  "geometry": {"coordinates":[-83.811458,32.512433],"type":"Point"}
}