{
  "type": "Feature",
  "properties": {
    "addr:full":"750 Bugscuffle Rd Hiawassee GA 30546",
    "addr:housenumber":"750",
    "addr:postcode":"30546",
    "addr:street":"Bugscuffle Rd",
    "iso:country":"US",
    "sg:address":"750 Bugscuffle Rd",
    "sg:city":"Hiawassee",
    "sg:classifiers":[
        {
            "category":"Freight",
            "type":"Transportation"
        }
    ],
    "sg:phone":"+1 706 896 3819",
    "sg:postcode":"30546",
    "sg:province":"GA",
    "sg:tags":[
        "operator",
        "local",
        "trucking"
    ],
    "wof:name":"Jerry Turpin Trucking Inc",
    "wof:placetype":"venue"
},
  "geometry": {"coordinates":[-83.72735400000001,34.936183],"type":"Point"}
}