{
  "type": "Feature",
  "properties": {
    "iso:country":"US",
    "sg:address":"254 Old County Rd",
    "sg:city":"Ringgold",
    "sg:classifiers":[
        {
            "category":"Professional",
            "subcategory":"Management & Consulting",
            "type":"Services"
        },
        {
            "category":"Professional",
            "subcategory":"Advertising",
            "type":"Services"
        }
    ],
    "sg:phone":"+1 706 965 5793",
    "sg:postcode":"30736",
    "sg:province":"GA",
    "sg:tags":[
        "marketing",
        "program",
        "consultant"
    ],
    "wof:name":"Southern Sales Mktg",
    "wof:placetype":"venue"
},
  "geometry": {"coordinates":[-85.121189,34.919258],"type":"Point"}
}