{
  "type": "Feature",
  "properties": {
    "addr:full":"2800 Plant Atkinson Rd Smyrna GA 30080",
    "addr:housenumber":"2800",
    "addr:postcode":"30080",
    "addr:street":"Plant Atkinson Rd",
    "iso:country":"US",
    "sg:address":"2800 Plant Atkinson Rd",
    "sg:city":"Smyrna",
    "sg:classifiers":[
        {
            "category":"Wholesale",
            "subcategory":"Hardware",
            "type":"Manufacturing & Wholesale Goods"
        }
    ],
    "sg:phone":"+1 404 351 1010",
    "sg:postcode":"30080",
    "sg:province":"GA",
    "sg:tags":[
        "heater",
        "make",
        "air"
    ],
    "sg:website":"www.tombarrow.com",
    "wof:name":"Tom Barrow Co Inc",
    "wof:placetype":"venue"
},
  "geometry": {"coordinates":[-84.478042,33.831738],"type":"Point"}
}