{
  "type": "Feature",
  "properties": {
    "addr:full":"2673 Chimney Springs Dr Marietta GA 30062",
    "addr:housenumber":"2673",
    "addr:postcode":"30062",
    "addr:street":"Chimney Springs Dr",
    "iso:country":"US",
    "sg:address":"2673 Chimney Springs Dr",
    "sg:city":"Marietta",
    "sg:classifiers":[
        {
            "category":"Shopping",
            "subcategory":"Hobbies, Toys, & Games",
            "type":"Retail Goods"
        }
    ],
    "sg:phone":"+1 770 518 8407",
    "sg:postcode":"30062",
    "sg:province":"GA",
    "wof:name":"Glory Bee",
    "wof:placetype":"venue"
},
  "geometry": {"coordinates":[-84.415305,34.010809],"type":"Point"}
}