{
  "type": "Feature",
  "properties": {
    "iso:country":"US",
    "sg:address":"6356 State Rte 85",
    "sg:city":"Riverdale",
    "sg:classifiers":[
        {
            "category":"Shopping",
            "subcategory":"Musical Instruments",
            "type":"Retail Goods"
        }
    ],
    "sg:phone":"+1 678 216 0660",
    "sg:postcode":"30274",
    "sg:province":"GA",
    "sg:tags":[
        "music",
        "dealer"
    ],
    "wof:name":"Pro Music Outlet",
    "wof:placetype":"venue"
},
  "geometry": {"coordinates":[-84.41077300000001,33.583635],"type":"Point"}
}