{
  "type": "Feature",
  "properties": {
    "iso:country":"US",
    "sg:address":"3844 Leprechaun Ct",
    "sg:city":"Decatur",
    "sg:classifiers":[
        {
            "category":"Retail",
            "subcategory":"Repair Shop",
            "type":"Services"
        }
    ],
    "sg:phone":"+1 404 289 0505",
    "sg:postcode":"30034",
    "sg:province":"GA",
    "sg:tags":[
        "lock",
        "locksmith"
    ],
    "wof:name":"Auto Lock & Key",
    "wof:placetype":"venue"
},
  "geometry": {"coordinates":[-84.23609,33.710547],"type":"Point"}
}