{
  "type": "Feature",
  "properties": {
    "addr:full":"3405 Covington Dr Decatur GA 30032",
    "addr:housenumber":"3405",
    "addr:postcode":"30032",
    "addr:street":"Covington Dr",
    "iso:country":"US",
    "sg:address":"3405 Covington Dr",
    "sg:city":"Decatur",
    "sg:classifiers":[
        {
            "category":"Food & Beverages",
            "subcategory":"Specialty",
            "type":"Retail Goods"
        }
    ],
    "sg:phone":"+1 404 288 6638",
    "sg:postcode":"30032",
    "sg:province":"GA",
    "sg:tags":[
        "herb"
    ],
    "wof:name":"Sundial Natural Mystic Herbal",
    "wof:placetype":"venue"
},
  "geometry": {"coordinates":[-84.248194,33.761468],"type":"Point"}
}