{
  "type": "Feature",
  "properties": {
    "addr:full":"7314 Alexander Cir Fort Stewart GA 31315",
    "addr:housenumber":"7314",
    "addr:postcode":"31315",
    "addr:street":"Alexander Cir",
    "iso:country":"US",
    "sg:address":"7314 Alexander Cir",
    "sg:city":"Fort Stewart",
    "sg:classifiers":[
        {
            "category":"Professional",
            "subcategory":"Accounting & Tax Preparation",
            "type":"Services"
        }
    ],
    "sg:phone":"+1 912 370 2852",
    "sg:postcode":"31315",
    "sg:province":"GA",
    "sg:tags":[
        "bookkeeping"
    ],
    "wof:name":"Sharon Binion",
    "wof:placetype":"venue"
},
  "geometry": {"coordinates":[-81.594385,31.891333],"type":"Point"}
}