{
  "type": "Feature",
  "properties": {
    "iso:country":"US",
    "sg:address":"17535 State Rte 34",
    "sg:city":"Franklin",
    "sg:classifiers":[
        {
            "category":"Retail",
            "subcategory":"Auto Repair",
            "type":"Services"
        }
    ],
    "sg:phone":"+1 706 675 0220",
    "sg:postcode":"30217",
    "sg:province":"GA",
    "sg:tags":[
        "glass",
        "replacement"
    ],
    "wof:name":"Premium Auto Glass",
    "wof:placetype":"venue"
},
  "geometry": {"coordinates":[-85.012941,33.326797],"type":"Point"}
}