{
  "type": "Feature",
  "properties": {
    "iso:country":"US",
    "sg:address":"5116 Gilgal Way",
    "sg:city":"Ellenwood",
    "sg:classifiers":[
        {
            "category":"Transit Center",
            "subcategory":"Freight",
            "type":"Transportation"
        },
        {
            "category":"Freight",
            "type":"Transportation"
        }
    ],
    "sg:phone":"+1 404 293 3176",
    "sg:postcode":"30294",
    "sg:province":"GA",
    "sg:tags":[
        "local",
        "trucking-motor",
        "trucking"
    ],
    "wof:name":"J & D Neal Trucking, Inc.",
    "wof:placetype":"venue"
},
  "geometry": {"coordinates":[-84.278644,33.614141],"type":"Point"}
}