{
  "type": "Feature",
  "properties": {
    "iso:country":"US",
    "sg:address":"5009 US Hwy 27",
    "sg:city":"La Fayette",
    "sg:classifiers":[
        {
            "category":"Food & Beverages",
            "subcategory":"Groceries & Convenience Stores",
            "type":"Retail Goods"
        }
    ],
    "sg:phone":"+1 706 764 2110",
    "sg:postcode":"30728",
    "sg:province":"GA",
    "sg:tags":[
        "grocer"
    ],
    "wof:name":"Pit Stop Food Stores",
    "wof:placetype":"venue"
},
  "geometry": {"coordinates":[-85.255403,34.77902],"type":"Point"}
}