{
  "type": "Feature",
  "properties": {
    "iso:country":"US",
    "sg:address":"1065 Pepperwood Trl",
    "sg:city":"Norcross",
    "sg:classifiers":[
        {
            "category":"Professional",
            "type":"Services"
        }
    ],
    "sg:phone":"+1 770 717 0110",
    "sg:postcode":"30093",
    "sg:province":"GA",
    "wof:name":"Lilis Creations",
    "wof:placetype":"venue"
},
  "geometry": {"coordinates":[-84.14698300000001,33.913749],"type":"Point"}
}