{
  "type": "Feature",
  "properties": {
    "iso:country":"US",
    "sg:address":"113 Winston St",
    "sg:city":"Reynolds",
    "sg:classifiers":[
        {
            "category":"Retail",
            "subcategory":"Laundry & Dry Cleaning",
            "type":"Services"
        }
    ],
    "sg:phone":"+1 478 847 2764",
    "sg:postcode":"31076",
    "sg:province":"GA",
    "wof:name":"Maloy Laundry & Dry Cleaners",
    "wof:placetype":"venue"
},
  "geometry": {"coordinates":[-84.09623000000001,32.558334],"type":"Point"}
}