{
  "type": "Feature",
  "properties": {
    "iso:country":"US",
    "sg:address":"5778 Trotters Ct",
    "sg:city":"Stone Mountain",
    "sg:classifiers":[
        {
            "category":"Organizations",
            "subcategory":"Membership Organization",
            "type":"Services"
        }
    ],
    "sg:phone":"+1 770 414 4244",
    "sg:postcode":"30087",
    "sg:province":"GA",
    "wof:name":"Summit Community Assoc In",
    "wof:placetype":"venue"
},
  "geometry": {"coordinates":[-84.155405,33.834464],"type":"Point"}
}