{
  "type": "Feature",
  "properties": {
    "iso:country":"US",
    "sg:address":"1885 Harper Dr Apt 15A",
    "sg:city":"Morrow",
    "sg:classifiers":[
        {
            "category":"Shopping",
            "subcategory":"Clothing, Apparel, & Fashions",
            "type":"Retail Goods"
        }
    ],
    "sg:phone":"+1 404 452 8312",
    "sg:postcode":"30260",
    "sg:province":"GA",
    "sg:tags":[
        "apparel",
        "women's"
    ],
    "wof:name":"Livin' Life Clothing Co",
    "wof:placetype":"venue"
},
  "geometry": {"coordinates":[-84.326273,33.599542],"type":"Point"}
}