{
  "type": "Feature",
  "properties": {
    "iso:country":"US",
    "sg:address":"1823 Chase Common Dr",
    "sg:city":"Norcross",
    "sg:classifiers":[
        {
            "category":"Professional",
            "subcategory":"Business Services",
            "type":"Services"
        }
    ],
    "sg:phone":"+1 770 582 0016",
    "sg:postcode":"30071",
    "sg:province":"GA",
    "sg:tags":[
        "recording",
        "studio"
    ],
    "wof:name":"Majestic Flava Entertainment",
    "wof:placetype":"venue"
},
  "geometry": {"coordinates":[-84.20063399999999,33.921601],"type":"Point"}
}