{
  "type": "Feature",
  "properties": {
    "addr:full":"6702 Shannon Pkwy Union City GA 30291",
    "addr:housenumber":"6702",
    "addr:postcode":"30291",
    "addr:street":"Shannon Pkwy",
    "iso:country":"US",
    "sg:address":"6702 Shannon Pkwy",
    "sg:city":"Union City",
    "sg:classifiers":[
        {
            "category":"Retail",
            "subcategory":"Veterinary Services",
            "type":"Services"
        },
        {
            "category":"Retail",
            "subcategory":"Pet Boarding",
            "type":"Services"
        }
    ],
    "sg:phone":"+1 770 964 0700",
    "sg:postcode":"30291",
    "sg:province":"GA",
    "sg:tags":[
        "veterinarian",
        "boarding/pet",
        "sitting"
    ],
    "wof:name":"Un City Veterinary Medical Ctr & Emergency Clinic",
    "wof:placetype":"venue"
},
  "geometry": {"coordinates":[-84.539497,33.572399],"type":"Point"}
}