{
  "type": "Feature",
  "properties": {
    "iso:country":"US",
    "sg:address":"5134 Timber Trl NE",
    "sg:city":"Atlanta",
    "sg:classifiers":[
        {
            "category":"Professional",
            "subcategory":"Business Services",
            "type":"Services"
        }
    ],
    "sg:phone":"+1 404 255 1430",
    "sg:postcode":"30342",
    "sg:province":"GA",
    "sg:tags":[
        "commercial",
        "design"
    ],
    "wof:name":"Susan Wells and Associates",
    "wof:placetype":"venue"
},
  "geometry": {"coordinates":[-84.371487,33.900078],"type":"Point"}
}