{
  "type": "Feature",
  "properties": {
    "addr:full":"118 12th Ave E Cordele GA 31015",
    "addr:housenumber":"118",
    "addr:postcode":"31015",
    "addr:street":"12Th Ave E",
    "iso:country":"US",
    "sg:address":"118 12th Ave E",
    "sg:city":"Cordele",
    "sg:classifiers":[
        {
            "category":"Health Services",
            "subcategory":"Chiropractor",
            "type":"Services"
        }
    ],
    "sg:phone":"+1 229 273 3977",
    "sg:postcode":"31015",
    "sg:province":"GA",
    "wof:name":"Gentle Chiropractic Wellness",
    "wof:placetype":"venue"
},
  "geometry": {"coordinates":[-83.781385,31.967901],"type":"Point"}
}