{
  "type": "Feature",
  "properties": {
    "addr:full":"1305 Fallsbrook Ter Acworth GA 30101",
    "addr:housenumber":"1305",
    "addr:postcode":"30101",
    "addr:street":"Fallsbrook Ter",
    "iso:country":"US",
    "sg:address":"1305 Fallsbrook Ter",
    "sg:city":"Acworth",
    "sg:classifiers":[
        {
            "category":"Professional",
            "subcategory":"Management & Consulting",
            "type":"Services"
        }
    ],
    "sg:phone":"+1 770 425 7666",
    "sg:postcode":"30101",
    "sg:province":"GA",
    "sg:tags":[
        "business"
    ],
    "wof:name":"Sorsco Inc",
    "wof:placetype":"venue"
},
  "geometry": {"coordinates":[-84.71795899999999,33.990522],"type":"Point"}
}