{
  "type": "Feature",
  "properties": {
    "iso:country":"US",
    "sg:address":"3031 E Ponce De Leon Ave",
    "sg:city":"Decatur",
    "sg:classifiers":[
        {
            "category":"Shopping",
            "subcategory":"Discount & Variety Stores",
            "type":"Retail Goods"
        }
    ],
    "sg:phone":"+1 404 452 2333",
    "sg:postcode":"30030",
    "sg:province":"GA",
    "sg:tags":[
        "wholesale"
    ],
    "wof:name":"Bargain Warehouse Outlet Store",
    "wof:placetype":"venue"
},
  "geometry": {"coordinates":[-84.27052500000001,33.784317],"type":"Point"}
}