{
  "type": "Feature",
  "properties": {
    "iso:country":"US",
    "sg:address":"120 N Louise Ave",
    "sg:city":"Calhoun",
    "sg:classifiers":[
        {
            "category":"Government",
            "subcategory":"Office",
            "type":"Public Place"
        }
    ],
    "sg:phone":"+1 706 629 1846",
    "sg:postcode":"30701",
    "sg:province":"GA",
    "sg:tags":[
        "village"
    ],
    "wof:name":"Calhoun Sewer Infiltration",
    "wof:placetype":"venue"
},
  "geometry": {"coordinates":[-84.95062299999999,34.489202],"type":"Point"}
}