{
  "type": "Feature",
  "properties": {
    "iso:country":"US",
    "sg:address":"4805 Powder Springs Rd",
    "sg:city":"Austell",
    "sg:classifiers":[
        {
            "category":"Building & Trades",
            "subcategory":"Plumbing",
            "type":"Services"
        }
    ],
    "sg:phone":"+1 770 941 3373",
    "sg:postcode":"30106",
    "sg:province":"GA",
    "sg:tags":[
        "heat",
        "pump"
    ],
    "wof:name":"E Dennis Inc",
    "wof:placetype":"venue"
},
  "geometry": {"coordinates":[-84.65845299999999,33.839201],"type":"Point"}
}