{
  "type": "Feature",
  "properties": {
    "addr:full":"4652 Mahonia Way Acworth GA 30102",
    "addr:housenumber":"4652",
    "addr:postcode":"30102",
    "addr:street":"Mahonia Way",
    "iso:country":"US",
    "sg:address":"4652 Mahonia Way",
    "sg:city":"Acworth",
    "sg:classifiers":[
        {
            "category":"Retail",
            "subcategory":"Portrait Studio",
            "type":"Services"
        }
    ],
    "sg:phone":"+1 770 919 8133",
    "sg:postcode":"30102",
    "sg:province":"GA",
    "sg:tags":[
        "photo"
    ],
    "wof:name":"Kingsley Photography",
    "wof:placetype":"venue"
},
  "geometry": {"coordinates":[-84.593174,34.067674],"type":"Point"}
}