{
  "type": "Feature",
  "properties": {
    "addr:full":"6102 E Oglethorpe Hwy Midway GA 31320",
    "addr:housenumber":"6102",
    "addr:postcode":"31320",
    "addr:street":"E Oglethorpe Hwy",
    "iso:country":"US",
    "sg:address":"6102 E Oglethorpe Hwy",
    "sg:city":"Midway",
    "sg:classifiers":[
        {
            "category":"Place Of Worship",
            "type":"Public Place"
        },
        {
            "category":"Place Of Worship",
            "subcategory":"Temple",
            "type":"Public Place"
        }
    ],
    "sg:phone":"+1 912 884 5770",
    "sg:postcode":"31320",
    "sg:province":"GA",
    "sg:tags":[
        "church"
    ],
    "wof:name":"Zion Temple Holliness Ch",
    "wof:placetype":"venue"
},
  "geometry": {"coordinates":[-81.414086,31.799763],"type":"Point"}
}