{
  "type": "Feature",
  "properties": {
    "iso:country":"US",
    "sg:address":"300 Morning Pine Way",
    "sg:city":"Alpharetta",
    "sg:classifiers":[
        {
            "category":"Building & Trades",
            "subcategory":"Construction",
            "type":"Services"
        }
    ],
    "sg:phone":"+1 770 346 0836",
    "sg:postcode":"30005",
    "sg:province":"GA",
    "sg:tags":[
        "residential"
    ],
    "wof:name":"Home Refinements",
    "wof:placetype":"venue"
},
  "geometry": {"coordinates":[-84.194919,34.083356],"type":"Point"}
}