{
  "type": "Feature",
  "properties": {
    "addr:full":"2445 Rex Rd Ellenwood GA 30294",
    "addr:housenumber":"2445",
    "addr:postcode":"30294",
    "addr:street":"Rex Rd",
    "iso:country":"US",
    "sg:address":"2445 Rex Rd",
    "sg:city":"Ellenwood",
    "sg:classifiers":[
        {
            "category":"Manufacturing",
            "subcategory":"Printing",
            "type":"Manufacturing & Wholesale Goods"
        }
    ],
    "sg:phone":"+1 770 960 8098",
    "sg:postcode":"30294",
    "sg:province":"GA",
    "sg:tags":[
        "publishing"
    ],
    "wof:name":"Miluv Publishing Co",
    "wof:placetype":"venue"
},
  "geometry": {"coordinates":[-84.31030800000001,33.595172],"type":"Point"}
}