{
  "type": "Feature",
  "properties": {
    "addr:full":"4555 Doral Dr SW Atlanta GA 30331",
    "addr:housenumber":"4555",
    "addr:postcode":"30331",
    "addr:street":"Doral Dr Sw",
    "iso:country":"US",
    "sg:address":"4555 Doral Dr SW",
    "sg:city":"Atlanta",
    "sg:classifiers":[
        {
            "category":"Building & Trades",
            "subcategory":"Construction",
            "type":"Services"
        }
    ],
    "sg:phone":"+1 404 349 3327",
    "sg:postcode":"30331",
    "sg:province":"GA",
    "sg:tags":[
        "roofing",
        "consultant",
        "contractor"
    ],
    "wof:name":"John S Roofing Repair",
    "wof:placetype":"venue"
},
  "geometry": {"coordinates":[-84.537509,33.688429],"type":"Point"}
}