{
  "type": "Feature",
  "properties": {
    "addr:full":"6066 Buford Hwy NE Atlanta GA 30340",
    "addr:housenumber":"6066",
    "addr:postcode":"30340",
    "addr:street":"Buford Hwy Ne",
    "iso:country":"US",
    "sg:address":"6066 Buford Hwy NE",
    "sg:city":"Atlanta",
    "sg:classifiers":[
        {
            "category":"Autos & Motor Vehicles",
            "subcategory":"Automobile Sales",
            "type":"Retail Goods"
        }
    ],
    "sg:phone":"+1 770 458 8868",
    "sg:postcode":"30340",
    "sg:province":"GA",
    "sg:tags":[
        "dealers-used",
        "car",
        "used",
        "cars-wholesale"
    ],
    "wof:name":"Marie Lito Tavi Auto Sales Inc",
    "wof:placetype":"venue"
},
  "geometry": {"coordinates":[-84.26020800000001,33.91592],"type":"Point"}
}