{
  "type": "Feature",
  "properties": {
    "iso:country":"US",
    "sg:address":"2322 Ironwood Hill Ct",
    "sg:city":"Dacula",
    "sg:classifiers":[
        {
            "category":"Social Services",
            "subcategory":"Child Care",
            "type":"Services"
        }
    ],
    "sg:phone":"+1 770 271 2036",
    "sg:postcode":"30019",
    "sg:province":"GA",
    "sg:tags":[
        "day"
    ],
    "wof:name":"Unique Land Care Inc",
    "wof:placetype":"venue"
},
  "geometry": {"coordinates":[-83.930306,34.061852],"type":"Point"}
}