{
  "type": "Feature",
  "properties": {
    "iso:country":"US",
    "sg:address":"451 Bennett Still Hwy",
    "sg:city":"Alma",
    "sg:classifiers":[
        {
            "category":"Real Estate",
            "subcategory":"Real Estate Operator",
            "type":"Services"
        }
    ],
    "sg:phone":"+1 912 632 7387",
    "sg:postcode":"31510",
    "sg:province":"GA",
    "sg:tags":[
        "mobile",
        "home",
        "community"
    ],
    "wof:name":"Lee's Trailer Park",
    "wof:placetype":"venue"
},
  "geometry": {"coordinates":[-82.431039,31.565584],"type":"Point"}
}