{
  "type": "Feature",
  "properties": {
    "addr:full":"1399 Montreal Rd Tucker GA 30084",
    "addr:housenumber":"1399",
    "addr:postcode":"30084",
    "addr:street":"Montreal Rd",
    "iso:country":"US",
    "sg:address":"1399 Montreal Rd",
    "sg:city":"Tucker",
    "sg:classifiers":[
        {
            "category":"Personal",
            "type":"Services"
        }
    ],
    "sg:phone":"+1 770 322 6007",
    "sg:postcode":"30084",
    "sg:province":"GA",
    "sg:tags":[
        "counseling"
    ],
    "wof:name":"National African American Rela",
    "wof:placetype":"venue"
},
  "geometry": {"coordinates":[-84.25102099999999,33.824432],"type":"Point"}
}