{
  "type": "Feature",
  "properties": {
    "addr:full":"3420 Oakcliff Rd Atlanta GA 30340",
    "addr:housenumber":"3420",
    "addr:postcode":"30340",
    "addr:street":"Oakcliff Rd",
    "iso:country":"US",
    "sg:address":"3420 Oakcliff Rd",
    "sg:city":"Atlanta",
    "sg:classifiers":[
        {
            "category":"Manufacturing",
            "subcategory":"Printing",
            "type":"Manufacturing & Wholesale Goods"
        }
    ],
    "sg:phone":"+1 770 458 1451",
    "sg:postcode":"30340",
    "sg:province":"GA",
    "sg:tags":[
        "commercial",
        "proof"
    ],
    "wof:name":"Color Comps Inc",
    "wof:placetype":"venue"
},
  "geometry": {"coordinates":[-84.25334599999999,33.903059],"type":"Point"}
}