{
  "type": "Feature",
  "properties": {
    "addr:full":"3235 Valley View St Powder Springs GA 30127",
    "addr:housenumber":"3235",
    "addr:postcode":"30127",
    "addr:street":"Valley View St",
    "iso:country":"US",
    "sg:address":"3235 Valley View St",
    "sg:city":"Powder Springs",
    "sg:classifiers":[
        {
            "category":"Shopping",
            "subcategory":"Gifts & Souvenirs",
            "type":"Retail Goods"
        }
    ],
    "sg:phone":"+1 770 943 6333",
    "sg:postcode":"30127",
    "sg:province":"GA",
    "wof:name":"Bradley Richardson Inc",
    "wof:placetype":"venue"
},
  "geometry": {"coordinates":[-84.65508,33.882121],"type":"Point"}
}