{
  "type": "Feature",
  "properties": {
    "addr:full":"1782 Panola Rd Ellenwood GA 30294",
    "addr:housenumber":"1782",
    "addr:postcode":"30294",
    "addr:street":"Panola Rd",
    "iso:country":"US",
    "sg:address":"1782 Panola Rd",
    "sg:city":"Ellenwood",
    "sg:classifiers":[
        {
            "category":"Restaurant",
            "type":"Food & Drink"
        }
    ],
    "sg:phone":"+1 770 808 8890",
    "sg:postcode":"30294",
    "sg:province":"GA",
    "sg:tags":[
        "eating"
    ],
    "wof:name":"Watersburys Bar & Grill",
    "wof:placetype":"venue"
},
  "geometry": {"coordinates":[-84.233598,33.622551],"type":"Point"}
}