{
  "type": "Feature",
  "properties": {
    "iso:country":"US",
    "sg:address":"110 Creek Cove Ln",
    "sg:city":"Ellenwood",
    "sg:classifiers":[
        {
            "category":"Retail",
            "subcategory":"Repair Shop",
            "type":"Services"
        }
    ],
    "sg:phone":"+1 770 322 6984",
    "sg:postcode":"30294",
    "sg:province":"GA",
    "wof:name":"Amazing Art & Framing",
    "wof:placetype":"venue"
},
  "geometry": {"coordinates":[-84.24647299999999,33.637438],"type":"Point"}
}