{
  "type": "Feature",
  "properties": {
    "iso:country":"US",
    "sg:address":"1900 E Broad St",
    "sg:city":"Savannah",
    "sg:classifiers":[
        {
            "category":"Organizations",
            "subcategory":"Religious Organization",
            "type":"Services"
        }
    ],
    "sg:phone":"+1 912 232 1098",
    "sg:postcode":"31401",
    "sg:province":"GA",
    "sg:tags":[
        "church"
    ],
    "wof:name":"Genesis New Life Apostolic",
    "wof:placetype":"venue"
},
  "geometry": {"coordinates":[-81.09229499999999,32.056663],"type":"Point"}
}