{
  "type": "Feature",
  "properties": {
    "addr:full":"3654 Shallowford Rd NE Atlanta GA 30340",
    "addr:housenumber":"3654",
    "addr:postcode":"30340",
    "addr:street":"Shallowford Rd Ne",
    "iso:country":"US",
    "sg:address":"3654 Shallowford Rd NE",
    "sg:city":"Atlanta",
    "sg:classifiers":[
        {
            "category":"Building & Trades",
            "subcategory":"Equipment Rental",
            "type":"Services"
        }
    ],
    "sg:phone":"+1 770 458 7810",
    "sg:postcode":"30340",
    "sg:province":"GA",
    "sg:tags":[
        "merchandise",
        "camping"
    ],
    "wof:name":"Metro Tent Rentals Inc",
    "wof:placetype":"venue"
},
  "geometry": {"coordinates":[-84.285934,33.89465],"type":"Point"}
}