{
  "type": "Feature",
  "properties": {
    "iso:country":"US",
    "sg:address":"3999 Austell Rd",
    "sg:city":"Austell",
    "sg:classifiers":[
        {
            "category":"Shopping",
            "subcategory":"Gifts & Souvenirs",
            "type":"Retail Goods"
        }
    ],
    "sg:phone":"+1 770 732 6137",
    "sg:postcode":"30106",
    "sg:province":"GA",
    "sg:tags":[
        "shop"
    ],
    "wof:name":"Tuesday Morning",
    "wof:placetype":"venue"
},
  "geometry": {"coordinates":[-84.60032099999999,33.858094],"type":"Point"}
}