{
  "type": "Feature",
  "properties": {
    "addr:full":"3300 Buckeye Rd Atlanta GA 30341",
    "addr:housenumber":"3300",
    "addr:postcode":"30341",
    "addr:street":"Buckeye Rd",
    "iso:country":"US",
    "sg:address":"3300 Buckeye Rd",
    "sg:city":"Atlanta",
    "sg:classifiers":[
        {
            "category":"Professional",
            "type":"Services"
        },
        {
            "category":"Professional",
            "subcategory":"Advertising",
            "type":"Services"
        }
    ],
    "sg:phone":"+1 770 457 9818",
    "sg:postcode":"30341",
    "sg:province":"GA",
    "sg:tags":[
        "counselor"
    ],
    "wof:name":"Carribean Buzz",
    "wof:placetype":"venue"
},
  "geometry": {"coordinates":[-84.25778699999999,33.885342],"type":"Point"}
}