{
  "type": "Feature",
  "properties": {
    "iso:country":"US",
    "sg:address":"115 Lake Wildwood Dr",
    "sg:city":"Macon",
    "sg:classifiers":[
        {
            "category":"Organizations",
            "subcategory":"Community Association",
            "type":"Services"
        }
    ],
    "sg:phone":"+1 478 474 8895",
    "sg:postcode":"31220",
    "sg:province":"GA",
    "wof:name":"Lake Wildwood Association Inc",
    "wof:placetype":"venue"
},
  "geometry": {"coordinates":[-83.773999,32.879484],"type":"Point"}
}