{
  "type": "Feature",
  "properties": {
    "iso:country":"US",
    "sg:address":"103 Georgetown Ct",
    "sg:city":"Macon",
    "sg:classifiers":[
        {
            "category":"Travel",
            "subcategory":"Travel Agent",
            "type":"Entertainment"
        }
    ],
    "sg:phone":"+1 478 474 0505",
    "sg:postcode":"31210",
    "sg:province":"GA",
    "sg:tags":[
        "agency"
    ],
    "wof:name":"Personal Travel Consultants",
    "wof:placetype":"venue"
},
  "geometry": {"coordinates":[-83.719043,32.890947],"type":"Point"}
}