{
  "type": "Feature",
  "properties": {
    "addr:full":"3835 Kings Hwy Douglasville GA 30135",
    "addr:housenumber":"3835",
    "addr:postcode":"30135",
    "addr:street":"Kings Hwy",
    "iso:country":"US",
    "sg:address":"3835 Kings Hwy",
    "sg:city":"Douglasville",
    "sg:classifiers":[
        {
            "category":"Building & Trades",
            "subcategory":"Construction",
            "type":"Services"
        }
    ],
    "sg:phone":"+1 770 949 2952",
    "sg:postcode":"30135",
    "sg:province":"GA",
    "sg:tags":[
        "fire",
        "repair",
        "restoration",
        "commercial",
        "damage"
    ],
    "wof:name":"Ideal Fire Repair Inc",
    "wof:placetype":"venue"
},
  "geometry": {"coordinates":[-84.77157,33.700928],"type":"Point"}
}