{
  "type": "Feature",
  "properties": {
    "iso:country":"US",
    "sg:address":"625 Nellie B Ave",
    "sg:city":"Athens",
    "sg:classifiers":[
        {
            "category":"Retail",
            "subcategory":"Funeral Services",
            "type":"Services"
        }
    ],
    "sg:phone":"+1 706 543 8213",
    "sg:postcode":"30601",
    "sg:province":"GA",
    "sg:tags":[
        "director"
    ],
    "wof:name":"Mack & Payne Funeral Home Inc",
    "wof:placetype":"venue"
},
  "geometry": {"coordinates":[-83.346442,33.955562],"type":"Point"}
}