{
  "type": "Feature",
  "properties": {
    "iso:country":"US",
    "sg:address":"5994 Memorial Dr",
    "sg:city":"Stone Mountain",
    "sg:classifiers":[
        {
            "category":"Banks & Credit Unions",
            "subcategory":"Bank",
            "type":"Services"
        }
    ],
    "sg:phone":"+1 404 296 7550",
    "sg:postcode":"30083",
    "sg:province":"GA",
    "sg:tags":[
        "depository",
        "banking",
        "check",
        "cashing"
    ],
    "wof:name":"Atlanta Check Cashers Inc",
    "wof:placetype":"venue"
},
  "geometry": {"coordinates":[-84.19631,33.800711],"type":"Point"}
}