{
  "type": "Feature",
  "properties": {
    "iso:country":"US",
    "sg:address":"288 Styles Lake Rd",
    "sg:city":"Waco",
    "sg:classifiers":[
        {
            "category":"Personal",
            "subcategory":"Beauty Salon",
            "type":"Services"
        }
    ],
    "sg:phone":"+1 770 832 6289",
    "sg:postcode":"30182",
    "sg:province":"GA",
    "wof:name":"Styles Leland & Martha",
    "wof:placetype":"venue"
},
  "geometry": {"coordinates":[-85.193932,33.656952],"type":"Point"}
}