{
  "type": "Feature",
  "properties": {
    "iso:country":"US",
    "sg:address":"4155 Pebble Creek Dr",
    "sg:city":"Valdosta",
    "sg:classifiers":[
        {
            "category":"Building & Trades",
            "subcategory":"Construction",
            "type":"Services"
        }
    ],
    "sg:phone":"+1 229 244 1486",
    "sg:postcode":"31605",
    "sg:province":"GA",
    "sg:tags":[
        "marking",
        "maintenance",
        "parking"
    ],
    "wof:name":"Jim's Asphalt Sealcoating",
    "wof:placetype":"venue"
},
  "geometry": {"coordinates":[-83.244698,30.944597],"type":"Point"}
}