{
  "type": "Feature",
  "properties": {
    "iso:country":"US",
    "sg:address":"4107 Trotters Way Dr",
    "sg:city":"Snellville",
    "sg:classifiers":[
        {
            "category":"Banks & Credit Unions",
            "subcategory":"Financial Services",
            "type":"Services"
        }
    ],
    "sg:phone":"+1 404 840 9244",
    "sg:postcode":"30039",
    "sg:province":"GA",
    "sg:tags":[
        "company",
        "investment",
        "holding",
        "except"
    ],
    "wof:name":"Ebo Holdings",
    "wof:placetype":"venue"
},
  "geometry": {"coordinates":[-84.06159100000001,33.817458],"type":"Point"}
}