{
  "type": "Feature",
  "properties": {
    "iso:country":"US",
    "sg:address":"1035 Franklin Rd SE",
    "sg:city":"Marietta",
    "sg:classifiers":[
        {
            "category":"Sports & Exercise",
            "subcategory":"Gym",
            "type":"Entertainment"
        }
    ],
    "sg:phone":"+1 770 859 9751",
    "sg:postcode":"30067",
    "sg:province":"GA",
    "sg:tags":[
        "fitness",
        "physical",
        "facility"
    ],
    "wof:name":"Optimal Fitness",
    "wof:placetype":"venue"
},
  "geometry": {"coordinates":[-84.492503,33.926978],"type":"Point"}
}