{
  "type": "Feature",
  "properties": {
    "iso:country":"US",
    "sg:address":"800 N Veterans Pkwy",
    "sg:city":"Moultrie",
    "sg:classifiers":[
        {
            "category":"Education",
            "subcategory":"Junior College",
            "type":"Public Place"
        }
    ],
    "sg:phone":"+1 229 891 7000",
    "sg:postcode":"31788",
    "sg:province":"GA",
    "sg:tags":[
        "technical",
        "institute"
    ],
    "wof:name":"Moultrie Area Technical Inst",
    "wof:placetype":"venue"
},
  "geometry": {"coordinates":[-83.76707,31.196093],"type":"Point"}
}