{
  "type": "Feature",
  "properties": {
    "iso:country":"US",
    "sg:address":"103 Church St",
    "sg:city":"Hiawassee",
    "sg:classifiers":[
        {
            "category":"Health Services",
            "subcategory":"Doctor",
            "type":"Services"
        }
    ],
    "sg:phone":"+1 706 896 4602",
    "sg:postcode":"30546",
    "sg:province":"GA",
    "sg:tags":[
        "medicine",
        "physician",
        "practice",
        "surgeons",
        "family"
    ],
    "wof:name":"Holly A Berndt Md Pc",
    "wof:placetype":"venue"
},
  "geometry": {"coordinates":[-83.754645,34.948614],"type":"Point"}
}