{
  "type": "Feature",
  "properties": {
    "addr:full":"3645 Chamblee Tucker Rd Atlanta GA 30341",
    "addr:housenumber":"3645",
    "addr:postcode":"30341",
    "addr:street":"Chamblee Tucker Rd",
    "iso:country":"US",
    "sg:address":"3645 Chamblee Tucker Rd",
    "sg:city":"Atlanta",
    "sg:phone":"+1 770 934 7975",
    "sg:postcode":"30341",
    "sg:province":"GA",
    "wof:name":"Chamblee Auto Repair",
    "wof:placetype":"venue"
},
  "geometry": {"coordinates":[-84.245287,33.883349],"type":"Point"}
}