{
  "type": "Feature",
  "properties": {
    "addr:full":"1700 Clifton Atlanta GA 30329",
    "addr:housenumber":"1700",
    "addr:postcode":"30329",
    "addr:street":"Clifton",
    "iso:country":"US",
    "sg:address":"1700 Clifton",
    "sg:city":"Atlanta",
    "sg:classifiers":[
        {
            "category":"Social Services",
            "subcategory":"Child Care",
            "type":"Services"
        }
    ],
    "sg:phone":"+1 404 321 9477",
    "sg:postcode":"30329",
    "sg:province":"GA",
    "sg:tags":[
        "day"
    ],
    "wof:name":"Cdc Clifton Road Childcare",
    "wof:placetype":"venue"
},
  "geometry": {"coordinates":[-84.323601,33.831299],"type":"Point"}
}