{
  "type": "Feature",
  "properties": {
    "iso:country":"US",
    "sg:address":"180 Parkway 575",
    "sg:city":"Woodstock",
    "sg:classifiers":[
        {
            "category":"Restaurant",
            "type":"Food & Drink"
        }
    ],
    "sg:menulink":"http://www.allmenus.com/ga/woodstock/216953-folks-southern-kitchen/menu/",
    "sg:phone":"+1 770 516 0308",
    "sg:postcode":"30188",
    "sg:province":"GA",
    "sg:tags":[
        "american"
    ],
    "wof:name":"Folks Southern Kitchen",
    "wof:placetype":"venue"
},
  "geometry": {"coordinates":[-84.530935,34.087022],"type":"Point"}
}