{
  "type": "Feature",
  "properties": {
    "iso:country":"US",
    "sg:address":"4095 Minchew Blvd",
    "sg:city":"Waycross",
    "sg:classifiers":[
        {
            "category":"Manufacturing",
            "subcategory":"Glass & Minerals",
            "type":"Manufacturing & Wholesale Goods"
        }
    ],
    "sg:phone":"+1 912 283 2439",
    "sg:postcode":"31503",
    "sg:province":"GA",
    "sg:tags":[
        "concrete",
        "tank",
        "septic",
        "mfg"
    ],
    "wof:name":"Minchew Concrete Products Co",
    "wof:placetype":"venue"
},
  "geometry": {"coordinates":[-82.29055099999999,31.220429],"type":"Point"}
}