{
  "type": "Feature",
  "properties": {
    "addr:full":"409 Lincoln Ln Cataula GA 31804",
    "addr:housenumber":"409",
    "addr:postcode":"31804",
    "addr:street":"Lincoln Ln",
    "iso:country":"US",
    "sg:address":"409 Lincoln Ln",
    "sg:city":"Cataula",
    "sg:classifiers":[
        {
            "category":"Shopping",
            "subcategory":"Bicycles & Sporting Goods",
            "type":"Retail Goods"
        }
    ],
    "sg:phone":"+1 706 568 5615",
    "sg:postcode":"31804",
    "sg:province":"GA",
    "wof:name":"Outdoor Comforts",
    "wof:placetype":"venue"
},
  "geometry": {"coordinates":[-84.865937,32.670546],"type":"Point"}
}