{
  "type": "Feature",
  "properties": {
    "iso:country":"US",
    "sg:address":"891 Raines Rd",
    "sg:city":"Ashburn",
    "sg:classifiers":[
        {
            "category":"Professional",
            "type":"Services"
        }
    ],
    "sg:phone":"+1 229 567 0571",
    "sg:postcode":"31714",
    "sg:province":"GA",
    "wof:name":"Amanda Bridges",
    "wof:placetype":"venue"
},
  "geometry": {"coordinates":[-83.688129,31.698359],"type":"Point"}
}