{
  "type": "Feature",
  "properties": {
    "addr:full":"1307 B St Pine Mtn Valley GA 31823",
    "addr:housenumber":"1307",
    "addr:postcode":"31823",
    "addr:street":"B St Pine Mtn",
    "iso:country":"US",
    "sg:address":"1307 B St",
    "sg:city":"Pine Mtn Valley",
    "sg:classifiers":[
        {
            "category":"Manufacturing",
            "subcategory":"Lumber",
            "type":"Manufacturing & Wholesale Goods"
        }
    ],
    "sg:phone":"+1 706 628 4215",
    "sg:postcode":"31823",
    "sg:province":"GA",
    "sg:tags":[
        "forester"
    ],
    "sg:website":"www.americanfitness.org",
    "wof:name":"Owen L Riley & Assoc",
    "wof:placetype":"venue"
},
  "geometry": {"coordinates":[-84.822774,32.78252],"type":"Point"}
}