{
  "type": "Feature",
  "properties": {
    "addr:full":"500 G St Brunswick GA 31520",
    "addr:housenumber":"500",
    "addr:postcode":"31520",
    "addr:street":"G St",
    "iso:country":"US",
    "sg:address":"500 G St",
    "sg:city":"Brunswick",
    "sg:classifiers":[
        {
            "category":"Building & Trades",
            "subcategory":"Construction",
            "type":"Services"
        }
    ],
    "sg:phone":"+1 912 466 0001",
    "sg:postcode":"31520",
    "sg:province":"GA",
    "sg:tags":[
        "contractor"
    ],
    "wof:name":"Chambers Contracting Svc",
    "wof:placetype":"venue"
},
  "geometry": {"coordinates":[-81.495136,31.152072],"type":"Point"}
}