{
  "type": "Feature",
  "properties": {
    "iso:country":"US",
    "sg:address":"3939 Royal Dr NW",
    "sg:city":"Kennesaw",
    "sg:classifiers":[
        {
            "category":"Autos & Motor Vehicles",
            "subcategory":"Motorcycle Sales",
            "type":"Retail Goods"
        }
    ],
    "sg:phone":"+1 770 423 2827",
    "sg:postcode":"30144",
    "sg:province":"GA",
    "wof:name":"Cobra Scooter Llc",
    "wof:placetype":"venue"
},
  "geometry": {"coordinates":[-84.60423400000001,34.049221],"type":"Point"}
}