{
  "type": "Feature",
  "properties": {
    "iso:country":"US",
    "sg:address":"1685 Kingsley Cir",
    "sg:city":"Lawrenceville",
    "sg:classifiers":[
        {
            "category":"Real Estate",
            "subcategory":"Real Estate Operator",
            "type":"Services"
        }
    ],
    "sg:phone":"+1 678 697 4312",
    "sg:postcode":"30043",
    "sg:province":"GA",
    "sg:tags":[
        "building",
        "nonresidential"
    ],
    "wof:name":"Doug Baker",
    "wof:placetype":"venue"
},
  "geometry": {"coordinates":[-84.046021,33.981342],"type":"Point"}
}