{
  "type": "Feature",
  "properties": {
    "iso:country":"US",
    "sg:address":"174 Legg Rd",
    "sg:city":"Jefferson",
    "sg:classifiers":[
        {
            "category":"Real Estate",
            "subcategory":"Real Estate Operator",
            "type":"Services"
        }
    ],
    "sg:phone":"+1 706 367 0204",
    "sg:postcode":"30549",
    "sg:province":"GA",
    "sg:tags":[
        "building",
        "apartment"
    ],
    "wof:name":"Curry Creek Partnership LP",
    "wof:placetype":"venue"
},
  "geometry": {"coordinates":[-83.579444,34.165665],"type":"Point"}
}