{
  "type": "Feature",
  "properties": {
    "iso:country":"US",
    "sg:address":"2917 Thrasher Ave",
    "sg:city":"Albany",
    "sg:classifiers":[
        {
            "category":"Real Estate",
            "subcategory":"Real Estate Agent",
            "type":"Services"
        }
    ],
    "sg:phone":"+1 229 883 3998",
    "sg:postcode":"31721",
    "sg:province":"GA",
    "wof:name":"P&T Rentals Inc",
    "wof:placetype":"venue"
},
  "geometry": {"coordinates":[-84.235888,31.500691],"type":"Point"}
}