{
  "type": "Feature",
  "properties": {
    "addr:full":"260 Frankie Ln Covington GA 30014",
    "addr:housenumber":"260",
    "addr:postcode":"30014",
    "addr:street":"Frankie Ln",
    "iso:country":"US",
    "sg:address":"260 Frankie Ln",
    "sg:city":"Covington",
    "sg:classifiers":[
        {
            "category":"Manufacturing",
            "subcategory":"Metals",
            "type":"Manufacturing & Wholesale Goods"
        }
    ],
    "sg:phone":"+1 770 786 4801",
    "sg:postcode":"30014",
    "sg:province":"GA",
    "sg:tags":[
        "metalwork",
        "sheet",
        "mfg"
    ],
    "wof:name":"Terry Wells",
    "wof:placetype":"venue"
},
  "geometry": {"coordinates":[-83.84340400000001,33.452402],"type":"Point"}
}