{
  "type": "Feature",
  "properties": {
    "iso:country":"US",
    "sg:address":"105 Hanover Trace Ct",
    "sg:city":"Alpharetta",
    "sg:classifiers":[
        {
            "category":"Home & Garden",
            "subcategory":"Carpets & Floor Coverings",
            "type":"Retail Goods"
        }
    ],
    "sg:phone":"+1 770 619 3009",
    "sg:postcode":"30022",
    "sg:province":"GA",
    "wof:name":"Carpet Design Inc",
    "wof:placetype":"venue"
},
  "geometry": {"coordinates":[-84.21833100000001,34.059072],"type":"Point"}
}