{
  "type": "Feature",
  "properties": {
    "iso:country":"US",
    "sg:address":"110 Downing Ct",
    "sg:city":"Fayetteville",
    "sg:classifiers":[
        {
            "category":"Building & Trades",
            "subcategory":"Pest Control",
            "type":"Services"
        }
    ],
    "sg:phone":"+1 770 460 7378",
    "sg:postcode":"30214",
    "sg:province":"GA",
    "wof:name":"Atlas Commercial Exterminators",
    "wof:placetype":"venue"
},
  "geometry": {"coordinates":[-84.429114,33.475397],"type":"Point"}
}