{
  "type": "Feature",
  "properties": {
    "addr:full":"11213 Hwy 53 E Marble Hill GA 30734",
    "addr:housenumber":"11213",
    "addr:postcode":"30734",
    "addr:street":"Hwy 53 E",
    "iso:country":"US",
    "sg:address":"11213 Hwy 53 E",
    "sg:city":"Marble Hill",
    "sg:classifiers":[
        {
            "category":"Restaurant",
            "type":"Food & Drink"
        }
    ],
    "sg:phone":"+1 770 893 6096",
    "sg:postcode":"30734",
    "sg:province":"GA",
    "sg:tags":[
        "eating"
    ],
    "wof:name":"Sharons Pit Stop Cafe",
    "wof:placetype":"venue"
},
  "geometry": {"coordinates":[-84.314623,34.417075],"type":"Point"}
}