{
  "type": "Feature",
  "properties": {
    "iso:country":"US",
    "sg:address":"105 Holly St",
    "sg:city":"Canton",
    "sg:classifiers":[
        {
            "category":"Building & Trades",
            "subcategory":"Construction",
            "type":"Services"
        }
    ],
    "sg:phone":"+1 678 493 7452",
    "sg:postcode":"30114",
    "sg:province":"GA",
    "sg:tags":[
        "general",
        "contractor"
    ],
    "wof:name":"S & D Builders",
    "wof:placetype":"venue"
},
  "geometry": {"coordinates":[-84.552194,34.191326],"type":"Point"}
}