{
  "type": "Feature",
  "properties": {
    "iso:country":"US",
    "sg:address":"711 W Church St",
    "sg:city":"Sandersville",
    "sg:classifiers":[
        {
            "category":"Insurance",
            "subcategory":"Hazard Insurance",
            "type":"Services"
        }
    ],
    "sg:phone":"+1 478 452 7175",
    "sg:postcode":"31082",
    "sg:province":"GA",
    "sg:tags":[
        "commercial",
        "business"
    ],
    "wof:name":"Adams, Benny Insurance Agency",
    "wof:placetype":"venue"
},
  "geometry": {"coordinates":[-82.830719,32.981119],"type":"Point"}
}