{
  "type": "Feature",
  "properties": {
    "addr:full":"1 Diamond Cswy Savannah GA 31406",
    "addr:housenumber":"1",
    "addr:postcode":"31406",
    "addr:street":"Diamond Cswy",
    "iso:country":"US",
    "sg:address":"1 Diamond Cswy",
    "sg:city":"Savannah",
    "sg:classifiers":[
        {
            "category":"Restaurant",
            "type":"Food & Drink"
        }
    ],
    "sg:menulink":"http://www.allmenus.com/ga/montgomery/132667-subway/menu/",
    "sg:phone":"+1 912 354 0004",
    "sg:postcode":"31406",
    "sg:province":"GA",
    "sg:tags":[
        "american",
        "sandwich"
    ],
    "wof:name":"Subway",
    "wof:placetype":"venue"
},
  "geometry": {"coordinates":[-81.097729,31.957484],"type":"Point"}
}