{
  "type": "Feature",
  "properties": {
    "iso:country":"US",
    "sg:address":"7030 W Marshall St",
    "sg:city":"Meigs",
    "sg:classifiers":[
        {
            "category":"Building & Trades",
            "subcategory":"Construction",
            "type":"Services"
        }
    ],
    "sg:phone":"+1 229 683 3954",
    "sg:postcode":"31765",
    "sg:province":"GA",
    "sg:tags":[
        "contractor"
    ],
    "wof:name":"Gator Contracting",
    "wof:placetype":"venue"
},
  "geometry": {"coordinates":[-84.095629,31.06863],"type":"Point"}
}