{
  "type": "Feature",
  "properties": {
    "addr:full":"4102 Sandstone Shares Dr Lithonia GA 30038",
    "addr:housenumber":"4102",
    "addr:postcode":"30038",
    "addr:street":"Sandstone Shares Dr",
    "iso:country":"US",
    "sg:address":"4102 Sandstone Shares Dr",
    "sg:city":"Lithonia",
    "sg:classifiers":[
        {
            "category":"Real Estate",
            "subcategory":"Real Estate Operator",
            "type":"Services"
        }
    ],
    "sg:phone":"+1 404 886 8016",
    "sg:postcode":"30038",
    "sg:province":"GA",
    "sg:tags":[
        "building",
        "nonresidential"
    ],
    "wof:name":"Imperial Properties",
    "wof:placetype":"venue"
},
  "geometry": {"coordinates":[-84.171898,33.658244],"type":"Point"}
}