{
  "type": "Feature",
  "properties": {
    "iso:country":"US",
    "sg:address":"4601 Ridgeview Road",
    "sg:city":"Atlanta",
    "sg:classifiers":[
        {
            "category":"Travel",
            "subcategory":"Hotels & Motels",
            "type":"Entertainment"
        }
    ],
    "sg:phone":"+1 678 320 0250",
    "sg:postcode":"30338",
    "sg:province":"GA",
    "wof:name":"Bass Hotels",
    "wof:placetype":"venue"
},
  "geometry": {"coordinates":[-84.34419800000001,33.932764],"type":"Point"}
}