{
  "type": "Feature",
  "properties": {
    "addr:full":"1158 Canton St Roswell GA 30075",
    "addr:housenumber":"1158",
    "addr:postcode":"30075",
    "addr:street":"Canton St",
    "iso:country":"US",
    "sg:address":"1158 Canton St",
    "sg:city":"Roswell",
    "sg:classifiers":[
        {
            "category":"Professional",
            "subcategory":"Engineering",
            "type":"Services"
        }
    ],
    "sg:phone":"+1 770 992 5077",
    "sg:postcode":"30075",
    "sg:province":"GA",
    "sg:tags":[
        "consulting",
        "engineer"
    ],
    "wof:name":"Craig L Molnar Consulting Engineers",
    "wof:placetype":"venue"
},
  "geometry": {"coordinates":[-84.361418,34.030163],"type":"Point"}
}