{
  "type": "Feature",
  "properties": {
    "addr:full":"456 Canterbury Place Dr Suwanee GA 30024",
    "addr:housenumber":"456",
    "addr:postcode":"30024",
    "addr:street":"Canterbury Place Dr",
    "iso:country":"US",
    "sg:address":"456 Canterbury Place Dr",
    "sg:city":"Suwanee",
    "sg:classifiers":[
        {
            "category":"Education",
            "subcategory":"Special Training",
            "type":"Public Place"
        }
    ],
    "sg:phone":"+1 770 265 0174",
    "sg:postcode":"30024",
    "sg:province":"GA",
    "sg:tags":[
        "tutoring"
    ],
    "wof:name":"Certified Tutors",
    "wof:placetype":"venue"
},
  "geometry": {"coordinates":[-84.02985099999999,34.051806],"type":"Point"}
}