{
  "type": "Feature",
  "properties": {
    "iso:country":"US",
    "sg:address":"1400 Wellbrook Cir NE",
    "sg:city":"Conyers",
    "sg:classifiers":[
        {
            "category":"Health Services",
            "subcategory":"Optometrist",
            "type":"Services"
        }
    ],
    "sg:phone":"+1 770 922 2201",
    "sg:postcode":"30012",
    "sg:province":"GA",
    "sg:tags":[
        "ophthalmologist"
    ],
    "wof:name":"Salmenson Brian D MD",
    "wof:placetype":"venue"
},
  "geometry": {"coordinates":[-84.00369999999999,33.677299],"type":"Point"}
}