{
  "type": "Feature",
  "properties": {
    "addr:full":"129 Cooper Dr Dallas GA 30157",
    "addr:housenumber":"129",
    "addr:postcode":"30157",
    "addr:street":"Cooper Dr",
    "iso:country":"US",
    "sg:address":"129 Cooper Dr",
    "sg:city":"Dallas",
    "sg:classifiers":[
        {
            "category":"Building & Trades",
            "subcategory":"Construction",
            "type":"Services"
        }
    ],
    "sg:phone":"+1 678 363 7785",
    "sg:postcode":"30157",
    "sg:province":"GA",
    "sg:tags":[
        "residential"
    ],
    "wof:name":"Tpg Constructon",
    "wof:placetype":"venue"
},
  "geometry": {"coordinates":[-84.78187,33.921509],"type":"Point"}
}