{
  "type": "Feature",
  "properties": {
    "iso:country":"US",
    "sg:address":"1565 Woodington Cir",
    "sg:city":"Lawrenceville",
    "sg:classifiers":[
        {
            "category":"Education",
            "subcategory":"Kindergarten",
            "type":"Public Place"
        }
    ],
    "sg:phone":"+1 770 279 0032",
    "sg:postcode":"30044",
    "sg:province":"GA",
    "sg:tags":[
        "school",
        "driving"
    ],
    "wof:name":"Lowcost Driving School",
    "wof:placetype":"venue"
},
  "geometry": {"coordinates":[-84.125675,33.941097],"type":"Point"}
}