{
  "type": "Feature",
  "properties": {
    "addr:full":"5901 A PEACHTREE DUNWOODY RD, STE 450 Atlanta GA 30328",
    "addr:housenumber":"5901 a",
    "addr:postcode":"30328",
    "addr:street":"Peachtree Dunwoody Rd Ste 450",
    "iso:country":"US",
    "sg:address":"5901 A PEACHTREE DUNWOODY RD, STE 450",
    "sg:city":"Atlanta",
    "sg:classifiers":[
        {
            "category":"Building & Trades",
            "subcategory":"Construction",
            "type":"Services"
        }
    ],
    "sg:phone":"+1 678 459 3000",
    "sg:postcode":"30328",
    "sg:province":"GA",
    "sg:tags":[
        "consultant"
    ],
    "sg:website":"http://www.dprconstruction.com",
    "wof:name":"DPR Construction Atlanta",
    "wof:placetype":"venue"
},
  "geometry": {"coordinates":[-84.35417200000001,33.931702],"type":"Point"}
}