{
  "type": "Feature",
  "properties": {
    "addr:full":"321 Dairy Rd Millen GA 30442",
    "addr:housenumber":"321",
    "addr:postcode":"30442",
    "addr:street":"Dairy Rd",
    "iso:country":"US",
    "sg:address":"321 Dairy Rd",
    "sg:city":"Millen",
    "sg:classifiers":[
        {
            "category":"Professional",
            "type":"Services"
        }
    ],
    "sg:phone":"+1 478 982 1734",
    "sg:postcode":"30442",
    "sg:province":"GA",
    "wof:name":"Robert J Wright",
    "wof:placetype":"venue"
},
  "geometry": {"coordinates":[-81.921334,32.811134],"type":"Point"}
}