{
  "type": "Feature",
  "properties": {
    "addr:full":"2987 Watson Blvd Warner Robins GA 31093",
    "addr:housenumber":"2987",
    "addr:postcode":"31093",
    "addr:street":"Watson Blvd",
    "iso:country":"US",
    "sg:address":"2987 Watson Blvd",
    "sg:city":"Warner Robins",
    "sg:classifiers":[
        {
            "category":"Shopping",
            "subcategory":"Crafts & Fabrics",
            "type":"Retail Goods"
        }
    ],
    "sg:phone":"+1 478 971 4042",
    "sg:postcode":"31093",
    "sg:province":"GA",
    "sg:tags":[
        "art",
        "supply"
    ],
    "sg:website":"www.hobbylobby.com",
    "wof:name":"Hobby Lobby Creative Center",
    "wof:placetype":"venue"
},
  "geometry": {"coordinates":[-83.688864,32.617602],"type":"Point"}
}