{
  "type": "Feature",
  "properties": {
    "iso:country":"US",
    "sg:address":"1100 W Walker St",
    "sg:city":"Douglas",
    "sg:classifiers":[
        {
            "category":"Autos & Motor Vehicles",
            "subcategory":"Automobile Sales",
            "type":"Retail Goods"
        }
    ],
    "sg:phone":"+1 912 384 2600",
    "sg:postcode":"31533",
    "sg:province":"GA",
    "wof:name":"Village Cars & Trucks",
    "wof:placetype":"venue"
},
  "geometry": {"coordinates":[-82.865928,31.520408],"type":"Point"}
}