{
  "type": "Feature",
  "properties": {
    "iso:country":"US",
    "sg:address":"4417 Beallwood Ave",
    "sg:city":"Columbus",
    "sg:classifiers":[
        {
            "category":"Retail",
            "subcategory":"Auto Repair",
            "type":"Services"
        }
    ],
    "sg:phone":"+1 706 327 9983",
    "sg:postcode":"31904",
    "sg:province":"GA",
    "sg:tags":[
        "general"
    ],
    "wof:name":"Stills Auto Service Inc",
    "wof:placetype":"venue"
},
  "geometry": {"coordinates":[-84.97255,32.506009],"type":"Point"}
}