{
  "type": "Feature",
  "properties": {
    "addr:full":"751 Woodson St Atlanta GA 30315",
    "addr:housenumber":"751",
    "addr:postcode":"30315",
    "addr:street":"Woodson St",
    "iso:country":"US",
    "sg:address":"751 Woodson St",
    "sg:city":"Atlanta",
    "sg:classifiers":[
        {
            "category":"Building & Trades",
            "subcategory":"Construction",
            "type":"Services"
        }
    ],
    "sg:phone":"+1 770 329 3689",
    "sg:postcode":"30315",
    "sg:province":"GA",
    "sg:tags":[
        "interior",
        "design"
    ],
    "sg:website":"www.sinksntubs.com",
    "wof:name":"Sinks n Tubs",
    "wof:placetype":"venue"
},
  "geometry": {"coordinates":[-84.37943,33.734016],"type":"Point"}
}