{
  "type": "Feature",
  "properties": {
    "addr:full":"2323 Rowland Ave Savannah GA 31404",
    "addr:housenumber":"2323",
    "addr:postcode":"31404",
    "addr:street":"Rowland Ave",
    "iso:country":"US",
    "sg:address":"2323 Rowland Ave",
    "sg:city":"Savannah",
    "sg:classifiers":[
        {
            "category":"Building & Trades",
            "subcategory":"Electrical",
            "type":"Services"
        }
    ],
    "sg:phone":"+1 912 352 0110",
    "sg:postcode":"31404",
    "sg:province":"GA",
    "sg:tags":[
        "general",
        "electrical",
        "contractor"
    ],
    "wof:name":"M L Sloan Electric Co",
    "wof:placetype":"venue"
},
  "geometry": {"coordinates":[-81.06365599999999,32.039406],"type":"Point"}
}