{
  "type": "Feature",
  "properties": {
    "addr:full":"2840 Martin Luther King Jr Dr SW Atlanta GA 30311",
    "addr:housenumber":"2840",
    "addr:postcode":"30311",
    "addr:street":"Martin Luther King Jr Dr Sw",
    "iso:country":"US",
    "sg:address":"2840 Martin Luther King Jr Dr SW",
    "sg:city":"Atlanta",
    "sg:classifiers":[
        {
            "category":"Travel",
            "subcategory":"Hotels & Motels",
            "type":"Entertainment"
        }
    ],
    "sg:phone":"+1 404 696 0320",
    "sg:postcode":"30311",
    "sg:province":"GA",
    "wof:name":"Crown Motel",
    "wof:placetype":"venue"
},
  "geometry": {"coordinates":[-84.481129,33.754412],"type":"Point"}
}