{
  "type": "Feature",
  "properties": {
    "addr:full":"2572 Highway 42 N McDonough GA 30253",
    "addr:housenumber":"2572",
    "addr:postcode":"30253",
    "addr:street":"Highway 42 N",
    "iso:country":"US",
    "sg:address":"2572 Highway 42 N",
    "sg:city":"McDonough",
    "sg:classifiers":[
        {
            "category":"Shopping",
            "subcategory":"Florist",
            "type":"Retail Goods"
        }
    ],
    "sg:phone":"+1 770 914 5500",
    "sg:postcode":"30253",
    "sg:province":"GA",
    "wof:name":"Always Flowers & Gifts",
    "wof:placetype":"venue"
},
  "geometry": {"coordinates":[-84.188698,33.511902],"type":"Point"}
}