{
  "type": "Feature",
  "properties": {
    "addr:full":"2221 Dawn Ct Suwanee GA 30024",
    "addr:housenumber":"2221",
    "addr:postcode":"30024",
    "addr:street":"Dawn Ct",
    "iso:country":"US",
    "sg:address":"2221 Dawn Ct",
    "sg:city":"Suwanee",
    "sg:classifiers":[
        {
            "category":"Food & Beverages",
            "subcategory":"Groceries & Convenience Stores",
            "type":"Retail Goods"
        }
    ],
    "sg:phone":"+1 770 682 2007",
    "sg:postcode":"30024",
    "sg:province":"GA",
    "wof:name":"Joseph R Little Etal",
    "wof:placetype":"venue"
},
  "geometry": {"coordinates":[-84.03341399999999,34.009883],"type":"Point"}
}