{
  "type": "Feature",
  "properties": {
    "iso:country":"US",
    "sg:address":"976 W Pointe Ct",
    "sg:city":"Lithia Springs",
    "sg:classifiers":[
        {
            "category":"Travel",
            "subcategory":"Hotels & Motels",
            "type":"Entertainment"
        }
    ],
    "sg:phone":"+1 770 739 2800",
    "sg:postcode":"30122",
    "sg:province":"GA",
    "sg:website":"www.marriott.com",
    "wof:name":"Fairfield Inn by Marriott-Six Flags",
    "wof:placetype":"venue"
},
  "geometry": {"coordinates":[-84.605981,33.774387],"type":"Point"}
}