{
  "type": "Feature",
  "properties": {
    "iso:country":"US",
    "sg:address":"1 W Court Sq",
    "sg:city":"Decatur",
    "sg:classifiers":[
        {
            "category":"Education",
            "subcategory":"Special Training",
            "type":"Public Place"
        },
        {
            "category":"Education",
            "subcategory":"Vocational School",
            "type":"Public Place"
        },
        {
            "category":"Education",
            "subcategory":"University",
            "type":"Public Place"
        },
        {
            "category":"Education",
            "subcategory":"School",
            "type":"Public Place"
        }
    ],
    "sg:phone":"+1 877 268 3879",
    "sg:postcode":"30030",
    "sg:province":"GA",
    "sg:tags":[
        "college",
        "adult",
        "business"
    ],
    "sg:website":"http://www.kelleradvantage.com/landing36/index.html?vc=167328",
    "wof:name":"Keller Graduate School of Management",
    "wof:placetype":"venue"
},
  "geometry": {"coordinates":[-84.296944,33.77504],"type":"Point"}
}