{
  "type": "Feature",
  "properties": {
    "iso:country":"US",
    "sg:address":"270 Plantation Way",
    "sg:city":"Roswell",
    "sg:classifiers":[
        {
            "category":"Professional",
            "subcategory":"Lawyer & Legal Services",
            "type":"Services"
        }
    ],
    "sg:phone":"+1 770 645 5040",
    "sg:postcode":"30075",
    "sg:province":"GA",
    "sg:tags":[
        "attorney"
    ],
    "wof:name":"Jeffrey W Brown Law Offices",
    "wof:placetype":"venue"
},
  "geometry": {"coordinates":[-84.38945099999999,34.038765],"type":"Point"}
}