{
  "type": "Feature",
  "properties": {
    "addr:full":"5915 Seven Oaks Dr Powder Springs GA 30127",
    "addr:housenumber":"5915",
    "addr:postcode":"30127",
    "addr:street":"Seven Oaks Dr",
    "iso:country":"US",
    "sg:address":"5915 Seven Oaks Dr",
    "sg:city":"Powder Springs",
    "sg:classifiers":[
        {
            "category":"Professional",
            "type":"Services"
        }
    ],
    "sg:phone":"+1 770 514 7142",
    "sg:postcode":"30127",
    "sg:province":"GA",
    "wof:name":"Gracie & Co",
    "wof:placetype":"venue"
},
  "geometry": {"coordinates":[-84.731025,33.949947],"type":"Point"}
}