{
  "type": "Feature",
  "properties": {
    "addr:full":"128 Talmadge Dr Moultrie GA 31768",
    "addr:housenumber":"128",
    "addr:postcode":"31768",
    "addr:street":"Talmadge Dr",
    "iso:country":"US",
    "sg:address":"128 Talmadge Dr",
    "sg:city":"Moultrie",
    "sg:classifiers":[
        {
            "category":"Manufacturing",
            "subcategory":"Tools & Machinery",
            "type":"Manufacturing & Wholesale Goods"
        }
    ],
    "sg:phone":"+1 229 985 5445",
    "sg:postcode":"31768",
    "sg:province":"GA",
    "sg:tags":[
        "farm",
        "equipment"
    ],
    "wof:name":"Taylor Manufacturing Co",
    "wof:placetype":"venue"
},
  "geometry": {"coordinates":[-83.77341800000001,31.177879],"type":"Point"}
}