{
  "type": "Feature",
  "properties": {
    "addr:full":"1341 Stoneleigh Dr Conyers GA 30094",
    "addr:housenumber":"1341",
    "addr:postcode":"30094",
    "addr:street":"Stoneleigh Dr",
    "iso:country":"US",
    "sg:address":"1341 Stoneleigh Dr",
    "sg:city":"Conyers",
    "sg:classifiers":[
        {
            "category":"Professional",
            "subcategory":"Computer Services",
            "type":"Services"
        }
    ],
    "sg:phone":"+1 770 761 3895",
    "sg:postcode":"30094",
    "sg:province":"GA",
    "sg:tags":[
        "consultant",
        "designer"
    ],
    "wof:name":"Addico Solutions",
    "wof:placetype":"venue"
},
  "geometry": {"coordinates":[-84.06761400000001,33.672212],"type":"Point"}
}