{
  "type": "Feature",
  "properties": {
    "iso:country":"US",
    "sg:address":"2860 Old Atlanta Rd",
    "sg:city":"Cumming",
    "sg:classifiers":[
        {
            "category":"Retail",
            "subcategory":"Self-service Laundry",
            "type":"Services"
        }
    ],
    "sg:phone":"+1 770 886 3115",
    "sg:postcode":"30041",
    "sg:province":"GA",
    "sg:tags":[
        "coin"
    ],
    "wof:name":"Super Cleaner",
    "wof:placetype":"venue"
},
  "geometry": {"coordinates":[-84.155084,34.117457],"type":"Point"}
}