{
  "type": "Feature",
  "properties": {
    "addr:full":"223 James Brown Blvd Augusta GA 30901",
    "addr:housenumber":"223",
    "addr:postcode":"30901",
    "addr:street":"James Brown Blvd",
    "iso:country":"US",
    "sg:address":"223 James Brown Blvd",
    "sg:city":"Augusta",
    "sg:classifiers":[
        {
            "category":"Banks & Credit Unions",
            "subcategory":"Bank",
            "type":"Services"
        }
    ],
    "sg:phone":"+1 706 724 9638",
    "sg:postcode":"30901",
    "sg:province":"GA",
    "sg:tags":[
        "institution",
        "business"
    ],
    "wof:name":"CFC",
    "wof:placetype":"venue"
},
  "geometry": {"coordinates":[-81.96805000000001,33.475046],"type":"Point"}
}