{
  "type": "Feature",
  "properties": {
    "addr:full":"75 5th St NW Ste 110 Atlanta GA 30308",
    "addr:housenumber":"75",
    "addr:postcode":"30308",
    "addr:street":"5Th St Nw Ste 110",
    "iso:country":"US",
    "sg:address":"75 5th St NW Ste 110",
    "sg:city":"Atlanta",
    "sg:classifiers":[
        {
            "category":"Home & Garden",
            "subcategory":"Home Furnishings",
            "type":"Retail Goods"
        },
        {
            "category":"Home & Garden",
            "subcategory":"Carpets & Floor Coverings",
            "type":"Retail Goods"
        }
    ],
    "sg:phone":"+1 404 877 5002",
    "sg:postcode":"30308",
    "sg:province":"GA",
    "sg:tags":[
        "decor",
        "flooring"
    ],
    "sg:website":"www.interfaceflor.com",
    "wof:name":"Interface FLOR",
    "wof:placetype":"venue"
},
  "geometry": {"coordinates":[-84.38958700000001,33.776834],"type":"Point"}
}