{
  "type": "Feature",
  "properties": {
    "addr:full":"120 S Hill St Griffin GA 30223",
    "addr:housenumber":"120",
    "addr:postcode":"30223",
    "addr:street":"S Hill St",
    "iso:country":"US",
    "sg:address":"120 S Hill St",
    "sg:city":"Griffin",
    "sg:classifiers":[
        {
            "category":"Insurance",
            "subcategory":"Insurance Agent",
            "type":"Services"
        }
    ],
    "sg:phone":"+1 770 233 3300",
    "sg:postcode":"30223",
    "sg:province":"GA",
    "wof:name":"Primerica Financial Svc",
    "wof:placetype":"venue"
},
  "geometry": {"coordinates":[-84.263673,33.24858],"type":"Point"}
}