{
  "type": "Feature",
  "properties": {
    "addr:full":"4700 S Lee St Buford GA 30518",
    "addr:housenumber":"4700",
    "addr:postcode":"30518",
    "addr:street":"S Lee St",
    "iso:country":"US",
    "sg:address":"4700 S Lee St",
    "sg:city":"Buford",
    "sg:classifiers":[
        {
            "category":"Taxi",
            "type":"Transportation"
        }
    ],
    "sg:phone":"+1 678 714 2921",
    "sg:postcode":"30518",
    "sg:province":"GA",
    "sg:tags":[
        "taxicab"
    ],
    "wof:name":"Yami's Taxi",
    "wof:placetype":"venue"
},
  "geometry": {"coordinates":[-83.998756,34.092385],"type":"Point"}
}