{
  "type": "Feature",
  "properties": {
    "addr:full":"14 Westgate Blvd Savannah GA 31405",
    "addr:housenumber":"14",
    "addr:postcode":"31405",
    "addr:street":"Westgate Blvd",
    "iso:country":"US",
    "sg:address":"14 Westgate Blvd",
    "sg:city":"Savannah",
    "sg:classifiers":[
        {
            "category":"Wholesale",
            "subcategory":"Machinery & Supplies",
            "type":"Manufacturing & Wholesale Goods"
        }
    ],
    "sg:phone":"+1 912 232 2602",
    "sg:postcode":"31405",
    "sg:province":"GA",
    "sg:tags":[
        "engine"
    ],
    "sg:website":"www.illiams.com",
    "wof:name":"W W Williams",
    "wof:placetype":"venue"
},
  "geometry": {"coordinates":[-81.14401700000001,32.053724],"type":"Point"}
}