{
  "type": "Feature",
  "properties": {
    "addr:full":"221 Cardinal St Sandersville GA 31082",
    "addr:housenumber":"221",
    "addr:postcode":"31082",
    "addr:street":"Cardinal St",
    "iso:country":"US",
    "sg:address":"221 Cardinal St",
    "sg:city":"Sandersville",
    "sg:classifiers":[
        {
            "category":"Organizations",
            "subcategory":"Religious Organization",
            "type":"Services"
        }
    ],
    "sg:phone":"+1 478 552 5989",
    "sg:postcode":"31082",
    "sg:province":"GA",
    "wof:name":"Christian Life Center",
    "wof:placetype":"venue"
},
  "geometry": {"coordinates":[-82.80819099999999,32.979252],"type":"Point"}
}