{
  "type": "Feature",
  "properties": {
    "addr:full":"6135 New Peachtree Road Atlanta GA 30340",
    "addr:housenumber":"6135",
    "addr:postcode":"30340",
    "addr:street":"New Peachtree Road",
    "iso:country":"US",
    "sg:address":"6135 New Peachtree Road",
    "sg:city":"Atlanta",
    "sg:classifiers":[
        {
            "category":"Real Estate",
            "subcategory":"Real Estate Operator",
            "type":"Services"
        }
    ],
    "sg:phone":"+1 770 458 3161",
    "sg:postcode":"30340",
    "sg:province":"GA",
    "sg:tags":[
        "apartment"
    ],
    "wof:name":"Pebblewood Apartments",
    "wof:placetype":"venue"
},
  "geometry": {"coordinates":[-84.275941,33.905471],"type":"Point"}
}