{
  "type": "Feature",
  "properties": {
    "addr:full":"11 Greenwood Ave Statesboro GA 30458",
    "addr:housenumber":"11",
    "addr:postcode":"30458",
    "addr:street":"Greenwood Ave",
    "iso:country":"US",
    "sg:address":"11 Greenwood Ave",
    "sg:city":"Statesboro",
    "sg:classifiers":[
        {
            "category":"Food & Beverages",
            "subcategory":"Specialty",
            "type":"Retail Goods"
        }
    ],
    "sg:phone":"+1 912 871 5239",
    "sg:postcode":"30458",
    "sg:province":"GA",
    "wof:name":"Georgia Nutrition Council Inc",
    "wof:placetype":"venue"
},
  "geometry": {"coordinates":[-81.766927,32.426597],"type":"Point"}
}