{
  "type": "Feature",
  "properties": {
    "addr:full":"Northeast Plaza 3303 Buford Hwy NE Atlanta GA 30329",
    "addr:housenumber":"3303",
    "addr:postcode":"30329",
    "addr:street":"Northeast;Buford Hwy Ne",
    "iso:country":"US",
    "sg:address":"Northeast Plaza 3303 Buford Hwy NE",
    "sg:city":"Atlanta",
    "sg:classifiers":[
        {
            "category":"Manufacturing",
            "subcategory":"Leather Goods",
            "type":"Manufacturing & Wholesale Goods"
        }
    ],
    "sg:postcode":"30329",
    "sg:province":"GA",
    "wof:name":"Mora's Boots",
    "wof:placetype":"venue"
},
  "geometry": {"coordinates":[-84.328821,33.842806],"type":"Point"}
}