{
  "type": "Feature",
  "properties": {
    "addr:full":"9403 Highland Rdg Jonesboro GA 30238",
    "addr:housenumber":"9403",
    "addr:postcode":"30238",
    "addr:street":"Highland Rdg",
    "iso:country":"US",
    "sg:address":"9403 Highland Rdg",
    "sg:city":"Jonesboro",
    "sg:classifiers":[
        {
            "category":"Shopping",
            "type":"Retail Goods"
        }
    ],
    "sg:phone":"+1 770 996 1746",
    "sg:postcode":"30238",
    "sg:province":"GA",
    "sg:tags":[
        "merchandise"
    ],
    "wof:name":"Tommy S Shop",
    "wof:placetype":"venue"
},
  "geometry": {"coordinates":[-84.40073,33.499185],"type":"Point"}
}