{
  "type": "Feature",
  "properties": {
    "addr:full":"6753 Jones Mill Ct Ste E Norcross GA 30092",
    "addr:housenumber":"6753",
    "addr:postcode":"30092",
    "addr:street":"Jones Mill Ct Ste E",
    "iso:country":"US",
    "sg:address":"6753 Jones Mill Ct Ste E",
    "sg:city":"Norcross",
    "sg:classifiers":[
        {
            "category":"Shopping",
            "subcategory":"Stationery & Office Supplies",
            "type":"Retail Goods"
        }
    ],
    "sg:phone":"+1 770 409 9999",
    "sg:postcode":"30092",
    "sg:province":"GA",
    "sg:tags":[
        "equipment"
    ],
    "wof:name":"Results International Inc",
    "wof:placetype":"venue"
},
  "geometry": {"coordinates":[-84.253799,33.942799],"type":"Point"}
}