{
  "type": "Feature",
  "properties": {
    "addr:full":"5830 Wilbanks Dr Norcross GA 30092",
    "addr:housenumber":"5830",
    "addr:postcode":"30092",
    "addr:street":"Wilbanks Dr",
    "iso:country":"US",
    "sg:address":"5830 Wilbanks Dr",
    "sg:city":"Norcross",
    "sg:classifiers":[
        {
            "category":"Professional",
            "subcategory":"Management & Consulting",
            "type":"Services"
        }
    ],
    "sg:phone":"+1 770 449 6224",
    "sg:postcode":"30092",
    "sg:province":"GA",
    "sg:tags":[
        "business"
    ],
    "wof:name":"Do-It-4-U Computer Services",
    "wof:placetype":"venue"
},
  "geometry": {"coordinates":[-84.243815,33.980963],"type":"Point"}
}