{
  "type": "Feature",
  "properties": {
    "addr:full":"710 1st St NE Moultrie GA 31768",
    "addr:housenumber":"710",
    "addr:postcode":"31768",
    "addr:street":"1St St Ne",
    "iso:country":"US",
    "sg:address":"710 1st St NE",
    "sg:city":"Moultrie",
    "sg:classifiers":[
        {
            "category":"Professional",
            "subcategory":"Management & Consulting",
            "type":"Services"
        }
    ],
    "sg:phone":"+1 229 891 2447",
    "sg:postcode":"31768",
    "sg:province":"GA",
    "sg:tags":[
        "credit",
        "institution",
        "business"
    ],
    "wof:name":"Colquitt County Fast Cash",
    "wof:placetype":"venue"
},
  "geometry": {"coordinates":[-83.78759100000001,31.187375],"type":"Point"}
}