{
  "type": "Feature",
  "properties": {
    "iso:country":"US",
    "sg:address":"629 Glenwood Ave SE",
    "sg:city":"Atlanta",
    "sg:classifiers":[
        {
            "category":"Shopping",
            "type":"Retail Goods"
        }
    ],
    "sg:phone":"+1 404 627 0393",
    "sg:postcode":"30312",
    "sg:province":"GA",
    "sg:tags":[
        "art",
        "gallery",
        "merchandise",
        "dealer"
    ],
    "wof:name":"Young Blood Galleries",
    "wof:placetype":"venue"
},
  "geometry": {"coordinates":[-84.36676799999999,33.742526],"type":"Point"}
}