{
  "type": "Feature",
  "properties": {
    "iso:country":"US",
    "sg:address":"767 Grogan St",
    "sg:city":"Lavonia",
    "sg:classifiers":[
        {
            "category":"Home & Garden",
            "subcategory":"Building Materials",
            "type":"Retail Goods"
        }
    ],
    "sg:phone":"+1 706 356 8495",
    "sg:postcode":"30553",
    "sg:province":"GA",
    "sg:tags":[
        "glass",
        "window",
        "plate"
    ],
    "wof:name":"Shirley's Glass Masters",
    "wof:placetype":"venue"
},
  "geometry": {"coordinates":[-83.105705,34.435682],"type":"Point"}
}