{
  "type": "Feature",
  "properties": {
    "iso:country":"US",
    "sg:address":"4015 S Cobb Dr SE",
    "sg:city":"Smyrna",
    "sg:classifiers":[
        {
            "category":"Health Services",
            "subcategory":"Doctor",
            "type":"Services"
        }
    ],
    "sg:phone":"+1 770 739 0052",
    "sg:postcode":"30080",
    "sg:province":"GA",
    "sg:tags":[
        "medicine",
        "physician",
        "practice",
        "surgeons",
        "family"
    ],
    "wof:name":"Shailesh Gandhi Md Pc",
    "wof:placetype":"venue"
},
  "geometry": {"coordinates":[-84.511836,33.85395],"type":"Point"}
}