{
  "type": "Feature",
  "properties": {
    "addr:full":"23 Bacon St Maysville GA 30558",
    "addr:housenumber":"23",
    "addr:postcode":"30558",
    "addr:street":"Bacon St",
    "iso:country":"US",
    "sg:address":"23 Bacon St",
    "sg:city":"Maysville",
    "sg:classifiers":[
        {
            "category":"Shopping",
            "subcategory":"Musical Instruments",
            "type":"Retail Goods"
        }
    ],
    "sg:phone":"+1 706 652 3155",
    "sg:postcode":"30558",
    "sg:province":"GA",
    "sg:tags":[
        "music",
        "dealer"
    ],
    "sg:website":"www.roguerecords.biz",
    "wof:name":"Rogue Records",
    "wof:placetype":"venue"
},
  "geometry": {"coordinates":[-83.563228,34.254384],"type":"Point"}
}