{
  "type": "Feature",
  "properties": {
    "addr:full":"22 Jakes Way Dahlonega GA 30533",
    "addr:housenumber":"22",
    "addr:postcode":"30533",
    "addr:street":"Jakes Way",
    "iso:country":"US",
    "sg:address":"22 Jakes Way",
    "sg:city":"Dahlonega",
    "sg:classifiers":[
        {
            "category":"Retail",
            "subcategory":"Repair Shop",
            "type":"Services"
        }
    ],
    "sg:phone":"+1 706 864 6585",
    "sg:postcode":"30533",
    "sg:province":"GA",
    "sg:tags":[
        "repairing",
        "lawn",
        "mower"
    ],
    "wof:name":"Danny's Small Engine Repair",
    "wof:placetype":"venue"
},
  "geometry": {"coordinates":[-84.03269299999999,34.561983],"type":"Point"}
}