{
  "type": "Feature",
  "properties": {
    "iso:country":"US",
    "sg:address":"2518 State Rte 101",
    "sg:city":"Dallas",
    "sg:classifiers":[
        {
            "category":"Building & Trades",
            "subcategory":"Landscaping Services",
            "type":"Services"
        }
    ],
    "sg:phone":"+1 678 363 8298",
    "sg:postcode":"30157",
    "sg:province":"GA",
    "wof:name":"Nash Tree",
    "wof:placetype":"venue"
},
  "geometry": {"coordinates":[-85.002662,33.876703],"type":"Point"}
}