{
  "type": "Feature",
  "properties": {
    "addr:full":"5795 Elm Tree Dr NE Buford GA 30518",
    "addr:housenumber":"5795",
    "addr:postcode":"30518",
    "addr:street":"Elm Tree Dr Ne",
    "iso:country":"US",
    "sg:address":"5795 Elm Tree Dr NE",
    "sg:city":"Buford",
    "sg:classifiers":[
        {
            "category":"Manufacturing",
            "subcategory":"Tools & Machinery",
            "type":"Manufacturing & Wholesale Goods"
        }
    ],
    "sg:phone":"+1 770 945 3490",
    "sg:postcode":"30518",
    "sg:province":"GA",
    "sg:tags":[
        "analytical",
        "instrument",
        "mfg"
    ],
    "wof:name":"Groom Jimmy W Et Al",
    "wof:placetype":"venue"
},
  "geometry": {"coordinates":[-84.02521299999999,34.142471],"type":"Point"}
}