{
  "type": "Feature",
  "properties": {
    "iso:country":"US",
    "sg:address":"2694 Ridgewood Dr",
    "sg:city":"Marietta",
    "sg:classifiers":[
        {
            "category":"Building & Trades",
            "subcategory":"Pest Control",
            "type":"Services"
        }
    ],
    "sg:phone":"+1 770 426 7930",
    "sg:postcode":"30066",
    "sg:province":"GA",
    "wof:name":"Assured Pest Control",
    "wof:placetype":"venue"
},
  "geometry": {"coordinates":[-84.5457,34.016399],"type":"Point"}
}