{
  "type": "Feature",
  "properties": {
    "addr:full":"756 Holcomb Bridge Rd Norcross GA 30071",
    "addr:housenumber":"756",
    "addr:postcode":"30071",
    "addr:street":"Holcomb Bridge Rd",
    "iso:country":"US",
    "sg:address":"756 Holcomb Bridge Rd",
    "sg:city":"Norcross",
    "sg:classifiers":[
        {
            "category":"Manufacturing",
            "subcategory":"Textiles",
            "type":"Manufacturing & Wholesale Goods"
        }
    ],
    "sg:phone":"+1 678 282 0178",
    "sg:postcode":"30071",
    "sg:province":"GA",
    "sg:tags":[
        "textiles-manufacturers"
    ],
    "wof:name":"R J Ackaway And Associates",
    "wof:placetype":"venue"
},
  "geometry": {"coordinates":[-84.224464,33.945524],"type":"Point"}
}