{
  "type": "Feature",
  "properties": {
    "addr:full":"2012 Airport Ind Park Dr SE Ste A Marietta GA 30060",
    "addr:housenumber":"2012",
    "addr:postcode":"30060",
    "addr:street":"Airport Ind Park Dr Se Ste A",
    "iso:country":"US",
    "sg:address":"2012 Airport Ind Park Dr SE Ste A",
    "sg:city":"Marietta",
    "sg:classifiers":[
        {
            "category":"Retail",
            "subcategory":"Auto Repair",
            "type":"Services"
        }
    ],
    "sg:phone":"+1 770 612 0056",
    "sg:postcode":"30060",
    "sg:province":"GA",
    "wof:name":"Auto Tech",
    "wof:placetype":"venue"
},
  "geometry": {"coordinates":[-84.498794,33.902665],"type":"Point"}
}