{
  "type": "Feature",
  "properties": {
    "addr:full":"1230 Silverwood Ct NE Lawrenceville GA 30043",
    "addr:housenumber":"1230",
    "addr:postcode":"30043",
    "addr:street":"Silverwood Ct Ne",
    "iso:country":"US",
    "sg:address":"1230 Silverwood Ct NE",
    "sg:city":"Lawrenceville",
    "sg:classifiers":[
        {
            "category":"Real Estate",
            "subcategory":"Real Estate Operator",
            "type":"Services"
        }
    ],
    "sg:phone":"+1 770 277 3789",
    "sg:postcode":"30043",
    "sg:province":"GA",
    "sg:tags":[
        "building",
        "nonresidential"
    ],
    "wof:name":"Shin Properties Lllp",
    "wof:placetype":"venue"
},
  "geometry": {"coordinates":[-83.95226099999999,34.01571],"type":"Point"}
}