{
  "type": "Feature",
  "properties": {
    "iso:country":"US",
    "sg:address":"816 19th Ave E",
    "sg:city":"Cordele",
    "sg:classifiers":[
        {
            "category":"Building & Trades",
            "subcategory":"Construction",
            "type":"Services"
        }
    ],
    "sg:phone":"+1 229 273 0461",
    "sg:postcode":"31015",
    "sg:province":"GA",
    "sg:tags":[
        "house"
    ],
    "wof:name":"Jimmie Meadows",
    "wof:placetype":"venue"
},
  "geometry": {"coordinates":[-83.770505,31.960346],"type":"Point"}
}