{
  "type": "Feature",
  "properties": {
    "addr:full":"6317 Peachtree Industrial Blvd Atlanta GA 30360",
    "addr:housenumber":"6317",
    "addr:postcode":"30360",
    "addr:street":"Peachtree Industrial Blvd",
    "iso:country":"US",
    "sg:address":"6317 Peachtree Industrial Blvd",
    "sg:city":"Atlanta",
    "sg:classifiers":[
        {
            "category":"Utilities",
            "subcategory":"Electric",
            "type":"Services"
        }
    ],
    "sg:phone":"+1 770 454 7453",
    "sg:postcode":"30360",
    "sg:province":"GA",
    "sg:tags":[
        "company"
    ],
    "wof:name":"Georgia Power Company",
    "wof:placetype":"venue"
},
  "geometry": {"coordinates":[-84.28343099999999,33.92008],"type":"Point"}
}