{
  "type": "Feature",
  "properties": {
    "addr:full":"590 Cascade Avenue SW Atlanta GA 30310",
    "addr:housenumber":"590",
    "addr:postcode":"30310",
    "addr:street":"Cascade Avenue Sw",
    "iso:country":"US",
    "sg:address":"590 Cascade Avenue SW",
    "sg:city":"Atlanta",
    "sg:classifiers":[
        {
            "category":"Banks & Credit Unions",
            "subcategory":"Bank",
            "type":"Services"
        },
        {
            "category":"Banks & Credit Unions",
            "subcategory":"Financial Services",
            "type":"Services"
        }
    ],
    "sg:phone":"+1 404 753 4258",
    "sg:postcode":"30310",
    "sg:province":"GA",
    "sg:tags":[
        "broker",
        "mortgage"
    ],
    "wof:name":"Washington Mutual",
    "wof:placetype":"venue"
},
  "geometry": {"coordinates":[-84.434882,33.738447],"type":"Point"}
}