{
  "type": "Feature",
  "properties": {
    "addr:full":"1239 Colony Bend Ct Lawrenceville GA 30043",
    "addr:housenumber":"1239",
    "addr:postcode":"30043",
    "addr:street":"Colony Bend Ct",
    "iso:country":"US",
    "sg:address":"1239 Colony Bend Ct",
    "sg:city":"Lawrenceville",
    "sg:classifiers":[
        {
            "category":"Professional",
            "type":"Services"
        }
    ],
    "sg:phone":"+1 770 338 9247",
    "sg:postcode":"30043",
    "sg:province":"GA",
    "wof:name":"Oriental Building Service Inc",
    "wof:placetype":"venue"
},
  "geometry": {"coordinates":[-84.03986,33.969637],"type":"Point"}
}