{
  "type": "Feature",
  "properties": {
    "addr:full":"1764 Hudson Bridge Rd Stockbridge GA 30281",
    "addr:housenumber":"1764",
    "addr:postcode":"30281",
    "addr:street":"Hudson Bridge Rd",
    "iso:country":"US",
    "sg:address":"1764 Hudson Bridge Rd",
    "sg:city":"Stockbridge",
    "sg:classifiers":[
        {
            "category":"Restaurant",
            "type":"Food & Drink"
        }
    ],
    "sg:menulink":"http://www.allmenus.com/ga/stockbridge/132711-subway/menu/",
    "sg:phone":"+1 770 389 5455",
    "sg:postcode":"30281",
    "sg:province":"GA",
    "sg:tags":[
        "american",
        "sandwich"
    ],
    "wof:name":"Subway",
    "wof:placetype":"venue"
},
  "geometry": {"coordinates":[-84.243354,33.501665],"type":"Point"}
}