{
  "type": "Feature",
  "properties": {
    "iso:country":"US",
    "sg:address":"993 Cleburne Pkwy",
    "sg:city":"Hiram",
    "sg:classifiers":[
        {
            "category":"Retail",
            "subcategory":"Auto Repair",
            "type":"Services"
        }
    ],
    "sg:phone":"+1 770 439 0080",
    "sg:postcode":"30141",
    "sg:province":"GA",
    "sg:tags":[
        "body",
        "shop"
    ],
    "wof:name":"Maty Classic Imports",
    "wof:placetype":"venue"
},
  "geometry": {"coordinates":[-84.728798,33.869801],"type":"Point"}
}