{
  "type": "Feature",
  "properties": {
    "addr:full":"5313 Red Rock Trce Powder Springs GA 30127",
    "addr:housenumber":"5313",
    "addr:postcode":"30127",
    "addr:street":"Red Rock Trce",
    "iso:country":"US",
    "sg:address":"5313 Red Rock Trce",
    "sg:city":"Powder Springs",
    "sg:classifiers":[
        {
            "category":"Building & Trades",
            "subcategory":"Electrical",
            "type":"Services"
        }
    ],
    "sg:phone":"+1 770 794 5945",
    "sg:postcode":"30127",
    "sg:province":"GA",
    "sg:tags":[
        "electric",
        "contractor"
    ],
    "wof:name":"Mitchell Electric",
    "wof:placetype":"venue"
},
  "geometry": {"coordinates":[-84.70712,33.971184],"type":"Point"}
}