{
  "type": "Feature",
  "properties": {
    "iso:country":"US",
    "sg:address":"3055 Nancy Creek Rd NW",
    "sg:city":"Atlanta",
    "sg:classifiers":[
        {
            "category":"Sports & Exercise",
            "subcategory":"Gym",
            "type":"Entertainment"
        }
    ],
    "sg:phone":"+1 404 355 0068",
    "sg:postcode":"30327",
    "sg:province":"GA",
    "sg:tags":[
        "training",
        "motivational"
    ],
    "wof:name":"Atlanta Tennis Academy",
    "wof:placetype":"venue"
},
  "geometry": {"coordinates":[-84.44257399999999,33.837897],"type":"Point"}
}