{
  "type": "Feature",
  "properties": {
    "iso:country":"US",
    "sg:address":"50 Upper Alabama St SW Ste 7",
    "sg:city":"Atlanta",
    "sg:classifiers":[
        {
            "category":"Shopping Center",
            "type":"Public Place"
        }
    ],
    "sg:phone":"+1 404 523 2311",
    "sg:postcode":"30303",
    "sg:province":"GA",
    "wof:name":"O'leary Partners Inc",
    "wof:placetype":"venue"
},
  "geometry": {"coordinates":[-84.391899,33.752201],"type":"Point"}
}