{
  "type": "Feature",
  "properties": {
    "addr:full":"920 Cripple Creek Dr Lawrenceville GA 30043",
    "addr:housenumber":"920",
    "addr:postcode":"30043",
    "addr:street":"Cripple Creek Dr",
    "iso:country":"US",
    "sg:address":"920 Cripple Creek Dr",
    "sg:city":"Lawrenceville",
    "sg:classifiers":[
        {
            "category":"Building & Trades",
            "subcategory":"Construction",
            "type":"Services"
        }
    ],
    "sg:phone":"+1 770 736 6868",
    "sg:postcode":"30043",
    "sg:province":"GA",
    "wof:name":"Southern Breeze",
    "wof:placetype":"venue"
},
  "geometry": {"coordinates":[-83.98595,33.985422],"type":"Point"}
}