{
  "type": "Feature",
  "properties": {
    "iso:country":"US",
    "sg:address":"204 Bluff Creek Dr",
    "sg:city":"Woodstock",
    "sg:classifiers":[
        {
            "category":"Building & Trades",
            "subcategory":"Pest Control",
            "type":"Services"
        }
    ],
    "sg:phone":"+1 770 926 3784",
    "sg:postcode":"30188",
    "sg:province":"GA",
    "wof:name":"Jenkins Exterminating Co",
    "wof:placetype":"venue"
},
  "geometry": {"coordinates":[-84.456205,34.122651],"type":"Point"}
}