{
  "type": "Feature",
  "properties": {
    "iso:country":"US",
    "sg:address":"433 Shiloh Rd",
    "sg:city":"Cedartown",
    "sg:classifiers":[
        {
            "category":"Organizations",
            "subcategory":"Religious Organization",
            "type":"Services"
        }
    ],
    "sg:phone":"+1 770 749 1540",
    "sg:postcode":"30125",
    "sg:province":"GA",
    "wof:name":"Shiloh Baptist Church",
    "wof:placetype":"venue"
},
  "geometry": {"coordinates":[-85.359882,33.947976],"type":"Point"}
}