{
  "type": "Feature",
  "properties": {
    "addr:full":"3170 Wicks Creek Trl Marietta GA 30062",
    "addr:postcode":"3170;30062",
    "addr:street":"Wicks Creek Trl",
    "iso:country":"US",
    "sg:address":"3170 Wicks Creek Trl",
    "sg:city":"Marietta",
    "sg:classifiers":[
        {
            "category":"Professional",
            "subcategory":"Business Services",
            "type":"Services"
        }
    ],
    "sg:phone":"+1 770 565 4850",
    "sg:postcode":"30062",
    "sg:province":"GA",
    "wof:name":"Nationwide Purchasing Assn",
    "wof:placetype":"venue"
},
  "geometry": {"coordinates":[-84.456208,33.991836],"type":"Point"}
}