{
  "type": "Feature",
  "properties": {
    "iso:country":"US",
    "sg:address":"4940 Forestglade Ct",
    "sg:city":"Stone Mountain",
    "sg:classifiers":[
        {
            "category":"Building & Trades",
            "subcategory":"Construction",
            "type":"Services"
        }
    ],
    "sg:phone":"+1 770 496 5651",
    "sg:postcode":"30087",
    "sg:province":"GA",
    "sg:tags":[
        "general",
        "contractor"
    ],
    "wof:name":"D K Lippy Construction Company",
    "wof:placetype":"venue"
},
  "geometry": {"coordinates":[-84.185518,33.840808],"type":"Point"}
}