{
  "type": "Feature",
  "properties": {
    "addr:full":"234 W Main St Manchester GA 31816",
    "addr:housenumber":"234",
    "addr:postcode":"31816",
    "addr:street":"W Main St",
    "iso:country":"US",
    "sg:address":"234 W Main St",
    "sg:city":"Manchester",
    "sg:classifiers":[
        {
            "category":"Personal",
            "subcategory":"Beauty Salon",
            "type":"Services"
        }
    ],
    "sg:phone":"+1 706 846 8376",
    "sg:postcode":"31816",
    "sg:province":"GA",
    "sg:tags":[
        "shop"
    ],
    "wof:name":"Styles By Jackie",
    "wof:placetype":"venue"
},
  "geometry": {"coordinates":[-84.616866,32.853239],"type":"Point"}
}