{
  "type": "Feature",
  "properties": {
    "addr:full":"1306 Troupe St Augusta GA 30904",
    "addr:housenumber":"1306",
    "addr:postcode":"30904",
    "addr:street":"Troupe St",
    "iso:country":"US",
    "sg:address":"1306 Troupe St",
    "sg:city":"Augusta",
    "sg:classifiers":[
        {
            "category":"Shopping",
            "subcategory":"Optical Goods",
            "type":"Retail Goods"
        }
    ],
    "sg:phone":"+1 706 733 6634",
    "sg:postcode":"30904",
    "sg:province":"GA",
    "sg:tags":[
        "optician"
    ],
    "wof:name":"Murphy Jennings Opticians",
    "wof:placetype":"venue"
},
  "geometry": {"coordinates":[-82.014427,33.467395],"type":"Point"}
}