{
  "type": "Feature",
  "properties": {
    "iso:country":"US",
    "sg:address":"160 Freys Gin Rd SE",
    "sg:city":"Marietta",
    "sg:classifiers":[
        {
            "category":"Retail",
            "subcategory":"Auto Repair",
            "type":"Services"
        }
    ],
    "sg:phone":"+1 678 797 1903",
    "sg:postcode":"30067",
    "sg:province":"GA",
    "wof:name":"Carbras Auto Service Llc",
    "wof:placetype":"venue"
},
  "geometry": {"coordinates":[-84.516728,33.948318],"type":"Point"}
}