{
  "type": "Feature",
  "properties": {
    "iso:country":"US",
    "sg:address":"6 Tanglewood Rd",
    "sg:city":"St Simons Island",
    "sg:classifiers":[
        {
            "category":"Building & Trades",
            "subcategory":"Construction",
            "type":"Services"
        },
        {
            "category":"Home & Garden",
            "subcategory":"Home Furnishings",
            "type":"Retail Goods"
        }
    ],
    "sg:phone":"+1 912 634 5736",
    "sg:postcode":"31522",
    "sg:province":"GA",
    "sg:tags":[
        "c",
        "retailer",
        "cabinet",
        "lighting",
        "custom",
        "maker"
    ],
    "wof:name":"Design Lines",
    "wof:placetype":"venue"
},
  "geometry": {"coordinates":[-81.37516599999999,31.186359],"type":"Point"}
}