{
  "type": "Feature",
  "properties": {
    "iso:country":"US",
    "sg:address":"7210 Hwy 85",
    "sg:city":"Riverdale",
    "sg:classifiers":[
        {
            "category":"Restaurant",
            "type":"Food & Drink"
        }
    ],
    "sg:phone":"+1 770 996 0703",
    "sg:postcode":"30274",
    "sg:province":"GA",
    "sg:tags":[
        "seafood"
    ],
    "sg:website":"http://loucatfishkithen.com",
    "wof:name":"Louisiana Catfish Kitchen",
    "wof:placetype":"venue"
},
  "geometry": {"coordinates":[-84.413849,33.558212],"type":"Point"}
}