{
  "type": "Feature",
  "properties": {
    "addr:full":"402 S Oak St Eatonton GA 31024",
    "addr:housenumber":"402",
    "addr:postcode":"31024",
    "addr:street":"S Oak St",
    "iso:country":"US",
    "sg:address":"402 S Oak St",
    "sg:city":"Eatonton",
    "sg:classifiers":[
        {
            "category":"Place Of Worship",
            "subcategory":"Church",
            "type":"Public Place"
        },
        {
            "category":"Place Of Worship",
            "type":"Public Place"
        }
    ],
    "sg:phone":"+1 706 485 9967",
    "sg:postcode":"31024",
    "sg:province":"GA",
    "sg:tags":[
        "churches-interdenominational",
        "churches-various",
        "denomination"
    ],
    "wof:name":"Zion Covenant Fellowship",
    "wof:placetype":"venue"
},
  "geometry": {"coordinates":[-83.390079,33.319386],"type":"Point"}
}