{
  "type": "Feature",
  "properties": {
    "addr:full":"357 Market St Swainsboro GA 30401",
    "addr:housenumber":"357",
    "addr:postcode":"30401",
    "addr:street":"Market St",
    "iso:country":"US",
    "sg:address":"357 Market St",
    "sg:city":"Swainsboro",
    "sg:classifiers":[
        {
            "category":"Professional",
            "subcategory":"Management & Consulting",
            "type":"Services"
        }
    ],
    "sg:phone":"+1 478 237 5078",
    "sg:postcode":"30401",
    "sg:province":"GA",
    "sg:tags":[
        "public",
        "relations"
    ],
    "wof:name":"Public Works",
    "wof:placetype":"venue"
},
  "geometry": {"coordinates":[-82.324029,32.591373],"type":"Point"}
}