{
  "type": "Feature",
  "properties": {
    "iso:country":"US",
    "sg:address":"27 Doranne Ct",
    "sg:city":"Smyrna",
    "sg:classifiers":[
        {
            "category":"Professional",
            "subcategory":"Computer Services",
            "type":"Services"
        }
    ],
    "sg:phone":"+1 770 433 2002",
    "sg:postcode":"30080",
    "sg:province":"GA",
    "sg:tags":[
        "datum"
    ],
    "wof:name":"Gaelan Technologies Inc",
    "wof:placetype":"venue"
},
  "geometry": {"coordinates":[-84.49312500000001,33.894139],"type":"Point"}
}