{
  "type": "Feature",
  "properties": {
    "iso:country":"US",
    "sg:address":"114 Sunset Dr",
    "sg:city":"Sharpsburg",
    "sg:classifiers":[
        {
            "category":"Building & Trades",
            "subcategory":"Construction",
            "type":"Services"
        }
    ],
    "sg:phone":"+1 770 253 7908",
    "sg:postcode":"30277",
    "sg:province":"GA",
    "sg:tags":[
        "hanging",
        "contractor"
    ],
    "wof:name":"McDonald Painting",
    "wof:placetype":"venue"
},
  "geometry": {"coordinates":[-84.644711,33.344553],"type":"Point"}
}