{
  "type": "Feature",
  "properties": {
    "iso:country":"US",
    "sg:address":"730 W Habersham St",
    "sg:city":"Milledgeville",
    "sg:classifiers":[
        {
            "category":"Home & Garden",
            "subcategory":"Garden Supply",
            "type":"Retail Goods"
        },
        {
            "category":"Shopping",
            "subcategory":"Gifts & Souvenirs",
            "type":"Retail Goods"
        },
        {
            "category":"Shopping",
            "subcategory":"Crafts & Fabrics",
            "type":"Retail Goods"
        },
        {
            "category":"Shopping",
            "subcategory":"Florist",
            "type":"Retail Goods"
        }
    ],
    "sg:phone":"+1 478 452 1921",
    "sg:postcode":"31061",
    "sg:province":"GA",
    "sg:tags":[
        "plant",
        "etc-retail",
        "dried",
        "basket",
        "trees-silk",
        "flowers"
    ],
    "sg:website":"http://www.lawrenceflowershop.com",
    "wof:name":"Lawrence's Flower Shop",
    "wof:placetype":"venue"
},
  "geometry": {"coordinates":[-83.239158,33.084706],"type":"Point"}
}