{
  "type": "Feature",
  "properties": {
    "iso:country":"US",
    "sg:address":"1706 Chestnut Oak Dr",
    "sg:city":"Dalton",
    "sg:classifiers":[
        {
            "category":"Professional",
            "type":"Services"
        }
    ],
    "sg:phone":"+1 706 259 5522",
    "sg:postcode":"30721",
    "sg:province":"GA",
    "wof:name":"George Hill",
    "wof:placetype":"venue"
},
  "geometry": {"coordinates":[-84.960803,34.807109],"type":"Point"}
}