{
  "type": "Feature",
  "properties": {
    "addr:full":"5141 Stone Mountain Fwy SW Stone Mountain GA 30087",
    "addr:housenumber":"5141",
    "addr:postcode":"30087",
    "addr:street":"Fwy Sw",
    "iso:country":"US",
    "sg:address":"5141 Stone Mountain Fwy SW",
    "sg:city":"Stone Mountain",
    "sg:classifiers":[
        {
            "category":"Shopping",
            "subcategory":"Florist",
            "type":"Retail Goods"
        }
    ],
    "sg:phone":"+1 770 982 3598",
    "sg:postcode":"30087",
    "sg:province":"GA",
    "wof:name":"Tammy's Flowers",
    "wof:placetype":"venue"
},
  "geometry": {"coordinates":[-84.107975,33.824194],"type":"Point"}
}