{
  "type": "Feature",
  "properties": {
    "addr:full":"1105 N 5th Ave Rome GA 30165",
    "addr:housenumber":"1105",
    "addr:postcode":"ga 30165",
    "addr:street":"N 5Th Ave",
    "iso:country":"US",
    "sg:address":"1105 N 5th Ave",
    "sg:city":"Rome",
    "sg:classifiers":[
        {
            "category":"Health Services",
            "subcategory":"Doctor",
            "type":"Services"
        }
    ],
    "sg:phone":"+1 706 291 0884",
    "sg:postcode":"30165",
    "sg:province":"GA",
    "sg:tags":[
        "medical"
    ],
    "wof:name":"Northwest Georgia Ob-Gyn Assoc",
    "wof:placetype":"venue"
},
  "geometry": {"coordinates":[-85.17839499999999,34.264669],"type":"Point"}
}