{
  "type": "Feature",
  "properties": {
    "addr:full":"72 Appaloosa Way Sharpsburg GA 30277",
    "addr:housenumber":"72",
    "addr:postcode":"30277",
    "addr:street":"Appaloosa Way",
    "iso:country":"US",
    "sg:address":"72 Appaloosa Way",
    "sg:city":"Sharpsburg",
    "sg:classifiers":[
        {
            "category":"Manufacturing",
            "subcategory":"Toys & Sporting Goods",
            "type":"Manufacturing & Wholesale Goods"
        }
    ],
    "sg:phone":"+1 770 253 9752",
    "sg:postcode":"30277",
    "sg:province":"GA",
    "sg:tags":[
        "mfg"
    ],
    "wof:name":"Smallwood Firearms",
    "wof:placetype":"venue"
},
  "geometry": {"coordinates":[-84.699196,33.31203],"type":"Point"}
}