{
  "type": "Feature",
  "properties": {
    "iso:country":"US",
    "sg:address":"450 Spruce Ct",
    "sg:city":"Alpharetta",
    "sg:classifiers":[
        {
            "category":"Banks & Credit Unions",
            "subcategory":"Bank",
            "type":"Services"
        }
    ],
    "sg:phone":"+1 770 751 9820",
    "sg:postcode":"30004",
    "sg:province":"GA",
    "sg:tags":[
        "company",
        "mortgage"
    ],
    "wof:name":"Torch Mortgage Corporation",
    "wof:placetype":"venue"
},
  "geometry": {"coordinates":[-84.247029,34.124427],"type":"Point"}
}