{
  "type": "Feature",
  "properties": {
    "iso:country":"US",
    "sg:address":"185 Commercial Dr",
    "sg:city":"Rincon",
    "sg:phone":"+1 912 826 7497",
    "sg:postcode":"31326",
    "sg:province":"GA",
    "sg:website":"http://www.sassystepsdance.com",
    "wof:name":"Sassy Steps School of Dance & Baton",
    "wof:placetype":"venue"
},
  "geometry": {"coordinates":[-81.20760799999999,32.251264],"type":"Point"}
}