{
  "type": "Feature",
  "properties": {
    "iso:country":"US",
    "sg:address":"3191 Valley Brook Pl",
    "sg:city":"Decatur",
    "sg:classifiers":[
        {
            "category":"Building & Trades",
            "subcategory":"Landscaping Services",
            "type":"Services"
        }
    ],
    "sg:phone":"+1 404 444 0240",
    "sg:postcode":"30033",
    "sg:province":"GA",
    "wof:name":"J & D Tree Service",
    "wof:placetype":"venue"
},
  "geometry": {"coordinates":[-84.26563299999999,33.807314],"type":"Point"}
}