{
  "type": "Feature",
  "properties": {
    "iso:country":"US",
    "sg:address":"10 Packinghouse Rd",
    "sg:city":"Statesboro",
    "sg:classifiers":[
        {
            "category":"Professional",
            "subcategory":"Management & Consulting",
            "type":"Services"
        }
    ],
    "sg:phone":"+1 912 489 1001",
    "sg:postcode":"30458",
    "sg:province":"GA",
    "wof:name":"Madison Meadows",
    "wof:placetype":"venue"
},
  "geometry": {"coordinates":[-81.767216,32.451884],"type":"Point"}
}