{
  "type": "Feature",
  "properties": {
    "addr:full":"3248 Shallowford Rd NE Atlanta GA 30341",
    "addr:housenumber":"3248",
    "addr:postcode":"30341",
    "addr:street":"Shallowford Rd Ne",
    "iso:country":"US",
    "sg:address":"3248 Shallowford Rd NE",
    "sg:city":"Atlanta",
    "sg:classifiers":[
        {
            "category":"Autos & Motor Vehicles",
            "subcategory":"Automobile Sales",
            "type":"Retail Goods"
        }
    ],
    "sg:phone":"+1 678 502 7062",
    "sg:postcode":"30341",
    "sg:province":"GA",
    "sg:tags":[
        "car",
        "used",
        "cars-wholesale",
        "dealers-used"
    ],
    "wof:name":"Pars Auto Trading",
    "wof:placetype":"venue"
},
  "geometry": {"coordinates":[-84.285053,33.88297],"type":"Point"}
}