{
  "type": "Feature",
  "properties": {
    "addr:full":"3575 Fulton Mill Rd Macon GA 31206",
    "addr:housenumber":"3575",
    "addr:postcode":"31206",
    "addr:street":"Fulton Mill Rd",
    "iso:country":"US",
    "sg:address":"3575 Fulton Mill Rd",
    "sg:city":"Macon",
    "sg:classifiers":[
        {
            "category":"Health Services",
            "subcategory":"Hospital",
            "type":"Services"
        }
    ],
    "sg:phone":"+1 478 471 5388",
    "sg:postcode":"31206",
    "sg:province":"GA",
    "sg:tags":[
        "specialty"
    ],
    "wof:name":"River Edge Recovery Center",
    "wof:placetype":"venue"
},
  "geometry": {"coordinates":[-83.748419,32.804936],"type":"Point"}
}