{
  "type": "Feature",
  "properties": {
    "addr:full":"100 Pinewood Way Dalton GA 30721",
    "addr:housenumber":"100",
    "addr:postcode":"30721",
    "addr:street":"Pinewood Way",
    "iso:country":"US",
    "sg:address":"100 Pinewood Way",
    "sg:city":"Dalton",
    "sg:classifiers":[
        {
            "category":"Organizations",
            "subcategory":"Community Association",
            "type":"Services"
        }
    ],
    "sg:phone":"+1 706 259 9280",
    "sg:postcode":"30721",
    "sg:province":"GA",
    "wof:name":"Kiwanis International Inc",
    "wof:placetype":"venue"
},
  "geometry": {"coordinates":[-84.964491,34.818341],"type":"Point"}
}