{
  "type": "Feature",
  "properties": {
    "addr:full":"348 W Pine St Jesup GA 31545",
    "addr:housenumber":"348",
    "addr:postcode":"31545",
    "addr:street":"W Pine St",
    "iso:country":"US",
    "sg:address":"348 W Pine St",
    "sg:city":"Jesup",
    "sg:classifiers":[
        {
            "category":"Building & Trades",
            "subcategory":"Electrical",
            "type":"Services"
        }
    ],
    "sg:phone":"+1 912 530 9930",
    "sg:postcode":"31545",
    "sg:province":"GA",
    "sg:tags":[
        "good",
        "electrical",
        "contractor"
    ],
    "wof:name":"Southern Wholesale Fishing",
    "wof:placetype":"venue"
},
  "geometry": {"coordinates":[-81.88302,31.609348],"type":"Point"}
}