{
  "type": "Feature",
  "properties": {
    "iso:country":"US",
    "sg:address":"127 Sullivan Rd",
    "sg:city":"Zebulon",
    "sg:classifiers":[
        {
            "category":"Social Services",
            "subcategory":"Child Care",
            "type":"Services"
        }
    ],
    "sg:phone":"+1 706 567 8969",
    "sg:postcode":"30295",
    "sg:province":"GA",
    "sg:tags":[
        "day"
    ],
    "wof:name":"Sonshine Day Care Center",
    "wof:placetype":"venue"
},
  "geometry": {"coordinates":[-84.371044,33.058853],"type":"Point"}
}