{
  "type": "Feature",
  "properties": {
    "iso:country":"US",
    "sg:address":"4921 Jackson Trail Rd",
    "sg:city":"Hoschton",
    "sg:classifiers":[
        {
            "category":"Organizations",
            "subcategory":"Religious Organization",
            "type":"Services"
        }
    ],
    "sg:phone":"+1 706 367 2777",
    "sg:postcode":"30549",
    "sg:province":"GA",
    "sg:tags":[
        "church"
    ],
    "wof:name":"Oak Grove Baptist Church",
    "wof:placetype":"venue"
},
  "geometry": {"coordinates":[-83.681335,34.071399],"type":"Point"}
}