{
  "type": "Feature",
  "properties": {
    "iso:country":"US",
    "sg:address":"2210 Sumner Rd",
    "sg:city":"Moultrie",
    "sg:classifiers":[
        {
            "category":"Farming",
            "subcategory":"Farm",
            "type":"Manufacturing & Wholesale Goods"
        }
    ],
    "sg:phone":"+1 229 985 6677",
    "sg:postcode":"31768",
    "sg:province":"GA",
    "sg:tags":[
        "crop",
        "general"
    ],
    "wof:name":"G R Smith",
    "wof:placetype":"venue"
},
  "geometry": {"coordinates":[-83.77013700000001,31.271052],"type":"Point"}
}