{
  "type": "Feature",
  "properties": {
    "iso:country":"US",
    "sg:address":"205 Pancras Rd SW",
    "sg:city":"Milledgeville",
    "sg:classifiers":[
        {
            "category":"Building & Trades",
            "subcategory":"Construction",
            "type":"Services"
        }
    ],
    "sg:phone":"+1 478 452 5437",
    "sg:postcode":"31061",
    "sg:province":"GA",
    "sg:tags":[
        "billboard",
        "sign"
    ],
    "wof:name":"Wayne Martin Farm",
    "wof:placetype":"venue"
},
  "geometry": {"coordinates":[-83.324512,32.984963],"type":"Point"}
}