{
  "type": "Feature",
  "properties": {
    "iso:country":"US",
    "sg:address":"1875 Old Alabama Rd",
    "sg:city":"Roswell",
    "sg:classifiers":[
        {
            "category":"Professional",
            "subcategory":"Management & Consulting",
            "type":"Services"
        }
    ],
    "sg:phone":"+1 770 518 7576",
    "sg:postcode":"30076",
    "sg:province":"GA",
    "sg:tags":[
        "marketing",
        "consultant"
    ],
    "wof:name":"Chiropractic Scheduling Inst",
    "wof:placetype":"venue"
},
  "geometry": {"coordinates":[-84.314317,34.022394],"type":"Point"}
}