{
  "type": "Feature",
  "properties": {
    "addr:full":"10360 Medlock Bridge Rd Duluth GA 30097",
    "addr:housenumber":"10360",
    "addr:postcode":"30097",
    "addr:street":"Medlock Bridge Rd",
    "iso:country":"US",
    "sg:address":"10360 Medlock Bridge Rd",
    "sg:city":"Duluth",
    "sg:classifiers":[
        {
            "category":"Professional",
            "subcategory":"Detective & Security Services",
            "type":"Services"
        }
    ],
    "sg:phone":"+1 404 495 8364",
    "sg:postcode":"30097",
    "sg:province":"GA",
    "sg:tags":[
        "car"
    ],
    "wof:name":"Investigative Data",
    "wof:placetype":"venue"
},
  "geometry": {"coordinates":[-84.185981,34.033424],"type":"Point"}
}