{
  "type": "Feature",
  "properties": {
    "addr:full":"5900 Coca Cola Blvd Columbus GA 31909",
    "addr:housenumber":"5900",
    "addr:postcode":"31909",
    "addr:street":"Coca Cola Blvd",
    "iso:country":"US",
    "sg:address":"5900 Coca Cola Blvd",
    "sg:city":"Columbus",
    "sg:classifiers":[
        {
            "category":"Shopping",
            "subcategory":"Used Merchandise",
            "type":"Retail Goods"
        }
    ],
    "sg:phone":"+1 706 507 2742",
    "sg:postcode":"31909",
    "sg:province":"GA",
    "sg:tags":[
        "typewriter",
        "furniture"
    ],
    "sg:website":"http://www.teamofficeonline.com",
    "wof:name":"Team Office Products",
    "wof:placetype":"venue"
},
  "geometry": {"coordinates":[-84.887139,32.529101],"type":"Point"}
}