{
  "type": "Feature",
  "properties": {
    "iso:country":"US",
    "sg:address":"281 Lavonia Hwy",
    "sg:city":"Bowersville",
    "sg:classifiers":[
        {
            "category":"Retail",
            "subcategory":"Auto Repair",
            "type":"Services"
        }
    ],
    "sg:phone":"+1 706 376 4751",
    "sg:postcode":"30516",
    "sg:province":"GA",
    "sg:tags":[
        "muffler",
        "exhaust",
        "system"
    ],
    "wof:name":"Adams Muffler Ctr",
    "wof:placetype":"venue"
},
  "geometry": {"coordinates":[-82.968599,34.361612],"type":"Point"}
}