{
  "type": "Feature",
  "properties": {
    "addr:full":"1770 Presidential Cir Ste 115 Snellville GA 30078",
    "addr:housenumber":"1770",
    "addr:postcode":"30078",
    "addr:street":"Presidential Cir Ste 115",
    "iso:country":"US",
    "sg:address":"1770 Presidential Cir Ste 115",
    "sg:city":"Snellville",
    "sg:classifiers":[
        {
            "category":"Railroad",
            "type":"Transportation"
        },
        {
            "category":"Airline",
            "type":"Transportation"
        },
        {
            "category":"Travel",
            "subcategory":"Travel Agent",
            "type":"Entertainment"
        },
        {
            "category":"Marine",
            "type":"Transportation"
        }
    ],
    "sg:phone":"+1 770 972 0875",
    "sg:postcode":"30078",
    "sg:province":"GA",
    "sg:tags":[
        "railroads-ticket",
        "agency",
        "services-commercial",
        "cruise",
        "ticket",
        "steamship"
    ],
    "sg:website":"http://www.carlsontravel.com",
    "wof:name":"Carlson Wagonlit Travel",
    "wof:placetype":"venue"
},
  "geometry": {"coordinates":[-84.017419,33.876932],"type":"Point"}
}