{
  "type": "Feature",
  "properties": {
    "iso:country":"US",
    "sg:address":"973 US Hwy 78",
    "sg:city":"Temple",
    "sg:classifiers":[
        {
            "category":"Banks & Credit Unions",
            "subcategory":"Financial Services",
            "type":"Services"
        }
    ],
    "sg:phone":"+1 770 562 5617",
    "sg:postcode":"30179",
    "sg:province":"GA",
    "sg:tags":[
        "investor"
    ],
    "wof:name":"Bks Investments Inc",
    "wof:placetype":"venue"
},
  "geometry": {"coordinates":[-84.999205,33.737009],"type":"Point"}
}