{
  "type": "Feature",
  "properties": {
    "addr:full":"255 Airport Rd Eastman GA 31023",
    "addr:housenumber":"255",
    "addr:postcode":"31023",
    "addr:street":"Airport Rd",
    "iso:country":"US",
    "sg:address":"255 Airport Rd",
    "sg:city":"Eastman",
    "sg:classifiers":[
        {
            "category":"Airport",
            "type":"Transportation"
        }
    ],
    "sg:phone":"+1 478 374 3797",
    "sg:postcode":"31023",
    "sg:province":"GA",
    "sg:tags":[
        "aircraft",
        "maintenance"
    ],
    "wof:name":"Central Aviation Maintenance",
    "wof:placetype":"venue"
},
  "geometry": {"coordinates":[-83.127843,32.20581],"type":"Point"}
}