{
  "type": "Feature",
  "properties": {
    "addr:full":"60 Adam Dr Flintstone GA 30725",
    "addr:housenumber":"60",
    "addr:postcode":"30725",
    "addr:street":"Adam Dr",
    "iso:country":"US",
    "sg:address":"60 Adam Dr",
    "sg:city":"Flintstone",
    "sg:classifiers":[
        {
            "category":"Health Services",
            "subcategory":"Health Practitioner",
            "type":"Services"
        }
    ],
    "sg:phone":"+1 706 820 1371",
    "sg:postcode":"30725",
    "sg:province":"GA",
    "sg:tags":[
        "physician",
        "ophthalmology",
        "surgeons"
    ],
    "wof:name":"D Williams, Kyle",
    "wof:placetype":"venue"
},
  "geometry": {"coordinates":[-85.351654,34.92174],"type":"Point"}
}