{
  "type": "Feature",
  "properties": {
    "iso:country":"US",
    "sg:address":"6258 Thomaston Rd",
    "sg:city":"Macon",
    "sg:classifiers":[
        {
            "category":"Organizations",
            "subcategory":"Religious Organization",
            "type":"Services"
        }
    ],
    "sg:phone":"+1 478 477 6097",
    "sg:postcode":"31220",
    "sg:province":"GA",
    "wof:name":"Doles United Methodist Church",
    "wof:placetype":"venue"
},
  "geometry": {"coordinates":[-83.764004,32.851916],"type":"Point"}
}