{
  "type": "Feature",
  "properties": {
    "iso:country":"US",
    "sg:address":"3151 Joe T Rd",
    "sg:city":"Blackshear",
    "sg:classifiers":[
        {
            "category":"Freight",
            "type":"Transportation"
        },
        {
            "category":"Real Estate",
            "subcategory":"Real Estate Operator",
            "type":"Services"
        }
    ],
    "sg:phone":"+1 912 449 2859",
    "sg:postcode":"31516",
    "sg:province":"GA",
    "sg:tags":[
        "mobile",
        "home",
        "site"
    ],
    "wof:name":"Williamson Enterprises",
    "wof:placetype":"venue"
},
  "geometry": {"coordinates":[-82.27703099999999,31.399226],"type":"Point"}
}