{
  "type": "Feature",
  "properties": {
    "addr:full":"5495 Pace Rd Fairburn GA 30213",
    "addr:housenumber":"5495",
    "addr:postcode":"30213",
    "addr:street":"Pace Rd",
    "iso:country":"US",
    "sg:address":"5495 Pace Rd",
    "sg:city":"Fairburn",
    "sg:classifiers":[
        {
            "category":"Building & Trades",
            "subcategory":"Landscaping Services",
            "type":"Services"
        }
    ],
    "sg:phone":"+1 770 969 1927",
    "sg:postcode":"30213",
    "sg:province":"GA",
    "wof:name":"Jims Lawn Service",
    "wof:placetype":"venue"
},
  "geometry": {"coordinates":[-84.737478,33.606875],"type":"Point"}
}