{
  "type": "Feature",
  "properties": {
    "addr:full":"3213 Old Cornelia Hwy Gainesville GA 30507",
    "addr:housenumber":"3213",
    "addr:postcode":"30507",
    "addr:street":"Old Cornelia Hwy",
    "iso:country":"US",
    "sg:address":"3213 Old Cornelia Hwy",
    "sg:city":"Gainesville",
    "sg:classifiers":[
        {
            "category":"Real Estate",
            "subcategory":"Real Estate Operator",
            "type":"Services"
        }
    ],
    "sg:phone":"+1 770 535 0920",
    "sg:postcode":"30507",
    "sg:province":"GA",
    "sg:tags":[
        "property",
        "lessor"
    ],
    "wof:name":"Top Hat Properties LLP",
    "wof:placetype":"venue"
},
  "geometry": {"coordinates":[-83.753319,34.328537],"type":"Point"}
}