{
  "type": "Feature",
  "properties": {
    "iso:country":"US",
    "sg:address":"2903 Mount Vernon Rd",
    "sg:city":"Lithia Springs",
    "sg:classifiers":[
        {
            "category":"Building & Trades",
            "subcategory":"Cleaning & Sanitation",
            "type":"Services"
        }
    ],
    "sg:phone":"+1 770 920 7023",
    "sg:postcode":"30122",
    "sg:province":"GA",
    "sg:tags":[
        "janitor"
    ],
    "wof:name":"Cleanest Clean",
    "wof:placetype":"venue"
},
  "geometry": {"coordinates":[-84.66063200000001,33.726564],"type":"Point"}
}