{
  "type": "Feature",
  "properties": {
    "iso:country":"US",
    "sg:address":"4250 Chatham View Dr",
    "sg:city":"Buford",
    "sg:classifiers":[
        {
            "category":"Professional",
            "subcategory":"Art Services",
            "type":"Services"
        }
    ],
    "sg:phone":"+1 678 482 5300",
    "sg:postcode":"30518",
    "sg:province":"GA",
    "sg:tags":[
        "commercial",
        "design"
    ],
    "wof:name":"Wild Apple Graphics Ltd",
    "wof:placetype":"venue"
},
  "geometry": {"coordinates":[-84.02195399999999,34.082505],"type":"Point"}
}