{
  "type": "Feature",
  "properties": {
    "iso:country":"US",
    "sg:address":"2476 Boone Ford Rd SE",
    "sg:city":"Calhoun",
    "sg:classifiers":[
        {
            "category":"Government",
            "subcategory":"Police Station",
            "type":"Public Place"
        }
    ],
    "sg:phone":"+1 706 629 5073",
    "sg:postcode":"30701",
    "sg:province":"GA",
    "sg:tags":[
        "protection"
    ],
    "wof:name":"Sheriff David",
    "wof:placetype":"venue"
},
  "geometry": {"coordinates":[-84.84164800000001,34.472072],"type":"Point"}
}