{
  "type": "Feature",
  "properties": {
    "iso:country":"US",
    "sg:address":"2928 Moody Rd",
    "sg:city":"Bonaire",
    "sg:classifiers":[
        {
            "category":"Personal",
            "subcategory":"Day Spa",
            "type":"Services"
        }
    ],
    "sg:phone":"+1 478 225 9211",
    "sg:postcode":"31005",
    "sg:province":"GA",
    "sg:website":"www.mintjulipsalonandspa.com",
    "wof:name":"Mint Julip Salon & Spa",
    "wof:placetype":"venue"
},
  "geometry": {"coordinates":[-83.62446799999999,32.559011],"type":"Point"}
}