{
  "type": "Feature",
  "properties": {
    "addr:full":"11 Gateway Blvd S Ste 60 Savannah GA 31419",
    "addr:housenumber":"11;60",
    "addr:postcode":"31419",
    "addr:street":"Gateway Blvd S Ste",
    "iso:country":"US",
    "sg:address":"11 Gateway Blvd S Ste 60",
    "sg:city":"Savannah",
    "sg:classifiers":[
        {
            "category":"Shopping",
            "subcategory":"Department Store",
            "type":"Retail Goods"
        }
    ],
    "sg:phone":"+1 912 925 3488",
    "sg:postcode":"31419",
    "sg:province":"GA",
    "sg:website":"http://www.bealls.com/",
    "wof:name":"Bealls Department Store",
    "wof:placetype":"venue"
},
  "geometry": {"coordinates":[-81.282639,32.00148],"type":"Point"}
}