{
  "type": "Feature",
  "properties": {
    "iso:country":"US",
    "sg:address":"513 Gaskin Ave S",
    "sg:city":"Douglas",
    "sg:classifiers":[
        {
            "category":"Wholesale",
            "subcategory":"Farm Supplies",
            "type":"Manufacturing & Wholesale Goods"
        }
    ],
    "sg:phone":"+1 912 384 5762",
    "sg:postcode":"31533",
    "sg:province":"GA",
    "sg:tags":[
        "grain"
    ],
    "wof:name":"Douglas Peanut & Grain Co",
    "wof:placetype":"venue"
},
  "geometry": {"coordinates":[-82.845383,31.50472],"type":"Point"}
}