{
  "type": "Feature",
  "properties": {
    "iso:country":"US",
    "sg:address":"3035 Lauren Ct",
    "sg:city":"Roswell",
    "sg:classifiers":[
        {
            "category":"Building & Trades",
            "subcategory":"Construction",
            "type":"Services"
        }
    ],
    "sg:phone":"+1 770 518 8849",
    "sg:postcode":"30075",
    "sg:province":"GA",
    "sg:tags":[
        "general",
        "contractor"
    ],
    "wof:name":"Winik Gillman Electrical",
    "wof:placetype":"venue"
},
  "geometry": {"coordinates":[-84.338176,34.02681],"type":"Point"}
}