{
  "type": "Feature",
  "properties": {
    "iso:country":"US",
    "sg:address":"4917 New Peachtree Rd",
    "sg:city":"Chamblee",
    "sg:classifiers":[
        {
            "category":"Wholesale",
            "subcategory":"Auto Parts",
            "type":"Manufacturing & Wholesale Goods"
        }
    ],
    "sg:phone":"+1 770 455 4848",
    "sg:postcode":"30341",
    "sg:province":"GA",
    "sg:tags":[
        "automobile",
        "rebuilt"
    ],
    "sg:website":"www.mazmart.com",
    "wof:name":"Mazmart",
    "wof:placetype":"venue"
},
  "geometry": {"coordinates":[-84.319086,33.880378],"type":"Point"}
}