{
  "type": "Feature",
  "properties": {
    "addr:full":"1723 McCollum Pkwy NW Kennesaw GA 30144",
    "addr:housenumber":"1723",
    "addr:postcode":"30144",
    "addr:street":"Mccollum Pkwy Nw",
    "iso:country":"US",
    "sg:address":"1723 McCollum Pkwy NW",
    "sg:city":"Kennesaw",
    "sg:classifiers":[
        {
            "category":"Building & Trades",
            "subcategory":"Locksmith",
            "type":"Services"
        }
    ],
    "sg:phone":"+1 678 269 7295",
    "sg:postcode":"30144",
    "sg:province":"GA",
    "sg:tags":[
        "key"
    ],
    "wof:name":"555 Emergency Locksmith",
    "wof:placetype":"venue"
},
  "geometry": {"coordinates":[-84.607085,34.014841],"type":"Point"}
}