{
  "type": "Feature",
  "properties": {
    "iso:country":"US",
    "sg:address":"6530 Charter Way",
    "sg:city":"Lithonia",
    "sg:classifiers":[
        {
            "category":"Building & Trades",
            "subcategory":"Cleaning & Sanitation",
            "type":"Services"
        }
    ],
    "sg:phone":"+1 678 526 0307",
    "sg:postcode":"30058",
    "sg:province":"GA",
    "sg:tags":[
        "maintenance"
    ],
    "sg:website":"www.crimescenecleaning.org",
    "wof:name":"Crime Scene Cleaning",
    "wof:placetype":"venue"
},
  "geometry": {"coordinates":[-84.125011,33.730383],"type":"Point"}
}