{
  "type": "Feature",
  "properties": {
    "iso:country":"US",
    "sg:address":"3219 Wintercreeper Dr",
    "sg:city":"Lithonia",
    "sg:classifiers":[
        {
            "category":"Building & Trades",
            "subcategory":"Construction",
            "type":"Services"
        }
    ],
    "sg:phone":"+1 770 981 1588",
    "sg:postcode":"30038",
    "sg:province":"GA",
    "sg:tags":[
        "house"
    ],
    "wof:name":"Gaitor Construction",
    "wof:placetype":"venue"
},
  "geometry": {"coordinates":[-84.196636,33.687568],"type":"Point"}
}