{
  "type": "Feature",
  "properties": {
    "addr:full":"2457 Riverdale Road Atlanta GA 30337",
    "addr:housenumber":"2457",
    "addr:postcode":"30337",
    "addr:street":"Riverdale Road",
    "iso:country":"US",
    "sg:address":"2457 Riverdale Road",
    "sg:city":"Atlanta",
    "sg:classifiers":[
        {
            "category":"Health Services",
            "subcategory":"Dentist",
            "type":"Services"
        }
    ],
    "sg:phone":"+1 404 767 9356",
    "sg:postcode":"30337",
    "sg:province":"GA",
    "wof:name":"Wilson Aldus DMD Jr",
    "wof:placetype":"venue"
},
  "geometry": {"coordinates":[-84.46894899999999,33.634855],"type":"Point"}
}