{
  "type": "Feature",
  "properties": {
    "iso:country":"US",
    "sg:address":"3297 Northcrest Rd",
    "sg:city":"Atlanta",
    "sg:classifiers":[
        {
            "category":"Professional",
            "type":"Services"
        }
    ],
    "sg:phone":"+1 770 908 9224",
    "sg:postcode":"30340",
    "sg:province":"GA",
    "wof:name":"Millennium Images",
    "wof:placetype":"venue"
},
  "geometry": {"coordinates":[-84.24807800000001,33.886349],"type":"Point"}
}