{
  "type": "Feature",
  "properties": {
    "iso:country":"US",
    "sg:address":"2306 Dayna Dr",
    "sg:city":"Atlanta",
    "sg:classifiers":[
        {
            "category":"Organizations",
            "subcategory":"Community Association",
            "type":"Services"
        }
    ],
    "sg:phone":"+1 404 454 3836",
    "sg:postcode":"30349",
    "sg:province":"GA",
    "sg:tags":[
        "club"
    ],
    "wof:name":"Curvy Nation, LLC",
    "wof:placetype":"venue"
},
  "geometry": {"coordinates":[-84.41739200000001,33.587841],"type":"Point"}
}