{
  "type": "Feature",
  "properties": {
    "iso:country":"US",
    "sg:address":"5954 Coca Cola Blvd",
    "sg:city":"Columbus",
    "sg:classifiers":[
        {
            "category":"Shopping",
            "subcategory":"Bicycles & Sporting Goods",
            "type":"Retail Goods"
        }
    ],
    "sg:phone":"+1 706 563 6654",
    "sg:postcode":"31909",
    "sg:province":"GA",
    "sg:tags":[
        "equipment",
        "golf",
        "supply"
    ],
    "wof:name":"S E Golf",
    "wof:placetype":"venue"
},
  "geometry": {"coordinates":[-84.88707700000001,32.52956],"type":"Point"}
}