{
  "type": "Feature",
  "properties": {
    "iso:country":"US",
    "sg:address":"2999 Cedar Mill Xing",
    "sg:city":"Acworth",
    "sg:classifiers":[
        {
            "category":"Professional",
            "type":"Services"
        }
    ],
    "sg:phone":"+1 770 975 7363",
    "sg:postcode":"30102",
    "sg:province":"GA",
    "wof:name":"Drainman Inc",
    "wof:placetype":"venue"
},
  "geometry": {"coordinates":[-84.63502200000001,34.115519],"type":"Point"}
}