{
  "type": "Feature",
  "properties": {
    "iso:country":"US",
    "sg:address":"145 Knox Shopping Center",
    "sg:city":"Thomson",
    "sg:classifiers":[
        {
            "category":"Banks & Credit Unions",
            "subcategory":"Bank",
            "type":"Services"
        }
    ],
    "sg:phone":"+1 706 595 4755",
    "sg:postcode":"30824",
    "sg:province":"GA",
    "sg:tags":[
        "personal",
        "institution"
    ],
    "wof:name":"World Finance",
    "wof:placetype":"venue"
},
  "geometry": {"coordinates":[-82.50216899999999,33.467391],"type":"Point"}
}