{
  "type": "Feature",
  "properties": {
    "iso:country":"US",
    "sg:address":"708 Francis St",
    "sg:city":"Waycross",
    "sg:classifiers":[
        {
            "category":"Retail",
            "subcategory":"Auto Repair",
            "type":"Services"
        }
    ],
    "sg:phone":"+1 912 283 7473",
    "sg:postcode":"31503",
    "sg:province":"GA",
    "sg:tags":[
        "automobile",
        "part",
        "brake",
        "supply"
    ],
    "wof:name":"Finn Brothers Brake Service",
    "wof:placetype":"venue"
},
  "geometry": {"coordinates":[-82.362156,31.207865],"type":"Point"}
}