{
  "type": "Feature",
  "properties": {
    "addr:full":"214 W King St Dalton GA 30720",
    "addr:housenumber":"214",
    "addr:postcode":"30720",
    "addr:street":"W King St",
    "iso:country":"US",
    "sg:address":"214 W King St",
    "sg:city":"Dalton",
    "sg:classifiers":[
        {
            "category":"Government",
            "subcategory":"Court House",
            "type":"Public Place"
        }
    ],
    "sg:phone":"+1 706 278 5897",
    "sg:postcode":"30720",
    "sg:province":"GA",
    "sg:tags":[
        "county"
    ],
    "wof:name":"Whitfield Cnty Superior Court",
    "wof:placetype":"venue"
},
  "geometry": {"coordinates":[-84.970709,34.772418],"type":"Point"}
}