{
  "type": "Feature",
  "properties": {
    "iso:country":"US",
    "sg:address":"863 Lackey Dr",
    "sg:city":"Macon",
    "sg:classifiers":[
        {
            "category":"Place Of Worship",
            "subcategory":"Church",
            "type":"Public Place"
        },
        {
            "category":"Place Of Worship",
            "type":"Public Place"
        }
    ],
    "sg:phone":"+1 478 781 6547",
    "sg:postcode":"31206",
    "sg:province":"GA",
    "sg:tags":[
        "churches-interdenominational",
        "churches-various",
        "denomination"
    ],
    "wof:name":"Outreach Revival Center Church",
    "wof:placetype":"venue"
},
  "geometry": {"coordinates":[-83.65205899999999,32.806163],"type":"Point"}
}