{
  "type": "Feature",
  "properties": {
    "addr:full":"445 Glencastle Dr NW Atlanta GA 30327",
    "addr:housenumber":"445",
    "addr:postcode":"30327",
    "addr:street":"Glencastle Dr Nw",
    "iso:country":"US",
    "sg:address":"445 Glencastle Dr NW",
    "sg:city":"Atlanta",
    "sg:classifiers":[
        {
            "category":"Shopping",
            "subcategory":"Bicycles & Sporting Goods",
            "type":"Retail Goods"
        }
    ],
    "sg:phone":"+1 404 847 0971",
    "sg:postcode":"30327",
    "sg:province":"GA",
    "wof:name":"Direct Kick Inc",
    "wof:placetype":"venue"
},
  "geometry": {"coordinates":[-84.398527,33.901151],"type":"Point"}
}