{
  "type": "Feature",
  "properties": {
    "iso:country":"US",
    "sg:address":"6858 Old Jefferson Hwy",
    "sg:city":"Woodbine",
    "sg:classifiers":[
        {
            "category":"Shopping",
            "type":"Retail Goods"
        }
    ],
    "sg:phone":"+1 912 882 8602",
    "sg:postcode":"31569",
    "sg:province":"GA",
    "sg:tags":[
        "art",
        "gallery",
        "dealer"
    ],
    "wof:name":"Watercolors By Mary O",
    "wof:placetype":"venue"
},
  "geometry": {"coordinates":[-81.790487,30.967761],"type":"Point"}
}