{
  "type": "Feature",
  "properties": {
    "iso:country":"US",
    "sg:address":"1304 Glenn Ave",
    "sg:city":"Augusta",
    "sg:classifiers":[
        {
            "category":"Freight",
            "type":"Transportation"
        }
    ],
    "sg:phone":"+1 706 738 4135",
    "sg:postcode":"30904",
    "sg:province":"GA",
    "sg:tags":[
        "broker"
    ],
    "wof:name":"Unishippers",
    "wof:placetype":"venue"
},
  "geometry": {"coordinates":[-82.029445,33.472652],"type":"Point"}
}