{
  "type": "Feature",
  "properties": {
    "iso:country":"US",
    "sg:address":"124 Collier Rd",
    "sg:city":"Jackson",
    "sg:classifiers":[
        {
            "category":"Organizations",
            "subcategory":"Religious Organization",
            "type":"Services"
        }
    ],
    "sg:phone":"+1 770 775 1600",
    "sg:postcode":"30233",
    "sg:province":"GA",
    "sg:tags":[
        "church"
    ],
    "wof:name":"South River Baptist Church",
    "wof:placetype":"venue"
},
  "geometry": {"coordinates":[-83.90908899999999,33.376233],"type":"Point"}
}