{
  "type": "Feature",
  "properties": {
    "addr:full":"1872 Forge St Tucker GA 30084",
    "addr:housenumber":"1872",
    "addr:postcode":"30084",
    "addr:street":"Forge St",
    "iso:country":"US",
    "sg:address":"1872 Forge St",
    "sg:city":"Tucker",
    "sg:classifiers":[
        {
            "category":"Building & Trades",
            "subcategory":"Locksmith",
            "type":"Services"
        }
    ],
    "sg:phone":"+1 678 369 5591",
    "sg:postcode":"30084",
    "sg:province":"GA",
    "sg:tags":[
        "key"
    ],
    "wof:name":"All Day Emergency Locksmith",
    "wof:placetype":"venue"
},
  "geometry": {"coordinates":[-84.198812,33.839148],"type":"Point"}
}