{
  "type": "Feature",
  "properties": {
    "addr:full":"3482 Flat Shoals Rd Decatur GA 30034",
    "addr:housenumber":"3482",
    "addr:postcode":"30034",
    "addr:street":"Flat Shoals Rd",
    "iso:country":"US",
    "sg:address":"3482 Flat Shoals Rd",
    "sg:city":"Decatur",
    "sg:classifiers":[
        {
            "category":"Social Services",
            "type":"Services"
        },
        {
            "category":"Social Services",
            "subcategory":"Child Care",
            "type":"Services"
        },
        {
            "category":"Exhibition Hall",
            "type":"Public Place"
        }
    ],
    "sg:phone":"+1 404 243 9662",
    "sg:postcode":"30034",
    "sg:province":"GA",
    "sg:tags":[
        "ballroom",
        "services-information",
        "program",
        "referral",
        "halls",
        "auditorium"
    ],
    "wof:name":"Ymca",
    "wof:placetype":"venue"
},
  "geometry": {"coordinates":[-84.27287099999999,33.705014],"type":"Point"}
}