{
  "type": "Feature",
  "properties": {
    "addr:full":"2885 Mount Vernon Rd Lithia Springs GA 30122",
    "addr:housenumber":"2885",
    "addr:postcode":"30122",
    "addr:street":"Mount Vernon Rd",
    "iso:country":"US",
    "sg:address":"2885 Mount Vernon Rd",
    "sg:city":"Lithia Springs",
    "sg:classifiers":[
        {
            "category":"Professional",
            "subcategory":"Business Services",
            "type":"Services"
        },
        {
            "category":"Building & Trades",
            "subcategory":"Construction",
            "type":"Services"
        }
    ],
    "sg:phone":"+1 770 949 6940",
    "sg:postcode":"30122",
    "sg:province":"GA",
    "sg:tags":[
        "general",
        "contractor"
    ],
    "wof:name":"Southern Construction Notice S",
    "wof:placetype":"venue"
},
  "geometry": {"coordinates":[-84.660686,33.726221],"type":"Point"}
}