{
  "type": "Feature",
  "properties": {
    "iso:country":"US",
    "sg:address":"2038 State Rte 270 E",
    "sg:city":"Doerun",
    "sg:classifiers":[
        {
            "category":"Real Estate",
            "subcategory":"Real Estate Operator",
            "type":"Services"
        }
    ],
    "sg:phone":"+1 229 782 5728",
    "sg:postcode":"31744",
    "sg:province":"GA",
    "sg:tags":[
        "property",
        "lessor"
    ],
    "wof:name":"Agnes C Childree",
    "wof:placetype":"venue"
},
  "geometry": {"coordinates":[-83.90161000000001,31.321198],"type":"Point"}
}