{
  "type": "Feature",
  "properties": {
    "iso:country":"US",
    "sg:address":"255 Settlement Ln",
    "sg:city":"Alpharetta",
    "sg:classifiers":[
        {
            "category":"Farming",
            "subcategory":"Farm",
            "type":"Manufacturing & Wholesale Goods"
        }
    ],
    "sg:phone":"+1 770 889 1037",
    "sg:postcode":"30004",
    "sg:province":"GA",
    "sg:tags":[
        "crop",
        "general"
    ],
    "wof:name":"Hillbright Farm Inc",
    "wof:placetype":"venue"
},
  "geometry": {"coordinates":[-84.282129,34.189164],"type":"Point"}
}