{
  "type": "Feature",
  "properties": {
    "addr:full":"3435 Alexander Pl Smyrna GA 30082",
    "addr:housenumber":"3435",
    "addr:postcode":"30082",
    "addr:street":"Alexander Pl",
    "iso:country":"US",
    "sg:address":"3435 Alexander Pl",
    "sg:city":"Smyrna",
    "sg:classifiers":[
        {
            "category":"Shopping",
            "subcategory":"Clothing, Apparel, & Fashions",
            "type":"Retail Goods"
        }
    ],
    "sg:phone":"+1 678 305 9714",
    "sg:postcode":"30082",
    "sg:province":"GA",
    "wof:name":"Nealwear Sports",
    "wof:placetype":"venue"
},
  "geometry": {"coordinates":[-84.563717,33.871143],"type":"Point"}
}