{
  "type": "Feature",
  "properties": {
    "iso:country":"US",
    "sg:address":"110 Viola Dr",
    "sg:city":"Dallas",
    "sg:classifiers":[
        {
            "category":"Professional",
            "subcategory":"Business Services",
            "type":"Services"
        }
    ],
    "sg:phone":"+1 678 363 3337",
    "sg:postcode":"30157",
    "sg:province":"GA",
    "wof:name":"Kerlin Enterprises Inc",
    "wof:placetype":"venue"
},
  "geometry": {"coordinates":[-84.740144,33.96152],"type":"Point"}
}