{
  "type": "Feature",
  "properties": {
    "addr:full":"6649 Roswell Rd Atlanta GA 30328",
    "addr:housenumber":"6649",
    "addr:postcode":"30328",
    "addr:street":"Roswell Rd",
    "iso:country":"US",
    "sg:address":"6649 Roswell Rd",
    "sg:city":"Atlanta",
    "sg:classifiers":[
        {
            "category":"Shopping",
            "type":"Retail Goods"
        }
    ],
    "sg:phone":"+1 404 943 9155",
    "sg:postcode":"30328",
    "sg:province":"GA",
    "sg:tags":[
        "pet",
        "food",
        "supply"
    ],
    "wof:name":"Red Bandanna Pet Food",
    "wof:placetype":"venue"
},
  "geometry": {"coordinates":[-84.378604,33.936458],"type":"Point"}
}