{
  "type": "Feature",
  "properties": {
    "addr:full":"3054 Hudson Woods Ct Decatur GA 30033",
    "addr:housenumber":"3054",
    "addr:postcode":"30033",
    "addr:street":"Hudson Woods Ct",
    "iso:country":"US",
    "sg:address":"3054 Hudson Woods Ct",
    "sg:city":"Decatur",
    "sg:classifiers":[
        {
            "category":"Shopping",
            "subcategory":"Musical Instruments",
            "type":"Retail Goods"
        }
    ],
    "sg:phone":"+1 770 939 8093",
    "sg:postcode":"30033",
    "sg:province":"GA",
    "sg:tags":[
        "repair",
        "local",
        "teacher",
        "trucking"
    ],
    "wof:name":"Master Piano Rebuilders",
    "wof:placetype":"venue"
},
  "geometry": {"coordinates":[-84.26309999999999,33.8339],"type":"Point"}
}