{
  "type": "Feature",
  "properties": {
    "addr:full":"3119 Furber Ave Savannah GA 31404",
    "addr:housenumber":"3119",
    "addr:postcode":"31404",
    "addr:street":"Furber Ave",
    "iso:country":"US",
    "sg:address":"3119 Furber Ave",
    "sg:city":"Savannah",
    "sg:classifiers":[
        {
            "category":"Arts & Performance",
            "subcategory":"Theater",
            "type":"Entertainment"
        }
    ],
    "sg:phone":"+1 912 355 3366",
    "sg:postcode":"31404",
    "sg:province":"GA",
    "sg:tags":[
        "entertainer",
        "theatrical",
        "product",
        "mfg"
    ],
    "wof:name":"Puppet People",
    "wof:placetype":"venue"
},
  "geometry": {"coordinates":[-81.052796,32.035676],"type":"Point"}
}