{
  "type": "Feature",
  "properties": {
    "addr:full":"455 Newport Hts Alpharetta GA 30005",
    "addr:housenumber":"455",
    "addr:postcode":"30005",
    "addr:street":"Newport Hts",
    "iso:country":"US",
    "sg:address":"455 Newport Hts",
    "sg:city":"Alpharetta",
    "sg:classifiers":[
        {
            "category":"Professional",
            "subcategory":"Business Services",
            "type":"Services"
        }
    ],
    "sg:phone":"+1 770 752 7394",
    "sg:postcode":"30005",
    "sg:province":"GA",
    "wof:name":"Donovan Assoc Consulting Svcs",
    "wof:placetype":"venue"
},
  "geometry": {"coordinates":[-84.21020799999999,34.081853],"type":"Point"}
}