{
  "type": "Feature",
  "properties": {
    "addr:full":"367 Highland Ave Augusta GA 30904",
    "addr:housenumber":"367",
    "addr:postcode":"30904",
    "addr:street":"Highland Ave",
    "iso:country":"US",
    "sg:address":"367 Highland Ave",
    "sg:city":"Augusta",
    "sg:classifiers":[
        {
            "category":"Professional",
            "subcategory":"Business Services",
            "type":"Services"
        }
    ],
    "sg:phone":"+1 706 736 0722",
    "sg:postcode":"30904",
    "sg:province":"GA",
    "sg:tags":[
        "interior",
        "consultant",
        "design",
        "decorator"
    ],
    "wof:name":"Villa",
    "wof:placetype":"venue"
},
  "geometry": {"coordinates":[-82.03006499999999,33.484562],"type":"Point"}
}