{
  "type": "Feature",
  "properties": {
    "addr:full":"3901 Roswell Rd Marietta GA 30062",
    "addr:housenumber":"3901",
    "addr:postcode":"30062",
    "addr:street":"Roswell Rd",
    "iso:country":"US",
    "sg:address":"3901 Roswell Rd",
    "sg:city":"Marietta",
    "sg:classifiers":[
        {
            "category":"Real Estate",
            "subcategory":"Real Estate Agent",
            "type":"Services"
        }
    ],
    "sg:phone":"+1 770 973 2705",
    "sg:postcode":"30062",
    "sg:province":"GA",
    "wof:name":"Will Gurley Realtors",
    "wof:placetype":"venue"
},
  "geometry": {"coordinates":[-84.437867,33.978017],"type":"Point"}
}