{
  "type": "Feature",
  "properties": {
    "iso:country":"US",
    "sg:address":"1500 T St",
    "sg:city":"Brunswick",
    "sg:classifiers":[
        {
            "category":"Manufacturing",
            "subcategory":"Metals",
            "type":"Manufacturing & Wholesale Goods"
        }
    ],
    "sg:phone":"+1 912 265 6551",
    "sg:postcode":"31520",
    "sg:province":"GA",
    "sg:tags":[
        "plumbing",
        "fixture",
        "supply"
    ],
    "wof:name":"Home Depot Supply",
    "wof:placetype":"venue"
},
  "geometry": {"coordinates":[-81.49517,31.170994],"type":"Point"}
}