{
  "type": "Feature",
  "properties": {
    "iso:country":"US",
    "sg:address":"3900 State Rte 53",
    "sg:city":"Hoschton",
    "sg:classifiers":[
        {
            "category":"Building & Trades",
            "subcategory":"Construction",
            "type":"Services"
        }
    ],
    "sg:phone":"+1 706 654 2575",
    "sg:postcode":"30548",
    "sg:province":"GA",
    "sg:tags":[
        "grading",
        "contractor"
    ],
    "wof:name":"Johnson Brothers Grading Inc",
    "wof:placetype":"venue"
},
  "geometry": {"coordinates":[-83.759259,34.091671],"type":"Point"}
}