{
  "type": "Feature",
  "properties": {
    "iso:country":"US",
    "sg:address":"2079 Watson Blvd",
    "sg:city":"Warner Robins",
    "sg:classifiers":[
        {
            "category":"Travel",
            "subcategory":"Hotels & Motels",
            "type":"Entertainment"
        }
    ],
    "sg:phone":"+1 478 929 9526",
    "sg:postcode":"31093",
    "sg:province":"GA",
    "wof:name":"Admiral Benbow Inn",
    "wof:placetype":"venue"
},
  "geometry": {"coordinates":[-83.6567,32.618198],"type":"Point"}
}