{
  "type": "Feature",
  "properties": {
    "addr:full":"341 Kelly St SE Atlanta GA 30312",
    "addr:housenumber":"341",
    "addr:postcode":"30312",
    "addr:street":"Kelly St Se",
    "iso:country":"US",
    "sg:address":"341 Kelly St SE",
    "sg:city":"Atlanta",
    "sg:classifiers":[
        {
            "category":"Organizations",
            "subcategory":"Membership Organization",
            "type":"Services"
        }
    ],
    "sg:phone":"+1 404 853 2840",
    "sg:postcode":"30312",
    "sg:province":"GA",
    "wof:name":"Familys First",
    "wof:placetype":"venue"
},
  "geometry": {"coordinates":[-84.380526,33.746772],"type":"Point"}
}