{
  "type": "Feature",
  "properties": {
    "addr:full":"36 Indian Trl SE Cartersville GA 30120",
    "addr:housenumber":"36",
    "addr:postcode":"30120",
    "addr:street":"Indian Trl Se",
    "iso:country":"US",
    "sg:address":"36 Indian Trl SE",
    "sg:city":"Cartersville",
    "sg:classifiers":[
        {
            "category":"Real Estate",
            "subcategory":"Real Estate Agent",
            "type":"Services"
        }
    ],
    "sg:phone":"+1 770 382 7005",
    "sg:postcode":"30120",
    "sg:province":"GA",
    "sg:tags":[
        "inspection"
    ],
    "wof:name":"Professional Home Inspection",
    "wof:placetype":"venue"
},
  "geometry": {"coordinates":[-84.811689,34.141986],"type":"Point"}
}