{
  "type": "Feature",
  "properties": {
    "iso:country":"US",
    "sg:address":"1315 Verdon Dr",
    "sg:city":"Dunwoody",
    "sg:classifiers":[
        {
            "category":"Health Services",
            "subcategory":"Clinic",
            "type":"Services"
        }
    ],
    "sg:phone":"+1 770 671 1116",
    "sg:postcode":"30338",
    "sg:province":"GA",
    "sg:tags":[
        "organization",
        "medical",
        "surgical"
    ],
    "wof:name":"Cor Solutions Inc",
    "wof:placetype":"venue"
},
  "geometry": {"coordinates":[-84.33665499999999,33.958586],"type":"Point"}
}