{
  "type": "Feature",
  "properties": {
    "iso:country":"US",
    "sg:address":"600 S Central Ave",
    "sg:city":"Atlanta",
    "sg:classifiers":[
        {
            "category":"Professional",
            "subcategory":"Lawyer & Legal Services",
            "type":"Services"
        }
    ],
    "sg:phone":"+1 404 763 3401",
    "sg:postcode":"30354",
    "sg:province":"GA",
    "sg:tags":[
        "personal",
        "injury"
    ],
    "wof:name":"Eidson & Associates PC",
    "wof:placetype":"venue"
},
  "geometry": {"coordinates":[-84.40799699999999,33.658001],"type":"Point"}
}