{
  "type": "Feature",
  "properties": {
    "addr:full":"959 Light House Way Lawrenceville GA 30043",
    "addr:housenumber":"959",
    "addr:postcode":"30043",
    "addr:street":"Light House Way",
    "iso:country":"US",
    "sg:address":"959 Light House Way",
    "sg:city":"Lawrenceville",
    "sg:classifiers":[
        {
            "category":"Professional",
            "type":"Services"
        }
    ],
    "sg:phone":"+1 770 442 9857",
    "sg:postcode":"30043",
    "sg:province":"GA",
    "wof:name":"Global Link Intl",
    "wof:placetype":"venue"
},
  "geometry": {"coordinates":[-84.051216,33.99952],"type":"Point"}
}