{
  "type": "Feature",
  "properties": {
    "addr:full":"6624 Dawson Blvd Norcross GA 30093",
    "addr:housenumber":"6624",
    "addr:postcode":"30093",
    "addr:street":"Dawson Blvd",
    "iso:country":"US",
    "sg:address":"6624 Dawson Blvd",
    "sg:city":"Norcross",
    "sg:classifiers":[
        {
            "category":"Shopping",
            "subcategory":"Gifts & Souvenirs",
            "type":"Retail Goods"
        }
    ],
    "sg:phone":"+1 404 723 9066",
    "sg:postcode":"30093",
    "sg:province":"GA",
    "sg:tags":[
        "shop"
    ],
    "wof:name":"Mandarin Shop",
    "wof:placetype":"venue"
},
  "geometry": {"coordinates":[-84.223246,33.909529],"type":"Point"}
}