{
  "type": "Feature",
  "properties": {
    "addr:full":"5504 Montgomery St Savannah GA 31405",
    "addr:housenumber":"5504",
    "addr:postcode":"31405",
    "addr:street":"Montgomery St",
    "iso:country":"US",
    "sg:address":"5504 Montgomery St",
    "sg:city":"Savannah",
    "sg:classifiers":[
        {
            "category":"Manufacturing",
            "subcategory":"Printing",
            "type":"Manufacturing & Wholesale Goods"
        }
    ],
    "sg:phone":"+1 912 355 8270",
    "sg:postcode":"31405",
    "sg:province":"GA",
    "sg:tags":[
        "work"
    ],
    "wof:name":"Coastal Binding",
    "wof:placetype":"venue"
},
  "geometry": {"coordinates":[-81.119978,32.027596],"type":"Point"}
}