{
  "type": "Feature",
  "properties": {
    "iso:country":"US",
    "sg:address":"705 Dena Dr",
    "sg:city":"Canton",
    "sg:classifiers":[
        {
            "category":"Professional",
            "type":"Services"
        }
    ],
    "sg:phone":"+1 770 720 3283",
    "sg:postcode":"30114",
    "sg:province":"GA",
    "wof:name":"James Cole",
    "wof:placetype":"venue"
},
  "geometry": {"coordinates":[-84.51991,34.19003],"type":"Point"}
}