{
  "type": "Feature",
  "properties": {
    "iso:country":"US",
    "sg:address":"760 Winston Dr",
    "sg:city":"Lawrenceville",
    "sg:classifiers":[
        {
            "category":"Shopping",
            "subcategory":"Department Store",
            "type":"Retail Goods"
        }
    ],
    "sg:phone":"+1 770 972 6515",
    "sg:postcode":"30044",
    "sg:province":"GA",
    "wof:name":"Collier Beall",
    "wof:placetype":"venue"
},
  "geometry": {"coordinates":[-84.052802,33.898699],"type":"Point"}
}