{
  "type": "Feature",
  "properties": {
    "iso:country":"US",
    "sg:address":"118 Chastain Rd NW",
    "sg:city":"Kennesaw",
    "sg:classifiers":[
        {
            "category":"Building & Trades",
            "subcategory":"Locksmith",
            "type":"Services"
        }
    ],
    "sg:phone":"+1 770 308 1573",
    "sg:postcode":"30144",
    "sg:province":"GA",
    "sg:tags":[
        "key"
    ],
    "wof:name":"Any Emerg Locksmith 24 Hour",
    "wof:placetype":"venue"
},
  "geometry": {"coordinates":[-84.55336699999999,34.034969],"type":"Point"}
}