{
  "type": "Feature",
  "properties": {
    "addr:full":"387 Lauren Marie Dr Braselton GA 30517",
    "addr:housenumber":"387",
    "addr:postcode":"30517",
    "addr:street":"Lauren Marie Dr",
    "iso:country":"US",
    "sg:address":"387 Lauren Marie Dr",
    "sg:city":"Braselton",
    "sg:classifiers":[
        {
            "category":"Home & Garden",
            "subcategory":"Building Materials",
            "type":"Retail Goods"
        }
    ],
    "sg:phone":"+1 706 654 5686",
    "sg:postcode":"30517",
    "sg:province":"GA",
    "sg:tags":[
        "downspouts",
        "gutter"
    ],
    "wof:name":"Dts Contracting Inc",
    "wof:placetype":"venue"
},
  "geometry": {"coordinates":[-83.7741,34.150305],"type":"Point"}
}