{
  "type": "Feature",
  "properties": {
    "iso:country":"US",
    "sg:address":"379 Player's Cir",
    "sg:city":"Fayetteville",
    "sg:classifiers":[
        {
            "category":"Travel",
            "subcategory":"Travel Agent",
            "type":"Entertainment"
        }
    ],
    "sg:phone":"+1 678 817 1323",
    "sg:postcode":"30215",
    "sg:province":"GA",
    "sg:tags":[
        "agency",
        "bureau"
    ],
    "wof:name":"Satellite Travel Agency & Tour",
    "wof:placetype":"venue"
},
  "geometry": {"coordinates":[-84.392354,33.42967],"type":"Point"}
}