{
  "type": "Feature",
  "properties": {
    "iso:country":"US",
    "sg:address":"150 Roberson Ln",
    "sg:city":"Milledgeville",
    "sg:classifiers":[
        {
            "category":"Professional",
            "subcategory":"Business Services",
            "type":"Services"
        },
        {
            "category":"Restaurant",
            "type":"Food & Drink"
        }
    ],
    "sg:phone":"+1 478 453 8300",
    "sg:postcode":"31027",
    "sg:province":"GA",
    "sg:tags":[
        "eating"
    ],
    "wof:name":"Progressive Restaurant Concept",
    "wof:placetype":"venue"
},
  "geometry": {"coordinates":[-82.873465,32.553982],"type":"Point"}
}