{
  "type": "Feature",
  "properties": {
    "addr:full":"1207 W Medical Park Rd Augusta GA 30909",
    "addr:housenumber":"1207",
    "addr:postcode":"30909",
    "addr:street":"W Medical Park Rd",
    "iso:country":"US",
    "sg:address":"1207 W Medical Park Rd",
    "sg:city":"Augusta",
    "sg:classifiers":[
        {
            "category":"Health Services",
            "subcategory":"Doctor",
            "type":"Services"
        }
    ],
    "sg:phone":"+1 706 854 1511",
    "sg:postcode":"30909",
    "sg:province":"GA",
    "sg:tags":[
        "medical"
    ],
    "wof:name":"General Vsclr Srgry Assocs",
    "wof:placetype":"venue"
},
  "geometry": {"coordinates":[-82.08961600000001,33.482138],"type":"Point"}
}