{
  "type": "Feature",
  "properties": {
    "iso:country":"US",
    "sg:address":"475 Dawsonville Hwy",
    "sg:city":"Gainesville",
    "sg:classifiers":[
        {
            "category":"Insurance",
            "subcategory":"Insurance Agent",
            "type":"Services"
        }
    ],
    "sg:phone":"+1 770 535 1277",
    "sg:postcode":"30501",
    "sg:province":"GA",
    "wof:name":"State Farm Insurance",
    "wof:placetype":"venue"
},
  "geometry": {"coordinates":[-83.845631,34.296694],"type":"Point"}
}