{
  "type": "Feature",
  "properties": {
    "iso:country":"US",
    "sg:address":"50 Ernest W Barrett Pkwy",
    "sg:city":"Marietta",
    "sg:classifiers":[
        {
            "category":"Personal",
            "subcategory":"Tanning Parlor",
            "type":"Services"
        }
    ],
    "sg:phone":"+1 770 218 2121",
    "sg:postcode":"30066",
    "sg:province":"GA",
    "sg:tags":[
        "salon"
    ],
    "wof:name":"Hollywood Tans",
    "wof:placetype":"venue"
},
  "geometry": {"coordinates":[-84.550966,34.014085],"type":"Point"}
}