{
  "type": "Feature",
  "properties": {
    "iso:country":"US",
    "sg:address":"26 Aldanat Dr",
    "sg:city":"Edgefield",
    "sg:classifiers":[
        {
            "category":"Home & Garden",
            "subcategory":"Building Materials",
            "type":"Retail Goods"
        }
    ],
    "sg:phone":"+1 803 637 5300",
    "sg:postcode":"29824",
    "sg:province":"SC",
    "wof:name":"Contractors Choice",
    "wof:placetype":"venue"
},
  "geometry": {"coordinates":[-82.059847,33.731054],"type":"Point"}
}