{
  "type": "Feature",
  "properties": {
    "iso:country":"US",
    "sg:address":"1054 Avery Creek Dr",
    "sg:city":"Woodstock",
    "sg:classifiers":[
        {
            "category":"Food & Beverages",
            "subcategory":"Liquor & Beverages",
            "type":"Retail Goods"
        }
    ],
    "sg:phone":"+1 770 517 6277",
    "sg:postcode":"30188",
    "sg:province":"GA",
    "sg:tags":[
        "alcoholic"
    ],
    "wof:name":"Obrien Package Service Inc",
    "wof:placetype":"venue"
},
  "geometry": {"coordinates":[-84.44959,34.151558],"type":"Point"}
}