{
  "type": "Feature",
  "properties": {
    "iso:country":"US",
    "sg:address":"1033 Franklin Rd SE Ste D",
    "sg:city":"Marietta",
    "sg:classifiers":[
        {
            "category":"Restaurant",
            "type":"Food & Drink"
        }
    ],
    "sg:phone":"+1 770 984 0021",
    "sg:postcode":"30067",
    "sg:province":"GA",
    "wof:name":"Jamaican",
    "wof:placetype":"venue"
},
  "geometry": {"coordinates":[-84.494202,33.928699],"type":"Point"}
}