{
  "type": "Feature",
  "properties": {
    "addr:full":"180 Allen Rd NE Atlanta GA 30328",
    "addr:housenumber":"180",
    "addr:postcode":"30328",
    "addr:street":"Allen Rd Ne",
    "iso:country":"US",
    "sg:address":"180 Allen Rd NE",
    "sg:city":"Atlanta",
    "sg:classifiers":[
        {
            "category":"Professional",
            "subcategory":"Computer Services",
            "type":"Services"
        }
    ],
    "sg:phone":"+1 404 303 9540",
    "sg:postcode":"30328",
    "sg:province":"GA",
    "sg:tags":[
        "processing",
        "datum"
    ],
    "wof:name":"Southern Information Systems",
    "wof:placetype":"venue"
},
  "geometry": {"coordinates":[-84.38108099999999,33.9135],"type":"Point"}
}