{
  "type": "Feature",
  "properties": {
    "addr:full":"930 Marietta Hwy Canton GA 30114",
    "addr:housenumber":"930",
    "addr:postcode":"30114",
    "addr:street":"Marietta Hwy",
    "iso:country":"US",
    "sg:address":"930 Marietta Hwy",
    "sg:city":"Canton",
    "sg:classifiers":[
        {
            "category":"Education",
            "subcategory":"School",
            "type":"Public Place"
        }
    ],
    "sg:phone":"+1 770 479 8745",
    "sg:postcode":"30114",
    "sg:province":"GA",
    "wof:name":"Turkey Highschool",
    "wof:placetype":"venue"
},
  "geometry": {"coordinates":[-84.500005,34.234373],"type":"Point"}
}