{
  "type": "Feature",
  "properties": {
    "addr:full":"54 Clubhouse Dr Midway GA 31320",
    "addr:housenumber":"54",
    "addr:postcode":"31320",
    "addr:street":"Clubhouse Dr",
    "iso:country":"US",
    "sg:address":"54 Clubhouse Dr",
    "sg:city":"Midway",
    "sg:classifiers":[
        {
            "category":"Real Estate",
            "subcategory":"Real Estate Agent",
            "type":"Services"
        }
    ],
    "sg:phone":"+1 770 271 4414",
    "sg:postcode":"31320",
    "sg:province":"GA",
    "wof:name":"American Classic Realty",
    "wof:placetype":"venue"
},
  "geometry": {"coordinates":[-81.394648,31.833286],"type":"Point"}
}