{
  "type": "Feature",
  "properties": {
    "addr:full":"222 Decatur Rd Mcdonough GA 30253",
    "addr:housenumber":"222",
    "addr:postcode":"30253",
    "addr:street":"Decatur Rd",
    "iso:country":"US",
    "sg:address":"222 Decatur Rd",
    "sg:city":"Mcdonough",
    "sg:classifiers":[
        {
            "category":"Building & Trades",
            "subcategory":"Construction",
            "type":"Services"
        }
    ],
    "sg:phone":"+1 770 914 9039",
    "sg:postcode":"30253",
    "sg:province":"GA",
    "sg:tags":[
        "general",
        "contractor"
    ],
    "wof:name":"Sun Sites Inc",
    "wof:placetype":"venue"
},
  "geometry": {"coordinates":[-84.14146700000001,33.455292],"type":"Point"}
}