{
  "type": "Feature",
  "properties": {
    "iso:country":"US",
    "sg:address":"1205 Johnson Ferry Rd",
    "sg:city":"Marietta",
    "sg:classifiers":[
        {
            "category":"Personal",
            "type":"Services"
        }
    ],
    "sg:phone":"+1 770 973 5156",
    "sg:postcode":"30068",
    "sg:province":"GA",
    "sg:tags":[
        "sewing",
        "alteration"
    ],
    "wof:name":"Alterations by Lee Inc",
    "wof:placetype":"venue"
},
  "geometry": {"coordinates":[-84.42150100000001,33.979301],"type":"Point"}
}