{
  "type": "Feature",
  "properties": {
    "iso:country":"US",
    "sg:address":"3857 Dundee Dr NE",
    "sg:city":"Roswell",
    "sg:classifiers":[
        {
            "category":"Wholesale",
            "subcategory":"Machinery & Supplies",
            "type":"Manufacturing & Wholesale Goods"
        }
    ],
    "sg:phone":"+1 770 518 3302",
    "sg:postcode":"30075",
    "sg:province":"GA",
    "sg:tags":[
        "mill",
        "paper"
    ],
    "wof:name":"Monadnock Paper Mill",
    "wof:placetype":"venue"
},
  "geometry": {"coordinates":[-84.43113200000001,34.043089],"type":"Point"}
}