{
  "type": "Feature",
  "properties": {
    "addr:full":"365 Westminster Way Dallas GA 30132",
    "addr:housenumber":"365",
    "addr:postcode":"30132",
    "addr:street":"Westminster Way",
    "iso:country":"US",
    "sg:address":"365 Westminster Way",
    "sg:city":"Dallas",
    "sg:classifiers":[
        {
            "category":"Professional",
            "type":"Services"
        }
    ],
    "sg:phone":"+1 770 445 7524",
    "sg:postcode":"30132",
    "sg:province":"GA",
    "wof:name":"Jay M Waldrep",
    "wof:placetype":"venue"
},
  "geometry": {"coordinates":[-84.843216,33.936971],"type":"Point"}
}