{
  "type": "Feature",
  "properties": {
    "addr:full":"214 Eastin Rd Fayetteville GA 30214",
    "addr:housenumber":"214",
    "addr:postcode":"30214",
    "addr:street":"Eastin Rd",
    "iso:country":"US",
    "sg:address":"214 Eastin Rd",
    "sg:city":"Fayetteville",
    "sg:classifiers":[
        {
            "category":"Banks & Credit Unions",
            "subcategory":"Financial Services",
            "type":"Services"
        }
    ],
    "sg:phone":"+1 770 460 6429",
    "sg:postcode":"30214",
    "sg:province":"GA",
    "sg:tags":[
        "investor"
    ],
    "wof:name":"B J Investments Inc",
    "wof:placetype":"venue"
},
  "geometry": {"coordinates":[-84.50504100000001,33.488392],"type":"Point"}
}