{
  "type": "Feature",
  "properties": {
    "iso:country":"US",
    "sg:address":"50 Glenlake Pkwy NE",
    "sg:city":"Atlanta",
    "sg:classifiers":[
        {
            "category":"Utilities",
            "subcategory":"Telephone",
            "type":"Services"
        }
    ],
    "sg:phone":"+1 404 350 7300",
    "sg:postcode":"30328",
    "sg:province":"GA",
    "sg:tags":[
        "company"
    ],
    "wof:name":"ICG Netcom",
    "wof:placetype":"venue"
},
  "geometry": {"coordinates":[-84.36153400000001,33.934611],"type":"Point"}
}