{
  "type": "Feature",
  "properties": {
    "addr:full":"1210 Lake Valley Rd Macon GA 31210",
    "addr:housenumber":"1210",
    "addr:postcode":"31210",
    "addr:street":"Lake Valley Rd",
    "iso:country":"US",
    "sg:address":"1210 Lake Valley Rd",
    "sg:city":"Macon",
    "sg:classifiers":[
        {
            "category":"Professional",
            "type":"Services"
        }
    ],
    "sg:phone":"+1 478 477 5082",
    "sg:postcode":"31210",
    "sg:province":"GA",
    "sg:tags":[
        "contractor",
        "mechanical"
    ],
    "wof:name":"Rapid Onsite Service Inc",
    "wof:placetype":"venue"
},
  "geometry": {"coordinates":[-83.70205900000001,32.888561],"type":"Point"}
}