{
  "type": "Feature",
  "properties": {
    "iso:country":"US",
    "sg:address":"1086 Valley View Rd SE",
    "sg:city":"Atlanta",
    "sg:classifiers":[
        {
            "category":"Social Services",
            "subcategory":"Child Care",
            "type":"Services"
        }
    ],
    "sg:phone":"+1 404 627 4818",
    "sg:postcode":"30315",
    "sg:province":"GA",
    "wof:name":"As We Grow In Home Daycare",
    "wof:placetype":"venue"
},
  "geometry": {"coordinates":[-84.35460999999999,33.69094],"type":"Point"}
}