{
  "type": "Feature",
  "properties": {
    "addr:full":"1631 Autumn Blvd NE Conyers GA 30012",
    "addr:housenumber":"1631",
    "addr:postcode":"30012",
    "addr:street":"Autumn Blvd Ne",
    "iso:country":"US",
    "sg:address":"1631 Autumn Blvd NE",
    "sg:city":"Conyers",
    "sg:classifiers":[
        {
            "category":"Shopping",
            "subcategory":"Pharmacy",
            "type":"Retail Goods"
        }
    ],
    "sg:phone":"+1 678 750 0473",
    "sg:postcode":"30012",
    "sg:province":"GA",
    "sg:tags":[
        "drugstore"
    ],
    "wof:name":"Reagan Home Care Pharmacy",
    "wof:placetype":"venue"
},
  "geometry": {"coordinates":[-83.985321,33.672187],"type":"Point"}
}