{
  "type": "Feature",
  "properties": {
    "iso:country":"US",
    "sg:address":"5450 Chamblee Dunwoody Road",
    "sg:city":"Atlanta",
    "sg:classifiers":[
        {
            "category":"Retail",
            "subcategory":"Veterinary Services",
            "type":"Services"
        }
    ],
    "sg:phone":"+1 770 394 4030",
    "sg:postcode":"30338",
    "sg:province":"GA",
    "sg:tags":[
        "veterinarian"
    ],
    "sg:website":"www.dunwoodyanimal.com",
    "wof:name":"Dunwoody Animal Hospital PC",
    "wof:placetype":"venue"
},
  "geometry": {"coordinates":[-84.33459000000001,33.946642],"type":"Point"}
}