{
  "type": "Feature",
  "properties": {
    "iso:country":"US",
    "sg:address":"3100 River Exchange Dr",
    "sg:city":"Norcross",
    "sg:classifiers":[
        {
            "category":"Building & Trades",
            "subcategory":"Construction",
            "type":"Services"
        }
    ],
    "sg:phone":"+1 770 248 0848",
    "sg:postcode":"30092",
    "sg:province":"GA",
    "sg:tags":[
        "contractor"
    ],
    "wof:name":"Amrescon Construction Inc",
    "wof:placetype":"venue"
},
  "geometry": {"coordinates":[-84.26085399999999,33.970697],"type":"Point"}
}