{
  "type": "Feature",
  "properties": {
    "addr:full":"7943 Union Grove Rd Lithonia GA 30058",
    "addr:housenumber":"7943",
    "addr:postcode":"30058",
    "addr:street":"Union Grove Rd",
    "iso:country":"US",
    "sg:address":"7943 Union Grove Rd",
    "sg:city":"Lithonia",
    "sg:classifiers":[
        {
            "category":"Real Estate",
            "subcategory":"Real Estate Agent",
            "type":"Services"
        }
    ],
    "sg:phone":"+1 770 482 7922",
    "sg:postcode":"30058",
    "sg:province":"GA",
    "wof:name":"Chupp Construction Co Inc",
    "wof:placetype":"venue"
},
  "geometry": {"coordinates":[-84.075507,33.721867],"type":"Point"}
}