{
  "type": "Feature",
  "properties": {
    "addr:full":"212 W Madison St Dublin GA 31021",
    "addr:housenumber":"212",
    "addr:postcode":"31021",
    "addr:street":"W Madison St",
    "iso:country":"US",
    "sg:address":"212 W Madison St",
    "sg:city":"Dublin",
    "sg:classifiers":[
        {
            "category":"Utilities",
            "subcategory":"Telephone",
            "type":"Services"
        }
    ],
    "sg:phone":"+1 478 275 1592",
    "sg:postcode":"31021",
    "sg:province":"GA",
    "sg:tags":[
        "company"
    ],
    "wof:name":"Strange Rentals & Sales",
    "wof:placetype":"venue"
},
  "geometry": {"coordinates":[-82.90404599999999,32.538716],"type":"Point"}
}