{
  "type": "Feature",
  "properties": {
    "addr:full":"9197 Highway 278 E Covington GA 30014",
    "addr:housenumber":"9197",
    "addr:postcode":"30014",
    "addr:street":"Highway 278 E",
    "iso:country":"US",
    "sg:address":"9197 Highway 278 E",
    "sg:city":"Covington",
    "sg:classifiers":[
        {
            "category":"Food & Beverages",
            "subcategory":"Liquor & Beverages",
            "type":"Retail Goods"
        }
    ],
    "sg:phone":"+1 770 786 2633",
    "sg:postcode":"30014",
    "sg:province":"GA",
    "sg:tags":[
        "store"
    ],
    "wof:name":"Newton Package Shop",
    "wof:placetype":"venue"
},
  "geometry": {"coordinates":[-83.80577599999999,33.592943],"type":"Point"}
}