{
  "type": "Feature",
  "properties": {
    "iso:country":"US",
    "sg:address":"2704 Tree Corners Pkwy",
    "sg:city":"Norcross",
    "sg:classifiers":[
        {
            "category":"Communications",
            "type":"Services"
        }
    ],
    "sg:phone":"+1 770 242 7677",
    "sg:postcode":"30092",
    "sg:province":"GA",
    "sg:tags":[
        "communication"
    ],
    "wof:name":"Lunacom Media Inc",
    "wof:placetype":"venue"
},
  "geometry": {"coordinates":[-84.243154,33.949566],"type":"Point"}
}