{
  "type": "Feature",
  "properties": {
    "iso:country":"US",
    "sg:address":"108 S Thornton Ave",
    "sg:city":"Dalton",
    "sg:classifiers":[
        {
            "category":"Real Estate",
            "subcategory":"Real Estate Agent",
            "type":"Services"
        }
    ],
    "sg:phone":"+1 706 278 2119",
    "sg:postcode":"30720",
    "sg:province":"GA",
    "wof:name":"Octavio Perez",
    "wof:placetype":"venue"
},
  "geometry": {"coordinates":[-84.971839,34.771475],"type":"Point"}
}