{
  "type": "Feature",
  "properties": {
    "iso:country":"US",
    "sg:address":"1900 Abbey Ct",
    "sg:city":"Alpharetta",
    "sg:classifiers":[
        {
            "category":"Building & Trades",
            "subcategory":"Construction",
            "type":"Services"
        }
    ],
    "sg:phone":"+1 770 667 2650",
    "sg:postcode":"30004",
    "sg:province":"GA",
    "sg:tags":[
        "builder",
        "deck"
    ],
    "wof:name":"Peachtree Decks And Porches",
    "wof:placetype":"venue"
},
  "geometry": {"coordinates":[-84.354752,34.086971],"type":"Point"}
}