{
  "type": "Feature",
  "properties": {
    "addr:full":"4651 Gateside Ln SE Marietta GA 30067",
    "addr:housenumber":"4651",
    "addr:postcode":"30067",
    "addr:street":"Gateside Ln Se",
    "iso:country":"US",
    "sg:address":"4651 Gateside Ln SE",
    "sg:city":"Marietta",
    "sg:classifiers":[
        {
            "category":"Professional",
            "subcategory":"Business Services",
            "type":"Services"
        }
    ],
    "sg:phone":"+1 770 984 8104",
    "sg:postcode":"30067",
    "sg:province":"GA",
    "sg:tags":[
        "recording",
        "studio"
    ],
    "wof:name":"Dynasonic LLC",
    "wof:placetype":"venue"
},
  "geometry": {"coordinates":[-84.416145,33.947322],"type":"Point"}
}