{
  "type": "Feature",
  "properties": {
    "addr:full":"109 Shadow Wood Ct Macon GA 31206",
    "addr:housenumber":"109",
    "addr:postcode":"31206",
    "addr:street":"Shadow Wood Ct",
    "iso:country":"US",
    "sg:address":"109 Shadow Wood Ct",
    "sg:city":"Macon",
    "sg:classifiers":[
        {
            "category":"Building & Trades",
            "subcategory":"Construction",
            "type":"Services"
        }
    ],
    "sg:phone":"+1 478 719 8442",
    "sg:postcode":"31206",
    "sg:province":"GA",
    "sg:tags":[
        "lot",
        "parking"
    ],
    "wof:name":"M&D Parking Lot Service",
    "wof:placetype":"venue"
},
  "geometry": {"coordinates":[-83.75048200000001,32.829493],"type":"Point"}
}