{
  "type": "Feature",
  "properties": {
    "iso:country":"US",
    "sg:address":"684 Grayson Pkwy",
    "sg:city":"Grayson",
    "sg:classifiers":[
        {
            "category":"Professional",
            "subcategory":"Detective & Security Services",
            "type":"Services"
        }
    ],
    "sg:phone":"+1 770 962 4240",
    "sg:postcode":"30017",
    "sg:province":"GA",
    "sg:tags":[
        "information",
        "bureau"
    ],
    "wof:name":"Bg Service Solutions Inc",
    "wof:placetype":"venue"
},
  "geometry": {"coordinates":[-83.964158,33.888871],"type":"Point"}
}