{
  "type": "Feature",
  "properties": {
    "addr:full":"2697 Glynn Ave Brunswick GA 31520",
    "addr:housenumber":"2697",
    "addr:postcode":"31520",
    "addr:street":"Glynn Ave",
    "iso:country":"US",
    "sg:address":"2697 Glynn Ave",
    "sg:city":"Brunswick",
    "sg:classifiers":[
        {
            "category":"Travel",
            "subcategory":"Hotels & Motels",
            "type":"Entertainment"
        }
    ],
    "sg:phone":"+1 912 265 2282",
    "sg:postcode":"31520",
    "sg:province":"GA",
    "wof:name":"Seabreeze Motel",
    "wof:placetype":"venue"
},
  "geometry": {"coordinates":[-81.474868,31.169094],"type":"Point"}
}