{
  "type": "Feature",
  "properties": {
    "iso:country":"US",
    "sg:address":"1451 N East St",
    "sg:city":"Greensboro",
    "sg:classifiers":[
        {
            "category":"Organizations",
            "subcategory":"Religious Organization",
            "type":"Services"
        }
    ],
    "sg:phone":"+1 706 453 4977",
    "sg:postcode":"30642",
    "sg:province":"GA",
    "wof:name":"Hills Chapel Baptist Church",
    "wof:placetype":"venue"
},
  "geometry": {"coordinates":[-83.165674,33.588892],"type":"Point"}
}