{
  "type": "Feature",
  "properties": {
    "iso:country":"US",
    "sg:address":"821 W Taylor St",
    "sg:city":"Griffin",
    "sg:classifiers":[
        {
            "category":"Restaurant",
            "type":"Food & Drink"
        }
    ],
    "sg:phone":"+1 770 233 9270",
    "sg:postcode":"30223",
    "sg:province":"GA",
    "sg:tags":[
        "personal",
        "eating"
    ],
    "wof:name":"Milanos Italian Cafe",
    "wof:placetype":"venue"
},
  "geometry": {"coordinates":[-84.27630600000001,33.247455],"type":"Point"}
}