{
  "type": "Feature",
  "properties": {
    "addr:full":"6505 Bankhead Hwy Douglasville GA 30134",
    "addr:housenumber":"6505",
    "addr:postcode":"30134",
    "addr:street":"Bankhead Hwy",
    "iso:country":"US",
    "sg:address":"6505 Bankhead Hwy",
    "sg:city":"Douglasville",
    "sg:classifiers":[
        {
            "category":"Manufacturing",
            "subcategory":"Petroleum Products",
            "type":"Manufacturing & Wholesale Goods"
        },
        {
            "category":"Building & Trades",
            "subcategory":"Construction",
            "type":"Services"
        }
    ],
    "sg:phone":"+1 770 920 9168",
    "sg:postcode":"30134",
    "sg:province":"GA",
    "sg:tags":[
        "contractor",
        "paving",
        "asphalt",
        "mfg"
    ],
    "wof:name":"Baldwin Paving Company Inc",
    "wof:placetype":"venue"
},
  "geometry": {"coordinates":[-84.744625,33.752734],"type":"Point"}
}