{
  "type": "Feature",
  "properties": {
    "iso:country":"US",
    "sg:address":"4523 New Jesup Hwy",
    "sg:city":"Brunswick",
    "sg:classifiers":[
        {
            "category":"Shopping",
            "subcategory":"Gifts & Souvenirs",
            "type":"Retail Goods"
        }
    ],
    "sg:phone":"+1 912 265 7983",
    "sg:postcode":"31520",
    "sg:province":"GA",
    "sg:tags":[
        "balloon",
        "artist"
    ],
    "wof:name":"Balloons Unlimited",
    "wof:placetype":"venue"
},
  "geometry": {"coordinates":[-81.512845,31.210559],"type":"Point"}
}