{
  "type": "Feature",
  "properties": {
    "addr:full":"173 Tanner Cemetery Rd Fitzgerald GA 31750",
    "addr:housenumber":"173",
    "addr:postcode":"31750",
    "addr:street":"Tanner Cemetery Rd",
    "iso:country":"US",
    "sg:address":"173 Tanner Cemetery Rd",
    "sg:city":"Fitzgerald",
    "sg:phone":"+1 229 423 7577",
    "sg:postcode":"31750",
    "sg:province":"GA",
    "sg:tags":[
        "farm",
        "field",
        "corn",
        "crop"
    ],
    "wof:name":"Woody Wilson",
    "wof:placetype":"venue"
},
  "geometry": {"coordinates":[-83.15941100000001,31.793899],"type":"Point"}
}