{
  "type": "Feature",
  "properties": {
    "iso:country":"US",
    "sg:address":"231 Maxham Rd",
    "sg:city":"Austell",
    "sg:classifiers":[
        {
            "category":"Professional",
            "subcategory":"Accounting & Tax Preparation",
            "type":"Services"
        }
    ],
    "sg:phone":"+1 770 745 3663",
    "sg:postcode":"30168",
    "sg:province":"GA",
    "wof:name":"Rathels Accounting",
    "wof:placetype":"venue"
},
  "geometry": {"coordinates":[-84.623345,33.787574],"type":"Point"}
}