{
  "type": "Feature",
  "properties": {
    "iso:country":"US",
    "sg:address":"1416 W Gwinnett St",
    "sg:city":"Savannah",
    "sg:classifiers":[
        {
            "category":"Organizations",
            "subcategory":"Religious Organization",
            "type":"Services"
        }
    ],
    "sg:phone":"+1 912 233 3198",
    "sg:postcode":"31415",
    "sg:province":"GA",
    "sg:tags":[
        "church"
    ],
    "wof:name":"Independent Christian Church",
    "wof:placetype":"venue"
},
  "geometry": {"coordinates":[-81.11698199999999,32.072612],"type":"Point"}
}