{
  "type": "Feature",
  "properties": {
    "addr:full":"2361 Hurt St Milledgeville GA 31061",
    "addr:housenumber":"2361",
    "addr:postcode":"31061",
    "addr:street":"Hurt St",
    "iso:country":"US",
    "sg:address":"2361 Hurt St",
    "sg:city":"Milledgeville",
    "sg:classifiers":[
        {
            "category":"Building & Trades",
            "subcategory":"Equipment Rental",
            "type":"Services"
        }
    ],
    "sg:phone":"+1 478 452 7021",
    "sg:postcode":"31061",
    "sg:province":"GA",
    "sg:tags":[
        "leasing"
    ],
    "wof:name":"M&M Leasing Inc",
    "wof:placetype":"venue"
},
  "geometry": {"coordinates":[-83.24858399999999,33.109214],"type":"Point"}
}