{
  "type": "Feature",
  "properties": {
    "addr:full":"54 Elm St Douglas GA 31533",
    "addr:housenumber":"54",
    "addr:postcode":"31533",
    "addr:street":"Elm St",
    "iso:country":"US",
    "sg:address":"54 Elm St",
    "sg:city":"Douglas",
    "sg:classifiers":[
        {
            "category":"Building & Trades",
            "subcategory":"Construction",
            "type":"Services"
        }
    ],
    "sg:phone":"+1 912 384 7684",
    "sg:postcode":"31533",
    "sg:province":"GA",
    "wof:name":"Huey Beasley Utility Buildings",
    "wof:placetype":"venue"
},
  "geometry": {"coordinates":[-82.82034299999999,31.523258],"type":"Point"}
}