{
  "type": "Feature",
  "properties": {
    "iso:country":"US",
    "sg:address":"3249 Hazelwood Dr SW",
    "sg:city":"Atlanta",
    "sg:classifiers":[
        {
            "category":"Organizations",
            "subcategory":"Community Association",
            "type":"Services"
        }
    ],
    "sg:phone":"+1 404 696 8111",
    "sg:postcode":"30311",
    "sg:province":"GA",
    "wof:name":"National Assn Lfthnded Golfers",
    "wof:placetype":"venue"
},
  "geometry": {"coordinates":[-84.494148,33.727578],"type":"Point"}
}