{
  "type": "Feature",
  "properties": {
    "addr:full":"1989 Cheshire Bridge Rd NE Atlanta GA 30324",
    "addr:housenumber":"1989",
    "addr:postcode":"30324",
    "addr:street":"Cheshire Bridge Rd Ne",
    "iso:country":"US",
    "sg:address":"1989 Cheshire Bridge Rd NE",
    "sg:city":"Atlanta",
    "sg:classifiers":[
        {
            "category":"Building & Trades",
            "subcategory":"Locksmith",
            "type":"Services"
        }
    ],
    "sg:phone":"+1 866 580 8152",
    "sg:postcode":"30324",
    "sg:province":"GA",
    "sg:tags":[
        "key"
    ],
    "wof:name":"24 Hour 7 Day Emergency Locksmith",
    "wof:placetype":"venue"
},
  "geometry": {"coordinates":[-84.35797700000001,33.810707],"type":"Point"}
}