{
  "type": "Feature",
  "properties": {
    "iso:country":"US",
    "sg:address":"2781 Holcomb Bridge Rd",
    "sg:city":"Alpharetta",
    "sg:classifiers":[
        {
            "category":"Professional",
            "subcategory":"Management & Consulting",
            "type":"Services"
        }
    ],
    "sg:phone":"+1 678 461 1950",
    "sg:postcode":"30022",
    "sg:province":"GA",
    "wof:name":"Dawane M Young",
    "wof:placetype":"venue"
},
  "geometry": {"coordinates":[-84.280289,33.992888],"type":"Point"}
}