{
  "type": "Feature",
  "properties": {
    "addr:full":"5483 Chamblee Dunwoody Rd Dunwoody GA 30338",
    "addr:housenumber":"5483",
    "addr:postcode":"30338",
    "addr:street":"Chamblee Dunwoody Rd",
    "iso:country":"US",
    "sg:address":"5483 Chamblee Dunwoody Rd",
    "sg:city":"Dunwoody",
    "sg:classifiers":[
        {
            "category":"Shopping",
            "subcategory":"Clothing, Apparel, & Fashions",
            "type":"Retail Goods"
        }
    ],
    "sg:phone":"+1 770 399 6454",
    "sg:postcode":"30338",
    "sg:province":"GA",
    "sg:tags":[
        "tailor"
    ],
    "wof:name":"Dunwoody Village Tailors",
    "wof:placetype":"venue"
},
  "geometry": {"coordinates":[-84.33595099999999,33.948925],"type":"Point"}
}