{
  "type": "Feature",
  "properties": {
    "iso:country":"US",
    "sg:address":"9396 S Main St",
    "sg:city":"Jonesboro",
    "sg:classifiers":[
        {
            "category":"Retail",
            "subcategory":"Repair Shop",
            "type":"Services"
        }
    ],
    "sg:phone":"+1 770 603 7099",
    "sg:postcode":"30236",
    "sg:province":"GA",
    "sg:tags":[
        "scooter",
        "motorcycle",
        "motor"
    ],
    "wof:name":"Beckman Racing & Custom Auto",
    "wof:placetype":"venue"
},
  "geometry": {"coordinates":[-84.33877,33.492707],"type":"Point"}
}