{
  "type": "Feature",
  "properties": {
    "addr:full":"Atlanta Civic Center 397 Piedmont Ave NE Atlanta GA 30308",
    "addr:housenumber":"397",
    "addr:postcode":"30308",
    "addr:street":"Piedmont Ave Ne",
    "iso:country":"US",
    "sg:address":"Atlanta Civic Center 397 Piedmont Ave NE",
    "sg:city":"Atlanta",
    "sg:classifiers":[
        {
            "category":"Museum",
            "type":"Entertainment"
        }
    ],
    "sg:phone":"+1 404 222 2423",
    "sg:postcode":"30308",
    "sg:province":"GA",
    "sg:website":"www.prxi.com",
    "wof:name":"Titanic: the Aritifacts Exhibition",
    "wof:placetype":"venue"
},
  "geometry": {"coordinates":[-84.38179599999999,33.767238],"type":"Point"}
}