{
  "type": "Feature",
  "properties": {
    "iso:country":"US",
    "sg:address":"1119 Banbury Cross",
    "sg:city":"Avondale Estates",
    "sg:classifiers":[
        {
            "category":"Real Estate",
            "subcategory":"Real Estate Agent",
            "type":"Services"
        }
    ],
    "sg:phone":"+1 404 299 0505",
    "sg:postcode":"30002",
    "sg:province":"GA",
    "sg:tags":[
        "personal"
    ],
    "wof:name":"Samford Enterprises Inc",
    "wof:placetype":"venue"
},
  "geometry": {"coordinates":[-84.261968,33.761686],"type":"Point"}
}