{
  "type": "Feature",
  "properties": {
    "addr:full":"707 W Broad Ave Albany GA 31701",
    "addr:housenumber":"707",
    "addr:postcode":"31701",
    "addr:street":"W Broad Ave",
    "iso:country":"US",
    "sg:address":"707 W Broad Ave",
    "sg:city":"Albany",
    "sg:classifiers":[
        {
            "category":"Shopping",
            "type":"Retail Goods"
        }
    ],
    "sg:phone":"+1 229 420 2005",
    "sg:postcode":"31701",
    "sg:province":"GA",
    "sg:tags":[
        "factory",
        "outlet"
    ],
    "wof:name":"Urban Designing Outlet",
    "wof:placetype":"venue"
},
  "geometry": {"coordinates":[-84.164817,31.576938],"type":"Point"}
}