{
  "type": "Feature",
  "properties": {
    "iso:country":"US",
    "sg:address":"4543 E Kings Point Cir",
    "sg:city":"Atlanta",
    "sg:classifiers":[
        {
            "category":"Building & Trades",
            "subcategory":"Landscaping Services",
            "type":"Services"
        }
    ],
    "sg:phone":"+1 404 444 0512",
    "sg:postcode":"30338",
    "sg:province":"GA",
    "wof:name":"Ross Landscaping",
    "wof:placetype":"venue"
},
  "geometry": {"coordinates":[-84.290138,33.928062],"type":"Point"}
}