{
  "type": "Feature",
  "properties": {
    "addr:full":"85 5th St NW Atlanta GA 30308",
    "addr:housenumber":"85",
    "addr:postcode":"30308",
    "addr:street":"5Th St Nw",
    "iso:country":"US",
    "sg:address":"85 5th St NW",
    "sg:city":"Atlanta",
    "sg:classifiers":[
        {
            "category":"Parking",
            "type":"Transportation"
        }
    ],
    "sg:phone":"+1 404 872 7650",
    "sg:postcode":"30308",
    "sg:province":"GA",
    "sg:tags":[
        "garage"
    ],
    "wof:name":"Lanier Parking Systems",
    "wof:placetype":"venue"
},
  "geometry": {"coordinates":[-84.389443,33.776925],"type":"Point"}
}