{
  "type": "Feature",
  "properties": {
    "addr:full":"2414 Louisiana Ave Savannah GA 31404",
    "addr:housenumber":"2414",
    "addr:postcode":"31404",
    "addr:street":"Louisiana Ave",
    "iso:country":"US",
    "sg:address":"2414 Louisiana Ave",
    "sg:city":"Savannah",
    "sg:classifiers":[
        {
            "category":"Organizations",
            "subcategory":"Religious Organization",
            "type":"Services"
        }
    ],
    "sg:phone":"+1 912 231 0504",
    "sg:postcode":"31404",
    "sg:province":"GA",
    "wof:name":"Bread Of Life Church COGIC",
    "wof:placetype":"venue"
},
  "geometry": {"coordinates":[-81.053454,32.052653],"type":"Point"}
}