{
  "type": "Feature",
  "properties": {
    "iso:country":"US",
    "sg:address":"220 Farmers High Rd",
    "sg:city":"Carrollton",
    "sg:classifiers":[
        {
            "category":"Manufacturing",
            "subcategory":"Buildings",
            "type":"Manufacturing & Wholesale Goods"
        },
        {
            "category":"Building & Trades",
            "subcategory":"Construction",
            "type":"Services"
        }
    ],
    "sg:phone":"+1 678 601 3555",
    "sg:postcode":"30117",
    "sg:province":"GA",
    "sg:tags":[
        "home",
        "builder",
        "contractor"
    ],
    "wof:name":"Pauls Home Improvement",
    "wof:placetype":"venue"
},
  "geometry": {"coordinates":[-85.18512,33.55374],"type":"Point"}
}