{
  "type": "Feature",
  "properties": {
    "addr:full":"232 Cotton Indian Creek Rd Mc Donough GA 30252",
    "addr:housenumber":"232",
    "addr:postcode":"30252",
    "addr:street":"Cotton Indian Creek Rd",
    "iso:country":"US",
    "sg:address":"232 Cotton Indian Creek Rd",
    "sg:city":"Mc Donough",
    "sg:classifiers":[
        {
            "category":"Building & Trades",
            "subcategory":"Electrical",
            "type":"Services"
        }
    ],
    "sg:phone":"+1 770 957 9029",
    "sg:postcode":"30252",
    "sg:province":"GA",
    "sg:tags":[
        "electrical",
        "contractor"
    ],
    "wof:name":"All Electric Distributors",
    "wof:placetype":"venue"
},
  "geometry": {"coordinates":[-84.11268699999999,33.533239],"type":"Point"}
}