{
  "type": "Feature",
  "properties": {
    "addr:full":"38 Superior Blvd SE Rome GA 30161",
    "addr:housenumber":"38",
    "addr:postcode":"ga 30161",
    "addr:street":"Superior Blvd Se",
    "iso:country":"US",
    "sg:address":"38 Superior Blvd SE",
    "sg:city":"Rome",
    "sg:classifiers":[
        {
            "category":"Wholesale",
            "subcategory":"Machinery & Supplies",
            "type":"Manufacturing & Wholesale Goods"
        }
    ],
    "sg:phone":"+1 706 291 2518",
    "sg:postcode":"30161",
    "sg:province":"GA",
    "sg:tags":[
        "janitor"
    ],
    "wof:name":"Camp Industries",
    "wof:placetype":"venue"
},
  "geometry": {"coordinates":[-85.197221,34.16916],"type":"Point"}
}