{
  "type": "Feature",
  "properties": {
    "addr:full":"200 Cotton Creek Ct Mc Donough GA 30252",
    "addr:housenumber":"200",
    "addr:postcode":"30252",
    "addr:street":"Cotton Creek Ct",
    "iso:country":"US",
    "sg:address":"200 Cotton Creek Ct",
    "sg:city":"Mc Donough",
    "sg:classifiers":[
        {
            "category":"Shopping",
            "subcategory":"Florist",
            "type":"Retail Goods"
        }
    ],
    "sg:phone":"+1 770 898 5943",
    "sg:postcode":"30252",
    "sg:province":"GA",
    "wof:name":"Flowers By Linda",
    "wof:placetype":"venue"
},
  "geometry": {"coordinates":[-84.094595,33.529961],"type":"Point"}
}