{
  "type": "Feature",
  "properties": {
    "addr:full":"587 Cobb Pkwy S Marietta GA 30060",
    "addr:housenumber":"587",
    "addr:postcode":"30060",
    "addr:street":"Cobb Pkwy S",
    "iso:country":"US",
    "sg:address":"587 Cobb Pkwy S",
    "sg:city":"Marietta",
    "sg:classifiers":[
        {
            "category":"Shopping",
            "subcategory":"Jewelry",
            "type":"Retail Goods"
        }
    ],
    "sg:phone":"+1 770 427 8833",
    "sg:postcode":"30060",
    "sg:province":"GA",
    "sg:website":"www.cashamerica.com",
    "wof:name":"Cash America Pawn",
    "wof:placetype":"venue"
},
  "geometry": {"coordinates":[-84.514297,33.9394],"type":"Point"}
}