{
  "type": "Feature",
  "properties": {
    "addr:full":"315 W Ponce de Leon Ave Decatur GA 30030",
    "addr:housenumber":"315",
    "addr:postcode":"30030",
    "addr:street":"W Ponce De Leon Ave",
    "iso:country":"US",
    "sg:address":"315 W Ponce de Leon Ave",
    "sg:city":"Decatur",
    "sg:classifiers":[
        {
            "category":"Professional",
            "subcategory":"Lawyer & Legal Services",
            "type":"Services"
        }
    ],
    "sg:phone":"+1 404 687 5215",
    "sg:postcode":"30030",
    "sg:province":"GA",
    "wof:name":"Diana McDonald PC",
    "wof:placetype":"venue"
},
  "geometry": {"coordinates":[-84.30219700000001,33.77572],"type":"Point"}
}