{
  "type": "Feature",
  "properties": {
    "addr:full":"1730 Baughs Cross Rd West Point GA 31833",
    "addr:housenumber":"1730",
    "addr:postcode":"31833",
    "addr:street":"Baughs Cross Rd",
    "iso:country":"US",
    "sg:address":"1730 Baughs Cross Rd",
    "sg:city":"West Point",
    "sg:classifiers":[
        {
            "category":"Building & Trades",
            "subcategory":"Construction",
            "type":"Services"
        }
    ],
    "sg:phone":"+1 706 883 7825",
    "sg:postcode":"31833",
    "sg:province":"GA",
    "sg:tags":[
        "house"
    ],
    "wof:name":"Steven Daniel Construction",
    "wof:placetype":"venue"
},
  "geometry": {"coordinates":[-85.025018,32.917074],"type":"Point"}
}