{
  "type": "Feature",
  "properties": {
    "addr:full":"460 Grayson Pkwy Grayson GA 30017",
    "addr:housenumber":"460",
    "addr:postcode":"30017",
    "addr:street":"Grayson Pkwy",
    "iso:country":"US",
    "sg:address":"460 Grayson Pkwy",
    "sg:city":"Grayson",
    "sg:classifiers":[
        {
            "category":"Education",
            "subcategory":"School",
            "type":"Public Place"
        }
    ],
    "sg:phone":"+1 770 963 7189",
    "sg:postcode":"30017",
    "sg:province":"GA",
    "sg:tags":[
        "elementary"
    ],
    "sg:website":"www.gwinnett.k12.ga.us",
    "wof:name":"Grayson Elementary School",
    "wof:placetype":"venue"
},
  "geometry": {"coordinates":[-83.957357,33.89336],"type":"Point"}
}