{
  "type": "Feature",
  "properties": {
    "addr:full":"436 Canton Rd Cumming GA 30040",
    "addr:housenumber":"436",
    "addr:postcode":"30040",
    "addr:street":"Canton Rd",
    "iso:country":"US",
    "sg:address":"436 Canton Rd",
    "sg:city":"Cumming",
    "sg:classifiers":[
        {
            "category":"Food & Beverages",
            "subcategory":"Groceries & Convenience Stores",
            "type":"Retail Goods"
        }
    ],
    "sg:phone":"+1 770 889 5868",
    "sg:postcode":"30040",
    "sg:province":"GA",
    "sg:website":"www.inglesmarkets.com",
    "wof:name":"Ingles",
    "wof:placetype":"venue"
},
  "geometry": {"coordinates":[-84.14563800000001,34.213946],"type":"Point"}
}