{
  "type": "Feature",
  "properties": {
    "addr:full":"738 North Ave Macon GA 31211",
    "addr:housenumber":"738",
    "addr:postcode":"31211",
    "addr:street":"North Ave",
    "iso:country":"US",
    "sg:address":"738 North Ave",
    "sg:city":"Macon",
    "sg:classifiers":[
        {
            "category":"Landmark",
            "subcategory":"Tourist Information",
            "type":"Public Place"
        }
    ],
    "sg:phone":"+1 478 746 3520",
    "sg:postcode":"31211",
    "sg:province":"GA",
    "sg:tags":[
        "promoter",
        "tours-operators"
    ],
    "wof:name":"Coleman Tours",
    "wof:placetype":"venue"
},
  "geometry": {"coordinates":[-83.62354000000001,32.8508],"type":"Point"}
}