{
  "type": "Feature",
  "properties": {
    "addr:full":"4501 Montgomery St Savannah GA 31405",
    "addr:housenumber":"4501",
    "addr:postcode":"31405",
    "addr:street":"Montgomery St",
    "iso:country":"US",
    "sg:address":"4501 Montgomery St",
    "sg:city":"Savannah",
    "sg:classifiers":[
        {
            "category":"Wholesale",
            "subcategory":"Machinery & Supplies",
            "type":"Manufacturing & Wholesale Goods"
        }
    ],
    "sg:phone":"+1 912 447 4740",
    "sg:postcode":"31405",
    "sg:province":"GA",
    "sg:tags":[
        "equipment",
        "establishment"
    ],
    "wof:name":"Leading Edge Inc",
    "wof:placetype":"venue"
},
  "geometry": {"coordinates":[-81.11154399999999,32.039426],"type":"Point"}
}