{
  "type": "Feature",
  "properties": {
    "addr:full":"275 E Lanier Ave Fayetteville GA 30214",
    "addr:housenumber":"275",
    "addr:postcode":"30214",
    "addr:street":"E Lanier Ave",
    "iso:country":"US",
    "sg:address":"275 E Lanier Ave",
    "sg:city":"Fayetteville",
    "sg:classifiers":[
        {
            "category":"Shopping",
            "subcategory":"Bicycles & Sporting Goods",
            "type":"Retail Goods"
        }
    ],
    "sg:phone":"+1 770 716 3383",
    "sg:postcode":"30214",
    "sg:province":"GA",
    "wof:name":"Head Covers",
    "wof:placetype":"venue"
},
  "geometry": {"coordinates":[-84.451088,33.448703],"type":"Point"}
}