{
  "type": "Feature",
  "properties": {
    "addr:full":"1607 Grove Point Rd Savannah GA 31419",
    "addr:housenumber":"1607",
    "addr:postcode":"31419",
    "addr:street":"Grove Point Rd",
    "iso:country":"US",
    "sg:address":"1607 Grove Point Rd",
    "sg:city":"Savannah",
    "sg:classifiers":[
        {
            "category":"Real Estate",
            "subcategory":"Real Estate Services",
            "type":"Services"
        },
        {
            "category":"Real Estate",
            "subcategory":"Real Estate Agent",
            "type":"Services"
        }
    ],
    "sg:phone":"+1 912 925 5258",
    "sg:postcode":"31419",
    "sg:province":"GA",
    "sg:tags":[
        "buyer",
        "broker"
    ],
    "wof:name":"Rlo Consulting Group Cabinet R",
    "wof:placetype":"venue"
},
  "geometry": {"coordinates":[-81.238077,31.993938],"type":"Point"}
}