{
  "type": "Feature",
  "properties": {
    "addr:full":"111 Palmetto Bay Rd Savannah GA 31410",
    "addr:housenumber":"111",
    "addr:postcode":"31410",
    "addr:street":"Palmetto Bay Rd",
    "iso:country":"US",
    "sg:address":"111 Palmetto Bay Rd",
    "sg:city":"Savannah",
    "sg:classifiers":[
        {
            "category":"Professional",
            "subcategory":"Management & Consulting",
            "type":"Services"
        }
    ],
    "sg:phone":"+1 912 897 7292",
    "sg:postcode":"31410",
    "sg:province":"GA",
    "sg:tags":[
        "business"
    ],
    "wof:name":"Robert E Jones Consulting Inc",
    "wof:placetype":"venue"
},
  "geometry": {"coordinates":[-80.964203,32.010782],"type":"Point"}
}