{
  "type": "Feature",
  "properties": {
    "addr:full":"45 W Crossville Rd Ste 501 Roswell GA 30075",
    "addr:housenumber":"45",
    "addr:postcode":"30075",
    "addr:street":"W Crossville Rd Ste 501",
    "iso:country":"US",
    "sg:address":"45 W Crossville Rd Ste 501",
    "sg:city":"Roswell",
    "sg:classifiers":[
        {
            "category":"Health Services",
            "subcategory":"Health Practitioner",
            "type":"Services"
        }
    ],
    "sg:phone":"+1 678 372 2913",
    "sg:postcode":"30075",
    "sg:province":"GA",
    "sg:tags":[
        "nutritionist"
    ],
    "sg:website":"www.nutritionallyyours.net",
    "wof:name":"Nutritionally Yours",
    "wof:placetype":"venue"
},
  "geometry": {"coordinates":[-84.36129,34.048169],"type":"Point"}
}