{
  "type": "Feature",
  "properties": {
    "iso:country":"US",
    "sg:address":"5414 Seaton Dr",
    "sg:city":"Atlanta",
    "sg:classifiers":[
        {
            "category":"Professional",
            "subcategory":"Computer Services",
            "type":"Services"
        }
    ],
    "sg:phone":"+1 770 395 6259",
    "sg:postcode":"30338",
    "sg:province":"GA",
    "sg:tags":[
        "related"
    ],
    "wof:name":"Pinnacle Data Sltns Inc",
    "wof:placetype":"venue"
},
  "geometry": {"coordinates":[-84.30116099999999,33.953406],"type":"Point"}
}