{
  "type": "Feature",
  "properties": {
    "addr:full":"1246 Veterans Pkwy Columbus GA 31901",
    "addr:housenumber":"1246",
    "addr:postcode":"31901",
    "addr:street":"Veterans Pkwy",
    "iso:country":"US",
    "sg:address":"1246 Veterans Pkwy",
    "sg:city":"Columbus",
    "sg:classifiers":[
        {
            "category":"Autos & Motor Vehicles",
            "subcategory":"Fuel & Gas Station",
            "type":"Retail Goods"
        }
    ],
    "sg:phone":"+1 706 324 3209",
    "sg:postcode":"31901",
    "sg:province":"GA",
    "sg:tags":[
        "station",
        "gasoline",
        "oil"
    ],
    "wof:name":"Buddy Helton Chevron",
    "wof:placetype":"venue"
},
  "geometry": {"coordinates":[-84.987503,32.46958],"type":"Point"}
}