{
  "type": "Feature",
  "properties": {
    "iso:country":"US",
    "sg:address":"2463 Hamilton Mill Pkwy",
    "sg:city":"Dacula",
    "sg:classifiers":[
        {
            "category":"Restaurant",
            "type":"Food & Drink"
        }
    ],
    "sg:phone":"+1 678 541 8486",
    "sg:postcode":"30019",
    "sg:province":"GA",
    "wof:name":"Uncle Vito's New York Pizza",
    "wof:placetype":"venue"
},
  "geometry": {"coordinates":[-83.913568,34.058053],"type":"Point"}
}