{
  "type": "Feature",
  "properties": {
    "addr:full":"2225 Cascade Rd SW Atlanta GA 30311",
    "addr:housenumber":"2225",
    "addr:postcode":"30311",
    "addr:street":"Cascade Rd Sw",
    "iso:country":"US",
    "sg:address":"2225 Cascade Rd SW",
    "sg:city":"Atlanta",
    "sg:classifiers":[
        {
            "category":"Shopping",
            "subcategory":"Gifts & Souvenirs",
            "type":"Retail Goods"
        },
        {
            "category":"Professional",
            "subcategory":"Printing & Photocopies",
            "type":"Services"
        },
        {
            "category":"Manufacturing",
            "subcategory":"Retail Goods",
            "type":"Manufacturing & Wholesale Goods"
        }
    ],
    "sg:phone":"+1 404 753 1998",
    "sg:postcode":"30311",
    "sg:province":"GA",
    "sg:tags":[
        "shop",
        "duplicating",
        "oils-essential",
        "copying"
    ],
    "wof:name":"J D's Precious Oils & Lil-Kute Things",
    "wof:placetype":"venue"
},
  "geometry": {"coordinates":[-84.461051,33.722338],"type":"Point"}
}