{
  "type": "Feature",
  "properties": {
    "addr:full":"509 Flint Ave Albany GA 31701",
    "addr:housenumber":"509",
    "addr:postcode":"31701",
    "addr:street":"Flint Ave",
    "iso:country":"US",
    "sg:address":"509 Flint Ave",
    "sg:city":"Albany",
    "sg:classifiers":[
        {
            "category":"Utilities",
            "subcategory":"Telephone",
            "type":"Services"
        }
    ],
    "sg:phone":"+1 229 883 2080",
    "sg:postcode":"31701",
    "sg:province":"GA",
    "sg:tags":[
        "company"
    ],
    "wof:name":"Comcast Cable",
    "wof:placetype":"venue"
},
  "geometry": {"coordinates":[-84.16171799999999,31.580052],"type":"Point"}
}