{
  "type": "Feature",
  "properties": {
    "iso:country":"US",
    "sg:address":"41 Marietta St NW",
    "sg:city":"Atlanta",
    "sg:classifiers":[
        {
            "category":"Autos & Motor Vehicles",
            "subcategory":"Automobile Sales",
            "type":"Retail Goods"
        }
    ],
    "sg:phone":"+1 678 913 7774",
    "sg:postcode":"30303",
    "sg:province":"GA",
    "sg:tags":[
        "new",
        "car"
    ],
    "wof:name":"Mdt International",
    "wof:placetype":"venue"
},
  "geometry": {"coordinates":[-84.390839,33.755203],"type":"Point"}
}