{
  "type": "Feature",
  "properties": {
    "addr:full":"6053 Christina Ct Bethlehem GA 30620",
    "addr:housenumber":"6053",
    "addr:postcode":"30620",
    "addr:street":"Christina Ct",
    "iso:country":"US",
    "sg:address":"6053 Christina Ct",
    "sg:city":"Bethlehem",
    "sg:classifiers":[
        {
            "category":"Building & Trades",
            "subcategory":"Landscaping Services",
            "type":"Services"
        }
    ],
    "sg:phone":"+1 770 266 0577",
    "sg:postcode":"30620",
    "sg:province":"GA",
    "sg:tags":[
        "landscape",
        "contractor"
    ],
    "wof:name":"CTD Enterprises",
    "wof:placetype":"venue"
},
  "geometry": {"coordinates":[-83.782994,33.913188],"type":"Point"}
}