{
  "type": "Feature",
  "properties": {
    "iso:country":"US",
    "sg:address":"3379 Aztec Rd",
    "sg:city":"Atlanta",
    "sg:classifiers":[
        {
            "category":"Building & Trades",
            "subcategory":"Landscaping Services",
            "type":"Services"
        }
    ],
    "sg:phone":"+1 770 449 0497",
    "sg:postcode":"30340",
    "sg:province":"GA",
    "sg:tags":[
        "lawn",
        "maintenance",
        "grounds"
    ],
    "wof:name":"Reid Lawn Care",
    "wof:placetype":"venue"
},
  "geometry": {"coordinates":[-84.272384,33.886435],"type":"Point"}
}