{
  "type": "Feature",
  "properties": {
    "addr:full":"1800 Willow Trail Pkwy Norcross GA 30093",
    "addr:housenumber":"1800",
    "addr:postcode":"30093",
    "addr:street":"Willow Trail Pkwy",
    "iso:country":"US",
    "sg:address":"1800 Willow Trail Pkwy",
    "sg:city":"Norcross",
    "sg:classifiers":[
        {
            "category":"Building & Trades",
            "subcategory":"Locksmith",
            "type":"Services"
        }
    ],
    "sg:phone":"+1 888 568 9094",
    "sg:postcode":"30093",
    "sg:province":"GA",
    "sg:tags":[
        "key"
    ],
    "wof:name":"1 24 Hour Emergency Locksmith",
    "wof:placetype":"venue"
},
  "geometry": {"coordinates":[-84.171503,33.927367],"type":"Point"}
}