{
  "type": "Feature",
  "properties": {
    "addr:full":"609 Chestatee Pt Dawsonville GA 30534",
    "addr:housenumber":"609",
    "addr:postcode":"30534",
    "addr:street":"Chestatee Pt",
    "iso:country":"US",
    "sg:address":"609 Chestatee Pt",
    "sg:city":"Dawsonville",
    "sg:classifiers":[
        {
            "category":"Retail",
            "subcategory":"Laundry & Dry Cleaning",
            "type":"Services"
        }
    ],
    "sg:phone":"+1 706 216 3302",
    "sg:postcode":"30534",
    "sg:province":"GA",
    "wof:name":"Spring Cleaners",
    "wof:placetype":"venue"
},
  "geometry": {"coordinates":[-83.988265,34.379337],"type":"Point"}
}