{
  "type": "Feature",
  "properties": {
    "iso:country":"US",
    "sg:address":"1206 Dunbar Rd",
    "sg:city":"Warner Robins",
    "sg:classifiers":[
        {
            "category":"Building & Trades",
            "subcategory":"Construction",
            "type":"Services"
        }
    ],
    "sg:phone":"+1 478 953 3220",
    "sg:postcode":"31093",
    "sg:province":"GA",
    "sg:tags":[
        "hanging",
        "contractor"
    ],
    "wof:name":"H&H Paint Contracting",
    "wof:placetype":"venue"
},
  "geometry": {"coordinates":[-83.698852,32.659445],"type":"Point"}
}