{
  "type": "Feature",
  "properties": {
    "addr:full":"3801 Washington Rd Augusta GA 30907",
    "addr:housenumber":"3801",
    "addr:postcode":"30907",
    "addr:street":"Washington Rd",
    "iso:country":"US",
    "sg:address":"3801 Washington Rd",
    "sg:city":"Augusta",
    "sg:classifiers":[
        {
            "category":"Personal",
            "subcategory":"Beauty Salon",
            "type":"Services"
        }
    ],
    "sg:phone":"+1 706 869 0957",
    "sg:postcode":"30907",
    "sg:province":"GA",
    "sg:tags":[
        "shop",
        "manicuring"
    ],
    "wof:name":"Nail Xpress",
    "wof:placetype":"venue"
},
  "geometry": {"coordinates":[-82.087688,33.512645],"type":"Point"}
}