{
  "type": "Feature",
  "properties": {
    "addr:full":"1680 Mall of Georgia Blvd Buford GA 30519",
    "addr:housenumber":"1680",
    "addr:postcode":"30519",
    "addr:street":"Mall Of Georgia Blvd",
    "iso:country":"US",
    "sg:address":"1680 Mall of Georgia Blvd",
    "sg:city":"Buford",
    "sg:classifiers":[
        {
            "category":"Restaurant",
            "type":"Food & Drink"
        }
    ],
    "sg:menulink":"http://www.allmenus.com/ga/buford/246375-fajitas/menu/",
    "sg:phone":"+1 678 482 2993",
    "sg:postcode":"30519",
    "sg:province":"GA",
    "sg:tags":[
        "mexican"
    ],
    "wof:name":"Fajita's",
    "wof:placetype":"venue"
},
  "geometry": {"coordinates":[-83.994317,34.061968],"type":"Point"}
}