{
  "type": "Feature",
  "properties": {
    "addr:full":"2250 Rhinehill Rd SE Atlanta GA 30315",
    "addr:housenumber":"2250",
    "addr:postcode":"30315",
    "addr:street":"Rhinehill Rd Se",
    "iso:country":"US",
    "sg:address":"2250 Rhinehill Rd SE",
    "sg:city":"Atlanta",
    "sg:classifiers":[
        {
            "category":"Insurance",
            "subcategory":"Insurance Agent",
            "type":"Services"
        }
    ],
    "sg:phone":"+1 404 624 0466",
    "sg:postcode":"30315",
    "sg:province":"GA",
    "wof:name":"McKinney Mary Brown Insurance",
    "wof:placetype":"venue"
},
  "geometry": {"coordinates":[-84.378952,33.6943],"type":"Point"}
}