{
  "type": "Feature",
  "properties": {
    "iso:country":"US",
    "sg:address":"2258 Sumter Lake Dr",
    "sg:city":"Marietta",
    "sg:classifiers":[
        {
            "category":"Health Services",
            "subcategory":"Chiropractor",
            "type":"Services"
        }
    ],
    "sg:phone":"+1 770 971 5554",
    "sg:postcode":"30062",
    "sg:province":"GA",
    "wof:name":"Shallowford Chiropractic",
    "wof:placetype":"venue"
},
  "geometry": {"coordinates":[-84.46068099999999,34.005931],"type":"Point"}
}