{
  "type": "Feature",
  "properties": {
    "addr:full":"109 Magnolia Dr S Tifton GA 31794",
    "addr:housenumber":"109",
    "addr:postcode":"31794",
    "addr:street":"Magnolia Dr S",
    "iso:country":"US",
    "sg:address":"109 Magnolia Dr S",
    "sg:city":"Tifton",
    "sg:classifiers":[
        {
            "category":"Food & Beverages",
            "subcategory":"Bakery",
            "type":"Retail Goods"
        },
        {
            "category":"Bakery",
            "type":"Food & Drink"
        }
    ],
    "sg:phone":"+1 229 382 3767",
    "sg:postcode":"31794",
    "sg:province":"GA",
    "sg:tags":[
        "cake",
        "wedding",
        "bakers-wholesale",
        "pastry"
    ],
    "sg:website":"http://www.flowersfoods.com",
    "wof:name":"Flowers Baking Company",
    "wof:placetype":"venue"
},
  "geometry": {"coordinates":[-83.524924,31.455521],"type":"Point"}
}