{
  "type": "Feature",
  "properties": {
    "iso:country":"US",
    "sg:address":"222 Allison Dr",
    "sg:city":"Woodstock",
    "sg:classifiers":[
        {
            "category":"Manufacturing",
            "subcategory":"Rubber & Plastics",
            "type":"Manufacturing & Wholesale Goods"
        },
        {
            "category":"Manufacturing",
            "subcategory":"Chemicals & Compounds",
            "type":"Manufacturing & Wholesale Goods"
        }
    ],
    "sg:phone":"+1 678 494 4050",
    "sg:postcode":"30188",
    "sg:province":"GA",
    "sg:tags":[
        "vessel",
        "pressure",
        "tanks-wholesale",
        "manufacturer"
    ],
    "wof:name":"Southeastern Transition Group",
    "wof:placetype":"venue"
},
  "geometry": {"coordinates":[-84.48965200000001,34.131933],"type":"Point"}
}