{
  "type": "Feature",
  "properties": {
    "addr:full":"1670 Settindown Dr Roswell GA 30075",
    "addr:housenumber":"1670",
    "addr:postcode":"30075",
    "addr:street":"Settindown Dr",
    "iso:country":"US",
    "sg:address":"1670 Settindown Dr",
    "sg:city":"Roswell",
    "sg:classifiers":[
        {
            "category":"Manufacturing",
            "subcategory":"Printing",
            "type":"Manufacturing & Wholesale Goods"
        }
    ],
    "sg:phone":"+1 770 453 9954",
    "sg:postcode":"30075",
    "sg:province":"GA",
    "sg:tags":[
        "periodical"
    ],
    "wof:name":"Magazine Guys",
    "wof:placetype":"venue"
},
  "geometry": {"coordinates":[-84.416107,34.105133],"type":"Point"}
}