{
  "type": "Feature",
  "properties": {
    "iso:country":"US",
    "sg:address":"1051 Glover Rd",
    "sg:city":"Hogansville",
    "sg:classifiers":[
        {
            "category":"Professional",
            "subcategory":"Business Services",
            "type":"Services"
        }
    ],
    "sg:phone":"+1 706 637 0400",
    "sg:postcode":"30230",
    "sg:province":"GA",
    "wof:name":"Materials Inspection Inc",
    "wof:placetype":"venue"
},
  "geometry": {"coordinates":[-84.92350999999999,33.205015],"type":"Point"}
}