{
  "type": "Feature",
  "properties": {
    "iso:country":"US",
    "sg:address":"1500 Crooked Tree Ln",
    "sg:city":"Stone Mountain",
    "sg:classifiers":[
        {
            "category":"Wholesale",
            "subcategory":"Toys & Hobbies",
            "type":"Manufacturing & Wholesale Goods"
        }
    ],
    "sg:phone":"+1 770 987 4695",
    "sg:postcode":"30088",
    "sg:province":"GA",
    "wof:name":"Ingram Ideas",
    "wof:placetype":"venue"
},
  "geometry": {"coordinates":[-84.184973,33.747047],"type":"Point"}
}