{
  "type": "Feature",
  "properties": {
    "iso:country":"US",
    "sg:address":"3564 Ashford Dunwoody Road",
    "sg:city":"Atlanta",
    "sg:classifiers":[
        {
            "category":"Real Estate",
            "subcategory":"Real Estate Operator",
            "type":"Services"
        }
    ],
    "sg:phone":"+1 770 451 5425",
    "sg:postcode":"30319",
    "sg:province":"GA",
    "sg:tags":[
        "apartment"
    ],
    "wof:name":"The Ashford",
    "wof:placetype":"venue"
},
  "geometry": {"coordinates":[-84.32995,33.896971],"type":"Point"}
}