{
  "type": "Feature",
  "properties": {
    "iso:country":"US",
    "sg:address":"1100 Reynolds St",
    "sg:city":"Augusta",
    "sg:classifiers":[
        {
            "category":"Building & Trades",
            "subcategory":"Landscaping Services",
            "type":"Services"
        }
    ],
    "sg:phone":"+1 706 724 3530",
    "sg:postcode":"30901",
    "sg:province":"GA",
    "sg:tags":[
        "lawn",
        "maintenance",
        "grounds"
    ],
    "wof:name":"Valley Crest Landscape Mntnc",
    "wof:placetype":"venue"
},
  "geometry": {"coordinates":[-81.971933,33.47922],"type":"Point"}
}