{
  "type": "Feature",
  "properties": {
    "addr:full":"108 Malone St Sandersville GA 31082",
    "addr:housenumber":"108",
    "addr:postcode":"31082",
    "addr:street":"Malone St",
    "iso:country":"US",
    "sg:address":"108 Malone St",
    "sg:city":"Sandersville",
    "sg:classifiers":[
        {
            "category":"Shopping",
            "subcategory":"Stationery & Office Supplies",
            "type":"Retail Goods"
        }
    ],
    "sg:phone":"+1 478 552 6026",
    "sg:postcode":"31082",
    "sg:province":"GA",
    "wof:name":"Brooker Business Products",
    "wof:placetype":"venue"
},
  "geometry": {"coordinates":[-82.812065,32.983858],"type":"Point"}
}