{
  "type": "Feature",
  "properties": {
    "iso:country":"US",
    "sg:address":"3975 Arkwright Rd",
    "sg:city":"Macon",
    "sg:classifiers":[
        {
            "category":"Restaurant",
            "type":"Food & Drink"
        }
    ],
    "sg:phone":"+1 478 476 8272",
    "sg:postcode":"31210",
    "sg:province":"GA",
    "sg:tags":[
        "eating"
    ],
    "wof:name":"Paul's Bistro",
    "wof:placetype":"venue"
},
  "geometry": {"coordinates":[-83.689772,32.910719],"type":"Point"}
}