{
  "type": "Feature",
  "properties": {
    "addr:full":"173 Kilgore Rd Carrollton GA 30116",
    "addr:housenumber":"173",
    "addr:postcode":"30116",
    "addr:street":"Kilgore Rd",
    "iso:country":"US",
    "sg:address":"173 Kilgore Rd",
    "sg:city":"Carrollton",
    "sg:classifiers":[
        {
            "category":"Professional",
            "subcategory":"Engineering",
            "type":"Services"
        }
    ],
    "sg:phone":"+1 770 832 9009",
    "sg:postcode":"30116",
    "sg:province":"GA",
    "sg:tags":[
        "engineer"
    ],
    "wof:name":"Developmental Technologies Inc",
    "wof:placetype":"venue"
},
  "geometry": {"coordinates":[-85.036551,33.592724],"type":"Point"}
}