{
  "type": "Feature",
  "properties": {
    "iso:country":"US",
    "sg:address":"3872 Roswell Rd Ste C3",
    "sg:city":"Atlanta",
    "sg:classifiers":[
        {
            "category":"Insurance",
            "subcategory":"Hazard Insurance",
            "type":"Services"
        }
    ],
    "sg:phone":"+1 404 816 8885",
    "sg:postcode":"30342",
    "sg:province":"GA",
    "sg:website":"http://statefarm.mqgroup.com/url.asp?usr=112298",
    "wof:name":"State Farm Insurance Agent-Janet Thomas",
    "wof:placetype":"venue"
},
  "geometry": {"coordinates":[-84.380521,33.860345],"type":"Point"}
}