{
  "type": "Feature",
  "properties": {
    "iso:country":"US",
    "sg:address":"217 Forrest St",
    "sg:city":"Americus",
    "sg:classifiers":[
        {
            "category":"Social Services",
            "type":"Services"
        }
    ],
    "sg:phone":"+1 229 928 2080",
    "sg:postcode":"31709",
    "sg:province":"GA",
    "sg:tags":[
        "organization",
        "welfare"
    ],
    "wof:name":"Prison & Jail Project",
    "wof:placetype":"venue"
},
  "geometry": {"coordinates":[-84.234966,32.070139],"type":"Point"}
}