{
  "type": "Feature",
  "properties": {
    "iso:country":"US",
    "sg:address":"241 S Main St",
    "sg:city":"Jonesboro",
    "sg:classifiers":[
        {
            "category":"Professional",
            "subcategory":"Business Services",
            "type":"Services"
        }
    ],
    "sg:phone":"+1 770 471 1967",
    "sg:postcode":"30236",
    "sg:province":"GA",
    "wof:name":"BNF Enterprises",
    "wof:placetype":"venue"
},
  "geometry": {"coordinates":[-84.35238699999999,33.511524],"type":"Point"}
}