{
  "type": "Feature",
  "properties": {
    "addr:full":"309 Paradise Dr Savannah GA 31406",
    "addr:housenumber":"309",
    "addr:postcode":"31406",
    "addr:street":"Paradise Dr",
    "iso:country":"US",
    "sg:address":"309 Paradise Dr",
    "sg:city":"Savannah",
    "sg:classifiers":[
        {
            "category":"Banks & Credit Unions",
            "subcategory":"Financial Services",
            "type":"Services"
        }
    ],
    "sg:phone":"+1 912 925 4266",
    "sg:postcode":"31406",
    "sg:province":"GA",
    "sg:tags":[
        "trust",
        "investment",
        "real estate"
    ],
    "wof:name":"Lancaster 204 LLC",
    "wof:placetype":"venue"
},
  "geometry": {"coordinates":[-81.12514,31.98589],"type":"Point"}
}