{
  "type": "Feature",
  "properties": {
    "iso:country":"US",
    "sg:address":"521 W Montgomery St",
    "sg:city":"Milledgeville",
    "sg:classifiers":[
        {
            "category":"Social Services",
            "type":"Services"
        }
    ],
    "sg:phone":"+1 478 445 4431",
    "sg:postcode":"31061",
    "sg:province":"GA",
    "wof:name":"Milledgeville Parole Office",
    "wof:placetype":"venue"
},
  "geometry": {"coordinates":[-83.23487299999999,33.082753],"type":"Point"}
}