{
  "type": "Feature",
  "properties": {
    "addr:full":"5000 Clark Howell Hwy Atlanta GA 30349",
    "addr:housenumber":"5000",
    "addr:postcode":"30349",
    "addr:street":"Clark Howell Hwy",
    "iso:country":"US",
    "sg:address":"5000 Clark Howell Hwy",
    "sg:city":"Atlanta",
    "sg:classifiers":[
        {
            "category":"Wholesale",
            "subcategory":"Machinery & Supplies",
            "type":"Manufacturing & Wholesale Goods"
        },
        {
            "category":"Retail",
            "subcategory":"Repair Shop",
            "type":"Services"
        }
    ],
    "sg:phone":"+1 404 767 4667",
    "sg:postcode":"30349",
    "sg:province":"GA",
    "sg:tags":[
        "avionics",
        "aircraft",
        "transportation",
        "equipment"
    ],
    "sg:website":"www.precision-electronics.com",
    "wof:name":"Precision Electronics Inc",
    "wof:placetype":"venue"
},
  "geometry": {"coordinates":[-84.40304399999999,33.615286],"type":"Point"}
}