{
  "type": "Feature",
  "properties": {
    "iso:country":"US",
    "sg:address":"11395 Alpharetta Hwy",
    "sg:city":"Roswell",
    "sg:classifiers":[
        {
            "category":"Real Estate",
            "subcategory":"Real Estate Operator",
            "type":"Services"
        }
    ],
    "sg:phone":"+1 770 475 0251",
    "sg:postcode":"30076",
    "sg:province":"GA",
    "sg:tags":[
        "apartment"
    ],
    "wof:name":"Rosemont Apartments",
    "wof:placetype":"venue"
},
  "geometry": {"coordinates":[-84.32483999999999,34.06059],"type":"Point"}
}