{
  "type": "Feature",
  "properties": {
    "addr:full":"13270 New Providence Rd Alpharetta GA 30004",
    "addr:housenumber":"13270",
    "addr:postcode":"30004",
    "addr:street":"New Providence Rd",
    "iso:country":"US",
    "sg:address":"13270 New Providence Rd",
    "sg:city":"Alpharetta",
    "sg:classifiers":[
        {
            "category":"Building & Trades",
            "subcategory":"Construction",
            "type":"Services"
        }
    ],
    "sg:phone":"+1 770 351 7975",
    "sg:postcode":"30004",
    "sg:province":"GA",
    "sg:tags":[
        "hanging",
        "contractor"
    ],
    "wof:name":"Lam Painting Inc",
    "wof:placetype":"venue"
},
  "geometry": {"coordinates":[-84.361329,34.102349],"type":"Point"}
}