{
  "type": "Feature",
  "properties": {
    "iso:country":"US",
    "sg:address":"138 Mulberry Rd",
    "sg:city":"Winder",
    "sg:classifiers":[
        {
            "category":"Farming",
            "subcategory":"Farm",
            "type":"Manufacturing & Wholesale Goods"
        }
    ],
    "sg:phone":"+1 770 307 2024",
    "sg:postcode":"30680",
    "sg:province":"GA",
    "sg:tags":[
        "crop",
        "general"
    ],
    "wof:name":"Whiddon Farm 2",
    "wof:placetype":"venue"
},
  "geometry": {"coordinates":[-83.726057,34.051812],"type":"Point"}
}