{
  "type": "Feature",
  "properties": {
    "addr:full":"2930 Lawrenceville Suwanee Rd Suwanee GA 30024",
    "addr:housenumber":"2930",
    "addr:postcode":"30024",
    "addr:street":"Lawrenceville Suwanee Rd",
    "iso:country":"US",
    "sg:address":"2930 Lawrenceville Suwanee Rd",
    "sg:city":"Suwanee",
    "sg:classifiers":[
        {
            "category":"Restaurant",
            "type":"Food & Drink"
        }
    ],
    "sg:phone":"+1 770 932 2395",
    "sg:postcode":"30024",
    "sg:province":"GA",
    "wof:name":"Checkers Drive In",
    "wof:placetype":"venue"
},
  "geometry": {"coordinates":[-84.046088,34.027723],"type":"Point"}
}