{
  "type": "Feature",
  "properties": {
    "addr:full":"2131 Pleasant Hill Rd Duluth GA 30096",
    "addr:housenumber":"2131",
    "addr:postcode":"30096",
    "addr:street":"Pleasant Hill Rd",
    "iso:country":"US",
    "sg:address":"2131 Pleasant Hill Rd",
    "sg:city":"Duluth",
    "sg:classifiers":[
        {
            "category":"Insurance",
            "subcategory":"Insurance Agent",
            "type":"Services"
        }
    ],
    "sg:phone":"+1 770 623 0077",
    "sg:postcode":"30096",
    "sg:province":"GA",
    "wof:name":"Esquire Insurance Agencies",
    "wof:placetype":"venue"
},
  "geometry": {"coordinates":[-84.134147,33.95808],"type":"Point"}
}