{
  "type": "Feature",
  "properties": {
    "iso:country":"US",
    "sg:address":"7214 Meadow Gate Way",
    "sg:city":"Woodstock",
    "sg:classifiers":[
        {
            "category":"Building & Trades",
            "subcategory":"Construction",
            "type":"Services"
        }
    ],
    "sg:phone":"+1 770 516 2998",
    "sg:postcode":"30189",
    "sg:province":"GA",
    "sg:tags":[
        "course",
        "golf"
    ],
    "wof:name":"Fore Front Construction Corp",
    "wof:placetype":"venue"
},
  "geometry": {"coordinates":[-84.586074,34.14322],"type":"Point"}
}