{
  "type": "Feature",
  "properties": {
    "addr:full":"3879 Lake St Macon GA 31204",
    "addr:housenumber":"3879",
    "addr:postcode":"31204",
    "addr:street":"Lake St",
    "iso:country":"US",
    "sg:address":"3879 Lake St",
    "sg:city":"Macon",
    "sg:classifiers":[
        {
            "category":"Shopping",
            "subcategory":"Computers & Home Electronics",
            "type":"Retail Goods"
        }
    ],
    "sg:phone":"+1 478 755 0087",
    "sg:postcode":"31204",
    "sg:province":"GA",
    "sg:tags":[
        "equipment",
        "dealer"
    ],
    "wof:name":"Professional Computer Systems",
    "wof:placetype":"venue"
},
  "geometry": {"coordinates":[-83.684601,32.853299],"type":"Point"}
}