{
  "type": "Feature",
  "properties": {
    "iso:country":"US",
    "sg:address":"426 SW Broad St",
    "sg:city":"Fairburn",
    "sg:classifiers":[
        {
            "category":"Restaurant",
            "type":"Food & Drink"
        }
    ],
    "sg:phone":"+1 770 964 8181",
    "sg:postcode":"30213",
    "sg:province":"GA",
    "wof:name":"Cruse Inn",
    "wof:placetype":"venue"
},
  "geometry": {"coordinates":[-84.590142,33.558556],"type":"Point"}
}