{
  "type": "Feature",
  "properties": {
    "iso:country":"US",
    "sg:address":"112 Lanthier",
    "sg:city":"Winder",
    "sg:classifiers":[
        {
            "category":"Professional",
            "type":"Services"
        }
    ],
    "sg:phone":"+1 770 868 1283",
    "sg:postcode":"30680",
    "sg:province":"GA",
    "sg:tags":[
        "establishment"
    ],
    "wof:name":"SBP",
    "wof:placetype":"venue"
},
  "geometry": {"coordinates":[-83.722706,33.986052],"type":"Point"}
}