{
  "type": "Feature",
  "properties": {
    "addr:full":"3600 Dallas Hwy Marietta GA 30064",
    "addr:housenumber":"3600",
    "addr:postcode":"30064",
    "addr:street":"Dallas Hwy",
    "iso:country":"US",
    "sg:address":"3600 Dallas Hwy",
    "sg:city":"Marietta",
    "sg:classifiers":[
        {
            "category":"Personal",
            "subcategory":"Beauty Salon",
            "type":"Services"
        }
    ],
    "sg:phone":"+1 770 499 0514",
    "sg:postcode":"30064",
    "sg:province":"GA",
    "sg:tags":[
        "shop"
    ],
    "wof:name":"Kelley & Co Hair Salon Inc",
    "wof:placetype":"venue"
},
  "geometry": {"coordinates":[-84.657061,33.953798],"type":"Point"}
}