{
  "type": "Feature",
  "properties": {
    "addr:full":"14825 E Bluff Rd Alpharetta GA 30004",
    "addr:housenumber":"14825",
    "addr:postcode":"30004",
    "addr:street":"E Bluff Rd",
    "iso:country":"US",
    "sg:address":"14825 E Bluff Rd",
    "sg:city":"Alpharetta",
    "sg:classifiers":[
        {
            "category":"Home & Garden",
            "subcategory":"Building Materials",
            "type":"Retail Goods"
        }
    ],
    "sg:phone":"+1 678 867 7760",
    "sg:postcode":"30004",
    "sg:province":"GA",
    "wof:name":"Distinctive Building Materials",
    "wof:placetype":"venue"
},
  "geometry": {"coordinates":[-84.305352,34.140964],"type":"Point"}
}