{
  "type": "Feature",
  "properties": {
    "iso:country":"US",
    "sg:address":"498 Baxter St",
    "sg:city":"Athens",
    "sg:classifiers":[
        {
            "category":"Restaurant",
            "type":"Food & Drink"
        }
    ],
    "sg:menulink":"http://www.allmenus.com/ga/athens/80804-papa-johns-pizza/menu/",
    "sg:phone":"+1 706 543 7272",
    "sg:postcode":"30605",
    "sg:province":"GA",
    "sg:tags":[
        "american",
        "pizza"
    ],
    "wof:name":"Papa John's Pizza",
    "wof:placetype":"venue"
},
  "geometry": {"coordinates":[-83.383735,33.950091],"type":"Point"}
}