{
  "type": "Feature",
  "properties": {
    "addr:full":"8111 Bells Ferry Rd Canton GA 30114",
    "addr:housenumber":"8111",
    "addr:postcode":"30114",
    "addr:street":"Bells Ferry Rd",
    "iso:country":"US",
    "sg:address":"8111 Bells Ferry Rd",
    "sg:city":"Canton",
    "sg:classifiers":[
        {
            "category":"Home & Garden",
            "subcategory":"Furniture",
            "type":"Retail Goods"
        }
    ],
    "sg:phone":"+1 770 704 9904",
    "sg:postcode":"30114",
    "sg:province":"GA",
    "sg:website":"www.hillhouseonline.com",
    "wof:name":"Hill House",
    "wof:placetype":"venue"
},
  "geometry": {"coordinates":[-84.563281,34.17138],"type":"Point"}
}