{
  "type": "Feature",
  "properties": {
    "iso:country":"US",
    "sg:address":"610 Woodbrook Way",
    "sg:city":"Lawrenceville",
    "sg:classifiers":[
        {
            "category":"Professional",
            "type":"Services"
        }
    ],
    "sg:phone":"+1 770 237 9091",
    "sg:postcode":"30043",
    "sg:province":"GA",
    "wof:name":"R&R Designs",
    "wof:placetype":"venue"
},
  "geometry": {"coordinates":[-84.016248,34.034018],"type":"Point"}
}