{
  "type": "Feature",
  "properties": {
    "addr:full":"1230 Peachtree St NE Atlanta GA 30309",
    "addr:housenumber":"1230",
    "addr:postcode":"30309",
    "addr:street":"Peachtree St Ne",
    "iso:country":"US",
    "sg:address":"1230 Peachtree St NE",
    "sg:city":"Atlanta",
    "sg:classifiers":[
        {
            "category":"Professional",
            "subcategory":"Lawyer & Legal Services",
            "type":"Services"
        }
    ],
    "sg:phone":"+1 404 688 2600",
    "sg:postcode":"30309",
    "sg:province":"GA",
    "wof:name":"Haynes Jennifer Atty",
    "wof:placetype":"venue"
},
  "geometry": {"coordinates":[-84.384201,33.789101],"type":"Point"}
}