{
  "type": "Feature",
  "properties": {
    "iso:country":"US",
    "sg:address":"835 Vista Bluff Dr",
    "sg:city":"Duluth",
    "sg:classifiers":[
        {
            "category":"Health Services",
            "subcategory":"Dentist",
            "type":"Services"
        }
    ],
    "sg:phone":"+1 770 582 0325",
    "sg:postcode":"30097",
    "sg:province":"GA",
    "wof:name":"Mohme Edward H DMD",
    "wof:placetype":"venue"
},
  "geometry": {"coordinates":[-84.200699,33.992001],"type":"Point"}
}