{
  "type": "Feature",
  "properties": {
    "iso:country":"US",
    "sg:address":"562 Concord Dr",
    "sg:city":"Smyrna",
    "sg:classifiers":[
        {
            "category":"Health Services",
            "subcategory":"Clinic",
            "type":"Services"
        }
    ],
    "sg:phone":"+1 404 417 1760",
    "sg:postcode":"30082",
    "sg:province":"GA",
    "sg:tags":[
        "patient",
        "specialty",
        "out"
    ],
    "wof:name":"Smyrna Veterans ADM Clinic",
    "wof:placetype":"venue"
},
  "geometry": {"coordinates":[-84.533322,33.872216],"type":"Point"}
}