{
  "type": "Feature",
  "properties": {
    "iso:country":"US",
    "sg:address":"2304 Bouldercrest Rd SE",
    "sg:city":"Atlanta",
    "sg:classifiers":[
        {
            "category":"Professional",
            "subcategory":"Accounting & Tax Preparation",
            "type":"Services"
        }
    ],
    "sg:phone":"+1 404 212 1026",
    "sg:postcode":"30316",
    "sg:province":"GA",
    "sg:tags":[
        "return",
        "filing"
    ],
    "wof:name":"Epiphany Financial Svc",
    "wof:placetype":"venue"
},
  "geometry": {"coordinates":[-84.314656,33.688935],"type":"Point"}
}