{
  "type": "Feature",
  "properties": {
    "iso:country":"US",
    "sg:address":"202 Old Villanow Rd",
    "sg:city":"La Fayette",
    "sg:classifiers":[
        {
            "category":"Government",
            "subcategory":"Office",
            "type":"Public Place"
        }
    ],
    "sg:phone":"+1 706 638 5536",
    "sg:postcode":"30728",
    "sg:province":"GA",
    "sg:tags":[
        "state",
        "program"
    ],
    "wof:name":"Rehabilitation Service",
    "wof:placetype":"venue"
},
  "geometry": {"coordinates":[-85.198211,34.695683],"type":"Point"}
}