{
  "type": "Feature",
  "properties": {
    "addr:full":"830 Littlefield St Jesup GA 31545",
    "addr:housenumber":"830",
    "addr:postcode":"31545",
    "addr:street":"Littlefield St",
    "iso:country":"US",
    "sg:address":"830 Littlefield St",
    "sg:city":"Jesup",
    "sg:classifiers":[
        {
            "category":"Building & Trades",
            "subcategory":"Cleaning & Sanitation",
            "type":"Services"
        }
    ],
    "sg:phone":"+1 912 588 0528",
    "sg:postcode":"31545",
    "sg:province":"GA",
    "sg:tags":[
        "maintenance"
    ],
    "wof:name":"Ginas Commercial Cleaning",
    "wof:placetype":"venue"
},
  "geometry": {"coordinates":[-81.883554,31.584742],"type":"Point"}
}