{
  "type": "Feature",
  "properties": {
    "addr:full":"20 3rd Ave NW Cairo GA 39828",
    "addr:housenumber":"20",
    "addr:postcode":"39828",
    "addr:street":"3Rd Ave Nw",
    "iso:country":"US",
    "sg:address":"20 3rd Ave NW",
    "sg:city":"Cairo",
    "sg:classifiers":[
        {
            "category":"Personal",
            "subcategory":"Beauty Salon",
            "type":"Services"
        }
    ],
    "sg:phone":"+1 229 377 1115",
    "sg:postcode":"39828",
    "sg:province":"GA",
    "wof:name":"Cuttin Loose",
    "wof:placetype":"venue"
},
  "geometry": {"coordinates":[-84.208493,30.87911],"type":"Point"}
}