{
  "type": "Feature",
  "properties": {
    "iso:country":"US",
    "sg:address":"4885 Roswell Rd",
    "sg:city":"Atlanta",
    "sg:classifiers":[
        {
            "category":"Building & Trades",
            "subcategory":"Locksmith",
            "type":"Services"
        }
    ],
    "sg:phone":"+1 404 965 0327",
    "sg:postcode":"30342",
    "sg:province":"GA",
    "sg:tags":[
        "key"
    ],
    "wof:name":"24 Hour Emergency Locksmith",
    "wof:placetype":"venue"
},
  "geometry": {"coordinates":[-84.381398,33.888108],"type":"Point"}
}