{
  "type": "Feature",
  "properties": {
    "iso:country":"US",
    "sg:address":"2383 Old Lee Rd",
    "sg:city":"Lithia Springs",
    "sg:classifiers":[
        {
            "category":"Shopping",
            "type":"Retail Goods"
        }
    ],
    "sg:phone":"+1 770 949 2932",
    "sg:postcode":"30122",
    "sg:province":"GA",
    "sg:tags":[
        "merchandise"
    ],
    "wof:name":"Delor Accent & More",
    "wof:placetype":"venue"
},
  "geometry": {"coordinates":[-84.67175,33.739557],"type":"Point"}
}