{
  "type": "Feature",
  "properties": {
    "iso:country":"US",
    "sg:address":"1770 The Exchange SE",
    "sg:city":"Atlanta",
    "sg:classifiers":[
        {
            "category":"Professional",
            "subcategory":"Computer Services",
            "type":"Services"
        }
    ],
    "sg:phone":"+1 770 226 8089",
    "sg:postcode":"30339",
    "sg:province":"GA",
    "sg:tags":[
        "internet"
    ],
    "wof:name":"Build Net",
    "wof:placetype":"venue"
},
  "geometry": {"coordinates":[-84.480142,33.909306],"type":"Point"}
}