{
  "type": "Feature",
  "properties": {
    "addr:full":"1422 Old River Rd Dublin GA 31027",
    "addr:housenumber":"1422",
    "addr:postcode":"31027",
    "addr:street":"Old River Rd",
    "iso:country":"US",
    "sg:address":"1422 Old River Rd",
    "sg:city":"Dublin",
    "sg:classifiers":[
        {
            "category":"Retail",
            "subcategory":"Repair Shop",
            "type":"Services"
        }
    ],
    "sg:phone":"+1 478 272 6561",
    "sg:postcode":"31027",
    "sg:province":"GA",
    "wof:name":"Scarboroughs TV",
    "wof:placetype":"venue"
},
  "geometry": {"coordinates":[-82.835542,32.505442],"type":"Point"}
}