{
  "type": "Feature",
  "properties": {
    "iso:country":"US",
    "sg:address":"1375 New Hope Rd",
    "sg:city":"Lawrenceville",
    "sg:classifiers":[
        {
            "category":"Organizations",
            "subcategory":"Religious Organization",
            "type":"Services"
        }
    ],
    "sg:phone":"+1 770 963 9542",
    "sg:postcode":"30045",
    "sg:province":"GA",
    "sg:tags":[
        "church"
    ],
    "sg:website":"www.pgbaptistchurch.com",
    "wof:name":"Pleasant Grove Baptist Church",
    "wof:placetype":"venue"
},
  "geometry": {"coordinates":[-83.937258,33.929124],"type":"Point"}
}