{
  "type": "Feature",
  "properties": {
    "iso:country":"US",
    "sg:address":"1594 Mount Vernon Rd",
    "sg:city":"Atlanta",
    "sg:classifiers":[
        {
            "category":"Restaurant",
            "type":"Food & Drink"
        }
    ],
    "sg:phone":"+1 678 320 0223",
    "sg:postcode":"30338",
    "sg:province":"GA",
    "sg:tags":[
        "eating"
    ],
    "wof:name":"Togos Eatery",
    "wof:placetype":"venue"
},
  "geometry": {"coordinates":[-84.33523,33.945752],"type":"Point"}
}