{
  "type": "Feature",
  "properties": {
    "iso:country":"US",
    "sg:address":"106 E Force St",
    "sg:city":"Valdosta",
    "sg:classifiers":[
        {
            "category":"Professional",
            "subcategory":"Lawyer & Legal Services",
            "type":"Services"
        }
    ],
    "sg:phone":"+1 229 245 0064",
    "sg:postcode":"31601",
    "sg:province":"GA",
    "wof:name":"Mullis J Michael Atty At Law",
    "wof:placetype":"venue"
},
  "geometry": {"coordinates":[-83.28236200000001,30.841101],"type":"Point"}
}