{
  "type": "Feature",
  "properties": {
    "iso:country":"US",
    "sg:address":"1600 Pleasant Hill Rd",
    "sg:city":"Duluth",
    "sg:classifiers":[
        {
            "category":"Restaurant",
            "type":"Food & Drink"
        }
    ],
    "sg:phone":"+1 770 279 9144",
    "sg:postcode":"30096",
    "sg:province":"GA",
    "sg:tags":[
        "seafood"
    ],
    "wof:name":"Blue Marlin Seafood",
    "wof:placetype":"venue"
},
  "geometry": {"coordinates":[-84.1245,33.944469],"type":"Point"}
}