{
  "type": "Feature",
  "properties": {
    "addr:full":"2625 Piedmont Rd NE Atlanta GA 30324",
    "addr:housenumber":"2625",
    "addr:postcode":"30324",
    "addr:street":"Piedmont Rd Ne",
    "iso:country":"US",
    "sg:address":"2625 Piedmont Rd NE",
    "sg:city":"Atlanta",
    "sg:classifiers":[
        {
            "category":"Shopping",
            "subcategory":"Crafts & Fabrics",
            "type":"Retail Goods"
        }
    ],
    "sg:phone":"+1 404 266 0517",
    "sg:postcode":"30324",
    "sg:province":"GA",
    "sg:tags":[
        "shop",
        "sewing",
        "piece"
    ],
    "wof:name":"Hancock Fabrics 44",
    "wof:placetype":"venue"
},
  "geometry": {"coordinates":[-84.367143,33.825876],"type":"Point"}
}