{
  "type": "Feature",
  "properties": {
    "addr:full":"510 Industrial Way Cumming GA 30040",
    "addr:housenumber":"510",
    "addr:postcode":"30040",
    "addr:street":"Industrial Way",
    "iso:country":"US",
    "sg:address":"510 Industrial Way",
    "sg:city":"Cumming",
    "sg:classifiers":[
        {
            "category":"Autos & Motor Vehicles",
            "subcategory":"Automobile Sales",
            "type":"Retail Goods"
        }
    ],
    "sg:phone":"+1 678 965 5515",
    "sg:postcode":"30040",
    "sg:province":"GA",
    "sg:tags":[
        "new",
        "car"
    ],
    "wof:name":"Ep's Custom Cars",
    "wof:placetype":"venue"
},
  "geometry": {"coordinates":[-84.15007300000001,34.202036],"type":"Point"}
}