{
  "type": "Feature",
  "properties": {
    "iso:country":"US",
    "sg:address":"3005 Hallman Cir SW",
    "sg:city":"Marietta",
    "sg:classifiers":[
        {
            "category":"Professional",
            "subcategory":"Accounting & Tax Preparation",
            "type":"Services"
        }
    ],
    "sg:phone":"+1 770 419 3676",
    "sg:postcode":"30064",
    "sg:province":"GA",
    "sg:tags":[
        "return"
    ],
    "wof:name":"CPA Tax Advantage",
    "wof:placetype":"venue"
},
  "geometry": {"coordinates":[-84.64643,33.929712],"type":"Point"}
}