{
  "type": "Feature",
  "properties": {
    "addr:full":"831 Cairo Rd Camilla GA 31730",
    "addr:housenumber":"831",
    "addr:postcode":"31730",
    "addr:street":"Cairo Rd",
    "iso:country":"US",
    "sg:address":"831 Cairo Rd",
    "sg:city":"Camilla",
    "sg:classifiers":[
        {
            "category":"Place Of Worship",
            "type":"Public Place"
        }
    ],
    "sg:phone":"+1 229 336 0511",
    "sg:postcode":"31730",
    "sg:province":"GA",
    "sg:tags":[
        "church"
    ],
    "wof:name":"Southside Baptist Church",
    "wof:placetype":"venue"
},
  "geometry": {"coordinates":[-84.218613,31.210523],"type":"Point"}
}