{
  "type": "Feature",
  "properties": {
    "addr:full":"3105 Rich Ave Albany GA 31705",
    "addr:housenumber":"3105",
    "addr:postcode":"31705",
    "addr:street":"Rich Ave",
    "iso:country":"US",
    "sg:address":"3105 Rich Ave",
    "sg:city":"Albany",
    "sg:classifiers":[
        {
            "category":"Building & Trades",
            "subcategory":"Construction",
            "type":"Services"
        }
    ],
    "sg:phone":"+1 229 432 5447",
    "sg:postcode":"31705",
    "sg:province":"GA",
    "sg:tags":[
        "wallcoverings-installation",
        "wallpaper",
        "painting",
        "contractor"
    ],
    "wof:name":"York Painting",
    "wof:placetype":"venue"
},
  "geometry": {"coordinates":[-84.00842,31.626875],"type":"Point"}
}