{
  "type": "Feature",
  "properties": {
    "iso:country":"US",
    "sg:address":"109 Aviation Dr",
    "sg:city":"Thomaston",
    "sg:classifiers":[
        {
            "category":"Professional",
            "subcategory":"Business Services",
            "type":"Services"
        },
        {
            "category":"Building & Trades",
            "subcategory":"Plumbing",
            "type":"Services"
        }
    ],
    "sg:phone":"+1 706 647 1671",
    "sg:postcode":"30286",
    "sg:province":"GA",
    "sg:tags":[
        "septic"
    ],
    "wof:name":"Do Mor Construction Co",
    "wof:placetype":"venue"
},
  "geometry": {"coordinates":[-84.337389,32.937765],"type":"Point"}
}