{
  "type": "Feature",
  "properties": {
    "addr:full":"520 Wharton Cir SW Atlanta GA 30336",
    "addr:housenumber":"520",
    "addr:postcode":"30336",
    "addr:street":"Wharton Cir Sw",
    "iso:country":"US",
    "sg:address":"520 Wharton Cir SW",
    "sg:city":"Atlanta",
    "sg:classifiers":[
        {
            "category":"Professional",
            "subcategory":"Business Services",
            "type":"Services"
        }
    ],
    "sg:phone":"+1 404 627 2777",
    "sg:postcode":"30336",
    "sg:province":"GA",
    "sg:tags":[
        "repossessing"
    ],
    "wof:name":"Alsco Inc",
    "wof:placetype":"venue"
},
  "geometry": {"coordinates":[-84.552637,33.758556],"type":"Point"}
}