{
  "type": "Feature",
  "properties": {
    "iso:country":"US",
    "sg:address":"157 Comanchee Rd",
    "sg:city":"Brunswick",
    "sg:classifiers":[
        {
            "category":"Professional",
            "type":"Services"
        }
    ],
    "sg:phone":"+1 912 261 1399",
    "sg:postcode":"31525",
    "sg:province":"GA",
    "wof:name":"Masters Money Inc",
    "wof:placetype":"venue"
},
  "geometry": {"coordinates":[-81.46521799999999,31.308773],"type":"Point"}
}