{
  "type": "Feature",
  "properties": {
    "iso:country":"US",
    "sg:address":"1722 Crestridge Dr SE",
    "sg:city":"Marietta",
    "sg:classifiers":[
        {
            "category":"Building & Trades",
            "subcategory":"Construction",
            "type":"Services"
        }
    ],
    "sg:phone":"+1 770 579 1205",
    "sg:postcode":"30067",
    "sg:province":"GA",
    "sg:tags":[
        "house"
    ],
    "wof:name":"Young Construction",
    "wof:placetype":"venue"
},
  "geometry": {"coordinates":[-84.503652,33.94351],"type":"Point"}
}