{
  "type": "Feature",
  "properties": {
    "addr:full":"121 David Dr Thomaston GA 30286",
    "addr:housenumber":"121",
    "addr:postcode":"30286",
    "addr:street":"David Dr",
    "iso:country":"US",
    "sg:address":"121 David Dr",
    "sg:city":"Thomaston",
    "sg:classifiers":[
        {
            "category":"Wholesale",
            "subcategory":"Non-durable Goods",
            "type":"Manufacturing & Wholesale Goods"
        },
        {
            "category":"Professional",
            "subcategory":"Business Services",
            "type":"Services"
        }
    ],
    "sg:phone":"+1 706 648 6461",
    "sg:postcode":"30286",
    "sg:province":"GA",
    "sg:tags":[
        "broker",
        "merchandise",
        "merchandise-wholesale"
    ],
    "wof:name":"Ron Coats Assoc",
    "wof:placetype":"venue"
},
  "geometry": {"coordinates":[-84.326519,32.934598],"type":"Point"}
}