{
  "type": "Feature",
  "properties": {
    "addr:full":"1116 Highway 20 81 Mcdonough GA 30253",
    "addr:housenumber":"1116;81",
    "addr:postcode":"30253",
    "addr:street":"Highway 20",
    "iso:country":"US",
    "sg:address":"1116 Highway 20 81",
    "sg:city":"Mcdonough",
    "sg:classifiers":[
        {
            "category":"Restaurant",
            "type":"Food & Drink"
        }
    ],
    "sg:menulink":"http://www.allmenus.com/ga/mcdonough/158339-arbys/menu/",
    "sg:phone":"+1 404 957 8088",
    "sg:postcode":"30253",
    "sg:province":"GA",
    "sg:tags":[
        "burger",
        "american"
    ],
    "wof:name":"Arby's",
    "wof:placetype":"venue"
},
  "geometry": {"coordinates":[-84.17994,33.42943],"type":"Point"}
}