{
  "type": "Feature",
  "properties": {
    "iso:country":"US",
    "sg:address":"1054 Camp Creek Dr SW",
    "sg:city":"Lilburn",
    "sg:classifiers":[
        {
            "category":"Manufacturing",
            "subcategory":"Printing",
            "type":"Manufacturing & Wholesale Goods"
        }
    ],
    "sg:phone":"+1 770 381 3628",
    "sg:postcode":"30047",
    "sg:province":"GA",
    "sg:tags":[
        "periodical"
    ],
    "wof:name":"Jive Magazine",
    "wof:placetype":"venue"
},
  "geometry": {"coordinates":[-84.117508,33.854043],"type":"Point"}
}