{
  "type": "Feature",
  "properties": {
    "iso:country":"US",
    "sg:address":"1912 Hiram Douglasville Hwy",
    "sg:city":"Hiram",
    "sg:classifiers":[
        {
            "category":"Retail",
            "subcategory":"Auto Repair",
            "type":"Services"
        }
    ],
    "sg:phone":"+1 678 567 1656",
    "sg:postcode":"30141",
    "sg:province":"GA",
    "sg:tags":[
        "automobile",
        "testing",
        "emission"
    ],
    "wof:name":"A Quick Emissions",
    "wof:placetype":"venue"
},
  "geometry": {"coordinates":[-84.764605,33.870976],"type":"Point"}
}