{
  "type": "Feature",
  "properties": {
    "iso:country":"US",
    "sg:address":"600 Kilcrease Rd",
    "sg:city":"Auburn",
    "sg:classifiers":[
        {
            "category":"Building & Trades",
            "subcategory":"Construction",
            "type":"Services"
        }
    ],
    "sg:phone":"+1 770 867 6576",
    "sg:postcode":"30011",
    "sg:province":"GA",
    "wof:name":"Grading Mathis & Hauling",
    "wof:placetype":"venue"
},
  "geometry": {"coordinates":[-83.822047,33.980887],"type":"Point"}
}