{
  "type": "Feature",
  "properties": {
    "addr:full":"230 Fuller Rd Athens GA 30607",
    "addr:housenumber":"230",
    "addr:postcode":"30607",
    "addr:street":"Fuller Rd",
    "iso:country":"US",
    "sg:address":"230 Fuller Rd",
    "sg:city":"Athens",
    "sg:classifiers":[
        {
            "category":"Building & Trades",
            "subcategory":"Plumbing",
            "type":"Services"
        }
    ],
    "sg:phone":"+1 706 353 0080",
    "sg:postcode":"30607",
    "sg:province":"GA",
    "sg:tags":[
        "repair",
        "contractor",
        "re"
    ],
    "wof:name":"Days Plumbing Sewer & Drain S",
    "wof:placetype":"venue"
},
  "geometry": {"coordinates":[-83.47476899999999,34.006493],"type":"Point"}
}