{
  "type": "Feature",
  "properties": {
    "addr:full":"2012 Eatonton Rd Madison GA 30650",
    "addr:housenumber":"2012",
    "addr:postcode":"30650",
    "addr:street":"Eatonton Rd",
    "iso:country":"US",
    "sg:address":"2012 Eatonton Rd",
    "sg:city":"Madison",
    "sg:classifiers":[
        {
            "category":"Travel",
            "subcategory":"Hotels & Motels",
            "type":"Entertainment"
        }
    ],
    "sg:phone":"+1 706 342 9003",
    "sg:postcode":"30650",
    "sg:province":"GA",
    "sg:tags":[
        "corporate",
        "lodging"
    ],
    "sg:website":"http://www.madisonga.hamptoninn.com",
    "wof:name":"Hampton Inn",
    "wof:placetype":"venue"
},
  "geometry": {"coordinates":[-83.475398,33.557499],"type":"Point"}
}