{
  "type": "Feature",
  "properties": {
    "iso:country":"US",
    "sg:address":"767 Main St",
    "sg:city":"Stone Mountain",
    "sg:classifiers":[
        {
            "category":"Manufacturing",
            "subcategory":"Furniture",
            "type":"Manufacturing & Wholesale Goods"
        }
    ],
    "sg:phone":"+1 770 469 8208",
    "sg:postcode":"30083",
    "sg:province":"GA",
    "sg:tags":[
        "material",
        "fixture",
        "display"
    ],
    "wof:name":"Joseph Hurt Studio Inc",
    "wof:placetype":"venue"
},
  "geometry": {"coordinates":[-84.169307,33.800232],"type":"Point"}
}