{
  "type": "Feature",
  "properties": {
    "iso:country":"US",
    "sg:address":"5052 Womack Ave NW",
    "sg:city":"Acworth",
    "sg:classifiers":[
        {
            "category":"Health Services",
            "subcategory":"Nursing And Care Facility",
            "type":"Services"
        },
        {
            "category":"Social Services",
            "subcategory":"Retirement Home",
            "type":"Services"
        }
    ],
    "sg:phone":"+1 770 529 3754",
    "sg:postcode":"30101",
    "sg:province":"GA",
    "sg:tags":[
        "personal",
        "convalescent"
    ],
    "wof:name":"Life Well Lived Services, Inc.",
    "wof:placetype":"venue"
},
  "geometry": {"coordinates":[-84.699045,34.040482],"type":"Point"}
}