{
  "type": "Feature",
  "properties": {
    "iso:country":"US",
    "sg:address":"314 Sassafras Ln SW",
    "sg:city":"Lilburn",
    "sg:classifiers":[
        {
            "category":"Professional",
            "subcategory":"Research",
            "type":"Services"
        }
    ],
    "sg:phone":"+1 770 923 7705",
    "sg:postcode":"30047",
    "sg:province":"GA",
    "sg:tags":[
        "organization",
        "noncommercial"
    ],
    "wof:name":"Linda D Moneyham",
    "wof:placetype":"venue"
},
  "geometry": {"coordinates":[-84.155991,33.861339],"type":"Point"}
}