{
  "type": "Feature",
  "properties": {
    "iso:country":"US",
    "sg:address":"1680 Mulkey Rd # E",
    "sg:city":"Austell",
    "sg:classifiers":[
        {
            "category":"Health Services",
            "subcategory":"Doctor",
            "type":"Services"
        }
    ],
    "sg:phone":"+1 770 941 5107",
    "sg:postcode":"30106",
    "sg:province":"GA",
    "sg:tags":[
        "physician",
        "surgeon"
    ],
    "wof:name":"Kaiser, Richard R, Md - Children's Medical Ctr Pa",
    "wof:placetype":"venue"
},
  "geometry": {"coordinates":[-84.60319,33.858399],"type":"Point"}
}