{
  "type": "Feature",
  "properties": {
    "iso:country":"US",
    "sg:address":"6 Old Rockmart Rd SE",
    "sg:city":"Lindale",
    "sg:classifiers":[
        {
            "category":"Organizations",
            "subcategory":"Religious Organization",
            "type":"Services"
        }
    ],
    "sg:phone":"+1 706 234 6862",
    "sg:postcode":"30147",
    "sg:province":"GA",
    "sg:tags":[
        "church"
    ],
    "wof:name":"Silver Creek Presbyterian Chr",
    "wof:placetype":"venue"
},
  "geometry": {"coordinates":[-85.166014,34.190154],"type":"Point"}
}