{
  "type": "Feature",
  "properties": {
    "addr:full":"330 West Ave Cedartown GA 30125",
    "addr:housenumber":"330",
    "addr:postcode":"30125",
    "addr:street":"West Ave",
    "iso:country":"US",
    "sg:address":"330 West Ave",
    "sg:city":"Cedartown",
    "sg:classifiers":[
        {
            "category":"Education",
            "subcategory":"School",
            "type":"Public Place"
        }
    ],
    "sg:phone":"+1 770 748 4078",
    "sg:postcode":"30125",
    "sg:province":"GA",
    "wof:name":"Purks Middle",
    "wof:placetype":"venue"
},
  "geometry": {"coordinates":[-85.262171,34.011258],"type":"Point"}
}