{
  "type": "Feature",
  "properties": {
    "addr:full":"2102 Creswell St Waycross GA 31503",
    "addr:housenumber":"2102",
    "addr:postcode":"31503",
    "addr:street":"Creswell St",
    "iso:country":"US",
    "sg:address":"2102 Creswell St",
    "sg:city":"Waycross",
    "sg:classifiers":[
        {
            "category":"Retail",
            "subcategory":"Repair Shop",
            "type":"Services"
        }
    ],
    "sg:phone":"+1 912 285 1221",
    "sg:postcode":"31503",
    "sg:province":"GA",
    "sg:tags":[
        "electrical"
    ],
    "wof:name":"Davis Appliance Repair",
    "wof:placetype":"venue"
},
  "geometry": {"coordinates":[-82.36219699999999,31.187616],"type":"Point"}
}