{
  "type": "Feature",
  "properties": {
    "iso:country":"US",
    "sg:address":"4840 Roswell Rd",
    "sg:city":"Atlanta",
    "sg:classifiers":[
        {
            "category":"Health Services",
            "subcategory":"Doctor",
            "type":"Services"
        },
        {
            "category":"Health Services",
            "subcategory":"Clinic",
            "type":"Services"
        },
        {
            "category":"Health Services",
            "subcategory":"Chiropractor",
            "type":"Services"
        }
    ],
    "sg:phone":"+1 404 843 3040",
    "sg:postcode":"30342",
    "sg:province":"GA",
    "sg:tags":[
        "physician",
        "medical",
        "surgeon",
        "chiropractic"
    ],
    "wof:name":"Samuels Chiropractic Health Clinic",
    "wof:placetype":"venue"
},
  "geometry": {"coordinates":[-84.38164999999999,33.886251],"type":"Point"}
}