{
  "type": "Feature",
  "properties": {
    "iso:country":"US",
    "sg:address":"355 Lori Ln",
    "sg:city":"Canton",
    "sg:classifiers":[
        {
            "category":"Building & Trades",
            "subcategory":"Construction",
            "type":"Services"
        }
    ],
    "sg:phone":"+1 770 345 6898",
    "sg:postcode":"30114",
    "sg:province":"GA",
    "sg:tags":[
        "hanging",
        "contractor"
    ],
    "wof:name":"Due West Painting",
    "wof:placetype":"venue"
},
  "geometry": {"coordinates":[-84.514602,34.19374],"type":"Point"}
}