{
  "type": "Feature",
  "properties": {
    "iso:country":"US",
    "sg:address":"515 Hussamy Ln",
    "sg:city":"Fairburn",
    "sg:classifiers":[
        {
            "category":"Organizations",
            "subcategory":"Religious Organization",
            "type":"Services"
        }
    ],
    "sg:phone":"+1 770 964 0656",
    "sg:postcode":"30213",
    "sg:province":"GA",
    "wof:name":"Holy Sprits Gathering Together",
    "wof:placetype":"venue"
},
  "geometry": {"coordinates":[-84.50487099999999,33.565932],"type":"Point"}
}