{
  "type": "Feature",
  "properties": {
    "iso:country":"US",
    "sg:address":"4518 Windsor Dr SW",
    "sg:city":"Smyrna",
    "sg:classifiers":[
        {
            "category":"Professional",
            "subcategory":"Lawyer & Legal Services",
            "type":"Services"
        }
    ],
    "sg:phone":"+1 770 434 0762",
    "sg:postcode":"30082",
    "sg:province":"GA",
    "wof:name":"Davis Douglas Roy Atty",
    "wof:placetype":"venue"
},
  "geometry": {"coordinates":[-84.566299,33.844002],"type":"Point"}
}