{
  "type": "Feature",
  "properties": {
    "iso:country":"US",
    "sg:address":"297 Lowery Rd",
    "sg:city":"Fayetteville",
    "sg:classifiers":[
        {
            "category":"Building & Trades",
            "subcategory":"Construction",
            "type":"Services"
        }
    ],
    "sg:phone":"+1 770 716 2559",
    "sg:postcode":"30215",
    "sg:province":"GA",
    "sg:tags":[
        "pressure",
        "washing"
    ],
    "wof:name":"Taylor Pressure Washing",
    "wof:placetype":"venue"
},
  "geometry": {"coordinates":[-84.41561,33.315961],"type":"Point"}
}