{
  "type": "Feature",
  "properties": {
    "iso:country":"US",
    "sg:address":"21 Lorwood Dr",
    "sg:city":"Savannah",
    "sg:classifiers":[
        {
            "category":"Organizations",
            "subcategory":"Religious Organization",
            "type":"Services"
        }
    ],
    "sg:phone":"+1 912 921 0805",
    "sg:postcode":"31406",
    "sg:province":"GA",
    "sg:tags":[
        "church"
    ],
    "wof:name":"Zion White Bluff Baptst Church",
    "wof:placetype":"venue"
},
  "geometry": {"coordinates":[-81.12575699999999,31.986523],"type":"Point"}
}