{
  "type": "Feature",
  "properties": {
    "addr:full":"1703 Brookgreen Way Acworth GA 30101",
    "addr:housenumber":"1703",
    "addr:postcode":"30101",
    "addr:street":"Brookgreen Way",
    "iso:country":"US",
    "sg:address":"1703 Brookgreen Way",
    "sg:city":"Acworth",
    "sg:classifiers":[
        {
            "category":"Professional",
            "subcategory":"Management & Consulting",
            "type":"Services"
        }
    ],
    "sg:phone":"+1 770 425 0476",
    "sg:postcode":"30101",
    "sg:province":"GA",
    "wof:name":"Mike Berry Seminars Inc",
    "wof:placetype":"venue"
},
  "geometry": {"coordinates":[-84.71381700000001,33.996728],"type":"Point"}
}