{
  "type": "Feature",
  "properties": {
    "iso:country":"US",
    "sg:address":"521 Augusta Rd",
    "sg:city":"North Augusta",
    "sg:classifiers":[
        {
            "category":"Banks & Credit Unions",
            "subcategory":"Bank",
            "type":"Services"
        }
    ],
    "sg:phone":"+1 803 278 4290",
    "sg:postcode":"29822",
    "sg:province":"SC",
    "sg:tags":[
        "personal",
        "loan",
        "institution"
    ],
    "wof:name":"Security Finance Corp",
    "wof:placetype":"venue"
},
  "geometry": {"coordinates":[-81.892045,33.496712],"type":"Point"}
}