{
  "type": "Feature",
  "properties": {
    "iso:country":"US",
    "sg:address":"2700 Ledo Rd",
    "sg:city":"Albany",
    "sg:classifiers":[
        {
            "category":"Food & Beverages",
            "subcategory":"Liquor & Beverages",
            "type":"Retail Goods"
        }
    ],
    "sg:phone":"+1 229 883 3109",
    "sg:postcode":"31707",
    "sg:province":"GA",
    "sg:tags":[
        "alcoholic"
    ],
    "wof:name":"Moonshine Shack",
    "wof:placetype":"venue"
},
  "geometry": {"coordinates":[-84.210279,31.622534],"type":"Point"}
}