{
  "type": "Feature",
  "properties": {
    "addr:full":"8000 Mall Pkwy Lithonia GA 30038",
    "addr:housenumber":"8000",
    "addr:postcode":"30038",
    "addr:street":"Mall Pkwy",
    "iso:country":"US",
    "sg:address":"8000 Mall Pkwy",
    "sg:city":"Lithonia",
    "sg:classifiers":[
        {
            "category":"Shopping",
            "subcategory":"Books",
            "type":"Retail Goods"
        }
    ],
    "sg:phone":"+1 678 526 2550",
    "sg:postcode":"30038",
    "sg:province":"GA",
    "sg:tags":[
        "store"
    ],
    "sg:website":"http://www.borders.com",
    "wof:name":"Borders",
    "wof:placetype":"venue"
},
  "geometry": {"coordinates":[-84.097734,33.693985],"type":"Point"}
}