{
  "type": "Feature",
  "properties": {
    "iso:country":"US",
    "sg:address":"1247 Greenridge Ave",
    "sg:city":"Lithonia",
    "sg:classifiers":[
        {
            "category":"Utilities",
            "subcategory":"Water",
            "type":"Services"
        },
        {
            "category":"Building & Trades",
            "subcategory":"Cleaning & Sanitation",
            "type":"Services"
        },
        {
            "category":"Retail",
            "subcategory":"Repair Shop",
            "type":"Services"
        },
        {
            "category":"Retail",
            "subcategory":"Laundry & Dry Cleaning",
            "type":"Services"
        },
        {
            "category":"Home & Garden",
            "subcategory":"Carpets & Floor Coverings",
            "type":"Retail Goods"
        }
    ],
    "sg:phone":"+1 404 671 9249",
    "sg:postcode":"30058",
    "sg:province":"GA",
    "sg:tags":[
        "cleaner",
        "emergency",
        "cleaners-water",
        "rug",
        "damage",
        "extraction",
        "remediation",
        "mold"
    ],
    "wof:name":"24 Hour Carpet Care",
    "wof:placetype":"venue"
},
  "geometry": {"coordinates":[-84.153457,33.757226],"type":"Point"}
}