{
  "type": "Feature",
  "properties": {
    "iso:country":"US",
    "sg:address":"230 Spring St NW",
    "sg:city":"Atlanta",
    "sg:classifiers":[
        {
            "category":"Home & Garden",
            "subcategory":"Garden Supply",
            "type":"Retail Goods"
        }
    ],
    "sg:phone":"+1 404 577 1900",
    "sg:postcode":"30303",
    "sg:province":"GA",
    "sg:tags":[
        "electrical",
        "mfg"
    ],
    "wof:name":"Gki",
    "wof:placetype":"venue"
},
  "geometry": {"coordinates":[-84.38915,33.759785],"type":"Point"}
}