{
  "type": "Feature",
  "properties": {
    "addr:full":"5490 Chamblee Dunwoody Rd Atlanta GA 30338",
    "addr:housenumber":"5490",
    "addr:postcode":"30338",
    "addr:street":"Chamblee Dunwoody Rd",
    "iso:country":"US",
    "sg:address":"5490 Chamblee Dunwoody Rd",
    "sg:city":"Atlanta",
    "sg:classifiers":[
        {
            "category":"Building & Trades",
            "subcategory":"Construction",
            "type":"Services"
        }
    ],
    "sg:phone":"+1 404 329 8773",
    "sg:postcode":"30338",
    "sg:province":"GA",
    "sg:tags":[
        "systems-repairing",
        "specialty",
        "heating",
        "contractor",
        "equipment"
    ],
    "wof:name":"A A Incredible Heat And Air",
    "wof:placetype":"venue"
},
  "geometry": {"coordinates":[-84.33551799999999,33.947762],"type":"Point"}
}