{
  "type": "Feature",
  "properties": {
    "addr:full":"3177 Clairwood Ter Atlanta GA 30341",
    "addr:housenumber":"3177",
    "addr:postcode":"30341",
    "addr:street":"Clairwood Ter",
    "iso:country":"US",
    "sg:address":"3177 Clairwood Ter",
    "sg:city":"Atlanta",
    "sg:classifiers":[
        {
            "category":"Organizations",
            "subcategory":"Religious Organization",
            "type":"Services"
        }
    ],
    "sg:phone":"+1 770 451 0200",
    "sg:postcode":"30341",
    "sg:province":"GA",
    "sg:tags":[
        "church"
    ],
    "wof:name":"Good Faith",
    "wof:placetype":"venue"
},
  "geometry": {"coordinates":[-84.310715,33.882711],"type":"Point"}
}