{
  "type": "Feature",
  "properties": {
    "addr:full":"527 Irwin St NE Atlanta GA 30312",
    "addr:housenumber":"527",
    "addr:postcode":"30312",
    "addr:street":"Irwin St Ne",
    "iso:country":"US",
    "sg:address":"527 Irwin St NE",
    "sg:city":"Atlanta",
    "sg:classifiers":[
        {
            "category":"Personal",
            "subcategory":"Beauty Salon",
            "type":"Services"
        }
    ],
    "sg:phone":"+1 678 681 0080",
    "sg:postcode":"30312",
    "sg:province":"GA",
    "sg:tags":[
        "hair"
    ],
    "wof:name":"Dynamic Hair",
    "wof:placetype":"venue"
},
  "geometry": {"coordinates":[-84.370138,33.757486],"type":"Point"}
}