{
  "type": "Feature",
  "properties": {
    "addr:full":"253 S Fry St Valdosta GA 31601",
    "addr:housenumber":"253",
    "addr:postcode":"31601",
    "addr:street":"S Fry St",
    "iso:country":"US",
    "sg:address":"253 S Fry St",
    "sg:city":"Valdosta",
    "sg:classifiers":[
        {
            "category":"Home & Garden",
            "subcategory":"Building Materials",
            "type":"Retail Goods"
        },
        {
            "category":"Building & Trades",
            "subcategory":"Construction",
            "type":"Services"
        }
    ],
    "sg:phone":"+1 229 244 1100",
    "sg:postcode":"31601",
    "sg:province":"GA",
    "sg:tags":[
        "concrete",
        "grading",
        "paving",
        "contractor"
    ],
    "sg:website":"http://southlandgeneralcontractors.com",
    "wof:name":"Southland General Contractors",
    "wof:placetype":"venue"
},
  "geometry": {"coordinates":[-83.269211,30.831004],"type":"Point"}
}