{
  "type": "Feature",
  "properties": {
    "addr:full":"1844 Junction 77 Hartwell GA 30643",
    "addr:housenumber":"1844;77",
    "addr:postcode":"30643",
    "addr:street":"Junction",
    "iso:country":"US",
    "sg:address":"1844 Junction 77",
    "sg:city":"Hartwell",
    "sg:classifiers":[
        {
            "category":"Building & Trades",
            "subcategory":"Plumbing",
            "type":"Services"
        }
    ],
    "sg:phone":"+1 706 356 2851",
    "sg:postcode":"30643",
    "sg:province":"GA",
    "sg:tags":[
        "contractor"
    ],
    "wof:name":"Dyar Mechanical LLC",
    "wof:placetype":"venue"
},
  "geometry": {"coordinates":[-83.013965,34.412558],"type":"Point"}
}