{
  "type": "Feature",
  "properties": {
    "iso:country":"US",
    "sg:address":"3379 Peachtree Road NE",
    "sg:city":"Atlanta",
    "sg:classifiers":[
        {
            "category":"Professional",
            "subcategory":"Lawyer & Legal Services",
            "type":"Services"
        }
    ],
    "sg:phone":"+1 404 814 0200",
    "sg:postcode":"30326",
    "sg:province":"GA",
    "sg:website":"www.wmolaw.com",
    "wof:name":"Lavinger Kathleen Atty",
    "wof:placetype":"venue"
},
  "geometry": {"coordinates":[-84.36637500000001,33.848665],"type":"Point"}
}