{
  "type": "Feature",
  "properties": {
    "addr:full":"1640 Powers Ferry Rd SE Marietta GA 30067",
    "addr:housenumber":"1640",
    "addr:postcode":"30067",
    "addr:street":"Powers Ferry Rd Se",
    "iso:country":"US",
    "sg:address":"1640 Powers Ferry Rd SE",
    "sg:city":"Marietta",
    "sg:classifiers":[
        {
            "category":"Health Services",
            "subcategory":"Doctor",
            "type":"Services"
        }
    ],
    "sg:phone":"+1 678 384 5904",
    "sg:postcode":"30067",
    "sg:province":"GA",
    "sg:tags":[
        "physician",
        "surgeon",
        "surgeons",
        "psychiatry"
    ],
    "wof:name":"Center For Attention And Psychiatry",
    "wof:placetype":"venue"
},
  "geometry": {"coordinates":[-84.46534,33.913849],"type":"Point"}
}