{
  "type": "Feature",
  "properties": {
    "addr:full":"707 Whitlock Ave SW Marietta GA 30064",
    "addr:housenumber":"707",
    "addr:postcode":"30064",
    "addr:street":"Whitlock Ave Sw",
    "iso:country":"US",
    "sg:address":"707 Whitlock Ave SW",
    "sg:city":"Marietta",
    "sg:classifiers":[
        {
            "category":"Health Services",
            "subcategory":"Doctor",
            "type":"Services"
        }
    ],
    "sg:phone":"+1 770 424 7525",
    "sg:postcode":"30064",
    "sg:province":"GA",
    "sg:tags":[
        "surgeon",
        "oral"
    ],
    "sg:website":"www.hutsondr.com",
    "wof:name":"Hutson James H Jr DDS",
    "wof:placetype":"venue"
},
  "geometry": {"coordinates":[-84.572244,33.951914],"type":"Point"}
}