{
  "type": "Feature",
  "properties": {
    "addr:full":"139 Ridgeview Trl SE Cartersville GA 30120",
    "addr:housenumber":"139",
    "addr:postcode":"30120",
    "addr:street":"Ridgeview Trl Se",
    "iso:country":"US",
    "sg:address":"139 Ridgeview Trl SE",
    "sg:city":"Cartersville",
    "sg:classifiers":[
        {
            "category":"Real Estate",
            "subcategory":"Real Estate Services",
            "type":"Services"
        },
        {
            "category":"Real Estate",
            "subcategory":"Real Estate Agent",
            "type":"Services"
        }
    ],
    "sg:phone":"+1 770 386 1834",
    "sg:postcode":"30120",
    "sg:province":"GA",
    "sg:tags":[
        "buyer",
        "broker"
    ],
    "wof:name":"Tmf Enterprises Inc",
    "wof:placetype":"venue"
},
  "geometry": {"coordinates":[-84.747522,34.098259],"type":"Point"}
}