{
  "type": "Feature",
  "properties": {
    "addr:full":"500 W 9th St Chickamauga GA 30707",
    "addr:housenumber":"500",
    "addr:postcode":"30707",
    "addr:street":"W 9Th St",
    "iso:country":"US",
    "sg:address":"500 W 9th St",
    "sg:city":"Chickamauga",
    "sg:classifiers":[
        {
            "category":"Retail",
            "subcategory":"Auto Repair",
            "type":"Services"
        }
    ],
    "sg:phone":"+1 706 375 7907",
    "sg:postcode":"30707",
    "sg:province":"GA",
    "sg:tags":[
        "brake",
        "balancing",
        "wheels-aligning"
    ],
    "wof:name":"Chickamauga Auto Center",
    "wof:placetype":"venue"
},
  "geometry": {"coordinates":[-85.290314,34.87291],"type":"Point"}
}