{
  "type": "Feature",
  "properties": {
    "iso:country":"US",
    "sg:address":"2502 Deans Bridge Rd",
    "sg:city":"Augusta",
    "sg:classifiers":[
        {
            "category":"Social Services",
            "subcategory":"Child Care",
            "type":"Services"
        }
    ],
    "sg:phone":"+1 706 736 0030",
    "sg:postcode":"30906",
    "sg:province":"GA",
    "wof:name":"A Child's Dream Child Care",
    "wof:placetype":"venue"
},
  "geometry": {"coordinates":[-82.015179,33.445106],"type":"Point"}
}