{
  "type": "Feature",
  "properties": {
    "iso:country":"US",
    "sg:address":"3025 Windward Plz",
    "sg:city":"Alpharetta",
    "sg:classifiers":[
        {
            "category":"Insurance",
            "subcategory":"Health Insurance",
            "type":"Services"
        }
    ],
    "sg:phone":"+1 770 346 0170",
    "sg:postcode":"30005",
    "sg:province":"GA",
    "sg:tags":[
        "reinsurance",
        "company"
    ],
    "wof:name":"Odyssey Amer Reinsurance Corp",
    "wof:placetype":"venue"
},
  "geometry": {"coordinates":[-84.239941,34.09323],"type":"Point"}
}