{
  "type": "Feature",
  "properties": {
    "iso:country":"US",
    "sg:address":"25 Atlanta St SE Ste D",
    "sg:city":"Marietta",
    "sg:classifiers":[
        {
            "category":"Professional",
            "subcategory":"Lawyer & Legal Services",
            "type":"Services"
        }
    ],
    "sg:phone":"+1 770 794 0399",
    "sg:postcode":"30060",
    "sg:province":"GA",
    "sg:tags":[
        "attorney",
        "practice"
    ],
    "wof:name":"Samuel Morrison Law",
    "wof:placetype":"venue"
},
  "geometry": {"coordinates":[-84.548855,33.951623],"type":"Point"}
}