{
  "type": "Feature",
  "properties": {
    "addr:full":"252 1st St SE Cairo GA 39828",
    "addr:housenumber":"252",
    "addr:postcode":"39828",
    "addr:street":"1St St Se",
    "iso:country":"US",
    "sg:address":"252 1st St SE",
    "sg:city":"Cairo",
    "sg:classifiers":[
        {
            "category":"Organizations",
            "subcategory":"Membership Organization",
            "type":"Services"
        }
    ],
    "sg:phone":"+1 229 377 5785",
    "sg:postcode":"39828",
    "sg:province":"GA",
    "wof:name":"Womans Club of Cairo Geor",
    "wof:placetype":"venue"
},
  "geometry": {"coordinates":[-84.207302,30.874578],"type":"Point"}
}