{
  "type": "Feature",
  "properties": {
    "iso:country":"US",
    "sg:address":"2514 Skeenah Gap Rd",
    "sg:city":"Suches",
    "sg:classifiers":[
        {
            "category":"Real Estate",
            "subcategory":"Real Estate Agent",
            "type":"Services"
        }
    ],
    "sg:phone":"+1 706 838 0146",
    "sg:postcode":"30572",
    "sg:province":"GA",
    "wof:name":"Sticks & Stones Log Hm & Rlty",
    "wof:placetype":"venue"
},
  "geometry": {"coordinates":[-84.15892700000001,34.797202],"type":"Point"}
}