{
  "type": "Feature",
  "properties": {
    "iso:country":"US",
    "sg:address":"170 11th St NE",
    "sg:city":"Atlanta",
    "sg:classifiers":[
        {
            "category":"Food & Beverages",
            "subcategory":"Groceries & Convenience Stores",
            "type":"Retail Goods"
        }
    ],
    "sg:phone":"+1 404 874 9890",
    "sg:postcode":"30309",
    "sg:province":"GA",
    "wof:name":"ATL Gay & Lesbian Center",
    "wof:placetype":"venue"
},
  "geometry": {"coordinates":[-84.379938,33.783071],"type":"Point"}
}