{
  "type": "Feature",
  "properties": {
    "addr:full":"29 McEntire St Carnesville GA 30521",
    "addr:housenumber":"29",
    "addr:postcode":"30521",
    "addr:street":"Mcentire St",
    "iso:country":"US",
    "sg:address":"29 McEntire St",
    "sg:city":"Carnesville",
    "sg:classifiers":[
        {
            "category":"Social Services",
            "subcategory":"Adult Care",
            "type":"Services"
        }
    ],
    "sg:phone":"+1 706 384 2315",
    "sg:postcode":"30521",
    "sg:province":"GA",
    "sg:tags":[
        "home",
        "group"
    ],
    "wof:name":"West Avenue Homes",
    "wof:placetype":"venue"
},
  "geometry": {"coordinates":[-83.232365,34.366762],"type":"Point"}
}