{
  "type": "Feature",
  "properties": {
    "iso:country":"US",
    "sg:address":"2970 Peachtree Rd NW",
    "sg:city":"Atlanta",
    "sg:classifiers":[
        {
            "category":"Structure",
            "subcategory":"Warehouse",
            "type":"Public Place"
        },
        {
            "category":"Retail",
            "subcategory":"Storage",
            "type":"Services"
        }
    ],
    "sg:phone":"+1 404 233 4774",
    "sg:postcode":"30305",
    "sg:province":"GA",
    "sg:tags":[
        "self",
        "commercial",
        "warehouses-public-commercial",
        "household"
    ],
    "wof:name":"Atlanta Storage Partners",
    "wof:placetype":"venue"
},
  "geometry": {"coordinates":[-84.382082,33.835568],"type":"Point"}
}