{
  "type": "Feature",
  "properties": {
    "addr:full":"1025 Kirkland Ln Douglas GA 31533",
    "addr:housenumber":"1025",
    "addr:postcode":"31533",
    "addr:street":"Kirkland Ln",
    "iso:country":"US",
    "sg:address":"1025 Kirkland Ln",
    "sg:city":"Douglas",
    "sg:classifiers":[
        {
            "category":"Health Services",
            "subcategory":"Doctor",
            "type":"Services"
        }
    ],
    "sg:phone":"+1 912 384 3010",
    "sg:postcode":"31533",
    "sg:province":"GA",
    "sg:tags":[
        "physician",
        "surgeon"
    ],
    "wof:name":"Douglas Medical Clinic",
    "wof:placetype":"venue"
},
  "geometry": {"coordinates":[-82.86239399999999,31.505637],"type":"Point"}
}