{
  "type": "Feature",
  "properties": {
    "addr:full":"2424 Warm Springs Rd Columbus GA 31904",
    "addr:housenumber":"2424",
    "addr:postcode":"31904",
    "addr:street":"Warm Springs Rd",
    "iso:country":"US",
    "sg:address":"2424 Warm Springs Rd",
    "sg:city":"Columbus",
    "sg:classifiers":[
        {
            "category":"Health Services",
            "subcategory":"Clinic",
            "type":"Services"
        },
        {
            "category":"Health Services",
            "subcategory":"Doctor",
            "type":"Services"
        }
    ],
    "sg:phone":"+1 706 322 1959",
    "sg:postcode":"31904",
    "sg:province":"GA",
    "sg:tags":[
        "medical",
        "kidney",
        "center",
        "dialysis",
        "supply"
    ],
    "wof:name":"Dialysis Clinic Inc",
    "wof:placetype":"venue"
},
  "geometry": {"coordinates":[-84.953322,32.50229],"type":"Point"}
}