{
  "type": "Feature",
  "properties": {
    "iso:country":"US",
    "sg:address":"653 Hill St",
    "sg:city":"Louisville",
    "sg:classifiers":[
        {
            "category":"Organizations",
            "subcategory":"Religious Organization",
            "type":"Services"
        }
    ],
    "sg:phone":"+1 478 625 9409",
    "sg:postcode":"30434",
    "sg:province":"GA",
    "sg:tags":[
        "church"
    ],
    "wof:name":"Greater St Matthew AME Chr",
    "wof:placetype":"venue"
},
  "geometry": {"coordinates":[-82.415132,33.003779],"type":"Point"}
}