{
  "type": "Feature",
  "properties": {
    "iso:country":"US",
    "sg:address":"131 S Harris St",
    "sg:city":"Sandersville",
    "sg:classifiers":[
        {
            "category":"Insurance",
            "subcategory":"Insurance Agent",
            "type":"Services"
        }
    ],
    "sg:phone":"+1 478 552 2506",
    "sg:postcode":"31082",
    "sg:province":"GA",
    "sg:tags":[
        "homeowner"
    ],
    "sg:website":"http://www.yellowpages.com/sandersville-ga/mip/sammons-insurance-inc-5593506?lid=157834524",
    "wof:name":"Sammons Insurance Inc",
    "wof:placetype":"venue"
},
  "geometry": {"coordinates":[-82.810917,32.983019],"type":"Point"}
}