{
  "type": "Feature",
  "properties": {
    "addr:full":"1700 Cumberland Point Dr Marietta GA 30067",
    "addr:housenumber":"1700",
    "addr:postcode":"30067",
    "addr:street":"Cumberland Point Dr",
    "iso:country":"US",
    "sg:address":"1700 Cumberland Point Dr",
    "sg:city":"Marietta",
    "sg:classifiers":[
        {
            "category":"Wholesale",
            "subcategory":"Office Equipment",
            "type":"Manufacturing & Wholesale Goods"
        }
    ],
    "sg:phone":"+1 770 952 2144",
    "sg:postcode":"30067",
    "sg:province":"GA",
    "sg:tags":[
        "machine",
        "duplicating",
        "copying"
    ],
    "wof:name":"Copier Warehouse Inc",
    "wof:placetype":"venue"
},
  "geometry": {"coordinates":[-84.49408,33.910235],"type":"Point"}
}