{
  "type": "Feature",
  "properties": {
    "addr:full":"6073 Riverview Rd SE Mableton GA 30126",
    "addr:housenumber":"6073",
    "addr:postcode":"30126",
    "addr:street":"Riverview Rd Se",
    "iso:country":"US",
    "sg:address":"6073 Riverview Rd SE",
    "sg:city":"Mableton",
    "sg:classifiers":[
        {
            "category":"Real Estate",
            "subcategory":"Real Estate Operator",
            "type":"Services"
        },
        {
            "category":"Manufacturing",
            "subcategory":"Building Materials",
            "type":"Manufacturing & Wholesale Goods"
        }
    ],
    "sg:phone":"+1 404 699 0633",
    "sg:postcode":"30126",
    "sg:province":"GA",
    "sg:tags":[
        "grouting",
        "gunite",
        "contractor"
    ],
    "wof:name":"Atlanta Gunite Co",
    "wof:placetype":"venue"
},
  "geometry": {"coordinates":[-84.501003,33.804856],"type":"Point"}
}