{
  "type": "Feature",
  "properties": {
    "addr:full":"2505 Chastain Meadows Pkwy Ste I-2 Marietta GA 30066",
    "addr:housenumber":"2505",
    "addr:postcode":"30066",
    "addr:street":"Chastain Meadows Pkwy Ste I-2",
    "iso:country":"US",
    "sg:address":"2505 Chastain Meadows Pkwy Ste I-2",
    "sg:city":"Marietta",
    "sg:classifiers":[
        {
            "category":"Professional",
            "subcategory":"Employment Agencies",
            "type":"Services"
        }
    ],
    "sg:phone":"+1 770 421 8893",
    "sg:postcode":"30066",
    "sg:province":"GA",
    "sg:website":"www.staffmark.com",
    "wof:name":"Staffmark",
    "wof:placetype":"venue"
},
  "geometry": {"coordinates":[-84.554655,34.014822],"type":"Point"}
}