{
  "type": "Feature",
  "properties": {
    "addr:full":"1533 Old Hwy 85 Fayetteville GA 30215",
    "addr:housenumber":"1533",
    "addr:postcode":"30215",
    "addr:street":"Old Hwy 85",
    "iso:country":"US",
    "sg:address":"1533 Old Hwy 85",
    "sg:city":"Fayetteville",
    "sg:classifiers":[
        {
            "category":"Education",
            "subcategory":"School",
            "type":"Public Place"
        }
    ],
    "sg:phone":"+1 770 460 3450",
    "sg:postcode":"30215",
    "sg:province":"GA",
    "sg:tags":[
        "middle"
    ],
    "wof:name":"White Water Middle School",
    "wof:placetype":"venue"
},
  "geometry": {"coordinates":[-84.46992400000001,33.391529],"type":"Point"}
}