{
  "type": "Feature",
  "properties": {
    "iso:country":"US",
    "sg:address":"2700 Cumberland Parkway SE",
    "sg:city":"Atlanta",
    "sg:classifiers":[
        {
            "category":"Professional",
            "subcategory":"Lawyer & Legal Services",
            "type":"Services"
        }
    ],
    "sg:phone":"+1 678 305 9606",
    "sg:postcode":"30339",
    "sg:province":"GA",
    "wof:name":"Focus Receivable Management",
    "wof:placetype":"venue"
},
  "geometry": {"coordinates":[-84.473872,33.875951],"type":"Point"}
}