{
  "type": "Feature",
  "properties": {
    "addr:full":"6000 Lake Forrest Drive NW Atlanta GA 30328",
    "addr:housenumber":"6000",
    "addr:postcode":"30328",
    "addr:street":"Lake Forrest Drive Nw",
    "iso:country":"US",
    "sg:address":"6000 Lake Forrest Drive NW",
    "sg:city":"Atlanta",
    "sg:classifiers":[
        {
            "category":"Banks & Credit Unions",
            "subcategory":"Financial Services",
            "type":"Services"
        }
    ],
    "sg:phone":"+1 404 847 9800",
    "sg:postcode":"30328",
    "sg:province":"GA",
    "sg:tags":[
        "broker",
        "mortgage"
    ],
    "wof:name":"Arbor Commercial Mortgage",
    "wof:placetype":"venue"
},
  "geometry": {"coordinates":[-84.38709,33.9193],"type":"Point"}
}