{
  "type": "Feature",
  "properties": {
    "addr:full":"333 Kensington Dr Savannah GA 31405",
    "addr:housenumber":"333",
    "addr:postcode":"31405",
    "addr:street":"Kensington Dr",
    "iso:country":"US",
    "sg:address":"333 Kensington Dr",
    "sg:city":"Savannah",
    "sg:classifiers":[
        {
            "category":"Real Estate",
            "subcategory":"Real Estate Services",
            "type":"Services"
        },
        {
            "category":"Real Estate",
            "subcategory":"Real Estate Agent",
            "type":"Services"
        }
    ],
    "sg:phone":"+1 912 355 3374",
    "sg:postcode":"31405",
    "sg:province":"GA",
    "sg:tags":[
        "buyer",
        "broker"
    ],
    "wof:name":"Anliker Realtor",
    "wof:placetype":"venue"
},
  "geometry": {"coordinates":[-81.098187,32.020171],"type":"Point"}
}