{
  "type": "Feature",
  "properties": {
    "iso:country":"US",
    "sg:address":"119 E Hendry St",
    "sg:city":"Hinesville",
    "sg:classifiers":[
        {
            "category":"Shopping",
            "subcategory":"Clothing, Apparel, & Fashions",
            "type":"Retail Goods"
        }
    ],
    "sg:phone":"+1 912 368 2662",
    "sg:postcode":"31313",
    "sg:province":"GA",
    "wof:name":"Pro Feet",
    "wof:placetype":"venue"
},
  "geometry": {"coordinates":[-81.594641,31.843445],"type":"Point"}
}