{
  "type": "Feature",
  "properties": {
    "addr:full":"2629 Cagle St Lithonia GA 30058",
    "addr:housenumber":"2629",
    "addr:postcode":"30058",
    "addr:street":"Cagle St",
    "iso:country":"US",
    "sg:address":"2629 Cagle St",
    "sg:city":"Lithonia",
    "sg:classifiers":[
        {
            "category":"Organizations",
            "subcategory":"Religious Organization",
            "type":"Services"
        }
    ],
    "sg:phone":"+1 770 482 8885",
    "sg:postcode":"30058",
    "sg:province":"GA",
    "wof:name":"ATL Praise & Worship Center",
    "wof:placetype":"venue"
},
  "geometry": {"coordinates":[-84.10246600000001,33.708717],"type":"Point"}
}