{
  "type": "Feature",
  "properties": {
    "addr:full":"6451 Tara Blvd Jonesboro GA 30236",
    "addr:housenumber":"6451",
    "addr:postcode":"30236",
    "addr:street":"Tara Blvd",
    "iso:country":"US",
    "sg:address":"6451 Tara Blvd",
    "sg:city":"Jonesboro",
    "sg:classifiers":[
        {
            "category":"Restaurant",
            "type":"Food & Drink"
        }
    ],
    "sg:phone":"+1 770 471 8399",
    "sg:postcode":"30236",
    "sg:province":"GA",
    "sg:tags":[
        "eating"
    ],
    "wof:name":"Los Toribio Mexican Restaurant",
    "wof:placetype":"venue"
},
  "geometry": {"coordinates":[-84.377895,33.583017],"type":"Point"}
}