{
  "type": "Feature",
  "properties": {
    "addr:full":"7200 Britton Dr Columbus GA 31904",
    "addr:housenumber":"7200",
    "addr:postcode":"31904",
    "addr:street":"Britton Dr",
    "iso:country":"US",
    "sg:address":"7200 Britton Dr",
    "sg:city":"Columbus",
    "sg:classifiers":[
        {
            "category":"Professional",
            "type":"Services"
        }
    ],
    "sg:phone":"+1 706 327 1370",
    "sg:postcode":"31904",
    "sg:province":"GA",
    "wof:name":"Five Ears LP",
    "wof:placetype":"venue"
},
  "geometry": {"coordinates":[-84.994073,32.551358],"type":"Point"}
}