{
  "type": "Feature",
  "properties": {
    "iso:country":"US",
    "sg:address":"108 Ave C",
    "sg:city":"Lindale",
    "sg:classifiers":[
        {
            "category":"Wholesale",
            "subcategory":"Electrical",
            "type":"Manufacturing & Wholesale Goods"
        }
    ],
    "sg:phone":"+1 706 295 0889",
    "sg:postcode":"30147",
    "sg:province":"GA",
    "sg:tags":[
        "alarm",
        "burglar",
        "system"
    ],
    "sg:website":"www.genevaroad.com",
    "wof:name":"Williams Alarm & Communication",
    "wof:placetype":"venue"
},
  "geometry": {"coordinates":[-85.17464099999999,34.192648],"type":"Point"}
}