{
  "type": "Feature",
  "properties": {
    "addr:full":"390 Tower Dr Martinez GA 30907",
    "addr:housenumber":"390",
    "addr:postcode":"30907",
    "addr:street":"Tower Dr Martinez",
    "iso:country":"US",
    "sg:address":"390 Tower Dr",
    "sg:city":"Martinez",
    "sg:classifiers":[
        {
            "category":"Building & Trades",
            "subcategory":"Construction",
            "type":"Services"
        }
    ],
    "sg:phone":"+1 706 228 5077",
    "sg:postcode":"30907",
    "sg:province":"GA",
    "sg:tags":[
        "utility",
        "contractor"
    ],
    "sg:website":"www.anscoinc.com",
    "wof:name":"Ansco & Assoc Inc",
    "wof:placetype":"venue"
},
  "geometry": {"coordinates":[-82.124049,33.48777],"type":"Point"}
}