{
  "type": "Feature",
  "properties": {
    "iso:country":"US",
    "sg:address":"820 Springhaven Rd",
    "sg:city":"Dexter",
    "sg:classifiers":[
        {
            "category":"Building & Trades",
            "subcategory":"Construction",
            "type":"Services"
        }
    ],
    "sg:phone":"+1 478 275 0505",
    "sg:postcode":"31019",
    "sg:province":"GA",
    "wof:name":"Ralph Hall Construction",
    "wof:placetype":"venue"
},
  "geometry": {"coordinates":[-82.950294,32.446486],"type":"Point"}
}