{
  "type": "Feature",
  "properties": {
    "iso:country":"US",
    "sg:address":"5914 Goshen Springs Rd",
    "sg:city":"Norcross",
    "sg:classifiers":[
        {
            "category":"Building & Trades",
            "subcategory":"Landscaping Services",
            "type":"Services"
        }
    ],
    "sg:phone":"+1 770 263 0797",
    "sg:postcode":"30071",
    "sg:province":"GA",
    "wof:name":"Jackson Michael Landscaping Co",
    "wof:placetype":"venue"
},
  "geometry": {"coordinates":[-84.200425,33.917667],"type":"Point"}
}