{
  "type": "Feature",
  "properties": {
    "addr:full":"14671 Hwy 36 Covington GA 30014",
    "addr:housenumber":"14671",
    "addr:postcode":"30014",
    "addr:street":"Hwy 36",
    "iso:country":"US",
    "sg:address":"14671 Hwy 36",
    "sg:city":"Covington",
    "sg:classifiers":[
        {
            "category":"Government",
            "subcategory":"Fire Station",
            "type":"Public Place"
        }
    ],
    "sg:phone":"+1 770 787 0746",
    "sg:postcode":"30014",
    "sg:province":"GA",
    "sg:tags":[
        "protection"
    ],
    "wof:name":"Stewart Volunteer Fire Dept",
    "wof:placetype":"venue"
},
  "geometry": {"coordinates":[-83.844872,33.453364],"type":"Point"}
}