{
  "type": "Feature",
  "properties": {
    "iso:country":"US",
    "sg:address":"964 N Indian Creek Dr",
    "sg:city":"Clarkston",
    "sg:classifiers":[
        {
            "category":"Professional",
            "type":"Services"
        }
    ],
    "sg:phone":"+1 404 292 7499",
    "sg:postcode":"30021",
    "sg:province":"GA",
    "wof:name":"Bridging Gap",
    "wof:placetype":"venue"
},
  "geometry": {"coordinates":[-84.239118,33.804384],"type":"Point"}
}