{
  "type": "Feature",
  "properties": {
    "addr:full":"1945 Barnett Shoals Rd Athens GA 30605",
    "addr:housenumber":"1945",
    "addr:postcode":"30605",
    "addr:street":"Barnett Shoals Rd",
    "iso:country":"US",
    "sg:address":"1945 Barnett Shoals Rd",
    "sg:city":"Athens",
    "sg:classifiers":[
        {
            "category":"Retail",
            "subcategory":"Laundry & Dry Cleaning",
            "type":"Services"
        }
    ],
    "sg:phone":"+1 706 543 6383",
    "sg:postcode":"30605",
    "sg:province":"GA",
    "sg:tags":[
        "drycleaning",
        "plant"
    ],
    "wof:name":"One Price Dry Cleaning",
    "wof:placetype":"venue"
},
  "geometry": {"coordinates":[-83.34120299999999,33.922157],"type":"Point"}
}