{
  "type": "Feature",
  "properties": {
    "addr:full":"514 N Tennessee St Cartersville GA 30120",
    "addr:housenumber":"514",
    "addr:postcode":"30120",
    "addr:street":"N Tennessee St",
    "iso:country":"US",
    "sg:address":"514 N Tennessee St",
    "sg:city":"Cartersville",
    "sg:classifiers":[
        {
            "category":"Taxi",
            "type":"Transportation"
        }
    ],
    "sg:phone":"+1 770 607 9100",
    "sg:postcode":"30120",
    "sg:province":"GA",
    "sg:tags":[
        "taxicab"
    ],
    "wof:name":"A Cab Bartow Co",
    "wof:placetype":"venue"
},
  "geometry": {"coordinates":[-84.793487,34.177204],"type":"Point"}
}