{
  "type": "Feature",
  "properties": {
    "addr:full":"3384 Shallowford Road NE Atlanta GA 30341",
    "addr:housenumber":"3384",
    "addr:postcode":"30341",
    "addr:street":"Shallowford Road Ne",
    "iso:country":"US",
    "sg:address":"3384 Shallowford Road NE",
    "sg:city":"Atlanta",
    "sg:classifiers":[
        {
            "category":"Restaurant",
            "type":"Food & Drink"
        }
    ],
    "sg:phone":"+1 678 205 1412",
    "sg:postcode":"30341",
    "sg:province":"GA",
    "sg:tags":[
        "mexican"
    ],
    "wof:name":"Restaurante Guatemala",
    "wof:placetype":"venue"
},
  "geometry": {"coordinates":[-84.285009,33.886818],"type":"Point"}
}