{
  "type": "Feature",
  "properties": {
    "iso:country":"US",
    "sg:address":"2870 Peachtree Industrial Blvd",
    "sg:city":"Duluth",
    "sg:classifiers":[
        {
            "category":"Insurance",
            "subcategory":"Insurance Agent",
            "type":"Services"
        }
    ],
    "sg:phone":"+1 770 622 9904",
    "sg:postcode":"30096",
    "sg:province":"GA",
    "wof:name":"State Farm Insurance",
    "wof:placetype":"venue"
},
  "geometry": {"coordinates":[-84.130349,34.021848],"type":"Point"}
}