{
  "type": "Feature",
  "properties": {
    "iso:country":"US",
    "sg:address":"6000 Singleton Rd",
    "sg:city":"Norcross",
    "sg:classifiers":[
        {
            "category":"Bars & Pubs",
            "subcategory":"Sports Bar",
            "type":"Food & Drink"
        }
    ],
    "sg:phone":"+1 770 613 0708",
    "sg:postcode":"30093",
    "sg:province":"GA",
    "sg:tags":[
        "hall",
        "pool"
    ],
    "wof:name":"Uno Cafe & Billiards",
    "wof:placetype":"venue"
},
  "geometry": {"coordinates":[-84.19740299999999,33.906601],"type":"Point"}
}