{
  "type": "Feature",
  "properties": {
    "addr:full":"3079 Midway Rd Decatur GA 30032",
    "addr:housenumber":"3079",
    "addr:postcode":"30032",
    "addr:street":"Midway Rd",
    "iso:country":"US",
    "sg:address":"3079 Midway Rd",
    "sg:city":"Decatur",
    "sg:classifiers":[
        {
            "category":"Sports & Exercise",
            "subcategory":"Gym",
            "type":"Entertainment"
        },
        {
            "category":"Sports & Exercise",
            "subcategory":"Playing Field",
            "type":"Entertainment"
        },
        {
            "category":"Arena",
            "subcategory":"Sports Club",
            "type":"Entertainment"
        }
    ],
    "sg:phone":"+1 404 289 5652",
    "sg:postcode":"30032",
    "sg:province":"GA",
    "sg:tags":[
        "trainer",
        "chi",
        "martial art",
        "instruction",
        "yoga",
        "tai"
    ],
    "sg:website":"www.tai-chi-association.com",
    "wof:name":"Tai Chi Association",
    "wof:placetype":"venue"
},
  "geometry": {"coordinates":[-84.263789,33.75461],"type":"Point"}
}