{
  "type": "Feature",
  "properties": {
    "iso:country":"US",
    "sg:address":"3100 Five Forks Trickum Rd SW",
    "sg:city":"Lilburn",
    "sg:classifiers":[
        {
            "category":"Real Estate",
            "subcategory":"Real Estate Services",
            "type":"Services"
        }
    ],
    "sg:phone":"+1 770 736 6615",
    "sg:postcode":"30047",
    "sg:province":"GA",
    "sg:tags":[
        "company",
        "title"
    ],
    "wof:name":"First Guaranty Title Inc",
    "wof:placetype":"venue"
},
  "geometry": {"coordinates":[-84.061736,33.884548],"type":"Point"}
}