{
  "type": "Feature",
  "properties": {
    "addr:full":"746 Green St NE Gainesville GA 30501",
    "addr:housenumber":"746",
    "addr:postcode":"30501",
    "addr:street":"Green St Ne;Ga",
    "iso:country":"US",
    "sg:address":"746 Green St NE",
    "sg:city":"Gainesville",
    "sg:classifiers":[
        {
            "category":"Personal",
            "subcategory":"Massage",
            "type":"Services"
        }
    ],
    "sg:phone":"+1 770 374 8487",
    "sg:postcode":"30501",
    "sg:province":"GA",
    "sg:tags":[
        "therapist"
    ],
    "wof:name":"Maggie's Spa",
    "wof:placetype":"venue"
},
  "geometry": {"coordinates":[-83.827454,34.30949],"type":"Point"}
}