{
  "type": "Feature",
  "properties": {
    "addr:full":"133 Main St Jersey GA 30018",
    "addr:housenumber":"133",
    "addr:postcode":"30018",
    "addr:street":"Main St",
    "iso:country":"US",
    "sg:address":"133 Main St",
    "sg:city":"Jersey",
    "sg:classifiers":[
        {
            "category":"Personal",
            "subcategory":"Beauty Salon",
            "type":"Services"
        }
    ],
    "sg:phone":"+1 770 464 3644",
    "sg:postcode":"30018",
    "sg:province":"GA",
    "sg:tags":[
        "shop"
    ],
    "wof:name":"Tangles & Tan Salon",
    "wof:placetype":"venue"
},
  "geometry": {"coordinates":[-83.801407,33.712252],"type":"Point"}
}