{
  "type": "Feature",
  "properties": {
    "iso:country":"US",
    "sg:address":"3645 Lake Shore Dr",
    "sg:city":"Augusta",
    "sg:classifiers":[
        {
            "category":"Professional",
            "subcategory":"Research",
            "type":"Services"
        }
    ],
    "sg:phone":"+1 706 860 9424",
    "sg:postcode":"30907",
    "sg:province":"GA",
    "sg:tags":[
        "medical"
    ],
    "wof:name":"Teresa Herron",
    "wof:placetype":"venue"
},
  "geometry": {"coordinates":[-82.08095899999999,33.526978],"type":"Point"}
}