{
  "type": "Feature",
  "properties": {
    "iso:country":"US",
    "sg:address":"1028 Green St SW",
    "sg:city":"Conyers",
    "sg:classifiers":[
        {
            "category":"Professional",
            "subcategory":"Lawyer & Legal Services",
            "type":"Services"
        }
    ],
    "sg:phone":"+1 770 922 3819",
    "sg:postcode":"30012",
    "sg:province":"GA",
    "wof:name":"Morrison Bob Atty",
    "wof:placetype":"venue"
},
  "geometry": {"coordinates":[-84.022205,33.668704],"type":"Point"}
}