{
  "type": "Feature",
  "properties": {
    "addr:full":"5504 Barnes Pl Macon GA 31216",
    "addr:housenumber":"5504",
    "addr:postcode":"31216",
    "addr:street":"Barnes Pl",
    "iso:country":"US",
    "sg:address":"5504 Barnes Pl",
    "sg:city":"Macon",
    "sg:classifiers":[
        {
            "category":"Home & Garden",
            "subcategory":"Carpets & Floor Coverings",
            "type":"Retail Goods"
        },
        {
            "category":"Building & Trades",
            "subcategory":"Construction",
            "type":"Services"
        }
    ],
    "sg:phone":"+1 478 788 3693",
    "sg:postcode":"31216",
    "sg:province":"GA",
    "sg:tags":[
        "tile",
        "laying",
        "co",
        "dealer"
    ],
    "wof:name":"A J Thompson Floors Inc",
    "wof:placetype":"venue"
},
  "geometry": {"coordinates":[-83.65625300000001,32.752096],"type":"Point"}
}