{
  "type": "Feature",
  "properties": {
    "addr:full":"2619 Sandy Plains Rd NE Marietta GA 30066",
    "addr:housenumber":"2619",
    "addr:postcode":"30066",
    "addr:street":"Sandy Plains Rd Ne",
    "iso:country":"US",
    "sg:address":"2619 Sandy Plains Rd NE",
    "sg:city":"Marietta",
    "sg:classifiers":[
        {
            "category":"Wholesale",
            "subcategory":"Durable Goods & Equipment",
            "type":"Manufacturing & Wholesale Goods"
        }
    ],
    "sg:phone":"+1 770 509 8404",
    "sg:postcode":"30066",
    "sg:province":"GA",
    "sg:tags":[
        "engineering",
        "supply"
    ],
    "wof:name":"Mazak Nissho Iwai Corporation",
    "wof:placetype":"venue"
},
  "geometry": {"coordinates":[-84.495408,34.013575],"type":"Point"}
}