{
  "type": "Feature",
  "properties": {
    "addr:full":"184 Sunset Dr Hartwell GA 30643",
    "addr:housenumber":"184",
    "addr:postcode":"30643",
    "addr:street":"Sunset Dr",
    "iso:country":"US",
    "sg:address":"184 Sunset Dr",
    "sg:city":"Hartwell",
    "sg:classifiers":[
        {
            "category":"Retail",
            "subcategory":"Repair Shop",
            "type":"Services"
        }
    ],
    "sg:phone":"+1 706 376 3551",
    "sg:postcode":"30643",
    "sg:province":"GA",
    "wof:name":"Bobby J Hall",
    "wof:placetype":"venue"
},
  "geometry": {"coordinates":[-82.965717,34.331084],"type":"Point"}
}