{
  "type": "Feature",
  "properties": {
    "addr:full":"5522 New Peachtree Rd Atlanta GA 30341",
    "addr:housenumber":"5522",
    "addr:postcode":"30341",
    "addr:street":"New Peachtree Rd",
    "iso:country":"US",
    "sg:address":"5522 New Peachtree Rd",
    "sg:city":"Atlanta",
    "sg:classifiers":[
        {
            "category":"Shopping",
            "subcategory":"Clothing, Apparel, & Fashions",
            "type":"Retail Goods"
        }
    ],
    "sg:phone":"+1 770 452 0082",
    "sg:postcode":"30341",
    "sg:province":"GA",
    "sg:tags":[
        "shop",
        "bridal"
    ],
    "wof:name":"Saidas Bridal & Formal",
    "wof:placetype":"venue"
},
  "geometry": {"coordinates":[-84.29836299999999,33.892416],"type":"Point"}
}