{
  "type": "Feature",
  "properties": {
    "iso:country":"US",
    "sg:address":"8207 Dunwoody Pl",
    "sg:city":"Atlanta",
    "sg:classifiers":[
        {
            "category":"Professional",
            "subcategory":"Advertising",
            "type":"Services"
        }
    ],
    "sg:phone":"+1 770 993 1623",
    "sg:postcode":"30350",
    "sg:province":"GA",
    "sg:tags":[
        "publisher",
        "representative"
    ],
    "wof:name":"Blynn Richards & Associates",
    "wof:placetype":"venue"
},
  "geometry": {"coordinates":[-84.341691,33.983835],"type":"Point"}
}