{
  "type": "Feature",
  "properties": {
    "addr:full":"214 W Main St Cartersville GA 30120",
    "addr:housenumber":"214",
    "addr:postcode":"30120",
    "addr:street":"W Main St",
    "iso:country":"US",
    "sg:address":"214 W Main St",
    "sg:city":"Cartersville",
    "sg:classifiers":[
        {
            "category":"Banks & Credit Unions",
            "subcategory":"Bank",
            "type":"Services"
        }
    ],
    "sg:phone":"+1 770 386 4448",
    "sg:postcode":"30120",
    "sg:province":"GA",
    "sg:tags":[
        "broker",
        "mortgage"
    ],
    "wof:name":"Approved Mortgage Services",
    "wof:placetype":"venue"
},
  "geometry": {"coordinates":[-84.805565,34.163067],"type":"Point"}
}