{
  "type": "Feature",
  "properties": {
    "iso:country":"US",
    "sg:address":"125 Friar Tuck Cir",
    "sg:city":"Reidsville",
    "sg:classifiers":[
        {
            "category":"Communications",
            "subcategory":"Radio Station",
            "type":"Services"
        }
    ],
    "sg:phone":"+1 912 557 3777",
    "sg:postcode":"30453",
    "sg:province":"GA",
    "sg:tags":[
        "company",
        "broadcasting"
    ],
    "wof:name":"WRBX",
    "wof:placetype":"venue"
},
  "geometry": {"coordinates":[-82.12671400000001,32.086782],"type":"Point"}
}