{
  "type": "Feature",
  "properties": {
    "iso:country":"US",
    "sg:address":"1181 Northwoods Rd",
    "sg:city":"Watkinsville",
    "sg:classifiers":[
        {
            "category":"Shopping",
            "subcategory":"Gifts & Souvenirs",
            "type":"Retail Goods"
        }
    ],
    "sg:phone":"+1 706 769 6547",
    "sg:postcode":"30677",
    "sg:province":"GA",
    "sg:tags":[
        "merchandise"
    ],
    "wof:name":"Caudles Tole",
    "wof:placetype":"venue"
},
  "geometry": {"coordinates":[-83.460241,33.877701],"type":"Point"}
}