{
  "type": "Feature",
  "properties": {
    "iso:country":"US",
    "sg:address":"2190 Monroe Dr",
    "sg:city":"Alpharetta",
    "sg:classifiers":[
        {
            "category":"Professional",
            "type":"Services"
        }
    ],
    "sg:phone":"+1 770 442 5033",
    "sg:postcode":"30004",
    "sg:province":"GA",
    "sg:tags":[
        "communication",
        "graphic"
    ],
    "wof:name":"Winsor/Cohn Communications",
    "wof:placetype":"venue"
},
  "geometry": {"coordinates":[-84.282301,34.084129],"type":"Point"}
}