{
  "type": "Feature",
  "properties": {
    "iso:country":"US",
    "sg:address":"3875 Washington Rd",
    "sg:city":"Atlanta",
    "sg:classifiers":[
        {
            "category":"Building & Trades",
            "subcategory":"Locksmith",
            "type":"Services"
        }
    ],
    "sg:phone":"+1 866 805 2762",
    "sg:postcode":"30344",
    "sg:province":"GA",
    "sg:tags":[
        "key"
    ],
    "wof:name":"24 Hour 1 Emergency Locksmith",
    "wof:placetype":"venue"
},
  "geometry": {"coordinates":[-84.48999000000001,33.649876],"type":"Point"}
}