{
  "type": "Feature",
  "properties": {
    "iso:country":"US",
    "sg:address":"1015 Traymore Dr",
    "sg:city":"Norcross",
    "sg:classifiers":[
        {
            "category":"Building & Trades",
            "subcategory":"Construction",
            "type":"Services"
        }
    ],
    "sg:phone":"+1 770 717 1420",
    "sg:postcode":"30092",
    "sg:province":"GA",
    "sg:tags":[
        "floor",
        "laying",
        "contractor"
    ],
    "wof:name":"R 3 Flooring Services",
    "wof:placetype":"venue"
},
  "geometry": {"coordinates":[-84.146203,33.913068],"type":"Point"}
}