{
  "type": "Feature",
  "properties": {
    "iso:country":"US",
    "sg:address":"2300 Shallowford Rd NE",
    "sg:city":"Atlanta",
    "sg:classifiers":[
        {
            "category":"Education",
            "subcategory":"Music School",
            "type":"Public Place"
        },
        {
            "category":"Education",
            "subcategory":"School",
            "type":"Public Place"
        }
    ],
    "sg:phone":"+1 404 517 3343",
    "sg:postcode":"30345",
    "sg:province":"GA",
    "wof:name":"Sandpiper Music Studio",
    "wof:placetype":"venue"
},
  "geometry": {"coordinates":[-84.281631,33.855251],"type":"Point"}
}