{
  "type": "Feature",
  "properties": {
    "addr:full":"2655 N Decatur Rd Decatur GA 30033",
    "addr:housenumber":"2655",
    "addr:postcode":"30033",
    "addr:street":"N Decatur Rd",
    "iso:country":"US",
    "sg:address":"2655 N Decatur Rd",
    "sg:city":"Decatur",
    "sg:classifiers":[
        {
            "category":"Shopping",
            "subcategory":"Crafts & Fabrics",
            "type":"Retail Goods"
        }
    ],
    "sg:phone":"+1 404 378 8220",
    "sg:postcode":"30033",
    "sg:province":"GA",
    "sg:tags":[
        "store"
    ],
    "wof:name":"Hancock Fabrics",
    "wof:placetype":"venue"
},
  "geometry": {"coordinates":[-84.286102,33.792301],"type":"Point"}
}