{
  "type": "Feature",
  "properties": {
    "iso:country":"US",
    "sg:address":"6181 Memorial Dr Ste 3",
    "sg:city":"Stone Mountain",
    "sg:classifiers":[
        {
            "category":"Insurance",
            "subcategory":"Hazard Insurance",
            "type":"Services"
        }
    ],
    "sg:phone":"+1 770 465 7800",
    "sg:postcode":"30083",
    "sg:province":"GA",
    "wof:name":"Trinity Universal Insurance Agency",
    "wof:placetype":"venue"
},
  "geometry": {"coordinates":[-84.187282,33.805515],"type":"Point"}
}