{
  "type": "Feature",
  "properties": {
    "iso:country":"US",
    "sg:address":"2600 Pinemeadow Ct",
    "sg:city":"Duluth",
    "sg:classifiers":[
        {
            "category":"Freight",
            "type":"Transportation"
        }
    ],
    "sg:phone":"+1 770 623 5060",
    "sg:postcode":"30096",
    "sg:province":"GA",
    "sg:tags":[
        "terminal",
        "gas",
        "petroleum"
    ],
    "sg:website":"http://www.phillips66.com",
    "wof:name":"Conoco Atlanta Dist Ctr",
    "wof:placetype":"venue"
},
  "geometry": {"coordinates":[-84.101563,33.972132],"type":"Point"}
}