{
  "type": "Feature",
  "properties": {
    "iso:country":"US",
    "sg:address":"196 Sentinel Pl",
    "sg:city":"Marietta",
    "sg:classifiers":[
        {
            "category":"Shopping",
            "subcategory":"Discount & Variety Stores",
            "type":"Retail Goods"
        },
        {
            "category":"Manufacturing",
            "subcategory":"Rubber & Plastics",
            "type":"Manufacturing & Wholesale Goods"
        }
    ],
    "sg:phone":"+1 770 422 0500",
    "sg:postcode":"30067",
    "sg:province":"GA",
    "sg:tags":[
        "product",
        "general",
        "merchandise",
        "mfg"
    ],
    "wof:name":"Omnidex Products Inc",
    "wof:placetype":"venue"
},
  "geometry": {"coordinates":[-84.43825,33.951265],"type":"Point"}
}