{
  "type": "Feature",
  "properties": {
    "iso:country":"US",
    "sg:address":"865 N Main St",
    "sg:city":"Alpharetta",
    "sg:classifiers":[
        {
            "category":"Restaurant",
            "type":"Food & Drink"
        }
    ],
    "sg:menulink":"http://www.allmenus.com/ga/roswell-alpharetta/206219-hudson-grille/menu/",
    "sg:phone":"+1 770 777 4127",
    "sg:postcode":"30004",
    "sg:province":"GA",
    "sg:tags":[
        "american"
    ],
    "wof:name":"Hudson Grille",
    "wof:placetype":"venue"
},
  "geometry": {"coordinates":[-84.28025700000001,34.09261],"type":"Point"}
}