{
  "type": "Feature",
  "properties": {
    "iso:country":"US",
    "sg:address":"2001 Marietta Rd NW",
    "sg:city":"Atlanta",
    "sg:classifiers":[
        {
            "category":"Social Services",
            "type":"Services"
        }
    ],
    "sg:phone":"+1 404 351 4949",
    "sg:postcode":"30318",
    "sg:province":"GA",
    "wof:name":"Rebuilding Together-Atlanta",
    "wof:placetype":"venue"
},
  "geometry": {"coordinates":[-84.44976699999999,33.808055],"type":"Point"}
}