{
  "type": "Feature",
  "properties": {
    "iso:country":"US",
    "sg:address":"5116 Belmont Rd N",
    "sg:city":"Louisville",
    "sg:classifiers":[
        {
            "category":"Organizations",
            "subcategory":"Religious Organization",
            "type":"Services"
        }
    ],
    "sg:phone":"+1 478 625 7502",
    "sg:postcode":"30434",
    "sg:province":"GA",
    "sg:tags":[
        "church"
    ],
    "wof:name":"Hardeman Springfld Baptist Chr",
    "wof:placetype":"venue"
},
  "geometry": {"coordinates":[-82.55432999999999,33.039643],"type":"Point"}
}