{
  "type": "Feature",
  "properties": {
    "addr:full":"5268 Buford Hwy NE Atlanta GA 30340",
    "addr:housenumber":"5268",
    "addr:postcode":"30340",
    "addr:street":"Buford Hwy Ne",
    "iso:country":"US",
    "sg:address":"5268 Buford Hwy NE",
    "sg:city":"Atlanta",
    "sg:classifiers":[
        {
            "category":"Shopping",
            "subcategory":"Books",
            "type":"Retail Goods"
        }
    ],
    "sg:phone":"+1 770 455 3222",
    "sg:postcode":"30340",
    "sg:province":"GA",
    "sg:tags":[
        "bookstore"
    ],
    "wof:name":"Koryo Book Store",
    "wof:placetype":"venue"
},
  "geometry": {"coordinates":[-84.281998,33.896301],"type":"Point"}
}