{
  "type": "Feature",
  "properties": {
    "iso:country":"US",
    "sg:address":"655 E Hill St",
    "sg:city":"Thomson",
    "sg:classifiers":[
        {
            "category":"Retail",
            "subcategory":"Auto Repair",
            "type":"Services"
        }
    ],
    "sg:phone":"+1 706 597 9230",
    "sg:postcode":"30824",
    "sg:province":"GA",
    "sg:tags":[
        "general"
    ],
    "wof:name":"Number 1 Auto Repair",
    "wof:placetype":"venue"
},
  "geometry": {"coordinates":[-82.491147,33.462852],"type":"Point"}
}