{
  "type": "Feature",
  "properties": {
    "iso:country":"US",
    "sg:address":"376 Glynn St N",
    "sg:city":"Fayetteville",
    "sg:classifiers":[
        {
            "category":"Banks & Credit Unions",
            "subcategory":"Bank",
            "type":"Services"
        }
    ],
    "sg:phone":"+1 770 716 2123",
    "sg:postcode":"30214",
    "sg:province":"GA",
    "sg:tags":[
        "broker",
        "mortgage"
    ],
    "wof:name":"Wall Street Brokers Inc",
    "wof:placetype":"venue"
},
  "geometry": {"coordinates":[-84.454905,33.455694],"type":"Point"}
}