{
  "type": "Feature",
  "properties": {
    "iso:country":"US",
    "sg:address":"4352 Windmoor Dr NW",
    "sg:city":"Kennesaw",
    "sg:classifiers":[
        {
            "category":"Building & Trades",
            "subcategory":"Landscaping Services",
            "type":"Services"
        }
    ],
    "sg:phone":"+1 770 420 2169",
    "sg:postcode":"30144",
    "sg:province":"GA",
    "sg:tags":[
        "landscape",
        "contractor"
    ],
    "wof:name":"Ft Landscaping",
    "wof:placetype":"venue"
},
  "geometry": {"coordinates":[-84.596585,34.05859],"type":"Point"}
}