{
  "type": "Feature",
  "properties": {
    "iso:country":"US",
    "sg:address":"4091 Moreland Ave",
    "sg:city":"Conley",
    "sg:classifiers":[
        {
            "category":"Manufacturing",
            "subcategory":"Metals",
            "type":"Manufacturing & Wholesale Goods"
        }
    ],
    "sg:phone":"+1 404 361 4400",
    "sg:postcode":"30288",
    "sg:province":"GA",
    "sg:tags":[
        "steel"
    ],
    "wof:name":"Knight Steel Inc",
    "wof:placetype":"venue"
},
  "geometry": {"coordinates":[-84.32028,33.635758],"type":"Point"}
}