{
  "type": "Feature",
  "properties": {
    "addr:full":"1600 Parkwood Cir SE Atlanta GA 30339",
    "addr:housenumber":"1600",
    "addr:postcode":"30339",
    "addr:street":"Parkwood Cir Se",
    "iso:country":"US",
    "sg:address":"1600 Parkwood Cir SE",
    "sg:city":"Atlanta",
    "sg:classifiers":[
        {
            "category":"Professional",
            "subcategory":"Management & Consulting",
            "type":"Services"
        }
    ],
    "sg:phone":"+1 404 635 1150",
    "sg:postcode":"30339",
    "sg:province":"GA",
    "wof:name":"Southwestern Professional Serv",
    "wof:placetype":"venue"
},
  "geometry": {"coordinates":[-84.456209,33.901424],"type":"Point"}
}