{
  "type": "Feature",
  "properties": {
    "iso:country":"US",
    "sg:address":"3355 McDaniel Rd",
    "sg:city":"Duluth",
    "sg:classifiers":[
        {
            "category":"Health Services",
            "subcategory":"Clinic",
            "type":"Services"
        }
    ],
    "sg:phone":"+1 678 475 1340",
    "sg:postcode":"30096",
    "sg:province":"GA",
    "wof:name":"Health Data International Inc",
    "wof:placetype":"venue"
},
  "geometry": {"coordinates":[-84.12937100000001,33.967829],"type":"Point"}
}