{
  "type": "Feature",
  "properties": {
    "iso:country":"US",
    "sg:address":"290 Main St N",
    "sg:city":"Cornelia",
    "sg:classifiers":[
        {
            "category":"Retail",
            "subcategory":"Auto Rental",
            "type":"Services"
        }
    ],
    "sg:phone":"+1 706 894 2047",
    "sg:postcode":"30531",
    "sg:province":"GA",
    "sg:tags":[
        "renting",
        "truck",
        "leasing"
    ],
    "wof:name":"U-Haul Co",
    "wof:placetype":"venue"
},
  "geometry": {"coordinates":[-83.52776,34.512516],"type":"Point"}
}