{
  "type": "Feature",
  "properties": {
    "addr:full":"103 Jesse Jewell Pkwy SE Gainesville GA 30501",
    "addr:housenumber":"103",
    "addr:postcode":"30501",
    "addr:street":"Jesse Jewell Pkwy Se;Ga",
    "iso:country":"US",
    "sg:address":"103 Jesse Jewell Pkwy SE",
    "sg:city":"Gainesville",
    "sg:classifiers":[
        {
            "category":"Shopping",
            "subcategory":"Pharmacy",
            "type":"Retail Goods"
        }
    ],
    "sg:phone":"+1 770 536 3441",
    "sg:postcode":"30501",
    "sg:province":"GA",
    "sg:website":"www.cvs.com",
    "wof:name":"CVS Pharmacy",
    "wof:placetype":"venue"
},
  "geometry": {"coordinates":[-83.82317500000001,34.298511],"type":"Point"}
}