{
  "type": "Feature",
  "properties": {
    "iso:country":"US",
    "sg:address":"850 Wymill Dr",
    "sg:city":"Norcross",
    "sg:classifiers":[
        {
            "category":"Building & Trades",
            "subcategory":"Landscaping Services",
            "type":"Services"
        }
    ],
    "sg:phone":"+1 770 935 7788",
    "sg:postcode":"30093",
    "sg:province":"GA",
    "wof:name":"Automatic Lawn Care Inc",
    "wof:placetype":"venue"
},
  "geometry": {"coordinates":[-84.172629,33.893377],"type":"Point"}
}