{
  "type": "Feature",
  "properties": {
    "iso:country":"US",
    "sg:address":"2970 George Busbee Pkwy",
    "sg:city":"Kennesaw",
    "sg:classifiers":[
        {
            "category":"Autos & Motor Vehicles",
            "subcategory":"Auto Supplies",
            "type":"Retail Goods"
        },
        {
            "category":"Retail",
            "subcategory":"Auto Repair",
            "type":"Services"
        }
    ],
    "sg:phone":"+1 770 792 2982",
    "sg:postcode":"30066",
    "sg:province":"GA",
    "sg:tags":[
        "tire"
    ],
    "sg:website":"dwcampbelltire.com",
    "wof:name":"DW Campbell Goodyear",
    "wof:placetype":"venue"
},
  "geometry": {"coordinates":[-84.567145,34.026332],"type":"Point"}
}