{
  "type": "Feature",
  "properties": {
    "addr:full":"7961 State Hwy 92 Woodstock GA 30189",
    "addr:housenumber":"7961",
    "addr:postcode":"30189",
    "addr:street":"State Hwy 92",
    "iso:country":"US",
    "sg:address":"7961 State Hwy 92",
    "sg:city":"Woodstock",
    "sg:classifiers":[
        {
            "category":"Building & Trades",
            "subcategory":"Pest Control",
            "type":"Services"
        }
    ],
    "sg:phone":"+1 770 926 2779",
    "sg:postcode":"30189",
    "sg:province":"GA",
    "sg:website":"www.arrowexterminators.com",
    "wof:name":"Arrow Exterminators Inc",
    "wof:placetype":"venue"
},
  "geometry": {"coordinates":[-84.553296,34.085037],"type":"Point"}
}