{
  "type": "Feature",
  "properties": {
    "addr:full":"112 S Main St Nahunta GA 31553",
    "addr:housenumber":"112",
    "addr:postcode":"31553",
    "addr:street":"S Main St",
    "iso:country":"US",
    "sg:address":"112 S Main St",
    "sg:city":"Nahunta",
    "sg:classifiers":[
        {
            "category":"Home & Garden",
            "subcategory":"Building Materials",
            "type":"Retail Goods"
        }
    ],
    "sg:phone":"+1 912 462 7552",
    "sg:postcode":"31553",
    "sg:province":"GA",
    "wof:name":"Farmers & Builders Supply Inc",
    "wof:placetype":"venue"
},
  "geometry": {"coordinates":[-81.983559,31.199555],"type":"Point"}
}