{
  "type": "Feature",
  "properties": {
    "addr:full":"1213 Nicole Ct NW Norcross GA 30093",
    "addr:housenumber":"1213",
    "addr:postcode":"30093",
    "addr:street":"Nicole Ct Nw",
    "iso:country":"US",
    "sg:address":"1213 Nicole Ct NW",
    "sg:city":"Norcross",
    "sg:classifiers":[
        {
            "category":"Wholesale",
            "subcategory":"Electrical",
            "type":"Manufacturing & Wholesale Goods"
        }
    ],
    "sg:phone":"+1 678 463 7671",
    "sg:postcode":"30093",
    "sg:province":"GA",
    "sg:tags":[
        "equipment"
    ],
    "wof:name":"Lighting Supply Company",
    "wof:placetype":"venue"
},
  "geometry": {"coordinates":[-84.199209,33.894155],"type":"Point"}
}