{
  "type": "Feature",
  "properties": {
    "addr:full":"663 Mormon Church Rd Buchanan GA 30113",
    "addr:housenumber":"663",
    "addr:postcode":"30113",
    "addr:street":"Mormon Church Rd",
    "iso:country":"US",
    "sg:address":"663 Mormon Church Rd",
    "sg:city":"Buchanan",
    "sg:classifiers":[
        {
            "category":"Organizations",
            "subcategory":"Religious Organization",
            "type":"Services"
        }
    ],
    "sg:phone":"+1 770 646 3164",
    "sg:postcode":"30113",
    "sg:province":"GA",
    "sg:tags":[
        "church"
    ],
    "wof:name":"Church Of Jesus Christ Of Lds",
    "wof:placetype":"venue"
},
  "geometry": {"coordinates":[-85.199716,33.841324],"type":"Point"}
}