{
  "type": "Feature",
  "properties": {
    "iso:country":"US",
    "sg:address":"2740 Greenbriar Pkwy SW",
    "sg:city":"Atlanta",
    "sg:classifiers":[
        {
            "category":"Building & Trades",
            "subcategory":"Locksmith",
            "type":"Services"
        }
    ],
    "sg:phone":"+1 404 909 8702",
    "sg:postcode":"30331",
    "sg:province":"GA",
    "sg:tags":[
        "key"
    ],
    "wof:name":"Locksmith 24 Hours",
    "wof:placetype":"venue"
},
  "geometry": {"coordinates":[-84.48901600000001,33.689032],"type":"Point"}
}