{
  "type": "Feature",
  "properties": {
    "addr:full":"127 P Rickman Industrial Dr Canton GA 30115",
    "addr:housenumber":"127",
    "addr:postcode":"30115",
    "addr:street":"P Rickman Industrial Dr",
    "iso:country":"US",
    "sg:address":"127 P Rickman Industrial Dr",
    "sg:city":"Canton",
    "sg:classifiers":[
        {
            "category":"Professional",
            "subcategory":"Research",
            "type":"Services"
        }
    ],
    "sg:phone":"+1 770 720 9780",
    "sg:postcode":"30115",
    "sg:province":"GA",
    "sg:tags":[
        "development",
        "cryogenic"
    ],
    "sg:website":"www.chart-ind.com",
    "wof:name":"Chart Cryogenics",
    "wof:placetype":"venue"
},
  "geometry": {"coordinates":[-84.50073999999999,34.174153],"type":"Point"}
}