{
  "type": "Feature",
  "properties": {
    "iso:country":"US",
    "sg:address":"1300 Cedar Keys Ct",
    "sg:city":"Stone Mountain",
    "sg:classifiers":[
        {
            "category":"Building & Trades",
            "subcategory":"Cleaning & Sanitation",
            "type":"Services"
        }
    ],
    "sg:phone":"+1 404 299 2697",
    "sg:postcode":"30083",
    "sg:province":"GA",
    "sg:tags":[
        "maintenance"
    ],
    "wof:name":"Christies Maid Svc",
    "wof:placetype":"venue"
},
  "geometry": {"coordinates":[-84.200711,33.816553],"type":"Point"}
}