{
  "type": "Feature",
  "properties": {
    "addr:full":"3403 Memorial Dr Decatur GA 30032",
    "addr:housenumber":"3403",
    "addr:postcode":"30032",
    "addr:street":"Memorial Dr",
    "iso:country":"US",
    "sg:address":"3403 Memorial Dr",
    "sg:city":"Decatur",
    "sg:classifiers":[
        {
            "category":"Travel",
            "subcategory":"Hotels & Motels",
            "type":"Entertainment"
        }
    ],
    "sg:phone":"+1 404 288 8722",
    "sg:postcode":"30032",
    "sg:province":"GA",
    "sg:tags":[
        "operation"
    ],
    "sg:website":"www.the.ramada.com/decatur02487",
    "wof:name":"Ramada Inn",
    "wof:placetype":"venue"
},
  "geometry": {"coordinates":[-84.268416,33.754209],"type":"Point"}
}