{
  "type": "Feature",
  "properties": {
    "iso:country":"US",
    "sg:address":"6610 Broad St",
    "sg:city":"Douglasville",
    "sg:classifiers":[
        {
            "category":"Shopping",
            "subcategory":"Stationery & Office Supplies",
            "type":"Retail Goods"
        }
    ],
    "sg:phone":"+1 770 949 0937",
    "sg:postcode":"30134",
    "sg:province":"GA",
    "sg:tags":[
        "equipment"
    ],
    "sg:website":"www.stopetc.com",
    "wof:name":"Stop Etc Office Supplies",
    "wof:placetype":"venue"
},
  "geometry": {"coordinates":[-84.747902,33.771301],"type":"Point"}
}