{
  "type": "Feature",
  "properties": {
    "addr:full":"4166 Snapfinger Woods Dr Decatur GA 30035",
    "addr:housenumber":"4166",
    "addr:postcode":"30035",
    "addr:street":"Snapfinger Woods Dr",
    "iso:country":"US",
    "sg:address":"4166 Snapfinger Woods Dr",
    "sg:city":"Decatur",
    "sg:classifiers":[
        {
            "category":"Building & Trades",
            "subcategory":"Locksmith",
            "type":"Services"
        }
    ],
    "sg:phone":"+1 877 551 8584",
    "sg:postcode":"30035",
    "sg:province":"GA",
    "sg:tags":[
        "key"
    ],
    "wof:name":"1 24 Hour Emergency Locksmith",
    "wof:placetype":"venue"
},
  "geometry": {"coordinates":[-84.21990099999999,33.714739],"type":"Point"}
}