{
  "type": "Feature",
  "properties": {
    "addr:full":"1961 Wrens Hwy Thomson GA 30824",
    "addr:housenumber":"1961",
    "addr:postcode":"30824",
    "addr:street":"Wrens Hwy",
    "iso:country":"US",
    "sg:address":"1961 Wrens Hwy",
    "sg:city":"Thomson",
    "sg:classifiers":[
        {
            "category":"Restaurant",
            "type":"Food & Drink"
        }
    ],
    "sg:phone":"+1 706 595 0040",
    "sg:postcode":"30824",
    "sg:province":"GA",
    "sg:tags":[
        "eating"
    ],
    "wof:name":"Dyes Steak",
    "wof:placetype":"venue"
},
  "geometry": {"coordinates":[-82.48586299999999,33.425663],"type":"Point"}
}