{
  "type": "Feature",
  "properties": {
    "iso:country":"US",
    "sg:address":"510 Swanson Rd",
    "sg:city":"Tyrone",
    "sg:classifiers":[
        {
            "category":"Health Services",
            "subcategory":"Clinic",
            "type":"Services"
        },
        {
            "category":"Insurance",
            "subcategory":"Insurance Agent",
            "type":"Services"
        }
    ],
    "sg:phone":"+1 770 774 1445",
    "sg:postcode":"30290",
    "sg:province":"GA",
    "wof:name":"Capitol Group Health Svc",
    "wof:placetype":"venue"
},
  "geometry": {"coordinates":[-84.58153799999999,33.486625],"type":"Point"}
}