{
  "type": "Feature",
  "properties": {
    "addr:full":"757 Maner Ter SE Smyrna GA 30080",
    "addr:housenumber":"757",
    "addr:postcode":"30080",
    "addr:street":"Maner Ter Se",
    "iso:country":"US",
    "sg:address":"757 Maner Ter SE",
    "sg:city":"Smyrna",
    "sg:classifiers":[
        {
            "category":"Building & Trades",
            "subcategory":"Plumbing",
            "type":"Services"
        }
    ],
    "sg:phone":"+1 770 300 9469",
    "sg:postcode":"30080",
    "sg:province":"GA",
    "sg:tags":[
        "contractor"
    ],
    "wof:name":"Rf Mechanical",
    "wof:placetype":"venue"
},
  "geometry": {"coordinates":[-84.483456,33.827548],"type":"Point"}
}