{
  "type": "Feature",
  "properties": {
    "addr:full":"2514 Martin Luther King Jr Blvd Dalton GA 30721",
    "addr:housenumber":"2514",
    "addr:postcode":"30721",
    "addr:street":"Martin Luther King Jr Blvd",
    "iso:country":"US",
    "sg:address":"2514 Martin Luther King Jr Blvd",
    "sg:city":"Dalton",
    "sg:classifiers":[
        {
            "category":"Retail",
            "subcategory":"Repair Shop",
            "type":"Services"
        }
    ],
    "sg:phone":"+1 706 279 9217",
    "sg:postcode":"30721",
    "sg:province":"GA",
    "sg:tags":[
        "welding"
    ],
    "wof:name":"Holmes Portable Welding Inc",
    "wof:placetype":"venue"
},
  "geometry": {"coordinates":[-84.926576,34.779776],"type":"Point"}
}