{
  "type": "Feature",
  "properties": {
    "addr:full":"103 Walker Cir Wrens GA 30833",
    "addr:housenumber":"103",
    "addr:postcode":"30833",
    "addr:street":"Walker Cir",
    "iso:country":"US",
    "sg:address":"103 Walker Cir",
    "sg:city":"Wrens",
    "sg:classifiers":[
        {
            "category":"Personal",
            "subcategory":"Beauty Salon",
            "type":"Services"
        }
    ],
    "sg:phone":"+1 706 547 0080",
    "sg:postcode":"30833",
    "sg:province":"GA",
    "wof:name":"Ramsey Nail Salon",
    "wof:placetype":"venue"
},
  "geometry": {"coordinates":[-82.388381,33.205972],"type":"Point"}
}