{
  "type": "Feature",
  "properties": {
    "addr:full":"8302 Seabolt Dr Cumming GA 30028",
    "addr:housenumber":"8302",
    "addr:postcode":"30028",
    "addr:street":"Seabolt Dr",
    "iso:country":"US",
    "sg:address":"8302 Seabolt Dr",
    "sg:city":"Cumming",
    "sg:classifiers":[
        {
            "category":"Building & Trades",
            "subcategory":"Construction",
            "type":"Services"
        }
    ],
    "sg:phone":"+1 770 844 1119",
    "sg:postcode":"30028",
    "sg:province":"GA",
    "sg:tags":[
        "welder"
    ],
    "wof:name":"Echols Welding & Fabrication",
    "wof:placetype":"venue"
},
  "geometry": {"coordinates":[-84.221481,34.297379],"type":"Point"}
}