{
  "type": "Feature",
  "properties": {
    "iso:country":"US",
    "sg:address":"3196 E Ponce de Leon Ave",
    "sg:city":"Scottdale",
    "sg:classifiers":[
        {
            "category":"Wholesale",
            "subcategory":"Machinery & Supplies",
            "type":"Manufacturing & Wholesale Goods"
        }
    ],
    "sg:phone":"+1 404 294 5321",
    "sg:postcode":"30079",
    "sg:province":"GA",
    "sg:tags":[
        "equipment",
        "hydraulic"
    ],
    "wof:name":"Alvin's Garage Equipment",
    "wof:placetype":"venue"
},
  "geometry": {"coordinates":[-84.264809,33.789201],"type":"Point"}
}