{
  "type": "Feature",
  "properties": {
    "iso:country":"US",
    "sg:address":"100 Greystone Dr",
    "sg:city":"McDonough",
    "sg:classifiers":[
        {
            "category":"Real Estate",
            "subcategory":"Real Estate Operator",
            "type":"Services"
        }
    ],
    "sg:phone":"+1 678 583 1812",
    "sg:postcode":"30252",
    "sg:province":"GA",
    "sg:tags":[
        "apartment"
    ],
    "wof:name":"Greystone Apartments",
    "wof:placetype":"venue"
},
  "geometry": {"coordinates":[-84.13211699999999,33.432759],"type":"Point"}
}