{
  "type": "Feature",
  "properties": {
    "iso:country":"US",
    "sg:address":"302 Winifred Rd",
    "sg:city":"Leesburg",
    "sg:classifiers":[
        {
            "category":"Government",
            "subcategory":"Office",
            "type":"Public Place"
        }
    ],
    "sg:phone":"+1 229 439 8181",
    "sg:postcode":"31763",
    "sg:province":"GA",
    "sg:tags":[
        "federal"
    ],
    "wof:name":"US Federal Aviation Adm",
    "wof:placetype":"venue"
},
  "geometry": {"coordinates":[-84.28865999999999,31.660096],"type":"Point"}
}