{
  "type": "Feature",
  "properties": {
    "addr:full":"5028 State Rte 33 N Moultrie GA 31768",
    "addr:housenumber":"5028",
    "addr:postcode":"31768",
    "addr:street":"State Rte 33 N",
    "iso:country":"US",
    "sg:address":"5028 State Rte 33 N",
    "sg:city":"Moultrie",
    "sg:classifiers":[
        {
            "category":"Professional",
            "type":"Services"
        }
    ],
    "sg:phone":"+1 229 782 7142",
    "sg:postcode":"31768",
    "sg:province":"GA",
    "wof:name":"Scottish Heritage",
    "wof:placetype":"venue"
},
  "geometry": {"coordinates":[-83.818478,31.2925],"type":"Point"}
}