{
  "type": "Feature",
  "properties": {
    "iso:country":"US",
    "sg:address":"2258 Mount Zion Rd",
    "sg:city":"Jonesboro",
    "sg:classifiers":[
        {
            "category":"Professional",
            "subcategory":"Lawyer & Legal Services",
            "type":"Services"
        }
    ],
    "sg:phone":"+1 770 478 9950",
    "sg:postcode":"30236",
    "sg:province":"GA",
    "wof:name":"Fincher Steven M Atty",
    "wof:placetype":"venue"
},
  "geometry": {"coordinates":[-84.317902,33.5602],"type":"Point"}
}