{
  "type": "Feature",
  "properties": {
    "addr:full":"2752 US Hwy 129 Cleveland GA 30528",
    "addr:housenumber":"2752",
    "addr:postcode":"30528",
    "addr:street":"Us Hwy 129",
    "iso:country":"US",
    "sg:address":"2752 US Hwy 129",
    "sg:city":"Cleveland",
    "sg:classifiers":[
        {
            "category":"Retail",
            "subcategory":"Auto Repair",
            "type":"Services"
        }
    ],
    "sg:phone":"+1 706 348 1744",
    "sg:postcode":"30528",
    "sg:province":"GA",
    "sg:tags":[
        "automobile",
        "frame",
        "straightening"
    ],
    "wof:name":"Don's Auto Frame Shop",
    "wof:placetype":"venue"
},
  "geometry": {"coordinates":[-83.760779,34.551738],"type":"Point"}
}