{
  "type": "Feature",
  "properties": {
    "addr:full":"716 Cedar Ave NW Atlanta GA 30318",
    "addr:housenumber":"716",
    "addr:postcode":"30318",
    "addr:street":"Cedar Ave Nw",
    "iso:country":"US",
    "sg:address":"716 Cedar Ave NW",
    "sg:city":"Atlanta",
    "sg:classifiers":[
        {
            "category":"Personal",
            "type":"Services"
        }
    ],
    "sg:phone":"+1 404 768 6514",
    "sg:postcode":"30318",
    "sg:province":"GA",
    "sg:tags":[
        "information"
    ],
    "wof:name":"GATCHA",
    "wof:placetype":"venue"
},
  "geometry": {"coordinates":[-84.465042,33.775358],"type":"Point"}
}