{
  "type": "Feature",
  "properties": {
    "iso:country":"US",
    "sg:address":"9525 Knollcrest Blvd",
    "sg:city":"Alpharetta",
    "sg:classifiers":[
        {
            "category":"Professional",
            "subcategory":"Management & Consulting",
            "type":"Services"
        }
    ],
    "sg:phone":"+1 770 409 1343",
    "sg:postcode":"30022",
    "sg:province":"GA",
    "wof:name":"Jackson Wong & Assoc",
    "wof:placetype":"venue"
},
  "geometry": {"coordinates":[-84.210109,34.010618],"type":"Point"}
}