{
  "type": "Feature",
  "properties": {
    "iso:country":"US",
    "sg:address":"102 Martha Dr",
    "sg:city":"St Marys",
    "sg:classifiers":[
        {
            "category":"Insurance",
            "subcategory":"Insurance Agent",
            "type":"Services"
        }
    ],
    "sg:phone":"+1 912 882 5702",
    "sg:postcode":"31558",
    "sg:province":"GA",
    "wof:name":"Smith Insurance",
    "wof:placetype":"venue"
},
  "geometry": {"coordinates":[-81.569053,30.756827],"type":"Point"}
}