{
  "type": "Feature",
  "properties": {
    "iso:country":"US",
    "sg:address":"12637 Cornish Walk",
    "sg:city":"Alpharetta",
    "sg:classifiers":[
        {
            "category":"Professional",
            "subcategory":"Business Services",
            "type":"Services"
        }
    ],
    "sg:phone":"+1 770 339 0686",
    "sg:postcode":"30005",
    "sg:province":"GA",
    "wof:name":"Grove Park Interiors",
    "wof:placetype":"venue"
},
  "geometry": {"coordinates":[-84.19714500000001,34.08782],"type":"Point"}
}