{
  "type": "Feature",
  "properties": {
    "addr:full":"4075 Elnora Dr Macon GA 31210",
    "addr:housenumber":"4075",
    "addr:postcode":"31210",
    "addr:street":"Elnora Dr",
    "iso:country":"US",
    "sg:address":"4075 Elnora Dr",
    "sg:city":"Macon",
    "sg:classifiers":[
        {
            "category":"Health Services",
            "subcategory":"Doctor",
            "type":"Services"
        }
    ],
    "sg:phone":"+1 478 757 7888",
    "sg:postcode":"31210",
    "sg:province":"GA",
    "sg:tags":[
        "physician",
        "surgeon",
        "medical"
    ],
    "wof:name":"Central Georgia Fertility Inst",
    "wof:placetype":"venue"
},
  "geometry": {"coordinates":[-83.69304099999999,32.898737],"type":"Point"}
}