{
  "type": "Feature",
  "properties": {
    "addr:full":"2571 Brookhaven Chase Ln NE Atlanta GA 30319",
    "addr:housenumber":"2571",
    "addr:postcode":"30319",
    "addr:street":"Brookhaven Chase Ln Ne",
    "iso:country":"US",
    "sg:address":"2571 Brookhaven Chase Ln NE",
    "sg:city":"Atlanta",
    "sg:classifiers":[
        {
            "category":"Sports & Exercise",
            "subcategory":"Sports Center",
            "type":"Entertainment"
        }
    ],
    "sg:phone":"+1 404 814 2254",
    "sg:postcode":"30319",
    "sg:province":"GA",
    "sg:tags":[
        "manager",
        "promoter"
    ],
    "wof:name":"Vye, Andrew",
    "wof:placetype":"venue"
},
  "geometry": {"coordinates":[-84.339203,33.856159],"type":"Point"}
}