{
  "type": "Feature",
  "properties": {
    "iso:country":"US",
    "sg:address":"1313 Turner Mccall Blvd SE",
    "sg:city":"Rome",
    "sg:classifiers":[
        {
            "category":"Restaurant",
            "type":"Food & Drink"
        }
    ],
    "sg:menulink":"http://www.allmenus.com/ga/rome/160529-burger-king/menu/",
    "sg:phone":"+1 706 234 0072",
    "sg:postcode":"30161",
    "sg:province":"GA",
    "sg:tags":[
        "burger",
        "american"
    ],
    "wof:name":"Burger King",
    "wof:placetype":"venue"
},
  "geometry": {"coordinates":[-85.163758,34.253471],"type":"Point"}
}