{
  "type": "Feature",
  "properties": {
    "iso:country":"US",
    "sg:address":"104 W Wilson St",
    "sg:city":"Leslie",
    "sg:classifiers":[
        {
            "category":"Personal",
            "subcategory":"Beauty Salon",
            "type":"Services"
        }
    ],
    "sg:phone":"+1 229 874 7268",
    "sg:postcode":"31764",
    "sg:province":"GA",
    "sg:tags":[
        "shop"
    ],
    "wof:name":"Heavenly Hands Hair Salon",
    "wof:placetype":"venue"
},
  "geometry": {"coordinates":[-84.08749,31.954459],"type":"Point"}
}