{
  "type": "Feature",
  "properties": {
    "iso:country":"US",
    "sg:address":"6978 Rogers Lake Rd",
    "sg:city":"Lithonia",
    "sg:classifiers":[
        {
            "category":"Building & Trades",
            "subcategory":"Construction",
            "type":"Services"
        }
    ],
    "sg:phone":"+1 770 482 6790",
    "sg:postcode":"30058",
    "sg:province":"GA",
    "sg:tags":[
        "material",
        "paving"
    ],
    "wof:name":"Shepherd Construction Co",
    "wof:placetype":"venue"
},
  "geometry": {"coordinates":[-84.107422,33.72337],"type":"Point"}
}