{
  "type": "Feature",
  "properties": {
    "iso:country":"US",
    "sg:address":"72 Hamilton Ave NW",
    "sg:city":"Rome",
    "sg:classifiers":[
        {
            "category":"Real Estate",
            "subcategory":"Real Estate Operator",
            "type":"Services"
        }
    ],
    "sg:phone":"+1 706 291 0694",
    "sg:postcode":"30165",
    "sg:province":"GA",
    "sg:tags":[
        "apartment"
    ],
    "wof:name":"Hamilton Ridge Apartments",
    "wof:placetype":"venue"
},
  "geometry": {"coordinates":[-85.189018,34.26416],"type":"Point"}
}