{
  "type": "Feature",
  "properties": {
    "iso:country":"US",
    "sg:address":"665 Grady Place",
    "sg:city":"Atlanta",
    "sg:classifiers":[
        {
            "category":"Home & Garden",
            "subcategory":"Carpets & Floor Coverings",
            "type":"Retail Goods"
        }
    ],
    "sg:phone":"+1 678 469 0741",
    "sg:postcode":"30310",
    "sg:province":"GA",
    "sg:tags":[
        "material",
        "flooring"
    ],
    "wof:name":"Atlanta Metro Flooring",
    "wof:placetype":"venue"
},
  "geometry": {"coordinates":[-84.42691000000001,33.736878],"type":"Point"}
}