{
  "type": "Feature",
  "properties": {
    "addr:full":"5352 Rockwood Ct SW Stone Mountain GA 30087",
    "addr:housenumber":"5352",
    "addr:postcode":"30087",
    "addr:street":"Rockwood Ct Sw",
    "iso:country":"US",
    "sg:address":"5352 Rockwood Ct SW",
    "sg:city":"Stone Mountain",
    "sg:classifiers":[
        {
            "category":"Banks & Credit Unions",
            "subcategory":"Financial Services",
            "type":"Services"
        }
    ],
    "sg:phone":"+1 770 469 4150",
    "sg:postcode":"30087",
    "sg:province":"GA",
    "sg:tags":[
        "trust",
        "management"
    ],
    "wof:name":"Sterling A Huff Jr",
    "wof:placetype":"venue"
},
  "geometry": {"coordinates":[-84.109604,33.811947],"type":"Point"}
}