{
  "type": "Feature",
  "properties": {
    "iso:country":"US",
    "sg:address":"612 Vermillion Ln",
    "sg:city":"Peachtree City",
    "sg:classifiers":[
        {
            "category":"Professional",
            "type":"Services"
        }
    ],
    "sg:phone":"+1 770 486 7771",
    "sg:postcode":"30269",
    "sg:province":"GA",
    "wof:name":"Gary L Hinkle",
    "wof:placetype":"venue"
},
  "geometry": {"coordinates":[-84.59986600000001,33.392021],"type":"Point"}
}