{
  "type": "Feature",
  "properties": {
    "addr:full":"258 S Main St Jonesboro GA 30236",
    "addr:housenumber":"258",
    "addr:postcode":"30236",
    "addr:street":"S Main St",
    "iso:country":"US",
    "sg:address":"258 S Main St",
    "sg:city":"Jonesboro",
    "sg:classifiers":[
        {
            "category":"Shopping",
            "subcategory":"Used Merchandise",
            "type":"Retail Goods"
        }
    ],
    "sg:phone":"+1 770 477 1646",
    "sg:postcode":"30236",
    "sg:province":"GA",
    "sg:tags":[
        "pawnbroker",
        "pawnshop"
    ],
    "wof:name":"Jonesboro Exchange The",
    "wof:placetype":"venue"
},
  "geometry": {"coordinates":[-84.35256200000001,33.511832],"type":"Point"}
}