{
  "type": "Feature",
  "properties": {
    "addr:full":"926 Hollywood Dr Lot 48 Hinesville GA 31313",
    "addr:housenumber":"926;48",
    "addr:postcode":"31313",
    "addr:street":"Hollywood Dr Lot",
    "iso:country":"US",
    "sg:address":"926 Hollywood Dr Lot 48",
    "sg:city":"Hinesville",
    "sg:classifiers":[
        {
            "category":"Restaurant",
            "type":"Food & Drink"
        }
    ],
    "sg:phone":"+1 662 352 9225",
    "sg:postcode":"31313",
    "sg:province":"GA",
    "wof:name":"Mcelveen's Sports Bar And Grill",
    "wof:placetype":"venue"
},
  "geometry": {"coordinates":[-81.62351200000001,31.823891],"type":"Point"}
}