{
  "type": "Feature",
  "properties": {
    "addr:full":"1573 Egg And Butter Rd S Thomasville GA 31757",
    "addr:housenumber":"1573",
    "addr:postcode":"31757",
    "addr:street":"And Butter Rd",
    "iso:country":"US",
    "sg:address":"1573 Egg And Butter Rd S",
    "sg:city":"Thomasville",
    "sg:classifiers":[
        {
            "category":"Education",
            "subcategory":"Library",
            "type":"Public Place"
        }
    ],
    "sg:phone":"+1 229 228 1397",
    "sg:postcode":"31757",
    "sg:province":"GA",
    "sg:website":"http://www.southgeorgiarelic.org",
    "wof:name":"South Georgia Relic Resource Library Inc",
    "wof:placetype":"venue"
},
  "geometry": {"coordinates":[-83.979669,30.918413],"type":"Point"}
}