{
  "type": "Feature",
  "properties": {
    "addr:full":"310 E Oak St Mc Rae GA 31055",
    "addr:housenumber":"310",
    "addr:postcode":"31055",
    "addr:street":"E Oak St Mc Rae",
    "iso:country":"US",
    "sg:address":"310 E Oak St",
    "sg:city":"Mc Rae",
    "sg:classifiers":[
        {
            "category":"Restaurant",
            "type":"Food & Drink"
        }
    ],
    "sg:phone":"+1 229 868 6438",
    "sg:postcode":"31055",
    "sg:province":"GA",
    "sg:tags":[
        "pizza"
    ],
    "wof:name":"Village Pizza",
    "wof:placetype":"venue"
},
  "geometry": {"coordinates":[-82.88053499999999,32.0599],"type":"Point"}
}