{
  "type": "Feature",
  "properties": {
    "addr:full":"627 Maddox Dr Ellijay GA 30540",
    "addr:housenumber":"627",
    "addr:postcode":"30540",
    "addr:street":"Maddox Dr Ellijay",
    "iso:country":"US",
    "sg:address":"627 Maddox Dr",
    "sg:city":"Ellijay",
    "sg:classifiers":[
        {
            "category":"Shopping",
            "subcategory":"Hobbies, Toys, & Games",
            "type":"Retail Goods"
        },
        {
            "category":"Shopping",
            "subcategory":"Pawn Shop",
            "type":"Retail Goods"
        },
        {
            "category":"Recreation",
            "subcategory":"Gun Range",
            "type":"Entertainment"
        }
    ],
    "sg:phone":"+1 706 276 7296",
    "sg:postcode":"30540",
    "sg:province":"GA",
    "sg:tags":[
        "pawnbroker",
        "safety",
        "instruction",
        "marksmanship",
        "gunsmith"
    ],
    "wof:name":"East Ellijay Pawn",
    "wof:placetype":"venue"
},
  "geometry": {"coordinates":[-84.48423099999999,34.679764],"type":"Point"}
}