{
  "type": "Feature",
  "properties": {
    "iso:country":"US",
    "sg:address":"4105 Bridle Ridge Dr",
    "sg:city":"Suwanee",
    "sg:classifiers":[
        {
            "category":"Real Estate",
            "subcategory":"Real Estate Agent",
            "type":"Services"
        }
    ],
    "sg:phone":"+1 678 513 0993",
    "sg:postcode":"30024",
    "sg:province":"GA",
    "wof:name":"Regency Real Estate Partners",
    "wof:placetype":"venue"
},
  "geometry": {"coordinates":[-84.170036,34.086242],"type":"Point"}
}