{
  "type": "Feature",
  "properties": {
    "iso:country":"US",
    "sg:address":"7750 Wentworth Dr",
    "sg:city":"Duluth",
    "sg:classifiers":[
        {
            "category":"Professional",
            "type":"Services"
        }
    ],
    "sg:phone":"+1 770 495 8800",
    "sg:postcode":"30097",
    "sg:province":"GA",
    "wof:name":"Cdg",
    "wof:placetype":"venue"
},
  "geometry": {"coordinates":[-84.150509,34.067589],"type":"Point"}
}