{
  "type": "Feature",
  "properties": {
    "iso:country":"US",
    "sg:address":"1411 Dresden Dr NE",
    "sg:city":"Atlanta",
    "sg:classifiers":[
        {
            "category":"Organizations",
            "subcategory":"Religious Organization",
            "type":"Services"
        }
    ],
    "sg:phone":"+1 404 231 1049",
    "sg:postcode":"30319",
    "sg:province":"GA",
    "wof:name":"Ministry Of Spirit",
    "wof:placetype":"venue"
},
  "geometry": {"coordinates":[-84.331605,33.860755],"type":"Point"}
}