{
  "type": "Feature",
  "properties": {
    "iso:country":"US",
    "sg:address":"2490 Cruse Rd",
    "sg:city":"Lawrenceville",
    "sg:classifiers":[
        {
            "category":"Food & Beverages",
            "subcategory":"Groceries & Convenience Stores",
            "type":"Retail Goods"
        }
    ],
    "sg:phone":"+1 770 962 7375",
    "sg:postcode":"30044",
    "sg:province":"GA",
    "sg:website":"www.citgo.com",
    "wof:name":"Citgo Food Mart",
    "wof:placetype":"venue"
},
  "geometry": {"coordinates":[-84.07647799999999,33.942357],"type":"Point"}
}