{
  "type": "Feature",
  "properties": {
    "iso:country":"US",
    "sg:address":"209 Parkview Dr",
    "sg:city":"Cartersville",
    "sg:classifiers":[
        {
            "category":"Wholesale",
            "subcategory":"Farm Supplies",
            "type":"Manufacturing & Wholesale Goods"
        }
    ],
    "sg:phone":"+1 770 606 0040",
    "sg:postcode":"30120",
    "sg:province":"GA",
    "sg:tags":[
        "fertilizer"
    ],
    "wof:name":"Carolina Eastern-Atlanta",
    "wof:placetype":"venue"
},
  "geometry": {"coordinates":[-84.818326,34.147147],"type":"Point"}
}