{
  "type": "Feature",
  "properties": {
    "addr:full":"4605 Fulton Industrial Blvd SW Atlanta GA 30336",
    "addr:housenumber":"4605",
    "addr:postcode":"30336",
    "addr:street":"Fulton Industrial Blvd Sw",
    "iso:country":"US",
    "sg:address":"4605 Fulton Industrial Blvd SW",
    "sg:city":"Atlanta",
    "sg:classifiers":[
        {
            "category":"Professional",
            "type":"Services"
        },
        {
            "category":"Retail",
            "subcategory":"Auto Rental",
            "type":"Services"
        },
        {
            "category":"Building & Trades",
            "subcategory":"Equipment Rental",
            "type":"Services"
        },
        {
            "category":"Retail",
            "subcategory":"Storage",
            "type":"Services"
        }
    ],
    "sg:phone":"+1 866 205 7339",
    "sg:postcode":"30336",
    "sg:province":"GA",
    "sg:tags":[
        "renting",
        "moving-self",
        "leasing",
        "material",
        "moving",
        "services-labor",
        "truck",
        "trailer"
    ],
    "sg:website":"http://www.pensketruckrental.com/personal_rental/?cid=Yptmlist",
    "wof:name":"Penske Truck Rental",
    "wof:placetype":"venue"
},
  "geometry": {"coordinates":[-84.537705,33.761151],"type":"Point"}
}