{
  "type": "Feature",
  "properties": {
    "iso:country":"US",
    "sg:address":"141 Hicks Dr",
    "sg:city":"Perry",
    "sg:classifiers":[
        {
            "category":"Retail",
            "subcategory":"Repair Shop",
            "type":"Services"
        }
    ],
    "sg:phone":"+1 478 987 0906",
    "sg:postcode":"31069",
    "sg:province":"GA",
    "wof:name":"Utility Service Co Inc",
    "wof:placetype":"venue"
},
  "geometry": {"coordinates":[-83.765845,32.439433],"type":"Point"}
}