{
  "type": "Feature",
  "properties": {
    "addr:full":"107 Medical Dr Lagrange GA 30240",
    "addr:housenumber":"107",
    "addr:postcode":"30240",
    "addr:street":"Medical Dr",
    "iso:country":"US",
    "sg:address":"107 Medical Dr",
    "sg:city":"Lagrange",
    "sg:classifiers":[
        {
            "category":"Government",
            "subcategory":"Office",
            "type":"Public Place"
        }
    ],
    "sg:phone":"+1 706 845 4085",
    "sg:postcode":"30240",
    "sg:province":"GA",
    "sg:tags":[
        "state",
        "program",
        "health"
    ],
    "wof:name":"Health Dept",
    "wof:placetype":"venue"
},
  "geometry": {"coordinates":[-85.058143,33.031308],"type":"Point"}
}