{
  "type": "Feature",
  "properties": {
    "iso:country":"US",
    "sg:address":"2712 Lawrenceville Hwy",
    "sg:city":"Decatur",
    "sg:classifiers":[
        {
            "category":"Professional",
            "subcategory":"Credit Reporting & Collection",
            "type":"Services"
        }
    ],
    "sg:phone":"+1 770 491 0505",
    "sg:postcode":"30033",
    "sg:province":"GA",
    "wof:name":"Trillum Group Ltd",
    "wof:placetype":"venue"
},
  "geometry": {"coordinates":[-84.26193000000001,33.823403],"type":"Point"}
}