{
  "type": "Feature",
  "properties": {
    "iso:country":"US",
    "sg:address":"614 E Winthrope Ave",
    "sg:city":"Millen",
    "sg:classifiers":[
        {
            "category":"Personal",
            "subcategory":"Beauty Salon",
            "type":"Services"
        }
    ],
    "sg:phone":"+1 478 982 1506",
    "sg:postcode":"30442",
    "sg:province":"GA",
    "wof:name":"Kytrena's Hair Salon",
    "wof:placetype":"venue"
},
  "geometry": {"coordinates":[-81.938889,32.803695],"type":"Point"}
}