{
  "type": "Feature",
  "properties": {
    "addr:full":"116 Hillcrest Dr Dublin GA 31021",
    "addr:housenumber":"116",
    "addr:postcode":"31021",
    "addr:street":"Hillcrest Dr",
    "iso:country":"US",
    "sg:address":"116 Hillcrest Dr",
    "sg:city":"Dublin",
    "sg:classifiers":[
        {
            "category":"Shopping",
            "subcategory":"Shoes",
            "type":"Retail Goods"
        }
    ],
    "sg:phone":"+1 912 275 3369",
    "sg:postcode":"31021",
    "sg:province":"GA",
    "wof:name":"Meldisco K-M Hillcrest Dr Conn",
    "wof:placetype":"venue"
},
  "geometry": {"coordinates":[-82.912705,32.548511],"type":"Point"}
}