{
  "type": "Feature",
  "properties": {
    "addr:full":"2993 Bankhead Hwy Austell GA 30168",
    "addr:housenumber":"2993",
    "addr:postcode":"30168",
    "addr:street":"Bankhead Hwy",
    "iso:country":"US",
    "sg:address":"2993 Bankhead Hwy",
    "sg:city":"Austell",
    "sg:classifiers":[
        {
            "category":"Shopping",
            "subcategory":"Pawn Shop",
            "type":"Retail Goods"
        }
    ],
    "sg:phone":"+1 770 941 4390",
    "sg:postcode":"30168",
    "sg:province":"GA",
    "wof:name":"Title Max",
    "wof:placetype":"venue"
},
  "geometry": {"coordinates":[-84.636312,33.806382],"type":"Point"}
}