{
  "type": "Feature",
  "properties": {
    "addr:full":"5521 Clinchfield Trl Norcross GA 30092",
    "addr:housenumber":"5521",
    "addr:postcode":"30092",
    "addr:street":"Clinchfield Trl",
    "iso:country":"US",
    "sg:address":"5521 Clinchfield Trl",
    "sg:city":"Norcross",
    "sg:classifiers":[
        {
            "category":"Professional",
            "subcategory":"Management & Consulting",
            "type":"Services"
        }
    ],
    "sg:phone":"+1 770 449 0030",
    "sg:postcode":"30092",
    "sg:province":"GA",
    "wof:name":"BDL Enterprises Inc",
    "wof:placetype":"venue"
},
  "geometry": {"coordinates":[-84.231517,33.981862],"type":"Point"}
}