{
  "type": "Feature",
  "properties": {
    "addr:full":"4080 Washington Rd Martinez GA 30907",
    "addr:housenumber":"4080",
    "addr:postcode":"30907",
    "addr:street":"Washington Rd",
    "iso:country":"US",
    "sg:address":"4080 Washington Rd",
    "sg:city":"Martinez",
    "sg:classifiers":[
        {
            "category":"Freight",
            "type":"Transportation"
        }
    ],
    "sg:phone":"+1 706 651 8881",
    "sg:postcode":"30907",
    "sg:province":"GA",
    "sg:tags":[
        "commercial",
        "storage"
    ],
    "wof:name":"Washington Road Self Storage",
    "wof:placetype":"venue"
},
  "geometry": {"coordinates":[-82.10968699999999,33.514327],"type":"Point"}
}