{
  "type": "Feature",
  "properties": {
    "iso:country":"US",
    "sg:address":"114 Magnolia Dr",
    "sg:city":"Tifton",
    "sg:classifiers":[
        {
            "category":"Shopping",
            "subcategory":"Clothing, Apparel, & Fashions",
            "type":"Retail Goods"
        }
    ],
    "sg:phone":"+1 229 387 8737",
    "sg:postcode":"31794",
    "sg:province":"GA",
    "sg:tags":[
        "staff",
        "hotel",
        "uniform"
    ],
    "wof:name":"Uniform Works Inc",
    "wof:placetype":"venue"
},
  "geometry": {"coordinates":[-83.523201,31.462696],"type":"Point"}
}