{
  "type": "Feature",
  "properties": {
    "addr:full":"8701 Bowman Hwy Dewy Rose GA 30634",
    "addr:housenumber":"8701",
    "addr:postcode":"30634",
    "addr:street":"Bowman Hwy",
    "iso:country":"US",
    "sg:address":"8701 Bowman Hwy",
    "sg:city":"Dewy Rose",
    "sg:classifiers":[
        {
            "category":"Building & Trades",
            "subcategory":"Plumbing",
            "type":"Services"
        }
    ],
    "sg:phone":"+1 706 245 6075",
    "sg:postcode":"30634",
    "sg:province":"GA",
    "sg:tags":[
        "plumbing",
        "contractor"
    ],
    "wof:name":"Larry Saxon Appliance Svc",
    "wof:placetype":"venue"
},
  "geometry": {"coordinates":[-82.99757099999999,34.236952],"type":"Point"}
}