{
  "type": "Feature",
  "properties": {
    "addr:full":"4293 Arbor Club Dr Marietta GA 30066",
    "addr:housenumber":"4293",
    "addr:postcode":"30066",
    "addr:street":"Arbor Club Dr",
    "iso:country":"US",
    "sg:address":"4293 Arbor Club Dr",
    "sg:city":"Marietta",
    "sg:classifiers":[
        {
            "category":"Professional",
            "subcategory":"Management & Consulting",
            "type":"Services"
        }
    ],
    "sg:phone":"+1 770 928 4721",
    "sg:postcode":"30066",
    "sg:province":"GA",
    "sg:tags":[
        "business"
    ],
    "wof:name":"Littman Consulting Inc",
    "wof:placetype":"venue"
},
  "geometry": {"coordinates":[-84.47292,34.049034],"type":"Point"}
}