{
  "type": "Feature",
  "properties": {
    "iso:country":"US",
    "sg:address":"1924 Regents Ct NE",
    "sg:city":"Marietta",
    "sg:classifiers":[
        {
            "category":"Wholesale",
            "subcategory":"Machinery & Supplies",
            "type":"Manufacturing & Wholesale Goods"
        }
    ],
    "sg:phone":"+1 770 578 6912",
    "sg:postcode":"30062",
    "sg:province":"GA",
    "sg:tags":[
        "equipment",
        "industrial"
    ],
    "wof:name":"Blue Planet Inc",
    "wof:placetype":"venue"
},
  "geometry": {"coordinates":[-84.46996,33.997122],"type":"Point"}
}