{
  "type": "Feature",
  "properties": {
    "iso:country":"US",
    "sg:address":"4025 Pleasantdale Rd",
    "sg:city":"Atlanta",
    "sg:classifiers":[
        {
            "category":"Food & Beverages",
            "subcategory":"Liquor & Beverages",
            "type":"Retail Goods"
        },
        {
            "category":"Wholesale",
            "subcategory":"Wine & Distilled Alcoholic Beverages",
            "type":"Manufacturing & Wholesale Goods"
        }
    ],
    "sg:phone":"+1 678 421 9790",
    "sg:postcode":"30340",
    "sg:province":"GA",
    "sg:tags":[
        "broker"
    ],
    "wof:name":"Artisan Vines Distribution Corp",
    "wof:placetype":"venue"
},
  "geometry": {"coordinates":[-84.243523,33.89949],"type":"Point"}
}