{
  "type": "Feature",
  "properties": {
    "addr:full":"4140 Jonesboro Rd Forest Park GA 30297",
    "addr:housenumber":"4140",
    "addr:postcode":"30297",
    "addr:street":"Jonesboro Rd",
    "iso:country":"US",
    "sg:address":"4140 Jonesboro Rd",
    "sg:city":"Forest Park",
    "sg:classifiers":[
        {
            "category":"Social Services",
            "type":"Services"
        }
    ],
    "sg:phone":"+1 404 366 8677",
    "sg:postcode":"30297",
    "sg:province":"GA",
    "sg:tags":[
        "organization",
        "welfare"
    ],
    "wof:name":"An Viet",
    "wof:placetype":"venue"
},
  "geometry": {"coordinates":[-84.36252500000001,33.642304],"type":"Point"}
}