{
  "type": "Feature",
  "properties": {
    "iso:country":"US",
    "sg:address":"2797 Campbellton Rd SW",
    "sg:city":"Atlanta",
    "sg:classifiers":[
        {
            "category":"Health Services",
            "subcategory":"Health Practitioner",
            "type":"Services"
        }
    ],
    "sg:phone":"+1 404 349 2112",
    "sg:postcode":"30311",
    "sg:province":"GA",
    "wof:name":"Family Centered Midwifer",
    "wof:placetype":"venue"
},
  "geometry": {"coordinates":[-84.482173,33.699048],"type":"Point"}
}