{
  "type": "Feature",
  "properties": {
    "addr:full":"212 S 1st St Jesup GA 31545",
    "addr:housenumber":"212",
    "addr:postcode":"31545",
    "addr:street":"S 1St St",
    "iso:country":"US",
    "sg:address":"212 S 1st St",
    "sg:city":"Jesup",
    "sg:classifiers":[
        {
            "category":"Professional",
            "subcategory":"Accounting & Tax Preparation",
            "type":"Services"
        }
    ],
    "sg:phone":"+1 912 588 9509",
    "sg:postcode":"31545",
    "sg:province":"GA",
    "sg:tags":[
        "return"
    ],
    "wof:name":"Payday Advance & Tax Service",
    "wof:placetype":"venue"
},
  "geometry": {"coordinates":[-81.886668,31.606107],"type":"Point"}
}