{
  "type": "Feature",
  "properties": {
    "iso:country":"US",
    "sg:address":"111 Reese Dr",
    "sg:city":"Blakely",
    "sg:classifiers":[
        {
            "category":"Autos & Motor Vehicles",
            "subcategory":"Auto Supplies",
            "type":"Retail Goods"
        }
    ],
    "sg:phone":"+1 229 723 3534",
    "sg:postcode":"31705",
    "sg:province":"GA",
    "sg:tags":[
        "tire"
    ],
    "wof:name":"Day's Tire Svc Ctr",
    "wof:placetype":"venue"
},
  "geometry": {"coordinates":[-84.138564,31.545757],"type":"Point"}
}