{
  "type": "Feature",
  "properties": {
    "iso:country":"US",
    "sg:address":"912 Martin Luther King Jr Dr",
    "sg:city":"Dublin",
    "sg:classifiers":[
        {
            "category":"Organizations",
            "subcategory":"Religious Organization",
            "type":"Services"
        }
    ],
    "sg:phone":"+1 478 272 7387",
    "sg:postcode":"31021",
    "sg:province":"GA",
    "sg:tags":[
        "church"
    ],
    "wof:name":"St Peters Baptist Church",
    "wof:placetype":"venue"
},
  "geometry": {"coordinates":[-82.900779,32.526139],"type":"Point"}
}