{
  "type": "Feature",
  "properties": {
    "addr:full":"2501 E Piedmont Rd Marietta GA 30062",
    "addr:housenumber":"2501",
    "addr:postcode":"30062",
    "addr:street":"E Piedmont Rd",
    "iso:country":"US",
    "sg:address":"2501 E Piedmont Rd",
    "sg:city":"Marietta",
    "sg:classifiers":[
        {
            "category":"Real Estate",
            "subcategory":"Real Estate Agent",
            "type":"Services"
        }
    ],
    "sg:phone":"+1 770 575 5700",
    "sg:postcode":"30062",
    "sg:province":"GA",
    "wof:name":"Innova Center",
    "wof:placetype":"venue"
},
  "geometry": {"coordinates":[-84.49015300000001,34.010253],"type":"Point"}
}