{
  "type": "Feature",
  "properties": {
    "iso:country":"US",
    "sg:address":"3006 Lake Park Trl",
    "sg:city":"Acworth",
    "sg:classifiers":[
        {
            "category":"Building & Trades",
            "subcategory":"Landscaping Services",
            "type":"Services"
        }
    ],
    "sg:phone":"+1 404 993 0533",
    "sg:postcode":"30101",
    "sg:province":"GA",
    "wof:name":"Pinnacle Ldscp MGT Group LLC",
    "wof:placetype":"venue"
},
  "geometry": {"coordinates":[-84.640333,34.067487],"type":"Point"}
}