{
  "type": "Feature",
  "properties": {
    "addr:full":"1 Sanderson St NE Atlanta GA 30307",
    "addr:housenumber":"1",
    "addr:postcode":"30307",
    "addr:street":"Sanderson St Ne",
    "iso:country":"US",
    "sg:address":"1 Sanderson St NE",
    "sg:city":"Atlanta",
    "sg:classifiers":[
        {
            "category":"Building & Trades",
            "subcategory":"Locksmith",
            "type":"Services"
        }
    ],
    "sg:phone":"+1 404 736 9598",
    "sg:postcode":"30307",
    "sg:province":"GA",
    "sg:tags":[
        "key"
    ],
    "wof:name":"1 Hour All A 24 Locksmith",
    "wof:placetype":"venue"
},
  "geometry": {"coordinates":[-84.345725,33.75341],"type":"Point"}
}