{
  "type": "Feature",
  "properties": {
    "addr:full":"6295 Weatherly Dr NW Atlanta GA 30328",
    "addr:housenumber":"6295",
    "addr:postcode":"30328",
    "addr:street":"Weatherly Dr Nw",
    "iso:country":"US",
    "sg:address":"6295 Weatherly Dr NW",
    "sg:city":"Atlanta",
    "sg:classifiers":[
        {
            "category":"Real Estate",
            "subcategory":"Real Estate Agent",
            "type":"Services"
        }
    ],
    "sg:phone":"+1 404 255 7124",
    "sg:postcode":"30328",
    "sg:province":"GA",
    "wof:name":"Almmo LLC",
    "wof:placetype":"venue"
},
  "geometry": {"coordinates":[-84.41375600000001,33.92477],"type":"Point"}
}