{
  "type": "Feature",
  "properties": {
    "addr:full":"2170 Panola Way Ct Lithonia GA 30058",
    "addr:housenumber":"2170",
    "addr:postcode":"30058",
    "addr:street":"Panola Way Ct",
    "iso:country":"US",
    "sg:address":"2170 Panola Way Ct",
    "sg:city":"Lithonia",
    "sg:classifiers":[
        {
            "category":"Building & Trades",
            "subcategory":"Construction",
            "type":"Services"
        }
    ],
    "sg:phone":"+1 770 323 2803",
    "sg:postcode":"30058",
    "sg:province":"GA",
    "sg:tags":[
        "house"
    ],
    "wof:name":"DNB Builders Inc",
    "wof:placetype":"venue"
},
  "geometry": {"coordinates":[-84.16965399999999,33.729765],"type":"Point"}
}