{
  "type": "Feature",
  "properties": {
    "addr:full":"3025 Woodfield Dr Dublin GA 31021",
    "addr:housenumber":"3025",
    "addr:postcode":"31021",
    "addr:street":"Woodfield Dr",
    "iso:country":"US",
    "sg:address":"3025 Woodfield Dr",
    "sg:city":"Dublin",
    "sg:classifiers":[
        {
            "category":"Retail",
            "subcategory":"Car Wash",
            "type":"Services"
        }
    ],
    "sg:phone":"+1 912 529 6853",
    "sg:postcode":"31021",
    "sg:province":"GA",
    "wof:name":"Central Drive Wash and Shine",
    "wof:placetype":"venue"
},
  "geometry": {"coordinates":[-82.90100099999999,32.449535],"type":"Point"}
}