{
  "type": "Feature",
  "properties": {
    "addr:full":"102 Crain Dr Cumming GA 30040",
    "addr:housenumber":"102",
    "addr:postcode":"30040",
    "addr:street":"Crain Dr",
    "iso:country":"US",
    "sg:address":"102 Crain Dr",
    "sg:city":"Cumming",
    "sg:classifiers":[
        {
            "category":"Professional",
            "type":"Services"
        }
    ],
    "sg:phone":"+1 770 887 2456",
    "sg:postcode":"30040",
    "sg:province":"GA",
    "wof:name":"Doyle Jones",
    "wof:placetype":"venue"
},
  "geometry": {"coordinates":[-84.13434700000001,34.225442],"type":"Point"}
}