{
  "type": "Feature",
  "properties": {
    "addr:full":"11 Glenmar Dr Newnan GA 30263",
    "addr:housenumber":"11",
    "addr:postcode":"30263",
    "addr:street":"Glenmar Dr",
    "iso:country":"US",
    "sg:address":"11 Glenmar Dr",
    "sg:city":"Newnan",
    "sg:classifiers":[
        {
            "category":"Building & Trades",
            "subcategory":"Construction",
            "type":"Services"
        }
    ],
    "sg:phone":"+1 770 252 9959",
    "sg:postcode":"30263",
    "sg:province":"GA",
    "sg:tags":[
        "carpenter"
    ],
    "wof:name":"Dale Carpenter Dale Carpenter",
    "wof:placetype":"venue"
},
  "geometry": {"coordinates":[-84.847768,33.357735],"type":"Point"}
}