{
  "type": "Feature",
  "properties": {
    "iso:country":"US",
    "sg:address":"28 Womack Rd",
    "sg:city":"Covington",
    "sg:classifiers":[
        {
            "category":"Real Estate",
            "subcategory":"Real Estate Operator",
            "type":"Services"
        }
    ],
    "sg:phone":"+1 678 625 2455",
    "sg:postcode":"30016",
    "sg:province":"GA",
    "sg:tags":[
        "building",
        "nonresidential"
    ],
    "wof:name":"Suburban Properties",
    "wof:placetype":"venue"
},
  "geometry": {"coordinates":[-83.951159,33.61068],"type":"Point"}
}