{
  "type": "Feature",
  "properties": {
    "addr:full":"1097 Radar Cir Marietta GA 30062",
    "addr:housenumber":"1097",
    "addr:postcode":"30062",
    "addr:street":"Radar Cir",
    "iso:country":"US",
    "sg:address":"1097 Radar Cir",
    "sg:city":"Marietta",
    "sg:classifiers":[
        {
            "category":"Autos & Motor Vehicles",
            "subcategory":"Automobile Sales",
            "type":"Retail Goods"
        }
    ],
    "sg:phone":"+1 770 426 7009",
    "sg:postcode":"30062",
    "sg:province":"GA",
    "sg:tags":[
        "car",
        "used",
        "dealer"
    ],
    "wof:name":"J & B Auto Sales Inc",
    "wof:placetype":"venue"
},
  "geometry": {"coordinates":[-84.519701,33.951053],"type":"Point"}
}