{
  "type": "Feature",
  "properties": {
    "iso:country":"US",
    "sg:address":"308 S Dandy St",
    "sg:city":"Saint Marys",
    "sg:classifiers":[
        {
            "category":"Building & Trades",
            "subcategory":"Construction",
            "type":"Services"
        }
    ],
    "sg:phone":"+1 912 882 8969",
    "sg:postcode":"31558",
    "sg:province":"GA",
    "sg:tags":[
        "house"
    ],
    "wof:name":"A D Renovation",
    "wof:placetype":"venue"
},
  "geometry": {"coordinates":[-81.563306,30.742262],"type":"Point"}
}