{
  "type": "Feature",
  "properties": {
    "iso:country":"US",
    "sg:address":"87 Laurel Forest Cir NE",
    "sg:city":"Atlanta",
    "sg:classifiers":[
        {
            "category":"Manufacturing",
            "subcategory":"Food",
            "type":"Manufacturing & Wholesale Goods"
        }
    ],
    "sg:phone":"+1 404 895 4488",
    "sg:postcode":"30342",
    "sg:province":"GA",
    "sg:tags":[
        "drink",
        "soft",
        "mfg"
    ],
    "wof:name":"Noel Marts Cola",
    "wof:placetype":"venue"
},
  "geometry": {"coordinates":[-84.384733,33.862739],"type":"Point"}
}