{
  "type": "Feature",
  "properties": {
    "addr:full":"8034 Covington Hwy Lithonia GA 30058",
    "addr:housenumber":"8034",
    "addr:postcode":"30058",
    "addr:street":"Covington Hwy",
    "iso:country":"US",
    "sg:address":"8034 Covington Hwy",
    "sg:city":"Lithonia",
    "sg:classifiers":[
        {
            "category":"Bars & Pubs",
            "type":"Food & Drink"
        }
    ],
    "sg:phone":"+1 770 482 6542",
    "sg:postcode":"30058",
    "sg:province":"GA",
    "sg:tags":[
        "drinking"
    ],
    "wof:name":"Double G",
    "wof:placetype":"venue"
},
  "geometry": {"coordinates":[-84.09195099999999,33.702332],"type":"Point"}
}