{
  "type": "Feature",
  "properties": {
    "iso:country":"US",
    "sg:address":"481 Dickson Rd",
    "sg:city":"Marietta",
    "sg:classifiers":[
        {
            "category":"Building & Trades",
            "subcategory":"Construction",
            "type":"Services"
        }
    ],
    "sg:phone":"+1 770 499 7938",
    "sg:postcode":"30066",
    "sg:province":"GA",
    "sg:tags":[
        "restoration",
        "cleaning",
        "patio",
        "deck"
    ],
    "wof:name":"ABC Pressure Washing",
    "wof:placetype":"venue"
},
  "geometry": {"coordinates":[-84.536419,33.986242],"type":"Point"}
}