{
  "type": "Feature",
  "properties": {
    "iso:country":"US",
    "sg:address":"5500 Buford Hwy NE",
    "sg:city":"Atlanta",
    "sg:classifiers":[
        {
            "category":"Autos & Motor Vehicles",
            "subcategory":"Fuel & Gas Station",
            "type":"Retail Goods"
        }
    ],
    "sg:phone":"+1 770 220 0450",
    "sg:postcode":"30340",
    "sg:province":"GA",
    "wof:name":"Speedy's",
    "wof:placetype":"venue"
},
  "geometry": {"coordinates":[-84.277,33.900398],"type":"Point"}
}