{
  "type": "Feature",
  "properties": {
    "iso:country":"US",
    "sg:address":"508 Mill Pond Ct SE",
    "sg:city":"Smyrna",
    "sg:classifiers":[
        {
            "category":"Manufacturing",
            "subcategory":"Metals",
            "type":"Manufacturing & Wholesale Goods"
        },
        {
            "category":"Professional",
            "type":"Services"
        }
    ],
    "sg:phone":"+1 770 434 5558",
    "sg:postcode":"30082",
    "sg:province":"GA",
    "sg:tags":[
        "fiber",
        "optics",
        "system"
    ],
    "wof:name":"Fiber Connect Inc",
    "wof:placetype":"venue"
},
  "geometry": {"coordinates":[-84.522593,33.859263],"type":"Point"}
}