{
  "type": "Feature",
  "properties": {
    "addr:full":"840 Shallowford Rd NE Kennesaw GA 30144",
    "addr:housenumber":"840",
    "addr:postcode":"30144",
    "addr:street":"Shallowford Rd Ne",
    "iso:country":"US",
    "sg:address":"840 Shallowford Rd NE",
    "sg:city":"Kennesaw",
    "sg:classifiers":[
        {
            "category":"Retail",
            "subcategory":"Auto Repair",
            "type":"Services"
        }
    ],
    "sg:phone":"+1 678 445 8887",
    "sg:postcode":"30144",
    "sg:province":"GA",
    "sg:tags":[
        "repairing",
        "automobile"
    ],
    "wof:name":"Faith Automotive",
    "wof:placetype":"venue"
},
  "geometry": {"coordinates":[-84.522385,34.063958],"type":"Point"}
}