{
  "type": "Feature",
  "properties": {
    "addr:full":"5071 Peachtree Industrial Blvd Chamblee GA 30341",
    "addr:housenumber":"5071",
    "addr:postcode":"30341",
    "addr:street":"Peachtree Industrial Blvd",
    "iso:country":"US",
    "sg:address":"5071 Peachtree Industrial Blvd",
    "sg:city":"Chamblee",
    "sg:classifiers":[
        {
            "category":"Wholesale",
            "subcategory":"Office Equipment",
            "type":"Manufacturing & Wholesale Goods"
        }
    ],
    "sg:phone":"+1 770 457 6554",
    "sg:postcode":"30341",
    "sg:province":"GA",
    "sg:tags":[
        "register",
        "cash",
        "supply"
    ],
    "wof:name":"Commercial Electronics Svc Ctr",
    "wof:placetype":"venue"
},
  "geometry": {"coordinates":[-84.31336,33.888386],"type":"Point"}
}