{
  "type": "Feature",
  "properties": {
    "addr:full":"335 Gees Mill Business Pkwy NE Conyers GA 30013",
    "addr:housenumber":"335",
    "addr:postcode":"30013",
    "addr:street":"Gees Mill Business Pkwy Ne",
    "iso:country":"US",
    "sg:address":"335 Gees Mill Business Pkwy NE",
    "sg:city":"Conyers",
    "sg:classifiers":[
        {
            "category":"Wholesale",
            "subcategory":"Hardware",
            "type":"Manufacturing & Wholesale Goods"
        },
        {
            "category":"Retail",
            "subcategory":"Repair Shop",
            "type":"Services"
        }
    ],
    "sg:phone":"+1 770 918 9132",
    "sg:postcode":"30013",
    "sg:province":"GA",
    "sg:tags":[
        "heater",
        "make",
        "refrigeration",
        "air"
    ],
    "wof:name":"Mingledorff's Inc",
    "wof:placetype":"venue"
},
  "geometry": {"coordinates":[-83.974357,33.64856],"type":"Point"}
}