{
  "type": "Feature",
  "properties": {
    "iso:country":"US",
    "sg:address":"70 Andover Dr",
    "sg:city":"Jonesboro",
    "sg:classifiers":[
        {
            "category":"Professional",
            "subcategory":"Detective & Security Services",
            "type":"Services"
        }
    ],
    "sg:phone":"+1 770 914 5888",
    "sg:postcode":"30238",
    "sg:province":"GA",
    "sg:tags":[
        "information",
        "bureau"
    ],
    "wof:name":"Browns Inventory Services Inc",
    "wof:placetype":"venue"
},
  "geometry": {"coordinates":[-84.388672,33.513664],"type":"Point"}
}