{
  "type": "Feature",
  "properties": {
    "iso:country":"US",
    "sg:address":"275 Dearing St",
    "sg:city":"Athens",
    "sg:classifiers":[
        {
            "category":"Organizations",
            "subcategory":"Membership Organization",
            "type":"Services"
        }
    ],
    "sg:phone":"+1 706 613 1714",
    "sg:postcode":"30605",
    "sg:province":"GA",
    "wof:name":"Dearing Condominium Assn",
    "wof:placetype":"venue"
},
  "geometry": {"coordinates":[-83.38435200000001,33.954626],"type":"Point"}
}