{
  "type": "Feature",
  "properties": {
    "addr:full":"1204 W 3rd Ave Albany GA 31707",
    "addr:housenumber":"1204",
    "addr:postcode":"31707",
    "addr:street":"W 3Rd Ave",
    "iso:country":"US",
    "sg:address":"1204 W 3rd Ave",
    "sg:city":"Albany",
    "sg:classifiers":[
        {
            "category":"Professional",
            "subcategory":"Lawyer & Legal Services",
            "type":"Services"
        }
    ],
    "sg:phone":"+1 229 432 0961",
    "sg:postcode":"31707",
    "sg:province":"GA",
    "wof:name":"Frazer Betty S Attorney At Law",
    "wof:placetype":"venue"
},
  "geometry": {"coordinates":[-84.17771,31.590139],"type":"Point"}
}