{
  "type": "Feature",
  "properties": {
    "iso:country":"US",
    "sg:address":"8337 Tara Blvd",
    "sg:city":"Jonesboro",
    "sg:classifiers":[
        {
            "category":"Retail",
            "subcategory":"Storage",
            "type":"Services"
        }
    ],
    "sg:phone":"+1 770 477 9400",
    "sg:postcode":"30236",
    "sg:province":"GA",
    "sg:tags":[
        "self"
    ],
    "sg:website":"www.extraspace.com",
    "wof:name":"Extra Space Storage",
    "wof:placetype":"venue"
},
  "geometry": {"coordinates":[-84.364991,33.526879],"type":"Point"}
}