{
  "type": "Feature",
  "properties": {
    "iso:country":"US",
    "sg:address":"117 5th Street, NE",
    "sg:city":"Atlanta",
    "sg:classifiers":[
        {
            "category":"Personal",
            "subcategory":"Massage",
            "type":"Services"
        },
        {
            "category":"Health Services",
            "subcategory":"Nursing And Care Facility",
            "type":"Services"
        },
        {
            "category":"Health Services",
            "subcategory":"Health Practitioner",
            "type":"Services"
        }
    ],
    "sg:phone":"+1 404 384 3901",
    "sg:postcode":"30308",
    "sg:province":"GA",
    "sg:tags":[
        "therapist",
        "aromatherapy",
        "management",
        "pain",
        "home"
    ],
    "sg:website":"http://www.rhythmstouch.com",
    "wof:name":"Rhythm's Touch Massage Therapy",
    "wof:placetype":"venue"
},
  "geometry": {"coordinates":[-84.383499,33.776074],"type":"Point"}
}