{
  "type": "Feature",
  "properties": {
    "iso:country":"US",
    "sg:address":"1001 Greensboro Rd",
    "sg:city":"Eatonton",
    "sg:classifiers":[
        {
            "category":"Restaurant",
            "type":"Food & Drink"
        }
    ],
    "sg:menulink":"http://www.allmenus.com/ga/phoenix/203280-mcdonalds/menu/",
    "sg:postcode":"31024",
    "sg:province":"GA",
    "sg:tags":[
        "burger",
        "american"
    ],
    "wof:name":"McDonald's",
    "wof:placetype":"venue"
},
  "geometry": {"coordinates":[-83.273166,33.41767],"type":"Point"}
}