{
  "type": "Feature",
  "properties": {
    "iso:country":"US",
    "sg:address":"74 Hiram Acworth Hwy",
    "sg:city":"Hiram",
    "sg:classifiers":[
        {
            "category":"Restaurant",
            "type":"Food & Drink"
        }
    ],
    "sg:menulink":"http://www.allmenus.com/ga/dallas/140697-waffle-house/menu/",
    "sg:phone":"+1 770 469 8596",
    "sg:postcode":"30141",
    "sg:province":"GA",
    "sg:tags":[
        "american"
    ],
    "wof:name":"Waffle House",
    "wof:placetype":"venue"
},
  "geometry": {"coordinates":[-84.74837100000001,33.908097],"type":"Point"}
}