{
  "type": "Feature",
  "properties": {
    "iso:country":"US",
    "sg:address":"4204 Mundy Mill Rd",
    "sg:city":"Oakwood",
    "sg:classifiers":[
        {
            "category":"Health Services",
            "subcategory":"Doctor",
            "type":"Services"
        }
    ],
    "sg:phone":"+1 770 503 0404",
    "sg:postcode":"30566",
    "sg:province":"GA",
    "sg:tags":[
        "dentist"
    ],
    "wof:name":"Lanier Orthodontics",
    "wof:placetype":"venue"
},
  "geometry": {"coordinates":[-83.884722,34.246438],"type":"Point"}
}