{
  "type": "Feature",
  "properties": {
    "iso:country":"US",
    "sg:address":"1812 Mills B Lane Blvd",
    "sg:city":"Savannah",
    "sg:classifiers":[
        {
            "category":"Home & Garden",
            "subcategory":"Household Appliances",
            "type":"Retail Goods"
        },
        {
            "category":"Retail",
            "subcategory":"Repair Shop",
            "type":"Services"
        }
    ],
    "sg:phone":"+1 912 234 2588",
    "sg:postcode":"31405",
    "sg:province":"GA",
    "sg:tags":[
        "cleaners",
        "parts",
        "electrical",
        "vacuum"
    ],
    "wof:name":"W D Horne W D Inc",
    "wof:placetype":"venue"
},
  "geometry": {"coordinates":[-81.131047,32.051656],"type":"Point"}
}