{
  "type": "Feature",
  "properties": {
    "iso:country":"US",
    "sg:address":"4895 Cascade Hills Cir SW",
    "sg:city":"Atlanta",
    "sg:classifiers":[
        {
            "category":"Health Services",
            "subcategory":"Clinic",
            "type":"Services"
        }
    ],
    "sg:phone":"+1 404 472 0943",
    "sg:postcode":"30331",
    "sg:province":"GA",
    "sg:tags":[
        "physicist"
    ],
    "wof:name":"Willie Rockward",
    "wof:placetype":"venue"
},
  "geometry": {"coordinates":[-84.56305,33.723016],"type":"Point"}
}