{
  "type": "Feature",
  "properties": {
    "addr:full":"3990 Bankhead Hwy Douglasville GA 30134",
    "addr:housenumber":"3990",
    "addr:postcode":"30134",
    "addr:street":"Bankhead Hwy",
    "iso:country":"US",
    "sg:address":"3990 Bankhead Hwy",
    "sg:city":"Douglasville",
    "sg:classifiers":[
        {
            "category":"Professional",
            "subcategory":"Management & Consulting",
            "type":"Services"
        }
    ],
    "sg:phone":"+1 770 949 6943",
    "sg:postcode":"30134",
    "sg:province":"GA",
    "sg:tags":[
        "consultant"
    ],
    "wof:name":"Landmark Consultants",
    "wof:placetype":"venue"
},
  "geometry": {"coordinates":[-84.702702,33.782513],"type":"Point"}
}