{
  "type": "Feature",
  "properties": {
    "iso:country":"US",
    "sg:address":"3645 Grovemont Cove",
    "sg:city":"Cumming",
    "sg:classifiers":[
        {
            "category":"Insurance",
            "subcategory":"Insurance Agent",
            "type":"Services"
        }
    ],
    "sg:phone":"+1 678 867 0717",
    "sg:postcode":"30041",
    "sg:province":"GA",
    "wof:name":"Lafave Insurance Group",
    "wof:placetype":"venue"
},
  "geometry": {"coordinates":[-84.18651,34.087602],"type":"Point"}
}