{
  "type": "Feature",
  "properties": {
    "iso:country":"US",
    "sg:address":"4700 Baker Grove Rd",
    "sg:city":"Acworth",
    "sg:classifiers":[
        {
            "category":"Health Services",
            "subcategory":"Nursing And Care Facility",
            "type":"Services"
        }
    ],
    "sg:phone":"+1 770 966 8536",
    "sg:postcode":"30101",
    "sg:province":"GA",
    "sg:tags":[
        "home",
        "retirement",
        "community"
    ],
    "wof:name":"Barrington Square/United Chr",
    "wof:placetype":"venue"
},
  "geometry": {"coordinates":[-84.649344,34.069171],"type":"Point"}
}