{
  "type": "Feature",
  "properties": {
    "addr:full":"301 Plantation Chase St Simons Island GA 31522",
    "addr:housenumber":"301",
    "addr:postcode":"31522",
    "addr:street":"Plantation Chase St Simons Island",
    "iso:country":"US",
    "sg:address":"301 Plantation Chase",
    "sg:city":"St Simons Island",
    "sg:classifiers":[
        {
            "category":"Real Estate",
            "subcategory":"Real Estate Agent",
            "type":"Services"
        }
    ],
    "sg:phone":"+1 912 634 2289",
    "sg:postcode":"31522",
    "sg:province":"GA",
    "wof:name":"Plantation Creek Realty",
    "wof:placetype":"venue"
},
  "geometry": {"coordinates":[-81.398979,31.166594],"type":"Point"}
}