{
  "type": "Feature",
  "properties": {
    "iso:country":"US",
    "sg:address":"2458 US Hwy 41",
    "sg:city":"Perry",
    "sg:classifiers":[
        {
            "category":"Manufacturing",
            "subcategory":"Lumber",
            "type":"Manufacturing & Wholesale Goods"
        }
    ],
    "sg:phone":"+1 478 988 9702",
    "sg:postcode":"31069",
    "sg:province":"GA",
    "sg:tags":[
        "forester"
    ],
    "wof:name":"Ga Forestry Cell Site",
    "wof:placetype":"venue"
},
  "geometry": {"coordinates":[-83.788557,32.390088],"type":"Point"}
}