{
  "type": "Feature",
  "properties": {
    "addr:full":"104 Corporate Park E Lagrange GA 30241",
    "addr:housenumber":"104",
    "addr:postcode":"30241",
    "addr:street":"Corporate Park E",
    "iso:country":"US",
    "sg:address":"104 Corporate Park E",
    "sg:city":"Lagrange",
    "sg:classifiers":[
        {
            "category":"Professional",
            "subcategory":"Computer Services",
            "type":"Services"
        }
    ],
    "sg:phone":"+1 706 884 4155",
    "sg:postcode":"30241",
    "sg:province":"GA",
    "sg:tags":[
        "repair"
    ],
    "wof:name":"Professional Technology Sltns",
    "wof:placetype":"venue"
},
  "geometry": {"coordinates":[-84.980864,33.033153],"type":"Point"}
}