{
  "type": "Feature",
  "properties": {
    "iso:country":"US",
    "sg:address":"1685 Hawthorne Ave",
    "sg:city":"Atlanta",
    "sg:classifiers":[
        {
            "category":"Retail",
            "subcategory":"Repair Shop",
            "type":"Services"
        }
    ],
    "sg:phone":"+1 404 209 9281",
    "sg:postcode":"30337",
    "sg:province":"GA",
    "wof:name":"Fix It Repair Services Inc",
    "wof:placetype":"venue"
},
  "geometry": {"coordinates":[-84.44469599999999,33.656955],"type":"Point"}
}