{
  "type": "Feature",
  "properties": {
    "addr:full":"1580 Watercove Ln Lawrenceville GA 30043",
    "addr:housenumber":"1580",
    "addr:postcode":"30043",
    "addr:street":"Watercove Ln",
    "iso:country":"US",
    "sg:address":"1580 Watercove Ln",
    "sg:city":"Lawrenceville",
    "sg:classifiers":[
        {
            "category":"Building & Trades",
            "subcategory":"Cleaning & Sanitation",
            "type":"Services"
        }
    ],
    "sg:phone":"+1 770 822 6354",
    "sg:postcode":"30043",
    "sg:province":"GA",
    "sg:tags":[
        "butler",
        "maid"
    ],
    "wof:name":"Busy Bees Cleaning Svc",
    "wof:placetype":"venue"
},
  "geometry": {"coordinates":[-84.038723,33.983057],"type":"Point"}
}