{
  "type": "Feature",
  "properties": {
    "addr:full":"615 Hembree Pkwy Roswell GA 30076",
    "addr:housenumber":"615",
    "addr:postcode":"30076",
    "addr:street":"Hembree Pkwy",
    "iso:country":"US",
    "sg:address":"615 Hembree Pkwy",
    "sg:city":"Roswell",
    "sg:classifiers":[
        {
            "category":"Home & Garden",
            "subcategory":"Furniture",
            "type":"Retail Goods"
        }
    ],
    "sg:phone":"+1 770 569 9960",
    "sg:postcode":"30076",
    "sg:province":"GA",
    "sg:tags":[
        "cabinet"
    ],
    "wof:name":"Cabinet Man",
    "wof:placetype":"venue"
},
  "geometry": {"coordinates":[-84.319078,34.060097],"type":"Point"}
}