{
  "type": "Feature",
  "properties": {
    "addr:full":"67 Athens St Jefferson GA 30549",
    "addr:housenumber":"67",
    "addr:postcode":"30549",
    "addr:street":"Athens St",
    "iso:country":"US",
    "sg:address":"67 Athens St",
    "sg:city":"Jefferson",
    "sg:classifiers":[
        {
            "category":"Government",
            "subcategory":"Office",
            "type":"Public Place"
        }
    ],
    "sg:phone":"+1 706 367 6314",
    "sg:postcode":"30549",
    "sg:province":"GA",
    "wof:name":"Jackson County Manager's Ofc",
    "wof:placetype":"venue"
},
  "geometry": {"coordinates":[-83.574445,34.116316],"type":"Point"}
}