{
  "type": "Feature",
  "properties": {
    "addr:full":"110 Wedgewood Walk Griffin GA 30223",
    "addr:housenumber":"110",
    "addr:postcode":"30223",
    "addr:street":"Wedgewood Walk",
    "iso:country":"US",
    "sg:address":"110 Wedgewood Walk",
    "sg:city":"Griffin",
    "sg:classifiers":[
        {
            "category":"Professional",
            "type":"Services"
        }
    ],
    "sg:phone":"+1 770 233 4868",
    "sg:postcode":"30223",
    "sg:province":"GA",
    "sg:tags":[
        "establishment"
    ],
    "wof:name":"Renae",
    "wof:placetype":"venue"
},
  "geometry": {"coordinates":[-84.29432799999999,33.26414],"type":"Point"}
}