{
  "type": "Feature",
  "properties": {
    "iso:country":"US",
    "sg:address":"27 Township Dr",
    "sg:city":"Hiram",
    "sg:classifiers":[
        {
            "category":"Professional",
            "subcategory":"Business Services",
            "type":"Services"
        }
    ],
    "sg:phone":"+1 770 943 0715",
    "sg:postcode":"30141",
    "sg:province":"GA",
    "wof:name":"Designs In Creative Stone",
    "wof:placetype":"venue"
},
  "geometry": {"coordinates":[-84.77584400000001,33.862231],"type":"Point"}
}