{
  "type": "Feature",
  "properties": {
    "addr:full":"1723 Viceroy Way Riverdale GA 30296",
    "addr:housenumber":"1723",
    "addr:postcode":"30296",
    "addr:street":"Viceroy Way",
    "iso:country":"US",
    "sg:address":"1723 Viceroy Way",
    "sg:city":"Riverdale",
    "sg:classifiers":[
        {
            "category":"Building & Trades",
            "subcategory":"Electrical",
            "type":"Services"
        }
    ],
    "sg:phone":"+1 770 907 6645",
    "sg:postcode":"30296",
    "sg:province":"GA",
    "sg:tags":[
        "electrical",
        "contractor"
    ],
    "wof:name":"Power Solutions Inc",
    "wof:placetype":"venue"
},
  "geometry": {"coordinates":[-84.44640099999999,33.554974],"type":"Point"}
}