{
  "type": "Feature",
  "properties": {
    "addr:full":"3665 Salem Rd Covington GA 30016",
    "addr:housenumber":"3665",
    "addr:postcode":"30016",
    "addr:street":"Salem Rd",
    "iso:country":"US",
    "sg:address":"3665 Salem Rd",
    "sg:city":"Covington",
    "sg:classifiers":[
        {
            "category":"Retail",
            "subcategory":"Car Wash",
            "type":"Services"
        }
    ],
    "sg:phone":"+1 770 385 1800",
    "sg:postcode":"30016",
    "sg:province":"GA",
    "sg:tags":[
        "carwash"
    ],
    "wof:name":"Precise Auto Detail",
    "wof:placetype":"venue"
},
  "geometry": {"coordinates":[-83.96968699999999,33.592251],"type":"Point"}
}