{
  "type": "Feature",
  "properties": {
    "iso:country":"US",
    "sg:address":"360 Dashing Wave Ln",
    "sg:city":"Alpharetta",
    "sg:classifiers":[
        {
            "category":"Shopping",
            "subcategory":"Computers & Home Electronics",
            "type":"Retail Goods"
        }
    ],
    "sg:phone":"+1 770 475 1301",
    "sg:postcode":"30005",
    "sg:province":"GA",
    "sg:tags":[
        "software"
    ],
    "wof:name":"Metanology Corp",
    "wof:placetype":"venue"
},
  "geometry": {"coordinates":[-84.23342,34.077624],"type":"Point"}
}