{
  "type": "Feature",
  "properties": {
    "iso:country":"US",
    "sg:address":"140 Deloach Ln",
    "sg:city":"Glennville",
    "sg:classifiers":[
        {
            "category":"Professional",
            "subcategory":"Accounting & Tax Preparation",
            "type":"Services"
        }
    ],
    "sg:phone":"+1 912 654 2130",
    "sg:postcode":"30427",
    "sg:province":"GA",
    "wof:name":"Tammy D Waters CPA",
    "wof:placetype":"venue"
},
  "geometry": {"coordinates":[-81.93577500000001,31.926472],"type":"Point"}
}