{
  "type": "Feature",
  "properties": {
    "addr:full":"110 E Church St Americus GA 31709",
    "addr:housenumber":"110",
    "addr:postcode":"31709",
    "addr:street":"E Church St",
    "iso:country":"US",
    "sg:address":"110 E Church St",
    "sg:city":"Americus",
    "sg:classifiers":[
        {
            "category":"Personal",
            "subcategory":"Beauty Salon",
            "type":"Services"
        }
    ],
    "sg:phone":"+1 229 924 1311",
    "sg:postcode":"31709",
    "sg:province":"GA",
    "sg:tags":[
        "shop"
    ],
    "wof:name":"New Beginning Hair Designs",
    "wof:placetype":"venue"
},
  "geometry": {"coordinates":[-84.230754,32.07048],"type":"Point"}
}