{
  "type": "Feature",
  "properties": {
    "addr:full":"5 Lagrange St Newnan GA 30263",
    "addr:housenumber":"5",
    "addr:postcode":"30263",
    "addr:street":"Lagrange St",
    "iso:country":"US",
    "sg:address":"5 Lagrange St",
    "sg:city":"Newnan",
    "sg:classifiers":[
        {
            "category":"Shopping",
            "subcategory":"Clothing, Apparel, & Fashions",
            "type":"Retail Goods"
        }
    ],
    "sg:phone":"+1 770 304 0024",
    "sg:postcode":"30263",
    "sg:province":"GA",
    "sg:tags":[
        "tailor",
        "alterations-clothing"
    ],
    "wof:name":"Lucy's Alterations & Custom Design",
    "wof:placetype":"venue"
},
  "geometry": {"coordinates":[-84.80053700000001,33.374063],"type":"Point"}
}