{
  "type": "Feature",
  "properties": {
    "addr:full":"3729 Dumbarton Rd NW Atlanta GA 30327",
    "addr:housenumber":"3729",
    "addr:postcode":"30327",
    "addr:street":"Dumbarton Rd Nw",
    "iso:country":"US",
    "sg:address":"3729 Dumbarton Rd NW",
    "sg:city":"Atlanta",
    "sg:classifiers":[
        {
            "category":"Real Estate",
            "subcategory":"Real Estate Operator",
            "type":"Services"
        }
    ],
    "sg:phone":"+1 404 814 1540",
    "sg:postcode":"30327",
    "sg:province":"GA",
    "sg:tags":[
        "building",
        "nonresidential"
    ],
    "wof:name":"Harvin Properties Inc",
    "wof:placetype":"venue"
},
  "geometry": {"coordinates":[-84.41632,33.857105],"type":"Point"}
}