{
  "type": "Feature",
  "properties": {
    "addr:full":"1200 Ponce De Leon Avenue NE Atlanta GA 30306",
    "addr:housenumber":"1200",
    "addr:postcode":"30306",
    "addr:street":"Ponce De Leon Avenue Ne",
    "iso:country":"US",
    "sg:address":"1200 Ponce De Leon Avenue NE",
    "sg:city":"Atlanta",
    "sg:classifiers":[
        {
            "category":"Organizations",
            "subcategory":"Religious Organization",
            "type":"Services"
        }
    ],
    "sg:phone":"+1 404 377 6481",
    "sg:postcode":"30306",
    "sg:province":"GA",
    "sg:website":"www.umc.org",
    "wof:name":"Druid Hills United Methodist Church",
    "wof:placetype":"venue"
},
  "geometry": {"coordinates":[-84.348302,33.773804],"type":"Point"}
}