{
  "type": "Feature",
  "properties": {
    "iso:country":"US",
    "sg:address":"300 Allatoona Rd",
    "sg:city":"Lawrenceville",
    "sg:classifiers":[
        {
            "category":"Manufacturing",
            "subcategory":"Metals",
            "type":"Manufacturing & Wholesale Goods"
        }
    ],
    "sg:phone":"+1 770 963 9001",
    "sg:postcode":"30043",
    "sg:province":"GA",
    "sg:tags":[
        "steel",
        "erectors"
    ],
    "wof:name":"American Reinforcing Steel Erectors Inc",
    "wof:placetype":"venue"
},
  "geometry": {"coordinates":[-84.033799,34.001876],"type":"Point"}
}