{
  "type": "Feature",
  "properties": {
    "addr:full":"825 Westwood Ave Ashburn GA 31714",
    "addr:housenumber":"825",
    "addr:postcode":"31714",
    "addr:street":"Westwood Ave",
    "iso:country":"US",
    "sg:address":"825 Westwood Ave",
    "sg:city":"Ashburn",
    "sg:classifiers":[
        {
            "category":"Professional",
            "type":"Services"
        }
    ],
    "sg:phone":"+1 229 567 0381",
    "sg:postcode":"31714",
    "sg:province":"GA",
    "wof:name":"Carl Fortson",
    "wof:placetype":"venue"
},
  "geometry": {"coordinates":[-83.63696400000001,31.699016],"type":"Point"}
}