{
  "type": "Feature",
  "properties": {
    "addr:full":"624 Stevens Creek Rd Augusta GA 30907",
    "addr:housenumber":"624",
    "addr:postcode":"30907",
    "addr:street":"Stevens Creek Rd",
    "iso:country":"US",
    "sg:address":"624 Stevens Creek Rd",
    "sg:city":"Augusta",
    "sg:classifiers":[
        {
            "category":"Farming",
            "subcategory":"Farm",
            "type":"Manufacturing & Wholesale Goods"
        }
    ],
    "sg:phone":"+1 706 854 1663",
    "sg:postcode":"30907",
    "sg:province":"GA",
    "wof:name":"Rhodes Farms",
    "wof:placetype":"venue"
},
  "geometry": {"coordinates":[-82.053292,33.540541],"type":"Point"}
}