{
  "type": "Feature",
  "properties": {
    "iso:country":"US",
    "sg:address":"428 N Main St",
    "sg:city":"Blakely",
    "sg:classifiers":[
        {
            "category":"Restaurant",
            "type":"Food & Drink"
        }
    ],
    "sg:phone":"+1 229 723 2500",
    "sg:postcode":"31768",
    "sg:province":"GA",
    "sg:tags":[
        "eating"
    ],
    "wof:name":"Magnolias On Main",
    "wof:placetype":"venue"
},
  "geometry": {"coordinates":[-83.788759,31.184674],"type":"Point"}
}