{
  "type": "Feature",
  "properties": {
    "iso:country":"US",
    "sg:address":"210 E 4th St",
    "sg:city":"Woodbine",
    "sg:classifiers":[
        {
            "category":"Government",
            "subcategory":"Court House",
            "type":"Public Place"
        },
        {
            "category":"Government",
            "subcategory":"Office",
            "type":"Public Place"
        }
    ],
    "sg:phone":"+1 912 576 5658",
    "sg:postcode":"31569",
    "sg:province":"GA",
    "sg:tags":[
        "justice",
        "parish",
        "government-county"
    ],
    "wof:name":"Camden County Magistrate Court",
    "wof:placetype":"venue"
},
  "geometry": {"coordinates":[-81.725255,30.967495],"type":"Point"}
}