{
  "type": "Feature",
  "properties": {
    "addr:full":"1753 Lenox Rd NE Atlanta GA 30306",
    "addr:housenumber":"1753",
    "addr:postcode":"30306",
    "addr:street":"Lenox Rd Ne",
    "iso:country":"US",
    "sg:address":"1753 Lenox Rd NE",
    "sg:city":"Atlanta",
    "sg:classifiers":[
        {
            "category":"Professional",
            "subcategory":"Lawyer & Legal Services",
            "type":"Services"
        }
    ],
    "sg:phone":"+1 404 872 7938",
    "sg:postcode":"30306",
    "sg:province":"GA",
    "wof:name":"Georgeson Stephen Law Offices",
    "wof:placetype":"venue"
},
  "geometry": {"coordinates":[-84.35083400000001,33.802483],"type":"Point"}
}