{
  "type": "Feature",
  "properties": {
    "addr:full":"5940 Masters Club Dr Suwanee GA 30024",
    "addr:housenumber":"5940",
    "addr:postcode":"30024",
    "addr:street":"Masters Club Dr",
    "iso:country":"US",
    "sg:address":"5940 Masters Club Dr",
    "sg:city":"Suwanee",
    "sg:classifiers":[
        {
            "category":"Professional",
            "subcategory":"Management & Consulting",
            "type":"Services"
        }
    ],
    "sg:phone":"+1 770 623 4663",
    "sg:postcode":"30024",
    "sg:province":"GA",
    "sg:tags":[
        "consultant"
    ],
    "wof:name":"Consulting Solutions",
    "wof:placetype":"venue"
},
  "geometry": {"coordinates":[-84.119028,34.082664],"type":"Point"}
}