{
  "type": "Feature",
  "properties": {
    "addr:full":"3575 Koger Blvd Duluth GA 30096",
    "addr:housenumber":"3575",
    "addr:postcode":"30096",
    "addr:street":"Koger Blvd",
    "iso:country":"US",
    "sg:address":"3575 Koger Blvd",
    "sg:city":"Duluth",
    "sg:classifiers":[
        {
            "category":"Professional",
            "subcategory":"Credit Reporting & Collection",
            "type":"Services"
        }
    ],
    "sg:phone":"+1 770 638 0116",
    "sg:postcode":"30096",
    "sg:province":"GA",
    "wof:name":"Central Credit Services Inc",
    "wof:placetype":"venue"
},
  "geometry": {"coordinates":[-84.123504,33.948719],"type":"Point"}
}