{
  "type": "Feature",
  "properties": {
    "iso:country":"US",
    "sg:address":"36 2nd St",
    "sg:city":"Jackson",
    "sg:classifiers":[
        {
            "category":"Shopping",
            "subcategory":"Department Store",
            "type":"Retail Goods"
        }
    ],
    "sg:phone":"+1 770 775 2518",
    "sg:postcode":"30233",
    "sg:province":"GA",
    "wof:name":"Deraney's Department Store",
    "wof:placetype":"venue"
},
  "geometry": {"coordinates":[-83.967035,33.295146],"type":"Point"}
}