{
  "type": "Feature",
  "properties": {
    "iso:country":"US",
    "sg:address":"211 Cemetery St",
    "sg:city":"Norcross",
    "sg:classifiers":[
        {
            "category":"Park",
            "type":"Public Place"
        }
    ],
    "sg:phone":"+1 770 822 5142",
    "sg:postcode":"30071",
    "sg:province":"GA",
    "sg:website":"www.gwinnettcounty.com",
    "wof:name":"Cemetery Field",
    "wof:placetype":"venue"
},
  "geometry": {"coordinates":[-84.20895,33.93728],"type":"Point"}
}