{
  "type": "Feature",
  "properties": {
    "addr:full":"325 N Cobb St Milledgeville GA 31061",
    "addr:housenumber":"325",
    "addr:postcode":"31061",
    "addr:street":"N Cobb St",
    "iso:country":"US",
    "sg:address":"325 N Cobb St",
    "sg:city":"Milledgeville",
    "sg:classifiers":[
        {
            "category":"Health Services",
            "subcategory":"Doctor",
            "type":"Services"
        }
    ],
    "sg:phone":"+1 478 453 1085",
    "sg:postcode":"31061",
    "sg:province":"GA",
    "sg:tags":[
        "medical"
    ],
    "wof:name":"Omitowo Akin MD",
    "wof:placetype":"venue"
},
  "geometry": {"coordinates":[-83.241563,33.082468],"type":"Point"}
}