{
  "type": "Feature",
  "properties": {
    "iso:country":"US",
    "sg:address":"530 Lake Center Pkwy",
    "sg:city":"Cumming",
    "sg:classifiers":[
        {
            "category":"Restaurant",
            "type":"Food & Drink"
        }
    ],
    "sg:phone":"+1 770 888 7222",
    "sg:postcode":"30040",
    "sg:province":"GA",
    "wof:name":"Jersey Mike's Submarines",
    "wof:placetype":"venue"
},
  "geometry": {"coordinates":[-84.133728,34.196373],"type":"Point"}
}