{
  "type": "Feature",
  "properties": {
    "addr:full":"311 4th Ave SE Moultrie GA 31768",
    "addr:housenumber":"311",
    "addr:postcode":"31768",
    "addr:street":"4Th Ave Se",
    "iso:country":"US",
    "sg:address":"311 4th Ave SE",
    "sg:city":"Moultrie",
    "sg:classifiers":[
        {
            "category":"Building & Trades",
            "subcategory":"Plumbing",
            "type":"Services"
        }
    ],
    "sg:phone":"+1 229 985 8234",
    "sg:postcode":"31768",
    "sg:province":"GA",
    "sg:tags":[
        "conditioning",
        "air",
        "system",
        "contractor"
    ],
    "wof:name":"Kenwood Refrigeration Elec Htg",
    "wof:placetype":"venue"
},
  "geometry": {"coordinates":[-83.78509099999999,31.175828],"type":"Point"}
}