{
  "type": "Feature",
  "properties": {
    "iso:country":"US",
    "sg:address":"311 N Dawson St",
    "sg:city":"Thomasville",
    "sg:classifiers":[
        {
            "category":"Government",
            "subcategory":"Office",
            "type":"Public Place"
        }
    ],
    "sg:phone":"+1 229 226 3616",
    "sg:postcode":"31792",
    "sg:province":"GA",
    "sg:tags":[
        "county"
    ],
    "wof:name":"Thomas County Public Defenders",
    "wof:placetype":"venue"
},
  "geometry": {"coordinates":[-83.980321,30.84213],"type":"Point"}
}