{
  "type": "Feature",
  "properties": {
    "addr:full":"24 Indian River Rd SE Lindale GA 30147",
    "addr:housenumber":"24",
    "addr:postcode":"30147",
    "addr:street":"Indian River Rd Se",
    "iso:country":"US",
    "sg:address":"24 Indian River Rd SE",
    "sg:city":"Lindale",
    "sg:classifiers":[
        {
            "category":"Shopping",
            "type":"Retail Goods"
        }
    ],
    "sg:phone":"+1 706 234 1728",
    "sg:postcode":"30147",
    "sg:province":"GA",
    "sg:tags":[
        "merchandise"
    ],
    "wof:name":"Broomes Trophy",
    "wof:placetype":"venue"
},
  "geometry": {"coordinates":[-85.16919300000001,34.160815],"type":"Point"}
}