{
  "type": "Feature",
  "properties": {
    "addr:full":"1249 Jonesboro Rd Mcdonough GA 30253",
    "addr:housenumber":"1249",
    "addr:postcode":"30253",
    "addr:street":"Jonesboro Rd",
    "iso:country":"US",
    "sg:address":"1249 Jonesboro Rd",
    "sg:city":"Mcdonough",
    "sg:classifiers":[
        {
            "category":"Professional",
            "subcategory":"Business Services",
            "type":"Services"
        }
    ],
    "sg:phone":"+1 770 954 3535",
    "sg:postcode":"30253",
    "sg:province":"GA",
    "wof:name":"Carfinders Of South Atlanta",
    "wof:placetype":"venue"
},
  "geometry": {"coordinates":[-84.201365,33.461131],"type":"Point"}
}