{
  "type": "Feature",
  "properties": {
    "iso:country":"US",
    "sg:address":"8302 Office Park Dr",
    "sg:city":"Douglasville",
    "sg:classifiers":[
        {
            "category":"Professional",
            "subcategory":"Lawyer & Legal Services",
            "type":"Services"
        }
    ],
    "sg:phone":"+1 770 577 3020",
    "sg:postcode":"30134",
    "sg:province":"GA",
    "sg:tags":[
        "litigation"
    ],
    "wof:name":"Murphy & Clay Llc",
    "wof:placetype":"venue"
},
  "geometry": {"coordinates":[-84.73670199999999,33.754002],"type":"Point"}
}