{
  "type": "Feature",
  "properties": {
    "addr:full":"445 Hinton Rd Social Circle GA 30025",
    "addr:housenumber":"445",
    "addr:postcode":"30025",
    "addr:street":"Hinton Rd;Circle",
    "iso:country":"US",
    "sg:address":"445 Hinton Rd",
    "sg:city":"Social Circle",
    "sg:classifiers":[
        {
            "category":"Building & Trades",
            "subcategory":"Construction",
            "type":"Services"
        }
    ],
    "sg:phone":"+1 770 787 0735",
    "sg:postcode":"30025",
    "sg:province":"GA",
    "sg:tags":[
        "house"
    ],
    "wof:name":"Lemonds Hipps Construction",
    "wof:placetype":"venue"
},
  "geometry": {"coordinates":[-83.73172700000001,33.597835],"type":"Point"}
}