{
  "type": "Feature",
  "properties": {
    "addr:full":"3607 Old Norcross Rd Duluth GA 30096",
    "addr:housenumber":"3607",
    "addr:postcode":"30096",
    "addr:street":"Old Norcross Rd",
    "iso:country":"US",
    "sg:address":"3607 Old Norcross Rd",
    "sg:city":"Duluth",
    "sg:classifiers":[
        {
            "category":"Social Services",
            "subcategory":"Child Care",
            "type":"Services"
        },
        {
            "category":"Education",
            "subcategory":"Preschool",
            "type":"Public Place"
        }
    ],
    "sg:phone":"+1 770 476 1338",
    "sg:postcode":"30096",
    "sg:province":"GA",
    "sg:tags":[
        "kindergarten",
        "nursery",
        "day"
    ],
    "sg:website":"http://www.lapetite.com",
    "wof:name":"La Petite Academy",
    "wof:placetype":"venue"
},
  "geometry": {"coordinates":[-84.13750400000001,33.965194],"type":"Point"}
}