{
  "type": "Feature",
  "properties": {
    "addr:full":"5014 Sussex Dr Evans GA 30809",
    "addr:housenumber":"5014",
    "addr:postcode":"30809",
    "addr:street":"Sussex Dr",
    "iso:country":"US",
    "sg:address":"5014 Sussex Dr",
    "sg:city":"Evans",
    "sg:classifiers":[
        {
            "category":"Professional",
            "subcategory":"Advertising",
            "type":"Services"
        }
    ],
    "sg:phone":"+1 706 627 6351",
    "sg:postcode":"30809",
    "sg:province":"GA",
    "sg:tags":[
        "distribution"
    ],
    "wof:name":"Specialty Brokers Of Augusta",
    "wof:placetype":"venue"
},
  "geometry": {"coordinates":[-82.14908,33.59063],"type":"Point"}
}