{
  "type": "Feature",
  "properties": {
    "addr:full":"1637 Preserve Park Dr Loganville GA 30052",
    "addr:housenumber":"1637",
    "addr:postcode":"30052",
    "addr:street":"Preserve Park Dr",
    "iso:country":"US",
    "sg:address":"1637 Preserve Park Dr",
    "sg:city":"Loganville",
    "sg:classifiers":[
        {
            "category":"Professional",
            "subcategory":"Art Services",
            "type":"Services"
        }
    ],
    "sg:phone":"+1 770 736 5983",
    "sg:postcode":"30052",
    "sg:province":"GA",
    "sg:tags":[
        "graphic",
        "designer"
    ],
    "wof:name":"With Love Creations",
    "wof:placetype":"venue"
},
  "geometry": {"coordinates":[-83.97597500000001,33.836849],"type":"Point"}
}