{
  "type": "Feature",
  "properties": {
    "addr:full":"4600 Cat Creek Rd Valdosta GA 31605",
    "addr:housenumber":"4600",
    "addr:postcode":"31605",
    "addr:street":"Cat Creek Rd",
    "iso:country":"US",
    "sg:address":"4600 Cat Creek Rd",
    "sg:city":"Valdosta",
    "sg:classifiers":[
        {
            "category":"Real Estate",
            "subcategory":"Real Estate Operator",
            "type":"Services"
        }
    ],
    "sg:phone":"+1 229 242 3203",
    "sg:postcode":"31605",
    "sg:province":"GA",
    "sg:tags":[
        "mobile",
        "home",
        "site"
    ],
    "wof:name":"Steedley Mobile Home",
    "wof:placetype":"venue"
},
  "geometry": {"coordinates":[-83.24253299999999,30.965985],"type":"Point"}
}