{
  "type": "Feature",
  "properties": {
    "addr:full":"416 N West St Bainbridge GA 39817",
    "addr:housenumber":"416",
    "addr:postcode":"39817",
    "addr:street":"N West St",
    "iso:country":"US",
    "sg:address":"416 N West St",
    "sg:city":"Bainbridge",
    "sg:classifiers":[
        {
            "category":"Building & Trades",
            "subcategory":"Construction",
            "type":"Services"
        }
    ],
    "sg:phone":"+1 229 246 5564",
    "sg:postcode":"39817",
    "sg:province":"GA",
    "sg:tags":[
        "contractor"
    ],
    "wof:name":"Mc Millan Construction Inc",
    "wof:placetype":"venue"
},
  "geometry": {"coordinates":[-84.57647900000001,30.908408],"type":"Point"}
}