{
  "type": "Feature",
  "properties": {
    "addr:full":"2827 Meredyth Dr Albany GA 31707",
    "addr:housenumber":"2827",
    "addr:postcode":"31707",
    "addr:street":"Meredyth Dr",
    "iso:country":"US",
    "sg:address":"2827 Meredyth Dr",
    "sg:city":"Albany",
    "sg:classifiers":[
        {
            "category":"Retail",
            "subcategory":"Laundry & Dry Cleaning",
            "type":"Services"
        }
    ],
    "sg:phone":"+1 229 883 7097",
    "sg:postcode":"31707",
    "sg:province":"GA",
    "sg:tags":[
        "cleaners"
    ],
    "wof:name":"Northwest Cleaners Inc",
    "wof:placetype":"venue"
},
  "geometry": {"coordinates":[-84.210177,31.609088],"type":"Point"}
}