{
  "type": "Feature",
  "properties": {
    "iso:country":"US",
    "sg:address":"580 Spring Hill Rd",
    "sg:city":"Mauk",
    "sg:classifiers":[
        {
            "category":"Home & Garden",
            "subcategory":"Household Appliances",
            "type":"Retail Goods"
        },
        {
            "category":"Retail",
            "subcategory":"Repair Shop",
            "type":"Services"
        }
    ],
    "sg:phone":"+1 229 649 7301",
    "sg:postcode":"31058",
    "sg:province":"GA",
    "sg:tags":[
        "small",
        "major",
        "refinishing",
        "appliances-small"
    ],
    "wof:name":"Appliance & Air",
    "wof:placetype":"venue"
},
  "geometry": {"coordinates":[-84.50939700000001,32.453335],"type":"Point"}
}