{
  "type": "Feature",
  "properties": {
    "iso:country":"US",
    "sg:address":"3734 Stanford Cir",
    "sg:city":"Decatur",
    "sg:classifiers":[
        {
            "category":"Shopping",
            "type":"Retail Goods"
        }
    ],
    "sg:phone":"+1 770 987 2353",
    "sg:postcode":"30034",
    "sg:province":"GA",
    "sg:tags":[
        "cosmetic",
        "perfume"
    ],
    "wof:name":"Zepp's Cosmetics",
    "wof:placetype":"venue"
},
  "geometry": {"coordinates":[-84.215999,33.674697],"type":"Point"}
}