{
  "type": "Feature",
  "properties": {
    "iso:country":"US",
    "sg:address":"240 Sarah Chapel Rd",
    "sg:city":"Wildwood",
    "sg:classifiers":[
        {
            "category":"Building & Trades",
            "subcategory":"Construction",
            "type":"Services"
        }
    ],
    "sg:phone":"+1 706 657 7212",
    "sg:postcode":"30752",
    "sg:province":"GA",
    "sg:tags":[
        "nonresidential"
    ],
    "wof:name":"Vaughan Construction",
    "wof:placetype":"venue"
},
  "geometry": {"coordinates":[-85.455541,34.926783],"type":"Point"}
}