{
  "type": "Feature",
  "properties": {
    "addr:full":"1837 Bill Murdock Rd Marietta GA 30062",
    "addr:housenumber":"1837",
    "addr:postcode":"30062",
    "addr:street":"Bill Murdock Rd",
    "iso:country":"US",
    "sg:address":"1837 Bill Murdock Rd",
    "sg:city":"Marietta",
    "sg:classifiers":[
        {
            "category":"Organizations",
            "subcategory":"Religious Organization",
            "type":"Services"
        }
    ],
    "sg:phone":"+1 770 977 7487",
    "sg:postcode":"30062",
    "sg:province":"GA",
    "wof:name":"Grace Community Presbyterian",
    "wof:placetype":"venue"
},
  "geometry": {"coordinates":[-84.44348100000001,33.99449],"type":"Point"}
}