{
  "type": "Feature",
  "properties": {
    "addr:full":"238 Bullsboro Dr Newnan GA 30263",
    "addr:housenumber":"238",
    "addr:postcode":"30263",
    "addr:street":"Bullsboro Dr",
    "iso:country":"US",
    "sg:address":"238 Bullsboro Dr",
    "sg:city":"Newnan",
    "sg:classifiers":[
        {
            "category":"Autos & Motor Vehicles",
            "subcategory":"Automobile Sales",
            "type":"Retail Goods"
        }
    ],
    "sg:phone":"+1 770 502 3673",
    "sg:postcode":"30263",
    "sg:province":"GA",
    "sg:tags":[
        "car",
        "dealer"
    ],
    "sg:website":"www.mikefitzpatrick-flm.com",
    "wof:name":"Mike Fitzpatrick Ford Lincoln",
    "wof:placetype":"venue"
},
  "geometry": {"coordinates":[-84.770273,33.391051],"type":"Point"}
}