{
  "type": "Feature",
  "properties": {
    "iso:country":"US",
    "sg:address":"735 W Oglethorpe Hwy",
    "sg:city":"Hinesville",
    "sg:classifiers":[
        {
            "category":"Home & Garden",
            "subcategory":"Building Materials",
            "type":"Retail Goods"
        }
    ],
    "sg:phone":"+1 912 408 1001",
    "sg:postcode":"31313",
    "sg:province":"GA",
    "sg:tags":[
        "improvement"
    ],
    "wof:name":"Lowes",
    "wof:placetype":"venue"
},
  "geometry": {"coordinates":[-81.59975,31.821835],"type":"Point"}
}