{
  "type": "Feature",
  "properties": {
    "addr:full":"114 Ocilla Hwy Fitzgerald GA 31750",
    "addr:housenumber":"114",
    "addr:postcode":"31750",
    "addr:street":"Ocilla Hwy Fitzgerald",
    "iso:country":"US",
    "sg:address":"114 Ocilla Hwy",
    "sg:city":"Fitzgerald",
    "sg:classifiers":[
        {
            "category":"Shopping",
            "subcategory":"Mobile Phones",
            "type":"Retail Goods"
        },
        {
            "category":"Autos & Motor Vehicles",
            "subcategory":"Recreational Vehicle Sales",
            "type":"Retail Goods"
        }
    ],
    "sg:phone":"+1 229 426 7625",
    "sg:postcode":"31750",
    "sg:province":"GA",
    "sg:tags":[
        "home",
        "camper"
    ],
    "wof:name":"Affordable Homes Campers",
    "wof:placetype":"venue"
},
  "geometry": {"coordinates":[-83.252033,31.701978],"type":"Point"}
}