{
  "type": "Feature",
  "properties": {
    "iso:country":"US",
    "sg:address":"2500 Wildflower Ct NW",
    "sg:city":"Acworth",
    "sg:classifiers":[
        {
            "category":"Professional",
            "subcategory":"Management & Consulting",
            "type":"Services"
        }
    ],
    "sg:phone":"+1 678 574 9682",
    "sg:postcode":"30101",
    "sg:province":"GA",
    "wof:name":"Hatch Marketing & Design",
    "wof:placetype":"venue"
},
  "geometry": {"coordinates":[-84.621466,34.059571],"type":"Point"}
}