{
  "type": "Feature",
  "properties": {
    "addr:full":"3340 Peachtree Road, NE   Suite 570 Atlanta GA 30326",
    "addr:housenumber":"3340",
    "addr:postcode":"30326",
    "addr:street":"Peachtree Road Ne Suite 570",
    "iso:country":"US",
    "sg:address":"3340 Peachtree Road, NE   Suite 570",
    "sg:city":"Atlanta",
    "sg:classifiers":[
        {
            "category":"Professional",
            "subcategory":"Computer Services",
            "type":"Services"
        }
    ],
    "sg:phone":"+1 212 220 3000",
    "sg:postcode":"30326",
    "sg:province":"GA",
    "sg:tags":[
        "bmi",
        "pro",
        "performing-right-organization",
        "copyright",
        "songwriter",
        "publisher",
        "royalties",
        "royalty",
        "licensing",
        "music",
        "songwriting"
    ],
    "sg:website":"http://bmi.com",
    "wof:name":"Broadcast Music, Inc (BMI)",
    "wof:placetype":"venue"
},
  "geometry": {"coordinates":[-84.367406,33.847858],"type":"Point"}
}