{
  "type": "Feature",
  "properties": {
    "addr:full":"447 Cooper Lake Rd SE Mableton GA 30126",
    "addr:housenumber":"447",
    "addr:postcode":"30126",
    "addr:street":"Cooper Lake Rd Se",
    "iso:country":"US",
    "sg:address":"447 Cooper Lake Rd SE",
    "sg:city":"Mableton",
    "sg:classifiers":[
        {
            "category":"Retail",
            "subcategory":"Auto Rental",
            "type":"Services"
        }
    ],
    "sg:phone":"+1 770 948 3179",
    "sg:postcode":"30126",
    "sg:province":"GA",
    "sg:tags":[
        "passenger",
        "car"
    ],
    "wof:name":"All Aboard Van Rental",
    "wof:placetype":"venue"
},
  "geometry": {"coordinates":[-84.538155,33.832839],"type":"Point"}
}