{
  "type": "Feature",
  "properties": {
    "addr:full":"12166 State Rte 136 Rising Fawn GA 30738",
    "addr:housenumber":"12166",
    "addr:postcode":"30738",
    "addr:street":"State Rte 136",
    "iso:country":"US",
    "sg:address":"12166 State Rte 136",
    "sg:city":"Rising Fawn",
    "sg:classifiers":[
        {
            "category":"Food & Beverages",
            "subcategory":"Groceries & Convenience Stores",
            "type":"Retail Goods"
        }
    ],
    "sg:phone":"+1 706 398 2940",
    "sg:postcode":"30738",
    "sg:province":"GA",
    "wof:name":"Canyon Quick Stop",
    "wof:placetype":"venue"
},
  "geometry": {"coordinates":[-85.425145,34.806853],"type":"Point"}
}