{
  "type": "Feature",
  "properties": {
    "iso:country":"US",
    "sg:address":"225 Carl Vinson Pkwy",
    "sg:city":"Warner Robins",
    "sg:classifiers":[
        {
            "category":"Health Services",
            "subcategory":"Doctor",
            "type":"Services"
        }
    ],
    "sg:phone":"+1 478 923 0232",
    "sg:postcode":"31088",
    "sg:province":"GA",
    "sg:tags":[
        "dentist"
    ],
    "wof:name":"Russell G Eyman Inc",
    "wof:placetype":"venue"
},
  "geometry": {"coordinates":[-83.66512,32.597859],"type":"Point"}
}