{
  "type": "Feature",
  "properties": {
    "iso:country":"US",
    "sg:address":"550 Glass Bridge Rd",
    "sg:city":"Lagrange",
    "sg:classifiers":[
        {
            "category":"Organizations",
            "subcategory":"Religious Organization",
            "type":"Services"
        }
    ],
    "sg:phone":"+1 706 882 5087",
    "sg:postcode":"30240",
    "sg:province":"GA",
    "sg:tags":[
        "church"
    ],
    "wof:name":"Loyd Presbyterian Church Inc",
    "wof:placetype":"venue"
},
  "geometry": {"coordinates":[-85.125029,33.004401],"type":"Point"}
}