{
  "type": "Feature",
  "properties": {
    "iso:country":"US",
    "sg:address":"2738 Harrington Dr",
    "sg:city":"Decatur",
    "sg:classifiers":[
        {
            "category":"Shopping",
            "subcategory":"Gifts & Souvenirs",
            "type":"Retail Goods"
        }
    ],
    "sg:phone":"+1 404 508 3350",
    "sg:postcode":"30033",
    "sg:province":"GA",
    "sg:tags":[
        "basket"
    ],
    "wof:name":"Atlanta Basket Co",
    "wof:placetype":"venue"
},
  "geometry": {"coordinates":[-84.279146,33.803032],"type":"Point"}
}