{
  "type": "Feature",
  "properties": {
    "addr:full":"1790 Benningfield Dr SW Marietta GA 30064",
    "addr:housenumber":"1790",
    "addr:postcode":"30064",
    "addr:street":"Benningfield Dr Sw",
    "iso:country":"US",
    "sg:address":"1790 Benningfield Dr SW",
    "sg:city":"Marietta",
    "sg:classifiers":[
        {
            "category":"Building & Trades",
            "subcategory":"Cleaning & Sanitation",
            "type":"Services"
        }
    ],
    "sg:phone":"+1 770 420 2820",
    "sg:postcode":"30064",
    "sg:province":"GA",
    "sg:tags":[
        "construction",
        "site-clean-up"
    ],
    "wof:name":"Property Prep Associates Inc",
    "wof:placetype":"venue"
},
  "geometry": {"coordinates":[-84.60833,33.909241],"type":"Point"}
}