{
  "type": "Feature",
  "properties": {
    "addr:full":"249 Martin Rd Midway GA 31320",
    "addr:housenumber":"249",
    "addr:postcode":"31320",
    "addr:street":"Martin Rd",
    "iso:country":"US",
    "sg:address":"249 Martin Rd",
    "sg:city":"Midway",
    "sg:classifiers":[
        {
            "category":"Place Of Worship",
            "subcategory":"Church",
            "type":"Public Place"
        },
        {
            "category":"Place Of Worship",
            "type":"Public Place"
        }
    ],
    "sg:phone":"+1 912 884 2329",
    "sg:postcode":"31320",
    "sg:province":"GA",
    "sg:tags":[
        "churches-methodist"
    ],
    "wof:name":"Midway United Methodist Church",
    "wof:placetype":"venue"
},
  "geometry": {"coordinates":[-81.42465799999999,31.805108],"type":"Point"}
}