{
  "type": "Feature",
  "properties": {
    "addr:full":"3192 Howell Mill Rd NW Atlanta GA 30327",
    "addr:housenumber":"3192",
    "addr:postcode":"30327",
    "addr:street":"Howell Mill Rd Nw",
    "iso:country":"US",
    "sg:address":"3192 Howell Mill Rd NW",
    "sg:city":"Atlanta",
    "sg:classifiers":[
        {
            "category":"Health Services",
            "subcategory":"Doctor",
            "type":"Services"
        }
    ],
    "sg:phone":"+1 404 603 9090",
    "sg:postcode":"30327",
    "sg:province":"GA",
    "sg:tags":[
        "physician",
        "management",
        "pain",
        "surgeons"
    ],
    "wof:name":"Atlanta Rheumatology Consultants",
    "wof:placetype":"venue"
},
  "geometry": {"coordinates":[-84.42727499999999,33.840724],"type":"Point"}
}