{
  "type": "Feature",
  "properties": {
    "addr:full":"105 Plantation Dr Macon GA 31210",
    "addr:housenumber":"105",
    "addr:postcode":"31210",
    "addr:street":"Plantation Dr",
    "iso:country":"US",
    "sg:address":"105 Plantation Dr",
    "sg:city":"Macon",
    "sg:classifiers":[
        {
            "category":"Banks & Credit Unions",
            "subcategory":"Financial Services",
            "type":"Services"
        }
    ],
    "sg:phone":"+1 478 405 6194",
    "sg:postcode":"31210",
    "sg:province":"GA",
    "sg:tags":[
        "investor"
    ],
    "wof:name":"East Coast Capital",
    "wof:placetype":"venue"
},
  "geometry": {"coordinates":[-83.741827,32.949007],"type":"Point"}
}