{
  "type": "Feature",
  "properties": {
    "iso:country":"US",
    "sg:address":"1420 Braselton Hwy",
    "sg:city":"Lawrenceville",
    "sg:classifiers":[
        {
            "category":"Retail",
            "subcategory":"Laundry & Dry Cleaning",
            "type":"Services"
        }
    ],
    "sg:phone":"+1 770 277 8778",
    "sg:postcode":"30043",
    "sg:province":"GA",
    "sg:tags":[
        "cleaners",
        "rug",
        "carpet"
    ],
    "wof:name":"Carpet Dry Clean",
    "wof:placetype":"venue"
},
  "geometry": {"coordinates":[-83.965227,34.020502],"type":"Point"}
}