{
  "type": "Feature",
  "properties": {
    "addr:full":"2324 Danielle Ct Marietta GA 30062",
    "addr:housenumber":"2324",
    "addr:postcode":"30062",
    "addr:street":"Danielle Ct",
    "iso:country":"US",
    "sg:address":"2324 Danielle Ct",
    "sg:city":"Marietta",
    "sg:classifiers":[
        {
            "category":"Building & Trades",
            "subcategory":"Construction",
            "type":"Services"
        }
    ],
    "sg:phone":"+1 678 560 2488",
    "sg:postcode":"30062",
    "sg:province":"GA",
    "sg:tags":[
        "contractor"
    ],
    "wof:name":"Lgf General Contracting",
    "wof:placetype":"venue"
},
  "geometry": {"coordinates":[-84.48027500000001,34.022856],"type":"Point"}
}