{
  "type": "Feature",
  "properties": {
    "iso:country":"US",
    "sg:address":"720 Murphy Ave SW",
    "sg:city":"Atlanta",
    "sg:classifiers":[
        {
            "category":"Retail",
            "subcategory":"Repair Shop",
            "type":"Services"
        }
    ],
    "sg:phone":"+1 404 753 0260",
    "sg:postcode":"30310",
    "sg:province":"GA",
    "sg:tags":[
        "repairing",
        "piano",
        "refinishing"
    ],
    "wof:name":"Zume Tuning",
    "wof:placetype":"venue"
},
  "geometry": {"coordinates":[-84.412304,33.737334],"type":"Point"}
}