{
  "type": "Feature",
  "properties": {
    "addr:full":"5298 S Dicks Creek Rd La Fayette GA 30728",
    "addr:housenumber":"5298",
    "addr:postcode":"30728",
    "addr:street":"S Dicks Creek Rd;Fayette",
    "iso:country":"US",
    "sg:address":"5298 S Dicks Creek Rd",
    "sg:city":"La Fayette",
    "sg:classifiers":[
        {
            "category":"Autos & Motor Vehicles",
            "subcategory":"Automobile Sales",
            "type":"Retail Goods"
        }
    ],
    "sg:phone":"+1 706 397 2087",
    "sg:postcode":"30728",
    "sg:province":"GA",
    "sg:tags":[
        "used"
    ],
    "wof:name":"Babb Used Cars Inc",
    "wof:placetype":"venue"
},
  "geometry": {"coordinates":[-85.14065100000001,34.615307],"type":"Point"}
}