{
  "type": "Feature",
  "properties": {
    "iso:country":"US",
    "sg:address":"103 Winchester Dr",
    "sg:city":"Savannah",
    "sg:classifiers":[
        {
            "category":"Banks & Credit Unions",
            "subcategory":"Investment Brokerage",
            "type":"Services"
        }
    ],
    "sg:phone":"+1 912 233 0808",
    "sg:postcode":"31410",
    "sg:province":"GA",
    "sg:tags":[
        "trade",
        "barter",
        "exchange"
    ],
    "wof:name":"Southeast Exchange",
    "wof:placetype":"venue"
},
  "geometry": {"coordinates":[-80.99489699999999,31.997841],"type":"Point"}
}