{
  "type": "Feature",
  "properties": {
    "addr:full":"3242 Auraria Rd Dahlonega GA 30533",
    "addr:housenumber":"3242",
    "addr:postcode":"30533",
    "addr:street":"Auraria Rd",
    "iso:country":"US",
    "sg:address":"3242 Auraria Rd",
    "sg:city":"Dahlonega",
    "sg:classifiers":[
        {
            "category":"Autos & Motor Vehicles",
            "subcategory":"Fuel & Gas Station",
            "type":"Retail Goods"
        }
    ],
    "sg:phone":"+1 706 864 0062",
    "sg:postcode":"30533",
    "sg:province":"GA",
    "sg:tags":[
        "oil"
    ],
    "wof:name":"Ben Higgins Citgo",
    "wof:placetype":"venue"
},
  "geometry": {"coordinates":[-84.020746,34.486627],"type":"Point"}
}