{
  "type": "Feature",
  "properties": {
    "addr:full":"5010 State Rte 138 Union City GA 30291",
    "addr:housenumber":"5010",
    "addr:postcode":"30291",
    "addr:street":"State Rte 138",
    "iso:country":"US",
    "sg:address":"5010 State Rte 138",
    "sg:city":"Union City",
    "sg:classifiers":[
        {
            "category":"Autos & Motor Vehicles",
            "subcategory":"Automobile Sales",
            "type":"Retail Goods"
        }
    ],
    "sg:phone":"+1 770 964 1376",
    "sg:postcode":"30291",
    "sg:province":"GA",
    "sg:tags":[
        "car",
        "dealer"
    ],
    "wof:name":"BMVW Inc",
    "wof:placetype":"venue"
},
  "geometry": {"coordinates":[-84.546347,33.570389],"type":"Point"}
}