{
  "type": "Feature",
  "properties": {
    "iso:country":"US",
    "sg:address":"4026 Winters Chapel Road",
    "sg:city":"Atlanta",
    "sg:classifiers":[
        {
            "category":"Autos & Motor Vehicles",
            "subcategory":"Fuel & Gas Station",
            "type":"Retail Goods"
        }
    ],
    "sg:phone":"+1 770 457 5251",
    "sg:postcode":"30360",
    "sg:province":"GA",
    "wof:name":"Chevron USA",
    "wof:placetype":"venue"
},
  "geometry": {"coordinates":[-84.270006,33.912162],"type":"Point"}
}