{
  "type": "Feature",
  "properties": {
    "addr:full":"2394 Gresham Road SE Atlanta GA 30316",
    "addr:housenumber":"2394",
    "addr:postcode":"30316",
    "addr:street":"Gresham Road Se",
    "iso:country":"US",
    "sg:address":"2394 Gresham Road SE",
    "sg:city":"Atlanta",
    "sg:classifiers":[
        {
            "category":"Place Of Worship",
            "subcategory":"Church",
            "type":"Public Place"
        },
        {
            "category":"Place Of Worship",
            "type":"Public Place"
        },
        {
            "category":"Social Services",
            "subcategory":"Child Care",
            "type":"Services"
        },
        {
            "category":"Organizations",
            "subcategory":"Religious Organization",
            "type":"Services"
        }
    ],
    "sg:phone":"+1 404 243 9288",
    "sg:postcode":"30316",
    "sg:province":"GA",
    "sg:tags":[
        "churches-baptist-general",
        "nursery",
        "day",
        "churches-baptist"
    ],
    "wof:name":"First Baptist Church On Gresham Rd",
    "wof:placetype":"venue"
},
  "geometry": {"coordinates":[-84.310507,33.718415],"type":"Point"}
}