{
  "type": "Feature",
  "properties": {
    "iso:country":"US",
    "sg:address":"191 Peachtree Street NE",
    "sg:city":"Atlanta",
    "sg:classifiers":[
        {
            "category":"Professional",
            "subcategory":"Lawyer & Legal Services",
            "type":"Services"
        }
    ],
    "sg:phone":"+1 404 659 1410",
    "sg:postcode":"30303",
    "sg:province":"GA",
    "sg:tags":[
        "litigation"
    ],
    "wof:name":"Ouzts Brandy F Atty",
    "wof:placetype":"venue"
},
  "geometry": {"coordinates":[-84.387528,33.758976],"type":"Point"}
}