{
  "type": "Feature",
  "properties": {
    "addr:full":"2199 N Decatur Rd Decatur GA 30033",
    "addr:housenumber":"2199",
    "addr:postcode":"30033",
    "addr:street":"N Decatur Rd",
    "iso:country":"US",
    "sg:address":"2199 N Decatur Rd",
    "sg:city":"Decatur",
    "sg:classifiers":[
        {
            "category":"Food & Beverages",
            "subcategory":"Specialty",
            "type":"Retail Goods"
        }
    ],
    "sg:phone":"+1 404 235 7776",
    "sg:postcode":"30033",
    "sg:province":"GA",
    "wof:name":"Body Ecology Diet",
    "wof:placetype":"venue"
},
  "geometry": {"coordinates":[-84.300738,33.79081],"type":"Point"}
}