{
  "type": "Feature",
  "properties": {
    "addr:full":"202 Greenville St La Grange GA 30241",
    "addr:housenumber":"202",
    "addr:postcode":"30241",
    "addr:street":"Greenville St",
    "iso:country":"US",
    "sg:address":"202 Greenville St",
    "sg:city":"La Grange",
    "sg:classifiers":[
        {
            "category":"Retail",
            "subcategory":"Repair Shop",
            "type":"Services"
        }
    ],
    "sg:phone":"+1 706 883 7532",
    "sg:postcode":"30241",
    "sg:province":"GA",
    "wof:name":"Georgia West Locksmith Inc",
    "wof:placetype":"venue"
},
  "geometry": {"coordinates":[-85.02830299999999,33.039504],"type":"Point"}
}