{
  "type": "Feature",
  "properties": {
    "iso:country":"US",
    "sg:address":"4757 State Rte 34",
    "sg:city":"Sharpsburg",
    "sg:classifiers":[
        {
            "category":"Organizations",
            "subcategory":"Religious Organization",
            "type":"Services"
        }
    ],
    "sg:phone":"+1 770 252 3734",
    "sg:postcode":"30277",
    "sg:province":"GA",
    "sg:tags":[
        "church"
    ],
    "sg:website":"www.sharpsburgfirst.com",
    "wof:name":"Sharpsburg Church-The Nazarene",
    "wof:placetype":"venue"
},
  "geometry": {"coordinates":[-84.62717600000001,33.39968],"type":"Point"}
}