{
  "type": "Feature",
  "properties": {
    "addr:full":"2282 Lovvorn Rd Carrollton GA 30117",
    "addr:housenumber":"2282",
    "addr:postcode":"30117",
    "addr:street":"Lovvorn Rd",
    "iso:country":"US",
    "sg:address":"2282 Lovvorn Rd",
    "sg:city":"Carrollton",
    "sg:classifiers":[
        {
            "category":"Professional",
            "type":"Services"
        }
    ],
    "sg:phone":"+1 770 214 1361",
    "sg:postcode":"30117",
    "sg:province":"GA",
    "wof:name":"West GA Wood Recycle Co",
    "wof:placetype":"venue"
},
  "geometry": {"coordinates":[-85.14222599999999,33.584675],"type":"Point"}
}