{
  "type": "Feature",
  "properties": {
    "addr:full":"1498 Jesse Jewell Pkwy SE Gainesville GA 30501",
    "addr:housenumber":"1498",
    "addr:postcode":"30501",
    "addr:street":"Jesse Jewell Pkwy Se;Ga",
    "iso:country":"US",
    "sg:address":"1498 Jesse Jewell Pkwy SE",
    "sg:city":"Gainesville",
    "sg:classifiers":[
        {
            "category":"Health Services",
            "subcategory":"Doctor",
            "type":"Services"
        }
    ],
    "sg:phone":"+1 678 450 4757",
    "sg:postcode":"30501",
    "sg:province":"GA",
    "sg:tags":[
        "gynecology",
        "physician",
        "surgeons",
        "obstetrics"
    ],
    "sg:website":"http://www.lakesideobgyn.net",
    "wof:name":"Lakeside OB GYN",
    "wof:placetype":"venue"
},
  "geometry": {"coordinates":[-83.805908,34.307079],"type":"Point"}
}