{
  "type": "Feature",
  "properties": {
    "addr:full":"4470 Bishop Lake Rd Marietta GA 30062",
    "addr:housenumber":"4470",
    "addr:postcode":"30062",
    "addr:street":"Bishop Lake Rd",
    "iso:country":"US",
    "sg:address":"4470 Bishop Lake Rd",
    "sg:city":"Marietta",
    "sg:classifiers":[
        {
            "category":"Professional",
            "subcategory":"Business Services",
            "type":"Services"
        }
    ],
    "sg:phone":"+1 770 973 5631",
    "sg:postcode":"30062",
    "sg:province":"GA",
    "sg:tags":[
        "interior",
        "consultant",
        "design",
        "decorator"
    ],
    "wof:name":"Dimensions In Design",
    "wof:placetype":"venue"
},
  "geometry": {"coordinates":[-84.41797699999999,34.001555],"type":"Point"}
}