{
  "type": "Feature",
  "properties": {
    "iso:country":"US",
    "sg:address":"918 Dailey Mill Rd",
    "sg:city":"McDonough",
    "sg:classifiers":[
        {
            "category":"Personal",
            "type":"Services"
        }
    ],
    "sg:phone":"+1 770 898 5760",
    "sg:postcode":"30253",
    "sg:province":"GA",
    "sg:tags":[
        "party",
        "planning",
        "event"
    ],
    "wof:name":"Flip Flop Inflatables",
    "wof:placetype":"venue"
},
  "geometry": {"coordinates":[-84.185518,33.478924],"type":"Point"}
}