{
  "type": "Feature",
  "properties": {
    "addr:full":"599 Carriage Dr NE Atlanta GA 30328",
    "addr:housenumber":"599",
    "addr:postcode":"30328",
    "addr:street":"Carriage Dr Ne",
    "iso:country":"US",
    "sg:address":"599 Carriage Dr NE",
    "sg:city":"Atlanta",
    "sg:classifiers":[
        {
            "category":"Manufacturing",
            "subcategory":"Tools & Machinery",
            "type":"Manufacturing & Wholesale Goods"
        },
        {
            "category":"Manufacturing",
            "subcategory":"Motor Vehicles & Parts",
            "type":"Manufacturing & Wholesale Goods"
        }
    ],
    "sg:phone":"+1 404 845 0083",
    "sg:postcode":"30328",
    "sg:province":"GA",
    "sg:tags":[
        "trailers-equipment",
        "trailers-automobile",
        "parts-wholesale",
        "utility-manufacturers",
        "manufacturer"
    ],
    "wof:name":"Heil Trailer International",
    "wof:placetype":"venue"
},
  "geometry": {"coordinates":[-84.37088,33.92976],"type":"Point"}
}