{
  "type": "Feature",
  "properties": {
    "iso:country":"US",
    "sg:address":"5745 Buford Hwy NE",
    "sg:city":"Atlanta",
    "sg:classifiers":[
        {
            "category":"Shopping",
            "subcategory":"Beauty & Cosmetics",
            "type":"Retail Goods"
        }
    ],
    "sg:phone":"+1 770 451 4060",
    "sg:postcode":"30340",
    "sg:province":"GA",
    "sg:tags":[
        "supply"
    ],
    "wof:name":"A-1 Trading Company",
    "wof:placetype":"venue"
},
  "geometry": {"coordinates":[-84.26856100000001,33.907455],"type":"Point"}
}