{
  "type": "Feature",
  "properties": {
    "iso:country":"US",
    "sg:address":"1215 Hickory Flat Hwy",
    "sg:city":"Canton",
    "sg:classifiers":[
        {
            "category":"Real Estate",
            "subcategory":"Real Estate Operator",
            "type":"Services"
        }
    ],
    "sg:phone":"+1 770 720 1444",
    "sg:postcode":"30115",
    "sg:province":"GA",
    "sg:tags":[
        "apartment"
    ],
    "wof:name":"Laurels At Greenwood",
    "wof:placetype":"venue"
},
  "geometry": {"coordinates":[-84.418198,34.175598],"type":"Point"}
}