{
  "type": "Feature",
  "properties": {
    "addr:full":"43 Sycamore St Jefferson GA 30549",
    "addr:housenumber":"43",
    "addr:postcode":"30549",
    "addr:street":"Sycamore St",
    "iso:country":"US",
    "sg:address":"43 Sycamore St",
    "sg:city":"Jefferson",
    "sg:classifiers":[
        {
            "category":"Personal",
            "subcategory":"Beauty Salon",
            "type":"Services"
        }
    ],
    "sg:phone":"+1 706 367 5678",
    "sg:postcode":"30549",
    "sg:province":"GA",
    "sg:tags":[
        "shop"
    ],
    "wof:name":"Casual Beauty Shop",
    "wof:placetype":"venue"
},
  "geometry": {"coordinates":[-83.571955,34.118281],"type":"Point"}
}