{
  "type": "Feature",
  "properties": {
    "addr:full":"130 Ponderosa Dr Athens GA 30605",
    "addr:housenumber":"130",
    "addr:postcode":"30605",
    "addr:street":"Ponderosa Dr",
    "iso:country":"US",
    "sg:address":"130 Ponderosa Dr",
    "sg:city":"Athens",
    "sg:classifiers":[
        {
            "category":"Building & Trades",
            "subcategory":"Construction",
            "type":"Services"
        }
    ],
    "sg:phone":"+1 706 369 9143",
    "sg:postcode":"30605",
    "sg:province":"GA",
    "sg:tags":[
        "cleaning",
        "exterior"
    ],
    "wof:name":"Southeastern Cleaning Systems",
    "wof:placetype":"venue"
},
  "geometry": {"coordinates":[-83.327348,33.93362],"type":"Point"}
}