{
  "type": "Feature",
  "properties": {
    "iso:country":"US",
    "sg:address":"372 Johnson St",
    "sg:city":"Statesboro",
    "sg:classifiers":[
        {
            "category":"Building & Trades",
            "subcategory":"Construction",
            "type":"Services"
        }
    ],
    "sg:phone":"+1 912 764 5029",
    "sg:postcode":"30458",
    "sg:province":"GA",
    "sg:tags":[
        "house",
        "general",
        "contractor"
    ],
    "wof:name":"Paul Moore Construction Co",
    "wof:placetype":"venue"
},
  "geometry": {"coordinates":[-81.79749,32.444035],"type":"Point"}
}