{
  "type": "Feature",
  "properties": {
    "addr:full":"18 Sylvia Dr Bowdon GA 30108",
    "addr:housenumber":"18",
    "addr:postcode":"30108",
    "addr:street":"Sylvia Dr Bowdon",
    "iso:country":"US",
    "sg:address":"18 Sylvia Dr",
    "sg:city":"Bowdon",
    "sg:classifiers":[
        {
            "category":"Professional",
            "subcategory":"Detective & Security Services",
            "type":"Services"
        }
    ],
    "sg:phone":"+1 770 258 9971",
    "sg:postcode":"30108",
    "sg:province":"GA",
    "sg:tags":[
        "guard",
        "contract"
    ],
    "wof:name":"Eric Brown",
    "wof:placetype":"venue"
},
  "geometry": {"coordinates":[-85.25569400000001,33.517144],"type":"Point"}
}