{
  "type": "Feature",
  "properties": {
    "iso:country":"US",
    "sg:address":"912 Fernwood Rd",
    "sg:city":"Woodstock",
    "sg:classifiers":[
        {
            "category":"Travel",
            "subcategory":"Travel Agent",
            "type":"Entertainment"
        }
    ],
    "sg:phone":"+1 770 924 7689",
    "sg:postcode":"30189",
    "sg:province":"GA",
    "sg:tags":[
        "package"
    ],
    "wof:name":"Executive World Travel Inc",
    "wof:placetype":"venue"
},
  "geometry": {"coordinates":[-84.55387500000001,34.143155],"type":"Point"}
}