{
  "type": "Feature",
  "properties": {
    "addr:full":"8795 Terrace Ln Roswell GA 30076",
    "addr:housenumber":"8795",
    "addr:postcode":"30076",
    "addr:street":"Terrace Ln",
    "iso:country":"US",
    "sg:address":"8795 Terrace Ln",
    "sg:city":"Roswell",
    "sg:classifiers":[
        {
            "category":"Freight",
            "type":"Transportation"
        }
    ],
    "sg:phone":"+1 770 993 7250",
    "sg:postcode":"30076",
    "sg:province":"GA",
    "sg:tags":[
        "arrangement"
    ],
    "wof:name":"Capital Consolidators Inc",
    "wof:placetype":"venue"
},
  "geometry": {"coordinates":[-84.307998,33.994348],"type":"Point"}
}