{
  "type": "Feature",
  "properties": {
    "addr:full":"4308 Collard Valley Rd Cedartown GA 30125",
    "addr:postcode":"4308;30125",
    "addr:street":"Collard Valley Rd",
    "iso:country":"US",
    "sg:address":"4308 Collard Valley Rd",
    "sg:city":"Cedartown",
    "sg:classifiers":[
        {
            "category":"Retail",
            "subcategory":"Laundry & Dry Cleaning",
            "type":"Services"
        }
    ],
    "sg:phone":"+1 770 684 0552",
    "sg:postcode":"30125",
    "sg:province":"GA",
    "wof:name":"Daves Carpet Steamer",
    "wof:placetype":"venue"
},
  "geometry": {"coordinates":[-85.132868,34.064552],"type":"Point"}
}