{
  "type": "Feature",
  "properties": {
    "iso:country":"US",
    "sg:address":"4565 Danforth Rd SW",
    "sg:city":"Atlanta",
    "sg:classifiers":[
        {
            "category":"Professional",
            "subcategory":"Business Services",
            "type":"Services"
        }
    ],
    "sg:phone":"+1 404 699 1415",
    "sg:postcode":"30331",
    "sg:province":"GA",
    "wof:name":"Ms Design",
    "wof:placetype":"venue"
},
  "geometry": {"coordinates":[-84.539068,33.727325],"type":"Point"}
}