{
  "type": "Feature",
  "properties": {
    "iso:country":"US",
    "sg:address":"2104 Jeffersonville Rd",
    "sg:city":"Macon",
    "sg:classifiers":[
        {
            "category":"Health Services",
            "subcategory":"Nursing And Care Facility",
            "type":"Services"
        }
    ],
    "sg:phone":"+1 478 738 0015",
    "sg:postcode":"31217",
    "sg:province":"GA",
    "sg:tags":[
        "personal",
        "home"
    ],
    "wof:name":"Invericas Homes Inc",
    "wof:placetype":"venue"
},
  "geometry": {"coordinates":[-83.583822,32.851191],"type":"Point"}
}