{
  "type": "Feature",
  "properties": {
    "iso:country":"US",
    "sg:address":"1497 W 12th St",
    "sg:city":"Alma",
    "sg:classifiers":[
        {
            "category":"Organizations",
            "subcategory":"Religious Organization",
            "type":"Services"
        }
    ],
    "sg:phone":"+1 912 632 3744",
    "sg:postcode":"31510",
    "sg:province":"GA",
    "sg:tags":[
        "church"
    ],
    "wof:name":"First Community Church of Alma",
    "wof:placetype":"venue"
},
  "geometry": {"coordinates":[-82.496765,31.543596],"type":"Point"}
}