{
  "type": "Feature",
  "properties": {
    "iso:country":"US",
    "sg:address":"2759 Church St",
    "sg:city":"Atlanta",
    "sg:classifiers":[
        {
            "category":"Shopping",
            "subcategory":"Gifts & Souvenirs",
            "type":"Retail Goods"
        }
    ],
    "sg:phone":"+1 404 763 1773",
    "sg:postcode":"30344",
    "sg:province":"GA",
    "sg:tags":[
        "basket",
        "parcel"
    ],
    "wof:name":"A Different Basket Inc",
    "wof:placetype":"venue"
},
  "geometry": {"coordinates":[-84.44368,33.680226],"type":"Point"}
}