{
  "type": "Feature",
  "properties": {
    "addr:full":"112 24th Ave E Cordele GA 31015",
    "addr:housenumber":"112",
    "addr:postcode":"31015",
    "addr:street":"24Th Ave E",
    "iso:country":"US",
    "sg:address":"112 24th Ave E",
    "sg:city":"Cordele",
    "sg:classifiers":[
        {
            "category":"Personal",
            "subcategory":"Beauty Salon",
            "type":"Services"
        }
    ],
    "sg:phone":"+1 229 271 2322",
    "sg:postcode":"31015",
    "sg:province":"GA",
    "sg:tags":[
        "shop"
    ],
    "wof:name":"Sensations Beauty Salon",
    "wof:placetype":"venue"
},
  "geometry": {"coordinates":[-83.781031,31.954851],"type":"Point"}
}