{
  "type": "Feature",
  "properties": {
    "iso:country":"US",
    "sg:address":"4295 International Blvd NW",
    "sg:city":"Norcross",
    "sg:classifiers":[
        {
            "category":"Wholesale",
            "subcategory":"Medical Equipment & Supplies",
            "type":"Manufacturing & Wholesale Goods"
        }
    ],
    "sg:phone":"+1 770 441 7511",
    "sg:postcode":"30093",
    "sg:province":"GA",
    "sg:tags":[
        "therapy",
        "physical"
    ],
    "wof:name":"Medical Maintenance Conslnt",
    "wof:placetype":"venue"
},
  "geometry": {"coordinates":[-84.14550800000001,33.933994],"type":"Point"}
}