{
  "type": "Feature",
  "properties": {
    "addr:full":"1445 Maynard Road NW Atlanta GA 30331",
    "addr:housenumber":"1445",
    "addr:postcode":"30331",
    "addr:street":"Maynard Road Nw",
    "iso:country":"US",
    "sg:address":"1445 Maynard Road NW",
    "sg:city":"Atlanta",
    "sg:classifiers":[
        {
            "category":"Education",
            "subcategory":"School",
            "type":"Public Place"
        }
    ],
    "sg:phone":"+1 404 699 4504",
    "sg:postcode":"30331",
    "sg:province":"GA",
    "sg:tags":[
        "high",
        "middle",
        "elementary"
    ],
    "wof:name":"Atlanta City School District",
    "wof:placetype":"venue"
},
  "geometry": {"coordinates":[-84.498856,33.794644],"type":"Point"}
}