{
  "type": "Feature",
  "properties": {
    "iso:country":"US",
    "sg:address":"4001 Park Place Cir",
    "sg:city":"Ellenwood",
    "sg:classifiers":[
        {
            "category":"Wholesale",
            "subcategory":"Apparel",
            "type":"Manufacturing & Wholesale Goods"
        }
    ],
    "sg:phone":"+1 404 243 8500",
    "sg:postcode":"30294",
    "sg:province":"GA",
    "sg:tags":[
        "woman",
        "mfg"
    ],
    "wof:name":"LORd&robin Apparel Company",
    "wof:placetype":"venue"
},
  "geometry": {"coordinates":[-84.223297,33.65683],"type":"Point"}
}