{
  "type": "Feature",
  "properties": {
    "addr:full":"3133 Washington Rd Augusta GA 30907",
    "addr:housenumber":"3133",
    "addr:postcode":"30907",
    "addr:street":"Washington Rd",
    "iso:country":"US",
    "sg:address":"3133 Washington Rd",
    "sg:city":"Augusta",
    "sg:classifiers":[
        {
            "category":"Banks & Credit Unions",
            "subcategory":"Bank",
            "type":"Services"
        }
    ],
    "sg:phone":"+1 706 860 3133",
    "sg:postcode":"30907",
    "sg:province":"GA",
    "sg:tags":[
        "federal",
        "savings",
        "institution"
    ],
    "wof:name":"Georgia Bank & Trust Co",
    "wof:placetype":"venue"
},
  "geometry": {"coordinates":[-82.057057,33.514166],"type":"Point"}
}