{
  "type": "Feature",
  "properties": {
    "addr:full":"7 Alfred St Savannah GA 31408",
    "addr:housenumber":"7",
    "addr:postcode":"31408",
    "addr:street":"Alfred St",
    "iso:country":"US",
    "sg:address":"7 Alfred St",
    "sg:city":"Savannah",
    "sg:classifiers":[
        {
            "category":"Wholesale",
            "subcategory":"Meat",
            "type":"Manufacturing & Wholesale Goods"
        }
    ],
    "sg:phone":"+1 912 964 6335",
    "sg:postcode":"31408",
    "sg:province":"GA",
    "sg:tags":[
        "prod",
        "prepared"
    ],
    "wof:name":"Roger Wood Foods Inc",
    "wof:placetype":"venue"
},
  "geometry": {"coordinates":[-81.134755,32.08798],"type":"Point"}
}