{
  "type": "Feature",
  "properties": {
    "addr:full":"3232 Russell St Savannah GA 31404",
    "addr:housenumber":"3232",
    "addr:postcode":"31404",
    "addr:street":"Russell St",
    "iso:country":"US",
    "sg:address":"3232 Russell St",
    "sg:city":"Savannah",
    "sg:classifiers":[
        {
            "category":"Professional",
            "subcategory":"Lawyer & Legal Services",
            "type":"Services"
        }
    ],
    "sg:phone":"+1 912 355 7055",
    "sg:postcode":"31404",
    "sg:province":"GA",
    "sg:tags":[
        "firm"
    ],
    "wof:name":"Cardillo Frank G",
    "wof:placetype":"venue"
},
  "geometry": {"coordinates":[-81.050726,32.031195],"type":"Point"}
}