{
  "type": "Feature",
  "properties": {
    "iso:country":"US",
    "sg:address":"7995 Senoia Rd",
    "sg:city":"Fairburn",
    "sg:classifiers":[
        {
            "category":"Retail",
            "subcategory":"Car Wash",
            "type":"Services"
        }
    ],
    "sg:phone":"+1 770 969 4022",
    "sg:postcode":"30213",
    "sg:province":"GA",
    "wof:name":"Golden Car Wash Fairburn",
    "wof:placetype":"venue"
},
  "geometry": {"coordinates":[-84.577232,33.53692],"type":"Point"}
}