{
  "type": "Feature",
  "properties": {
    "addr:full":"340 Chandler Ct Buford GA 30518",
    "addr:housenumber":"340",
    "addr:postcode":"30518",
    "addr:street":"Chandler Ct",
    "iso:country":"US",
    "sg:address":"340 Chandler Ct",
    "sg:city":"Buford",
    "sg:classifiers":[
        {
            "category":"Manufacturing",
            "subcategory":"Tools & Machinery",
            "type":"Manufacturing & Wholesale Goods"
        }
    ],
    "sg:phone":"+1 770 271 9464",
    "sg:postcode":"30518",
    "sg:province":"GA",
    "sg:tags":[
        "mfg"
    ],
    "wof:name":"Dies Vincent A Etal",
    "wof:placetype":"venue"
},
  "geometry": {"coordinates":[-84.062254,34.086177],"type":"Point"}
}