{
  "type": "Feature",
  "properties": {
    "iso:country":"US",
    "sg:address":"719 3rd Ave",
    "sg:city":"Columbus",
    "sg:classifiers":[
        {
            "category":"Professional",
            "subcategory":"Management & Consulting",
            "type":"Services"
        }
    ],
    "sg:phone":"+1 706 324 1974",
    "sg:postcode":"31901",
    "sg:province":"GA",
    "sg:tags":[
        "personnel",
        "agency",
        "employment",
        "consultant"
    ],
    "wof:name":"Staff Zone",
    "wof:placetype":"venue"
},
  "geometry": {"coordinates":[-84.989023,32.459748],"type":"Point"}
}