{
  "type": "Feature",
  "properties": {
    "addr:full":"1581 Cobb Pkwy S Marietta GA 30060",
    "addr:housenumber":"1581",
    "addr:postcode":"30060",
    "addr:street":"Cobb Pkwy S",
    "iso:country":"US",
    "sg:address":"1581 Cobb Pkwy S",
    "sg:city":"Marietta",
    "sg:classifiers":[
        {
            "category":"Manufacturing",
            "subcategory":"Signs",
            "type":"Manufacturing & Wholesale Goods"
        }
    ],
    "sg:phone":"+1 770 984 0001",
    "sg:postcode":"30060",
    "sg:province":"GA",
    "sg:tags":[
        "mfg",
        "advertising",
        "specialty"
    ],
    "wof:name":"Fastsigns",
    "wof:placetype":"venue"
},
  "geometry": {"coordinates":[-84.49754,33.914077],"type":"Point"}
}