{
  "type": "Feature",
  "properties": {
    "addr:full":"1420 E Park Ave Valdosta GA 31602",
    "addr:housenumber":"1420",
    "addr:postcode":"31602",
    "addr:street":"E Park Ave",
    "iso:country":"US",
    "sg:address":"1420 E Park Ave",
    "sg:city":"Valdosta",
    "sg:classifiers":[
        {
            "category":"Professional",
            "subcategory":"Accounting & Tax Preparation",
            "type":"Services"
        }
    ],
    "sg:phone":"+1 229 241 1911",
    "sg:postcode":"31602",
    "sg:province":"GA",
    "sg:tags":[
        "return"
    ],
    "wof:name":"Platinum Tax",
    "wof:placetype":"venue"
},
  "geometry": {"coordinates":[-83.26844,30.857347],"type":"Point"}
}