{
  "type": "Feature",
  "properties": {
    "addr:full":"465 Glenwood Ave SE Atlanta GA 30312",
    "addr:housenumber":"465",
    "addr:postcode":"30312",
    "addr:street":"Glenwood Ave Se",
    "iso:country":"US",
    "sg:address":"465 Glenwood Ave SE",
    "sg:city":"Atlanta",
    "sg:classifiers":[
        {
            "category":"Wholesale",
            "subcategory":"Durable Goods & Equipment",
            "type":"Manufacturing & Wholesale Goods"
        }
    ],
    "sg:phone":"+1 404 284 2464",
    "sg:postcode":"30312",
    "sg:province":"GA",
    "sg:tags":[
        "exporter"
    ],
    "wof:name":"Georgia Enforcement Agency",
    "wof:placetype":"venue"
},
  "geometry": {"coordinates":[-84.372209,33.742941],"type":"Point"}
}