{
  "type": "Feature",
  "properties": {
    "addr:full":"420 Athens Hwy Loganville GA 30052",
    "addr:housenumber":"420",
    "addr:postcode":"30052",
    "addr:street":"Athens Hwy",
    "iso:country":"US",
    "sg:address":"420 Athens Hwy",
    "sg:city":"Loganville",
    "sg:classifiers":[
        {
            "category":"Manufacturing",
            "subcategory":"Motor Vehicles & Parts",
            "type":"Manufacturing & Wholesale Goods"
        }
    ],
    "sg:phone":"+1 770 554 3311",
    "sg:postcode":"30052",
    "sg:province":"GA",
    "sg:tags":[
        "body",
        "mfg"
    ],
    "wof:name":"Way Racing",
    "wof:placetype":"venue"
},
  "geometry": {"coordinates":[-83.928102,33.852756],"type":"Point"}
}