{
  "type": "Feature",
  "properties": {
    "addr:full":"2525 Old Alabama Rd Austell GA 30168",
    "addr:housenumber":"2525",
    "addr:postcode":"30168",
    "addr:street":"Old Alabama Rd",
    "iso:country":"US",
    "sg:address":"2525 Old Alabama Rd",
    "sg:city":"Austell",
    "sg:classifiers":[
        {
            "category":"Utilities",
            "subcategory":"Electric",
            "type":"Services"
        }
    ],
    "sg:phone":"+1 770 732 2100",
    "sg:postcode":"30168",
    "sg:province":"GA",
    "wof:name":"Georgia Power Company",
    "wof:placetype":"venue"
},
  "geometry": {"coordinates":[-84.62769900000001,33.799752],"type":"Point"}
}