{
  "type": "Feature",
  "properties": {
    "addr:full":"70 Ogden Rd Baxley GA 31546",
    "addr:housenumber":"70",
    "addr:postcode":"31546",
    "addr:street":"Ogden Rd",
    "iso:country":"US",
    "sg:address":"70 Ogden Rd",
    "sg:city":"Baxley",
    "sg:classifiers":[
        {
            "category":"Freight",
            "type":"Transportation"
        }
    ],
    "sg:phone":"+1 912 367 7832",
    "sg:postcode":"31546",
    "sg:province":"GA",
    "sg:tags":[
        "trucking"
    ],
    "sg:website":"www.aaacooper.com",
    "wof:name":"AAA Cooper Transportation",
    "wof:placetype":"venue"
},
  "geometry": {"coordinates":[-81.911475,31.579216],"type":"Point"}
}