{
  "type": "Feature",
  "properties": {
    "iso:country":"US",
    "sg:address":"431 Walker St",
    "sg:city":"Augusta",
    "sg:classifiers":[
        {
            "category":"Professional",
            "subcategory":"Lawyer & Legal Services",
            "type":"Services"
        }
    ],
    "sg:phone":"+1 706 722 7886",
    "sg:postcode":"30901",
    "sg:province":"GA",
    "sg:tags":[
        "attorney"
    ],
    "wof:name":"Kevin S Little PC",
    "wof:placetype":"venue"
},
  "geometry": {"coordinates":[-81.958382,33.468004],"type":"Point"}
}