{
  "type": "Feature",
  "properties": {
    "iso:country":"US",
    "sg:address":"4258 Cascade Rd",
    "sg:city":"Atlanta",
    "sg:classifiers":[
        {
            "category":"Organizations",
            "subcategory":"Membership Organization",
            "type":"Services"
        }
    ],
    "sg:phone":"+1 404 699 0118",
    "sg:postcode":"30331",
    "sg:province":"GA",
    "wof:name":"Providence Association Inc",
    "wof:placetype":"venue"
},
  "geometry": {"coordinates":[-84.52396,33.729732],"type":"Point"}
}