{
  "type": "Feature",
  "properties": {
    "iso:country":"US",
    "sg:address":"549 W Hill St",
    "sg:city":"Thomson",
    "sg:classifiers":[
        {
            "category":"Insurance",
            "subcategory":"Hazard Insurance",
            "type":"Services"
        }
    ],
    "sg:phone":"+1 706 597 8000",
    "sg:postcode":"30824",
    "sg:province":"GA",
    "wof:name":"Queensborough Agency",
    "wof:placetype":"venue"
},
  "geometry": {"coordinates":[-82.50779199999999,33.460655],"type":"Point"}
}