{
  "type": "Feature",
  "properties": {
    "iso:country":"US",
    "sg:address":"4270 Belier Frontage Rd",
    "sg:city":"Augusta",
    "sg:classifiers":[
        {
            "category":"Professional",
            "subcategory":"Business Services",
            "type":"Services"
        }
    ],
    "sg:phone":"+1 706 860 6807",
    "sg:postcode":"30909",
    "sg:province":"GA",
    "sg:tags":[
        "planning",
        "design",
        "drafting"
    ],
    "wof:name":"Definitive Designs",
    "wof:placetype":"venue"
},
  "geometry": {"coordinates":[-82.109008,33.485798],"type":"Point"}
}