{
  "type": "Feature",
  "properties": {
    "addr:full":"5730 Grove Point Rd Alpharetta GA 30022",
    "addr:housenumber":"5730",
    "addr:postcode":"30022",
    "addr:street":"Grove Point Rd",
    "iso:country":"US",
    "sg:address":"5730 Grove Point Rd",
    "sg:city":"Alpharetta",
    "sg:classifiers":[
        {
            "category":"Professional",
            "subcategory":"Computer Services",
            "type":"Services"
        }
    ],
    "sg:phone":"+1 770 495 7846",
    "sg:postcode":"30022",
    "sg:province":"GA",
    "sg:tags":[
        "website",
        "design"
    ],
    "wof:name":"Tech Genesis Co Inc",
    "wof:placetype":"venue"
},
  "geometry": {"coordinates":[-84.191863,34.024724],"type":"Point"}
}