{
  "type": "Feature",
  "properties": {
    "addr:full":"2960 Amwiler Rd Atlanta GA 30360",
    "addr:postcode":"2960;30360",
    "addr:street":"Amwiler Rd",
    "iso:country":"US",
    "sg:address":"2960 Amwiler Rd",
    "sg:city":"Atlanta",
    "sg:classifiers":[
        {
            "category":"Shopping",
            "type":"Retail Goods"
        }
    ],
    "sg:phone":"+1 770 458 7234",
    "sg:postcode":"30360",
    "sg:province":"GA",
    "sg:website":"www.dawsonjones.com",
    "wof:name":"Dawson & Jones Equipment",
    "wof:placetype":"venue"
},
  "geometry": {"coordinates":[-84.260566,33.927482],"type":"Point"}
}