{
  "type": "Feature",
  "properties": {
    "addr:full":"2320 Henry Clower Blvd Ste A Snellville GA 30078",
    "addr:housenumber":"2320",
    "addr:postcode":"30078",
    "addr:street":"Henry Clower Blvd Ste A",
    "iso:country":"US",
    "sg:address":"2320 Henry Clower Blvd Ste A",
    "sg:city":"Snellville",
    "sg:classifiers":[
        {
            "category":"Shopping",
            "subcategory":"Beauty & Cosmetics",
            "type":"Retail Goods"
        }
    ],
    "sg:phone":"+1 770 923 3708",
    "sg:postcode":"30078",
    "sg:province":"GA",
    "sg:tags":[
        "supply"
    ],
    "sg:website":"www.cbslink.com",
    "wof:name":"Columbia Beauty Supply",
    "wof:placetype":"venue"
},
  "geometry": {"coordinates":[-84.022034,33.853177],"type":"Point"}
}