{
  "type": "Feature",
  "properties": {
    "iso:country":"US",
    "sg:address":"184 Elbert St",
    "sg:city":"Athens",
    "sg:classifiers":[
        {
            "category":"Utilities",
            "subcategory":"Refuse",
            "type":"Services"
        }
    ],
    "sg:phone":"+1 706 227 3222",
    "sg:postcode":"30601",
    "sg:province":"GA",
    "sg:tags":[
        "garbage",
        "collection"
    ],
    "wof:name":"Waste Pro",
    "wof:placetype":"venue"
},
  "geometry": {"coordinates":[-83.35603500000001,33.947965],"type":"Point"}
}