{
  "type": "Feature",
  "properties": {
    "addr:full":"4670 Lionshead Cir Lithonia GA 30038",
    "addr:housenumber":"4670",
    "addr:postcode":"30038",
    "addr:street":"Lionshead Cir",
    "iso:country":"US",
    "sg:address":"4670 Lionshead Cir",
    "sg:city":"Lithonia",
    "sg:classifiers":[
        {
            "category":"Home & Garden",
            "subcategory":"Household Appliances",
            "type":"Retail Goods"
        },
        {
            "category":"Building & Trades",
            "subcategory":"Cleaning & Sanitation",
            "type":"Services"
        },
        {
            "category":"Building & Trades",
            "subcategory":"Construction",
            "type":"Services"
        }
    ],
    "sg:phone":"+1 770 808 8068",
    "sg:postcode":"30038",
    "sg:province":"GA",
    "sg:tags":[
        "site-clean-up",
        "floor",
        "waxing",
        "contractor",
        "window",
        "cleaning-industrial",
        "vacuum",
        "polishing",
        "janitorial"
    ],
    "sg:website":"https://smclean.custhelp.com/cgi-bin/smclean.cfg/php/enduser/doc_serve.php?2=BSYellowPages09",
    "wof:name":"ServiceMaster Clean",
    "wof:placetype":"venue"
},
  "geometry": {"coordinates":[-84.197389,33.694515],"type":"Point"}
}