{
  "type": "Feature",
  "properties": {
    "iso:country":"US",
    "sg:address":"1609 John Ward Rd SW",
    "sg:city":"Marietta",
    "sg:classifiers":[
        {
            "category":"Building & Trades",
            "subcategory":"Locksmith",
            "type":"Services"
        }
    ],
    "sg:phone":"+1 404 929 3640",
    "sg:postcode":"30064",
    "sg:province":"GA",
    "sg:tags":[
        "key"
    ],
    "wof:name":"A A Frederick Locksmith",
    "wof:placetype":"venue"
},
  "geometry": {"coordinates":[-84.60950099999999,33.913429],"type":"Point"}
}