{
  "type": "Feature",
  "properties": {
    "iso:country":"US",
    "sg:address":"202 E Oakridge Dr",
    "sg:city":"Albany",
    "sg:classifiers":[
        {
            "category":"Utilities",
            "subcategory":"Telephone",
            "type":"Services"
        }
    ],
    "sg:phone":"+1 229 888 2800",
    "sg:postcode":"31705",
    "sg:province":"GA",
    "sg:tags":[
        "communications"
    ],
    "wof:name":"Georgia Internet Cafe",
    "wof:placetype":"venue"
},
  "geometry": {"coordinates":[-84.14576599999999,31.552602],"type":"Point"}
}