{
  "type": "Feature",
  "properties": {
    "addr:full":"2266 Alpha Dr Decatur GA 30032",
    "addr:housenumber":"2266",
    "addr:postcode":"30032",
    "addr:street":"Alpha Dr",
    "iso:country":"US",
    "sg:address":"2266 Alpha Dr",
    "sg:city":"Decatur",
    "sg:classifiers":[
        {
            "category":"Arts & Performance",
            "subcategory":"Theater",
            "type":"Entertainment"
        }
    ],
    "sg:phone":"+1 404 378 0409",
    "sg:postcode":"30032",
    "sg:province":"GA",
    "sg:tags":[
        "company"
    ],
    "wof:name":"Paradise Entertainment Intl",
    "wof:placetype":"venue"
},
  "geometry": {"coordinates":[-84.29810500000001,33.730115],"type":"Point"}
}