{
  "type": "Feature",
  "properties": {
    "iso:country":"US",
    "sg:address":"1292 Parkside Club Dr NW",
    "sg:city":"Lawrenceville",
    "sg:classifiers":[
        {
            "category":"Professional",
            "type":"Services"
        }
    ],
    "sg:phone":"+1 770 338 2060",
    "sg:postcode":"30044",
    "sg:province":"GA",
    "wof:name":"Lowell Wright & As",
    "wof:placetype":"venue"
},
  "geometry": {"coordinates":[-84.07925,33.952721],"type":"Point"}
}