{
  "type": "Feature",
  "properties": {
    "iso:country":"US",
    "sg:address":"19 E Main St",
    "sg:city":"Dahlonega",
    "sg:classifiers":[
        {
            "category":"Restaurant",
            "type":"Food & Drink"
        }
    ],
    "sg:phone":"+1 706 864 9540",
    "sg:postcode":"30533",
    "sg:province":"GA",
    "sg:tags":[
        "pizza"
    ],
    "wof:name":"Curly's Pizza",
    "wof:placetype":"venue"
},
  "geometry": {"coordinates":[-83.984512,34.532887],"type":"Point"}
}