{
  "type": "Feature",
  "properties": {
    "addr:full":"121 Key Dr Brunswick GA 31520",
    "addr:housenumber":"121",
    "addr:postcode":"31520",
    "addr:street":"Key Dr",
    "iso:country":"US",
    "sg:address":"121 Key Dr",
    "sg:city":"Brunswick",
    "sg:classifiers":[
        {
            "category":"Retail",
            "subcategory":"Auto Repair",
            "type":"Services"
        }
    ],
    "sg:phone":"+1 912 265 5076",
    "sg:postcode":"31520",
    "sg:province":"GA",
    "sg:tags":[
        "repairing",
        "automobile"
    ],
    "wof:name":"Auto Express Svc Ctr",
    "wof:placetype":"venue"
},
  "geometry": {"coordinates":[-81.498333,31.200553],"type":"Point"}
}