{
  "type": "Feature",
  "properties": {
    "iso:country":"US",
    "sg:address":"1780 Century Blvd NE",
    "sg:city":"Atlanta",
    "sg:classifiers":[
        {
            "category":"Building & Trades",
            "subcategory":"Locksmith",
            "type":"Services"
        }
    ],
    "sg:phone":"+1 404 270 1800",
    "sg:postcode":"30345",
    "sg:province":"GA",
    "sg:tags":[
        "key"
    ],
    "wof:name":"Locksmith 24 Hours",
    "wof:placetype":"venue"
},
  "geometry": {"coordinates":[-84.314291,33.845922],"type":"Point"}
}