{
  "type": "Feature",
  "properties": {
    "iso:country":"US",
    "sg:address":"120 N 8th St",
    "sg:city":"Mc Intyre",
    "sg:classifiers":[
        {
            "category":"Personal",
            "subcategory":"Beauty Salon",
            "type":"Services"
        }
    ],
    "sg:phone":"+1 478 946 2122",
    "sg:postcode":"31054",
    "sg:province":"GA",
    "wof:name":"Becky's Family Hair Styles",
    "wof:placetype":"venue"
},
  "geometry": {"coordinates":[-83.20307099999999,32.847225],"type":"Point"}
}