{
  "type": "Feature",
  "properties": {
    "iso:country":"US",
    "sg:address":"100 N Selvidge St",
    "sg:city":"Dalton",
    "sg:classifiers":[
        {
            "category":"Professional",
            "subcategory":"Lawyer & Legal Services",
            "type":"Services"
        }
    ],
    "sg:phone":"+1 706 277 4000",
    "sg:postcode":"30720",
    "sg:province":"GA",
    "sg:tags":[
        "attorney"
    ],
    "wof:name":"Davis Kemp Joiner Melton",
    "wof:placetype":"venue"
},
  "geometry": {"coordinates":[-84.970709,34.772418],"type":"Point"}
}