{
  "type": "Feature",
  "properties": {
    "addr:full":"870 Pea Ridge Rd Eatonton GA 31024",
    "addr:housenumber":"870",
    "addr:postcode":"31024",
    "addr:street":"Pea Ridge Rd",
    "iso:country":"US",
    "sg:address":"870 Pea Ridge Rd",
    "sg:city":"Eatonton",
    "sg:classifiers":[
        {
            "category":"Farming",
            "subcategory":"Dairy Farm",
            "type":"Manufacturing & Wholesale Goods"
        }
    ],
    "sg:phone":"+1 706 485 8877",
    "sg:postcode":"31024",
    "sg:province":"GA",
    "wof:name":"De Loach & Son Dairy",
    "wof:placetype":"venue"
},
  "geometry": {"coordinates":[-83.294196,33.327675],"type":"Point"}
}