{
  "type": "Feature",
  "properties": {
    "addr:full":"4024 Stone Mountain St Tallapoosa GA 30176",
    "addr:housenumber":"4024",
    "addr:postcode":"30176",
    "addr:street":"Stone Mountain St",
    "iso:country":"US",
    "sg:address":"4024 Stone Mountain St",
    "sg:city":"Tallapoosa",
    "sg:classifiers":[
        {
            "category":"Wholesale",
            "subcategory":"Machinery & Supplies",
            "type":"Manufacturing & Wholesale Goods"
        }
    ],
    "sg:phone":"+1 770 574 2559",
    "sg:postcode":"30176",
    "sg:province":"GA",
    "sg:tags":[
        "rubber",
        "product"
    ],
    "wof:name":"Cox Rubber Products Co",
    "wof:placetype":"venue"
},
  "geometry": {"coordinates":[-85.292102,33.72871],"type":"Point"}
}