{
  "type": "Feature",
  "properties": {
    "addr:full":"1701 S Slappey Blvd Albany GA 31701",
    "addr:housenumber":"1701",
    "addr:postcode":"31701",
    "addr:street":"S Slappey Blvd",
    "iso:country":"US",
    "sg:address":"1701 S Slappey Blvd",
    "sg:city":"Albany",
    "sg:classifiers":[
        {
            "category":"Wholesale",
            "subcategory":"Machinery & Supplies",
            "type":"Manufacturing & Wholesale Goods"
        }
    ],
    "sg:phone":"+1 229 439 2217",
    "sg:postcode":"31701",
    "sg:province":"GA",
    "sg:tags":[
        "farm",
        "equipment"
    ],
    "wof:name":"Amadas Industries",
    "wof:placetype":"venue"
},
  "geometry": {"coordinates":[-84.176692,31.556131],"type":"Point"}
}