{
  "type": "Feature",
  "properties": {
    "addr:full":"711 E Victory Dr Savannah GA 31405",
    "addr:housenumber":"711",
    "addr:postcode":"31405",
    "addr:street":"E Victory Dr",
    "iso:country":"US",
    "sg:address":"711 E Victory Dr",
    "sg:city":"Savannah",
    "sg:classifiers":[
        {
            "category":"Organizations",
            "subcategory":"Religious Organization",
            "type":"Services"
        }
    ],
    "sg:phone":"+1 912 236 8271",
    "sg:postcode":"31405",
    "sg:province":"GA",
    "wof:name":"First Christian Preschool",
    "wof:placetype":"venue"
},
  "geometry": {"coordinates":[-81.089398,32.049301],"type":"Point"}
}