{
  "type": "Feature",
  "properties": {
    "addr:full":"2119 Lake Park Dr SE Smyrna GA 30080",
    "addr:housenumber":"2119",
    "addr:postcode":"30080",
    "addr:street":"Lake Park Dr Se",
    "iso:country":"US",
    "sg:address":"2119 Lake Park Dr SE",
    "sg:city":"Smyrna",
    "sg:classifiers":[
        {
            "category":"Professional",
            "subcategory":"Computer Services",
            "type":"Services"
        }
    ],
    "sg:phone":"+1 770 801 0953",
    "sg:postcode":"30080",
    "sg:province":"GA",
    "sg:tags":[
        "consulting",
        "internet"
    ],
    "wof:name":"Applied Internet Technologies",
    "wof:placetype":"venue"
},
  "geometry": {"coordinates":[-84.491896,33.895019],"type":"Point"}
}