{
  "type": "Feature",
  "properties": {
    "addr:full":"6901 Glenlake Pkwy NE Atlanta GA 30328",
    "addr:housenumber":"6901",
    "addr:postcode":"30328",
    "addr:street":"Glenlake Pkwy Ne",
    "iso:country":"US",
    "sg:address":"6901 Glenlake Pkwy NE",
    "sg:city":"Atlanta",
    "sg:phone":"+1 877 515 3442",
    "sg:postcode":"30328",
    "sg:province":"GA",
    "sg:website":"http://local.ingenio.com/Listings/Details.aspx?NUM=a%3a10328995%3a13%3a4859924%3a14%3a0%3a7",
    "wof:name":"Glen Lake",
    "wof:placetype":"venue"
},
  "geometry": {"coordinates":[-84.364161,33.94253],"type":"Point"}
}