{
  "type": "Feature",
  "properties": {
    "iso:country":"US",
    "sg:address":"801 Conley Rd SE",
    "sg:city":"Atlanta",
    "sg:classifiers":[
        {
            "category":"Building & Trades",
            "subcategory":"Locksmith",
            "type":"Services"
        }
    ],
    "sg:phone":"+1 770 308 1419",
    "sg:postcode":"30354",
    "sg:province":"GA",
    "sg:tags":[
        "key"
    ],
    "wof:name":"0 1 Emergency A Locksmith",
    "wof:placetype":"venue"
},
  "geometry": {"coordinates":[-84.363356,33.648566],"type":"Point"}
}