{
  "type": "Feature",
  "properties": {
    "addr:full":"324 John Elliott Rd McDonough GA 30252",
    "addr:housenumber":"324",
    "addr:postcode":"30252",
    "addr:street":"John Elliott Rd",
    "iso:country":"US",
    "sg:address":"324 John Elliott Rd",
    "sg:city":"McDonough",
    "sg:classifiers":[
        {
            "category":"Building & Trades",
            "subcategory":"Locksmith",
            "type":"Services"
        }
    ],
    "sg:phone":"+1 888 353 9542",
    "sg:postcode":"30252",
    "sg:province":"GA",
    "sg:tags":[
        "key"
    ],
    "wof:name":"A 1 Lock & Locksmith",
    "wof:placetype":"venue"
},
  "geometry": {"coordinates":[-84.123458,33.516402],"type":"Point"}
}