{
  "type": "Feature",
  "properties": {
    "addr:full":"321 Greenville St Lagrange GA 30241",
    "addr:housenumber":"321",
    "addr:postcode":"30241",
    "addr:street":"Greenville St",
    "iso:country":"US",
    "sg:address":"321 Greenville St",
    "sg:city":"Lagrange",
    "sg:classifiers":[
        {
            "category":"Health Services",
            "subcategory":"Doctor",
            "type":"Services"
        }
    ],
    "sg:phone":"+1 706 884 1080",
    "sg:postcode":"30241",
    "sg:province":"GA",
    "sg:tags":[
        "physician",
        "surgeon"
    ],
    "wof:name":"Center For Creative Growth",
    "wof:placetype":"venue"
},
  "geometry": {"coordinates":[-85.025233,33.040189],"type":"Point"}
}