{
  "type": "Feature",
  "properties": {
    "addr:full":"314 S Hamilton St Dalton GA 30720",
    "addr:housenumber":"314",
    "addr:postcode":"30720",
    "addr:street":"S Hamilton St",
    "iso:country":"US",
    "sg:address":"314 S Hamilton St",
    "sg:city":"Dalton",
    "sg:classifiers":[
        {
            "category":"Health Services",
            "subcategory":"Clinic",
            "type":"Services"
        }
    ],
    "sg:phone":"+1 706 270 5040",
    "sg:postcode":"30720",
    "sg:province":"GA",
    "sg:tags":[
        "specialty",
        "outpatient"
    ],
    "wof:name":"Three Rivers",
    "wof:placetype":"venue"
},
  "geometry": {"coordinates":[-84.967972,34.769679],"type":"Point"}
}