{
  "type": "Feature",
  "properties": {
    "iso:country":"US",
    "sg:address":"3539 Cherry Hill Ct",
    "sg:city":"Decatur",
    "sg:classifiers":[
        {
            "category":"Real Estate",
            "subcategory":"Real Estate Agent",
            "type":"Services"
        }
    ],
    "sg:phone":"+1 404 244 0084",
    "sg:postcode":"30034",
    "sg:province":"GA",
    "wof:name":"Gaither Realty",
    "wof:placetype":"venue"
},
  "geometry": {"coordinates":[-84.23993299999999,33.679522],"type":"Point"}
}