{
  "type": "Feature",
  "properties": {
    "iso:country":"US",
    "sg:address":"936 I St",
    "sg:city":"Waycross",
    "sg:classifiers":[
        {
            "category":"Professional",
            "type":"Services"
        }
    ],
    "sg:phone":"+1 912 283 7903",
    "sg:postcode":"31501",
    "sg:province":"GA",
    "wof:name":"James Conaway",
    "wof:placetype":"venue"
},
  "geometry": {"coordinates":[-82.365937,31.221074],"type":"Point"}
}