{
  "type": "Feature",
  "properties": {
    "iso:country":"US",
    "sg:address":"6217 Hwy 278 NE",
    "sg:city":"Covington",
    "sg:phone":"+1 770 784 1305",
    "sg:postcode":"30014",
    "sg:province":"GA",
    "sg:tags":[
        "transmission",
        "facsimile"
    ],
    "wof:name":"Public Fax",
    "wof:placetype":"venue"
},
  "geometry": {"coordinates":[-83.842562,33.602217],"type":"Point"}
}