{
  "type": "Feature",
  "properties": {
    "iso:country":"US",
    "sg:address":"4057 Ivey Gate",
    "sg:city":"Atlanta",
    "sg:classifiers":[
        {
            "category":"Professional",
            "subcategory":"Business Services",
            "type":"Services"
        }
    ],
    "sg:phone":"+1 770 455 7251",
    "sg:postcode":"30341",
    "sg:province":"GA",
    "wof:name":"Rhjg Enterprises LLC",
    "wof:placetype":"venue"
},
  "geometry": {"coordinates":[-84.315774,33.914103],"type":"Point"}
}