{
  "type": "Feature",
  "properties": {
    "addr:full":"46 N Church St Clayton GA 30525",
    "addr:housenumber":"46",
    "addr:postcode":"30525",
    "addr:street":"N Church St",
    "iso:country":"US",
    "sg:address":"46 N Church St",
    "sg:city":"Clayton",
    "sg:classifiers":[
        {
            "category":"Personal",
            "subcategory":"Massage",
            "type":"Services"
        }
    ],
    "sg:phone":"+1 706 782 3841",
    "sg:postcode":"30525",
    "sg:province":"GA",
    "wof:name":"Sandra Broker Lic Massage Ther",
    "wof:placetype":"venue"
},
  "geometry": {"coordinates":[-83.40190699999999,34.879279],"type":"Point"}
}