{
  "type": "Feature",
  "properties": {
    "addr:full":"3358 Carpet Capital Dr SW Dalton GA 30720",
    "addr:housenumber":"3358",
    "addr:postcode":"30720",
    "addr:street":"Carpet Capital Dr Sw",
    "iso:country":"US",
    "sg:address":"3358 Carpet Capital Dr SW",
    "sg:city":"Dalton",
    "sg:classifiers":[
        {
            "category":"Manufacturing",
            "subcategory":"Textiles",
            "type":"Manufacturing & Wholesale Goods"
        }
    ],
    "sg:phone":"+1 706 259 9486",
    "sg:postcode":"30720",
    "sg:province":"GA",
    "sg:tags":[
        "rug",
        "carpet"
    ],
    "wof:name":"Northwest Carpets Inc",
    "wof:placetype":"venue"
},
  "geometry": {"coordinates":[-85.003254,34.676713],"type":"Point"}
}