{
  "type": "Feature",
  "properties": {
    "iso:country":"US",
    "sg:address":"383 Pine Forest Dr",
    "sg:city":"Lawrenceville",
    "sg:classifiers":[
        {
            "category":"Insurance",
            "subcategory":"Insurance Agent",
            "type":"Services"
        }
    ],
    "sg:phone":"+1 770 338 0188",
    "sg:postcode":"30045",
    "sg:province":"GA",
    "wof:name":"Choice Insurance",
    "wof:placetype":"venue"
},
  "geometry": {"coordinates":[-83.99411600000001,33.930125],"type":"Point"}
}