{
  "type": "Feature",
  "properties": {
    "iso:country":"US",
    "sg:address":"2251 State Rte 121",
    "sg:city":"Mershon",
    "sg:classifiers":[
        {
            "category":"Autos & Motor Vehicles",
            "subcategory":"Automobile Sales",
            "type":"Retail Goods"
        }
    ],
    "sg:phone":"+1 912 647 0604",
    "sg:postcode":"31551",
    "sg:province":"GA",
    "sg:tags":[
        "car",
        "used",
        "dealer"
    ],
    "wof:name":"Integrity Auto Sales",
    "wof:placetype":"venue"
},
  "geometry": {"coordinates":[-82.21828499999999,31.434614],"type":"Point"}
}