{
  "type": "Feature",
  "properties": {
    "addr:full":"7295 Julian Wiley Rd Lula GA 30554",
    "addr:housenumber":"7295",
    "addr:postcode":"30554",
    "addr:street":"Julian Wiley Rd",
    "iso:country":"US",
    "sg:address":"7295 Julian Wiley Rd",
    "sg:city":"Lula",
    "sg:classifiers":[
        {
            "category":"Building & Trades",
            "subcategory":"Plumbing",
            "type":"Services"
        }
    ],
    "sg:phone":"+1 770 983 3434",
    "sg:postcode":"30554",
    "sg:province":"GA",
    "sg:tags":[
        "contractor"
    ],
    "wof:name":"Wiley Plumbing",
    "wof:placetype":"venue"
},
  "geometry": {"coordinates":[-83.714277,34.441929],"type":"Point"}
}