{
  "type": "Feature",
  "properties": {
    "iso:country":"US",
    "sg:address":"41 Fox Croft Rd",
    "sg:city":"Rome",
    "sg:classifiers":[
        {
            "category":"Government",
            "subcategory":"Office",
            "type":"Public Place"
        }
    ],
    "sg:phone":"+1 706 802 7682",
    "sg:postcode":"30165",
    "sg:province":"GA",
    "sg:tags":[
        "educational",
        "program"
    ],
    "wof:name":"GA Educ tech Consortium Inc",
    "wof:placetype":"venue"
},
  "geometry": {"coordinates":[-85.26442299999999,34.280734],"type":"Point"}
}