{
  "type": "Feature",
  "properties": {
    "iso:country":"US",
    "sg:address":"1139 Hubbard St SW",
    "sg:city":"Atlanta",
    "sg:classifiers":[
        {
            "category":"Organizations",
            "subcategory":"Religious Organization",
            "type":"Services"
        }
    ],
    "sg:phone":"+1 404 223 6419",
    "sg:postcode":"30310",
    "sg:province":"GA",
    "sg:tags":[
        "church"
    ],
    "wof:name":"New Greater Timothy Baptist",
    "wof:placetype":"venue"
},
  "geometry": {"coordinates":[-84.40250899999999,33.723367],"type":"Point"}
}