{
  "type": "Feature",
  "properties": {
    "iso:country":"US",
    "sg:address":"379 Atlanta St SE",
    "sg:city":"Marietta",
    "sg:classifiers":[
        {
            "category":"Professional",
            "subcategory":"Management & Consulting",
            "type":"Services"
        }
    ],
    "sg:phone":"+1 770 419 1500",
    "sg:postcode":"30060",
    "sg:province":"GA",
    "sg:tags":[
        "business"
    ],
    "wof:name":"Performnce Enhncment Strtegies",
    "wof:placetype":"venue"
},
  "geometry": {"coordinates":[-84.54589300000001,33.943517],"type":"Point"}
}