{
  "type": "Feature",
  "properties": {
    "addr:full":"5133 Parnell Way Augusta GA 30907",
    "addr:housenumber":"5133",
    "addr:postcode":"30907",
    "addr:street":"Parnell Way",
    "iso:country":"US",
    "sg:address":"5133 Parnell Way",
    "sg:city":"Augusta",
    "sg:classifiers":[
        {
            "category":"Building & Trades",
            "subcategory":"Plumbing",
            "type":"Services"
        }
    ],
    "sg:phone":"+1 706 868 7731",
    "sg:postcode":"30907",
    "sg:province":"GA",
    "sg:tags":[
        "contractor"
    ],
    "wof:name":"Custom Mechanical CSRA Inc",
    "wof:placetype":"venue"
},
  "geometry": {"coordinates":[-82.160307,33.487347],"type":"Point"}
}