{
  "type": "Feature",
  "properties": {
    "addr:full":"1135 Veterans Memorial Hwy SW Mableton GA 30126",
    "addr:housenumber":"1135",
    "addr:postcode":"30126",
    "addr:street":"Veterans Memorial Hwy Sw",
    "iso:country":"US",
    "sg:address":"1135 Veterans Memorial Hwy SW",
    "sg:city":"Mableton",
    "sg:classifiers":[
        {
            "category":"Shopping",
            "subcategory":"Department Store",
            "type":"Retail Goods"
        }
    ],
    "sg:phone":"+1 770 739 2425",
    "sg:postcode":"30126",
    "sg:province":"GA",
    "sg:tags":[
        "variety"
    ],
    "sg:website":"http://www.dollar.com",
    "wof:name":"Dolex Dollar Express, Inc.",
    "wof:placetype":"venue"
},
  "geometry": {"coordinates":[-84.587704,33.817479],"type":"Point"}
}