{
  "type": "Feature",
  "properties": {
    "iso:country":"US",
    "sg:address":"1643 Mount Vernon Rd",
    "sg:city":"Dunwoody",
    "sg:classifiers":[
        {
            "category":"Building & Trades",
            "subcategory":"Equipment Rental",
            "type":"Services"
        }
    ],
    "sg:phone":"+1 770 828 0095",
    "sg:postcode":"30338",
    "sg:province":"GA",
    "sg:tags":[
        "leasing"
    ],
    "sg:website":"www.crestcapital.com",
    "wof:name":"Crest Capital & Leasing",
    "wof:placetype":"venue"
},
  "geometry": {"coordinates":[-84.332278,33.946669],"type":"Point"}
}