{
  "type": "Feature",
  "properties": {
    "iso:country":"US",
    "sg:address":"4268 Seago Rd",
    "sg:city":"Hephzibah",
    "sg:classifiers":[
        {
            "category":"Manufacturing",
            "subcategory":"Lumber",
            "type":"Manufacturing & Wholesale Goods"
        }
    ],
    "sg:phone":"+1 706 831 0379",
    "sg:postcode":"30815",
    "sg:province":"GA",
    "sg:tags":[
        "hardwood",
        "mills",
        "dimension",
        "flooring"
    ],
    "wof:name":"Augusta Aiken Wood Flooring",
    "wof:placetype":"venue"
},
  "geometry": {"coordinates":[-82.00962699999999,33.312264],"type":"Point"}
}