{
  "type": "Feature",
  "properties": {
    "addr:full":"804 Whitesville St Lagrange GA 30240",
    "addr:housenumber":"804",
    "addr:postcode":"30240",
    "addr:street":"Whitesville St",
    "iso:country":"US",
    "sg:address":"804 Whitesville St",
    "sg:city":"Lagrange",
    "sg:classifiers":[
        {
            "category":"Restaurant",
            "type":"Food & Drink"
        }
    ],
    "sg:phone":"+1 706 845 7117",
    "sg:postcode":"30240",
    "sg:province":"GA",
    "wof:name":"Southern Belle's Fried Chicken",
    "wof:placetype":"venue"
},
  "geometry": {"coordinates":[-85.028932,33.026112],"type":"Point"}
}