{
  "type": "Feature",
  "properties": {
    "iso:country":"US",
    "sg:address":"118 Thornwood Dr SW",
    "sg:city":"Rome",
    "sg:classifiers":[
        {
            "category":"Professional",
            "subcategory":"Business Services",
            "type":"Services"
        }
    ],
    "sg:phone":"+1 770 855 7438",
    "sg:postcode":"30165",
    "sg:province":"GA",
    "sg:tags":[
        "consultant",
        "coach"
    ],
    "wof:name":"Brannan Edwards",
    "wof:placetype":"venue"
},
  "geometry": {"coordinates":[-85.252392,34.263334],"type":"Point"}
}