{
  "type": "Feature",
  "properties": {
    "iso:country":"US",
    "sg:address":"6067 Buford Hwy",
    "sg:city":"Norcross",
    "sg:classifiers":[
        {
            "category":"Travel",
            "subcategory":"Hotels & Motels",
            "type":"Entertainment"
        },
        {
            "category":"Real Estate",
            "subcategory":"Real Estate Operator",
            "type":"Services"
        }
    ],
    "sg:phone":"+1 770 840 7778",
    "sg:postcode":"30071",
    "sg:province":"GA",
    "sg:tags":[
        "apartment"
    ],
    "wof:name":"Intown Suites of Norcross",
    "wof:placetype":"venue"
},
  "geometry": {"coordinates":[-84.2201,33.932701],"type":"Point"}
}