{
  "type": "Feature",
  "properties": {
    "addr:full":"4754 Woodmere Ln Columbus GA 31907",
    "addr:housenumber":"4754",
    "addr:postcode":"31907",
    "addr:street":"Woodmere Ln",
    "iso:country":"US",
    "sg:address":"4754 Woodmere Ln",
    "sg:city":"Columbus",
    "sg:classifiers":[
        {
            "category":"Manufacturing",
            "subcategory":"Tools & Machinery",
            "type":"Manufacturing & Wholesale Goods"
        }
    ],
    "sg:phone":"+1 706 561 3176",
    "sg:postcode":"31907",
    "sg:province":"GA",
    "sg:tags":[
        "c",
        "mfg",
        "industry",
        "hanging"
    ],
    "wof:name":"Hmf Services",
    "wof:placetype":"venue"
},
  "geometry": {"coordinates":[-84.91384600000001,32.501035],"type":"Point"}
}