{
  "type": "Feature",
  "properties": {
    "addr:full":"624 New St Macon GA 31201",
    "addr:housenumber":"624",
    "addr:postcode":"31201",
    "addr:street":"New St",
    "iso:country":"US",
    "sg:address":"624 New St",
    "sg:city":"Macon",
    "sg:classifiers":[
        {
            "category":"Health Services",
            "subcategory":"Clinic",
            "type":"Services"
        }
    ],
    "sg:phone":"+1 478 633 1331",
    "sg:postcode":"31201",
    "sg:province":"GA",
    "sg:tags":[
        "home",
        "care"
    ],
    "wof:name":"GA Medical Resource Pool",
    "wof:placetype":"venue"
},
  "geometry": {"coordinates":[-83.63460000000001,32.835392],"type":"Point"}
}