{
  "type": "Feature",
  "properties": {
    "addr:full":"4718 Arapahoe Trl Gainesville GA 30506",
    "addr:housenumber":"4718",
    "addr:postcode":"30506",
    "addr:street":"Arapahoe Trl",
    "iso:country":"US",
    "sg:address":"4718 Arapahoe Trl",
    "sg:city":"Gainesville",
    "sg:classifiers":[
        {
            "category":"Insurance",
            "subcategory":"Hazard Insurance",
            "type":"Services"
        }
    ],
    "sg:phone":"+1 770 983 2300",
    "sg:postcode":"30506",
    "sg:province":"GA",
    "sg:tags":[
        "commercial",
        "business"
    ],
    "wof:name":"Jon Cronic Ins",
    "wof:placetype":"venue"
},
  "geometry": {"coordinates":[-83.84864399999999,34.419392],"type":"Point"}
}