{
  "type": "Feature",
  "properties": {
    "addr:full":"29 Augusta Rd North Augusta SC 29822",
    "addr:postcode":"29822",
    "addr:street":"29 Augusta Rd",
    "iso:country":"US",
    "sg:address":"29 Augusta Rd",
    "sg:city":"North Augusta",
    "sg:classifiers":[
        {
            "category":"Health Services",
            "subcategory":"Nursing And Care Facility",
            "type":"Services"
        }
    ],
    "sg:phone":"+1 803 593 9608",
    "sg:postcode":"29822",
    "sg:province":"SC",
    "sg:tags":[
        "home",
        "retirement",
        "community"
    ],
    "wof:name":"Gregory's Community Care",
    "wof:placetype":"venue"
},
  "geometry": {"coordinates":[-81.89211400000001,33.49667],"type":"Point"}
}