{
  "type": "Feature",
  "properties": {
    "iso:country":"US",
    "sg:address":"1802 Skidmore Cir",
    "sg:city":"Lawrenceville",
    "sg:classifiers":[
        {
            "category":"Building & Trades",
            "subcategory":"Plumbing",
            "type":"Services"
        }
    ],
    "sg:phone":"+1 404 280 6389",
    "sg:postcode":"30044",
    "sg:province":"GA",
    "sg:tags":[
        "contractor"
    ],
    "wof:name":"Circuit Services",
    "wof:placetype":"venue"
},
  "geometry": {"coordinates":[-84.033529,33.91935],"type":"Point"}
}