{
  "type": "Feature",
  "properties": {
    "addr:full":"921 Reed Ave Atlanta GA 30344",
    "addr:housenumber":"921",
    "addr:postcode":"30344",
    "addr:street":"Reed Ave",
    "iso:country":"US",
    "sg:address":"921 Reed Ave",
    "sg:city":"Atlanta",
    "sg:classifiers":[
        {
            "category":"Arts & Performance",
            "subcategory":"Theater",
            "type":"Entertainment"
        }
    ],
    "sg:phone":"+1 404 767 5587",
    "sg:postcode":"30344",
    "sg:province":"GA",
    "sg:tags":[
        "theatrical"
    ],
    "wof:name":"Close Link Ltd",
    "wof:placetype":"venue"
},
  "geometry": {"coordinates":[-84.419265,33.68027],"type":"Point"}
}