{
  "type": "Feature",
  "properties": {
    "iso:country":"US",
    "sg:address":"3917 Bull St",
    "sg:city":"Savannah",
    "sg:classifiers":[
        {
            "category":"Retail",
            "subcategory":"Auto Repair",
            "type":"Services"
        }
    ],
    "sg:phone":"+1 912 651 0100",
    "sg:postcode":"31405",
    "sg:province":"GA",
    "sg:tags":[
        "automotive",
        "general"
    ],
    "wof:name":"Discount Tune & Lube",
    "wof:placetype":"venue"
},
  "geometry": {"coordinates":[-81.106228,32.041898],"type":"Point"}
}