{
  "type": "Feature",
  "properties": {
    "iso:country":"US",
    "sg:address":"235 King Rd",
    "sg:city":"Alto",
    "sg:classifiers":[
        {
            "category":"Personal",
            "subcategory":"Beauty Salon",
            "type":"Services"
        }
    ],
    "sg:phone":"+1 706 776 2971",
    "sg:postcode":"30510",
    "sg:province":"GA",
    "sg:tags":[
        "shop"
    ],
    "wof:name":"Shear Fantasy Buty & Tan Salon",
    "wof:placetype":"venue"
},
  "geometry": {"coordinates":[-83.621342,34.460018],"type":"Point"}
}