{
  "type": "Feature",
  "properties": {
    "iso:country":"US",
    "sg:address":"422 Whitaker St",
    "sg:city":"Savannah",
    "sg:classifiers":[
        {
            "category":"Shopping",
            "subcategory":"Used Merchandise",
            "type":"Retail Goods"
        }
    ],
    "sg:phone":"+1 912 236 6000",
    "sg:postcode":"31401",
    "sg:province":"GA",
    "wof:name":"Arcanum Antiques Interiors",
    "wof:placetype":"venue"
},
  "geometry": {"coordinates":[-81.09575700000001,32.071868],"type":"Point"}
}