{
  "type": "Feature",
  "properties": {
    "iso:country":"US",
    "sg:address":"1600 Athens Hwy",
    "sg:city":"Gainesville",
    "sg:classifiers":[
        {
            "category":"Manufacturing",
            "subcategory":"Metals",
            "type":"Manufacturing & Wholesale Goods"
        }
    ],
    "sg:phone":"+1 770 533 9724",
    "sg:postcode":"30507",
    "sg:province":"GA",
    "sg:tags":[
        "fabrication",
        "structural"
    ],
    "wof:name":"Strategic Concepts Inc",
    "wof:placetype":"venue"
},
  "geometry": {"coordinates":[-83.800371,34.283516],"type":"Point"}
}