{
  "type": "Feature",
  "properties": {
    "iso:country":"US",
    "sg:address":"601 NW Frontage Rd",
    "sg:city":"Augusta",
    "sg:classifiers":[
        {
            "category":"Travel",
            "subcategory":"Hotels & Motels",
            "type":"Entertainment"
        }
    ],
    "sg:phone":"+1 706 863 2882",
    "sg:postcode":"30907",
    "sg:province":"GA",
    "sg:tags":[
        "operation"
    ],
    "wof:name":"Howard Johnson",
    "wof:placetype":"venue"
},
  "geometry": {"coordinates":[-82.086938,33.497984],"type":"Point"}
}