{
  "type": "Feature",
  "properties": {
    "iso:country":"US",
    "sg:address":"1357 Flat Shoals Rd SW",
    "sg:city":"Conyers",
    "sg:classifiers":[
        {
            "category":"Building & Trades",
            "subcategory":"Electrical",
            "type":"Services"
        }
    ],
    "sg:phone":"+1 770 922 8005",
    "sg:postcode":"30094",
    "sg:province":"GA",
    "sg:tags":[
        "electrical",
        "contractor"
    ],
    "wof:name":"Premier Electrical Servic",
    "wof:placetype":"venue"
},
  "geometry": {"coordinates":[-84.035006,33.646541],"type":"Point"}
}