{
  "type": "Feature",
  "properties": {
    "addr:full":"3400 Concord Corner SE Conyers GA 30013",
    "addr:housenumber":"3400",
    "addr:postcode":"30013",
    "addr:street":"Concord;Se",
    "iso:country":"US",
    "sg:address":"3400 Concord Corner SE",
    "sg:city":"Conyers",
    "sg:classifiers":[
        {
            "category":"Professional",
            "type":"Services"
        }
    ],
    "sg:phone":"+1 770 918 0628",
    "sg:postcode":"30013",
    "sg:province":"GA",
    "wof:name":"Kam Service Inc",
    "wof:placetype":"venue"
},
  "geometry": {"coordinates":[-83.982742,33.599419],"type":"Point"}
}