{
  "type": "Feature",
  "properties": {
    "addr:full":"49 Toni Branch Rd Ellabell GA 31308",
    "addr:housenumber":"49",
    "addr:postcode":"31308",
    "addr:street":"Toni Branch Rd",
    "iso:country":"US",
    "sg:address":"49 Toni Branch Rd",
    "sg:city":"Ellabell",
    "sg:classifiers":[
        {
            "category":"Manufacturing",
            "subcategory":"Motor Vehicles & Parts",
            "type":"Manufacturing & Wholesale Goods"
        }
    ],
    "sg:phone":"+1 912 858 2959",
    "sg:postcode":"31308",
    "sg:province":"GA",
    "sg:tags":[
        "body",
        "mfg"
    ],
    "wof:name":"Shuman Towing",
    "wof:placetype":"venue"
},
  "geometry": {"coordinates":[-81.512378,32.151572],"type":"Point"}
}