{
  "type": "Feature",
  "properties": {
    "iso:country":"US",
    "sg:address":"6067 Buford Hwy NE Suite B",
    "sg:city":"Atlanta",
    "sg:classifiers":[
        {
            "category":"Professional",
            "type":"Services"
        }
    ],
    "sg:phone":"+1 770 368 8222",
    "sg:postcode":"30340",
    "sg:province":"GA",
    "sg:tags":[
        "caterer"
    ],
    "wof:name":"Jin Gogae Catering Corporation",
    "wof:placetype":"venue"
},
  "geometry": {"coordinates":[-84.25993699999999,33.916184],"type":"Point"}
}