{
  "type": "Feature",
  "properties": {
    "addr:full":"880 Buckhead Rd Statesboro GA 30442",
    "addr:housenumber":"880",
    "addr:postcode":"30442",
    "addr:street":"Buckhead Rd",
    "iso:country":"US",
    "sg:address":"880 Buckhead Rd",
    "sg:city":"Statesboro",
    "sg:classifiers":[
        {
            "category":"Restaurant",
            "type":"Food & Drink"
        }
    ],
    "sg:phone":"+1 912 489 3242",
    "sg:postcode":"30442",
    "sg:province":"GA",
    "wof:name":"Sonic Drive-In",
    "wof:placetype":"venue"
},
  "geometry": {"coordinates":[-81.953304,32.808839],"type":"Point"}
}