{
  "type": "Feature",
  "properties": {
    "addr:full":"30 State Rte 101 Dallas GA 30157",
    "addr:housenumber":"30",
    "addr:postcode":"30157",
    "addr:street":"State Rte 101",
    "iso:country":"US",
    "sg:address":"30 State Rte 101",
    "sg:city":"Dallas",
    "sg:classifiers":[
        {
            "category":"Home & Garden",
            "subcategory":"Hardware",
            "type":"Retail Goods"
        }
    ],
    "sg:phone":"+1 770 459 2176",
    "sg:postcode":"30157",
    "sg:province":"GA",
    "wof:name":"Swafford's Grocery",
    "wof:placetype":"venue"
},
  "geometry": {"coordinates":[-84.982024,33.844846],"type":"Point"}
}