{
  "type": "Feature",
  "properties": {
    "iso:country":"US",
    "sg:address":"3272 Holly Mill Ct",
    "sg:city":"Marietta",
    "sg:classifiers":[
        {
            "category":"Government",
            "subcategory":"Office",
            "type":"Public Place"
        }
    ],
    "sg:phone":"+1 770 321 6284",
    "sg:postcode":"30062",
    "sg:province":"GA",
    "sg:tags":[
        "equipment",
        "wildlife",
        "consulting",
        "sales"
    ],
    "wof:name":"Environmental Management Svcs",
    "wof:placetype":"venue"
},
  "geometry": {"coordinates":[-84.457049,34.000344],"type":"Point"}
}