{
  "type": "Feature",
  "properties": {
    "iso:country":"US",
    "sg:address":"926 Winall Down Rd NE",
    "sg:city":"Atlanta",
    "sg:classifiers":[
        {
            "category":"Real Estate",
            "subcategory":"Real Estate Agent",
            "type":"Services"
        }
    ],
    "sg:phone":"+1 404 231 9822",
    "sg:postcode":"30319",
    "sg:province":"GA",
    "wof:name":"Deyonker Real Estate Group",
    "wof:placetype":"venue"
},
  "geometry": {"coordinates":[-84.357017,33.864421],"type":"Point"}
}