{
  "type": "Feature",
  "properties": {
    "addr:full":"1111 Ethridge Mill Rd Griffin GA 30224",
    "addr:housenumber":"1111",
    "addr:postcode":"30224",
    "addr:street":"Ethridge Mill Rd",
    "iso:country":"US",
    "sg:address":"1111 Ethridge Mill Rd",
    "sg:city":"Griffin",
    "sg:classifiers":[
        {
            "category":"Recreation",
            "type":"Entertainment"
        }
    ],
    "sg:phone":"+1 770 233 1218",
    "sg:postcode":"30224",
    "sg:province":"GA",
    "sg:tags":[
        "parlor",
        "billiard"
    ],
    "wof:name":"Griffin Billiards",
    "wof:placetype":"venue"
},
  "geometry": {"coordinates":[-84.27112,33.219945],"type":"Point"}
}