{
  "type": "Feature",
  "properties": {
    "addr:full":"109 Park of Commerce Dr Savannah GA 31405",
    "addr:housenumber":"109",
    "addr:postcode":"31405",
    "addr:street":"Park;Dr",
    "iso:country":"US",
    "sg:address":"109 Park of Commerce Dr",
    "sg:city":"Savannah",
    "sg:classifiers":[
        {
            "category":"Professional",
            "subcategory":"Engineering",
            "type":"Services"
        }
    ],
    "sg:phone":"+1 912 236 4565",
    "sg:postcode":"31405",
    "sg:province":"GA",
    "sg:tags":[
        "engineer"
    ],
    "wof:name":"Dean Oliver Intl",
    "wof:placetype":"venue"
},
  "geometry": {"coordinates":[-81.16143599999999,32.063934],"type":"Point"}
}