{
  "type": "Feature",
  "properties": {
    "iso:country":"US",
    "sg:address":"122 Birdie Rd",
    "sg:city":"Griffin",
    "sg:classifiers":[
        {
            "category":"Building & Trades",
            "subcategory":"Construction",
            "type":"Services"
        }
    ],
    "sg:phone":"+1 770 228 6552",
    "sg:postcode":"30223",
    "sg:province":"GA",
    "sg:tags":[
        "nonresidential"
    ],
    "wof:name":"Meek Construction Inc",
    "wof:placetype":"venue"
},
  "geometry": {"coordinates":[-84.286563,33.319263],"type":"Point"}
}