{
  "type": "Feature",
  "properties": {
    "addr:full":"3218 Mike Padgett Hwy Augusta GA 30906",
    "addr:housenumber":"3218",
    "addr:postcode":"30906",
    "addr:street":"Mike Padgett Hwy",
    "iso:country":"US",
    "sg:address":"3218 Mike Padgett Hwy",
    "sg:city":"Augusta",
    "sg:classifiers":[
        {
            "category":"Manufacturing",
            "subcategory":"Buildings",
            "type":"Manufacturing & Wholesale Goods"
        },
        {
            "category":"Building & Trades",
            "subcategory":"Construction",
            "type":"Services"
        }
    ],
    "sg:phone":"+1 706 790 7273",
    "sg:postcode":"30906",
    "sg:province":"GA",
    "sg:tags":[
        "foundation",
        "waterproofing",
        "house",
        "contractor",
        "mover",
        "raising"
    ],
    "sg:website":"http://www.bartonandbartonaugusta.com",
    "wof:name":"Barton And Barton Contracting",
    "wof:placetype":"venue"
},
  "geometry": {"coordinates":[-82.00633500000001,33.408181],"type":"Point"}
}