{
  "type": "Feature",
  "properties": {
    "iso:country":"US",
    "sg:address":"3884 Rock Mill Pkwy",
    "sg:city":"Marietta",
    "sg:classifiers":[
        {
            "category":"Professional",
            "subcategory":"Business Services",
            "type":"Services"
        }
    ],
    "sg:phone":"+1 770 649 9115",
    "sg:postcode":"30062",
    "sg:province":"GA",
    "wof:name":"Lance Michael Enterprises Inc",
    "wof:placetype":"venue"
},
  "geometry": {"coordinates":[-84.435997,34.03849],"type":"Point"}
}