{
  "type": "Feature",
  "properties": {
    "addr:full":"1645 Redan E Lithonia GA 30058",
    "addr:housenumber":"1645",
    "addr:postcode":"30058",
    "addr:street":"Redan E",
    "iso:country":"US",
    "sg:address":"1645 Redan E",
    "sg:city":"Lithonia",
    "sg:classifiers":[
        {
            "category":"Social Services",
            "subcategory":"Child Care",
            "type":"Services"
        }
    ],
    "sg:phone":"+1 678 526 9755",
    "sg:postcode":"30058",
    "sg:province":"GA",
    "sg:tags":[
        "day"
    ],
    "wof:name":"Christian Imani Child Care",
    "wof:placetype":"venue"
},
  "geometry": {"coordinates":[-84.128083,33.743247],"type":"Point"}
}