{
  "type": "Feature",
  "properties": {
    "addr:full":"130 Emerald Dr Mc Donough GA 30253",
    "addr:housenumber":"130",
    "addr:postcode":"30253",
    "addr:street":"Emerald Dr",
    "iso:country":"US",
    "sg:address":"130 Emerald Dr",
    "sg:city":"Mc Donough",
    "sg:classifiers":[
        {
            "category":"Professional",
            "type":"Services"
        }
    ],
    "sg:phone":"+1 678 432 8211",
    "sg:postcode":"30253",
    "sg:province":"GA",
    "wof:name":"Kuhne Sandra M & Glenn",
    "wof:placetype":"venue"
},
  "geometry": {"coordinates":[-84.141434,33.474018],"type":"Point"}
}