{
  "type": "Feature",
  "properties": {
    "iso:country":"US",
    "sg:address":"127 Peachtree St NE Ste 700",
    "sg:city":"Atlanta",
    "sg:classifiers":[
        {
            "category":"Professional",
            "subcategory":"Lawyer & Legal Services",
            "type":"Services"
        }
    ],
    "sg:phone":"+1 404 653 0300",
    "sg:postcode":"30303",
    "sg:province":"GA",
    "wof:name":"Andre & Blaustein",
    "wof:placetype":"venue"
},
  "geometry": {"coordinates":[-84.38809999999999,33.756901],"type":"Point"}
}