{
  "type": "Feature",
  "properties": {
    "iso:country":"US",
    "sg:address":"378 Ridge Rd",
    "sg:city":"Dawsonville",
    "sg:classifiers":[
        {
            "category":"Wholesale",
            "subcategory":"Electrical",
            "type":"Manufacturing & Wholesale Goods"
        }
    ],
    "sg:phone":"+1 770 893 6043",
    "sg:postcode":"30534",
    "sg:province":"GA",
    "sg:tags":[
        "control",
        "security",
        "system"
    ],
    "wof:name":"All Secure Alert Systems Inc",
    "wof:placetype":"venue"
},
  "geometry": {"coordinates":[-84.210413,34.527001],"type":"Point"}
}