{
  "type": "Feature",
  "properties": {
    "iso:country":"US",
    "sg:address":"149 Peyton Place SW Suite 1",
    "sg:city":"Atlanta",
    "sg:classifiers":[
        {
            "category":"Professional",
            "type":"Services"
        }
    ],
    "sg:phone":"+1 404 505 9706",
    "sg:postcode":"30311",
    "sg:province":"GA",
    "sg:tags":[
        "publication",
        "editorial"
    ],
    "wof:name":"AE Jones Scientific Publishing Co",
    "wof:placetype":"venue"
},
  "geometry": {"coordinates":[-84.47590599999999,33.750591],"type":"Point"}
}