{
  "type": "Feature",
  "properties": {
    "iso:country":"US",
    "sg:address":"109 Franklin St",
    "sg:city":"Darien",
    "sg:classifiers":[
        {
            "category":"Real Estate",
            "subcategory":"Real Estate Agent",
            "type":"Services"
        }
    ],
    "sg:phone":"+1 912 437 6863",
    "sg:postcode":"31305",
    "sg:province":"GA",
    "sg:tags":[
        "appraiser"
    ],
    "wof:name":"Greenhaven Consulting",
    "wof:placetype":"venue"
},
  "geometry": {"coordinates":[-81.43323599999999,31.36856],"type":"Point"}
}