{
  "type": "Feature",
  "properties": {
    "iso:country":"US",
    "sg:address":"375 McDonough Rd",
    "sg:city":"Jackson",
    "sg:classifiers":[
        {
            "category":"Health Services",
            "subcategory":"Doctor",
            "type":"Services"
        }
    ],
    "sg:phone":"+1 770 775 4622",
    "sg:postcode":"30233",
    "sg:province":"GA",
    "sg:tags":[
        "physician",
        "surgeon"
    ],
    "wof:name":"Jackson Medical Bldg Family",
    "wof:placetype":"venue"
},
  "geometry": {"coordinates":[-83.971158,33.297416],"type":"Point"}
}