{
  "type": "Feature",
  "properties": {
    "iso:country":"US",
    "sg:address":"1000 Bus Center Dr",
    "sg:city":"Savannah",
    "sg:classifiers":[
        {
            "category":"Utilities",
            "subcategory":"Telephone",
            "type":"Services"
        }
    ],
    "sg:phone":"+1 912 233 1407",
    "sg:postcode":"31405",
    "sg:province":"GA",
    "sg:tags":[
        "communications"
    ],
    "wof:name":"AT&T",
    "wof:placetype":"venue"
},
  "geometry": {"coordinates":[-81.16396899999999,32.05218],"type":"Point"}
}