{
  "type": "Feature",
  "properties": {
    "addr:full":"3624 J Dewey Gray Cir Augusta GA 30909",
    "addr:housenumber":"3624 j",
    "addr:postcode":"30909",
    "addr:street":"Dewey Gray Cir",
    "iso:country":"US",
    "sg:address":"3624 J Dewey Gray Cir",
    "sg:city":"Augusta",
    "sg:classifiers":[
        {
            "category":"Health Services",
            "subcategory":"Hospital",
            "type":"Services"
        }
    ],
    "sg:phone":"+1 706 651 6199",
    "sg:postcode":"30909",
    "sg:province":"GA",
    "wof:name":"Acute Care Consultants Of Augusta",
    "wof:placetype":"venue"
},
  "geometry": {"coordinates":[-82.096687,33.48621],"type":"Point"}
}