{
  "type": "Feature",
  "properties": {
    "addr:full":"3280 Peachtree Rd NE #27 Atlanta GA 30305",
    "addr:housenumber":"3280",
    "addr:postcode":"30305",
    "addr:street":"Peachtree Rd Ne # 27",
    "iso:country":"US",
    "sg:address":"3280 Peachtree Rd NE #27",
    "sg:city":"Atlanta",
    "sg:classifiers":[
        {
            "category":"Professional",
            "subcategory":"Management & Consulting",
            "type":"Services"
        },
        {
            "category":"Banks & Credit Unions",
            "subcategory":"Investment Brokerage",
            "type":"Services"
        },
        {
            "category":"Banks & Credit Unions",
            "subcategory":"Financial Services",
            "type":"Services"
        }
    ],
    "sg:phone":"+1 404 760 2210",
    "sg:postcode":"30305",
    "sg:province":"GA",
    "sg:tags":[
        "advisory",
        "financing",
        "planner",
        "consultant",
        "planning",
        "trust"
    ],
    "sg:website":"http://www.wilmingtontrust.com",
    "wof:name":"Wilmington Trust",
    "wof:placetype":"venue"
},
  "geometry": {"coordinates":[-84.369946,33.844524],"type":"Point"}
}