{
  "type": "Feature",
  "properties": {
    "iso:country":"US",
    "sg:address":"388 Robinson Rd",
    "sg:city":"Chatsworth",
    "sg:classifiers":[
        {
            "category":"Professional",
            "subcategory":"Employment Agencies",
            "type":"Services"
        }
    ],
    "sg:phone":"+1 706 270 3179",
    "sg:postcode":"30705",
    "sg:province":"GA",
    "sg:tags":[
        "help",
        "supply"
    ],
    "wof:name":"Jackson Trucking",
    "wof:placetype":"venue"
},
  "geometry": {"coordinates":[-84.842185,34.736046],"type":"Point"}
}