{
  "type": "Feature",
  "properties": {
    "addr:full":"150 Maison Pl NW Atlanta GA 30327",
    "addr:housenumber":"150",
    "addr:postcode":"30327",
    "addr:street":"Maison Pl Nw",
    "iso:country":"US",
    "sg:address":"150 Maison Pl NW",
    "sg:city":"Atlanta",
    "sg:classifiers":[
        {
            "category":"Home & Garden",
            "subcategory":"Building Materials",
            "type":"Retail Goods"
        },
        {
            "category":"Building & Trades",
            "subcategory":"Construction",
            "type":"Services"
        }
    ],
    "sg:phone":"+1 678 442 6333",
    "sg:postcode":"30327",
    "sg:province":"GA",
    "sg:tags":[
        "roofing",
        "industrial",
        "altering",
        "contractor",
        "contractors-commercial",
        "remodeling"
    ],
    "sg:website":"http://www.columbiahi.com",
    "wof:name":"Columbia Home Improvement (Dunw Tel No)",
    "wof:placetype":"venue"
},
  "geometry": {"coordinates":[-84.424713,33.816292],"type":"Point"}
}