{
  "type": "Feature",
  "properties": {
    "iso:country":"US",
    "sg:address":"665 Amberidge Trl NW",
    "sg:city":"Atlanta",
    "sg:classifiers":[
        {
            "category":"Retail",
            "subcategory":"Portrait Studio",
            "type":"Services"
        },
        {
            "category":"Professional",
            "subcategory":"Art Services",
            "type":"Services"
        }
    ],
    "sg:phone":"+1 404 303 1415",
    "sg:postcode":"30328",
    "sg:province":"GA",
    "sg:tags":[
        "rental",
        "photographers-portrait",
        "photographic",
        "darkroom"
    ],
    "wof:name":"Schaben Pictorials",
    "wof:placetype":"venue"
},
  "geometry": {"coordinates":[-84.402387,33.932997],"type":"Point"}
}