{
  "type": "Feature",
  "properties": {
    "iso:country":"US",
    "sg:address":"1151 Dawson Rd",
    "sg:city":"Albany",
    "sg:classifiers":[
        {
            "category":"Real Estate",
            "subcategory":"Real Estate Agent",
            "type":"Services"
        }
    ],
    "sg:phone":"+1 229 438 9707",
    "sg:postcode":"31707",
    "sg:province":"GA",
    "sg:tags":[
        "appraiser",
        "business"
    ],
    "wof:name":"Musgrove Appraisals",
    "wof:placetype":"venue"
},
  "geometry": {"coordinates":[-84.17627400000001,31.581591],"type":"Point"}
}