{
  "type": "Feature",
  "properties": {
    "addr:full":"3600 Dekalb Technology Pkwy Atlanta GA 30340",
    "addr:housenumber":"3600",
    "addr:postcode":"30340",
    "addr:street":"Dekalb Technology Pkwy",
    "iso:country":"US",
    "sg:address":"3600 Dekalb Technology Pkwy",
    "sg:city":"Atlanta",
    "sg:classifiers":[
        {
            "category":"Professional",
            "subcategory":"Management & Consulting",
            "type":"Services"
        }
    ],
    "sg:phone":"+1 404 419 6326",
    "sg:postcode":"30340",
    "sg:province":"GA",
    "sg:tags":[
        "consultant",
        "motel",
        "hotel"
    ],
    "wof:name":"Amorc-Atlanta Lodge",
    "wof:placetype":"venue"
},
  "geometry": {"coordinates":[-84.27166,33.881409],"type":"Point"}
}