{
  "type": "Feature",
  "properties": {
    "iso:country":"US",
    "sg:address":"2867 Donald Lee Hollowell Pkwy NW",
    "sg:city":"Atlanta",
    "sg:classifiers":[
        {
            "category":"Autos & Motor Vehicles",
            "subcategory":"Auto Supplies",
            "type":"Retail Goods"
        }
    ],
    "sg:phone":"+1 404 799 0808",
    "sg:postcode":"30318",
    "sg:province":"GA",
    "sg:tags":[
        "tire"
    ],
    "wof:name":"Jordan Tire Service",
    "wof:placetype":"venue"
},
  "geometry": {"coordinates":[-84.481706,33.781001],"type":"Point"}
}