{
  "type": "Feature",
  "properties": {
    "addr:full":"1130 Cumberland Mall SE Atlanta GA 30339",
    "addr:housenumber":"1130",
    "addr:postcode":"30339",
    "addr:street":"Cumberland Mall Se",
    "iso:country":"US",
    "sg:address":"1130 Cumberland Mall SE",
    "sg:city":"Atlanta",
    "sg:classifiers":[
        {
            "category":"Shopping",
            "subcategory":"Shoes",
            "type":"Retail Goods"
        }
    ],
    "sg:phone":"+1 770 431 8564",
    "sg:postcode":"30339",
    "sg:province":"GA",
    "sg:tags":[
        "store"
    ],
    "wof:name":"Bakers Shoes",
    "wof:placetype":"venue"
},
  "geometry": {"coordinates":[-84.47161699999999,33.88133],"type":"Point"}
}