{
  "type": "Feature",
  "properties": {
    "iso:country":"US",
    "sg:address":"333 Sandy Springs Cir NE",
    "sg:city":"Atlanta",
    "sg:classifiers":[
        {
            "category":"Professional",
            "type":"Services"
        }
    ],
    "sg:phone":"+1 404 531 0379",
    "sg:postcode":"30328",
    "sg:province":"GA",
    "sg:tags":[
        "actuary"
    ],
    "wof:name":"Acturial Services & Financial",
    "wof:placetype":"venue"
},
  "geometry": {"coordinates":[-84.379757,33.926727],"type":"Point"}
}