{
  "type": "Feature",
  "properties": {
    "iso:country":"US",
    "sg:address":"447 River North Blvd",
    "sg:city":"Macon",
    "sg:classifiers":[
        {
            "category":"Professional",
            "subcategory":"Management & Consulting",
            "type":"Services"
        }
    ],
    "sg:phone":"+1 478 743 5214",
    "sg:postcode":"31211",
    "sg:province":"GA",
    "sg:tags":[
        "consultation",
        "disability",
        "vocational"
    ],
    "wof:name":"OConnor & Company Inc",
    "wof:placetype":"venue"
},
  "geometry": {"coordinates":[-83.66776900000001,32.935598],"type":"Point"}
}