{
  "type": "Feature",
  "properties": {
    "addr:full":"2701 Washington Rd Augusta GA 30904",
    "addr:housenumber":"2701",
    "addr:postcode":"30904",
    "addr:street":"Washington Rd",
    "iso:country":"US",
    "sg:address":"2701 Washington Rd",
    "sg:city":"Augusta",
    "sg:classifiers":[
        {
            "category":"Utilities",
            "subcategory":"Mobile Phone",
            "type":"Services"
        }
    ],
    "sg:phone":"+1 706 396 7200",
    "sg:postcode":"30904",
    "sg:province":"GA",
    "sg:tags":[
        "telephone",
        "cellular"
    ],
    "wof:name":"Sprint PCS",
    "wof:placetype":"venue"
},
  "geometry": {"coordinates":[-82.024598,33.509077],"type":"Point"}
}