{
  "type": "Feature",
  "properties": {
    "addr:full":"111 Wedowee St Bowdon GA 30108",
    "addr:housenumber":"111",
    "addr:postcode":"30108",
    "addr:street":"Wedowee St",
    "iso:country":"US",
    "sg:address":"111 Wedowee St",
    "sg:city":"Bowdon",
    "sg:classifiers":[
        {
            "category":"Arts & Performance",
            "subcategory":"Theater",
            "type":"Entertainment"
        }
    ],
    "sg:phone":"+1 770 838 9889",
    "sg:postcode":"30108",
    "sg:province":"GA",
    "sg:tags":[
        "dance",
        "company"
    ],
    "wof:name":"Generation Dance",
    "wof:placetype":"venue"
},
  "geometry": {"coordinates":[-85.25322799999999,33.537473],"type":"Point"}
}