{
  "type": "Feature",
  "properties": {
    "iso:country":"US",
    "sg:address":"4441 Homestead Dr SE",
    "sg:city":"Acworth",
    "sg:classifiers":[
        {
            "category":"Building & Trades",
            "subcategory":"Construction",
            "type":"Services"
        }
    ],
    "sg:phone":"+1 770 845 5270",
    "sg:postcode":"30102",
    "sg:province":"GA",
    "sg:tags":[
        "contractor"
    ],
    "wof:name":"Kab Contractors",
    "wof:placetype":"venue"
},
  "geometry": {"coordinates":[-84.67805799999999,34.085451],"type":"Point"}
}