{
  "type": "Feature",
  "properties": {
    "addr:full":"845 Rose Cir SW Atlanta GA 30310",
    "addr:housenumber":"845",
    "addr:postcode":"30310",
    "addr:street":"Rose Cir Sw",
    "iso:country":"US",
    "sg:address":"845 Rose Cir SW",
    "sg:city":"Atlanta",
    "sg:classifiers":[
        {
            "category":"Place Of Worship",
            "subcategory":"Church",
            "type":"Public Place"
        }
    ],
    "sg:phone":"+1 404 752 9948",
    "sg:postcode":"30310",
    "sg:province":"GA",
    "sg:tags":[
        "churches-non-denominational"
    ],
    "wof:name":"Accomplishing Things By Faith Ministries",
    "wof:placetype":"venue"
},
  "geometry": {"coordinates":[-84.415192,33.730999],"type":"Point"}
}