{
  "type": "Feature",
  "properties": {
    "iso:country":"US",
    "sg:address":"295 Capri Dr",
    "sg:city":"Gainesville",
    "sg:classifiers":[
        {
            "category":"Health Services",
            "subcategory":"Health Practitioner",
            "type":"Services"
        }
    ],
    "sg:phone":"+1 770 536 1633",
    "sg:postcode":"30506",
    "sg:province":"GA",
    "wof:name":"Linda Singleton",
    "wof:placetype":"venue"
},
  "geometry": {"coordinates":[-83.86155100000001,34.343686],"type":"Point"}
}