{
  "type": "Feature",
  "properties": {
    "iso:country":"US",
    "sg:address":"3770 Pentel Ct NW",
    "sg:city":"Atlanta",
    "sg:classifiers":[
        {
            "category":"Wholesale",
            "subcategory":"Electrical",
            "type":"Manufacturing & Wholesale Goods"
        }
    ],
    "sg:phone":"+1 770 668 0679",
    "sg:postcode":"30360",
    "sg:province":"GA",
    "sg:tags":[
        "equipment",
        "engineering"
    ],
    "wof:name":"Georgia Farmis Inc",
    "wof:placetype":"venue"
},
  "geometry": {"coordinates":[-84.262648,33.956344],"type":"Point"}
}