{
  "type": "Feature",
  "properties": {
    "addr:full":"233 Peachtree St Atlanta GA 30303",
    "addr:housenumber":"233",
    "addr:postcode":"30303",
    "addr:street":"Peachtree St",
    "iso:country":"US",
    "sg:address":"233 Peachtree St",
    "sg:city":"Atlanta",
    "sg:classifiers":[
        {
            "category":"Fast Food",
            "type":"Food & Drink"
        },
        {
            "category":"Restaurant",
            "type":"Food & Drink"
        },
        {
            "category":"Ice Cream",
            "type":"Food & Drink"
        }
    ],
    "sg:phone":"+1 404 389 0682",
    "sg:postcode":"30303",
    "sg:province":"GA",
    "sg:tags":[
        "frozen",
        "dessert"
    ],
    "sg:website":"http://www.dairyqueen.com",
    "wof:name":"Dairy Queen",
    "wof:placetype":"venue"
},
  "geometry": {"coordinates":[-84.395263,33.748091],"type":"Point"}
}