{
  "type": "Feature",
  "properties": {
    "addr:full":"600 S Central Ave Atlanta GA 30354",
    "addr:housenumber":"600",
    "addr:postcode":"30354",
    "addr:street":"S Central Ave",
    "iso:country":"US",
    "sg:address":"600 S Central Ave",
    "sg:city":"Atlanta",
    "sg:classifiers":[
        {
            "category":"Personal",
            "type":"Services"
        }
    ],
    "sg:phone":"+1 404 368 6890",
    "sg:postcode":"30354",
    "sg:province":"GA",
    "sg:tags":[
        "consultant",
        "program",
        "health",
        "fitness"
    ],
    "sg:website":"http://quickeasydiets.net",
    "wof:name":"Quick Easy Diets",
    "wof:placetype":"venue"
},
  "geometry": {"coordinates":[-84.407661,33.657784],"type":"Point"}
}