{
  "type": "Feature",
  "properties": {
    "iso:country":"US",
    "sg:address":"2933 Milledgeville Rd",
    "sg:city":"Augusta",
    "sg:classifiers":[
        {
            "category":"Building & Trades",
            "subcategory":"Construction",
            "type":"Services"
        }
    ],
    "sg:phone":"+1 706 739 0331",
    "sg:postcode":"30904",
    "sg:province":"GA",
    "sg:tags":[
        "home",
        "builder"
    ],
    "wof:name":"Apple Homes",
    "wof:placetype":"venue"
},
  "geometry": {"coordinates":[-82.03958299999999,33.447963],"type":"Point"}
}