{
  "type": "Feature",
  "properties": {
    "addr:full":"315 Commerce Blvd Bogart GA 30622",
    "addr:housenumber":"315",
    "addr:postcode":"30622",
    "addr:street":"Commerce Blvd",
    "iso:country":"US",
    "sg:address":"315 Commerce Blvd",
    "sg:city":"Bogart",
    "sg:classifiers":[
        {
            "category":"Manufacturing",
            "subcategory":"Tools & Machinery",
            "type":"Manufacturing & Wholesale Goods"
        }
    ],
    "sg:phone":"+1 706 546 5578",
    "sg:postcode":"30622",
    "sg:province":"GA",
    "sg:tags":[
        "trade",
        "repair",
        "industrial",
        "contract",
        "mfg"
    ],
    "wof:name":"Athens Speciality Mfg Inc",
    "wof:placetype":"venue"
},
  "geometry": {"coordinates":[-83.477783,33.931171],"type":"Point"}
}