{
  "type": "Feature",
  "properties": {
    "addr:full":"5280 Winder Hwy Braselton GA 30517",
    "addr:housenumber":"5280",
    "addr:postcode":"30517",
    "addr:street":"Winder Hwy",
    "iso:country":"US",
    "sg:address":"5280 Winder Hwy",
    "sg:city":"Braselton",
    "sg:classifiers":[
        {
            "category":"Autos & Motor Vehicles",
            "subcategory":"Automobile Sales",
            "type":"Retail Goods"
        }
    ],
    "sg:phone":"+1 770 965 4112",
    "sg:postcode":"30517",
    "sg:province":"GA",
    "sg:tags":[
        "performance",
        "race",
        "dealer"
    ],
    "wof:name":"MSB Motorsport",
    "wof:placetype":"venue"
},
  "geometry": {"coordinates":[-83.812574,34.151764],"type":"Point"}
}