{
  "type": "Feature",
  "properties": {
    "addr:full":"333 Main St Ste 100 Suwanee GA 30024",
    "addr:housenumber":"333",
    "addr:postcode":"30024",
    "addr:street":"Main St Ste 100",
    "iso:country":"US",
    "sg:address":"333 Main St Ste 100",
    "sg:city":"Suwanee",
    "sg:classifiers":[
        {
            "category":"Retail",
            "subcategory":"Portrait Studio",
            "type":"Services"
        },
        {
            "category":"Professional",
            "subcategory":"Art Services",
            "type":"Services"
        },
        {
            "category":"Professional",
            "subcategory":"Printing & Photocopies",
            "type":"Services"
        }
    ],
    "sg:phone":"+1 770 614 1960",
    "sg:postcode":"30024",
    "sg:province":"GA",
    "sg:tags":[
        "photographic",
        "photographers-portrait",
        "photographers-commercial",
        "rental",
        "darkroom"
    ],
    "wof:name":"Shotz Studio",
    "wof:placetype":"venue"
},
  "geometry": {"coordinates":[-84.066157,34.057964],"type":"Point"}
}