{
  "type": "Feature",
  "properties": {
    "iso:country":"US",
    "sg:address":"1313 Grace Dr",
    "sg:city":"Savannah",
    "sg:classifiers":[
        {
            "category":"Real Estate",
            "subcategory":"Real Estate Agent",
            "type":"Services"
        },
        {
            "category":"Professional",
            "subcategory":"Business Services",
            "type":"Services"
        }
    ],
    "sg:phone":"+1 912 354 0018",
    "sg:postcode":"31406",
    "sg:province":"GA",
    "sg:tags":[
        "inspection"
    ],
    "wof:name":"Hometeam Inspection Service",
    "wof:placetype":"venue"
},
  "geometry": {"coordinates":[-81.10614700000001,31.979074],"type":"Point"}
}