{
  "type": "Feature",
  "properties": {
    "addr:full":"732 Lynn Cir SW Atlanta GA 30311",
    "addr:housenumber":"732",
    "addr:postcode":"30311",
    "addr:street":"Lynn Cir Sw",
    "iso:country":"US",
    "sg:address":"732 Lynn Cir SW",
    "sg:city":"Atlanta",
    "sg:classifiers":[
        {
            "category":"Building & Trades",
            "subcategory":"Landscaping Services",
            "type":"Services"
        }
    ],
    "sg:phone":"+1 404 663 0251",
    "sg:postcode":"30311",
    "sg:province":"GA",
    "sg:tags":[
        "tree"
    ],
    "wof:name":"One Source Stump Cutter",
    "wof:placetype":"venue"
},
  "geometry": {"coordinates":[-84.486126,33.733173],"type":"Point"}
}