{
  "type": "Feature",
  "properties": {
    "addr:full":"334 Travis St Riverdale GA 30296",
    "addr:housenumber":"334",
    "addr:postcode":"30296",
    "addr:street":"Travis St",
    "iso:country":"US",
    "sg:address":"334 Travis St",
    "sg:city":"Riverdale",
    "sg:classifiers":[
        {
            "category":"Retail",
            "subcategory":"Car Wash",
            "type":"Services"
        }
    ],
    "sg:phone":"+1 770 996 6249",
    "sg:postcode":"30296",
    "sg:province":"GA",
    "sg:tags":[
        "carwash"
    ],
    "wof:name":"Sallee Striping/Pressure Wash",
    "wof:placetype":"venue"
},
  "geometry": {"coordinates":[-84.444018,33.540493],"type":"Point"}
}