{
  "type": "Feature",
  "properties": {
    "iso:country":"US",
    "sg:address":"21 Lee St",
    "sg:city":"Jonesboro",
    "sg:classifiers":[
        {
            "category":"Professional",
            "subcategory":"Lawyer & Legal Services",
            "type":"Services"
        }
    ],
    "sg:phone":"+1 770 471 0599",
    "sg:postcode":"30236",
    "sg:province":"GA",
    "wof:name":"Frey Steven M Atty",
    "wof:placetype":"venue"
},
  "geometry": {"coordinates":[-84.357101,33.521801],"type":"Point"}
}