{
  "type": "Feature",
  "properties": {
    "iso:country":"US",
    "sg:address":"5083 Union St",
    "sg:city":"Union City",
    "sg:classifiers":[
        {
            "category":"Professional",
            "subcategory":"Advertising",
            "type":"Services"
        }
    ],
    "sg:phone":"+1 770 964 7877",
    "sg:postcode":"30291",
    "sg:province":"GA",
    "wof:name":"Production Construction Inc",
    "wof:placetype":"venue"
},
  "geometry": {"coordinates":[-84.554073,33.579477],"type":"Point"}
}