{
  "type": "Feature",
  "properties": {
    "addr:full":"1403 Albany St Brunswick GA 31520",
    "addr:housenumber":"1403",
    "addr:postcode":"31520",
    "addr:street":"Albany St",
    "iso:country":"US",
    "sg:address":"1403 Albany St",
    "sg:city":"Brunswick",
    "sg:classifiers":[
        {
            "category":"Organizations",
            "subcategory":"Religious Organization",
            "type":"Services"
        }
    ],
    "sg:phone":"+1 912 264 3985",
    "sg:postcode":"31520",
    "sg:province":"GA",
    "sg:tags":[
        "church"
    ],
    "wof:name":"St Athanasius Episcopal Church",
    "wof:placetype":"venue"
},
  "geometry": {"coordinates":[-81.489621,31.150566],"type":"Point"}
}