{
  "type": "Feature",
  "properties": {
    "addr:full":"5120 Joe Frank Harris Pkwy NW Adairsville GA 30103",
    "addr:housenumber":"5120",
    "addr:postcode":"adairsville;30103",
    "addr:street":"Joe Frank Harris Pkwy Nw",
    "iso:country":"US",
    "sg:address":"5120 Joe Frank Harris Pkwy NW",
    "sg:city":"Adairsville",
    "sg:classifiers":[
        {
            "category":"Shopping",
            "subcategory":"Department Store",
            "type":"Retail Goods"
        }
    ],
    "sg:phone":"+1 770 877 5444",
    "sg:postcode":"30103",
    "sg:province":"GA",
    "sg:tags":[
        "shop"
    ],
    "wof:name":"Fred's Store",
    "wof:placetype":"venue"
},
  "geometry": {"coordinates":[-84.90979400000001,34.343932],"type":"Point"}
}