{
  "type": "Feature",
  "properties": {
    "addr:full":"506 Hamilton Rd Lagrange GA 30241",
    "addr:housenumber":"506",
    "addr:postcode":"30241",
    "addr:street":"Hamilton Rd",
    "iso:country":"US",
    "sg:address":"506 Hamilton Rd",
    "sg:city":"Lagrange",
    "sg:classifiers":[
        {
            "category":"Organizations",
            "subcategory":"Religious Organization",
            "type":"Services"
        }
    ],
    "sg:phone":"+1 706 882 4439",
    "sg:postcode":"30241",
    "sg:province":"GA",
    "sg:tags":[
        "church"
    ],
    "wof:name":"Central Baptist Church",
    "wof:placetype":"venue"
},
  "geometry": {"coordinates":[-85.024355,33.030579],"type":"Point"}
}