{
  "type": "Feature",
  "properties": {
    "addr:full":"919 Center St NE Conyers GA 30012",
    "addr:housenumber":"919",
    "addr:postcode":"30012",
    "addr:street":"Center St Ne",
    "iso:country":"US",
    "sg:address":"919 Center St NE",
    "sg:city":"Conyers",
    "sg:classifiers":[
        {
            "category":"Professional",
            "subcategory":"Secretarial Services",
            "type":"Services"
        }
    ],
    "sg:phone":"+1 770 922 7797",
    "sg:postcode":"30012",
    "sg:province":"GA",
    "sg:tags":[
        "reporting",
        "court"
    ],
    "wof:name":"Court Reporting Svc",
    "wof:placetype":"venue"
},
  "geometry": {"coordinates":[-84.01734,33.667432],"type":"Point"}
}