{
  "type": "Feature",
  "properties": {
    "addr:full":"679 Grady Pl SW Atlanta GA 30310",
    "addr:housenumber":"679",
    "addr:postcode":"30310",
    "addr:street":"Grady Pl Sw",
    "iso:country":"US",
    "sg:address":"679 Grady Pl SW",
    "sg:city":"Atlanta",
    "sg:classifiers":[
        {
            "category":"Arts & Performance",
            "subcategory":"Theater",
            "type":"Entertainment"
        }
    ],
    "sg:phone":"+1 404 758 9859",
    "sg:postcode":"30310",
    "sg:province":"GA",
    "sg:tags":[
        "group"
    ],
    "wof:name":"Tropical Steel Vibes",
    "wof:placetype":"venue"
},
  "geometry": {"coordinates":[-84.42665599999999,33.737875],"type":"Point"}
}