{
  "type": "Feature",
  "properties": {
    "addr:full":"7260 Amberleigh Way Duluth GA 30097",
    "addr:housenumber":"7260",
    "addr:postcode":"30097",
    "addr:street":"Amberleigh Way",
    "iso:country":"US",
    "sg:address":"7260 Amberleigh Way",
    "sg:city":"Duluth",
    "sg:classifiers":[
        {
            "category":"Professional",
            "subcategory":"Business Services",
            "type":"Services"
        }
    ],
    "sg:phone":"+1 770 622 4745",
    "sg:postcode":"30097",
    "sg:province":"GA",
    "wof:name":"Accessible Solutions Inc",
    "wof:placetype":"venue"
},
  "geometry": {"coordinates":[-84.147642,34.048512],"type":"Point"}
}