{
  "type": "Feature",
  "properties": {
    "addr:full":"134 Spalding St Griffin GA 30223",
    "addr:housenumber":"134",
    "addr:postcode":"30223",
    "addr:street":"Spalding St",
    "iso:country":"US",
    "sg:address":"134 Spalding St",
    "sg:city":"Griffin",
    "sg:classifiers":[
        {
            "category":"Banks & Credit Unions",
            "subcategory":"Bank",
            "type":"Services"
        }
    ],
    "sg:phone":"+1 770 227 2155",
    "sg:postcode":"30223",
    "sg:province":"GA",
    "sg:tags":[
        "commercial",
        "financing",
        "consumer"
    ],
    "wof:name":"Citi Financial",
    "wof:placetype":"venue"
},
  "geometry": {"coordinates":[-84.24573100000001,33.247253],"type":"Point"}
}