{
  "type": "Feature",
  "properties": {
    "iso:country":"US",
    "sg:address":"253 Heron Lake Ct",
    "sg:city":"Lawrenceville",
    "sg:classifiers":[
        {
            "category":"Home & Garden",
            "subcategory":"Home Furnishings",
            "type":"Retail Goods"
        }
    ],
    "sg:phone":"+1 866 839 4770",
    "sg:postcode":"30043",
    "sg:province":"GA",
    "sg:tags":[
        "draperies",
        "vertical",
        "blinds-venetian",
        "window",
        "treatment",
        "curtain"
    ],
    "wof:name":"Budget Blinds of West Lawrenceville",
    "wof:placetype":"venue"
},
  "geometry": {"coordinates":[-84.019899,34.032376],"type":"Point"}
}