{
  "type": "Feature",
  "properties": {
    "iso:country":"US",
    "sg:address":"100 S Houston Lake Rd",
    "sg:city":"Centerville",
    "sg:classifiers":[
        {
            "category":"Recreation",
            "subcategory":"Amusement Park",
            "type":"Entertainment"
        }
    ],
    "sg:phone":"+1 478 953 4382",
    "sg:postcode":"31028",
    "sg:province":"GA",
    "wof:name":"Dmz Gift Shop",
    "wof:placetype":"venue"
},
  "geometry": {"coordinates":[-83.68220700000001,32.617756],"type":"Point"}
}