{
  "type": "Feature",
  "properties": {
    "addr:full":"1800 Millside Ter Dacula GA 30019",
    "addr:housenumber":"1800",
    "addr:postcode":"ga 30019",
    "addr:street":"Millside Ter",
    "iso:country":"US",
    "sg:address":"1800 Millside Ter",
    "sg:city":"Dacula",
    "sg:classifiers":[
        {
            "category":"Professional",
            "type":"Services"
        }
    ],
    "sg:phone":"+1 770 831 8790",
    "sg:postcode":"30019",
    "sg:province":"GA",
    "wof:name":"Tender Ones Therapy Services",
    "wof:placetype":"venue"
},
  "geometry": {"coordinates":[-83.914295,34.056115],"type":"Point"}
}