{
  "type": "Feature",
  "properties": {
    "iso:country":"US",
    "sg:address":"1723 Zemory Dr",
    "sg:city":"Tucker",
    "sg:classifiers":[
        {
            "category":"Shopping",
            "type":"Retail Goods"
        }
    ],
    "sg:phone":"+1 678 595 2798",
    "sg:postcode":"30084",
    "sg:province":"GA",
    "sg:tags":[
        "merchandise"
    ],
    "wof:name":"Noahs Art Pet Products",
    "wof:placetype":"venue"
},
  "geometry": {"coordinates":[-84.24209999999999,33.829705],"type":"Point"}
}