{
  "type": "Feature",
  "properties": {
    "addr:full":"2223 Lawrenceville Hwy Decatur GA 30033",
    "addr:housenumber":"2223",
    "addr:postcode":"30033",
    "addr:street":"Lawrenceville Hwy",
    "iso:country":"US",
    "sg:address":"2223 Lawrenceville Hwy",
    "sg:city":"Decatur",
    "sg:classifiers":[
        {
            "category":"Fast Food",
            "type":"Food & Drink"
        }
    ],
    "sg:phone":"+1 404 633 7579",
    "sg:postcode":"30033",
    "sg:province":"GA",
    "sg:website":"www.krystal.com",
    "wof:name":"Krystal Company the",
    "wof:placetype":"venue"
},
  "geometry": {"coordinates":[-84.27130099999999,33.8125],"type":"Point"}
}