{
  "type": "Feature",
  "properties": {
    "addr:full":"788 Old Hwy 100 Tallapoosa GA 30176",
    "addr:housenumber":"788",
    "addr:postcode":"30176",
    "addr:street":"Old Hwy 100",
    "iso:country":"US",
    "sg:address":"788 Old Hwy 100",
    "sg:city":"Tallapoosa",
    "sg:classifiers":[
        {
            "category":"Travel",
            "subcategory":"Hotels & Motels",
            "type":"Entertainment"
        }
    ],
    "sg:phone":"+1 770 574 5575",
    "sg:postcode":"30176",
    "sg:province":"GA",
    "sg:tags":[
        "operation"
    ],
    "wof:name":"Comfort Inn",
    "wof:placetype":"venue"
},
  "geometry": {"coordinates":[-85.28751,33.65652],"type":"Point"}
}