{
  "type": "Feature",
  "properties": {
    "addr:full":"144 River Oaks Dr Woodstock GA 30188",
    "addr:housenumber":"144",
    "addr:postcode":"30188",
    "addr:street":"River Oaks Dr",
    "iso:country":"US",
    "sg:address":"144 River Oaks Dr",
    "sg:city":"Woodstock",
    "sg:classifiers":[
        {
            "category":"Freight",
            "type":"Transportation"
        }
    ],
    "sg:phone":"+1 770 517 9081",
    "sg:postcode":"30188",
    "sg:province":"GA",
    "sg:tags":[
        "courier"
    ],
    "wof:name":"Joe Liu Inc",
    "wof:placetype":"venue"
},
  "geometry": {"coordinates":[-84.46421100000001,34.108354],"type":"Point"}
}