{
  "type": "Feature",
  "properties": {
    "iso:country":"US",
    "sg:address":"4422 Fincher Rd",
    "sg:city":"Canton",
    "sg:classifiers":[
        {
            "category":"Building & Trades",
            "subcategory":"Construction",
            "type":"Services"
        }
    ],
    "sg:phone":"+1 770 345 4065",
    "sg:postcode":"30114",
    "sg:province":"GA",
    "sg:tags":[
        "house"
    ],
    "wof:name":"Tsw Custom Built Homes Inc",
    "wof:placetype":"venue"
},
  "geometry": {"coordinates":[-84.584551,34.26944],"type":"Point"}
}