{
  "type": "Feature",
  "properties": {
    "iso:country":"US",
    "sg:address":"5445 Columbia Rd",
    "sg:city":"Grovetown",
    "sg:classifiers":[
        {
            "category":"Recreation",
            "type":"Entertainment"
        }
    ],
    "sg:phone":"+1 706 868 3458",
    "sg:postcode":"30813",
    "sg:province":"GA",
    "sg:tags":[
        "parks"
    ],
    "wof:name":"Patriots Park",
    "wof:placetype":"venue"
},
  "geometry": {"coordinates":[-82.21939399999999,33.512591],"type":"Point"}
}