{
  "type": "Feature",
  "properties": {
    "addr:full":"2456 Golden Camp Rd Augusta GA 30906",
    "addr:housenumber":"2456",
    "addr:postcode":"30906",
    "addr:street":"Golden Camp Rd",
    "iso:country":"US",
    "sg:address":"2456 Golden Camp Rd",
    "sg:city":"Augusta",
    "sg:classifiers":[
        {
            "category":"Government",
            "subcategory":"Office",
            "type":"Public Place"
        }
    ],
    "sg:phone":"+1 706 771 2654",
    "sg:postcode":"30906",
    "sg:province":"GA",
    "sg:tags":[
        "village"
    ],
    "wof:name":"Belle Terrace Community Ctr",
    "wof:placetype":"venue"
},
  "geometry": {"coordinates":[-82.050363,33.431171],"type":"Point"}
}