{
  "type": "Feature",
  "properties": {
    "addr:full":"116 William Way Juliette GA 31023",
    "addr:housenumber":"116",
    "addr:postcode":"31023",
    "addr:street":"William Way Juliette",
    "iso:country":"US",
    "sg:address":"116 William Way",
    "sg:city":"Juliette",
    "sg:classifiers":[
        {
            "category":"Professional",
            "type":"Services"
        }
    ],
    "sg:phone":"+1 877 587 6407",
    "sg:postcode":"31023",
    "sg:province":"GA",
    "wof:name":"Piedmont Power Service",
    "wof:placetype":"venue"
},
  "geometry": {"coordinates":[-83.147795,32.184165],"type":"Point"}
}