{
  "type": "Feature",
  "properties": {
    "addr:full":"182 Bedsole Rd Eastman GA 31023",
    "addr:housenumber":"182",
    "addr:postcode":"31023",
    "addr:street":"Bedsole Rd",
    "iso:country":"US",
    "sg:address":"182 Bedsole Rd",
    "sg:city":"Eastman",
    "sg:classifiers":[
        {
            "category":"Banks & Credit Unions",
            "subcategory":"Bank",
            "type":"Services"
        }
    ],
    "sg:phone":"+1 478 374 1004",
    "sg:postcode":"31023",
    "sg:province":"GA",
    "sg:tags":[
        "broker",
        "mortgage"
    ],
    "wof:name":"Champion Home Mortgage Inc",
    "wof:placetype":"venue"
},
  "geometry": {"coordinates":[-83.13896099999999,32.199924],"type":"Point"}
}