{
  "type": "Feature",
  "properties": {
    "iso:country":"US",
    "sg:address":"105 High Point Walk NE",
    "sg:city":"Atlanta",
    "sg:classifiers":[
        {
            "category":"Real Estate",
            "subcategory":"Real Estate Agent",
            "type":"Services"
        }
    ],
    "sg:phone":"+1 404 303 7811",
    "sg:postcode":"30342",
    "sg:province":"GA",
    "wof:name":"LBP Ind Inc",
    "wof:placetype":"venue"
},
  "geometry": {"coordinates":[-84.367104,33.891511],"type":"Point"}
}