{
  "type": "Feature",
  "properties": {
    "iso:country":"US",
    "sg:address":"330 Toccoa Pl",
    "sg:city":"Jonesboro",
    "sg:classifiers":[
        {
            "category":"Manufacturing",
            "subcategory":"Apparel",
            "type":"Manufacturing & Wholesale Goods"
        },
        {
            "category":"Shopping",
            "subcategory":"Clothing, Apparel, & Fashions",
            "type":"Retail Goods"
        }
    ],
    "sg:phone":"+1 770 506 8391",
    "sg:postcode":"30236",
    "sg:province":"GA",
    "sg:tags":[
        "manufacture",
        "shop",
        "menswear",
        "coat",
        "bridal",
        "dress"
    ],
    "wof:name":"Gloria's Custom Designs",
    "wof:placetype":"venue"
},
  "geometry": {"coordinates":[-84.27104300000001,33.515565],"type":"Point"}
}