{
  "type": "Feature",
  "properties": {
    "iso:country":"US",
    "sg:address":"187 Cole Cir",
    "sg:city":"Bethlehem",
    "sg:classifiers":[
        {
            "category":"Building & Trades",
            "subcategory":"Plumbing",
            "type":"Services"
        }
    ],
    "sg:phone":"+1 770 868 1131",
    "sg:postcode":"30620",
    "sg:province":"GA",
    "sg:tags":[
        "contractor"
    ],
    "wof:name":"America Refrigeration Georgia",
    "wof:placetype":"venue"
},
  "geometry": {"coordinates":[-83.763976,33.93503],"type":"Point"}
}