{
  "type": "Feature",
  "properties": {
    "iso:country":"US",
    "sg:address":"5328 Innisbrook Ln",
    "sg:city":"Gainesville",
    "sg:classifiers":[
        {
            "category":"Shopping",
            "type":"Retail Goods"
        }
    ],
    "sg:phone":"+1 770 983 1982",
    "sg:postcode":"30506",
    "sg:province":"GA",
    "sg:tags":[
        "merchandise"
    ],
    "wof:name":"Lester Lajuania",
    "wof:placetype":"venue"
},
  "geometry": {"coordinates":[-83.843548,34.444145],"type":"Point"}
}