{
  "type": "Feature",
  "properties": {
    "iso:country":"US",
    "sg:address":"11 Westminster Close Dr NW",
    "sg:city":"Atlanta",
    "sg:classifiers":[
        {
            "category":"Organizations",
            "subcategory":"Religious Organization",
            "type":"Services"
        }
    ],
    "sg:phone":"+1 404 351 4396",
    "sg:postcode":"30327",
    "sg:province":"GA",
    "sg:tags":[
        "clergy"
    ],
    "wof:name":"L H Bishop",
    "wof:placetype":"venue"
},
  "geometry": {"coordinates":[-84.424942,33.83886],"type":"Point"}
}