{
  "type": "Feature",
  "properties": {
    "iso:country":"US",
    "sg:address":"79 US Hwy 319 N",
    "sg:city":"Tifton",
    "sg:classifiers":[
        {
            "category":"Home & Garden",
            "subcategory":"Mobile Homes",
            "type":"Retail Goods"
        }
    ],
    "sg:phone":"+1 229 386 8419",
    "sg:postcode":"31794",
    "sg:province":"GA",
    "wof:name":"Sheppard's Homes",
    "wof:placetype":"venue"
},
  "geometry": {"coordinates":[-83.484506,31.446832],"type":"Point"}
}