{
  "type": "Feature",
  "properties": {
    "iso:country":"US",
    "sg:address":"3804 Martin Luther King J",
    "sg:city":"Atlanta",
    "sg:classifiers":[
        {
            "category":"Real Estate",
            "subcategory":"Real Estate Operator",
            "type":"Services"
        }
    ],
    "sg:phone":"+1 404 696 4481",
    "sg:postcode":"30331",
    "sg:province":"GA",
    "sg:tags":[
        "apartment"
    ],
    "wof:name":"Windsor Square Townhouses",
    "wof:placetype":"venue"
},
  "geometry": {"coordinates":[-84.512929,33.767906],"type":"Point"}
}