{
  "type": "Feature",
  "properties": {
    "addr:full":"1975 Highpoint Rd Snellville GA 30078",
    "addr:housenumber":"1975",
    "addr:postcode":"30078",
    "addr:street":"Highpoint Rd",
    "iso:country":"US",
    "sg:address":"1975 Highpoint Rd",
    "sg:city":"Snellville",
    "sg:classifiers":[
        {
            "category":"Shopping",
            "subcategory":"Hobbies, Toys, & Games",
            "type":"Retail Goods"
        }
    ],
    "sg:phone":"+1 770 982 0509",
    "sg:postcode":"30078",
    "sg:province":"GA",
    "wof:name":"Ashley Enterprises",
    "wof:placetype":"venue"
},
  "geometry": {"coordinates":[-84.046875,33.853606],"type":"Point"}
}