{
  "type": "Feature",
  "properties": {
    "iso:country":"US",
    "sg:address":"1244 Buford Hwy",
    "sg:city":"Cumming",
    "sg:classifiers":[
        {
            "category":"Retail",
            "subcategory":"Auto Repair",
            "type":"Services"
        }
    ],
    "sg:phone":"+1 678 947 5514",
    "sg:postcode":"30041",
    "sg:province":"GA",
    "sg:tags":[
        "automotive"
    ],
    "wof:name":"Express Emissions",
    "wof:placetype":"venue"
},
  "geometry": {"coordinates":[-84.125905,34.172014],"type":"Point"}
}