{
  "type": "Feature",
  "properties": {
    "addr:full":"202 Magnolia Pl Guyton GA 31312",
    "addr:housenumber":"202",
    "addr:postcode":"31312",
    "addr:street":"Magnolia Pl",
    "iso:country":"US",
    "sg:address":"202 Magnolia Pl",
    "sg:city":"Guyton",
    "sg:classifiers":[
        {
            "category":"Farming",
            "subcategory":"Farm",
            "type":"Manufacturing & Wholesale Goods"
        }
    ],
    "sg:phone":"+1 912 772 3345",
    "sg:postcode":"31312",
    "sg:province":"GA",
    "sg:tags":[
        "crop",
        "general"
    ],
    "wof:name":"Woodlawn Plantation LP",
    "wof:placetype":"venue"
},
  "geometry": {"coordinates":[-81.35856200000001,32.342181],"type":"Point"}
}