{
  "type": "Feature",
  "properties": {
    "addr:full":"3981 McGill Dr Decatur GA 30034",
    "addr:housenumber":"3981",
    "addr:postcode":"30034",
    "addr:street":"Mcgill Dr",
    "iso:country":"US",
    "sg:address":"3981 McGill Dr",
    "sg:city":"Decatur",
    "sg:classifiers":[
        {
            "category":"Education",
            "subcategory":"School",
            "type":"Public Place"
        }
    ],
    "sg:phone":"+1 678 676 9202",
    "sg:postcode":"30034",
    "sg:province":"GA",
    "sg:tags":[
        "high",
        "middle",
        "elementary"
    ],
    "wof:name":"Dekalb County School District",
    "wof:placetype":"venue"
},
  "geometry": {"coordinates":[-84.227273,33.667233],"type":"Point"}
}