{
  "type": "Feature",
  "properties": {
    "iso:country":"US",
    "sg:address":"1025 Winding Bridge Way",
    "sg:city":"Duluth",
    "sg:classifiers":[
        {
            "category":"Building & Trades",
            "subcategory":"Construction",
            "type":"Services"
        }
    ],
    "sg:phone":"+1 770 294 7800",
    "sg:postcode":"30097",
    "sg:province":"GA",
    "sg:tags":[
        "general",
        "contractor"
    ],
    "wof:name":"D & M Toneff",
    "wof:placetype":"venue"
},
  "geometry": {"coordinates":[-84.16702100000001,34.033966],"type":"Point"}
}