{
  "type": "Feature",
  "properties": {
    "iso:country":"US",
    "sg:address":"203 W Shotwell St",
    "sg:city":"Bainbridge",
    "sg:classifiers":[
        {
            "category":"Communications",
            "subcategory":"Radio Station",
            "type":"Services"
        }
    ],
    "sg:phone":"+1 229 246 1650",
    "sg:postcode":"39819",
    "sg:province":"GA",
    "sg:tags":[
        "company",
        "broadcasting"
    ],
    "wof:name":"WMGR AM 930",
    "wof:placetype":"venue"
},
  "geometry": {"coordinates":[-84.578102,30.903977],"type":"Point"}
}