{
  "type": "Feature",
  "properties": {
    "iso:country":"US",
    "sg:address":"1176 Grimes Bridge Rd",
    "sg:city":"Roswell",
    "sg:classifiers":[
        {
            "category":"Professional",
            "subcategory":"Management & Consulting",
            "type":"Services"
        }
    ],
    "sg:phone":"+1 770 642 2305",
    "sg:postcode":"30075",
    "sg:province":"GA",
    "wof:name":"Fleming Wealth Management LLC",
    "wof:placetype":"venue"
},
  "geometry": {"coordinates":[-84.34199099999999,34.031202],"type":"Point"}
}