{
  "type": "Feature",
  "properties": {
    "iso:country":"US",
    "sg:address":"1807 Beaver Ruin Rd",
    "sg:city":"Norcross",
    "sg:classifiers":[
        {
            "category":"Professional",
            "type":"Services"
        }
    ],
    "sg:phone":"+1 770 849 0390",
    "sg:postcode":"30071",
    "sg:province":"GA",
    "wof:name":"Quality Fuel Inc",
    "wof:placetype":"venue"
},
  "geometry": {"coordinates":[-84.163128,33.938347],"type":"Point"}
}