{
  "type": "Feature",
  "properties": {
    "iso:country":"US",
    "sg:address":"11250 State Bridge Rd",
    "sg:city":"Alpharetta",
    "sg:classifiers":[
        {
            "category":"Education",
            "subcategory":"School",
            "type":"Public Place"
        }
    ],
    "sg:phone":"+1 770 754 4796",
    "sg:postcode":"30097",
    "sg:province":"GA",
    "sg:website":"www.goddardpreschool.com",
    "wof:name":"Goddard School",
    "wof:placetype":"venue"
},
  "geometry": {"coordinates":[-84.180285,34.008304],"type":"Point"}
}