{
  "type": "Feature",
  "properties": {
    "addr:full":"650 Murphy Ave SW Atlanta GA 30310",
    "addr:housenumber":"650",
    "addr:postcode":"30310",
    "addr:street":"Murphy Ave Sw",
    "iso:country":"US",
    "sg:address":"650 Murphy Ave SW",
    "sg:city":"Atlanta",
    "sg:classifiers":[
        {
            "category":"Wholesale",
            "subcategory":"Groceries",
            "type":"Manufacturing & Wholesale Goods"
        }
    ],
    "sg:phone":"+1 404 753 8777",
    "sg:postcode":"30310",
    "sg:province":"GA",
    "sg:tags":[
        "water",
        "distributor"
    ],
    "wof:name":"Carolina Mountain Water",
    "wof:placetype":"venue"
},
  "geometry": {"coordinates":[-84.412318,33.735209],"type":"Point"}
}