{
  "type": "Feature",
  "properties": {
    "iso:country":"US",
    "sg:address":"6498 Tara Blvd",
    "sg:city":"Jonesboro",
    "sg:classifiers":[
        {
            "category":"Insurance",
            "subcategory":"Insurance Agent",
            "type":"Services"
        }
    ],
    "sg:phone":"+1 770 968 1008",
    "sg:postcode":"30236",
    "sg:province":"GA",
    "wof:name":"Primerica Financial Svc",
    "wof:placetype":"venue"
},
  "geometry": {"coordinates":[-84.374045,33.579022],"type":"Point"}
}