{
  "type": "Feature",
  "properties": {
    "iso:country":"US",
    "sg:address":"1295 Powder Springs Rd SW",
    "sg:city":"Marietta",
    "sg:classifiers":[
        {
            "category":"Shopping",
            "subcategory":"Pharmacy",
            "type":"Retail Goods"
        }
    ],
    "sg:phone":"+1 770 919 1281",
    "sg:postcode":"30064",
    "sg:province":"GA",
    "sg:tags":[
        "drugstore"
    ],
    "sg:website":"www.cvs.com",
    "wof:name":"Cvs Pharmacy",
    "wof:placetype":"venue"
},
  "geometry": {"coordinates":[-84.591458,33.914337],"type":"Point"}
}