{
  "type": "Feature",
  "properties": {
    "addr:full":"1065 Buckhead Xing Woodstock GA 30189",
    "addr:housenumber":"1065",
    "addr:postcode":"30189",
    "addr:street":"Buckhead Xing",
    "iso:country":"US",
    "sg:address":"1065 Buckhead Xing",
    "sg:city":"Woodstock",
    "sg:classifiers":[
        {
            "category":"Restaurant",
            "type":"Food & Drink"
        }
    ],
    "sg:menulink":"http://www.allmenus.com/ga/woodstock/205814-la-parilla/menu/",
    "sg:phone":"+1 770 928 3606",
    "sg:postcode":"30189",
    "sg:province":"GA",
    "sg:tags":[
        "mexican"
    ],
    "wof:name":"La Parilla",
    "wof:placetype":"venue"
},
  "geometry": {"coordinates":[-84.540475,34.105265],"type":"Point"}
}