{
  "type": "Feature",
  "properties": {
    "iso:country":"US",
    "sg:address":"2252 Boulevard Granada SW",
    "sg:city":"Atlanta",
    "sg:classifiers":[
        {
            "category":"Professional",
            "subcategory":"Management & Consulting",
            "type":"Services"
        }
    ],
    "sg:phone":"+1 404 752 9080",
    "sg:postcode":"30311",
    "sg:province":"GA",
    "sg:tags":[
        "consultant",
        "educational"
    ],
    "sg:website":"http://www.hookitupconsulting.net",
    "wof:name":"Hookitup Conssulting & Education",
    "wof:placetype":"venue"
},
  "geometry": {"coordinates":[-84.46274699999999,33.718852],"type":"Point"}
}