{
  "type": "Feature",
  "properties": {
    "iso:country":"US",
    "sg:address":"1405 9th Ave",
    "sg:city":"Albany",
    "sg:classifiers":[
        {
            "category":"Building & Trades",
            "subcategory":"Construction",
            "type":"Services"
        }
    ],
    "sg:phone":"+1 229 881 0812",
    "sg:postcode":"31707",
    "sg:province":"GA",
    "sg:tags":[
        "heavy"
    ],
    "wof:name":"Britan Land Clearing",
    "wof:placetype":"venue"
},
  "geometry": {"coordinates":[-84.184314,31.598271],"type":"Point"}
}