{
  "type": "Feature",
  "properties": {
    "addr:full":"1298 Central Ave East Point GA 30344",
    "addr:housenumber":"1298",
    "addr:postcode":"30344",
    "addr:street":"Central Ave",
    "iso:country":"US",
    "sg:address":"1298 Central Ave",
    "sg:city":"East Point",
    "sg:classifiers":[
        {
            "category":"Building & Trades",
            "subcategory":"Locksmith",
            "type":"Services"
        }
    ],
    "sg:phone":"+1 877 645 7153",
    "sg:postcode":"30344",
    "sg:province":"GA",
    "sg:tags":[
        "key"
    ],
    "wof:name":"A 1 Emergency Locksmith",
    "wof:placetype":"venue"
},
  "geometry": {"coordinates":[-84.431253,33.66768],"type":"Point"}
}