{
  "type": "Feature",
  "properties": {
    "addr:full":"202 E 3rd Ave Rome GA 30161",
    "addr:housenumber":"202",
    "addr:postcode":"ga 30161",
    "addr:street":"E 3Rd Ave",
    "iso:country":"US",
    "sg:address":"202 E 3rd Ave",
    "sg:city":"Rome",
    "sg:classifiers":[
        {
            "category":"Social Services",
            "subcategory":"Child Care",
            "type":"Services"
        }
    ],
    "sg:phone":"+1 706 291 9331",
    "sg:postcode":"30161",
    "sg:province":"GA",
    "sg:tags":[
        "kindergarten",
        "academic",
        "school"
    ],
    "wof:name":"First United Methodist Church",
    "wof:placetype":"venue"
},
  "geometry": {"coordinates":[-85.170782,34.251529],"type":"Point"}
}