{
  "type": "Feature",
  "properties": {
    "addr:full":"830 Starlight Cir NE Atlanta GA 30342",
    "addr:housenumber":"830",
    "addr:postcode":"30342",
    "addr:street":"Starlight Cir Ne",
    "iso:country":"US",
    "sg:address":"830 Starlight Cir NE",
    "sg:city":"Atlanta",
    "sg:classifiers":[
        {
            "category":"Professional",
            "type":"Services"
        }
    ],
    "sg:phone":"+1 404 256 9869",
    "sg:postcode":"30342",
    "sg:province":"GA",
    "wof:name":"Dowis & Company Inc",
    "wof:placetype":"venue"
},
  "geometry": {"coordinates":[-84.36024999999999,33.880467],"type":"Point"}
}