{
  "type": "Feature",
  "properties": {
    "addr:full":"1455 Danbury Dr NW Norcross GA 30093",
    "addr:housenumber":"1455",
    "addr:postcode":"30093",
    "addr:street":"Danbury Dr Nw",
    "iso:country":"US",
    "sg:address":"1455 Danbury Dr NW",
    "sg:city":"Norcross",
    "sg:classifiers":[
        {
            "category":"Local Transit",
            "type":"Transportation"
        }
    ],
    "sg:phone":"+1 770 368 9846",
    "sg:postcode":"30093",
    "sg:province":"GA",
    "sg:tags":[
        "passenger"
    ],
    "wof:name":"Courtneys Limousine Service",
    "wof:placetype":"venue"
},
  "geometry": {"coordinates":[-84.20697800000001,33.899514],"type":"Point"}
}