{
  "type": "Feature",
  "properties": {
    "iso:country":"US",
    "sg:address":"221 8th St",
    "sg:city":"Augusta",
    "sg:classifiers":[
        {
            "category":"Shopping",
            "type":"Retail Goods"
        }
    ],
    "sg:phone":"+1 706 722 6212",
    "sg:postcode":"30901",
    "sg:province":"GA",
    "sg:tags":[
        "merchandise"
    ],
    "wof:name":"Mapout Inc",
    "wof:placetype":"venue"
},
  "geometry": {"coordinates":[-81.965834,33.474516],"type":"Point"}
}