{
  "type": "Feature",
  "properties": {
    "iso:country":"US",
    "sg:address":"3042 Farmington Dr NW",
    "sg:city":"Atlanta",
    "sg:classifiers":[
        {
            "category":"Professional",
            "subcategory":"Accounting & Tax Preparation",
            "type":"Services"
        }
    ],
    "sg:phone":"+1 770 434 9460",
    "sg:postcode":"30339",
    "sg:province":"GA",
    "sg:tags":[
        "accountant"
    ],
    "wof:name":"Adams Hugh G CPA",
    "wof:placetype":"venue"
},
  "geometry": {"coordinates":[-84.464837,33.850318],"type":"Point"}
}