{
  "type": "Feature",
  "properties": {
    "addr:full":"3 Latimer Ln NE Kennesaw GA 30144",
    "addr:housenumber":"3",
    "addr:postcode":"30144",
    "addr:street":"Latimer Ln Ne",
    "iso:country":"US",
    "sg:address":"3 Latimer Ln NE",
    "sg:city":"Kennesaw",
    "sg:classifiers":[
        {
            "category":"Building & Trades",
            "subcategory":"Locksmith",
            "type":"Services"
        }
    ],
    "sg:phone":"+1 877 834 6690",
    "sg:postcode":"30144",
    "sg:province":"GA",
    "sg:tags":[
        "key"
    ],
    "wof:name":"24 Hour 1 Emergency Locksmith",
    "wof:placetype":"venue"
},
  "geometry": {"coordinates":[-84.55091,34.066679],"type":"Point"}
}