{
  "type": "Feature",
  "properties": {
    "iso:country":"US",
    "sg:address":"250 Saratoga Ct",
    "sg:city":"Covington",
    "sg:classifiers":[
        {
            "category":"Organizations",
            "subcategory":"Religious Organization",
            "type":"Services"
        }
    ],
    "sg:phone":"+1 770 784 5655",
    "sg:postcode":"30016",
    "sg:province":"GA",
    "wof:name":"Time 2 Shine Inc",
    "wof:placetype":"venue"
},
  "geometry": {"coordinates":[-83.99930999999999,33.509347],"type":"Point"}
}