{
  "type": "Feature",
  "properties": {
    "addr:full":"4564 Doral Dr SW Atlanta GA 30331",
    "addr:housenumber":"4564",
    "addr:postcode":"30331",
    "addr:street":"Doral Dr Sw",
    "iso:country":"US",
    "sg:address":"4564 Doral Dr SW",
    "sg:city":"Atlanta",
    "sg:classifiers":[
        {
            "category":"Place Of Worship",
            "subcategory":"Church",
            "type":"Public Place"
        },
        {
            "category":"Place Of Worship",
            "type":"Public Place"
        },
        {
            "category":"Organizations",
            "subcategory":"Religious Organization",
            "type":"Services"
        }
    ],
    "sg:phone":"+1 404 346 9911",
    "sg:postcode":"30331",
    "sg:province":"GA",
    "sg:tags":[
        "churches-non-denominational"
    ],
    "wof:name":"Jada International Ministries Inc",
    "wof:placetype":"venue"
},
  "geometry": {"coordinates":[-84.537637,33.688488],"type":"Point"}
}