{
  "type": "Feature",
  "properties": {
    "iso:country":"US",
    "sg:address":"4567 Winters Chapel Road",
    "sg:city":"Atlanta",
    "sg:classifiers":[
        {
            "category":"Home & Garden",
            "subcategory":"Furniture",
            "type":"Retail Goods"
        }
    ],
    "sg:phone":"+1 770 449 9770",
    "sg:postcode":"30360",
    "sg:province":"GA",
    "sg:tags":[
        "store"
    ],
    "sg:website":"www.furniturewithasoul.com",
    "wof:name":"Nadeau Imports",
    "wof:placetype":"venue"
},
  "geometry": {"coordinates":[-84.264742,33.929983],"type":"Point"}
}