{
  "type": "Feature",
  "properties": {
    "iso:country":"US",
    "sg:address":"8641 Dorris Rd Ste 220B",
    "sg:city":"Douglasville",
    "sg:classifiers":[
        {
            "category":"Professional",
            "subcategory":"Lawyer & Legal Services",
            "type":"Services"
        }
    ],
    "sg:phone":"+1 770 920 2124",
    "sg:postcode":"30134",
    "sg:province":"GA",
    "sg:tags":[
        "attorney",
        "practice"
    ],
    "wof:name":"Hilton Bryan P Attorney At Law",
    "wof:placetype":"venue"
},
  "geometry": {"coordinates":[-84.731796,33.746101],"type":"Point"}
}