{
  "type": "Feature",
  "properties": {
    "addr:full":"186 North St Canton GA 30114",
    "addr:housenumber":"186",
    "addr:postcode":"30114",
    "addr:street":"North St",
    "iso:country":"US",
    "sg:address":"186 North St",
    "sg:city":"Canton",
    "sg:classifiers":[
        {
            "category":"Organizations",
            "subcategory":"Religious Organization",
            "type":"Services"
        }
    ],
    "sg:phone":"+1 678 493 8920",
    "sg:postcode":"30114",
    "sg:province":"GA",
    "wof:name":"Liberty.Hill Umc Inc",
    "wof:placetype":"venue"
},
  "geometry": {"coordinates":[-84.49005,34.237143],"type":"Point"}
}