{
  "type": "Feature",
  "properties": {
    "addr:full":"5536 Colbert Trl Norcross GA 30092",
    "addr:housenumber":"5536",
    "addr:postcode":"30092",
    "addr:street":"Colbert Trl",
    "iso:country":"US",
    "sg:address":"5536 Colbert Trl",
    "sg:city":"Norcross",
    "sg:classifiers":[
        {
            "category":"Professional",
            "subcategory":"Computer Services",
            "type":"Services"
        }
    ],
    "sg:phone":"+1 770 441 2191",
    "sg:postcode":"30092",
    "sg:province":"GA",
    "sg:tags":[
        "design",
        "integrated",
        "system"
    ],
    "wof:name":"Computer Synthesis",
    "wof:placetype":"venue"
},
  "geometry": {"coordinates":[-84.23051700000001,33.981036],"type":"Point"}
}