{
  "type": "Feature",
  "properties": {
    "addr:full":"555 Lakeshore Dr Fayetteville GA 30214",
    "addr:housenumber":"555",
    "addr:postcode":"30214",
    "addr:street":"Lakeshore Dr",
    "iso:country":"US",
    "sg:address":"555 Lakeshore Dr",
    "sg:city":"Fayetteville",
    "sg:classifiers":[
        {
            "category":"Wholesale",
            "subcategory":"Machinery & Supplies",
            "type":"Manufacturing & Wholesale Goods"
        }
    ],
    "sg:phone":"+1 770 719 3883",
    "sg:postcode":"30214",
    "sg:province":"GA",
    "sg:tags":[
        "tubing",
        "hose",
        "plastic"
    ],
    "wof:name":"Hagood Hose & Hydraulics",
    "wof:placetype":"venue"
},
  "geometry": {"coordinates":[-84.46329299999999,33.461816],"type":"Point"}
}