{
  "type": "Feature",
  "properties": {
    "addr:full":"37 Adair Hollow Rd NW Adairsville GA 30103",
    "addr:housenumber":"37",
    "addr:postcode":"adairsville;30103",
    "addr:street":"Adair Hollow Rd Nw",
    "iso:country":"US",
    "sg:address":"37 Adair Hollow Rd NW",
    "sg:city":"Adairsville",
    "sg:classifiers":[
        {
            "category":"Organizations",
            "subcategory":"Religious Organization",
            "type":"Services"
        }
    ],
    "sg:phone":"+1 770 773 7223",
    "sg:postcode":"30103",
    "sg:province":"GA",
    "wof:name":"Robert Chancey Rev",
    "wof:placetype":"venue"
},
  "geometry": {"coordinates":[-84.947592,34.371877],"type":"Point"}
}