{
  "type": "Feature",
  "properties": {
    "iso:country":"US",
    "sg:address":"112 Krog St NE",
    "sg:city":"Atlanta",
    "sg:classifiers":[
        {
            "category":"Professional",
            "subcategory":"Lawyer & Legal Services",
            "type":"Services"
        }
    ],
    "sg:phone":"+1 404 931 3263",
    "sg:postcode":"30307",
    "sg:province":"GA",
    "wof:name":"M Bryan Enterprises",
    "wof:placetype":"venue"
},
  "geometry": {"coordinates":[-84.364403,33.756018],"type":"Point"}
}