{
  "type": "Feature",
  "properties": {
    "addr:full":"101 W Ponce de Leon Ave Decatur GA 30030",
    "addr:housenumber":"101",
    "addr:postcode":"30030",
    "addr:street":"W Ponce De Leon Ave",
    "iso:country":"US",
    "sg:address":"101 W Ponce de Leon Ave",
    "sg:city":"Decatur",
    "sg:classifiers":[
        {
            "category":"Professional",
            "subcategory":"Research",
            "type":"Services"
        }
    ],
    "sg:phone":"+1 404 778 2283",
    "sg:postcode":"30030",
    "sg:province":"GA",
    "sg:tags":[
        "organization",
        "noncommercial"
    ],
    "wof:name":"Emery Healthcare Marketing",
    "wof:placetype":"venue"
},
  "geometry": {"coordinates":[-84.297095,33.775577],"type":"Point"}
}