{
  "type": "Feature",
  "properties": {
    "iso:country":"US",
    "sg:address":"1414 Golf Link Dr",
    "sg:city":"Stone Mountain",
    "sg:classifiers":[
        {
            "category":"Building & Trades",
            "subcategory":"Construction",
            "type":"Services"
        }
    ],
    "sg:phone":"+1 770 987 1169",
    "sg:postcode":"30088",
    "sg:province":"GA",
    "sg:tags":[
        "residential"
    ],
    "wof:name":"Gnj Repairs & Maintenance",
    "wof:placetype":"venue"
},
  "geometry": {"coordinates":[-84.18288699999999,33.747767],"type":"Point"}
}