{
  "type": "Feature",
  "properties": {
    "addr:full":"100 Habersham Dr Fayetteville GA 30214",
    "addr:housenumber":"100",
    "addr:postcode":"30214",
    "addr:street":"Habersham Dr",
    "iso:country":"US",
    "sg:address":"100 Habersham Dr",
    "sg:city":"Fayetteville",
    "sg:classifiers":[
        {
            "category":"Professional",
            "subcategory":"Lawyer & Legal Services",
            "type":"Services"
        }
    ],
    "sg:phone":"+1 770 461 2223",
    "sg:postcode":"30214",
    "sg:province":"GA",
    "sg:tags":[
        "litigation",
        "attorney",
        "injury",
        "estate",
        "family",
        "trial",
        "personal",
        "divorce",
        "civil",
        "planning",
        "law"
    ],
    "sg:website":"http://www.realpagessites.com/mcnallyfoxgrant",
    "wof:name":"McNally Fox & Grant PC",
    "wof:placetype":"venue"
},
  "geometry": {"coordinates":[-84.4533,33.4585],"type":"Point"}
}