{
  "type": "Feature",
  "properties": {
    "addr:full":"5137 Salem Rd Lithonia GA 30038",
    "addr:housenumber":"5137",
    "addr:postcode":"30038",
    "addr:street":"Salem Rd",
    "iso:country":"US",
    "sg:address":"5137 Salem Rd",
    "sg:city":"Lithonia",
    "sg:classifiers":[
        {
            "category":"Education",
            "subcategory":"Library",
            "type":"Public Place"
        }
    ],
    "sg:phone":"+1 770 987 6900",
    "sg:postcode":"30038",
    "sg:province":"GA",
    "wof:name":"Public Library",
    "wof:placetype":"venue"
},
  "geometry": {"coordinates":[-84.176034,33.678459],"type":"Point"}
}