{
  "type": "Feature",
  "properties": {
    "addr:full":"2857 Fork Creek Church Rd Ellenwood GA 30294",
    "addr:housenumber":"2857",
    "addr:postcode":"30294",
    "addr:street":"Fork Creek Church Rd",
    "iso:country":"US",
    "sg:address":"2857 Fork Creek Church Rd",
    "sg:city":"Ellenwood",
    "sg:classifiers":[
        {
            "category":"Utilities",
            "subcategory":"Cable",
            "type":"Services"
        }
    ],
    "sg:phone":"+1 404 328 3000",
    "sg:postcode":"30294",
    "sg:province":"GA",
    "sg:tags":[
        "satellite",
        "carrier"
    ],
    "sg:website":"www.panamsat.com",
    "wof:name":"Panamsat",
    "wof:placetype":"venue"
},
  "geometry": {"coordinates":[-84.278932,33.666293],"type":"Point"}
}