{
  "type": "Feature",
  "properties": {
    "iso:country":"US",
    "sg:address":"1831 Peachtree Rd NE",
    "sg:city":"Atlanta",
    "sg:classifiers":[
        {
            "category":"Building & Trades",
            "subcategory":"Locksmith",
            "type":"Services"
        }
    ],
    "sg:phone":"+1 678 845 9220",
    "sg:postcode":"30309",
    "sg:province":"GA",
    "sg:tags":[
        "key"
    ],
    "wof:name":"Anywhere A Locksmith A Service",
    "wof:placetype":"venue"
},
  "geometry": {"coordinates":[-84.393604,33.805257],"type":"Point"}
}