{
  "type": "Feature",
  "properties": {
    "iso:country":"US",
    "sg:address":"1991 Lower Roswell Rd",
    "sg:city":"Marietta",
    "sg:classifiers":[
        {
            "category":"Banks & Credit Unions",
            "subcategory":"Bank",
            "type":"Services"
        }
    ],
    "sg:phone":"+1 770 565 3794",
    "sg:postcode":"30068",
    "sg:province":"GA",
    "wof:name":"Georgia Methodist Federal Credit Union",
    "wof:placetype":"venue"
},
  "geometry": {"coordinates":[-84.49430099999999,33.950401],"type":"Point"}
}