{
  "type": "Feature",
  "properties": {
    "addr:full":"1914 Elberta Rd Warner Robins GA 31093",
    "addr:housenumber":"1914",
    "addr:postcode":"31093",
    "addr:street":"Elberta Rd",
    "iso:country":"US",
    "sg:address":"1914 Elberta Rd",
    "sg:city":"Warner Robins",
    "sg:classifiers":[
        {
            "category":"Retail",
            "subcategory":"Car Wash",
            "type":"Services"
        }
    ],
    "sg:phone":"+1 478 922 8328",
    "sg:postcode":"31093",
    "sg:province":"GA",
    "sg:tags":[
        "automobile",
        "detail",
        "clean"
    ],
    "wof:name":"J &J Auto Cleaning",
    "wof:placetype":"venue"
},
  "geometry": {"coordinates":[-83.653659,32.633621],"type":"Point"}
}