{
  "type": "Feature",
  "properties": {
    "iso:country":"US",
    "sg:address":"2620 Cobb Pkwy S",
    "sg:city":"Smyrna",
    "sg:classifiers":[
        {
            "category":"Professional",
            "type":"Services"
        }
    ],
    "sg:phone":"+1 678 483 1413",
    "sg:postcode":"30080",
    "sg:province":"GA",
    "sg:tags":[
        "establishment"
    ],
    "wof:name":"IBL Inc",
    "wof:placetype":"venue"
},
  "geometry": {"coordinates":[-84.47488199999999,33.889353],"type":"Point"}
}