{
  "type": "Feature",
  "properties": {
    "iso:country":"US",
    "sg:address":"2431 Cobb Pkwy S",
    "sg:city":"Smyrna",
    "sg:classifiers":[
        {
            "category":"Shopping",
            "subcategory":"Clothing, Apparel, & Fashions",
            "type":"Retail Goods"
        }
    ],
    "sg:phone":"+1 770 953 1001",
    "sg:postcode":"30080",
    "sg:province":"GA",
    "sg:tags":[
        "furnishing"
    ],
    "wof:name":"Hyroop's The Big Tall Place",
    "wof:placetype":"venue"
},
  "geometry": {"coordinates":[-84.47833300000001,33.893139],"type":"Point"}
}