{
  "type": "Feature",
  "properties": {
    "addr:full":"4503 Grapevine Ct NW Acworth GA 30102",
    "addr:housenumber":"4503",
    "addr:postcode":"30102",
    "addr:street":"Grapevine Ct Nw",
    "iso:country":"US",
    "sg:address":"4503 Grapevine Ct NW",
    "sg:city":"Acworth",
    "sg:classifiers":[
        {
            "category":"Real Estate",
            "subcategory":"Real Estate Agent",
            "type":"Services"
        }
    ],
    "sg:phone":"+1 770 592 6170",
    "sg:postcode":"30102",
    "sg:province":"GA",
    "wof:name":"Lockheed Martin",
    "wof:placetype":"venue"
},
  "geometry": {"coordinates":[-84.569509,34.062573],"type":"Point"}
}