{
  "type": "Feature",
  "properties": {
    "addr:full":"911 N 3rd Ave Chatsworth GA 30705",
    "addr:housenumber":"911",
    "addr:postcode":"30705",
    "addr:street":"N 3Rd Ave",
    "iso:country":"US",
    "sg:address":"911 N 3rd Ave",
    "sg:city":"Chatsworth",
    "sg:classifiers":[
        {
            "category":"Health Services",
            "subcategory":"Optometrist",
            "type":"Services"
        }
    ],
    "sg:phone":"+1 706 695 4676",
    "sg:postcode":"30705",
    "sg:province":"GA",
    "wof:name":"Advanced Eye Care",
    "wof:placetype":"venue"
},
  "geometry": {"coordinates":[-84.769952,34.781939],"type":"Point"}
}