{
  "type": "Feature",
  "properties": {
    "iso:country":"US",
    "sg:address":"2965 Holcomb Bridge Rd",
    "sg:city":"Alpharetta",
    "sg:classifiers":[
        {
            "category":"Retail",
            "subcategory":"Auto Repair",
            "type":"Services"
        }
    ],
    "sg:phone":"+1 770 640 7087",
    "sg:postcode":"30022",
    "sg:province":"GA",
    "sg:tags":[
        "repairing",
        "automobile"
    ],
    "wof:name":"Holcomb Auto",
    "wof:placetype":"venue"
},
  "geometry": {"coordinates":[-84.275415,33.989817],"type":"Point"}
}