{
  "type": "Feature",
  "properties": {
    "iso:country":"US",
    "sg:address":"PO Box 8845",
    "sg:city":"Savannah",
    "sg:classifiers":[
        {
            "category":"Professional",
            "subcategory":"Computer Services",
            "type":"Services"
        }
    ],
    "sg:postcode":"31412",
    "sg:province":"GA",
    "sg:tags":[
        "rails",
        "rubyonrails",
        "hosting",
        "applications",
        "infrastructure",
        "scaling",
        "support"
    ],
    "sg:website":"http://railsmachine.com",
    "wof:name":"Rails Machine",
    "wof:placetype":"venue"
},
  "geometry": {"coordinates":[-81.07156000000001,31.971394],"type":"Point"}
}