{
  "type": "Feature",
  "properties": {
    "iso:country":"US",
    "sg:address":"143 Morton Springs Rd",
    "sg:city":"Cedartown",
    "sg:classifiers":[
        {
            "category":"Health Services",
            "subcategory":"Clinic",
            "type":"Services"
        }
    ],
    "sg:phone":"+1 770 749 0911",
    "sg:postcode":"30125",
    "sg:province":"GA",
    "sg:tags":[
        "home",
        "care"
    ],
    "wof:name":"Rainbow Manner",
    "wof:placetype":"venue"
},
  "geometry": {"coordinates":[-85.252377,33.975807],"type":"Point"}
}