{
  "type": "Feature",
  "properties": {
    "addr:full":"107 E Franklin St Sylvester GA 31791",
    "addr:housenumber":"107",
    "addr:postcode":"31791",
    "addr:street":"E Franklin St",
    "iso:country":"US",
    "sg:address":"107 E Franklin St",
    "sg:city":"Sylvester",
    "sg:classifiers":[
        {
            "category":"Food & Beverages",
            "subcategory":"Groceries & Convenience Stores",
            "type":"Retail Goods"
        }
    ],
    "sg:phone":"+1 229 776 3546",
    "sg:postcode":"31791",
    "sg:province":"GA",
    "wof:name":"Handy Andy",
    "wof:placetype":"venue"
},
  "geometry": {"coordinates":[-83.837373,31.530677],"type":"Point"}
}