{
  "type": "Feature",
  "properties": {
    "addr:full":"413 N Hairston Rd Stone Mountain GA 30083",
    "addr:housenumber":"413",
    "addr:postcode":"30083",
    "addr:street":"N Hairston Rd",
    "iso:country":"US",
    "sg:address":"413 N Hairston Rd",
    "sg:city":"Stone Mountain",
    "sg:classifiers":[
        {
            "category":"Banks & Credit Unions",
            "subcategory":"Bank",
            "type":"Services"
        }
    ],
    "sg:phone":"+1 404 499 1019",
    "sg:postcode":"30083",
    "sg:province":"GA",
    "sg:tags":[
        "loan",
        "real estate"
    ],
    "wof:name":"CFIC Home Mortgage",
    "wof:placetype":"venue"
},
  "geometry": {"coordinates":[-84.195284,33.78974],"type":"Point"}
}