{
  "type": "Feature",
  "properties": {
    "iso:country":"US",
    "sg:address":"137 Burke St",
    "sg:city":"Marietta",
    "sg:classifiers":[
        {
            "category":"Bus Charters",
            "type":"Transportation"
        }
    ],
    "sg:phone":"+1 770 218 6231",
    "sg:postcode":"30060",
    "sg:province":"GA",
    "sg:tags":[
        "rental"
    ],
    "wof:name":"R & D Coaching Inc",
    "wof:placetype":"venue"
},
  "geometry": {"coordinates":[-84.548965,33.910162],"type":"Point"}
}