{
  "type": "Feature",
  "properties": {
    "iso:country":"US",
    "sg:address":"51 Rice Rd",
    "sg:city":"Rockmart",
    "sg:classifiers":[
        {
            "category":"Professional",
            "subcategory":"Detective & Security Services",
            "type":"Services"
        }
    ],
    "sg:phone":"+1 770 684 8690",
    "sg:postcode":"30153",
    "sg:province":"GA",
    "sg:tags":[
        "information",
        "bureau"
    ],
    "wof:name":"American Plant Services",
    "wof:placetype":"venue"
},
  "geometry": {"coordinates":[-85.011228,34.034933],"type":"Point"}
}