{
  "type": "Feature",
  "properties": {
    "addr:full":"702 Cedar Dr Ashburn GA 31714",
    "addr:housenumber":"702",
    "addr:postcode":"31714",
    "addr:street":"Cedar Dr",
    "iso:country":"US",
    "sg:address":"702 Cedar Dr",
    "sg:city":"Ashburn",
    "sg:phone":"+1 229 567 3645",
    "sg:postcode":"31714",
    "sg:province":"GA",
    "sg:tags":[
        "farm",
        "grain",
        "cash"
    ],
    "wof:name":"Jimmy Freeman",
    "wof:placetype":"venue"
},
  "geometry": {"coordinates":[-83.64266600000001,31.71762],"type":"Point"}
}