{
  "type": "Feature",
  "properties": {
    "addr:full":"64 Brooks Trce Cleveland GA 30540",
    "addr:housenumber":"64",
    "addr:postcode":"30540",
    "addr:street":"Brooks Trce",
    "iso:country":"US",
    "sg:address":"64 Brooks Trce",
    "sg:city":"Cleveland",
    "sg:classifiers":[
        {
            "category":"Banks & Credit Unions",
            "subcategory":"Investment Brokerage",
            "type":"Services"
        }
    ],
    "sg:phone":"+1 706 865 0933",
    "sg:postcode":"30540",
    "sg:province":"GA",
    "sg:tags":[
        "security"
    ],
    "wof:name":"Edward Jones Co",
    "wof:placetype":"venue"
},
  "geometry": {"coordinates":[-84.51760899999999,34.728121],"type":"Point"}
}