{
  "type": "Feature",
  "properties": {
    "iso:country":"US",
    "sg:address":"8465 Holcomb Bridge Rd",
    "sg:city":"Alpharetta",
    "sg:classifiers":[
        {
            "category":"Professional",
            "subcategory":"Research",
            "type":"Services"
        }
    ],
    "sg:phone":"+1 770 649 0006",
    "sg:postcode":"30022",
    "sg:province":"GA",
    "sg:tags":[
        "marketing",
        "energy",
        "power"
    ],
    "wof:name":"CPS Financial",
    "wof:placetype":"venue"
},
  "geometry": {"coordinates":[-84.270566,33.986069],"type":"Point"}
}