{
  "type": "Feature",
  "properties": {
    "iso:country":"US",
    "sg:address":"139 N Main St",
    "sg:city":"Jonesboro",
    "sg:classifiers":[
        {
            "category":"Banks & Credit Unions",
            "subcategory":"Bank",
            "type":"Services"
        },
        {
            "category":"Banks & Credit Unions",
            "subcategory":"Financial Services",
            "type":"Services"
        }
    ],
    "sg:phone":"+1 770 478 7252",
    "sg:postcode":"30236",
    "sg:province":"GA",
    "sg:tags":[
        "loan",
        "financing"
    ],
    "sg:website":"http://www.SunTrust.com",
    "wof:name":"SunTrust Bank - Jonesboro",
    "wof:placetype":"venue"
},
  "geometry": {"coordinates":[-84.35442399999999,33.522606],"type":"Point"}
}