{
  "type": "Feature",
  "properties": {
    "addr:full":"5095 Stone Trce Stone Mountain GA 30083",
    "addr:housenumber":"5095",
    "addr:postcode":"30083",
    "addr:street":"Stone Trce",
    "iso:country":"US",
    "sg:address":"5095 Stone Trce",
    "sg:city":"Stone Mountain",
    "sg:classifiers":[
        {
            "category":"Food & Beverages",
            "subcategory":"Groceries & Convenience Stores",
            "type":"Retail Goods"
        }
    ],
    "sg:phone":"+1 770 498 0911",
    "sg:postcode":"30083",
    "sg:province":"GA",
    "sg:tags":[
        "gas"
    ],
    "wof:name":"Cheveron Food Mart",
    "wof:placetype":"venue"
},
  "geometry": {"coordinates":[-84.186086,33.798671],"type":"Point"}
}