{
  "type": "Feature",
  "properties": {
    "addr:full":"2512 Moody Rd Warner Robins GA 31088",
    "addr:housenumber":"2512",
    "addr:postcode":"31088",
    "addr:street":"Moody Rd",
    "iso:country":"US",
    "sg:address":"2512 Moody Rd",
    "sg:city":"Warner Robins",
    "sg:classifiers":[
        {
            "category":"Food & Beverages",
            "subcategory":"Groceries & Convenience Stores",
            "type":"Retail Goods"
        }
    ],
    "sg:phone":"+1 478 922 7433",
    "sg:postcode":"31088",
    "sg:province":"GA",
    "wof:name":"Stop N Shop",
    "wof:placetype":"venue"
},
  "geometry": {"coordinates":[-83.62374699999999,32.578162],"type":"Point"}
}