{
  "type": "Feature",
  "properties": {
    "iso:country":"US",
    "sg:address":"4618 Woodstock Rd",
    "sg:city":"Roswell",
    "sg:classifiers":[
        {
            "category":"Real Estate",
            "subcategory":"Real Estate Agent",
            "type":"Services"
        }
    ],
    "sg:phone":"+1 770 641 6553",
    "sg:postcode":"30075",
    "sg:province":"GA",
    "wof:name":"Mid South Realty",
    "wof:placetype":"venue"
},
  "geometry": {"coordinates":[-84.419556,34.061632],"type":"Point"}
}