{
  "type": "Feature",
  "properties": {
    "iso:country":"US",
    "sg:address":"1053 Hightower Church Rd",
    "sg:city":"Dahlonega",
    "sg:classifiers":[
        {
            "category":"Shopping",
            "subcategory":"Musical Instruments",
            "type":"Retail Goods"
        }
    ],
    "sg:phone":"+1 706 867 8634",
    "sg:postcode":"30533",
    "sg:province":"GA",
    "sg:tags":[
        "music",
        "dealer"
    ],
    "wof:name":"KATY J's Music Ranch",
    "wof:placetype":"venue"
},
  "geometry": {"coordinates":[-84.057661,34.565863],"type":"Point"}
}