{
  "type": "Feature",
  "properties": {
    "iso:country":"US",
    "sg:address":"301 7th Ave W",
    "sg:city":"Cordele",
    "sg:classifiers":[
        {
            "category":"Retail",
            "subcategory":"Animal Services",
            "type":"Services"
        }
    ],
    "sg:phone":"+1 229 273 1084",
    "sg:postcode":"31015",
    "sg:province":"GA",
    "sg:tags":[
        "pet",
        "grooming",
        "washing"
    ],
    "wof:name":"Doggy Boutique",
    "wof:placetype":"venue"
},
  "geometry": {"coordinates":[-83.786379,31.97281],"type":"Point"}
}