{
  "type": "Feature",
  "properties": {
    "addr:full":"431 Lester Rd Fayetteville GA 30215",
    "addr:housenumber":"431",
    "addr:postcode":"30215",
    "addr:street":"Lester Rd",
    "iso:country":"US",
    "sg:address":"431 Lester Rd",
    "sg:city":"Fayetteville",
    "sg:classifiers":[
        {
            "category":"Banks & Credit Unions",
            "subcategory":"Financial Services",
            "type":"Services"
        }
    ],
    "sg:phone":"+1 770 487 6202",
    "sg:postcode":"30215",
    "sg:province":"GA",
    "sg:tags":[
        "investment",
        "closed"
    ],
    "wof:name":"Bisher Co LLC",
    "wof:placetype":"venue"
},
  "geometry": {"coordinates":[-84.503998,33.432764],"type":"Point"}
}