{
  "type": "Feature",
  "properties": {
    "iso:country":"US",
    "sg:address":"5368 Veterans Pkwy",
    "sg:city":"Columbus",
    "sg:classifiers":[
        {
            "category":"Bars & Pubs",
            "type":"Food & Drink"
        }
    ],
    "sg:phone":"+1 706 653 6332",
    "sg:postcode":"31904",
    "sg:province":"GA",
    "sg:tags":[
        "drinking"
    ],
    "wof:name":"Cat Walk",
    "wof:placetype":"venue"
},
  "geometry": {"coordinates":[-84.968198,32.516768],"type":"Point"}
}