{
  "type": "Feature",
  "properties": {
    "addr:full":"1160 Old Powder Springs Rd SW Mableton GA 30126",
    "addr:housenumber":"1160",
    "addr:postcode":"30126",
    "addr:street":"Old Powder Springs Rd Sw",
    "iso:country":"US",
    "sg:address":"1160 Old Powder Springs Rd SW",
    "sg:city":"Mableton",
    "sg:classifiers":[
        {
            "category":"Manufacturing",
            "subcategory":"Printing",
            "type":"Manufacturing & Wholesale Goods"
        }
    ],
    "sg:phone":"+1 770 732 1910",
    "sg:postcode":"30126",
    "sg:province":"GA",
    "sg:tags":[
        "printer"
    ],
    "wof:name":"Express Printing Svc",
    "wof:placetype":"venue"
},
  "geometry": {"coordinates":[-84.589322,33.814646],"type":"Point"}
}