{
  "type": "Feature",
  "properties": {
    "iso:country":"US",
    "sg:address":"1034 Main St NW",
    "sg:city":"Conyers",
    "sg:classifiers":[
        {
            "category":"Professional",
            "subcategory":"Management & Consulting",
            "type":"Services"
        }
    ],
    "sg:phone":"+1 770 918 8858",
    "sg:postcode":"30012",
    "sg:province":"GA",
    "sg:tags":[
        "consultant",
        "business"
    ],
    "wof:name":"William Fincher Assoc",
    "wof:placetype":"venue"
},
  "geometry": {"coordinates":[-84.024598,33.673987],"type":"Point"}
}