{
  "type": "Feature",
  "properties": {
    "addr:full":"2745 Pappys Plz Blairsville GA 30512",
    "addr:housenumber":"2745",
    "addr:postcode":"30512",
    "addr:street":"Pappys Plz",
    "iso:country":"US",
    "sg:address":"2745 Pappys Plz",
    "sg:city":"Blairsville",
    "sg:classifiers":[
        {
            "category":"Real Estate",
            "subcategory":"Real Estate Agent",
            "type":"Services"
        }
    ],
    "sg:phone":"+1 706 745 1777",
    "sg:postcode":"30512",
    "sg:province":"GA",
    "wof:name":"Re Max Enotah Realty",
    "wof:placetype":"venue"
},
  "geometry": {"coordinates":[-83.909695,34.825675],"type":"Point"}
}