{
  "type": "Feature",
  "properties": {
    "addr:full":"2305 Fox Hall Dr Augusta GA 30907",
    "addr:housenumber":"2305",
    "addr:postcode":"30907",
    "addr:street":"Fox Hall Dr",
    "iso:country":"US",
    "sg:address":"2305 Fox Hall Dr",
    "sg:city":"Augusta",
    "sg:classifiers":[
        {
            "category":"Professional",
            "subcategory":"Business Services",
            "type":"Services"
        }
    ],
    "sg:phone":"+1 877 233 2523",
    "sg:postcode":"30907",
    "sg:province":"GA",
    "wof:name":"Advanced Covert Technology",
    "wof:placetype":"venue"
},
  "geometry": {"coordinates":[-82.076982,33.50244],"type":"Point"}
}