{
  "type": "Feature",
  "properties": {
    "iso:country":"US",
    "sg:address":"3109 Hwy 411 NE",
    "sg:city":"White",
    "sg:classifiers":[
        {
            "category":"Personal",
            "subcategory":"Beauty Salon",
            "type":"Services"
        }
    ],
    "sg:phone":"+1 770 607 7363",
    "sg:postcode":"30184",
    "sg:province":"GA",
    "wof:name":"Styles By Stacy",
    "wof:placetype":"venue"
},
  "geometry": {"coordinates":[-84.74852,34.273261],"type":"Point"}
}