{
  "type": "Feature",
  "properties": {
    "addr:full":"105 S Pond St Toccoa GA 30577",
    "addr:housenumber":"105",
    "addr:postcode":"30577",
    "addr:street":"S Pond St",
    "iso:country":"US",
    "sg:address":"105 S Pond St",
    "sg:city":"Toccoa",
    "sg:classifiers":[
        {
            "category":"Autos & Motor Vehicles",
            "subcategory":"Automobile Sales",
            "type":"Retail Goods"
        }
    ],
    "sg:phone":"+1 706 886 3161",
    "sg:postcode":"30577",
    "sg:province":"GA",
    "sg:tags":[
        "car",
        "dealer"
    ],
    "wof:name":"Tabor Motor Co",
    "wof:placetype":"venue"
},
  "geometry": {"coordinates":[-83.32830800000001,34.57823],"type":"Point"}
}