{
  "type": "Feature",
  "properties": {
    "addr:full":"1005 Windsor Trl Roswell GA 30076",
    "addr:housenumber":"1005",
    "addr:postcode":"30076",
    "addr:street":"Windsor Trl",
    "iso:country":"US",
    "sg:address":"1005 Windsor Trl",
    "sg:city":"Roswell",
    "sg:classifiers":[
        {
            "category":"Wholesale",
            "subcategory":"Metals & Minerals",
            "type":"Manufacturing & Wholesale Goods"
        }
    ],
    "sg:phone":"+1 770 993 4931",
    "sg:postcode":"30076",
    "sg:province":"GA",
    "sg:tags":[
        "representative",
        "mfg"
    ],
    "wof:name":"K B K Piping Systems",
    "wof:placetype":"venue"
},
  "geometry": {"coordinates":[-84.348854,34.045674],"type":"Point"}
}