{
  "type": "Feature",
  "properties": {
    "iso:country":"US",
    "sg:address":"4352 Gina Ct NW",
    "sg:city":"Lilburn",
    "sg:classifiers":[
        {
            "category":"Taxi",
            "type":"Transportation"
        }
    ],
    "sg:phone":"+1 770 242 0004",
    "sg:postcode":"30047",
    "sg:province":"GA",
    "sg:tags":[
        "taxicab"
    ],
    "wof:name":"Mexican Taxi/Lmsn Inc",
    "wof:placetype":"venue"
},
  "geometry": {"coordinates":[-84.12459800000001,33.895272],"type":"Point"}
}