{
  "type": "Feature",
  "properties": {
    "iso:country":"US",
    "sg:address":"1847 Elmwood Dr",
    "sg:city":"Austell",
    "sg:classifiers":[
        {
            "category":"Professional",
            "subcategory":"Computer Services",
            "type":"Services"
        }
    ],
    "sg:phone":"+1 770 732 9284",
    "sg:postcode":"30106",
    "sg:province":"GA",
    "sg:tags":[
        "leasing"
    ],
    "wof:name":"Compscan",
    "wof:placetype":"venue"
},
  "geometry": {"coordinates":[-84.605313,33.845792],"type":"Point"}
}