{
  "type": "Feature",
  "properties": {
    "iso:country":"US",
    "sg:address":"2144 Imperial Dr",
    "sg:city":"Gainesville",
    "sg:classifiers":[
        {
            "category":"Building & Trades",
            "subcategory":"Construction",
            "type":"Services"
        }
    ],
    "sg:phone":"+1 770 532 8117",
    "sg:postcode":"30501",
    "sg:province":"GA",
    "sg:tags":[
        "housing"
    ],
    "wof:name":"Imperial Construction Co",
    "wof:placetype":"venue"
},
  "geometry": {"coordinates":[-83.816419,34.345681],"type":"Point"}
}