{
  "type": "Feature",
  "properties": {
    "iso:country":"US",
    "sg:address":"1495 Old McDonough Hwy SE",
    "sg:city":"Conyers",
    "sg:classifiers":[
        {
            "category":"Health Services",
            "subcategory":"Doctor",
            "type":"Services"
        }
    ],
    "sg:phone":"+1 770 922 7000",
    "sg:postcode":"30094",
    "sg:province":"GA",
    "sg:tags":[
        "medical"
    ],
    "wof:name":"Mohamed N Dharamsi MD",
    "wof:placetype":"venue"
},
  "geometry": {"coordinates":[-84.01290400000001,33.650083],"type":"Point"}
}