{
  "type": "Feature",
  "properties": {
    "addr:full":"108 S Nicholson Cir Savannah GA 31419",
    "addr:housenumber":"108",
    "addr:postcode":"31419",
    "addr:street":"S Nicholson Cir",
    "iso:country":"US",
    "sg:address":"108 S Nicholson Cir",
    "sg:city":"Savannah",
    "sg:classifiers":[
        {
            "category":"Retail",
            "subcategory":"Repair Shop",
            "type":"Services"
        }
    ],
    "sg:phone":"+1 912 927 6594",
    "sg:postcode":"31419",
    "sg:province":"GA",
    "wof:name":"Sailor S Nautical Service",
    "wof:placetype":"venue"
},
  "geometry": {"coordinates":[-81.143998,31.962757],"type":"Point"}
}