{
  "type": "Feature",
  "properties": {
    "addr:full":"503 S Lincoln Trace Ave SE Smyrna GA 30080",
    "addr:housenumber":"503",
    "addr:postcode":"30080",
    "addr:street":"S Lincoln Trace Ave Se",
    "iso:country":"US",
    "sg:address":"503 S Lincoln Trace Ave SE",
    "sg:city":"Smyrna",
    "sg:classifiers":[
        {
            "category":"Personal",
            "type":"Services"
        }
    ],
    "sg:phone":"+1 678 401 4711",
    "sg:postcode":"30080",
    "sg:province":"GA",
    "sg:tags":[
        "assistant"
    ],
    "wof:name":"Jmh Mobile Detailing",
    "wof:placetype":"venue"
},
  "geometry": {"coordinates":[-84.474456,33.890428],"type":"Point"}
}