{
  "type": "Feature",
  "properties": {
    "iso:country":"US",
    "sg:address":"7030 State Rte 15",
    "sg:city":"Warthen",
    "sg:classifiers":[
        {
            "category":"Organizations",
            "subcategory":"Religious Organization",
            "type":"Services"
        }
    ],
    "sg:phone":"+1 478 552 6650",
    "sg:postcode":"31094",
    "sg:province":"GA",
    "sg:tags":[
        "church"
    ],
    "wof:name":"New Light Church Of Jesus",
    "wof:placetype":"venue"
},
  "geometry": {"coordinates":[-82.805958,33.086703],"type":"Point"}
}