{
  "type": "Feature",
  "properties": {
    "iso:country":"US",
    "sg:address":"3650 Brookside Pkwy",
    "sg:city":"Alpharetta",
    "sg:classifiers":[
        {
            "category":"Building & Trades",
            "subcategory":"Construction",
            "type":"Services"
        }
    ],
    "sg:phone":"+1 770 777 4129",
    "sg:postcode":"30022",
    "sg:province":"GA",
    "sg:tags":[
        "general",
        "contractor"
    ],
    "wof:name":"Brasfield & Gorrie",
    "wof:placetype":"venue"
},
  "geometry": {"coordinates":[-84.247462,34.060433],"type":"Point"}
}