{
  "type": "Feature",
  "properties": {
    "addr:full":"380 E Lake Blvd SE Atlanta GA 30317",
    "addr:housenumber":"380",
    "addr:postcode":"30317",
    "addr:street":"E Lake Blvd Se",
    "iso:country":"US",
    "sg:address":"380 E Lake Blvd SE",
    "sg:city":"Atlanta",
    "sg:classifiers":[
        {
            "category":"Government",
            "subcategory":"Office",
            "type":"Public Place"
        }
    ],
    "sg:phone":"+1 404 370 8107",
    "sg:postcode":"30317",
    "sg:province":"GA",
    "sg:tags":[
        "government-united",
        "state"
    ],
    "wof:name":"East Lake Towers",
    "wof:placetype":"venue"
},
  "geometry": {"coordinates":[-84.31453500000001,33.743891],"type":"Point"}
}