{
  "type": "Feature",
  "properties": {
    "addr:full":"220 Blueberry Ln Dawsonville GA 30534",
    "addr:housenumber":"220",
    "addr:postcode":"30534",
    "addr:street":"Blueberry Ln",
    "iso:country":"US",
    "sg:address":"220 Blueberry Ln",
    "sg:city":"Dawsonville",
    "sg:classifiers":[
        {
            "category":"Professional",
            "type":"Services"
        }
    ],
    "sg:phone":"+1 706 265 6839",
    "sg:postcode":"30534",
    "sg:province":"GA",
    "wof:name":"Wildernest Inc",
    "wof:placetype":"venue"
},
  "geometry": {"coordinates":[-84.092129,34.472422],"type":"Point"}
}