{
  "type": "Feature",
  "properties": {
    "iso:country":"US",
    "sg:address":"5901 Ogeechee Rd",
    "sg:city":"Savannah",
    "sg:classifiers":[
        {
            "category":"Shopping",
            "type":"Retail Goods"
        }
    ],
    "sg:phone":"+1 912 925 1777",
    "sg:postcode":"31419",
    "sg:province":"GA",
    "sg:tags":[
        "pet",
        "shop",
        "merchandise"
    ],
    "wof:name":"Tweeters N Peepers",
    "wof:placetype":"venue"
},
  "geometry": {"coordinates":[-81.24975999999999,31.999063],"type":"Point"}
}