{
  "type": "Feature",
  "properties": {
    "iso:country":"US",
    "sg:address":"5941 Moss Dr",
    "sg:city":"Forest Park",
    "sg:classifiers":[
        {
            "category":"Professional",
            "subcategory":"Business Services",
            "type":"Services"
        }
    ],
    "sg:phone":"+1 404 366 6859",
    "sg:postcode":"30297",
    "sg:province":"GA",
    "wof:name":"4lb Express Inc",
    "wof:placetype":"venue"
},
  "geometry": {"coordinates":[-84.375474,33.592399],"type":"Point"}
}