{
  "type": "Feature",
  "properties": {
    "addr:full":"159 Hannah Dr Ellijay GA 30540",
    "addr:housenumber":"159",
    "addr:postcode":"30540",
    "addr:street":"Hannah Dr Ellijay",
    "iso:country":"US",
    "sg:address":"159 Hannah Dr",
    "sg:city":"Ellijay",
    "sg:classifiers":[
        {
            "category":"Shopping",
            "subcategory":"Stationery & Office Supplies",
            "type":"Retail Goods"
        },
        {
            "category":"Wholesale",
            "subcategory":"Office Equipment",
            "type":"Manufacturing & Wholesale Goods"
        },
        {
            "category":"Retail",
            "subcategory":"Repair Shop",
            "type":"Services"
        },
        {
            "category":"Shopping",
            "subcategory":"Antiques",
            "type":"Retail Goods"
        },
        {
            "category":"Home & Garden",
            "subcategory":"Furniture",
            "type":"Retail Goods"
        }
    ],
    "sg:phone":"+1 706 391 5028",
    "sg:postcode":"30540",
    "sg:province":"GA",
    "sg:tags":[
        "equipment-wholesale",
        "refinish",
        "store",
        "manufacturer"
    ],
    "sg:website":"http://www.citysearch.com/profile/external/649901450/ellijay_ga/furniture_medic.html?publisher=yellowpages&reference_id=7&placement=ypwebsitemip",
    "wof:name":"Furniture Medic",
    "wof:placetype":"venue"
},
  "geometry": {"coordinates":[-84.512029,34.637046],"type":"Point"}
}