{
  "type": "Feature",
  "properties": {
    "iso:country":"US",
    "sg:address":"1019 Queensbury Run",
    "sg:city":"Acworth",
    "sg:classifiers":[
        {
            "category":"Banks & Credit Unions",
            "subcategory":"Financial Services",
            "type":"Services"
        }
    ],
    "sg:phone":"+1 770 592 2185",
    "sg:postcode":"30102",
    "sg:province":"GA",
    "sg:tags":[
        "investor"
    ],
    "wof:name":"New Horizon Inv Prpts LLC",
    "wof:placetype":"venue"
},
  "geometry": {"coordinates":[-84.59954500000001,34.105739],"type":"Point"}
}