{
  "type": "Feature",
  "properties": {
    "addr:full":"4539 Holly Forest Dr Gainesville GA 30507",
    "addr:housenumber":"4539",
    "addr:postcode":"30507",
    "addr:street":"Holly Forest Dr",
    "iso:country":"US",
    "sg:address":"4539 Holly Forest Dr",
    "sg:city":"Gainesville",
    "sg:classifiers":[
        {
            "category":"Retail",
            "subcategory":"Laundry & Dry Cleaning",
            "type":"Services"
        }
    ],
    "sg:phone":"+1 770 535 7697",
    "sg:postcode":"30507",
    "sg:province":"GA",
    "sg:tags":[
        "cleaners",
        "rug",
        "carpet"
    ],
    "wof:name":"Bill's Carpet & Upholstery",
    "wof:placetype":"venue"
},
  "geometry": {"coordinates":[-83.80694200000001,34.194526],"type":"Point"}
}