{
  "type": "Feature",
  "properties": {
    "addr:full":"205 W Cherokee Ave Cartersville GA 30120",
    "addr:housenumber":"205",
    "addr:postcode":"30120",
    "addr:street":"W Cherokee Ave",
    "iso:country":"US",
    "sg:address":"205 W Cherokee Ave",
    "sg:city":"Cartersville",
    "sg:classifiers":[
        {
            "category":"Organizations",
            "subcategory":"Religious Organization",
            "type":"Services"
        }
    ],
    "sg:phone":"+1 770 382 2626",
    "sg:postcode":"30120",
    "sg:province":"GA",
    "sg:website":"www.ascensioncartersville.org",
    "wof:name":"Episcopal Church Of Ascension",
    "wof:placetype":"venue"
},
  "geometry": {"coordinates":[-84.798018,34.165531],"type":"Point"}
}