{
  "type": "Feature",
  "properties": {
    "addr:full":"2705 Shoemaker Ln Snellville GA 30039",
    "addr:housenumber":"2705",
    "addr:postcode":"30039",
    "addr:street":"Shoemaker Ln",
    "iso:country":"US",
    "sg:address":"2705 Shoemaker Ln",
    "sg:city":"Snellville",
    "sg:classifiers":[
        {
            "category":"Real Estate",
            "subcategory":"Real Estate Services",
            "type":"Services"
        }
    ],
    "sg:phone":"+1 678 591 0010",
    "sg:postcode":"30039",
    "sg:province":"GA",
    "sg:tags":[
        "management"
    ],
    "wof:name":"Lewis Property Management",
    "wof:placetype":"venue"
},
  "geometry": {"coordinates":[-84.069188,33.818975],"type":"Point"}
}