{
  "type": "Feature",
  "properties": {
    "addr:full":"434 Marietta Street Suite 303 Atlanta GA 30313",
    "addr:housenumber":"434",
    "addr:postcode":"30313",
    "addr:street":"Marietta Street Suite 303",
    "iso:country":"US",
    "sg:address":"434 Marietta Street Suite 303",
    "sg:city":"Atlanta",
    "sg:classifiers":[
        {
            "category":"Professional",
            "subcategory":"Advertising",
            "type":"Services"
        }
    ],
    "sg:phone":"+1 404 680 7987",
    "sg:postcode":"30313",
    "sg:province":"GA",
    "sg:tags":[
        "seo",
        "ppc",
        "website-consulting",
        "website-optimization",
        "website-design",
        "website-development"
    ],
    "sg:website":"http://www.medianomic.com",
    "wof:name":"Medianomic",
    "wof:placetype":"venue"
},
  "geometry": {"coordinates":[-84.39738,33.765353],"type":"Point"}
}