{
  "type": "Feature",
  "properties": {
    "addr:full":"1432 Mount Olive Church Rd Dahlonega GA 30533",
    "addr:housenumber":"1432",
    "addr:postcode":"30533",
    "addr:street":"Mount;Church Rd",
    "iso:country":"US",
    "sg:address":"1432 Mount Olive Church Rd",
    "sg:city":"Dahlonega",
    "sg:classifiers":[
        {
            "category":"Social Services",
            "type":"Services"
        }
    ],
    "sg:phone":"+1 706 867 7612",
    "sg:postcode":"30533",
    "sg:province":"GA",
    "sg:tags":[
        "shelter",
        "storm"
    ],
    "wof:name":"R & R Storm Shelters",
    "wof:placetype":"venue"
},
  "geometry": {"coordinates":[-83.880899,34.482034],"type":"Point"}
}