{
  "type": "Feature",
  "properties": {
    "iso:country":"US",
    "sg:address":"229 Hurricane Shoals Rd NW",
    "sg:city":"Lawrenceville",
    "sg:classifiers":[
        {
            "category":"Building & Trades",
            "subcategory":"Equipment Rental",
            "type":"Services"
        }
    ],
    "sg:phone":"+1 770 532 8558",
    "sg:postcode":"30045",
    "sg:province":"GA",
    "sg:tags":[
        "heavy",
        "construction"
    ],
    "wof:name":"Rental Service Corporation",
    "wof:placetype":"venue"
},
  "geometry": {"coordinates":[-83.998954,33.968548],"type":"Point"}
}