{
  "type": "Feature",
  "properties": {
    "iso:country":"US",
    "sg:address":"4525 Roosevelt Hwy",
    "sg:city":"Atlanta",
    "sg:classifiers":[
        {
            "category":"Retail",
            "subcategory":"Auto Rental",
            "type":"Services"
        }
    ],
    "sg:phone":"+1 404 559 8797",
    "sg:postcode":"30349",
    "sg:province":"GA",
    "sg:tags":[
        "truck",
        "rent",
        "lease"
    ],
    "wof:name":"Ryder",
    "wof:placetype":"venue"
},
  "geometry": {"coordinates":[-84.536941,33.604559],"type":"Point"}
}