{
  "type": "Feature",
  "properties": {
    "addr:full":"1225 Old Chattahoochee Ave NW Atlanta GA 30318",
    "addr:housenumber":"1225",
    "addr:postcode":"30318",
    "addr:street":"Old Chattahoochee Ave Nw",
    "iso:country":"US",
    "sg:address":"1225 Old Chattahoochee Ave NW",
    "sg:city":"Atlanta",
    "sg:classifiers":[
        {
            "category":"Building & Trades",
            "subcategory":"Locksmith",
            "type":"Services"
        }
    ],
    "sg:phone":"+1 678 298 6583",
    "sg:postcode":"30318",
    "sg:province":"GA",
    "sg:tags":[
        "key"
    ],
    "wof:name":"0 & 0 & 1 24 Hour A Emergency A Locksmith",
    "wof:placetype":"venue"
},
  "geometry": {"coordinates":[-84.425802,33.800547],"type":"Point"}
}