{
  "type": "Feature",
  "properties": {
    "iso:country":"US",
    "sg:address":"708 S Grant St",
    "sg:city":"Fitzgerald",
    "sg:classifiers":[
        {
            "category":"Shopping",
            "subcategory":"Clothing, Apparel, & Fashions",
            "type":"Retail Goods"
        }
    ],
    "sg:phone":"+1 229 423 5019",
    "sg:postcode":"31750",
    "sg:province":"GA",
    "wof:name":"Engelmann J Ltd Mens Store",
    "wof:placetype":"venue"
},
  "geometry": {"coordinates":[-83.25292399999999,31.70728],"type":"Point"}
}