{
  "type": "Feature",
  "properties": {
    "addr:full":"853 Wood St NW Atlanta GA 30318",
    "addr:housenumber":"853",
    "addr:postcode":"30318",
    "addr:street":"Wood St Nw",
    "iso:country":"US",
    "sg:address":"853 Wood St NW",
    "sg:city":"Atlanta",
    "sg:classifiers":[
        {
            "category":"Organizations",
            "subcategory":"Religious Organization",
            "type":"Services"
        }
    ],
    "sg:phone":"+1 404 373 0105",
    "sg:postcode":"30318",
    "sg:province":"GA",
    "wof:name":"Unity Church of God",
    "wof:placetype":"venue"
},
  "geometry": {"coordinates":[-84.457696,33.77817],"type":"Point"}
}