{
  "type": "Feature",
  "properties": {
    "addr:full":"5945 Monterey Dr Morrow GA 30260",
    "addr:housenumber":"5945",
    "addr:postcode":"30260",
    "addr:street":"Monterey Dr",
    "iso:country":"US",
    "sg:address":"5945 Monterey Dr",
    "sg:city":"Morrow",
    "sg:classifiers":[
        {
            "category":"Organizations",
            "subcategory":"Community Association",
            "type":"Services"
        }
    ],
    "sg:phone":"+1 770 968 6518",
    "sg:postcode":"30260",
    "sg:province":"GA",
    "wof:name":"Young Women Christian Council",
    "wof:placetype":"venue"
},
  "geometry": {"coordinates":[-84.347039,33.593385],"type":"Point"}
}