{
  "type": "Feature",
  "properties": {
    "addr:full":"1870 Harrietts Bluff Rd Woodbine GA 31569",
    "addr:housenumber":"1870",
    "addr:postcode":"31569",
    "addr:street":"Harrietts Bluff Rd",
    "iso:country":"US",
    "sg:address":"1870 Harrietts Bluff Rd",
    "sg:city":"Woodbine",
    "sg:classifiers":[
        {
            "category":"Fast Food",
            "type":"Food & Drink"
        },
        {
            "category":"Restaurant",
            "type":"Food & Drink"
        },
        {
            "category":"Food & Beverages",
            "subcategory":"Groceries & Convenience Stores",
            "type":"Retail Goods"
        }
    ],
    "sg:phone":"+1 912 673 1043",
    "sg:postcode":"31569",
    "sg:province":"GA",
    "sg:tags":[
        "shop",
        "american",
        "sandwich",
        "take"
    ],
    "sg:website":"http://www.subway.com",
    "wof:name":"Subway",
    "wof:placetype":"venue"
},
  "geometry": {"coordinates":[-81.668814,30.84837],"type":"Point"}
}