{
  "type": "Feature",
  "properties": {
    "addr:full":"2 Northside 75 NW Atlanta GA 30318",
    "addr:housenumber":"2;75",
    "addr:postcode":"30318",
    "addr:street":"Northside;Nw",
    "iso:country":"US",
    "sg:address":"2 Northside 75 NW",
    "sg:city":"Atlanta",
    "sg:classifiers":[
        {
            "category":"Deli",
            "type":"Food & Drink"
        },
        {
            "category":"Restaurant",
            "type":"Food & Drink"
        }
    ],
    "sg:phone":"+1 404 351 4921",
    "sg:postcode":"30318",
    "sg:province":"GA",
    "sg:tags":[
        "delicatessen",
        "american"
    ],
    "wof:name":"Corner Kitchen",
    "wof:placetype":"venue"
},
  "geometry": {"coordinates":[-84.40778,33.800176],"type":"Point"}
}