{
  "type": "Feature",
  "properties": {
    "addr:full":"2260 Moon Station Ct NW Kennesaw GA 30144",
    "addr:housenumber":"2260",
    "addr:postcode":"30144",
    "addr:street":"Moon Station Ct Nw",
    "iso:country":"US",
    "sg:address":"2260 Moon Station Ct NW",
    "sg:city":"Kennesaw",
    "sg:classifiers":[
        {
            "category":"Building & Trades",
            "subcategory":"Plumbing",
            "type":"Services"
        }
    ],
    "sg:phone":"+1 770 425 8779",
    "sg:postcode":"30144",
    "sg:province":"GA",
    "sg:tags":[
        "conditioning",
        "contractor",
        "system",
        "air"
    ],
    "wof:name":"D Mc Keon Heating & Air Cond",
    "wof:placetype":"venue"
},
  "geometry": {"coordinates":[-84.61690400000001,34.040512],"type":"Point"}
}