{
  "type": "Feature",
  "properties": {
    "addr:full":"3760 Baccurate Way Marietta GA 30062",
    "addr:housenumber":"3760",
    "addr:postcode":"30062",
    "addr:street":"Baccurate Way",
    "iso:country":"US",
    "sg:address":"3760 Baccurate Way",
    "sg:city":"Marietta",
    "sg:classifiers":[
        {
            "category":"Building & Trades",
            "subcategory":"Construction",
            "type":"Services"
        }
    ],
    "sg:phone":"+1 404 267 6829",
    "sg:postcode":"30062",
    "sg:province":"GA",
    "sg:tags":[
        "masonry",
        "industrial",
        "contractors-commercial"
    ],
    "wof:name":"Curbscapes of Atlanta",
    "wof:placetype":"venue"
},
  "geometry": {"coordinates":[-84.43883599999999,34.019216],"type":"Point"}
}