{
  "type": "Feature",
  "properties": {
    "iso:country":"US",
    "sg:address":"6505 Highway 85",
    "sg:city":"Riverdale",
    "sg:classifiers":[
        {
            "category":"Food & Beverages",
            "subcategory":"Groceries & Convenience Stores",
            "type":"Retail Goods"
        }
    ],
    "sg:phone":"+1 770 997 1770",
    "sg:postcode":"30274",
    "sg:province":"GA",
    "wof:name":"El Camercio Mexican Market",
    "wof:placetype":"venue"
},
  "geometry": {"coordinates":[-84.411903,33.577499],"type":"Point"}
}