{
  "type": "Feature",
  "properties": {
    "iso:country":"US",
    "sg:address":"7340 Lester Rd",
    "sg:city":"Union City",
    "sg:classifiers":[
        {
            "category":"Insurance",
            "subcategory":"Insurance Agent",
            "type":"Services"
        }
    ],
    "sg:phone":"+1 770 969 5303",
    "sg:postcode":"30291",
    "sg:province":"GA",
    "sg:tags":[
        "accident"
    ],
    "wof:name":"Care Entree'",
    "wof:placetype":"venue"
},
  "geometry": {"coordinates":[-84.52471799999999,33.55435],"type":"Point"}
}