{
  "type": "Feature",
  "properties": {
    "addr:full":"166 1st Ave Arabi GA 31712",
    "addr:housenumber":"166",
    "addr:postcode":"31712",
    "addr:street":"1St Ave",
    "iso:country":"US",
    "sg:address":"166 1st Ave",
    "sg:city":"Arabi",
    "sg:classifiers":[
        {
            "category":"Insurance",
            "subcategory":"Insurance Agent",
            "type":"Services"
        }
    ],
    "sg:phone":"+1 229 273 5881",
    "sg:postcode":"31712",
    "sg:province":"GA",
    "wof:name":"AFLAC",
    "wof:placetype":"venue"
},
  "geometry": {"coordinates":[-83.741519,31.829596],"type":"Point"}
}