{
  "type": "Feature",
  "properties": {
    "addr:full":"250 Rope Mill Rd Woodstock GA 30188",
    "addr:housenumber":"250",
    "addr:postcode":"30188",
    "addr:street":"Rope Mill Rd",
    "iso:country":"US",
    "sg:address":"250 Rope Mill Rd",
    "sg:city":"Woodstock",
    "sg:classifiers":[
        {
            "category":"Building & Trades",
            "subcategory":"Construction",
            "type":"Services"
        }
    ],
    "sg:phone":"+1 770 591 1234",
    "sg:postcode":"30188",
    "sg:province":"GA",
    "sg:tags":[
        "tile",
        "dealer"
    ],
    "wof:name":"Cherokee Tile Distributors Inc",
    "wof:placetype":"venue"
},
  "geometry": {"coordinates":[-84.527298,34.112094],"type":"Point"}
}