{
  "type": "Feature",
  "properties": {
    "iso:country":"US",
    "sg:address":"4054 N Valdosta Rd",
    "sg:city":"Valdosta",
    "sg:classifiers":[
        {
            "category":"Retail",
            "subcategory":"Auto Rental",
            "type":"Services"
        }
    ],
    "sg:phone":"+1 229 247 5556",
    "sg:postcode":"31602",
    "sg:province":"GA",
    "sg:tags":[
        "passenger",
        "car"
    ],
    "wof:name":"Buggy Works",
    "wof:placetype":"venue"
},
  "geometry": {"coordinates":[-83.323408,30.897101],"type":"Point"}
}