{
  "type": "Feature",
  "properties": {
    "iso:country":"US",
    "sg:address":"1197 Alpharetta Hwy",
    "sg:city":"Roswell",
    "sg:classifiers":[
        {
            "category":"Autos & Motor Vehicles",
            "subcategory":"Automobile Sales",
            "type":"Retail Goods"
        }
    ],
    "sg:phone":"+1 770 649 9997",
    "sg:postcode":"30075",
    "sg:province":"GA",
    "sg:tags":[
        "car",
        "used",
        "dealer"
    ],
    "wof:name":"Roswell Auto Imports Inc",
    "wof:placetype":"venue"
},
  "geometry": {"coordinates":[-84.349858,34.033044],"type":"Point"}
}