{
  "type": "Feature",
  "properties": {
    "iso:country":"US",
    "sg:address":"1305 1st St NE",
    "sg:city":"Moultrie",
    "sg:classifiers":[
        {
            "category":"Food & Beverages",
            "subcategory":"Groceries & Convenience Stores",
            "type":"Retail Goods"
        }
    ],
    "sg:phone":"+1 229 985 1488",
    "sg:postcode":"31768",
    "sg:province":"GA",
    "sg:tags":[
        "station",
        "gas"
    ],
    "wof:name":"Larry's Quick Stop",
    "wof:placetype":"venue"
},
  "geometry": {"coordinates":[-83.78769200000001,31.193516],"type":"Point"}
}