{
  "type": "Feature",
  "properties": {
    "addr:full":"3755 Memorial Dr Decatur GA 30032",
    "addr:housenumber":"3755",
    "addr:postcode":"30032",
    "addr:street":"Memorial Dr",
    "iso:country":"US",
    "sg:address":"3755 Memorial Dr",
    "sg:city":"Decatur",
    "sg:classifiers":[
        {
            "category":"Building & Trades",
            "subcategory":"Construction",
            "type":"Services"
        }
    ],
    "sg:phone":"+1 404 289 1588",
    "sg:postcode":"30032",
    "sg:province":"GA",
    "sg:tags":[
        "general",
        "contractor"
    ],
    "wof:name":"Lavish Lifestyle General Contr",
    "wof:placetype":"venue"
},
  "geometry": {"coordinates":[-84.26050600000001,33.760266],"type":"Point"}
}