{
  "type": "Feature",
  "properties": {
    "addr:full":"3056 Anvil Block Rd Ellenwood GA 30294",
    "addr:housenumber":"3056",
    "addr:postcode":"30294",
    "addr:street":"Anvil Block Rd",
    "iso:country":"US",
    "sg:address":"3056 Anvil Block Rd",
    "sg:city":"Ellenwood",
    "sg:classifiers":[
        {
            "category":"Shopping",
            "subcategory":"Department Store",
            "type":"Retail Goods"
        },
        {
            "category":"Shopping",
            "type":"Retail Goods"
        },
        {
            "category":"Shopping",
            "subcategory":"Discount & Variety Stores",
            "type":"Retail Goods"
        }
    ],
    "sg:phone":"+1 404 675 9830",
    "sg:postcode":"30294",
    "sg:province":"GA",
    "sg:tags":[
        "merchandise"
    ],
    "sg:website":"http://www.dollartree.com/",
    "wof:name":"Dollar Tree",
    "wof:placetype":"venue"
},
  "geometry": {"coordinates":[-84.28862700000001,33.633735],"type":"Point"}
}