{
  "type": "Feature",
  "properties": {
    "addr:full":"1385 Cherokee Trl NW Lawrenceville GA 30043",
    "addr:housenumber":"1385",
    "addr:postcode":"30043",
    "addr:street":"Cherokee Trl Nw",
    "iso:country":"US",
    "sg:address":"1385 Cherokee Trl NW",
    "sg:city":"Lawrenceville",
    "sg:classifiers":[
        {
            "category":"Professional",
            "type":"Services"
        }
    ],
    "sg:phone":"+1 770 822 1043",
    "sg:postcode":"30043",
    "sg:province":"GA",
    "wof:name":"Paul Lee Hang",
    "wof:placetype":"venue"
},
  "geometry": {"coordinates":[-84.046341,33.965212],"type":"Point"}
}