{
  "type": "Feature",
  "properties": {
    "iso:country":"US",
    "sg:address":"1197 Dustin Ct",
    "sg:city":"Stone Mountain",
    "sg:classifiers":[
        {
            "category":"Shopping",
            "subcategory":"Hobbies, Toys, & Games",
            "type":"Retail Goods"
        }
    ],
    "sg:phone":"+1 770 879 9815",
    "sg:postcode":"30088",
    "sg:province":"GA",
    "wof:name":"Silks By Andrianne",
    "wof:placetype":"venue"
},
  "geometry": {"coordinates":[-84.16712099999999,33.758947],"type":"Point"}
}