{
  "type": "Feature",
  "properties": {
    "iso:country":"US",
    "sg:address":"1301 Parkaire Xing",
    "sg:city":"Marietta",
    "sg:classifiers":[
        {
            "category":"Professional",
            "subcategory":"Business Services",
            "type":"Services"
        }
    ],
    "sg:phone":"+1 770 509 1105",
    "sg:postcode":"30068",
    "sg:province":"GA",
    "wof:name":"Montague Home Inspections",
    "wof:placetype":"venue"
},
  "geometry": {"coordinates":[-84.404472,33.965124],"type":"Point"}
}