{
  "type": "Feature",
  "properties": {
    "addr:full":"3202 Northlake Pkwy Tucker GA 30084",
    "addr:housenumber":"3202",
    "addr:postcode":"30084",
    "addr:street":"Northlake Pkwy",
    "iso:country":"US",
    "sg:address":"3202 Northlake Pkwy",
    "sg:city":"Tucker",
    "sg:classifiers":[
        {
            "category":"Building & Trades",
            "subcategory":"Locksmith",
            "type":"Services"
        }
    ],
    "sg:phone":"+1 678 269 7149",
    "sg:postcode":"30084",
    "sg:province":"GA",
    "sg:tags":[
        "key"
    ],
    "wof:name":"555 Emergency Locksmith",
    "wof:placetype":"venue"
},
  "geometry": {"coordinates":[-84.246073,33.851128],"type":"Point"}
}