{
  "type": "Feature",
  "properties": {
    "addr:full":"428 Rawley Rd Americus GA 31719",
    "addr:housenumber":"428",
    "addr:postcode":"31719",
    "addr:street":"Rawley Rd",
    "iso:country":"US",
    "sg:address":"428 Rawley Rd",
    "sg:city":"Americus",
    "sg:classifiers":[
        {
            "category":"Professional",
            "subcategory":"Art Services",
            "type":"Services"
        }
    ],
    "sg:phone":"+1 229 924 2580",
    "sg:postcode":"31719",
    "sg:province":"GA",
    "sg:tags":[
        "photography",
        "commercial"
    ],
    "wof:name":"Southern Exposures",
    "wof:placetype":"venue"
},
  "geometry": {"coordinates":[-84.251605,32.099396],"type":"Point"}
}