{
  "type": "Feature",
  "properties": {
    "addr:full":"1212 N Peterson Ave Douglas GA 31533",
    "addr:housenumber":"1212",
    "addr:postcode":"31533",
    "addr:street":"N Peterson Ave",
    "iso:country":"US",
    "sg:address":"1212 N Peterson Ave",
    "sg:city":"Douglas",
    "sg:classifiers":[
        {
            "category":"Shopping",
            "type":"Retail Goods"
        }
    ],
    "sg:phone":"+1 912 393 3630",
    "sg:postcode":"31533",
    "sg:province":"GA",
    "sg:tags":[
        "ice"
    ],
    "wof:name":"H & P Ice Co",
    "wof:placetype":"venue"
},
  "geometry": {"coordinates":[-82.850413,31.52284],"type":"Point"}
}