{
  "type": "Feature",
  "properties": {
    "addr:full":"1147 Veterans Memorial Hwy SW Mableton GA 30126",
    "addr:housenumber":"1147",
    "addr:postcode":"30126",
    "addr:street":"Veterans Memorial Hwy Sw",
    "iso:country":"US",
    "sg:address":"1147 Veterans Memorial Hwy SW",
    "sg:city":"Mableton",
    "sg:classifiers":[
        {
            "category":"Insurance",
            "subcategory":"Hazard Insurance",
            "type":"Services"
        }
    ],
    "sg:phone":"+1 770 819 0404",
    "sg:postcode":"30126",
    "sg:province":"GA",
    "sg:tags":[
        "commercial",
        "business"
    ],
    "wof:name":"Metrowide Insurance Agency Inc",
    "wof:placetype":"venue"
},
  "geometry": {"coordinates":[-84.58801200000001,33.817383],"type":"Point"}
}