{
  "type": "Feature",
  "properties": {
    "addr:full":"929 Zion Cir Roswell GA 30075",
    "addr:housenumber":"929",
    "addr:postcode":"30075",
    "addr:street":"Zion Cir",
    "iso:country":"US",
    "sg:address":"929 Zion Cir",
    "sg:city":"Roswell",
    "sg:classifiers":[
        {
            "category":"Education",
            "subcategory":"School",
            "type":"Public Place"
        }
    ],
    "sg:phone":"+1 770 993 0207",
    "sg:postcode":"30075",
    "sg:province":"GA",
    "sg:tags":[
        "high",
        "middle",
        "elementary"
    ],
    "wof:name":"A Cps Inc At Zion Missionary Baptist Church",
    "wof:placetype":"venue"
},
  "geometry": {"coordinates":[-84.3545,34.023102],"type":"Point"}
}