{
  "type": "Feature",
  "properties": {
    "iso:country":"US",
    "sg:address":"2401 Dawson Rd",
    "sg:city":"Albany",
    "sg:classifiers":[
        {
            "category":"Shopping",
            "subcategory":"Clothing, Apparel, & Fashions",
            "type":"Retail Goods"
        }
    ],
    "sg:phone":"+1 229 888 2965",
    "sg:postcode":"31707",
    "sg:province":"GA",
    "sg:tags":[
        "infant",
        "wear",
        "furniture"
    ],
    "wof:name":"Classy Kids Consignment Shop",
    "wof:placetype":"venue"
},
  "geometry": {"coordinates":[-84.208124,31.60711],"type":"Point"}
}