{
  "type": "Feature",
  "properties": {
    "addr:full":"906 Pointe Cir Woodstock GA 30188",
    "addr:housenumber":"906",
    "addr:postcode":"30188",
    "addr:street":"Pointe Cir",
    "iso:country":"US",
    "sg:address":"906 Pointe Cir",
    "sg:city":"Woodstock",
    "sg:classifiers":[
        {
            "category":"Health Services",
            "subcategory":"Health Practitioner",
            "type":"Services"
        }
    ],
    "sg:phone":"+1 678 445 4010",
    "sg:postcode":"30188",
    "sg:province":"GA",
    "sg:tags":[
        "occupational",
        "therapist"
    ],
    "wof:name":"IRC",
    "wof:placetype":"venue"
},
  "geometry": {"coordinates":[-84.430257,34.074194],"type":"Point"}
}