{
  "type": "Feature",
  "properties": {
    "iso:country":"US",
    "sg:address":"405 Dock Lathem Trl",
    "sg:city":"Ball Ground",
    "sg:classifiers":[
        {
            "category":"Building & Trades",
            "subcategory":"Construction",
            "type":"Services"
        }
    ],
    "sg:phone":"+1 770 479 7980",
    "sg:postcode":"30107",
    "sg:province":"GA",
    "sg:tags":[
        "carpentry",
        "contractor"
    ],
    "wof:name":"Champlins Custom Carpentry",
    "wof:placetype":"venue"
},
  "geometry": {"coordinates":[-84.353534,34.263194],"type":"Point"}
}