{
  "type": "Feature",
  "properties": {
    "addr:full":"505 Brookford Ct SW Atlanta GA 30331",
    "addr:housenumber":"505",
    "addr:postcode":"30331",
    "addr:street":"Brookford Ct Sw",
    "iso:country":"US",
    "sg:address":"505 Brookford Ct SW",
    "sg:city":"Atlanta",
    "sg:classifiers":[
        {
            "category":"Community Center",
            "subcategory":"Youth",
            "type":"Public Place"
        }
    ],
    "sg:phone":"+1 770 238 9495",
    "sg:postcode":"30331",
    "sg:province":"GA",
    "wof:name":"Milford Youth Organization",
    "wof:placetype":"venue"
},
  "geometry": {"coordinates":[-84.60368699999999,33.680149],"type":"Point"}
}