{
  "type": "Feature",
  "properties": {
    "addr:full":"550 Welcome Hill Rd Trion GA 30753",
    "addr:housenumber":"550",
    "addr:postcode":"30753",
    "addr:street":"Welcome Hill Rd",
    "iso:country":"US",
    "sg:address":"550 Welcome Hill Rd",
    "sg:city":"Trion",
    "sg:classifiers":[
        {
            "category":"Manufacturing",
            "subcategory":"Buildings",
            "type":"Manufacturing & Wholesale Goods"
        },
        {
            "category":"Building & Trades",
            "subcategory":"Construction",
            "type":"Services"
        }
    ],
    "sg:phone":"+1 706 734 2711",
    "sg:postcode":"30753",
    "sg:province":"GA",
    "sg:tags":[
        "home",
        "builder",
        "contractor"
    ],
    "wof:name":"Broyles Construction",
    "wof:placetype":"venue"
},
  "geometry": {"coordinates":[-85.315701,34.568724],"type":"Point"}
}