{
  "type": "Feature",
  "properties": {
    "iso:country":"US",
    "sg:address":"2063 Westwood Rd SE",
    "sg:city":"Smyrna",
    "sg:classifiers":[
        {
            "category":"Professional",
            "type":"Services"
        }
    ],
    "sg:phone":"+1 770 789 2730",
    "sg:postcode":"30080",
    "sg:province":"GA",
    "wof:name":"Halco Services Inc",
    "wof:placetype":"venue"
},
  "geometry": {"coordinates":[-84.493914,33.858561],"type":"Point"}
}