{
  "type": "Feature",
  "properties": {
    "iso:country":"US",
    "sg:address":"2000 Southpoint Dr",
    "sg:city":"Forest Park",
    "sg:classifiers":[
        {
            "category":"Professional",
            "type":"Services"
        }
    ],
    "sg:phone":"+1 404 675 1025",
    "sg:postcode":"30297",
    "sg:province":"GA",
    "sg:tags":[
        "establishment"
    ],
    "wof:name":"Amerisource",
    "wof:placetype":"venue"
},
  "geometry": {"coordinates":[-84.3828,33.631651],"type":"Point"}
}