{
  "type": "Feature",
  "properties": {
    "addr:full":"1670 Defoor Ave NW Atlanta GA 30318",
    "addr:housenumber":"1670",
    "addr:postcode":"30318",
    "addr:street":"Defoor Ave Nw",
    "iso:country":"US",
    "sg:address":"1670 Defoor Ave NW",
    "sg:city":"Atlanta",
    "sg:classifiers":[
        {
            "category":"Building & Trades",
            "subcategory":"Construction",
            "type":"Services"
        }
    ],
    "sg:phone":"+1 678 352 0716",
    "sg:postcode":"30318",
    "sg:province":"GA",
    "sg:tags":[
        "home",
        "builder"
    ],
    "wof:name":"Home Providers",
    "wof:placetype":"venue"
},
  "geometry": {"coordinates":[-84.418207,33.800644],"type":"Point"}
}