{
  "type": "Feature",
  "properties": {
    "addr:full":"3425 Cascade Rd SW Atlanta GA 30311",
    "addr:housenumber":"3425",
    "addr:postcode":"30311",
    "addr:street":"Cascade Rd Sw",
    "iso:country":"US",
    "sg:address":"3425 Cascade Rd SW",
    "sg:city":"Atlanta",
    "sg:classifiers":[
        {
            "category":"Building & Trades",
            "subcategory":"Locksmith",
            "type":"Services"
        }
    ],
    "sg:phone":"+1 678 321 4617",
    "sg:postcode":"30311",
    "sg:province":"GA",
    "sg:tags":[
        "key"
    ],
    "wof:name":"7 Days Emergency Locksmith",
    "wof:placetype":"venue"
},
  "geometry": {"coordinates":[-84.499528,33.722919],"type":"Point"}
}