{
  "type": "Feature",
  "properties": {
    "addr:full":"384 Hansell Chastain Rd Thomasville GA 31757",
    "addr:housenumber":"384",
    "addr:postcode":"31757",
    "addr:street":"Hansell Chastain Rd",
    "iso:country":"US",
    "sg:address":"384 Hansell Chastain Rd",
    "sg:city":"Thomasville",
    "sg:classifiers":[
        {
            "category":"Wholesale",
            "subcategory":"Construction Materials",
            "type":"Manufacturing & Wholesale Goods"
        }
    ],
    "sg:phone":"+1 229 226 9623",
    "sg:postcode":"31757",
    "sg:province":"GA",
    "sg:tags":[
        "stakes"
    ],
    "wof:name":"Sowega Stake",
    "wof:placetype":"venue"
},
  "geometry": {"coordinates":[-83.959998,30.938646],"type":"Point"}
}