{
  "type": "Feature",
  "properties": {
    "iso:country":"US",
    "sg:address":"213 W Point Rd",
    "sg:city":"Saint Simons Island",
    "sg:classifiers":[
        {
            "category":"Professional",
            "type":"Services"
        }
    ],
    "sg:phone":"+1 912 634 1386",
    "sg:postcode":"31522",
    "sg:province":"GA",
    "sg:tags":[
        "merchandise"
    ],
    "wof:name":"Caseys Designs",
    "wof:placetype":"venue"
},
  "geometry": {"coordinates":[-81.38771699999999,31.233137],"type":"Point"}
}