{
  "type": "Feature",
  "properties": {
    "iso:country":"US",
    "sg:address":"5104 N Henry Blvd",
    "sg:city":"Stockbridge",
    "sg:classifiers":[
        {
            "category":"Shopping",
            "subcategory":"Party Supplies",
            "type":"Retail Goods"
        },
        {
            "category":"Shopping",
            "type":"Retail Goods"
        },
        {
            "category":"Sports & Exercise",
            "subcategory":"Swimming Pool",
            "type":"Entertainment"
        }
    ],
    "sg:phone":"+1 770 389 9949",
    "sg:postcode":"30281",
    "sg:province":"GA",
    "sg:tags":[
        "charter",
        "divers'",
        "favors",
        "instruction",
        "equipment",
        "diving",
        "excursion"
    ],
    "sg:website":"http://www.wetsetscuba.com",
    "wof:name":"Wet Set Scuba & Swimming",
    "wof:placetype":"venue"
},
  "geometry": {"coordinates":[-84.245165,33.545112],"type":"Point"}
}