{
  "type": "Feature",
  "properties": {
    "iso:country":"US",
    "sg:address":"5000 Austell Powder Springs Rd",
    "sg:city":"Austell",
    "sg:classifiers":[
        {
            "category":"Real Estate",
            "subcategory":"Real Estate Agent",
            "type":"Services"
        }
    ],
    "sg:phone":"+1 770 222 0953",
    "sg:postcode":"30106",
    "sg:province":"GA",
    "wof:name":"Integrealty Inc",
    "wof:placetype":"venue"
},
  "geometry": {"coordinates":[-84.65400099999999,33.832159],"type":"Point"}
}