{
  "type": "Feature",
  "properties": {
    "addr:full":"618 Oaktree Park Ct NW Lawrenceville GA 30044",
    "addr:housenumber":"618",
    "addr:postcode":"30044",
    "addr:street":"Oaktree Park Ct Nw",
    "iso:country":"US",
    "sg:address":"618 Oaktree Park Ct NW",
    "sg:city":"Lawrenceville",
    "sg:classifiers":[
        {
            "category":"Organizations",
            "subcategory":"Religious Organization",
            "type":"Services"
        }
    ],
    "sg:phone":"+1 770 638 4801",
    "sg:postcode":"30044",
    "sg:province":"GA",
    "wof:name":"Cong Khana",
    "wof:placetype":"venue"
},
  "geometry": {"coordinates":[-84.096158,33.923158],"type":"Point"}
}