{
  "type": "Feature",
  "properties": {
    "iso:country":"US",
    "sg:address":"139 Moran Lake Rd NE",
    "sg:city":"Rome",
    "sg:classifiers":[
        {
            "category":"Health Services",
            "subcategory":"Nursing And Care Facility",
            "type":"Services"
        }
    ],
    "sg:phone":"+1 706 291 8212",
    "sg:postcode":"30161",
    "sg:province":"GA",
    "sg:tags":[
        "skilled"
    ],
    "wof:name":"Sunpointe",
    "wof:placetype":"venue"
},
  "geometry": {"coordinates":[-85.11107800000001,34.25813],"type":"Point"}
}