{
  "type": "Feature",
  "properties": {
    "iso:country":"US",
    "sg:address":"892 Ponce de Leon Ave NE",
    "sg:city":"Atlanta",
    "sg:classifiers":[
        {
            "category":"Professional",
            "subcategory":"Management & Consulting",
            "type":"Services"
        }
    ],
    "sg:phone":"+1 404 932 8143",
    "sg:postcode":"30306",
    "sg:province":"GA",
    "sg:tags":[
        "business"
    ],
    "wof:name":"Small Wonders Consulting",
    "wof:placetype":"venue"
},
  "geometry": {"coordinates":[-84.357642,33.773892],"type":"Point"}
}