{
  "type": "Feature",
  "properties": {
    "addr:full":"2322 Goodwood Blvd SE Smyrna GA 30080",
    "addr:housenumber":"2322",
    "addr:postcode":"30080",
    "addr:street":"Goodwood Blvd Se",
    "iso:country":"US",
    "sg:address":"2322 Goodwood Blvd SE",
    "sg:city":"Smyrna",
    "sg:classifiers":[
        {
            "category":"Wholesale",
            "subcategory":"Machinery & Supplies",
            "type":"Manufacturing & Wholesale Goods"
        }
    ],
    "sg:phone":"+1 770 319 1901",
    "sg:postcode":"30080",
    "sg:province":"GA",
    "sg:tags":[
        "sales"
    ],
    "wof:name":"Filters For Industry Inc",
    "wof:placetype":"venue"
},
  "geometry": {"coordinates":[-84.49362600000001,33.877772],"type":"Point"}
}