{
  "type": "Feature",
  "properties": {
    "iso:country":"US",
    "sg:address":"333 Daniel St",
    "sg:city":"Americus",
    "sg:classifiers":[
        {
            "category":"Building & Trades",
            "subcategory":"Construction",
            "type":"Services"
        }
    ],
    "sg:phone":"+1 229 924 4620",
    "sg:postcode":"31709",
    "sg:province":"GA",
    "sg:tags":[
        "contractor"
    ],
    "wof:name":"Cooperative Contracting Svcs",
    "wof:placetype":"venue"
},
  "geometry": {"coordinates":[-84.231741,32.053156],"type":"Point"}
}