{
  "type": "Feature",
  "properties": {
    "addr:full":"1641 Collins Rd NW Kennesaw GA 30152",
    "addr:housenumber":"1641",
    "addr:postcode":"30152",
    "addr:street":"Collins Rd Nw",
    "iso:country":"US",
    "sg:address":"1641 Collins Rd NW",
    "sg:city":"Kennesaw",
    "sg:classifiers":[
        {
            "category":"Building & Trades",
            "subcategory":"Locksmith",
            "type":"Services"
        }
    ],
    "sg:phone":"+1 877 807 6806",
    "sg:postcode":"30152",
    "sg:province":"GA",
    "sg:tags":[
        "key"
    ],
    "wof:name":"A 1 Emergency Locksmith",
    "wof:placetype":"venue"
},
  "geometry": {"coordinates":[-84.59872300000001,33.992391],"type":"Point"}
}