{
  "type": "Feature",
  "properties": {
    "iso:country":"US",
    "sg:address":"840 S Laurel St",
    "sg:city":"Springfield",
    "sg:classifiers":[
        {
            "category":"Fast Food",
            "type":"Food & Drink"
        }
    ],
    "sg:phone":"+1 912 754 6633",
    "sg:postcode":"31329",
    "sg:province":"GA",
    "sg:tags":[
        "restaurant"
    ],
    "wof:name":"Dairy Queen",
    "wof:placetype":"venue"
},
  "geometry": {"coordinates":[-81.30612499999999,32.361929],"type":"Point"}
}