{
  "type": "Feature",
  "properties": {
    "addr:full":"839 Fireside Way Stone Mountain GA 30083",
    "addr:housenumber":"839",
    "addr:postcode":"30083",
    "addr:street":"Fireside Way",
    "iso:country":"US",
    "sg:address":"839 Fireside Way",
    "sg:city":"Stone Mountain",
    "sg:classifiers":[
        {
            "category":"Social Services",
            "subcategory":"Adult Care",
            "type":"Services"
        }
    ],
    "sg:phone":"+1 404 294 7353",
    "sg:postcode":"30083",
    "sg:province":"GA",
    "sg:tags":[
        "residential"
    ],
    "wof:name":"Classic Community Support",
    "wof:placetype":"venue"
},
  "geometry": {"coordinates":[-84.20281,33.803436],"type":"Point"}
}