{
  "type": "Feature",
  "properties": {
    "iso:country":"US",
    "sg:address":"234 Norwood Ave NE",
    "sg:city":"Atlanta",
    "sg:classifiers":[
        {
            "category":"Professional",
            "type":"Services"
        }
    ],
    "sg:phone":"+1 404 378 8828",
    "sg:postcode":"30317",
    "sg:province":"GA",
    "wof:name":"Labrador Inc",
    "wof:placetype":"venue"
},
  "geometry": {"coordinates":[-84.320165,33.758533],"type":"Point"}
}