{
  "type": "Feature",
  "properties": {
    "iso:country":"US",
    "sg:address":"603 N Elm St",
    "sg:city":"Dalton",
    "sg:classifiers":[
        {
            "category":"Wholesale",
            "subcategory":"Home Furnishings",
            "type":"Manufacturing & Wholesale Goods"
        }
    ],
    "sg:phone":"+1 706 270 9486",
    "sg:postcode":"30721",
    "sg:province":"GA",
    "sg:tags":[
        "rug",
        "carpet"
    ],
    "wof:name":"Garland Sales",
    "wof:placetype":"venue"
},
  "geometry": {"coordinates":[-84.962345,34.781868],"type":"Point"}
}