{
  "type": "Feature",
  "properties": {
    "iso:country":"US",
    "sg:address":"5002 Snapfinger Woods Dr",
    "sg:city":"Decatur",
    "sg:classifiers":[
        {
            "category":"Organizations",
            "subcategory":"Religious Organization",
            "type":"Services"
        }
    ],
    "sg:phone":"+1 770 322 0422",
    "sg:postcode":"30035",
    "sg:province":"GA",
    "wof:name":"Salon Epiphany By BKB",
    "wof:placetype":"venue"
},
  "geometry": {"coordinates":[-84.182002,33.711258],"type":"Point"}
}