{
  "type": "Feature",
  "properties": {
    "addr:full":"235 Peachtree St NE Ste 200 Atlanta GA 30303",
    "addr:housenumber":"235",
    "addr:postcode":"30303",
    "addr:street":"Peachtree St Ne Ste 200",
    "iso:country":"US",
    "sg:address":"235 Peachtree St NE Ste 200",
    "sg:city":"Atlanta",
    "sg:classifiers":[
        {
            "category":"Professional",
            "subcategory":"Lawyer & Legal Services",
            "type":"Services"
        }
    ],
    "sg:phone":"+1 404 659 7799",
    "sg:postcode":"30303",
    "sg:province":"GA",
    "wof:name":"Freidman Stephen A Atty",
    "wof:placetype":"venue"
},
  "geometry": {"coordinates":[-84.386703,33.763302],"type":"Point"}
}