{
  "type": "Feature",
  "properties": {
    "addr:full":"3742 Sugar Valley Rd NW Sugar Valley GA 30746",
    "addr:housenumber":"3742",
    "addr:postcode":"30746",
    "addr:street":"Sugar Valley Rd Nw",
    "iso:country":"US",
    "sg:address":"3742 Sugar Valley Rd NW",
    "sg:city":"Sugar Valley",
    "sg:classifiers":[
        {
            "category":"Organizations",
            "subcategory":"Religious Organization",
            "type":"Services"
        }
    ],
    "sg:phone":"+1 706 629 0893",
    "sg:postcode":"30746",
    "sg:province":"GA",
    "sg:tags":[
        "church"
    ],
    "wof:name":"Sugar Valley First Baptist Chr",
    "wof:placetype":"venue"
},
  "geometry": {"coordinates":[-85.024502,34.571399],"type":"Point"}
}