{
  "type": "Feature",
  "properties": {
    "iso:country":"US",
    "sg:address":"PO Box 957983",
    "sg:city":"Duluth",
    "sg:classifiers":[
        {
            "category":"Building & Trades",
            "subcategory":"Cleaning & Sanitation",
            "type":"Services"
        }
    ],
    "sg:phone":"+1 770 912 4123",
    "sg:postcode":"30095",
    "sg:province":"GA",
    "sg:tags":[
        "carpet"
    ],
    "wof:name":"A 1 Drs Carpet Cleaning Service",
    "wof:placetype":"venue"
},
  "geometry": {"coordinates":[-84.134697,33.959],"type":"Point"}
}