{
  "type": "Feature",
  "properties": {
    "iso:country":"US",
    "sg:address":"1204 Swift St",
    "sg:city":"Perry",
    "sg:classifiers":[
        {
            "category":"Travel",
            "subcategory":"Hotels & Motels",
            "type":"Entertainment"
        }
    ],
    "sg:phone":"+1 478 988 9148",
    "sg:postcode":"31069",
    "sg:province":"GA",
    "sg:tags":[
        "breakfast",
        "accommodation",
        "bed"
    ],
    "wof:name":"Swift Street Inn",
    "wof:placetype":"venue"
},
  "geometry": {"coordinates":[-83.726772,32.461598],"type":"Point"}
}