{
  "type": "Feature",
  "properties": {
    "iso:country":"US",
    "sg:address":"6725 Jimmy Carter Blvd",
    "sg:city":"Norcross",
    "sg:classifiers":[
        {
            "category":"Manufacturing",
            "subcategory":"Printing",
            "type":"Manufacturing & Wholesale Goods"
        }
    ],
    "sg:phone":"+1 770 448 4165",
    "sg:postcode":"30071",
    "sg:province":"GA",
    "sg:tags":[
        "printer"
    ],
    "sg:website":"www.theflyeralternative.com",
    "wof:name":"Brandon's Printing",
    "wof:placetype":"venue"
},
  "geometry": {"coordinates":[-84.23612799999999,33.939072],"type":"Point"}
}