{
  "type": "Feature",
  "properties": {
    "addr:full":"105 S Hill St Griffin GA 30224",
    "addr:housenumber":"105",
    "addr:postcode":"30224",
    "addr:street":"S Hill St",
    "iso:country":"US",
    "sg:address":"105 S Hill St",
    "sg:city":"Griffin",
    "sg:classifiers":[
        {
            "category":"Health Services",
            "subcategory":"Optometrist",
            "type":"Services"
        }
    ],
    "sg:phone":"+1 770 227 2346",
    "sg:postcode":"30224",
    "sg:province":"GA",
    "wof:name":"James E Clark",
    "wof:placetype":"venue"
},
  "geometry": {"coordinates":[-84.263818,33.248879],"type":"Point"}
}