{
  "type": "Feature",
  "properties": {
    "iso:country":"US",
    "sg:address":"881 Carlene Dr",
    "sg:city":"Harlem",
    "sg:classifiers":[
        {
            "category":"Shopping",
            "subcategory":"Discount & Variety Stores",
            "type":"Retail Goods"
        }
    ],
    "sg:phone":"+1 706 556 2500",
    "sg:postcode":"30814",
    "sg:province":"GA",
    "sg:tags":[
        "merchandise",
        "general"
    ],
    "wof:name":"Tanglefoots Treasures",
    "wof:placetype":"venue"
},
  "geometry": {"coordinates":[-82.262298,33.429019],"type":"Point"}
}