{
  "type": "Feature",
  "properties": {
    "addr:full":"610 Ridley Ave Lagrange GA 30240",
    "addr:housenumber":"610",
    "addr:postcode":"30240",
    "addr:street":"Ridley Ave",
    "iso:country":"US",
    "sg:address":"610 Ridley Ave",
    "sg:city":"Lagrange",
    "sg:classifiers":[
        {
            "category":"Education",
            "subcategory":"Special Training",
            "type":"Public Place"
        }
    ],
    "sg:phone":"+1 706 884 6668",
    "sg:postcode":"30240",
    "sg:province":"GA",
    "sg:tags":[
        "instruction",
        "driving"
    ],
    "wof:name":"Best Choice Dui School",
    "wof:placetype":"venue"
},
  "geometry": {"coordinates":[-85.029915,33.048455],"type":"Point"}
}