{
  "type": "Feature",
  "properties": {
    "iso:country":"US",
    "sg:address":"5200 Riverview Rd NW",
    "sg:city":"Atlanta",
    "sg:classifiers":[
        {
            "category":"Wholesale",
            "subcategory":"Machinery & Supplies",
            "type":"Manufacturing & Wholesale Goods"
        }
    ],
    "sg:phone":"+1 770 980 9757",
    "sg:postcode":"30327",
    "sg:province":"GA",
    "sg:tags":[
        "industrial"
    ],
    "wof:name":"Intelligent Graphics Systems",
    "wof:placetype":"venue"
},
  "geometry": {"coordinates":[-84.439896,33.894734],"type":"Point"}
}