{
  "type": "Feature",
  "properties": {
    "iso:country":"US",
    "sg:address":"1365 Pilgrim Mill Rd",
    "sg:city":"Cumming",
    "sg:classifiers":[
        {
            "category":"Autos & Motor Vehicles",
            "subcategory":"Auto Supplies",
            "type":"Retail Goods"
        },
        {
            "category":"Retail",
            "subcategory":"Auto Repair",
            "type":"Services"
        }
    ],
    "sg:phone":"+1 770 205 0905",
    "sg:postcode":"30040",
    "sg:province":"GA",
    "sg:tags":[
        "automobile",
        "part",
        "truck"
    ],
    "sg:website":"http://clickserve.dartsearch.net/link/click?lid=43000000313868763&ds_s_kwgid=58000000006820725&ds_e_matchtype={MatchType}&ds_e_kwdid={OrderItemId}&ds_e_adid={AdId}&ds_url_v=2",
    "wof:name":"North Georgia Radiator & Cooling",
    "wof:placetype":"venue"
},
  "geometry": {"coordinates":[-84.108734,34.227116],"type":"Point"}
}