{
  "type": "Feature",
  "properties": {
    "addr:full":"516 N Elm St Dalton GA 30721",
    "addr:housenumber":"516",
    "addr:postcode":"30721",
    "addr:street":"N Elm St",
    "iso:country":"US",
    "sg:address":"516 N Elm St",
    "sg:city":"Dalton",
    "sg:classifiers":[
        {
            "category":"Wholesale",
            "subcategory":"Durable Goods & Equipment",
            "type":"Manufacturing & Wholesale Goods"
        }
    ],
    "sg:phone":"+1 706 278 1250",
    "sg:postcode":"30721",
    "sg:province":"GA",
    "sg:tags":[
        "business"
    ],
    "wof:name":"Fire Extngsher Sls Svc of N GA",
    "wof:placetype":"venue"
},
  "geometry": {"coordinates":[-84.962233,34.779539],"type":"Point"}
}