{
  "type": "Feature",
  "properties": {
    "iso:country":"US",
    "sg:address":"4481 Jonesboro Rd",
    "sg:city":"Forest Park",
    "sg:classifiers":[
        {
            "category":"Deli",
            "type":"Food & Drink"
        }
    ],
    "sg:phone":"+1 404 608 8646",
    "sg:postcode":"30297",
    "sg:province":"GA",
    "wof:name":"American Deli",
    "wof:placetype":"venue"
},
  "geometry": {"coordinates":[-84.357201,33.632301],"type":"Point"}
}