{
  "type": "Feature",
  "properties": {
    "iso:country":"US",
    "sg:address":"3109 1st St",
    "sg:city":"Vidalia",
    "sg:classifiers":[
        {
            "category":"Restaurant",
            "type":"Food & Drink"
        }
    ],
    "sg:phone":"+1 912 537 8608",
    "sg:postcode":"30474",
    "sg:province":"GA",
    "wof:name":"Mc Donald's",
    "wof:placetype":"venue"
},
  "geometry": {"coordinates":[-82.403629,32.160918],"type":"Point"}
}