{
  "type": "Feature",
  "properties": {
    "iso:country":"US",
    "sg:address":"3991 Royal Dr NW",
    "sg:city":"Kennesaw",
    "sg:classifiers":[
        {
            "category":"Building & Trades",
            "subcategory":"Plumbing",
            "type":"Services"
        }
    ],
    "sg:phone":"+1 770 394 7159",
    "sg:postcode":"30144",
    "sg:province":"GA",
    "wof:name":"Superior Plumbing Services",
    "wof:placetype":"venue"
},
  "geometry": {"coordinates":[-84.604202,34.048698],"type":"Point"}
}