{
  "type": "Feature",
  "properties": {
    "iso:country":"US",
    "sg:address":"431 Commerce Park Dr SE Ste 106",
    "sg:city":"Marietta",
    "sg:classifiers":[
        {
            "category":"Shopping",
            "subcategory":"Pharmacy",
            "type":"Retail Goods"
        }
    ],
    "sg:phone":"+1 770 421 1399",
    "sg:postcode":"30060",
    "sg:province":"GA",
    "sg:tags":[
        "drugstore"
    ],
    "wof:name":"Miller Compounding Pharmacy",
    "wof:placetype":"venue"
},
  "geometry": {"coordinates":[-84.533798,33.941601],"type":"Point"}
}