{
  "type": "Feature",
  "properties": {
    "iso:country":"US",
    "sg:address":"3214 Summerstone Ln",
    "sg:city":"Kennesaw",
    "sg:classifiers":[
        {
            "category":"Freight",
            "type":"Transportation"
        }
    ],
    "sg:phone":"+1 770 795 4986",
    "sg:postcode":"30168",
    "sg:province":"GA",
    "sg:tags":[
        "operator",
        "trucking"
    ],
    "wof:name":"Merritt Trucking",
    "wof:placetype":"venue"
},
  "geometry": {"coordinates":[-84.590272,33.777782],"type":"Point"}
}