{
  "type": "Feature",
  "properties": {
    "addr:full":"1286 Lynx Ct Hampton GA 30228",
    "addr:housenumber":"1286",
    "addr:postcode":"30228",
    "addr:street":"Lynx Ct",
    "iso:country":"US",
    "sg:address":"1286 Lynx Ct",
    "sg:city":"Hampton",
    "sg:classifiers":[
        {
            "category":"Building & Trades",
            "subcategory":"Landscaping Services",
            "type":"Services"
        }
    ],
    "sg:phone":"+1 770 603 7037",
    "sg:postcode":"30228",
    "sg:province":"GA",
    "wof:name":"Tara Tilling & Aerating",
    "wof:placetype":"venue"
},
  "geometry": {"coordinates":[-84.34938200000001,33.456898],"type":"Point"}
}