{
  "type": "Feature",
  "properties": {
    "iso:country":"US",
    "sg:address":"911 Dutchtown Rd",
    "sg:city":"Savannah",
    "sg:classifiers":[
        {
            "category":"Social Services",
            "subcategory":"Child Care",
            "type":"Services"
        }
    ],
    "sg:phone":"+1 912 925 4566",
    "sg:postcode":"31419",
    "sg:province":"GA",
    "sg:tags":[
        "day"
    ],
    "wof:name":"Dutchtown Childrens Center",
    "wof:placetype":"venue"
},
  "geometry": {"coordinates":[-81.156386,31.986796],"type":"Point"}
}