{
  "type": "Feature",
  "properties": {
    "iso:country":"US",
    "sg:address":"1205 S 5th St",
    "sg:city":"Cordele",
    "sg:classifiers":[
        {
            "category":"Recreation",
            "type":"Entertainment"
        }
    ],
    "sg:phone":"+1 229 276 2797",
    "sg:postcode":"31015",
    "sg:province":"GA",
    "sg:tags":[
        "center"
    ],
    "wof:name":"Crisp County Recreation Dept",
    "wof:placetype":"venue"
},
  "geometry": {"coordinates":[-83.77939499999999,31.95696],"type":"Point"}
}