{
  "type": "Feature",
  "properties": {
    "addr:full":"160 Dietz Avenue Atlanta GA 30330",
    "addr:housenumber":"160",
    "addr:postcode":"30330",
    "addr:street":"Dietz Avenue",
    "iso:country":"US",
    "sg:address":"160 Dietz Avenue",
    "sg:city":"Atlanta",
    "sg:classifiers":[
        {
            "category":"Personal",
            "subcategory":"Barber",
            "type":"Services"
        }
    ],
    "sg:phone":"+1 404 758 9081",
    "sg:postcode":"30330",
    "sg:province":"GA",
    "wof:name":"Gino Morena Enterprises",
    "wof:placetype":"venue"
},
  "geometry": {"coordinates":[-84.43360300000001,33.707655],"type":"Point"}
}