{
  "type": "Feature",
  "properties": {
    "iso:country":"US",
    "sg:address":"3017 US Hwy 441 S",
    "sg:city":"Homer",
    "sg:classifiers":[
        {
            "category":"Restaurant",
            "type":"Food & Drink"
        }
    ],
    "sg:phone":"+1 706 677 4978",
    "sg:postcode":"30547",
    "sg:province":"GA",
    "sg:tags":[
        "eating"
    ],
    "wof:name":"Leopard Drive Inn",
    "wof:placetype":"venue"
},
  "geometry": {"coordinates":[-83.504547,34.329711],"type":"Point"}
}