{
  "type": "Feature",
  "properties": {
    "iso:country":"US",
    "sg:address":"404 Islandora Cove",
    "sg:city":"Woodstock",
    "sg:classifiers":[
        {
            "category":"Building & Trades",
            "subcategory":"Construction",
            "type":"Services"
        }
    ],
    "sg:phone":"+1 404 229 0118",
    "sg:postcode":"30188",
    "sg:province":"GA",
    "sg:tags":[
        "house"
    ],
    "wof:name":"Just Right Home Improvement",
    "wof:placetype":"venue"
},
  "geometry": {"coordinates":[-84.472139,34.099776],"type":"Point"}
}