{
  "type": "Feature",
  "properties": {
    "addr:full":"1131 Moreland Pl SE Atlanta GA 30316",
    "addr:housenumber":"1131",
    "addr:postcode":"30316",
    "addr:street":"Moreland Pl Se",
    "iso:country":"US",
    "sg:address":"1131 Moreland Pl SE",
    "sg:city":"Atlanta",
    "sg:classifiers":[
        {
            "category":"Retail",
            "subcategory":"Auto Repair",
            "type":"Services"
        }
    ],
    "sg:phone":"+1 404 622 1344",
    "sg:postcode":"30316",
    "sg:province":"GA",
    "sg:tags":[
        "glass",
        "replacement"
    ],
    "wof:name":"A Mobile Windshield Repair",
    "wof:placetype":"venue"
},
  "geometry": {"coordinates":[-84.34983099999999,33.738366],"type":"Point"}
}