{
  "type": "Feature",
  "properties": {
    "iso:country":"US",
    "sg:address":"211 Gaskin Ave S",
    "sg:city":"Douglas",
    "sg:classifiers":[
        {
            "category":"Government",
            "subcategory":"Office",
            "type":"Public Place"
        }
    ],
    "sg:phone":"+1 912 384 5161",
    "sg:postcode":"31533",
    "sg:province":"GA",
    "sg:tags":[
        "village"
    ],
    "wof:name":"Douglas Main Street",
    "wof:placetype":"venue"
},
  "geometry": {"coordinates":[-82.84523,31.507934],"type":"Point"}
}