{
  "type": "Feature",
  "properties": {
    "iso:country":"US",
    "sg:address":"7620 Bethel Rd",
    "sg:city":"Gainesville",
    "sg:classifiers":[
        {
            "category":"Restaurant",
            "type":"Food & Drink"
        }
    ],
    "sg:phone":"+1 770 887 1444",
    "sg:postcode":"30506",
    "sg:province":"GA",
    "sg:tags":[
        "eating"
    ],
    "wof:name":"Debbie's Wing-Out",
    "wof:placetype":"venue"
},
  "geometry": {"coordinates":[-83.99763299999999,34.246829],"type":"Point"}
}