{
  "type": "Feature",
  "properties": {
    "iso:country":"US",
    "sg:address":"7214 Douglas Blvd Ste G",
    "sg:city":"Douglasville",
    "sg:classifiers":[
        {
            "category":"Personal",
            "subcategory":"Tanning Parlor",
            "type":"Services"
        }
    ],
    "sg:phone":"+1 770 942 6303",
    "sg:postcode":"30135",
    "sg:province":"GA",
    "wof:name":"Dazzle Tan",
    "wof:placetype":"venue"
},
  "geometry": {"coordinates":[-84.765503,33.7248],"type":"Point"}
}