{
  "type": "Feature",
  "properties": {
    "addr:full":"1163 Old Chattanooga Valley Rd Flintstone GA 30725",
    "addr:housenumber":"1163",
    "addr:postcode":"30725",
    "addr:street":"Old Chattanooga Valley Rd",
    "iso:country":"US",
    "sg:address":"1163 Old Chattanooga Valley Rd",
    "sg:city":"Flintstone",
    "sg:classifiers":[
        {
            "category":"Health Services",
            "subcategory":"Nursing And Care Facility",
            "type":"Services"
        }
    ],
    "sg:phone":"+1 706 931 2784",
    "sg:postcode":"30725",
    "sg:province":"GA",
    "sg:tags":[
        "home"
    ],
    "wof:name":"Bryan Fukuea",
    "wof:placetype":"venue"
},
  "geometry": {"coordinates":[-85.351313,34.897027],"type":"Point"}
}