{
  "type": "Feature",
  "properties": {
    "iso:country":"US",
    "sg:address":"2453 Rockcliff Rd SE",
    "sg:city":"Atlanta",
    "sg:classifiers":[
        {
            "category":"Health Services",
            "subcategory":"Nursing And Care Facility",
            "type":"Services"
        },
        {
            "category":"Social Services",
            "subcategory":"Retirement Home",
            "type":"Services"
        }
    ],
    "sg:phone":"+1 404 243 8423",
    "sg:postcode":"30316",
    "sg:province":"GA",
    "sg:tags":[
        "personal",
        "convalescent"
    ],
    "wof:name":"Smith Wayne/Dorothy",
    "wof:placetype":"venue"
},
  "geometry": {"coordinates":[-84.321602,33.715988],"type":"Point"}
}