{
  "type": "Feature",
  "properties": {
    "addr:full":"4494 Acworth Industrial Dr NW Acworth GA 30101",
    "addr:housenumber":"4494",
    "addr:postcode":"30101",
    "addr:street":"Acworth Industrial Dr Nw",
    "iso:country":"US",
    "sg:address":"4494 Acworth Industrial Dr NW",
    "sg:city":"Acworth",
    "sg:classifiers":[
        {
            "category":"Utilities",
            "subcategory":"Sewage",
            "type":"Services"
        }
    ],
    "sg:phone":"+1 678 285 2600",
    "sg:postcode":"30101",
    "sg:province":"GA",
    "sg:tags":[
        "control",
        "odor"
    ],
    "wof:name":"Burning Solutions",
    "wof:placetype":"venue"
},
  "geometry": {"coordinates":[-84.660454,34.063496],"type":"Point"}
}