{
  "type": "Feature",
  "properties": {
    "iso:country":"US",
    "sg:address":"475 Hazel Ave",
    "sg:city":"Nashville",
    "sg:classifiers":[
        {
            "category":"Restaurant",
            "type":"Food & Drink"
        }
    ],
    "sg:phone":"+1 706 894 2993",
    "sg:postcode":"31639",
    "sg:province":"GA",
    "sg:tags":[
        "delicatessen"
    ],
    "wof:name":"Dave's Deli",
    "wof:placetype":"venue"
},
  "geometry": {"coordinates":[-83.241659,31.198571],"type":"Point"}
}