{
  "type": "Feature",
  "properties": {
    "addr:full":"6111 Live Oak Pkwy Norcross GA 30093",
    "addr:housenumber":"6111",
    "addr:postcode":"30093",
    "addr:street":"Live Oak Pkwy",
    "iso:country":"US",
    "sg:address":"6111 Live Oak Pkwy",
    "sg:city":"Norcross",
    "sg:classifiers":[
        {
            "category":"Professional",
            "subcategory":"Business Services",
            "type":"Services"
        }
    ],
    "sg:phone":"+1 770 246 0345",
    "sg:postcode":"30093",
    "sg:province":"GA",
    "sg:tags":[
        "record"
    ],
    "wof:name":"Recall Total Information Mgmt",
    "wof:placetype":"venue"
},
  "geometry": {"coordinates":[-84.205297,33.907505],"type":"Point"}
}