{
  "type": "Feature",
  "properties": {
    "iso:country":"US",
    "sg:address":"734 Atlanta Rd",
    "sg:city":"Cumming",
    "sg:classifiers":[
        {
            "category":"Autos & Motor Vehicles",
            "subcategory":"Automobile Sales",
            "type":"Retail Goods"
        }
    ],
    "sg:phone":"+1 678 947 5533",
    "sg:postcode":"30040",
    "sg:province":"GA",
    "sg:tags":[
        "car",
        "dealer"
    ],
    "wof:name":"Frontera Auto Sales Inc",
    "wof:placetype":"venue"
},
  "geometry": {"coordinates":[-84.143182,34.187333],"type":"Point"}
}