{
  "type": "Feature",
  "properties": {
    "addr:full":"6606 Selman Dr Douglasville GA 30134",
    "addr:housenumber":"6606",
    "addr:postcode":"30134",
    "addr:street":"Selman Dr",
    "iso:country":"US",
    "sg:address":"6606 Selman Dr",
    "sg:city":"Douglasville",
    "sg:classifiers":[
        {
            "category":"Sports & Exercise",
            "subcategory":"Golf",
            "type":"Entertainment"
        }
    ],
    "sg:phone":"+1 770 489 8826",
    "sg:postcode":"30134",
    "sg:province":"GA",
    "sg:tags":[
        "course"
    ],
    "wof:name":"West Pines Turf Care",
    "wof:placetype":"venue"
},
  "geometry": {"coordinates":[-84.746498,33.742468],"type":"Point"}
}