{
  "type": "Feature",
  "properties": {
    "iso:country":"US",
    "sg:address":"4147 Old Waynesboro Rd",
    "sg:city":"Hephzibah",
    "sg:classifiers":[
        {
            "category":"Freight",
            "type":"Transportation"
        }
    ],
    "sg:phone":"+1 706 829 6396",
    "sg:postcode":"30815",
    "sg:province":"GA",
    "sg:tags":[
        "hauling",
        "trucking"
    ],
    "wof:name":"M R Transport",
    "wof:placetype":"venue"
},
  "geometry": {"coordinates":[-82.01295399999999,33.325739],"type":"Point"}
}