{
  "type": "Feature",
  "properties": {
    "addr:full":"170 Barnes Nursery Rd Bronwood GA 39826",
    "addr:housenumber":"170",
    "addr:postcode":"39826",
    "addr:street":"Barnes Nursery Rd",
    "iso:country":"US",
    "sg:address":"170 Barnes Nursery Rd",
    "sg:city":"Bronwood",
    "sg:classifiers":[
        {
            "category":"Wholesale",
            "subcategory":"Durable Goods & Equipment",
            "type":"Manufacturing & Wholesale Goods"
        }
    ],
    "sg:phone":"+1 229 995 5200",
    "sg:postcode":"39826",
    "sg:province":"GA",
    "sg:tags":[
        "importer"
    ],
    "wof:name":"Barnes Imports Inc",
    "wof:placetype":"venue"
},
  "geometry": {"coordinates":[-84.34826200000001,31.859289],"type":"Point"}
}