{
  "type": "Feature",
  "properties": {
    "iso:country":"US",
    "sg:address":"218 E Main St NE",
    "sg:city":"Hiawassee",
    "sg:classifiers":[
        {
            "category":"Personal",
            "subcategory":"Beauty Salon",
            "type":"Services"
        }
    ],
    "sg:phone":"+1 706 896 7721",
    "sg:postcode":"30518",
    "sg:province":"GA",
    "wof:name":"Merle Norman Cosmetics",
    "wof:placetype":"venue"
},
  "geometry": {"coordinates":[-84.003033,34.121889],"type":"Point"}
}