{
  "type": "Feature",
  "properties": {
    "iso:country":"US",
    "sg:address":"3100 Highlands Pkwy SE",
    "sg:city":"Smyrna",
    "sg:classifiers":[
        {
            "category":"Shopping",
            "type":"Retail Goods"
        }
    ],
    "sg:phone":"+1 404 792 0209",
    "sg:postcode":"30082",
    "sg:province":"GA",
    "sg:tags":[
        "religious"
    ],
    "wof:name":"Glory Christian Bookstore",
    "wof:placetype":"venue"
},
  "geometry": {"coordinates":[-84.495364,33.827849],"type":"Point"}
}