{
  "type": "Feature",
  "properties": {
    "iso:country":"US",
    "sg:address":"6030 Macon Rd",
    "sg:city":"Columbus",
    "sg:classifiers":[
        {
            "category":"Home & Garden",
            "subcategory":"Mobile Homes",
            "type":"Retail Goods"
        }
    ],
    "sg:phone":"+1 706 568 6603",
    "sg:postcode":"31907",
    "sg:province":"GA",
    "wof:name":"Crystal Valley Mobile Homes",
    "wof:placetype":"venue"
},
  "geometry": {"coordinates":[-84.88472400000001,32.516329],"type":"Point"}
}