{
  "type": "Feature",
  "properties": {
    "addr:full":"280 Paulding Ln Dallas GA 30132",
    "addr:housenumber":"280",
    "addr:postcode":"30132",
    "addr:street":"Paulding Ln",
    "iso:country":"US",
    "sg:address":"280 Paulding Ln",
    "sg:city":"Dallas",
    "sg:classifiers":[
        {
            "category":"Banks & Credit Unions",
            "subcategory":"Bank",
            "type":"Services"
        }
    ],
    "sg:phone":"+1 770 445 0693",
    "sg:postcode":"30132",
    "sg:province":"GA",
    "sg:tags":[
        "financing"
    ],
    "wof:name":"Money Til Payday",
    "wof:placetype":"venue"
},
  "geometry": {"coordinates":[-84.83399300000001,33.91246],"type":"Point"}
}