{
  "type": "Feature",
  "properties": {
    "iso:country":"US",
    "sg:address":"908 E Piedmont Rd",
    "sg:city":"Marietta",
    "sg:classifiers":[
        {
            "category":"Restaurant",
            "type":"Food & Drink"
        }
    ],
    "sg:menulink":"http://www.allmenus.com/ga/northeast-cobb/185221-the-mad-italian/menu/",
    "sg:phone":"+1 770 952 1806",
    "sg:postcode":"30062",
    "sg:province":"GA",
    "sg:tags":[
        "italian"
    ],
    "wof:name":"The Mad Italian",
    "wof:placetype":"venue"
},
  "geometry": {"coordinates":[-84.479483,33.974431],"type":"Point"}
}