{
  "type": "Feature",
  "properties": {
    "iso:country":"US",
    "sg:address":"121 W Midland Ave",
    "sg:city":"Winder",
    "sg:classifiers":[
        {
            "category":"Food & Beverages",
            "subcategory":"Groceries & Convenience Stores",
            "type":"Retail Goods"
        }
    ],
    "sg:phone":"+1 770 867 0017",
    "sg:postcode":"30680",
    "sg:province":"GA",
    "sg:tags":[
        "house",
        "construction"
    ],
    "wof:name":"Midland Superette",
    "wof:placetype":"venue"
},
  "geometry": {"coordinates":[-83.72134,33.997927],"type":"Point"}
}