{
  "type": "Feature",
  "properties": {
    "addr:full":"709 Long Rd Ball Ground GA 30107",
    "addr:housenumber":"709",
    "addr:postcode":"30107",
    "addr:street":"Long Rd",
    "iso:country":"US",
    "sg:address":"709 Long Rd",
    "sg:city":"Ball Ground",
    "sg:classifiers":[
        {
            "category":"Building & Trades",
            "subcategory":"Construction",
            "type":"Services"
        }
    ],
    "sg:phone":"+1 770 720 2217",
    "sg:postcode":"30107",
    "sg:province":"GA",
    "sg:tags":[
        "maker",
        "cabinet"
    ],
    "wof:name":"American Cabinets",
    "wof:placetype":"venue"
},
  "geometry": {"coordinates":[-84.439801,34.313893],"type":"Point"}
}