{
  "type": "Feature",
  "properties": {
    "iso:country":"US",
    "sg:address":"404 School St",
    "sg:city":"Dalton",
    "sg:classifiers":[
        {
            "category":"Government",
            "subcategory":"Fire Station",
            "type":"Public Place"
        },
        {
            "category":"Government",
            "subcategory":"Office",
            "type":"Public Place"
        }
    ],
    "sg:phone":"+1 706 278 7363",
    "sg:postcode":"30720",
    "sg:province":"GA",
    "sg:tags":[
        "department",
        "township",
        "protection",
        "government-city",
        "village"
    ],
    "sg:website":"http://www.daltontradecenter.com",
    "wof:name":"Dalton Fire Department",
    "wof:placetype":"venue"
},
  "geometry": {"coordinates":[-84.971897,34.773233],"type":"Point"}
}