{
  "type": "Feature",
  "properties": {
    "addr:full":"4984 Clubgreen Summit Rd Stone Mountain GA 30088",
    "addr:housenumber":"4984",
    "addr:postcode":"30088",
    "addr:street":"Clubgreen Summit Rd",
    "iso:country":"US",
    "sg:address":"4984 Clubgreen Summit Rd",
    "sg:city":"Stone Mountain",
    "sg:classifiers":[
        {
            "category":"Professional",
            "subcategory":"Business Services",
            "type":"Services"
        }
    ],
    "sg:phone":"+1 770 981 7606",
    "sg:postcode":"30088",
    "sg:province":"GA",
    "wof:name":"Wheeling Evans Enterprise",
    "wof:placetype":"venue"
},
  "geometry": {"coordinates":[-84.185452,33.741506],"type":"Point"}
}