{
  "type": "Feature",
  "properties": {
    "iso:country":"US",
    "sg:address":"10789 Loving Rd",
    "sg:city":"Morganton",
    "sg:classifiers":[
        {
            "category":"Shopping",
            "type":"Retail Goods"
        }
    ],
    "sg:phone":"+1 706 374 2136",
    "sg:postcode":"30560",
    "sg:province":"GA",
    "sg:tags":[
        "merchandise"
    ],
    "wof:name":"Odoms Water Pump Sales & Svc",
    "wof:placetype":"venue"
},
  "geometry": {"coordinates":[-84.150201,34.949765],"type":"Point"}
}