{
  "type": "Feature",
  "properties": {
    "addr:full":"819 Cedar St Carrollton GA 30117",
    "addr:housenumber":"819",
    "addr:postcode":"30117",
    "addr:street":"Cedar St",
    "iso:country":"US",
    "sg:address":"819 Cedar St",
    "sg:city":"Carrollton",
    "sg:phone":"+1 770 838 1600",
    "sg:postcode":"30117",
    "sg:province":"GA",
    "sg:website":"http://hairartsalonga.com",
    "wof:name":"Hair Art Salon",
    "wof:placetype":"venue"
},
  "geometry": {"coordinates":[-85.061761,33.582519],"type":"Point"}
}