{
  "type": "Feature",
  "properties": {
    "iso:country":"US",
    "sg:address":"3804 Vinyard Way",
    "sg:city":"Marietta",
    "sg:classifiers":[
        {
            "category":"Building & Trades",
            "subcategory":"Landscaping Services",
            "type":"Services"
        }
    ],
    "sg:phone":"+1 770 578 1086",
    "sg:postcode":"30062",
    "sg:province":"GA",
    "sg:tags":[
        "landscape",
        "contractor"
    ],
    "wof:name":"Southeastern Scapes",
    "wof:placetype":"venue"
},
  "geometry": {"coordinates":[-84.440399,34.006844],"type":"Point"}
}