{
  "type": "Feature",
  "properties": {
    "addr:full":"124 S Main St Jonesboro GA 30236",
    "addr:housenumber":"124",
    "addr:postcode":"30236",
    "addr:street":"S Main St",
    "iso:country":"US",
    "sg:address":"124 S Main St",
    "sg:city":"Jonesboro",
    "sg:classifiers":[
        {
            "category":"Professional",
            "subcategory":"Business Services",
            "type":"Services"
        }
    ],
    "sg:phone":"+1 770 210 0766",
    "sg:postcode":"30236",
    "sg:province":"GA",
    "sg:tags":[
        "paralegal"
    ],
    "wof:name":"Paralegal & Multiservice Bur",
    "wof:placetype":"venue"
},
  "geometry": {"coordinates":[-84.353798,33.515646],"type":"Point"}
}