{
  "type": "Feature",
  "properties": {
    "addr:full":"1120 Vistavia Cir Decatur GA 30033",
    "addr:housenumber":"1120",
    "addr:postcode":"30033",
    "addr:street":"Vistavia Cir",
    "iso:country":"US",
    "sg:address":"1120 Vistavia Cir",
    "sg:city":"Decatur",
    "sg:classifiers":[
        {
            "category":"Professional",
            "subcategory":"Computer Services",
            "type":"Services"
        }
    ],
    "sg:phone":"+1 404 728 1120",
    "sg:postcode":"30033",
    "sg:province":"GA",
    "sg:tags":[
        "developer",
        "publisher",
        "software",
        "designer",
        "consultant"
    ],
    "sg:website":"http://www.frontrowsystems.com",
    "wof:name":"Front Row Systems",
    "wof:placetype":"venue"
},
  "geometry": {"coordinates":[-84.31485499999999,33.808988],"type":"Point"}
}