{
  "type": "Feature",
  "properties": {
    "addr:full":"115 Smith Dr Perry GA 31069",
    "addr:housenumber":"115",
    "addr:postcode":"31069",
    "addr:street":"Smith Dr",
    "iso:country":"US",
    "sg:address":"115 Smith Dr",
    "sg:city":"Perry",
    "sg:classifiers":[
        {
            "category":"Home & Garden",
            "subcategory":"Garden Supply",
            "type":"Retail Goods"
        }
    ],
    "sg:phone":"+1 478 987 3433",
    "sg:postcode":"31069",
    "sg:province":"GA",
    "sg:tags":[
        "fertilizer"
    ],
    "wof:name":"Langston Rainbow Ctr",
    "wof:placetype":"venue"
},
  "geometry": {"coordinates":[-83.73840300000001,32.465327],"type":"Point"}
}