{
  "type": "Feature",
  "properties": {
    "addr:full":"626 23rd St Columbus GA 31904",
    "addr:housenumber":"626",
    "addr:postcode":"31904",
    "addr:street":"23Rd St",
    "iso:country":"US",
    "sg:address":"626 23rd St",
    "sg:city":"Columbus",
    "sg:classifiers":[
        {
            "category":"Health Services",
            "subcategory":"Doctor",
            "type":"Services"
        }
    ],
    "sg:phone":"+1 706 660 1177",
    "sg:postcode":"31904",
    "sg:province":"GA",
    "sg:tags":[
        "physician",
        "medical",
        "pediatrics",
        "surgeons"
    ],
    "wof:name":"Panvelkar Real Estate",
    "wof:placetype":"venue"
},
  "geometry": {"coordinates":[-84.984154,32.485598],"type":"Point"}
}