{
  "type": "Feature",
  "properties": {
    "addr:full":"6551 Peachtree Industrial Blvd Atlanta GA 30360",
    "addr:housenumber":"6551",
    "addr:postcode":"30360",
    "addr:street":"Peachtree Industrial Blvd",
    "iso:country":"US",
    "sg:address":"6551 Peachtree Industrial Blvd",
    "sg:city":"Atlanta",
    "sg:classifiers":[
        {
            "category":"Utilities",
            "subcategory":"Natural Gas",
            "type":"Services"
        }
    ],
    "sg:phone":"+1 770 455 6724",
    "sg:postcode":"30360",
    "sg:province":"GA",
    "sg:tags":[
        "stone"
    ],
    "wof:name":"S & S Stone",
    "wof:placetype":"venue"
},
  "geometry": {"coordinates":[-84.276741,33.925491],"type":"Point"}
}