{
  "type": "Feature",
  "properties": {
    "iso:country":"US",
    "sg:address":"83 Northwood Cir",
    "sg:city":"Colbert",
    "sg:classifiers":[
        {
            "category":"Building & Trades",
            "subcategory":"Construction",
            "type":"Services"
        }
    ],
    "sg:phone":"+1 706 789 2893",
    "sg:postcode":"30628",
    "sg:province":"GA",
    "sg:tags":[
        "painter"
    ],
    "wof:name":"Kentnor Painting",
    "wof:placetype":"venue"
},
  "geometry": {"coordinates":[-83.30024400000001,34.096404],"type":"Point"}
}