{
  "type": "Feature",
  "properties": {
    "iso:country":"US",
    "sg:address":"1970 Peachford Road",
    "sg:city":"Atlanta",
    "sg:classifiers":[
        {
            "category":"Real Estate",
            "subcategory":"Real Estate Operator",
            "type":"Services"
        }
    ],
    "sg:phone":"+1 770 452 0001",
    "sg:postcode":"30338",
    "sg:province":"GA",
    "sg:tags":[
        "apartment"
    ],
    "wof:name":"Dunwoody Gables",
    "wof:placetype":"venue"
},
  "geometry": {"coordinates":[-84.304495,33.923457],"type":"Point"}
}