{
  "type": "Feature",
  "properties": {
    "addr:full":"2450 Confederate Trl NW Kennesaw GA 30152",
    "addr:housenumber":"2450",
    "addr:postcode":"30152",
    "addr:street":"Confederate Trl Nw",
    "iso:country":"US",
    "sg:address":"2450 Confederate Trl NW",
    "sg:city":"Kennesaw",
    "sg:classifiers":[
        {
            "category":"Autos & Motor Vehicles",
            "subcategory":"Automobile Sales",
            "type":"Retail Goods"
        }
    ],
    "sg:phone":"+1 770 422 5642",
    "sg:postcode":"30152",
    "sg:province":"GA",
    "wof:name":"Rj Weeks Inc",
    "wof:placetype":"venue"
},
  "geometry": {"coordinates":[-84.63314200000001,34.012263],"type":"Point"}
}