{
  "type": "Feature",
  "properties": {
    "addr:full":"4400 Ashford Dunwoody Rd NE Suite #1360 Suite #1360 Atlanta GA 30346",
    "addr:housenumber":"4400;1360 suite # 1360",
    "addr:postcode":"30346",
    "addr:street":"Ashford Dunwoody Rd Ne Suite #",
    "iso:country":"US",
    "sg:address":"4400 Ashford Dunwoody Rd NE Suite #1360 Suite #1360",
    "sg:city":"Atlanta",
    "sg:classifiers":[
        {
            "category":"Shopping",
            "subcategory":"Clothing, Apparel, & Fashions",
            "type":"Retail Goods"
        }
    ],
    "sg:phone":"+1 770 391 1484",
    "sg:postcode":"30346",
    "sg:province":"GA",
    "sg:website":"www.forever21.com",
    "wof:name":"XXI Forever",
    "wof:placetype":"venue"
},
  "geometry": {"coordinates":[-84.338115,33.923765],"type":"Point"}
}