{
  "type": "Feature",
  "properties": {
    "addr:full":"1029 Westbrooke Way NE Atlanta GA 30319",
    "addr:housenumber":"1029",
    "addr:postcode":"30319",
    "addr:street":"Westbrooke Way Ne",
    "iso:country":"US",
    "sg:address":"1029 Westbrooke Way NE",
    "sg:city":"Atlanta",
    "sg:classifiers":[
        {
            "category":"Professional",
            "subcategory":"Business Services",
            "type":"Services"
        }
    ],
    "sg:phone":"+1 404 497 0577",
    "sg:postcode":"30319",
    "sg:province":"GA",
    "wof:name":"Executive Telecommunications",
    "wof:placetype":"venue"
},
  "geometry": {"coordinates":[-84.345615,33.902897],"type":"Point"}
}