{
  "type": "Feature",
  "properties": {
    "iso:country":"US",
    "sg:address":"241 W General Screven Way",
    "sg:city":"Hinesville",
    "sg:classifiers":[
        {
            "category":"Shopping",
            "subcategory":"Used Merchandise",
            "type":"Retail Goods"
        }
    ],
    "sg:phone":"+1 912 876 8740",
    "sg:postcode":"31313",
    "sg:province":"GA",
    "sg:tags":[
        "pawnbroker"
    ],
    "wof:name":"Mr Cash",
    "wof:placetype":"venue"
},
  "geometry": {"coordinates":[-81.59780499999999,31.84084],"type":"Point"}
}