{
  "type": "Feature",
  "properties": {
    "iso:country":"US",
    "sg:address":"2905 Amwiler Rd",
    "sg:city":"Atlanta",
    "sg:classifiers":[
        {
            "category":"Autos & Motor Vehicles",
            "subcategory":"Motorcycle Sales",
            "type":"Retail Goods"
        }
    ],
    "sg:phone":"+1 770 409 9595",
    "sg:postcode":"30360",
    "sg:province":"GA",
    "sg:tags":[
        "scooter"
    ],
    "wof:name":"ABC Space Corp",
    "wof:placetype":"venue"
},
  "geometry": {"coordinates":[-84.254712,33.925543],"type":"Point"}
}