{
  "type": "Feature",
  "properties": {
    "iso:country":"US",
    "sg:address":"911 1st St",
    "sg:city":"Macon",
    "sg:classifiers":[
        {
            "category":"Professional",
            "type":"Services"
        }
    ],
    "sg:phone":"+1 478 742 2330",
    "sg:postcode":"31201",
    "sg:province":"GA",
    "sg:tags":[
        "establishment"
    ],
    "wof:name":"Crime Stoppers",
    "wof:placetype":"venue"
},
  "geometry": {"coordinates":[-83.63656899999999,32.830535],"type":"Point"}
}