{
  "type": "Feature",
  "properties": {
    "iso:country":"US",
    "sg:address":"2417 Regency Blvd",
    "sg:city":"Augusta",
    "sg:classifiers":[
        {
            "category":"Professional",
            "subcategory":"Management & Consulting",
            "type":"Services"
        }
    ],
    "sg:phone":"+1 706 771 8528",
    "sg:postcode":"30904",
    "sg:province":"GA",
    "sg:tags":[
        "project",
        "construction"
    ],
    "wof:name":"Sears Contract Sales",
    "wof:placetype":"venue"
},
  "geometry": {"coordinates":[-82.03479799999999,33.440933],"type":"Point"}
}