{
  "type": "Feature",
  "properties": {
    "iso:country":"US",
    "sg:address":"4665 Lower Roswell Rd",
    "sg:city":"Marietta",
    "sg:classifiers":[
        {
            "category":"Personal",
            "type":"Services"
        }
    ],
    "sg:phone":"+1 770 973 6820",
    "sg:postcode":"30068",
    "sg:province":"GA",
    "sg:tags":[
        "party",
        "planning",
        "event"
    ],
    "wof:name":"Magical Entertainment",
    "wof:placetype":"venue"
},
  "geometry": {"coordinates":[-84.414902,33.9655],"type":"Point"}
}