{
  "type": "Feature",
  "properties": {
    "iso:country":"US",
    "sg:address":"748 Veterans Memorial Hwy SW Mableton",
    "sg:city":"Mableton",
    "sg:classifiers":[
        {
            "category":"Shopping",
            "subcategory":"Computers & Home Electronics",
            "type":"Retail Goods"
        }
    ],
    "sg:phone":"+1 770 941 4030",
    "sg:postcode":"30126",
    "sg:province":"GA",
    "sg:tags":[
        "renting",
        "equipment",
        "leasing"
    ],
    "sg:website":"http://www.shopaarons.com",
    "wof:name":"Aaron's Rental Purchase",
    "wof:placetype":"venue"
},
  "geometry": {"coordinates":[-84.576258,33.818454],"type":"Point"}
}