{
  "type": "Feature",
  "properties": {
    "iso:country":"US",
    "sg:address":"6670 Corners Industrial Ct",
    "sg:city":"Norcross",
    "sg:classifiers":[
        {
            "category":"Shopping",
            "subcategory":"Stationery & Office Supplies",
            "type":"Retail Goods"
        }
    ],
    "sg:phone":"+1 770 849 0354",
    "sg:postcode":"30092",
    "sg:province":"GA",
    "sg:tags":[
        "equipment"
    ],
    "wof:name":"Cwc Office Supply & Coffee Butler",
    "wof:placetype":"venue"
},
  "geometry": {"coordinates":[-84.253224,33.939936],"type":"Point"}
}