{
  "type": "Feature",
  "properties": {
    "addr:full":"1910 E Atlanta Rd Stockbridge GA 30281",
    "addr:housenumber":"1910",
    "addr:postcode":"30281",
    "addr:street":"E Atlanta Rd",
    "iso:country":"US",
    "sg:address":"1910 E Atlanta Rd",
    "sg:city":"Stockbridge",
    "sg:classifiers":[
        {
            "category":"Professional",
            "subcategory":"Engineering",
            "type":"Services"
        }
    ],
    "sg:phone":"+1 770 474 1107",
    "sg:postcode":"30281",
    "sg:province":"GA",
    "sg:tags":[
        "system",
        "cad"
    ],
    "wof:name":"S D Cadd Services",
    "wof:placetype":"venue"
},
  "geometry": {"coordinates":[-84.23361199999999,33.59383],"type":"Point"}
}