{
  "type": "Feature",
  "properties": {
    "addr:full":"35 Mack Dr Edison GA 31794",
    "addr:housenumber":"35",
    "addr:postcode":"31794",
    "addr:street":"Mack Dr",
    "iso:country":"US",
    "sg:address":"35 Mack Dr",
    "sg:city":"Edison",
    "sg:classifiers":[
        {
            "category":"Wholesale",
            "subcategory":"Farm Supplies",
            "type":"Manufacturing & Wholesale Goods"
        }
    ],
    "sg:phone":"+1 229 835 2700",
    "sg:postcode":"31794",
    "sg:province":"GA",
    "sg:tags":[
        "grain"
    ],
    "wof:name":"Mac Grain Co",
    "wof:placetype":"venue"
},
  "geometry": {"coordinates":[-83.461707,31.46993],"type":"Point"}
}