{
  "type": "Feature",
  "properties": {
    "addr:full":"177 Omega Dr Lawrenceville GA 30044",
    "addr:housenumber":"177",
    "addr:postcode":"30044",
    "addr:street":"Omega Dr",
    "iso:country":"US",
    "sg:address":"177 Omega Dr",
    "sg:city":"Lawrenceville",
    "sg:classifiers":[
        {
            "category":"Professional",
            "type":"Services"
        }
    ],
    "sg:phone":"+1 770 873 3726",
    "sg:postcode":"30044",
    "sg:province":"GA",
    "wof:name":"M Tech Svcs",
    "wof:placetype":"venue"
},
  "geometry": {"coordinates":[-84.09591399999999,33.910641],"type":"Point"}
}