{
  "type": "Feature",
  "properties": {
    "iso:country":"US",
    "sg:address":"3613 Robinson Walk Dr",
    "sg:city":"Marietta",
    "sg:classifiers":[
        {
            "category":"Building & Trades",
            "subcategory":"Landscaping Services",
            "type":"Services"
        }
    ],
    "sg:phone":"+1 404 394 2976",
    "sg:postcode":"30068",
    "sg:province":"GA",
    "wof:name":"Yards & More",
    "wof:placetype":"venue"
},
  "geometry": {"coordinates":[-84.446518,33.973714],"type":"Point"}
}