{
  "type": "Feature",
  "properties": {
    "iso:country":"US",
    "sg:address":"1888 Emery St NW",
    "sg:city":"Atlanta",
    "sg:classifiers":[
        {
            "category":"Professional",
            "subcategory":"Computer Services",
            "type":"Services"
        }
    ],
    "sg:phone":"+1 404 425 7190",
    "sg:postcode":"30318",
    "sg:province":"GA",
    "sg:tags":[
        "repair"
    ],
    "wof:name":"Avit Services",
    "wof:placetype":"venue"
},
  "geometry": {"coordinates":[-84.41439800000001,33.807301],"type":"Point"}
}