{
  "type": "Feature",
  "properties": {
    "addr:full":"2694 Suzanne Ln Acworth GA 30102",
    "addr:housenumber":"2694",
    "addr:postcode":"30102",
    "addr:street":"Suzanne Ln",
    "iso:country":"US",
    "sg:address":"2694 Suzanne Ln",
    "sg:city":"Acworth",
    "sg:classifiers":[
        {
            "category":"Building & Trades",
            "subcategory":"Construction",
            "type":"Services"
        }
    ],
    "sg:phone":"+1 770 966 9767",
    "sg:postcode":"30102",
    "sg:province":"GA",
    "sg:tags":[
        "house",
        "improvement",
        "home"
    ],
    "wof:name":"Rittman's Renovations",
    "wof:placetype":"venue"
},
  "geometry": {"coordinates":[-84.609734,34.087984],"type":"Point"}
}