{
  "type": "Feature",
  "properties": {
    "addr:full":"107 Postelle St Cartersville GA 30120",
    "addr:housenumber":"107",
    "addr:postcode":"30120",
    "addr:street":"Postelle St",
    "iso:country":"US",
    "sg:address":"107 Postelle St",
    "sg:city":"Cartersville",
    "sg:classifiers":[
        {
            "category":"Real Estate",
            "subcategory":"Real Estate Agent",
            "type":"Services"
        }
    ],
    "sg:phone":"+1 770 480 1693",
    "sg:postcode":"30120",
    "sg:province":"GA",
    "wof:name":"Action Property Management",
    "wof:placetype":"venue"
},
  "geometry": {"coordinates":[-84.791456,34.161828],"type":"Point"}
}