{
  "type": "Feature",
  "properties": {
    "iso:country":"US",
    "sg:address":"822 Waterford Pl NE",
    "sg:city":"Atlanta",
    "sg:classifiers":[
        {
            "category":"Professional",
            "subcategory":"Computer Services",
            "type":"Services"
        }
    ],
    "sg:phone":"+1 678 334 8039",
    "sg:postcode":"30342",
    "sg:province":"GA",
    "sg:tags":[
        "nigeria",
        "africa",
        "social-bookmarking",
        "search-engine",
        "sturvs"
    ],
    "sg:website":"http://www.sturvs.com",
    "wof:name":"Sturvs",
    "wof:placetype":"venue"
},
  "geometry": {"coordinates":[-84.37855,33.889427],"type":"Point"}
}