{
  "type": "Feature",
  "properties": {
    "addr:full":"264 Fowler Cir NE Marietta GA 30060",
    "addr:housenumber":"264",
    "addr:postcode":"30060",
    "addr:street":"Fowler Cir Ne",
    "iso:country":"US",
    "sg:address":"264 Fowler Cir NE",
    "sg:city":"Marietta",
    "sg:classifiers":[
        {
            "category":"Organizations",
            "subcategory":"Religious Organization",
            "type":"Services"
        }
    ],
    "sg:phone":"+1 770 427 6251",
    "sg:postcode":"30060",
    "sg:province":"GA",
    "sg:tags":[
        "church"
    ],
    "wof:name":"Union Chapel United Methodist",
    "wof:placetype":"venue"
},
  "geometry": {"coordinates":[-84.546837,33.959235],"type":"Point"}
}