{
  "type": "Feature",
  "properties": {
    "addr:full":"4910 Piney Grove Dr Cumming GA 30040",
    "addr:housenumber":"4910",
    "addr:postcode":"30040",
    "addr:street":"Piney Grove Dr",
    "iso:country":"US",
    "sg:address":"4910 Piney Grove Dr",
    "sg:city":"Cumming",
    "sg:classifiers":[
        {
            "category":"Recreation",
            "type":"Entertainment"
        }
    ],
    "sg:phone":"+1 770 205 8618",
    "sg:postcode":"30040",
    "sg:province":"GA",
    "sg:tags":[
        "club",
        "membership"
    ],
    "wof:name":"Forsyth Racquet Club",
    "wof:placetype":"venue"
},
  "geometry": {"coordinates":[-84.174515,34.187837],"type":"Point"}
}