{
  "type": "Feature",
  "properties": {
    "addr:full":"3160 Main St W Snellville GA 30078",
    "addr:housenumber":"3160",
    "addr:postcode":"30078",
    "addr:street":"Main St W",
    "iso:country":"US",
    "sg:address":"3160 Main St W",
    "sg:city":"Snellville",
    "sg:classifiers":[
        {
            "category":"Autos & Motor Vehicles",
            "subcategory":"Auto Supplies",
            "type":"Retail Goods"
        }
    ],
    "sg:phone":"+1 678 615 3749",
    "sg:postcode":"30078",
    "sg:province":"GA",
    "sg:tags":[
        "tire"
    ],
    "wof:name":"Latin Tire Services",
    "wof:placetype":"venue"
},
  "geometry": {"coordinates":[-84.042986,33.851875],"type":"Point"}
}