{
  "type": "Feature",
  "properties": {
    "iso:country":"US",
    "sg:address":"819 Chickamauga Ave",
    "sg:city":"Rossville",
    "sg:classifiers":[
        {
            "category":"Restaurant",
            "type":"Food & Drink"
        }
    ],
    "sg:phone":"+1 706 858 7800",
    "sg:postcode":"30741",
    "sg:province":"GA",
    "sg:tags":[
        "eating"
    ],
    "wof:name":"Johns Barbeque",
    "wof:placetype":"venue"
},
  "geometry": {"coordinates":[-85.27773999999999,34.979828],"type":"Point"}
}