{
  "type": "Feature",
  "properties": {
    "addr:full":"3511 Autumn Farm Ter Buford GA 30519",
    "addr:housenumber":"3511",
    "addr:postcode":"30519",
    "addr:street":"Autumn Farm Ter",
    "iso:country":"US",
    "sg:address":"3511 Autumn Farm Ter",
    "sg:city":"Buford",
    "sg:classifiers":[
        {
            "category":"Building & Trades",
            "subcategory":"Locksmith",
            "type":"Services"
        }
    ],
    "sg:phone":"+1 877 246 8188",
    "sg:postcode":"30519",
    "sg:province":"GA",
    "sg:tags":[
        "key"
    ],
    "wof:name":"7 Day 24 Hour Emergency Locksmith",
    "wof:placetype":"venue"
},
  "geometry": {"coordinates":[-83.909493,34.122979],"type":"Point"}
}