{
  "type": "Feature",
  "properties": {
    "iso:country":"US",
    "sg:address":"3171 Pritchards Pt",
    "sg:city":"Douglasville",
    "sg:classifiers":[
        {
            "category":"Building & Trades",
            "subcategory":"Construction",
            "type":"Services"
        }
    ],
    "sg:phone":"+1 770 617 5619",
    "sg:postcode":"30135",
    "sg:province":"GA",
    "sg:tags":[
        "house"
    ],
    "wof:name":"Bill & Sons",
    "wof:placetype":"venue"
},
  "geometry": {"coordinates":[-84.68116499999999,33.725834],"type":"Point"}
}