{
  "type": "Feature",
  "properties": {
    "addr:full":"277 Big Sky Ct Hamilton GA 31811",
    "addr:housenumber":"277",
    "addr:postcode":"31811",
    "addr:street":"Big Sky Ct",
    "iso:country":"US",
    "sg:address":"277 Big Sky Ct",
    "sg:city":"Hamilton",
    "sg:classifiers":[
        {
            "category":"Professional",
            "subcategory":"Detective & Security Services",
            "type":"Services"
        }
    ],
    "sg:phone":"+1 706 527 3192",
    "sg:postcode":"31811",
    "sg:province":"GA",
    "sg:tags":[
        "guard",
        "patrol"
    ],
    "wof:name":"Integrated Security",
    "wof:placetype":"venue"
},
  "geometry": {"coordinates":[-84.928363,32.714318],"type":"Point"}
}