{
  "type": "Feature",
  "properties": {
    "addr:full":"1514 Old Dean Forest Rd Savannah GA 31408",
    "addr:housenumber":"1514",
    "addr:postcode":"31408",
    "addr:street":"Old Dean Forest Rd",
    "iso:country":"US",
    "sg:address":"1514 Old Dean Forest Rd",
    "sg:city":"Savannah",
    "sg:classifiers":[
        {
            "category":"Building & Trades",
            "subcategory":"Electrical",
            "type":"Services"
        }
    ],
    "sg:phone":"+1 912 963 9601",
    "sg:postcode":"31408",
    "sg:province":"GA",
    "sg:tags":[
        "electrical",
        "contractor"
    ],
    "wof:name":"White Electrical Cnstr Co",
    "wof:placetype":"venue"
},
  "geometry": {"coordinates":[-81.19735300000001,32.073749],"type":"Point"}
}