{
  "type": "Feature",
  "properties": {
    "iso:country":"US",
    "sg:address":"1765 W Oak Pkwy Ste 700",
    "sg:city":"Marietta",
    "sg:classifiers":[
        {
            "category":"Building & Trades",
            "subcategory":"Construction",
            "type":"Services"
        },
        {
            "category":"Utilities",
            "type":"Services"
        }
    ],
    "sg:phone":"+1 770 429 7835",
    "sg:postcode":"30062",
    "sg:province":"GA",
    "sg:tags":[
        "excavation",
        "contractor"
    ],
    "wof:name":"Second Mile",
    "wof:placetype":"venue"
},
  "geometry": {"coordinates":[-84.522462,33.985298],"type":"Point"}
}