{
  "type": "Feature",
  "properties": {
    "addr:full":"650 Murphy Ave SW Atlanta GA 30310",
    "addr:housenumber":"650",
    "addr:postcode":"30310",
    "addr:street":"Murphy Ave Sw",
    "iso:country":"US",
    "sg:address":"650 Murphy Ave SW",
    "sg:city":"Atlanta",
    "sg:classifiers":[
        {
            "category":"Building & Trades",
            "subcategory":"Electrical",
            "type":"Services"
        }
    ],
    "sg:phone":"+1 404 758 8856",
    "sg:postcode":"30310",
    "sg:province":"GA",
    "sg:tags":[
        "electric",
        "contractor"
    ],
    "wof:name":"M Bec Electrical Contr Inc",
    "wof:placetype":"venue"
},
  "geometry": {"coordinates":[-84.412318,33.735209],"type":"Point"}
}