{
  "type": "Feature",
  "properties": {
    "iso:country":"US",
    "sg:address":"6776 Highway 85",
    "sg:city":"Riverdale",
    "sg:classifiers":[
        {
            "category":"Food & Beverages",
            "subcategory":"Liquor & Beverages",
            "type":"Retail Goods"
        },
        {
            "category":"Banks & Credit Unions",
            "subcategory":"Financial Services",
            "type":"Services"
        }
    ],
    "sg:phone":"+1 770 997 3500",
    "sg:postcode":"30274",
    "sg:province":"GA",
    "sg:tags":[
        "cashing",
        "beer",
        "wine",
        "spirit",
        "check"
    ],
    "wof:name":"New South Package Store",
    "wof:placetype":"venue"
},
  "geometry": {"coordinates":[-84.412903,33.569599],"type":"Point"}
}