{
  "type": "Feature",
  "properties": {
    "iso:country":"US",
    "sg:address":"3254 Middle Ground Rd",
    "sg:city":"Statesboro",
    "sg:classifiers":[
        {
            "category":"Wholesale",
            "subcategory":"Construction Materials",
            "type":"Manufacturing & Wholesale Goods"
        },
        {
            "category":"Building & Trades",
            "subcategory":"Construction",
            "type":"Services"
        }
    ],
    "sg:phone":"+1 912 587 5536",
    "sg:postcode":"30461",
    "sg:province":"GA",
    "sg:tags":[
        "fence",
        "contractor"
    ],
    "wof:name":"Morris Fence Company",
    "wof:placetype":"venue"
},
  "geometry": {"coordinates":[-81.811515,32.543999],"type":"Point"}
}