{
  "type": "Feature",
  "properties": {
    "addr:full":"3407 Landrum Dr SE Smyrna GA 30082",
    "addr:housenumber":"3407",
    "addr:postcode":"30082",
    "addr:street":"Landrum Dr Se",
    "iso:country":"US",
    "sg:address":"3407 Landrum Dr SE",
    "sg:city":"Smyrna",
    "sg:classifiers":[
        {
            "category":"Building & Trades",
            "subcategory":"Construction",
            "type":"Services"
        }
    ],
    "sg:phone":"+1 404 697 4300",
    "sg:postcode":"30082",
    "sg:province":"GA",
    "sg:tags":[
        "siding",
        "contractor"
    ],
    "wof:name":"George Liverpool Contracting",
    "wof:placetype":"venue"
},
  "geometry": {"coordinates":[-84.552952,33.870816],"type":"Point"}
}