{
  "type": "Feature",
  "properties": {
    "iso:country":"US",
    "sg:address":"3931 Mission Ln NW",
    "sg:city":"Loganville",
    "sg:classifiers":[
        {
            "category":"Restaurant",
            "type":"Food & Drink"
        }
    ],
    "sg:phone":"+1 770 972 0996",
    "sg:postcode":"30071",
    "sg:province":"GA",
    "sg:tags":[
        "eating"
    ],
    "wof:name":"Kitchen Burian",
    "wof:placetype":"venue"
},
  "geometry": {"coordinates":[-84.22537,33.929023],"type":"Point"}
}