{
  "type": "Feature",
  "properties": {
    "addr:full":"1610 Julian Dr Watkinsville GA 30677",
    "addr:housenumber":"1610",
    "addr:postcode":"30677",
    "addr:street":"Julian Dr",
    "iso:country":"US",
    "sg:address":"1610 Julian Dr",
    "sg:city":"Watkinsville",
    "sg:classifiers":[
        {
            "category":"Professional",
            "subcategory":"Management & Consulting",
            "type":"Services"
        }
    ],
    "sg:phone":"+1 770 725 0859",
    "sg:postcode":"30677",
    "sg:province":"GA",
    "sg:tags":[
        "personnel",
        "consultant"
    ],
    "wof:name":"Pro Nurse Inc",
    "wof:placetype":"venue"
},
  "geometry": {"coordinates":[-83.499129,33.926115],"type":"Point"}
}