{
  "type": "Feature",
  "properties": {
    "iso:country":"US",
    "sg:address":"1016 Howell Mill Road NW Suite 1502",
    "sg:city":"Atlanta",
    "sg:classifiers":[
        {
            "category":"Professional",
            "subcategory":"Computer Services",
            "type":"Services"
        }
    ],
    "sg:phone":"+1 404 539 8032",
    "sg:postcode":"30318",
    "sg:province":"GA",
    "sg:tags":[
        "forum-software",
        "message-board",
        "real-time"
    ],
    "sg:website":"http://ninjapost.com",
    "wof:name":"Ninja Post",
    "wof:placetype":"venue"
},
  "geometry": {"coordinates":[-84.41152700000001,33.782177],"type":"Point"}
}