{
  "type": "Feature",
  "properties": {
    "addr:full":"3173 Delowe Dr Atlanta GA 30344",
    "addr:housenumber":"3173",
    "addr:postcode":"30344",
    "addr:street":"Delowe Dr",
    "iso:country":"US",
    "sg:address":"3173 Delowe Dr",
    "sg:city":"Atlanta",
    "sg:classifiers":[
        {
            "category":"Building & Trades",
            "subcategory":"Construction",
            "type":"Services"
        }
    ],
    "sg:phone":"+1 404 559 9292",
    "sg:postcode":"30344",
    "sg:province":"GA",
    "sg:tags":[
        "house"
    ],
    "wof:name":"Bussey Home Improvement",
    "wof:placetype":"venue"
},
  "geometry": {"coordinates":[-84.458184,33.668403],"type":"Point"}
}