{
  "type": "Feature",
  "properties": {
    "iso:country":"US",
    "sg:address":"330 S Wall St",
    "sg:city":"Calhoun",
    "sg:classifiers":[
        {
            "category":"Professional",
            "type":"Services"
        }
    ],
    "sg:phone":"+1 706 624 0018",
    "sg:postcode":"30701",
    "sg:province":"GA",
    "sg:tags":[
        "establishment"
    ],
    "wof:name":"Meyercord Co",
    "wof:placetype":"venue"
},
  "geometry": {"coordinates":[-84.951883,34.498909],"type":"Point"}
}