{
  "type": "Feature",
  "properties": {
    "addr:full":"2908 Sylvester Rd Albany GA 31705",
    "addr:housenumber":"2908",
    "addr:postcode":"31705",
    "addr:street":"Sylvester Rd",
    "iso:country":"US",
    "sg:address":"2908 Sylvester Rd",
    "sg:city":"Albany",
    "sg:classifiers":[
        {
            "category":"Building & Trades",
            "subcategory":"Construction",
            "type":"Services"
        },
        {
            "category":"Home & Garden",
            "subcategory":"Mobile Homes",
            "type":"Retail Goods"
        }
    ],
    "sg:phone":"+1 229 535 6152",
    "sg:postcode":"31705",
    "sg:province":"GA",
    "sg:tags":[
        "manufactured",
        "housing-communities",
        "park"
    ],
    "wof:name":"Minix Mobile Home Park",
    "wof:placetype":"venue"
},
  "geometry": {"coordinates":[-84.07575199999999,31.57402],"type":"Point"}
}