{
  "type": "Feature",
  "properties": {
    "addr:full":"3660 Atlanta Hwy Athens GA 30606",
    "addr:housenumber":"3660",
    "addr:postcode":"30606",
    "addr:street":"Atlanta Hwy",
    "iso:country":"US",
    "sg:address":"3660 Atlanta Hwy",
    "sg:city":"Athens",
    "sg:classifiers":[
        {
            "category":"Home & Garden",
            "subcategory":"Home Furnishings",
            "type":"Retail Goods"
        }
    ],
    "sg:phone":"+1 706 227 4259",
    "sg:postcode":"30606",
    "sg:province":"GA",
    "sg:tags":[
        "housewares"
    ],
    "wof:name":"Bed Bath & Beyond 313",
    "wof:placetype":"venue"
},
  "geometry": {"coordinates":[-83.461512,33.939475],"type":"Point"}
}