{
  "type": "Feature",
  "properties": {
    "addr:full":"231 E Solomon St Griffin GA 30223",
    "addr:housenumber":"231",
    "addr:postcode":"30223",
    "addr:street":"E Solomon St",
    "iso:country":"US",
    "sg:address":"231 E Solomon St",
    "sg:city":"Griffin",
    "sg:classifiers":[
        {
            "category":"Government",
            "subcategory":"Office",
            "type":"Public Place"
        }
    ],
    "sg:phone":"+1 770 233 4130",
    "sg:postcode":"30223",
    "sg:province":"GA",
    "sg:tags":[
        "village"
    ],
    "wof:name":"Griffin Development Svc Dept",
    "wof:placetype":"venue"
},
  "geometry": {"coordinates":[-84.26179399999999,33.24867],"type":"Point"}
}