{
  "type": "Feature",
  "properties": {
    "addr:full":"1281 Beaverdale Rd NE Dalton GA 30721",
    "addr:housenumber":"1281",
    "addr:postcode":"30721",
    "addr:street":"Beaverdale Rd Ne",
    "iso:country":"US",
    "sg:address":"1281 Beaverdale Rd NE",
    "sg:city":"Dalton",
    "sg:classifiers":[
        {
            "category":"Food & Beverages",
            "subcategory":"Groceries & Convenience Stores",
            "type":"Retail Goods"
        }
    ],
    "sg:phone":"+1 706 259 3413",
    "sg:postcode":"30721",
    "sg:province":"GA",
    "wof:name":"Uncle Buck's General Store",
    "wof:placetype":"venue"
},
  "geometry": {"coordinates":[-84.88981099999999,34.867052],"type":"Point"}
}