{
  "type": "Feature",
  "properties": {
    "iso:country":"US",
    "sg:address":"7901 Cleo Dr",
    "sg:city":"Columbus",
    "sg:classifiers":[
        {
            "category":"Professional",
            "subcategory":"Business Services",
            "type":"Services"
        }
    ],
    "sg:phone":"+1 706 571 0075",
    "sg:postcode":"31909",
    "sg:province":"GA",
    "wof:name":"Total Cleaning Solutions",
    "wof:placetype":"venue"
},
  "geometry": {"coordinates":[-84.95285699999999,32.562904],"type":"Point"}
}