{
  "type": "Feature",
  "properties": {
    "iso:country":"US",
    "sg:address":"7275 Roswell Rd",
    "sg:city":"Atlanta",
    "sg:classifiers":[
        {
            "category":"Building & Trades",
            "subcategory":"Landscaping Services",
            "type":"Services"
        }
    ],
    "sg:phone":"+1 404 459 6867",
    "sg:postcode":"30328",
    "sg:province":"GA",
    "wof:name":"Brian Heitz",
    "wof:placetype":"venue"
},
  "geometry": {"coordinates":[-84.369156,33.950049],"type":"Point"}
}