{
  "type": "Feature",
  "properties": {
    "iso:country":"US",
    "sg:address":"2743 Perimeter Pkwy",
    "sg:city":"Augusta",
    "sg:classifiers":[
        {
            "category":"Real Estate",
            "subcategory":"Real Estate Agent",
            "type":"Services"
        },
        {
            "category":"Real Estate",
            "subcategory":"Real Estate Operator",
            "type":"Services"
        }
    ],
    "sg:phone":"+1 706 855 0116",
    "sg:postcode":"30909",
    "sg:province":"GA",
    "sg:tags":[
        "building",
        "agency",
        "radio",
        "advertising",
        "parks"
    ],
    "wof:name":"Augusta Corporate Centre",
    "wof:placetype":"venue"
},
  "geometry": {"coordinates":[-82.083493,33.487467],"type":"Point"}
}