{
  "type": "Feature",
  "properties": {
    "iso:country":"US",
    "sg:address":"437 Kings Way",
    "sg:city":"St Simons Island",
    "sg:classifiers":[
        {
            "category":"Travel",
            "subcategory":"Hotels & Motels",
            "type":"Entertainment"
        }
    ],
    "sg:phone":"+1 912 638 8459",
    "sg:postcode":"31522",
    "sg:province":"GA",
    "wof:name":"Queen's Court",
    "wof:placetype":"venue"
},
  "geometry": {"coordinates":[-81.39646399999999,31.137663],"type":"Point"}
}