{
  "type": "Feature",
  "properties": {
    "iso:country":"US",
    "sg:address":"395 Cleveland St",
    "sg:city":"Blairsville",
    "sg:classifiers":[
        {
            "category":"Health Services",
            "subcategory":"Doctor",
            "type":"Services"
        }
    ],
    "sg:phone":"+1 706 745 6848",
    "sg:postcode":"30512",
    "sg:province":"GA",
    "sg:tags":[
        "dentist"
    ],
    "wof:name":"Ageless Smiles",
    "wof:placetype":"venue"
},
  "geometry": {"coordinates":[-83.95496199999999,34.870642],"type":"Point"}
}