{
  "type": "Feature",
  "properties": {
    "iso:country":"US",
    "sg:address":"106 Pleasant Home Rd",
    "sg:city":"Augusta",
    "sg:classifiers":[
        {
            "category":"Professional",
            "subcategory":"Art Services",
            "type":"Services"
        }
    ],
    "sg:phone":"+1 706 650 8442",
    "sg:postcode":"30907",
    "sg:province":"GA",
    "sg:tags":[
        "graphic",
        "designer"
    ],
    "wof:name":"Red Nose Graphic & Web Design",
    "wof:placetype":"venue"
},
  "geometry": {"coordinates":[-82.070941,33.513027],"type":"Point"}
}