{
  "type": "Feature",
  "properties": {
    "addr:full":"599 Mitchell St SW Atlanta GA 30314",
    "addr:housenumber":"599",
    "addr:postcode":"30314",
    "addr:street":"Mitchell St Sw",
    "iso:country":"US",
    "sg:address":"599 Mitchell St SW",
    "sg:city":"Atlanta",
    "sg:classifiers":[
        {
            "category":"Education",
            "subcategory":"School",
            "type":"Public Place"
        }
    ],
    "sg:phone":"+1 404 549 7750",
    "sg:postcode":"30314",
    "sg:province":"GA",
    "wof:name":"Imhotep Academy",
    "wof:placetype":"venue"
},
  "geometry": {"coordinates":[-84.406547,33.754057],"type":"Point"}
}