{
  "type": "Feature",
  "properties": {
    "addr:full":"16 E 48th St Savannah GA 31405",
    "addr:housenumber":"16",
    "addr:postcode":"31405",
    "addr:street":"E 48Th St",
    "iso:country":"US",
    "sg:address":"16 E 48th St",
    "sg:city":"Savannah",
    "sg:classifiers":[
        {
            "category":"Real Estate",
            "subcategory":"Real Estate Agent",
            "type":"Services"
        }
    ],
    "sg:phone":"+1 912 236 2737",
    "sg:postcode":"31405",
    "sg:province":"GA",
    "wof:name":"Courington Realty",
    "wof:placetype":"venue"
},
  "geometry": {"coordinates":[-81.102057,32.048533],"type":"Point"}
}