{
  "type": "Feature",
  "properties": {
    "iso:country":"US",
    "sg:address":"2575 Snapfinger Rd",
    "sg:city":"Decatur",
    "sg:classifiers":[
        {
            "category":"Social Services",
            "subcategory":"Child Care",
            "type":"Services"
        }
    ],
    "sg:phone":"+1 678 418 2657",
    "sg:postcode":"30034",
    "sg:province":"GA",
    "sg:tags":[
        "day"
    ],
    "wof:name":"Active Learner",
    "wof:placetype":"venue"
},
  "geometry": {"coordinates":[-84.21578700000001,33.705008],"type":"Point"}
}