{
  "type": "Feature",
  "properties": {
    "iso:country":"US",
    "sg:address":"3851 Green Industrial Way",
    "sg:city":"Atlanta",
    "sg:classifiers":[
        {
            "category":"Manufacturing",
            "subcategory":"Wood Products",
            "type":"Manufacturing & Wholesale Goods"
        },
        {
            "category":"Manufacturing",
            "subcategory":"Furniture",
            "type":"Manufacturing & Wholesale Goods"
        },
        {
            "category":"Home & Garden",
            "subcategory":"Furniture",
            "type":"Retail Goods"
        }
    ],
    "sg:phone":"+1 770 455 1163",
    "sg:postcode":"30341",
    "sg:province":"GA",
    "sg:tags":[
        "designer",
        "builder",
        "custom",
        "millwork-wholesale",
        "millwork",
        "store",
        "manufacturer"
    ],
    "wof:name":"Torrente's Furniture & Millwork",
    "wof:placetype":"venue"
},
  "geometry": {"coordinates":[-84.298447,33.904228],"type":"Point"}
}