{
  "type": "Feature",
  "properties": {
    "iso:country":"US",
    "sg:address":"325 8th Ave NE",
    "sg:city":"Cairo",
    "sg:classifiers":[
        {
            "category":"Restaurant",
            "type":"Food & Drink"
        }
    ],
    "sg:phone":"+1 229 378 8828",
    "sg:postcode":"39828",
    "sg:province":"GA",
    "sg:tags":[
        "asian",
        "chinese",
        "pan"
    ],
    "wof:name":"No 1 China",
    "wof:placetype":"venue"
},
  "geometry": {"coordinates":[-84.20523300000001,30.885499],"type":"Point"}
}