{
  "type": "Feature",
  "properties": {
    "iso:country":"US",
    "sg:address":"2964 Ember Drive, Ste 135",
    "sg:city":"Decatur",
    "sg:phone":"+1 678 971 7703",
    "sg:postcode":"30034",
    "sg:province":"GA",
    "sg:website":"http://notarypublic.webs.com",
    "wof:name":"Creme-De-La Concepts",
    "wof:placetype":"venue"
},
  "geometry": {"coordinates":[-84.266994,33.712553],"type":"Point"}
}