{
  "type": "Feature",
  "properties": {
    "addr:full":"118 Bull St La Grange GA 30240",
    "addr:housenumber":"118",
    "addr:postcode":"30240",
    "addr:street":"Bull St",
    "iso:country":"US",
    "sg:address":"118 Bull St",
    "sg:city":"La Grange",
    "sg:classifiers":[
        {
            "category":"Personal",
            "subcategory":"Beauty Salon",
            "type":"Services"
        }
    ],
    "sg:phone":"+1 706 884 1090",
    "sg:postcode":"30240",
    "sg:province":"GA",
    "sg:tags":[
        "shop"
    ],
    "wof:name":"Hair Cutters Uptown",
    "wof:placetype":"venue"
},
  "geometry": {"coordinates":[-85.03211899999999,33.038494],"type":"Point"}
}