{
  "type": "Feature",
  "properties": {
    "iso:country":"US",
    "sg:address":"5150 Buford Hwy NE",
    "sg:city":"Atlanta",
    "sg:classifiers":[
        {
            "category":"Shopping",
            "subcategory":"Optical Goods",
            "type":"Retail Goods"
        },
        {
            "category":"Health Services",
            "subcategory":"Optometrist",
            "type":"Services"
        }
    ],
    "sg:phone":"+1 770 234 0306",
    "sg:postcode":"30329",
    "sg:province":"GA",
    "wof:name":"Eye Best",
    "wof:placetype":"venue"
},
  "geometry": {"coordinates":[-84.27763899999999,33.900019],"type":"Point"}
}