{
  "type": "Feature",
  "properties": {
    "addr:full":"13 Jessica Pl Marietta GA 30062",
    "addr:housenumber":"13",
    "addr:postcode":"30062",
    "addr:street":"Jessica Pl",
    "iso:country":"US",
    "sg:address":"13 Jessica Pl",
    "sg:city":"Marietta",
    "sg:classifiers":[
        {
            "category":"Professional",
            "type":"Services"
        }
    ],
    "sg:phone":"+1 770 552 1366",
    "sg:postcode":"30062",
    "sg:province":"GA",
    "wof:name":"Diane Paull",
    "wof:placetype":"venue"
},
  "geometry": {"coordinates":[-84.431862,34.016415],"type":"Point"}
}