{
  "type": "Feature",
  "properties": {
    "addr:full":"494 N Grove St Dahlonega GA 30533",
    "addr:housenumber":"494",
    "addr:postcode":"30533",
    "addr:street":"N Grove St",
    "iso:country":"US",
    "sg:address":"494 N Grove St",
    "sg:city":"Dahlonega",
    "sg:classifiers":[
        {
            "category":"Building & Trades",
            "subcategory":"Construction",
            "type":"Services"
        }
    ],
    "sg:phone":"+1 706 864 2598",
    "sg:postcode":"30533",
    "sg:province":"GA",
    "sg:tags":[
        "general",
        "contractor"
    ],
    "wof:name":"Self & Self General Contrs",
    "wof:placetype":"venue"
},
  "geometry": {"coordinates":[-83.985998,34.536999],"type":"Point"}
}