{
  "type": "Feature",
  "properties": {
    "iso:country":"US",
    "sg:address":"2530 Rockbridge Rd",
    "sg:city":"Stone Mountain",
    "sg:classifiers":[
        {
            "category":"Retail",
            "subcategory":"Laundry & Dry Cleaning",
            "type":"Services"
        }
    ],
    "sg:phone":"+1 770 465 6530",
    "sg:postcode":"30087",
    "sg:province":"GA",
    "wof:name":"Best Cleaners III",
    "wof:placetype":"venue"
},
  "geometry": {"coordinates":[-84.099197,33.811798],"type":"Point"}
}