{
  "type": "Feature",
  "properties": {
    "iso:country":"US",
    "sg:address":"2800 Cumberland Blvd SE",
    "sg:city":"Smyrna",
    "sg:classifiers":[
        {
            "category":"Shopping",
            "subcategory":"Jewelry",
            "type":"Retail Goods"
        }
    ],
    "sg:phone":"+1 770 434 4367",
    "sg:postcode":"30080",
    "sg:province":"GA",
    "sg:website":"www.cumberlanddiamond.com",
    "wof:name":"Cumberland Diamond Exchange",
    "wof:placetype":"venue"
},
  "geometry": {"coordinates":[-84.47519699999999,33.882301],"type":"Point"}
}