{
  "type": "Feature",
  "properties": {
    "addr:full":"2790 Buford Hwy Duluth GA 30096",
    "addr:housenumber":"2790",
    "addr:postcode":"30096",
    "addr:street":"Buford Hwy",
    "iso:country":"US",
    "sg:address":"2790 Buford Hwy",
    "sg:city":"Duluth",
    "sg:classifiers":[
        {
            "category":"Fast Food",
            "type":"Food & Drink"
        },
        {
            "category":"Restaurant",
            "type":"Food & Drink"
        }
    ],
    "sg:phone":"+1 770 622 7750",
    "sg:postcode":"30096",
    "sg:province":"GA",
    "sg:tags":[
        "shop",
        "hamburger",
        "dog",
        "hot",
        "fountain",
        "soda",
        "american"
    ],
    "sg:website":"http://www.awrestaurants.com",
    "wof:name":"A & W Restaurants",
    "wof:placetype":"venue"
},
  "geometry": {"coordinates":[-84.133467,34.007276],"type":"Point"}
}