{
  "type": "Feature",
  "properties": {
    "iso:country":"US",
    "sg:address":"50 Nimitz Dr",
    "sg:city":"Marietta",
    "sg:classifiers":[
        {
            "category":"Building & Trades",
            "subcategory":"Construction",
            "type":"Services"
        }
    ],
    "sg:phone":"+1 770 422 4038",
    "sg:postcode":"30060",
    "sg:province":"GA",
    "sg:tags":[
        "paving",
        "contractor"
    ],
    "wof:name":"C & S Paving",
    "wof:placetype":"venue"
},
  "geometry": {"coordinates":[-84.53247500000001,33.913018],"type":"Point"}
}