{
  "type": "Feature",
  "properties": {
    "addr:full":"4576 Ridgegate Dr NW Duluth GA 30097",
    "addr:housenumber":"4576",
    "addr:postcode":"30097",
    "addr:street":"Ridgegate Dr Nw",
    "iso:country":"US",
    "sg:address":"4576 Ridgegate Dr NW",
    "sg:city":"Duluth",
    "sg:phone":"+1 404 633 2944",
    "sg:postcode":"30097",
    "sg:province":"GA",
    "sg:tags":[
        "equipment",
        "grocery",
        "commercial"
    ],
    "wof:name":"Cyber Beverages",
    "wof:placetype":"venue"
},
  "geometry": {"coordinates":[-84.209248,33.995776],"type":"Point"}
}