{
  "type": "Feature",
  "properties": {
    "addr:full":"5150 Buford Hwy Ste 1 Norcross GA 30071",
    "addr:housenumber":"5150",
    "addr:postcode":"30071",
    "addr:street":"Buford Hwy Ste 1",
    "iso:country":"US",
    "sg:address":"5150 Buford Hwy Ste 1",
    "sg:city":"Norcross",
    "sg:classifiers":[
        {
            "category":"Building & Trades",
            "subcategory":"Construction",
            "type":"Services"
        }
    ],
    "sg:phone":"+1 770 449 3250",
    "sg:postcode":"30071",
    "sg:province":"GA",
    "sg:tags":[
        "contractor"
    ],
    "wof:name":"Woodwind Construction Company",
    "wof:placetype":"venue"
},
  "geometry": {"coordinates":[-84.194397,33.952702],"type":"Point"}
}