{
  "type": "Feature",
  "properties": {
    "iso:country":"US",
    "sg:address":"3823 Roswell Rd Ste 202",
    "sg:city":"Marietta",
    "sg:classifiers":[
        {
            "category":"Health Services",
            "subcategory":"Dentist",
            "type":"Services"
        }
    ],
    "sg:phone":"+1 770 977 1632",
    "sg:postcode":"30062",
    "sg:province":"GA",
    "wof:name":"East Marietta Family Dentistry",
    "wof:placetype":"venue"
},
  "geometry": {"coordinates":[-84.426804,33.984001],"type":"Point"}
}