{
  "type": "Feature",
  "properties": {
    "iso:country":"US",
    "sg:address":"221 Commodore Dr",
    "sg:city":"Savannah",
    "sg:classifiers":[
        {
            "category":"Professional",
            "subcategory":"Business Services",
            "type":"Services"
        }
    ],
    "sg:phone":"+1 912 897 6310",
    "sg:postcode":"31410",
    "sg:province":"GA",
    "wof:name":"Mobley Donna Ray Artistic Inte",
    "wof:placetype":"venue"
},
  "geometry": {"coordinates":[-81.012058,32.027363],"type":"Point"}
}