{
  "type": "Feature",
  "properties": {
    "addr:full":"7131 Pineneedle Dr SW Covington GA 30014",
    "addr:housenumber":"7131",
    "addr:postcode":"30014",
    "addr:street":"Pineneedle Dr Sw",
    "iso:country":"US",
    "sg:address":"7131 Pineneedle Dr SW",
    "sg:city":"Covington",
    "sg:classifiers":[
        {
            "category":"Professional",
            "type":"Services"
        }
    ],
    "sg:phone":"+1 770 786 0534",
    "sg:postcode":"30014",
    "sg:province":"GA",
    "wof:name":"Vickey Freeman",
    "wof:placetype":"venue"
},
  "geometry": {"coordinates":[-83.863124,33.580935],"type":"Point"}
}