{
  "type": "Feature",
  "properties": {
    "addr:full":"320 New Crossing Trl NE Kennesaw GA 30144",
    "addr:housenumber":"320",
    "addr:postcode":"30144",
    "addr:street":"New Crossing Trl Ne",
    "iso:country":"US",
    "sg:address":"320 New Crossing Trl NE",
    "sg:city":"Kennesaw",
    "sg:classifiers":[
        {
            "category":"Building & Trades",
            "subcategory":"Construction",
            "type":"Services"
        }
    ],
    "sg:phone":"+1 770 591 9407",
    "sg:postcode":"30144",
    "sg:province":"GA",
    "sg:tags":[
        "contractor"
    ],
    "wof:name":"Express Contracting Inc",
    "wof:placetype":"venue"
},
  "geometry": {"coordinates":[-84.53787699999999,34.05802],"type":"Point"}
}