{
  "type": "Feature",
  "properties": {
    "addr:full":"11770 Haynes Bridge Rd Alpharetta GA 30009",
    "addr:housenumber":"11770",
    "addr:postcode":"30009",
    "addr:street":"Haynes Bridge Rd",
    "iso:country":"US",
    "sg:address":"11770 Haynes Bridge Rd",
    "sg:city":"Alpharetta",
    "sg:phone":"+1 770 751 9898",
    "sg:postcode":"30009",
    "sg:province":"GA",
    "wof:name":"Locos Grill & Pub",
    "wof:placetype":"venue"
},
  "geometry": {"coordinates":[-84.29373200000001,34.069611],"type":"Point"}
}