{
  "type": "Feature",
  "properties": {
    "iso:country":"US",
    "sg:address":"3609 Shallowford Rd NE",
    "sg:city":"Atlanta",
    "sg:classifiers":[
        {
            "category":"Personal",
            "type":"Services"
        }
    ],
    "sg:phone":"+1 770 452 0087",
    "sg:postcode":"30340",
    "sg:province":"GA",
    "sg:tags":[
        "control",
        "weight"
    ],
    "wof:name":"Forma Vital",
    "wof:placetype":"venue"
},
  "geometry": {"coordinates":[-84.28460800000001,33.896689],"type":"Point"}
}