{
  "type": "Feature",
  "properties": {
    "iso:country":"US",
    "sg:address":"3127 Floyd Rd",
    "sg:city":"Augusta",
    "sg:classifiers":[
        {
            "category":"Health Services",
            "subcategory":"Medical Lab",
            "type":"Services"
        }
    ],
    "sg:phone":"+1 706 793 6229",
    "sg:postcode":"30906",
    "sg:province":"GA",
    "sg:tags":[
        "laboratory"
    ],
    "wof:name":"Norwood Crown & Bridge Dental",
    "wof:placetype":"venue"
},
  "geometry": {"coordinates":[-82.028359,33.410857],"type":"Point"}
}