{
  "type": "Feature",
  "properties": {
    "iso:country":"US",
    "sg:address":"136 Lincoln Dr",
    "sg:city":"Thomson",
    "sg:classifiers":[
        {
            "category":"Building & Trades",
            "subcategory":"Construction",
            "type":"Services"
        }
    ],
    "sg:phone":"+1 706 595 5890",
    "sg:postcode":"30824",
    "sg:province":"GA",
    "sg:tags":[
        "carpentry",
        "contractor"
    ],
    "wof:name":"Johnny F Murray",
    "wof:placetype":"venue"
},
  "geometry": {"coordinates":[-82.48546899999999,33.473357],"type":"Point"}
}