{
  "type": "Feature",
  "properties": {
    "iso:country":"US",
    "sg:address":"2655 N Decatur Rd",
    "sg:city":"Decatur",
    "sg:classifiers":[
        {
            "category":"Professional",
            "subcategory":"Business Services",
            "type":"Services"
        }
    ],
    "sg:phone":"+1 404 373 2547",
    "sg:postcode":"30033",
    "sg:province":"GA",
    "sg:tags":[
        "packaging",
        "mail",
        "drop",
        "location"
    ],
    "wof:name":"Mail Bag",
    "wof:placetype":"venue"
},
  "geometry": {"coordinates":[-84.281722,33.792341],"type":"Point"}
}