{
  "type": "Feature",
  "properties": {
    "addr:full":"4896 N Royal Atlanta Dr Tucker GA 30084",
    "addr:housenumber":"4896",
    "addr:postcode":"30084",
    "addr:street":"N Royal Atlanta Dr",
    "iso:country":"US",
    "sg:address":"4896 N Royal Atlanta Dr",
    "sg:city":"Tucker",
    "sg:classifiers":[
        {
            "category":"Banks & Credit Unions",
            "subcategory":"Investment Brokerage",
            "type":"Services"
        }
    ],
    "sg:phone":"+1 770 496 2721",
    "sg:postcode":"30084",
    "sg:province":"GA",
    "sg:tags":[
        "investing"
    ],
    "wof:name":"Asset Management Specialist",
    "wof:placetype":"venue"
},
  "geometry": {"coordinates":[-84.188047,33.859298],"type":"Point"}
}