{
  "type": "Feature",
  "properties": {
    "addr:full":"3100 Breckinridge Blvd Duluth GA 30096",
    "addr:housenumber":"3100",
    "addr:postcode":"30096",
    "addr:street":"Breckinridge Blvd",
    "iso:country":"US",
    "sg:address":"3100 Breckinridge Blvd",
    "sg:city":"Duluth",
    "sg:classifiers":[
        {
            "category":"Wholesale",
            "subcategory":"Books, Periodicals, & Newspapers",
            "type":"Manufacturing & Wholesale Goods"
        }
    ],
    "sg:phone":"+1 770 717 7007",
    "sg:postcode":"30096",
    "sg:province":"GA",
    "sg:tags":[
        "text"
    ],
    "wof:name":"Glencoe/Mc Graw-Hill Pubg",
    "wof:placetype":"venue"
},
  "geometry": {"coordinates":[-84.105648,33.960103],"type":"Point"}
}