{
  "type": "Feature",
  "properties": {
    "iso:country":"US",
    "sg:address":"811 Virginia Ave",
    "sg:city":"Hapeville",
    "sg:classifiers":[
        {
            "category":"Building & Trades",
            "subcategory":"Locksmith",
            "type":"Services"
        }
    ],
    "sg:phone":"+1 678 271 6451",
    "sg:postcode":"30354",
    "sg:province":"GA",
    "sg:tags":[
        "key"
    ],
    "wof:name":"24 Hbours A Locksmith",
    "wof:placetype":"venue"
},
  "geometry": {"coordinates":[-84.41597299999999,33.659726],"type":"Point"}
}