{
  "type": "Feature",
  "properties": {
    "addr:full":"1932 Shade Murphy Rd Moultrie GA 31768",
    "addr:housenumber":"1932",
    "addr:postcode":"31768",
    "addr:street":"Shade Murphy Rd",
    "iso:country":"US",
    "sg:address":"1932 Shade Murphy Rd",
    "sg:city":"Moultrie",
    "sg:classifiers":[
        {
            "category":"Government",
            "subcategory":"Office",
            "type":"Public Place"
        }
    ],
    "sg:phone":"+1 229 616 7460",
    "sg:postcode":"31768",
    "sg:province":"GA",
    "wof:name":"Colquitt Cnty Drug Task Force",
    "wof:placetype":"venue"
},
  "geometry": {"coordinates":[-83.843012,31.091557],"type":"Point"}
}