{
  "type": "Feature",
  "properties": {
    "addr:full":"251 Rio Cir Decatur GA 30030",
    "addr:housenumber":"251",
    "addr:postcode":"30030",
    "addr:street":"Rio Cir",
    "iso:country":"US",
    "sg:address":"251 Rio Cir",
    "sg:city":"Decatur",
    "sg:classifiers":[
        {
            "category":"Home & Garden",
            "subcategory":"Furniture",
            "type":"Retail Goods"
        }
    ],
    "sg:phone":"+1 404 377 4021",
    "sg:postcode":"30030",
    "sg:province":"GA",
    "sg:tags":[
        "carpentry",
        "contractor"
    ],
    "wof:name":"Cherokee Cabinet Shop Inc",
    "wof:placetype":"venue"
},
  "geometry": {"coordinates":[-84.270447,33.781609],"type":"Point"}
}