{
  "type": "Feature",
  "properties": {
    "addr:full":"4799 Arden Dr Buford GA 30518",
    "addr:housenumber":"4799",
    "addr:postcode":"30518",
    "addr:street":"Arden Dr",
    "iso:country":"US",
    "sg:address":"4799 Arden Dr",
    "sg:city":"Buford",
    "sg:classifiers":[
        {
            "category":"Retail",
            "subcategory":"Car Wash",
            "type":"Services"
        }
    ],
    "sg:phone":"+1 770 932 1447",
    "sg:postcode":"30518",
    "sg:province":"GA",
    "sg:tags":[
        "carwash"
    ],
    "wof:name":"William Epps Car Care",
    "wof:placetype":"venue"
},
  "geometry": {"coordinates":[-83.977964,34.121919],"type":"Point"}
}