{
  "type": "Feature",
  "properties": {
    "addr:full":"2958 Albion Farm Rd Duluth GA 30097",
    "addr:housenumber":"2958",
    "addr:postcode":"30097",
    "addr:street":"Albion Farm Rd",
    "iso:country":"US",
    "sg:address":"2958 Albion Farm Rd",
    "sg:city":"Duluth",
    "sg:classifiers":[
        {
            "category":"Arena",
            "subcategory":"Sports Club",
            "type":"Entertainment"
        }
    ],
    "sg:phone":"+1 770 476 9850",
    "sg:postcode":"30097",
    "sg:province":"GA",
    "sg:tags":[
        "martial art"
    ],
    "wof:name":"Gta Karate Family Martial Arts Center",
    "wof:placetype":"venue"
},
  "geometry": {"coordinates":[-84.14993,34.018567],"type":"Point"}
}