{
  "type": "Feature",
  "properties": {
    "iso:country":"US",
    "sg:address":"1517 Hillhaven Dr",
    "sg:city":"Marietta",
    "sg:classifiers":[
        {
            "category":"Real Estate",
            "subcategory":"Real Estate Services",
            "type":"Services"
        },
        {
            "category":"Real Estate",
            "subcategory":"Real Estate Agent",
            "type":"Services"
        }
    ],
    "sg:phone":"+1 770 579 0029",
    "sg:postcode":"30062",
    "sg:province":"GA",
    "sg:tags":[
        "management"
    ],
    "sg:website":"http://www.yvonnebrooksphotography.com",
    "wof:name":"Yvonne Brooks Inc",
    "wof:placetype":"venue"
},
  "geometry": {"coordinates":[-84.5068,33.98238],"type":"Point"}
}