{
  "type": "Feature",
  "properties": {
    "addr:full":"820 Glen Royal Dr Roswell GA 30076",
    "addr:housenumber":"820",
    "addr:postcode":"30076",
    "addr:street":"Glen Royal Dr",
    "iso:country":"US",
    "sg:address":"820 Glen Royal Dr",
    "sg:city":"Roswell",
    "sg:classifiers":[
        {
            "category":"Building & Trades",
            "subcategory":"Construction",
            "type":"Services"
        }
    ],
    "sg:phone":"+1 770 649 0681",
    "sg:postcode":"30076",
    "sg:province":"GA",
    "sg:tags":[
        "home",
        "family",
        "contractor"
    ],
    "wof:name":"Issa Homes Inc",
    "wof:placetype":"venue"
},
  "geometry": {"coordinates":[-84.277952,33.986735],"type":"Point"}
}