{
  "type": "Feature",
  "properties": {
    "addr:full":"5300 Sidney Simons Blvd Columbus GA 31904",
    "addr:housenumber":"5300",
    "addr:postcode":"31904",
    "addr:street":"Sidney Simons Blvd",
    "iso:country":"US",
    "sg:address":"5300 Sidney Simons Blvd",
    "sg:city":"Columbus",
    "sg:classifiers":[
        {
            "category":"Banks & Credit Unions",
            "subcategory":"Bank",
            "type":"Services"
        }
    ],
    "sg:phone":"+1 706 323 7373",
    "sg:postcode":"31904",
    "sg:province":"GA",
    "sg:tags":[
        "mortgage"
    ],
    "wof:name":"Beneficial",
    "wof:placetype":"venue"
},
  "geometry": {"coordinates":[-84.957195,32.518485],"type":"Point"}
}