{
  "type": "Feature",
  "properties": {
    "addr:full":"3543 Hancock Landing Rd Waynesboro GA 30830",
    "addr:housenumber":"3543",
    "addr:postcode":"30830",
    "addr:street":"Hancock Landing Rd",
    "iso:country":"US",
    "sg:address":"3543 Hancock Landing Rd",
    "sg:city":"Waynesboro",
    "sg:classifiers":[
        {
            "category":"Building & Trades",
            "subcategory":"Construction",
            "type":"Services"
        }
    ],
    "sg:phone":"+1 706 832 6588",
    "sg:postcode":"30830",
    "sg:province":"GA",
    "sg:tags":[
        "house"
    ],
    "wof:name":"Riverbend Construction",
    "wof:placetype":"venue"
},
  "geometry": {"coordinates":[-81.78917800000001,33.156613],"type":"Point"}
}