{
  "type": "Feature",
  "properties": {
    "iso:country":"US",
    "sg:address":"2181 Brockett Rd",
    "sg:city":"Tucker",
    "sg:classifiers":[
        {
            "category":"Retail",
            "subcategory":"Auto Repair",
            "type":"Services"
        }
    ],
    "sg:phone":"+1 770 934 0386",
    "sg:postcode":"30084",
    "sg:province":"GA",
    "sg:tags":[
        "truck"
    ],
    "wof:name":"Sobon's Truck Repair",
    "wof:placetype":"venue"
},
  "geometry": {"coordinates":[-84.22305900000001,33.848621],"type":"Point"}
}