{
  "type": "Feature",
  "properties": {
    "iso:country":"US",
    "sg:address":"17 Aviation Rd",
    "sg:city":"Marietta",
    "sg:classifiers":[
        {
            "category":"Real Estate",
            "subcategory":"Real Estate Agent",
            "type":"Services"
        }
    ],
    "sg:phone":"+1 770 427 5711",
    "sg:postcode":"30060",
    "sg:province":"GA",
    "sg:tags":[
        "management"
    ],
    "wof:name":"Mc Creary Realty Management",
    "wof:placetype":"venue"
},
  "geometry": {"coordinates":[-84.52703,33.94957],"type":"Point"}
}