{
  "type": "Feature",
  "properties": {
    "addr:full":"313 Ga Highway 49 N Byron GA 31008",
    "addr:housenumber":"313",
    "addr:postcode":"31008",
    "addr:street":"Ga Highway 49 N",
    "iso:country":"US",
    "sg:address":"313 Ga Highway 49 N",
    "sg:city":"Byron",
    "sg:phone":"+1 478 956 0320",
    "sg:postcode":"31008",
    "sg:province":"GA",
    "sg:website":"http://www.bk.com",
    "wof:name":"Burger King",
    "wof:placetype":"venue"
},
  "geometry": {"coordinates":[-83.75115099999999,32.655507],"type":"Point"}
}