{
  "type": "Feature",
  "properties": {
    "iso:country":"US",
    "sg:address":"496 Arnold Mill Rd",
    "sg:city":"Woodstock",
    "sg:classifiers":[
        {
            "category":"Insurance",
            "subcategory":"Hazard Insurance",
            "type":"Services"
        }
    ],
    "sg:phone":"+1 770 924 3293",
    "sg:postcode":"30188",
    "sg:province":"GA",
    "sg:tags":[
        "commercial",
        "business"
    ],
    "wof:name":"Dean Agency The",
    "wof:placetype":"venue"
},
  "geometry": {"coordinates":[-84.471825,34.118302],"type":"Point"}
}