{
  "type": "Feature",
  "properties": {
    "addr:full":"223 Perimeter Center Pkwy NE Atlanta GA 30346",
    "addr:housenumber":"223",
    "addr:postcode":"30346",
    "addr:street":"Perimeter Center Pkwy Ne",
    "iso:country":"US",
    "sg:address":"223 Perimeter Center Pkwy NE",
    "sg:city":"Atlanta",
    "sg:classifiers":[
        {
            "category":"Shopping",
            "subcategory":"Department Store",
            "type":"Retail Goods"
        },
        {
            "category":"Shopping",
            "subcategory":"Discount & Variety Stores",
            "type":"Retail Goods"
        }
    ],
    "sg:phone":"+1 770 913 5506",
    "sg:postcode":"30346",
    "sg:province":"GA",
    "wof:name":"Sue Frankiewiez",
    "wof:placetype":"venue"
},
  "geometry": {"coordinates":[-84.34530599999999,33.923309],"type":"Point"}
}