{
  "type": "Feature",
  "properties": {
    "addr:full":"125 Wc Bryant Pkwy Calhoun GA 30701",
    "addr:housenumber":"125",
    "addr:postcode":"30701",
    "addr:street":"Wc Bryant Pkwy",
    "iso:country":"US",
    "sg:address":"125 Wc Bryant Pkwy",
    "sg:city":"Calhoun",
    "sg:classifiers":[
        {
            "category":"Restaurant",
            "type":"Food & Drink"
        }
    ],
    "sg:phone":"+1 706 602 7827",
    "sg:postcode":"30701",
    "sg:province":"GA",
    "wof:name":"Blimpie Subs & Salads",
    "wof:placetype":"venue"
},
  "geometry": {"coordinates":[-84.94626100000001,34.483915],"type":"Point"}
}