{
  "type": "Feature",
  "properties": {
    "addr:full":"1475 Clearview Dr Ringgold GA 30736",
    "addr:housenumber":"1475",
    "addr:postcode":"30736",
    "addr:street":"Clearview Dr",
    "iso:country":"US",
    "sg:address":"1475 Clearview Dr",
    "sg:city":"Ringgold",
    "sg:classifiers":[
        {
            "category":"Shopping",
            "subcategory":"Gifts & Souvenirs",
            "type":"Retail Goods"
        }
    ],
    "sg:phone":"+1 706 965 4500",
    "sg:postcode":"30736",
    "sg:province":"GA",
    "sg:tags":[
        "shop"
    ],
    "wof:name":"Interlude Gifts & Designs",
    "wof:placetype":"venue"
},
  "geometry": {"coordinates":[-85.09538999999999,34.925872],"type":"Point"}
}