{
  "type": "Feature",
  "properties": {
    "iso:country":"US",
    "sg:address":"924 Gainesville Hwy",
    "sg:city":"Buford",
    "sg:classifiers":[
        {
            "category":"Wholesale",
            "subcategory":"Medical Equipment & Supplies",
            "type":"Manufacturing & Wholesale Goods"
        }
    ],
    "sg:phone":"+1 678 482 5032",
    "sg:postcode":"30518",
    "sg:province":"GA",
    "sg:tags":[
        "physician",
        "surgeon"
    ],
    "wof:name":"Rotech Health Care",
    "wof:placetype":"venue"
},
  "geometry": {"coordinates":[-83.96360799999999,34.146505],"type":"Point"}
}