{
  "type": "Feature",
  "properties": {
    "addr:full":"4512 Chateau Dr Albany GA 31721",
    "addr:housenumber":"4512",
    "addr:postcode":"31721",
    "addr:street":"Chateau Dr",
    "iso:country":"US",
    "sg:address":"4512 Chateau Dr",
    "sg:city":"Albany",
    "sg:classifiers":[
        {
            "category":"Professional",
            "type":"Services"
        }
    ],
    "sg:phone":"+1 229 639 2199",
    "sg:postcode":"31721",
    "sg:province":"GA",
    "wof:name":"Internet Services of Albany",
    "wof:placetype":"venue"
},
  "geometry": {"coordinates":[-84.270408,31.590756],"type":"Point"}
}