{
  "type": "Feature",
  "properties": {
    "addr:full":"3631 Peachtree Industrial Blvd Duluth GA 30096",
    "addr:housenumber":"3631",
    "addr:postcode":"30096",
    "addr:street":"Peachtree Industrial Blvd",
    "iso:country":"US",
    "sg:address":"3631 Peachtree Industrial Blvd",
    "sg:city":"Duluth",
    "sg:classifiers":[
        {
            "category":"Coffee & Tea",
            "type":"Food & Drink"
        }
    ],
    "sg:menulink":"http://www.allmenus.com/ga/suwanee-duluth/108036-starbucks-coffee/menu/",
    "sg:phone":"+1 770 622 3057",
    "sg:postcode":"30096",
    "sg:province":"GA",
    "sg:tags":[
        "american"
    ],
    "wof:name":"Starbucks Coffee",
    "wof:placetype":"venue"
},
  "geometry": {"coordinates":[-84.16818499999999,33.997874],"type":"Point"}
}