{
  "type": "Feature",
  "properties": {
    "iso:country":"US",
    "sg:address":"600 Peachtree Street NE",
    "sg:city":"Atlanta",
    "sg:classifiers":[
        {
            "category":"Professional",
            "subcategory":"Lawyer & Legal Services",
            "type":"Services"
        }
    ],
    "sg:phone":"+1 404 815 2133",
    "sg:postcode":"30308",
    "sg:province":"GA",
    "wof:name":"Dantin Suzanne H Atty",
    "wof:placetype":"venue"
},
  "geometry": {"coordinates":[-84.38501100000001,33.770996],"type":"Point"}
}