{
  "type": "Feature",
  "properties": {
    "iso:country":"US",
    "sg:address":"100 Cecil Ct",
    "sg:city":"Fayetteville",
    "sg:classifiers":[
        {
            "category":"Home & Garden",
            "subcategory":"Carpets & Floor Coverings",
            "type":"Retail Goods"
        }
    ],
    "sg:phone":"+1 770 460 9663",
    "sg:postcode":"30214",
    "sg:province":"GA",
    "wof:name":"Georgia Oak Floor Distributors",
    "wof:placetype":"venue"
},
  "geometry": {"coordinates":[-84.435592,33.500841],"type":"Point"}
}