{
  "type": "Feature",
  "properties": {
    "addr:full":"391 W Church St Plains GA 31780",
    "addr:housenumber":"391",
    "addr:postcode":"31780",
    "addr:street":"W Church St",
    "iso:country":"US",
    "sg:address":"391 W Church St",
    "sg:city":"Plains",
    "sg:classifiers":[
        {
            "category":"Farming",
            "subcategory":"Livestock Farm",
            "type":"Manufacturing & Wholesale Goods"
        }
    ],
    "sg:phone":"+1 229 824 5581",
    "sg:postcode":"31780",
    "sg:province":"GA",
    "sg:tags":[
        "hog",
        "or",
        "feedlot"
    ],
    "wof:name":"Young Hog Farm",
    "wof:placetype":"venue"
},
  "geometry": {"coordinates":[-84.398526,32.033951],"type":"Point"}
}