{
  "type": "Feature",
  "properties": {
    "iso:country":"US",
    "sg:address":"2840 Mitchell Dr",
    "sg:city":"Decatur",
    "sg:classifiers":[
        {
            "category":"Banks & Credit Unions",
            "subcategory":"Financial Services",
            "type":"Services"
        }
    ],
    "sg:phone":"+1 770 810 7129",
    "sg:postcode":"30032",
    "sg:province":"GA",
    "wof:name":"Pc Direct",
    "wof:placetype":"venue"
},
  "geometry": {"coordinates":[-84.273838,33.734582],"type":"Point"}
}