{
  "type": "Feature",
  "properties": {
    "addr:full":"644 Windy Hill Rd SE Smyrna GA 30080",
    "addr:housenumber":"644",
    "addr:postcode":"30080",
    "addr:street":"Windy Hill Rd Se",
    "iso:country":"US",
    "sg:address":"644 Windy Hill Rd SE",
    "sg:city":"Smyrna",
    "sg:classifiers":[
        {
            "category":"Social Services",
            "subcategory":"Child Care",
            "type":"Services"
        }
    ],
    "sg:phone":"+1 770 435 4896",
    "sg:postcode":"30080",
    "sg:province":"GA",
    "sg:tags":[
        "day"
    ],
    "wof:name":"All My Children Daycare Learing Center",
    "wof:placetype":"venue"
},
  "geometry": {"coordinates":[-84.535004,33.894402],"type":"Point"}
}