{
  "type": "Feature",
  "properties": {
    "iso:country":"US",
    "sg:address":"703 Anne St",
    "sg:city":"St Marys",
    "sg:classifiers":[
        {
            "category":"Building & Trades",
            "subcategory":"Construction",
            "type":"Services"
        }
    ],
    "sg:phone":"+1 912 882 0667",
    "sg:postcode":"31558",
    "sg:province":"GA",
    "sg:tags":[
        "roofing",
        "contractor"
    ],
    "wof:name":"Triple T Roofing",
    "wof:placetype":"venue"
},
  "geometry": {"coordinates":[-81.55649099999999,30.732148],"type":"Point"}
}