{
  "type": "Feature",
  "properties": {
    "addr:full":"1105 Rocky Creek Rd Macon GA 31206",
    "addr:housenumber":"1105",
    "addr:postcode":"31206",
    "addr:street":"Rocky Creek Rd",
    "iso:country":"US",
    "sg:address":"1105 Rocky Creek Rd",
    "sg:city":"Macon",
    "sg:classifiers":[
        {
            "category":"Retail",
            "subcategory":"Auto Repair",
            "type":"Services"
        }
    ],
    "sg:phone":"+1 478 785 9906",
    "sg:postcode":"31206",
    "sg:province":"GA",
    "sg:tags":[
        "glass",
        "coating",
        "tinting"
    ],
    "wof:name":"Tint Master",
    "wof:placetype":"venue"
},
  "geometry": {"coordinates":[-83.658165,32.791606],"type":"Point"}
}