{
  "type": "Feature",
  "properties": {
    "iso:country":"US",
    "sg:address":"3014 Heritage Rd NE Ste 1",
    "sg:city":"Milledgeville",
    "sg:classifiers":[
        {
            "category":"Home & Garden",
            "subcategory":"Garden Supply",
            "type":"Retail Goods"
        },
        {
            "category":"Government",
            "subcategory":"Office",
            "type":"Public Place"
        }
    ],
    "sg:phone":"+1 478 445 5766",
    "sg:postcode":"31061",
    "sg:province":"GA",
    "sg:tags":[
        "government-state",
        "conservation",
        "soil"
    ],
    "sg:website":"http://www.gaswcc.org",
    "wof:name":"Georgia Soil Water Con",
    "wof:placetype":"venue"
},
  "geometry": {"coordinates":[-83.258493,33.1215],"type":"Point"}
}