{
  "type": "Feature",
  "properties": {
    "iso:country":"US",
    "sg:address":"38 David Ln",
    "sg:city":"Newnan",
    "sg:classifiers":[
        {
            "category":"Banks & Credit Unions",
            "subcategory":"Bank",
            "type":"Services"
        }
    ],
    "sg:phone":"+1 770 254 9844",
    "sg:postcode":"30263",
    "sg:province":"GA",
    "sg:tags":[
        "mortgage"
    ],
    "wof:name":"Fiserv Mrtg Servicing Systems",
    "wof:placetype":"venue"
},
  "geometry": {"coordinates":[-84.86182599999999,33.390152],"type":"Point"}
}