{
  "type": "Feature",
  "properties": {
    "iso:country":"US",
    "sg:address":"2185 Northlake Pkwy",
    "sg:city":"Tucker",
    "sg:classifiers":[
        {
            "category":"Real Estate",
            "subcategory":"Real Estate Agent",
            "type":"Services"
        }
    ],
    "sg:phone":"+1 770 270 5551",
    "sg:postcode":"30084",
    "sg:province":"GA",
    "sg:tags":[
        "consultant"
    ],
    "wof:name":"Wealth Builders Intl",
    "wof:placetype":"venue"
},
  "geometry": {"coordinates":[-84.244529,33.847508],"type":"Point"}
}