{
  "type": "Feature",
  "properties": {
    "addr:full":"696 Antone St NW Atlanta GA 30318",
    "addr:housenumber":"696",
    "addr:postcode":"30318",
    "addr:street":"Antone St Nw",
    "iso:country":"US",
    "sg:address":"696 Antone St NW",
    "sg:city":"Atlanta",
    "sg:phone":"+1 404 603 9143",
    "sg:postcode":"30318",
    "sg:province":"GA",
    "wof:name":"Highland Waterworks",
    "wof:placetype":"venue"
},
  "geometry": {"coordinates":[-84.411354,33.79781],"type":"Point"}
}