{
  "type": "Feature",
  "properties": {
    "iso:country":"US",
    "sg:address":"607 Atlantic Dr",
    "sg:city":"St Simons Island",
    "sg:classifiers":[
        {
            "category":"Building & Trades",
            "subcategory":"Construction",
            "type":"Services"
        }
    ],
    "sg:phone":"+1 912 638 3555",
    "sg:postcode":"31522",
    "sg:province":"GA",
    "sg:tags":[
        "nonresidential"
    ],
    "wof:name":"David Colquitt Construction",
    "wof:placetype":"venue"
},
  "geometry": {"coordinates":[-81.387281,31.188433],"type":"Point"}
}