{
  "type": "Feature",
  "properties": {
    "iso:country":"US",
    "sg:address":"6280 Ponderosa Ct",
    "sg:city":"Atlanta",
    "sg:classifiers":[
        {
            "category":"Food & Beverages",
            "subcategory":"Groceries & Convenience Stores",
            "type":"Retail Goods"
        }
    ],
    "sg:phone":"+1 770 909 9078",
    "sg:postcode":"30349",
    "sg:province":"GA",
    "wof:name":"Andreas Living Foods Market",
    "wof:placetype":"venue"
},
  "geometry": {"coordinates":[-84.495351,33.58656],"type":"Point"}
}