{
  "type": "Feature",
  "properties": {
    "iso:country":"US",
    "sg:address":"1704 Strand Ave",
    "sg:city":"Tybee Island",
    "sg:classifiers":[
        {
            "category":"Building & Trades",
            "subcategory":"Construction",
            "type":"Services"
        }
    ],
    "sg:phone":"+1 912 786 7955",
    "sg:postcode":"31328",
    "sg:province":"GA",
    "sg:tags":[
        "general",
        "contractor"
    ],
    "wof:name":"Pelican Point",
    "wof:placetype":"venue"
},
  "geometry": {"coordinates":[-80.848123,31.989629],"type":"Point"}
}