{
  "type": "Feature",
  "properties": {
    "addr:full":"748 N Main St Cedartown GA 30125",
    "addr:housenumber":"748",
    "addr:postcode":"30125",
    "addr:street":"N Main St",
    "iso:country":"US",
    "sg:address":"748 N Main St",
    "sg:city":"Cedartown",
    "sg:classifiers":[
        {
            "category":"Personal",
            "subcategory":"Nail Salon",
            "type":"Services"
        }
    ],
    "sg:phone":"+1 770 748 2332",
    "sg:postcode":"30125",
    "sg:province":"GA",
    "wof:name":"Nations Nail",
    "wof:placetype":"venue"
},
  "geometry": {"coordinates":[-85.253292,33.989521],"type":"Point"}
}