{
  "type": "Feature",
  "properties": {
    "addr:full":"100 Crescent Center Pkwy Tucker GA 30084",
    "addr:housenumber":"100",
    "addr:postcode":"30084",
    "addr:street":"Crescent Center Pkwy",
    "iso:country":"US",
    "sg:address":"100 Crescent Center Pkwy",
    "sg:city":"Tucker",
    "sg:classifiers":[
        {
            "category":"Restaurant",
            "type":"Food & Drink"
        }
    ],
    "sg:phone":"+1 770 939 5583",
    "sg:postcode":"30084",
    "sg:province":"GA",
    "wof:name":"Maurice's Cafe",
    "wof:placetype":"venue"
},
  "geometry": {"coordinates":[-84.247697,33.838285],"type":"Point"}
}