{
  "type": "Feature",
  "properties": {
    "iso:country":"US",
    "sg:address":"104 8th St W",
    "sg:city":"Tifton",
    "sg:classifiers":[
        {
            "category":"Professional",
            "subcategory":"Employment Agencies",
            "type":"Services"
        }
    ],
    "sg:phone":"+1 229 386 8689",
    "sg:postcode":"31794",
    "sg:province":"GA",
    "sg:tags":[
        "opportunity"
    ],
    "wof:name":"Quality Employment Service",
    "wof:placetype":"venue"
},
  "geometry": {"coordinates":[-83.507424,31.459656],"type":"Point"}
}