{
  "type": "Feature",
  "properties": {
    "addr:full":"413 Sunset Dr SE Acworth GA 30102",
    "addr:housenumber":"413",
    "addr:postcode":"30102",
    "addr:street":"Sunset Dr Se",
    "iso:country":"US",
    "sg:address":"413 Sunset Dr SE",
    "sg:city":"Acworth",
    "sg:classifiers":[
        {
            "category":"Professional",
            "type":"Services"
        }
    ],
    "sg:phone":"+1 770 529 0847",
    "sg:postcode":"30102",
    "sg:province":"GA",
    "wof:name":"Terri Dieter",
    "wof:placetype":"venue"
},
  "geometry": {"coordinates":[-84.707222,34.092901],"type":"Point"}
}