{
  "type": "Feature",
  "properties": {
    "iso:country":"US",
    "sg:address":"517 Rising Dr",
    "sg:city":"Woodstock",
    "sg:classifiers":[
        {
            "category":"Building & Trades",
            "subcategory":"Equipment Rental",
            "type":"Services"
        }
    ],
    "sg:phone":"+1 678 494 3438",
    "sg:postcode":"30189",
    "sg:province":"GA",
    "sg:tags":[
        "yard",
        "leasing",
        "store"
    ],
    "wof:name":"Beat All Rental",
    "wof:placetype":"venue"
},
  "geometry": {"coordinates":[-84.557767,34.107904],"type":"Point"}
}