{
  "type": "Feature",
  "properties": {
    "addr:full":"3395 Northeast Expy Suite 150 Atlanta GA 30341",
    "addr:housenumber":"3395",
    "addr:postcode":"30341",
    "addr:street":"Northeast Expy Suite 150",
    "iso:country":"US",
    "sg:address":"3395 Northeast Expy Suite 150",
    "sg:city":"Atlanta",
    "sg:classifiers":[
        {
            "category":"Health Services",
            "subcategory":"Health Practitioner",
            "type":"Services"
        }
    ],
    "sg:phone":"+1 770 452 1684",
    "sg:postcode":"30341",
    "sg:province":"GA",
    "sg:tags":[
        "home",
        "care"
    ],
    "sg:website":"www.homehealthcareatlanta.com",
    "wof:name":"Home Health Care Atlanta",
    "wof:placetype":"venue"
},
  "geometry": {"coordinates":[-84.258402,33.892149],"type":"Point"}
}