{
  "type": "Feature",
  "properties": {
    "iso:country":"US",
    "sg:address":"4500 Winters Chapel Rd",
    "sg:city":"Atlanta",
    "sg:classifiers":[
        {
            "category":"Professional",
            "subcategory":"Business Services",
            "type":"Services"
        },
        {
            "category":"Organizations",
            "subcategory":"Professional Association",
            "type":"Services"
        }
    ],
    "sg:phone":"+1 770 242 9277",
    "sg:postcode":"30360",
    "sg:province":"GA",
    "sg:tags":[
        "referral",
        "contractor"
    ],
    "sg:website":"http://www.iecatlanta.com",
    "wof:name":"I E C",
    "wof:placetype":"venue"
},
  "geometry": {"coordinates":[-84.269125,33.926402],"type":"Point"}
}