{
  "type": "Feature",
  "properties": {
    "iso:country":"US",
    "sg:address":"1702 Hazel St",
    "sg:city":"Waycross",
    "sg:classifiers":[
        {
            "category":"Building & Trades",
            "subcategory":"Construction",
            "type":"Services"
        }
    ],
    "sg:phone":"+1 912 285 2761",
    "sg:postcode":"31501",
    "sg:province":"GA",
    "sg:tags":[
        "contractor"
    ],
    "wof:name":"Jjs Masonry",
    "wof:placetype":"venue"
},
  "geometry": {"coordinates":[-82.362634,31.235128],"type":"Point"}
}