{
  "type": "Feature",
  "properties": {
    "addr:full":"4165 Old Milton Pkwy Ste 100 Alpharetta GA 30005",
    "addr:housenumber":"4165",
    "addr:postcode":"30005",
    "addr:street":"Old Milton Pkwy Ste 100",
    "iso:country":"US",
    "sg:address":"4165 Old Milton Pkwy Ste 100",
    "sg:city":"Alpharetta",
    "sg:classifiers":[
        {
            "category":"Health Services",
            "subcategory":"Doctor",
            "type":"Services"
        }
    ],
    "sg:phone":"+1 770 667 0904",
    "sg:postcode":"30005",
    "sg:province":"GA",
    "sg:tags":[
        "surgeon",
        "cosmetic"
    ],
    "wof:name":"Plastic Surgery Association of Atlanta PC",
    "wof:placetype":"venue"
},
  "geometry": {"coordinates":[-84.23719800000001,34.059399],"type":"Point"}
}