{
  "type": "Feature",
  "properties": {
    "iso:country":"US",
    "sg:address":"360 Bay St",
    "sg:city":"Augusta",
    "sg:classifiers":[
        {
            "category":"Building & Trades",
            "subcategory":"Cleaning & Sanitation",
            "type":"Services"
        }
    ],
    "sg:phone":"+1 706 722 7122",
    "sg:postcode":"30901",
    "sg:province":"GA",
    "sg:tags":[
        "maintenance"
    ],
    "wof:name":"New South Building",
    "wof:placetype":"venue"
},
  "geometry": {"coordinates":[-81.95531699999999,33.473878],"type":"Point"}
}