{
  "type": "Feature",
  "properties": {
    "addr:full":"821 Atlanta St Roswell GA 30075",
    "addr:housenumber":"821",
    "addr:postcode":"30075",
    "addr:street":"Atlanta St",
    "iso:country":"US",
    "sg:address":"821 Atlanta St",
    "sg:city":"Roswell",
    "sg:classifiers":[
        {
            "category":"Shopping",
            "subcategory":"Pharmacy",
            "type":"Retail Goods"
        }
    ],
    "sg:phone":"+1 678 461 2984",
    "sg:postcode":"30075",
    "sg:province":"GA",
    "sg:tags":[
        "drugstore"
    ],
    "sg:website":"www.cvs.com",
    "wof:name":"Cvs Pharmacy",
    "wof:placetype":"venue"
},
  "geometry": {"coordinates":[-84.361801,34.021099],"type":"Point"}
}