{
  "type": "Feature",
  "properties": {
    "iso:country":"US",
    "sg:address":"4520 Buena Vista Rd",
    "sg:city":"Columbus",
    "sg:classifiers":[
        {
            "category":"Shopping",
            "subcategory":"Used Merchandise",
            "type":"Retail Goods"
        }
    ],
    "sg:phone":"+1 706 563 7636",
    "sg:postcode":"31907",
    "sg:province":"GA",
    "wof:name":"Federal Pawn Shop",
    "wof:placetype":"venue"
},
  "geometry": {"coordinates":[-84.919217,32.465091],"type":"Point"}
}