{
  "type": "Feature",
  "properties": {
    "addr:full":"431 E College St Jackson GA 30233",
    "addr:housenumber":"431",
    "addr:postcode":"30233",
    "addr:street":"E College St",
    "iso:country":"US",
    "sg:address":"431 E College St",
    "sg:city":"Jackson",
    "sg:classifiers":[
        {
            "category":"Organizations",
            "subcategory":"Professional Association",
            "type":"Services"
        }
    ],
    "sg:phone":"+1 770 775 4851",
    "sg:postcode":"30233",
    "sg:province":"GA",
    "sg:tags":[
        "chambers",
        "commerce"
    ],
    "wof:name":"Butts County Ind Development",
    "wof:placetype":"venue"
},
  "geometry": {"coordinates":[-83.96297,33.292971],"type":"Point"}
}