{
  "type": "Feature",
  "properties": {
    "iso:country":"US",
    "sg:address":"270 Cobb Pkwy S",
    "sg:city":"Marietta",
    "sg:classifiers":[
        {
            "category":"Professional",
            "subcategory":"Computer Services",
            "type":"Services"
        }
    ],
    "sg:phone":"+1 770 428 6998",
    "sg:postcode":"30006",
    "sg:province":"GA",
    "sg:tags":[
        "repair"
    ],
    "wof:name":"Ginstar Computer",
    "wof:placetype":"venue"
},
  "geometry": {"coordinates":[-84.52516300000001,33.957711],"type":"Point"}
}