{
  "type": "Feature",
  "properties": {
    "iso:country":"US",
    "sg:address":"1132 Graydon St",
    "sg:city":"Savannah",
    "sg:classifiers":[
        {
            "category":"Professional",
            "subcategory":"Management & Consulting",
            "type":"Services"
        }
    ],
    "sg:phone":"+1 912 201 0065",
    "sg:postcode":"31404",
    "sg:province":"GA",
    "wof:name":"Player Coach & Co LLC",
    "wof:placetype":"venue"
},
  "geometry": {"coordinates":[-81.078306,32.062199],"type":"Point"}
}