{
  "type": "Feature",
  "properties": {
    "iso:country":"US",
    "sg:address":"5128 Summerwood Ln",
    "sg:city":"Young Harris",
    "sg:classifiers":[
        {
            "category":"Professional",
            "subcategory":"Management & Consulting",
            "type":"Services"
        }
    ],
    "sg:phone":"+1 706 379 1248",
    "sg:postcode":"30582",
    "sg:province":"GA",
    "wof:name":"Mountain Valley Acres Inc",
    "wof:placetype":"venue"
},
  "geometry": {"coordinates":[-83.847725,34.959793],"type":"Point"}
}