{
  "type": "Feature",
  "properties": {
    "iso:country":"US",
    "sg:address":"111 Sunnymeade Dr",
    "sg:city":"Valdosta",
    "sg:classifiers":[
        {
            "category":"Professional",
            "subcategory":"Business Services",
            "type":"Services"
        }
    ],
    "sg:phone":"+1 229 245 7923",
    "sg:postcode":"31605",
    "sg:province":"GA",
    "wof:name":"C Jackson Interiors",
    "wof:placetype":"venue"
},
  "geometry": {"coordinates":[-83.29448600000001,30.890693],"type":"Point"}
}