{
  "type": "Feature",
  "properties": {
    "iso:country":"US",
    "sg:address":"5070 Elrod Cir",
    "sg:city":"Cumming",
    "sg:classifiers":[
        {
            "category":"Manufacturing",
            "subcategory":"Tools & Machinery",
            "type":"Manufacturing & Wholesale Goods"
        }
    ],
    "sg:phone":"+1 770 887 6887",
    "sg:postcode":"30041",
    "sg:province":"GA",
    "sg:tags":[
        "lift",
        "boat"
    ],
    "wof:name":"J & L Dock Supplies",
    "wof:placetype":"venue"
},
  "geometry": {"coordinates":[-84.059923,34.250362],"type":"Point"}
}