{
  "type": "Feature",
  "properties": {
    "iso:country":"US",
    "sg:address":"7630 Hardrock Rd",
    "sg:city":"Douglasville",
    "sg:classifiers":[
        {
            "category":"Retail",
            "subcategory":"Auto Repair",
            "type":"Services"
        }
    ],
    "sg:phone":"+1 770 489 4468",
    "sg:postcode":"30134",
    "sg:province":"GA",
    "sg:tags":[
        "repairing",
        "automobile"
    ],
    "wof:name":"Hard Rock Automotive Inc",
    "wof:placetype":"venue"
},
  "geometry": {"coordinates":[-84.77570299999999,33.740002],"type":"Point"}
}