{
  "type": "Feature",
  "properties": {
    "iso:country":"US",
    "sg:address":"637 Simpson St NW",
    "sg:city":"Atlanta",
    "sg:classifiers":[
        {
            "category":"Organizations",
            "subcategory":"Religious Organization",
            "type":"Services"
        }
    ],
    "sg:phone":"+1 404 524 0981",
    "sg:postcode":"30314",
    "sg:province":"GA",
    "wof:name":"Thessalonian Baptist Church",
    "wof:placetype":"venue"
},
  "geometry": {"coordinates":[-84.408357,33.763508],"type":"Point"}
}