{
  "type": "Feature",
  "properties": {
    "iso:country":"US",
    "sg:address":"201 Peachtree Cir NE",
    "sg:city":"Atlanta",
    "sg:classifiers":[
        {
            "category":"Professional",
            "subcategory":"Lawyer & Legal Services",
            "type":"Services"
        }
    ],
    "sg:phone":"+1 404 873 2544",
    "sg:postcode":"30309",
    "sg:province":"GA",
    "sg:tags":[
        "attorney",
        "resource",
        "environment",
        "natural",
        "law"
    ],
    "wof:name":"Butler, George E Il Esq Attorney",
    "wof:placetype":"venue"
},
  "geometry": {"coordinates":[-84.38475,33.794971],"type":"Point"}
}