{
  "type": "Feature",
  "properties": {
    "addr:full":"2795 Lake Monroe Rd Douglasville GA 30135",
    "addr:housenumber":"2795",
    "addr:postcode":"30135",
    "addr:street":"Lake Monroe Rd",
    "iso:country":"US",
    "sg:address":"2795 Lake Monroe Rd",
    "sg:city":"Douglasville",
    "sg:classifiers":[
        {
            "category":"Building & Trades",
            "subcategory":"Construction",
            "type":"Services"
        }
    ],
    "sg:phone":"+1 770 947 0401",
    "sg:postcode":"30135",
    "sg:province":"GA",
    "sg:tags":[
        "contractor"
    ],
    "wof:name":"Builders of Metro Atlanta",
    "wof:placetype":"venue"
},
  "geometry": {"coordinates":[-84.66709899999999,33.7299],"type":"Point"}
}