{
  "type": "Feature",
  "properties": {
    "iso:country":"US",
    "sg:address":"2001 Westside Pkwy",
    "sg:city":"Alpharetta",
    "sg:classifiers":[
        {
            "category":"Shopping",
            "subcategory":"Computers & Home Electronics",
            "type":"Retail Goods"
        },
        {
            "category":"Professional",
            "subcategory":"Computer Services",
            "type":"Services"
        }
    ],
    "sg:phone":"+1 678 393 1704",
    "sg:postcode":"30004",
    "sg:province":"GA",
    "sg:tags":[
        "development",
        "software",
        "internet"
    ],
    "wof:name":"Abel Solutions Inc",
    "wof:placetype":"venue"
},
  "geometry": {"coordinates":[-84.28804,34.061019],"type":"Point"}
}