{
  "type": "Feature",
  "properties": {
    "iso:country":"US",
    "sg:address":"1633 Devon Ct",
    "sg:city":"Stone Mountain",
    "sg:classifiers":[
        {
            "category":"Building & Trades",
            "subcategory":"Cleaning & Sanitation",
            "type":"Services"
        }
    ],
    "sg:phone":"+1 770 981 3811",
    "sg:postcode":"30088",
    "sg:province":"GA",
    "sg:tags":[
        "maintenance"
    ],
    "wof:name":"Mighty Man Cleaning Svc",
    "wof:placetype":"venue"
},
  "geometry": {"coordinates":[-84.194901,33.74305],"type":"Point"}
}