{
  "type": "Feature",
  "properties": {
    "addr:full":"249 Oakwood Cir Stockbridge GA 30281",
    "addr:housenumber":"249",
    "addr:postcode":"30281",
    "addr:street":"Oakwood Cir",
    "iso:country":"US",
    "sg:address":"249 Oakwood Cir",
    "sg:city":"Stockbridge",
    "sg:classifiers":[
        {
            "category":"Professional",
            "subcategory":"Art Services",
            "type":"Services"
        }
    ],
    "sg:phone":"+1 678 570 5991",
    "sg:postcode":"30281",
    "sg:province":"GA",
    "sg:tags":[
        "graphic",
        "commercial",
        "designer",
        "artist"
    ],
    "wof:name":"Wedge Events",
    "wof:placetype":"venue"
},
  "geometry": {"coordinates":[-84.240611,33.506043],"type":"Point"}
}