{
  "type": "Feature",
  "properties": {
    "iso:country":"US",
    "sg:address":"425 Augusta Rd",
    "sg:city":"North Augusta",
    "sg:classifiers":[
        {
            "category":"Building & Trades",
            "subcategory":"Construction",
            "type":"Services"
        }
    ],
    "sg:phone":"+1 803 278 1613",
    "sg:postcode":"29822",
    "sg:province":"SC",
    "sg:tags":[
        "home",
        "contractor"
    ],
    "wof:name":"Lewis Hadden Inc",
    "wof:placetype":"venue"
},
  "geometry": {"coordinates":[-81.892058,33.496704],"type":"Point"}
}