{
  "type": "Feature",
  "properties": {
    "addr:full":"425 Augusta Rd North Augusta SC 29822",
    "addr:housenumber":"425",
    "addr:postcode":"29822",
    "addr:street":"Augusta Rd",
    "iso:country":"US",
    "sg:address":"425 Augusta Rd",
    "sg:city":"North Augusta",
    "sg:classifiers":[
        {
            "category":"Building & Trades",
            "subcategory":"Construction",
            "type":"Services"
        }
    ],
    "sg:phone":"+1 803 278 1613",
    "sg:postcode":"29822",
    "sg:province":"SC",
    "sg:tags":[
        "home",
        "contractor"
    ],
    "wof:name":"Lewis Hadden Inc",
    "wof:placetype":"venue"
},
  "geometry": {"coordinates":[-81.89205800000001,33.496704],"type":"Point"}
}