{
  "type": "Feature",
  "properties": {
    "addr:full":"2911 Lonesome Rd Albany GA 31721",
    "addr:housenumber":"2911",
    "addr:postcode":"31721",
    "addr:street":"Lonesome Rd",
    "iso:country":"US",
    "sg:address":"2911 Lonesome Rd",
    "sg:city":"Albany",
    "sg:classifiers":[
        {
            "category":"Restaurant",
            "type":"Food & Drink"
        }
    ],
    "sg:phone":"+1 229 436 4539",
    "sg:postcode":"31721",
    "sg:province":"GA",
    "sg:tags":[
        "eating"
    ],
    "wof:name":"Lawson Music Catering",
    "wof:placetype":"venue"
},
  "geometry": {"coordinates":[-84.232051,31.494585],"type":"Point"}
}