{
  "type": "Feature",
  "properties": {
    "addr:full":"764 Bass Ln Dublin GA 31021",
    "addr:housenumber":"764",
    "addr:postcode":"31021",
    "addr:street":"Bass Ln",
    "iso:country":"US",
    "sg:address":"764 Bass Ln",
    "sg:city":"Dublin",
    "sg:classifiers":[
        {
            "category":"Building & Trades",
            "subcategory":"Landscaping Services",
            "type":"Services"
        }
    ],
    "sg:phone":"+1 478 272 1448",
    "sg:postcode":"31021",
    "sg:province":"GA",
    "sg:tags":[
        "lawn",
        "maintenance",
        "grounds"
    ],
    "wof:name":"Pitts Lawn Care",
    "wof:placetype":"venue"
},
  "geometry": {"coordinates":[-82.916911,32.477822],"type":"Point"}
}