{
  "type": "Feature",
  "properties": {
    "addr:full":"1880 Panola Rd Lithonia GA 30058",
    "addr:housenumber":"1880",
    "addr:postcode":"30058",
    "addr:street":"Panola Rd",
    "iso:country":"US",
    "sg:address":"1880 Panola Rd",
    "sg:city":"Lithonia",
    "sg:classifiers":[
        {
            "category":"Utilities",
            "subcategory":"Refuse",
            "type":"Services"
        }
    ],
    "sg:phone":"+1 770 987 9075",
    "sg:postcode":"30058",
    "sg:province":"GA",
    "sg:tags":[
        "garbage",
        "collection"
    ],
    "wof:name":"Cruz Hauling Construction",
    "wof:placetype":"venue"
},
  "geometry": {"coordinates":[-84.168679,33.735742],"type":"Point"}
}