{
  "type": "Feature",
  "properties": {
    "addr:full":"516 Avrett Ct Evans GA 30809",
    "addr:housenumber":"516",
    "addr:postcode":"30809",
    "addr:street":"Avrett Ct",
    "iso:country":"US",
    "sg:address":"516 Avrett Ct",
    "sg:city":"Evans",
    "sg:classifiers":[
        {
            "category":"Freight",
            "type":"Transportation"
        }
    ],
    "sg:phone":"+1 706 863 3332",
    "sg:postcode":"30809",
    "sg:province":"GA",
    "sg:tags":[
        "general"
    ],
    "wof:name":"Evans Self Storage",
    "wof:placetype":"venue"
},
  "geometry": {"coordinates":[-82.19086299999999,33.554802],"type":"Point"}
}