{
  "type": "Feature",
  "properties": {
    "addr:full":"110 W Main St Hahira GA 31632",
    "addr:housenumber":"110",
    "addr:postcode":"31632",
    "addr:street":"W Main St",
    "iso:country":"US",
    "sg:address":"110 W Main St",
    "sg:city":"Hahira",
    "sg:classifiers":[
        {
            "category":"Banks & Credit Unions",
            "subcategory":"Bank",
            "type":"Services"
        }
    ],
    "sg:phone":"+1 229 794 2494",
    "sg:postcode":"31632",
    "sg:province":"GA",
    "wof:name":"Commercial Banking Co",
    "wof:placetype":"venue"
},
  "geometry": {"coordinates":[-83.373769,30.991189],"type":"Point"}
}