{
  "type": "Feature",
  "properties": {
    "iso:country":"US",
    "sg:address":"203 S Clayton St",
    "sg:city":"Lawrenceville",
    "sg:classifiers":[
        {
            "category":"Shopping",
            "subcategory":"Florist",
            "type":"Retail Goods"
        }
    ],
    "sg:phone":"+1 770 339 6463",
    "sg:postcode":"30045",
    "sg:province":"GA",
    "wof:name":"Garden Basket",
    "wof:placetype":"venue"
},
  "geometry": {"coordinates":[-83.98524999999999,33.945781],"type":"Point"}
}