{
  "type": "Feature",
  "properties": {
    "addr:full":"445 Meadowfield Ct Lawrenceville GA 30043",
    "addr:housenumber":"445",
    "addr:postcode":"30043",
    "addr:street":"Meadowfield Ct",
    "iso:country":"US",
    "sg:address":"445 Meadowfield Ct",
    "sg:city":"Lawrenceville",
    "sg:classifiers":[
        {
            "category":"Building & Trades",
            "subcategory":"Construction",
            "type":"Services"
        }
    ],
    "sg:phone":"+1 770 339 8876",
    "sg:postcode":"30043",
    "sg:province":"GA",
    "wof:name":"Raines Mark A Etal",
    "wof:placetype":"venue"
},
  "geometry": {"coordinates":[-84.01840199999999,33.984311],"type":"Point"}
}