{
  "type": "Feature",
  "properties": {
    "addr:full":"121 Center St Avondale Estates GA 30002",
    "addr:housenumber":"121",
    "addr:postcode":"30002",
    "addr:street":"Center St",
    "iso:country":"US",
    "sg:address":"121 Center St",
    "sg:city":"Avondale Estates",
    "sg:classifiers":[
        {
            "category":"Wholesale",
            "subcategory":"Durable Goods & Equipment",
            "type":"Manufacturing & Wholesale Goods"
        }
    ],
    "sg:phone":"+1 404 296 2839",
    "sg:postcode":"30002",
    "sg:province":"GA",
    "sg:tags":[
        "exporter"
    ],
    "wof:name":"Global Expediting & Marketing",
    "wof:placetype":"venue"
},
  "geometry": {"coordinates":[-84.26839099999999,33.777024],"type":"Point"}
}