{
  "type": "Feature",
  "properties": {
    "addr:full":"512 Thornton Rd Lithia Springs GA 30122",
    "addr:housenumber":"512",
    "addr:postcode":"30122",
    "addr:street":"Thornton Rd",
    "iso:country":"US",
    "sg:address":"512 Thornton Rd",
    "sg:city":"Lithia Springs",
    "sg:classifiers":[
        {
            "category":"Retail",
            "subcategory":"Auto Repair",
            "type":"Services"
        }
    ],
    "sg:phone":"+1 770 745 1500",
    "sg:postcode":"30122",
    "sg:province":"GA",
    "sg:website":"www.midas.com",
    "wof:name":"Midas Auto Service",
    "wof:placetype":"venue"
},
  "geometry": {"coordinates":[-84.62672000000001,33.791353],"type":"Point"}
}