{
  "type": "Feature",
  "properties": {
    "iso:country":"US",
    "sg:address":"1638 Esquire Pl",
    "sg:city":"Norcross",
    "sg:classifiers":[
        {
            "category":"Shopping",
            "subcategory":"Computers & Home Electronics",
            "type":"Retail Goods"
        }
    ],
    "sg:phone":"+1 770 938 6034",
    "sg:postcode":"30093",
    "sg:province":"GA",
    "sg:tags":[
        "software"
    ],
    "wof:name":"Zipsco Inc",
    "wof:placetype":"venue"
},
  "geometry": {"coordinates":[-84.219999,33.897374],"type":"Point"}
}