{
  "type": "Feature",
  "properties": {
    "addr:full":"8000 Waters Ave Savannah GA 31406",
    "addr:housenumber":"8000",
    "addr:postcode":"31406",
    "addr:street":"Waters Ave",
    "iso:country":"US",
    "sg:address":"8000 Waters Ave",
    "sg:city":"Savannah",
    "sg:classifiers":[
        {
            "category":"Real Estate",
            "subcategory":"Real Estate Operator",
            "type":"Services"
        }
    ],
    "sg:phone":"+1 912 354 2064",
    "sg:postcode":"31406",
    "sg:province":"GA",
    "sg:tags":[
        "apartment"
    ],
    "wof:name":"Cypress Landing",
    "wof:placetype":"venue"
},
  "geometry": {"coordinates":[-81.103409,31.999644],"type":"Point"}
}