{
  "type": "Feature",
  "properties": {
    "iso:country":"US",
    "sg:address":"3005 Camelot Woods Dr NW",
    "sg:city":"Lawrenceville",
    "sg:classifiers":[
        {
            "category":"Professional",
            "subcategory":"Computer Services",
            "type":"Services"
        }
    ],
    "sg:phone":"+1 770 310 6690",
    "sg:postcode":"30044",
    "sg:province":"GA",
    "sg:tags":[
        "related"
    ],
    "wof:name":"Dbtrix Inc",
    "wof:placetype":"venue"
},
  "geometry": {"coordinates":[-84.088441,33.934244],"type":"Point"}
}