{
  "type": "Feature",
  "properties": {
    "addr:full":"3235 Industrial Way Snellville GA 30039",
    "addr:housenumber":"3235",
    "addr:postcode":"30039",
    "addr:street":"Industrial Way",
    "iso:country":"US",
    "sg:address":"3235 Industrial Way",
    "sg:city":"Snellville",
    "sg:classifiers":[
        {
            "category":"Building & Trades",
            "subcategory":"Locksmith",
            "type":"Services"
        }
    ],
    "sg:phone":"+1 888 310 6957",
    "sg:postcode":"30039",
    "sg:province":"GA",
    "sg:tags":[
        "key"
    ],
    "wof:name":"1 & A Emergency Locksmith",
    "wof:placetype":"venue"
},
  "geometry": {"coordinates":[-84.00769099999999,33.829823],"type":"Point"}
}