{
  "type": "Feature",
  "properties": {
    "addr:full":"1993 N Decatur Rd Atlanta GA 30307",
    "addr:housenumber":"1993",
    "addr:postcode":"30307",
    "addr:street":"N Decatur Rd",
    "iso:country":"US",
    "sg:address":"1993 N Decatur Rd",
    "sg:city":"Atlanta",
    "sg:classifiers":[
        {
            "category":"Professional",
            "subcategory":"Management & Consulting",
            "type":"Services"
        }
    ],
    "sg:phone":"+1 404 310 6808",
    "sg:postcode":"30307",
    "sg:province":"GA",
    "sg:tags":[
        "business"
    ],
    "wof:name":"Lani Walsh Consulting",
    "wof:placetype":"venue"
},
  "geometry": {"coordinates":[-84.311727,33.791956],"type":"Point"}
}