{
  "type": "Feature",
  "properties": {
    "addr:full":"1523 Grace Meadows Ln SE Smyrna GA 30082",
    "addr:housenumber":"1523",
    "addr:postcode":"30082",
    "addr:street":"Grace Meadows Ln Se",
    "iso:country":"US",
    "sg:address":"1523 Grace Meadows Ln SE",
    "sg:city":"Smyrna",
    "sg:classifiers":[
        {
            "category":"Organizations",
            "subcategory":"Religious Organization",
            "type":"Services"
        }
    ],
    "sg:phone":"+1 770 384 0612",
    "sg:postcode":"30082",
    "sg:province":"GA",
    "wof:name":"Wys Ministries",
    "wof:placetype":"venue"
},
  "geometry": {"coordinates":[-84.53266600000001,33.863551],"type":"Point"}
}