{
  "type": "Feature",
  "properties": {
    "addr:full":"1104 Mable St Mableton GA 30126",
    "addr:housenumber":"1104",
    "addr:postcode":"30126",
    "addr:street":"Mable St",
    "iso:country":"US",
    "sg:address":"1104 Mable St",
    "sg:city":"Mableton",
    "sg:classifiers":[
        {
            "category":"Retail",
            "subcategory":"Laundry & Dry Cleaning",
            "type":"Services"
        }
    ],
    "sg:phone":"+1 404 579 3851",
    "sg:postcode":"30126",
    "sg:province":"GA",
    "wof:name":"C Fluids Carpet Care",
    "wof:placetype":"venue"
},
  "geometry": {"coordinates":[-84.589595,33.822773],"type":"Point"}
}