{
  "type": "Feature",
  "properties": {
    "iso:country":"US",
    "sg:address":"659 Lake Hills Dr",
    "sg:city":"Trenton",
    "sg:classifiers":[
        {
            "category":"Professional",
            "subcategory":"Computer Services",
            "type":"Services"
        }
    ],
    "sg:phone":"+1 706 657 2377",
    "sg:postcode":"30752",
    "sg:province":"GA",
    "sg:tags":[
        "programing",
        "custom"
    ],
    "wof:name":"Qualex Consulting Services",
    "wof:placetype":"venue"
},
  "geometry": {"coordinates":[-85.508436,34.891579],"type":"Point"}
}