{
  "type": "Feature",
  "properties": {
    "iso:country":"US",
    "sg:address":"9705 Carolina Dr",
    "sg:city":"Jonesboro",
    "sg:classifiers":[
        {
            "category":"Freight",
            "type":"Transportation"
        }
    ],
    "sg:phone":"+1 404 425 3675",
    "sg:postcode":"30238",
    "sg:province":"GA",
    "sg:tags":[
        "operator",
        "trucking"
    ],
    "wof:name":"Mdj Trucking",
    "wof:placetype":"venue"
},
  "geometry": {"coordinates":[-84.349683,33.490202],"type":"Point"}
}