{
  "type": "Feature",
  "properties": {
    "addr:full":"105 Johnson Ave Fayetteville GA 30214",
    "addr:housenumber":"105",
    "addr:postcode":"30214",
    "addr:street":"Johnson Ave",
    "iso:country":"US",
    "sg:address":"105 Johnson Ave",
    "sg:city":"Fayetteville",
    "sg:classifiers":[
        {
            "category":"Government",
            "subcategory":"Police Station",
            "type":"Public Place"
        }
    ],
    "sg:phone":"+1 770 461 4441",
    "sg:postcode":"30214",
    "sg:province":"GA",
    "sg:tags":[
        "department"
    ],
    "wof:name":"Fayetteville Police Dept",
    "wof:placetype":"venue"
},
  "geometry": {"coordinates":[-84.45375300000001,33.446435],"type":"Point"}
}