{
  "type": "Feature",
  "properties": {
    "addr:full":"2636 Tobacco Rd Hephzibah GA 30815",
    "addr:housenumber":"2636",
    "addr:postcode":"30815",
    "addr:street":"Tobacco Rd",
    "iso:country":"US",
    "sg:address":"2636 Tobacco Rd",
    "sg:city":"Hephzibah",
    "sg:classifiers":[
        {
            "category":"Personal",
            "subcategory":"Beauty Salon",
            "type":"Services"
        }
    ],
    "sg:phone":"+1 706 771 7771",
    "sg:postcode":"30815",
    "sg:province":"GA",
    "wof:name":"Salon HQ",
    "wof:placetype":"venue"
},
  "geometry": {"coordinates":[-82.090487,33.380626],"type":"Point"}
}