{
  "type": "Feature",
  "properties": {
    "iso:country":"US",
    "sg:address":"5000 Old Dixie Hwy",
    "sg:city":"Forest Park",
    "sg:classifiers":[
        {
            "category":"Food & Beverages",
            "subcategory":"Groceries & Convenience Stores",
            "type":"Retail Goods"
        }
    ],
    "sg:phone":"+1 404 363 8199",
    "sg:postcode":"30297",
    "sg:province":"GA",
    "wof:name":"Brito Supermarket #3",
    "wof:placetype":"venue"
},
  "geometry": {"coordinates":[-84.38311,33.618066],"type":"Point"}
}