{
  "type": "Feature",
  "properties": {
    "iso:country":"US",
    "sg:address":"1427 Highway 138 SE",
    "sg:city":"Conyers",
    "sg:classifiers":[
        {
            "category":"Banks & Credit Unions",
            "subcategory":"Financial Services",
            "type":"Services"
        }
    ],
    "sg:phone":"+1 770 278 0393",
    "sg:postcode":"30013",
    "sg:province":"GA",
    "wof:name":"Trimax Financia",
    "wof:placetype":"venue"
},
  "geometry": {"coordinates":[-84.00022800000001,33.658417],"type":"Point"}
}