{
  "type": "Feature",
  "properties": {
    "addr:full":"531 Walker Rd Brunswick GA 31525",
    "addr:housenumber":"531",
    "addr:postcode":"31525",
    "addr:street":"Walker Rd",
    "iso:country":"US",
    "sg:address":"531 Walker Rd",
    "sg:city":"Brunswick",
    "sg:classifiers":[
        {
            "category":"Autos & Motor Vehicles",
            "subcategory":"Automobile Sales",
            "type":"Retail Goods"
        }
    ],
    "sg:phone":"+1 888 265 6625",
    "sg:postcode":"31525",
    "sg:province":"GA",
    "sg:tags":[
        "car",
        "used"
    ],
    "sg:website":"http://www.goldenislesnissan.com/",
    "wof:name":"Golden Isles Nissan",
    "wof:placetype":"venue"
},
  "geometry": {"coordinates":[-81.492333,31.226179],"type":"Point"}
}