{
  "type": "Feature",
  "properties": {
    "iso:country":"US",
    "sg:address":"1523 Highway 16 E",
    "sg:city":"Jackson",
    "sg:classifiers":[
        {
            "category":"Place Of Worship",
            "type":"Public Place"
        },
        {
            "category":"Organizations",
            "subcategory":"Religious Organization",
            "type":"Services"
        }
    ],
    "sg:phone":"+1 770 775 3998",
    "sg:postcode":"30233",
    "sg:province":"GA",
    "sg:tags":[
        "church"
    ],
    "wof:name":"Jackson Church of Nazarene",
    "wof:placetype":"venue"
},
  "geometry": {"coordinates":[-83.93482400000001,33.288856],"type":"Point"}
}