{
  "type": "Feature",
  "properties": {
    "addr:full":"4487 Trickum Rd NE Marietta GA 30066",
    "addr:housenumber":"4487",
    "addr:postcode":"30066",
    "addr:street":"Trickum Rd Ne",
    "iso:country":"US",
    "sg:address":"4487 Trickum Rd NE",
    "sg:city":"Marietta",
    "sg:classifiers":[
        {
            "category":"Real Estate",
            "subcategory":"Real Estate Services",
            "type":"Services"
        },
        {
            "category":"Social Services",
            "subcategory":"Retirement Home",
            "type":"Services"
        }
    ],
    "sg:phone":"+1 770 926 5209",
    "sg:postcode":"30066",
    "sg:province":"GA",
    "sg:tags":[
        "boarding",
        "house",
        "rooming"
    ],
    "wof:name":"Sims House",
    "wof:placetype":"venue"
},
  "geometry": {"coordinates":[-84.48645,34.06068],"type":"Point"}
}