{
  "type": "Feature",
  "properties": {
    "iso:country":"US",
    "sg:address":"719 Peri Leigh Rd",
    "sg:city":"Harlem",
    "sg:classifiers":[
        {
            "category":"Arts & Performance",
            "subcategory":"Theater",
            "type":"Entertainment"
        }
    ],
    "sg:phone":"+1 706 556 0806",
    "sg:postcode":"30814",
    "sg:province":"GA",
    "sg:tags":[
        "group"
    ],
    "wof:name":"Maples Entertainment Agency",
    "wof:placetype":"venue"
},
  "geometry": {"coordinates":[-82.277451,33.421117],"type":"Point"}
}