{
  "type": "Feature",
  "properties": {
    "addr:full":"2196 Salem Rd SE Conyers GA 30013",
    "addr:housenumber":"2196",
    "addr:postcode":"30013",
    "addr:street":"Salem Rd Se",
    "iso:country":"US",
    "sg:address":"2196 Salem Rd SE",
    "sg:city":"Conyers",
    "sg:classifiers":[
        {
            "category":"Shopping",
            "subcategory":"Used Merchandise",
            "type":"Retail Goods"
        }
    ],
    "sg:phone":"+1 770 761 0300",
    "sg:postcode":"30013",
    "sg:province":"GA",
    "wof:name":"Salem Antiques Mall",
    "wof:placetype":"venue"
},
  "geometry": {"coordinates":[-83.97806,33.634447],"type":"Point"}
}