{
  "type": "Feature",
  "properties": {
    "addr:full":"3650 Bakers Ferry Rd SW Atlanta GA 30331",
    "addr:housenumber":"3650",
    "addr:postcode":"30331",
    "addr:street":"Bakers Ferry Rd Sw",
    "iso:country":"US",
    "sg:address":"3650 Bakers Ferry Rd SW",
    "sg:city":"Atlanta",
    "sg:classifiers":[
        {
            "category":"Organizations",
            "subcategory":"Religious Organization",
            "type":"Services"
        }
    ],
    "sg:phone":"+1 404 505 8288",
    "sg:postcode":"30331",
    "sg:province":"GA",
    "wof:name":"New Clark Street Baptist",
    "wof:placetype":"venue"
},
  "geometry": {"coordinates":[-84.50964399999999,33.76017],"type":"Point"}
}