{
  "type": "Feature",
  "properties": {
    "addr:full":"1256 Yatesville Hwy Thomaston GA 30286",
    "addr:housenumber":"1256",
    "addr:postcode":"30286",
    "addr:street":"Yatesville Hwy",
    "iso:country":"US",
    "sg:address":"1256 Yatesville Hwy",
    "sg:city":"Thomaston",
    "sg:classifiers":[
        {
            "category":"Building & Trades",
            "subcategory":"Plumbing",
            "type":"Services"
        }
    ],
    "sg:phone":"+1 706 646 4498",
    "sg:postcode":"30286",
    "sg:province":"GA",
    "sg:tags":[
        "plumbing",
        "contractor"
    ],
    "wof:name":"Mimbs Plumbing",
    "wof:placetype":"venue"
},
  "geometry": {"coordinates":[-84.296285,32.890339],"type":"Point"}
}