{
  "type": "Feature",
  "properties": {
    "addr:full":"2724 Yorktown Ave Albany GA 31705",
    "addr:housenumber":"2724",
    "addr:postcode":"31705",
    "addr:street":"Yorktown Ave",
    "iso:country":"US",
    "sg:address":"2724 Yorktown Ave",
    "sg:city":"Albany",
    "sg:classifiers":[
        {
            "category":"Retail",
            "subcategory":"Repair Shop",
            "type":"Services"
        }
    ],
    "sg:phone":"+1 229 888 5081",
    "sg:postcode":"31705",
    "sg:province":"GA",
    "wof:name":"Brileys Carpet & Uphl Clg",
    "wof:placetype":"venue"
},
  "geometry": {"coordinates":[-84.078908,31.579348],"type":"Point"}
}