{
  "type": "Feature",
  "properties": {
    "iso:country":"US",
    "sg:address":"400 Wynne St S",
    "sg:city":"Chester",
    "sg:classifiers":[
        {
            "category":"Real Estate",
            "subcategory":"Real Estate Operator",
            "type":"Services"
        }
    ],
    "sg:phone":"+1 478 358 4323",
    "sg:postcode":"31012",
    "sg:province":"GA",
    "sg:tags":[
        "apartment"
    ],
    "wof:name":"Chester Apartments",
    "wof:placetype":"venue"
},
  "geometry": {"coordinates":[-83.15455300000001,32.392796],"type":"Point"}
}