{
  "type": "Feature",
  "properties": {
    "iso:country":"US",
    "sg:address":"609 Ponder Place Dr # A",
    "sg:city":"Evans",
    "sg:classifiers":[
        {
            "category":"Professional",
            "subcategory":"Lawyer & Legal Services",
            "type":"Services"
        }
    ],
    "sg:phone":"+1 706 855 0035",
    "sg:postcode":"30809",
    "sg:province":"GA",
    "sg:tags":[
        "information",
        "attorney",
        "referral",
        "family",
        "law"
    ],
    "sg:website":"http://www.ldanielbutler.com",
    "wof:name":"L Daniel Butler Pc",
    "wof:placetype":"venue"
},
  "geometry": {"coordinates":[-82.136915,33.529741],"type":"Point"}
}