{
  "type": "Feature",
  "properties": {
    "iso:country":"US",
    "sg:address":"1989 Barnett Shoals Rd",
    "sg:city":"Athens",
    "sg:classifiers":[
        {
            "category":"Health Services",
            "subcategory":"Doctor",
            "type":"Services"
        }
    ],
    "sg:phone":"+1 706 353 7018",
    "sg:postcode":"30605",
    "sg:province":"GA",
    "wof:name":"Dental Care Clinic of Athens",
    "wof:placetype":"venue"
},
  "geometry": {"coordinates":[-83.34101200000001,33.9226],"type":"Point"}
}