{
  "type": "Feature",
  "properties": {
    "iso:country":"US",
    "sg:address":"1068 Salem Church Rd",
    "sg:city":"Tifton",
    "sg:classifiers":[
        {
            "category":"Insurance",
            "subcategory":"Hazard Insurance",
            "type":"Services"
        }
    ],
    "sg:phone":"+1 229 528 4606",
    "sg:postcode":"31794",
    "sg:province":"GA",
    "sg:tags":[
        "bond"
    ],
    "wof:name":"Dillard's Bail Bond Co",
    "wof:placetype":"venue"
},
  "geometry": {"coordinates":[-83.635232,31.391569],"type":"Point"}
}