{
  "type": "Feature",
  "properties": {
    "addr:full":"1661 Lumpkin St Atlanta GA 30344",
    "addr:housenumber":"1661",
    "addr:postcode":"30344",
    "addr:street":"Lumpkin St",
    "iso:country":"US",
    "sg:address":"1661 Lumpkin St",
    "sg:city":"Atlanta",
    "sg:classifiers":[
        {
            "category":"Restaurant",
            "type":"Food & Drink"
        }
    ],
    "sg:menulink":"http://www.allmenus.com/ga/east-point/241684-tavern-at-the-arch/menu/",
    "sg:phone":"+1 706 354 1404",
    "sg:postcode":"30344",
    "sg:province":"GA",
    "sg:tags":[
        "irish"
    ],
    "wof:name":"Tavern At The Arch",
    "wof:placetype":"venue"
},
  "geometry": {"coordinates":[-84.449499,33.69162],"type":"Point"}
}