{
  "type": "Feature",
  "properties": {
    "addr:full":"1133 Agerton Ln Augusta GA 30909",
    "addr:housenumber":"1133",
    "addr:postcode":"30909",
    "addr:street":"Agerton Ln",
    "iso:country":"US",
    "sg:address":"1133 Agerton Ln",
    "sg:city":"Augusta",
    "sg:classifiers":[
        {
            "category":"Restaurant",
            "type":"Food & Drink"
        }
    ],
    "sg:phone":"+1 706 733 7910",
    "sg:postcode":"30909",
    "sg:province":"GA",
    "sg:tags":[
        "pizza"
    ],
    "wof:name":"Romas Pizza",
    "wof:placetype":"venue"
},
  "geometry": {"coordinates":[-82.07893799999999,33.488182],"type":"Point"}
}