{
  "type": "Feature",
  "properties": {
    "addr:full":"6694 Dawson Blvd Norcross GA 30093",
    "addr:housenumber":"6694",
    "addr:postcode":"30093",
    "addr:street":"Dawson Blvd",
    "iso:country":"US",
    "sg:address":"6694 Dawson Blvd",
    "sg:city":"Norcross",
    "sg:classifiers":[
        {
            "category":"Home & Garden",
            "subcategory":"Furniture",
            "type":"Retail Goods"
        }
    ],
    "sg:phone":"+1 770 441 1154",
    "sg:postcode":"30093",
    "sg:province":"GA",
    "sg:tags":[
        "store"
    ],
    "sg:website":"www.underpricedfurniture.com",
    "wof:name":"Under Priced Furniture",
    "wof:placetype":"venue"
},
  "geometry": {"coordinates":[-84.230598,33.907902],"type":"Point"}
}