{
  "type": "Feature",
  "properties": {
    "iso:country":"US",
    "sg:address":"80 Moore Ave NE",
    "sg:city":"Marietta",
    "sg:classifiers":[
        {
            "category":"Retail",
            "subcategory":"Auto Repair",
            "type":"Services"
        }
    ],
    "sg:phone":"+1 678 738 0947",
    "sg:postcode":"30060",
    "sg:province":"GA",
    "sg:tags":[
        "body",
        "shop"
    ],
    "wof:name":"R & D Collision",
    "wof:placetype":"venue"
},
  "geometry": {"coordinates":[-84.533897,33.952801],"type":"Point"}
}