{
  "type": "Feature",
  "properties": {
    "addr:full":"125 Highgrove Dr Suwanee GA 30024",
    "addr:housenumber":"125",
    "addr:postcode":"30024",
    "addr:street":"Highgrove Dr",
    "iso:country":"US",
    "sg:address":"125 Highgrove Dr",
    "sg:city":"Suwanee",
    "sg:classifiers":[
        {
            "category":"Real Estate",
            "subcategory":"Real Estate Agent",
            "type":"Services"
        }
    ],
    "sg:phone":"+1 770 317 1503",
    "sg:postcode":"30024",
    "sg:province":"GA",
    "sg:tags":[
        "inspection"
    ],
    "wof:name":"Inspect Your House",
    "wof:placetype":"venue"
},
  "geometry": {"coordinates":[-84.110343,34.108455],"type":"Point"}
}