{
  "type": "Feature",
  "properties": {
    "addr:full":"1099 Harbins Rd Dacula GA 30019",
    "addr:housenumber":"1099",
    "addr:postcode":"ga 30019",
    "addr:street":"Harbins Rd",
    "iso:country":"US",
    "sg:address":"1099 Harbins Rd",
    "sg:city":"Dacula",
    "sg:classifiers":[
        {
            "category":"Professional",
            "subcategory":"Business Services",
            "type":"Services"
        }
    ],
    "sg:phone":"+1 770 682 2776",
    "sg:postcode":"30019",
    "sg:province":"GA",
    "wof:name":"Royal Treatment",
    "wof:placetype":"venue"
},
  "geometry": {"coordinates":[-83.883079,33.961436],"type":"Point"}
}