{
  "type": "Feature",
  "properties": {
    "iso:country":"US",
    "sg:address":"83 Glenn St SE",
    "sg:city":"Atlanta",
    "sg:classifiers":[
        {
            "category":"Professional",
            "subcategory":"Management & Consulting",
            "type":"Services"
        }
    ],
    "sg:phone":"+1 404 688 9812",
    "sg:postcode":"30312",
    "sg:province":"GA",
    "sg:tags":[
        "business"
    ],
    "wof:name":"Pendulum Consulting Inc",
    "wof:placetype":"venue"
},
  "geometry": {"coordinates":[-84.38554000000001,33.737916],"type":"Point"}
}