{
  "type": "Feature",
  "properties": {
    "iso:country":"US",
    "sg:address":"2210 Fort Benning Rd",
    "sg:city":"Columbus",
    "sg:classifiers":[
        {
            "category":"Travel",
            "subcategory":"Hotels & Motels",
            "type":"Entertainment"
        }
    ],
    "sg:phone":"+1 706 689 5510",
    "sg:postcode":"31903",
    "sg:province":"GA",
    "sg:tags":[
        "drinking",
        "operation"
    ],
    "wof:name":"Traffic Light Inn",
    "wof:placetype":"venue"
},
  "geometry": {"coordinates":[-84.944571,32.411986],"type":"Point"}
}