{
  "type": "Feature",
  "properties": {
    "iso:country":"US",
    "sg:address":"4187 Hannah Rd",
    "sg:city":"Tucker",
    "sg:classifiers":[
        {
            "category":"Sports & Exercise",
            "subcategory":"Race Track",
            "type":"Entertainment"
        }
    ],
    "sg:phone":"+1 770 938 7150",
    "sg:postcode":"30084",
    "sg:province":"GA",
    "sg:website":"http://www.helmetventilationsystems.com",
    "wof:name":"Yarini Racing Enterprises",
    "wof:placetype":"venue"
},
  "geometry": {"coordinates":[-84.21740699999999,33.861004],"type":"Point"}
}