{
  "type": "Feature",
  "properties": {
    "addr:full":"1806 Carmichael Ct Augusta GA 30906",
    "addr:housenumber":"1806",
    "addr:postcode":"30906",
    "addr:street":"Carmichael Ct",
    "iso:country":"US",
    "sg:address":"1806 Carmichael Ct",
    "sg:city":"Augusta",
    "sg:classifiers":[
        {
            "category":"Professional",
            "type":"Services"
        },
        {
            "category":"Retail",
            "subcategory":"Auto Rental",
            "type":"Services"
        },
        {
            "category":"Building & Trades",
            "subcategory":"Equipment Rental",
            "type":"Services"
        },
        {
            "category":"Retail",
            "subcategory":"Storage",
            "type":"Services"
        }
    ],
    "sg:phone":"+1 866 205 7339",
    "sg:postcode":"30906",
    "sg:province":"GA",
    "sg:tags":[
        "renting",
        "moving-self",
        "leasing",
        "material",
        "moving",
        "services-labor",
        "truck",
        "trailer"
    ],
    "sg:website":"http://www.pensketruckrental.com/personal_rental/?cid=Yptmlist",
    "wof:name":"Penske Truck Rental",
    "wof:placetype":"venue"
},
  "geometry": {"coordinates":[-82.00444400000001,33.382431],"type":"Point"}
}