{
  "type": "Feature",
  "properties": {
    "addr:full":"2200 Old Alpharetta Rd Cumming GA 30041",
    "addr:housenumber":"2200",
    "addr:postcode":"30041",
    "addr:street":"Old Alpharetta Rd",
    "iso:country":"US",
    "sg:address":"2200 Old Alpharetta Rd",
    "sg:city":"Cumming",
    "sg:classifiers":[
        {
            "category":"Professional",
            "type":"Services"
        }
    ],
    "sg:phone":"+1 770 886 3297",
    "sg:postcode":"30041",
    "sg:province":"GA",
    "wof:name":"D and M Services Inc",
    "wof:placetype":"venue"
},
  "geometry": {"coordinates":[-84.18959700000001,34.109466],"type":"Point"}
}