{
  "type": "Feature",
  "properties": {
    "addr:full":"1240 Menlo Dr NW Atlanta GA 30318",
    "addr:housenumber":"1240",
    "addr:postcode":"30318",
    "addr:street":"Menlo Dr Nw",
    "iso:country":"US",
    "sg:address":"1240 Menlo Dr NW",
    "sg:city":"Atlanta",
    "sg:classifiers":[
        {
            "category":"Building & Trades",
            "subcategory":"Locksmith",
            "type":"Services"
        }
    ],
    "sg:phone":"+1 404 270 1722",
    "sg:postcode":"30318",
    "sg:province":"GA",
    "sg:tags":[
        "key"
    ],
    "wof:name":"Locksmith",
    "wof:placetype":"venue"
},
  "geometry": {"coordinates":[-84.42457899999999,33.788226],"type":"Point"}
}