{
  "type": "Feature",
  "properties": {
    "addr:full":"3725 Highway 78 W Snellville GA 30039",
    "addr:housenumber":"3725",
    "addr:postcode":"30039",
    "addr:street":"Highway 78 W",
    "iso:country":"US",
    "sg:address":"3725 Highway 78 W",
    "sg:city":"Snellville",
    "sg:classifiers":[
        {
            "category":"Personal",
            "subcategory":"Tattoo Parlor",
            "type":"Services"
        },
        {
            "category":"Personal",
            "subcategory":"Piercing",
            "type":"Services"
        }
    ],
    "sg:phone":"+1 770 982 9930",
    "sg:postcode":"30039",
    "sg:province":"GA",
    "wof:name":"Good Clean Fun Tattoo Studio",
    "wof:placetype":"venue"
},
  "geometry": {"coordinates":[-84.058998,33.842701],"type":"Point"}
}