{
  "type": "Feature",
  "properties": {
    "addr:full":"3918 Downing Ln NE Atlanta GA 30319",
    "addr:housenumber":"3918",
    "addr:postcode":"30319",
    "addr:street":"Downing Ln Ne",
    "iso:country":"US",
    "sg:address":"3918 Downing Ln NE",
    "sg:city":"Atlanta",
    "sg:classifiers":[
        {
            "category":"Professional",
            "subcategory":"Management & Consulting",
            "type":"Services"
        }
    ],
    "sg:phone":"+1 404 257 8799",
    "sg:postcode":"30319",
    "sg:province":"GA",
    "sg:tags":[
        "consultant",
        "business"
    ],
    "wof:name":"IDA Ireland",
    "wof:placetype":"venue"
},
  "geometry": {"coordinates":[-84.341522,33.907408],"type":"Point"}
}