{
  "type": "Feature",
  "properties": {
    "addr:full":"115 W Greenwood Dr Carrollton GA 30117",
    "addr:housenumber":"115",
    "addr:postcode":"30117",
    "addr:street":"W Greenwood Dr",
    "iso:country":"US",
    "sg:address":"115 W Greenwood Dr",
    "sg:city":"Carrollton",
    "sg:classifiers":[
        {
            "category":"Building & Trades",
            "subcategory":"Construction",
            "type":"Services"
        }
    ],
    "sg:phone":"+1 770 836 8532",
    "sg:postcode":"30117",
    "sg:province":"GA",
    "sg:tags":[
        "work",
        "installation"
    ],
    "wof:name":"Profoam Corporation",
    "wof:placetype":"venue"
},
  "geometry": {"coordinates":[-85.121565,33.566607],"type":"Point"}
}