{
  "type": "Feature",
  "properties": {
    "iso:country":"US",
    "sg:address":"4800 Briarcliff Rd NE",
    "sg:city":"Atlanta",
    "sg:classifiers":[
        {
            "category":"Personal",
            "subcategory":"Beauty Salon",
            "type":"Services"
        }
    ],
    "sg:phone":"+1 770 908 8935",
    "sg:postcode":"30345",
    "sg:province":"GA",
    "wof:name":"Essence Beauty",
    "wof:placetype":"venue"
},
  "geometry": {"coordinates":[-84.255785,33.848165],"type":"Point"}
}