{
  "type": "Feature",
  "properties": {
    "iso:country":"US",
    "sg:address":"2150 Moreland Ave SE",
    "sg:city":"Atlanta",
    "sg:classifiers":[
        {
            "category":"Manufacturing",
            "subcategory":"Motor Vehicles & Parts",
            "type":"Manufacturing & Wholesale Goods"
        }
    ],
    "sg:phone":"+1 404 622 2800",
    "sg:postcode":"30315",
    "sg:province":"GA",
    "sg:tags":[
        "driveshaft"
    ],
    "wof:name":"Custom Drive Line Co",
    "wof:placetype":"venue"
},
  "geometry": {"coordinates":[-84.34956200000001,33.695595],"type":"Point"}
}