{
  "type": "Feature",
  "properties": {
    "iso:country":"US",
    "sg:address":"429 Wesley Camp Rd",
    "sg:city":"Tallapoosa",
    "sg:classifiers":[
        {
            "category":"Home & Garden",
            "subcategory":"Carpets & Floor Coverings",
            "type":"Retail Goods"
        }
    ],
    "sg:phone":"+1 678 647 3064",
    "sg:postcode":"30176",
    "sg:province":"GA",
    "sg:tags":[
        "material"
    ],
    "wof:name":"Georgia Floors And More",
    "wof:placetype":"venue"
},
  "geometry": {"coordinates":[-85.204615,33.795895],"type":"Point"}
}