{
  "type": "Feature",
  "properties": {
    "iso:country":"US",
    "sg:address":"620 Cotton Ave",
    "sg:city":"Albany",
    "sg:classifiers":[
        {
            "category":"Manufacturing",
            "subcategory":"Textiles",
            "type":"Manufacturing & Wholesale Goods"
        }
    ],
    "sg:phone":"+1 229 435 5542",
    "sg:postcode":"31701",
    "sg:province":"GA",
    "sg:tags":[
        "mill",
        "cotton",
        "fabric",
        "grocery",
        "general"
    ],
    "wof:name":"Covins Drapery",
    "wof:placetype":"venue"
},
  "geometry": {"coordinates":[-84.164276,31.567109],"type":"Point"}
}