{
  "type": "Feature",
  "properties": {
    "addr:full":"18 Palmetto Bay Rd Savannah GA 31410",
    "addr:housenumber":"18",
    "addr:postcode":"31410",
    "addr:street":"Palmetto Bay Rd",
    "iso:country":"US",
    "sg:address":"18 Palmetto Bay Rd",
    "sg:city":"Savannah",
    "sg:classifiers":[
        {
            "category":"Personal",
            "type":"Services"
        }
    ],
    "sg:phone":"+1 912 898 0677",
    "sg:postcode":"31410",
    "sg:province":"GA",
    "wof:name":"Bbd International",
    "wof:placetype":"venue"
},
  "geometry": {"coordinates":[-80.964432,32.011619],"type":"Point"}
}