{
  "type": "Feature",
  "properties": {
    "iso:country":"US",
    "sg:address":"7091 S Main St",
    "sg:city":"Helen",
    "sg:classifiers":[
        {
            "category":"Travel",
            "subcategory":"Hotels & Motels",
            "type":"Entertainment"
        }
    ],
    "sg:phone":"+1 706 878 1800",
    "sg:postcode":"30545",
    "sg:province":"GA",
    "sg:tags":[
        "resort"
    ],
    "wof:name":"Nacoochee Village",
    "wof:placetype":"venue"
},
  "geometry": {"coordinates":[-83.71544900000001,34.696145],"type":"Point"}
}