{
  "type": "Feature",
  "properties": {
    "addr:full":"1246 E Bryan St Douglas GA 31533",
    "addr:housenumber":"1246",
    "addr:postcode":"31533",
    "addr:street":"E Bryan St",
    "iso:country":"US",
    "sg:address":"1246 E Bryan St",
    "sg:city":"Douglas",
    "sg:classifiers":[
        {
            "category":"Organizations",
            "subcategory":"Religious Organization",
            "type":"Services"
        }
    ],
    "sg:phone":"+1 912 383 7562",
    "sg:postcode":"31533",
    "sg:province":"GA",
    "wof:name":"Mt Ebell Baptist Church Inc",
    "wof:placetype":"venue"
},
  "geometry": {"coordinates":[-82.835323,31.505837],"type":"Point"}
}