{
  "type": "Feature",
  "properties": {
    "addr:full":"8559 Columbus Rd Lizella GA 31052",
    "addr:housenumber":"8559",
    "addr:postcode":"31052",
    "addr:street":"Columbus Rd",
    "iso:country":"US",
    "sg:address":"8559 Columbus Rd",
    "sg:city":"Lizella",
    "sg:classifiers":[
        {
            "category":"Wholesale",
            "subcategory":"Scrap",
            "type":"Manufacturing & Wholesale Goods"
        }
    ],
    "sg:phone":"+1 478 935 8800",
    "sg:postcode":"31052",
    "sg:province":"GA",
    "sg:tags":[
        "oil"
    ],
    "wof:name":"API Recycling",
    "wof:placetype":"venue"
},
  "geometry": {"coordinates":[-83.835972,32.809414],"type":"Point"}
}