{
  "type": "Feature",
  "properties": {
    "iso:country":"US",
    "sg:address":"300 Old Powers Ln NW",
    "sg:city":"Atlanta",
    "sg:classifiers":[
        {
            "category":"Real Estate",
            "subcategory":"Real Estate Agent",
            "type":"Services"
        }
    ],
    "sg:phone":"+1 404 250 9518",
    "sg:postcode":"30327",
    "sg:province":"GA",
    "wof:name":"Ebuff Inc",
    "wof:placetype":"venue"
},
  "geometry": {"coordinates":[-84.397953,33.882795],"type":"Point"}
}