{
  "type": "Feature",
  "properties": {
    "iso:country":"US",
    "sg:address":"3216 Milledgeville Rd",
    "sg:city":"Augusta",
    "sg:classifiers":[
        {
            "category":"Retail",
            "subcategory":"Repair Shop",
            "type":"Services"
        }
    ],
    "sg:phone":"+1 706 736 6895",
    "sg:postcode":"30909",
    "sg:province":"GA",
    "sg:tags":[
        "upholsterer"
    ],
    "wof:name":"Tuck Master Upholstery",
    "wof:placetype":"venue"
},
  "geometry": {"coordinates":[-82.048542,33.448217],"type":"Point"}
}