{
  "type": "Feature",
  "properties": {
    "iso:country":"US",
    "sg:address":"1219 Old Hog Mountain Rd",
    "sg:city":"Auburn",
    "sg:classifiers":[
        {
            "category":"Restaurant",
            "type":"Food & Drink"
        }
    ],
    "sg:phone":"+1 770 868 8960",
    "sg:postcode":"30011",
    "sg:province":"GA",
    "wof:name":"Happy Table",
    "wof:placetype":"venue"
},
  "geometry": {"coordinates":[-83.817384,34.071742],"type":"Point"}
}