{
  "type": "Feature",
  "properties": {
    "iso:country":"US",
    "sg:address":"3490 Sims Rd",
    "sg:city":"Snellville",
    "sg:classifiers":[
        {
            "category":"Building & Trades",
            "subcategory":"Construction",
            "type":"Services"
        }
    ],
    "sg:phone":"+1 770 972 6647",
    "sg:postcode":"30039",
    "sg:province":"GA",
    "sg:tags":[
        "contractor"
    ],
    "wof:name":"Alliance Gutter & Home Repair",
    "wof:placetype":"venue"
},
  "geometry": {"coordinates":[-84.04377700000001,33.832222],"type":"Point"}
}