{
  "type": "Feature",
  "properties": {
    "addr:full":"3916 Pine Gorge Ct Dacula GA 30019",
    "addr:housenumber":"3916",
    "addr:postcode":"ga 30019",
    "addr:street":"Pine Gorge Ct",
    "iso:country":"US",
    "sg:address":"3916 Pine Gorge Ct",
    "sg:city":"Dacula",
    "sg:classifiers":[
        {
            "category":"Freight",
            "type":"Transportation"
        }
    ],
    "sg:phone":"+1 770 271 3876",
    "sg:postcode":"30019",
    "sg:province":"GA",
    "sg:tags":[
        "operator",
        "local",
        "trucking"
    ],
    "wof:name":"Adams Trucking",
    "wof:placetype":"venue"
},
  "geometry": {"coordinates":[-83.88852900000001,34.061216],"type":"Point"}
}