{
  "type": "Feature",
  "properties": {
    "addr:full":"1020 Hospital Dr Stockbridge GA 30281",
    "addr:housenumber":"1020",
    "addr:postcode":"30281",
    "addr:street":"Hospital Dr",
    "iso:country":"US",
    "sg:address":"1020 Hospital Dr",
    "sg:city":"Stockbridge",
    "sg:classifiers":[
        {
            "category":"Health Services",
            "subcategory":"Doctor",
            "type":"Services"
        }
    ],
    "sg:phone":"+1 770 389 0403",
    "sg:postcode":"30281",
    "sg:province":"GA",
    "sg:tags":[
        "physician",
        "surgeon"
    ],
    "wof:name":"Healthy Women's MD PC",
    "wof:placetype":"venue"
},
  "geometry": {"coordinates":[-84.225667,33.50949],"type":"Point"}
}