{
  "type": "Feature",
  "properties": {
    "iso:country":"US",
    "sg:address":"375 River North Blvd",
    "sg:city":"Macon",
    "sg:classifiers":[
        {
            "category":"Building & Trades",
            "subcategory":"Construction",
            "type":"Services"
        }
    ],
    "sg:phone":"+1 478 742 0555",
    "sg:postcode":"31211",
    "sg:province":"GA",
    "sg:tags":[
        "concrete",
        "contractor"
    ],
    "wof:name":"Dan Kis",
    "wof:placetype":"venue"
},
  "geometry": {"coordinates":[-83.666377,32.936425],"type":"Point"}
}