{
  "type": "Feature",
  "properties": {
    "addr:full":"183 Greenville St S Newnan GA 30263",
    "addr:housenumber":"183",
    "addr:postcode":"30263",
    "addr:street":"Greenville St S",
    "iso:country":"US",
    "sg:address":"183 Greenville St S",
    "sg:city":"Newnan",
    "sg:classifiers":[
        {
            "category":"Autos & Motor Vehicles",
            "subcategory":"Fuel & Gas Station",
            "type":"Retail Goods"
        }
    ],
    "sg:phone":"+1 770 253 3115",
    "sg:postcode":"30263",
    "sg:province":"GA",
    "sg:tags":[
        "station",
        "gasoline"
    ],
    "wof:name":"G&G Amoco",
    "wof:placetype":"venue"
},
  "geometry": {"coordinates":[-84.79416999999999,33.363301],"type":"Point"}
}