{
  "type": "Feature",
  "properties": {
    "addr:full":"1733 Oak Dr Augusta GA 30904",
    "addr:housenumber":"1733",
    "addr:postcode":"30904",
    "addr:street":"Oak Dr",
    "iso:country":"US",
    "sg:address":"1733 Oak Dr",
    "sg:city":"Augusta",
    "sg:classifiers":[
        {
            "category":"Building & Trades",
            "subcategory":"Landscaping Services",
            "type":"Services"
        }
    ],
    "sg:phone":"+1 706 736 2391",
    "sg:postcode":"30904",
    "sg:province":"GA",
    "sg:tags":[
        "lawn",
        "maintenance",
        "grounds"
    ],
    "wof:name":"Laurel Springs Lawn & Lndscpng",
    "wof:placetype":"venue"
},
  "geometry": {"coordinates":[-82.017363,33.456835],"type":"Point"}
}