{
  "type": "Feature",
  "properties": {
    "iso:country":"US",
    "sg:address":"2900 Camp Creek Pkwy",
    "sg:city":"Atlanta",
    "sg:classifiers":[
        {
            "category":"Professional",
            "subcategory":"Computer Services",
            "type":"Services"
        }
    ],
    "sg:phone":"+1 404 767 4706",
    "sg:postcode":"30337",
    "sg:province":"GA",
    "sg:tags":[
        "technology"
    ],
    "wof:name":"Simplixity",
    "wof:placetype":"venue"
},
  "geometry": {"coordinates":[-84.47291800000001,33.650752],"type":"Point"}
}