{
  "type": "Feature",
  "properties": {
    "addr:full":"224 Hearthstone Dr Lagrange GA 30241",
    "addr:housenumber":"224",
    "addr:postcode":"30241",
    "addr:street":"Hearthstone Dr",
    "iso:country":"US",
    "sg:address":"224 Hearthstone Dr",
    "sg:city":"Lagrange",
    "sg:classifiers":[
        {
            "category":"Personal",
            "subcategory":"Beauty Salon",
            "type":"Services"
        }
    ],
    "sg:phone":"+1 706 884 3622",
    "sg:postcode":"30241",
    "sg:province":"GA",
    "wof:name":"Hair Quarters",
    "wof:placetype":"venue"
},
  "geometry": {"coordinates":[-85.01646,33.05607],"type":"Point"}
}