{
  "type": "Feature",
  "properties": {
    "iso:country":"US",
    "sg:address":"3144 Lake Ranch Dr",
    "sg:city":"Gainesville",
    "sg:classifiers":[
        {
            "category":"Professional",
            "subcategory":"Art Services",
            "type":"Services"
        }
    ],
    "sg:phone":"+1 770 560 3095",
    "sg:postcode":"30506",
    "sg:province":"GA",
    "sg:tags":[
        "designer",
        "display",
        "producer"
    ],
    "wof:name":"Stapler Floor Designs",
    "wof:placetype":"venue"
},
  "geometry": {"coordinates":[-83.918779,34.339029],"type":"Point"}
}