{
  "type": "Feature",
  "properties": {
    "iso:country":"US",
    "sg:address":"1040 Booth Rd",
    "sg:city":"Warner Robins",
    "sg:classifiers":[
        {
            "category":"Wholesale",
            "subcategory":"Machinery & Supplies",
            "type":"Manufacturing & Wholesale Goods"
        }
    ],
    "sg:phone":"+1 478 922 5340",
    "sg:postcode":"31088",
    "sg:province":"GA",
    "sg:tags":[
        "janitor"
    ],
    "wof:name":"Clean Control Corp",
    "wof:placetype":"venue"
},
  "geometry": {"coordinates":[-83.59714,32.58976],"type":"Point"}
}