{
  "type": "Feature",
  "properties": {
    "iso:country":"US",
    "sg:address":"4261 Hiram Lithia Springs Rd",
    "sg:city":"Powder Springs",
    "sg:classifiers":[
        {
            "category":"Manufacturing",
            "subcategory":"Glass & Minerals",
            "type":"Manufacturing & Wholesale Goods"
        }
    ],
    "sg:phone":"+1 770 439 0197",
    "sg:postcode":"30127",
    "sg:province":"GA",
    "sg:tags":[
        "plastic"
    ],
    "wof:name":"Corning",
    "wof:placetype":"venue"
},
  "geometry": {"coordinates":[-84.710284,33.851903],"type":"Point"}
}