{
  "type": "Feature",
  "properties": {
    "addr:full":"210 N Scott St Bainbridge GA 39817",
    "addr:housenumber":"210",
    "addr:postcode":"39817",
    "addr:street":"N Scott St",
    "iso:country":"US",
    "sg:address":"210 N Scott St",
    "sg:city":"Bainbridge",
    "sg:classifiers":[
        {
            "category":"Retail",
            "subcategory":"Laundry & Dry Cleaning",
            "type":"Services"
        }
    ],
    "sg:phone":"+1 229 246 2364",
    "sg:postcode":"39817",
    "sg:province":"GA",
    "sg:tags":[
        "power"
    ],
    "wof:name":"Las Lomas Laundry Mat",
    "wof:placetype":"venue"
},
  "geometry": {"coordinates":[-84.567773,30.907391],"type":"Point"}
}