{
  "type": "Feature",
  "properties": {
    "addr:full":"1258 Concord Rd Smyrna GA 30080",
    "addr:housenumber":"1258",
    "addr:postcode":"30080",
    "addr:street":"Concord Rd",
    "iso:country":"US",
    "sg:address":"1258 Concord Rd",
    "sg:city":"Smyrna",
    "sg:classifiers":[
        {
            "category":"Professional",
            "subcategory":"Accounting & Tax Preparation",
            "type":"Services"
        }
    ],
    "sg:phone":"+1 770 333 1813",
    "sg:postcode":"30080",
    "sg:province":"GA",
    "wof:name":"General Business Services",
    "wof:placetype":"venue"
},
  "geometry": {"coordinates":[-84.51765399999999,33.878905],"type":"Point"}
}