{
  "type": "Feature",
  "properties": {
    "addr:full":"3123 Raymond Dr Atlanta GA 30340",
    "addr:housenumber":"3123",
    "addr:postcode":"30340",
    "addr:street":"Raymond Dr",
    "iso:country":"US",
    "sg:address":"3123 Raymond Dr",
    "sg:city":"Atlanta",
    "sg:classifiers":[
        {
            "category":"Professional",
            "subcategory":"Art Services",
            "type":"Services"
        }
    ],
    "sg:phone":"+1 770 457 4373",
    "sg:postcode":"30340",
    "sg:province":"GA",
    "sg:tags":[
        "graphic",
        "designer"
    ],
    "wof:name":"R Creations",
    "wof:placetype":"venue"
},
  "geometry": {"coordinates":[-84.277112,33.88683],"type":"Point"}
}