{
  "type": "Feature",
  "properties": {
    "addr:full":"2861 Bankers Industrial Dr Atlanta GA 30360",
    "addr:housenumber":"2861",
    "addr:postcode":"30360",
    "addr:street":"Bankers Industrial Dr",
    "iso:country":"US",
    "sg:address":"2861 Bankers Industrial Dr",
    "sg:city":"Atlanta",
    "sg:classifiers":[
        {
            "category":"Wholesale",
            "subcategory":"Auto Parts",
            "type":"Manufacturing & Wholesale Goods"
        }
    ],
    "sg:phone":"+1 770 449 7755",
    "sg:postcode":"30360",
    "sg:province":"GA",
    "sg:tags":[
        "accessory"
    ],
    "wof:name":"Reliable Automotive of GA",
    "wof:placetype":"venue"
},
  "geometry": {"coordinates":[-84.26244800000001,33.923433],"type":"Point"}
}