{
  "type": "Feature",
  "properties": {
    "iso:country":"US",
    "sg:address":"250 Curie Dr",
    "sg:city":"Alpharetta",
    "sg:classifiers":[
        {
            "category":"Freight",
            "type":"Transportation"
        }
    ],
    "sg:phone":"+1 678 393 2122",
    "sg:postcode":"30005",
    "sg:province":"GA",
    "sg:tags":[
        "warehouse"
    ],
    "wof:name":"The House of Fine Furniture",
    "wof:placetype":"venue"
},
  "geometry": {"coordinates":[-84.210319,34.103533],"type":"Point"}
}