{
  "type": "Feature",
  "properties": {
    "iso:country":"US",
    "sg:address":"215 E 16th St",
    "sg:city":"Alma",
    "sg:classifiers":[
        {
            "category":"Shopping",
            "subcategory":"Pharmacy",
            "type":"Retail Goods"
        }
    ],
    "sg:phone":"+1 912 632 6322",
    "sg:postcode":"31510",
    "sg:province":"GA",
    "wof:name":"Mobleys Pharmacy",
    "wof:placetype":"venue"
},
  "geometry": {"coordinates":[-82.460043,31.538886],"type":"Point"}
}