{
  "type": "Feature",
  "properties": {
    "iso:country":"US",
    "sg:address":"748 Grove St",
    "sg:city":"Gainesville",
    "sg:classifiers":[
        {
            "category":"Building & Trades",
            "subcategory":"Construction",
            "type":"Services"
        }
    ],
    "sg:phone":"+1 770 534 3161",
    "sg:postcode":"30501",
    "sg:province":"GA",
    "sg:tags":[
        "roofing",
        "contractor"
    ],
    "wof:name":"Parr Roofing Co Inc",
    "wof:placetype":"venue"
},
  "geometry": {"coordinates":[-83.824343,34.291988],"type":"Point"}
}