{
  "type": "Feature",
  "properties": {
    "addr:full":"140 Vann St Ste 350 Marietta GA 30060",
    "addr:housenumber":"140",
    "addr:postcode":"30060",
    "addr:street":"Vann St Ste 350",
    "iso:country":"US",
    "sg:address":"140 Vann St Ste 350",
    "sg:city":"Marietta",
    "sg:classifiers":[
        {
            "category":"Health Services",
            "subcategory":"Doctor",
            "type":"Services"
        }
    ],
    "sg:phone":"+1 770 574 4868",
    "sg:postcode":"30060",
    "sg:province":"GA",
    "sg:tags":[
        "surgeon",
        "cosmetic"
    ],
    "sg:website":"www.drchampion.com",
    "wof:name":"Dr. JK Champion - Bariatric Surgeon",
    "wof:placetype":"venue"
},
  "geometry": {"coordinates":[-84.549212,33.972191],"type":"Point"}
}