{
  "type": "Feature",
  "properties": {
    "iso:country":"US",
    "sg:address":"765 Pleasant Hill Rd NW",
    "sg:city":"Lilburn",
    "sg:classifiers":[
        {
            "category":"Professional",
            "subcategory":"Lawyer & Legal Services",
            "type":"Services"
        }
    ],
    "sg:phone":"+1 770 921 7048",
    "sg:postcode":"30047",
    "sg:province":"GA",
    "wof:name":"Boyce Peter F Atty",
    "wof:placetype":"venue"
},
  "geometry": {"coordinates":[-84.115303,33.911201],"type":"Point"}
}