{
  "type": "Feature",
  "properties": {
    "addr:full":"2243 Peeksville Rd Locust Grove GA 30248",
    "addr:housenumber":"2243",
    "addr:postcode":"30248",
    "addr:street":"Peeksville Rd",
    "iso:country":"US",
    "sg:address":"2243 Peeksville Rd",
    "sg:city":"Locust Grove",
    "sg:classifiers":[
        {
            "category":"Retail",
            "subcategory":"Repair Shop",
            "type":"Services"
        }
    ],
    "sg:phone":"+1 770 898 0758",
    "sg:postcode":"30248",
    "sg:province":"GA",
    "sg:tags":[
        "taxidermist"
    ],
    "wof:name":"Keith Clay Wildlife Taxidermy",
    "wof:placetype":"venue"
},
  "geometry": {"coordinates":[-84.038764,33.362286],"type":"Point"}
}