{
  "type": "Feature",
  "properties": {
    "iso:country":"US",
    "sg:address":"7035 Lagrange Blvd SW",
    "sg:city":"Atlanta",
    "sg:classifiers":[
        {
            "category":"Wholesale",
            "subcategory":"Home Furnishings",
            "type":"Manufacturing & Wholesale Goods"
        },
        {
            "category":"Manufacturing",
            "subcategory":"Rubber & Plastics",
            "type":"Manufacturing & Wholesale Goods"
        }
    ],
    "sg:phone":"+1 404 349 9005",
    "sg:postcode":"30336",
    "sg:province":"GA",
    "sg:tags":[
        "mfg",
        "floor",
        "mat",
        "matting",
        "covering"
    ],
    "sg:website":"www.multyindustries.com",
    "wof:name":"Multy Industries (usa) Inc",
    "wof:placetype":"venue"
},
  "geometry": {"coordinates":[-84.590919,33.721408],"type":"Point"}
}