{
  "type": "Feature",
  "properties": {
    "addr:full":"526 Ponce De Leon Ave NE Atlanta GA 30308",
    "addr:housenumber":"526",
    "addr:postcode":"30308",
    "addr:street":"Ponce De Leon Ave Ne",
    "iso:country":"US",
    "sg:address":"526 Ponce De Leon Ave NE",
    "sg:city":"Atlanta",
    "sg:classifiers":[
        {
            "category":"Fast Food",
            "type":"Food & Drink"
        }
    ],
    "sg:phone":"+1 404 874 7848",
    "sg:postcode":"30308",
    "sg:province":"GA",
    "sg:website":"www.mcdonalds.com/",
    "wof:name":"McDonald's",
    "wof:placetype":"venue"
},
  "geometry": {"coordinates":[-84.369575,33.773789],"type":"Point"}
}