{
  "type": "Feature",
  "properties": {
    "addr:full":"5 Hardee Dr Savannah GA 31406",
    "addr:housenumber":"5",
    "addr:postcode":"31406",
    "addr:street":"Hardee Dr",
    "iso:country":"US",
    "sg:address":"5 Hardee Dr",
    "sg:city":"Savannah",
    "sg:classifiers":[
        {
            "category":"Building & Trades",
            "subcategory":"Construction",
            "type":"Services"
        }
    ],
    "sg:phone":"+1 912 352 0237",
    "sg:postcode":"31406",
    "sg:province":"GA",
    "sg:tags":[
        "siding",
        "contractor"
    ],
    "wof:name":"Quarles Vinyl Products",
    "wof:placetype":"venue"
},
  "geometry": {"coordinates":[-81.083882,31.929863],"type":"Point"}
}