{
  "type": "Feature",
  "properties": {
    "addr:full":"1 Randolph Ct Evans GA 30809",
    "addr:housenumber":"1",
    "addr:postcode":"30809",
    "addr:street":"Randolph Ct",
    "iso:country":"US",
    "sg:address":"1 Randolph Ct",
    "sg:city":"Evans",
    "sg:classifiers":[
        {
            "category":"Utilities",
            "subcategory":"Water",
            "type":"Services"
        },
        {
            "category":"Building & Trades",
            "subcategory":"Cleaning & Sanitation",
            "type":"Services"
        },
        {
            "category":"Retail",
            "subcategory":"Laundry & Dry Cleaning",
            "type":"Services"
        },
        {
            "category":"Home & Garden",
            "subcategory":"Carpets & Floor Coverings",
            "type":"Retail Goods"
        }
    ],
    "sg:phone":"+1 706 868 5441",
    "sg:postcode":"30809",
    "sg:province":"GA",
    "sg:tags":[
        "cleaner",
        "emergency",
        "fire",
        "cleaners-water",
        "rug",
        "damage",
        "extraction",
        "restoration",
        "remediation",
        "mold"
    ],
    "sg:website":"http://www.servpro.com",
    "wof:name":"Servpro",
    "wof:placetype":"venue"
},
  "geometry": {"coordinates":[-82.114639,33.535599],"type":"Point"}
}