{
  "type": "Feature",
  "properties": {
    "addr:full":"3848 Creek Hollow Way Marietta GA 30062",
    "addr:housenumber":"3848",
    "addr:postcode":"30062",
    "addr:street":"Creek Hollow Way",
    "iso:country":"US",
    "sg:address":"3848 Creek Hollow Way",
    "sg:city":"Marietta",
    "sg:classifiers":[
        {
            "category":"Building & Trades",
            "subcategory":"Construction",
            "type":"Services"
        }
    ],
    "sg:phone":"+1 770 579 1193",
    "sg:postcode":"30062",
    "sg:province":"GA",
    "sg:tags":[
        "house"
    ],
    "wof:name":"Meticulous Woodworking Inc",
    "wof:placetype":"venue"
},
  "geometry": {"coordinates":[-84.45062900000001,34.043746],"type":"Point"}
}