{
  "type": "Feature",
  "properties": {
    "addr:full":"2650 Evergreen Ave Savannah GA 31404",
    "addr:housenumber":"2650",
    "addr:postcode":"31404",
    "addr:street":"Evergreen Ave",
    "iso:country":"US",
    "sg:address":"2650 Evergreen Ave",
    "sg:city":"Savannah",
    "sg:classifiers":[
        {
            "category":"Organizations",
            "subcategory":"Religious Organization",
            "type":"Services"
        }
    ],
    "sg:phone":"+1 912 232 3082",
    "sg:postcode":"31404",
    "sg:province":"GA",
    "wof:name":"First Corinthian Baptst Church",
    "wof:placetype":"venue"
},
  "geometry": {"coordinates":[-81.058712,32.039012],"type":"Point"}
}