{
  "type": "Feature",
  "properties": {
    "addr:full":"335 Hammond Dr NE Atlanta GA 30328",
    "addr:housenumber":"335",
    "addr:postcode":"30328",
    "addr:street":"Hammond Dr Ne",
    "iso:country":"US",
    "sg:address":"335 Hammond Dr NE",
    "sg:city":"Atlanta",
    "sg:classifiers":[
        {
            "category":"Personal",
            "subcategory":"Beauty Salon",
            "type":"Services"
        }
    ],
    "sg:phone":"+1 404 255 2737",
    "sg:postcode":"30328",
    "sg:province":"GA",
    "sg:tags":[
        "shop"
    ],
    "wof:name":"Zephyr Hair Salon",
    "wof:placetype":"venue"
},
  "geometry": {"coordinates":[-84.378141,33.919033],"type":"Point"}
}