{
  "type": "Feature",
  "properties": {
    "iso:country":"US",
    "sg:address":"3079 Morgan Rd",
    "sg:city":"Bremen",
    "sg:classifiers":[
        {
            "category":"Building & Trades",
            "subcategory":"Construction",
            "type":"Services"
        }
    ],
    "sg:phone":"+1 770 562 1102",
    "sg:postcode":"30110",
    "sg:province":"GA",
    "sg:tags":[
        "house"
    ],
    "wof:name":"Baggett Construction Co",
    "wof:placetype":"venue"
},
  "geometry": {"coordinates":[-85.065506,33.783822],"type":"Point"}
}