{
  "type": "Feature",
  "properties": {
    "iso:country":"US",
    "sg:address":"1660 Quail Run SW",
    "sg:city":"Conyers",
    "sg:classifiers":[
        {
            "category":"Building & Trades",
            "subcategory":"Construction",
            "type":"Services"
        }
    ],
    "sg:phone":"+1 770 761 0400",
    "sg:postcode":"30094",
    "sg:province":"GA",
    "wof:name":"Overstreet Paving & Repairs",
    "wof:placetype":"venue"
},
  "geometry": {"coordinates":[-84.046481,33.584219],"type":"Point"}
}