{
  "type": "Feature",
  "properties": {
    "iso:country":"US",
    "sg:address":"1061 Hale Rd",
    "sg:city":"Watkinsville",
    "sg:classifiers":[
        {
            "category":"Education",
            "subcategory":"Special Training",
            "type":"Public Place"
        }
    ],
    "sg:phone":"+1 706 769 1171",
    "sg:postcode":"30677",
    "sg:province":"GA",
    "sg:tags":[
        "professor"
    ],
    "wof:name":"Charles Hofacre",
    "wof:placetype":"venue"
},
  "geometry": {"coordinates":[-83.35512799999999,33.738361],"type":"Point"}
}