{
  "type": "Feature",
  "properties": {
    "addr:full":"103 Broad St Manchester GA 31830",
    "addr:housenumber":"103",
    "addr:postcode":"31830",
    "addr:street":"Broad St",
    "iso:country":"US",
    "sg:address":"103 Broad St",
    "sg:city":"Manchester",
    "sg:classifiers":[
        {
            "category":"Professional",
            "subcategory":"Advertising",
            "type":"Services"
        }
    ],
    "sg:phone":"+1 706 846 4336",
    "sg:postcode":"31830",
    "sg:province":"GA",
    "wof:name":"Trib Publications Inc",
    "wof:placetype":"venue"
},
  "geometry": {"coordinates":[-84.678839,32.89099],"type":"Point"}
}