{
  "type": "Feature",
  "properties": {
    "iso:country":"US",
    "sg:address":"5320 Cherokee St",
    "sg:city":"Acworth",
    "sg:classifiers":[
        {
            "category":"Travel",
            "subcategory":"Hotels & Motels",
            "type":"Entertainment"
        },
        {
            "category":"Travel",
            "subcategory":"Bed & Breakfast",
            "type":"Entertainment"
        }
    ],
    "sg:phone":"+1 770 974 5400",
    "sg:postcode":"30101",
    "sg:province":"GA",
    "sg:tags":[
        "inn",
        "lodging"
    ],
    "sg:website":"http://www.americasbestinns.com",
    "wof:name":"America's Best Inn",
    "wof:placetype":"venue"
},
  "geometry": {"coordinates":[-84.676407,34.07843],"type":"Point"}
}