{
  "type": "Feature",
  "properties": {
    "iso:country":"US",
    "sg:address":"1260 Brookview Ct",
    "sg:city":"Morrow",
    "sg:classifiers":[
        {
            "category":"Autos & Motor Vehicles",
            "subcategory":"Auto Supplies",
            "type":"Retail Goods"
        }
    ],
    "sg:phone":"+1 404 849 7255",
    "sg:postcode":"30260",
    "sg:province":"GA",
    "sg:tags":[
        "automobile",
        "top",
        "upholstery",
        "covers",
        "seat"
    ],
    "wof:name":"Correa S Custom Trim",
    "wof:placetype":"venue"
},
  "geometry": {"coordinates":[-84.349158,33.582835],"type":"Point"}
}