{
  "type": "Feature",
  "properties": {
    "iso:country":"US",
    "sg:address":"100 S Hill St",
    "sg:city":"Griffin",
    "sg:classifiers":[
        {
            "category":"Social Services",
            "type":"Services"
        }
    ],
    "sg:phone":"+1 770 229 4212",
    "sg:postcode":"30223",
    "sg:province":"GA",
    "sg:tags":[
        "organization",
        "welfare"
    ],
    "wof:name":"United Way",
    "wof:placetype":"venue"
},
  "geometry": {"coordinates":[-84.263667,33.248959],"type":"Point"}
}