{
  "type": "Feature",
  "properties": {
    "iso:country":"US",
    "sg:address":"3 E Halls Valley Rd",
    "sg:city":"Trion",
    "sg:classifiers":[
        {
            "category":"Personal",
            "subcategory":"Beauty Salon",
            "type":"Services"
        }
    ],
    "sg:phone":"+1 706 734 3576",
    "sg:postcode":"30753",
    "sg:province":"GA",
    "sg:tags":[
        "shop"
    ],
    "wof:name":"Linda Thomas",
    "wof:placetype":"venue"
},
  "geometry": {"coordinates":[-85.265277,34.565339],"type":"Point"}
}