{
  "type": "Feature",
  "properties": {
    "addr:full":"6555 Peachtree Industrial Blvd Atlanta GA 30360",
    "addr:housenumber":"6555",
    "addr:postcode":"30360",
    "addr:street":"Peachtree Industrial Blvd",
    "iso:country":"US",
    "sg:address":"6555 Peachtree Industrial Blvd",
    "sg:city":"Atlanta",
    "sg:classifiers":[
        {
            "category":"Autos & Motor Vehicles",
            "subcategory":"Auto Supplies",
            "type":"Retail Goods"
        }
    ],
    "sg:phone":"+1 770 455 1080",
    "sg:postcode":"30360",
    "sg:province":"GA",
    "sg:tags":[
        "tire"
    ],
    "sg:website":"www.ntb.com",
    "wof:name":"Ntb-National Tire & Battery",
    "wof:placetype":"venue"
},
  "geometry": {"coordinates":[-84.605512,33.702204],"type":"Point"}
}