{
  "type": "Feature",
  "properties": {
    "addr:full":"1705 State Rte 16 W Griffin GA 30223",
    "addr:housenumber":"1705",
    "addr:postcode":"30223",
    "addr:street":"State Rte 16 W",
    "iso:country":"US",
    "sg:address":"1705 State Rte 16 W",
    "sg:city":"Griffin",
    "sg:classifiers":[
        {
            "category":"Retail",
            "subcategory":"Auto Repair",
            "type":"Services"
        }
    ],
    "sg:phone":"+1 770 228 2661",
    "sg:postcode":"30223",
    "sg:province":"GA",
    "sg:tags":[
        "general"
    ],
    "wof:name":"Goodman Glass Company",
    "wof:placetype":"venue"
},
  "geometry": {"coordinates":[-84.307649,33.244651],"type":"Point"}
}