{
  "type": "Feature",
  "properties": {
    "iso:country":"US",
    "sg:address":"4377 Hugh Howell Rd",
    "sg:city":"Tucker",
    "sg:classifiers":[
        {
            "category":"Home & Garden",
            "subcategory":"Furniture",
            "type":"Retail Goods"
        }
    ],
    "sg:phone":"+1 770 270 0450",
    "sg:postcode":"30084",
    "sg:province":"GA",
    "sg:tags":[
        "store"
    ],
    "wof:name":"Furniture Liquidators",
    "wof:placetype":"venue"
},
  "geometry": {"coordinates":[-84.20770899999999,33.851302],"type":"Point"}
}