{
  "type": "Feature",
  "properties": {
    "addr:full":"604 Haddington Ln Peachtree City GA 30269",
    "addr:housenumber":"604",
    "addr:postcode":"30269",
    "addr:street":"Haddington Ln",
    "iso:country":"US",
    "sg:address":"604 Haddington Ln",
    "sg:city":"Peachtree City",
    "sg:classifiers":[
        {
            "category":"Communications",
            "subcategory":"Film & Video Production",
            "type":"Services"
        }
    ],
    "sg:phone":"+1 770 487 5292",
    "sg:postcode":"30269",
    "sg:province":"GA",
    "sg:tags":[
        "motion"
    ],
    "wof:name":"Precious Memories",
    "wof:placetype":"venue"
},
  "geometry": {"coordinates":[-84.57437299999999,33.430816],"type":"Point"}
}