{
  "type": "Feature",
  "properties": {
    "iso:country":"US",
    "sg:address":"7718 N Main St",
    "sg:city":"Jonesboro",
    "sg:classifiers":[
        {
            "category":"Shopping",
            "subcategory":"Bicycles & Sporting Goods",
            "type":"Retail Goods"
        }
    ],
    "sg:phone":"+1 770 477 8862",
    "sg:postcode":"30236",
    "sg:province":"GA",
    "sg:tags":[
        "bait",
        "fishing"
    ],
    "wof:name":"Lane's Bait & Tackle",
    "wof:placetype":"venue"
},
  "geometry": {"coordinates":[-84.36579,33.542422],"type":"Point"}
}