{
  "type": "Feature",
  "properties": {
    "addr:full":"101 Hoffman Dr Lagrange GA 30241",
    "addr:housenumber":"101",
    "addr:postcode":"30241",
    "addr:street":"Hoffman Dr",
    "iso:country":"US",
    "sg:address":"101 Hoffman Dr",
    "sg:city":"Lagrange",
    "sg:classifiers":[
        {
            "category":"Food & Beverages",
            "subcategory":"Groceries & Convenience Stores",
            "type":"Retail Goods"
        },
        {
            "category":"Autos & Motor Vehicles",
            "subcategory":"Fuel & Gas Station",
            "type":"Retail Goods"
        }
    ],
    "sg:phone":"+1 706 882 8760",
    "sg:postcode":"30241",
    "sg:province":"GA",
    "sg:tags":[
        "product",
        "oil",
        "petroleum"
    ],
    "wof:name":"Shell Food Mart 8",
    "wof:placetype":"venue"
},
  "geometry": {"coordinates":[-84.97530500000001,33.039564],"type":"Point"}
}