{
  "type": "Feature",
  "properties": {
    "addr:full":"2590 Peachtree Industrial Blvd Duluth GA 30097",
    "addr:housenumber":"2590",
    "addr:postcode":"30097",
    "addr:street":"Peachtree Industrial Blvd",
    "iso:country":"US",
    "sg:address":"2590 Peachtree Industrial Blvd",
    "sg:city":"Duluth",
    "sg:classifiers":[
        {
            "category":"Sports & Exercise",
            "subcategory":"Gym",
            "type":"Entertainment"
        },
        {
            "category":"Arena",
            "subcategory":"Sports Club",
            "type":"Entertainment"
        }
    ],
    "sg:phone":"+1 770 476 5645",
    "sg:postcode":"30097",
    "sg:province":"GA",
    "sg:tags":[
        "program",
        "health",
        "physical",
        "fitness"
    ],
    "sg:website":"http://www.jazzercise.com",
    "wof:name":"Jazzercise",
    "wof:placetype":"venue"
},
  "geometry": {"coordinates":[-84.136961,34.022624],"type":"Point"}
}