{
  "type": "Feature",
  "properties": {
    "addr:full":"10275 Industrial Blvd NE Covington GA 30014",
    "addr:housenumber":"10275",
    "addr:postcode":"30014",
    "addr:street":"Industrial Blvd Ne",
    "iso:country":"US",
    "sg:address":"10275 Industrial Blvd NE",
    "sg:city":"Covington",
    "sg:classifiers":[
        {
            "category":"Insurance",
            "subcategory":"Insurance Agent",
            "type":"Services"
        }
    ],
    "sg:phone":"+1 770 385 7347",
    "sg:postcode":"30014",
    "sg:province":"GA",
    "wof:name":"Midsouth Insurance",
    "wof:placetype":"venue"
},
  "geometry": {"coordinates":[-83.838297,33.606176],"type":"Point"}
}