{
  "type": "Feature",
  "properties": {
    "addr:full":"1704 Wiscasset Pl Tucker GA 30084",
    "addr:housenumber":"1704",
    "addr:postcode":"30084",
    "addr:street":"Wiscasset Pl",
    "iso:country":"US",
    "sg:address":"1704 Wiscasset Pl",
    "sg:city":"Tucker",
    "sg:classifiers":[
        {
            "category":"Building & Trades",
            "subcategory":"Construction",
            "type":"Services"
        }
    ],
    "sg:phone":"+1 770 934 2420",
    "sg:postcode":"30084",
    "sg:province":"GA",
    "sg:tags":[
        "painter"
    ],
    "wof:name":"Elite Renovation & Painting",
    "wof:placetype":"venue"
},
  "geometry": {"coordinates":[-84.215338,33.833161],"type":"Point"}
}