{
  "type": "Feature",
  "properties": {
    "iso:country":"US",
    "sg:address":"2136 W Park Place Blvd",
    "sg:city":"Stone Mountain",
    "sg:classifiers":[
        {
            "category":"Wholesale",
            "subcategory":"Hardware",
            "type":"Manufacturing & Wholesale Goods"
        }
    ],
    "sg:phone":"+1 770 363 3313",
    "sg:postcode":"30087",
    "sg:province":"GA",
    "sg:tags":[
        "air",
        "parts",
        "conditioning",
        "supply"
    ],
    "wof:name":"Fox Appliance Parts",
    "wof:placetype":"venue"
},
  "geometry": {"coordinates":[-84.11887400000001,33.817678],"type":"Point"}
}