{
  "type": "Feature",
  "properties": {
    "iso:country":"US",
    "sg:address":"6470 Spalding Dr Ste N",
    "sg:city":"Norcross",
    "sg:phone":"+1 770 242 6406",
    "sg:postcode":"30092",
    "sg:province":"GA",
    "wof:name":"Taido Karate",
    "wof:placetype":"venue"
},
  "geometry": {"coordinates":[-84.260274,33.967509],"type":"Point"}
}