{
  "type": "Feature",
  "properties": {
    "addr:full":"6470 Spalding Dr Ste N Norcross GA 30092",
    "addr:housenumber":"6470",
    "addr:postcode":"30092",
    "addr:street":"Spalding Dr Ste N",
    "iso:country":"US",
    "sg:address":"6470 Spalding Dr Ste N",
    "sg:city":"Norcross",
    "sg:phone":"+1 770 242 6406",
    "sg:postcode":"30092",
    "sg:province":"GA",
    "wof:name":"Taido Karate",
    "wof:placetype":"venue"
},
  "geometry": {"coordinates":[-84.260274,33.967509],"type":"Point"}
}