{
  "type": "Feature",
  "properties": {
    "addr:full":"968 1st St Macon GA 31201",
    "addr:housenumber":"968",
    "addr:postcode":"31201",
    "addr:street":"1St St",
    "iso:country":"US",
    "sg:address":"968 1st St",
    "sg:city":"Macon",
    "sg:classifiers":[
        {
            "category":"Shopping",
            "subcategory":"Gifts & Souvenirs",
            "type":"Retail Goods"
        }
    ],
    "sg:phone":"+1 478 746 9901",
    "sg:postcode":"31201",
    "sg:province":"GA",
    "sg:tags":[
        "shop"
    ],
    "wof:name":"Essentials & Accessories",
    "wof:placetype":"venue"
},
  "geometry": {"coordinates":[-83.63737999999999,32.829941],"type":"Point"}
}