{
  "type": "Feature",
  "properties": {
    "addr:full":"7 Holland Park Dr Ellenwood GA 30294",
    "addr:housenumber":"7",
    "addr:postcode":"30294",
    "addr:street":"Holland Park Dr",
    "iso:country":"US",
    "sg:address":"7 Holland Park Dr",
    "sg:city":"Ellenwood",
    "sg:classifiers":[
        {
            "category":"Real Estate",
            "subcategory":"Real Estate Operator",
            "type":"Services"
        }
    ],
    "sg:phone":"+1 404 366 2030",
    "sg:postcode":"30294",
    "sg:province":"GA",
    "sg:tags":[
        "apartment"
    ],
    "wof:name":"Kennon Properties",
    "wof:placetype":"venue"
},
  "geometry": {"coordinates":[-84.31053199999999,33.619678],"type":"Point"}
}