{
  "type": "Feature",
  "properties": {
    "iso:country":"US",
    "sg:address":"118 Rosemary Way",
    "sg:city":"Lincolnton",
    "sg:classifiers":[
        {
            "category":"Building & Trades",
            "subcategory":"Plumbing",
            "type":"Services"
        }
    ],
    "sg:phone":"+1 706 359 4927",
    "sg:postcode":"30830",
    "sg:province":"GA",
    "sg:tags":[
        "contractor"
    ],
    "wof:name":"B & B Mechanical",
    "wof:placetype":"venue"
},
  "geometry": {"coordinates":[-81.94659799999999,33.131084],"type":"Point"}
}