{
  "type": "Feature",
  "properties": {
    "addr:full":"128 W Belmont Dr Calhoun GA 30701",
    "addr:housenumber":"128",
    "addr:postcode":"30701",
    "addr:street":"W Belmont Dr",
    "iso:country":"US",
    "sg:address":"128 W Belmont Dr",
    "sg:city":"Calhoun",
    "sg:classifiers":[
        {
            "category":"Restaurant",
            "type":"Food & Drink"
        }
    ],
    "sg:menulink":"http://www.allmenus.com/ga/calhoun/87315-little-caesars-pizza/menu/",
    "sg:phone":"+1 706 629 0003",
    "sg:postcode":"30701",
    "sg:province":"GA",
    "sg:tags":[
        "american",
        "pizza"
    ],
    "wof:name":"Little Caesar's Pizza",
    "wof:placetype":"venue"
},
  "geometry": {"coordinates":[-84.936091,34.479002],"type":"Point"}
}