{
  "type": "Feature",
  "properties": {
    "iso:country":"US",
    "sg:address":"8060 Mall Parkway",
    "sg:city":"Lithonia",
    "sg:classifiers":[
        {
            "category":"Cinema",
            "subcategory":"Movie Theater",
            "type":"Entertainment"
        }
    ],
    "sg:phone":"+1 770 484 8818",
    "sg:postcode":"30038",
    "sg:province":"GA",
    "sg:website":"www.amctheatres.com",
    "wof:name":"AMC Theatres Stonecrest 16",
    "wof:placetype":"venue"
},
  "geometry": {"coordinates":[-84.083099,33.695499],"type":"Point"}
}