{
  "type": "Feature",
  "properties": {
    "addr:full":"3340 Haddon Hall Dr Buford GA 30519",
    "addr:housenumber":"3340",
    "addr:postcode":"30519",
    "addr:street":"Haddon Hall Dr",
    "iso:country":"US",
    "sg:address":"3340 Haddon Hall Dr",
    "sg:city":"Buford",
    "sg:classifiers":[
        {
            "category":"Insurance",
            "subcategory":"Insurance Agent",
            "type":"Services"
        }
    ],
    "sg:phone":"+1 678 546 0459",
    "sg:postcode":"30519",
    "sg:province":"GA",
    "sg:tags":[
        "security"
    ],
    "wof:name":"Martin Johnson",
    "wof:placetype":"venue"
},
  "geometry": {"coordinates":[-83.927947,34.09671],"type":"Point"}
}