{
  "type": "Feature",
  "properties": {
    "addr:full":"7001 Bellville Rd Lake Park GA 31636",
    "addr:housenumber":"7001",
    "addr:postcode":"31636",
    "addr:street":"Bellville Rd",
    "iso:country":"US",
    "sg:address":"7001 Bellville Rd",
    "sg:city":"Lake Park",
    "sg:classifiers":[
        {
            "category":"Restaurant",
            "type":"Food & Drink"
        }
    ],
    "sg:phone":"+1 229 559 6700",
    "sg:postcode":"31636",
    "sg:province":"GA",
    "wof:name":"Flying J Restaurant",
    "wof:placetype":"venue"
},
  "geometry": {"coordinates":[-83.189516,30.643341],"type":"Point"}
}