{
  "type": "Feature",
  "properties": {
    "iso:country":"US",
    "sg:address":"741 Northern Ave",
    "sg:city":"Clarkston",
    "sg:classifiers":[
        {
            "category":"Shopping",
            "subcategory":"Clothing, Apparel, & Fashions",
            "type":"Retail Goods"
        }
    ],
    "sg:phone":"+1 404 297 2023",
    "sg:postcode":"30021",
    "sg:province":"GA",
    "sg:tags":[
        "family"
    ],
    "wof:name":"Aminata",
    "wof:placetype":"venue"
},
  "geometry": {"coordinates":[-84.247345,33.801026],"type":"Point"}
}