{
  "type": "Feature",
  "properties": {
    "iso:country":"US",
    "sg:address":"2003 Flightway Dr",
    "sg:city":"Atlanta",
    "sg:classifiers":[
        {
            "category":"Education",
            "subcategory":"Special Training",
            "type":"Public Place"
        }
    ],
    "sg:phone":"+1 770 452 8887",
    "sg:postcode":"30341",
    "sg:province":"GA",
    "sg:tags":[
        "broadcast",
        "station",
        "radio"
    ],
    "wof:name":"Flightsafety International",
    "wof:placetype":"venue"
},
  "geometry": {"coordinates":[-84.305436,33.885243],"type":"Point"}
}