{
  "type": "Feature",
  "properties": {
    "iso:country":"US",
    "sg:address":"5845 Jackaranda Dr SE",
    "sg:city":"Mableton",
    "sg:classifiers":[
        {
            "category":"Professional",
            "subcategory":"Business Services",
            "type":"Services"
        }
    ],
    "sg:phone":"+1 404 699 5555",
    "sg:postcode":"30126",
    "sg:province":"GA",
    "wof:name":"Personnel & Safety Admin",
    "wof:placetype":"venue"
},
  "geometry": {"coordinates":[-84.495248,33.811615],"type":"Point"}
}