{
  "type": "Feature",
  "properties": {
    "iso:country":"US",
    "sg:address":"473 Stewart Mill Rd",
    "sg:city":"Stone Mountain",
    "sg:classifiers":[
        {
            "category":"Retail",
            "subcategory":"Repair Shop",
            "type":"Services"
        }
    ],
    "sg:phone":"+1 770 879 1976",
    "sg:postcode":"30087",
    "sg:province":"GA",
    "wof:name":"Telecable TV & Phone Wiring",
    "wof:placetype":"venue"
},
  "geometry": {"coordinates":[-84.118634,33.794609],"type":"Point"}
}