{
  "type": "Feature",
  "properties": {
    "addr:full":"8441 Bebber Dr Blairsville GA 30512",
    "addr:housenumber":"8441",
    "addr:postcode":"30512",
    "addr:street":"Bebber Dr",
    "iso:country":"US",
    "sg:address":"8441 Bebber Dr",
    "sg:city":"Blairsville",
    "sg:classifiers":[
        {
            "category":"Autos & Motor Vehicles",
            "subcategory":"Automobile Sales",
            "type":"Retail Goods"
        }
    ],
    "sg:phone":"+1 706 745 5482",
    "sg:postcode":"30512",
    "sg:province":"GA",
    "sg:tags":[
        "cart"
    ],
    "wof:name":"Andretti's Cart Shop",
    "wof:placetype":"venue"
},
  "geometry": {"coordinates":[-84.108,34.845336],"type":"Point"}
}