{
  "type": "Feature",
  "properties": {
    "iso:country":"US",
    "sg:address":"9348 Sweetbriar Trce",
    "sg:city":"Jonesboro",
    "sg:classifiers":[
        {
            "category":"Building & Trades",
            "subcategory":"Cleaning & Sanitation",
            "type":"Services"
        }
    ],
    "sg:phone":"+1 770 477 7906",
    "sg:postcode":"30236",
    "sg:province":"GA",
    "sg:tags":[
        "maintenance"
    ],
    "wof:name":"B&N Janitorial Service Inc",
    "wof:placetype":"venue"
},
  "geometry": {"coordinates":[-84.291138,33.499151],"type":"Point"}
}