{
  "type": "Feature",
  "properties": {
    "addr:full":"2428 E Main St Snellville GA 30078",
    "addr:housenumber":"2428",
    "addr:postcode":"30078",
    "addr:street":"E Main St",
    "iso:country":"US",
    "sg:address":"2428 E Main St",
    "sg:city":"Snellville",
    "sg:classifiers":[
        {
            "category":"Education",
            "subcategory":"School",
            "type":"Public Place"
        }
    ],
    "sg:phone":"+1 770 982 3773",
    "sg:postcode":"30078",
    "sg:province":"GA",
    "wof:name":"Asbury Christian Academy",
    "wof:placetype":"venue"
},
  "geometry": {"coordinates":[-84.01722599999999,33.856798],"type":"Point"}
}