{
  "type": "Feature",
  "properties": {
    "iso:country":"US",
    "sg:address":"305 Buckhead Ave NE",
    "sg:city":"Atlanta",
    "sg:classifiers":[
        {
            "category":"Professional",
            "subcategory":"Lawyer & Legal Services",
            "type":"Services"
        }
    ],
    "sg:phone":"+1 404 842 9811",
    "sg:postcode":"30305",
    "sg:province":"GA",
    "wof:name":"Millender Ivan A",
    "wof:placetype":"venue"
},
  "geometry": {"coordinates":[-84.376538,33.838128],"type":"Point"}
}