{
  "type": "Feature",
  "properties": {
    "addr:full":"4415 Felmellow Dr Grovetown GA 30813",
    "addr:housenumber":"4415",
    "addr:postcode":"30813",
    "addr:street":"Felmellow Dr",
    "iso:country":"US",
    "sg:address":"4415 Felmellow Dr",
    "sg:city":"Grovetown",
    "sg:classifiers":[
        {
            "category":"Building & Trades",
            "subcategory":"Construction",
            "type":"Services"
        }
    ],
    "sg:phone":"+1 706 869 0655",
    "sg:postcode":"30813",
    "sg:province":"GA",
    "sg:tags":[
        "home",
        "builder"
    ],
    "wof:name":"Neil Youngblood Builders",
    "wof:placetype":"venue"
},
  "geometry": {"coordinates":[-82.181815,33.441932],"type":"Point"}
}