{
  "type": "Feature",
  "properties": {
    "iso:country":"US",
    "sg:address":"130 W Wieuca Rd NE",
    "sg:city":"Atlanta",
    "sg:classifiers":[
        {
            "category":"Real Estate",
            "subcategory":"Real Estate Agent",
            "type":"Services"
        }
    ],
    "sg:phone":"+1 404 255 3050",
    "sg:postcode":"30342",
    "sg:province":"GA",
    "wof:name":"McClure & Assoc Inc",
    "wof:placetype":"venue"
},
  "geometry": {"coordinates":[-84.383698,33.877582],"type":"Point"}
}