{
  "type": "Feature",
  "properties": {
    "iso:country":"US",
    "sg:address":"235 Walnut Ave S",
    "sg:city":"Leesburg",
    "sg:classifiers":[
        {
            "category":"Health Services",
            "subcategory":"Clinic",
            "type":"Services"
        }
    ],
    "sg:phone":"+1 229 759 6508",
    "sg:postcode":"31763",
    "sg:province":"GA",
    "wof:name":"Parsley, Lea K MD",
    "wof:placetype":"venue"
},
  "geometry": {"coordinates":[-84.172134,31.727777],"type":"Point"}
}