{
  "type": "Feature",
  "properties": {
    "addr:full":"220 W College Ave Decatur GA 30030",
    "addr:housenumber":"220",
    "addr:postcode":"30030",
    "addr:street":"W College Ave",
    "iso:country":"US",
    "sg:address":"220 W College Ave",
    "sg:city":"Decatur",
    "sg:classifiers":[
        {
            "category":"Education",
            "subcategory":"School",
            "type":"Public Place"
        }
    ],
    "sg:phone":"+1 404 370 4440",
    "sg:postcode":"30030",
    "sg:province":"GA",
    "sg:tags":[
        "high",
        "middle",
        "elementary"
    ],
    "wof:name":"Decatur Board of Education",
    "wof:placetype":"venue"
},
  "geometry": {"coordinates":[-84.29901599999999,33.768685],"type":"Point"}
}