{
  "type": "Feature",
  "properties": {
    "iso:country":"US",
    "sg:address":"903 E Screven St",
    "sg:city":"Quitman",
    "sg:classifiers":[
        {
            "category":"Travel",
            "subcategory":"Hotels & Motels",
            "type":"Entertainment"
        }
    ],
    "sg:phone":"+1 229 263 4114",
    "sg:postcode":"31643",
    "sg:province":"GA",
    "sg:tags":[
        "operation"
    ],
    "wof:name":"Georgian Motel",
    "wof:placetype":"venue"
},
  "geometry": {"coordinates":[-83.55253399999999,30.784633],"type":"Point"}
}