{
  "type": "Feature",
  "properties": {
    "iso:country":"US",
    "sg:address":"116 Holly Dr",
    "sg:city":"Warner Robins",
    "sg:classifiers":[
        {
            "category":"Real Estate",
            "subcategory":"Real Estate Agent",
            "type":"Services"
        }
    ],
    "sg:phone":"+1 478 929 5277",
    "sg:postcode":"31088",
    "sg:province":"GA",
    "wof:name":"Eden Hill Property Management",
    "wof:placetype":"venue"
},
  "geometry": {"coordinates":[-83.580693,32.571518],"type":"Point"}
}