{
  "type": "Feature",
  "properties": {
    "addr:full":"493 State Rte 2 W Crandall GA 30711",
    "addr:housenumber":"493",
    "addr:postcode":"30711",
    "addr:street":"State Rte 2 W",
    "iso:country":"US",
    "sg:address":"493 State Rte 2 W",
    "sg:city":"Crandall",
    "sg:classifiers":[
        {
            "category":"Shopping",
            "subcategory":"Shoes",
            "type":"Retail Goods"
        }
    ],
    "sg:phone":"+1 706 234 8335",
    "sg:postcode":"30711",
    "sg:province":"GA",
    "wof:name":"My Shoe Store Inc",
    "wof:placetype":"venue"
},
  "geometry": {"coordinates":[-84.789396,34.941312],"type":"Point"}
}