{
  "type": "Feature",
  "properties": {
    "addr:full":"81 W Ridge Dr SE Cartersville GA 30121",
    "addr:housenumber":"81",
    "addr:postcode":"30121",
    "addr:street":"W Ridge Dr Se",
    "iso:country":"US",
    "sg:address":"81 W Ridge Dr SE",
    "sg:city":"Cartersville",
    "sg:classifiers":[
        {
            "category":"Retail",
            "subcategory":"Animal Services",
            "type":"Services"
        }
    ],
    "sg:phone":"+1 770 606 9433",
    "sg:postcode":"30121",
    "sg:province":"GA",
    "sg:tags":[
        "pet"
    ],
    "wof:name":"Big City Dogs",
    "wof:placetype":"venue"
},
  "geometry": {"coordinates":[-84.748924,34.201491],"type":"Point"}
}