{
  "type": "Feature",
  "properties": {
    "addr:full":"9656 Bowman Hwy Bowman GA 30624",
    "addr:housenumber":"9656",
    "addr:postcode":"30624",
    "addr:street":"Bowman Hwy",
    "iso:country":"US",
    "sg:address":"9656 Bowman Hwy",
    "sg:city":"Bowman",
    "sg:classifiers":[
        {
            "category":"Farming",
            "subcategory":"Livestock Farm",
            "type":"Manufacturing & Wholesale Goods"
        }
    ],
    "sg:phone":"+1 706 245 6949",
    "sg:postcode":"30624",
    "sg:province":"GA",
    "sg:tags":[
        "animal",
        "general"
    ],
    "wof:name":"Terry Mize",
    "wof:placetype":"venue"
},
  "geometry": {"coordinates":[-83.001017,34.233359],"type":"Point"}
}