{
  "type": "Feature",
  "properties": {
    "addr:full":"3348 Peachtree Rd NE Ste 1425 Atlanta GA 30326",
    "addr:housenumber":"3348",
    "addr:postcode":"30326",
    "addr:street":"Peachtree Rd Ne Ste 1425",
    "iso:country":"US",
    "sg:address":"3348 Peachtree Rd NE Ste 1425",
    "sg:city":"Atlanta",
    "sg:classifiers":[
        {
            "category":"Shopping",
            "subcategory":"Jewelry",
            "type":"Retail Goods"
        }
    ],
    "sg:phone":"+1 404 239 9151",
    "sg:postcode":"30326",
    "sg:province":"GA",
    "sg:website":"www.neilsaundersdiamonds.com",
    "wof:name":"Neil Saunders Co Inc",
    "wof:placetype":"venue"
},
  "geometry": {"coordinates":[-84.369238,33.846491],"type":"Point"}
}