{
  "type": "Feature",
  "properties": {
    "addr:full":"8575 Creekwood Ridge Dr Palmetto GA 30268",
    "addr:housenumber":"8575",
    "addr:postcode":"30268",
    "addr:street":"Creekwood Ridge Dr",
    "iso:country":"US",
    "sg:address":"8575 Creekwood Ridge Dr",
    "sg:city":"Palmetto",
    "sg:classifiers":[
        {
            "category":"Building & Trades",
            "subcategory":"Construction",
            "type":"Services"
        }
    ],
    "sg:phone":"+1 770 306 7572",
    "sg:postcode":"30268",
    "sg:province":"GA",
    "sg:tags":[
        "handyman"
    ],
    "wof:name":"Milton Turner Handyman",
    "wof:placetype":"venue"
},
  "geometry": {"coordinates":[-84.60023099999999,33.522584],"type":"Point"}
}