{
  "type": "Feature",
  "properties": {
    "addr:full":"4800 Briarcliff Rd NE Atlanta GA 30345",
    "addr:housenumber":"4800",
    "addr:postcode":"30345",
    "addr:street":"Briarcliff Rd Ne",
    "iso:country":"US",
    "sg:address":"4800 Briarcliff Rd NE",
    "sg:city":"Atlanta",
    "sg:classifiers":[
        {
            "category":"Wholesale",
            "subcategory":"Stationery",
            "type":"Manufacturing & Wholesale Goods"
        }
    ],
    "sg:phone":"+1 770 938 2980",
    "sg:postcode":"30345",
    "sg:province":"GA",
    "sg:tags":[
        "card"
    ],
    "wof:name":"Social Expressions",
    "wof:placetype":"venue"
},
  "geometry": {"coordinates":[-84.256699,33.8489],"type":"Point"}
}