{
  "type": "Feature",
  "properties": {
    "iso:country":"US",
    "sg:address":"481 N Main St",
    "sg:city":"Ellijay",
    "sg:classifiers":[
        {
            "category":"Health Services",
            "subcategory":"Hospital",
            "type":"Services"
        }
    ],
    "sg:phone":"+1 706 635 4943",
    "sg:postcode":"30540",
    "sg:province":"GA",
    "sg:tags":[
        "sleep",
        "treatment",
        "disorders-information"
    ],
    "wof:name":"Sports Therapy Clinic",
    "wof:placetype":"venue"
},
  "geometry": {"coordinates":[-84.478887,34.700353],"type":"Point"}
}