{
  "type": "Feature",
  "properties": {
    "iso:country":"US",
    "sg:address":"538 N Oak St",
    "sg:city":"Jackson",
    "sg:classifiers":[
        {
            "category":"Personal",
            "subcategory":"Beauty Salon",
            "type":"Services"
        }
    ],
    "sg:phone":"+1 770 775 0754",
    "sg:postcode":"30233",
    "sg:province":"GA",
    "wof:name":"Chic Beauty Salon",
    "wof:placetype":"venue"
},
  "geometry": {"coordinates":[-83.967416,33.29989],"type":"Point"}
}