{
  "type": "Feature",
  "properties": {
    "iso:country":"US",
    "sg:address":"5 W Jarman St",
    "sg:city":"Hazlehurst",
    "sg:classifiers":[
        {
            "category":"Home & Garden",
            "subcategory":"Carpets & Floor Coverings",
            "type":"Retail Goods"
        }
    ],
    "sg:phone":"+1 912 375 5158",
    "sg:postcode":"31539",
    "sg:province":"GA",
    "sg:tags":[
        "dealer",
        "rug"
    ],
    "wof:name":"Davis Carpet World",
    "wof:placetype":"venue"
},
  "geometry": {"coordinates":[-82.59702900000001,31.870717],"type":"Point"}
}