{
  "type": "Feature",
  "properties": {
    "iso:country":"US",
    "sg:address":"1951 Canton Rd",
    "sg:city":"Marietta",
    "sg:classifiers":[
        {
            "category":"Home & Garden",
            "subcategory":"Hardware",
            "type":"Retail Goods"
        }
    ],
    "sg:phone":"+1 770 428 8837",
    "sg:postcode":"30066",
    "sg:province":"GA",
    "sg:tags":[
        "supply"
    ],
    "wof:name":"Ford Hardware Co",
    "wof:placetype":"venue"
},
  "geometry": {"coordinates":[-84.523859,33.998007],"type":"Point"}
}