{
  "type": "Feature",
  "properties": {
    "iso:country":"US",
    "sg:address":"500 Fulton St SW",
    "sg:city":"Atlanta",
    "sg:classifiers":[
        {
            "category":"Building & Trades",
            "subcategory":"Cleaning & Sanitation",
            "type":"Services"
        }
    ],
    "sg:phone":"+1 404 223 2229",
    "sg:postcode":"30312",
    "sg:province":"GA",
    "sg:tags":[
        "house"
    ],
    "wof:name":"Cynithia House Cleaning",
    "wof:placetype":"venue"
},
  "geometry": {"coordinates":[-84.40522799999999,33.740542],"type":"Point"}
}