{
  "type": "Feature",
  "properties": {
    "addr:full":"270 Hilderbrand Dr NE Atlanta GA 30328",
    "addr:housenumber":"270",
    "addr:postcode":"30328",
    "addr:street":"Hilderbrand Dr Ne",
    "iso:country":"US",
    "sg:address":"270 Hilderbrand Dr NE",
    "sg:city":"Atlanta",
    "sg:classifiers":[
        {
            "category":"Recreation",
            "type":"Entertainment"
        }
    ],
    "sg:phone":"+1 404 252 2344",
    "sg:postcode":"30328",
    "sg:province":"GA",
    "sg:tags":[
        "art",
        "gallery"
    ],
    "wof:name":"Springs Gallery",
    "wof:placetype":"venue"
},
  "geometry": {"coordinates":[-84.37795699999999,33.923042],"type":"Point"}
}