{
  "type": "Feature",
  "properties": {
    "iso:country":"US",
    "sg:address":"1643 Mount Vernon Rd",
    "sg:city":"Atlanta",
    "sg:classifiers":[
        {
            "category":"Banks & Credit Unions",
            "subcategory":"Investment Brokerage",
            "type":"Services"
        }
    ],
    "sg:phone":"+1 770 558 8182",
    "sg:postcode":"30338",
    "sg:province":"GA",
    "sg:tags":[
        "security"
    ],
    "wof:name":"Kevin Latty Investment Managem",
    "wof:placetype":"venue"
},
  "geometry": {"coordinates":[-84.332278,33.946669],"type":"Point"}
}