{
  "type": "Feature",
  "properties": {
    "addr:full":"248 N Broad St Monroe GA 30655",
    "addr:housenumber":"248",
    "addr:postcode":"30655",
    "addr:street":"N Broad St",
    "iso:country":"US",
    "sg:address":"248 N Broad St",
    "sg:city":"Monroe",
    "sg:classifiers":[
        {
            "category":"Real Estate",
            "subcategory":"Real Estate Agent",
            "type":"Services"
        }
    ],
    "sg:phone":"+1 770 267 7261",
    "sg:postcode":"30655",
    "sg:province":"GA",
    "wof:name":"Century 21",
    "wof:placetype":"venue"
},
  "geometry": {"coordinates":[-83.713734,33.797659],"type":"Point"}
}