{
  "type": "Feature",
  "properties": {
    "iso:country":"US",
    "sg:address":"10 Herring St",
    "sg:city":"Cartersville",
    "sg:classifiers":[
        {
            "category":"Manufacturing",
            "subcategory":"Lumber",
            "type":"Manufacturing & Wholesale Goods"
        }
    ],
    "sg:phone":"+1 770 607 7779",
    "sg:postcode":"30120",
    "sg:province":"GA",
    "sg:tags":[
        "mill"
    ],
    "wof:name":"Perfect Designs",
    "wof:placetype":"venue"
},
  "geometry": {"coordinates":[-84.80374399999999,34.161058],"type":"Point"}
}