{
  "type": "Feature",
  "properties": {
    "addr:full":"2523 Roosevelt Hwy Atlanta GA 30337",
    "addr:housenumber":"2523",
    "addr:postcode":"30337",
    "addr:street":"Roosevelt Hwy",
    "iso:country":"US",
    "sg:address":"2523 Roosevelt Hwy",
    "sg:city":"Atlanta",
    "sg:classifiers":[
        {
            "category":"Professional",
            "subcategory":"Business Services",
            "type":"Services"
        }
    ],
    "sg:phone":"+1 404 761 2257",
    "sg:postcode":"30337",
    "sg:province":"GA",
    "wof:name":"Professnal Tctic Answring Svcs",
    "wof:placetype":"venue"
},
  "geometry": {"coordinates":[-84.469437,33.63143],"type":"Point"}
}