{
  "type": "Feature",
  "properties": {
    "iso:country":"US",
    "sg:address":"255 Norcross St",
    "sg:city":"Roswell",
    "sg:classifiers":[
        {
            "category":"Professional",
            "subcategory":"Engineering",
            "type":"Services"
        }
    ],
    "sg:phone":"+1 770 998 5521",
    "sg:postcode":"30075",
    "sg:province":"GA",
    "sg:tags":[
        "engineer"
    ],
    "wof:name":"DMD Engineering & Testing",
    "wof:placetype":"venue"
},
  "geometry": {"coordinates":[-84.353706,34.025638],"type":"Point"}
}