{
  "type": "Feature",
  "properties": {
    "addr:full":"3420 Oakcliff Rd Doraville GA 30340",
    "addr:housenumber":"3420",
    "addr:postcode":"30340",
    "addr:street":"Oakcliff Rd",
    "iso:country":"US",
    "sg:address":"3420 Oakcliff Rd",
    "sg:city":"Doraville",
    "sg:classifiers":[
        {
            "category":"Manufacturing",
            "subcategory":"Apparel",
            "type":"Manufacturing & Wholesale Goods"
        }
    ],
    "sg:phone":"+1 770 368 0195",
    "sg:postcode":"30340",
    "sg:province":"GA",
    "sg:tags":[
        "flag",
        "banner"
    ],
    "sg:website":"www.flagsmore.com",
    "wof:name":"Flagsmore",
    "wof:placetype":"venue"
},
  "geometry": {"coordinates":[-84.25334599999999,33.903059],"type":"Point"}
}