{
  "type": "Feature",
  "properties": {
    "iso:country":"US",
    "sg:address":"3647 Bob White Ln SW",
    "sg:city":"Loganville",
    "sg:classifiers":[
        {
            "category":"Building & Trades",
            "subcategory":"Construction",
            "type":"Services"
        }
    ],
    "sg:phone":"+1 770 554 9103",
    "sg:postcode":"30052",
    "sg:province":"GA",
    "sg:tags":[
        "nonresidential"
    ],
    "wof:name":"Construction Staking Svcs",
    "wof:placetype":"venue"
},
  "geometry": {"coordinates":[-83.94240600000001,33.846204],"type":"Point"}
}