{
  "type": "Feature",
  "properties": {
    "iso:country":"US",
    "sg:address":"2283 Echo Trl NE",
    "sg:city":"Atlanta",
    "sg:classifiers":[
        {
            "category":"Professional",
            "subcategory":"Business Services",
            "type":"Services"
        }
    ],
    "sg:phone":"+1 404 320 0990",
    "sg:postcode":"30345",
    "sg:province":"GA",
    "wof:name":"Lang Group LLC",
    "wof:placetype":"venue"
},
  "geometry": {"coordinates":[-84.288027,33.850347],"type":"Point"}
}