{
  "type": "Feature",
  "properties": {
    "iso:country":"US",
    "sg:address":"201 Industrial Dr",
    "sg:city":"Hogansville",
    "sg:classifiers":[
        {
            "category":"Home & Garden",
            "subcategory":"Building Materials",
            "type":"Retail Goods"
        }
    ],
    "sg:phone":"+1 706 637 9885",
    "sg:postcode":"30230",
    "sg:province":"GA",
    "sg:tags":[
        "mixed",
        "concrete"
    ],
    "wof:name":"Middle Georgia Concrete",
    "wof:placetype":"venue"
},
  "geometry": {"coordinates":[-84.914512,33.155832],"type":"Point"}
}