{
  "type": "Feature",
  "properties": {
    "iso:country":"US",
    "sg:address":"9 Lagrange St",
    "sg:city":"Newnan",
    "sg:classifiers":[
        {
            "category":"Shopping",
            "type":"Retail Goods"
        }
    ],
    "sg:phone":"+1 770 251 7373",
    "sg:postcode":"30263",
    "sg:province":"GA",
    "sg:tags":[
        "merchandise"
    ],
    "wof:name":"Sprint P C S Newnan",
    "wof:placetype":"venue"
},
  "geometry": {"coordinates":[-84.80100299999999,33.37106],"type":"Point"}
}