{
  "type": "Feature",
  "properties": {
    "addr:full":"189 W Main St Rutledge GA 30663",
    "addr:housenumber":"189",
    "addr:postcode":"30663",
    "addr:street":"W Main St",
    "iso:country":"US",
    "sg:address":"189 W Main St",
    "sg:city":"Rutledge",
    "sg:classifiers":[
        {
            "category":"Building & Trades",
            "subcategory":"Construction",
            "type":"Services"
        }
    ],
    "sg:phone":"+1 706 557 7762",
    "sg:postcode":"30663",
    "sg:province":"GA",
    "sg:tags":[
        "drywall",
        "contractor"
    ],
    "wof:name":"Pierre F Glardon",
    "wof:placetype":"venue"
},
  "geometry": {"coordinates":[-83.61476500000001,33.627973],"type":"Point"}
}