{
  "type": "Feature",
  "properties": {
    "addr:full":"128 Duvall St Ste B Clayton GA 30525",
    "addr:housenumber":"128",
    "addr:postcode":"30525",
    "addr:street":"Duvall St Ste B",
    "iso:country":"US",
    "sg:address":"128 Duvall St Ste B",
    "sg:city":"Clayton",
    "sg:classifiers":[
        {
            "category":"Food & Beverages",
            "subcategory":"Groceries & Convenience Stores",
            "type":"Retail Goods"
        }
    ],
    "sg:phone":"+1 706 782 3189",
    "sg:postcode":"30525",
    "sg:province":"GA",
    "wof:name":"La Jerezana Inc",
    "wof:placetype":"venue"
},
  "geometry": {"coordinates":[-83.40234599999999,34.873712],"type":"Point"}
}