{
  "type": "Feature",
  "properties": {
    "addr:full":"530 Thornton Rd Austell GA 30122",
    "addr:housenumber":"530",
    "addr:postcode":"30122",
    "addr:street":"Thornton Rd",
    "iso:country":"US",
    "sg:address":"530 Thornton Rd",
    "sg:city":"Austell",
    "sg:classifiers":[
        {
            "category":"Restaurant",
            "type":"Food & Drink"
        }
    ],
    "sg:phone":"+1 770 819 0034",
    "sg:postcode":"30122",
    "sg:province":"GA",
    "sg:tags":[
        "out"
    ],
    "wof:name":"Jamaican & Amer Kitchen Take",
    "wof:placetype":"venue"
},
  "geometry": {"coordinates":[-84.629216,33.791584],"type":"Point"}
}