{
  "type": "Feature",
  "properties": {
    "iso:country":"US",
    "sg:address":"161 17th St NE",
    "sg:city":"Atlanta",
    "sg:classifiers":[
        {
            "category":"Professional",
            "subcategory":"Lawyer & Legal Services",
            "type":"Services"
        }
    ],
    "sg:phone":"+1 404 872 6783",
    "sg:postcode":"30309",
    "sg:province":"GA",
    "wof:name":"Hanes Paul L Atty",
    "wof:placetype":"venue"
},
  "geometry": {"coordinates":[-84.379997,33.793201],"type":"Point"}
}