{
  "type": "Feature",
  "properties": {
    "iso:country":"US",
    "sg:address":"1166 Bond St",
    "sg:city":"Macon",
    "sg:classifiers":[
        {
            "category":"Professional",
            "subcategory":"Business Services",
            "type":"Services"
        }
    ],
    "sg:phone":"+1 478 750 7436",
    "sg:postcode":"31201",
    "sg:province":"GA",
    "wof:name":"TP Enterprises",
    "wof:placetype":"venue"
},
  "geometry": {"coordinates":[-83.636205,32.843579],"type":"Point"}
}