{
  "type": "Feature",
  "properties": {
    "addr:full":"2303 S Ravine Way Dalton GA 30720",
    "addr:housenumber":"2303",
    "addr:postcode":"30720",
    "addr:street":"S Ravine Way",
    "iso:country":"US",
    "sg:address":"2303 S Ravine Way",
    "sg:city":"Dalton",
    "sg:classifiers":[
        {
            "category":"Professional",
            "type":"Services"
        }
    ],
    "sg:phone":"+1 706 226 6108",
    "sg:postcode":"30720",
    "sg:province":"GA",
    "wof:name":"Sprague Family LLC",
    "wof:placetype":"venue"
},
  "geometry": {"coordinates":[-85.00828199999999,34.765274],"type":"Point"}
}