{
  "type": "Feature",
  "properties": {
    "iso:country":"US",
    "sg:address":"811 Osborne St",
    "sg:city":"Saint Marys",
    "sg:classifiers":[
        {
            "category":"Professional",
            "subcategory":"Lawyer & Legal Services",
            "type":"Services"
        }
    ],
    "sg:phone":"+1 912 882 3093",
    "sg:postcode":"31558",
    "sg:province":"GA",
    "wof:name":"Stevens Esq",
    "wof:placetype":"venue"
},
  "geometry": {"coordinates":[-81.54603899999999,30.731781],"type":"Point"}
}