{
  "type": "Feature",
  "properties": {
    "addr:full":"1705 Belle Meade Ct Lawrenceville GA 30043",
    "addr:housenumber":"1705",
    "addr:postcode":"30043",
    "addr:street":"Belle Meade Ct",
    "iso:country":"US",
    "sg:address":"1705 Belle Meade Ct",
    "sg:city":"Lawrenceville",
    "sg:classifiers":[
        {
            "category":"Manufacturing",
            "subcategory":"Tools & Machinery",
            "type":"Manufacturing & Wholesale Goods"
        },
        {
            "category":"Wholesale",
            "subcategory":"Machinery & Supplies",
            "type":"Manufacturing & Wholesale Goods"
        }
    ],
    "sg:phone":"+1 770 339 2888",
    "sg:postcode":"30043",
    "sg:province":"GA",
    "sg:tags":[
        "control",
        "flood",
        "pump",
        "equipment"
    ],
    "wof:name":"W E Marshall Company",
    "wof:placetype":"venue"
},
  "geometry": {"coordinates":[-84.055228,33.960796],"type":"Point"}
}