{
  "type": "Feature",
  "properties": {
    "iso:country":"US",
    "sg:address":"1841 Mountain Industrial Blvd",
    "sg:city":"Tucker",
    "sg:classifiers":[
        {
            "category":"Building & Trades",
            "subcategory":"Construction",
            "type":"Services"
        }
    ],
    "sg:phone":"+1 770 938 0541",
    "sg:postcode":"30084",
    "sg:province":"GA",
    "sg:tags":[
        "planning",
        "remodeling",
        "kitchen"
    ],
    "wof:name":"Howdens Millwork",
    "wof:placetype":"venue"
},
  "geometry": {"coordinates":[-84.200698,33.837062],"type":"Point"}
}