{
  "type": "Feature",
  "properties": {
    "iso:country":"US",
    "sg:address":"310 Warren Dr",
    "sg:city":"Sylvester",
    "sg:classifiers":[
        {
            "category":"Place Of Worship",
            "subcategory":"Church",
            "type":"Public Place"
        },
        {
            "category":"Place Of Worship",
            "type":"Public Place"
        }
    ],
    "sg:phone":"+1 229 777 0292",
    "sg:postcode":"31791",
    "sg:province":"GA",
    "sg:tags":[
        "churches-baptist-general",
        "churches-baptist"
    ],
    "wof:name":"Victory Independent Baptist Church",
    "wof:placetype":"venue"
},
  "geometry": {"coordinates":[-83.841116,31.542514],"type":"Point"}
}