{
  "type": "Feature",
  "properties": {
    "addr:full":"7 Dawne Dr Statesboro GA 30458",
    "addr:housenumber":"7",
    "addr:postcode":"30458",
    "addr:street":"Dawne Dr",
    "iso:country":"US",
    "sg:address":"7 Dawne Dr",
    "sg:city":"Statesboro",
    "sg:classifiers":[
        {
            "category":"Building & Trades",
            "subcategory":"Construction",
            "type":"Services"
        }
    ],
    "sg:phone":"+1 912 852 5167",
    "sg:postcode":"30458",
    "sg:province":"GA",
    "sg:tags":[
        "house"
    ],
    "wof:name":"Kitt Construction",
    "wof:placetype":"venue"
},
  "geometry": {"coordinates":[-81.84371299999999,32.441807],"type":"Point"}
}