{
  "type": "Feature",
  "properties": {
    "addr:full":"2385 Satellite Blvd Duluth GA 30096",
    "addr:housenumber":"2385",
    "addr:postcode":"30096",
    "addr:street":"Satellite Blvd",
    "iso:country":"US",
    "sg:address":"2385 Satellite Blvd",
    "sg:city":"Duluth",
    "sg:classifiers":[
        {
            "category":"Insurance",
            "subcategory":"Hazard Insurance",
            "type":"Services"
        },
        {
            "category":"Insurance",
            "subcategory":"Life Insurance",
            "type":"Services"
        },
        {
            "category":"Banks & Credit Unions",
            "subcategory":"Financial Services",
            "type":"Services"
        }
    ],
    "sg:phone":"+1 678 775 3008",
    "sg:postcode":"30096",
    "sg:province":"GA",
    "sg:tags":[
        "annuity",
        "retirement",
        "plan"
    ],
    "wof:name":"Hannah, John",
    "wof:placetype":"venue"
},
  "geometry": {"coordinates":[-84.09378700000001,33.97481],"type":"Point"}
}