{
  "type": "Feature",
  "properties": {
    "addr:full":"542 Fortune Ridge Rd Stone Mountain GA 30087",
    "addr:housenumber":"542",
    "addr:postcode":"30087",
    "addr:street":"Fortune Ridge Rd",
    "iso:country":"US",
    "sg:address":"542 Fortune Ridge Rd",
    "sg:city":"Stone Mountain",
    "sg:classifiers":[
        {
            "category":"Personal",
            "subcategory":"Beauty Salon",
            "type":"Services"
        }
    ],
    "sg:phone":"+1 770 469 9500",
    "sg:postcode":"30087",
    "sg:province":"GA",
    "wof:name":"Stylistics Hair Salon",
    "wof:placetype":"venue"
},
  "geometry": {"coordinates":[-84.106005,33.779845],"type":"Point"}
}