{
  "type": "Feature",
  "properties": {
    "addr:full":"6467 Wright Cir NE Atlanta GA 30328",
    "addr:housenumber":"6467",
    "addr:postcode":"30328",
    "addr:street":"Wright Cir Ne",
    "iso:country":"US",
    "sg:address":"6467 Wright Cir NE",
    "sg:city":"Atlanta",
    "sg:classifiers":[
        {
            "category":"Banks & Credit Unions",
            "subcategory":"Investment Brokerage",
            "type":"Services"
        }
    ],
    "sg:phone":"+1 770 963 0221",
    "sg:postcode":"30328",
    "sg:province":"GA",
    "sg:tags":[
        "consultant",
        "planning",
        "financial"
    ],
    "wof:name":"Planning Concepts",
    "wof:placetype":"venue"
},
  "geometry": {"coordinates":[-84.38418299999999,33.932484],"type":"Point"}
}