{
  "type": "Feature",
  "properties": {
    "addr:full":"5560 Williams Shores Dr Cumming GA 30041",
    "addr:housenumber":"5560",
    "addr:postcode":"30041",
    "addr:street":"Williams Shores Dr",
    "iso:country":"US",
    "sg:address":"5560 Williams Shores Dr",
    "sg:city":"Cumming",
    "sg:classifiers":[
        {
            "category":"Professional",
            "subcategory":"Computer Services",
            "type":"Services"
        }
    ],
    "sg:phone":"+1 770 887 8881",
    "sg:postcode":"30041",
    "sg:province":"GA",
    "sg:tags":[
        "prepackaged",
        "software"
    ],
    "wof:name":"Xign Corporation",
    "wof:placetype":"venue"
},
  "geometry": {"coordinates":[-84.066998,34.189218],"type":"Point"}
}