{
  "type": "Feature",
  "properties": {
    "iso:country":"US",
    "sg:address":"6823 New Jesup Hwy",
    "sg:city":"Brunswick",
    "sg:classifiers":[
        {
            "category":"Real Estate",
            "subcategory":"Real Estate Services",
            "type":"Services"
        },
        {
            "category":"Real Estate",
            "subcategory":"Real Estate Agent",
            "type":"Services"
        }
    ],
    "sg:phone":"+1 912 264 4277",
    "sg:postcode":"31523",
    "sg:province":"GA",
    "sg:tags":[
        "vacancy",
        "management",
        "rental",
        "listing"
    ],
    "wof:name":"F R Landon Inc",
    "wof:placetype":"venue"
},
  "geometry": {"coordinates":[-81.55990300000001,31.265405],"type":"Point"}
}