{
  "type": "Feature",
  "properties": {
    "iso:country":"US",
    "sg:address":"206 W Broad St",
    "sg:city":"Sparta",
    "sg:classifiers":[
        {
            "category":"Personal",
            "subcategory":"Beauty Salon",
            "type":"Services"
        }
    ],
    "sg:phone":"+1 706 444 9988",
    "sg:postcode":"31087",
    "sg:province":"GA",
    "wof:name":"Perfect 10",
    "wof:placetype":"venue"
},
  "geometry": {"coordinates":[-82.978599,33.275005],"type":"Point"}
}