{
  "type": "Feature",
  "properties": {
    "iso:country":"US",
    "sg:address":"1114 Brookhaven Commons Dr NE",
    "sg:city":"Atlanta",
    "sg:classifiers":[
        {
            "category":"Building & Trades",
            "subcategory":"Construction",
            "type":"Services"
        }
    ],
    "sg:phone":"+1 404 467 0288",
    "sg:postcode":"30319",
    "sg:province":"GA",
    "sg:tags":[
        "general",
        "contractor"
    ],
    "wof:name":"Pleasants Industries",
    "wof:placetype":"venue"
},
  "geometry": {"coordinates":[-84.34197,33.868384],"type":"Point"}
}