{
  "type": "Feature",
  "properties": {
    "iso:country":"US",
    "sg:address":"3647 Creekstone Dr",
    "sg:city":"Norcross",
    "sg:classifiers":[
        {
            "category":"Communications",
            "type":"Services"
        }
    ],
    "sg:phone":"+1 770 449 3233",
    "sg:postcode":"30092",
    "sg:province":"GA",
    "sg:tags":[
        "web",
        "design"
    ],
    "wof:name":"Mindwhirl",
    "wof:placetype":"venue"
},
  "geometry": {"coordinates":[-84.23519899999999,33.964001],"type":"Point"}
}