{
  "type": "Feature",
  "properties": {
    "addr:full":"76 April Ave Stockbridge GA 30281",
    "addr:housenumber":"76",
    "addr:postcode":"30281",
    "addr:street":"April Ave",
    "iso:country":"US",
    "sg:address":"76 April Ave",
    "sg:city":"Stockbridge",
    "sg:classifiers":[
        {
            "category":"Building & Trades",
            "subcategory":"Construction",
            "type":"Services"
        }
    ],
    "sg:phone":"+1 770 351 6602",
    "sg:postcode":"30281",
    "sg:province":"GA",
    "sg:tags":[
        "home",
        "improvement"
    ],
    "wof:name":"Affordable Home Improvement",
    "wof:placetype":"venue"
},
  "geometry": {"coordinates":[-84.24924,33.504974],"type":"Point"}
}