{
  "type": "Feature",
  "properties": {
    "addr:full":"11877 Douglas Rd Alpharetta GA 30005",
    "addr:housenumber":"11877",
    "addr:postcode":"30005",
    "addr:street":"Douglas Rd",
    "iso:country":"US",
    "sg:address":"11877 Douglas Rd",
    "sg:city":"Alpharetta",
    "sg:classifiers":[
        {
            "category":"Recreation",
            "type":"Entertainment"
        }
    ],
    "sg:phone":"+1 678 867 2277",
    "sg:postcode":"30005",
    "sg:province":"GA",
    "sg:tags":[
        "martial",
        "arts",
        "instruction"
    ],
    "wof:name":"Tae KWON Do Academy",
    "wof:placetype":"venue"
},
  "geometry": {"coordinates":[-84.205862,34.072361],"type":"Point"}
}