{
  "type": "Feature",
  "properties": {
    "iso:country":"US",
    "sg:address":"3475 Holcomb Bridge Rd",
    "sg:city":"Norcross",
    "sg:classifiers":[
        {
            "category":"Personal",
            "type":"Services"
        }
    ],
    "sg:phone":"+1 770 417 5040",
    "sg:postcode":"30092",
    "sg:province":"GA",
    "sg:tags":[
        "therapist",
        "massage"
    ],
    "wof:name":"Heavenly Touch Wellness Ctr",
    "wof:placetype":"venue"
},
  "geometry": {"coordinates":[-84.24403599999999,33.954296],"type":"Point"}
}