{
  "type": "Feature",
  "properties": {
    "iso:country":"US",
    "sg:address":"1610 Sigman Rd NW",
    "sg:city":"Conyers",
    "sg:classifiers":[
        {
            "category":"Retail",
            "subcategory":"Auto Repair",
            "type":"Services"
        }
    ],
    "sg:phone":"+1 770 761 4546",
    "sg:postcode":"30012",
    "sg:province":"GA",
    "wof:name":"Master Tech Automotive",
    "wof:placetype":"venue"
},
  "geometry": {"coordinates":[-84.03830000000001,33.686401],"type":"Point"}
}