{
  "type": "Feature",
  "properties": {
    "iso:country":"US",
    "sg:address":"145 Sandy Springs Dr",
    "sg:city":"Athens",
    "sg:classifiers":[
        {
            "category":"Retail",
            "subcategory":"Animal Services",
            "type":"Services"
        }
    ],
    "sg:phone":"+1 706 354 8944",
    "sg:postcode":"30601",
    "sg:province":"GA",
    "sg:tags":[
        "pet",
        "boarding",
        "sitting"
    ],
    "wof:name":"Pets' Retreat",
    "wof:placetype":"venue"
},
  "geometry": {"coordinates":[-83.35836500000001,34.03374],"type":"Point"}
}