{
  "type": "Feature",
  "properties": {
    "addr:full":"3625 Dallas Hwy Marietta GA 30064",
    "addr:housenumber":"3625",
    "addr:postcode":"30064",
    "addr:street":"Dallas Hwy",
    "iso:country":"US",
    "sg:address":"3625 Dallas Hwy",
    "sg:city":"Marietta",
    "sg:classifiers":[
        {
            "category":"Restaurant",
            "type":"Food & Drink"
        }
    ],
    "sg:phone":"+1 770 419 8808",
    "sg:postcode":"30064",
    "sg:province":"GA",
    "sg:tags":[
        "fusion",
        "asian"
    ],
    "sg:website":"www.zyngatlanta.com",
    "wof:name":"Zyng Asian Grill",
    "wof:placetype":"venue"
},
  "geometry": {"coordinates":[-84.658181,33.953392],"type":"Point"}
}