{
  "type": "Feature",
  "properties": {
    "addr:full":"305 Waldron Rd Douglas GA 31535",
    "addr:housenumber":"305",
    "addr:postcode":"31535",
    "addr:street":"Waldron Rd",
    "iso:country":"US",
    "sg:address":"305 Waldron Rd",
    "sg:city":"Douglas",
    "sg:classifiers":[
        {
            "category":"Farming",
            "subcategory":"Poultry Farm",
            "type":"Manufacturing & Wholesale Goods"
        }
    ],
    "sg:phone":"+1 912 384 7226",
    "sg:postcode":"31535",
    "sg:province":"GA",
    "sg:tags":[
        "chicken",
        "egg"
    ],
    "wof:name":"Ed T Cor Inc",
    "wof:placetype":"venue"
},
  "geometry": {"coordinates":[-82.81675199999999,31.421547],"type":"Point"}
}