{
  "type": "Feature",
  "properties": {
    "addr:full":"1142 Dawson Rd Albany GA 31707",
    "addr:housenumber":"1142",
    "addr:postcode":"31707",
    "addr:street":"Dawson Rd",
    "iso:country":"US",
    "sg:address":"1142 Dawson Rd",
    "sg:city":"Albany",
    "sg:classifiers":[
        {
            "category":"Professional",
            "subcategory":"Management & Consulting",
            "type":"Services"
        }
    ],
    "sg:phone":"+1 229 420 9399",
    "sg:postcode":"31707",
    "sg:province":"GA",
    "sg:tags":[
        "insurance"
    ],
    "wof:name":"Axa Advisors",
    "wof:placetype":"venue"
},
  "geometry": {"coordinates":[-84.17627400000001,31.581591],"type":"Point"}
}