{
  "type": "Feature",
  "properties": {
    "iso:country":"US",
    "sg:address":"232 Beulah Church Rd",
    "sg:city":"Carrollton",
    "sg:classifiers":[
        {
            "category":"Manufacturing",
            "subcategory":"Food",
            "type":"Manufacturing & Wholesale Goods"
        }
    ],
    "sg:phone":"+1 770 214 1351",
    "sg:postcode":"30117",
    "sg:province":"GA",
    "sg:tags":[
        "manufacture",
        "syrup"
    ],
    "wof:name":"Cocoasyrupcom Inc",
    "wof:placetype":"venue"
},
  "geometry": {"coordinates":[-85.09789499999999,33.600711],"type":"Point"}
}