{
  "type": "Feature",
  "properties": {
    "iso:country":"US",
    "sg:address":"590 W Crossville Rd Ste 201",
    "sg:city":"Roswell",
    "sg:classifiers":[
        {
            "category":"Professional",
            "subcategory":"Computer Services",
            "type":"Services"
        }
    ],
    "sg:phone":"+1 678 323 5000",
    "sg:postcode":"30075",
    "sg:province":"GA",
    "sg:tags":[
        "repair"
    ],
    "sg:website":"www.comnexia.com",
    "wof:name":"Comnexia",
    "wof:placetype":"venue"
},
  "geometry": {"coordinates":[-84.377602,34.055401],"type":"Point"}
}