{
  "type": "Feature",
  "properties": {
    "iso:country":"US",
    "sg:address":"3046 Spring Hill Pkwy SE",
    "sg:city":"Smyrna",
    "sg:classifiers":[
        {
            "category":"Building & Trades",
            "subcategory":"Cleaning & Sanitation",
            "type":"Services"
        }
    ],
    "sg:phone":"+1 770 432 2830",
    "sg:postcode":"30080",
    "sg:province":"GA",
    "sg:tags":[
        "janitor"
    ],
    "wof:name":"Atlanta Cleaning Svc",
    "wof:placetype":"venue"
},
  "geometry": {"coordinates":[-84.475528,33.87616],"type":"Point"}
}