{
  "type": "Feature",
  "properties": {
    "iso:country":"US",
    "sg:address":"86 Upper Riverdale Rd SW",
    "sg:city":"Riverdale",
    "sg:classifiers":[
        {
            "category":"Health Services",
            "subcategory":"Optometrist",
            "type":"Services"
        }
    ],
    "sg:phone":"+1 770 996 4844",
    "sg:postcode":"30274",
    "sg:province":"GA",
    "sg:tags":[
        "ophthalmologist"
    ],
    "wof:name":"Akstein Ricardo B MD Facs",
    "wof:placetype":"venue"
},
  "geometry": {"coordinates":[-84.39299,33.57677],"type":"Point"}
}