{
  "type": "Feature",
  "properties": {
    "iso:country":"US",
    "sg:address":"2000 Dogwood Dr SE",
    "sg:city":"Conyers",
    "sg:classifiers":[
        {
            "category":"Manufacturing",
            "subcategory":"Paper Products",
            "type":"Manufacturing & Wholesale Goods"
        }
    ],
    "sg:phone":"+1 770 918 6130",
    "sg:postcode":"30013",
    "sg:province":"GA",
    "sg:tags":[
        "paper-wholesale",
        "manufacturer"
    ],
    "wof:name":"Stellar Distribution",
    "wof:placetype":"venue"
},
  "geometry": {"coordinates":[-83.979653,33.637256],"type":"Point"}
}