{
  "type": "Feature",
  "properties": {
    "addr:full":"2520 Delk Rd SE Marietta GA 30067",
    "addr:housenumber":"2520",
    "addr:postcode":"30067",
    "addr:street":"Delk Rd Se",
    "iso:country":"US",
    "sg:address":"2520 Delk Rd SE",
    "sg:city":"Marietta",
    "sg:classifiers":[
        {
            "category":"Restaurant",
            "type":"Food & Drink"
        }
    ],
    "sg:menulink":"http://www.allmenus.com/ga/marietta/154436-hardees/menu/",
    "sg:phone":"+1 770 951 2102",
    "sg:postcode":"30067",
    "sg:province":"GA",
    "sg:tags":[
        "burger",
        "american"
    ],
    "wof:name":"Hardee's",
    "wof:placetype":"venue"
},
  "geometry": {"coordinates":[-84.481081,33.922653],"type":"Point"}
}