{
  "type": "Feature",
  "properties": {
    "addr:full":"804 Overlook Ter Atlanta GA 30349",
    "addr:housenumber":"804",
    "addr:postcode":"30349",
    "addr:street":"Overlook Ter",
    "iso:country":"US",
    "sg:address":"804 Overlook Ter",
    "sg:city":"Atlanta",
    "sg:classifiers":[
        {
            "category":"Personal",
            "type":"Services"
        }
    ],
    "sg:phone":"+1 404 969 7675",
    "sg:postcode":"30349",
    "sg:province":"GA",
    "sg:tags":[
        "planning",
        "event"
    ],
    "wof:name":"Fyne Inc",
    "wof:placetype":"venue"
},
  "geometry": {"coordinates":[-84.415532,33.588348],"type":"Point"}
}