{
  "type": "Feature",
  "properties": {
    "addr:full":"130 John Frank Ward Blvd McDonough GA 30253",
    "addr:housenumber":"130",
    "addr:postcode":"30253",
    "addr:street":"John Frank Ward Blvd",
    "iso:country":"US",
    "sg:address":"130 John Frank Ward Blvd",
    "sg:city":"McDonough",
    "sg:classifiers":[
        {
            "category":"Health Services",
            "subcategory":"Chiropractor",
            "type":"Services"
        }
    ],
    "sg:phone":"+1 770 957 4165",
    "sg:postcode":"30253",
    "sg:province":"GA",
    "wof:name":"Spine Care Chiropractic Center",
    "wof:placetype":"venue"
},
  "geometry": {"coordinates":[-84.144096,33.446999],"type":"Point"}
}