{
  "type": "Feature",
  "properties": {
    "addr:full":"3805 Canton Pl NW Kennesaw GA 30144",
    "addr:housenumber":"3805",
    "addr:postcode":"30144",
    "addr:street":"Canton Pl Nw",
    "iso:country":"US",
    "sg:address":"3805 Canton Pl NW",
    "sg:city":"Kennesaw",
    "sg:classifiers":[
        {
            "category":"Social Services",
            "subcategory":"Retirement Home",
            "type":"Services"
        }
    ],
    "sg:phone":"+1 770 426 0668",
    "sg:postcode":"30144",
    "sg:province":"GA",
    "sg:tags":[
        "rooming",
        "house"
    ],
    "wof:name":"University Village",
    "wof:placetype":"venue"
},
  "geometry": {"coordinates":[-84.58427,34.041814],"type":"Point"}
}