{
  "type": "Feature",
  "properties": {
    "addr:full":"200 W Wieuca Rd NE Atlanta GA 30342",
    "addr:housenumber":"200",
    "addr:postcode":"30342",
    "addr:street":"W Wieuca Rd Ne",
    "iso:country":"US",
    "sg:address":"200 W Wieuca Rd NE",
    "sg:city":"Atlanta",
    "sg:phone":"+1 404 266 3678",
    "sg:postcode":"30342",
    "sg:province":"GA",
    "wof:name":"Avril's Car Wash & Detailing",
    "wof:placetype":"venue"
},
  "geometry": {"coordinates":[-84.379929,33.876862],"type":"Point"}
}