{
  "type": "Feature",
  "properties": {
    "iso:country":"US",
    "sg:address":"3787 Main Street",
    "sg:city":"Atlanta",
    "sg:classifiers":[
        {
            "category":"Shopping",
            "subcategory":"Shoes",
            "type":"Retail Goods"
        }
    ],
    "sg:phone":"+1 404 766 1254",
    "sg:postcode":"30337",
    "sg:province":"GA",
    "sg:tags":[
        "store"
    ],
    "wof:name":"College Park Shoes",
    "wof:placetype":"venue"
},
  "geometry": {"coordinates":[-84.449476,33.651428],"type":"Point"}
}