{
  "type": "Feature",
  "properties": {
    "iso:country":"US",
    "sg:address":"3417 Tuxedo Rd NW",
    "sg:city":"Atlanta",
    "sg:classifiers":[
        {
            "category":"Banks & Credit Unions",
            "subcategory":"Financial Services",
            "type":"Services"
        }
    ],
    "sg:phone":"+1 404 237 8502",
    "sg:postcode":"30305",
    "sg:province":"GA",
    "sg:tags":[
        "trust",
        "nonprofit",
        "management"
    ],
    "wof:name":"The Blonder Family Foundation Inc",
    "wof:placetype":"venue"
},
  "geometry": {"coordinates":[-84.405587,33.848802],"type":"Point"}
}