{
  "type": "Feature",
  "properties": {
    "addr:full":"120 Shell Dr Brunswick GA 31520",
    "addr:housenumber":"120",
    "addr:postcode":"31520",
    "addr:street":"Shell Dr",
    "iso:country":"US",
    "sg:address":"120 Shell Dr",
    "sg:city":"Brunswick",
    "sg:classifiers":[
        {
            "category":"Wholesale",
            "subcategory":"Groceries",
            "type":"Manufacturing & Wholesale Goods"
        }
    ],
    "sg:phone":"+1 912 265 9305",
    "sg:postcode":"31520",
    "sg:province":"GA",
    "sg:tags":[
        "food",
        "snack"
    ],
    "wof:name":"Frito-Lay",
    "wof:placetype":"venue"
},
  "geometry": {"coordinates":[-81.494557,31.200946],"type":"Point"}
}