{
  "type": "Feature",
  "properties": {
    "addr:full":"407 Jennifer Ct Dalton GA 30721",
    "addr:housenumber":"407",
    "addr:postcode":"30721",
    "addr:street":"Jennifer Ct",
    "iso:country":"US",
    "sg:address":"407 Jennifer Ct",
    "sg:city":"Dalton",
    "sg:classifiers":[
        {
            "category":"Shopping",
            "subcategory":"Gifts & Souvenirs",
            "type":"Retail Goods"
        }
    ],
    "sg:phone":"+1 706 277 5058",
    "sg:postcode":"30721",
    "sg:province":"GA",
    "wof:name":"Michael Babb",
    "wof:placetype":"venue"
},
  "geometry": {"coordinates":[-84.960093,34.71875],"type":"Point"}
}