{
  "type": "Feature",
  "properties": {
    "iso:country":"US",
    "sg:address":"300 Johnson Ferry Rd NE",
    "sg:city":"Atlanta",
    "sg:classifiers":[
        {
            "category":"Manufacturing",
            "subcategory":"Wood Products",
            "type":"Manufacturing & Wholesale Goods"
        },
        {
            "category":"Manufacturing",
            "subcategory":"Furniture",
            "type":"Manufacturing & Wholesale Goods"
        }
    ],
    "sg:phone":"+1 404 843 2261",
    "sg:postcode":"30328",
    "sg:province":"GA",
    "sg:tags":[
        "woodworking",
        "builder",
        "designer",
        "custom"
    ],
    "wof:name":"James Keith",
    "wof:placetype":"venue"
},
  "geometry": {"coordinates":[-84.377831,33.924629],"type":"Point"}
}