{
  "type": "Feature",
  "properties": {
    "iso:country":"US",
    "sg:address":"3700 Atlanta Hwy",
    "sg:city":"Athens",
    "sg:classifiers":[
        {
            "category":"Shopping",
            "subcategory":"Gifts & Souvenirs",
            "type":"Retail Goods"
        }
    ],
    "sg:phone":"+1 706 549 9293",
    "sg:postcode":"30606",
    "sg:province":"GA",
    "sg:tags":[
        "shop"
    ],
    "wof:name":"Briar Patch",
    "wof:placetype":"venue"
},
  "geometry": {"coordinates":[-83.466112,33.940778],"type":"Point"}
}