{
  "type": "Feature",
  "properties": {
    "iso:country":"US",
    "sg:address":"603 Hurt Rd SW",
    "sg:city":"Smyrna",
    "sg:classifiers":[
        {
            "category":"Professional",
            "subcategory":"Business Services",
            "type":"Services"
        }
    ],
    "sg:phone":"+1 770 444 9012",
    "sg:postcode":"30082",
    "sg:province":"GA",
    "wof:name":"Primary Orange",
    "wof:placetype":"venue"
},
  "geometry": {"coordinates":[-84.569121,33.864449],"type":"Point"}
}