{
  "type": "Feature",
  "properties": {
    "addr:full":"3380 Tanglewood Dr Augusta GA 30909",
    "addr:housenumber":"3380",
    "addr:postcode":"30909",
    "addr:street":"Tanglewood Dr",
    "iso:country":"US",
    "sg:address":"3380 Tanglewood Dr",
    "sg:city":"Augusta",
    "sg:classifiers":[
        {
            "category":"Professional",
            "subcategory":"Detective & Security Services",
            "type":"Services"
        }
    ],
    "sg:phone":"+1 706 589 5987",
    "sg:postcode":"30909",
    "sg:province":"GA",
    "sg:tags":[
        "guard",
        "patrol"
    ],
    "wof:name":"Jag Detective & Security",
    "wof:placetype":"venue"
},
  "geometry": {"coordinates":[-82.08197,33.474541],"type":"Point"}
}