{
  "type": "Feature",
  "properties": {
    "iso:country":"US",
    "sg:address":"1016 White Cir",
    "sg:city":"Hinesville",
    "sg:classifiers":[
        {
            "category":"Retail",
            "subcategory":"Auto Repair",
            "type":"Services"
        }
    ],
    "sg:phone":"+1 912 368 9116",
    "sg:postcode":"31313",
    "sg:province":"GA",
    "sg:tags":[
        "shop",
        "automotive",
        "general"
    ],
    "wof:name":"D and D Mobile",
    "wof:placetype":"venue"
},
  "geometry": {"coordinates":[-81.615019,31.821983],"type":"Point"}
}