{
  "type": "Feature",
  "properties": {
    "iso:country":"US",
    "sg:address":"2903 2nd Ave",
    "sg:city":"Columbus",
    "sg:classifiers":[
        {
            "category":"Shopping",
            "subcategory":"Used Merchandise",
            "type":"Retail Goods"
        }
    ],
    "sg:phone":"+1 706 322 1562",
    "sg:postcode":"31904",
    "sg:province":"GA",
    "sg:tags":[
        "shop",
        "thrift"
    ],
    "wof:name":"Valley Rescue Mission Inc",
    "wof:placetype":"venue"
},
  "geometry": {"coordinates":[-84.99019699999999,32.491681],"type":"Point"}
}