{
  "type": "Feature",
  "properties": {
    "addr:full":"206 Norris Cir Tunnel Hill GA 30755",
    "addr:housenumber":"206",
    "addr:postcode":"30755",
    "addr:street":"Norris Cir Tunnel Hill",
    "iso:country":"US",
    "sg:address":"206 Norris Cir",
    "sg:city":"Tunnel Hill",
    "sg:classifiers":[
        {
            "category":"Building & Trades",
            "subcategory":"Construction",
            "type":"Services"
        }
    ],
    "sg:phone":"+1 706 673 2253",
    "sg:postcode":"30755",
    "sg:province":"GA",
    "sg:tags":[
        "house"
    ],
    "wof:name":"Kerry Ridley Construction Co",
    "wof:placetype":"venue"
},
  "geometry": {"coordinates":[-85.04848200000001,34.856949],"type":"Point"}
}