{
  "type": "Feature",
  "properties": {
    "addr:full":"182 Bennie West Rd Waverly GA 31565",
    "addr:housenumber":"182",
    "addr:postcode":"31565",
    "addr:street":"Bennie West Rd",
    "iso:country":"US",
    "sg:address":"182 Bennie West Rd",
    "sg:city":"Waverly",
    "sg:classifiers":[
        {
            "category":"Manufacturing",
            "subcategory":"Signs",
            "type":"Manufacturing & Wholesale Goods"
        }
    ],
    "sg:phone":"+1 912 267 9801",
    "sg:postcode":"31565",
    "sg:province":"GA",
    "sg:tags":[
        "specialty",
        "mfg"
    ],
    "wof:name":"Signs Unlimited",
    "wof:placetype":"venue"
},
  "geometry": {"coordinates":[-81.61640300000001,31.096528],"type":"Point"}
}