{
  "type": "Feature",
  "properties": {
    "addr:full":"3035 Lexington Rd Athens GA 30605",
    "addr:housenumber":"3035",
    "addr:postcode":"30605",
    "addr:street":"Lexington Rd",
    "iso:country":"US",
    "sg:address":"3035 Lexington Rd",
    "sg:city":"Athens",
    "sg:classifiers":[
        {
            "category":"Shopping",
            "subcategory":"Pharmacy",
            "type":"Retail Goods"
        }
    ],
    "sg:phone":"+1 706 549 0605",
    "sg:postcode":"30605",
    "sg:province":"GA",
    "wof:name":"Metro Drug Squad",
    "wof:placetype":"venue"
},
  "geometry": {"coordinates":[-83.32656299999999,33.941062],"type":"Point"}
}