{
  "type": "Feature",
  "properties": {
    "iso:country":"US",
    "sg:address":"3104 Vineville Ave",
    "sg:city":"Macon",
    "sg:classifiers":[
        {
            "category":"Professional",
            "subcategory":"Computer Services",
            "type":"Services"
        }
    ],
    "sg:phone":"+1 478 741 5515",
    "sg:postcode":"31210",
    "sg:province":"GA",
    "sg:tags":[
        "custom-dog-shirts--custom-dog-t-shirts--personalized-dog-t-shirts--personalized-dog-bandanas--personalized-dog-tee-shirts--make-your-own-dog-t-shirts--custom-pet-shirts--create-a-dog-tee-shirt--custom-dog-bandanas"
    ],
    "sg:website":"http://www.designadoggietee.com",
    "wof:name":"DoggieInk",
    "wof:placetype":"venue"
},
  "geometry": {"coordinates":[-83.690005,32.86345],"type":"Point"}
}