{
  "type": "Feature",
  "properties": {
    "iso:country":"US",
    "sg:address":"139 Park Dr",
    "sg:city":"Forsyth",
    "sg:classifiers":[
        {
            "category":"Building & Trades",
            "subcategory":"Plumbing",
            "type":"Services"
        }
    ],
    "sg:phone":"+1 478 994 2027",
    "sg:postcode":"31029",
    "sg:province":"GA",
    "sg:tags":[
        "plumbing",
        "contractor"
    ],
    "wof:name":"Davis Plumbing Of Forsyth",
    "wof:placetype":"venue"
},
  "geometry": {"coordinates":[-83.96326000000001,33.036342],"type":"Point"}
}