{
  "type": "Feature",
  "properties": {
    "iso:country":"US",
    "sg:address":"2145 Versailles Pl NE",
    "sg:city":"Lawrenceville",
    "sg:classifiers":[
        {
            "category":"Building & Trades",
            "subcategory":"Construction",
            "type":"Services"
        }
    ],
    "sg:phone":"+1 770 995 9979",
    "sg:postcode":"30043",
    "sg:province":"GA",
    "sg:tags":[
        "general",
        "contractor"
    ],
    "wof:name":"James H Stanley Home Builders",
    "wof:placetype":"venue"
},
  "geometry": {"coordinates":[-83.935112,34.023025],"type":"Point"}
}