{
  "type": "Feature",
  "properties": {
    "iso:country":"US",
    "sg:address":"4420 Waynesboro Hwy",
    "sg:city":"Sylvania",
    "sg:classifiers":[
        {
            "category":"Farming",
            "subcategory":"Farm",
            "type":"Manufacturing & Wholesale Goods"
        }
    ],
    "sg:phone":"+1 912 829 4722",
    "sg:postcode":"30467",
    "sg:province":"GA",
    "sg:tags":[
        "crop",
        "general"
    ],
    "wof:name":"Joe Thompson",
    "wof:placetype":"venue"
},
  "geometry": {"coordinates":[-81.708646,32.929891],"type":"Point"}
}