{
  "type": "Feature",
  "properties": {
    "iso:country":"US",
    "sg:address":"420 Shannon Dr",
    "sg:city":"East Dublin",
    "sg:classifiers":[
        {
            "category":"Retail",
            "subcategory":"Auto Repair",
            "type":"Services"
        }
    ],
    "sg:phone":"+1 478 275 0008",
    "sg:postcode":"31027",
    "sg:province":"GA",
    "sg:tags":[
        "repairing",
        "automobile"
    ],
    "wof:name":"Oliver's Auto Pepair",
    "wof:placetype":"venue"
},
  "geometry": {"coordinates":[-82.86295699999999,32.586329],"type":"Point"}
}