{
  "type": "Feature",
  "properties": {
    "addr:full":"118 Industrial Blvd Blue Ridge GA 30513",
    "addr:housenumber":"118",
    "addr:postcode":"30513",
    "addr:street":"Industrial Blvd",
    "iso:country":"US",
    "sg:address":"118 Industrial Blvd",
    "sg:city":"Blue Ridge",
    "sg:classifiers":[
        {
            "category":"Manufacturing",
            "subcategory":"Metals",
            "type":"Manufacturing & Wholesale Goods"
        }
    ],
    "sg:phone":"+1 706 258 3511",
    "sg:postcode":"30513",
    "sg:province":"GA",
    "sg:tags":[
        "product",
        "wire",
        "fabricated",
        "mfg"
    ],
    "wof:name":"Whitepath Fab Tech Inc",
    "wof:placetype":"venue"
},
  "geometry": {"coordinates":[-84.32302199999999,34.855047],"type":"Point"}
}