{
  "type": "Feature",
  "properties": {
    "addr:full":"7183 Jonesboro Rd Morrow GA 30260",
    "addr:housenumber":"7183",
    "addr:postcode":"30260",
    "addr:street":"Jonesboro Rd",
    "iso:country":"US",
    "sg:address":"7183 Jonesboro Rd",
    "sg:city":"Morrow",
    "sg:classifiers":[
        {
            "category":"Professional",
            "subcategory":"Management & Consulting",
            "type":"Services"
        },
        {
            "category":"Professional",
            "subcategory":"Advertising",
            "type":"Services"
        }
    ],
    "sg:phone":"+1 770 461 3249",
    "sg:postcode":"30260",
    "sg:province":"GA",
    "sg:tags":[
        "marketing",
        "program",
        "consultant"
    ],
    "wof:name":"Royce & Forbes Ipc Inc",
    "wof:placetype":"venue"
},
  "geometry": {"coordinates":[-84.34612799999999,33.557708],"type":"Point"}
}