{
  "type": "Feature",
  "properties": {
    "addr:full":"2301 W Savannah Ave Valdosta GA 31601",
    "addr:housenumber":"2301",
    "addr:postcode":"31601",
    "addr:street":"W Savannah Ave",
    "iso:country":"US",
    "sg:address":"2301 W Savannah Ave",
    "sg:city":"Valdosta",
    "sg:classifiers":[
        {
            "category":"Home & Garden",
            "subcategory":"Building Materials",
            "type":"Retail Goods"
        }
    ],
    "sg:phone":"+1 229 249 9548",
    "sg:postcode":"31601",
    "sg:province":"GA",
    "wof:name":"Discount Home Supply",
    "wof:placetype":"venue"
},
  "geometry": {"coordinates":[-83.312307,30.816278],"type":"Point"}
}