{
  "type": "Feature",
  "properties": {
    "iso:country":"US",
    "sg:address":"648 S Harris St",
    "sg:city":"Sandersville",
    "sg:classifiers":[
        {
            "category":"Food & Beverages",
            "subcategory":"Groceries & Convenience Stores",
            "type":"Retail Goods"
        }
    ],
    "sg:phone":"+1 478 552 7174",
    "sg:postcode":"31082",
    "sg:province":"GA",
    "sg:tags":[
        "grocer"
    ],
    "sg:website":"www.winndixie.com",
    "wof:name":"Winn-Dixie",
    "wof:placetype":"venue"
},
  "geometry": {"coordinates":[-82.80878300000001,32.973157],"type":"Point"}
}