{
  "type": "Feature",
  "properties": {
    "addr:full":"3978 Devonshire Dr Marietta GA 30066",
    "addr:housenumber":"3978",
    "addr:postcode":"30066",
    "addr:street":"Devonshire Dr",
    "iso:country":"US",
    "sg:address":"3978 Devonshire Dr",
    "sg:city":"Marietta",
    "sg:classifiers":[
        {
            "category":"Real Estate",
            "subcategory":"Real Estate Agent",
            "type":"Services"
        }
    ],
    "sg:phone":"+1 770 926 4016",
    "sg:postcode":"30066",
    "sg:province":"GA",
    "wof:name":"Homefinders Inc",
    "wof:placetype":"venue"
},
  "geometry": {"coordinates":[-84.533968,34.047764],"type":"Point"}
}