{
  "type": "Feature",
  "properties": {
    "addr:full":"1002 Bay Rockyford Rd Hartsfield GA 31756",
    "addr:housenumber":"1002",
    "addr:postcode":"31756",
    "addr:street":"Bay Rockyford Rd",
    "iso:country":"US",
    "sg:address":"1002 Bay Rockyford Rd",
    "sg:city":"Hartsfield",
    "sg:classifiers":[
        {
            "category":"Farming",
            "subcategory":"Farm & Veterinary Services",
            "type":"Manufacturing & Wholesale Goods"
        }
    ],
    "sg:phone":"+1 229 941 5544",
    "sg:postcode":"31756",
    "sg:province":"GA",
    "sg:tags":[
        "crop",
        "harvesting"
    ],
    "wof:name":"Wendell Brown",
    "wof:placetype":"venue"
},
  "geometry": {"coordinates":[-83.915631,31.167744],"type":"Point"}
}