{
  "type": "Feature",
  "properties": {
    "iso:country":"US",
    "sg:address":"2215 Cheshire Bridge Rd NE",
    "sg:city":"Atlanta",
    "sg:classifiers":[
        {
            "category":"Health Services",
            "subcategory":"Clinic",
            "type":"Services"
        }
    ],
    "sg:phone":"+1 404 728 9557",
    "sg:postcode":"30324",
    "sg:province":"GA",
    "sg:tags":[
        "rehabilitation"
    ],
    "wof:name":"Georgia Rehabilitation Outreach, Inc.",
    "wof:placetype":"venue"
},
  "geometry": {"coordinates":[-84.352767,33.815587],"type":"Point"}
}