{
  "type": "Feature",
  "properties": {
    "iso:country":"US",
    "sg:address":"1010 Main St",
    "sg:city":"Stone Mountain",
    "sg:classifiers":[
        {
            "category":"Building & Trades",
            "subcategory":"Pest Control",
            "type":"Services"
        }
    ],
    "sg:phone":"+1 770 498 7998",
    "sg:postcode":"30083",
    "sg:province":"GA",
    "sg:website":"www.alertpestx.com",
    "wof:name":"Alert Exterminators",
    "wof:placetype":"venue"
},
  "geometry": {"coordinates":[-84.1707,33.8097],"type":"Point"}
}