{
  "type": "Feature",
  "properties": {
    "iso:country":"US",
    "sg:address":"216 Meadow Ln",
    "sg:city":"Cartersville",
    "sg:classifiers":[
        {
            "category":"Personal",
            "subcategory":"Beauty Salon",
            "type":"Services"
        }
    ],
    "sg:phone":"+1 770 382 1342",
    "sg:postcode":"30120",
    "sg:province":"GA",
    "wof:name":"Doubles Beauty Shop",
    "wof:placetype":"venue"
},
  "geometry": {"coordinates":[-84.818145,34.201409],"type":"Point"}
}