{
  "type": "Feature",
  "properties": {
    "iso:country":"US",
    "sg:address":"340 Pleasant Grove Cir",
    "sg:city":"Mc Donough",
    "sg:classifiers":[
        {
            "category":"Home & Garden",
            "subcategory":"Carpets & Floor Coverings",
            "type":"Retail Goods"
        }
    ],
    "sg:phone":"+1 770 898 3594",
    "sg:postcode":"30252",
    "sg:province":"GA",
    "wof:name":"Osborne Floors Inc",
    "wof:placetype":"venue"
},
  "geometry": {"coordinates":[-84.120386,33.555061],"type":"Point"}
}