{
  "type": "Feature",
  "properties": {
    "addr:full":"850 Bobbin Mill Rd Athens GA 30606",
    "addr:housenumber":"850",
    "addr:postcode":"30606",
    "addr:street":"Bobbin Mill Rd",
    "iso:country":"US",
    "sg:address":"850 Bobbin Mill Rd",
    "sg:city":"Athens",
    "sg:classifiers":[
        {
            "category":"Professional",
            "type":"Services"
        }
    ],
    "sg:phone":"+1 706 369 1021",
    "sg:postcode":"30606",
    "sg:province":"GA",
    "sg:tags":[
        "establishment"
    ],
    "wof:name":"WGMG",
    "wof:placetype":"venue"
},
  "geometry": {"coordinates":[-83.398385,33.940823],"type":"Point"}
}