{
  "type": "Feature",
  "properties": {
    "addr:full":"6765 Peachtree Industrial Blvd Atlanta GA 30360",
    "addr:housenumber":"6765",
    "addr:postcode":"30360",
    "addr:street":"Peachtree Industrial Blvd",
    "iso:country":"US",
    "sg:address":"6765 Peachtree Industrial Blvd",
    "sg:city":"Atlanta",
    "sg:classifiers":[
        {
            "category":"Manufacturing",
            "subcategory":"Electronics",
            "type":"Manufacturing & Wholesale Goods"
        }
    ],
    "sg:phone":"+1 770 448 1604",
    "sg:postcode":"30360",
    "sg:province":"GA",
    "sg:tags":[
        "defense",
        "electronic",
        "system",
        "mfg"
    ],
    "wof:name":"Lockheed Martin",
    "wof:placetype":"venue"
},
  "geometry": {"coordinates":[-84.252495,33.936899],"type":"Point"}
}