{
  "type": "Feature",
  "properties": {
    "addr:full":"2430 Wall St SE Conyers GA 30013",
    "addr:housenumber":"2430",
    "addr:postcode":"30013",
    "addr:street":"Wall St Se",
    "iso:country":"US",
    "sg:address":"2430 Wall St SE",
    "sg:city":"Conyers",
    "sg:classifiers":[
        {
            "category":"Building & Trades",
            "subcategory":"Locksmith",
            "type":"Services"
        }
    ],
    "sg:phone":"+1 877 411 1154",
    "sg:postcode":"30013",
    "sg:province":"GA",
    "sg:tags":[
        "key"
    ],
    "wof:name":"A 1 Lock & Locksmith",
    "wof:placetype":"venue"
},
  "geometry": {"coordinates":[-83.981987,33.625423],"type":"Point"}
}