{
  "type": "Feature",
  "properties": {
    "iso:country":"US",
    "sg:address":"1 Atlanta Ave SW",
    "sg:city":"Atlanta",
    "sg:classifiers":[
        {
            "category":"Building & Trades",
            "subcategory":"Construction",
            "type":"Services"
        }
    ],
    "sg:phone":"+1 404 530 6630",
    "sg:postcode":"30315",
    "sg:province":"GA",
    "sg:tags":[
        "house"
    ],
    "wof:name":"Citadel Design Const Corp",
    "wof:placetype":"venue"
},
  "geometry": {"coordinates":[-84.38944600000001,33.730415],"type":"Point"}
}