{
  "type": "Feature",
  "properties": {
    "addr:full":"6433 Kettle Creek Way Flowery Branch GA 30542",
    "addr:housenumber":"6433",
    "addr:postcode":"30542",
    "addr:street":"Kettle Creek Way",
    "iso:country":"US",
    "sg:address":"6433 Kettle Creek Way",
    "sg:city":"Flowery Branch",
    "sg:classifiers":[
        {
            "category":"Education",
            "subcategory":"Special Training",
            "type":"Public Place"
        }
    ],
    "sg:phone":"+1 770 965 9919",
    "sg:postcode":"30542",
    "sg:province":"GA",
    "wof:name":"Drivers Seat LLC",
    "wof:placetype":"venue"
},
  "geometry": {"coordinates":[-83.93591000000001,34.191404],"type":"Point"}
}