{
  "type": "Feature",
  "properties": {
    "addr:full":"1153 Melton Dr SW Lilburn GA 30047",
    "addr:housenumber":"1153",
    "addr:postcode":"30047",
    "addr:street":"Melton Dr Sw",
    "iso:country":"US",
    "sg:address":"1153 Melton Dr SW",
    "sg:city":"Lilburn",
    "sg:classifiers":[
        {
            "category":"Wholesale",
            "subcategory":"Medical Equipment & Supplies",
            "type":"Manufacturing & Wholesale Goods"
        }
    ],
    "sg:phone":"+1 770 978 7575",
    "sg:postcode":"30047",
    "sg:province":"GA",
    "sg:tags":[
        "dental"
    ],
    "wof:name":"LWH Management Inc",
    "wof:placetype":"venue"
},
  "geometry": {"coordinates":[-84.052513,33.879024],"type":"Point"}
}