{
  "type": "Feature",
  "properties": {
    "addr:full":"1300 Holland Rd Cataula GA 31804",
    "addr:housenumber":"1300",
    "addr:postcode":"31804",
    "addr:street":"Holland Rd",
    "iso:country":"US",
    "sg:address":"1300 Holland Rd",
    "sg:city":"Cataula",
    "sg:classifiers":[
        {
            "category":"Building & Trades",
            "subcategory":"Construction",
            "type":"Services"
        }
    ],
    "sg:phone":"+1 706 576 5679",
    "sg:postcode":"31804",
    "sg:province":"GA",
    "sg:tags":[
        "house"
    ],
    "wof:name":"Satterwhite Construction",
    "wof:placetype":"venue"
},
  "geometry": {"coordinates":[-84.86374499999999,32.636373],"type":"Point"}
}