{
  "type": "Feature",
  "properties": {
    "addr:full":"305 N Burnt Hickory Rd Douglasville GA 30134",
    "addr:housenumber":"305",
    "addr:postcode":"30134",
    "addr:street":"N Burnt Hickory Rd",
    "iso:country":"US",
    "sg:address":"305 N Burnt Hickory Rd",
    "sg:city":"Douglasville",
    "sg:classifiers":[
        {
            "category":"Place Of Worship",
            "subcategory":"Church",
            "type":"Public Place"
        },
        {
            "category":"Place Of Worship",
            "type":"Public Place"
        }
    ],
    "sg:phone":"+1 770 489 9365",
    "sg:postcode":"30134",
    "sg:province":"GA",
    "sg:tags":[
        "churches-evangelical"
    ],
    "wof:name":"Faith Evangelical Methodist Church",
    "wof:placetype":"venue"
},
  "geometry": {"coordinates":[-84.723141,33.795966],"type":"Point"}
}