{
  "type": "Feature",
  "properties": {
    "addr:full":"1431 Cobb Pkwy S Marietta GA 30060",
    "addr:housenumber":"1431",
    "addr:postcode":"30060",
    "addr:street":"Cobb Pkwy S",
    "iso:country":"US",
    "sg:address":"1431 Cobb Pkwy S",
    "sg:city":"Marietta",
    "sg:classifiers":[
        {
            "category":"Autos & Motor Vehicles",
            "subcategory":"Automobile Sales",
            "type":"Retail Goods"
        }
    ],
    "sg:phone":"+1 770 514 7408",
    "sg:postcode":"30060",
    "sg:province":"GA",
    "wof:name":"Lexus Parts",
    "wof:placetype":"venue"
},
  "geometry": {"coordinates":[-84.50074499999999,33.917846],"type":"Point"}
}