{
  "type": "Feature",
  "properties": {
    "addr:full":"5784 Lake Forrest Dr NW Atlanta GA 30328",
    "addr:housenumber":"5784",
    "addr:postcode":"30328",
    "addr:street":"Lake Forrest Dr Nw",
    "iso:country":"US",
    "sg:address":"5784 Lake Forrest Dr NW",
    "sg:city":"Atlanta",
    "sg:classifiers":[
        {
            "category":"Professional",
            "subcategory":"Management & Consulting",
            "type":"Services"
        },
        {
            "category":"Professional",
            "subcategory":"Employment Agencies",
            "type":"Services"
        }
    ],
    "sg:phone":"+1 404 256 4191",
    "sg:postcode":"30328",
    "sg:province":"GA",
    "sg:tags":[
        "consultant",
        "resource",
        "human",
        "personnel"
    ],
    "wof:name":"The Recruiting Group",
    "wof:placetype":"venue"
},
  "geometry": {"coordinates":[-84.387097,33.913241],"type":"Point"}
}