{
  "type": "Feature",
  "properties": {
    "iso:country":"US",
    "sg:address":"189 Jamison St SE",
    "sg:city":"Calhoun",
    "sg:classifiers":[
        {
            "category":"Travel",
            "subcategory":"Hotels & Motels",
            "type":"Entertainment"
        }
    ],
    "sg:phone":"+1 706 629 8133",
    "sg:postcode":"30701",
    "sg:province":"GA",
    "sg:tags":[
        "operation"
    ],
    "wof:name":"Jameson Inns",
    "wof:placetype":"venue"
},
  "geometry": {"coordinates":[-84.920885,34.4704],"type":"Point"}
}