{
  "type": "Feature",
  "properties": {
    "addr:full":"50 E Great Southwest Pkwy SW Atlanta GA 30336",
    "addr:housenumber":"50",
    "addr:postcode":"30336",
    "addr:street":"E Great Southwest Pkwy Sw",
    "iso:country":"US",
    "sg:address":"50 E Great Southwest Pkwy SW",
    "sg:city":"Atlanta",
    "sg:classifiers":[
        {
            "category":"Manufacturing",
            "subcategory":"Furniture",
            "type":"Manufacturing & Wholesale Goods"
        }
    ],
    "sg:phone":"+1 404 691 8833",
    "sg:postcode":"30336",
    "sg:province":"GA",
    "wof:name":"Iem Atlanta Corp",
    "wof:placetype":"venue"
},
  "geometry": {"coordinates":[-84.55831999999999,33.74395],"type":"Point"}
}