{
  "type": "Feature",
  "properties": {
    "addr:full":"2565 Jolly Rd Atlanta GA 30349",
    "addr:housenumber":"2565",
    "addr:postcode":"30349",
    "addr:street":"Jolly Rd",
    "iso:country":"US",
    "sg:address":"2565 Jolly Rd",
    "sg:city":"Atlanta",
    "sg:classifiers":[
        {
            "category":"Personal",
            "subcategory":"Massage",
            "type":"Services"
        }
    ],
    "sg:phone":"+1 678 608 8938",
    "sg:postcode":"30349",
    "sg:province":"GA",
    "wof:name":"Essential Touch Therapeutic Massage",
    "wof:placetype":"venue"
},
  "geometry": {"coordinates":[-84.473448,33.612011],"type":"Point"}
}