{
  "type": "Feature",
  "properties": {
    "iso:country":"US",
    "sg:address":"2329 Wilderness Way",
    "sg:city":"Marietta",
    "sg:classifiers":[
        {
            "category":"Manufacturing",
            "subcategory":"Tools & Machinery",
            "type":"Manufacturing & Wholesale Goods"
        }
    ],
    "sg:phone":"+1 770 977 5858",
    "sg:postcode":"30066",
    "sg:province":"GA",
    "sg:tags":[
        "computer",
        "electronic",
        "mfg"
    ],
    "wof:name":"Jupiter Systems",
    "wof:placetype":"venue"
},
  "geometry": {"coordinates":[-84.50617099999999,34.00711],"type":"Point"}
}