{
  "type": "Feature",
  "properties": {
    "iso:country":"US",
    "sg:address":"105 Patton Dr",
    "sg:city":"Americus",
    "sg:classifiers":[
        {
            "category":"Professional",
            "subcategory":"Engineering",
            "type":"Services"
        }
    ],
    "sg:phone":"+1 229 928 4098",
    "sg:postcode":"31719",
    "sg:province":"GA",
    "wof:name":"Larry Allen",
    "wof:placetype":"venue"
},
  "geometry": {"coordinates":[-84.24378299999999,32.096483],"type":"Point"}
}