{
  "type": "Feature",
  "properties": {
    "addr:full":"2768 E College Ave Decatur GA 30030",
    "addr:housenumber":"2768",
    "addr:postcode":"30030",
    "addr:street":"E College Ave",
    "iso:country":"US",
    "sg:address":"2768 E College Ave",
    "sg:city":"Decatur",
    "sg:classifiers":[
        {
            "category":"Personal",
            "type":"Services"
        }
    ],
    "sg:phone":"+1 404 373 4074",
    "sg:postcode":"30030",
    "sg:province":"GA",
    "sg:tags":[
        "home"
    ],
    "sg:website":"http://www.aceanda.com",
    "wof:name":"Ace & A Heating & Air Conditioning",
    "wof:placetype":"venue"
},
  "geometry": {"coordinates":[-84.276703,33.774899],"type":"Point"}
}