{
  "type": "Feature",
  "properties": {
    "iso:country":"US",
    "sg:address":"407 W Savannah Ave",
    "sg:city":"Valdosta",
    "sg:classifiers":[
        {
            "category":"Organizations",
            "subcategory":"Religious Organization",
            "type":"Services"
        }
    ],
    "sg:phone":"+1 229 259 0055",
    "sg:postcode":"31601",
    "sg:province":"GA",
    "wof:name":"Christ Temple Holiness Church",
    "wof:placetype":"venue"
},
  "geometry": {"coordinates":[-83.282584,30.82803],"type":"Point"}
}