{
  "type": "Feature",
  "properties": {
    "addr:full":"19 Pat Dixon Rd Hazlehurst GA 31539",
    "addr:housenumber":"19",
    "addr:postcode":"31539",
    "addr:street":"Pat Dixon Rd",
    "iso:country":"US",
    "sg:address":"19 Pat Dixon Rd",
    "sg:city":"Hazlehurst",
    "sg:classifiers":[
        {
            "category":"Freight",
            "type":"Transportation"
        }
    ],
    "sg:phone":"+1 912 375 9008",
    "sg:postcode":"31539",
    "sg:province":"GA",
    "wof:name":"Ga Dept Of Transportation",
    "wof:placetype":"venue"
},
  "geometry": {"coordinates":[-82.60659099999999,31.864095],"type":"Point"}
}