{
  "type": "Feature",
  "properties": {
    "addr:full":"1335 Marietta Blvd NW Atlanta GA 30318",
    "addr:housenumber":"1335",
    "addr:postcode":"30318",
    "addr:street":"Marietta Blvd Nw",
    "iso:country":"US",
    "sg:address":"1335 Marietta Blvd NW",
    "sg:city":"Atlanta",
    "sg:classifiers":[
        {
            "category":"Shopping",
            "subcategory":"Clothing, Apparel, & Fashions",
            "type":"Retail Goods"
        },
        {
            "category":"Banks & Credit Unions",
            "subcategory":"Bank",
            "type":"Services"
        },
        {
            "category":"Shopping",
            "subcategory":"Used Merchandise",
            "type":"Retail Goods"
        }
    ],
    "sg:phone":"+1 404 352 5109",
    "sg:postcode":"30318",
    "sg:province":"GA",
    "sg:tags":[
        "shop",
        "resale",
        "second",
        "consignment",
        "hand"
    ],
    "wof:name":"The Market Place At M West",
    "wof:placetype":"venue"
},
  "geometry": {"coordinates":[-84.42990899999999,33.79147],"type":"Point"}
}