{
  "type": "Feature",
  "properties": {
    "addr:full":"1488 Sisters Ct Lawrenceville GA 30043",
    "addr:housenumber":"1488",
    "addr:postcode":"30043",
    "addr:street":"Sisters Ct",
    "iso:country":"US",
    "sg:address":"1488 Sisters Ct",
    "sg:city":"Lawrenceville",
    "sg:classifiers":[
        {
            "category":"Building & Trades",
            "subcategory":"Construction",
            "type":"Services"
        }
    ],
    "sg:phone":"+1 770 527 8854",
    "sg:postcode":"30043",
    "sg:province":"GA",
    "sg:tags":[
        "house"
    ],
    "wof:name":"Jeffrey Homes Inc",
    "wof:placetype":"venue"
},
  "geometry": {"coordinates":[-84.04835199999999,33.967354],"type":"Point"}
}