{
  "type": "Feature",
  "properties": {
    "addr:full":"781 Wheeler St NW Ste 11 Atlanta GA 30318",
    "addr:housenumber":"781",
    "addr:postcode":"30318",
    "addr:street":"Wheeler St Nw Ste 11",
    "iso:country":"US",
    "sg:address":"781 Wheeler St NW Ste 11",
    "sg:city":"Atlanta",
    "sg:classifiers":[
        {
            "category":"Real Estate",
            "subcategory":"Real Estate Services",
            "type":"Services"
        }
    ],
    "sg:phone":"+1 404 664 6948",
    "sg:postcode":"30318",
    "sg:province":"GA",
    "sg:tags":[
        "apartment",
        "vacancy",
        "listing",
        "rental",
        "finder"
    ],
    "wof:name":"Morel Studio Support",
    "wof:placetype":"venue"
},
  "geometry": {"coordinates":[-84.41185299999999,33.77407],"type":"Point"}
}