{
  "type": "Feature",
  "properties": {
    "addr:full":"Ivan Allen Jr Blvd Atlanta GA 30313",
    "addr:postcode":"30313",
    "addr:street":"Jr Blvd",
    "iso:country":"US",
    "sg:address":"Ivan Allen Jr Blvd",
    "sg:city":"Atlanta",
    "sg:classifiers":[
        {
            "category":"Retail",
            "subcategory":"Event Space",
            "type":"Services"
        }
    ],
    "sg:phone":"+1 404 581 4000",
    "sg:postcode":"30313",
    "sg:province":"GA",
    "sg:tags":[
        "venue"
    ],
    "sg:website":"www.georgiaaquarium.org/bookYour...",
    "wof:name":"Georgia Aquarium - Event Space",
    "wof:placetype":"venue"
},
  "geometry": {"coordinates":[-84.39420800000001,33.764621],"type":"Point"}
}