{
  "type": "Feature",
  "properties": {
    "addr:full":"985 Asbury Mill Rd Cleveland GA 30528",
    "addr:housenumber":"985",
    "addr:postcode":"30528",
    "addr:street":"Asbury Mill Rd",
    "iso:country":"US",
    "sg:address":"985 Asbury Mill Rd",
    "sg:city":"Cleveland",
    "sg:classifiers":[
        {
            "category":"Home & Garden",
            "subcategory":"Furniture",
            "type":"Retail Goods"
        }
    ],
    "sg:phone":"+1 706 348 1810",
    "sg:postcode":"30528",
    "sg:province":"GA",
    "wof:name":"Buck Mountain Outdoors",
    "wof:placetype":"venue"
},
  "geometry": {"coordinates":[-83.80022099999999,34.578878],"type":"Point"}
}