{
  "type": "Feature",
  "properties": {
    "iso:country":"US",
    "sg:address":"1501 Broad St",
    "sg:city":"Augusta",
    "sg:classifiers":[
        {
            "category":"Autos & Motor Vehicles",
            "subcategory":"Fuel & Gas Station",
            "type":"Retail Goods"
        }
    ],
    "sg:phone":"+1 706 722 4517",
    "sg:postcode":"30904",
    "sg:province":"GA",
    "sg:tags":[
        "automotive",
        "station",
        "gasoline",
        "truck",
        "rent"
    ],
    "wof:name":"Amoco",
    "wof:placetype":"venue"
},
  "geometry": {"coordinates":[-81.98263300000001,33.480908],"type":"Point"}
}