{
  "type": "Feature",
  "properties": {
    "iso:country":"US",
    "sg:address":"870 N Highland Ave NE",
    "sg:city":"Atlanta",
    "sg:classifiers":[
        {
            "category":"Restaurant",
            "type":"Food & Drink"
        }
    ],
    "sg:phone":"+1 404 897 3463",
    "sg:postcode":"30306",
    "sg:province":"GA",
    "sg:tags":[
        "eating"
    ],
    "wof:name":"Dish Restaurant",
    "wof:placetype":"venue"
},
  "geometry": {"coordinates":[-84.35310800000001,33.778818],"type":"Point"}
}