{
  "type": "Feature",
  "properties": {
    "iso:country":"US",
    "sg:address":"2453 Ridge Rd",
    "sg:city":"Augusta",
    "sg:classifiers":[
        {
            "category":"Professional",
            "type":"Services"
        }
    ],
    "sg:phone":"+1 706 798 9883",
    "sg:postcode":"30906",
    "sg:province":"GA",
    "sg:tags":[
        "establishment"
    ],
    "wof:name":"Interfaith Hospitality Network",
    "wof:placetype":"venue"
},
  "geometry": {"coordinates":[-82.045676,33.429285],"type":"Point"}
}