{
  "type": "Feature",
  "properties": {
    "addr:full":"2207 Cusseta Rd Columbus GA 31903",
    "addr:housenumber":"2207",
    "addr:postcode":"31903",
    "addr:street":"Cusseta Rd",
    "iso:country":"US",
    "sg:address":"2207 Cusseta Rd",
    "sg:city":"Columbus",
    "sg:classifiers":[
        {
            "category":"Retail",
            "subcategory":"Auto Repair",
            "type":"Services"
        }
    ],
    "sg:phone":"+1 706 687 5766",
    "sg:postcode":"31903",
    "sg:province":"GA",
    "sg:tags":[
        "repairing",
        "automobile"
    ],
    "wof:name":"C's Auto Repair",
    "wof:placetype":"venue"
},
  "geometry": {"coordinates":[-84.960294,32.448782],"type":"Point"}
}