{
  "type": "Feature",
  "properties": {
    "addr:full":"3812 Oakcliff Industrial Ct Atlanta GA 30340",
    "addr:housenumber":"3812",
    "addr:postcode":"30340",
    "addr:street":"Oakcliff Industrial Ct",
    "iso:country":"US",
    "sg:address":"3812 Oakcliff Industrial Ct",
    "sg:city":"Atlanta",
    "sg:classifiers":[
        {
            "category":"Building & Trades",
            "subcategory":"Locksmith",
            "type":"Services"
        }
    ],
    "sg:phone":"+1 678 823 4886",
    "sg:postcode":"30340",
    "sg:province":"GA",
    "sg:tags":[
        "key"
    ],
    "wof:name":"Locksmith",
    "wof:placetype":"venue"
},
  "geometry": {"coordinates":[-84.248333,33.903534],"type":"Point"}
}