{
  "type": "Feature",
  "properties": {
    "iso:country":"US",
    "sg:address":"372 Glynn St N",
    "sg:city":"Fayetteville",
    "sg:classifiers":[
        {
            "category":"Shopping",
            "subcategory":"Bicycles & Sporting Goods",
            "type":"Retail Goods"
        }
    ],
    "sg:phone":"+1 678 817 4532",
    "sg:postcode":"30214",
    "sg:province":"GA",
    "sg:tags":[
        "golf",
        "supply"
    ],
    "wof:name":"Pro Golf Discount",
    "wof:placetype":"venue"
},
  "geometry": {"coordinates":[-84.45493,33.455598],"type":"Point"}
}