{
  "type": "Feature",
  "properties": {
    "addr:full":"310 Winterberry Dr Athens GA 30606",
    "addr:housenumber":"310",
    "addr:postcode":"30606",
    "addr:street":"Winterberry Dr",
    "iso:country":"US",
    "sg:address":"310 Winterberry Dr",
    "sg:city":"Athens",
    "sg:classifiers":[
        {
            "category":"Recreation",
            "type":"Entertainment"
        }
    ],
    "sg:phone":"+1 706 549 4900",
    "sg:postcode":"30606",
    "sg:province":"GA",
    "sg:tags":[
        "paint",
        "ball",
        "sport"
    ],
    "wof:name":"Doro Paintball",
    "wof:placetype":"venue"
},
  "geometry": {"coordinates":[-83.444788,33.930232],"type":"Point"}
}