{
  "type": "Feature",
  "properties": {
    "addr:full":"7456 Battlefield Pkwy Ringgold GA 30736",
    "addr:housenumber":"7456",
    "addr:postcode":"30736",
    "addr:street":"Battlefield Pkwy",
    "iso:country":"US",
    "sg:address":"7456 Battlefield Pkwy",
    "sg:city":"Ringgold",
    "sg:classifiers":[
        {
            "category":"Personal",
            "subcategory":"Tanning Parlor",
            "type":"Services"
        },
        {
            "category":"Personal",
            "subcategory":"Beauty Salon",
            "type":"Services"
        },
        {
            "category":"Personal",
            "subcategory":"Massage",
            "type":"Services"
        },
        {
            "category":"Personal",
            "subcategory":"Day Spa",
            "type":"Services"
        },
        {
            "category":"Personal",
            "subcategory":"Nail Salon",
            "type":"Services"
        }
    ],
    "sg:phone":"+1 706 965 7546",
    "sg:postcode":"30736",
    "sg:province":"GA",
    "sg:tags":[
        "therapist"
    ],
    "wof:name":"Twenty Fifth Hour Spa & Salon",
    "wof:placetype":"venue"
},
  "geometry": {"coordinates":[-85.142904,34.926352],"type":"Point"}
}