{
  "type": "Feature",
  "properties": {
    "iso:country":"US",
    "sg:address":"4920 Flat Shoals Pkwy",
    "sg:city":"Decatur",
    "sg:classifiers":[
        {
            "category":"Retail",
            "subcategory":"Laundry & Dry Cleaning",
            "type":"Services"
        }
    ],
    "sg:phone":"+1 770 981 8883",
    "sg:postcode":"30034",
    "sg:province":"GA",
    "wof:name":"Best Cleaners # 2",
    "wof:placetype":"venue"
},
  "geometry": {"coordinates":[-84.226353,33.680634],"type":"Point"}
}