{
  "type": "Feature",
  "properties": {
    "addr:full":"314 E Tyler St Dalton GA 30721",
    "addr:housenumber":"314",
    "addr:postcode":"30721",
    "addr:street":"E Tyler St",
    "iso:country":"US",
    "sg:address":"314 E Tyler St",
    "sg:city":"Dalton",
    "sg:classifiers":[
        {
            "category":"Retail",
            "subcategory":"Auto Repair",
            "type":"Services"
        }
    ],
    "sg:phone":"+1 706 272 0198",
    "sg:postcode":"30721",
    "sg:province":"GA",
    "sg:tags":[
        "general"
    ],
    "wof:name":"Super Tune Up and Brake",
    "wof:placetype":"venue"
},
  "geometry": {"coordinates":[-84.964544,34.779686],"type":"Point"}
}