{
  "type": "Feature",
  "properties": {
    "iso:country":"US",
    "sg:address":"450 Beaver Ruin Rd",
    "sg:city":"Norcross",
    "sg:classifiers":[
        {
            "category":"Autos & Motor Vehicles",
            "subcategory":"Motorcycle Sales",
            "type":"Retail Goods"
        }
    ],
    "sg:phone":"+1 770 717 1767",
    "sg:postcode":"30071",
    "sg:province":"GA",
    "wof:name":"S K S Motorcycles V Twin",
    "wof:placetype":"venue"
},
  "geometry": {"coordinates":[-84.202698,33.943501],"type":"Point"}
}