{
  "type": "Feature",
  "properties": {
    "iso:country":"US",
    "sg:address":"511 Broad St",
    "sg:city":"Augusta",
    "sg:classifiers":[
        {
            "category":"Shopping",
            "subcategory":"Clothing, Apparel, & Fashions",
            "type":"Retail Goods"
        }
    ],
    "sg:phone":"+1 706 722 1500",
    "sg:postcode":"30901",
    "sg:province":"GA",
    "sg:tags":[
        "uniform"
    ],
    "wof:name":"Command Uniforms",
    "wof:placetype":"venue"
},
  "geometry": {"coordinates":[-81.960111,33.473567],"type":"Point"}
}