{
  "type": "Feature",
  "properties": {
    "iso:country":"US",
    "sg:address":"484 Flat Shoals Ave SE",
    "sg:city":"Atlanta",
    "sg:classifiers":[
        {
            "category":"Shopping",
            "type":"Retail Goods"
        }
    ],
    "sg:phone":"+1 404 523 5299",
    "sg:postcode":"30316",
    "sg:province":"GA",
    "sg:tags":[
        "merchandise"
    ],
    "wof:name":"Utopian Bazaar",
    "wof:placetype":"venue"
},
  "geometry": {"coordinates":[-84.346296,33.74114],"type":"Point"}
}