{
  "type": "Feature",
  "properties": {
    "iso:country":"US",
    "sg:address":"1230 Peachtree Street NE",
    "sg:city":"Atlanta",
    "sg:classifiers":[
        {
            "category":"Building & Trades",
            "subcategory":"Construction",
            "type":"Services"
        },
        {
            "category":"Real Estate",
            "subcategory":"Architect",
            "type":"Services"
        }
    ],
    "sg:phone":"+1 404 888 6600",
    "sg:postcode":"30309",
    "sg:province":"GA",
    "sg:tags":[
        "interior",
        "design"
    ],
    "sg:website":"www.tvsa.com",
    "wof:name":"Thompson Ventulett Stainback & Associates",
    "wof:placetype":"venue"
},
  "geometry": {"coordinates":[-84.384032,33.788865],"type":"Point"}
}