{
  "type": "Feature",
  "properties": {
    "iso:country":"US",
    "sg:address":"2318 2nd Ave",
    "sg:city":"Decatur",
    "sg:classifiers":[
        {
            "category":"Organizations",
            "subcategory":"Religious Organization",
            "type":"Services"
        }
    ],
    "sg:phone":"+1 404 243 0000",
    "sg:postcode":"30032",
    "sg:province":"GA",
    "wof:name":"Kingdom Living Ministries",
    "wof:placetype":"venue"
},
  "geometry": {"coordinates":[-84.307863,33.721293],"type":"Point"}
}