{
  "type": "Feature",
  "properties": {
    "addr:full":"1365 Forest Pkwy Morrow GA 30260",
    "addr:housenumber":"1365",
    "addr:postcode":"30260",
    "addr:street":"Forest Pkwy",
    "iso:country":"US",
    "sg:address":"1365 Forest Pkwy",
    "sg:city":"Morrow",
    "sg:classifiers":[
        {
            "category":"Retail",
            "subcategory":"Laundry & Dry Cleaning",
            "type":"Services"
        }
    ],
    "sg:phone":"+1 404 363 8662",
    "sg:postcode":"30260",
    "sg:province":"GA",
    "wof:name":"Lake City Alterations",
    "wof:placetype":"venue"
},
  "geometry": {"coordinates":[-84.344707,33.61305],"type":"Point"}
}