{
  "type": "Feature",
  "properties": {
    "iso:country":"US",
    "sg:address":"1620 E Shotwell St",
    "sg:city":"Bainbridge",
    "sg:classifiers":[
        {
            "category":"Banks & Credit Unions",
            "subcategory":"Bank",
            "type":"Services"
        }
    ],
    "sg:phone":"+1 229 248 5848",
    "sg:postcode":"39819",
    "sg:province":"GA",
    "sg:tags":[
        "personal",
        "institution"
    ],
    "wof:name":"Advance America",
    "wof:placetype":"venue"
},
  "geometry": {"coordinates":[-84.550363,30.90377],"type":"Point"}
}