{
  "type": "Feature",
  "properties": {
    "iso:country":"US",
    "sg:address":"2520 Edgewater Rd",
    "sg:city":"Cumming",
    "sg:classifiers":[
        {
            "category":"Building & Trades",
            "subcategory":"Construction",
            "type":"Services"
        }
    ],
    "sg:phone":"+1 770 887 8745",
    "sg:postcode":"30041",
    "sg:province":"GA",
    "sg:tags":[
        "house"
    ],
    "wof:name":"Dsk Remodeling",
    "wof:placetype":"venue"
},
  "geometry": {"coordinates":[-84.105885,34.203342],"type":"Point"}
}