{
  "type": "Feature",
  "properties": {
    "iso:country":"US",
    "sg:address":"20 Executive Park S NE",
    "sg:city":"Atlanta",
    "sg:classifiers":[
        {
            "category":"Professional",
            "subcategory":"Art Services",
            "type":"Services"
        }
    ],
    "sg:phone":"+1 404 529 9937",
    "sg:postcode":"30329",
    "sg:province":"GA",
    "sg:tags":[
        "commercial",
        "design",
        "business"
    ],
    "wof:name":"Mastermind Graphics LLC",
    "wof:placetype":"venue"
},
  "geometry": {"coordinates":[-84.342412,33.827332],"type":"Point"}
}