{
  "type": "Feature",
  "properties": {
    "addr:full":"187 Dalton St Ellijay GA 30540",
    "addr:housenumber":"187",
    "addr:postcode":"30540",
    "addr:street":"Dalton St",
    "iso:country":"US",
    "sg:address":"187 Dalton St",
    "sg:city":"Ellijay",
    "sg:classifiers":[
        {
            "category":"Place Of Worship",
            "subcategory":"Church",
            "type":"Public Place"
        },
        {
            "category":"Place Of Worship",
            "type":"Public Place"
        }
    ],
    "sg:phone":"+1 706 635 5613",
    "sg:postcode":"30540",
    "sg:province":"GA",
    "sg:tags":[
        "churches-baptist-general",
        "churches-baptist"
    ],
    "sg:website":"http://www.abc-usa.org",
    "wof:name":"First Baptist Church",
    "wof:placetype":"venue"
},
  "geometry": {"coordinates":[-84.482071,34.6968],"type":"Point"}
}