{
  "type": "Feature",
  "properties": {
    "iso:country":"US",
    "sg:address":"320 S Jefferson St",
    "sg:city":"Dublin",
    "sg:classifiers":[
        {
            "category":"Food & Beverages",
            "subcategory":"Groceries & Convenience Stores",
            "type":"Retail Goods"
        }
    ],
    "sg:phone":"+1 478 272 2143",
    "sg:postcode":"31021",
    "sg:province":"GA",
    "wof:name":"Cochran Brothers Co",
    "wof:placetype":"venue"
},
  "geometry": {"coordinates":[-82.903336,32.537665],"type":"Point"}
}