{
  "type": "Feature",
  "properties": {
    "iso:country":"US",
    "sg:address":"211 Russell Pkwy",
    "sg:city":"Warner Robins",
    "sg:classifiers":[
        {
            "category":"Cinema",
            "subcategory":"Movie Rental",
            "type":"Entertainment"
        }
    ],
    "sg:phone":"+1 478 329 1595",
    "sg:postcode":"31088",
    "sg:province":"GA",
    "sg:tags":[
        "game",
        "video"
    ],
    "sg:website":"www.blockbuster.com",
    "wof:name":"Blockbuster Video",
    "wof:placetype":"venue"
},
  "geometry": {"coordinates":[-83.627701,32.5937],"type":"Point"}
}