{
  "type": "Feature",
  "properties": {
    "addr:full":"30 Old Oak Ct Covington GA 30016",
    "addr:housenumber":"30",
    "addr:postcode":"30016",
    "addr:street":"Old Oak Ct",
    "iso:country":"US",
    "sg:address":"30 Old Oak Ct",
    "sg:city":"Covington",
    "sg:classifiers":[
        {
            "category":"Building & Trades",
            "subcategory":"Construction",
            "type":"Services"
        }
    ],
    "sg:phone":"+1 770 786 8830",
    "sg:postcode":"30016",
    "sg:province":"GA",
    "sg:tags":[
        "contractor"
    ],
    "wof:name":"Zuber Installation",
    "wof:placetype":"venue"
},
  "geometry": {"coordinates":[-83.952102,33.569131],"type":"Point"}
}