{
  "type": "Feature",
  "properties": {
    "iso:country":"US",
    "sg:address":"2901 Tree Summit Pkwy",
    "sg:city":"Duluth",
    "sg:classifiers":[
        {
            "category":"Banks & Credit Unions",
            "subcategory":"Financial Services",
            "type":"Services"
        }
    ],
    "sg:phone":"+1 678 516 1391",
    "sg:postcode":"30096",
    "sg:province":"GA",
    "sg:tags":[
        "investor"
    ],
    "wof:name":"Atlanta Thrift & Investment LP",
    "wof:placetype":"venue"
},
  "geometry": {"coordinates":[-84.162263,33.987146],"type":"Point"}
}