{
  "type": "Feature",
  "properties": {
    "addr:full":"2691 Shallowford Road NE Atlanta GA 30341",
    "addr:housenumber":"2691",
    "addr:postcode":"30341",
    "addr:street":"Shallowford Road Ne",
    "iso:country":"US",
    "sg:address":"2691 Shallowford Road NE",
    "sg:city":"Atlanta",
    "sg:classifiers":[
        {
            "category":"Retail",
            "subcategory":"Laundry & Dry Cleaning",
            "type":"Services"
        }
    ],
    "sg:phone":"+1 770 451 9760",
    "sg:postcode":"30341",
    "sg:province":"GA",
    "wof:name":"Tops Coin Laundry",
    "wof:placetype":"venue"
},
  "geometry": {"coordinates":[-84.28945400000001,33.865603],"type":"Point"}
}