{
  "type": "Feature",
  "properties": {
    "iso:country":"US",
    "sg:address":"1049 Meadow Glen Cir",
    "sg:city":"Fairburn",
    "sg:classifiers":[
        {
            "category":"Building & Trades",
            "subcategory":"Cleaning & Sanitation",
            "type":"Services"
        }
    ],
    "sg:phone":"+1 770 306 1168",
    "sg:postcode":"30213",
    "sg:province":"GA",
    "sg:tags":[
        "janitor"
    ],
    "wof:name":"LA Spanks Cleaning Svc",
    "wof:placetype":"venue"
},
  "geometry": {"coordinates":[-84.58063799999999,33.534056],"type":"Point"}
}