{
  "type": "Feature",
  "properties": {
    "iso:country":"US",
    "sg:address":"37 Howard St SE Kirkwood Station",
    "sg:city":"Atlanta",
    "sg:classifiers":[
        {
            "category":"Shopping",
            "subcategory":"Jewelry",
            "type":"Retail Goods"
        },
        {
            "category":"Professional",
            "subcategory":"Art Services",
            "type":"Services"
        }
    ],
    "sg:phone":"+1 404 343 3916",
    "sg:postcode":"30317",
    "sg:province":"GA",
    "sg:tags":[
        "designer",
        "display",
        "producer"
    ],
    "sg:website":"www.augustadesigns.com",
    "wof:name":"Augusta Designs",
    "wof:placetype":"venue"
},
  "geometry": {"coordinates":[-84.323256,33.750872],"type":"Point"}
}