{
  "type": "Feature",
  "properties": {
    "addr:full":"563 Lakeland Plz Cumming GA 30040",
    "addr:housenumber":"563",
    "addr:postcode":"30040",
    "addr:street":"Lakeland Plz",
    "iso:country":"US",
    "sg:address":"563 Lakeland Plz",
    "sg:city":"Cumming",
    "sg:classifiers":[
        {
            "category":"Health Services",
            "subcategory":"Chiropractor",
            "type":"Services"
        }
    ],
    "sg:phone":"+1 770 781 9050",
    "sg:postcode":"30040",
    "sg:province":"GA",
    "sg:tags":[
        "physician"
    ],
    "wof:name":"Levinson Chiropractic Center",
    "wof:placetype":"venue"
},
  "geometry": {"coordinates":[-84.145807,34.182459],"type":"Point"}
}