{
  "type": "Feature",
  "properties": {
    "addr:full":"525 Grayson Hwy Lawrenceville GA 30045",
    "addr:housenumber":"525",
    "addr:postcode":"30045",
    "addr:street":"Grayson Hwy",
    "iso:country":"US",
    "sg:address":"525 Grayson Hwy",
    "sg:city":"Lawrenceville",
    "sg:classifiers":[
        {
            "category":"Autos & Motor Vehicles",
            "subcategory":"Auto Supplies",
            "type":"Retail Goods"
        }
    ],
    "sg:phone":"+1 770 995 7257",
    "sg:postcode":"30045",
    "sg:province":"GA",
    "sg:tags":[
        "automobile",
        "parts"
    ],
    "wof:name":"O'REILLY Auto Parts",
    "wof:placetype":"venue"
},
  "geometry": {"coordinates":[-83.98060599999999,33.937546],"type":"Point"}
}