{
  "type": "Feature",
  "properties": {
    "iso:country":"US",
    "sg:address":"928 Bennock Mill Rd",
    "sg:city":"Augusta",
    "sg:classifiers":[
        {
            "category":"Professional",
            "type":"Services"
        }
    ],
    "sg:phone":"+1 706 793 9271",
    "sg:postcode":"30906",
    "sg:province":"GA",
    "wof:name":"Michael J Koch",
    "wof:placetype":"venue"
},
  "geometry": {"coordinates":[-81.932902,33.302527],"type":"Point"}
}