{
  "type": "Feature",
  "properties": {
    "iso:country":"US",
    "sg:address":"3379 Peachtree Rd NE Ste 101",
    "sg:city":"Atlanta",
    "sg:classifiers":[
        {
            "category":"Restaurant",
            "type":"Food & Drink"
        }
    ],
    "sg:phone":"+1 404 816 6535",
    "sg:postcode":"30326",
    "sg:province":"GA",
    "sg:tags":[
        "steakhouse"
    ],
    "sg:website":"mortons.com",
    "wof:name":"Morton's the Steakhouse",
    "wof:placetype":"venue"
},
  "geometry": {"coordinates":[-84.36581700000001,33.848114],"type":"Point"}
}