{
  "type": "Feature",
  "properties": {
    "addr:full":"8 Collier Rd NW Atlanta GA 30309",
    "addr:housenumber":"8",
    "addr:postcode":"30309",
    "addr:street":"Collier Rd Nw",
    "iso:country":"US",
    "sg:address":"8 Collier Rd NW",
    "sg:city":"Atlanta",
    "sg:classifiers":[
        {
            "category":"Professional",
            "type":"Services"
        }
    ],
    "sg:phone":"+1 404 351 9643",
    "sg:postcode":"30309",
    "sg:province":"GA",
    "wof:name":"Faux Fx",
    "wof:placetype":"venue"
},
  "geometry": {"coordinates":[-84.39391999999999,33.806717],"type":"Point"}
}