{
  "type": "Feature",
  "properties": {
    "addr:full":"308 S Broad St Butler GA 31006",
    "addr:housenumber":"308",
    "addr:postcode":"31006",
    "addr:street":"S Broad St",
    "iso:country":"US",
    "sg:address":"308 S Broad St",
    "sg:city":"Butler",
    "sg:classifiers":[
        {
            "category":"Professional",
            "subcategory":"Accounting & Tax Preparation",
            "type":"Services"
        }
    ],
    "sg:phone":"+1 478 987 0947",
    "sg:postcode":"31006",
    "sg:province":"GA",
    "sg:tags":[
        "return",
        "filing"
    ],
    "wof:name":"William A Amos",
    "wof:placetype":"venue"
},
  "geometry": {"coordinates":[-84.239414,32.553465],"type":"Point"}
}