{
  "type": "Feature",
  "properties": {
    "addr:full":"536 Hunt Station Dr Lawrenceville GA 30044",
    "addr:housenumber":"536",
    "addr:postcode":"30044",
    "addr:street":"Hunt Station Dr",
    "iso:country":"US",
    "sg:address":"536 Hunt Station Dr",
    "sg:city":"Lawrenceville",
    "sg:classifiers":[
        {
            "category":"Shopping",
            "subcategory":"Computers & Home Electronics",
            "type":"Retail Goods"
        }
    ],
    "sg:phone":"+1 770 978 4177",
    "sg:postcode":"30044",
    "sg:province":"GA",
    "wof:name":"Arabed Corp",
    "wof:placetype":"venue"
},
  "geometry": {"coordinates":[-84.076807,33.891737],"type":"Point"}
}