{
  "type": "Feature",
  "properties": {
    "addr:full":"8552 Jamestown Way Jonesboro GA 30238",
    "addr:housenumber":"8552",
    "addr:postcode":"30238",
    "addr:street":"Jamestown Way",
    "iso:country":"US",
    "sg:address":"8552 Jamestown Way",
    "sg:city":"Jonesboro",
    "sg:classifiers":[
        {
            "category":"Professional",
            "subcategory":"Management & Consulting",
            "type":"Services"
        }
    ],
    "sg:phone":"+1 770 473 4662",
    "sg:postcode":"30238",
    "sg:province":"GA",
    "sg:tags":[
        "aids",
        "primarily",
        "prevention"
    ],
    "wof:name":"Friends Stopping Aids Inc",
    "wof:placetype":"venue"
},
  "geometry": {"coordinates":[-84.414995,33.521437],"type":"Point"}
}