{
  "type": "Feature",
  "properties": {
    "iso:country":"US",
    "sg:address":"2990 Collier Dr NW",
    "sg:city":"Atlanta",
    "sg:classifiers":[
        {
            "category":"Retail",
            "subcategory":"Repair Shop",
            "type":"Services"
        },
        {
            "category":"Professional",
            "subcategory":"Detective & Security Services",
            "type":"Services"
        }
    ],
    "sg:phone":"+1 404 472 0900",
    "sg:postcode":"30318",
    "sg:province":"GA",
    "sg:tags":[
        "skip",
        "tracing",
        "bail",
        "bond"
    ],
    "wof:name":"B & B Bail Bonds",
    "wof:placetype":"venue"
},
  "geometry": {"coordinates":[-84.48484000000001,33.762874],"type":"Point"}
}