{
  "type": "Feature",
  "properties": {
    "addr:full":"300 N Highland Ave NE Ste B Atlanta GA 30307",
    "addr:housenumber":"300",
    "addr:postcode":"30307",
    "addr:street":"N Highland Ave Ne Ste B",
    "iso:country":"US",
    "sg:address":"300 N Highland Ave NE Ste B",
    "sg:city":"Atlanta",
    "sg:classifiers":[
        {
            "category":"Real Estate",
            "subcategory":"Real Estate Services",
            "type":"Services"
        },
        {
            "category":"Personal",
            "type":"Services"
        }
    ],
    "sg:phone":"+1 877 563 1987",
    "sg:postcode":"30307",
    "sg:province":"GA",
    "sg:tags":[
        "management",
        "property",
        "maintenance"
    ],
    "sg:website":"http://local.ingenio.com/Listings/Details.aspx?NUM=a%3a10323813%3a13%3a4859924%3a14%3a0%3a7",
    "wof:name":"Ritan Property Group, INC",
    "wof:placetype":"venue"
},
  "geometry": {"coordinates":[-84.358189,33.762841],"type":"Point"}
}