{
  "type": "Feature",
  "properties": {
    "iso:country":"US",
    "sg:address":"9 10th St",
    "sg:city":"Columbus",
    "sg:classifiers":[
        {
            "category":"Education",
            "subcategory":"Special Training",
            "type":"Public Place"
        }
    ],
    "sg:phone":"+1 706 324 2061",
    "sg:postcode":"31901",
    "sg:province":"GA",
    "sg:tags":[
        "school",
        "instruction",
        "art"
    ],
    "wof:name":"Lucas Studios",
    "wof:placetype":"venue"
},
  "geometry": {"coordinates":[-84.991846,32.464836],"type":"Point"}
}