{
  "type": "Feature",
  "properties": {
    "iso:country":"US",
    "sg:address":"151 Heinz Rd SE",
    "sg:city":"Calhoun",
    "sg:classifiers":[
        {
            "category":"Professional",
            "type":"Services"
        }
    ],
    "sg:phone":"+1 706 625 4640",
    "sg:postcode":"30701",
    "sg:province":"GA",
    "wof:name":"Stan L Brafford",
    "wof:placetype":"venue"
},
  "geometry": {"coordinates":[-84.872592,34.462236],"type":"Point"}
}