{
  "type": "Feature",
  "properties": {
    "iso:country":"US",
    "sg:address":"4015 Wetherburn Way",
    "sg:city":"Norcross",
    "sg:classifiers":[
        {
            "category":"Professional",
            "type":"Services"
        }
    ],
    "sg:phone":"+1 770 416 6592",
    "sg:postcode":"30092",
    "sg:province":"GA",
    "sg:tags":[
        "establishment"
    ],
    "wof:name":"G Barnes & Co Inc",
    "wof:placetype":"venue"
},
  "geometry": {"coordinates":[-84.25498399999999,33.966788],"type":"Point"}
}