{
  "type": "Feature",
  "properties": {
    "addr:full":"6449 Bowdens Pond Rd Dearing GA 30808",
    "addr:housenumber":"6449",
    "addr:postcode":"30808",
    "addr:street":"Bowdens Pond Rd",
    "iso:country":"US",
    "sg:address":"6449 Bowdens Pond Rd",
    "sg:city":"Dearing",
    "sg:classifiers":[
        {
            "category":"Farming",
            "subcategory":"Livestock Farm",
            "type":"Manufacturing & Wholesale Goods"
        }
    ],
    "sg:phone":"+1 706 595 8436",
    "sg:postcode":"30808",
    "sg:province":"GA",
    "sg:tags":[
        "beef",
        "feedlot",
        "cattle"
    ],
    "wof:name":"Green Top",
    "wof:placetype":"venue"
},
  "geometry": {"coordinates":[-82.38033799999999,33.326307],"type":"Point"}
}