{
  "type": "Feature",
  "properties": {
    "iso:country":"US",
    "sg:address":"236 Old Epps Bridge Rd",
    "sg:city":"Athens",
    "sg:classifiers":[
        {
            "category":"Travel",
            "subcategory":"Hotels & Motels",
            "type":"Entertainment"
        }
    ],
    "sg:phone":"+1 706 612 9100",
    "sg:postcode":"30606",
    "sg:province":"GA",
    "sg:tags":[
        "lodging"
    ],
    "sg:website":"http://www.countryinns.com/athensga",
    "wof:name":"Country Inn & Suites Athens",
    "wof:placetype":"venue"
},
  "geometry": {"coordinates":[-83.412144,33.949859],"type":"Point"}
}