{
  "type": "Feature",
  "properties": {
    "iso:country":"US",
    "sg:address":"416 Lake Joy Rd Apt B",
    "sg:city":"Kathleen",
    "sg:classifiers":[
        {
            "category":"Manufacturing",
            "subcategory":"Buildings",
            "type":"Manufacturing & Wholesale Goods"
        },
        {
            "category":"Building & Trades",
            "subcategory":"Construction",
            "type":"Services"
        }
    ],
    "sg:phone":"+1 478 987 0904",
    "sg:postcode":"31047",
    "sg:province":"GA",
    "sg:tags":[
        "home",
        "builder",
        "contractor"
    ],
    "wof:name":"Scott Builders",
    "wof:placetype":"venue"
},
  "geometry": {"coordinates":[-83.69105,32.518755],"type":"Point"}
}