{
  "type": "Feature",
  "properties": {
    "addr:full":"3220 Barnett Shoals Rd Athens GA 30605",
    "addr:housenumber":"3220",
    "addr:postcode":"30605",
    "addr:street":"Barnett Shoals Rd",
    "iso:country":"US",
    "sg:address":"3220 Barnett Shoals Rd",
    "sg:city":"Athens",
    "sg:classifiers":[
        {
            "category":"Education",
            "subcategory":"School",
            "type":"Public Place"
        }
    ],
    "sg:phone":"+1 706 357 5334",
    "sg:postcode":"30605",
    "sg:province":"GA",
    "sg:tags":[
        "executive"
    ],
    "sg:website":"www.ccsd.com",
    "wof:name":"Barnett Shoals Elementary Schl",
    "wof:placetype":"venue"
},
  "geometry": {"coordinates":[-83.335054,33.898758],"type":"Point"}
}