{
  "type": "Feature",
  "properties": {
    "iso:country":"US",
    "sg:address":"758 Gordon St",
    "sg:city":"Blackshear",
    "sg:classifiers":[
        {
            "category":"Professional",
            "type":"Services"
        }
    ],
    "sg:phone":"+1 912 449 5976",
    "sg:postcode":"31516",
    "sg:province":"GA",
    "sg:tags":[
        "establishment"
    ],
    "wof:name":"Suncoast Properties Inc",
    "wof:placetype":"venue"
},
  "geometry": {"coordinates":[-82.24225,31.312593],"type":"Point"}
}