{
  "type": "Feature",
  "properties": {
    "iso:country":"US",
    "sg:address":"12420 Cumming Hwy",
    "sg:city":"Canton",
    "sg:classifiers":[
        {
            "category":"Personal",
            "subcategory":"Beauty Salon",
            "type":"Services"
        }
    ],
    "sg:phone":"+1 678 455 7919",
    "sg:postcode":"30115",
    "sg:province":"GA",
    "sg:tags":[
        "shop"
    ],
    "wof:name":"Salon Lefaye",
    "wof:placetype":"venue"
},
  "geometry": {"coordinates":[-84.290964,34.238836],"type":"Point"}
}