{
  "type": "Feature",
  "properties": {
    "iso:country":"US",
    "sg:address":"444 Arabi Warwick Rd",
    "sg:city":"Arabi",
    "sg:classifiers":[
        {
            "category":"Farming",
            "subcategory":"Farm",
            "type":"Manufacturing & Wholesale Goods"
        }
    ],
    "sg:phone":"+1 229 273 5064",
    "sg:postcode":"31712",
    "sg:province":"GA",
    "wof:name":"Childers Farms",
    "wof:placetype":"venue"
},
  "geometry": {"coordinates":[-83.77002400000001,31.834909],"type":"Point"}
}