{
  "type": "Feature",
  "properties": {
    "addr:full":"107 Drennon Dr Jesup GA 31545",
    "addr:housenumber":"107",
    "addr:postcode":"31545",
    "addr:street":"Drennon Dr",
    "iso:country":"US",
    "sg:address":"107 Drennon Dr",
    "sg:city":"Jesup",
    "sg:classifiers":[
        {
            "category":"Health Services",
            "subcategory":"Doctor",
            "type":"Services"
        }
    ],
    "sg:phone":"+1 912 427 7072",
    "sg:postcode":"31545",
    "sg:province":"GA",
    "wof:name":"Gary A Lewis DDS PA",
    "wof:placetype":"venue"
},
  "geometry": {"coordinates":[-81.905152,31.606197],"type":"Point"}
}