{
  "type": "Feature",
  "properties": {
    "iso:country":"US",
    "sg:address":"4056 Wetherburn Way NW",
    "sg:city":"Norcross",
    "sg:classifiers":[
        {
            "category":"Building & Trades",
            "subcategory":"Construction",
            "type":"Services"
        }
    ],
    "sg:phone":"+1 770 449 5798",
    "sg:postcode":"30092",
    "sg:province":"GA",
    "sg:tags":[
        "specializing",
        "speculative",
        "general",
        "ho",
        "contractor"
    ],
    "wof:name":"J Patrick O'Donnell Inc",
    "wof:placetype":"venue"
},
  "geometry": {"coordinates":[-84.25512500000001,33.967796],"type":"Point"}
}