{
  "type": "Feature",
  "properties": {
    "iso:country":"US",
    "sg:address":"212 N 3rd Ave",
    "sg:city":"Chatsworth",
    "sg:classifiers":[
        {
            "category":"Wholesale",
            "subcategory":"Plants",
            "type":"Manufacturing & Wholesale Goods"
        },
        {
            "category":"Shopping",
            "subcategory":"Florist",
            "type":"Retail Goods"
        }
    ],
    "sg:phone":"+1 706 517 2747",
    "sg:postcode":"30705",
    "sg:province":"GA",
    "sg:tags":[
        "supply"
    ],
    "wof:name":"Pooh's Bridal Flowers & Gift",
    "wof:placetype":"venue"
},
  "geometry": {"coordinates":[-84.76952199999999,34.768681],"type":"Point"}
}