{
  "type": "Feature",
  "properties": {
    "addr:full":"7370 Hodgson Memorial Dr Savannah GA 31406",
    "addr:housenumber":"7370",
    "addr:postcode":"31406",
    "addr:street":"Hodgson Memorial Dr",
    "iso:country":"US",
    "sg:address":"7370 Hodgson Memorial Dr",
    "sg:city":"Savannah",
    "sg:classifiers":[
        {
            "category":"Wholesale",
            "subcategory":"Medical Equipment & Supplies",
            "type":"Manufacturing & Wholesale Goods"
        }
    ],
    "sg:phone":"+1 912 691 2103",
    "sg:postcode":"31406",
    "sg:province":"GA",
    "sg:tags":[
        "pharmaceutical"
    ],
    "wof:name":"Vital Healthcare LLC",
    "wof:placetype":"venue"
},
  "geometry": {"coordinates":[-81.11315999999999,32.001728],"type":"Point"}
}