{
  "type": "Feature",
  "properties": {
    "iso:country":"US",
    "sg:address":"332 Kinney Lake Rd",
    "sg:city":"Carrollton",
    "sg:classifiers":[
        {
            "category":"Building & Trades",
            "subcategory":"Equipment Rental",
            "type":"Services"
        }
    ],
    "sg:phone":"+1 770 459 8543",
    "sg:postcode":"30116",
    "sg:province":"GA",
    "wof:name":"Atlanta Arrow Aircraft Inc",
    "wof:placetype":"venue"
},
  "geometry": {"coordinates":[-84.961984,33.668594],"type":"Point"}
}