{
  "type": "Feature",
  "properties": {
    "iso:country":"US",
    "sg:address":"1151 Hammond Dr NE Ste 200 Studio 126",
    "sg:city":"Dunwoody",
    "sg:classifiers":[
        {
            "category":"Personal",
            "subcategory":"Beauty Salon",
            "type":"Services"
        }
    ],
    "sg:phone":"+1 770 361 3557",
    "sg:postcode":"30346",
    "sg:province":"GA",
    "sg:tags":[
        "hair"
    ],
    "wof:name":"Verrilli Hair Studio",
    "wof:placetype":"venue"
},
  "geometry": {"coordinates":[-84.342266,33.920527],"type":"Point"}
}