{
  "type": "Feature",
  "properties": {
    "iso:country":"US",
    "sg:address":"1029 Franklin Rd SE",
    "sg:city":"Marietta",
    "sg:classifiers":[
        {
            "category":"Professional",
            "subcategory":"Business Services",
            "type":"Services"
        }
    ],
    "sg:phone":"+1 770 799 1886",
    "sg:postcode":"30067",
    "sg:province":"GA",
    "wof:name":"T3 Technologies Inc",
    "wof:placetype":"venue"
},
  "geometry": {"coordinates":[-84.49411000000001,33.928595],"type":"Point"}
}