{
  "type": "Feature",
  "properties": {
    "iso:country":"US",
    "sg:address":"2362 Lawrenceville Hwy",
    "sg:city":"Decatur",
    "sg:classifiers":[
        {
            "category":"Social Services",
            "subcategory":"Child Care",
            "type":"Services"
        }
    ],
    "sg:phone":"+1 404 963 6350",
    "sg:postcode":"30033",
    "sg:province":"GA",
    "sg:tags":[
        "day"
    ],
    "wof:name":"Lawrenceville Hwy Early Childhood Development Ctr",
    "wof:placetype":"venue"
},
  "geometry": {"coordinates":[-84.26799800000001,33.816502],"type":"Point"}
}