{
  "type": "Feature",
  "properties": {
    "addr:full":"6400 Peachtree Industrial Blvd Atlanta GA 30360",
    "addr:housenumber":"6400",
    "addr:postcode":"30360",
    "addr:street":"Peachtree Industrial Blvd",
    "iso:country":"US",
    "sg:address":"6400 Peachtree Industrial Blvd",
    "sg:city":"Atlanta",
    "sg:classifiers":[
        {
            "category":"Food & Beverages",
            "subcategory":"Liquor & Beverages",
            "type":"Retail Goods"
        }
    ],
    "sg:phone":"+1 770 457 0272",
    "sg:postcode":"30360",
    "sg:province":"GA",
    "sg:tags":[
        "store"
    ],
    "wof:name":"Holiday Center",
    "wof:placetype":"venue"
},
  "geometry": {"coordinates":[-84.281158,33.92387],"type":"Point"}
}