{
  "type": "Feature",
  "properties": {
    "iso:country":"US",
    "sg:address":"1650 Whitesville St",
    "sg:city":"Lagrange",
    "sg:classifiers":[
        {
            "category":"Food & Beverages",
            "subcategory":"Groceries & Convenience Stores",
            "type":"Retail Goods"
        }
    ],
    "sg:phone":"+1 706 885 0055",
    "sg:postcode":"30240",
    "sg:province":"GA",
    "wof:name":"Jr Food Store",
    "wof:placetype":"venue"
},
  "geometry": {"coordinates":[-85.02913100000001,33.010765],"type":"Point"}
}