{
  "type": "Feature",
  "properties": {
    "iso:country":"US",
    "sg:address":"980 Hammond Dr NE",
    "sg:city":"Atlanta",
    "sg:classifiers":[
        {
            "category":"Professional",
            "type":"Services"
        }
    ],
    "sg:phone":"+1 770 352 2195",
    "sg:postcode":"30328",
    "sg:province":"GA",
    "sg:tags":[
        "establishment"
    ],
    "wof:name":"Edmc",
    "wof:placetype":"venue"
},
  "geometry": {"coordinates":[-84.357083,33.919002],"type":"Point"}
}