{
  "type": "Feature",
  "properties": {
    "iso:country":"US",
    "sg:address":"340 N Peachtree Pkwy",
    "sg:city":"Peachtree City",
    "sg:classifiers":[
        {
            "category":"Retail",
            "subcategory":"Portrait Studio",
            "type":"Services"
        },
        {
            "category":"Professional",
            "subcategory":"Art Services",
            "type":"Services"
        }
    ],
    "sg:phone":"+1 770 486 5407",
    "sg:postcode":"30269",
    "sg:province":"GA",
    "sg:tags":[
        "photographer",
        "photography",
        "store"
    ],
    "wof:name":"Photographic Concepts",
    "wof:placetype":"venue"
},
  "geometry": {"coordinates":[-84.566704,33.417447],"type":"Point"}
}