{
  "type": "Feature",
  "properties": {
    "addr:full":"5408 Odum Smallwood Rd Gainesville GA 30506",
    "addr:housenumber":"5408",
    "addr:postcode":"30506",
    "addr:street":"Odum Smallwood Rd",
    "iso:country":"US",
    "sg:address":"5408 Odum Smallwood Rd",
    "sg:city":"Gainesville",
    "sg:classifiers":[
        {
            "category":"Farming",
            "subcategory":"Farm",
            "type":"Manufacturing & Wholesale Goods"
        }
    ],
    "sg:phone":"+1 770 983 3495",
    "sg:postcode":"30506",
    "sg:province":"GA",
    "sg:tags":[
        "crop",
        "general"
    ],
    "wof:name":"Smallwood Farms",
    "wof:placetype":"venue"
},
  "geometry": {"coordinates":[-83.82937800000001,34.437942],"type":"Point"}
}