{
  "type": "Feature",
  "properties": {
    "iso:country":"US",
    "sg:address":"100 Gadson St",
    "sg:city":"Rome",
    "sg:classifiers":[
        {
            "category":"Social Services",
            "subcategory":"Child Care",
            "type":"Services"
        }
    ],
    "sg:phone":"+1 706 234 0594",
    "sg:postcode":"30165",
    "sg:province":"GA",
    "sg:tags":[
        "day"
    ],
    "wof:name":"Boys & Girls Club of Romes",
    "wof:placetype":"venue"
},
  "geometry": {"coordinates":[-85.203442,34.268062],"type":"Point"}
}