{
  "type": "Feature",
  "properties": {
    "iso:country":"US",
    "sg:address":"4120 Pinnacle Pines Ct",
    "sg:city":"Hephzibah",
    "sg:classifiers":[
        {
            "category":"Organizations",
            "subcategory":"Religious Organization",
            "type":"Services"
        }
    ],
    "sg:phone":"+1 706 793 7003",
    "sg:postcode":"30815",
    "sg:province":"GA",
    "wof:name":"Johnnie Bussey Rev",
    "wof:placetype":"venue"
},
  "geometry": {"coordinates":[-82.096626,33.382594],"type":"Point"}
}