{
  "type": "Feature",
  "properties": {
    "iso:country":"US",
    "sg:address":"2077 Chestnut Hill Cir",
    "sg:city":"Decatur",
    "sg:classifiers":[
        {
            "category":"Wholesale",
            "subcategory":"Home Furnishings",
            "type":"Manufacturing & Wholesale Goods"
        }
    ],
    "sg:phone":"+1 404 284 9036",
    "sg:postcode":"30032",
    "sg:province":"GA",
    "sg:tags":[
        "manufacturer",
        "baskets-wholesale"
    ],
    "wof:name":"Beautiful Baskets",
    "wof:placetype":"venue"
},
  "geometry": {"coordinates":[-84.241863,33.7292],"type":"Point"}
}