{
  "type": "Feature",
  "properties": {
    "addr:full":"7045 Holmesville Rd Screven GA 31560",
    "addr:housenumber":"7045",
    "addr:postcode":"31560",
    "addr:street":"Holmesville Rd",
    "iso:country":"US",
    "sg:address":"7045 Holmesville Rd",
    "sg:city":"Screven",
    "sg:classifiers":[
        {
            "category":"Farming",
            "subcategory":"Farm",
            "type":"Manufacturing & Wholesale Goods"
        }
    ],
    "sg:phone":"+1 912 367 1410",
    "sg:postcode":"31560",
    "sg:province":"GA",
    "wof:name":"Sidney Wildes Farm",
    "wof:placetype":"venue"
},
  "geometry": {"coordinates":[-82.03241800000001,31.622276],"type":"Point"}
}