{
  "type": "Feature",
  "properties": {
    "addr:full":"3509 Prince Rd Augusta GA 30906",
    "addr:housenumber":"3509",
    "addr:postcode":"30906",
    "addr:street":"Prince Rd",
    "iso:country":"US",
    "sg:address":"3509 Prince Rd",
    "sg:city":"Augusta",
    "sg:classifiers":[
        {
            "category":"Organizations",
            "subcategory":"Religious Organization",
            "type":"Services"
        }
    ],
    "sg:phone":"+1 706 560 0019",
    "sg:postcode":"30906",
    "sg:province":"GA",
    "sg:tags":[
        "church"
    ],
    "wof:name":"Origional Church of God",
    "wof:placetype":"venue"
},
  "geometry": {"coordinates":[-82.061414,33.401291],"type":"Point"}
}