{
  "type": "Feature",
  "properties": {
    "iso:country":"US",
    "sg:address":"1950 Century Blvd NE",
    "sg:city":"Atlanta",
    "sg:classifiers":[
        {
            "category":"Banks & Credit Unions",
            "subcategory":"Investment Brokerage",
            "type":"Services"
        },
        {
            "category":"Insurance",
            "subcategory":"Insurance Agent",
            "type":"Services"
        }
    ],
    "sg:phone":"+1 404 321 6950",
    "sg:postcode":"30345",
    "sg:province":"GA",
    "sg:tags":[
        "consultant",
        "life",
        "planning",
        "financial",
        "health"
    ],
    "sg:website":"www.hintonmccurry.com",
    "wof:name":"Hinton Mc Curry Financial Inc",
    "wof:placetype":"venue"
},
  "geometry": {"coordinates":[-84.310158,33.845404],"type":"Point"}
}