{
  "type": "Feature",
  "properties": {
    "addr:full":"415 Ridgewood Dr Fayetteville GA 30215",
    "addr:housenumber":"415",
    "addr:postcode":"30215",
    "addr:street":"Ridgewood Dr",
    "iso:country":"US",
    "sg:address":"415 Ridgewood Dr",
    "sg:city":"Fayetteville",
    "sg:classifiers":[
        {
            "category":"Professional",
            "type":"Services"
        }
    ],
    "sg:phone":"+1 770 716 7602",
    "sg:postcode":"30215",
    "sg:province":"GA",
    "wof:name":"Jaymin B Patel",
    "wof:placetype":"venue"
},
  "geometry": {"coordinates":[-84.485794,33.425112],"type":"Point"}
}