{
  "type": "Feature",
  "properties": {
    "addr:full":"1521 Eryn Cir Suwanee GA 30024",
    "addr:housenumber":"1521",
    "addr:postcode":"30024",
    "addr:street":"Eryn Cir",
    "iso:country":"US",
    "sg:address":"1521 Eryn Cir",
    "sg:city":"Suwanee",
    "sg:classifiers":[
        {
            "category":"Arts & Performance",
            "subcategory":"Theater",
            "type":"Entertainment"
        }
    ],
    "sg:phone":"+1 770 497 0520",
    "sg:postcode":"30024",
    "sg:province":"GA",
    "sg:tags":[
        "entertainer"
    ],
    "wof:name":"Class Act Band",
    "wof:placetype":"venue"
},
  "geometry": {"coordinates":[-84.093254,34.023223],"type":"Point"}
}