{
  "type": "Feature",
  "properties": {
    "addr:full":"950 Dannon Vw SW Ste 4101 Atlanta GA 30331",
    "addr:housenumber":"950",
    "addr:postcode":"30331",
    "addr:street":"Dannon Vw Sw Ste 4101",
    "iso:country":"US",
    "sg:address":"950 Dannon Vw SW Ste 4101",
    "sg:city":"Atlanta",
    "sg:classifiers":[
        {
            "category":"Health Services",
            "subcategory":"Doctor",
            "type":"Services"
        }
    ],
    "sg:phone":"+1 404 629 5550",
    "sg:postcode":"30331",
    "sg:province":"GA",
    "sg:tags":[
        "psychiatrist"
    ],
    "wof:name":"Cascade Medical Group",
    "wof:placetype":"venue"
},
  "geometry": {"coordinates":[-84.50861500000001,33.721732],"type":"Point"}
}