{
  "type": "Feature",
  "properties": {
    "addr:full":"18 N Kimball St Forsyth GA 31029",
    "addr:housenumber":"18",
    "addr:postcode":"31029",
    "addr:street":"N Kimball St",
    "iso:country":"US",
    "sg:address":"18 N Kimball St",
    "sg:city":"Forsyth",
    "sg:classifiers":[
        {
            "category":"Personal",
            "subcategory":"Beauty Salon",
            "type":"Services"
        }
    ],
    "sg:phone":"+1 478 994 6587",
    "sg:postcode":"31029",
    "sg:province":"GA",
    "sg:tags":[
        "shop"
    ],
    "wof:name":"His & Hers Styles",
    "wof:placetype":"venue"
},
  "geometry": {"coordinates":[-83.93762599999999,33.034926],"type":"Point"}
}