{
  "type": "Feature",
  "properties": {
    "addr:full":"408 Railroad St W Douglas GA 31533",
    "addr:housenumber":"408",
    "addr:postcode":"31533",
    "addr:street":"Railroad St W",
    "iso:country":"US",
    "sg:address":"408 Railroad St W",
    "sg:city":"Douglas",
    "sg:classifiers":[
        {
            "category":"Shopping",
            "subcategory":"Party Supplies",
            "type":"Retail Goods"
        },
        {
            "category":"Shopping",
            "subcategory":"Bridal",
            "type":"Retail Goods"
        }
    ],
    "sg:phone":"+1 912 384 0805",
    "sg:postcode":"31533",
    "sg:province":"GA",
    "sg:tags":[
        "shop",
        "wedding"
    ],
    "wof:name":"Erma's Bridal & Gift",
    "wof:placetype":"venue"
},
  "geometry": {"coordinates":[-82.851546,31.505195],"type":"Point"}
}