{
  "type": "Feature",
  "properties": {
    "iso:country":"US",
    "sg:address":"205 Rigsbee Dr",
    "sg:city":"Vidalia",
    "sg:classifiers":[
        {
            "category":"Insurance",
            "subcategory":"Insurance Agent",
            "type":"Services"
        }
    ],
    "sg:phone":"+1 912 537 3628",
    "sg:postcode":"30474",
    "sg:province":"GA",
    "wof:name":"State Farm Insurance",
    "wof:placetype":"venue"
},
  "geometry": {"coordinates":[-82.394986,32.210458],"type":"Point"}
}