{
  "type": "Feature",
  "properties": {
    "addr:full":"308 Legion Dr Eastman GA 31023",
    "addr:housenumber":"308",
    "addr:postcode":"31023",
    "addr:street":"Legion Dr",
    "iso:country":"US",
    "sg:address":"308 Legion Dr",
    "sg:city":"Eastman",
    "sg:classifiers":[
        {
            "category":"Government",
            "subcategory":"Office",
            "type":"Public Place"
        }
    ],
    "sg:phone":"+1 478 374 6984",
    "sg:postcode":"31023",
    "sg:province":"GA",
    "sg:tags":[
        "state",
        "security"
    ],
    "wof:name":"National Guard Recruiter",
    "wof:placetype":"venue"
},
  "geometry": {"coordinates":[-83.182709,32.190281],"type":"Point"}
}