{
  "type": "Feature",
  "properties": {
    "addr:full":"1000 Southlake Mall Morrow GA 30260",
    "addr:housenumber":"1000",
    "addr:postcode":"30260",
    "addr:street":"Southlake Mall",
    "iso:country":"US",
    "sg:address":"1000 Southlake Mall",
    "sg:city":"Morrow",
    "sg:classifiers":[
        {
            "category":"Retail",
            "subcategory":"Auto Repair",
            "type":"Services"
        }
    ],
    "sg:phone":"+1 678 422 4926",
    "sg:postcode":"30260",
    "sg:province":"GA",
    "sg:tags":[
        "body",
        "automobile",
        "painting"
    ],
    "wof:name":"Body Shop Of America Inc",
    "wof:placetype":"venue"
},
  "geometry": {"coordinates":[-84.35478999999999,33.573584],"type":"Point"}
}