{
  "type": "Feature",
  "properties": {
    "addr:full":"3312 Piedmont Rd NE Atlanta GA 30305",
    "addr:housenumber":"3312",
    "addr:postcode":"30305",
    "addr:street":"Piedmont Rd Ne",
    "iso:country":"US",
    "sg:address":"3312 Piedmont Rd NE",
    "sg:city":"Atlanta",
    "sg:classifiers":[
        {
            "category":"Health Services",
            "subcategory":"Doctor",
            "type":"Services"
        }
    ],
    "sg:phone":"+1 404 233 1102",
    "sg:postcode":"30305",
    "sg:province":"GA",
    "wof:name":"Cann Roberta D DMD",
    "wof:placetype":"venue"
},
  "geometry": {"coordinates":[-84.374196,33.848513],"type":"Point"}
}