{
  "type": "Feature",
  "properties": {
    "iso:country":"US",
    "sg:address":"9250 Homewood Dr",
    "sg:city":"Riverdale",
    "sg:classifiers":[
        {
            "category":"Professional",
            "subcategory":"Business Services",
            "type":"Services"
        }
    ],
    "sg:phone":"+1 404 428 1096",
    "sg:postcode":"30274",
    "sg:province":"GA",
    "wof:name":"Art Stone Design Installation",
    "wof:placetype":"venue"
},
  "geometry": {"coordinates":[-84.400733,33.51814],"type":"Point"}
}