{
  "type": "Feature",
  "properties": {
    "addr:full":"333 Hartwell St Royston GA 30662",
    "addr:housenumber":"333",
    "addr:postcode":"30662",
    "addr:street":"Hartwell St",
    "iso:country":"US",
    "sg:address":"333 Hartwell St",
    "sg:city":"Royston",
    "sg:classifiers":[
        {
            "category":"Retail",
            "subcategory":"Auto Repair",
            "type":"Services"
        }
    ],
    "sg:phone":"+1 706 246 9038",
    "sg:postcode":"30662",
    "sg:province":"GA",
    "sg:tags":[
        "body",
        "automobile",
        "painting",
        "repairing"
    ],
    "wof:name":"Parten & Son Paint & Body Shop Inc",
    "wof:placetype":"venue"
},
  "geometry": {"coordinates":[-83.10412100000001,34.287186],"type":"Point"}
}