{
  "type": "Feature",
  "properties": {
    "addr:full":"137 E Bacon St Pembroke GA 31321",
    "addr:housenumber":"137",
    "addr:postcode":"31321",
    "addr:street":"E Bacon St",
    "iso:country":"US",
    "sg:address":"137 E Bacon St",
    "sg:city":"Pembroke",
    "sg:classifiers":[
        {
            "category":"Shopping",
            "subcategory":"Gifts & Souvenirs",
            "type":"Retail Goods"
        },
        {
            "category":"Shopping",
            "subcategory":"Pharmacy",
            "type":"Retail Goods"
        }
    ],
    "sg:phone":"+1 912 653 2772",
    "sg:postcode":"31321",
    "sg:province":"GA",
    "sg:tags":[
        "shop"
    ],
    "wof:name":"Leader Drug Store",
    "wof:placetype":"venue"
},
  "geometry": {"coordinates":[-81.62203700000001,32.135786],"type":"Point"}
}