{
  "type": "Feature",
  "properties": {
    "iso:country":"US",
    "sg:address":"3112 E Park Ave",
    "sg:city":"Brunswick",
    "sg:classifiers":[
        {
            "category":"Social Services",
            "type":"Services"
        }
    ],
    "sg:phone":"+1 912 264 3058",
    "sg:postcode":"31520",
    "sg:province":"GA",
    "sg:tags":[
        "crisis",
        "intervention"
    ],
    "wof:name":"Rape Crisis Ctr",
    "wof:placetype":"venue"
},
  "geometry": {"coordinates":[-81.487315,31.175056],"type":"Point"}
}