{
  "type": "Feature",
  "properties": {
    "addr:full":"2401 Nottingham Way Albany GA 31707",
    "addr:housenumber":"2401",
    "addr:postcode":"31707",
    "addr:street":"Nottingham Way",
    "iso:country":"US",
    "sg:address":"2401 Nottingham Way",
    "sg:city":"Albany",
    "sg:classifiers":[
        {
            "category":"Professional",
            "type":"Services"
        }
    ],
    "sg:phone":"+1 229 438 7956",
    "sg:postcode":"31707",
    "sg:province":"GA",
    "wof:name":"Douglas Vicky",
    "wof:placetype":"venue"
},
  "geometry": {"coordinates":[-84.20420300000001,31.611974],"type":"Point"}
}