{
  "type": "Feature",
  "properties": {
    "addr:full":"4912 Bill Gardner Pkwy Locust Grove GA 30248",
    "addr:housenumber":"4912",
    "addr:postcode":"30248",
    "addr:street":"Bill Gardner Pkwy",
    "iso:country":"US",
    "sg:address":"4912 Bill Gardner Pkwy",
    "sg:city":"Locust Grove",
    "sg:classifiers":[
        {
            "category":"Food & Beverages",
            "subcategory":"Groceries & Convenience Stores",
            "type":"Retail Goods"
        }
    ],
    "sg:phone":"+1 770 898 7801",
    "sg:postcode":"30248",
    "sg:province":"GA",
    "wof:name":"S K Convenience",
    "wof:placetype":"venue"
},
  "geometry": {"coordinates":[-84.113955,33.35339],"type":"Point"}
}