{
  "type": "Feature",
  "properties": {
    "addr:full":"829 Pinehurst Dr Woodstock GA 30188",
    "addr:housenumber":"829",
    "addr:postcode":"30188",
    "addr:street":"Pinehurst Dr",
    "iso:country":"US",
    "sg:address":"829 Pinehurst Dr",
    "sg:city":"Woodstock",
    "sg:classifiers":[
        {
            "category":"Building & Trades",
            "subcategory":"Landscaping Services",
            "type":"Services"
        }
    ],
    "sg:phone":"+1 770 928 4448",
    "sg:postcode":"30188",
    "sg:province":"GA",
    "wof:name":"Fairway Lawn Services Inc",
    "wof:placetype":"venue"
},
  "geometry": {"coordinates":[-84.450396,34.131123],"type":"Point"}
}