{
  "type": "Feature",
  "properties": {
    "iso:country":"US",
    "sg:address":"241 Blanton Ave",
    "sg:city":"Griffin",
    "sg:classifiers":[
        {
            "category":"Organizations",
            "subcategory":"Professional Association",
            "type":"Services"
        }
    ],
    "sg:phone":"+1 770 233 3321",
    "sg:postcode":"30223",
    "sg:province":"GA",
    "wof:name":"Spalding Basketball Assn",
    "wof:placetype":"venue"
},
  "geometry": {"coordinates":[-84.25823,33.260564],"type":"Point"}
}