{
  "type": "Feature",
  "properties": {
    "iso:country":"US",
    "sg:address":"305 Larry Dr",
    "sg:city":"Ringgold",
    "sg:classifiers":[
        {
            "category":"Home & Garden",
            "subcategory":"Building Materials",
            "type":"Retail Goods"
        }
    ],
    "sg:phone":"+1 706 891 0128",
    "sg:postcode":"30736",
    "sg:province":"GA",
    "wof:name":"Bill R Linda D Foxworth",
    "wof:placetype":"venue"
},
  "geometry": {"coordinates":[-85.18632599999999,34.969353],"type":"Point"}
}