{
  "type": "Feature",
  "properties": {
    "addr:full":"1315 Old Woodbine Rd NE Atlanta GA 30319",
    "addr:housenumber":"1315",
    "addr:postcode":"30319",
    "addr:street":"Old Woodbine Rd Ne",
    "iso:country":"US",
    "sg:address":"1315 Old Woodbine Rd NE",
    "sg:city":"Atlanta",
    "sg:classifiers":[
        {
            "category":"Farming",
            "subcategory":"Orchard",
            "type":"Manufacturing & Wholesale Goods"
        },
        {
            "category":"Food & Beverages",
            "subcategory":"Specialty",
            "type":"Retail Goods"
        },
        {
            "category":"Shopping",
            "subcategory":"Gifts & Souvenirs",
            "type":"Retail Goods"
        },
        {
            "category":"Food & Beverages",
            "subcategory":"Chocolate",
            "type":"Retail Goods"
        },
        {
            "category":"Coffee & Tea",
            "type":"Food & Drink"
        }
    ],
    "sg:phone":"+1 404 992 5775",
    "sg:postcode":"30319",
    "sg:province":"GA",
    "sg:tags":[
        "shop",
        "gourmet",
        "cocoa",
        "basket",
        "flowers-preserved"
    ],
    "sg:website":"http://www.giftbasketforme.com",
    "wof:name":"Gift Basket For Me",
    "wof:placetype":"venue"
},
  "geometry": {"coordinates":[-84.348899,33.885306],"type":"Point"}
}