{
  "type": "Feature",
  "properties": {
    "iso:country":"US",
    "sg:address":"85 Bermuda Run Dr",
    "sg:city":"Covington",
    "sg:classifiers":[
        {
            "category":"Professional",
            "type":"Services"
        }
    ],
    "sg:phone":"+1 678 342 7893",
    "sg:postcode":"30016",
    "sg:province":"GA",
    "wof:name":"B & B Petroleum System Svcs",
    "wof:placetype":"venue"
},
  "geometry": {"coordinates":[-83.932873,33.596328],"type":"Point"}
}