{
  "type": "Feature",
  "properties": {
    "addr:full":"605 2nd St W Tifton GA 31794",
    "addr:housenumber":"605",
    "addr:postcode":"31794",
    "addr:street":"2Nd St W",
    "iso:country":"US",
    "sg:address":"605 2nd St W",
    "sg:city":"Tifton",
    "sg:classifiers":[
        {
            "category":"Banks & Credit Unions",
            "subcategory":"Bank",
            "type":"Services"
        }
    ],
    "sg:phone":"+1 229 386 2265",
    "sg:postcode":"31794",
    "sg:province":"GA",
    "wof:name":"Colony Bank Worth",
    "wof:placetype":"venue"
},
  "geometry": {"coordinates":[-83.519809,31.457734],"type":"Point"}
}