{
  "type": "Feature",
  "properties": {
    "addr:full":"600 Embassy Row NE # 500 Atlanta GA 30328",
    "addr:housenumber":"600",
    "addr:postcode":"30328",
    "addr:street":"Embassy Row Ne # 500",
    "iso:country":"US",
    "sg:address":"600 Embassy Row NE # 500",
    "sg:city":"Atlanta",
    "sg:classifiers":[
        {
            "category":"Manufacturing",
            "subcategory":"Electronics",
            "type":"Manufacturing & Wholesale Goods"
        },
        {
            "category":"Shopping",
            "subcategory":"Computers & Home Electronics",
            "type":"Retail Goods"
        }
    ],
    "sg:phone":"+1 770 379 2861",
    "sg:postcode":"30328",
    "sg:province":"GA",
    "sg:tags":[
        "supplies-wholesale",
        "manufacturer",
        "electronic",
        "consumer",
        "equipment"
    ],
    "sg:website":"http://www.gte.com",
    "wof:name":"Verizon",
    "wof:placetype":"venue"
},
  "geometry": {"coordinates":[-84.35575799999999,33.938932],"type":"Point"}
}