{
  "type": "Feature",
  "properties": {
    "addr:full":"511 N Peterson Ave Douglas GA 31533",
    "addr:housenumber":"511",
    "addr:postcode":"31533",
    "addr:street":"N Peterson Ave",
    "iso:country":"US",
    "sg:address":"511 N Peterson Ave",
    "sg:city":"Douglas",
    "sg:classifiers":[
        {
            "category":"Health Services",
            "subcategory":"Clinic",
            "type":"Services"
        }
    ],
    "sg:phone":"+1 912 383 6636",
    "sg:postcode":"31533",
    "sg:province":"GA",
    "sg:tags":[
        "organization",
        "medical",
        "surgical"
    ],
    "wof:name":"Diagnostic Imaging Of South Ga",
    "wof:placetype":"venue"
},
  "geometry": {"coordinates":[-82.850632,31.514097],"type":"Point"}
}