{
  "type": "Feature",
  "properties": {
    "addr:full":"3833 Roswell Rd Ste 114 Atlanta GA 30342",
    "addr:housenumber":"3833",
    "addr:postcode":"30342",
    "addr:street":"Roswell Rd Ste 114",
    "iso:country":"US",
    "sg:address":"3833 Roswell Rd Ste 114",
    "sg:city":"Atlanta",
    "sg:classifiers":[
        {
            "category":"Professional",
            "subcategory":"Credit Reporting & Collection",
            "type":"Services"
        }
    ],
    "sg:phone":"+1 404 231 3791",
    "sg:postcode":"30342",
    "sg:province":"GA",
    "sg:tags":[
        "agency",
        "investigator"
    ],
    "wof:name":"Sterling Associates Inc",
    "wof:placetype":"venue"
},
  "geometry": {"coordinates":[-84.380591,33.859768],"type":"Point"}
}