{
  "type": "Feature",
  "properties": {
    "iso:country":"US",
    "sg:address":"1848 Old Norcross Rd",
    "sg:city":"Lawrenceville",
    "sg:classifiers":[
        {
            "category":"Museum",
            "type":"Entertainment"
        }
    ],
    "sg:phone":"+1 678 226 2040",
    "sg:postcode":"30044",
    "sg:province":"GA",
    "sg:tags":[
        "organization",
        "arts",
        "information"
    ],
    "wof:name":"Sylvia African Arts",
    "wof:placetype":"venue"
},
  "geometry": {"coordinates":[-84.059573,33.951871],"type":"Point"}
}