{
  "type": "Feature",
  "properties": {
    "iso:country":"US",
    "sg:address":"1360 Highway 85 N",
    "sg:city":"Fayetteville",
    "sg:classifiers":[
        {
            "category":"Building & Trades",
            "subcategory":"Locksmith",
            "type":"Services"
        }
    ],
    "sg:phone":"+1 678 269 6056",
    "sg:postcode":"30214",
    "sg:province":"GA",
    "sg:tags":[
        "key"
    ],
    "wof:name":"Universal Emergency Locksmith",
    "wof:placetype":"venue"
},
  "geometry": {"coordinates":[-84.441464,33.474587],"type":"Point"}
}