{
  "type": "Feature",
  "properties": {
    "addr:full":"4260 Communications Dr Norcross GA 30093",
    "addr:postcode":"4260;30093",
    "addr:street":"Communications Dr",
    "iso:country":"US",
    "sg:address":"4260 Communications Dr",
    "sg:city":"Norcross",
    "sg:classifiers":[
        {
            "category":"Wholesale",
            "subcategory":"Machinery & Supplies",
            "type":"Manufacturing & Wholesale Goods"
        }
    ],
    "sg:phone":"+1 770 381 4999",
    "sg:postcode":"30093",
    "sg:province":"GA",
    "sg:tags":[
        "equipment",
        "industrial",
        "mfg"
    ],
    "sg:website":"www.crown.com",
    "wof:name":"Crown Lift Trucks",
    "wof:placetype":"venue"
},
  "geometry": {"coordinates":[-84.147066,33.936824],"type":"Point"}
}