{
  "type": "Feature",
  "properties": {
    "iso:country":"US",
    "sg:address":"2690 Mount Vernon Road",
    "sg:city":"Atlanta",
    "sg:classifiers":[
        {
            "category":"Organizations",
            "subcategory":"Religious Organization",
            "type":"Services"
        }
    ],
    "sg:phone":"+1 770 399 0660",
    "sg:postcode":"30338",
    "sg:province":"GA",
    "wof:name":"Life Center Ministries",
    "wof:placetype":"venue"
},
  "geometry": {"coordinates":[-84.293172,33.954168],"type":"Point"}
}