{
  "type": "Feature",
  "properties": {
    "iso:country":"US",
    "sg:address":"279 Powers Ferry Rd SE",
    "sg:city":"Marietta",
    "sg:classifiers":[
        {
            "category":"Shopping",
            "subcategory":"Music",
            "type":"Retail Goods"
        }
    ],
    "sg:phone":"+1 770 565 0677",
    "sg:postcode":"30067",
    "sg:province":"GA",
    "sg:tags":[
        "game",
        "disc",
        "tape",
        "video",
        "rental",
        "cassette"
    ],
    "wof:name":"Jhankar Videos",
    "wof:placetype":"venue"
},
  "geometry": {"coordinates":[-84.498497,33.9454],"type":"Point"}
}