{
  "type": "Feature",
  "properties": {
    "addr:full":"2800 Main St W Snellville GA 30078",
    "addr:housenumber":"2800",
    "addr:postcode":"30078",
    "addr:street":"Main St W",
    "iso:country":"US",
    "sg:address":"2800 Main St W",
    "sg:city":"Snellville",
    "sg:classifiers":[
        {
            "category":"Health Services",
            "subcategory":"Doctor",
            "type":"Services"
        }
    ],
    "sg:phone":"+1 770 979 2600",
    "sg:postcode":"30078",
    "sg:province":"GA",
    "wof:name":"Zaman Pediatric Center",
    "wof:placetype":"venue"
},
  "geometry": {"coordinates":[-84.03089900000001,33.8545],"type":"Point"}
}