{
  "type": "Feature",
  "properties": {
    "iso:country":"US",
    "sg:address":"2258 Wrightsboro Rd",
    "sg:city":"Augusta",
    "sg:classifiers":[
        {
            "category":"Health Services",
            "subcategory":"Doctor",
            "type":"Services"
        }
    ],
    "sg:phone":"+1 706 736 2273",
    "sg:postcode":"30904",
    "sg:province":"GA",
    "sg:tags":[
        "physician",
        "medical",
        "surgeons",
        "internal",
        "medicine",
        "surgeon"
    ],
    "wof:name":"Augusta Internal Medicine",
    "wof:placetype":"venue"
},
  "geometry": {"coordinates":[-82.017616,33.467659],"type":"Point"}
}