{
  "type": "Feature",
  "properties": {
    "iso:country":"US",
    "sg:address":"6315 Robins Trce",
    "sg:city":"Stone Mountain",
    "sg:classifiers":[
        {
            "category":"Real Estate",
            "subcategory":"Real Estate Agent",
            "type":"Services"
        }
    ],
    "sg:phone":"+1 404 216 0483",
    "sg:postcode":"30087",
    "sg:province":"GA",
    "wof:name":"Zacharys Property Management",
    "wof:placetype":"venue"
},
  "geometry": {"coordinates":[-84.12989,33.769169],"type":"Point"}
}