{
  "type": "Feature",
  "properties": {
    "iso:country":"US",
    "sg:address":"1168 Atcheson Ln",
    "sg:city":"Atlanta",
    "sg:classifiers":[
        {
            "category":"Organizations",
            "subcategory":"Membership Organization",
            "type":"Services"
        }
    ],
    "sg:phone":"+1 770 394 2839",
    "sg:postcode":"30338",
    "sg:province":"GA",
    "wof:name":"Chinese American Cultural Inst",
    "wof:placetype":"venue"
},
  "geometry": {"coordinates":[-84.34117500000001,33.941289],"type":"Point"}
}