{
  "type": "Feature",
  "properties": {
    "iso:country":"US",
    "sg:address":"576 Main St",
    "sg:city":"Palmetto",
    "sg:classifiers":[
        {
            "category":"Home & Garden",
            "subcategory":"Garden Supply",
            "type":"Retail Goods"
        }
    ],
    "sg:phone":"+1 770 463 3156",
    "sg:postcode":"30268",
    "sg:province":"GA",
    "sg:tags":[
        "lawn",
        "mower"
    ],
    "sg:website":"www.jackpeekssales.com",
    "wof:name":"Jack Peek's Sales",
    "wof:placetype":"venue"
},
  "geometry": {"coordinates":[-84.670906,33.509806],"type":"Point"}
}