{
  "type": "Feature",
  "properties": {
    "iso:country":"US",
    "sg:address":"4920 Canyon Lake Dr",
    "sg:city":"Atlanta",
    "sg:classifiers":[
        {
            "category":"Health Services",
            "subcategory":"Doctor",
            "type":"Services"
        }
    ],
    "sg:phone":"+1 404 753 8915",
    "sg:postcode":"30349",
    "sg:province":"GA",
    "sg:tags":[
        "medical"
    ],
    "wof:name":"Otis Powell Dr",
    "wof:placetype":"venue"
},
  "geometry": {"coordinates":[-84.546893,33.643649],"type":"Point"}
}