{
  "type": "Feature",
  "properties": {
    "addr:full":"4052 W Cove Rd Chickamauga GA 30707",
    "addr:housenumber":"4052",
    "addr:postcode":"30707",
    "addr:street":"W Cove Rd",
    "iso:country":"US",
    "sg:address":"4052 W Cove Rd",
    "sg:city":"Chickamauga",
    "sg:classifiers":[
        {
            "category":"Shopping",
            "type":"Retail Goods"
        }
    ],
    "sg:phone":"+1 706 539 2216",
    "sg:postcode":"30707",
    "sg:province":"GA",
    "sg:tags":[
        "wedding",
        "supply"
    ],
    "wof:name":"Butterflies From Fragrant",
    "wof:placetype":"venue"
},
  "geometry": {"coordinates":[-85.426306,34.715768],"type":"Point"}
}