{
  "type": "Feature",
  "properties": {
    "addr:full":"10620 State Rte 52 Chatsworth GA 30705",
    "addr:housenumber":"10620",
    "addr:postcode":"30705",
    "addr:street":"State Rte 52",
    "iso:country":"US",
    "sg:address":"10620 State Rte 52",
    "sg:city":"Chatsworth",
    "sg:classifiers":[
        {
            "category":"Professional",
            "subcategory":"Lawyer & Legal Services",
            "type":"Services"
        }
    ],
    "sg:phone":"+1 706 695 7780",
    "sg:postcode":"30705",
    "sg:province":"GA",
    "sg:tags":[
        "attorney"
    ],
    "wof:name":"John T Longino Law Office",
    "wof:placetype":"venue"
},
  "geometry": {"coordinates":[-84.653842,34.775741],"type":"Point"}
}