{
  "type": "Feature",
  "properties": {
    "addr:full":"666 Herman Tanner Pl Roswell GA 30044",
    "addr:housenumber":"666",
    "addr:postcode":"30044",
    "addr:street":"Herman Tanner Pl",
    "iso:country":"US",
    "sg:address":"666 Herman Tanner Pl",
    "sg:city":"Roswell",
    "sg:classifiers":[
        {
            "category":"Restaurant",
            "type":"Food & Drink"
        }
    ],
    "sg:phone":"+1 770 642 6600",
    "sg:postcode":"30044",
    "sg:province":"GA",
    "sg:tags":[
        "eating"
    ],
    "wof:name":"Pizza Hut",
    "wof:placetype":"venue"
},
  "geometry": {"coordinates":[-84.00752900000001,33.917869],"type":"Point"}
}