{
  "type": "Feature",
  "properties": {
    "iso:country":"US",
    "sg:address":"452 1st Ave",
    "sg:city":"Arabi",
    "sg:classifiers":[
        {
            "category":"Shopping",
            "subcategory":"Gifts & Souvenirs",
            "type":"Retail Goods"
        }
    ],
    "sg:phone":"+1 229 273 5205",
    "sg:postcode":"31712",
    "sg:province":"GA",
    "sg:tags":[
        "shop",
        "novelty"
    ],
    "wof:name":"Plantation House",
    "wof:placetype":"venue"
},
  "geometry": {"coordinates":[-83.741433,31.829048],"type":"Point"}
}