{
  "type": "Feature",
  "properties": {
    "iso:country":"US",
    "sg:address":"14 E 3rd Ave",
    "sg:city":"Rome",
    "sg:classifiers":[
        {
            "category":"Home & Garden",
            "subcategory":"Furniture",
            "type":"Retail Goods"
        }
    ],
    "sg:phone":"+1 706 234 0533",
    "sg:postcode":"30161",
    "sg:province":"GA",
    "sg:tags":[
        "design",
        "furnishing"
    ],
    "wof:name":"Chisholm & Thomason LTD",
    "wof:placetype":"venue"
},
  "geometry": {"coordinates":[-85.172286,34.253033],"type":"Point"}
}