{
  "type": "Feature",
  "properties": {
    "iso:country":"US",
    "sg:address":"1950 Howell Mill Rd",
    "sg:city":"Atlanta",
    "sg:classifiers":[
        {
            "category":"Professional",
            "type":"Services"
        }
    ],
    "sg:phone":"+1 404 351 5465",
    "sg:postcode":"30318",
    "sg:province":"GA",
    "wof:name":"Delta Exportimport Company",
    "wof:placetype":"venue"
},
  "geometry": {"coordinates":[-84.41278699999999,33.807007],"type":"Point"}
}