{
  "type": "Feature",
  "properties": {
    "addr:full":"1777 Phoenix Pkwy Atlanta GA 30349",
    "addr:housenumber":"1777",
    "addr:postcode":"30349",
    "addr:street":"Phoenix Pkwy",
    "iso:country":"US",
    "sg:address":"1777 Phoenix Pkwy",
    "sg:city":"Atlanta",
    "sg:classifiers":[
        {
            "category":"Banks & Credit Unions",
            "subcategory":"Investment Brokerage",
            "type":"Services"
        }
    ],
    "sg:phone":"+1 404 527 7630",
    "sg:postcode":"30349",
    "sg:province":"GA",
    "sg:tags":[
        "advisory"
    ],
    "wof:name":"Consumer CD Cun Sv Al",
    "wof:placetype":"venue"
},
  "geometry": {"coordinates":[-84.4447,33.614756],"type":"Point"}
}