{
  "type": "Feature",
  "properties": {
    "iso:country":"US",
    "sg:address":"4321 Buford Hwy Ste C",
    "sg:city":"Atlanta",
    "sg:classifiers":[
        {
            "category":"Autos & Motor Vehicles",
            "subcategory":"Auto Supplies",
            "type":"Retail Goods"
        },
        {
            "category":"Wholesale",
            "subcategory":"Auto Parts",
            "type":"Manufacturing & Wholesale Goods"
        },
        {
            "category":"Retail",
            "subcategory":"Auto Repair",
            "type":"Services"
        }
    ],
    "sg:phone":"+1 404 325 3966",
    "sg:postcode":"30341",
    "sg:province":"GA",
    "sg:tags":[
        "body",
        "repairing",
        "automobile",
        "accessory",
        "rebuilt-wholesale",
        "supplies-used",
        "painting",
        "manufacturer"
    ],
    "sg:website":"http://www.benz-store.com",
    "wof:name":"Benz Store",
    "wof:placetype":"venue"
},
  "geometry": {"coordinates":[-84.300831,33.86792],"type":"Point"}
}