{
  "type": "Feature",
  "properties": {
    "addr:full":"188 S Hulin Ave Tignall GA 30668",
    "addr:housenumber":"188",
    "addr:postcode":"30668",
    "addr:street":"S Hulin Ave",
    "iso:country":"US",
    "sg:address":"188 S Hulin Ave",
    "sg:city":"Tignall",
    "sg:classifiers":[
        {
            "category":"Organizations",
            "subcategory":"Religious Organization",
            "type":"Services"
        }
    ],
    "sg:phone":"+1 706 285 2192",
    "sg:postcode":"30668",
    "sg:province":"GA",
    "sg:tags":[
        "clergy"
    ],
    "wof:name":"Dale Fincher",
    "wof:placetype":"venue"
},
  "geometry": {"coordinates":[-82.74241600000001,33.858741],"type":"Point"}
}