{
  "type": "Feature",
  "properties": {
    "iso:country":"US",
    "sg:address":"105 Buckingham Pl",
    "sg:city":"Brunswick",
    "sg:classifiers":[
        {
            "category":"Organizations",
            "subcategory":"Religious Organization",
            "type":"Services"
        }
    ],
    "sg:phone":"+1 912 265 2807",
    "sg:postcode":"31525",
    "sg:province":"GA",
    "wof:name":"North Brnswick Wesleyan Church",
    "wof:placetype":"venue"
},
  "geometry": {"coordinates":[-81.481511,31.206394],"type":"Point"}
}