{
  "type": "Feature",
  "properties": {
    "addr:full":"4471 Calhoun Rd NE Rome GA 30161",
    "addr:housenumber":"4471",
    "addr:postcode":"ga 30161",
    "addr:street":"Calhoun Rd Ne",
    "iso:country":"US",
    "sg:address":"4471 Calhoun Rd NE",
    "sg:city":"Rome",
    "sg:classifiers":[
        {
            "category":"Building & Trades",
            "subcategory":"Plumbing",
            "type":"Services"
        }
    ],
    "sg:phone":"+1 706 232 3877",
    "sg:postcode":"30161",
    "sg:province":"GA",
    "sg:tags":[
        "mechanical",
        "contractor"
    ],
    "wof:name":"Industrial Mechanical",
    "wof:placetype":"venue"
},
  "geometry": {"coordinates":[-85.072115,34.335983],"type":"Point"}
}