{
  "type": "Feature",
  "properties": {
    "addr:full":"2847 Hedgewood Dr NW Atlanta GA 30311",
    "addr:housenumber":"2847",
    "addr:postcode":"30311",
    "addr:street":"Hedgewood Dr Nw",
    "iso:country":"US",
    "sg:address":"2847 Hedgewood Dr NW",
    "sg:city":"Atlanta",
    "sg:classifiers":[
        {
            "category":"Professional",
            "subcategory":"Business Services",
            "type":"Services"
        }
    ],
    "sg:phone":"+1 404 691 2733",
    "sg:postcode":"30311",
    "sg:province":"GA",
    "wof:name":"Libra 3 Interiors",
    "wof:placetype":"venue"
},
  "geometry": {"coordinates":[-84.47878,33.757755],"type":"Point"}
}