{
  "type": "Feature",
  "properties": {
    "addr:full":"2275 Oak Rd Snellville GA 30078",
    "addr:housenumber":"2275",
    "addr:postcode":"30078",
    "addr:street":"Oak Rd",
    "iso:country":"US",
    "sg:address":"2275 Oak Rd",
    "sg:city":"Snellville",
    "sg:phone":"+1 770 736 9572",
    "sg:postcode":"30078",
    "sg:province":"GA",
    "wof:name":"Golden Age Insurance Specialists",
    "wof:placetype":"venue"
},
  "geometry": {"coordinates":[-84.017278,33.859613],"type":"Point"}
}