{
  "type": "Feature",
  "properties": {
    "iso:country":"US",
    "sg:address":"1300 Martin Luther King Jr Blvd",
    "sg:city":"Columbus",
    "sg:classifiers":[
        {
            "category":"Food & Beverages",
            "subcategory":"Bakery",
            "type":"Retail Goods"
        }
    ],
    "sg:phone":"+1 706 323 5777",
    "sg:postcode":"31906",
    "sg:province":"GA",
    "sg:tags":[
        "product",
        "doughnut",
        "mfg"
    ],
    "wof:name":"Veri Best Donut Company",
    "wof:placetype":"venue"
},
  "geometry": {"coordinates":[-84.971555,32.458824],"type":"Point"}
}