{
  "type": "Feature",
  "properties": {
    "addr:full":"1311 Juniper St La Grange GA 30240",
    "addr:housenumber":"1311",
    "addr:postcode":"30240",
    "addr:street":"Juniper St",
    "iso:country":"US",
    "sg:address":"1311 Juniper St",
    "sg:city":"La Grange",
    "sg:classifiers":[
        {
            "category":"Professional",
            "type":"Services"
        }
    ],
    "sg:phone":"+1 706 812 0772",
    "sg:postcode":"30240",
    "sg:province":"GA",
    "wof:name":"Rickiey J Norred",
    "wof:placetype":"venue"
},
  "geometry": {"coordinates":[-85.04020199999999,33.020476],"type":"Point"}
}