{
  "type": "Feature",
  "properties": {
    "addr:full":"5925 Roswell Rd Atlanta GA 30328",
    "addr:housenumber":"5925",
    "addr:postcode":"30328",
    "addr:street":"Roswell Rd",
    "iso:country":"US",
    "sg:address":"5925 Roswell Rd",
    "sg:city":"Atlanta",
    "sg:classifiers":[
        {
            "category":"Wholesale",
            "subcategory":"Durable Goods & Equipment",
            "type":"Manufacturing & Wholesale Goods"
        }
    ],
    "sg:phone":"+1 404 252 9244",
    "sg:postcode":"30328",
    "sg:province":"GA",
    "sg:tags":[
        "professional"
    ],
    "wof:name":"Cabe & Cato Inc",
    "wof:placetype":"venue"
},
  "geometry": {"coordinates":[-84.379017,33.917869],"type":"Point"}
}