{
  "type": "Feature",
  "properties": {
    "iso:country":"US",
    "sg:address":"3079 Metts Rd",
    "sg:city":"Statesboro",
    "sg:classifiers":[
        {
            "category":"Recreation",
            "type":"Entertainment"
        },
        {
            "category":"Farming",
            "subcategory":"Fish & Marine Products",
            "type":"Manufacturing & Wholesale Goods"
        }
    ],
    "sg:phone":"+1 912 587 5727",
    "sg:postcode":"30461",
    "sg:province":"GA",
    "sg:tags":[
        "club",
        "membership",
        "preserves",
        "hunting",
        "fishing"
    ],
    "wof:name":"Marsh Hunting Preserve Inc",
    "wof:placetype":"venue"
},
  "geometry": {"coordinates":[-81.825987,32.560044],"type":"Point"}
}