{
  "type": "Feature",
  "properties": {
    "addr:full":"4625 River Green Pkwy Duluth GA 30096",
    "addr:housenumber":"4625",
    "addr:postcode":"30096",
    "addr:street":"River Green Pkwy",
    "iso:country":"US",
    "sg:address":"4625 River Green Pkwy",
    "sg:city":"Duluth",
    "sg:classifiers":[
        {
            "category":"Professional",
            "type":"Services"
        }
    ],
    "sg:phone":"+1 678 417 0493",
    "sg:postcode":"30096",
    "sg:province":"GA",
    "wof:name":"Green Tree",
    "wof:placetype":"venue"
},
  "geometry": {"coordinates":[-84.172439,34.017682],"type":"Point"}
}