{
  "type": "Feature",
  "properties": {
    "addr:full":"116 Westbrook Rd Dalton GA 30721",
    "addr:housenumber":"116",
    "addr:postcode":"30721",
    "addr:street":"Westbrook Rd",
    "iso:country":"US",
    "sg:address":"116 Westbrook Rd",
    "sg:city":"Dalton",
    "sg:classifiers":[
        {
            "category":"Banks & Credit Unions",
            "subcategory":"Financial Services",
            "type":"Services"
        }
    ],
    "sg:phone":"+1 706 278 0561",
    "sg:postcode":"30721",
    "sg:province":"GA",
    "sg:tags":[
        "investor",
        "real estate"
    ],
    "wof:name":"Smith Properties",
    "wof:placetype":"venue"
},
  "geometry": {"coordinates":[-84.956245,34.808809],"type":"Point"}
}