{
  "type": "Feature",
  "properties": {
    "addr:full":"1055 Piedmont Ave NE Atlanta GA 30309",
    "addr:housenumber":"1055",
    "addr:postcode":"30309",
    "addr:street":"Piedmont Ave Ne",
    "iso:country":"US",
    "sg:address":"1055 Piedmont Ave NE",
    "sg:city":"Atlanta",
    "sg:classifiers":[
        {
            "category":"Real Estate",
            "subcategory":"Real Estate Services",
            "type":"Services"
        }
    ],
    "sg:phone":"+1 404 853 4104",
    "sg:postcode":"30309",
    "sg:province":"GA",
    "sg:tags":[
        "management",
        "condominium"
    ],
    "wof:name":"Piedmont Crest",
    "wof:placetype":"venue"
},
  "geometry": {"coordinates":[-84.379548,33.783335],"type":"Point"}
}