{
  "type": "Feature",
  "properties": {
    "addr:full":"1890 State Rte 95 Rock Spring GA 30739",
    "addr:housenumber":"1890",
    "addr:postcode":"30739",
    "addr:street":"State Rte 95",
    "iso:country":"US",
    "sg:address":"1890 State Rte 95",
    "sg:city":"Rock Spring",
    "sg:classifiers":[
        {
            "category":"Building & Trades",
            "subcategory":"Construction",
            "type":"Services"
        }
    ],
    "sg:phone":"+1 706 764 9990",
    "sg:postcode":"30739",
    "sg:province":"GA",
    "sg:tags":[
        "house"
    ],
    "wof:name":"Adam Steadman Service Co",
    "wof:placetype":"venue"
},
  "geometry": {"coordinates":[-85.218633,34.804079],"type":"Point"}
}