{
  "type": "Feature",
  "properties": {
    "addr:full":"4195 S Lee St Ste E Buford GA 30518",
    "addr:housenumber":"4195",
    "addr:postcode":"30518",
    "addr:street":"S Lee St Ste E",
    "iso:country":"US",
    "sg:address":"4195 S Lee St Ste E",
    "sg:city":"Buford",
    "sg:classifiers":[
        {
            "category":"Restaurant",
            "type":"Food & Drink"
        }
    ],
    "sg:phone":"+1 770 271 0011",
    "sg:postcode":"30518",
    "sg:province":"GA",
    "sg:tags":[
        "southern"
    ],
    "wof:name":"DP's Cafe",
    "wof:placetype":"venue"
},
  "geometry": {"coordinates":[-83.999838,34.095281],"type":"Point"}
}