{
  "type": "Feature",
  "properties": {
    "iso:country":"US",
    "sg:address":"4710 Lower Roswell Rd",
    "sg:city":"Marietta",
    "sg:classifiers":[
        {
            "category":"Building & Trades",
            "subcategory":"Construction",
            "type":"Services"
        }
    ],
    "sg:phone":"+1 770 565 2103",
    "sg:postcode":"30068",
    "sg:province":"GA",
    "sg:tags":[
        "concrete",
        "contractor"
    ],
    "wof:name":"Hemma Concrete",
    "wof:placetype":"venue"
},
  "geometry": {"coordinates":[-84.413623,33.965874],"type":"Point"}
}