{
  "type": "Feature",
  "properties": {
    "addr:full":"2114 Shorter Ave NW Rome GA 30165",
    "addr:postcode":"2114;ga 30165",
    "addr:street":"Shorter Ave Nw",
    "iso:country":"US",
    "sg:address":"2114 Shorter Ave NW",
    "sg:city":"Rome",
    "sg:classifiers":[
        {
            "category":"Restaurant",
            "type":"Food & Drink"
        }
    ],
    "sg:menulink":"http://www.allmenus.com/ga/rome/160567-burger-king/menu/",
    "sg:phone":"+1 706 232 2621",
    "sg:postcode":"30165",
    "sg:province":"GA",
    "sg:tags":[
        "burger",
        "american"
    ],
    "wof:name":"Burger King",
    "wof:placetype":"venue"
},
  "geometry": {"coordinates":[-85.22314900000001,34.270964],"type":"Point"}
}