{
  "type": "Feature",
  "properties": {
    "iso:country":"US",
    "sg:address":"868 Robert Lewis Rd",
    "sg:city":"Dublin",
    "sg:classifiers":[
        {
            "category":"Manufacturing",
            "subcategory":"Furniture",
            "type":"Manufacturing & Wholesale Goods"
        }
    ],
    "sg:phone":"+1 478 274 8141",
    "sg:postcode":"31027",
    "sg:province":"GA",
    "sg:tags":[
        "household",
        "wood",
        "mfg"
    ],
    "wof:name":"Bracewell Furniture",
    "wof:placetype":"venue"
},
  "geometry": {"coordinates":[-82.800292,32.527431],"type":"Point"}
}