{
  "type": "Feature",
  "properties": {
    "addr:full":"3015 E Walnut Ave Dalton GA 30721",
    "addr:housenumber":"3015",
    "addr:postcode":"30721",
    "addr:street":"E Walnut Ave",
    "iso:country":"US",
    "sg:address":"3015 E Walnut Ave",
    "sg:city":"Dalton",
    "sg:classifiers":[
        {
            "category":"Manufacturing",
            "subcategory":"Rubber & Plastics",
            "type":"Manufacturing & Wholesale Goods"
        },
        {
            "category":"Autos & Motor Vehicles",
            "subcategory":"Auto Supplies",
            "type":"Retail Goods"
        },
        {
            "category":"Retail",
            "subcategory":"Auto Repair",
            "type":"Services"
        }
    ],
    "sg:phone":"+1 706 278 0713",
    "sg:postcode":"30721",
    "sg:province":"GA",
    "sg:tags":[
        "recap",
        "retread",
        "tires-wholesale",
        "tire",
        "manufacturer"
    ],
    "sg:website":"http://www.coopertire.com/html/",
    "wof:name":"Chadwick Tire",
    "wof:placetype":"venue"
},
  "geometry": {"coordinates":[-84.920771,34.773965],"type":"Point"}
}