{
  "type": "Feature",
  "properties": {
    "addr:full":"360 Rehoboth Rd Bowman GA 30624",
    "addr:housenumber":"360",
    "addr:postcode":"30624",
    "addr:street":"Rehoboth Rd",
    "iso:country":"US",
    "sg:address":"360 Rehoboth Rd",
    "sg:city":"Bowman",
    "sg:classifiers":[
        {
            "category":"Autos & Motor Vehicles",
            "subcategory":"Automobile Sales",
            "type":"Retail Goods"
        }
    ],
    "sg:phone":"+1 706 283 6452",
    "sg:postcode":"30624",
    "sg:province":"GA",
    "sg:tags":[
        "used"
    ],
    "wof:name":"Krt Cars Inc",
    "wof:placetype":"venue"
},
  "geometry": {"coordinates":[-83.03016599999999,34.196102],"type":"Point"}
}