{
  "type": "Feature",
  "properties": {
    "addr:full":"104 Levrenti Dr Fort Valley GA 31030",
    "addr:housenumber":"104",
    "addr:postcode":"31030",
    "addr:street":"Levrenti Dr Fort Valley",
    "iso:country":"US",
    "sg:address":"104 Levrenti Dr",
    "sg:city":"Fort Valley",
    "sg:classifiers":[
        {
            "category":"Social Services",
            "type":"Services"
        }
    ],
    "sg:phone":"+1 478 825 1511",
    "sg:postcode":"31030",
    "sg:province":"GA",
    "wof:name":"Sharing Day Care",
    "wof:placetype":"venue"
},
  "geometry": {"coordinates":[-83.883667,32.545364],"type":"Point"}
}