{
  "type": "Feature",
  "properties": {
    "addr:full":"6451 Veterans Pkwy Columbus GA 31909",
    "addr:housenumber":"6451",
    "addr:postcode":"31909",
    "addr:street":"Veterans Pkwy",
    "iso:country":"US",
    "sg:address":"6451 Veterans Pkwy",
    "sg:city":"Columbus",
    "sg:classifiers":[
        {
            "category":"Autos & Motor Vehicles",
            "subcategory":"Auto Supplies",
            "type":"Retail Goods"
        }
    ],
    "sg:phone":"+1 706 571 9988",
    "sg:postcode":"31909",
    "sg:province":"GA",
    "sg:tags":[
        "automobile",
        "parts"
    ],
    "wof:name":"Advance Auto Parts Inc",
    "wof:placetype":"venue"
},
  "geometry": {"coordinates":[-84.956881,32.531076],"type":"Point"}
}