{
  "type": "Feature",
  "properties": {
    "addr:full":"6595 Peachtree Industrial Blvd Norcross GA 30092",
    "addr:housenumber":"6595",
    "addr:postcode":"30092",
    "addr:street":"Peachtree Industrial Blvd",
    "iso:country":"US",
    "sg:address":"6595 Peachtree Industrial Blvd",
    "sg:city":"Norcross",
    "sg:classifiers":[
        {
            "category":"Professional",
            "subcategory":"Management & Consulting",
            "type":"Services"
        }
    ],
    "sg:phone":"+1 770 350 0099",
    "sg:postcode":"30092",
    "sg:province":"GA",
    "sg:tags":[
        "technology"
    ],
    "wof:name":"Itc Consulting",
    "wof:placetype":"venue"
},
  "geometry": {"coordinates":[-84.24766,33.939904],"type":"Point"}
}