{
  "type": "Feature",
  "properties": {
    "iso:country":"US",
    "sg:address":"1470 Stoneleigh Cir",
    "sg:city":"Stone Mountain",
    "sg:classifiers":[
        {
            "category":"Organizations",
            "subcategory":"Professional Association",
            "type":"Services"
        }
    ],
    "sg:phone":"+1 770 498 9493",
    "sg:postcode":"30088",
    "sg:province":"GA",
    "sg:tags":[
        "education",
        "teacher"
    ],
    "wof:name":"Southern Assoc Student Council",
    "wof:placetype":"venue"
},
  "geometry": {"coordinates":[-84.16410399999999,33.747471],"type":"Point"}
}