{
  "type": "Feature",
  "properties": {
    "iso:country":"US",
    "sg:address":"5475 Buford Hwy",
    "sg:city":"Norcross",
    "sg:classifiers":[
        {
            "category":"Retail",
            "subcategory":"Laundry & Dry Cleaning",
            "type":"Services"
        }
    ],
    "sg:phone":"+1 770 662 5913",
    "sg:postcode":"30071",
    "sg:province":"GA",
    "sg:tags":[
        "cleaners"
    ],
    "wof:name":"Best Cleaners",
    "wof:placetype":"venue"
},
  "geometry": {"coordinates":[-84.202939,33.945768],"type":"Point"}
}