{
  "type": "Feature",
  "properties": {
    "addr:full":"5136 Madison Green Dr SW Mableton GA 30126",
    "addr:housenumber":"5136",
    "addr:postcode":"30126",
    "addr:street":"Madison Green Dr Sw",
    "iso:country":"US",
    "sg:address":"5136 Madison Green Dr SW",
    "sg:city":"Mableton",
    "sg:classifiers":[
        {
            "category":"Wholesale",
            "subcategory":"Construction Materials",
            "type":"Manufacturing & Wholesale Goods"
        },
        {
            "category":"Home & Garden",
            "subcategory":"Building Materials",
            "type":"Retail Goods"
        }
    ],
    "sg:phone":"+1 770 745 7270",
    "sg:postcode":"30126",
    "sg:province":"GA",
    "sg:tags":[
        "windows-wholesale",
        "window",
        "manufacturer"
    ],
    "wof:name":"Barnes Window And Doors",
    "wof:placetype":"venue"
},
  "geometry": {"coordinates":[-84.585796,33.828949],"type":"Point"}
}