{
  "type": "Feature",
  "properties": {
    "iso:country":"US",
    "sg:address":"8 Johnson Ave",
    "sg:city":"Newnan",
    "sg:classifiers":[
        {
            "category":"Building & Trades",
            "subcategory":"Construction",
            "type":"Services"
        }
    ],
    "sg:phone":"+1 770 304 9812",
    "sg:postcode":"30263",
    "sg:province":"GA",
    "sg:tags":[
        "general",
        "electrical",
        "contractor"
    ],
    "wof:name":"Moss Contractors",
    "wof:placetype":"venue"
},
  "geometry": {"coordinates":[-84.78966699999999,33.369827],"type":"Point"}
}