{
  "type": "Feature",
  "properties": {
    "iso:country":"US",
    "sg:address":"4600 Pine St",
    "sg:city":"Smyrna",
    "sg:classifiers":[
        {
            "category":"Building & Trades",
            "subcategory":"Landscaping Services",
            "type":"Services"
        }
    ],
    "sg:phone":"+1 770 436 8398",
    "sg:postcode":"30080",
    "sg:province":"GA",
    "wof:name":"Gair Landscape Co Inc",
    "wof:placetype":"venue"
},
  "geometry": {"coordinates":[-84.491294,33.840773],"type":"Point"}
}