{
  "type": "Feature",
  "properties": {
    "iso:country":"US",
    "sg:address":"6505 Shiloh road Suite 110B",
    "sg:city":"Alpharetta",
    "sg:classifiers":[
        {
            "category":"Professional",
            "subcategory":"Computer Services",
            "type":"Services"
        }
    ],
    "sg:phone":"+41 26 425 48 50",
    "sg:postcode":"30005",
    "sg:province":"GA",
    "sg:tags":[
        "video",
        "web",
        "video-enrichment",
        "sport",
        "education",
        "healthcare"
    ],
    "sg:website":"http://www.dartfish.tv",
    "wof:name":"Dartfish",
    "wof:placetype":"venue"
},
  "geometry": {"coordinates":[-84.198955,34.110824],"type":"Point"}
}