{
  "type": "Feature",
  "properties": {
    "iso:country":"US",
    "sg:address":"198 Ponce de Leon Ave NE 6C",
    "sg:city":"Atlanta",
    "sg:classifiers":[
        {
            "category":"Building & Trades",
            "subcategory":"Construction",
            "type":"Services"
        }
    ],
    "sg:phone":"+1 404 888 0166",
    "sg:postcode":"30308",
    "sg:province":"GA",
    "sg:tags":[
        "mason",
        "masonry",
        "industrial",
        "contractors-commercial",
        "contractor"
    ],
    "wof:name":"Rk Masonry",
    "wof:placetype":"venue"
},
  "geometry": {"coordinates":[-84.38108099999999,33.77253],"type":"Point"}
}