{
  "type": "Feature",
  "properties": {
    "iso:country":"US",
    "sg:address":"104 R St SW",
    "sg:city":"Thomaston",
    "sg:classifiers":[
        {
            "category":"Shopping",
            "subcategory":"Florist",
            "type":"Retail Goods"
        }
    ],
    "sg:phone":"+1 706 647 8037",
    "sg:postcode":"30286",
    "sg:province":"GA",
    "wof:name":"Special Touch Florist",
    "wof:placetype":"venue"
},
  "geometry": {"coordinates":[-84.33669,32.903107],"type":"Point"}
}