{
  "type": "Feature",
  "properties": {
    "addr:full":"4505 Best Road Atlanta GA 30337",
    "addr:housenumber":"4505",
    "addr:postcode":"30337",
    "addr:street":"Best Road",
    "iso:country":"US",
    "sg:address":"4505 Best Road",
    "sg:city":"Atlanta",
    "sg:classifiers":[
        {
            "category":"Travel",
            "subcategory":"Hotels & Motels",
            "type":"Entertainment"
        }
    ],
    "sg:phone":"+1 404 767 1224",
    "sg:postcode":"30337",
    "sg:province":"GA",
    "wof:name":"Days",
    "wof:placetype":"venue"
},
  "geometry": {"coordinates":[-84.457898,33.631363],"type":"Point"}
}