{
  "type": "Feature",
  "properties": {
    "iso:country":"US",
    "sg:address":"7 15th St NE",
    "sg:city":"Atlanta",
    "sg:classifiers":[
        {
            "category":"Arena",
            "subcategory":"Horse Racetrack",
            "type":"Entertainment"
        }
    ],
    "sg:phone":"+1 404 885 6149",
    "sg:postcode":"30309",
    "sg:province":"GA",
    "sg:tags":[
        "breeder"
    ],
    "wof:name":"Celtic Stables Inc",
    "wof:placetype":"venue"
},
  "geometry": {"coordinates":[-84.38747100000001,33.788523],"type":"Point"}
}