{
  "type": "Feature",
  "properties": {
    "addr:full":"4825 Steve Reynolds Blvd Norcross GA 30093",
    "addr:housenumber":"4825",
    "addr:postcode":"30093",
    "addr:street":"Steve Reynolds Blvd",
    "iso:country":"US",
    "sg:address":"4825 Steve Reynolds Blvd",
    "sg:city":"Norcross",
    "sg:classifiers":[
        {
            "category":"Restaurant",
            "type":"Food & Drink"
        }
    ],
    "sg:phone":"+1 770 921 2071",
    "sg:postcode":"30093",
    "sg:province":"GA",
    "sg:tags":[
        "eating"
    ],
    "wof:name":"Romans Paul Etal",
    "wof:placetype":"venue"
},
  "geometry": {"coordinates":[-84.15549799999999,33.914365],"type":"Point"}
}