{
  "type": "Feature",
  "properties": {
    "iso:country":"US",
    "sg:address":"1096 Green St",
    "sg:city":"Roswell",
    "sg:classifiers":[
        {
            "category":"Retail",
            "subcategory":"Photofinishing",
            "type":"Services"
        }
    ],
    "sg:phone":"+1 770 993 7088",
    "sg:postcode":"30075",
    "sg:province":"GA",
    "sg:tags":[
        "laboratory"
    ],
    "wof:name":"In Living Black & White",
    "wof:placetype":"venue"
},
  "geometry": {"coordinates":[-84.359765,34.029497],"type":"Point"}
}