{
  "type": "Feature",
  "properties": {
    "addr:full":"4009 Derby Dr Gainesville GA 30507",
    "addr:housenumber":"4009",
    "addr:postcode":"30507",
    "addr:street":"Derby Dr",
    "iso:country":"US",
    "sg:address":"4009 Derby Dr",
    "sg:city":"Gainesville",
    "sg:classifiers":[
        {
            "category":"Shopping",
            "subcategory":"Gifts & Souvenirs",
            "type":"Retail Goods"
        }
    ],
    "sg:phone":"+1 770 965 0193",
    "sg:postcode":"30507",
    "sg:province":"GA",
    "sg:tags":[
        "shop"
    ],
    "wof:name":"Gift Shop",
    "wof:placetype":"venue"
},
  "geometry": {"coordinates":[-83.813086,34.173581],"type":"Point"}
}