{
  "type": "Feature",
  "properties": {
    "addr:full":"5098 Aska Rd Blue Ridge GA 30513",
    "addr:postcode":"5098;30513",
    "addr:street":"Aska Rd",
    "iso:country":"US",
    "sg:address":"5098 Aska Rd",
    "sg:city":"Blue Ridge",
    "sg:classifiers":[
        {
            "category":"Building & Trades",
            "subcategory":"Construction",
            "type":"Services"
        }
    ],
    "sg:phone":"+1 706 632 2866",
    "sg:postcode":"30513",
    "sg:province":"GA",
    "sg:tags":[
        "excavation",
        "heavy",
        "contractor"
    ],
    "wof:name":"Kennon Curbow Excavating",
    "wof:placetype":"venue"
},
  "geometry": {"coordinates":[-84.283958,34.807992],"type":"Point"}
}