{
  "type": "Feature",
  "properties": {
    "addr:full":"1546 Maple St Augusta GA 30901",
    "addr:housenumber":"1546",
    "addr:postcode":"30901",
    "addr:street":"Maple St",
    "iso:country":"US",
    "sg:address":"1546 Maple St",
    "sg:city":"Augusta",
    "sg:classifiers":[
        {
            "category":"Organizations",
            "subcategory":"Religious Organization",
            "type":"Services"
        }
    ],
    "sg:phone":"+1 706 722 4560",
    "sg:postcode":"30901",
    "sg:province":"GA",
    "sg:tags":[
        "church"
    ],
    "wof:name":"Greater Temple Of Truth & Del",
    "wof:placetype":"venue"
},
  "geometry": {"coordinates":[-81.976434,33.457705],"type":"Point"}
}