{
  "type": "Feature",
  "properties": {
    "addr:full":"2662 Holcomb Bridge Rd Alpharetta GA 30022",
    "addr:housenumber":"2662",
    "addr:postcode":"30022",
    "addr:street":"Holcomb Bridge Rd",
    "iso:country":"US",
    "sg:address":"2662 Holcomb Bridge Rd",
    "sg:city":"Alpharetta",
    "sg:classifiers":[
        {
            "category":"Shopping",
            "type":"Retail Goods"
        }
    ],
    "sg:phone":"+1 770 650 8418",
    "sg:postcode":"30022",
    "sg:province":"GA",
    "sg:tags":[
        "trophy",
        "medal",
        "award"
    ],
    "wof:name":"Net Knacks Tennis Gifts & Awrd",
    "wof:placetype":"venue"
},
  "geometry": {"coordinates":[-84.28255,33.996175],"type":"Point"}
}