{
  "type": "Feature",
  "properties": {
    "addr:full":"5015 Buford Hwy Norcross GA 30071",
    "addr:housenumber":"5015",
    "addr:postcode":"30071",
    "addr:street":"Buford Hwy",
    "iso:country":"US",
    "sg:address":"5015 Buford Hwy",
    "sg:city":"Norcross",
    "sg:classifiers":[
        {
            "category":"Wholesale",
            "subcategory":"Furniture",
            "type":"Manufacturing & Wholesale Goods"
        }
    ],
    "sg:phone":"+1 770 903 1113",
    "sg:postcode":"30071",
    "sg:province":"GA",
    "sg:tags":[
        "furniture-wholesale",
        "manufacturer"
    ],
    "sg:website":"http://www.atlasfurniture.net",
    "wof:name":"Atlas International Inc",
    "wof:placetype":"venue"
},
  "geometry": {"coordinates":[-84.19395299999999,33.953029],"type":"Point"}
}