{
  "type": "Feature",
  "properties": {
    "addr:full":"1211 Stuart Ave Albany GA 31707",
    "addr:housenumber":"1211",
    "addr:postcode":"31707",
    "addr:street":"Stuart Ave",
    "iso:country":"US",
    "sg:address":"1211 Stuart Ave",
    "sg:city":"Albany",
    "sg:classifiers":[
        {
            "category":"Organizations",
            "subcategory":"Religious Organization",
            "type":"Services"
        }
    ],
    "sg:phone":"+1 229 439 7056",
    "sg:postcode":"31707",
    "sg:province":"GA",
    "sg:tags":[
        "church"
    ],
    "sg:website":"www.firstassemblyofalbany.org",
    "wof:name":"First Assembly Of God",
    "wof:placetype":"venue"
},
  "geometry": {"coordinates":[-84.17774,31.611769],"type":"Point"}
}