{
  "type": "Feature",
  "properties": {
    "iso:country":"US",
    "sg:address":"3700 Dekalb Technology Pkwy",
    "sg:city":"Atlanta",
    "sg:classifiers":[
        {
            "category":"Manufacturing",
            "subcategory":"Metals",
            "type":"Manufacturing & Wholesale Goods"
        }
    ],
    "sg:phone":"+1 770 454 7323",
    "sg:postcode":"30340",
    "sg:province":"GA",
    "sg:tags":[
        "door",
        "mfg",
        "windows",
        "rim",
        "vinyl",
        "storm",
        "patio"
    ],
    "wof:name":"Champion Win Co of Atlanta N",
    "wof:placetype":"venue"
},
  "geometry": {"coordinates":[-84.268807,33.884648],"type":"Point"}
}