{
  "type": "Feature",
  "properties": {
    "iso:country":"US",
    "sg:address":"1241 Smokey Rd",
    "sg:city":"Newnan",
    "sg:classifiers":[
        {
            "category":"Professional",
            "subcategory":"Computer Services",
            "type":"Services"
        }
    ],
    "sg:phone":"+1 770 251 7324",
    "sg:postcode":"30263",
    "sg:province":"GA",
    "sg:tags":[
        "design",
        "system",
        "related"
    ],
    "wof:name":"Cadrafting & Design",
    "wof:placetype":"venue"
},
  "geometry": {"coordinates":[-84.852419,33.353183],"type":"Point"}
}