{
  "type": "Feature",
  "properties": {
    "addr:full":"9255 Floyd Rd Jonesboro GA 30236",
    "addr:housenumber":"9255",
    "addr:postcode":"30236",
    "addr:street":"Floyd Rd",
    "iso:country":"US",
    "sg:address":"9255 Floyd Rd",
    "sg:city":"Jonesboro",
    "sg:classifiers":[
        {
            "category":"Building & Trades",
            "subcategory":"Construction",
            "type":"Services"
        }
    ],
    "sg:phone":"+1 770 478 6340",
    "sg:postcode":"30236",
    "sg:province":"GA",
    "sg:tags":[
        "house"
    ],
    "wof:name":"Wilkerson Homes Inc",
    "wof:placetype":"venue"
},
  "geometry": {"coordinates":[-84.28688099999999,33.499485],"type":"Point"}
}