{
  "type": "Feature",
  "properties": {
    "iso:country":"US",
    "sg:address":"117 Jesse Jewell Pkwy SE",
    "sg:city":"Gainesville",
    "sg:classifiers":[
        {
            "category":"Government",
            "subcategory":"Office",
            "type":"Public Place"
        }
    ],
    "sg:phone":"+1 770 531 7634",
    "sg:postcode":"30501",
    "sg:province":"GA",
    "sg:tags":[
        "village"
    ],
    "sg:website":"www.georgiamountainscenter.com",
    "wof:name":"City Of Gainesville",
    "wof:placetype":"venue"
},
  "geometry": {"coordinates":[-83.823234,34.29848],"type":"Point"}
}