{
  "type": "Feature",
  "properties": {
    "addr:full":"176 Country Club Rd Statesboro GA 30458",
    "addr:housenumber":"176",
    "addr:postcode":"30458",
    "addr:street":"Country Club Rd",
    "iso:country":"US",
    "sg:address":"176 Country Club Rd",
    "sg:city":"Statesboro",
    "sg:classifiers":[
        {
            "category":"Building & Trades",
            "subcategory":"Construction",
            "type":"Services"
        }
    ],
    "sg:phone":"+1 912 852 5062",
    "sg:postcode":"30458",
    "sg:province":"GA",
    "sg:tags":[
        "house"
    ],
    "wof:name":"Creative Construction & Design",
    "wof:placetype":"venue"
},
  "geometry": {"coordinates":[-81.85114799999999,32.405341],"type":"Point"}
}