{
  "type": "Feature",
  "properties": {
    "addr:full":"8384 Roswell Rd Atlanta GA 30350",
    "addr:housenumber":"8384",
    "addr:postcode":"30350",
    "addr:street":"Roswell Rd",
    "iso:country":"US",
    "sg:address":"8384 Roswell Rd",
    "sg:city":"Atlanta",
    "sg:classifiers":[
        {
            "category":"Professional",
            "subcategory":"Computer Services",
            "type":"Services"
        }
    ],
    "sg:phone":"+1 404 649 0460",
    "sg:postcode":"30350",
    "sg:province":"GA",
    "sg:tags":[
        "prepackaged",
        "software"
    ],
    "wof:name":"Perimeter Technology",
    "wof:placetype":"venue"
},
  "geometry": {"coordinates":[-84.35051799999999,33.979977],"type":"Point"}
}