{
  "type": "Feature",
  "properties": {
    "iso:country":"US",
    "sg:address":"1453 Greene St",
    "sg:city":"Augusta",
    "sg:classifiers":[
        {
            "category":"Wholesale",
            "subcategory":"Computers",
            "type":"Manufacturing & Wholesale Goods"
        },
        {
            "category":"Professional",
            "subcategory":"Computer Services",
            "type":"Services"
        },
        {
            "category":"Internet Cafe",
            "subcategory":"None",
            "type":"Food & Drink"
        }
    ],
    "sg:phone":"+1 706 210 3521",
    "sg:postcode":"30901",
    "sg:province":"GA",
    "sg:tags":[
        "web",
        "product",
        "publisher",
        "site",
        "equipment",
        "design",
        "developer",
        "software"
    ],
    "wof:name":"Accessone Technologies",
    "wof:placetype":"venue"
},
  "geometry": {"coordinates":[-81.982303,33.478572],"type":"Point"}
}