{
  "type": "Feature",
  "properties": {
    "addr:full":"5755 Mallory Rd Atlanta GA 30349",
    "addr:housenumber":"5755",
    "addr:postcode":"30349",
    "addr:street":"Mallory Rd",
    "iso:country":"US",
    "sg:address":"5755 Mallory Rd",
    "sg:city":"Atlanta",
    "sg:classifiers":[
        {
            "category":"Cemetery",
            "type":"Public Place"
        }
    ],
    "sg:phone":"+1 770 964 7871",
    "sg:postcode":"30349",
    "sg:province":"GA",
    "sg:tags":[
        "crematory"
    ],
    "wof:name":"Sci",
    "wof:placetype":"venue"
},
  "geometry": {"coordinates":[-84.526466,33.601021],"type":"Point"}
}