{
  "type": "Feature",
  "properties": {
    "addr:full":"2575 Delk Rd SE Marietta GA 30067",
    "addr:housenumber":"2575",
    "addr:postcode":"30067",
    "addr:street":"Delk Rd Se",
    "iso:country":"US",
    "sg:address":"2575 Delk Rd SE",
    "sg:city":"Marietta",
    "sg:classifiers":[
        {
            "category":"Building & Trades",
            "subcategory":"Construction",
            "type":"Services"
        }
    ],
    "sg:phone":"+1 770 953 8430",
    "sg:postcode":"30067",
    "sg:province":"GA",
    "sg:tags":[
        "house"
    ],
    "wof:name":"Keyton Construction Co",
    "wof:placetype":"venue"
},
  "geometry": {"coordinates":[-84.478577,33.922778],"type":"Point"}
}