{
  "type": "Feature",
  "properties": {
    "addr:full":"1020 Crackers Neck Rd Greensboro GA 30642",
    "addr:housenumber":"1020",
    "addr:postcode":"30642",
    "addr:street":"Crackers Neck Rd",
    "iso:country":"US",
    "sg:address":"1020 Crackers Neck Rd",
    "sg:city":"Greensboro",
    "sg:classifiers":[
        {
            "category":"Banks & Credit Unions",
            "subcategory":"Financial Services",
            "type":"Services"
        }
    ],
    "sg:phone":"+1 706 467 0695",
    "sg:postcode":"30642",
    "sg:province":"GA",
    "sg:tags":[
        "company",
        "holding"
    ],
    "wof:name":"Vaughan Holdings LLC",
    "wof:placetype":"venue"
},
  "geometry": {"coordinates":[-83.211252,33.407836],"type":"Point"}
}