{
  "type": "Feature",
  "properties": {
    "iso:country":"US",
    "sg:address":"120 Southlake Ct",
    "sg:city":"Alpharetta",
    "sg:classifiers":[
        {
            "category":"Recreation",
            "type":"Entertainment"
        }
    ],
    "sg:phone":"+1 770 521 0898",
    "sg:postcode":"30005",
    "sg:province":"GA",
    "wof:name":"Beef Obradys",
    "wof:placetype":"venue"
},
  "geometry": {"coordinates":[-84.21904000000001,34.075568],"type":"Point"}
}