{
  "type": "Feature",
  "properties": {
    "iso:country":"US",
    "sg:address":"1435 Fred Chance Rd",
    "sg:city":"Perkins",
    "sg:classifiers":[
        {
            "category":"Building & Trades",
            "subcategory":"Landscaping Services",
            "type":"Services"
        }
    ],
    "sg:phone":"+1 478 982 2722",
    "sg:postcode":"30822",
    "sg:province":"GA",
    "sg:tags":[
        "lawn"
    ],
    "wof:name":"R & R Landscape",
    "wof:placetype":"venue"
},
  "geometry": {"coordinates":[-81.78560400000001,32.891563],"type":"Point"}
}