{
  "type": "Feature",
  "properties": {
    "iso:country":"US",
    "sg:address":"1036 Cherry Creek Dr",
    "sg:city":"Valdosta",
    "sg:classifiers":[
        {
            "category":"Manufacturing",
            "subcategory":"Buildings",
            "type":"Manufacturing & Wholesale Goods"
        },
        {
            "category":"Building & Trades",
            "subcategory":"Construction",
            "type":"Services"
        }
    ],
    "sg:phone":"+1 229 247 5024",
    "sg:postcode":"31605",
    "sg:province":"GA",
    "sg:tags":[
        "home",
        "builder",
        "contractor"
    ],
    "wof:name":"Consulting Home Economist",
    "wof:placetype":"venue"
},
  "geometry": {"coordinates":[-83.29604399999999,30.91059],"type":"Point"}
}