{
  "type": "Feature",
  "properties": {
    "iso:country":"US",
    "sg:address":"784 N Highland Ave NE",
    "sg:city":"Atlanta",
    "sg:classifiers":[
        {
            "category":"Shopping",
            "subcategory":"Clothing, Apparel, & Fashions",
            "type":"Retail Goods"
        }
    ],
    "sg:phone":"+1 404 607 7694",
    "sg:postcode":"30306",
    "sg:province":"GA",
    "wof:name":"Planetarian Ornaments",
    "wof:placetype":"venue"
},
  "geometry": {"coordinates":[-84.352575,33.775644],"type":"Point"}
}