{
  "type": "Feature",
  "properties": {
    "addr:full":"6243 Joseph Way NW Norcross GA 30093",
    "addr:housenumber":"6243",
    "addr:postcode":"30093",
    "addr:street":"Joseph Way Nw",
    "iso:country":"US",
    "sg:address":"6243 Joseph Way NW",
    "sg:city":"Norcross",
    "sg:classifiers":[
        {
            "category":"Personal",
            "subcategory":"Beauty Salon",
            "type":"Services"
        }
    ],
    "sg:phone":"+1 770 613 0357",
    "sg:postcode":"30093",
    "sg:province":"GA",
    "sg:tags":[
        "shop"
    ],
    "wof:name":"Nina Nails",
    "wof:placetype":"venue"
},
  "geometry": {"coordinates":[-84.205895,33.905837],"type":"Point"}
}