{
  "type": "Feature",
  "properties": {
    "iso:country":"US",
    "sg:address":"144 Ridgewood Dr",
    "sg:city":"Woodstock",
    "sg:classifiers":[
        {
            "category":"Social Services",
            "subcategory":"Child Care",
            "type":"Services"
        }
    ],
    "sg:phone":"+1 770 926 2544",
    "sg:postcode":"30188",
    "sg:province":"GA",
    "sg:tags":[
        "day"
    ],
    "wof:name":"Just Like Home Daycare",
    "wof:placetype":"venue"
},
  "geometry": {"coordinates":[-84.53074700000001,34.076165],"type":"Point"}
}