{
  "type": "Feature",
  "properties": {
    "iso:country":"US",
    "sg:address":"909 Senoia Rd",
    "sg:city":"Tyrone",
    "sg:classifiers":[
        {
            "category":"Building & Trades",
            "subcategory":"Construction",
            "type":"Services"
        }
    ],
    "sg:phone":"+1 770 631 8010",
    "sg:postcode":"30290",
    "sg:province":"GA",
    "sg:tags":[
        "contractor"
    ],
    "wof:name":"Jones Builders Inc",
    "wof:placetype":"venue"
},
  "geometry": {"coordinates":[-84.595001,33.4786],"type":"Point"}
}