{
  "type": "Feature",
  "properties": {
    "addr:full":"1202 W Marietta St NW Atlanta GA 30318",
    "addr:housenumber":"1202",
    "addr:postcode":"30318",
    "addr:street":"W Marietta St Nw",
    "iso:country":"US",
    "sg:address":"1202 W Marietta St NW",
    "sg:city":"Atlanta",
    "sg:classifiers":[
        {
            "category":"Place Of Worship",
            "type":"Public Place"
        }
    ],
    "sg:phone":"+1 404 794 1470",
    "sg:postcode":"30318",
    "sg:province":"GA",
    "sg:tags":[
        "church"
    ],
    "sg:website":"http://www.mtephraim.com",
    "wof:name":"Mt Ephraim Baptist Church",
    "wof:placetype":"venue"
},
  "geometry": {"coordinates":[-84.426374,33.786009],"type":"Point"}
}