{
  "type": "Feature",
  "properties": {
    "addr:full":"2246 Roswell Rd Marietta GA 30062",
    "addr:housenumber":"2246",
    "addr:postcode":"30062",
    "addr:street":"Roswell Rd",
    "iso:country":"US",
    "sg:address":"2246 Roswell Rd",
    "sg:city":"Marietta",
    "sg:classifiers":[
        {
            "category":"Insurance",
            "subcategory":"Hazard Insurance",
            "type":"Services"
        }
    ],
    "sg:phone":"+1 770 973 0373",
    "sg:postcode":"30062",
    "sg:province":"GA",
    "sg:website":"http://statefarm.mqgroup.com/url.asp?usr=111774",
    "wof:name":"State Farm Insurance Agent-Gary Motley",
    "wof:placetype":"venue"
},
  "geometry": {"coordinates":[-84.486194,33.972903],"type":"Point"}
}