{
  "type": "Feature",
  "properties": {
    "addr:full":"5015 New Jesup Hwy Brunswick GA 31520",
    "addr:housenumber":"5015",
    "addr:postcode":"31520",
    "addr:street":"New Jesup Hwy",
    "iso:country":"US",
    "sg:address":"5015 New Jesup Hwy",
    "sg:city":"Brunswick",
    "sg:classifiers":[
        {
            "category":"Restaurant",
            "type":"Food & Drink"
        }
    ],
    "sg:phone":"+1 912 265 9501",
    "sg:postcode":"31520",
    "sg:province":"GA",
    "sg:tags":[
        "fast"
    ],
    "wof:name":"Burger King",
    "wof:placetype":"venue"
},
  "geometry": {"coordinates":[-81.52052999999999,31.218762],"type":"Point"}
}