{
  "type": "Feature",
  "properties": {
    "iso:country":"US",
    "sg:address":"405 Rome St",
    "sg:city":"Carrollton",
    "sg:classifiers":[
        {
            "category":"Coffee & Tea",
            "type":"Food & Drink"
        },
        {
            "category":"Restaurant",
            "type":"Food & Drink"
        }
    ],
    "sg:phone":"+1 770 836 3210",
    "sg:postcode":"30117",
    "sg:province":"GA",
    "sg:tags":[
        "lunch",
        "brunch",
        "cafeteria",
        "espresso",
        "breakfast"
    ],
    "wof:name":"Sunny Side Cafe",
    "wof:placetype":"venue"
},
  "geometry": {"coordinates":[-85.074791,33.582244],"type":"Point"}
}