{
  "type": "Feature",
  "properties": {
    "iso:country":"US",
    "sg:address":"123 E Felton Rd",
    "sg:city":"Cartersville",
    "sg:classifiers":[
        {
            "category":"Personal",
            "subcategory":"Beauty Salon",
            "type":"Services"
        }
    ],
    "sg:phone":"+1 770 606 0400",
    "sg:postcode":"30120",
    "sg:province":"GA",
    "sg:tags":[
        "shop"
    ],
    "wof:name":"J C Nails",
    "wof:placetype":"venue"
},
  "geometry": {"coordinates":[-84.79613000000001,34.196725],"type":"Point"}
}