{
  "type": "Feature",
  "properties": {
    "addr:full":"1350 Bluegrass Lakes Pkwy Alpharetta GA 30004",
    "addr:housenumber":"1350",
    "addr:postcode":"30004",
    "addr:street":"Bluegrass Lakes Pkwy",
    "iso:country":"US",
    "sg:address":"1350 Bluegrass Lakes Pkwy",
    "sg:city":"Alpharetta",
    "sg:classifiers":[
        {
            "category":"Wholesale",
            "subcategory":"Hardware",
            "type":"Manufacturing & Wholesale Goods"
        }
    ],
    "sg:phone":"+1 404 915 2244",
    "sg:postcode":"30004",
    "sg:province":"GA",
    "sg:tags":[
        "water"
    ],
    "wof:name":"USA Marketing",
    "wof:placetype":"venue"
},
  "geometry": {"coordinates":[-84.228921,34.115263],"type":"Point"}
}