{
  "type": "Feature",
  "properties": {
    "iso:country":"US",
    "sg:address":"5182 Old Dixie Hwy",
    "sg:city":"Forest Park",
    "sg:classifiers":[
        {
            "category":"Shopping",
            "subcategory":"Department Store",
            "type":"Retail Goods"
        }
    ],
    "sg:phone":"+1 404 366 3224",
    "sg:postcode":"30297",
    "sg:province":"GA",
    "sg:tags":[
        "club",
        "wholesale"
    ],
    "sg:website":"www.uniway.com",
    "wof:name":"Uniway Central Purchasing",
    "wof:placetype":"venue"
},
  "geometry": {"coordinates":[-84.383026,33.615235],"type":"Point"}
}