{
  "type": "Feature",
  "properties": {
    "iso:country":"US",
    "sg:address":"1756 Century Blvd NE",
    "sg:city":"Atlanta",
    "sg:classifiers":[
        {
            "category":"Professional",
            "type":"Services"
        }
    ],
    "sg:phone":"+1 404 636 9985",
    "sg:postcode":"30345",
    "sg:province":"GA",
    "sg:tags":[
        "establishment"
    ],
    "wof:name":"International Alliance",
    "wof:placetype":"venue"
},
  "geometry": {"coordinates":[-84.31492299999999,33.845577],"type":"Point"}
}