{
  "type": "Feature",
  "properties": {
    "addr:full":"3531 Highway 20 SE Conyers GA 30013",
    "addr:housenumber":"3531",
    "addr:postcode":"30013",
    "addr:street":"Highway 20 Se",
    "iso:country":"US",
    "sg:address":"3531 Highway 20 SE",
    "sg:city":"Conyers",
    "sg:classifiers":[
        {
            "category":"Cinema",
            "subcategory":"Movie Rental",
            "type":"Entertainment"
        }
    ],
    "sg:phone":"+1 770 483 4563",
    "sg:postcode":"30013",
    "sg:province":"GA",
    "sg:tags":[
        "game",
        "video"
    ],
    "sg:website":"www.blockbuster.com",
    "wof:name":"Blockbuster Video",
    "wof:placetype":"venue"
},
  "geometry": {"coordinates":[-84.014994,33.595404],"type":"Point"}
}