{
  "type": "Feature",
  "properties": {
    "addr:full":"120 Dorough Rd S Cordele GA 31015",
    "addr:housenumber":"120",
    "addr:postcode":"31015",
    "addr:street":"Dorough Rd",
    "iso:country":"US",
    "sg:address":"120 Dorough Rd S",
    "sg:city":"Cordele",
    "sg:classifiers":[
        {
            "category":"Professional",
            "type":"Services"
        }
    ],
    "sg:phone":"+1 229 276 0706",
    "sg:postcode":"31015",
    "sg:province":"GA",
    "wof:name":"Ronnie C Carr",
    "wof:placetype":"venue"
},
  "geometry": {"coordinates":[-83.679498,31.955289],"type":"Point"}
}