{
  "type": "Feature",
  "properties": {
    "addr:full":"623 Cherokee Ave SE Atlanta GA 30312",
    "addr:housenumber":"623",
    "addr:postcode":"30312",
    "addr:street":"Cherokee Ave Se",
    "iso:country":"US",
    "sg:address":"623 Cherokee Ave SE",
    "sg:city":"Atlanta",
    "sg:classifiers":[
        {
            "category":"Shopping",
            "subcategory":"Pets & Pet Supplies",
            "type":"Retail Goods"
        }
    ],
    "sg:phone":"+1 404 536 8472",
    "sg:postcode":"30312",
    "sg:province":"GA",
    "sg:tags":[
        "furnishing",
        "dog",
        "store",
        "cat"
    ],
    "wof:name":"Pets Are Loving Support",
    "wof:placetype":"venue"
},
  "geometry": {"coordinates":[-84.373621,33.737451],"type":"Point"}
}