{
  "type": "Feature",
  "properties": {
    "addr:full":"8108 Abercorn St Savannah GA 31406",
    "addr:housenumber":"8108",
    "addr:postcode":"31406",
    "addr:street":"Abercorn St",
    "iso:country":"US",
    "sg:address":"8108 Abercorn St",
    "sg:city":"Savannah",
    "sg:classifiers":[
        {
            "category":"Bakery",
            "type":"Food & Drink"
        }
    ],
    "sg:menulink":"http://www.allmenus.com/ga/savannah/103221-panera-bread/menu/",
    "sg:phone":"+1 912 961 0905",
    "sg:postcode":"31406",
    "sg:province":"GA",
    "sg:tags":[
        "american",
        "sandwich",
        "pastry"
    ],
    "wof:name":"Panera Bread",
    "wof:placetype":"venue"
},
  "geometry": {"coordinates":[-81.12483899999999,32.001916],"type":"Point"}
}