{
  "type": "Feature",
  "properties": {
    "addr:full":"4624 Jimmy Carter Blvd Norcross GA 30093",
    "addr:housenumber":"4624",
    "addr:postcode":"30093",
    "addr:street":"Jimmy Carter Blvd",
    "iso:country":"US",
    "sg:address":"4624 Jimmy Carter Blvd",
    "sg:city":"Norcross",
    "sg:classifiers":[
        {
            "category":"Restaurant",
            "type":"Food & Drink"
        }
    ],
    "sg:phone":"+1 678 382 1100",
    "sg:postcode":"30093",
    "sg:province":"GA",
    "wof:name":"Impacto Restaurant & Billards",
    "wof:placetype":"venue"
},
  "geometry": {"coordinates":[-84.191902,33.885399],"type":"Point"}
}