{
  "type": "Feature",
  "properties": {
    "iso:country":"US",
    "sg:address":"1198 Bishop Pl NW",
    "sg:city":"Atlanta",
    "sg:classifiers":[
        {
            "category":"Building & Trades",
            "subcategory":"Electrical",
            "type":"Services"
        }
    ],
    "sg:phone":"+1 404 351 8606",
    "sg:postcode":"30318",
    "sg:province":"GA",
    "sg:tags":[
        "electric",
        "contractor"
    ],
    "wof:name":"Excel Electrical Tech",
    "wof:placetype":"venue"
},
  "geometry": {"coordinates":[-84.410595,33.790659],"type":"Point"}
}