{
  "type": "Feature",
  "properties": {
    "iso:country":"US",
    "sg:address":"1084 Allen Rd",
    "sg:city":"Commerce",
    "sg:classifiers":[
        {
            "category":"Manufacturing",
            "subcategory":"Tools & Machinery",
            "type":"Manufacturing & Wholesale Goods"
        }
    ],
    "sg:phone":"+1 706 335 8165",
    "sg:postcode":"30530",
    "sg:province":"GA",
    "sg:tags":[
        "machine",
        "shop"
    ],
    "wof:name":"Metro Machine Works Inc",
    "wof:placetype":"venue"
},
  "geometry": {"coordinates":[-83.34631400000001,34.182632],"type":"Point"}
}