{
  "type": "Feature",
  "properties": {
    "iso:country":"US",
    "sg:address":"1441 N Expy",
    "sg:city":"Griffin",
    "sg:classifiers":[
        {
            "category":"Restaurant",
            "type":"Food & Drink"
        }
    ],
    "sg:phone":"+1 770 228 4194",
    "sg:postcode":"30223",
    "sg:province":"GA",
    "wof:name":"Captain D's Seafood",
    "wof:placetype":"venue"
},
  "geometry": {"coordinates":[-84.288257,33.256503],"type":"Point"}
}