{
  "type": "Feature",
  "properties": {
    "iso:country":"US",
    "sg:address":"3282 Hampton Ridge Dr NE",
    "sg:city":"Marietta",
    "sg:classifiers":[
        {
            "category":"Professional",
            "subcategory":"Computer Services",
            "type":"Services"
        }
    ],
    "sg:phone":"+1 770 926 9075",
    "sg:postcode":"30066",
    "sg:province":"GA",
    "sg:tags":[
        "consulting"
    ],
    "wof:name":"Add Tech Services Inc",
    "wof:placetype":"venue"
},
  "geometry": {"coordinates":[-84.459473,34.062064],"type":"Point"}
}