{
  "type": "Feature",
  "properties": {
    "iso:country":"US",
    "sg:address":"1312 Marlton Chase Dr",
    "sg:city":"Lawrenceville",
    "sg:classifiers":[
        {
            "category":"Professional",
            "subcategory":"Business Services",
            "type":"Services"
        }
    ],
    "sg:phone":"+1 678 640 9810",
    "sg:postcode":"30044",
    "sg:province":"GA",
    "sg:tags":[
        "holding"
    ],
    "wof:name":"Ahe Lux Holdings",
    "wof:placetype":"venue"
},
  "geometry": {"coordinates":[-84.023246,33.928602],"type":"Point"}
}