{
  "type": "Feature",
  "properties": {
    "iso:country":"US",
    "sg:address":"2380 Cobb Pkwy S",
    "sg:city":"Smyrna",
    "sg:classifiers":[
        {
            "category":"Shopping",
            "subcategory":"Clothing, Apparel, & Fashions",
            "type":"Retail Goods"
        }
    ],
    "sg:phone":"+1 770 850 9394",
    "sg:postcode":"30080",
    "sg:province":"GA",
    "sg:tags":[
        "alteration"
    ],
    "wof:name":"Country Cleaners",
    "wof:placetype":"venue"
},
  "geometry": {"coordinates":[-84.478488,33.893215],"type":"Point"}
}