{
  "type": "Feature",
  "properties": {
    "iso:country":"US",
    "sg:address":"3316 Snapfinger Rd",
    "sg:city":"Lithonia",
    "sg:classifiers":[
        {
            "category":"Personal",
            "subcategory":"Beauty Salon",
            "type":"Services"
        }
    ],
    "sg:phone":"+1 678 418 6507",
    "sg:postcode":"30038",
    "sg:province":"GA",
    "wof:name":"Genesis Hair Salon",
    "wof:placetype":"venue"
},
  "geometry": {"coordinates":[-84.198785,33.684186],"type":"Point"}
}