{
  "type": "Feature",
  "properties": {
    "addr:full":"2247 Wrights Chapel Rd Sumner GA 31789",
    "addr:housenumber":"2247",
    "addr:postcode":"31789",
    "addr:street":"Wrights Chapel Rd",
    "iso:country":"US",
    "sg:address":"2247 Wrights Chapel Rd",
    "sg:city":"Sumner",
    "sg:phone":"+1 229 776 5842",
    "sg:postcode":"31789",
    "sg:province":"GA",
    "sg:tags":[
        "farm",
        "field",
        "corn",
        "crop"
    ],
    "wof:name":"Powell Farms",
    "wof:placetype":"venue"
},
  "geometry": {"coordinates":[-83.698481,31.362896],"type":"Point"}
}