{
  "type": "Feature",
  "properties": {
    "addr:full":"3370 Sugarloaf Pkwy Lawrenceville GA 30044",
    "addr:housenumber":"3370",
    "addr:postcode":"30044",
    "addr:street":"Sugarloaf Pkwy",
    "iso:country":"US",
    "sg:address":"3370 Sugarloaf Pkwy",
    "sg:city":"Lawrenceville",
    "sg:classifiers":[
        {
            "category":"Shopping",
            "subcategory":"Pets & Pet Supplies",
            "type":"Retail Goods"
        }
    ],
    "sg:phone":"+1 770 682 4771",
    "sg:postcode":"30044",
    "sg:province":"GA",
    "sg:tags":[
        "store"
    ],
    "sg:website":"www.petsupermarket.com",
    "wof:name":"Pet Supermarket",
    "wof:placetype":"venue"
},
  "geometry": {"coordinates":[-84.018434,33.921572],"type":"Point"}
}