{
  "type": "Feature",
  "properties": {
    "iso:country":"US",
    "sg:address":"3565 Valeland Ave SW",
    "sg:city":"Atlanta",
    "sg:classifiers":[
        {
            "category":"Health Services",
            "subcategory":"Clinic",
            "type":"Services"
        },
        {
            "category":"Social Services",
            "subcategory":"Job Training",
            "type":"Services"
        }
    ],
    "sg:phone":"+1 404 349 7700",
    "sg:postcode":"30331",
    "sg:province":"GA",
    "sg:tags":[
        "rehabilitation",
        "intervention"
    ],
    "wof:name":"Rehabilitation Exposure Inc",
    "wof:placetype":"venue"
},
  "geometry": {"coordinates":[-84.504735,33.687349],"type":"Point"}
}