{
  "type": "Feature",
  "properties": {
    "iso:country":"US",
    "sg:address":"17 N Court Sq",
    "sg:city":"Newnan",
    "sg:classifiers":[
        {
            "category":"Professional",
            "subcategory":"Business Services",
            "type":"Services"
        }
    ],
    "sg:phone":"+1 770 502 8811",
    "sg:postcode":"30263",
    "sg:province":"GA",
    "wof:name":"Bridges & Associates",
    "wof:placetype":"venue"
},
  "geometry": {"coordinates":[-84.800298,33.375127],"type":"Point"}
}