{
  "type": "Feature",
  "properties": {
    "addr:full":"500 Summer Ter Woodstock GA 30189",
    "addr:housenumber":"500",
    "addr:postcode":"30189",
    "addr:street":"Summer Ter",
    "iso:country":"US",
    "sg:address":"500 Summer Ter",
    "sg:city":"Woodstock",
    "sg:classifiers":[
        {
            "category":"Professional",
            "subcategory":"Business Services",
            "type":"Services"
        }
    ],
    "sg:phone":"+1 770 928 9573",
    "sg:postcode":"30189",
    "sg:province":"GA",
    "wof:name":"Parry & Associates Inc",
    "wof:placetype":"venue"
},
  "geometry": {"coordinates":[-84.575564,34.121322],"type":"Point"}
}