{
  "type": "Feature",
  "properties": {
    "iso:country":"US",
    "sg:address":"75 Ponce De Leon Ave Ne",
    "sg:city":"Atlanta",
    "sg:classifiers":[
        {
            "category":"Food & Beverages",
            "subcategory":"Groceries & Convenience Stores",
            "type":"Retail Goods"
        }
    ],
    "sg:phone":"+1 404 733 4098",
    "sg:postcode":"30308",
    "sg:province":"GA",
    "wof:name":"Peachtree Superette",
    "wof:placetype":"venue"
},
  "geometry": {"coordinates":[-84.38471199999999,33.772056],"type":"Point"}
}