{
  "type": "Feature",
  "properties": {
    "iso:country":"US",
    "sg:address":"1398 Campbell Ridge Rd",
    "sg:city":"Royston",
    "sg:classifiers":[
        {
            "category":"Farming",
            "subcategory":"Farm",
            "type":"Manufacturing & Wholesale Goods"
        }
    ],
    "sg:phone":"+1 706 246 0621",
    "sg:postcode":"30662",
    "sg:province":"GA",
    "wof:name":"Earl Smith Poultry Farm",
    "wof:placetype":"venue"
},
  "geometry": {"coordinates":[-83.13047400000001,34.3055],"type":"Point"}
}