{
  "type": "Feature",
  "properties": {
    "addr:full":"1308 3rd St Macon GA 31201",
    "addr:housenumber":"1308",
    "addr:postcode":"31201",
    "addr:street":"3Rd St",
    "iso:country":"US",
    "sg:address":"1308 3rd St",
    "sg:city":"Macon",
    "sg:classifiers":[
        {
            "category":"Retail",
            "subcategory":"Auto Repair",
            "type":"Services"
        }
    ],
    "sg:phone":"+1 478 745 2791",
    "sg:postcode":"31201",
    "sg:province":"GA",
    "sg:tags":[
        "wheel",
        "axle",
        "alignment"
    ],
    "wof:name":"Brown's Automotive",
    "wof:placetype":"venue"
},
  "geometry": {"coordinates":[-83.635982,32.825206],"type":"Point"}
}