{
  "type": "Feature",
  "properties": {
    "iso:country":"US",
    "sg:address":"3258 Wrightsboro Rd",
    "sg:city":"Augusta",
    "sg:classifiers":[
        {
            "category":"Shopping",
            "subcategory":"Department Store",
            "type":"Retail Goods"
        },
        {
            "category":"Shopping",
            "subcategory":"Discount & Variety Stores",
            "type":"Retail Goods"
        }
    ],
    "sg:phone":"+1 706 667 8175",
    "sg:postcode":"30909",
    "sg:province":"GA",
    "sg:tags":[
        "shop"
    ],
    "sg:website":"http://www.familydollar.com",
    "wof:name":"Family Dollar Stores",
    "wof:placetype":"venue"
},
  "geometry": {"coordinates":[-82.06502,33.469472],"type":"Point"}
}