{
  "type": "Feature",
  "properties": {
    "addr:full":"655 Anderson Walk Marietta GA 30062",
    "addr:housenumber":"655",
    "addr:postcode":"30062",
    "addr:street":"Anderson Walk",
    "iso:country":"US",
    "sg:address":"655 Anderson Walk",
    "sg:city":"Marietta",
    "sg:classifiers":[
        {
            "category":"Banks & Credit Unions",
            "subcategory":"Investment Brokerage",
            "type":"Services"
        }
    ],
    "sg:phone":"+1 678 354 9000",
    "sg:postcode":"30062",
    "sg:province":"GA",
    "sg:tags":[
        "advisory",
        "financial"
    ],
    "wof:name":"Comfort Financial Svc",
    "wof:placetype":"venue"
},
  "geometry": {"coordinates":[-84.51319100000001,33.967518],"type":"Point"}
}