{
  "type": "Feature",
  "properties": {
    "addr:full":"2327 Hwy 140 NW Adairsville GA 30103",
    "addr:housenumber":"2327",
    "addr:postcode":"adairsville;30103",
    "addr:street":"Hwy 140 Nw",
    "iso:country":"US",
    "sg:address":"2327 Hwy 140 NW",
    "sg:city":"Adairsville",
    "sg:classifiers":[
        {
            "category":"Farming",
            "subcategory":"Livestock Farm",
            "type":"Manufacturing & Wholesale Goods"
        }
    ],
    "sg:phone":"+1 770 773 7434",
    "sg:postcode":"30103",
    "sg:province":"GA",
    "sg:tags":[
        "chicken",
        "beef",
        "feedlot",
        "cattle"
    ],
    "wof:name":"Cobb Poultry Farm",
    "wof:placetype":"venue"
},
  "geometry": {"coordinates":[-84.818001,34.380552],"type":"Point"}
}