{
  "type": "Feature",
  "properties": {
    "addr:full":"2920 Satellite Blvd Duluth GA 30096",
    "addr:housenumber":"2920",
    "addr:postcode":"30096",
    "addr:street":"Satellite Blvd",
    "iso:country":"US",
    "sg:address":"2920 Satellite Blvd",
    "sg:city":"Duluth",
    "sg:classifiers":[
        {
            "category":"Autos & Motor Vehicles",
            "subcategory":"Automobile Sales",
            "type":"Retail Goods"
        },
        {
            "category":"Retail",
            "subcategory":"Auto Repair",
            "type":"Services"
        }
    ],
    "sg:phone":"+1 678 475 3500",
    "sg:postcode":"30096",
    "sg:province":"GA",
    "sg:tags":[
        "car"
    ],
    "sg:website":"www.subaruofgwinnett.com/index.htm",
    "wof:name":"Subaru of Gwinnett Atlanta",
    "wof:placetype":"venue"
},
  "geometry": {"coordinates":[-84.112297,33.9632],"type":"Point"}
}