{
  "type": "Feature",
  "properties": {
    "addr:full":"627 S Marietta Pkwy SE Marietta GA 30060",
    "addr:housenumber":"627",
    "addr:postcode":"30060",
    "addr:street":"S Marietta Pkwy Se",
    "iso:country":"US",
    "sg:address":"627 S Marietta Pkwy SE",
    "sg:city":"Marietta",
    "sg:classifiers":[
        {
            "category":"Shopping",
            "subcategory":"Beauty & Cosmetics",
            "type":"Retail Goods"
        }
    ],
    "sg:phone":"+1 770 424 2822",
    "sg:postcode":"30060",
    "sg:province":"GA",
    "sg:tags":[
        "equipment",
        "supply"
    ],
    "wof:name":"Beauty Plus",
    "wof:placetype":"venue"
},
  "geometry": {"coordinates":[-84.534201,33.943327],"type":"Point"}
}