{
  "type": "Feature",
  "properties": {
    "addr:full":"1964 Phillips Rd Lithonia GA 30058",
    "addr:housenumber":"1964",
    "addr:postcode":"30058",
    "addr:street":"Phillips Rd",
    "iso:country":"US",
    "sg:address":"1964 Phillips Rd",
    "sg:city":"Lithonia",
    "sg:classifiers":[
        {
            "category":"Building & Trades",
            "subcategory":"Plumbing",
            "type":"Services"
        },
        {
            "category":"Government",
            "subcategory":"Department Of Motor Vehicles",
            "type":"Public Place"
        },
        {
            "category":"Utilities",
            "subcategory":"Sewage",
            "type":"Services"
        },
        {
            "category":"Building & Trades",
            "subcategory":"Cleaning & Sanitation",
            "type":"Services"
        }
    ],
    "sg:phone":"+1 770 482 8746",
    "sg:postcode":"30058",
    "sg:province":"GA",
    "sg:tags":[
        "cleaner",
        "systems-cleaning",
        "grease",
        "tank",
        "septic",
        "repairer",
        "sewer",
        "trap",
        "plumbing-drain"
    ],
    "sg:website":"http://www.cmrogersandsons.com",
    "wof:name":"Rogers & Sons Inc",
    "wof:placetype":"venue"
},
  "geometry": {"coordinates":[-84.13320899999999,33.731697],"type":"Point"}
}