{
  "type": "Feature",
  "properties": {
    "iso:country":"US",
    "sg:address":"2099 State Rte 133 S",
    "sg:city":"Moultrie",
    "sg:classifiers":[
        {
            "category":"Manufacturing",
            "subcategory":"Aerospace",
            "type":"Manufacturing & Wholesale Goods"
        }
    ],
    "sg:phone":"+1 229 985 2045",
    "sg:postcode":"31788",
    "sg:province":"GA",
    "sg:tags":[
        "aircraft",
        "parts",
        "mfg"
    ],
    "sg:website":"www.mauleairinc.com",
    "wof:name":"Maule Air Inc",
    "wof:placetype":"venue"
},
  "geometry": {"coordinates":[-83.760362,31.176059],"type":"Point"}
}