{
  "type": "Feature",
  "properties": {
    "addr:full":"106 S Hagan Bridge Rd Hahira GA 31632",
    "addr:housenumber":"106",
    "addr:postcode":"31632",
    "addr:street":"S Hagan Bridge Rd",
    "iso:country":"US",
    "sg:address":"106 S Hagan Bridge Rd",
    "sg:city":"Hahira",
    "sg:classifiers":[
        {
            "category":"Home & Garden",
            "subcategory":"Building Materials",
            "type":"Retail Goods"
        },
        {
            "category":"Building & Trades",
            "subcategory":"Construction",
            "type":"Services"
        },
        {
            "category":"Military Area",
            "subcategory":"Armory",
            "type":"Public Place"
        }
    ],
    "sg:phone":"+1 229 460 1434",
    "sg:postcode":"31632",
    "sg:province":"GA",
    "sg:tags":[
        "repair",
        "fence-sales",
        "fence",
        "contractor"
    ],
    "wof:name":"A1 Quality Fence Company",
    "wof:placetype":"venue"
},
  "geometry": {"coordinates":[-83.360178,30.992859],"type":"Point"}
}