{
  "type": "Feature",
  "properties": {
    "iso:country":"US",
    "sg:address":"20 Concourse Pkwy NE",
    "sg:city":"Atlanta",
    "sg:classifiers":[
        {
            "category":"Professional",
            "type":"Services"
        }
    ],
    "sg:phone":"+1 678 443 7900",
    "sg:postcode":"30328",
    "sg:province":"GA",
    "sg:tags":[
        "establishment"
    ],
    "wof:name":"Yodlee Inc",
    "wof:placetype":"venue"
},
  "geometry": {"coordinates":[-84.35118199999999,33.916461],"type":"Point"}
}