{
  "type": "Feature",
  "properties": {
    "iso:country":"US",
    "sg:address":"8025 Westside Pkwy",
    "sg:city":"Alpharetta",
    "sg:classifiers":[
        {
            "category":"Professional",
            "subcategory":"Lawyer & Legal Services",
            "type":"Services"
        },
        {
            "category":"Banks & Credit Unions",
            "subcategory":"Financial Services",
            "type":"Services"
        }
    ],
    "sg:phone":"+1 770 346 9722",
    "sg:postcode":"30004",
    "sg:province":"GA",
    "sg:tags":[
        "attorney",
        "investment",
        "closed"
    ],
    "wof:name":"Jenkins & Gallagher LLC",
    "wof:placetype":"venue"
},
  "geometry": {"coordinates":[-84.28613199999999,34.067354],"type":"Point"}
}