{
  "type": "Feature",
  "properties": {
    "iso:country":"US",
    "sg:address":"1 Dunwoody Park",
    "sg:city":"Atlanta",
    "sg:classifiers":[
        {
            "category":"Health Services",
            "subcategory":"Health Practitioner",
            "type":"Services"
        }
    ],
    "sg:phone":"+1 770 394 4110",
    "sg:postcode":"30338",
    "sg:province":"GA",
    "sg:tags":[
        "therapy",
        "physical"
    ],
    "wof:name":"Injury Prevention & Management Consulting",
    "wof:placetype":"venue"
},
  "geometry": {"coordinates":[-84.31374599999999,33.924051],"type":"Point"}
}