{
  "type": "Feature",
  "properties": {
    "iso:country":"US",
    "sg:address":"225 Peachtree St NE",
    "sg:city":"Atlanta",
    "sg:classifiers":[
        {
            "category":"Social Services",
            "subcategory":"Job Training",
            "type":"Services"
        }
    ],
    "sg:phone":"+1 404 446 4174",
    "sg:postcode":"30303",
    "sg:province":"GA",
    "sg:tags":[
        "consultant"
    ],
    "wof:name":"Cifal Atlanta",
    "wof:placetype":"venue"
},
  "geometry": {"coordinates":[-84.39510300000001,33.748291],"type":"Point"}
}