{
  "type": "Feature",
  "properties": {
    "addr:full":"1322 Hendrix Ave Atlanta GA 30344",
    "addr:housenumber":"1322",
    "addr:postcode":"30344",
    "addr:street":"Hendrix Ave",
    "iso:country":"US",
    "sg:address":"1322 Hendrix Ave",
    "sg:city":"Atlanta",
    "sg:classifiers":[
        {
            "category":"Organizations",
            "subcategory":"Religious Organization",
            "type":"Services"
        }
    ],
    "sg:phone":"+1 404 763 4390",
    "sg:postcode":"30344",
    "sg:province":"GA",
    "wof:name":"Abel In Christ Inc",
    "wof:placetype":"venue"
},
  "geometry": {"coordinates":[-84.432778,33.67758],"type":"Point"}
}