{
  "type": "Feature",
  "properties": {
    "addr:full":"4225 Union Hill Rd Alpharetta GA 30004",
    "addr:housenumber":"4225",
    "addr:postcode":"30004",
    "addr:street":"Union Hill Rd",
    "iso:country":"US",
    "sg:address":"4225 Union Hill Rd",
    "sg:city":"Alpharetta",
    "sg:classifiers":[
        {
            "category":"Retail",
            "subcategory":"Animal Services",
            "type":"Services"
        }
    ],
    "sg:phone":"+1 770 753 9998",
    "sg:postcode":"30004",
    "sg:province":"GA",
    "sg:tags":[
        "pet",
        "grooming",
        "washing"
    ],
    "wof:name":"Waggin Tails Boarding Grooming",
    "wof:placetype":"venue"
},
  "geometry": {"coordinates":[-84.283109,34.081116],"type":"Point"}
}