{
  "type": "Feature",
  "properties": {
    "iso:country":"US",
    "sg:address":"600 Progress Industrial Blvd",
    "sg:city":"Lawrenceville",
    "sg:classifiers":[
        {
            "category":"Building & Trades",
            "subcategory":"Construction",
            "type":"Services"
        },
        {
            "category":"Home & Garden",
            "subcategory":"Home Furnishings",
            "type":"Retail Goods"
        }
    ],
    "sg:phone":"+1 770 339 8644",
    "sg:postcode":"30043",
    "sg:province":"GA",
    "sg:tags":[
        "venetian",
        "blind",
        "window",
        "installation",
        "treatment"
    ],
    "sg:website":"www.windowco.net",
    "wof:name":"Bartimaeus Inc",
    "wof:placetype":"venue"
},
  "geometry": {"coordinates":[-83.961077,33.990278],"type":"Point"}
}