{
  "type": "Feature",
  "properties": {
    "addr:full":"3807 State Rte 32 W Douglas GA 31533",
    "addr:housenumber":"3807",
    "addr:postcode":"31533",
    "addr:street":"State Rte 32 W",
    "iso:country":"US",
    "sg:address":"3807 State Rte 32 W",
    "sg:city":"Douglas",
    "sg:classifiers":[
        {
            "category":"Shopping",
            "subcategory":"Used Merchandise",
            "type":"Retail Goods"
        }
    ],
    "sg:phone":"+1 912 393 1153",
    "sg:postcode":"31533",
    "sg:province":"GA",
    "sg:tags":[
        "second",
        "store",
        "hand"
    ],
    "wof:name":"Treasures",
    "wof:placetype":"venue"
},
  "geometry": {"coordinates":[-82.87672000000001,31.514809],"type":"Point"}
}