{
  "type": "Feature",
  "properties": {
    "iso:country":"US",
    "sg:address":"1034 Wesley Chapel Rd",
    "sg:city":"Dahlonega",
    "sg:classifiers":[
        {
            "category":"Recreation",
            "type":"Entertainment"
        }
    ],
    "sg:phone":"+1 706 864 7251",
    "sg:postcode":"30533",
    "sg:province":"GA",
    "sg:tags":[
        "stable"
    ],
    "sg:website":"www.springermountainstables.com",
    "wof:name":"Springer Mountain Stables",
    "wof:placetype":"venue"
},
  "geometry": {"coordinates":[-84.17491800000001,34.543794],"type":"Point"}
}