{
  "type": "Feature",
  "properties": {
    "addr:full":"3125 Park Chase Alpharetta GA 30022",
    "addr:housenumber":"3125",
    "addr:postcode":"30022",
    "addr:street":"Park Chase",
    "iso:country":"US",
    "sg:address":"3125 Park Chase",
    "sg:city":"Alpharetta",
    "sg:classifiers":[
        {
            "category":"Insurance",
            "subcategory":"Insurance Agent",
            "type":"Services"
        }
    ],
    "sg:phone":"+1 770 594 9344",
    "sg:postcode":"30022",
    "sg:province":"GA",
    "wof:name":"Insurance Solutions Group",
    "wof:placetype":"venue"
},
  "geometry": {"coordinates":[-84.26982700000001,34.001138],"type":"Point"}
}