{
  "type": "Feature",
  "properties": {
    "addr:full":"1809 Trailing Ivy Ct Marietta GA 30062",
    "addr:housenumber":"1809",
    "addr:postcode":"30062",
    "addr:street":"Trailing Ivy Ct",
    "iso:country":"US",
    "sg:address":"1809 Trailing Ivy Ct",
    "sg:city":"Marietta",
    "sg:classifiers":[
        {
            "category":"Professional",
            "type":"Services"
        }
    ],
    "sg:phone":"+1 770 977 4337",
    "sg:postcode":"30062",
    "sg:province":"GA",
    "wof:name":"VJ&h Inc",
    "wof:placetype":"venue"
},
  "geometry": {"coordinates":[-84.43407000000001,33.994418],"type":"Point"}
}