{
  "type": "Feature",
  "properties": {
    "iso:country":"US",
    "sg:address":"300 Longer Dr",
    "sg:city":"Peachtree City",
    "sg:classifiers":[
        {
            "category":"Professional",
            "type":"Services"
        }
    ],
    "sg:phone":"+1 770 631 8588",
    "sg:postcode":"30269",
    "sg:province":"GA",
    "wof:name":"Chemtron",
    "wof:placetype":"venue"
},
  "geometry": {"coordinates":[-84.589983,33.417206],"type":"Point"}
}