{
  "type": "Feature",
  "properties": {
    "addr:full":"3455 Peachtree Industrial Blvd Duluth GA 30096",
    "addr:housenumber":"3455",
    "addr:postcode":"30096",
    "addr:street":"Peachtree Industrial Blvd",
    "iso:country":"US",
    "sg:address":"3455 Peachtree Industrial Blvd",
    "sg:city":"Duluth",
    "sg:classifiers":[
        {
            "category":"Food & Beverages",
            "subcategory":"Groceries & Convenience Stores",
            "type":"Retail Goods"
        }
    ],
    "sg:phone":"+1 770 476 7914",
    "sg:postcode":"30096",
    "sg:province":"GA",
    "wof:name":"Kroger",
    "wof:placetype":"venue"
},
  "geometry": {"coordinates":[-84.17152400000001,34.007745],"type":"Point"}
}