{
  "type": "Feature",
  "properties": {
    "iso:country":"US",
    "sg:address":"6624 Jimmy Carter Blvd",
    "sg:city":"Norcross",
    "sg:classifiers":[
        {
            "category":"Shopping",
            "subcategory":"Mobile Phones",
            "type":"Retail Goods"
        }
    ],
    "sg:phone":"+1 678 994 0737",
    "sg:postcode":"30071",
    "sg:province":"GA",
    "wof:name":"S E Wireless",
    "wof:placetype":"venue"
},
  "geometry": {"coordinates":[-84.23110200000001,33.935398],"type":"Point"}
}