{
  "type": "Feature",
  "properties": {
    "addr:full":"475 Dividend Dr Peachtree City GA 30269",
    "addr:housenumber":"475",
    "addr:postcode":"30269",
    "addr:street":"Dividend Dr",
    "iso:country":"US",
    "sg:address":"475 Dividend Dr",
    "sg:city":"Peachtree City",
    "sg:classifiers":[
        {
            "category":"Organizations",
            "subcategory":"Religious Organization",
            "type":"Services"
        }
    ],
    "sg:phone":"+1 770 631 0267",
    "sg:postcode":"30269",
    "sg:province":"GA",
    "wof:name":"Bethlehem Baptist Church",
    "wof:placetype":"venue"
},
  "geometry": {"coordinates":[-84.57543800000001,33.369872],"type":"Point"}
}