{
  "type": "Feature",
  "properties": {
    "addr:full":"1300 Bull St Savannah GA 31401",
    "addr:housenumber":"1300",
    "addr:postcode":"31401",
    "addr:street":"Bull St",
    "iso:country":"US",
    "sg:address":"1300 Bull St",
    "sg:city":"Savannah",
    "sg:classifiers":[
        {
            "category":"Building & Trades",
            "subcategory":"Construction",
            "type":"Services"
        }
    ],
    "sg:phone":"+1 912 233 2111",
    "sg:postcode":"31401",
    "sg:province":"GA",
    "sg:tags":[
        "porch",
        "enclosure",
        "patio",
        "deck"
    ],
    "wof:name":"Southern Home Products Inc",
    "wof:placetype":"venue"
},
  "geometry": {"coordinates":[-81.09801400000001,32.062818],"type":"Point"}
}