{
  "type": "Feature",
  "properties": {
    "addr:full":"1404 O St Brunswick GA 31520",
    "addr:housenumber":"1404",
    "addr:postcode":"31520",
    "addr:street":"O St",
    "iso:country":"US",
    "sg:address":"1404 O St",
    "sg:city":"Brunswick",
    "sg:classifiers":[
        {
            "category":"Organizations",
            "subcategory":"Religious Organization",
            "type":"Services"
        }
    ],
    "sg:phone":"+1 912 264 8652",
    "sg:postcode":"31520",
    "sg:province":"GA",
    "wof:name":"O Street Church Of God",
    "wof:placetype":"venue"
},
  "geometry": {"coordinates":[-81.492929,31.164227],"type":"Point"}
}