{
  "type": "Feature",
  "properties": {
    "iso:country":"US",
    "sg:address":"3077 Francine Dr",
    "sg:city":"Decatur",
    "sg:classifiers":[
        {
            "category":"Building & Trades",
            "subcategory":"Landscaping Services",
            "type":"Services"
        }
    ],
    "sg:phone":"+1 404 570 4377",
    "sg:postcode":"30033",
    "sg:province":"GA",
    "wof:name":"Drd Lawn Svcs",
    "wof:placetype":"venue"
},
  "geometry": {"coordinates":[-84.265141,33.814043],"type":"Point"}
}