{
  "type": "Feature",
  "properties": {
    "iso:country":"US",
    "sg:address":"2735 Candler Rd",
    "sg:city":"Decatur",
    "sg:classifiers":[
        {
            "category":"Personal",
            "subcategory":"Day Spa",
            "type":"Services"
        }
    ],
    "sg:phone":"+1 404 343 4657",
    "sg:postcode":"30034",
    "sg:province":"GA",
    "wof:name":"Braids & Beyond",
    "wof:placetype":"venue"
},
  "geometry": {"coordinates":[-84.271895,33.709633],"type":"Point"}
}