{
  "type": "Feature",
  "properties": {
    "addr:full":"6731 Davidson Ct Lithonia GA 30058",
    "addr:housenumber":"6731",
    "addr:postcode":"30058",
    "addr:street":"Davidson Ct",
    "iso:country":"US",
    "sg:address":"6731 Davidson Ct",
    "sg:city":"Lithonia",
    "sg:classifiers":[
        {
            "category":"Professional",
            "subcategory":"Business Services",
            "type":"Services"
        }
    ],
    "sg:phone":"+1 770 482 4543",
    "sg:postcode":"30058",
    "sg:province":"GA",
    "wof:name":"Industrial Hlth & Safety Svcs",
    "wof:placetype":"venue"
},
  "geometry": {"coordinates":[-84.11325600000001,33.704608],"type":"Point"}
}