{
  "type": "Feature",
  "properties": {
    "addr:full":"1411 Chelsea Downs Ln NE Conyers GA 30013",
    "addr:housenumber":"1411",
    "addr:postcode":"30013",
    "addr:street":"Chelsea Downs Ln Ne",
    "iso:country":"US",
    "sg:address":"1411 Chelsea Downs Ln NE",
    "sg:city":"Conyers",
    "sg:classifiers":[
        {
            "category":"Professional",
            "subcategory":"Lawyer & Legal Services",
            "type":"Services"
        }
    ],
    "sg:phone":"+1 770 483 7111",
    "sg:postcode":"30013",
    "sg:province":"GA",
    "sg:tags":[
        "attorney"
    ],
    "wof:name":"Steven E Conner Law Office",
    "wof:placetype":"venue"
},
  "geometry": {"coordinates":[-83.96878,33.678838],"type":"Point"}
}