{
  "type": "Feature",
  "properties": {
    "addr:full":"1448 Wilson Rd Rossville GA 30741",
    "addr:housenumber":"1448",
    "addr:postcode":"30741",
    "addr:street":"Wilson Rd",
    "iso:country":"US",
    "sg:address":"1448 Wilson Rd",
    "sg:city":"Rossville",
    "sg:classifiers":[
        {
            "category":"Food & Beverages",
            "subcategory":"Groceries & Convenience Stores",
            "type":"Retail Goods"
        }
    ],
    "sg:phone":"+1 706 866 6913",
    "sg:postcode":"30741",
    "sg:province":"GA",
    "wof:name":"Grocery Store Inc",
    "wof:placetype":"venue"
},
  "geometry": {"coordinates":[-85.30991899999999,34.96669],"type":"Point"}
}