{
  "type": "Feature",
  "properties": {
    "addr:full":"5393 Glenbrooke Trl Atlanta GA 30338",
    "addr:housenumber":"5393",
    "addr:postcode":"30338",
    "addr:street":"Glenbrooke Trl",
    "iso:country":"US",
    "sg:address":"5393 Glenbrooke Trl",
    "sg:city":"Atlanta",
    "sg:classifiers":[
        {
            "category":"Wholesale",
            "subcategory":"Non-durable Goods",
            "type":"Manufacturing & Wholesale Goods"
        }
    ],
    "sg:phone":"+1 770 390 0810",
    "sg:postcode":"30338",
    "sg:province":"GA",
    "wof:name":"Sst Enterprises Inc",
    "wof:placetype":"venue"
},
  "geometry": {"coordinates":[-84.295115,33.95845],"type":"Point"}
}