{
  "type": "Feature",
  "properties": {
    "iso:country":"US",
    "sg:address":"614 Blue Flag Ln",
    "sg:city":"Fairburn",
    "sg:classifiers":[
        {
            "category":"Building & Trades",
            "subcategory":"Construction",
            "type":"Services"
        }
    ],
    "sg:phone":"+1 770 964 8634",
    "sg:postcode":"30213",
    "sg:province":"GA",
    "sg:tags":[
        "hanging",
        "contractor"
    ],
    "wof:name":"Pilgrim S Painting",
    "wof:placetype":"venue"
},
  "geometry": {"coordinates":[-84.591769,33.57609],"type":"Point"}
}