{
  "type": "Feature",
  "properties": {
    "iso:country":"US",
    "sg:address":"2300 Global Forum Blvd",
    "sg:city":"Atlanta",
    "sg:classifiers":[
        {
            "category":"Organizations",
            "subcategory":"Professional Association",
            "type":"Services"
        }
    ],
    "sg:phone":"+1 404 643 7641",
    "sg:postcode":"30340",
    "sg:province":"GA",
    "sg:tags":[
        "agency",
        "bureau",
        "entertainment"
    ],
    "wof:name":"Infinite Potential",
    "wof:placetype":"venue"
},
  "geometry": {"coordinates":[-84.253433,33.916431],"type":"Point"}
}