{
  "type": "Feature",
  "properties": {
    "iso:country":"US",
    "sg:address":"406 Line Creek Dr",
    "sg:city":"Peachtree City",
    "sg:classifiers":[
        {
            "category":"Wholesale",
            "subcategory":"Construction Materials",
            "type":"Manufacturing & Wholesale Goods"
        }
    ],
    "sg:phone":"+1 770 631 9710",
    "sg:postcode":"30269",
    "sg:province":"GA",
    "sg:tags":[
        "lumber"
    ],
    "wof:name":"Builder Marts Of America",
    "wof:placetype":"venue"
},
  "geometry": {"coordinates":[-84.60160500000001,33.396768],"type":"Point"}
}