{
  "type": "Feature",
  "properties": {
    "addr:full":"16634 Blackshear Hwy Bristol GA 31518",
    "addr:postcode":"16634;31518",
    "addr:street":"Blackshear Hwy",
    "iso:country":"US",
    "sg:address":"16634 Blackshear Hwy",
    "sg:city":"Bristol",
    "sg:classifiers":[
        {
            "category":"Freight",
            "type":"Transportation"
        }
    ],
    "sg:phone":"+1 912 367 7719",
    "sg:postcode":"31518",
    "sg:province":"GA",
    "sg:tags":[
        "operator",
        "local",
        "trucking"
    ],
    "wof:name":"Morris Transport",
    "wof:placetype":"venue"
},
  "geometry": {"coordinates":[-82.21762099999999,31.565762],"type":"Point"}
}