{
  "type": "Feature",
  "properties": {
    "addr:full":"2190 US Hwy 441 Dublin GA 31021",
    "addr:housenumber":"2190",
    "addr:postcode":"31021",
    "addr:street":"Us Hwy 441",
    "iso:country":"US",
    "sg:address":"2190 US Hwy 441",
    "sg:city":"Dublin",
    "sg:classifiers":[
        {
            "category":"Restaurant",
            "type":"Food & Drink"
        }
    ],
    "sg:phone":"+1 478 296 3900",
    "sg:postcode":"31021",
    "sg:province":"GA",
    "sg:tags":[
        "eating"
    ],
    "wof:name":"Ruby Tuesday",
    "wof:placetype":"venue"
},
  "geometry": {"coordinates":[-82.90894900000001,32.533609],"type":"Point"}
}