{
  "type": "Feature",
  "properties": {
    "iso:country":"US",
    "sg:address":"3294 Medlock Bridge Rd",
    "sg:city":"Norcross",
    "sg:classifiers":[
        {
            "category":"Health Services",
            "subcategory":"Dentist",
            "type":"Services"
        }
    ],
    "sg:phone":"+1 770 446 7425",
    "sg:postcode":"30092",
    "sg:province":"GA",
    "sg:tags":[
        "orthodontist"
    ],
    "wof:name":"Pickron Orthodonics",
    "wof:placetype":"venue"
},
  "geometry": {"coordinates":[-84.20819899999999,33.962898],"type":"Point"}
}