{
  "type": "Feature",
  "properties": {
    "iso:country":"US",
    "sg:address":"105 E King St",
    "sg:city":"Sylvester",
    "sg:classifiers":[
        {
            "category":"Government",
            "subcategory":"Office",
            "type":"Public Place"
        }
    ],
    "sg:phone":"+1 229 776 8508",
    "sg:postcode":"31791",
    "sg:province":"GA",
    "sg:tags":[
        "village"
    ],
    "sg:website":"www.cityofsylvester.com",
    "wof:name":"Sylvester City Light & Water",
    "wof:placetype":"venue"
},
  "geometry": {"coordinates":[-83.836603,31.544553],"type":"Point"}
}