{
  "type": "Feature",
  "properties": {
    "iso:country":"US",
    "sg:address":"533 Johnson Ferry Rd",
    "sg:city":"Marietta",
    "sg:classifiers":[
        {
            "category":"Manufacturing",
            "subcategory":"Printing",
            "type":"Manufacturing & Wholesale Goods"
        }
    ],
    "sg:phone":"+1 678 560 8552",
    "sg:postcode":"30068",
    "sg:province":"GA",
    "sg:tags":[
        "publisher",
        "software"
    ],
    "wof:name":"Logic Junction Inc",
    "wof:placetype":"venue"
},
  "geometry": {"coordinates":[-84.411725,33.961964],"type":"Point"}
}