{
  "type": "Feature",
  "properties": {
    "iso:country":"US",
    "sg:address":"3030 Washington Rd",
    "sg:city":"Augusta",
    "sg:classifiers":[
        {
            "category":"Personal",
            "subcategory":"Barber",
            "type":"Services"
        }
    ],
    "sg:phone":"+1 706 736 7468",
    "sg:postcode":"30907",
    "sg:province":"GA",
    "sg:tags":[
        "shop"
    ],
    "wof:name":"Razor Gator",
    "wof:placetype":"venue"
},
  "geometry": {"coordinates":[-82.05181,33.513241],"type":"Point"}
}