{
  "type": "Feature",
  "properties": {
    "addr:full":"3706 Atlanta Hwy Athens GA 30606",
    "addr:housenumber":"3706",
    "addr:postcode":"30606",
    "addr:street":"Atlanta Hwy",
    "iso:country":"US",
    "sg:address":"3706 Atlanta Hwy",
    "sg:city":"Athens",
    "sg:classifiers":[
        {
            "category":"Education",
            "subcategory":"Special Training",
            "type":"Public Place"
        }
    ],
    "sg:phone":"+1 706 354 4402",
    "sg:postcode":"30606",
    "sg:province":"GA",
    "wof:name":"A1 Dui Defensive Driving Schl",
    "wof:placetype":"venue"
},
  "geometry": {"coordinates":[-83.46592099999999,33.940834],"type":"Point"}
}