{
  "type": "Feature",
  "properties": {
    "addr:full":"329 Concord St NE Pelham GA 31779",
    "addr:housenumber":"329",
    "addr:postcode":"31779",
    "addr:street":"Concord St Ne",
    "iso:country":"US",
    "sg:address":"329 Concord St NE",
    "sg:city":"Pelham",
    "sg:classifiers":[
        {
            "category":"Personal",
            "subcategory":"Beauty Salon",
            "type":"Services"
        }
    ],
    "sg:phone":"+1 229 294 9208",
    "sg:postcode":"31779",
    "sg:province":"GA",
    "sg:tags":[
        "shop"
    ],
    "wof:name":"Berts Hair Affair",
    "wof:placetype":"venue"
},
  "geometry": {"coordinates":[-84.149252,31.135197],"type":"Point"}
}