{
  "type": "Feature",
  "properties": {
    "addr:full":"1905 Scenic Hwy N Ste 230 Snellville GA 30078",
    "addr:housenumber":"1905",
    "addr:postcode":"30078",
    "addr:street":"Scenic Hwy N Ste 230",
    "iso:country":"US",
    "sg:address":"1905 Scenic Hwy N Ste 230",
    "sg:city":"Snellville",
    "sg:classifiers":[
        {
            "category":"Professional",
            "subcategory":"Accounting & Tax Preparation",
            "type":"Services"
        }
    ],
    "sg:phone":"+1 770 979 9878",
    "sg:postcode":"30078",
    "sg:province":"GA",
    "sg:tags":[
        "accountant"
    ],
    "sg:website":"www.hrblock.com",
    "wof:name":"H & R Block",
    "wof:placetype":"venue"
},
  "geometry": {"coordinates":[-84.014937,33.876778],"type":"Point"}
}