{
  "type": "Feature",
  "properties": {
    "iso:country":"US",
    "sg:address":"650 Glynn St N",
    "sg:city":"Fayetteville",
    "sg:classifiers":[
        {
            "category":"Restaurant",
            "type":"Food & Drink"
        }
    ],
    "sg:phone":"+1 770 460 3030",
    "sg:postcode":"30214",
    "sg:province":"GA",
    "sg:tags":[
        "eating",
        "pizza"
    ],
    "wof:name":"Pizza Hut",
    "wof:placetype":"venue"
},
  "geometry": {"coordinates":[-84.45268799999999,33.460474],"type":"Point"}
}