{
  "type": "Feature",
  "properties": {
    "iso:country":"US",
    "sg:address":"4132 Hwy 278 NE",
    "sg:city":"Covington",
    "sg:classifiers":[
        {
            "category":"Retail",
            "subcategory":"Auto Rental",
            "type":"Services"
        }
    ],
    "sg:phone":"+1 770 788 5570",
    "sg:postcode":"30014",
    "sg:province":"GA",
    "sg:tags":[
        "passenger",
        "car"
    ],
    "wof:name":"Enterprise Rent-A-Car",
    "wof:placetype":"venue"
},
  "geometry": {"coordinates":[-83.85275799999999,33.602925],"type":"Point"}
}