{
  "type": "Feature",
  "properties": {
    "addr:full":"306 Telfair St Augusta GA 30901",
    "addr:housenumber":"306",
    "addr:postcode":"30901",
    "addr:street":"Telfair St",
    "iso:country":"US",
    "sg:address":"306 Telfair St",
    "sg:city":"Augusta",
    "sg:classifiers":[
        {
            "category":"Building & Trades",
            "subcategory":"Construction",
            "type":"Services"
        }
    ],
    "sg:phone":"+1 706 722 5313",
    "sg:postcode":"30901",
    "sg:province":"GA",
    "sg:tags":[
        "industrial",
        "wallcoverings-installation",
        "wallpaper",
        "contractor",
        "contractors-commercial",
        "painting"
    ],
    "wof:name":"Ela Enterprises Inc",
    "wof:placetype":"venue"
},
  "geometry": {"coordinates":[-81.95578,33.468206],"type":"Point"}
}