{
  "type": "Feature",
  "properties": {
    "addr:full":"5465 Lakeshore Rd Columbus GA 31907",
    "addr:housenumber":"5465",
    "addr:postcode":"31907",
    "addr:street":"Lakeshore Rd",
    "iso:country":"US",
    "sg:address":"5465 Lakeshore Rd",
    "sg:city":"Columbus",
    "sg:classifiers":[
        {
            "category":"Building & Trades",
            "subcategory":"Construction",
            "type":"Services"
        }
    ],
    "sg:phone":"+1 770 904 4000",
    "sg:postcode":"31907",
    "sg:province":"GA",
    "sg:tags":[
        "general",
        "contractor"
    ],
    "wof:name":"Heavy Constructors",
    "wof:placetype":"venue"
},
  "geometry": {"coordinates":[-84.888434,32.518719],"type":"Point"}
}