{
  "type": "Feature",
  "properties": {
    "addr:full":"6814 State Rte 85 Riverdale GA 30274",
    "addr:housenumber":"6814",
    "addr:postcode":"30274",
    "addr:street":"State Rte 85",
    "iso:country":"US",
    "sg:address":"6814 State Rte 85",
    "sg:city":"Riverdale",
    "sg:classifiers":[
        {
            "category":"Restaurant",
            "type":"Food & Drink"
        }
    ],
    "sg:phone":"+1 770 991 0830",
    "sg:postcode":"30274",
    "sg:province":"GA",
    "sg:tags":[
        "eating"
    ],
    "wof:name":"Mrs Winners Chicken & Biscuits",
    "wof:placetype":"venue"
},
  "geometry": {"coordinates":[-84.411654,33.579825],"type":"Point"}
}