{
  "type": "Feature",
  "properties": {
    "iso:country":"US",
    "sg:address":"250 Industrial Blvd",
    "sg:city":"Chatsworth",
    "sg:classifiers":[
        {
            "category":"Manufacturing",
            "subcategory":"Textiles",
            "type":"Manufacturing & Wholesale Goods"
        }
    ],
    "sg:phone":"+1 706 695 9691",
    "sg:postcode":"30705",
    "sg:province":"GA",
    "sg:tags":[
        "spinning",
        "mill",
        "yarn",
        "fabric"
    ],
    "wof:name":"Shaw Industries Plant 84",
    "wof:placetype":"venue"
},
  "geometry": {"coordinates":[-84.78609,34.790174],"type":"Point"}
}