{
  "type": "Feature",
  "properties": {
    "addr:full":"1120 Marks Church Rd Augusta GA 30909",
    "addr:housenumber":"1120",
    "addr:postcode":"30909",
    "addr:street":"Marks Church Rd",
    "iso:country":"US",
    "sg:address":"1120 Marks Church Rd",
    "sg:city":"Augusta",
    "sg:classifiers":[
        {
            "category":"Place Of Worship",
            "subcategory":"Church",
            "type":"Public Place"
        },
        {
            "category":"Place Of Worship",
            "type":"Public Place"
        },
        {
            "category":"Organizations",
            "subcategory":"Religious Organization",
            "type":"Services"
        }
    ],
    "sg:phone":"+1 706 736 1211",
    "sg:postcode":"30909",
    "sg:province":"GA",
    "sg:tags":[
        "clergy",
        "churches-baptist"
    ],
    "wof:name":"Georgia Baptist Convention",
    "wof:placetype":"venue"
},
  "geometry": {"coordinates":[-82.08363199999999,33.481497],"type":"Point"}
}