{
  "type": "Feature",
  "properties": {
    "iso:country":"US",
    "sg:address":"2001 Riverside Dr",
    "sg:city":"Gainesville",
    "sg:classifiers":[
        {
            "category":"Building & Trades",
            "subcategory":"Construction",
            "type":"Services"
        }
    ],
    "sg:phone":"+1 770 297 6264",
    "sg:postcode":"30501",
    "sg:province":"GA",
    "sg:tags":[
        "house"
    ],
    "wof:name":"Turner Construction Company",
    "wof:placetype":"venue"
},
  "geometry": {"coordinates":[-83.831063,34.332809],"type":"Point"}
}