{
  "type": "Feature",
  "properties": {
    "iso:country":"US",
    "sg:address":"114 Burleyson Dr",
    "sg:city":"Mc Donough",
    "sg:classifiers":[
        {
            "category":"Building & Trades",
            "subcategory":"Landscaping Services",
            "type":"Services"
        }
    ],
    "sg:phone":"+1 770 957 2777",
    "sg:postcode":"30253",
    "sg:province":"GA",
    "sg:tags":[
        "landscape"
    ],
    "wof:name":"Ponds By John",
    "wof:placetype":"venue"
},
  "geometry": {"coordinates":[-84.17317300000001,33.451525],"type":"Point"}
}