{
  "type": "Feature",
  "properties": {
    "iso:country":"US",
    "sg:address":"1186 W Broad St",
    "sg:city":"Athens",
    "sg:classifiers":[
        {
            "category":"Insurance",
            "subcategory":"Insurance Agent",
            "type":"Services"
        }
    ],
    "sg:phone":"+1 706 208 1900",
    "sg:postcode":"30606",
    "sg:province":"GA",
    "wof:name":"Abbey Insurance",
    "wof:placetype":"venue"
},
  "geometry": {"coordinates":[-83.390969,33.954256],"type":"Point"}
}