{
  "type": "Feature",
  "properties": {
    "iso:country":"US",
    "sg:address":"3774 Lavista Rd",
    "sg:city":"Tucker",
    "sg:classifiers":[
        {
            "category":"Professional",
            "subcategory":"Computer Services",
            "type":"Services"
        }
    ],
    "sg:phone":"+1 770 636 3300",
    "sg:postcode":"30084",
    "sg:province":"GA",
    "sg:tags":[
        "programing",
        "custom"
    ],
    "wof:name":"Techni-Cor",
    "wof:placetype":"venue"
},
  "geometry": {"coordinates":[-84.26106299999999,33.840998],"type":"Point"}
}