{
  "type": "Feature",
  "properties": {
    "iso:country":"US",
    "sg:address":"Hammond Springs Shopping Center 5975 Roswell Road, Suite A-107 S",
    "sg:city":"Sandy Springs",
    "sg:classifiers":[
        {
            "category":"Fast Food",
            "type":"Food & Drink"
        },
        {
            "category":"Restaurant",
            "type":"Food & Drink"
        }
    ],
    "sg:postcode":"30328",
    "sg:province":"GA",
    "sg:tags":[
        "burger"
    ],
    "sg:website":"www.boardwalkfreshburgersandfrie...",
    "wof:name":"Boardwalk Fresh Burgers and Fries",
    "wof:placetype":"venue"
},
  "geometry": {"coordinates":[-84.379127,33.917913],"type":"Point"}
}