{
  "type": "Feature",
  "properties": {
    "addr:full":"2421 de Soto Ave Savannah GA 31401",
    "addr:housenumber":"2421",
    "addr:postcode":"31401",
    "addr:street":"De Soto Ave",
    "iso:country":"US",
    "sg:address":"2421 de Soto Ave",
    "sg:city":"Savannah",
    "sg:classifiers":[
        {
            "category":"Food & Beverages",
            "subcategory":"Liquor & Beverages",
            "type":"Retail Goods"
        }
    ],
    "sg:phone":"+1 912 790 7272",
    "sg:postcode":"31401",
    "sg:province":"GA",
    "sg:tags":[
        "alcoholic"
    ],
    "wof:name":"Le Chai",
    "wof:placetype":"venue"
},
  "geometry": {"coordinates":[-81.10190900000001,32.054143],"type":"Point"}
}