{
  "type": "Feature",
  "properties": {
    "iso:country":"US",
    "sg:address":"310 Stone Path Way",
    "sg:city":"Roswell",
    "sg:classifiers":[
        {
            "category":"Manufacturing",
            "subcategory":"Paper Products",
            "type":"Manufacturing & Wholesale Goods"
        }
    ],
    "sg:phone":"+1 770 993 2207",
    "sg:postcode":"30075",
    "sg:province":"GA",
    "sg:tags":[
        "converted",
        "mfg"
    ],
    "wof:name":"Mail-Well Envelope",
    "wof:placetype":"venue"
},
  "geometry": {"coordinates":[-84.408315,34.071013],"type":"Point"}
}