{
  "type": "Feature",
  "properties": {
    "iso:country":"US",
    "sg:address":"775 Atlanta South Pkwy",
    "sg:city":"Atlanta",
    "sg:classifiers":[
        {
            "category":"Professional",
            "subcategory":"Management & Consulting",
            "type":"Services"
        }
    ],
    "sg:phone":"+1 404 766 8958",
    "sg:postcode":"30349",
    "sg:province":"GA",
    "sg:tags":[
        "logistics"
    ],
    "wof:name":"C mS Logistics",
    "wof:placetype":"venue"
},
  "geometry": {"coordinates":[-84.408276,33.611472],"type":"Point"}
}