{
  "type": "Feature",
  "properties": {
    "iso:country":"US",
    "sg:address":"111 Lucille Dr",
    "sg:city":"Thomaston",
    "sg:classifiers":[
        {
            "category":"Building & Trades",
            "subcategory":"Electrical",
            "type":"Services"
        }
    ],
    "sg:phone":"+1 706 647 7220",
    "sg:postcode":"30286",
    "sg:province":"GA",
    "sg:tags":[
        "electrical",
        "contractor"
    ],
    "wof:name":"Chet Wheless",
    "wof:placetype":"venue"
},
  "geometry": {"coordinates":[-84.406548,32.899869],"type":"Point"}
}