{
  "type": "Feature",
  "properties": {
    "addr:full":"8450 State Rte 65 Camilla GA 31730",
    "addr:housenumber":"8450",
    "addr:postcode":"31730",
    "addr:street":"State Rte 65",
    "iso:country":"US",
    "sg:address":"8450 State Rte 65",
    "sg:city":"Camilla",
    "sg:classifiers":[
        {
            "category":"Autos & Motor Vehicles",
            "subcategory":"Automobile Sales",
            "type":"Retail Goods"
        }
    ],
    "sg:phone":"+1 229 294 9779",
    "sg:postcode":"31730",
    "sg:province":"GA",
    "sg:tags":[
        "car",
        "dealer"
    ],
    "wof:name":"Hurst Auto Sales",
    "wof:placetype":"venue"
},
  "geometry": {"coordinates":[-84.34295299999999,31.161014],"type":"Point"}
}