{
  "type": "Feature",
  "properties": {
    "iso:country":"US",
    "sg:address":"137 Church St NE",
    "sg:city":"Marietta",
    "sg:classifiers":[
        {
            "category":"Restaurant",
            "type":"Food & Drink"
        }
    ],
    "sg:phone":"+1 770 426 7000",
    "sg:postcode":"30060",
    "sg:province":"GA",
    "sg:tags":[
        "tea",
        "rooms"
    ],
    "wof:name":"LA Tea Da's",
    "wof:placetype":"venue"
},
  "geometry": {"coordinates":[-84.55017599999999,33.955346],"type":"Point"}
}