{
  "type": "Feature",
  "properties": {
    "addr:full":"2955 West Rd Riverdale GA 30296",
    "addr:housenumber":"2955",
    "addr:postcode":"30296",
    "addr:street":"West Rd",
    "iso:country":"US",
    "sg:address":"2955 West Rd",
    "sg:city":"Riverdale",
    "sg:classifiers":[
        {
            "category":"Organizations",
            "subcategory":"Religious Organization",
            "type":"Services"
        }
    ],
    "sg:phone":"+1 770 996 9255",
    "sg:postcode":"30296",
    "sg:province":"GA",
    "sg:tags":[
        "church"
    ],
    "wof:name":"Daystar Temple Ministries",
    "wof:placetype":"venue"
},
  "geometry": {"coordinates":[-84.482783,33.557081],"type":"Point"}
}