{
  "type": "Feature",
  "properties": {
    "addr:full":"5205 Charleston Pl Atlanta GA 30338",
    "addr:housenumber":"5205",
    "addr:postcode":"30338",
    "addr:street":"Charleston Pl",
    "iso:country":"US",
    "sg:address":"5205 Charleston Pl",
    "sg:city":"Atlanta",
    "sg:classifiers":[
        {
            "category":"Professional",
            "subcategory":"Research",
            "type":"Services"
        }
    ],
    "sg:phone":"+1 770 452 0477",
    "sg:postcode":"30338",
    "sg:province":"GA",
    "sg:tags":[
        "marketing",
        "consulting",
        "business"
    ],
    "wof:name":"Faststarts Inc",
    "wof:placetype":"venue"
},
  "geometry": {"coordinates":[-84.30588899999999,33.924425],"type":"Point"}
}