{
  "type": "Feature",
  "properties": {
    "iso:country":"US",
    "sg:address":"5756 Bells Ferry Rd",
    "sg:city":"Acworth",
    "sg:classifiers":[
        {
            "category":"Building & Trades",
            "subcategory":"Equipment Rental",
            "type":"Services"
        }
    ],
    "sg:phone":"+1 770 516 6264",
    "sg:postcode":"30102",
    "sg:province":"GA",
    "wof:name":"Aaarons",
    "wof:placetype":"venue"
},
  "geometry": {"coordinates":[-84.58211900000001,34.092667],"type":"Point"}
}