{
  "type": "Feature",
  "properties": {
    "iso:country":"US",
    "sg:address":"37 Powder Springs St SE",
    "sg:city":"Marietta",
    "sg:classifiers":[
        {
            "category":"Banks & Credit Unions",
            "subcategory":"Financial Services",
            "type":"Services"
        }
    ],
    "sg:phone":"+1 678 290 9592",
    "sg:postcode":"30064",
    "sg:province":"GA",
    "sg:tags":[
        "broker",
        "mortgage"
    ],
    "wof:name":"Covenant Capital Partners Llc",
    "wof:placetype":"venue"
},
  "geometry": {"coordinates":[-84.550301,33.946098],"type":"Point"}
}