{
  "type": "Feature",
  "properties": {
    "iso:country":"US",
    "sg:address":"129 Reynolds Bridge Rd",
    "sg:city":"Kingston",
    "sg:classifiers":[
        {
            "category":"Building & Trades",
            "subcategory":"Construction",
            "type":"Services"
        }
    ],
    "sg:phone":"+1 770 336 9005",
    "sg:postcode":"30145",
    "sg:province":"GA",
    "sg:tags":[
        "house"
    ],
    "wof:name":"Alan Kiser Building & Cnstr",
    "wof:placetype":"venue"
},
  "geometry": {"coordinates":[-84.963916,34.228133],"type":"Point"}
}