{
  "type": "Feature",
  "properties": {
    "iso:country":"US",
    "sg:address":"2847 Windsor Oaks Trce",
    "sg:city":"Marietta",
    "sg:classifiers":[
        {
            "category":"Professional",
            "subcategory":"Management & Consulting",
            "type":"Services"
        }
    ],
    "sg:phone":"+1 678 494 4655",
    "sg:postcode":"30066",
    "sg:province":"GA",
    "sg:tags":[
        "marketing",
        "program"
    ],
    "wof:name":"Spectra Marketing",
    "wof:placetype":"venue"
},
  "geometry": {"coordinates":[-84.46816699999999,34.059279],"type":"Point"}
}