{
  "type": "Feature",
  "properties": {
    "addr:full":"115 Perimeter Center Pl NE Ste 660 Atlanta GA 30346",
    "addr:housenumber":"115",
    "addr:postcode":"30346",
    "addr:street":"Perimeter Center Pl Ne Ste 660",
    "iso:country":"US",
    "sg:address":"115 Perimeter Center Pl NE Ste 660",
    "sg:city":"Atlanta",
    "sg:classifiers":[
        {
            "category":"Wholesale",
            "subcategory":"Computers",
            "type":"Manufacturing & Wholesale Goods"
        }
    ],
    "sg:phone":"+1 678 579 9939",
    "sg:postcode":"30346",
    "sg:province":"GA",
    "wof:name":"Tata Consultancy Services",
    "wof:placetype":"venue"
},
  "geometry": {"coordinates":[-84.34071900000001,33.92893],"type":"Point"}
}