{
  "type": "Feature",
  "properties": {
    "iso:country":"US",
    "sg:address":"60 N Rountree St",
    "sg:city":"Metter",
    "sg:classifiers":[
        {
            "category":"Health Services",
            "subcategory":"Chiropractor",
            "type":"Services"
        }
    ],
    "sg:phone":"+1 912 685 2324",
    "sg:postcode":"30439",
    "sg:province":"GA",
    "wof:name":"Metter Chiropractic Ctr",
    "wof:placetype":"venue"
},
  "geometry": {"coordinates":[-82.06125900000001,32.398587],"type":"Point"}
}