{
  "type": "Feature",
  "properties": {
    "iso:country":"US",
    "sg:address":"4190 Cedar Ridge Trl",
    "sg:city":"Stone Mountain",
    "sg:classifiers":[
        {
            "category":"Organizations",
            "subcategory":"Religious Organization",
            "type":"Services"
        }
    ],
    "sg:phone":"+1 770 593 2881",
    "sg:postcode":"30083",
    "sg:province":"GA",
    "sg:tags":[
        "church"
    ],
    "wof:name":"Gateway Family Worship Ctr",
    "wof:placetype":"venue"
},
  "geometry": {"coordinates":[-84.199276,33.741766],"type":"Point"}
}