{
  "type": "Feature",
  "properties": {
    "iso:country":"US",
    "sg:address":"3499 Pinemont Dr",
    "sg:city":"Douglasville",
    "sg:classifiers":[
        {
            "category":"Retail",
            "subcategory":"Animal Services",
            "type":"Services"
        }
    ],
    "sg:phone":"+1 678 838 7297",
    "sg:postcode":"30135",
    "sg:province":"GA",
    "sg:tags":[
        "pet",
        "boarding",
        "sitting"
    ],
    "wof:name":"Four Paws Pet Sitting Svc",
    "wof:placetype":"venue"
},
  "geometry": {"coordinates":[-84.71714299999999,33.71021],"type":"Point"}
}