{
  "type": "Feature",
  "properties": {
    "addr:full":"238 W Griffin St Dallas GA 30132",
    "addr:housenumber":"238",
    "addr:postcode":"30132",
    "addr:street":"W Griffin St",
    "iso:country":"US",
    "sg:address":"238 W Griffin St",
    "sg:city":"Dallas",
    "sg:classifiers":[
        {
            "category":"Retail",
            "subcategory":"Laundry & Dry Cleaning",
            "type":"Services"
        }
    ],
    "sg:phone":"+1 770 445 3270",
    "sg:postcode":"30132",
    "sg:province":"GA",
    "sg:tags":[
        "cleaners"
    ],
    "wof:name":"Dallas Laundry & Cleaners",
    "wof:placetype":"venue"
},
  "geometry": {"coordinates":[-84.84190599999999,33.923477],"type":"Point"}
}