{
  "type": "Feature",
  "properties": {
    "addr:full":"8601 Dunwoody Pl Atlanta GA 30350",
    "addr:housenumber":"8601",
    "addr:postcode":"30350",
    "addr:street":"Dunwoody Pl",
    "iso:country":"US",
    "sg:address":"8601 Dunwoody Pl",
    "sg:city":"Atlanta",
    "sg:classifiers":[
        {
            "category":"Utilities",
            "subcategory":"Mobile Phone",
            "type":"Services"
        }
    ],
    "sg:phone":"+1 678 352 9356",
    "sg:postcode":"30350",
    "sg:province":"GA",
    "sg:tags":[
        "wireless",
        "broadband"
    ],
    "wof:name":"Tri-State Broadband  Inc",
    "wof:placetype":"venue"
},
  "geometry": {"coordinates":[-84.341386,33.988783],"type":"Point"}
}