{
  "type": "Feature",
  "properties": {
    "addr:full":"16 Greenville St Newnan GA 30263",
    "addr:housenumber":"16",
    "addr:postcode":"30263",
    "addr:street":"Greenville St",
    "iso:country":"US",
    "sg:address":"16 Greenville St",
    "sg:city":"Newnan",
    "sg:classifiers":[
        {
            "category":"Professional",
            "subcategory":"Art Services",
            "type":"Services"
        },
        {
            "category":"Home & Garden",
            "subcategory":"Home Furnishings",
            "type":"Retail Goods"
        },
        {
            "category":"Home & Garden",
            "subcategory":"Building Materials",
            "type":"Retail Goods"
        },
        {
            "category":"Home & Garden",
            "subcategory":"Furniture",
            "type":"Retail Goods"
        }
    ],
    "sg:phone":"+1 770 251 4557",
    "sg:postcode":"30263",
    "sg:province":"GA",
    "sg:tags":[
        "draperies",
        "designer",
        "vertical",
        "wallpaper",
        "blinds-venetian",
        "window",
        "treatment",
        "wallcoverings",
        "interior",
        "curtain",
        "decorator",
        "store"
    ],
    "sg:website":"http://www.panoplyinc.com/main.html",
    "wof:name":"Panoply Inc",
    "wof:placetype":"venue"
},
  "geometry": {"coordinates":[-84.79969800000001,33.373589],"type":"Point"}
}