{
  "type": "Feature",
  "properties": {
    "iso:country":"US",
    "sg:address":"6100 Lake Forrest Dr NW",
    "sg:city":"Atlanta",
    "sg:phone":"+1 404 531 0515",
    "sg:postcode":"30328",
    "sg:province":"GA",
    "wof:name":"Carson Elizabeth W Md",
    "wof:placetype":"venue"
},
  "geometry": {"coordinates":[-84.38700900000001,33.921754],"type":"Point"}
}