{
  "type": "Feature",
  "properties": {
    "addr:full":"976 Mansell Rd Ste 500 Roswell GA 30076",
    "addr:housenumber":"976",
    "addr:postcode":"30076",
    "addr:street":"Mansell Rd Ste 500",
    "iso:country":"US",
    "sg:address":"976 Mansell Rd Ste 500",
    "sg:city":"Roswell",
    "sg:classifiers":[
        {
            "category":"Banks & Credit Unions",
            "subcategory":"Bank",
            "type":"Services"
        }
    ],
    "sg:phone":"+1 770 518 0134",
    "sg:postcode":"30076",
    "sg:province":"GA",
    "sg:website":"www.wamu.com",
    "wof:name":"Washington Mutual",
    "wof:placetype":"venue"
},
  "geometry": {"coordinates":[-84.332122,34.042914],"type":"Point"}
}