{
  "type": "Feature",
  "properties": {
    "addr:full":"395 Industrial Dr Hogansville GA 30230",
    "addr:housenumber":"395",
    "addr:postcode":"30230",
    "addr:street":"Industrial Dr Hogansville",
    "iso:country":"US",
    "sg:address":"395 Industrial Dr",
    "sg:city":"Hogansville",
    "sg:classifiers":[
        {
            "category":"Manufacturing",
            "subcategory":"Furniture",
            "type":"Manufacturing & Wholesale Goods"
        }
    ],
    "sg:phone":"+1 706 637 5622",
    "sg:postcode":"30230",
    "sg:province":"GA",
    "sg:tags":[
        "shop",
        "cut",
        "lumber",
        "metal",
        "fabrication",
        "wood",
        "resell"
    ],
    "wof:name":"Covenant Enterprises",
    "wof:placetype":"venue"
},
  "geometry": {"coordinates":[-84.917216,33.147349],"type":"Point"}
}