{
  "type": "Feature",
  "properties": {
    "iso:country":"US",
    "sg:address":"296 Culver St",
    "sg:city":"Lawrenceville",
    "sg:classifiers":[
        {
            "category":"Professional",
            "subcategory":"Lawyer & Legal Services",
            "type":"Services"
        }
    ],
    "sg:phone":"+1 770 822 6025",
    "sg:postcode":"30046",
    "sg:province":"GA",
    "wof:name":"Mullinax Alan Dgn Atty",
    "wof:placetype":"venue"
},
  "geometry": {"coordinates":[-83.991193,33.958493],"type":"Point"}
}