{
  "type": "Feature",
  "properties": {
    "addr:full":"619 Cohutta Springs Rd Crandall GA 30711",
    "addr:housenumber":"619",
    "addr:postcode":"30711",
    "addr:street":"Cohutta Springs Rd",
    "iso:country":"US",
    "sg:address":"619 Cohutta Springs Rd",
    "sg:city":"Crandall",
    "sg:classifiers":[
        {
            "category":"Building & Trades",
            "subcategory":"Construction",
            "type":"Services"
        }
    ],
    "sg:phone":"+1 706 695 3920",
    "sg:postcode":"30711",
    "sg:province":"GA",
    "sg:tags":[
        "house"
    ],
    "wof:name":"Tony Kendrick",
    "wof:placetype":"venue"
},
  "geometry": {"coordinates":[-84.74146399999999,34.889054],"type":"Point"}
}