{
  "type": "Feature",
  "properties": {
    "addr:full":"3707 University Ave Columbus GA 31907",
    "addr:housenumber":"3707",
    "addr:postcode":"31907",
    "addr:street":"University Ave",
    "iso:country":"US",
    "sg:address":"3707 University Ave",
    "sg:city":"Columbus",
    "sg:classifiers":[
        {
            "category":"Shopping",
            "type":"Retail Goods"
        }
    ],
    "sg:phone":"+1 706 568 9008",
    "sg:postcode":"31907",
    "sg:province":"GA",
    "sg:tags":[
        "pet",
        "food",
        "supply"
    ],
    "wof:name":"Allen's Pest Control Products",
    "wof:placetype":"venue"
},
  "geometry": {"coordinates":[-84.93230699999999,32.497225],"type":"Point"}
}