{
  "type": "Feature",
  "properties": {
    "addr:full":"539 Golden Meadows Ln Suwanee GA 30024",
    "addr:housenumber":"539",
    "addr:postcode":"30024",
    "addr:street":"Golden Meadows Ln",
    "iso:country":"US",
    "sg:address":"539 Golden Meadows Ln",
    "sg:city":"Suwanee",
    "sg:classifiers":[
        {
            "category":"Building & Trades",
            "subcategory":"Construction",
            "type":"Services"
        }
    ],
    "sg:phone":"+1 678 482 1706",
    "sg:postcode":"30024",
    "sg:province":"GA",
    "sg:tags":[
        "house"
    ],
    "wof:name":"Peters & Pikula Const In",
    "wof:placetype":"venue"
},
  "geometry": {"coordinates":[-84.061753,34.039316],"type":"Point"}
}