{
  "type": "Feature",
  "properties": {
    "iso:country":"US",
    "sg:address":"1582 New Normantown Rd",
    "sg:city":"Vidalia",
    "sg:classifiers":[
        {
            "category":"Manufacturing",
            "subcategory":"Building Materials",
            "type":"Manufacturing & Wholesale Goods"
        }
    ],
    "sg:phone":"+1 912 537 3691",
    "sg:postcode":"30474",
    "sg:province":"GA",
    "sg:tags":[
        "mfg",
        "wood",
        "kitchen",
        "cabinet"
    ],
    "wof:name":"Jackson Wood Works",
    "wof:placetype":"venue"
},
  "geometry": {"coordinates":[-82.382401,32.300397],"type":"Point"}
}