{
  "type": "Feature",
  "properties": {
    "addr:full":"2682 Reese Rd Columbus GA 31907",
    "addr:housenumber":"2682",
    "addr:postcode":"31907",
    "addr:street":"Reese Rd",
    "iso:country":"US",
    "sg:address":"2682 Reese Rd",
    "sg:city":"Columbus",
    "sg:classifiers":[
        {
            "category":"Autos & Motor Vehicles",
            "subcategory":"Auto Supplies",
            "type":"Retail Goods"
        }
    ],
    "sg:phone":"+1 706 569 7786",
    "sg:postcode":"31907",
    "sg:province":"GA",
    "sg:tags":[
        "tire"
    ],
    "wof:name":"Carroll Tire Co",
    "wof:placetype":"venue"
},
  "geometry": {"coordinates":[-84.91288400000001,32.490705],"type":"Point"}
}