{
  "type": "Feature",
  "properties": {
    "iso:country":"US",
    "sg:address":"378 Frank Hendry Rd",
    "sg:city":"Ellabell",
    "sg:classifiers":[
        {
            "category":"Manufacturing",
            "subcategory":"Glass & Minerals",
            "type":"Manufacturing & Wholesale Goods"
        }
    ],
    "sg:phone":"+1 912 858 4527",
    "sg:postcode":"31308",
    "sg:province":"GA",
    "sg:tags":[
        "plate",
        "window",
        "glass-auto"
    ],
    "wof:name":"Lee's Glass And Supply",
    "wof:placetype":"venue"
},
  "geometry": {"coordinates":[-81.49166700000001,32.157806],"type":"Point"}
}