{
  "type": "Feature",
  "properties": {
    "addr:full":"207 Milledge Rd Augusta GA 30904",
    "addr:housenumber":"207",
    "addr:postcode":"30904",
    "addr:street":"Milledge Rd",
    "iso:country":"US",
    "sg:address":"207 Milledge Rd",
    "sg:city":"Augusta",
    "sg:classifiers":[
        {
            "category":"Retail",
            "subcategory":"Repair Shop",
            "type":"Services"
        }
    ],
    "sg:phone":"+1 706 733 5938",
    "sg:postcode":"30904",
    "sg:province":"GA",
    "sg:tags":[
        "audio"
    ],
    "wof:name":"Radio TV Svc Ctr",
    "wof:placetype":"venue"
},
  "geometry": {"coordinates":[-82.006112,33.488465],"type":"Point"}
}