{
  "type": "Feature",
  "properties": {
    "iso:country":"US",
    "sg:address":"406 W Taylor St",
    "sg:city":"Griffin",
    "sg:classifiers":[
        {
            "category":"Restaurant",
            "type":"Food & Drink"
        }
    ],
    "sg:menulink":"http://www.allmenus.com/ga/griffin/76228-dominos-pizza/menu/",
    "sg:phone":"+1 770 229 1872",
    "sg:postcode":"30223",
    "sg:province":"GA",
    "sg:tags":[
        "american",
        "wing",
        "pizza"
    ],
    "wof:name":"Domino's Pizza",
    "wof:placetype":"venue"
},
  "geometry": {"coordinates":[-84.268857,33.247151],"type":"Point"}
}