{
  "type": "Feature",
  "properties": {
    "iso:country":"US",
    "sg:address":"3222 Pawnee Dr",
    "sg:city":"Rex",
    "sg:classifiers":[
        {
            "category":"Professional",
            "subcategory":"Management & Consulting",
            "type":"Services"
        }
    ],
    "sg:phone":"+1 404 381 4499",
    "sg:postcode":"30273",
    "sg:province":"GA",
    "sg:tags":[
        "fuel"
    ],
    "wof:name":"Dynasty Management",
    "wof:placetype":"venue"
},
  "geometry": {"coordinates":[-84.285523,33.583215],"type":"Point"}
}