{
  "type": "Feature",
  "properties": {
    "addr:full":"615 Roswell St NE Marietta GA 30060",
    "addr:housenumber":"615",
    "addr:postcode":"30060",
    "addr:street":"Roswell St Ne",
    "iso:country":"US",
    "sg:address":"615 Roswell St NE",
    "sg:city":"Marietta",
    "sg:classifiers":[
        {
            "category":"Professional",
            "subcategory":"Employment Agencies",
            "type":"Services"
        }
    ],
    "sg:phone":"+1 770 499 2172",
    "sg:postcode":"30060",
    "sg:province":"GA",
    "sg:tags":[
        "opportunity"
    ],
    "wof:name":"Supported Employment Specialists",
    "wof:placetype":"venue"
},
  "geometry": {"coordinates":[-84.534302,33.9506],"type":"Point"}
}