{
  "type": "Feature",
  "properties": {
    "addr:full":"1401 Peachtree Street NE Atlanta GA 30309",
    "addr:housenumber":"1401",
    "addr:postcode":"30309",
    "addr:street":"Peachtree Street Ne",
    "iso:country":"US",
    "sg:address":"1401 Peachtree Street NE",
    "sg:city":"Atlanta",
    "sg:classifiers":[
        {
            "category":"Professional",
            "subcategory":"Lawyer & Legal Services",
            "type":"Services"
        }
    ],
    "sg:phone":"+1 404 885 6668",
    "sg:postcode":"30309",
    "sg:province":"GA",
    "wof:name":"Hargrove Bedelia C ESQ",
    "wof:placetype":"venue"
},
  "geometry": {"coordinates":[-84.386633,33.792907],"type":"Point"}
}