{
  "type": "Feature",
  "properties": {
    "iso:country":"US",
    "sg:address":"309 Agnew Dr",
    "sg:city":"Forest Park",
    "sg:classifiers":[
        {
            "category":"Wholesale",
            "subcategory":"Electrical",
            "type":"Manufacturing & Wholesale Goods"
        }
    ],
    "sg:phone":"+1 404 675 8990",
    "sg:postcode":"30297",
    "sg:province":"GA",
    "sg:tags":[
        "communication",
        "radio",
        "system"
    ],
    "sg:website":"www.diversifiedelectronics.com",
    "wof:name":"Diversified Electronics",
    "wof:placetype":"venue"
},
  "geometry": {"coordinates":[-84.380169,33.610831],"type":"Point"}
}