{
  "type": "Feature",
  "properties": {
    "addr:full":"88 Martin Ave SE Atlanta GA 30315",
    "addr:housenumber":"88",
    "addr:postcode":"30315",
    "addr:street":"Martin Ave Se",
    "iso:country":"US",
    "sg:address":"88 Martin Ave SE",
    "sg:city":"Atlanta",
    "sg:classifiers":[
        {
            "category":"Organizations",
            "subcategory":"Religious Organization",
            "type":"Services"
        }
    ],
    "sg:phone":"+1 404 525 3129",
    "sg:postcode":"30315",
    "sg:province":"GA",
    "wof:name":"New Generation Baptist Church",
    "wof:placetype":"venue"
},
  "geometry": {"coordinates":[-84.384668,33.717692],"type":"Point"}
}