{
  "type": "Feature",
  "properties": {
    "iso:country":"US",
    "sg:address":"116 Bethea Dr",
    "sg:city":"Fayetteville",
    "sg:classifiers":[
        {
            "category":"Manufacturing",
            "subcategory":"Glass & Minerals",
            "type":"Manufacturing & Wholesale Goods"
        }
    ],
    "sg:phone":"+1 770 719 2051",
    "sg:postcode":"30214",
    "sg:province":"GA",
    "sg:tags":[
        "art"
    ],
    "sg:website":"www.bfinkjet.com",
    "wof:name":"B F Ink Jet Media Inc",
    "wof:placetype":"venue"
},
  "geometry": {"coordinates":[-84.449196,33.499609],"type":"Point"}
}