{
  "type": "Feature",
  "properties": {
    "addr:full":"1084 Colquitt Ave NE Atlanta GA 30307",
    "addr:housenumber":"1084",
    "addr:postcode":"30307",
    "addr:street":"Colquitt Ave Ne",
    "iso:country":"US",
    "sg:address":"1084 Colquitt Ave NE",
    "sg:city":"Atlanta",
    "sg:classifiers":[
        {
            "category":"Shopping",
            "subcategory":"Florist",
            "type":"Retail Goods"
        }
    ],
    "sg:phone":"+1 404 577 6379",
    "sg:postcode":"30307",
    "sg:province":"GA",
    "wof:name":"Bob Bargerons Home of Flowers",
    "wof:placetype":"venue"
},
  "geometry": {"coordinates":[-84.350667,33.765085],"type":"Point"}
}