{
  "type": "Feature",
  "properties": {
    "addr:full":"615 Croydon Ln Alpharetta GA 30022",
    "addr:housenumber":"615",
    "addr:postcode":"30022",
    "addr:street":"Croydon Ln",
    "iso:country":"US",
    "sg:address":"615 Croydon Ln",
    "sg:city":"Alpharetta",
    "sg:classifiers":[
        {
            "category":"Professional",
            "type":"Services"
        }
    ],
    "sg:phone":"+1 770 410 0527",
    "sg:postcode":"30022",
    "sg:province":"GA",
    "wof:name":"Sali Inc",
    "wof:placetype":"venue"
},
  "geometry": {"coordinates":[-84.210981,34.030092],"type":"Point"}
}