{
  "type": "Feature",
  "properties": {
    "addr:full":"495 Paper Mill Rd Lawrenceville GA 30045",
    "addr:housenumber":"495",
    "addr:postcode":"30045",
    "addr:street":"Paper Mill Rd",
    "iso:country":"US",
    "sg:address":"495 Paper Mill Rd",
    "sg:city":"Lawrenceville",
    "sg:classifiers":[
        {
            "category":"Health Services",
            "subcategory":"Clinic",
            "type":"Services"
        }
    ],
    "sg:phone":"+1 770 962 3334",
    "sg:postcode":"30045",
    "sg:province":"GA",
    "sg:tags":[
        "home"
    ],
    "wof:name":"Marian Home Care",
    "wof:placetype":"venue"
},
  "geometry": {"coordinates":[-83.956593,33.950224],"type":"Point"}
}