{
  "type": "Feature",
  "properties": {
    "iso:country":"US",
    "sg:address":"415 Shallowford Rd NE",
    "sg:city":"Kennesaw",
    "sg:classifiers":[
        {
            "category":"Building & Trades",
            "subcategory":"Construction",
            "type":"Services"
        }
    ],
    "sg:phone":"+1 770 517 1266",
    "sg:postcode":"30144",
    "sg:province":"GA",
    "sg:tags":[
        "contractor"
    ],
    "wof:name":"Construction Dynamics Group",
    "wof:placetype":"venue"
},
  "geometry": {"coordinates":[-84.53673,34.068449],"type":"Point"}
}