{
  "type": "Feature",
  "properties": {
    "addr:full":"114 Mall Blvd Savannah GA 31406",
    "addr:housenumber":"114",
    "addr:postcode":"31406",
    "addr:street":"Mall Blvd",
    "iso:country":"US",
    "sg:address":"114 Mall Blvd",
    "sg:city":"Savannah",
    "sg:classifiers":[
        {
            "category":"Travel",
            "subcategory":"Hotels & Motels",
            "type":"Entertainment"
        }
    ],
    "sg:phone":"+1 912 352 4455",
    "sg:postcode":"31406",
    "sg:province":"GA",
    "sg:tags":[
        "operation"
    ],
    "wof:name":"Days Inn",
    "wof:placetype":"venue"
},
  "geometry": {"coordinates":[-81.112149,32.002933],"type":"Point"}
}