{
  "type": "Feature",
  "properties": {
    "addr:full":"303 Mosley St Vidalia GA 30474",
    "addr:housenumber":"303",
    "addr:postcode":"30474",
    "addr:street":"Mosley St",
    "iso:country":"US",
    "sg:address":"303 Mosley St",
    "sg:city":"Vidalia",
    "sg:classifiers":[
        {
            "category":"Personal",
            "subcategory":"Beauty Salon",
            "type":"Services"
        }
    ],
    "sg:phone":"+1 912 538 8598",
    "sg:postcode":"30474",
    "sg:province":"GA",
    "sg:tags":[
        "shop"
    ],
    "wof:name":"Hair Shack",
    "wof:placetype":"venue"
},
  "geometry": {"coordinates":[-82.409733,32.214545],"type":"Point"}
}