{
  "type": "Feature",
  "properties": {
    "iso:country":"US",
    "sg:address":"160 Rozier Rd",
    "sg:city":"Brooklet",
    "sg:classifiers":[
        {
            "category":"Farming",
            "subcategory":"Farm",
            "type":"Manufacturing & Wholesale Goods"
        }
    ],
    "sg:phone":"+1 912 842 2656",
    "sg:postcode":"30415",
    "sg:province":"GA",
    "sg:tags":[
        "crop",
        "general"
    ],
    "wof:name":"Hickory Ridge Farms",
    "wof:placetype":"venue"
},
  "geometry": {"coordinates":[-81.6073,32.286831],"type":"Point"}
}