{
  "type": "Feature",
  "properties": {
    "iso:country":"US",
    "sg:address":"1073 Green St",
    "sg:city":"Roswell",
    "sg:classifiers":[
        {
            "category":"Building & Trades",
            "subcategory":"Construction",
            "type":"Services"
        }
    ],
    "sg:phone":"+1 678 352 0384",
    "sg:postcode":"30075",
    "sg:province":"GA",
    "sg:tags":[
        "designer",
        "dealer",
        "pool",
        "swimming"
    ],
    "wof:name":"Atlanta Aquatics",
    "wof:placetype":"venue"
},
  "geometry": {"coordinates":[-84.35995800000001,34.025925],"type":"Point"}
}