{
  "type": "Feature",
  "properties": {
    "iso:country":"US",
    "sg:address":"4157 S Main St",
    "sg:city":"Acworth",
    "sg:classifiers":[
        {
            "category":"Retail",
            "subcategory":"Auto Repair",
            "type":"Services"
        }
    ],
    "sg:phone":"+1 770 974 6032",
    "sg:postcode":"30101",
    "sg:province":"GA",
    "wof:name":"Brooks Garage",
    "wof:placetype":"venue"
},
  "geometry": {"coordinates":[-84.66390199999999,34.0555],"type":"Point"}
}