{
  "type": "Feature",
  "properties": {
    "addr:full":"101 Meadow Dr Cumming GA 30040",
    "addr:housenumber":"101",
    "addr:postcode":"30040",
    "addr:street":"Meadow Dr",
    "iso:country":"US",
    "sg:address":"101 Meadow Dr",
    "sg:city":"Cumming",
    "sg:classifiers":[
        {
            "category":"Building & Trades",
            "subcategory":"Construction",
            "type":"Services"
        }
    ],
    "sg:phone":"+1 770 889 3869",
    "sg:postcode":"30040",
    "sg:province":"GA",
    "sg:tags":[
        "siding",
        "contractor"
    ],
    "wof:name":"Roe Siding Inc",
    "wof:placetype":"venue"
},
  "geometry": {"coordinates":[-84.135398,34.200663],"type":"Point"}
}