{
  "type": "Feature",
  "properties": {
    "addr:full":"330 Turner Mccall Blvd SW Rome GA 30165",
    "addr:housenumber":"330",
    "addr:postcode":"ga 30165",
    "addr:street":"Turner Mccall Blvd Sw",
    "iso:country":"US",
    "sg:address":"330 Turner Mccall Blvd SW",
    "sg:city":"Rome",
    "sg:classifiers":[
        {
            "category":"Health Services",
            "subcategory":"Doctor",
            "type":"Services"
        }
    ],
    "sg:phone":"+1 706 509 6400",
    "sg:postcode":"30165",
    "sg:province":"GA",
    "sg:tags":[
        "physician",
        "surgeons",
        "surgery-general"
    ],
    "sg:website":"http://www.tomtracker.com/redirect.cfm?bID=20797&hID=123581",
    "wof:name":"Floyd Outpatient Surgery Center",
    "wof:placetype":"venue"
},
  "geometry": {"coordinates":[-85.178223,34.26046],"type":"Point"}
}