{
  "type": "Feature",
  "properties": {
    "addr:full":"8110 Mall Pkwy Lithonia GA 30038",
    "addr:housenumber":"8110",
    "addr:postcode":"30038",
    "addr:street":"Mall Pkwy",
    "iso:country":"US",
    "sg:address":"8110 Mall Pkwy",
    "sg:city":"Lithonia",
    "sg:classifiers":[
        {
            "category":"Shopping",
            "subcategory":"Shoes",
            "type":"Retail Goods"
        }
    ],
    "sg:phone":"+1 678 526 8550",
    "sg:postcode":"30038",
    "sg:province":"GA",
    "sg:tags":[
        "store"
    ],
    "wof:name":"Dsw Shoe Warehouse",
    "wof:placetype":"venue"
},
  "geometry": {"coordinates":[-84.098602,33.694401],"type":"Point"}
}