{
  "type": "Feature",
  "properties": {
    "addr:full":"5290 Big A Rd Douglasville GA 30135",
    "addr:housenumber":"5290",
    "addr:postcode":"30135",
    "addr:street":"Big A Rd",
    "iso:country":"US",
    "sg:address":"5290 Big A Rd",
    "sg:city":"Douglasville",
    "sg:classifiers":[
        {
            "category":"Professional",
            "subcategory":"Business Services",
            "type":"Services"
        }
    ],
    "sg:phone":"+1 770 577 0775",
    "sg:postcode":"30135",
    "sg:province":"GA",
    "wof:name":"Site Solutions",
    "wof:placetype":"venue"
},
  "geometry": {"coordinates":[-84.794222,33.664439],"type":"Point"}
}