{
  "type": "Feature",
  "properties": {
    "addr:full":"4471 Columbia Rd Augusta GA 30907",
    "addr:housenumber":"4471",
    "addr:postcode":"30907",
    "addr:street":"Columbia Rd",
    "iso:country":"US",
    "sg:address":"4471 Columbia Rd",
    "sg:city":"Augusta",
    "sg:classifiers":[
        {
            "category":"Organizations",
            "subcategory":"Professional Association",
            "type":"Services"
        }
    ],
    "sg:phone":"+1 706 863 7662",
    "sg:postcode":"30907",
    "sg:province":"GA",
    "sg:tags":[
        "business"
    ],
    "wof:name":"Commerce South Carolina Dept",
    "wof:placetype":"venue"
},
  "geometry": {"coordinates":[-82.141992,33.507593],"type":"Point"}
}