{
  "type": "Feature",
  "properties": {
    "addr:full":"7281 Union Grove Rd Lithonia GA 30058",
    "addr:housenumber":"7281",
    "addr:postcode":"30058",
    "addr:street":"Union Grove Rd",
    "iso:country":"US",
    "sg:address":"7281 Union Grove Rd",
    "sg:city":"Lithonia",
    "sg:classifiers":[
        {
            "category":"Professional",
            "subcategory":"Business Services",
            "type":"Services"
        }
    ],
    "sg:phone":"+1 770 484 5000",
    "sg:postcode":"30058",
    "sg:province":"GA",
    "sg:tags":[
        "contractor"
    ],
    "wof:name":"Grifco Interiors Inc",
    "wof:placetype":"venue"
},
  "geometry": {"coordinates":[-84.08958199999999,33.722937],"type":"Point"}
}