{
  "type": "Feature",
  "properties": {
    "addr:full":"3145 Peachtree Rd NE Atlanta GA 30305",
    "addr:housenumber":"3145",
    "addr:postcode":"30305",
    "addr:street":"Peachtree Rd Ne",
    "iso:country":"US",
    "sg:address":"3145 Peachtree Rd NE",
    "sg:city":"Atlanta",
    "sg:classifiers":[
        {
            "category":"Manufacturing",
            "subcategory":"Wood Products",
            "type":"Manufacturing & Wholesale Goods"
        },
        {
            "category":"Professional",
            "subcategory":"Art Services",
            "type":"Services"
        }
    ],
    "sg:phone":"+1 404 261 4090",
    "sg:postcode":"30305",
    "sg:province":"GA",
    "sg:tags":[
        "picture",
        "frame",
        "frames-wholesale",
        "manufacturer"
    ],
    "wof:name":"Picture This Gallery & Framing",
    "wof:placetype":"venue"
},
  "geometry": {"coordinates":[-84.377391,33.840356],"type":"Point"}
}