{
  "type": "Feature",
  "properties": {
    "iso:country":"US",
    "sg:address":"942 Green St SW",
    "sg:city":"Conyers",
    "sg:classifiers":[
        {
            "category":"Retail",
            "subcategory":"Car Wash",
            "type":"Services"
        },
        {
            "category":"Autos & Motor Vehicles",
            "subcategory":"Auto Supplies",
            "type":"Retail Goods"
        }
    ],
    "sg:phone":"+1 770 602 4261",
    "sg:postcode":"30012",
    "sg:province":"GA",
    "sg:tags":[
        "polishing",
        "washing"
    ],
    "wof:name":"American Carwash Eqp & Sup Co",
    "wof:placetype":"venue"
},
  "geometry": {"coordinates":[-84.019918,33.667088],"type":"Point"}
}