{
  "type": "Feature",
  "properties": {
    "addr:full":"505 Industrial Way E Macon GA 31217",
    "addr:housenumber":"505",
    "addr:postcode":"31217",
    "addr:street":"Industrial Way E",
    "iso:country":"US",
    "sg:address":"505 Industrial Way E",
    "sg:city":"Macon",
    "sg:classifiers":[
        {
            "category":"Education",
            "subcategory":"College",
            "type":"Public Place"
        },
        {
            "category":"Shopping",
            "subcategory":"Party Supplies",
            "type":"Retail Goods"
        },
        {
            "category":"Retail",
            "subcategory":"Event Space",
            "type":"Services"
        },
        {
            "category":"Shopping",
            "subcategory":"Bicycles & Sporting Goods",
            "type":"Retail Goods"
        },
        {
            "category":"Building & Trades",
            "subcategory":"Equipment Rental",
            "type":"Services"
        }
    ],
    "sg:phone":"+1 478 746 8269",
    "sg:postcode":"31217",
    "sg:province":"GA",
    "sg:tags":[
        "yard",
        "tables-folding",
        "tents-rental",
        "location",
        "reception",
        "wedding",
        "store",
        "tent"
    ],
    "sg:website":"http://www.realpagessites.com/macontentrental/",
    "wof:name":"Macon Tent Rentals",
    "wof:placetype":"venue"
},
  "geometry": {"coordinates":[-83.58456700000001,32.844437],"type":"Point"}
}