{
  "type": "Feature",
  "properties": {
    "iso:country":"US",
    "sg:address":"4665 Jefferson Township Pl",
    "sg:city":"Marietta",
    "sg:classifiers":[
        {
            "category":"Shopping",
            "type":"Retail Goods"
        }
    ],
    "sg:phone":"+1 770 641 0002",
    "sg:postcode":"30066",
    "sg:province":"GA",
    "sg:tags":[
        "merchandise"
    ],
    "wof:name":"Focus Medical Systems Inc",
    "wof:placetype":"venue"
},
  "geometry": {"coordinates":[-84.432807,34.067392],"type":"Point"}
}