{
  "type": "Feature",
  "properties": {
    "addr:full":"1516 Woodrow Ave Dublin GA 31021",
    "addr:housenumber":"1516",
    "addr:postcode":"31021",
    "addr:street":"Woodrow Ave",
    "iso:country":"US",
    "sg:address":"1516 Woodrow Ave",
    "sg:city":"Dublin",
    "sg:classifiers":[
        {
            "category":"Professional",
            "type":"Services"
        }
    ],
    "sg:phone":"+1 478 275 8874",
    "sg:postcode":"31021",
    "sg:province":"GA",
    "wof:name":"Mayers Pinestraw Inc",
    "wof:placetype":"venue"
},
  "geometry": {"coordinates":[-82.929536,32.538219],"type":"Point"}
}