{
  "type": "Feature",
  "properties": {
    "addr:full":"990 Norcross Industrial Ct Norcross GA 30071",
    "addr:housenumber":"990",
    "addr:postcode":"30071",
    "addr:street":"Norcross Industrial Ct",
    "iso:country":"US",
    "sg:address":"990 Norcross Industrial Ct",
    "sg:city":"Norcross",
    "sg:classifiers":[
        {
            "category":"Organizations",
            "subcategory":"Membership Organization",
            "type":"Services"
        }
    ],
    "sg:phone":"+1 770 441 2242",
    "sg:postcode":"30071",
    "sg:province":"GA",
    "sg:tags":[
        "athletic"
    ],
    "wof:name":"Berkeley Baseball Softball Acd",
    "wof:placetype":"venue"
},
  "geometry": {"coordinates":[-84.201587,33.94872],"type":"Point"}
}