{
  "type": "Feature",
  "properties": {
    "iso:country":"US",
    "sg:address":"603 Industrial Ct",
    "sg:city":"Woodstock",
    "sg:classifiers":[
        {
            "category":"Retail",
            "subcategory":"Repair Shop",
            "type":"Services"
        }
    ],
    "sg:phone":"+1 770 926 7520",
    "sg:postcode":"30189",
    "sg:province":"GA",
    "sg:tags":[
        "hydraulic"
    ],
    "wof:name":"Cherokee Air & Fluid Power",
    "wof:placetype":"venue"
},
  "geometry": {"coordinates":[-84.55806800000001,34.086309],"type":"Point"}
}