{
  "type": "Feature",
  "properties": {
    "iso:country":"US",
    "sg:address":"480 E Paces Ferry Road NE",
    "sg:city":"Atlanta",
    "sg:classifiers":[
        {
            "category":"Professional",
            "subcategory":"Lawyer & Legal Services",
            "type":"Services"
        }
    ],
    "sg:phone":"+1 404 261 7565",
    "sg:postcode":"30305",
    "sg:province":"GA",
    "sg:tags":[
        "divorce",
        "law",
        "family"
    ],
    "wof:name":"Alembik Gary M Atty",
    "wof:placetype":"venue"
},
  "geometry": {"coordinates":[-84.371951,33.838387],"type":"Point"}
}