{
  "type": "Feature",
  "properties": {
    "addr:full":"2130 Riverside Dr Macon GA 31204",
    "addr:housenumber":"2130",
    "addr:postcode":"31204",
    "addr:street":"Riverside Dr",
    "iso:country":"US",
    "sg:address":"2130 Riverside Dr",
    "sg:city":"Macon",
    "sg:classifiers":[
        {
            "category":"Autos & Motor Vehicles",
            "subcategory":"Automobile Sales",
            "type":"Retail Goods"
        }
    ],
    "sg:phone":"+1 478 750 1401",
    "sg:postcode":"31204",
    "sg:province":"GA",
    "sg:tags":[
        "car",
        "dealer"
    ],
    "sg:website":"www.economysales.com",
    "wof:name":"Economy Sales Div",
    "wof:placetype":"venue"
},
  "geometry": {"coordinates":[-83.650614,32.862062],"type":"Point"}
}