{
  "type": "Feature",
  "properties": {
    "addr:full":"8257 State Rte 254 Cleveland GA 30528",
    "addr:housenumber":"8257",
    "addr:postcode":"30528",
    "addr:street":"State Rte 254",
    "iso:country":"US",
    "sg:address":"8257 State Rte 254",
    "sg:city":"Cleveland",
    "sg:classifiers":[
        {
            "category":"Retail",
            "subcategory":"Auto Repair",
            "type":"Services"
        }
    ],
    "sg:phone":"+1 706 865 4420",
    "sg:postcode":"30528",
    "sg:province":"GA",
    "sg:tags":[
        "general"
    ],
    "wof:name":"Satterfields Auto Service Ctr",
    "wof:placetype":"venue"
},
  "geometry": {"coordinates":[-83.744913,34.509875],"type":"Point"}
}