{
  "type": "Feature",
  "properties": {
    "addr:full":"1950 Spectrum Cir SE Marietta GA 30067",
    "addr:housenumber":"1950",
    "addr:postcode":"30067",
    "addr:street":"Spectrum Cir Se",
    "iso:country":"US",
    "sg:address":"1950 Spectrum Cir SE",
    "sg:city":"Marietta",
    "sg:classifiers":[
        {
            "category":"Health Services",
            "subcategory":"Clinic",
            "type":"Services"
        },
        {
            "category":"Health Services",
            "subcategory":"Health Practitioner",
            "type":"Services"
        }
    ],
    "sg:phone":"+1 770 541 7401",
    "sg:postcode":"30067",
    "sg:province":"GA",
    "sg:tags":[
        "occupational",
        "therapist",
        "therapy",
        "physical"
    ],
    "sg:website":"http://www.thefreedmangroup.com",
    "wof:name":"Freedman Group The",
    "wof:placetype":"venue"
},
  "geometry": {"coordinates":[-84.46874699999999,33.905575],"type":"Point"}
}