{
  "type": "Feature",
  "properties": {
    "addr:full":"10960 State Bridge Rd Alpharetta GA 30022",
    "addr:housenumber":"10960",
    "addr:postcode":"30022",
    "addr:street":"State Bridge Rd",
    "iso:country":"US",
    "sg:address":"10960 State Bridge Rd",
    "sg:city":"Alpharetta",
    "sg:classifiers":[
        {
            "category":"Restaurant",
            "type":"Food & Drink"
        }
    ],
    "sg:menulink":"http://www.allmenus.com/ga/roswell-alpharetta/189989-kfc---kentucky-fried-chicken/menu/",
    "sg:phone":"+1 678 762 0762",
    "sg:postcode":"30022",
    "sg:province":"GA",
    "sg:tags":[
        "american",
        "chicken"
    ],
    "wof:name":"KFC - Kentucky Fried Chicken",
    "wof:placetype":"venue"
},
  "geometry": {"coordinates":[-84.22375,34.047489],"type":"Point"}
}