{
  "type": "Feature",
  "properties": {
    "addr:full":"51 Bryant St Jasper GA 30143",
    "addr:housenumber":"51",
    "addr:postcode":"30143",
    "addr:street":"Bryant St",
    "iso:country":"US",
    "sg:address":"51 Bryant St",
    "sg:city":"Jasper",
    "sg:classifiers":[
        {
            "category":"Professional",
            "subcategory":"Lawyer & Legal Services",
            "type":"Services"
        }
    ],
    "sg:phone":"+1 706 253 7700",
    "sg:postcode":"30143",
    "sg:province":"GA",
    "sg:tags":[
        "attorney"
    ],
    "wof:name":"Hartman Imbriale LLP",
    "wof:placetype":"venue"
},
  "geometry": {"coordinates":[-84.44207,34.467211],"type":"Point"}
}