{
  "type": "Feature",
  "properties": {
    "iso:country":"US",
    "sg:address":"230 Forest Ln",
    "sg:city":"Washington",
    "sg:classifiers":[
        {
            "category":"Building & Trades",
            "subcategory":"Plumbing",
            "type":"Services"
        }
    ],
    "sg:phone":"+1 706 678 7443",
    "sg:postcode":"30673",
    "sg:province":"GA",
    "sg:tags":[
        "plumbing",
        "contractor"
    ],
    "wof:name":"Vandiver Plumbing & Electric",
    "wof:placetype":"venue"
},
  "geometry": {"coordinates":[-82.781164,33.749632],"type":"Point"}
}