{
  "type": "Feature",
  "properties": {
    "addr:full":"100 Wendell Ct SW Atlanta GA 30336",
    "addr:housenumber":"100",
    "addr:postcode":"30336",
    "addr:street":"Wendell Ct Sw",
    "iso:country":"US",
    "sg:address":"100 Wendell Ct SW",
    "sg:city":"Atlanta",
    "sg:classifiers":[
        {
            "category":"Arts & Performance",
            "subcategory":"Theater",
            "type":"Entertainment"
        }
    ],
    "sg:phone":"+1 404 454 1120",
    "sg:postcode":"30336",
    "sg:province":"GA",
    "sg:tags":[
        "group"
    ],
    "wof:name":"Unlawful Entry Entrmt Prdctons",
    "wof:placetype":"venue"
},
  "geometry": {"coordinates":[-84.521001,33.766853],"type":"Point"}
}