{
  "type": "Feature",
  "properties": {
    "iso:country":"US",
    "sg:address":"1295 Russell Pkwy",
    "sg:city":"Warner Robins",
    "sg:classifiers":[
        {
            "category":"Health Services",
            "subcategory":"Doctor",
            "type":"Services"
        }
    ],
    "sg:phone":"+1 478 929 2190",
    "sg:postcode":"31088",
    "sg:province":"GA",
    "wof:name":"Curtis O Hayslip DMD",
    "wof:placetype":"venue"
},
  "geometry": {"coordinates":[-83.65001599999999,32.59391],"type":"Point"}
}