{
  "type": "Feature",
  "properties": {
    "iso:country":"US",
    "sg:address":"8210 Old Mill Dr",
    "sg:city":"Gainesville",
    "sg:classifiers":[
        {
            "category":"Professional",
            "subcategory":"Business Services",
            "type":"Services"
        }
    ],
    "sg:phone":"+1 770 887 9871",
    "sg:postcode":"30506",
    "sg:province":"GA",
    "wof:name":"Eagle Networks",
    "wof:placetype":"venue"
},
  "geometry": {"coordinates":[-83.991185,34.241366],"type":"Point"}
}