{
  "type": "Feature",
  "properties": {
    "addr:full":"703 Oothcalooga St Calhoun GA 30701",
    "addr:housenumber":"703",
    "addr:postcode":"30701",
    "addr:street":"Oothcalooga St",
    "iso:country":"US",
    "sg:address":"703 Oothcalooga St",
    "sg:city":"Calhoun",
    "sg:classifiers":[
        {
            "category":"Food & Beverages",
            "subcategory":"Groceries & Convenience Stores",
            "type":"Retail Goods"
        }
    ],
    "sg:phone":"+1 706 629 2944",
    "sg:postcode":"30701",
    "sg:province":"GA",
    "wof:name":"ABC Convenience Store",
    "wof:placetype":"venue"
},
  "geometry": {"coordinates":[-84.95703899999999,34.501801],"type":"Point"}
}