{
  "type": "Feature",
  "properties": {
    "iso:country":"US",
    "sg:address":"803 Wedgewood Way",
    "sg:city":"Atlanta",
    "sg:classifiers":[
        {
            "category":"Organizations",
            "subcategory":"Professional Association",
            "type":"Services"
        }
    ],
    "sg:phone":"+1 770 649 8872",
    "sg:postcode":"30350",
    "sg:province":"GA",
    "wof:name":"Atlanta Advertising Club",
    "wof:placetype":"venue"
},
  "geometry": {"coordinates":[-84.33671699999999,34.006486],"type":"Point"}
}