{
  "type": "Feature",
  "properties": {
    "addr:full":"10230 Flat Shoals Rd Covington GA 30014",
    "addr:housenumber":"10230",
    "addr:postcode":"30014",
    "addr:street":"Flat Shoals Rd",
    "iso:country":"US",
    "sg:address":"10230 Flat Shoals Rd",
    "sg:city":"Covington",
    "sg:classifiers":[
        {
            "category":"Professional",
            "subcategory":"Business Services",
            "type":"Services"
        }
    ],
    "sg:phone":"+1 770 385 7224",
    "sg:postcode":"30014",
    "sg:province":"GA",
    "wof:name":"Johnsons Recording Studi",
    "wof:placetype":"venue"
},
  "geometry": {"coordinates":[-83.873535,33.572536],"type":"Point"}
}