{
  "type": "Feature",
  "properties": {
    "addr:full":"1100 Aviation Blvd Atlanta GA 30354",
    "addr:housenumber":"1100",
    "addr:postcode":"30354",
    "addr:street":"Aviation Blvd",
    "iso:country":"US",
    "sg:address":"1100 Aviation Blvd",
    "sg:city":"Atlanta",
    "sg:classifiers":[
        {
            "category":"Government",
            "subcategory":"Office",
            "type":"Public Place"
        }
    ],
    "sg:phone":"+1 404 669 1250",
    "sg:postcode":"30354",
    "sg:province":"GA",
    "sg:tags":[
        "federal"
    ],
    "wof:name":"US Airway Facilities Sector",
    "wof:placetype":"venue"
},
  "geometry": {"coordinates":[-84.395833,33.640194],"type":"Point"}
}