{
  "type": "Feature",
  "properties": {
    "addr:full":"1380 Prince Ave Athens GA 30606",
    "addr:housenumber":"1380",
    "addr:postcode":"30606",
    "addr:street":"Prince Ave",
    "iso:country":"US",
    "sg:address":"1380 Prince Ave",
    "sg:city":"Athens",
    "sg:classifiers":[
        {
            "category":"Food & Beverages",
            "subcategory":"Groceries & Convenience Stores",
            "type":"Retail Goods"
        }
    ],
    "sg:phone":"+1 706 543 6777",
    "sg:postcode":"30606",
    "sg:province":"GA",
    "sg:tags":[
        "eating"
    ],
    "sg:website":"www.agualinda.net",
    "wof:name":"Los Compadres",
    "wof:placetype":"venue"
},
  "geometry": {"coordinates":[-83.400925,33.963486],"type":"Point"}
}