{
  "type": "Feature",
  "properties": {
    "addr:full":"1045 Athens St Gainesville GA 30501",
    "addr:housenumber":"1045",
    "addr:postcode":"30501",
    "addr:street":"Athens St",
    "iso:country":"US",
    "sg:address":"1045 Athens St",
    "sg:city":"Gainesville",
    "sg:classifiers":[
        {
            "category":"Retail",
            "subcategory":"Self-service Laundry",
            "type":"Services"
        }
    ],
    "sg:phone":"+1 770 536 6211",
    "sg:postcode":"30501",
    "sg:province":"GA",
    "sg:tags":[
        "coin"
    ],
    "wof:name":"Sophie's Coin Laundry",
    "wof:placetype":"venue"
},
  "geometry": {"coordinates":[-83.804614,34.291767],"type":"Point"}
}