{
  "type": "Feature",
  "properties": {
    "iso:country":"US",
    "sg:address":"4322 Harbor Walk",
    "sg:city":"Fairburn",
    "sg:classifiers":[
        {
            "category":"Real Estate",
            "subcategory":"Real Estate Services",
            "type":"Services"
        },
        {
            "category":"Real Estate",
            "subcategory":"Real Estate Agent",
            "type":"Services"
        }
    ],
    "sg:phone":"+1 678 431 7700",
    "sg:postcode":"30213",
    "sg:province":"GA",
    "sg:tags":[
        "management"
    ],
    "wof:name":"The Agent I N C",
    "wof:placetype":"venue"
},
  "geometry": {"coordinates":[-84.598293,33.556819],"type":"Point"}
}