{
  "type": "Feature",
  "properties": {
    "addr:full":"107 1/2 S College St Sparks GA 31647",
    "addr:housenumber":"107 1 / 2 s",
    "addr:postcode":"31647",
    "addr:street":"College St",
    "iso:country":"US",
    "sg:address":"107 1/2 S College St",
    "sg:city":"Sparks",
    "sg:classifiers":[
        {
            "category":"Arena",
            "subcategory":"Auto Racetrack",
            "type":"Entertainment"
        }
    ],
    "sg:phone":"+1 229 549 8447",
    "sg:postcode":"31647",
    "sg:province":"GA",
    "sg:tags":[
        "racing"
    ],
    "wof:name":"Sherry Roberts Racing",
    "wof:placetype":"venue"
},
  "geometry": {"coordinates":[-83.439148,31.16637],"type":"Point"}
}