{
  "type": "Feature",
  "properties": {
    "addr:full":"835 Franklin Rd SE Marietta GA 30067",
    "addr:housenumber":"835",
    "addr:postcode":"30067",
    "addr:street":"Franklin Rd Se",
    "iso:country":"US",
    "sg:address":"835 Franklin Rd SE",
    "sg:city":"Marietta",
    "sg:classifiers":[
        {
            "category":"Shopping",
            "subcategory":"Florist",
            "type":"Retail Goods"
        }
    ],
    "sg:phone":"+1 770 393 1475",
    "sg:postcode":"30067",
    "sg:province":"GA",
    "sg:website":"www.carithers.com",
    "wof:name":"Carithers Flowers & Gifts",
    "wof:placetype":"venue"
},
  "geometry": {"coordinates":[-84.500426,33.932849],"type":"Point"}
}