{
  "type": "Feature",
  "properties": {
    "addr:full":"5269 Stewart Mill Rd Douglasville GA 30135",
    "addr:housenumber":"5269",
    "addr:postcode":"30135",
    "addr:street":"Stewart Mill Rd",
    "iso:country":"US",
    "sg:address":"5269 Stewart Mill Rd",
    "sg:city":"Douglasville",
    "sg:classifiers":[
        {
            "category":"Retail",
            "subcategory":"Car Wash",
            "type":"Services"
        }
    ],
    "sg:phone":"+1 678 715 7080",
    "sg:postcode":"30135",
    "sg:province":"GA",
    "sg:tags":[
        "polishing",
        "washing"
    ],
    "wof:name":"Allegience Car Wash",
    "wof:placetype":"venue"
},
  "geometry": {"coordinates":[-84.75310399999999,33.708697],"type":"Point"}
}