{
  "type": "Feature",
  "properties": {
    "iso:country":"US",
    "sg:address":"301 E Webster St",
    "sg:city":"Cuthbert",
    "sg:classifiers":[
        {
            "category":"Government",
            "subcategory":"Office",
            "type":"Public Place"
        }
    ],
    "sg:phone":"+1 229 732 6211",
    "sg:postcode":"31792",
    "sg:province":"GA",
    "sg:tags":[
        "federal"
    ],
    "wof:name":"Natural Resources Conservation",
    "wof:placetype":"venue"
},
  "geometry": {"coordinates":[-83.982209,30.846408],"type":"Point"}
}