{
  "type": "Feature",
  "properties": {
    "iso:country":"US",
    "sg:address":"1109 S Main St",
    "sg:city":"Cedartown",
    "sg:classifiers":[
        {
            "category":"Shopping",
            "subcategory":"Clothing, Apparel, & Fashions",
            "type":"Retail Goods"
        }
    ],
    "sg:phone":"+1 770 749 0330",
    "sg:postcode":"30125",
    "sg:province":"GA",
    "wof:name":"Holidays Fresh Wear",
    "wof:placetype":"venue"
},
  "geometry": {"coordinates":[-85.25424700000001,34.001815],"type":"Point"}
}