{
  "type": "Feature",
  "properties": {
    "addr:full":"725 Cedar Creek Way Woodstock GA 30189",
    "addr:housenumber":"725",
    "addr:postcode":"30189",
    "addr:street":"Cedar Creek Way",
    "iso:country":"US",
    "sg:address":"725 Cedar Creek Way",
    "sg:city":"Woodstock",
    "sg:classifiers":[
        {
            "category":"Building & Trades",
            "subcategory":"Construction",
            "type":"Services"
        }
    ],
    "sg:phone":"+1 770 592 1597",
    "sg:postcode":"30189",
    "sg:province":"GA",
    "sg:tags":[
        "contractor"
    ],
    "wof:name":"Advanced Stucco Repair Inc",
    "wof:placetype":"venue"
},
  "geometry": {"coordinates":[-84.60635000000001,34.153086],"type":"Point"}
}