{
  "type": "Feature",
  "properties": {
    "addr:full":"466 W General Screven Way Hinesville GA 31313",
    "addr:housenumber":"466",
    "addr:postcode":"31313",
    "addr:street":"W General Screven Way",
    "iso:country":"US",
    "sg:address":"466 W General Screven Way",
    "sg:city":"Hinesville",
    "sg:classifiers":[
        {
            "category":"Restaurant",
            "type":"Food & Drink"
        }
    ],
    "sg:menulink":"http://www.allmenus.com/ga/hinesville/239625-wok-n-roll/menu/",
    "sg:phone":"+1 912 877 3883",
    "sg:postcode":"31313",
    "sg:province":"GA",
    "sg:tags":[
        "asian",
        "chinese"
    ],
    "wof:name":"Wok 'n Roll",
    "wof:placetype":"venue"
},
  "geometry": {"coordinates":[-81.606388,31.853288],"type":"Point"}
}