{
  "type": "Feature",
  "properties": {
    "addr:full":"735 Martin Rd Jasper GA 30143",
    "addr:housenumber":"735",
    "addr:postcode":"30143",
    "addr:street":"Martin Rd",
    "iso:country":"US",
    "sg:address":"735 Martin Rd",
    "sg:city":"Jasper",
    "sg:classifiers":[
        {
            "category":"Health Services",
            "subcategory":"Doctor",
            "type":"Services"
        }
    ],
    "sg:phone":"+1 706 253 3366",
    "sg:postcode":"30143",
    "sg:province":"GA",
    "sg:tags":[
        "medical"
    ],
    "wof:name":"Parkway Medical Center",
    "wof:placetype":"venue"
},
  "geometry": {"coordinates":[-84.43704099999999,34.438305],"type":"Point"}
}