{
  "type": "Feature",
  "properties": {
    "iso:country":"US",
    "sg:address":"190 Calla Lily Cir",
    "sg:city":"Alma",
    "sg:classifiers":[
        {
            "category":"Shopping",
            "subcategory":"Tobacco",
            "type":"Retail Goods"
        }
    ],
    "sg:phone":"+1 912 632 6351",
    "sg:postcode":"31510",
    "sg:province":"GA",
    "wof:name":"Tony King",
    "wof:placetype":"venue"
},
  "geometry": {"coordinates":[-82.365779,31.437806],"type":"Point"}
}