{
  "type": "Feature",
  "properties": {
    "addr:full":"4275 Savannah Hwy Jesup GA 31545",
    "addr:housenumber":"4275",
    "addr:postcode":"31545",
    "addr:street":"Savannah Hwy",
    "iso:country":"US",
    "sg:address":"4275 Savannah Hwy",
    "sg:city":"Jesup",
    "sg:classifiers":[
        {
            "category":"Retail",
            "subcategory":"Auto Rental",
            "type":"Services"
        }
    ],
    "sg:phone":"+1 912 427 6851",
    "sg:postcode":"31545",
    "sg:province":"GA",
    "sg:tags":[
        "renting",
        "automobile"
    ],
    "wof:name":"Carver's Sales & Rental",
    "wof:placetype":"venue"
},
  "geometry": {"coordinates":[-81.850386,31.657738],"type":"Point"}
}