{
  "type": "Feature",
  "properties": {
    "iso:country":"US",
    "sg:address":"373 Highway 138 SW Ste C",
    "sg:city":"Riverdale",
    "sg:classifiers":[
        {
            "category":"Personal",
            "subcategory":"Nail Salon",
            "type":"Services"
        }
    ],
    "sg:phone":"+1 770 477 1401",
    "sg:postcode":"30274",
    "sg:province":"GA",
    "wof:name":"Luu Nail",
    "wof:placetype":"venue"
},
  "geometry": {"coordinates":[-84.402298,33.5443],"type":"Point"}
}