{
  "type": "Feature",
  "properties": {
    "iso:country":"US",
    "sg:address":"5540 Zanola Dr",
    "sg:city":"Mableton",
    "sg:classifiers":[
        {
            "category":"Food & Beverages",
            "subcategory":"Liquor & Beverages",
            "type":"Retail Goods"
        }
    ],
    "sg:phone":"+1 770 941 1131",
    "sg:postcode":"30126",
    "sg:province":"GA",
    "sg:tags":[
        "alcoholic"
    ],
    "wof:name":"Lifting Spirits",
    "wof:placetype":"venue"
},
  "geometry": {"coordinates":[-84.596874,33.820087],"type":"Point"}
}