{
  "type": "Feature",
  "properties": {
    "iso:country":"US",
    "sg:address":"324 E Franklin St",
    "sg:city":"Hartwell",
    "sg:classifiers":[
        {
            "category":"Restaurant",
            "type":"Food & Drink"
        }
    ],
    "sg:menulink":"http://www.allmenus.com/ga/hartwell/101681-huddle-house/menu/",
    "sg:phone":"+1 706 377 4220",
    "sg:postcode":"30643",
    "sg:province":"GA",
    "sg:tags":[
        "american",
        "diner"
    ],
    "wof:name":"Huddle House",
    "wof:placetype":"venue"
},
  "geometry": {"coordinates":[-82.927605,34.352604],"type":"Point"}
}