{
  "type": "Feature",
  "properties": {
    "addr:full":"601 S Enota Dr NE Gainesville GA 30501",
    "addr:housenumber":"601",
    "addr:postcode":"30501",
    "addr:street":"S Enota Dr Ne;Ga",
    "iso:country":"US",
    "sg:address":"601 S Enota Dr NE",
    "sg:city":"Gainesville",
    "sg:classifiers":[
        {
            "category":"Food & Beverages",
            "subcategory":"Groceries & Convenience Stores",
            "type":"Retail Goods"
        }
    ],
    "sg:phone":"+1 770 297 9417",
    "sg:postcode":"30501",
    "sg:province":"GA",
    "sg:tags":[
        "supermarket"
    ],
    "sg:website":"www.foodlion.com",
    "wof:name":"Food Lion",
    "wof:placetype":"venue"
},
  "geometry": {"coordinates":[-83.81467000000001,34.313072],"type":"Point"}
}