{
  "type": "Feature",
  "properties": {
    "addr:full":"2669 Co Rd 49 Smithville GA 31783",
    "addr:housenumber":"2669;49",
    "addr:postcode":"31783",
    "addr:street":"Co Rd",
    "iso:country":"US",
    "sg:address":"2669 Co Rd 49",
    "sg:city":"Smithville",
    "sg:phone":"+1 229 846 5651",
    "sg:postcode":"31783",
    "sg:province":"GA",
    "sg:tags":[
        "farm",
        "field",
        "corn",
        "crop",
        "soybean"
    ],
    "wof:name":"Julian & Brenda Cosby Jr",
    "wof:placetype":"venue"
},
  "geometry": {"coordinates":[-83.532779,31.802091],"type":"Point"}
}