{
  "type": "Feature",
  "properties": {
    "addr:full":"1400 Dogwood Dr SE Conyers GA 30013",
    "addr:housenumber":"1400",
    "addr:postcode":"30013",
    "addr:street":"Dogwood Dr Se",
    "iso:country":"US",
    "sg:address":"1400 Dogwood Dr SE",
    "sg:city":"Conyers",
    "sg:classifiers":[
        {
            "category":"Real Estate",
            "subcategory":"Real Estate Services",
            "type":"Services"
        },
        {
            "category":"Real Estate",
            "subcategory":"Real Estate Agent",
            "type":"Services"
        }
    ],
    "sg:phone":"+1 770 483 2100",
    "sg:postcode":"30013",
    "sg:province":"GA",
    "sg:tags":[
        "buyer",
        "broker"
    ],
    "sg:website":"http://www.eastatlantahomebuyers.com",
    "wof:name":"Re/Max",
    "wof:placetype":"venue"
},
  "geometry": {"coordinates":[-84.00200700000001,33.652795],"type":"Point"}
}