{
  "type": "Feature",
  "properties": {
    "addr:full":"931 Monroe Dr Ste A102 Atlanta GA 30308",
    "addr:housenumber":"931",
    "addr:postcode":"30308",
    "addr:street":"Monroe Dr Ste A102",
    "iso:country":"US",
    "sg:address":"931 Monroe Dr Ste A102",
    "sg:city":"Atlanta",
    "sg:classifiers":[
        {
            "category":"Building & Trades",
            "subcategory":"Pest Control",
            "type":"Services"
        }
    ],
    "sg:phone":"+1 678 504 0202",
    "sg:postcode":"30308",
    "sg:province":"GA",
    "sg:website":"www.raintreepestcontrol.com/atlanta",
    "wof:name":"Raintree Pest Control",
    "wof:placetype":"venue"
},
  "geometry": {"coordinates":[-84.36796200000001,33.779736],"type":"Point"}
}