{
  "type": "Feature",
  "properties": {
    "iso:country":"US",
    "sg:address":"1462 Brookcliff Dr",
    "sg:city":"Marietta",
    "sg:classifiers":[
        {
            "category":"Shopping",
            "subcategory":"Computers & Home Electronics",
            "type":"Retail Goods"
        }
    ],
    "sg:phone":"+1 770 973 1908",
    "sg:postcode":"30062",
    "sg:province":"GA",
    "sg:tags":[
        "related"
    ],
    "wof:name":"Business Computing Inc",
    "wof:placetype":"venue"
},
  "geometry": {"coordinates":[-84.472376,33.986511],"type":"Point"}
}