{
  "type": "Feature",
  "properties": {
    "addr:full":"180 Nail Dr McDonough GA 30253",
    "addr:housenumber":"180",
    "addr:postcode":"30253",
    "addr:street":"Nail Dr",
    "iso:country":"US",
    "sg:address":"180 Nail Dr",
    "sg:city":"McDonough",
    "sg:classifiers":[
        {
            "category":"Social Services",
            "subcategory":"Child Care",
            "type":"Services"
        },
        {
            "category":"Education",
            "subcategory":"Preschool",
            "type":"Public Place"
        },
        {
            "category":"Education",
            "subcategory":"School",
            "type":"Public Place"
        }
    ],
    "sg:phone":"+1 770 573 8218",
    "sg:postcode":"30253",
    "sg:province":"GA",
    "sg:tags":[
        "elementary",
        "day"
    ],
    "sg:website":"www.meadowlandmontessori.org",
    "wof:name":"Meadowland Montessori School",
    "wof:placetype":"venue"
},
  "geometry": {"coordinates":[-84.198402,33.4258],"type":"Point"}
}