{
  "type": "Feature",
  "properties": {
    "iso:country":"US",
    "sg:address":"3523 Washington Road",
    "sg:city":"Atlanta",
    "sg:classifiers":[
        {
            "category":"Personal",
            "subcategory":"Beauty Salon",
            "type":"Services"
        }
    ],
    "sg:phone":"+1 404 766 4862",
    "sg:postcode":"30344",
    "sg:province":"GA",
    "sg:tags":[
        "hair"
    ],
    "wof:name":"Carolyn's Hair Stage",
    "wof:placetype":"venue"
},
  "geometry": {"coordinates":[-84.480273,33.658636],"type":"Point"}
}