{
  "type": "Feature",
  "properties": {
    "iso:country":"US",
    "sg:address":"3347 Crest Hwy",
    "sg:city":"Thomaston",
    "sg:classifiers":[
        {
            "category":"Building & Trades",
            "subcategory":"Plumbing",
            "type":"Services"
        }
    ],
    "sg:phone":"+1 706 647 3755",
    "sg:postcode":"30286",
    "sg:province":"GA",
    "sg:tags":[
        "conditioning",
        "air",
        "system",
        "contractor"
    ],
    "wof:name":"Airtech Heating & Cooling Inc",
    "wof:placetype":"venue"
},
  "geometry": {"coordinates":[-84.41097000000001,32.89835],"type":"Point"}
}