{
  "type": "Feature",
  "properties": {
    "iso:country":"US",
    "sg:address":"188 Gleneagles Cir",
    "sg:city":"Macon",
    "sg:classifiers":[
        {
            "category":"Professional",
            "subcategory":"Management & Consulting",
            "type":"Services"
        }
    ],
    "sg:phone":"+1 478 474 5319",
    "sg:postcode":"31210",
    "sg:province":"GA",
    "sg:tags":[
        "consultant",
        "training"
    ],
    "wof:name":"Asm Assoc",
    "wof:placetype":"venue"
},
  "geometry": {"coordinates":[-83.715431,32.861511],"type":"Point"}
}