{
  "type": "Feature",
  "properties": {
    "addr:full":"67 Kersey St Hazlehurst GA 31539",
    "addr:housenumber":"67",
    "addr:postcode":"31539",
    "addr:street":"Kersey St",
    "iso:country":"US",
    "sg:address":"67 Kersey St",
    "sg:city":"Hazlehurst",
    "sg:classifiers":[
        {
            "category":"Freight",
            "type":"Transportation"
        }
    ],
    "sg:phone":"+1 912 375 3759",
    "sg:postcode":"31539",
    "sg:province":"GA",
    "sg:tags":[
        "operator",
        "local",
        "trucking"
    ],
    "wof:name":"Kersey Chirp Chirp",
    "wof:placetype":"venue"
},
  "geometry": {"coordinates":[-82.609151,31.869425],"type":"Point"}
}