{
  "type": "Feature",
  "properties": {
    "addr:full":"1683 N Expy Griffin GA 30223",
    "addr:housenumber":"1683",
    "addr:postcode":"30223",
    "addr:street":"N Expy",
    "iso:country":"US",
    "sg:address":"1683 N Expy",
    "sg:city":"Griffin",
    "sg:classifiers":[
        {
            "category":"Personal",
            "type":"Services"
        }
    ],
    "sg:phone":"+1 770 227 3010",
    "sg:postcode":"30223",
    "sg:province":"GA",
    "wof:name":"Hot Tan Cafe",
    "wof:placetype":"venue"
},
  "geometry": {"coordinates":[-84.288066,33.255095],"type":"Point"}
}