{
  "type": "Feature",
  "properties": {
    "addr:full":"2543 Gilmore St Waycross GA 31503",
    "addr:housenumber":"2543",
    "addr:postcode":"31503",
    "addr:street":"Gilmore St",
    "iso:country":"US",
    "sg:address":"2543 Gilmore St",
    "sg:city":"Waycross",
    "sg:classifiers":[
        {
            "category":"Shopping",
            "subcategory":"Gifts & Souvenirs",
            "type":"Retail Goods"
        }
    ],
    "sg:phone":"+1 912 285 4044",
    "sg:postcode":"31503",
    "sg:province":"GA",
    "wof:name":"S G&",
    "wof:placetype":"venue"
},
  "geometry": {"coordinates":[-82.356145,31.174007],"type":"Point"}
}