{
  "type": "Feature",
  "properties": {
    "iso:country":"US",
    "sg:address":"1112 Brett Dr SW",
    "sg:city":"Conyers",
    "sg:classifiers":[
        {
            "category":"Professional",
            "subcategory":"Business Services",
            "type":"Services"
        }
    ],
    "sg:phone":"+1 770 761 1198",
    "sg:postcode":"30094",
    "sg:province":"GA",
    "sg:tags":[
        "repossessing"
    ],
    "wof:name":"Recovery South",
    "wof:placetype":"venue"
},
  "geometry": {"coordinates":[-84.02569800000001,33.653128],"type":"Point"}
}