{
  "type": "Feature",
  "properties": {
    "addr:full":"1113 West Ave SW Conyers GA 30012",
    "addr:housenumber":"1113",
    "addr:postcode":"30012",
    "addr:street":"West Ave Sw",
    "iso:country":"US",
    "sg:address":"1113 West Ave SW",
    "sg:city":"Conyers",
    "sg:classifiers":[
        {
            "category":"Professional",
            "subcategory":"Business Services",
            "type":"Services"
        }
    ],
    "sg:phone":"+1 678 413 8387",
    "sg:postcode":"30012",
    "sg:province":"GA",
    "wof:name":"Pangean Solutions Inc",
    "wof:placetype":"venue"
},
  "geometry": {"coordinates":[-84.02534,33.667362],"type":"Point"}
}