{
  "type": "Feature",
  "properties": {
    "addr:full":"4051 Stone Mountain Hwy Ste D103 Lilburn GA 30047",
    "addr:housenumber":"4051",
    "addr:postcode":"30047",
    "addr:street":"Stone Mountain Hwy Ste D103",
    "iso:country":"US",
    "sg:address":"4051 Stone Mountain Hwy Ste D103",
    "sg:city":"Lilburn",
    "sg:classifiers":[
        {
            "category":"Shopping",
            "subcategory":"Beauty & Cosmetics",
            "type":"Retail Goods"
        }
    ],
    "sg:phone":"+1 678 344 2157",
    "sg:postcode":"30047",
    "sg:province":"GA",
    "sg:tags":[
        "supply"
    ],
    "sg:website":"www.sallybeauty.com",
    "wof:name":"Sally Beauty Supply",
    "wof:placetype":"venue"
},
  "geometry": {"coordinates":[-84.07085600000001,33.837048],"type":"Point"}
}