{
  "type": "Feature",
  "properties": {
    "iso:country":"US",
    "sg:address":"2109 Wesley Chapel Rd",
    "sg:city":"Pavo",
    "sg:classifiers":[
        {
            "category":"Manufacturing",
            "subcategory":"Wood Products",
            "type":"Manufacturing & Wholesale Goods"
        }
    ],
    "sg:phone":"+1 229 324 2247",
    "sg:postcode":"31778",
    "sg:province":"GA",
    "sg:tags":[
        "container",
        "mfg"
    ],
    "wof:name":"Quality Wood Products",
    "wof:placetype":"venue"
},
  "geometry": {"coordinates":[-83.628699,31.039765],"type":"Point"}
}