{
  "type": "Feature",
  "properties": {
    "iso:country":"US",
    "sg:address":"1675 Cumberland Pkwy SE",
    "sg:city":"Smyrna",
    "sg:classifiers":[
        {
            "category":"Home & Garden",
            "subcategory":"Home Furnishings",
            "type":"Retail Goods"
        }
    ],
    "sg:phone":"+1 770 444 3200",
    "sg:postcode":"30080",
    "sg:province":"GA",
    "sg:tags":[
        "furniture-children's"
    ],
    "sg:website":"http://www.preciouscargofurniture.com",
    "wof:name":"Precious Cargo",
    "wof:placetype":"venue"
},
  "geometry": {"coordinates":[-84.49073799999999,33.849079],"type":"Point"}
}