{
  "type": "Feature",
  "properties": {
    "iso:country":"US",
    "sg:address":"2696 Wesley Chapel Rd",
    "sg:city":"Decatur",
    "sg:classifiers":[
        {
            "category":"Retail",
            "subcategory":"Laundry & Dry Cleaning",
            "type":"Services"
        }
    ],
    "sg:phone":"+1 404 284 5083",
    "sg:postcode":"30034",
    "sg:province":"GA",
    "sg:tags":[
        "curtain",
        "drapery",
        "cleaners"
    ],
    "wof:name":"Flip's Cleaners & Launderers",
    "wof:placetype":"venue"
},
  "geometry": {"coordinates":[-84.218378,33.707152],"type":"Point"}
}