{
  "type": "Feature",
  "properties": {
    "addr:full":"528 S Main St Baxley GA 31513",
    "addr:housenumber":"528",
    "addr:postcode":"31513",
    "addr:street":"S Main St",
    "iso:country":"US",
    "sg:address":"528 S Main St",
    "sg:city":"Baxley",
    "sg:classifiers":[
        {
            "category":"Health Services",
            "subcategory":"Doctor",
            "type":"Services"
        }
    ],
    "sg:phone":"+1 912 367 9737",
    "sg:postcode":"31513",
    "sg:province":"GA",
    "sg:tags":[
        "gynecology",
        "physician",
        "surgeon",
        "surgeons",
        "obstetrics"
    ],
    "wof:name":"Born Of Joy Obstetrics Gynecology Pc",
    "wof:placetype":"venue"
},
  "geometry": {"coordinates":[-82.351658,31.770775],"type":"Point"}
}