{
  "type": "Feature",
  "properties": {
    "addr:full":"2907 Cable Way Augusta GA 30909",
    "addr:housenumber":"2907",
    "addr:postcode":"30909",
    "addr:street":"Cable Way",
    "iso:country":"US",
    "sg:address":"2907 Cable Way",
    "sg:city":"Augusta",
    "sg:classifiers":[
        {
            "category":"Home & Garden",
            "subcategory":"Garden Supply",
            "type":"Retail Goods"
        },
        {
            "category":"Building & Trades",
            "subcategory":"Landscaping Services",
            "type":"Services"
        }
    ],
    "sg:phone":"+1 706 868 5669",
    "sg:postcode":"30909",
    "sg:province":"GA",
    "sg:tags":[
        "lawn",
        "maintenance",
        "grounds"
    ],
    "wof:name":"Mc Kenzie Landscaping",
    "wof:placetype":"venue"
},
  "geometry": {"coordinates":[-82.112825,33.46288],"type":"Point"}
}