{
  "type": "Feature",
  "properties": {
    "addr:full":"7351 Old Moon Rd Columbus GA 31909",
    "addr:housenumber":"7351",
    "addr:postcode":"31909",
    "addr:street":"Old Moon Rd",
    "iso:country":"US",
    "sg:address":"7351 Old Moon Rd",
    "sg:city":"Columbus",
    "sg:classifiers":[
        {
            "category":"Health Services",
            "subcategory":"Podiatrist",
            "type":"Services"
        }
    ],
    "sg:phone":"+1 706 653 5501",
    "sg:postcode":"31909",
    "sg:province":"GA",
    "wof:name":"Columbus Foot & Ankle PC",
    "wof:placetype":"venue"
},
  "geometry": {"coordinates":[-84.937493,32.559753],"type":"Point"}
}