{
  "type": "Feature",
  "properties": {
    "iso:country":"US",
    "sg:address":"1519 Glynn Ave",
    "sg:city":"Brunswick",
    "sg:classifiers":[
        {
            "category":"Professional",
            "subcategory":"Lawyer & Legal Services",
            "type":"Services"
        }
    ],
    "sg:phone":"+1 912 262 1211",
    "sg:postcode":"31520",
    "sg:province":"GA",
    "sg:tags":[
        "attorney",
        "law",
        "business",
        "bankruptcy"
    ],
    "wof:name":"Robert M Cunningham Pc",
    "wof:placetype":"venue"
},
  "geometry": {"coordinates":[-81.47956499999999,31.154265],"type":"Point"}
}