{
  "type": "Feature",
  "properties": {
    "iso:country":"US",
    "sg:address":"1045 S Main St",
    "sg:city":"Cedartown",
    "sg:classifiers":[
        {
            "category":"Manufacturing",
            "subcategory":"Metals",
            "type":"Manufacturing & Wholesale Goods"
        }
    ],
    "sg:phone":"+1 770 748 8590",
    "sg:postcode":"30125",
    "sg:province":"GA",
    "sg:tags":[
        "metalwork",
        "sheet",
        "mfg"
    ],
    "wof:name":"Ayers Sheet Metal",
    "wof:placetype":"venue"
},
  "geometry": {"coordinates":[-85.254435,34.002627],"type":"Point"}
}