{
  "type": "Feature",
  "properties": {
    "iso:country":"US",
    "sg:address":"6611 Highway 85",
    "sg:city":"Riverdale",
    "sg:classifiers":[
        {
            "category":"Retail",
            "subcategory":"Auto Repair",
            "type":"Services"
        }
    ],
    "sg:phone":"+1 770 869 8179",
    "sg:postcode":"30274",
    "sg:province":"GA",
    "sg:website":"www.drivepowerusa.com",
    "wof:name":"Drive Power USA",
    "wof:placetype":"venue"
},
  "geometry": {"coordinates":[-84.412464,33.575033],"type":"Point"}
}