{
  "type": "Feature",
  "properties": {
    "iso:country":"US",
    "sg:address":"80 Forrest Pl NE",
    "sg:city":"Atlanta",
    "sg:classifiers":[
        {
            "category":"Travel",
            "subcategory":"Hotels & Motels",
            "type":"Entertainment"
        }
    ],
    "sg:phone":"+1 404 943 1666",
    "sg:postcode":"30328",
    "sg:province":"GA",
    "wof:name":"Universal Remote Control",
    "wof:placetype":"venue"
},
  "geometry": {"coordinates":[-84.385902,33.917839],"type":"Point"}
}