{
  "type": "Feature",
  "properties": {
    "addr:full":"6690 Buford Hwy NE Atlanta GA 30340",
    "addr:housenumber":"6690",
    "addr:postcode":"30340",
    "addr:street":"Buford Hwy Ne",
    "iso:country":"US",
    "sg:address":"6690 Buford Hwy NE",
    "sg:city":"Atlanta",
    "sg:classifiers":[
        {
            "category":"Place Of Worship",
            "subcategory":"Church",
            "type":"Public Place"
        },
        {
            "category":"Place Of Worship",
            "type":"Public Place"
        }
    ],
    "sg:phone":"+1 770 448 2656",
    "sg:postcode":"30340",
    "sg:province":"GA",
    "sg:tags":[
        "churches-baptist-general",
        "churches-baptist-independent",
        "churches-baptist"
    ],
    "wof:name":"Gwinnett Baptist Tabernacle",
    "wof:placetype":"venue"
},
  "geometry": {"coordinates":[-84.24220800000001,33.927613],"type":"Point"}
}