{
  "type": "Feature",
  "properties": {
    "addr:full":"5024 Dogwood Hills Dr Buford GA 30518",
    "addr:housenumber":"5024",
    "addr:postcode":"30518",
    "addr:street":"Dogwood Hills Dr",
    "iso:country":"US",
    "sg:address":"5024 Dogwood Hills Dr",
    "sg:city":"Buford",
    "sg:classifiers":[
        {
            "category":"Real Estate",
            "subcategory":"Real Estate Agent",
            "type":"Services"
        }
    ],
    "sg:phone":"+1 770 945 2017",
    "sg:postcode":"30518",
    "sg:province":"GA",
    "wof:name":"Gibbs Properties Inc",
    "wof:placetype":"venue"
},
  "geometry": {"coordinates":[-84.05143099999999,34.100165],"type":"Point"}
}