{
  "type": "Feature",
  "properties": {
    "addr:full":"1721 Russell Pkwy Warner Robins GA 31088",
    "addr:housenumber":"1721",
    "addr:postcode":"31088",
    "addr:street":"Russell Pkwy",
    "iso:country":"US",
    "sg:address":"1721 Russell Pkwy",
    "sg:city":"Warner Robins",
    "sg:classifiers":[
        {
            "category":"Health Services",
            "subcategory":"Doctor",
            "type":"Services"
        }
    ],
    "sg:phone":"+1 478 328 7049",
    "sg:postcode":"31088",
    "sg:province":"GA",
    "wof:name":"Gary L Pool DMD Ms PC",
    "wof:placetype":"venue"
},
  "geometry": {"coordinates":[-83.665578,32.592992],"type":"Point"}
}