{
  "type": "Feature",
  "properties": {
    "iso:country":"US",
    "sg:address":"7362 Aubrey Dr",
    "sg:city":"Riverdale",
    "sg:classifiers":[
        {
            "category":"Building & Trades",
            "subcategory":"Landscaping Services",
            "type":"Services"
        }
    ],
    "sg:phone":"+1 678 665 9656",
    "sg:postcode":"30296",
    "sg:province":"GA",
    "sg:tags":[
        "lawn",
        "maintenance"
    ],
    "wof:name":"Rag Time Cleaning & Lawn Ser",
    "wof:placetype":"venue"
},
  "geometry": {"coordinates":[-84.419855,33.554276],"type":"Point"}
}