{
  "type": "Feature",
  "properties": {
    "iso:country":"US",
    "sg:address":"810 Cobb Pkwy S",
    "sg:city":"Marietta",
    "sg:classifiers":[
        {
            "category":"Autos & Motor Vehicles",
            "subcategory":"Automobile Sales",
            "type":"Retail Goods"
        }
    ],
    "sg:phone":"+1 770 422 4546",
    "sg:postcode":"30060",
    "sg:province":"GA",
    "sg:tags":[
        "car"
    ],
    "wof:name":"Team Nissan",
    "wof:placetype":"venue"
},
  "geometry": {"coordinates":[-84.510144,33.931397],"type":"Point"}
}