{
  "type": "Feature",
  "properties": {
    "iso:country":"US",
    "sg:address":"600 N Slappey Blvd",
    "sg:city":"Albany",
    "sg:classifiers":[
        {
            "category":"Professional",
            "subcategory":"Art Services",
            "type":"Services"
        },
        {
            "category":"Home & Garden",
            "subcategory":"Furniture",
            "type":"Retail Goods"
        }
    ],
    "sg:phone":"+1 229 432 5321",
    "sg:postcode":"31701",
    "sg:province":"GA",
    "sg:tags":[
        "interior",
        "designer",
        "decorator",
        "store"
    ],
    "wof:name":"Gerst Brothers Interiors",
    "wof:placetype":"venue"
},
  "geometry": {"coordinates":[-84.17617,31.584249],"type":"Point"}
}