{
  "type": "Feature",
  "properties": {
    "addr:full":"195 N Main St Hiawassee GA 30545",
    "addr:housenumber":"195",
    "addr:postcode":"30545",
    "addr:street":"N Main St",
    "iso:country":"US",
    "sg:address":"195 N Main St",
    "sg:city":"Hiawassee",
    "sg:classifiers":[
        {
            "category":"Professional",
            "subcategory":"Business Services",
            "type":"Services"
        },
        {
            "category":"Restaurant",
            "type":"Food & Drink"
        }
    ],
    "sg:phone":"+1 706 896 9385",
    "sg:postcode":"30545",
    "sg:province":"GA",
    "sg:tags":[
        "shop",
        "coffee"
    ],
    "wof:name":"Mystic Mountain Coffee House",
    "wof:placetype":"venue"
},
  "geometry": {"coordinates":[-83.725978,34.700028],"type":"Point"}
}