{
  "type": "Feature",
  "properties": {
    "addr:full":"118 30th Ave Columbus GA 31903",
    "addr:housenumber":"118",
    "addr:postcode":"31903",
    "addr:street":"30Th Ave",
    "iso:country":"US",
    "sg:address":"118 30th Ave",
    "sg:city":"Columbus",
    "sg:classifiers":[
        {
            "category":"Building & Trades",
            "subcategory":"Landscaping Services",
            "type":"Services"
        }
    ],
    "sg:phone":"+1 706 682 8730",
    "sg:postcode":"31903",
    "sg:province":"GA",
    "sg:tags":[
        "lawn",
        "masonry",
        "maintenance"
    ],
    "wof:name":"Works Art Lawn Maint Cnstr Co",
    "wof:placetype":"venue"
},
  "geometry": {"coordinates":[-84.958381,32.439549],"type":"Point"}
}