{
  "type": "Feature",
  "properties": {
    "iso:country":"US",
    "sg:address":"452 E Paces Ferry Road NE",
    "sg:city":"Atlanta",
    "sg:classifiers":[
        {
            "category":"Real Estate",
            "subcategory":"Architect",
            "type":"Services"
        }
    ],
    "sg:phone":"+1 404 876 8169",
    "sg:postcode":"30305",
    "sg:province":"GA",
    "wof:name":"Alex Munoz & Associates",
    "wof:placetype":"venue"
},
  "geometry": {"coordinates":[-84.372389,33.838188],"type":"Point"}
}