{
  "type": "Feature",
  "properties": {
    "iso:country":"US",
    "sg:address":"104 Wexford Cir",
    "sg:city":"Bonaire",
    "sg:classifiers":[
        {
            "category":"Building & Trades",
            "subcategory":"Electrical",
            "type":"Services"
        }
    ],
    "sg:phone":"+1 478 923 6800",
    "sg:postcode":"31005",
    "sg:province":"GA",
    "sg:tags":[
        "personal",
        "electrical",
        "contractor"
    ],
    "wof:name":"Mkg Services Inc",
    "wof:placetype":"venue"
},
  "geometry": {"coordinates":[-83.60614200000001,32.563336],"type":"Point"}
}