{
  "type": "Feature",
  "properties": {
    "iso:country":"US",
    "sg:address":"121 Junaluska Dr",
    "sg:city":"Woodstock",
    "sg:classifiers":[
        {
            "category":"Building & Trades",
            "subcategory":"Construction",
            "type":"Services"
        }
    ],
    "sg:phone":"+1 770 592 8748",
    "sg:postcode":"30188",
    "sg:province":"GA",
    "sg:tags":[
        "project"
    ],
    "wof:name":"A Spears Construction",
    "wof:placetype":"venue"
},
  "geometry": {"coordinates":[-84.418235,34.12188],"type":"Point"}
}