{
  "type": "Feature",
  "properties": {
    "iso:country":"US",
    "sg:address":"220 Peach Tree St",
    "sg:city":"Lincolnton",
    "sg:classifiers":[
        {
            "category":"Building & Trades",
            "subcategory":"Construction",
            "type":"Services"
        }
    ],
    "sg:phone":"+1 706 359 3528",
    "sg:postcode":"30817",
    "sg:province":"GA",
    "sg:tags":[
        "house"
    ],
    "wof:name":"Jack Reese Builders",
    "wof:placetype":"venue"
},
  "geometry": {"coordinates":[-82.47756699999999,33.79467],"type":"Point"}
}