{
  "type": "Feature",
  "properties": {
    "iso:country":"US",
    "sg:address":"211 Georgia Ave",
    "sg:city":"Atlanta",
    "sg:classifiers":[
        {
            "category":"Building & Trades",
            "subcategory":"Construction",
            "type":"Services"
        }
    ],
    "sg:phone":"+1 404 522 8900",
    "sg:postcode":"30312",
    "sg:province":"GA",
    "sg:tags":[
        "home",
        "improvement"
    ],
    "wof:name":"Summerhill Neighborhood Inc",
    "wof:placetype":"venue"
},
  "geometry": {"coordinates":[-84.38011400000001,33.736666],"type":"Point"}
}