{
  "type": "Feature",
  "properties": {
    "iso:country":"US",
    "sg:address":"302 9th St",
    "sg:city":"Vienna",
    "sg:classifiers":[
        {
            "category":"Community Center",
            "type":"Public Place"
        },
        {
            "category":"Government",
            "subcategory":"Office",
            "type":"Public Place"
        }
    ],
    "sg:phone":"+1 229 268 9176",
    "sg:postcode":"31092",
    "sg:province":"GA",
    "sg:tags":[
        "parish",
        "recreation",
        "government-county"
    ],
    "wof:name":"Dooly County Recreation D",
    "wof:placetype":"venue"
},
  "geometry": {"coordinates":[-83.78479299999999,32.09087],"type":"Point"}
}