{
  "type": "Feature",
  "properties": {
    "addr:full":"755 Commerce Dr Ste 415 Decatur GA 30030",
    "addr:housenumber":"755",
    "addr:postcode":"30030",
    "addr:street":"Commerce Dr Ste 415",
    "iso:country":"US",
    "sg:address":"755 Commerce Dr Ste 415",
    "sg:city":"Decatur",
    "sg:classifiers":[
        {
            "category":"Social Services",
            "type":"Services"
        }
    ],
    "sg:phone":"+1 770 270 6860",
    "sg:postcode":"30030",
    "sg:province":"GA",
    "sg:website":"http://www.silcga.org",
    "wof:name":"Statewide Independent Living Council Of Georgia",
    "wof:placetype":"venue"
},
  "geometry": {"coordinates":[-84.29372499999999,33.777763],"type":"Point"}
}