{
  "type": "Feature",
  "properties": {
    "addr:full":"7036 Grand Vista Ln Monroe GA 30656",
    "addr:housenumber":"7036",
    "addr:postcode":"30656",
    "addr:street":"Grand Vista Ln",
    "iso:country":"US",
    "sg:address":"7036 Grand Vista Ln",
    "sg:city":"Monroe",
    "sg:classifiers":[
        {
            "category":"Professional",
            "subcategory":"Detective & Security Services",
            "type":"Services"
        }
    ],
    "sg:phone":"+1 770 207 7694",
    "sg:postcode":"30656",
    "sg:province":"GA",
    "sg:tags":[
        "inventory"
    ],
    "wof:name":"Total Interactive Service Inc",
    "wof:placetype":"venue"
},
  "geometry": {"coordinates":[-83.76777199999999,33.898769],"type":"Point"}
}