{
  "type": "Feature",
  "properties": {
    "iso:country":"US",
    "sg:address":"4075 Old Milton Pkwy",
    "sg:city":"Alpharetta",
    "sg:classifiers":[
        {
            "category":"Restaurant",
            "type":"Food & Drink"
        },
        {
            "category":"Food & Beverages",
            "subcategory":"Bakery",
            "type":"Retail Goods"
        }
    ],
    "sg:phone":"+1 678 366 3866",
    "sg:postcode":"30005",
    "sg:province":"GA",
    "sg:tags":[
        "sandwich"
    ],
    "sg:website":"www.jerseymikes.com",
    "wof:name":"Jersey Mike's Subs",
    "wof:placetype":"venue"
},
  "geometry": {"coordinates":[-84.242699,34.060699],"type":"Point"}
}