{
  "type": "Feature",
  "properties": {
    "addr:full":"1956 N Jefferson St Milledgeville GA 31061",
    "addr:housenumber":"1956",
    "addr:postcode":"31061",
    "addr:street":"N Jefferson St",
    "iso:country":"US",
    "sg:address":"1956 N Jefferson St",
    "sg:city":"Milledgeville",
    "sg:classifiers":[
        {
            "category":"Building & Trades",
            "subcategory":"Construction",
            "type":"Services"
        }
    ],
    "sg:phone":"+1 478 452 5289",
    "sg:postcode":"31061",
    "sg:province":"GA",
    "sg:tags":[
        "contractor"
    ],
    "wof:name":"Cook Brothers Inc",
    "wof:placetype":"venue"
},
  "geometry": {"coordinates":[-83.23206399999999,33.110583],"type":"Point"}
}