{
  "type": "Feature",
  "properties": {
    "iso:country":"US",
    "sg:address":"968 Broad St",
    "sg:city":"Augusta",
    "sg:classifiers":[
        {
            "category":"Professional",
            "type":"Services"
        }
    ],
    "sg:phone":"+1 706 722 2959",
    "sg:postcode":"30901",
    "sg:province":"GA",
    "wof:name":"Eboni Economic Dev Corp",
    "wof:placetype":"venue"
},
  "geometry": {"coordinates":[-81.96962499999999,33.476839],"type":"Point"}
}