{
  "type": "Feature",
  "properties": {
    "iso:country":"US",
    "sg:address":"491 Hodges Cir",
    "sg:city":"Mansfield",
    "sg:phone":"+1 770 786 6965",
    "sg:postcode":"30055",
    "sg:province":"GA",
    "sg:tags":[
        "farm",
        "wheat"
    ],
    "wof:name":"Eugene Hodges",
    "wof:placetype":"venue"
},
  "geometry": {"coordinates":[-83.727878,33.56824],"type":"Point"}
}