{
  "type": "Feature",
  "properties": {
    "iso:country":"US",
    "sg:address":"977 Coronado Dr NW",
    "sg:city":"Atlanta",
    "sg:classifiers":[
        {
            "category":"Professional",
            "subcategory":"Engineering",
            "type":"Services"
        }
    ],
    "sg:phone":"+1 678 510 9964",
    "sg:postcode":"30327",
    "sg:province":"GA",
    "sg:tags":[
        "consulting",
        "engineer"
    ],
    "wof:name":"Jack Wexler",
    "wof:placetype":"venue"
},
  "geometry": {"coordinates":[-84.42094899999999,33.87375],"type":"Point"}
}