{
  "type": "Feature",
  "properties": {
    "iso:country":"US",
    "sg:address":"100 Lakeview Estates Dr",
    "sg:city":"Eatonton",
    "sg:classifiers":[
        {
            "category":"Social Services",
            "subcategory":"Child Care",
            "type":"Services"
        },
        {
            "category":"Education",
            "subcategory":"School",
            "type":"Public Place"
        }
    ],
    "sg:phone":"+1 706 484 0820",
    "sg:postcode":"31024",
    "sg:province":"GA",
    "sg:tags":[
        "nursery",
        "private",
        "k-",
        "day"
    ],
    "sg:website":"http://www.lakeviewacademy.com",
    "wof:name":"Lakeview Academy",
    "wof:placetype":"venue"
},
  "geometry": {"coordinates":[-83.263138,33.42852],"type":"Point"}
}