{
  "type": "Feature",
  "properties": {
    "iso:country":"US",
    "sg:address":"301 N Jefferson St",
    "sg:city":"Dublin",
    "sg:classifiers":[
        {
            "category":"Sports & Exercise",
            "subcategory":"Gym",
            "type":"Entertainment"
        }
    ],
    "sg:phone":"+1 478 275 2745",
    "sg:postcode":"31021",
    "sg:province":"GA",
    "sg:tags":[
        "fitness",
        "physical",
        "facility"
    ],
    "wof:name":"Dublin Fitness",
    "wof:placetype":"venue"
},
  "geometry": {"coordinates":[-82.90529100000001,32.541486],"type":"Point"}
}