{
  "type": "Feature",
  "properties": {
    "addr:full":"1006 Shawnee St Savannah GA 31419",
    "addr:housenumber":"1006",
    "addr:postcode":"31419",
    "addr:street":"Shawnee St",
    "iso:country":"US",
    "sg:address":"1006 Shawnee St",
    "sg:city":"Savannah",
    "sg:classifiers":[
        {
            "category":"Professional",
            "subcategory":"Business Services",
            "type":"Services"
        }
    ],
    "sg:phone":"+1 912 921 3200",
    "sg:postcode":"31419",
    "sg:province":"GA",
    "wof:name":"Cjs Dispatch",
    "wof:placetype":"venue"
},
  "geometry": {"coordinates":[-81.167559,31.98462],"type":"Point"}
}