{
  "type": "Feature",
  "properties": {
    "addr:full":"70 Village Centre East Woodstock GA 30188",
    "addr:housenumber":"70",
    "addr:postcode":"30188",
    "addr:street":"Village Centre East",
    "iso:country":"US",
    "sg:address":"70 Village Centre East",
    "sg:city":"Woodstock",
    "sg:classifiers":[
        {
            "category":"Retail",
            "subcategory":"Auto Repair",
            "type":"Services"
        }
    ],
    "sg:phone":"+1 770 517 4747",
    "sg:postcode":"30188",
    "sg:province":"GA",
    "sg:tags":[
        "oil",
        "change"
    ],
    "sg:website":"www.expressoil.com/",
    "wof:name":"Express Oil Change & Service Center",
    "wof:placetype":"venue"
},
  "geometry": {"coordinates":[-84.468902,34.087617],"type":"Point"}
}