{
  "type": "Feature",
  "properties": {
    "iso:country":"US",
    "sg:address":"916 Everee Inn Rd",
    "sg:city":"Griffin",
    "sg:classifiers":[
        {
            "category":"Freight",
            "type":"Transportation"
        }
    ],
    "sg:phone":"+1 770 233 6930",
    "sg:postcode":"30224",
    "sg:province":"GA",
    "sg:tags":[
        "trucking"
    ],
    "wof:name":"Landstar Ranger Inc",
    "wof:placetype":"venue"
},
  "geometry": {"coordinates":[-84.282259,33.231781],"type":"Point"}
}