{
  "type": "Feature",
  "properties": {
    "addr:full":"3957 Sweet Bottom Dr Duluth GA 30096",
    "addr:housenumber":"3957",
    "addr:postcode":"30096",
    "addr:street":"Sweet Bottom Dr",
    "iso:country":"US",
    "sg:address":"3957 Sweet Bottom Dr",
    "sg:city":"Duluth",
    "sg:classifiers":[
        {
            "category":"Professional",
            "type":"Services"
        }
    ],
    "sg:phone":"+1 770 623 0624",
    "sg:postcode":"30096",
    "sg:province":"GA",
    "wof:name":"Island Fantasy Yacht",
    "wof:placetype":"venue"
},
  "geometry": {"coordinates":[-84.17767499999999,34.004832],"type":"Point"}
}