{
  "type": "Feature",
  "properties": {
    "iso:country":"US",
    "sg:address":"1801 W Bay St",
    "sg:city":"Savannah",
    "sg:classifiers":[
        {
            "category":"Wholesale",
            "subcategory":"Machinery & Supplies",
            "type":"Manufacturing & Wholesale Goods"
        }
    ],
    "sg:phone":"+1 912 963 0040",
    "sg:postcode":"31415",
    "sg:province":"GA",
    "sg:tags":[
        "industrial"
    ],
    "wof:name":"Power Hydraulics Inc",
    "wof:placetype":"venue"
},
  "geometry": {"coordinates":[-81.120947,32.088975],"type":"Point"}
}