{
  "type": "Feature",
  "properties": {
    "addr:full":"3761 Mars Hill Rd Watkinsville GA 30677",
    "addr:housenumber":"3761",
    "addr:postcode":"30677",
    "addr:street":"Mars Hill Rd",
    "iso:country":"US",
    "sg:address":"3761 Mars Hill Rd",
    "sg:city":"Watkinsville",
    "sg:classifiers":[
        {
            "category":"Organizations",
            "subcategory":"Religious Organization",
            "type":"Services"
        }
    ],
    "sg:phone":"+1 706 310 1306",
    "sg:postcode":"30677",
    "sg:province":"GA",
    "sg:tags":[
        "church"
    ],
    "sg:website":"www.stphilothea.ga.goarch.org",
    "wof:name":"St Philothea Greek Orthodox",
    "wof:placetype":"venue"
},
  "geometry": {"coordinates":[-83.47513499999999,33.910072],"type":"Point"}
}