{
  "type": "Feature",
  "properties": {
    "addr:full":"2970 Holcomb Bridge Rd Alpharetta GA 30022",
    "addr:housenumber":"2970",
    "addr:postcode":"30022",
    "addr:street":"Holcomb Bridge Rd",
    "iso:country":"US",
    "sg:address":"2970 Holcomb Bridge Rd",
    "sg:city":"Alpharetta",
    "sg:classifiers":[
        {
            "category":"Autos & Motor Vehicles",
            "subcategory":"Fuel & Gas Station",
            "type":"Retail Goods"
        }
    ],
    "sg:phone":"+1 770 998 0749",
    "sg:postcode":"30022",
    "sg:province":"GA",
    "sg:tags":[
        "oil"
    ],
    "wof:name":"Chevron Food Mart",
    "wof:placetype":"venue"
},
  "geometry": {"coordinates":[-84.275429,33.989828],"type":"Point"}
}