{
  "type": "Feature",
  "properties": {
    "addr:full":"62 5th Street NW Atlanta GA 30308",
    "addr:housenumber":"62",
    "addr:postcode":"30308",
    "addr:street":"5Th Street Nw",
    "iso:country":"US",
    "sg:address":"62 5th Street NW",
    "sg:city":"Atlanta",
    "sg:classifiers":[
        {
            "category":"Personal",
            "subcategory":"Nail Salon",
            "type":"Services"
        }
    ],
    "sg:phone":"+1 404 817 9326",
    "sg:postcode":"30308",
    "sg:province":"GA",
    "sg:website":"www.nailtalkandspa.com",
    "wof:name":"Nail Talk & Tan",
    "wof:placetype":"venue"
},
  "geometry": {"coordinates":[-84.389127,33.776841],"type":"Point"}
}