{
  "type": "Feature",
  "properties": {
    "addr:full":"461 Loganville Hwy Winder GA 30680",
    "addr:housenumber":"461",
    "addr:postcode":"30680",
    "addr:street":"Loganville Hwy",
    "iso:country":"US",
    "sg:address":"461 Loganville Hwy",
    "sg:city":"Winder",
    "sg:classifiers":[
        {
            "category":"Organizations",
            "subcategory":"Religious Organization",
            "type":"Services"
        }
    ],
    "sg:phone":"+1 770 867 0460",
    "sg:postcode":"30680",
    "sg:province":"GA",
    "sg:tags":[
        "place",
        "worship",
        "church"
    ],
    "wof:name":"Pentecostal Deliverance Church",
    "wof:placetype":"venue"
},
  "geometry": {"coordinates":[-83.74239300000001,33.972401],"type":"Point"}
}