{
  "type": "Feature",
  "properties": {
    "addr:full":"2865 Andrews Dr NW Atlanta GA 30305",
    "addr:housenumber":"2865",
    "addr:postcode":"30305",
    "addr:street":"Andrews Dr Nw",
    "iso:country":"US",
    "sg:address":"2865 Andrews Dr NW",
    "sg:city":"Atlanta",
    "sg:classifiers":[
        {
            "category":"Banks & Credit Unions",
            "subcategory":"Investment Brokerage",
            "type":"Services"
        }
    ],
    "sg:phone":"+1 404 233 2996",
    "sg:postcode":"30305",
    "sg:province":"GA",
    "sg:tags":[
        "advisory"
    ],
    "wof:name":"Summit Financial Corp",
    "wof:placetype":"venue"
},
  "geometry": {"coordinates":[-84.388987,33.834335],"type":"Point"}
}