{
  "type": "Feature",
  "properties": {
    "iso:country":"US",
    "sg:address":"735 Harbor Bay Dr",
    "sg:city":"Lawrenceville",
    "sg:classifiers":[
        {
            "category":"Professional",
            "subcategory":"Advertising",
            "type":"Services"
        }
    ],
    "sg:phone":"+1 770 237 3337",
    "sg:postcode":"30045",
    "sg:province":"GA",
    "wof:name":"Moore Huie Enterprises",
    "wof:placetype":"venue"
},
  "geometry": {"coordinates":[-83.921137,33.90602],"type":"Point"}
}