{
  "type": "Feature",
  "properties": {
    "iso:country":"US",
    "sg:address":"1312 Ridgeview Rd",
    "sg:city":"Lavonia",
    "sg:classifiers":[
        {
            "category":"Farming",
            "subcategory":"Farm",
            "type":"Manufacturing & Wholesale Goods"
        }
    ],
    "sg:phone":"+1 706 476 4961",
    "sg:postcode":"30553",
    "sg:province":"GA",
    "sg:tags":[
        "crop",
        "general"
    ],
    "wof:name":"Leard Farms",
    "wof:placetype":"venue"
},
  "geometry": {"coordinates":[-83.07492499999999,34.410508],"type":"Point"}
}