{
  "type": "Feature",
  "properties": {
    "addr:full":"1656 Sweet City Rd Elberton GA 30635",
    "addr:housenumber":"1656",
    "addr:postcode":"30635",
    "addr:street":"Sweet City Rd",
    "iso:country":"US",
    "sg:address":"1656 Sweet City Rd",
    "sg:city":"Elberton",
    "sg:classifiers":[
        {
            "category":"Wholesale",
            "subcategory":"Construction Materials",
            "type":"Manufacturing & Wholesale Goods"
        }
    ],
    "sg:phone":"+1 706 213 1772",
    "sg:postcode":"30635",
    "sg:province":"GA",
    "wof:name":"Voyager Granite Inc",
    "wof:placetype":"venue"
},
  "geometry": {"coordinates":[-82.95236800000001,34.101249],"type":"Point"}
}