{
  "type": "Feature",
  "properties": {
    "iso:country":"US",
    "sg:address":"1050 Shiloh Rd NW",
    "sg:city":"Kennesaw",
    "sg:classifiers":[
        {
            "category":"Professional",
            "subcategory":"Advertising",
            "type":"Services"
        },
        {
            "category":"Professional",
            "subcategory":"Art Services",
            "type":"Services"
        }
    ],
    "sg:phone":"+1 770 424 4140",
    "sg:postcode":"30144",
    "sg:province":"GA",
    "sg:tags":[
        "product",
        "graphic",
        "specialty",
        "designer",
        "advertising-promotional"
    ],
    "sg:website":"http://www.totalgraphix.com",
    "wof:name":"Total Graphics Inc",
    "wof:placetype":"venue"
},
  "geometry": {"coordinates":[-84.580808,34.050526],"type":"Point"}
}