{
  "type": "Feature",
  "properties": {
    "addr:full":"2401 N Slappey Blvd Albany GA 31701",
    "addr:housenumber":"2401",
    "addr:postcode":"31701",
    "addr:street":"N Slappey Blvd",
    "iso:country":"US",
    "sg:address":"2401 N Slappey Blvd",
    "sg:city":"Albany",
    "sg:classifiers":[
        {
            "category":"Insurance",
            "subcategory":"Insurance Agent",
            "type":"Services"
        }
    ],
    "sg:phone":"+1 229 436 7736",
    "sg:postcode":"31701",
    "sg:province":"GA",
    "sg:website":"www.copelaninsurance.com",
    "wof:name":"Copelan Insurance Inc",
    "wof:placetype":"venue"
},
  "geometry": {"coordinates":[-84.17582299999999,31.610619],"type":"Point"}
}