{
  "type": "Feature",
  "properties": {
    "iso:country":"US",
    "sg:address":"1500 Harbor Landing #603",
    "sg:city":"Roswell",
    "sg:classifiers":[
        {
            "category":"Building & Trades",
            "subcategory":"Cleaning & Sanitation",
            "type":"Services"
        }
    ],
    "sg:phone":"+1 678 999 4403",
    "sg:postcode":"30076",
    "sg:province":"GA",
    "sg:tags":[
        "home"
    ],
    "sg:website":"saintfarcleaning.com/",
    "wof:name":"Saint-Far Super Cleaning",
    "wof:placetype":"venue"
},
  "geometry": {"coordinates":[-84.316784,34.008391],"type":"Point"}
}