{
  "type": "Feature",
  "properties": {
    "iso:country":"US",
    "sg:address":"125 S College St",
    "sg:city":"Statesboro",
    "sg:classifiers":[
        {
            "category":"Shopping",
            "type":"Retail Goods"
        }
    ],
    "sg:phone":"+1 912 212 2787",
    "sg:postcode":"30458",
    "sg:province":"GA",
    "sg:tags":[
        "art",
        "gallery",
        "dealer"
    ],
    "wof:name":"Averitt Center For The Arts",
    "wof:placetype":"venue"
},
  "geometry": {"coordinates":[-81.78602100000001,32.446077],"type":"Point"}
}