{
  "type": "Feature",
  "properties": {
    "addr:full":"2998 Barry Ave Smyrna GA 30082",
    "addr:housenumber":"2998",
    "addr:postcode":"30082",
    "addr:street":"Barry Ave",
    "iso:country":"US",
    "sg:address":"2998 Barry Ave",
    "sg:city":"Smyrna",
    "sg:classifiers":[
        {
            "category":"Building & Trades",
            "subcategory":"Construction",
            "type":"Services"
        }
    ],
    "sg:phone":"+1 770 851 0578",
    "sg:postcode":"30082",
    "sg:province":"GA",
    "sg:tags":[
        "hanging",
        "contractor"
    ],
    "wof:name":"Posada Painting",
    "wof:placetype":"venue"
},
  "geometry": {"coordinates":[-84.54984399999999,33.88362],"type":"Point"}
}