{
  "type": "Feature",
  "properties": {
    "addr:full":"6576 Church St Douglasville GA 30134",
    "addr:housenumber":"6576",
    "addr:postcode":"30134",
    "addr:street":"Church St",
    "iso:country":"US",
    "sg:address":"6576 Church St",
    "sg:city":"Douglasville",
    "sg:classifiers":[
        {
            "category":"Professional",
            "subcategory":"Accounting & Tax Preparation",
            "type":"Services"
        }
    ],
    "sg:phone":"+1 770 942 1560",
    "sg:postcode":"30134",
    "sg:province":"GA",
    "sg:tags":[
        "accountant"
    ],
    "wof:name":"Cherry Beckart & Holland Cpa's",
    "wof:placetype":"venue"
},
  "geometry": {"coordinates":[-84.745276,33.751529],"type":"Point"}
}