{
  "type": "Feature",
  "properties": {
    "addr:full":"1499 State Rte 54 Fayetteville GA 30214",
    "addr:housenumber":"1499",
    "addr:postcode":"30214",
    "addr:street":"State Rte 54",
    "iso:country":"US",
    "sg:address":"1499 State Rte 54",
    "sg:city":"Fayetteville",
    "sg:classifiers":[
        {
            "category":"Restaurant",
            "type":"Food & Drink"
        }
    ],
    "sg:phone":"+1 770 487 8906",
    "sg:postcode":"30214",
    "sg:province":"GA",
    "sg:tags":[
        "eating"
    ],
    "wof:name":"Chicken & Taters",
    "wof:placetype":"venue"
},
  "geometry": {"coordinates":[-84.524536,33.445858],"type":"Point"}
}