{
  "type": "Feature",
  "properties": {
    "addr:full":"232 Freedom Church Rd Royston GA 30662",
    "addr:housenumber":"232",
    "addr:postcode":"30662",
    "addr:street":"Freedom Church Rd",
    "iso:country":"US",
    "sg:address":"232 Freedom Church Rd",
    "sg:city":"Royston",
    "sg:classifiers":[
        {
            "category":"Organizations",
            "subcategory":"Community Association",
            "type":"Services"
        }
    ],
    "sg:phone":"+1 706 245 6584",
    "sg:postcode":"30662",
    "sg:province":"GA",
    "wof:name":"Trout Unlimited",
    "wof:placetype":"venue"
},
  "geometry": {"coordinates":[-83.099189,34.249776],"type":"Point"}
}