{
  "type": "Feature",
  "properties": {
    "addr:full":"137 Sunnywood Dr Augusta GA 30907",
    "addr:housenumber":"137",
    "addr:postcode":"30907",
    "addr:street":"Sunnywood Dr",
    "iso:country":"US",
    "sg:address":"137 Sunnywood Dr",
    "sg:city":"Augusta",
    "sg:classifiers":[
        {
            "category":"Building & Trades",
            "subcategory":"Construction",
            "type":"Services"
        }
    ],
    "sg:phone":"+1 706 650 2187",
    "sg:postcode":"30907",
    "sg:province":"GA",
    "sg:tags":[
        "house"
    ],
    "wof:name":"Modern Interiors & Cnstr",
    "wof:placetype":"venue"
},
  "geometry": {"coordinates":[-82.139664,33.508999],"type":"Point"}
}