{
  "type": "Feature",
  "properties": {
    "addr:full":"836 Oakhill Ave SW Atlanta GA 30310",
    "addr:housenumber":"836",
    "addr:postcode":"30310",
    "addr:street":"Oakhill Ave Sw",
    "iso:country":"US",
    "sg:address":"836 Oakhill Ave SW",
    "sg:city":"Atlanta",
    "sg:classifiers":[
        {
            "category":"Shopping",
            "subcategory":"Clothing, Apparel, & Fashions",
            "type":"Retail Goods"
        }
    ],
    "sg:phone":"+1 404 361 2819",
    "sg:postcode":"30310",
    "sg:province":"GA",
    "wof:name":"Cameron & Cameron",
    "wof:placetype":"venue"
},
  "geometry": {"coordinates":[-84.40924,33.732126],"type":"Point"}
}