{
  "type": "Feature",
  "properties": {
    "addr:full":"5030 Winding Rose Dr Suwanee GA 30024",
    "addr:housenumber":"5030",
    "addr:postcode":"30024",
    "addr:street":"Winding Rose Dr",
    "iso:country":"US",
    "sg:address":"5030 Winding Rose Dr",
    "sg:city":"Suwanee",
    "sg:classifiers":[
        {
            "category":"Professional",
            "type":"Services"
        }
    ],
    "sg:phone":"+1 678 482 5518",
    "sg:postcode":"30024",
    "sg:province":"GA",
    "wof:name":"Showvision Inc",
    "wof:placetype":"venue"
},
  "geometry": {"coordinates":[-84.082544,34.08226],"type":"Point"}
}