{
  "type": "Feature",
  "properties": {
    "iso:country":"US",
    "sg:address":"1019 Love Ave",
    "sg:city":"Tifton",
    "sg:classifiers":[
        {
            "category":"Social Services",
            "type":"Services"
        }
    ],
    "sg:phone":"+1 229 382 9919",
    "sg:postcode":"31794",
    "sg:province":"GA",
    "sg:tags":[
        "youth",
        "organization",
        "center"
    ],
    "wof:name":"Kids Advocacy Coalition",
    "wof:placetype":"venue"
},
  "geometry": {"coordinates":[-83.505516,31.46277],"type":"Point"}
}