{
  "type": "Feature",
  "properties": {
    "iso:country":"US",
    "sg:address":"3735 Sunny Hill Dr",
    "sg:city":"Loganville",
    "sg:classifiers":[
        {
            "category":"Building & Trades",
            "subcategory":"Plumbing",
            "type":"Services"
        }
    ],
    "sg:phone":"+1 770 466 8264",
    "sg:postcode":"30052",
    "sg:province":"GA",
    "sg:tags":[
        "contractor"
    ],
    "wof:name":"Carroll Plumbing",
    "wof:placetype":"venue"
},
  "geometry": {"coordinates":[-83.964799,33.779578],"type":"Point"}
}