{
  "type": "Feature",
  "properties": {
    "iso:country":"US",
    "sg:address":"3032 Hopkins St",
    "sg:city":"Savannah",
    "sg:classifiers":[
        {
            "category":"Social Services",
            "type":"Services"
        }
    ],
    "sg:phone":"+1 912 443 9709",
    "sg:postcode":"31405",
    "sg:province":"GA",
    "wof:name":"Parenting Guidance For Krystal",
    "wof:placetype":"venue"
},
  "geometry": {"coordinates":[-81.11680699999999,32.049946],"type":"Point"}
}