{
  "type": "Feature",
  "properties": {
    "iso:country":"US",
    "sg:address":"217 Nacoochee Dr",
    "sg:city":"Woodstock",
    "sg:classifiers":[
        {
            "category":"Building & Trades",
            "subcategory":"Construction",
            "type":"Services"
        }
    ],
    "sg:phone":"+1 770 924 7815",
    "sg:postcode":"30188",
    "sg:province":"GA",
    "sg:tags":[
        "home",
        "improvement"
    ],
    "wof:name":"George Hall",
    "wof:placetype":"venue"
},
  "geometry": {"coordinates":[-84.41662700000001,34.115078],"type":"Point"}
}