{
  "type": "Feature",
  "properties": {
    "addr:full":"3280-B Peachtree Corners Cir. Norcross GA 30071",
    "addr:housenumber":"3280-b",
    "addr:postcode":"30071",
    "addr:street":"Peachtree Corners Cir.",
    "iso:country":"US",
    "sg:address":"3280-B Peachtree Corners Cir.",
    "sg:city":"Norcross",
    "sg:classifiers":[
        {
            "category":"Building & Trades",
            "subcategory":"Construction",
            "type":"Services"
        }
    ],
    "sg:phone":"+1 770 409 8330",
    "sg:postcode":"30071",
    "sg:province":"GA",
    "sg:tags":[
        "contractor"
    ],
    "sg:website":"www.peachtreeawnings.com",
    "wof:name":"Peachtree Awnings",
    "wof:placetype":"venue"
},
  "geometry": {"coordinates":[-84.250891,33.945299],"type":"Point"}
}