{
  "type": "Feature",
  "properties": {
    "iso:country":"US",
    "sg:address":"277 Pottery Factory Dr",
    "sg:city":"Commerce",
    "sg:classifiers":[
        {
            "category":"Home & Garden",
            "subcategory":"Furniture",
            "type":"Retail Goods"
        }
    ],
    "sg:phone":"+1 706 336 6585",
    "sg:postcode":"30529",
    "sg:province":"GA",
    "wof:name":"Patio Outlet",
    "wof:placetype":"venue"
},
  "geometry": {"coordinates":[-83.46605099999999,34.251114],"type":"Point"}
}