{
  "type": "Feature",
  "properties": {
    "iso:country":"US",
    "sg:address":"122 E Lake Dr",
    "sg:city":"Decatur",
    "sg:classifiers":[
        {
            "category":"Building & Trades",
            "subcategory":"Construction",
            "type":"Services"
        }
    ],
    "sg:phone":"+1 404 378 8850",
    "sg:postcode":"30030",
    "sg:province":"GA",
    "sg:tags":[
        "contractor"
    ],
    "wof:name":"Alltop Roofing Co",
    "wof:placetype":"venue"
},
  "geometry": {"coordinates":[-84.310982,33.763421],"type":"Point"}
}