{
  "type": "Feature",
  "properties": {
    "iso:country":"US",
    "sg:address":"4783 Jonesboro Rd",
    "sg:city":"Union City",
    "sg:classifiers":[
        {
            "category":"Food & Beverages",
            "subcategory":"Liquor & Beverages",
            "type":"Retail Goods"
        }
    ],
    "sg:phone":"+1 770 964 4000",
    "sg:postcode":"30291",
    "sg:province":"GA",
    "sg:tags":[
        "beer",
        "spirit",
        "wine"
    ],
    "wof:name":"Larrys Beverage Outlet",
    "wof:placetype":"venue"
},
  "geometry": {"coordinates":[-84.543677,33.570216],"type":"Point"}
}