{
  "type": "Feature",
  "properties": {
    "addr:full":"822 Main St Forest Park GA 30297",
    "addr:housenumber":"822",
    "addr:postcode":"30297",
    "addr:street":"Main St",
    "iso:country":"US",
    "sg:address":"822 Main St",
    "sg:city":"Forest Park",
    "sg:classifiers":[
        {
            "category":"Banks & Credit Unions",
            "subcategory":"Bank",
            "type":"Services"
        }
    ],
    "sg:phone":"+1 404 366 1743",
    "sg:postcode":"30297",
    "sg:province":"GA",
    "sg:tags":[
        "national"
    ],
    "wof:name":"Heritage Bank",
    "wof:placetype":"venue"
},
  "geometry": {"coordinates":[-84.363506,33.620782],"type":"Point"}
}