{
  "type": "Feature",
  "properties": {
    "addr:full":"622 Lakes Blvd Lake Park GA 31636",
    "addr:housenumber":"622",
    "addr:postcode":"31636",
    "addr:street":"Lakes Blvd",
    "iso:country":"US",
    "sg:address":"622 Lakes Blvd",
    "sg:city":"Lake Park",
    "sg:classifiers":[
        {
            "category":"Professional",
            "subcategory":"Accounting & Tax Preparation",
            "type":"Services"
        }
    ],
    "sg:phone":"+1 229 559 7575",
    "sg:postcode":"31636",
    "sg:province":"GA",
    "sg:tags":[
        "school",
        "return",
        "vocational"
    ],
    "wof:name":"H & R Block",
    "wof:placetype":"venue"
},
  "geometry": {"coordinates":[-83.209338,30.683986],"type":"Point"}
}