{
  "type": "Feature",
  "properties": {
    "addr:full":"1960 Alison Ct SW Atlanta GA 30311",
    "addr:housenumber":"1960",
    "addr:postcode":"30311",
    "addr:street":"Alison Ct Sw",
    "iso:country":"US",
    "sg:address":"1960 Alison Ct SW",
    "sg:city":"Atlanta",
    "sg:classifiers":[
        {
            "category":"Building & Trades",
            "subcategory":"Construction",
            "type":"Services"
        }
    ],
    "sg:phone":"+1 678 499 2559",
    "sg:postcode":"30311",
    "sg:province":"GA",
    "sg:tags":[
        "repair",
        "air conditioning"
    ],
    "wof:name":"Let Us Fix It Heating & Ac",
    "wof:placetype":"venue"
},
  "geometry": {"coordinates":[-84.45262099999999,33.700668],"type":"Point"}
}