{
  "type": "Feature",
  "properties": {
    "addr:full":"3040 Marietta Hwy Canton GA 30114",
    "addr:housenumber":"3040",
    "addr:postcode":"30114",
    "addr:street":"Marietta Hwy",
    "iso:country":"US",
    "sg:address":"3040 Marietta Hwy",
    "sg:city":"Canton",
    "sg:classifiers":[
        {
            "category":"Autos & Motor Vehicles",
            "subcategory":"Auto Supplies",
            "type":"Retail Goods"
        }
    ],
    "sg:phone":"+1 770 479 2522",
    "sg:postcode":"30114",
    "sg:province":"GA",
    "sg:tags":[
        "tire"
    ],
    "wof:name":"South Canton Coastal",
    "wof:placetype":"venue"
},
  "geometry": {"coordinates":[-84.505988,34.206399],"type":"Point"}
}