{
  "type": "Feature",
  "properties": {
    "iso:country":"US",
    "sg:address":"422 Banks Rd",
    "sg:city":"Fayetteville",
    "sg:classifiers":[
        {
            "category":"Communications",
            "subcategory":"Film & Video Production",
            "type":"Services"
        }
    ],
    "sg:phone":"+1 678 884 0586",
    "sg:postcode":"30214",
    "sg:province":"GA",
    "sg:tags":[
        "web",
        "photography",
        "design"
    ],
    "wof:name":"zoned 4 Jesus Productions LLC",
    "wof:placetype":"venue"
},
  "geometry": {"coordinates":[-84.423805,33.467727],"type":"Point"}
}