{
  "type": "Feature",
  "properties": {
    "addr:full":"263 W Clayton St Athens GA 30601",
    "addr:housenumber":"263",
    "addr:postcode":"30601",
    "addr:street":"W Clayton St",
    "iso:country":"US",
    "sg:address":"263 W Clayton St",
    "sg:city":"Athens",
    "sg:classifiers":[
        {
            "category":"Professional",
            "subcategory":"Computer Services",
            "type":"Services"
        }
    ],
    "sg:phone":"+1 706 353 1484",
    "sg:postcode":"30601",
    "sg:province":"GA",
    "sg:tags":[
        "consultant",
        "designer"
    ],
    "wof:name":"Voquette",
    "wof:placetype":"venue"
},
  "geometry": {"coordinates":[-83.379262,33.957688],"type":"Point"}
}