{
  "type": "Feature",
  "properties": {
    "addr:full":"55 Glenlake Pkwy NE Atlanta GA 30328",
    "addr:housenumber":"55",
    "addr:postcode":"30328",
    "addr:street":"Glenlake Pkwy Ne",
    "iso:country":"US",
    "sg:address":"55 Glenlake Pkwy NE",
    "sg:city":"Atlanta",
    "sg:classifiers":[
        {
            "category":"Building & Trades",
            "subcategory":"Construction",
            "type":"Services"
        }
    ],
    "sg:phone":"+1 770 872 4474",
    "sg:postcode":"30328",
    "sg:province":"GA",
    "sg:tags":[
        "air",
        "heating",
        "conditioning/hvac"
    ],
    "wof:name":"Omega Heating and Air",
    "wof:placetype":"venue"
},
  "geometry": {"coordinates":[-84.360355,33.943115],"type":"Point"}
}