{
  "type": "Feature",
  "properties": {
    "addr:full":"3431 Post Rd Hortense GA 31543",
    "addr:housenumber":"3431",
    "addr:postcode":"31543",
    "addr:street":"Post Rd",
    "iso:country":"US",
    "sg:address":"3431 Post Rd",
    "sg:city":"Hortense",
    "sg:classifiers":[
        {
            "category":"Professional",
            "subcategory":"Management & Consulting",
            "type":"Services"
        }
    ],
    "sg:phone":"+1 912 530 8871",
    "sg:postcode":"31543",
    "sg:province":"GA",
    "sg:tags":[
        "training",
        "investigator"
    ],
    "wof:name":"Undercover Surveillance Assoc",
    "wof:placetype":"venue"
},
  "geometry": {"coordinates":[-81.68940600000001,31.404529],"type":"Point"}
}