{
  "type": "Feature",
  "properties": {
    "addr:full":"118 Cumberland Rd Griffin GA 30224",
    "addr:housenumber":"118",
    "addr:postcode":"30224",
    "addr:street":"Cumberland Rd",
    "iso:country":"US",
    "sg:address":"118 Cumberland Rd",
    "sg:city":"Griffin",
    "sg:classifiers":[
        {
            "category":"Professional",
            "subcategory":"Business Services",
            "type":"Services"
        }
    ],
    "sg:phone":"+1 770 412 7098",
    "sg:postcode":"30224",
    "sg:province":"GA",
    "wof:name":"Meeks Enterprises Inc",
    "wof:placetype":"venue"
},
  "geometry": {"coordinates":[-84.246985,33.204023],"type":"Point"}
}