{
  "type": "Feature",
  "properties": {
    "iso:country":"US",
    "sg:address":"773 Highway 138 SW",
    "sg:city":"Riverdale",
    "sg:classifiers":[
        {
            "category":"Personal",
            "subcategory":"Nail Salon",
            "type":"Services"
        }
    ],
    "sg:phone":"+1 770 909 0720",
    "sg:postcode":"30296",
    "sg:province":"GA",
    "wof:name":"Foxy Nail",
    "wof:placetype":"venue"
},
  "geometry": {"coordinates":[-84.415802,33.550098],"type":"Point"}
}