{
  "type": "Feature",
  "properties": {
    "addr:full":"1110 Haynes Creek Dr NE Conyers GA 30012",
    "addr:housenumber":"1110",
    "addr:postcode":"30012",
    "addr:street":"Haynes Creek Dr Ne",
    "iso:country":"US",
    "sg:address":"1110 Haynes Creek Dr NE",
    "sg:city":"Conyers",
    "sg:classifiers":[
        {
            "category":"Wholesale",
            "subcategory":"Electrical",
            "type":"Manufacturing & Wholesale Goods"
        }
    ],
    "sg:phone":"+1 770 483 5506",
    "sg:postcode":"30012",
    "sg:province":"GA",
    "sg:tags":[
        "alarm",
        "burglar",
        "system"
    ],
    "wof:name":"Noble Securtiy & Home Theater",
    "wof:placetype":"venue"
},
  "geometry": {"coordinates":[-83.977521,33.761089],"type":"Point"}
}