{
  "type": "Feature",
  "properties": {
    "iso:country":"US",
    "sg:address":"1200 Hayes Industrial Dr",
    "sg:city":"Marietta",
    "sg:classifiers":[
        {
            "category":"Professional",
            "subcategory":"Business Services",
            "type":"Services"
        }
    ],
    "sg:phone":"+1 770 425 0603",
    "sg:postcode":"30062",
    "sg:province":"GA",
    "sg:tags":[
        "delivery",
        "courier"
    ],
    "wof:name":"Travis Delivery Service",
    "wof:placetype":"venue"
},
  "geometry": {"coordinates":[-84.54029800000001,33.979401],"type":"Point"}
}