{
  "type": "Feature",
  "properties": {
    "iso:country":"US",
    "sg:address":"908 Mickleton Ln",
    "sg:city":"Peachtree City",
    "sg:classifiers":[
        {
            "category":"Personal",
            "subcategory":"Beauty Salon",
            "type":"Services"
        }
    ],
    "sg:phone":"+1 770 487 3430",
    "sg:postcode":"30269",
    "sg:province":"GA",
    "sg:tags":[
        "shop"
    ],
    "wof:name":"Cindys Place",
    "wof:placetype":"venue"
},
  "geometry": {"coordinates":[-84.571382,33.432378],"type":"Point"}
}