{
  "type": "Feature",
  "properties": {
    "addr:full":"4195 Quail Springs Cir Augusta GA 30907",
    "addr:housenumber":"4195",
    "addr:postcode":"30907",
    "addr:street":"Quail Springs Cir",
    "iso:country":"US",
    "sg:address":"4195 Quail Springs Cir",
    "sg:city":"Augusta",
    "sg:classifiers":[
        {
            "category":"Restaurant",
            "type":"Food & Drink"
        }
    ],
    "sg:phone":"+1 706 863 8864",
    "sg:postcode":"30907",
    "sg:province":"GA",
    "sg:tags":[
        "business"
    ],
    "wof:name":"Monica Enterprises Inc",
    "wof:placetype":"venue"
},
  "geometry": {"coordinates":[-82.11090799999999,33.502788],"type":"Point"}
}