{
  "type": "Feature",
  "properties": {
    "iso:country":"US",
    "sg:address":"1904 Lazenby Dr",
    "sg:city":"Augusta",
    "sg:classifiers":[
        {
            "category":"Freight",
            "type":"Transportation"
        }
    ],
    "sg:phone":"+1 706 793 9674",
    "sg:postcode":"30906",
    "sg:province":"GA",
    "sg:tags":[
        "mobile",
        "home"
    ],
    "wof:name":"Dansby's Mobile Home Svc",
    "wof:placetype":"venue"
},
  "geometry": {"coordinates":[-82.00536099999999,33.439525],"type":"Point"}
}