{
  "type": "Feature",
  "properties": {
    "iso:country":"US",
    "sg:address":"3669 Meadow Glen Cir",
    "sg:city":"Ellenwood",
    "sg:classifiers":[
        {
            "category":"Retail",
            "subcategory":"Car Wash",
            "type":"Services"
        }
    ],
    "sg:phone":"+1 770 318 7321",
    "sg:postcode":"30294",
    "sg:province":"GA",
    "sg:tags":[
        "carwash"
    ],
    "wof:name":"Divine Shine",
    "wof:placetype":"venue"
},
  "geometry": {"coordinates":[-84.267509,33.62212],"type":"Point"}
}