{
  "type": "Feature",
  "properties": {
    "iso:country":"US",
    "sg:address":"1104 Monticello St SW",
    "sg:city":"Covington",
    "sg:classifiers":[
        {
            "category":"Building & Trades",
            "subcategory":"Construction",
            "type":"Services"
        }
    ],
    "sg:phone":"+1 770 786 0163",
    "sg:postcode":"30014",
    "sg:province":"GA",
    "sg:tags":[
        "general",
        "contractor"
    ],
    "wof:name":"Waterways Construction Inc",
    "wof:placetype":"venue"
},
  "geometry": {"coordinates":[-83.86040300000001,33.596004],"type":"Point"}
}