{
  "type": "Feature",
  "properties": {
    "addr:full":"570 Main St Clermont GA 30527",
    "addr:housenumber":"570",
    "addr:postcode":"30527",
    "addr:street":"Main St",
    "iso:country":"US",
    "sg:address":"570 Main St",
    "sg:city":"Clermont",
    "sg:classifiers":[
        {
            "category":"Retail",
            "subcategory":"Auto Repair",
            "type":"Services"
        }
    ],
    "sg:phone":"+1 678 316 6401",
    "sg:postcode":"30527",
    "sg:province":"GA",
    "sg:tags":[
        "engine",
        "engines-rebuild",
        "exchange",
        "rebuilding"
    ],
    "wof:name":"R & R Lawnmower",
    "wof:placetype":"venue"
},
  "geometry": {"coordinates":[-83.77050800000001,34.48402],"type":"Point"}
}