{
  "type": "Feature",
  "properties": {
    "iso:country":"US",
    "sg:address":"2655 Ross Rd",
    "sg:city":"Snellville",
    "sg:classifiers":[
        {
            "category":"Insurance",
            "subcategory":"Hazard Insurance",
            "type":"Services"
        }
    ],
    "sg:phone":"+1 770 736 4220",
    "sg:postcode":"30039",
    "sg:province":"GA",
    "sg:tags":[
        "carrier"
    ],
    "wof:name":"Empire Fire & Marine Insur Co",
    "wof:placetype":"venue"
},
  "geometry": {"coordinates":[-84.06949299999999,33.818324],"type":"Point"}
}