{
  "type": "Feature",
  "properties": {
    "addr:full":"2103 Lenox Rd NE Atlanta GA 30324",
    "addr:housenumber":"2103",
    "addr:postcode":"30324",
    "addr:street":"Lenox Rd Ne",
    "iso:country":"US",
    "sg:address":"2103 Lenox Rd NE",
    "sg:city":"Atlanta",
    "sg:classifiers":[
        {
            "category":"Shopping",
            "subcategory":"Gifts & Souvenirs",
            "type":"Retail Goods"
        }
    ],
    "sg:phone":"+1 404 593 8698",
    "sg:postcode":"30324",
    "sg:province":"GA",
    "sg:tags":[
        "shop"
    ],
    "wof:name":"Sensational Scents Inc",
    "wof:placetype":"venue"
},
  "geometry": {"coordinates":[-84.351303,33.811531],"type":"Point"}
}