{
  "type": "Feature",
  "properties": {
    "addr:full":"562 Old Evans Rd Evans GA 30809",
    "addr:housenumber":"562",
    "addr:postcode":"30809",
    "addr:street":"Old Evans Rd",
    "iso:country":"US",
    "sg:address":"562 Old Evans Rd",
    "sg:city":"Evans",
    "sg:classifiers":[
        {
            "category":"Professional",
            "subcategory":"Management & Consulting",
            "type":"Services"
        }
    ],
    "sg:phone":"+1 706 855 5790",
    "sg:postcode":"30809",
    "sg:province":"GA",
    "sg:tags":[
        "consultant",
        "educational"
    ],
    "wof:name":"Freida A Lachman Consultant",
    "wof:placetype":"venue"
},
  "geometry": {"coordinates":[-82.124071,33.535134],"type":"Point"}
}