{
  "type": "Feature",
  "properties": {
    "addr:full":"1085 Howell Mill Rd NW Atlanta GA 30318",
    "addr:housenumber":"1085",
    "addr:postcode":"30318",
    "addr:street":"Howell Mill Rd Nw",
    "iso:country":"US",
    "sg:address":"1085 Howell Mill Rd NW",
    "sg:city":"Atlanta",
    "sg:classifiers":[
        {
            "category":"Manufacturing",
            "subcategory":"Metals",
            "type":"Manufacturing & Wholesale Goods"
        },
        {
            "category":"Wholesale",
            "subcategory":"Construction Materials",
            "type":"Manufacturing & Wholesale Goods"
        },
        {
            "category":"Building & Trades",
            "subcategory":"Construction",
            "type":"Services"
        },
        {
            "category":"Manufacturing",
            "subcategory":"Building Materials",
            "type":"Manufacturing & Wholesale Goods"
        },
        {
            "category":"Train Station",
            "subcategory":"Rail",
            "type":"Transportation"
        }
    ],
    "sg:phone":"+1 404 351 7038",
    "sg:postcode":"30318",
    "sg:province":"GA",
    "sg:tags":[
        "stairway",
        "fence-sales",
        "work",
        "rails",
        "contractor",
        "fence-wholesale",
        "iron",
        "railing",
        "gate",
        "accessory",
        "manufacturer"
    ],
    "sg:website":"http://www.ironworks-intl.com",
    "wof:name":"Ironworks International Inc",
    "wof:placetype":"venue"
},
  "geometry": {"coordinates":[-84.411905,33.784257],"type":"Point"}
}