{
  "type": "Feature",
  "properties": {
    "iso:country":"US",
    "sg:address":"1191 Lake Dr",
    "sg:city":"Midway",
    "sg:classifiers":[
        {
            "category":"Professional",
            "type":"Services"
        }
    ],
    "sg:phone":"+1 912 884 5096",
    "sg:postcode":"31320",
    "sg:province":"GA",
    "wof:name":"Michelle R Bunkley",
    "wof:placetype":"venue"
},
  "geometry": {"coordinates":[-81.371149,31.835026],"type":"Point"}
}