{
  "type": "Feature",
  "properties": {
    "iso:country":"US",
    "sg:address":"605 Green St NW",
    "sg:city":"Gainesville",
    "sg:classifiers":[
        {
            "category":"Professional",
            "subcategory":"Accounting & Tax Preparation",
            "type":"Services"
        }
    ],
    "sg:phone":"+1 678 450 6478",
    "sg:postcode":"30501",
    "sg:province":"GA",
    "sg:tags":[
        "accountant"
    ],
    "wof:name":"Paul F Kelly CPA",
    "wof:placetype":"venue"
},
  "geometry": {"coordinates":[-83.825791,34.300404],"type":"Point"}
}