{
  "type": "Feature",
  "properties": {
    "addr:full":"1404 Ashley Run Ct Norcross GA 30092",
    "addr:housenumber":"1404",
    "addr:postcode":"30092",
    "addr:street":"Ashley Run Ct",
    "iso:country":"US",
    "sg:address":"1404 Ashley Run Ct",
    "sg:city":"Norcross",
    "sg:classifiers":[
        {
            "category":"Building & Trades",
            "subcategory":"Construction",
            "type":"Services"
        }
    ],
    "sg:phone":"+1 770 449 5914",
    "sg:postcode":"30092",
    "sg:province":"GA",
    "sg:tags":[
        "house"
    ],
    "wof:name":"Y2k Construction LLC",
    "wof:placetype":"venue"
},
  "geometry": {"coordinates":[-84.260381,33.948271],"type":"Point"}
}