{
  "type": "Feature",
  "properties": {
    "addr:full":"6305 Roswell Rd NE Atlanta GA 30328",
    "addr:housenumber":"6305;rd",
    "addr:postcode":"30328",
    "addr:street":"Roswell;Ne",
    "iso:country":"US",
    "sg:address":"6305 Roswell Rd NE",
    "sg:city":"Atlanta",
    "sg:classifiers":[
        {
            "category":"Personal",
            "type":"Services"
        },
        {
            "category":"Sports & Exercise",
            "subcategory":"Gym",
            "type":"Entertainment"
        },
        {
            "category":"Health Services",
            "subcategory":"Health Practitioner",
            "type":"Services"
        },
        {
            "category":"Arena",
            "subcategory":"Sports Club",
            "type":"Entertainment"
        }
    ],
    "sg:phone":"+1 800 615 7352",
    "sg:postcode":"30328",
    "sg:province":"GA",
    "sg:tags":[
        "trainer",
        "control",
        "weight",
        "consultant",
        "program",
        "fitness",
        "physical"
    ],
    "sg:website":"http://atlanta.citysearch.com/profile/external/38663262/atlanta_ga/curves.html?publisher=yellowpages&reference_id=1&placement=ypwebsitemip",
    "wof:name":"Curves",
    "wof:placetype":"venue"
},
  "geometry": {"coordinates":[-84.379097,33.926775],"type":"Point"}
}