{
  "type": "Feature",
  "properties": {
    "iso:country":"US",
    "sg:address":"5462 Mayfair Crossing Dr",
    "sg:city":"Lithonia",
    "sg:classifiers":[
        {
            "category":"Building & Trades",
            "subcategory":"Construction",
            "type":"Services"
        }
    ],
    "sg:phone":"+1 770 981 3104",
    "sg:postcode":"30038",
    "sg:province":"GA",
    "sg:tags":[
        "contractor"
    ],
    "wof:name":"Alp Contracting Inc",
    "wof:placetype":"venue"
},
  "geometry": {"coordinates":[-84.16631700000001,33.698519],"type":"Point"}
}