{
  "type": "Feature",
  "properties": {
    "addr:full":"2290 Darlington Dr Augusta GA 30904",
    "addr:housenumber":"2290",
    "addr:postcode":"30904",
    "addr:street":"Darlington Dr",
    "iso:country":"US",
    "sg:address":"2290 Darlington Dr",
    "sg:city":"Augusta",
    "sg:classifiers":[
        {
            "category":"Health Services",
            "subcategory":"Clinic",
            "type":"Services"
        }
    ],
    "sg:phone":"+1 706 736 6614",
    "sg:postcode":"30904",
    "sg:province":"GA",
    "sg:tags":[
        "home",
        "intermediate",
        "care",
        "facility"
    ],
    "wof:name":"H & J Family Personal Care",
    "wof:placetype":"venue"
},
  "geometry": {"coordinates":[-82.02328,33.451572],"type":"Point"}
}