{
  "type": "Feature",
  "properties": {
    "iso:country":"US",
    "sg:address":"7292 Woodland Cir",
    "sg:city":"Riverdale",
    "sg:classifiers":[
        {
            "category":"Wholesale",
            "subcategory":"Vending Machines",
            "type":"Manufacturing & Wholesale Goods"
        }
    ],
    "sg:phone":"+1 770 473 7656",
    "sg:postcode":"30274",
    "sg:province":"GA",
    "wof:name":"L & M Vending",
    "wof:placetype":"venue"
},
  "geometry": {"coordinates":[-84.396286,33.556013],"type":"Point"}
}