{
  "type": "Feature",
  "properties": {
    "iso:country":"US",
    "sg:address":"6293 Mountain Brook Way NW",
    "sg:city":"Atlanta",
    "sg:classifiers":[
        {
            "category":"Shopping",
            "subcategory":"Shoes",
            "type":"Retail Goods"
        }
    ],
    "sg:phone":"+1 404 256 1127",
    "sg:postcode":"30328",
    "sg:province":"GA",
    "sg:tags":[
        "store"
    ],
    "wof:name":"Stockton Sales Inc",
    "wof:placetype":"venue"
},
  "geometry": {"coordinates":[-84.41355799999999,33.927153],"type":"Point"}
}