{
  "type": "Feature",
  "properties": {
    "addr:full":"19 Pottersville Ct Jefferson GA 30549",
    "addr:housenumber":"19",
    "addr:postcode":"30549",
    "addr:street":"Pottersville Ct",
    "iso:country":"US",
    "sg:address":"19 Pottersville Ct",
    "sg:city":"Jefferson",
    "sg:classifiers":[
        {
            "category":"Manufacturing",
            "subcategory":"Buildings",
            "type":"Manufacturing & Wholesale Goods"
        },
        {
            "category":"Building & Trades",
            "subcategory":"Construction",
            "type":"Services"
        }
    ],
    "sg:phone":"+1 706 215 1706",
    "sg:postcode":"30549",
    "sg:province":"GA",
    "sg:tags":[
        "industrial",
        "consultant",
        "builder",
        "contractor",
        "contractors-commercial",
        "home"
    ],
    "wof:name":"Adkins Builders Inc",
    "wof:placetype":"venue"
},
  "geometry": {"coordinates":[-83.594657,34.160263],"type":"Point"}
}