{
  "type": "Feature",
  "properties": {
    "addr:full":"281 S Main St Alpharetta GA 30004",
    "addr:housenumber":"281",
    "addr:postcode":"30004",
    "addr:street":"S Main St",
    "iso:country":"US",
    "sg:address":"281 S Main St",
    "sg:city":"Alpharetta",
    "sg:classifiers":[
        {
            "category":"Shopping",
            "subcategory":"Hobbies, Toys, & Games",
            "type":"Retail Goods"
        }
    ],
    "sg:phone":"+1 770 772 4500",
    "sg:postcode":"30004",
    "sg:province":"GA",
    "sg:tags":[
        "supply"
    ],
    "wof:name":"Player One Games",
    "wof:placetype":"venue"
},
  "geometry": {"coordinates":[-84.30067,34.068305],"type":"Point"}
}