{
  "type": "Feature",
  "properties": {
    "iso:country":"US",
    "sg:address":"2933 Amwiler Ct NW",
    "sg:city":"Atlanta",
    "sg:classifiers":[
        {
            "category":"Manufacturing",
            "subcategory":"Furniture",
            "type":"Manufacturing & Wholesale Goods"
        }
    ],
    "sg:phone":"+1 770 300 9313",
    "sg:postcode":"30360",
    "sg:province":"GA",
    "sg:tags":[
        "mfg",
        "mattress"
    ],
    "wof:name":"Golden Mattress",
    "wof:placetype":"venue"
},
  "geometry": {"coordinates":[-84.257053,33.92884],"type":"Point"}
}