{
  "type": "Feature",
  "properties": {
    "addr:full":"215 Blackberry Run Fayetteville GA 30214",
    "addr:housenumber":"215",
    "addr:postcode":"30214",
    "addr:street":"Blackberry Run",
    "iso:country":"US",
    "sg:address":"215 Blackberry Run",
    "sg:city":"Fayetteville",
    "sg:classifiers":[
        {
            "category":"Building & Trades",
            "subcategory":"Cleaning & Sanitation",
            "type":"Services"
        }
    ],
    "sg:phone":"+1 678 817 0886",
    "sg:postcode":"30214",
    "sg:province":"GA",
    "sg:tags":[
        "maintenance"
    ],
    "wof:name":"Atk Cleaning Services",
    "wof:placetype":"venue"
},
  "geometry": {"coordinates":[-84.51512200000001,33.488594],"type":"Point"}
}