{
  "type": "Feature",
  "properties": {
    "addr:full":"175 W Shore Dr La Fayette GA 30728",
    "addr:housenumber":"175",
    "addr:postcode":"30728",
    "addr:street":"W Shore Dr La Fayette",
    "iso:country":"US",
    "sg:address":"175 W Shore Dr",
    "sg:city":"La Fayette",
    "sg:classifiers":[
        {
            "category":"Professional",
            "subcategory":"Management & Consulting",
            "type":"Services"
        }
    ],
    "sg:phone":"+1 706 638 0558",
    "sg:postcode":"30728",
    "sg:province":"GA",
    "sg:tags":[
        "public",
        "relations"
    ],
    "wof:name":"H & H Sales & Marketing Inc",
    "wof:placetype":"venue"
},
  "geometry": {"coordinates":[-85.263851,34.730852],"type":"Point"}
}