{
  "type": "Feature",
  "properties": {
    "addr:full":"3379 Peachtree Rd Atlanta GA 30326",
    "addr:housenumber":"3379",
    "addr:postcode":"30326",
    "addr:street":"Peachtree Rd",
    "iso:country":"US",
    "sg:address":"3379 Peachtree Rd",
    "sg:city":"Atlanta",
    "sg:classifiers":[
        {
            "category":"Banks & Credit Unions",
            "subcategory":"Bank",
            "type":"Services"
        }
    ],
    "sg:phone":"+1 404 261 2612",
    "sg:postcode":"30326",
    "sg:province":"GA",
    "sg:tags":[
        "federal",
        "savings"
    ],
    "wof:name":"Colonial Bank",
    "wof:placetype":"venue"
},
  "geometry": {"coordinates":[-84.36201699999999,33.850598],"type":"Point"}
}