{
  "type": "Feature",
  "properties": {
    "iso:country":"US",
    "sg:address":"1501 10th Ave",
    "sg:city":"Albany",
    "sg:classifiers":[
        {
            "category":"Professional",
            "subcategory":"Lawyer & Legal Services",
            "type":"Services"
        }
    ],
    "sg:phone":"+1 229 483 9772",
    "sg:postcode":"31707",
    "sg:province":"GA",
    "wof:name":"Jennifer R Robinson Atty",
    "wof:placetype":"venue"
},
  "geometry": {"coordinates":[-84.18850399999999,31.598255],"type":"Point"}
}