{
  "type": "Feature",
  "properties": {
    "iso:country":"US",
    "sg:address":"1289 Oconee St",
    "sg:city":"Athens",
    "sg:classifiers":[
        {
            "category":"Food & Beverages",
            "subcategory":"Liquor & Beverages",
            "type":"Retail Goods"
        }
    ],
    "sg:phone":"+1 706 353 2833",
    "sg:postcode":"30605",
    "sg:province":"GA",
    "sg:tags":[
        "alcoholic"
    ],
    "wof:name":"Red & Black Package Store",
    "wof:placetype":"venue"
},
  "geometry": {"coordinates":[-83.362268,33.94979],"type":"Point"}
}