{
  "type": "Feature",
  "properties": {
    "addr:full":"8861 Wesley Pl Jonesboro GA 30238",
    "addr:housenumber":"8861",
    "addr:postcode":"30238",
    "addr:street":"Wesley Pl",
    "iso:country":"US",
    "sg:address":"8861 Wesley Pl",
    "sg:city":"Jonesboro",
    "sg:classifiers":[
        {
            "category":"Professional",
            "subcategory":"Employment Agencies",
            "type":"Services"
        }
    ],
    "sg:phone":"+1 770 477 7201",
    "sg:postcode":"30238",
    "sg:province":"GA",
    "wof:name":"Banks Staffing Services",
    "wof:placetype":"venue"
},
  "geometry": {"coordinates":[-84.405773,33.514097],"type":"Point"}
}