{
  "type": "Feature",
  "properties": {
    "addr:full":"352 Ward Rd Ellenwood GA 30294",
    "addr:housenumber":"352",
    "addr:postcode":"30294",
    "addr:street":"Ward Rd",
    "iso:country":"US",
    "sg:address":"352 Ward Rd",
    "sg:city":"Ellenwood",
    "sg:classifiers":[
        {
            "category":"Professional",
            "subcategory":"Engineering",
            "type":"Services"
        },
        {
            "category":"Professional",
            "subcategory":"Computer Services",
            "type":"Services"
        }
    ],
    "sg:phone":"+1 770 323 3200",
    "sg:postcode":"30294",
    "sg:province":"GA",
    "sg:tags":[
        "engineer",
        "consultant",
        "designer",
        "integration",
        "system"
    ],
    "wof:name":"J3 Development, Inc.",
    "wof:placetype":"venue"
},
  "geometry": {"coordinates":[-84.19103200000001,33.632259],"type":"Point"}
}