{
  "type": "Feature",
  "properties": {
    "addr:full":"3200 Austell Rd SW Marietta GA 30008",
    "addr:housenumber":"3200",
    "addr:postcode":"30008",
    "addr:street":"Austell Rd Sw",
    "iso:country":"US",
    "sg:address":"3200 Austell Rd SW",
    "sg:city":"Marietta",
    "sg:classifiers":[
        {
            "category":"Manufacturing",
            "subcategory":"Glass & Minerals",
            "type":"Manufacturing & Wholesale Goods"
        }
    ],
    "sg:phone":"+1 770 434 2041",
    "sg:postcode":"30008",
    "sg:province":"GA",
    "sg:website":"www.afgdmarietta.com",
    "wof:name":"Afg Glass",
    "wof:placetype":"venue"
},
  "geometry": {"coordinates":[-84.58969399999999,33.876561],"type":"Point"}
}