{
  "type": "Feature",
  "properties": {
    "addr:full":"1892 Forge St Tucker GA 30084",
    "addr:housenumber":"1892",
    "addr:postcode":"30084",
    "addr:street":"Forge St",
    "iso:country":"US",
    "sg:address":"1892 Forge St",
    "sg:city":"Tucker",
    "sg:classifiers":[
        {
            "category":"Manufacturing",
            "subcategory":"Food",
            "type":"Manufacturing & Wholesale Goods"
        }
    ],
    "sg:phone":"+1 770 938 1929",
    "sg:postcode":"30084",
    "sg:province":"GA",
    "sg:tags":[
        "frozen"
    ],
    "wof:name":"Saborex Inc",
    "wof:placetype":"venue"
},
  "geometry": {"coordinates":[-84.198662,33.838915],"type":"Point"}
}