{
  "type": "Feature",
  "properties": {
    "iso:country":"US",
    "sg:address":"500 Medical Center Blvd Ste 290",
    "sg:city":"Lawrenceville",
    "sg:classifiers":[
        {
            "category":"Health Services",
            "subcategory":"Doctor",
            "type":"Services"
        }
    ],
    "sg:phone":"+1 770 962 5100",
    "sg:postcode":"30046",
    "sg:province":"GA",
    "sg:tags":[
        "obstetrician",
        "gynecologist"
    ],
    "wof:name":"Dorigen K Komjathy MD",
    "wof:placetype":"venue"
},
  "geometry": {"coordinates":[-84.01283599999999,33.966093],"type":"Point"}
}