{
  "type": "Feature",
  "properties": {
    "addr:full":"6419 Campbellton Redwine Rd Palmetto GA 30268",
    "addr:housenumber":"6419",
    "addr:postcode":"30268",
    "addr:street":"Campbellton Redwine Rd",
    "iso:country":"US",
    "sg:address":"6419 Campbellton Redwine Rd",
    "sg:city":"Palmetto",
    "sg:classifiers":[
        {
            "category":"Building & Trades",
            "subcategory":"Construction",
            "type":"Services"
        }
    ],
    "sg:phone":"+1 770 463 0930",
    "sg:postcode":"30268",
    "sg:province":"GA",
    "sg:tags":[
        "house"
    ],
    "wof:name":"Hannah Home Contracting",
    "wof:placetype":"venue"
},
  "geometry": {"coordinates":[-84.773365,33.5801],"type":"Point"}
}