{
  "type": "Feature",
  "properties": {
    "iso:country":"US",
    "sg:address":"135 Summer Xing",
    "sg:city":"Atlanta",
    "sg:classifiers":[
        {
            "category":"Professional",
            "subcategory":"Art Services",
            "type":"Services"
        }
    ],
    "sg:phone":"+1 770 900 9826",
    "sg:postcode":"30350",
    "sg:province":"GA",
    "sg:tags":[
        "designer",
        "display",
        "producer"
    ],
    "wof:name":"Your Travel By Design",
    "wof:placetype":"venue"
},
  "geometry": {"coordinates":[-84.334883,34.000097],"type":"Point"}
}