{
  "type": "Feature",
  "properties": {
    "iso:country":"US",
    "sg:address":"437 Hosanna Cir",
    "sg:city":"Americus",
    "sg:classifiers":[
        {
            "category":"Organizations",
            "subcategory":"Religious Organization",
            "type":"Services"
        }
    ],
    "sg:phone":"+1 229 928 5536",
    "sg:postcode":"31719",
    "sg:province":"GA",
    "wof:name":"Household of Faith Ministries",
    "wof:placetype":"venue"
},
  "geometry": {"coordinates":[-84.239133,32.09749],"type":"Point"}
}