{
  "type": "Feature",
  "properties": {
    "addr:full":"4315 Jodeco Rd Mcdonough GA 30253",
    "addr:housenumber":"4315",
    "addr:postcode":"30253",
    "addr:street":"Jodeco Rd",
    "iso:country":"US",
    "sg:address":"4315 Jodeco Rd",
    "sg:city":"Mcdonough",
    "sg:classifiers":[
        {
            "category":"Restaurant",
            "type":"Food & Drink"
        }
    ],
    "sg:phone":"+1 770 954 0311",
    "sg:postcode":"30253",
    "sg:province":"GA",
    "sg:tags":[
        "delivery",
        "eating"
    ],
    "wof:name":"Santos Taqueria Express",
    "wof:placetype":"venue"
},
  "geometry": {"coordinates":[-84.17665100000001,33.487799],"type":"Point"}
}