{
  "type": "Feature",
  "properties": {
    "iso:country":"US",
    "sg:address":"222 Pine Ave",
    "sg:city":"Albany",
    "sg:classifiers":[
        {
            "category":"Government",
            "subcategory":"Office",
            "type":"Public Place"
        }
    ],
    "sg:phone":"+1 229 431 2161",
    "sg:postcode":"31701",
    "sg:province":"GA",
    "sg:tags":[
        "village"
    ],
    "wof:name":"Albany Board Of Commissioners",
    "wof:placetype":"venue"
},
  "geometry": {"coordinates":[-84.152136,31.578408],"type":"Point"}
}