{
  "type": "Feature",
  "properties": {
    "iso:country":"US",
    "sg:address":"165 Willow Tree Ter",
    "sg:city":"Covington",
    "sg:classifiers":[
        {
            "category":"Utilities",
            "subcategory":"Telephone",
            "type":"Services"
        }
    ],
    "sg:phone":"+1 770 786 3943",
    "sg:postcode":"30016",
    "sg:province":"GA",
    "sg:tags":[
        "company"
    ],
    "wof:name":"A T & T Cits",
    "wof:placetype":"venue"
},
  "geometry": {"coordinates":[-83.943864,33.582651],"type":"Point"}
}