{
  "type": "Feature",
  "properties": {
    "iso:country":"US",
    "sg:address":"1680 Mountain Shadow",
    "sg:city":"Stone Mountain",
    "sg:classifiers":[
        {
            "category":"Professional",
            "type":"Services"
        }
    ],
    "sg:phone":"+1 770 414 9809",
    "sg:postcode":"30087",
    "sg:province":"GA",
    "wof:name":"AK Corporation",
    "wof:placetype":"venue"
},
  "geometry": {"coordinates":[-84.174978,33.83711],"type":"Point"}
}