{
  "type": "Feature",
  "properties": {
    "addr:full":"4200 Paces Ferry Rd NW Atlanta GA 30303",
    "addr:housenumber":"4200",
    "addr:postcode":"30303",
    "addr:street":"Paces Ferry Rd Nw",
    "iso:country":"US",
    "sg:address":"4200 Paces Ferry Rd NW",
    "sg:city":"Atlanta",
    "sg:classifiers":[
        {
            "category":"Shopping",
            "subcategory":"Clothing, Apparel, & Fashions",
            "type":"Retail Goods"
        }
    ],
    "sg:phone":"+1 770 435 4999",
    "sg:postcode":"30303",
    "sg:province":"GA",
    "sg:tags":[
        "accessory"
    ],
    "wof:name":"Talbots",
    "wof:placetype":"venue"
},
  "geometry": {"coordinates":[-84.39070100000001,33.756302],"type":"Point"}
}