{
  "type": "Feature",
  "properties": {
    "addr:full":"440 Pleasant Hill Rd NW Lilburn GA 30047",
    "addr:housenumber":"440",
    "addr:postcode":"30047",
    "addr:street":"Pleasant Hill Rd Nw",
    "iso:country":"US",
    "sg:address":"440 Pleasant Hill Rd NW",
    "sg:city":"Lilburn",
    "sg:classifiers":[
        {
            "category":"Communications",
            "type":"Services"
        }
    ],
    "sg:phone":"+1 770 931 4551",
    "sg:postcode":"30047",
    "sg:province":"GA",
    "sg:tags":[
        "carrier",
        "radiotelephone",
        "communications-common"
    ],
    "wof:name":"P H Wireless",
    "wof:placetype":"venue"
},
  "geometry": {"coordinates":[-84.112454,33.908696],"type":"Point"}
}