{
  "type": "Feature",
  "properties": {
    "addr:full":"1553 Blanchard Blvd Columbus GA 31901",
    "addr:housenumber":"1553",
    "addr:postcode":"31901",
    "addr:street":"Blanchard Blvd",
    "iso:country":"US",
    "sg:address":"1553 Blanchard Blvd",
    "sg:city":"Columbus",
    "sg:classifiers":[
        {
            "category":"Wholesale",
            "subcategory":"Machinery & Supplies",
            "type":"Manufacturing & Wholesale Goods"
        }
    ],
    "sg:phone":"+1 706 322 6512",
    "sg:postcode":"31901",
    "sg:province":"GA",
    "sg:tags":[
        "sprinkler"
    ],
    "wof:name":"Sprinkler Contractors Inc",
    "wof:placetype":"venue"
},
  "geometry": {"coordinates":[-84.970539,32.447952],"type":"Point"}
}