{
  "type": "Feature",
  "properties": {
    "iso:country":"US",
    "sg:address":"659 E King Ave",
    "sg:city":"Kingsland",
    "sg:classifiers":[
        {
            "category":"Retail",
            "subcategory":"Laundry & Dry Cleaning",
            "type":"Services"
        }
    ],
    "sg:phone":"+1 912 729 8490",
    "sg:postcode":"31548",
    "sg:province":"GA",
    "wof:name":"Sewing Special",
    "wof:placetype":"venue"
},
  "geometry": {"coordinates":[-81.682345,30.801199],"type":"Point"}
}