{
  "type": "Feature",
  "properties": {
    "iso:country":"US",
    "sg:address":"35 Meadow Dr",
    "sg:city":"Ellaville",
    "sg:classifiers":[
        {
            "category":"Social Services",
            "subcategory":"Child Care",
            "type":"Services"
        }
    ],
    "sg:phone":"+1 229 937 5390",
    "sg:postcode":"31806",
    "sg:province":"GA",
    "sg:tags":[
        "nursery",
        "day"
    ],
    "wof:name":"Cradles To Crowns",
    "wof:placetype":"venue"
},
  "geometry": {"coordinates":[-84.302172,32.234503],"type":"Point"}
}