{
  "type": "Feature",
  "properties": {
    "iso:country":"US",
    "sg:address":"2034 Happy Valley Cir",
    "sg:city":"Newnan",
    "sg:classifiers":[
        {
            "category":"Manufacturing",
            "subcategory":"Wood Products",
            "type":"Manufacturing & Wholesale Goods"
        }
    ],
    "sg:phone":"+1 770 251 5234",
    "sg:postcode":"30263",
    "sg:province":"GA",
    "sg:tags":[
        "pallet",
        "mfg"
    ],
    "wof:name":"Palletman",
    "wof:placetype":"venue"
},
  "geometry": {"coordinates":[-84.790954,33.47925],"type":"Point"}
}