{
  "type": "Feature",
  "properties": {
    "addr:full":"715 Univeter Rd Canton GA 30115",
    "addr:housenumber":"715",
    "addr:postcode":"30115",
    "addr:street":"Univeter Rd",
    "iso:country":"US",
    "sg:address":"715 Univeter Rd",
    "sg:city":"Canton",
    "sg:classifiers":[
        {
            "category":"Home & Garden",
            "subcategory":"Building Materials",
            "type":"Retail Goods"
        }
    ],
    "sg:phone":"+1 770 345 1239",
    "sg:postcode":"30115",
    "sg:province":"GA",
    "sg:tags":[
        "mixed",
        "concrete"
    ],
    "sg:website":"www.alliedreadymix.com",
    "wof:name":"Rmc Cemex",
    "wof:placetype":"venue"
},
  "geometry": {"coordinates":[-84.500361,34.196106],"type":"Point"}
}