{
  "type": "Feature",
  "properties": {
    "iso:country":"US",
    "sg:address":"291 Plantation Centre Dr S",
    "sg:city":"Macon",
    "sg:classifiers":[
        {
            "category":"Building & Trades",
            "subcategory":"Construction",
            "type":"Services"
        }
    ],
    "sg:phone":"+1 478 477 8621",
    "sg:postcode":"31210",
    "sg:province":"GA",
    "sg:tags":[
        "house"
    ],
    "wof:name":"Sahir Construction Inc",
    "wof:placetype":"venue"
},
  "geometry": {"coordinates":[-83.761872,32.876473],"type":"Point"}
}