{
  "type": "Feature",
  "properties": {
    "iso:country":"US",
    "sg:address":"119 Washington St NE",
    "sg:city":"Gainesville",
    "sg:phone":"+1 770 535 0006",
    "sg:postcode":"30501",
    "sg:province":"GA",
    "wof:name":"New Vision Tattoo",
    "wof:placetype":"venue"
},
  "geometry": {"coordinates":[-83.826656,34.299852],"type":"Point"}
}