{
  "type": "Feature",
  "properties": {
    "iso:country":"US",
    "sg:address":"4172 Knollcrest Cir N",
    "sg:city":"Augusta",
    "sg:classifiers":[
        {
            "category":"Shopping",
            "type":"Retail Goods"
        },
        {
            "category":"Manufacturing",
            "subcategory":"Paper Products",
            "type":"Manufacturing & Wholesale Goods"
        }
    ],
    "sg:phone":"+1 706 869 1941",
    "sg:postcode":"30907",
    "sg:province":"GA",
    "sg:tags":[
        "packaging",
        "materials-wholesale",
        "material",
        "manufacturer"
    ],
    "wof:name":"Deborah Packer",
    "wof:placetype":"venue"
},
  "geometry": {"coordinates":[-82.11792,33.49971],"type":"Point"}
}