{
  "type": "Feature",
  "properties": {
    "addr:full":"815 Concept 21 Cir Austell GA 30168",
    "addr:housenumber":"815;21",
    "addr:postcode":"30168",
    "addr:street":"Concept;Cir",
    "iso:country":"US",
    "sg:address":"815 Concept 21 Cir",
    "sg:city":"Austell",
    "sg:classifiers":[
        {
            "category":"Shopping",
            "subcategory":"Computers & Home Electronics",
            "type":"Retail Goods"
        }
    ],
    "sg:phone":"+1 770 251 0449",
    "sg:postcode":"30168",
    "sg:province":"GA",
    "wof:name":"Bennett Comp Service Inc",
    "wof:placetype":"venue"
},
  "geometry": {"coordinates":[-84.562155,33.776693],"type":"Point"}
}