{
  "type": "Feature",
  "properties": {
    "iso:country":"US",
    "sg:address":"735 Piedmont Avenue NE",
    "sg:city":"Atlanta",
    "sg:classifiers":[
        {
            "category":"Health Services",
            "subcategory":"Doctor",
            "type":"Services"
        }
    ],
    "sg:phone":"+1 404 881 6910",
    "sg:postcode":"30308",
    "sg:province":"GA",
    "wof:name":"Hudson Richard A DO",
    "wof:placetype":"venue"
},
  "geometry": {"coordinates":[-84.381722,33.774501],"type":"Point"}
}