{
  "type": "Feature",
  "properties": {
    "iso:country":"US",
    "sg:address":"138 Tallokas Trl",
    "sg:city":"Moultrie",
    "sg:classifiers":[
        {
            "category":"Real Estate",
            "subcategory":"Real Estate Agent",
            "type":"Services"
        }
    ],
    "sg:phone":"+1 229 985 9344",
    "sg:postcode":"31788",
    "sg:province":"GA",
    "wof:name":"Reagin Properties LLC",
    "wof:placetype":"venue"
},
  "geometry": {"coordinates":[-83.759479,31.134593],"type":"Point"}
}