{
  "type": "Feature",
  "properties": {
    "iso:country":"US",
    "sg:address":"23 E Charlton St",
    "sg:city":"Savannah",
    "sg:classifiers":[
        {
            "category":"Professional",
            "subcategory":"Management & Consulting",
            "type":"Services"
        }
    ],
    "sg:phone":"+1 912 236 8433",
    "sg:postcode":"31401",
    "sg:province":"GA",
    "wof:name":"Delta Construction Management",
    "wof:placetype":"venue"
},
  "geometry": {"coordinates":[-81.093124,32.072913],"type":"Point"}
}