{
  "type": "Feature",
  "properties": {
    "iso:country":"US",
    "sg:address":"3375 Kensington Rd",
    "sg:city":"Decatur",
    "sg:classifiers":[
        {
            "category":"Building & Trades",
            "subcategory":"Pest Control",
            "type":"Services"
        }
    ],
    "sg:phone":"+1 706 468 8511",
    "sg:postcode":"30032",
    "sg:province":"GA",
    "sg:website":"www.bug-busters.net",
    "wof:name":"Bug Busters USA",
    "wof:placetype":"venue"
},
  "geometry": {"coordinates":[-84.252486,33.771629],"type":"Point"}
}