{
  "type": "Feature",
  "properties": {
    "addr:full":"4565 Fairway View Ct Duluth GA 30096",
    "addr:housenumber":"4565",
    "addr:postcode":"30096",
    "addr:street":"Fairway View Ct",
    "iso:country":"US",
    "sg:address":"4565 Fairway View Ct",
    "sg:city":"Duluth",
    "sg:classifiers":[
        {
            "category":"Building & Trades",
            "subcategory":"Electrical",
            "type":"Services"
        }
    ],
    "sg:phone":"+1 770 613 0166",
    "sg:postcode":"30096",
    "sg:province":"GA",
    "sg:tags":[
        "telecommunication",
        "contractor"
    ],
    "wof:name":"A T & Tcits",
    "wof:placetype":"venue"
},
  "geometry": {"coordinates":[-84.166377,33.945206],"type":"Point"}
}