{
  "type": "Feature",
  "properties": {
    "addr:full":"6305 Wilmington Way Flowery Branch GA 30542",
    "addr:housenumber":"6305",
    "addr:postcode":"30542",
    "addr:street":"Wilmington Way",
    "iso:country":"US",
    "sg:address":"6305 Wilmington Way",
    "sg:city":"Flowery Branch",
    "sg:classifiers":[
        {
            "category":"Building & Trades",
            "subcategory":"Cleaning & Sanitation",
            "type":"Services"
        }
    ],
    "sg:phone":"+1 770 965 8801",
    "sg:postcode":"30542",
    "sg:province":"GA",
    "sg:tags":[
        "maintenance"
    ],
    "wof:name":"Clean Sweep",
    "wof:placetype":"venue"
},
  "geometry": {"coordinates":[-83.932914,34.150058],"type":"Point"}
}