{
  "type": "Feature",
  "properties": {
    "iso:country":"US",
    "sg:address":"3180 Highway 166",
    "sg:city":"Douglasville",
    "sg:classifiers":[
        {
            "category":"Professional",
            "type":"Services"
        }
    ],
    "sg:phone":"+1 770 577 3001",
    "sg:postcode":"30135",
    "sg:province":"GA",
    "sg:tags":[
        "caterer"
    ],
    "wof:name":"A Taste To Remember",
    "wof:placetype":"venue"
},
  "geometry": {"coordinates":[-84.681,33.6651],"type":"Point"}
}