{
  "type": "Feature",
  "properties": {
    "addr:full":"5113 Crescent Cove Ln Mableton GA 30126",
    "addr:housenumber":"5113",
    "addr:postcode":"30126",
    "addr:street":"Crescent Cove Ln",
    "iso:country":"US",
    "sg:address":"5113 Crescent Cove Ln",
    "sg:city":"Mableton",
    "sg:classifiers":[
        {
            "category":"Home & Garden",
            "subcategory":"Garden Supply",
            "type":"Retail Goods"
        }
    ],
    "sg:phone":"+1 770 948 2996",
    "sg:postcode":"30126",
    "sg:province":"GA",
    "sg:tags":[
        "topsoil"
    ],
    "wof:name":"Joe Datin Office",
    "wof:placetype":"venue"
},
  "geometry": {"coordinates":[-84.531462,33.828646],"type":"Point"}
}