{
  "type": "Feature",
  "properties": {
    "iso:country":"US",
    "sg:address":"84 N Windsong Ct",
    "sg:city":"Cataula",
    "sg:classifiers":[
        {
            "category":"Deli",
            "type":"Food & Drink"
        },
        {
            "category":"Restaurant",
            "type":"Food & Drink"
        }
    ],
    "sg:phone":"+1 706 327 0055",
    "sg:postcode":"31804",
    "sg:province":"GA",
    "sg:tags":[
        "delicatessen"
    ],
    "wof:name":"Betancourt Deli",
    "wof:placetype":"venue"
},
  "geometry": {"coordinates":[-84.925387,32.628215],"type":"Point"}
}