{
  "type": "Feature",
  "properties": {
    "addr:full":"1466 N Decatur Rd Atlanta GA 30306",
    "addr:housenumber":"1466",
    "addr:postcode":"30306",
    "addr:street":"N Decatur Rd",
    "iso:country":"US",
    "sg:address":"1466 N Decatur Rd",
    "sg:city":"Atlanta",
    "sg:classifiers":[
        {
            "category":"Professional",
            "subcategory":"Management & Consulting",
            "type":"Services"
        }
    ],
    "sg:phone":"+1 404 371 8100",
    "sg:postcode":"30306",
    "sg:province":"GA",
    "sg:tags":[
        "marketing",
        "consultant"
    ],
    "wof:name":"Edgedweller Inc",
    "wof:placetype":"venue"
},
  "geometry": {"coordinates":[-84.33038999999999,33.788158],"type":"Point"}
}