{
  "type": "Feature",
  "properties": {
    "addr:full":"359 E Broad St Winder GA 30680",
    "addr:housenumber":"359",
    "addr:postcode":"30680",
    "addr:street":"E Broad St",
    "iso:country":"US",
    "sg:address":"359 E Broad St",
    "sg:city":"Winder",
    "sg:classifiers":[
        {
            "category":"Health Services",
            "subcategory":"Doctor",
            "type":"Services"
        }
    ],
    "sg:phone":"+1 770 867 6868",
    "sg:postcode":"30680",
    "sg:province":"GA",
    "sg:tags":[
        "dentist"
    ],
    "sg:website":"www.waorthodontics.com",
    "wof:name":"Waugh & Allen Assoc",
    "wof:placetype":"venue"
},
  "geometry": {"coordinates":[-83.69892400000001,33.997921],"type":"Point"}
}