{
  "type": "Feature",
  "properties": {
    "iso:country":"US",
    "sg:address":"2167 Ga Highway 68 S",
    "sg:city":"Tennille",
    "sg:classifiers":[
        {
            "category":"Restaurant",
            "type":"Food & Drink"
        }
    ],
    "sg:phone":"+1 478 552 8862",
    "sg:postcode":"31089",
    "sg:province":"GA",
    "sg:tags":[
        "house",
        "steak"
    ],
    "wof:name":"Dean Helton",
    "wof:placetype":"venue"
},
  "geometry": {"coordinates":[-82.815349,32.906714],"type":"Point"}
}