{
  "type": "Feature",
  "properties": {
    "addr:full":"2355 Mansell Rd Alpharetta GA 30022",
    "addr:housenumber":"2355",
    "addr:postcode":"30022",
    "addr:street":"Mansell Rd",
    "iso:country":"US",
    "sg:address":"2355 Mansell Rd",
    "sg:city":"Alpharetta",
    "sg:classifiers":[
        {
            "category":"Bars & Pubs",
            "type":"Food & Drink"
        },
        {
            "category":"Restaurant",
            "type":"Food & Drink"
        }
    ],
    "sg:phone":"+1 770 650 6400",
    "sg:postcode":"30022",
    "sg:province":"GA",
    "sg:tags":[
        "tavern",
        "new",
        "american",
        "diner"
    ],
    "sg:website":"www.thedineratnorthpoint.com",
    "wof:name":"The Diner at North Point",
    "wof:placetype":"venue"
},
  "geometry": {"coordinates":[-84.30745400000001,34.037425],"type":"Point"}
}