{
  "type": "Feature",
  "properties": {
    "addr:full":"202 S Broad St Thomasville GA 31792",
    "addr:housenumber":"202",
    "addr:postcode":"31792",
    "addr:street":"S Broad St",
    "iso:country":"US",
    "sg:address":"202 S Broad St",
    "sg:city":"Thomasville",
    "sg:classifiers":[
        {
            "category":"Retail",
            "subcategory":"Repair Shop",
            "type":"Services"
        }
    ],
    "sg:phone":"+1 229 226 4249",
    "sg:postcode":"31792",
    "sg:province":"GA",
    "sg:tags":[
        "machine",
        "cleaners",
        "sewing",
        "vacuum"
    ],
    "wof:name":"Jimmys Sewing Mch & Vac Svc",
    "wof:placetype":"venue"
},
  "geometry": {"coordinates":[-83.979321,30.836392],"type":"Point"}
}