{
  "type": "Feature",
  "properties": {
    "addr:full":"506 Hawthorne St Macon GA 31201",
    "addr:housenumber":"506",
    "addr:postcode":"31201",
    "addr:street":"Hawthorne St",
    "iso:country":"US",
    "sg:address":"506 Hawthorne St",
    "sg:city":"Macon",
    "sg:classifiers":[
        {
            "category":"Organizations",
            "subcategory":"Religious Organization",
            "type":"Services"
        }
    ],
    "sg:phone":"+1 478 742 8312",
    "sg:postcode":"31201",
    "sg:province":"GA",
    "sg:tags":[
        "church"
    ],
    "wof:name":"Fulton Baptist Church",
    "wof:placetype":"venue"
},
  "geometry": {"coordinates":[-83.634726,32.827803],"type":"Point"}
}