{
  "type": "Feature",
  "properties": {
    "addr:full":"6113 Jenkins Rd Albany GA 31705",
    "addr:housenumber":"6113",
    "addr:postcode":"31705",
    "addr:street":"Jenkins Rd",
    "iso:country":"US",
    "sg:address":"6113 Jenkins Rd",
    "sg:city":"Albany",
    "sg:classifiers":[
        {
            "category":"Recreation",
            "type":"Entertainment"
        }
    ],
    "sg:phone":"+1 229 436 9583",
    "sg:postcode":"31705",
    "sg:province":"GA",
    "wof:name":"Wire Grass Barn",
    "wof:placetype":"venue"
},
  "geometry": {"coordinates":[-83.982613,31.46356],"type":"Point"}
}