{
  "type": "Feature",
  "properties": {
    "iso:country":"US",
    "sg:address":"851 Lakeside Dr",
    "sg:city":"Griffin",
    "sg:classifiers":[
        {
            "category":"Professional",
            "type":"Services"
        }
    ],
    "sg:phone":"+1 770 412 6887",
    "sg:postcode":"30224",
    "sg:province":"GA",
    "wof:name":"James F Coker",
    "wof:placetype":"venue"
},
  "geometry": {"coordinates":[-84.316705,33.189731],"type":"Point"}
}