{
  "type": "Feature",
  "properties": {
    "iso:country":"US",
    "sg:address":"990 Sigman Rd NW",
    "sg:city":"Conyers",
    "sg:classifiers":[
        {
            "category":"Restaurant",
            "type":"Food & Drink"
        }
    ],
    "sg:phone":"+1 770 922 5525",
    "sg:postcode":"30012",
    "sg:province":"GA",
    "sg:tags":[
        "eating"
    ],
    "wof:name":"Taco Loco",
    "wof:placetype":"venue"
},
  "geometry": {"coordinates":[-84.021659,33.689111],"type":"Point"}
}