{
  "type": "Feature",
  "properties": {
    "addr:full":"331 Memorial Rd Hartwell GA 30643",
    "addr:housenumber":"331",
    "addr:postcode":"30643",
    "addr:street":"Memorial Rd",
    "iso:country":"US",
    "sg:address":"331 Memorial Rd",
    "sg:city":"Hartwell",
    "sg:classifiers":[
        {
            "category":"Social Services",
            "type":"Services"
        }
    ],
    "sg:phone":"+1 706 856 2663",
    "sg:postcode":"30643",
    "sg:province":"GA",
    "sg:tags":[
        "probation"
    ],
    "wof:name":"Hartwell Parole Office",
    "wof:placetype":"venue"
},
  "geometry": {"coordinates":[-82.973074,34.34381],"type":"Point"}
}