{
  "type": "Feature",
  "properties": {
    "addr:full":"1589 Martha Jean Pl Tucker GA 30084",
    "addr:housenumber":"1589",
    "addr:postcode":"30084",
    "addr:street":"Martha Jean Pl",
    "iso:country":"US",
    "sg:address":"1589 Martha Jean Pl",
    "sg:city":"Tucker",
    "sg:classifiers":[
        {
            "category":"Building & Trades",
            "subcategory":"Construction",
            "type":"Services"
        }
    ],
    "sg:phone":"+1 770 939 6906",
    "sg:postcode":"30084",
    "sg:province":"GA",
    "sg:tags":[
        "contractor"
    ],
    "wof:name":"Ayala Massonory",
    "wof:placetype":"venue"
},
  "geometry": {"coordinates":[-84.22070100000001,33.829519],"type":"Point"}
}