{
  "type": "Feature",
  "properties": {
    "iso:country":"US",
    "sg:address":"4192 Newton Dr NE",
    "sg:city":"Covington",
    "sg:classifiers":[
        {
            "category":"Wholesale",
            "subcategory":"Stationery",
            "type":"Manufacturing & Wholesale Goods"
        }
    ],
    "sg:phone":"+1 770 787 1031",
    "sg:postcode":"30014",
    "sg:province":"GA",
    "sg:tags":[
        "legal",
        "form"
    ],
    "wof:name":"Clyde Castleberry Co",
    "wof:placetype":"venue"
},
  "geometry": {"coordinates":[-83.84693799999999,33.599645],"type":"Point"}
}