{
  "type": "Feature",
  "properties": {
    "iso:country":"US",
    "sg:address":"108 Bridget Dr",
    "sg:city":"Hampton",
    "sg:classifiers":[
        {
            "category":"Shopping",
            "subcategory":"Hobbies, Toys, & Games",
            "type":"Retail Goods"
        }
    ],
    "sg:phone":"+1 770 946 5098",
    "sg:postcode":"30228",
    "sg:province":"GA",
    "wof:name":"Wee-Be-Toys Inc",
    "wof:placetype":"venue"
},
  "geometry": {"coordinates":[-84.224198,33.405251],"type":"Point"}
}