{
  "type": "Feature",
  "properties": {
    "addr:full":"1015 Edgewood Avenue NE Atlanta GA 30307",
    "addr:housenumber":"1015",
    "addr:postcode":"30307",
    "addr:street":"Edgewood Avenue Ne",
    "iso:country":"US",
    "sg:address":"1015 Edgewood Avenue NE",
    "sg:city":"Atlanta",
    "sg:classifiers":[
        {
            "category":"Social Services",
            "subcategory":"Child Care",
            "type":"Services"
        },
        {
            "category":"Education",
            "subcategory":"Special Training",
            "type":"Public Place"
        },
        {
            "category":"Education",
            "subcategory":"Preschool",
            "type":"Public Place"
        },
        {
            "category":"Education",
            "subcategory":"School",
            "type":"Public Place"
        }
    ],
    "sg:phone":"+1 404 688 9550",
    "sg:postcode":"30307",
    "sg:province":"GA",
    "sg:tags":[
        "kindergarten",
        "educational",
        "k-",
        "high",
        "middle",
        "nursery",
        "private",
        "elementary",
        "day"
    ],
    "sg:website":"http://www.theatlantaschool.com",
    "wof:name":"The Atlanta School",
    "wof:placetype":"venue"
},
  "geometry": {"coordinates":[-84.355102,33.756847],"type":"Point"}
}