{
  "type": "Feature",
  "properties": {
    "addr:full":"2644 Mountain Industrial Blvd Tucker GA 30084",
    "addr:housenumber":"2644",
    "addr:postcode":"30084",
    "addr:street":"Mountain Industrial Blvd",
    "iso:country":"US",
    "sg:address":"2644 Mountain Industrial Blvd",
    "sg:city":"Tucker",
    "sg:classifiers":[
        {
            "category":"Food & Beverages",
            "subcategory":"Groceries & Convenience Stores",
            "type":"Retail Goods"
        },
        {
            "category":"Real Estate",
            "subcategory":"Real Estate Agent",
            "type":"Services"
        }
    ],
    "sg:phone":"+1 770 492 1114",
    "sg:postcode":"30084",
    "sg:province":"GA",
    "sg:tags":[
        "appraiser"
    ],
    "wof:name":"Market Watch LLC",
    "wof:placetype":"venue"
},
  "geometry": {"coordinates":[-84.196135,33.857125],"type":"Point"}
}