{
  "type": "Feature",
  "properties": {
    "iso:country":"US",
    "sg:address":"1087 Westshire Pl NW",
    "sg:city":"Atlanta",
    "sg:classifiers":[
        {
            "category":"Professional",
            "subcategory":"Engineering",
            "type":"Services"
        }
    ],
    "sg:phone":"+1 404 872 6020",
    "sg:postcode":"30318",
    "sg:province":"GA",
    "wof:name":"Mhm Consulting Engineers",
    "wof:placetype":"venue"
},
  "geometry": {"coordinates":[-84.39657200000001,33.784172],"type":"Point"}
}