{
  "type": "Feature",
  "properties": {
    "addr:full":"20 W Stephens St Winder GA 30680",
    "addr:housenumber":"20",
    "addr:postcode":"30680",
    "addr:street":"W Stephens St",
    "iso:country":"US",
    "sg:address":"20 W Stephens St",
    "sg:city":"Winder",
    "sg:classifiers":[
        {
            "category":"Professional",
            "subcategory":"Lawyer & Legal Services",
            "type":"Services"
        }
    ],
    "sg:phone":"+1 770 867 8618",
    "sg:postcode":"30680",
    "sg:province":"GA",
    "sg:tags":[
        "attorney"
    ],
    "wof:name":"Russell & Mingledorff",
    "wof:placetype":"venue"
},
  "geometry": {"coordinates":[-83.71872,33.994966],"type":"Point"}
}