{
  "type": "Feature",
  "properties": {
    "addr:full":"2298 Maple Rd Rome GA 30161",
    "addr:housenumber":"2298",
    "addr:postcode":"ga 30161",
    "addr:street":"Maple Rd",
    "iso:country":"US",
    "sg:address":"2298 Maple Rd",
    "sg:city":"Rome",
    "sg:classifiers":[
        {
            "category":"Personal",
            "subcategory":"Beauty Salon",
            "type":"Services"
        }
    ],
    "sg:phone":"+1 706 291 2889",
    "sg:postcode":"30161",
    "sg:province":"GA",
    "sg:tags":[
        "shop",
        "barber"
    ],
    "wof:name":"Ladies Gents Buty Barbr Salon",
    "wof:placetype":"venue"
},
  "geometry": {"coordinates":[-85.167329,34.222987],"type":"Point"}
}