{
  "type": "Feature",
  "properties": {
    "addr:full":"3024 Bob Cox Rd Marietta GA 30064",
    "addr:housenumber":"3024",
    "addr:postcode":"30064",
    "addr:street":"Bob Cox Rd",
    "iso:country":"US",
    "sg:address":"3024 Bob Cox Rd",
    "sg:city":"Marietta",
    "sg:classifiers":[
        {
            "category":"Building & Trades",
            "subcategory":"Construction",
            "type":"Services"
        }
    ],
    "sg:phone":"+1 770 427 3470",
    "sg:postcode":"30064",
    "sg:province":"GA",
    "sg:tags":[
        "contractor"
    ],
    "wof:name":"G & G Installations Inc",
    "wof:placetype":"venue"
},
  "geometry": {"coordinates":[-84.63685700000001,33.960728],"type":"Point"}
}