{
  "type": "Feature",
  "properties": {
    "iso:country":"US",
    "sg:address":"615 Northside Dr",
    "sg:city":"Griffin",
    "sg:classifiers":[
        {
            "category":"Professional",
            "type":"Services"
        }
    ],
    "sg:phone":"+1 770 233 3338",
    "sg:postcode":"30223",
    "sg:province":"GA",
    "wof:name":"Tamikyos Brading",
    "wof:placetype":"venue"
},
  "geometry": {"coordinates":[-84.265399,33.269046],"type":"Point"}
}