{
  "type": "Feature",
  "properties": {
    "iso:country":"US",
    "sg:address":"2436 Elmwood Cir SE",
    "sg:city":"Smyrna",
    "sg:classifiers":[
        {
            "category":"Home & Garden",
            "subcategory":"Building Materials",
            "type":"Retail Goods"
        },
        {
            "category":"Building & Trades",
            "subcategory":"Construction",
            "type":"Services"
        }
    ],
    "sg:phone":"+1 770 953 9353",
    "sg:postcode":"30082",
    "sg:province":"GA",
    "sg:tags":[
        "concrete",
        "staining",
        "contractor"
    ],
    "sg:website":"http://www.atlantastampedconcrete.com",
    "wof:name":"Atlanta Stamped Concrete Inc",
    "wof:placetype":"venue"
},
  "geometry": {"coordinates":[-84.485564,33.819848],"type":"Point"}
}