{
  "type": "Feature",
  "properties": {
    "addr:full":"3511 Hidden Acres Dr Atlanta GA 30340",
    "addr:housenumber":"3511",
    "addr:postcode":"30340",
    "addr:street":"Hidden Acres Dr",
    "iso:country":"US",
    "sg:address":"3511 Hidden Acres Dr",
    "sg:city":"Atlanta",
    "sg:classifiers":[
        {
            "category":"Professional",
            "type":"Services"
        }
    ],
    "sg:phone":"+1 770 444 9144",
    "sg:postcode":"30340",
    "sg:province":"GA",
    "sg:tags":[
        "establishment"
    ],
    "wof:name":"R Trix Inc",
    "wof:placetype":"venue"
},
  "geometry": {"coordinates":[-84.23690999999999,33.888754],"type":"Point"}
}