{
  "type": "Feature",
  "properties": {
    "iso:country":"US",
    "sg:address":"805 W Lincoln Ave",
    "sg:city":"Albany",
    "sg:classifiers":[
        {
            "category":"Organizations",
            "subcategory":"Community Association",
            "type":"Services"
        }
    ],
    "sg:phone":"+1 229 888 0919",
    "sg:postcode":"31701",
    "sg:province":"GA",
    "sg:tags":[
        "club"
    ],
    "wof:name":"Club 106",
    "wof:placetype":"venue"
},
  "geometry": {"coordinates":[-84.170551,31.569242],"type":"Point"}
}