{
  "type": "Feature",
  "properties": {
    "iso:country":"US",
    "sg:address":"109 Larson Rd",
    "sg:city":"Leslie",
    "sg:classifiers":[
        {
            "category":"Farming",
            "subcategory":"Farm",
            "type":"Manufacturing & Wholesale Goods"
        }
    ],
    "sg:phone":"+1 229 874 6502",
    "sg:postcode":"31743",
    "sg:province":"GA",
    "wof:name":"Lone Oak Plantation Inc",
    "wof:placetype":"venue"
},
  "geometry": {"coordinates":[-83.97678999999999,31.905512],"type":"Point"}
}