{
  "type": "Feature",
  "properties": {
    "addr:full":"1130 N Point Cir Alpharetta GA 30022",
    "addr:housenumber":"1130",
    "addr:postcode":"30022",
    "addr:street":"N Point Cir",
    "iso:country":"US",
    "sg:address":"1130 N Point Cir",
    "sg:city":"Alpharetta",
    "sg:classifiers":[
        {
            "category":"Bakery",
            "type":"Food & Drink"
        }
    ],
    "sg:menulink":"http://www.allmenus.com/ga/roswell-alpharetta/219857-auntie-annes-pretzels/menu/",
    "sg:phone":"+1 770 667 1260",
    "sg:postcode":"30022",
    "sg:province":"GA",
    "sg:tags":[
        "american",
        "pastry"
    ],
    "wof:name":"Auntie Anne's Pretzels",
    "wof:placetype":"venue"
},
  "geometry": {"coordinates":[-84.291394,34.050516],"type":"Point"}
}