{
  "type": "Feature",
  "properties": {
    "addr:full":"216 W Fambrough St Monroe GA 30655",
    "addr:housenumber":"216",
    "addr:postcode":"30655",
    "addr:street":"W Fambrough St",
    "iso:country":"US",
    "sg:address":"216 W Fambrough St",
    "sg:city":"Monroe",
    "sg:classifiers":[
        {
            "category":"Real Estate",
            "subcategory":"Real Estate Operator",
            "type":"Services"
        }
    ],
    "sg:phone":"+1 770 207 5999",
    "sg:postcode":"30655",
    "sg:province":"GA",
    "sg:tags":[
        "building",
        "apartment"
    ],
    "wof:name":"Las Casitas",
    "wof:placetype":"venue"
},
  "geometry": {"coordinates":[-83.70779400000001,33.780016],"type":"Point"}
}