{
  "type": "Feature",
  "properties": {
    "iso:country":"US",
    "sg:address":"180 N Macon St",
    "sg:city":"Jesup",
    "sg:classifiers":[
        {
            "category":"Communications",
            "subcategory":"Film & Video Production",
            "type":"Services"
        }
    ],
    "sg:phone":"+1 912 427 0444",
    "sg:postcode":"31545",
    "sg:province":"GA",
    "sg:tags":[
        "recording",
        "service-sound"
    ],
    "wof:name":"Unified Productions Recording Studios",
    "wof:placetype":"venue"
},
  "geometry": {"coordinates":[-81.883634,31.606767],"type":"Point"}
}