{
  "type": "Feature",
  "properties": {
    "addr:full":"6380 Mableton Pkwy SE Mableton GA 30126",
    "addr:housenumber":"6380",
    "addr:postcode":"30126",
    "addr:street":"Mableton Pkwy Se",
    "iso:country":"US",
    "sg:address":"6380 Mableton Pkwy SE",
    "sg:city":"Mableton",
    "sg:classifiers":[
        {
            "category":"Building & Trades",
            "subcategory":"Construction",
            "type":"Services"
        }
    ],
    "sg:phone":"+1 770 377 0332",
    "sg:postcode":"30126",
    "sg:province":"GA",
    "sg:tags":[
        "wallpaper"
    ],
    "wof:name":"J L Wallpaper",
    "wof:placetype":"venue"
},
  "geometry": {"coordinates":[-84.566669,33.80052],"type":"Point"}
}