{
  "type": "Feature",
  "properties": {
    "iso:country":"US",
    "sg:address":"1090 Powers Ferry Rd SE",
    "sg:city":"Marietta",
    "sg:classifiers":[
        {
            "category":"Real Estate",
            "subcategory":"Real Estate Operator",
            "type":"Services"
        }
    ],
    "sg:phone":"+1 770 952 9754",
    "sg:postcode":"30067",
    "sg:province":"GA",
    "sg:tags":[
        "apartment"
    ],
    "wof:name":"Winterset Apartments",
    "wof:placetype":"venue"
},
  "geometry": {"coordinates":[-84.469803,33.925098],"type":"Point"}
}