{
  "type": "Feature",
  "properties": {
    "iso:country":"US",
    "sg:address":"824 Gi Maddox Pkwy",
    "sg:city":"Chatsworth",
    "sg:classifiers":[
        {
            "category":"Health Services",
            "subcategory":"Doctor",
            "type":"Services"
        }
    ],
    "sg:phone":"+1 706 695 0561",
    "sg:postcode":"30705",
    "sg:province":"GA",
    "sg:tags":[
        "physician",
        "family",
        "practice",
        "surgeons",
        "medicine"
    ],
    "wof:name":"Anthony Cabrera Md",
    "wof:placetype":"venue"
},
  "geometry": {"coordinates":[-84.788084,34.78278],"type":"Point"}
}