{
  "type": "Feature",
  "properties": {
    "addr:full":"2305 Sherbrooke Dr NE Atlanta GA 30345",
    "addr:housenumber":"2305",
    "addr:postcode":"30345",
    "addr:street":"Sherbrooke Dr Ne",
    "iso:country":"US",
    "sg:address":"2305 Sherbrooke Dr NE",
    "sg:city":"Atlanta",
    "sg:classifiers":[
        {
            "category":"Manufacturing",
            "subcategory":"Printing",
            "type":"Manufacturing & Wholesale Goods"
        },
        {
            "category":"Professional",
            "subcategory":"Advertising",
            "type":"Services"
        },
        {
            "category":"Wholesale",
            "subcategory":"Books, Periodicals, & Newspapers",
            "type":"Manufacturing & Wholesale Goods"
        }
    ],
    "sg:phone":"+1 404 633 1779",
    "sg:postcode":"30345",
    "sg:province":"GA",
    "sg:tags":[
        "publisher",
        "publishers-directory",
        "book",
        "directory",
        "guide"
    ],
    "wof:name":"Oz Publishing Inc",
    "wof:placetype":"venue"
},
  "geometry": {"coordinates":[-84.286636,33.85955],"type":"Point"}
}