{
  "type": "Feature",
  "properties": {
    "iso:country":"US",
    "sg:address":"1210 Cedar St",
    "sg:city":"Carrollton",
    "sg:classifiers":[
        {
            "category":"Professional",
            "subcategory":"Detective & Security Services",
            "type":"Services"
        }
    ],
    "sg:phone":"+1 770 838 0055",
    "sg:postcode":"30117",
    "sg:province":"GA",
    "sg:tags":[
        "car"
    ],
    "wof:name":"Sizemore Inc",
    "wof:placetype":"venue"
},
  "geometry": {"coordinates":[-85.051675,33.583203],"type":"Point"}
}