{
  "type": "Feature",
  "properties": {
    "iso:country":"US",
    "sg:address":"1205 Hightower Rd",
    "sg:city":"Macon",
    "sg:classifiers":[
        {
            "category":"Autos & Motor Vehicles",
            "subcategory":"Recreational Vehicle Sales",
            "type":"Retail Goods"
        },
        {
            "category":"Retail",
            "subcategory":"Auto Repair",
            "type":"Services"
        }
    ],
    "sg:phone":"+1 478 781 9211",
    "sg:postcode":"31206",
    "sg:province":"GA",
    "sg:tags":[
        "automotive",
        "cap",
        "shell",
        "truck",
        "canopy"
    ],
    "wof:name":"Wayne Truck Equipment Co",
    "wof:placetype":"venue"
},
  "geometry": {"coordinates":[-83.662251,32.811324],"type":"Point"}
}