{
  "type": "Feature",
  "properties": {
    "addr:full":"86 Pryor St SW Ste 300 Atlanta GA 30303",
    "addr:housenumber":"86",
    "addr:postcode":"30303",
    "addr:street":"Pryor St Sw Ste 300",
    "iso:country":"US",
    "sg:address":"86 Pryor St SW Ste 300",
    "sg:city":"Atlanta",
    "sg:classifiers":[
        {
            "category":"Professional",
            "subcategory":"Management & Consulting",
            "type":"Services"
        }
    ],
    "sg:phone":"+1 404 880 4100",
    "sg:postcode":"30303",
    "sg:province":"GA",
    "sg:tags":[
        "consultant"
    ],
    "sg:website":"http://www.atlantada.com",
    "wof:name":"A D A",
    "wof:placetype":"venue"
},
  "geometry": {"coordinates":[-84.39035800000001,33.752121],"type":"Point"}
}