{
  "type": "Feature",
  "properties": {
    "iso:country":"US",
    "sg:address":"95 Potter House Rd",
    "sg:city":"Jefferson",
    "sg:classifiers":[
        {
            "category":"Freight",
            "type":"Transportation"
        }
    ],
    "sg:phone":"+1 706 546 7448",
    "sg:postcode":"30549",
    "sg:province":"GA",
    "sg:tags":[
        "general"
    ],
    "wof:name":"B & L Mini Storage",
    "wof:placetype":"venue"
},
  "geometry": {"coordinates":[-83.51021299999999,34.064818],"type":"Point"}
}