{
  "type": "Feature",
  "properties": {
    "addr:full":"5155 Cowan Rd Acworth GA 30101",
    "addr:housenumber":"5155",
    "addr:postcode":"30101",
    "addr:street":"Cowan Rd",
    "iso:country":"US",
    "sg:address":"5155 Cowan Rd",
    "sg:city":"Acworth",
    "sg:classifiers":[
        {
            "category":"Travel",
            "subcategory":"Hotels & Motels",
            "type":"Entertainment"
        }
    ],
    "sg:phone":"+1 770 974 0116",
    "sg:postcode":"30101",
    "sg:province":"GA",
    "wof:name":"Best Western Acworth Inn",
    "wof:placetype":"venue"
},
  "geometry": {"coordinates":[-84.65351699999999,34.076895],"type":"Point"}
}