{
  "type": "Feature",
  "properties": {
    "addr:full":"1499 Kennedy Rd Ste C Tifton GA 31794",
    "addr:housenumber":"1499",
    "addr:postcode":"31794",
    "addr:street":"Kennedy Rd Ste C",
    "iso:country":"US",
    "sg:address":"1499 Kennedy Rd Ste C",
    "sg:city":"Tifton",
    "sg:classifiers":[
        {
            "category":"Health Services",
            "subcategory":"Dentist",
            "type":"Services"
        }
    ],
    "sg:phone":"+1 229 386 1336",
    "sg:postcode":"31794",
    "sg:province":"GA",
    "sg:tags":[
        "dentists-orthodontists"
    ],
    "wof:name":"Fender Goggans",
    "wof:placetype":"venue"
},
  "geometry": {"coordinates":[-83.491501,31.468719],"type":"Point"}
}