{
  "type": "Feature",
  "properties": {
    "addr:full":"3723 Clairmont Rd Atlanta GA 30341",
    "addr:housenumber":"3723",
    "addr:postcode":"30341",
    "addr:street":"Clairmont Rd",
    "iso:country":"US",
    "sg:address":"3723 Clairmont Rd",
    "sg:city":"Atlanta",
    "sg:classifiers":[
        {
            "category":"Building & Trades",
            "subcategory":"Construction",
            "type":"Services"
        }
    ],
    "sg:phone":"+1 770 378 4033",
    "sg:postcode":"30341",
    "sg:province":"GA",
    "sg:tags":[
        "roofing",
        "siding",
        "waterproofing",
        "contractor"
    ],
    "wof:name":"Church Roofing Service",
    "wof:placetype":"venue"
},
  "geometry": {"coordinates":[-84.30948100000001,33.868877],"type":"Point"}
}