{
  "type": "Feature",
  "properties": {
    "addr:full":"629 Greison Trl Newnan GA 30263",
    "addr:housenumber":"629",
    "addr:postcode":"30263",
    "addr:street":"Greison Trl",
    "iso:country":"US",
    "sg:address":"629 Greison Trl",
    "sg:city":"Newnan",
    "sg:classifiers":[
        {
            "category":"Autos & Motor Vehicles",
            "subcategory":"Automobile Sales",
            "type":"Retail Goods"
        }
    ],
    "sg:phone":"+1 770 252 8480",
    "sg:postcode":"30263",
    "sg:province":"GA",
    "sg:tags":[
        "car",
        "dealer"
    ],
    "wof:name":"Auto Link",
    "wof:placetype":"venue"
},
  "geometry": {"coordinates":[-84.782298,33.381977],"type":"Point"}
}