{
  "type": "Feature",
  "properties": {
    "addr:full":"277 Pat Mell Rd SE Marietta GA 30060",
    "addr:housenumber":"277",
    "addr:postcode":"30060",
    "addr:street":"Pat Mell Rd Se",
    "iso:country":"US",
    "sg:address":"277 Pat Mell Rd SE",
    "sg:city":"Marietta",
    "sg:classifiers":[
        {
            "category":"Building & Trades",
            "subcategory":"Construction",
            "type":"Services"
        }
    ],
    "sg:phone":"+1 770 333 1647",
    "sg:postcode":"30060",
    "sg:province":"GA",
    "sg:tags":[
        "consul",
        "defect",
        "exterior"
    ],
    "wof:name":"Bbci",
    "wof:placetype":"venue"
},
  "geometry": {"coordinates":[-84.546458,33.90213],"type":"Point"}
}