{
  "type": "Feature",
  "properties": {
    "iso:country":"US",
    "sg:address":"115 Burns Dr",
    "sg:city":"Warner Robins",
    "sg:classifiers":[
        {
            "category":"Professional",
            "subcategory":"Business Services",
            "type":"Services"
        }
    ],
    "sg:phone":"+1 478 328 9860",
    "sg:postcode":"31088",
    "sg:province":"GA",
    "sg:tags":[
        "interior",
        "consultant",
        "design",
        "decorator"
    ],
    "wof:name":"Design Impressions",
    "wof:placetype":"venue"
},
  "geometry": {"coordinates":[-83.644367,32.593955],"type":"Point"}
}