{
  "type": "Feature",
  "properties": {
    "iso:country":"US",
    "sg:address":"5905 Suwanee Dam Rd",
    "sg:city":"Buford",
    "sg:classifiers":[
        {
            "category":"Retail",
            "subcategory":"Laundry & Dry Cleaning",
            "type":"Services"
        }
    ],
    "sg:phone":"+1 770 614 2992",
    "sg:postcode":"30518",
    "sg:province":"GA",
    "sg:tags":[
        "garment",
        "agent"
    ],
    "wof:name":"Majik Touch Cleaners",
    "wof:placetype":"venue"
},
  "geometry": {"coordinates":[-84.076477,34.119473],"type":"Point"}
}