{
  "type": "Feature",
  "properties": {
    "addr:full":"5920 Ogeechee Rd Savannah GA 31419",
    "addr:housenumber":"5920",
    "addr:postcode":"31419",
    "addr:street":"Ogeechee Rd",
    "iso:country":"US",
    "sg:address":"5920 Ogeechee Rd",
    "sg:city":"Savannah",
    "sg:classifiers":[
        {
            "category":"Food & Beverages",
            "subcategory":"Groceries & Convenience Stores",
            "type":"Retail Goods"
        }
    ],
    "sg:phone":"+1 912 925 5155",
    "sg:postcode":"31419",
    "sg:province":"GA",
    "wof:name":"Circle K Store",
    "wof:placetype":"venue"
},
  "geometry": {"coordinates":[-81.251006,31.998659],"type":"Point"}
}