{
  "type": "Feature",
  "properties": {
    "iso:country":"US",
    "sg:address":"1380 Atlanta Rd SE",
    "sg:city":"Smyrna",
    "sg:classifiers":[
        {
            "category":"Building & Trades",
            "subcategory":"Locksmith",
            "type":"Services"
        }
    ],
    "sg:phone":"+1 404 982 1910",
    "sg:postcode":"30082",
    "sg:province":"GA",
    "sg:tags":[
        "key"
    ],
    "wof:name":"A A Falcon Locksmith",
    "wof:placetype":"venue"
},
  "geometry": {"coordinates":[-84.54180700000001,33.919122],"type":"Point"}
}