{
  "type": "Feature",
  "properties": {
    "addr:full":"548 Blackburn Dr Martinez GA 30907",
    "addr:housenumber":"548",
    "addr:postcode":"30907",
    "addr:street":"Blackburn Dr Martinez",
    "iso:country":"US",
    "sg:address":"548 Blackburn Dr",
    "sg:city":"Martinez",
    "sg:classifiers":[
        {
            "category":"Personal",
            "type":"Services"
        }
    ],
    "sg:phone":"+1 706 364 6450",
    "sg:postcode":"30907",
    "sg:province":"GA",
    "sg:tags":[
        "therapist",
        "massage"
    ],
    "wof:name":"Garden City Massage",
    "wof:placetype":"venue"
},
  "geometry": {"coordinates":[-82.079061,33.533955],"type":"Point"}
}