{
  "type": "Feature",
  "properties": {
    "addr:full":"1491 Howell Mill Rd NW Atlanta GA 30318",
    "addr:housenumber":"1491",
    "addr:postcode":"30318",
    "addr:street":"Howell Mill Rd Nw",
    "iso:country":"US",
    "sg:address":"1491 Howell Mill Rd NW",
    "sg:city":"Atlanta",
    "sg:classifiers":[
        {
            "category":"Autos & Motor Vehicles",
            "subcategory":"Auto Supplies",
            "type":"Retail Goods"
        },
        {
            "category":"Retail",
            "subcategory":"Auto Repair",
            "type":"Services"
        }
    ],
    "sg:phone":"+1 404 351 2727",
    "sg:postcode":"30318",
    "sg:province":"GA",
    "sg:tags":[
        "automobile",
        "part",
        "accessory"
    ],
    "wof:name":"S & J Automotive Parts",
    "wof:placetype":"venue"
},
  "geometry": {"coordinates":[-84.415457,33.79534],"type":"Point"}
}