{
  "type": "Feature",
  "properties": {
    "iso:country":"US",
    "sg:address":"490 Herring Rd",
    "sg:city":"Grayson",
    "sg:classifiers":[
        {
            "category":"Freight",
            "type":"Transportation"
        }
    ],
    "sg:phone":"+1 770 339 3964",
    "sg:postcode":"30017",
    "sg:province":"GA",
    "sg:tags":[
        "operator",
        "local",
        "trucking"
    ],
    "wof:name":"Powell W T Trucking Inc",
    "wof:placetype":"venue"
},
  "geometry": {"coordinates":[-83.93122,33.893141],"type":"Point"}
}