{
  "type": "Feature",
  "properties": {
    "addr:full":"4932 Buford Hwy Atlanta GA 30341",
    "addr:housenumber":"4932",
    "addr:postcode":"30341",
    "addr:street":"Buford Hwy",
    "iso:country":"US",
    "sg:address":"4932 Buford Hwy",
    "sg:city":"Atlanta",
    "sg:classifiers":[
        {
            "category":"Health Services",
            "subcategory":"Health Practitioner",
            "type":"Services"
        }
    ],
    "sg:phone":"+1 770 452 8783",
    "sg:postcode":"30341",
    "sg:province":"GA",
    "sg:tags":[
        "acupuncture"
    ],
    "wof:name":"Liu Dr Henry Z",
    "wof:placetype":"venue"
},
  "geometry": {"coordinates":[-84.287903,33.886398],"type":"Point"}
}