{
  "type": "Feature",
  "properties": {
    "addr:full":"1 Copenhill Ave NE Atlanta GA 30307",
    "addr:housenumber":"1",
    "addr:postcode":"30307",
    "addr:street":"Copenhill Ave Ne",
    "iso:country":"US",
    "sg:address":"1 Copenhill Ave NE",
    "sg:city":"Atlanta",
    "sg:classifiers":[
        {
            "category":"Education",
            "subcategory":"Library",
            "type":"Public Place"
        }
    ],
    "sg:phone":"+1 404 865 7100",
    "sg:postcode":"30307",
    "sg:province":"GA",
    "wof:name":"Jimmy Carter Library",
    "wof:placetype":"venue"
},
  "geometry": {"coordinates":[-84.35730700000001,33.76334],"type":"Point"}
}