{
  "type": "Feature",
  "properties": {
    "addr:full":"6000 N Point Cir Alpharetta GA 30022",
    "addr:housenumber":"6000",
    "addr:postcode":"30022",
    "addr:street":"N Point Cir",
    "iso:country":"US",
    "sg:address":"6000 N Point Cir",
    "sg:city":"Alpharetta",
    "sg:classifiers":[
        {
            "category":"Shopping",
            "subcategory":"Clothing, Apparel, & Fashions",
            "type":"Retail Goods"
        },
        {
            "category":"Home & Garden",
            "subcategory":"Household Appliances",
            "type":"Retail Goods"
        },
        {
            "category":"Autos & Motor Vehicles",
            "subcategory":"Auto Supplies",
            "type":"Retail Goods"
        },
        {
            "category":"Shopping",
            "subcategory":"Department Store",
            "type":"Retail Goods"
        }
    ],
    "sg:phone":"+1 770 667 6774",
    "sg:postcode":"30022",
    "sg:province":"GA",
    "sg:tags":[
        "major",
        "clothing",
        "tire"
    ],
    "sg:website":"http://www.sears.com",
    "wof:name":"Sears",
    "wof:placetype":"venue"
},
  "geometry": {"coordinates":[-84.294601,34.046101],"type":"Point"}
}