{
  "type": "Feature",
  "properties": {
    "iso:country":"US",
    "sg:address":"189 Gloster Rd SW",
    "sg:city":"Lawrenceville",
    "sg:classifiers":[
        {
            "category":"Manufacturing",
            "subcategory":"Glass & Minerals",
            "type":"Manufacturing & Wholesale Goods"
        }
    ],
    "sg:phone":"+1 770 931 0738",
    "sg:postcode":"30044",
    "sg:province":"GA",
    "sg:tags":[
        "mfg",
        "cut",
        "contractor"
    ],
    "wof:name":"Ticos Stone",
    "wof:placetype":"venue"
},
  "geometry": {"coordinates":[-84.065439,33.90981],"type":"Point"}
}