{
  "type": "Feature",
  "properties": {
    "addr:full":"1307 Staff Row SW Atlanta GA 30310",
    "addr:housenumber":"1307",
    "addr:postcode":"30310",
    "addr:street":"Staff Row Sw",
    "iso:country":"US",
    "sg:address":"1307 Staff Row SW",
    "sg:city":"Atlanta",
    "sg:classifiers":[
        {
            "category":"Government",
            "subcategory":"Office",
            "type":"Public Place"
        }
    ],
    "sg:phone":"+1 404 753 6381",
    "sg:postcode":"30310",
    "sg:province":"GA",
    "sg:tags":[
        "national",
        "security"
    ],
    "wof:name":"Robert I Minor Col",
    "wof:placetype":"venue"
},
  "geometry": {"coordinates":[-84.429857,33.713312],"type":"Point"}
}