{
  "type": "Feature",
  "properties": {
    "addr:full":"2225 Cape Courage Way Suwanee GA 30024",
    "addr:housenumber":"2225",
    "addr:postcode":"30024",
    "addr:street":"Cape Courage Way",
    "iso:country":"US",
    "sg:address":"2225 Cape Courage Way",
    "sg:city":"Suwanee",
    "sg:classifiers":[
        {
            "category":"Professional",
            "subcategory":"Business Services",
            "type":"Services"
        }
    ],
    "sg:phone":"+1 770 338 5690",
    "sg:postcode":"30024",
    "sg:province":"GA",
    "wof:name":"Kelly Whittington Agency LLC",
    "wof:placetype":"venue"
},
  "geometry": {"coordinates":[-84.02490299999999,34.013788],"type":"Point"}
}