{
  "type": "Feature",
  "properties": {
    "addr:full":"4239 Buttermilk Rd Sylvania GA 30467",
    "addr:housenumber":"4239",
    "addr:postcode":"30467",
    "addr:street":"Buttermilk Rd",
    "iso:country":"US",
    "sg:address":"4239 Buttermilk Rd",
    "sg:city":"Sylvania",
    "sg:classifiers":[
        {
            "category":"Professional",
            "subcategory":"Business Services",
            "type":"Services"
        }
    ],
    "sg:phone":"+1 912 966 9111",
    "sg:postcode":"30467",
    "sg:province":"GA",
    "wof:name":"Post Digital Document Storage",
    "wof:placetype":"venue"
},
  "geometry": {"coordinates":[-81.714343,32.821866],"type":"Point"}
}