{
  "type": "Feature",
  "properties": {
    "addr:full":"1048 Industrial Ct NW Suwanee GA 30024",
    "addr:housenumber":"1048",
    "addr:postcode":"30024",
    "addr:street":"Industrial Ct Nw",
    "iso:country":"US",
    "sg:address":"1048 Industrial Ct NW",
    "sg:city":"Suwanee",
    "sg:classifiers":[
        {
            "category":"Professional",
            "subcategory":"Engineering",
            "type":"Services"
        }
    ],
    "sg:phone":"+1 770 614 1633",
    "sg:postcode":"30024",
    "sg:province":"GA",
    "sg:tags":[
        "consulting",
        "engineer"
    ],
    "wof:name":"Consulting Enterprises Corp",
    "wof:placetype":"venue"
},
  "geometry": {"coordinates":[-84.089843,34.035248],"type":"Point"}
}