{
  "type": "Feature",
  "properties": {
    "addr:full":"1401 N Slappey Blvd Albany GA 31701",
    "addr:housenumber":"1401",
    "addr:postcode":"31701",
    "addr:street":"N Slappey Blvd",
    "iso:country":"US",
    "sg:address":"1401 N Slappey Blvd",
    "sg:city":"Albany",
    "sg:classifiers":[
        {
            "category":"Building & Trades",
            "subcategory":"Construction",
            "type":"Services"
        }
    ],
    "sg:phone":"+1 229 883 6937",
    "sg:postcode":"31701",
    "sg:province":"GA",
    "sg:tags":[
        "painter"
    ],
    "wof:name":"Affordable Painting & Rmdlng",
    "wof:placetype":"venue"
},
  "geometry": {"coordinates":[-84.175955,31.597077],"type":"Point"}
}