{
  "type": "Feature",
  "properties": {
    "iso:country":"US",
    "sg:address":"4825 Sugarloaf Pkwy Ste N",
    "sg:city":"Lawrenceville",
    "sg:classifiers":[
        {
            "category":"Shopping",
            "subcategory":"Pets & Pet Supplies",
            "type":"Retail Goods"
        }
    ],
    "sg:phone":"+1 678 985 1545",
    "sg:postcode":"30044",
    "sg:province":"GA",
    "sg:tags":[
        "groomers"
    ],
    "wof:name":"Pawsitviely Purrfect Grooming",
    "wof:placetype":"venue"
},
  "geometry": {"coordinates":[-84.052915,33.954894],"type":"Point"}
}