{
  "type": "Feature",
  "properties": {
    "iso:country":"US",
    "sg:address":"780 Bentgrass Ct",
    "sg:city":"Dacula",
    "sg:classifiers":[
        {
            "category":"Wholesale",
            "subcategory":"Hardware",
            "type":"Manufacturing & Wholesale Goods"
        }
    ],
    "sg:phone":"+1 770 513 0734",
    "sg:postcode":"30019",
    "sg:province":"GA",
    "sg:tags":[
        "refrigeration",
        "refrigerating"
    ],
    "wof:name":"Computer Process Controls Inc",
    "wof:placetype":"venue"
},
  "geometry": {"coordinates":[-83.90862199999999,34.018519],"type":"Point"}
}