{
  "type": "Feature",
  "properties": {
    "iso:country":"US",
    "sg:address":"4355 Shackleford Rd",
    "sg:city":"Norcross",
    "sg:classifiers":[
        {
            "category":"Professional",
            "subcategory":"Employment Agencies",
            "type":"Services"
        }
    ],
    "sg:phone":"+1 770 564 5585",
    "sg:postcode":"30093",
    "sg:province":"GA",
    "wof:name":"Peachtree Peopleware",
    "wof:placetype":"venue"
},
  "geometry": {"coordinates":[-84.15239699999999,33.938],"type":"Point"}
}