{
  "type": "Feature",
  "properties": {
    "iso:country":"US",
    "sg:address":"4300 Buford Hwy NE Ste 209",
    "sg:city":"Atlanta",
    "sg:classifiers":[
        {
            "category":"Restaurant",
            "type":"Food & Drink"
        }
    ],
    "sg:phone":"+1 404 254 4526",
    "sg:postcode":"30345",
    "sg:province":"GA",
    "sg:tags":[
        "vietnamese"
    ],
    "wof:name":"Dem Saigon",
    "wof:placetype":"venue"
},
  "geometry": {"coordinates":[-84.301834,33.867606],"type":"Point"}
}