{
  "type": "Feature",
  "properties": {
    "addr:full":"8550 Cedar Grove Rd Fairburn GA 30213",
    "addr:housenumber":"8550",
    "addr:postcode":"30213",
    "addr:street":"Cedar Grove Rd",
    "iso:country":"US",
    "sg:address":"8550 Cedar Grove Rd",
    "sg:city":"Fairburn",
    "sg:classifiers":[
        {
            "category":"Building & Trades",
            "subcategory":"Construction",
            "type":"Services"
        }
    ],
    "sg:phone":"+1 678 725 1680",
    "sg:postcode":"30213",
    "sg:province":"GA",
    "sg:tags":[
        "house"
    ],
    "wof:name":"M T Eskew Land Dev & MGT",
    "wof:placetype":"venue"
},
  "geometry": {"coordinates":[-84.66121099999999,33.606679],"type":"Point"}
}