{
  "type": "Feature",
  "properties": {
    "addr:full":"4225 Northfield Ln Cumming GA 30041",
    "addr:housenumber":"4225",
    "addr:postcode":"30041",
    "addr:street":"Northfield Ln",
    "iso:country":"US",
    "sg:address":"4225 Northfield Ln",
    "sg:city":"Cumming",
    "sg:classifiers":[
        {
            "category":"Home & Garden",
            "subcategory":"Building Materials",
            "type":"Retail Goods"
        }
    ],
    "sg:phone":"+1 770 844 9780",
    "sg:postcode":"30041",
    "sg:province":"GA",
    "sg:tags":[
        "paint"
    ],
    "wof:name":"J & A Paint Decorations",
    "wof:placetype":"venue"
},
  "geometry": {"coordinates":[-84.087406,34.151693],"type":"Point"}
}