{
  "type": "Feature",
  "properties": {
    "iso:country":"US",
    "sg:address":"5303 Orly Ter",
    "sg:city":"Atlanta",
    "sg:classifiers":[
        {
            "category":"Personal",
            "subcategory":"Beauty Salon",
            "type":"Services"
        }
    ],
    "sg:phone":"+1 404 763 1389",
    "sg:postcode":"30349",
    "sg:province":"GA",
    "wof:name":"Grand Illusions Hair Design",
    "wof:placetype":"venue"
},
  "geometry": {"coordinates":[-84.462205,33.612042],"type":"Point"}
}