{
  "type": "Feature",
  "properties": {
    "iso:country":"US",
    "sg:address":"3373 Dallas Hwy",
    "sg:city":"Marietta",
    "sg:classifiers":[
        {
            "category":"Building & Trades",
            "subcategory":"Construction",
            "type":"Services"
        }
    ],
    "sg:phone":"+1 770 419 1122",
    "sg:postcode":"30064",
    "sg:province":"GA",
    "sg:tags":[
        "cabinetry",
        "custom"
    ],
    "wof:name":"Concept Design Mill Inc",
    "wof:placetype":"venue"
},
  "geometry": {"coordinates":[-84.649328,33.953029],"type":"Point"}
}