{
  "type": "Feature",
  "properties": {
    "addr:full":"1316 10th Ave Columbus GA 31901",
    "addr:housenumber":"1316",
    "addr:postcode":"31901",
    "addr:street":"10Th Ave",
    "iso:country":"US",
    "sg:address":"1316 10th Ave",
    "sg:city":"Columbus",
    "sg:classifiers":[
        {
            "category":"Food & Beverages",
            "subcategory":"Bakery",
            "type":"Retail Goods"
        }
    ],
    "sg:phone":"+1 706 322 7565",
    "sg:postcode":"31901",
    "sg:province":"GA",
    "wof:name":"Sara Lee Bakery Group Inc",
    "wof:placetype":"venue"
},
  "geometry": {"coordinates":[-84.979651,32.472324],"type":"Point"}
}