{
  "type": "Feature",
  "properties": {
    "iso:country":"US",
    "sg:address":"1628 Newcastle St",
    "sg:city":"Brunswick",
    "sg:classifiers":[
        {
            "category":"Shopping",
            "type":"Retail Goods"
        }
    ],
    "sg:phone":"+1 912 554 0056",
    "sg:postcode":"31520",
    "sg:province":"GA",
    "sg:tags":[
        "art",
        "gallery",
        "merchandise",
        "dealer"
    ],
    "wof:name":"Gallery On Newcastle Inc",
    "wof:placetype":"venue"
},
  "geometry": {"coordinates":[-81.49632200000001,31.151635],"type":"Point"}
}