{
  "type": "Feature",
  "properties": {
    "iso:country":"US",
    "sg:address":"1835 S Cobb Industrial Blvd SE",
    "sg:city":"Smyrna",
    "sg:classifiers":[
        {
            "category":"Manufacturing",
            "subcategory":"Paper Products",
            "type":"Manufacturing & Wholesale Goods"
        }
    ],
    "sg:phone":"+1 770 433 8075",
    "sg:postcode":"30082",
    "sg:province":"GA",
    "sg:tags":[
        "bag"
    ],
    "wof:name":"Market Bag Co Inc",
    "wof:placetype":"venue"
},
  "geometry": {"coordinates":[-84.49991199999999,33.837876],"type":"Point"}
}