{
  "type": "Feature",
  "properties": {
    "iso:country":"US",
    "sg:address":"3605 Sandy Plains Rd Ste 120",
    "sg:city":"Marietta",
    "sg:classifiers":[
        {
            "category":"Personal",
            "subcategory":"Beauty Salon",
            "type":"Services"
        }
    ],
    "sg:phone":"+1 770 565 3625",
    "sg:postcode":"30066",
    "sg:province":"GA",
    "sg:tags":[
        "hair"
    ],
    "sg:website":"www.getthelook.com",
    "wof:name":"Famous Hair",
    "wof:placetype":"venue"
},
  "geometry": {"coordinates":[-84.465321,34.03852],"type":"Point"}
}