{
  "type": "Feature",
  "properties": {
    "iso:country":"US",
    "sg:address":"601 W Franklin St",
    "sg:city":"Sylvester",
    "sg:classifiers":[
        {
            "category":"Organizations",
            "subcategory":"Religious Organization",
            "type":"Services"
        }
    ],
    "sg:phone":"+1 229 776 1699",
    "sg:postcode":"31791",
    "sg:province":"GA",
    "wof:name":"Second Chance Ministry",
    "wof:placetype":"venue"
},
  "geometry": {"coordinates":[-83.84595899999999,31.53099],"type":"Point"}
}