{
  "type": "Feature",
  "properties": {
    "addr:full":"4475 River Green Pkwy Duluth GA 30096",
    "addr:housenumber":"4475",
    "addr:postcode":"30096",
    "addr:street":"River Green Pkwy",
    "iso:country":"US",
    "sg:address":"4475 River Green Pkwy",
    "sg:city":"Duluth",
    "sg:phone":"+1 404 784 5281",
    "sg:postcode":"30096",
    "sg:province":"GA",
    "wof:name":"Detail Masters of Atlanta",
    "wof:placetype":"venue"
},
  "geometry": {"coordinates":[-84.171243,34.020747],"type":"Point"}
}