{
  "type": "Feature",
  "properties": {
    "iso:country":"US",
    "sg:address":"4241 Sterling Pointe Dr",
    "sg:city":"Douglasville",
    "sg:classifiers":[
        {
            "category":"Building & Trades",
            "subcategory":"Construction",
            "type":"Services"
        }
    ],
    "sg:phone":"+1 770 312 0966",
    "sg:postcode":"30135",
    "sg:province":"GA",
    "sg:tags":[
        "repairing",
        "remodeling",
        "contractor"
    ],
    "wof:name":"Southeastern Steel",
    "wof:placetype":"venue"
},
  "geometry": {"coordinates":[-84.712678,33.674233],"type":"Point"}
}