{
  "type": "Feature",
  "properties": {
    "addr:full":"317 Southshore Ln Dallas GA 30157",
    "addr:housenumber":"317",
    "addr:postcode":"30157",
    "addr:street":"Southshore Ln",
    "iso:country":"US",
    "sg:address":"317 Southshore Ln",
    "sg:city":"Dallas",
    "sg:classifiers":[
        {
            "category":"Wholesale",
            "subcategory":"Non-durable Goods",
            "type":"Manufacturing & Wholesale Goods"
        }
    ],
    "sg:phone":"+1 770 445 2994",
    "sg:postcode":"30157",
    "sg:province":"GA",
    "wof:name":"Sbk Distributors",
    "wof:placetype":"venue"
},
  "geometry": {"coordinates":[-84.76310599999999,33.929338],"type":"Point"}
}