{
  "type": "Feature",
  "properties": {
    "addr:full":"3176 Nectarine Cir Decatur GA 30034",
    "addr:housenumber":"3176",
    "addr:postcode":"30034",
    "addr:street":"Nectarine Cir",
    "iso:country":"US",
    "sg:address":"3176 Nectarine Cir",
    "sg:city":"Decatur",
    "sg:classifiers":[
        {
            "category":"Home & Garden",
            "subcategory":"Building Materials",
            "type":"Retail Goods"
        }
    ],
    "sg:phone":"+1 404 259 8173",
    "sg:postcode":"30034",
    "sg:province":"GA",
    "sg:tags":[
        "company",
        "fence"
    ],
    "wof:name":"W & W Fence Company",
    "wof:placetype":"venue"
},
  "geometry": {"coordinates":[-84.258678,33.692213],"type":"Point"}
}