{
  "type": "Feature",
  "properties": {
    "iso:country":"US",
    "sg:address":"2755 Canton Rd",
    "sg:city":"Marietta",
    "sg:classifiers":[
        {
            "category":"Restaurant",
            "type":"Food & Drink"
        }
    ],
    "sg:menulink":"http://www.allmenus.com/ga/marietta/241229-grape-leaf-grill/menu/",
    "sg:phone":"+1 678 797 9187",
    "sg:postcode":"30066",
    "sg:province":"GA",
    "sg:tags":[
        "asian",
        "vietnamese"
    ],
    "wof:name":"Grape Leaf Grill",
    "wof:placetype":"venue"
},
  "geometry": {"coordinates":[-84.52825799999999,34.018388],"type":"Point"}
}