{
  "type": "Feature",
  "properties": {
    "iso:country":"US",
    "sg:address":"6925 Discovery Blvd",
    "sg:city":"Mableton",
    "sg:classifiers":[
        {
            "category":"Wholesale",
            "subcategory":"Machinery & Supplies",
            "type":"Manufacturing & Wholesale Goods"
        }
    ],
    "sg:phone":"+1 770 819 9555",
    "sg:postcode":"30126",
    "sg:province":"GA",
    "sg:tags":[
        "chains"
    ],
    "wof:name":"Columbus Mc Kinnon Corp",
    "wof:placetype":"venue"
},
  "geometry": {"coordinates":[-84.52980599999999,33.785288],"type":"Point"}
}