{
  "type": "Feature",
  "properties": {
    "iso:country":"US",
    "sg:address":"4730 Winder Hwy",
    "sg:city":"Flowery Branch",
    "sg:classifiers":[
        {
            "category":"Food & Beverages",
            "subcategory":"Fruits & Vegetables",
            "type":"Retail Goods"
        }
    ],
    "sg:phone":"+1 770 965 2524",
    "sg:postcode":"30542",
    "sg:province":"GA",
    "sg:tags":[
        "produce"
    ],
    "wof:name":"Hulsey's Produce",
    "wof:placetype":"venue"
},
  "geometry": {"coordinates":[-83.838188,34.172657],"type":"Point"}
}