{
  "type": "Feature",
  "properties": {
    "iso:country":"US",
    "sg:address":"2117 Woodland Dr",
    "sg:city":"Atlanta",
    "sg:classifiers":[
        {
            "category":"Sports & Exercise",
            "subcategory":"Golf",
            "type":"Entertainment"
        }
    ],
    "sg:phone":"+1 404 766 3056",
    "sg:postcode":"30354",
    "sg:province":"GA",
    "sg:tags":[
        "instruction"
    ],
    "wof:name":"Delta Golf Committee",
    "wof:placetype":"venue"
},
  "geometry": {"coordinates":[-84.397454,33.6632],"type":"Point"}
}