{
  "type": "Feature",
  "properties": {
    "addr:full":"405 W Cuyler St Dalton GA 30720",
    "addr:housenumber":"405",
    "addr:postcode":"30720",
    "addr:street":"W Cuyler St",
    "iso:country":"US",
    "sg:address":"405 W Cuyler St",
    "sg:city":"Dalton",
    "sg:classifiers":[
        {
            "category":"Shopping",
            "subcategory":"Bicycles & Sporting Goods",
            "type":"Retail Goods"
        }
    ],
    "sg:phone":"+1 706 275 8710",
    "sg:postcode":"30720",
    "sg:province":"GA",
    "wof:name":"Skates Eric & Mandy",
    "wof:placetype":"venue"
},
  "geometry": {"coordinates":[-84.972374,34.769781],"type":"Point"}
}