{
  "type": "Feature",
  "properties": {
    "addr:full":"5150 N Royal Atlanta Dr Tucker GA 30084",
    "addr:housenumber":"5150",
    "addr:postcode":"30084",
    "addr:street":"N Royal Atlanta Dr",
    "iso:country":"US",
    "sg:address":"5150 N Royal Atlanta Dr",
    "sg:city":"Tucker",
    "sg:classifiers":[
        {
            "category":"Manufacturing",
            "subcategory":"Printing",
            "type":"Manufacturing & Wholesale Goods"
        }
    ],
    "sg:phone":"+1 770 908 5650",
    "sg:postcode":"30084",
    "sg:province":"GA",
    "sg:tags":[
        "book",
        "publishing"
    ],
    "wof:name":"Emergence Creative Labs",
    "wof:placetype":"venue"
},
  "geometry": {"coordinates":[-84.183145,33.858306],"type":"Point"}
}