{
  "type": "Feature",
  "properties": {
    "addr:full":"2900 Chamblee Tucker Rd Atlanta GA 30341",
    "addr:housenumber":"2900",
    "addr:postcode":"30341",
    "addr:street":"Chamblee Tucker Rd",
    "iso:country":"US",
    "sg:address":"2900 Chamblee Tucker Rd",
    "sg:city":"Atlanta",
    "sg:classifiers":[
        {
            "category":"Banks & Credit Unions",
            "subcategory":"Bank",
            "type":"Services"
        }
    ],
    "sg:phone":"+1 770 457 6006",
    "sg:postcode":"30341",
    "sg:province":"GA",
    "sg:tags":[
        "loan",
        "broker",
        "mortgage"
    ],
    "wof:name":"Allied Home Mrtg Capitl Corp",
    "wof:placetype":"venue"
},
  "geometry": {"coordinates":[-84.26906700000001,33.877884],"type":"Point"}
}