{
  "type": "Feature",
  "properties": {
    "addr:full":"1612 Ridge Brook Trl Duluth GA 30096",
    "addr:housenumber":"1612",
    "addr:postcode":"30096",
    "addr:street":"Ridge Brook Trl",
    "iso:country":"US",
    "sg:address":"1612 Ridge Brook Trl",
    "sg:city":"Duluth",
    "sg:classifiers":[
        {
            "category":"Professional",
            "type":"Services"
        }
    ],
    "sg:phone":"+1 770 368 3190",
    "sg:postcode":"30096",
    "sg:province":"GA",
    "wof:name":"Wendy Slatery",
    "wof:placetype":"venue"
},
  "geometry": {"coordinates":[-84.15499199999999,33.949108],"type":"Point"}
}