{
  "type": "Feature",
  "properties": {
    "iso:country":"US",
    "sg:address":"1353 13th Ave",
    "sg:city":"Columbus",
    "sg:classifiers":[
        {
            "category":"Communications",
            "subcategory":"Radio Station",
            "type":"Services"
        }
    ],
    "sg:phone":"+1 706 322 1077",
    "sg:postcode":"31901",
    "sg:province":"GA",
    "sg:tags":[
        "company",
        "broadcasting"
    ],
    "sg:website":"www.mcclurebroadcasting.com",
    "wof:name":"WCGQ",
    "wof:placetype":"venue"
},
  "geometry": {"coordinates":[-84.974468,32.471587],"type":"Point"}
}