{
  "type": "Feature",
  "properties": {
    "iso:country":"US",
    "sg:address":"327 Douglas Creek Rd",
    "sg:city":"Flovilla",
    "sg:classifiers":[
        {
            "category":"Building & Trades",
            "subcategory":"Construction",
            "type":"Services"
        }
    ],
    "sg:phone":"+1 770 775 5531",
    "sg:postcode":"30216",
    "sg:province":"GA",
    "sg:tags":[
        "house"
    ],
    "wof:name":"Dewey C Gillis",
    "wof:placetype":"venue"
},
  "geometry": {"coordinates":[-83.88058700000001,33.248205],"type":"Point"}
}