{
  "type": "Feature",
  "properties": {
    "addr:full":"2505 Scruggs Dr Lithonia GA 30058",
    "addr:housenumber":"2505",
    "addr:postcode":"30058",
    "addr:street":"Scruggs Dr",
    "iso:country":"US",
    "sg:address":"2505 Scruggs Dr",
    "sg:city":"Lithonia",
    "sg:classifiers":[
        {
            "category":"Building & Trades",
            "subcategory":"Plumbing",
            "type":"Services"
        }
    ],
    "sg:phone":"+1 678 418 6545",
    "sg:postcode":"30058",
    "sg:province":"GA",
    "sg:tags":[
        "contractor"
    ],
    "wof:name":"Barrys Heating & Air",
    "wof:placetype":"venue"
},
  "geometry": {"coordinates":[-84.159735,33.713726],"type":"Point"}
}