{
  "type": "Feature",
  "properties": {
    "iso:country":"US",
    "sg:address":"2713 Braselton Hwy",
    "sg:city":"Dacula",
    "sg:classifiers":[
        {
            "category":"Retail",
            "subcategory":"Car Wash",
            "type":"Services"
        }
    ],
    "sg:phone":"+1 770 831 5781",
    "sg:postcode":"30019",
    "sg:province":"GA",
    "wof:name":"Mill Creek Car Wash & Lube",
    "wof:placetype":"venue"
},
  "geometry": {"coordinates":[-83.928377,34.050446],"type":"Point"}
}