{
  "type": "Feature",
  "properties": {
    "iso:country":"US",
    "sg:address":"1402 Patten Rd",
    "sg:city":"Lookout Mountain",
    "sg:classifiers":[
        {
            "category":"Real Estate",
            "subcategory":"Architect",
            "type":"Services"
        }
    ],
    "sg:phone":"+1 706 820 9225",
    "sg:postcode":"30750",
    "sg:province":"GA",
    "wof:name":"Patton Watkins Designs",
    "wof:placetype":"venue"
},
  "geometry": {"coordinates":[-85.35004600000001,34.972769],"type":"Point"}
}