{
  "type": "Feature",
  "properties": {
    "addr:full":"307 Summer Pl Peachtree City GA 30269",
    "addr:housenumber":"307",
    "addr:postcode":"30269",
    "addr:street":"Summer Pl",
    "iso:country":"US",
    "sg:address":"307 Summer Pl",
    "sg:city":"Peachtree City",
    "sg:classifiers":[
        {
            "category":"Building & Trades",
            "subcategory":"Construction",
            "type":"Services"
        }
    ],
    "sg:phone":"+1 770 632 6487",
    "sg:postcode":"30269",
    "sg:province":"GA",
    "sg:tags":[
        "general",
        "contractor"
    ],
    "wof:name":"Versatile Services",
    "wof:placetype":"venue"
},
  "geometry": {"coordinates":[-84.529751,33.349907],"type":"Point"}
}