{
  "type": "Feature",
  "properties": {
    "addr:full":"2595 Jeremiah Industrial Way SW Conyers GA 30012",
    "addr:housenumber":"2595",
    "addr:postcode":"30012",
    "addr:street":"Jeremiah Industrial Way Sw",
    "iso:country":"US",
    "sg:address":"2595 Jeremiah Industrial Way SW",
    "sg:city":"Conyers",
    "sg:classifiers":[
        {
            "category":"Manufacturing",
            "subcategory":"Chemicals & Compounds",
            "type":"Manufacturing & Wholesale Goods"
        }
    ],
    "sg:phone":"+1 770 929 1983",
    "sg:postcode":"30012",
    "sg:province":"GA",
    "sg:tags":[
        "paint",
        "varnish",
        "allied",
        "product"
    ],
    "wof:name":"Willamette Valley Cp",
    "wof:placetype":"venue"
},
  "geometry": {"coordinates":[-84.069113,33.692319],"type":"Point"}
}