{
  "type": "Feature",
  "properties": {
    "addr:full":"2702 Whatley Ave Savannah GA 31404",
    "addr:housenumber":"2702",
    "addr:postcode":"31404",
    "addr:street":"Whatley Ave",
    "iso:country":"US",
    "sg:address":"2702 Whatley Ave",
    "sg:city":"Savannah",
    "sg:classifiers":[
        {
            "category":"Freight",
            "type":"Transportation"
        }
    ],
    "sg:phone":"+1 912 356 3598",
    "sg:postcode":"31404",
    "sg:province":"GA",
    "sg:tags":[
        "foreign",
        "forwarder",
        "customhouse",
        "broker",
        "customs"
    ],
    "wof:name":"Anderson Shipping Corporation",
    "wof:placetype":"venue"
},
  "geometry": {"coordinates":[-81.05493199999999,32.036281],"type":"Point"}
}