{
  "type": "Feature",
  "properties": {
    "iso:country":"US",
    "sg:address":"234 S Candler St",
    "sg:city":"Villa Rica",
    "sg:classifiers":[
        {
            "category":"Banks & Credit Unions",
            "subcategory":"Financial Services",
            "type":"Services"
        }
    ],
    "sg:phone":"+1 770 363 4060",
    "sg:postcode":"30180",
    "sg:province":"GA",
    "sg:tags":[
        "trust",
        "investment",
        "real estate"
    ],
    "wof:name":"Dansum Inc",
    "wof:placetype":"venue"
},
  "geometry": {"coordinates":[-84.921993,33.730196],"type":"Point"}
}