{
  "type": "Feature",
  "properties": {
    "iso:country":"US",
    "sg:address":"1921 Old Covington Rd NE",
    "sg:city":"Conyers",
    "sg:classifiers":[
        {
            "category":"Building & Trades",
            "subcategory":"Plumbing",
            "type":"Services"
        }
    ],
    "sg:phone":"+1 770 922 3337",
    "sg:postcode":"30013",
    "sg:province":"GA",
    "sg:tags":[
        "conditioning",
        "contractor",
        "system",
        "air"
    ],
    "wof:name":"Deerman Heating & Air Cond",
    "wof:placetype":"venue"
},
  "geometry": {"coordinates":[-83.98501400000001,33.651353],"type":"Point"}
}