{
  "type": "Feature",
  "properties": {
    "iso:country":"US",
    "sg:address":"3186 Zebulon Rd",
    "sg:city":"Griffin",
    "sg:classifiers":[
        {
            "category":"Wholesale",
            "subcategory":"Construction Materials",
            "type":"Manufacturing & Wholesale Goods"
        }
    ],
    "sg:phone":"+1 770 229 4303",
    "sg:postcode":"30295",
    "sg:province":"GA",
    "sg:tags":[
        "timberland",
        "company",
        "timber"
    ],
    "wof:name":"Cox Land & Timber Inc",
    "wof:placetype":"venue"
},
  "geometry": {"coordinates":[-84.321606,33.139502],"type":"Point"}
}