{
  "type": "Feature",
  "properties": {
    "iso:country":"US",
    "sg:address":"295 Marsh Glen Dr",
    "sg:city":"Riverdale",
    "sg:classifiers":[
        {
            "category":"Building & Trades",
            "subcategory":"Construction",
            "type":"Services"
        }
    ],
    "sg:phone":"+1 678 508 0151",
    "sg:postcode":"30238",
    "sg:province":"GA",
    "sg:tags":[
        "house"
    ],
    "wof:name":"Sunset Painting & Home Repair",
    "wof:placetype":"venue"
},
  "geometry": {"coordinates":[-84.401352,33.498309],"type":"Point"}
}