{
  "type": "Feature",
  "properties": {
    "iso:country":"US",
    "sg:address":"75 Huffaker Rd NW",
    "sg:city":"Rome",
    "sg:classifiers":[
        {
            "category":"Sports & Exercise",
            "subcategory":"Bowling",
            "type":"Entertainment"
        }
    ],
    "sg:phone":"+1 706 234 3323",
    "sg:postcode":"30165",
    "sg:province":"GA",
    "sg:tags":[
        "center"
    ],
    "wof:name":"Classic Bowling Ctr",
    "wof:placetype":"venue"
},
  "geometry": {"coordinates":[-85.238553,34.276033],"type":"Point"}
}