{
  "type": "Feature",
  "properties": {
    "addr:full":"60 Andrew Young International Blvd NE Atlanta GA 30303",
    "addr:housenumber":"60;young",
    "addr:postcode":"30303",
    "addr:street":"Andrew;International Blvd Ne",
    "iso:country":"US",
    "sg:address":"60 Andrew Young International Blvd NE",
    "sg:city":"Atlanta",
    "sg:classifiers":[
        {
            "category":"Building & Trades",
            "subcategory":"Locksmith",
            "type":"Services"
        }
    ],
    "sg:phone":"+1 866 863 8723",
    "sg:postcode":"30303",
    "sg:province":"GA",
    "sg:tags":[
        "key"
    ],
    "wof:name":"24 Hour 7 Day Emergency Locksmith",
    "wof:placetype":"venue"
},
  "geometry": {"coordinates":[-84.385913,33.759817],"type":"Point"}
}