{
  "type": "Feature",
  "properties": {
    "iso:country":"US",
    "sg:address":"2103 Idlewood Rd",
    "sg:city":"Tucker",
    "sg:classifiers":[
        {
            "category":"Home & Garden",
            "subcategory":"Building Materials",
            "type":"Retail Goods"
        },
        {
            "category":"Building & Trades",
            "subcategory":"Construction",
            "type":"Services"
        },
        {
            "category":"Utilities",
            "subcategory":"Sewage",
            "type":"Services"
        }
    ],
    "sg:phone":"+1 770 493 3030",
    "sg:postcode":"30084",
    "sg:province":"GA",
    "sg:tags":[
        "foundation",
        "waterproofing",
        "roofing",
        "contractor",
        "concrete",
        "drainage"
    ],
    "wof:name":"Sundry Waterproofing",
    "wof:placetype":"venue"
},
  "geometry": {"coordinates":[-84.21328,33.845095],"type":"Point"}
}