{
  "type": "Feature",
  "properties": {
    "addr:full":"4890 Roswell Road NE Atlanta GA 30342",
    "addr:housenumber":"4890",
    "addr:postcode":"30342",
    "addr:street":"Roswell Road Ne",
    "iso:country":"US",
    "sg:address":"4890 Roswell Road NE",
    "sg:city":"Atlanta",
    "sg:classifiers":[
        {
            "category":"Health Services",
            "subcategory":"Doctor",
            "type":"Services"
        }
    ],
    "sg:phone":"+1 770 421 1420",
    "sg:postcode":"30342",
    "sg:province":"GA",
    "sg:tags":[
        "orthopedist"
    ],
    "wof:name":"Non-Surgical Orthopaedic & Spine Center P C",
    "wof:placetype":"venue"
},
  "geometry": {"coordinates":[-84.381494,33.887459],"type":"Point"}
}