{
  "type": "Feature",
  "properties": {
    "iso:country":"US",
    "sg:address":"100 Sutton Ln",
    "sg:city":"Rocky Face",
    "sg:classifiers":[
        {
            "category":"Farming",
            "subcategory":"Nursery",
            "type":"Manufacturing & Wholesale Goods"
        }
    ],
    "sg:phone":"+1 706 673 9774",
    "sg:postcode":"30740",
    "sg:province":"GA",
    "sg:tags":[
        "turf"
    ],
    "wof:name":"ACS Turf",
    "wof:placetype":"venue"
},
  "geometry": {"coordinates":[-85.059223,34.759189],"type":"Point"}
}