{
  "type": "Feature",
  "properties": {
    "iso:country":"US",
    "sg:address":"1150 Samples Industrial Dr",
    "sg:city":"Cumming",
    "sg:classifiers":[
        {
            "category":"Autos & Motor Vehicles",
            "subcategory":"Auto Supplies",
            "type":"Retail Goods"
        },
        {
            "category":"Retail",
            "subcategory":"Auto Repair",
            "type":"Services"
        }
    ],
    "sg:phone":"+1 770 886 8877",
    "sg:postcode":"30041",
    "sg:province":"GA",
    "sg:tags":[
        "automobile",
        "part",
        "accessory"
    ],
    "wof:name":"Turbo Diesel Register",
    "wof:placetype":"venue"
},
  "geometry": {"coordinates":[-84.15358500000001,34.160722],"type":"Point"}
}