{
  "type": "Feature",
  "properties": {
    "addr:full":"2840 Norman Berry Dr Atlanta GA 30344",
    "addr:housenumber":"2840",
    "addr:postcode":"30344",
    "addr:street":"Norman Berry Dr",
    "iso:country":"US",
    "sg:address":"2840 Norman Berry Dr",
    "sg:city":"Atlanta",
    "sg:classifiers":[
        {
            "category":"Transit Center",
            "subcategory":"Freight",
            "type":"Transportation"
        },
        {
            "category":"Freight",
            "type":"Transportation"
        }
    ],
    "sg:phone":"+1 404 992 0812",
    "sg:postcode":"30344",
    "sg:province":"GA",
    "sg:tags":[
        "local",
        "trucking-motor",
        "trucking"
    ],
    "wof:name":"Humphrey Trucking \"Llc\"",
    "wof:placetype":"venue"
},
  "geometry": {"coordinates":[-84.427356,33.678392],"type":"Point"}
}