{
  "type": "Feature",
  "properties": {
    "iso:country":"US",
    "sg:address":"112 Pine Cir SW",
    "sg:city":"Cairo",
    "sg:classifiers":[
        {
            "category":"Organizations",
            "subcategory":"Religious Organization",
            "type":"Services"
        }
    ],
    "sg:phone":"+1 229 377 9350",
    "sg:postcode":"39828",
    "sg:province":"GA",
    "sg:tags":[
        "church"
    ],
    "wof:name":"Pine Hill Baptist Church",
    "wof:placetype":"venue"
},
  "geometry": {"coordinates":[-84.21151999999999,30.866481],"type":"Point"}
}