{
  "type": "Feature",
  "properties": {
    "iso:country":"US",
    "sg:address":"1134 Telfair St",
    "sg:city":"Augusta",
    "sg:classifiers":[
        {
            "category":"Retail",
            "subcategory":"Funeral Services",
            "type":"Services"
        }
    ],
    "sg:phone":"+1 706 722 5566",
    "sg:postcode":"30901",
    "sg:province":"GA",
    "sg:tags":[
        "crematory"
    ],
    "wof:name":"Elliots Funeral Home",
    "wof:placetype":"venue"
},
  "geometry": {"coordinates":[-81.973733,33.474356],"type":"Point"}
}