{
  "type": "Feature",
  "properties": {
    "iso:country":"US",
    "sg:address":"29 E Moreno St",
    "sg:city":"Buford",
    "sg:classifiers":[
        {
            "category":"Manufacturing",
            "subcategory":"Tools & Machinery",
            "type":"Manufacturing & Wholesale Goods"
        }
    ],
    "sg:phone":"+1 770 945 0867",
    "sg:postcode":"30518",
    "sg:province":"GA",
    "sg:tags":[
        "mfg",
        "custom"
    ],
    "wof:name":"Duttons Machine Shop Inc",
    "wof:placetype":"venue"
},
  "geometry": {"coordinates":[-84.00497900000001,34.119487],"type":"Point"}
}