{
  "type": "Feature",
  "properties": {
    "addr:full":"106 la Rue Pl NW Atlanta GA 30327",
    "addr:housenumber":"106",
    "addr:postcode":"30327",
    "addr:street":"La Rue Pl Nw",
    "iso:country":"US",
    "sg:address":"106 la Rue Pl NW",
    "sg:city":"Atlanta",
    "sg:classifiers":[
        {
            "category":"Building & Trades",
            "subcategory":"Construction",
            "type":"Services"
        }
    ],
    "sg:phone":"+1 404 355 9203",
    "sg:postcode":"30327",
    "sg:province":"GA",
    "sg:tags":[
        "wall",
        "specialty",
        "covering"
    ],
    "wof:name":"Blue Rhino Spclty Wall Catings",
    "wof:placetype":"venue"
},
  "geometry": {"coordinates":[-84.485198,33.801423],"type":"Point"}
}