{
  "type": "Feature",
  "properties": {
    "iso:country":"US",
    "sg:address":"60 Johnson Rd",
    "sg:city":"Atlanta",
    "sg:classifiers":[
        {
            "category":"Organizations",
            "subcategory":"Religious Organization",
            "type":"Services"
        }
    ],
    "sg:phone":"+1 404 799 0324",
    "sg:postcode":"30318",
    "sg:province":"GA",
    "wof:name":"Second Refuge Church",
    "wof:placetype":"venue"
},
  "geometry": {"coordinates":[-84.453731,33.782845],"type":"Point"}
}