{
  "type": "Feature",
  "properties": {
    "addr:full":"2068 Brian Way Decatur GA 30033",
    "addr:housenumber":"2068",
    "addr:postcode":"30033",
    "addr:street":"Brian Way",
    "iso:country":"US",
    "sg:address":"2068 Brian Way",
    "sg:city":"Decatur",
    "sg:classifiers":[
        {
            "category":"Recreation",
            "type":"Entertainment"
        }
    ],
    "sg:phone":"+1 404 297 9187",
    "sg:postcode":"30033",
    "sg:province":"GA",
    "sg:tags":[
        "pool",
        "swimming"
    ],
    "wof:name":"Druid Woods Condominiums Pool",
    "wof:placetype":"venue"
},
  "geometry": {"coordinates":[-84.266519,33.811597],"type":"Point"}
}