{
  "type": "Feature",
  "properties": {
    "iso:country":"US",
    "sg:address":"1612 Mars Hill Rd",
    "sg:city":"Watkinsville",
    "sg:classifiers":[
        {
            "category":"Health Services",
            "subcategory":"Doctor",
            "type":"Services"
        }
    ],
    "sg:phone":"+1 706 769 1100",
    "sg:postcode":"30677",
    "sg:province":"GA",
    "sg:tags":[
        "physician",
        "family",
        "practice",
        "surgeons",
        "medicine",
        "surgeon"
    ],
    "wof:name":"Earhart Mark MD",
    "wof:placetype":"venue"
},
  "geometry": {"coordinates":[-83.454937,33.882645],"type":"Point"}
}