{
  "type": "Feature",
  "properties": {
    "iso:country":"US",
    "sg:address":"1138 Euclid Ave",
    "sg:city":"Atlanta",
    "sg:classifiers":[
        {
            "category":"Restaurant",
            "type":"Food & Drink"
        }
    ],
    "sg:phone":"+1 404 917 0106",
    "sg:postcode":"30307",
    "sg:province":"GA",
    "sg:tags":[
        "vegetarian",
        "indian"
    ],
    "wof:name":"Niramish",
    "wof:placetype":"venue"
},
  "geometry": {"coordinates":[-84.35001800000001,33.7648],"type":"Point"}
}