{
  "type": "Feature",
  "properties": {
    "iso:country":"US",
    "sg:address":"804 Commerce Blvd Ste B",
    "sg:city":"Riverdale",
    "sg:classifiers":[
        {
            "category":"Health Services",
            "subcategory":"Doctor",
            "type":"Services"
        }
    ],
    "sg:phone":"+1 770 997 6644",
    "sg:postcode":"30296",
    "sg:province":"GA",
    "sg:tags":[
        "medicine",
        "internal"
    ],
    "wof:name":"Southside Internal Medicine",
    "wof:placetype":"venue"
},
  "geometry": {"coordinates":[-84.417801,33.5481],"type":"Point"}
}