{
  "type": "Feature",
  "properties": {
    "addr:full":"1147 Henry Ave Columbus GA 31906",
    "addr:housenumber":"1147",
    "addr:postcode":"31906",
    "addr:street":"Henry Ave",
    "iso:country":"US",
    "sg:address":"1147 Henry Ave",
    "sg:city":"Columbus",
    "sg:classifiers":[
        {
            "category":"Personal",
            "subcategory":"Beauty Salon",
            "type":"Services"
        }
    ],
    "sg:phone":"+1 706 322 4336",
    "sg:postcode":"31906",
    "sg:province":"GA",
    "sg:tags":[
        "shop"
    ],
    "wof:name":"Elements of Style",
    "wof:placetype":"venue"
},
  "geometry": {"coordinates":[-84.957375,32.467938],"type":"Point"}
}