{
  "type": "Feature",
  "properties": {
    "iso:country":"US",
    "sg:address":"760 King George Blvd",
    "sg:city":"Savannah",
    "sg:classifiers":[
        {
            "category":"Building & Trades",
            "subcategory":"Equipment Rental",
            "type":"Services"
        }
    ],
    "sg:phone":"+1 912 920 7777",
    "sg:postcode":"31419",
    "sg:province":"GA",
    "sg:tags":[
        "leasing",
        "furniture"
    ],
    "wof:name":"Furnish America-Warehouse",
    "wof:placetype":"venue"
},
  "geometry": {"coordinates":[-81.21055699999999,31.98988],"type":"Point"}
}