{
  "type": "Feature",
  "properties": {
    "iso:country":"US",
    "sg:address":"3565 Fieldstone Xing",
    "sg:city":"Alpharetta",
    "sg:classifiers":[
        {
            "category":"Professional",
            "subcategory":"Computer Services",
            "type":"Services"
        }
    ],
    "sg:phone":"+1 770 752 3714",
    "sg:postcode":"30005",
    "sg:province":"GA",
    "sg:tags":[
        "related"
    ],
    "wof:name":"Ejava Inc",
    "wof:placetype":"venue"
},
  "geometry": {"coordinates":[-84.209091,34.091864],"type":"Point"}
}