{
  "type": "Feature",
  "properties": {
    "iso:country":"US",
    "sg:address":"564 N Talbotton St",
    "sg:city":"Greenville",
    "sg:classifiers":[
        {
            "category":"Professional",
            "subcategory":"Lawyer & Legal Services",
            "type":"Services"
        }
    ],
    "sg:phone":"+1 706 672 1717",
    "sg:postcode":"30222",
    "sg:province":"GA",
    "sg:tags":[
        "attorney"
    ],
    "wof:name":"C E Ryan Fuller Atty At Law",
    "wof:placetype":"venue"
},
  "geometry": {"coordinates":[-84.712838,33.029627],"type":"Point"}
}