{
  "type": "Feature",
  "properties": {
    "addr:full":"635 Atlanta St Roswell GA 30075",
    "addr:housenumber":"635",
    "addr:postcode":"30075",
    "addr:street":"Atlanta St",
    "iso:country":"US",
    "sg:address":"635 Atlanta St",
    "sg:city":"Roswell",
    "sg:classifiers":[
        {
            "category":"Restaurant",
            "type":"Food & Drink"
        }
    ],
    "sg:menulink":"http://www.allmenus.com/ga/roswell-alpharetta/259292-spiced-right-ribhouse/menu/",
    "sg:phone":"+1 678 352 9633",
    "sg:postcode":"30075",
    "sg:province":"GA",
    "sg:tags":[
        "barbecue",
        "american"
    ],
    "wof:name":"Spiced Right Ribhouse",
    "wof:placetype":"venue"
},
  "geometry": {"coordinates":[-84.362666,34.015915],"type":"Point"}
}