{
  "type": "Feature",
  "properties": {
    "iso:country":"US",
    "sg:address":"5113 S Royal Atlanta Dr",
    "sg:city":"Tucker",
    "sg:classifiers":[
        {
            "category":"Building & Trades",
            "subcategory":"Cleaning & Sanitation",
            "type":"Services"
        }
    ],
    "sg:phone":"+1 770 939 9399",
    "sg:postcode":"30084",
    "sg:province":"GA",
    "sg:tags":[
        "janitor"
    ],
    "wof:name":"Modern Maintenance Inc",
    "wof:placetype":"venue"
},
  "geometry": {"coordinates":[-84.18597200000001,33.856217],"type":"Point"}
}