{
  "type": "Feature",
  "properties": {
    "addr:full":"1228 Dover Pl SE Conyers GA 30013",
    "addr:housenumber":"1228",
    "addr:postcode":"30013",
    "addr:street":"Dover Pl Se",
    "iso:country":"US",
    "sg:address":"1228 Dover Pl SE",
    "sg:city":"Conyers",
    "sg:classifiers":[
        {
            "category":"Building & Trades",
            "subcategory":"Construction",
            "type":"Services"
        }
    ],
    "sg:phone":"+1 770 679 1729",
    "sg:postcode":"30013",
    "sg:province":"GA",
    "sg:tags":[
        "house"
    ],
    "wof:name":"Steve Robinson Builders Inc",
    "wof:placetype":"venue"
},
  "geometry": {"coordinates":[-84.011268,33.568475],"type":"Point"}
}