{
  "type": "Feature",
  "properties": {
    "addr:full":"4695 Candacraig Rd Alpharetta GA 30022",
    "addr:housenumber":"4695",
    "addr:postcode":"30022",
    "addr:street":"Candacraig Rd",
    "iso:country":"US",
    "sg:address":"4695 Candacraig Rd",
    "sg:city":"Alpharetta",
    "sg:classifiers":[
        {
            "category":"Shopping",
            "type":"Retail Goods"
        }
    ],
    "sg:phone":"+1 770 772 0828",
    "sg:postcode":"30022",
    "sg:province":"GA",
    "sg:tags":[
        "merchandise"
    ],
    "wof:name":"Horse Depot Inc",
    "wof:placetype":"venue"
},
  "geometry": {"coordinates":[-84.22102599999999,34.035471],"type":"Point"}
}