{
  "type": "Feature",
  "properties": {
    "iso:country":"US",
    "sg:address":"2775 Clairmont Rd",
    "sg:city":"Atlanta",
    "sg:classifiers":[
        {
            "category":"Restaurant",
            "type":"Food & Drink"
        }
    ],
    "sg:phone":"+1 404 321 0303",
    "sg:postcode":"30329",
    "sg:province":"GA",
    "sg:tags":[
        "traditional",
        "american"
    ],
    "sg:website":"www.benchwarmersgrill.com",
    "wof:name":"Benchwarmer's",
    "wof:placetype":"venue"
},
  "geometry": {"coordinates":[-84.312085,33.837978],"type":"Point"}
}