{
  "type": "Feature",
  "properties": {
    "iso:country":"US",
    "sg:address":"2324 Winchester Rd",
    "sg:city":"Albany",
    "sg:classifiers":[
        {
            "category":"Wholesale",
            "subcategory":"Machinery & Supplies",
            "type":"Manufacturing & Wholesale Goods"
        }
    ],
    "sg:phone":"+1 229 883 3931",
    "sg:postcode":"31721",
    "sg:province":"GA",
    "sg:tags":[
        "material",
        "representative",
        "handling"
    ],
    "wof:name":"Baugh Handling Systems Inc",
    "wof:placetype":"venue"
},
  "geometry": {"coordinates":[-84.256817,31.601464],"type":"Point"}
}