{
  "type": "Feature",
  "properties": {
    "iso:country":"US",
    "sg:address":"908 E Solomon St",
    "sg:city":"Griffin",
    "sg:classifiers":[
        {
            "category":"Food & Beverages",
            "subcategory":"Groceries & Convenience Stores",
            "type":"Retail Goods"
        }
    ],
    "sg:phone":"+1 770 228 3099",
    "sg:postcode":"30223",
    "sg:province":"GA",
    "wof:name":"East Griffin Grocery Co",
    "wof:placetype":"venue"
},
  "geometry": {"coordinates":[-84.247128,33.247992],"type":"Point"}
}