{
  "type": "Feature",
  "properties": {
    "addr:full":"3680 Tree Shade Way Cumming GA 30041",
    "addr:housenumber":"3680",
    "addr:postcode":"30041",
    "addr:street":"Tree Shade Way",
    "iso:country":"US",
    "sg:address":"3680 Tree Shade Way",
    "sg:city":"Cumming",
    "sg:classifiers":[
        {
            "category":"Restaurant",
            "type":"Food & Drink"
        }
    ],
    "sg:phone":"+1 770 205 1288",
    "sg:postcode":"30041",
    "sg:province":"GA",
    "sg:tags":[
        "eating"
    ],
    "wof:name":"Single Gourmet",
    "wof:placetype":"venue"
},
  "geometry": {"coordinates":[-84.07279800000001,34.251163],"type":"Point"}
}