{
  "type": "Feature",
  "properties": {
    "iso:country":"US",
    "sg:address":"314 Cash Memorial Blvd",
    "sg:city":"Forest Park",
    "sg:classifiers":[
        {
            "category":"Autos & Motor Vehicles",
            "subcategory":"Auto Supplies",
            "type":"Retail Goods"
        }
    ],
    "sg:phone":"+1 404 968 0123",
    "sg:postcode":"30297",
    "sg:province":"GA",
    "wof:name":"Eagle Tire Co",
    "wof:placetype":"venue"
},
  "geometry": {"coordinates":[-84.37973100000001,33.608248],"type":"Point"}
}