{
  "type": "Feature",
  "properties": {
    "addr:full":"306 Radcliff Ave Douglas GA 31533",
    "addr:housenumber":"306",
    "addr:postcode":"31533",
    "addr:street":"Radcliff Ave",
    "iso:country":"US",
    "sg:address":"306 Radcliff Ave",
    "sg:city":"Douglas",
    "sg:classifiers":[
        {
            "category":"Health Services",
            "subcategory":"Doctor",
            "type":"Services"
        }
    ],
    "sg:phone":"+1 912 384 0867",
    "sg:postcode":"31533",
    "sg:province":"GA",
    "sg:tags":[
        "physician",
        "surgeon"
    ],
    "wof:name":"L Davis Jacobs MD",
    "wof:placetype":"venue"
},
  "geometry": {"coordinates":[-82.86250200000001,31.506808],"type":"Point"}
}