{
  "type": "Feature",
  "properties": {
    "iso:country":"US",
    "sg:address":"2159 Faircrest Ave",
    "sg:city":"Augusta",
    "sg:classifiers":[
        {
            "category":"Organizations",
            "subcategory":"Religious Organization",
            "type":"Services"
        }
    ],
    "sg:phone":"+1 706 771 0084",
    "sg:postcode":"30906",
    "sg:province":"GA",
    "sg:tags":[
        "church"
    ],
    "wof:name":"El Shaddai Refuge Ctr Inc",
    "wof:placetype":"venue"
},
  "geometry": {"coordinates":[-82.039249,33.379703],"type":"Point"}
}