{
  "type": "Feature",
  "properties": {
    "iso:country":"US",
    "sg:address":"2850 Delk Rd SE",
    "sg:city":"Marietta",
    "sg:classifiers":[
        {
            "category":"Building & Trades",
            "subcategory":"Cleaning & Sanitation",
            "type":"Services"
        }
    ],
    "sg:phone":"+1 770 955 9167",
    "sg:postcode":"30067",
    "sg:province":"GA",
    "sg:tags":[
        "janitor"
    ],
    "wof:name":"C & L Complete Svc",
    "wof:placetype":"venue"
},
  "geometry": {"coordinates":[-84.47041900000001,33.92413],"type":"Point"}
}