{
  "type": "Feature",
  "properties": {
    "iso:country":"US",
    "sg:address":"1100 Johnson Ferry Rd NE",
    "sg:city":"Atlanta",
    "sg:classifiers":[
        {
            "category":"Shopping",
            "subcategory":"Stationery & Office Supplies",
            "type":"Retail Goods"
        },
        {
            "category":"Wholesale",
            "subcategory":"Photographic Equipment",
            "type":"Manufacturing & Wholesale Goods"
        }
    ],
    "sg:phone":"+1 678 904 9040",
    "sg:postcode":"30342",
    "sg:province":"GA",
    "sg:tags":[
        "coding",
        "bar",
        "system",
        "label"
    ],
    "sg:website":"http://www.barcodeid.com",
    "wof:name":"BarCode ID Systems Inc",
    "wof:placetype":"venue"
},
  "geometry": {"coordinates":[-84.352699,33.907242],"type":"Point"}
}