{
  "type": "Feature",
  "properties": {
    "addr:full":"125 Weldon Rd Cordele GA 31015",
    "addr:housenumber":"125",
    "addr:postcode":"31015",
    "addr:street":"Weldon Rd",
    "iso:country":"US",
    "sg:address":"125 Weldon Rd",
    "sg:city":"Cordele",
    "sg:classifiers":[
        {
            "category":"Organizations",
            "subcategory":"Religious Organization",
            "type":"Services"
        }
    ],
    "sg:phone":"+1 229 271 9664",
    "sg:postcode":"31015",
    "sg:province":"GA",
    "sg:tags":[
        "church"
    ],
    "wof:name":"Crossroad Baptist Church",
    "wof:placetype":"venue"
},
  "geometry": {"coordinates":[-83.85988,31.916393],"type":"Point"}
}