{
  "type": "Feature",
  "properties": {
    "iso:country":"US",
    "sg:address":"5390 Triangle Pkwy NW",
    "sg:city":"Norcross",
    "sg:classifiers":[
        {
            "category":"Manufacturing",
            "subcategory":"Tools & Machinery",
            "type":"Manufacturing & Wholesale Goods"
        }
    ],
    "sg:phone":"+1 678 969 4000",
    "sg:postcode":"30092",
    "sg:province":"GA",
    "sg:tags":[
        "storage",
        "computer",
        "datum",
        "devices",
        "mfg"
    ],
    "wof:name":"Storagetek",
    "wof:placetype":"venue"
},
  "geometry": {"coordinates":[-84.22265,33.97402],"type":"Point"}
}