{
  "type": "Feature",
  "properties": {
    "addr:full":"1611 Lawrenceville Suwanee Rd Lawrenceville GA 30043",
    "addr:housenumber":"1611",
    "addr:postcode":"30043",
    "addr:street":"Lawrenceville Suwanee Rd",
    "iso:country":"US",
    "sg:address":"1611 Lawrenceville Suwanee Rd",
    "sg:city":"Lawrenceville",
    "sg:classifiers":[
        {
            "category":"Organizations",
            "subcategory":"Non-profit Organization",
            "type":"Services"
        },
        {
            "category":"Professional",
            "type":"Services"
        }
    ],
    "sg:phone":"+1 770 962 8215",
    "sg:postcode":"30043",
    "sg:province":"GA",
    "sg:tags":[
        "info",
        "addiction",
        "abuse",
        "treatment",
        "drug"
    ],
    "wof:name":"Purple Inc",
    "wof:placetype":"venue"
},
  "geometry": {"coordinates":[-84.03262599999999,33.9916],"type":"Point"}
}