{
  "type": "Feature",
  "properties": {
    "iso:country":"US",
    "sg:address":"204 Springfield Ave",
    "sg:city":"Guyton",
    "sg:classifiers":[
        {
            "category":"Building & Trades",
            "subcategory":"Construction",
            "type":"Services"
        }
    ],
    "sg:phone":"+1 912 826 0820",
    "sg:postcode":"31312",
    "sg:province":"GA",
    "sg:tags":[
        "general",
        "contractor"
    ],
    "wof:name":"Long Builders Inc",
    "wof:placetype":"venue"
},
  "geometry": {"coordinates":[-81.391176,32.330775],"type":"Point"}
}