{
  "type": "Feature",
  "properties": {
    "iso:country":"US",
    "sg:address":"887 Howell Mill Rd",
    "sg:city":"Atlanta",
    "sg:classifiers":[
        {
            "category":"Restaurant",
            "type":"Food & Drink"
        }
    ],
    "sg:phone":"+1 404 815 1399",
    "sg:postcode":"30318",
    "sg:province":"GA",
    "sg:tags":[
        "new",
        "american"
    ],
    "sg:website":"www.bocadoatlanta.com",
    "wof:name":"Bocado",
    "wof:placetype":"venue"
},
  "geometry": {"coordinates":[-84.409693,33.779383],"type":"Point"}
}