{
  "type": "Feature",
  "properties": {
    "addr:full":"106 Folds Dr Carrollton GA 30117",
    "addr:housenumber":"106",
    "addr:postcode":"30117",
    "addr:street":"Folds Dr",
    "iso:country":"US",
    "sg:address":"106 Folds Dr",
    "sg:city":"Carrollton",
    "sg:classifiers":[
        {
            "category":"Retail",
            "subcategory":"Laundry & Dry Cleaning",
            "type":"Services"
        },
        {
            "category":"Wholesale",
            "subcategory":"Chemicals & Plastics",
            "type":"Manufacturing & Wholesale Goods"
        }
    ],
    "sg:phone":"+1 770 838 0730",
    "sg:postcode":"30117",
    "sg:province":"GA",
    "sg:tags":[
        "equipment",
        "home",
        "supply"
    ],
    "wof:name":"Pro Cleaners",
    "wof:placetype":"venue"
},
  "geometry": {"coordinates":[-85.053175,33.588858],"type":"Point"}
}