{
  "type": "Feature",
  "properties": {
    "addr:full":"195 Barr Ave Bowdon GA 30108",
    "addr:housenumber":"195",
    "addr:postcode":"30108",
    "addr:street":"Barr Ave",
    "iso:country":"US",
    "sg:address":"195 Barr Ave",
    "sg:city":"Bowdon",
    "sg:classifiers":[
        {
            "category":"Farming",
            "subcategory":"Poultry Farm",
            "type":"Manufacturing & Wholesale Goods"
        }
    ],
    "sg:phone":"+1 770 258 9728",
    "sg:postcode":"30108",
    "sg:province":"GA",
    "wof:name":"Gold KIST Inc",
    "wof:placetype":"venue"
},
  "geometry": {"coordinates":[-85.249174,33.529126],"type":"Point"}
}