{
  "type": "Feature",
  "properties": {
    "iso:country":"US",
    "sg:address":"2081 Goldmine Holly Springs Rd",
    "sg:city":"Royston",
    "sg:classifiers":[
        {
            "category":"Organizations",
            "subcategory":"Religious Organization",
            "type":"Services"
        }
    ],
    "sg:phone":"+1 706 245 9693",
    "sg:postcode":"30662",
    "sg:province":"GA",
    "wof:name":"Goldmine PH Church",
    "wof:placetype":"venue"
},
  "geometry": {"coordinates":[-83.038106,34.266577],"type":"Point"}
}