{
  "type": "Feature",
  "properties": {
    "addr:full":"120 Sims Dr Stockbridge GA 30281",
    "addr:housenumber":"120",
    "addr:postcode":"30281",
    "addr:street":"Sims Dr",
    "iso:country":"US",
    "sg:address":"120 Sims Dr",
    "sg:city":"Stockbridge",
    "sg:classifiers":[
        {
            "category":"Building & Trades",
            "subcategory":"Plumbing",
            "type":"Services"
        }
    ],
    "sg:phone":"+1 770 507 0467",
    "sg:postcode":"30281",
    "sg:province":"GA",
    "sg:tags":[
        "air",
        "heating",
        "conditioning",
        "contractor"
    ],
    "wof:name":"Ken Williams",
    "wof:placetype":"venue"
},
  "geometry": {"coordinates":[-84.168026,33.578085],"type":"Point"}
}