{
  "type": "Feature",
  "properties": {
    "addr:full":"1099 Berkshire Rd NE Atlanta GA 30306",
    "addr:housenumber":"1099",
    "addr:postcode":"30306",
    "addr:street":"Berkshire Rd Ne",
    "iso:country":"US",
    "sg:address":"1099 Berkshire Rd NE",
    "sg:city":"Atlanta",
    "sg:classifiers":[
        {
            "category":"Professional",
            "subcategory":"Business Services",
            "type":"Services"
        }
    ],
    "sg:phone":"+1 404 897 5817",
    "sg:postcode":"30306",
    "sg:province":"GA",
    "wof:name":"Mossbrook & Associates Inc",
    "wof:placetype":"venue"
},
  "geometry": {"coordinates":[-84.350274,33.798389],"type":"Point"}
}