{
  "type": "Feature",
  "properties": {
    "iso:country":"US",
    "sg:address":"151 Crossroads Pkwy",
    "sg:city":"Savannah",
    "sg:classifiers":[
        {
            "category":"Shopping",
            "subcategory":"Department Store",
            "type":"Retail Goods"
        },
        {
            "category":"Shopping",
            "subcategory":"Discount & Variety Stores",
            "type":"Retail Goods"
        }
    ],
    "sg:phone":"+1 912 965 1994",
    "sg:postcode":"31407",
    "sg:province":"GA",
    "sg:website":"http://www.dollartree.com",
    "wof:name":"Dollar Tree Distribution Ctr",
    "wof:placetype":"venue"
},
  "geometry": {"coordinates":[-81.224791,32.15209],"type":"Point"}
}