{
  "type": "Feature",
  "properties": {
    "iso:country":"US",
    "sg:address":"396 Deal's Cir S",
    "sg:city":"Woodbine",
    "sg:classifiers":[
        {
            "category":"Building & Trades",
            "subcategory":"Construction",
            "type":"Services"
        }
    ],
    "sg:phone":"+1 912 882 9344",
    "sg:postcode":"31569",
    "sg:province":"GA",
    "sg:tags":[
        "concrete",
        "contractor"
    ],
    "wof:name":"Wainwright Concrete",
    "wof:placetype":"venue"
},
  "geometry": {"coordinates":[-81.651417,30.84375],"type":"Point"}
}