{
  "type": "Feature",
  "properties": {
    "addr:full":"441 Marietta St Atlanta GA 30313",
    "addr:housenumber":"441",
    "addr:postcode":"30313",
    "addr:street":"Marietta St",
    "iso:country":"US",
    "sg:address":"441 Marietta St",
    "sg:city":"Atlanta",
    "sg:classifiers":[
        {
            "category":"Personal",
            "subcategory":"Beauty Salon",
            "type":"Services"
        },
        {
            "category":"Personal",
            "subcategory":"Nail Salon",
            "type":"Services"
        }
    ],
    "sg:phone":"+1 678 732 9383",
    "sg:postcode":"30313",
    "sg:province":"GA",
    "sg:tags":[
        "eyelash",
        "cosmetologist"
    ],
    "sg:website":"www.flirtnflutterlashloft.com/",
    "wof:name":"Flirt And Flutter Lash Loft",
    "wof:placetype":"venue"
},
  "geometry": {"coordinates":[-84.397245,33.765057],"type":"Point"}
}