{
  "type": "Feature",
  "properties": {
    "iso:country":"US",
    "sg:address":"5270 Highway 129 N",
    "sg:city":"Jefferson",
    "sg:classifiers":[
        {
            "category":"Fast Food",
            "type":"Food & Drink"
        },
        {
            "category":"Restaurant",
            "type":"Food & Drink"
        }
    ],
    "sg:phone":"+1 706 693 4442",
    "sg:postcode":"30549",
    "sg:province":"GA",
    "sg:tags":[
        "american",
        "hot",
        "hamburger",
        "dog"
    ],
    "sg:website":"http://www.wendys.com",
    "wof:name":"Wendy's",
    "wof:placetype":"venue"
},
  "geometry": {"coordinates":[-83.65124,34.152791],"type":"Point"}
}