{
  "type": "Feature",
  "properties": {
    "addr:full":"265 Abbott Dr Waleska GA 30114",
    "addr:housenumber":"265",
    "addr:postcode":"30114",
    "addr:street":"Abbott Dr",
    "iso:country":"US",
    "sg:address":"265 Abbott Dr",
    "sg:city":"Waleska",
    "sg:classifiers":[
        {
            "category":"Building & Trades",
            "subcategory":"Construction",
            "type":"Services"
        }
    ],
    "sg:phone":"+1 770 479 4479",
    "sg:postcode":"30114",
    "sg:province":"GA",
    "sg:tags":[
        "home",
        "builder"
    ],
    "wof:name":"A C Custom Homes",
    "wof:placetype":"venue"
},
  "geometry": {"coordinates":[-84.50512000000001,34.288868],"type":"Point"}
}