{
  "type": "Feature",
  "properties": {
    "addr:full":"1199 Prince Ave Athens GA 30606",
    "addr:housenumber":"1199",
    "addr:postcode":"30606",
    "addr:street":"Prince Ave",
    "iso:country":"US",
    "sg:address":"1199 Prince Ave",
    "sg:city":"Athens",
    "sg:classifiers":[
        {
            "category":"Professional",
            "type":"Services"
        }
    ],
    "sg:phone":"+1 706 546 5226",
    "sg:postcode":"30606",
    "sg:province":"GA",
    "sg:tags":[
        "establishment"
    ],
    "wof:name":"E Solutions Xperts Inc",
    "wof:placetype":"venue"
},
  "geometry": {"coordinates":[-83.398234,33.962423],"type":"Point"}
}