{
  "type": "Feature",
  "properties": {
    "iso:country":"US",
    "sg:address":"1851 Hodgeville Rd",
    "sg:city":"Rincon",
    "sg:classifiers":[
        {
            "category":"Building & Trades",
            "subcategory":"Construction",
            "type":"Services"
        }
    ],
    "sg:phone":"+1 912 728 8303",
    "sg:postcode":"31326",
    "sg:province":"GA",
    "wof:name":"GDI",
    "wof:placetype":"venue"
},
  "geometry": {"coordinates":[-81.256803,32.205909],"type":"Point"}
}