{
  "type": "Feature",
  "properties": {
    "addr:full":"225 W King St Dalton GA 30720",
    "addr:housenumber":"225",
    "addr:postcode":"30720",
    "addr:street":"W King St",
    "iso:country":"US",
    "sg:address":"225 W King St",
    "sg:city":"Dalton",
    "sg:classifiers":[
        {
            "category":"Professional",
            "subcategory":"Lawyer & Legal Services",
            "type":"Services"
        }
    ],
    "sg:phone":"+1 706 278 5211",
    "sg:postcode":"30720",
    "sg:province":"GA",
    "sg:tags":[
        "attorney"
    ],
    "wof:name":"Sponcler & Tharpe",
    "wof:placetype":"venue"
},
  "geometry": {"coordinates":[-84.970556,34.772344],"type":"Point"}
}