{
  "type": "Feature",
  "properties": {
    "addr:full":"1221 Sam Bell Rd Clarkesville GA 30523",
    "addr:housenumber":"1221",
    "addr:postcode":"30523",
    "addr:street":"Sam Bell Rd",
    "iso:country":"US",
    "sg:address":"1221 Sam Bell Rd",
    "sg:city":"Clarkesville",
    "sg:classifiers":[
        {
            "category":"Wholesale",
            "subcategory":"Machinery & Supplies",
            "type":"Manufacturing & Wholesale Goods"
        }
    ],
    "sg:phone":"+1 706 754 4057",
    "sg:postcode":"30523",
    "sg:province":"GA",
    "sg:tags":[
        "equipment",
        "industrial"
    ],
    "wof:name":"Powerhouse Outdoor Equipment",
    "wof:placetype":"venue"
},
  "geometry": {"coordinates":[-83.58568699999999,34.639464],"type":"Point"}
}