{
  "type": "Feature",
  "properties": {
    "iso:country":"US",
    "sg:address":"6362 Fairburn Rd",
    "sg:city":"Douglasville",
    "sg:classifiers":[
        {
            "category":"Autos & Motor Vehicles",
            "subcategory":"Automobile Sales",
            "type":"Retail Goods"
        }
    ],
    "sg:phone":"+1 770 942 5868",
    "sg:postcode":"30134",
    "sg:province":"GA",
    "sg:tags":[
        "car",
        "dealer"
    ],
    "wof:name":"Gray Motors",
    "wof:placetype":"venue"
},
  "geometry": {"coordinates":[-84.74014099999999,33.751326],"type":"Point"}
}