{
  "type": "Feature",
  "properties": {
    "addr:full":"1458 Ila Rd Commerce GA 30530",
    "addr:housenumber":"1458",
    "addr:postcode":"30530",
    "addr:street":"Ila Rd",
    "iso:country":"US",
    "sg:address":"1458 Ila Rd",
    "sg:city":"Commerce",
    "sg:classifiers":[
        {
            "category":"Banks & Credit Unions",
            "subcategory":"Bank",
            "type":"Services"
        }
    ],
    "sg:phone":"+1 706 335 4957",
    "sg:postcode":"30530",
    "sg:province":"GA",
    "sg:tags":[
        "loan"
    ],
    "wof:name":"A G Credit Team",
    "wof:placetype":"venue"
},
  "geometry": {"coordinates":[-83.42413500000001,34.194265],"type":"Point"}
}