{
  "type": "Feature",
  "properties": {
    "iso:country":"US",
    "sg:address":"5241 Wrightsboro Rd",
    "sg:city":"Grovetown",
    "sg:classifiers":[
        {
            "category":"Autos & Motor Vehicles",
            "subcategory":"Automobile Sales",
            "type":"Retail Goods"
        }
    ],
    "sg:phone":"+1 706 210 9314",
    "sg:postcode":"30813",
    "sg:province":"GA",
    "wof:name":"B & W Auto Sales",
    "wof:placetype":"venue"
},
  "geometry": {"coordinates":[-82.208153,33.454473],"type":"Point"}
}