{
  "type": "Feature",
  "properties": {
    "addr:full":"193 Panther Path Fayetteville GA 30215",
    "addr:housenumber":"193",
    "addr:postcode":"30215",
    "addr:street":"Panther Path",
    "iso:country":"US",
    "sg:address":"193 Panther Path",
    "sg:city":"Fayetteville",
    "sg:classifiers":[
        {
            "category":"Organizations",
            "subcategory":"Community Association",
            "type":"Services"
        }
    ],
    "sg:phone":"+1 770 631 0805",
    "sg:postcode":"30215",
    "sg:province":"GA",
    "wof:name":"Stars Mill Band Boosters",
    "wof:placetype":"venue"
},
  "geometry": {"coordinates":[-84.524997,33.343977],"type":"Point"}
}