{
  "type": "Feature",
  "properties": {
    "addr:full":"1804 E Park Ave Valdosta GA 31602",
    "addr:housenumber":"1804",
    "addr:postcode":"31602",
    "addr:street":"E Park Ave",
    "iso:country":"US",
    "sg:address":"1804 E Park Ave",
    "sg:city":"Valdosta",
    "sg:classifiers":[
        {
            "category":"Building & Trades",
            "subcategory":"Construction",
            "type":"Services"
        }
    ],
    "sg:phone":"+1 229 244 0608",
    "sg:postcode":"31602",
    "sg:province":"GA",
    "sg:tags":[
        "demolition",
        "contractor"
    ],
    "wof:name":"Lund General Contracting Svc",
    "wof:placetype":"venue"
},
  "geometry": {"coordinates":[-83.256688,30.86009],"type":"Point"}
}