{
  "type": "Feature",
  "properties": {
    "iso:country":"US",
    "sg:address":"530 Means St NW",
    "sg:city":"Atlanta",
    "sg:classifiers":[
        {
            "category":"Shopping",
            "subcategory":"Computers & Home Electronics",
            "type":"Retail Goods"
        }
    ],
    "sg:phone":"+1 404 880 0909",
    "sg:postcode":"30318",
    "sg:province":"GA",
    "sg:tags":[
        "software"
    ],
    "wof:name":"Pallas Technology",
    "wof:placetype":"venue"
},
  "geometry": {"coordinates":[-84.405096,33.772664],"type":"Point"}
}