{
  "type": "Feature",
  "properties": {
    "iso:country":"US",
    "sg:address":"6125 Covington Hwy",
    "sg:city":"Decatur",
    "sg:classifiers":[
        {
            "category":"Personal",
            "subcategory":"Beauty Salon",
            "type":"Services"
        }
    ],
    "sg:phone":"+1 770 593 4049",
    "sg:postcode":"30035",
    "sg:province":"GA",
    "sg:tags":[
        "pedicurist",
        "manicurist",
        "manicuring"
    ],
    "wof:name":"Fine Nails",
    "wof:placetype":"venue"
},
  "geometry": {"coordinates":[-84.172034,33.723751],"type":"Point"}
}