{
  "type": "Feature",
  "properties": {
    "addr:full":"144 Waugh Rd Lagrange GA 30241",
    "addr:housenumber":"144",
    "addr:postcode":"30241",
    "addr:street":"Waugh Rd",
    "iso:country":"US",
    "sg:address":"144 Waugh Rd",
    "sg:city":"Lagrange",
    "sg:classifiers":[
        {
            "category":"Building & Trades",
            "subcategory":"Plumbing",
            "type":"Services"
        }
    ],
    "sg:phone":"+1 706 884 1736",
    "sg:postcode":"30241",
    "sg:province":"GA",
    "sg:tags":[
        "plumbing",
        "contractor"
    ],
    "wof:name":"Wood Plumbing Inc",
    "wof:placetype":"venue"
},
  "geometry": {"coordinates":[-85.022688,33.076148],"type":"Point"}
}