{
  "type": "Feature",
  "properties": {
    "iso:country":"US",
    "sg:address":"2395 Bowman Hwy",
    "sg:city":"Dewy Rose",
    "sg:classifiers":[
        {
            "category":"Cinema",
            "subcategory":"Drive-in Theater",
            "type":"Entertainment"
        }
    ],
    "sg:phone":"+1 706 213 7693",
    "sg:postcode":"30634",
    "sg:province":"GA",
    "sg:tags":[
        "movie"
    ],
    "wof:name":"Highway 17 Theatres",
    "wof:placetype":"venue"
},
  "geometry": {"coordinates":[-82.96744099999999,34.180006],"type":"Point"}
}