{
  "type": "Feature",
  "properties": {
    "iso:country":"US",
    "sg:address":"639 Johnson Ferry Rd",
    "sg:city":"Marietta",
    "sg:classifiers":[
        {
            "category":"Farming",
            "subcategory":"Farm",
            "type":"Manufacturing & Wholesale Goods"
        }
    ],
    "sg:phone":"+1 770 973 7131",
    "sg:postcode":"30068",
    "sg:province":"GA",
    "wof:name":"Homestead Farms",
    "wof:placetype":"venue"
},
  "geometry": {"coordinates":[-84.411923,33.966306],"type":"Point"}
}