{
  "type": "Feature",
  "properties": {
    "iso:country":"US",
    "sg:address":"628 Battle Rd SW",
    "sg:city":"Calhoun",
    "sg:classifiers":[
        {
            "category":"Farming",
            "subcategory":"Farm",
            "type":"Manufacturing & Wholesale Goods"
        }
    ],
    "sg:phone":"+1 706 624 3460",
    "sg:postcode":"30701",
    "sg:province":"GA",
    "wof:name":"Haven Farms",
    "wof:placetype":"venue"
},
  "geometry": {"coordinates":[-85.087757,34.438233],"type":"Point"}
}