{
  "type": "Feature",
  "properties": {
    "iso:country":"US",
    "sg:address":"4465 Dodson Dr",
    "sg:city":"Douglasville",
    "sg:classifiers":[
        {
            "category":"Professional",
            "type":"Services"
        }
    ],
    "sg:phone":"+1 770 949 2971",
    "sg:postcode":"30134",
    "sg:province":"GA",
    "wof:name":"C&V Installation & Services In",
    "wof:placetype":"venue"
},
  "geometry": {"coordinates":[-84.72005799999999,33.761535],"type":"Point"}
}