{
  "type": "Feature",
  "properties": {
    "addr:full":"10 W Main St Cartersville GA 30120",
    "addr:housenumber":"10",
    "addr:postcode":"30120",
    "addr:street":"W Main St",
    "iso:country":"US",
    "sg:address":"10 W Main St",
    "sg:city":"Cartersville",
    "sg:classifiers":[
        {
            "category":"Professional",
            "subcategory":"Business Services",
            "type":"Services"
        }
    ],
    "sg:phone":"+1 770 606 0062",
    "sg:postcode":"30120",
    "sg:province":"GA",
    "wof:name":"Looking Glass Studio",
    "wof:placetype":"venue"
},
  "geometry": {"coordinates":[-84.80028799999999,34.163798],"type":"Point"}
}