{
  "type": "Feature",
  "properties": {
    "addr:full":"135 Mountain Brook Dr Canton GA 30115",
    "addr:housenumber":"135",
    "addr:postcode":"30115",
    "addr:street":"Mountain Brook Dr",
    "iso:country":"US",
    "sg:address":"135 Mountain Brook Dr",
    "sg:city":"Canton",
    "sg:classifiers":[
        {
            "category":"Professional",
            "subcategory":"Printing & Photocopies",
            "type":"Services"
        }
    ],
    "sg:phone":"+1 770 479 1576",
    "sg:postcode":"30115",
    "sg:province":"GA",
    "sg:tags":[
        "photocopying"
    ],
    "wof:name":"Ani Copy Center",
    "wof:placetype":"venue"
},
  "geometry": {"coordinates":[-84.504993,34.178662],"type":"Point"}
}