{
  "type": "Feature",
  "properties": {
    "addr:full":"1 Mary Alice Park Rd Cumming GA 30040",
    "addr:housenumber":"1",
    "addr:postcode":"30040",
    "addr:street":"Mary Alice Park Rd",
    "iso:country":"US",
    "sg:address":"1 Mary Alice Park Rd",
    "sg:city":"Cumming",
    "sg:classifiers":[
        {
            "category":"Professional",
            "subcategory":"Employment Agencies",
            "type":"Services"
        }
    ],
    "sg:phone":"+1 678 513 7328",
    "sg:postcode":"30040",
    "sg:province":"GA",
    "sg:tags":[
        "opportunity"
    ],
    "wof:name":"Labor Finders",
    "wof:placetype":"venue"
},
  "geometry": {"coordinates":[-84.134201,34.200378],"type":"Point"}
}