{
  "type": "Feature",
  "properties": {
    "iso:country":"US",
    "sg:address":"165 Atwater Rd",
    "sg:city":"Thomaston",
    "sg:classifiers":[
        {
            "category":"Building & Trades",
            "subcategory":"Electrical",
            "type":"Services"
        }
    ],
    "sg:phone":"+1 706 648 3272",
    "sg:postcode":"30286",
    "sg:province":"GA",
    "sg:tags":[
        "air",
        "electrical",
        "conditioning",
        "contractor"
    ],
    "wof:name":"Great Lite Electric Inc",
    "wof:placetype":"venue"
},
  "geometry": {"coordinates":[-84.341953,32.951055],"type":"Point"}
}