{
  "type": "Feature",
  "properties": {
    "iso:country":"US",
    "sg:address":"2905 Burruss Trl",
    "sg:city":"Cumming",
    "sg:classifiers":[
        {
            "category":"Professional",
            "subcategory":"Management & Consulting",
            "type":"Services"
        }
    ],
    "sg:phone":"+1 770 887 2803",
    "sg:postcode":"30040",
    "sg:province":"GA",
    "sg:tags":[
        "consultant"
    ],
    "wof:name":"Blp Enterprises Inc",
    "wof:placetype":"venue"
},
  "geometry": {"coordinates":[-84.102778,34.264219],"type":"Point"}
}