{
  "type": "Feature",
  "properties": {
    "addr:full":"223 Newport Dr Peachtree City GA 30269",
    "addr:housenumber":"223",
    "addr:postcode":"30269",
    "addr:street":"Newport Dr",
    "iso:country":"US",
    "sg:address":"223 Newport Dr",
    "sg:city":"Peachtree City",
    "sg:classifiers":[
        {
            "category":"Professional",
            "subcategory":"Management & Consulting",
            "type":"Services"
        }
    ],
    "sg:phone":"+1 770 631 4079",
    "sg:postcode":"30269",
    "sg:province":"GA",
    "sg:tags":[
        "consultant"
    ],
    "wof:name":"John J Yeosock",
    "wof:placetype":"venue"
},
  "geometry": {"coordinates":[-84.58579400000001,33.432555],"type":"Point"}
}