{
  "type": "Feature",
  "properties": {
    "iso:country":"US",
    "sg:address":"1325 Patterson Dr",
    "sg:city":"Gainesville",
    "sg:classifiers":[
        {
            "category":"Professional",
            "type":"Services"
        }
    ],
    "sg:phone":"+1 770 538 0274",
    "sg:postcode":"30501",
    "sg:province":"GA",
    "wof:name":"Right Way Svcs",
    "wof:placetype":"venue"
},
  "geometry": {"coordinates":[-83.80148199999999,34.294119],"type":"Point"}
}