{
  "type": "Feature",
  "properties": {
    "addr:full":"376 Maxham Rd Austell GA 30168",
    "addr:housenumber":"376",
    "addr:postcode":"30168",
    "addr:street":"Maxham Rd",
    "iso:country":"US",
    "sg:address":"376 Maxham Rd",
    "sg:city":"Austell",
    "sg:classifiers":[
        {
            "category":"Professional",
            "subcategory":"Advertising",
            "type":"Services"
        }
    ],
    "sg:phone":"+1 770 944 3800",
    "sg:postcode":"30168",
    "sg:province":"GA",
    "sg:tags":[
        "mail",
        "mailing",
        "direct",
        "shipping"
    ],
    "wof:name":"E Z Pack & Mail",
    "wof:placetype":"venue"
},
  "geometry": {"coordinates":[-84.62354000000001,33.78622],"type":"Point"}
}