{
  "type": "Feature",
  "properties": {
    "iso:country":"US",
    "sg:address":"1107 Memorial Dr",
    "sg:city":"Dalton",
    "sg:classifiers":[
        {
            "category":"Health Services",
            "subcategory":"Doctor",
            "type":"Services"
        }
    ],
    "sg:phone":"+1 706 226 3139",
    "sg:postcode":"30720",
    "sg:province":"GA",
    "sg:tags":[
        "physician",
        "surgeon",
        "medical"
    ],
    "wof:name":"Cornerstone Medical Group",
    "wof:placetype":"venue"
},
  "geometry": {"coordinates":[-84.981281,34.789041],"type":"Point"}
}