{
  "type": "Feature",
  "properties": {
    "iso:country":"US",
    "sg:address":"2300 Peachford Rd",
    "sg:city":"Atlanta",
    "sg:classifiers":[
        {
            "category":"Banks & Credit Unions",
            "subcategory":"Investment Brokerage",
            "type":"Services"
        }
    ],
    "sg:phone":"+1 770 454 1889",
    "sg:postcode":"30338",
    "sg:province":"GA",
    "sg:tags":[
        "commodity"
    ],
    "wof:name":"ADM Srcurities",
    "wof:placetype":"venue"
},
  "geometry": {"coordinates":[-84.30003000000001,33.924922],"type":"Point"}
}