{
  "type": "Feature",
  "properties": {
    "addr:full":"1990 Lakeside Pkwy Ste 230 Tucker GA 30084",
    "addr:housenumber":"1990",
    "addr:postcode":"30084",
    "addr:street":"Lakeside Pkwy Ste 230",
    "iso:country":"US",
    "sg:address":"1990 Lakeside Pkwy Ste 230",
    "sg:city":"Tucker",
    "sg:classifiers":[
        {
            "category":"Autos & Motor Vehicles",
            "subcategory":"Fuel & Gas Station",
            "type":"Retail Goods"
        },
        {
            "category":"Wholesale",
            "subcategory":"Petroleum",
            "type":"Manufacturing & Wholesale Goods"
        },
        {
            "category":"Food & Beverages",
            "subcategory":"Groceries & Convenience Stores",
            "type":"Retail Goods"
        }
    ],
    "sg:phone":"+1 770 414 1014",
    "sg:postcode":"30084",
    "sg:province":"GA",
    "sg:tags":[
        "gasoline-wholesale"
    ],
    "wof:name":"Sugar Bear Inc",
    "wof:placetype":"venue"
},
  "geometry": {"coordinates":[-84.24009700000001,33.840302],"type":"Point"}
}