{
  "type": "Feature",
  "properties": {
    "iso:country":"US",
    "sg:address":"121 Haynes St",
    "sg:city":"Marietta",
    "sg:classifiers":[
        {
            "category":"Banks & Credit Unions",
            "subcategory":"Bank",
            "type":"Services"
        }
    ],
    "sg:phone":"+1 770 659 1070",
    "sg:postcode":"30060",
    "sg:province":"GA",
    "sg:tags":[
        "state",
        "commercial"
    ],
    "sg:website":"www.southtrust.com",
    "wof:name":"South Trust Bank",
    "wof:placetype":"venue"
},
  "geometry": {"coordinates":[-84.54710300000001,33.954044],"type":"Point"}
}