{
  "type": "Feature",
  "properties": {
    "iso:country":"US",
    "sg:address":"30 E Kennedy St",
    "sg:city":"Statesboro",
    "sg:classifiers":[
        {
            "category":"Manufacturing",
            "subcategory":"Printing",
            "type":"Manufacturing & Wholesale Goods"
        }
    ],
    "sg:phone":"+1 912 681 6824",
    "sg:postcode":"30458",
    "sg:province":"GA",
    "sg:tags":[
        "lithographic",
        "b",
        "commercial",
        "typesetting"
    ],
    "wof:name":"Lewis Color Printing Solutions",
    "wof:placetype":"venue"
},
  "geometry": {"coordinates":[-81.784413,32.43404],"type":"Point"}
}