{
  "type": "Feature",
  "properties": {
    "iso:country":"US",
    "sg:address":"420 S Marcus St",
    "sg:city":"Wrightsville",
    "sg:classifiers":[
        {
            "category":"Food & Beverages",
            "subcategory":"Groceries & Convenience Stores",
            "type":"Retail Goods"
        }
    ],
    "sg:phone":"+1 478 864 2766",
    "sg:postcode":"31096",
    "sg:province":"GA",
    "wof:name":"Amee's Quick Stop",
    "wof:placetype":"venue"
},
  "geometry": {"coordinates":[-82.71968099999999,32.725854],"type":"Point"}
}