{
  "type": "Feature",
  "properties": {
    "iso:country":"US",
    "sg:address":"2395 Wall St SE",
    "sg:city":"Conyers",
    "sg:classifiers":[
        {
            "category":"Insurance",
            "subcategory":"Insurance Agent",
            "type":"Services"
        },
        {
            "category":"Insurance",
            "subcategory":"Hazard Insurance",
            "type":"Services"
        },
        {
            "category":"Insurance",
            "subcategory":"Title Insurance",
            "type":"Services"
        },
        {
            "category":"Insurance",
            "subcategory":"Life Insurance",
            "type":"Services"
        }
    ],
    "sg:phone":"+1 770 922 4220",
    "sg:postcode":"30013",
    "sg:province":"GA",
    "sg:tags":[
        "business",
        "auto",
        "commercial",
        "homeowner",
        "motorcycle",
        "renter"
    ],
    "wof:name":"Allstate Insurance Company - Sean Ellerbee Inc",
    "wof:placetype":"venue"
},
  "geometry": {"coordinates":[-83.980428,33.62547],"type":"Point"}
}