{
  "type": "Feature",
  "properties": {
    "addr:full":"3425 Buford Dr Buford GA 30519",
    "addr:housenumber":"3425",
    "addr:postcode":"30519",
    "addr:street":"Buford Dr",
    "iso:country":"US",
    "sg:address":"3425 Buford Dr",
    "sg:city":"Buford",
    "sg:classifiers":[
        {
            "category":"Health Services",
            "subcategory":"Health Practitioner",
            "type":"Services"
        }
    ],
    "sg:phone":"+1 770 945 1045",
    "sg:postcode":"30519",
    "sg:province":"GA",
    "sg:tags":[
        "therapy",
        "physical"
    ],
    "wof:name":"Rehab South",
    "wof:placetype":"venue"
},
  "geometry": {"coordinates":[-83.98368499999999,34.075158],"type":"Point"}
}