{
  "type": "Feature",
  "properties": {
    "iso:country":"US",
    "sg:address":"321 Pharr Rd NE",
    "sg:city":"Atlanta",
    "sg:classifiers":[
        {
            "category":"Shopping",
            "subcategory":"Used Merchandise",
            "type":"Retail Goods"
        },
        {
            "category":"Shopping",
            "subcategory":"Clothing, Apparel, & Fashions",
            "type":"Retail Goods"
        }
    ],
    "sg:phone":"+1 404 261 7519",
    "sg:postcode":"30305",
    "sg:province":"GA",
    "sg:tags":[
        "shop",
        "consignment",
        "wear"
    ],
    "wof:name":"Sweet Repeats",
    "wof:placetype":"venue"
},
  "geometry": {"coordinates":[-84.376847,33.836953],"type":"Point"}
}