{
  "type": "Feature",
  "properties": {
    "addr:full":"2332 Merrymount Dr Suwanee GA 30024",
    "addr:housenumber":"2332",
    "addr:postcode":"30024",
    "addr:street":"Merrymount Dr",
    "iso:country":"US",
    "sg:address":"2332 Merrymount Dr",
    "sg:city":"Suwanee",
    "sg:classifiers":[
        {
            "category":"Wholesale",
            "subcategory":"Durable Goods & Equipment",
            "type":"Manufacturing & Wholesale Goods"
        }
    ],
    "sg:phone":"+1 770 962 9827",
    "sg:postcode":"30024",
    "sg:province":"GA",
    "wof:name":"Dawsonville Supply Co Inc",
    "wof:placetype":"venue"
},
  "geometry": {"coordinates":[-84.027412,34.011638],"type":"Point"}
}