{
  "type": "Feature",
  "properties": {
    "addr:full":"2296 Hosea L Williams Dr NE Atlanta GA 30317",
    "addr:housenumber":"2296",
    "addr:postcode":"30317",
    "addr:street":"Hosea L Williams Dr Ne",
    "iso:country":"US",
    "sg:address":"2296 Hosea L Williams Dr NE",
    "sg:city":"Atlanta",
    "sg:classifiers":[
        {
            "category":"Retail",
            "subcategory":"Auto Repair",
            "type":"Services"
        }
    ],
    "sg:phone":"+1 404 371 4393",
    "sg:postcode":"30317",
    "sg:province":"GA",
    "sg:tags":[
        "general"
    ],
    "wof:name":"Convenient Car Care Club",
    "wof:placetype":"venue"
},
  "geometry": {"coordinates":[-84.31303200000001,33.751159],"type":"Point"}
}