{
  "type": "Feature",
  "properties": {
    "addr:full":"931 N Tennessee St Cartersville GA 30120",
    "addr:housenumber":"931",
    "addr:postcode":"30120",
    "addr:street":"N Tennessee St",
    "iso:country":"US",
    "sg:address":"931 N Tennessee St",
    "sg:city":"Cartersville",
    "sg:classifiers":[
        {
            "category":"Health Services",
            "subcategory":"Clinic",
            "type":"Services"
        },
        {
            "category":"Health Services",
            "subcategory":"Chiropractor",
            "type":"Services"
        }
    ],
    "sg:phone":"+1 770 387 1144",
    "sg:postcode":"30120",
    "sg:province":"GA",
    "sg:tags":[
        "chiropractic"
    ],
    "wof:name":"Kalb, Erin DC",
    "wof:placetype":"venue"
},
  "geometry": {"coordinates":[-84.795418,34.187389],"type":"Point"}
}