{
  "type": "Feature",
  "properties": {
    "iso:country":"US",
    "sg:address":"2773 Evans Mill Rd",
    "sg:city":"Lithonia",
    "sg:classifiers":[
        {
            "category":"Restaurant",
            "type":"Food & Drink"
        }
    ],
    "sg:phone":"+1 770 482 2331",
    "sg:postcode":"30058",
    "sg:province":"GA",
    "sg:website":"www.wendys.com",
    "wof:name":"Wendy's Old Fashioned Hamburgers",
    "wof:placetype":"venue"
},
  "geometry": {"coordinates":[-84.114799,33.704399],"type":"Point"}
}