{
  "type": "Feature",
  "properties": {
    "iso:country":"US",
    "sg:address":"160 Bud Hardy Rd SE",
    "sg:city":"Calhoun",
    "sg:classifiers":[
        {
            "category":"Wholesale",
            "subcategory":"Vending Machines",
            "type":"Manufacturing & Wholesale Goods"
        }
    ],
    "sg:phone":"+1 706 625 8817",
    "sg:postcode":"30701",
    "sg:province":"GA",
    "sg:tags":[
        "operator",
        "repair",
        "machinery-rebuild"
    ],
    "wof:name":"Blalock's Machine Shop",
    "wof:placetype":"venue"
},
  "geometry": {"coordinates":[-84.82892099999999,34.446138],"type":"Point"}
}