{
  "type": "Feature",
  "properties": {
    "iso:country":"US",
    "sg:address":"1211 Moreland Avenue SE",
    "sg:city":"Atlanta",
    "sg:classifiers":[
        {
            "category":"Restaurant",
            "type":"Food & Drink"
        }
    ],
    "sg:phone":"+1 404 627 0808",
    "sg:postcode":"30316",
    "sg:province":"GA",
    "wof:name":"Huddle House",
    "wof:placetype":"venue"
},
  "geometry": {"coordinates":[-84.349453,33.721806],"type":"Point"}
}