{
  "type": "Feature",
  "properties": {
    "iso:country":"US",
    "sg:address":"1500 Huntcliff Village Ct",
    "sg:city":"Atlanta",
    "sg:classifiers":[
        {
            "category":"Real Estate",
            "subcategory":"Real Estate Operator",
            "type":"Services"
        }
    ],
    "sg:phone":"+1 770 587 0999",
    "sg:postcode":"30350",
    "sg:province":"GA",
    "sg:tags":[
        "apartment"
    ],
    "wof:name":"Huntcliff Village Apartments",
    "wof:placetype":"venue"
},
  "geometry": {"coordinates":[-84.351005,33.99913],"type":"Point"}
}