{
  "type": "Feature",
  "properties": {
    "iso:country":"US",
    "sg:address":"4119 Oates Ave",
    "sg:city":"Columbus",
    "sg:classifiers":[
        {
            "category":"Organizations",
            "subcategory":"Religious Organization",
            "type":"Services"
        }
    ],
    "sg:phone":"+1 706 324 3377",
    "sg:postcode":"31904",
    "sg:province":"GA",
    "wof:name":"Oates Avenue Baptist Church",
    "wof:placetype":"venue"
},
  "geometry": {"coordinates":[-84.98410800000001,32.501673],"type":"Point"}
}