{
  "type": "Feature",
  "properties": {
    "addr:full":"541 Londonberry Rd NW Atlanta GA 30327",
    "addr:housenumber":"541",
    "addr:postcode":"30327",
    "addr:street":"Londonberry Rd Nw",
    "iso:country":"US",
    "sg:address":"541 Londonberry Rd NW",
    "sg:city":"Atlanta",
    "sg:classifiers":[
        {
            "category":"Building & Trades",
            "subcategory":"Construction",
            "type":"Services"
        }
    ],
    "sg:phone":"+1 404 255 9414",
    "sg:postcode":"30327",
    "sg:province":"GA",
    "sg:tags":[
        "designer"
    ],
    "wof:name":"Silvester Associates",
    "wof:placetype":"venue"
},
  "geometry": {"coordinates":[-84.405817,33.89732],"type":"Point"}
}