{
  "type": "Feature",
  "properties": {
    "iso:country":"US",
    "sg:address":"4825 Battlefield Pkwy",
    "sg:city":"Ringgold",
    "sg:classifiers":[
        {
            "category":"Restaurant",
            "type":"Food & Drink"
        }
    ],
    "sg:phone":"+1 706 866 3311",
    "sg:postcode":"30736",
    "sg:province":"GA",
    "sg:tags":[
        "mexican"
    ],
    "wof:name":"Tres Amigos Mexican Restaurant",
    "wof:placetype":"venue"
},
  "geometry": {"coordinates":[-85.186986,34.933021],"type":"Point"}
}