{
  "type": "Feature",
  "properties": {
    "addr:full":"1481 Dean Forest Rd Savannah GA 31405",
    "addr:housenumber":"1481",
    "addr:postcode":"31405",
    "addr:street":"Dean Forest Rd",
    "iso:country":"US",
    "sg:address":"1481 Dean Forest Rd",
    "sg:city":"Savannah",
    "sg:classifiers":[
        {
            "category":"Professional",
            "subcategory":"Engineering",
            "type":"Services"
        }
    ],
    "sg:phone":"+1 912 790 0123",
    "sg:postcode":"31405",
    "sg:province":"GA",
    "sg:tags":[
        "engineer"
    ],
    "wof:name":"Collins Engineers Inc",
    "wof:placetype":"venue"
},
  "geometry": {"coordinates":[-81.20483299999999,32.068259],"type":"Point"}
}