{
  "type": "Feature",
  "properties": {
    "iso:country":"US",
    "sg:address":"7180 Fawn Lake Dr",
    "sg:city":"Suwanee",
    "sg:classifiers":[
        {
            "category":"Manufacturing",
            "subcategory":"Chemicals & Compounds",
            "type":"Manufacturing & Wholesale Goods"
        }
    ],
    "sg:phone":"+1 770 888 4070",
    "sg:postcode":"30005",
    "sg:province":"GA",
    "sg:tags":[
        "product",
        "mfg"
    ],
    "wof:name":"Carboline Company",
    "wof:placetype":"venue"
},
  "geometry": {"coordinates":[-84.173748,34.076148],"type":"Point"}
}