{
  "type": "Feature",
  "properties": {
    "iso:country":"US",
    "sg:address":"2865 Dahlonega Hwy",
    "sg:city":"Cumming",
    "sg:classifiers":[
        {
            "category":"Wholesale",
            "subcategory":"Machinery & Supplies",
            "type":"Manufacturing & Wholesale Goods"
        }
    ],
    "sg:phone":"+1 770 887 1969",
    "sg:postcode":"30040",
    "sg:province":"GA",
    "sg:tags":[
        "equipment",
        "material",
        "handling"
    ],
    "wof:name":"Southern Lift Equip Corp Inc",
    "wof:placetype":"venue"
},
  "geometry": {"coordinates":[-84.102323,34.267869],"type":"Point"}
}