{
  "type": "Feature",
  "properties": {
    "addr:full":"455 North Ave Atlanta GA 30354",
    "addr:housenumber":"455",
    "addr:postcode":"30354",
    "addr:street":"North Ave",
    "iso:country":"US",
    "sg:address":"455 North Ave",
    "sg:city":"Atlanta",
    "sg:classifiers":[
        {
            "category":"Shopping",
            "subcategory":"Pharmacy",
            "type":"Retail Goods"
        }
    ],
    "sg:phone":"+1 404 876 6655",
    "sg:postcode":"30354",
    "sg:province":"GA",
    "wof:name":"CVS",
    "wof:placetype":"venue"
},
  "geometry": {"coordinates":[-84.403491,33.665356],"type":"Point"}
}