{
  "type": "Feature",
  "properties": {
    "addr:full":"163 Cumberland Crossing SE Smyrna GA 30080",
    "addr:housenumber":"163",
    "addr:postcode":"30080",
    "addr:street":"Cumberland Crossing Se",
    "iso:country":"US",
    "sg:address":"163 Cumberland Crossing SE",
    "sg:city":"Smyrna",
    "sg:classifiers":[
        {
            "category":"Health Services",
            "subcategory":"Clinic",
            "type":"Services"
        }
    ],
    "sg:phone":"+1 404 798 6214",
    "sg:postcode":"30080",
    "sg:province":"GA",
    "sg:tags":[
        "medical"
    ],
    "sg:website":"www.myspautopia.com/default.htm",
    "wof:name":"Spa Utopia",
    "wof:placetype":"venue"
},
  "geometry": {"coordinates":[-84.480963,33.879131],"type":"Point"}
}