{
  "type": "Feature",
  "properties": {
    "iso:country":"US",
    "sg:address":"197 Brighton Rd NE",
    "sg:city":"Atlanta",
    "sg:classifiers":[
        {
            "category":"Professional",
            "type":"Services"
        }
    ],
    "sg:phone":"+1 404 352 3571",
    "sg:postcode":"30309",
    "sg:province":"GA",
    "wof:name":"Amy Mattingly",
    "wof:placetype":"venue"
},
  "geometry": {"coordinates":[-84.386252,33.810712],"type":"Point"}
}