{
  "type": "Feature",
  "properties": {
    "iso:country":"US",
    "sg:address":"115 S Elm St",
    "sg:city":"Adel",
    "sg:classifiers":[
        {
            "category":"Real Estate",
            "subcategory":"Real Estate Agent",
            "type":"Services"
        }
    ],
    "sg:phone":"+1 229 896 4372",
    "sg:postcode":"31620",
    "sg:province":"GA",
    "wof:name":"Bruce Griner Real Estate",
    "wof:placetype":"venue"
},
  "geometry": {"coordinates":[-83.432985,31.134277],"type":"Point"}
}