{
  "type": "Feature",
  "properties": {
    "addr:full":"1635 Pirkle Rd Norcross GA 30093",
    "addr:housenumber":"1635",
    "addr:postcode":"30093",
    "addr:street":"Pirkle Rd",
    "iso:country":"US",
    "sg:address":"1635 Pirkle Rd",
    "sg:city":"Norcross",
    "sg:classifiers":[
        {
            "category":"Home & Garden",
            "subcategory":"Building Materials",
            "type":"Retail Goods"
        }
    ],
    "sg:phone":"+1 770 931 2244",
    "sg:postcode":"30093",
    "sg:province":"GA",
    "sg:tags":[
        "marble-natural",
        "top",
        "counter",
        "granite"
    ],
    "sg:website":"http://www.andrewsassociates.net",
    "wof:name":"A A Marble & Granite LLC",
    "wof:placetype":"venue"
},
  "geometry": {"coordinates":[-84.189165,33.912555],"type":"Point"}
}