{
  "type": "Feature",
  "properties": {
    "addr:full":"3965 Lawrenceville Hwy Tucker GA 30084",
    "addr:housenumber":"3965",
    "addr:postcode":"30084",
    "addr:street":"Lawrenceville Hwy",
    "iso:country":"US",
    "sg:address":"3965 Lawrenceville Hwy",
    "sg:city":"Tucker",
    "sg:classifiers":[
        {
            "category":"Recreation",
            "subcategory":"Dance Hall",
            "type":"Entertainment"
        }
    ],
    "sg:phone":"+1 770 934 3475",
    "sg:postcode":"30084",
    "sg:province":"GA",
    "sg:tags":[
        "club"
    ],
    "sg:website":"www.nocturnalatlanta.com",
    "wof:name":"Nocturnal Dance Lounge",
    "wof:placetype":"venue"
},
  "geometry": {"coordinates":[-84.219345,33.84996],"type":"Point"}
}