{
  "type": "Feature",
  "properties": {
    "addr:full":"114 State Rte 61 Villa Rica GA 30180",
    "addr:housenumber":"114",
    "addr:postcode":"30180",
    "addr:street":"State Rte 61",
    "iso:country":"US",
    "sg:address":"114 State Rte 61",
    "sg:city":"Villa Rica",
    "sg:classifiers":[
        {
            "category":"Restaurant",
            "type":"Food & Drink"
        }
    ],
    "sg:phone":"+1 770 459 8059",
    "sg:postcode":"30180",
    "sg:province":"GA",
    "wof:name":"Subway Sandwiches & Salads",
    "wof:placetype":"venue"
},
  "geometry": {"coordinates":[-84.922518,33.737047],"type":"Point"}
}