{
  "type": "Feature",
  "properties": {
    "iso:country":"US",
    "sg:address":"1175 Lyndhurst Way",
    "sg:city":"Roswell",
    "sg:classifiers":[
        {
            "category":"Professional",
            "subcategory":"Computer Services",
            "type":"Services"
        }
    ],
    "sg:phone":"+1 770 594 9544",
    "sg:postcode":"30075",
    "sg:province":"GA",
    "sg:website":"www.fiscalcontrol.com",
    "wof:name":"Direct Sight Networks Inc",
    "wof:placetype":"venue"
},
  "geometry": {"coordinates":[-84.377189,34.052312],"type":"Point"}
}