{
  "type": "Feature",
  "properties": {
    "iso:country":"US",
    "sg:address":"156 Parker St NW",
    "sg:city":"Atlanta",
    "sg:classifiers":[
        {
            "category":"Organizations",
            "subcategory":"Religious Organization",
            "type":"Services"
        }
    ],
    "sg:phone":"+1 404 881 1291",
    "sg:postcode":"30313",
    "sg:province":"GA",
    "sg:tags":[
        "church"
    ],
    "wof:name":"Clark Howell Techwood Baptist",
    "wof:placetype":"venue"
},
  "geometry": {"coordinates":[-84.39286300000001,33.765888],"type":"Point"}
}