{
  "type": "Feature",
  "properties": {
    "addr:full":"108 E Macedonia Church Rd Oxford GA 30054",
    "addr:housenumber":"108",
    "addr:postcode":"30054",
    "addr:street":"E Macedonia Church Rd",
    "iso:country":"US",
    "sg:address":"108 E Macedonia Church Rd",
    "sg:city":"Oxford",
    "sg:classifiers":[
        {
            "category":"Organizations",
            "subcategory":"Religious Organization",
            "type":"Services"
        }
    ],
    "sg:phone":"+1 770 786 4336",
    "sg:postcode":"30054",
    "sg:province":"GA",
    "sg:tags":[
        "church"
    ],
    "wof:name":"Macedonia Baptist Church",
    "wof:placetype":"venue"
},
  "geometry": {"coordinates":[-83.847291,33.669937],"type":"Point"}
}