{
  "type": "Feature",
  "properties": {
    "iso:country":"US",
    "sg:address":"3176 Marjan Dr",
    "sg:city":"Atlanta",
    "sg:classifiers":[
        {
            "category":"Shopping",
            "subcategory":"Computers & Home Electronics",
            "type":"Retail Goods"
        }
    ],
    "sg:phone":"+1 770 986 0095",
    "sg:postcode":"30340",
    "sg:province":"GA",
    "sg:tags":[
        "software",
        "accessory"
    ],
    "wof:name":"Moore Wallace North Amer Inc",
    "wof:placetype":"venue"
},
  "geometry": {"coordinates":[-84.268108,33.881668],"type":"Point"}
}