{
  "type": "Feature",
  "properties": {
    "addr:full":"225 Ponce De Leon Avenue NE Atlanta GA 30308",
    "addr:housenumber":"225",
    "addr:postcode":"30308",
    "addr:street":"Ponce De Leon Avenue Ne",
    "iso:country":"US",
    "sg:address":"225 Ponce De Leon Avenue NE",
    "sg:city":"Atlanta",
    "sg:classifiers":[
        {
            "category":"Shopping",
            "subcategory":"Pharmacy",
            "type":"Retail Goods"
        }
    ],
    "sg:phone":"+1 404 373 0241",
    "sg:postcode":"30308",
    "sg:province":"GA",
    "sg:tags":[
        "drugstore"
    ],
    "sg:website":"www.cvs.com",
    "wof:name":"Cvs Pharmacy",
    "wof:placetype":"venue"
},
  "geometry": {"coordinates":[-84.38002299999999,33.772687],"type":"Point"}
}