{
  "type": "Feature",
  "properties": {
    "iso:country":"US",
    "sg:address":"4757 Forest Valley Pl",
    "sg:city":"Marietta",
    "sg:classifiers":[
        {
            "category":"Professional",
            "subcategory":"Lawyer & Legal Services",
            "type":"Services"
        }
    ],
    "sg:phone":"+1 770 643 2755",
    "sg:postcode":"30066",
    "sg:province":"GA",
    "wof:name":"McCalla Raymer",
    "wof:placetype":"venue"
},
  "geometry": {"coordinates":[-84.469973,34.063589],"type":"Point"}
}