{
  "type": "Feature",
  "properties": {
    "addr:full":"975 Cobb Place Blvd NW # 303 Kennesaw GA 30144",
    "addr:housenumber":"975",
    "addr:postcode":"30144",
    "addr:street":"Cobb Place Blvd Nw # 303",
    "iso:country":"US",
    "sg:address":"975 Cobb Place Blvd NW # 303",
    "sg:city":"Kennesaw",
    "sg:classifiers":[
        {
            "category":"Building & Trades",
            "subcategory":"Electrical",
            "type":"Services"
        }
    ],
    "sg:phone":"+1 706 625 1111",
    "sg:postcode":"30144",
    "sg:province":"GA",
    "sg:tags":[
        "electrician"
    ],
    "sg:website":"http://www.southtel.net",
    "wof:name":"South Tel Communications",
    "wof:placetype":"venue"
},
  "geometry": {"coordinates":[-84.582427,34.009667],"type":"Point"}
}