{
  "type": "Feature",
  "properties": {
    "iso:country":"US",
    "sg:address":"4872 Hickory Flat Hwy",
    "sg:city":"Canton",
    "sg:classifiers":[
        {
            "category":"Real Estate",
            "subcategory":"Developer",
            "type":"Services"
        }
    ],
    "sg:phone":"+1 770 345 5531",
    "sg:postcode":"30115",
    "sg:province":"GA",
    "sg:tags":[
        "mobile",
        "home"
    ],
    "wof:name":"Bennie Darnell Mobile Homes",
    "wof:placetype":"venue"
},
  "geometry": {"coordinates":[-84.43805500000001,34.186465],"type":"Point"}
}