{
  "type": "Feature",
  "properties": {
    "iso:country":"US",
    "sg:address":"1641 Spring Rd SE",
    "sg:city":"Smyrna",
    "sg:classifiers":[
        {
            "category":"Restaurant",
            "type":"Food & Drink"
        }
    ],
    "sg:phone":"+1 770 432 3809",
    "sg:postcode":"30080",
    "sg:province":"GA",
    "wof:name":"Dairy Queen",
    "wof:placetype":"venue"
},
  "geometry": {"coordinates":[-84.504898,33.882301],"type":"Point"}
}