{
  "type": "Feature",
  "properties": {
    "iso:country":"US",
    "sg:address":"1929 Wee Kirk Rd SE",
    "sg:city":"Atlanta",
    "sg:classifiers":[
        {
            "category":"Shopping",
            "subcategory":"Music",
            "type":"Retail Goods"
        }
    ],
    "sg:phone":"+1 770 655 4422",
    "sg:postcode":"30316",
    "sg:province":"GA",
    "wof:name":"Dirt South Rythmes",
    "wof:placetype":"venue"
},
  "geometry": {"coordinates":[-84.310377,33.699739],"type":"Point"}
}