{
  "type": "Feature",
  "properties": {
    "iso:country":"US",
    "sg:address":"1647 Emory Place Dr NE",
    "sg:city":"Atlanta",
    "sg:classifiers":[
        {
            "category":"Arena",
            "subcategory":"Sports Club",
            "type":"Entertainment"
        }
    ],
    "sg:phone":"+1 404 982 1640",
    "sg:postcode":"30329",
    "sg:province":"GA",
    "sg:tags":[
        "management",
        "corporate",
        "event"
    ],
    "wof:name":"Outsource Events",
    "wof:placetype":"venue"
},
  "geometry": {"coordinates":[-84.320363,33.825319],"type":"Point"}
}