{
  "type": "Feature",
  "properties": {
    "addr:full":"4810 Harris Trl NW Atlanta GA 30327",
    "addr:housenumber":"4810",
    "addr:postcode":"30327",
    "addr:street":"Harris Trl Nw",
    "iso:country":"US",
    "sg:address":"4810 Harris Trl NW",
    "sg:city":"Atlanta",
    "sg:classifiers":[
        {
            "category":"Professional",
            "subcategory":"Management & Consulting",
            "type":"Services"
        }
    ],
    "sg:phone":"+1 404 847 7072",
    "sg:postcode":"30327",
    "sg:province":"GA",
    "sg:tags":[
        "consultant",
        "business"
    ],
    "wof:name":"Red Bridge Consulting Inc",
    "wof:placetype":"venue"
},
  "geometry": {"coordinates":[-84.430933,33.882443],"type":"Point"}
}