{
  "type": "Feature",
  "properties": {
    "addr:full":"314 E College St Wrightsville GA 31096",
    "addr:housenumber":"314",
    "addr:postcode":"31096",
    "addr:street":"E College St",
    "iso:country":"US",
    "sg:address":"314 E College St",
    "sg:city":"Wrightsville",
    "sg:classifiers":[
        {
            "category":"Manufacturing",
            "subcategory":"Retail Goods",
            "type":"Manufacturing & Wholesale Goods"
        }
    ],
    "sg:phone":"+1 478 864 7799",
    "sg:postcode":"31096",
    "sg:province":"GA",
    "sg:tags":[
        "product",
        "mfg"
    ],
    "wof:name":"N Woods Water Inc",
    "wof:placetype":"venue"
},
  "geometry": {"coordinates":[-82.716255,32.728691],"type":"Point"}
}