{
  "type": "Feature",
  "properties": {
    "addr:full":"3791 Fairplay Rd Madison GA 30650",
    "addr:housenumber":"3791",
    "addr:postcode":"30650",
    "addr:street":"Fairplay Rd",
    "iso:country":"US",
    "sg:address":"3791 Fairplay Rd",
    "sg:city":"Madison",
    "sg:classifiers":[
        {
            "category":"Education",
            "subcategory":"Library",
            "type":"Public Place"
        }
    ],
    "sg:phone":"+1 706 342 3637",
    "sg:postcode":"30650",
    "sg:province":"GA",
    "wof:name":"James Alexander Branch",
    "wof:placetype":"venue"
},
  "geometry": {"coordinates":[-83.53812600000001,33.709984],"type":"Point"}
}