{
  "type": "Feature",
  "properties": {
    "addr:full":"317 Hale St Augusta GA 30901",
    "addr:housenumber":"317",
    "addr:postcode":"30901",
    "addr:street":"Hale St",
    "iso:country":"US",
    "sg:address":"317 Hale St",
    "sg:city":"Augusta",
    "sg:classifiers":[
        {
            "category":"Wholesale",
            "subcategory":"Non-durable Goods",
            "type":"Manufacturing & Wholesale Goods"
        }
    ],
    "sg:phone":"+1 706 733 9998",
    "sg:postcode":"30901",
    "sg:province":"GA",
    "sg:tags":[
        "candle"
    ],
    "wof:name":"Candle Nuts",
    "wof:placetype":"venue"
},
  "geometry": {"coordinates":[-81.96052400000001,33.46273],"type":"Point"}
}