{
  "type": "Feature",
  "properties": {
    "iso:country":"US",
    "sg:address":"1991 Claude Floyd Rd",
    "sg:city":"Bogart",
    "sg:classifiers":[
        {
            "category":"Professional",
            "type":"Services"
        }
    ],
    "sg:phone":"+1 706 769 8029",
    "sg:postcode":"30662",
    "sg:province":"GA",
    "wof:name":"Thomas Jamey",
    "wof:placetype":"venue"
},
  "geometry": {"coordinates":[-83.082482,34.260822],"type":"Point"}
}