{
  "type": "Feature",
  "properties": {
    "addr:full":"10 Wayne Davis Dr Tallapoosa GA 30176",
    "addr:housenumber":"10",
    "addr:postcode":"30176",
    "addr:street":"Wayne Davis Dr",
    "iso:country":"US",
    "sg:address":"10 Wayne Davis Dr",
    "sg:city":"Tallapoosa",
    "sg:classifiers":[
        {
            "category":"Wholesale",
            "subcategory":"Construction Materials",
            "type":"Manufacturing & Wholesale Goods"
        }
    ],
    "sg:phone":"+1 770 574 2326",
    "sg:postcode":"30176",
    "sg:province":"GA",
    "sg:tags":[
        "mixed",
        "concrete-ready"
    ],
    "sg:website":"http://www.waynedavisconcrete.com",
    "wof:name":"Wayne Davis COncrete Co",
    "wof:placetype":"venue"
},
  "geometry": {"coordinates":[-85.294214,33.761703],"type":"Point"}
}