{
  "type": "Feature",
  "properties": {
    "iso:country":"US",
    "sg:address":"112 Ennis St",
    "sg:city":"Sylvania",
    "sg:classifiers":[
        {
            "category":"Shopping",
            "subcategory":"Florist",
            "type":"Retail Goods"
        }
    ],
    "sg:phone":"+1 912 564 2708",
    "sg:postcode":"30467",
    "sg:province":"GA",
    "wof:name":"Lanier's Florist",
    "wof:placetype":"venue"
},
  "geometry": {"coordinates":[-81.637906,32.749227],"type":"Point"}
}