{
  "type": "Feature",
  "properties": {
    "addr:full":"2169 Centennial Dr Gainesville GA 30504",
    "addr:housenumber":"2169",
    "addr:postcode":"30504",
    "addr:street":"Centennial Dr",
    "iso:country":"US",
    "sg:address":"2169 Centennial Dr",
    "sg:city":"Gainesville",
    "sg:classifiers":[
        {
            "category":"Manufacturing",
            "subcategory":"Metals",
            "type":"Manufacturing & Wholesale Goods"
        },
        {
            "category":"Building & Trades",
            "subcategory":"Construction",
            "type":"Services"
        }
    ],
    "sg:phone":"+1 770 538 6000",
    "sg:postcode":"30504",
    "sg:province":"GA",
    "sg:tags":[
        "fabricator",
        "structural",
        "fabrication",
        "business",
        "mfg"
    ],
    "wof:name":"Laser Craft Technologies Inc",
    "wof:placetype":"venue"
},
  "geometry": {"coordinates":[-83.86071099999999,34.264773],"type":"Point"}
}