{
  "type": "Feature",
  "properties": {
    "addr:full":"290 Howell Dr SW Atlanta GA 30331",
    "addr:housenumber":"290",
    "addr:postcode":"30331",
    "addr:street":"Howell Dr Sw",
    "iso:country":"US",
    "sg:address":"290 Howell Dr SW",
    "sg:city":"Atlanta",
    "sg:classifiers":[
        {
            "category":"Building & Trades",
            "subcategory":"Construction",
            "type":"Services"
        }
    ],
    "sg:phone":"+1 770 969 3294",
    "sg:postcode":"30331",
    "sg:province":"GA",
    "sg:tags":[
        "house"
    ],
    "wof:name":"Larry S Remodeling",
    "wof:placetype":"venue"
},
  "geometry": {"coordinates":[-84.506683,33.753352],"type":"Point"}
}