{
  "type": "Feature",
  "properties": {
    "iso:country":"US",
    "sg:address":"425 Atlanta Rd",
    "sg:city":"Gainesville",
    "sg:classifiers":[
        {
            "category":"Shopping",
            "subcategory":"Jewelry",
            "type":"Retail Goods"
        }
    ],
    "sg:phone":"+1 770 534 5553",
    "sg:postcode":"30501",
    "sg:province":"GA",
    "wof:name":"Royal Jewelry",
    "wof:placetype":"venue"
},
  "geometry": {"coordinates":[-83.83934000000001,34.281804],"type":"Point"}
}