{
  "type": "Feature",
  "properties": {
    "iso:country":"US",
    "sg:address":"850 Dogwood Rd",
    "sg:city":"Lawrenceville",
    "sg:classifiers":[
        {
            "category":"Shopping",
            "subcategory":"Musical Instruments",
            "type":"Retail Goods"
        }
    ],
    "sg:phone":"+1 770 982 8299",
    "sg:postcode":"30044",
    "sg:province":"GA",
    "wof:name":"Whipkey's Music Inc",
    "wof:placetype":"venue"
},
  "geometry": {"coordinates":[-84.060844,33.888655],"type":"Point"}
}