{
  "type": "Feature",
  "properties": {
    "iso:country":"US",
    "sg:address":"75 Log Cabin Rd",
    "sg:city":"Dallas",
    "sg:classifiers":[
        {
            "category":"Building & Trades",
            "subcategory":"Plumbing",
            "type":"Services"
        }
    ],
    "sg:phone":"+1 404 202 0008",
    "sg:postcode":"30185",
    "sg:province":"GA",
    "sg:tags":[
        "contractor"
    ],
    "wof:name":"Sweeden Process Heating & Tech",
    "wof:placetype":"venue"
},
  "geometry": {"coordinates":[-84.923112,33.522955],"type":"Point"}
}