{
  "type": "Feature",
  "properties": {
    "iso:country":"US",
    "sg:address":"4499 Broadway",
    "sg:city":"Macon",
    "sg:classifiers":[
        {
            "category":"Autos & Motor Vehicles",
            "subcategory":"Automobile Sales",
            "type":"Retail Goods"
        }
    ],
    "sg:phone":"+1 478 781 0585",
    "sg:postcode":"31206",
    "sg:province":"GA",
    "sg:tags":[
        "car",
        "dealer"
    ],
    "wof:name":"Freeway Auto Credit",
    "wof:placetype":"venue"
},
  "geometry": {"coordinates":[-83.65478899999999,32.780996],"type":"Point"}
}