{
  "type": "Feature",
  "properties": {
    "iso:country":"US",
    "sg:address":"1979 Lakeside Pkwy",
    "sg:city":"Tucker",
    "sg:classifiers":[
        {
            "category":"Banks & Credit Unions",
            "subcategory":"Investment Brokerage",
            "type":"Services"
        }
    ],
    "sg:phone":"+1 770 492 8950",
    "sg:postcode":"30084",
    "sg:province":"GA",
    "sg:tags":[
        "advisory",
        "financial"
    ],
    "wof:name":"Presidential Financial",
    "wof:placetype":"venue"
},
  "geometry": {"coordinates":[-84.239446,33.838981],"type":"Point"}
}