{
  "type": "Feature",
  "properties": {
    "addr:full":"3453 Old Norcross Rd Duluth GA 30096",
    "addr:housenumber":"3453",
    "addr:postcode":"30096",
    "addr:street":"Old Norcross Rd",
    "iso:country":"US",
    "sg:address":"3453 Old Norcross Rd",
    "sg:city":"Duluth",
    "sg:classifiers":[
        {
            "category":"Autos & Motor Vehicles",
            "subcategory":"Auto Supplies",
            "type":"Retail Goods"
        }
    ],
    "sg:phone":"+1 404 762 4944",
    "sg:postcode":"30096",
    "sg:province":"GA",
    "wof:name":"Kauffman Tire Inc",
    "wof:placetype":"venue"
},
  "geometry": {"coordinates":[-84.13571,33.965644],"type":"Point"}
}