{
  "type": "Feature",
  "properties": {
    "iso:country":"US",
    "sg:address":"309 2nd Ave NE",
    "sg:city":"Cairo",
    "sg:classifiers":[
        {
            "category":"Manufacturing",
            "subcategory":"Food",
            "type":"Manufacturing & Wholesale Goods"
        }
    ],
    "sg:phone":"+1 229 377 3422",
    "sg:postcode":"39828",
    "sg:province":"GA",
    "sg:tags":[
        "ice"
    ],
    "wof:name":"M & M Ice & Cold Storage",
    "wof:placetype":"venue"
},
  "geometry": {"coordinates":[-84.202754,30.87825],"type":"Point"}
}