{
  "type": "Feature",
  "properties": {
    "addr:full":"5902 Hwy 41 Ringgold GA 30736",
    "addr:housenumber":"5902",
    "addr:postcode":"30736",
    "addr:street":"Hwy 41",
    "iso:country":"US",
    "sg:address":"5902 Hwy 41",
    "sg:city":"Ringgold",
    "sg:classifiers":[
        {
            "category":"Professional",
            "subcategory":"Employment Agencies",
            "type":"Services"
        }
    ],
    "sg:phone":"+1 706 965 9850",
    "sg:postcode":"30736",
    "sg:province":"GA",
    "sg:tags":[
        "opportunity"
    ],
    "wof:name":"Snelling Personnel Svc",
    "wof:placetype":"venue"
},
  "geometry": {"coordinates":[-85.136855,34.932981],"type":"Point"}
}