{
  "type": "Feature",
  "properties": {
    "iso:country":"US",
    "sg:address":"200 Hampstead Ave",
    "sg:city":"Savannah",
    "sg:classifiers":[
        {
            "category":"Real Estate",
            "subcategory":"Real Estate Operator",
            "type":"Services"
        }
    ],
    "sg:phone":"+1 912 356 5656",
    "sg:postcode":"31405",
    "sg:province":"GA",
    "sg:tags":[
        "apartment"
    ],
    "wof:name":"Hampstead Oaks Apts",
    "wof:placetype":"venue"
},
  "geometry": {"coordinates":[-81.11631800000001,32.026699],"type":"Point"}
}