{
  "type": "Feature",
  "properties": {
    "addr:full":"3914 Wabash Ln Ellenwood GA 30294",
    "addr:housenumber":"3914",
    "addr:postcode":"30294",
    "addr:street":"Wabash Ln",
    "iso:country":"US",
    "sg:address":"3914 Wabash Ln",
    "sg:city":"Ellenwood",
    "sg:classifiers":[
        {
            "category":"Manufacturing",
            "subcategory":"Printing",
            "type":"Manufacturing & Wholesale Goods"
        }
    ],
    "sg:phone":"+1 770 981 2756",
    "sg:postcode":"30294",
    "sg:province":"GA",
    "sg:tags":[
        "printer"
    ],
    "wof:name":"Munson J Printing",
    "wof:placetype":"venue"
},
  "geometry": {"coordinates":[-84.248661,33.664375],"type":"Point"}
}