{
  "type": "Feature",
  "properties": {
    "addr:full":"276 Glynn St N Fayetteville GA 30214",
    "addr:housenumber":"276",
    "addr:postcode":"30214",
    "addr:street":"Glynn St N",
    "iso:country":"US",
    "sg:address":"276 Glynn St N",
    "sg:city":"Fayetteville",
    "sg:classifiers":[
        {
            "category":"Retail",
            "subcategory":"Auto Repair",
            "type":"Services"
        }
    ],
    "sg:phone":"+1 678 817 6335",
    "sg:postcode":"30214",
    "sg:province":"GA",
    "sg:tags":[
        "muffler",
        "exhaust",
        "system"
    ],
    "wof:name":"Just Brakes",
    "wof:placetype":"venue"
},
  "geometry": {"coordinates":[-84.455186,33.453209],"type":"Point"}
}