{
  "type": "Feature",
  "properties": {
    "addr:full":"445 Winn Way Decatur GA 30030",
    "addr:housenumber":"445",
    "addr:postcode":"30030",
    "addr:street":"Winn Way",
    "iso:country":"US",
    "sg:address":"445 Winn Way",
    "sg:city":"Decatur",
    "sg:classifiers":[
        {
            "category":"Professional",
            "subcategory":"Business Services",
            "type":"Services"
        }
    ],
    "sg:phone":"+1 404 294 3789",
    "sg:postcode":"30030",
    "sg:province":"GA",
    "sg:tags":[
        "medical",
        "administration"
    ],
    "sg:website":"http://www.dekalbpubsafety.com",
    "wof:name":"County Of Dekalb",
    "wof:placetype":"venue"
},
  "geometry": {"coordinates":[-84.279391,33.788836],"type":"Point"}
}