{
  "type": "Feature",
  "properties": {
    "addr:full":"113 W Shotwell St Bainbridge GA 39819",
    "addr:housenumber":"113",
    "addr:postcode":"39819",
    "addr:street":"W Shotwell St",
    "iso:country":"US",
    "sg:address":"113 W Shotwell St",
    "sg:city":"Bainbridge",
    "sg:classifiers":[
        {
            "category":"Real Estate",
            "subcategory":"Real Estate Agent",
            "type":"Services"
        }
    ],
    "sg:phone":"+1 229 243 9200",
    "sg:postcode":"39819",
    "sg:province":"GA",
    "wof:name":"ERA",
    "wof:placetype":"venue"
},
  "geometry": {"coordinates":[-84.577263,30.903895],"type":"Point"}
}