{
  "type": "Feature",
  "properties": {
    "iso:country":"US",
    "sg:address":"396 Baxter St",
    "sg:city":"Athens",
    "sg:classifiers":[
        {
            "category":"Retail",
            "subcategory":"Laundry & Dry Cleaning",
            "type":"Services"
        }
    ],
    "sg:phone":"+1 706 227 6338",
    "sg:postcode":"30605",
    "sg:province":"GA",
    "sg:tags":[
        "laundries-self"
    ],
    "wof:name":"Sudz Laundry",
    "wof:placetype":"venue"
},
  "geometry": {"coordinates":[-83.382402,33.950458],"type":"Point"}
}