{
  "type": "Feature",
  "properties": {
    "iso:country":"US",
    "sg:address":"119 Ridley Ave",
    "sg:city":"La Grange",
    "sg:classifiers":[
        {
            "category":"Professional",
            "subcategory":"Lawyer & Legal Services",
            "type":"Services"
        }
    ],
    "sg:phone":"+1 706 812 0200",
    "sg:postcode":"30240",
    "sg:province":"GA",
    "wof:name":"Patterson & Patterson Inc",
    "wof:placetype":"venue"
},
  "geometry": {"coordinates":[-85.031154,33.040515],"type":"Point"}
}