{
  "type": "Feature",
  "properties": {
    "iso:country":"US",
    "sg:address":"1255 Veterans Memorial Pkwy SW",
    "sg:city":"Mableton",
    "sg:classifiers":[
        {
            "category":"Wholesale",
            "subcategory":"Non-durable Goods",
            "type":"Manufacturing & Wholesale Goods"
        }
    ],
    "sg:phone":"+1 770 732 1899",
    "sg:postcode":"30126",
    "sg:province":"GA",
    "sg:tags":[
        "art",
        "framed"
    ],
    "wof:name":"Crown Arts",
    "wof:placetype":"venue"
},
  "geometry": {"coordinates":[-84.58814700000001,33.817387],"type":"Point"}
}