{
  "type": "Feature",
  "properties": {
    "iso:country":"US",
    "sg:address":"1520 Quacco Rd",
    "sg:city":"Pooler",
    "sg:classifiers":[
        {
            "category":"Personal",
            "subcategory":"Beauty Salon",
            "type":"Services"
        }
    ],
    "sg:phone":"+1 912 927 2676",
    "sg:postcode":"31322",
    "sg:province":"GA",
    "sg:tags":[
        "shop"
    ],
    "wof:name":"Born Again",
    "wof:placetype":"venue"
},
  "geometry": {"coordinates":[-81.26617899999999,32.051932],"type":"Point"}
}