{
  "type": "Feature",
  "properties": {
    "iso:country":"US",
    "sg:address":"3180 Stone Mountain St",
    "sg:city":"Lithonia",
    "sg:classifiers":[
        {
            "category":"Autos & Motor Vehicles",
            "subcategory":"Fuel & Gas Station",
            "type":"Retail Goods"
        }
    ],
    "sg:phone":"+1 678 344 7704",
    "sg:postcode":"30058",
    "sg:province":"GA",
    "sg:website":"www.chevron.com",
    "wof:name":"Chevron Food Mark",
    "wof:placetype":"venue"
},
  "geometry": {"coordinates":[-84.107051,33.711635],"type":"Point"}
}