{
  "type": "Feature",
  "properties": {
    "addr:full":"153 Dempsey Ave Jackson GA 30233",
    "addr:housenumber":"153",
    "addr:postcode":"30233",
    "addr:street":"Dempsey Ave",
    "iso:country":"US",
    "sg:address":"153 Dempsey Ave",
    "sg:city":"Jackson",
    "sg:classifiers":[
        {
            "category":"Retail",
            "subcategory":"Animal Services",
            "type":"Services"
        }
    ],
    "sg:phone":"+1 770 775 5270",
    "sg:postcode":"30233",
    "sg:province":"GA",
    "sg:tags":[
        "pet",
        "grooming",
        "washing"
    ],
    "wof:name":"Virginia's Clip & Dip",
    "wof:placetype":"venue"
},
  "geometry": {"coordinates":[-83.96463900000001,33.29341],"type":"Point"}
}