{
  "type": "Feature",
  "properties": {
    "addr:full":"490 Padgett Rd Senoia GA 30276",
    "addr:housenumber":"490",
    "addr:postcode":"30276",
    "addr:street":"Padgett Rd",
    "iso:country":"US",
    "sg:address":"490 Padgett Rd",
    "sg:city":"Senoia",
    "sg:classifiers":[
        {
            "category":"Home & Garden",
            "subcategory":"Building Materials",
            "type":"Retail Goods"
        }
    ],
    "sg:phone":"+1 770 719 0458",
    "sg:postcode":"30276",
    "sg:province":"GA",
    "sg:tags":[
        "door"
    ],
    "wof:name":"Progressive Door Co Inc",
    "wof:placetype":"venue"
},
  "geometry": {"coordinates":[-84.505437,33.297907],"type":"Point"}
}