{
  "type": "Feature",
  "properties": {
    "addr:full":"1544 Georgia Ave Omega GA 31775",
    "addr:housenumber":"1544",
    "addr:postcode":"31775",
    "addr:street":"Georgia Ave",
    "iso:country":"US",
    "sg:address":"1544 Georgia Ave",
    "sg:city":"Omega",
    "sg:classifiers":[
        {
            "category":"Government",
            "subcategory":"Office",
            "type":"Public Place"
        }
    ],
    "sg:phone":"+1 229 528 6411",
    "sg:postcode":"31775",
    "sg:province":"GA",
    "sg:tags":[
        "county"
    ],
    "wof:name":"Tift County Bd Of Elections",
    "wof:placetype":"venue"
},
  "geometry": {"coordinates":[-83.595957,31.338618],"type":"Point"}
}