{
  "type": "Feature",
  "properties": {
    "addr:full":"2462 Highway 34 E Newman GA 30265",
    "addr:housenumber":"2462",
    "addr:postcode":"30265",
    "addr:street":"Highway 34 E",
    "iso:country":"US",
    "sg:address":"2462 Highway 34 E",
    "sg:city":"Newman",
    "sg:classifiers":[
        {
            "category":"Building & Trades",
            "subcategory":"Construction",
            "type":"Services"
        }
    ],
    "sg:phone":"+1 770 461 5780",
    "sg:postcode":"30265",
    "sg:province":"GA",
    "sg:tags":[
        "roofing"
    ],
    "sg:website":"atlroof.com",
    "wof:name":"ATLRoof.com",
    "wof:placetype":"venue"
},
  "geometry": {"coordinates":[-84.678856,33.407008],"type":"Point"}
}