{
  "type": "Feature",
  "properties": {
    "addr:full":"160 Pooler Pkwy Pooler GA 31322",
    "addr:housenumber":"160",
    "addr:postcode":"31322",
    "addr:street":"Pooler Pkwy",
    "iso:country":"US",
    "sg:address":"160 Pooler Pkwy",
    "sg:city":"Pooler",
    "sg:classifiers":[
        {
            "category":"Restaurant",
            "type":"Food & Drink"
        }
    ],
    "sg:menulink":"http://www.allmenus.com/ga/port-wentworth/202543-mcdonalds/menu/",
    "sg:postcode":"31322",
    "sg:province":"GA",
    "sg:tags":[
        "burger",
        "american"
    ],
    "wof:name":"McDonald's",
    "wof:placetype":"venue"
},
  "geometry": {"coordinates":[-81.24440199999999,32.141053],"type":"Point"}
}