{
  "type": "Feature",
  "properties": {
    "iso:country":"US",
    "sg:address":"91 Haygood Ave SE",
    "sg:city":"Atlanta",
    "sg:classifiers":[
        {
            "category":"Building & Trades",
            "subcategory":"Locksmith",
            "type":"Services"
        }
    ],
    "sg:phone":"+1 404 260 5234",
    "sg:postcode":"30315",
    "sg:province":"GA",
    "sg:tags":[
        "key"
    ],
    "wof:name":"A Locksmith 0 1 24 Hour",
    "wof:placetype":"venue"
},
  "geometry": {"coordinates":[-84.38515200000001,33.726373],"type":"Point"}
}