{
  "type": "Feature",
  "properties": {
    "addr:full":"1937 Clairmont Rd Decatur GA 30033",
    "addr:housenumber":"1937",
    "addr:postcode":"30033",
    "addr:street":"Clairmont Rd",
    "iso:country":"US",
    "sg:address":"1937 Clairmont Rd",
    "sg:city":"Decatur",
    "sg:classifiers":[
        {
            "category":"Banks & Credit Unions",
            "subcategory":"Bank",
            "type":"Services"
        }
    ],
    "sg:phone":"+1 404 728 1226",
    "sg:postcode":"30033",
    "sg:province":"GA",
    "sg:tags":[
        "national",
        "commercial"
    ],
    "wof:name":"SunTrust",
    "wof:placetype":"venue"
},
  "geometry": {"coordinates":[-84.30811799999999,33.811785],"type":"Point"}
}