{
  "type": "Feature",
  "properties": {
    "addr:full":"990 Holcomb Bridge Rd Roswell GA 30076",
    "addr:housenumber":"990",
    "addr:postcode":"30076",
    "addr:street":"Holcomb Bridge Rd",
    "iso:country":"US",
    "sg:address":"990 Holcomb Bridge Rd",
    "sg:city":"Roswell",
    "sg:classifiers":[
        {
            "category":"Real Estate",
            "subcategory":"Real Estate Services",
            "type":"Services"
        }
    ],
    "sg:phone":"+1 770 587 0004",
    "sg:postcode":"30076",
    "sg:province":"GA",
    "sg:tags":[
        "company",
        "title"
    ],
    "wof:name":"Gulf Coast Title Closings",
    "wof:placetype":"venue"
},
  "geometry": {"coordinates":[-84.334372,34.028036],"type":"Point"}
}