{
  "type": "Feature",
  "properties": {
    "iso:country":"US",
    "sg:address":"8175 Washington St SW",
    "sg:city":"Covington",
    "sg:classifiers":[
        {
            "category":"Retail",
            "subcategory":"Repair Shop",
            "type":"Services"
        }
    ],
    "sg:phone":"+1 770 786 2115",
    "sg:postcode":"30014",
    "sg:province":"GA",
    "sg:tags":[
        "electrical"
    ],
    "wof:name":"Moseleys Major Appliance Sales",
    "wof:placetype":"venue"
},
  "geometry": {"coordinates":[-83.87869499999999,33.582198],"type":"Point"}
}