{
  "type": "Feature",
  "properties": {
    "addr:full":"3741 Houston Ave Macon GA 31206",
    "addr:housenumber":"3741",
    "addr:postcode":"31206",
    "addr:street":"Houston Ave",
    "iso:country":"US",
    "sg:address":"3741 Houston Ave",
    "sg:city":"Macon",
    "sg:classifiers":[
        {
            "category":"Health Services",
            "subcategory":"Doctor",
            "type":"Services"
        }
    ],
    "sg:phone":"+1 478 781 2992",
    "sg:postcode":"31206",
    "sg:province":"GA",
    "sg:tags":[
        "medical"
    ],
    "wof:name":"South McOn Fmly Physcans Clnic",
    "wof:placetype":"venue"
},
  "geometry": {"coordinates":[-83.653814,32.795935],"type":"Point"}
}