{
  "type": "Feature",
  "properties": {
    "iso:country":"US",
    "sg:address":"1484 Old Salem Rd SE",
    "sg:city":"Conyers",
    "sg:classifiers":[
        {
            "category":"Retail",
            "subcategory":"Laundry & Dry Cleaning",
            "type":"Services"
        }
    ],
    "sg:phone":"+1 770 483 2251",
    "sg:postcode":"30013",
    "sg:province":"GA",
    "sg:tags":[
        "cleaners",
        "plant",
        "drycleaning"
    ],
    "wof:name":"Martin's Cleaners",
    "wof:placetype":"venue"
},
  "geometry": {"coordinates":[-84.003159,33.647141],"type":"Point"}
}