{
  "type": "Feature",
  "properties": {
    "iso:country":"US",
    "sg:address":"2094 Cobb Pkwy S",
    "sg:city":"Marietta",
    "sg:classifiers":[
        {
            "category":"Food & Beverages",
            "subcategory":"Liquor & Beverages",
            "type":"Retail Goods"
        }
    ],
    "sg:phone":"+1 770 916 1252",
    "sg:postcode":"30060",
    "sg:province":"GA",
    "sg:tags":[
        "bartending"
    ],
    "wof:name":"National Bartending Institute",
    "wof:placetype":"venue"
},
  "geometry": {"coordinates":[-84.541442,33.902137],"type":"Point"}
}