{
  "type": "Feature",
  "properties": {
    "addr:full":"258 John Walraven Rd Dallas GA 30132",
    "addr:housenumber":"258",
    "addr:postcode":"30132",
    "addr:street":"John Walraven Rd",
    "iso:country":"US",
    "sg:address":"258 John Walraven Rd",
    "sg:city":"Dallas",
    "sg:classifiers":[
        {
            "category":"Building & Trades",
            "subcategory":"Construction",
            "type":"Services"
        }
    ],
    "sg:phone":"+1 678 614 9972",
    "sg:postcode":"30132",
    "sg:province":"GA",
    "sg:tags":[
        "house"
    ],
    "wof:name":"Billy Taylor Construction",
    "wof:placetype":"venue"
},
  "geometry": {"coordinates":[-84.841521,33.959934],"type":"Point"}
}