{
  "type": "Feature",
  "properties": {
    "addr:full":"940 Cobb Place Manor Dr Marietta GA 30066",
    "addr:housenumber":"940",
    "addr:postcode":"30066",
    "addr:street":"Cobb Place Manor Dr",
    "iso:country":"US",
    "sg:address":"940 Cobb Place Manor Dr",
    "sg:city":"Marietta",
    "sg:classifiers":[
        {
            "category":"Shopping",
            "type":"Retail Goods"
        }
    ],
    "sg:phone":"+1 770 218 7373",
    "sg:postcode":"30066",
    "sg:province":"GA",
    "sg:tags":[
        "merchandise"
    ],
    "wof:name":"Smile Communication",
    "wof:placetype":"venue"
},
  "geometry": {"coordinates":[-84.53613799999999,34.019051],"type":"Point"}
}