{
  "type": "Feature",
  "properties": {
    "iso:country":"US",
    "sg:address":"126 Spring Dr",
    "sg:city":"Roswell",
    "sg:classifiers":[
        {
            "category":"Building & Trades",
            "subcategory":"Construction",
            "type":"Services"
        }
    ],
    "sg:phone":"+1 770 993 0423",
    "sg:postcode":"30075",
    "sg:province":"GA",
    "sg:tags":[
        "contractor"
    ],
    "wof:name":"TRW Contractors Inc",
    "wof:placetype":"venue"
},
  "geometry": {"coordinates":[-84.367346,34.009031],"type":"Point"}
}