{
  "type": "Feature",
  "properties": {
    "addr:full":"619 Rankin St NE Atlanta GA 30308",
    "addr:housenumber":"619",
    "addr:postcode":"30308",
    "addr:street":"Rankin St Ne",
    "iso:country":"US",
    "sg:address":"619 Rankin St NE",
    "sg:city":"Atlanta",
    "sg:classifiers":[
        {
            "category":"Health Services",
            "subcategory":"Doctor",
            "type":"Services"
        }
    ],
    "sg:phone":"+1 404 874 3102",
    "sg:postcode":"30308",
    "sg:province":"GA",
    "sg:tags":[
        "medicine",
        "internal"
    ],
    "wof:name":"Bernard Anette M MD",
    "wof:placetype":"venue"
},
  "geometry": {"coordinates":[-84.36668299999999,33.76705],"type":"Point"}
}