{
  "type": "Feature",
  "properties": {
    "iso:country":"US",
    "sg:address":"1107 Old Pelham Rd",
    "sg:city":"Climax",
    "sg:classifiers":[
        {
            "category":"Professional",
            "type":"Services"
        }
    ],
    "sg:phone":"+1 229 246 7420",
    "sg:postcode":"39834",
    "sg:province":"GA",
    "wof:name":"Bonnie S Trammell",
    "wof:placetype":"venue"
},
  "geometry": {"coordinates":[-84.45751199999999,30.969033],"type":"Point"}
}