{
  "type": "Feature",
  "properties": {
    "iso:country":"US",
    "sg:address":"2139 The Rock Rd",
    "sg:city":"Montrose",
    "sg:classifiers":[
        {
            "category":"Building & Trades",
            "subcategory":"Landscaping Services",
            "type":"Services"
        }
    ],
    "sg:phone":"+1 478 376 4403",
    "sg:postcode":"31065",
    "sg:province":"GA",
    "sg:tags":[
        "tree"
    ],
    "wof:name":"Lord's Tree Svc Inc",
    "wof:placetype":"venue"
},
  "geometry": {"coordinates":[-83.190657,32.539803],"type":"Point"}
}