{
  "type": "Feature",
  "properties": {
    "addr:full":"951 Carl Vinson Pkwy Centerville GA 31028",
    "addr:housenumber":"951",
    "addr:postcode":"31028",
    "addr:street":"Carl Vinson Pkwy",
    "iso:country":"US",
    "sg:address":"951 Carl Vinson Pkwy",
    "sg:city":"Centerville",
    "sg:classifiers":[
        {
            "category":"Wholesale",
            "subcategory":"Painting Supplies",
            "type":"Manufacturing & Wholesale Goods"
        },
        {
            "category":"Home & Garden",
            "subcategory":"Building Materials",
            "type":"Retail Goods"
        },
        {
            "category":"Building & Trades",
            "subcategory":"Construction",
            "type":"Services"
        }
    ],
    "sg:phone":"+1 478 923 5614",
    "sg:postcode":"31028",
    "sg:province":"GA",
    "sg:tags":[
        "wall",
        "wallpaper",
        "coating",
        "contractor",
        "wallcoverings",
        "painter"
    ],
    "wof:name":"Taylor Wendell Wallcoverings Inc",
    "wof:placetype":"venue"
},
  "geometry": {"coordinates":[-83.660797,32.637699],"type":"Point"}
}