{
  "type": "Feature",
  "properties": {
    "addr:full":"3715 Settingdown Rd Cumming GA 30040",
    "addr:housenumber":"3715",
    "addr:postcode":"30040",
    "addr:street":"Settingdown Rd",
    "iso:country":"US",
    "sg:address":"3715 Settingdown Rd",
    "sg:city":"Cumming",
    "sg:classifiers":[
        {
            "category":"Professional",
            "type":"Services"
        }
    ],
    "sg:phone":"+1 770 888 9897",
    "sg:postcode":"30040",
    "sg:province":"GA",
    "wof:name":"Lineside Outfitters",
    "wof:placetype":"venue"
},
  "geometry": {"coordinates":[-84.08196599999999,34.277433],"type":"Point"}
}