{
  "type": "Feature",
  "properties": {
    "iso:country":"US",
    "sg:address":"1528 Crescent Dr",
    "sg:city":"Augusta",
    "sg:phone":"+1 706 736 6662",
    "sg:postcode":"30909",
    "sg:province":"GA",
    "sg:website":"http://www.creightonlaircey.com",
    "wof:name":"Creighton Laircey Co Inc",
    "wof:placetype":"venue"
},
  "geometry": {"coordinates":[-82.085381,33.463402],"type":"Point"}
}