{
  "type": "Feature",
  "properties": {
    "iso:country":"US",
    "sg:address":"4126 Steve Reynolds Blvd",
    "sg:city":"Norcross",
    "sg:classifiers":[
        {
            "category":"Professional",
            "type":"Services"
        }
    ],
    "sg:phone":"+1 678 287 1500",
    "sg:postcode":"30093",
    "sg:province":"GA",
    "wof:name":"Pharmaderm",
    "wof:placetype":"venue"
},
  "geometry": {"coordinates":[-84.147324,33.928488],"type":"Point"}
}