{
  "type": "Feature",
  "properties": {
    "addr:full":"3183 Peachtree Rd NE Atlanta GA 30305",
    "addr:housenumber":"3183",
    "addr:postcode":"30305",
    "addr:street":"Peachtree Rd Ne",
    "iso:country":"US",
    "sg:address":"3183 Peachtree Rd NE",
    "sg:city":"Atlanta",
    "sg:classifiers":[
        {
            "category":"Building & Trades",
            "subcategory":"Locksmith",
            "type":"Services"
        }
    ],
    "sg:phone":"+1 404 736 3017",
    "sg:postcode":"30305",
    "sg:province":"GA",
    "sg:tags":[
        "key"
    ],
    "wof:name":"1 After Drinking Locksmith Rescue",
    "wof:placetype":"venue"
},
  "geometry": {"coordinates":[-84.37542500000001,33.840978],"type":"Point"}
}