{
  "type": "Feature",
  "properties": {
    "iso:country":"US",
    "sg:address":"3398 Chancelor's Dr",
    "sg:city":"Powder Springs",
    "sg:classifiers":[
        {
            "category":"Professional",
            "subcategory":"Business Services",
            "type":"Services"
        }
    ],
    "sg:phone":"+1 770 439 9234",
    "sg:postcode":"30127",
    "sg:province":"GA",
    "wof:name":"K T L Enterprises Inc",
    "wof:placetype":"venue"
},
  "geometry": {"coordinates":[-84.640501,33.87299],"type":"Point"}
}