{
  "type": "Feature",
  "properties": {
    "addr:full":"4825 Duncans Lake Dr Buford GA 30519",
    "addr:housenumber":"4825",
    "addr:postcode":"30519",
    "addr:street":"Duncans Lake Dr",
    "iso:country":"US",
    "sg:address":"4825 Duncans Lake Dr",
    "sg:city":"Buford",
    "sg:classifiers":[
        {
            "category":"Autos & Motor Vehicles",
            "subcategory":"Automobile Sales",
            "type":"Retail Goods"
        }
    ],
    "sg:phone":"+1 678 714 9048",
    "sg:postcode":"30519",
    "sg:province":"GA",
    "sg:tags":[
        "new",
        "car"
    ],
    "wof:name":"Gwinnett Place Ford",
    "wof:placetype":"venue"
},
  "geometry": {"coordinates":[-83.879997,34.097542],"type":"Point"}
}