{
  "type": "Feature",
  "properties": {
    "iso:country":"US",
    "sg:address":"5071 Kathryn Glen Dr",
    "sg:city":"Acworth",
    "sg:classifiers":[
        {
            "category":"Travel",
            "subcategory":"Hotels & Motels",
            "type":"Entertainment"
        }
    ],
    "sg:phone":"+1 678 574 3664",
    "sg:postcode":"30101",
    "sg:province":"GA",
    "sg:tags":[
        "operation"
    ],
    "wof:name":"Cottages At Baker Road",
    "wof:placetype":"venue"
},
  "geometry": {"coordinates":[-84.643513,34.077482],"type":"Point"}
}