{
  "type": "Feature",
  "properties": {
    "iso:country":"US",
    "sg:address":"14 N West St",
    "sg:city":"Jasper",
    "sg:classifiers":[
        {
            "category":"Shopping",
            "subcategory":"Bicycles & Sporting Goods",
            "type":"Retail Goods"
        }
    ],
    "sg:phone":"+1 706 253 5425",
    "sg:postcode":"30143",
    "sg:province":"GA",
    "wof:name":"United Karate Studio",
    "wof:placetype":"venue"
},
  "geometry": {"coordinates":[-84.430738,34.468566],"type":"Point"}
}