{
  "type": "Feature",
  "properties": {
    "addr:full":"1950 Spectrum Cir Marietta GA 30067",
    "addr:housenumber":"1950",
    "addr:postcode":"30067",
    "addr:street":"Spectrum Cir",
    "iso:country":"US",
    "sg:address":"1950 Spectrum Cir",
    "sg:city":"Marietta",
    "sg:classifiers":[
        {
            "category":"Professional",
            "subcategory":"Lawyer & Legal Services",
            "type":"Services"
        }
    ],
    "sg:phone":"+1 678 921 2958",
    "sg:postcode":"30067",
    "sg:province":"GA",
    "sg:tags":[
        "attorney"
    ],
    "wof:name":"Daniel J Hoppe Law Office",
    "wof:placetype":"venue"
},
  "geometry": {"coordinates":[-84.468422,33.905372],"type":"Point"}
}