{
  "type": "Feature",
  "properties": {
    "iso:country":"US",
    "sg:address":"414 N Main St",
    "sg:city":"Swainsboro",
    "sg:classifiers":[
        {
            "category":"Retail",
            "subcategory":"Auto Repair",
            "type":"Services"
        },
        {
            "category":"Wholesale",
            "subcategory":"Auto Parts",
            "type":"Manufacturing & Wholesale Goods"
        }
    ],
    "sg:phone":"+1 478 237 2996",
    "sg:postcode":"30401",
    "sg:province":"GA",
    "sg:tags":[
        "automotive",
        "tire"
    ],
    "wof:name":"Fast Go Oil & Lube Inc",
    "wof:placetype":"venue"
},
  "geometry": {"coordinates":[-82.34012199999999,32.605502],"type":"Point"}
}