{
  "type": "Feature",
  "properties": {
    "iso:country":"US",
    "sg:address":"105 Hickory St",
    "sg:city":"Warner Robins",
    "sg:classifiers":[
        {
            "category":"Personal",
            "subcategory":"Beauty Salon",
            "type":"Services"
        }
    ],
    "sg:phone":"+1 478 922 7228",
    "sg:postcode":"31093",
    "sg:province":"GA",
    "sg:tags":[
        "shop"
    ],
    "wof:name":"Bette Austin's Hair Salon",
    "wof:placetype":"venue"
},
  "geometry": {"coordinates":[-83.63688999999999,32.61974],"type":"Point"}
}