{
  "type": "Feature",
  "properties": {
    "addr:full":"3100 Leary Rd Albany GA 31721",
    "addr:housenumber":"3100",
    "addr:postcode":"31721",
    "addr:street":"Leary Rd",
    "iso:country":"US",
    "sg:address":"3100 Leary Rd",
    "sg:city":"Albany",
    "sg:classifiers":[
        {
            "category":"Building & Trades",
            "subcategory":"Construction",
            "type":"Services"
        }
    ],
    "sg:phone":"+1 229 432 1948",
    "sg:postcode":"31721",
    "sg:province":"GA",
    "sg:tags":[
        "contractor"
    ],
    "wof:name":"James Unlimited",
    "wof:placetype":"venue"
},
  "geometry": {"coordinates":[-84.24791399999999,31.504106],"type":"Point"}
}