{
  "type": "Feature",
  "properties": {
    "iso:country":"US",
    "sg:address":"111 S Commercial Cir",
    "sg:city":"Warner Robins",
    "sg:classifiers":[
        {
            "category":"Personal",
            "subcategory":"Beauty Salon",
            "type":"Services"
        }
    ],
    "sg:phone":"+1 478 328 8878",
    "sg:postcode":"31088",
    "sg:province":"GA",
    "wof:name":"All Dolled Up Hair Salon",
    "wof:placetype":"venue"
},
  "geometry": {"coordinates":[-83.612076,32.618205],"type":"Point"}
}