{
  "type": "Feature",
  "properties": {
    "iso:country":"US",
    "sg:address":"960 Dean Hill Rd SE",
    "sg:city":"Monroe",
    "sg:classifiers":[
        {
            "category":"Building & Trades",
            "subcategory":"Construction",
            "type":"Services"
        }
    ],
    "sg:phone":"+1 770 267 8725",
    "sg:postcode":"30655",
    "sg:province":"GA",
    "sg:tags":[
        "house"
    ],
    "wof:name":"Premium Construction",
    "wof:placetype":"venue"
},
  "geometry": {"coordinates":[-83.730617,33.750423],"type":"Point"}
}