{
  "type": "Feature",
  "properties": {
    "iso:country":"US",
    "sg:address":"18 Hummingbird Ln",
    "sg:city":"Jasper",
    "sg:classifiers":[
        {
            "category":"Manufacturing",
            "subcategory":"Tools & Machinery",
            "type":"Manufacturing & Wholesale Goods"
        }
    ],
    "sg:phone":"+1 706 692 3978",
    "sg:postcode":"30143",
    "sg:province":"GA",
    "sg:tags":[
        "tick",
        "remover",
        "mfg"
    ],
    "wof:name":"Caddar",
    "wof:placetype":"venue"
},
  "geometry": {"coordinates":[-84.37382599999999,34.491052],"type":"Point"}
}