{
  "type": "Feature",
  "properties": {
    "iso:country":"US",
    "sg:address":"2170 Avery Rd",
    "sg:city":"Pine Mountain",
    "sg:classifiers":[
        {
            "category":"Farming",
            "subcategory":"Farm & Veterinary Services",
            "type":"Manufacturing & Wholesale Goods"
        }
    ],
    "sg:phone":"+1 706 884 5074",
    "sg:postcode":"31822",
    "sg:province":"GA",
    "sg:tags":[
        "breeder",
        "livestock"
    ],
    "wof:name":"Canaan Farms",
    "wof:placetype":"venue"
},
  "geometry": {"coordinates":[-85.01076999999999,32.862134],"type":"Point"}
}