{
  "type": "Feature",
  "properties": {
    "addr:full":"423 College St Carrollton GA 30117",
    "addr:housenumber":"423",
    "addr:postcode":"30117",
    "addr:street":"College St",
    "iso:country":"US",
    "sg:address":"423 College St",
    "sg:city":"Carrollton",
    "sg:classifiers":[
        {
            "category":"Professional",
            "subcategory":"Management & Consulting",
            "type":"Services"
        }
    ],
    "sg:phone":"+1 770 830 5863",
    "sg:postcode":"30117",
    "sg:province":"GA",
    "sg:tags":[
        "consultant",
        "coach",
        "business"
    ],
    "sg:website":"http://www.ccwageorgia.com",
    "wof:name":"Business Licenses",
    "wof:placetype":"venue"
},
  "geometry": {"coordinates":[-85.07212,33.583678],"type":"Point"}
}