{
  "type": "Feature",
  "properties": {
    "addr:full":"27 Artley Rd Savannah GA 31408",
    "addr:housenumber":"27",
    "addr:postcode":"31408",
    "addr:street":"Artley Rd",
    "iso:country":"US",
    "sg:address":"27 Artley Rd",
    "sg:city":"Savannah",
    "sg:classifiers":[
        {
            "category":"Manufacturing",
            "subcategory":"Wood Products",
            "type":"Manufacturing & Wholesale Goods"
        }
    ],
    "sg:phone":"+1 912 330 0083",
    "sg:postcode":"31408",
    "sg:province":"GA",
    "sg:tags":[
        "lumber"
    ],
    "sg:website":"www.conceptfinishing.com",
    "wof:name":"Concept Finishing",
    "wof:placetype":"venue"
},
  "geometry": {"coordinates":[-81.219509,32.110408],"type":"Point"}
}