{
  "type": "Feature",
  "properties": {
    "iso:country":"US",
    "sg:address":"842 W Thigpen Ave",
    "sg:city":"Lakeland",
    "sg:classifiers":[
        {
            "category":"Education",
            "subcategory":"School",
            "type":"Public Place"
        }
    ],
    "sg:phone":"+1 229 482 2418",
    "sg:postcode":"31635",
    "sg:province":"GA",
    "wof:name":"Lakeland Svth School",
    "wof:placetype":"venue"
},
  "geometry": {"coordinates":[-83.08594100000001,31.0416],"type":"Point"}
}