{
  "type": "Feature",
  "properties": {
    "iso:country":"US",
    "sg:address":"2986 Nestle Creek Dr",
    "sg:city":"Marietta",
    "sg:classifiers":[
        {
            "category":"Professional",
            "type":"Services"
        }
    ],
    "sg:phone":"+1 770 971 2435",
    "sg:postcode":"30062",
    "sg:province":"GA",
    "wof:name":"Pooria Fine Art",
    "wof:placetype":"venue"
},
  "geometry": {"coordinates":[-84.46656900000001,33.990036],"type":"Point"}
}