{
  "type": "Feature",
  "properties": {
    "iso:country":"US",
    "sg:address":"11347 Chelsea Ln",
    "sg:city":"Hampton",
    "sg:classifiers":[
        {
            "category":"Professional",
            "subcategory":"Business Services",
            "type":"Services"
        }
    ],
    "sg:phone":"+1 678 545 1204",
    "sg:postcode":"30228",
    "sg:province":"GA",
    "wof:name":"CPM Enterprises",
    "wof:placetype":"venue"
},
  "geometry": {"coordinates":[-84.348348,33.450011],"type":"Point"}
}