{
  "type": "Feature",
  "properties": {
    "addr:full":"100 Cattlemens Dr Macon GA 31220",
    "addr:housenumber":"100",
    "addr:postcode":"31220",
    "addr:street":"Cattlemens Dr",
    "iso:country":"US",
    "sg:address":"100 Cattlemens Dr",
    "sg:city":"Macon",
    "sg:classifiers":[
        {
            "category":"Organizations",
            "subcategory":"Professional Association",
            "type":"Services"
        }
    ],
    "sg:phone":"+1 478 405 0992",
    "sg:postcode":"31220",
    "sg:province":"GA",
    "wof:name":"Georgia Cattlemens Assn",
    "wof:placetype":"venue"
},
  "geometry": {"coordinates":[-83.73089299999999,32.823012],"type":"Point"}
}