{
  "type": "Feature",
  "properties": {
    "addr:full":"4151 Mercer University Dr Macon GA 31204",
    "addr:housenumber":"4151",
    "addr:postcode":"31204",
    "addr:street":"Mercer University Dr",
    "iso:country":"US",
    "sg:address":"4151 Mercer University Dr",
    "sg:city":"Macon",
    "sg:classifiers":[
        {
            "category":"Shopping",
            "subcategory":"Department Store",
            "type":"Retail Goods"
        }
    ],
    "sg:phone":"+1 478 757 8804",
    "sg:postcode":"31204",
    "sg:province":"GA",
    "sg:tags":[
        "shop"
    ],
    "wof:name":"Super Discount Ctr",
    "wof:placetype":"venue"
},
  "geometry": {"coordinates":[-83.706951,32.825154],"type":"Point"}
}