{
  "type": "Feature",
  "properties": {
    "addr:full":"3720 Club Dr Duluth GA 30096",
    "addr:housenumber":"3720",
    "addr:postcode":"30096",
    "addr:street":"Club Dr",
    "iso:country":"US",
    "sg:address":"3720 Club Dr",
    "sg:city":"Duluth",
    "sg:classifiers":[
        {
            "category":"Autos & Motor Vehicles",
            "subcategory":"Fuel & Gas Station",
            "type":"Retail Goods"
        }
    ],
    "sg:phone":"+1 770 638 2988",
    "sg:postcode":"30096",
    "sg:province":"GA",
    "sg:website":"www.chevron.com",
    "wof:name":"Chevron Food Mart",
    "wof:placetype":"venue"
},
  "geometry": {"coordinates":[-84.12696800000001,33.941985],"type":"Point"}
}