{
  "type": "Feature",
  "properties": {
    "addr:full":"933 Historic Homer Hwy Homer GA 30547",
    "addr:housenumber":"933",
    "addr:postcode":"30547",
    "addr:street":"Historic Homer Hwy",
    "iso:country":"US",
    "sg:address":"933 Historic Homer Hwy",
    "sg:city":"Homer",
    "sg:classifiers":[
        {
            "category":"Personal",
            "subcategory":"Beauty Salon",
            "type":"Services"
        }
    ],
    "sg:phone":"+1 706 677 2406",
    "sg:postcode":"30547",
    "sg:province":"GA",
    "wof:name":"Angie Campbell",
    "wof:placetype":"venue"
},
  "geometry": {"coordinates":[-83.497429,34.334539],"type":"Point"}
}