{
  "type": "Feature",
  "properties": {
    "addr:full":"1523 Roswell Rd Marietta GA 30062",
    "addr:housenumber":"1523",
    "addr:postcode":"30062",
    "addr:street":"Roswell Rd",
    "iso:country":"US",
    "sg:address":"1523 Roswell Rd",
    "sg:city":"Marietta",
    "sg:classifiers":[
        {
            "category":"Retail",
            "subcategory":"Repair Shop",
            "type":"Services"
        }
    ],
    "sg:phone":"+1 770 565 8007",
    "sg:postcode":"30062",
    "sg:province":"GA",
    "sg:tags":[
        "appliance",
        "electrical"
    ],
    "wof:name":"Davis Appliance Serv",
    "wof:placetype":"venue"
},
  "geometry": {"coordinates":[-84.50835600000001,33.951314],"type":"Point"}
}