{
  "type": "Feature",
  "properties": {
    "iso:country":"US",
    "sg:address":"3243 Maysville Rd",
    "sg:city":"Commerce",
    "sg:classifiers":[
        {
            "category":"Retail",
            "subcategory":"Auto Repair",
            "type":"Services"
        }
    ],
    "sg:phone":"+1 706 335 6355",
    "sg:postcode":"30529",
    "sg:province":"GA",
    "sg:tags":[
        "lubricating",
        "automotive"
    ],
    "wof:name":"Don's Quick Lube Auto & Truck",
    "wof:placetype":"venue"
},
  "geometry": {"coordinates":[-83.48049,34.209832],"type":"Point"}
}