{
  "type": "Feature",
  "properties": {
    "addr:full":"3461 Roosevelt Hwy Atlanta GA 30349",
    "addr:housenumber":"3461",
    "addr:postcode":"30349",
    "addr:street":"Roosevelt Hwy",
    "iso:country":"US",
    "sg:address":"3461 Roosevelt Hwy",
    "sg:city":"Atlanta",
    "sg:classifiers":[
        {
            "category":"Banks & Credit Unions",
            "subcategory":"Bank",
            "type":"Services"
        }
    ],
    "sg:phone":"+1 404 209 8022",
    "sg:postcode":"30349",
    "sg:province":"GA",
    "sg:tags":[
        "cashing",
        "check"
    ],
    "wof:name":"Check Cashed",
    "wof:placetype":"venue"
},
  "geometry": {"coordinates":[-84.50211899999999,33.622016],"type":"Point"}
}