{
  "type": "Feature",
  "properties": {
    "addr:full":"949 W Marietta Street NW Atlanta GA 30318",
    "addr:housenumber":"949",
    "addr:postcode":"30318",
    "addr:street":"W Marietta Street Nw",
    "iso:country":"US",
    "sg:address":"949 W Marietta Street NW",
    "sg:city":"Atlanta",
    "sg:classifiers":[
        {
            "category":"Professional",
            "subcategory":"Lawyer & Legal Services",
            "type":"Services"
        }
    ],
    "sg:phone":"+1 404 892 2001",
    "sg:postcode":"30318",
    "sg:province":"GA",
    "wof:name":"Leonard Jonathan E PC",
    "wof:placetype":"venue"
},
  "geometry": {"coordinates":[-84.418301,33.783998],"type":"Point"}
}