{
  "type": "Feature",
  "properties": {
    "iso:country":"US",
    "sg:address":"1578 Warrenton Hwy",
    "sg:city":"Thomson",
    "sg:classifiers":[
        {
            "category":"Manufacturing",
            "subcategory":"Apparel",
            "type":"Manufacturing & Wholesale Goods"
        }
    ],
    "sg:phone":"+1 706 595 8794",
    "sg:postcode":"30824",
    "sg:province":"GA",
    "sg:tags":[
        "dress"
    ],
    "wof:name":"Chardan LTD",
    "wof:placetype":"venue"
},
  "geometry": {"coordinates":[-82.52954,33.454587],"type":"Point"}
}