{
  "type": "Feature",
  "properties": {
    "iso:country":"US",
    "sg:address":"4107 Buena Vista Rd",
    "sg:city":"Columbus",
    "sg:classifiers":[
        {
            "category":"Shopping",
            "subcategory":"Used Merchandise",
            "type":"Retail Goods"
        }
    ],
    "sg:phone":"+1 706 568 3336",
    "sg:postcode":"31907",
    "sg:province":"GA",
    "sg:tags":[
        "pawnbroker"
    ],
    "wof:name":"Title Max",
    "wof:placetype":"venue"
},
  "geometry": {"coordinates":[-84.923249,32.464172],"type":"Point"}
}