{
  "type": "Feature",
  "properties": {
    "addr:full":"108 Bucksnort Rd Griffin GA 30224",
    "addr:housenumber":"108",
    "addr:postcode":"30224",
    "addr:street":"Bucksnort Rd",
    "iso:country":"US",
    "sg:address":"108 Bucksnort Rd",
    "sg:city":"Griffin",
    "sg:classifiers":[
        {
            "category":"Organizations",
            "subcategory":"Religious Organization",
            "type":"Services"
        }
    ],
    "sg:phone":"+1 770 227 3772",
    "sg:postcode":"30224",
    "sg:province":"GA",
    "wof:name":"Oakgrove Baptist Church",
    "wof:placetype":"venue"
},
  "geometry": {"coordinates":[-84.140061,33.231975],"type":"Point"}
}