{
  "type": "Feature",
  "properties": {
    "iso:country":"US",
    "sg:address":"26 Barnett Shoals Rd",
    "sg:city":"Watkinsville",
    "sg:classifiers":[
        {
            "category":"Manufacturing",
            "subcategory":"Printing",
            "type":"Manufacturing & Wholesale Goods"
        }
    ],
    "sg:phone":"+1 706 769 5175",
    "sg:postcode":"30677",
    "sg:province":"GA",
    "sg:tags":[
        "newspaper"
    ],
    "sg:website":"www.oconeeenterprise.com",
    "wof:name":"Oconee Enterprise",
    "wof:placetype":"venue"
},
  "geometry": {"coordinates":[-83.40404599999999,33.860568],"type":"Point"}
}