{
  "type": "Feature",
  "properties": {
    "addr:full":"564 James St SW Lilburn GA 30047",
    "addr:housenumber":"564",
    "addr:postcode":"30047",
    "addr:street":"James St Sw",
    "iso:country":"US",
    "sg:address":"564 James St SW",
    "sg:city":"Lilburn",
    "sg:classifiers":[
        {
            "category":"Home & Garden",
            "subcategory":"Home Furnishings",
            "type":"Retail Goods"
        }
    ],
    "sg:phone":"+1 770 935 6946",
    "sg:postcode":"30047",
    "sg:province":"GA",
    "wof:name":"Carolyn Rice Art Pottery",
    "wof:placetype":"venue"
},
  "geometry": {"coordinates":[-84.101336,33.879907],"type":"Point"}
}