{
  "type": "Feature",
  "properties": {
    "iso:country":"US",
    "sg:address":"10 Ramshorn Ct",
    "sg:city":"Savannah",
    "sg:classifiers":[
        {
            "category":"Social Services",
            "subcategory":"Job Training",
            "type":"Services"
        }
    ],
    "sg:phone":"+1 912 658 4865",
    "sg:postcode":"31411",
    "sg:province":"GA",
    "wof:name":"Starfish Aquatics Institute",
    "wof:placetype":"venue"
},
  "geometry": {"coordinates":[-81.03715099999999,31.942795],"type":"Point"}
}