{
  "type": "Feature",
  "properties": {
    "addr:full":"202 Jefferson St Fort Gaines GA 39851",
    "addr:housenumber":"202",
    "addr:postcode":"39851",
    "addr:street":"Jefferson St",
    "iso:country":"US",
    "sg:address":"202 Jefferson St",
    "sg:city":"Fort Gaines",
    "sg:classifiers":[
        {
            "category":"Building & Trades",
            "subcategory":"Construction",
            "type":"Services"
        }
    ],
    "sg:phone":"+1 229 768 3948",
    "sg:postcode":"39851",
    "sg:province":"GA",
    "sg:tags":[
        "contractor"
    ],
    "wof:name":"Ed Smith Construction Co",
    "wof:placetype":"venue"
},
  "geometry": {"coordinates":[-85.05234299999999,31.607416],"type":"Point"}
}