{
  "type": "Feature",
  "properties": {
    "iso:country":"US",
    "sg:address":"4955 Ivy Ridge Dr SE",
    "sg:city":"Smyrna",
    "sg:classifiers":[
        {
            "category":"Building & Trades",
            "subcategory":"Construction",
            "type":"Services"
        }
    ],
    "sg:phone":"+1 678 305 1270",
    "sg:postcode":"30080",
    "sg:province":"GA",
    "sg:tags":[
        "contractor"
    ],
    "wof:name":"John Wieland Homes",
    "wof:placetype":"venue"
},
  "geometry": {"coordinates":[-84.48264,33.843241],"type":"Point"}
}