{
  "type": "Feature",
  "properties": {
    "addr:full":"5250 New Jesup Hwy Brunswick GA 31523",
    "addr:housenumber":"5250",
    "addr:postcode":"31523",
    "addr:street":"New Jesup Hwy",
    "iso:country":"US",
    "sg:address":"5250 New Jesup Hwy",
    "sg:city":"Brunswick",
    "sg:classifiers":[
        {
            "category":"Restaurant",
            "type":"Food & Drink"
        }
    ],
    "sg:phone":"+1 912 280 0091",
    "sg:postcode":"31523",
    "sg:province":"GA",
    "sg:tags":[
        "eating"
    ],
    "wof:name":"Mulligan's Bar & Grill",
    "wof:placetype":"venue"
},
  "geometry": {"coordinates":[-81.52368199999999,31.222132],"type":"Point"}
}