{
  "type": "Feature",
  "properties": {
    "addr:full":"1321 Niskey Lake Rd SW Atlanta GA 30331",
    "addr:housenumber":"1321",
    "addr:postcode":"30331",
    "addr:street":"Niskey Lake Rd Sw",
    "iso:country":"US",
    "sg:address":"1321 Niskey Lake Rd SW",
    "sg:city":"Atlanta",
    "sg:classifiers":[
        {
            "category":"Retail",
            "subcategory":"Auto Repair",
            "type":"Services"
        }
    ],
    "sg:phone":"+1 404 629 1204",
    "sg:postcode":"30331",
    "sg:province":"GA",
    "sg:tags":[
        "automotive",
        "tire",
        "general"
    ],
    "wof:name":"Caine Tire Inc",
    "wof:placetype":"venue"
},
  "geometry": {"coordinates":[-84.535055,33.715704],"type":"Point"}
}