{
  "type": "Feature",
  "properties": {
    "iso:country":"US",
    "sg:address":"700 Waterfield Dr",
    "sg:city":"Hinesville",
    "sg:classifiers":[
        {
            "category":"Professional",
            "subcategory":"Business Services",
            "type":"Services"
        }
    ],
    "sg:phone":"+1 912 572 1008",
    "sg:postcode":"31313",
    "sg:province":"GA",
    "sg:tags":[
        "automotive",
        "repair"
    ],
    "wof:name":"Automotive Maintenance Svcs",
    "wof:placetype":"venue"
},
  "geometry": {"coordinates":[-81.64892399999999,31.802865],"type":"Point"}
}