{
  "type": "Feature",
  "properties": {
    "iso:country":"US",
    "sg:address":"116 Mimosa Dr",
    "sg:city":"Stockbridge",
    "sg:classifiers":[
        {
            "category":"Retail",
            "subcategory":"Repair Shop",
            "type":"Services"
        }
    ],
    "sg:phone":"+1 770 474 0922",
    "sg:postcode":"30281",
    "sg:province":"GA",
    "sg:tags":[
        "appliance"
    ],
    "wof:name":"Aces' Major Appliance Repair",
    "wof:placetype":"venue"
},
  "geometry": {"coordinates":[-84.24177,33.54251],"type":"Point"}
}