{
  "type": "Feature",
  "properties": {
    "addr:full":"983 Bay Berry Ln Lawrenceville GA 30043",
    "addr:housenumber":"983",
    "addr:postcode":"30043",
    "addr:street":"Bay Berry Ln",
    "iso:country":"US",
    "sg:address":"983 Bay Berry Ln",
    "sg:city":"Lawrenceville",
    "sg:classifiers":[
        {
            "category":"Retail",
            "subcategory":"Animal Services",
            "type":"Services"
        }
    ],
    "sg:phone":"+1 770 963 7660",
    "sg:postcode":"30043",
    "sg:province":"GA",
    "sg:tags":[
        "pet"
    ],
    "wof:name":"No Place Like Home",
    "wof:placetype":"venue"
},
  "geometry": {"coordinates":[-83.961823,33.999253],"type":"Point"}
}