{
  "type": "Feature",
  "properties": {
    "iso:country":"US",
    "sg:address":"310 Sandy Run Ct",
    "sg:city":"Augusta",
    "sg:classifiers":[
        {
            "category":"Education",
            "subcategory":"Special Training",
            "type":"Public Place"
        }
    ],
    "sg:phone":"+1 706 650 7882",
    "sg:postcode":"30907",
    "sg:province":"GA",
    "sg:tags":[
        "science",
        "camp",
        "teacher",
        "for"
    ],
    "wof:name":"Elizabeth Toole",
    "wof:placetype":"venue"
},
  "geometry": {"coordinates":[-82.07118,33.507783],"type":"Point"}
}