{
  "type": "Feature",
  "properties": {
    "iso:country":"US",
    "sg:address":"1710 Zebulon Rd",
    "sg:city":"Griffin",
    "sg:classifiers":[
        {
            "category":"Restaurant",
            "type":"Food & Drink"
        }
    ],
    "sg:menulink":"http://www.allmenus.com/ga/griffin/106369-waffle-house/menu/",
    "sg:phone":"+1 770 467 9936",
    "sg:postcode":"30224",
    "sg:province":"GA",
    "sg:tags":[
        "american"
    ],
    "wof:name":"Waffle House",
    "wof:placetype":"venue"
},
  "geometry": {"coordinates":[-84.281941,33.199156],"type":"Point"}
}