{
  "type": "Feature",
  "properties": {
    "iso:country":"US",
    "sg:address":"728 Mallard Dr",
    "sg:city":"Winder",
    "sg:classifiers":[
        {
            "category":"Professional",
            "subcategory":"Management & Consulting",
            "type":"Services"
        }
    ],
    "sg:phone":"+1 770 307 3569",
    "sg:postcode":"30680",
    "sg:province":"GA",
    "sg:tags":[
        "public",
        "relations"
    ],
    "wof:name":"Deivox Music",
    "wof:placetype":"venue"
},
  "geometry": {"coordinates":[-83.74156000000001,34.009092],"type":"Point"}
}