{
  "type": "Feature",
  "properties": {
    "addr:full":"3471 Cherokee Ave Columbus GA 31906",
    "addr:housenumber":"3471",
    "addr:postcode":"31906",
    "addr:street":"Cherokee Ave",
    "iso:country":"US",
    "sg:address":"3471 Cherokee Ave",
    "sg:city":"Columbus",
    "sg:classifiers":[
        {
            "category":"Wholesale",
            "subcategory":"Non-durable Goods",
            "type":"Manufacturing & Wholesale Goods"
        }
    ],
    "sg:phone":"+1 706 323 9422",
    "sg:postcode":"31906",
    "sg:province":"GA",
    "wof:name":"Ruth Brown",
    "wof:placetype":"venue"
},
  "geometry": {"coordinates":[-84.95999500000001,32.49547],"type":"Point"}
}