{
  "type": "Feature",
  "properties": {
    "addr:full":"4404 N Shallowford Rd Atlanta GA 30338",
    "addr:housenumber":"4404",
    "addr:postcode":"30338",
    "addr:street":"N Shallowford Rd",
    "iso:country":"US",
    "sg:address":"4404 N Shallowford Rd",
    "sg:city":"Atlanta",
    "sg:classifiers":[
        {
            "category":"Utilities",
            "subcategory":"Electric",
            "type":"Services"
        }
    ],
    "sg:phone":"+1 770 216 1305",
    "sg:postcode":"30338",
    "sg:province":"GA",
    "wof:name":"Georgia Power Company",
    "wof:placetype":"venue"
},
  "geometry": {"coordinates":[-84.30638999999999,33.923018],"type":"Point"}
}