{
  "type": "Feature",
  "properties": {
    "addr:full":"300 17th Ave NW Cairo GA 39827",
    "addr:housenumber":"300",
    "addr:postcode":"39827",
    "addr:street":"17Th Ave Nw",
    "iso:country":"US",
    "sg:address":"300 17th Ave NW",
    "sg:city":"Cairo",
    "sg:classifiers":[
        {
            "category":"Building & Trades",
            "subcategory":"Construction",
            "type":"Services"
        }
    ],
    "sg:phone":"+1 229 377 7088",
    "sg:postcode":"39827",
    "sg:province":"GA",
    "sg:tags":[
        "carpentry",
        "contractor"
    ],
    "wof:name":"E J Hooper Inc",
    "wof:placetype":"venue"
},
  "geometry": {"coordinates":[-84.212751,30.899418],"type":"Point"}
}