{
  "type": "Feature",
  "properties": {
    "iso:country":"US",
    "sg:address":"4715 S Atlanta Rd SE",
    "sg:city":"Smyrna",
    "sg:classifiers":[
        {
            "category":"Building & Trades",
            "subcategory":"Cleaning & Sanitation",
            "type":"Services"
        }
    ],
    "sg:phone":"+1 770 436 0336",
    "sg:postcode":"30080",
    "sg:province":"GA",
    "sg:tags":[
        "maintenance"
    ],
    "wof:name":"Cloud Nine Cleaning Services",
    "wof:placetype":"venue"
},
  "geometry": {"coordinates":[-84.481236,33.838085],"type":"Point"}
}