{
  "type": "Feature",
  "properties": {
    "iso:country":"US",
    "sg:address":"5191 Eisenhower Pkwy",
    "sg:city":"Macon",
    "sg:classifiers":[
        {
            "category":"Organizations",
            "subcategory":"Religious Organization",
            "type":"Services"
        }
    ],
    "sg:phone":"+1 478 477 5678",
    "sg:postcode":"31206",
    "sg:province":"GA",
    "sg:tags":[
        "church"
    ],
    "wof:name":"Parkway Assembly Of God",
    "wof:placetype":"venue"
},
  "geometry": {"coordinates":[-83.731452,32.8063],"type":"Point"}
}