{
  "type": "Feature",
  "properties": {
    "addr:full":"820 Frank Rd Fitzgerald GA 31750",
    "addr:housenumber":"820",
    "addr:postcode":"31750",
    "addr:street":"Frank Rd",
    "iso:country":"US",
    "sg:address":"820 Frank Rd",
    "sg:city":"Fitzgerald",
    "sg:classifiers":[
        {
            "category":"Retail",
            "subcategory":"Auto Repair",
            "type":"Services"
        }
    ],
    "sg:phone":"+1 229 423 8622",
    "sg:postcode":"31750",
    "sg:province":"GA",
    "sg:tags":[
        "body",
        "automobile",
        "painting"
    ],
    "wof:name":"Paint Barn",
    "wof:placetype":"venue"
},
  "geometry": {"coordinates":[-83.210617,31.65323],"type":"Point"}
}