{
  "type": "Feature",
  "properties": {
    "iso:country":"US",
    "sg:address":"11117 US Hwy 84",
    "sg:city":"Midway",
    "sg:classifiers":[
        {
            "category":"Restaurant",
            "type":"Food & Drink"
        }
    ],
    "sg:phone":"+1 912 884 5657",
    "sg:postcode":"31320",
    "sg:province":"GA",
    "sg:tags":[
        "eating"
    ],
    "wof:name":"Tinas Deli",
    "wof:placetype":"venue"
},
  "geometry": {"coordinates":[-81.42690899999999,31.799816],"type":"Point"}
}