{
  "type": "Feature",
  "properties": {
    "iso:country":"US",
    "sg:address":"194 Lake Forrest Ln NE",
    "sg:city":"Atlanta",
    "sg:classifiers":[
        {
            "category":"Professional",
            "subcategory":"Accounting & Tax Preparation",
            "type":"Services"
        }
    ],
    "sg:phone":"+1 404 252 6741",
    "sg:postcode":"30342",
    "sg:province":"GA",
    "wof:name":"McConnell Brock",
    "wof:placetype":"venue"
},
  "geometry": {"coordinates":[-84.384719,33.874577],"type":"Point"}
}