{
  "type": "Feature",
  "properties": {
    "addr:full":"4300 Bankers Cir Atlanta GA 30360",
    "addr:postcode":"4300;30360",
    "addr:street":"Bankers Cir",
    "iso:country":"US",
    "sg:address":"4300 Bankers Cir",
    "sg:city":"Atlanta",
    "sg:classifiers":[
        {
            "category":"Wholesale",
            "subcategory":"Machinery & Supplies",
            "type":"Manufacturing & Wholesale Goods"
        }
    ],
    "sg:phone":"+1 770 936 9690",
    "sg:postcode":"30360",
    "sg:province":"GA",
    "sg:tags":[
        "dry",
        "screw",
        "importer",
        "fastener"
    ],
    "wof:name":"Inter",
    "wof:placetype":"venue"
},
  "geometry": {"coordinates":[-84.263822,33.924992],"type":"Point"}
}