{
  "type": "Feature",
  "properties": {
    "iso:country":"US",
    "sg:address":"144 E Crogan St",
    "sg:city":"Lawrenceville",
    "sg:classifiers":[
        {
            "category":"Restaurant",
            "type":"Food & Drink"
        }
    ],
    "sg:phone":"+1 770 338 9274",
    "sg:postcode":"30045",
    "sg:province":"GA",
    "wof:name":"Cosmo's Original Little Italy",
    "wof:placetype":"venue"
},
  "geometry": {"coordinates":[-83.97446100000001,33.958398],"type":"Point"}
}