{
  "type": "Feature",
  "properties": {
    "addr:full":"7185 Jonsway Cumming GA 30041",
    "addr:housenumber":"7185",
    "addr:postcode":"30041",
    "addr:street":"Jonsway",
    "iso:country":"US",
    "sg:address":"7185 Jonsway",
    "sg:city":"Cumming",
    "sg:classifiers":[
        {
            "category":"Professional",
            "subcategory":"Management & Consulting",
            "type":"Services"
        }
    ],
    "sg:phone":"+1 770 888 0838",
    "sg:postcode":"30041",
    "sg:province":"GA",
    "sg:tags":[
        "business"
    ],
    "wof:name":"Greycat Consulting",
    "wof:placetype":"venue"
},
  "geometry": {"coordinates":[-84.02931,34.250926],"type":"Point"}
}