{
  "type": "Feature",
  "properties": {
    "addr:full":"320 E 53rd St Savannah GA 31405",
    "addr:housenumber":"320",
    "addr:postcode":"31405",
    "addr:street":"E 53Rd St",
    "iso:country":"US",
    "sg:address":"320 E 53rd St",
    "sg:city":"Savannah",
    "sg:classifiers":[
        {
            "category":"Shopping",
            "subcategory":"Gifts & Souvenirs",
            "type":"Retail Goods"
        }
    ],
    "sg:phone":"+1 912 238 4840",
    "sg:postcode":"31405",
    "sg:province":"GA",
    "wof:name":"Nesmith Gift",
    "wof:placetype":"venue"
},
  "geometry": {"coordinates":[-81.096475,32.042959],"type":"Point"}
}