{
  "type": "Feature",
  "properties": {
    "iso:country":"US",
    "sg:address":"7735 Tara Blvd",
    "sg:city":"Jonesboro",
    "sg:classifiers":[
        {
            "category":"Taxi",
            "type":"Transportation"
        }
    ],
    "sg:phone":"+1 770 473 6008",
    "sg:postcode":"30236",
    "sg:province":"GA",
    "sg:tags":[
        "taxicab"
    ],
    "wof:name":"Victors Taxi",
    "wof:placetype":"venue"
},
  "geometry": {"coordinates":[-84.36511,33.537851],"type":"Point"}
}