{
  "type": "Feature",
  "properties": {
    "iso:country":"US",
    "sg:address":"67 Peachtree Park Dr NE",
    "sg:city":"Atlanta",
    "sg:classifiers":[
        {
            "category":"Banks & Credit Unions",
            "subcategory":"Financial Services",
            "type":"Services"
        }
    ],
    "sg:phone":"+1 404 352 2007",
    "sg:postcode":"30309",
    "sg:province":"GA",
    "sg:tags":[
        "card-merchant"
    ],
    "wof:name":"Falcon Payment Solutions",
    "wof:placetype":"venue"
},
  "geometry": {"coordinates":[-84.38937300000001,33.812439],"type":"Point"}
}