{
  "type": "Feature",
  "properties": {
    "iso:country":"US",
    "sg:address":"1997 State St",
    "sg:city":"Waycross",
    "sg:classifiers":[
        {
            "category":"Bars & Pubs",
            "type":"Food & Drink"
        }
    ],
    "sg:phone":"+1 912 285 2878",
    "sg:postcode":"31501",
    "sg:province":"GA",
    "sg:tags":[
        "club",
        "drinking",
        "night"
    ],
    "wof:name":"Dennis & Marty's",
    "wof:placetype":"venue"
},
  "geometry": {"coordinates":[-82.37203599999999,31.240361],"type":"Point"}
}