{
  "type": "Feature",
  "properties": {
    "addr:full":"3861 Washington Rd Augusta GA 30907",
    "addr:housenumber":"3861",
    "addr:postcode":"30907",
    "addr:street":"Washington Rd",
    "iso:country":"US",
    "sg:address":"3861 Washington Rd",
    "sg:city":"Augusta",
    "sg:classifiers":[
        {
            "category":"Restaurant",
            "type":"Food & Drink"
        }
    ],
    "sg:menulink":"http://www.allmenus.com/ga/evans/196054-taco-bell/menu/",
    "sg:postcode":"30907",
    "sg:province":"GA",
    "sg:tags":[
        "mexican"
    ],
    "wof:name":"Taco Bell",
    "wof:placetype":"venue"
},
  "geometry": {"coordinates":[-82.09313,33.511183],"type":"Point"}
}