{
  "type": "Feature",
  "properties": {
    "addr:full":"84 Jewell Slaton Rd Dawsonville GA 30534",
    "addr:housenumber":"84",
    "addr:postcode":"30534",
    "addr:street":"Jewell Slaton Rd",
    "iso:country":"US",
    "sg:address":"84 Jewell Slaton Rd",
    "sg:city":"Dawsonville",
    "sg:classifiers":[
        {
            "category":"Freight",
            "type":"Transportation"
        }
    ],
    "sg:phone":"+1 678 873 4733",
    "sg:postcode":"30534",
    "sg:province":"GA",
    "sg:tags":[
        "delivery"
    ],
    "wof:name":"Action Delivery Svc Inc",
    "wof:placetype":"venue"
},
  "geometry": {"coordinates":[-84.12335899999999,34.343916],"type":"Point"}
}