{
  "type": "Feature",
  "properties": {
    "addr:full":"1307 Cleveland Rd Bogart GA 30622",
    "addr:housenumber":"1307",
    "addr:postcode":"30622",
    "addr:street":"Cleveland Rd",
    "iso:country":"US",
    "sg:address":"1307 Cleveland Rd",
    "sg:city":"Bogart",
    "sg:classifiers":[
        {
            "category":"Travel",
            "subcategory":"Travel Agent",
            "type":"Entertainment"
        },
        {
            "category":"Airline",
            "type":"Transportation"
        },
        {
            "category":"Railroad",
            "type":"Transportation"
        },
        {
            "category":"Marine",
            "type":"Transportation"
        }
    ],
    "sg:phone":"+1 706 552 3300",
    "sg:postcode":"30622",
    "sg:province":"GA",
    "sg:tags":[
        "railroads-ticket",
        "agency",
        "services-commercial",
        "cruise",
        "ticket"
    ],
    "sg:website":"http://www.the-joy-of-travel.com",
    "wof:name":"The Joy Of Travel",
    "wof:placetype":"venue"
},
  "geometry": {"coordinates":[-83.492593,33.962136],"type":"Point"}
}