{
  "type": "Feature",
  "properties": {
    "iso:country":"US",
    "sg:address":"2188 Columbia Ave",
    "sg:city":"Atlanta",
    "sg:classifiers":[
        {
            "category":"Food & Beverages",
            "subcategory":"Groceries & Convenience Stores",
            "type":"Retail Goods"
        }
    ],
    "sg:phone":"+1 404 755 4047",
    "sg:postcode":"30337",
    "sg:province":"GA",
    "wof:name":"EMB African Market",
    "wof:placetype":"venue"
},
  "geometry": {"coordinates":[-84.45749000000001,33.652173],"type":"Point"}
}