{
  "type": "Feature",
  "properties": {
    "iso:country":"US",
    "sg:address":"3483 Satellite Blvd",
    "sg:city":"Duluth",
    "sg:classifiers":[
        {
            "category":"Banks & Credit Unions",
            "subcategory":"Financial Services",
            "type":"Services"
        }
    ],
    "sg:phone":"+1 770 418 9668",
    "sg:postcode":"30096",
    "sg:province":"GA",
    "sg:tags":[
        "broker",
        "mortgage"
    ],
    "wof:name":"Eagle Nationwide Mortgage Company",
    "wof:placetype":"venue"
},
  "geometry": {"coordinates":[-84.13239299999999,33.962542],"type":"Point"}
}