{
  "type": "Feature",
  "properties": {
    "addr:full":"1007 Union Center Dr Alpharetta GA 30004",
    "addr:housenumber":"1007",
    "addr:postcode":"30004",
    "addr:street":"Union Center Dr",
    "iso:country":"US",
    "sg:address":"1007 Union Center Dr",
    "sg:city":"Alpharetta",
    "sg:classifiers":[
        {
            "category":"Shopping",
            "subcategory":"Clothing, Apparel, & Fashions",
            "type":"Retail Goods"
        }
    ],
    "sg:phone":"+1 678 672 6290",
    "sg:postcode":"30004",
    "sg:province":"GA",
    "sg:tags":[
        "apparel",
        "racing",
        "merchandise"
    ],
    "wof:name":"Monette Racing Group",
    "wof:placetype":"venue"
},
  "geometry": {"coordinates":[-84.234009,34.126239],"type":"Point"}
}