{
  "type": "Feature",
  "properties": {
    "addr:full":"1745 Lake Heights Cir Dacula GA 30019",
    "addr:housenumber":"1745",
    "addr:postcode":"ga 30019",
    "addr:street":"Lake Heights Cir",
    "iso:country":"US",
    "sg:address":"1745 Lake Heights Cir",
    "sg:city":"Dacula",
    "sg:classifiers":[
        {
            "category":"Retail",
            "subcategory":"Portrait Studio",
            "type":"Services"
        }
    ],
    "sg:phone":"+1 770 904 0475",
    "sg:postcode":"30019",
    "sg:province":"GA",
    "sg:tags":[
        "photo"
    ],
    "wof:name":"Bowman Photography",
    "wof:placetype":"venue"
},
  "geometry": {"coordinates":[-83.900963,34.050263],"type":"Point"}
}