{
  "type": "Feature",
  "properties": {
    "iso:country":"US",
    "sg:address":"2618 Max Cleland Blvd",
    "sg:city":"Lithonia",
    "sg:classifiers":[
        {
            "category":"Shopping",
            "subcategory":"Crafts & Fabrics",
            "type":"Retail Goods"
        }
    ],
    "sg:phone":"+1 770 484 1844",
    "sg:postcode":"30058",
    "sg:province":"GA",
    "sg:tags":[
        "art"
    ],
    "sg:website":"www.crazyoncrafts.com",
    "wof:name":"Crazy On Crafts",
    "wof:placetype":"venue"
},
  "geometry": {"coordinates":[-84.10894500000001,33.710955],"type":"Point"}
}