{
  "type": "Feature",
  "properties": {
    "iso:country":"US",
    "sg:address":"2794 Clairmont Rd NE",
    "sg:city":"Atlanta",
    "sg:classifiers":[
        {
            "category":"Food & Beverages",
            "subcategory":"Groceries & Convenience Stores",
            "type":"Retail Goods"
        }
    ],
    "sg:phone":"+1 404 321 3405",
    "sg:postcode":"30329",
    "sg:province":"GA",
    "sg:website":"www.shell.com",
    "wof:name":"Shell Food Mart",
    "wof:placetype":"venue"
},
  "geometry": {"coordinates":[-84.312275,33.838036],"type":"Point"}
}