{
  "type": "Feature",
  "properties": {
    "addr:full":"871 Dawsonville Hwy Gainesville GA 30501",
    "addr:housenumber":"871",
    "addr:postcode":"30501",
    "addr:street":"Dawsonville Hwy",
    "iso:country":"US",
    "sg:address":"871 Dawsonville Hwy",
    "sg:city":"Gainesville",
    "sg:classifiers":[
        {
            "category":"Personal",
            "subcategory":"Nail Salon",
            "type":"Services"
        }
    ],
    "sg:phone":"+1 770 297 0092",
    "sg:postcode":"30501",
    "sg:province":"GA",
    "wof:name":"Solara Sol",
    "wof:placetype":"venue"
},
  "geometry": {"coordinates":[-83.85677200000001,34.298355],"type":"Point"}
}