{
  "type": "Feature",
  "properties": {
    "addr:full":"5386 Lambert Dr Norcross GA 30093",
    "addr:housenumber":"5386",
    "addr:postcode":"30093",
    "addr:street":"Lambert Dr",
    "iso:country":"US",
    "sg:address":"5386 Lambert Dr",
    "sg:city":"Norcross",
    "sg:classifiers":[
        {
            "category":"Professional",
            "subcategory":"Research",
            "type":"Services"
        }
    ],
    "sg:phone":"+1 770 935 7526",
    "sg:postcode":"30093",
    "sg:province":"GA",
    "sg:tags":[
        "environmental",
        "ecological"
    ],
    "wof:name":"Grove Environmental",
    "wof:placetype":"venue"
},
  "geometry": {"coordinates":[-84.17131999999999,33.904846],"type":"Point"}
}