{
  "type": "Feature",
  "properties": {
    "iso:country":"US",
    "sg:address":"204 Longview Dr",
    "sg:city":"Rossville",
    "sg:classifiers":[
        {
            "category":"Building & Trades",
            "subcategory":"Construction",
            "type":"Services"
        }
    ],
    "sg:phone":"+1 706 861 6135",
    "sg:postcode":"30741",
    "sg:province":"GA",
    "sg:tags":[
        "house"
    ],
    "wof:name":"Paving & Paving",
    "wof:placetype":"venue"
},
  "geometry": {"coordinates":[-85.270715,34.967609],"type":"Point"}
}