{
  "type": "Feature",
  "properties": {
    "iso:country":"US",
    "sg:address":"2817 Clifton Springs Rd",
    "sg:city":"Decatur",
    "sg:classifiers":[
        {
            "category":"Arena",
            "subcategory":"Sports Club",
            "type":"Entertainment"
        }
    ],
    "sg:phone":"+1 404 243 4737",
    "sg:postcode":"30034",
    "sg:province":"GA",
    "wof:name":"Panthersville Stadium",
    "wof:placetype":"venue"
},
  "geometry": {"coordinates":[-84.27931700000001,33.690502],"type":"Point"}
}