{
  "type": "Feature",
  "properties": {
    "iso:country":"US",
    "sg:address":"110 Old Buford Rd",
    "sg:city":"Cumming",
    "sg:classifiers":[
        {
            "category":"Health Services",
            "subcategory":"Health Practitioner",
            "type":"Services"
        }
    ],
    "sg:phone":"+1 770 205 1751",
    "sg:postcode":"30040",
    "sg:province":"GA",
    "wof:name":"Jeanne Latiolais Psyd",
    "wof:placetype":"venue"
},
  "geometry": {"coordinates":[-84.13909200000001,34.206877],"type":"Point"}
}