{
  "type": "Feature",
  "properties": {
    "addr:full":"2587 Crestdale Cir SE Atlanta GA 30316",
    "addr:housenumber":"2587",
    "addr:postcode":"30316",
    "addr:street":"Crestdale Cir Se",
    "iso:country":"US",
    "sg:address":"2587 Crestdale Cir SE",
    "sg:city":"Atlanta",
    "sg:classifiers":[
        {
            "category":"Building & Trades",
            "subcategory":"Cleaning & Sanitation",
            "type":"Services"
        }
    ],
    "sg:phone":"+1 404 343 0231",
    "sg:postcode":"30316",
    "sg:province":"GA",
    "sg:tags":[
        "maintenance"
    ],
    "wof:name":"R & H",
    "wof:placetype":"venue"
},
  "geometry": {"coordinates":[-84.33728000000001,33.712622],"type":"Point"}
}