{
  "type": "Feature",
  "properties": {
    "addr:full":"488 Bartram Street Suite B Atlanta GA 30316",
    "addr:housenumber":"488",
    "addr:postcode":"30316",
    "addr:street":"Bartram Street Suite B",
    "iso:country":"US",
    "sg:address":"488 Bartram Street Suite B",
    "sg:city":"Atlanta",
    "sg:classifiers":[
        {
            "category":"Professional",
            "subcategory":"Art Services",
            "type":"Services"
        },
        {
            "category":"Communications",
            "type":"Services"
        }
    ],
    "sg:phone":"+1 404 622 1099",
    "sg:postcode":"30316",
    "sg:province":"GA",
    "sg:tags":[
        "web",
        "graphic",
        "design"
    ],
    "sg:website":"www.vistabranding.com",
    "wof:name":"Vista Branding",
    "wof:placetype":"venue"
},
  "geometry": {"coordinates":[-84.357096,33.740907],"type":"Point"}
}