{
  "type": "Feature",
  "properties": {
    "iso:country":"US",
    "sg:address":"291 E Davis Bridge Rd",
    "sg:city":"Villa Rica",
    "sg:classifiers":[
        {
            "category":"Professional",
            "subcategory":"Business Services",
            "type":"Services"
        }
    ],
    "sg:phone":"+1 770 459 1806",
    "sg:postcode":"30180",
    "sg:province":"GA",
    "sg:tags":[
        "brokerage"
    ],
    "wof:name":"Poly Plus",
    "wof:placetype":"venue"
},
  "geometry": {"coordinates":[-84.98751,33.71329],"type":"Point"}
}