{
  "type": "Feature",
  "properties": {
    "addr:full":"112 E Commerce St Pineview GA 31071",
    "addr:housenumber":"112",
    "addr:postcode":"31071",
    "addr:street":"E Commerce St",
    "iso:country":"US",
    "sg:address":"112 E Commerce St",
    "sg:city":"Pineview",
    "sg:classifiers":[
        {
            "category":"Food & Beverages",
            "subcategory":"Groceries & Convenience Stores",
            "type":"Retail Goods"
        }
    ],
    "sg:phone":"+1 229 624 2380",
    "sg:postcode":"31071",
    "sg:province":"GA",
    "wof:name":"Doc's Quick Stop",
    "wof:placetype":"venue"
},
  "geometry": {"coordinates":[-83.500984,32.110064],"type":"Point"}
}