{
  "type": "Feature",
  "properties": {
    "addr:full":"367 W Warren Rd La Fayette GA 30728",
    "addr:housenumber":"367",
    "addr:postcode":"30728",
    "addr:street":"W Warren Rd",
    "iso:country":"US",
    "sg:address":"367 W Warren Rd",
    "sg:city":"La Fayette",
    "sg:classifiers":[
        {
            "category":"Health Services",
            "subcategory":"Clinic",
            "type":"Services"
        },
        {
            "category":"Social Services",
            "type":"Services"
        }
    ],
    "sg:phone":"+1 706 639 1889",
    "sg:postcode":"30728",
    "sg:province":"GA",
    "sg:tags":[
        "organization",
        "welfare",
        "specialty",
        "outpatient"
    ],
    "wof:name":"A Plus Women's Care",
    "wof:placetype":"venue"
},
  "geometry": {"coordinates":[-85.27281000000001,34.751259],"type":"Point"}
}