{
  "type": "Feature",
  "properties": {
    "addr:full":"120 Stone Bridge Pkwy Woodstock GA 30101",
    "addr:housenumber":"120",
    "addr:postcode":"30101",
    "addr:street":"Stone Bridge Pkwy",
    "iso:country":"US",
    "sg:address":"120 Stone Bridge Pkwy",
    "sg:city":"Woodstock",
    "sg:classifiers":[
        {
            "category":"Professional",
            "type":"Services"
        }
    ],
    "sg:phone":"+1 770 517 5882",
    "sg:postcode":"30101",
    "sg:province":"GA",
    "sg:tags":[
        "establishment"
    ],
    "wof:name":"Group Vi",
    "wof:placetype":"venue"
},
  "geometry": {"coordinates":[-84.536214,34.10161],"type":"Point"}
}