{
  "type": "Feature",
  "properties": {
    "addr:full":"4598 Atlanta Hwy Bogart GA 30622",
    "addr:housenumber":"4598",
    "addr:postcode":"30622",
    "addr:street":"Atlanta Hwy Bogart",
    "iso:country":"US",
    "sg:address":"4598 Atlanta Hwy",
    "sg:city":"Bogart",
    "sg:classifiers":[
        {
            "category":"Real Estate",
            "subcategory":"Real Estate Operator",
            "type":"Services"
        }
    ],
    "sg:phone":"+1 706 548 0230",
    "sg:postcode":"30622",
    "sg:province":"GA",
    "sg:tags":[
        "building",
        "parks"
    ],
    "wof:name":"Quality Buildings Of Athens",
    "wof:placetype":"venue"
},
  "geometry": {"coordinates":[-83.494955,33.940098],"type":"Point"}
}