{
  "type": "Feature",
  "properties": {
    "addr:full":"532 Barber St Athens GA 30601",
    "addr:housenumber":"532",
    "addr:postcode":"30601",
    "addr:street":"Barber St",
    "iso:country":"US",
    "sg:address":"532 Barber St",
    "sg:city":"Athens",
    "sg:classifiers":[
        {
            "category":"Shopping",
            "subcategory":"Used Merchandise",
            "type":"Retail Goods"
        }
    ],
    "sg:phone":"+1 706 354 0936",
    "sg:postcode":"30601",
    "sg:province":"GA",
    "sg:tags":[
        "shop",
        "thrift"
    ],
    "wof:name":"Habitat For Humanity",
    "wof:placetype":"venue"
},
  "geometry": {"coordinates":[-83.386409,33.968209],"type":"Point"}
}