{
  "type": "Feature",
  "properties": {
    "addr:full":"2060 Eagle Pt Dalton GA 30720",
    "addr:housenumber":"2060",
    "addr:postcode":"30720",
    "addr:street":"Eagle Pt",
    "iso:country":"US",
    "sg:address":"2060 Eagle Pt",
    "sg:city":"Dalton",
    "sg:classifiers":[
        {
            "category":"Airline",
            "type":"Transportation"
        }
    ],
    "sg:phone":"+1 706 277 9920",
    "sg:postcode":"30720",
    "sg:province":"GA",
    "sg:tags":[
        "scheduled",
        "air"
    ],
    "wof:name":"International Helicopter",
    "wof:placetype":"venue"
},
  "geometry": {"coordinates":[-85.012655,34.717323],"type":"Point"}
}