{
  "type": "Feature",
  "properties": {
    "iso:country":"US",
    "sg:address":"340 Stone Mill Trl NE",
    "sg:city":"Atlanta",
    "sg:classifiers":[
        {
            "category":"Professional",
            "type":"Services"
        }
    ],
    "sg:phone":"+1 404 303 7521",
    "sg:postcode":"30328",
    "sg:province":"GA",
    "wof:name":"Amy L Alcorn",
    "wof:placetype":"venue"
},
  "geometry": {"coordinates":[-84.381828,33.942748],"type":"Point"}
}