{
  "type": "Feature",
  "properties": {
    "iso:country":"US",
    "sg:address":"101 Atlantic Ave",
    "sg:city":"Fort Valley",
    "sg:classifiers":[
        {
            "category":"Real Estate",
            "subcategory":"Real Estate Operator",
            "type":"Services"
        }
    ],
    "sg:phone":"+1 478 825 7313",
    "sg:postcode":"31030",
    "sg:province":"GA",
    "sg:tags":[
        "apartment"
    ],
    "wof:name":"Marvin Gardens II",
    "wof:placetype":"venue"
},
  "geometry": {"coordinates":[-83.88946799999999,32.544981],"type":"Point"}
}