{
  "type": "Feature",
  "properties": {
    "addr:full":"3600 Lawrenceville Suwanee Rd Suwanee GA 30024",
    "addr:housenumber":"3600",
    "addr:postcode":"30024",
    "addr:street":"Lawrenceville Suwanee Rd",
    "iso:country":"US",
    "sg:address":"3600 Lawrenceville Suwanee Rd",
    "sg:city":"Suwanee",
    "sg:classifiers":[
        {
            "category":"Organizations",
            "subcategory":"Labor Organization",
            "type":"Services"
        },
        {
            "category":"Building & Trades",
            "subcategory":"Cleaning & Sanitation",
            "type":"Services"
        }
    ],
    "sg:phone":"+1 770 932 8668",
    "sg:postcode":"30024",
    "sg:province":"GA",
    "sg:tags":[
        "sweeping",
        "street",
        "service-power"
    ],
    "wof:name":"Atlanta Sweeping Services",
    "wof:placetype":"venue"
},
  "geometry": {"coordinates":[-84.059048,34.046533],"type":"Point"}
}