{
  "type": "Feature",
  "properties": {
    "iso:country":"US",
    "sg:address":"406 Lawton St SW",
    "sg:city":"Atlanta",
    "sg:classifiers":[
        {
            "category":"Government",
            "subcategory":"Office",
            "type":"Public Place"
        }
    ],
    "sg:phone":"+1 404 752 8751",
    "sg:postcode":"30310",
    "sg:province":"GA",
    "sg:tags":[
        "county",
        "program",
        "health"
    ],
    "wof:name":"Roy Mc Gee Health Ctr",
    "wof:placetype":"venue"
},
  "geometry": {"coordinates":[-84.423239,33.744298],"type":"Point"}
}