{
  "type": "Feature",
  "properties": {
    "addr:full":"627 N St Marys Ln NE Marietta GA 30064",
    "addr:housenumber":"627",
    "addr:postcode":"30064",
    "addr:street":"N St Marys Ln Ne",
    "iso:country":"US",
    "sg:address":"627 N St Marys Ln NE",
    "sg:city":"Marietta",
    "sg:classifiers":[
        {
            "category":"Health Services",
            "subcategory":"Doctor",
            "type":"Services"
        }
    ],
    "sg:phone":"+1 770 427 7481",
    "sg:postcode":"30064",
    "sg:province":"GA",
    "wof:name":"Doxey Clem M Jr MD",
    "wof:placetype":"venue"
},
  "geometry": {"coordinates":[-84.575633,33.969649],"type":"Point"}
}