{
  "type": "Feature",
  "properties": {
    "addr:full":"29 Arbor Hills Ter Talking Rock GA 30175",
    "addr:housenumber":"29",
    "addr:postcode":"30175",
    "addr:street":"Arbor Hills Ter",
    "iso:country":"US",
    "sg:address":"29 Arbor Hills Ter",
    "sg:city":"Talking Rock",
    "sg:classifiers":[
        {
            "category":"Real Estate",
            "subcategory":"Developer",
            "type":"Services"
        }
    ],
    "sg:phone":"+1 706 253 1455",
    "sg:postcode":"30175",
    "sg:province":"GA",
    "wof:name":"Arbor Hills Community",
    "wof:placetype":"venue"
},
  "geometry": {"coordinates":[-84.452313,34.490821],"type":"Point"}
}