{
  "type": "Feature",
  "properties": {
    "iso:country":"US",
    "sg:address":"3747 Kensington Ct",
    "sg:city":"Decatur",
    "sg:classifiers":[
        {
            "category":"Personal",
            "subcategory":"Beauty Salon",
            "type":"Services"
        }
    ],
    "sg:phone":"+1 404 298 3383",
    "sg:postcode":"30032",
    "sg:province":"GA",
    "sg:tags":[
        "shop"
    ],
    "wof:name":"Shawlawn's Salon & Spa",
    "wof:placetype":"venue"
},
  "geometry": {"coordinates":[-84.237962,33.76911],"type":"Point"}
}