{
  "type": "Feature",
  "properties": {
    "addr:full":"3374 Aztec Road Atlanta GA 30340",
    "addr:housenumber":"3374",
    "addr:postcode":"30340",
    "addr:street":"Aztec Road",
    "iso:country":"US",
    "sg:address":"3374 Aztec Road",
    "sg:city":"Atlanta",
    "sg:classifiers":[
        {
            "category":"Real Estate",
            "subcategory":"Real Estate Operator",
            "type":"Services"
        }
    ],
    "sg:phone":"+1 770 455 4470",
    "sg:postcode":"30340",
    "sg:province":"GA",
    "sg:tags":[
        "apartment"
    ],
    "wof:name":"Chestnut Creek Apartments",
    "wof:placetype":"venue"
},
  "geometry": {"coordinates":[-84.27048600000001,33.888265],"type":"Point"}
}