{
  "type": "Feature",
  "properties": {
    "addr:full":"2765 Roxburgh Dr Roswell GA 30076",
    "addr:housenumber":"2765",
    "addr:postcode":"30076",
    "addr:street":"Roxburgh Dr",
    "iso:country":"US",
    "sg:address":"2765 Roxburgh Dr",
    "sg:city":"Roswell",
    "sg:classifiers":[
        {
            "category":"Wholesale",
            "subcategory":"Apparel",
            "type":"Manufacturing & Wholesale Goods"
        }
    ],
    "sg:phone":"+1 770 475 9534",
    "sg:postcode":"30076",
    "sg:province":"GA",
    "sg:tags":[
        "footwear"
    ],
    "wof:name":"John Hunter Co",
    "wof:placetype":"venue"
},
  "geometry": {"coordinates":[-84.281035,34.034327],"type":"Point"}
}