{
  "type": "Feature",
  "properties": {
    "iso:country":"US",
    "sg:address":"1111 Buffington Dr",
    "sg:city":"Pendergrass",
    "sg:classifiers":[
        {
            "category":"Home & Garden",
            "subcategory":"Building Materials",
            "type":"Retail Goods"
        },
        {
            "category":"Building & Trades",
            "subcategory":"Construction",
            "type":"Services"
        },
        {
            "category":"Manufacturing",
            "subcategory":"Building Materials",
            "type":"Manufacturing & Wholesale Goods"
        }
    ],
    "sg:phone":"+1 770 654 4545",
    "sg:postcode":"30567",
    "sg:province":"GA",
    "sg:tags":[
        "gate",
        "fence-sales",
        "accessory",
        "fence",
        "contractor"
    ],
    "wof:name":"Legendary Fencing",
    "wof:placetype":"venue"
},
  "geometry": {"coordinates":[-83.670113,34.230998],"type":"Point"}
}