{
  "type": "Feature",
  "properties": {
    "addr:full":"995 Ednaville Rd Braselton GA 30517",
    "addr:housenumber":"995",
    "addr:postcode":"30517",
    "addr:street":"Ednaville Rd",
    "iso:country":"US",
    "sg:address":"995 Ednaville Rd",
    "sg:city":"Braselton",
    "sg:classifiers":[
        {
            "category":"Organizations",
            "subcategory":"Religious Organization",
            "type":"Services"
        }
    ],
    "sg:phone":"+1 706 654 9089",
    "sg:postcode":"30517",
    "sg:province":"GA",
    "sg:tags":[
        "church"
    ],
    "wof:name":"Braselton Congregation-Jehovah",
    "wof:placetype":"venue"
},
  "geometry": {"coordinates":[-83.785195,34.122223],"type":"Point"}
}