{
  "type": "Feature",
  "properties": {
    "iso:country":"US",
    "sg:address":"3425 Main St.",
    "sg:city":"Lilburn",
    "sg:classifiers":[
        {
            "category":"Manufacturing",
            "subcategory":"Electronics",
            "type":"Manufacturing & Wholesale Goods"
        },
        {
            "category":"Building & Trades",
            "subcategory":"Construction",
            "type":"Services"
        },
        {
            "category":"Building & Trades",
            "subcategory":"Electrical",
            "type":"Services"
        }
    ],
    "sg:phone":"+1 678 294 7903",
    "sg:postcode":"30047",
    "sg:province":"GA",
    "sg:tags":[
        "control",
        "industrial",
        "electric",
        "contractor",
        "regulators-control",
        "contractors-commercial",
        "panel"
    ],
    "wof:name":"Apex Appliance repair",
    "wof:placetype":"venue"
},
  "geometry": {"coordinates":[-84.14111699999999,33.892715],"type":"Point"}
}