{
  "type": "Feature",
  "properties": {
    "addr:full":"100 Parkway Ave Smyrna GA 30080",
    "addr:housenumber":"100",
    "addr:postcode":"30080",
    "addr:street":"Parkway Ave",
    "iso:country":"US",
    "sg:address":"100 Parkway Ave",
    "sg:city":"Smyrna",
    "sg:classifiers":[
        {
            "category":"Real Estate",
            "subcategory":"Real Estate Agent",
            "type":"Services"
        },
        {
            "category":"Real Estate",
            "subcategory":"Real Estate Operator",
            "type":"Services"
        }
    ],
    "sg:phone":"+1 770 434 6144",
    "sg:postcode":"30080",
    "sg:province":"GA",
    "sg:tags":[
        "company",
        "apartment",
        "investment"
    ],
    "wof:name":"Brighton Way Apartments",
    "wof:placetype":"venue"
},
  "geometry": {"coordinates":[-84.492058,33.896636],"type":"Point"}
}