{
  "type": "Feature",
  "properties": {
    "addr:full":"144 Habersham Ter Cornelia GA 30531",
    "addr:housenumber":"144",
    "addr:postcode":"30531",
    "addr:street":"Habersham Ter Cornelia",
    "iso:country":"US",
    "sg:address":"144 Habersham Ter",
    "sg:city":"Cornelia",
    "sg:classifiers":[
        {
            "category":"Personal",
            "subcategory":"Beauty Salon",
            "type":"Services"
        }
    ],
    "sg:phone":"+1 706 776 7988",
    "sg:postcode":"30531",
    "sg:province":"GA",
    "wof:name":"Cost Cutters Family Hair Care",
    "wof:placetype":"venue"
},
  "geometry": {"coordinates":[-83.51573999999999,34.509792],"type":"Point"}
}