{
  "type": "Feature",
  "properties": {
    "addr:full":"3635 US Hwy 280 Cobb GA 31735",
    "addr:housenumber":"3635",
    "addr:postcode":"31735",
    "addr:street":"Us Hwy 280",
    "iso:country":"US",
    "sg:address":"3635 US Hwy 280",
    "sg:city":"Cobb",
    "sg:classifiers":[
        {
            "category":"Professional",
            "type":"Services"
        }
    ],
    "sg:phone":"+1 229 853 3205",
    "sg:postcode":"31735",
    "sg:province":"GA",
    "wof:name":"Plant Place",
    "wof:placetype":"venue"
},
  "geometry": {"coordinates":[-83.97465200000001,31.95818],"type":"Point"}
}