{
  "type": "Feature",
  "properties": {
    "iso:country":"US",
    "sg:address":"52 N Avondale Rd",
    "sg:city":"Avondale Estates",
    "sg:classifiers":[
        {
            "category":"Banks & Credit Unions",
            "subcategory":"Bank",
            "type":"Services"
        }
    ],
    "sg:phone":"+1 404 297 1190",
    "sg:postcode":"30002",
    "sg:province":"GA",
    "sg:tags":[
        "national",
        "commercial"
    ],
    "wof:name":"Bank of America",
    "wof:placetype":"venue"
},
  "geometry": {"coordinates":[-84.26927499999999,33.775946],"type":"Point"}
}