{
  "type": "Feature",
  "properties": {
    "addr:full":"742 Simon Park Cir Lawrenceville GA 30045",
    "addr:housenumber":"742",
    "addr:postcode":"30045",
    "addr:street":"Simon Park Cir",
    "iso:country":"US",
    "sg:address":"742 Simon Park Cir",
    "sg:city":"Lawrenceville",
    "sg:classifiers":[
        {
            "category":"Professional",
            "type":"Services"
        }
    ],
    "sg:phone":"+1 770 237 5129",
    "sg:postcode":"30045",
    "sg:province":"GA",
    "wof:name":"Key Focus Inc",
    "wof:placetype":"venue"
},
  "geometry": {"coordinates":[-83.944298,33.947682],"type":"Point"}
}