{
  "type": "Feature",
  "properties": {
    "iso:country":"US",
    "sg:address":"1218 W Paces Ferry Rd NW",
    "sg:city":"Atlanta",
    "sg:classifiers":[
        {
            "category":"Health Services",
            "subcategory":"Dentist",
            "type":"Services"
        }
    ],
    "sg:phone":"+1 404 262 2212",
    "sg:postcode":"30327",
    "sg:province":"GA",
    "sg:tags":[
        "orthodontist"
    ],
    "wof:name":"Yurfest Paul DDS PC",
    "wof:placetype":"venue"
},
  "geometry": {"coordinates":[-84.427803,33.8498],"type":"Point"}
}