{
  "type": "Feature",
  "properties": {
    "addr:full":"2975 Lenora Springs Dr Snellville GA 30039",
    "addr:housenumber":"2975",
    "addr:postcode":"30039",
    "addr:street":"Lenora Springs Dr",
    "iso:country":"US",
    "sg:address":"2975 Lenora Springs Dr",
    "sg:city":"Snellville",
    "sg:classifiers":[
        {
            "category":"Organizations",
            "subcategory":"Religious Organization",
            "type":"Services"
        }
    ],
    "sg:phone":"+1 770 985 1892",
    "sg:postcode":"30039",
    "sg:province":"GA",
    "wof:name":"Untd Hlth Care Svcs Inc",
    "wof:placetype":"venue"
},
  "geometry": {"coordinates":[-84.00636799999999,33.80808],"type":"Point"}
}