{
  "type": "Feature",
  "properties": {
    "addr:full":"3323 Burnt Hickory Rd NW Marietta GA 30064",
    "addr:housenumber":"3323",
    "addr:postcode":"30064",
    "addr:street":"Burnt Hickory Rd Nw",
    "iso:country":"US",
    "sg:address":"3323 Burnt Hickory Rd NW",
    "sg:city":"Marietta",
    "sg:classifiers":[
        {
            "category":"Shopping",
            "type":"Retail Goods"
        }
    ],
    "sg:phone":"+1 678 355 5555",
    "sg:postcode":"30064",
    "sg:province":"GA",
    "sg:tags":[
        "equipment",
        "care",
        "health",
        "home"
    ],
    "wof:name":"Barr & Assoc",
    "wof:placetype":"venue"
},
  "geometry": {"coordinates":[-84.64901399999999,33.966517],"type":"Point"}
}