{
  "type": "Feature",
  "properties": {
    "addr:full":"1108 Bear Creek Blvd Hampton GA 30228",
    "addr:housenumber":"1108",
    "addr:postcode":"30228",
    "addr:street":"Bear Creek Blvd",
    "iso:country":"US",
    "sg:address":"1108 Bear Creek Blvd",
    "sg:city":"Hampton",
    "sg:classifiers":[
        {
            "category":"Social Services",
            "subcategory":"Child Care",
            "type":"Services"
        }
    ],
    "sg:phone":"+1 770 897 0603",
    "sg:postcode":"30228",
    "sg:province":"GA",
    "sg:tags":[
        "day"
    ],
    "sg:website":"www.sunshinehouse.com",
    "wof:name":"Sunshine House Inc",
    "wof:placetype":"venue"
},
  "geometry": {"coordinates":[-84.297284,33.373387],"type":"Point"}
}