{
  "type": "Feature",
  "properties": {
    "addr:full":"2073 Perrin Dr Lawrenceville GA 30043",
    "addr:housenumber":"2073",
    "addr:postcode":"30043",
    "addr:street":"Perrin Dr",
    "iso:country":"US",
    "sg:address":"2073 Perrin Dr",
    "sg:city":"Lawrenceville",
    "sg:classifiers":[
        {
            "category":"Building & Trades",
            "subcategory":"Construction",
            "type":"Services"
        }
    ],
    "sg:phone":"+1 770 339 0851",
    "sg:postcode":"30043",
    "sg:province":"GA",
    "sg:tags":[
        "concrete",
        "contractor"
    ],
    "wof:name":"Metro Walls & Foundation Inc",
    "wof:placetype":"venue"
},
  "geometry": {"coordinates":[-83.99485,34.023526],"type":"Point"}
}