{
  "type": "Feature",
  "properties": {
    "addr:full":"3323 Bemiss Rd Valdosta GA 31605",
    "addr:housenumber":"3323",
    "addr:postcode":"31605",
    "addr:street":"Bemiss Rd",
    "iso:country":"US",
    "sg:address":"3323 Bemiss Rd",
    "sg:city":"Valdosta",
    "sg:classifiers":[
        {
            "category":"Professional",
            "subcategory":"Computer Services",
            "type":"Services"
        }
    ],
    "sg:phone":"+1 229 242 5613",
    "sg:postcode":"31605",
    "sg:province":"GA",
    "wof:name":"Total Technology Integrators",
    "wof:placetype":"venue"
},
  "geometry": {"coordinates":[-83.272851,30.884369],"type":"Point"}
}