{
  "type": "Feature",
  "properties": {
    "addr:full":"210 Riverdale Dr Macon GA 31204",
    "addr:housenumber":"210",
    "addr:postcode":"31204",
    "addr:street":"Riverdale Dr",
    "iso:country":"US",
    "sg:address":"210 Riverdale Dr",
    "sg:city":"Macon",
    "sg:classifiers":[
        {
            "category":"Organizations",
            "subcategory":"Religious Organization",
            "type":"Services"
        }
    ],
    "sg:phone":"+1 478 471 7164",
    "sg:postcode":"31204",
    "sg:province":"GA",
    "wof:name":"Christ Chapel",
    "wof:placetype":"venue"
},
  "geometry": {"coordinates":[-83.682163,32.862471],"type":"Point"}
}