{
  "type": "Feature",
  "properties": {
    "iso:country":"US",
    "sg:address":"225 Peachtree Street NE",
    "sg:city":"Atlanta",
    "sg:classifiers":[
        {
            "category":"Professional",
            "subcategory":"Lawyer & Legal Services",
            "type":"Services"
        }
    ],
    "sg:phone":"+1 404 524 7212",
    "sg:postcode":"30303",
    "sg:province":"GA",
    "wof:name":"Holiday & Associates",
    "wof:placetype":"venue"
},
  "geometry": {"coordinates":[-84.38752100000001,33.760084],"type":"Point"}
}