{
  "type": "Feature",
  "properties": {
    "iso:country":"US",
    "sg:address":"500 Sugar Mill Rd",
    "sg:city":"Atlanta",
    "sg:classifiers":[
        {
            "category":"Professional",
            "subcategory":"Engineering",
            "type":"Services"
        }
    ],
    "sg:phone":"+1 770 650 9061",
    "sg:postcode":"30350",
    "sg:province":"GA",
    "sg:tags":[
        "engineer"
    ],
    "wof:name":"Phillips Engineering Group PC",
    "wof:placetype":"venue"
},
  "geometry": {"coordinates":[-84.356273,33.980899],"type":"Point"}
}