{
  "type": "Feature",
  "properties": {
    "addr:full":"1700 Bold Springs Church Rd Carnesville GA 30521",
    "addr:housenumber":"1700",
    "addr:postcode":"30521",
    "addr:street":"Bold Springs Church Rd",
    "iso:country":"US",
    "sg:address":"1700 Bold Springs Church Rd",
    "sg:city":"Carnesville",
    "sg:classifiers":[
        {
            "category":"Wholesale",
            "subcategory":"Poultry",
            "type":"Manufacturing & Wholesale Goods"
        }
    ],
    "sg:phone":"+1 706 335 9288",
    "sg:postcode":"30521",
    "sg:province":"GA",
    "wof:name":"Rocking F Farm",
    "wof:placetype":"venue"
},
  "geometry": {"coordinates":[-83.355543,34.325291],"type":"Point"}
}