{
  "type": "Feature",
  "properties": {
    "addr:full":"1019 Perry Cove Savannah GA 31410",
    "addr:housenumber":"1019",
    "addr:postcode":"31410",
    "addr:street":"Perry Cove",
    "iso:country":"US",
    "sg:address":"1019 Perry Cove",
    "sg:city":"Savannah",
    "sg:classifiers":[
        {
            "category":"Bus Charters",
            "type":"Transportation"
        },
        {
            "category":"Recreation",
            "type":"Entertainment"
        }
    ],
    "sg:phone":"+1 912 897 4705",
    "sg:postcode":"31410",
    "sg:province":"GA",
    "sg:tags":[
        "rental",
        "guide"
    ],
    "wof:name":"A A Atlantic Coast Charters",
    "wof:placetype":"venue"
},
  "geometry": {"coordinates":[-81.01527900000001,32.045685],"type":"Point"}
}