{
  "type": "Feature",
  "properties": {
    "iso:country":"US",
    "sg:address":"471 County Line Rd",
    "sg:city":"Cumming",
    "sg:classifiers":[
        {
            "category":"Building & Trades",
            "subcategory":"Construction",
            "type":"Services"
        }
    ],
    "sg:phone":"+1 678 455 6759",
    "sg:postcode":"30040",
    "sg:province":"GA",
    "sg:tags":[
        "contractor"
    ],
    "wof:name":"Garcia Masonry Inc",
    "wof:placetype":"venue"
},
  "geometry": {"coordinates":[-84.26994000000001,34.216919],"type":"Point"}
}