{
  "type": "Feature",
  "properties": {
    "addr:full":"324 Grant Ave Macon GA 31201",
    "addr:housenumber":"324",
    "addr:postcode":"31201",
    "addr:street":"Grant Ave",
    "iso:country":"US",
    "sg:address":"324 Grant Ave",
    "sg:city":"Macon",
    "sg:classifiers":[
        {
            "category":"Manufacturing",
            "subcategory":"Retail Goods",
            "type":"Manufacturing & Wholesale Goods"
        }
    ],
    "sg:phone":"+1 478 745 5054",
    "sg:postcode":"31201",
    "sg:province":"GA",
    "sg:tags":[
        "airbrush",
        "art"
    ],
    "wof:name":"Artrageous",
    "wof:placetype":"venue"
},
  "geometry": {"coordinates":[-83.647054,32.848793],"type":"Point"}
}