{
  "type": "Feature",
  "properties": {
    "iso:country":"US",
    "sg:address":"455 Jordan Rd",
    "sg:city":"Byron",
    "sg:classifiers":[
        {
            "category":"Manufacturing",
            "subcategory":"Buildings",
            "type":"Manufacturing & Wholesale Goods"
        },
        {
            "category":"Building & Trades",
            "subcategory":"Construction",
            "type":"Services"
        }
    ],
    "sg:phone":"+1 478 956 1509",
    "sg:postcode":"31008",
    "sg:province":"GA",
    "sg:tags":[
        "home",
        "builder",
        "contractor"
    ],
    "wof:name":"D S Construction Company",
    "wof:placetype":"venue"
},
  "geometry": {"coordinates":[-83.842271,32.68101],"type":"Point"}
}