{
  "type": "Feature",
  "properties": {
    "addr:full":"5455 Mount Vernon Pkwy NW Atlanta GA 30327",
    "addr:housenumber":"5455",
    "addr:postcode":"30327",
    "addr:street":"Mount Vernon Pkwy Nw",
    "iso:country":"US",
    "sg:address":"5455 Mount Vernon Pkwy NW",
    "sg:city":"Atlanta",
    "sg:classifiers":[
        {
            "category":"Professional",
            "subcategory":"Management & Consulting",
            "type":"Services"
        }
    ],
    "sg:phone":"+1 404 252 2612",
    "sg:postcode":"30327",
    "sg:province":"GA",
    "sg:tags":[
        "personnel",
        "consultant"
    ],
    "wof:name":"Office Consultants Inc",
    "wof:placetype":"venue"
},
  "geometry": {"coordinates":[-84.408642,33.902753],"type":"Point"}
}