{
  "type": "Feature",
  "properties": {
    "addr:full":"4097 E River Rd Camilla GA 31730",
    "addr:housenumber":"4097",
    "addr:postcode":"31730",
    "addr:street":"E River Rd",
    "iso:country":"US",
    "sg:address":"4097 E River Rd",
    "sg:city":"Camilla",
    "sg:classifiers":[
        {
            "category":"Farming",
            "subcategory":"Farm",
            "type":"Manufacturing & Wholesale Goods"
        }
    ],
    "sg:phone":"+1 229 246 7871",
    "sg:postcode":"31730",
    "sg:province":"GA",
    "sg:tags":[
        "crop",
        "general"
    ],
    "wof:name":"Singleton Farms",
    "wof:placetype":"venue"
},
  "geometry": {"coordinates":[-84.505971,31.040581],"type":"Point"}
}