{
  "type": "Feature",
  "properties": {
    "addr:full":"808 Walnut St Macon GA 31201",
    "addr:housenumber":"808",
    "addr:postcode":"31201",
    "addr:street":"Walnut St",
    "iso:country":"US",
    "sg:address":"808 Walnut St",
    "sg:city":"Macon",
    "sg:classifiers":[
        {
            "category":"Food & Beverages",
            "subcategory":"Liquor & Beverages",
            "type":"Retail Goods"
        }
    ],
    "sg:phone":"+1 478 745 4887",
    "sg:postcode":"31201",
    "sg:province":"GA",
    "sg:tags":[
        "store"
    ],
    "wof:name":"Cherio Package Store",
    "wof:placetype":"venue"
},
  "geometry": {"coordinates":[-83.63054200000001,32.841367],"type":"Point"}
}