{
  "type": "Feature",
  "properties": {
    "addr:full":"208 W Harris St Savannah GA 31401",
    "addr:housenumber":"208",
    "addr:postcode":"31401",
    "addr:street":"W Harris St",
    "iso:country":"US",
    "sg:address":"208 W Harris St",
    "sg:city":"Savannah",
    "sg:classifiers":[
        {
            "category":"Professional",
            "subcategory":"Research",
            "type":"Services"
        }
    ],
    "sg:phone":"+1 912 236 4870",
    "sg:postcode":"31401",
    "sg:province":"GA",
    "sg:tags":[
        "foundation",
        "philanthropic"
    ],
    "wof:name":"Beehive Foundation",
    "wof:placetype":"venue"
},
  "geometry": {"coordinates":[-81.09626799999999,32.074572],"type":"Point"}
}