{
  "type": "Feature",
  "properties": {
    "addr:full":"3396 Cowhide Rd Thomson GA 30824",
    "addr:housenumber":"3396",
    "addr:postcode":"30824",
    "addr:street":"Cowhide Rd",
    "iso:country":"US",
    "sg:address":"3396 Cowhide Rd",
    "sg:city":"Thomson",
    "sg:classifiers":[
        {
            "category":"Retail",
            "subcategory":"Repair Shop",
            "type":"Services"
        }
    ],
    "sg:phone":"+1 706 595 8120",
    "sg:postcode":"30824",
    "sg:province":"GA",
    "sg:tags":[
        "welding"
    ],
    "wof:name":"Jt Welding & Equip Repa",
    "wof:placetype":"venue"
},
  "geometry": {"coordinates":[-82.539317,33.363513],"type":"Point"}
}