{
  "type": "Feature",
  "properties": {
    "addr:full":"1526 Foye Ave Columbus GA 31903",
    "addr:housenumber":"1526",
    "addr:postcode":"31903",
    "addr:street":"Foye Ave",
    "iso:country":"US",
    "sg:address":"1526 Foye Ave",
    "sg:city":"Columbus",
    "sg:classifiers":[
        {
            "category":"Professional",
            "subcategory":"Detective & Security Services",
            "type":"Services"
        }
    ],
    "sg:phone":"+1 706 687 5957",
    "sg:postcode":"31903",
    "sg:province":"GA",
    "sg:tags":[
        "guard"
    ],
    "wof:name":"Suzanne Wilson",
    "wof:placetype":"venue"
},
  "geometry": {"coordinates":[-84.933869,32.425648],"type":"Point"}
}