{
  "type": "Feature",
  "properties": {
    "addr:full":"535 E Congress St Savannah GA 31401",
    "addr:housenumber":"535",
    "addr:postcode":"31401",
    "addr:street":"E Congress St",
    "iso:country":"US",
    "sg:address":"535 E Congress St",
    "sg:city":"Savannah",
    "sg:classifiers":[
        {
            "category":"Professional",
            "subcategory":"Business Services",
            "type":"Services"
        }
    ],
    "sg:phone":"+1 912 790 7535",
    "sg:postcode":"31401",
    "sg:province":"GA",
    "wof:name":"Gail G Lawrence Interior Desig",
    "wof:placetype":"venue"
},
  "geometry": {"coordinates":[-81.085477,32.077987],"type":"Point"}
}