{
  "type": "Feature",
  "properties": {
    "iso:country":"US",
    "sg:address":"5180 Roswell Rd",
    "sg:city":"Atlanta",
    "sg:classifiers":[
        {
            "category":"Professional",
            "subcategory":"Engineering",
            "type":"Services"
        }
    ],
    "sg:phone":"+1 404 256 8800",
    "sg:postcode":"30342",
    "sg:province":"GA",
    "sg:tags":[
        "management",
        "project",
        "real estate",
        "accounting"
    ],
    "wof:name":"Centre Properties",
    "wof:placetype":"venue"
},
  "geometry": {"coordinates":[-84.38152100000001,33.897738],"type":"Point"}
}