{
  "type": "Feature",
  "properties": {
    "iso:country":"US",
    "sg:address":"2230 Bent Creek Mnr",
    "sg:city":"Alpharetta",
    "sg:classifiers":[
        {
            "category":"Banks & Credit Unions",
            "subcategory":"Financial Services",
            "type":"Services"
        }
    ],
    "sg:phone":"+1 678 624 3995",
    "sg:postcode":"30005",
    "sg:province":"GA",
    "sg:tags":[
        "broker",
        "mortgage"
    ],
    "wof:name":"Home Source Lending Group Llc",
    "wof:placetype":"venue"
},
  "geometry": {"coordinates":[-84.21446400000001,34.085653],"type":"Point"}
}