{
  "type": "Feature",
  "properties": {
    "iso:country":"US",
    "sg:address":"8012 Cumming Hwy",
    "sg:city":"Canton",
    "sg:classifiers":[
        {
            "category":"Shopping",
            "subcategory":"Gifts & Souvenirs",
            "type":"Retail Goods"
        }
    ],
    "sg:phone":"+1 770 479 4943",
    "sg:postcode":"30115",
    "sg:province":"GA",
    "wof:name":"Arbor Lane Gifts & Home Accent",
    "wof:placetype":"venue"
},
  "geometry": {"coordinates":[-84.351805,34.254045],"type":"Point"}
}