{
  "type": "Feature",
  "properties": {
    "iso:country":"US",
    "sg:address":"40 Mike Dr E Ste 1",
    "sg:city":"Ellijay",
    "sg:classifiers":[
        {
            "category":"Home & Garden",
            "subcategory":"Building Materials",
            "type":"Retail Goods"
        },
        {
            "category":"Manufacturing",
            "subcategory":"Glass & Minerals",
            "type":"Manufacturing & Wholesale Goods"
        },
        {
            "category":"Manufacturing",
            "subcategory":"Building Materials",
            "type":"Manufacturing & Wholesale Goods"
        }
    ],
    "sg:phone":"+1 706 636 1247",
    "sg:postcode":"30540",
    "sg:province":"GA",
    "sg:tags":[
        "plate",
        "repair",
        "glazier",
        "window",
        "accessory",
        "glass-wholesale",
        "shape",
        "doors",
        "frames",
        "circle",
        "replacement",
        "special",
        "manufacturer"
    ],
    "wof:name":"Freeman Glass Company Inc.",
    "wof:placetype":"venue"
},
  "geometry": {"coordinates":[-84.484165,34.678811],"type":"Point"}
}