{
  "type": "Feature",
  "properties": {
    "addr:full":"976 Broad St Augusta GA 30901",
    "addr:housenumber":"976",
    "addr:postcode":"30901",
    "addr:street":"Broad St",
    "iso:country":"US",
    "sg:address":"976 Broad St",
    "sg:city":"Augusta",
    "sg:classifiers":[
        {
            "category":"Restaurant",
            "type":"Food & Drink"
        }
    ],
    "sg:phone":"+1 706 724 0501",
    "sg:postcode":"30901",
    "sg:province":"GA",
    "sg:tags":[
        "eating"
    ],
    "wof:name":"Nacho Mama's Burritos Inc",
    "wof:placetype":"venue"
},
  "geometry": {"coordinates":[-81.967427,33.476076],"type":"Point"}
}