{
  "type": "Feature",
  "properties": {
    "addr:full":"1055 Hudson Dr NE Atlanta GA 30306",
    "addr:housenumber":"1055",
    "addr:postcode":"30306",
    "addr:street":"Hudson Dr Ne",
    "iso:country":"US",
    "sg:address":"1055 Hudson Dr NE",
    "sg:city":"Atlanta",
    "sg:classifiers":[
        {
            "category":"Banks & Credit Unions",
            "subcategory":"Financial Services",
            "type":"Services"
        }
    ],
    "sg:phone":"+1 404 733 5881",
    "sg:postcode":"30306",
    "sg:province":"GA",
    "sg:tags":[
        "investor"
    ],
    "wof:name":"Inland Securities Corporation",
    "wof:placetype":"venue"
},
  "geometry": {"coordinates":[-84.35328,33.780868],"type":"Point"}
}