{
  "type": "Feature",
  "properties": {
    "addr:full":"6240 Old Highway 5 Woodstock GA 30188",
    "addr:housenumber":"6240",
    "addr:postcode":"30188",
    "addr:street":"Old Highway 5",
    "iso:country":"US",
    "sg:address":"6240 Old Highway 5",
    "sg:city":"Woodstock",
    "sg:classifiers":[
        {
            "category":"Restaurant",
            "type":"Food & Drink"
        }
    ],
    "sg:menulink":"http://www.allmenus.com/ga/holly-springs/220722-philly-connection/menu/",
    "sg:phone":"+1 770 516 3447",
    "sg:postcode":"30188",
    "sg:province":"GA",
    "sg:tags":[
        "cheesesteaks",
        "sandwich",
        "american"
    ],
    "wof:name":"Philly Connection",
    "wof:placetype":"venue"
},
  "geometry": {"coordinates":[-84.49785900000001,34.130396],"type":"Point"}
}