{
  "type": "Feature",
  "properties": {
    "iso:country":"US",
    "sg:address":"715 Hawkins St",
    "sg:city":"Americus",
    "sg:classifiers":[
        {
            "category":"Organizations",
            "subcategory":"Religious Organization",
            "type":"Services"
        }
    ],
    "sg:phone":"+1 229 924 4501",
    "sg:postcode":"31719",
    "sg:province":"GA",
    "wof:name":"New Genesis Missionary Ch",
    "wof:placetype":"venue"
},
  "geometry": {"coordinates":[-84.24103100000001,32.083243],"type":"Point"}
}