{
  "type": "Feature",
  "properties": {
    "addr:full":"102 Forest Ave Peachtree City GA 30233",
    "addr:housenumber":"102",
    "addr:postcode":"30233",
    "addr:street":"Forest Ave",
    "iso:country":"US",
    "sg:address":"102 Forest Ave",
    "sg:city":"Peachtree City",
    "sg:classifiers":[
        {
            "category":"Communications",
            "type":"Services"
        }
    ],
    "sg:phone":"+1 770 487 6472",
    "sg:postcode":"30233",
    "sg:province":"GA",
    "sg:tags":[
        "communication"
    ],
    "wof:name":"Capital Communications Inc",
    "wof:placetype":"venue"
},
  "geometry": {"coordinates":[-83.976675,33.294938],"type":"Point"}
}