{
  "type": "Feature",
  "properties": {
    "iso:country":"US",
    "sg:address":"1826 Metropolitan Pkwy SW",
    "sg:city":"Atlanta",
    "sg:classifiers":[
        {
            "category":"Retail",
            "subcategory":"Auto Repair",
            "type":"Services"
        }
    ],
    "sg:phone":"+1 404 758 9888",
    "sg:postcode":"30315",
    "sg:province":"GA",
    "sg:tags":[
        "body",
        "shop"
    ],
    "wof:name":"Maaco Auto Painting & Bodyworks",
    "wof:placetype":"venue"
},
  "geometry": {"coordinates":[-84.408203,33.703098],"type":"Point"}
}