{
  "type": "Feature",
  "properties": {
    "iso:country":"US",
    "sg:address":"4120 S Laurel Grove Rd",
    "sg:city":"Douglasville",
    "sg:classifiers":[
        {
            "category":"Building & Trades",
            "subcategory":"Equipment Rental",
            "type":"Services"
        }
    ],
    "sg:phone":"+1 770 489 0936",
    "sg:postcode":"30135",
    "sg:province":"GA",
    "wof:name":"Stork Lady",
    "wof:placetype":"venue"
},
  "geometry": {"coordinates":[-84.695716,33.666634],"type":"Point"}
}