{
  "type": "Feature",
  "properties": {
    "iso:country":"US",
    "sg:address":"1800 James Jackson Pkwy NW",
    "sg:city":"Atlanta",
    "sg:classifiers":[
        {
            "category":"Government",
            "subcategory":"Post Office",
            "type":"Public Place"
        }
    ],
    "sg:phone":"+1 404 792 3181",
    "sg:postcode":"30318",
    "sg:province":"GA",
    "sg:tags":[
        "postal",
        "us"
    ],
    "wof:name":"Trans Mgmt Service Center",
    "wof:placetype":"venue"
},
  "geometry": {"coordinates":[-84.47566999999999,33.803042],"type":"Point"}
}