{
  "type": "Feature",
  "properties": {
    "addr:full":"3285 McCullers Dr Loganville GA 30655",
    "addr:housenumber":"3285",
    "addr:postcode":"30655",
    "addr:street":"Mccullers Dr",
    "iso:country":"US",
    "sg:address":"3285 McCullers Dr",
    "sg:city":"Loganville",
    "sg:classifiers":[
        {
            "category":"Building & Trades",
            "subcategory":"Landscaping Services",
            "type":"Services"
        }
    ],
    "sg:phone":"+1 770 466 1021",
    "sg:postcode":"30655",
    "sg:province":"GA",
    "sg:tags":[
        "designer",
        "landscape"
    ],
    "wof:name":"Holder Landscape Management Co",
    "wof:placetype":"venue"
},
  "geometry": {"coordinates":[-83.876153,33.848665],"type":"Point"}
}