{
  "type": "Feature",
  "properties": {
    "addr:full":"165 Chestlehurst Dr Fayetteville GA 30215",
    "addr:housenumber":"165",
    "addr:postcode":"30215",
    "addr:street":"Chestlehurst Dr",
    "iso:country":"US",
    "sg:address":"165 Chestlehurst Dr",
    "sg:city":"Fayetteville",
    "sg:classifiers":[
        {
            "category":"Shopping",
            "type":"Retail Goods"
        }
    ],
    "sg:phone":"+1 770 719 8433",
    "sg:postcode":"30215",
    "sg:province":"GA",
    "sg:tags":[
        "product",
        "wood"
    ],
    "wof:name":"Wood Expressions",
    "wof:placetype":"venue"
},
  "geometry": {"coordinates":[-84.466987,33.394455],"type":"Point"}
}