{
  "type": "Feature",
  "properties": {
    "iso:country":"US",
    "sg:address":"222 E Morris St",
    "sg:city":"Dalton",
    "sg:classifiers":[
        {
            "category":"Autos & Motor Vehicles",
            "subcategory":"Auto Supplies",
            "type":"Retail Goods"
        }
    ],
    "sg:phone":"+1 706 278 9040",
    "sg:postcode":"30721",
    "sg:province":"GA",
    "sg:tags":[
        "repair",
        "center",
        "tire"
    ],
    "wof:name":"Taylors Tire & Service",
    "wof:placetype":"venue"
},
  "geometry": {"coordinates":[-84.965193,34.768553],"type":"Point"}
}