{
  "type": "Feature",
  "properties": {
    "iso:country":"US",
    "sg:address":"3711 Stagecoach Rd NE",
    "sg:city":"Thomson",
    "sg:classifiers":[
        {
            "category":"Retail",
            "subcategory":"Auto Repair",
            "type":"Services"
        }
    ],
    "sg:phone":"+1 706 595 8501",
    "sg:postcode":"30824",
    "sg:province":"GA",
    "sg:tags":[
        "automotive"
    ],
    "wof:name":"Blacks Towing Service",
    "wof:placetype":"venue"
},
  "geometry": {"coordinates":[-82.418959,33.520819],"type":"Point"}
}