{
  "type": "Feature",
  "properties": {
    "iso:country":"US",
    "sg:address":"3193 Howell Mill Rd NW",
    "sg:city":"Atlanta",
    "sg:classifiers":[
        {
            "category":"Health Services",
            "subcategory":"Doctor",
            "type":"Services"
        },
        {
            "category":"Health Services",
            "subcategory":"Medical Lab",
            "type":"Services"
        }
    ],
    "sg:phone":"+1 404 352 0444",
    "sg:postcode":"30327",
    "sg:province":"GA",
    "sg:tags":[
        "physician",
        "radiology",
        "pediatrics-radiology",
        "surgeons",
        "laboratory",
        "surgeon"
    ],
    "wof:name":"West Paces Imaging Associates",
    "wof:placetype":"venue"
},
  "geometry": {"coordinates":[-84.427268,33.840715],"type":"Point"}
}