{
  "type": "Feature",
  "properties": {
    "iso:country":"US",
    "sg:address":"100 S Dooly St",
    "sg:city":"Montezuma",
    "sg:classifiers":[
        {
            "category":"Building & Trades",
            "subcategory":"Equipment Rental",
            "type":"Services"
        }
    ],
    "sg:phone":"+1 478 472 8166",
    "sg:postcode":"31063",
    "sg:province":"GA",
    "sg:tags":[
        "medical"
    ],
    "wof:name":"Med-Equip",
    "wof:placetype":"venue"
},
  "geometry": {"coordinates":[-84.030158,32.300337],"type":"Point"}
}