{
  "type": "Feature",
  "properties": {
    "addr:full":"132 E Church St Sandersville GA 31082",
    "addr:housenumber":"132",
    "addr:postcode":"31082",
    "addr:street":"E Church St",
    "iso:country":"US",
    "sg:address":"132 E Church St",
    "sg:city":"Sandersville",
    "sg:classifiers":[
        {
            "category":"Shopping",
            "subcategory":"Books",
            "type":"Retail Goods"
        }
    ],
    "sg:phone":"+1 478 553 0596",
    "sg:postcode":"31082",
    "sg:province":"GA",
    "wof:name":"His Vineyard",
    "wof:placetype":"venue"
},
  "geometry": {"coordinates":[-82.810198,32.981402],"type":"Point"}
}