{
  "type": "Feature",
  "properties": {
    "iso:country":"US",
    "sg:address":"101 Uphill Dr",
    "sg:city":"Dahlonega",
    "sg:classifiers":[
        {
            "category":"Building & Trades",
            "subcategory":"Landscaping Services",
            "type":"Services"
        }
    ],
    "sg:phone":"+1 706 867 8465",
    "sg:postcode":"30533",
    "sg:province":"GA",
    "sg:tags":[
        "lawn",
        "maintenance",
        "grounds"
    ],
    "wof:name":"John's Lawn Care",
    "wof:placetype":"venue"
},
  "geometry": {"coordinates":[-83.935892,34.562705],"type":"Point"}
}