{
  "type": "Feature",
  "properties": {
    "iso:country":"US",
    "sg:address":"5881 McIntosh Rd",
    "sg:city":"Blairsville",
    "sg:classifiers":[
        {
            "category":"Building & Trades",
            "subcategory":"Construction",
            "type":"Services"
        }
    ],
    "sg:phone":"+1 706 781 1652",
    "sg:postcode":"30512",
    "sg:province":"GA",
    "sg:tags":[
        "hanging",
        "contractor"
    ],
    "wof:name":"Georgia Mountain Painting",
    "wof:placetype":"venue"
},
  "geometry": {"coordinates":[-84.06329700000001,34.912007],"type":"Point"}
}