{
  "type": "Feature",
  "properties": {
    "addr:full":"200 Sandy Lake Cir Ellenwood GA 30214",
    "addr:housenumber":"200",
    "addr:postcode":"30214",
    "addr:street":"Sandy Lake Cir",
    "iso:country":"US",
    "sg:address":"200 Sandy Lake Cir",
    "sg:city":"Ellenwood",
    "sg:classifiers":[
        {
            "category":"Freight",
            "type":"Transportation"
        }
    ],
    "sg:phone":"+1 770 389 3585",
    "sg:postcode":"30214",
    "sg:province":"GA",
    "sg:tags":[
        "operator",
        "trucking"
    ],
    "wof:name":"Jackson Trucking",
    "wof:placetype":"venue"
},
  "geometry": {"coordinates":[-84.537727,33.478378],"type":"Point"}
}