{
  "type": "Feature",
  "properties": {
    "iso:country":"US",
    "sg:address":"964 Northcliffe Dr NW",
    "sg:city":"Atlanta",
    "sg:classifiers":[
        {
            "category":"Food & Beverages",
            "subcategory":"Fruits & Vegetables",
            "type":"Retail Goods"
        }
    ],
    "sg:phone":"+1 404 355 3911",
    "sg:postcode":"30318",
    "sg:province":"GA",
    "sg:tags":[
        "market"
    ],
    "wof:name":"Foster Hicks Produce Co Inc",
    "wof:placetype":"venue"
},
  "geometry": {"coordinates":[-84.41958099999999,33.81875],"type":"Point"}
}