{
  "type": "Feature",
  "properties": {
    "iso:country":"US",
    "sg:address":"138 N Highway 113",
    "sg:city":"Carrollton",
    "sg:classifiers":[
        {
            "category":"Health Services",
            "subcategory":"Doctor",
            "type":"Services"
        }
    ],
    "sg:phone":"+1 770 832 7463",
    "sg:postcode":"30117",
    "sg:province":"GA",
    "sg:tags":[
        "medicine",
        "physician",
        "practice",
        "surgeons",
        "family"
    ],
    "wof:name":"Annelle Garrett Family Partner",
    "wof:placetype":"venue"
},
  "geometry": {"coordinates":[-85.078913,33.603166],"type":"Point"}
}