{
  "type": "Feature",
  "properties": {
    "iso:country":"US",
    "sg:address":"1605 1st Ave SE",
    "sg:city":"Moultrie",
    "sg:classifiers":[
        {
            "category":"Shopping",
            "type":"Retail Goods"
        }
    ],
    "sg:phone":"+1 229 985 1414",
    "sg:postcode":"31768",
    "sg:province":"GA",
    "sg:tags":[
        "ice"
    ],
    "wof:name":"Market Ice House",
    "wof:placetype":"venue"
},
  "geometry": {"coordinates":[-83.766279,31.177741],"type":"Point"}
}