{
  "type": "Feature",
  "properties": {
    "addr:full":"107 Chestnut Ct Kingsland GA 31548",
    "addr:housenumber":"107",
    "addr:postcode":"31548",
    "addr:street":"Chestnut Ct",
    "iso:country":"US",
    "sg:address":"107 Chestnut Ct",
    "sg:city":"Kingsland",
    "sg:classifiers":[
        {
            "category":"Building & Trades",
            "subcategory":"Electrical",
            "type":"Services"
        }
    ],
    "sg:phone":"+1 912 882 2395",
    "sg:postcode":"31548",
    "sg:province":"GA",
    "sg:tags":[
        "electric",
        "contractor"
    ],
    "wof:name":"JIT Electric",
    "wof:placetype":"venue"
},
  "geometry": {"coordinates":[-81.64746100000001,30.794671],"type":"Point"}
}