{
  "type": "Feature",
  "properties": {
    "addr:full":"220 Grape Creek Rd Milner GA 30257",
    "addr:housenumber":"220",
    "addr:postcode":"30257",
    "addr:street":"Grape Creek Rd",
    "iso:country":"US",
    "sg:address":"220 Grape Creek Rd",
    "sg:city":"Milner",
    "sg:classifiers":[
        {
            "category":"Building & Trades",
            "subcategory":"Landscaping Services",
            "type":"Services"
        },
        {
            "category":"Professional",
            "type":"Services"
        },
        {
            "category":"Personal",
            "type":"Services"
        }
    ],
    "sg:phone":"+1 770 358 9355",
    "sg:postcode":"30257",
    "sg:province":"GA",
    "sg:tags":[
        "control",
        "lawn",
        "property",
        "contractor",
        "fertilizing",
        "maintenance",
        "weed",
        "landscape"
    ],
    "wof:name":"Diversified Maintenance",
    "wof:placetype":"venue"
},
  "geometry": {"coordinates":[-84.226573,33.11706],"type":"Point"}
}