{
  "type": "Feature",
  "properties": {
    "iso:country":"US",
    "sg:address":"368 Knox Dr",
    "sg:city":"Brunswick",
    "sg:classifiers":[
        {
            "category":"Professional",
            "type":"Services"
        }
    ],
    "sg:phone":"+1 912 264 2339",
    "sg:postcode":"31525",
    "sg:province":"GA",
    "wof:name":"C Hunter Jana",
    "wof:placetype":"venue"
},
  "geometry": {"coordinates":[-81.47289499999999,31.228309],"type":"Point"}
}