{
  "type": "Feature",
  "properties": {
    "iso:country":"US",
    "sg:address":"1915 Courtland Ln",
    "sg:city":"Dalton",
    "sg:classifiers":[
        {
            "category":"Organizations",
            "subcategory":"Religious Organization",
            "type":"Services"
        }
    ],
    "sg:phone":"+1 706 226 8454",
    "sg:postcode":"30720",
    "sg:province":"GA",
    "sg:tags":[
        "clergy"
    ],
    "wof:name":"Rick Mc Cormick",
    "wof:placetype":"venue"
},
  "geometry": {"coordinates":[-85.000191,34.736688],"type":"Point"}
}