{
  "type": "Feature",
  "properties": {
    "iso:country":"US",
    "sg:address":"754 N Lake Dr",
    "sg:city":"Sandersville",
    "sg:classifiers":[
        {
            "category":"Retail",
            "subcategory":"Repair Shop",
            "type":"Services"
        }
    ],
    "sg:phone":"+1 478 553 1444",
    "sg:postcode":"31082",
    "sg:province":"GA",
    "wof:name":"A A A Blind Clg & Repr Svc",
    "wof:placetype":"venue"
},
  "geometry": {"coordinates":[-82.803105,33.013066],"type":"Point"}
}