{
  "type": "Feature",
  "properties": {
    "iso:country":"US",
    "sg:address":"9 Mutec Dr",
    "sg:city":"Columbus",
    "sg:classifiers":[
        {
            "category":"Professional",
            "subcategory":"Employment Agencies",
            "type":"Services"
        }
    ],
    "sg:phone":"+1 706 653 6004",
    "sg:postcode":"31907",
    "sg:province":"GA",
    "sg:tags":[
        "help",
        "contractor"
    ],
    "sg:website":"www.spherion.com",
    "wof:name":"Spherion On Premise",
    "wof:placetype":"venue"
},
  "geometry": {"coordinates":[-84.870283,32.50373],"type":"Point"}
}