{
  "type": "Feature",
  "properties": {
    "addr:full":"1640 Powers Ferry Rd Marietta GA 30067",
    "addr:housenumber":"1640",
    "addr:postcode":"30067",
    "addr:street":"Powers Ferry Rd",
    "iso:country":"US",
    "sg:address":"1640 Powers Ferry Rd",
    "sg:city":"Marietta",
    "sg:classifiers":[
        {
            "category":"Professional",
            "type":"Services"
        }
    ],
    "sg:phone":"+1 770 859 9543",
    "sg:postcode":"30067",
    "sg:province":"GA",
    "wof:name":"Lineman Davis & Dully Inc",
    "wof:placetype":"venue"
},
  "geometry": {"coordinates":[-84.46549,33.914384],"type":"Point"}
}