{
  "type": "Feature",
  "properties": {
    "addr:full":"5159 Davidson Rd Marietta GA 30068",
    "addr:housenumber":"5159",
    "addr:postcode":"30068",
    "addr:street":"Davidson Rd",
    "iso:country":"US",
    "sg:address":"5159 Davidson Rd",
    "sg:city":"Marietta",
    "sg:classifiers":[
        {
            "category":"Professional",
            "subcategory":"Management & Consulting",
            "type":"Services"
        }
    ],
    "sg:phone":"+1 770 565 5251",
    "sg:postcode":"30068",
    "sg:province":"GA",
    "wof:name":"FP Sales Marketing",
    "wof:placetype":"venue"
},
  "geometry": {"coordinates":[-84.39902499999999,33.962786],"type":"Point"}
}