{
  "type": "Feature",
  "properties": {
    "addr:full":"2187 Birch Hollow Trl Lawrenceville GA 30043",
    "addr:housenumber":"2187",
    "addr:postcode":"30043",
    "addr:street":"Birch Hollow Trl",
    "iso:country":"US",
    "sg:address":"2187 Birch Hollow Trl",
    "sg:city":"Lawrenceville",
    "sg:classifiers":[
        {
            "category":"Professional",
            "subcategory":"Business Services",
            "type":"Services"
        }
    ],
    "sg:phone":"+1 770 682 3281",
    "sg:postcode":"30043",
    "sg:province":"GA",
    "sg:tags":[
        "interior",
        "consultant",
        "design",
        "decorator"
    ],
    "wof:name":"C & G Design",
    "wof:placetype":"venue"
},
  "geometry": {"coordinates":[-84.05399,33.997018],"type":"Point"}
}