{
  "type": "Feature",
  "properties": {
    "iso:country":"US",
    "sg:address":"1880 Old State Rd",
    "sg:city":"Menlo",
    "sg:classifiers":[
        {
            "category":"Building & Trades",
            "subcategory":"Electrical",
            "type":"Services"
        }
    ],
    "sg:phone":"+1 706 398 2782",
    "sg:postcode":"30731",
    "sg:province":"GA",
    "sg:tags":[
        "electrician"
    ],
    "wof:name":"Maxx Electric Co",
    "wof:placetype":"venue"
},
  "geometry": {"coordinates":[-85.47085199999999,34.725207],"type":"Point"}
}