{
  "type": "Feature",
  "properties": {
    "addr:full":"1575 Old Alabama Rd Ste 201 Roswell GA 30076",
    "addr:housenumber":"1575",
    "addr:postcode":"30076",
    "addr:street":"Old Alabama Rd Ste 201",
    "iso:country":"US",
    "sg:address":"1575 Old Alabama Rd Ste 201",
    "sg:city":"Roswell",
    "sg:classifiers":[
        {
            "category":"Personal",
            "subcategory":"Massage",
            "type":"Services"
        },
        {
            "category":"Personal",
            "subcategory":"Beauty Salon",
            "type":"Services"
        },
        {
            "category":"Personal",
            "subcategory":"Day Spa",
            "type":"Services"
        },
        {
            "category":"Personal",
            "subcategory":"Skin Care",
            "type":"Services"
        }
    ],
    "sg:phone":"+1 770 993 5002",
    "sg:postcode":"30076",
    "sg:province":"GA",
    "sg:tags":[
        "hair",
        "therapist",
        "stylist"
    ],
    "wof:name":"Studio 208 @ Salon Studios",
    "wof:placetype":"venue"
},
  "geometry": {"coordinates":[-84.31559900000001,34.021777],"type":"Point"}
}