{
  "type": "Feature",
  "properties": {
    "addr:full":"4866 Township Trce Marietta GA 30066",
    "addr:housenumber":"4866",
    "addr:postcode":"30066",
    "addr:street":"Township Trce",
    "iso:country":"US",
    "sg:address":"4866 Township Trce",
    "sg:city":"Marietta",
    "sg:classifiers":[
        {
            "category":"Banks & Credit Unions",
            "subcategory":"Bank",
            "type":"Services"
        }
    ],
    "sg:phone":"+1 770 992 2205",
    "sg:postcode":"30066",
    "sg:province":"GA",
    "sg:tags":[
        "loan",
        "real estate"
    ],
    "wof:name":"Mortgage Service Assoc Inc",
    "wof:placetype":"venue"
},
  "geometry": {"coordinates":[-84.43966500000001,34.071386],"type":"Point"}
}