{
  "type": "Feature",
  "properties": {
    "addr:full":"180 Helton Rd Bremen GA 30110",
    "addr:housenumber":"180",
    "addr:postcode":"30110",
    "addr:street":"Helton Rd",
    "iso:country":"US",
    "sg:address":"180 Helton Rd",
    "sg:city":"Bremen",
    "sg:classifiers":[
        {
            "category":"Place Of Worship",
            "subcategory":"Church",
            "type":"Public Place"
        },
        {
            "category":"Place Of Worship",
            "type":"Public Place"
        }
    ],
    "sg:phone":"+1 770 537 1933",
    "sg:postcode":"30110",
    "sg:province":"GA",
    "sg:tags":[
        "churches-non-denominational"
    ],
    "wof:name":"Kingdom Rock Family Worship Center",
    "wof:placetype":"venue"
},
  "geometry": {"coordinates":[-85.08953099999999,33.726505],"type":"Point"}
}