{
  "type": "Feature",
  "properties": {
    "addr:full":"117 Ginny Ln Griffin GA 30223",
    "addr:housenumber":"117",
    "addr:postcode":"30223",
    "addr:street":"Ginny Ln",
    "iso:country":"US",
    "sg:address":"117 Ginny Ln",
    "sg:city":"Griffin",
    "sg:classifiers":[
        {
            "category":"Professional",
            "type":"Services"
        }
    ],
    "sg:phone":"+1 770 467 0475",
    "sg:postcode":"30223",
    "sg:province":"GA",
    "wof:name":"Ronald Elrod",
    "wof:placetype":"venue"
},
  "geometry": {"coordinates":[-84.12433,33.283043],"type":"Point"}
}