{
  "type": "Feature",
  "properties": {
    "iso:country":"US",
    "sg:address":"2946 Grandview Ave NE",
    "sg:city":"Atlanta",
    "sg:classifiers":[
        {
            "category":"Professional",
            "subcategory":"Business Services",
            "type":"Services"
        }
    ],
    "sg:phone":"+1 404 365 9311",
    "sg:postcode":"30305",
    "sg:province":"GA",
    "wof:name":"Dooley Rchard Rsdntial Designs",
    "wof:placetype":"venue"
},
  "geometry": {"coordinates":[-84.376431,33.836375],"type":"Point"}
}