{
  "type": "Feature",
  "properties": {
    "iso:country":"US",
    "sg:address":"11755 Pointe Pl",
    "sg:city":"Roswell",
    "sg:classifiers":[
        {
            "category":"Health Services",
            "subcategory":"Doctor",
            "type":"Services"
        }
    ],
    "sg:phone":"+1 770 992 0109",
    "sg:postcode":"30076",
    "sg:province":"GA",
    "sg:tags":[
        "psychiatrist"
    ],
    "wof:name":"Northwest Behavioral Research Center",
    "wof:placetype":"venue"
},
  "geometry": {"coordinates":[-84.326526,34.06772],"type":"Point"}
}