{
  "type": "Feature",
  "properties": {
    "iso:country":"US",
    "sg:address":"905 N Island Dr NW",
    "sg:city":"Atlanta",
    "sg:classifiers":[
        {
            "category":"Shopping Center",
            "type":"Public Place"
        }
    ],
    "sg:phone":"+1 404 255 0829",
    "sg:postcode":"30327",
    "sg:province":"GA",
    "sg:tags":[
        "mall"
    ],
    "wof:name":"West Paces Ferry Shopping Center",
    "wof:placetype":"venue"
},
  "geometry": {"coordinates":[-84.415536,33.890729],"type":"Point"}
}