{
  "type": "Feature",
  "properties": {
    "addr:full":"2740 Kinjac Dr Marietta GA 30066",
    "addr:housenumber":"2740",
    "addr:postcode":"30066",
    "addr:street":"Kinjac Dr",
    "iso:country":"US",
    "sg:address":"2740 Kinjac Dr",
    "sg:city":"Marietta",
    "sg:classifiers":[
        {
            "category":"Building & Trades",
            "subcategory":"Electrical",
            "type":"Services"
        }
    ],
    "sg:phone":"+1 770 509 9432",
    "sg:postcode":"30066",
    "sg:province":"GA",
    "sg:tags":[
        "electrician",
        "contractor"
    ],
    "wof:name":"Jc Contracting",
    "wof:placetype":"venue"
},
  "geometry": {"coordinates":[-84.496359,34.0163],"type":"Point"}
}