{
  "type": "Feature",
  "properties": {
    "addr:full":"96 Hawkins Store Rd NW Kennesaw GA 30144",
    "addr:housenumber":"96",
    "addr:postcode":"30144",
    "addr:street":"Hawkins Store Rd Nw",
    "iso:country":"US",
    "sg:address":"96 Hawkins Store Rd NW",
    "sg:city":"Kennesaw",
    "sg:classifiers":[
        {
            "category":"Building & Trades",
            "subcategory":"Construction",
            "type":"Services"
        }
    ],
    "sg:phone":"+1 651 998 0100",
    "sg:postcode":"30144",
    "sg:province":"GA",
    "sg:tags":[
        "contractor"
    ],
    "sg:website":"www.invisiblefence.com",
    "wof:name":"Invisible Fence",
    "wof:placetype":"venue"
},
  "geometry": {"coordinates":[-84.553051,34.057877],"type":"Point"}
}