{
  "type": "Feature",
  "properties": {
    "addr:full":"21 W Park Ave Savannah GA 31401",
    "addr:housenumber":"21",
    "addr:postcode":"31401",
    "addr:street":"W Park Ave",
    "iso:country":"US",
    "sg:address":"21 W Park Ave",
    "sg:city":"Savannah",
    "sg:classifiers":[
        {
            "category":"Professional",
            "subcategory":"Engineering",
            "type":"Services"
        }
    ],
    "sg:phone":"+1 912 353 8800",
    "sg:postcode":"31401",
    "sg:province":"GA",
    "sg:tags":[
        "engineer"
    ],
    "wof:name":"David Sladek Engineering",
    "wof:placetype":"venue"
},
  "geometry": {"coordinates":[-81.09815999999999,32.065002],"type":"Point"}
}