{
  "type": "Feature",
  "properties": {
    "iso:country":"US",
    "sg:address":"532 The Falls Pkwy",
    "sg:city":"Duluth",
    "sg:classifiers":[
        {
            "category":"Building & Trades",
            "subcategory":"Construction",
            "type":"Services"
        }
    ],
    "sg:phone":"+1 678 852 4746",
    "sg:postcode":"30096",
    "sg:province":"GA",
    "sg:tags":[
        "contractor"
    ],
    "wof:name":"Southerns Appliances Install",
    "wof:placetype":"venue"
},
  "geometry": {"coordinates":[-84.14482599999999,33.955096],"type":"Point"}
}