{
  "type": "Feature",
  "properties": {
    "addr:full":"231 Doc Moates Rd Aragon GA 30104",
    "addr:housenumber":"231",
    "addr:postcode":"30104",
    "addr:street":"Doc Moates Rd",
    "iso:country":"US",
    "sg:address":"231 Doc Moates Rd",
    "sg:city":"Aragon",
    "sg:classifiers":[
        {
            "category":"Professional",
            "subcategory":"Business Services",
            "type":"Services"
        }
    ],
    "sg:phone":"+1 770 684 8075",
    "sg:postcode":"30104",
    "sg:province":"GA",
    "wof:name":"Dave Ferguson Rev",
    "wof:placetype":"venue"
},
  "geometry": {"coordinates":[-85.082858,34.071831],"type":"Point"}
}