{
  "type": "Feature",
  "properties": {
    "iso:country":"US",
    "sg:address":"4122 Tate St NE",
    "sg:city":"Covington",
    "sg:classifiers":[
        {
            "category":"Health Services",
            "subcategory":"Doctor",
            "type":"Services"
        }
    ],
    "sg:phone":"+1 770 788 1144",
    "sg:postcode":"30014",
    "sg:province":"GA",
    "sg:tags":[
        "dentist"
    ],
    "wof:name":"Noah's Ark Childrens Dentistry",
    "wof:placetype":"venue"
},
  "geometry": {"coordinates":[-83.84978099999999,33.600477],"type":"Point"}
}