{
  "type": "Feature",
  "properties": {
    "iso:country":"US",
    "sg:address":"108 Dodgen Rd",
    "sg:city":"Hampton",
    "sg:classifiers":[
        {
            "category":"Professional",
            "subcategory":"Management & Consulting",
            "type":"Services"
        }
    ],
    "sg:phone":"+1 770 946 3783",
    "sg:postcode":"30228",
    "sg:province":"GA",
    "wof:name":"Lt Consulting",
    "wof:placetype":"venue"
},
  "geometry": {"coordinates":[-84.27169000000001,33.421851],"type":"Point"}
}