{
  "type": "Feature",
  "properties": {
    "addr:full":"2700 W Britt David Rd Columbus GA 31909",
    "addr:housenumber":"2700",
    "addr:postcode":"31909",
    "addr:street":"W Britt David Rd",
    "iso:country":"US",
    "sg:address":"2700 W Britt David Rd",
    "sg:city":"Columbus",
    "sg:classifiers":[
        {
            "category":"Community Center",
            "type":"Public Place"
        }
    ],
    "sg:phone":"+1 706 653 4196",
    "sg:postcode":"31909",
    "sg:province":"GA",
    "sg:tags":[
        "recreation"
    ],
    "wof:name":"City Of Columbus",
    "wof:placetype":"venue"
},
  "geometry": {"coordinates":[-84.952652,32.52816],"type":"Point"}
}