{
  "type": "Feature",
  "properties": {
    "iso:country":"US",
    "sg:address":"403 N Peachtree Pkwy",
    "sg:city":"Peachtree City",
    "sg:classifiers":[
        {
            "category":"Retail",
            "subcategory":"Portrait Studio",
            "type":"Services"
        }
    ],
    "sg:phone":"+1 678 472 2238",
    "sg:postcode":"30269",
    "sg:province":"GA",
    "sg:tags":[
        "photo"
    ],
    "wof:name":"Priceless Moments Photography",
    "wof:placetype":"venue"
},
  "geometry": {"coordinates":[-84.56791699999999,33.422674],"type":"Point"}
}