{
  "type": "Feature",
  "properties": {
    "addr:full":"513 Edgewood Avenue SE Atlanta GA 30312",
    "addr:housenumber":"513",
    "addr:postcode":"30312",
    "addr:street":"Edgewood Avenue Se",
    "iso:country":"US",
    "sg:address":"513 Edgewood Avenue SE",
    "sg:city":"Atlanta",
    "sg:classifiers":[
        {
            "category":"Health Services",
            "subcategory":"Doctor",
            "type":"Services"
        }
    ],
    "sg:phone":"+1 404 827 7011",
    "sg:postcode":"30312",
    "sg:province":"GA",
    "sg:tags":[
        "psychiatry",
        "physician",
        "surgeon",
        "surgeons"
    ],
    "wof:name":"Maass-Robinson Saundra A MD",
    "wof:placetype":"venue"
},
  "geometry": {"coordinates":[-84.37054999999999,33.754422],"type":"Point"}
}