{
  "type": "Feature",
  "properties": {
    "addr:full":"113 1st St SE Moultrie GA 31768",
    "addr:housenumber":"113",
    "addr:postcode":"31768",
    "addr:street":"1St St Se",
    "iso:country":"US",
    "sg:address":"113 1st St SE",
    "sg:city":"Moultrie",
    "sg:classifiers":[
        {
            "category":"Personal",
            "subcategory":"Beauty Salon",
            "type":"Services"
        }
    ],
    "sg:phone":"+1 229 890 7344",
    "sg:postcode":"31768",
    "sg:province":"GA",
    "wof:name":"Cuttin' Loose",
    "wof:placetype":"venue"
},
  "geometry": {"coordinates":[-83.787555,31.178836],"type":"Point"}
}