{
  "type": "Feature",
  "properties": {
    "iso:country":"US",
    "sg:address":"1307 1st St",
    "sg:city":"Bainbridge",
    "sg:classifiers":[
        {
            "category":"Professional",
            "subcategory":"Accounting & Tax Preparation",
            "type":"Services"
        }
    ],
    "sg:phone":"+1 229 246 9482",
    "sg:postcode":"39817",
    "sg:province":"GA",
    "sg:tags":[
        "return"
    ],
    "wof:name":"Peggys Tax & Professional Svcs",
    "wof:placetype":"venue"
},
  "geometry": {"coordinates":[-84.59257700000001,30.914037],"type":"Point"}
}