{
  "type": "Feature",
  "properties": {
    "iso:country":"US",
    "sg:address":"318 Cordele Rd",
    "sg:city":"Albany",
    "sg:classifiers":[
        {
            "category":"Autos & Motor Vehicles",
            "subcategory":"Auto Supplies",
            "type":"Retail Goods"
        }
    ],
    "sg:phone":"+1 229 888 1881",
    "sg:postcode":"31705",
    "sg:province":"GA",
    "sg:tags":[
        "tire"
    ],
    "wof:name":"Sowega Tire Service",
    "wof:placetype":"venue"
},
  "geometry": {"coordinates":[-84.076346,31.589471],"type":"Point"}
}