{
  "type": "Feature",
  "properties": {
    "iso:country":"US",
    "sg:address":"212 W Jackson St",
    "sg:city":"Dublin",
    "sg:classifiers":[
        {
            "category":"Social Services",
            "type":"Services"
        }
    ],
    "sg:phone":"+1 478 275 1125",
    "sg:postcode":"31021",
    "sg:province":"GA",
    "wof:name":"Sam Loves Office",
    "wof:placetype":"venue"
},
  "geometry": {"coordinates":[-82.906041,32.539306],"type":"Point"}
}