{
  "type": "Feature",
  "properties": {
    "iso:country":"US",
    "sg:address":"4102 Plantation Dr",
    "sg:city":"Marietta",
    "sg:classifiers":[
        {
            "category":"Professional",
            "type":"Services"
        },
        {
            "category":"Building & Trades",
            "subcategory":"Construction",
            "type":"Services"
        }
    ],
    "sg:phone":"+1 770 650 0596",
    "sg:postcode":"30062",
    "sg:province":"GA",
    "sg:tags":[
        "carpentry",
        "contractor"
    ],
    "wof:name":"Newmac Services LLC",
    "wof:placetype":"venue"
},
  "geometry": {"coordinates":[-84.434195,34.022792],"type":"Point"}
}