{
  "type": "Feature",
  "properties": {
    "addr:full":"512 Big Cedar Rd Washington GA 30673",
    "addr:housenumber":"512",
    "addr:postcode":"30673",
    "addr:street":"Big Cedar Rd",
    "iso:country":"US",
    "sg:address":"512 Big Cedar Rd",
    "sg:city":"Washington",
    "sg:classifiers":[
        {
            "category":"Organizations",
            "subcategory":"Religious Organization",
            "type":"Services"
        }
    ],
    "sg:phone":"+1 706 678 7980",
    "sg:postcode":"30673",
    "sg:province":"GA",
    "wof:name":"Bethlehem Baptist Church",
    "wof:placetype":"venue"
},
  "geometry": {"coordinates":[-82.631225,33.660106],"type":"Point"}
}