{
  "type": "Feature",
  "properties": {
    "addr:full":"1520 Brookcliff Cir Marietta GA 30062",
    "addr:housenumber":"1520",
    "addr:postcode":"30062",
    "addr:street":"Brookcliff Cir",
    "iso:country":"US",
    "sg:address":"1520 Brookcliff Cir",
    "sg:city":"Marietta",
    "sg:classifiers":[
        {
            "category":"Museum",
            "subcategory":"Botanical Garden",
            "type":"Entertainment"
        }
    ],
    "sg:phone":"+1 770 923 7566",
    "sg:postcode":"30062",
    "sg:province":"GA",
    "sg:tags":[
        "zoological"
    ],
    "wof:name":"Strickly For The Birds",
    "wof:placetype":"venue"
},
  "geometry": {"coordinates":[-84.4678,33.986552],"type":"Point"}
}