{
  "type": "Feature",
  "properties": {
    "iso:country":"US",
    "sg:address":"55 Boone Dr",
    "sg:city":"Newnan",
    "sg:classifiers":[
        {
            "category":"Building & Trades",
            "subcategory":"Construction",
            "type":"Services"
        }
    ],
    "sg:phone":"+1 770 254 2360",
    "sg:postcode":"30263",
    "sg:province":"GA",
    "sg:tags":[
        "marking",
        "maintenance",
        "parking"
    ],
    "wof:name":"Street Dept Public Works",
    "wof:placetype":"venue"
},
  "geometry": {"coordinates":[-84.81235,33.372188],"type":"Point"}
}