{
  "type": "Feature",
  "properties": {
    "iso:country":"US",
    "sg:address":"170 Floyd Ln",
    "sg:city":"Hampton",
    "sg:classifiers":[
        {
            "category":"Personal",
            "subcategory":"Beauty Salon",
            "type":"Services"
        }
    ],
    "sg:phone":"+1 770 946 3340",
    "sg:postcode":"30228",
    "sg:province":"GA",
    "wof:name":"Hair Styles By Juliane",
    "wof:placetype":"venue"
},
  "geometry": {"coordinates":[-84.271823,33.371038],"type":"Point"}
}