{
  "type": "Feature",
  "properties": {
    "iso:country":"US",
    "sg:address":"991 Deron Dr",
    "sg:city":"Lawrenceville",
    "sg:classifiers":[
        {
            "category":"Wholesale",
            "subcategory":"Durable Goods & Equipment",
            "type":"Manufacturing & Wholesale Goods"
        }
    ],
    "sg:phone":"+1 770 982 6768",
    "sg:postcode":"30044",
    "sg:province":"GA",
    "sg:tags":[
        "fire",
        "extinguisher"
    ],
    "wof:name":"Fire Pro",
    "wof:placetype":"venue"
},
  "geometry": {"coordinates":[-84.02522999999999,33.900631],"type":"Point"}
}