{
  "type": "Feature",
  "properties": {
    "iso:country":"US",
    "sg:address":"600 W Peachtree St Ste 1570",
    "sg:city":"Atlanta",
    "sg:classifiers":[
        {
            "category":"Health Services",
            "subcategory":"Clinic",
            "type":"Services"
        }
    ],
    "sg:phone":"+1 678 522 6548",
    "sg:postcode":"30308",
    "sg:province":"GA",
    "sg:tags":[
        "counseling",
        "mental"
    ],
    "sg:website":"www.drturpeau.com",
    "wof:name":"Dr. Aaron Turpeau",
    "wof:placetype":"venue"
},
  "geometry": {"coordinates":[-84.388158,33.77074],"type":"Point"}
}