{
  "type": "Feature",
  "properties": {
    "iso:country":"US",
    "sg:address":"1922 Ledo Rd",
    "sg:city":"Albany",
    "sg:classifiers":[
        {
            "category":"Building & Trades",
            "subcategory":"Construction",
            "type":"Services"
        }
    ],
    "sg:phone":"+1 229 446 1515",
    "sg:postcode":"31707",
    "sg:province":"GA",
    "sg:tags":[
        "contractor"
    ],
    "wof:name":"Meco Of Albany",
    "wof:placetype":"venue"
},
  "geometry": {"coordinates":[-84.188491,31.622599],"type":"Point"}
}