{
  "type": "Feature",
  "properties": {
    "addr:full":"510 Main St Palmetto GA 30268",
    "addr:housenumber":"510",
    "addr:postcode":"30268",
    "addr:street":"Main St",
    "iso:country":"US",
    "sg:address":"510 Main St",
    "sg:city":"Palmetto",
    "sg:classifiers":[
        {
            "category":"Retail",
            "subcategory":"Auto Repair",
            "type":"Services"
        }
    ],
    "sg:phone":"+1 770 463 2639",
    "sg:postcode":"30268",
    "sg:province":"GA",
    "sg:tags":[
        "body",
        "shop"
    ],
    "wof:name":"Palmetto Auto Body",
    "wof:placetype":"venue"
},
  "geometry": {"coordinates":[-84.70909899999999,33.5322],"type":"Point"}
}