{
  "type": "Feature",
  "properties": {
    "addr:full":"5525 Ogeechee Rd Savannah GA 31405",
    "addr:housenumber":"5525",
    "addr:postcode":"31405",
    "addr:street":"Ogeechee Rd",
    "iso:country":"US",
    "sg:address":"5525 Ogeechee Rd",
    "sg:city":"Savannah",
    "sg:classifiers":[
        {
            "category":"Autos & Motor Vehicles",
            "subcategory":"Automobile Sales",
            "type":"Retail Goods"
        }
    ],
    "sg:phone":"+1 912 447 5155",
    "sg:postcode":"31405",
    "sg:province":"GA",
    "sg:tags":[
        "car",
        "used"
    ],
    "wof:name":"DC Auto Sales",
    "wof:placetype":"venue"
},
  "geometry": {"coordinates":[-81.209937,32.039004],"type":"Point"}
}