{
  "type": "Feature",
  "properties": {
    "iso:country":"US",
    "sg:address":"3445 Peachtree Rd",
    "sg:city":"Atlanta",
    "sg:classifiers":[
        {
            "category":"Real Estate",
            "subcategory":"Developer",
            "type":"Services"
        }
    ],
    "sg:phone":"+1 404 495 7500",
    "sg:postcode":"30305",
    "sg:province":"GA",
    "wof:name":"Place Collegiate Properties LP",
    "wof:placetype":"venue"
},
  "geometry": {"coordinates":[-84.365098,33.848806],"type":"Point"}
}