{
  "type": "Feature",
  "properties": {
    "addr:full":"215 Tawneywood Way Alpharetta GA 30022",
    "addr:housenumber":"215",
    "addr:postcode":"30022",
    "addr:street":"Tawneywood Way",
    "iso:country":"US",
    "sg:address":"215 Tawneywood Way",
    "sg:city":"Alpharetta",
    "sg:classifiers":[
        {
            "category":"Professional",
            "subcategory":"Management & Consulting",
            "type":"Services"
        }
    ],
    "sg:phone":"+1 770 442 9805",
    "sg:postcode":"30022",
    "sg:province":"GA",
    "wof:name":"Wordman Inc",
    "wof:placetype":"venue"
},
  "geometry": {"coordinates":[-84.26287499999999,34.031734],"type":"Point"}
}