{
  "type": "Feature",
  "properties": {
    "addr:full":"1915 Porter Springs Rd Dahlonega GA 30533",
    "addr:housenumber":"1915",
    "addr:postcode":"30533",
    "addr:street":"Porter Springs Rd",
    "iso:country":"US",
    "sg:address":"1915 Porter Springs Rd",
    "sg:city":"Dahlonega",
    "sg:classifiers":[
        {
            "category":"Banks & Credit Unions",
            "subcategory":"Bank",
            "type":"Services"
        }
    ],
    "sg:phone":"+1 706 864 5365",
    "sg:postcode":"30533",
    "sg:province":"GA",
    "sg:tags":[
        "mortgage"
    ],
    "wof:name":"Sb Processing",
    "wof:placetype":"venue"
},
  "geometry": {"coordinates":[-83.930774,34.588756],"type":"Point"}
}