{
  "type": "Feature",
  "properties": {
    "iso:country":"US",
    "sg:address":"103 Memorial Dr",
    "sg:city":"Warrenton",
    "sg:classifiers":[
        {
            "category":"Real Estate",
            "subcategory":"Real Estate Agent",
            "type":"Services"
        }
    ],
    "sg:phone":"+1 706 465 3241",
    "sg:postcode":"30828",
    "sg:province":"GA",
    "wof:name":"Forest & Land Svc Inc",
    "wof:placetype":"venue"
},
  "geometry": {"coordinates":[-82.66234,33.406313],"type":"Point"}
}