{
  "type": "Feature",
  "properties": {
    "iso:country":"US",
    "sg:address":"2788 E Cherokee Dr",
    "sg:city":"Canton",
    "sg:classifiers":[
        {
            "category":"Shopping",
            "subcategory":"Bicycles & Sporting Goods",
            "type":"Retail Goods"
        }
    ],
    "sg:phone":"+1 770 345 1356",
    "sg:postcode":"30115",
    "sg:province":"GA",
    "wof:name":"Ultimate Paintball Inc",
    "wof:placetype":"venue"
},
  "geometry": {"coordinates":[-84.42268300000001,34.16988],"type":"Point"}
}