{
  "type": "Feature",
  "properties": {
    "iso:country":"US",
    "sg:address":"1110 Telfair St",
    "sg:city":"Dublin",
    "sg:classifiers":[
        {
            "category":"Retail",
            "subcategory":"Car Wash",
            "type":"Services"
        }
    ],
    "sg:phone":"+1 478 275 9001",
    "sg:postcode":"31021",
    "sg:province":"GA",
    "sg:tags":[
        "carwash"
    ],
    "wof:name":"Sparkle Car Wash",
    "wof:placetype":"venue"
},
  "geometry": {"coordinates":[-82.91495999999999,32.52622],"type":"Point"}
}