{
  "type": "Feature",
  "properties": {
    "addr:full":"139 Bowens Mill Rd SE Douglas GA 31533",
    "addr:housenumber":"139",
    "addr:postcode":"31533",
    "addr:street":"Bowens Mill Rd Se",
    "iso:country":"US",
    "sg:address":"139 Bowens Mill Rd SE",
    "sg:city":"Douglas",
    "sg:classifiers":[
        {
            "category":"Retail",
            "subcategory":"Auto Repair",
            "type":"Services"
        }
    ],
    "sg:phone":"+1 912 384 4447",
    "sg:postcode":"31533",
    "sg:province":"GA",
    "sg:tags":[
        "general"
    ],
    "wof:name":"Roberts Auto Plus",
    "wof:placetype":"venue"
},
  "geometry": {"coordinates":[-82.850167,31.487823],"type":"Point"}
}