{
  "type": "Feature",
  "properties": {
    "iso:country":"US",
    "sg:address":"4400 Reason Rd NW",
    "sg:city":"Acworth",
    "sg:classifiers":[
        {
            "category":"Manufacturing",
            "subcategory":"Metals",
            "type":"Manufacturing & Wholesale Goods"
        }
    ],
    "sg:phone":"+1 770 974 1480",
    "sg:postcode":"30101",
    "sg:province":"GA",
    "sg:tags":[
        "equipment",
        "heat",
        "mfg",
        "fusing",
        "transfer"
    ],
    "wof:name":"Practix Mfg",
    "wof:placetype":"venue"
},
  "geometry": {"coordinates":[-84.65136699999999,34.06255],"type":"Point"}
}