{
  "type": "Feature",
  "properties": {
    "addr:full":"407 Red Oak Rd Tifton GA 31793",
    "addr:housenumber":"407",
    "addr:postcode":"31793",
    "addr:street":"Red Oak Rd",
    "iso:country":"US",
    "sg:address":"407 Red Oak Rd",
    "sg:city":"Tifton",
    "sg:classifiers":[
        {
            "category":"Farming",
            "subcategory":"Farm",
            "type":"Manufacturing & Wholesale Goods"
        }
    ],
    "sg:phone":"+1 229 386 1608",
    "sg:postcode":"31793",
    "sg:province":"GA",
    "sg:tags":[
        "crop",
        "general"
    ],
    "wof:name":"Roger Womack",
    "wof:placetype":"venue"
},
  "geometry": {"coordinates":[-83.606909,31.57123],"type":"Point"}
}