{
  "type": "Feature",
  "properties": {
    "addr:full":"5518 Chamblee Dunwoody Rd Atlanta GA 30338",
    "addr:housenumber":"5518",
    "addr:postcode":"30338",
    "addr:street":"Chamblee Dunwoody Rd",
    "iso:country":"US",
    "sg:address":"5518 Chamblee Dunwoody Rd",
    "sg:city":"Atlanta",
    "sg:classifiers":[
        {
            "category":"Shopping",
            "type":"Retail Goods"
        }
    ],
    "sg:phone":"+1 770 804 8090",
    "sg:postcode":"30338",
    "sg:province":"GA",
    "sg:tags":[
        "wireless",
        "satellite"
    ],
    "wof:name":"Dial America Inc",
    "wof:placetype":"venue"
},
  "geometry": {"coordinates":[-84.336117,33.94894],"type":"Point"}
}