{
  "type": "Feature",
  "properties": {
    "iso:country":"US",
    "sg:address":"207 Main St",
    "sg:city":"Eastman",
    "sg:classifiers":[
        {
            "category":"Personal",
            "subcategory":"Shoe Repair & Shine",
            "type":"Services"
        }
    ],
    "sg:phone":"+1 478 374 1792",
    "sg:postcode":"31023",
    "sg:province":"GA",
    "sg:tags":[
        "repairing",
        "boot"
    ],
    "wof:name":"Eastman Shoe Hospital",
    "wof:placetype":"venue"
},
  "geometry": {"coordinates":[-83.17569899999999,32.198093],"type":"Point"}
}