{
  "type": "Feature",
  "properties": {
    "addr:full":"1313 Hogansville Rd La Grange GA 30241",
    "addr:housenumber":"1313",
    "addr:postcode":"30241",
    "addr:street":"Hogansville Rd",
    "iso:country":"US",
    "sg:address":"1313 Hogansville Rd",
    "sg:city":"La Grange",
    "sg:classifiers":[
        {
            "category":"Retail",
            "subcategory":"Auto Repair",
            "type":"Services"
        }
    ],
    "sg:phone":"+1 706 837 9601",
    "sg:postcode":"30241",
    "sg:province":"GA",
    "sg:tags":[
        "center",
        "tire"
    ],
    "wof:name":"Tech Tires Inc",
    "wof:placetype":"venue"
},
  "geometry": {"coordinates":[-85.00343599999999,33.052919],"type":"Point"}
}