{
  "type": "Feature",
  "properties": {
    "addr:full":"1883 Jameson Cir Lawrenceville GA 30043",
    "addr:housenumber":"1883",
    "addr:postcode":"30043",
    "addr:street":"Jameson Cir",
    "iso:country":"US",
    "sg:address":"1883 Jameson Cir",
    "sg:city":"Lawrenceville",
    "sg:classifiers":[
        {
            "category":"Shopping",
            "subcategory":"Gifts & Souvenirs",
            "type":"Retail Goods"
        }
    ],
    "sg:phone":"+1 770 513 7671",
    "sg:postcode":"30043",
    "sg:province":"GA",
    "sg:tags":[
        "shop"
    ],
    "wof:name":"Almart Enterprises",
    "wof:placetype":"venue"
},
  "geometry": {"coordinates":[-83.970558,34.032726],"type":"Point"}
}