{
  "type": "Feature",
  "properties": {
    "iso:country":"US",
    "sg:address":"962 Glenverness Dr",
    "sg:city":"Marietta",
    "sg:classifiers":[
        {
            "category":"Health Services",
            "subcategory":"Doctor",
            "type":"Services"
        }
    ],
    "sg:phone":"+1 770 992 0235",
    "sg:postcode":"30068",
    "sg:province":"GA",
    "sg:tags":[
        "surgeon",
        "oral"
    ],
    "wof:name":"Sayeg Mark G DDS",
    "wof:placetype":"venue"
},
  "geometry": {"coordinates":[-84.392799,33.973099],"type":"Point"}
}