{
  "type": "Feature",
  "properties": {
    "addr:full":"50 Circle Creek Dr Stockbridge GA 30281",
    "addr:housenumber":"50",
    "addr:postcode":"30281",
    "addr:street":"Circle Creek Dr",
    "iso:country":"US",
    "sg:address":"50 Circle Creek Dr",
    "sg:city":"Stockbridge",
    "sg:classifiers":[
        {
            "category":"Personal",
            "type":"Services"
        }
    ],
    "sg:phone":"+1 770 474 7532",
    "sg:postcode":"30281",
    "sg:province":"GA",
    "wof:name":"Marshall D Hembree",
    "wof:placetype":"venue"
},
  "geometry": {"coordinates":[-84.19654800000001,33.565981],"type":"Point"}
}