{
  "type": "Feature",
  "properties": {
    "iso:country":"US",
    "sg:address":"1930 Rocksram Dr",
    "sg:city":"Buford",
    "sg:classifiers":[
        {
            "category":"Airline",
            "type":"Transportation"
        }
    ],
    "sg:phone":"+1 678 442 8006",
    "sg:postcode":"30519",
    "sg:province":"GA",
    "wof:name":"Bovee Services Company Inc",
    "wof:placetype":"venue"
},
  "geometry": {"coordinates":[-83.959968,34.048885],"type":"Point"}
}