{
  "type": "Feature",
  "properties": {
    "addr:full":"2135 Post Oak Tritt Rd Marietta GA 30062",
    "addr:housenumber":"2135",
    "addr:postcode":"30062",
    "addr:street":"Post Oak Tritt Rd",
    "iso:country":"US",
    "sg:address":"2135 Post Oak Tritt Rd",
    "sg:city":"Marietta",
    "sg:classifiers":[
        {
            "category":"Retail",
            "subcategory":"Veterinary Services",
            "type":"Services"
        },
        {
            "category":"Retail",
            "subcategory":"Pet Boarding",
            "type":"Services"
        }
    ],
    "sg:phone":"+1 770 977 8300",
    "sg:postcode":"30062",
    "sg:province":"GA",
    "sg:tags":[
        "veterinarian",
        "boarding/pet",
        "sitting"
    ],
    "sg:website":"www.sprayberryanimalhospital.com",
    "wof:name":"Sprayberry Animal Hospital",
    "wof:placetype":"venue"
},
  "geometry": {"coordinates":[-84.487999,34.016899],"type":"Point"}
}