{
  "type": "Feature",
  "properties": {
    "addr:full":"452 Park 20 W Grovetown GA 30813",
    "addr:housenumber":"452;20",
    "addr:postcode":"30813",
    "addr:street":"Park;W",
    "iso:country":"US",
    "sg:address":"452 Park 20 W",
    "sg:city":"Grovetown",
    "sg:classifiers":[
        {
            "category":"Travel",
            "subcategory":"Hotels & Motels",
            "type":"Entertainment"
        }
    ],
    "sg:phone":"+1 706 651 9100",
    "sg:postcode":"30813",
    "sg:province":"GA",
    "wof:name":"Best Western Inn",
    "wof:placetype":"venue"
},
  "geometry": {"coordinates":[-82.134523,33.480144],"type":"Point"}
}