{
  "type": "Feature",
  "properties": {
    "addr:full":"10506 Tobano Trl Jonesboro GA 30238",
    "addr:housenumber":"10506",
    "addr:postcode":"30238",
    "addr:street":"Tobano Trl",
    "iso:country":"US",
    "sg:address":"10506 Tobano Trl",
    "sg:city":"Jonesboro",
    "sg:classifiers":[
        {
            "category":"Restaurant",
            "type":"Food & Drink"
        }
    ],
    "sg:phone":"+1 770 472 3579",
    "sg:postcode":"30238",
    "sg:province":"GA",
    "sg:tags":[
        "eating"
    ],
    "wof:name":"Sweets Southern Kit & Catrg",
    "wof:placetype":"venue"
},
  "geometry": {"coordinates":[-84.360361,33.469185],"type":"Point"}
}