{
  "type": "Feature",
  "properties": {
    "addr:full":"3620 Wilson Cove Ct Snellville GA 30039",
    "addr:housenumber":"3620",
    "addr:postcode":"30039",
    "addr:street":"Wilson Cove Ct",
    "iso:country":"US",
    "sg:address":"3620 Wilson Cove Ct",
    "sg:city":"Snellville",
    "sg:classifiers":[
        {
            "category":"Professional",
            "subcategory":"Computer Services",
            "type":"Services"
        }
    ],
    "sg:phone":"+1 678 344 9113",
    "sg:postcode":"30039",
    "sg:province":"GA",
    "sg:tags":[
        "development",
        "software"
    ],
    "wof:name":"Vision 6 Inc",
    "wof:placetype":"venue"
},
  "geometry": {"coordinates":[-84.063712,33.789438],"type":"Point"}
}