{
  "type": "Feature",
  "properties": {
    "iso:country":"US",
    "sg:address":"1204 Weatherstone Way",
    "sg:city":"Peachtree City",
    "sg:classifiers":[
        {
            "category":"Building & Trades",
            "subcategory":"Construction",
            "type":"Services"
        }
    ],
    "sg:phone":"+1 770 487 3295",
    "sg:postcode":"30269",
    "sg:province":"GA",
    "sg:tags":[
        "house"
    ],
    "wof:name":"Protege Homes",
    "wof:placetype":"venue"
},
  "geometry": {"coordinates":[-84.53844700000001,33.360328],"type":"Point"}
}