{
  "type": "Feature",
  "properties": {
    "addr:full":"1631 S Broad St Monroe GA 30655",
    "addr:housenumber":"1631",
    "addr:postcode":"30655",
    "addr:street":"S Broad St",
    "iso:country":"US",
    "sg:address":"1631 S Broad St",
    "sg:city":"Monroe",
    "sg:classifiers":[
        {
            "category":"Building & Trades",
            "subcategory":"Construction",
            "type":"Services"
        }
    ],
    "sg:phone":"+1 770 207 6637",
    "sg:postcode":"30655",
    "sg:province":"GA",
    "sg:tags":[
        "contractor"
    ],
    "wof:name":"Gratis Drywall Inc",
    "wof:placetype":"venue"
},
  "geometry": {"coordinates":[-83.701976,33.771418],"type":"Point"}
}