{
  "type": "Feature",
  "properties": {
    "addr:full":"2759 Campbell Blvd Ellenwood GA 30294",
    "addr:housenumber":"2759",
    "addr:postcode":"30294",
    "addr:street":"Campbell Blvd",
    "iso:country":"US",
    "sg:address":"2759 Campbell Blvd",
    "sg:city":"Ellenwood",
    "sg:classifiers":[
        {
            "category":"Retail",
            "subcategory":"Auto Rental",
            "type":"Services"
        }
    ],
    "sg:phone":"+1 404 968 0818",
    "sg:postcode":"30294",
    "sg:province":"GA",
    "sg:tags":[
        "renting",
        "leasing",
        "trailer",
        "utility"
    ],
    "sg:website":"www.nationalsemi.com",
    "wof:name":"National Semi Trailer Corp",
    "wof:placetype":"venue"
},
  "geometry": {"coordinates":[-84.306527,33.618064],"type":"Point"}
}