{
  "type": "Feature",
  "properties": {
    "iso:country":"US",
    "sg:address":"430 Highland Lake Vw",
    "sg:city":"Atlanta",
    "sg:classifiers":[
        {
            "category":"Personal",
            "subcategory":"Beauty Salon",
            "type":"Services"
        }
    ],
    "sg:phone":"+1 404 346 0715",
    "sg:postcode":"30349",
    "sg:province":"GA",
    "sg:tags":[
        "treatment",
        "skin"
    ],
    "wof:name":"IIWI Natural Skin & Body Cr",
    "wof:placetype":"venue"
},
  "geometry": {"coordinates":[-84.554766,33.644486],"type":"Point"}
}