{
  "type": "Feature",
  "properties": {
    "iso:country":"US",
    "sg:address":"283 Nancy Dr",
    "sg:city":"Hartwell",
    "sg:classifiers":[
        {
            "category":"Real Estate",
            "subcategory":"Real Estate Operator",
            "type":"Services"
        }
    ],
    "sg:phone":"+1 706 376 2589",
    "sg:postcode":"30643",
    "sg:province":"GA",
    "sg:tags":[
        "apartment"
    ],
    "wof:name":"Juniper Court Apartments",
    "wof:placetype":"venue"
},
  "geometry": {"coordinates":[-82.913675,34.359008],"type":"Point"}
}