{
  "type": "Feature",
  "properties": {
    "addr:full":"7 Lee's Xing Valdosta GA 31605",
    "addr:housenumber":"7",
    "addr:postcode":"31605",
    "addr:street":"Lee'S Xing",
    "iso:country":"US",
    "sg:address":"7 Lee's Xing",
    "sg:city":"Valdosta",
    "sg:classifiers":[
        {
            "category":"Organizations",
            "subcategory":"Religious Organization",
            "type":"Services"
        }
    ],
    "sg:phone":"+1 229 242 3828",
    "sg:postcode":"31605",
    "sg:province":"GA",
    "wof:name":"Watch & Pray Ministries",
    "wof:placetype":"venue"
},
  "geometry": {"coordinates":[-83.300138,30.896055],"type":"Point"}
}