{
  "type": "Feature",
  "properties": {
    "addr:full":"2219 Toledo Dr Albany GA 31705",
    "addr:housenumber":"2219",
    "addr:postcode":"31705",
    "addr:street":"Toledo Dr",
    "iso:country":"US",
    "sg:address":"2219 Toledo Dr",
    "sg:city":"Albany",
    "sg:classifiers":[
        {
            "category":"Freight",
            "type":"Transportation"
        }
    ],
    "sg:phone":"+1 229 888 5850",
    "sg:postcode":"31705",
    "sg:province":"GA",
    "sg:tags":[
        "courier"
    ],
    "wof:name":"UPS",
    "wof:placetype":"venue"
},
  "geometry": {"coordinates":[-84.09837899999999,31.558393],"type":"Point"}
}