{
  "type": "Feature",
  "properties": {
    "addr:full":"9314 Callus Mill Rd Lula GA 30554",
    "addr:housenumber":"9314",
    "addr:postcode":"30554",
    "addr:street":"Callus Mill Rd",
    "iso:country":"US",
    "sg:address":"9314 Callus Mill Rd",
    "sg:city":"Lula",
    "sg:classifiers":[
        {
            "category":"Professional",
            "type":"Services"
        }
    ],
    "sg:phone":"+1 770 983 3014",
    "sg:postcode":"30554",
    "sg:province":"GA",
    "wof:name":"Irvin G Michel",
    "wof:placetype":"venue"
},
  "geometry": {"coordinates":[-83.689167,34.501178],"type":"Point"}
}