{
  "type": "Feature",
  "properties": {
    "iso:country":"US",
    "sg:address":"2803 Fears Rd",
    "sg:city":"Madison",
    "sg:classifiers":[
        {
            "category":"Building & Trades",
            "subcategory":"Construction",
            "type":"Services"
        }
    ],
    "sg:phone":"+1 706 557 7444",
    "sg:postcode":"30650",
    "sg:province":"GA",
    "sg:tags":[
        "heavy"
    ],
    "wof:name":"Cedar Hill Inc",
    "wof:placetype":"venue"
},
  "geometry": {"coordinates":[-83.581639,33.56548],"type":"Point"}
}