{
  "type": "Feature",
  "properties": {
    "iso:country":"US",
    "sg:address":"8494 Main St",
    "sg:city":"Woodstock",
    "sg:classifiers":[
        {
            "category":"Professional",
            "subcategory":"Business Services",
            "type":"Services"
        }
    ],
    "sg:phone":"+1 770 591 5944",
    "sg:postcode":"30188",
    "sg:province":"GA",
    "sg:tags":[
        "interior",
        "consultant",
        "design",
        "decorator"
    ],
    "wof:name":"Christine's Creations",
    "wof:placetype":"venue"
},
  "geometry": {"coordinates":[-84.51909999999999,34.102384],"type":"Point"}
}