{
  "type": "Feature",
  "properties": {
    "addr:full":"2337 Dunwoody Xing Atlanta GA 30338",
    "addr:housenumber":"2337",
    "addr:postcode":"30338",
    "addr:street":"Dunwoody Xing",
    "iso:country":"US",
    "sg:address":"2337 Dunwoody Xing",
    "sg:city":"Atlanta",
    "sg:classifiers":[
        {
            "category":"Food & Beverages",
            "subcategory":"Specialty",
            "type":"Retail Goods"
        }
    ],
    "sg:phone":"+1 770 452 0870",
    "sg:postcode":"30338",
    "sg:province":"GA",
    "sg:tags":[
        "vitamin"
    ],
    "wof:name":"GOG",
    "wof:placetype":"venue"
},
  "geometry": {"coordinates":[-84.29052299999999,33.920725],"type":"Point"}
}