{
  "type": "Feature",
  "properties": {
    "iso:country":"US",
    "sg:address":"1800 Parrish Dr SE",
    "sg:city":"Rome",
    "sg:classifiers":[
        {
            "category":"Retail",
            "subcategory":"Laundry & Dry Cleaning",
            "type":"Services"
        }
    ],
    "sg:phone":"+1 706 238 9694",
    "sg:postcode":"30161",
    "sg:province":"GA",
    "sg:tags":[
        "linen",
        "supply"
    ],
    "wof:name":"TARTAN Textile Svc",
    "wof:placetype":"venue"
},
  "geometry": {"coordinates":[-85.19512400000001,34.199172],"type":"Point"}
}