{
  "type": "Feature",
  "properties": {
    "iso:country":"US",
    "sg:address":"111 Chestnut St",
    "sg:city":"Trion",
    "sg:classifiers":[
        {
            "category":"Professional",
            "subcategory":"Accounting & Tax Preparation",
            "type":"Services"
        }
    ],
    "sg:phone":"+1 706 734 7451",
    "sg:postcode":"30753",
    "sg:province":"GA",
    "sg:tags":[
        "return"
    ],
    "wof:name":"Pettett Tax Svc",
    "wof:placetype":"venue"
},
  "geometry": {"coordinates":[-85.31576699999999,34.540172],"type":"Point"}
}