{
  "type": "Feature",
  "properties": {
    "iso:country":"US",
    "sg:address":"7095 Chappell Cir NW",
    "sg:city":"Atlanta",
    "sg:classifiers":[
        {
            "category":"Professional",
            "type":"Services"
        }
    ],
    "sg:phone":"+1 770 441 0868",
    "sg:postcode":"30360",
    "sg:province":"GA",
    "wof:name":"K & K Contract Services",
    "wof:placetype":"venue"
},
  "geometry": {"coordinates":[-84.262784,33.936818],"type":"Point"}
}