{
  "type": "Feature",
  "properties": {
    "addr:full":"4480 Park Street Atlanta GA 30303",
    "addr:housenumber":"4480",
    "addr:postcode":"30303",
    "addr:street":"Park Street",
    "iso:country":"US",
    "sg:address":"4480 Park Street",
    "sg:city":"Atlanta",
    "sg:classifiers":[
        {
            "category":"Coffee & Tea",
            "type":"Food & Drink"
        }
    ],
    "sg:phone":"+1 678 574 6449",
    "sg:postcode":"30303",
    "sg:province":"GA",
    "sg:website":"www.missscarlets.com",
    "wof:name":"Miss Scarlets Chocolate Emporium",
    "wof:placetype":"venue"
},
  "geometry": {"coordinates":[-84.38897,33.755418],"type":"Point"}
}