{
  "type": "Feature",
  "properties": {
    "iso:country":"US",
    "sg:address":"2359 Timber Ridge Ct",
    "sg:city":"Decatur",
    "sg:classifiers":[
        {
            "category":"Building & Trades",
            "subcategory":"Construction",
            "type":"Services"
        }
    ],
    "sg:phone":"+1 404 212 8916",
    "sg:postcode":"30032",
    "sg:province":"GA",
    "sg:tags":[
        "contractor"
    ],
    "wof:name":"G & C Insulators Inc",
    "wof:placetype":"venue"
},
  "geometry": {"coordinates":[-84.291595,33.714763],"type":"Point"}
}