{
  "type": "Feature",
  "properties": {
    "iso:country":"US",
    "sg:address":"1078 Cooley Dr",
    "sg:city":"Gainesville",
    "sg:classifiers":[
        {
            "category":"Building & Trades",
            "subcategory":"Construction",
            "type":"Services"
        }
    ],
    "sg:phone":"+1 770 536 9296",
    "sg:postcode":"30501",
    "sg:province":"GA",
    "sg:tags":[
        "concrete",
        "contractor"
    ],
    "wof:name":"Leroy Goss Jr",
    "wof:placetype":"venue"
},
  "geometry": {"coordinates":[-83.807154,34.289173],"type":"Point"}
}