{
  "type": "Feature",
  "properties": {
    "addr:full":"11 Towns Bluff Rd Hazlehurst GA 31539",
    "addr:housenumber":"11",
    "addr:postcode":"31539",
    "addr:street":"Towns Bluff Rd",
    "iso:country":"US",
    "sg:address":"11 Towns Bluff Rd",
    "sg:city":"Hazlehurst",
    "sg:classifiers":[
        {
            "category":"Shopping",
            "subcategory":"Bicycles & Sporting Goods",
            "type":"Retail Goods"
        }
    ],
    "sg:phone":"+1 912 375 3700",
    "sg:postcode":"31539",
    "sg:province":"GA",
    "wof:name":"J & E Bait & Tackle",
    "wof:placetype":"venue"
},
  "geometry": {"coordinates":[-82.587197,31.919537],"type":"Point"}
}