{
  "type": "Feature",
  "properties": {
    "iso:country":"US",
    "sg:address":"421 S Main St",
    "sg:city":"Alpharetta",
    "sg:classifiers":[
        {
            "category":"Retail",
            "subcategory":"Auto Repair",
            "type":"Services"
        }
    ],
    "sg:phone":"+1 770 442 9451",
    "sg:postcode":"30004",
    "sg:province":"GA",
    "sg:website":"www.AtlProRepair.com",
    "wof:name":"Professional Automotive Repair",
    "wof:placetype":"venue"
},
  "geometry": {"coordinates":[-84.30551,34.066245],"type":"Point"}
}