{
  "type": "Feature",
  "properties": {
    "iso:country":"US",
    "sg:address":"126 Riverstone Pkwy",
    "sg:city":"Canton",
    "sg:classifiers":[
        {
            "category":"Personal",
            "subcategory":"Barber",
            "type":"Services"
        }
    ],
    "sg:phone":"+1 770 720 7068",
    "sg:postcode":"30114",
    "sg:province":"GA",
    "wof:name":"A Touch of Beauty",
    "wof:placetype":"venue"
},
  "geometry": {"coordinates":[-84.465103,34.255699],"type":"Point"}
}