{
  "type": "Feature",
  "properties": {
    "iso:country":"US",
    "sg:address":"2870 Highway 212 SW Ste C",
    "sg:city":"Conyers",
    "sg:classifiers":[
        {
            "category":"Restaurant",
            "type":"Food & Drink"
        }
    ],
    "sg:phone":"+1 770 761 2999",
    "sg:postcode":"30094",
    "sg:province":"GA",
    "sg:tags":[
        "chinese"
    ],
    "wof:name":"Conyers China Star",
    "wof:placetype":"venue"
},
  "geometry": {"coordinates":[-84.079227,33.616639],"type":"Point"}
}