{
  "type": "Feature",
  "properties": {
    "iso:country":"US",
    "sg:address":"23 N Avondale Plz",
    "sg:city":"Avondale Estates",
    "sg:classifiers":[
        {
            "category":"Professional",
            "subcategory":"Lawyer & Legal Services",
            "type":"Services"
        }
    ],
    "sg:phone":"+1 404 296 7976",
    "sg:postcode":"30002",
    "sg:province":"GA",
    "wof:name":"Nicholas Stephen W Atty",
    "wof:placetype":"venue"
},
  "geometry": {"coordinates":[-84.266899,33.776299],"type":"Point"}
}