{
  "type": "Feature",
  "properties": {
    "addr:full":"2474 Magnolia Rd Thomasville GA 31757",
    "addr:housenumber":"2474",
    "addr:postcode":"31757",
    "addr:street":"Magnolia Rd",
    "iso:country":"US",
    "sg:address":"2474 Magnolia Rd",
    "sg:city":"Thomasville",
    "sg:classifiers":[
        {
            "category":"Banks & Credit Unions",
            "subcategory":"Bank",
            "type":"Services"
        }
    ],
    "sg:phone":"+1 229 228 6460",
    "sg:postcode":"31757",
    "sg:province":"GA",
    "sg:tags":[
        "financing"
    ],
    "wof:name":"Modern Loan Administrative Ofc",
    "wof:placetype":"venue"
},
  "geometry": {"coordinates":[-83.980959,30.805059],"type":"Point"}
}