{
  "type": "Feature",
  "properties": {
    "addr:full":"3234 Talimore Cir Marietta GA 30066",
    "addr:housenumber":"3234",
    "addr:postcode":"30066",
    "addr:street":"Talimore Cir",
    "iso:country":"US",
    "sg:address":"3234 Talimore Cir",
    "sg:city":"Marietta",
    "sg:classifiers":[
        {
            "category":"Professional",
            "type":"Services"
        }
    ],
    "sg:phone":"+1 770 321 6566",
    "sg:postcode":"30066",
    "sg:province":"GA",
    "sg:tags":[
        "establishment"
    ],
    "wof:name":"Arlan Grp",
    "wof:placetype":"venue"
},
  "geometry": {"coordinates":[-84.468689,34.036358],"type":"Point"}
}