{
  "type": "Feature",
  "properties": {
    "iso:country":"US",
    "sg:address":"2000 Lakewood Ave SE",
    "sg:city":"Atlanta",
    "sg:classifiers":[
        {
            "category":"Communications",
            "subcategory":"Film & Video Production",
            "type":"Services"
        }
    ],
    "sg:phone":"+1 404 622 9245",
    "sg:postcode":"30315",
    "sg:province":"GA",
    "sg:tags":[
        "motion",
        "picture"
    ],
    "wof:name":"Bob Shelley's Special Effects International Inc",
    "wof:placetype":"venue"
},
  "geometry": {"coordinates":[-84.38800000000001,33.70076],"type":"Point"}
}