{
  "type": "Feature",
  "properties": {
    "addr:full":"2900 Delk Rd SE Ste 1700 Marietta GA 30067",
    "addr:housenumber":"2900",
    "addr:postcode":"30067",
    "addr:street":"Delk Rd Se Ste 1700",
    "iso:country":"US",
    "sg:address":"2900 Delk Rd SE Ste 1700",
    "sg:city":"Marietta",
    "sg:phone":"+1 770 952 1965",
    "sg:postcode":"30067",
    "sg:province":"GA",
    "sg:website":"http://www.kiriakos.com",
    "wof:name":"Christos' Pizza",
    "wof:placetype":"venue"
},
  "geometry": {"coordinates":[-84.468644,33.923976],"type":"Point"}
}