{
  "type": "Feature",
  "properties": {
    "addr:full":"6163 Pine Ln Douglasville GA 30135",
    "addr:housenumber":"6163",
    "addr:postcode":"30135",
    "addr:street":"Pine Ln",
    "iso:country":"US",
    "sg:address":"6163 Pine Ln",
    "sg:city":"Douglasville",
    "sg:classifiers":[
        {
            "category":"Professional",
            "subcategory":"Business Services",
            "type":"Services"
        }
    ],
    "sg:phone":"+1 770 942 1773",
    "sg:postcode":"30135",
    "sg:province":"GA",
    "wof:name":"Calibre Enterprises Inc",
    "wof:placetype":"venue"
},
  "geometry": {"coordinates":[-84.776184,33.717293],"type":"Point"}
}