{
  "type": "Feature",
  "properties": {
    "iso:country":"US",
    "sg:address":"1219 Cumberland Mall",
    "sg:city":"Atlanta",
    "sg:classifiers":[
        {
            "category":"Shopping",
            "subcategory":"Clothing, Apparel, & Fashions",
            "type":"Retail Goods"
        }
    ],
    "sg:phone":"+1 678 305 0406",
    "sg:postcode":"30339",
    "sg:province":"GA",
    "wof:name":"August Max",
    "wof:placetype":"venue"
},
  "geometry": {"coordinates":[-84.47125,33.879584],"type":"Point"}
}