{
  "type": "Feature",
  "properties": {
    "iso:country":"US",
    "sg:address":"522 Main St S",
    "sg:city":"Tifton",
    "sg:classifiers":[
        {
            "category":"Restaurant",
            "type":"Food & Drink"
        }
    ],
    "sg:phone":"+1 229 382 7811",
    "sg:postcode":"31794",
    "sg:province":"GA",
    "sg:tags":[
        "eating"
    ],
    "wof:name":"Shady Lane Drive Inn Inc",
    "wof:placetype":"venue"
},
  "geometry": {"coordinates":[-83.50923299999999,31.450867],"type":"Point"}
}