{
  "type": "Feature",
  "properties": {
    "addr:full":"8290 Lee Rd Lithia Springs GA 30122",
    "addr:housenumber":"8290",
    "addr:postcode":"30122",
    "addr:street":"Lee Rd",
    "iso:country":"US",
    "sg:address":"8290 Lee Rd",
    "sg:city":"Lithia Springs",
    "sg:classifiers":[
        {
            "category":"Building & Trades",
            "subcategory":"Construction",
            "type":"Services"
        }
    ],
    "sg:phone":"+1 678 945 9888",
    "sg:postcode":"30122",
    "sg:province":"GA",
    "sg:tags":[
        "installation",
        "machinery"
    ],
    "wof:name":"A-1 Metal Erecting Inc",
    "wof:placetype":"venue"
},
  "geometry": {"coordinates":[-84.65755900000001,33.749969],"type":"Point"}
}