{
  "type": "Feature",
  "properties": {
    "iso:country":"US",
    "sg:address":"2137 Kingston Ct",
    "sg:city":"Marietta",
    "sg:classifiers":[
        {
            "category":"Shopping",
            "subcategory":"Clothing, Apparel, & Fashions",
            "type":"Retail Goods"
        }
    ],
    "sg:phone":"+1 770 850 9402",
    "sg:postcode":"30067",
    "sg:province":"GA",
    "wof:name":"Renata Fashion",
    "wof:placetype":"venue"
},
  "geometry": {"coordinates":[-84.49205000000001,33.925467],"type":"Point"}
}