{
  "type": "Feature",
  "properties": {
    "addr:full":"1070 Wedgewood Dr SE Conyers GA 30094",
    "addr:housenumber":"1070",
    "addr:postcode":"30094",
    "addr:street":"Wedgewood Dr Se",
    "iso:country":"US",
    "sg:address":"1070 Wedgewood Dr SE",
    "sg:city":"Conyers",
    "sg:classifiers":[
        {
            "category":"Manufacturing",
            "subcategory":"Retail Goods",
            "type":"Manufacturing & Wholesale Goods"
        }
    ],
    "sg:phone":"+1 770 388 0842",
    "sg:postcode":"30094",
    "sg:province":"GA",
    "sg:tags":[
        "floor",
        "covering"
    ],
    "wof:name":"Dilme Fred Flr Cvg Spclsts LLC",
    "wof:placetype":"venue"
},
  "geometry": {"coordinates":[-84.04390600000001,33.571002],"type":"Point"}
}