{
  "type": "Feature",
  "properties": {
    "iso:country":"US",
    "sg:address":"1026 Ponce de Leon Ave NE",
    "sg:city":"Atlanta",
    "sg:classifiers":[
        {
            "category":"Organizations",
            "subcategory":"Non-profit Organization",
            "type":"Services"
        }
    ],
    "sg:phone":"+1 404 815 0524",
    "sg:postcode":"30306",
    "sg:province":"GA",
    "sg:tags":[
        "social"
    ],
    "wof:name":"Bread For World",
    "wof:placetype":"venue"
},
  "geometry": {"coordinates":[-84.354578,33.773901],"type":"Point"}
}