{
  "type": "Feature",
  "properties": {
    "addr:full":"3816 Northeast Expy NE Atlanta GA 30345",
    "addr:housenumber":"3816",
    "addr:postcode":"30345",
    "addr:street":"Northeast Expy Ne",
    "iso:country":"US",
    "sg:address":"3816 Northeast Expy NE",
    "sg:city":"Atlanta",
    "sg:classifiers":[
        {
            "category":"Building & Trades",
            "subcategory":"Pest Control",
            "type":"Services"
        }
    ],
    "sg:phone":"+1 770 908 1788",
    "sg:postcode":"30345",
    "sg:province":"GA",
    "wof:name":"Orkin Exterminating Co Inc",
    "wof:placetype":"venue"
},
  "geometry": {"coordinates":[-84.31292000000001,33.841011],"type":"Point"}
}