{
  "type": "Feature",
  "properties": {
    "iso:country":"US",
    "sg:address":"1072 Canton St",
    "sg:city":"Roswell",
    "sg:classifiers":[
        {
            "category":"Building & Trades",
            "subcategory":"Construction",
            "type":"Services"
        }
    ],
    "sg:phone":"+1 770 642 6973",
    "sg:postcode":"30075",
    "sg:province":"GA",
    "sg:tags":[
        "interior",
        "design"
    ],
    "sg:website":"www.aprilmi.com",
    "wof:name":"April Mi",
    "wof:placetype":"venue"
},
  "geometry": {"coordinates":[-84.361625,34.027795],"type":"Point"}
}