{
  "type": "Feature",
  "properties": {
    "iso:country":"US",
    "sg:address":"2225 Annie B Trl",
    "sg:city":"Cumming",
    "sg:classifiers":[
        {
            "category":"Autos & Motor Vehicles",
            "subcategory":"Boat Sales",
            "type":"Retail Goods"
        }
    ],
    "sg:phone":"+1 678 455 9146",
    "sg:postcode":"30040",
    "sg:province":"GA",
    "wof:name":"Hercules Marine LLC",
    "wof:placetype":"venue"
},
  "geometry": {"coordinates":[-84.114175,34.24013],"type":"Point"}
}