{
  "type": "Feature",
  "properties": {
    "addr:full":"31 Demorest Ave NE Atlanta GA 30305",
    "addr:housenumber":"31",
    "addr:postcode":"30305",
    "addr:street":"Demorest Ave Ne",
    "iso:country":"US",
    "sg:address":"31 Demorest Ave NE",
    "sg:city":"Atlanta",
    "sg:classifiers":[
        {
            "category":"Professional",
            "type":"Services"
        }
    ],
    "sg:phone":"+1 404 237 7013",
    "sg:postcode":"30305",
    "sg:province":"GA",
    "wof:name":"Elizabeth Kane Inc",
    "wof:placetype":"venue"
},
  "geometry": {"coordinates":[-84.383578,33.826776],"type":"Point"}
}