{
  "type": "Feature",
  "properties": {
    "iso:country":"US",
    "sg:address":"190 W Main St",
    "sg:city":"Canton",
    "sg:classifiers":[
        {
            "category":"Government",
            "subcategory":"Fire Station",
            "type":"Public Place"
        }
    ],
    "sg:phone":"+1 770 479 7287",
    "sg:postcode":"30114",
    "sg:province":"GA",
    "sg:tags":[
        "department"
    ],
    "wof:name":"Canton Fire Dept",
    "wof:placetype":"venue"
},
  "geometry": {"coordinates":[-84.492285,34.237037],"type":"Point"}
}