{
  "type": "Feature",
  "properties": {
    "iso:country":"US",
    "sg:address":"303 Birkdale Blvd",
    "sg:city":"Carrollton",
    "sg:classifiers":[
        {
            "category":"Real Estate",
            "subcategory":"Developer",
            "type":"Services"
        }
    ],
    "sg:phone":"+1 770 301 3798",
    "sg:postcode":"30116",
    "sg:province":"GA",
    "wof:name":"Joswick Development Inc",
    "wof:placetype":"venue"
},
  "geometry": {"coordinates":[-85.020927,33.57056],"type":"Point"}
}