{
  "type": "Feature",
  "properties": {
    "addr:full":"300 Bill Hart Rd Newnan GA 30265",
    "addr:housenumber":"300",
    "addr:postcode":"30265",
    "addr:street":"Bill Hart Rd",
    "iso:country":"US",
    "sg:address":"300 Bill Hart Rd",
    "sg:city":"Newnan",
    "sg:classifiers":[
        {
            "category":"Building & Trades",
            "subcategory":"Construction",
            "type":"Services"
        }
    ],
    "sg:phone":"+1 770 251 6743",
    "sg:postcode":"30265",
    "sg:province":"GA",
    "sg:tags":[
        "finishing",
        "wood"
    ],
    "wof:name":"Benefield Siding & Cornice",
    "wof:placetype":"venue"
},
  "geometry": {"coordinates":[-84.702583,33.343114],"type":"Point"}
}