{
  "type": "Feature",
  "properties": {
    "iso:country":"US",
    "sg:address":"2580 Laurel Ridge Dr",
    "sg:city":"Decatur",
    "sg:classifiers":[
        {
            "category":"Professional",
            "type":"Services"
        }
    ],
    "sg:phone":"+1 404 272 6742",
    "sg:postcode":"30033",
    "sg:province":"GA",
    "sg:tags":[
        "editorial"
    ],
    "wof:name":"Dan Williams",
    "wof:placetype":"venue"
},
  "geometry": {"coordinates":[-84.282025,33.816541],"type":"Point"}
}