{
  "type": "Feature",
  "properties": {
    "iso:country":"US",
    "sg:address":"3926 Glenwood Rd",
    "sg:city":"Decatur",
    "sg:classifiers":[
        {
            "category":"Organizations",
            "subcategory":"Religious Organization",
            "type":"Services"
        }
    ],
    "sg:phone":"+1 404 454 9915",
    "sg:postcode":"30032",
    "sg:province":"GA",
    "sg:tags":[
        "faith",
        "based",
        "church"
    ],
    "wof:name":"Cornerstone Of Faith",
    "wof:placetype":"venue"
},
  "geometry": {"coordinates":[-84.257581,33.738121],"type":"Point"}
}