{
  "type": "Feature",
  "properties": {
    "addr:full":"210 Central Ave Folkston GA 31537",
    "addr:housenumber":"210",
    "addr:postcode":"31537",
    "addr:street":"Central Ave",
    "iso:country":"US",
    "sg:address":"210 Central Ave",
    "sg:city":"Folkston",
    "sg:classifiers":[
        {
            "category":"Shopping",
            "subcategory":"Crafts & Fabrics",
            "type":"Retail Goods"
        },
        {
            "category":"Professional",
            "subcategory":"Art Services",
            "type":"Services"
        }
    ],
    "sg:phone":"+1 912 496 2280",
    "sg:postcode":"31537",
    "sg:province":"GA",
    "sg:tags":[
        "punching",
        "design",
        "embroidery"
    ],
    "sg:website":"http://www.firstcoastembroidery.com",
    "wof:name":"First Coast Embroidery",
    "wof:placetype":"venue"
},
  "geometry": {"coordinates":[-82.025278,30.854914],"type":"Point"}
}