{
  "type": "Feature",
  "properties": {
    "addr:full":"1750 Enterprise Way SE Ste 109 Marietta GA 30067",
    "addr:housenumber":"1750",
    "addr:postcode":"30067",
    "addr:street":"Enterprise Way Se Ste 109",
    "iso:country":"US",
    "sg:address":"1750 Enterprise Way SE Ste 109",
    "sg:city":"Marietta",
    "sg:classifiers":[
        {
            "category":"Home & Garden",
            "subcategory":"Carpets & Floor Coverings",
            "type":"Retail Goods"
        }
    ],
    "sg:phone":"+1 770 980 1234",
    "sg:postcode":"30067",
    "sg:province":"GA",
    "sg:tags":[
        "carpeting"
    ],
    "wof:name":"Romanoff Floor Covering Co",
    "wof:placetype":"venue"
},
  "geometry": {"coordinates":[-84.492302,33.913101],"type":"Point"}
}