{
  "type": "Feature",
  "properties": {
    "iso:country":"US",
    "sg:address":"1611 Austell Rd SE",
    "sg:city":"Marietta",
    "sg:classifiers":[
        {
            "category":"Food & Beverages",
            "subcategory":"Groceries & Convenience Stores",
            "type":"Retail Goods"
        }
    ],
    "sg:phone":"+1 770 423 1187",
    "sg:postcode":"30008",
    "sg:province":"GA",
    "wof:name":"Quik Trip",
    "wof:placetype":"venue"
},
  "geometry": {"coordinates":[-84.554029,33.914363],"type":"Point"}
}