{
  "type": "Feature",
  "properties": {
    "iso:country":"US",
    "sg:address":"1151 Mc Ree's Mill Rd",
    "sg:city":"Watkinsville",
    "sg:classifiers":[
        {
            "category":"Building & Trades",
            "subcategory":"Landscaping Services",
            "type":"Services"
        }
    ],
    "sg:phone":"+1 706 769 0621",
    "sg:postcode":"30677",
    "sg:province":"GA",
    "wof:name":"Horticulture Specialties Inc",
    "wof:placetype":"venue"
},
  "geometry": {"coordinates":[-83.336665,33.85519],"type":"Point"}
}