{
  "type": "Feature",
  "properties": {
    "addr:full":"8 Waverly Cir Newnan GA 30263",
    "addr:housenumber":"8",
    "addr:postcode":"30263",
    "addr:street":"Waverly Cir",
    "iso:country":"US",
    "sg:address":"8 Waverly Cir",
    "sg:city":"Newnan",
    "sg:classifiers":[
        {
            "category":"Shopping",
            "subcategory":"Beauty & Cosmetics",
            "type":"Retail Goods"
        }
    ],
    "sg:phone":"+1 770 251 3262",
    "sg:postcode":"30263",
    "sg:province":"GA",
    "sg:tags":[
        "merchandise"
    ],
    "wof:name":"Mary Kay Cosmetics",
    "wof:placetype":"venue"
},
  "geometry": {"coordinates":[-84.808896,33.36768],"type":"Point"}
}