{
  "type": "Feature",
  "properties": {
    "iso:country":"US",
    "sg:address":"6980 Northgreen Dr NE",
    "sg:city":"Atlanta",
    "sg:classifiers":[
        {
            "category":"Health Services",
            "subcategory":"Doctor",
            "type":"Services"
        }
    ],
    "sg:phone":"+1 770 673 0369",
    "sg:postcode":"30328",
    "sg:province":"GA",
    "sg:tags":[
        "medical"
    ],
    "wof:name":"Joseph L Micca MD",
    "wof:placetype":"venue"
},
  "geometry": {"coordinates":[-84.358985,33.949259],"type":"Point"}
}