{
  "type": "Feature",
  "properties": {
    "iso:country":"US",
    "sg:address":"1235 Arthur Ct",
    "sg:city":"Lawrenceville",
    "sg:classifiers":[
        {
            "category":"Banks & Credit Unions",
            "subcategory":"Bank",
            "type":"Services"
        }
    ],
    "sg:phone":"+1 770 237 3668",
    "sg:postcode":"30043",
    "sg:province":"GA",
    "sg:tags":[
        "mortgage"
    ],
    "wof:name":"Complete Mortgage Solutions",
    "wof:placetype":"venue"
},
  "geometry": {"coordinates":[-83.960696,34.00153],"type":"Point"}
}