{
  "type": "Feature",
  "properties": {
    "addr:full":"1196 Moreland Ave SE Atlanta GA 30316",
    "addr:housenumber":"1196",
    "addr:postcode":"30316",
    "addr:street":"Moreland Ave Se",
    "iso:country":"US",
    "sg:address":"1196 Moreland Ave SE",
    "sg:city":"Atlanta",
    "sg:classifiers":[
        {
            "category":"Autos & Motor Vehicles",
            "subcategory":"Automobile Sales",
            "type":"Retail Goods"
        }
    ],
    "sg:phone":"+1 404 622 5311",
    "sg:postcode":"30316",
    "sg:province":"GA",
    "sg:tags":[
        "car",
        "dealer"
    ],
    "wof:name":"Ken Red Auto Sales",
    "wof:placetype":"venue"
},
  "geometry": {"coordinates":[-84.34954,33.71951],"type":"Point"}
}