{
  "type": "Feature",
  "properties": {
    "iso:country":"US",
    "sg:address":"3393 Peachtree Rd NE Ste 3084",
    "sg:city":"Atlanta",
    "sg:classifiers":[
        {
            "category":"Shopping",
            "subcategory":"Clothing, Apparel, & Fashions",
            "type":"Retail Goods"
        }
    ],
    "sg:phone":"+1 404 816 8700",
    "sg:postcode":"30326",
    "sg:province":"GA",
    "sg:tags":[
        "apparel",
        "accessory",
        "clothing",
        "women's"
    ],
    "sg:website":"http://www.michaelkors.com",
    "wof:name":"Michael Kors",
    "wof:placetype":"venue"
},
  "geometry": {"coordinates":[-84.364468,33.8488],"type":"Point"}
}