{
  "type": "Feature",
  "properties": {
    "iso:country":"US",
    "sg:address":"1551 Asheforde Dr",
    "sg:city":"Marietta",
    "sg:classifiers":[
        {
            "category":"Recreation",
            "type":"Entertainment"
        }
    ],
    "sg:phone":"+1 770 552 8185",
    "sg:postcode":"30068",
    "sg:province":"GA",
    "sg:tags":[
        "club",
        "membership",
        "beach",
        "pool",
        "swimming"
    ],
    "wof:name":"Asheforde Swimming Pool",
    "wof:placetype":"venue"
},
  "geometry": {"coordinates":[-84.387001,33.986],"type":"Point"}
}