{
  "type": "Feature",
  "properties": {
    "addr:full":"825 Marathon Pkwy Lawrenceville GA 30045",
    "addr:housenumber":"825",
    "addr:postcode":"30045",
    "addr:street":"Marathon Pkwy",
    "iso:country":"US",
    "sg:address":"825 Marathon Pkwy",
    "sg:city":"Lawrenceville",
    "sg:classifiers":[
        {
            "category":"Professional",
            "subcategory":"Computer Services",
            "type":"Services"
        }
    ],
    "sg:phone":"+1 770 339 9560",
    "sg:postcode":"30045",
    "sg:province":"GA",
    "sg:tags":[
        "repair"
    ],
    "wof:name":"Southern Refurb Inc",
    "wof:placetype":"venue"
},
  "geometry": {"coordinates":[-84.04969800000001,33.958099],"type":"Point"}
}