{
  "type": "Feature",
  "properties": {
    "iso:country":"US",
    "sg:address":"1475 Hawthorne Way",
    "sg:city":"Atlanta",
    "sg:classifiers":[
        {
            "category":"Real Estate",
            "subcategory":"Real Estate Agent",
            "type":"Services"
        }
    ],
    "sg:phone":"+1 404 763 3000",
    "sg:postcode":"30344",
    "sg:province":"GA",
    "wof:name":"Keep On Truckin LLC",
    "wof:placetype":"venue"
},
  "geometry": {"coordinates":[-84.43582499999999,33.697935],"type":"Point"}
}