{
  "type": "Feature",
  "properties": {
    "addr:full":"4032 Kings Cswy Ellenwood GA 30294",
    "addr:housenumber":"4032",
    "addr:postcode":"30294",
    "addr:street":"Kings Cswy",
    "iso:country":"US",
    "sg:address":"4032 Kings Cswy",
    "sg:city":"Ellenwood",
    "sg:classifiers":[
        {
            "category":"Manufacturing",
            "subcategory":"Printing",
            "type":"Manufacturing & Wholesale Goods"
        }
    ],
    "sg:phone":"+1 404 272 7418",
    "sg:postcode":"30294",
    "sg:province":"GA",
    "sg:tags":[
        "magazines-distributors",
        "periodical"
    ],
    "wof:name":"Conscious Living",
    "wof:placetype":"venue"
},
  "geometry": {"coordinates":[-84.227153,33.661127],"type":"Point"}
}