{
  "type": "Feature",
  "properties": {
    "iso:country":"US",
    "sg:address":"1736 Langston Ave SW",
    "sg:city":"Atlanta",
    "sg:classifiers":[
        {
            "category":"Building & Trades",
            "subcategory":"Plumbing",
            "type":"Services"
        }
    ],
    "sg:phone":"+1 404 752 6233",
    "sg:postcode":"30310",
    "sg:province":"GA",
    "sg:tags":[
        "contractor"
    ],
    "wof:name":"Clark AC Inc",
    "wof:placetype":"venue"
},
  "geometry": {"coordinates":[-84.42204599999999,33.707958],"type":"Point"}
}