{
  "type": "Feature",
  "properties": {
    "iso:country":"US",
    "sg:address":"312 Oakridge Church Rd",
    "sg:city":"Tifton",
    "sg:classifiers":[
        {
            "category":"Transit Center",
            "subcategory":"Freight",
            "type":"Transportation"
        },
        {
            "category":"Building & Trades",
            "subcategory":"Construction",
            "type":"Services"
        }
    ],
    "sg:phone":"+1 229 388 5748",
    "sg:postcode":"31794",
    "sg:province":"GA",
    "sg:tags":[
        "fork",
        "trucks-industrial",
        "lift",
        "forklift",
        "truck"
    ],
    "sg:website":"http://www.dyna-lift.com",
    "wof:name":"Dyna-Lift Inc",
    "wof:placetype":"venue"
},
  "geometry": {"coordinates":[-83.493353,31.402766],"type":"Point"}
}