{
  "type": "Feature",
  "properties": {
    "iso:country":"US",
    "sg:address":"1550 Lexington Rd",
    "sg:city":"Athens",
    "sg:classifiers":[
        {
            "category":"Building & Trades",
            "subcategory":"Cleaning & Sanitation",
            "type":"Services"
        }
    ],
    "sg:phone":"+1 706 583 1844",
    "sg:postcode":"30605",
    "sg:province":"GA",
    "sg:tags":[
        "house"
    ],
    "wof:name":"Merry Maids Inc",
    "wof:placetype":"venue"
},
  "geometry": {"coordinates":[-83.351435,33.946519],"type":"Point"}
}