{
  "type": "Feature",
  "properties": {
    "addr:full":"1471 Richard Rd Decatur GA 30032",
    "addr:housenumber":"1471",
    "addr:postcode":"30032",
    "addr:street":"Richard Rd",
    "iso:country":"US",
    "sg:address":"1471 Richard Rd",
    "sg:city":"Decatur",
    "sg:classifiers":[
        {
            "category":"Taxi",
            "type":"Transportation"
        }
    ],
    "sg:phone":"+1 404 261 0647",
    "sg:postcode":"30032",
    "sg:province":"GA",
    "wof:name":"Lenox Yellow Cab",
    "wof:placetype":"venue"
},
  "geometry": {"coordinates":[-84.245003,33.760601],"type":"Point"}
}