{
  "type": "Feature",
  "properties": {
    "iso:country":"US",
    "sg:address":"3005 River Dr",
    "sg:city":"Savannah",
    "sg:classifiers":[
        {
            "category":"Professional",
            "subcategory":"Employment Agencies",
            "type":"Services"
        }
    ],
    "sg:phone":"+1 912 353 7773",
    "sg:postcode":"31404",
    "sg:province":"GA",
    "wof:name":"Qvs International",
    "wof:placetype":"venue"
},
  "geometry": {"coordinates":[-81.050111,32.027514],"type":"Point"}
}