{
  "type": "Feature",
  "properties": {
    "addr:full":"469 Tillman St Baxley GA 31555",
    "addr:housenumber":"469",
    "addr:postcode":"31555",
    "addr:street":"Tillman St",
    "iso:country":"US",
    "sg:address":"469 Tillman St",
    "sg:city":"Baxley",
    "sg:classifiers":[
        {
            "category":"Manufacturing",
            "subcategory":"Lumber",
            "type":"Manufacturing & Wholesale Goods"
        }
    ],
    "sg:phone":"+1 912 367 2241",
    "sg:postcode":"31555",
    "sg:province":"GA",
    "sg:tags":[
        "forester"
    ],
    "wof:name":"TLT Forestry",
    "wof:placetype":"venue"
},
  "geometry": {"coordinates":[-82.026584,31.661096],"type":"Point"}
}