{
  "type": "Feature",
  "properties": {
    "addr:full":"225 Deer Trl Fayetteville GA 30214",
    "addr:housenumber":"225",
    "addr:postcode":"30214",
    "addr:street":"Deer Trl",
    "iso:country":"US",
    "sg:address":"225 Deer Trl",
    "sg:city":"Fayetteville",
    "sg:classifiers":[
        {
            "category":"Recreation",
            "subcategory":"Arcade",
            "type":"Entertainment"
        }
    ],
    "sg:phone":"+1 770 719 2268",
    "sg:postcode":"30214",
    "sg:province":"GA",
    "sg:tags":[
        "device",
        "operator",
        "amusement"
    ],
    "wof:name":"Gregorys Toy Chest",
    "wof:placetype":"venue"
},
  "geometry": {"coordinates":[-84.441365,33.468071],"type":"Point"}
}