{
  "type": "Feature",
  "properties": {
    "iso:country":"US",
    "sg:address":"4304 Oak Walk N",
    "sg:city":"Cumming",
    "sg:classifiers":[
        {
            "category":"Shopping",
            "type":"Retail Goods"
        }
    ],
    "sg:phone":"+1 770 784 0609",
    "sg:postcode":"30041",
    "sg:province":"GA",
    "sg:tags":[
        "merchandise"
    ],
    "wof:name":"Sharp Copier Services",
    "wof:placetype":"venue"
},
  "geometry": {"coordinates":[-84.112227,34.179789],"type":"Point"}
}