{
  "type": "Feature",
  "properties": {
    "iso:country":"US",
    "sg:address":"1715 Lake Lucerne Rd SW",
    "sg:city":"Lilburn",
    "sg:classifiers":[
        {
            "category":"Building & Trades",
            "subcategory":"Construction",
            "type":"Services"
        }
    ],
    "sg:phone":"+1 770 978 8874",
    "sg:postcode":"30047",
    "sg:province":"GA",
    "sg:tags":[
        "retaining",
        "wall"
    ],
    "wof:name":"Frh Tie Walls Inc",
    "wof:placetype":"venue"
},
  "geometry": {"coordinates":[-84.094199,33.839202],"type":"Point"}
}