{
  "type": "Feature",
  "properties": {
    "iso:country":"US",
    "sg:address":"5354 Cleveland Hwy",
    "sg:city":"Clermont",
    "sg:classifiers":[
        {
            "category":"Shopping",
            "subcategory":"Florist",
            "type":"Retail Goods"
        }
    ],
    "sg:phone":"+1 770 983 0590",
    "sg:postcode":"30527",
    "sg:province":"GA",
    "wof:name":"Flowers By Deanna",
    "wof:placetype":"venue"
},
  "geometry": {"coordinates":[-83.802235,34.4521],"type":"Point"}
}