{
  "type": "Feature",
  "properties": {
    "iso:country":"US",
    "sg:address":"2727 Timber Ln",
    "sg:city":"Blairsville",
    "sg:classifiers":[
        {
            "category":"Building & Trades",
            "subcategory":"Construction",
            "type":"Services"
        }
    ],
    "sg:phone":"+1 706 745 5594",
    "sg:postcode":"30512",
    "sg:province":"GA",
    "sg:tags":[
        "house"
    ],
    "wof:name":"Rutherford Builders",
    "wof:placetype":"venue"
},
  "geometry": {"coordinates":[-83.898826,34.835721],"type":"Point"}
}