{
  "type": "Feature",
  "properties": {
    "iso:country":"US",
    "sg:address":"2615 Fox Hall Ln N",
    "sg:city":"Atlanta",
    "sg:classifiers":[
        {
            "category":"Professional",
            "subcategory":"Management & Consulting",
            "type":"Services"
        }
    ],
    "sg:phone":"+1 770 907 0760",
    "sg:postcode":"30349",
    "sg:province":"GA",
    "wof:name":"Jada Transport Inc",
    "wof:placetype":"venue"
},
  "geometry": {"coordinates":[-84.475121,33.571681],"type":"Point"}
}