{
  "type": "Feature",
  "properties": {
    "addr:full":"2910 Pio Nono Ave Macon GA 31206",
    "addr:housenumber":"2910",
    "addr:postcode":"31206",
    "addr:street":"Pio Nono Ave",
    "iso:country":"US",
    "sg:address":"2910 Pio Nono Ave",
    "sg:city":"Macon",
    "sg:classifiers":[
        {
            "category":"Autos & Motor Vehicles",
            "subcategory":"Automobile Sales",
            "type":"Retail Goods"
        }
    ],
    "sg:phone":"+1 478 781 8881",
    "sg:postcode":"31206",
    "sg:province":"GA",
    "sg:tags":[
        "car",
        "dealer"
    ],
    "wof:name":"City Wide Auto Sales",
    "wof:placetype":"venue"
},
  "geometry": {"coordinates":[-83.66289500000001,32.810114],"type":"Point"}
}