{
  "type": "Feature",
  "properties": {
    "addr:full":"5600 United Dr SE Smyrna GA 30082",
    "addr:postcode":"5600;30082",
    "addr:street":"United Dr Se",
    "iso:country":"US",
    "sg:address":"5600 United Dr SE",
    "sg:city":"Smyrna",
    "sg:classifiers":[
        {
            "category":"Shopping",
            "subcategory":"Computers & Home Electronics",
            "type":"Retail Goods"
        }
    ],
    "sg:phone":"+1 770 444 0160",
    "sg:postcode":"30082",
    "sg:province":"GA",
    "sg:tags":[
        "renting",
        "equipment",
        "leasing"
    ],
    "wof:name":"Comdisco",
    "wof:placetype":"venue"
},
  "geometry": {"coordinates":[-84.523982,33.841004],"type":"Point"}
}