{
  "type": "Feature",
  "properties": {
    "addr:full":"402 GA Hwy 247 Ste 1100 Bonaire GA 31005",
    "addr:housenumber":"402",
    "addr:postcode":"31005",
    "addr:street":"Ga Hwy 247 Ste 1100",
    "iso:country":"US",
    "sg:address":"402 GA Hwy 247 Ste 1100",
    "sg:city":"Bonaire",
    "sg:classifiers":[
        {
            "category":"Building & Trades",
            "subcategory":"Cleaning & Sanitation",
            "type":"Services"
        },
        {
            "category":"Building & Trades",
            "subcategory":"Construction",
            "type":"Services"
        }
    ],
    "sg:phone":"+1 478 333 6677",
    "sg:postcode":"31005",
    "sg:province":"GA",
    "sg:tags":[
        "cleaner",
        "pool",
        "contractor"
    ],
    "sg:website":"www.poolsbyemerson.com/",
    "wof:name":"Emerson's Pool & Spa",
    "wof:placetype":"venue"
},
  "geometry": {"coordinates":[-83.593746,32.567506],"type":"Point"}
}