{
  "type": "Feature",
  "properties": {
    "addr:full":"831 Mountaintown Rd Ellijay GA 30540",
    "addr:housenumber":"831",
    "addr:postcode":"30540",
    "addr:street":"Mountaintown Rd",
    "iso:country":"US",
    "sg:address":"831 Mountaintown Rd",
    "sg:city":"Ellijay",
    "sg:classifiers":[
        {
            "category":"Travel",
            "subcategory":"Campground",
            "type":"Entertainment"
        }
    ],
    "sg:phone":"+1 706 635 1999",
    "sg:postcode":"30540",
    "sg:province":"GA",
    "sg:tags":[
        "trailer"
    ],
    "wof:name":"North Orchard Mobile Home Park",
    "wof:placetype":"venue"
},
  "geometry": {"coordinates":[-84.560309,34.75463],"type":"Point"}
}