{
  "type": "Feature",
  "properties": {
    "addr:full":"1014 11th Ave Augusta GA 30901",
    "addr:housenumber":"1014",
    "addr:postcode":"30901",
    "addr:street":"11Th Ave",
    "iso:country":"US",
    "sg:address":"1014 11th Ave",
    "sg:city":"Augusta",
    "sg:classifiers":[
        {
            "category":"Government",
            "subcategory":"Office",
            "type":"Public Place"
        }
    ],
    "sg:phone":"+1 706 722 1951",
    "sg:postcode":"30901",
    "sg:province":"GA",
    "sg:tags":[
        "village"
    ],
    "wof:name":"City Of Augusta",
    "wof:placetype":"venue"
},
  "geometry": {"coordinates":[-81.99555100000001,33.448672],"type":"Point"}
}