{
  "type": "Feature",
  "properties": {
    "addr:full":"1100 Hillcrest Pkwy # D Dublin GA 31021",
    "addr:housenumber":"1100",
    "addr:postcode":"31021",
    "addr:street":"Hillcrest Pkwy # D",
    "iso:country":"US",
    "sg:address":"1100 Hillcrest Pkwy # D",
    "sg:city":"Dublin",
    "sg:phone":"+1 478 272 5388",
    "sg:postcode":"31021",
    "sg:province":"GA",
    "sg:website":"http://www.huddlehouse.com/",
    "wof:name":"Huddle House",
    "wof:placetype":"venue"
},
  "geometry": {"coordinates":[-82.928301,32.547947],"type":"Point"}
}