{
  "type": "Feature",
  "properties": {
    "addr:full":"410 Burdett Ridge Ct College Park GA 30349",
    "addr:housenumber":"410",
    "addr:postcode":"30349",
    "addr:street":"Burdett Ridge Ct",
    "iso:country":"US",
    "sg:address":"410 Burdett Ridge Ct",
    "sg:city":"College Park",
    "sg:classifiers":[
        {
            "category":"Manufacturing",
            "subcategory":"Printing",
            "type":"Manufacturing & Wholesale Goods"
        }
    ],
    "sg:phone":"+1 770 716 5482",
    "sg:postcode":"30349",
    "sg:province":"GA",
    "sg:tags":[
        "publisher"
    ],
    "wof:name":"Cloven Tongues Of Fire",
    "wof:placetype":"venue"
},
  "geometry": {"coordinates":[-84.481673,33.596934],"type":"Point"}
}