{
  "type": "Feature",
  "properties": {
    "addr:full":"6691 Tribble St Lithonia GA 30058",
    "addr:housenumber":"6691",
    "addr:postcode":"30058",
    "addr:street":"Tribble St",
    "iso:country":"US",
    "sg:address":"6691 Tribble St",
    "sg:city":"Lithonia",
    "sg:classifiers":[
        {
            "category":"Building & Trades",
            "subcategory":"Cleaning & Sanitation",
            "type":"Services"
        },
        {
            "category":"Wholesale",
            "subcategory":"Construction Materials",
            "type":"Manufacturing & Wholesale Goods"
        },
        {
            "category":"Home & Garden",
            "subcategory":"Building Materials",
            "type":"Retail Goods"
        },
        {
            "category":"Industrial Area",
            "type":"Public Place"
        }
    ],
    "sg:phone":"+1 770 482 5220",
    "sg:postcode":"30058",
    "sg:province":"GA",
    "sg:tags":[
        "coatings-protective",
        "floors-industrial",
        "water",
        "sandblasting",
        "treatment",
        "waste"
    ],
    "sg:website":"http://www.mechanicaljobbers.com",
    "wof:name":"Mechanical Jobbers Sandblasting & Coatings",
    "wof:placetype":"venue"
},
  "geometry": {"coordinates":[-84.11573799999999,33.718689],"type":"Point"}
}