{
  "type": "Feature",
  "properties": {
    "addr:full":"3200 Industrial Way SW Snellville GA 30039",
    "addr:housenumber":"3200",
    "addr:postcode":"30039",
    "addr:street":"Industrial Way Sw",
    "iso:country":"US",
    "sg:address":"3200 Industrial Way SW",
    "sg:city":"Snellville",
    "sg:classifiers":[
        {
            "category":"Wholesale",
            "subcategory":"Metals & Minerals",
            "type":"Manufacturing & Wholesale Goods"
        }
    ],
    "sg:phone":"+1 770 972 7315",
    "sg:postcode":"30039",
    "sg:province":"GA",
    "sg:tags":[
        "steel",
        "product"
    ],
    "wof:name":"Metro Steel Inc",
    "wof:placetype":"venue"
},
  "geometry": {"coordinates":[-84.007244,33.829607],"type":"Point"}
}