{
  "type": "Feature",
  "properties": {
    "iso:country":"US",
    "sg:address":"564 Peachtree Pkwy",
    "sg:city":"Cumming",
    "sg:classifiers":[
        {
            "category":"Social Services",
            "type":"Services"
        }
    ],
    "sg:phone":"+1 770 888 7099",
    "sg:postcode":"30041",
    "sg:province":"GA",
    "wof:name":"Psychological & Eductl Cons",
    "wof:placetype":"venue"
},
  "geometry": {"coordinates":[-84.173903,34.150993],"type":"Point"}
}