{
  "type": "Feature",
  "properties": {
    "addr:full":"170 Powder Creek Dr Dallas GA 30157",
    "addr:housenumber":"170",
    "addr:postcode":"30157",
    "addr:street":"Powder Creek Dr",
    "iso:country":"US",
    "sg:address":"170 Powder Creek Dr",
    "sg:city":"Dallas",
    "sg:classifiers":[
        {
            "category":"Shopping",
            "subcategory":"Tobacco",
            "type":"Retail Goods"
        }
    ],
    "sg:phone":"+1 770 445 4467",
    "sg:postcode":"30157",
    "sg:province":"GA",
    "sg:tags":[
        "product"
    ],
    "wof:name":"Dougs Cigars Unlimited",
    "wof:placetype":"venue"
},
  "geometry": {"coordinates":[-84.746545,33.916973],"type":"Point"}
}