{
  "type": "Feature",
  "properties": {
    "iso:country":"US",
    "sg:address":"1022 White Fox Run",
    "sg:city":"Lawrenceville",
    "sg:classifiers":[
        {
            "category":"Real Estate",
            "subcategory":"Real Estate Services",
            "type":"Services"
        },
        {
            "category":"Real Estate",
            "subcategory":"Real Estate Agent",
            "type":"Services"
        }
    ],
    "sg:phone":"+1 404 399 3200",
    "sg:postcode":"30045",
    "sg:province":"GA",
    "sg:tags":[
        "buyer",
        "broker"
    ],
    "wof:name":"Southern House Realty",
    "wof:placetype":"venue"
},
  "geometry": {"coordinates":[-83.99569099999999,33.913919],"type":"Point"}
}