{
  "type": "Feature",
  "properties": {
    "addr:full":"3803 Armour Ave Columbus GA 31904",
    "addr:housenumber":"3803",
    "addr:postcode":"31904",
    "addr:street":"Armour Ave",
    "iso:country":"US",
    "sg:address":"3803 Armour Ave",
    "sg:city":"Columbus",
    "sg:classifiers":[
        {
            "category":"Utilities",
            "subcategory":"Refuse",
            "type":"Services"
        }
    ],
    "sg:phone":"+1 706 320 9709",
    "sg:postcode":"31904",
    "sg:province":"GA",
    "sg:tags":[
        "system"
    ],
    "wof:name":"Tarver Tire Recycling",
    "wof:placetype":"venue"
},
  "geometry": {"coordinates":[-84.950287,32.498831],"type":"Point"}
}