{
  "type": "Feature",
  "properties": {
    "addr:full":"1180 Upper Hembree Rd Roswell GA 30076",
    "addr:housenumber":"1180",
    "addr:postcode":"30076",
    "addr:street":"Upper Hembree Rd",
    "iso:country":"US",
    "sg:address":"1180 Upper Hembree Rd",
    "sg:city":"Roswell",
    "sg:classifiers":[
        {
            "category":"Food & Beverages",
            "subcategory":"Groceries & Convenience Stores",
            "type":"Retail Goods"
        }
    ],
    "sg:phone":"+1 770 751 3320",
    "sg:postcode":"30076",
    "sg:province":"GA",
    "wof:name":"Harry's Manufacturing Prepared Foods",
    "wof:placetype":"venue"
},
  "geometry": {"coordinates":[-84.326103,34.068001],"type":"Point"}
}