{
  "type": "Feature",
  "properties": {
    "iso:country":"US",
    "sg:address":"590 Walthour Rd",
    "sg:city":"Savannah",
    "sg:classifiers":[
        {
            "category":"Organizations",
            "subcategory":"Religious Organization",
            "type":"Services"
        }
    ],
    "sg:phone":"+1 912 897 5725",
    "sg:postcode":"31410",
    "sg:province":"GA",
    "wof:name":"St Francis Isl Episcpl Chur",
    "wof:placetype":"venue"
},
  "geometry": {"coordinates":[-80.958996,32.011983],"type":"Point"}
}