{
  "type": "Feature",
  "properties": {
    "addr:full":"3849 Oakview Dr Powder Springs GA 30127",
    "addr:housenumber":"3849",
    "addr:postcode":"30127",
    "addr:street":"Oakview Dr",
    "iso:country":"US",
    "sg:address":"3849 Oakview Dr",
    "sg:city":"Powder Springs",
    "sg:classifiers":[
        {
            "category":"Professional",
            "type":"Services"
        }
    ],
    "sg:phone":"+1 770 222 1483",
    "sg:postcode":"30127",
    "sg:province":"GA",
    "wof:name":"Iron Mountain Development",
    "wof:placetype":"venue"
},
  "geometry": {"coordinates":[-84.683378,33.859903],"type":"Point"}
}