{
  "type": "Feature",
  "properties": {
    "addr:full":"421 N Hairston Rd Stone Mountain GA 30083",
    "addr:housenumber":"421",
    "addr:postcode":"30083",
    "addr:street":"N Hairston Rd",
    "iso:country":"US",
    "sg:address":"421 N Hairston Rd",
    "sg:city":"Stone Mountain",
    "sg:classifiers":[
        {
            "category":"Building & Trades",
            "subcategory":"Construction",
            "type":"Services"
        }
    ],
    "sg:phone":"+1 404 292 6622",
    "sg:postcode":"30083",
    "sg:province":"GA",
    "sg:tags":[
        "painting",
        "contractor"
    ],
    "wof:name":"Ni-Tam Inc",
    "wof:placetype":"venue"
},
  "geometry": {"coordinates":[-84.19523599999999,33.789927],"type":"Point"}
}