{
  "type": "Feature",
  "properties": {
    "iso:country":"US",
    "sg:address":"2404 Rat Kinney Rd",
    "sg:city":"Statham",
    "sg:classifiers":[
        {
            "category":"Organizations",
            "subcategory":"Religious Organization",
            "type":"Services"
        }
    ],
    "sg:phone":"+1 770 725 5010",
    "sg:postcode":"30666",
    "sg:province":"GA",
    "sg:tags":[
        "church"
    ],
    "wof:name":"Greater Barbers Creek Church",
    "wof:placetype":"venue"
},
  "geometry": {"coordinates":[-83.557844,33.976486],"type":"Point"}
}