{
  "type": "Feature",
  "properties": {
    "iso:country":"US",
    "sg:address":"401 College St",
    "sg:city":"Nashville",
    "sg:classifiers":[
        {
            "category":"Food & Beverages",
            "subcategory":"Groceries & Convenience Stores",
            "type":"Retail Goods"
        }
    ],
    "sg:phone":"+1 229 686 7371",
    "sg:postcode":"31639",
    "sg:province":"GA",
    "wof:name":"Singletary Grocery Office",
    "wof:placetype":"venue"
},
  "geometry": {"coordinates":[-83.251419,31.203011],"type":"Point"}
}