{
  "type": "Feature",
  "properties": {
    "iso:country":"US",
    "sg:address":"645 Ernest W Barrett Pkwy",
    "sg:city":"Kennesaw",
    "sg:classifiers":[
        {
            "category":"Professional",
            "subcategory":"Business Services",
            "type":"Services"
        },
        {
            "category":"Organizations",
            "subcategory":"Community Association",
            "type":"Services"
        }
    ],
    "sg:phone":"+1 770 427 0299",
    "sg:postcode":"30144",
    "sg:province":"GA",
    "sg:tags":[
        "club"
    ],
    "wof:name":"Club Demonstration Services",
    "wof:placetype":"venue"
},
  "geometry": {"coordinates":[-84.568254,34.009332],"type":"Point"}
}