{
  "type": "Feature",
  "properties": {
    "iso:country":"US",
    "sg:address":"918 S 1st St",
    "sg:city":"Jesup",
    "sg:classifiers":[
        {
            "category":"Wholesale",
            "subcategory":"Medical Equipment & Supplies",
            "type":"Manufacturing & Wholesale Goods"
        }
    ],
    "sg:phone":"+1 912 427 6600",
    "sg:postcode":"31545",
    "sg:province":"GA",
    "wof:name":"Jones Medical Equipment",
    "wof:placetype":"venue"
},
  "geometry": {"coordinates":[-81.892321,31.601979],"type":"Point"}
}