{
  "type": "Feature",
  "properties": {
    "iso:country":"US",
    "sg:address":"95 Highlands Forest Ln",
    "sg:city":"Oxford",
    "sg:classifiers":[
        {
            "category":"Building & Trades",
            "subcategory":"Construction",
            "type":"Services"
        }
    ],
    "sg:phone":"+1 770 786 1113",
    "sg:postcode":"30054",
    "sg:province":"GA",
    "sg:tags":[
        "house"
    ],
    "wof:name":"Paul Williams Homes",
    "wof:placetype":"venue"
},
  "geometry": {"coordinates":[-83.91572499999999,33.68355],"type":"Point"}
}