{
  "type": "Feature",
  "properties": {
    "addr:full":"1942 Teeterville Rd Nashville GA 31639",
    "addr:housenumber":"1942",
    "addr:postcode":"31639",
    "addr:street":"Teeterville Rd",
    "iso:country":"US",
    "sg:address":"1942 Teeterville Rd",
    "sg:city":"Nashville",
    "sg:classifiers":[
        {
            "category":"Building & Trades",
            "subcategory":"Construction",
            "type":"Services"
        }
    ],
    "sg:phone":"+1 229 686 9319",
    "sg:postcode":"31639",
    "sg:province":"GA",
    "sg:tags":[
        "wallcoverings-installation",
        "wallpaper",
        "painting",
        "contractor"
    ],
    "wof:name":"Smith Painting And Repair",
    "wof:placetype":"venue"
},
  "geometry": {"coordinates":[-83.17021699999999,31.17412],"type":"Point"}
}