{
  "type": "Feature",
  "properties": {
    "iso:country":"US",
    "sg:address":"970 Cedartown Hwy",
    "sg:city":"Rockmart",
    "sg:classifiers":[
        {
            "category":"Professional",
            "subcategory":"Accounting & Tax Preparation",
            "type":"Services"
        }
    ],
    "sg:phone":"+1 678 757 9888",
    "sg:postcode":"30153",
    "sg:province":"GA",
    "sg:tags":[
        "return",
        "preparation-business"
    ],
    "wof:name":"Jay Pearl Tax Service",
    "wof:placetype":"venue"
},
  "geometry": {"coordinates":[-85.06531,34.005391],"type":"Point"}
}