{
  "type": "Feature",
  "properties": {
    "addr:full":"1022 Greenbriar Cir Decatur GA 30033",
    "addr:housenumber":"1022",
    "addr:postcode":"30033",
    "addr:street":"Greenbriar Cir",
    "iso:country":"US",
    "sg:address":"1022 Greenbriar Cir",
    "sg:city":"Decatur",
    "sg:classifiers":[
        {
            "category":"Professional",
            "subcategory":"Art Services",
            "type":"Services"
        }
    ],
    "sg:phone":"+1 404 294 8398",
    "sg:postcode":"30033",
    "sg:province":"GA",
    "sg:tags":[
        "commercial",
        "design"
    ],
    "wof:name":"Poplar Designs",
    "wof:placetype":"venue"
},
  "geometry": {"coordinates":[-84.26284699999999,33.807951],"type":"Point"}
}