{
  "type": "Feature",
  "properties": {
    "iso:country":"US",
    "sg:address":"5455 Buford Hwy NE 202A",
    "sg:city":"Atlanta",
    "sg:classifiers":[
        {
            "category":"Real Estate",
            "subcategory":"Real Estate Services",
            "type":"Services"
        },
        {
            "category":"Real Estate",
            "subcategory":"Real Estate Agent",
            "type":"Services"
        }
    ],
    "sg:phone":"+1 770 458 2700",
    "sg:postcode":"30340",
    "sg:province":"GA",
    "sg:tags":[
        "buyer",
        "management",
        "broker"
    ],
    "wof:name":"S B A Realty Group Inc",
    "wof:placetype":"venue"
},
  "geometry": {"coordinates":[-84.276554,33.900902],"type":"Point"}
}