{
  "type": "Feature",
  "properties": {
    "iso:country":"US",
    "sg:address":"103 Gunn Rd Ste B",
    "sg:city":"Centerville",
    "sg:classifiers":[
        {
            "category":"Restaurant",
            "type":"Food & Drink"
        }
    ],
    "sg:phone":"+1 478 953 2200",
    "sg:postcode":"31028",
    "sg:province":"GA",
    "sg:tags":[
        "pizza"
    ],
    "sg:website":"www.meldinos.com",
    "wof:name":"Meldino's",
    "wof:placetype":"venue"
},
  "geometry": {"coordinates":[-83.687136,32.623478],"type":"Point"}
}