{
  "type": "Feature",
  "properties": {
    "addr:full":"709 Slew Ave Lawrenceville GA 30043",
    "addr:housenumber":"709",
    "addr:postcode":"30043",
    "addr:street":"Slew Ave",
    "iso:country":"US",
    "sg:address":"709 Slew Ave",
    "sg:city":"Lawrenceville",
    "sg:classifiers":[
        {
            "category":"Building & Trades",
            "subcategory":"Electrical",
            "type":"Services"
        }
    ],
    "sg:phone":"+1 770 822 0470",
    "sg:postcode":"30043",
    "sg:province":"GA",
    "sg:tags":[
        "electric",
        "contractor"
    ],
    "wof:name":"Jordan Electric",
    "wof:placetype":"venue"
},
  "geometry": {"coordinates":[-84.00230999999999,34.030157],"type":"Point"}
}