{
  "type": "Feature",
  "properties": {
    "iso:country":"US",
    "sg:address":"1900 Wesleyan Dr Apt 1101",
    "sg:city":"Macon",
    "sg:classifiers":[
        {
            "category":"Banks & Credit Unions",
            "subcategory":"Bank",
            "type":"Services"
        }
    ],
    "sg:phone":"+1 478 390 2066",
    "sg:postcode":"31210",
    "sg:province":"GA",
    "wof:name":"Business Credit Concepts",
    "wof:placetype":"venue"
},
  "geometry": {"coordinates":[-83.71669,32.93372],"type":"Point"}
}