{
  "type": "Feature",
  "properties": {
    "addr:full":"400 Pio Nono Ave Macon GA 31204",
    "addr:postcode":"31204",
    "addr:street":"Pio Nono Ave",
    "iso:country":"US",
    "sg:address":"400 Pio Nono Ave",
    "sg:city":"Macon",
    "sg:classifiers":[
        {
            "category":"Personal",
            "subcategory":"Beauty Salon",
            "type":"Services"
        }
    ],
    "sg:phone":"+1 478 742 7533",
    "sg:postcode":"31204",
    "sg:province":"GA",
    "sg:tags":[
        "shop"
    ],
    "wof:name":"Urembo Hair Salon",
    "wof:placetype":"venue"
},
  "geometry": {"coordinates":[-83.662386,32.841901],"type":"Point"}
}