{
  "type": "Feature",
  "properties": {
    "iso:country":"US",
    "sg:address":"514 Lucile St",
    "sg:city":"Griffin",
    "sg:classifiers":[
        {
            "category":"Personal",
            "subcategory":"Beauty Salon",
            "type":"Services"
        }
    ],
    "sg:phone":"+1 770 233 8912",
    "sg:postcode":"30223",
    "sg:province":"GA",
    "sg:tags":[
        "shop"
    ],
    "wof:name":"World Class Cuts",
    "wof:placetype":"venue"
},
  "geometry": {"coordinates":[-84.256418,33.256486],"type":"Point"}
}