{
  "type": "Feature",
  "properties": {
    "iso:country":"US",
    "sg:address":"906 Drayton St",
    "sg:city":"Savannah",
    "sg:classifiers":[
        {
            "category":"Health Services",
            "subcategory":"Doctor",
            "type":"Services"
        }
    ],
    "sg:phone":"+1 912 961 5758",
    "sg:postcode":"31401",
    "sg:province":"GA",
    "sg:tags":[
        "physician",
        "surgeon"
    ],
    "wof:name":"Sandra Chapkowski MD",
    "wof:placetype":"venue"
},
  "geometry": {"coordinates":[-81.095735,32.065362],"type":"Point"}
}