{
  "type": "Feature",
  "properties": {
    "iso:country":"US",
    "sg:address":"290 Grayson Hwy",
    "sg:city":"Lawrenceville",
    "sg:classifiers":[
        {
            "category":"Fast Food",
            "type":"Food & Drink"
        }
    ],
    "sg:phone":"+1 770 962 2502",
    "sg:postcode":"30046",
    "sg:province":"GA",
    "sg:tags":[
        "chicken",
        "wing"
    ],
    "wof:name":"Mrs Winner's Chicken & Biscuits",
    "wof:placetype":"venue"
},
  "geometry": {"coordinates":[-83.9853,33.945907],"type":"Point"}
}