{
  "type": "Feature",
  "properties": {
    "addr:full":"115 Sanders-Davis Rd Newnan GA 30263",
    "addr:housenumber":"115",
    "addr:postcode":"30263",
    "addr:street":"Sanders-Davis Rd",
    "iso:country":"US",
    "sg:address":"115 Sanders-Davis Rd",
    "sg:city":"Newnan",
    "sg:classifiers":[
        {
            "category":"Building & Trades",
            "subcategory":"Construction",
            "type":"Services"
        }
    ],
    "sg:phone":"+1 770 251 8983",
    "sg:postcode":"30263",
    "sg:province":"GA",
    "sg:tags":[
        "clearing",
        "land",
        "leveling"
    ],
    "wof:name":"Rustin's Bobcat Svc",
    "wof:placetype":"venue"
},
  "geometry": {"coordinates":[-84.919372,33.351786],"type":"Point"}
}