{
  "type": "Feature",
  "properties": {
    "addr:full":"5157 Patriot Dr Stone Mountain GA 30087",
    "addr:housenumber":"5157",
    "addr:postcode":"30087",
    "addr:street":"Patriot Dr",
    "iso:country":"US",
    "sg:address":"5157 Patriot Dr",
    "sg:city":"Stone Mountain",
    "sg:classifiers":[
        {
            "category":"Health Services",
            "subcategory":"Doctor",
            "type":"Services"
        }
    ],
    "sg:phone":"+1 770 621 0833",
    "sg:postcode":"30087",
    "sg:province":"GA",
    "sg:tags":[
        "osteopathic"
    ],
    "wof:name":"Paula M Gregory Do Inc",
    "wof:placetype":"venue"
},
  "geometry": {"coordinates":[-84.17818200000001,33.844463],"type":"Point"}
}