{
  "type": "Feature",
  "properties": {
    "iso:country":"US",
    "sg:address":"3435 Breckinridge Blvd",
    "sg:city":"Duluth",
    "sg:classifiers":[
        {
            "category":"Retail",
            "subcategory":"Portrait Studio",
            "type":"Services"
        }
    ],
    "sg:phone":"+1 770 849 0555",
    "sg:postcode":"30096",
    "sg:province":"GA",
    "sg:tags":[
        "photography",
        "store"
    ],
    "wof:name":"Camera Repair Japan",
    "wof:placetype":"venue"
},
  "geometry": {"coordinates":[-84.123001,33.952499],"type":"Point"}
}