{
  "type": "Feature",
  "properties": {
    "iso:country":"US",
    "sg:address":"5343 Highway 20 S",
    "sg:city":"Covington",
    "sg:classifiers":[
        {
            "category":"Autos & Motor Vehicles",
            "subcategory":"Fuel & Gas Station",
            "type":"Retail Goods"
        }
    ],
    "sg:phone":"+1 678 625 4200",
    "sg:postcode":"30016",
    "sg:province":"GA",
    "wof:name":"B P Magnet",
    "wof:placetype":"venue"
},
  "geometry": {"coordinates":[-84.01676999999999,33.548064],"type":"Point"}
}