{
  "type": "Feature",
  "properties": {
    "iso:country":"US",
    "sg:address":"4836 Miller Rd",
    "sg:city":"Columbus",
    "sg:phone":"+1 706 563 3623",
    "sg:postcode":"31909",
    "sg:province":"GA",
    "sg:website":"http://www.unitedfencecolumbus.com",
    "wof:name":"United Fence",
    "wof:placetype":"venue"
},
  "geometry": {"coordinates":[-84.90901700000001,32.522831],"type":"Point"}
}