{
  "type": "Feature",
  "properties": {
    "iso:country":"US",
    "sg:address":"2860 Interlaken Dr",
    "sg:city":"Marietta",
    "sg:classifiers":[
        {
            "category":"Autos & Motor Vehicles",
            "subcategory":"Auto Supplies",
            "type":"Retail Goods"
        }
    ],
    "sg:phone":"+1 770 649 1185",
    "sg:postcode":"30062",
    "sg:province":"GA",
    "sg:tags":[
        "tire"
    ],
    "wof:name":"Goodyear Mileage Sales Lease",
    "wof:placetype":"venue"
},
  "geometry": {"coordinates":[-84.427393,34.018005],"type":"Point"}
}