{
  "type": "Feature",
  "properties": {
    "addr:full":"1876 Hedge Brooke Way NW Acworth GA 30101",
    "addr:housenumber":"1876",
    "addr:postcode":"30101",
    "addr:street":"Hedge Brooke Way Nw",
    "iso:country":"US",
    "sg:address":"1876 Hedge Brooke Way NW",
    "sg:city":"Acworth",
    "sg:classifiers":[
        {
            "category":"Manufacturing",
            "subcategory":"Chemicals & Compounds",
            "type":"Manufacturing & Wholesale Goods"
        }
    ],
    "sg:phone":"+1 770 792 8943",
    "sg:postcode":"30101",
    "sg:province":"GA",
    "sg:tags":[
        "explosive",
        "mfg"
    ],
    "wof:name":"Kidde Technologies Inc",
    "wof:placetype":"venue"
},
  "geometry": {"coordinates":[-84.712402,34.002625],"type":"Point"}
}