{
  "type": "Feature",
  "properties": {
    "addr:full":"4984 Kiowa Ct SW Lilburn GA 30047",
    "addr:housenumber":"4984",
    "addr:postcode":"30047",
    "addr:street":"Kiowa Ct Sw",
    "iso:country":"US",
    "sg:address":"4984 Kiowa Ct SW",
    "sg:city":"Lilburn",
    "sg:classifiers":[
        {
            "category":"Building & Trades",
            "subcategory":"Cleaning & Sanitation",
            "type":"Services"
        }
    ],
    "sg:phone":"+1 770 879 1589",
    "sg:postcode":"30047",
    "sg:province":"GA",
    "sg:tags":[
        "maintenance"
    ],
    "wof:name":"Quarterman Cleaning Service",
    "wof:placetype":"venue"
},
  "geometry": {"coordinates":[-84.09228899999999,33.815643],"type":"Point"}
}