{
  "type": "Feature",
  "properties": {
    "addr:full":"3862 Pool Rd Winston GA 30187",
    "addr:housenumber":"3862",
    "addr:postcode":"30187",
    "addr:street":"Pool Rd",
    "iso:country":"US",
    "sg:address":"3862 Pool Rd",
    "sg:city":"Winston",
    "sg:classifiers":[
        {
            "category":"Building & Trades",
            "subcategory":"Construction",
            "type":"Services"
        }
    ],
    "sg:phone":"+1 770 459 5250",
    "sg:postcode":"30187",
    "sg:province":"GA",
    "sg:tags":[
        "house"
    ],
    "wof:name":"Jerry Dean Construction",
    "wof:placetype":"venue"
},
  "geometry": {"coordinates":[-84.861311,33.701688],"type":"Point"}
}