{
  "type": "Feature",
  "properties": {
    "iso:country":"US",
    "sg:address":"2840 Montclair Ct",
    "sg:city":"Atlanta",
    "sg:classifiers":[
        {
            "category":"Building & Trades",
            "subcategory":"Construction",
            "type":"Services"
        }
    ],
    "sg:phone":"+1 770 668 0910",
    "sg:postcode":"30360",
    "sg:province":"GA",
    "sg:tags":[
        "house"
    ],
    "wof:name":"Macs Homes",
    "wof:placetype":"venue"
},
  "geometry": {"coordinates":[-84.271789,33.955071],"type":"Point"}
}