{
  "type": "Feature",
  "properties": {
    "addr:full":"2425 Colonial Dr NE Atlanta GA 30319",
    "addr:housenumber":"2425",
    "addr:postcode":"30319",
    "addr:street":"Colonial Dr Ne",
    "iso:country":"US",
    "sg:address":"2425 Colonial Dr NE",
    "sg:city":"Atlanta",
    "sg:classifiers":[
        {
            "category":"Building & Trades",
            "subcategory":"Locksmith",
            "type":"Services"
        }
    ],
    "sg:phone":"+1 866 663 1545",
    "sg:postcode":"30319",
    "sg:province":"GA",
    "sg:tags":[
        "key"
    ],
    "wof:name":"7 Day 24 Hour Emergency Locksmith",
    "wof:placetype":"venue"
},
  "geometry": {"coordinates":[-84.342962,33.856255],"type":"Point"}
}