{
  "type": "Feature",
  "properties": {
    "iso:country":"US",
    "sg:address":"843 Potomac Pl",
    "sg:city":"Winder",
    "sg:classifiers":[
        {
            "category":"Transit Center",
            "subcategory":"Freight",
            "type":"Transportation"
        },
        {
            "category":"Freight",
            "type":"Transportation"
        }
    ],
    "sg:phone":"+1 770 307 0214",
    "sg:postcode":"30680",
    "sg:province":"GA",
    "sg:tags":[
        "local",
        "trucking-motor",
        "trucking"
    ],
    "wof:name":"S&B Swafford's Trucking, Inc.",
    "wof:placetype":"venue"
},
  "geometry": {"coordinates":[-83.772136,34.053668],"type":"Point"}
}