{
  "type": "Feature",
  "properties": {
    "iso:country":"US",
    "sg:address":"1230 Peachtree St NE",
    "sg:city":"Atlanta",
    "sg:classifiers":[
        {
            "category":"Professional",
            "subcategory":"Detective & Security Services",
            "type":"Services"
        }
    ],
    "sg:phone":"+1 404 942 3865",
    "sg:postcode":"30309",
    "sg:province":"GA",
    "sg:tags":[
        "bodyguard",
        "patrol",
        "guard"
    ],
    "wof:name":"HR Services",
    "wof:placetype":"venue"
},
  "geometry": {"coordinates":[-84.383549,33.787713],"type":"Point"}
}