{
  "type": "Feature",
  "properties": {
    "addr:full":"1699 Hancock Ave Exd Gainesville GA 30501",
    "addr:housenumber":"1699",
    "addr:postcode":"30501",
    "addr:street":"Hancock Ave Exd;Ga",
    "iso:country":"US",
    "sg:address":"1699 Hancock Ave Exd",
    "sg:city":"Gainesville",
    "sg:classifiers":[
        {
            "category":"Freight",
            "type":"Transportation"
        }
    ],
    "sg:phone":"+1 770 536 2112",
    "sg:postcode":"30501",
    "sg:province":"GA",
    "sg:tags":[
        "operator",
        "auto",
        "trucking",
        "body",
        "local"
    ],
    "wof:name":"Gainesville Sand & Gravel",
    "wof:placetype":"venue"
},
  "geometry": {"coordinates":[-83.81665599999999,34.272205],"type":"Point"}
}