{
  "type": "Feature",
  "properties": {
    "addr:full":"1096 Bridge Mill Ave Canton GA 30114",
    "addr:housenumber":"1096",
    "addr:postcode":"30114",
    "addr:street":"Bridge Mill Ave",
    "iso:country":"US",
    "sg:address":"1096 Bridge Mill Ave",
    "sg:city":"Canton",
    "sg:classifiers":[
        {
            "category":"Banks & Credit Unions",
            "subcategory":"Investment Brokerage",
            "type":"Services"
        }
    ],
    "sg:phone":"+1 770 345 9020",
    "sg:postcode":"30114",
    "sg:province":"GA",
    "sg:tags":[
        "advisory"
    ],
    "wof:name":"Madison Assoc",
    "wof:placetype":"venue"
},
  "geometry": {"coordinates":[-84.56027899999999,34.181798],"type":"Point"}
}