{
  "type": "Feature",
  "properties": {
    "addr:full":"701 Broad St Ste 450 Rome GA 30161",
    "addr:housenumber":"701",
    "addr:postcode":"ga 30161",
    "addr:street":"Broad St Ste 450",
    "iso:country":"US",
    "sg:address":"701 Broad St Ste 450",
    "sg:city":"Rome",
    "sg:classifiers":[
        {
            "category":"Professional",
            "subcategory":"Computer Services",
            "type":"Services"
        }
    ],
    "sg:phone":"+1 706 232 9557",
    "sg:postcode":"30161",
    "sg:province":"GA",
    "sg:tags":[
        "design",
        "system",
        "network"
    ],
    "wof:name":"In-Touch Computer Services, Inc.",
    "wof:placetype":"venue"
},
  "geometry": {"coordinates":[-85.16739699999999,34.256618],"type":"Point"}
}