{
  "type": "Feature",
  "properties": {
    "iso:country":"US",
    "sg:address":"504 Crestview Dr",
    "sg:city":"Statesboro",
    "sg:classifiers":[
        {
            "category":"Building & Trades",
            "subcategory":"Equipment Rental",
            "type":"Services"
        }
    ],
    "sg:phone":"+1 912 823 9273",
    "sg:postcode":"30458",
    "sg:province":"GA",
    "wof:name":"Salter Entertainment",
    "wof:placetype":"venue"
},
  "geometry": {"coordinates":[-81.835053,32.411732],"type":"Point"}
}