{
  "type": "Feature",
  "properties": {
    "iso:country":"US",
    "sg:address":"223 E Thread Needle Rd",
    "sg:city":"Augusta",
    "sg:classifiers":[
        {
            "category":"Building & Trades",
            "subcategory":"Construction",
            "type":"Services"
        }
    ],
    "sg:phone":"+1 706 863 4510",
    "sg:postcode":"30907",
    "sg:province":"GA",
    "sg:tags":[
        "general",
        "contractor"
    ],
    "wof:name":"J P Mc Manus Construction Inc",
    "wof:placetype":"venue"
},
  "geometry": {"coordinates":[-82.06741599999999,33.507131],"type":"Point"}
}