{
  "type": "Feature",
  "properties": {
    "iso:country":"US",
    "sg:address":"3016 Heritage Rd",
    "sg:city":"Milledgeville",
    "sg:classifiers":[
        {
            "category":"Personal",
            "subcategory":"Beauty Salon",
            "type":"Services"
        }
    ],
    "sg:phone":"+1 478 452 6313",
    "sg:postcode":"31061",
    "sg:province":"GA",
    "sg:tags":[
        "shop"
    ],
    "wof:name":"Donna's Hair Designs",
    "wof:placetype":"venue"
},
  "geometry": {"coordinates":[-83.260927,33.119472],"type":"Point"}
}