{
  "type": "Feature",
  "properties": {
    "iso:country":"US",
    "sg:address":"117 Hurt Dr SE",
    "sg:city":"Smyrna",
    "sg:classifiers":[
        {
            "category":"Organizations",
            "subcategory":"Professional Association",
            "type":"Services"
        }
    ],
    "sg:phone":"+1 770 490 4340",
    "sg:postcode":"30082",
    "sg:province":"GA",
    "wof:name":"Greater Atlanta Permitting Svc",
    "wof:placetype":"venue"
},
  "geometry": {"coordinates":[-84.549144,33.869354],"type":"Point"}
}