{
  "type": "Feature",
  "properties": {
    "iso:country":"US",
    "sg:address":"5105 Paulsen St",
    "sg:city":"Savannah",
    "sg:classifiers":[
        {
            "category":"Health Services",
            "subcategory":"Nursing And Care Facility",
            "type":"Services"
        }
    ],
    "sg:phone":"+1 912 352 8200",
    "sg:postcode":"31405",
    "sg:province":"GA",
    "sg:tags":[
        "hospice"
    ],
    "wof:name":"Odyssey Healthcare",
    "wof:placetype":"venue"
},
  "geometry": {"coordinates":[-81.096622,32.029043],"type":"Point"}
}