{
  "type": "Feature",
  "properties": {
    "addr:full":"309 Merrill Dr La Grange GA 30241",
    "addr:housenumber":"309",
    "addr:postcode":"30241",
    "addr:street":"Merrill Dr",
    "iso:country":"US",
    "sg:address":"309 Merrill Dr",
    "sg:city":"La Grange",
    "sg:classifiers":[
        {
            "category":"Building & Trades",
            "subcategory":"Construction",
            "type":"Services"
        }
    ],
    "sg:phone":"+1 706 884 6091",
    "sg:postcode":"30241",
    "sg:province":"GA",
    "sg:tags":[
        "house"
    ],
    "wof:name":"Arrington Const Co",
    "wof:placetype":"venue"
},
  "geometry": {"coordinates":[-84.982141,33.060657],"type":"Point"}
}