{
  "type": "Feature",
  "properties": {
    "iso:country":"US",
    "sg:address":"585 River Oak Loop",
    "sg:city":"Lawrenceville",
    "sg:classifiers":[
        {
            "category":"Building & Trades",
            "subcategory":"Landscaping Services",
            "type":"Services"
        }
    ],
    "sg:phone":"+1 770 978 1551",
    "sg:postcode":"30044",
    "sg:province":"GA",
    "sg:tags":[
        "lawn",
        "maintenance",
        "grounds"
    ],
    "wof:name":"Lush Lawns Turf Care Inc",
    "wof:placetype":"venue"
},
  "geometry": {"coordinates":[-84.073756,33.891672],"type":"Point"}
}