{
  "type": "Feature",
  "properties": {
    "iso:country":"US",
    "sg:address":"56 Marietta St NW",
    "sg:city":"Atlanta",
    "sg:phone":"+1 404 525 1994",
    "sg:postcode":"30303",
    "sg:province":"GA",
    "wof:name":"Global Crossing",
    "wof:placetype":"venue"
},
  "geometry": {"coordinates":[-84.391323,33.75568],"type":"Point"}
}