{
  "type": "Feature",
  "properties": {
    "addr:full":"5047 Memorial Dr Stone Mountain GA 30087",
    "addr:housenumber":"5047",
    "addr:postcode":"30087",
    "addr:street":"Memorial Dr",
    "iso:country":"US",
    "sg:address":"5047 Memorial Dr",
    "sg:city":"Stone Mountain",
    "sg:classifiers":[
        {
            "category":"Restaurant",
            "type":"Food & Drink"
        }
    ],
    "sg:phone":"+1 678 705 9100",
    "sg:postcode":"30087",
    "sg:province":"GA",
    "sg:tags":[
        "ethiopian"
    ],
    "wof:name":"Daallo Restaurant",
    "wof:placetype":"venue"
},
  "geometry": {"coordinates":[-84.17379800000001,33.810574],"type":"Point"}
}