{
  "type": "Feature",
  "properties": {
    "addr:full":"6100 Veterans Pkwy Columbus GA 31909",
    "addr:housenumber":"6100",
    "addr:postcode":"31909",
    "addr:street":"Veterans Pkwy",
    "iso:country":"US",
    "sg:address":"6100 Veterans Pkwy",
    "sg:city":"Columbus",
    "sg:classifiers":[
        {
            "category":"Restaurant",
            "type":"Food & Drink"
        }
    ],
    "sg:phone":"+1 706 324 7282",
    "sg:postcode":"31909",
    "sg:province":"GA",
    "sg:tags":[
        "eating"
    ],
    "wof:name":"El Zapata II",
    "wof:placetype":"venue"
},
  "geometry": {"coordinates":[-84.95544700000001,32.53291],"type":"Point"}
}