{
  "type": "Feature",
  "properties": {
    "addr:full":"4004 Lawrenceville Hwy NW Lilburn GA 30047",
    "addr:housenumber":"4004",
    "addr:postcode":"30047",
    "addr:street":"Lawrenceville Hwy Nw",
    "iso:country":"US",
    "sg:address":"4004 Lawrenceville Hwy NW",
    "sg:city":"Lilburn",
    "sg:classifiers":[
        {
            "category":"Deli",
            "type":"Food & Drink"
        }
    ],
    "sg:menulink":"http://www.allmenus.com/ga/lilburn/127004-blimpie-subs--sandwiches/menu/",
    "sg:phone":"+1 770 638 5112",
    "sg:postcode":"30047",
    "sg:province":"GA",
    "sg:tags":[
        "wrap",
        "american",
        "sandwich"
    ],
    "wof:name":"Blimpie Subs & Sandwiches",
    "wof:placetype":"venue"
},
  "geometry": {"coordinates":[-84.114895,33.904012],"type":"Point"}
}