{
  "type": "Feature",
  "properties": {
    "iso:country":"US",
    "sg:address":"4761 Holley Rd",
    "sg:city":"Lizella",
    "sg:classifiers":[
        {
            "category":"Farming",
            "subcategory":"Berry Farm",
            "type":"Manufacturing & Wholesale Goods"
        }
    ],
    "sg:phone":"+1 478 935 8180",
    "sg:postcode":"31052",
    "sg:province":"GA",
    "sg:tags":[
        "crop"
    ],
    "wof:name":"Elliott Farms",
    "wof:placetype":"venue"
},
  "geometry": {"coordinates":[-83.839411,32.783752],"type":"Point"}
}