{
  "type": "Feature",
  "properties": {
    "iso:country":"US",
    "sg:address":"1141 Cleveland Ave",
    "sg:city":"Buckhead",
    "sg:classifiers":[
        {
            "category":"Professional",
            "subcategory":"Business Services",
            "type":"Services"
        },
        {
            "category":"Shopping",
            "subcategory":"Computers & Home Electronics",
            "type":"Retail Goods"
        }
    ],
    "sg:phone":"+1 706 342 0198",
    "sg:postcode":"30625",
    "sg:province":"GA",
    "sg:tags":[
        "publishing"
    ],
    "wof:name":"H S I/My Business",
    "wof:placetype":"venue"
},
  "geometry": {"coordinates":[-83.364273,33.575079],"type":"Point"}
}