{
  "type": "Feature",
  "properties": {
    "addr:full":"450 Caxton Ct SW Atlanta GA 30331",
    "addr:housenumber":"450",
    "addr:postcode":"30331",
    "addr:street":"Caxton Ct Sw",
    "iso:country":"US",
    "sg:address":"450 Caxton Ct SW",
    "sg:city":"Atlanta",
    "sg:classifiers":[
        {
            "category":"Arts & Performance",
            "subcategory":"Dance",
            "type":"Entertainment"
        }
    ],
    "sg:phone":"+1 678 705 4828",
    "sg:postcode":"30331",
    "sg:province":"GA",
    "sg:tags":[
        "instruction",
        "dancing"
    ],
    "wof:name":"Wimberly Dance Studios",
    "wof:placetype":"venue"
},
  "geometry": {"coordinates":[-84.57201499999999,33.709397],"type":"Point"}
}