{
  "type": "Feature",
  "properties": {
    "iso:country":"US",
    "sg:address":"413 N Broad St",
    "sg:city":"Bainbridge",
    "sg:classifiers":[
        {
            "category":"Autos & Motor Vehicles",
            "subcategory":"Auto Supplies",
            "type":"Retail Goods"
        }
    ],
    "sg:phone":"+1 229 246 6111",
    "sg:postcode":"39817",
    "sg:province":"GA",
    "sg:tags":[
        "automobile",
        "parts"
    ],
    "wof:name":"Decatur Auto Parts",
    "wof:placetype":"venue"
},
  "geometry": {"coordinates":[-84.57557199999999,30.909215],"type":"Point"}
}