{
  "type": "Feature",
  "properties": {
    "addr:full":"974 Hunting Valley Pl Decatur GA 30033",
    "addr:housenumber":"974",
    "addr:postcode":"30033",
    "addr:street":"Hunting Valley Pl",
    "iso:country":"US",
    "sg:address":"974 Hunting Valley Pl",
    "sg:city":"Decatur",
    "sg:classifiers":[
        {
            "category":"Professional",
            "type":"Services"
        }
    ],
    "sg:phone":"+1 404 583 8742",
    "sg:postcode":"30033",
    "sg:province":"GA",
    "sg:tags":[
        "establishment"
    ],
    "wof:name":"Designers Dream Workroom",
    "wof:placetype":"venue"
},
  "geometry": {"coordinates":[-84.29131099999999,33.806564],"type":"Point"}
}