{
  "type": "Feature",
  "properties": {
    "iso:country":"US",
    "sg:address":"374 Maynard Ter SE",
    "sg:city":"Atlanta",
    "sg:classifiers":[
        {
            "category":"Banks & Credit Unions",
            "subcategory":"Atm",
            "type":"Services"
        }
    ],
    "sg:phone":"+1 404 373 7776",
    "sg:postcode":"30316",
    "sg:province":"GA",
    "sg:tags":[
        "bankruptcy"
    ],
    "wof:name":"Archibong Natalyn M Atty",
    "wof:placetype":"venue"
},
  "geometry": {"coordinates":[-84.335787,33.725002],"type":"Point"}
}