{
  "type": "Feature",
  "properties": {
    "addr:full":"6635 Pirkle Pl Cumming GA 30040",
    "addr:housenumber":"6635",
    "addr:postcode":"30040",
    "addr:street":"Pirkle Pl",
    "iso:country":"US",
    "sg:address":"6635 Pirkle Pl",
    "sg:city":"Cumming",
    "sg:classifiers":[
        {
            "category":"Building & Trades",
            "subcategory":"Landscaping Services",
            "type":"Services"
        }
    ],
    "sg:phone":"+1 770 205 1101",
    "sg:postcode":"30040",
    "sg:province":"GA",
    "sg:tags":[
        "landscape"
    ],
    "wof:name":"Lawn Ranger",
    "wof:placetype":"venue"
},
  "geometry": {"coordinates":[-84.123576,34.324094],"type":"Point"}
}