{
  "type": "Feature",
  "properties": {
    "addr:full":"5048 Buford Hwy Chamblee GA 30341",
    "addr:housenumber":"5048",
    "addr:postcode":"30341",
    "addr:street":"Buford Hwy",
    "iso:country":"US",
    "sg:address":"5048 Buford Hwy",
    "sg:city":"Chamblee",
    "sg:classifiers":[
        {
            "category":"Building & Trades",
            "subcategory":"Locksmith",
            "type":"Services"
        }
    ],
    "sg:phone":"+1 678 259 8348",
    "sg:postcode":"30341",
    "sg:province":"GA",
    "sg:tags":[
        "key"
    ],
    "wof:name":"Locksmith 1 & 24 by 7",
    "wof:placetype":"venue"
},
  "geometry": {"coordinates":[-84.286041,33.889979],"type":"Point"}
}