{
  "type": "Feature",
  "properties": {
    "iso:country":"US",
    "sg:address":"7600 Roswell Rd.",
    "sg:city":"Sandy Springs",
    "sg:classifiers":[
        {
            "category":"Real Estate",
            "subcategory":"Real Estate Operator",
            "type":"Services"
        }
    ],
    "sg:phone":"+1 770 396 0222",
    "sg:postcode":"30350",
    "sg:province":"GA",
    "sg:tags":[
        "apartment"
    ],
    "wof:name":"The Edgewater at Sandy Springs",
    "wof:placetype":"venue"
},
  "geometry": {"coordinates":[-84.365711,33.962045],"type":"Point"}
}