{
  "type": "Feature",
  "properties": {
    "iso:country":"US",
    "sg:address":"701 Oak St",
    "sg:city":"Waycross",
    "sg:classifiers":[
        {
            "category":"Recreation",
            "type":"Entertainment"
        }
    ],
    "sg:phone":"+1 912 285 4111",
    "sg:postcode":"31501",
    "sg:province":"GA",
    "sg:tags":[
        "parlor",
        "billiard"
    ],
    "wof:name":"Bobo's Game Room",
    "wof:placetype":"venue"
},
  "geometry": {"coordinates":[-82.36293499999999,31.217625],"type":"Point"}
}