{
  "type": "Feature",
  "properties": {
    "iso:country":"US",
    "sg:address":"1082 Dassow Ct",
    "sg:city":"Alpharetta",
    "sg:classifiers":[
        {
            "category":"Building & Trades",
            "subcategory":"Construction",
            "type":"Services"
        }
    ],
    "sg:phone":"+1 770 667 0862",
    "sg:postcode":"30004",
    "sg:province":"GA",
    "sg:tags":[
        "contractor"
    ],
    "wof:name":"McCloud Roofing",
    "wof:placetype":"venue"
},
  "geometry": {"coordinates":[-84.318607,34.047326],"type":"Point"}
}