{
  "type": "Feature",
  "properties": {
    "iso:country":"US",
    "sg:address":"20 Oaks Dr",
    "sg:city":"Covington",
    "sg:classifiers":[
        {
            "category":"Building & Trades",
            "subcategory":"Plumbing",
            "type":"Services"
        }
    ],
    "sg:phone":"+1 770 385 7251",
    "sg:postcode":"30016",
    "sg:province":"GA",
    "sg:tags":[
        "plumbing",
        "contractor"
    ],
    "wof:name":"Collins Plumbing",
    "wof:placetype":"venue"
},
  "geometry": {"coordinates":[-83.91172,33.478732],"type":"Point"}
}