{
  "type": "Feature",
  "properties": {
    "addr:full":"509 Huntcliff Village Ct Atlanta GA 30350",
    "addr:housenumber":"509",
    "addr:postcode":"30350",
    "addr:street":"Huntcliff Village Ct",
    "iso:country":"US",
    "sg:address":"509 Huntcliff Village Ct",
    "sg:city":"Atlanta",
    "sg:classifiers":[
        {
            "category":"Manufacturing",
            "subcategory":"Chemicals & Compounds",
            "type":"Manufacturing & Wholesale Goods"
        }
    ],
    "sg:phone":"+1 770 849 7730",
    "sg:postcode":"30350",
    "sg:province":"GA",
    "sg:tags":[
        "chemicals-wholesale",
        "manufacturer"
    ],
    "wof:name":"Nalco Company ATL",
    "wof:placetype":"venue"
},
  "geometry": {"coordinates":[-84.354313,34.000097],"type":"Point"}
}