{
  "type": "Feature",
  "properties": {
    "iso:country":"US",
    "sg:address":"823 2nd Ave",
    "sg:city":"Columbus",
    "sg:classifiers":[
        {
            "category":"Professional",
            "subcategory":"Lawyer & Legal Services",
            "type":"Services"
        }
    ],
    "sg:phone":"+1 706 322 1637",
    "sg:postcode":"31901",
    "sg:province":"GA",
    "sg:tags":[
        "attorney"
    ],
    "wof:name":"Thomas L Thompson Jr",
    "wof:placetype":"venue"
},
  "geometry": {"coordinates":[-84.990449,32.462474],"type":"Point"}
}