{
  "type": "Feature",
  "properties": {
    "addr:full":"1190 Rosedale Rd NE Atlanta GA 30306",
    "addr:housenumber":"1190",
    "addr:postcode":"30306",
    "addr:street":"Rosedale Rd Ne",
    "iso:country":"US",
    "sg:address":"1190 Rosedale Rd NE",
    "sg:city":"Atlanta",
    "sg:classifiers":[
        {
            "category":"Professional",
            "subcategory":"Management & Consulting",
            "type":"Services"
        }
    ],
    "sg:phone":"+1 404 874 0291",
    "sg:postcode":"30306",
    "sg:province":"GA",
    "sg:tags":[
        "consultant",
        "educational"
    ],
    "wof:name":"Lawriters",
    "wof:placetype":"venue"
},
  "geometry": {"coordinates":[-84.34809,33.786033],"type":"Point"}
}