{
  "type": "Feature",
  "properties": {
    "addr:full":"4448 Atlanta Rd SE Smyrna GA 30080",
    "addr:housenumber":"4448",
    "addr:postcode":"30080",
    "addr:street":"Atlanta Rd Se",
    "iso:country":"US",
    "sg:address":"4448 Atlanta Rd SE",
    "sg:city":"Smyrna",
    "sg:classifiers":[
        {
            "category":"Building & Trades",
            "subcategory":"Plumbing",
            "type":"Services"
        }
    ],
    "sg:phone":"+1 770 433 3232",
    "sg:postcode":"30080",
    "sg:province":"GA",
    "sg:website":"www.artplumbing.com",
    "wof:name":"Art Plumbing Co",
    "wof:placetype":"venue"
},
  "geometry": {"coordinates":[-84.490286,33.844996],"type":"Point"}
}