{
  "type": "Feature",
  "properties": {
    "addr:full":"514 W Ogeechee St Sylvania GA 30467",
    "addr:housenumber":"514",
    "addr:postcode":"30467",
    "addr:street":"W Ogeechee St",
    "iso:country":"US",
    "sg:address":"514 W Ogeechee St",
    "sg:city":"Sylvania",
    "sg:classifiers":[
        {
            "category":"Shopping",
            "subcategory":"Department Store",
            "type":"Retail Goods"
        },
        {
            "category":"Shopping",
            "subcategory":"Discount & Variety Stores",
            "type":"Retail Goods"
        },
        {
            "category":"Shopping",
            "type":"Retail Goods"
        },
        {
            "category":"Food & Beverages",
            "subcategory":"Groceries & Convenience Stores",
            "type":"Retail Goods"
        }
    ],
    "sg:phone":"+1 912 564 7211",
    "sg:postcode":"30467",
    "sg:province":"GA",
    "sg:tags":[
        "merchandise"
    ],
    "sg:website":"http://www.dollargeneral.com",
    "wof:name":"Dollar General",
    "wof:placetype":"venue"
},
  "geometry": {"coordinates":[-81.644667,32.747119],"type":"Point"}
}