{
  "type": "Feature",
  "properties": {
    "iso:country":"US",
    "sg:address":"1330 Morrow Rd",
    "sg:city":"Morrow",
    "sg:classifiers":[
        {
            "category":"Personal",
            "subcategory":"Beauty Salon",
            "type":"Services"
        }
    ],
    "sg:phone":"+1 770 961 1900",
    "sg:postcode":"30260",
    "sg:province":"GA",
    "sg:tags":[
        "hair"
    ],
    "wof:name":"Southlake Haircuts",
    "wof:placetype":"venue"
},
  "geometry": {"coordinates":[-84.34511500000001,33.583438],"type":"Point"}
}