{
  "type": "Feature",
  "properties": {
    "iso:country":"US",
    "sg:address":"6220 Milgen Rd",
    "sg:city":"Columbus",
    "sg:classifiers":[
        {
            "category":"Recreation",
            "type":"Entertainment"
        }
    ],
    "sg:phone":"+1 706 563 4411",
    "sg:postcode":"31907",
    "sg:province":"GA",
    "sg:tags":[
        "martial",
        "arts",
        "instruction"
    ],
    "wof:name":"Kenshin School Yoshukai Karate",
    "wof:placetype":"venue"
},
  "geometry": {"coordinates":[-84.886399,32.526559],"type":"Point"}
}