{
  "type": "Feature",
  "properties": {
    "addr:full":"1745 GA-138 SE Conyers GA 30013",
    "addr:housenumber":"1745",
    "addr:postcode":"30013",
    "addr:street":"Ga-138 Se",
    "iso:country":"US",
    "sg:address":"1745 GA-138 SE",
    "sg:city":"Conyers",
    "sg:classifiers":[
        {
            "category":"Restaurant",
            "type":"Food & Drink"
        }
    ],
    "sg:menulink":"http://www.allmenus.com/ga/conyers/235047-roly-poly-sandwiches/menu/",
    "sg:phone":"+1 770 483 8464",
    "sg:postcode":"30013",
    "sg:province":"GA",
    "sg:tags":[
        "wrap",
        "american",
        "sandwich"
    ],
    "wof:name":"Roly Poly Sandwiches",
    "wof:placetype":"venue"
},
  "geometry": {"coordinates":[-83.98808,33.668711],"type":"Point"}
}