{
  "type": "Feature",
  "properties": {
    "addr:full":"233 Dorothy St NE Moultrie GA 31768",
    "addr:housenumber":"233",
    "addr:postcode":"31768",
    "addr:street":"Dorothy St Ne",
    "iso:country":"US",
    "sg:address":"233 Dorothy St NE",
    "sg:city":"Moultrie",
    "sg:classifiers":[
        {
            "category":"Building & Trades",
            "subcategory":"Landscaping Services",
            "type":"Services"
        }
    ],
    "sg:phone":"+1 229 985 7545",
    "sg:postcode":"31768",
    "sg:province":"GA",
    "wof:name":"Charles Merrit Company Inc",
    "wof:placetype":"venue"
},
  "geometry": {"coordinates":[-83.76675299999999,31.181542],"type":"Point"}
}