{
  "type": "Feature",
  "properties": {
    "iso:country":"US",
    "sg:address":"2828 Browns Bridge Rd",
    "sg:city":"Gainesville",
    "sg:classifiers":[
        {
            "category":"Wholesale",
            "subcategory":"Motor Vehicles",
            "type":"Manufacturing & Wholesale Goods"
        },
        {
            "category":"Retail",
            "subcategory":"Auto Rental",
            "type":"Services"
        }
    ],
    "sg:phone":"+1 770 718 9500",
    "sg:postcode":"30504",
    "sg:province":"GA",
    "sg:tags":[
        "passenger",
        "used",
        "leasing",
        "automobile",
        "broker",
        "truck",
        "car"
    ],
    "wof:name":"Kafka Automotive Sales & Leasi",
    "wof:placetype":"venue"
},
  "geometry": {"coordinates":[-83.87672999999999,34.279739],"type":"Point"}
}