{
  "type": "Feature",
  "properties": {
    "iso:country":"US",
    "sg:address":"203 Medical Way",
    "sg:city":"Riverdale",
    "sg:classifiers":[
        {
            "category":"Health Services",
            "subcategory":"Clinic",
            "type":"Services"
        },
        {
            "category":"Health Services",
            "subcategory":"Doctor",
            "type":"Services"
        }
    ],
    "sg:phone":"+1 770 997 7077",
    "sg:postcode":"30274",
    "sg:province":"GA",
    "sg:tags":[
        "physician",
        "surgeon"
    ],
    "wof:name":"Wellspring Medical Center",
    "wof:placetype":"venue"
},
  "geometry": {"coordinates":[-84.39930699999999,33.577669],"type":"Point"}
}