{
  "type": "Feature",
  "properties": {
    "addr:full":"6465 E Johns Xing Duluth GA 30097",
    "addr:housenumber":"6465",
    "addr:postcode":"30097",
    "addr:street":"E Johns Xing",
    "iso:country":"US",
    "sg:address":"6465 E Johns Xing",
    "sg:city":"Duluth",
    "sg:classifiers":[
        {
            "category":"Shopping",
            "subcategory":"Computers & Home Electronics",
            "type":"Retail Goods"
        }
    ],
    "sg:phone":"+1 770 814 4345",
    "sg:postcode":"30097",
    "sg:province":"GA",
    "sg:tags":[
        "software"
    ],
    "wof:name":"RTS Software",
    "wof:placetype":"venue"
},
  "geometry": {"coordinates":[-84.16585600000001,34.063189],"type":"Point"}
}