{
  "type": "Feature",
  "properties": {
    "iso:country":"US",
    "sg:address":"100 Russell Pkwy",
    "sg:city":"Warner Robins",
    "sg:classifiers":[
        {
            "category":"Food & Beverages",
            "subcategory":"Groceries & Convenience Stores",
            "type":"Retail Goods"
        },
        {
            "category":"Autos & Motor Vehicles",
            "subcategory":"Fuel & Gas Station",
            "type":"Retail Goods"
        }
    ],
    "sg:phone":"+1 478 923 6499",
    "sg:postcode":"31088",
    "sg:province":"GA",
    "sg:tags":[
        "station",
        "gasoline"
    ],
    "wof:name":"Mini Food Stores Inc",
    "wof:placetype":"venue"
},
  "geometry": {"coordinates":[-83.625332,32.593846],"type":"Point"}
}