{
  "type": "Feature",
  "properties": {
    "addr:full":"5457 Roswell Rd Atlanta GA 30342",
    "addr:housenumber":"5457",
    "addr:postcode":"30342",
    "addr:street":"Roswell Rd",
    "iso:country":"US",
    "sg:address":"5457 Roswell Rd",
    "sg:city":"Atlanta",
    "sg:classifiers":[
        {
            "category":"Professional",
            "subcategory":"Computer Services",
            "type":"Services"
        }
    ],
    "sg:phone":"+1 404 256 1218",
    "sg:postcode":"30342",
    "sg:province":"GA",
    "sg:tags":[
        "related"
    ],
    "wof:name":"Clark George E CPA",
    "wof:placetype":"venue"
},
  "geometry": {"coordinates":[-84.378569,33.90574],"type":"Point"}
}