{
  "type": "Feature",
  "properties": {
    "addr:full":"3166 Wrightsboro Rd Augusta GA 30909",
    "addr:housenumber":"3166",
    "addr:postcode":"30909",
    "addr:street":"Wrightsboro Rd",
    "iso:country":"US",
    "sg:address":"3166 Wrightsboro Rd",
    "sg:city":"Augusta",
    "sg:classifiers":[
        {
            "category":"Restaurant",
            "type":"Food & Drink"
        }
    ],
    "sg:menulink":"http://www.allmenus.com/ga/augusta/100632-captain-ds-seafood/menu/",
    "sg:phone":"+1 706 733 5361",
    "sg:postcode":"30909",
    "sg:province":"GA",
    "sg:tags":[
        "seafood",
        "american"
    ],
    "wof:name":"Captain D's Seafood",
    "wof:placetype":"venue"
},
  "geometry": {"coordinates":[-82.057188,33.469894],"type":"Point"}
}