{
  "type": "Feature",
  "properties": {
    "iso:country":"US",
    "sg:address":"2740 Buckeye Rd",
    "sg:city":"Tennille",
    "sg:classifiers":[
        {
            "category":"Organizations",
            "subcategory":"Religious Organization",
            "type":"Services"
        }
    ],
    "sg:phone":"+1 478 552 4166",
    "sg:postcode":"31089",
    "sg:province":"GA",
    "sg:tags":[
        "church"
    ],
    "wof:name":"Bethesda Christian Church",
    "wof:placetype":"venue"
},
  "geometry": {"coordinates":[-82.850849,32.799661],"type":"Point"}
}