{
  "type": "Feature",
  "properties": {
    "addr:full":"5430 Jimmy Carter Blvd Norcross GA 30093",
    "addr:housenumber":"5430",
    "addr:postcode":"30093",
    "addr:street":"Jimmy Carter Blvd",
    "iso:country":"US",
    "sg:address":"5430 Jimmy Carter Blvd",
    "sg:city":"Norcross",
    "sg:classifiers":[
        {
            "category":"Professional",
            "subcategory":"Employment Agencies",
            "type":"Services"
        }
    ],
    "sg:phone":"+1 770 409 3111",
    "sg:postcode":"30093",
    "sg:province":"GA",
    "sg:tags":[
        "help",
        "supply"
    ],
    "wof:name":"Prodrivers",
    "wof:placetype":"venue"
},
  "geometry": {"coordinates":[-84.206095,33.906416],"type":"Point"}
}