{
  "type": "Feature",
  "properties": {
    "addr:full":"5502 Peachtree Rd Atlanta GA 30341",
    "addr:housenumber":"5502",
    "addr:postcode":"30341",
    "addr:street":"Peachtree Rd",
    "iso:country":"US",
    "sg:address":"5502 Peachtree Rd",
    "sg:city":"Atlanta",
    "sg:classifiers":[
        {
            "category":"Autos & Motor Vehicles",
            "subcategory":"Automobile Sales",
            "type":"Retail Goods"
        }
    ],
    "sg:phone":"+1 770 455 1188",
    "sg:postcode":"30341",
    "sg:province":"GA",
    "sg:tags":[
        "used"
    ],
    "wof:name":"Whys Automotive Retail Corp",
    "wof:placetype":"venue"
},
  "geometry": {"coordinates":[-84.29607300000001,33.895194],"type":"Point"}
}