{
  "type": "Feature",
  "properties": {
    "addr:full":"1003 Saint Patricks Dr Perry GA 31069",
    "addr:housenumber":"1003",
    "addr:postcode":"31069",
    "addr:street":"Saint Patricks Dr",
    "iso:country":"US",
    "sg:address":"1003 Saint Patricks Dr",
    "sg:city":"Perry",
    "sg:classifiers":[
        {
            "category":"Utilities",
            "subcategory":"Mobile Phone",
            "type":"Services"
        },
        {
            "category":"Shopping",
            "subcategory":"Mobile Phones",
            "type":"Retail Goods"
        },
        {
            "category":"Utilities",
            "subcategory":"Telephone",
            "type":"Services"
        },
        {
            "category":"Professional",
            "subcategory":"Computer Services",
            "type":"Services"
        }
    ],
    "sg:phone":"+1 478 988 3755",
    "sg:postcode":"31069",
    "sg:province":"GA",
    "sg:tags":[
        "telecommunication",
        "supply",
        "communication",
        "system",
        "wireless",
        "equipment",
        "cellular"
    ],
    "sg:website":"http://clickserve.dartsearch.net/link/click?lid=43000000308049899",
    "wof:name":"T-Mobile",
    "wof:placetype":"venue"
},
  "geometry": {"coordinates":[-83.743031,32.470968],"type":"Point"}
}