{
  "type": "Feature",
  "properties": {
    "addr:full":"4741 State Rte 85 Ellerslie GA 31807",
    "addr:housenumber":"4741",
    "addr:postcode":"31807",
    "addr:street":"State Rte 85",
    "iso:country":"US",
    "sg:address":"4741 State Rte 85",
    "sg:city":"Ellerslie",
    "sg:classifiers":[
        {
            "category":"Shopping",
            "subcategory":"Music",
            "type":"Retail Goods"
        },
        {
            "category":"Cinema",
            "subcategory":"Movie Rental",
            "type":"Entertainment"
        }
    ],
    "sg:phone":"+1 706 565 8215",
    "sg:postcode":"31807",
    "sg:province":"GA",
    "sg:tags":[
        "video",
        "disc",
        "tape",
        "cassette"
    ],
    "wof:name":"Movie The Place",
    "wof:placetype":"venue"
},
  "geometry": {"coordinates":[-84.785708,32.642103],"type":"Point"}
}