{
  "type": "Feature",
  "properties": {
    "iso:country":"US",
    "sg:address":"2547 Lakeview East Ct SE",
    "sg:city":"Atlanta",
    "sg:phone":"+1 404 577 0033",
    "sg:postcode":"30316",
    "sg:province":"GA",
    "wof:name":"Flick Hair Studio",
    "wof:placetype":"venue"
},
  "geometry": {"coordinates":[-84.334962,33.714861],"type":"Point"}
}