{
  "type": "Feature",
  "properties": {
    "iso:country":"US",
    "sg:address":"124 Barrett Ct",
    "sg:city":"Midway",
    "sg:classifiers":[
        {
            "category":"Personal",
            "subcategory":"Beauty Salon",
            "type":"Services"
        }
    ],
    "sg:phone":"+1 912 884 5859",
    "sg:postcode":"31320",
    "sg:province":"GA",
    "wof:name":"Barretts Beauty Shop",
    "wof:placetype":"venue"
},
  "geometry": {"coordinates":[-81.502431,31.813285],"type":"Point"}
}