{
  "type": "Feature",
  "properties": {
    "iso:country":"US",
    "sg:address":"419 3rd Ave",
    "sg:city":"Decatur",
    "sg:classifiers":[
        {
            "category":"Wholesale",
            "subcategory":"Non-durable Goods",
            "type":"Manufacturing & Wholesale Goods"
        }
    ],
    "sg:phone":"+1 404 377 0691",
    "sg:postcode":"30030",
    "sg:province":"GA",
    "wof:name":"Lmtc LLC",
    "wof:placetype":"venue"
},
  "geometry": {"coordinates":[-84.30833699999999,33.758407],"type":"Point"}
}