{
  "type": "Feature",
  "properties": {
    "addr:full":"700 N Cleveland St Albany GA 31701",
    "addr:housenumber":"700",
    "addr:postcode":"31701",
    "addr:street":"N Cleveland St",
    "iso:country":"US",
    "sg:address":"700 N Cleveland St",
    "sg:city":"Albany",
    "sg:classifiers":[
        {
            "category":"Social Services",
            "subcategory":"Child Care",
            "type":"Services"
        }
    ],
    "sg:phone":"+1 229 888 1162",
    "sg:postcode":"31701",
    "sg:province":"GA",
    "wof:name":"Wee-Kare Day Care & Pre School",
    "wof:placetype":"venue"
},
  "geometry": {"coordinates":[-84.17388,31.587024],"type":"Point"}
}