{
  "type": "Feature",
  "properties": {
    "iso:country":"US",
    "sg:address":"4473 College St",
    "sg:city":"Forest Park",
    "sg:classifiers":[
        {
            "category":"Organizations",
            "subcategory":"Religious Organization",
            "type":"Services"
        }
    ],
    "sg:phone":"+1 404 366 2121",
    "sg:postcode":"30297",
    "sg:province":"GA",
    "sg:tags":[
        "church"
    ],
    "wof:name":"Park Forest United Methodist",
    "wof:placetype":"venue"
},
  "geometry": {"coordinates":[-84.35860599999999,33.63363],"type":"Point"}
}