{
  "type": "Feature",
  "properties": {
    "iso:country":"US",
    "sg:address":"729 3rd Ave",
    "sg:city":"Decatur",
    "sg:classifiers":[
        {
            "category":"Professional",
            "type":"Services"
        }
    ],
    "sg:phone":"+1 404 377 4761",
    "sg:postcode":"30030",
    "sg:province":"GA",
    "wof:name":"Allwrite Inc",
    "wof:placetype":"venue"
},
  "geometry": {"coordinates":[-84.308316,33.757231],"type":"Point"}
}