{
  "type": "Feature",
  "properties": {
    "iso:country":"US",
    "sg:address":"612 College St",
    "sg:city":"Atlanta",
    "sg:classifiers":[
        {
            "category":"Education",
            "subcategory":"School",
            "type":"Public Place"
        }
    ],
    "sg:phone":"+1 770 748 0832",
    "sg:postcode":"30354",
    "sg:province":"GA",
    "sg:tags":[
        "high",
        "middle",
        "elementary"
    ],
    "wof:name":"Polk School District",
    "wof:placetype":"venue"
},
  "geometry": {"coordinates":[-84.409361,33.65659],"type":"Point"}
}