{
  "type": "Feature",
  "properties": {
    "iso:country":"US",
    "sg:address":"1191 Larson Ln",
    "sg:city":"Marietta",
    "sg:classifiers":[
        {
            "category":"Banks & Credit Unions",
            "subcategory":"Financial Services",
            "type":"Services"
        }
    ],
    "sg:phone":"+1 770 419 7903",
    "sg:postcode":"30064",
    "sg:province":"GA",
    "sg:tags":[
        "investor"
    ],
    "wof:name":"Capital Rcvery Cnsulting Group",
    "wof:placetype":"venue"
},
  "geometry": {"coordinates":[-84.60035499999999,33.924688],"type":"Point"}
}