{
  "type": "Feature",
  "properties": {
    "iso:country":"US",
    "sg:address":"3044 Morgan Rd",
    "sg:city":"Bremen",
    "sg:classifiers":[
        {
            "category":"Organizations",
            "subcategory":"Religious Organization",
            "type":"Services"
        }
    ],
    "sg:phone":"+1 770 562 0016",
    "sg:postcode":"30110",
    "sg:province":"GA",
    "wof:name":"District Line United Methodist",
    "wof:placetype":"venue"
},
  "geometry": {"coordinates":[-85.06858,33.783865],"type":"Point"}
}