{
  "type": "Feature",
  "properties": {
    "addr:full":"29 Uppr Riverdale Rd SW Riverdale GA 30274",
    "addr:housenumber":"29",
    "addr:postcode":"30274",
    "addr:street":"Uppr Riverdale Rd Sw",
    "iso:country":"US",
    "sg:address":"29 Uppr Riverdale Rd SW",
    "sg:city":"Riverdale",
    "sg:classifiers":[
        {
            "category":"Health Services",
            "subcategory":"Doctor",
            "type":"Services"
        }
    ],
    "sg:phone":"+1 770 907 1199",
    "sg:postcode":"30274",
    "sg:province":"GA",
    "wof:name":"Urology of Atlanta L L C",
    "wof:placetype":"venue"
},
  "geometry": {"coordinates":[-84.391098,33.577301],"type":"Point"}
}