{
  "type": "Feature",
  "properties": {
    "iso:country":"US",
    "sg:address":"415 University Cir",
    "sg:city":"Athens",
    "sg:classifiers":[
        {
            "category":"Professional",
            "subcategory":"Lawyer & Legal Services",
            "type":"Services"
        }
    ],
    "sg:phone":"+1 706 549 0083",
    "sg:postcode":"30605",
    "sg:province":"GA",
    "wof:name":"Expert Med Lgal Consulting LLC",
    "wof:placetype":"venue"
},
  "geometry": {"coordinates":[-83.357811,33.91734],"type":"Point"}
}