{
  "type": "Feature",
  "properties": {
    "addr:full":"2663 Corinault Way NW Acworth GA 30101",
    "addr:housenumber":"2663",
    "addr:postcode":"30101",
    "addr:street":"Corinault Way Nw",
    "iso:country":"US",
    "sg:address":"2663 Corinault Way NW",
    "sg:city":"Acworth",
    "sg:classifiers":[
        {
            "category":"Building & Trades",
            "subcategory":"Construction",
            "type":"Services"
        }
    ],
    "sg:phone":"+1 770 529 5993",
    "sg:postcode":"30101",
    "sg:province":"GA",
    "sg:tags":[
        "hanging",
        "contractor"
    ],
    "wof:name":"Trent Rogers Painting",
    "wof:placetype":"venue"
},
  "geometry": {"coordinates":[-84.696003,34.017642],"type":"Point"}
}