{
  "type": "Feature",
  "properties": {
    "iso:country":"US",
    "sg:address":"608 Holcomb Bridge Rd # 261",
    "sg:city":"Roswell",
    "sg:classifiers":[
        {
            "category":"Manufacturing",
            "subcategory":"Toys & Sporting Goods",
            "type":"Manufacturing & Wholesale Goods"
        }
    ],
    "sg:phone":"+1 678 613 5452",
    "sg:postcode":"30076",
    "sg:province":"GA",
    "sg:tags":[
        "goods-wholesale",
        "manufacturer"
    ],
    "wof:name":"V2 Sports",
    "wof:placetype":"venue"
},
  "geometry": {"coordinates":[-84.34226200000001,34.035149],"type":"Point"}
}