{
  "type": "Feature",
  "properties": {
    "addr:full":"216 W College St Colquitt GA 39837",
    "addr:housenumber":"216",
    "addr:postcode":"39837",
    "addr:street":"W College St",
    "iso:country":"US",
    "sg:address":"216 W College St",
    "sg:city":"Colquitt",
    "sg:classifiers":[
        {
            "category":"Home & Garden",
            "subcategory":"Furniture",
            "type":"Retail Goods"
        }
    ],
    "sg:phone":"+1 229 758 3466",
    "sg:postcode":"39837",
    "sg:province":"GA",
    "sg:tags":[
        "store"
    ],
    "wof:name":"Bevis Furniture Co",
    "wof:placetype":"venue"
},
  "geometry": {"coordinates":[-84.731252,31.170927],"type":"Point"}
}