{
  "type": "Feature",
  "properties": {
    "iso:country":"US",
    "sg:address":"102 Saxon St",
    "sg:city":"Brunswick",
    "sg:classifiers":[
        {
            "category":"Freight",
            "type":"Transportation"
        }
    ],
    "sg:phone":"+1 912 264 6006",
    "sg:postcode":"31525",
    "sg:province":"GA",
    "wof:name":"Jones Transport",
    "wof:placetype":"venue"
},
  "geometry": {"coordinates":[-81.47829400000001,31.211349],"type":"Point"}
}