{
  "type": "Feature",
  "properties": {
    "addr:full":"2963 Cobb Parkway Atlanta GA 30339",
    "addr:housenumber":"2963",
    "addr:postcode":"30339",
    "addr:street":"Cobb Parkway",
    "iso:country":"US",
    "sg:address":"2963 Cobb Parkway",
    "sg:city":"Atlanta",
    "sg:classifiers":[
        {
            "category":"Professional",
            "subcategory":"Computer Services",
            "type":"Services"
        }
    ],
    "sg:phone":"+1 770 953 4467",
    "sg:postcode":"30339",
    "sg:province":"GA",
    "sg:tags":[
        "stereo",
        "installation"
    ],
    "wof:name":"Circuit City",
    "wof:placetype":"venue"
},
  "geometry": {"coordinates":[-84.459828,33.880007],"type":"Point"}
}