{
  "type": "Feature",
  "properties": {
    "addr:full":"2694 Wesley Chapel Rd Decatur GA 30034",
    "addr:housenumber":"2694",
    "addr:postcode":"30034",
    "addr:street":"Wesley Chapel Rd",
    "iso:country":"US",
    "sg:address":"2694 Wesley Chapel Rd",
    "sg:city":"Decatur",
    "sg:classifiers":[
        {
            "category":"Manufacturing",
            "subcategory":"Printing",
            "type":"Manufacturing & Wholesale Goods"
        }
    ],
    "sg:phone":"+1 404 289 9026",
    "sg:postcode":"30034",
    "sg:province":"GA",
    "sg:tags":[
        "printer",
        "offset"
    ],
    "wof:name":"Mr Quick Copy & Printing",
    "wof:placetype":"venue"
},
  "geometry": {"coordinates":[-84.218386,33.707089],"type":"Point"}
}