{
  "type": "Feature",
  "properties": {
    "addr:full":"786 Madison Ln Cairo GA 39828",
    "addr:housenumber":"786",
    "addr:postcode":"39828",
    "addr:street":"Madison Ln",
    "iso:country":"US",
    "sg:address":"786 Madison Ln",
    "sg:city":"Cairo",
    "sg:classifiers":[
        {
            "category":"Organizations",
            "subcategory":"Religious Organization",
            "type":"Services"
        }
    ],
    "sg:phone":"+1 229 377 5262",
    "sg:postcode":"39828",
    "sg:province":"GA",
    "sg:tags":[
        "place",
        "worship",
        "church"
    ],
    "wof:name":"Full Gospel Church",
    "wof:placetype":"venue"
},
  "geometry": {"coordinates":[-84.219855,30.866658],"type":"Point"}
}