{
  "type": "Feature",
  "properties": {
    "iso:country":"US",
    "sg:address":"6105 Ball Ground Rd",
    "sg:city":"Ball Ground",
    "sg:classifiers":[
        {
            "category":"Shopping",
            "type":"Retail Goods"
        }
    ],
    "sg:phone":"+1 770 887 3171",
    "sg:postcode":"30107",
    "sg:province":"GA",
    "sg:tags":[
        "merchandise"
    ],
    "wof:name":"Gibbs Monument Company",
    "wof:placetype":"venue"
},
  "geometry": {"coordinates":[-84.298931,34.279029],"type":"Point"}
}