{
  "type": "Feature",
  "properties": {
    "addr:full":"735 Brand South Trl Lawrenceville GA 30045",
    "addr:housenumber":"735",
    "addr:postcode":"30045",
    "addr:street":"Brand South Trl",
    "iso:country":"US",
    "sg:address":"735 Brand South Trl",
    "sg:city":"Lawrenceville",
    "sg:classifiers":[
        {
            "category":"Health Services",
            "subcategory":"Clinic",
            "type":"Services"
        },
        {
            "category":"Health Services",
            "subcategory":"Health Practitioner",
            "type":"Services"
        }
    ],
    "sg:phone":"+1 770 963 4650",
    "sg:postcode":"30045",
    "sg:province":"GA",
    "wof:name":"Healthy Lotus LLC",
    "wof:placetype":"venue"
},
  "geometry": {"coordinates":[-83.96998600000001,33.934365],"type":"Point"}
}