{
  "type": "Feature",
  "properties": {
    "iso:country":"US",
    "sg:address":"1825 Mall of Georgia Blvd",
    "sg:city":"Buford",
    "sg:classifiers":[
        {
            "category":"Food & Beverages",
            "subcategory":"Groceries & Convenience Stores",
            "type":"Retail Goods"
        }
    ],
    "sg:phone":"+1 678 733 5426",
    "sg:postcode":"30519",
    "sg:province":"GA",
    "sg:tags":[
        "do-it-yourself"
    ],
    "sg:website":"www.genghisgrill.com",
    "wof:name":"Genghis Grill",
    "wof:placetype":"venue"
},
  "geometry": {"coordinates":[-83.990436,34.060774],"type":"Point"}
}