{
  "type": "Feature",
  "properties": {
    "addr:full":"1867 Catoosa Pkwy Tunnel Hill GA 30755",
    "addr:housenumber":"1867",
    "addr:postcode":"30755",
    "addr:street":"Catoosa Pkwy Tunnel Hill",
    "iso:country":"US",
    "sg:address":"1867 Catoosa Pkwy",
    "sg:city":"Tunnel Hill",
    "sg:classifiers":[
        {
            "category":"Manufacturing",
            "subcategory":"Lumber",
            "type":"Manufacturing & Wholesale Goods"
        }
    ],
    "sg:phone":"+1 706 965 6396",
    "sg:postcode":"30755",
    "sg:province":"GA",
    "sg:tags":[
        "logging"
    ],
    "wof:name":"L&L Logging",
    "wof:placetype":"venue"
},
  "geometry": {"coordinates":[-85.045495,34.899044],"type":"Point"}
}