{
  "type": "Feature",
  "properties": {
    "iso:country":"US",
    "sg:address":"8815 Ozell Rd",
    "sg:city":"Boston",
    "sg:classifiers":[
        {
            "category":"Farming",
            "subcategory":"Aquatic Farm",
            "type":"Manufacturing & Wholesale Goods"
        }
    ],
    "sg:phone":"+1 229 498 7308",
    "sg:postcode":"31626",
    "sg:province":"GA",
    "sg:tags":[
        "fish"
    ],
    "wof:name":"Duke Growers & Marketing",
    "wof:placetype":"venue"
},
  "geometry": {"coordinates":[-83.769313,30.849811],"type":"Point"}
}