{
  "type": "Feature",
  "properties": {
    "iso:country":"US",
    "sg:address":"4088 Cat Creek Rd",
    "sg:city":"Valdosta",
    "sg:classifiers":[
        {
            "category":"Real Estate",
            "subcategory":"Real Estate Operator",
            "type":"Services"
        }
    ],
    "sg:phone":"+1 229 242 6923",
    "sg:postcode":"31605",
    "sg:province":"GA",
    "sg:tags":[
        "mobile",
        "home",
        "site"
    ],
    "wof:name":"Kutzlis Mobile Home Park",
    "wof:placetype":"venue"
},
  "geometry": {"coordinates":[-83.242377,30.94613],"type":"Point"}
}