{
  "type": "Feature",
  "properties": {
    "addr:full":"112 Garden Hill Dr Albany GA 31705",
    "addr:housenumber":"112",
    "addr:postcode":"31705",
    "addr:street":"Garden Hill Dr",
    "iso:country":"US",
    "sg:address":"112 Garden Hill Dr",
    "sg:city":"Albany",
    "sg:classifiers":[
        {
            "category":"Professional",
            "subcategory":"Secretarial Services",
            "type":"Services"
        }
    ],
    "sg:phone":"+1 229 888 3867",
    "sg:postcode":"31705",
    "sg:province":"GA",
    "sg:tags":[
        "reporting"
    ],
    "wof:name":"Bettergrants",
    "wof:placetype":"venue"
},
  "geometry": {"coordinates":[-84.13421099999999,31.537726],"type":"Point"}
}