{
  "type": "Feature",
  "properties": {
    "addr:full":"111 Hickory Knoll Cumming GA 30040",
    "addr:housenumber":"111",
    "addr:postcode":"30040",
    "addr:street":"Hickory Knoll",
    "iso:country":"US",
    "sg:address":"111 Hickory Knoll",
    "sg:city":"Cumming",
    "sg:classifiers":[
        {
            "category":"Professional",
            "type":"Services"
        }
    ],
    "sg:phone":"+1 770 887 0145",
    "sg:postcode":"30040",
    "sg:province":"GA",
    "wof:name":"Larry D Deckard",
    "wof:placetype":"venue"
},
  "geometry": {"coordinates":[-84.150543,34.210427],"type":"Point"}
}