{
  "type": "Feature",
  "properties": {
    "addr:full":"5306 Buford Hwy NE Atlanta GA 30340",
    "addr:housenumber":"5306",
    "addr:postcode":"30340",
    "addr:street":"Buford Hwy Ne",
    "iso:country":"US",
    "sg:address":"5306 Buford Hwy NE",
    "sg:city":"Atlanta",
    "sg:classifiers":[
        {
            "category":"Banks & Credit Unions",
            "subcategory":"Financial Services",
            "type":"Services"
        }
    ],
    "sg:phone":"+1 770 457 4973",
    "sg:postcode":"30340",
    "sg:province":"GA",
    "sg:tags":[
        "cashing",
        "check"
    ],
    "wof:name":"Abc Check Cashing",
    "wof:placetype":"venue"
},
  "geometry": {"coordinates":[-84.281125,33.897187],"type":"Point"}
}