{
  "type": "Feature",
  "properties": {
    "addr:full":"65 Wilmington Dr Covington GA 30016",
    "addr:housenumber":"65",
    "addr:postcode":"30016",
    "addr:street":"Wilmington Dr",
    "iso:country":"US",
    "sg:address":"65 Wilmington Dr",
    "sg:city":"Covington",
    "sg:classifiers":[
        {
            "category":"Professional",
            "type":"Services"
        }
    ],
    "sg:phone":"+1 770 385 5781",
    "sg:postcode":"30016",
    "sg:province":"GA",
    "wof:name":"Westchristopher",
    "wof:placetype":"venue"
},
  "geometry": {"coordinates":[-83.8927,33.460174],"type":"Point"}
}