{
  "type": "Feature",
  "properties": {
    "iso:country":"US",
    "sg:address":"296 W Wesley Rd NW",
    "sg:city":"Atlanta",
    "sg:classifiers":[
        {
            "category":"Professional",
            "subcategory":"Art Services",
            "type":"Services"
        }
    ],
    "sg:phone":"+1 404 605 0545",
    "sg:postcode":"30305",
    "sg:province":"GA",
    "sg:tags":[
        "interior",
        "designer",
        "decorator"
    ],
    "wof:name":"G H Ideas",
    "wof:placetype":"venue"
},
  "geometry": {"coordinates":[-84.397586,33.828666],"type":"Point"}
}