{
  "type": "Feature",
  "properties": {
    "addr:full":"5435 Sugarloaf Pkwy Lawrenceville GA 30043",
    "addr:housenumber":"5435",
    "addr:postcode":"30043",
    "addr:street":"Sugarloaf Pkwy",
    "iso:country":"US",
    "sg:address":"5435 Sugarloaf Pkwy",
    "sg:city":"Lawrenceville",
    "sg:classifiers":[
        {
            "category":"Professional",
            "subcategory":"Employment Agencies",
            "type":"Services"
        }
    ],
    "sg:phone":"+1 770 962 5800",
    "sg:postcode":"30043",
    "sg:province":"GA",
    "wof:name":"Davis Companies",
    "wof:placetype":"venue"
},
  "geometry": {"coordinates":[-84.06950399999999,33.968201],"type":"Point"}
}