{
  "type": "Feature",
  "properties": {
    "addr:full":"1720 Shallowford Rd Marietta GA 30066",
    "addr:housenumber":"1720",
    "addr:postcode":"30066",
    "addr:street":"Shallowford Rd",
    "iso:country":"US",
    "sg:address":"1720 Shallowford Rd",
    "sg:city":"Marietta",
    "sg:classifiers":[
        {
            "category":"Building & Trades",
            "subcategory":"Construction",
            "type":"Services"
        }
    ],
    "sg:phone":"+1 770 592 1516",
    "sg:postcode":"30066",
    "sg:province":"GA",
    "sg:tags":[
        "hanging",
        "contractor"
    ],
    "wof:name":"Darryl Landfried Wallcoverings",
    "wof:placetype":"venue"
},
  "geometry": {"coordinates":[-84.505511,34.050533],"type":"Point"}
}