{
  "type": "Feature",
  "properties": {
    "addr:full":"2421 Stuart Ave Albany GA 31707",
    "addr:housenumber":"2421",
    "addr:postcode":"31707",
    "addr:street":"Stuart Ave",
    "iso:country":"US",
    "sg:address":"2421 Stuart Ave",
    "sg:city":"Albany",
    "sg:classifiers":[
        {
            "category":"Autos & Motor Vehicles",
            "subcategory":"Auto Supplies",
            "type":"Retail Goods"
        },
        {
            "category":"Retail",
            "subcategory":"Auto Repair",
            "type":"Services"
        }
    ],
    "sg:phone":"+1 229 439 9223",
    "sg:postcode":"31707",
    "sg:province":"GA",
    "sg:tags":[
        "equipment",
        "racing",
        "automobile",
        "car",
        "general"
    ],
    "wof:name":"B & M Automotives",
    "wof:placetype":"venue"
},
  "geometry": {"coordinates":[-84.21214500000001,31.613501],"type":"Point"}
}