{
  "type": "Feature",
  "properties": {
    "addr:full":"701 Courtland Dr Hinesville GA 31313",
    "addr:housenumber":"701",
    "addr:postcode":"31313",
    "addr:street":"Courtland Dr",
    "iso:country":"US",
    "sg:address":"701 Courtland Dr",
    "sg:city":"Hinesville",
    "sg:classifiers":[
        {
            "category":"Retail",
            "subcategory":"Auto Repair",
            "type":"Services"
        }
    ],
    "sg:phone":"+1 912 876 5500",
    "sg:postcode":"31313",
    "sg:province":"GA",
    "sg:tags":[
        "body",
        "painting",
        "repairing",
        "automobile"
    ],
    "wof:name":"Mach 1 Body Shop",
    "wof:placetype":"venue"
},
  "geometry": {"coordinates":[-81.597717,31.8291],"type":"Point"}
}