{
  "type": "Feature",
  "properties": {
    "addr:full":"226 Early Hutchinson Rd Tifton GA 31793",
    "addr:housenumber":"226",
    "addr:postcode":"31793",
    "addr:street":"Early Hutchinson Rd",
    "iso:country":"US",
    "sg:address":"226 Early Hutchinson Rd",
    "sg:city":"Tifton",
    "sg:classifiers":[
        {
            "category":"Freight",
            "type":"Transportation"
        }
    ],
    "sg:phone":"+1 229 556 9744",
    "sg:postcode":"31793",
    "sg:province":"GA",
    "sg:tags":[
        "mobile",
        "home"
    ],
    "wof:name":"Pinnacle Transportation",
    "wof:placetype":"venue"
},
  "geometry": {"coordinates":[-83.581006,31.503773],"type":"Point"}
}