{
  "type": "Feature",
  "properties": {
    "addr:full":"216 Hartwell Rd Lavonia GA 30553",
    "addr:housenumber":"216",
    "addr:postcode":"30553",
    "addr:street":"Hartwell Rd",
    "iso:country":"US",
    "sg:address":"216 Hartwell Rd",
    "sg:city":"Lavonia",
    "sg:classifiers":[
        {
            "category":"Professional",
            "type":"Services"
        }
    ],
    "sg:phone":"+1 706 245 9607",
    "sg:postcode":"30553",
    "sg:province":"GA",
    "sg:tags":[
        "establishment"
    ],
    "wof:name":"Athens Technical Clg Franklin",
    "wof:placetype":"venue"
},
  "geometry": {"coordinates":[-83.095534,34.431967],"type":"Point"}
}