{
  "type": "Feature",
  "properties": {
    "addr:full":"2805 Bull St Savannah GA 31405",
    "addr:housenumber":"2805",
    "addr:postcode":"31405",
    "addr:street":"Bull St",
    "iso:country":"US",
    "sg:address":"2805 Bull St",
    "sg:city":"Savannah",
    "sg:classifiers":[
        {
            "category":"Wholesale",
            "subcategory":"Farm Supplies",
            "type":"Manufacturing & Wholesale Goods"
        }
    ],
    "sg:phone":"+1 912 231 0838",
    "sg:postcode":"31405",
    "sg:province":"GA",
    "sg:tags":[
        "pet",
        "feed",
        "store"
    ],
    "wof:name":"Victory Feed & Seed Co",
    "wof:placetype":"venue"
},
  "geometry": {"coordinates":[-81.102236,32.052058],"type":"Point"}
}