{
  "type": "Feature",
  "properties": {
    "addr:full":"989 Spring St NW Atlanta GA 30309",
    "addr:housenumber":"989",
    "addr:postcode":"30309",
    "addr:street":"Spring St Nw",
    "iso:country":"US",
    "sg:address":"989 Spring St NW",
    "sg:city":"Atlanta",
    "sg:classifiers":[
        {
            "category":"Restaurant",
            "type":"Food & Drink"
        }
    ],
    "sg:menulink":"http://www.allmenus.com/ga/atlanta/163267-rallys/menu/",
    "sg:phone":"+1 404 892 7717",
    "sg:postcode":"30309",
    "sg:province":"GA",
    "sg:tags":[
        "sandwich",
        "dog",
        "burger",
        "hot",
        "wrap",
        "american"
    ],
    "wof:name":"Rally's",
    "wof:placetype":"venue"
},
  "geometry": {"coordinates":[-84.389132,33.781333],"type":"Point"}
}