{
  "type": "Feature",
  "properties": {
    "iso:country":"US",
    "sg:address":"1093 W Ave SW Apt 339",
    "sg:city":"Atlanta",
    "sg:classifiers":[
        {
            "category":"Real Estate",
            "subcategory":"Real Estate Operator",
            "type":"Services"
        }
    ],
    "sg:phone":"+1 404 614 0808",
    "sg:postcode":"30315",
    "sg:province":"GA",
    "sg:tags":[
        "apartment"
    ],
    "sg:website":"www.signaturemanagement.com",
    "wof:name":"The Crogman School Lofts Apartments",
    "wof:placetype":"venue"
},
  "geometry": {"coordinates":[-84.39582900000001,33.724848],"type":"Point"}
}