{
  "type": "Feature",
  "properties": {
    "iso:country":"US",
    "sg:address":"170 Glynn St S",
    "sg:city":"Fayetteville",
    "sg:classifiers":[
        {
            "category":"Professional",
            "subcategory":"Advertising",
            "type":"Services"
        }
    ],
    "sg:phone":"+1 770 486 1772",
    "sg:postcode":"30214",
    "sg:province":"GA",
    "sg:tags":[
        "publisher",
        "representative"
    ],
    "wof:name":"Prepared Foods Magazines",
    "wof:placetype":"venue"
},
  "geometry": {"coordinates":[-84.455003,33.447201],"type":"Point"}
}