{
  "type": "Feature",
  "properties": {
    "iso:country":"US",
    "sg:address":"91 Boyd Rd SW",
    "sg:city":"Rome",
    "sg:classifiers":[
        {
            "category":"Real Estate",
            "subcategory":"Real Estate Agent",
            "type":"Services"
        }
    ],
    "sg:phone":"+1 706 291 1563",
    "sg:postcode":"30161",
    "sg:province":"GA",
    "wof:name":"Ronald D Dempsey Real Estate",
    "wof:placetype":"venue"
},
  "geometry": {"coordinates":[-85.305486,34.193019],"type":"Point"}
}