{
  "type": "Feature",
  "properties": {
    "addr:full":"104 Whitehead Rd Athens GA 30606",
    "addr:housenumber":"104",
    "addr:postcode":"30606",
    "addr:street":"Whitehead Rd",
    "iso:country":"US",
    "sg:address":"104 Whitehead Rd",
    "sg:city":"Athens",
    "sg:classifiers":[
        {
            "category":"Retail",
            "subcategory":"Auto Repair",
            "type":"Services"
        }
    ],
    "sg:phone":"+1 706 546 5773",
    "sg:postcode":"30606",
    "sg:province":"GA",
    "sg:tags":[
        "body",
        "automobile",
        "painting",
        "general"
    ],
    "wof:name":"A C Auto Inc",
    "wof:placetype":"venue"
},
  "geometry": {"coordinates":[-83.43059599999999,33.989596],"type":"Point"}
}