{
  "type": "Feature",
  "properties": {
    "iso:country":"US",
    "sg:address":"600 Peachtree St NE",
    "sg:city":"Atlanta",
    "sg:classifiers":[
        {
            "category":"Insurance",
            "subcategory":"Hazard Insurance",
            "type":"Services"
        }
    ],
    "sg:phone":"+1 404 885 3106",
    "sg:postcode":"30308",
    "sg:province":"GA",
    "wof:name":"Korhonen, Jana L",
    "wof:placetype":"venue"
},
  "geometry": {"coordinates":[-84.385009,33.770909],"type":"Point"}
}