{
  "type": "Feature",
  "properties": {
    "addr:full":"5652 Fairburn Rd Douglasville GA 30134",
    "addr:housenumber":"5652",
    "addr:postcode":"30134",
    "addr:street":"Fairburn Rd",
    "iso:country":"US",
    "sg:address":"5652 Fairburn Rd",
    "sg:city":"Douglasville",
    "sg:classifiers":[
        {
            "category":"Autos & Motor Vehicles",
            "subcategory":"Fuel & Gas Station",
            "type":"Retail Goods"
        }
    ],
    "sg:phone":"+1 770 949 3378",
    "sg:postcode":"30134",
    "sg:province":"GA",
    "sg:tags":[
        "oil"
    ],
    "wof:name":"Shell",
    "wof:placetype":"venue"
},
  "geometry": {"coordinates":[-84.72927199999999,33.751071],"type":"Point"}
}