{
  "type": "Feature",
  "properties": {
    "iso:country":"US",
    "sg:address":"5 Fite St",
    "sg:city":"Cartersville",
    "sg:classifiers":[
        {
            "category":"Health Services",
            "subcategory":"Nursing And Care Facility",
            "type":"Services"
        }
    ],
    "sg:phone":"+1 770 382 2002",
    "sg:postcode":"30120",
    "sg:province":"GA",
    "sg:tags":[
        "personal"
    ],
    "wof:name":"Fite Living Centre",
    "wof:placetype":"venue"
},
  "geometry": {"coordinates":[-84.803499,34.1653],"type":"Point"}
}