{
  "type": "Feature",
  "properties": {
    "iso:country":"US",
    "sg:address":"4063 Northridge Way",
    "sg:city":"Norcross",
    "sg:classifiers":[
        {
            "category":"Freight",
            "type":"Transportation"
        }
    ],
    "sg:phone":"+1 770 316 3754",
    "sg:postcode":"30093",
    "sg:province":"GA",
    "sg:tags":[
        "mover"
    ],
    "wof:name":"A J Moving Svc",
    "wof:placetype":"venue"
},
  "geometry": {"coordinates":[-84.13303500000001,33.929129],"type":"Point"}
}