{
  "type": "Feature",
  "properties": {
    "addr:full":"120 Deerwood Trl Sharpsburg GA 30277",
    "addr:housenumber":"120",
    "addr:postcode":"30277",
    "addr:street":"Deerwood Trl",
    "iso:country":"US",
    "sg:address":"120 Deerwood Trl",
    "sg:city":"Sharpsburg",
    "sg:classifiers":[
        {
            "category":"Retail",
            "subcategory":"Veterinary Services",
            "type":"Services"
        }
    ],
    "sg:phone":"+1 770 502 1050",
    "sg:postcode":"30277",
    "sg:province":"GA",
    "sg:tags":[
        "specialty"
    ],
    "wof:name":"All Creatures Great & Small",
    "wof:placetype":"venue"
},
  "geometry": {"coordinates":[-84.64398300000001,33.39285],"type":"Point"}
}