{
  "type": "Feature",
  "properties": {
    "iso:country":"US",
    "sg:address":"2906 Abelia Dr",
    "sg:city":"Augusta",
    "sg:classifiers":[
        {
            "category":"Health Services",
            "subcategory":"Nursing And Care Facility",
            "type":"Services"
        }
    ],
    "sg:phone":"+1 706 790 5455",
    "sg:postcode":"30906",
    "sg:province":"GA",
    "wof:name":"Dunbars Personal Care",
    "wof:placetype":"venue"
},
  "geometry": {"coordinates":[-82.009716,33.416732],"type":"Point"}
}