{
  "type": "Feature",
  "properties": {
    "addr:full":"278 Lumpkin St Winder GA 30680",
    "addr:housenumber":"278",
    "addr:postcode":"30680",
    "addr:street":"Lumpkin St",
    "iso:country":"US",
    "sg:address":"278 Lumpkin St",
    "sg:city":"Winder",
    "sg:classifiers":[
        {
            "category":"Education",
            "subcategory":"Special Training",
            "type":"Public Place"
        }
    ],
    "sg:phone":"+1 770 867 2628",
    "sg:postcode":"30680",
    "sg:province":"GA",
    "sg:tags":[
        "center"
    ],
    "wof:name":"Smarty Pants Montessori Inc",
    "wof:placetype":"venue"
},
  "geometry": {"coordinates":[-83.70694399999999,34.000336],"type":"Point"}
}