{
  "type": "Feature",
  "properties": {
    "addr:full":"2192 Mount Zion Pkwy Morrow GA 30260",
    "addr:housenumber":"2192",
    "addr:postcode":"30260",
    "addr:street":"Mount Zion Pkwy",
    "iso:country":"US",
    "sg:address":"2192 Mount Zion Pkwy",
    "sg:city":"Morrow",
    "sg:classifiers":[
        {
            "category":"Professional",
            "subcategory":"Management & Consulting",
            "type":"Services"
        }
    ],
    "sg:phone":"+1 678 485 4199",
    "sg:postcode":"30260",
    "sg:province":"GA",
    "sg:tags":[
        "business"
    ],
    "wof:name":"Mira Network Solutions",
    "wof:placetype":"venue"
},
  "geometry": {"coordinates":[-84.310731,33.555878],"type":"Point"}
}