{
  "type": "Feature",
  "properties": {
    "iso:country":"US",
    "sg:address":"210 River Oak Dr",
    "sg:city":"Fayetteville",
    "sg:classifiers":[
        {
            "category":"Building & Trades",
            "subcategory":"Construction",
            "type":"Services"
        }
    ],
    "sg:phone":"+1 770 460 1379",
    "sg:postcode":"30274",
    "sg:province":"GA",
    "sg:tags":[
        "floor",
        "laying",
        "contractor"
    ],
    "wof:name":"B & B Hardwood Floors",
    "wof:placetype":"venue"
},
  "geometry": {"coordinates":[-84.400902,33.576911],"type":"Point"}
}