{
  "type": "Feature",
  "properties": {
    "addr:full":"35 Forsyth St SW Atlanta GA 30303",
    "addr:housenumber":"35",
    "addr:postcode":"30303",
    "addr:street":"Forsyth St Sw",
    "iso:country":"US",
    "sg:address":"35 Forsyth St SW",
    "sg:city":"Atlanta",
    "sg:classifiers":[
        {
            "category":"Professional",
            "subcategory":"Business Services",
            "type":"Services"
        }
    ],
    "sg:phone":"+1 404 681 2642",
    "sg:postcode":"30303",
    "sg:province":"GA",
    "sg:tags":[
        "management"
    ],
    "wof:name":"Perseco",
    "wof:placetype":"venue"
},
  "geometry": {"coordinates":[-84.392679,33.753752],"type":"Point"}
}