{
  "type": "Feature",
  "properties": {
    "addr:full":"1943 Mineral Springs Rd Hoschton GA 30548",
    "addr:housenumber":"1943",
    "addr:postcode":"30548",
    "addr:street":"Mineral Springs Rd",
    "iso:country":"US",
    "sg:address":"1943 Mineral Springs Rd",
    "sg:city":"Hoschton",
    "sg:classifiers":[
        {
            "category":"Building & Trades",
            "subcategory":"Electrical",
            "type":"Services"
        }
    ],
    "sg:phone":"+1 770 932 9422",
    "sg:postcode":"30548",
    "sg:province":"GA",
    "sg:tags":[
        "electrical",
        "contractor"
    ],
    "wof:name":"Delta Electric Co Inc",
    "wof:placetype":"venue"
},
  "geometry": {"coordinates":[-83.884252,34.067083],"type":"Point"}
}