{
  "type": "Feature",
  "properties": {
    "addr:full":"4411 Covington Hwy Decatur GA 30035",
    "addr:housenumber":"4411",
    "addr:postcode":"30035",
    "addr:street":"Covington Hwy",
    "iso:country":"US",
    "sg:address":"4411 Covington Hwy",
    "sg:city":"Decatur",
    "sg:classifiers":[
        {
            "category":"Insurance",
            "subcategory":"Insurance Agent",
            "type":"Services"
        }
    ],
    "sg:phone":"+1 404 284 1555",
    "sg:postcode":"30035",
    "sg:province":"GA",
    "sg:tags":[
        "agency"
    ],
    "wof:name":"Montgomery Insurance Agency",
    "wof:placetype":"venue"
},
  "geometry": {"coordinates":[-84.222189,33.747016],"type":"Point"}
}