{
  "type": "Feature",
  "properties": {
    "addr:full":"2170 Satellite Blvd Duluth GA 30097",
    "addr:housenumber":"2170",
    "addr:postcode":"30097",
    "addr:street":"Satellite Blvd",
    "iso:country":"US",
    "sg:address":"2170 Satellite Blvd",
    "sg:city":"Duluth",
    "sg:classifiers":[
        {
            "category":"Professional",
            "subcategory":"Employment Agencies",
            "type":"Services"
        }
    ],
    "sg:phone":"+1 678 473 1313",
    "sg:postcode":"30097",
    "sg:province":"GA",
    "wof:name":"Accountemps",
    "wof:placetype":"venue"
},
  "geometry": {"coordinates":[-84.092697,33.983398],"type":"Point"}
}