{
  "type": "Feature",
  "properties": {
    "addr:full":"165 Breakstone Dr Dahlonega GA 30533",
    "addr:housenumber":"165",
    "addr:postcode":"30533",
    "addr:street":"Breakstone Dr",
    "iso:country":"US",
    "sg:address":"165 Breakstone Dr",
    "sg:city":"Dahlonega",
    "sg:classifiers":[
        {
            "category":"Wholesale",
            "subcategory":"Electrical",
            "type":"Manufacturing & Wholesale Goods"
        }
    ],
    "sg:phone":"+1 706 864 9684",
    "sg:postcode":"30533",
    "sg:province":"GA",
    "sg:tags":[
        "equipment"
    ],
    "wof:name":"Siemens Energy & Automation",
    "wof:placetype":"venue"
},
  "geometry": {"coordinates":[-83.988326,34.440474],"type":"Point"}
}