{
  "type": "Feature",
  "properties": {
    "iso:country":"US",
    "sg:address":"2265 Roswell Rd",
    "sg:city":"Marietta",
    "sg:classifiers":[
        {
            "category":"Arena",
            "subcategory":"Sports Club",
            "type":"Entertainment"
        }
    ],
    "sg:phone":"+1 770 509 2240",
    "sg:postcode":"30062",
    "sg:province":"GA",
    "sg:tags":[
        "ticket",
        "sale"
    ],
    "wof:name":"Mercy Seat Assembly",
    "wof:placetype":"venue"
},
  "geometry": {"coordinates":[-84.48594799999999,33.973078],"type":"Point"}
}