{
  "type": "Feature",
  "properties": {
    "iso:country":"US",
    "sg:address":"107 E Back St",
    "sg:city":"Savannah",
    "sg:classifiers":[
        {
            "category":"Building & Trades",
            "subcategory":"Construction",
            "type":"Services"
        }
    ],
    "sg:phone":"+1 912 925 9174",
    "sg:postcode":"31419",
    "sg:province":"GA",
    "sg:tags":[
        "general",
        "contractor"
    ],
    "wof:name":"PINCO",
    "wof:placetype":"venue"
},
  "geometry": {"coordinates":[-81.15253800000001,31.936523],"type":"Point"}
}