{
  "type": "Feature",
  "properties": {
    "addr:full":"3410 Bold Springs Rd Monroe GA 30656",
    "addr:housenumber":"3410",
    "addr:postcode":"30656",
    "addr:street":"Bold Springs Rd",
    "iso:country":"US",
    "sg:address":"3410 Bold Springs Rd",
    "sg:city":"Monroe",
    "sg:classifiers":[
        {
            "category":"Insurance",
            "subcategory":"Title Insurance",
            "type":"Services"
        },
        {
            "category":"Real Estate",
            "subcategory":"Real Estate Services",
            "type":"Services"
        }
    ],
    "sg:phone":"+1 770 267 2727",
    "sg:postcode":"30656",
    "sg:province":"GA",
    "sg:tags":[
        "abstract"
    ],
    "wof:name":"Atlanta Title Abstractors Inc",
    "wof:placetype":"venue"
},
  "geometry": {"coordinates":[-83.758715,33.872538],"type":"Point"}
}