{
  "type": "Feature",
  "properties": {
    "addr:full":"900 Hall St NW Atlanta GA 30318",
    "addr:housenumber":"900",
    "addr:postcode":"30318",
    "addr:street":"Hall St Nw",
    "iso:country":"US",
    "sg:address":"900 Hall St NW",
    "sg:city":"Atlanta",
    "sg:classifiers":[
        {
            "category":"Building & Trades",
            "subcategory":"Construction",
            "type":"Services"
        }
    ],
    "sg:phone":"+1 404 792 2299",
    "sg:postcode":"30318",
    "sg:province":"GA",
    "sg:tags":[
        "home",
        "improvement"
    ],
    "wof:name":"Alpha & Omega Complete Mntnc",
    "wof:placetype":"venue"
},
  "geometry": {"coordinates":[-84.4658,33.781261],"type":"Point"}
}