{
  "type": "Feature",
  "properties": {
    "addr:full":"2391 Peachtree Rd NE Atlanta GA 30305",
    "addr:housenumber":"2391",
    "addr:postcode":"30305",
    "addr:street":"Peachtree Rd Ne",
    "iso:country":"US",
    "sg:address":"2391 Peachtree Rd NE",
    "sg:city":"Atlanta",
    "sg:classifiers":[
        {
            "category":"Personal",
            "subcategory":"Nail Salon",
            "type":"Services"
        }
    ],
    "sg:phone":"+1 404 846 3308",
    "sg:postcode":"30305",
    "sg:province":"GA",
    "wof:name":"Nail Shawdow",
    "wof:placetype":"venue"
},
  "geometry": {"coordinates":[-84.384399,33.8325],"type":"Point"}
}