{
  "type": "Feature",
  "properties": {
    "iso:country":"US",
    "sg:address":"2888 Buford Hwy NE",
    "sg:city":"Atlanta",
    "sg:classifiers":[
        {
            "category":"Restaurant",
            "type":"Food & Drink"
        }
    ],
    "sg:phone":"+1 404 320 7756",
    "sg:postcode":"30329",
    "sg:province":"GA",
    "sg:tags":[
        "middle",
        "eastern"
    ],
    "sg:website":"Lawrencescafe.com",
    "wof:name":"Lawrence's Cafe & Restaurant",
    "wof:placetype":"venue"
},
  "geometry": {"coordinates":[-84.341605,33.832823],"type":"Point"}
}