{
  "type": "Feature",
  "properties": {
    "iso:country":"US",
    "sg:address":"7267 Woodcreek Way",
    "sg:city":"Douglasville",
    "sg:classifiers":[
        {
            "category":"Manufacturing",
            "subcategory":"Signs",
            "type":"Manufacturing & Wholesale Goods"
        }
    ],
    "sg:phone":"+1 770 577 7500",
    "sg:postcode":"30134",
    "sg:province":"GA",
    "sg:tags":[
        "specialty",
        "mfg"
    ],
    "wof:name":"Fx Signs",
    "wof:placetype":"venue"
},
  "geometry": {"coordinates":[-84.764838,33.76321],"type":"Point"}
}