{
  "type": "Feature",
  "properties": {
    "addr:full":"2706 2nd Ave Columbus GA 31904",
    "addr:housenumber":"2706",
    "addr:postcode":"31904",
    "addr:street":"2Nd Ave",
    "iso:country":"US",
    "sg:address":"2706 2nd Ave",
    "sg:city":"Columbus",
    "sg:classifiers":[
        {
            "category":"Wholesale",
            "subcategory":"Office Equipment",
            "type":"Manufacturing & Wholesale Goods"
        }
    ],
    "sg:phone":"+1 706 327 0732",
    "sg:postcode":"31904",
    "sg:province":"GA",
    "sg:tags":[
        "machine",
        "mailing"
    ],
    "sg:website":"www.a-1postagemeters.com",
    "wof:name":"A 1 Postage Meters & Shipping",
    "wof:placetype":"venue"
},
  "geometry": {"coordinates":[-84.990039,32.489741],"type":"Point"}
}