{
  "type": "Feature",
  "properties": {
    "addr:full":"307 Church St Ste A Lagrange GA 30240",
    "addr:housenumber":"307",
    "addr:postcode":"30240",
    "addr:street":"Church St Ste A Lagrange",
    "iso:country":"US",
    "sg:address":"307 Church St Ste A",
    "sg:city":"Lagrange",
    "sg:classifiers":[
        {
            "category":"Professional",
            "subcategory":"Lawyer & Legal Services",
            "type":"Services"
        }
    ],
    "sg:phone":"+1 706 812 1224",
    "sg:postcode":"30240",
    "sg:province":"GA",
    "sg:tags":[
        "plan"
    ],
    "wof:name":"Daniel W Lee P C",
    "wof:placetype":"venue"
},
  "geometry": {"coordinates":[-85.03196699999999,33.042109],"type":"Point"}
}