{
  "type": "Feature",
  "properties": {
    "iso:country":"US",
    "sg:address":"3004 Kaley Dr NW",
    "sg:city":"Kennesaw",
    "sg:classifiers":[
        {
            "category":"Professional",
            "subcategory":"Computer Services",
            "type":"Services"
        }
    ],
    "sg:phone":"+1 770 422 4066",
    "sg:postcode":"30152",
    "sg:province":"GA",
    "sg:tags":[
        "datum"
    ],
    "wof:name":"Cyberzign",
    "wof:placetype":"venue"
},
  "geometry": {"coordinates":[-84.63914800000001,34.015613],"type":"Point"}
}