{
  "type": "Feature",
  "properties": {
    "iso:country":"US",
    "sg:address":"1297 Ficklen Church Way",
    "sg:city":"Canton",
    "sg:classifiers":[
        {
            "category":"Professional",
            "type":"Services"
        }
    ],
    "sg:phone":"+1 770 704 7984",
    "sg:postcode":"30114",
    "sg:province":"GA",
    "wof:name":"Lanier Outdoors Inc",
    "wof:placetype":"venue"
},
  "geometry": {"coordinates":[-84.61095,34.211499],"type":"Point"}
}