{
  "type": "Feature",
  "properties": {
    "addr:full":"6475 Roswell Rd NE Atlanta GA 30328",
    "addr:housenumber":"6475;rd",
    "addr:postcode":"30328",
    "addr:street":"Roswell;Ne",
    "iso:country":"US",
    "sg:address":"6475 Roswell Rd NE",
    "sg:city":"Atlanta",
    "sg:classifiers":[
        {
            "category":"Autos & Motor Vehicles",
            "subcategory":"Automobile Sales",
            "type":"Retail Goods"
        },
        {
            "category":"Banks & Credit Unions",
            "subcategory":"Financial Services",
            "type":"Services"
        },
        {
            "category":"Retail",
            "subcategory":"Auto Repair",
            "type":"Services"
        }
    ],
    "sg:phone":"+1 404 256 3392",
    "sg:postcode":"30328",
    "sg:province":"GA",
    "sg:tags":[
        "financing",
        "used",
        "car",
        "truck",
        "new"
    ],
    "sg:website":"www.sandyspringstoyota.com",
    "wof:name":"Sandy Springs Toyota",
    "wof:placetype":"venue"
},
  "geometry": {"coordinates":[-84.37997799999999,33.931784],"type":"Point"}
}