{
  "type": "Feature",
  "properties": {
    "iso:country":"US",
    "sg:address":"4 Falcon Dr",
    "sg:city":"Peachtree City",
    "sg:classifiers":[
        {
            "category":"Professional",
            "type":"Services"
        }
    ],
    "sg:phone":"+1 770 486 9629",
    "sg:postcode":"30269",
    "sg:province":"GA",
    "wof:name":"Nws Forecast Ofc",
    "wof:placetype":"venue"
},
  "geometry": {"coordinates":[-84.56849099999999,33.360443],"type":"Point"}
}