{
  "type": "Feature",
  "properties": {
    "addr:full":"4246 Smithsonia Ct Tucker GA 30084",
    "addr:housenumber":"4246",
    "addr:postcode":"30084",
    "addr:street":"Smithsonia Ct",
    "iso:country":"US",
    "sg:address":"4246 Smithsonia Ct",
    "sg:city":"Tucker",
    "sg:classifiers":[
        {
            "category":"Professional",
            "subcategory":"Accounting & Tax Preparation",
            "type":"Services"
        }
    ],
    "sg:phone":"+1 770 621 9122",
    "sg:postcode":"30084",
    "sg:province":"GA",
    "sg:tags":[
        "consulting"
    ],
    "wof:name":"Accucount Consulting",
    "wof:placetype":"venue"
},
  "geometry": {"coordinates":[-84.213775,33.869995],"type":"Point"}
}