{
  "type": "Feature",
  "properties": {
    "addr:full":"139 Bull St Savannah GA 31401",
    "addr:housenumber":"139",
    "addr:postcode":"31401",
    "addr:street":"Bull St",
    "iso:country":"US",
    "sg:address":"139 Bull St",
    "sg:city":"Savannah",
    "sg:classifiers":[
        {
            "category":"Professional",
            "subcategory":"Lawyer & Legal Services",
            "type":"Services"
        }
    ],
    "sg:phone":"+1 912 236 8434",
    "sg:postcode":"31401",
    "sg:province":"GA",
    "wof:name":"Bowen Tmmy L Attrney At Law PC",
    "wof:placetype":"venue"
},
  "geometry": {"coordinates":[-81.092539,32.07755],"type":"Point"}
}