{
  "type": "Feature",
  "properties": {
    "iso:country":"US",
    "sg:address":"8536 Shoreline Dr",
    "sg:city":"Jonesboro",
    "sg:classifiers":[
        {
            "category":"Building & Trades",
            "subcategory":"Construction",
            "type":"Services"
        }
    ],
    "sg:phone":"+1 770 471 6220",
    "sg:postcode":"30236",
    "sg:province":"GA",
    "sg:tags":[
        "wallcoverings-installation",
        "wallpaper",
        "painting",
        "contractor"
    ],
    "wof:name":"Cardinal Painting",
    "wof:placetype":"venue"
},
  "geometry": {"coordinates":[-84.310451,33.519021],"type":"Point"}
}