{
  "type": "Feature",
  "properties": {
    "iso:country":"US",
    "sg:address":"305 Old Mill Cove",
    "sg:city":"Woodstock",
    "sg:classifiers":[
        {
            "category":"Retail",
            "subcategory":"Repair Shop",
            "type":"Services"
        }
    ],
    "sg:phone":"+1 770 410 1622",
    "sg:postcode":"30188",
    "sg:province":"GA",
    "wof:name":"Frame It Yourself Inc",
    "wof:placetype":"venue"
},
  "geometry": {"coordinates":[-84.410421,34.15256],"type":"Point"}
}