{
  "type": "Feature",
  "properties": {
    "addr:full":"110 Wheat Dr Dalton GA 30721",
    "addr:housenumber":"110",
    "addr:postcode":"30721",
    "addr:street":"Wheat Dr",
    "iso:country":"US",
    "sg:address":"110 Wheat Dr",
    "sg:city":"Dalton",
    "sg:classifiers":[
        {
            "category":"Organizations",
            "subcategory":"Religious Organization",
            "type":"Services"
        }
    ],
    "sg:phone":"+1 706 694 4400",
    "sg:postcode":"30721",
    "sg:province":"GA",
    "wof:name":"Church",
    "wof:placetype":"venue"
},
  "geometry": {"coordinates":[-84.94580000000001,34.900538],"type":"Point"}
}