{
  "type": "Feature",
  "properties": {
    "addr:full":"1060 Red Bud Rd NE Calhoun GA 30701",
    "addr:housenumber":"1060",
    "addr:postcode":"30701",
    "addr:street":"Red Bud Rd Ne",
    "iso:country":"US",
    "sg:address":"1060 Red Bud Rd NE",
    "sg:city":"Calhoun",
    "sg:classifiers":[
        {
            "category":"Health Services",
            "subcategory":"Clinic",
            "type":"Services"
        }
    ],
    "sg:phone":"+1 706 602 1340",
    "sg:postcode":"30701",
    "sg:province":"GA",
    "wof:name":"Southeastern Cardiac Rehab",
    "wof:placetype":"venue"
},
  "geometry": {"coordinates":[-84.924829,34.511892],"type":"Point"}
}