{
  "type": "Feature",
  "properties": {
    "iso:country":"US",
    "sg:address":"5555 N Peachtree Rd",
    "sg:city":"Dunwoody",
    "sg:classifiers":[
        {
            "category":"Health Services",
            "subcategory":"Doctor",
            "type":"Services"
        }
    ],
    "sg:phone":"+1 770 394 2900",
    "sg:postcode":"30338",
    "sg:province":"GA",
    "sg:tags":[
        "dermatologist"
    ],
    "wof:name":"Georgia Dermatologic Surgery Center MD PC",
    "wof:placetype":"venue"
},
  "geometry": {"coordinates":[-84.30091,33.957856],"type":"Point"}
}