{
  "type": "Feature",
  "properties": {
    "addr:full":"1835 Savoy Dr Ste 203 Atlanta GA 30341",
    "addr:housenumber":"1835",
    "addr:postcode":"30341",
    "addr:street":"Savoy Dr Ste 203",
    "iso:country":"US",
    "sg:address":"1835 Savoy Dr Ste 203",
    "sg:city":"Atlanta",
    "sg:classifiers":[
        {
            "category":"Professional",
            "subcategory":"Lawyer & Legal Services",
            "type":"Services"
        }
    ],
    "sg:phone":"+1 770 220 0344",
    "sg:postcode":"30341",
    "sg:province":"GA",
    "sg:website":"www.cohen-immigration.com",
    "wof:name":"Cohen & Associates",
    "wof:placetype":"venue"
},
  "geometry": {"coordinates":[-84.313231,33.919227],"type":"Point"}
}