{
  "type": "Feature",
  "properties": {
    "iso:country":"US",
    "sg:address":"1286 Broad St",
    "sg:city":"Augusta",
    "sg:classifiers":[
        {
            "category":"Building & Trades",
            "subcategory":"Electrical",
            "type":"Services"
        }
    ],
    "sg:phone":"+1 706 828 6700",
    "sg:postcode":"30901",
    "sg:province":"GA",
    "sg:tags":[
        "electrical",
        "contractor"
    ],
    "wof:name":"Digistar Genesis Inc",
    "wof:placetype":"venue"
},
  "geometry": {"coordinates":[-81.973035,33.477882],"type":"Point"}
}