{
  "type": "Feature",
  "properties": {
    "iso:country":"US",
    "sg:address":"765 Buford Hwy",
    "sg:city":"Buford",
    "sg:classifiers":[
        {
            "category":"Professional",
            "subcategory":"Business Services",
            "type":"Services"
        }
    ],
    "sg:phone":"+1 770 614 1222",
    "sg:postcode":"30024",
    "sg:province":"GA",
    "sg:tags":[
        "auto",
        "general",
        "repair"
    ],
    "wof:name":"Bobby Peavy S Auto",
    "wof:placetype":"venue"
},
  "geometry": {"coordinates":[-84.02817899999999,34.085491],"type":"Point"}
}