{
  "type": "Feature",
  "properties": {
    "iso:country":"US",
    "sg:address":"1054 Redwood Dr",
    "sg:city":"Norcross",
    "sg:classifiers":[
        {
            "category":"Professional",
            "subcategory":"Advertising",
            "type":"Services"
        }
    ],
    "sg:phone":"+1 678 344 6374",
    "sg:postcode":"30093",
    "sg:province":"GA",
    "sg:tags":[
        "marketing",
        "program"
    ],
    "wof:name":"Atlanta Chapter Of The American Marketing Association, Inc.",
    "wof:placetype":"venue"
},
  "geometry": {"coordinates":[-84.19096,33.89374],"type":"Point"}
}