{
  "type": "Feature",
  "properties": {
    "addr:full":"2945 Buford Hwy Duluth GA 30096",
    "addr:housenumber":"2945",
    "addr:postcode":"30096",
    "addr:street":"Buford Hwy",
    "iso:country":"US",
    "sg:address":"2945 Buford Hwy",
    "sg:city":"Duluth",
    "sg:classifiers":[
        {
            "category":"Professional",
            "subcategory":"Art Services",
            "type":"Services"
        }
    ],
    "sg:phone":"+1 404 456 0245",
    "sg:postcode":"30096",
    "sg:province":"GA",
    "sg:tags":[
        "designer",
        "display",
        "producer"
    ],
    "wof:name":"Managed Care Concepts",
    "wof:placetype":"venue"
},
  "geometry": {"coordinates":[-84.138952,34.00446],"type":"Point"}
}