{
  "type": "Feature",
  "properties": {
    "iso:country":"US",
    "sg:address":"417 Hastings Pl",
    "sg:city":"Augusta",
    "sg:classifiers":[
        {
            "category":"Building & Trades",
            "subcategory":"Landscaping Services",
            "type":"Services"
        }
    ],
    "sg:phone":"+1 706 854 1622",
    "sg:postcode":"30907",
    "sg:province":"GA",
    "wof:name":"Easy As Pye Lawn Care Inc",
    "wof:placetype":"venue"
},
  "geometry": {"coordinates":[-82.063669,33.538324],"type":"Point"}
}