{
  "type": "Feature",
  "properties": {
    "iso:country":"US",
    "sg:address":"8301 Jett Ferry Rd",
    "sg:city":"Atlanta",
    "sg:classifiers":[
        {
            "category":"Building & Trades",
            "subcategory":"Locksmith",
            "type":"Services"
        }
    ],
    "sg:phone":"+1 770 225 6257",
    "sg:postcode":"30350",
    "sg:province":"GA",
    "sg:tags":[
        "key"
    ],
    "wof:name":"1 1 24 Hour Any Locksmith",
    "wof:placetype":"venue"
},
  "geometry": {"coordinates":[-84.287623,33.973449],"type":"Point"}
}