{
  "type": "Feature",
  "properties": {
    "iso:country":"US",
    "sg:address":"3005 Parquet Rd",
    "sg:city":"Dalton",
    "sg:classifiers":[
        {
            "category":"Building & Trades",
            "subcategory":"Construction",
            "type":"Services"
        }
    ],
    "sg:phone":"+1 706 277 1449",
    "sg:postcode":"30720",
    "sg:province":"GA",
    "sg:tags":[
        "layer",
        "carpet"
    ],
    "sg:website":"www.spaceflooring.com",
    "wof:name":"SPACE Flooring",
    "wof:placetype":"venue"
},
  "geometry": {"coordinates":[-85.009906,34.694982],"type":"Point"}
}