{
  "type": "Feature",
  "properties": {
    "addr:full":"20 Saratoga Way Covington GA 30016",
    "addr:housenumber":"20",
    "addr:postcode":"30016",
    "addr:street":"Saratoga Way",
    "iso:country":"US",
    "sg:address":"20 Saratoga Way",
    "sg:city":"Covington",
    "sg:classifiers":[
        {
            "category":"Wholesale",
            "subcategory":"Construction Materials",
            "type":"Manufacturing & Wholesale Goods"
        }
    ],
    "sg:phone":"+1 678 625 8792",
    "sg:postcode":"30016",
    "sg:province":"GA",
    "sg:tags":[
        "sand",
        "gravel"
    ],
    "wof:name":"South River Sand LLC",
    "wof:placetype":"venue"
},
  "geometry": {"coordinates":[-84.003865,33.509047],"type":"Point"}
}