{
  "type": "Feature",
  "properties": {
    "iso:country":"US",
    "sg:address":"3250 Lee Dr",
    "sg:city":"Buford",
    "sg:classifiers":[
        {
            "category":"Building & Trades",
            "subcategory":"Landscaping Services",
            "type":"Services"
        }
    ],
    "sg:phone":"+1 770 656 8534",
    "sg:postcode":"30518",
    "sg:province":"GA",
    "sg:tags":[
        "landscape"
    ],
    "wof:name":"SRS Landscaping",
    "wof:placetype":"venue"
},
  "geometry": {"coordinates":[-83.97651500000001,34.155736],"type":"Point"}
}