{
  "type": "Feature",
  "properties": {
    "addr:full":"330 Page Rd Rossville GA 30741",
    "addr:housenumber":"330",
    "addr:postcode":"30741",
    "addr:street":"Page Rd",
    "iso:country":"US",
    "sg:address":"330 Page Rd",
    "sg:city":"Rossville",
    "sg:classifiers":[
        {
            "category":"Professional",
            "subcategory":"Research",
            "type":"Services"
        }
    ],
    "sg:phone":"+1 706 866 6125",
    "sg:postcode":"30741",
    "sg:province":"GA",
    "sg:tags":[
        "organization",
        "noncommercial"
    ],
    "wof:name":"Biblical Consulting Ministries",
    "wof:placetype":"venue"
},
  "geometry": {"coordinates":[-85.242862,34.984456],"type":"Point"}
}