{
  "type": "Feature",
  "properties": {
    "addr:full":"4172 Railroad Ave Tucker GA 30084",
    "addr:housenumber":"4172",
    "addr:postcode":"30084",
    "addr:street":"Railroad Ave",
    "iso:country":"US",
    "sg:address":"4172 Railroad Ave",
    "sg:city":"Tucker",
    "sg:classifiers":[
        {
            "category":"Retail",
            "subcategory":"Auto Repair",
            "type":"Services"
        }
    ],
    "sg:phone":"+1 770 414 0308",
    "sg:postcode":"30084",
    "sg:province":"GA",
    "wof:name":"Mdl Auto Service",
    "wof:placetype":"venue"
},
  "geometry": {"coordinates":[-84.21779600000001,33.851501],"type":"Point"}
}