{
  "type": "Feature",
  "properties": {
    "iso:country":"US",
    "sg:address":"2436 Juniper Dr",
    "sg:city":"Augusta",
    "sg:classifiers":[
        {
            "category":"Shopping",
            "subcategory":"Florist",
            "type":"Retail Goods"
        }
    ],
    "sg:phone":"+1 706 793 0111",
    "sg:postcode":"30906",
    "sg:province":"GA",
    "wof:name":"Peaches Flower Shop",
    "wof:placetype":"venue"
},
  "geometry": {"coordinates":[-82.047774,33.431358],"type":"Point"}
}