{
  "type": "Feature",
  "properties": {
    "addr:full":"227 Sandy Springs Place NE Suite E Atlanta GA 30328",
    "addr:housenumber":"227",
    "addr:postcode":"30328",
    "addr:street":"Sandy Springs Place Ne Suite E",
    "iso:country":"US",
    "sg:address":"227 Sandy Springs Place NE Suite E",
    "sg:city":"Atlanta",
    "sg:classifiers":[
        {
            "category":"Personal",
            "subcategory":"Nail Salon",
            "type":"Services"
        }
    ],
    "sg:phone":"+1 404 255 2878",
    "sg:postcode":"30328",
    "sg:province":"GA",
    "wof:name":"Nail USA",
    "wof:placetype":"venue"
},
  "geometry": {"coordinates":[-84.381942,33.921428],"type":"Point"}
}