{
  "type": "Feature",
  "properties": {
    "iso:country":"US",
    "sg:address":"4467 Columbia Rd",
    "sg:city":"Martinez",
    "sg:classifiers":[
        {
            "category":"Restaurant",
            "type":"Food & Drink"
        }
    ],
    "sg:phone":"+1 706 860 1377",
    "sg:postcode":"30907",
    "sg:province":"GA",
    "wof:name":"Lotus Chinese Restaurant",
    "wof:placetype":"venue"
},
  "geometry": {"coordinates":[-82.141661,33.507528],"type":"Point"}
}