{
  "type": "Feature",
  "properties": {
    "addr:full":"1177 West Ave SW Conyers GA 30012",
    "addr:housenumber":"1177",
    "addr:postcode":"30012",
    "addr:street":"West Ave Sw",
    "iso:country":"US",
    "sg:address":"1177 West Ave SW",
    "sg:city":"Conyers",
    "sg:classifiers":[
        {
            "category":"Shopping",
            "subcategory":"Beauty & Cosmetics",
            "type":"Retail Goods"
        }
    ],
    "sg:phone":"+1 678 413 3244",
    "sg:postcode":"30012",
    "sg:province":"GA",
    "sg:tags":[
        "supply"
    ],
    "wof:name":"Uptown Beauty & Salon",
    "wof:placetype":"venue"
},
  "geometry": {"coordinates":[-84.024902,33.6674],"type":"Point"}
}