{
  "type": "Feature",
  "properties": {
    "addr:full":"3379 Peachtree Rd NE Atlanta GA 30326",
    "addr:housenumber":"3379",
    "addr:postcode":"30326",
    "addr:street":"Peachtree Rd Ne",
    "iso:country":"US",
    "sg:address":"3379 Peachtree Rd NE",
    "sg:city":"Atlanta",
    "sg:classifiers":[
        {
            "category":"Professional",
            "subcategory":"Lawyer & Legal Services",
            "type":"Services"
        }
    ],
    "sg:phone":"+1 404 995 0610",
    "sg:postcode":"30326",
    "sg:province":"GA",
    "wof:name":"Elsner Robert A Atty At Law",
    "wof:placetype":"venue"
},
  "geometry": {"coordinates":[-84.366096,33.848701],"type":"Point"}
}