{
  "type": "Feature",
  "properties": {
    "iso:country":"US",
    "sg:address":"4979 Woodfall Dr SW",
    "sg:city":"Lilburn",
    "sg:classifiers":[
        {
            "category":"Travel",
            "subcategory":"Travel Agent",
            "type":"Entertainment"
        }
    ],
    "sg:phone":"+1 678 924 1537",
    "sg:postcode":"30047",
    "sg:province":"GA",
    "sg:tags":[
        "agency"
    ],
    "wof:name":"Aim 2 Go Travel",
    "wof:placetype":"venue"
},
  "geometry": {"coordinates":[-84.132485,33.879692],"type":"Point"}
}