{
  "type": "Feature",
  "properties": {
    "addr:full":"2500 Old Norcross Rd Lawrenceville GA 30044",
    "addr:housenumber":"2500",
    "addr:postcode":"30044",
    "addr:street":"Old Norcross Rd",
    "iso:country":"US",
    "sg:address":"2500 Old Norcross Rd",
    "sg:city":"Lawrenceville",
    "sg:classifiers":[
        {
            "category":"Building & Trades",
            "subcategory":"Locksmith",
            "type":"Services"
        }
    ],
    "sg:phone":"+1 888 244 6019",
    "sg:postcode":"30044",
    "sg:province":"GA",
    "sg:tags":[
        "key"
    ],
    "wof:name":"24 Hour 1 Emergency Locksmith",
    "wof:placetype":"venue"
},
  "geometry": {"coordinates":[-84.08242,33.949193],"type":"Point"}
}