{
  "type": "Feature",
  "properties": {
    "iso:country":"US",
    "sg:address":"310 Asa Lindsey Rd",
    "sg:city":"Kite",
    "sg:classifiers":[
        {
            "category":"Farming",
            "subcategory":"Farm",
            "type":"Manufacturing & Wholesale Goods"
        }
    ],
    "sg:phone":"+1 478 469 5173",
    "sg:postcode":"31049",
    "sg:province":"GA",
    "sg:tags":[
        "crop",
        "general"
    ],
    "wof:name":"L & M Farms Office & Shop",
    "wof:placetype":"venue"
},
  "geometry": {"coordinates":[-82.48398,32.631412],"type":"Point"}
}