{
  "type": "Feature",
  "properties": {
    "addr:full":"3659 Clairmont Rd Atlanta GA 30341",
    "addr:housenumber":"3659",
    "addr:postcode":"30341",
    "addr:street":"Clairmont Rd",
    "iso:country":"US",
    "sg:address":"3659 Clairmont Rd",
    "sg:city":"Atlanta",
    "sg:classifiers":[
        {
            "category":"Organizations",
            "subcategory":"Non-profit Organization",
            "type":"Services"
        }
    ],
    "sg:phone":"+1 770 457 8550",
    "sg:postcode":"30341",
    "sg:province":"GA",
    "sg:tags":[
        "information",
        "alcoholism",
        "treatment"
    ],
    "wof:name":"Alcoholics Anonymous",
    "wof:placetype":"venue"
},
  "geometry": {"coordinates":[-84.309376,33.865754],"type":"Point"}
}