{
  "type": "Feature",
  "properties": {
    "iso:country":"US",
    "sg:address":"3108 Piedmont Rd NE",
    "sg:city":"Atlanta",
    "sg:classifiers":[
        {
            "category":"Real Estate",
            "subcategory":"Real Estate Agent",
            "type":"Services"
        }
    ],
    "sg:phone":"+1 404 467 8240",
    "sg:postcode":"30305",
    "sg:province":"GA",
    "sg:tags":[
        "agency",
        "rental"
    ],
    "wof:name":"Aaron Rents",
    "wof:placetype":"venue"
},
  "geometry": {"coordinates":[-84.370037,33.840587],"type":"Point"}
}