{
  "type": "Feature",
  "properties": {
    "iso:country":"US",
    "sg:address":"5700 Holloman Rd",
    "sg:city":"Powder Springs",
    "sg:classifiers":[
        {
            "category":"Recreation",
            "type":"Entertainment"
        }
    ],
    "sg:phone":"+1 770 943 8592",
    "sg:postcode":"30127",
    "sg:province":"GA",
    "sg:website":"www.sujonfarms.com",
    "wof:name":"Sujon Farms Inc",
    "wof:placetype":"venue"
},
  "geometry": {"coordinates":[-84.696985,33.809425],"type":"Point"}
}