{
  "type": "Feature",
  "properties": {
    "iso:country":"US",
    "sg:address":"1240 Old Jackson Rd",
    "sg:city":"Locust Grove",
    "sg:classifiers":[
        {
            "category":"Professional",
            "subcategory":"Business Services",
            "type":"Services"
        }
    ],
    "sg:phone":"+1 770 898 8179",
    "sg:postcode":"30248",
    "sg:province":"GA",
    "sg:tags":[
        "embroidery"
    ],
    "wof:name":"Sew Mini Stitches",
    "wof:placetype":"venue"
},
  "geometry": {"coordinates":[-84.07122200000001,33.40189],"type":"Point"}
}