{
  "type": "Feature",
  "properties": {
    "addr:full":"6258 Holiday Dr Forest Park GA 30297",
    "addr:housenumber":"6258",
    "addr:postcode":"30297",
    "addr:street":"Holiday Dr",
    "iso:country":"US",
    "sg:address":"6258 Holiday Dr",
    "sg:city":"Forest Park",
    "sg:classifiers":[
        {
            "category":"Building & Trades",
            "subcategory":"Construction",
            "type":"Services"
        }
    ],
    "sg:phone":"+1 770 961 9623",
    "sg:postcode":"30297",
    "sg:province":"GA",
    "sg:tags":[
        "contractor"
    ],
    "wof:name":"All Trades General Contracting Inc",
    "wof:placetype":"venue"
},
  "geometry": {"coordinates":[-84.365285,33.583824],"type":"Point"}
}