{
  "type": "Feature",
  "properties": {
    "iso:country":"US",
    "sg:address":"20 Berkeley Rd",
    "sg:city":"Avondale Estates",
    "sg:classifiers":[
        {
            "category":"Arts & Performance",
            "subcategory":"Theater",
            "type":"Entertainment"
        }
    ],
    "sg:phone":"+1 404 299 1771",
    "sg:postcode":"30002",
    "sg:province":"GA",
    "sg:tags":[
        "theatrical",
        "bureau"
    ],
    "wof:name":"Trace Management LLC",
    "wof:placetype":"venue"
},
  "geometry": {"coordinates":[-84.26603900000001,33.77271],"type":"Point"}
}