{
  "type": "Feature",
  "properties": {
    "iso:country":"US",
    "sg:address":"3490 Honeycomb Dr SE",
    "sg:city":"Conyers",
    "sg:classifiers":[
        {
            "category":"Building & Trades",
            "subcategory":"Construction",
            "type":"Services"
        }
    ],
    "sg:phone":"+1 770 483 0961",
    "sg:postcode":"30094",
    "sg:province":"GA",
    "sg:tags":[
        "contractor"
    ],
    "wof:name":"J & D Sun & Shade",
    "wof:placetype":"venue"
},
  "geometry": {"coordinates":[-84.034297,33.591776],"type":"Point"}
}