{
  "type": "Feature",
  "properties": {
    "iso:country":"US",
    "sg:address":"1364 Echo Mill Ct",
    "sg:city":"Powder Springs",
    "sg:classifiers":[
        {
            "category":"Professional",
            "subcategory":"Business Services",
            "type":"Services"
        }
    ],
    "sg:phone":"+1 770 222 9470",
    "sg:postcode":"30127",
    "sg:province":"GA",
    "wof:name":"JB Technology Inc",
    "wof:placetype":"venue"
},
  "geometry": {"coordinates":[-84.709588,33.918963],"type":"Point"}
}