{
  "type": "Feature",
  "properties": {
    "addr:full":"2490 Fairview Ln Jonesboro GA 30236",
    "addr:housenumber":"2490",
    "addr:postcode":"30236",
    "addr:street":"Fairview Ln",
    "iso:country":"US",
    "sg:address":"2490 Fairview Ln",
    "sg:city":"Jonesboro",
    "sg:classifiers":[
        {
            "category":"Social Services",
            "type":"Services"
        }
    ],
    "sg:phone":"+1 770 478 0260",
    "sg:postcode":"30236",
    "sg:province":"GA",
    "wof:name":"Creative Counseling Concepts",
    "wof:placetype":"venue"
},
  "geometry": {"coordinates":[-84.311334,33.50445],"type":"Point"}
}