{
  "type": "Feature",
  "properties": {
    "iso:country":"US",
    "sg:address":"5306 Rogers Rd",
    "sg:city":"Lizella",
    "sg:classifiers":[
        {
            "category":"Organizations",
            "subcategory":"Religious Organization",
            "type":"Services"
        }
    ],
    "sg:phone":"+1 478 788 8931",
    "sg:postcode":"31052",
    "sg:province":"GA",
    "wof:name":"Fellowship Cmnty Chrch Lizella",
    "wof:placetype":"venue"
},
  "geometry": {"coordinates":[-83.788946,32.755648],"type":"Point"}
}