{
  "type": "Feature",
  "properties": {
    "iso:country":"US",
    "sg:address":"1604 US Hwy 1",
    "sg:city":"Swainsboro",
    "sg:classifiers":[
        {
            "category":"Shopping",
            "subcategory":"Computers & Home Electronics",
            "type":"Retail Goods"
        }
    ],
    "sg:phone":"+1 478 237 4767",
    "sg:postcode":"30401",
    "sg:province":"GA",
    "sg:tags":[
        "equipment",
        "dealer"
    ],
    "wof:name":"J S Computer Store",
    "wof:placetype":"venue"
},
  "geometry": {"coordinates":[-82.353081,32.62529],"type":"Point"}
}