{
  "type": "Feature",
  "properties": {
    "iso:country":"US",
    "sg:address":"1557 Gordon Hwy",
    "sg:city":"Augusta",
    "sg:classifiers":[
        {
            "category":"Health Services",
            "subcategory":"Doctor",
            "type":"Services"
        }
    ],
    "sg:phone":"+1 706 738 1711",
    "sg:postcode":"30906",
    "sg:province":"GA",
    "wof:name":"Dwayne McGahee Dr",
    "wof:placetype":"venue"
},
  "geometry": {"coordinates":[-82.007682,33.43811],"type":"Point"}
}