{
  "type": "Feature",
  "properties": {
    "addr:full":"3505 Hutchinson Rd Cumming GA 30040",
    "addr:housenumber":"3505",
    "addr:postcode":"30040",
    "addr:street":"Hutchinson Rd",
    "iso:country":"US",
    "sg:address":"3505 Hutchinson Rd",
    "sg:city":"Cumming",
    "sg:classifiers":[
        {
            "category":"Wholesale",
            "subcategory":"Machinery & Supplies",
            "type":"Manufacturing & Wholesale Goods"
        }
    ],
    "sg:phone":"+1 770 889 2858",
    "sg:postcode":"30040",
    "sg:province":"GA",
    "sg:tags":[
        "distributor",
        "control",
        "devices"
    ],
    "wof:name":"Automation Directcom",
    "wof:placetype":"venue"
},
  "geometry": {"coordinates":[-84.14781000000001,34.189678],"type":"Point"}
}