{
  "type": "Feature",
  "properties": {
    "addr:full":"1001 James Madison Ct Mc Donough GA 30253",
    "addr:housenumber":"1001",
    "addr:postcode":"30253",
    "addr:street":"James Madison Ct",
    "iso:country":"US",
    "sg:address":"1001 James Madison Ct",
    "sg:city":"Mc Donough",
    "sg:classifiers":[
        {
            "category":"Professional",
            "subcategory":"Art Services",
            "type":"Services"
        }
    ],
    "sg:phone":"+1 770 898 9161",
    "sg:postcode":"30253",
    "sg:province":"GA",
    "sg:tags":[
        "commercial",
        "design"
    ],
    "wof:name":"Classic Frames & Design",
    "wof:placetype":"venue"
},
  "geometry": {"coordinates":[-84.18234699999999,33.464269],"type":"Point"}
}