{
  "type": "Feature",
  "properties": {
    "iso:country":"US",
    "sg:address":"4248 Indian Manor Dr",
    "sg:city":"Stone Mountain",
    "sg:classifiers":[
        {
            "category":"Real Estate",
            "subcategory":"Real Estate Agent",
            "type":"Services"
        }
    ],
    "sg:phone":"+1 404 292 1689",
    "sg:postcode":"30083",
    "sg:province":"GA",
    "wof:name":"A Platt Company",
    "wof:placetype":"venue"
},
  "geometry": {"coordinates":[-84.223646,33.773908],"type":"Point"}
}