{
  "type": "Feature",
  "properties": {
    "addr:full":"2014 Powers Ferry Rd SE Ste 300 Atlanta GA 30339",
    "addr:housenumber":"2014",
    "addr:postcode":"30339",
    "addr:street":"Powers Ferry Rd Se Ste 300",
    "iso:country":"US",
    "sg:address":"2014 Powers Ferry Rd SE Ste 300",
    "sg:city":"Atlanta",
    "sg:classifiers":[
        {
            "category":"Food & Beverages",
            "subcategory":"Bakery",
            "type":"Retail Goods"
        }
    ],
    "sg:phone":"+1 678 279 9990",
    "sg:postcode":"30339",
    "sg:province":"GA",
    "sg:tags":[
        "sandwich"
    ],
    "sg:website":"www.jerseymikes.com",
    "wof:name":"Jersey Mike's Subs",
    "wof:placetype":"venue"
},
  "geometry": {"coordinates":[-84.46046699999999,33.903239],"type":"Point"}
}