{
  "type": "Feature",
  "properties": {
    "iso:country":"US",
    "sg:address":"6495 Bevin Dr",
    "sg:city":"Macon",
    "sg:classifiers":[
        {
            "category":"Shopping",
            "type":"Retail Goods"
        }
    ],
    "sg:phone":"+1 478 746 3291",
    "sg:postcode":"31216",
    "sg:province":"GA",
    "sg:tags":[
        "miscellaneous",
        "store"
    ],
    "wof:name":"Olde London Gold & Silver Exch",
    "wof:placetype":"venue"
},
  "geometry": {"coordinates":[-83.67824400000001,32.724733],"type":"Point"}
}