{
  "type": "Feature",
  "properties": {
    "addr:full":"10305 Medlock Bridge Rd Duluth GA 30097",
    "addr:housenumber":"10305",
    "addr:postcode":"30097",
    "addr:street":"Medlock Bridge Rd",
    "iso:country":"US",
    "sg:address":"10305 Medlock Bridge Rd",
    "sg:city":"Duluth",
    "sg:classifiers":[
        {
            "category":"Banks & Credit Unions",
            "subcategory":"Financial Services",
            "type":"Services"
        }
    ],
    "sg:phone":"+1 678 475 2725",
    "sg:postcode":"30097",
    "sg:province":"GA",
    "sg:tags":[
        "broker",
        "mortgage"
    ],
    "wof:name":"U Sa Financial Services Inc",
    "wof:placetype":"venue"
},
  "geometry": {"coordinates":[-84.18650100000001,34.030701],"type":"Point"}
}