{
  "type": "Feature",
  "properties": {
    "addr:full":"6679 Peachtree Industrial Blvd Norcross GA 30092",
    "addr:housenumber":"6679",
    "addr:postcode":"30092",
    "addr:street":"Peachtree Industrial Blvd",
    "iso:country":"US",
    "sg:address":"6679 Peachtree Industrial Blvd",
    "sg:city":"Norcross",
    "sg:classifiers":[
        {
            "category":"Professional",
            "type":"Services"
        }
    ],
    "sg:phone":"+1 770 992 8820",
    "sg:postcode":"30092",
    "sg:province":"GA",
    "sg:tags":[
        "establishment"
    ],
    "wof:name":"Broomfield & Assoc",
    "wof:placetype":"venue"
},
  "geometry": {"coordinates":[-84.24991900000001,33.93857],"type":"Point"}
}