{
  "type": "Feature",
  "properties": {
    "iso:country":"US",
    "sg:address":"416 N 5th Ave",
    "sg:city":"Rome",
    "sg:classifiers":[
        {
            "category":"Organizations",
            "subcategory":"Religious Organization",
            "type":"Services"
        }
    ],
    "sg:phone":"+1 706 291 0689",
    "sg:postcode":"30165",
    "sg:province":"GA",
    "sg:tags":[
        "church"
    ],
    "wof:name":"Fifth Avenue Baptist Church",
    "wof:placetype":"venue"
},
  "geometry": {"coordinates":[-85.175084,34.259522],"type":"Point"}
}