{
  "type": "Feature",
  "properties": {
    "iso:country":"US",
    "sg:address":"6050 Peachtree Industrial Blvd",
    "sg:city":"Norcross",
    "sg:classifiers":[
        {
            "category":"Bars & Pubs",
            "type":"Food & Drink"
        },
        {
            "category":"Bars & Pubs",
            "subcategory":"Lounge",
            "type":"Food & Drink"
        },
        {
            "category":"Restaurant",
            "type":"Food & Drink"
        },
        {
            "category":"Travel",
            "subcategory":"Hotels & Motels",
            "type":"Entertainment"
        }
    ],
    "sg:phone":"+1 770 448 4400",
    "sg:postcode":"30071",
    "sg:province":"GA",
    "sg:tags":[
        "cocktail"
    ],
    "sg:website":"http://www.doubletreeoakridge.com",
    "wof:name":"Louie's Grill",
    "wof:placetype":"venue"
},
  "geometry": {"coordinates":[-84.231711,33.949002],"type":"Point"}
}