{
  "type": "Feature",
  "properties": {
    "addr:full":"916 Woodmere Dr NW Atlanta GA 30318",
    "addr:housenumber":"916",
    "addr:postcode":"30318",
    "addr:street":"Woodmere Dr Nw",
    "iso:country":"US",
    "sg:address":"916 Woodmere Dr NW",
    "sg:city":"Atlanta",
    "sg:classifiers":[
        {
            "category":"Building & Trades",
            "subcategory":"Electrical",
            "type":"Services"
        }
    ],
    "sg:phone":"+1 404 792 0841",
    "sg:postcode":"30318",
    "sg:province":"GA",
    "sg:tags":[
        "electrician"
    ],
    "wof:name":"First Light Electric",
    "wof:placetype":"venue"
},
  "geometry": {"coordinates":[-84.48502000000001,33.781301],"type":"Point"}
}