{
  "type": "Feature",
  "properties": {
    "iso:country":"US",
    "sg:address":"3403 Main St",
    "sg:city":"College Park",
    "sg:classifiers":[
        {
            "category":"Restaurant",
            "type":"Food & Drink"
        }
    ],
    "sg:menulink":"http://www.allmenus.com/ga/college-park/281327-the-brake-pad/menu/",
    "sg:phone":"+1 404 766 1515",
    "sg:postcode":"30337",
    "sg:province":"GA",
    "sg:tags":[
        "american"
    ],
    "wof:name":"The Brake Pad",
    "wof:placetype":"venue"
},
  "geometry": {"coordinates":[-84.44664299999999,33.662857],"type":"Point"}
}