{
  "type": "Feature",
  "properties": {
    "addr:full":"2911 Airport Thruway Columbus GA 31909",
    "addr:housenumber":"2911",
    "addr:postcode":"31909",
    "addr:street":"Airport Thruway",
    "iso:country":"US",
    "sg:address":"2911 Airport Thruway",
    "sg:city":"Columbus",
    "sg:classifiers":[
        {
            "category":"Restaurant",
            "type":"Food & Drink"
        }
    ],
    "sg:menulink":"http://www.allmenus.com/ga/columbus/94200-china-moon-/menu/",
    "sg:phone":"+1 706 323 1388",
    "sg:postcode":"31909",
    "sg:province":"GA",
    "sg:tags":[
        "asian",
        "chinese"
    ],
    "wof:name":"China Moon ",
    "wof:placetype":"venue"
},
  "geometry": {"coordinates":[-84.948279,32.520511],"type":"Point"}
}