{
  "type": "Feature",
  "properties": {
    "addr:full":"125 Perimeter Center W Atlanta GA 30346",
    "addr:housenumber":"125",
    "addr:postcode":"30346",
    "addr:street":"Perimeter Center W",
    "iso:country":"US",
    "sg:address":"125 Perimeter Center W",
    "sg:city":"Atlanta",
    "sg:classifiers":[
        {
            "category":"Building & Trades",
            "subcategory":"Construction",
            "type":"Services"
        }
    ],
    "sg:phone":"+1 770 393 9081",
    "sg:postcode":"30346",
    "sg:province":"GA",
    "sg:tags":[
        "general",
        "contractor"
    ],
    "wof:name":"Ordner Construction",
    "wof:placetype":"venue"
},
  "geometry": {"coordinates":[-84.34156,33.926901],"type":"Point"}
}