{
  "type": "Feature",
  "properties": {
    "addr:full":"155 Forrest Rd Fort Oglethorpe GA 30742",
    "addr:housenumber":"155",
    "addr:postcode":"30742",
    "addr:street":"Forrest Rd",
    "iso:country":"US",
    "sg:address":"155 Forrest Rd",
    "sg:city":"Fort Oglethorpe",
    "sg:classifiers":[
        {
            "category":"Government",
            "subcategory":"Post Office",
            "type":"Public Place"
        }
    ],
    "sg:phone":"+1 706 866 9350",
    "sg:postcode":"30742",
    "sg:province":"GA",
    "sg:tags":[
        "postal",
        "us"
    ],
    "wof:name":"US Post Office",
    "wof:placetype":"venue"
},
  "geometry": {"coordinates":[-85.25685199999999,34.94854],"type":"Point"}
}