{
  "type": "Feature",
  "properties": {
    "addr:full":"2688 Bonaire Ter Marietta GA 30066",
    "addr:housenumber":"2688",
    "addr:postcode":"30066",
    "addr:street":"Bonaire Ter",
    "iso:country":"US",
    "sg:address":"2688 Bonaire Ter",
    "sg:city":"Marietta",
    "sg:classifiers":[
        {
            "category":"Shopping",
            "subcategory":"Gifts & Souvenirs",
            "type":"Retail Goods"
        }
    ],
    "sg:phone":"+1 770 971 7489",
    "sg:postcode":"30066",
    "sg:province":"GA",
    "sg:tags":[
        "cards",
        "greeting"
    ],
    "wof:name":"Greetings & Gatherings",
    "wof:placetype":"venue"
},
  "geometry": {"coordinates":[-84.47064899999999,34.037308],"type":"Point"}
}