{
  "type": "Feature",
  "properties": {
    "iso:country":"US",
    "sg:address":"1719 Russell Pkwy",
    "sg:city":"Warner Robins",
    "sg:classifiers":[
        {
            "category":"Professional",
            "subcategory":"Lawyer & Legal Services",
            "type":"Services"
        }
    ],
    "sg:phone":"+1 478 922 3010",
    "sg:postcode":"31088",
    "sg:province":"GA",
    "sg:tags":[
        "attorney"
    ],
    "wof:name":"Varner & Adams PC",
    "wof:placetype":"venue"
},
  "geometry": {"coordinates":[-83.665228,32.593136],"type":"Point"}
}