{
  "type": "Feature",
  "properties": {
    "addr:full":"1735 Buford Hwy Cumming GA 30041",
    "addr:housenumber":"1735",
    "addr:postcode":"30041",
    "addr:street":"Buford Hwy",
    "iso:country":"US",
    "sg:address":"1735 Buford Hwy",
    "sg:city":"Cumming",
    "sg:classifiers":[
        {
            "category":"Personal",
            "subcategory":"Beauty Salon",
            "type":"Services"
        }
    ],
    "sg:phone":"+1 678 455 5597",
    "sg:postcode":"30041",
    "sg:province":"GA",
    "wof:name":"Great Clips",
    "wof:placetype":"venue"
},
  "geometry": {"coordinates":[-84.11592,34.162195],"type":"Point"}
}