{
  "type": "Feature",
  "properties": {
    "iso:country":"US",
    "sg:address":"2200 Century Pkwy NE # 300",
    "sg:city":"Atlanta",
    "sg:classifiers":[
        {
            "category":"Insurance",
            "subcategory":"Insurance Agent",
            "type":"Services"
        },
        {
            "category":"Insurance",
            "subcategory":"Hazard Insurance",
            "type":"Services"
        }
    ],
    "sg:phone":"+1 404 929 0299",
    "sg:postcode":"30345",
    "sg:province":"GA",
    "sg:tags":[
        "auto"
    ],
    "wof:name":"America Century Casualty Insurance Company",
    "wof:placetype":"venue"
},
  "geometry": {"coordinates":[-84.307739,33.845341],"type":"Point"}
}