{
  "type": "Feature",
  "properties": {
    "iso:country":"US",
    "sg:address":"502 Sutters Pt NE",
    "sg:city":"Atlanta",
    "sg:classifiers":[
        {
            "category":"Professional",
            "type":"Services"
        }
    ],
    "sg:phone":"+1 404 255 0305",
    "sg:postcode":"30328",
    "sg:province":"GA",
    "wof:name":"Latham & Phillips",
    "wof:placetype":"venue"
},
  "geometry": {"coordinates":[-84.36386400000001,33.916298],"type":"Point"}
}