{
  "type": "Feature",
  "properties": {
    "addr:full":"2088 Stoneleigh Dr Stone Mountain GA 30087",
    "addr:housenumber":"2088",
    "addr:postcode":"30087",
    "addr:street":"Stoneleigh Dr",
    "iso:country":"US",
    "sg:address":"2088 Stoneleigh Dr",
    "sg:city":"Stone Mountain",
    "sg:classifiers":[
        {
            "category":"Travel",
            "subcategory":"Travel Agent",
            "type":"Entertainment"
        }
    ],
    "sg:phone":"+1 770 414 1414",
    "sg:postcode":"30087",
    "sg:province":"GA",
    "sg:tags":[
        "agency",
        "bureau"
    ],
    "wof:name":"Third Millennium Travel",
    "wof:placetype":"venue"
},
  "geometry": {"coordinates":[-84.17668500000001,33.839887],"type":"Point"}
}