{
  "type": "Feature",
  "properties": {
    "iso:country":"US",
    "sg:address":"322 E Taylor St",
    "sg:city":"Savannah",
    "sg:classifiers":[
        {
            "category":"Professional",
            "type":"Services"
        }
    ],
    "sg:phone":"+1 912 232 7103",
    "sg:postcode":"31401",
    "sg:province":"GA",
    "wof:name":"Sisters Network Inc",
    "wof:placetype":"venue"
},
  "geometry": {"coordinates":[-81.09061199999999,32.070676],"type":"Point"}
}