{
  "type": "Feature",
  "properties": {
    "iso:country":"US",
    "sg:address":"545 Highway 515 S",
    "sg:city":"Jasper",
    "sg:classifiers":[
        {
            "category":"Autos & Motor Vehicles",
            "subcategory":"Automobile Sales",
            "type":"Retail Goods"
        },
        {
            "category":"Retail",
            "subcategory":"Auto Repair",
            "type":"Services"
        }
    ],
    "sg:phone":"+1 706 692 3441",
    "sg:postcode":"30143",
    "sg:province":"GA",
    "sg:tags":[
        "body",
        "car",
        "new",
        "painting",
        "repairing"
    ],
    "sg:website":"http://www.lawsonchevy.com",
    "wof:name":"Lawson Chevrolet Body Shop",
    "wof:placetype":"venue"
},
  "geometry": {"coordinates":[-84.45398,34.456292],"type":"Point"}
}