{
  "type": "Feature",
  "properties": {
    "addr:full":"1940 Wylie Dr Augusta GA 30906",
    "addr:housenumber":"1940",
    "addr:postcode":"30906",
    "addr:street":"Wylie Dr",
    "iso:country":"US",
    "sg:address":"1940 Wylie Dr",
    "sg:city":"Augusta",
    "sg:classifiers":[
        {
            "category":"Health Services",
            "subcategory":"Nursing And Care Facility",
            "type":"Services"
        }
    ],
    "sg:phone":"+1 706 360 0299",
    "sg:postcode":"30906",
    "sg:province":"GA",
    "wof:name":"Bryants Personal Care Home",
    "wof:placetype":"venue"
},
  "geometry": {"coordinates":[-82.010081,33.408153],"type":"Point"}
}