{
  "type": "Feature",
  "properties": {
    "iso:country":"US",
    "sg:address":"808 Country Club Rd",
    "sg:city":"Dublin",
    "sg:classifiers":[
        {
            "category":"Professional",
            "type":"Services"
        }
    ],
    "sg:phone":"+1 478 277 9071",
    "sg:postcode":"31021",
    "sg:province":"GA",
    "wof:name":"Amy Kimbell",
    "wof:placetype":"venue"
},
  "geometry": {"coordinates":[-82.89651600000001,32.601041],"type":"Point"}
}