{
  "type": "Feature",
  "properties": {
    "iso:country":"US",
    "sg:address":"22 New Hope Church Rd",
    "sg:city":"Chatsworth",
    "sg:classifiers":[
        {
            "category":"Shopping",
            "type":"Retail Goods"
        }
    ],
    "sg:phone":"+1 706 695 0801",
    "sg:postcode":"30705",
    "sg:province":"GA",
    "sg:tags":[
        "merchandise"
    ],
    "wof:name":"This & That Shop",
    "wof:placetype":"venue"
},
  "geometry": {"coordinates":[-84.82015699999999,34.729961],"type":"Point"}
}