{
  "type": "Feature",
  "properties": {
    "iso:country":"US",
    "sg:address":"1143 Monticello St SW",
    "sg:city":"Covington",
    "sg:classifiers":[
        {
            "category":"Shopping",
            "subcategory":"Books",
            "type":"Retail Goods"
        }
    ],
    "sg:phone":"+1 770 786 2546",
    "sg:postcode":"30014",
    "sg:province":"GA",
    "sg:tags":[
        "store"
    ],
    "wof:name":"Max & Lily's",
    "wof:placetype":"venue"
},
  "geometry": {"coordinates":[-83.860336,33.596062],"type":"Point"}
}