{
  "type": "Feature",
  "properties": {
    "iso:country":"US",
    "sg:address":"6525 Best Friend Rd",
    "sg:city":"Norcross",
    "sg:classifiers":[
        {
            "category":"Professional",
            "subcategory":"Management & Consulting",
            "type":"Services"
        }
    ],
    "sg:phone":"+1 770 840 7251",
    "sg:postcode":"30071",
    "sg:province":"GA",
    "sg:tags":[
        "logistics"
    ],
    "wof:name":"Worldwide Logistics",
    "wof:placetype":"venue"
},
  "geometry": {"coordinates":[-84.22755100000001,33.916624],"type":"Point"}
}