{
  "type": "Feature",
  "properties": {
    "iso:country":"US",
    "sg:address":"714 Mallard Dr",
    "sg:city":"Winder",
    "sg:classifiers":[
        {
            "category":"Professional",
            "type":"Services"
        }
    ],
    "sg:phone":"+1 770 867 5167",
    "sg:postcode":"30680",
    "sg:province":"GA",
    "wof:name":"Lipscombreid",
    "wof:placetype":"venue"
},
  "geometry": {"coordinates":[-83.74038899999999,34.010215],"type":"Point"}
}