{
  "type": "Feature",
  "properties": {
    "addr:full":"2811 Birchwood Ct Marietta GA 30060",
    "addr:housenumber":"2811",
    "addr:postcode":"30060",
    "addr:street":"Birchwood Ct",
    "iso:country":"US",
    "sg:address":"2811 Birchwood Ct",
    "sg:city":"Marietta",
    "sg:classifiers":[
        {
            "category":"Building & Trades",
            "subcategory":"Construction",
            "type":"Services"
        }
    ],
    "sg:phone":"+1 770 432 0314",
    "sg:postcode":"30060",
    "sg:province":"GA",
    "sg:tags":[
        "house"
    ],
    "wof:name":"DD&h Remodeling",
    "wof:placetype":"venue"
},
  "geometry": {"coordinates":[-84.57489,33.886316],"type":"Point"}
}