{
  "type": "Feature",
  "properties": {
    "iso:country":"US",
    "sg:address":"5050 N Henry Blvd",
    "sg:city":"Stockbridge",
    "sg:classifiers":[
        {
            "category":"Retail",
            "subcategory":"Auto Repair",
            "type":"Services"
        }
    ],
    "sg:phone":"+1 770 474 1392",
    "sg:postcode":"30281",
    "sg:province":"GA",
    "wof:name":"Strictly Tires Inc # 2",
    "wof:placetype":"venue"
},
  "geometry": {"coordinates":[-84.24412,33.545023],"type":"Point"}
}