{
  "type": "Feature",
  "properties": {
    "addr:full":"397 Boone Ford Rd SE Calhoun GA 30701",
    "addr:housenumber":"397",
    "addr:postcode":"30701",
    "addr:street":"Boone Ford Rd Se",
    "iso:country":"US",
    "sg:address":"397 Boone Ford Rd SE",
    "sg:city":"Calhoun",
    "sg:classifiers":[
        {
            "category":"Shopping",
            "subcategory":"Florist",
            "type":"Retail Goods"
        }
    ],
    "sg:phone":"+1 706 602 7706",
    "sg:postcode":"30701",
    "sg:province":"GA",
    "wof:name":"G W S Flowers",
    "wof:placetype":"venue"
},
  "geometry": {"coordinates":[-84.90920300000001,34.476471],"type":"Point"}
}