{
  "type": "Feature",
  "properties": {
    "addr:full":"7325 Ga Hwy Buchanan GA 30113",
    "addr:housenumber":"7325",
    "addr:postcode":"30113",
    "addr:street":"Ga Hwy",
    "iso:country":"US",
    "sg:address":"7325 Ga Hwy",
    "sg:city":"Buchanan",
    "sg:classifiers":[
        {
            "category":"Autos & Motor Vehicles",
            "subcategory":"Auto Supplies",
            "type":"Retail Goods"
        }
    ],
    "sg:phone":"+1 770 646 8095",
    "sg:postcode":"30113",
    "sg:province":"GA",
    "wof:name":"J & J Tire & Brake",
    "wof:placetype":"venue"
},
  "geometry": {"coordinates":[-85.292393,33.84478],"type":"Point"}
}