{
  "type": "Feature",
  "properties": {
    "iso:country":"US",
    "sg:address":"650 Russell Pkwy",
    "sg:city":"Warner Robins",
    "sg:classifiers":[
        {
            "category":"Retail",
            "subcategory":"Auto Repair",
            "type":"Services"
        }
    ],
    "sg:phone":"+1 478 929 5909",
    "sg:postcode":"31088",
    "sg:province":"GA",
    "sg:website":"www.importsonly.net",
    "wof:name":"Imports Only Inc",
    "wof:placetype":"venue"
},
  "geometry": {"coordinates":[-83.632401,32.594047],"type":"Point"}
}