{
  "type": "Feature",
  "properties": {
    "addr:full":"320 Pilgramage Pointe Alpharetta GA 30022",
    "addr:housenumber":"320",
    "addr:postcode":"30022",
    "addr:street":"Pilgramage Pointe",
    "iso:country":"US",
    "sg:address":"320 Pilgramage Pointe",
    "sg:city":"Alpharetta",
    "sg:classifiers":[
        {
            "category":"Building & Trades",
            "subcategory":"Landscaping Services",
            "type":"Services"
        }
    ],
    "sg:phone":"+1 770 663 0754",
    "sg:postcode":"30022",
    "sg:province":"GA",
    "sg:tags":[
        "house",
        "construction",
        "landscape"
    ],
    "wof:name":"Urbanscapes",
    "wof:placetype":"venue"
},
  "geometry": {"coordinates":[-84.248609,34.036574],"type":"Point"}
}