{
  "type": "Feature",
  "properties": {
    "iso:country":"US",
    "sg:address":"202 Cassidy Rd",
    "sg:city":"Thomasville",
    "sg:classifiers":[
        {
            "category":"Retail",
            "subcategory":"Laundry & Dry Cleaning",
            "type":"Services"
        }
    ],
    "sg:phone":"+1 229 226 6242",
    "sg:postcode":"31792",
    "sg:province":"GA",
    "sg:tags":[
        "rental",
        "uniform"
    ],
    "wof:name":"Aramark",
    "wof:placetype":"venue"
},
  "geometry": {"coordinates":[-83.992373,30.849815],"type":"Point"}
}