{
  "type": "Feature",
  "properties": {
    "addr:full":"1465 Bentcreek Dr Marietta GA 30062",
    "addr:housenumber":"1465",
    "addr:postcode":"30062",
    "addr:street":"Bentcreek Dr",
    "iso:country":"US",
    "sg:address":"1465 Bentcreek Dr",
    "sg:city":"Marietta",
    "sg:classifiers":[
        {
            "category":"Retail",
            "subcategory":"Photofinishing",
            "type":"Services"
        }
    ],
    "sg:phone":"+1 770 321 2440",
    "sg:postcode":"30062",
    "sg:province":"GA",
    "sg:tags":[
        "photo",
        "restoration",
        "retouching"
    ],
    "sg:website":"http://www.soleilphotography.com",
    "wof:name":"Soleil Photography",
    "wof:placetype":"venue"
},
  "geometry": {"coordinates":[-84.50882,33.97905],"type":"Point"}
}