{
  "type": "Feature",
  "properties": {
    "addr:full":"4285 Roswell Rd NE Atlanta GA 30342",
    "addr:housenumber":"4285;rd",
    "addr:postcode":"30342",
    "addr:street":"Roswell;Ne",
    "iso:country":"US",
    "sg:address":"4285 Roswell Rd NE",
    "sg:city":"Atlanta",
    "sg:classifiers":[
        {
            "category":"Cinema",
            "subcategory":"Movie Rental",
            "type":"Entertainment"
        }
    ],
    "sg:phone":"+1 404 843 8932",
    "sg:postcode":"30342",
    "sg:province":"GA",
    "sg:tags":[
        "game",
        "video"
    ],
    "sg:website":"www.ebgames.com",
    "wof:name":"Eb Games",
    "wof:placetype":"venue"
},
  "geometry": {"coordinates":[-84.380898,33.872101],"type":"Point"}
}