{
  "type": "Feature",
  "properties": {
    "addr:full":"4711 Stagecoach Rd Albany GA 31705",
    "addr:housenumber":"4711",
    "addr:postcode":"31705",
    "addr:street":"Stagecoach Rd",
    "iso:country":"US",
    "sg:address":"4711 Stagecoach Rd",
    "sg:city":"Albany",
    "sg:classifiers":[
        {
            "category":"Home & Garden",
            "subcategory":"Building Materials",
            "type":"Retail Goods"
        }
    ],
    "sg:phone":"+1 229 446 0606",
    "sg:postcode":"31705",
    "sg:province":"GA",
    "sg:tags":[
        "glass",
        "window",
        "plate"
    ],
    "wof:name":"Novus Auto Glass Repair",
    "wof:placetype":"venue"
},
  "geometry": {"coordinates":[-84.118728,31.456542],"type":"Point"}
}