{
  "type": "Feature",
  "properties": {
    "addr:full":"139 Maple St Monticello GA 31064",
    "addr:housenumber":"139",
    "addr:postcode":"31064",
    "addr:street":"Maple St",
    "iso:country":"US",
    "sg:address":"139 Maple St",
    "sg:city":"Monticello",
    "sg:classifiers":[
        {
            "category":"Insurance",
            "subcategory":"Insurance Agent",
            "type":"Services"
        }
    ],
    "sg:phone":"+1 706 468 8869",
    "sg:postcode":"31064",
    "sg:province":"GA",
    "wof:name":"Paul Holmes Office",
    "wof:placetype":"venue"
},
  "geometry": {"coordinates":[-83.685907,33.302049],"type":"Point"}
}