{
  "type": "Feature",
  "properties": {
    "iso:country":"US",
    "sg:address":"890 Herrington Bend Rd NW",
    "sg:city":"Calhoun",
    "sg:classifiers":[
        {
            "category":"Building & Trades",
            "subcategory":"Plumbing",
            "type":"Services"
        }
    ],
    "sg:phone":"+1 706 625 2389",
    "sg:postcode":"30701",
    "sg:province":"GA",
    "sg:tags":[
        "contractor"
    ],
    "wof:name":"Dp Plumbing Electric",
    "wof:placetype":"venue"
},
  "geometry": {"coordinates":[-84.99747600000001,34.522759],"type":"Point"}
}