{
  "type": "Feature",
  "properties": {
    "addr:full":"2004 Melrose Dr Augusta GA 30906",
    "addr:housenumber":"2004",
    "addr:postcode":"30906",
    "addr:street":"Melrose Dr",
    "iso:country":"US",
    "sg:address":"2004 Melrose Dr",
    "sg:city":"Augusta",
    "sg:classifiers":[
        {
            "category":"Manufacturing",
            "subcategory":"Printing",
            "type":"Manufacturing & Wholesale Goods"
        }
    ],
    "sg:phone":"+1 706 560 1828",
    "sg:postcode":"30906",
    "sg:province":"GA",
    "sg:tags":[
        "periodical"
    ],
    "wof:name":"Open Magazine",
    "wof:placetype":"venue"
},
  "geometry": {"coordinates":[-82.02562500000001,33.40297],"type":"Point"}
}