{
  "type": "Feature",
  "properties": {
    "iso:country":"US",
    "sg:address":"2900 Green Meadows Dr",
    "sg:city":"Augusta",
    "sg:classifiers":[
        {
            "category":"Recreation",
            "type":"Entertainment"
        }
    ],
    "sg:phone":"+1 706 798 1533",
    "sg:postcode":"30906",
    "sg:province":"GA",
    "sg:tags":[
        "course",
        "golf"
    ],
    "wof:name":"Green Meadows Country Club",
    "wof:placetype":"venue"
},
  "geometry": {"coordinates":[-82.04033699999999,33.417538],"type":"Point"}
}