{
  "type": "Feature",
  "properties": {
    "iso:country":"US",
    "sg:address":"350 Fieldstone Ln",
    "sg:city":"Covington",
    "sg:classifiers":[
        {
            "category":"Autos & Motor Vehicles",
            "subcategory":"Fuel & Gas Station",
            "type":"Retail Goods"
        }
    ],
    "sg:phone":"+1 770 788 9200",
    "sg:postcode":"30016",
    "sg:province":"GA",
    "sg:tags":[
        "station",
        "gasoline"
    ],
    "wof:name":"JS Worldmart Citgo",
    "wof:placetype":"venue"
},
  "geometry": {"coordinates":[-83.92705100000001,33.573365],"type":"Point"}
}