{
  "type": "Feature",
  "properties": {
    "iso:country":"US",
    "sg:address":"215 W Gordon Ave",
    "sg:city":"Rossville",
    "sg:classifiers":[
        {
            "category":"Freight",
            "type":"Transportation"
        }
    ],
    "sg:phone":"+1 706 858 6937",
    "sg:postcode":"30741",
    "sg:province":"GA",
    "sg:tags":[
        "trucking"
    ],
    "sg:website":"www.sandh-trucking.com",
    "wof:name":"S & H Trucking Inc",
    "wof:placetype":"venue"
},
  "geometry": {"coordinates":[-85.289714,34.984142],"type":"Point"}
}