{
  "type": "Feature",
  "properties": {
    "addr:full":"2903 N Patterson St Valdosta GA 31602",
    "addr:housenumber":"2903",
    "addr:postcode":"31602",
    "addr:street":"N Patterson St",
    "iso:country":"US",
    "sg:address":"2903 N Patterson St",
    "sg:city":"Valdosta",
    "sg:classifiers":[
        {
            "category":"Utilities",
            "subcategory":"Mobile Phone",
            "type":"Services"
        }
    ],
    "sg:phone":"+1 912 247 8300",
    "sg:postcode":"31602",
    "sg:province":"GA",
    "sg:tags":[
        "communication",
        "radiotelephone"
    ],
    "wof:name":"United States Cellular Corp",
    "wof:placetype":"venue"
},
  "geometry": {"coordinates":[-83.291645,30.873917],"type":"Point"}
}