{
  "type": "Feature",
  "properties": {
    "iso:country":"US",
    "sg:address":"263 Mac Johnson Rd NW",
    "sg:city":"Cartersville",
    "sg:classifiers":[
        {
            "category":"Real Estate",
            "subcategory":"Real Estate Operator",
            "type":"Services"
        }
    ],
    "sg:phone":"+1 770 386 4414",
    "sg:postcode":"30121",
    "sg:province":"GA",
    "sg:tags":[
        "mobile",
        "site",
        "home",
        "rental",
        "trailer",
        "utility"
    ],
    "wof:name":"Ansley Park Of Cartersville",
    "wof:placetype":"venue"
},
  "geometry": {"coordinates":[-84.84553699999999,34.233976],"type":"Point"}
}