{
  "type": "Feature",
  "properties": {
    "addr:full":"3465 Highcroft Cir NW Norcross GA 30092",
    "addr:housenumber":"3465",
    "addr:postcode":"30092",
    "addr:street":"Highcroft Cir Nw",
    "iso:country":"US",
    "sg:address":"3465 Highcroft Cir NW",
    "sg:city":"Norcross",
    "sg:classifiers":[
        {
            "category":"Manufacturing",
            "subcategory":"Paper Products",
            "type":"Manufacturing & Wholesale Goods"
        }
    ],
    "sg:phone":"+1 770 449 4324",
    "sg:postcode":"30092",
    "sg:province":"GA",
    "sg:tags":[
        "stationery",
        "mfg"
    ],
    "wof:name":"Paper Perfect",
    "wof:placetype":"venue"
},
  "geometry": {"coordinates":[-84.203502,33.970885],"type":"Point"}
}