{
  "type": "Feature",
  "properties": {
    "addr:full":"5180 Charmant Pl Atlanta GA 30360",
    "addr:housenumber":"5180",
    "addr:postcode":"30360",
    "addr:street":"Charmant Pl",
    "iso:country":"US",
    "sg:address":"5180 Charmant Pl",
    "sg:city":"Atlanta",
    "sg:classifiers":[
        {
            "category":"Professional",
            "subcategory":"Business Services",
            "type":"Services"
        }
    ],
    "sg:phone":"+1 770 396 8434",
    "sg:postcode":"30360",
    "sg:province":"GA",
    "wof:name":"Bnb Corporate Solutions Inc",
    "wof:placetype":"venue"
},
  "geometry": {"coordinates":[-84.272615,33.949181],"type":"Point"}
}