{
  "type": "Feature",
  "properties": {
    "addr:full":"3079 Pio Nono Ave Macon GA 31206",
    "addr:housenumber":"3079",
    "addr:postcode":"31206",
    "addr:street":"Pio Nono Ave",
    "iso:country":"US",
    "sg:address":"3079 Pio Nono Ave",
    "sg:city":"Macon",
    "sg:classifiers":[
        {
            "category":"Banks & Credit Unions",
            "subcategory":"Bank",
            "type":"Services"
        }
    ],
    "sg:phone":"+1 478 781 0820",
    "sg:postcode":"31206",
    "sg:province":"GA",
    "sg:tags":[
        "personal",
        "institution"
    ],
    "wof:name":"American General Finance Inc",
    "wof:placetype":"venue"
},
  "geometry": {"coordinates":[-83.66314,32.806885],"type":"Point"}
}