{
  "type": "Feature",
  "properties": {
    "iso:country":"US",
    "sg:address":"6365 Joe Frank Harris Pkwy NW",
    "sg:city":"Adairsville",
    "sg:classifiers":[
        {
            "category":"Restaurant",
            "type":"Food & Drink"
        }
    ],
    "sg:phone":"+1 770 773 3807",
    "sg:postcode":"30103",
    "sg:province":"GA",
    "wof:name":"Whistle Stop Drive Thru",
    "wof:placetype":"venue"
},
  "geometry": {"coordinates":[-84.929796,34.373092],"type":"Point"}
}