{
  "type": "Feature",
  "properties": {
    "addr:full":"2225 E Walnut Ave Dalton GA 30721",
    "addr:housenumber":"2225",
    "addr:postcode":"30721",
    "addr:street":"E Walnut Ave",
    "iso:country":"US",
    "sg:address":"2225 E Walnut Ave",
    "sg:city":"Dalton",
    "sg:classifiers":[
        {
            "category":"Shopping",
            "type":"Retail Goods"
        }
    ],
    "sg:phone":"+1 706 226 7179",
    "sg:postcode":"30721",
    "sg:province":"GA",
    "sg:tags":[
        "telephone",
        "cellular"
    ],
    "wof:name":"Communications & Electronic",
    "wof:placetype":"venue"
},
  "geometry": {"coordinates":[-84.927286,34.767103],"type":"Point"}
}