{
  "type": "Feature",
  "properties": {
    "addr:full":"2 Lakeland Dr NW Rome GA 30165",
    "addr:housenumber":"2",
    "addr:postcode":"ga 30165",
    "addr:street":"Lakeland Dr Nw",
    "iso:country":"US",
    "sg:address":"2 Lakeland Dr NW",
    "sg:city":"Rome",
    "sg:classifiers":[
        {
            "category":"Freight",
            "type":"Transportation"
        }
    ],
    "sg:phone":"+1 706 235 7253",
    "sg:postcode":"30165",
    "sg:province":"GA",
    "sg:tags":[
        "dry",
        "bulk",
        "trucking"
    ],
    "wof:name":"Sand Man Transportation",
    "wof:placetype":"venue"
},
  "geometry": {"coordinates":[-85.30775800000001,34.265055],"type":"Point"}
}