{
  "type": "Feature",
  "properties": {
    "iso:country":"US",
    "sg:address":"475 Moreland Ave NE",
    "sg:city":"Atlanta",
    "sg:classifiers":[
        {
            "category":"Shopping",
            "subcategory":"Discount & Variety Stores",
            "type":"Retail Goods"
        }
    ],
    "sg:phone":"+1 404 635 1004",
    "sg:postcode":"30307",
    "sg:province":"GA",
    "wof:name":"Dollar King",
    "wof:placetype":"venue"
},
  "geometry": {"coordinates":[-84.349124,33.766005],"type":"Point"}
}