{
  "type": "Feature",
  "properties": {
    "iso:country":"US",
    "sg:address":"503 E Spring St",
    "sg:city":"Monroe",
    "sg:classifiers":[
        {
            "category":"Personal",
            "subcategory":"Beauty Salon",
            "type":"Services"
        }
    ],
    "sg:phone":"+1 770 267 0466",
    "sg:postcode":"30655",
    "sg:province":"GA",
    "sg:tags":[
        "shop"
    ],
    "wof:name":"Mane Street Hair Studio",
    "wof:placetype":"venue"
},
  "geometry": {"coordinates":[-83.70710800000001,33.79689],"type":"Point"}
}