{
  "type": "Feature",
  "properties": {
    "addr:full":"1004 Bankhead Hwy Carrollton GA 30117",
    "addr:housenumber":"1004",
    "addr:postcode":"30117",
    "addr:street":"Bankhead Hwy",
    "iso:country":"US",
    "sg:address":"1004 Bankhead Hwy",
    "sg:city":"Carrollton",
    "sg:classifiers":[
        {
            "category":"Banks & Credit Unions",
            "subcategory":"Bank",
            "type":"Services"
        }
    ],
    "sg:phone":"+1 770 834 2399",
    "sg:postcode":"30117",
    "sg:province":"GA",
    "sg:tags":[
        "loan",
        "mortgage"
    ],
    "wof:name":"Citi Financial",
    "wof:placetype":"venue"
},
  "geometry": {"coordinates":[-85.046392,33.591995],"type":"Point"}
}