{
  "type": "Feature",
  "properties": {
    "addr:full":"143 E Main St Rutledge GA 30663",
    "addr:housenumber":"143",
    "addr:postcode":"30663",
    "addr:street":"E Main St",
    "iso:country":"US",
    "sg:address":"143 E Main St",
    "sg:city":"Rutledge",
    "sg:classifiers":[
        {
            "category":"Retail",
            "subcategory":"Auto Repair",
            "type":"Services"
        }
    ],
    "sg:phone":"+1 706 557 8880",
    "sg:postcode":"30663",
    "sg:province":"GA",
    "sg:tags":[
        "body"
    ],
    "wof:name":"Accidntal Frends Collision Ctr",
    "wof:placetype":"venue"
},
  "geometry": {"coordinates":[-83.606925,33.624691],"type":"Point"}
}