{
  "type": "Feature",
  "properties": {
    "addr:full":"75 Arcado Rd SW Lilburn GA 30047",
    "addr:housenumber":"75",
    "addr:postcode":"30047",
    "addr:street":"Arcado Rd Sw",
    "iso:country":"US",
    "sg:address":"75 Arcado Rd SW",
    "sg:city":"Lilburn",
    "sg:classifiers":[
        {
            "category":"Building & Trades",
            "subcategory":"Construction",
            "type":"Services"
        }
    ],
    "sg:phone":"+1 770 279 9321",
    "sg:postcode":"30047",
    "sg:province":"GA",
    "sg:tags":[
        "contractor"
    ],
    "wof:name":"Contractors In Genesis Grading",
    "wof:placetype":"venue"
},
  "geometry": {"coordinates":[-84.114091,33.893575],"type":"Point"}
}