{
  "type": "Feature",
  "properties": {
    "iso:country":"US",
    "sg:address":"38 Imperial Dr",
    "sg:city":"Hiram",
    "sg:classifiers":[
        {
            "category":"Home & Garden",
            "subcategory":"Carpets & Floor Coverings",
            "type":"Retail Goods"
        }
    ],
    "sg:phone":"+1 678 567 0382",
    "sg:postcode":"30141",
    "sg:province":"GA",
    "wof:name":"Vaughns Carpet",
    "wof:placetype":"venue"
},
  "geometry": {"coordinates":[-84.74085100000001,33.909378],"type":"Point"}
}