{
  "type": "Feature",
  "properties": {
    "iso:country":"US",
    "sg:address":"3258 Loch Laurel Rd",
    "sg:city":"Lake Park",
    "sg:classifiers":[
        {
            "category":"Building & Trades",
            "subcategory":"Construction",
            "type":"Services"
        }
    ],
    "sg:phone":"+1 229 245 9971",
    "sg:postcode":"31636",
    "sg:province":"GA",
    "sg:tags":[
        "general",
        "contractor"
    ],
    "wof:name":"K & K Construction",
    "wof:placetype":"venue"
},
  "geometry": {"coordinates":[-83.25143300000001,30.7388],"type":"Point"}
}