{
  "type": "Feature",
  "properties": {
    "addr:full":"25 Waburn Walk Dallas GA 30132",
    "addr:housenumber":"25",
    "addr:postcode":"30132",
    "addr:street":"Waburn Walk",
    "iso:country":"US",
    "sg:address":"25 Waburn Walk",
    "sg:city":"Dallas",
    "sg:classifiers":[
        {
            "category":"Food & Beverages",
            "subcategory":"Groceries & Convenience Stores",
            "type":"Retail Goods"
        }
    ],
    "sg:phone":"+1 770 443 0037",
    "sg:postcode":"30132",
    "sg:province":"GA",
    "wof:name":"T L Food Service",
    "wof:placetype":"venue"
},
  "geometry": {"coordinates":[-84.81782,33.976701],"type":"Point"}
}