{
  "type": "Feature",
  "properties": {
    "iso:country":"US",
    "sg:address":"34 E 1st St",
    "sg:city":"Dawsonville",
    "sg:classifiers":[
        {
            "category":"Personal",
            "subcategory":"Beauty Salon",
            "type":"Services"
        },
        {
            "category":"Personal",
            "subcategory":"Hair Removal",
            "type":"Services"
        },
        {
            "category":"Personal",
            "subcategory":"Barber",
            "type":"Services"
        }
    ],
    "sg:phone":"+1 706 265 6551",
    "sg:postcode":"30534",
    "sg:province":"GA",
    "wof:name":"Salon Zaya",
    "wof:placetype":"venue"
},
  "geometry": {"coordinates":[-84.118765,34.419862],"type":"Point"}
}