{
  "type": "Feature",
  "properties": {
    "addr:full":"10745 Alpharetta Hwy Roswell GA 30076",
    "addr:housenumber":"10745",
    "addr:postcode":"30076",
    "addr:street":"Alpharetta Hwy",
    "iso:country":"US",
    "sg:address":"10745 Alpharetta Hwy",
    "sg:city":"Roswell",
    "sg:classifiers":[
        {
            "category":"Home & Garden",
            "subcategory":"Building Materials",
            "type":"Retail Goods"
        }
    ],
    "sg:phone":"+1 770 993 0552",
    "sg:postcode":"30076",
    "sg:province":"GA",
    "sg:tags":[
        "wallpaper"
    ],
    "wof:name":"Warehouse Wallpapers Inc",
    "wof:placetype":"venue"
},
  "geometry": {"coordinates":[-84.33779800000001,34.049831],"type":"Point"}
}