{
  "type": "Feature",
  "properties": {
    "addr:full":"333 Cobb Pkwy N Marietta GA 30062",
    "addr:housenumber":"333",
    "addr:postcode":"30062",
    "addr:street":"Cobb Pkwy N",
    "iso:country":"US",
    "sg:address":"333 Cobb Pkwy N",
    "sg:city":"Marietta",
    "sg:classifiers":[
        {
            "category":"Autos & Motor Vehicles",
            "subcategory":"Motorcycle Sales",
            "type":"Retail Goods"
        }
    ],
    "sg:phone":"+1 770 425 4000",
    "sg:postcode":"30062",
    "sg:province":"GA",
    "sg:website":"www.motionslive.com",
    "wof:name":"Motions-Honda-Kawasaki-Suzuki Yamaha",
    "wof:placetype":"venue"
},
  "geometry": {"coordinates":[-84.528012,33.96016],"type":"Point"}
}