{
  "type": "Feature",
  "properties": {
    "iso:country":"US",
    "sg:address":"101 Bridgewater Dr",
    "sg:city":"Peachtree City",
    "sg:classifiers":[
        {
            "category":"Professional",
            "type":"Services"
        }
    ],
    "sg:phone":"+1 770 631 2466",
    "sg:postcode":"30269",
    "sg:province":"GA",
    "wof:name":"Bill Everage",
    "wof:placetype":"venue"
},
  "geometry": {"coordinates":[-84.59653,33.421104],"type":"Point"}
}