{
  "type": "Feature",
  "properties": {
    "iso:country":"US",
    "sg:address":"3515 Betty Wise Rd",
    "sg:city":"Dawson",
    "sg:classifiers":[
        {
            "category":"Organizations",
            "subcategory":"Community Association",
            "type":"Services"
        }
    ],
    "sg:phone":"+1 229 995 4890",
    "sg:postcode":"39826",
    "sg:province":"GA",
    "sg:tags":[
        "fraternal"
    ],
    "wof:name":"Southpoint Plantation Lodge",
    "wof:placetype":"venue"
},
  "geometry": {"coordinates":[-84.335843,31.803541],"type":"Point"}
}