{
  "type": "Feature",
  "properties": {
    "iso:country":"US",
    "sg:address":"308 W Main St",
    "sg:city":"Thomaston",
    "sg:classifiers":[
        {
            "category":"Health Services",
            "subcategory":"Doctor",
            "type":"Services"
        }
    ],
    "sg:phone":"+1 706 647 7191",
    "sg:postcode":"30286",
    "sg:province":"GA",
    "sg:tags":[
        "physician",
        "surgeon"
    ],
    "wof:name":"Lawrence Allen MD",
    "wof:placetype":"venue"
},
  "geometry": {"coordinates":[-84.330997,32.888708],"type":"Point"}
}