{
  "type": "Feature",
  "properties": {
    "addr:full":"500 Ballard Bridge Rd Carrollton GA 30117",
    "addr:housenumber":"500",
    "addr:postcode":"30117",
    "addr:street":"Ballard Bridge Rd",
    "iso:country":"US",
    "sg:address":"500 Ballard Bridge Rd",
    "sg:city":"Carrollton",
    "sg:classifiers":[
        {
            "category":"Government",
            "subcategory":"Office",
            "type":"Public Place"
        }
    ],
    "sg:phone":"+1 770 830 2019",
    "sg:postcode":"30117",
    "sg:province":"GA",
    "sg:tags":[
        "village"
    ],
    "wof:name":"Carrollton Land Application",
    "wof:placetype":"venue"
},
  "geometry": {"coordinates":[-85.13836999999999,33.580769],"type":"Point"}
}