{
  "type": "Feature",
  "properties": {
    "iso:country":"US",
    "sg:address":"1283 Columbia Dr",
    "sg:city":"Decatur",
    "sg:classifiers":[
        {
            "category":"Social Services",
            "type":"Services"
        }
    ],
    "sg:phone":"+1 404 289 5775",
    "sg:postcode":"30032",
    "sg:province":"GA",
    "wof:name":"Headstart",
    "wof:placetype":"venue"
},
  "geometry": {"coordinates":[-84.26548099999999,33.752126],"type":"Point"}
}