{
  "type": "Feature",
  "properties": {
    "iso:country":"US",
    "sg:address":"925 W Taylor St",
    "sg:city":"Griffin",
    "sg:classifiers":[
        {
            "category":"Recreation",
            "type":"Entertainment"
        }
    ],
    "sg:phone":"+1 770 233 2696",
    "sg:postcode":"30223",
    "sg:province":"GA",
    "sg:tags":[
        "parlor",
        "billiard"
    ],
    "wof:name":"Anytime",
    "wof:placetype":"venue"
},
  "geometry": {"coordinates":[-84.27747599999999,33.247475],"type":"Point"}
}