{
  "type": "Feature",
  "properties": {
    "iso:country":"US",
    "sg:address":"234 Bonds Rd",
    "sg:city":"Canon",
    "sg:classifiers":[
        {
            "category":"Building & Trades",
            "subcategory":"Construction",
            "type":"Services"
        }
    ],
    "sg:phone":"+1 706 245 5194",
    "sg:postcode":"30520",
    "sg:province":"GA",
    "sg:tags":[
        "concrete",
        "contractor"
    ],
    "wof:name":"Bob Finley Concrete Constr",
    "wof:placetype":"venue"
},
  "geometry": {"coordinates":[-83.04592,34.29068],"type":"Point"}
}