{
  "type": "Feature",
  "properties": {
    "iso:country":"US",
    "sg:address":"1610 Hosea L Williams Dr Ste C",
    "sg:city":"Atlanta",
    "sg:classifiers":[
        {
            "category":"Real Estate",
            "subcategory":"Real Estate Services",
            "type":"Services"
        }
    ],
    "sg:phone":"+1 404 218 1040",
    "sg:postcode":"30316",
    "sg:province":"GA",
    "sg:tags":[
        "home",
        "inspector"
    ],
    "sg:website":"www.home-probe.com",
    "wof:name":"Home-Probe, Inc.",
    "wof:placetype":"venue"
},
  "geometry": {"coordinates":[-84.33501800000001,33.75369],"type":"Point"}
}