{
  "type": "Feature",
  "properties": {
    "iso:country":"US",
    "sg:address":"347 Fountain St",
    "sg:city":"Elberton",
    "sg:classifiers":[
        {
            "category":"Professional",
            "type":"Services"
        }
    ],
    "sg:phone":"+1 706 283 0860",
    "sg:postcode":"30635",
    "sg:province":"GA",
    "wof:name":"Landers",
    "wof:placetype":"venue"
},
  "geometry": {"coordinates":[-82.8531,34.112395],"type":"Point"}
}