{
  "type": "Feature",
  "properties": {
    "addr:full":"183 Mc Bride Rd Fayetteville GA 30215",
    "addr:housenumber":"183",
    "addr:postcode":"30215",
    "addr:street":"Mc Bride Rd",
    "iso:country":"US",
    "sg:address":"183 Mc Bride Rd",
    "sg:city":"Fayetteville",
    "sg:classifiers":[
        {
            "category":"Professional",
            "subcategory":"Business Services",
            "type":"Services"
        }
    ],
    "sg:phone":"+1 770 719 0881",
    "sg:postcode":"30215",
    "sg:province":"GA",
    "wof:name":"Jack Deal Enterprises Inc",
    "wof:placetype":"venue"
},
  "geometry": {"coordinates":[-84.42936400000001,33.387773],"type":"Point"}
}