{
  "type": "Feature",
  "properties": {
    "addr:full":"4722 Woodvale Dr NW Atlanta GA 30327",
    "addr:housenumber":"4722",
    "addr:postcode":"30327",
    "addr:street":"Woodvale Dr Nw",
    "iso:country":"US",
    "sg:address":"4722 Woodvale Dr NW",
    "sg:city":"Atlanta",
    "sg:classifiers":[
        {
            "category":"Professional",
            "subcategory":"Business Services",
            "type":"Services"
        }
    ],
    "sg:phone":"+1 404 303 0850",
    "sg:postcode":"30327",
    "sg:province":"GA",
    "wof:name":"Candler Interiors",
    "wof:placetype":"venue"
},
  "geometry": {"coordinates":[-84.419905,33.886747],"type":"Point"}
}