{
  "type": "Feature",
  "properties": {
    "iso:country":"US",
    "sg:address":"179 del Rio Rd",
    "sg:city":"Demorest",
    "sg:classifiers":[
        {
            "category":"Farming",
            "subcategory":"Farm & Veterinary Services",
            "type":"Manufacturing & Wholesale Goods"
        }
    ],
    "sg:phone":"+1 706 754 2587",
    "sg:postcode":"30535",
    "sg:province":"GA",
    "sg:tags":[
        "livestock"
    ],
    "wof:name":"Miracle Farms",
    "wof:placetype":"venue"
},
  "geometry": {"coordinates":[-83.629193,34.575992],"type":"Point"}
}