{
  "type": "Feature",
  "properties": {
    "iso:country":"US",
    "sg:address":"3308 Winthrop Cir",
    "sg:city":"Marietta",
    "sg:classifiers":[
        {
            "category":"Building & Trades",
            "subcategory":"Locksmith",
            "type":"Services"
        }
    ],
    "sg:phone":"+1 770 308 0341",
    "sg:postcode":"30067",
    "sg:province":"GA",
    "sg:tags":[
        "key"
    ],
    "wof:name":"A A 24 Hour AAA Locksmith",
    "wof:placetype":"venue"
},
  "geometry": {"coordinates":[-84.457109,33.929021],"type":"Point"}
}