{
  "type": "Feature",
  "properties": {
    "iso:country":"US",
    "sg:address":"9104 Middleground Rd",
    "sg:city":"Savannah",
    "sg:classifiers":[
        {
            "category":"Government",
            "subcategory":"Office",
            "type":"Public Place"
        }
    ],
    "sg:phone":"+1 912 927 5393",
    "sg:postcode":"31406",
    "sg:province":"GA",
    "sg:tags":[
        "state"
    ],
    "sg:website":"www.georgia.gov",
    "wof:name":"Georgia Technology Authority",
    "wof:placetype":"venue"
},
  "geometry": {"coordinates":[-81.14998199999999,31.996022],"type":"Point"}
}