{
  "type": "Feature",
  "properties": {
    "iso:country":"US",
    "sg:address":"433 Canton Rd Suite 201A",
    "sg:city":"Cumming",
    "sg:classifiers":[
        {
            "category":"Home & Garden",
            "subcategory":"Home Furnishings",
            "type":"Retail Goods"
        },
        {
            "category":"Building & Trades",
            "subcategory":"Construction",
            "type":"Services"
        },
        {
            "category":"Manufacturing",
            "subcategory":"Building Materials",
            "type":"Manufacturing & Wholesale Goods"
        },
        {
            "category":"Home & Garden",
            "subcategory":"Furniture",
            "type":"Retail Goods"
        }
    ],
    "sg:phone":"+1 404 748 3355",
    "sg:postcode":"30040",
    "sg:province":"GA",
    "sg:tags":[
        "industrial",
        "cabinetmakers-commercial",
        "equipment-household",
        "refacing",
        "resurfacing",
        "cabinet",
        "maker",
        "cabinets-refinishing",
        "kitchen"
    ],
    "sg:website":"http://www.mrcabinetman.com",
    "wof:name":"Mr CabinetMan",
    "wof:placetype":"venue"
},
  "geometry": {"coordinates":[-84.149151,34.216223],"type":"Point"}
}