{
  "type": "Feature",
  "properties": {
    "iso:country":"US",
    "sg:address":"265 Peachtree Center Ave NE",
    "sg:city":"Atlanta",
    "sg:classifiers":[
        {
            "category":"Shopping",
            "subcategory":"Jewelry",
            "type":"Retail Goods"
        }
    ],
    "sg:phone":"+1 404 584 2813",
    "sg:postcode":"30303",
    "sg:province":"GA",
    "sg:tags":[
        "jeweler"
    ],
    "wof:name":"Kahn & Co",
    "wof:placetype":"venue"
},
  "geometry": {"coordinates":[-84.385953,33.761456],"type":"Point"}
}