{
  "type": "Feature",
  "properties": {
    "addr:full":"1439 Bowdon Junction Rd Carrollton GA 30117",
    "addr:housenumber":"1439",
    "addr:postcode":"30117",
    "addr:street":"Bowdon Junction Rd",
    "iso:country":"US",
    "sg:address":"1439 Bowdon Junction Rd",
    "sg:city":"Carrollton",
    "sg:classifiers":[
        {
            "category":"Building & Trades",
            "subcategory":"Construction",
            "type":"Services"
        }
    ],
    "sg:phone":"+1 770 836 0044",
    "sg:postcode":"30117",
    "sg:province":"GA",
    "sg:tags":[
        "maker",
        "cabinet"
    ],
    "wof:name":"Bilt Rite Cabinet Shop",
    "wof:placetype":"venue"
},
  "geometry": {"coordinates":[-85.151706,33.662559],"type":"Point"}
}