{
  "type": "Feature",
  "properties": {
    "addr:full":"227 W Lakemont Dr Kingsland GA 31548",
    "addr:housenumber":"227",
    "addr:postcode":"31548",
    "addr:street":"W Lakemont Dr",
    "iso:country":"US",
    "sg:address":"227 W Lakemont Dr",
    "sg:city":"Kingsland",
    "sg:classifiers":[
        {
            "category":"Building & Trades",
            "subcategory":"Construction",
            "type":"Services"
        }
    ],
    "sg:phone":"+1 912 882 3259",
    "sg:postcode":"31548",
    "sg:province":"GA",
    "sg:tags":[
        "wallpaper"
    ],
    "wof:name":"Judy's Wallpaper",
    "wof:placetype":"venue"
},
  "geometry": {"coordinates":[-81.618646,30.764956],"type":"Point"}
}