{
  "type": "Feature",
  "properties": {
    "iso:country":"US",
    "sg:address":"1019 Collier Rd NW",
    "sg:city":"Atlanta",
    "sg:classifiers":[
        {
            "category":"Home & Garden",
            "subcategory":"Building Materials",
            "type":"Retail Goods"
        }
    ],
    "sg:phone":"+1 770 368 0017",
    "sg:postcode":"30318",
    "sg:province":"GA",
    "sg:tags":[
        "screen",
        "window"
    ],
    "wof:name":"Hide Away Screens",
    "wof:placetype":"venue"
},
  "geometry": {"coordinates":[-84.42057,33.810153],"type":"Point"}
}