{
  "type": "Feature",
  "properties": {
    "addr:full":"10850 Haynes Bridge Rd Alpharetta GA 30022",
    "addr:housenumber":"10850",
    "addr:postcode":"30022",
    "addr:street":"Haynes Bridge Rd",
    "iso:country":"US",
    "sg:address":"10850 Haynes Bridge Rd",
    "sg:city":"Alpharetta",
    "sg:classifiers":[
        {
            "category":"Restaurant",
            "type":"Food & Drink"
        }
    ],
    "sg:phone":"+1 770 751 1160",
    "sg:postcode":"30022",
    "sg:province":"GA",
    "sg:website":"www.tacobell.com",
    "wof:name":"Taco Bell",
    "wof:placetype":"venue"
},
  "geometry": {"coordinates":[-84.286102,34.050301],"type":"Point"}
}