{
  "type": "Feature",
  "properties": {
    "iso:country":"US",
    "sg:address":"3145 Gateway Dr Ste H",
    "sg:city":"Norcross",
    "sg:classifiers":[
        {
            "category":"Shopping",
            "subcategory":"Clothing, Apparel, & Fashions",
            "type":"Retail Goods"
        }
    ],
    "sg:phone":"+1 770 248 0905",
    "sg:postcode":"30071",
    "sg:province":"GA",
    "sg:tags":[
        "children's",
        "clothing"
    ],
    "sg:website":"www.kateandlibby.com",
    "wof:name":"Kate and Libby",
    "wof:placetype":"venue"
},
  "geometry": {"coordinates":[-84.257611,33.932427],"type":"Point"}
}