{
  "type": "Feature",
  "properties": {
    "addr:full":"5474 Laurel Ln NW Lilburn GA 30047",
    "addr:housenumber":"5474",
    "addr:postcode":"30047",
    "addr:street":"Laurel Ln Nw",
    "iso:country":"US",
    "sg:address":"5474 Laurel Ln NW",
    "sg:city":"Lilburn",
    "sg:classifiers":[
        {
            "category":"Freight",
            "type":"Transportation"
        }
    ],
    "sg:phone":"+1 770 921 7234",
    "sg:postcode":"30047",
    "sg:province":"GA",
    "sg:tags":[
        "local",
        "hauling"
    ],
    "wof:name":"Cochran Bobby Hlg & Backhoe",
    "wof:placetype":"venue"
},
  "geometry": {"coordinates":[-84.158114,33.874001],"type":"Point"}
}