{
  "type": "Feature",
  "properties": {
    "addr:full":"1391 Sutters Dr Lawrenceville GA 30045",
    "addr:housenumber":"1391",
    "addr:postcode":"30045",
    "addr:street":"Sutters Dr",
    "iso:country":"US",
    "sg:address":"1391 Sutters Dr",
    "sg:city":"Lawrenceville",
    "sg:classifiers":[
        {
            "category":"Shopping",
            "subcategory":"Gifts & Souvenirs",
            "type":"Retail Goods"
        }
    ],
    "sg:phone":"+1 678 376 0064",
    "sg:postcode":"30045",
    "sg:province":"GA",
    "sg:tags":[
        "shop"
    ],
    "wof:name":"Professional Recruiters",
    "wof:placetype":"venue"
},
  "geometry": {"coordinates":[-83.963075,33.913161],"type":"Point"}
}