{
  "type": "Feature",
  "properties": {
    "addr:full":"4109 Mullikin Rd Evans GA 30809",
    "addr:housenumber":"4109",
    "addr:postcode":"30809",
    "addr:street":"Mullikin Rd",
    "iso:country":"US",
    "sg:address":"4109 Mullikin Rd",
    "sg:city":"Evans",
    "sg:classifiers":[
        {
            "category":"Education",
            "subcategory":"School",
            "type":"Public Place"
        }
    ],
    "sg:phone":"+1 706 447 1016",
    "sg:postcode":"30809",
    "sg:province":"GA",
    "wof:name":"Columbia County School District",
    "wof:placetype":"venue"
},
  "geometry": {"coordinates":[-82.10593799999999,33.572478],"type":"Point"}
}