{
  "type": "Feature",
  "properties": {
    "iso:country":"US",
    "sg:address":"960 Key St",
    "sg:city":"Macon",
    "sg:classifiers":[
        {
            "category":"Banks & Credit Unions",
            "subcategory":"Bank",
            "type":"Services"
        }
    ],
    "sg:phone":"+1 478 784 5860",
    "sg:postcode":"31204",
    "sg:province":"GA",
    "wof:name":"Georgia Power Macon Federal Cu",
    "wof:placetype":"venue"
},
  "geometry": {"coordinates":[-83.67522700000001,32.818786],"type":"Point"}
}