{
  "type": "Feature",
  "properties": {
    "iso:country":"US",
    "sg:address":"1210 Morrow Rd",
    "sg:city":"Morrow",
    "sg:classifiers":[
        {
            "category":"Retail",
            "subcategory":"Funeral Services",
            "type":"Services"
        }
    ],
    "sg:phone":"+1 770 961 2700",
    "sg:postcode":"30260",
    "sg:province":"GA",
    "sg:tags":[
        "cemetery"
    ],
    "wof:name":"Dickson & Son Funeral Home Morrow Chapel",
    "wof:placetype":"venue"
},
  "geometry": {"coordinates":[-84.350998,33.5858],"type":"Point"}
}