{
  "type": "Feature",
  "properties": {
    "addr:full":"107 Ashford Cir La Grange GA 30240",
    "addr:housenumber":"107",
    "addr:postcode":"30240",
    "addr:street":"Ashford Cir",
    "iso:country":"US",
    "sg:address":"107 Ashford Cir",
    "sg:city":"La Grange",
    "sg:classifiers":[
        {
            "category":"Professional",
            "subcategory":"Management & Consulting",
            "type":"Services"
        }
    ],
    "sg:phone":"+1 706 883 6403",
    "sg:postcode":"30240",
    "sg:province":"GA",
    "wof:name":"Ellis & Ellis",
    "wof:placetype":"venue"
},
  "geometry": {"coordinates":[-85.050105,33.084204],"type":"Point"}
}