{
  "type": "Feature",
  "properties": {
    "addr:full":"75 Piedmont Ave NE Atlanta GA 30303",
    "addr:housenumber":"75",
    "addr:postcode":"30303",
    "addr:street":"Piedmont Ave Ne",
    "iso:country":"US",
    "sg:address":"75 Piedmont Ave NE",
    "sg:city":"Atlanta",
    "sg:classifiers":[
        {
            "category":"Communications",
            "subcategory":"Radio Station",
            "type":"Services"
        }
    ],
    "sg:phone":"+1 404 765 9750",
    "sg:postcode":"30303",
    "sg:province":"GA",
    "wof:name":"Wjzz Radio Station",
    "wof:placetype":"venue"
},
  "geometry": {"coordinates":[-84.382301,33.754799],"type":"Point"}
}