{
  "type": "Feature",
  "properties": {
    "iso:country":"US",
    "sg:address":"99 Baldwin Ct",
    "sg:city":"Newnan",
    "sg:classifiers":[
        {
            "category":"Insurance",
            "subcategory":"Hazard Insurance",
            "type":"Services"
        }
    ],
    "sg:phone":"+1 770 683 3535",
    "sg:postcode":"30263",
    "sg:province":"GA",
    "sg:tags":[
        "commercial",
        "business"
    ],
    "wof:name":"The Vermilya Insurance Group",
    "wof:placetype":"venue"
},
  "geometry": {"coordinates":[-84.79061900000001,33.409504],"type":"Point"}
}