{
  "type": "Feature",
  "properties": {
    "iso:country":"US",
    "sg:address":"3200 Post Woods Dr",
    "sg:city":"Atlanta",
    "sg:classifiers":[
        {
            "category":"Real Estate",
            "subcategory":"Real Estate Operator",
            "type":"Services"
        }
    ],
    "sg:phone":"+1 770 952 0848",
    "sg:postcode":"30339",
    "sg:province":"GA",
    "sg:tags":[
        "apartment"
    ],
    "sg:website":"www.madisonviningsridge.com",
    "wof:name":"Madison Vinings Ridge",
    "wof:placetype":"venue"
},
  "geometry": {"coordinates":[-84.454354,33.876003],"type":"Point"}
}