{
  "type": "Feature",
  "properties": {
    "addr:full":"846 Ponce de Leon Ter NE Atlanta GA 30306",
    "addr:housenumber":"846",
    "addr:postcode":"30306",
    "addr:street":"Ponce De Leon Ter Ne",
    "iso:country":"US",
    "sg:address":"846 Ponce de Leon Ter NE",
    "sg:city":"Atlanta",
    "sg:classifiers":[
        {
            "category":"Professional",
            "subcategory":"Detective & Security Services",
            "type":"Services"
        }
    ],
    "sg:phone":"+1 404 873 0403",
    "sg:postcode":"30306",
    "sg:province":"GA",
    "sg:tags":[
        "information",
        "bureau"
    ],
    "wof:name":"Geared To Go Services Inc",
    "wof:placetype":"venue"
},
  "geometry": {"coordinates":[-84.36054,33.778756],"type":"Point"}
}