{
  "type": "Feature",
  "properties": {
    "iso:country":"US",
    "sg:address":"1365 Clifton Rd NE Ste A1200",
    "sg:city":"Atlanta",
    "sg:classifiers":[
        {
            "category":"Health Services",
            "subcategory":"Doctor",
            "type":"Services"
        }
    ],
    "sg:phone":"+1 404 778 5299",
    "sg:postcode":"30322",
    "sg:province":"GA",
    "sg:tags":[
        "physician",
        "surgeons",
        "anesthesiology",
        "surgeon",
        "cardiology"
    ],
    "wof:name":"Alexander Wayne Md",
    "wof:placetype":"venue"
},
  "geometry": {"coordinates":[-84.32096900000001,33.7925],"type":"Point"}
}