{
  "type": "Feature",
  "properties": {
    "iso:country":"US",
    "sg:address":"9135 S Main St",
    "sg:city":"Jonesboro",
    "sg:classifiers":[
        {
            "category":"Building & Trades",
            "subcategory":"Construction",
            "type":"Services"
        }
    ],
    "sg:phone":"+1 770 478 0628",
    "sg:postcode":"30236",
    "sg:province":"GA",
    "sg:tags":[
        "system",
        "contractor",
        "air conditioning"
    ],
    "wof:name":"Bowen & Sons AAA Services",
    "wof:placetype":"venue"
},
  "geometry": {"coordinates":[-84.348067,33.504282],"type":"Point"}
}