{
  "type": "Feature",
  "properties": {
    "iso:country":"US",
    "sg:address":"707 Lake Side Ln",
    "sg:city":"Canton",
    "sg:classifiers":[
        {
            "category":"Professional",
            "subcategory":"Business Services",
            "type":"Services"
        }
    ],
    "sg:phone":"+1 770 345 8715",
    "sg:postcode":"30114",
    "sg:province":"GA",
    "wof:name":"Infotallycom LLC",
    "wof:placetype":"venue"
},
  "geometry": {"coordinates":[-84.53081899999999,34.169202],"type":"Point"}
}