{
  "type": "Feature",
  "properties": {
    "iso:country":"US",
    "sg:address":"130 Ruby St",
    "sg:city":"Wadley",
    "sg:classifiers":[
        {
            "category":"Personal",
            "subcategory":"Beauty Salon",
            "type":"Services"
        }
    ],
    "sg:phone":"+1 478 252 2017",
    "sg:postcode":"30477",
    "sg:province":"GA",
    "sg:tags":[
        "manicuring"
    ],
    "wof:name":"Maw Nails",
    "wof:placetype":"venue"
},
  "geometry": {"coordinates":[-82.40631,32.860059],"type":"Point"}
}