{
  "type": "Feature",
  "properties": {
    "iso:country":"US",
    "sg:address":"601 Maple St",
    "sg:city":"Carrollton",
    "sg:classifiers":[
        {
            "category":"Education",
            "subcategory":"School",
            "type":"Public Place"
        }
    ],
    "sg:phone":"+1 770 834 1868",
    "sg:postcode":"30117",
    "sg:province":"GA",
    "sg:tags":[
        "housing",
        "for",
        "special",
        "facility"
    ],
    "wof:name":"Instructional Services",
    "wof:placetype":"venue"
},
  "geometry": {"coordinates":[-85.08238900000001,33.575898],"type":"Point"}
}