{
  "type": "Feature",
  "properties": {
    "iso:country":"US",
    "sg:address":"587 Wesley Chapel Rd SE",
    "sg:city":"Calhoun",
    "sg:classifiers":[
        {
            "category":"Farming",
            "subcategory":"Farm",
            "type":"Manufacturing & Wholesale Goods"
        }
    ],
    "sg:phone":"+1 706 629 6960",
    "sg:postcode":"30701",
    "sg:province":"GA",
    "sg:tags":[
        "crop",
        "general"
    ],
    "wof:name":"Carney Farms",
    "wof:placetype":"venue"
},
  "geometry": {"coordinates":[-84.820212,34.45269],"type":"Point"}
}