{
  "type": "Feature",
  "properties": {
    "iso:country":"US",
    "sg:address":"4475 Roswell Rd",
    "sg:city":"Marietta",
    "sg:classifiers":[
        {
            "category":"Shopping",
            "subcategory":"Clothing, Apparel, & Fashions",
            "type":"Retail Goods"
        }
    ],
    "sg:phone":"+1 770 509 9344",
    "sg:postcode":"30062",
    "sg:province":"GA",
    "wof:name":"Harolds",
    "wof:placetype":"venue"
},
  "geometry": {"coordinates":[-84.421871,33.986435],"type":"Point"}
}