{
  "type": "Feature",
  "properties": {
    "addr:full":"6040 Walden Pond Rd Gainesville GA 30506",
    "addr:housenumber":"6040",
    "addr:postcode":"30506",
    "addr:street":"Walden Pond Rd",
    "iso:country":"US",
    "sg:address":"6040 Walden Pond Rd",
    "sg:city":"Gainesville",
    "sg:classifiers":[
        {
            "category":"Building & Trades",
            "subcategory":"Landscaping Services",
            "type":"Services"
        }
    ],
    "sg:phone":"+1 770 652 0507",
    "sg:postcode":"30506",
    "sg:province":"GA",
    "sg:tags":[
        "lawn"
    ],
    "wof:name":"S P M Landscapes",
    "wof:placetype":"venue"
},
  "geometry": {"coordinates":[-83.81553599999999,34.424839],"type":"Point"}
}