{
  "type": "Feature",
  "properties": {
    "iso:country":"US",
    "sg:address":"6050 Peachtree Pkwy NW",
    "sg:city":"Smyrna",
    "sg:classifiers":[
        {
            "category":"Restaurant",
            "type":"Food & Drink"
        }
    ],
    "sg:phone":"+1 770 438 9599",
    "sg:postcode":"30092",
    "sg:province":"GA",
    "sg:tags":[
        "caterer"
    ],
    "wof:name":"Food Glorious Food",
    "wof:placetype":"venue"
},
  "geometry": {"coordinates":[-84.232923,33.95454],"type":"Point"}
}