{
  "type": "Feature",
  "properties": {
    "addr:full":"229 Peachtree St NE Atlanta GA 30303",
    "addr:housenumber":"229",
    "addr:postcode":"30303",
    "addr:street":"Peachtree St Ne",
    "iso:country":"US",
    "sg:address":"229 Peachtree St NE",
    "sg:city":"Atlanta",
    "sg:classifiers":[
        {
            "category":"Restaurant",
            "type":"Food & Drink"
        }
    ],
    "sg:menulink":"http://www.allmenus.com/ga/atlanta/23239-azio/menu/",
    "sg:phone":"+1 404 222 0808",
    "sg:postcode":"30303",
    "sg:province":"GA",
    "sg:tags":[
        "sandwich",
        "salad",
        "seafood",
        "soup",
        "american",
        "wrap",
        "pizza",
        "italian"
    ],
    "wof:name":"Azio",
    "wof:placetype":"venue"
},
  "geometry": {"coordinates":[-84.387564,33.761797],"type":"Point"}
}