{
  "type": "Feature",
  "properties": {
    "iso:country":"US",
    "sg:address":"1775 Parkway Pl SE",
    "sg:city":"Marietta",
    "sg:classifiers":[
        {
            "category":"Travel",
            "subcategory":"Hotels & Motels",
            "type":"Entertainment"
        }
    ],
    "sg:phone":"+1 770 281 4310",
    "sg:postcode":"30067",
    "sg:province":"GA",
    "wof:name":"Four Points Hotel",
    "wof:placetype":"venue"
},
  "geometry": {"coordinates":[-84.504997,33.939098],"type":"Point"}
}