{
  "type": "Feature",
  "properties": {
    "iso:country":"US",
    "sg:address":"897 Welch St SW",
    "sg:city":"Atlanta",
    "sg:classifiers":[
        {
            "category":"Education",
            "subcategory":"School",
            "type":"Public Place"
        }
    ],
    "sg:phone":"+1 404 752 0782",
    "sg:postcode":"30310",
    "sg:province":"GA",
    "wof:name":"Gideon Elem Sch",
    "wof:placetype":"venue"
},
  "geometry": {"coordinates":[-84.404904,33.730113],"type":"Point"}
}