{
  "type": "Feature",
  "properties": {
    "addr:full":"3312 Northside Dr Macon GA 31210",
    "addr:housenumber":"3312",
    "addr:postcode":"31210",
    "addr:street":"Northside Dr",
    "iso:country":"US",
    "sg:address":"3312 Northside Dr",
    "sg:city":"Macon",
    "sg:classifiers":[
        {
            "category":"Social Services",
            "subcategory":"Job Training",
            "type":"Services"
        },
        {
            "category":"Health Services",
            "subcategory":"Nursing And Care Facility",
            "type":"Services"
        },
        {
            "category":"Health Services",
            "subcategory":"Health Practitioner",
            "type":"Services"
        }
    ],
    "sg:phone":"+1 478 476 4627",
    "sg:postcode":"31210",
    "sg:province":"GA",
    "sg:tags":[
        "home",
        "eldercare-home",
        "homes-skilled"
    ],
    "wof:name":"Southern Care",
    "wof:placetype":"venue"
},
  "geometry": {"coordinates":[-83.678726,32.891163],"type":"Point"}
}