{
  "type": "Feature",
  "properties": {
    "addr:full":"1109 Burleyson Rd Dalton GA 30720",
    "addr:housenumber":"1109",
    "addr:postcode":"30720",
    "addr:street":"Burleyson Rd",
    "iso:country":"US",
    "sg:address":"1109 Burleyson Rd",
    "sg:city":"Dalton",
    "sg:classifiers":[
        {
            "category":"Health Services",
            "subcategory":"Doctor",
            "type":"Services"
        }
    ],
    "sg:phone":"+1 706 428 3822",
    "sg:postcode":"30720",
    "sg:province":"GA",
    "sg:tags":[
        "gynecology",
        "physician",
        "surgeon",
        "surgeons",
        "obstetrics"
    ],
    "wof:name":"Glass Brian Md Ob Gyn",
    "wof:placetype":"venue"
},
  "geometry": {"coordinates":[-84.985922,34.79047],"type":"Point"}
}