{
  "type": "Feature",
  "properties": {
    "addr:full":"873 Argonne Ave NE Atlanta GA 30309",
    "addr:housenumber":"873",
    "addr:postcode":"30309",
    "addr:street":"Argonne Ave Ne",
    "iso:country":"US",
    "sg:address":"873 Argonne Ave NE",
    "sg:city":"Atlanta",
    "sg:classifiers":[
        {
            "category":"Professional",
            "subcategory":"Printing & Photocopies",
            "type":"Services"
        }
    ],
    "sg:phone":"+1 404 892 3630",
    "sg:postcode":"30309",
    "sg:province":"GA",
    "sg:tags":[
        "photographers-commercial"
    ],
    "wof:name":"Ballay Studio",
    "wof:placetype":"venue"
},
  "geometry": {"coordinates":[-84.377662,33.778159],"type":"Point"}
}