{
  "type": "Feature",
  "properties": {
    "iso:country":"US",
    "sg:address":"601 Callahan Rd SE",
    "sg:city":"Dalton",
    "sg:classifiers":[
        {
            "category":"Manufacturing",
            "subcategory":"Textiles",
            "type":"Manufacturing & Wholesale Goods"
        }
    ],
    "sg:phone":"+1 706 277 6277",
    "sg:postcode":"30721",
    "sg:province":"GA",
    "sg:tags":[
        "rug",
        "carpet"
    ],
    "wof:name":"Cherokee Carpet Industry",
    "wof:placetype":"venue"
},
  "geometry": {"coordinates":[-84.95693300000001,34.713015],"type":"Point"}
}