{
  "type": "Feature",
  "properties": {
    "iso:country":"US",
    "sg:address":"329 Lawrence St NE",
    "sg:city":"Marietta",
    "sg:classifiers":[
        {
            "category":"Professional",
            "subcategory":"Lawyer & Legal Services",
            "type":"Services"
        }
    ],
    "sg:phone":"+1 770 573 8392",
    "sg:postcode":"30060",
    "sg:province":"GA",
    "sg:tags":[
        "divorce",
        "law",
        "family"
    ],
    "sg:website":"www.hillmac.com",
    "wof:name":"Hill-MacDonald Llc",
    "wof:placetype":"venue"
},
  "geometry": {"coordinates":[-84.542659,33.953247],"type":"Point"}
}