{
  "type": "Feature",
  "properties": {
    "addr:full":"1479 Cedar Ridge Way Stone Mountain GA 30083",
    "addr:housenumber":"1479",
    "addr:postcode":"30083",
    "addr:street":"Cedar Ridge Way",
    "iso:country":"US",
    "sg:address":"1479 Cedar Ridge Way",
    "sg:city":"Stone Mountain",
    "sg:classifiers":[
        {
            "category":"Social Services",
            "subcategory":"Child Care",
            "type":"Services"
        }
    ],
    "sg:phone":"+1 770 593 3935",
    "sg:postcode":"30083",
    "sg:province":"GA",
    "sg:tags":[
        "day"
    ],
    "wof:name":"My Activity House",
    "wof:placetype":"venue"
},
  "geometry": {"coordinates":[-84.202579,33.749493],"type":"Point"}
}