{
  "type": "Feature",
  "properties": {
    "iso:country":"US",
    "sg:address":"611 E Long Hollow Rd",
    "sg:city":"Rock Spring",
    "sg:classifiers":[
        {
            "category":"Building & Trades",
            "subcategory":"Pest Control",
            "type":"Services"
        }
    ],
    "sg:phone":"+1 706 375 9819",
    "sg:postcode":"30739",
    "sg:province":"GA",
    "wof:name":"Cats Termite Pest Control Inc",
    "wof:placetype":"venue"
},
  "geometry": {"coordinates":[-85.223117,34.847123],"type":"Point"}
}