{
  "type": "Feature",
  "properties": {
    "addr:full":"2599 Indian Ford Rd Valdosta GA 31601",
    "addr:housenumber":"2599",
    "addr:postcode":"31601",
    "addr:street":"Indian Ford Rd",
    "iso:country":"US",
    "sg:address":"2599 Indian Ford Rd",
    "sg:city":"Valdosta",
    "sg:classifiers":[
        {
            "category":"Building & Trades",
            "subcategory":"Construction",
            "type":"Services"
        }
    ],
    "sg:phone":"+1 229 249 8642",
    "sg:postcode":"31601",
    "sg:province":"GA",
    "sg:tags":[
        "contractor"
    ],
    "wof:name":"ADM Contractors Inc",
    "wof:placetype":"venue"
},
  "geometry": {"coordinates":[-83.31093300000001,30.783293],"type":"Point"}
}