{
  "type": "Feature",
  "properties": {
    "iso:country":"US",
    "sg:address":"714 Antone St NW",
    "sg:city":"Atlanta",
    "sg:classifiers":[
        {
            "category":"Government",
            "subcategory":"Office",
            "type":"Public Place"
        }
    ],
    "sg:phone":"+1 404 352 0460",
    "sg:postcode":"30318",
    "sg:province":"GA",
    "wof:name":"State Of Mind Muzic Inc",
    "wof:placetype":"venue"
},
  "geometry": {"coordinates":[-84.41251800000001,33.797741],"type":"Point"}
}