{
  "type": "Feature",
  "properties": {
    "iso:country":"US",
    "sg:address":"110 S Glenwood Ave",
    "sg:city":"Dalton",
    "sg:classifiers":[
        {
            "category":"Professional",
            "type":"Services"
        }
    ],
    "sg:phone":"+1 706 226 2818",
    "sg:postcode":"30721",
    "sg:province":"GA",
    "sg:tags":[
        "establishment"
    ],
    "sg:website":"www.alconsys.com",
    "wof:name":"Alcon Systems Inc",
    "wof:placetype":"venue"
},
  "geometry": {"coordinates":[-84.96559999999999,34.770665],"type":"Point"}
}