{
  "type": "Feature",
  "properties": {
    "iso:country":"US",
    "sg:address":"2705 Northgate Ct",
    "sg:city":"Cumming",
    "sg:classifiers":[
        {
            "category":"Wholesale",
            "subcategory":"Construction Materials",
            "type":"Manufacturing & Wholesale Goods"
        }
    ],
    "sg:phone":"+1 770 781 8525",
    "sg:postcode":"30041",
    "sg:province":"GA",
    "sg:tags":[
        "interior",
        "building",
        "mfg",
        "exterior",
        "supply"
    ],
    "wof:name":"Bowman Building Supplies Inc",
    "wof:placetype":"venue"
},
  "geometry": {"coordinates":[-84.153454,34.166644],"type":"Point"}
}