{
  "type": "Feature",
  "properties": {
    "iso:country":"US",
    "sg:address":"1080 Kamera Rd",
    "sg:city":"Douglas",
    "sg:classifiers":[
        {
            "category":"Organizations",
            "subcategory":"Religious Organization",
            "type":"Services"
        }
    ],
    "sg:phone":"+1 912 384 4594",
    "sg:postcode":"31533",
    "sg:province":"GA",
    "wof:name":"Carver Baptist Church",
    "wof:placetype":"venue"
},
  "geometry": {"coordinates":[-82.86600199999999,31.439719],"type":"Point"}
}