{
  "type": "Feature",
  "properties": {
    "iso:country":"US",
    "sg:address":"2257 Tilson Cir",
    "sg:city":"Decatur",
    "sg:classifiers":[
        {
            "category":"Building & Trades",
            "subcategory":"Locksmith",
            "type":"Services"
        }
    ],
    "sg:phone":"+1 678 365 0265",
    "sg:postcode":"30032",
    "sg:province":"GA",
    "sg:tags":[
        "key"
    ],
    "wof:name":"1 0 1 24 A Emerg Locksmith",
    "wof:placetype":"venue"
},
  "geometry": {"coordinates":[-84.29669,33.722917],"type":"Point"}
}