{
  "type": "Feature",
  "properties": {
    "addr:full":"1837 Hadrian Way Lithonia GA 30058",
    "addr:housenumber":"1837",
    "addr:postcode":"30058",
    "addr:street":"Hadrian Way",
    "iso:country":"US",
    "sg:address":"1837 Hadrian Way",
    "sg:city":"Lithonia",
    "sg:classifiers":[
        {
            "category":"Building & Trades",
            "subcategory":"Pest Control",
            "type":"Services"
        }
    ],
    "sg:phone":"+1 678 760 7184",
    "sg:postcode":"30058",
    "sg:province":"GA",
    "sg:tags":[
        "termite"
    ],
    "wof:name":"Alis Termite & Pest Control",
    "wof:placetype":"venue"
},
  "geometry": {"coordinates":[-84.164827,33.736338],"type":"Point"}
}