{
  "type": "Feature",
  "properties": {
    "addr:full":"3875 Genoa Ct Duluth GA 30096",
    "addr:housenumber":"3875",
    "addr:postcode":"30096",
    "addr:street":"Genoa Ct",
    "iso:country":"US",
    "sg:address":"3875 Genoa Ct",
    "sg:city":"Duluth",
    "sg:classifiers":[
        {
            "category":"Arts & Performance",
            "subcategory":"Theater",
            "type":"Entertainment"
        }
    ],
    "sg:phone":"+1 770 377 7363",
    "sg:postcode":"30096",
    "sg:province":"GA",
    "sg:tags":[
        "entertainer"
    ],
    "wof:name":"Pepe Lopez Mariachi Band",
    "wof:placetype":"venue"
},
  "geometry": {"coordinates":[-84.158158,33.967813],"type":"Point"}
}