{
  "type": "Feature",
  "properties": {
    "iso:country":"US",
    "sg:address":"3731 Dally Rd",
    "sg:city":"Covington",
    "sg:classifiers":[
        {
            "category":"Building & Trades",
            "subcategory":"Construction",
            "type":"Services"
        }
    ],
    "sg:phone":"+1 770 464 9811",
    "sg:postcode":"30014",
    "sg:province":"GA",
    "sg:tags":[
        "house"
    ],
    "wof:name":"Jimmy Smith General Contg",
    "wof:placetype":"venue"
},
  "geometry": {"coordinates":[-83.77816900000001,33.704152],"type":"Point"}
}