{
  "type": "Feature",
  "properties": {
    "addr:full":"871 Lee Rd Macon GA 31204",
    "addr:housenumber":"871",
    "addr:postcode":"31204",
    "addr:street":"Lee Rd",
    "iso:country":"US",
    "sg:address":"871 Lee Rd",
    "sg:city":"Macon",
    "sg:classifiers":[
        {
            "category":"Insurance",
            "subcategory":"Insurance Agent",
            "type":"Services"
        }
    ],
    "sg:phone":"+1 478 746 1015",
    "sg:postcode":"31204",
    "sg:province":"GA",
    "wof:name":"Alfa Insurance 248",
    "wof:placetype":"venue"
},
  "geometry": {"coordinates":[-83.66656,32.877254],"type":"Point"}
}