{
  "type": "Feature",
  "properties": {
    "iso:country":"US",
    "sg:address":"111 W Bay St",
    "sg:city":"Savannah",
    "sg:classifiers":[
        {
            "category":"Professional",
            "subcategory":"Advertising",
            "type":"Services"
        }
    ],
    "sg:phone":"+1 912 652 0250",
    "sg:postcode":"31401",
    "sg:province":"GA",
    "sg:website":"www.savannahsquare.net",
    "wof:name":"Savannah Morning News",
    "wof:placetype":"venue"
},
  "geometry": {"coordinates":[-81.093245,32.081368],"type":"Point"}
}