{
  "type": "Feature",
  "properties": {
    "iso:country":"US",
    "sg:address":"593 Joseph E Lowery Boulevard",
    "sg:city":"Atlanta",
    "sg:classifiers":[
        {
            "category":"Restaurant",
            "type":"Food & Drink"
        },
        {
            "category":"Deli",
            "type":"Food & Drink"
        },
        {
            "category":"Food & Beverages",
            "subcategory":"Bakery",
            "type":"Retail Goods"
        },
        {
            "category":"Food & Beverages",
            "subcategory":"Groceries & Convenience Stores",
            "type":"Retail Goods"
        }
    ],
    "sg:phone":"+1 404 755 6658",
    "sg:postcode":"30310",
    "sg:province":"GA",
    "sg:tags":[
        "shop",
        "delicatessen",
        "sandwich"
    ],
    "wof:name":"New York Sandwich Shop",
    "wof:placetype":"venue"
},
  "geometry": {"coordinates":[-84.417571,33.738353],"type":"Point"}
}