{
  "type": "Feature",
  "properties": {
    "addr:full":"962 Chimney Rd Rincon GA 31326",
    "addr:housenumber":"962",
    "addr:postcode":"31326",
    "addr:street":"Chimney Rd",
    "iso:country":"US",
    "sg:address":"962 Chimney Rd",
    "sg:city":"Rincon",
    "sg:classifiers":[
        {
            "category":"Personal",
            "subcategory":"Beauty Salon",
            "type":"Services"
        }
    ],
    "sg:phone":"+1 912 826 5775",
    "sg:postcode":"31326",
    "sg:province":"GA",
    "wof:name":"Salon J Hair Spa",
    "wof:placetype":"venue"
},
  "geometry": {"coordinates":[-81.196034,32.270649],"type":"Point"}
}