{
  "type": "Feature",
  "properties": {
    "addr:full":"20 Wilderness Path Dallas GA 30132",
    "addr:housenumber":"20",
    "addr:postcode":"30132",
    "addr:street":"Wilderness Path",
    "iso:country":"US",
    "sg:address":"20 Wilderness Path",
    "sg:city":"Dallas",
    "sg:classifiers":[
        {
            "category":"Wholesale",
            "subcategory":"Auto Parts",
            "type":"Manufacturing & Wholesale Goods"
        }
    ],
    "sg:phone":"+1 770 740 9910",
    "sg:postcode":"30132",
    "sg:province":"GA",
    "wof:name":"Norris Automotive Industries",
    "wof:placetype":"venue"
},
  "geometry": {"coordinates":[-84.935461,33.944734],"type":"Point"}
}