{
  "type": "Feature",
  "properties": {
    "addr:full":"2236 S Van Wert Rd Villa Rica GA 30180",
    "addr:housenumber":"2236",
    "addr:postcode":"30180",
    "addr:street":"S Van Wert Rd",
    "iso:country":"US",
    "sg:address":"2236 S Van Wert Rd",
    "sg:city":"Villa Rica",
    "sg:classifiers":[
        {
            "category":"Restaurant",
            "type":"Food & Drink"
        }
    ],
    "sg:phone":"+1 770 459 2250",
    "sg:postcode":"30180",
    "sg:province":"GA",
    "wof:name":"Smith & Smith",
    "wof:placetype":"venue"
},
  "geometry": {"coordinates":[-84.953678,33.706963],"type":"Point"}
}