{
  "type": "Feature",
  "properties": {
    "addr:full":"605 US Hwy 80 Savannah GA 31408",
    "addr:housenumber":"605",
    "addr:postcode":"31408",
    "addr:street":"Us Hwy 80",
    "iso:country":"US",
    "sg:address":"605 US Hwy 80",
    "sg:city":"Savannah",
    "sg:classifiers":[
        {
            "category":"Retail",
            "subcategory":"Auto Repair",
            "type":"Services"
        }
    ],
    "sg:phone":"+1 912 964 0190",
    "sg:postcode":"31408",
    "sg:province":"GA",
    "sg:tags":[
        "repairing",
        "automobile"
    ],
    "wof:name":"Anderson Auto Repairs",
    "wof:placetype":"venue"
},
  "geometry": {"coordinates":[-81.147508,32.09402],"type":"Point"}
}