{
  "type": "Feature",
  "properties": {
    "addr:full":"707 3rd St W Tifton GA 31794",
    "addr:housenumber":"707",
    "addr:postcode":"31794",
    "addr:street":"3Rd St W",
    "iso:country":"US",
    "sg:address":"707 3rd St W",
    "sg:city":"Tifton",
    "sg:classifiers":[
        {
            "category":"Shopping",
            "subcategory":"Clothing, Apparel, & Fashions",
            "type":"Retail Goods"
        }
    ],
    "sg:phone":"+1 229 382 9156",
    "sg:postcode":"31794",
    "sg:province":"GA",
    "wof:name":"El Herrero",
    "wof:placetype":"venue"
},
  "geometry": {"coordinates":[-83.524984,31.452264],"type":"Point"}
}